Classfile /Users/mw/Projects/slang-braindump/.jar/jar8/assemble/slang-braindump/assemble/content/com/fasterxml/jackson/databind/node/ArrayNode.class
  Last modified May 29, 2022; size 23428 bytes
  SHA-256 checksum 2814c4b9473cf842396950ff034d278bb1217bc643bbc9c24a5c3cf109b0918d
  Compiled from "ArrayNode.java"
public class com.fasterxml.jackson.databind.node.ArrayNode extends com.fasterxml.jackson.databind.node.ContainerNode<com.fasterxml.jackson.databind.node.ArrayNode> implements java.io.Serializable
  minor version: 0
  major version: 52
  flags: (0x0021) ACC_PUBLIC, ACC_SUPER
  this_class: #8                          // com/fasterxml/jackson/databind/node/ArrayNode
  super_class: #91                        // com/fasterxml/jackson/databind/node/ContainerNode
  interfaces: 1, fields: 2, methods: 106, attributes: 2
Constant pool:
    #1 = Methodref          #91.#309      // com/fasterxml/jackson/databind/node/ContainerNode."<init>":(Lcom/fasterxml/jackson/databind/node/JsonNodeFactory;)V
    #2 = Class              #310          // java/util/ArrayList
    #3 = Methodref          #2.#311       // java/util/ArrayList."<init>":()V
    #4 = Fieldref           #8.#312       // com/fasterxml/jackson/databind/node/ArrayNode._children:Ljava/util/List;
    #5 = Methodref          #2.#313       // java/util/ArrayList."<init>":(I)V
    #6 = Methodref          #314.#315     // com/fasterxml/jackson/core/JsonPointer.getMatchingIndex:()I
    #7 = Methodref          #8.#316       // com/fasterxml/jackson/databind/node/ArrayNode.get:(I)Lcom/fasterxml/jackson/databind/JsonNode;
    #8 = Class              #317          // com/fasterxml/jackson/databind/node/ArrayNode
    #9 = Fieldref           #8.#318       // com/fasterxml/jackson/databind/node/ArrayNode._nodeFactory:Lcom/fasterxml/jackson/databind/node/JsonNodeFactory;
   #10 = Methodref          #8.#309       // com/fasterxml/jackson/databind/node/ArrayNode."<init>":(Lcom/fasterxml/jackson/databind/node/JsonNodeFactory;)V
   #11 = InterfaceMethodref #319.#320     // java/util/List.iterator:()Ljava/util/Iterator;
   #12 = InterfaceMethodref #321.#322     // java/util/Iterator.hasNext:()Z
   #13 = InterfaceMethodref #321.#323     // java/util/Iterator.next:()Ljava/lang/Object;
   #14 = Class              #324          // com/fasterxml/jackson/databind/JsonNode
   #15 = Methodref          #14.#325      // com/fasterxml/jackson/databind/JsonNode.deepCopy:()Lcom/fasterxml/jackson/databind/JsonNode;
   #16 = InterfaceMethodref #319.#326     // java/util/List.add:(Ljava/lang/Object;)Z
   #17 = InterfaceMethodref #319.#327     // java/util/List.isEmpty:()Z
   #18 = Fieldref           #328.#329     // com/fasterxml/jackson/databind/node/JsonNodeType.ARRAY:Lcom/fasterxml/jackson/databind/node/JsonNodeType;
   #19 = Fieldref           #330.#331     // com/fasterxml/jackson/core/JsonToken.START_ARRAY:Lcom/fasterxml/jackson/core/JsonToken;
   #20 = InterfaceMethodref #319.#332     // java/util/List.size:()I
   #21 = InterfaceMethodref #319.#333     // java/util/List.get:(I)Ljava/lang/Object;
   #22 = Methodref          #334.#335     // com/fasterxml/jackson/databind/node/MissingNode.getInstance:()Lcom/fasterxml/jackson/databind/node/MissingNode;
   #23 = String             #336          // No value at index #%d [0, %d) of `ArrayNode`
   #24 = Class              #337          // java/lang/Object
   #25 = Methodref          #338.#339     // java/lang/Integer.valueOf:(I)Ljava/lang/Integer;
   #26 = Methodref          #8.#340       // com/fasterxml/jackson/databind/node/ArrayNode._reportRequiredViolation:(Ljava/lang/String;[Ljava/lang/Object;)Ljava/lang/Object;
   #27 = Methodref          #8.#332       // com/fasterxml/jackson/databind/node/ArrayNode.size:()I
   #28 = Methodref          #14.#341      // com/fasterxml/jackson/databind/JsonNode.equals:(Ljava/util/Comparator;Lcom/fasterxml/jackson/databind/JsonNode;)Z
   #29 = Methodref          #342.#343     // com/fasterxml/jackson/core/JsonGenerator.writeStartArray:(Ljava/lang/Object;I)V
   #30 = Class              #344          // com/fasterxml/jackson/databind/node/BaseJsonNode
   #31 = Methodref          #30.#345      // com/fasterxml/jackson/databind/node/BaseJsonNode.serialize:(Lcom/fasterxml/jackson/core/JsonGenerator;Lcom/fasterxml/jackson/databind/SerializerProvider;)V
   #32 = Methodref          #342.#346     // com/fasterxml/jackson/core/JsonGenerator.writeEndArray:()V
   #33 = Methodref          #347.#348     // com/fasterxml/jackson/databind/jsontype/TypeSerializer.typeId:(Ljava/lang/Object;Lcom/fasterxml/jackson/core/JsonToken;)Lcom/fasterxml/jackson/core/type/WritableTypeId;
   #34 = Methodref          #347.#349     // com/fasterxml/jackson/databind/jsontype/TypeSerializer.writeTypePrefix:(Lcom/fasterxml/jackson/core/JsonGenerator;Lcom/fasterxml/jackson/core/type/WritableTypeId;)Lcom/fasterxml/jackson/core/type/WritableTypeId;
   #35 = Methodref          #347.#350     // com/fasterxml/jackson/databind/jsontype/TypeSerializer.writeTypeSuffix:(Lcom/fasterxml/jackson/core/JsonGenerator;Lcom/fasterxml/jackson/core/type/WritableTypeId;)Lcom/fasterxml/jackson/core/type/WritableTypeId;
   #36 = Methodref          #14.#351      // com/fasterxml/jackson/databind/JsonNode.findValue:(Ljava/lang/String;)Lcom/fasterxml/jackson/databind/JsonNode;
   #37 = Methodref          #14.#352      // com/fasterxml/jackson/databind/JsonNode.findValues:(Ljava/lang/String;Ljava/util/List;)Ljava/util/List;
   #38 = Methodref          #14.#353      // com/fasterxml/jackson/databind/JsonNode.findValuesAsText:(Ljava/lang/String;Ljava/util/List;)Ljava/util/List;
   #39 = Methodref          #14.#354      // com/fasterxml/jackson/databind/JsonNode.findParent:(Ljava/lang/String;)Lcom/fasterxml/jackson/databind/JsonNode;
   #40 = Class              #355          // com/fasterxml/jackson/databind/node/ObjectNode
   #41 = Methodref          #14.#356      // com/fasterxml/jackson/databind/JsonNode.findParents:(Ljava/lang/String;Ljava/util/List;)Ljava/util/List;
   #42 = Methodref          #8.#357       // com/fasterxml/jackson/databind/node/ArrayNode.nullNode:()Lcom/fasterxml/jackson/databind/node/NullNode;
   #43 = Class              #358          // java/lang/IndexOutOfBoundsException
   #44 = Class              #359          // java/lang/StringBuilder
   #45 = Methodref          #44.#311      // java/lang/StringBuilder."<init>":()V
   #46 = String             #360          // Illegal index
   #47 = Methodref          #44.#361      // java/lang/StringBuilder.append:(Ljava/lang/String;)Ljava/lang/StringBuilder;
   #48 = Methodref          #44.#362      // java/lang/StringBuilder.append:(I)Ljava/lang/StringBuilder;
   #49 = String             #363          // , array size
   #50 = Methodref          #44.#364      // java/lang/StringBuilder.toString:()Ljava/lang/String;
   #51 = Methodref          #43.#365      // java/lang/IndexOutOfBoundsException."<init>":(Ljava/lang/String;)V
   #52 = InterfaceMethodref #319.#366     // java/util/List.set:(ILjava/lang/Object;)Ljava/lang/Object;
   #53 = Methodref          #8.#367       // com/fasterxml/jackson/databind/node/ArrayNode._add:(Lcom/fasterxml/jackson/databind/JsonNode;)Lcom/fasterxml/jackson/databind/node/ArrayNode;
   #54 = InterfaceMethodref #319.#368     // java/util/List.addAll:(Ljava/util/Collection;)Z
   #55 = InterfaceMethodref #369.#320     // java/util/Collection.iterator:()Ljava/util/Iterator;
   #56 = Methodref          #8.#370       // com/fasterxml/jackson/databind/node/ArrayNode.add:(Lcom/fasterxml/jackson/databind/JsonNode;)Lcom/fasterxml/jackson/databind/node/ArrayNode;
   #57 = Methodref          #8.#371       // com/fasterxml/jackson/databind/node/ArrayNode._insert:(ILcom/fasterxml/jackson/databind/JsonNode;)Lcom/fasterxml/jackson/databind/node/ArrayNode;
   #58 = InterfaceMethodref #319.#372     // java/util/List.remove:(I)Ljava/lang/Object;
   #59 = InterfaceMethodref #319.#373     // java/util/List.clear:()V
   #60 = Methodref          #8.#374       // com/fasterxml/jackson/databind/node/ArrayNode.arrayNode:()Lcom/fasterxml/jackson/databind/node/ArrayNode;
   #61 = Methodref          #8.#375       // com/fasterxml/jackson/databind/node/ArrayNode.objectNode:()Lcom/fasterxml/jackson/databind/node/ObjectNode;
   #62 = Methodref          #8.#376       // com/fasterxml/jackson/databind/node/ArrayNode.pojoNode:(Ljava/lang/Object;)Lcom/fasterxml/jackson/databind/node/ValueNode;
   #63 = Methodref          #8.#377       // com/fasterxml/jackson/databind/node/ArrayNode.rawValueNode:(Lcom/fasterxml/jackson/databind/util/RawValue;)Lcom/fasterxml/jackson/databind/node/ValueNode;
   #64 = Methodref          #8.#378       // com/fasterxml/jackson/databind/node/ArrayNode.numberNode:(S)Lcom/fasterxml/jackson/databind/node/NumericNode;
   #65 = Methodref          #379.#380     // java/lang/Short.shortValue:()S
   #66 = Methodref          #8.#381       // com/fasterxml/jackson/databind/node/ArrayNode.numberNode:(I)Lcom/fasterxml/jackson/databind/node/NumericNode;
   #67 = Methodref          #338.#382     // java/lang/Integer.intValue:()I
   #68 = Methodref          #8.#383       // com/fasterxml/jackson/databind/node/ArrayNode.numberNode:(J)Lcom/fasterxml/jackson/databind/node/NumericNode;
   #69 = Methodref          #384.#385     // java/lang/Long.longValue:()J
   #70 = Methodref          #8.#386       // com/fasterxml/jackson/databind/node/ArrayNode.numberNode:(F)Lcom/fasterxml/jackson/databind/node/NumericNode;
   #71 = Methodref          #387.#388     // java/lang/Float.floatValue:()F
   #72 = Methodref          #8.#389       // com/fasterxml/jackson/databind/node/ArrayNode.numberNode:(D)Lcom/fasterxml/jackson/databind/node/NumericNode;
   #73 = Methodref          #390.#391     // java/lang/Double.doubleValue:()D
   #74 = Methodref          #8.#392       // com/fasterxml/jackson/databind/node/ArrayNode.numberNode:(Ljava/math/BigDecimal;)Lcom/fasterxml/jackson/databind/node/ValueNode;
   #75 = Methodref          #8.#393       // com/fasterxml/jackson/databind/node/ArrayNode.numberNode:(Ljava/math/BigInteger;)Lcom/fasterxml/jackson/databind/node/ValueNode;
   #76 = Methodref          #8.#394       // com/fasterxml/jackson/databind/node/ArrayNode.textNode:(Ljava/lang/String;)Lcom/fasterxml/jackson/databind/node/TextNode;
   #77 = Methodref          #8.#395       // com/fasterxml/jackson/databind/node/ArrayNode.booleanNode:(Z)Lcom/fasterxml/jackson/databind/node/BooleanNode;
   #78 = Methodref          #396.#397     // java/lang/Boolean.booleanValue:()Z
   #79 = Methodref          #8.#398       // com/fasterxml/jackson/databind/node/ArrayNode.binaryNode:([B)Lcom/fasterxml/jackson/databind/node/BinaryNode;
   #80 = Methodref          #8.#399       // com/fasterxml/jackson/databind/node/ArrayNode.insertNull:(I)Lcom/fasterxml/jackson/databind/node/ArrayNode;
   #81 = Methodref          #8.#400       // com/fasterxml/jackson/databind/node/ArrayNode._set:(ILcom/fasterxml/jackson/databind/JsonNode;)Lcom/fasterxml/jackson/databind/node/ArrayNode;
   #82 = InterfaceMethodref #319.#401     // java/util/List.equals:(Ljava/lang/Object;)Z
   #83 = InterfaceMethodref #319.#402     // java/util/List.hashCode:()I
   #84 = InterfaceMethodref #319.#403     // java/util/List.add:(ILjava/lang/Object;)V
   #85 = Methodref          #8.#404       // com/fasterxml/jackson/databind/node/ArrayNode.removeAll:()Lcom/fasterxml/jackson/databind/node/ArrayNode;
   #86 = Methodref          #8.#405       // com/fasterxml/jackson/databind/node/ArrayNode.findParent:(Ljava/lang/String;)Lcom/fasterxml/jackson/databind/node/ObjectNode;
   #87 = Methodref          #8.#406       // com/fasterxml/jackson/databind/node/ArrayNode.deepCopy:()Lcom/fasterxml/jackson/databind/node/ArrayNode;
   #88 = Methodref          #8.#407       // com/fasterxml/jackson/databind/node/ArrayNode.path:(I)Lcom/fasterxml/jackson/databind/JsonNode;
   #89 = Methodref          #8.#408       // com/fasterxml/jackson/databind/node/ArrayNode.path:(Ljava/lang/String;)Lcom/fasterxml/jackson/databind/JsonNode;
   #90 = Methodref          #8.#409       // com/fasterxml/jackson/databind/node/ArrayNode.get:(Ljava/lang/String;)Lcom/fasterxml/jackson/databind/JsonNode;
   #91 = Class              #410          // com/fasterxml/jackson/databind/node/ContainerNode
   #92 = Class              #411          // java/io/Serializable
   #93 = Utf8               serialVersionUID
   #94 = Utf8               J
   #95 = Utf8               ConstantValue
   #96 = Long               1l
   #98 = Utf8               _children
   #99 = Utf8               Ljava/util/List;
  #100 = Utf8               Signature
  #101 = Utf8               Ljava/util/List<Lcom/fasterxml/jackson/databind/JsonNode;>;
  #102 = Utf8               <init>
  #103 = Utf8               (Lcom/fasterxml/jackson/databind/node/JsonNodeFactory;)V
  #104 = Utf8               Code
  #105 = Utf8               LineNumberTable
  #106 = Utf8               LocalVariableTable
  #107 = Utf8               this
  #108 = Utf8               Lcom/fasterxml/jackson/databind/node/ArrayNode;
  #109 = Utf8               nf
  #110 = Utf8               Lcom/fasterxml/jackson/databind/node/JsonNodeFactory;
  #111 = Utf8               (Lcom/fasterxml/jackson/databind/node/JsonNodeFactory;I)V
  #112 = Utf8               capacity
  #113 = Utf8               I
  #114 = Utf8               (Lcom/fasterxml/jackson/databind/node/JsonNodeFactory;Ljava/util/List;)V
  #115 = Utf8               children
  #116 = Utf8               LocalVariableTypeTable
  #117 = Utf8               (Lcom/fasterxml/jackson/databind/node/JsonNodeFactory;Ljava/util/List<Lcom/fasterxml/jackson/databind/JsonNode;>;)V
  #118 = Utf8               _at
  #119 = Utf8               (Lcom/fasterxml/jackson/core/JsonPointer;)Lcom/fasterxml/jackson/databind/JsonNode;
  #120 = Utf8               ptr
  #121 = Utf8               Lcom/fasterxml/jackson/core/JsonPointer;
  #122 = Utf8               deepCopy
  #123 = Utf8               ()Lcom/fasterxml/jackson/databind/node/ArrayNode;
  #124 = Utf8               element
  #125 = Utf8               Lcom/fasterxml/jackson/databind/JsonNode;
  #126 = Utf8               ret
  #127 = Utf8               StackMapTable
  #128 = Class              #317          // com/fasterxml/jackson/databind/node/ArrayNode
  #129 = Class              #412          // java/util/Iterator
  #130 = Utf8               isEmpty
  #131 = Utf8               (Lcom/fasterxml/jackson/databind/SerializerProvider;)Z
  #132 = Utf8               serializers
  #133 = Utf8               Lcom/fasterxml/jackson/databind/SerializerProvider;
  #134 = Utf8               getNodeType
  #135 = Utf8               ()Lcom/fasterxml/jackson/databind/node/JsonNodeType;
  #136 = Utf8               isArray
  #137 = Utf8               ()Z
  #138 = Utf8               asToken
  #139 = Utf8               ()Lcom/fasterxml/jackson/core/JsonToken;
  #140 = Utf8               size
  #141 = Utf8               ()I
  #142 = Utf8               elements
  #143 = Utf8               ()Ljava/util/Iterator;
  #144 = Utf8               ()Ljava/util/Iterator<Lcom/fasterxml/jackson/databind/JsonNode;>;
  #145 = Utf8               get
  #146 = Utf8               (I)Lcom/fasterxml/jackson/databind/JsonNode;
  #147 = Utf8               index
  #148 = Utf8               (Ljava/lang/String;)Lcom/fasterxml/jackson/databind/JsonNode;
  #149 = Utf8               fieldName
  #150 = Utf8               Ljava/lang/String;
  #151 = Utf8               path
  #152 = Utf8               required
  #153 = Utf8               equals
  #154 = Utf8               (Ljava/util/Comparator;Lcom/fasterxml/jackson/databind/JsonNode;)Z
  #155 = Utf8               i
  #156 = Utf8               comparator
  #157 = Utf8               Ljava/util/Comparator;
  #158 = Utf8               o
  #159 = Utf8               other
  #160 = Utf8               len
  #161 = Utf8               l1
  #162 = Utf8               l2
  #163 = Utf8               Ljava/util/Comparator<Lcom/fasterxml/jackson/databind/JsonNode;>;
  #164 = Class              #413          // java/util/List
  #165 = Utf8               (Ljava/util/Comparator<Lcom/fasterxml/jackson/databind/JsonNode;>;Lcom/fasterxml/jackson/databind/JsonNode;)Z
  #166 = Utf8               serialize
  #167 = Utf8               (Lcom/fasterxml/jackson/core/JsonGenerator;Lcom/fasterxml/jackson/databind/SerializerProvider;)V
  #168 = Utf8               n
  #169 = Utf8               f
  #170 = Utf8               Lcom/fasterxml/jackson/core/JsonGenerator;
  #171 = Utf8               provider
  #172 = Utf8               c
  #173 = Utf8               Exceptions
  #174 = Class              #414          // java/io/IOException
  #175 = Utf8               serializeWithType
  #176 = Utf8               (Lcom/fasterxml/jackson/core/JsonGenerator;Lcom/fasterxml/jackson/databind/SerializerProvider;Lcom/fasterxml/jackson/databind/jsontype/TypeSerializer;)V
  #177 = Utf8               g
  #178 = Utf8               typeSer
  #179 = Utf8               Lcom/fasterxml/jackson/databind/jsontype/TypeSerializer;
  #180 = Utf8               typeIdDef
  #181 = Utf8               Lcom/fasterxml/jackson/core/type/WritableTypeId;
  #182 = Class              #415          // com/fasterxml/jackson/core/type/WritableTypeId
  #183 = Utf8               findValue
  #184 = Utf8               value
  #185 = Utf8               node
  #186 = Utf8               findValues
  #187 = Utf8               (Ljava/lang/String;Ljava/util/List;)Ljava/util/List;
  #188 = Utf8               foundSoFar
  #189 = Utf8               (Ljava/lang/String;Ljava/util/List<Lcom/fasterxml/jackson/databind/JsonNode;>;)Ljava/util/List<Lcom/fasterxml/jackson/databind/JsonNode;>;
  #190 = Utf8               findValuesAsText
  #191 = Utf8               Ljava/util/List<Ljava/lang/String;>;
  #192 = Utf8               (Ljava/lang/String;Ljava/util/List<Ljava/lang/String;>;)Ljava/util/List<Ljava/lang/String;>;
  #193 = Utf8               findParent
  #194 = Utf8               (Ljava/lang/String;)Lcom/fasterxml/jackson/databind/node/ObjectNode;
  #195 = Utf8               parent
  #196 = Utf8               findParents
  #197 = Utf8               set
  #198 = Utf8               (ILcom/fasterxml/jackson/databind/JsonNode;)Lcom/fasterxml/jackson/databind/JsonNode;
  #199 = Utf8               add
  #200 = Utf8               (Lcom/fasterxml/jackson/databind/JsonNode;)Lcom/fasterxml/jackson/databind/node/ArrayNode;
  #201 = Utf8               addAll
  #202 = Utf8               (Lcom/fasterxml/jackson/databind/node/ArrayNode;)Lcom/fasterxml/jackson/databind/node/ArrayNode;
  #203 = Utf8               (Ljava/util/Collection;)Lcom/fasterxml/jackson/databind/node/ArrayNode;
  #204 = Utf8               nodes
  #205 = Utf8               Ljava/util/Collection;
  #206 = Utf8               Ljava/util/Collection<+Lcom/fasterxml/jackson/databind/JsonNode;>;
  #207 = Utf8               (Ljava/util/Collection<+Lcom/fasterxml/jackson/databind/JsonNode;>;)Lcom/fasterxml/jackson/databind/node/ArrayNode;
  #208 = Utf8               insert
  #209 = Utf8               (ILcom/fasterxml/jackson/databind/JsonNode;)Lcom/fasterxml/jackson/databind/node/ArrayNode;
  #210 = Utf8               remove
  #211 = Utf8               removeAll
  #212 = Utf8               addArray
  #213 = Utf8               addObject
  #214 = Utf8               ()Lcom/fasterxml/jackson/databind/node/ObjectNode;
  #215 = Utf8               Lcom/fasterxml/jackson/databind/node/ObjectNode;
  #216 = Utf8               addPOJO
  #217 = Utf8               (Ljava/lang/Object;)Lcom/fasterxml/jackson/databind/node/ArrayNode;
  #218 = Utf8               pojo
  #219 = Utf8               Ljava/lang/Object;
  #220 = Class              #337          // java/lang/Object
  #221 = Class              #324          // com/fasterxml/jackson/databind/JsonNode
  #222 = Utf8               addRawValue
  #223 = Utf8               (Lcom/fasterxml/jackson/databind/util/RawValue;)Lcom/fasterxml/jackson/databind/node/ArrayNode;
  #224 = Utf8               raw
  #225 = Utf8               Lcom/fasterxml/jackson/databind/util/RawValue;
  #226 = Class              #416          // com/fasterxml/jackson/databind/util/RawValue
  #227 = Utf8               addNull
  #228 = Utf8               (S)Lcom/fasterxml/jackson/databind/node/ArrayNode;
  #229 = Utf8               v
  #230 = Utf8               S
  #231 = Utf8               (Ljava/lang/Short;)Lcom/fasterxml/jackson/databind/node/ArrayNode;
  #232 = Utf8               Ljava/lang/Short;
  #233 = Class              #417          // java/lang/Short
  #234 = Utf8               (I)Lcom/fasterxml/jackson/databind/node/ArrayNode;
  #235 = Utf8               (Ljava/lang/Integer;)Lcom/fasterxml/jackson/databind/node/ArrayNode;
  #236 = Utf8               Ljava/lang/Integer;
  #237 = Class              #418          // java/lang/Integer
  #238 = Utf8               (J)Lcom/fasterxml/jackson/databind/node/ArrayNode;
  #239 = Utf8               (Ljava/lang/Long;)Lcom/fasterxml/jackson/databind/node/ArrayNode;
  #240 = Utf8               Ljava/lang/Long;
  #241 = Class              #419          // java/lang/Long
  #242 = Utf8               (F)Lcom/fasterxml/jackson/databind/node/ArrayNode;
  #243 = Utf8               F
  #244 = Utf8               (Ljava/lang/Float;)Lcom/fasterxml/jackson/databind/node/ArrayNode;
  #245 = Utf8               Ljava/lang/Float;
  #246 = Class              #420          // java/lang/Float
  #247 = Utf8               (D)Lcom/fasterxml/jackson/databind/node/ArrayNode;
  #248 = Utf8               D
  #249 = Utf8               (Ljava/lang/Double;)Lcom/fasterxml/jackson/databind/node/ArrayNode;
  #250 = Utf8               Ljava/lang/Double;
  #251 = Class              #421          // java/lang/Double
  #252 = Utf8               (Ljava/math/BigDecimal;)Lcom/fasterxml/jackson/databind/node/ArrayNode;
  #253 = Utf8               Ljava/math/BigDecimal;
  #254 = Class              #422          // java/math/BigDecimal
  #255 = Utf8               (Ljava/math/BigInteger;)Lcom/fasterxml/jackson/databind/node/ArrayNode;
  #256 = Utf8               Ljava/math/BigInteger;
  #257 = Class              #423          // java/math/BigInteger
  #258 = Utf8               (Ljava/lang/String;)Lcom/fasterxml/jackson/databind/node/ArrayNode;
  #259 = Class              #424          // java/lang/String
  #260 = Utf8               (Z)Lcom/fasterxml/jackson/databind/node/ArrayNode;
  #261 = Utf8               Z
  #262 = Utf8               (Ljava/lang/Boolean;)Lcom/fasterxml/jackson/databind/node/ArrayNode;
  #263 = Utf8               Ljava/lang/Boolean;
  #264 = Class              #425          // java/lang/Boolean
  #265 = Utf8               ([B)Lcom/fasterxml/jackson/databind/node/ArrayNode;
  #266 = Utf8               [B
  #267 = Class              #266          // "[B"
  #268 = Utf8               insertArray
  #269 = Utf8               insertObject
  #270 = Utf8               (I)Lcom/fasterxml/jackson/databind/node/ObjectNode;
  #271 = Utf8               insertNull
  #272 = Utf8               insertPOJO
  #273 = Utf8               (ILjava/lang/Object;)Lcom/fasterxml/jackson/databind/node/ArrayNode;
  #274 = Utf8               insertRawValue
  #275 = Utf8               (ILcom/fasterxml/jackson/databind/util/RawValue;)Lcom/fasterxml/jackson/databind/node/ArrayNode;
  #276 = Utf8               (IS)Lcom/fasterxml/jackson/databind/node/ArrayNode;
  #277 = Utf8               (ILjava/lang/Short;)Lcom/fasterxml/jackson/databind/node/ArrayNode;
  #278 = Utf8               (II)Lcom/fasterxml/jackson/databind/node/ArrayNode;
  #279 = Utf8               (ILjava/lang/Integer;)Lcom/fasterxml/jackson/databind/node/ArrayNode;
  #280 = Utf8               (IJ)Lcom/fasterxml/jackson/databind/node/ArrayNode;
  #281 = Utf8               (ILjava/lang/Long;)Lcom/fasterxml/jackson/databind/node/ArrayNode;
  #282 = Utf8               (IF)Lcom/fasterxml/jackson/databind/node/ArrayNode;
  #283 = Utf8               (ILjava/lang/Float;)Lcom/fasterxml/jackson/databind/node/ArrayNode;
  #284 = Utf8               (ID)Lcom/fasterxml/jackson/databind/node/ArrayNode;
  #285 = Utf8               (ILjava/lang/Double;)Lcom/fasterxml/jackson/databind/node/ArrayNode;
  #286 = Utf8               (ILjava/math/BigDecimal;)Lcom/fasterxml/jackson/databind/node/ArrayNode;
  #287 = Utf8               (ILjava/math/BigInteger;)Lcom/fasterxml/jackson/databind/node/ArrayNode;
  #288 = Utf8               (ILjava/lang/String;)Lcom/fasterxml/jackson/databind/node/ArrayNode;
  #289 = Utf8               (IZ)Lcom/fasterxml/jackson/databind/node/ArrayNode;
  #290 = Utf8               (ILjava/lang/Boolean;)Lcom/fasterxml/jackson/databind/node/ArrayNode;
  #291 = Utf8               (I[B)Lcom/fasterxml/jackson/databind/node/ArrayNode;
  #292 = Utf8               setNull
  #293 = Utf8               setPOJO
  #294 = Utf8               setRawValue
  #295 = Utf8               (Ljava/lang/Object;)Z
  #296 = Utf8               _childrenEqual
  #297 = Utf8               (Lcom/fasterxml/jackson/databind/node/ArrayNode;)Z
  #298 = Utf8               hashCode
  #299 = Utf8               _set
  #300 = Utf8               _add
  #301 = Utf8               _insert
  #302 = Utf8               ()Lcom/fasterxml/jackson/databind/node/ContainerNode;
  #303 = Utf8               ()Lcom/fasterxml/jackson/databind/JsonNode;
  #304 = Utf8               (I)Lcom/fasterxml/jackson/core/TreeNode;
  #305 = Utf8               (Ljava/lang/String;)Lcom/fasterxml/jackson/core/TreeNode;
  #306 = Utf8               Lcom/fasterxml/jackson/databind/node/ContainerNode<Lcom/fasterxml/jackson/databind/node/ArrayNode;>;Ljava/io/Serializable;
  #307 = Utf8               SourceFile
  #308 = Utf8               ArrayNode.java
  #309 = NameAndType        #102:#103     // "<init>":(Lcom/fasterxml/jackson/databind/node/JsonNodeFactory;)V
  #310 = Utf8               java/util/ArrayList
  #311 = NameAndType        #102:#426     // "<init>":()V
  #312 = NameAndType        #98:#99       // _children:Ljava/util/List;
  #313 = NameAndType        #102:#427     // "<init>":(I)V
  #314 = Class              #428          // com/fasterxml/jackson/core/JsonPointer
  #315 = NameAndType        #429:#141     // getMatchingIndex:()I
  #316 = NameAndType        #145:#146     // get:(I)Lcom/fasterxml/jackson/databind/JsonNode;
  #317 = Utf8               com/fasterxml/jackson/databind/node/ArrayNode
  #318 = NameAndType        #430:#110     // _nodeFactory:Lcom/fasterxml/jackson/databind/node/JsonNodeFactory;
  #319 = Class              #413          // java/util/List
  #320 = NameAndType        #431:#143     // iterator:()Ljava/util/Iterator;
  #321 = Class              #412          // java/util/Iterator
  #322 = NameAndType        #432:#137     // hasNext:()Z
  #323 = NameAndType        #433:#434     // next:()Ljava/lang/Object;
  #324 = Utf8               com/fasterxml/jackson/databind/JsonNode
  #325 = NameAndType        #122:#303     // deepCopy:()Lcom/fasterxml/jackson/databind/JsonNode;
  #326 = NameAndType        #199:#295     // add:(Ljava/lang/Object;)Z
  #327 = NameAndType        #130:#137     // isEmpty:()Z
  #328 = Class              #435          // com/fasterxml/jackson/databind/node/JsonNodeType
  #329 = NameAndType        #436:#437     // ARRAY:Lcom/fasterxml/jackson/databind/node/JsonNodeType;
  #330 = Class              #438          // com/fasterxml/jackson/core/JsonToken
  #331 = NameAndType        #439:#440     // START_ARRAY:Lcom/fasterxml/jackson/core/JsonToken;
  #332 = NameAndType        #140:#141     // size:()I
  #333 = NameAndType        #145:#441     // get:(I)Ljava/lang/Object;
  #334 = Class              #442          // com/fasterxml/jackson/databind/node/MissingNode
  #335 = NameAndType        #443:#444     // getInstance:()Lcom/fasterxml/jackson/databind/node/MissingNode;
  #336 = Utf8               No value at index #%d [0, %d) of `ArrayNode`
  #337 = Utf8               java/lang/Object
  #338 = Class              #418          // java/lang/Integer
  #339 = NameAndType        #445:#446     // valueOf:(I)Ljava/lang/Integer;
  #340 = NameAndType        #447:#448     // _reportRequiredViolation:(Ljava/lang/String;[Ljava/lang/Object;)Ljava/lang/Object;
  #341 = NameAndType        #153:#154     // equals:(Ljava/util/Comparator;Lcom/fasterxml/jackson/databind/JsonNode;)Z
  #342 = Class              #449          // com/fasterxml/jackson/core/JsonGenerator
  #343 = NameAndType        #450:#451     // writeStartArray:(Ljava/lang/Object;I)V
  #344 = Utf8               com/fasterxml/jackson/databind/node/BaseJsonNode
  #345 = NameAndType        #166:#167     // serialize:(Lcom/fasterxml/jackson/core/JsonGenerator;Lcom/fasterxml/jackson/databind/SerializerProvider;)V
  #346 = NameAndType        #452:#426     // writeEndArray:()V
  #347 = Class              #453          // com/fasterxml/jackson/databind/jsontype/TypeSerializer
  #348 = NameAndType        #454:#455     // typeId:(Ljava/lang/Object;Lcom/fasterxml/jackson/core/JsonToken;)Lcom/fasterxml/jackson/core/type/WritableTypeId;
  #349 = NameAndType        #456:#457     // writeTypePrefix:(Lcom/fasterxml/jackson/core/JsonGenerator;Lcom/fasterxml/jackson/core/type/WritableTypeId;)Lcom/fasterxml/jackson/core/type/WritableTypeId;
  #350 = NameAndType        #458:#457     // writeTypeSuffix:(Lcom/fasterxml/jackson/core/JsonGenerator;Lcom/fasterxml/jackson/core/type/WritableTypeId;)Lcom/fasterxml/jackson/core/type/WritableTypeId;
  #351 = NameAndType        #183:#148     // findValue:(Ljava/lang/String;)Lcom/fasterxml/jackson/databind/JsonNode;
  #352 = NameAndType        #186:#187     // findValues:(Ljava/lang/String;Ljava/util/List;)Ljava/util/List;
  #353 = NameAndType        #190:#187     // findValuesAsText:(Ljava/lang/String;Ljava/util/List;)Ljava/util/List;
  #354 = NameAndType        #193:#148     // findParent:(Ljava/lang/String;)Lcom/fasterxml/jackson/databind/JsonNode;
  #355 = Utf8               com/fasterxml/jackson/databind/node/ObjectNode
  #356 = NameAndType        #196:#187     // findParents:(Ljava/lang/String;Ljava/util/List;)Ljava/util/List;
  #357 = NameAndType        #459:#460     // nullNode:()Lcom/fasterxml/jackson/databind/node/NullNode;
  #358 = Utf8               java/lang/IndexOutOfBoundsException
  #359 = Utf8               java/lang/StringBuilder
  #360 = Utf8               Illegal index
  #361 = NameAndType        #461:#462     // append:(Ljava/lang/String;)Ljava/lang/StringBuilder;
  #362 = NameAndType        #461:#463     // append:(I)Ljava/lang/StringBuilder;
  #363 = Utf8               , array size
  #364 = NameAndType        #464:#465     // toString:()Ljava/lang/String;
  #365 = NameAndType        #102:#466     // "<init>":(Ljava/lang/String;)V
  #366 = NameAndType        #197:#467     // set:(ILjava/lang/Object;)Ljava/lang/Object;
  #367 = NameAndType        #300:#200     // _add:(Lcom/fasterxml/jackson/databind/JsonNode;)Lcom/fasterxml/jackson/databind/node/ArrayNode;
  #368 = NameAndType        #201:#468     // addAll:(Ljava/util/Collection;)Z
  #369 = Class              #469          // java/util/Collection
  #370 = NameAndType        #199:#200     // add:(Lcom/fasterxml/jackson/databind/JsonNode;)Lcom/fasterxml/jackson/databind/node/ArrayNode;
  #371 = NameAndType        #301:#209     // _insert:(ILcom/fasterxml/jackson/databind/JsonNode;)Lcom/fasterxml/jackson/databind/node/ArrayNode;
  #372 = NameAndType        #210:#441     // remove:(I)Ljava/lang/Object;
  #373 = NameAndType        #470:#426     // clear:()V
  #374 = NameAndType        #471:#123     // arrayNode:()Lcom/fasterxml/jackson/databind/node/ArrayNode;
  #375 = NameAndType        #472:#214     // objectNode:()Lcom/fasterxml/jackson/databind/node/ObjectNode;
  #376 = NameAndType        #473:#474     // pojoNode:(Ljava/lang/Object;)Lcom/fasterxml/jackson/databind/node/ValueNode;
  #377 = NameAndType        #475:#476     // rawValueNode:(Lcom/fasterxml/jackson/databind/util/RawValue;)Lcom/fasterxml/jackson/databind/node/ValueNode;
  #378 = NameAndType        #477:#478     // numberNode:(S)Lcom/fasterxml/jackson/databind/node/NumericNode;
  #379 = Class              #417          // java/lang/Short
  #380 = NameAndType        #479:#480     // shortValue:()S
  #381 = NameAndType        #477:#481     // numberNode:(I)Lcom/fasterxml/jackson/databind/node/NumericNode;
  #382 = NameAndType        #482:#141     // intValue:()I
  #383 = NameAndType        #477:#483     // numberNode:(J)Lcom/fasterxml/jackson/databind/node/NumericNode;
  #384 = Class              #419          // java/lang/Long
  #385 = NameAndType        #484:#485     // longValue:()J
  #386 = NameAndType        #477:#486     // numberNode:(F)Lcom/fasterxml/jackson/databind/node/NumericNode;
  #387 = Class              #420          // java/lang/Float
  #388 = NameAndType        #487:#488     // floatValue:()F
  #389 = NameAndType        #477:#489     // numberNode:(D)Lcom/fasterxml/jackson/databind/node/NumericNode;
  #390 = Class              #421          // java/lang/Double
  #391 = NameAndType        #490:#491     // doubleValue:()D
  #392 = NameAndType        #477:#492     // numberNode:(Ljava/math/BigDecimal;)Lcom/fasterxml/jackson/databind/node/ValueNode;
  #393 = NameAndType        #477:#493     // numberNode:(Ljava/math/BigInteger;)Lcom/fasterxml/jackson/databind/node/ValueNode;
  #394 = NameAndType        #494:#495     // textNode:(Ljava/lang/String;)Lcom/fasterxml/jackson/databind/node/TextNode;
  #395 = NameAndType        #496:#497     // booleanNode:(Z)Lcom/fasterxml/jackson/databind/node/BooleanNode;
  #396 = Class              #425          // java/lang/Boolean
  #397 = NameAndType        #498:#137     // booleanValue:()Z
  #398 = NameAndType        #499:#500     // binaryNode:([B)Lcom/fasterxml/jackson/databind/node/BinaryNode;
  #399 = NameAndType        #271:#234     // insertNull:(I)Lcom/fasterxml/jackson/databind/node/ArrayNode;
  #400 = NameAndType        #299:#209     // _set:(ILcom/fasterxml/jackson/databind/JsonNode;)Lcom/fasterxml/jackson/databind/node/ArrayNode;
  #401 = NameAndType        #153:#295     // equals:(Ljava/lang/Object;)Z
  #402 = NameAndType        #298:#141     // hashCode:()I
  #403 = NameAndType        #199:#501     // add:(ILjava/lang/Object;)V
  #404 = NameAndType        #211:#123     // removeAll:()Lcom/fasterxml/jackson/databind/node/ArrayNode;
  #405 = NameAndType        #193:#194     // findParent:(Ljava/lang/String;)Lcom/fasterxml/jackson/databind/node/ObjectNode;
  #406 = NameAndType        #122:#123     // deepCopy:()Lcom/fasterxml/jackson/databind/node/ArrayNode;
  #407 = NameAndType        #151:#146     // path:(I)Lcom/fasterxml/jackson/databind/JsonNode;
  #408 = NameAndType        #151:#148     // path:(Ljava/lang/String;)Lcom/fasterxml/jackson/databind/JsonNode;
  #409 = NameAndType        #145:#148     // get:(Ljava/lang/String;)Lcom/fasterxml/jackson/databind/JsonNode;
  #410 = Utf8               com/fasterxml/jackson/databind/node/ContainerNode
  #411 = Utf8               java/io/Serializable
  #412 = Utf8               java/util/Iterator
  #413 = Utf8               java/util/List
  #414 = Utf8               java/io/IOException
  #415 = Utf8               com/fasterxml/jackson/core/type/WritableTypeId
  #416 = Utf8               com/fasterxml/jackson/databind/util/RawValue
  #417 = Utf8               java/lang/Short
  #418 = Utf8               java/lang/Integer
  #419 = Utf8               java/lang/Long
  #420 = Utf8               java/lang/Float
  #421 = Utf8               java/lang/Double
  #422 = Utf8               java/math/BigDecimal
  #423 = Utf8               java/math/BigInteger
  #424 = Utf8               java/lang/String
  #425 = Utf8               java/lang/Boolean
  #426 = Utf8               ()V
  #427 = Utf8               (I)V
  #428 = Utf8               com/fasterxml/jackson/core/JsonPointer
  #429 = Utf8               getMatchingIndex
  #430 = Utf8               _nodeFactory
  #431 = Utf8               iterator
  #432 = Utf8               hasNext
  #433 = Utf8               next
  #434 = Utf8               ()Ljava/lang/Object;
  #435 = Utf8               com/fasterxml/jackson/databind/node/JsonNodeType
  #436 = Utf8               ARRAY
  #437 = Utf8               Lcom/fasterxml/jackson/databind/node/JsonNodeType;
  #438 = Utf8               com/fasterxml/jackson/core/JsonToken
  #439 = Utf8               START_ARRAY
  #440 = Utf8               Lcom/fasterxml/jackson/core/JsonToken;
  #441 = Utf8               (I)Ljava/lang/Object;
  #442 = Utf8               com/fasterxml/jackson/databind/node/MissingNode
  #443 = Utf8               getInstance
  #444 = Utf8               ()Lcom/fasterxml/jackson/databind/node/MissingNode;
  #445 = Utf8               valueOf
  #446 = Utf8               (I)Ljava/lang/Integer;
  #447 = Utf8               _reportRequiredViolation
  #448 = Utf8               (Ljava/lang/String;[Ljava/lang/Object;)Ljava/lang/Object;
  #449 = Utf8               com/fasterxml/jackson/core/JsonGenerator
  #450 = Utf8               writeStartArray
  #451 = Utf8               (Ljava/lang/Object;I)V
  #452 = Utf8               writeEndArray
  #453 = Utf8               com/fasterxml/jackson/databind/jsontype/TypeSerializer
  #454 = Utf8               typeId
  #455 = Utf8               (Ljava/lang/Object;Lcom/fasterxml/jackson/core/JsonToken;)Lcom/fasterxml/jackson/core/type/WritableTypeId;
  #456 = Utf8               writeTypePrefix
  #457 = Utf8               (Lcom/fasterxml/jackson/core/JsonGenerator;Lcom/fasterxml/jackson/core/type/WritableTypeId;)Lcom/fasterxml/jackson/core/type/WritableTypeId;
  #458 = Utf8               writeTypeSuffix
  #459 = Utf8               nullNode
  #460 = Utf8               ()Lcom/fasterxml/jackson/databind/node/NullNode;
  #461 = Utf8               append
  #462 = Utf8               (Ljava/lang/String;)Ljava/lang/StringBuilder;
  #463 = Utf8               (I)Ljava/lang/StringBuilder;
  #464 = Utf8               toString
  #465 = Utf8               ()Ljava/lang/String;
  #466 = Utf8               (Ljava/lang/String;)V
  #467 = Utf8               (ILjava/lang/Object;)Ljava/lang/Object;
  #468 = Utf8               (Ljava/util/Collection;)Z
  #469 = Utf8               java/util/Collection
  #470 = Utf8               clear
  #471 = Utf8               arrayNode
  #472 = Utf8               objectNode
  #473 = Utf8               pojoNode
  #474 = Utf8               (Ljava/lang/Object;)Lcom/fasterxml/jackson/databind/node/ValueNode;
  #475 = Utf8               rawValueNode
  #476 = Utf8               (Lcom/fasterxml/jackson/databind/util/RawValue;)Lcom/fasterxml/jackson/databind/node/ValueNode;
  #477 = Utf8               numberNode
  #478 = Utf8               (S)Lcom/fasterxml/jackson/databind/node/NumericNode;
  #479 = Utf8               shortValue
  #480 = Utf8               ()S
  #481 = Utf8               (I)Lcom/fasterxml/jackson/databind/node/NumericNode;
  #482 = Utf8               intValue
  #483 = Utf8               (J)Lcom/fasterxml/jackson/databind/node/NumericNode;
  #484 = Utf8               longValue
  #485 = Utf8               ()J
  #486 = Utf8               (F)Lcom/fasterxml/jackson/databind/node/NumericNode;
  #487 = Utf8               floatValue
  #488 = Utf8               ()F
  #489 = Utf8               (D)Lcom/fasterxml/jackson/databind/node/NumericNode;
  #490 = Utf8               doubleValue
  #491 = Utf8               ()D
  #492 = Utf8               (Ljava/math/BigDecimal;)Lcom/fasterxml/jackson/databind/node/ValueNode;
  #493 = Utf8               (Ljava/math/BigInteger;)Lcom/fasterxml/jackson/databind/node/ValueNode;
  #494 = Utf8               textNode
  #495 = Utf8               (Ljava/lang/String;)Lcom/fasterxml/jackson/databind/node/TextNode;
  #496 = Utf8               booleanNode
  #497 = Utf8               (Z)Lcom/fasterxml/jackson/databind/node/BooleanNode;
  #498 = Utf8               booleanValue
  #499 = Utf8               binaryNode
  #500 = Utf8               ([B)Lcom/fasterxml/jackson/databind/node/BinaryNode;
  #501 = Utf8               (ILjava/lang/Object;)V
{
  private static final long serialVersionUID;
    descriptor: J
    flags: (0x001a) ACC_PRIVATE, ACC_STATIC, ACC_FINAL
    ConstantValue: long 1l

  private final java.util.List<com.fasterxml.jackson.databind.JsonNode> _children;
    descriptor: Ljava/util/List;
    flags: (0x0012) ACC_PRIVATE, ACC_FINAL
    Signature: #101                         // Ljava/util/List<Lcom/fasterxml/jackson/databind/JsonNode;>;

  public com.fasterxml.jackson.databind.node.ArrayNode(com.fasterxml.jackson.databind.node.JsonNodeFactory);
    descriptor: (Lcom/fasterxml/jackson/databind/node/JsonNodeFactory;)V
    flags: (0x0001) ACC_PUBLIC
    Code:
      stack=3, locals=2, args_size=2
         0: aload_0
         1: aload_1
         2: invokespecial #1                  // Method com/fasterxml/jackson/databind/node/ContainerNode."<init>":(Lcom/fasterxml/jackson/databind/node/JsonNodeFactory;)V
         5: aload_0
         6: new           #2                  // class java/util/ArrayList
         9: dup
        10: invokespecial #3                  // Method java/util/ArrayList."<init>":()V
        13: putfield      #4                  // Field _children:Ljava/util/List;
        16: return
      LineNumberTable:
        line 33: 0
        line 34: 5
        line 35: 16
      LocalVariableTable:
        Start  Length  Slot  Name   Signature
            0      17     0  this   Lcom/fasterxml/jackson/databind/node/ArrayNode;
            0      17     1    nf   Lcom/fasterxml/jackson/databind/node/JsonNodeFactory;

  public com.fasterxml.jackson.databind.node.ArrayNode(com.fasterxml.jackson.databind.node.JsonNodeFactory, int);
    descriptor: (Lcom/fasterxml/jackson/databind/node/JsonNodeFactory;I)V
    flags: (0x0001) ACC_PUBLIC
    Code:
      stack=4, locals=3, args_size=3
         0: aload_0
         1: aload_1
         2: invokespecial #1                  // Method com/fasterxml/jackson/databind/node/ContainerNode."<init>":(Lcom/fasterxml/jackson/databind/node/JsonNodeFactory;)V
         5: aload_0
         6: new           #2                  // class java/util/ArrayList
         9: dup
        10: iload_2
        11: invokespecial #5                  // Method java/util/ArrayList."<init>":(I)V
        14: putfield      #4                  // Field _children:Ljava/util/List;
        17: return
      LineNumberTable:
        line 41: 0
        line 42: 5
        line 43: 17
      LocalVariableTable:
        Start  Length  Slot  Name   Signature
            0      18     0  this   Lcom/fasterxml/jackson/databind/node/ArrayNode;
            0      18     1    nf   Lcom/fasterxml/jackson/databind/node/JsonNodeFactory;
            0      18     2 capacity   I

  public com.fasterxml.jackson.databind.node.ArrayNode(com.fasterxml.jackson.databind.node.JsonNodeFactory, java.util.List<com.fasterxml.jackson.databind.JsonNode>);
    descriptor: (Lcom/fasterxml/jackson/databind/node/JsonNodeFactory;Ljava/util/List;)V
    flags: (0x0001) ACC_PUBLIC
    Code:
      stack=2, locals=3, args_size=3
         0: aload_0
         1: aload_1
         2: invokespecial #1                  // Method com/fasterxml/jackson/databind/node/ContainerNode."<init>":(Lcom/fasterxml/jackson/databind/node/JsonNodeFactory;)V
         5: aload_0
         6: aload_2
         7: putfield      #4                  // Field _children:Ljava/util/List;
        10: return
      LineNumberTable:
        line 49: 0
        line 50: 5
        line 51: 10
      LocalVariableTable:
        Start  Length  Slot  Name   Signature
            0      11     0  this   Lcom/fasterxml/jackson/databind/node/ArrayNode;
            0      11     1    nf   Lcom/fasterxml/jackson/databind/node/JsonNodeFactory;
            0      11     2 children   Ljava/util/List;
      LocalVariableTypeTable:
        Start  Length  Slot  Name   Signature
            0      11     2 children   Ljava/util/List<Lcom/fasterxml/jackson/databind/JsonNode;>;
    Signature: #117                         // (Lcom/fasterxml/jackson/databind/node/JsonNodeFactory;Ljava/util/List<Lcom/fasterxml/jackson/databind/JsonNode;>;)V

  protected com.fasterxml.jackson.databind.JsonNode _at(com.fasterxml.jackson.core.JsonPointer);
    descriptor: (Lcom/fasterxml/jackson/core/JsonPointer;)Lcom/fasterxml/jackson/databind/JsonNode;
    flags: (0x0004) ACC_PROTECTED
    Code:
      stack=2, locals=2, args_size=2
         0: aload_0
         1: aload_1
         2: invokevirtual #6                  // Method com/fasterxml/jackson/core/JsonPointer.getMatchingIndex:()I
         5: invokevirtual #7                  // Method get:(I)Lcom/fasterxml/jackson/databind/JsonNode;
         8: areturn
      LineNumberTable:
        line 55: 0
      LocalVariableTable:
        Start  Length  Slot  Name   Signature
            0       9     0  this   Lcom/fasterxml/jackson/databind/node/ArrayNode;
            0       9     1   ptr   Lcom/fasterxml/jackson/core/JsonPointer;

  public com.fasterxml.jackson.databind.node.ArrayNode deepCopy();
    descriptor: ()Lcom/fasterxml/jackson/databind/node/ArrayNode;
    flags: (0x0001) ACC_PUBLIC
    Code:
      stack=3, locals=4, args_size=1
         0: new           #8                  // class com/fasterxml/jackson/databind/node/ArrayNode
         3: dup
         4: aload_0
         5: getfield      #9                  // Field _nodeFactory:Lcom/fasterxml/jackson/databind/node/JsonNodeFactory;
         8: invokespecial #10                 // Method "<init>":(Lcom/fasterxml/jackson/databind/node/JsonNodeFactory;)V
        11: astore_1
        12: aload_0
        13: getfield      #4                  // Field _children:Ljava/util/List;
        16: invokeinterface #11,  1           // InterfaceMethod java/util/List.iterator:()Ljava/util/Iterator;
        21: astore_2
        22: aload_2
        23: invokeinterface #12,  1           // InterfaceMethod java/util/Iterator.hasNext:()Z
        28: ifeq          58
        31: aload_2
        32: invokeinterface #13,  1           // InterfaceMethod java/util/Iterator.next:()Ljava/lang/Object;
        37: checkcast     #14                 // class com/fasterxml/jackson/databind/JsonNode
        40: astore_3
        41: aload_1
        42: getfield      #4                  // Field _children:Ljava/util/List;
        45: aload_3
        46: invokevirtual #15                 // Method com/fasterxml/jackson/databind/JsonNode.deepCopy:()Lcom/fasterxml/jackson/databind/JsonNode;
        49: invokeinterface #16,  2           // InterfaceMethod java/util/List.add:(Ljava/lang/Object;)Z
        54: pop
        55: goto          22
        58: aload_1
        59: areturn
      LineNumberTable:
        line 63: 0
        line 65: 12
        line 66: 41
        line 68: 58
      LocalVariableTable:
        Start  Length  Slot  Name   Signature
           41      14     3 element   Lcom/fasterxml/jackson/databind/JsonNode;
            0      60     0  this   Lcom/fasterxml/jackson/databind/node/ArrayNode;
           12      48     1   ret   Lcom/fasterxml/jackson/databind/node/ArrayNode;
      StackMapTable: number_of_entries = 2
        frame_type = 253 /* append */
          offset_delta = 22
          locals = [ class com/fasterxml/jackson/databind/node/ArrayNode, class java/util/Iterator ]
        frame_type = 250 /* chop */
          offset_delta = 35

  public boolean isEmpty(com.fasterxml.jackson.databind.SerializerProvider);
    descriptor: (Lcom/fasterxml/jackson/databind/SerializerProvider;)Z
    flags: (0x0001) ACC_PUBLIC
    Code:
      stack=1, locals=2, args_size=2
         0: aload_0
         1: getfield      #4                  // Field _children:Ljava/util/List;
         4: invokeinterface #17,  1           // InterfaceMethod java/util/List.isEmpty:()Z
         9: ireturn
      LineNumberTable:
        line 79: 0
      LocalVariableTable:
        Start  Length  Slot  Name   Signature
            0      10     0  this   Lcom/fasterxml/jackson/databind/node/ArrayNode;
            0      10     1 serializers   Lcom/fasterxml/jackson/databind/SerializerProvider;

  public com.fasterxml.jackson.databind.node.JsonNodeType getNodeType();
    descriptor: ()Lcom/fasterxml/jackson/databind/node/JsonNodeType;
    flags: (0x0001) ACC_PUBLIC
    Code:
      stack=1, locals=1, args_size=1
         0: getstatic     #18                 // Field com/fasterxml/jackson/databind/node/JsonNodeType.ARRAY:Lcom/fasterxml/jackson/databind/node/JsonNodeType;
         3: areturn
      LineNumberTable:
        line 90: 0
      LocalVariableTable:
        Start  Length  Slot  Name   Signature
            0       4     0  this   Lcom/fasterxml/jackson/databind/node/ArrayNode;

  public boolean isArray();
    descriptor: ()Z
    flags: (0x0001) ACC_PUBLIC
    Code:
      stack=1, locals=1, args_size=1
         0: iconst_1
         1: ireturn
      LineNumberTable:
        line 95: 0
      LocalVariableTable:
        Start  Length  Slot  Name   Signature
            0       2     0  this   Lcom/fasterxml/jackson/databind/node/ArrayNode;

  public com.fasterxml.jackson.core.JsonToken asToken();
    descriptor: ()Lcom/fasterxml/jackson/core/JsonToken;
    flags: (0x0001) ACC_PUBLIC
    Code:
      stack=1, locals=1, args_size=1
         0: getstatic     #19                 // Field com/fasterxml/jackson/core/JsonToken.START_ARRAY:Lcom/fasterxml/jackson/core/JsonToken;
         3: areturn
      LineNumberTable:
        line 98: 0
      LocalVariableTable:
        Start  Length  Slot  Name   Signature
            0       4     0  this   Lcom/fasterxml/jackson/databind/node/ArrayNode;

  public int size();
    descriptor: ()I
    flags: (0x0001) ACC_PUBLIC
    Code:
      stack=1, locals=1, args_size=1
         0: aload_0
         1: getfield      #4                  // Field _children:Ljava/util/List;
         4: invokeinterface #20,  1           // InterfaceMethod java/util/List.size:()I
         9: ireturn
      LineNumberTable:
        line 102: 0
      LocalVariableTable:
        Start  Length  Slot  Name   Signature
            0      10     0  this   Lcom/fasterxml/jackson/databind/node/ArrayNode;

  public boolean isEmpty();
    descriptor: ()Z
    flags: (0x0001) ACC_PUBLIC
    Code:
      stack=1, locals=1, args_size=1
         0: aload_0
         1: getfield      #4                  // Field _children:Ljava/util/List;
         4: invokeinterface #17,  1           // InterfaceMethod java/util/List.isEmpty:()Z
         9: ireturn
      LineNumberTable:
        line 106: 0
      LocalVariableTable:
        Start  Length  Slot  Name   Signature
            0      10     0  this   Lcom/fasterxml/jackson/databind/node/ArrayNode;

  public java.util.Iterator<com.fasterxml.jackson.databind.JsonNode> elements();
    descriptor: ()Ljava/util/Iterator;
    flags: (0x0001) ACC_PUBLIC
    Code:
      stack=1, locals=1, args_size=1
         0: aload_0
         1: getfield      #4                  // Field _children:Ljava/util/List;
         4: invokeinterface #11,  1           // InterfaceMethod java/util/List.iterator:()Ljava/util/Iterator;
         9: areturn
      LineNumberTable:
        line 110: 0
      LocalVariableTable:
        Start  Length  Slot  Name   Signature
            0      10     0  this   Lcom/fasterxml/jackson/databind/node/ArrayNode;
    Signature: #144                         // ()Ljava/util/Iterator<Lcom/fasterxml/jackson/databind/JsonNode;>;

  public com.fasterxml.jackson.databind.JsonNode get(int);
    descriptor: (I)Lcom/fasterxml/jackson/databind/JsonNode;
    flags: (0x0001) ACC_PUBLIC
    Code:
      stack=2, locals=2, args_size=2
         0: iload_1
         1: iflt          31
         4: iload_1
         5: aload_0
         6: getfield      #4                  // Field _children:Ljava/util/List;
         9: invokeinterface #20,  1           // InterfaceMethod java/util/List.size:()I
        14: if_icmpge     31
        17: aload_0
        18: getfield      #4                  // Field _children:Ljava/util/List;
        21: iload_1
        22: invokeinterface #21,  2           // InterfaceMethod java/util/List.get:(I)Ljava/lang/Object;
        27: checkcast     #14                 // class com/fasterxml/jackson/databind/JsonNode
        30: areturn
        31: aconst_null
        32: areturn
      LineNumberTable:
        line 115: 0
        line 116: 17
        line 118: 31
      LocalVariableTable:
        Start  Length  Slot  Name   Signature
            0      33     0  this   Lcom/fasterxml/jackson/databind/node/ArrayNode;
            0      33     1 index   I
      StackMapTable: number_of_entries = 1
        frame_type = 31 /* same */

  public com.fasterxml.jackson.databind.JsonNode get(java.lang.String);
    descriptor: (Ljava/lang/String;)Lcom/fasterxml/jackson/databind/JsonNode;
    flags: (0x0001) ACC_PUBLIC
    Code:
      stack=1, locals=2, args_size=2
         0: aconst_null
         1: areturn
      LineNumberTable:
        line 122: 0
      LocalVariableTable:
        Start  Length  Slot  Name   Signature
            0       2     0  this   Lcom/fasterxml/jackson/databind/node/ArrayNode;
            0       2     1 fieldName   Ljava/lang/String;

  public com.fasterxml.jackson.databind.JsonNode path(java.lang.String);
    descriptor: (Ljava/lang/String;)Lcom/fasterxml/jackson/databind/JsonNode;
    flags: (0x0001) ACC_PUBLIC
    Code:
      stack=1, locals=2, args_size=2
         0: invokestatic  #22                 // Method com/fasterxml/jackson/databind/node/MissingNode.getInstance:()Lcom/fasterxml/jackson/databind/node/MissingNode;
         3: areturn
      LineNumberTable:
        line 125: 0
      LocalVariableTable:
        Start  Length  Slot  Name   Signature
            0       4     0  this   Lcom/fasterxml/jackson/databind/node/ArrayNode;
            0       4     1 fieldName   Ljava/lang/String;

  public com.fasterxml.jackson.databind.JsonNode path(int);
    descriptor: (I)Lcom/fasterxml/jackson/databind/JsonNode;
    flags: (0x0001) ACC_PUBLIC
    Code:
      stack=2, locals=2, args_size=2
         0: iload_1
         1: iflt          31
         4: iload_1
         5: aload_0
         6: getfield      #4                  // Field _children:Ljava/util/List;
         9: invokeinterface #20,  1           // InterfaceMethod java/util/List.size:()I
        14: if_icmpge     31
        17: aload_0
        18: getfield      #4                  // Field _children:Ljava/util/List;
        21: iload_1
        22: invokeinterface #21,  2           // InterfaceMethod java/util/List.get:(I)Ljava/lang/Object;
        27: checkcast     #14                 // class com/fasterxml/jackson/databind/JsonNode
        30: areturn
        31: invokestatic  #22                 // Method com/fasterxml/jackson/databind/node/MissingNode.getInstance:()Lcom/fasterxml/jackson/databind/node/MissingNode;
        34: areturn
      LineNumberTable:
        line 129: 0
        line 130: 17
        line 132: 31
      LocalVariableTable:
        Start  Length  Slot  Name   Signature
            0      35     0  this   Lcom/fasterxml/jackson/databind/node/ArrayNode;
            0      35     1 index   I
      StackMapTable: number_of_entries = 1
        frame_type = 31 /* same */

  public com.fasterxml.jackson.databind.JsonNode required(int);
    descriptor: (I)Lcom/fasterxml/jackson/databind/JsonNode;
    flags: (0x0001) ACC_PUBLIC
    Code:
      stack=6, locals=2, args_size=2
         0: iload_1
         1: iflt          31
         4: iload_1
         5: aload_0
         6: getfield      #4                  // Field _children:Ljava/util/List;
         9: invokeinterface #20,  1           // InterfaceMethod java/util/List.size:()I
        14: if_icmpge     31
        17: aload_0
        18: getfield      #4                  // Field _children:Ljava/util/List;
        21: iload_1
        22: invokeinterface #21,  2           // InterfaceMethod java/util/List.get:(I)Ljava/lang/Object;
        27: checkcast     #14                 // class com/fasterxml/jackson/databind/JsonNode
        30: areturn
        31: aload_0
        32: ldc           #23                 // String No value at index #%d [0, %d) of `ArrayNode`
        34: iconst_2
        35: anewarray     #24                 // class java/lang/Object
        38: dup
        39: iconst_0
        40: iload_1
        41: invokestatic  #25                 // Method java/lang/Integer.valueOf:(I)Ljava/lang/Integer;
        44: aastore
        45: dup
        46: iconst_1
        47: aload_0
        48: getfield      #4                  // Field _children:Ljava/util/List;
        51: invokeinterface #20,  1           // InterfaceMethod java/util/List.size:()I
        56: invokestatic  #25                 // Method java/lang/Integer.valueOf:(I)Ljava/lang/Integer;
        59: aastore
        60: invokevirtual #26                 // Method _reportRequiredViolation:(Ljava/lang/String;[Ljava/lang/Object;)Ljava/lang/Object;
        63: checkcast     #14                 // class com/fasterxml/jackson/databind/JsonNode
        66: areturn
      LineNumberTable:
        line 137: 0
        line 138: 17
        line 140: 31
        line 141: 41
        line 140: 60
      LocalVariableTable:
        Start  Length  Slot  Name   Signature
            0      67     0  this   Lcom/fasterxml/jackson/databind/node/ArrayNode;
            0      67     1 index   I
      StackMapTable: number_of_entries = 1
        frame_type = 31 /* same */

  public boolean equals(java.util.Comparator<com.fasterxml.jackson.databind.JsonNode>, com.fasterxml.jackson.databind.JsonNode);
    descriptor: (Ljava/util/Comparator;Lcom/fasterxml/jackson/databind/JsonNode;)Z
    flags: (0x0001) ACC_PUBLIC
    Code:
      stack=4, locals=8, args_size=3
         0: aload_2
         1: instanceof    #8                  // class com/fasterxml/jackson/databind/node/ArrayNode
         4: ifne          9
         7: iconst_0
         8: ireturn
         9: aload_2
        10: checkcast     #8                  // class com/fasterxml/jackson/databind/node/ArrayNode
        13: astore_3
        14: aload_0
        15: getfield      #4                  // Field _children:Ljava/util/List;
        18: invokeinterface #20,  1           // InterfaceMethod java/util/List.size:()I
        23: istore        4
        25: aload_3
        26: invokevirtual #27                 // Method size:()I
        29: iload         4
        31: if_icmpeq     36
        34: iconst_0
        35: ireturn
        36: aload_0
        37: getfield      #4                  // Field _children:Ljava/util/List;
        40: astore        5
        42: aload_3
        43: getfield      #4                  // Field _children:Ljava/util/List;
        46: astore        6
        48: iconst_0
        49: istore        7
        51: iload         7
        53: iload         4
        55: if_icmpge     97
        58: aload         5
        60: iload         7
        62: invokeinterface #21,  2           // InterfaceMethod java/util/List.get:(I)Ljava/lang/Object;
        67: checkcast     #14                 // class com/fasterxml/jackson/databind/JsonNode
        70: aload_1
        71: aload         6
        73: iload         7
        75: invokeinterface #21,  2           // InterfaceMethod java/util/List.get:(I)Ljava/lang/Object;
        80: checkcast     #14                 // class com/fasterxml/jackson/databind/JsonNode
        83: invokevirtual #28                 // Method com/fasterxml/jackson/databind/JsonNode.equals:(Ljava/util/Comparator;Lcom/fasterxml/jackson/databind/JsonNode;)Z
        86: ifne          91
        89: iconst_0
        90: ireturn
        91: iinc          7, 1
        94: goto          51
        97: iconst_1
        98: ireturn
      LineNumberTable:
        line 147: 0
        line 148: 7
        line 150: 9
        line 151: 14
        line 152: 25
        line 153: 34
        line 155: 36
        line 156: 42
        line 157: 48
        line 158: 58
        line 159: 89
        line 157: 91
        line 162: 97
      LocalVariableTable:
        Start  Length  Slot  Name   Signature
           51      46     7     i   I
            0      99     0  this   Lcom/fasterxml/jackson/databind/node/ArrayNode;
            0      99     1 comparator   Ljava/util/Comparator;
            0      99     2     o   Lcom/fasterxml/jackson/databind/JsonNode;
           14      85     3 other   Lcom/fasterxml/jackson/databind/node/ArrayNode;
           25      74     4   len   I
           42      57     5    l1   Ljava/util/List;
           48      51     6    l2   Ljava/util/List;
      LocalVariableTypeTable:
        Start  Length  Slot  Name   Signature
            0      99     1 comparator   Ljava/util/Comparator<Lcom/fasterxml/jackson/databind/JsonNode;>;
           42      57     5    l1   Ljava/util/List<Lcom/fasterxml/jackson/databind/JsonNode;>;
           48      51     6    l2   Ljava/util/List<Lcom/fasterxml/jackson/databind/JsonNode;>;
      StackMapTable: number_of_entries = 5
        frame_type = 9 /* same */
        frame_type = 253 /* append */
          offset_delta = 26
          locals = [ class com/fasterxml/jackson/databind/node/ArrayNode, int ]
        frame_type = 254 /* append */
          offset_delta = 14
          locals = [ class java/util/List, class java/util/List, int ]
        frame_type = 39 /* same */
        frame_type = 250 /* chop */
          offset_delta = 5
    Signature: #165                         // (Ljava/util/Comparator<Lcom/fasterxml/jackson/databind/JsonNode;>;Lcom/fasterxml/jackson/databind/JsonNode;)Z

  public void serialize(com.fasterxml.jackson.core.JsonGenerator, com.fasterxml.jackson.databind.SerializerProvider) throws java.io.IOException;
    descriptor: (Lcom/fasterxml/jackson/core/JsonGenerator;Lcom/fasterxml/jackson/databind/SerializerProvider;)V
    flags: (0x0001) ACC_PUBLIC
    Code:
      stack=3, locals=7, args_size=3
         0: aload_0
         1: getfield      #4                  // Field _children:Ljava/util/List;
         4: astore_3
         5: aload_3
         6: invokeinterface #20,  1           // InterfaceMethod java/util/List.size:()I
        11: istore        4
        13: aload_1
        14: aload_0
        15: iload         4
        17: invokevirtual #29                 // Method com/fasterxml/jackson/core/JsonGenerator.writeStartArray:(Ljava/lang/Object;I)V
        20: iconst_0
        21: istore        5
        23: iload         5
        25: iload         4
        27: if_icmpge     59
        30: aload_3
        31: iload         5
        33: invokeinterface #21,  2           // InterfaceMethod java/util/List.get:(I)Ljava/lang/Object;
        38: checkcast     #14                 // class com/fasterxml/jackson/databind/JsonNode
        41: astore        6
        43: aload         6
        45: checkcast     #30                 // class com/fasterxml/jackson/databind/node/BaseJsonNode
        48: aload_1
        49: aload_2
        50: invokevirtual #31                 // Method com/fasterxml/jackson/databind/node/BaseJsonNode.serialize:(Lcom/fasterxml/jackson/core/JsonGenerator;Lcom/fasterxml/jackson/databind/SerializerProvider;)V
        53: iinc          5, 1
        56: goto          23
        59: aload_1
        60: invokevirtual #32                 // Method com/fasterxml/jackson/core/JsonGenerator.writeEndArray:()V
        63: return
      LineNumberTable:
        line 174: 0
        line 175: 5
        line 176: 13
        line 177: 20
        line 179: 30
        line 180: 43
        line 177: 53
        line 182: 59
        line 183: 63
      LocalVariableTable:
        Start  Length  Slot  Name   Signature
           43      10     6     n   Lcom/fasterxml/jackson/databind/JsonNode;
           23      36     5     i   I
            0      64     0  this   Lcom/fasterxml/jackson/databind/node/ArrayNode;
            0      64     1     f   Lcom/fasterxml/jackson/core/JsonGenerator;
            0      64     2 provider   Lcom/fasterxml/jackson/databind/SerializerProvider;
            5      59     3     c   Ljava/util/List;
           13      51     4  size   I
      LocalVariableTypeTable:
        Start  Length  Slot  Name   Signature
            5      59     3     c   Ljava/util/List<Lcom/fasterxml/jackson/databind/JsonNode;>;
      StackMapTable: number_of_entries = 2
        frame_type = 254 /* append */
          offset_delta = 23
          locals = [ class java/util/List, int, int ]
        frame_type = 250 /* chop */
          offset_delta = 35
    Exceptions:
      throws java.io.IOException

  public void serializeWithType(com.fasterxml.jackson.core.JsonGenerator, com.fasterxml.jackson.databind.SerializerProvider, com.fasterxml.jackson.databind.jsontype.TypeSerializer) throws java.io.IOException;
    descriptor: (Lcom/fasterxml/jackson/core/JsonGenerator;Lcom/fasterxml/jackson/databind/SerializerProvider;Lcom/fasterxml/jackson/databind/jsontype/TypeSerializer;)V
    flags: (0x0001) ACC_PUBLIC
    Code:
      stack=5, locals=7, args_size=4
         0: aload_3
         1: aload_1
         2: aload_3
         3: aload_0
         4: getstatic     #19                 // Field com/fasterxml/jackson/core/JsonToken.START_ARRAY:Lcom/fasterxml/jackson/core/JsonToken;
         7: invokevirtual #33                 // Method com/fasterxml/jackson/databind/jsontype/TypeSerializer.typeId:(Ljava/lang/Object;Lcom/fasterxml/jackson/core/JsonToken;)Lcom/fasterxml/jackson/core/type/WritableTypeId;
        10: invokevirtual #34                 // Method com/fasterxml/jackson/databind/jsontype/TypeSerializer.writeTypePrefix:(Lcom/fasterxml/jackson/core/JsonGenerator;Lcom/fasterxml/jackson/core/type/WritableTypeId;)Lcom/fasterxml/jackson/core/type/WritableTypeId;
        13: astore        4
        15: aload_0
        16: getfield      #4                  // Field _children:Ljava/util/List;
        19: invokeinterface #11,  1           // InterfaceMethod java/util/List.iterator:()Ljava/util/Iterator;
        24: astore        5
        26: aload         5
        28: invokeinterface #12,  1           // InterfaceMethod java/util/Iterator.hasNext:()Z
        33: ifeq          61
        36: aload         5
        38: invokeinterface #13,  1           // InterfaceMethod java/util/Iterator.next:()Ljava/lang/Object;
        43: checkcast     #14                 // class com/fasterxml/jackson/databind/JsonNode
        46: astore        6
        48: aload         6
        50: checkcast     #30                 // class com/fasterxml/jackson/databind/node/BaseJsonNode
        53: aload_1
        54: aload_2
        55: invokevirtual #31                 // Method com/fasterxml/jackson/databind/node/BaseJsonNode.serialize:(Lcom/fasterxml/jackson/core/JsonGenerator;Lcom/fasterxml/jackson/databind/SerializerProvider;)V
        58: goto          26
        61: aload_3
        62: aload_1
        63: aload         4
        65: invokevirtual #35                 // Method com/fasterxml/jackson/databind/jsontype/TypeSerializer.writeTypeSuffix:(Lcom/fasterxml/jackson/core/JsonGenerator;Lcom/fasterxml/jackson/core/type/WritableTypeId;)Lcom/fasterxml/jackson/core/type/WritableTypeId;
        68: pop
        69: return
      LineNumberTable:
        line 189: 0
        line 190: 7
        line 189: 10
        line 191: 15
        line 192: 48
        line 193: 58
        line 194: 61
        line 195: 69
      LocalVariableTable:
        Start  Length  Slot  Name   Signature
           48      10     6     n   Lcom/fasterxml/jackson/databind/JsonNode;
            0      70     0  this   Lcom/fasterxml/jackson/databind/node/ArrayNode;
            0      70     1     g   Lcom/fasterxml/jackson/core/JsonGenerator;
            0      70     2 provider   Lcom/fasterxml/jackson/databind/SerializerProvider;
            0      70     3 typeSer   Lcom/fasterxml/jackson/databind/jsontype/TypeSerializer;
           15      55     4 typeIdDef   Lcom/fasterxml/jackson/core/type/WritableTypeId;
      StackMapTable: number_of_entries = 2
        frame_type = 253 /* append */
          offset_delta = 26
          locals = [ class com/fasterxml/jackson/core/type/WritableTypeId, class java/util/Iterator ]
        frame_type = 250 /* chop */
          offset_delta = 34
    Exceptions:
      throws java.io.IOException

  public com.fasterxml.jackson.databind.JsonNode findValue(java.lang.String);
    descriptor: (Ljava/lang/String;)Lcom/fasterxml/jackson/databind/JsonNode;
    flags: (0x0001) ACC_PUBLIC
    Code:
      stack=2, locals=5, args_size=2
         0: aload_0
         1: getfield      #4                  // Field _children:Ljava/util/List;
         4: invokeinterface #11,  1           // InterfaceMethod java/util/List.iterator:()Ljava/util/Iterator;
         9: astore_2
        10: aload_2
        11: invokeinterface #12,  1           // InterfaceMethod java/util/Iterator.hasNext:()Z
        16: ifeq          47
        19: aload_2
        20: invokeinterface #13,  1           // InterfaceMethod java/util/Iterator.next:()Ljava/lang/Object;
        25: checkcast     #14                 // class com/fasterxml/jackson/databind/JsonNode
        28: astore_3
        29: aload_3
        30: aload_1
        31: invokevirtual #36                 // Method com/fasterxml/jackson/databind/JsonNode.findValue:(Ljava/lang/String;)Lcom/fasterxml/jackson/databind/JsonNode;
        34: astore        4
        36: aload         4
        38: ifnull        44
        41: aload         4
        43: areturn
        44: goto          10
        47: aconst_null
        48: areturn
      LineNumberTable:
        line 206: 0
        line 207: 29
        line 208: 36
        line 209: 41
        line 211: 44
        line 212: 47
      LocalVariableTable:
        Start  Length  Slot  Name   Signature
           36       8     4 value   Lcom/fasterxml/jackson/databind/JsonNode;
           29      15     3  node   Lcom/fasterxml/jackson/databind/JsonNode;
            0      49     0  this   Lcom/fasterxml/jackson/databind/node/ArrayNode;
            0      49     1 fieldName   Ljava/lang/String;
      StackMapTable: number_of_entries = 3
        frame_type = 252 /* append */
          offset_delta = 10
          locals = [ class java/util/Iterator ]
        frame_type = 33 /* same */
        frame_type = 250 /* chop */
          offset_delta = 2

  public java.util.List<com.fasterxml.jackson.databind.JsonNode> findValues(java.lang.String, java.util.List<com.fasterxml.jackson.databind.JsonNode>);
    descriptor: (Ljava/lang/String;Ljava/util/List;)Ljava/util/List;
    flags: (0x0001) ACC_PUBLIC
    Code:
      stack=3, locals=5, args_size=3
         0: aload_0
         1: getfield      #4                  // Field _children:Ljava/util/List;
         4: invokeinterface #11,  1           // InterfaceMethod java/util/List.iterator:()Ljava/util/Iterator;
         9: astore_3
        10: aload_3
        11: invokeinterface #12,  1           // InterfaceMethod java/util/Iterator.hasNext:()Z
        16: ifeq          41
        19: aload_3
        20: invokeinterface #13,  1           // InterfaceMethod java/util/Iterator.next:()Ljava/lang/Object;
        25: checkcast     #14                 // class com/fasterxml/jackson/databind/JsonNode
        28: astore        4
        30: aload         4
        32: aload_1
        33: aload_2
        34: invokevirtual #37                 // Method com/fasterxml/jackson/databind/JsonNode.findValues:(Ljava/lang/String;Ljava/util/List;)Ljava/util/List;
        37: astore_2
        38: goto          10
        41: aload_2
        42: areturn
      LineNumberTable:
        line 218: 0
        line 219: 30
        line 220: 38
        line 221: 41
      LocalVariableTable:
        Start  Length  Slot  Name   Signature
           30       8     4  node   Lcom/fasterxml/jackson/databind/JsonNode;
            0      43     0  this   Lcom/fasterxml/jackson/databind/node/ArrayNode;
            0      43     1 fieldName   Ljava/lang/String;
            0      43     2 foundSoFar   Ljava/util/List;
      LocalVariableTypeTable:
        Start  Length  Slot  Name   Signature
            0      43     2 foundSoFar   Ljava/util/List<Lcom/fasterxml/jackson/databind/JsonNode;>;
      StackMapTable: number_of_entries = 2
        frame_type = 252 /* append */
          offset_delta = 10
          locals = [ class java/util/Iterator ]
        frame_type = 250 /* chop */
          offset_delta = 30
    Signature: #189                         // (Ljava/lang/String;Ljava/util/List<Lcom/fasterxml/jackson/databind/JsonNode;>;)Ljava/util/List<Lcom/fasterxml/jackson/databind/JsonNode;>;

  public java.util.List<java.lang.String> findValuesAsText(java.lang.String, java.util.List<java.lang.String>);
    descriptor: (Ljava/lang/String;Ljava/util/List;)Ljava/util/List;
    flags: (0x0001) ACC_PUBLIC
    Code:
      stack=3, locals=5, args_size=3
         0: aload_0
         1: getfield      #4                  // Field _children:Ljava/util/List;
         4: invokeinterface #11,  1           // InterfaceMethod java/util/List.iterator:()Ljava/util/Iterator;
         9: astore_3
        10: aload_3
        11: invokeinterface #12,  1           // InterfaceMethod java/util/Iterator.hasNext:()Z
        16: ifeq          41
        19: aload_3
        20: invokeinterface #13,  1           // InterfaceMethod java/util/Iterator.next:()Ljava/lang/Object;
        25: checkcast     #14                 // class com/fasterxml/jackson/databind/JsonNode
        28: astore        4
        30: aload         4
        32: aload_1
        33: aload_2
        34: invokevirtual #38                 // Method com/fasterxml/jackson/databind/JsonNode.findValuesAsText:(Ljava/lang/String;Ljava/util/List;)Ljava/util/List;
        37: astore_2
        38: goto          10
        41: aload_2
        42: areturn
      LineNumberTable:
        line 227: 0
        line 228: 30
        line 229: 38
        line 230: 41
      LocalVariableTable:
        Start  Length  Slot  Name   Signature
           30       8     4  node   Lcom/fasterxml/jackson/databind/JsonNode;
            0      43     0  this   Lcom/fasterxml/jackson/databind/node/ArrayNode;
            0      43     1 fieldName   Ljava/lang/String;
            0      43     2 foundSoFar   Ljava/util/List;
      LocalVariableTypeTable:
        Start  Length  Slot  Name   Signature
            0      43     2 foundSoFar   Ljava/util/List<Ljava/lang/String;>;
      StackMapTable: number_of_entries = 2
        frame_type = 252 /* append */
          offset_delta = 10
          locals = [ class java/util/Iterator ]
        frame_type = 250 /* chop */
          offset_delta = 30
    Signature: #192                         // (Ljava/lang/String;Ljava/util/List<Ljava/lang/String;>;)Ljava/util/List<Ljava/lang/String;>;

  public com.fasterxml.jackson.databind.node.ObjectNode findParent(java.lang.String);
    descriptor: (Ljava/lang/String;)Lcom/fasterxml/jackson/databind/node/ObjectNode;
    flags: (0x0001) ACC_PUBLIC
    Code:
      stack=2, locals=5, args_size=2
         0: aload_0
         1: getfield      #4                  // Field _children:Ljava/util/List;
         4: invokeinterface #11,  1           // InterfaceMethod java/util/List.iterator:()Ljava/util/Iterator;
         9: astore_2
        10: aload_2
        11: invokeinterface #12,  1           // InterfaceMethod java/util/Iterator.hasNext:()Z
        16: ifeq          50
        19: aload_2
        20: invokeinterface #13,  1           // InterfaceMethod java/util/Iterator.next:()Ljava/lang/Object;
        25: checkcast     #14                 // class com/fasterxml/jackson/databind/JsonNode
        28: astore_3
        29: aload_3
        30: aload_1
        31: invokevirtual #39                 // Method com/fasterxml/jackson/databind/JsonNode.findParent:(Ljava/lang/String;)Lcom/fasterxml/jackson/databind/JsonNode;
        34: astore        4
        36: aload         4
        38: ifnull        47
        41: aload         4
        43: checkcast     #40                 // class com/fasterxml/jackson/databind/node/ObjectNode
        46: areturn
        47: goto          10
        50: aconst_null
        51: areturn
      LineNumberTable:
        line 236: 0
        line 237: 29
        line 238: 36
        line 239: 41
        line 241: 47
        line 242: 50
      LocalVariableTable:
        Start  Length  Slot  Name   Signature
           36      11     4 parent   Lcom/fasterxml/jackson/databind/JsonNode;
           29      18     3  node   Lcom/fasterxml/jackson/databind/JsonNode;
            0      52     0  this   Lcom/fasterxml/jackson/databind/node/ArrayNode;
            0      52     1 fieldName   Ljava/lang/String;
      StackMapTable: number_of_entries = 3
        frame_type = 252 /* append */
          offset_delta = 10
          locals = [ class java/util/Iterator ]
        frame_type = 36 /* same */
        frame_type = 250 /* chop */
          offset_delta = 2

  public java.util.List<com.fasterxml.jackson.databind.JsonNode> findParents(java.lang.String, java.util.List<com.fasterxml.jackson.databind.JsonNode>);
    descriptor: (Ljava/lang/String;Ljava/util/List;)Ljava/util/List;
    flags: (0x0001) ACC_PUBLIC
    Code:
      stack=3, locals=5, args_size=3
         0: aload_0
         1: getfield      #4                  // Field _children:Ljava/util/List;
         4: invokeinterface #11,  1           // InterfaceMethod java/util/List.iterator:()Ljava/util/Iterator;
         9: astore_3
        10: aload_3
        11: invokeinterface #12,  1           // InterfaceMethod java/util/Iterator.hasNext:()Z
        16: ifeq          41
        19: aload_3
        20: invokeinterface #13,  1           // InterfaceMethod java/util/Iterator.next:()Ljava/lang/Object;
        25: checkcast     #14                 // class com/fasterxml/jackson/databind/JsonNode
        28: astore        4
        30: aload         4
        32: aload_1
        33: aload_2
        34: invokevirtual #41                 // Method com/fasterxml/jackson/databind/JsonNode.findParents:(Ljava/lang/String;Ljava/util/List;)Ljava/util/List;
        37: astore_2
        38: goto          10
        41: aload_2
        42: areturn
      LineNumberTable:
        line 248: 0
        line 249: 30
        line 250: 38
        line 251: 41
      LocalVariableTable:
        Start  Length  Slot  Name   Signature
           30       8     4  node   Lcom/fasterxml/jackson/databind/JsonNode;
            0      43     0  this   Lcom/fasterxml/jackson/databind/node/ArrayNode;
            0      43     1 fieldName   Ljava/lang/String;
            0      43     2 foundSoFar   Ljava/util/List;
      LocalVariableTypeTable:
        Start  Length  Slot  Name   Signature
            0      43     2 foundSoFar   Ljava/util/List<Lcom/fasterxml/jackson/databind/JsonNode;>;
      StackMapTable: number_of_entries = 2
        frame_type = 252 /* append */
          offset_delta = 10
          locals = [ class java/util/Iterator ]
        frame_type = 250 /* chop */
          offset_delta = 30
    Signature: #189                         // (Ljava/lang/String;Ljava/util/List<Lcom/fasterxml/jackson/databind/JsonNode;>;)Ljava/util/List<Lcom/fasterxml/jackson/databind/JsonNode;>;

  public com.fasterxml.jackson.databind.JsonNode set(int, com.fasterxml.jackson.databind.JsonNode);
    descriptor: (ILcom/fasterxml/jackson/databind/JsonNode;)Lcom/fasterxml/jackson/databind/JsonNode;
    flags: (0x0001) ACC_PUBLIC
    Code:
      stack=4, locals=3, args_size=3
         0: aload_2
         1: ifnonnull     9
         4: aload_0
         5: invokevirtual #42                 // Method nullNode:()Lcom/fasterxml/jackson/databind/node/NullNode;
         8: astore_2
         9: iload_1
        10: iflt          26
        13: iload_1
        14: aload_0
        15: getfield      #4                  // Field _children:Ljava/util/List;
        18: invokeinterface #20,  1           // InterfaceMethod java/util/List.size:()I
        23: if_icmplt     65
        26: new           #43                 // class java/lang/IndexOutOfBoundsException
        29: dup
        30: new           #44                 // class java/lang/StringBuilder
        33: dup
        34: invokespecial #45                 // Method java/lang/StringBuilder."<init>":()V
        37: ldc           #46                 // String Illegal index
        39: invokevirtual #47                 // Method java/lang/StringBuilder.append:(Ljava/lang/String;)Ljava/lang/StringBuilder;
        42: iload_1
        43: invokevirtual #48                 // Method java/lang/StringBuilder.append:(I)Ljava/lang/StringBuilder;
        46: ldc           #49                 // String , array size
        48: invokevirtual #47                 // Method java/lang/StringBuilder.append:(Ljava/lang/String;)Ljava/lang/StringBuilder;
        51: aload_0
        52: invokevirtual #27                 // Method size:()I
        55: invokevirtual #48                 // Method java/lang/StringBuilder.append:(I)Ljava/lang/StringBuilder;
        58: invokevirtual #50                 // Method java/lang/StringBuilder.toString:()Ljava/lang/String;
        61: invokespecial #51                 // Method java/lang/IndexOutOfBoundsException."<init>":(Ljava/lang/String;)V
        64: athrow
        65: aload_0
        66: getfield      #4                  // Field _children:Ljava/util/List;
        69: iload_1
        70: aload_2
        71: invokeinterface #52,  3           // InterfaceMethod java/util/List.set:(ILjava/lang/Object;)Ljava/lang/Object;
        76: checkcast     #14                 // class com/fasterxml/jackson/databind/JsonNode
        79: areturn
      LineNumberTable:
        line 273: 0
        line 274: 4
        line 276: 9
        line 277: 26
        line 279: 65
      LocalVariableTable:
        Start  Length  Slot  Name   Signature
            0      80     0  this   Lcom/fasterxml/jackson/databind/node/ArrayNode;
            0      80     1 index   I
            0      80     2 value   Lcom/fasterxml/jackson/databind/JsonNode;
      StackMapTable: number_of_entries = 3
        frame_type = 9 /* same */
        frame_type = 16 /* same */
        frame_type = 38 /* same */

  public com.fasterxml.jackson.databind.node.ArrayNode add(com.fasterxml.jackson.databind.JsonNode);
    descriptor: (Lcom/fasterxml/jackson/databind/JsonNode;)Lcom/fasterxml/jackson/databind/node/ArrayNode;
    flags: (0x0001) ACC_PUBLIC
    Code:
      stack=2, locals=2, args_size=2
         0: aload_1
         1: ifnonnull     9
         4: aload_0
         5: invokevirtual #42                 // Method nullNode:()Lcom/fasterxml/jackson/databind/node/NullNode;
         8: astore_1
         9: aload_0
        10: aload_1
        11: invokevirtual #53                 // Method _add:(Lcom/fasterxml/jackson/databind/JsonNode;)Lcom/fasterxml/jackson/databind/node/ArrayNode;
        14: pop
        15: aload_0
        16: areturn
      LineNumberTable:
        line 289: 0
        line 290: 4
        line 292: 9
        line 293: 15
      LocalVariableTable:
        Start  Length  Slot  Name   Signature
            0      17     0  this   Lcom/fasterxml/jackson/databind/node/ArrayNode;
            0      17     1 value   Lcom/fasterxml/jackson/databind/JsonNode;
      StackMapTable: number_of_entries = 1
        frame_type = 9 /* same */

  public com.fasterxml.jackson.databind.node.ArrayNode addAll(com.fasterxml.jackson.databind.node.ArrayNode);
    descriptor: (Lcom/fasterxml/jackson/databind/node/ArrayNode;)Lcom/fasterxml/jackson/databind/node/ArrayNode;
    flags: (0x0001) ACC_PUBLIC
    Code:
      stack=2, locals=2, args_size=2
         0: aload_0
         1: getfield      #4                  // Field _children:Ljava/util/List;
         4: aload_1
         5: getfield      #4                  // Field _children:Ljava/util/List;
         8: invokeinterface #54,  2           // InterfaceMethod java/util/List.addAll:(Ljava/util/Collection;)Z
        13: pop
        14: aload_0
        15: areturn
      LineNumberTable:
        line 306: 0
        line 307: 14
      LocalVariableTable:
        Start  Length  Slot  Name   Signature
            0      16     0  this   Lcom/fasterxml/jackson/databind/node/ArrayNode;
            0      16     1 other   Lcom/fasterxml/jackson/databind/node/ArrayNode;

  public com.fasterxml.jackson.databind.node.ArrayNode addAll(java.util.Collection<? extends com.fasterxml.jackson.databind.JsonNode>);
    descriptor: (Ljava/util/Collection;)Lcom/fasterxml/jackson/databind/node/ArrayNode;
    flags: (0x0001) ACC_PUBLIC
    Code:
      stack=2, locals=4, args_size=2
         0: aload_1
         1: invokeinterface #55,  1           // InterfaceMethod java/util/Collection.iterator:()Ljava/util/Iterator;
         6: astore_2
         7: aload_2
         8: invokeinterface #12,  1           // InterfaceMethod java/util/Iterator.hasNext:()Z
        13: ifeq          35
        16: aload_2
        17: invokeinterface #13,  1           // InterfaceMethod java/util/Iterator.next:()Ljava/lang/Object;
        22: checkcast     #14                 // class com/fasterxml/jackson/databind/JsonNode
        25: astore_3
        26: aload_0
        27: aload_3
        28: invokevirtual #56                 // Method add:(Lcom/fasterxml/jackson/databind/JsonNode;)Lcom/fasterxml/jackson/databind/node/ArrayNode;
        31: pop
        32: goto          7
        35: aload_0
        36: areturn
      LineNumberTable:
        line 319: 0
        line 320: 26
        line 321: 32
        line 322: 35
      LocalVariableTable:
        Start  Length  Slot  Name   Signature
           26       6     3  node   Lcom/fasterxml/jackson/databind/JsonNode;
            0      37     0  this   Lcom/fasterxml/jackson/databind/node/ArrayNode;
            0      37     1 nodes   Ljava/util/Collection;
      LocalVariableTypeTable:
        Start  Length  Slot  Name   Signature
            0      37     1 nodes   Ljava/util/Collection<+Lcom/fasterxml/jackson/databind/JsonNode;>;
      StackMapTable: number_of_entries = 2
        frame_type = 252 /* append */
          offset_delta = 7
          locals = [ class java/util/Iterator ]
        frame_type = 250 /* chop */
          offset_delta = 27
    Signature: #207                         // (Ljava/util/Collection<+Lcom/fasterxml/jackson/databind/JsonNode;>;)Lcom/fasterxml/jackson/databind/node/ArrayNode;

  public com.fasterxml.jackson.databind.node.ArrayNode insert(int, com.fasterxml.jackson.databind.JsonNode);
    descriptor: (ILcom/fasterxml/jackson/databind/JsonNode;)Lcom/fasterxml/jackson/databind/node/ArrayNode;
    flags: (0x0001) ACC_PUBLIC
    Code:
      stack=3, locals=3, args_size=3
         0: aload_2
         1: ifnonnull     9
         4: aload_0
         5: invokevirtual #42                 // Method nullNode:()Lcom/fasterxml/jackson/databind/node/NullNode;
         8: astore_2
         9: aload_0
        10: iload_1
        11: aload_2
        12: invokevirtual #57                 // Method _insert:(ILcom/fasterxml/jackson/databind/JsonNode;)Lcom/fasterxml/jackson/databind/node/ArrayNode;
        15: pop
        16: aload_0
        17: areturn
      LineNumberTable:
        line 336: 0
        line 337: 4
        line 339: 9
        line 340: 16
      LocalVariableTable:
        Start  Length  Slot  Name   Signature
            0      18     0  this   Lcom/fasterxml/jackson/databind/node/ArrayNode;
            0      18     1 index   I
            0      18     2 value   Lcom/fasterxml/jackson/databind/JsonNode;
      StackMapTable: number_of_entries = 1
        frame_type = 9 /* same */

  public com.fasterxml.jackson.databind.JsonNode remove(int);
    descriptor: (I)Lcom/fasterxml/jackson/databind/JsonNode;
    flags: (0x0001) ACC_PUBLIC
    Code:
      stack=2, locals=2, args_size=2
         0: iload_1
         1: iflt          31
         4: iload_1
         5: aload_0
         6: getfield      #4                  // Field _children:Ljava/util/List;
         9: invokeinterface #20,  1           // InterfaceMethod java/util/List.size:()I
        14: if_icmpge     31
        17: aload_0
        18: getfield      #4                  // Field _children:Ljava/util/List;
        21: iload_1
        22: invokeinterface #58,  2           // InterfaceMethod java/util/List.remove:(I)Ljava/lang/Object;
        27: checkcast     #14                 // class com/fasterxml/jackson/databind/JsonNode
        30: areturn
        31: aconst_null
        32: areturn
      LineNumberTable:
        line 352: 0
        line 353: 17
        line 355: 31
      LocalVariableTable:
        Start  Length  Slot  Name   Signature
            0      33     0  this   Lcom/fasterxml/jackson/databind/node/ArrayNode;
            0      33     1 index   I
      StackMapTable: number_of_entries = 1
        frame_type = 31 /* same */

  public com.fasterxml.jackson.databind.node.ArrayNode removeAll();
    descriptor: ()Lcom/fasterxml/jackson/databind/node/ArrayNode;
    flags: (0x0001) ACC_PUBLIC
    Code:
      stack=1, locals=1, args_size=1
         0: aload_0
         1: getfield      #4                  // Field _children:Ljava/util/List;
         4: invokeinterface #59,  1           // InterfaceMethod java/util/List.clear:()V
         9: aload_0
        10: areturn
      LineNumberTable:
        line 367: 0
        line 368: 9
      LocalVariableTable:
        Start  Length  Slot  Name   Signature
            0      11     0  this   Lcom/fasterxml/jackson/databind/node/ArrayNode;

  public com.fasterxml.jackson.databind.node.ArrayNode addArray();
    descriptor: ()Lcom/fasterxml/jackson/databind/node/ArrayNode;
    flags: (0x0001) ACC_PUBLIC
    Code:
      stack=2, locals=2, args_size=1
         0: aload_0
         1: invokevirtual #60                 // Method arrayNode:()Lcom/fasterxml/jackson/databind/node/ArrayNode;
         4: astore_1
         5: aload_0
         6: aload_1
         7: invokevirtual #53                 // Method _add:(Lcom/fasterxml/jackson/databind/JsonNode;)Lcom/fasterxml/jackson/databind/node/ArrayNode;
        10: pop
        11: aload_1
        12: areturn
      LineNumberTable:
        line 385: 0
        line 386: 5
        line 387: 11
      LocalVariableTable:
        Start  Length  Slot  Name   Signature
            0      13     0  this   Lcom/fasterxml/jackson/databind/node/ArrayNode;
            5       8     1     n   Lcom/fasterxml/jackson/databind/node/ArrayNode;

  public com.fasterxml.jackson.databind.node.ObjectNode addObject();
    descriptor: ()Lcom/fasterxml/jackson/databind/node/ObjectNode;
    flags: (0x0001) ACC_PUBLIC
    Code:
      stack=2, locals=2, args_size=1
         0: aload_0
         1: invokevirtual #61                 // Method objectNode:()Lcom/fasterxml/jackson/databind/node/ObjectNode;
         4: astore_1
         5: aload_0
         6: aload_1
         7: invokevirtual #53                 // Method _add:(Lcom/fasterxml/jackson/databind/JsonNode;)Lcom/fasterxml/jackson/databind/node/ArrayNode;
        10: pop
        11: aload_1
        12: areturn
      LineNumberTable:
        line 398: 0
        line 399: 5
        line 400: 11
      LocalVariableTable:
        Start  Length  Slot  Name   Signature
            0      13     0  this   Lcom/fasterxml/jackson/databind/node/ArrayNode;
            5       8     1     n   Lcom/fasterxml/jackson/databind/node/ObjectNode;

  public com.fasterxml.jackson.databind.node.ArrayNode addPOJO(java.lang.Object);
    descriptor: (Ljava/lang/Object;)Lcom/fasterxml/jackson/databind/node/ArrayNode;
    flags: (0x0001) ACC_PUBLIC
    Code:
      stack=3, locals=2, args_size=2
         0: aload_0
         1: aload_1
         2: ifnonnull     12
         5: aload_0
         6: invokevirtual #42                 // Method nullNode:()Lcom/fasterxml/jackson/databind/node/NullNode;
         9: goto          17
        12: aload_0
        13: aload_1
        14: invokevirtual #62                 // Method pojoNode:(Ljava/lang/Object;)Lcom/fasterxml/jackson/databind/node/ValueNode;
        17: invokevirtual #53                 // Method _add:(Lcom/fasterxml/jackson/databind/JsonNode;)Lcom/fasterxml/jackson/databind/node/ArrayNode;
        20: areturn
      LineNumberTable:
        line 410: 0
      LocalVariableTable:
        Start  Length  Slot  Name   Signature
            0      21     0  this   Lcom/fasterxml/jackson/databind/node/ArrayNode;
            0      21     1  pojo   Ljava/lang/Object;
      StackMapTable: number_of_entries = 2
        frame_type = 76 /* same_locals_1_stack_item */
          stack = [ class com/fasterxml/jackson/databind/node/ArrayNode ]
        frame_type = 255 /* full_frame */
          offset_delta = 4
          locals = [ class com/fasterxml/jackson/databind/node/ArrayNode, class java/lang/Object ]
          stack = [ class com/fasterxml/jackson/databind/node/ArrayNode, class com/fasterxml/jackson/databind/JsonNode ]

  public com.fasterxml.jackson.databind.node.ArrayNode addRawValue(com.fasterxml.jackson.databind.util.RawValue);
    descriptor: (Lcom/fasterxml/jackson/databind/util/RawValue;)Lcom/fasterxml/jackson/databind/node/ArrayNode;
    flags: (0x0001) ACC_PUBLIC
    Code:
      stack=3, locals=2, args_size=2
         0: aload_0
         1: aload_1
         2: ifnonnull     12
         5: aload_0
         6: invokevirtual #42                 // Method nullNode:()Lcom/fasterxml/jackson/databind/node/NullNode;
         9: goto          17
        12: aload_0
        13: aload_1
        14: invokevirtual #63                 // Method rawValueNode:(Lcom/fasterxml/jackson/databind/util/RawValue;)Lcom/fasterxml/jackson/databind/node/ValueNode;
        17: invokevirtual #53                 // Method _add:(Lcom/fasterxml/jackson/databind/JsonNode;)Lcom/fasterxml/jackson/databind/node/ArrayNode;
        20: areturn
      LineNumberTable:
        line 419: 0
      LocalVariableTable:
        Start  Length  Slot  Name   Signature
            0      21     0  this   Lcom/fasterxml/jackson/databind/node/ArrayNode;
            0      21     1   raw   Lcom/fasterxml/jackson/databind/util/RawValue;
      StackMapTable: number_of_entries = 2
        frame_type = 76 /* same_locals_1_stack_item */
          stack = [ class com/fasterxml/jackson/databind/node/ArrayNode ]
        frame_type = 255 /* full_frame */
          offset_delta = 4
          locals = [ class com/fasterxml/jackson/databind/node/ArrayNode, class com/fasterxml/jackson/databind/util/RawValue ]
          stack = [ class com/fasterxml/jackson/databind/node/ArrayNode, class com/fasterxml/jackson/databind/JsonNode ]

  public com.fasterxml.jackson.databind.node.ArrayNode addNull();
    descriptor: ()Lcom/fasterxml/jackson/databind/node/ArrayNode;
    flags: (0x0001) ACC_PUBLIC
    Code:
      stack=2, locals=1, args_size=1
         0: aload_0
         1: aload_0
         2: invokevirtual #42                 // Method nullNode:()Lcom/fasterxml/jackson/databind/node/NullNode;
         5: invokevirtual #53                 // Method _add:(Lcom/fasterxml/jackson/databind/JsonNode;)Lcom/fasterxml/jackson/databind/node/ArrayNode;
         8: areturn
      LineNumberTable:
        line 428: 0
      LocalVariableTable:
        Start  Length  Slot  Name   Signature
            0       9     0  this   Lcom/fasterxml/jackson/databind/node/ArrayNode;

  public com.fasterxml.jackson.databind.node.ArrayNode add(short);
    descriptor: (S)Lcom/fasterxml/jackson/databind/node/ArrayNode;
    flags: (0x0001) ACC_PUBLIC
    Code:
      stack=3, locals=2, args_size=2
         0: aload_0
         1: aload_0
         2: iload_1
         3: invokevirtual #64                 // Method numberNode:(S)Lcom/fasterxml/jackson/databind/node/NumericNode;
         6: invokevirtual #53                 // Method _add:(Lcom/fasterxml/jackson/databind/JsonNode;)Lcom/fasterxml/jackson/databind/node/ArrayNode;
         9: areturn
      LineNumberTable:
        line 439: 0
      LocalVariableTable:
        Start  Length  Slot  Name   Signature
            0      10     0  this   Lcom/fasterxml/jackson/databind/node/ArrayNode;
            0      10     1     v   S

  public com.fasterxml.jackson.databind.node.ArrayNode add(java.lang.Short);
    descriptor: (Ljava/lang/Short;)Lcom/fasterxml/jackson/databind/node/ArrayNode;
    flags: (0x0001) ACC_PUBLIC
    Code:
      stack=3, locals=2, args_size=2
         0: aload_0
         1: aload_1
         2: ifnonnull     12
         5: aload_0
         6: invokevirtual #42                 // Method nullNode:()Lcom/fasterxml/jackson/databind/node/NullNode;
         9: goto          20
        12: aload_0
        13: aload_1
        14: invokevirtual #65                 // Method java/lang/Short.shortValue:()S
        17: invokevirtual #64                 // Method numberNode:(S)Lcom/fasterxml/jackson/databind/node/NumericNode;
        20: invokevirtual #53                 // Method _add:(Lcom/fasterxml/jackson/databind/JsonNode;)Lcom/fasterxml/jackson/databind/node/ArrayNode;
        23: areturn
      LineNumberTable:
        line 451: 0
      LocalVariableTable:
        Start  Length  Slot  Name   Signature
            0      24     0  this   Lcom/fasterxml/jackson/databind/node/ArrayNode;
            0      24     1     v   Ljava/lang/Short;
      StackMapTable: number_of_entries = 2
        frame_type = 76 /* same_locals_1_stack_item */
          stack = [ class com/fasterxml/jackson/databind/node/ArrayNode ]
        frame_type = 255 /* full_frame */
          offset_delta = 7
          locals = [ class com/fasterxml/jackson/databind/node/ArrayNode, class java/lang/Short ]
          stack = [ class com/fasterxml/jackson/databind/node/ArrayNode, class com/fasterxml/jackson/databind/JsonNode ]

  public com.fasterxml.jackson.databind.node.ArrayNode add(int);
    descriptor: (I)Lcom/fasterxml/jackson/databind/node/ArrayNode;
    flags: (0x0001) ACC_PUBLIC
    Code:
      stack=3, locals=2, args_size=2
         0: aload_0
         1: aload_0
         2: iload_1
         3: invokevirtual #66                 // Method numberNode:(I)Lcom/fasterxml/jackson/databind/node/NumericNode;
         6: invokevirtual #53                 // Method _add:(Lcom/fasterxml/jackson/databind/JsonNode;)Lcom/fasterxml/jackson/databind/node/ArrayNode;
         9: areturn
      LineNumberTable:
        line 460: 0
      LocalVariableTable:
        Start  Length  Slot  Name   Signature
            0      10     0  this   Lcom/fasterxml/jackson/databind/node/ArrayNode;
            0      10     1     v   I

  public com.fasterxml.jackson.databind.node.ArrayNode add(java.lang.Integer);
    descriptor: (Ljava/lang/Integer;)Lcom/fasterxml/jackson/databind/node/ArrayNode;
    flags: (0x0001) ACC_PUBLIC
    Code:
      stack=3, locals=2, args_size=2
         0: aload_0
         1: aload_1
         2: ifnonnull     12
         5: aload_0
         6: invokevirtual #42                 // Method nullNode:()Lcom/fasterxml/jackson/databind/node/NullNode;
         9: goto          20
        12: aload_0
        13: aload_1
        14: invokevirtual #67                 // Method java/lang/Integer.intValue:()I
        17: invokevirtual #66                 // Method numberNode:(I)Lcom/fasterxml/jackson/databind/node/NumericNode;
        20: invokevirtual #53                 // Method _add:(Lcom/fasterxml/jackson/databind/JsonNode;)Lcom/fasterxml/jackson/databind/node/ArrayNode;
        23: areturn
      LineNumberTable:
        line 470: 0
      LocalVariableTable:
        Start  Length  Slot  Name   Signature
            0      24     0  this   Lcom/fasterxml/jackson/databind/node/ArrayNode;
            0      24     1     v   Ljava/lang/Integer;
      StackMapTable: number_of_entries = 2
        frame_type = 76 /* same_locals_1_stack_item */
          stack = [ class com/fasterxml/jackson/databind/node/ArrayNode ]
        frame_type = 255 /* full_frame */
          offset_delta = 7
          locals = [ class com/fasterxml/jackson/databind/node/ArrayNode, class java/lang/Integer ]
          stack = [ class com/fasterxml/jackson/databind/node/ArrayNode, class com/fasterxml/jackson/databind/JsonNode ]

  public com.fasterxml.jackson.databind.node.ArrayNode add(long);
    descriptor: (J)Lcom/fasterxml/jackson/databind/node/ArrayNode;
    flags: (0x0001) ACC_PUBLIC
    Code:
      stack=4, locals=3, args_size=2
         0: aload_0
         1: aload_0
         2: lload_1
         3: invokevirtual #68                 // Method numberNode:(J)Lcom/fasterxml/jackson/databind/node/NumericNode;
         6: invokevirtual #53                 // Method _add:(Lcom/fasterxml/jackson/databind/JsonNode;)Lcom/fasterxml/jackson/databind/node/ArrayNode;
         9: areturn
      LineNumberTable:
        line 478: 0
      LocalVariableTable:
        Start  Length  Slot  Name   Signature
            0      10     0  this   Lcom/fasterxml/jackson/databind/node/ArrayNode;
            0      10     1     v   J

  public com.fasterxml.jackson.databind.node.ArrayNode add(java.lang.Long);
    descriptor: (Ljava/lang/Long;)Lcom/fasterxml/jackson/databind/node/ArrayNode;
    flags: (0x0001) ACC_PUBLIC
    Code:
      stack=4, locals=2, args_size=2
         0: aload_0
         1: aload_1
         2: ifnonnull     12
         5: aload_0
         6: invokevirtual #42                 // Method nullNode:()Lcom/fasterxml/jackson/databind/node/NullNode;
         9: goto          20
        12: aload_0
        13: aload_1
        14: invokevirtual #69                 // Method java/lang/Long.longValue:()J
        17: invokevirtual #68                 // Method numberNode:(J)Lcom/fasterxml/jackson/databind/node/NumericNode;
        20: invokevirtual #53                 // Method _add:(Lcom/fasterxml/jackson/databind/JsonNode;)Lcom/fasterxml/jackson/databind/node/ArrayNode;
        23: areturn
      LineNumberTable:
        line 487: 0
      LocalVariableTable:
        Start  Length  Slot  Name   Signature
            0      24     0  this   Lcom/fasterxml/jackson/databind/node/ArrayNode;
            0      24     1     v   Ljava/lang/Long;
      StackMapTable: number_of_entries = 2
        frame_type = 76 /* same_locals_1_stack_item */
          stack = [ class com/fasterxml/jackson/databind/node/ArrayNode ]
        frame_type = 255 /* full_frame */
          offset_delta = 7
          locals = [ class com/fasterxml/jackson/databind/node/ArrayNode, class java/lang/Long ]
          stack = [ class com/fasterxml/jackson/databind/node/ArrayNode, class com/fasterxml/jackson/databind/JsonNode ]

  public com.fasterxml.jackson.databind.node.ArrayNode add(float);
    descriptor: (F)Lcom/fasterxml/jackson/databind/node/ArrayNode;
    flags: (0x0001) ACC_PUBLIC
    Code:
      stack=3, locals=2, args_size=2
         0: aload_0
         1: aload_0
         2: fload_1
         3: invokevirtual #70                 // Method numberNode:(F)Lcom/fasterxml/jackson/databind/node/NumericNode;
         6: invokevirtual #53                 // Method _add:(Lcom/fasterxml/jackson/databind/JsonNode;)Lcom/fasterxml/jackson/databind/node/ArrayNode;
         9: areturn
      LineNumberTable:
        line 496: 0
      LocalVariableTable:
        Start  Length  Slot  Name   Signature
            0      10     0  this   Lcom/fasterxml/jackson/databind/node/ArrayNode;
            0      10     1     v   F

  public com.fasterxml.jackson.databind.node.ArrayNode add(java.lang.Float);
    descriptor: (Ljava/lang/Float;)Lcom/fasterxml/jackson/databind/node/ArrayNode;
    flags: (0x0001) ACC_PUBLIC
    Code:
      stack=3, locals=2, args_size=2
         0: aload_0
         1: aload_1
         2: ifnonnull     12
         5: aload_0
         6: invokevirtual #42                 // Method nullNode:()Lcom/fasterxml/jackson/databind/node/NullNode;
         9: goto          20
        12: aload_0
        13: aload_1
        14: invokevirtual #71                 // Method java/lang/Float.floatValue:()F
        17: invokevirtual #70                 // Method numberNode:(F)Lcom/fasterxml/jackson/databind/node/NumericNode;
        20: invokevirtual #53                 // Method _add:(Lcom/fasterxml/jackson/databind/JsonNode;)Lcom/fasterxml/jackson/databind/node/ArrayNode;
        23: areturn
      LineNumberTable:
        line 506: 0
      LocalVariableTable:
        Start  Length  Slot  Name   Signature
            0      24     0  this   Lcom/fasterxml/jackson/databind/node/ArrayNode;
            0      24     1     v   Ljava/lang/Float;
      StackMapTable: number_of_entries = 2
        frame_type = 76 /* same_locals_1_stack_item */
          stack = [ class com/fasterxml/jackson/databind/node/ArrayNode ]
        frame_type = 255 /* full_frame */
          offset_delta = 7
          locals = [ class com/fasterxml/jackson/databind/node/ArrayNode, class java/lang/Float ]
          stack = [ class com/fasterxml/jackson/databind/node/ArrayNode, class com/fasterxml/jackson/databind/JsonNode ]

  public com.fasterxml.jackson.databind.node.ArrayNode add(double);
    descriptor: (D)Lcom/fasterxml/jackson/databind/node/ArrayNode;
    flags: (0x0001) ACC_PUBLIC
    Code:
      stack=4, locals=3, args_size=2
         0: aload_0
         1: aload_0
         2: dload_1
         3: invokevirtual #72                 // Method numberNode:(D)Lcom/fasterxml/jackson/databind/node/NumericNode;
         6: invokevirtual #53                 // Method _add:(Lcom/fasterxml/jackson/databind/JsonNode;)Lcom/fasterxml/jackson/databind/node/ArrayNode;
         9: areturn
      LineNumberTable:
        line 515: 0
      LocalVariableTable:
        Start  Length  Slot  Name   Signature
            0      10     0  this   Lcom/fasterxml/jackson/databind/node/ArrayNode;
            0      10     1     v   D

  public com.fasterxml.jackson.databind.node.ArrayNode add(java.lang.Double);
    descriptor: (Ljava/lang/Double;)Lcom/fasterxml/jackson/databind/node/ArrayNode;
    flags: (0x0001) ACC_PUBLIC
    Code:
      stack=4, locals=2, args_size=2
         0: aload_0
         1: aload_1
         2: ifnonnull     12
         5: aload_0
         6: invokevirtual #42                 // Method nullNode:()Lcom/fasterxml/jackson/databind/node/NullNode;
         9: goto          20
        12: aload_0
        13: aload_1
        14: invokevirtual #73                 // Method java/lang/Double.doubleValue:()D
        17: invokevirtual #72                 // Method numberNode:(D)Lcom/fasterxml/jackson/databind/node/NumericNode;
        20: invokevirtual #53                 // Method _add:(Lcom/fasterxml/jackson/databind/JsonNode;)Lcom/fasterxml/jackson/databind/node/ArrayNode;
        23: areturn
      LineNumberTable:
        line 525: 0
      LocalVariableTable:
        Start  Length  Slot  Name   Signature
            0      24     0  this   Lcom/fasterxml/jackson/databind/node/ArrayNode;
            0      24     1     v   Ljava/lang/Double;
      StackMapTable: number_of_entries = 2
        frame_type = 76 /* same_locals_1_stack_item */
          stack = [ class com/fasterxml/jackson/databind/node/ArrayNode ]
        frame_type = 255 /* full_frame */
          offset_delta = 7
          locals = [ class com/fasterxml/jackson/databind/node/ArrayNode, class java/lang/Double ]
          stack = [ class com/fasterxml/jackson/databind/node/ArrayNode, class com/fasterxml/jackson/databind/JsonNode ]

  public com.fasterxml.jackson.databind.node.ArrayNode add(java.math.BigDecimal);
    descriptor: (Ljava/math/BigDecimal;)Lcom/fasterxml/jackson/databind/node/ArrayNode;
    flags: (0x0001) ACC_PUBLIC
    Code:
      stack=3, locals=2, args_size=2
         0: aload_0
         1: aload_1
         2: ifnonnull     12
         5: aload_0
         6: invokevirtual #42                 // Method nullNode:()Lcom/fasterxml/jackson/databind/node/NullNode;
         9: goto          17
        12: aload_0
        13: aload_1
        14: invokevirtual #74                 // Method numberNode:(Ljava/math/BigDecimal;)Lcom/fasterxml/jackson/databind/node/ValueNode;
        17: invokevirtual #53                 // Method _add:(Lcom/fasterxml/jackson/databind/JsonNode;)Lcom/fasterxml/jackson/databind/node/ArrayNode;
        20: areturn
      LineNumberTable:
        line 534: 0
      LocalVariableTable:
        Start  Length  Slot  Name   Signature
            0      21     0  this   Lcom/fasterxml/jackson/databind/node/ArrayNode;
            0      21     1     v   Ljava/math/BigDecimal;
      StackMapTable: number_of_entries = 2
        frame_type = 76 /* same_locals_1_stack_item */
          stack = [ class com/fasterxml/jackson/databind/node/ArrayNode ]
        frame_type = 255 /* full_frame */
          offset_delta = 4
          locals = [ class com/fasterxml/jackson/databind/node/ArrayNode, class java/math/BigDecimal ]
          stack = [ class com/fasterxml/jackson/databind/node/ArrayNode, class com/fasterxml/jackson/databind/JsonNode ]

  public com.fasterxml.jackson.databind.node.ArrayNode add(java.math.BigInteger);
    descriptor: (Ljava/math/BigInteger;)Lcom/fasterxml/jackson/databind/node/ArrayNode;
    flags: (0x0001) ACC_PUBLIC
    Code:
      stack=3, locals=2, args_size=2
         0: aload_0
         1: aload_1
         2: ifnonnull     12
         5: aload_0
         6: invokevirtual #42                 // Method nullNode:()Lcom/fasterxml/jackson/databind/node/NullNode;
         9: goto          17
        12: aload_0
        13: aload_1
        14: invokevirtual #75                 // Method numberNode:(Ljava/math/BigInteger;)Lcom/fasterxml/jackson/databind/node/ValueNode;
        17: invokevirtual #53                 // Method _add:(Lcom/fasterxml/jackson/databind/JsonNode;)Lcom/fasterxml/jackson/databind/node/ArrayNode;
        20: areturn
      LineNumberTable:
        line 545: 0
      LocalVariableTable:
        Start  Length  Slot  Name   Signature
            0      21     0  this   Lcom/fasterxml/jackson/databind/node/ArrayNode;
            0      21     1     v   Ljava/math/BigInteger;
      StackMapTable: number_of_entries = 2
        frame_type = 76 /* same_locals_1_stack_item */
          stack = [ class com/fasterxml/jackson/databind/node/ArrayNode ]
        frame_type = 255 /* full_frame */
          offset_delta = 4
          locals = [ class com/fasterxml/jackson/databind/node/ArrayNode, class java/math/BigInteger ]
          stack = [ class com/fasterxml/jackson/databind/node/ArrayNode, class com/fasterxml/jackson/databind/JsonNode ]

  public com.fasterxml.jackson.databind.node.ArrayNode add(java.lang.String);
    descriptor: (Ljava/lang/String;)Lcom/fasterxml/jackson/databind/node/ArrayNode;
    flags: (0x0001) ACC_PUBLIC
    Code:
      stack=3, locals=2, args_size=2
         0: aload_0
         1: aload_1
         2: ifnonnull     12
         5: aload_0
         6: invokevirtual #42                 // Method nullNode:()Lcom/fasterxml/jackson/databind/node/NullNode;
         9: goto          17
        12: aload_0
        13: aload_1
        14: invokevirtual #76                 // Method textNode:(Ljava/lang/String;)Lcom/fasterxml/jackson/databind/node/TextNode;
        17: invokevirtual #53                 // Method _add:(Lcom/fasterxml/jackson/databind/JsonNode;)Lcom/fasterxml/jackson/databind/node/ArrayNode;
        20: areturn
      LineNumberTable:
        line 554: 0
      LocalVariableTable:
        Start  Length  Slot  Name   Signature
            0      21     0  this   Lcom/fasterxml/jackson/databind/node/ArrayNode;
            0      21     1     v   Ljava/lang/String;
      StackMapTable: number_of_entries = 2
        frame_type = 76 /* same_locals_1_stack_item */
          stack = [ class com/fasterxml/jackson/databind/node/ArrayNode ]
        frame_type = 255 /* full_frame */
          offset_delta = 4
          locals = [ class com/fasterxml/jackson/databind/node/ArrayNode, class java/lang/String ]
          stack = [ class com/fasterxml/jackson/databind/node/ArrayNode, class com/fasterxml/jackson/databind/JsonNode ]

  public com.fasterxml.jackson.databind.node.ArrayNode add(boolean);
    descriptor: (Z)Lcom/fasterxml/jackson/databind/node/ArrayNode;
    flags: (0x0001) ACC_PUBLIC
    Code:
      stack=3, locals=2, args_size=2
         0: aload_0
         1: aload_0
         2: iload_1
         3: invokevirtual #77                 // Method booleanNode:(Z)Lcom/fasterxml/jackson/databind/node/BooleanNode;
         6: invokevirtual #53                 // Method _add:(Lcom/fasterxml/jackson/databind/JsonNode;)Lcom/fasterxml/jackson/databind/node/ArrayNode;
         9: areturn
      LineNumberTable:
        line 563: 0
      LocalVariableTable:
        Start  Length  Slot  Name   Signature
            0      10     0  this   Lcom/fasterxml/jackson/databind/node/ArrayNode;
            0      10     1     v   Z

  public com.fasterxml.jackson.databind.node.ArrayNode add(java.lang.Boolean);
    descriptor: (Ljava/lang/Boolean;)Lcom/fasterxml/jackson/databind/node/ArrayNode;
    flags: (0x0001) ACC_PUBLIC
    Code:
      stack=3, locals=2, args_size=2
         0: aload_0
         1: aload_1
         2: ifnonnull     12
         5: aload_0
         6: invokevirtual #42                 // Method nullNode:()Lcom/fasterxml/jackson/databind/node/NullNode;
         9: goto          20
        12: aload_0
        13: aload_1
        14: invokevirtual #78                 // Method java/lang/Boolean.booleanValue:()Z
        17: invokevirtual #77                 // Method booleanNode:(Z)Lcom/fasterxml/jackson/databind/node/BooleanNode;
        20: invokevirtual #53                 // Method _add:(Lcom/fasterxml/jackson/databind/JsonNode;)Lcom/fasterxml/jackson/databind/node/ArrayNode;
        23: areturn
      LineNumberTable:
        line 573: 0
      LocalVariableTable:
        Start  Length  Slot  Name   Signature
            0      24     0  this   Lcom/fasterxml/jackson/databind/node/ArrayNode;
            0      24     1     v   Ljava/lang/Boolean;
      StackMapTable: number_of_entries = 2
        frame_type = 76 /* same_locals_1_stack_item */
          stack = [ class com/fasterxml/jackson/databind/node/ArrayNode ]
        frame_type = 255 /* full_frame */
          offset_delta = 7
          locals = [ class com/fasterxml/jackson/databind/node/ArrayNode, class java/lang/Boolean ]
          stack = [ class com/fasterxml/jackson/databind/node/ArrayNode, class com/fasterxml/jackson/databind/JsonNode ]

  public com.fasterxml.jackson.databind.node.ArrayNode add(byte[]);
    descriptor: ([B)Lcom/fasterxml/jackson/databind/node/ArrayNode;
    flags: (0x0001) ACC_PUBLIC
    Code:
      stack=3, locals=2, args_size=2
         0: aload_0
         1: aload_1
         2: ifnonnull     12
         5: aload_0
         6: invokevirtual #42                 // Method nullNode:()Lcom/fasterxml/jackson/databind/node/NullNode;
         9: goto          17
        12: aload_0
        13: aload_1
        14: invokevirtual #79                 // Method binaryNode:([B)Lcom/fasterxml/jackson/databind/node/BinaryNode;
        17: invokevirtual #53                 // Method _add:(Lcom/fasterxml/jackson/databind/JsonNode;)Lcom/fasterxml/jackson/databind/node/ArrayNode;
        20: areturn
      LineNumberTable:
        line 583: 0
      LocalVariableTable:
        Start  Length  Slot  Name   Signature
            0      21     0  this   Lcom/fasterxml/jackson/databind/node/ArrayNode;
            0      21     1     v   [B
      StackMapTable: number_of_entries = 2
        frame_type = 76 /* same_locals_1_stack_item */
          stack = [ class com/fasterxml/jackson/databind/node/ArrayNode ]
        frame_type = 255 /* full_frame */
          offset_delta = 4
          locals = [ class com/fasterxml/jackson/databind/node/ArrayNode, class "[B" ]
          stack = [ class com/fasterxml/jackson/databind/node/ArrayNode, class com/fasterxml/jackson/databind/JsonNode ]

  public com.fasterxml.jackson.databind.node.ArrayNode insertArray(int);
    descriptor: (I)Lcom/fasterxml/jackson/databind/node/ArrayNode;
    flags: (0x0001) ACC_PUBLIC
    Code:
      stack=3, locals=3, args_size=2
         0: aload_0
         1: invokevirtual #60                 // Method arrayNode:()Lcom/fasterxml/jackson/databind/node/ArrayNode;
         4: astore_2
         5: aload_0
         6: iload_1
         7: aload_2
         8: invokevirtual #57                 // Method _insert:(ILcom/fasterxml/jackson/databind/JsonNode;)Lcom/fasterxml/jackson/databind/node/ArrayNode;
        11: pop
        12: aload_2
        13: areturn
      LineNumberTable:
        line 596: 0
        line 597: 5
        line 598: 12
      LocalVariableTable:
        Start  Length  Slot  Name   Signature
            0      14     0  this   Lcom/fasterxml/jackson/databind/node/ArrayNode;
            0      14     1 index   I
            5       9     2     n   Lcom/fasterxml/jackson/databind/node/ArrayNode;

  public com.fasterxml.jackson.databind.node.ObjectNode insertObject(int);
    descriptor: (I)Lcom/fasterxml/jackson/databind/node/ObjectNode;
    flags: (0x0001) ACC_PUBLIC
    Code:
      stack=3, locals=3, args_size=2
         0: aload_0
         1: invokevirtual #61                 // Method objectNode:()Lcom/fasterxml/jackson/databind/node/ObjectNode;
         4: astore_2
         5: aload_0
         6: iload_1
         7: aload_2
         8: invokevirtual #57                 // Method _insert:(ILcom/fasterxml/jackson/databind/JsonNode;)Lcom/fasterxml/jackson/databind/node/ArrayNode;
        11: pop
        12: aload_2
        13: areturn
      LineNumberTable:
        line 610: 0
        line 611: 5
        line 612: 12
      LocalVariableTable:
        Start  Length  Slot  Name   Signature
            0      14     0  this   Lcom/fasterxml/jackson/databind/node/ArrayNode;
            0      14     1 index   I
            5       9     2     n   Lcom/fasterxml/jackson/databind/node/ObjectNode;

  public com.fasterxml.jackson.databind.node.ArrayNode insertNull(int);
    descriptor: (I)Lcom/fasterxml/jackson/databind/node/ArrayNode;
    flags: (0x0001) ACC_PUBLIC
    Code:
      stack=3, locals=2, args_size=2
         0: aload_0
         1: iload_1
         2: aload_0
         3: invokevirtual #42                 // Method nullNode:()Lcom/fasterxml/jackson/databind/node/NullNode;
         6: invokevirtual #57                 // Method _insert:(ILcom/fasterxml/jackson/databind/JsonNode;)Lcom/fasterxml/jackson/databind/node/ArrayNode;
         9: areturn
      LineNumberTable:
        line 622: 0
      LocalVariableTable:
        Start  Length  Slot  Name   Signature
            0      10     0  this   Lcom/fasterxml/jackson/databind/node/ArrayNode;
            0      10     1 index   I

  public com.fasterxml.jackson.databind.node.ArrayNode insertPOJO(int, java.lang.Object);
    descriptor: (ILjava/lang/Object;)Lcom/fasterxml/jackson/databind/node/ArrayNode;
    flags: (0x0001) ACC_PUBLIC
    Code:
      stack=4, locals=3, args_size=3
         0: aload_0
         1: iload_1
         2: aload_2
         3: ifnonnull     13
         6: aload_0
         7: invokevirtual #42                 // Method nullNode:()Lcom/fasterxml/jackson/databind/node/NullNode;
        10: goto          18
        13: aload_0
        14: aload_2
        15: invokevirtual #62                 // Method pojoNode:(Ljava/lang/Object;)Lcom/fasterxml/jackson/databind/node/ValueNode;
        18: invokevirtual #57                 // Method _insert:(ILcom/fasterxml/jackson/databind/JsonNode;)Lcom/fasterxml/jackson/databind/node/ArrayNode;
        21: areturn
      LineNumberTable:
        line 632: 0
      LocalVariableTable:
        Start  Length  Slot  Name   Signature
            0      22     0  this   Lcom/fasterxml/jackson/databind/node/ArrayNode;
            0      22     1 index   I
            0      22     2  pojo   Ljava/lang/Object;
      StackMapTable: number_of_entries = 2
        frame_type = 255 /* full_frame */
          offset_delta = 13
          locals = [ class com/fasterxml/jackson/databind/node/ArrayNode, int, class java/lang/Object ]
          stack = [ class com/fasterxml/jackson/databind/node/ArrayNode, int ]
        frame_type = 255 /* full_frame */
          offset_delta = 4
          locals = [ class com/fasterxml/jackson/databind/node/ArrayNode, int, class java/lang/Object ]
          stack = [ class com/fasterxml/jackson/databind/node/ArrayNode, int, class com/fasterxml/jackson/databind/JsonNode ]

  public com.fasterxml.jackson.databind.node.ArrayNode insertRawValue(int, com.fasterxml.jackson.databind.util.RawValue);
    descriptor: (ILcom/fasterxml/jackson/databind/util/RawValue;)Lcom/fasterxml/jackson/databind/node/ArrayNode;
    flags: (0x0001) ACC_PUBLIC
    Code:
      stack=4, locals=3, args_size=3
         0: aload_0
         1: iload_1
         2: aload_2
         3: ifnonnull     13
         6: aload_0
         7: invokevirtual #42                 // Method nullNode:()Lcom/fasterxml/jackson/databind/node/NullNode;
        10: goto          18
        13: aload_0
        14: aload_2
        15: invokevirtual #63                 // Method rawValueNode:(Lcom/fasterxml/jackson/databind/util/RawValue;)Lcom/fasterxml/jackson/databind/node/ValueNode;
        18: invokevirtual #57                 // Method _insert:(ILcom/fasterxml/jackson/databind/JsonNode;)Lcom/fasterxml/jackson/databind/node/ArrayNode;
        21: areturn
      LineNumberTable:
        line 641: 0
      LocalVariableTable:
        Start  Length  Slot  Name   Signature
            0      22     0  this   Lcom/fasterxml/jackson/databind/node/ArrayNode;
            0      22     1 index   I
            0      22     2   raw   Lcom/fasterxml/jackson/databind/util/RawValue;
      StackMapTable: number_of_entries = 2
        frame_type = 255 /* full_frame */
          offset_delta = 13
          locals = [ class com/fasterxml/jackson/databind/node/ArrayNode, int, class com/fasterxml/jackson/databind/util/RawValue ]
          stack = [ class com/fasterxml/jackson/databind/node/ArrayNode, int ]
        frame_type = 255 /* full_frame */
          offset_delta = 4
          locals = [ class com/fasterxml/jackson/databind/node/ArrayNode, int, class com/fasterxml/jackson/databind/util/RawValue ]
          stack = [ class com/fasterxml/jackson/databind/node/ArrayNode, int, class com/fasterxml/jackson/databind/JsonNode ]

  public com.fasterxml.jackson.databind.node.ArrayNode insert(int, short);
    descriptor: (IS)Lcom/fasterxml/jackson/databind/node/ArrayNode;
    flags: (0x0001) ACC_PUBLIC
    Code:
      stack=4, locals=3, args_size=3
         0: aload_0
         1: iload_1
         2: aload_0
         3: iload_2
         4: invokevirtual #64                 // Method numberNode:(S)Lcom/fasterxml/jackson/databind/node/NumericNode;
         7: invokevirtual #57                 // Method _insert:(ILcom/fasterxml/jackson/databind/JsonNode;)Lcom/fasterxml/jackson/databind/node/ArrayNode;
        10: areturn
      LineNumberTable:
        line 653: 0
      LocalVariableTable:
        Start  Length  Slot  Name   Signature
            0      11     0  this   Lcom/fasterxml/jackson/databind/node/ArrayNode;
            0      11     1 index   I
            0      11     2     v   S

  public com.fasterxml.jackson.databind.node.ArrayNode insert(int, java.lang.Short);
    descriptor: (ILjava/lang/Short;)Lcom/fasterxml/jackson/databind/node/ArrayNode;
    flags: (0x0001) ACC_PUBLIC
    Code:
      stack=4, locals=3, args_size=3
         0: aload_0
         1: iload_1
         2: aload_2
         3: ifnonnull     13
         6: aload_0
         7: invokevirtual #42                 // Method nullNode:()Lcom/fasterxml/jackson/databind/node/NullNode;
        10: goto          21
        13: aload_0
        14: aload_2
        15: invokevirtual #65                 // Method java/lang/Short.shortValue:()S
        18: invokevirtual #64                 // Method numberNode:(S)Lcom/fasterxml/jackson/databind/node/NumericNode;
        21: invokevirtual #57                 // Method _insert:(ILcom/fasterxml/jackson/databind/JsonNode;)Lcom/fasterxml/jackson/databind/node/ArrayNode;
        24: areturn
      LineNumberTable:
        line 665: 0
      LocalVariableTable:
        Start  Length  Slot  Name   Signature
            0      25     0  this   Lcom/fasterxml/jackson/databind/node/ArrayNode;
            0      25     1 index   I
            0      25     2 value   Ljava/lang/Short;
      StackMapTable: number_of_entries = 2
        frame_type = 255 /* full_frame */
          offset_delta = 13
          locals = [ class com/fasterxml/jackson/databind/node/ArrayNode, int, class java/lang/Short ]
          stack = [ class com/fasterxml/jackson/databind/node/ArrayNode, int ]
        frame_type = 255 /* full_frame */
          offset_delta = 7
          locals = [ class com/fasterxml/jackson/databind/node/ArrayNode, int, class java/lang/Short ]
          stack = [ class com/fasterxml/jackson/databind/node/ArrayNode, int, class com/fasterxml/jackson/databind/JsonNode ]

  public com.fasterxml.jackson.databind.node.ArrayNode insert(int, int);
    descriptor: (II)Lcom/fasterxml/jackson/databind/node/ArrayNode;
    flags: (0x0001) ACC_PUBLIC
    Code:
      stack=4, locals=3, args_size=3
         0: aload_0
         1: iload_1
         2: aload_0
         3: iload_2
         4: invokevirtual #66                 // Method numberNode:(I)Lcom/fasterxml/jackson/databind/node/NumericNode;
         7: invokevirtual #57                 // Method _insert:(ILcom/fasterxml/jackson/databind/JsonNode;)Lcom/fasterxml/jackson/databind/node/ArrayNode;
        10: areturn
      LineNumberTable:
        line 675: 0
      LocalVariableTable:
        Start  Length  Slot  Name   Signature
            0      11     0  this   Lcom/fasterxml/jackson/databind/node/ArrayNode;
            0      11     1 index   I
            0      11     2     v   I

  public com.fasterxml.jackson.databind.node.ArrayNode insert(int, java.lang.Integer);
    descriptor: (ILjava/lang/Integer;)Lcom/fasterxml/jackson/databind/node/ArrayNode;
    flags: (0x0001) ACC_PUBLIC
    Code:
      stack=4, locals=3, args_size=3
         0: aload_0
         1: iload_1
         2: aload_2
         3: ifnonnull     13
         6: aload_0
         7: invokevirtual #42                 // Method nullNode:()Lcom/fasterxml/jackson/databind/node/NullNode;
        10: goto          21
        13: aload_0
        14: aload_2
        15: invokevirtual #67                 // Method java/lang/Integer.intValue:()I
        18: invokevirtual #66                 // Method numberNode:(I)Lcom/fasterxml/jackson/databind/node/NumericNode;
        21: invokevirtual #57                 // Method _insert:(ILcom/fasterxml/jackson/databind/JsonNode;)Lcom/fasterxml/jackson/databind/node/ArrayNode;
        24: areturn
      LineNumberTable:
        line 685: 0
      LocalVariableTable:
        Start  Length  Slot  Name   Signature
            0      25     0  this   Lcom/fasterxml/jackson/databind/node/ArrayNode;
            0      25     1 index   I
            0      25     2     v   Ljava/lang/Integer;
      StackMapTable: number_of_entries = 2
        frame_type = 255 /* full_frame */
          offset_delta = 13
          locals = [ class com/fasterxml/jackson/databind/node/ArrayNode, int, class java/lang/Integer ]
          stack = [ class com/fasterxml/jackson/databind/node/ArrayNode, int ]
        frame_type = 255 /* full_frame */
          offset_delta = 7
          locals = [ class com/fasterxml/jackson/databind/node/ArrayNode, int, class java/lang/Integer ]
          stack = [ class com/fasterxml/jackson/databind/node/ArrayNode, int, class com/fasterxml/jackson/databind/JsonNode ]

  public com.fasterxml.jackson.databind.node.ArrayNode insert(int, long);
    descriptor: (IJ)Lcom/fasterxml/jackson/databind/node/ArrayNode;
    flags: (0x0001) ACC_PUBLIC
    Code:
      stack=5, locals=4, args_size=3
         0: aload_0
         1: iload_1
         2: aload_0
         3: lload_2
         4: invokevirtual #68                 // Method numberNode:(J)Lcom/fasterxml/jackson/databind/node/NumericNode;
         7: invokevirtual #57                 // Method _insert:(ILcom/fasterxml/jackson/databind/JsonNode;)Lcom/fasterxml/jackson/databind/node/ArrayNode;
        10: areturn
      LineNumberTable:
        line 695: 0
      LocalVariableTable:
        Start  Length  Slot  Name   Signature
            0      11     0  this   Lcom/fasterxml/jackson/databind/node/ArrayNode;
            0      11     1 index   I
            0      11     2     v   J

  public com.fasterxml.jackson.databind.node.ArrayNode insert(int, java.lang.Long);
    descriptor: (ILjava/lang/Long;)Lcom/fasterxml/jackson/databind/node/ArrayNode;
    flags: (0x0001) ACC_PUBLIC
    Code:
      stack=5, locals=3, args_size=3
         0: aload_0
         1: iload_1
         2: aload_2
         3: ifnonnull     13
         6: aload_0
         7: invokevirtual #42                 // Method nullNode:()Lcom/fasterxml/jackson/databind/node/NullNode;
        10: goto          21
        13: aload_0
        14: aload_2
        15: invokevirtual #69                 // Method java/lang/Long.longValue:()J
        18: invokevirtual #68                 // Method numberNode:(J)Lcom/fasterxml/jackson/databind/node/NumericNode;
        21: invokevirtual #57                 // Method _insert:(ILcom/fasterxml/jackson/databind/JsonNode;)Lcom/fasterxml/jackson/databind/node/ArrayNode;
        24: areturn
      LineNumberTable:
        line 705: 0
      LocalVariableTable:
        Start  Length  Slot  Name   Signature
            0      25     0  this   Lcom/fasterxml/jackson/databind/node/ArrayNode;
            0      25     1 index   I
            0      25     2     v   Ljava/lang/Long;
      StackMapTable: number_of_entries = 2
        frame_type = 255 /* full_frame */
          offset_delta = 13
          locals = [ class com/fasterxml/jackson/databind/node/ArrayNode, int, class java/lang/Long ]
          stack = [ class com/fasterxml/jackson/databind/node/ArrayNode, int ]
        frame_type = 255 /* full_frame */
          offset_delta = 7
          locals = [ class com/fasterxml/jackson/databind/node/ArrayNode, int, class java/lang/Long ]
          stack = [ class com/fasterxml/jackson/databind/node/ArrayNode, int, class com/fasterxml/jackson/databind/JsonNode ]

  public com.fasterxml.jackson.databind.node.ArrayNode insert(int, float);
    descriptor: (IF)Lcom/fasterxml/jackson/databind/node/ArrayNode;
    flags: (0x0001) ACC_PUBLIC
    Code:
      stack=4, locals=3, args_size=3
         0: aload_0
         1: iload_1
         2: aload_0
         3: fload_2
         4: invokevirtual #70                 // Method numberNode:(F)Lcom/fasterxml/jackson/databind/node/NumericNode;
         7: invokevirtual #57                 // Method _insert:(ILcom/fasterxml/jackson/databind/JsonNode;)Lcom/fasterxml/jackson/databind/node/ArrayNode;
        10: areturn
      LineNumberTable:
        line 715: 0
      LocalVariableTable:
        Start  Length  Slot  Name   Signature
            0      11     0  this   Lcom/fasterxml/jackson/databind/node/ArrayNode;
            0      11     1 index   I
            0      11     2     v   F

  public com.fasterxml.jackson.databind.node.ArrayNode insert(int, java.lang.Float);
    descriptor: (ILjava/lang/Float;)Lcom/fasterxml/jackson/databind/node/ArrayNode;
    flags: (0x0001) ACC_PUBLIC
    Code:
      stack=4, locals=3, args_size=3
         0: aload_0
         1: iload_1
         2: aload_2
         3: ifnonnull     13
         6: aload_0
         7: invokevirtual #42                 // Method nullNode:()Lcom/fasterxml/jackson/databind/node/NullNode;
        10: goto          21
        13: aload_0
        14: aload_2
        15: invokevirtual #71                 // Method java/lang/Float.floatValue:()F
        18: invokevirtual #70                 // Method numberNode:(F)Lcom/fasterxml/jackson/databind/node/NumericNode;
        21: invokevirtual #57                 // Method _insert:(ILcom/fasterxml/jackson/databind/JsonNode;)Lcom/fasterxml/jackson/databind/node/ArrayNode;
        24: areturn
      LineNumberTable:
        line 725: 0
      LocalVariableTable:
        Start  Length  Slot  Name   Signature
            0      25     0  this   Lcom/fasterxml/jackson/databind/node/ArrayNode;
            0      25     1 index   I
            0      25     2     v   Ljava/lang/Float;
      StackMapTable: number_of_entries = 2
        frame_type = 255 /* full_frame */
          offset_delta = 13
          locals = [ class com/fasterxml/jackson/databind/node/ArrayNode, int, class java/lang/Float ]
          stack = [ class com/fasterxml/jackson/databind/node/ArrayNode, int ]
        frame_type = 255 /* full_frame */
          offset_delta = 7
          locals = [ class com/fasterxml/jackson/databind/node/ArrayNode, int, class java/lang/Float ]
          stack = [ class com/fasterxml/jackson/databind/node/ArrayNode, int, class com/fasterxml/jackson/databind/JsonNode ]

  public com.fasterxml.jackson.databind.node.ArrayNode insert(int, double);
    descriptor: (ID)Lcom/fasterxml/jackson/databind/node/ArrayNode;
    flags: (0x0001) ACC_PUBLIC
    Code:
      stack=5, locals=4, args_size=3
         0: aload_0
         1: iload_1
         2: aload_0
         3: dload_2
         4: invokevirtual #72                 // Method numberNode:(D)Lcom/fasterxml/jackson/databind/node/NumericNode;
         7: invokevirtual #57                 // Method _insert:(ILcom/fasterxml/jackson/databind/JsonNode;)Lcom/fasterxml/jackson/databind/node/ArrayNode;
        10: areturn
      LineNumberTable:
        line 735: 0
      LocalVariableTable:
        Start  Length  Slot  Name   Signature
            0      11     0  this   Lcom/fasterxml/jackson/databind/node/ArrayNode;
            0      11     1 index   I
            0      11     2     v   D

  public com.fasterxml.jackson.databind.node.ArrayNode insert(int, java.lang.Double);
    descriptor: (ILjava/lang/Double;)Lcom/fasterxml/jackson/databind/node/ArrayNode;
    flags: (0x0001) ACC_PUBLIC
    Code:
      stack=5, locals=3, args_size=3
         0: aload_0
         1: iload_1
         2: aload_2
         3: ifnonnull     13
         6: aload_0
         7: invokevirtual #42                 // Method nullNode:()Lcom/fasterxml/jackson/databind/node/NullNode;
        10: goto          21
        13: aload_0
        14: aload_2
        15: invokevirtual #73                 // Method java/lang/Double.doubleValue:()D
        18: invokevirtual #72                 // Method numberNode:(D)Lcom/fasterxml/jackson/databind/node/NumericNode;
        21: invokevirtual #57                 // Method _insert:(ILcom/fasterxml/jackson/databind/JsonNode;)Lcom/fasterxml/jackson/databind/node/ArrayNode;
        24: areturn
      LineNumberTable:
        line 745: 0
      LocalVariableTable:
        Start  Length  Slot  Name   Signature
            0      25     0  this   Lcom/fasterxml/jackson/databind/node/ArrayNode;
            0      25     1 index   I
            0      25     2     v   Ljava/lang/Double;
      StackMapTable: number_of_entries = 2
        frame_type = 255 /* full_frame */
          offset_delta = 13
          locals = [ class com/fasterxml/jackson/databind/node/ArrayNode, int, class java/lang/Double ]
          stack = [ class com/fasterxml/jackson/databind/node/ArrayNode, int ]
        frame_type = 255 /* full_frame */
          offset_delta = 7
          locals = [ class com/fasterxml/jackson/databind/node/ArrayNode, int, class java/lang/Double ]
          stack = [ class com/fasterxml/jackson/databind/node/ArrayNode, int, class com/fasterxml/jackson/databind/JsonNode ]

  public com.fasterxml.jackson.databind.node.ArrayNode insert(int, java.math.BigDecimal);
    descriptor: (ILjava/math/BigDecimal;)Lcom/fasterxml/jackson/databind/node/ArrayNode;
    flags: (0x0001) ACC_PUBLIC
    Code:
      stack=4, locals=3, args_size=3
         0: aload_0
         1: iload_1
         2: aload_2
         3: ifnonnull     13
         6: aload_0
         7: invokevirtual #42                 // Method nullNode:()Lcom/fasterxml/jackson/databind/node/NullNode;
        10: goto          18
        13: aload_0
        14: aload_2
        15: invokevirtual #74                 // Method numberNode:(Ljava/math/BigDecimal;)Lcom/fasterxml/jackson/databind/node/ValueNode;
        18: invokevirtual #57                 // Method _insert:(ILcom/fasterxml/jackson/databind/JsonNode;)Lcom/fasterxml/jackson/databind/node/ArrayNode;
        21: areturn
      LineNumberTable:
        line 755: 0
      LocalVariableTable:
        Start  Length  Slot  Name   Signature
            0      22     0  this   Lcom/fasterxml/jackson/databind/node/ArrayNode;
            0      22     1 index   I
            0      22     2     v   Ljava/math/BigDecimal;
      StackMapTable: number_of_entries = 2
        frame_type = 255 /* full_frame */
          offset_delta = 13
          locals = [ class com/fasterxml/jackson/databind/node/ArrayNode, int, class java/math/BigDecimal ]
          stack = [ class com/fasterxml/jackson/databind/node/ArrayNode, int ]
        frame_type = 255 /* full_frame */
          offset_delta = 4
          locals = [ class com/fasterxml/jackson/databind/node/ArrayNode, int, class java/math/BigDecimal ]
          stack = [ class com/fasterxml/jackson/databind/node/ArrayNode, int, class com/fasterxml/jackson/databind/JsonNode ]

  public com.fasterxml.jackson.databind.node.ArrayNode insert(int, java.math.BigInteger);
    descriptor: (ILjava/math/BigInteger;)Lcom/fasterxml/jackson/databind/node/ArrayNode;
    flags: (0x0001) ACC_PUBLIC
    Code:
      stack=4, locals=3, args_size=3
         0: aload_0
         1: iload_1
         2: aload_2
         3: ifnonnull     13
         6: aload_0
         7: invokevirtual #42                 // Method nullNode:()Lcom/fasterxml/jackson/databind/node/NullNode;
        10: goto          18
        13: aload_0
        14: aload_2
        15: invokevirtual #75                 // Method numberNode:(Ljava/math/BigInteger;)Lcom/fasterxml/jackson/databind/node/ValueNode;
        18: invokevirtual #57                 // Method _insert:(ILcom/fasterxml/jackson/databind/JsonNode;)Lcom/fasterxml/jackson/databind/node/ArrayNode;
        21: areturn
      LineNumberTable:
        line 767: 0
      LocalVariableTable:
        Start  Length  Slot  Name   Signature
            0      22     0  this   Lcom/fasterxml/jackson/databind/node/ArrayNode;
            0      22     1 index   I
            0      22     2     v   Ljava/math/BigInteger;
      StackMapTable: number_of_entries = 2
        frame_type = 255 /* full_frame */
          offset_delta = 13
          locals = [ class com/fasterxml/jackson/databind/node/ArrayNode, int, class java/math/BigInteger ]
          stack = [ class com/fasterxml/jackson/databind/node/ArrayNode, int ]
        frame_type = 255 /* full_frame */
          offset_delta = 4
          locals = [ class com/fasterxml/jackson/databind/node/ArrayNode, int, class java/math/BigInteger ]
          stack = [ class com/fasterxml/jackson/databind/node/ArrayNode, int, class com/fasterxml/jackson/databind/JsonNode ]

  public com.fasterxml.jackson.databind.node.ArrayNode insert(int, java.lang.String);
    descriptor: (ILjava/lang/String;)Lcom/fasterxml/jackson/databind/node/ArrayNode;
    flags: (0x0001) ACC_PUBLIC
    Code:
      stack=4, locals=3, args_size=3
         0: aload_0
         1: iload_1
         2: aload_2
         3: ifnonnull     13
         6: aload_0
         7: invokevirtual #42                 // Method nullNode:()Lcom/fasterxml/jackson/databind/node/NullNode;
        10: goto          18
        13: aload_0
        14: aload_2
        15: invokevirtual #76                 // Method textNode:(Ljava/lang/String;)Lcom/fasterxml/jackson/databind/node/TextNode;
        18: invokevirtual #57                 // Method _insert:(ILcom/fasterxml/jackson/databind/JsonNode;)Lcom/fasterxml/jackson/databind/node/ArrayNode;
        21: areturn
      LineNumberTable:
        line 777: 0
      LocalVariableTable:
        Start  Length  Slot  Name   Signature
            0      22     0  this   Lcom/fasterxml/jackson/databind/node/ArrayNode;
            0      22     1 index   I
            0      22     2     v   Ljava/lang/String;
      StackMapTable: number_of_entries = 2
        frame_type = 255 /* full_frame */
          offset_delta = 13
          locals = [ class com/fasterxml/jackson/databind/node/ArrayNode, int, class java/lang/String ]
          stack = [ class com/fasterxml/jackson/databind/node/ArrayNode, int ]
        frame_type = 255 /* full_frame */
          offset_delta = 4
          locals = [ class com/fasterxml/jackson/databind/node/ArrayNode, int, class java/lang/String ]
          stack = [ class com/fasterxml/jackson/databind/node/ArrayNode, int, class com/fasterxml/jackson/databind/JsonNode ]

  public com.fasterxml.jackson.databind.node.ArrayNode insert(int, boolean);
    descriptor: (IZ)Lcom/fasterxml/jackson/databind/node/ArrayNode;
    flags: (0x0001) ACC_PUBLIC
    Code:
      stack=4, locals=3, args_size=3
         0: aload_0
         1: iload_1
         2: aload_0
         3: iload_2
         4: invokevirtual #77                 // Method booleanNode:(Z)Lcom/fasterxml/jackson/databind/node/BooleanNode;
         7: invokevirtual #57                 // Method _insert:(ILcom/fasterxml/jackson/databind/JsonNode;)Lcom/fasterxml/jackson/databind/node/ArrayNode;
        10: areturn
      LineNumberTable:
        line 787: 0
      LocalVariableTable:
        Start  Length  Slot  Name   Signature
            0      11     0  this   Lcom/fasterxml/jackson/databind/node/ArrayNode;
            0      11     1 index   I
            0      11     2     v   Z

  public com.fasterxml.jackson.databind.node.ArrayNode insert(int, java.lang.Boolean);
    descriptor: (ILjava/lang/Boolean;)Lcom/fasterxml/jackson/databind/node/ArrayNode;
    flags: (0x0001) ACC_PUBLIC
    Code:
      stack=4, locals=3, args_size=3
         0: aload_2
         1: ifnonnull     10
         4: aload_0
         5: iload_1
         6: invokevirtual #80                 // Method insertNull:(I)Lcom/fasterxml/jackson/databind/node/ArrayNode;
         9: areturn
        10: aload_0
        11: iload_1
        12: aload_0
        13: aload_2
        14: invokevirtual #78                 // Method java/lang/Boolean.booleanValue:()Z
        17: invokevirtual #77                 // Method booleanNode:(Z)Lcom/fasterxml/jackson/databind/node/BooleanNode;
        20: invokevirtual #57                 // Method _insert:(ILcom/fasterxml/jackson/databind/JsonNode;)Lcom/fasterxml/jackson/databind/node/ArrayNode;
        23: areturn
      LineNumberTable:
        line 797: 0
        line 798: 4
        line 800: 10
      LocalVariableTable:
        Start  Length  Slot  Name   Signature
            0      24     0  this   Lcom/fasterxml/jackson/databind/node/ArrayNode;
            0      24     1 index   I
            0      24     2 value   Ljava/lang/Boolean;
      StackMapTable: number_of_entries = 1
        frame_type = 10 /* same */

  public com.fasterxml.jackson.databind.node.ArrayNode insert(int, byte[]);
    descriptor: (I[B)Lcom/fasterxml/jackson/databind/node/ArrayNode;
    flags: (0x0001) ACC_PUBLIC
    Code:
      stack=4, locals=3, args_size=3
         0: aload_2
         1: ifnonnull     10
         4: aload_0
         5: iload_1
         6: invokevirtual #80                 // Method insertNull:(I)Lcom/fasterxml/jackson/databind/node/ArrayNode;
         9: areturn
        10: aload_0
        11: iload_1
        12: aload_0
        13: aload_2
        14: invokevirtual #79                 // Method binaryNode:([B)Lcom/fasterxml/jackson/databind/node/BinaryNode;
        17: invokevirtual #57                 // Method _insert:(ILcom/fasterxml/jackson/databind/JsonNode;)Lcom/fasterxml/jackson/databind/node/ArrayNode;
        20: areturn
      LineNumberTable:
        line 811: 0
        line 812: 4
        line 814: 10
      LocalVariableTable:
        Start  Length  Slot  Name   Signature
            0      21     0  this   Lcom/fasterxml/jackson/databind/node/ArrayNode;
            0      21     1 index   I
            0      21     2     v   [B
      StackMapTable: number_of_entries = 1
        frame_type = 10 /* same */

  public com.fasterxml.jackson.databind.node.ArrayNode setNull(int);
    descriptor: (I)Lcom/fasterxml/jackson/databind/node/ArrayNode;
    flags: (0x0001) ACC_PUBLIC
    Code:
      stack=3, locals=2, args_size=2
         0: aload_0
         1: iload_1
         2: aload_0
         3: invokevirtual #42                 // Method nullNode:()Lcom/fasterxml/jackson/databind/node/NullNode;
         6: invokevirtual #81                 // Method _set:(ILcom/fasterxml/jackson/databind/JsonNode;)Lcom/fasterxml/jackson/databind/node/ArrayNode;
         9: areturn
      LineNumberTable:
        line 823: 0
      LocalVariableTable:
        Start  Length  Slot  Name   Signature
            0      10     0  this   Lcom/fasterxml/jackson/databind/node/ArrayNode;
            0      10     1 index   I

  public com.fasterxml.jackson.databind.node.ArrayNode setPOJO(int, java.lang.Object);
    descriptor: (ILjava/lang/Object;)Lcom/fasterxml/jackson/databind/node/ArrayNode;
    flags: (0x0001) ACC_PUBLIC
    Code:
      stack=4, locals=3, args_size=3
         0: aload_0
         1: iload_1
         2: aload_2
         3: ifnonnull     13
         6: aload_0
         7: invokevirtual #42                 // Method nullNode:()Lcom/fasterxml/jackson/databind/node/NullNode;
        10: goto          18
        13: aload_0
        14: aload_2
        15: invokevirtual #62                 // Method pojoNode:(Ljava/lang/Object;)Lcom/fasterxml/jackson/databind/node/ValueNode;
        18: invokevirtual #81                 // Method _set:(ILcom/fasterxml/jackson/databind/JsonNode;)Lcom/fasterxml/jackson/databind/node/ArrayNode;
        21: areturn
      LineNumberTable:
        line 832: 0
      LocalVariableTable:
        Start  Length  Slot  Name   Signature
            0      22     0  this   Lcom/fasterxml/jackson/databind/node/ArrayNode;
            0      22     1 index   I
            0      22     2  pojo   Ljava/lang/Object;
      StackMapTable: number_of_entries = 2
        frame_type = 255 /* full_frame */
          offset_delta = 13
          locals = [ class com/fasterxml/jackson/databind/node/ArrayNode, int, class java/lang/Object ]
          stack = [ class com/fasterxml/jackson/databind/node/ArrayNode, int ]
        frame_type = 255 /* full_frame */
          offset_delta = 4
          locals = [ class com/fasterxml/jackson/databind/node/ArrayNode, int, class java/lang/Object ]
          stack = [ class com/fasterxml/jackson/databind/node/ArrayNode, int, class com/fasterxml/jackson/databind/JsonNode ]

  public com.fasterxml.jackson.databind.node.ArrayNode setRawValue(int, com.fasterxml.jackson.databind.util.RawValue);
    descriptor: (ILcom/fasterxml/jackson/databind/util/RawValue;)Lcom/fasterxml/jackson/databind/node/ArrayNode;
    flags: (0x0001) ACC_PUBLIC
    Code:
      stack=4, locals=3, args_size=3
         0: aload_0
         1: iload_1
         2: aload_2
         3: ifnonnull     13
         6: aload_0
         7: invokevirtual #42                 // Method nullNode:()Lcom/fasterxml/jackson/databind/node/NullNode;
        10: goto          18
        13: aload_0
        14: aload_2
        15: invokevirtual #63                 // Method rawValueNode:(Lcom/fasterxml/jackson/databind/util/RawValue;)Lcom/fasterxml/jackson/databind/node/ValueNode;
        18: invokevirtual #81                 // Method _set:(ILcom/fasterxml/jackson/databind/JsonNode;)Lcom/fasterxml/jackson/databind/node/ArrayNode;
        21: areturn
      LineNumberTable:
        line 841: 0
      LocalVariableTable:
        Start  Length  Slot  Name   Signature
            0      22     0  this   Lcom/fasterxml/jackson/databind/node/ArrayNode;
            0      22     1 index   I
            0      22     2   raw   Lcom/fasterxml/jackson/databind/util/RawValue;
      StackMapTable: number_of_entries = 2
        frame_type = 255 /* full_frame */
          offset_delta = 13
          locals = [ class com/fasterxml/jackson/databind/node/ArrayNode, int, class com/fasterxml/jackson/databind/util/RawValue ]
          stack = [ class com/fasterxml/jackson/databind/node/ArrayNode, int ]
        frame_type = 255 /* full_frame */
          offset_delta = 4
          locals = [ class com/fasterxml/jackson/databind/node/ArrayNode, int, class com/fasterxml/jackson/databind/util/RawValue ]
          stack = [ class com/fasterxml/jackson/databind/node/ArrayNode, int, class com/fasterxml/jackson/databind/JsonNode ]

  public com.fasterxml.jackson.databind.node.ArrayNode set(int, short);
    descriptor: (IS)Lcom/fasterxml/jackson/databind/node/ArrayNode;
    flags: (0x0001) ACC_PUBLIC
    Code:
      stack=4, locals=3, args_size=3
         0: aload_0
         1: iload_1
         2: aload_0
         3: iload_2
         4: invokevirtual #64                 // Method numberNode:(S)Lcom/fasterxml/jackson/databind/node/NumericNode;
         7: invokevirtual #81                 // Method _set:(ILcom/fasterxml/jackson/databind/JsonNode;)Lcom/fasterxml/jackson/databind/node/ArrayNode;
        10: areturn
      LineNumberTable:
        line 850: 0
      LocalVariableTable:
        Start  Length  Slot  Name   Signature
            0      11     0  this   Lcom/fasterxml/jackson/databind/node/ArrayNode;
            0      11     1 index   I
            0      11     2     v   S

  public com.fasterxml.jackson.databind.node.ArrayNode set(int, java.lang.Short);
    descriptor: (ILjava/lang/Short;)Lcom/fasterxml/jackson/databind/node/ArrayNode;
    flags: (0x0001) ACC_PUBLIC
    Code:
      stack=4, locals=3, args_size=3
         0: aload_0
         1: iload_1
         2: aload_2
         3: ifnonnull     13
         6: aload_0
         7: invokevirtual #42                 // Method nullNode:()Lcom/fasterxml/jackson/databind/node/NullNode;
        10: goto          21
        13: aload_0
        14: aload_2
        15: invokevirtual #65                 // Method java/lang/Short.shortValue:()S
        18: invokevirtual #64                 // Method numberNode:(S)Lcom/fasterxml/jackson/databind/node/NumericNode;
        21: invokevirtual #81                 // Method _set:(ILcom/fasterxml/jackson/databind/JsonNode;)Lcom/fasterxml/jackson/databind/node/ArrayNode;
        24: areturn
      LineNumberTable:
        line 862: 0
      LocalVariableTable:
        Start  Length  Slot  Name   Signature
            0      25     0  this   Lcom/fasterxml/jackson/databind/node/ArrayNode;
            0      25     1 index   I
            0      25     2     v   Ljava/lang/Short;
      StackMapTable: number_of_entries = 2
        frame_type = 255 /* full_frame */
          offset_delta = 13
          locals = [ class com/fasterxml/jackson/databind/node/ArrayNode, int, class java/lang/Short ]
          stack = [ class com/fasterxml/jackson/databind/node/ArrayNode, int ]
        frame_type = 255 /* full_frame */
          offset_delta = 7
          locals = [ class com/fasterxml/jackson/databind/node/ArrayNode, int, class java/lang/Short ]
          stack = [ class com/fasterxml/jackson/databind/node/ArrayNode, int, class com/fasterxml/jackson/databind/JsonNode ]

  public com.fasterxml.jackson.databind.node.ArrayNode set(int, int);
    descriptor: (II)Lcom/fasterxml/jackson/databind/node/ArrayNode;
    flags: (0x0001) ACC_PUBLIC
    Code:
      stack=4, locals=3, args_size=3
         0: aload_0
         1: iload_1
         2: aload_0
         3: iload_2
         4: invokevirtual #66                 // Method numberNode:(I)Lcom/fasterxml/jackson/databind/node/NumericNode;
         7: invokevirtual #81                 // Method _set:(ILcom/fasterxml/jackson/databind/JsonNode;)Lcom/fasterxml/jackson/databind/node/ArrayNode;
        10: areturn
      LineNumberTable:
        line 871: 0
      LocalVariableTable:
        Start  Length  Slot  Name   Signature
            0      11     0  this   Lcom/fasterxml/jackson/databind/node/ArrayNode;
            0      11     1 index   I
            0      11     2     v   I

  public com.fasterxml.jackson.databind.node.ArrayNode set(int, java.lang.Integer);
    descriptor: (ILjava/lang/Integer;)Lcom/fasterxml/jackson/databind/node/ArrayNode;
    flags: (0x0001) ACC_PUBLIC
    Code:
      stack=4, locals=3, args_size=3
         0: aload_0
         1: iload_1
         2: aload_2
         3: ifnonnull     13
         6: aload_0
         7: invokevirtual #42                 // Method nullNode:()Lcom/fasterxml/jackson/databind/node/NullNode;
        10: goto          21
        13: aload_0
        14: aload_2
        15: invokevirtual #67                 // Method java/lang/Integer.intValue:()I
        18: invokevirtual #66                 // Method numberNode:(I)Lcom/fasterxml/jackson/databind/node/NumericNode;
        21: invokevirtual #81                 // Method _set:(ILcom/fasterxml/jackson/databind/JsonNode;)Lcom/fasterxml/jackson/databind/node/ArrayNode;
        24: areturn
      LineNumberTable:
        line 883: 0
      LocalVariableTable:
        Start  Length  Slot  Name   Signature
            0      25     0  this   Lcom/fasterxml/jackson/databind/node/ArrayNode;
            0      25     1 index   I
            0      25     2     v   Ljava/lang/Integer;
      StackMapTable: number_of_entries = 2
        frame_type = 255 /* full_frame */
          offset_delta = 13
          locals = [ class com/fasterxml/jackson/databind/node/ArrayNode, int, class java/lang/Integer ]
          stack = [ class com/fasterxml/jackson/databind/node/ArrayNode, int ]
        frame_type = 255 /* full_frame */
          offset_delta = 7
          locals = [ class com/fasterxml/jackson/databind/node/ArrayNode, int, class java/lang/Integer ]
          stack = [ class com/fasterxml/jackson/databind/node/ArrayNode, int, class com/fasterxml/jackson/databind/JsonNode ]

  public com.fasterxml.jackson.databind.node.ArrayNode set(int, long);
    descriptor: (IJ)Lcom/fasterxml/jackson/databind/node/ArrayNode;
    flags: (0x0001) ACC_PUBLIC
    Code:
      stack=5, locals=4, args_size=3
         0: aload_0
         1: iload_1
         2: aload_0
         3: lload_2
         4: invokevirtual #68                 // Method numberNode:(J)Lcom/fasterxml/jackson/databind/node/NumericNode;
         7: invokevirtual #81                 // Method _set:(ILcom/fasterxml/jackson/databind/JsonNode;)Lcom/fasterxml/jackson/databind/node/ArrayNode;
        10: areturn
      LineNumberTable:
        line 892: 0
      LocalVariableTable:
        Start  Length  Slot  Name   Signature
            0      11     0  this   Lcom/fasterxml/jackson/databind/node/ArrayNode;
            0      11     1 index   I
            0      11     2     v   J

  public com.fasterxml.jackson.databind.node.ArrayNode set(int, java.lang.Long);
    descriptor: (ILjava/lang/Long;)Lcom/fasterxml/jackson/databind/node/ArrayNode;
    flags: (0x0001) ACC_PUBLIC
    Code:
      stack=5, locals=3, args_size=3
         0: aload_0
         1: iload_1
         2: aload_2
         3: ifnonnull     13
         6: aload_0
         7: invokevirtual #42                 // Method nullNode:()Lcom/fasterxml/jackson/databind/node/NullNode;
        10: goto          21
        13: aload_0
        14: aload_2
        15: invokevirtual #69                 // Method java/lang/Long.longValue:()J
        18: invokevirtual #68                 // Method numberNode:(J)Lcom/fasterxml/jackson/databind/node/NumericNode;
        21: invokevirtual #81                 // Method _set:(ILcom/fasterxml/jackson/databind/JsonNode;)Lcom/fasterxml/jackson/databind/node/ArrayNode;
        24: areturn
      LineNumberTable:
        line 901: 0
      LocalVariableTable:
        Start  Length  Slot  Name   Signature
            0      25     0  this   Lcom/fasterxml/jackson/databind/node/ArrayNode;
            0      25     1 index   I
            0      25     2     v   Ljava/lang/Long;
      StackMapTable: number_of_entries = 2
        frame_type = 255 /* full_frame */
          offset_delta = 13
          locals = [ class com/fasterxml/jackson/databind/node/ArrayNode, int, class java/lang/Long ]
          stack = [ class com/fasterxml/jackson/databind/node/ArrayNode, int ]
        frame_type = 255 /* full_frame */
          offset_delta = 7
          locals = [ class com/fasterxml/jackson/databind/node/ArrayNode, int, class java/lang/Long ]
          stack = [ class com/fasterxml/jackson/databind/node/ArrayNode, int, class com/fasterxml/jackson/databind/JsonNode ]

  public com.fasterxml.jackson.databind.node.ArrayNode set(int, float);
    descriptor: (IF)Lcom/fasterxml/jackson/databind/node/ArrayNode;
    flags: (0x0001) ACC_PUBLIC
    Code:
      stack=4, locals=3, args_size=3
         0: aload_0
         1: iload_1
         2: aload_0
         3: fload_2
         4: invokevirtual #70                 // Method numberNode:(F)Lcom/fasterxml/jackson/databind/node/NumericNode;
         7: invokevirtual #81                 // Method _set:(ILcom/fasterxml/jackson/databind/JsonNode;)Lcom/fasterxml/jackson/databind/node/ArrayNode;
        10: areturn
      LineNumberTable:
        line 912: 0
      LocalVariableTable:
        Start  Length  Slot  Name   Signature
            0      11     0  this   Lcom/fasterxml/jackson/databind/node/ArrayNode;
            0      11     1 index   I
            0      11     2     v   F

  public com.fasterxml.jackson.databind.node.ArrayNode set(int, java.lang.Float);
    descriptor: (ILjava/lang/Float;)Lcom/fasterxml/jackson/databind/node/ArrayNode;
    flags: (0x0001) ACC_PUBLIC
    Code:
      stack=4, locals=3, args_size=3
         0: aload_0
         1: iload_1
         2: aload_2
         3: ifnonnull     13
         6: aload_0
         7: invokevirtual #42                 // Method nullNode:()Lcom/fasterxml/jackson/databind/node/NullNode;
        10: goto          21
        13: aload_0
        14: aload_2
        15: invokevirtual #71                 // Method java/lang/Float.floatValue:()F
        18: invokevirtual #70                 // Method numberNode:(F)Lcom/fasterxml/jackson/databind/node/NumericNode;
        21: invokevirtual #81                 // Method _set:(ILcom/fasterxml/jackson/databind/JsonNode;)Lcom/fasterxml/jackson/databind/node/ArrayNode;
        24: areturn
      LineNumberTable:
        line 924: 0
      LocalVariableTable:
        Start  Length  Slot  Name   Signature
            0      25     0  this   Lcom/fasterxml/jackson/databind/node/ArrayNode;
            0      25     1 index   I
            0      25     2     v   Ljava/lang/Float;
      StackMapTable: number_of_entries = 2
        frame_type = 255 /* full_frame */
          offset_delta = 13
          locals = [ class com/fasterxml/jackson/databind/node/ArrayNode, int, class java/lang/Float ]
          stack = [ class com/fasterxml/jackson/databind/node/ArrayNode, int ]
        frame_type = 255 /* full_frame */
          offset_delta = 7
          locals = [ class com/fasterxml/jackson/databind/node/ArrayNode, int, class java/lang/Float ]
          stack = [ class com/fasterxml/jackson/databind/node/ArrayNode, int, class com/fasterxml/jackson/databind/JsonNode ]

  public com.fasterxml.jackson.databind.node.ArrayNode set(int, double);
    descriptor: (ID)Lcom/fasterxml/jackson/databind/node/ArrayNode;
    flags: (0x0001) ACC_PUBLIC
    Code:
      stack=5, locals=4, args_size=3
         0: aload_0
         1: iload_1
         2: aload_0
         3: dload_2
         4: invokevirtual #72                 // Method numberNode:(D)Lcom/fasterxml/jackson/databind/node/NumericNode;
         7: invokevirtual #81                 // Method _set:(ILcom/fasterxml/jackson/databind/JsonNode;)Lcom/fasterxml/jackson/databind/node/ArrayNode;
        10: areturn
      LineNumberTable:
        line 935: 0
      LocalVariableTable:
        Start  Length  Slot  Name   Signature
            0      11     0  this   Lcom/fasterxml/jackson/databind/node/ArrayNode;
            0      11     1 index   I
            0      11     2     v   D

  public com.fasterxml.jackson.databind.node.ArrayNode set(int, java.lang.Double);
    descriptor: (ILjava/lang/Double;)Lcom/fasterxml/jackson/databind/node/ArrayNode;
    flags: (0x0001) ACC_PUBLIC
    Code:
      stack=5, locals=3, args_size=3
         0: aload_0
         1: iload_1
         2: aload_2
         3: ifnonnull     13
         6: aload_0
         7: invokevirtual #42                 // Method nullNode:()Lcom/fasterxml/jackson/databind/node/NullNode;
        10: goto          21
        13: aload_0
        14: aload_2
        15: invokevirtual #73                 // Method java/lang/Double.doubleValue:()D
        18: invokevirtual #72                 // Method numberNode:(D)Lcom/fasterxml/jackson/databind/node/NumericNode;
        21: invokevirtual #81                 // Method _set:(ILcom/fasterxml/jackson/databind/JsonNode;)Lcom/fasterxml/jackson/databind/node/ArrayNode;
        24: areturn
      LineNumberTable:
        line 947: 0
      LocalVariableTable:
        Start  Length  Slot  Name   Signature
            0      25     0  this   Lcom/fasterxml/jackson/databind/node/ArrayNode;
            0      25     1 index   I
            0      25     2     v   Ljava/lang/Double;
      StackMapTable: number_of_entries = 2
        frame_type = 255 /* full_frame */
          offset_delta = 13
          locals = [ class com/fasterxml/jackson/databind/node/ArrayNode, int, class java/lang/Double ]
          stack = [ class com/fasterxml/jackson/databind/node/ArrayNode, int ]
        frame_type = 255 /* full_frame */
          offset_delta = 7
          locals = [ class com/fasterxml/jackson/databind/node/ArrayNode, int, class java/lang/Double ]
          stack = [ class com/fasterxml/jackson/databind/node/ArrayNode, int, class com/fasterxml/jackson/databind/JsonNode ]

  public com.fasterxml.jackson.databind.node.ArrayNode set(int, java.math.BigDecimal);
    descriptor: (ILjava/math/BigDecimal;)Lcom/fasterxml/jackson/databind/node/ArrayNode;
    flags: (0x0001) ACC_PUBLIC
    Code:
      stack=4, locals=3, args_size=3
         0: aload_0
         1: iload_1
         2: aload_2
         3: ifnonnull     13
         6: aload_0
         7: invokevirtual #42                 // Method nullNode:()Lcom/fasterxml/jackson/databind/node/NullNode;
        10: goto          18
        13: aload_0
        14: aload_2
        15: invokevirtual #74                 // Method numberNode:(Ljava/math/BigDecimal;)Lcom/fasterxml/jackson/databind/node/ValueNode;
        18: invokevirtual #81                 // Method _set:(ILcom/fasterxml/jackson/databind/JsonNode;)Lcom/fasterxml/jackson/databind/node/ArrayNode;
        21: areturn
      LineNumberTable:
        line 958: 0
      LocalVariableTable:
        Start  Length  Slot  Name   Signature
            0      22     0  this   Lcom/fasterxml/jackson/databind/node/ArrayNode;
            0      22     1 index   I
            0      22     2     v   Ljava/math/BigDecimal;
      StackMapTable: number_of_entries = 2
        frame_type = 255 /* full_frame */
          offset_delta = 13
          locals = [ class com/fasterxml/jackson/databind/node/ArrayNode, int, class java/math/BigDecimal ]
          stack = [ class com/fasterxml/jackson/databind/node/ArrayNode, int ]
        frame_type = 255 /* full_frame */
          offset_delta = 4
          locals = [ class com/fasterxml/jackson/databind/node/ArrayNode, int, class java/math/BigDecimal ]
          stack = [ class com/fasterxml/jackson/databind/node/ArrayNode, int, class com/fasterxml/jackson/databind/JsonNode ]

  public com.fasterxml.jackson.databind.node.ArrayNode set(int, java.math.BigInteger);
    descriptor: (ILjava/math/BigInteger;)Lcom/fasterxml/jackson/databind/node/ArrayNode;
    flags: (0x0001) ACC_PUBLIC
    Code:
      stack=4, locals=3, args_size=3
         0: aload_0
         1: iload_1
         2: aload_2
         3: ifnonnull     13
         6: aload_0
         7: invokevirtual #42                 // Method nullNode:()Lcom/fasterxml/jackson/databind/node/NullNode;
        10: goto          18
        13: aload_0
        14: aload_2
        15: invokevirtual #75                 // Method numberNode:(Ljava/math/BigInteger;)Lcom/fasterxml/jackson/databind/node/ValueNode;
        18: invokevirtual #81                 // Method _set:(ILcom/fasterxml/jackson/databind/JsonNode;)Lcom/fasterxml/jackson/databind/node/ArrayNode;
        21: areturn
      LineNumberTable:
        line 969: 0
      LocalVariableTable:
        Start  Length  Slot  Name   Signature
            0      22     0  this   Lcom/fasterxml/jackson/databind/node/ArrayNode;
            0      22     1 index   I
            0      22     2     v   Ljava/math/BigInteger;
      StackMapTable: number_of_entries = 2
        frame_type = 255 /* full_frame */
          offset_delta = 13
          locals = [ class com/fasterxml/jackson/databind/node/ArrayNode, int, class java/math/BigInteger ]
          stack = [ class com/fasterxml/jackson/databind/node/ArrayNode, int ]
        frame_type = 255 /* full_frame */
          offset_delta = 4
          locals = [ class com/fasterxml/jackson/databind/node/ArrayNode, int, class java/math/BigInteger ]
          stack = [ class com/fasterxml/jackson/databind/node/ArrayNode, int, class com/fasterxml/jackson/databind/JsonNode ]

  public com.fasterxml.jackson.databind.node.ArrayNode set(int, java.lang.String);
    descriptor: (ILjava/lang/String;)Lcom/fasterxml/jackson/databind/node/ArrayNode;
    flags: (0x0001) ACC_PUBLIC
    Code:
      stack=4, locals=3, args_size=3
         0: aload_0
         1: iload_1
         2: aload_2
         3: ifnonnull     13
         6: aload_0
         7: invokevirtual #42                 // Method nullNode:()Lcom/fasterxml/jackson/databind/node/NullNode;
        10: goto          18
        13: aload_0
        14: aload_2
        15: invokevirtual #76                 // Method textNode:(Ljava/lang/String;)Lcom/fasterxml/jackson/databind/node/TextNode;
        18: invokevirtual #81                 // Method _set:(ILcom/fasterxml/jackson/databind/JsonNode;)Lcom/fasterxml/jackson/databind/node/ArrayNode;
        21: areturn
      LineNumberTable:
        line 980: 0
      LocalVariableTable:
        Start  Length  Slot  Name   Signature
            0      22     0  this   Lcom/fasterxml/jackson/databind/node/ArrayNode;
            0      22     1 index   I
            0      22     2     v   Ljava/lang/String;
      StackMapTable: number_of_entries = 2
        frame_type = 255 /* full_frame */
          offset_delta = 13
          locals = [ class com/fasterxml/jackson/databind/node/ArrayNode, int, class java/lang/String ]
          stack = [ class com/fasterxml/jackson/databind/node/ArrayNode, int ]
        frame_type = 255 /* full_frame */
          offset_delta = 4
          locals = [ class com/fasterxml/jackson/databind/node/ArrayNode, int, class java/lang/String ]
          stack = [ class com/fasterxml/jackson/databind/node/ArrayNode, int, class com/fasterxml/jackson/databind/JsonNode ]

  public com.fasterxml.jackson.databind.node.ArrayNode set(int, boolean);
    descriptor: (IZ)Lcom/fasterxml/jackson/databind/node/ArrayNode;
    flags: (0x0001) ACC_PUBLIC
    Code:
      stack=4, locals=3, args_size=3
         0: aload_0
         1: iload_1
         2: aload_0
         3: iload_2
         4: invokevirtual #77                 // Method booleanNode:(Z)Lcom/fasterxml/jackson/databind/node/BooleanNode;
         7: invokevirtual #81                 // Method _set:(ILcom/fasterxml/jackson/databind/JsonNode;)Lcom/fasterxml/jackson/databind/node/ArrayNode;
        10: areturn
      LineNumberTable:
        line 991: 0
      LocalVariableTable:
        Start  Length  Slot  Name   Signature
            0      11     0  this   Lcom/fasterxml/jackson/databind/node/ArrayNode;
            0      11     1 index   I
            0      11     2     v   Z

  public com.fasterxml.jackson.databind.node.ArrayNode set(int, java.lang.Boolean);
    descriptor: (ILjava/lang/Boolean;)Lcom/fasterxml/jackson/databind/node/ArrayNode;
    flags: (0x0001) ACC_PUBLIC
    Code:
      stack=4, locals=3, args_size=3
         0: aload_0
         1: iload_1
         2: aload_2
         3: ifnonnull     13
         6: aload_0
         7: invokevirtual #42                 // Method nullNode:()Lcom/fasterxml/jackson/databind/node/NullNode;
        10: goto          21
        13: aload_0
        14: aload_2
        15: invokevirtual #78                 // Method java/lang/Boolean.booleanValue:()Z
        18: invokevirtual #77                 // Method booleanNode:(Z)Lcom/fasterxml/jackson/databind/node/BooleanNode;
        21: invokevirtual #81                 // Method _set:(ILcom/fasterxml/jackson/databind/JsonNode;)Lcom/fasterxml/jackson/databind/node/ArrayNode;
        24: areturn
      LineNumberTable:
        line 1003: 0
      LocalVariableTable:
        Start  Length  Slot  Name   Signature
            0      25     0  this   Lcom/fasterxml/jackson/databind/node/ArrayNode;
            0      25     1 index   I
            0      25     2     v   Ljava/lang/Boolean;
      StackMapTable: number_of_entries = 2
        frame_type = 255 /* full_frame */
          offset_delta = 13
          locals = [ class com/fasterxml/jackson/databind/node/ArrayNode, int, class java/lang/Boolean ]
          stack = [ class com/fasterxml/jackson/databind/node/ArrayNode, int ]
        frame_type = 255 /* full_frame */
          offset_delta = 7
          locals = [ class com/fasterxml/jackson/databind/node/ArrayNode, int, class java/lang/Boolean ]
          stack = [ class com/fasterxml/jackson/databind/node/ArrayNode, int, class com/fasterxml/jackson/databind/JsonNode ]

  public com.fasterxml.jackson.databind.node.ArrayNode set(int, byte[]);
    descriptor: (I[B)Lcom/fasterxml/jackson/databind/node/ArrayNode;
    flags: (0x0001) ACC_PUBLIC
    Code:
      stack=4, locals=3, args_size=3
         0: aload_0
         1: iload_1
         2: aload_2
         3: ifnonnull     13
         6: aload_0
         7: invokevirtual #42                 // Method nullNode:()Lcom/fasterxml/jackson/databind/node/NullNode;
        10: goto          18
        13: aload_0
        14: aload_2
        15: invokevirtual #79                 // Method binaryNode:([B)Lcom/fasterxml/jackson/databind/node/BinaryNode;
        18: invokevirtual #81                 // Method _set:(ILcom/fasterxml/jackson/databind/JsonNode;)Lcom/fasterxml/jackson/databind/node/ArrayNode;
        21: areturn
      LineNumberTable:
        line 1014: 0
      LocalVariableTable:
        Start  Length  Slot  Name   Signature
            0      22     0  this   Lcom/fasterxml/jackson/databind/node/ArrayNode;
            0      22     1 index   I
            0      22     2     v   [B
      StackMapTable: number_of_entries = 2
        frame_type = 255 /* full_frame */
          offset_delta = 13
          locals = [ class com/fasterxml/jackson/databind/node/ArrayNode, int, class "[B" ]
          stack = [ class com/fasterxml/jackson/databind/node/ArrayNode, int ]
        frame_type = 255 /* full_frame */
          offset_delta = 4
          locals = [ class com/fasterxml/jackson/databind/node/ArrayNode, int, class "[B" ]
          stack = [ class com/fasterxml/jackson/databind/node/ArrayNode, int, class com/fasterxml/jackson/databind/JsonNode ]

  public boolean equals(java.lang.Object);
    descriptor: (Ljava/lang/Object;)Z
    flags: (0x0001) ACC_PUBLIC
    Code:
      stack=2, locals=2, args_size=2
         0: aload_1
         1: aload_0
         2: if_acmpne     7
         5: iconst_1
         6: ireturn
         7: aload_1
         8: ifnonnull     13
        11: iconst_0
        12: ireturn
        13: aload_1
        14: instanceof    #8                  // class com/fasterxml/jackson/databind/node/ArrayNode
        17: ifeq          37
        20: aload_0
        21: getfield      #4                  // Field _children:Ljava/util/List;
        24: aload_1
        25: checkcast     #8                  // class com/fasterxml/jackson/databind/node/ArrayNode
        28: getfield      #4                  // Field _children:Ljava/util/List;
        31: invokeinterface #82,  2           // InterfaceMethod java/util/List.equals:(Ljava/lang/Object;)Z
        36: ireturn
        37: iconst_0
        38: ireturn
      LineNumberTable:
        line 1026: 0
        line 1027: 7
        line 1028: 13
        line 1029: 20
        line 1031: 37
      LocalVariableTable:
        Start  Length  Slot  Name   Signature
            0      39     0  this   Lcom/fasterxml/jackson/databind/node/ArrayNode;
            0      39     1     o   Ljava/lang/Object;
      StackMapTable: number_of_entries = 3
        frame_type = 7 /* same */
        frame_type = 5 /* same */
        frame_type = 23 /* same */

  protected boolean _childrenEqual(com.fasterxml.jackson.databind.node.ArrayNode);
    descriptor: (Lcom/fasterxml/jackson/databind/node/ArrayNode;)Z
    flags: (0x0004) ACC_PROTECTED
    Code:
      stack=2, locals=2, args_size=2
         0: aload_0
         1: getfield      #4                  // Field _children:Ljava/util/List;
         4: aload_1
         5: getfield      #4                  // Field _children:Ljava/util/List;
         8: invokeinterface #82,  2           // InterfaceMethod java/util/List.equals:(Ljava/lang/Object;)Z
        13: ireturn
      LineNumberTable:
        line 1038: 0
      LocalVariableTable:
        Start  Length  Slot  Name   Signature
            0      14     0  this   Lcom/fasterxml/jackson/databind/node/ArrayNode;
            0      14     1 other   Lcom/fasterxml/jackson/databind/node/ArrayNode;

  public int hashCode();
    descriptor: ()I
    flags: (0x0001) ACC_PUBLIC
    Code:
      stack=1, locals=1, args_size=1
         0: aload_0
         1: getfield      #4                  // Field _children:Ljava/util/List;
         4: invokeinterface #83,  1           // InterfaceMethod java/util/List.hashCode:()I
         9: ireturn
      LineNumberTable:
        line 1043: 0
      LocalVariableTable:
        Start  Length  Slot  Name   Signature
            0      10     0  this   Lcom/fasterxml/jackson/databind/node/ArrayNode;

  protected com.fasterxml.jackson.databind.node.ArrayNode _set(int, com.fasterxml.jackson.databind.JsonNode);
    descriptor: (ILcom/fasterxml/jackson/databind/JsonNode;)Lcom/fasterxml/jackson/databind/node/ArrayNode;
    flags: (0x0004) ACC_PROTECTED
    Code:
      stack=4, locals=3, args_size=3
         0: iload_1
         1: iflt          17
         4: iload_1
         5: aload_0
         6: getfield      #4                  // Field _children:Ljava/util/List;
         9: invokeinterface #20,  1           // InterfaceMethod java/util/List.size:()I
        14: if_icmplt     56
        17: new           #43                 // class java/lang/IndexOutOfBoundsException
        20: dup
        21: new           #44                 // class java/lang/StringBuilder
        24: dup
        25: invokespecial #45                 // Method java/lang/StringBuilder."<init>":()V
        28: ldc           #46                 // String Illegal index
        30: invokevirtual #47                 // Method java/lang/StringBuilder.append:(Ljava/lang/String;)Ljava/lang/StringBuilder;
        33: iload_1
        34: invokevirtual #48                 // Method java/lang/StringBuilder.append:(I)Ljava/lang/StringBuilder;
        37: ldc           #49                 // String , array size
        39: invokevirtual #47                 // Method java/lang/StringBuilder.append:(Ljava/lang/String;)Ljava/lang/StringBuilder;
        42: aload_0
        43: invokevirtual #27                 // Method size:()I
        46: invokevirtual #48                 // Method java/lang/StringBuilder.append:(I)Ljava/lang/StringBuilder;
        49: invokevirtual #50                 // Method java/lang/StringBuilder.toString:()Ljava/lang/String;
        52: invokespecial #51                 // Method java/lang/IndexOutOfBoundsException."<init>":(Ljava/lang/String;)V
        55: athrow
        56: aload_0
        57: getfield      #4                  // Field _children:Ljava/util/List;
        60: iload_1
        61: aload_2
        62: invokeinterface #52,  3           // InterfaceMethod java/util/List.set:(ILjava/lang/Object;)Ljava/lang/Object;
        67: pop
        68: aload_0
        69: areturn
      LineNumberTable:
        line 1053: 0
        line 1054: 17
        line 1056: 56
        line 1057: 68
      LocalVariableTable:
        Start  Length  Slot  Name   Signature
            0      70     0  this   Lcom/fasterxml/jackson/databind/node/ArrayNode;
            0      70     1 index   I
            0      70     2  node   Lcom/fasterxml/jackson/databind/JsonNode;
      StackMapTable: number_of_entries = 2
        frame_type = 17 /* same */
        frame_type = 38 /* same */

  protected com.fasterxml.jackson.databind.node.ArrayNode _add(com.fasterxml.jackson.databind.JsonNode);
    descriptor: (Lcom/fasterxml/jackson/databind/JsonNode;)Lcom/fasterxml/jackson/databind/node/ArrayNode;
    flags: (0x0004) ACC_PROTECTED
    Code:
      stack=2, locals=2, args_size=2
         0: aload_0
         1: getfield      #4                  // Field _children:Ljava/util/List;
         4: aload_1
         5: invokeinterface #16,  2           // InterfaceMethod java/util/List.add:(Ljava/lang/Object;)Z
        10: pop
        11: aload_0
        12: areturn
      LineNumberTable:
        line 1061: 0
        line 1062: 11
      LocalVariableTable:
        Start  Length  Slot  Name   Signature
            0      13     0  this   Lcom/fasterxml/jackson/databind/node/ArrayNode;
            0      13     1  node   Lcom/fasterxml/jackson/databind/JsonNode;

  protected com.fasterxml.jackson.databind.node.ArrayNode _insert(int, com.fasterxml.jackson.databind.JsonNode);
    descriptor: (ILcom/fasterxml/jackson/databind/JsonNode;)Lcom/fasterxml/jackson/databind/node/ArrayNode;
    flags: (0x0004) ACC_PROTECTED
    Code:
      stack=3, locals=3, args_size=3
         0: iload_1
         1: ifge          18
         4: aload_0
         5: getfield      #4                  // Field _children:Ljava/util/List;
         8: iconst_0
         9: aload_2
        10: invokeinterface #84,  3           // InterfaceMethod java/util/List.add:(ILjava/lang/Object;)V
        15: goto          56
        18: iload_1
        19: aload_0
        20: getfield      #4                  // Field _children:Ljava/util/List;
        23: invokeinterface #20,  1           // InterfaceMethod java/util/List.size:()I
        28: if_icmplt     45
        31: aload_0
        32: getfield      #4                  // Field _children:Ljava/util/List;
        35: aload_2
        36: invokeinterface #16,  2           // InterfaceMethod java/util/List.add:(Ljava/lang/Object;)Z
        41: pop
        42: goto          56
        45: aload_0
        46: getfield      #4                  // Field _children:Ljava/util/List;
        49: iload_1
        50: aload_2
        51: invokeinterface #84,  3           // InterfaceMethod java/util/List.add:(ILjava/lang/Object;)V
        56: aload_0
        57: areturn
      LineNumberTable:
        line 1067: 0
        line 1068: 4
        line 1069: 18
        line 1070: 31
        line 1072: 45
        line 1074: 56
      LocalVariableTable:
        Start  Length  Slot  Name   Signature
            0      58     0  this   Lcom/fasterxml/jackson/databind/node/ArrayNode;
            0      58     1 index   I
            0      58     2  node   Lcom/fasterxml/jackson/databind/JsonNode;
      StackMapTable: number_of_entries = 3
        frame_type = 18 /* same */
        frame_type = 26 /* same */
        frame_type = 10 /* same */

  public com.fasterxml.jackson.databind.node.ContainerNode removeAll();
    descriptor: ()Lcom/fasterxml/jackson/databind/node/ContainerNode;
    flags: (0x1041) ACC_PUBLIC, ACC_BRIDGE, ACC_SYNTHETIC
    Code:
      stack=1, locals=1, args_size=1
         0: aload_0
         1: invokevirtual #85                 // Method removeAll:()Lcom/fasterxml/jackson/databind/node/ArrayNode;
         4: areturn
      LineNumberTable:
        line 24: 0
      LocalVariableTable:
        Start  Length  Slot  Name   Signature
            0       5     0  this   Lcom/fasterxml/jackson/databind/node/ArrayNode;

  public com.fasterxml.jackson.databind.JsonNode findParent(java.lang.String);
    descriptor: (Ljava/lang/String;)Lcom/fasterxml/jackson/databind/JsonNode;
    flags: (0x1041) ACC_PUBLIC, ACC_BRIDGE, ACC_SYNTHETIC
    Code:
      stack=2, locals=2, args_size=2
         0: aload_0
         1: aload_1
         2: invokevirtual #86                 // Method findParent:(Ljava/lang/String;)Lcom/fasterxml/jackson/databind/node/ObjectNode;
         5: areturn
      LineNumberTable:
        line 24: 0
      LocalVariableTable:
        Start  Length  Slot  Name   Signature
            0       6     0  this   Lcom/fasterxml/jackson/databind/node/ArrayNode;

  public com.fasterxml.jackson.databind.JsonNode deepCopy();
    descriptor: ()Lcom/fasterxml/jackson/databind/JsonNode;
    flags: (0x1041) ACC_PUBLIC, ACC_BRIDGE, ACC_SYNTHETIC
    Code:
      stack=1, locals=1, args_size=1
         0: aload_0
         1: invokevirtual #87                 // Method deepCopy:()Lcom/fasterxml/jackson/databind/node/ArrayNode;
         4: areturn
      LineNumberTable:
        line 24: 0
      LocalVariableTable:
        Start  Length  Slot  Name   Signature
            0       5     0  this   Lcom/fasterxml/jackson/databind/node/ArrayNode;

  public com.fasterxml.jackson.core.TreeNode path(int);
    descriptor: (I)Lcom/fasterxml/jackson/core/TreeNode;
    flags: (0x1041) ACC_PUBLIC, ACC_BRIDGE, ACC_SYNTHETIC
    Code:
      stack=2, locals=2, args_size=2
         0: aload_0
         1: iload_1
         2: invokevirtual #88                 // Method path:(I)Lcom/fasterxml/jackson/databind/JsonNode;
         5: areturn
      LineNumberTable:
        line 24: 0
      LocalVariableTable:
        Start  Length  Slot  Name   Signature
            0       6     0  this   Lcom/fasterxml/jackson/databind/node/ArrayNode;

  public com.fasterxml.jackson.core.TreeNode path(java.lang.String);
    descriptor: (Ljava/lang/String;)Lcom/fasterxml/jackson/core/TreeNode;
    flags: (0x1041) ACC_PUBLIC, ACC_BRIDGE, ACC_SYNTHETIC
    Code:
      stack=2, locals=2, args_size=2
         0: aload_0
         1: aload_1
         2: invokevirtual #89                 // Method path:(Ljava/lang/String;)Lcom/fasterxml/jackson/databind/JsonNode;
         5: areturn
      LineNumberTable:
        line 24: 0
      LocalVariableTable:
        Start  Length  Slot  Name   Signature
            0       6     0  this   Lcom/fasterxml/jackson/databind/node/ArrayNode;

  public com.fasterxml.jackson.core.TreeNode get(int);
    descriptor: (I)Lcom/fasterxml/jackson/core/TreeNode;
    flags: (0x1041) ACC_PUBLIC, ACC_BRIDGE, ACC_SYNTHETIC
    Code:
      stack=2, locals=2, args_size=2
         0: aload_0
         1: iload_1
         2: invokevirtual #7                  // Method get:(I)Lcom/fasterxml/jackson/databind/JsonNode;
         5: areturn
      LineNumberTable:
        line 24: 0
      LocalVariableTable:
        Start  Length  Slot  Name   Signature
            0       6     0  this   Lcom/fasterxml/jackson/databind/node/ArrayNode;

  public com.fasterxml.jackson.core.TreeNode get(java.lang.String);
    descriptor: (Ljava/lang/String;)Lcom/fasterxml/jackson/core/TreeNode;
    flags: (0x1041) ACC_PUBLIC, ACC_BRIDGE, ACC_SYNTHETIC
    Code:
      stack=2, locals=2, args_size=2
         0: aload_0
         1: aload_1
         2: invokevirtual #90                 // Method get:(Ljava/lang/String;)Lcom/fasterxml/jackson/databind/JsonNode;
         5: areturn
      LineNumberTable:
        line 24: 0
      LocalVariableTable:
        Start  Length  Slot  Name   Signature
            0       6     0  this   Lcom/fasterxml/jackson/databind/node/ArrayNode;
}
Signature: #306                         // Lcom/fasterxml/jackson/databind/node/ContainerNode<Lcom/fasterxml/jackson/databind/node/ArrayNode;>;Ljava/io/Serializable;
SourceFile: "ArrayNode.java"
