Classfile /Users/mw/Projects/slang-braindump/.jar/jar8/assemble/slang-braindump/assemble/content/com/fasterxml/jackson/databind/node/NodeCursor.class
  Last modified May 29, 2022; size 2626 bytes
  SHA-256 checksum 38e893392c82be317960f0bc0adf5a21159a7c3d42ccbe67357d184952467022
  Compiled from "NodeCursor.java"
abstract class com.fasterxml.jackson.databind.node.NodeCursor extends com.fasterxml.jackson.core.JsonStreamContext
  minor version: 0
  major version: 52
  flags: (0x0420) ACC_SUPER, ACC_ABSTRACT
  this_class: #25                         // com/fasterxml/jackson/databind/node/NodeCursor
  super_class: #26                        // com/fasterxml/jackson/core/JsonStreamContext
  interfaces: 0, fields: 3, methods: 12, attributes: 2
Constant pool:
    #1 = Methodref          #26.#73       // com/fasterxml/jackson/core/JsonStreamContext."<init>":()V
    #2 = Fieldref           #25.#74       // com/fasterxml/jackson/databind/node/NodeCursor._type:I
    #3 = Fieldref           #25.#75       // com/fasterxml/jackson/databind/node/NodeCursor._index:I
    #4 = Fieldref           #25.#76       // com/fasterxml/jackson/databind/node/NodeCursor._parent:Lcom/fasterxml/jackson/databind/node/NodeCursor;
    #5 = Fieldref           #25.#77       // com/fasterxml/jackson/databind/node/NodeCursor._currentName:Ljava/lang/String;
    #6 = Fieldref           #25.#78       // com/fasterxml/jackson/databind/node/NodeCursor._currentValue:Ljava/lang/Object;
    #7 = Methodref          #25.#79       // com/fasterxml/jackson/databind/node/NodeCursor.currentNode:()Lcom/fasterxml/jackson/databind/JsonNode;
    #8 = Class              #80           // java/lang/IllegalStateException
    #9 = String             #81           // No current node
   #10 = Methodref          #8.#82        // java/lang/IllegalStateException."<init>":(Ljava/lang/String;)V
   #11 = Methodref          #83.#84       // com/fasterxml/jackson/databind/JsonNode.isArray:()Z
   #12 = Class              #85           // com/fasterxml/jackson/databind/node/NodeCursor$ArrayCursor
   #13 = Methodref          #12.#86       // com/fasterxml/jackson/databind/node/NodeCursor$ArrayCursor."<init>":(Lcom/fasterxml/jackson/databind/JsonNode;Lcom/fasterxml/jackson/databind/node/NodeCursor;)V
   #14 = Methodref          #83.#87       // com/fasterxml/jackson/databind/JsonNode.isObject:()Z
   #15 = Class              #88           // com/fasterxml/jackson/databind/node/NodeCursor$ObjectCursor
   #16 = Methodref          #15.#86       // com/fasterxml/jackson/databind/node/NodeCursor$ObjectCursor."<init>":(Lcom/fasterxml/jackson/databind/JsonNode;Lcom/fasterxml/jackson/databind/node/NodeCursor;)V
   #17 = Class              #89           // java/lang/StringBuilder
   #18 = Methodref          #17.#73       // java/lang/StringBuilder."<init>":()V
   #19 = String             #90           // Current node of type
   #20 = Methodref          #17.#91       // java/lang/StringBuilder.append:(Ljava/lang/String;)Ljava/lang/StringBuilder;
   #21 = Methodref          #92.#93       // java/lang/Object.getClass:()Ljava/lang/Class;
   #22 = Methodref          #94.#95       // java/lang/Class.getName:()Ljava/lang/String;
   #23 = Methodref          #17.#96       // java/lang/StringBuilder.toString:()Ljava/lang/String;
   #24 = Methodref          #25.#97       // com/fasterxml/jackson/databind/node/NodeCursor.getParent:()Lcom/fasterxml/jackson/databind/node/NodeCursor;
   #25 = Class              #98           // com/fasterxml/jackson/databind/node/NodeCursor
   #26 = Class              #99           // com/fasterxml/jackson/core/JsonStreamContext
   #27 = Utf8               ObjectCursor
   #28 = Utf8               InnerClasses
   #29 = Utf8               ArrayCursor
   #30 = Class              #100          // com/fasterxml/jackson/databind/node/NodeCursor$RootCursor
   #31 = Utf8               RootCursor
   #32 = Utf8               _parent
   #33 = Utf8               Lcom/fasterxml/jackson/databind/node/NodeCursor;
   #34 = Utf8               _currentName
   #35 = Utf8               Ljava/lang/String;
   #36 = Utf8               _currentValue
   #37 = Utf8               Ljava/lang/Object;
   #38 = Utf8               <init>
   #39 = Utf8               (ILcom/fasterxml/jackson/databind/node/NodeCursor;)V
   #40 = Utf8               Code
   #41 = Utf8               LineNumberTable
   #42 = Utf8               LocalVariableTable
   #43 = Utf8               this
   #44 = Utf8               contextType
   #45 = Utf8               I
   #46 = Utf8               p
   #47 = Utf8               getParent
   #48 = Utf8               ()Lcom/fasterxml/jackson/databind/node/NodeCursor;
   #49 = Utf8               getCurrentName
   #50 = Utf8               ()Ljava/lang/String;
   #51 = Utf8               overrideCurrentName
   #52 = Utf8               (Ljava/lang/String;)V
   #53 = Utf8               name
   #54 = Utf8               getCurrentValue
   #55 = Utf8               ()Ljava/lang/Object;
   #56 = Utf8               setCurrentValue
   #57 = Utf8               (Ljava/lang/Object;)V
   #58 = Utf8               v
   #59 = Utf8               nextToken
   #60 = Utf8               ()Lcom/fasterxml/jackson/core/JsonToken;
   #61 = Utf8               currentNode
   #62 = Utf8               ()Lcom/fasterxml/jackson/databind/JsonNode;
   #63 = Utf8               startObject
   #64 = Utf8               startArray
   #65 = Utf8               iterateChildren
   #66 = Utf8               n
   #67 = Utf8               Lcom/fasterxml/jackson/databind/JsonNode;
   #68 = Utf8               StackMapTable
   #69 = Class              #101          // com/fasterxml/jackson/databind/JsonNode
   #70 = Utf8               ()Lcom/fasterxml/jackson/core/JsonStreamContext;
   #71 = Utf8               SourceFile
   #72 = Utf8               NodeCursor.java
   #73 = NameAndType        #38:#102      // "<init>":()V
   #74 = NameAndType        #103:#45      // _type:I
   #75 = NameAndType        #104:#45      // _index:I
   #76 = NameAndType        #32:#33       // _parent:Lcom/fasterxml/jackson/databind/node/NodeCursor;
   #77 = NameAndType        #34:#35       // _currentName:Ljava/lang/String;
   #78 = NameAndType        #36:#37       // _currentValue:Ljava/lang/Object;
   #79 = NameAndType        #61:#62       // currentNode:()Lcom/fasterxml/jackson/databind/JsonNode;
   #80 = Utf8               java/lang/IllegalStateException
   #81 = Utf8               No current node
   #82 = NameAndType        #38:#52       // "<init>":(Ljava/lang/String;)V
   #83 = Class              #101          // com/fasterxml/jackson/databind/JsonNode
   #84 = NameAndType        #105:#106     // isArray:()Z
   #85 = Utf8               com/fasterxml/jackson/databind/node/NodeCursor$ArrayCursor
   #86 = NameAndType        #38:#107      // "<init>":(Lcom/fasterxml/jackson/databind/JsonNode;Lcom/fasterxml/jackson/databind/node/NodeCursor;)V
   #87 = NameAndType        #108:#106     // isObject:()Z
   #88 = Utf8               com/fasterxml/jackson/databind/node/NodeCursor$ObjectCursor
   #89 = Utf8               java/lang/StringBuilder
   #90 = Utf8               Current node of type
   #91 = NameAndType        #109:#110     // append:(Ljava/lang/String;)Ljava/lang/StringBuilder;
   #92 = Class              #111          // java/lang/Object
   #93 = NameAndType        #112:#113     // getClass:()Ljava/lang/Class;
   #94 = Class              #114          // java/lang/Class
   #95 = NameAndType        #115:#50      // getName:()Ljava/lang/String;
   #96 = NameAndType        #116:#50      // toString:()Ljava/lang/String;
   #97 = NameAndType        #47:#48       // getParent:()Lcom/fasterxml/jackson/databind/node/NodeCursor;
   #98 = Utf8               com/fasterxml/jackson/databind/node/NodeCursor
   #99 = Utf8               com/fasterxml/jackson/core/JsonStreamContext
  #100 = Utf8               com/fasterxml/jackson/databind/node/NodeCursor$RootCursor
  #101 = Utf8               com/fasterxml/jackson/databind/JsonNode
  #102 = Utf8               ()V
  #103 = Utf8               _type
  #104 = Utf8               _index
  #105 = Utf8               isArray
  #106 = Utf8               ()Z
  #107 = Utf8               (Lcom/fasterxml/jackson/databind/JsonNode;Lcom/fasterxml/jackson/databind/node/NodeCursor;)V
  #108 = Utf8               isObject
  #109 = Utf8               append
  #110 = Utf8               (Ljava/lang/String;)Ljava/lang/StringBuilder;
  #111 = Utf8               java/lang/Object
  #112 = Utf8               getClass
  #113 = Utf8               ()Ljava/lang/Class;
  #114 = Utf8               java/lang/Class
  #115 = Utf8               getName
  #116 = Utf8               toString
{
  protected final com.fasterxml.jackson.databind.node.NodeCursor _parent;
    descriptor: Lcom/fasterxml/jackson/databind/node/NodeCursor;
    flags: (0x0014) ACC_PROTECTED, ACC_FINAL

  protected java.lang.String _currentName;
    descriptor: Ljava/lang/String;
    flags: (0x0004) ACC_PROTECTED

  protected java.lang.Object _currentValue;
    descriptor: Ljava/lang/Object;
    flags: (0x0004) ACC_PROTECTED

  public com.fasterxml.jackson.databind.node.NodeCursor(int, com.fasterxml.jackson.databind.node.NodeCursor);
    descriptor: (ILcom/fasterxml/jackson/databind/node/NodeCursor;)V
    flags: (0x0001) ACC_PUBLIC
    Code:
      stack=2, locals=3, args_size=3
         0: aload_0
         1: invokespecial #1                  // Method com/fasterxml/jackson/core/JsonStreamContext."<init>":()V
         4: aload_0
         5: iload_1
         6: putfield      #2                  // Field _type:I
         9: aload_0
        10: iconst_m1
        11: putfield      #3                  // Field _index:I
        14: aload_0
        15: aload_2
        16: putfield      #4                  // Field _parent:Lcom/fasterxml/jackson/databind/node/NodeCursor;
        19: return
      LineNumberTable:
        line 33: 0
        line 34: 4
        line 35: 9
        line 36: 14
        line 37: 19
      LocalVariableTable:
        Start  Length  Slot  Name   Signature
            0      20     0  this   Lcom/fasterxml/jackson/databind/node/NodeCursor;
            0      20     1 contextType   I
            0      20     2     p   Lcom/fasterxml/jackson/databind/node/NodeCursor;

  public final com.fasterxml.jackson.databind.node.NodeCursor getParent();
    descriptor: ()Lcom/fasterxml/jackson/databind/node/NodeCursor;
    flags: (0x0011) ACC_PUBLIC, ACC_FINAL
    Code:
      stack=1, locals=1, args_size=1
         0: aload_0
         1: getfield      #4                  // Field _parent:Lcom/fasterxml/jackson/databind/node/NodeCursor;
         4: areturn
      LineNumberTable:
        line 47: 0
      LocalVariableTable:
        Start  Length  Slot  Name   Signature
            0       5     0  this   Lcom/fasterxml/jackson/databind/node/NodeCursor;

  public final java.lang.String getCurrentName();
    descriptor: ()Ljava/lang/String;
    flags: (0x0011) ACC_PUBLIC, ACC_FINAL
    Code:
      stack=1, locals=1, args_size=1
         0: aload_0
         1: getfield      #5                  // Field _currentName:Ljava/lang/String;
         4: areturn
      LineNumberTable:
        line 51: 0
      LocalVariableTable:
        Start  Length  Slot  Name   Signature
            0       5     0  this   Lcom/fasterxml/jackson/databind/node/NodeCursor;

  public void overrideCurrentName(java.lang.String);
    descriptor: (Ljava/lang/String;)V
    flags: (0x0001) ACC_PUBLIC
    Code:
      stack=2, locals=2, args_size=2
         0: aload_0
         1: aload_1
         2: putfield      #5                  // Field _currentName:Ljava/lang/String;
         5: return
      LineNumberTable:
        line 58: 0
        line 59: 5
      LocalVariableTable:
        Start  Length  Slot  Name   Signature
            0       6     0  this   Lcom/fasterxml/jackson/databind/node/NodeCursor;
            0       6     1  name   Ljava/lang/String;

  public java.lang.Object getCurrentValue();
    descriptor: ()Ljava/lang/Object;
    flags: (0x0001) ACC_PUBLIC
    Code:
      stack=1, locals=1, args_size=1
         0: aload_0
         1: getfield      #6                  // Field _currentValue:Ljava/lang/Object;
         4: areturn
      LineNumberTable:
        line 63: 0
      LocalVariableTable:
        Start  Length  Slot  Name   Signature
            0       5     0  this   Lcom/fasterxml/jackson/databind/node/NodeCursor;

  public void setCurrentValue(java.lang.Object);
    descriptor: (Ljava/lang/Object;)V
    flags: (0x0001) ACC_PUBLIC
    Code:
      stack=2, locals=2, args_size=2
         0: aload_0
         1: aload_1
         2: putfield      #6                  // Field _currentValue:Ljava/lang/Object;
         5: return
      LineNumberTable:
        line 68: 0
        line 69: 5
      LocalVariableTable:
        Start  Length  Slot  Name   Signature
            0       6     0  this   Lcom/fasterxml/jackson/databind/node/NodeCursor;
            0       6     1     v   Ljava/lang/Object;

  public abstract com.fasterxml.jackson.core.JsonToken nextToken();
    descriptor: ()Lcom/fasterxml/jackson/core/JsonToken;
    flags: (0x0401) ACC_PUBLIC, ACC_ABSTRACT

  public abstract com.fasterxml.jackson.databind.JsonNode currentNode();
    descriptor: ()Lcom/fasterxml/jackson/databind/JsonNode;
    flags: (0x0401) ACC_PUBLIC, ACC_ABSTRACT

  public abstract com.fasterxml.jackson.databind.node.NodeCursor startObject();
    descriptor: ()Lcom/fasterxml/jackson/databind/node/NodeCursor;
    flags: (0x0401) ACC_PUBLIC, ACC_ABSTRACT

  public abstract com.fasterxml.jackson.databind.node.NodeCursor startArray();
    descriptor: ()Lcom/fasterxml/jackson/databind/node/NodeCursor;
    flags: (0x0401) ACC_PUBLIC, ACC_ABSTRACT

  public final com.fasterxml.jackson.databind.node.NodeCursor iterateChildren();
    descriptor: ()Lcom/fasterxml/jackson/databind/node/NodeCursor;
    flags: (0x0011) ACC_PUBLIC, ACC_FINAL
    Code:
      stack=4, locals=2, args_size=1
         0: aload_0
         1: invokevirtual #7                  // Method currentNode:()Lcom/fasterxml/jackson/databind/JsonNode;
         4: astore_1
         5: aload_1
         6: ifnonnull     19
         9: new           #8                  // class java/lang/IllegalStateException
        12: dup
        13: ldc           #9                  // String No current node
        15: invokespecial #10                 // Method java/lang/IllegalStateException."<init>":(Ljava/lang/String;)V
        18: athrow
        19: aload_1
        20: invokevirtual #11                 // Method com/fasterxml/jackson/databind/JsonNode.isArray:()Z
        23: ifeq          36
        26: new           #12                 // class com/fasterxml/jackson/databind/node/NodeCursor$ArrayCursor
        29: dup
        30: aload_1
        31: aload_0
        32: invokespecial #13                 // Method com/fasterxml/jackson/databind/node/NodeCursor$ArrayCursor."<init>":(Lcom/fasterxml/jackson/databind/JsonNode;Lcom/fasterxml/jackson/databind/node/NodeCursor;)V
        35: areturn
        36: aload_1
        37: invokevirtual #14                 // Method com/fasterxml/jackson/databind/JsonNode.isObject:()Z
        40: ifeq          53
        43: new           #15                 // class com/fasterxml/jackson/databind/node/NodeCursor$ObjectCursor
        46: dup
        47: aload_1
        48: aload_0
        49: invokespecial #16                 // Method com/fasterxml/jackson/databind/node/NodeCursor$ObjectCursor."<init>":(Lcom/fasterxml/jackson/databind/JsonNode;Lcom/fasterxml/jackson/databind/node/NodeCursor;)V
        52: areturn
        53: new           #8                  // class java/lang/IllegalStateException
        56: dup
        57: new           #17                 // class java/lang/StringBuilder
        60: dup
        61: invokespecial #18                 // Method java/lang/StringBuilder."<init>":()V
        64: ldc           #19                 // String Current node of type
        66: invokevirtual #20                 // Method java/lang/StringBuilder.append:(Ljava/lang/String;)Ljava/lang/StringBuilder;
        69: aload_1
        70: invokevirtual #21                 // Method java/lang/Object.getClass:()Ljava/lang/Class;
        73: invokevirtual #22                 // Method java/lang/Class.getName:()Ljava/lang/String;
        76: invokevirtual #20                 // Method java/lang/StringBuilder.append:(Ljava/lang/String;)Ljava/lang/StringBuilder;
        79: invokevirtual #23                 // Method java/lang/StringBuilder.toString:()Ljava/lang/String;
        82: invokespecial #10                 // Method java/lang/IllegalStateException."<init>":(Ljava/lang/String;)V
        85: athrow
      LineNumberTable:
        line 88: 0
        line 89: 5
        line 90: 19
        line 91: 26
        line 93: 36
        line 94: 43
        line 96: 53
      LocalVariableTable:
        Start  Length  Slot  Name   Signature
            0      86     0  this   Lcom/fasterxml/jackson/databind/node/NodeCursor;
            5      81     1     n   Lcom/fasterxml/jackson/databind/JsonNode;
      StackMapTable: number_of_entries = 3
        frame_type = 252 /* append */
          offset_delta = 19
          locals = [ class com/fasterxml/jackson/databind/JsonNode ]
        frame_type = 16 /* same */
        frame_type = 16 /* same */

  public com.fasterxml.jackson.core.JsonStreamContext getParent();
    descriptor: ()Lcom/fasterxml/jackson/core/JsonStreamContext;
    flags: (0x1041) ACC_PUBLIC, ACC_BRIDGE, ACC_SYNTHETIC
    Code:
      stack=1, locals=1, args_size=1
         0: aload_0
         1: invokevirtual #24                 // Method getParent:()Lcom/fasterxml/jackson/databind/node/NodeCursor;
         4: areturn
      LineNumberTable:
        line 12: 0
      LocalVariableTable:
        Start  Length  Slot  Name   Signature
            0       5     0  this   Lcom/fasterxml/jackson/databind/node/NodeCursor;
}
SourceFile: "NodeCursor.java"
InnerClasses:
  protected static final #27= #15 of #25; // ObjectCursor=class com/fasterxml/jackson/databind/node/NodeCursor$ObjectCursor of class com/fasterxml/jackson/databind/node/NodeCursor
  protected static final #29= #12 of #25; // ArrayCursor=class com/fasterxml/jackson/databind/node/NodeCursor$ArrayCursor of class com/fasterxml/jackson/databind/node/NodeCursor
  protected static final #31= #30 of #25; // RootCursor=class com/fasterxml/jackson/databind/node/NodeCursor$RootCursor of class com/fasterxml/jackson/databind/node/NodeCursor
