Classfile /Users/mw/Projects/slang-braindump/.jar/jar8/assemble/slang-braindump/assemble/content/com/fasterxml/jackson/databind/node/ObjectNode.class
  Last modified May 29, 2022; size 22325 bytes
  SHA-256 checksum 3272406a5fecb7e37cfc87e0f80b3a6a41ce34c18ee8774e5f330abfa022c690
  Compiled from "ObjectNode.java"
public class com.fasterxml.jackson.databind.node.ObjectNode extends com.fasterxml.jackson.databind.node.ContainerNode<com.fasterxml.jackson.databind.node.ObjectNode> implements java.io.Serializable
  minor version: 0
  major version: 52
  flags: (0x0021) ACC_PUBLIC, ACC_SUPER
  this_class: #7                          // com/fasterxml/jackson/databind/node/ObjectNode
  super_class: #112                       // com/fasterxml/jackson/databind/node/ContainerNode
  interfaces: 1, fields: 2, methods: 77, attributes: 3
Constant pool:
    #1 = Methodref          #112.#332     // com/fasterxml/jackson/databind/node/ContainerNode."<init>":(Lcom/fasterxml/jackson/databind/node/JsonNodeFactory;)V
    #2 = Class              #333          // java/util/LinkedHashMap
    #3 = Methodref          #2.#334       // java/util/LinkedHashMap."<init>":()V
    #4 = Fieldref           #7.#335       // com/fasterxml/jackson/databind/node/ObjectNode._children:Ljava/util/Map;
    #5 = Methodref          #336.#337     // com/fasterxml/jackson/core/JsonPointer.getMatchingProperty:()Ljava/lang/String;
    #6 = Methodref          #7.#338       // com/fasterxml/jackson/databind/node/ObjectNode.get:(Ljava/lang/String;)Lcom/fasterxml/jackson/databind/JsonNode;
    #7 = Class              #339          // com/fasterxml/jackson/databind/node/ObjectNode
    #8 = Fieldref           #7.#340       // com/fasterxml/jackson/databind/node/ObjectNode._nodeFactory:Lcom/fasterxml/jackson/databind/node/JsonNodeFactory;
    #9 = Methodref          #7.#332       // com/fasterxml/jackson/databind/node/ObjectNode."<init>":(Lcom/fasterxml/jackson/databind/node/JsonNodeFactory;)V
   #10 = InterfaceMethodref #341.#342     // java/util/Map.entrySet:()Ljava/util/Set;
   #11 = InterfaceMethodref #343.#344     // java/util/Set.iterator:()Ljava/util/Iterator;
   #12 = InterfaceMethodref #345.#346     // java/util/Iterator.hasNext:()Z
   #13 = InterfaceMethodref #345.#347     // java/util/Iterator.next:()Ljava/lang/Object;
   #14 = Class              #348          // java/util/Map$Entry
   #15 = InterfaceMethodref #14.#349      // java/util/Map$Entry.getKey:()Ljava/lang/Object;
   #16 = InterfaceMethodref #14.#350      // java/util/Map$Entry.getValue:()Ljava/lang/Object;
   #17 = Class              #351          // com/fasterxml/jackson/databind/JsonNode
   #18 = Methodref          #17.#352      // com/fasterxml/jackson/databind/JsonNode.deepCopy:()Lcom/fasterxml/jackson/databind/JsonNode;
   #19 = InterfaceMethodref #341.#353     // java/util/Map.put:(Ljava/lang/Object;Ljava/lang/Object;)Ljava/lang/Object;
   #20 = InterfaceMethodref #341.#354     // java/util/Map.isEmpty:()Z
   #21 = Fieldref           #355.#356     // com/fasterxml/jackson/databind/node/JsonNodeType.OBJECT:Lcom/fasterxml/jackson/databind/node/JsonNodeType;
   #22 = Fieldref           #357.#358     // com/fasterxml/jackson/core/JsonToken.START_OBJECT:Lcom/fasterxml/jackson/core/JsonToken;
   #23 = InterfaceMethodref #341.#359     // java/util/Map.size:()I
   #24 = InterfaceMethodref #341.#360     // java/util/Map.values:()Ljava/util/Collection;
   #25 = InterfaceMethodref #361.#344     // java/util/Collection.iterator:()Ljava/util/Iterator;
   #26 = InterfaceMethodref #341.#362     // java/util/Map.get:(Ljava/lang/Object;)Ljava/lang/Object;
   #27 = InterfaceMethodref #341.#363     // java/util/Map.keySet:()Ljava/util/Set;
   #28 = Methodref          #364.#365     // com/fasterxml/jackson/databind/node/MissingNode.getInstance:()Lcom/fasterxml/jackson/databind/node/MissingNode;
   #29 = String             #366          // No value for property \'%s\' of `ObjectNode`
   #30 = Class              #367          // java/lang/Object
   #31 = Methodref          #7.#368       // com/fasterxml/jackson/databind/node/ObjectNode._reportRequiredViolation:(Ljava/lang/String;[Ljava/lang/Object;)Ljava/lang/Object;
   #32 = Class              #369          // java/lang/UnsupportedOperationException
   #33 = Class              #370          // java/lang/StringBuilder
   #34 = Methodref          #33.#334      // java/lang/StringBuilder."<init>":()V
   #35 = String             #371          // Property \'
   #36 = Methodref          #33.#372      // java/lang/StringBuilder.append:(Ljava/lang/String;)Ljava/lang/StringBuilder;
   #37 = String             #373          // \' has value that is not of type ObjectNode (but
   #38 = Methodref          #30.#374      // java/lang/Object.getClass:()Ljava/lang/Class;
   #39 = Methodref          #375.#376     // java/lang/Class.getName:()Ljava/lang/String;
   #40 = String             #377          // )
   #41 = Methodref          #33.#378      // java/lang/StringBuilder.toString:()Ljava/lang/String;
   #42 = Methodref          #32.#379      // java/lang/UnsupportedOperationException."<init>":(Ljava/lang/String;)V
   #43 = Methodref          #7.#380       // com/fasterxml/jackson/databind/node/ObjectNode.objectNode:()Lcom/fasterxml/jackson/databind/node/ObjectNode;
   #44 = Class              #381          // com/fasterxml/jackson/databind/node/ArrayNode
   #45 = String             #382          // \' has value that is not of type ArrayNode (but
   #46 = Methodref          #7.#383       // com/fasterxml/jackson/databind/node/ObjectNode.arrayNode:()Lcom/fasterxml/jackson/databind/node/ArrayNode;
   #47 = Methodref          #17.#384      // com/fasterxml/jackson/databind/JsonNode.equals:(Ljava/util/Comparator;Lcom/fasterxml/jackson/databind/JsonNode;)Z
   #48 = Methodref          #64.#385      // java/lang/String.equals:(Ljava/lang/Object;)Z
   #49 = Methodref          #17.#386      // com/fasterxml/jackson/databind/JsonNode.findValue:(Ljava/lang/String;)Lcom/fasterxml/jackson/databind/JsonNode;
   #50 = Class              #387          // java/util/ArrayList
   #51 = Methodref          #50.#334      // java/util/ArrayList."<init>":()V
   #52 = InterfaceMethodref #388.#389     // java/util/List.add:(Ljava/lang/Object;)Z
   #53 = Methodref          #17.#390      // com/fasterxml/jackson/databind/JsonNode.findValues:(Ljava/lang/String;Ljava/util/List;)Ljava/util/List;
   #54 = Methodref          #17.#391      // com/fasterxml/jackson/databind/JsonNode.asText:()Ljava/lang/String;
   #55 = Methodref          #17.#392      // com/fasterxml/jackson/databind/JsonNode.findValuesAsText:(Ljava/lang/String;Ljava/util/List;)Ljava/util/List;
   #56 = Methodref          #17.#393      // com/fasterxml/jackson/databind/JsonNode.findParent:(Ljava/lang/String;)Lcom/fasterxml/jackson/databind/JsonNode;
   #57 = Methodref          #17.#394      // com/fasterxml/jackson/databind/JsonNode.findParents:(Ljava/lang/String;Ljava/util/List;)Ljava/util/List;
   #58 = Fieldref           #395.#396     // com/fasterxml/jackson/databind/SerializationFeature.WRITE_EMPTY_JSON_ARRAYS:Lcom/fasterxml/jackson/databind/SerializationFeature;
   #59 = Methodref          #397.#398     // com/fasterxml/jackson/databind/SerializerProvider.isEnabled:(Lcom/fasterxml/jackson/databind/SerializationFeature;)Z
   #60 = Methodref          #399.#400     // com/fasterxml/jackson/core/JsonGenerator.writeStartObject:(Ljava/lang/Object;)V
   #61 = Class              #401          // com/fasterxml/jackson/databind/node/BaseJsonNode
   #62 = Methodref          #61.#402      // com/fasterxml/jackson/databind/node/BaseJsonNode.isArray:()Z
   #63 = Methodref          #61.#403      // com/fasterxml/jackson/databind/node/BaseJsonNode.isEmpty:(Lcom/fasterxml/jackson/databind/SerializerProvider;)Z
   #64 = Class              #404          // java/lang/String
   #65 = Methodref          #399.#405     // com/fasterxml/jackson/core/JsonGenerator.writeFieldName:(Ljava/lang/String;)V
   #66 = Methodref          #61.#406      // com/fasterxml/jackson/databind/node/BaseJsonNode.serialize:(Lcom/fasterxml/jackson/core/JsonGenerator;Lcom/fasterxml/jackson/databind/SerializerProvider;)V
   #67 = Methodref          #399.#407     // com/fasterxml/jackson/core/JsonGenerator.writeEndObject:()V
   #68 = Methodref          #408.#409     // com/fasterxml/jackson/databind/jsontype/TypeSerializer.typeId:(Ljava/lang/Object;Lcom/fasterxml/jackson/core/JsonToken;)Lcom/fasterxml/jackson/core/type/WritableTypeId;
   #69 = Methodref          #408.#410     // com/fasterxml/jackson/databind/jsontype/TypeSerializer.writeTypePrefix:(Lcom/fasterxml/jackson/core/JsonGenerator;Lcom/fasterxml/jackson/core/type/WritableTypeId;)Lcom/fasterxml/jackson/core/type/WritableTypeId;
   #70 = Methodref          #408.#411     // com/fasterxml/jackson/databind/jsontype/TypeSerializer.writeTypeSuffix:(Lcom/fasterxml/jackson/core/JsonGenerator;Lcom/fasterxml/jackson/core/type/WritableTypeId;)Lcom/fasterxml/jackson/core/type/WritableTypeId;
   #71 = Methodref          #7.#412       // com/fasterxml/jackson/databind/node/ObjectNode.nullNode:()Lcom/fasterxml/jackson/databind/node/NullNode;
   #72 = InterfaceMethodref #341.#413     // java/util/Map.putAll:(Ljava/util/Map;)V
   #73 = InterfaceMethodref #341.#414     // java/util/Map.remove:(Ljava/lang/Object;)Ljava/lang/Object;
   #74 = InterfaceMethodref #343.#415     // java/util/Set.removeAll:(Ljava/util/Collection;)Z
   #75 = InterfaceMethodref #341.#416     // java/util/Map.putIfAbsent:(Ljava/lang/Object;Ljava/lang/Object;)Ljava/lang/Object;
   #76 = InterfaceMethodref #341.#417     // java/util/Map.clear:()V
   #77 = Methodref          #7.#418       // com/fasterxml/jackson/databind/node/ObjectNode.setAll:(Ljava/util/Map;)Lcom/fasterxml/jackson/databind/JsonNode;
   #78 = Methodref          #7.#419       // com/fasterxml/jackson/databind/node/ObjectNode.setAll:(Lcom/fasterxml/jackson/databind/node/ObjectNode;)Lcom/fasterxml/jackson/databind/JsonNode;
   #79 = InterfaceMethodref #343.#420     // java/util/Set.retainAll:(Ljava/util/Collection;)Z
   #80 = Methodref          #421.#422     // java/util/Arrays.asList:([Ljava/lang/Object;)Ljava/util/List;
   #81 = Methodref          #7.#423       // com/fasterxml/jackson/databind/node/ObjectNode.retain:(Ljava/util/Collection;)Lcom/fasterxml/jackson/databind/node/ObjectNode;
   #82 = Methodref          #7.#424       // com/fasterxml/jackson/databind/node/ObjectNode._put:(Ljava/lang/String;Lcom/fasterxml/jackson/databind/JsonNode;)Lcom/fasterxml/jackson/databind/node/ObjectNode;
   #83 = Methodref          #7.#425       // com/fasterxml/jackson/databind/node/ObjectNode.pojoNode:(Ljava/lang/Object;)Lcom/fasterxml/jackson/databind/node/ValueNode;
   #84 = Methodref          #7.#426       // com/fasterxml/jackson/databind/node/ObjectNode.rawValueNode:(Lcom/fasterxml/jackson/databind/util/RawValue;)Lcom/fasterxml/jackson/databind/node/ValueNode;
   #85 = Methodref          #7.#427       // com/fasterxml/jackson/databind/node/ObjectNode.numberNode:(S)Lcom/fasterxml/jackson/databind/node/NumericNode;
   #86 = Methodref          #428.#429     // java/lang/Short.shortValue:()S
   #87 = Methodref          #7.#430       // com/fasterxml/jackson/databind/node/ObjectNode.numberNode:(I)Lcom/fasterxml/jackson/databind/node/NumericNode;
   #88 = Methodref          #431.#432     // java/lang/Integer.intValue:()I
   #89 = Methodref          #7.#433       // com/fasterxml/jackson/databind/node/ObjectNode.numberNode:(J)Lcom/fasterxml/jackson/databind/node/NumericNode;
   #90 = Methodref          #434.#435     // java/lang/Long.longValue:()J
   #91 = Methodref          #7.#436       // com/fasterxml/jackson/databind/node/ObjectNode.numberNode:(F)Lcom/fasterxml/jackson/databind/node/NumericNode;
   #92 = Methodref          #437.#438     // java/lang/Float.floatValue:()F
   #93 = Methodref          #7.#439       // com/fasterxml/jackson/databind/node/ObjectNode.numberNode:(D)Lcom/fasterxml/jackson/databind/node/NumericNode;
   #94 = Methodref          #440.#441     // java/lang/Double.doubleValue:()D
   #95 = Methodref          #7.#442       // com/fasterxml/jackson/databind/node/ObjectNode.numberNode:(Ljava/math/BigDecimal;)Lcom/fasterxml/jackson/databind/node/ValueNode;
   #96 = Methodref          #7.#443       // com/fasterxml/jackson/databind/node/ObjectNode.numberNode:(Ljava/math/BigInteger;)Lcom/fasterxml/jackson/databind/node/ValueNode;
   #97 = Methodref          #7.#444       // com/fasterxml/jackson/databind/node/ObjectNode.textNode:(Ljava/lang/String;)Lcom/fasterxml/jackson/databind/node/TextNode;
   #98 = Methodref          #7.#445       // com/fasterxml/jackson/databind/node/ObjectNode.booleanNode:(Z)Lcom/fasterxml/jackson/databind/node/BooleanNode;
   #99 = Methodref          #446.#447     // java/lang/Boolean.booleanValue:()Z
  #100 = Methodref          #7.#448       // com/fasterxml/jackson/databind/node/ObjectNode.binaryNode:([B)Lcom/fasterxml/jackson/databind/node/BinaryNode;
  #101 = Methodref          #7.#449       // com/fasterxml/jackson/databind/node/ObjectNode._childrenEqual:(Lcom/fasterxml/jackson/databind/node/ObjectNode;)Z
  #102 = InterfaceMethodref #341.#385     // java/util/Map.equals:(Ljava/lang/Object;)Z
  #103 = InterfaceMethodref #341.#450     // java/util/Map.hashCode:()I
  #104 = Methodref          #7.#451       // com/fasterxml/jackson/databind/node/ObjectNode.removeAll:()Lcom/fasterxml/jackson/databind/node/ObjectNode;
  #105 = Methodref          #7.#452       // com/fasterxml/jackson/databind/node/ObjectNode.withArray:(Ljava/lang/String;)Lcom/fasterxml/jackson/databind/node/ArrayNode;
  #106 = Methodref          #7.#453       // com/fasterxml/jackson/databind/node/ObjectNode.with:(Ljava/lang/String;)Lcom/fasterxml/jackson/databind/node/ObjectNode;
  #107 = Methodref          #7.#454       // com/fasterxml/jackson/databind/node/ObjectNode.findParent:(Ljava/lang/String;)Lcom/fasterxml/jackson/databind/node/ObjectNode;
  #108 = Methodref          #7.#455       // com/fasterxml/jackson/databind/node/ObjectNode.deepCopy:()Lcom/fasterxml/jackson/databind/node/ObjectNode;
  #109 = Methodref          #7.#456       // com/fasterxml/jackson/databind/node/ObjectNode.path:(I)Lcom/fasterxml/jackson/databind/JsonNode;
  #110 = Methodref          #7.#457       // com/fasterxml/jackson/databind/node/ObjectNode.path:(Ljava/lang/String;)Lcom/fasterxml/jackson/databind/JsonNode;
  #111 = Methodref          #7.#458       // com/fasterxml/jackson/databind/node/ObjectNode.get:(I)Lcom/fasterxml/jackson/databind/JsonNode;
  #112 = Class              #459          // com/fasterxml/jackson/databind/node/ContainerNode
  #113 = Class              #460          // java/io/Serializable
  #114 = Utf8               serialVersionUID
  #115 = Utf8               J
  #116 = Utf8               ConstantValue
  #117 = Long               1l
  #119 = Utf8               _children
  #120 = Utf8               Ljava/util/Map;
  #121 = Utf8               Signature
  #122 = Utf8               Ljava/util/Map<Ljava/lang/String;Lcom/fasterxml/jackson/databind/JsonNode;>;
  #123 = Utf8               <init>
  #124 = Utf8               (Lcom/fasterxml/jackson/databind/node/JsonNodeFactory;)V
  #125 = Utf8               Code
  #126 = Utf8               LineNumberTable
  #127 = Utf8               LocalVariableTable
  #128 = Utf8               this
  #129 = Utf8               Lcom/fasterxml/jackson/databind/node/ObjectNode;
  #130 = Utf8               nc
  #131 = Utf8               Lcom/fasterxml/jackson/databind/node/JsonNodeFactory;
  #132 = Utf8               (Lcom/fasterxml/jackson/databind/node/JsonNodeFactory;Ljava/util/Map;)V
  #133 = Utf8               kids
  #134 = Utf8               LocalVariableTypeTable
  #135 = Utf8               (Lcom/fasterxml/jackson/databind/node/JsonNodeFactory;Ljava/util/Map<Ljava/lang/String;Lcom/fasterxml/jackson/databind/JsonNode;>;)V
  #136 = Utf8               _at
  #137 = Utf8               (Lcom/fasterxml/jackson/core/JsonPointer;)Lcom/fasterxml/jackson/databind/JsonNode;
  #138 = Utf8               ptr
  #139 = Utf8               Lcom/fasterxml/jackson/core/JsonPointer;
  #140 = Utf8               deepCopy
  #141 = Utf8               ()Lcom/fasterxml/jackson/databind/node/ObjectNode;
  #142 = Utf8               entry
  #143 = Utf8               Entry
  #144 = Utf8               InnerClasses
  #145 = Utf8               Ljava/util/Map$Entry;
  #146 = Utf8               ret
  #147 = Utf8               Ljava/util/Map$Entry<Ljava/lang/String;Lcom/fasterxml/jackson/databind/JsonNode;>;
  #148 = Utf8               StackMapTable
  #149 = Class              #339          // com/fasterxml/jackson/databind/node/ObjectNode
  #150 = Class              #461          // java/util/Iterator
  #151 = Utf8               isEmpty
  #152 = Utf8               (Lcom/fasterxml/jackson/databind/SerializerProvider;)Z
  #153 = Utf8               serializers
  #154 = Utf8               Lcom/fasterxml/jackson/databind/SerializerProvider;
  #155 = Utf8               getNodeType
  #156 = Utf8               ()Lcom/fasterxml/jackson/databind/node/JsonNodeType;
  #157 = Utf8               isObject
  #158 = Utf8               ()Z
  #159 = Utf8               asToken
  #160 = Utf8               ()Lcom/fasterxml/jackson/core/JsonToken;
  #161 = Utf8               size
  #162 = Utf8               ()I
  #163 = Utf8               elements
  #164 = Utf8               ()Ljava/util/Iterator;
  #165 = Utf8               ()Ljava/util/Iterator<Lcom/fasterxml/jackson/databind/JsonNode;>;
  #166 = Utf8               get
  #167 = Utf8               (I)Lcom/fasterxml/jackson/databind/JsonNode;
  #168 = Utf8               index
  #169 = Utf8               I
  #170 = Utf8               (Ljava/lang/String;)Lcom/fasterxml/jackson/databind/JsonNode;
  #171 = Utf8               propertyName
  #172 = Utf8               Ljava/lang/String;
  #173 = Utf8               fieldNames
  #174 = Utf8               ()Ljava/util/Iterator<Ljava/lang/String;>;
  #175 = Utf8               path
  #176 = Utf8               n
  #177 = Utf8               Lcom/fasterxml/jackson/databind/JsonNode;
  #178 = Class              #351          // com/fasterxml/jackson/databind/JsonNode
  #179 = Utf8               required
  #180 = Utf8               fields
  #181 = Utf8               ()Ljava/util/Iterator<Ljava/util/Map$Entry<Ljava/lang/String;Lcom/fasterxml/jackson/databind/JsonNode;>;>;
  #182 = Utf8               with
  #183 = Utf8               (Ljava/lang/String;)Lcom/fasterxml/jackson/databind/node/ObjectNode;
  #184 = Utf8               result
  #185 = Utf8               withArray
  #186 = Utf8               (Ljava/lang/String;)Lcom/fasterxml/jackson/databind/node/ArrayNode;
  #187 = Utf8               Lcom/fasterxml/jackson/databind/node/ArrayNode;
  #188 = Utf8               equals
  #189 = Utf8               (Ljava/util/Comparator;Lcom/fasterxml/jackson/databind/JsonNode;)Z
  #190 = Utf8               v2
  #191 = Utf8               comparator
  #192 = Utf8               Ljava/util/Comparator;
  #193 = Utf8               o
  #194 = Utf8               other
  #195 = Utf8               m1
  #196 = Utf8               m2
  #197 = Utf8               len
  #198 = Utf8               Ljava/util/Comparator<Lcom/fasterxml/jackson/databind/JsonNode;>;
  #199 = Class              #462          // java/util/Comparator
  #200 = Class              #463          // java/util/Map
  #201 = Class              #348          // java/util/Map$Entry
  #202 = Utf8               (Ljava/util/Comparator<Lcom/fasterxml/jackson/databind/JsonNode;>;Lcom/fasterxml/jackson/databind/JsonNode;)Z
  #203 = Utf8               findValue
  #204 = Utf8               value
  #205 = Utf8               findValues
  #206 = Utf8               (Ljava/lang/String;Ljava/util/List;)Ljava/util/List;
  #207 = Utf8               foundSoFar
  #208 = Utf8               Ljava/util/List;
  #209 = Utf8               Ljava/util/List<Lcom/fasterxml/jackson/databind/JsonNode;>;
  #210 = Utf8               (Ljava/lang/String;Ljava/util/List<Lcom/fasterxml/jackson/databind/JsonNode;>;)Ljava/util/List<Lcom/fasterxml/jackson/databind/JsonNode;>;
  #211 = Utf8               findValuesAsText
  #212 = Utf8               Ljava/util/List<Ljava/lang/String;>;
  #213 = Utf8               (Ljava/lang/String;Ljava/util/List<Ljava/lang/String;>;)Ljava/util/List<Ljava/lang/String;>;
  #214 = Utf8               findParent
  #215 = Utf8               findParents
  #216 = Utf8               serialize
  #217 = Utf8               (Lcom/fasterxml/jackson/core/JsonGenerator;Lcom/fasterxml/jackson/databind/SerializerProvider;)V
  #218 = Utf8               Lcom/fasterxml/jackson/databind/node/BaseJsonNode;
  #219 = Utf8               en
  #220 = Utf8               g
  #221 = Utf8               Lcom/fasterxml/jackson/core/JsonGenerator;
  #222 = Utf8               provider
  #223 = Utf8               trimEmptyArray
  #224 = Utf8               Z
  #225 = Class              #401          // com/fasterxml/jackson/databind/node/BaseJsonNode
  #226 = Utf8               Exceptions
  #227 = Class              #464          // java/io/IOException
  #228 = Utf8               serializeWithType
  #229 = Utf8               (Lcom/fasterxml/jackson/core/JsonGenerator;Lcom/fasterxml/jackson/databind/SerializerProvider;Lcom/fasterxml/jackson/databind/jsontype/TypeSerializer;)V
  #230 = Utf8               typeSer
  #231 = Utf8               Lcom/fasterxml/jackson/databind/jsontype/TypeSerializer;
  #232 = Utf8               typeIdDef
  #233 = Utf8               Lcom/fasterxml/jackson/core/type/WritableTypeId;
  #234 = Class              #465          // com/fasterxml/jackson/core/type/WritableTypeId
  #235 = Utf8               set
  #236 = Utf8               (Ljava/lang/String;Lcom/fasterxml/jackson/databind/JsonNode;)Lcom/fasterxml/jackson/databind/JsonNode;
  #237 = Utf8               <T:Lcom/fasterxml/jackson/databind/JsonNode;>(Ljava/lang/String;Lcom/fasterxml/jackson/databind/JsonNode;)TT;
  #238 = Utf8               setAll
  #239 = Utf8               (Ljava/util/Map;)Lcom/fasterxml/jackson/databind/JsonNode;
  #240 = Utf8               properties
  #241 = Utf8               Ljava/util/Map$Entry<Ljava/lang/String;+Lcom/fasterxml/jackson/databind/JsonNode;>;
  #242 = Utf8               Ljava/util/Map<Ljava/lang/String;+Lcom/fasterxml/jackson/databind/JsonNode;>;
  #243 = Utf8               <T:Lcom/fasterxml/jackson/databind/JsonNode;>(Ljava/util/Map<Ljava/lang/String;+Lcom/fasterxml/jackson/databind/JsonNode;>;)TT;
  #244 = Utf8               (Lcom/fasterxml/jackson/databind/node/ObjectNode;)Lcom/fasterxml/jackson/databind/JsonNode;
  #245 = Utf8               <T:Lcom/fasterxml/jackson/databind/JsonNode;>(Lcom/fasterxml/jackson/databind/node/ObjectNode;)TT;
  #246 = Utf8               replace
  #247 = Utf8               without
  #248 = Utf8               <T:Lcom/fasterxml/jackson/databind/JsonNode;>(Ljava/lang/String;)TT;
  #249 = Utf8               (Ljava/util/Collection;)Lcom/fasterxml/jackson/databind/JsonNode;
  #250 = Utf8               propertyNames
  #251 = Utf8               Ljava/util/Collection;
  #252 = Utf8               Ljava/util/Collection<Ljava/lang/String;>;
  #253 = Utf8               <T:Lcom/fasterxml/jackson/databind/JsonNode;>(Ljava/util/Collection<Ljava/lang/String;>;)TT;
  #254 = Utf8               put
  #255 = Utf8               Deprecated
  #256 = Utf8               RuntimeVisibleAnnotations
  #257 = Utf8               Ljava/lang/Deprecated;
  #258 = Utf8               putIfAbsent
  #259 = Utf8               remove
  #260 = Utf8               (Ljava/util/Collection;)Lcom/fasterxml/jackson/databind/node/ObjectNode;
  #261 = Utf8               (Ljava/util/Collection<Ljava/lang/String;>;)Lcom/fasterxml/jackson/databind/node/ObjectNode;
  #262 = Utf8               removeAll
  #263 = Utf8               putAll
  #264 = Utf8               (Ljava/util/Map<Ljava/lang/String;+Lcom/fasterxml/jackson/databind/JsonNode;>;)Lcom/fasterxml/jackson/databind/JsonNode;
  #265 = Utf8               retain
  #266 = Utf8               ([Ljava/lang/String;)Lcom/fasterxml/jackson/databind/node/ObjectNode;
  #267 = Utf8               [Ljava/lang/String;
  #268 = Utf8               putArray
  #269 = Utf8               putObject
  #270 = Utf8               putPOJO
  #271 = Utf8               (Ljava/lang/String;Ljava/lang/Object;)Lcom/fasterxml/jackson/databind/node/ObjectNode;
  #272 = Utf8               pojo
  #273 = Utf8               Ljava/lang/Object;
  #274 = Utf8               putRawValue
  #275 = Utf8               (Ljava/lang/String;Lcom/fasterxml/jackson/databind/util/RawValue;)Lcom/fasterxml/jackson/databind/node/ObjectNode;
  #276 = Utf8               raw
  #277 = Utf8               Lcom/fasterxml/jackson/databind/util/RawValue;
  #278 = Utf8               putNull
  #279 = Utf8               (Ljava/lang/String;S)Lcom/fasterxml/jackson/databind/node/ObjectNode;
  #280 = Utf8               v
  #281 = Utf8               S
  #282 = Utf8               (Ljava/lang/String;Ljava/lang/Short;)Lcom/fasterxml/jackson/databind/node/ObjectNode;
  #283 = Utf8               fieldName
  #284 = Utf8               Ljava/lang/Short;
  #285 = Class              #404          // java/lang/String
  #286 = Class              #466          // java/lang/Short
  #287 = Utf8               (Ljava/lang/String;I)Lcom/fasterxml/jackson/databind/node/ObjectNode;
  #288 = Utf8               (Ljava/lang/String;Ljava/lang/Integer;)Lcom/fasterxml/jackson/databind/node/ObjectNode;
  #289 = Utf8               Ljava/lang/Integer;
  #290 = Class              #467          // java/lang/Integer
  #291 = Utf8               (Ljava/lang/String;J)Lcom/fasterxml/jackson/databind/node/ObjectNode;
  #292 = Utf8               (Ljava/lang/String;Ljava/lang/Long;)Lcom/fasterxml/jackson/databind/node/ObjectNode;
  #293 = Utf8               Ljava/lang/Long;
  #294 = Class              #468          // java/lang/Long
  #295 = Utf8               (Ljava/lang/String;F)Lcom/fasterxml/jackson/databind/node/ObjectNode;
  #296 = Utf8               F
  #297 = Utf8               (Ljava/lang/String;Ljava/lang/Float;)Lcom/fasterxml/jackson/databind/node/ObjectNode;
  #298 = Utf8               Ljava/lang/Float;
  #299 = Class              #469          // java/lang/Float
  #300 = Utf8               (Ljava/lang/String;D)Lcom/fasterxml/jackson/databind/node/ObjectNode;
  #301 = Utf8               D
  #302 = Utf8               (Ljava/lang/String;Ljava/lang/Double;)Lcom/fasterxml/jackson/databind/node/ObjectNode;
  #303 = Utf8               Ljava/lang/Double;
  #304 = Class              #470          // java/lang/Double
  #305 = Utf8               (Ljava/lang/String;Ljava/math/BigDecimal;)Lcom/fasterxml/jackson/databind/node/ObjectNode;
  #306 = Utf8               Ljava/math/BigDecimal;
  #307 = Class              #471          // java/math/BigDecimal
  #308 = Utf8               (Ljava/lang/String;Ljava/math/BigInteger;)Lcom/fasterxml/jackson/databind/node/ObjectNode;
  #309 = Utf8               Ljava/math/BigInteger;
  #310 = Class              #472          // java/math/BigInteger
  #311 = Utf8               (Ljava/lang/String;Ljava/lang/String;)Lcom/fasterxml/jackson/databind/node/ObjectNode;
  #312 = Utf8               (Ljava/lang/String;Z)Lcom/fasterxml/jackson/databind/node/ObjectNode;
  #313 = Utf8               (Ljava/lang/String;Ljava/lang/Boolean;)Lcom/fasterxml/jackson/databind/node/ObjectNode;
  #314 = Utf8               Ljava/lang/Boolean;
  #315 = Class              #473          // java/lang/Boolean
  #316 = Utf8               (Ljava/lang/String;[B)Lcom/fasterxml/jackson/databind/node/ObjectNode;
  #317 = Utf8               [B
  #318 = Class              #317          // "[B"
  #319 = Utf8               (Ljava/lang/Object;)Z
  #320 = Utf8               _childrenEqual
  #321 = Utf8               (Lcom/fasterxml/jackson/databind/node/ObjectNode;)Z
  #322 = Utf8               hashCode
  #323 = Utf8               _put
  #324 = Utf8               (Ljava/lang/String;Lcom/fasterxml/jackson/databind/JsonNode;)Lcom/fasterxml/jackson/databind/node/ObjectNode;
  #325 = Utf8               ()Lcom/fasterxml/jackson/databind/node/ContainerNode;
  #326 = Utf8               ()Lcom/fasterxml/jackson/databind/JsonNode;
  #327 = Utf8               (I)Lcom/fasterxml/jackson/core/TreeNode;
  #328 = Utf8               (Ljava/lang/String;)Lcom/fasterxml/jackson/core/TreeNode;
  #329 = Utf8               Lcom/fasterxml/jackson/databind/node/ContainerNode<Lcom/fasterxml/jackson/databind/node/ObjectNode;>;Ljava/io/Serializable;
  #330 = Utf8               SourceFile
  #331 = Utf8               ObjectNode.java
  #332 = NameAndType        #123:#124     // "<init>":(Lcom/fasterxml/jackson/databind/node/JsonNodeFactory;)V
  #333 = Utf8               java/util/LinkedHashMap
  #334 = NameAndType        #123:#474     // "<init>":()V
  #335 = NameAndType        #119:#120     // _children:Ljava/util/Map;
  #336 = Class              #475          // com/fasterxml/jackson/core/JsonPointer
  #337 = NameAndType        #476:#477     // getMatchingProperty:()Ljava/lang/String;
  #338 = NameAndType        #166:#170     // get:(Ljava/lang/String;)Lcom/fasterxml/jackson/databind/JsonNode;
  #339 = Utf8               com/fasterxml/jackson/databind/node/ObjectNode
  #340 = NameAndType        #478:#131     // _nodeFactory:Lcom/fasterxml/jackson/databind/node/JsonNodeFactory;
  #341 = Class              #463          // java/util/Map
  #342 = NameAndType        #479:#480     // entrySet:()Ljava/util/Set;
  #343 = Class              #481          // java/util/Set
  #344 = NameAndType        #482:#164     // iterator:()Ljava/util/Iterator;
  #345 = Class              #461          // java/util/Iterator
  #346 = NameAndType        #483:#158     // hasNext:()Z
  #347 = NameAndType        #484:#485     // next:()Ljava/lang/Object;
  #348 = Utf8               java/util/Map$Entry
  #349 = NameAndType        #486:#485     // getKey:()Ljava/lang/Object;
  #350 = NameAndType        #487:#485     // getValue:()Ljava/lang/Object;
  #351 = Utf8               com/fasterxml/jackson/databind/JsonNode
  #352 = NameAndType        #140:#326     // deepCopy:()Lcom/fasterxml/jackson/databind/JsonNode;
  #353 = NameAndType        #254:#488     // put:(Ljava/lang/Object;Ljava/lang/Object;)Ljava/lang/Object;
  #354 = NameAndType        #151:#158     // isEmpty:()Z
  #355 = Class              #489          // com/fasterxml/jackson/databind/node/JsonNodeType
  #356 = NameAndType        #490:#491     // OBJECT:Lcom/fasterxml/jackson/databind/node/JsonNodeType;
  #357 = Class              #492          // com/fasterxml/jackson/core/JsonToken
  #358 = NameAndType        #493:#494     // START_OBJECT:Lcom/fasterxml/jackson/core/JsonToken;
  #359 = NameAndType        #161:#162     // size:()I
  #360 = NameAndType        #495:#496     // values:()Ljava/util/Collection;
  #361 = Class              #497          // java/util/Collection
  #362 = NameAndType        #166:#498     // get:(Ljava/lang/Object;)Ljava/lang/Object;
  #363 = NameAndType        #499:#480     // keySet:()Ljava/util/Set;
  #364 = Class              #500          // com/fasterxml/jackson/databind/node/MissingNode
  #365 = NameAndType        #501:#502     // getInstance:()Lcom/fasterxml/jackson/databind/node/MissingNode;
  #366 = Utf8               No value for property \'%s\' of `ObjectNode`
  #367 = Utf8               java/lang/Object
  #368 = NameAndType        #503:#504     // _reportRequiredViolation:(Ljava/lang/String;[Ljava/lang/Object;)Ljava/lang/Object;
  #369 = Utf8               java/lang/UnsupportedOperationException
  #370 = Utf8               java/lang/StringBuilder
  #371 = Utf8               Property \'
  #372 = NameAndType        #505:#506     // append:(Ljava/lang/String;)Ljava/lang/StringBuilder;
  #373 = Utf8               \' has value that is not of type ObjectNode (but
  #374 = NameAndType        #507:#508     // getClass:()Ljava/lang/Class;
  #375 = Class              #509          // java/lang/Class
  #376 = NameAndType        #510:#477     // getName:()Ljava/lang/String;
  #377 = Utf8               )
  #378 = NameAndType        #511:#477     // toString:()Ljava/lang/String;
  #379 = NameAndType        #123:#512     // "<init>":(Ljava/lang/String;)V
  #380 = NameAndType        #513:#141     // objectNode:()Lcom/fasterxml/jackson/databind/node/ObjectNode;
  #381 = Utf8               com/fasterxml/jackson/databind/node/ArrayNode
  #382 = Utf8               \' has value that is not of type ArrayNode (but
  #383 = NameAndType        #514:#515     // arrayNode:()Lcom/fasterxml/jackson/databind/node/ArrayNode;
  #384 = NameAndType        #188:#189     // equals:(Ljava/util/Comparator;Lcom/fasterxml/jackson/databind/JsonNode;)Z
  #385 = NameAndType        #188:#319     // equals:(Ljava/lang/Object;)Z
  #386 = NameAndType        #203:#170     // findValue:(Ljava/lang/String;)Lcom/fasterxml/jackson/databind/JsonNode;
  #387 = Utf8               java/util/ArrayList
  #388 = Class              #516          // java/util/List
  #389 = NameAndType        #517:#319     // add:(Ljava/lang/Object;)Z
  #390 = NameAndType        #205:#206     // findValues:(Ljava/lang/String;Ljava/util/List;)Ljava/util/List;
  #391 = NameAndType        #518:#477     // asText:()Ljava/lang/String;
  #392 = NameAndType        #211:#206     // findValuesAsText:(Ljava/lang/String;Ljava/util/List;)Ljava/util/List;
  #393 = NameAndType        #214:#170     // findParent:(Ljava/lang/String;)Lcom/fasterxml/jackson/databind/JsonNode;
  #394 = NameAndType        #215:#206     // findParents:(Ljava/lang/String;Ljava/util/List;)Ljava/util/List;
  #395 = Class              #519          // com/fasterxml/jackson/databind/SerializationFeature
  #396 = NameAndType        #520:#521     // WRITE_EMPTY_JSON_ARRAYS:Lcom/fasterxml/jackson/databind/SerializationFeature;
  #397 = Class              #522          // com/fasterxml/jackson/databind/SerializerProvider
  #398 = NameAndType        #523:#524     // isEnabled:(Lcom/fasterxml/jackson/databind/SerializationFeature;)Z
  #399 = Class              #525          // com/fasterxml/jackson/core/JsonGenerator
  #400 = NameAndType        #526:#527     // writeStartObject:(Ljava/lang/Object;)V
  #401 = Utf8               com/fasterxml/jackson/databind/node/BaseJsonNode
  #402 = NameAndType        #528:#158     // isArray:()Z
  #403 = NameAndType        #151:#152     // isEmpty:(Lcom/fasterxml/jackson/databind/SerializerProvider;)Z
  #404 = Utf8               java/lang/String
  #405 = NameAndType        #529:#512     // writeFieldName:(Ljava/lang/String;)V
  #406 = NameAndType        #216:#217     // serialize:(Lcom/fasterxml/jackson/core/JsonGenerator;Lcom/fasterxml/jackson/databind/SerializerProvider;)V
  #407 = NameAndType        #530:#474     // writeEndObject:()V
  #408 = Class              #531          // com/fasterxml/jackson/databind/jsontype/TypeSerializer
  #409 = NameAndType        #532:#533     // typeId:(Ljava/lang/Object;Lcom/fasterxml/jackson/core/JsonToken;)Lcom/fasterxml/jackson/core/type/WritableTypeId;
  #410 = NameAndType        #534:#535     // writeTypePrefix:(Lcom/fasterxml/jackson/core/JsonGenerator;Lcom/fasterxml/jackson/core/type/WritableTypeId;)Lcom/fasterxml/jackson/core/type/WritableTypeId;
  #411 = NameAndType        #536:#535     // writeTypeSuffix:(Lcom/fasterxml/jackson/core/JsonGenerator;Lcom/fasterxml/jackson/core/type/WritableTypeId;)Lcom/fasterxml/jackson/core/type/WritableTypeId;
  #412 = NameAndType        #537:#538     // nullNode:()Lcom/fasterxml/jackson/databind/node/NullNode;
  #413 = NameAndType        #263:#539     // putAll:(Ljava/util/Map;)V
  #414 = NameAndType        #259:#498     // remove:(Ljava/lang/Object;)Ljava/lang/Object;
  #415 = NameAndType        #262:#540     // removeAll:(Ljava/util/Collection;)Z
  #416 = NameAndType        #258:#488     // putIfAbsent:(Ljava/lang/Object;Ljava/lang/Object;)Ljava/lang/Object;
  #417 = NameAndType        #541:#474     // clear:()V
  #418 = NameAndType        #238:#239     // setAll:(Ljava/util/Map;)Lcom/fasterxml/jackson/databind/JsonNode;
  #419 = NameAndType        #238:#244     // setAll:(Lcom/fasterxml/jackson/databind/node/ObjectNode;)Lcom/fasterxml/jackson/databind/JsonNode;
  #420 = NameAndType        #542:#540     // retainAll:(Ljava/util/Collection;)Z
  #421 = Class              #543          // java/util/Arrays
  #422 = NameAndType        #544:#545     // asList:([Ljava/lang/Object;)Ljava/util/List;
  #423 = NameAndType        #265:#260     // retain:(Ljava/util/Collection;)Lcom/fasterxml/jackson/databind/node/ObjectNode;
  #424 = NameAndType        #323:#324     // _put:(Ljava/lang/String;Lcom/fasterxml/jackson/databind/JsonNode;)Lcom/fasterxml/jackson/databind/node/ObjectNode;
  #425 = NameAndType        #546:#547     // pojoNode:(Ljava/lang/Object;)Lcom/fasterxml/jackson/databind/node/ValueNode;
  #426 = NameAndType        #548:#549     // rawValueNode:(Lcom/fasterxml/jackson/databind/util/RawValue;)Lcom/fasterxml/jackson/databind/node/ValueNode;
  #427 = NameAndType        #550:#551     // numberNode:(S)Lcom/fasterxml/jackson/databind/node/NumericNode;
  #428 = Class              #466          // java/lang/Short
  #429 = NameAndType        #552:#553     // shortValue:()S
  #430 = NameAndType        #550:#554     // numberNode:(I)Lcom/fasterxml/jackson/databind/node/NumericNode;
  #431 = Class              #467          // java/lang/Integer
  #432 = NameAndType        #555:#162     // intValue:()I
  #433 = NameAndType        #550:#556     // numberNode:(J)Lcom/fasterxml/jackson/databind/node/NumericNode;
  #434 = Class              #468          // java/lang/Long
  #435 = NameAndType        #557:#558     // longValue:()J
  #436 = NameAndType        #550:#559     // numberNode:(F)Lcom/fasterxml/jackson/databind/node/NumericNode;
  #437 = Class              #469          // java/lang/Float
  #438 = NameAndType        #560:#561     // floatValue:()F
  #439 = NameAndType        #550:#562     // numberNode:(D)Lcom/fasterxml/jackson/databind/node/NumericNode;
  #440 = Class              #470          // java/lang/Double
  #441 = NameAndType        #563:#564     // doubleValue:()D
  #442 = NameAndType        #550:#565     // numberNode:(Ljava/math/BigDecimal;)Lcom/fasterxml/jackson/databind/node/ValueNode;
  #443 = NameAndType        #550:#566     // numberNode:(Ljava/math/BigInteger;)Lcom/fasterxml/jackson/databind/node/ValueNode;
  #444 = NameAndType        #567:#568     // textNode:(Ljava/lang/String;)Lcom/fasterxml/jackson/databind/node/TextNode;
  #445 = NameAndType        #569:#570     // booleanNode:(Z)Lcom/fasterxml/jackson/databind/node/BooleanNode;
  #446 = Class              #473          // java/lang/Boolean
  #447 = NameAndType        #571:#158     // booleanValue:()Z
  #448 = NameAndType        #572:#573     // binaryNode:([B)Lcom/fasterxml/jackson/databind/node/BinaryNode;
  #449 = NameAndType        #320:#321     // _childrenEqual:(Lcom/fasterxml/jackson/databind/node/ObjectNode;)Z
  #450 = NameAndType        #322:#162     // hashCode:()I
  #451 = NameAndType        #262:#141     // removeAll:()Lcom/fasterxml/jackson/databind/node/ObjectNode;
  #452 = NameAndType        #185:#186     // withArray:(Ljava/lang/String;)Lcom/fasterxml/jackson/databind/node/ArrayNode;
  #453 = NameAndType        #182:#183     // with:(Ljava/lang/String;)Lcom/fasterxml/jackson/databind/node/ObjectNode;
  #454 = NameAndType        #214:#183     // findParent:(Ljava/lang/String;)Lcom/fasterxml/jackson/databind/node/ObjectNode;
  #455 = NameAndType        #140:#141     // deepCopy:()Lcom/fasterxml/jackson/databind/node/ObjectNode;
  #456 = NameAndType        #175:#167     // path:(I)Lcom/fasterxml/jackson/databind/JsonNode;
  #457 = NameAndType        #175:#170     // path:(Ljava/lang/String;)Lcom/fasterxml/jackson/databind/JsonNode;
  #458 = NameAndType        #166:#167     // get:(I)Lcom/fasterxml/jackson/databind/JsonNode;
  #459 = Utf8               com/fasterxml/jackson/databind/node/ContainerNode
  #460 = Utf8               java/io/Serializable
  #461 = Utf8               java/util/Iterator
  #462 = Utf8               java/util/Comparator
  #463 = Utf8               java/util/Map
  #464 = Utf8               java/io/IOException
  #465 = Utf8               com/fasterxml/jackson/core/type/WritableTypeId
  #466 = Utf8               java/lang/Short
  #467 = Utf8               java/lang/Integer
  #468 = Utf8               java/lang/Long
  #469 = Utf8               java/lang/Float
  #470 = Utf8               java/lang/Double
  #471 = Utf8               java/math/BigDecimal
  #472 = Utf8               java/math/BigInteger
  #473 = Utf8               java/lang/Boolean
  #474 = Utf8               ()V
  #475 = Utf8               com/fasterxml/jackson/core/JsonPointer
  #476 = Utf8               getMatchingProperty
  #477 = Utf8               ()Ljava/lang/String;
  #478 = Utf8               _nodeFactory
  #479 = Utf8               entrySet
  #480 = Utf8               ()Ljava/util/Set;
  #481 = Utf8               java/util/Set
  #482 = Utf8               iterator
  #483 = Utf8               hasNext
  #484 = Utf8               next
  #485 = Utf8               ()Ljava/lang/Object;
  #486 = Utf8               getKey
  #487 = Utf8               getValue
  #488 = Utf8               (Ljava/lang/Object;Ljava/lang/Object;)Ljava/lang/Object;
  #489 = Utf8               com/fasterxml/jackson/databind/node/JsonNodeType
  #490 = Utf8               OBJECT
  #491 = Utf8               Lcom/fasterxml/jackson/databind/node/JsonNodeType;
  #492 = Utf8               com/fasterxml/jackson/core/JsonToken
  #493 = Utf8               START_OBJECT
  #494 = Utf8               Lcom/fasterxml/jackson/core/JsonToken;
  #495 = Utf8               values
  #496 = Utf8               ()Ljava/util/Collection;
  #497 = Utf8               java/util/Collection
  #498 = Utf8               (Ljava/lang/Object;)Ljava/lang/Object;
  #499 = Utf8               keySet
  #500 = Utf8               com/fasterxml/jackson/databind/node/MissingNode
  #501 = Utf8               getInstance
  #502 = Utf8               ()Lcom/fasterxml/jackson/databind/node/MissingNode;
  #503 = Utf8               _reportRequiredViolation
  #504 = Utf8               (Ljava/lang/String;[Ljava/lang/Object;)Ljava/lang/Object;
  #505 = Utf8               append
  #506 = Utf8               (Ljava/lang/String;)Ljava/lang/StringBuilder;
  #507 = Utf8               getClass
  #508 = Utf8               ()Ljava/lang/Class;
  #509 = Utf8               java/lang/Class
  #510 = Utf8               getName
  #511 = Utf8               toString
  #512 = Utf8               (Ljava/lang/String;)V
  #513 = Utf8               objectNode
  #514 = Utf8               arrayNode
  #515 = Utf8               ()Lcom/fasterxml/jackson/databind/node/ArrayNode;
  #516 = Utf8               java/util/List
  #517 = Utf8               add
  #518 = Utf8               asText
  #519 = Utf8               com/fasterxml/jackson/databind/SerializationFeature
  #520 = Utf8               WRITE_EMPTY_JSON_ARRAYS
  #521 = Utf8               Lcom/fasterxml/jackson/databind/SerializationFeature;
  #522 = Utf8               com/fasterxml/jackson/databind/SerializerProvider
  #523 = Utf8               isEnabled
  #524 = Utf8               (Lcom/fasterxml/jackson/databind/SerializationFeature;)Z
  #525 = Utf8               com/fasterxml/jackson/core/JsonGenerator
  #526 = Utf8               writeStartObject
  #527 = Utf8               (Ljava/lang/Object;)V
  #528 = Utf8               isArray
  #529 = Utf8               writeFieldName
  #530 = Utf8               writeEndObject
  #531 = Utf8               com/fasterxml/jackson/databind/jsontype/TypeSerializer
  #532 = Utf8               typeId
  #533 = Utf8               (Ljava/lang/Object;Lcom/fasterxml/jackson/core/JsonToken;)Lcom/fasterxml/jackson/core/type/WritableTypeId;
  #534 = Utf8               writeTypePrefix
  #535 = Utf8               (Lcom/fasterxml/jackson/core/JsonGenerator;Lcom/fasterxml/jackson/core/type/WritableTypeId;)Lcom/fasterxml/jackson/core/type/WritableTypeId;
  #536 = Utf8               writeTypeSuffix
  #537 = Utf8               nullNode
  #538 = Utf8               ()Lcom/fasterxml/jackson/databind/node/NullNode;
  #539 = Utf8               (Ljava/util/Map;)V
  #540 = Utf8               (Ljava/util/Collection;)Z
  #541 = Utf8               clear
  #542 = Utf8               retainAll
  #543 = Utf8               java/util/Arrays
  #544 = Utf8               asList
  #545 = Utf8               ([Ljava/lang/Object;)Ljava/util/List;
  #546 = Utf8               pojoNode
  #547 = Utf8               (Ljava/lang/Object;)Lcom/fasterxml/jackson/databind/node/ValueNode;
  #548 = Utf8               rawValueNode
  #549 = Utf8               (Lcom/fasterxml/jackson/databind/util/RawValue;)Lcom/fasterxml/jackson/databind/node/ValueNode;
  #550 = Utf8               numberNode
  #551 = Utf8               (S)Lcom/fasterxml/jackson/databind/node/NumericNode;
  #552 = Utf8               shortValue
  #553 = Utf8               ()S
  #554 = Utf8               (I)Lcom/fasterxml/jackson/databind/node/NumericNode;
  #555 = Utf8               intValue
  #556 = Utf8               (J)Lcom/fasterxml/jackson/databind/node/NumericNode;
  #557 = Utf8               longValue
  #558 = Utf8               ()J
  #559 = Utf8               (F)Lcom/fasterxml/jackson/databind/node/NumericNode;
  #560 = Utf8               floatValue
  #561 = Utf8               ()F
  #562 = Utf8               (D)Lcom/fasterxml/jackson/databind/node/NumericNode;
  #563 = Utf8               doubleValue
  #564 = Utf8               ()D
  #565 = Utf8               (Ljava/math/BigDecimal;)Lcom/fasterxml/jackson/databind/node/ValueNode;
  #566 = Utf8               (Ljava/math/BigInteger;)Lcom/fasterxml/jackson/databind/node/ValueNode;
  #567 = Utf8               textNode
  #568 = Utf8               (Ljava/lang/String;)Lcom/fasterxml/jackson/databind/node/TextNode;
  #569 = Utf8               booleanNode
  #570 = Utf8               (Z)Lcom/fasterxml/jackson/databind/node/BooleanNode;
  #571 = Utf8               booleanValue
  #572 = Utf8               binaryNode
  #573 = Utf8               ([B)Lcom/fasterxml/jackson/databind/node/BinaryNode;
{
  private static final long serialVersionUID;
    descriptor: J
    flags: (0x001a) ACC_PRIVATE, ACC_STATIC, ACC_FINAL
    ConstantValue: long 1l

  protected final java.util.Map<java.lang.String, com.fasterxml.jackson.databind.JsonNode> _children;
    descriptor: Ljava/util/Map;
    flags: (0x0014) ACC_PROTECTED, ACC_FINAL
    Signature: #122                         // Ljava/util/Map<Ljava/lang/String;Lcom/fasterxml/jackson/databind/JsonNode;>;

  public com.fasterxml.jackson.databind.node.ObjectNode(com.fasterxml.jackson.databind.node.JsonNodeFactory);
    descriptor: (Lcom/fasterxml/jackson/databind/node/JsonNodeFactory;)V
    flags: (0x0001) ACC_PUBLIC
    Code:
      stack=3, locals=2, args_size=2
         0: aload_0
         1: aload_1
         2: invokespecial #1                  // Method com/fasterxml/jackson/databind/node/ContainerNode."<init>":(Lcom/fasterxml/jackson/databind/node/JsonNodeFactory;)V
         5: aload_0
         6: new           #2                  // class java/util/LinkedHashMap
         9: dup
        10: invokespecial #3                  // Method java/util/LinkedHashMap."<init>":()V
        13: putfield      #4                  // Field _children:Ljava/util/Map;
        16: return
      LineNumberTable:
        line 29: 0
        line 30: 5
        line 31: 16
      LocalVariableTable:
        Start  Length  Slot  Name   Signature
            0      17     0  this   Lcom/fasterxml/jackson/databind/node/ObjectNode;
            0      17     1    nc   Lcom/fasterxml/jackson/databind/node/JsonNodeFactory;

  public com.fasterxml.jackson.databind.node.ObjectNode(com.fasterxml.jackson.databind.node.JsonNodeFactory, java.util.Map<java.lang.String, com.fasterxml.jackson.databind.JsonNode>);
    descriptor: (Lcom/fasterxml/jackson/databind/node/JsonNodeFactory;Ljava/util/Map;)V
    flags: (0x0001) ACC_PUBLIC
    Code:
      stack=2, locals=3, args_size=3
         0: aload_0
         1: aload_1
         2: invokespecial #1                  // Method com/fasterxml/jackson/databind/node/ContainerNode."<init>":(Lcom/fasterxml/jackson/databind/node/JsonNodeFactory;)V
         5: aload_0
         6: aload_2
         7: putfield      #4                  // Field _children:Ljava/util/Map;
        10: return
      LineNumberTable:
        line 37: 0
        line 38: 5
        line 39: 10
      LocalVariableTable:
        Start  Length  Slot  Name   Signature
            0      11     0  this   Lcom/fasterxml/jackson/databind/node/ObjectNode;
            0      11     1    nc   Lcom/fasterxml/jackson/databind/node/JsonNodeFactory;
            0      11     2  kids   Ljava/util/Map;
      LocalVariableTypeTable:
        Start  Length  Slot  Name   Signature
            0      11     2  kids   Ljava/util/Map<Ljava/lang/String;Lcom/fasterxml/jackson/databind/JsonNode;>;
    Signature: #135                         // (Lcom/fasterxml/jackson/databind/node/JsonNodeFactory;Ljava/util/Map<Ljava/lang/String;Lcom/fasterxml/jackson/databind/JsonNode;>;)V

  protected com.fasterxml.jackson.databind.JsonNode _at(com.fasterxml.jackson.core.JsonPointer);
    descriptor: (Lcom/fasterxml/jackson/core/JsonPointer;)Lcom/fasterxml/jackson/databind/JsonNode;
    flags: (0x0004) ACC_PROTECTED
    Code:
      stack=2, locals=2, args_size=2
         0: aload_0
         1: aload_1
         2: invokevirtual #5                  // Method com/fasterxml/jackson/core/JsonPointer.getMatchingProperty:()Ljava/lang/String;
         5: invokevirtual #6                  // Method get:(Ljava/lang/String;)Lcom/fasterxml/jackson/databind/JsonNode;
         8: areturn
      LineNumberTable:
        line 43: 0
      LocalVariableTable:
        Start  Length  Slot  Name   Signature
            0       9     0  this   Lcom/fasterxml/jackson/databind/node/ObjectNode;
            0       9     1   ptr   Lcom/fasterxml/jackson/core/JsonPointer;

  public com.fasterxml.jackson.databind.node.ObjectNode deepCopy();
    descriptor: ()Lcom/fasterxml/jackson/databind/node/ObjectNode;
    flags: (0x0001) ACC_PUBLIC
    Code:
      stack=3, locals=4, args_size=1
         0: new           #7                  // class com/fasterxml/jackson/databind/node/ObjectNode
         3: dup
         4: aload_0
         5: getfield      #8                  // Field _nodeFactory:Lcom/fasterxml/jackson/databind/node/JsonNodeFactory;
         8: invokespecial #9                  // Method "<init>":(Lcom/fasterxml/jackson/databind/node/JsonNodeFactory;)V
        11: astore_1
        12: aload_0
        13: getfield      #4                  // Field _children:Ljava/util/Map;
        16: invokeinterface #10,  1           // InterfaceMethod java/util/Map.entrySet:()Ljava/util/Set;
        21: invokeinterface #11,  1           // InterfaceMethod java/util/Set.iterator:()Ljava/util/Iterator;
        26: astore_2
        27: aload_2
        28: invokeinterface #12,  1           // InterfaceMethod java/util/Iterator.hasNext:()Z
        33: ifeq          77
        36: aload_2
        37: invokeinterface #13,  1           // InterfaceMethod java/util/Iterator.next:()Ljava/lang/Object;
        42: checkcast     #14                 // class java/util/Map$Entry
        45: astore_3
        46: aload_1
        47: getfield      #4                  // Field _children:Ljava/util/Map;
        50: aload_3
        51: invokeinterface #15,  1           // InterfaceMethod java/util/Map$Entry.getKey:()Ljava/lang/Object;
        56: aload_3
        57: invokeinterface #16,  1           // InterfaceMethod java/util/Map$Entry.getValue:()Ljava/lang/Object;
        62: checkcast     #17                 // class com/fasterxml/jackson/databind/JsonNode
        65: invokevirtual #18                 // Method com/fasterxml/jackson/databind/JsonNode.deepCopy:()Lcom/fasterxml/jackson/databind/JsonNode;
        68: invokeinterface #19,  3           // InterfaceMethod java/util/Map.put:(Ljava/lang/Object;Ljava/lang/Object;)Ljava/lang/Object;
        73: pop
        74: goto          27
        77: aload_1
        78: areturn
      LineNumberTable:
        line 54: 0
        line 56: 12
        line 57: 46
        line 59: 77
      LocalVariableTable:
        Start  Length  Slot  Name   Signature
           46      28     3 entry   Ljava/util/Map$Entry;
            0      79     0  this   Lcom/fasterxml/jackson/databind/node/ObjectNode;
           12      67     1   ret   Lcom/fasterxml/jackson/databind/node/ObjectNode;
      LocalVariableTypeTable:
        Start  Length  Slot  Name   Signature
           46      28     3 entry   Ljava/util/Map$Entry<Ljava/lang/String;Lcom/fasterxml/jackson/databind/JsonNode;>;
      StackMapTable: number_of_entries = 2
        frame_type = 253 /* append */
          offset_delta = 27
          locals = [ class com/fasterxml/jackson/databind/node/ObjectNode, class java/util/Iterator ]
        frame_type = 250 /* chop */
          offset_delta = 49

  public boolean isEmpty(com.fasterxml.jackson.databind.SerializerProvider);
    descriptor: (Lcom/fasterxml/jackson/databind/SerializerProvider;)Z
    flags: (0x0001) ACC_PUBLIC
    Code:
      stack=1, locals=2, args_size=2
         0: aload_0
         1: getfield      #4                  // Field _children:Ljava/util/Map;
         4: invokeinterface #20,  1           // InterfaceMethod java/util/Map.isEmpty:()Z
         9: ireturn
      LineNumberTable:
        line 70: 0
      LocalVariableTable:
        Start  Length  Slot  Name   Signature
            0      10     0  this   Lcom/fasterxml/jackson/databind/node/ObjectNode;
            0      10     1 serializers   Lcom/fasterxml/jackson/databind/SerializerProvider;

  public com.fasterxml.jackson.databind.node.JsonNodeType getNodeType();
    descriptor: ()Lcom/fasterxml/jackson/databind/node/JsonNodeType;
    flags: (0x0001) ACC_PUBLIC
    Code:
      stack=1, locals=1, args_size=1
         0: getstatic     #21                 // Field com/fasterxml/jackson/databind/node/JsonNodeType.OBJECT:Lcom/fasterxml/jackson/databind/node/JsonNodeType;
         3: areturn
      LineNumberTable:
        line 81: 0
      LocalVariableTable:
        Start  Length  Slot  Name   Signature
            0       4     0  this   Lcom/fasterxml/jackson/databind/node/ObjectNode;

  public final boolean isObject();
    descriptor: ()Z
    flags: (0x0011) ACC_PUBLIC, ACC_FINAL
    Code:
      stack=1, locals=1, args_size=1
         0: iconst_1
         1: ireturn
      LineNumberTable:
        line 86: 0
      LocalVariableTable:
        Start  Length  Slot  Name   Signature
            0       2     0  this   Lcom/fasterxml/jackson/databind/node/ObjectNode;

  public com.fasterxml.jackson.core.JsonToken asToken();
    descriptor: ()Lcom/fasterxml/jackson/core/JsonToken;
    flags: (0x0001) ACC_PUBLIC
    Code:
      stack=1, locals=1, args_size=1
         0: getstatic     #22                 // Field com/fasterxml/jackson/core/JsonToken.START_OBJECT:Lcom/fasterxml/jackson/core/JsonToken;
         3: areturn
      LineNumberTable:
        line 89: 0
      LocalVariableTable:
        Start  Length  Slot  Name   Signature
            0       4     0  this   Lcom/fasterxml/jackson/databind/node/ObjectNode;

  public int size();
    descriptor: ()I
    flags: (0x0001) ACC_PUBLIC
    Code:
      stack=1, locals=1, args_size=1
         0: aload_0
         1: getfield      #4                  // Field _children:Ljava/util/Map;
         4: invokeinterface #23,  1           // InterfaceMethod java/util/Map.size:()I
         9: ireturn
      LineNumberTable:
        line 93: 0
      LocalVariableTable:
        Start  Length  Slot  Name   Signature
            0      10     0  this   Lcom/fasterxml/jackson/databind/node/ObjectNode;

  public boolean isEmpty();
    descriptor: ()Z
    flags: (0x0001) ACC_PUBLIC
    Code:
      stack=1, locals=1, args_size=1
         0: aload_0
         1: getfield      #4                  // Field _children:Ljava/util/Map;
         4: invokeinterface #20,  1           // InterfaceMethod java/util/Map.isEmpty:()Z
         9: ireturn
      LineNumberTable:
        line 97: 0
      LocalVariableTable:
        Start  Length  Slot  Name   Signature
            0      10     0  this   Lcom/fasterxml/jackson/databind/node/ObjectNode;

  public java.util.Iterator<com.fasterxml.jackson.databind.JsonNode> elements();
    descriptor: ()Ljava/util/Iterator;
    flags: (0x0001) ACC_PUBLIC
    Code:
      stack=1, locals=1, args_size=1
         0: aload_0
         1: getfield      #4                  // Field _children:Ljava/util/Map;
         4: invokeinterface #24,  1           // InterfaceMethod java/util/Map.values:()Ljava/util/Collection;
         9: invokeinterface #25,  1           // InterfaceMethod java/util/Collection.iterator:()Ljava/util/Iterator;
        14: areturn
      LineNumberTable:
        line 101: 0
      LocalVariableTable:
        Start  Length  Slot  Name   Signature
            0      15     0  this   Lcom/fasterxml/jackson/databind/node/ObjectNode;
    Signature: #165                         // ()Ljava/util/Iterator<Lcom/fasterxml/jackson/databind/JsonNode;>;

  public com.fasterxml.jackson.databind.JsonNode get(int);
    descriptor: (I)Lcom/fasterxml/jackson/databind/JsonNode;
    flags: (0x0001) ACC_PUBLIC
    Code:
      stack=1, locals=2, args_size=2
         0: aconst_null
         1: areturn
      LineNumberTable:
        line 105: 0
      LocalVariableTable:
        Start  Length  Slot  Name   Signature
            0       2     0  this   Lcom/fasterxml/jackson/databind/node/ObjectNode;
            0       2     1 index   I

  public com.fasterxml.jackson.databind.JsonNode get(java.lang.String);
    descriptor: (Ljava/lang/String;)Lcom/fasterxml/jackson/databind/JsonNode;
    flags: (0x0001) ACC_PUBLIC
    Code:
      stack=2, locals=2, args_size=2
         0: aload_0
         1: getfield      #4                  // Field _children:Ljava/util/Map;
         4: aload_1
         5: invokeinterface #26,  2           // InterfaceMethod java/util/Map.get:(Ljava/lang/Object;)Ljava/lang/Object;
        10: checkcast     #17                 // class com/fasterxml/jackson/databind/JsonNode
        13: areturn
      LineNumberTable:
        line 109: 0
      LocalVariableTable:
        Start  Length  Slot  Name   Signature
            0      14     0  this   Lcom/fasterxml/jackson/databind/node/ObjectNode;
            0      14     1 propertyName   Ljava/lang/String;

  public java.util.Iterator<java.lang.String> fieldNames();
    descriptor: ()Ljava/util/Iterator;
    flags: (0x0001) ACC_PUBLIC
    Code:
      stack=1, locals=1, args_size=1
         0: aload_0
         1: getfield      #4                  // Field _children:Ljava/util/Map;
         4: invokeinterface #27,  1           // InterfaceMethod java/util/Map.keySet:()Ljava/util/Set;
         9: invokeinterface #11,  1           // InterfaceMethod java/util/Set.iterator:()Ljava/util/Iterator;
        14: areturn
      LineNumberTable:
        line 114: 0
      LocalVariableTable:
        Start  Length  Slot  Name   Signature
            0      15     0  this   Lcom/fasterxml/jackson/databind/node/ObjectNode;
    Signature: #174                         // ()Ljava/util/Iterator<Ljava/lang/String;>;

  public com.fasterxml.jackson.databind.JsonNode path(int);
    descriptor: (I)Lcom/fasterxml/jackson/databind/JsonNode;
    flags: (0x0001) ACC_PUBLIC
    Code:
      stack=1, locals=2, args_size=2
         0: invokestatic  #28                 // Method com/fasterxml/jackson/databind/node/MissingNode.getInstance:()Lcom/fasterxml/jackson/databind/node/MissingNode;
         3: areturn
      LineNumberTable:
        line 119: 0
      LocalVariableTable:
        Start  Length  Slot  Name   Signature
            0       4     0  this   Lcom/fasterxml/jackson/databind/node/ObjectNode;
            0       4     1 index   I

  public com.fasterxml.jackson.databind.JsonNode path(java.lang.String);
    descriptor: (Ljava/lang/String;)Lcom/fasterxml/jackson/databind/JsonNode;
    flags: (0x0001) ACC_PUBLIC
    Code:
      stack=2, locals=3, args_size=2
         0: aload_0
         1: getfield      #4                  // Field _children:Ljava/util/Map;
         4: aload_1
         5: invokeinterface #26,  2           // InterfaceMethod java/util/Map.get:(Ljava/lang/Object;)Ljava/lang/Object;
        10: checkcast     #17                 // class com/fasterxml/jackson/databind/JsonNode
        13: astore_2
        14: aload_2
        15: ifnull        20
        18: aload_2
        19: areturn
        20: invokestatic  #28                 // Method com/fasterxml/jackson/databind/node/MissingNode.getInstance:()Lcom/fasterxml/jackson/databind/node/MissingNode;
        23: areturn
      LineNumberTable:
        line 125: 0
        line 126: 14
        line 127: 18
        line 129: 20
      LocalVariableTable:
        Start  Length  Slot  Name   Signature
            0      24     0  this   Lcom/fasterxml/jackson/databind/node/ObjectNode;
            0      24     1 propertyName   Ljava/lang/String;
           14      10     2     n   Lcom/fasterxml/jackson/databind/JsonNode;
      StackMapTable: number_of_entries = 1
        frame_type = 252 /* append */
          offset_delta = 20
          locals = [ class com/fasterxml/jackson/databind/JsonNode ]

  public com.fasterxml.jackson.databind.JsonNode required(java.lang.String);
    descriptor: (Ljava/lang/String;)Lcom/fasterxml/jackson/databind/JsonNode;
    flags: (0x0001) ACC_PUBLIC
    Code:
      stack=6, locals=3, args_size=2
         0: aload_0
         1: getfield      #4                  // Field _children:Ljava/util/Map;
         4: aload_1
         5: invokeinterface #26,  2           // InterfaceMethod java/util/Map.get:(Ljava/lang/Object;)Ljava/lang/Object;
        10: checkcast     #17                 // class com/fasterxml/jackson/databind/JsonNode
        13: astore_2
        14: aload_2
        15: ifnull        20
        18: aload_2
        19: areturn
        20: aload_0
        21: ldc           #29                 // String No value for property \'%s\' of `ObjectNode`
        23: iconst_1
        24: anewarray     #30                 // class java/lang/Object
        27: dup
        28: iconst_0
        29: aload_1
        30: aastore
        31: invokevirtual #31                 // Method _reportRequiredViolation:(Ljava/lang/String;[Ljava/lang/Object;)Ljava/lang/Object;
        34: checkcast     #17                 // class com/fasterxml/jackson/databind/JsonNode
        37: areturn
      LineNumberTable:
        line 134: 0
        line 135: 14
        line 136: 18
        line 138: 20
      LocalVariableTable:
        Start  Length  Slot  Name   Signature
            0      38     0  this   Lcom/fasterxml/jackson/databind/node/ObjectNode;
            0      38     1 propertyName   Ljava/lang/String;
           14      24     2     n   Lcom/fasterxml/jackson/databind/JsonNode;
      StackMapTable: number_of_entries = 1
        frame_type = 252 /* append */
          offset_delta = 20
          locals = [ class com/fasterxml/jackson/databind/JsonNode ]

  public java.util.Iterator<java.util.Map$Entry<java.lang.String, com.fasterxml.jackson.databind.JsonNode>> fields();
    descriptor: ()Ljava/util/Iterator;
    flags: (0x0001) ACC_PUBLIC
    Code:
      stack=1, locals=1, args_size=1
         0: aload_0
         1: getfield      #4                  // Field _children:Ljava/util/Map;
         4: invokeinterface #10,  1           // InterfaceMethod java/util/Map.entrySet:()Ljava/util/Set;
         9: invokeinterface #11,  1           // InterfaceMethod java/util/Set.iterator:()Ljava/util/Iterator;
        14: areturn
      LineNumberTable:
        line 147: 0
      LocalVariableTable:
        Start  Length  Slot  Name   Signature
            0      15     0  this   Lcom/fasterxml/jackson/databind/node/ObjectNode;
    Signature: #181                         // ()Ljava/util/Iterator<Ljava/util/Map$Entry<Ljava/lang/String;Lcom/fasterxml/jackson/databind/JsonNode;>;>;

  public com.fasterxml.jackson.databind.node.ObjectNode with(java.lang.String);
    descriptor: (Ljava/lang/String;)Lcom/fasterxml/jackson/databind/node/ObjectNode;
    flags: (0x0001) ACC_PUBLIC
    Code:
      stack=4, locals=4, args_size=2
         0: aload_0
         1: getfield      #4                  // Field _children:Ljava/util/Map;
         4: aload_1
         5: invokeinterface #26,  2           // InterfaceMethod java/util/Map.get:(Ljava/lang/Object;)Ljava/lang/Object;
        10: checkcast     #17                 // class com/fasterxml/jackson/databind/JsonNode
        13: astore_2
        14: aload_2
        15: ifnull        77
        18: aload_2
        19: instanceof    #7                  // class com/fasterxml/jackson/databind/node/ObjectNode
        22: ifeq          30
        25: aload_2
        26: checkcast     #7                  // class com/fasterxml/jackson/databind/node/ObjectNode
        29: areturn
        30: new           #32                 // class java/lang/UnsupportedOperationException
        33: dup
        34: new           #33                 // class java/lang/StringBuilder
        37: dup
        38: invokespecial #34                 // Method java/lang/StringBuilder."<init>":()V
        41: ldc           #35                 // String Property \'
        43: invokevirtual #36                 // Method java/lang/StringBuilder.append:(Ljava/lang/String;)Ljava/lang/StringBuilder;
        46: aload_1
        47: invokevirtual #36                 // Method java/lang/StringBuilder.append:(Ljava/lang/String;)Ljava/lang/StringBuilder;
        50: ldc           #37                 // String \' has value that is not of type ObjectNode (but
        52: invokevirtual #36                 // Method java/lang/StringBuilder.append:(Ljava/lang/String;)Ljava/lang/StringBuilder;
        55: aload_2
        56: invokevirtual #38                 // Method java/lang/Object.getClass:()Ljava/lang/Class;
        59: invokevirtual #39                 // Method java/lang/Class.getName:()Ljava/lang/String;
        62: invokevirtual #36                 // Method java/lang/StringBuilder.append:(Ljava/lang/String;)Ljava/lang/StringBuilder;
        65: ldc           #40                 // String )
        67: invokevirtual #36                 // Method java/lang/StringBuilder.append:(Ljava/lang/String;)Ljava/lang/StringBuilder;
        70: invokevirtual #41                 // Method java/lang/StringBuilder.toString:()Ljava/lang/String;
        73: invokespecial #42                 // Method java/lang/UnsupportedOperationException."<init>":(Ljava/lang/String;)V
        76: athrow
        77: aload_0
        78: invokevirtual #43                 // Method objectNode:()Lcom/fasterxml/jackson/databind/node/ObjectNode;
        81: astore_3
        82: aload_0
        83: getfield      #4                  // Field _children:Ljava/util/Map;
        86: aload_1
        87: aload_3
        88: invokeinterface #19,  3           // InterfaceMethod java/util/Map.put:(Ljava/lang/Object;Ljava/lang/Object;)Ljava/lang/Object;
        93: pop
        94: aload_3
        95: areturn
      LineNumberTable:
        line 153: 0
        line 154: 14
        line 155: 18
        line 156: 25
        line 158: 30
        line 160: 56
        line 162: 77
        line 163: 82
        line 164: 94
      LocalVariableTable:
        Start  Length  Slot  Name   Signature
            0      96     0  this   Lcom/fasterxml/jackson/databind/node/ObjectNode;
            0      96     1 propertyName   Ljava/lang/String;
           14      82     2     n   Lcom/fasterxml/jackson/databind/JsonNode;
           82      14     3 result   Lcom/fasterxml/jackson/databind/node/ObjectNode;
      StackMapTable: number_of_entries = 2
        frame_type = 252 /* append */
          offset_delta = 30
          locals = [ class com/fasterxml/jackson/databind/JsonNode ]
        frame_type = 46 /* same */

  public com.fasterxml.jackson.databind.node.ArrayNode withArray(java.lang.String);
    descriptor: (Ljava/lang/String;)Lcom/fasterxml/jackson/databind/node/ArrayNode;
    flags: (0x0001) ACC_PUBLIC
    Code:
      stack=4, locals=4, args_size=2
         0: aload_0
         1: getfield      #4                  // Field _children:Ljava/util/Map;
         4: aload_1
         5: invokeinterface #26,  2           // InterfaceMethod java/util/Map.get:(Ljava/lang/Object;)Ljava/lang/Object;
        10: checkcast     #17                 // class com/fasterxml/jackson/databind/JsonNode
        13: astore_2
        14: aload_2
        15: ifnull        77
        18: aload_2
        19: instanceof    #44                 // class com/fasterxml/jackson/databind/node/ArrayNode
        22: ifeq          30
        25: aload_2
        26: checkcast     #44                 // class com/fasterxml/jackson/databind/node/ArrayNode
        29: areturn
        30: new           #32                 // class java/lang/UnsupportedOperationException
        33: dup
        34: new           #33                 // class java/lang/StringBuilder
        37: dup
        38: invokespecial #34                 // Method java/lang/StringBuilder."<init>":()V
        41: ldc           #35                 // String Property \'
        43: invokevirtual #36                 // Method java/lang/StringBuilder.append:(Ljava/lang/String;)Ljava/lang/StringBuilder;
        46: aload_1
        47: invokevirtual #36                 // Method java/lang/StringBuilder.append:(Ljava/lang/String;)Ljava/lang/StringBuilder;
        50: ldc           #45                 // String \' has value that is not of type ArrayNode (but
        52: invokevirtual #36                 // Method java/lang/StringBuilder.append:(Ljava/lang/String;)Ljava/lang/StringBuilder;
        55: aload_2
        56: invokevirtual #38                 // Method java/lang/Object.getClass:()Ljava/lang/Class;
        59: invokevirtual #39                 // Method java/lang/Class.getName:()Ljava/lang/String;
        62: invokevirtual #36                 // Method java/lang/StringBuilder.append:(Ljava/lang/String;)Ljava/lang/StringBuilder;
        65: ldc           #40                 // String )
        67: invokevirtual #36                 // Method java/lang/StringBuilder.append:(Ljava/lang/String;)Ljava/lang/StringBuilder;
        70: invokevirtual #41                 // Method java/lang/StringBuilder.toString:()Ljava/lang/String;
        73: invokespecial #42                 // Method java/lang/UnsupportedOperationException."<init>":(Ljava/lang/String;)V
        76: athrow
        77: aload_0
        78: invokevirtual #46                 // Method arrayNode:()Lcom/fasterxml/jackson/databind/node/ArrayNode;
        81: astore_3
        82: aload_0
        83: getfield      #4                  // Field _children:Ljava/util/Map;
        86: aload_1
        87: aload_3
        88: invokeinterface #19,  3           // InterfaceMethod java/util/Map.put:(Ljava/lang/Object;Ljava/lang/Object;)Ljava/lang/Object;
        93: pop
        94: aload_3
        95: areturn
      LineNumberTable:
        line 171: 0
        line 172: 14
        line 173: 18
        line 174: 25
        line 176: 30
        line 178: 56
        line 180: 77
        line 181: 82
        line 182: 94
      LocalVariableTable:
        Start  Length  Slot  Name   Signature
            0      96     0  this   Lcom/fasterxml/jackson/databind/node/ObjectNode;
            0      96     1 propertyName   Ljava/lang/String;
           14      82     2     n   Lcom/fasterxml/jackson/databind/JsonNode;
           82      14     3 result   Lcom/fasterxml/jackson/databind/node/ArrayNode;
      StackMapTable: number_of_entries = 2
        frame_type = 252 /* append */
          offset_delta = 30
          locals = [ class com/fasterxml/jackson/databind/JsonNode ]
        frame_type = 46 /* same */

  public boolean equals(java.util.Comparator<com.fasterxml.jackson.databind.JsonNode>, com.fasterxml.jackson.databind.JsonNode);
    descriptor: (Ljava/util/Comparator;Lcom/fasterxml/jackson/databind/JsonNode;)Z
    flags: (0x0001) ACC_PUBLIC
    Code:
      stack=3, locals=10, args_size=3
         0: aload_2
         1: instanceof    #7                  // class com/fasterxml/jackson/databind/node/ObjectNode
         4: ifne          9
         7: iconst_0
         8: ireturn
         9: aload_2
        10: checkcast     #7                  // class com/fasterxml/jackson/databind/node/ObjectNode
        13: astore_3
        14: aload_0
        15: getfield      #4                  // Field _children:Ljava/util/Map;
        18: astore        4
        20: aload_3
        21: getfield      #4                  // Field _children:Ljava/util/Map;
        24: astore        5
        26: aload         4
        28: invokeinterface #23,  1           // InterfaceMethod java/util/Map.size:()I
        33: istore        6
        35: aload         5
        37: invokeinterface #23,  1           // InterfaceMethod java/util/Map.size:()I
        42: iload         6
        44: if_icmpeq     49
        47: iconst_0
        48: ireturn
        49: aload         4
        51: invokeinterface #10,  1           // InterfaceMethod java/util/Map.entrySet:()Ljava/util/Set;
        56: invokeinterface #11,  1           // InterfaceMethod java/util/Set.iterator:()Ljava/util/Iterator;
        61: astore        7
        63: aload         7
        65: invokeinterface #12,  1           // InterfaceMethod java/util/Iterator.hasNext:()Z
        70: ifeq          133
        73: aload         7
        75: invokeinterface #13,  1           // InterfaceMethod java/util/Iterator.next:()Ljava/lang/Object;
        80: checkcast     #14                 // class java/util/Map$Entry
        83: astore        8
        85: aload         5
        87: aload         8
        89: invokeinterface #15,  1           // InterfaceMethod java/util/Map$Entry.getKey:()Ljava/lang/Object;
        94: invokeinterface #26,  2           // InterfaceMethod java/util/Map.get:(Ljava/lang/Object;)Ljava/lang/Object;
        99: checkcast     #17                 // class com/fasterxml/jackson/databind/JsonNode
       102: astore        9
       104: aload         9
       106: ifnull        128
       109: aload         8
       111: invokeinterface #16,  1           // InterfaceMethod java/util/Map$Entry.getValue:()Ljava/lang/Object;
       116: checkcast     #17                 // class com/fasterxml/jackson/databind/JsonNode
       119: aload_1
       120: aload         9
       122: invokevirtual #47                 // Method com/fasterxml/jackson/databind/JsonNode.equals:(Ljava/util/Comparator;Lcom/fasterxml/jackson/databind/JsonNode;)Z
       125: ifne          130
       128: iconst_0
       129: ireturn
       130: goto          63
       133: iconst_1
       134: ireturn
      LineNumberTable:
        line 188: 0
        line 189: 7
        line 191: 9
        line 192: 14
        line 193: 20
        line 195: 26
        line 196: 35
        line 197: 47
        line 200: 49
        line 201: 85
        line 202: 104
        line 203: 128
        line 205: 130
        line 206: 133
      LocalVariableTable:
        Start  Length  Slot  Name   Signature
          104      26     9    v2   Lcom/fasterxml/jackson/databind/JsonNode;
           85      45     8 entry   Ljava/util/Map$Entry;
            0     135     0  this   Lcom/fasterxml/jackson/databind/node/ObjectNode;
            0     135     1 comparator   Ljava/util/Comparator;
            0     135     2     o   Lcom/fasterxml/jackson/databind/JsonNode;
           14     121     3 other   Lcom/fasterxml/jackson/databind/node/ObjectNode;
           20     115     4    m1   Ljava/util/Map;
           26     109     5    m2   Ljava/util/Map;
           35     100     6   len   I
      LocalVariableTypeTable:
        Start  Length  Slot  Name   Signature
           85      45     8 entry   Ljava/util/Map$Entry<Ljava/lang/String;Lcom/fasterxml/jackson/databind/JsonNode;>;
            0     135     1 comparator   Ljava/util/Comparator<Lcom/fasterxml/jackson/databind/JsonNode;>;
           20     115     4    m1   Ljava/util/Map<Ljava/lang/String;Lcom/fasterxml/jackson/databind/JsonNode;>;
           26     109     5    m2   Ljava/util/Map<Ljava/lang/String;Lcom/fasterxml/jackson/databind/JsonNode;>;
      StackMapTable: number_of_entries = 6
        frame_type = 9 /* same */
        frame_type = 255 /* full_frame */
          offset_delta = 39
          locals = [ class com/fasterxml/jackson/databind/node/ObjectNode, class java/util/Comparator, class com/fasterxml/jackson/databind/JsonNode, class com/fasterxml/jackson/databind/node/ObjectNode, class java/util/Map, class java/util/Map, int ]
          stack = []
        frame_type = 252 /* append */
          offset_delta = 13
          locals = [ class java/util/Iterator ]
        frame_type = 253 /* append */
          offset_delta = 64
          locals = [ class java/util/Map$Entry, class com/fasterxml/jackson/databind/JsonNode ]
        frame_type = 249 /* chop */
          offset_delta = 1
        frame_type = 250 /* chop */
          offset_delta = 2
    Signature: #202                         // (Ljava/util/Comparator<Lcom/fasterxml/jackson/databind/JsonNode;>;Lcom/fasterxml/jackson/databind/JsonNode;)Z

  public com.fasterxml.jackson.databind.JsonNode findValue(java.lang.String);
    descriptor: (Ljava/lang/String;)Lcom/fasterxml/jackson/databind/JsonNode;
    flags: (0x0001) ACC_PUBLIC
    Code:
      stack=2, locals=5, args_size=2
         0: aload_0
         1: getfield      #4                  // Field _children:Ljava/util/Map;
         4: invokeinterface #10,  1           // InterfaceMethod java/util/Map.entrySet:()Ljava/util/Set;
         9: invokeinterface #11,  1           // InterfaceMethod java/util/Set.iterator:()Ljava/util/Iterator;
        14: astore_2
        15: aload_2
        16: invokeinterface #12,  1           // InterfaceMethod java/util/Iterator.hasNext:()Z
        21: ifeq          83
        24: aload_2
        25: invokeinterface #13,  1           // InterfaceMethod java/util/Iterator.next:()Ljava/lang/Object;
        30: checkcast     #14                 // class java/util/Map$Entry
        33: astore_3
        34: aload_1
        35: aload_3
        36: invokeinterface #15,  1           // InterfaceMethod java/util/Map$Entry.getKey:()Ljava/lang/Object;
        41: invokevirtual #48                 // Method java/lang/String.equals:(Ljava/lang/Object;)Z
        44: ifeq          57
        47: aload_3
        48: invokeinterface #16,  1           // InterfaceMethod java/util/Map$Entry.getValue:()Ljava/lang/Object;
        53: checkcast     #17                 // class com/fasterxml/jackson/databind/JsonNode
        56: areturn
        57: aload_3
        58: invokeinterface #16,  1           // InterfaceMethod java/util/Map$Entry.getValue:()Ljava/lang/Object;
        63: checkcast     #17                 // class com/fasterxml/jackson/databind/JsonNode
        66: aload_1
        67: invokevirtual #49                 // Method com/fasterxml/jackson/databind/JsonNode.findValue:(Ljava/lang/String;)Lcom/fasterxml/jackson/databind/JsonNode;
        70: astore        4
        72: aload         4
        74: ifnull        80
        77: aload         4
        79: areturn
        80: goto          15
        83: aconst_null
        84: areturn
      LineNumberTable:
        line 218: 0
        line 219: 34
        line 220: 47
        line 222: 57
        line 223: 72
        line 224: 77
        line 226: 80
        line 227: 83
      LocalVariableTable:
        Start  Length  Slot  Name   Signature
           72       8     4 value   Lcom/fasterxml/jackson/databind/JsonNode;
           34      46     3 entry   Ljava/util/Map$Entry;
            0      85     0  this   Lcom/fasterxml/jackson/databind/node/ObjectNode;
            0      85     1 propertyName   Ljava/lang/String;
      LocalVariableTypeTable:
        Start  Length  Slot  Name   Signature
           34      46     3 entry   Ljava/util/Map$Entry<Ljava/lang/String;Lcom/fasterxml/jackson/databind/JsonNode;>;
      StackMapTable: number_of_entries = 4
        frame_type = 252 /* append */
          offset_delta = 15
          locals = [ class java/util/Iterator ]
        frame_type = 252 /* append */
          offset_delta = 41
          locals = [ class java/util/Map$Entry ]
        frame_type = 250 /* chop */
          offset_delta = 22
        frame_type = 250 /* chop */
          offset_delta = 2

  public java.util.List<com.fasterxml.jackson.databind.JsonNode> findValues(java.lang.String, java.util.List<com.fasterxml.jackson.databind.JsonNode>);
    descriptor: (Ljava/lang/String;Ljava/util/List;)Ljava/util/List;
    flags: (0x0001) ACC_PUBLIC
    Code:
      stack=3, locals=5, args_size=3
         0: aload_0
         1: getfield      #4                  // Field _children:Ljava/util/Map;
         4: invokeinterface #10,  1           // InterfaceMethod java/util/Map.entrySet:()Ljava/util/Set;
         9: invokeinterface #11,  1           // InterfaceMethod java/util/Set.iterator:()Ljava/util/Iterator;
        14: astore_3
        15: aload_3
        16: invokeinterface #12,  1           // InterfaceMethod java/util/Iterator.hasNext:()Z
        21: ifeq          97
        24: aload_3
        25: invokeinterface #13,  1           // InterfaceMethod java/util/Iterator.next:()Ljava/lang/Object;
        30: checkcast     #14                 // class java/util/Map$Entry
        33: astore        4
        35: aload_1
        36: aload         4
        38: invokeinterface #15,  1           // InterfaceMethod java/util/Map$Entry.getKey:()Ljava/lang/Object;
        43: invokevirtual #48                 // Method java/lang/String.equals:(Ljava/lang/Object;)Z
        46: ifeq          78
        49: aload_2
        50: ifnonnull     61
        53: new           #50                 // class java/util/ArrayList
        56: dup
        57: invokespecial #51                 // Method java/util/ArrayList."<init>":()V
        60: astore_2
        61: aload_2
        62: aload         4
        64: invokeinterface #16,  1           // InterfaceMethod java/util/Map$Entry.getValue:()Ljava/lang/Object;
        69: invokeinterface #52,  2           // InterfaceMethod java/util/List.add:(Ljava/lang/Object;)Z
        74: pop
        75: goto          94
        78: aload         4
        80: invokeinterface #16,  1           // InterfaceMethod java/util/Map$Entry.getValue:()Ljava/lang/Object;
        85: checkcast     #17                 // class com/fasterxml/jackson/databind/JsonNode
        88: aload_1
        89: aload_2
        90: invokevirtual #53                 // Method com/fasterxml/jackson/databind/JsonNode.findValues:(Ljava/lang/String;Ljava/util/List;)Ljava/util/List;
        93: astore_2
        94: goto          15
        97: aload_2
        98: areturn
      LineNumberTable:
        line 233: 0
        line 234: 35
        line 235: 49
        line 236: 53
        line 238: 61
        line 240: 78
        line 242: 94
        line 243: 97
      LocalVariableTable:
        Start  Length  Slot  Name   Signature
           35      59     4 entry   Ljava/util/Map$Entry;
            0      99     0  this   Lcom/fasterxml/jackson/databind/node/ObjectNode;
            0      99     1 propertyName   Ljava/lang/String;
            0      99     2 foundSoFar   Ljava/util/List;
      LocalVariableTypeTable:
        Start  Length  Slot  Name   Signature
           35      59     4 entry   Ljava/util/Map$Entry<Ljava/lang/String;Lcom/fasterxml/jackson/databind/JsonNode;>;
            0      99     2 foundSoFar   Ljava/util/List<Lcom/fasterxml/jackson/databind/JsonNode;>;
      StackMapTable: number_of_entries = 5
        frame_type = 252 /* append */
          offset_delta = 15
          locals = [ class java/util/Iterator ]
        frame_type = 252 /* append */
          offset_delta = 45
          locals = [ class java/util/Map$Entry ]
        frame_type = 16 /* same */
        frame_type = 250 /* chop */
          offset_delta = 15
        frame_type = 250 /* chop */
          offset_delta = 2
    Signature: #210                         // (Ljava/lang/String;Ljava/util/List<Lcom/fasterxml/jackson/databind/JsonNode;>;)Ljava/util/List<Lcom/fasterxml/jackson/databind/JsonNode;>;

  public java.util.List<java.lang.String> findValuesAsText(java.lang.String, java.util.List<java.lang.String>);
    descriptor: (Ljava/lang/String;Ljava/util/List;)Ljava/util/List;
    flags: (0x0001) ACC_PUBLIC
    Code:
      stack=3, locals=5, args_size=3
         0: aload_0
         1: getfield      #4                  // Field _children:Ljava/util/Map;
         4: invokeinterface #10,  1           // InterfaceMethod java/util/Map.entrySet:()Ljava/util/Set;
         9: invokeinterface #11,  1           // InterfaceMethod java/util/Set.iterator:()Ljava/util/Iterator;
        14: astore_3
        15: aload_3
        16: invokeinterface #12,  1           // InterfaceMethod java/util/Iterator.hasNext:()Z
        21: ifeq          103
        24: aload_3
        25: invokeinterface #13,  1           // InterfaceMethod java/util/Iterator.next:()Ljava/lang/Object;
        30: checkcast     #14                 // class java/util/Map$Entry
        33: astore        4
        35: aload_1
        36: aload         4
        38: invokeinterface #15,  1           // InterfaceMethod java/util/Map$Entry.getKey:()Ljava/lang/Object;
        43: invokevirtual #48                 // Method java/lang/String.equals:(Ljava/lang/Object;)Z
        46: ifeq          84
        49: aload_2
        50: ifnonnull     61
        53: new           #50                 // class java/util/ArrayList
        56: dup
        57: invokespecial #51                 // Method java/util/ArrayList."<init>":()V
        60: astore_2
        61: aload_2
        62: aload         4
        64: invokeinterface #16,  1           // InterfaceMethod java/util/Map$Entry.getValue:()Ljava/lang/Object;
        69: checkcast     #17                 // class com/fasterxml/jackson/databind/JsonNode
        72: invokevirtual #54                 // Method com/fasterxml/jackson/databind/JsonNode.asText:()Ljava/lang/String;
        75: invokeinterface #52,  2           // InterfaceMethod java/util/List.add:(Ljava/lang/Object;)Z
        80: pop
        81: goto          100
        84: aload         4
        86: invokeinterface #16,  1           // InterfaceMethod java/util/Map$Entry.getValue:()Ljava/lang/Object;
        91: checkcast     #17                 // class com/fasterxml/jackson/databind/JsonNode
        94: aload_1
        95: aload_2
        96: invokevirtual #55                 // Method com/fasterxml/jackson/databind/JsonNode.findValuesAsText:(Ljava/lang/String;Ljava/util/List;)Ljava/util/List;
        99: astore_2
       100: goto          15
       103: aload_2
       104: areturn
      LineNumberTable:
        line 249: 0
        line 250: 35
        line 251: 49
        line 252: 53
        line 254: 61
        line 256: 84
        line 259: 100
        line 260: 103
      LocalVariableTable:
        Start  Length  Slot  Name   Signature
           35      65     4 entry   Ljava/util/Map$Entry;
            0     105     0  this   Lcom/fasterxml/jackson/databind/node/ObjectNode;
            0     105     1 propertyName   Ljava/lang/String;
            0     105     2 foundSoFar   Ljava/util/List;
      LocalVariableTypeTable:
        Start  Length  Slot  Name   Signature
           35      65     4 entry   Ljava/util/Map$Entry<Ljava/lang/String;Lcom/fasterxml/jackson/databind/JsonNode;>;
            0     105     2 foundSoFar   Ljava/util/List<Ljava/lang/String;>;
      StackMapTable: number_of_entries = 5
        frame_type = 252 /* append */
          offset_delta = 15
          locals = [ class java/util/Iterator ]
        frame_type = 252 /* append */
          offset_delta = 45
          locals = [ class java/util/Map$Entry ]
        frame_type = 22 /* same */
        frame_type = 250 /* chop */
          offset_delta = 15
        frame_type = 250 /* chop */
          offset_delta = 2
    Signature: #213                         // (Ljava/lang/String;Ljava/util/List<Ljava/lang/String;>;)Ljava/util/List<Ljava/lang/String;>;

  public com.fasterxml.jackson.databind.node.ObjectNode findParent(java.lang.String);
    descriptor: (Ljava/lang/String;)Lcom/fasterxml/jackson/databind/node/ObjectNode;
    flags: (0x0001) ACC_PUBLIC
    Code:
      stack=2, locals=5, args_size=2
         0: aload_0
         1: getfield      #4                  // Field _children:Ljava/util/Map;
         4: invokeinterface #10,  1           // InterfaceMethod java/util/Map.entrySet:()Ljava/util/Set;
         9: invokeinterface #11,  1           // InterfaceMethod java/util/Set.iterator:()Ljava/util/Iterator;
        14: astore_2
        15: aload_2
        16: invokeinterface #12,  1           // InterfaceMethod java/util/Iterator.hasNext:()Z
        21: ifeq          78
        24: aload_2
        25: invokeinterface #13,  1           // InterfaceMethod java/util/Iterator.next:()Ljava/lang/Object;
        30: checkcast     #14                 // class java/util/Map$Entry
        33: astore_3
        34: aload_1
        35: aload_3
        36: invokeinterface #15,  1           // InterfaceMethod java/util/Map$Entry.getKey:()Ljava/lang/Object;
        41: invokevirtual #48                 // Method java/lang/String.equals:(Ljava/lang/Object;)Z
        44: ifeq          49
        47: aload_0
        48: areturn
        49: aload_3
        50: invokeinterface #16,  1           // InterfaceMethod java/util/Map$Entry.getValue:()Ljava/lang/Object;
        55: checkcast     #17                 // class com/fasterxml/jackson/databind/JsonNode
        58: aload_1
        59: invokevirtual #56                 // Method com/fasterxml/jackson/databind/JsonNode.findParent:(Ljava/lang/String;)Lcom/fasterxml/jackson/databind/JsonNode;
        62: astore        4
        64: aload         4
        66: ifnull        75
        69: aload         4
        71: checkcast     #7                  // class com/fasterxml/jackson/databind/node/ObjectNode
        74: areturn
        75: goto          15
        78: aconst_null
        79: areturn
      LineNumberTable:
        line 266: 0
        line 267: 34
        line 268: 47
        line 270: 49
        line 271: 64
        line 272: 69
        line 274: 75
        line 275: 78
      LocalVariableTable:
        Start  Length  Slot  Name   Signature
           64      11     4 value   Lcom/fasterxml/jackson/databind/JsonNode;
           34      41     3 entry   Ljava/util/Map$Entry;
            0      80     0  this   Lcom/fasterxml/jackson/databind/node/ObjectNode;
            0      80     1 propertyName   Ljava/lang/String;
      LocalVariableTypeTable:
        Start  Length  Slot  Name   Signature
           34      41     3 entry   Ljava/util/Map$Entry<Ljava/lang/String;Lcom/fasterxml/jackson/databind/JsonNode;>;
      StackMapTable: number_of_entries = 4
        frame_type = 252 /* append */
          offset_delta = 15
          locals = [ class java/util/Iterator ]
        frame_type = 252 /* append */
          offset_delta = 33
          locals = [ class java/util/Map$Entry ]
        frame_type = 250 /* chop */
          offset_delta = 25
        frame_type = 250 /* chop */
          offset_delta = 2

  public java.util.List<com.fasterxml.jackson.databind.JsonNode> findParents(java.lang.String, java.util.List<com.fasterxml.jackson.databind.JsonNode>);
    descriptor: (Ljava/lang/String;Ljava/util/List;)Ljava/util/List;
    flags: (0x0001) ACC_PUBLIC
    Code:
      stack=3, locals=5, args_size=3
         0: aload_0
         1: getfield      #4                  // Field _children:Ljava/util/Map;
         4: invokeinterface #10,  1           // InterfaceMethod java/util/Map.entrySet:()Ljava/util/Set;
         9: invokeinterface #11,  1           // InterfaceMethod java/util/Set.iterator:()Ljava/util/Iterator;
        14: astore_3
        15: aload_3
        16: invokeinterface #12,  1           // InterfaceMethod java/util/Iterator.hasNext:()Z
        21: ifeq          91
        24: aload_3
        25: invokeinterface #13,  1           // InterfaceMethod java/util/Iterator.next:()Ljava/lang/Object;
        30: checkcast     #14                 // class java/util/Map$Entry
        33: astore        4
        35: aload_1
        36: aload         4
        38: invokeinterface #15,  1           // InterfaceMethod java/util/Map$Entry.getKey:()Ljava/lang/Object;
        43: invokevirtual #48                 // Method java/lang/String.equals:(Ljava/lang/Object;)Z
        46: ifeq          72
        49: aload_2
        50: ifnonnull     61
        53: new           #50                 // class java/util/ArrayList
        56: dup
        57: invokespecial #51                 // Method java/util/ArrayList."<init>":()V
        60: astore_2
        61: aload_2
        62: aload_0
        63: invokeinterface #52,  2           // InterfaceMethod java/util/List.add:(Ljava/lang/Object;)Z
        68: pop
        69: goto          88
        72: aload         4
        74: invokeinterface #16,  1           // InterfaceMethod java/util/Map$Entry.getValue:()Ljava/lang/Object;
        79: checkcast     #17                 // class com/fasterxml/jackson/databind/JsonNode
        82: aload_1
        83: aload_2
        84: invokevirtual #57                 // Method com/fasterxml/jackson/databind/JsonNode.findParents:(Ljava/lang/String;Ljava/util/List;)Ljava/util/List;
        87: astore_2
        88: goto          15
        91: aload_2
        92: areturn
      LineNumberTable:
        line 281: 0
        line 282: 35
        line 283: 49
        line 284: 53
        line 286: 61
        line 288: 72
        line 289: 84
        line 291: 88
        line 292: 91
      LocalVariableTable:
        Start  Length  Slot  Name   Signature
           35      53     4 entry   Ljava/util/Map$Entry;
            0      93     0  this   Lcom/fasterxml/jackson/databind/node/ObjectNode;
            0      93     1 propertyName   Ljava/lang/String;
            0      93     2 foundSoFar   Ljava/util/List;
      LocalVariableTypeTable:
        Start  Length  Slot  Name   Signature
           35      53     4 entry   Ljava/util/Map$Entry<Ljava/lang/String;Lcom/fasterxml/jackson/databind/JsonNode;>;
            0      93     2 foundSoFar   Ljava/util/List<Lcom/fasterxml/jackson/databind/JsonNode;>;
      StackMapTable: number_of_entries = 5
        frame_type = 252 /* append */
          offset_delta = 15
          locals = [ class java/util/Iterator ]
        frame_type = 252 /* append */
          offset_delta = 45
          locals = [ class java/util/Map$Entry ]
        frame_type = 10 /* same */
        frame_type = 250 /* chop */
          offset_delta = 15
        frame_type = 250 /* chop */
          offset_delta = 2
    Signature: #210                         // (Ljava/lang/String;Ljava/util/List<Lcom/fasterxml/jackson/databind/JsonNode;>;)Ljava/util/List<Lcom/fasterxml/jackson/databind/JsonNode;>;

  public void serialize(com.fasterxml.jackson.core.JsonGenerator, com.fasterxml.jackson.databind.SerializerProvider) throws java.io.IOException;
    descriptor: (Lcom/fasterxml/jackson/core/JsonGenerator;Lcom/fasterxml/jackson/databind/SerializerProvider;)V
    flags: (0x0001) ACC_PUBLIC
    Code:
      stack=3, locals=7, args_size=3
         0: aload_2
         1: ifnull        18
         4: aload_2
         5: getstatic     #58                 // Field com/fasterxml/jackson/databind/SerializationFeature.WRITE_EMPTY_JSON_ARRAYS:Lcom/fasterxml/jackson/databind/SerializationFeature;
         8: invokevirtual #59                 // Method com/fasterxml/jackson/databind/SerializerProvider.isEnabled:(Lcom/fasterxml/jackson/databind/SerializationFeature;)Z
        11: ifne          18
        14: iconst_1
        15: goto          19
        18: iconst_0
        19: istore_3
        20: aload_1
        21: aload_0
        22: invokevirtual #60                 // Method com/fasterxml/jackson/core/JsonGenerator.writeStartObject:(Ljava/lang/Object;)V
        25: aload_0
        26: getfield      #4                  // Field _children:Ljava/util/Map;
        29: invokeinterface #10,  1           // InterfaceMethod java/util/Map.entrySet:()Ljava/util/Set;
        34: invokeinterface #11,  1           // InterfaceMethod java/util/Set.iterator:()Ljava/util/Iterator;
        39: astore        4
        41: aload         4
        43: invokeinterface #12,  1           // InterfaceMethod java/util/Iterator.hasNext:()Z
        48: ifeq          123
        51: aload         4
        53: invokeinterface #13,  1           // InterfaceMethod java/util/Iterator.next:()Ljava/lang/Object;
        58: checkcast     #14                 // class java/util/Map$Entry
        61: astore        5
        63: aload         5
        65: invokeinterface #16,  1           // InterfaceMethod java/util/Map$Entry.getValue:()Ljava/lang/Object;
        70: checkcast     #61                 // class com/fasterxml/jackson/databind/node/BaseJsonNode
        73: astore        6
        75: iload_3
        76: ifeq          99
        79: aload         6
        81: invokevirtual #62                 // Method com/fasterxml/jackson/databind/node/BaseJsonNode.isArray:()Z
        84: ifeq          99
        87: aload         6
        89: aload_2
        90: invokevirtual #63                 // Method com/fasterxml/jackson/databind/node/BaseJsonNode.isEmpty:(Lcom/fasterxml/jackson/databind/SerializerProvider;)Z
        93: ifeq          99
        96: goto          41
        99: aload_1
       100: aload         5
       102: invokeinterface #15,  1           // InterfaceMethod java/util/Map$Entry.getKey:()Ljava/lang/Object;
       107: checkcast     #64                 // class java/lang/String
       110: invokevirtual #65                 // Method com/fasterxml/jackson/core/JsonGenerator.writeFieldName:(Ljava/lang/String;)V
       113: aload         6
       115: aload_1
       116: aload_2
       117: invokevirtual #66                 // Method com/fasterxml/jackson/databind/node/BaseJsonNode.serialize:(Lcom/fasterxml/jackson/core/JsonGenerator;Lcom/fasterxml/jackson/databind/SerializerProvider;)V
       120: goto          41
       123: aload_1
       124: invokevirtual #67                 // Method com/fasterxml/jackson/core/JsonGenerator.writeEndObject:()V
       127: return
      LineNumberTable:
        line 310: 0
        line 311: 8
        line 312: 20
        line 313: 25
        line 319: 63
        line 324: 75
        line 325: 96
        line 327: 99
        line 328: 113
        line 329: 120
        line 330: 123
        line 331: 127
      LocalVariableTable:
        Start  Length  Slot  Name   Signature
           75      45     6 value   Lcom/fasterxml/jackson/databind/node/BaseJsonNode;
           63      57     5    en   Ljava/util/Map$Entry;
            0     128     0  this   Lcom/fasterxml/jackson/databind/node/ObjectNode;
            0     128     1     g   Lcom/fasterxml/jackson/core/JsonGenerator;
            0     128     2 provider   Lcom/fasterxml/jackson/databind/SerializerProvider;
           20     108     3 trimEmptyArray   Z
      LocalVariableTypeTable:
        Start  Length  Slot  Name   Signature
           63      57     5    en   Ljava/util/Map$Entry<Ljava/lang/String;Lcom/fasterxml/jackson/databind/JsonNode;>;
      StackMapTable: number_of_entries = 5
        frame_type = 18 /* same */
        frame_type = 64 /* same_locals_1_stack_item */
          stack = [ int ]
        frame_type = 253 /* append */
          offset_delta = 21
          locals = [ int, class java/util/Iterator ]
        frame_type = 253 /* append */
          offset_delta = 57
          locals = [ class java/util/Map$Entry, class com/fasterxml/jackson/databind/node/BaseJsonNode ]
        frame_type = 248 /* chop */
          offset_delta = 23
    Exceptions:
      throws java.io.IOException

  public void serializeWithType(com.fasterxml.jackson.core.JsonGenerator, com.fasterxml.jackson.databind.SerializerProvider, com.fasterxml.jackson.databind.jsontype.TypeSerializer) throws java.io.IOException;
    descriptor: (Lcom/fasterxml/jackson/core/JsonGenerator;Lcom/fasterxml/jackson/databind/SerializerProvider;Lcom/fasterxml/jackson/databind/jsontype/TypeSerializer;)V
    flags: (0x0001) ACC_PUBLIC
    Code:
      stack=5, locals=9, args_size=4
         0: aload_2
         1: ifnull        18
         4: aload_2
         5: getstatic     #58                 // Field com/fasterxml/jackson/databind/SerializationFeature.WRITE_EMPTY_JSON_ARRAYS:Lcom/fasterxml/jackson/databind/SerializationFeature;
         8: invokevirtual #59                 // Method com/fasterxml/jackson/databind/SerializerProvider.isEnabled:(Lcom/fasterxml/jackson/databind/SerializationFeature;)Z
        11: ifne          18
        14: iconst_1
        15: goto          19
        18: iconst_0
        19: istore        4
        21: aload_3
        22: aload_1
        23: aload_3
        24: aload_0
        25: getstatic     #22                 // Field com/fasterxml/jackson/core/JsonToken.START_OBJECT:Lcom/fasterxml/jackson/core/JsonToken;
        28: invokevirtual #68                 // Method com/fasterxml/jackson/databind/jsontype/TypeSerializer.typeId:(Ljava/lang/Object;Lcom/fasterxml/jackson/core/JsonToken;)Lcom/fasterxml/jackson/core/type/WritableTypeId;
        31: invokevirtual #69                 // Method com/fasterxml/jackson/databind/jsontype/TypeSerializer.writeTypePrefix:(Lcom/fasterxml/jackson/core/JsonGenerator;Lcom/fasterxml/jackson/core/type/WritableTypeId;)Lcom/fasterxml/jackson/core/type/WritableTypeId;
        34: astore        5
        36: aload_0
        37: getfield      #4                  // Field _children:Ljava/util/Map;
        40: invokeinterface #10,  1           // InterfaceMethod java/util/Map.entrySet:()Ljava/util/Set;
        45: invokeinterface #11,  1           // InterfaceMethod java/util/Set.iterator:()Ljava/util/Iterator;
        50: astore        6
        52: aload         6
        54: invokeinterface #12,  1           // InterfaceMethod java/util/Iterator.hasNext:()Z
        59: ifeq          135
        62: aload         6
        64: invokeinterface #13,  1           // InterfaceMethod java/util/Iterator.next:()Ljava/lang/Object;
        69: checkcast     #14                 // class java/util/Map$Entry
        72: astore        7
        74: aload         7
        76: invokeinterface #16,  1           // InterfaceMethod java/util/Map$Entry.getValue:()Ljava/lang/Object;
        81: checkcast     #61                 // class com/fasterxml/jackson/databind/node/BaseJsonNode
        84: astore        8
        86: iload         4
        88: ifeq          111
        91: aload         8
        93: invokevirtual #62                 // Method com/fasterxml/jackson/databind/node/BaseJsonNode.isArray:()Z
        96: ifeq          111
        99: aload         8
       101: aload_2
       102: invokevirtual #63                 // Method com/fasterxml/jackson/databind/node/BaseJsonNode.isEmpty:(Lcom/fasterxml/jackson/databind/SerializerProvider;)Z
       105: ifeq          111
       108: goto          52
       111: aload_1
       112: aload         7
       114: invokeinterface #15,  1           // InterfaceMethod java/util/Map$Entry.getKey:()Ljava/lang/Object;
       119: checkcast     #64                 // class java/lang/String
       122: invokevirtual #65                 // Method com/fasterxml/jackson/core/JsonGenerator.writeFieldName:(Ljava/lang/String;)V
       125: aload         8
       127: aload_1
       128: aload_2
       129: invokevirtual #66                 // Method com/fasterxml/jackson/databind/node/BaseJsonNode.serialize:(Lcom/fasterxml/jackson/core/JsonGenerator;Lcom/fasterxml/jackson/databind/SerializerProvider;)V
       132: goto          52
       135: aload_3
       136: aload_1
       137: aload         5
       139: invokevirtual #70                 // Method com/fasterxml/jackson/databind/jsontype/TypeSerializer.writeTypeSuffix:(Lcom/fasterxml/jackson/core/JsonGenerator;Lcom/fasterxml/jackson/core/type/WritableTypeId;)Lcom/fasterxml/jackson/core/type/WritableTypeId;
       142: pop
       143: return
      LineNumberTable:
        line 339: 0
        line 340: 8
        line 342: 21
        line 343: 28
        line 342: 31
        line 344: 36
        line 345: 74
        line 350: 86
        line 351: 108
        line 354: 111
        line 355: 125
        line 356: 132
        line 357: 135
        line 358: 143
      LocalVariableTable:
        Start  Length  Slot  Name   Signature
           86      46     8 value   Lcom/fasterxml/jackson/databind/node/BaseJsonNode;
           74      58     7    en   Ljava/util/Map$Entry;
            0     144     0  this   Lcom/fasterxml/jackson/databind/node/ObjectNode;
            0     144     1     g   Lcom/fasterxml/jackson/core/JsonGenerator;
            0     144     2 provider   Lcom/fasterxml/jackson/databind/SerializerProvider;
            0     144     3 typeSer   Lcom/fasterxml/jackson/databind/jsontype/TypeSerializer;
           21     123     4 trimEmptyArray   Z
           36     108     5 typeIdDef   Lcom/fasterxml/jackson/core/type/WritableTypeId;
      LocalVariableTypeTable:
        Start  Length  Slot  Name   Signature
           74      58     7    en   Ljava/util/Map$Entry<Ljava/lang/String;Lcom/fasterxml/jackson/databind/JsonNode;>;
      StackMapTable: number_of_entries = 5
        frame_type = 18 /* same */
        frame_type = 64 /* same_locals_1_stack_item */
          stack = [ int ]
        frame_type = 254 /* append */
          offset_delta = 32
          locals = [ int, class com/fasterxml/jackson/core/type/WritableTypeId, class java/util/Iterator ]
        frame_type = 253 /* append */
          offset_delta = 58
          locals = [ class java/util/Map$Entry, class com/fasterxml/jackson/databind/node/BaseJsonNode ]
        frame_type = 248 /* chop */
          offset_delta = 23
    Exceptions:
      throws java.io.IOException

  public <T extends com.fasterxml.jackson.databind.JsonNode> T set(java.lang.String, com.fasterxml.jackson.databind.JsonNode);
    descriptor: (Ljava/lang/String;Lcom/fasterxml/jackson/databind/JsonNode;)Lcom/fasterxml/jackson/databind/JsonNode;
    flags: (0x0001) ACC_PUBLIC
    Code:
      stack=3, locals=3, args_size=3
         0: aload_2
         1: ifnonnull     9
         4: aload_0
         5: invokevirtual #71                 // Method nullNode:()Lcom/fasterxml/jackson/databind/node/NullNode;
         8: astore_2
         9: aload_0
        10: getfield      #4                  // Field _children:Ljava/util/Map;
        13: aload_1
        14: aload_2
        15: invokeinterface #19,  3           // InterfaceMethod java/util/Map.put:(Ljava/lang/Object;Ljava/lang/Object;)Ljava/lang/Object;
        20: pop
        21: aload_0
        22: areturn
      LineNumberTable:
        line 388: 0
        line 389: 4
        line 391: 9
        line 392: 21
      LocalVariableTable:
        Start  Length  Slot  Name   Signature
            0      23     0  this   Lcom/fasterxml/jackson/databind/node/ObjectNode;
            0      23     1 propertyName   Ljava/lang/String;
            0      23     2 value   Lcom/fasterxml/jackson/databind/JsonNode;
      StackMapTable: number_of_entries = 1
        frame_type = 9 /* same */
    Signature: #237                         // <T:Lcom/fasterxml/jackson/databind/JsonNode;>(Ljava/lang/String;Lcom/fasterxml/jackson/databind/JsonNode;)TT;

  public <T extends com.fasterxml.jackson.databind.JsonNode> T setAll(java.util.Map<java.lang.String, ? extends com.fasterxml.jackson.databind.JsonNode>);
    descriptor: (Ljava/util/Map;)Lcom/fasterxml/jackson/databind/JsonNode;
    flags: (0x0001) ACC_PUBLIC
    Code:
      stack=3, locals=5, args_size=2
         0: aload_1
         1: invokeinterface #10,  1           // InterfaceMethod java/util/Map.entrySet:()Ljava/util/Set;
         6: invokeinterface #11,  1           // InterfaceMethod java/util/Set.iterator:()Ljava/util/Iterator;
        11: astore_2
        12: aload_2
        13: invokeinterface #12,  1           // InterfaceMethod java/util/Iterator.hasNext:()Z
        18: ifeq          74
        21: aload_2
        22: invokeinterface #13,  1           // InterfaceMethod java/util/Iterator.next:()Ljava/lang/Object;
        27: checkcast     #14                 // class java/util/Map$Entry
        30: astore_3
        31: aload_3
        32: invokeinterface #16,  1           // InterfaceMethod java/util/Map$Entry.getValue:()Ljava/lang/Object;
        37: checkcast     #17                 // class com/fasterxml/jackson/databind/JsonNode
        40: astore        4
        42: aload         4
        44: ifnonnull     53
        47: aload_0
        48: invokevirtual #71                 // Method nullNode:()Lcom/fasterxml/jackson/databind/node/NullNode;
        51: astore        4
        53: aload_0
        54: getfield      #4                  // Field _children:Ljava/util/Map;
        57: aload_3
        58: invokeinterface #15,  1           // InterfaceMethod java/util/Map$Entry.getKey:()Ljava/lang/Object;
        63: aload         4
        65: invokeinterface #19,  3           // InterfaceMethod java/util/Map.put:(Ljava/lang/Object;Ljava/lang/Object;)Ljava/lang/Object;
        70: pop
        71: goto          12
        74: aload_0
        75: areturn
      LineNumberTable:
        line 410: 0
        line 411: 31
        line 412: 42
        line 413: 47
        line 415: 53
        line 416: 71
        line 417: 74
      LocalVariableTable:
        Start  Length  Slot  Name   Signature
           42      29     4     n   Lcom/fasterxml/jackson/databind/JsonNode;
           31      40     3    en   Ljava/util/Map$Entry;
            0      76     0  this   Lcom/fasterxml/jackson/databind/node/ObjectNode;
            0      76     1 properties   Ljava/util/Map;
      LocalVariableTypeTable:
        Start  Length  Slot  Name   Signature
           31      40     3    en   Ljava/util/Map$Entry<Ljava/lang/String;+Lcom/fasterxml/jackson/databind/JsonNode;>;
            0      76     1 properties   Ljava/util/Map<Ljava/lang/String;+Lcom/fasterxml/jackson/databind/JsonNode;>;
      StackMapTable: number_of_entries = 3
        frame_type = 252 /* append */
          offset_delta = 12
          locals = [ class java/util/Iterator ]
        frame_type = 253 /* append */
          offset_delta = 40
          locals = [ class java/util/Map$Entry, class com/fasterxml/jackson/databind/JsonNode ]
        frame_type = 248 /* chop */
          offset_delta = 20
    Signature: #243                         // <T:Lcom/fasterxml/jackson/databind/JsonNode;>(Ljava/util/Map<Ljava/lang/String;+Lcom/fasterxml/jackson/databind/JsonNode;>;)TT;

  public <T extends com.fasterxml.jackson.databind.JsonNode> T setAll(com.fasterxml.jackson.databind.node.ObjectNode);
    descriptor: (Lcom/fasterxml/jackson/databind/node/ObjectNode;)Lcom/fasterxml/jackson/databind/JsonNode;
    flags: (0x0001) ACC_PUBLIC
    Code:
      stack=2, locals=2, args_size=2
         0: aload_0
         1: getfield      #4                  // Field _children:Ljava/util/Map;
         4: aload_1
         5: getfield      #4                  // Field _children:Ljava/util/Map;
         8: invokeinterface #72,  2           // InterfaceMethod java/util/Map.putAll:(Ljava/util/Map;)V
        13: aload_0
        14: areturn
      LineNumberTable:
        line 435: 0
        line 436: 13
      LocalVariableTable:
        Start  Length  Slot  Name   Signature
            0      15     0  this   Lcom/fasterxml/jackson/databind/node/ObjectNode;
            0      15     1 other   Lcom/fasterxml/jackson/databind/node/ObjectNode;
    Signature: #245                         // <T:Lcom/fasterxml/jackson/databind/JsonNode;>(Lcom/fasterxml/jackson/databind/node/ObjectNode;)TT;

  public com.fasterxml.jackson.databind.JsonNode replace(java.lang.String, com.fasterxml.jackson.databind.JsonNode);
    descriptor: (Ljava/lang/String;Lcom/fasterxml/jackson/databind/JsonNode;)Lcom/fasterxml/jackson/databind/JsonNode;
    flags: (0x0001) ACC_PUBLIC
    Code:
      stack=3, locals=3, args_size=3
         0: aload_2
         1: ifnonnull     9
         4: aload_0
         5: invokevirtual #71                 // Method nullNode:()Lcom/fasterxml/jackson/databind/node/NullNode;
         8: astore_2
         9: aload_0
        10: getfield      #4                  // Field _children:Ljava/util/Map;
        13: aload_1
        14: aload_2
        15: invokeinterface #19,  3           // InterfaceMethod java/util/Map.put:(Ljava/lang/Object;Ljava/lang/Object;)Ljava/lang/Object;
        20: checkcast     #17                 // class com/fasterxml/jackson/databind/JsonNode
        23: areturn
      LineNumberTable:
        line 453: 0
        line 454: 4
        line 456: 9
      LocalVariableTable:
        Start  Length  Slot  Name   Signature
            0      24     0  this   Lcom/fasterxml/jackson/databind/node/ObjectNode;
            0      24     1 propertyName   Ljava/lang/String;
            0      24     2 value   Lcom/fasterxml/jackson/databind/JsonNode;
      StackMapTable: number_of_entries = 1
        frame_type = 9 /* same */

  public <T extends com.fasterxml.jackson.databind.JsonNode> T without(java.lang.String);
    descriptor: (Ljava/lang/String;)Lcom/fasterxml/jackson/databind/JsonNode;
    flags: (0x0001) ACC_PUBLIC
    Code:
      stack=2, locals=2, args_size=2
         0: aload_0
         1: getfield      #4                  // Field _children:Ljava/util/Map;
         4: aload_1
         5: invokeinterface #73,  2           // InterfaceMethod java/util/Map.remove:(Ljava/lang/Object;)Ljava/lang/Object;
        10: pop
        11: aload_0
        12: areturn
      LineNumberTable:
        line 472: 0
        line 473: 11
      LocalVariableTable:
        Start  Length  Slot  Name   Signature
            0      13     0  this   Lcom/fasterxml/jackson/databind/node/ObjectNode;
            0      13     1 propertyName   Ljava/lang/String;
    Signature: #248                         // <T:Lcom/fasterxml/jackson/databind/JsonNode;>(Ljava/lang/String;)TT;

  public <T extends com.fasterxml.jackson.databind.JsonNode> T without(java.util.Collection<java.lang.String>);
    descriptor: (Ljava/util/Collection;)Lcom/fasterxml/jackson/databind/JsonNode;
    flags: (0x0001) ACC_PUBLIC
    Code:
      stack=2, locals=2, args_size=2
         0: aload_0
         1: getfield      #4                  // Field _children:Ljava/util/Map;
         4: invokeinterface #27,  1           // InterfaceMethod java/util/Map.keySet:()Ljava/util/Set;
         9: aload_1
        10: invokeinterface #74,  2           // InterfaceMethod java/util/Set.removeAll:(Ljava/util/Collection;)Z
        15: pop
        16: aload_0
        17: areturn
      LineNumberTable:
        line 491: 0
        line 492: 16
      LocalVariableTable:
        Start  Length  Slot  Name   Signature
            0      18     0  this   Lcom/fasterxml/jackson/databind/node/ObjectNode;
            0      18     1 propertyNames   Ljava/util/Collection;
      LocalVariableTypeTable:
        Start  Length  Slot  Name   Signature
            0      18     1 propertyNames   Ljava/util/Collection<Ljava/lang/String;>;
    Signature: #253                         // <T:Lcom/fasterxml/jackson/databind/JsonNode;>(Ljava/util/Collection<Ljava/lang/String;>;)TT;

  public com.fasterxml.jackson.databind.JsonNode put(java.lang.String, com.fasterxml.jackson.databind.JsonNode);
    descriptor: (Ljava/lang/String;Lcom/fasterxml/jackson/databind/JsonNode;)Lcom/fasterxml/jackson/databind/JsonNode;
    flags: (0x0001) ACC_PUBLIC
    Code:
      stack=3, locals=3, args_size=3
         0: aload_2
         1: ifnonnull     9
         4: aload_0
         5: invokevirtual #71                 // Method nullNode:()Lcom/fasterxml/jackson/databind/node/NullNode;
         8: astore_2
         9: aload_0
        10: getfield      #4                  // Field _children:Ljava/util/Map;
        13: aload_1
        14: aload_2
        15: invokeinterface #19,  3           // InterfaceMethod java/util/Map.put:(Ljava/lang/Object;Ljava/lang/Object;)Ljava/lang/Object;
        20: checkcast     #17                 // class com/fasterxml/jackson/databind/JsonNode
        23: areturn
      LineNumberTable:
        line 517: 0
        line 518: 4
        line 520: 9
      LocalVariableTable:
        Start  Length  Slot  Name   Signature
            0      24     0  this   Lcom/fasterxml/jackson/databind/node/ObjectNode;
            0      24     1 propertyName   Ljava/lang/String;
            0      24     2 value   Lcom/fasterxml/jackson/databind/JsonNode;
      StackMapTable: number_of_entries = 1
        frame_type = 9 /* same */
    Deprecated: true
    RuntimeVisibleAnnotations:
      0: #257()
        java.lang.Deprecated

  public com.fasterxml.jackson.databind.JsonNode putIfAbsent(java.lang.String, com.fasterxml.jackson.databind.JsonNode);
    descriptor: (Ljava/lang/String;Lcom/fasterxml/jackson/databind/JsonNode;)Lcom/fasterxml/jackson/databind/JsonNode;
    flags: (0x0001) ACC_PUBLIC
    Code:
      stack=3, locals=3, args_size=3
         0: aload_2
         1: ifnonnull     9
         4: aload_0
         5: invokevirtual #71                 // Method nullNode:()Lcom/fasterxml/jackson/databind/node/NullNode;
         8: astore_2
         9: aload_0
        10: getfield      #4                  // Field _children:Ljava/util/Map;
        13: aload_1
        14: aload_2
        15: invokeinterface #75,  3           // InterfaceMethod java/util/Map.putIfAbsent:(Ljava/lang/Object;Ljava/lang/Object;)Ljava/lang/Object;
        20: checkcast     #17                 // class com/fasterxml/jackson/databind/JsonNode
        23: areturn
      LineNumberTable:
        line 548: 0
        line 549: 4
        line 551: 9
      LocalVariableTable:
        Start  Length  Slot  Name   Signature
            0      24     0  this   Lcom/fasterxml/jackson/databind/node/ObjectNode;
            0      24     1 propertyName   Ljava/lang/String;
            0      24     2 value   Lcom/fasterxml/jackson/databind/JsonNode;
      StackMapTable: number_of_entries = 1
        frame_type = 9 /* same */

  public com.fasterxml.jackson.databind.JsonNode remove(java.lang.String);
    descriptor: (Ljava/lang/String;)Lcom/fasterxml/jackson/databind/JsonNode;
    flags: (0x0001) ACC_PUBLIC
    Code:
      stack=2, locals=2, args_size=2
         0: aload_0
         1: getfield      #4                  // Field _children:Ljava/util/Map;
         4: aload_1
         5: invokeinterface #73,  2           // InterfaceMethod java/util/Map.remove:(Ljava/lang/Object;)Ljava/lang/Object;
        10: checkcast     #17                 // class com/fasterxml/jackson/databind/JsonNode
        13: areturn
      LineNumberTable:
        line 562: 0
      LocalVariableTable:
        Start  Length  Slot  Name   Signature
            0      14     0  this   Lcom/fasterxml/jackson/databind/node/ObjectNode;
            0      14     1 propertyName   Ljava/lang/String;

  public com.fasterxml.jackson.databind.node.ObjectNode remove(java.util.Collection<java.lang.String>);
    descriptor: (Ljava/util/Collection;)Lcom/fasterxml/jackson/databind/node/ObjectNode;
    flags: (0x0001) ACC_PUBLIC
    Code:
      stack=2, locals=2, args_size=2
         0: aload_0
         1: getfield      #4                  // Field _children:Ljava/util/Map;
         4: invokeinterface #27,  1           // InterfaceMethod java/util/Map.keySet:()Ljava/util/Set;
         9: aload_1
        10: invokeinterface #74,  2           // InterfaceMethod java/util/Set.removeAll:(Ljava/util/Collection;)Z
        15: pop
        16: aload_0
        17: areturn
      LineNumberTable:
        line 575: 0
        line 576: 16
      LocalVariableTable:
        Start  Length  Slot  Name   Signature
            0      18     0  this   Lcom/fasterxml/jackson/databind/node/ObjectNode;
            0      18     1 propertyNames   Ljava/util/Collection;
      LocalVariableTypeTable:
        Start  Length  Slot  Name   Signature
            0      18     1 propertyNames   Ljava/util/Collection<Ljava/lang/String;>;
    Signature: #261                         // (Ljava/util/Collection<Ljava/lang/String;>;)Lcom/fasterxml/jackson/databind/node/ObjectNode;

  public com.fasterxml.jackson.databind.node.ObjectNode removeAll();
    descriptor: ()Lcom/fasterxml/jackson/databind/node/ObjectNode;
    flags: (0x0001) ACC_PUBLIC
    Code:
      stack=1, locals=1, args_size=1
         0: aload_0
         1: getfield      #4                  // Field _children:Ljava/util/Map;
         4: invokeinterface #76,  1           // InterfaceMethod java/util/Map.clear:()V
         9: aload_0
        10: areturn
      LineNumberTable:
        line 588: 0
        line 589: 9
      LocalVariableTable:
        Start  Length  Slot  Name   Signature
            0      11     0  this   Lcom/fasterxml/jackson/databind/node/ObjectNode;

  public com.fasterxml.jackson.databind.JsonNode putAll(java.util.Map<java.lang.String, ? extends com.fasterxml.jackson.databind.JsonNode>);
    descriptor: (Ljava/util/Map;)Lcom/fasterxml/jackson/databind/JsonNode;
    flags: (0x0001) ACC_PUBLIC
    Code:
      stack=2, locals=2, args_size=2
         0: aload_0
         1: aload_1
         2: invokevirtual #77                 // Method setAll:(Ljava/util/Map;)Lcom/fasterxml/jackson/databind/JsonNode;
         5: areturn
      LineNumberTable:
        line 604: 0
      LocalVariableTable:
        Start  Length  Slot  Name   Signature
            0       6     0  this   Lcom/fasterxml/jackson/databind/node/ObjectNode;
            0       6     1 properties   Ljava/util/Map;
      LocalVariableTypeTable:
        Start  Length  Slot  Name   Signature
            0       6     1 properties   Ljava/util/Map<Ljava/lang/String;+Lcom/fasterxml/jackson/databind/JsonNode;>;
    Deprecated: true
    Signature: #264                         // (Ljava/util/Map<Ljava/lang/String;+Lcom/fasterxml/jackson/databind/JsonNode;>;)Lcom/fasterxml/jackson/databind/JsonNode;
    RuntimeVisibleAnnotations:
      0: #257()
        java.lang.Deprecated

  public com.fasterxml.jackson.databind.JsonNode putAll(com.fasterxml.jackson.databind.node.ObjectNode);
    descriptor: (Lcom/fasterxml/jackson/databind/node/ObjectNode;)Lcom/fasterxml/jackson/databind/JsonNode;
    flags: (0x0001) ACC_PUBLIC
    Code:
      stack=2, locals=2, args_size=2
         0: aload_0
         1: aload_1
         2: invokevirtual #78                 // Method setAll:(Lcom/fasterxml/jackson/databind/node/ObjectNode;)Lcom/fasterxml/jackson/databind/JsonNode;
         5: areturn
      LineNumberTable:
        line 619: 0
      LocalVariableTable:
        Start  Length  Slot  Name   Signature
            0       6     0  this   Lcom/fasterxml/jackson/databind/node/ObjectNode;
            0       6     1 other   Lcom/fasterxml/jackson/databind/node/ObjectNode;
    Deprecated: true
    RuntimeVisibleAnnotations:
      0: #257()
        java.lang.Deprecated

  public com.fasterxml.jackson.databind.node.ObjectNode retain(java.util.Collection<java.lang.String>);
    descriptor: (Ljava/util/Collection;)Lcom/fasterxml/jackson/databind/node/ObjectNode;
    flags: (0x0001) ACC_PUBLIC
    Code:
      stack=2, locals=2, args_size=2
         0: aload_0
         1: getfield      #4                  // Field _children:Ljava/util/Map;
         4: invokeinterface #27,  1           // InterfaceMethod java/util/Map.keySet:()Ljava/util/Set;
         9: aload_1
        10: invokeinterface #79,  2           // InterfaceMethod java/util/Set.retainAll:(Ljava/util/Collection;)Z
        15: pop
        16: aload_0
        17: areturn
      LineNumberTable:
        line 632: 0
        line 633: 16
      LocalVariableTable:
        Start  Length  Slot  Name   Signature
            0      18     0  this   Lcom/fasterxml/jackson/databind/node/ObjectNode;
            0      18     1 propertyNames   Ljava/util/Collection;
      LocalVariableTypeTable:
        Start  Length  Slot  Name   Signature
            0      18     1 propertyNames   Ljava/util/Collection<Ljava/lang/String;>;
    Signature: #261                         // (Ljava/util/Collection<Ljava/lang/String;>;)Lcom/fasterxml/jackson/databind/node/ObjectNode;

  public com.fasterxml.jackson.databind.node.ObjectNode retain(java.lang.String...);
    descriptor: ([Ljava/lang/String;)Lcom/fasterxml/jackson/databind/node/ObjectNode;
    flags: (0x0081) ACC_PUBLIC, ACC_VARARGS
    Code:
      stack=2, locals=2, args_size=2
         0: aload_0
         1: aload_1
         2: invokestatic  #80                 // Method java/util/Arrays.asList:([Ljava/lang/Object;)Ljava/util/List;
         5: invokevirtual #81                 // Method retain:(Ljava/util/Collection;)Lcom/fasterxml/jackson/databind/node/ObjectNode;
         8: areturn
      LineNumberTable:
        line 645: 0
      LocalVariableTable:
        Start  Length  Slot  Name   Signature
            0       9     0  this   Lcom/fasterxml/jackson/databind/node/ObjectNode;
            0       9     1 propertyNames   [Ljava/lang/String;

  public com.fasterxml.jackson.databind.node.ArrayNode putArray(java.lang.String);
    descriptor: (Ljava/lang/String;)Lcom/fasterxml/jackson/databind/node/ArrayNode;
    flags: (0x0001) ACC_PUBLIC
    Code:
      stack=3, locals=3, args_size=2
         0: aload_0
         1: invokevirtual #46                 // Method arrayNode:()Lcom/fasterxml/jackson/databind/node/ArrayNode;
         4: astore_2
         5: aload_0
         6: aload_1
         7: aload_2
         8: invokevirtual #82                 // Method _put:(Ljava/lang/String;Lcom/fasterxml/jackson/databind/JsonNode;)Lcom/fasterxml/jackson/databind/node/ObjectNode;
        11: pop
        12: aload_2
        13: areturn
      LineNumberTable:
        line 667: 0
        line 668: 5
        line 669: 12
      LocalVariableTable:
        Start  Length  Slot  Name   Signature
            0      14     0  this   Lcom/fasterxml/jackson/databind/node/ObjectNode;
            0      14     1 propertyName   Ljava/lang/String;
            5       9     2     n   Lcom/fasterxml/jackson/databind/node/ArrayNode;

  public com.fasterxml.jackson.databind.node.ObjectNode putObject(java.lang.String);
    descriptor: (Ljava/lang/String;)Lcom/fasterxml/jackson/databind/node/ObjectNode;
    flags: (0x0001) ACC_PUBLIC
    Code:
      stack=3, locals=3, args_size=2
         0: aload_0
         1: invokevirtual #43                 // Method objectNode:()Lcom/fasterxml/jackson/databind/node/ObjectNode;
         4: astore_2
         5: aload_0
         6: aload_1
         7: aload_2
         8: invokevirtual #82                 // Method _put:(Ljava/lang/String;Lcom/fasterxml/jackson/databind/JsonNode;)Lcom/fasterxml/jackson/databind/node/ObjectNode;
        11: pop
        12: aload_2
        13: areturn
      LineNumberTable:
        line 685: 0
        line 686: 5
        line 687: 12
      LocalVariableTable:
        Start  Length  Slot  Name   Signature
            0      14     0  this   Lcom/fasterxml/jackson/databind/node/ObjectNode;
            0      14     1 propertyName   Ljava/lang/String;
            5       9     2     n   Lcom/fasterxml/jackson/databind/node/ObjectNode;

  public com.fasterxml.jackson.databind.node.ObjectNode putPOJO(java.lang.String, java.lang.Object);
    descriptor: (Ljava/lang/String;Ljava/lang/Object;)Lcom/fasterxml/jackson/databind/node/ObjectNode;
    flags: (0x0001) ACC_PUBLIC
    Code:
      stack=4, locals=3, args_size=3
         0: aload_0
         1: aload_1
         2: aload_0
         3: aload_2
         4: invokevirtual #83                 // Method pojoNode:(Ljava/lang/Object;)Lcom/fasterxml/jackson/databind/node/ValueNode;
         7: invokevirtual #82                 // Method _put:(Ljava/lang/String;Lcom/fasterxml/jackson/databind/JsonNode;)Lcom/fasterxml/jackson/databind/node/ObjectNode;
        10: areturn
      LineNumberTable:
        line 709: 0
      LocalVariableTable:
        Start  Length  Slot  Name   Signature
            0      11     0  this   Lcom/fasterxml/jackson/databind/node/ObjectNode;
            0      11     1 propertyName   Ljava/lang/String;
            0      11     2  pojo   Ljava/lang/Object;

  public com.fasterxml.jackson.databind.node.ObjectNode putRawValue(java.lang.String, com.fasterxml.jackson.databind.util.RawValue);
    descriptor: (Ljava/lang/String;Lcom/fasterxml/jackson/databind/util/RawValue;)Lcom/fasterxml/jackson/databind/node/ObjectNode;
    flags: (0x0001) ACC_PUBLIC
    Code:
      stack=4, locals=3, args_size=3
         0: aload_0
         1: aload_1
         2: aload_0
         3: aload_2
         4: invokevirtual #84                 // Method rawValueNode:(Lcom/fasterxml/jackson/databind/util/RawValue;)Lcom/fasterxml/jackson/databind/node/ValueNode;
         7: invokevirtual #82                 // Method _put:(Ljava/lang/String;Lcom/fasterxml/jackson/databind/JsonNode;)Lcom/fasterxml/jackson/databind/node/ObjectNode;
        10: areturn
      LineNumberTable:
        line 716: 0
      LocalVariableTable:
        Start  Length  Slot  Name   Signature
            0      11     0  this   Lcom/fasterxml/jackson/databind/node/ObjectNode;
            0      11     1 propertyName   Ljava/lang/String;
            0      11     2   raw   Lcom/fasterxml/jackson/databind/util/RawValue;

  public com.fasterxml.jackson.databind.node.ObjectNode putNull(java.lang.String);
    descriptor: (Ljava/lang/String;)Lcom/fasterxml/jackson/databind/node/ObjectNode;
    flags: (0x0001) ACC_PUBLIC
    Code:
      stack=3, locals=2, args_size=2
         0: aload_0
         1: getfield      #4                  // Field _children:Ljava/util/Map;
         4: aload_1
         5: aload_0
         6: invokevirtual #71                 // Method nullNode:()Lcom/fasterxml/jackson/databind/node/NullNode;
         9: invokeinterface #19,  3           // InterfaceMethod java/util/Map.put:(Ljava/lang/Object;Ljava/lang/Object;)Ljava/lang/Object;
        14: pop
        15: aload_0
        16: areturn
      LineNumberTable:
        line 728: 0
        line 729: 15
      LocalVariableTable:
        Start  Length  Slot  Name   Signature
            0      17     0  this   Lcom/fasterxml/jackson/databind/node/ObjectNode;
            0      17     1 propertyName   Ljava/lang/String;

  public com.fasterxml.jackson.databind.node.ObjectNode put(java.lang.String, short);
    descriptor: (Ljava/lang/String;S)Lcom/fasterxml/jackson/databind/node/ObjectNode;
    flags: (0x0001) ACC_PUBLIC
    Code:
      stack=4, locals=3, args_size=3
         0: aload_0
         1: aload_1
         2: aload_0
         3: iload_2
         4: invokevirtual #85                 // Method numberNode:(S)Lcom/fasterxml/jackson/databind/node/NumericNode;
         7: invokevirtual #82                 // Method _put:(Ljava/lang/String;Lcom/fasterxml/jackson/databind/JsonNode;)Lcom/fasterxml/jackson/databind/node/ObjectNode;
        10: areturn
      LineNumberTable:
        line 738: 0
      LocalVariableTable:
        Start  Length  Slot  Name   Signature
            0      11     0  this   Lcom/fasterxml/jackson/databind/node/ObjectNode;
            0      11     1 propertyName   Ljava/lang/String;
            0      11     2     v   S

  public com.fasterxml.jackson.databind.node.ObjectNode put(java.lang.String, java.lang.Short);
    descriptor: (Ljava/lang/String;Ljava/lang/Short;)Lcom/fasterxml/jackson/databind/node/ObjectNode;
    flags: (0x0001) ACC_PUBLIC
    Code:
      stack=4, locals=3, args_size=3
         0: aload_0
         1: aload_1
         2: aload_2
         3: ifnonnull     13
         6: aload_0
         7: invokevirtual #71                 // Method nullNode:()Lcom/fasterxml/jackson/databind/node/NullNode;
        10: goto          21
        13: aload_0
        14: aload_2
        15: invokevirtual #86                 // Method java/lang/Short.shortValue:()S
        18: invokevirtual #85                 // Method numberNode:(S)Lcom/fasterxml/jackson/databind/node/NumericNode;
        21: invokevirtual #82                 // Method _put:(Ljava/lang/String;Lcom/fasterxml/jackson/databind/JsonNode;)Lcom/fasterxml/jackson/databind/node/ObjectNode;
        24: areturn
      LineNumberTable:
        line 748: 0
        line 749: 15
        line 748: 21
      LocalVariableTable:
        Start  Length  Slot  Name   Signature
            0      25     0  this   Lcom/fasterxml/jackson/databind/node/ObjectNode;
            0      25     1 fieldName   Ljava/lang/String;
            0      25     2     v   Ljava/lang/Short;
      StackMapTable: number_of_entries = 2
        frame_type = 255 /* full_frame */
          offset_delta = 13
          locals = [ class com/fasterxml/jackson/databind/node/ObjectNode, class java/lang/String, class java/lang/Short ]
          stack = [ class com/fasterxml/jackson/databind/node/ObjectNode, class java/lang/String ]
        frame_type = 255 /* full_frame */
          offset_delta = 7
          locals = [ class com/fasterxml/jackson/databind/node/ObjectNode, class java/lang/String, class java/lang/Short ]
          stack = [ class com/fasterxml/jackson/databind/node/ObjectNode, class java/lang/String, class com/fasterxml/jackson/databind/JsonNode ]

  public com.fasterxml.jackson.databind.node.ObjectNode put(java.lang.String, int);
    descriptor: (Ljava/lang/String;I)Lcom/fasterxml/jackson/databind/node/ObjectNode;
    flags: (0x0001) ACC_PUBLIC
    Code:
      stack=4, locals=3, args_size=3
         0: aload_0
         1: aload_1
         2: aload_0
         3: iload_2
         4: invokevirtual #87                 // Method numberNode:(I)Lcom/fasterxml/jackson/databind/node/NumericNode;
         7: invokevirtual #82                 // Method _put:(Ljava/lang/String;Lcom/fasterxml/jackson/databind/JsonNode;)Lcom/fasterxml/jackson/databind/node/ObjectNode;
        10: areturn
      LineNumberTable:
        line 762: 0
      LocalVariableTable:
        Start  Length  Slot  Name   Signature
            0      11     0  this   Lcom/fasterxml/jackson/databind/node/ObjectNode;
            0      11     1 fieldName   Ljava/lang/String;
            0      11     2     v   I

  public com.fasterxml.jackson.databind.node.ObjectNode put(java.lang.String, java.lang.Integer);
    descriptor: (Ljava/lang/String;Ljava/lang/Integer;)Lcom/fasterxml/jackson/databind/node/ObjectNode;
    flags: (0x0001) ACC_PUBLIC
    Code:
      stack=4, locals=3, args_size=3
         0: aload_0
         1: aload_1
         2: aload_2
         3: ifnonnull     13
         6: aload_0
         7: invokevirtual #71                 // Method nullNode:()Lcom/fasterxml/jackson/databind/node/NullNode;
        10: goto          21
        13: aload_0
        14: aload_2
        15: invokevirtual #88                 // Method java/lang/Integer.intValue:()I
        18: invokevirtual #87                 // Method numberNode:(I)Lcom/fasterxml/jackson/databind/node/NumericNode;
        21: invokevirtual #82                 // Method _put:(Ljava/lang/String;Lcom/fasterxml/jackson/databind/JsonNode;)Lcom/fasterxml/jackson/databind/node/ObjectNode;
        24: areturn
      LineNumberTable:
        line 772: 0
        line 773: 15
        line 772: 21
      LocalVariableTable:
        Start  Length  Slot  Name   Signature
            0      25     0  this   Lcom/fasterxml/jackson/databind/node/ObjectNode;
            0      25     1 fieldName   Ljava/lang/String;
            0      25     2     v   Ljava/lang/Integer;
      StackMapTable: number_of_entries = 2
        frame_type = 255 /* full_frame */
          offset_delta = 13
          locals = [ class com/fasterxml/jackson/databind/node/ObjectNode, class java/lang/String, class java/lang/Integer ]
          stack = [ class com/fasterxml/jackson/databind/node/ObjectNode, class java/lang/String ]
        frame_type = 255 /* full_frame */
          offset_delta = 7
          locals = [ class com/fasterxml/jackson/databind/node/ObjectNode, class java/lang/String, class java/lang/Integer ]
          stack = [ class com/fasterxml/jackson/databind/node/ObjectNode, class java/lang/String, class com/fasterxml/jackson/databind/JsonNode ]

  public com.fasterxml.jackson.databind.node.ObjectNode put(java.lang.String, long);
    descriptor: (Ljava/lang/String;J)Lcom/fasterxml/jackson/databind/node/ObjectNode;
    flags: (0x0001) ACC_PUBLIC
    Code:
      stack=5, locals=4, args_size=3
         0: aload_0
         1: aload_1
         2: aload_0
         3: lload_2
         4: invokevirtual #89                 // Method numberNode:(J)Lcom/fasterxml/jackson/databind/node/NumericNode;
         7: invokevirtual #82                 // Method _put:(Ljava/lang/String;Lcom/fasterxml/jackson/databind/JsonNode;)Lcom/fasterxml/jackson/databind/node/ObjectNode;
        10: areturn
      LineNumberTable:
        line 786: 0
      LocalVariableTable:
        Start  Length  Slot  Name   Signature
            0      11     0  this   Lcom/fasterxml/jackson/databind/node/ObjectNode;
            0      11     1 fieldName   Ljava/lang/String;
            0      11     2     v   J

  public com.fasterxml.jackson.databind.node.ObjectNode put(java.lang.String, java.lang.Long);
    descriptor: (Ljava/lang/String;Ljava/lang/Long;)Lcom/fasterxml/jackson/databind/node/ObjectNode;
    flags: (0x0001) ACC_PUBLIC
    Code:
      stack=5, locals=3, args_size=3
         0: aload_0
         1: aload_1
         2: aload_2
         3: ifnonnull     13
         6: aload_0
         7: invokevirtual #71                 // Method nullNode:()Lcom/fasterxml/jackson/databind/node/NullNode;
        10: goto          21
        13: aload_0
        14: aload_2
        15: invokevirtual #90                 // Method java/lang/Long.longValue:()J
        18: invokevirtual #89                 // Method numberNode:(J)Lcom/fasterxml/jackson/databind/node/NumericNode;
        21: invokevirtual #82                 // Method _put:(Ljava/lang/String;Lcom/fasterxml/jackson/databind/JsonNode;)Lcom/fasterxml/jackson/databind/node/ObjectNode;
        24: areturn
      LineNumberTable:
        line 802: 0
        line 803: 15
        line 802: 21
      LocalVariableTable:
        Start  Length  Slot  Name   Signature
            0      25     0  this   Lcom/fasterxml/jackson/databind/node/ObjectNode;
            0      25     1 fieldName   Ljava/lang/String;
            0      25     2     v   Ljava/lang/Long;
      StackMapTable: number_of_entries = 2
        frame_type = 255 /* full_frame */
          offset_delta = 13
          locals = [ class com/fasterxml/jackson/databind/node/ObjectNode, class java/lang/String, class java/lang/Long ]
          stack = [ class com/fasterxml/jackson/databind/node/ObjectNode, class java/lang/String ]
        frame_type = 255 /* full_frame */
          offset_delta = 7
          locals = [ class com/fasterxml/jackson/databind/node/ObjectNode, class java/lang/String, class java/lang/Long ]
          stack = [ class com/fasterxml/jackson/databind/node/ObjectNode, class java/lang/String, class com/fasterxml/jackson/databind/JsonNode ]

  public com.fasterxml.jackson.databind.node.ObjectNode put(java.lang.String, float);
    descriptor: (Ljava/lang/String;F)Lcom/fasterxml/jackson/databind/node/ObjectNode;
    flags: (0x0001) ACC_PUBLIC
    Code:
      stack=4, locals=3, args_size=3
         0: aload_0
         1: aload_1
         2: aload_0
         3: fload_2
         4: invokevirtual #91                 // Method numberNode:(F)Lcom/fasterxml/jackson/databind/node/NumericNode;
         7: invokevirtual #82                 // Method _put:(Ljava/lang/String;Lcom/fasterxml/jackson/databind/JsonNode;)Lcom/fasterxml/jackson/databind/node/ObjectNode;
        10: areturn
      LineNumberTable:
        line 812: 0
      LocalVariableTable:
        Start  Length  Slot  Name   Signature
            0      11     0  this   Lcom/fasterxml/jackson/databind/node/ObjectNode;
            0      11     1 fieldName   Ljava/lang/String;
            0      11     2     v   F

  public com.fasterxml.jackson.databind.node.ObjectNode put(java.lang.String, java.lang.Float);
    descriptor: (Ljava/lang/String;Ljava/lang/Float;)Lcom/fasterxml/jackson/databind/node/ObjectNode;
    flags: (0x0001) ACC_PUBLIC
    Code:
      stack=4, locals=3, args_size=3
         0: aload_0
         1: aload_1
         2: aload_2
         3: ifnonnull     13
         6: aload_0
         7: invokevirtual #71                 // Method nullNode:()Lcom/fasterxml/jackson/databind/node/NullNode;
        10: goto          21
        13: aload_0
        14: aload_2
        15: invokevirtual #92                 // Method java/lang/Float.floatValue:()F
        18: invokevirtual #91                 // Method numberNode:(F)Lcom/fasterxml/jackson/databind/node/NumericNode;
        21: invokevirtual #82                 // Method _put:(Ljava/lang/String;Lcom/fasterxml/jackson/databind/JsonNode;)Lcom/fasterxml/jackson/databind/node/ObjectNode;
        24: areturn
      LineNumberTable:
        line 822: 0
        line 823: 15
        line 822: 21
      LocalVariableTable:
        Start  Length  Slot  Name   Signature
            0      25     0  this   Lcom/fasterxml/jackson/databind/node/ObjectNode;
            0      25     1 fieldName   Ljava/lang/String;
            0      25     2     v   Ljava/lang/Float;
      StackMapTable: number_of_entries = 2
        frame_type = 255 /* full_frame */
          offset_delta = 13
          locals = [ class com/fasterxml/jackson/databind/node/ObjectNode, class java/lang/String, class java/lang/Float ]
          stack = [ class com/fasterxml/jackson/databind/node/ObjectNode, class java/lang/String ]
        frame_type = 255 /* full_frame */
          offset_delta = 7
          locals = [ class com/fasterxml/jackson/databind/node/ObjectNode, class java/lang/String, class java/lang/Float ]
          stack = [ class com/fasterxml/jackson/databind/node/ObjectNode, class java/lang/String, class com/fasterxml/jackson/databind/JsonNode ]

  public com.fasterxml.jackson.databind.node.ObjectNode put(java.lang.String, double);
    descriptor: (Ljava/lang/String;D)Lcom/fasterxml/jackson/databind/node/ObjectNode;
    flags: (0x0001) ACC_PUBLIC
    Code:
      stack=5, locals=4, args_size=3
         0: aload_0
         1: aload_1
         2: aload_0
         3: dload_2
         4: invokevirtual #93                 // Method numberNode:(D)Lcom/fasterxml/jackson/databind/node/NumericNode;
         7: invokevirtual #82                 // Method _put:(Ljava/lang/String;Lcom/fasterxml/jackson/databind/JsonNode;)Lcom/fasterxml/jackson/databind/node/ObjectNode;
        10: areturn
      LineNumberTable:
        line 832: 0
      LocalVariableTable:
        Start  Length  Slot  Name   Signature
            0      11     0  this   Lcom/fasterxml/jackson/databind/node/ObjectNode;
            0      11     1 fieldName   Ljava/lang/String;
            0      11     2     v   D

  public com.fasterxml.jackson.databind.node.ObjectNode put(java.lang.String, java.lang.Double);
    descriptor: (Ljava/lang/String;Ljava/lang/Double;)Lcom/fasterxml/jackson/databind/node/ObjectNode;
    flags: (0x0001) ACC_PUBLIC
    Code:
      stack=5, locals=3, args_size=3
         0: aload_0
         1: aload_1
         2: aload_2
         3: ifnonnull     13
         6: aload_0
         7: invokevirtual #71                 // Method nullNode:()Lcom/fasterxml/jackson/databind/node/NullNode;
        10: goto          21
        13: aload_0
        14: aload_2
        15: invokevirtual #94                 // Method java/lang/Double.doubleValue:()D
        18: invokevirtual #93                 // Method numberNode:(D)Lcom/fasterxml/jackson/databind/node/NumericNode;
        21: invokevirtual #82                 // Method _put:(Ljava/lang/String;Lcom/fasterxml/jackson/databind/JsonNode;)Lcom/fasterxml/jackson/databind/node/ObjectNode;
        24: areturn
      LineNumberTable:
        line 842: 0
        line 843: 15
        line 842: 21
      LocalVariableTable:
        Start  Length  Slot  Name   Signature
            0      25     0  this   Lcom/fasterxml/jackson/databind/node/ObjectNode;
            0      25     1 fieldName   Ljava/lang/String;
            0      25     2     v   Ljava/lang/Double;
      StackMapTable: number_of_entries = 2
        frame_type = 255 /* full_frame */
          offset_delta = 13
          locals = [ class com/fasterxml/jackson/databind/node/ObjectNode, class java/lang/String, class java/lang/Double ]
          stack = [ class com/fasterxml/jackson/databind/node/ObjectNode, class java/lang/String ]
        frame_type = 255 /* full_frame */
          offset_delta = 7
          locals = [ class com/fasterxml/jackson/databind/node/ObjectNode, class java/lang/String, class java/lang/Double ]
          stack = [ class com/fasterxml/jackson/databind/node/ObjectNode, class java/lang/String, class com/fasterxml/jackson/databind/JsonNode ]

  public com.fasterxml.jackson.databind.node.ObjectNode put(java.lang.String, java.math.BigDecimal);
    descriptor: (Ljava/lang/String;Ljava/math/BigDecimal;)Lcom/fasterxml/jackson/databind/node/ObjectNode;
    flags: (0x0001) ACC_PUBLIC
    Code:
      stack=4, locals=3, args_size=3
         0: aload_0
         1: aload_1
         2: aload_2
         3: ifnonnull     13
         6: aload_0
         7: invokevirtual #71                 // Method nullNode:()Lcom/fasterxml/jackson/databind/node/NullNode;
        10: goto          18
        13: aload_0
        14: aload_2
        15: invokevirtual #95                 // Method numberNode:(Ljava/math/BigDecimal;)Lcom/fasterxml/jackson/databind/node/ValueNode;
        18: invokevirtual #82                 // Method _put:(Ljava/lang/String;Lcom/fasterxml/jackson/databind/JsonNode;)Lcom/fasterxml/jackson/databind/node/ObjectNode;
        21: areturn
      LineNumberTable:
        line 852: 0
        line 853: 15
        line 852: 18
      LocalVariableTable:
        Start  Length  Slot  Name   Signature
            0      22     0  this   Lcom/fasterxml/jackson/databind/node/ObjectNode;
            0      22     1 fieldName   Ljava/lang/String;
            0      22     2     v   Ljava/math/BigDecimal;
      StackMapTable: number_of_entries = 2
        frame_type = 255 /* full_frame */
          offset_delta = 13
          locals = [ class com/fasterxml/jackson/databind/node/ObjectNode, class java/lang/String, class java/math/BigDecimal ]
          stack = [ class com/fasterxml/jackson/databind/node/ObjectNode, class java/lang/String ]
        frame_type = 255 /* full_frame */
          offset_delta = 4
          locals = [ class com/fasterxml/jackson/databind/node/ObjectNode, class java/lang/String, class java/math/BigDecimal ]
          stack = [ class com/fasterxml/jackson/databind/node/ObjectNode, class java/lang/String, class com/fasterxml/jackson/databind/JsonNode ]

  public com.fasterxml.jackson.databind.node.ObjectNode put(java.lang.String, java.math.BigInteger);
    descriptor: (Ljava/lang/String;Ljava/math/BigInteger;)Lcom/fasterxml/jackson/databind/node/ObjectNode;
    flags: (0x0001) ACC_PUBLIC
    Code:
      stack=4, locals=3, args_size=3
         0: aload_0
         1: aload_1
         2: aload_2
         3: ifnonnull     13
         6: aload_0
         7: invokevirtual #71                 // Method nullNode:()Lcom/fasterxml/jackson/databind/node/NullNode;
        10: goto          18
        13: aload_0
        14: aload_2
        15: invokevirtual #96                 // Method numberNode:(Ljava/math/BigInteger;)Lcom/fasterxml/jackson/databind/node/ValueNode;
        18: invokevirtual #82                 // Method _put:(Ljava/lang/String;Lcom/fasterxml/jackson/databind/JsonNode;)Lcom/fasterxml/jackson/databind/node/ObjectNode;
        21: areturn
      LineNumberTable:
        line 864: 0
        line 865: 15
        line 864: 18
      LocalVariableTable:
        Start  Length  Slot  Name   Signature
            0      22     0  this   Lcom/fasterxml/jackson/databind/node/ObjectNode;
            0      22     1 fieldName   Ljava/lang/String;
            0      22     2     v   Ljava/math/BigInteger;
      StackMapTable: number_of_entries = 2
        frame_type = 255 /* full_frame */
          offset_delta = 13
          locals = [ class com/fasterxml/jackson/databind/node/ObjectNode, class java/lang/String, class java/math/BigInteger ]
          stack = [ class com/fasterxml/jackson/databind/node/ObjectNode, class java/lang/String ]
        frame_type = 255 /* full_frame */
          offset_delta = 4
          locals = [ class com/fasterxml/jackson/databind/node/ObjectNode, class java/lang/String, class java/math/BigInteger ]
          stack = [ class com/fasterxml/jackson/databind/node/ObjectNode, class java/lang/String, class com/fasterxml/jackson/databind/JsonNode ]

  public com.fasterxml.jackson.databind.node.ObjectNode put(java.lang.String, java.lang.String);
    descriptor: (Ljava/lang/String;Ljava/lang/String;)Lcom/fasterxml/jackson/databind/node/ObjectNode;
    flags: (0x0001) ACC_PUBLIC
    Code:
      stack=4, locals=3, args_size=3
         0: aload_0
         1: aload_1
         2: aload_2
         3: ifnonnull     13
         6: aload_0
         7: invokevirtual #71                 // Method nullNode:()Lcom/fasterxml/jackson/databind/node/NullNode;
        10: goto          18
        13: aload_0
        14: aload_2
        15: invokevirtual #97                 // Method textNode:(Ljava/lang/String;)Lcom/fasterxml/jackson/databind/node/TextNode;
        18: invokevirtual #82                 // Method _put:(Ljava/lang/String;Lcom/fasterxml/jackson/databind/JsonNode;)Lcom/fasterxml/jackson/databind/node/ObjectNode;
        21: areturn
      LineNumberTable:
        line 874: 0
        line 875: 15
        line 874: 18
      LocalVariableTable:
        Start  Length  Slot  Name   Signature
            0      22     0  this   Lcom/fasterxml/jackson/databind/node/ObjectNode;
            0      22     1 fieldName   Ljava/lang/String;
            0      22     2     v   Ljava/lang/String;
      StackMapTable: number_of_entries = 2
        frame_type = 255 /* full_frame */
          offset_delta = 13
          locals = [ class com/fasterxml/jackson/databind/node/ObjectNode, class java/lang/String, class java/lang/String ]
          stack = [ class com/fasterxml/jackson/databind/node/ObjectNode, class java/lang/String ]
        frame_type = 255 /* full_frame */
          offset_delta = 4
          locals = [ class com/fasterxml/jackson/databind/node/ObjectNode, class java/lang/String, class java/lang/String ]
          stack = [ class com/fasterxml/jackson/databind/node/ObjectNode, class java/lang/String, class com/fasterxml/jackson/databind/JsonNode ]

  public com.fasterxml.jackson.databind.node.ObjectNode put(java.lang.String, boolean);
    descriptor: (Ljava/lang/String;Z)Lcom/fasterxml/jackson/databind/node/ObjectNode;
    flags: (0x0001) ACC_PUBLIC
    Code:
      stack=4, locals=3, args_size=3
         0: aload_0
         1: aload_1
         2: aload_0
         3: iload_2
         4: invokevirtual #98                 // Method booleanNode:(Z)Lcom/fasterxml/jackson/databind/node/BooleanNode;
         7: invokevirtual #82                 // Method _put:(Ljava/lang/String;Lcom/fasterxml/jackson/databind/JsonNode;)Lcom/fasterxml/jackson/databind/node/ObjectNode;
        10: areturn
      LineNumberTable:
        line 884: 0
      LocalVariableTable:
        Start  Length  Slot  Name   Signature
            0      11     0  this   Lcom/fasterxml/jackson/databind/node/ObjectNode;
            0      11     1 fieldName   Ljava/lang/String;
            0      11     2     v   Z

  public com.fasterxml.jackson.databind.node.ObjectNode put(java.lang.String, java.lang.Boolean);
    descriptor: (Ljava/lang/String;Ljava/lang/Boolean;)Lcom/fasterxml/jackson/databind/node/ObjectNode;
    flags: (0x0001) ACC_PUBLIC
    Code:
      stack=4, locals=3, args_size=3
         0: aload_0
         1: aload_1
         2: aload_2
         3: ifnonnull     13
         6: aload_0
         7: invokevirtual #71                 // Method nullNode:()Lcom/fasterxml/jackson/databind/node/NullNode;
        10: goto          21
        13: aload_0
        14: aload_2
        15: invokevirtual #99                 // Method java/lang/Boolean.booleanValue:()Z
        18: invokevirtual #98                 // Method booleanNode:(Z)Lcom/fasterxml/jackson/databind/node/BooleanNode;
        21: invokevirtual #82                 // Method _put:(Ljava/lang/String;Lcom/fasterxml/jackson/databind/JsonNode;)Lcom/fasterxml/jackson/databind/node/ObjectNode;
        24: areturn
      LineNumberTable:
        line 894: 0
        line 895: 15
        line 894: 21
      LocalVariableTable:
        Start  Length  Slot  Name   Signature
            0      25     0  this   Lcom/fasterxml/jackson/databind/node/ObjectNode;
            0      25     1 fieldName   Ljava/lang/String;
            0      25     2     v   Ljava/lang/Boolean;
      StackMapTable: number_of_entries = 2
        frame_type = 255 /* full_frame */
          offset_delta = 13
          locals = [ class com/fasterxml/jackson/databind/node/ObjectNode, class java/lang/String, class java/lang/Boolean ]
          stack = [ class com/fasterxml/jackson/databind/node/ObjectNode, class java/lang/String ]
        frame_type = 255 /* full_frame */
          offset_delta = 7
          locals = [ class com/fasterxml/jackson/databind/node/ObjectNode, class java/lang/String, class java/lang/Boolean ]
          stack = [ class com/fasterxml/jackson/databind/node/ObjectNode, class java/lang/String, class com/fasterxml/jackson/databind/JsonNode ]

  public com.fasterxml.jackson.databind.node.ObjectNode put(java.lang.String, byte[]);
    descriptor: (Ljava/lang/String;[B)Lcom/fasterxml/jackson/databind/node/ObjectNode;
    flags: (0x0001) ACC_PUBLIC
    Code:
      stack=4, locals=3, args_size=3
         0: aload_0
         1: aload_1
         2: aload_2
         3: ifnonnull     13
         6: aload_0
         7: invokevirtual #71                 // Method nullNode:()Lcom/fasterxml/jackson/databind/node/NullNode;
        10: goto          18
        13: aload_0
        14: aload_2
        15: invokevirtual #100                // Method binaryNode:([B)Lcom/fasterxml/jackson/databind/node/BinaryNode;
        18: invokevirtual #82                 // Method _put:(Ljava/lang/String;Lcom/fasterxml/jackson/databind/JsonNode;)Lcom/fasterxml/jackson/databind/node/ObjectNode;
        21: areturn
      LineNumberTable:
        line 904: 0
        line 905: 15
        line 904: 18
      LocalVariableTable:
        Start  Length  Slot  Name   Signature
            0      22     0  this   Lcom/fasterxml/jackson/databind/node/ObjectNode;
            0      22     1 fieldName   Ljava/lang/String;
            0      22     2     v   [B
      StackMapTable: number_of_entries = 2
        frame_type = 255 /* full_frame */
          offset_delta = 13
          locals = [ class com/fasterxml/jackson/databind/node/ObjectNode, class java/lang/String, class "[B" ]
          stack = [ class com/fasterxml/jackson/databind/node/ObjectNode, class java/lang/String ]
        frame_type = 255 /* full_frame */
          offset_delta = 4
          locals = [ class com/fasterxml/jackson/databind/node/ObjectNode, class java/lang/String, class "[B" ]
          stack = [ class com/fasterxml/jackson/databind/node/ObjectNode, class java/lang/String, class com/fasterxml/jackson/databind/JsonNode ]

  public boolean equals(java.lang.Object);
    descriptor: (Ljava/lang/Object;)Z
    flags: (0x0001) ACC_PUBLIC
    Code:
      stack=2, locals=2, args_size=2
         0: aload_1
         1: aload_0
         2: if_acmpne     7
         5: iconst_1
         6: ireturn
         7: aload_1
         8: ifnonnull     13
        11: iconst_0
        12: ireturn
        13: aload_1
        14: instanceof    #7                  // class com/fasterxml/jackson/databind/node/ObjectNode
        17: ifeq          29
        20: aload_0
        21: aload_1
        22: checkcast     #7                  // class com/fasterxml/jackson/databind/node/ObjectNode
        25: invokevirtual #101                // Method _childrenEqual:(Lcom/fasterxml/jackson/databind/node/ObjectNode;)Z
        28: ireturn
        29: iconst_0
        30: ireturn
      LineNumberTable:
        line 917: 0
        line 918: 7
        line 919: 13
        line 920: 20
        line 922: 29
      LocalVariableTable:
        Start  Length  Slot  Name   Signature
            0      31     0  this   Lcom/fasterxml/jackson/databind/node/ObjectNode;
            0      31     1     o   Ljava/lang/Object;
      StackMapTable: number_of_entries = 3
        frame_type = 7 /* same */
        frame_type = 5 /* same */
        frame_type = 15 /* same */

  protected boolean _childrenEqual(com.fasterxml.jackson.databind.node.ObjectNode);
    descriptor: (Lcom/fasterxml/jackson/databind/node/ObjectNode;)Z
    flags: (0x0004) ACC_PROTECTED
    Code:
      stack=2, locals=2, args_size=2
         0: aload_0
         1: getfield      #4                  // Field _children:Ljava/util/Map;
         4: aload_1
         5: getfield      #4                  // Field _children:Ljava/util/Map;
         8: invokeinterface #102,  2          // InterfaceMethod java/util/Map.equals:(Ljava/lang/Object;)Z
        13: ireturn
      LineNumberTable:
        line 930: 0
      LocalVariableTable:
        Start  Length  Slot  Name   Signature
            0      14     0  this   Lcom/fasterxml/jackson/databind/node/ObjectNode;
            0      14     1 other   Lcom/fasterxml/jackson/databind/node/ObjectNode;

  public int hashCode();
    descriptor: ()I
    flags: (0x0001) ACC_PUBLIC
    Code:
      stack=1, locals=1, args_size=1
         0: aload_0
         1: getfield      #4                  // Field _children:Ljava/util/Map;
         4: invokeinterface #103,  1          // InterfaceMethod java/util/Map.hashCode:()I
         9: ireturn
      LineNumberTable:
        line 936: 0
      LocalVariableTable:
        Start  Length  Slot  Name   Signature
            0      10     0  this   Lcom/fasterxml/jackson/databind/node/ObjectNode;

  protected com.fasterxml.jackson.databind.node.ObjectNode _put(java.lang.String, com.fasterxml.jackson.databind.JsonNode);
    descriptor: (Ljava/lang/String;Lcom/fasterxml/jackson/databind/JsonNode;)Lcom/fasterxml/jackson/databind/node/ObjectNode;
    flags: (0x0004) ACC_PROTECTED
    Code:
      stack=3, locals=3, args_size=3
         0: aload_0
         1: getfield      #4                  // Field _children:Ljava/util/Map;
         4: aload_1
         5: aload_2
         6: invokeinterface #19,  3           // InterfaceMethod java/util/Map.put:(Ljava/lang/Object;Ljava/lang/Object;)Ljava/lang/Object;
        11: pop
        12: aload_0
        13: areturn
      LineNumberTable:
        line 947: 0
        line 948: 12
      LocalVariableTable:
        Start  Length  Slot  Name   Signature
            0      14     0  this   Lcom/fasterxml/jackson/databind/node/ObjectNode;
            0      14     1 fieldName   Ljava/lang/String;
            0      14     2 value   Lcom/fasterxml/jackson/databind/JsonNode;

  public com.fasterxml.jackson.databind.node.ContainerNode removeAll();
    descriptor: ()Lcom/fasterxml/jackson/databind/node/ContainerNode;
    flags: (0x1041) ACC_PUBLIC, ACC_BRIDGE, ACC_SYNTHETIC
    Code:
      stack=1, locals=1, args_size=1
         0: aload_0
         1: invokevirtual #104                // Method removeAll:()Lcom/fasterxml/jackson/databind/node/ObjectNode;
         4: areturn
      LineNumberTable:
        line 19: 0
      LocalVariableTable:
        Start  Length  Slot  Name   Signature
            0       5     0  this   Lcom/fasterxml/jackson/databind/node/ObjectNode;

  public com.fasterxml.jackson.databind.JsonNode withArray(java.lang.String);
    descriptor: (Ljava/lang/String;)Lcom/fasterxml/jackson/databind/JsonNode;
    flags: (0x1041) ACC_PUBLIC, ACC_BRIDGE, ACC_SYNTHETIC
    Code:
      stack=2, locals=2, args_size=2
         0: aload_0
         1: aload_1
         2: invokevirtual #105                // Method withArray:(Ljava/lang/String;)Lcom/fasterxml/jackson/databind/node/ArrayNode;
         5: areturn
      LineNumberTable:
        line 19: 0
      LocalVariableTable:
        Start  Length  Slot  Name   Signature
            0       6     0  this   Lcom/fasterxml/jackson/databind/node/ObjectNode;

  public com.fasterxml.jackson.databind.JsonNode with(java.lang.String);
    descriptor: (Ljava/lang/String;)Lcom/fasterxml/jackson/databind/JsonNode;
    flags: (0x1041) ACC_PUBLIC, ACC_BRIDGE, ACC_SYNTHETIC
    Code:
      stack=2, locals=2, args_size=2
         0: aload_0
         1: aload_1
         2: invokevirtual #106                // Method with:(Ljava/lang/String;)Lcom/fasterxml/jackson/databind/node/ObjectNode;
         5: areturn
      LineNumberTable:
        line 19: 0
      LocalVariableTable:
        Start  Length  Slot  Name   Signature
            0       6     0  this   Lcom/fasterxml/jackson/databind/node/ObjectNode;

  public com.fasterxml.jackson.databind.JsonNode findParent(java.lang.String);
    descriptor: (Ljava/lang/String;)Lcom/fasterxml/jackson/databind/JsonNode;
    flags: (0x1041) ACC_PUBLIC, ACC_BRIDGE, ACC_SYNTHETIC
    Code:
      stack=2, locals=2, args_size=2
         0: aload_0
         1: aload_1
         2: invokevirtual #107                // Method findParent:(Ljava/lang/String;)Lcom/fasterxml/jackson/databind/node/ObjectNode;
         5: areturn
      LineNumberTable:
        line 19: 0
      LocalVariableTable:
        Start  Length  Slot  Name   Signature
            0       6     0  this   Lcom/fasterxml/jackson/databind/node/ObjectNode;

  public com.fasterxml.jackson.databind.JsonNode deepCopy();
    descriptor: ()Lcom/fasterxml/jackson/databind/JsonNode;
    flags: (0x1041) ACC_PUBLIC, ACC_BRIDGE, ACC_SYNTHETIC
    Code:
      stack=1, locals=1, args_size=1
         0: aload_0
         1: invokevirtual #108                // Method deepCopy:()Lcom/fasterxml/jackson/databind/node/ObjectNode;
         4: areturn
      LineNumberTable:
        line 19: 0
      LocalVariableTable:
        Start  Length  Slot  Name   Signature
            0       5     0  this   Lcom/fasterxml/jackson/databind/node/ObjectNode;

  public com.fasterxml.jackson.core.TreeNode path(int);
    descriptor: (I)Lcom/fasterxml/jackson/core/TreeNode;
    flags: (0x1041) ACC_PUBLIC, ACC_BRIDGE, ACC_SYNTHETIC
    Code:
      stack=2, locals=2, args_size=2
         0: aload_0
         1: iload_1
         2: invokevirtual #109                // Method path:(I)Lcom/fasterxml/jackson/databind/JsonNode;
         5: areturn
      LineNumberTable:
        line 19: 0
      LocalVariableTable:
        Start  Length  Slot  Name   Signature
            0       6     0  this   Lcom/fasterxml/jackson/databind/node/ObjectNode;

  public com.fasterxml.jackson.core.TreeNode path(java.lang.String);
    descriptor: (Ljava/lang/String;)Lcom/fasterxml/jackson/core/TreeNode;
    flags: (0x1041) ACC_PUBLIC, ACC_BRIDGE, ACC_SYNTHETIC
    Code:
      stack=2, locals=2, args_size=2
         0: aload_0
         1: aload_1
         2: invokevirtual #110                // Method path:(Ljava/lang/String;)Lcom/fasterxml/jackson/databind/JsonNode;
         5: areturn
      LineNumberTable:
        line 19: 0
      LocalVariableTable:
        Start  Length  Slot  Name   Signature
            0       6     0  this   Lcom/fasterxml/jackson/databind/node/ObjectNode;

  public com.fasterxml.jackson.core.TreeNode get(int);
    descriptor: (I)Lcom/fasterxml/jackson/core/TreeNode;
    flags: (0x1041) ACC_PUBLIC, ACC_BRIDGE, ACC_SYNTHETIC
    Code:
      stack=2, locals=2, args_size=2
         0: aload_0
         1: iload_1
         2: invokevirtual #111                // Method get:(I)Lcom/fasterxml/jackson/databind/JsonNode;
         5: areturn
      LineNumberTable:
        line 19: 0
      LocalVariableTable:
        Start  Length  Slot  Name   Signature
            0       6     0  this   Lcom/fasterxml/jackson/databind/node/ObjectNode;

  public com.fasterxml.jackson.core.TreeNode get(java.lang.String);
    descriptor: (Ljava/lang/String;)Lcom/fasterxml/jackson/core/TreeNode;
    flags: (0x1041) ACC_PUBLIC, ACC_BRIDGE, ACC_SYNTHETIC
    Code:
      stack=2, locals=2, args_size=2
         0: aload_0
         1: aload_1
         2: invokevirtual #6                  // Method get:(Ljava/lang/String;)Lcom/fasterxml/jackson/databind/JsonNode;
         5: areturn
      LineNumberTable:
        line 19: 0
      LocalVariableTable:
        Start  Length  Slot  Name   Signature
            0       6     0  this   Lcom/fasterxml/jackson/databind/node/ObjectNode;
}
Signature: #329                         // Lcom/fasterxml/jackson/databind/node/ContainerNode<Lcom/fasterxml/jackson/databind/node/ObjectNode;>;Ljava/io/Serializable;
SourceFile: "ObjectNode.java"
InnerClasses:
  public static #143= #14 of #341;        // Entry=class java/util/Map$Entry of class java/util/Map
