Classfile /Users/mw/Projects/slang-braindump/.jar/jar8/assemble/slang-braindump/assemble/content/argonaut/derive/HListProductEncodeJson$.class
  Last modified May 29, 2022; size 8314 bytes
  SHA-256 checksum 3cffad32b47ddadad8de7ab39891950fc2c2eca4101cbddd1b521e380eb3b2a1
  Compiled from "MkEncodeJson.scala"
public final class argonaut.derive.HListProductEncodeJson$
  minor version: 0
  major version: 52
  flags: (0x0031) ACC_PUBLIC, ACC_FINAL, ACC_SUPER
  this_class: #2                          // argonaut/derive/HListProductEncodeJson$
  super_class: #4                         // java/lang/Object
  interfaces: 0, fields: 2, methods: 17, attributes: 5
Constant pool:
    #1 = Utf8               argonaut/derive/HListProductEncodeJson$
    #2 = Class              #1            // argonaut/derive/HListProductEncodeJson$
    #3 = Utf8               java/lang/Object
    #4 = Class              #3            // java/lang/Object
    #5 = Utf8               MkEncodeJson.scala
    #6 = Utf8               argonaut/derive/HListProductEncodeJson$$anon$4
    #7 = Class              #6            // argonaut/derive/HListProductEncodeJson$$anon$4
    #8 = Utf8               java/lang/invoke/MethodHandles$Lookup
    #9 = Class              #8            // java/lang/invoke/MethodHandles$Lookup
   #10 = Utf8               java/lang/invoke/MethodHandles
   #11 = Class              #10           // java/lang/invoke/MethodHandles
   #12 = Utf8               Lookup
   #13 = Utf8               scala/Predef$ArrowAssoc$
   #14 = Class              #13           // scala/Predef$ArrowAssoc$
   #15 = Utf8               scala/Predef
   #16 = Class              #15           // scala/Predef
   #17 = Utf8               ArrowAssoc$
   #18 = Utf8               MODULE$
   #19 = Utf8               Largonaut/derive/HListProductEncodeJson$;
   #20 = Utf8               hnil
   #21 = Utf8               Largonaut/derive/HListProductEncodeJson;
   #22 = Utf8               Largonaut/derive/HListProductEncodeJson<Lshapeless/HNil;Lshapeless/HNil;>;
   #23 = Utf8               <clinit>
   #24 = Utf8               ()V
   #25 = Utf8               <init>
   #26 = NameAndType        #25:#24       // "<init>":()V
   #27 = Methodref          #2.#26        // argonaut/derive/HListProductEncodeJson$."<init>":()V
   #28 = NameAndType        #18:#19       // MODULE$:Largonaut/derive/HListProductEncodeJson$;
   #29 = Fieldref           #2.#28        // argonaut/derive/HListProductEncodeJson$.MODULE$:Largonaut/derive/HListProductEncodeJson$;
   #30 = Utf8               (Ljava/lang/Object;Ljava/lang/Object;)Ljava/lang/Object;
   #31 = MethodType         #30           //  (Ljava/lang/Object;Ljava/lang/Object;)Ljava/lang/Object;
   #32 = Utf8               $anonfun$hnil$1
   #33 = Utf8               (Largonaut/derive/JsonProductCodec;Lshapeless/HNil;)Largonaut/EncodeJson;
   #34 = NameAndType        #32:#33       // $anonfun$hnil$1:(Largonaut/derive/JsonProductCodec;Lshapeless/HNil;)Largonaut/EncodeJson;
   #35 = Methodref          #2.#34        // argonaut/derive/HListProductEncodeJson$.$anonfun$hnil$1:(Largonaut/derive/JsonProductCodec;Lshapeless/HNil;)Largonaut/EncodeJson;
   #36 = MethodHandle       6:#35         // REF_invokeStatic argonaut/derive/HListProductEncodeJson$.$anonfun$hnil$1:(Largonaut/derive/JsonProductCodec;Lshapeless/HNil;)Largonaut/EncodeJson;
   #37 = MethodType         #33           //  (Largonaut/derive/JsonProductCodec;Lshapeless/HNil;)Largonaut/EncodeJson;
   #38 = Integer            5
   #39 = Integer            1
   #40 = Utf8               java/lang/invoke/LambdaMetafactory
   #41 = Class              #40           // java/lang/invoke/LambdaMetafactory
   #42 = Utf8               altMetafactory
   #43 = Utf8               (Ljava/lang/invoke/MethodHandles$Lookup;Ljava/lang/String;Ljava/lang/invoke/MethodType;[Ljava/lang/Object;)Ljava/lang/invoke/CallSite;
   #44 = NameAndType        #42:#43       // altMetafactory:(Ljava/lang/invoke/MethodHandles$Lookup;Ljava/lang/String;Ljava/lang/invoke/MethodType;[Ljava/lang/Object;)Ljava/lang/invoke/CallSite;
   #45 = Methodref          #41.#44       // java/lang/invoke/LambdaMetafactory.altMetafactory:(Ljava/lang/invoke/MethodHandles$Lookup;Ljava/lang/String;Ljava/lang/invoke/MethodType;[Ljava/lang/Object;)Ljava/lang/invoke/CallSite;
   #46 = MethodHandle       6:#45         // REF_invokeStatic java/lang/invoke/LambdaMetafactory.altMetafactory:(Ljava/lang/invoke/MethodHandles$Lookup;Ljava/lang/String;Ljava/lang/invoke/MethodType;[Ljava/lang/Object;)Ljava/lang/invoke/CallSite;
   #47 = Utf8               apply
   #48 = Utf8               ()Lscala/Function2;
   #49 = NameAndType        #47:#48       // apply:()Lscala/Function2;
   #50 = InvokeDynamic      #0:#49        // #0:apply:()Lscala/Function2;
   #51 = Utf8               instance
   #52 = Utf8               (Lscala/Function2;)Largonaut/derive/HListProductEncodeJson;
   #53 = NameAndType        #51:#52       // instance:(Lscala/Function2;)Largonaut/derive/HListProductEncodeJson;
   #54 = Methodref          #2.#53        // argonaut/derive/HListProductEncodeJson$.instance:(Lscala/Function2;)Largonaut/derive/HListProductEncodeJson;
   #55 = NameAndType        #20:#21       // hnil:Largonaut/derive/HListProductEncodeJson;
   #56 = Fieldref           #2.#55        // argonaut/derive/HListProductEncodeJson$.hnil:Largonaut/derive/HListProductEncodeJson;
   #57 = Utf8               (Largonaut/derive/HListProductEncodeJson;)Largonaut/derive/HListProductEncodeJson;
   #58 = Utf8               <L::Lshapeless/HList;D::Lshapeless/HList;>(Largonaut/derive/HListProductEncodeJson<TL;TD;>;)Largonaut/derive/HListProductEncodeJson<TL;TD;>;
   #59 = Utf8               encodeJson
   #60 = Utf8               this
   #61 = Utf8               <L::Lshapeless/HList;D::Lshapeless/HList;>(Lscala/Function2<Largonaut/derive/JsonProductCodec;TD;Largonaut/EncodeJson<TL;>;>;)Largonaut/derive/HListProductEncodeJson<TL;TD;>;
   #62 = Utf8               f
   #63 = Utf8               (Lscala/Function2;)V
   #64 = NameAndType        #25:#63       // "<init>":(Lscala/Function2;)V
   #65 = Methodref          #7.#64        // argonaut/derive/HListProductEncodeJson$$anon$4."<init>":(Lscala/Function2;)V
   #66 = Utf8               Lscala/Function2;
   #67 = Utf8               ()Largonaut/derive/HListProductEncodeJson;
   #68 = Utf8               ()Largonaut/derive/HListProductEncodeJson<Lshapeless/HNil;Lshapeless/HNil;>;
   #69 = Utf8               hcons
   #70 = Utf8               (Lshapeless/Witness;Lshapeless/Strict;Largonaut/derive/HListProductEncodeJson;)Largonaut/derive/HListProductEncodeJson;
   #71 = Utf8               <K:Lscala/Symbol;H:Ljava/lang/Object;T::Lshapeless/HList;TD::Lshapeless/HList;>(Lshapeless/Witness;Lshapeless/Strict<Largonaut/EncodeJson<TH;>;>;Largonaut/derive/HListProductEncodeJson<TT;TTD;>;)Largonaut/derive/HListProductEncodeJson<Lshapeless/$colon$colon<TH;TT;>;Lshapeless/$colon$colon<Lscala/Option<TH;>;TTD;>;>;
   #72 = Utf8               key
   #73 = Utf8               headEncode
   #74 = Utf8               tailEncode
   #75 = Utf8               $anonfun$hcons$1
   #76 = Utf8               (Lshapeless/Strict;Largonaut/derive/HListProductEncodeJson;Lshapeless/Witness;Largonaut/derive/JsonProductCodec;Lshapeless/$colon$colon;)Largonaut/EncodeJson;
   #77 = NameAndType        #75:#76       // $anonfun$hcons$1:(Lshapeless/Strict;Largonaut/derive/HListProductEncodeJson;Lshapeless/Witness;Largonaut/derive/JsonProductCodec;Lshapeless/$colon$colon;)Largonaut/EncodeJson;
   #78 = Methodref          #2.#77        // argonaut/derive/HListProductEncodeJson$.$anonfun$hcons$1:(Lshapeless/Strict;Largonaut/derive/HListProductEncodeJson;Lshapeless/Witness;Largonaut/derive/JsonProductCodec;Lshapeless/$colon$colon;)Largonaut/EncodeJson;
   #79 = MethodHandle       6:#78         // REF_invokeStatic argonaut/derive/HListProductEncodeJson$.$anonfun$hcons$1:(Lshapeless/Strict;Largonaut/derive/HListProductEncodeJson;Lshapeless/Witness;Largonaut/derive/JsonProductCodec;Lshapeless/$colon$colon;)Largonaut/EncodeJson;
   #80 = Utf8               (Largonaut/derive/JsonProductCodec;Lshapeless/$colon$colon;)Largonaut/EncodeJson;
   #81 = MethodType         #80           //  (Largonaut/derive/JsonProductCodec;Lshapeless/$colon$colon;)Largonaut/EncodeJson;
   #82 = Utf8               (Lshapeless/Strict;Largonaut/derive/HListProductEncodeJson;Lshapeless/Witness;)Lscala/Function2;
   #83 = NameAndType        #47:#82       // apply:(Lshapeless/Strict;Largonaut/derive/HListProductEncodeJson;Lshapeless/Witness;)Lscala/Function2;
   #84 = InvokeDynamic      #1:#83        // #1:apply:(Lshapeless/Strict;Largonaut/derive/HListProductEncodeJson;Lshapeless/Witness;)Lscala/Function2;
   #85 = Utf8               Lshapeless/Witness;
   #86 = Utf8               Lshapeless/Strict;
   #87 = Utf8               $anonfun$hnil$2
   #88 = Utf8               (Largonaut/derive/JsonProductCodec;Lshapeless/HNil;)Largonaut/Json;
   #89 = Utf8               productCodec$1
   #90 = Utf8               x$2
   #91 = Utf8               argonaut/derive/JsonProductCodec
   #92 = Class              #91           // argonaut/derive/JsonProductCodec
   #93 = Utf8               encodeEmpty
   #94 = Utf8               ()Largonaut/Json;
   #95 = NameAndType        #93:#94       // encodeEmpty:()Largonaut/Json;
   #96 = InterfaceMethodref #92.#95       // argonaut/derive/JsonProductCodec.encodeEmpty:()Largonaut/Json;
   #97 = Utf8               Largonaut/derive/JsonProductCodec;
   #98 = Utf8               Lshapeless/HNil;
   #99 = Utf8               productCodec
  #100 = Utf8               x$1
  #101 = Utf8               argonaut/EncodeJson$
  #102 = Class              #101          // argonaut/EncodeJson$
  #103 = Utf8               Largonaut/EncodeJson$;
  #104 = NameAndType        #18:#103      // MODULE$:Largonaut/EncodeJson$;
  #105 = Fieldref           #102.#104     // argonaut/EncodeJson$.MODULE$:Largonaut/EncodeJson$;
  #106 = Utf8               (Ljava/lang/Object;)Ljava/lang/Object;
  #107 = MethodType         #106          //  (Ljava/lang/Object;)Ljava/lang/Object;
  #108 = NameAndType        #87:#88       // $anonfun$hnil$2:(Largonaut/derive/JsonProductCodec;Lshapeless/HNil;)Largonaut/Json;
  #109 = Methodref          #2.#108       // argonaut/derive/HListProductEncodeJson$.$anonfun$hnil$2:(Largonaut/derive/JsonProductCodec;Lshapeless/HNil;)Largonaut/Json;
  #110 = MethodHandle       6:#109        // REF_invokeStatic argonaut/derive/HListProductEncodeJson$.$anonfun$hnil$2:(Largonaut/derive/JsonProductCodec;Lshapeless/HNil;)Largonaut/Json;
  #111 = Utf8               (Lshapeless/HNil;)Largonaut/Json;
  #112 = MethodType         #111          //  (Lshapeless/HNil;)Largonaut/Json;
  #113 = Utf8               (Largonaut/derive/JsonProductCodec;)Lscala/Function1;
  #114 = NameAndType        #47:#113      // apply:(Largonaut/derive/JsonProductCodec;)Lscala/Function1;
  #115 = InvokeDynamic      #2:#114       // #2:apply:(Largonaut/derive/JsonProductCodec;)Lscala/Function1;
  #116 = Utf8               (Lscala/Function1;)Largonaut/EncodeJson;
  #117 = NameAndType        #47:#116      // apply:(Lscala/Function1;)Largonaut/EncodeJson;
  #118 = Methodref          #102.#117     // argonaut/EncodeJson$.apply:(Lscala/Function1;)Largonaut/EncodeJson;
  #119 = Utf8               $anonfun$hcons$2
  #120 = Utf8               (Lshapeless/Strict;Ljava/lang/Object;)Largonaut/Json;
  #121 = Utf8               headEncode$1
  #122 = Utf8               a
  #123 = Utf8               shapeless/Strict
  #124 = Class              #123          // shapeless/Strict
  #125 = Utf8               value
  #126 = Utf8               ()Ljava/lang/Object;
  #127 = NameAndType        #125:#126     // value:()Ljava/lang/Object;
  #128 = InterfaceMethodref #124.#127     // shapeless/Strict.value:()Ljava/lang/Object;
  #129 = Utf8               argonaut/EncodeJson
  #130 = Class              #129          // argonaut/EncodeJson
  #131 = Utf8               encode
  #132 = Utf8               (Ljava/lang/Object;)Largonaut/Json;
  #133 = NameAndType        #131:#132     // encode:(Ljava/lang/Object;)Largonaut/Json;
  #134 = InterfaceMethodref #130.#133     // argonaut/EncodeJson.encode:(Ljava/lang/Object;)Largonaut/Json;
  #135 = Utf8               Ljava/lang/Object;
  #136 = Utf8               defaultOpt$lzycompute$1
  #137 = Utf8               (Lscala/runtime/LazyRef;Lshapeless/$colon$colon;Lshapeless/Strict;)Lscala/Option;
  #138 = Utf8               defaultOpt$lzy$1
  #139 = Utf8               defaults$2
  #140 = Utf8               scala/runtime/LazyRef
  #141 = Class              #140          // scala/runtime/LazyRef
  #142 = Utf8               initialized
  #143 = Utf8               ()Z
  #144 = NameAndType        #142:#143     // initialized:()Z
  #145 = Methodref          #141.#144     // scala/runtime/LazyRef.initialized:()Z
  #146 = Methodref          #141.#127     // scala/runtime/LazyRef.value:()Ljava/lang/Object;
  #147 = Utf8               scala/Option
  #148 = Class              #147          // scala/Option
  #149 = Utf8               shapeless/$colon$colon
  #150 = Class              #149          // shapeless/$colon$colon
  #151 = Utf8               head
  #152 = NameAndType        #151:#126     // head:()Ljava/lang/Object;
  #153 = Methodref          #150.#152     // shapeless/$colon$colon.head:()Ljava/lang/Object;
  #154 = NameAndType        #119:#120     // $anonfun$hcons$2:(Lshapeless/Strict;Ljava/lang/Object;)Largonaut/Json;
  #155 = Methodref          #2.#154       // argonaut/derive/HListProductEncodeJson$.$anonfun$hcons$2:(Lshapeless/Strict;Ljava/lang/Object;)Largonaut/Json;
  #156 = MethodHandle       6:#155        // REF_invokeStatic argonaut/derive/HListProductEncodeJson$.$anonfun$hcons$2:(Lshapeless/Strict;Ljava/lang/Object;)Largonaut/Json;
  #157 = MethodType         #132          //  (Ljava/lang/Object;)Largonaut/Json;
  #158 = Utf8               (Lshapeless/Strict;)Lscala/Function1;
  #159 = NameAndType        #47:#158      // apply:(Lshapeless/Strict;)Lscala/Function1;
  #160 = InvokeDynamic      #3:#159       // #3:apply:(Lshapeless/Strict;)Lscala/Function1;
  #161 = Utf8               map
  #162 = Utf8               (Lscala/Function1;)Lscala/Option;
  #163 = NameAndType        #161:#162     // map:(Lscala/Function1;)Lscala/Option;
  #164 = Methodref          #148.#163     // scala/Option.map:(Lscala/Function1;)Lscala/Option;
  #165 = Utf8               initialize
  #166 = NameAndType        #165:#106     // initialize:(Ljava/lang/Object;)Ljava/lang/Object;
  #167 = Methodref          #141.#166     // scala/runtime/LazyRef.initialize:(Ljava/lang/Object;)Ljava/lang/Object;
  #168 = Utf8               Lscala/runtime/LazyRef;
  #169 = Utf8               Lshapeless/$colon$colon;
  #170 = Utf8               java/lang/Throwable
  #171 = Class              #170          // java/lang/Throwable
  #172 = Utf8               defaultOpt$1
  #173 = NameAndType        #136:#137     // defaultOpt$lzycompute$1:(Lscala/runtime/LazyRef;Lshapeless/$colon$colon;Lshapeless/Strict;)Lscala/Option;
  #174 = Methodref          #2.#173       // argonaut/derive/HListProductEncodeJson$.defaultOpt$lzycompute$1:(Lscala/runtime/LazyRef;Lshapeless/$colon$colon;Lshapeless/Strict;)Lscala/Option;
  #175 = Utf8               tailEncode0$lzycompute$1
  #176 = Utf8               (Lscala/runtime/LazyRef;Largonaut/derive/HListProductEncodeJson;Largonaut/derive/JsonProductCodec;Lshapeless/$colon$colon;)Largonaut/EncodeJson;
  #177 = Utf8               tailEncode0$lzy$1
  #178 = Utf8               tailEncode$1
  #179 = Utf8               productCodec$2
  #180 = Utf8               tail
  #181 = Utf8               ()Lshapeless/HList;
  #182 = NameAndType        #180:#181     // tail:()Lshapeless/HList;
  #183 = Methodref          #150.#182     // shapeless/$colon$colon.tail:()Lshapeless/HList;
  #184 = Utf8               argonaut/derive/HListProductEncodeJson
  #185 = Class              #184          // argonaut/derive/HListProductEncodeJson
  #186 = Utf8               (Largonaut/derive/JsonProductCodec;Lshapeless/HList;)Largonaut/EncodeJson;
  #187 = NameAndType        #47:#186      // apply:(Largonaut/derive/JsonProductCodec;Lshapeless/HList;)Largonaut/EncodeJson;
  #188 = InterfaceMethodref #185.#187     // argonaut/derive/HListProductEncodeJson.apply:(Largonaut/derive/JsonProductCodec;Lshapeless/HList;)Largonaut/EncodeJson;
  #189 = Utf8               tailEncode0$1
  #190 = NameAndType        #175:#176     // tailEncode0$lzycompute$1:(Lscala/runtime/LazyRef;Largonaut/derive/HListProductEncodeJson;Largonaut/derive/JsonProductCodec;Lshapeless/$colon$colon;)Largonaut/EncodeJson;
  #191 = Methodref          #2.#190       // argonaut/derive/HListProductEncodeJson$.tailEncode0$lzycompute$1:(Lscala/runtime/LazyRef;Largonaut/derive/HListProductEncodeJson;Largonaut/derive/JsonProductCodec;Lshapeless/$colon$colon;)Largonaut/EncodeJson;
  #192 = Utf8               $anonfun$hcons$4
  #193 = NameAndType        #172:#137     // defaultOpt$1:(Lscala/runtime/LazyRef;Lshapeless/$colon$colon;Lshapeless/Strict;)Lscala/Option;
  #194 = Methodref          #2.#193       // argonaut/derive/HListProductEncodeJson$.defaultOpt$1:(Lscala/runtime/LazyRef;Lshapeless/$colon$colon;Lshapeless/Strict;)Lscala/Option;
  #195 = Utf8               $anonfun$hcons$3
  #196 = Utf8               (Largonaut/derive/JsonProductCodec;Lshapeless/Witness;Lshapeless/Strict;Lscala/runtime/LazyRef;Largonaut/derive/HListProductEncodeJson;Lshapeless/$colon$colon;Lscala/runtime/LazyRef;Lshapeless/$colon$colon;)Largonaut/Json;
  #197 = Utf8               key$1
  #198 = Utf8               l
  #199 = Utf8               Lscala/Predef$ArrowAssoc$;
  #200 = NameAndType        #18:#199      // MODULE$:Lscala/Predef$ArrowAssoc$;
  #201 = Fieldref           #14.#200      // scala/Predef$ArrowAssoc$.MODULE$:Lscala/Predef$ArrowAssoc$;
  #202 = Utf8               scala/Predef$
  #203 = Class              #202          // scala/Predef$
  #204 = Utf8               Lscala/Predef$;
  #205 = NameAndType        #18:#204      // MODULE$:Lscala/Predef$;
  #206 = Fieldref           #203.#205     // scala/Predef$.MODULE$:Lscala/Predef$;
  #207 = Utf8               shapeless/Witness
  #208 = Class              #207          // shapeless/Witness
  #209 = InterfaceMethodref #208.#127     // shapeless/Witness.value:()Ljava/lang/Object;
  #210 = Utf8               scala/Symbol
  #211 = Class              #210          // scala/Symbol
  #212 = Utf8               name
  #213 = Utf8               ()Ljava/lang/String;
  #214 = NameAndType        #212:#213     // name:()Ljava/lang/String;
  #215 = Methodref          #211.#214     // scala/Symbol.name:()Ljava/lang/String;
  #216 = Utf8               ArrowAssoc
  #217 = NameAndType        #216:#106     // ArrowAssoc:(Ljava/lang/Object;)Ljava/lang/Object;
  #218 = Methodref          #203.#217     // scala/Predef$.ArrowAssoc:(Ljava/lang/Object;)Ljava/lang/Object;
  #219 = Utf8               $minus$greater$extension
  #220 = Utf8               (Ljava/lang/Object;Ljava/lang/Object;)Lscala/Tuple2;
  #221 = NameAndType        #219:#220     // $minus$greater$extension:(Ljava/lang/Object;Ljava/lang/Object;)Lscala/Tuple2;
  #222 = Methodref          #14.#221      // scala/Predef$ArrowAssoc$.$minus$greater$extension:(Ljava/lang/Object;Ljava/lang/Object;)Lscala/Tuple2;
  #223 = NameAndType        #189:#176     // tailEncode0$1:(Lscala/runtime/LazyRef;Largonaut/derive/HListProductEncodeJson;Largonaut/derive/JsonProductCodec;Lshapeless/$colon$colon;)Largonaut/EncodeJson;
  #224 = Methodref          #2.#223       // argonaut/derive/HListProductEncodeJson$.tailEncode0$1:(Lscala/runtime/LazyRef;Largonaut/derive/HListProductEncodeJson;Largonaut/derive/JsonProductCodec;Lshapeless/$colon$colon;)Largonaut/EncodeJson;
  #225 = MethodType         #126          //  ()Ljava/lang/Object;
  #226 = NameAndType        #192:#137     // $anonfun$hcons$4:(Lscala/runtime/LazyRef;Lshapeless/$colon$colon;Lshapeless/Strict;)Lscala/Option;
  #227 = Methodref          #2.#226       // argonaut/derive/HListProductEncodeJson$.$anonfun$hcons$4:(Lscala/runtime/LazyRef;Lshapeless/$colon$colon;Lshapeless/Strict;)Lscala/Option;
  #228 = MethodHandle       6:#227        // REF_invokeStatic argonaut/derive/HListProductEncodeJson$.$anonfun$hcons$4:(Lscala/runtime/LazyRef;Lshapeless/$colon$colon;Lshapeless/Strict;)Lscala/Option;
  #229 = Utf8               ()Lscala/Option;
  #230 = MethodType         #229          //  ()Lscala/Option;
  #231 = Utf8               (Lscala/runtime/LazyRef;Lshapeless/$colon$colon;Lshapeless/Strict;)Lscala/Function0;
  #232 = NameAndType        #47:#231      // apply:(Lscala/runtime/LazyRef;Lshapeless/$colon$colon;Lshapeless/Strict;)Lscala/Function0;
  #233 = InvokeDynamic      #4:#232       // #4:apply:(Lscala/runtime/LazyRef;Lshapeless/$colon$colon;Lshapeless/Strict;)Lscala/Function0;
  #234 = Utf8               encodeField
  #235 = Utf8               (Lscala/Tuple2;Largonaut/Json;Lscala/Function0;)Largonaut/Json;
  #236 = NameAndType        #234:#235     // encodeField:(Lscala/Tuple2;Largonaut/Json;Lscala/Function0;)Largonaut/Json;
  #237 = InterfaceMethodref #92.#236      // argonaut/derive/JsonProductCodec.encodeField:(Lscala/Tuple2;Largonaut/Json;Lscala/Function0;)Largonaut/Json;
  #238 = Utf8               defaults
  #239 = Methodref          #141.#26      // scala/runtime/LazyRef."<init>":()V
  #240 = NameAndType        #195:#196     // $anonfun$hcons$3:(Largonaut/derive/JsonProductCodec;Lshapeless/Witness;Lshapeless/Strict;Lscala/runtime/LazyRef;Largonaut/derive/HListProductEncodeJson;Lshapeless/$colon$colon;Lscala/runtime/LazyRef;Lshapeless/$colon$colon;)Largonaut/Json;
  #241 = Methodref          #2.#240       // argonaut/derive/HListProductEncodeJson$.$anonfun$hcons$3:(Largonaut/derive/JsonProductCodec;Lshapeless/Witness;Lshapeless/Strict;Lscala/runtime/LazyRef;Largonaut/derive/HListProductEncodeJson;Lshapeless/$colon$colon;Lscala/runtime/LazyRef;Lshapeless/$colon$colon;)Largonaut/Json;
  #242 = MethodHandle       6:#241        // REF_invokeStatic argonaut/derive/HListProductEncodeJson$.$anonfun$hcons$3:(Largonaut/derive/JsonProductCodec;Lshapeless/Witness;Lshapeless/Strict;Lscala/runtime/LazyRef;Largonaut/derive/HListProductEncodeJson;Lshapeless/$colon$colon;Lscala/runtime/LazyRef;Lshapeless/$colon$colon;)Largonaut/Json;
  #243 = Utf8               (Lshapeless/$colon$colon;)Largonaut/Json;
  #244 = MethodType         #243          //  (Lshapeless/$colon$colon;)Largonaut/Json;
  #245 = Utf8               (Largonaut/derive/JsonProductCodec;Lshapeless/Witness;Lshapeless/Strict;Lscala/runtime/LazyRef;Largonaut/derive/HListProductEncodeJson;Lshapeless/$colon$colon;Lscala/runtime/LazyRef;)Lscala/Function1;
  #246 = NameAndType        #47:#245      // apply:(Largonaut/derive/JsonProductCodec;Lshapeless/Witness;Lshapeless/Strict;Lscala/runtime/LazyRef;Largonaut/derive/HListProductEncodeJson;Lshapeless/$colon$colon;Lscala/runtime/LazyRef;)Lscala/Function1;
  #247 = InvokeDynamic      #5:#246       // #5:apply:(Largonaut/derive/JsonProductCodec;Lshapeless/Witness;Lshapeless/Strict;Lscala/runtime/LazyRef;Largonaut/derive/HListProductEncodeJson;Lshapeless/$colon$colon;Lscala/runtime/LazyRef;)Lscala/Function1;
  #248 = Utf8               defaultOpt$lzy
  #249 = Utf8               tailEncode0$lzy
  #250 = Methodref          #4.#26        // java/lang/Object."<init>":()V
  #251 = Utf8               $deserializeLambda$
  #252 = Utf8               (Ljava/lang/invoke/SerializedLambda;)Ljava/lang/Object;
  #253 = Utf8               scala/runtime/LambdaDeserialize
  #254 = Class              #253          // scala/runtime/LambdaDeserialize
  #255 = Utf8               bootstrap
  #256 = Utf8               (Ljava/lang/invoke/MethodHandles$Lookup;Ljava/lang/String;Ljava/lang/invoke/MethodType;[Ljava/lang/invoke/MethodHandle;)Ljava/lang/invoke/CallSite;
  #257 = NameAndType        #255:#256     // bootstrap:(Ljava/lang/invoke/MethodHandles$Lookup;Ljava/lang/String;Ljava/lang/invoke/MethodType;[Ljava/lang/invoke/MethodHandle;)Ljava/lang/invoke/CallSite;
  #258 = Methodref          #254.#257     // scala/runtime/LambdaDeserialize.bootstrap:(Ljava/lang/invoke/MethodHandles$Lookup;Ljava/lang/String;Ljava/lang/invoke/MethodType;[Ljava/lang/invoke/MethodHandle;)Ljava/lang/invoke/CallSite;
  #259 = MethodHandle       6:#258        // REF_invokeStatic scala/runtime/LambdaDeserialize.bootstrap:(Ljava/lang/invoke/MethodHandles$Lookup;Ljava/lang/String;Ljava/lang/invoke/MethodType;[Ljava/lang/invoke/MethodHandle;)Ljava/lang/invoke/CallSite;
  #260 = Utf8               lambdaDeserialize
  #261 = NameAndType        #260:#252     // lambdaDeserialize:(Ljava/lang/invoke/SerializedLambda;)Ljava/lang/Object;
  #262 = InvokeDynamic      #6:#261       // #6:lambdaDeserialize:(Ljava/lang/invoke/SerializedLambda;)Ljava/lang/Object;
  #263 = Utf8               Signature
  #264 = Utf8               Code
  #265 = Utf8               LineNumberTable
  #266 = Utf8               LocalVariableTable
  #267 = Utf8               MethodParameters
  #268 = Utf8               StackMapTable
  #269 = Utf8               InnerClasses
  #270 = Utf8               SourceFile
  #271 = Utf8               BootstrapMethods
  #272 = Utf8               ScalaInlineInfo
  #273 = Utf8               Scala
{
  public static final argonaut.derive.HListProductEncodeJson$ MODULE$;
    descriptor: Largonaut/derive/HListProductEncodeJson$;
    flags: (0x0019) ACC_PUBLIC, ACC_STATIC, ACC_FINAL

  private static final argonaut.derive.HListProductEncodeJson<shapeless.HNil, shapeless.HNil> hnil;
    descriptor: Largonaut/derive/HListProductEncodeJson;
    flags: (0x001a) ACC_PRIVATE, ACC_STATIC, ACC_FINAL
    Signature: #22                          // Largonaut/derive/HListProductEncodeJson<Lshapeless/HNil;Lshapeless/HNil;>;

  public static {};
    descriptor: ()V
    flags: (0x0009) ACC_PUBLIC, ACC_STATIC
    Code:
      stack=2, locals=0, args_size=0
         0: new           #2                  // class argonaut/derive/HListProductEncodeJson$
         3: dup
         4: invokespecial #27                 // Method "<init>":()V
         7: putstatic     #29                 // Field MODULE$:Largonaut/derive/HListProductEncodeJson$;
        10: getstatic     #29                 // Field MODULE$:Largonaut/derive/HListProductEncodeJson$;
        13: invokedynamic #50,  0             // InvokeDynamic #0:apply:()Lscala/Function2;
        18: invokevirtual #54                 // Method instance:(Lscala/Function2;)Largonaut/derive/HListProductEncodeJson;
        21: putstatic     #56                 // Field hnil:Largonaut/derive/HListProductEncodeJson;
        24: return
      LineNumberTable:
        line 71: 0
        line 82: 10
        line 81: 21
        line 71: 24

  public <L extends shapeless.HList, D extends shapeless.HList> argonaut.derive.HListProductEncodeJson<L, D> apply(argonaut.derive.HListProductEncodeJson<L, D>);
    descriptor: (Largonaut/derive/HListProductEncodeJson;)Largonaut/derive/HListProductEncodeJson;
    flags: (0x0001) ACC_PUBLIC
    Code:
      stack=1, locals=2, args_size=2
         0: aload_1
         1: areturn
      LineNumberTable:
        line 73: 0
      LocalVariableTable:
        Start  Length  Slot  Name   Signature
            0       2     0  this   Largonaut/derive/HListProductEncodeJson$;
            0       2     1 encodeJson   Largonaut/derive/HListProductEncodeJson;
    Signature: #58                          // <L::Lshapeless/HList;D::Lshapeless/HList;>(Largonaut/derive/HListProductEncodeJson<TL;TD;>;)Largonaut/derive/HListProductEncodeJson<TL;TD;>;
    MethodParameters:
      Name                           Flags
      encodeJson                     final

  public <L extends shapeless.HList, D extends shapeless.HList> argonaut.derive.HListProductEncodeJson<L, D> instance(scala.Function2<argonaut.derive.JsonProductCodec, D, argonaut.EncodeJson<L>>);
    descriptor: (Lscala/Function2;)Largonaut/derive/HListProductEncodeJson;
    flags: (0x0001) ACC_PUBLIC
    Code:
      stack=3, locals=2, args_size=2
         0: new           #7                  // class argonaut/derive/HListProductEncodeJson$$anon$4
         3: dup
         4: aload_1
         5: invokespecial #65                 // Method argonaut/derive/HListProductEncodeJson$$anon$4."<init>":(Lscala/Function2;)V
         8: areturn
      LineNumberTable:
        line 76: 0
      LocalVariableTable:
        Start  Length  Slot  Name   Signature
            0       9     0  this   Largonaut/derive/HListProductEncodeJson$;
            0       9     1     f   Lscala/Function2;
    Signature: #61                          // <L::Lshapeless/HList;D::Lshapeless/HList;>(Lscala/Function2<Largonaut/derive/JsonProductCodec;TD;Largonaut/EncodeJson<TL;>;>;)Largonaut/derive/HListProductEncodeJson<TL;TD;>;
    MethodParameters:
      Name                           Flags
      f                              final

  public argonaut.derive.HListProductEncodeJson<shapeless.HNil, shapeless.HNil> hnil();
    descriptor: ()Largonaut/derive/HListProductEncodeJson;
    flags: (0x0001) ACC_PUBLIC
    Code:
      stack=1, locals=1, args_size=1
         0: getstatic     #56                 // Field hnil:Largonaut/derive/HListProductEncodeJson;
         3: areturn
      LineNumberTable:
        line 81: 0
      LocalVariableTable:
        Start  Length  Slot  Name   Signature
            0       4     0  this   Largonaut/derive/HListProductEncodeJson$;
    Signature: #68                          // ()Largonaut/derive/HListProductEncodeJson<Lshapeless/HNil;Lshapeless/HNil;>;

  public <K extends scala.Symbol, H extends java.lang.Object, T extends shapeless.HList, TD extends shapeless.HList> argonaut.derive.HListProductEncodeJson<shapeless.$colon$colon<H, T>, shapeless.$colon$colon<scala.Option<H>, TD>> hcons(shapeless.Witness, shapeless.Strict<argonaut.EncodeJson<H>>, argonaut.derive.HListProductEncodeJson<T, TD>);
    descriptor: (Lshapeless/Witness;Lshapeless/Strict;Largonaut/derive/HListProductEncodeJson;)Largonaut/derive/HListProductEncodeJson;
    flags: (0x0001) ACC_PUBLIC
    Code:
      stack=4, locals=4, args_size=4
         0: aload_0
         1: aload_2
         2: aload_3
         3: aload_1
         4: invokedynamic #84,  0             // InvokeDynamic #1:apply:(Lshapeless/Strict;Largonaut/derive/HListProductEncodeJson;Lshapeless/Witness;)Lscala/Function2;
         9: invokevirtual #54                 // Method instance:(Lscala/Function2;)Largonaut/derive/HListProductEncodeJson;
        12: areturn
      LineNumberTable:
        line 94: 0
      LocalVariableTable:
        Start  Length  Slot  Name   Signature
            0      13     0  this   Largonaut/derive/HListProductEncodeJson$;
            0      13     1   key   Lshapeless/Witness;
            0      13     2 headEncode   Lshapeless/Strict;
            0      13     3 tailEncode   Largonaut/derive/HListProductEncodeJson;
    Signature: #71                          // <K:Lscala/Symbol;H:Ljava/lang/Object;T::Lshapeless/HList;TD::Lshapeless/HList;>(Lshapeless/Witness;Lshapeless/Strict<Largonaut/EncodeJson<TH;>;>;Largonaut/derive/HListProductEncodeJson<TT;TTD;>;)Largonaut/derive/HListProductEncodeJson<Lshapeless/$colon$colon<TH;TT;>;Lshapeless/$colon$colon<Lscala/Option<TH;>;TTD;>;>;
    MethodParameters:
      Name                           Flags
      key                            final
      headEncode                     final
      tailEncode                     final

  public static final argonaut.Json $anonfun$hnil$2(argonaut.derive.JsonProductCodec, shapeless.HNil);
    descriptor: (Largonaut/derive/JsonProductCodec;Lshapeless/HNil;)Largonaut/Json;
    flags: (0x1019) ACC_PUBLIC, ACC_STATIC, ACC_FINAL, ACC_SYNTHETIC
    Code:
      stack=1, locals=2, args_size=2
         0: aload_0
         1: invokeinterface #96,  1           // InterfaceMethod argonaut/derive/JsonProductCodec.encodeEmpty:()Largonaut/Json;
         6: areturn
      LineNumberTable:
        line 84: 0
      LocalVariableTable:
        Start  Length  Slot  Name   Signature
            0       7     0 productCodec$1   Largonaut/derive/JsonProductCodec;
            0       7     1   x$2   Lshapeless/HNil;
    MethodParameters:
      Name                           Flags
      productCodec$1                 final
      x$2                            final

  public static final argonaut.EncodeJson $anonfun$hnil$1(argonaut.derive.JsonProductCodec, shapeless.HNil);
    descriptor: (Largonaut/derive/JsonProductCodec;Lshapeless/HNil;)Largonaut/EncodeJson;
    flags: (0x1019) ACC_PUBLIC, ACC_STATIC, ACC_FINAL, ACC_SYNTHETIC
    Code:
      stack=2, locals=2, args_size=2
         0: getstatic     #105                // Field argonaut/EncodeJson$.MODULE$:Largonaut/EncodeJson$;
         3: aload_0
         4: invokedynamic #115,  0            // InvokeDynamic #2:apply:(Largonaut/derive/JsonProductCodec;)Lscala/Function1;
         9: invokevirtual #118                // Method argonaut/EncodeJson$.apply:(Lscala/Function1;)Largonaut/EncodeJson;
        12: areturn
      LineNumberTable:
        line 83: 0
      LocalVariableTable:
        Start  Length  Slot  Name   Signature
            0      13     0 productCodec   Largonaut/derive/JsonProductCodec;
            0      13     1   x$1   Lshapeless/HNil;
    MethodParameters:
      Name                           Flags
      productCodec                   final
      x$1                            final

  public static final argonaut.Json $anonfun$hcons$2(shapeless.Strict, java.lang.Object);
    descriptor: (Lshapeless/Strict;Ljava/lang/Object;)Largonaut/Json;
    flags: (0x1019) ACC_PUBLIC, ACC_STATIC, ACC_FINAL, ACC_SYNTHETIC
    Code:
      stack=2, locals=2, args_size=2
         0: aload_0
         1: invokeinterface #128,  1          // InterfaceMethod shapeless/Strict.value:()Ljava/lang/Object;
         6: checkcast     #130                // class argonaut/EncodeJson
         9: aload_1
        10: invokeinterface #134,  2          // InterfaceMethod argonaut/EncodeJson.encode:(Ljava/lang/Object;)Largonaut/Json;
        15: areturn
      LineNumberTable:
        line 95: 0
      LocalVariableTable:
        Start  Length  Slot  Name   Signature
            0      16     0 headEncode$1   Lshapeless/Strict;
            0      16     1     a   Ljava/lang/Object;
    MethodParameters:
      Name                           Flags
      headEncode$1                   final
      a                              final

  private static final scala.Option defaultOpt$lzycompute$1(scala.runtime.LazyRef, shapeless.$colon$colon, shapeless.Strict);
    descriptor: (Lscala/runtime/LazyRef;Lshapeless/$colon$colon;Lshapeless/Strict;)Lscala/Option;
    flags: (0x101a) ACC_PRIVATE, ACC_STATIC, ACC_FINAL, ACC_SYNTHETIC
    Code:
      stack=3, locals=5, args_size=3
         0: aload_0
         1: dup
         2: astore_3
         3: monitorenter
         4: aload_0
         5: invokevirtual #145                // Method scala/runtime/LazyRef.initialized:()Z
         8: ifeq          21
        11: aload_0
        12: invokevirtual #146                // Method scala/runtime/LazyRef.value:()Ljava/lang/Object;
        15: checkcast     #148                // class scala/Option
        18: goto          44
        21: aload_0
        22: aload_1
        23: invokevirtual #153                // Method shapeless/$colon$colon.head:()Ljava/lang/Object;
        26: checkcast     #148                // class scala/Option
        29: aload_2
        30: invokedynamic #160,  0            // InvokeDynamic #3:apply:(Lshapeless/Strict;)Lscala/Function1;
        35: invokevirtual #164                // Method scala/Option.map:(Lscala/Function1;)Lscala/Option;
        38: invokevirtual #167                // Method scala/runtime/LazyRef.initialize:(Ljava/lang/Object;)Ljava/lang/Object;
        41: checkcast     #148                // class scala/Option
        44: astore        4
        46: aload_3
        47: monitorexit
        48: aload         4
        50: goto          56
        53: aload_3
        54: monitorexit
        55: athrow
        56: areturn
      Exception table:
         from    to  target type
             4    46    53   any
      StackMapTable: number_of_entries = 4
        frame_type = 252 /* append */
          offset_delta = 21
          locals = [ class scala/runtime/LazyRef ]
        frame_type = 86 /* same_locals_1_stack_item */
          stack = [ class scala/Option ]
        frame_type = 72 /* same_locals_1_stack_item */
          stack = [ class java/lang/Throwable ]
        frame_type = 255 /* full_frame */
          offset_delta = 2
          locals = [ class scala/runtime/LazyRef, class shapeless/$colon$colon, class shapeless/Strict, class scala/runtime/LazyRef, class scala/Option ]
          stack = [ class scala/Option ]
      LineNumberTable:
        line 95: 0
      LocalVariableTable:
        Start  Length  Slot  Name   Signature
            0      57     0 defaultOpt$lzy$1   Lscala/runtime/LazyRef;
            0      57     1 defaults$2   Lshapeless/$colon$colon;
            0      57     2 headEncode$1   Lshapeless/Strict;
    MethodParameters:
      Name                           Flags
      defaultOpt$lzy$1               final
      defaults$2                     final
      headEncode$1                   final

  private static final scala.Option defaultOpt$1(scala.runtime.LazyRef, shapeless.$colon$colon, shapeless.Strict);
    descriptor: (Lscala/runtime/LazyRef;Lshapeless/$colon$colon;Lshapeless/Strict;)Lscala/Option;
    flags: (0x001a) ACC_PRIVATE, ACC_STATIC, ACC_FINAL
    Code:
      stack=3, locals=3, args_size=3
         0: aload_0
         1: invokevirtual #145                // Method scala/runtime/LazyRef.initialized:()Z
         4: ifeq          17
         7: aload_0
         8: invokevirtual #146                // Method scala/runtime/LazyRef.value:()Ljava/lang/Object;
        11: checkcast     #148                // class scala/Option
        14: goto          23
        17: aload_0
        18: aload_1
        19: aload_2
        20: invokestatic  #174                // Method defaultOpt$lzycompute$1:(Lscala/runtime/LazyRef;Lshapeless/$colon$colon;Lshapeless/Strict;)Lscala/Option;
        23: areturn
      StackMapTable: number_of_entries = 2
        frame_type = 17 /* same */
        frame_type = 69 /* same_locals_1_stack_item */
          stack = [ class scala/Option ]
      LineNumberTable:
        line 95: 0
      LocalVariableTable:
        Start  Length  Slot  Name   Signature
            0      24     0 defaultOpt$lzy$1   Lscala/runtime/LazyRef;
            0      24     1 defaults$2   Lshapeless/$colon$colon;
            0      24     2 headEncode$1   Lshapeless/Strict;
    MethodParameters:
      Name                           Flags
      defaultOpt$lzy$1               final
      defaults$2                     final
      headEncode$1                   final

  private static final argonaut.EncodeJson tailEncode0$lzycompute$1(scala.runtime.LazyRef, argonaut.derive.HListProductEncodeJson, argonaut.derive.JsonProductCodec, shapeless.$colon$colon);
    descriptor: (Lscala/runtime/LazyRef;Largonaut/derive/HListProductEncodeJson;Largonaut/derive/JsonProductCodec;Lshapeless/$colon$colon;)Largonaut/EncodeJson;
    flags: (0x101a) ACC_PRIVATE, ACC_STATIC, ACC_FINAL, ACC_SYNTHETIC
    Code:
      stack=4, locals=6, args_size=4
         0: aload_0
         1: dup
         2: astore        4
         4: monitorenter
         5: aload_0
         6: invokevirtual #145                // Method scala/runtime/LazyRef.initialized:()Z
         9: ifeq          22
        12: aload_0
        13: invokevirtual #146                // Method scala/runtime/LazyRef.value:()Ljava/lang/Object;
        16: checkcast     #130                // class argonaut/EncodeJson
        19: goto          40
        22: aload_0
        23: aload_1
        24: aload_2
        25: aload_3
        26: invokevirtual #183                // Method shapeless/$colon$colon.tail:()Lshapeless/HList;
        29: invokeinterface #188,  3          // InterfaceMethod argonaut/derive/HListProductEncodeJson.apply:(Largonaut/derive/JsonProductCodec;Lshapeless/HList;)Largonaut/EncodeJson;
        34: invokevirtual #167                // Method scala/runtime/LazyRef.initialize:(Ljava/lang/Object;)Ljava/lang/Object;
        37: checkcast     #130                // class argonaut/EncodeJson
        40: astore        5
        42: aload         4
        44: monitorexit
        45: aload         5
        47: goto          54
        50: aload         4
        52: monitorexit
        53: athrow
        54: areturn
      Exception table:
         from    to  target type
             5    42    50   any
      StackMapTable: number_of_entries = 4
        frame_type = 252 /* append */
          offset_delta = 22
          locals = [ class scala/runtime/LazyRef ]
        frame_type = 81 /* same_locals_1_stack_item */
          stack = [ class argonaut/EncodeJson ]
        frame_type = 73 /* same_locals_1_stack_item */
          stack = [ class java/lang/Throwable ]
        frame_type = 255 /* full_frame */
          offset_delta = 3
          locals = [ class scala/runtime/LazyRef, class argonaut/derive/HListProductEncodeJson, class argonaut/derive/JsonProductCodec, class shapeless/$colon$colon, class scala/runtime/LazyRef, class argonaut/EncodeJson ]
          stack = [ class argonaut/EncodeJson ]
      LineNumberTable:
        line 96: 0
      LocalVariableTable:
        Start  Length  Slot  Name   Signature
            0      55     0 tailEncode0$lzy$1   Lscala/runtime/LazyRef;
            0      55     1 tailEncode$1   Largonaut/derive/HListProductEncodeJson;
            0      55     2 productCodec$2   Largonaut/derive/JsonProductCodec;
            0      55     3 defaults$2   Lshapeless/$colon$colon;
    MethodParameters:
      Name                           Flags
      tailEncode0$lzy$1              final
      tailEncode$1                   final
      productCodec$2                 final
      defaults$2                     final

  private static final argonaut.EncodeJson tailEncode0$1(scala.runtime.LazyRef, argonaut.derive.HListProductEncodeJson, argonaut.derive.JsonProductCodec, shapeless.$colon$colon);
    descriptor: (Lscala/runtime/LazyRef;Largonaut/derive/HListProductEncodeJson;Largonaut/derive/JsonProductCodec;Lshapeless/$colon$colon;)Largonaut/EncodeJson;
    flags: (0x001a) ACC_PRIVATE, ACC_STATIC, ACC_FINAL
    Code:
      stack=4, locals=4, args_size=4
         0: aload_0
         1: invokevirtual #145                // Method scala/runtime/LazyRef.initialized:()Z
         4: ifeq          17
         7: aload_0
         8: invokevirtual #146                // Method scala/runtime/LazyRef.value:()Ljava/lang/Object;
        11: checkcast     #130                // class argonaut/EncodeJson
        14: goto          24
        17: aload_0
        18: aload_1
        19: aload_2
        20: aload_3
        21: invokestatic  #191                // Method tailEncode0$lzycompute$1:(Lscala/runtime/LazyRef;Largonaut/derive/HListProductEncodeJson;Largonaut/derive/JsonProductCodec;Lshapeless/$colon$colon;)Largonaut/EncodeJson;
        24: areturn
      StackMapTable: number_of_entries = 2
        frame_type = 17 /* same */
        frame_type = 70 /* same_locals_1_stack_item */
          stack = [ class argonaut/EncodeJson ]
      LineNumberTable:
        line 96: 0
      LocalVariableTable:
        Start  Length  Slot  Name   Signature
            0      25     0 tailEncode0$lzy$1   Lscala/runtime/LazyRef;
            0      25     1 tailEncode$1   Largonaut/derive/HListProductEncodeJson;
            0      25     2 productCodec$2   Largonaut/derive/JsonProductCodec;
            0      25     3 defaults$2   Lshapeless/$colon$colon;
    MethodParameters:
      Name                           Flags
      tailEncode0$lzy$1              final
      tailEncode$1                   final
      productCodec$2                 final
      defaults$2                     final

  public static final scala.Option $anonfun$hcons$4(scala.runtime.LazyRef, shapeless.$colon$colon, shapeless.Strict);
    descriptor: (Lscala/runtime/LazyRef;Lshapeless/$colon$colon;Lshapeless/Strict;)Lscala/Option;
    flags: (0x1019) ACC_PUBLIC, ACC_STATIC, ACC_FINAL, ACC_SYNTHETIC
    Code:
      stack=3, locals=3, args_size=3
         0: aload_0
         1: aload_1
         2: aload_2
         3: invokestatic  #194                // Method defaultOpt$1:(Lscala/runtime/LazyRef;Lshapeless/$colon$colon;Lshapeless/Strict;)Lscala/Option;
         6: areturn
      LineNumberTable:
        line 102: 0
      LocalVariableTable:
        Start  Length  Slot  Name   Signature
            0       7     0 defaultOpt$lzy$1   Lscala/runtime/LazyRef;
            0       7     1 defaults$2   Lshapeless/$colon$colon;
            0       7     2 headEncode$1   Lshapeless/Strict;
    MethodParameters:
      Name                           Flags
      defaultOpt$lzy$1               final
      defaults$2                     final
      headEncode$1                   final

  public static final argonaut.Json $anonfun$hcons$3(argonaut.derive.JsonProductCodec, shapeless.Witness, shapeless.Strict, scala.runtime.LazyRef, argonaut.derive.HListProductEncodeJson, shapeless.$colon$colon, scala.runtime.LazyRef, shapeless.$colon$colon);
    descriptor: (Largonaut/derive/JsonProductCodec;Lshapeless/Witness;Lshapeless/Strict;Lscala/runtime/LazyRef;Largonaut/derive/HListProductEncodeJson;Lshapeless/$colon$colon;Lscala/runtime/LazyRef;Lshapeless/$colon$colon;)Largonaut/Json;
    flags: (0x1019) ACC_PUBLIC, ACC_STATIC, ACC_FINAL, ACC_SYNTHETIC
    Code:
      stack=6, locals=8, args_size=8
         0: aload_0
         1: getstatic     #201                // Field scala/Predef$ArrowAssoc$.MODULE$:Lscala/Predef$ArrowAssoc$;
         4: getstatic     #206                // Field scala/Predef$.MODULE$:Lscala/Predef$;
         7: aload_1
         8: invokeinterface #209,  1          // InterfaceMethod shapeless/Witness.value:()Ljava/lang/Object;
        13: checkcast     #211                // class scala/Symbol
        16: invokevirtual #215                // Method scala/Symbol.name:()Ljava/lang/String;
        19: invokevirtual #218                // Method scala/Predef$.ArrowAssoc:(Ljava/lang/Object;)Ljava/lang/Object;
        22: aload_2
        23: invokeinterface #128,  1          // InterfaceMethod shapeless/Strict.value:()Ljava/lang/Object;
        28: checkcast     #130                // class argonaut/EncodeJson
        31: aload         7
        33: invokevirtual #153                // Method shapeless/$colon$colon.head:()Ljava/lang/Object;
        36: invokeinterface #134,  2          // InterfaceMethod argonaut/EncodeJson.encode:(Ljava/lang/Object;)Largonaut/Json;
        41: invokevirtual #222                // Method scala/Predef$ArrowAssoc$.$minus$greater$extension:(Ljava/lang/Object;Ljava/lang/Object;)Lscala/Tuple2;
        44: aload_3
        45: aload         4
        47: aload_0
        48: aload         5
        50: invokestatic  #224                // Method tailEncode0$1:(Lscala/runtime/LazyRef;Largonaut/derive/HListProductEncodeJson;Largonaut/derive/JsonProductCodec;Lshapeless/$colon$colon;)Largonaut/EncodeJson;
        53: aload         7
        55: invokevirtual #183                // Method shapeless/$colon$colon.tail:()Lshapeless/HList;
        58: invokeinterface #134,  2          // InterfaceMethod argonaut/EncodeJson.encode:(Ljava/lang/Object;)Largonaut/Json;
        63: aload         6
        65: aload         5
        67: aload_2
        68: invokedynamic #233,  0            // InvokeDynamic #4:apply:(Lscala/runtime/LazyRef;Lshapeless/$colon$colon;Lshapeless/Strict;)Lscala/Function0;
        73: invokeinterface #237,  4          // InterfaceMethod argonaut/derive/JsonProductCodec.encodeField:(Lscala/Tuple2;Largonaut/Json;Lscala/Function0;)Largonaut/Json;
        78: areturn
      LineNumberTable:
        line 99: 0
        line 100: 4
        line 101: 44
        line 102: 63
      LocalVariableTable:
        Start  Length  Slot  Name   Signature
            0      79     0 productCodec$2   Largonaut/derive/JsonProductCodec;
            0      79     1 key$1   Lshapeless/Witness;
            0      79     2 headEncode$1   Lshapeless/Strict;
            0      79     3 tailEncode0$lzy$1   Lscala/runtime/LazyRef;
            0      79     4 tailEncode$1   Largonaut/derive/HListProductEncodeJson;
            0      79     5 defaults$2   Lshapeless/$colon$colon;
            0      79     6 defaultOpt$lzy$1   Lscala/runtime/LazyRef;
            0      79     7     l   Lshapeless/$colon$colon;
    MethodParameters:
      Name                           Flags
      productCodec$2                 final
      key$1                          final
      headEncode$1                   final
      tailEncode0$lzy$1              final
      tailEncode$1                   final
      defaults$2                     final
      defaultOpt$lzy$1               final
      l                              final

  public static final argonaut.EncodeJson $anonfun$hcons$1(shapeless.Strict, argonaut.derive.HListProductEncodeJson, shapeless.Witness, argonaut.derive.JsonProductCodec, shapeless.$colon$colon);
    descriptor: (Lshapeless/Strict;Largonaut/derive/HListProductEncodeJson;Lshapeless/Witness;Largonaut/derive/JsonProductCodec;Lshapeless/$colon$colon;)Largonaut/EncodeJson;
    flags: (0x1019) ACC_PUBLIC, ACC_STATIC, ACC_FINAL, ACC_SYNTHETIC
    Code:
      stack=8, locals=7, args_size=5
         0: new           #141                // class scala/runtime/LazyRef
         3: dup
         4: invokespecial #239                // Method scala/runtime/LazyRef."<init>":()V
         7: astore        5
         9: new           #141                // class scala/runtime/LazyRef
        12: dup
        13: invokespecial #239                // Method scala/runtime/LazyRef."<init>":()V
        16: astore        6
        18: getstatic     #105                // Field argonaut/EncodeJson$.MODULE$:Largonaut/EncodeJson$;
        21: aload_3
        22: aload_2
        23: aload_0
        24: aload         6
        26: aload_1
        27: aload         4
        29: aload         5
        31: invokedynamic #247,  0            // InvokeDynamic #5:apply:(Largonaut/derive/JsonProductCodec;Lshapeless/Witness;Lshapeless/Strict;Lscala/runtime/LazyRef;Largonaut/derive/HListProductEncodeJson;Lshapeless/$colon$colon;Lscala/runtime/LazyRef;)Lscala/Function1;
        36: invokevirtual #118                // Method argonaut/EncodeJson$.apply:(Lscala/Function1;)Largonaut/EncodeJson;
        39: areturn
      LineNumberTable:
        line 95: 0
        line 96: 9
        line 98: 18
      LocalVariableTable:
        Start  Length  Slot  Name   Signature
            7      32     5 defaultOpt$lzy   Lscala/runtime/LazyRef;
           16      23     6 tailEncode0$lzy   Lscala/runtime/LazyRef;
            0      40     0 headEncode$1   Lshapeless/Strict;
            0      40     1 tailEncode$1   Largonaut/derive/HListProductEncodeJson;
            0      40     2 key$1   Lshapeless/Witness;
            0      40     3 productCodec   Largonaut/derive/JsonProductCodec;
            0      40     4 defaults   Lshapeless/$colon$colon;
    MethodParameters:
      Name                           Flags
      headEncode$1                   final
      tailEncode$1                   final
      key$1                          final
      productCodec                   final
      defaults                       final

  private argonaut.derive.HListProductEncodeJson$();
    descriptor: ()V
    flags: (0x0002) ACC_PRIVATE
    Code:
      stack=1, locals=1, args_size=1
         0: aload_0
         1: invokespecial #250                // Method java/lang/Object."<init>":()V
         4: return
      LineNumberTable:
        line 109: 0
        line 71: 4
      LocalVariableTable:
        Start  Length  Slot  Name   Signature
            0       5     0  this   Largonaut/derive/HListProductEncodeJson$;

  private static java.lang.Object $deserializeLambda$(java.lang.invoke.SerializedLambda);
    descriptor: (Ljava/lang/invoke/SerializedLambda;)Ljava/lang/Object;
    flags: (0x100a) ACC_PRIVATE, ACC_STATIC, ACC_SYNTHETIC
    Code:
      stack=1, locals=1, args_size=1
         0: aload_0
         1: invokedynamic #262,  0            // InvokeDynamic #6:lambdaDeserialize:(Ljava/lang/invoke/SerializedLambda;)Ljava/lang/Object;
         6: areturn
}
InnerClasses:
  public final #7;                        // class argonaut/derive/HListProductEncodeJson$$anon$4
  public static final #12= #9 of #11;     // Lookup=class java/lang/invoke/MethodHandles$Lookup of class java/lang/invoke/MethodHandles
  public static #17= #14 of #16;          // ArrowAssoc$=class scala/Predef$ArrowAssoc$ of class scala/Predef
SourceFile: "MkEncodeJson.scala"
BootstrapMethods:
  0: #46 REF_invokeStatic java/lang/invoke/LambdaMetafactory.altMetafactory:(Ljava/lang/invoke/MethodHandles$Lookup;Ljava/lang/String;Ljava/lang/invoke/MethodType;[Ljava/lang/Object;)Ljava/lang/invoke/CallSite;
    Method arguments:
      #31 (Ljava/lang/Object;Ljava/lang/Object;)Ljava/lang/Object;
      #36 REF_invokeStatic argonaut/derive/HListProductEncodeJson$.$anonfun$hnil$1:(Largonaut/derive/JsonProductCodec;Lshapeless/HNil;)Largonaut/EncodeJson;
      #37 (Largonaut/derive/JsonProductCodec;Lshapeless/HNil;)Largonaut/EncodeJson;
      #38 5
      #39 1
      #37 (Largonaut/derive/JsonProductCodec;Lshapeless/HNil;)Largonaut/EncodeJson;
  1: #46 REF_invokeStatic java/lang/invoke/LambdaMetafactory.altMetafactory:(Ljava/lang/invoke/MethodHandles$Lookup;Ljava/lang/String;Ljava/lang/invoke/MethodType;[Ljava/lang/Object;)Ljava/lang/invoke/CallSite;
    Method arguments:
      #31 (Ljava/lang/Object;Ljava/lang/Object;)Ljava/lang/Object;
      #79 REF_invokeStatic argonaut/derive/HListProductEncodeJson$.$anonfun$hcons$1:(Lshapeless/Strict;Largonaut/derive/HListProductEncodeJson;Lshapeless/Witness;Largonaut/derive/JsonProductCodec;Lshapeless/$colon$colon;)Largonaut/EncodeJson;
      #81 (Largonaut/derive/JsonProductCodec;Lshapeless/$colon$colon;)Largonaut/EncodeJson;
      #38 5
      #39 1
      #81 (Largonaut/derive/JsonProductCodec;Lshapeless/$colon$colon;)Largonaut/EncodeJson;
  2: #46 REF_invokeStatic java/lang/invoke/LambdaMetafactory.altMetafactory:(Ljava/lang/invoke/MethodHandles$Lookup;Ljava/lang/String;Ljava/lang/invoke/MethodType;[Ljava/lang/Object;)Ljava/lang/invoke/CallSite;
    Method arguments:
      #107 (Ljava/lang/Object;)Ljava/lang/Object;
      #110 REF_invokeStatic argonaut/derive/HListProductEncodeJson$.$anonfun$hnil$2:(Largonaut/derive/JsonProductCodec;Lshapeless/HNil;)Largonaut/Json;
      #112 (Lshapeless/HNil;)Largonaut/Json;
      #38 5
      #39 1
      #112 (Lshapeless/HNil;)Largonaut/Json;
  3: #46 REF_invokeStatic java/lang/invoke/LambdaMetafactory.altMetafactory:(Ljava/lang/invoke/MethodHandles$Lookup;Ljava/lang/String;Ljava/lang/invoke/MethodType;[Ljava/lang/Object;)Ljava/lang/invoke/CallSite;
    Method arguments:
      #107 (Ljava/lang/Object;)Ljava/lang/Object;
      #156 REF_invokeStatic argonaut/derive/HListProductEncodeJson$.$anonfun$hcons$2:(Lshapeless/Strict;Ljava/lang/Object;)Largonaut/Json;
      #157 (Ljava/lang/Object;)Largonaut/Json;
      #38 5
      #39 1
      #157 (Ljava/lang/Object;)Largonaut/Json;
  4: #46 REF_invokeStatic java/lang/invoke/LambdaMetafactory.altMetafactory:(Ljava/lang/invoke/MethodHandles$Lookup;Ljava/lang/String;Ljava/lang/invoke/MethodType;[Ljava/lang/Object;)Ljava/lang/invoke/CallSite;
    Method arguments:
      #225 ()Ljava/lang/Object;
      #228 REF_invokeStatic argonaut/derive/HListProductEncodeJson$.$anonfun$hcons$4:(Lscala/runtime/LazyRef;Lshapeless/$colon$colon;Lshapeless/Strict;)Lscala/Option;
      #230 ()Lscala/Option;
      #38 5
      #39 1
      #230 ()Lscala/Option;
  5: #46 REF_invokeStatic java/lang/invoke/LambdaMetafactory.altMetafactory:(Ljava/lang/invoke/MethodHandles$Lookup;Ljava/lang/String;Ljava/lang/invoke/MethodType;[Ljava/lang/Object;)Ljava/lang/invoke/CallSite;
    Method arguments:
      #107 (Ljava/lang/Object;)Ljava/lang/Object;
      #242 REF_invokeStatic argonaut/derive/HListProductEncodeJson$.$anonfun$hcons$3:(Largonaut/derive/JsonProductCodec;Lshapeless/Witness;Lshapeless/Strict;Lscala/runtime/LazyRef;Largonaut/derive/HListProductEncodeJson;Lshapeless/$colon$colon;Lscala/runtime/LazyRef;Lshapeless/$colon$colon;)Largonaut/Json;
      #244 (Lshapeless/$colon$colon;)Largonaut/Json;
      #38 5
      #39 1
      #244 (Lshapeless/$colon$colon;)Largonaut/Json;
  6: #259 REF_invokeStatic scala/runtime/LambdaDeserialize.bootstrap:(Ljava/lang/invoke/MethodHandles$Lookup;Ljava/lang/String;Ljava/lang/invoke/MethodType;[Ljava/lang/invoke/MethodHandle;)Ljava/lang/invoke/CallSite;
    Method arguments:
      #79 REF_invokeStatic argonaut/derive/HListProductEncodeJson$.$anonfun$hcons$1:(Lshapeless/Strict;Largonaut/derive/HListProductEncodeJson;Lshapeless/Witness;Largonaut/derive/JsonProductCodec;Lshapeless/$colon$colon;)Largonaut/EncodeJson;
      #156 REF_invokeStatic argonaut/derive/HListProductEncodeJson$.$anonfun$hcons$2:(Lshapeless/Strict;Ljava/lang/Object;)Largonaut/Json;
      #242 REF_invokeStatic argonaut/derive/HListProductEncodeJson$.$anonfun$hcons$3:(Largonaut/derive/JsonProductCodec;Lshapeless/Witness;Lshapeless/Strict;Lscala/runtime/LazyRef;Largonaut/derive/HListProductEncodeJson;Lshapeless/$colon$colon;Lscala/runtime/LazyRef;Lshapeless/$colon$colon;)Largonaut/Json;
      #228 REF_invokeStatic argonaut/derive/HListProductEncodeJson$.$anonfun$hcons$4:(Lscala/runtime/LazyRef;Lshapeless/$colon$colon;Lshapeless/Strict;)Lscala/Option;
      #36 REF_invokeStatic argonaut/derive/HListProductEncodeJson$.$anonfun$hnil$1:(Largonaut/derive/JsonProductCodec;Lshapeless/HNil;)Largonaut/EncodeJson;
      #110 REF_invokeStatic argonaut/derive/HListProductEncodeJson$.$anonfun$hnil$2:(Largonaut/derive/JsonProductCodec;Lshapeless/HNil;)Largonaut/Json;
  ScalaInlineInfo: length = 0x4F (unknown attribute)
   01 01 00 0F 00 4B 00 4C 01 00 77 00 78 01 00 C3
   00 C4 01 00 C0 00 89 01 00 20 00 21 01 00 57 00
   58 01 00 19 00 18 01 00 2F 00 39 01 00 AC 00 89
   01 00 88 00 89 01 00 45 00 46 01 00 14 00 43 01
   00 33 00 34 01 00 BD 00 B0 01 00 AF 00 B0 01
  Scala: length = 0x0 (unknown attribute)

