Classfile /Users/mw/Projects/slang-braindump/.jar/jar8/assemble/slang-braindump/assemble/content/argonaut/derive/JsonProductCodec$$anon$2.class
  Last modified May 29, 2022; size 1921 bytes
  SHA-256 checksum 5d2152c91672caf3ea8b1d68f9f26f401733a78c86646f18fe8d40fee2d09091
  Compiled from "JsonProductCodec.scala"
public final class argonaut.derive.JsonProductCodec$$anon$2 extends argonaut.derive.JsonProductObjCodec
  minor version: 0
  major version: 52
  flags: (0x0031) ACC_PUBLIC, ACC_FINAL, ACC_SUPER
  this_class: #2                          // argonaut/derive/JsonProductCodec$$anon$2
  super_class: #4                         // argonaut/derive/JsonProductObjCodec
  interfaces: 0, fields: 0, methods: 4, attributes: 6
Constant pool:
   #1 = Utf8               argonaut/derive/JsonProductCodec$$anon$2
   #2 = Class              #1             // argonaut/derive/JsonProductCodec$$anon$2
   #3 = Utf8               argonaut/derive/JsonProductObjCodec
   #4 = Class              #3             // argonaut/derive/JsonProductObjCodec
   #5 = Utf8               JsonProductCodec.scala
   #6 = Utf8               argonaut/derive/JsonProductCodec$
   #7 = Class              #6             // argonaut/derive/JsonProductCodec$
   #8 = Utf8               java/lang/invoke/MethodHandles$Lookup
   #9 = Class              #8             // java/lang/invoke/MethodHandles$Lookup
  #10 = Utf8               java/lang/invoke/MethodHandles
  #11 = Class              #10            // java/lang/invoke/MethodHandles
  #12 = Utf8               Lookup
  #13 = Utf8               encodeField
  #14 = Utf8               (Lscala/Tuple2;Largonaut/Json;Lscala/Function0;)Largonaut/Json;
  #15 = Utf8               (Lscala/Tuple2<Ljava/lang/String;Largonaut/Json;>;Largonaut/Json;Lscala/Function0<Lscala/Option<Largonaut/Json;>;>;)Largonaut/Json;
  #16 = Utf8               field
  #17 = Utf8               obj
  #18 = Utf8               default
  #19 = Utf8               ()Ljava/lang/Object;
  #20 = MethodType         #19            //  ()Ljava/lang/Object;
  #21 = Utf8               $anonfun$encodeField$1
  #22 = Utf8               ()Lscala/Option;
  #23 = NameAndType        #21:#22        // $anonfun$encodeField$1:()Lscala/Option;
  #24 = Methodref          #2.#23         // argonaut/derive/JsonProductCodec$$anon$2.$anonfun$encodeField$1:()Lscala/Option;
  #25 = MethodHandle       6:#24          // REF_invokeStatic argonaut/derive/JsonProductCodec$$anon$2.$anonfun$encodeField$1:()Lscala/Option;
  #26 = MethodType         #22            //  ()Lscala/Option;
  #27 = Integer            5
  #28 = Integer            1
  #29 = Utf8               java/lang/invoke/LambdaMetafactory
  #30 = Class              #29            // java/lang/invoke/LambdaMetafactory
  #31 = Utf8               altMetafactory
  #32 = Utf8               (Ljava/lang/invoke/MethodHandles$Lookup;Ljava/lang/String;Ljava/lang/invoke/MethodType;[Ljava/lang/Object;)Ljava/lang/invoke/CallSite;
  #33 = NameAndType        #31:#32        // altMetafactory:(Ljava/lang/invoke/MethodHandles$Lookup;Ljava/lang/String;Ljava/lang/invoke/MethodType;[Ljava/lang/Object;)Ljava/lang/invoke/CallSite;
  #34 = Methodref          #30.#33        // java/lang/invoke/LambdaMetafactory.altMetafactory:(Ljava/lang/invoke/MethodHandles$Lookup;Ljava/lang/String;Ljava/lang/invoke/MethodType;[Ljava/lang/Object;)Ljava/lang/invoke/CallSite;
  #35 = MethodHandle       6:#34          // REF_invokeStatic java/lang/invoke/LambdaMetafactory.altMetafactory:(Ljava/lang/invoke/MethodHandles$Lookup;Ljava/lang/String;Ljava/lang/invoke/MethodType;[Ljava/lang/Object;)Ljava/lang/invoke/CallSite;
  #36 = Utf8               apply
  #37 = Utf8               ()Lscala/Function0;
  #38 = NameAndType        #36:#37        // apply:()Lscala/Function0;
  #39 = InvokeDynamic      #0:#38         // #0:apply:()Lscala/Function0;
  #40 = NameAndType        #13:#14        // encodeField:(Lscala/Tuple2;Largonaut/Json;Lscala/Function0;)Largonaut/Json;
  #41 = Methodref          #4.#40         // argonaut/derive/JsonProductObjCodec.encodeField:(Lscala/Tuple2;Largonaut/Json;Lscala/Function0;)Largonaut/Json;
  #42 = Utf8               this
  #43 = Utf8               Largonaut/derive/JsonProductCodec$$anon$2;
  #44 = Utf8               Lscala/Tuple2;
  #45 = Utf8               Largonaut/Json;
  #46 = Utf8               Lscala/Function0;
  #47 = Utf8               scala/Option$
  #48 = Class              #47            // scala/Option$
  #49 = Utf8               MODULE$
  #50 = Utf8               Lscala/Option$;
  #51 = NameAndType        #49:#50        // MODULE$:Lscala/Option$;
  #52 = Fieldref           #48.#51        // scala/Option$.MODULE$:Lscala/Option$;
  #53 = Utf8               empty
  #54 = NameAndType        #53:#22        // empty:()Lscala/Option;
  #55 = Methodref          #48.#54        // scala/Option$.empty:()Lscala/Option;
  #56 = Utf8               <init>
  #57 = Utf8               ()V
  #58 = NameAndType        #56:#57        // "<init>":()V
  #59 = Methodref          #4.#58         // argonaut/derive/JsonProductObjCodec."<init>":()V
  #60 = Utf8               $deserializeLambda$
  #61 = Utf8               (Ljava/lang/invoke/SerializedLambda;)Ljava/lang/Object;
  #62 = Utf8               scala/runtime/LambdaDeserialize
  #63 = Class              #62            // scala/runtime/LambdaDeserialize
  #64 = Utf8               bootstrap
  #65 = Utf8               (Ljava/lang/invoke/MethodHandles$Lookup;Ljava/lang/String;Ljava/lang/invoke/MethodType;[Ljava/lang/invoke/MethodHandle;)Ljava/lang/invoke/CallSite;
  #66 = NameAndType        #64:#65        // bootstrap:(Ljava/lang/invoke/MethodHandles$Lookup;Ljava/lang/String;Ljava/lang/invoke/MethodType;[Ljava/lang/invoke/MethodHandle;)Ljava/lang/invoke/CallSite;
  #67 = Methodref          #63.#66        // scala/runtime/LambdaDeserialize.bootstrap:(Ljava/lang/invoke/MethodHandles$Lookup;Ljava/lang/String;Ljava/lang/invoke/MethodType;[Ljava/lang/invoke/MethodHandle;)Ljava/lang/invoke/CallSite;
  #68 = MethodHandle       6:#67          // REF_invokeStatic scala/runtime/LambdaDeserialize.bootstrap:(Ljava/lang/invoke/MethodHandles$Lookup;Ljava/lang/String;Ljava/lang/invoke/MethodType;[Ljava/lang/invoke/MethodHandle;)Ljava/lang/invoke/CallSite;
  #69 = Utf8               lambdaDeserialize
  #70 = NameAndType        #69:#61        // lambdaDeserialize:(Ljava/lang/invoke/SerializedLambda;)Ljava/lang/Object;
  #71 = InvokeDynamic      #1:#70         // #1:lambdaDeserialize:(Ljava/lang/invoke/SerializedLambda;)Ljava/lang/Object;
  #72 = Utf8               Code
  #73 = Utf8               LineNumberTable
  #74 = Utf8               LocalVariableTable
  #75 = Utf8               Signature
  #76 = Utf8               MethodParameters
  #77 = Utf8               InnerClasses
  #78 = Utf8               EnclosingMethod
  #79 = Utf8               SourceFile
  #80 = Utf8               BootstrapMethods
  #81 = Utf8               ScalaInlineInfo
  #82 = Utf8               Scala
{
  public argonaut.Json encodeField(scala.Tuple2<java.lang.String, argonaut.Json>, argonaut.Json, scala.Function0<scala.Option<argonaut.Json>>);
    descriptor: (Lscala/Tuple2;Largonaut/Json;Lscala/Function0;)Largonaut/Json;
    flags: (0x0001) ACC_PUBLIC
    Code:
      stack=4, locals=4, args_size=4
         0: aload_0
         1: aload_1
         2: aload_2
         3: invokedynamic #39,  0             // InvokeDynamic #0:apply:()Lscala/Function0;
         8: invokespecial #41                 // Method argonaut/derive/JsonProductObjCodec.encodeField:(Lscala/Tuple2;Largonaut/Json;Lscala/Function0;)Largonaut/Json;
        11: areturn
      LineNumberTable:
        line 20: 0
      LocalVariableTable:
        Start  Length  Slot  Name   Signature
            0      12     0  this   Largonaut/derive/JsonProductCodec$$anon$2;
            0      12     1 field   Lscala/Tuple2;
            0      12     2   obj   Largonaut/Json;
            0      12     3 default   Lscala/Function0;
    Signature: #15                          // (Lscala/Tuple2<Ljava/lang/String;Largonaut/Json;>;Largonaut/Json;Lscala/Function0<Lscala/Option<Largonaut/Json;>;>;)Largonaut/Json;
    MethodParameters:
      Name                           Flags
      field                          final
      obj                            final
      default                        final

  public static final scala.Option $anonfun$encodeField$1();
    descriptor: ()Lscala/Option;
    flags: (0x1019) ACC_PUBLIC, ACC_STATIC, ACC_FINAL, ACC_SYNTHETIC
    Code:
      stack=1, locals=0, args_size=0
         0: getstatic     #52                 // Field scala/Option$.MODULE$:Lscala/Option$;
         3: invokevirtual #55                 // Method scala/Option$.empty:()Lscala/Option;
         6: areturn
      LineNumberTable:
        line 20: 0

  public argonaut.derive.JsonProductCodec$$anon$2();
    descriptor: ()V
    flags: (0x0001) ACC_PUBLIC
    Code:
      stack=1, locals=1, args_size=1
         0: aload_0
         1: invokespecial #59                 // Method argonaut/derive/JsonProductObjCodec."<init>":()V
         4: return
      LineNumberTable:
        line 18: 0
      LocalVariableTable:
        Start  Length  Slot  Name   Signature
            0       5     0  this   Largonaut/derive/JsonProductCodec$$anon$2;

  private static java.lang.Object $deserializeLambda$(java.lang.invoke.SerializedLambda);
    descriptor: (Ljava/lang/invoke/SerializedLambda;)Ljava/lang/Object;
    flags: (0x100a) ACC_PRIVATE, ACC_STATIC, ACC_SYNTHETIC
    Code:
      stack=1, locals=1, args_size=1
         0: aload_0
         1: invokedynamic #71,  0             // InvokeDynamic #1:lambdaDeserialize:(Ljava/lang/invoke/SerializedLambda;)Ljava/lang/Object;
         6: areturn
}
InnerClasses:
  public final #2;                        // class argonaut/derive/JsonProductCodec$$anon$2
  public static final #12= #9 of #11;     // Lookup=class java/lang/invoke/MethodHandles$Lookup of class java/lang/invoke/MethodHandles
EnclosingMethod: #7.#0                  // argonaut.derive.JsonProductCodec$
SourceFile: "JsonProductCodec.scala"
BootstrapMethods:
  0: #35 REF_invokeStatic java/lang/invoke/LambdaMetafactory.altMetafactory:(Ljava/lang/invoke/MethodHandles$Lookup;Ljava/lang/String;Ljava/lang/invoke/MethodType;[Ljava/lang/Object;)Ljava/lang/invoke/CallSite;
    Method arguments:
      #20 ()Ljava/lang/Object;
      #25 REF_invokeStatic argonaut/derive/JsonProductCodec$$anon$2.$anonfun$encodeField$1:()Lscala/Option;
      #26 ()Lscala/Option;
      #27 5
      #28 1
      #26 ()Lscala/Option;
  1: #68 REF_invokeStatic scala/runtime/LambdaDeserialize.bootstrap:(Ljava/lang/invoke/MethodHandles$Lookup;Ljava/lang/String;Ljava/lang/invoke/MethodType;[Ljava/lang/invoke/MethodHandle;)Ljava/lang/invoke/CallSite;
    Method arguments:
      #25 REF_invokeStatic argonaut/derive/JsonProductCodec$$anon$2.$anonfun$encodeField$1:()Lscala/Option;
  ScalaInlineInfo: length = 0x13 (unknown attribute)
   01 01 00 03 00 15 00 16 01 00 38 00 39 01 00 0D
   00 0E 01
  Scala: length = 0x0 (unknown attribute)

