Classfile /Users/mw/Projects/slang-braindump/.jar/jar8/assemble/slang-braindump/assemble/content/argonaut/derive/ProductEncodeJson.class
  Last modified May 29, 2022; size 2306 bytes
  SHA-256 checksum 8890fabdf9e6d4138ccf1e3b2e118c6746b0df4a129e001d82fa439b5e144018
  Compiled from "MkEncodeJson.scala"
public interface argonaut.derive.ProductEncodeJson<P extends java.lang.Object>
  minor version: 0
  major version: 52
  flags: (0x0601) ACC_PUBLIC, ACC_INTERFACE, ACC_ABSTRACT
  this_class: #2                          // argonaut/derive/ProductEncodeJson
  super_class: #5                         // java/lang/Object
  interfaces: 0, fields: 0, methods: 3, attributes: 6
Constant pool:
   #1 = Utf8               argonaut/derive/ProductEncodeJson
   #2 = Class              #1             // argonaut/derive/ProductEncodeJson
   #3 = Utf8               <P:Ljava/lang/Object;>Ljava/lang/Object;
   #4 = Utf8               java/lang/Object
   #5 = Class              #4             // java/lang/Object
   #6 = Utf8               MkEncodeJson.scala
   #7 = Utf8               Lscala/reflect/ScalaSignature;
   #8 = Utf8               bytes
   #9 = Utf8               \u0006\u0005U4q\u0001C\u0005\u0011\u0002G\u0005a\u0002C\u0003\u0017\u0001\u0019\u0005qcB\u0003.\u0013!\u0005aFB\u0003\t\u0013!\u0005q\u0006C\u00031\u0007\u0011\u0005\u0011\u0007C\u0003\u0017\u0007\u0011\u0005!\u0007C\u0003:\u0007\u0011\u0005!\bC\u0003F\u0007\u0011\raIA\tQe>$Wo\u0019;F]\u000e|G-\u001a&t_:T!AC\u0006\u0002\r\u0011,\'/\u001b<f\u0015\u0005a\u0011\u0001C1sO>t\u0017-\u001e;\u0004\u0001U\u0011qBH\n\u0003\u0001A\u0001\"!\u0005\u000b\u000e\u0003IQ\u0011aE\u0001\u0006g\u000e\fG.Y\u0005\u0003+I\u0011a!\u00118z%\u00164\u0017!B1qa2LHC\u0001\r(!\rI\"\u0004H\u0007\u0002\u0017%\u00111d\u0003\u0002\u000b\u000b:\u001cw\u000eZ3Kg>t\u0007CA\u000f\u001f\u0019\u0001!Qa\b\u0001C\u0002\u0001\u0012\u0011\u0001U\t\u0003C\u0011\u0002\"!\u0005\u0012\n\u0005\r\u0012\"a\u0002(pi\"Lgn\u001a\t\u0003#\u0015J!A\n\n\u0003\u0007\u0005s\u0017\u0010C\u0003)\u0003\u0001\u0007\u0011&\u0001\u0007qe>$Wo\u0019;D_\u0012,7\r\u0005\u0002+W5\t\u0011\"\u0003\u0002-\u0013\t\u0001\"j]8o!J|G-^2u\u0007>$WmY\u0001\u0012!J|G-^2u\u000b:\u001cw\u000eZ3Kg>t\u0007C\u0001\u0016\u0004\'\t\u0019\u0001#\u0001\u0004=S:LGO\u0010\u000b\u0002]U\u00111G\u000e\u000b\u0003i]\u00022A\u000b\u00016!\tib\u0007B\u0003 \u000b\t\u0007\u0001\u0005C\u00039\u000b\u0001\u000fA\'\u0001\u0006f]\u000e|G-\u001a&t_:\f\u0001\"\u001b8ti\u0006t7-Z\u000b\u0003wy\"\"\u0001P \u0011\u0007)\u0002Q\b\u0005\u0002\u001e}\u0011)qD\u0002b\u0001A!)\u0001I\u0002a\u0001\u0003\u0006\ta\r\u0005\u0003\u0012\u0005&\"\u0015BA\"\u0013\u0005%1UO\\2uS>t\u0017\u0007E\u0002\u001a5u\nqaZ3oKJL7-\u0006\u0003H\u0015b[G\u0003\u0002%L=6\u00042A\u000b\u0001J!\ti\"\nB\u0003 \u000f\t\u0007\u0001\u0005C\u0003M\u000f\u0001\u000fQ*A\u0002hK:\u0004BA\u0014+J/:\u0011qJU\u0007\u0002!*\t\u0011+A\u0005tQ\u0006\u0004X\r\\3tg&\u00111\u000bU\u0001\u0010\u0019\u0006\u0014W\r\u001c7fI\u001e+g.\u001a:jG&\u0011QK\u0016\u0002\u0004\u0003VD(BA*Q!\ti\u0002\fB\u0003Z\u000f\t\u0007!LA\u0001M#\t\t3\f\u0005\u0002P9&\u0011Q\f\u0015\u0002\u0006\u00112K7\u000f\u001e\u0005\u0006?\u001e\u0001\u001d\u0001Y\u0001\tI\u00164\u0017-\u001e7ugB!\u0011\r[%k\u001d\t\u0011WM\u0004\u0002PG&\u0011A\rU\u0001\b\t\u00164\u0017-\u001e7u\u0013\t1w-A\u0005Bg>\u0003H/[8og*\u0011A\rU\u0005\u0003+&T!AZ4\u0011\u0005uYG!\u00027\b\u0005\u0004Q&!\u0001#\t\u000b9<\u00019A8\u0002\u0015UtG-\u001a:ms&tw\rE\u0002PaJL!!\u001d)\u0003\t1\u000b\'0\u001f\t\u0005UM<&.\u0003\u0002u\u0013\t1\u0002\nT5tiB\u0013x\u000eZ;di\u0016s7m\u001c3f\u0015N|g\u000e
  #10 = Utf8               shapeless/Default$AsOptions
  #11 = Class              #10            // shapeless/Default$AsOptions
  #12 = Utf8               shapeless/Default
  #13 = Class              #12            // shapeless/Default
  #14 = Utf8               AsOptions
  #15 = Utf8               generic
  #16 = Utf8               (Lshapeless/LabelledGeneric;Lshapeless/Default$AsOptions;Lshapeless/Lazy;)Largonaut/derive/ProductEncodeJson;
  #17 = Utf8               <P:Ljava/lang/Object;L::Lshapeless/HList;D::Lshapeless/HList;>(Lshapeless/LabelledGeneric<TP;>;Lshapeless/Default$AsOptions<TP;>;Lshapeless/Lazy<Largonaut/derive/HListProductEncodeJson<TL;TD;>;>;)Largonaut/derive/ProductEncodeJson<TP;>;
  #18 = Utf8               gen
  #19 = Utf8               defaults
  #20 = Utf8               underlying
  #21 = Utf8               argonaut/derive/ProductEncodeJson$
  #22 = Class              #21            // argonaut/derive/ProductEncodeJson$
  #23 = Utf8               MODULE$
  #24 = Utf8               Largonaut/derive/ProductEncodeJson$;
  #25 = NameAndType        #23:#24        // MODULE$:Largonaut/derive/ProductEncodeJson$;
  #26 = Fieldref           #22.#25        // argonaut/derive/ProductEncodeJson$.MODULE$:Largonaut/derive/ProductEncodeJson$;
  #27 = NameAndType        #15:#16        // generic:(Lshapeless/LabelledGeneric;Lshapeless/Default$AsOptions;Lshapeless/Lazy;)Largonaut/derive/ProductEncodeJson;
  #28 = Methodref          #22.#27        // argonaut/derive/ProductEncodeJson$.generic:(Lshapeless/LabelledGeneric;Lshapeless/Default$AsOptions;Lshapeless/Lazy;)Largonaut/derive/ProductEncodeJson;
  #29 = Utf8               instance
  #30 = Utf8               (Lscala/Function1;)Largonaut/derive/ProductEncodeJson;
  #31 = Utf8               <P:Ljava/lang/Object;>(Lscala/Function1<Largonaut/derive/JsonProductCodec;Largonaut/EncodeJson<TP;>;>;)Largonaut/derive/ProductEncodeJson<TP;>;
  #32 = Utf8               f
  #33 = NameAndType        #29:#30        // instance:(Lscala/Function1;)Largonaut/derive/ProductEncodeJson;
  #34 = Methodref          #22.#33        // argonaut/derive/ProductEncodeJson$.instance:(Lscala/Function1;)Largonaut/derive/ProductEncodeJson;
  #35 = Utf8               apply
  #36 = Utf8               (Largonaut/derive/JsonProductCodec;)Largonaut/EncodeJson;
  #37 = Utf8               (Largonaut/derive/JsonProductCodec;)Largonaut/EncodeJson<TP;>;
  #38 = Utf8               productCodec
  #39 = Utf8               Code
  #40 = Utf8               Signature
  #41 = Utf8               MethodParameters
  #42 = Utf8               InnerClasses
  #43 = Utf8               SourceFile
  #44 = Utf8               RuntimeVisibleAnnotations
  #45 = Utf8               ScalaInlineInfo
  #46 = Utf8               ScalaSig
{
  public static <P extends java.lang.Object, L extends shapeless.HList, D extends shapeless.HList> argonaut.derive.ProductEncodeJson<P> generic(shapeless.LabelledGeneric<P>, shapeless.Default$AsOptions<P>, shapeless.Lazy<argonaut.derive.HListProductEncodeJson<L, D>>);
    descriptor: (Lshapeless/LabelledGeneric;Lshapeless/Default$AsOptions;Lshapeless/Lazy;)Largonaut/derive/ProductEncodeJson;
    flags: (0x0009) ACC_PUBLIC, ACC_STATIC
    Code:
      stack=4, locals=3, args_size=3
         0: getstatic     #26                 // Field argonaut/derive/ProductEncodeJson$.MODULE$:Largonaut/derive/ProductEncodeJson$;
         3: aload_0
         4: aload_1
         5: aload_2
         6: invokevirtual #28                 // Method argonaut/derive/ProductEncodeJson$.generic:(Lshapeless/LabelledGeneric;Lshapeless/Default$AsOptions;Lshapeless/Lazy;)Largonaut/derive/ProductEncodeJson;
         9: areturn
    Signature: #17                          // <P:Ljava/lang/Object;L::Lshapeless/HList;D::Lshapeless/HList;>(Lshapeless/LabelledGeneric<TP;>;Lshapeless/Default$AsOptions<TP;>;Lshapeless/Lazy<Largonaut/derive/HListProductEncodeJson<TL;TD;>;>;)Largonaut/derive/ProductEncodeJson<TP;>;
    MethodParameters:
      Name                           Flags
      gen                            final
      defaults                       final
      underlying                     final

  public static <P extends java.lang.Object> argonaut.derive.ProductEncodeJson<P> instance(scala.Function1<argonaut.derive.JsonProductCodec, argonaut.EncodeJson<P>>);
    descriptor: (Lscala/Function1;)Largonaut/derive/ProductEncodeJson;
    flags: (0x0009) ACC_PUBLIC, ACC_STATIC
    Code:
      stack=2, locals=1, args_size=1
         0: getstatic     #26                 // Field argonaut/derive/ProductEncodeJson$.MODULE$:Largonaut/derive/ProductEncodeJson$;
         3: aload_0
         4: invokevirtual #34                 // Method argonaut/derive/ProductEncodeJson$.instance:(Lscala/Function1;)Largonaut/derive/ProductEncodeJson;
         7: areturn
    Signature: #31                          // <P:Ljava/lang/Object;>(Lscala/Function1<Largonaut/derive/JsonProductCodec;Largonaut/EncodeJson<TP;>;>;)Largonaut/derive/ProductEncodeJson<TP;>;
    MethodParameters:
      Name                           Flags
      f                              final

  public abstract argonaut.EncodeJson<P> apply(argonaut.derive.JsonProductCodec);
    descriptor: (Largonaut/derive/JsonProductCodec;)Largonaut/EncodeJson;
    flags: (0x0401) ACC_PUBLIC, ACC_ABSTRACT
    Signature: #37                          // (Largonaut/derive/JsonProductCodec;)Largonaut/EncodeJson<TP;>;
    MethodParameters:
      Name                           Flags
      productCodec                   final
}
InnerClasses:
  public static #14= #11 of #13;          // AsOptions=class shapeless/Default$AsOptions of class shapeless/Default
Signature: #3                           // <P:Ljava/lang/Object;>Ljava/lang/Object;
SourceFile: "MkEncodeJson.scala"
RuntimeVisibleAnnotations:
  0: #7(#8=s#9)
    scala.reflect.ScalaSignature(
      bytes="\u0006\u0005U4q\u0001C\u0005\u0011\u0002G\u0005a\u0002C\u0003\u0017\u0001\u0019\u0005qcB\u0003.\u0013!\u0005aFB\u0003\t\u0013!\u0005q\u0006C\u00031\u0007\u0011\u0005\u0011\u0007C\u0003\u0017\u0007\u0011\u0005!\u0007C\u0003:\u0007\u0011\u0005!\bC\u0003F\u0007\u0011\raIA\tQe>$Wo\u0019;F]\u000e|G-\u001a&t_:T!AC\u0006\u0002\r\u0011,\'/\u001b<f\u0015\u0005a\u0011\u0001C1sO>t\u0017-\u001e;\u0004\u0001U\u0011qBH\n\u0003\u0001A\u0001\"!\u0005\u000b\u000e\u0003IQ\u0011aE\u0001\u0006g\u000e\fG.Y\u0005\u0003+I\u0011a!\u00118z%\u00164\u0017!B1qa2LHC\u0001\r(!\rI\"\u0004H\u0007\u0002\u0017%\u00111d\u0003\u0002\u000b\u000b:\u001cw\u000eZ3Kg>t\u0007CA\u000f\u001f\u0019\u0001!Qa\b\u0001C\u0002\u0001\u0012\u0011\u0001U\t\u0003C\u0011\u0002\"!\u0005\u0012\n\u0005\r\u0012\"a\u0002(pi\"Lgn\u001a\t\u0003#\u0015J!A\n\n\u0003\u0007\u0005s\u0017\u0010C\u0003)\u0003\u0001\u0007\u0011&\u0001\u0007qe>$Wo\u0019;D_\u0012,7\r\u0005\u0002+W5\t\u0011\"\u0003\u0002-\u0013\t\u0001\"j]8o!J|G-^2u\u0007>$WmY\u0001\u0012!J|G-^2u\u000b:\u001cw\u000eZ3Kg>t\u0007C\u0001\u0016\u0004\'\t\u0019\u0001#\u0001\u0004=S:LGO\u0010\u000b\u0002]U\u00111G\u000e\u000b\u0003i]\u00022A\u000b\u00016!\tib\u0007B\u0003 \u000b\t\u0007\u0001\u0005C\u00039\u000b\u0001\u000fA\'\u0001\u0006f]\u000e|G-\u001a&t_:\f\u0001\"\u001b8ti\u0006t7-Z\u000b\u0003wy\"\"\u0001P \u0011\u0007)\u0002Q\b\u0005\u0002\u001e}\u0011)qD\u0002b\u0001A!)\u0001I\u0002a\u0001\u0003\u0006\ta\r\u0005\u0003\u0012\u0005&\"\u0015BA\"\u0013\u0005%1UO\\2uS>t\u0017\u0007E\u0002\u001a5u\nqaZ3oKJL7-\u0006\u0003H\u0015b[G\u0003\u0002%L=6\u00042A\u000b\u0001J!\ti\"\nB\u0003 \u000f\t\u0007\u0001\u0005C\u0003M\u000f\u0001\u000fQ*A\u0002hK:\u0004BA\u0014+J/:\u0011qJU\u0007\u0002!*\t\u0011+A\u0005tQ\u0006\u0004X\r\\3tg&\u00111\u000bU\u0001\u0010\u0019\u0006\u0014W\r\u001c7fI\u001e+g.\u001a:jG&\u0011QK\u0016\u0002\u0004\u0003VD(BA*Q!\ti\u0002\fB\u0003Z\u000f\t\u0007!LA\u0001M#\t\t3\f\u0005\u0002P9&\u0011Q\f\u0015\u0002\u0006\u00112K7\u000f\u001e\u0005\u0006?\u001e\u0001\u001d\u0001Y\u0001\tI\u00164\u0017-\u001e7ugB!\u0011\r[%k\u001d\t\u0011WM\u0004\u0002PG&\u0011A\rU\u0001\b\t\u00164\u0017-\u001e7u\u0013\t1w-A\u0005Bg>\u0003H/[8og*\u0011A\rU\u0005\u0003+&T!AZ4\u0011\u0005uYG!\u00027\b\u0005\u0004Q&!\u0001#\t\u000b9<\u00019A8\u0002\u0015UtG-\u001a:ms&tw\rE\u0002PaJL!!\u001d)\u0003\t1\u000b\'0\u001f\t\u0005UM<&.\u0003\u0002u\u0013\t1\u0002\nT5tiB\u0013x\u000eZ;di\u0016s7m\u001c3f\u0015N|g\u000e"
    )
  ScalaInlineInfo: length = 0x9 (unknown attribute)
   01 00 00 01 00 23 00 24 00
  ScalaSig: length = 0x3 (unknown attribute)
   05 02 00
