Classfile /Users/mw/Projects/slang-braindump/.jar/jar8/assemble/slang-braindump/assemble/content/argonaut/derive/SumEncodeJson$.class
  Last modified May 29, 2022; size 4220 bytes
  SHA-256 checksum 86ba37e54ead4b0cdd9ec633de8d8f8006c0f4a29ac79c6292f7f9153b6d490f
  Compiled from "MkEncodeJson.scala"
public final class argonaut.derive.SumEncodeJson$
  minor version: 0
  major version: 52
  flags: (0x0031) ACC_PUBLIC, ACC_FINAL, ACC_SUPER
  this_class: #2                          // argonaut/derive/SumEncodeJson$
  super_class: #4                         // java/lang/Object
  interfaces: 0, fields: 1, methods: 10, attributes: 5
Constant pool:
    #1 = Utf8               argonaut/derive/SumEncodeJson$
    #2 = Class              #1            // argonaut/derive/SumEncodeJson$
    #3 = Utf8               java/lang/Object
    #4 = Class              #3            // java/lang/Object
    #5 = Utf8               MkEncodeJson.scala
    #6 = Utf8               argonaut/derive/SumEncodeJson$$anon$5
    #7 = Class              #6            // argonaut/derive/SumEncodeJson$$anon$5
    #8 = Utf8               java/lang/invoke/MethodHandles$Lookup
    #9 = Class              #8            // java/lang/invoke/MethodHandles$Lookup
   #10 = Utf8               java/lang/invoke/MethodHandles
   #11 = Class              #10           // java/lang/invoke/MethodHandles
   #12 = Utf8               Lookup
   #13 = Utf8               MODULE$
   #14 = Utf8               Largonaut/derive/SumEncodeJson$;
   #15 = Utf8               <clinit>
   #16 = Utf8               ()V
   #17 = Utf8               <init>
   #18 = NameAndType        #17:#16       // "<init>":()V
   #19 = Methodref          #2.#18        // argonaut/derive/SumEncodeJson$."<init>":()V
   #20 = NameAndType        #13:#14       // MODULE$:Largonaut/derive/SumEncodeJson$;
   #21 = Fieldref           #2.#20        // argonaut/derive/SumEncodeJson$.MODULE$:Largonaut/derive/SumEncodeJson$;
   #22 = Utf8               apply
   #23 = Utf8               (Largonaut/derive/SumEncodeJson;)Largonaut/derive/SumEncodeJson;
   #24 = Utf8               <S:Ljava/lang/Object;>(Largonaut/derive/SumEncodeJson<TS;>;)Largonaut/derive/SumEncodeJson<TS;>;
   #25 = Utf8               encodeJson
   #26 = Utf8               this
   #27 = Utf8               Largonaut/derive/SumEncodeJson;
   #28 = Utf8               instance
   #29 = Utf8               (Lscala/Function1;)Largonaut/derive/SumEncodeJson;
   #30 = Utf8               <S:Ljava/lang/Object;>(Lscala/Function1<Largonaut/derive/JsonSumCodec;Largonaut/EncodeJson<TS;>;>;)Largonaut/derive/SumEncodeJson<TS;>;
   #31 = Utf8               f
   #32 = Utf8               (Lscala/Function1;)V
   #33 = NameAndType        #17:#32       // "<init>":(Lscala/Function1;)V
   #34 = Methodref          #7.#33        // argonaut/derive/SumEncodeJson$$anon$5."<init>":(Lscala/Function1;)V
   #35 = Utf8               Lscala/Function1;
   #36 = Utf8               union
   #37 = Utf8               (Largonaut/derive/CoproductSumEncodeJson;)Largonaut/derive/SumEncodeJson;
   #38 = Utf8               <U::Lshapeless/Coproduct;>(Largonaut/derive/CoproductSumEncodeJson<TU;>;)Largonaut/derive/SumEncodeJson<TU;>;
   #39 = Utf8               underlying
   #40 = Utf8               (Ljava/lang/Object;)Ljava/lang/Object;
   #41 = MethodType         #40           //  (Ljava/lang/Object;)Ljava/lang/Object;
   #42 = Utf8               $anonfun$union$1
   #43 = Utf8               (Largonaut/derive/CoproductSumEncodeJson;Largonaut/derive/JsonSumCodec;)Largonaut/EncodeJson;
   #44 = NameAndType        #42:#43       // $anonfun$union$1:(Largonaut/derive/CoproductSumEncodeJson;Largonaut/derive/JsonSumCodec;)Largonaut/EncodeJson;
   #45 = Methodref          #2.#44        // argonaut/derive/SumEncodeJson$.$anonfun$union$1:(Largonaut/derive/CoproductSumEncodeJson;Largonaut/derive/JsonSumCodec;)Largonaut/EncodeJson;
   #46 = MethodHandle       6:#45         // REF_invokeStatic argonaut/derive/SumEncodeJson$.$anonfun$union$1:(Largonaut/derive/CoproductSumEncodeJson;Largonaut/derive/JsonSumCodec;)Largonaut/EncodeJson;
   #47 = Utf8               (Largonaut/derive/JsonSumCodec;)Largonaut/EncodeJson;
   #48 = MethodType         #47           //  (Largonaut/derive/JsonSumCodec;)Largonaut/EncodeJson;
   #49 = Integer            5
   #50 = Integer            1
   #51 = Utf8               java/lang/invoke/LambdaMetafactory
   #52 = Class              #51           // java/lang/invoke/LambdaMetafactory
   #53 = Utf8               altMetafactory
   #54 = Utf8               (Ljava/lang/invoke/MethodHandles$Lookup;Ljava/lang/String;Ljava/lang/invoke/MethodType;[Ljava/lang/Object;)Ljava/lang/invoke/CallSite;
   #55 = NameAndType        #53:#54       // altMetafactory:(Ljava/lang/invoke/MethodHandles$Lookup;Ljava/lang/String;Ljava/lang/invoke/MethodType;[Ljava/lang/Object;)Ljava/lang/invoke/CallSite;
   #56 = Methodref          #52.#55       // java/lang/invoke/LambdaMetafactory.altMetafactory:(Ljava/lang/invoke/MethodHandles$Lookup;Ljava/lang/String;Ljava/lang/invoke/MethodType;[Ljava/lang/Object;)Ljava/lang/invoke/CallSite;
   #57 = MethodHandle       6:#56         // REF_invokeStatic java/lang/invoke/LambdaMetafactory.altMetafactory:(Ljava/lang/invoke/MethodHandles$Lookup;Ljava/lang/String;Ljava/lang/invoke/MethodType;[Ljava/lang/Object;)Ljava/lang/invoke/CallSite;
   #58 = Utf8               (Largonaut/derive/CoproductSumEncodeJson;)Lscala/Function1;
   #59 = NameAndType        #22:#58       // apply:(Largonaut/derive/CoproductSumEncodeJson;)Lscala/Function1;
   #60 = InvokeDynamic      #0:#59        // #0:apply:(Largonaut/derive/CoproductSumEncodeJson;)Lscala/Function1;
   #61 = NameAndType        #28:#29       // instance:(Lscala/Function1;)Largonaut/derive/SumEncodeJson;
   #62 = Methodref          #2.#61        // argonaut/derive/SumEncodeJson$.instance:(Lscala/Function1;)Largonaut/derive/SumEncodeJson;
   #63 = Utf8               Largonaut/derive/CoproductSumEncodeJson;
   #64 = Utf8               generic
   #65 = Utf8               (Lshapeless/LabelledGeneric;Lshapeless/Strict;)Largonaut/derive/SumEncodeJson;
   #66 = Utf8               <S:Ljava/lang/Object;C::Lshapeless/Coproduct;>(Lshapeless/LabelledGeneric<TS;>;Lshapeless/Strict<Largonaut/derive/CoproductSumEncodeJson<TC;>;>;)Largonaut/derive/SumEncodeJson<TS;>;
   #67 = Utf8               gen
   #68 = Utf8               $anonfun$generic$3
   #69 = Utf8               (Lshapeless/Strict;Lshapeless/LabelledGeneric;Largonaut/derive/JsonSumCodec;)Largonaut/EncodeJson;
   #70 = NameAndType        #68:#69       // $anonfun$generic$3:(Lshapeless/Strict;Lshapeless/LabelledGeneric;Largonaut/derive/JsonSumCodec;)Largonaut/EncodeJson;
   #71 = Methodref          #2.#70        // argonaut/derive/SumEncodeJson$.$anonfun$generic$3:(Lshapeless/Strict;Lshapeless/LabelledGeneric;Largonaut/derive/JsonSumCodec;)Largonaut/EncodeJson;
   #72 = MethodHandle       6:#71         // REF_invokeStatic argonaut/derive/SumEncodeJson$.$anonfun$generic$3:(Lshapeless/Strict;Lshapeless/LabelledGeneric;Largonaut/derive/JsonSumCodec;)Largonaut/EncodeJson;
   #73 = Utf8               (Lshapeless/Strict;Lshapeless/LabelledGeneric;)Lscala/Function1;
   #74 = NameAndType        #22:#73       // apply:(Lshapeless/Strict;Lshapeless/LabelledGeneric;)Lscala/Function1;
   #75 = InvokeDynamic      #1:#74        // #1:apply:(Lshapeless/Strict;Lshapeless/LabelledGeneric;)Lscala/Function1;
   #76 = Utf8               Lshapeless/LabelledGeneric;
   #77 = Utf8               Lshapeless/Strict;
   #78 = Utf8               underlying$4
   #79 = Utf8               sumCodec
   #80 = Utf8               argonaut/derive/CoproductSumEncodeJson
   #81 = Class              #80           // argonaut/derive/CoproductSumEncodeJson
   #82 = NameAndType        #22:#47       // apply:(Largonaut/derive/JsonSumCodec;)Largonaut/EncodeJson;
   #83 = InterfaceMethodref #81.#82       // argonaut/derive/CoproductSumEncodeJson.apply:(Largonaut/derive/JsonSumCodec;)Largonaut/EncodeJson;
   #84 = Utf8               Largonaut/derive/JsonSumCodec;
   #85 = Utf8               $anonfun$generic$4
   #86 = Utf8               (Lshapeless/LabelledGeneric;Ljava/lang/Object;)Lshapeless/Coproduct;
   #87 = Utf8               gen$2
   #88 = Utf8               t
   #89 = Utf8               shapeless/LabelledGeneric
   #90 = Class              #89           // shapeless/LabelledGeneric
   #91 = Utf8               to
   #92 = NameAndType        #91:#40       // to:(Ljava/lang/Object;)Ljava/lang/Object;
   #93 = InterfaceMethodref #90.#92       // shapeless/LabelledGeneric.to:(Ljava/lang/Object;)Ljava/lang/Object;
   #94 = Utf8               shapeless/Coproduct
   #95 = Class              #94           // shapeless/Coproduct
   #96 = Utf8               Ljava/lang/Object;
   #97 = Utf8               underlying$5
   #98 = Utf8               shapeless/Strict
   #99 = Class              #98           // shapeless/Strict
  #100 = Utf8               value
  #101 = Utf8               ()Ljava/lang/Object;
  #102 = NameAndType        #100:#101     // value:()Ljava/lang/Object;
  #103 = InterfaceMethodref #99.#102      // shapeless/Strict.value:()Ljava/lang/Object;
  #104 = NameAndType        #85:#86       // $anonfun$generic$4:(Lshapeless/LabelledGeneric;Ljava/lang/Object;)Lshapeless/Coproduct;
  #105 = Methodref          #2.#104       // argonaut/derive/SumEncodeJson$.$anonfun$generic$4:(Lshapeless/LabelledGeneric;Ljava/lang/Object;)Lshapeless/Coproduct;
  #106 = MethodHandle       6:#105        // REF_invokeStatic argonaut/derive/SumEncodeJson$.$anonfun$generic$4:(Lshapeless/LabelledGeneric;Ljava/lang/Object;)Lshapeless/Coproduct;
  #107 = Utf8               (Ljava/lang/Object;)Lshapeless/Coproduct;
  #108 = MethodType         #107          //  (Ljava/lang/Object;)Lshapeless/Coproduct;
  #109 = Utf8               (Lshapeless/LabelledGeneric;)Lscala/Function1;
  #110 = NameAndType        #22:#109      // apply:(Lshapeless/LabelledGeneric;)Lscala/Function1;
  #111 = InvokeDynamic      #2:#110       // #2:apply:(Lshapeless/LabelledGeneric;)Lscala/Function1;
  #112 = Utf8               argonaut/EncodeJson
  #113 = Class              #112          // argonaut/EncodeJson
  #114 = Utf8               contramap
  #115 = Utf8               (Lscala/Function1;)Largonaut/EncodeJson;
  #116 = NameAndType        #114:#115     // contramap:(Lscala/Function1;)Largonaut/EncodeJson;
  #117 = InterfaceMethodref #113.#116     // argonaut/EncodeJson.contramap:(Lscala/Function1;)Largonaut/EncodeJson;
  #118 = Methodref          #4.#18        // java/lang/Object."<init>":()V
  #119 = Utf8               $deserializeLambda$
  #120 = Utf8               (Ljava/lang/invoke/SerializedLambda;)Ljava/lang/Object;
  #121 = Utf8               scala/runtime/LambdaDeserialize
  #122 = Class              #121          // scala/runtime/LambdaDeserialize
  #123 = Utf8               bootstrap
  #124 = Utf8               (Ljava/lang/invoke/MethodHandles$Lookup;Ljava/lang/String;Ljava/lang/invoke/MethodType;[Ljava/lang/invoke/MethodHandle;)Ljava/lang/invoke/CallSite;
  #125 = NameAndType        #123:#124     // bootstrap:(Ljava/lang/invoke/MethodHandles$Lookup;Ljava/lang/String;Ljava/lang/invoke/MethodType;[Ljava/lang/invoke/MethodHandle;)Ljava/lang/invoke/CallSite;
  #126 = Methodref          #122.#125     // scala/runtime/LambdaDeserialize.bootstrap:(Ljava/lang/invoke/MethodHandles$Lookup;Ljava/lang/String;Ljava/lang/invoke/MethodType;[Ljava/lang/invoke/MethodHandle;)Ljava/lang/invoke/CallSite;
  #127 = MethodHandle       6:#126        // REF_invokeStatic scala/runtime/LambdaDeserialize.bootstrap:(Ljava/lang/invoke/MethodHandles$Lookup;Ljava/lang/String;Ljava/lang/invoke/MethodType;[Ljava/lang/invoke/MethodHandle;)Ljava/lang/invoke/CallSite;
  #128 = Utf8               lambdaDeserialize
  #129 = NameAndType        #128:#120     // lambdaDeserialize:(Ljava/lang/invoke/SerializedLambda;)Ljava/lang/Object;
  #130 = InvokeDynamic      #3:#129       // #3:lambdaDeserialize:(Ljava/lang/invoke/SerializedLambda;)Ljava/lang/Object;
  #131 = Utf8               Code
  #132 = Utf8               LineNumberTable
  #133 = Utf8               LocalVariableTable
  #134 = Utf8               Signature
  #135 = Utf8               MethodParameters
  #136 = Utf8               InnerClasses
  #137 = Utf8               SourceFile
  #138 = Utf8               BootstrapMethods
  #139 = Utf8               ScalaInlineInfo
  #140 = Utf8               Scala
{
  public static final argonaut.derive.SumEncodeJson$ MODULE$;
    descriptor: Largonaut/derive/SumEncodeJson$;
    flags: (0x0019) ACC_PUBLIC, ACC_STATIC, ACC_FINAL

  public static {};
    descriptor: ()V
    flags: (0x0009) ACC_PUBLIC, ACC_STATIC
    Code:
      stack=2, locals=0, args_size=0
         0: new           #2                  // class argonaut/derive/SumEncodeJson$
         3: dup
         4: invokespecial #19                 // Method "<init>":()V
         7: putstatic     #21                 // Field MODULE$:Largonaut/derive/SumEncodeJson$;
        10: return
      LineNumberTable:
        line 113: 0

  public <S extends java.lang.Object> argonaut.derive.SumEncodeJson<S> apply(argonaut.derive.SumEncodeJson<S>);
    descriptor: (Largonaut/derive/SumEncodeJson;)Largonaut/derive/SumEncodeJson;
    flags: (0x0001) ACC_PUBLIC
    Code:
      stack=1, locals=2, args_size=2
         0: aload_1
         1: areturn
      LineNumberTable:
        line 114: 0
      LocalVariableTable:
        Start  Length  Slot  Name   Signature
            0       2     0  this   Largonaut/derive/SumEncodeJson$;
            0       2     1 encodeJson   Largonaut/derive/SumEncodeJson;
    Signature: #24                          // <S:Ljava/lang/Object;>(Largonaut/derive/SumEncodeJson<TS;>;)Largonaut/derive/SumEncodeJson<TS;>;
    MethodParameters:
      Name                           Flags
      encodeJson                     final

  public <S extends java.lang.Object> argonaut.derive.SumEncodeJson<S> instance(scala.Function1<argonaut.derive.JsonSumCodec, argonaut.EncodeJson<S>>);
    descriptor: (Lscala/Function1;)Largonaut/derive/SumEncodeJson;
    flags: (0x0001) ACC_PUBLIC
    Code:
      stack=3, locals=2, args_size=2
         0: new           #7                  // class argonaut/derive/SumEncodeJson$$anon$5
         3: dup
         4: aload_1
         5: invokespecial #34                 // Method argonaut/derive/SumEncodeJson$$anon$5."<init>":(Lscala/Function1;)V
         8: areturn
      LineNumberTable:
        line 117: 0
      LocalVariableTable:
        Start  Length  Slot  Name   Signature
            0       9     0  this   Largonaut/derive/SumEncodeJson$;
            0       9     1     f   Lscala/Function1;
    Signature: #30                          // <S:Ljava/lang/Object;>(Lscala/Function1<Largonaut/derive/JsonSumCodec;Largonaut/EncodeJson<TS;>;>;)Largonaut/derive/SumEncodeJson<TS;>;
    MethodParameters:
      Name                           Flags
      f                              final

  public <U extends shapeless.Coproduct> argonaut.derive.SumEncodeJson<U> union(argonaut.derive.CoproductSumEncodeJson<U>);
    descriptor: (Largonaut/derive/CoproductSumEncodeJson;)Largonaut/derive/SumEncodeJson;
    flags: (0x0001) ACC_PUBLIC
    Code:
      stack=2, locals=2, args_size=2
         0: aload_0
         1: aload_1
         2: invokedynamic #60,  0             // InvokeDynamic #0:apply:(Largonaut/derive/CoproductSumEncodeJson;)Lscala/Function1;
         7: invokevirtual #62                 // Method instance:(Lscala/Function1;)Largonaut/derive/SumEncodeJson;
        10: areturn
      LineNumberTable:
        line 126: 0
      LocalVariableTable:
        Start  Length  Slot  Name   Signature
            0      11     0  this   Largonaut/derive/SumEncodeJson$;
            0      11     1 underlying   Largonaut/derive/CoproductSumEncodeJson;
    Signature: #38                          // <U::Lshapeless/Coproduct;>(Largonaut/derive/CoproductSumEncodeJson<TU;>;)Largonaut/derive/SumEncodeJson<TU;>;
    MethodParameters:
      Name                           Flags
      underlying                     final

  public <S extends java.lang.Object, C extends shapeless.Coproduct> argonaut.derive.SumEncodeJson<S> generic(shapeless.LabelledGeneric<S>, shapeless.Strict<argonaut.derive.CoproductSumEncodeJson<C>>);
    descriptor: (Lshapeless/LabelledGeneric;Lshapeless/Strict;)Largonaut/derive/SumEncodeJson;
    flags: (0x0001) ACC_PUBLIC
    Code:
      stack=3, locals=3, args_size=3
         0: aload_0
         1: aload_2
         2: aload_1
         3: invokedynamic #75,  0             // InvokeDynamic #1:apply:(Lshapeless/Strict;Lshapeless/LabelledGeneric;)Lscala/Function1;
         8: invokevirtual #62                 // Method instance:(Lscala/Function1;)Largonaut/derive/SumEncodeJson;
        11: areturn
      LineNumberTable:
        line 135: 0
      LocalVariableTable:
        Start  Length  Slot  Name   Signature
            0      12     0  this   Largonaut/derive/SumEncodeJson$;
            0      12     1   gen   Lshapeless/LabelledGeneric;
            0      12     2 underlying   Lshapeless/Strict;
    Signature: #66                          // <S:Ljava/lang/Object;C::Lshapeless/Coproduct;>(Lshapeless/LabelledGeneric<TS;>;Lshapeless/Strict<Largonaut/derive/CoproductSumEncodeJson<TC;>;>;)Largonaut/derive/SumEncodeJson<TS;>;
    MethodParameters:
      Name                           Flags
      gen                            final
      underlying                     final

  public static final argonaut.EncodeJson $anonfun$union$1(argonaut.derive.CoproductSumEncodeJson, argonaut.derive.JsonSumCodec);
    descriptor: (Largonaut/derive/CoproductSumEncodeJson;Largonaut/derive/JsonSumCodec;)Largonaut/EncodeJson;
    flags: (0x1019) ACC_PUBLIC, ACC_STATIC, ACC_FINAL, ACC_SYNTHETIC
    Code:
      stack=2, locals=2, args_size=2
         0: aload_0
         1: aload_1
         2: invokeinterface #83,  2           // InterfaceMethod argonaut/derive/CoproductSumEncodeJson.apply:(Largonaut/derive/JsonSumCodec;)Largonaut/EncodeJson;
         7: areturn
      LineNumberTable:
        line 127: 0
      LocalVariableTable:
        Start  Length  Slot  Name   Signature
            0       8     0 underlying$4   Largonaut/derive/CoproductSumEncodeJson;
            0       8     1 sumCodec   Largonaut/derive/JsonSumCodec;
    MethodParameters:
      Name                           Flags
      underlying$4                   final
      sumCodec                       final

  public static final shapeless.Coproduct $anonfun$generic$4(shapeless.LabelledGeneric, java.lang.Object);
    descriptor: (Lshapeless/LabelledGeneric;Ljava/lang/Object;)Lshapeless/Coproduct;
    flags: (0x1019) ACC_PUBLIC, ACC_STATIC, ACC_FINAL, ACC_SYNTHETIC
    Code:
      stack=2, locals=2, args_size=2
         0: aload_0
         1: aload_1
         2: invokeinterface #93,  2           // InterfaceMethod shapeless/LabelledGeneric.to:(Ljava/lang/Object;)Ljava/lang/Object;
         7: checkcast     #95                 // class shapeless/Coproduct
        10: areturn
      LineNumberTable:
        line 137: 0
      LocalVariableTable:
        Start  Length  Slot  Name   Signature
            0      11     0 gen$2   Lshapeless/LabelledGeneric;
            0      11     1     t   Ljava/lang/Object;
    MethodParameters:
      Name                           Flags
      gen$2                          final
      t                              final

  public static final argonaut.EncodeJson $anonfun$generic$3(shapeless.Strict, shapeless.LabelledGeneric, argonaut.derive.JsonSumCodec);
    descriptor: (Lshapeless/Strict;Lshapeless/LabelledGeneric;Largonaut/derive/JsonSumCodec;)Largonaut/EncodeJson;
    flags: (0x1019) ACC_PUBLIC, ACC_STATIC, ACC_FINAL, ACC_SYNTHETIC
    Code:
      stack=2, locals=3, args_size=3
         0: aload_0
         1: invokeinterface #103,  1          // InterfaceMethod shapeless/Strict.value:()Ljava/lang/Object;
         6: checkcast     #81                 // class argonaut/derive/CoproductSumEncodeJson
         9: aload_2
        10: invokeinterface #83,  2           // InterfaceMethod argonaut/derive/CoproductSumEncodeJson.apply:(Largonaut/derive/JsonSumCodec;)Largonaut/EncodeJson;
        15: aload_1
        16: invokedynamic #111,  0            // InvokeDynamic #2:apply:(Lshapeless/LabelledGeneric;)Lscala/Function1;
        21: invokeinterface #117,  2          // InterfaceMethod argonaut/EncodeJson.contramap:(Lscala/Function1;)Largonaut/EncodeJson;
        26: areturn
      LineNumberTable:
        line 136: 0
        line 137: 15
      LocalVariableTable:
        Start  Length  Slot  Name   Signature
            0      27     0 underlying$5   Lshapeless/Strict;
            0      27     1 gen$2   Lshapeless/LabelledGeneric;
            0      27     2 sumCodec   Largonaut/derive/JsonSumCodec;
    MethodParameters:
      Name                           Flags
      underlying$5                   final
      gen$2                          final
      sumCodec                       final

  private argonaut.derive.SumEncodeJson$();
    descriptor: ()V
    flags: (0x0002) ACC_PRIVATE
    Code:
      stack=1, locals=1, args_size=1
         0: aload_0
         1: invokespecial #118                // Method java/lang/Object."<init>":()V
         4: return
      LineNumberTable:
        line 141: 0
        line 113: 4
      LocalVariableTable:
        Start  Length  Slot  Name   Signature
            0       5     0  this   Largonaut/derive/SumEncodeJson$;

  private static java.lang.Object $deserializeLambda$(java.lang.invoke.SerializedLambda);
    descriptor: (Ljava/lang/invoke/SerializedLambda;)Ljava/lang/Object;
    flags: (0x100a) ACC_PRIVATE, ACC_STATIC, ACC_SYNTHETIC
    Code:
      stack=1, locals=1, args_size=1
         0: aload_0
         1: invokedynamic #130,  0            // InvokeDynamic #3:lambdaDeserialize:(Ljava/lang/invoke/SerializedLambda;)Ljava/lang/Object;
         6: areturn
}
InnerClasses:
  public final #7;                        // class argonaut/derive/SumEncodeJson$$anon$5
  public static final #12= #9 of #11;     // Lookup=class java/lang/invoke/MethodHandles$Lookup of class java/lang/invoke/MethodHandles
SourceFile: "MkEncodeJson.scala"
BootstrapMethods:
  0: #57 REF_invokeStatic java/lang/invoke/LambdaMetafactory.altMetafactory:(Ljava/lang/invoke/MethodHandles$Lookup;Ljava/lang/String;Ljava/lang/invoke/MethodType;[Ljava/lang/Object;)Ljava/lang/invoke/CallSite;
    Method arguments:
      #41 (Ljava/lang/Object;)Ljava/lang/Object;
      #46 REF_invokeStatic argonaut/derive/SumEncodeJson$.$anonfun$union$1:(Largonaut/derive/CoproductSumEncodeJson;Largonaut/derive/JsonSumCodec;)Largonaut/EncodeJson;
      #48 (Largonaut/derive/JsonSumCodec;)Largonaut/EncodeJson;
      #49 5
      #50 1
      #48 (Largonaut/derive/JsonSumCodec;)Largonaut/EncodeJson;
  1: #57 REF_invokeStatic java/lang/invoke/LambdaMetafactory.altMetafactory:(Ljava/lang/invoke/MethodHandles$Lookup;Ljava/lang/String;Ljava/lang/invoke/MethodType;[Ljava/lang/Object;)Ljava/lang/invoke/CallSite;
    Method arguments:
      #41 (Ljava/lang/Object;)Ljava/lang/Object;
      #72 REF_invokeStatic argonaut/derive/SumEncodeJson$.$anonfun$generic$3:(Lshapeless/Strict;Lshapeless/LabelledGeneric;Largonaut/derive/JsonSumCodec;)Largonaut/EncodeJson;
      #48 (Largonaut/derive/JsonSumCodec;)Largonaut/EncodeJson;
      #49 5
      #50 1
      #48 (Largonaut/derive/JsonSumCodec;)Largonaut/EncodeJson;
  2: #57 REF_invokeStatic java/lang/invoke/LambdaMetafactory.altMetafactory:(Ljava/lang/invoke/MethodHandles$Lookup;Ljava/lang/String;Ljava/lang/invoke/MethodType;[Ljava/lang/Object;)Ljava/lang/invoke/CallSite;
    Method arguments:
      #41 (Ljava/lang/Object;)Ljava/lang/Object;
      #106 REF_invokeStatic argonaut/derive/SumEncodeJson$.$anonfun$generic$4:(Lshapeless/LabelledGeneric;Ljava/lang/Object;)Lshapeless/Coproduct;
      #108 (Ljava/lang/Object;)Lshapeless/Coproduct;
      #49 5
      #50 1
      #108 (Ljava/lang/Object;)Lshapeless/Coproduct;
  3: #127 REF_invokeStatic scala/runtime/LambdaDeserialize.bootstrap:(Ljava/lang/invoke/MethodHandles$Lookup;Ljava/lang/String;Ljava/lang/invoke/MethodType;[Ljava/lang/invoke/MethodHandle;)Ljava/lang/invoke/CallSite;
    Method arguments:
      #72 REF_invokeStatic argonaut/derive/SumEncodeJson$.$anonfun$generic$3:(Lshapeless/Strict;Lshapeless/LabelledGeneric;Largonaut/derive/JsonSumCodec;)Largonaut/EncodeJson;
      #106 REF_invokeStatic argonaut/derive/SumEncodeJson$.$anonfun$generic$4:(Lshapeless/LabelledGeneric;Ljava/lang/Object;)Lshapeless/Coproduct;
      #46 REF_invokeStatic argonaut/derive/SumEncodeJson$.$anonfun$union$1:(Largonaut/derive/CoproductSumEncodeJson;Largonaut/derive/JsonSumCodec;)Largonaut/EncodeJson;
  ScalaInlineInfo: length = 0x2C (unknown attribute)
   01 01 00 08 00 44 00 45 01 00 55 00 56 01 00 2A
   00 2B 01 00 11 00 10 01 00 16 00 17 01 00 40 00
   41 01 00 1C 00 1D 01 00 24 00 25 01
  Scala: length = 0x0 (unknown attribute)

