Classfile /Users/mw/Projects/slang-braindump/.jar/jar8/assemble/slang-braindump/assemble/content/scala/collection/immutable/AbstractMap.class
  Last modified May 29, 2022; size 6141 bytes
  SHA-256 checksum 903de1eb702c826c99e229d65e4bd269fadac645cd3923cd94394c7c5576f206
  Compiled from "Map.scala"
public abstract class scala.collection.immutable.AbstractMap<K extends java.lang.Object, V extends java.lang.Object> extends scala.collection.AbstractMap<K, V> implements scala.collection.immutable.Map<K, V>
  minor version: 0
  major version: 52
  flags: (0x0421) ACC_PUBLIC, ACC_SUPER, ACC_ABSTRACT
  this_class: #2                          // scala/collection/immutable/AbstractMap
  super_class: #5                         // scala/collection/AbstractMap
  interfaces: 1, fields: 0, methods: 20, attributes: 5
Constant pool:
    #1 = Utf8               scala/collection/immutable/AbstractMap
    #2 = Class              #1            // scala/collection/immutable/AbstractMap
    #3 = Utf8               <K:Ljava/lang/Object;V:Ljava/lang/Object;>Lscala/collection/AbstractMap<TK;TV;>;Lscala/collection/immutable/Map<TK;TV;>;
    #4 = Utf8               scala/collection/AbstractMap
    #5 = Class              #4            // scala/collection/AbstractMap
    #6 = Utf8               scala/collection/immutable/Map
    #7 = Class              #6            // scala/collection/immutable/Map
    #8 = Utf8               Map.scala
    #9 = Utf8               Lscala/reflect/ScalaSignature;
   #10 = Utf8               bytes
   #11 = Utf8               \u0006\u0005\u00152QAA\u0002\u0002\u0002)AQA\t\u0001\u0005\u0002\r\u00121\"\u00112tiJ\f7\r^\'ba*\u0011A!B\u0001\nS6lW\u000f^1cY\u0016T!AB\u0004\u0002\u0015\r|G\u000e\\3di&|gNC\u0001\t\u0003\u0015\u00198-\u00197b\u0007\u0001)2aC\t\u001d\'\r\u0001AB\b\t\u0005\u001b9y1$D\u0001\u0006\u0013\t\u0011Q\u0001\u0005\u0002\u0011#1\u0001A!\u0002\n\u0001\u0005\u0004\u0019\"!A&\u0012\u0005QA\u0002CA\u000b\u0017\u001b\u00059\u0011BA\f\b\u0005\u001dqu\u000e\u001e5j]\u001e\u0004\"!F\r\n\u0005i9!aA!osB\u0011\u0001\u0003\b\u0003\u0007;\u0001!)\u0019A\n\u0003\u0003Y\u0003Ba\b\u0011\u001075\t1!\u0003\u0002\"\u0007\t\u0019Q*\u00199\u0002\rqJg.\u001b;?)\u0005!\u0003\u0003B\u0010\u0001\u001fm\u0001
   #12 = Utf8               mapFactory
   #13 = Utf8               ()Lscala/collection/MapFactory;
   #14 = Utf8               ()Lscala/collection/MapFactory<Lscala/collection/immutable/Map;>;
   #15 = Utf8               mapFactory$
   #16 = Utf8               (Lscala/collection/immutable/Map;)Lscala/collection/MapFactory;
   #17 = NameAndType        #15:#16       // mapFactory$:(Lscala/collection/immutable/Map;)Lscala/collection/MapFactory;
   #18 = InterfaceMethodref #7.#17        // scala/collection/immutable/Map.mapFactory$:(Lscala/collection/immutable/Map;)Lscala/collection/MapFactory;
   #19 = Utf8               this
   #20 = Utf8               Lscala/collection/immutable/AbstractMap;
   #21 = Utf8               toMap
   #22 = Utf8               (Lscala/$less$colon$less;)Lscala/collection/immutable/Map;
   #23 = Utf8               <K2:Ljava/lang/Object;V2:Ljava/lang/Object;>(Lscala/$less$colon$less<Lscala/Tuple2<TK;TV;>;Lscala/Tuple2<TK2;TV2;>;>;)Lscala/collection/immutable/Map<TK2;TV2;>;
   #24 = Utf8               ev
   #25 = Utf8               toMap$
   #26 = Utf8               (Lscala/collection/immutable/Map;Lscala/$less$colon$less;)Lscala/collection/immutable/Map;
   #27 = NameAndType        #25:#26       // toMap$:(Lscala/collection/immutable/Map;Lscala/$less$colon$less;)Lscala/collection/immutable/Map;
   #28 = InterfaceMethodref #7.#27        // scala/collection/immutable/Map.toMap$:(Lscala/collection/immutable/Map;Lscala/$less$colon$less;)Lscala/collection/immutable/Map;
   #29 = Utf8               Lscala/$less$colon$less;
   #30 = Utf8               withDefault
   #31 = Utf8               (Lscala/Function1;)Lscala/collection/immutable/Map;
   #32 = Utf8               <V1:Ljava/lang/Object;>(Lscala/Function1<TK;TV1;>;)Lscala/collection/immutable/Map<TK;TV1;>;
   #33 = Utf8               d
   #34 = Utf8               withDefault$
   #35 = Utf8               (Lscala/collection/immutable/Map;Lscala/Function1;)Lscala/collection/immutable/Map;
   #36 = NameAndType        #34:#35       // withDefault$:(Lscala/collection/immutable/Map;Lscala/Function1;)Lscala/collection/immutable/Map;
   #37 = InterfaceMethodref #7.#36        // scala/collection/immutable/Map.withDefault$:(Lscala/collection/immutable/Map;Lscala/Function1;)Lscala/collection/immutable/Map;
   #38 = Utf8               Lscala/Function1;
   #39 = Utf8               withDefaultValue
   #40 = Utf8               (Ljava/lang/Object;)Lscala/collection/immutable/Map;
   #41 = Utf8               <V1:Ljava/lang/Object;>(TV1;)Lscala/collection/immutable/Map<TK;TV1;>;
   #42 = Utf8               withDefaultValue$
   #43 = Utf8               (Lscala/collection/immutable/Map;Ljava/lang/Object;)Lscala/collection/immutable/Map;
   #44 = NameAndType        #42:#43       // withDefaultValue$:(Lscala/collection/immutable/Map;Ljava/lang/Object;)Lscala/collection/immutable/Map;
   #45 = InterfaceMethodref #7.#44        // scala/collection/immutable/Map.withDefaultValue$:(Lscala/collection/immutable/Map;Ljava/lang/Object;)Lscala/collection/immutable/Map;
   #46 = Utf8               Ljava/lang/Object;
   #47 = Utf8               $minus
   #48 = Utf8               (Ljava/lang/Object;)Lscala/collection/immutable/MapOps;
   #49 = Utf8               key
   #50 = Utf8               scala/collection/immutable/MapOps
   #51 = Class              #50           // scala/collection/immutable/MapOps
   #52 = Utf8               $minus$
   #53 = Utf8               (Lscala/collection/immutable/MapOps;Ljava/lang/Object;)Lscala/collection/immutable/MapOps;
   #54 = NameAndType        #52:#53       // $minus$:(Lscala/collection/immutable/MapOps;Ljava/lang/Object;)Lscala/collection/immutable/MapOps;
   #55 = InterfaceMethodref #51.#54       // scala/collection/immutable/MapOps.$minus$:(Lscala/collection/immutable/MapOps;Ljava/lang/Object;)Lscala/collection/immutable/MapOps;
   #56 = Utf8               (Ljava/lang/Object;Ljava/lang/Object;Lscala/collection/immutable/Seq;)Lscala/collection/immutable/MapOps;
   #57 = Utf8               key1
   #58 = Utf8               key2
   #59 = Utf8               keys
   #60 = Utf8               (Lscala/collection/immutable/MapOps;Ljava/lang/Object;Ljava/lang/Object;Lscala/collection/immutable/Seq;)Lscala/collection/immutable/MapOps;
   #61 = NameAndType        #52:#60       // $minus$:(Lscala/collection/immutable/MapOps;Ljava/lang/Object;Ljava/lang/Object;Lscala/collection/immutable/Seq;)Lscala/collection/immutable/MapOps;
   #62 = InterfaceMethodref #51.#61       // scala/collection/immutable/MapOps.$minus$:(Lscala/collection/immutable/MapOps;Ljava/lang/Object;Ljava/lang/Object;Lscala/collection/immutable/Seq;)Lscala/collection/immutable/MapOps;
   #63 = Utf8               Lscala/collection/immutable/Seq;
   #64 = Utf8               removedAll
   #65 = Utf8               (Lscala/collection/IterableOnce;)Lscala/collection/immutable/MapOps;
   #66 = Utf8               removedAll$
   #67 = Utf8               (Lscala/collection/immutable/MapOps;Lscala/collection/IterableOnce;)Lscala/collection/immutable/MapOps;
   #68 = NameAndType        #66:#67       // removedAll$:(Lscala/collection/immutable/MapOps;Lscala/collection/IterableOnce;)Lscala/collection/immutable/MapOps;
   #69 = InterfaceMethodref #51.#68       // scala/collection/immutable/MapOps.removedAll$:(Lscala/collection/immutable/MapOps;Lscala/collection/IterableOnce;)Lscala/collection/immutable/MapOps;
   #70 = Utf8               Lscala/collection/IterableOnce;
   #71 = Utf8               $minus$minus
   #72 = Utf8               $minus$minus$
   #73 = NameAndType        #72:#67       // $minus$minus$:(Lscala/collection/immutable/MapOps;Lscala/collection/IterableOnce;)Lscala/collection/immutable/MapOps;
   #74 = InterfaceMethodref #51.#73       // scala/collection/immutable/MapOps.$minus$minus$:(Lscala/collection/immutable/MapOps;Lscala/collection/IterableOnce;)Lscala/collection/immutable/MapOps;
   #75 = Utf8               updatedWith
   #76 = Utf8               (Ljava/lang/Object;Lscala/Function1;)Lscala/collection/immutable/MapOps;
   #77 = Utf8               remappingFunction
   #78 = Utf8               updatedWith$
   #79 = Utf8               (Lscala/collection/immutable/MapOps;Ljava/lang/Object;Lscala/Function1;)Lscala/collection/immutable/MapOps;
   #80 = NameAndType        #78:#79       // updatedWith$:(Lscala/collection/immutable/MapOps;Ljava/lang/Object;Lscala/Function1;)Lscala/collection/immutable/MapOps;
   #81 = InterfaceMethodref #51.#80       // scala/collection/immutable/MapOps.updatedWith$:(Lscala/collection/immutable/MapOps;Ljava/lang/Object;Lscala/Function1;)Lscala/collection/immutable/MapOps;
   #82 = Utf8               $plus
   #83 = Utf8               (Lscala/Tuple2;)Lscala/collection/immutable/MapOps;
   #84 = Utf8               kv
   #85 = Utf8               $plus$
   #86 = Utf8               (Lscala/collection/immutable/MapOps;Lscala/Tuple2;)Lscala/collection/immutable/MapOps;
   #87 = NameAndType        #85:#86       // $plus$:(Lscala/collection/immutable/MapOps;Lscala/Tuple2;)Lscala/collection/immutable/MapOps;
   #88 = InterfaceMethodref #51.#87       // scala/collection/immutable/MapOps.$plus$:(Lscala/collection/immutable/MapOps;Lscala/Tuple2;)Lscala/collection/immutable/MapOps;
   #89 = Utf8               Lscala/Tuple2;
   #90 = Utf8               transform
   #91 = Utf8               (Lscala/Function2;)Lscala/collection/immutable/MapOps;
   #92 = Utf8               f
   #93 = Utf8               transform$
   #94 = Utf8               (Lscala/collection/immutable/MapOps;Lscala/Function2;)Lscala/collection/immutable/MapOps;
   #95 = NameAndType        #93:#94       // transform$:(Lscala/collection/immutable/MapOps;Lscala/Function2;)Lscala/collection/immutable/MapOps;
   #96 = InterfaceMethodref #51.#95       // scala/collection/immutable/MapOps.transform$:(Lscala/collection/immutable/MapOps;Lscala/Function2;)Lscala/collection/immutable/MapOps;
   #97 = Utf8               Lscala/Function2;
   #98 = Utf8               keySet
   #99 = Utf8               ()Lscala/collection/immutable/Set;
  #100 = Utf8               ()Lscala/collection/immutable/Set<TK;>;
  #101 = Utf8               keySet$
  #102 = Utf8               (Lscala/collection/immutable/MapOps;)Lscala/collection/immutable/Set;
  #103 = NameAndType        #101:#102     // keySet$:(Lscala/collection/immutable/MapOps;)Lscala/collection/immutable/Set;
  #104 = InterfaceMethodref #51.#103      // scala/collection/immutable/MapOps.keySet$:(Lscala/collection/immutable/MapOps;)Lscala/collection/immutable/Set;
  #105 = Utf8               iterableFactory
  #106 = Utf8               ()Lscala/collection/IterableFactory;
  #107 = Utf8               ()Lscala/collection/IterableFactory<Lscala/collection/immutable/Iterable;>;
  #108 = Utf8               scala/collection/immutable/Iterable
  #109 = Class              #108          // scala/collection/immutable/Iterable
  #110 = Utf8               iterableFactory$
  #111 = Utf8               (Lscala/collection/immutable/Iterable;)Lscala/collection/IterableFactory;
  #112 = NameAndType        #110:#111     // iterableFactory$:(Lscala/collection/immutable/Iterable;)Lscala/collection/IterableFactory;
  #113 = InterfaceMethodref #109.#112     // scala/collection/immutable/Iterable.iterableFactory$:(Lscala/collection/immutable/Iterable;)Lscala/collection/IterableFactory;
  #114 = Utf8               coll
  #115 = Utf8               ()Lscala/collection/immutable/MapOps;
  #116 = Utf8               ()Lscala/collection/Iterable;
  #117 = NameAndType        #114:#116     // coll:()Lscala/collection/Iterable;
  #118 = Methodref          #2.#117       // scala/collection/immutable/AbstractMap.coll:()Lscala/collection/Iterable;
  #119 = Utf8               ()Lscala/collection/Set;
  #120 = NameAndType        #98:#99       // keySet:()Lscala/collection/immutable/Set;
  #121 = Methodref          #2.#120       // scala/collection/immutable/AbstractMap.keySet:()Lscala/collection/immutable/Set;
  #122 = Utf8               (Lscala/Tuple2;)Lscala/collection/IterableOps;
  #123 = NameAndType        #82:#83       // $plus:(Lscala/Tuple2;)Lscala/collection/immutable/MapOps;
  #124 = Methodref          #2.#123       // scala/collection/immutable/AbstractMap.$plus:(Lscala/Tuple2;)Lscala/collection/immutable/MapOps;
  #125 = Utf8               (Lscala/collection/IterableOnce;)Ljava/lang/Object;
  #126 = NameAndType        #71:#65       // $minus$minus:(Lscala/collection/IterableOnce;)Lscala/collection/immutable/MapOps;
  #127 = Methodref          #2.#126       // scala/collection/immutable/AbstractMap.$minus$minus:(Lscala/collection/IterableOnce;)Lscala/collection/immutable/MapOps;
  #128 = Utf8               (Ljava/lang/Object;Ljava/lang/Object;Lscala/collection/immutable/Seq;)Lscala/collection/Map;
  #129 = NameAndType        #47:#56       // $minus:(Ljava/lang/Object;Ljava/lang/Object;Lscala/collection/immutable/Seq;)Lscala/collection/immutable/MapOps;
  #130 = Methodref          #2.#129       // scala/collection/immutable/AbstractMap.$minus:(Ljava/lang/Object;Ljava/lang/Object;Lscala/collection/immutable/Seq;)Lscala/collection/immutable/MapOps;
  #131 = Utf8               scala/collection/Map
  #132 = Class              #131          // scala/collection/Map
  #133 = Utf8               (Ljava/lang/Object;)Lscala/collection/Map;
  #134 = NameAndType        #47:#48       // $minus:(Ljava/lang/Object;)Lscala/collection/immutable/MapOps;
  #135 = Methodref          #2.#134       // scala/collection/immutable/AbstractMap.$minus:(Ljava/lang/Object;)Lscala/collection/immutable/MapOps;
  #136 = Utf8               <init>
  #137 = Utf8               ()V
  #138 = NameAndType        #136:#137     // "<init>":()V
  #139 = Methodref          #5.#138       // scala/collection/AbstractMap."<init>":()V
  #140 = Utf8               Code
  #141 = Utf8               LineNumberTable
  #142 = Utf8               LocalVariableTable
  #143 = Utf8               Signature
  #144 = Utf8               MethodParameters
  #145 = Utf8               Deprecated
  #146 = Utf8               SourceFile
  #147 = Utf8               RuntimeVisibleAnnotations
  #148 = Utf8               ScalaInlineInfo
  #149 = Utf8               ScalaSig
{
  public scala.collection.MapFactory<scala.collection.immutable.Map> mapFactory();
    descriptor: ()Lscala/collection/MapFactory;
    flags: (0x0001) ACC_PUBLIC
    Code:
      stack=1, locals=1, args_size=1
         0: aload_0
         1: invokestatic  #18                 // InterfaceMethod scala/collection/immutable/Map.mapFactory$:(Lscala/collection/immutable/Map;)Lscala/collection/MapFactory;
         4: areturn
      LineNumberTable:
        line 641: 0
      LocalVariableTable:
        Start  Length  Slot  Name   Signature
            0       5     0  this   Lscala/collection/immutable/AbstractMap;
    Signature: #14                          // ()Lscala/collection/MapFactory<Lscala/collection/immutable/Map;>;

  public final <K2 extends java.lang.Object, V2 extends java.lang.Object> scala.collection.immutable.Map<K2, V2> toMap(scala.$less$colon$less<scala.Tuple2<K, V>, scala.Tuple2<K2, V2>>);
    descriptor: (Lscala/$less$colon$less;)Lscala/collection/immutable/Map;
    flags: (0x0011) ACC_PUBLIC, ACC_FINAL
    Code:
      stack=2, locals=2, args_size=2
         0: aload_0
         1: aload_1
         2: invokestatic  #28                 // InterfaceMethod scala/collection/immutable/Map.toMap$:(Lscala/collection/immutable/Map;Lscala/$less$colon$less;)Lscala/collection/immutable/Map;
         5: areturn
      LineNumberTable:
        line 641: 0
      LocalVariableTable:
        Start  Length  Slot  Name   Signature
            0       6     0  this   Lscala/collection/immutable/AbstractMap;
            0       6     1    ev   Lscala/$less$colon$less;
    Signature: #23                          // <K2:Ljava/lang/Object;V2:Ljava/lang/Object;>(Lscala/$less$colon$less<Lscala/Tuple2<TK;TV;>;Lscala/Tuple2<TK2;TV2;>;>;)Lscala/collection/immutable/Map<TK2;TV2;>;
    MethodParameters:
      Name                           Flags
      ev                             final

  public <V1 extends java.lang.Object> scala.collection.immutable.Map<K, V1> withDefault(scala.Function1<K, V1>);
    descriptor: (Lscala/Function1;)Lscala/collection/immutable/Map;
    flags: (0x0001) ACC_PUBLIC
    Code:
      stack=2, locals=2, args_size=2
         0: aload_0
         1: aload_1
         2: invokestatic  #37                 // InterfaceMethod scala/collection/immutable/Map.withDefault$:(Lscala/collection/immutable/Map;Lscala/Function1;)Lscala/collection/immutable/Map;
         5: areturn
      LineNumberTable:
        line 641: 0
      LocalVariableTable:
        Start  Length  Slot  Name   Signature
            0       6     0  this   Lscala/collection/immutable/AbstractMap;
            0       6     1     d   Lscala/Function1;
    Signature: #32                          // <V1:Ljava/lang/Object;>(Lscala/Function1<TK;TV1;>;)Lscala/collection/immutable/Map<TK;TV1;>;
    MethodParameters:
      Name                           Flags
      d                              final

  public <V1 extends java.lang.Object> scala.collection.immutable.Map<K, V1> withDefaultValue(V1);
    descriptor: (Ljava/lang/Object;)Lscala/collection/immutable/Map;
    flags: (0x0001) ACC_PUBLIC
    Code:
      stack=2, locals=2, args_size=2
         0: aload_0
         1: aload_1
         2: invokestatic  #45                 // InterfaceMethod scala/collection/immutable/Map.withDefaultValue$:(Lscala/collection/immutable/Map;Ljava/lang/Object;)Lscala/collection/immutable/Map;
         5: areturn
      LineNumberTable:
        line 641: 0
      LocalVariableTable:
        Start  Length  Slot  Name   Signature
            0       6     0  this   Lscala/collection/immutable/AbstractMap;
            0       6     1     d   Ljava/lang/Object;
    Signature: #41                          // <V1:Ljava/lang/Object;>(TV1;)Lscala/collection/immutable/Map<TK;TV1;>;
    MethodParameters:
      Name                           Flags
      d                              final

  public final scala.collection.immutable.MapOps $minus(java.lang.Object);
    descriptor: (Ljava/lang/Object;)Lscala/collection/immutable/MapOps;
    flags: (0x0011) ACC_PUBLIC, ACC_FINAL
    Code:
      stack=2, locals=2, args_size=2
         0: aload_0
         1: aload_1
         2: invokestatic  #55                 // InterfaceMethod scala/collection/immutable/MapOps.$minus$:(Lscala/collection/immutable/MapOps;Ljava/lang/Object;)Lscala/collection/immutable/MapOps;
         5: areturn
      LineNumberTable:
        line 641: 0
      LocalVariableTable:
        Start  Length  Slot  Name   Signature
            0       6     0  this   Lscala/collection/immutable/AbstractMap;
            0       6     1   key   Ljava/lang/Object;
    MethodParameters:
      Name                           Flags
      key                            final

  public scala.collection.immutable.MapOps $minus(java.lang.Object, java.lang.Object, scala.collection.immutable.Seq);
    descriptor: (Ljava/lang/Object;Ljava/lang/Object;Lscala/collection/immutable/Seq;)Lscala/collection/immutable/MapOps;
    flags: (0x0001) ACC_PUBLIC
    Code:
      stack=4, locals=4, args_size=4
         0: aload_0
         1: aload_1
         2: aload_2
         3: aload_3
         4: invokestatic  #62                 // InterfaceMethod scala/collection/immutable/MapOps.$minus$:(Lscala/collection/immutable/MapOps;Ljava/lang/Object;Ljava/lang/Object;Lscala/collection/immutable/Seq;)Lscala/collection/immutable/MapOps;
         7: areturn
      LineNumberTable:
        line 641: 0
      LocalVariableTable:
        Start  Length  Slot  Name   Signature
            0       8     0  this   Lscala/collection/immutable/AbstractMap;
            0       8     1  key1   Ljava/lang/Object;
            0       8     2  key2   Ljava/lang/Object;
            0       8     3  keys   Lscala/collection/immutable/Seq;
    Deprecated: true
    MethodParameters:
      Name                           Flags
      key1                           final
      key2                           final
      keys                           final

  public scala.collection.immutable.MapOps removedAll(scala.collection.IterableOnce);
    descriptor: (Lscala/collection/IterableOnce;)Lscala/collection/immutable/MapOps;
    flags: (0x0001) ACC_PUBLIC
    Code:
      stack=2, locals=2, args_size=2
         0: aload_0
         1: aload_1
         2: invokestatic  #69                 // InterfaceMethod scala/collection/immutable/MapOps.removedAll$:(Lscala/collection/immutable/MapOps;Lscala/collection/IterableOnce;)Lscala/collection/immutable/MapOps;
         5: areturn
      LineNumberTable:
        line 641: 0
      LocalVariableTable:
        Start  Length  Slot  Name   Signature
            0       6     0  this   Lscala/collection/immutable/AbstractMap;
            0       6     1  keys   Lscala/collection/IterableOnce;
    MethodParameters:
      Name                           Flags
      keys                           final

  public final scala.collection.immutable.MapOps $minus$minus(scala.collection.IterableOnce);
    descriptor: (Lscala/collection/IterableOnce;)Lscala/collection/immutable/MapOps;
    flags: (0x0011) ACC_PUBLIC, ACC_FINAL
    Code:
      stack=2, locals=2, args_size=2
         0: aload_0
         1: aload_1
         2: invokestatic  #74                 // InterfaceMethod scala/collection/immutable/MapOps.$minus$minus$:(Lscala/collection/immutable/MapOps;Lscala/collection/IterableOnce;)Lscala/collection/immutable/MapOps;
         5: areturn
      LineNumberTable:
        line 641: 0
      LocalVariableTable:
        Start  Length  Slot  Name   Signature
            0       6     0  this   Lscala/collection/immutable/AbstractMap;
            0       6     1  keys   Lscala/collection/IterableOnce;
    MethodParameters:
      Name                           Flags
      keys                           final

  public scala.collection.immutable.MapOps updatedWith(java.lang.Object, scala.Function1);
    descriptor: (Ljava/lang/Object;Lscala/Function1;)Lscala/collection/immutable/MapOps;
    flags: (0x0001) ACC_PUBLIC
    Code:
      stack=3, locals=3, args_size=3
         0: aload_0
         1: aload_1
         2: aload_2
         3: invokestatic  #81                 // InterfaceMethod scala/collection/immutable/MapOps.updatedWith$:(Lscala/collection/immutable/MapOps;Ljava/lang/Object;Lscala/Function1;)Lscala/collection/immutable/MapOps;
         6: areturn
      LineNumberTable:
        line 641: 0
      LocalVariableTable:
        Start  Length  Slot  Name   Signature
            0       7     0  this   Lscala/collection/immutable/AbstractMap;
            0       7     1   key   Ljava/lang/Object;
            0       7     2 remappingFunction   Lscala/Function1;
    MethodParameters:
      Name                           Flags
      key                            final
      remappingFunction              final

  public scala.collection.immutable.MapOps $plus(scala.Tuple2);
    descriptor: (Lscala/Tuple2;)Lscala/collection/immutable/MapOps;
    flags: (0x0001) ACC_PUBLIC
    Code:
      stack=2, locals=2, args_size=2
         0: aload_0
         1: aload_1
         2: invokestatic  #88                 // InterfaceMethod scala/collection/immutable/MapOps.$plus$:(Lscala/collection/immutable/MapOps;Lscala/Tuple2;)Lscala/collection/immutable/MapOps;
         5: areturn
      LineNumberTable:
        line 641: 0
      LocalVariableTable:
        Start  Length  Slot  Name   Signature
            0       6     0  this   Lscala/collection/immutable/AbstractMap;
            0       6     1    kv   Lscala/Tuple2;
    MethodParameters:
      Name                           Flags
      kv                             final

  public scala.collection.immutable.MapOps transform(scala.Function2);
    descriptor: (Lscala/Function2;)Lscala/collection/immutable/MapOps;
    flags: (0x0001) ACC_PUBLIC
    Code:
      stack=2, locals=2, args_size=2
         0: aload_0
         1: aload_1
         2: invokestatic  #96                 // InterfaceMethod scala/collection/immutable/MapOps.transform$:(Lscala/collection/immutable/MapOps;Lscala/Function2;)Lscala/collection/immutable/MapOps;
         5: areturn
      LineNumberTable:
        line 641: 0
      LocalVariableTable:
        Start  Length  Slot  Name   Signature
            0       6     0  this   Lscala/collection/immutable/AbstractMap;
            0       6     1     f   Lscala/Function2;
    MethodParameters:
      Name                           Flags
      f                              final

  public scala.collection.immutable.Set<K> keySet();
    descriptor: ()Lscala/collection/immutable/Set;
    flags: (0x0001) ACC_PUBLIC
    Code:
      stack=1, locals=1, args_size=1
         0: aload_0
         1: invokestatic  #104                // InterfaceMethod scala/collection/immutable/MapOps.keySet$:(Lscala/collection/immutable/MapOps;)Lscala/collection/immutable/Set;
         4: areturn
      LineNumberTable:
        line 641: 0
      LocalVariableTable:
        Start  Length  Slot  Name   Signature
            0       5     0  this   Lscala/collection/immutable/AbstractMap;
    Signature: #100                         // ()Lscala/collection/immutable/Set<TK;>;

  public scala.collection.IterableFactory<scala.collection.immutable.Iterable> iterableFactory();
    descriptor: ()Lscala/collection/IterableFactory;
    flags: (0x0001) ACC_PUBLIC
    Code:
      stack=1, locals=1, args_size=1
         0: aload_0
         1: invokestatic  #113                // InterfaceMethod scala/collection/immutable/Iterable.iterableFactory$:(Lscala/collection/immutable/Iterable;)Lscala/collection/IterableFactory;
         4: areturn
      LineNumberTable:
        line 641: 0
      LocalVariableTable:
        Start  Length  Slot  Name   Signature
            0       5     0  this   Lscala/collection/immutable/AbstractMap;
    Signature: #107                         // ()Lscala/collection/IterableFactory<Lscala/collection/immutable/Iterable;>;

  public final scala.collection.immutable.MapOps coll();
    descriptor: ()Lscala/collection/immutable/MapOps;
    flags: (0x1051) ACC_PUBLIC, ACC_FINAL, ACC_BRIDGE, ACC_SYNTHETIC
    Code:
      stack=1, locals=1, args_size=1
         0: aload_0
         1: invokevirtual #118                // Method coll:()Lscala/collection/Iterable;
         4: checkcast     #51                 // class scala/collection/immutable/MapOps
         7: areturn
      LineNumberTable:
        line 641: 0
      LocalVariableTable:
        Start  Length  Slot  Name   Signature
            0       8     0  this   Lscala/collection/immutable/AbstractMap;

  public scala.collection.Set keySet();
    descriptor: ()Lscala/collection/Set;
    flags: (0x1041) ACC_PUBLIC, ACC_BRIDGE, ACC_SYNTHETIC
    Code:
      stack=1, locals=1, args_size=1
         0: aload_0
         1: invokevirtual #121                // Method keySet:()Lscala/collection/immutable/Set;
         4: areturn
      LineNumberTable:
        line 641: 0
      LocalVariableTable:
        Start  Length  Slot  Name   Signature
            0       5     0  this   Lscala/collection/immutable/AbstractMap;

  public scala.collection.IterableOps $plus(scala.Tuple2);
    descriptor: (Lscala/Tuple2;)Lscala/collection/IterableOps;
    flags: (0x1041) ACC_PUBLIC, ACC_BRIDGE, ACC_SYNTHETIC
    Code:
      stack=2, locals=2, args_size=2
         0: aload_0
         1: aload_1
         2: invokevirtual #124                // Method $plus:(Lscala/Tuple2;)Lscala/collection/immutable/MapOps;
         5: areturn
      LineNumberTable:
        line 641: 0
      LocalVariableTable:
        Start  Length  Slot  Name   Signature
            0       6     0  this   Lscala/collection/immutable/AbstractMap;
            0       6     1    kv   Lscala/Tuple2;
    MethodParameters:
      Name                           Flags
      kv                             final

  public final java.lang.Object $minus$minus(scala.collection.IterableOnce);
    descriptor: (Lscala/collection/IterableOnce;)Ljava/lang/Object;
    flags: (0x1051) ACC_PUBLIC, ACC_FINAL, ACC_BRIDGE, ACC_SYNTHETIC
    Code:
      stack=2, locals=2, args_size=2
         0: aload_0
         1: aload_1
         2: invokevirtual #127                // Method $minus$minus:(Lscala/collection/IterableOnce;)Lscala/collection/immutable/MapOps;
         5: areturn
      LineNumberTable:
        line 641: 0
      LocalVariableTable:
        Start  Length  Slot  Name   Signature
            0       6     0  this   Lscala/collection/immutable/AbstractMap;
            0       6     1  keys   Lscala/collection/IterableOnce;
    MethodParameters:
      Name                           Flags
      keys                           final

  public scala.collection.Map $minus(java.lang.Object, java.lang.Object, scala.collection.immutable.Seq);
    descriptor: (Ljava/lang/Object;Ljava/lang/Object;Lscala/collection/immutable/Seq;)Lscala/collection/Map;
    flags: (0x1041) ACC_PUBLIC, ACC_BRIDGE, ACC_SYNTHETIC
    Code:
      stack=4, locals=4, args_size=4
         0: aload_0
         1: aload_1
         2: aload_2
         3: aload_3
         4: invokevirtual #130                // Method $minus:(Ljava/lang/Object;Ljava/lang/Object;Lscala/collection/immutable/Seq;)Lscala/collection/immutable/MapOps;
         7: checkcast     #132                // class scala/collection/Map
        10: areturn
      LineNumberTable:
        line 641: 0
      LocalVariableTable:
        Start  Length  Slot  Name   Signature
            0      11     0  this   Lscala/collection/immutable/AbstractMap;
            0      11     1  key1   Ljava/lang/Object;
            0      11     2  key2   Ljava/lang/Object;
            0      11     3  keys   Lscala/collection/immutable/Seq;
    Deprecated: true
    MethodParameters:
      Name                           Flags
      key1                           final
      key2                           final
      keys                           final

  public final scala.collection.Map $minus(java.lang.Object);
    descriptor: (Ljava/lang/Object;)Lscala/collection/Map;
    flags: (0x1051) ACC_PUBLIC, ACC_FINAL, ACC_BRIDGE, ACC_SYNTHETIC
    Code:
      stack=2, locals=2, args_size=2
         0: aload_0
         1: aload_1
         2: invokevirtual #135                // Method $minus:(Ljava/lang/Object;)Lscala/collection/immutable/MapOps;
         5: checkcast     #132                // class scala/collection/Map
         8: areturn
      LineNumberTable:
        line 641: 0
      LocalVariableTable:
        Start  Length  Slot  Name   Signature
            0       9     0  this   Lscala/collection/immutable/AbstractMap;
            0       9     1   key   Ljava/lang/Object;
    MethodParameters:
      Name                           Flags
      key                            final

  public scala.collection.immutable.AbstractMap();
    descriptor: ()V
    flags: (0x0001) ACC_PUBLIC
    Code:
      stack=1, locals=1, args_size=1
         0: aload_0
         1: invokespecial #139                // Method scala/collection/AbstractMap."<init>":()V
         4: return
      LineNumberTable:
        line 641: 0
      LocalVariableTable:
        Start  Length  Slot  Name   Signature
            0       5     0  this   Lscala/collection/immutable/AbstractMap;
}
Signature: #3                           // <K:Ljava/lang/Object;V:Ljava/lang/Object;>Lscala/collection/AbstractMap<TK;TV;>;Lscala/collection/immutable/Map<TK;TV;>;
SourceFile: "Map.scala"
RuntimeVisibleAnnotations:
  0: #9(#10=s#11)
    scala.reflect.ScalaSignature(
      bytes="\u0006\u0005\u00152QAA\u0002\u0002\u0002)AQA\t\u0001\u0005\u0002\r\u00121\"\u00112tiJ\f7\r^\'ba*\u0011A!B\u0001\nS6lW\u000f^1cY\u0016T!AB\u0004\u0002\u0015\r|G\u000e\\3di&|gNC\u0001\t\u0003\u0015\u00198-\u00197b\u0007\u0001)2aC\t\u001d\'\r\u0001AB\b\t\u0005\u001b9y1$D\u0001\u0006\u0013\t\u0011Q\u0001\u0005\u0002\u0011#1\u0001A!\u0002\n\u0001\u0005\u0004\u0019\"!A&\u0012\u0005QA\u0002CA\u000b\u0017\u001b\u00059\u0011BA\f\b\u0005\u001dqu\u000e\u001e5j]\u001e\u0004\"!F\r\n\u0005i9!aA!osB\u0011\u0001\u0003\b\u0003\u0007;\u0001!)\u0019A\n\u0003\u0003Y\u0003Ba\b\u0011\u001075\t1!\u0003\u0002\"\u0007\t\u0019Q*\u00199\u0002\rqJg.\u001b;?)\u0005!\u0003\u0003B\u0010\u0001\u001fm\u0001"
    )
  ScalaInlineInfo: length = 0x68 (unknown attribute)
   01 00 00 14 00 2F 00 85 05 00 2F 00 30 05 00 2F
   00 80 00 00 2F 00 38 00 00 47 00 7D 05 00 47 00
   41 05 00 52 00 7A 00 00 52 00 53 00 00 88 00 89
   00 00 72 00 73 01 00 69 00 6A 00 00 62 00 77 00
   00 62 00 63 00 00 0C 00 0D 00 00 40 00 41 00 00
   15 00 16 01 00 5A 00 5B 00 00 4B 00 4C 00 00 1E
   00 1F 00 00 27 00 28 00
  ScalaSig: length = 0x3 (unknown attribute)
   05 02 00
