Classfile /Users/mw/Projects/slang-braindump/.jar/jar8/assemble/slang-braindump/assemble/content/scala/collection/immutable/ArraySeq$ofChar.class
  Last modified May 29, 2022; size 6463 bytes
  SHA-256 checksum 6631247eded5ffe851c971087aa9bd14a25f4d32fd69eadf7d2a5f97b8936105
  Compiled from "ArraySeq.scala"
public final class scala.collection.immutable.ArraySeq$ofChar extends scala.collection.immutable.ArraySeq<java.lang.Object>
  minor version: 0
  major version: 52
  flags: (0x0031) ACC_PUBLIC, ACC_FINAL, ACC_SUPER
  this_class: #2                          // scala/collection/immutable/ArraySeq$ofChar
  super_class: #5                         // scala/collection/immutable/ArraySeq
  interfaces: 0, fields: 2, methods: 22, attributes: 5
Constant pool:
    #1 = Utf8               scala/collection/immutable/ArraySeq$ofChar
    #2 = Class              #1            // scala/collection/immutable/ArraySeq$ofChar
    #3 = Utf8               Lscala/collection/immutable/ArraySeq<Ljava/lang/Object;>;
    #4 = Utf8               scala/collection/immutable/ArraySeq
    #5 = Class              #4            // scala/collection/immutable/ArraySeq
    #6 = Utf8               ArraySeq.scala
    #7 = Utf8               scala/collection/AnyStepper$$anon$4
    #8 = Class              #7            // scala/collection/AnyStepper$$anon$4
    #9 = Utf8               ofChar
   #10 = Utf8               scala/collection/mutable/ArraySeq$ofChar
   #11 = Class              #10           // scala/collection/mutable/ArraySeq$ofChar
   #12 = Utf8               scala/collection/mutable/ArraySeq
   #13 = Class              #12           // scala/collection/mutable/ArraySeq
   #14 = Utf8               scala/math/Ordering$Char$
   #15 = Class              #14           // scala/math/Ordering$Char$
   #16 = Utf8               scala/math/Ordering
   #17 = Class              #16           // scala/math/Ordering
   #18 = Utf8               Char$
   #19 = Utf8               scala/reflect/ManifestFactory$CharManifest
   #20 = Class              #19           // scala/reflect/ManifestFactory$CharManifest
   #21 = Utf8               scala/reflect/ManifestFactory
   #22 = Class              #21           // scala/reflect/ManifestFactory
   #23 = Utf8               CharManifest
   #24 = Utf8               serialVersionUID
   #25 = Utf8               J
   #26 = Long               3l
   #28 = Utf8               unsafeArray
   #29 = Utf8               [C
   #30 = Utf8               ()[C
   #31 = NameAndType        #28:#29       // unsafeArray:[C
   #32 = Fieldref           #2.#31        // scala/collection/immutable/ArraySeq$ofChar.unsafeArray:[C
   #33 = Utf8               this
   #34 = Utf8               Lscala/collection/immutable/ArraySeq$ofChar;
   #35 = Utf8               elemTag
   #36 = Utf8               ()Lscala/reflect/ManifestFactory$CharManifest;
   #37 = Utf8               scala/reflect/ClassTag$
   #38 = Class              #37           // scala/reflect/ClassTag$
   #39 = Utf8               MODULE$
   #40 = Utf8               Lscala/reflect/ClassTag$;
   #41 = NameAndType        #39:#40       // MODULE$:Lscala/reflect/ClassTag$;
   #42 = Fieldref           #38.#41       // scala/reflect/ClassTag$.MODULE$:Lscala/reflect/ClassTag$;
   #43 = Utf8               Char
   #44 = NameAndType        #43:#36       // Char:()Lscala/reflect/ManifestFactory$CharManifest;
   #45 = Methodref          #38.#44       // scala/reflect/ClassTag$.Char:()Lscala/reflect/ManifestFactory$CharManifest;
   #46 = Utf8               length
   #47 = Utf8               ()I
   #48 = NameAndType        #28:#30       // unsafeArray:()[C
   #49 = Methodref          #2.#48        // scala/collection/immutable/ArraySeq$ofChar.unsafeArray:()[C
   #50 = Utf8               apply
   #51 = Utf8               (I)C
   #52 = Utf8               java/lang/ArrayIndexOutOfBoundsException
   #53 = Class              #52           // java/lang/ArrayIndexOutOfBoundsException
   #54 = Utf8               i
   #55 = Utf8               I
   #56 = Utf8               hashCode
   #57 = Utf8               scala/util/hashing/MurmurHash3$
   #58 = Class              #57           // scala/util/hashing/MurmurHash3$
   #59 = Utf8               Lscala/util/hashing/MurmurHash3$;
   #60 = NameAndType        #39:#59       // MODULE$:Lscala/util/hashing/MurmurHash3$;
   #61 = Fieldref           #58.#60       // scala/util/hashing/MurmurHash3$.MODULE$:Lscala/util/hashing/MurmurHash3$;
   #62 = Utf8               arraySeqHash$mCc$sp
   #63 = Utf8               ([C)I
   #64 = NameAndType        #62:#63       // arraySeqHash$mCc$sp:([C)I
   #65 = Methodref          #58.#64       // scala/util/hashing/MurmurHash3$.arraySeqHash$mCc$sp:([C)I
   #66 = Utf8               equals
   #67 = Utf8               (Ljava/lang/Object;)Z
   #68 = Utf8               that
   #69 = Utf8               java/util/Arrays
   #70 = Class              #69           // java/util/Arrays
   #71 = Utf8               ([C[C)Z
   #72 = NameAndType        #66:#71       // equals:([C[C)Z
   #73 = Methodref          #70.#72       // java/util/Arrays.equals:([C[C)Z
   #74 = Utf8               scala/collection/Seq
   #75 = Class              #74           // scala/collection/Seq
   #76 = Utf8               equals$
   #77 = Utf8               (Lscala/collection/Seq;Ljava/lang/Object;)Z
   #78 = NameAndType        #76:#77       // equals$:(Lscala/collection/Seq;Ljava/lang/Object;)Z
   #79 = InterfaceMethodref #75.#78       // scala/collection/Seq.equals$:(Lscala/collection/Seq;Ljava/lang/Object;)Z
   #80 = Utf8               Ljava/lang/Object;
   #81 = Utf8               sorted
   #82 = Utf8               (Lscala/math/Ordering;)Lscala/collection/immutable/ArraySeq;
   #83 = Utf8               <B:Ljava/lang/Object;>(Lscala/math/Ordering<TB;>;)Lscala/collection/immutable/ArraySeq<Ljava/lang/Object;>;
   #84 = Utf8               ord
   #85 = Utf8               Lscala/math/Ordering$Char$;
   #86 = NameAndType        #39:#85       // MODULE$:Lscala/math/Ordering$Char$;
   #87 = Fieldref           #15.#86       // scala/math/Ordering$Char$.MODULE$:Lscala/math/Ordering$Char$;
   #88 = Class              #29           // "[C"
   #89 = Utf8               clone
   #90 = Utf8               ()Ljava/lang/Object;
   #91 = NameAndType        #89:#90       // clone:()Ljava/lang/Object;
   #92 = Methodref          #88.#91       // "[C".clone:()Ljava/lang/Object;
   #93 = Utf8               sort
   #94 = Utf8               ([C)V
   #95 = NameAndType        #93:#94       // sort:([C)V
   #96 = Methodref          #70.#95       // java/util/Arrays.sort:([C)V
   #97 = Utf8               <init>
   #98 = NameAndType        #97:#94       // "<init>":([C)V
   #99 = Methodref          #2.#98        // scala/collection/immutable/ArraySeq$ofChar."<init>":([C)V
  #100 = NameAndType        #81:#82       // sorted:(Lscala/math/Ordering;)Lscala/collection/immutable/ArraySeq;
  #101 = Methodref          #5.#100       // scala/collection/immutable/ArraySeq.sorted:(Lscala/math/Ordering;)Lscala/collection/immutable/ArraySeq;
  #102 = Utf8               a
  #103 = Utf8               Lscala/math/Ordering;
  #104 = Utf8               iterator
  #105 = Utf8               ()Lscala/collection/Iterator;
  #106 = Utf8               ()Lscala/collection/Iterator<Ljava/lang/Object;>;
  #107 = Utf8               scala/collection/ArrayOps$ArrayIterator$mcC$sp
  #108 = Class              #107          // scala/collection/ArrayOps$ArrayIterator$mcC$sp
  #109 = Methodref          #108.#98      // scala/collection/ArrayOps$ArrayIterator$mcC$sp."<init>":([C)V
  #110 = Utf8               stepper
  #111 = Utf8               (Lscala/collection/StepperShape;)Lscala/collection/Stepper;
  #112 = Utf8               <S::Lscala/collection/Stepper<*>;>(Lscala/collection/StepperShape<Ljava/lang/Object;TS;>;)TS;
  #113 = Utf8               shape
  #114 = Utf8               scala/collection/StepperShape
  #115 = Class              #114          // scala/collection/StepperShape
  #116 = NameAndType        #113:#47      // shape:()I
  #117 = InterfaceMethodref #115.#116     // scala/collection/StepperShape.shape:()I
  #118 = Utf8               scala/collection/StepperShape$
  #119 = Class              #118          // scala/collection/StepperShape$
  #120 = Utf8               Lscala/collection/StepperShape$;
  #121 = NameAndType        #39:#120      // MODULE$:Lscala/collection/StepperShape$;
  #122 = Fieldref           #119.#121     // scala/collection/StepperShape$.MODULE$:Lscala/collection/StepperShape$;
  #123 = Utf8               ReferenceShape
  #124 = NameAndType        #123:#47      // ReferenceShape:()I
  #125 = Methodref          #119.#124     // scala/collection/StepperShape$.ReferenceShape:()I
  #126 = Utf8               scala/collection/AnyStepper$
  #127 = Class              #126          // scala/collection/AnyStepper$
  #128 = Utf8               Lscala/collection/AnyStepper$;
  #129 = NameAndType        #39:#128      // MODULE$:Lscala/collection/AnyStepper$;
  #130 = Fieldref           #127.#129     // scala/collection/AnyStepper$.MODULE$:Lscala/collection/AnyStepper$;
  #131 = Utf8               scala/collection/convert/impl/WidenedCharArrayStepper
  #132 = Class              #131          // scala/collection/convert/impl/WidenedCharArrayStepper
  #133 = Utf8               ([CII)V
  #134 = NameAndType        #97:#133      // "<init>":([CII)V
  #135 = Methodref          #132.#134     // scala/collection/convert/impl/WidenedCharArrayStepper."<init>":([CII)V
  #136 = Utf8               (Lscala/collection/IntStepper;)V
  #137 = NameAndType        #97:#136      // "<init>":(Lscala/collection/IntStepper;)V
  #138 = Methodref          #8.#137       // scala/collection/AnyStepper$$anon$4."<init>":(Lscala/collection/IntStepper;)V
  #139 = Utf8               scala/collection/Stepper
  #140 = Class              #139          // scala/collection/Stepper
  #141 = Utf8               Lscala/collection/StepperShape;
  #142 = Utf8               ofParIntStepper_st
  #143 = Utf8               Lscala/collection/IntStepper;
  #144 = Utf8               java/lang/Object
  #145 = Class              #144          // java/lang/Object
  #146 = Utf8               updated
  #147 = Utf8               (ILjava/lang/Object;)Lscala/collection/immutable/ArraySeq;
  #148 = Utf8               <B:Ljava/lang/Object;>(ITB;)Lscala/collection/immutable/ArraySeq<TB;>;
  #149 = Utf8               index
  #150 = Utf8               elem
  #151 = Utf8               java/lang/Character
  #152 = Class              #151          // java/lang/Character
  #153 = Utf8               scala/runtime/BoxesRunTime
  #154 = Class              #153          // scala/runtime/BoxesRunTime
  #155 = Utf8               unboxToChar
  #156 = Utf8               (Ljava/lang/Object;)C
  #157 = NameAndType        #155:#156     // unboxToChar:(Ljava/lang/Object;)C
  #158 = Methodref          #154.#157     // scala/runtime/BoxesRunTime.unboxToChar:(Ljava/lang/Object;)C
  #159 = Utf8               scala/collection/ArrayOps$
  #160 = Class              #159          // scala/collection/ArrayOps$
  #161 = Utf8               Lscala/collection/ArrayOps$;
  #162 = NameAndType        #39:#161      // MODULE$:Lscala/collection/ArrayOps$;
  #163 = Fieldref           #160.#162     // scala/collection/ArrayOps$.MODULE$:Lscala/collection/ArrayOps$;
  #164 = Utf8               valueOf
  #165 = Utf8               (C)Ljava/lang/Character;
  #166 = NameAndType        #164:#165     // valueOf:(C)Ljava/lang/Character;
  #167 = Methodref          #152.#166     // java/lang/Character.valueOf:(C)Ljava/lang/Character;
  #168 = Utf8               updated$extension
  #169 = Utf8               (Ljava/lang/Object;ILjava/lang/Object;Lscala/reflect/ClassTag;)Ljava/lang/Object;
  #170 = NameAndType        #168:#169     // updated$extension:(Ljava/lang/Object;ILjava/lang/Object;Lscala/reflect/ClassTag;)Ljava/lang/Object;
  #171 = Methodref          #160.#170     // scala/collection/ArrayOps$.updated$extension:(Ljava/lang/Object;ILjava/lang/Object;Lscala/reflect/ClassTag;)Ljava/lang/Object;
  #172 = NameAndType        #146:#147     // updated:(ILjava/lang/Object;)Lscala/collection/immutable/ArraySeq;
  #173 = Methodref          #5.#172       // scala/collection/immutable/ArraySeq.updated:(ILjava/lang/Object;)Lscala/collection/immutable/ArraySeq;
  #174 = Utf8               appended
  #175 = Utf8               (Ljava/lang/Object;)Lscala/collection/immutable/ArraySeq;
  #176 = Utf8               <B:Ljava/lang/Object;>(TB;)Lscala/collection/immutable/ArraySeq<TB;>;
  #177 = Utf8               appended$extension
  #178 = Utf8               (Ljava/lang/Object;Ljava/lang/Object;Lscala/reflect/ClassTag;)Ljava/lang/Object;
  #179 = NameAndType        #177:#178     // appended$extension:(Ljava/lang/Object;Ljava/lang/Object;Lscala/reflect/ClassTag;)Ljava/lang/Object;
  #180 = Methodref          #160.#179     // scala/collection/ArrayOps$.appended$extension:(Ljava/lang/Object;Ljava/lang/Object;Lscala/reflect/ClassTag;)Ljava/lang/Object;
  #181 = NameAndType        #174:#175     // appended:(Ljava/lang/Object;)Lscala/collection/immutable/ArraySeq;
  #182 = Methodref          #5.#181       // scala/collection/immutable/ArraySeq.appended:(Ljava/lang/Object;)Lscala/collection/immutable/ArraySeq;
  #183 = Utf8               prepended
  #184 = Utf8               prepended$extension
  #185 = NameAndType        #184:#178     // prepended$extension:(Ljava/lang/Object;Ljava/lang/Object;Lscala/reflect/ClassTag;)Ljava/lang/Object;
  #186 = Methodref          #160.#185     // scala/collection/ArrayOps$.prepended$extension:(Ljava/lang/Object;Ljava/lang/Object;Lscala/reflect/ClassTag;)Ljava/lang/Object;
  #187 = NameAndType        #183:#175     // prepended:(Ljava/lang/Object;)Lscala/collection/immutable/ArraySeq;
  #188 = Methodref          #5.#187       // scala/collection/immutable/ArraySeq.prepended:(Ljava/lang/Object;)Lscala/collection/immutable/ArraySeq;
  #189 = Utf8               addString
  #190 = Utf8               (Lscala/collection/mutable/StringBuilder;Ljava/lang/String;Ljava/lang/String;Ljava/lang/String;)Lscala/collection/mutable/StringBuilder;
  #191 = Utf8               sb
  #192 = Utf8               start
  #193 = Utf8               sep
  #194 = Utf8               end
  #195 = Methodref          #11.#98       // scala/collection/mutable/ArraySeq$ofChar."<init>":([C)V
  #196 = NameAndType        #189:#190     // addString:(Lscala/collection/mutable/StringBuilder;Ljava/lang/String;Ljava/lang/String;Ljava/lang/String;)Lscala/collection/mutable/StringBuilder;
  #197 = Methodref          #11.#196      // scala/collection/mutable/ArraySeq$ofChar.addString:(Lscala/collection/mutable/StringBuilder;Ljava/lang/String;Ljava/lang/String;Ljava/lang/String;)Lscala/collection/mutable/StringBuilder;
  #198 = Utf8               Lscala/collection/mutable/StringBuilder;
  #199 = Utf8               Ljava/lang/String;
  #200 = Utf8               (Ljava/lang/Object;)Ljava/lang/Object;
  #201 = Methodref          #2.#187       // scala/collection/immutable/ArraySeq$ofChar.prepended:(Ljava/lang/Object;)Lscala/collection/immutable/ArraySeq;
  #202 = Methodref          #2.#181       // scala/collection/immutable/ArraySeq$ofChar.appended:(Ljava/lang/Object;)Lscala/collection/immutable/ArraySeq;
  #203 = Utf8               (ILjava/lang/Object;)Ljava/lang/Object;
  #204 = Methodref          #2.#172       // scala/collection/immutable/ArraySeq$ofChar.updated:(ILjava/lang/Object;)Lscala/collection/immutable/ArraySeq;
  #205 = Utf8               (Lscala/math/Ordering;)Ljava/lang/Object;
  #206 = Methodref          #2.#100       // scala/collection/immutable/ArraySeq$ofChar.sorted:(Lscala/math/Ordering;)Lscala/collection/immutable/ArraySeq;
  #207 = Utf8               v1
  #208 = Utf8               unboxToInt
  #209 = Utf8               (Ljava/lang/Object;)I
  #210 = NameAndType        #208:#209     // unboxToInt:(Ljava/lang/Object;)I
  #211 = Methodref          #154.#210     // scala/runtime/BoxesRunTime.unboxToInt:(Ljava/lang/Object;)I
  #212 = NameAndType        #50:#51       // apply:(I)C
  #213 = Methodref          #2.#212       // scala/collection/immutable/ArraySeq$ofChar.apply:(I)C
  #214 = Utf8               boxToCharacter
  #215 = NameAndType        #214:#165     // boxToCharacter:(C)Ljava/lang/Character;
  #216 = Methodref          #154.#215     // scala/runtime/BoxesRunTime.boxToCharacter:(C)Ljava/lang/Character;
  #217 = Utf8               (I)Ljava/lang/Object;
  #218 = Utf8               ()Lscala/reflect/ClassTag;
  #219 = NameAndType        #35:#36       // elemTag:()Lscala/reflect/ManifestFactory$CharManifest;
  #220 = Methodref          #2.#219       // scala/collection/immutable/ArraySeq$ofChar.elemTag:()Lscala/reflect/ManifestFactory$CharManifest;
  #221 = Utf8               ()V
  #222 = NameAndType        #97:#221      // "<init>":()V
  #223 = Methodref          #5.#222       // scala/collection/immutable/ArraySeq."<init>":()V
  #224 = Utf8               ConstantValue
  #225 = Utf8               Code
  #226 = Utf8               LineNumberTable
  #227 = Utf8               LocalVariableTable
  #228 = Utf8               Exceptions
  #229 = Utf8               MethodParameters
  #230 = Utf8               StackMapTable
  #231 = Utf8               Signature
  #232 = Utf8               InnerClasses
  #233 = Utf8               SourceFile
  #234 = Utf8               ScalaInlineInfo
  #235 = Utf8               Scala
{
  private static final long serialVersionUID;
    descriptor: J
    flags: (0x001a) ACC_PRIVATE, ACC_STATIC, ACC_FINAL
    ConstantValue: long 3l

  private final char[] unsafeArray;
    descriptor: [C
    flags: (0x0012) ACC_PRIVATE, ACC_FINAL

  public char[] unsafeArray();
    descriptor: ()[C
    flags: (0x0001) ACC_PUBLIC
    Code:
      stack=1, locals=1, args_size=1
         0: aload_0
         1: getfield      #32                 // Field unsafeArray:[C
         4: areturn
      LineNumberTable:
        line 439: 0
      LocalVariableTable:
        Start  Length  Slot  Name   Signature
            0       5     0  this   Lscala/collection/immutable/ArraySeq$ofChar;

  public scala.reflect.ManifestFactory$CharManifest elemTag();
    descriptor: ()Lscala/reflect/ManifestFactory$CharManifest;
    flags: (0x0001) ACC_PUBLIC
    Code:
      stack=1, locals=1, args_size=1
         0: getstatic     #42                 // Field scala/reflect/ClassTag$.MODULE$:Lscala/reflect/ClassTag$;
         3: invokevirtual #45                 // Method scala/reflect/ClassTag$.Char:()Lscala/reflect/ManifestFactory$CharManifest;
         6: areturn
      LineNumberTable:
        line 440: 0
      LocalVariableTable:
        Start  Length  Slot  Name   Signature
            0       7     0  this   Lscala/collection/immutable/ArraySeq$ofChar;

  public int length();
    descriptor: ()I
    flags: (0x0001) ACC_PUBLIC
    Code:
      stack=1, locals=1, args_size=1
         0: aload_0
         1: invokevirtual #49                 // Method unsafeArray:()[C
         4: arraylength
         5: ireturn
      LineNumberTable:
        line 441: 0
      LocalVariableTable:
        Start  Length  Slot  Name   Signature
            0       6     0  this   Lscala/collection/immutable/ArraySeq$ofChar;

  public char apply(int) throws java.lang.ArrayIndexOutOfBoundsException;
    descriptor: (I)C
    flags: (0x0001) ACC_PUBLIC
    Code:
      stack=2, locals=2, args_size=2
         0: aload_0
         1: invokevirtual #49                 // Method unsafeArray:()[C
         4: iload_1
         5: caload
         6: ireturn
      LineNumberTable:
        line 443: 0
      LocalVariableTable:
        Start  Length  Slot  Name   Signature
            0       7     0  this   Lscala/collection/immutable/ArraySeq$ofChar;
            0       7     1     i   I
    Exceptions:
      throws java.lang.ArrayIndexOutOfBoundsException
    MethodParameters:
      Name                           Flags
      i                              final

  public int hashCode();
    descriptor: ()I
    flags: (0x0001) ACC_PUBLIC
    Code:
      stack=2, locals=1, args_size=1
         0: getstatic     #61                 // Field scala/util/hashing/MurmurHash3$.MODULE$:Lscala/util/hashing/MurmurHash3$;
         3: aload_0
         4: invokevirtual #49                 // Method unsafeArray:()[C
         7: invokevirtual #65                 // Method scala/util/hashing/MurmurHash3$.arraySeqHash$mCc$sp:([C)I
        10: ireturn
      LineNumberTable:
        line 444: 0
      LocalVariableTable:
        Start  Length  Slot  Name   Signature
            0      11     0  this   Lscala/collection/immutable/ArraySeq$ofChar;

  public boolean equals(java.lang.Object);
    descriptor: (Ljava/lang/Object;)Z
    flags: (0x0001) ACC_PUBLIC
    Code:
      stack=2, locals=4, args_size=2
         0: aload_1
         1: instanceof    #2                  // class scala/collection/immutable/ArraySeq$ofChar
         4: ifeq          27
         7: aload_1
         8: checkcast     #2                  // class scala/collection/immutable/ArraySeq$ofChar
        11: astore_3
        12: aload_0
        13: invokevirtual #49                 // Method unsafeArray:()[C
        16: aload_3
        17: invokevirtual #49                 // Method unsafeArray:()[C
        20: invokestatic  #73                 // Method java/util/Arrays.equals:([C[C)Z
        23: istore_2
        24: goto          33
        27: aload_0
        28: aload_1
        29: invokestatic  #79                 // InterfaceMethod scala/collection/Seq.equals$:(Lscala/collection/Seq;Ljava/lang/Object;)Z
        32: istore_2
        33: iload_2
        34: ireturn
      StackMapTable: number_of_entries = 2
        frame_type = 27 /* same */
        frame_type = 252 /* append */
          offset_delta = 5
          locals = [ int ]
      LineNumberTable:
        line 446: 0
        line 447: 27
        line 445: 33
      LocalVariableTable:
        Start  Length  Slot  Name   Signature
            0      35     0  this   Lscala/collection/immutable/ArraySeq$ofChar;
            0      35     1  that   Ljava/lang/Object;
    MethodParameters:
      Name                           Flags
      that                           final

  public <B extends java.lang.Object> scala.collection.immutable.ArraySeq<java.lang.Object> sorted(scala.math.Ordering<B>);
    descriptor: (Lscala/math/Ordering;)Lscala/collection/immutable/ArraySeq;
    flags: (0x0001) ACC_PUBLIC
    Code:
      stack=3, locals=3, args_size=2
         0: aload_0
         1: invokevirtual #49                 // Method unsafeArray:()[C
         4: arraylength
         5: iconst_1
         6: if_icmpgt     11
         9: aload_0
        10: areturn
        11: aload_1
        12: getstatic     #87                 // Field scala/math/Ordering$Char$.MODULE$:Lscala/math/Ordering$Char$;
        15: if_acmpne     42
        18: aload_0
        19: invokevirtual #49                 // Method unsafeArray:()[C
        22: invokevirtual #92                 // Method "[C".clone:()Ljava/lang/Object;
        25: checkcast     #88                 // class "[C"
        28: astore_2
        29: aload_2
        30: invokestatic  #96                 // Method java/util/Arrays.sort:([C)V
        33: new           #2                  // class scala/collection/immutable/ArraySeq$ofChar
        36: dup
        37: aload_2
        38: invokespecial #99                 // Method "<init>":([C)V
        41: areturn
        42: aload_0
        43: aload_1
        44: invokespecial #101                // Method scala/collection/immutable/ArraySeq.sorted:(Lscala/math/Ordering;)Lscala/collection/immutable/ArraySeq;
        47: areturn
      StackMapTable: number_of_entries = 2
        frame_type = 11 /* same */
        frame_type = 30 /* same */
      LineNumberTable:
        line 441: 0
        line 450: 5
        line 451: 11
        line 452: 18
        line 453: 29
        line 454: 33
        line 455: 42
      LocalVariableTable:
        Start  Length  Slot  Name   Signature
           29      12     2     a   [C
            0      48     0  this   Lscala/collection/immutable/ArraySeq$ofChar;
            0      48     1   ord   Lscala/math/Ordering;
    Signature: #83                          // <B:Ljava/lang/Object;>(Lscala/math/Ordering<TB;>;)Lscala/collection/immutable/ArraySeq<Ljava/lang/Object;>;
    MethodParameters:
      Name                           Flags
      ord                            final

  public scala.collection.Iterator<java.lang.Object> iterator();
    descriptor: ()Lscala/collection/Iterator;
    flags: (0x0001) ACC_PUBLIC
    Code:
      stack=3, locals=1, args_size=1
         0: new           #108                // class scala/collection/ArrayOps$ArrayIterator$mcC$sp
         3: dup
         4: aload_0
         5: invokevirtual #49                 // Method unsafeArray:()[C
         8: invokespecial #109                // Method scala/collection/ArrayOps$ArrayIterator$mcC$sp."<init>":([C)V
        11: areturn
      LineNumberTable:
        line 456: 0
      LocalVariableTable:
        Start  Length  Slot  Name   Signature
            0      12     0  this   Lscala/collection/immutable/ArraySeq$ofChar;
    Signature: #106                         // ()Lscala/collection/Iterator<Ljava/lang/Object;>;

  public <S extends scala.collection.Stepper<?>> S stepper(scala.collection.StepperShape<java.lang.Object, S>);
    descriptor: (Lscala/collection/StepperShape;)Lscala/collection/Stepper;
    flags: (0x0001) ACC_PUBLIC
    Code:
      stack=5, locals=3, args_size=2
         0: aload_1
         1: invokeinterface #117,  1          // InterfaceMethod scala/collection/StepperShape.shape:()I
         6: getstatic     #122                // Field scala/collection/StepperShape$.MODULE$:Lscala/collection/StepperShape$;
         9: invokevirtual #125                // Method scala/collection/StepperShape$.ReferenceShape:()I
        12: if_icmpne     50
        15: getstatic     #130                // Field scala/collection/AnyStepper$.MODULE$:Lscala/collection/AnyStepper$;
        18: pop
        19: new           #132                // class scala/collection/convert/impl/WidenedCharArrayStepper
        22: dup
        23: aload_0
        24: invokevirtual #49                 // Method unsafeArray:()[C
        27: iconst_0
        28: aload_0
        29: invokevirtual #49                 // Method unsafeArray:()[C
        32: arraylength
        33: invokespecial #135                // Method scala/collection/convert/impl/WidenedCharArrayStepper."<init>":([CII)V
        36: astore_2
        37: new           #8                  // class scala/collection/AnyStepper$$anon$4
        40: dup
        41: aload_2
        42: invokespecial #138                // Method scala/collection/AnyStepper$$anon$4."<init>":(Lscala/collection/IntStepper;)V
        45: aconst_null
        46: astore_2
        47: goto          67
        50: new           #132                // class scala/collection/convert/impl/WidenedCharArrayStepper
        53: dup
        54: aload_0
        55: invokevirtual #49                 // Method unsafeArray:()[C
        58: iconst_0
        59: aload_0
        60: invokevirtual #49                 // Method unsafeArray:()[C
        63: arraylength
        64: invokespecial #135                // Method scala/collection/convert/impl/WidenedCharArrayStepper."<init>":([CII)V
        67: checkcast     #140                // class scala/collection/Stepper
        70: areturn
      StackMapTable: number_of_entries = 2
        frame_type = 50 /* same */
        frame_type = 80 /* same_locals_1_stack_item */
          stack = [ class java/lang/Object ]
      LineNumberTable:
        line 458: 0
        line 459: 15
        line 460: 50
      LocalVariableTable:
        Start  Length  Slot  Name   Signature
            0      71     0  this   Lscala/collection/immutable/ArraySeq$ofChar;
            0      71     1 shape   Lscala/collection/StepperShape;
           37       8     2 ofParIntStepper_st   Lscala/collection/IntStepper;
    Signature: #112                         // <S::Lscala/collection/Stepper<*>;>(Lscala/collection/StepperShape<Ljava/lang/Object;TS;>;)TS;
    MethodParameters:
      Name                           Flags
      shape                          final

  public <B extends java.lang.Object> scala.collection.immutable.ArraySeq<B> updated(int, B);
    descriptor: (ILjava/lang/Object;)Lscala/collection/immutable/ArraySeq;
    flags: (0x0001) ACC_PUBLIC
    Code:
      stack=7, locals=5, args_size=3
         0: aload_2
         1: instanceof    #152                // class java/lang/Character
         4: ifeq          49
         7: aload_2
         8: invokestatic  #158                // Method scala/runtime/BoxesRunTime.unboxToChar:(Ljava/lang/Object;)C
        11: istore        4
        13: new           #2                  // class scala/collection/immutable/ArraySeq$ofChar
        16: dup
        17: getstatic     #163                // Field scala/collection/ArrayOps$.MODULE$:Lscala/collection/ArrayOps$;
        20: aload_0
        21: invokevirtual #49                 // Method unsafeArray:()[C
        24: iload_1
        25: iload         4
        27: invokestatic  #167                // Method java/lang/Character.valueOf:(C)Ljava/lang/Character;
        30: getstatic     #42                 // Field scala/reflect/ClassTag$.MODULE$:Lscala/reflect/ClassTag$;
        33: invokevirtual #45                 // Method scala/reflect/ClassTag$.Char:()Lscala/reflect/ManifestFactory$CharManifest;
        36: invokevirtual #171                // Method scala/collection/ArrayOps$.updated$extension:(Ljava/lang/Object;ILjava/lang/Object;Lscala/reflect/ClassTag;)Ljava/lang/Object;
        39: checkcast     #88                 // class "[C"
        42: invokespecial #99                 // Method "<init>":([C)V
        45: astore_3
        46: goto          56
        49: aload_0
        50: iload_1
        51: aload_2
        52: invokespecial #173                // Method scala/collection/immutable/ArraySeq.updated:(ILjava/lang/Object;)Lscala/collection/immutable/ArraySeq;
        55: astore_3
        56: aload_3
        57: areturn
      StackMapTable: number_of_entries = 2
        frame_type = 49 /* same */
        frame_type = 252 /* append */
          offset_delta = 6
          locals = [ class scala/collection/immutable/ArraySeq ]
      LineNumberTable:
        line 464: 0
        line 465: 49
        line 463: 56
      LocalVariableTable:
        Start  Length  Slot  Name   Signature
            0      58     0  this   Lscala/collection/immutable/ArraySeq$ofChar;
            0      58     1 index   I
            0      58     2  elem   Ljava/lang/Object;
    Signature: #148                         // <B:Ljava/lang/Object;>(ITB;)Lscala/collection/immutable/ArraySeq<TB;>;
    MethodParameters:
      Name                           Flags
      index                          final
      elem                           final

  public <B extends java.lang.Object> scala.collection.immutable.ArraySeq<B> appended(B);
    descriptor: (Ljava/lang/Object;)Lscala/collection/immutable/ArraySeq;
    flags: (0x0001) ACC_PUBLIC
    Code:
      stack=6, locals=4, args_size=2
         0: aload_1
         1: instanceof    #152                // class java/lang/Character
         4: ifeq          46
         7: aload_1
         8: invokestatic  #158                // Method scala/runtime/BoxesRunTime.unboxToChar:(Ljava/lang/Object;)C
        11: istore_3
        12: new           #2                  // class scala/collection/immutable/ArraySeq$ofChar
        15: dup
        16: getstatic     #163                // Field scala/collection/ArrayOps$.MODULE$:Lscala/collection/ArrayOps$;
        19: aload_0
        20: invokevirtual #49                 // Method unsafeArray:()[C
        23: iload_3
        24: invokestatic  #167                // Method java/lang/Character.valueOf:(C)Ljava/lang/Character;
        27: getstatic     #42                 // Field scala/reflect/ClassTag$.MODULE$:Lscala/reflect/ClassTag$;
        30: invokevirtual #45                 // Method scala/reflect/ClassTag$.Char:()Lscala/reflect/ManifestFactory$CharManifest;
        33: invokevirtual #180                // Method scala/collection/ArrayOps$.appended$extension:(Ljava/lang/Object;Ljava/lang/Object;Lscala/reflect/ClassTag;)Ljava/lang/Object;
        36: checkcast     #88                 // class "[C"
        39: invokespecial #99                 // Method "<init>":([C)V
        42: astore_2
        43: goto          52
        46: aload_0
        47: aload_1
        48: invokespecial #182                // Method scala/collection/immutable/ArraySeq.appended:(Ljava/lang/Object;)Lscala/collection/immutable/ArraySeq;
        51: astore_2
        52: aload_2
        53: areturn
      StackMapTable: number_of_entries = 2
        frame_type = 46 /* same */
        frame_type = 252 /* append */
          offset_delta = 5
          locals = [ class scala/collection/immutable/ArraySeq ]
      LineNumberTable:
        line 469: 0
        line 470: 46
        line 468: 52
      LocalVariableTable:
        Start  Length  Slot  Name   Signature
            0      54     0  this   Lscala/collection/immutable/ArraySeq$ofChar;
            0      54     1  elem   Ljava/lang/Object;
    Signature: #176                         // <B:Ljava/lang/Object;>(TB;)Lscala/collection/immutable/ArraySeq<TB;>;
    MethodParameters:
      Name                           Flags
      elem                           final

  public <B extends java.lang.Object> scala.collection.immutable.ArraySeq<B> prepended(B);
    descriptor: (Ljava/lang/Object;)Lscala/collection/immutable/ArraySeq;
    flags: (0x0001) ACC_PUBLIC
    Code:
      stack=6, locals=4, args_size=2
         0: aload_1
         1: instanceof    #152                // class java/lang/Character
         4: ifeq          46
         7: aload_1
         8: invokestatic  #158                // Method scala/runtime/BoxesRunTime.unboxToChar:(Ljava/lang/Object;)C
        11: istore_3
        12: new           #2                  // class scala/collection/immutable/ArraySeq$ofChar
        15: dup
        16: getstatic     #163                // Field scala/collection/ArrayOps$.MODULE$:Lscala/collection/ArrayOps$;
        19: aload_0
        20: invokevirtual #49                 // Method unsafeArray:()[C
        23: iload_3
        24: invokestatic  #167                // Method java/lang/Character.valueOf:(C)Ljava/lang/Character;
        27: getstatic     #42                 // Field scala/reflect/ClassTag$.MODULE$:Lscala/reflect/ClassTag$;
        30: invokevirtual #45                 // Method scala/reflect/ClassTag$.Char:()Lscala/reflect/ManifestFactory$CharManifest;
        33: invokevirtual #186                // Method scala/collection/ArrayOps$.prepended$extension:(Ljava/lang/Object;Ljava/lang/Object;Lscala/reflect/ClassTag;)Ljava/lang/Object;
        36: checkcast     #88                 // class "[C"
        39: invokespecial #99                 // Method "<init>":([C)V
        42: astore_2
        43: goto          52
        46: aload_0
        47: aload_1
        48: invokespecial #188                // Method scala/collection/immutable/ArraySeq.prepended:(Ljava/lang/Object;)Lscala/collection/immutable/ArraySeq;
        51: astore_2
        52: aload_2
        53: areturn
      StackMapTable: number_of_entries = 2
        frame_type = 46 /* same */
        frame_type = 252 /* append */
          offset_delta = 5
          locals = [ class scala/collection/immutable/ArraySeq ]
      LineNumberTable:
        line 474: 0
        line 475: 46
        line 473: 52
      LocalVariableTable:
        Start  Length  Slot  Name   Signature
            0      54     0  this   Lscala/collection/immutable/ArraySeq$ofChar;
            0      54     1  elem   Ljava/lang/Object;
    Signature: #176                         // <B:Ljava/lang/Object;>(TB;)Lscala/collection/immutable/ArraySeq<TB;>;
    MethodParameters:
      Name                           Flags
      elem                           final

  public scala.collection.mutable.StringBuilder addString(scala.collection.mutable.StringBuilder, java.lang.String, java.lang.String, java.lang.String);
    descriptor: (Lscala/collection/mutable/StringBuilder;Ljava/lang/String;Ljava/lang/String;Ljava/lang/String;)Lscala/collection/mutable/StringBuilder;
    flags: (0x0001) ACC_PUBLIC
    Code:
      stack=5, locals=5, args_size=5
         0: new           #11                 // class scala/collection/mutable/ArraySeq$ofChar
         3: dup
         4: aload_0
         5: invokevirtual #49                 // Method unsafeArray:()[C
         8: invokespecial #195                // Method scala/collection/mutable/ArraySeq$ofChar."<init>":([C)V
        11: aload_1
        12: aload_2
        13: aload_3
        14: aload         4
        16: invokevirtual #197                // Method scala/collection/mutable/ArraySeq$ofChar.addString:(Lscala/collection/mutable/StringBuilder;Ljava/lang/String;Ljava/lang/String;Ljava/lang/String;)Lscala/collection/mutable/StringBuilder;
        19: areturn
      LineNumberTable:
        line 479: 0
      LocalVariableTable:
        Start  Length  Slot  Name   Signature
            0      20     0  this   Lscala/collection/immutable/ArraySeq$ofChar;
            0      20     1    sb   Lscala/collection/mutable/StringBuilder;
            0      20     2 start   Ljava/lang/String;
            0      20     3   sep   Ljava/lang/String;
            0      20     4   end   Ljava/lang/String;
    MethodParameters:
      Name                           Flags
      sb                             final
      start                          final
      sep                            final
      end                            final

  public java.lang.Object prepended(java.lang.Object);
    descriptor: (Ljava/lang/Object;)Ljava/lang/Object;
    flags: (0x1041) ACC_PUBLIC, ACC_BRIDGE, ACC_SYNTHETIC
    Code:
      stack=2, locals=2, args_size=2
         0: aload_0
         1: aload_1
         2: invokevirtual #201                // Method prepended:(Ljava/lang/Object;)Lscala/collection/immutable/ArraySeq;
         5: areturn
      LineNumberTable:
        line 439: 0
      LocalVariableTable:
        Start  Length  Slot  Name   Signature
            0       6     0  this   Lscala/collection/immutable/ArraySeq$ofChar;
            0       6     1  elem   Ljava/lang/Object;
    MethodParameters:
      Name                           Flags
      elem                           final

  public java.lang.Object appended(java.lang.Object);
    descriptor: (Ljava/lang/Object;)Ljava/lang/Object;
    flags: (0x1041) ACC_PUBLIC, ACC_BRIDGE, ACC_SYNTHETIC
    Code:
      stack=2, locals=2, args_size=2
         0: aload_0
         1: aload_1
         2: invokevirtual #202                // Method appended:(Ljava/lang/Object;)Lscala/collection/immutable/ArraySeq;
         5: areturn
      LineNumberTable:
        line 439: 0
      LocalVariableTable:
        Start  Length  Slot  Name   Signature
            0       6     0  this   Lscala/collection/immutable/ArraySeq$ofChar;
            0       6     1  elem   Ljava/lang/Object;
    MethodParameters:
      Name                           Flags
      elem                           final

  public java.lang.Object updated(int, java.lang.Object);
    descriptor: (ILjava/lang/Object;)Ljava/lang/Object;
    flags: (0x1041) ACC_PUBLIC, ACC_BRIDGE, ACC_SYNTHETIC
    Code:
      stack=3, locals=3, args_size=3
         0: aload_0
         1: iload_1
         2: aload_2
         3: invokevirtual #204                // Method updated:(ILjava/lang/Object;)Lscala/collection/immutable/ArraySeq;
         6: areturn
      LineNumberTable:
        line 439: 0
      LocalVariableTable:
        Start  Length  Slot  Name   Signature
            0       7     0  this   Lscala/collection/immutable/ArraySeq$ofChar;
            0       7     1 index   I
            0       7     2  elem   Ljava/lang/Object;
    MethodParameters:
      Name                           Flags
      index                          final
      elem                           final

  public java.lang.Object sorted(scala.math.Ordering);
    descriptor: (Lscala/math/Ordering;)Ljava/lang/Object;
    flags: (0x1041) ACC_PUBLIC, ACC_BRIDGE, ACC_SYNTHETIC
    Code:
      stack=2, locals=2, args_size=2
         0: aload_0
         1: aload_1
         2: invokevirtual #206                // Method sorted:(Lscala/math/Ordering;)Lscala/collection/immutable/ArraySeq;
         5: areturn
      LineNumberTable:
        line 439: 0
      LocalVariableTable:
        Start  Length  Slot  Name   Signature
            0       6     0  this   Lscala/collection/immutable/ArraySeq$ofChar;
            0       6     1   ord   Lscala/math/Ordering;
    MethodParameters:
      Name                           Flags
      ord                            final

  public java.lang.Object apply(java.lang.Object) throws java.lang.ArrayIndexOutOfBoundsException;
    descriptor: (Ljava/lang/Object;)Ljava/lang/Object;
    flags: (0x1041) ACC_PUBLIC, ACC_BRIDGE, ACC_SYNTHETIC
    Code:
      stack=2, locals=2, args_size=2
         0: aload_0
         1: aload_1
         2: invokestatic  #211                // Method scala/runtime/BoxesRunTime.unboxToInt:(Ljava/lang/Object;)I
         5: invokevirtual #213                // Method apply:(I)C
         8: invokestatic  #216                // Method scala/runtime/BoxesRunTime.boxToCharacter:(C)Ljava/lang/Character;
        11: areturn
      LineNumberTable:
        line 439: 0
      LocalVariableTable:
        Start  Length  Slot  Name   Signature
            0      12     0  this   Lscala/collection/immutable/ArraySeq$ofChar;
            0      12     1    v1   Ljava/lang/Object;
    Exceptions:
      throws java.lang.ArrayIndexOutOfBoundsException
    MethodParameters:
      Name                           Flags
      v1                             final

  public java.lang.Object apply(int) throws java.lang.ArrayIndexOutOfBoundsException;
    descriptor: (I)Ljava/lang/Object;
    flags: (0x1041) ACC_PUBLIC, ACC_BRIDGE, ACC_SYNTHETIC
    Code:
      stack=2, locals=2, args_size=2
         0: aload_0
         1: iload_1
         2: invokevirtual #213                // Method apply:(I)C
         5: invokestatic  #216                // Method scala/runtime/BoxesRunTime.boxToCharacter:(C)Ljava/lang/Character;
         8: areturn
      LineNumberTable:
        line 439: 0
      LocalVariableTable:
        Start  Length  Slot  Name   Signature
            0       9     0  this   Lscala/collection/immutable/ArraySeq$ofChar;
            0       9     1     i   I
    Exceptions:
      throws java.lang.ArrayIndexOutOfBoundsException
    MethodParameters:
      Name                           Flags
      i                              final

  public scala.reflect.ClassTag elemTag();
    descriptor: ()Lscala/reflect/ClassTag;
    flags: (0x1041) ACC_PUBLIC, ACC_BRIDGE, ACC_SYNTHETIC
    Code:
      stack=1, locals=1, args_size=1
         0: aload_0
         1: invokevirtual #220                // Method elemTag:()Lscala/reflect/ManifestFactory$CharManifest;
         4: areturn
      LineNumberTable:
        line 439: 0
      LocalVariableTable:
        Start  Length  Slot  Name   Signature
            0       5     0  this   Lscala/collection/immutable/ArraySeq$ofChar;

  public java.lang.Object unsafeArray();
    descriptor: ()Ljava/lang/Object;
    flags: (0x1041) ACC_PUBLIC, ACC_BRIDGE, ACC_SYNTHETIC
    Code:
      stack=1, locals=1, args_size=1
         0: aload_0
         1: invokevirtual #49                 // Method unsafeArray:()[C
         4: areturn
      LineNumberTable:
        line 439: 0
      LocalVariableTable:
        Start  Length  Slot  Name   Signature
            0       5     0  this   Lscala/collection/immutable/ArraySeq$ofChar;

  public scala.collection.immutable.ArraySeq$ofChar(char[]);
    descriptor: ([C)V
    flags: (0x0001) ACC_PUBLIC
    Code:
      stack=2, locals=2, args_size=2
         0: aload_0
         1: aload_1
         2: putfield      #32                 // Field unsafeArray:[C
         5: aload_0
         6: invokespecial #223                // Method scala/collection/immutable/ArraySeq."<init>":()V
         9: return
      LineNumberTable:
        line 439: 0
      LocalVariableTable:
        Start  Length  Slot  Name   Signature
            0      10     0  this   Lscala/collection/immutable/ArraySeq$ofChar;
            0      10     1 unsafeArray   [C
    MethodParameters:
      Name                           Flags
      unsafeArray                    final
}
InnerClasses:
  public final #8;                        // class scala/collection/AnyStepper$$anon$4
  public static final #9= #2 of #5;       // ofChar=class scala/collection/immutable/ArraySeq$ofChar of class scala/collection/immutable/ArraySeq
  public static final #9= #11 of #13;     // ofChar=class scala/collection/mutable/ArraySeq$ofChar of class scala/collection/mutable/ArraySeq
  public static #18= #15 of #17;          // Char$=class scala/math/Ordering$Char$ of class scala/math/Ordering
  public static final #23= #20 of #22;    // CharManifest=class scala/reflect/ManifestFactory$CharManifest of class scala/reflect/ManifestFactory
Signature: #3                           // Lscala/collection/immutable/ArraySeq<Ljava/lang/Object;>;
SourceFile: "ArraySeq.scala"
  ScalaInlineInfo: length = 0x72 (unknown attribute)
   01 01 00 16 00 61 00 5E 01 00 BD 00 BE 01 00 AE
   00 C8 01 00 AE 00 AF 01 00 32 00 33 01 00 32 00
   D9 01 00 32 00 C8 01 00 23 00 DA 01 00 23 00 24
   01 00 42 00 43 01 00 38 00 2F 01 00 68 00 69 01
   00 2E 00 2F 01 00 B7 00 C8 01 00 B7 00 AF 01 00
   51 00 CD 01 00 51 00 52 01 00 6E 00 6F 01 00 1C
   00 5A 01 00 1C 00 1E 01 00 92 00 CB 01 00 92 00
   93 01
  Scala: length = 0x0 (unknown attribute)

