Classfile /Users/mw/Projects/slang-braindump/.jar/jar8/assemble/slang-braindump/assemble/content/scala/collection/immutable/BigVector.class
  Last modified May 29, 2022; size 2831 bytes
  SHA-256 checksum 8af559bf453b2938d5659f34eadbc65111ef368cc6ccff5f668355916c4f78c7
  Compiled from "Vector.scala"
public abstract class scala.collection.immutable.BigVector<A extends java.lang.Object> extends scala.collection.immutable.VectorImpl<A>
  minor version: 0
  major version: 52
  flags: (0x0421) ACC_PUBLIC, ACC_SUPER, ACC_ABSTRACT
  this_class: #2                          // scala/collection/immutable/BigVector
  super_class: #5                         // scala/collection/immutable/VectorImpl
  interfaces: 0, fields: 2, methods: 4, attributes: 5
Constant pool:
   #1 = Utf8               scala/collection/immutable/BigVector
   #2 = Class              #1             // scala/collection/immutable/BigVector
   #3 = Utf8               <A:Ljava/lang/Object;>Lscala/collection/immutable/VectorImpl<TA;>;
   #4 = Utf8               scala/collection/immutable/VectorImpl
   #5 = Class              #4             // scala/collection/immutable/VectorImpl
   #6 = Utf8               Vector.scala
   #7 = Utf8               Lscala/reflect/ScalaSignature;
   #8 = Utf8               bytes
   #9 = Utf8               \u0006\u0005\u00054Q\u0001C\u0005\u0002*AA\u0011B\t\u0001\u0003\u0002\u0003\u0006IaI\u001a\t\u0013]\u0002!Q1A\u0005\u0002%A\u0004\u0002C\u001d\u0001\u0005\u0003\u0005\u000b\u0011B\u0012\t\u0013i\u0002!Q1A\u0005\u0002%Y\u0004\u0002C \u0001\u0005\u0003\u0005\u000b\u0011\u0002\u001f\t\u000b\u0001\u0003A\u0011A!\t\r\u0019\u0003AQC\u0005H\u0005%\u0011\u0015n\u001a,fGR|\'O\u0003\u0002\u000b\u0017\u0005I\u0011.\\7vi\u0006\u0014G.\u001a\u0006\u0003\u00195\t!bY8mY\u0016\u001cG/[8o\u0015\u0005q\u0011!B:dC2\f7\u0001A\u000b\u0003#a\u0019\"\u0001\u0001\n\u0011\u0007M!b#D\u0001\n\u0013\t)\u0012B\u0001\u0006WK\u000e$xN]%na2\u0004\"a\u0006\r\r\u0001\u00111\u0011\u0004\u0001CC\u0002i\u0011\u0011!Q\t\u00037}\u0001\"\u0001H\u000f\u000e\u00035I!AH\u0007\u0003\u000f9{G\u000f[5oOB\u0011A\u0004I\u0005\u0003C5\u00111!\u00118z\u0003!y\u0006O]3gSb\f\u0004C\u0001\u00131\u001d\t)cF\u0004\u0002\'[9\u0011q\u0005\f\b\u0003Q-j\u0011!\u000b\u0006\u0003U=\ta\u0001\u0010:p_Rt\u0014\"\u0001\b\n\u00051i\u0011B\u0001\u0006\f\u0013\ty\u0013\"\u0001\u0007WK\u000e$xN]%oY&tW-\u0003\u00022e\t!\u0011I\u001d:2\u0015\ty\u0013\"\u0003\u00025k\u00059\u0001O]3gSb\f\u0014B\u0001\u001c\n\u0005\u00191Vm\u0019;pe\u000691/\u001e4gSb\fT#A\u0012\u0002\u0011M,hMZ5yc\u0001\nq\u0001\\3oORD\u0007\'F\u0001=!\taR(\u0003\u0002?\u001b\t\u0019\u0011J\u001c;\u0002\u00111,gn\u001a;ia\u0001\na\u0001P5oSRtD\u0003\u0002\"D\t\u0016\u00032a\u0005\u0001\u0017\u0011\u0015\u0011c\u00011\u0001$\u0011\u00159d\u00011\u0001$\u0011\u0015Qd\u00011\u0001=\u0003-1wN]3bG\"\u0014Vm\u001d;\u0016\u0005!\u0013FCA%M!\ta\"*\u0003\u0002L\u001b\t!QK\\5u\u0011\u0015iu\u00011\u0001O\u0003\u00051\u0007\u0003\u0002\u000fP-EK!\u0001U\u0007\u0003\u0013\u0019+hn\u0019;j_:\f\u0004CA\fS\t\u0015\u0019vA1\u0001\u001b\u0005\u0005)\u0016f\u0002\u0001V/f[Vl\u0018\u0006\u0003-&\tqAV3di>\u0014\b\'\u0003\u0002Y\u0013\t9a+Z2u_J\u0014\u0014B\u0001.\n\u0005\u001d1Vm\u0019;peNJ!\u0001X\u0005\u0003\u000fY+7\r^8si%\u0011a,\u0003\u0002\b-\u0016\u001cGo\u001c:6\u0013\t\u0001\u0017BA\u0004WK\u000e$xN\u001d\u001c
  #10 = Utf8               suffix1
  #11 = Utf8               [Ljava/lang/Object;
  #12 = Utf8               length0
  #13 = Utf8               I
  #14 = Utf8               ()[Ljava/lang/Object;
  #15 = NameAndType        #10:#11        // suffix1:[Ljava/lang/Object;
  #16 = Fieldref           #2.#15         // scala/collection/immutable/BigVector.suffix1:[Ljava/lang/Object;
  #17 = Utf8               this
  #18 = Utf8               Lscala/collection/immutable/BigVector;
  #19 = Utf8               ()I
  #20 = NameAndType        #12:#13        // length0:I
  #21 = Fieldref           #2.#20         // scala/collection/immutable/BigVector.length0:I
  #22 = Utf8               foreachRest
  #23 = Utf8               (Lscala/Function1;)V
  #24 = Utf8               <U:Ljava/lang/Object;>(Lscala/Function1<TA;TU;>;)V
  #25 = Utf8               f
  #26 = Utf8               vectorSliceCount
  #27 = NameAndType        #26:#19        // vectorSliceCount:()I
  #28 = Methodref          #2.#27         // scala/collection/immutable/BigVector.vectorSliceCount:()I
  #29 = Utf8               scala/collection/immutable/VectorStatics$
  #30 = Class              #29            // scala/collection/immutable/VectorStatics$
  #31 = Utf8               MODULE$
  #32 = Utf8               Lscala/collection/immutable/VectorStatics$;
  #33 = NameAndType        #31:#32        // MODULE$:Lscala/collection/immutable/VectorStatics$;
  #34 = Fieldref           #30.#33        // scala/collection/immutable/VectorStatics$.MODULE$:Lscala/collection/immutable/VectorStatics$;
  #35 = Utf8               scala/collection/immutable/VectorInline$
  #36 = Class              #35            // scala/collection/immutable/VectorInline$
  #37 = Utf8               Lscala/collection/immutable/VectorInline$;
  #38 = NameAndType        #31:#37        // MODULE$:Lscala/collection/immutable/VectorInline$;
  #39 = Fieldref           #36.#38        // scala/collection/immutable/VectorInline$.MODULE$:Lscala/collection/immutable/VectorInline$;
  #40 = Utf8               java/lang/Math
  #41 = Class              #40            // java/lang/Math
  #42 = Utf8               abs
  #43 = Utf8               (I)I
  #44 = NameAndType        #42:#43        // abs:(I)I
  #45 = Methodref          #41.#44        // java/lang/Math.abs:(I)I
  #46 = Utf8               vectorSlice
  #47 = Utf8               (I)[Ljava/lang/Object;
  #48 = NameAndType        #46:#47        // vectorSlice:(I)[Ljava/lang/Object;
  #49 = Methodref          #2.#48         // scala/collection/immutable/BigVector.vectorSlice:(I)[Ljava/lang/Object;
  #50 = Utf8               scala/Function1
  #51 = Class              #50            // scala/Function1
  #52 = Utf8               apply
  #53 = Utf8               (Ljava/lang/Object;)Ljava/lang/Object;
  #54 = NameAndType        #52:#53        // apply:(Ljava/lang/Object;)Ljava/lang/Object;
  #55 = InterfaceMethodref #51.#54        // scala/Function1.apply:(Ljava/lang/Object;)Ljava/lang/Object;
  #56 = Class              #11            // "[Ljava/lang/Object;"
  #57 = Utf8               foreachRec
  #58 = Utf8               (I[Ljava/lang/Object;Lscala/Function1;)V
  #59 = NameAndType        #57:#58        // foreachRec:(I[Ljava/lang/Object;Lscala/Function1;)V
  #60 = Methodref          #30.#59        // scala/collection/immutable/VectorStatics$.foreachRec:(I[Ljava/lang/Object;Lscala/Function1;)V
  #61 = Utf8               c
  #62 = Utf8               i
  #63 = Utf8               Lscala/Function1;
  #64 = Utf8               vectorSliceDim_c
  #65 = Utf8               foreachRec_l
  #66 = Utf8               foreachRec_i
  #67 = Utf8               foreachRec_len
  #68 = Utf8               foreachRec_this
  #69 = Utf8               foreachRec_level
  #70 = Utf8               foreachRec_a
  #71 = Utf8               <init>
  #72 = Utf8               ([Ljava/lang/Object;[Ljava/lang/Object;I)V
  #73 = Utf8               _prefix1
  #74 = Utf8               ([Ljava/lang/Object;)V
  #75 = NameAndType        #71:#74        // "<init>":([Ljava/lang/Object;)V
  #76 = Methodref          #5.#75         // scala/collection/immutable/VectorImpl."<init>":([Ljava/lang/Object;)V
  #77 = Utf8               Code
  #78 = Utf8               LineNumberTable
  #79 = Utf8               LocalVariableTable
  #80 = Utf8               StackMapTable
  #81 = Utf8               Signature
  #82 = Utf8               MethodParameters
  #83 = Utf8               SourceFile
  #84 = Utf8               RuntimeVisibleAnnotations
  #85 = Utf8               ScalaInlineInfo
  #86 = Utf8               ScalaSig
{
  private final java.lang.Object[] suffix1;
    descriptor: [Ljava/lang/Object;
    flags: (0x0012) ACC_PRIVATE, ACC_FINAL

  private final int length0;
    descriptor: I
    flags: (0x0012) ACC_PRIVATE, ACC_FINAL

  public java.lang.Object[] suffix1();
    descriptor: ()[Ljava/lang/Object;
    flags: (0x0001) ACC_PUBLIC
    Code:
      stack=1, locals=1, args_size=1
         0: aload_0
         1: getfield      #16                 // Field suffix1:[Ljava/lang/Object;
         4: areturn
      LineNumberTable:
        line 320: 0
      LocalVariableTable:
        Start  Length  Slot  Name   Signature
            0       5     0  this   Lscala/collection/immutable/BigVector;

  public int length0();
    descriptor: ()I
    flags: (0x0001) ACC_PUBLIC
    Code:
      stack=1, locals=1, args_size=1
         0: aload_0
         1: getfield      #21                 // Field length0:I
         4: ireturn
      LineNumberTable:
        line 320: 0
      LocalVariableTable:
        Start  Length  Slot  Name   Signature
            0       5     0  this   Lscala/collection/immutable/BigVector;

  public final <U extends java.lang.Object> void foreachRest(scala.Function1<A, U>);
    descriptor: (Lscala/Function1;)V
    flags: (0x0011) ACC_PUBLIC, ACC_FINAL
    Code:
      stack=4, locals=11, args_size=2
         0: aload_0
         1: invokevirtual #28                 // Method vectorSliceCount:()I
         4: istore_2
         5: iconst_1
         6: istore_3
         7: iload_3
         8: iload_2
         9: if_icmpge     135
        12: getstatic     #34                 // Field scala/collection/immutable/VectorStatics$.MODULE$:Lscala/collection/immutable/VectorStatics$;
        15: getstatic     #39                 // Field scala/collection/immutable/VectorInline$.MODULE$:Lscala/collection/immutable/VectorInline$;
        18: pop
        19: iload_2
        20: iconst_2
        21: idiv
        22: istore        4
        24: iload         4
        26: iconst_1
        27: iadd
        28: iload_3
        29: iload         4
        31: isub
        32: invokestatic  #45                 // Method java/lang/Math.abs:(I)I
        35: isub
        36: iconst_1
        37: isub
        38: aload_0
        39: iload_3
        40: invokevirtual #49                 // Method vectorSlice:(I)[Ljava/lang/Object;
        43: astore        7
        45: istore        6
        47: astore        5
        49: iconst_0
        50: istore        8
        52: aload         7
        54: arraylength
        55: istore        9
        57: iload         6
        59: iconst_0
        60: if_icmpne     88
        63: iload         8
        65: iload         9
        67: if_icmpge     123
        70: aload_1
        71: aload         7
        73: iload         8
        75: aaload
        76: invokeinterface #55,  2           // InterfaceMethod scala/Function1.apply:(Ljava/lang/Object;)Ljava/lang/Object;
        81: pop
        82: iinc          8, 1
        85: goto          63
        88: iload         6
        90: iconst_1
        91: isub
        92: istore        10
        94: iload         8
        96: iload         9
        98: if_icmpge     123
       101: aload         5
       103: iload         10
       105: aload         7
       107: iload         8
       109: aaload
       110: checkcast     #56                 // class "[Ljava/lang/Object;"
       113: aload_1
       114: invokevirtual #60                 // Method scala/collection/immutable/VectorStatics$.foreachRec:(I[Ljava/lang/Object;Lscala/Function1;)V
       117: iinc          8, 1
       120: goto          94
       123: aconst_null
       124: astore        5
       126: aconst_null
       127: astore        7
       129: iinc          3, 1
       132: goto          7
       135: return
      StackMapTable: number_of_entries = 6
        frame_type = 253 /* append */
          offset_delta = 7
          locals = [ int, int ]
        frame_type = 255 /* full_frame */
          offset_delta = 55
          locals = [ class scala/collection/immutable/BigVector, class scala/Function1, int, int, int, class scala/collection/immutable/VectorStatics$, int, class "[Ljava/lang/Object;", int, int ]
          stack = []
        frame_type = 24 /* same */
        frame_type = 252 /* append */
          offset_delta = 5
          locals = [ int ]
        frame_type = 250 /* chop */
          offset_delta = 28
        frame_type = 255 /* full_frame */
          offset_delta = 11
          locals = [ class scala/collection/immutable/BigVector, class scala/Function1, int, int ]
          stack = []
      LineNumberTable:
        line 323: 0
        line 324: 5
        line 325: 7
        line 326: 12
        line 1749: 19
        line 1750: 24
        line 326: 36
        line 1852: 49
        line 1853: 52
        line 1854: 57
        line 1855: 63
        line 1856: 70
        line 1857: 82
        line 1855: 85
        line 1860: 88
        line 1861: 94
        line 1862: 101
        line 1863: 117
        line 1861: 120
        line 327: 129
        line 325: 132
      LocalVariableTable:
        Start  Length  Slot  Name   Signature
            5     130     2     c   I
            7     128     3     i   I
            0     136     0  this   Lscala/collection/immutable/BigVector;
            0     136     1     f   Lscala/Function1;
           24      12     4 vectorSliceDim_c   I
           94      29    10 foreachRec_l   I
           52      71     8 foreachRec_i   I
           57      66     9 foreachRec_len   I
           49      74     5 foreachRec_this   Lscala/collection/immutable/VectorStatics$;
           49      74     6 foreachRec_level   I
           49      74     7 foreachRec_a   [Ljava/lang/Object;
    Signature: #24                          // <U:Ljava/lang/Object;>(Lscala/Function1<TA;TU;>;)V
    MethodParameters:
      Name                           Flags
      f                              final

  public scala.collection.immutable.BigVector(java.lang.Object[], java.lang.Object[], int);
    descriptor: ([Ljava/lang/Object;[Ljava/lang/Object;I)V
    flags: (0x0001) ACC_PUBLIC
    Code:
      stack=2, locals=4, args_size=4
         0: aload_0
         1: aload_2
         2: putfield      #16                 // Field suffix1:[Ljava/lang/Object;
         5: aload_0
         6: iload_3
         7: putfield      #21                 // Field length0:I
        10: aload_0
        11: aload_1
        12: invokespecial #76                 // Method scala/collection/immutable/VectorImpl."<init>":([Ljava/lang/Object;)V
        15: return
      LineNumberTable:
        line 320: 0
      LocalVariableTable:
        Start  Length  Slot  Name   Signature
            0      16     0  this   Lscala/collection/immutable/BigVector;
            0      16     1 _prefix1   [Ljava/lang/Object;
            0      16     2 suffix1   [Ljava/lang/Object;
            0      16     3 length0   I
    MethodParameters:
      Name                           Flags
      _prefix1                       final
      suffix1                        final
      length0                        final
}
Signature: #3                           // <A:Ljava/lang/Object;>Lscala/collection/immutable/VectorImpl<TA;>;
SourceFile: "Vector.scala"
RuntimeVisibleAnnotations:
  0: #7(#8=s#9)
    scala.reflect.ScalaSignature(
      bytes="\u0006\u0005\u00054Q\u0001C\u0005\u0002*AA\u0011B\t\u0001\u0003\u0002\u0003\u0006IaI\u001a\t\u0013]\u0002!Q1A\u0005\u0002%A\u0004\u0002C\u001d\u0001\u0005\u0003\u0005\u000b\u0011B\u0012\t\u0013i\u0002!Q1A\u0005\u0002%Y\u0004\u0002C \u0001\u0005\u0003\u0005\u000b\u0011\u0002\u001f\t\u000b\u0001\u0003A\u0011A!\t\r\u0019\u0003AQC\u0005H\u0005%\u0011\u0015n\u001a,fGR|\'O\u0003\u0002\u000b\u0017\u0005I\u0011.\\7vi\u0006\u0014G.\u001a\u0006\u0003\u00195\t!bY8mY\u0016\u001cG/[8o\u0015\u0005q\u0011!B:dC2\f7\u0001A\u000b\u0003#a\u0019\"\u0001\u0001\n\u0011\u0007M!b#D\u0001\n\u0013\t)\u0012B\u0001\u0006WK\u000e$xN]%na2\u0004\"a\u0006\r\r\u0001\u00111\u0011\u0004\u0001CC\u0002i\u0011\u0011!Q\t\u00037}\u0001\"\u0001H\u000f\u000e\u00035I!AH\u0007\u0003\u000f9{G\u000f[5oOB\u0011A\u0004I\u0005\u0003C5\u00111!\u00118z\u0003!y\u0006O]3gSb\f\u0004C\u0001\u00131\u001d\t)cF\u0004\u0002\'[9\u0011q\u0005\f\b\u0003Q-j\u0011!\u000b\u0006\u0003U=\ta\u0001\u0010:p_Rt\u0014\"\u0001\b\n\u00051i\u0011B\u0001\u0006\f\u0013\ty\u0013\"\u0001\u0007WK\u000e$xN]%oY&tW-\u0003\u00022e\t!\u0011I\u001d:2\u0015\ty\u0013\"\u0003\u00025k\u00059\u0001O]3gSb\f\u0014B\u0001\u001c\n\u0005\u00191Vm\u0019;pe\u000691/\u001e4gSb\fT#A\u0012\u0002\u0011M,hMZ5yc\u0001\nq\u0001\\3oORD\u0007\'F\u0001=!\taR(\u0003\u0002?\u001b\t\u0019\u0011J\u001c;\u0002\u00111,gn\u001a;ia\u0001\na\u0001P5oSRtD\u0003\u0002\"D\t\u0016\u00032a\u0005\u0001\u0017\u0011\u0015\u0011c\u00011\u0001$\u0011\u00159d\u00011\u0001$\u0011\u0015Qd\u00011\u0001=\u0003-1wN]3bG\"\u0014Vm\u001d;\u0016\u0005!\u0013FCA%M!\ta\"*\u0003\u0002L\u001b\t!QK\\5u\u0011\u0015iu\u00011\u0001O\u0003\u00051\u0007\u0003\u0002\u000fP-EK!\u0001U\u0007\u0003\u0013\u0019+hn\u0019;j_:\f\u0004CA\fS\t\u0015\u0019vA1\u0001\u001b\u0005\u0005)\u0016f\u0002\u0001V/f[Vl\u0018\u0006\u0003-&\tqAV3di>\u0014\b\'\u0003\u0002Y\u0013\t9a+Z2u_J\u0014\u0014B\u0001.\n\u0005\u001d1Vm\u0019;peNJ!\u0001X\u0005\u0003\u000fY+7\r^8si%\u0011a,\u0003\u0002\b-\u0016\u001cGo\u001c:6\u0013\t\u0001\u0017BA\u0004WK\u000e$xN\u001d\u001c"
    )
  ScalaInlineInfo: length = 0x18 (unknown attribute)
   01 00 00 04 00 47 00 48 01 00 16 00 17 01 00 0C
   00 13 01 00 0A 00 0E 01
  ScalaSig: length = 0x3 (unknown attribute)
   05 02 00
