Classfile /Users/mw/Projects/slang-braindump/.jar/jar8/assemble/slang-braindump/assemble/content/scala/collection/immutable/BitSet$.class
  Last modified May 29, 2022; size 5440 bytes
  SHA-256 checksum b02e638b490ff8e7961c430bbd86a3e04b9a931f99c51d489afe5e24544606a9
  Compiled from "BitSet.scala"
public final class scala.collection.immutable.BitSet$ extends java.lang.Object implements scala.collection.SpecificIterableFactory<java.lang.Object, scala.collection.immutable.BitSet>, java.io.Serializable
  minor version: 0
  major version: 52
  flags: (0x0031) ACC_PUBLIC, ACC_FINAL, ACC_SUPER
  this_class: #2                          // scala/collection/immutable/BitSet$
  super_class: #5                         // java/lang/Object
  interfaces: 2, fields: 3, methods: 16, attributes: 6
Constant pool:
    #1 = Utf8               scala/collection/immutable/BitSet$
    #2 = Class              #1            // scala/collection/immutable/BitSet$
    #3 = Utf8               Ljava/lang/Object;Lscala/collection/SpecificIterableFactory<Ljava/lang/Object;Lscala/collection/immutable/BitSet;>;Ljava/io/Serializable;
    #4 = Utf8               java/lang/Object
    #5 = Class              #4            // java/lang/Object
    #6 = Utf8               scala/collection/SpecificIterableFactory
    #7 = Class              #6            // scala/collection/SpecificIterableFactory
    #8 = Utf8               java/io/Serializable
    #9 = Class              #8            // java/io/Serializable
   #10 = Utf8               BitSet.scala
   #11 = Utf8               java/lang/invoke/MethodHandles$Lookup
   #12 = Class              #11           // java/lang/invoke/MethodHandles$Lookup
   #13 = Utf8               java/lang/invoke/MethodHandles
   #14 = Class              #13           // java/lang/invoke/MethodHandles
   #15 = Utf8               Lookup
   #16 = Utf8               scala/collection/immutable/BitSet$BitSet1
   #17 = Class              #16           // scala/collection/immutable/BitSet$BitSet1
   #18 = Utf8               scala/collection/immutable/BitSet
   #19 = Class              #18           // scala/collection/immutable/BitSet
   #20 = Utf8               BitSet1
   #21 = Utf8               scala/collection/immutable/BitSet$BitSet2
   #22 = Class              #21           // scala/collection/immutable/BitSet$BitSet2
   #23 = Utf8               BitSet2
   #24 = Utf8               scala/collection/immutable/BitSet$BitSetN
   #25 = Class              #24           // scala/collection/immutable/BitSet$BitSetN
   #26 = Utf8               BitSetN
   #27 = Utf8               MODULE$
   #28 = Utf8               Lscala/collection/immutable/BitSet$;
   #29 = Utf8               serialVersionUID
   #30 = Utf8               J
   #31 = Long               3l
   #33 = Utf8               empty
   #34 = Utf8               Lscala/collection/immutable/BitSet;
   #35 = Utf8               <clinit>
   #36 = Utf8               ()V
   #37 = Utf8               <init>
   #38 = NameAndType        #37:#36       // "<init>":()V
   #39 = Methodref          #2.#38        // scala/collection/immutable/BitSet$."<init>":()V
   #40 = NameAndType        #27:#28       // MODULE$:Lscala/collection/immutable/BitSet$;
   #41 = Fieldref           #2.#40        // scala/collection/immutable/BitSet$.MODULE$:Lscala/collection/immutable/BitSet$;
   #42 = Utf8               (J)V
   #43 = NameAndType        #37:#42       // "<init>":(J)V
   #44 = Methodref          #17.#43       // scala/collection/immutable/BitSet$BitSet1."<init>":(J)V
   #45 = NameAndType        #33:#34       // empty:Lscala/collection/immutable/BitSet;
   #46 = Fieldref           #2.#45        // scala/collection/immutable/BitSet$.empty:Lscala/collection/immutable/BitSet;
   #47 = Utf8               apply
   #48 = Utf8               (Lscala/collection/immutable/Seq;)Ljava/lang/Object;
   #49 = Utf8               xs
   #50 = Utf8               apply$
   #51 = Utf8               (Lscala/collection/SpecificIterableFactory;Lscala/collection/immutable/Seq;)Ljava/lang/Object;
   #52 = NameAndType        #50:#51       // apply$:(Lscala/collection/SpecificIterableFactory;Lscala/collection/immutable/Seq;)Ljava/lang/Object;
   #53 = InterfaceMethodref #7.#52        // scala/collection/SpecificIterableFactory.apply$:(Lscala/collection/SpecificIterableFactory;Lscala/collection/immutable/Seq;)Ljava/lang/Object;
   #54 = Utf8               this
   #55 = Utf8               Lscala/collection/immutable/Seq;
   #56 = Utf8               fill
   #57 = Utf8               (ILscala/Function0;)Ljava/lang/Object;
   #58 = Utf8               n
   #59 = Utf8               elem
   #60 = Utf8               fill$
   #61 = Utf8               (Lscala/collection/SpecificIterableFactory;ILscala/Function0;)Ljava/lang/Object;
   #62 = NameAndType        #60:#61       // fill$:(Lscala/collection/SpecificIterableFactory;ILscala/Function0;)Ljava/lang/Object;
   #63 = InterfaceMethodref #7.#62        // scala/collection/SpecificIterableFactory.fill$:(Lscala/collection/SpecificIterableFactory;ILscala/Function0;)Ljava/lang/Object;
   #64 = Utf8               I
   #65 = Utf8               Lscala/Function0;
   #66 = Utf8               specificIterableFactory
   #67 = Utf8               ()Lscala/collection/Factory;
   #68 = Utf8               ()Lscala/collection/Factory<Ljava/lang/Object;Lscala/collection/immutable/BitSet;>;
   #69 = Utf8               specificIterableFactory$
   #70 = Utf8               (Lscala/collection/SpecificIterableFactory;)Lscala/collection/Factory;
   #71 = NameAndType        #69:#70       // specificIterableFactory$:(Lscala/collection/SpecificIterableFactory;)Lscala/collection/Factory;
   #72 = InterfaceMethodref #7.#71        // scala/collection/SpecificIterableFactory.specificIterableFactory$:(Lscala/collection/SpecificIterableFactory;)Lscala/collection/Factory;
   #73 = Utf8               fromSpecific
   #74 = Utf8               (Lscala/collection/IterableOnce;)Lscala/collection/immutable/BitSet;
   #75 = Utf8               (Lscala/collection/IterableOnce<Ljava/lang/Object;>;)Lscala/collection/immutable/BitSet;
   #76 = Utf8               it
   #77 = Utf8               newBuilder
   #78 = Utf8               ()Lscala/collection/mutable/Builder;
   #79 = NameAndType        #77:#78       // newBuilder:()Lscala/collection/mutable/Builder;
   #80 = Methodref          #2.#79        // scala/collection/immutable/BitSet$.newBuilder:()Lscala/collection/mutable/Builder;
   #81 = Utf8               scala/collection/mutable/Growable
   #82 = Class              #81           // scala/collection/mutable/Growable
   #83 = Utf8               addAll
   #84 = Utf8               (Lscala/collection/IterableOnce;)Lscala/collection/mutable/Growable;
   #85 = NameAndType        #83:#84       // addAll:(Lscala/collection/IterableOnce;)Lscala/collection/mutable/Growable;
   #86 = InterfaceMethodref #82.#85       // scala/collection/mutable/Growable.addAll:(Lscala/collection/IterableOnce;)Lscala/collection/mutable/Growable;
   #87 = Utf8               scala/collection/mutable/Builder
   #88 = Class              #87           // scala/collection/mutable/Builder
   #89 = Utf8               result
   #90 = Utf8               ()Ljava/lang/Object;
   #91 = NameAndType        #89:#90       // result:()Ljava/lang/Object;
   #92 = InterfaceMethodref #88.#91       // scala/collection/mutable/Builder.result:()Ljava/lang/Object;
   #93 = Utf8               Lscala/collection/IterableOnce;
   #94 = Utf8               ()Lscala/collection/immutable/BitSet;
   #95 = Utf8               ()Lscala/collection/mutable/Builder<Ljava/lang/Object;Lscala/collection/immutable/BitSet;>;
   #96 = Utf8               scala/collection/mutable/BitSet$
   #97 = Class              #96           // scala/collection/mutable/BitSet$
   #98 = Utf8               Lscala/collection/mutable/BitSet$;
   #99 = NameAndType        #27:#98       // MODULE$:Lscala/collection/mutable/BitSet$;
  #100 = Fieldref           #97.#99       // scala/collection/mutable/BitSet$.MODULE$:Lscala/collection/mutable/BitSet$;
  #101 = Methodref          #97.#79       // scala/collection/mutable/BitSet$.newBuilder:()Lscala/collection/mutable/Builder;
  #102 = Utf8               (Ljava/lang/Object;)Ljava/lang/Object;
  #103 = MethodType         #102          //  (Ljava/lang/Object;)Ljava/lang/Object;
  #104 = Utf8               $anonfun$newBuilder$1
  #105 = Utf8               (Lscala/collection/mutable/BitSet;)Lscala/collection/immutable/BitSet;
  #106 = NameAndType        #104:#105     // $anonfun$newBuilder$1:(Lscala/collection/mutable/BitSet;)Lscala/collection/immutable/BitSet;
  #107 = Methodref          #2.#106       // scala/collection/immutable/BitSet$.$anonfun$newBuilder$1:(Lscala/collection/mutable/BitSet;)Lscala/collection/immutable/BitSet;
  #108 = MethodHandle       6:#107        // REF_invokeStatic scala/collection/immutable/BitSet$.$anonfun$newBuilder$1:(Lscala/collection/mutable/BitSet;)Lscala/collection/immutable/BitSet;
  #109 = MethodType         #105          //  (Lscala/collection/mutable/BitSet;)Lscala/collection/immutable/BitSet;
  #110 = Integer            5
  #111 = Integer            1
  #112 = Utf8               java/lang/invoke/LambdaMetafactory
  #113 = Class              #112          // java/lang/invoke/LambdaMetafactory
  #114 = Utf8               altMetafactory
  #115 = Utf8               (Ljava/lang/invoke/MethodHandles$Lookup;Ljava/lang/String;Ljava/lang/invoke/MethodType;[Ljava/lang/Object;)Ljava/lang/invoke/CallSite;
  #116 = NameAndType        #114:#115     // altMetafactory:(Ljava/lang/invoke/MethodHandles$Lookup;Ljava/lang/String;Ljava/lang/invoke/MethodType;[Ljava/lang/Object;)Ljava/lang/invoke/CallSite;
  #117 = Methodref          #113.#116     // java/lang/invoke/LambdaMetafactory.altMetafactory:(Ljava/lang/invoke/MethodHandles$Lookup;Ljava/lang/String;Ljava/lang/invoke/MethodType;[Ljava/lang/Object;)Ljava/lang/invoke/CallSite;
  #118 = MethodHandle       6:#117        // REF_invokeStatic java/lang/invoke/LambdaMetafactory.altMetafactory:(Ljava/lang/invoke/MethodHandles$Lookup;Ljava/lang/String;Ljava/lang/invoke/MethodType;[Ljava/lang/Object;)Ljava/lang/invoke/CallSite;
  #119 = Utf8               ()Lscala/Function1;
  #120 = NameAndType        #47:#119      // apply:()Lscala/Function1;
  #121 = InvokeDynamic      #0:#120       // #0:apply:()Lscala/Function1;
  #122 = Utf8               mapResult
  #123 = Utf8               (Lscala/Function1;)Lscala/collection/mutable/Builder;
  #124 = NameAndType        #122:#123     // mapResult:(Lscala/Function1;)Lscala/collection/mutable/Builder;
  #125 = InterfaceMethodref #88.#124      // scala/collection/mutable/Builder.mapResult:(Lscala/Function1;)Lscala/collection/mutable/Builder;
  #126 = Utf8               scala$collection$immutable$BitSet$$createSmall
  #127 = Utf8               (JJ)Lscala/collection/immutable/BitSet;
  #128 = Utf8               a
  #129 = Utf8               b
  #130 = Utf8               (JJ)V
  #131 = NameAndType        #37:#130      // "<init>":(JJ)V
  #132 = Methodref          #22.#131      // scala/collection/immutable/BitSet$BitSet2."<init>":(JJ)V
  #133 = Utf8               fromBitMask
  #134 = Utf8               ([J)Lscala/collection/immutable/BitSet;
  #135 = Utf8               elems
  #136 = NameAndType        #33:#94       // empty:()Lscala/collection/immutable/BitSet;
  #137 = Methodref          #2.#136       // scala/collection/immutable/BitSet$.empty:()Lscala/collection/immutable/BitSet;
  #138 = NameAndType        #126:#127     // scala$collection$immutable$BitSet$$createSmall:(JJ)Lscala/collection/immutable/BitSet;
  #139 = Methodref          #2.#138       // scala/collection/immutable/BitSet$.scala$collection$immutable$BitSet$$createSmall:(JJ)Lscala/collection/immutable/BitSet;
  #140 = Utf8               java/util/Arrays
  #141 = Class              #140          // java/util/Arrays
  #142 = Utf8               copyOf
  #143 = Utf8               ([JI)[J
  #144 = NameAndType        #142:#143     // copyOf:([JI)[J
  #145 = Methodref          #141.#144     // java/util/Arrays.copyOf:([JI)[J
  #146 = Utf8               ([J)V
  #147 = NameAndType        #37:#146      // "<init>":([J)V
  #148 = Methodref          #25.#147      // scala/collection/immutable/BitSet$BitSetN."<init>":([J)V
  #149 = Utf8               [J
  #150 = Utf8               len
  #151 = Utf8               fromBitMaskNoCopy
  #152 = Utf8               writeReplace
  #153 = Utf8               scala/runtime/ModuleSerializationProxy
  #154 = Class              #153          // scala/runtime/ModuleSerializationProxy
  #155 = Utf8               (Ljava/lang/Class;)V
  #156 = NameAndType        #37:#155      // "<init>":(Ljava/lang/Class;)V
  #157 = Methodref          #154.#156     // scala/runtime/ModuleSerializationProxy."<init>":(Ljava/lang/Class;)V
  #158 = Utf8               (Lscala/collection/IterableOnce;)Ljava/lang/Object;
  #159 = NameAndType        #73:#74       // fromSpecific:(Lscala/collection/IterableOnce;)Lscala/collection/immutable/BitSet;
  #160 = Methodref          #2.#159       // scala/collection/immutable/BitSet$.fromSpecific:(Lscala/collection/IterableOnce;)Lscala/collection/immutable/BitSet;
  #161 = Utf8               bs
  #162 = Utf8               scala/collection/mutable/BitSet
  #163 = Class              #162          // scala/collection/mutable/BitSet
  #164 = Utf8               ()[J
  #165 = NameAndType        #135:#164     // elems:()[J
  #166 = Methodref          #163.#165     // scala/collection/mutable/BitSet.elems:()[J
  #167 = NameAndType        #151:#134     // fromBitMaskNoCopy:([J)Lscala/collection/immutable/BitSet;
  #168 = Methodref          #2.#167       // scala/collection/immutable/BitSet$.fromBitMaskNoCopy:([J)Lscala/collection/immutable/BitSet;
  #169 = Utf8               Lscala/collection/mutable/BitSet;
  #170 = Methodref          #5.#38        // java/lang/Object."<init>":()V
  #171 = Utf8               $deserializeLambda$
  #172 = Utf8               (Ljava/lang/invoke/SerializedLambda;)Ljava/lang/Object;
  #173 = Utf8               scala/runtime/LambdaDeserialize
  #174 = Class              #173          // scala/runtime/LambdaDeserialize
  #175 = Utf8               bootstrap
  #176 = Utf8               (Ljava/lang/invoke/MethodHandles$Lookup;Ljava/lang/String;Ljava/lang/invoke/MethodType;[Ljava/lang/invoke/MethodHandle;)Ljava/lang/invoke/CallSite;
  #177 = NameAndType        #175:#176     // bootstrap:(Ljava/lang/invoke/MethodHandles$Lookup;Ljava/lang/String;Ljava/lang/invoke/MethodType;[Ljava/lang/invoke/MethodHandle;)Ljava/lang/invoke/CallSite;
  #178 = Methodref          #174.#177     // scala/runtime/LambdaDeserialize.bootstrap:(Ljava/lang/invoke/MethodHandles$Lookup;Ljava/lang/String;Ljava/lang/invoke/MethodType;[Ljava/lang/invoke/MethodHandle;)Ljava/lang/invoke/CallSite;
  #179 = MethodHandle       6:#178        // REF_invokeStatic scala/runtime/LambdaDeserialize.bootstrap:(Ljava/lang/invoke/MethodHandles$Lookup;Ljava/lang/String;Ljava/lang/invoke/MethodType;[Ljava/lang/invoke/MethodHandle;)Ljava/lang/invoke/CallSite;
  #180 = Utf8               lambdaDeserialize
  #181 = NameAndType        #180:#172     // lambdaDeserialize:(Ljava/lang/invoke/SerializedLambda;)Ljava/lang/Object;
  #182 = InvokeDynamic      #1:#181       // #1:lambdaDeserialize:(Ljava/lang/invoke/SerializedLambda;)Ljava/lang/Object;
  #183 = Utf8               ConstantValue
  #184 = Utf8               Code
  #185 = Utf8               LineNumberTable
  #186 = Utf8               LocalVariableTable
  #187 = Utf8               MethodParameters
  #188 = Utf8               Signature
  #189 = Utf8               StackMapTable
  #190 = Utf8               InnerClasses
  #191 = Utf8               SourceFile
  #192 = Utf8               BootstrapMethods
  #193 = Utf8               ScalaInlineInfo
  #194 = Utf8               Scala
{
  public static final scala.collection.immutable.BitSet$ MODULE$;
    descriptor: Lscala/collection/immutable/BitSet$;
    flags: (0x0019) ACC_PUBLIC, ACC_STATIC, ACC_FINAL

  private static final long serialVersionUID;
    descriptor: J
    flags: (0x001a) ACC_PRIVATE, ACC_STATIC, ACC_FINAL
    ConstantValue: long 3l

  private static final scala.collection.immutable.BitSet empty;
    descriptor: Lscala/collection/immutable/BitSet;
    flags: (0x001a) ACC_PRIVATE, ACC_STATIC, ACC_FINAL

  public static {};
    descriptor: ()V
    flags: (0x0009) ACC_PUBLIC, ACC_STATIC
    Code:
      stack=4, locals=0, args_size=0
         0: new           #2                  // class scala/collection/immutable/BitSet$
         3: dup
         4: invokespecial #39                 // Method "<init>":()V
         7: putstatic     #41                 // Field MODULE$:Lscala/collection/immutable/BitSet$;
        10: getstatic     #41                 // Field MODULE$:Lscala/collection/immutable/BitSet$;
        13: pop
        14: new           #17                 // class scala/collection/immutable/BitSet$BitSet1
        17: dup
        18: lconst_0
        19: invokespecial #44                 // Method scala/collection/immutable/BitSet$BitSet1."<init>":(J)V
        22: putstatic     #46                 // Field empty:Lscala/collection/immutable/BitSet;
        25: return
      LineNumberTable:
        line 95: 0
        line 103: 14
        line 95: 25

  public java.lang.Object apply(scala.collection.immutable.Seq);
    descriptor: (Lscala/collection/immutable/Seq;)Ljava/lang/Object;
    flags: (0x0001) ACC_PUBLIC
    Code:
      stack=2, locals=2, args_size=2
         0: aload_0
         1: aload_1
         2: invokestatic  #53                 // InterfaceMethod scala/collection/SpecificIterableFactory.apply$:(Lscala/collection/SpecificIterableFactory;Lscala/collection/immutable/Seq;)Ljava/lang/Object;
         5: areturn
      LineNumberTable:
        line 95: 0
      LocalVariableTable:
        Start  Length  Slot  Name   Signature
            0       6     0  this   Lscala/collection/immutable/BitSet$;
            0       6     1    xs   Lscala/collection/immutable/Seq;
    MethodParameters:
      Name                           Flags
      xs                             final

  public java.lang.Object fill(int, scala.Function0);
    descriptor: (ILscala/Function0;)Ljava/lang/Object;
    flags: (0x0001) ACC_PUBLIC
    Code:
      stack=3, locals=3, args_size=3
         0: aload_0
         1: iload_1
         2: aload_2
         3: invokestatic  #63                 // InterfaceMethod scala/collection/SpecificIterableFactory.fill$:(Lscala/collection/SpecificIterableFactory;ILscala/Function0;)Ljava/lang/Object;
         6: areturn
      LineNumberTable:
        line 95: 0
      LocalVariableTable:
        Start  Length  Slot  Name   Signature
            0       7     0  this   Lscala/collection/immutable/BitSet$;
            0       7     1     n   I
            0       7     2  elem   Lscala/Function0;
    MethodParameters:
      Name                           Flags
      n                              final
      elem                           final

  public scala.collection.Factory<java.lang.Object, scala.collection.immutable.BitSet> specificIterableFactory();
    descriptor: ()Lscala/collection/Factory;
    flags: (0x0001) ACC_PUBLIC
    Code:
      stack=1, locals=1, args_size=1
         0: aload_0
         1: invokestatic  #72                 // InterfaceMethod scala/collection/SpecificIterableFactory.specificIterableFactory$:(Lscala/collection/SpecificIterableFactory;)Lscala/collection/Factory;
         4: areturn
      LineNumberTable:
        line 95: 0
      LocalVariableTable:
        Start  Length  Slot  Name   Signature
            0       5     0  this   Lscala/collection/immutable/BitSet$;
    Signature: #68                          // ()Lscala/collection/Factory<Ljava/lang/Object;Lscala/collection/immutable/BitSet;>;

  public scala.collection.immutable.BitSet fromSpecific(scala.collection.IterableOnce<java.lang.Object>);
    descriptor: (Lscala/collection/IterableOnce;)Lscala/collection/immutable/BitSet;
    flags: (0x0001) ACC_PUBLIC
    Code:
      stack=2, locals=3, args_size=2
         0: aload_1
         1: instanceof    #19                 // class scala/collection/immutable/BitSet
         4: ifeq          15
         7: aload_1
         8: checkcast     #19                 // class scala/collection/immutable/BitSet
        11: astore_2
        12: goto          43
        15: aload_0
        16: invokevirtual #80                 // Method newBuilder:()Lscala/collection/mutable/Builder;
        19: dup
        20: ifnonnull     25
        23: aconst_null
        24: athrow
        25: aload_1
        26: invokeinterface #86,  2           // InterfaceMethod scala/collection/mutable/Growable.addAll:(Lscala/collection/IterableOnce;)Lscala/collection/mutable/Growable;
        31: checkcast     #88                 // class scala/collection/mutable/Builder
        34: invokeinterface #92,  1           // InterfaceMethod scala/collection/mutable/Builder.result:()Ljava/lang/Object;
        39: checkcast     #19                 // class scala/collection/immutable/BitSet
        42: astore_2
        43: aload_2
        44: areturn
      StackMapTable: number_of_entries = 3
        frame_type = 15 /* same */
        frame_type = 73 /* same_locals_1_stack_item */
          stack = [ class scala/collection/mutable/Builder ]
        frame_type = 252 /* append */
          offset_delta = 17
          locals = [ class scala/collection/immutable/BitSet ]
      LineNumberTable:
        line 99: 0
        line 100: 15
        line 98: 43
      LocalVariableTable:
        Start  Length  Slot  Name   Signature
            0      45     0  this   Lscala/collection/immutable/BitSet$;
            0      45     1    it   Lscala/collection/IterableOnce;
    Signature: #75                          // (Lscala/collection/IterableOnce<Ljava/lang/Object;>;)Lscala/collection/immutable/BitSet;
    MethodParameters:
      Name                           Flags
      it                             final

  public final scala.collection.immutable.BitSet empty();
    descriptor: ()Lscala/collection/immutable/BitSet;
    flags: (0x0011) ACC_PUBLIC, ACC_FINAL
    Code:
      stack=1, locals=1, args_size=1
         0: getstatic     #46                 // Field empty:Lscala/collection/immutable/BitSet;
         3: areturn
      LineNumberTable:
        line 103: 0
      LocalVariableTable:
        Start  Length  Slot  Name   Signature
            0       4     0  this   Lscala/collection/immutable/BitSet$;

  public scala.collection.mutable.Builder<java.lang.Object, scala.collection.immutable.BitSet> newBuilder();
    descriptor: ()Lscala/collection/mutable/Builder;
    flags: (0x0001) ACC_PUBLIC
    Code:
      stack=2, locals=1, args_size=1
         0: getstatic     #100                // Field scala/collection/mutable/BitSet$.MODULE$:Lscala/collection/mutable/BitSet$;
         3: invokevirtual #101                // Method scala/collection/mutable/BitSet$.newBuilder:()Lscala/collection/mutable/Builder;
         6: invokedynamic #121,  0            // InvokeDynamic #0:apply:()Lscala/Function1;
        11: invokeinterface #125,  2          // InterfaceMethod scala/collection/mutable/Builder.mapResult:(Lscala/Function1;)Lscala/collection/mutable/Builder;
        16: areturn
      LineNumberTable:
        line 106: 0
      LocalVariableTable:
        Start  Length  Slot  Name   Signature
            0      17     0  this   Lscala/collection/immutable/BitSet$;
    Signature: #95                          // ()Lscala/collection/mutable/Builder<Ljava/lang/Object;Lscala/collection/immutable/BitSet;>;

  public scala.collection.immutable.BitSet scala$collection$immutable$BitSet$$createSmall(long, long);
    descriptor: (JJ)Lscala/collection/immutable/BitSet;
    flags: (0x0001) ACC_PUBLIC
    Code:
      stack=6, locals=5, args_size=3
         0: lload_3
         1: lconst_0
         2: lcmp
         3: ifne          15
         6: new           #17                 // class scala/collection/immutable/BitSet$BitSet1
         9: dup
        10: lload_1
        11: invokespecial #44                 // Method scala/collection/immutable/BitSet$BitSet1."<init>":(J)V
        14: areturn
        15: new           #22                 // class scala/collection/immutable/BitSet$BitSet2
        18: dup
        19: lload_1
        20: lload_3
        21: invokespecial #132                // Method scala/collection/immutable/BitSet$BitSet2."<init>":(JJ)V
        24: areturn
      StackMapTable: number_of_entries = 1
        frame_type = 15 /* same */
      LineNumberTable:
        line 108: 0
      LocalVariableTable:
        Start  Length  Slot  Name   Signature
            0      25     0  this   Lscala/collection/immutable/BitSet$;
            0      25     1     a   J
            0      25     3     b   J
    MethodParameters:
      Name                           Flags
      a                              final
      b                              final

  public scala.collection.immutable.BitSet fromBitMask(long[]);
    descriptor: ([J)Lscala/collection/immutable/BitSet;
    flags: (0x0001) ACC_PUBLIC
    Code:
      stack=5, locals=4, args_size=2
         0: aload_1
         1: arraylength
         2: istore_2
         3: iload_2
         4: iconst_0
         5: if_icmpne     13
         8: aload_0
         9: invokevirtual #137                // Method empty:()Lscala/collection/immutable/BitSet;
        12: areturn
        13: iload_2
        14: iconst_1
        15: if_icmpne     29
        18: new           #17                 // class scala/collection/immutable/BitSet$BitSet1
        21: dup
        22: aload_1
        23: iconst_0
        24: laload
        25: invokespecial #44                 // Method scala/collection/immutable/BitSet$BitSet1."<init>":(J)V
        28: areturn
        29: iload_2
        30: iconst_2
        31: if_icmpne     45
        34: aload_0
        35: aload_1
        36: iconst_0
        37: laload
        38: aload_1
        39: iconst_1
        40: laload
        41: invokevirtual #139                // Method scala$collection$immutable$BitSet$$createSmall:(JJ)Lscala/collection/immutable/BitSet;
        44: areturn
        45: aload_1
        46: iload_2
        47: invokestatic  #145                // Method java/util/Arrays.copyOf:([JI)[J
        50: astore_3
        51: new           #25                 // class scala/collection/immutable/BitSet$BitSetN
        54: dup
        55: aload_3
        56: invokespecial #148                // Method scala/collection/immutable/BitSet$BitSetN."<init>":([J)V
        59: areturn
      StackMapTable: number_of_entries = 3
        frame_type = 252 /* append */
          offset_delta = 13
          locals = [ int ]
        frame_type = 15 /* same */
        frame_type = 15 /* same */
      LineNumberTable:
        line 112: 0
        line 113: 3
        line 114: 13
        line 115: 29
        line 117: 45
        line 118: 51
      LocalVariableTable:
        Start  Length  Slot  Name   Signature
           51       8     3     a   [J
            3      56     2   len   I
            0      60     0  this   Lscala/collection/immutable/BitSet$;
            0      60     1 elems   [J
    MethodParameters:
      Name                           Flags
      elems                          final

  public scala.collection.immutable.BitSet fromBitMaskNoCopy(long[]);
    descriptor: ([J)Lscala/collection/immutable/BitSet;
    flags: (0x0001) ACC_PUBLIC
    Code:
      stack=5, locals=3, args_size=2
         0: aload_1
         1: arraylength
         2: istore_2
         3: iload_2
         4: iconst_0
         5: if_icmpne     13
         8: aload_0
         9: invokevirtual #137                // Method empty:()Lscala/collection/immutable/BitSet;
        12: areturn
        13: iload_2
        14: iconst_1
        15: if_icmpne     29
        18: new           #17                 // class scala/collection/immutable/BitSet$BitSet1
        21: dup
        22: aload_1
        23: iconst_0
        24: laload
        25: invokespecial #44                 // Method scala/collection/immutable/BitSet$BitSet1."<init>":(J)V
        28: areturn
        29: iload_2
        30: iconst_2
        31: if_icmpne     45
        34: aload_0
        35: aload_1
        36: iconst_0
        37: laload
        38: aload_1
        39: iconst_1
        40: laload
        41: invokevirtual #139                // Method scala$collection$immutable$BitSet$$createSmall:(JJ)Lscala/collection/immutable/BitSet;
        44: areturn
        45: new           #25                 // class scala/collection/immutable/BitSet$BitSetN
        48: dup
        49: aload_1
        50: invokespecial #148                // Method scala/collection/immutable/BitSet$BitSetN."<init>":([J)V
        53: areturn
      StackMapTable: number_of_entries = 3
        frame_type = 252 /* append */
          offset_delta = 13
          locals = [ int ]
        frame_type = 15 /* same */
        frame_type = 15 /* same */
      LineNumberTable:
        line 126: 0
        line 127: 3
        line 128: 13
        line 129: 29
        line 130: 45
      LocalVariableTable:
        Start  Length  Slot  Name   Signature
            3      50     2   len   I
            0      54     0  this   Lscala/collection/immutable/BitSet$;
            0      54     1 elems   [J
    MethodParameters:
      Name                           Flags
      elems                          final

  private java.lang.Object writeReplace();
    descriptor: ()Ljava/lang/Object;
    flags: (0x0002) ACC_PRIVATE
    Code:
      stack=3, locals=1, args_size=1
         0: new           #154                // class scala/runtime/ModuleSerializationProxy
         3: dup
         4: ldc           #2                  // class scala/collection/immutable/BitSet$
         6: invokespecial #157                // Method scala/runtime/ModuleSerializationProxy."<init>":(Ljava/lang/Class;)V
         9: areturn
      LineNumberTable:
        line 95: 0
      LocalVariableTable:
        Start  Length  Slot  Name   Signature
            0      10     0  this   Lscala/collection/immutable/BitSet$;

  public final java.lang.Object empty();
    descriptor: ()Ljava/lang/Object;
    flags: (0x1051) ACC_PUBLIC, ACC_FINAL, ACC_BRIDGE, ACC_SYNTHETIC
    Code:
      stack=1, locals=1, args_size=1
         0: aload_0
         1: invokevirtual #137                // Method empty:()Lscala/collection/immutable/BitSet;
         4: areturn
      LineNumberTable:
        line 95: 0
      LocalVariableTable:
        Start  Length  Slot  Name   Signature
            0       5     0  this   Lscala/collection/immutable/BitSet$;

  public java.lang.Object fromSpecific(scala.collection.IterableOnce);
    descriptor: (Lscala/collection/IterableOnce;)Ljava/lang/Object;
    flags: (0x1041) ACC_PUBLIC, ACC_BRIDGE, ACC_SYNTHETIC
    Code:
      stack=2, locals=2, args_size=2
         0: aload_0
         1: aload_1
         2: invokevirtual #160                // Method fromSpecific:(Lscala/collection/IterableOnce;)Lscala/collection/immutable/BitSet;
         5: areturn
      LineNumberTable:
        line 95: 0
      LocalVariableTable:
        Start  Length  Slot  Name   Signature
            0       6     0  this   Lscala/collection/immutable/BitSet$;
            0       6     1    it   Lscala/collection/IterableOnce;
    MethodParameters:
      Name                           Flags
      it                             final

  public static final scala.collection.immutable.BitSet $anonfun$newBuilder$1(scala.collection.mutable.BitSet);
    descriptor: (Lscala/collection/mutable/BitSet;)Lscala/collection/immutable/BitSet;
    flags: (0x1019) ACC_PUBLIC, ACC_STATIC, ACC_FINAL, ACC_SYNTHETIC
    Code:
      stack=2, locals=1, args_size=1
         0: getstatic     #41                 // Field MODULE$:Lscala/collection/immutable/BitSet$;
         3: aload_0
         4: invokevirtual #166                // Method scala/collection/mutable/BitSet.elems:()[J
         7: invokevirtual #168                // Method fromBitMaskNoCopy:([J)Lscala/collection/immutable/BitSet;
        10: areturn
      LineNumberTable:
        line 106: 0
      LocalVariableTable:
        Start  Length  Slot  Name   Signature
            0      11     0    bs   Lscala/collection/mutable/BitSet;
    MethodParameters:
      Name                           Flags
      bs                             final

  private scala.collection.immutable.BitSet$();
    descriptor: ()V
    flags: (0x0002) ACC_PRIVATE
    Code:
      stack=1, locals=1, args_size=1
         0: aload_0
         1: invokespecial #170                // Method java/lang/Object."<init>":()V
         4: return
      LineNumberTable:
        line 95: 0
      LocalVariableTable:
        Start  Length  Slot  Name   Signature
            0       5     0  this   Lscala/collection/immutable/BitSet$;

  private static java.lang.Object $deserializeLambda$(java.lang.invoke.SerializedLambda);
    descriptor: (Ljava/lang/invoke/SerializedLambda;)Ljava/lang/Object;
    flags: (0x100a) ACC_PRIVATE, ACC_STATIC, ACC_SYNTHETIC
    Code:
      stack=1, locals=1, args_size=1
         0: aload_0
         1: invokedynamic #182,  0            // InvokeDynamic #1:lambdaDeserialize:(Ljava/lang/invoke/SerializedLambda;)Ljava/lang/Object;
         6: areturn
}
InnerClasses:
  public static final #15= #12 of #14;    // Lookup=class java/lang/invoke/MethodHandles$Lookup of class java/lang/invoke/MethodHandles
  public static #20= #17 of #19;          // BitSet1=class scala/collection/immutable/BitSet$BitSet1 of class scala/collection/immutable/BitSet
  public static #23= #22 of #19;          // BitSet2=class scala/collection/immutable/BitSet$BitSet2 of class scala/collection/immutable/BitSet
  public static #26= #25 of #19;          // BitSetN=class scala/collection/immutable/BitSet$BitSetN of class scala/collection/immutable/BitSet
Signature: #3                           // Ljava/lang/Object;Lscala/collection/SpecificIterableFactory<Ljava/lang/Object;Lscala/collection/immutable/BitSet;>;Ljava/io/Serializable;
SourceFile: "BitSet.scala"
BootstrapMethods:
  0: #118 REF_invokeStatic java/lang/invoke/LambdaMetafactory.altMetafactory:(Ljava/lang/invoke/MethodHandles$Lookup;Ljava/lang/String;Ljava/lang/invoke/MethodType;[Ljava/lang/Object;)Ljava/lang/invoke/CallSite;
    Method arguments:
      #103 (Ljava/lang/Object;)Ljava/lang/Object;
      #108 REF_invokeStatic scala/collection/immutable/BitSet$.$anonfun$newBuilder$1:(Lscala/collection/mutable/BitSet;)Lscala/collection/immutable/BitSet;
      #109 (Lscala/collection/mutable/BitSet;)Lscala/collection/immutable/BitSet;
      #110 5
      #111 1
      #109 (Lscala/collection/mutable/BitSet;)Lscala/collection/immutable/BitSet;
  1: #179 REF_invokeStatic scala/runtime/LambdaDeserialize.bootstrap:(Ljava/lang/invoke/MethodHandles$Lookup;Ljava/lang/String;Ljava/lang/invoke/MethodType;[Ljava/lang/invoke/MethodHandle;)Ljava/lang/invoke/CallSite;
    Method arguments:
      #108 REF_invokeStatic scala/collection/immutable/BitSet$.$anonfun$newBuilder$1:(Lscala/collection/mutable/BitSet;)Lscala/collection/immutable/BitSet;
  ScalaInlineInfo: length = 0x4A (unknown attribute)
   01 01 00 0E 00 68 00 69 01 00 25 00 24 01 00 2F
   00 30 01 00 21 00 5A 01 00 21 00 5E 01 00 38 00
   39 01 00 85 00 86 01 00 97 00 86 01 00 49 00 9E
   01 00 49 00 4A 01 00 4D 00 4E 01 00 7E 00 7F 01
   00 42 00 43 01 00 98 00 5A 01
  Scala: length = 0x0 (unknown attribute)

