Classfile /Users/mw/Projects/slang-braindump/.jar/jar8/assemble/slang-braindump/assemble/content/scala/collection/immutable/HashSetBuilder.class
  Last modified May 29, 2022; size 12678 bytes
  SHA-256 checksum 9cce44e4fcac37aea97731a818de4623e91445c8a4f1702ccaabef95d0d11471
  Compiled from "HashSet.scala"
public final class scala.collection.immutable.HashSetBuilder<A extends java.lang.Object> extends java.lang.Object implements scala.collection.mutable.ReusableBuilder<A, scala.collection.immutable.HashSet<A>>
  minor version: 0
  major version: 52
  flags: (0x0031) ACC_PUBLIC, ACC_FINAL, ACC_SUPER
  this_class: #2                          // scala/collection/immutable/HashSetBuilder
  super_class: #5                         // java/lang/Object
  interfaces: 1, fields: 2, methods: 30, attributes: 6
Constant pool:
    #1 = Utf8               scala/collection/immutable/HashSetBuilder
    #2 = Class              #1            // scala/collection/immutable/HashSetBuilder
    #3 = Utf8               <A:Ljava/lang/Object;>Ljava/lang/Object;Lscala/collection/mutable/ReusableBuilder<TA;Lscala/collection/immutable/HashSet<TA;>;>;
    #4 = Utf8               java/lang/Object
    #5 = Class              #4            // java/lang/Object
    #6 = Utf8               scala/collection/mutable/ReusableBuilder
    #7 = Class              #6            // scala/collection/mutable/ReusableBuilder
    #8 = Utf8               HashSet.scala
    #9 = Utf8               Lscala/reflect/ScalaSignature;
   #10 = Utf8               bytes
   #11 = Utf8               \u0006\u0005\u0005mb!\u0002\f\u0018\u0005ei\u0002\"B\u001d\u0001\t\u0003Q\u0004\"\u0002\u001f\u0001\t\u0013i\u0004\"C!\u0001\u0001\u0004\u0005\r\u0011\"\u0003C\u0011%\u0019\u0005\u00011AA\u0002\u0013%A\tC\u0005K\u0001\u0001\u0007\t\u0011)Q\u0005k!)1\n\u0001C\u0005\u0019\"9\u0001\u000b\u0001a\u0001\n\u0013i\u0004bB)\u0001\u0001\u0004%IA\u0015\u0005\u0007)\u0002\u0001\u000b\u0015\u0002 \t\u000bU\u0003A\u0011\u0002,\t\u000b\r\u0004A\u0011\u00023\t\u000bM\u0004A\u0011\u0002;\t\u000bi\u0004A\u0011A>\t\u000f\u0005E\u0001\u0001\"\u0003\u0002\u0014!9\u0011Q\u0003\u0001\u0005\n\u0005M\u0001bBA\f\u0001\u0011\u0005\u0013\u0011\u0004\u0005\b\u00037\u0001A\u0011IA\u000f\u0011\u001d\t\u0019\u0003\u0001C!\u0003KAq!a\r\u0001\t\u0003\n\u0019\u0002\u0003\u0005\u00026\u0001!\t!GA\u001c\u0011\u001d\tI\u0004\u0001C!\u0003o\u0011a\u0002S1tQN+GOQ;jY\u0012,\'O\u0003\u0002\u00193\u0005I\u0011.\\7vi\u0006\u0014G.\u001a\u0006\u00035m\t!bY8mY\u0016\u001cG/[8o\u0015\u0005a\u0012!B:dC2\fWC\u0001\u0010,\'\r\u0001qd\t\t\u0003A\u0005j\u0011aG\u0005\u0003Em\u0011a!\u00118z%\u00164\u0007\u0003\u0002\u0013(SUj\u0011!\n\u0006\u0003Me\tq!\\;uC\ndW-\u0003\u0002)K\ty!+Z;tC\ndWMQ;jY\u0012,\'\u000f\u0005\u0002+W1\u0001A!\u0002\u0017\u0001\u0005\u0004q#!A!\u0004\u0001E\u0011qF\r\t\u0003AAJ!!M\u000e\u0003\u000f9{G\u000f[5oOB\u0011\u0001eM\u0005\u0003im\u00111!\u00118z!\r1t\'K\u0007\u0002/%\u0011\u0001h\u0006\u0002\b\u0011\u0006\u001c\bnU3u\u0003\u0019a\u0014N\\5u}Q\t1\bE\u00027\u0001%\n\u0001C\\3x\u000b6\u0004H/\u001f*p_Rtu\u000eZ3\u0016\u0003y\u00022AN *\u0013\t\u0001uC\u0001\u000bCSRl\u0017\r]%oI\u0016DX\rZ*fi:{G-Z\u0001\bC2L\u0017m]3e+\u0005)\u0014aC1mS\u0006\u001cX\rZ0%KF$\"!\u0012%\u0011\u0005\u00012\u0015BA$\u001c\u0005\u0011)f.\u001b;\t\u000f%#\u0011\u0011!a\u0001k\u0005\u0019\u0001\u0010J\u0019\u0002\u0011\u0005d\u0017.Y:fI\u0002\n\u0011\"[:BY&\f7/\u001a3\u0016\u00035\u0003\"\u0001\t(\n\u0005=[\"a\u0002\"p_2,\u0017M\\\u0001\te>|GOT8eK\u0006a!o\\8u\u001d>$Wm\u0018\u0013fcR\u0011Qi\u0015\u0005\b\u0013\"\t\t\u00111\u0001?\u0003%\u0011xn\u001c;O_\u0012,\u0007%A\u0007j]N,\'\u000f^#mK6,g\u000e\u001e\u000b\u0005/v{\u0016\rE\u0002!1jK!!W\u000e\u0003\u000b\u0005\u0013(/Y=\u0011\u0005\u0001Z\u0016B\u0001/\u001c\u0005\rIe\u000e\u001e\u0005\u0006=*\u0001\raV\u0001\u0003CNDQ\u0001\u0019\u0006A\u0002i\u000b!!\u001b=\t\u000b\tT\u0001\u0019\u0001.\u0002\t\u0015dW-\\\u0001\fS:\u001cXM\u001d;WC2,X-\u0006\u0002faR1QI\u001a5kY:DQaZ\u0006A\u0002y\n!AY7\t\u000b%\\\u0001\u0019\u0001.\u0002\r\tLG\u000f]8t\u0011\u0015Y7\u00021\u0001*\u0003\rYW-\u001f\u0005\u0006[.\u0001\rAW\u0001\r_JLw-\u001b8bY\"\u000b7\u000f\u001b\u0005\u0006_.\u0001\rAW\u0001\bW\u0016L\b*Y:i\t\u0015\t8B1\u0001s\u0005\t\t\u0015\'\u0005\u0002*e\u0005A1/\u001a;WC2,X-\u0006\u0002vsR!QI^<y\u0011\u00159G\u00021\u0001?\u0011\u0015IG\u00021\u0001[\u0011\u0015\u0011G\u00021\u0001*\t\u0015\tHB1\u0001s\u0003\u0019)\b\u000fZ1uKRQQ\t`A\u0002\u0003\u000f\tI!!\u0004\t\u000bul\u0001\u0019\u0001@\u0002\u000fM,GOT8eKB\u0019ag`\u0015\n\u0007\u0005\u0005qCA\u0004TKRtu\u000eZ3\t\r\u0005\u0015Q\u00021\u0001*\u0003\u001d)G.Z7f]RDQ!\\\u0007A\u0002iCa!a\u0003\u000e\u0001\u0004Q\u0016aC3mK6,g\u000e\u001e%bg\"Da!a\u0004\u000e\u0001\u0004Q\u0016!B:iS\u001a$\u0018aD3ogV\u0014X-\u00168bY&\f7/\u001a3\u0015\u0003\u0015\u000b\u0011bY8qs\u0016cW-\\:\u0002\rI,7/\u001e7u)\u0005)\u0014AB1eI>sW\r\u0006\u0003\u0002 \u0005\u0005R\"\u0001\u0001\t\u000b\t\f\u0002\u0019A\u0015\u0002\r\u0005$G-\u00117m)\u0011\ty\"a\n\t\u000f\u0005%\"\u00031\u0001\u0002,\u0005\u0011\u0001p\u001d\t\u0006\u0003[\ty#K\u0007\u00023%\u0019\u0011\u0011G\r\u0003\u0019%#XM]1cY\u0016|enY3\u0002\u000b\rdW-\u0019:\u0002\tML\'0Z\u000b\u00025\u0006I1N\\8x]NK\'0\u001a
   #12 = Utf8               scala/collection/immutable/HashSetBuilder$$anon$1
   #13 = Class              #12           // scala/collection/immutable/HashSetBuilder$$anon$1
   #14 = Utf8               aliased
   #15 = Utf8               Lscala/collection/immutable/HashSet;
   #16 = Utf8               Lscala/collection/immutable/HashSet<TA;>;
   #17 = Utf8               scala$collection$immutable$HashSetBuilder$$rootNode
   #18 = Utf8               Lscala/collection/immutable/BitmapIndexedSetNode;
   #19 = Utf8               Lscala/collection/immutable/BitmapIndexedSetNode<TA;>;
   #20 = Utf8               sizeHint
   #21 = Utf8               (I)V
   #22 = Utf8               size
   #23 = Utf8               scala/collection/mutable/Builder
   #24 = Class              #23           // scala/collection/mutable/Builder
   #25 = Utf8               sizeHint$
   #26 = Utf8               (Lscala/collection/mutable/Builder;I)V
   #27 = NameAndType        #25:#26       // sizeHint$:(Lscala/collection/mutable/Builder;I)V
   #28 = InterfaceMethodref #24.#27       // scala/collection/mutable/Builder.sizeHint$:(Lscala/collection/mutable/Builder;I)V
   #29 = Utf8               this
   #30 = Utf8               Lscala/collection/immutable/HashSetBuilder;
   #31 = Utf8               I
   #32 = Utf8               (Lscala/collection/IterableOnce;I)V
   #33 = Utf8               (Lscala/collection/IterableOnce<*>;I)V
   #34 = Utf8               coll
   #35 = Utf8               delta
   #36 = Utf8               (Lscala/collection/mutable/Builder;Lscala/collection/IterableOnce;I)V
   #37 = NameAndType        #25:#36       // sizeHint$:(Lscala/collection/mutable/Builder;Lscala/collection/IterableOnce;I)V
   #38 = InterfaceMethodref #24.#37       // scala/collection/mutable/Builder.sizeHint$:(Lscala/collection/mutable/Builder;Lscala/collection/IterableOnce;I)V
   #39 = Utf8               Lscala/collection/IterableOnce;
   #40 = Utf8               sizeHint$default$2
   #41 = Utf8               ()I
   #42 = Utf8               sizeHint$default$2$
   #43 = Utf8               (Lscala/collection/mutable/Builder;)I
   #44 = NameAndType        #42:#43       // sizeHint$default$2$:(Lscala/collection/mutable/Builder;)I
   #45 = InterfaceMethodref #24.#44       // scala/collection/mutable/Builder.sizeHint$default$2$:(Lscala/collection/mutable/Builder;)I
   #46 = Utf8               sizeHintBounded
   #47 = Utf8               (ILscala/collection/Iterable;)V
   #48 = Utf8               (ILscala/collection/Iterable<*>;)V
   #49 = Utf8               boundingColl
   #50 = Utf8               sizeHintBounded$
   #51 = Utf8               (Lscala/collection/mutable/Builder;ILscala/collection/Iterable;)V
   #52 = NameAndType        #50:#51       // sizeHintBounded$:(Lscala/collection/mutable/Builder;ILscala/collection/Iterable;)V
   #53 = InterfaceMethodref #24.#52       // scala/collection/mutable/Builder.sizeHintBounded$:(Lscala/collection/mutable/Builder;ILscala/collection/Iterable;)V
   #54 = Utf8               Lscala/collection/Iterable;
   #55 = Utf8               mapResult
   #56 = Utf8               (Lscala/Function1;)Lscala/collection/mutable/Builder;
   #57 = Utf8               <NewTo:Ljava/lang/Object;>(Lscala/Function1<Lscala/collection/immutable/HashSet<TA;>;TNewTo;>;)Lscala/collection/mutable/Builder<TA;TNewTo;>;
   #58 = Utf8               f
   #59 = Utf8               mapResult$
   #60 = Utf8               (Lscala/collection/mutable/Builder;Lscala/Function1;)Lscala/collection/mutable/Builder;
   #61 = NameAndType        #59:#60       // mapResult$:(Lscala/collection/mutable/Builder;Lscala/Function1;)Lscala/collection/mutable/Builder;
   #62 = InterfaceMethodref #24.#61       // scala/collection/mutable/Builder.mapResult$:(Lscala/collection/mutable/Builder;Lscala/Function1;)Lscala/collection/mutable/Builder;
   #63 = Utf8               Lscala/Function1;
   #64 = Utf8               $plus$eq
   #65 = Utf8               (Ljava/lang/Object;)Lscala/collection/mutable/Growable;
   #66 = Utf8               (TA;)Lscala/collection/mutable/Growable<TA;>;
   #67 = Utf8               elem
   #68 = Utf8               scala/collection/mutable/Growable
   #69 = Class              #68           // scala/collection/mutable/Growable
   #70 = Utf8               $plus$eq$
   #71 = Utf8               (Lscala/collection/mutable/Growable;Ljava/lang/Object;)Lscala/collection/mutable/Growable;
   #72 = NameAndType        #70:#71       // $plus$eq$:(Lscala/collection/mutable/Growable;Ljava/lang/Object;)Lscala/collection/mutable/Growable;
   #73 = InterfaceMethodref #69.#72       // scala/collection/mutable/Growable.$plus$eq$:(Lscala/collection/mutable/Growable;Ljava/lang/Object;)Lscala/collection/mutable/Growable;
   #74 = Utf8               Ljava/lang/Object;
   #75 = Utf8               (Ljava/lang/Object;Ljava/lang/Object;Lscala/collection/immutable/Seq;)Lscala/collection/mutable/Growable;
   #76 = Utf8               (TA;TA;Lscala/collection/immutable/Seq<TA;>;)Lscala/collection/mutable/Growable<TA;>;
   #77 = Utf8               elem1
   #78 = Utf8               elem2
   #79 = Utf8               elems
   #80 = Utf8               (Lscala/collection/mutable/Growable;Ljava/lang/Object;Ljava/lang/Object;Lscala/collection/immutable/Seq;)Lscala/collection/mutable/Growable;
   #81 = NameAndType        #70:#80       // $plus$eq$:(Lscala/collection/mutable/Growable;Ljava/lang/Object;Ljava/lang/Object;Lscala/collection/immutable/Seq;)Lscala/collection/mutable/Growable;
   #82 = InterfaceMethodref #69.#81       // scala/collection/mutable/Growable.$plus$eq$:(Lscala/collection/mutable/Growable;Ljava/lang/Object;Ljava/lang/Object;Lscala/collection/immutable/Seq;)Lscala/collection/mutable/Growable;
   #83 = Utf8               Lscala/collection/immutable/Seq;
   #84 = Utf8               $plus$plus$eq
   #85 = Utf8               (Lscala/collection/IterableOnce;)Lscala/collection/mutable/Growable;
   #86 = Utf8               (Lscala/collection/IterableOnce<TA;>;)Lscala/collection/mutable/Growable<TA;>;
   #87 = Utf8               xs
   #88 = Utf8               $plus$plus$eq$
   #89 = Utf8               (Lscala/collection/mutable/Growable;Lscala/collection/IterableOnce;)Lscala/collection/mutable/Growable;
   #90 = NameAndType        #88:#89       // $plus$plus$eq$:(Lscala/collection/mutable/Growable;Lscala/collection/IterableOnce;)Lscala/collection/mutable/Growable;
   #91 = InterfaceMethodref #69.#90       // scala/collection/mutable/Growable.$plus$plus$eq$:(Lscala/collection/mutable/Growable;Lscala/collection/IterableOnce;)Lscala/collection/mutable/Growable;
   #92 = Utf8               newEmptyRootNode
   #93 = Utf8               ()Lscala/collection/immutable/BitmapIndexedSetNode;
   #94 = Utf8               ()Lscala/collection/immutable/BitmapIndexedSetNode<TA;>;
   #95 = Utf8               scala/collection/immutable/BitmapIndexedSetNode
   #96 = Class              #95           // scala/collection/immutable/BitmapIndexedSetNode
   #97 = Utf8               scala/Array$
   #98 = Class              #97           // scala/Array$
   #99 = Utf8               MODULE$
  #100 = Utf8               Lscala/Array$;
  #101 = NameAndType        #99:#100      // MODULE$:Lscala/Array$;
  #102 = Fieldref           #98.#101      // scala/Array$.MODULE$:Lscala/Array$;
  #103 = Utf8               emptyObjectArray
  #104 = Utf8               ()[Ljava/lang/Object;
  #105 = NameAndType        #103:#104     // emptyObjectArray:()[Ljava/lang/Object;
  #106 = Methodref          #98.#105      // scala/Array$.emptyObjectArray:()[Ljava/lang/Object;
  #107 = Utf8               emptyIntArray
  #108 = Utf8               ()[I
  #109 = NameAndType        #107:#108     // emptyIntArray:()[I
  #110 = Methodref          #98.#109      // scala/Array$.emptyIntArray:()[I
  #111 = Utf8               <init>
  #112 = Utf8               (II[Ljava/lang/Object;[III)V
  #113 = NameAndType        #111:#112     // "<init>":(II[Ljava/lang/Object;[III)V
  #114 = Methodref          #96.#113      // scala/collection/immutable/BitmapIndexedSetNode."<init>":(II[Ljava/lang/Object;[III)V
  #115 = Utf8               ()Lscala/collection/immutable/HashSet;
  #116 = Utf8               ()Lscala/collection/immutable/HashSet<TA;>;
  #117 = NameAndType        #14:#15       // aliased:Lscala/collection/immutable/HashSet;
  #118 = Fieldref           #2.#117       // scala/collection/immutable/HashSetBuilder.aliased:Lscala/collection/immutable/HashSet;
  #119 = Utf8               aliased_$eq
  #120 = Utf8               (Lscala/collection/immutable/HashSet;)V
  #121 = Utf8               (Lscala/collection/immutable/HashSet<TA;>;)V
  #122 = Utf8               x$1
  #123 = Utf8               isAliased
  #124 = Utf8               ()Z
  #125 = NameAndType        #14:#115      // aliased:()Lscala/collection/immutable/HashSet;
  #126 = Methodref          #2.#125       // scala/collection/immutable/HashSetBuilder.aliased:()Lscala/collection/immutable/HashSet;
  #127 = NameAndType        #17:#18       // scala$collection$immutable$HashSetBuilder$$rootNode:Lscala/collection/immutable/BitmapIndexedSetNode;
  #128 = Fieldref           #2.#127       // scala/collection/immutable/HashSetBuilder.scala$collection$immutable$HashSetBuilder$$rootNode:Lscala/collection/immutable/BitmapIndexedSetNode;
  #129 = Utf8               rootNode_$eq
  #130 = Utf8               (Lscala/collection/immutable/BitmapIndexedSetNode;)V
  #131 = Utf8               (Lscala/collection/immutable/BitmapIndexedSetNode<TA;>;)V
  #132 = Utf8               insertElement
  #133 = Utf8               ([III)[I
  #134 = Utf8               as
  #135 = Utf8               ix
  #136 = Utf8               java/lang/ArrayIndexOutOfBoundsException
  #137 = Class              #136          // java/lang/ArrayIndexOutOfBoundsException
  #138 = Utf8               ()V
  #139 = NameAndType        #111:#138     // "<init>":()V
  #140 = Methodref          #137.#139     // java/lang/ArrayIndexOutOfBoundsException."<init>":()V
  #141 = Utf8               java/lang/System
  #142 = Class              #141          // java/lang/System
  #143 = Utf8               arraycopy
  #144 = Utf8               (Ljava/lang/Object;ILjava/lang/Object;II)V
  #145 = NameAndType        #143:#144     // arraycopy:(Ljava/lang/Object;ILjava/lang/Object;II)V
  #146 = Methodref          #142.#145     // java/lang/System.arraycopy:(Ljava/lang/Object;ILjava/lang/Object;II)V
  #147 = Utf8               result
  #148 = Utf8               [I
  #149 = Utf8               insertValue
  #150 = Utf8               (Lscala/collection/immutable/BitmapIndexedSetNode;ILjava/lang/Object;II)V
  #151 = Utf8               <A1:Ljava/lang/Object;>(Lscala/collection/immutable/BitmapIndexedSetNode<TA;>;ITA;II)V
  #152 = Utf8               bm
  #153 = Utf8               bitpos
  #154 = Utf8               key
  #155 = Utf8               originalHash
  #156 = Utf8               keyHash
  #157 = Utf8               dataIndex
  #158 = Utf8               (I)I
  #159 = NameAndType        #157:#158     // dataIndex:(I)I
  #160 = Methodref          #96.#159      // scala/collection/immutable/BitmapIndexedSetNode.dataIndex:(I)I
  #161 = Utf8               content
  #162 = NameAndType        #161:#104     // content:()[Ljava/lang/Object;
  #163 = Methodref          #96.#162      // scala/collection/immutable/BitmapIndexedSetNode.content:()[Ljava/lang/Object;
  #164 = Utf8               originalHashes
  #165 = NameAndType        #164:#108     // originalHashes:()[I
  #166 = Methodref          #96.#165      // scala/collection/immutable/BitmapIndexedSetNode.originalHashes:()[I
  #167 = NameAndType        #132:#133     // insertElement:([III)[I
  #168 = Methodref          #2.#167       // scala/collection/immutable/HashSetBuilder.insertElement:([III)[I
  #169 = Utf8               dataMap
  #170 = NameAndType        #169:#41      // dataMap:()I
  #171 = Methodref          #96.#170      // scala/collection/immutable/BitmapIndexedSetNode.dataMap:()I
  #172 = Utf8               dataMap_$eq
  #173 = NameAndType        #172:#21      // dataMap_$eq:(I)V
  #174 = Methodref          #96.#173      // scala/collection/immutable/BitmapIndexedSetNode.dataMap_$eq:(I)V
  #175 = Utf8               content_$eq
  #176 = Utf8               ([Ljava/lang/Object;)V
  #177 = NameAndType        #175:#176     // content_$eq:([Ljava/lang/Object;)V
  #178 = Methodref          #96.#177      // scala/collection/immutable/BitmapIndexedSetNode.content_$eq:([Ljava/lang/Object;)V
  #179 = Utf8               originalHashes_$eq
  #180 = Utf8               ([I)V
  #181 = NameAndType        #179:#180     // originalHashes_$eq:([I)V
  #182 = Methodref          #96.#181      // scala/collection/immutable/BitmapIndexedSetNode.originalHashes_$eq:([I)V
  #183 = NameAndType        #22:#41       // size:()I
  #184 = Methodref          #96.#183      // scala/collection/immutable/BitmapIndexedSetNode.size:()I
  #185 = Utf8               size_$eq
  #186 = NameAndType        #185:#21      // size_$eq:(I)V
  #187 = Methodref          #96.#186      // scala/collection/immutable/BitmapIndexedSetNode.size_$eq:(I)V
  #188 = Utf8               cachedJavaKeySetHashCode
  #189 = NameAndType        #188:#41      // cachedJavaKeySetHashCode:()I
  #190 = Methodref          #96.#189      // scala/collection/immutable/BitmapIndexedSetNode.cachedJavaKeySetHashCode:()I
  #191 = Utf8               cachedJavaKeySetHashCode_$eq
  #192 = NameAndType        #191:#21      // cachedJavaKeySetHashCode_$eq:(I)V
  #193 = Methodref          #96.#192      // scala/collection/immutable/BitmapIndexedSetNode.cachedJavaKeySetHashCode_$eq:(I)V
  #194 = Utf8               dataIx
  #195 = Utf8               idx
  #196 = Utf8               src
  #197 = Utf8               [Ljava/lang/Object;
  #198 = Utf8               dst
  #199 = Utf8               dstHashes
  #200 = Utf8               setValue
  #201 = Utf8               (Lscala/collection/immutable/BitmapIndexedSetNode;ILjava/lang/Object;)V
  #202 = Utf8               <A1:Ljava/lang/Object;>(Lscala/collection/immutable/BitmapIndexedSetNode<TA;>;ITA;)V
  #203 = Utf8               update
  #204 = Utf8               (Lscala/collection/immutable/SetNode;Ljava/lang/Object;III)V
  #205 = Utf8               (Lscala/collection/immutable/SetNode<TA;>;TA;III)V
  #206 = Utf8               setNode
  #207 = Utf8               element
  #208 = Utf8               elementHash
  #209 = Utf8               shift
  #210 = Utf8               scala/collection/immutable/Node$
  #211 = Class              #210          // scala/collection/immutable/Node$
  #212 = Utf8               Lscala/collection/immutable/Node$;
  #213 = NameAndType        #99:#212      // MODULE$:Lscala/collection/immutable/Node$;
  #214 = Fieldref           #211.#213     // scala/collection/immutable/Node$.MODULE$:Lscala/collection/immutable/Node$;
  #215 = Utf8               indexFrom
  #216 = Utf8               (III)I
  #217 = NameAndType        #215:#216     // indexFrom:(III)I
  #218 = Methodref          #211.#217     // scala/collection/immutable/Node$.indexFrom:(III)I
  #219 = Utf8               scala/runtime/BoxesRunTime
  #220 = Class              #219          // scala/runtime/BoxesRunTime
  #221 = Utf8               equals
  #222 = Utf8               (Ljava/lang/Object;Ljava/lang/Object;)Z
  #223 = NameAndType        #221:#222     // equals:(Ljava/lang/Object;Ljava/lang/Object;)Z
  #224 = Methodref          #220.#223     // scala/runtime/BoxesRunTime.equals:(Ljava/lang/Object;Ljava/lang/Object;)Z
  #225 = NameAndType        #200:#201     // setValue:(Lscala/collection/immutable/BitmapIndexedSetNode;ILjava/lang/Object;)V
  #226 = Methodref          #2.#225       // scala/collection/immutable/HashSetBuilder.setValue:(Lscala/collection/immutable/BitmapIndexedSetNode;ILjava/lang/Object;)V
  #227 = Utf8               scala/collection/Hashing$
  #228 = Class              #227          // scala/collection/Hashing$
  #229 = Utf8               Lscala/collection/Hashing$;
  #230 = NameAndType        #99:#229      // MODULE$:Lscala/collection/Hashing$;
  #231 = Fieldref           #228.#230     // scala/collection/Hashing$.MODULE$:Lscala/collection/Hashing$;
  #232 = Utf8               improve
  #233 = NameAndType        #232:#158     // improve:(I)I
  #234 = Methodref          #228.#233     // scala/collection/Hashing$.improve:(I)I
  #235 = Utf8               mergeTwoKeyValPairs
  #236 = Utf8               (Ljava/lang/Object;IILjava/lang/Object;III)Lscala/collection/immutable/SetNode;
  #237 = NameAndType        #235:#236     // mergeTwoKeyValPairs:(Ljava/lang/Object;IILjava/lang/Object;III)Lscala/collection/immutable/SetNode;
  #238 = Methodref          #96.#237      // scala/collection/immutable/BitmapIndexedSetNode.mergeTwoKeyValPairs:(Ljava/lang/Object;IILjava/lang/Object;III)Lscala/collection/immutable/SetNode;
  #239 = Utf8               migrateFromInlineToNodeInPlace
  #240 = Utf8               (IILscala/collection/immutable/SetNode;)Lscala/collection/immutable/BitmapIndexedSetNode;
  #241 = NameAndType        #239:#240     // migrateFromInlineToNodeInPlace:(IILscala/collection/immutable/SetNode;)Lscala/collection/immutable/BitmapIndexedSetNode;
  #242 = Methodref          #96.#241      // scala/collection/immutable/BitmapIndexedSetNode.migrateFromInlineToNodeInPlace:(IILscala/collection/immutable/SetNode;)Lscala/collection/immutable/BitmapIndexedSetNode;
  #243 = Utf8               nodeMap
  #244 = NameAndType        #243:#41      // nodeMap:()I
  #245 = Methodref          #96.#244      // scala/collection/immutable/BitmapIndexedSetNode.nodeMap:()I
  #246 = Utf8               getNode
  #247 = Utf8               (I)Lscala/collection/immutable/SetNode;
  #248 = NameAndType        #246:#247     // getNode:(I)Lscala/collection/immutable/SetNode;
  #249 = Methodref          #96.#248      // scala/collection/immutable/BitmapIndexedSetNode.getNode:(I)Lscala/collection/immutable/SetNode;
  #250 = Utf8               scala/collection/immutable/SetNode
  #251 = Class              #250          // scala/collection/immutable/SetNode
  #252 = Methodref          #251.#183     // scala/collection/immutable/SetNode.size:()I
  #253 = Methodref          #251.#189     // scala/collection/immutable/SetNode.cachedJavaKeySetHashCode:()I
  #254 = NameAndType        #203:#204     // update:(Lscala/collection/immutable/SetNode;Ljava/lang/Object;III)V
  #255 = Methodref          #2.#254       // scala/collection/immutable/HashSetBuilder.update:(Lscala/collection/immutable/SetNode;Ljava/lang/Object;III)V
  #256 = NameAndType        #149:#150     // insertValue:(Lscala/collection/immutable/BitmapIndexedSetNode;ILjava/lang/Object;II)V
  #257 = Methodref          #2.#256       // scala/collection/immutable/HashSetBuilder.insertValue:(Lscala/collection/immutable/BitmapIndexedSetNode;ILjava/lang/Object;II)V
  #258 = Utf8               scala/collection/immutable/HashCollisionSetNode
  #259 = Class              #258          // scala/collection/immutable/HashCollisionSetNode
  #260 = Utf8               ()Lscala/collection/immutable/Vector;
  #261 = NameAndType        #161:#260     // content:()Lscala/collection/immutable/Vector;
  #262 = Methodref          #259.#261     // scala/collection/immutable/HashCollisionSetNode.content:()Lscala/collection/immutable/Vector;
  #263 = Utf8               scala/collection/immutable/Vector
  #264 = Class              #263          // scala/collection/immutable/Vector
  #265 = Utf8               indexOf
  #266 = Utf8               (Ljava/lang/Object;)I
  #267 = NameAndType        #265:#266     // indexOf:(Ljava/lang/Object;)I
  #268 = Methodref          #264.#267     // scala/collection/immutable/Vector.indexOf:(Ljava/lang/Object;)I
  #269 = Utf8               appended
  #270 = Utf8               (Ljava/lang/Object;)Lscala/collection/immutable/Vector;
  #271 = NameAndType        #269:#270     // appended:(Ljava/lang/Object;)Lscala/collection/immutable/Vector;
  #272 = Methodref          #264.#271     // scala/collection/immutable/Vector.appended:(Ljava/lang/Object;)Lscala/collection/immutable/Vector;
  #273 = Utf8               (Lscala/collection/immutable/Vector;)V
  #274 = NameAndType        #175:#273     // content_$eq:(Lscala/collection/immutable/Vector;)V
  #275 = Methodref          #259.#274     // scala/collection/immutable/HashCollisionSetNode.content_$eq:(Lscala/collection/immutable/Vector;)V
  #276 = Utf8               updated
  #277 = Utf8               (ILjava/lang/Object;)Lscala/collection/immutable/Vector;
  #278 = NameAndType        #276:#277     // updated:(ILjava/lang/Object;)Lscala/collection/immutable/Vector;
  #279 = Methodref          #264.#278     // scala/collection/immutable/Vector.updated:(ILjava/lang/Object;)Lscala/collection/immutable/Vector;
  #280 = Utf8               scala/MatchError
  #281 = Class              #280          // scala/MatchError
  #282 = Utf8               (Ljava/lang/Object;)V
  #283 = NameAndType        #111:#282     // "<init>":(Ljava/lang/Object;)V
  #284 = Methodref          #281.#283     // scala/MatchError."<init>":(Ljava/lang/Object;)V
  #285 = Utf8               element0Hash
  #286 = Utf8               subNodeNew
  #287 = Utf8               Lscala/collection/immutable/SetNode;
  #288 = Utf8               index
  #289 = Utf8               element0
  #290 = Utf8               subNode
  #291 = Utf8               beforeSize
  #292 = Utf8               beforeHashCode
  #293 = Utf8               ensureUnaliased
  #294 = NameAndType        #123:#124     // isAliased:()Z
  #295 = Methodref          #2.#294       // scala/collection/immutable/HashSetBuilder.isAliased:()Z
  #296 = Utf8               copyElems
  #297 = NameAndType        #296:#138     // copyElems:()V
  #298 = Methodref          #2.#297       // scala/collection/immutable/HashSetBuilder.copyElems:()V
  #299 = NameAndType        #119:#120     // aliased_$eq:(Lscala/collection/immutable/HashSet;)V
  #300 = Methodref          #2.#299       // scala/collection/immutable/HashSetBuilder.aliased_$eq:(Lscala/collection/immutable/HashSet;)V
  #301 = NameAndType        #17:#93       // scala$collection$immutable$HashSetBuilder$$rootNode:()Lscala/collection/immutable/BitmapIndexedSetNode;
  #302 = Methodref          #2.#301       // scala/collection/immutable/HashSetBuilder.scala$collection$immutable$HashSetBuilder$$rootNode:()Lscala/collection/immutable/BitmapIndexedSetNode;
  #303 = Utf8               copy
  #304 = NameAndType        #303:#93      // copy:()Lscala/collection/immutable/BitmapIndexedSetNode;
  #305 = Methodref          #96.#304      // scala/collection/immutable/BitmapIndexedSetNode.copy:()Lscala/collection/immutable/BitmapIndexedSetNode;
  #306 = NameAndType        #129:#130     // rootNode_$eq:(Lscala/collection/immutable/BitmapIndexedSetNode;)V
  #307 = Methodref          #2.#306       // scala/collection/immutable/HashSetBuilder.rootNode_$eq:(Lscala/collection/immutable/BitmapIndexedSetNode;)V
  #308 = Utf8               scala/collection/immutable/HashSet$
  #309 = Class              #308          // scala/collection/immutable/HashSet$
  #310 = Utf8               Lscala/collection/immutable/HashSet$;
  #311 = NameAndType        #99:#310      // MODULE$:Lscala/collection/immutable/HashSet$;
  #312 = Fieldref           #309.#311     // scala/collection/immutable/HashSet$.MODULE$:Lscala/collection/immutable/HashSet$;
  #313 = Utf8               empty
  #314 = NameAndType        #313:#115     // empty:()Lscala/collection/immutable/HashSet;
  #315 = Methodref          #309.#314     // scala/collection/immutable/HashSet$.empty:()Lscala/collection/immutable/HashSet;
  #316 = Utf8               scala/collection/immutable/HashSet
  #317 = Class              #316          // scala/collection/immutable/HashSet
  #318 = NameAndType        #111:#130     // "<init>":(Lscala/collection/immutable/BitmapIndexedSetNode;)V
  #319 = Methodref          #317.#318     // scala/collection/immutable/HashSet."<init>":(Lscala/collection/immutable/BitmapIndexedSetNode;)V
  #320 = Utf8               scala/runtime/Statics
  #321 = Class              #320          // scala/runtime/Statics
  #322 = Utf8               releaseFence
  #323 = NameAndType        #322:#138     // releaseFence:()V
  #324 = Methodref          #321.#323     // scala/runtime/Statics.releaseFence:()V
  #325 = Utf8               addOne
  #326 = Utf8               (Ljava/lang/Object;)Lscala/collection/immutable/HashSetBuilder;
  #327 = Utf8               (TA;)Lscala/collection/immutable/HashSetBuilder<TA;>;
  #328 = NameAndType        #293:#138     // ensureUnaliased:()V
  #329 = Methodref          #2.#328       // scala/collection/immutable/HashSetBuilder.ensureUnaliased:()V
  #330 = Utf8               anyHash
  #331 = NameAndType        #330:#266     // anyHash:(Ljava/lang/Object;)I
  #332 = Methodref          #321.#331     // scala/runtime/Statics.anyHash:(Ljava/lang/Object;)I
  #333 = Utf8               h
  #334 = Utf8               im
  #335 = Utf8               addAll
  #336 = Utf8               (Lscala/collection/IterableOnce;)Lscala/collection/immutable/HashSetBuilder;
  #337 = Utf8               (Lscala/collection/IterableOnce<TA;>;)Lscala/collection/immutable/HashSetBuilder<TA;>;
  #338 = Utf8               (Lscala/collection/immutable/HashSetBuilder;Lscala/collection/immutable/HashSet;)V
  #339 = NameAndType        #111:#338     // "<init>":(Lscala/collection/immutable/HashSetBuilder;Lscala/collection/immutable/HashSet;)V
  #340 = Methodref          #13.#339      // scala/collection/immutable/HashSetBuilder$$anon$1."<init>":(Lscala/collection/immutable/HashSetBuilder;Lscala/collection/immutable/HashSet;)V
  #341 = Utf8               scala/collection/IterableOnce
  #342 = Class              #341          // scala/collection/IterableOnce
  #343 = Utf8               iterator
  #344 = Utf8               ()Lscala/collection/Iterator;
  #345 = NameAndType        #343:#344     // iterator:()Lscala/collection/Iterator;
  #346 = InterfaceMethodref #342.#345     // scala/collection/IterableOnce.iterator:()Lscala/collection/Iterator;
  #347 = Utf8               scala/collection/Iterator
  #348 = Class              #347          // scala/collection/Iterator
  #349 = Utf8               hasNext
  #350 = NameAndType        #349:#124     // hasNext:()Z
  #351 = InterfaceMethodref #348.#350     // scala/collection/Iterator.hasNext:()Z
  #352 = Utf8               next
  #353 = Utf8               ()Ljava/lang/Object;
  #354 = NameAndType        #352:#353     // next:()Ljava/lang/Object;
  #355 = InterfaceMethodref #348.#354     // scala/collection/Iterator.next:()Ljava/lang/Object;
  #356 = NameAndType        #325:#326     // addOne:(Ljava/lang/Object;)Lscala/collection/immutable/HashSetBuilder;
  #357 = Methodref          #2.#356       // scala/collection/immutable/HashSetBuilder.addOne:(Ljava/lang/Object;)Lscala/collection/immutable/HashSetBuilder;
  #358 = Utf8               it
  #359 = Utf8               Lscala/collection/Iterator;
  #360 = Utf8               clear
  #361 = NameAndType        #92:#93       // newEmptyRootNode:()Lscala/collection/immutable/BitmapIndexedSetNode;
  #362 = Methodref          #2.#361       // scala/collection/immutable/HashSetBuilder.newEmptyRootNode:()Lscala/collection/immutable/BitmapIndexedSetNode;
  #363 = Utf8               knownSize
  #364 = NameAndType        #335:#336     // addAll:(Lscala/collection/IterableOnce;)Lscala/collection/immutable/HashSetBuilder;
  #365 = Methodref          #2.#364       // scala/collection/immutable/HashSetBuilder.addAll:(Lscala/collection/IterableOnce;)Lscala/collection/immutable/HashSetBuilder;
  #366 = NameAndType        #147:#115     // result:()Lscala/collection/immutable/HashSet;
  #367 = Methodref          #2.#366       // scala/collection/immutable/HashSetBuilder.result:()Lscala/collection/immutable/HashSet;
  #368 = Methodref          #5.#139       // java/lang/Object."<init>":()V
  #369 = Utf8               Signature
  #370 = Utf8               Code
  #371 = Utf8               LineNumberTable
  #372 = Utf8               LocalVariableTable
  #373 = Utf8               MethodParameters
  #374 = Utf8               Deprecated
  #375 = Utf8               StackMapTable
  #376 = Utf8               InnerClasses
  #377 = Utf8               SourceFile
  #378 = Utf8               RuntimeVisibleAnnotations
  #379 = Utf8               ScalaInlineInfo
  #380 = Utf8               ScalaSig
{
  private scala.collection.immutable.HashSet<A> aliased;
    descriptor: Lscala/collection/immutable/HashSet;
    flags: (0x0002) ACC_PRIVATE
    Signature: #16                          // Lscala/collection/immutable/HashSet<TA;>;

  private scala.collection.immutable.BitmapIndexedSetNode<A> scala$collection$immutable$HashSetBuilder$$rootNode;
    descriptor: Lscala/collection/immutable/BitmapIndexedSetNode;
    flags: (0x0002) ACC_PRIVATE
    Signature: #19                          // Lscala/collection/immutable/BitmapIndexedSetNode<TA;>;

  public void sizeHint(int);
    descriptor: (I)V
    flags: (0x0001) ACC_PUBLIC
    Code:
      stack=2, locals=2, args_size=2
         0: aload_0
         1: iload_1
         2: invokestatic  #28                 // InterfaceMethod scala/collection/mutable/Builder.sizeHint$:(Lscala/collection/mutable/Builder;I)V
         5: return
      LineNumberTable:
        line 1942: 0
      LocalVariableTable:
        Start  Length  Slot  Name   Signature
            0       6     0  this   Lscala/collection/immutable/HashSetBuilder;
            0       6     1  size   I
    MethodParameters:
      Name                           Flags
      size                           final

  public final void sizeHint(scala.collection.IterableOnce<?>, int);
    descriptor: (Lscala/collection/IterableOnce;I)V
    flags: (0x0011) ACC_PUBLIC, ACC_FINAL
    Code:
      stack=3, locals=3, args_size=3
         0: aload_0
         1: aload_1
         2: iload_2
         3: invokestatic  #38                 // InterfaceMethod scala/collection/mutable/Builder.sizeHint$:(Lscala/collection/mutable/Builder;Lscala/collection/IterableOnce;I)V
         6: return
      LineNumberTable:
        line 1942: 0
      LocalVariableTable:
        Start  Length  Slot  Name   Signature
            0       7     0  this   Lscala/collection/immutable/HashSetBuilder;
            0       7     1  coll   Lscala/collection/IterableOnce;
            0       7     2 delta   I
    Signature: #33                          // (Lscala/collection/IterableOnce<*>;I)V
    MethodParameters:
      Name                           Flags
      coll                           final
      delta                          final

  public final int sizeHint$default$2();
    descriptor: ()I
    flags: (0x0011) ACC_PUBLIC, ACC_FINAL
    Code:
      stack=1, locals=1, args_size=1
         0: aload_0
         1: invokestatic  #45                 // InterfaceMethod scala/collection/mutable/Builder.sizeHint$default$2$:(Lscala/collection/mutable/Builder;)I
         4: ireturn
      LineNumberTable:
        line 1942: 0
      LocalVariableTable:
        Start  Length  Slot  Name   Signature
            0       5     0  this   Lscala/collection/immutable/HashSetBuilder;

  public final void sizeHintBounded(int, scala.collection.Iterable<?>);
    descriptor: (ILscala/collection/Iterable;)V
    flags: (0x0011) ACC_PUBLIC, ACC_FINAL
    Code:
      stack=3, locals=3, args_size=3
         0: aload_0
         1: iload_1
         2: aload_2
         3: invokestatic  #53                 // InterfaceMethod scala/collection/mutable/Builder.sizeHintBounded$:(Lscala/collection/mutable/Builder;ILscala/collection/Iterable;)V
         6: return
      LineNumberTable:
        line 1942: 0
      LocalVariableTable:
        Start  Length  Slot  Name   Signature
            0       7     0  this   Lscala/collection/immutable/HashSetBuilder;
            0       7     1  size   I
            0       7     2 boundingColl   Lscala/collection/Iterable;
    Signature: #48                          // (ILscala/collection/Iterable<*>;)V
    MethodParameters:
      Name                           Flags
      size                           final
      boundingColl                   final

  public <NewTo extends java.lang.Object> scala.collection.mutable.Builder<A, NewTo> mapResult(scala.Function1<scala.collection.immutable.HashSet<A>, NewTo>);
    descriptor: (Lscala/Function1;)Lscala/collection/mutable/Builder;
    flags: (0x0001) ACC_PUBLIC
    Code:
      stack=2, locals=2, args_size=2
         0: aload_0
         1: aload_1
         2: invokestatic  #62                 // InterfaceMethod scala/collection/mutable/Builder.mapResult$:(Lscala/collection/mutable/Builder;Lscala/Function1;)Lscala/collection/mutable/Builder;
         5: areturn
      LineNumberTable:
        line 1942: 0
      LocalVariableTable:
        Start  Length  Slot  Name   Signature
            0       6     0  this   Lscala/collection/immutable/HashSetBuilder;
            0       6     1     f   Lscala/Function1;
    Signature: #57                          // <NewTo:Ljava/lang/Object;>(Lscala/Function1<Lscala/collection/immutable/HashSet<TA;>;TNewTo;>;)Lscala/collection/mutable/Builder<TA;TNewTo;>;
    MethodParameters:
      Name                           Flags
      f                              final

  public final scala.collection.mutable.Growable<A> $plus$eq(A);
    descriptor: (Ljava/lang/Object;)Lscala/collection/mutable/Growable;
    flags: (0x0011) ACC_PUBLIC, ACC_FINAL
    Code:
      stack=2, locals=2, args_size=2
         0: aload_0
         1: aload_1
         2: invokestatic  #73                 // InterfaceMethod scala/collection/mutable/Growable.$plus$eq$:(Lscala/collection/mutable/Growable;Ljava/lang/Object;)Lscala/collection/mutable/Growable;
         5: areturn
      LineNumberTable:
        line 1942: 0
      LocalVariableTable:
        Start  Length  Slot  Name   Signature
            0       6     0  this   Lscala/collection/immutable/HashSetBuilder;
            0       6     1  elem   Ljava/lang/Object;
    Signature: #66                          // (TA;)Lscala/collection/mutable/Growable<TA;>;
    MethodParameters:
      Name                           Flags
      elem                           final

  public final scala.collection.mutable.Growable<A> $plus$eq(A, A, scala.collection.immutable.Seq<A>);
    descriptor: (Ljava/lang/Object;Ljava/lang/Object;Lscala/collection/immutable/Seq;)Lscala/collection/mutable/Growable;
    flags: (0x0011) ACC_PUBLIC, ACC_FINAL
    Code:
      stack=4, locals=4, args_size=4
         0: aload_0
         1: aload_1
         2: aload_2
         3: aload_3
         4: invokestatic  #82                 // InterfaceMethod scala/collection/mutable/Growable.$plus$eq$:(Lscala/collection/mutable/Growable;Ljava/lang/Object;Ljava/lang/Object;Lscala/collection/immutable/Seq;)Lscala/collection/mutable/Growable;
         7: areturn
      LineNumberTable:
        line 1942: 0
      LocalVariableTable:
        Start  Length  Slot  Name   Signature
            0       8     0  this   Lscala/collection/immutable/HashSetBuilder;
            0       8     1 elem1   Ljava/lang/Object;
            0       8     2 elem2   Ljava/lang/Object;
            0       8     3 elems   Lscala/collection/immutable/Seq;
    Signature: #76                          // (TA;TA;Lscala/collection/immutable/Seq<TA;>;)Lscala/collection/mutable/Growable<TA;>;
    Deprecated: true
    MethodParameters:
      Name                           Flags
      elem1                          final
      elem2                          final
      elems                          final

  public final scala.collection.mutable.Growable<A> $plus$plus$eq(scala.collection.IterableOnce<A>);
    descriptor: (Lscala/collection/IterableOnce;)Lscala/collection/mutable/Growable;
    flags: (0x0011) ACC_PUBLIC, ACC_FINAL
    Code:
      stack=2, locals=2, args_size=2
         0: aload_0
         1: aload_1
         2: invokestatic  #91                 // InterfaceMethod scala/collection/mutable/Growable.$plus$plus$eq$:(Lscala/collection/mutable/Growable;Lscala/collection/IterableOnce;)Lscala/collection/mutable/Growable;
         5: areturn
      LineNumberTable:
        line 1942: 0
      LocalVariableTable:
        Start  Length  Slot  Name   Signature
            0       6     0  this   Lscala/collection/immutable/HashSetBuilder;
            0       6     1    xs   Lscala/collection/IterableOnce;
    Signature: #86                          // (Lscala/collection/IterableOnce<TA;>;)Lscala/collection/mutable/Growable<TA;>;
    MethodParameters:
      Name                           Flags
      xs                             final

  private scala.collection.immutable.BitmapIndexedSetNode<A> newEmptyRootNode();
    descriptor: ()Lscala/collection/immutable/BitmapIndexedSetNode;
    flags: (0x0002) ACC_PRIVATE
    Code:
      stack=8, locals=1, args_size=1
         0: new           #96                 // class scala/collection/immutable/BitmapIndexedSetNode
         3: dup
         4: iconst_0
         5: iconst_0
         6: getstatic     #102                // Field scala/Array$.MODULE$:Lscala/Array$;
         9: invokevirtual #106                // Method scala/Array$.emptyObjectArray:()[Ljava/lang/Object;
        12: getstatic     #102                // Field scala/Array$.MODULE$:Lscala/Array$;
        15: invokevirtual #110                // Method scala/Array$.emptyIntArray:()[I
        18: iconst_0
        19: iconst_0
        20: invokespecial #114                // Method scala/collection/immutable/BitmapIndexedSetNode."<init>":(II[Ljava/lang/Object;[III)V
        23: areturn
      LineNumberTable:
        line 1946: 0
      LocalVariableTable:
        Start  Length  Slot  Name   Signature
            0      24     0  this   Lscala/collection/immutable/HashSetBuilder;
    Signature: #94                          // ()Lscala/collection/immutable/BitmapIndexedSetNode<TA;>;

  private scala.collection.immutable.HashSet<A> aliased();
    descriptor: ()Lscala/collection/immutable/HashSet;
    flags: (0x0002) ACC_PRIVATE
    Code:
      stack=1, locals=1, args_size=1
         0: aload_0
         1: getfield      #118                // Field aliased:Lscala/collection/immutable/HashSet;
         4: areturn
      LineNumberTable:
        line 1951: 0
      LocalVariableTable:
        Start  Length  Slot  Name   Signature
            0       5     0  this   Lscala/collection/immutable/HashSetBuilder;
    Signature: #116                         // ()Lscala/collection/immutable/HashSet<TA;>;

  private void aliased_$eq(scala.collection.immutable.HashSet<A>);
    descriptor: (Lscala/collection/immutable/HashSet;)V
    flags: (0x0002) ACC_PRIVATE
    Code:
      stack=2, locals=2, args_size=2
         0: aload_0
         1: aload_1
         2: putfield      #118                // Field aliased:Lscala/collection/immutable/HashSet;
         5: return
      LineNumberTable:
        line 1951: 0
      LocalVariableTable:
        Start  Length  Slot  Name   Signature
            0       6     0  this   Lscala/collection/immutable/HashSetBuilder;
            0       6     1   x$1   Lscala/collection/immutable/HashSet;
    Signature: #121                         // (Lscala/collection/immutable/HashSet<TA;>;)V
    MethodParameters:
      Name                           Flags
      x$1                            final

  private boolean isAliased();
    descriptor: ()Z
    flags: (0x0002) ACC_PRIVATE
    Code:
      stack=1, locals=1, args_size=1
         0: aload_0
         1: invokespecial #126                // Method aliased:()Lscala/collection/immutable/HashSet;
         4: ifnull        9
         7: iconst_1
         8: ireturn
         9: iconst_0
        10: ireturn
      StackMapTable: number_of_entries = 1
        frame_type = 9 /* same */
      LineNumberTable:
        line 1953: 0
      LocalVariableTable:
        Start  Length  Slot  Name   Signature
            0      11     0  this   Lscala/collection/immutable/HashSetBuilder;

  public scala.collection.immutable.BitmapIndexedSetNode<A> scala$collection$immutable$HashSetBuilder$$rootNode();
    descriptor: ()Lscala/collection/immutable/BitmapIndexedSetNode;
    flags: (0x0001) ACC_PUBLIC
    Code:
      stack=1, locals=1, args_size=1
         0: aload_0
         1: getfield      #128                // Field scala$collection$immutable$HashSetBuilder$$rootNode:Lscala/collection/immutable/BitmapIndexedSetNode;
         4: areturn
      LineNumberTable:
        line 1956: 0
      LocalVariableTable:
        Start  Length  Slot  Name   Signature
            0       5     0  this   Lscala/collection/immutable/HashSetBuilder;
    Signature: #94                          // ()Lscala/collection/immutable/BitmapIndexedSetNode<TA;>;

  private void rootNode_$eq(scala.collection.immutable.BitmapIndexedSetNode<A>);
    descriptor: (Lscala/collection/immutable/BitmapIndexedSetNode;)V
    flags: (0x0002) ACC_PRIVATE
    Code:
      stack=2, locals=2, args_size=2
         0: aload_0
         1: aload_1
         2: putfield      #128                // Field scala$collection$immutable$HashSetBuilder$$rootNode:Lscala/collection/immutable/BitmapIndexedSetNode;
         5: return
      LineNumberTable:
        line 1956: 0
      LocalVariableTable:
        Start  Length  Slot  Name   Signature
            0       6     0  this   Lscala/collection/immutable/HashSetBuilder;
            0       6     1   x$1   Lscala/collection/immutable/BitmapIndexedSetNode;
    Signature: #131                         // (Lscala/collection/immutable/BitmapIndexedSetNode<TA;>;)V
    MethodParameters:
      Name                           Flags
      x$1                            final

  private int[] insertElement(int[], int, int);
    descriptor: ([III)[I
    flags: (0x0002) ACC_PRIVATE
    Code:
      stack=6, locals=5, args_size=4
         0: iload_2
         1: iconst_0
         2: if_icmpge     13
         5: new           #137                // class java/lang/ArrayIndexOutOfBoundsException
         8: dup
         9: invokespecial #140                // Method java/lang/ArrayIndexOutOfBoundsException."<init>":()V
        12: athrow
        13: iload_2
        14: aload_1
        15: arraylength
        16: if_icmple     27
        19: new           #137                // class java/lang/ArrayIndexOutOfBoundsException
        22: dup
        23: invokespecial #140                // Method java/lang/ArrayIndexOutOfBoundsException."<init>":()V
        26: athrow
        27: aload_1
        28: arraylength
        29: iconst_1
        30: iadd
        31: newarray       int
        33: astore        4
        35: aload_1
        36: iconst_0
        37: aload         4
        39: iconst_0
        40: iload_2
        41: invokestatic  #146                // Method java/lang/System.arraycopy:(Ljava/lang/Object;ILjava/lang/Object;II)V
        44: aload         4
        46: iload_2
        47: iload_3
        48: iastore
        49: aload_1
        50: iload_2
        51: aload         4
        53: iload_2
        54: iconst_1
        55: iadd
        56: aload_1
        57: arraylength
        58: iload_2
        59: isub
        60: invokestatic  #146                // Method java/lang/System.arraycopy:(Ljava/lang/Object;ILjava/lang/Object;II)V
        63: aload         4
        65: areturn
      StackMapTable: number_of_entries = 2
        frame_type = 13 /* same */
        frame_type = 13 /* same */
      LineNumberTable:
        line 1960: 0
        line 1961: 13
        line 1962: 27
        line 1963: 35
        line 1964: 44
        line 1965: 49
        line 1966: 63
      LocalVariableTable:
        Start  Length  Slot  Name   Signature
           35      30     4 result   [I
            0      66     0  this   Lscala/collection/immutable/HashSetBuilder;
            0      66     1    as   [I
            0      66     2    ix   I
            0      66     3  elem   I
    MethodParameters:
      Name                           Flags
      as                             final
      ix                             final
      elem                           final

  private <A1 extends java.lang.Object> void insertValue(scala.collection.immutable.BitmapIndexedSetNode<A>, int, A, int, int);
    descriptor: (Lscala/collection/immutable/BitmapIndexedSetNode;ILjava/lang/Object;II)V
    flags: (0x0002) ACC_PRIVATE
    Code:
      stack=6, locals=11, args_size=6
         0: aload_1
         1: iload_2
         2: invokevirtual #160                // Method scala/collection/immutable/BitmapIndexedSetNode.dataIndex:(I)I
         5: istore        6
         7: iconst_1
         8: iload         6
        10: imul
        11: istore        7
        13: aload_1
        14: invokevirtual #163                // Method scala/collection/immutable/BitmapIndexedSetNode.content:()[Ljava/lang/Object;
        17: astore        8
        19: aload         8
        21: arraylength
        22: iconst_1
        23: iadd
        24: anewarray     #5                  // class java/lang/Object
        27: astore        9
        29: aload         8
        31: iconst_0
        32: aload         9
        34: iconst_0
        35: iload         7
        37: invokestatic  #146                // Method java/lang/System.arraycopy:(Ljava/lang/Object;ILjava/lang/Object;II)V
        40: aload         9
        42: iload         7
        44: aload_3
        45: aastore
        46: aload         8
        48: iload         7
        50: aload         9
        52: iload         7
        54: iconst_1
        55: iadd
        56: aload         8
        58: arraylength
        59: iload         7
        61: isub
        62: invokestatic  #146                // Method java/lang/System.arraycopy:(Ljava/lang/Object;ILjava/lang/Object;II)V
        65: aload_0
        66: aload_1
        67: invokevirtual #166                // Method scala/collection/immutable/BitmapIndexedSetNode.originalHashes:()[I
        70: iload         6
        72: iload         4
        74: invokespecial #168                // Method insertElement:([III)[I
        77: astore        10
        79: aload_1
        80: aload_1
        81: invokevirtual #171                // Method scala/collection/immutable/BitmapIndexedSetNode.dataMap:()I
        84: iload_2
        85: ior
        86: invokevirtual #174                // Method scala/collection/immutable/BitmapIndexedSetNode.dataMap_$eq:(I)V
        89: aload_1
        90: aload         9
        92: invokevirtual #178                // Method scala/collection/immutable/BitmapIndexedSetNode.content_$eq:([Ljava/lang/Object;)V
        95: aload_1
        96: aload         10
        98: invokevirtual #182                // Method scala/collection/immutable/BitmapIndexedSetNode.originalHashes_$eq:([I)V
       101: aload_1
       102: aload_1
       103: invokevirtual #184                // Method scala/collection/immutable/BitmapIndexedSetNode.size:()I
       106: iconst_1
       107: iadd
       108: invokevirtual #187                // Method scala/collection/immutable/BitmapIndexedSetNode.size_$eq:(I)V
       111: aload_1
       112: aload_1
       113: invokevirtual #190                // Method scala/collection/immutable/BitmapIndexedSetNode.cachedJavaKeySetHashCode:()I
       116: iload         5
       118: iadd
       119: invokevirtual #193                // Method scala/collection/immutable/BitmapIndexedSetNode.cachedJavaKeySetHashCode_$eq:(I)V
       122: return
      LineNumberTable:
        line 1971: 0
        line 1972: 7
        line 1974: 13
        line 1975: 19
        line 1978: 29
        line 1979: 40
        line 1980: 46
        line 1982: 65
        line 1984: 79
        line 1985: 89
        line 1986: 95
        line 1987: 101
        line 1988: 111
      LocalVariableTable:
        Start  Length  Slot  Name   Signature
            7     115     6 dataIx   I
           13     109     7   idx   I
           19     103     8   src   [Ljava/lang/Object;
           29      93     9   dst   [Ljava/lang/Object;
           79      43    10 dstHashes   [I
            0     123     0  this   Lscala/collection/immutable/HashSetBuilder;
            0     123     1    bm   Lscala/collection/immutable/BitmapIndexedSetNode;
            0     123     2 bitpos   I
            0     123     3   key   Ljava/lang/Object;
            0     123     4 originalHash   I
            0     123     5 keyHash   I
    Signature: #151                         // <A1:Ljava/lang/Object;>(Lscala/collection/immutable/BitmapIndexedSetNode<TA;>;ITA;II)V
    MethodParameters:
      Name                           Flags
      bm                             final
      bitpos                         final
      key                            final
      originalHash                   final
      keyHash                        final

  private <A1 extends java.lang.Object> void setValue(scala.collection.immutable.BitmapIndexedSetNode<A>, int, A);
    descriptor: (Lscala/collection/immutable/BitmapIndexedSetNode;ILjava/lang/Object;)V
    flags: (0x0002) ACC_PRIVATE
    Code:
      stack=3, locals=6, args_size=4
         0: aload_1
         1: iload_2
         2: invokevirtual #160                // Method scala/collection/immutable/BitmapIndexedSetNode.dataIndex:(I)I
         5: istore        4
         7: iconst_1
         8: iload         4
        10: imul
        11: istore        5
        13: aload_1
        14: invokevirtual #163                // Method scala/collection/immutable/BitmapIndexedSetNode.content:()[Ljava/lang/Object;
        17: iload         5
        19: aload_3
        20: aastore
        21: return
      LineNumberTable:
        line 1993: 0
        line 1994: 7
        line 1995: 13
      LocalVariableTable:
        Start  Length  Slot  Name   Signature
            7      14     4 dataIx   I
           13       8     5   idx   I
            0      22     0  this   Lscala/collection/immutable/HashSetBuilder;
            0      22     1    bm   Lscala/collection/immutable/BitmapIndexedSetNode;
            0      22     2 bitpos   I
            0      22     3  elem   Ljava/lang/Object;
    Signature: #202                         // <A1:Ljava/lang/Object;>(Lscala/collection/immutable/BitmapIndexedSetNode<TA;>;ITA;)V
    MethodParameters:
      Name                           Flags
      bm                             final
      bitpos                         final
      elem                           final

  public void update(scala.collection.immutable.SetNode<A>, A, int, int, int);
    descriptor: (Lscala/collection/immutable/SetNode;Ljava/lang/Object;III)V
    flags: (0x0001) ACC_PUBLIC
    Code:
      stack=9, locals=21, args_size=6
         0: aload_1
         1: instanceof    #96                 // class scala/collection/immutable/BitmapIndexedSetNode
         4: ifeq          281
         7: aload_1
         8: checkcast     #96                 // class scala/collection/immutable/BitmapIndexedSetNode
        11: astore        6
        13: getstatic     #214                // Field scala/collection/immutable/Node$.MODULE$:Lscala/collection/immutable/Node$;
        16: pop
        17: iload         4
        19: iload         5
        21: iushr
        22: bipush        31
        24: iand
        25: istore        19
        27: getstatic     #214                // Field scala/collection/immutable/Node$.MODULE$:Lscala/collection/immutable/Node$;
        30: pop
        31: iconst_1
        32: iload         19
        34: ishl
        35: istore        20
        37: aload         6
        39: invokevirtual #171                // Method scala/collection/immutable/BitmapIndexedSetNode.dataMap:()I
        42: iload         20
        44: iand
        45: iconst_0
        46: if_icmpeq     163
        49: getstatic     #214                // Field scala/collection/immutable/Node$.MODULE$:Lscala/collection/immutable/Node$;
        52: aload         6
        54: invokevirtual #171                // Method scala/collection/immutable/BitmapIndexedSetNode.dataMap:()I
        57: iload         19
        59: iload         20
        61: invokevirtual #218                // Method scala/collection/immutable/Node$.indexFrom:(III)I
        64: istore        7
        66: aload         6
        68: invokevirtual #163                // Method scala/collection/immutable/BitmapIndexedSetNode.content:()[Ljava/lang/Object;
        71: iload         7
        73: aaload
        74: astore        17
        76: aload         17
        78: aconst_null
        79: astore        17
        81: astore        8
        83: aload         6
        85: invokevirtual #166                // Method scala/collection/immutable/BitmapIndexedSetNode.originalHashes:()[I
        88: iload         7
        90: iaload
        91: istore        18
        93: iload         18
        95: iload_3
        96: if_icmpne     119
        99: aload         8
       101: aload_2
       102: invokestatic  #224                // Method scala/runtime/BoxesRunTime.equals:(Ljava/lang/Object;Ljava/lang/Object;)Z
       105: ifeq          119
       108: aload_0
       109: aload         6
       111: iload         20
       113: aload         8
       115: invokespecial #226                // Method setValue:(Lscala/collection/immutable/BitmapIndexedSetNode;ILjava/lang/Object;)V
       118: return
       119: getstatic     #231                // Field scala/collection/Hashing$.MODULE$:Lscala/collection/Hashing$;
       122: iload         18
       124: invokevirtual #234                // Method scala/collection/Hashing$.improve:(I)I
       127: istore        9
       129: aload         6
       131: aload         8
       133: iload         18
       135: iload         9
       137: aload_2
       138: iload_3
       139: iload         4
       141: iload         5
       143: iconst_5
       144: iadd
       145: invokevirtual #238                // Method scala/collection/immutable/BitmapIndexedSetNode.mergeTwoKeyValPairs:(Ljava/lang/Object;IILjava/lang/Object;III)Lscala/collection/immutable/SetNode;
       148: astore        10
       150: aload         6
       152: iload         20
       154: iload         9
       156: aload         10
       158: invokevirtual #242                // Method scala/collection/immutable/BitmapIndexedSetNode.migrateFromInlineToNodeInPlace:(IILscala/collection/immutable/SetNode;)Lscala/collection/immutable/BitmapIndexedSetNode;
       161: pop
       162: return
       163: aload         6
       165: invokevirtual #245                // Method scala/collection/immutable/BitmapIndexedSetNode.nodeMap:()I
       168: iload         20
       170: iand
       171: iconst_0
       172: if_icmpeq     268
       175: getstatic     #214                // Field scala/collection/immutable/Node$.MODULE$:Lscala/collection/immutable/Node$;
       178: aload         6
       180: invokevirtual #245                // Method scala/collection/immutable/BitmapIndexedSetNode.nodeMap:()I
       183: iload         19
       185: iload         20
       187: invokevirtual #218                // Method scala/collection/immutable/Node$.indexFrom:(III)I
       190: istore        11
       192: aload         6
       194: iload         11
       196: invokevirtual #249                // Method scala/collection/immutable/BitmapIndexedSetNode.getNode:(I)Lscala/collection/immutable/SetNode;
       199: astore        12
       201: aload         12
       203: invokevirtual #252                // Method scala/collection/immutable/SetNode.size:()I
       206: istore        13
       208: aload         12
       210: invokevirtual #253                // Method scala/collection/immutable/SetNode.cachedJavaKeySetHashCode:()I
       213: istore        14
       215: aload_0
       216: aload         12
       218: aload_2
       219: iload_3
       220: iload         4
       222: iload         5
       224: iconst_5
       225: iadd
       226: invokevirtual #255                // Method update:(Lscala/collection/immutable/SetNode;Ljava/lang/Object;III)V
       229: aload         6
       231: aload         6
       233: invokevirtual #184                // Method scala/collection/immutable/BitmapIndexedSetNode.size:()I
       236: aload         12
       238: invokevirtual #252                // Method scala/collection/immutable/SetNode.size:()I
       241: iload         13
       243: isub
       244: iadd
       245: invokevirtual #187                // Method scala/collection/immutable/BitmapIndexedSetNode.size_$eq:(I)V
       248: aload         6
       250: aload         6
       252: invokevirtual #190                // Method scala/collection/immutable/BitmapIndexedSetNode.cachedJavaKeySetHashCode:()I
       255: aload         12
       257: invokevirtual #253                // Method scala/collection/immutable/SetNode.cachedJavaKeySetHashCode:()I
       260: iload         14
       262: isub
       263: iadd
       264: invokevirtual #193                // Method scala/collection/immutable/BitmapIndexedSetNode.cachedJavaKeySetHashCode_$eq:(I)V
       267: return
       268: aload_0
       269: aload         6
       271: iload         20
       273: aload_2
       274: iload_3
       275: iload         4
       277: invokespecial #257                // Method insertValue:(Lscala/collection/immutable/BitmapIndexedSetNode;ILjava/lang/Object;II)V
       280: return
       281: aload_1
       282: instanceof    #259                // class scala/collection/immutable/HashCollisionSetNode
       285: ifeq          343
       288: aload_1
       289: checkcast     #259                // class scala/collection/immutable/HashCollisionSetNode
       292: astore        15
       294: aload         15
       296: invokevirtual #262                // Method scala/collection/immutable/HashCollisionSetNode.content:()Lscala/collection/immutable/Vector;
       299: aload_2
       300: invokevirtual #268                // Method scala/collection/immutable/Vector.indexOf:(Ljava/lang/Object;)I
       303: istore        16
       305: iload         16
       307: iconst_0
       308: if_icmpge     326
       311: aload         15
       313: aload         15
       315: invokevirtual #262                // Method scala/collection/immutable/HashCollisionSetNode.content:()Lscala/collection/immutable/Vector;
       318: aload_2
       319: invokevirtual #272                // Method scala/collection/immutable/Vector.appended:(Ljava/lang/Object;)Lscala/collection/immutable/Vector;
       322: invokevirtual #275                // Method scala/collection/immutable/HashCollisionSetNode.content_$eq:(Lscala/collection/immutable/Vector;)V
       325: return
       326: aload         15
       328: aload         15
       330: invokevirtual #262                // Method scala/collection/immutable/HashCollisionSetNode.content:()Lscala/collection/immutable/Vector;
       333: iload         16
       335: aload_2
       336: invokevirtual #279                // Method scala/collection/immutable/Vector.updated:(ILjava/lang/Object;)Lscala/collection/immutable/Vector;
       339: invokevirtual #275                // Method scala/collection/immutable/HashCollisionSetNode.content_$eq:(Lscala/collection/immutable/Vector;)V
       342: return
       343: new           #281                // class scala/MatchError
       346: dup
       347: aload_1
       348: invokespecial #284                // Method scala/MatchError."<init>":(Ljava/lang/Object;)V
       351: athrow
      StackMapTable: number_of_entries = 6
        frame_type = 255 /* full_frame */
          offset_delta = 119
          locals = [ class scala/collection/immutable/HashSetBuilder, class scala/collection/immutable/SetNode, class java/lang/Object, int, int, int, class scala/collection/immutable/BitmapIndexedSetNode, int, class java/lang/Object, top, top, top, top, top, top, top, top, null, int, int, int ]
          stack = []
        frame_type = 255 /* full_frame */
          offset_delta = 43
          locals = [ class scala/collection/immutable/HashSetBuilder, class scala/collection/immutable/SetNode, class java/lang/Object, int, int, int, class scala/collection/immutable/BitmapIndexedSetNode, top, top, top, top, top, top, top, top, top, top, top, top, int, int ]
          stack = []
        frame_type = 251 /* same_frame_extended */
          offset_delta = 104
        frame_type = 255 /* full_frame */
          offset_delta = 12
          locals = [ class scala/collection/immutable/HashSetBuilder, class scala/collection/immutable/SetNode, class java/lang/Object, int, int, int ]
          stack = []
        frame_type = 255 /* full_frame */
          offset_delta = 44
          locals = [ class scala/collection/immutable/HashSetBuilder, class scala/collection/immutable/SetNode, class java/lang/Object, int, int, int, top, top, top, top, top, top, top, top, top, class scala/collection/immutable/HashCollisionSetNode, int ]
          stack = []
        frame_type = 255 /* full_frame */
          offset_delta = 16
          locals = [ class scala/collection/immutable/HashSetBuilder, class scala/collection/immutable/SetNode, class java/lang/Object, int, int, int ]
          stack = []
      LineNumberTable:
        line 2000: 0
        line 2001: 13
        line 2002: 27
        line 2004: 37
        line 2005: 49
        line 437: 66
        line 2006: 76
        line 439: 83
        line 2009: 93
        line 2010: 108
        line 2012: 119
        line 2013: 129
        line 2014: 150
        line 2016: 163
        line 2017: 175
        line 2018: 192
        line 2019: 201
        line 2020: 208
        line 2021: 215
        line 2022: 229
        line 2023: 248
        line 2025: 268
        line 2027: 281
        line 2028: 294
        line 2029: 305
        line 2030: 311
        line 2032: 326
        line 1999: 343
      LocalVariableTable:
        Start  Length  Slot  Name   Signature
          129      33     9 element0Hash   I
          150      12    10 subNodeNew   Lscala/collection/immutable/SetNode;
           66      96     7 index   I
           83      79     8 element0   Ljava/lang/Object;
          192      75    11 index   I
          201      66    12 subNode   Lscala/collection/immutable/SetNode;
          208      59    13 beforeSize   I
          215      52    14 beforeHashCode   I
          305      37    16 index   I
            0     352     0  this   Lscala/collection/immutable/HashSetBuilder;
            0     352     1 setNode   Lscala/collection/immutable/SetNode;
            0     352     2 element   Ljava/lang/Object;
            0     352     3 originalHash   I
            0     352     4 elementHash   I
            0     352     5 shift   I
    Signature: #205                         // (Lscala/collection/immutable/SetNode<TA;>;TA;III)V
    MethodParameters:
      Name                           Flags
      setNode                        final
      element                        final
      originalHash                   final
      elementHash                    final
      shift                          final

  private void ensureUnaliased();
    descriptor: ()V
    flags: (0x0002) ACC_PRIVATE
    Code:
      stack=2, locals=1, args_size=1
         0: aload_0
         1: invokespecial #295                // Method isAliased:()Z
         4: ifeq          11
         7: aload_0
         8: invokespecial #298                // Method copyElems:()V
        11: aload_0
        12: aconst_null
        13: invokespecial #300                // Method aliased_$eq:(Lscala/collection/immutable/HashSet;)V
        16: return
      StackMapTable: number_of_entries = 1
        frame_type = 11 /* same */
      LineNumberTable:
        line 2038: 0
        line 2039: 11
      LocalVariableTable:
        Start  Length  Slot  Name   Signature
            0      17     0  this   Lscala/collection/immutable/HashSetBuilder;

  private void copyElems();
    descriptor: ()V
    flags: (0x0002) ACC_PRIVATE
    Code:
      stack=2, locals=1, args_size=1
         0: aload_0
         1: aload_0
         2: invokevirtual #302                // Method scala$collection$immutable$HashSetBuilder$$rootNode:()Lscala/collection/immutable/BitmapIndexedSetNode;
         5: invokevirtual #305                // Method scala/collection/immutable/BitmapIndexedSetNode.copy:()Lscala/collection/immutable/BitmapIndexedSetNode;
         8: invokespecial #307                // Method rootNode_$eq:(Lscala/collection/immutable/BitmapIndexedSetNode;)V
        11: return
      LineNumberTable:
        line 2044: 0
      LocalVariableTable:
        Start  Length  Slot  Name   Signature
            0      12     0  this   Lscala/collection/immutable/HashSetBuilder;

  public scala.collection.immutable.HashSet<A> result();
    descriptor: ()Lscala/collection/immutable/HashSet;
    flags: (0x0001) ACC_PUBLIC
    Code:
      stack=4, locals=1, args_size=1
         0: aload_0
         1: invokevirtual #302                // Method scala$collection$immutable$HashSetBuilder$$rootNode:()Lscala/collection/immutable/BitmapIndexedSetNode;
         4: invokevirtual #184                // Method scala/collection/immutable/BitmapIndexedSetNode.size:()I
         7: iconst_0
         8: if_icmpne     18
        11: getstatic     #312                // Field scala/collection/immutable/HashSet$.MODULE$:Lscala/collection/immutable/HashSet$;
        14: invokevirtual #315                // Method scala/collection/immutable/HashSet$.empty:()Lscala/collection/immutable/HashSet;
        17: areturn
        18: aload_0
        19: invokespecial #126                // Method aliased:()Lscala/collection/immutable/HashSet;
        22: ifnull        30
        25: aload_0
        26: invokespecial #126                // Method aliased:()Lscala/collection/immutable/HashSet;
        29: areturn
        30: aload_0
        31: new           #317                // class scala/collection/immutable/HashSet
        34: dup
        35: aload_0
        36: invokevirtual #302                // Method scala$collection$immutable$HashSetBuilder$$rootNode:()Lscala/collection/immutable/BitmapIndexedSetNode;
        39: invokespecial #319                // Method scala/collection/immutable/HashSet."<init>":(Lscala/collection/immutable/BitmapIndexedSetNode;)V
        42: invokespecial #300                // Method aliased_$eq:(Lscala/collection/immutable/HashSet;)V
        45: invokestatic  #324                // Method scala/runtime/Statics.releaseFence:()V
        48: aload_0
        49: invokespecial #126                // Method aliased:()Lscala/collection/immutable/HashSet;
        52: areturn
      StackMapTable: number_of_entries = 2
        frame_type = 18 /* same */
        frame_type = 11 /* same */
      LineNumberTable:
        line 2048: 0
        line 2049: 11
        line 2050: 18
        line 2051: 25
        line 2053: 30
        line 2054: 45
        line 2055: 48
      LocalVariableTable:
        Start  Length  Slot  Name   Signature
            0      53     0  this   Lscala/collection/immutable/HashSetBuilder;
    Signature: #116                         // ()Lscala/collection/immutable/HashSet<TA;>;

  public scala.collection.immutable.HashSetBuilder<A> addOne(A);
    descriptor: (Ljava/lang/Object;)Lscala/collection/immutable/HashSetBuilder;
    flags: (0x0001) ACC_PUBLIC
    Code:
      stack=6, locals=4, args_size=2
         0: aload_0
         1: invokespecial #329                // Method ensureUnaliased:()V
         4: aload_1
         5: invokestatic  #332                // Method scala/runtime/Statics.anyHash:(Ljava/lang/Object;)I
         8: istore_2
         9: getstatic     #231                // Field scala/collection/Hashing$.MODULE$:Lscala/collection/Hashing$;
        12: iload_2
        13: invokevirtual #234                // Method scala/collection/Hashing$.improve:(I)I
        16: istore_3
        17: aload_0
        18: aload_0
        19: invokevirtual #302                // Method scala$collection$immutable$HashSetBuilder$$rootNode:()Lscala/collection/immutable/BitmapIndexedSetNode;
        22: aload_1
        23: iload_2
        24: iload_3
        25: iconst_0
        26: invokevirtual #255                // Method update:(Lscala/collection/immutable/SetNode;Ljava/lang/Object;III)V
        29: aload_0
        30: areturn
      LineNumberTable:
        line 2059: 0
        line 2060: 4
        line 2061: 9
        line 2062: 17
        line 2063: 29
      LocalVariableTable:
        Start  Length  Slot  Name   Signature
            9      21     2     h   I
           17      13     3    im   I
            0      31     0  this   Lscala/collection/immutable/HashSetBuilder;
            0      31     1  elem   Ljava/lang/Object;
    Signature: #327                         // (TA;)Lscala/collection/immutable/HashSetBuilder<TA;>;
    MethodParameters:
      Name                           Flags
      elem                           final

  public scala.collection.immutable.HashSetBuilder<A> addAll(scala.collection.IterableOnce<A>);
    descriptor: (Lscala/collection/IterableOnce;)Lscala/collection/immutable/HashSetBuilder;
    flags: (0x0001) ACC_PUBLIC
    Code:
      stack=3, locals=4, args_size=2
         0: aload_0
         1: invokespecial #329                // Method ensureUnaliased:()V
         4: aload_1
         5: instanceof    #317                // class scala/collection/immutable/HashSet
         8: ifeq          27
        11: aload_1
        12: checkcast     #317                // class scala/collection/immutable/HashSet
        15: astore_2
        16: new           #13                 // class scala/collection/immutable/HashSetBuilder$$anon$1
        19: aload_0
        20: aload_2
        21: invokespecial #340                // Method scala/collection/immutable/HashSetBuilder$$anon$1."<init>":(Lscala/collection/immutable/HashSetBuilder;Lscala/collection/immutable/HashSet;)V
        24: goto          57
        27: aload_1
        28: invokeinterface #346,  1          // InterfaceMethod scala/collection/IterableOnce.iterator:()Lscala/collection/Iterator;
        33: astore_3
        34: aload_3
        35: invokeinterface #351,  1          // InterfaceMethod scala/collection/Iterator.hasNext:()Z
        40: ifeq          57
        43: aload_0
        44: aload_3
        45: invokeinterface #355,  1          // InterfaceMethod scala/collection/Iterator.next:()Ljava/lang/Object;
        50: invokevirtual #357                // Method addOne:(Ljava/lang/Object;)Lscala/collection/immutable/HashSetBuilder;
        53: pop
        54: goto          34
        57: aload_0
        58: areturn
      StackMapTable: number_of_entries = 3
        frame_type = 27 /* same */
        frame_type = 253 /* append */
          offset_delta = 6
          locals = [ top, class scala/collection/Iterator ]
        frame_type = 249 /* chop */
          offset_delta = 22
      LineNumberTable:
        line 2067: 0
        line 2069: 4
        line 2070: 16
        line 2084: 27
        line 2085: 34
        line 2088: 57
      LocalVariableTable:
        Start  Length  Slot  Name   Signature
           34      23     3    it   Lscala/collection/Iterator;
            0      59     0  this   Lscala/collection/immutable/HashSetBuilder;
            0      59     1    xs   Lscala/collection/IterableOnce;
    Signature: #337                         // (Lscala/collection/IterableOnce<TA;>;)Lscala/collection/immutable/HashSetBuilder<TA;>;
    MethodParameters:
      Name                           Flags
      xs                             final

  public void clear();
    descriptor: ()V
    flags: (0x0001) ACC_PUBLIC
    Code:
      stack=2, locals=1, args_size=1
         0: aload_0
         1: aconst_null
         2: invokespecial #300                // Method aliased_$eq:(Lscala/collection/immutable/HashSet;)V
         5: aload_0
         6: invokevirtual #302                // Method scala$collection$immutable$HashSetBuilder$$rootNode:()Lscala/collection/immutable/BitmapIndexedSetNode;
         9: invokevirtual #184                // Method scala/collection/immutable/BitmapIndexedSetNode.size:()I
        12: iconst_0
        13: if_icmple     24
        16: aload_0
        17: aload_0
        18: invokespecial #362                // Method newEmptyRootNode:()Lscala/collection/immutable/BitmapIndexedSetNode;
        21: invokespecial #307                // Method rootNode_$eq:(Lscala/collection/immutable/BitmapIndexedSetNode;)V
        24: return
      StackMapTable: number_of_entries = 1
        frame_type = 24 /* same */
      LineNumberTable:
        line 2092: 0
        line 2093: 5
        line 2095: 16
        line 2093: 24
      LocalVariableTable:
        Start  Length  Slot  Name   Signature
            0      25     0  this   Lscala/collection/immutable/HashSetBuilder;

  public int size();
    descriptor: ()I
    flags: (0x0001) ACC_PUBLIC
    Code:
      stack=1, locals=1, args_size=1
         0: aload_0
         1: invokevirtual #302                // Method scala$collection$immutable$HashSetBuilder$$rootNode:()Lscala/collection/immutable/BitmapIndexedSetNode;
         4: invokevirtual #184                // Method scala/collection/immutable/BitmapIndexedSetNode.size:()I
         7: ireturn
      LineNumberTable:
        line 2099: 0
      LocalVariableTable:
        Start  Length  Slot  Name   Signature
            0       8     0  this   Lscala/collection/immutable/HashSetBuilder;

  public int knownSize();
    descriptor: ()I
    flags: (0x0001) ACC_PUBLIC
    Code:
      stack=1, locals=1, args_size=1
         0: aload_0
         1: invokevirtual #302                // Method scala$collection$immutable$HashSetBuilder$$rootNode:()Lscala/collection/immutable/BitmapIndexedSetNode;
         4: invokevirtual #184                // Method scala/collection/immutable/BitmapIndexedSetNode.size:()I
         7: ireturn
      LineNumberTable:
        line 2101: 0
      LocalVariableTable:
        Start  Length  Slot  Name   Signature
            0       8     0  this   Lscala/collection/immutable/HashSetBuilder;

  public scala.collection.mutable.Growable addAll(scala.collection.IterableOnce);
    descriptor: (Lscala/collection/IterableOnce;)Lscala/collection/mutable/Growable;
    flags: (0x1041) ACC_PUBLIC, ACC_BRIDGE, ACC_SYNTHETIC
    Code:
      stack=2, locals=2, args_size=2
         0: aload_0
         1: aload_1
         2: invokevirtual #365                // Method addAll:(Lscala/collection/IterableOnce;)Lscala/collection/immutable/HashSetBuilder;
         5: areturn
      LineNumberTable:
        line 1942: 0
      LocalVariableTable:
        Start  Length  Slot  Name   Signature
            0       6     0  this   Lscala/collection/immutable/HashSetBuilder;
            0       6     1    xs   Lscala/collection/IterableOnce;
    MethodParameters:
      Name                           Flags
      xs                             final

  public scala.collection.mutable.Growable addOne(java.lang.Object);
    descriptor: (Ljava/lang/Object;)Lscala/collection/mutable/Growable;
    flags: (0x1041) ACC_PUBLIC, ACC_BRIDGE, ACC_SYNTHETIC
    Code:
      stack=2, locals=2, args_size=2
         0: aload_0
         1: aload_1
         2: invokevirtual #357                // Method addOne:(Ljava/lang/Object;)Lscala/collection/immutable/HashSetBuilder;
         5: areturn
      LineNumberTable:
        line 1942: 0
      LocalVariableTable:
        Start  Length  Slot  Name   Signature
            0       6     0  this   Lscala/collection/immutable/HashSetBuilder;
            0       6     1  elem   Ljava/lang/Object;
    MethodParameters:
      Name                           Flags
      elem                           final

  public java.lang.Object result();
    descriptor: ()Ljava/lang/Object;
    flags: (0x1041) ACC_PUBLIC, ACC_BRIDGE, ACC_SYNTHETIC
    Code:
      stack=1, locals=1, args_size=1
         0: aload_0
         1: invokevirtual #367                // Method result:()Lscala/collection/immutable/HashSet;
         4: areturn
      LineNumberTable:
        line 1942: 0
      LocalVariableTable:
        Start  Length  Slot  Name   Signature
            0       5     0  this   Lscala/collection/immutable/HashSetBuilder;

  public scala.collection.immutable.HashSetBuilder();
    descriptor: ()V
    flags: (0x0001) ACC_PUBLIC
    Code:
      stack=2, locals=1, args_size=1
         0: aload_0
         1: invokespecial #368                // Method java/lang/Object."<init>":()V
         4: aload_0
         5: aload_0
         6: invokespecial #362                // Method newEmptyRootNode:()Lscala/collection/immutable/BitmapIndexedSetNode;
         9: putfield      #128                // Field scala$collection$immutable$HashSetBuilder$$rootNode:Lscala/collection/immutable/BitmapIndexedSetNode;
        12: return
      LineNumberTable:
        line 1942: 0
        line 1956: 4
        line 1942: 12
      LocalVariableTable:
        Start  Length  Slot  Name   Signature
            0      13     0  this   Lscala/collection/immutable/HashSetBuilder;
}
InnerClasses:
  public final #13;                       // class scala/collection/immutable/HashSetBuilder$$anon$1
Signature: #3                           // <A:Ljava/lang/Object;>Ljava/lang/Object;Lscala/collection/mutable/ReusableBuilder<TA;Lscala/collection/immutable/HashSet<TA;>;>;
SourceFile: "HashSet.scala"
RuntimeVisibleAnnotations:
  0: #9(#10=s#11)
    scala.reflect.ScalaSignature(
      bytes="\u0006\u0005\u0005mb!\u0002\f\u0018\u0005ei\u0002\"B\u001d\u0001\t\u0003Q\u0004\"\u0002\u001f\u0001\t\u0013i\u0004\"C!\u0001\u0001\u0004\u0005\r\u0011\"\u0003C\u0011%\u0019\u0005\u00011AA\u0002\u0013%A\tC\u0005K\u0001\u0001\u0007\t\u0011)Q\u0005k!)1\n\u0001C\u0005\u0019\"9\u0001\u000b\u0001a\u0001\n\u0013i\u0004bB)\u0001\u0001\u0004%IA\u0015\u0005\u0007)\u0002\u0001\u000b\u0015\u0002 \t\u000bU\u0003A\u0011\u0002,\t\u000b\r\u0004A\u0011\u00023\t\u000bM\u0004A\u0011\u0002;\t\u000bi\u0004A\u0011A>\t\u000f\u0005E\u0001\u0001\"\u0003\u0002\u0014!9\u0011Q\u0003\u0001\u0005\n\u0005M\u0001bBA\f\u0001\u0011\u0005\u0013\u0011\u0004\u0005\b\u00037\u0001A\u0011IA\u000f\u0011\u001d\t\u0019\u0003\u0001C!\u0003KAq!a\r\u0001\t\u0003\n\u0019\u0002\u0003\u0005\u00026\u0001!\t!GA\u001c\u0011\u001d\tI\u0004\u0001C!\u0003o\u0011a\u0002S1tQN+GOQ;jY\u0012,\'O\u0003\u0002\u00193\u0005I\u0011.\\7vi\u0006\u0014G.\u001a\u0006\u00035m\t!bY8mY\u0016\u001cG/[8o\u0015\u0005a\u0012!B:dC2\fWC\u0001\u0010,\'\r\u0001qd\t\t\u0003A\u0005j\u0011aG\u0005\u0003Em\u0011a!\u00118z%\u00164\u0007\u0003\u0002\u0013(SUj\u0011!\n\u0006\u0003Me\tq!\\;uC\ndW-\u0003\u0002)K\ty!+Z;tC\ndWMQ;jY\u0012,\'\u000f\u0005\u0002+W1\u0001A!\u0002\u0017\u0001\u0005\u0004q#!A!\u0004\u0001E\u0011qF\r\t\u0003AAJ!!M\u000e\u0003\u000f9{G\u000f[5oOB\u0011\u0001eM\u0005\u0003im\u00111!\u00118z!\r1t\'K\u0007\u0002/%\u0011\u0001h\u0006\u0002\b\u0011\u0006\u001c\bnU3u\u0003\u0019a\u0014N\\5u}Q\t1\bE\u00027\u0001%\n\u0001C\\3x\u000b6\u0004H/\u001f*p_Rtu\u000eZ3\u0016\u0003y\u00022AN *\u0013\t\u0001uC\u0001\u000bCSRl\u0017\r]%oI\u0016DX\rZ*fi:{G-Z\u0001\bC2L\u0017m]3e+\u0005)\u0014aC1mS\u0006\u001cX\rZ0%KF$\"!\u0012%\u0011\u0005\u00012\u0015BA$\u001c\u0005\u0011)f.\u001b;\t\u000f%#\u0011\u0011!a\u0001k\u0005\u0019\u0001\u0010J\u0019\u0002\u0011\u0005d\u0017.Y:fI\u0002\n\u0011\"[:BY&\f7/\u001a3\u0016\u00035\u0003\"\u0001\t(\n\u0005=[\"a\u0002\"p_2,\u0017M\\\u0001\te>|GOT8eK\u0006a!o\\8u\u001d>$Wm\u0018\u0013fcR\u0011Qi\u0015\u0005\b\u0013\"\t\t\u00111\u0001?\u0003%\u0011xn\u001c;O_\u0012,\u0007%A\u0007j]N,\'\u000f^#mK6,g\u000e\u001e\u000b\u0005/v{\u0016\rE\u0002!1jK!!W\u000e\u0003\u000b\u0005\u0013(/Y=\u0011\u0005\u0001Z\u0016B\u0001/\u001c\u0005\rIe\u000e\u001e\u0005\u0006=*\u0001\raV\u0001\u0003CNDQ\u0001\u0019\u0006A\u0002i\u000b!!\u001b=\t\u000b\tT\u0001\u0019\u0001.\u0002\t\u0015dW-\\\u0001\fS:\u001cXM\u001d;WC2,X-\u0006\u0002faR1QI\u001a5kY:DQaZ\u0006A\u0002y\n!AY7\t\u000b%\\\u0001\u0019\u0001.\u0002\r\tLG\u000f]8t\u0011\u0015Y7\u00021\u0001*\u0003\rYW-\u001f\u0005\u0006[.\u0001\rAW\u0001\r_JLw-\u001b8bY\"\u000b7\u000f\u001b\u0005\u0006_.\u0001\rAW\u0001\bW\u0016L\b*Y:i\t\u0015\t8B1\u0001s\u0005\t\t\u0015\'\u0005\u0002*e\u0005A1/\u001a;WC2,X-\u0006\u0002vsR!QI^<y\u0011\u00159G\u00021\u0001?\u0011\u0015IG\u00021\u0001[\u0011\u0015\u0011G\u00021\u0001*\t\u0015\tHB1\u0001s\u0003\u0019)\b\u000fZ1uKRQQ\t`A\u0002\u0003\u000f\tI!!\u0004\t\u000bul\u0001\u0019\u0001@\u0002\u000fM,GOT8eKB\u0019ag`\u0015\n\u0007\u0005\u0005qCA\u0004TKRtu\u000eZ3\t\r\u0005\u0015Q\u00021\u0001*\u0003\u001d)G.Z7f]RDQ!\\\u0007A\u0002iCa!a\u0003\u000e\u0001\u0004Q\u0016aC3mK6,g\u000e\u001e%bg\"Da!a\u0004\u000e\u0001\u0004Q\u0016!B:iS\u001a$\u0018aD3ogV\u0014X-\u00168bY&\f7/\u001a3\u0015\u0003\u0015\u000b\u0011bY8qs\u0016cW-\\:\u0002\rI,7/\u001e7u)\u0005)\u0014AB1eI>sW\r\u0006\u0003\u0002 \u0005\u0005R\"\u0001\u0001\t\u000b\t\f\u0002\u0019A\u0015\u0002\r\u0005$G-\u00117m)\u0011\ty\"a\n\t\u000f\u0005%\"\u00031\u0001\u0002,\u0005\u0011\u0001p\u001d\t\u0006\u0003[\ty#K\u0007\u00023%\u0019\u0011\u0011G\r\u0003\u0019%#XM]1cY\u0016|enY3\u0002\u000b\rdW-\u0019:\u0002\tML\'0Z\u000b\u00025\u0006I1N\\8x]NK\'0\u001a"
    )
  ScalaInlineInfo: length = 0x9A (unknown attribute)
   01 01 00 1E 00 40 00 41 05 00 40 00 4B 05 00 54
   00 55 05 00 6F 00 8A 01 01 4F 01 50 01 01 4F 00
   55 01 01 45 01 46 01 01 45 00 41 01 00 0E 00 73
   01 00 77 00 78 01 01 68 00 8A 01 01 28 00 8A 01
   01 25 00 8A 01 00 84 00 85 01 00 95 00 96 01 00
   7B 00 7C 01 01 6B 00 29 01 00 37 00 38 01 00 5C
   00 5D 01 00 93 01 61 01 00 93 00 73 01 00 81 00
   82 01 00 11 00 5D 01 00 C8 00 C9 01 00 16 00 29
   01 00 14 00 15 01 00 14 00 20 01 00 28 00 29 01
   00 2E 00 2F 01 00 CB 00 CC 01
  ScalaSig: length = 0x3 (unknown attribute)
   05 02 00
