Classfile /Users/mw/Projects/slang-braindump/.jar/jar8/assemble/slang-braindump/assemble/content/scala/collection/immutable/IntMapIterator.class
  Last modified May 29, 2022; size 3622 bytes
  SHA-256 checksum 2e7d7020fb48745cda227c0cdf39b4d8a9f188dc44c899f681d6c4329d728b3f
  Compiled from "IntMap.scala"
public abstract class scala.collection.immutable.IntMapIterator<V extends java.lang.Object, T extends java.lang.Object> extends scala.collection.AbstractIterator<T>
  minor version: 0
  major version: 52
  flags: (0x0421) ACC_PUBLIC, ACC_SUPER, ACC_ABSTRACT
  this_class: #2                          // scala/collection/immutable/IntMapIterator
  super_class: #5                         // scala/collection/AbstractIterator
  interfaces: 0, fields: 2, methods: 10, attributes: 6
Constant pool:
    #1 = Utf8               scala/collection/immutable/IntMapIterator
    #2 = Class              #1            // scala/collection/immutable/IntMapIterator
    #3 = Utf8               <V:Ljava/lang/Object;T:Ljava/lang/Object;>Lscala/collection/AbstractIterator<TT;>;
    #4 = Utf8               scala/collection/AbstractIterator
    #5 = Class              #4            // scala/collection/AbstractIterator
    #6 = Utf8               IntMap.scala
    #7 = Utf8               Lscala/reflect/ScalaSignature;
    #8 = Utf8               bytes
    #9 = Utf8               \u0006\u000514aAD\b\u0002\u0002=)\u0002\u0002\u0003\u0015\u0001\u0005\u0003\u0005\u000b\u0011B\u0015\t\u000bA\u0002A\u0011A\u0019\t\u000fQ\u0002\u0001\u0019!C\u0001k!9\u0011\b\u0001a\u0001\n\u0003Q\u0004B\u0002!\u0001A\u0003&a\u0007C\u0004B\u0001\u0001\u0007I\u0011\u0001\"\t\u000f%\u0003\u0001\u0019!C\u0001\u0015\"1A\n\u0001Q!\n\rCQ!\u0014\u0001\u0005\u00029CQa\u0014\u0001\u0005\u0002ACQa\u0015\u0001\u0007\u0002QCQA\u0018\u0001\u0005\u0002}CQa\u0019\u0001\u0005\u0006\u0011\u0014a\"\u00138u\u001b\u0006\u0004\u0018\n^3sCR|\'O\u0003\u0002\u0011#\u0005I\u0011.\\7vi\u0006\u0014G.\u001a\u0006\u0003%M\t!bY8mY\u0016\u001cG/[8o\u0015\u0005!\u0012!B:dC2\fWc\u0001\f/;M\u0011\u0001a\u0006\t\u00041eYR\"A\t\n\u0005i\t\"\u0001E!cgR\u0014\u0018m\u0019;Ji\u0016\u0014\u0018\r^8s!\taR\u0004\u0004\u0001\u0005\u000by\u0001!\u0019\u0001\u0011\u0003\u0003Q\u001b\u0001!\u0005\u0002\"KA\u0011!eI\u0007\u0002\'%\u0011Ae\u0005\u0002\b\u001d>$\b.\u001b8h!\t\u0011c%\u0003\u0002(\'\t\u0019\u0011I\\=\u0002\u0005%$\bc\u0001\u0016,[5\tq\"\u0003\u0002-\u001f\t1\u0011J\u001c;NCB\u0004\"\u0001\b\u0018\u0005\u000b=\u0002!\u0019\u0001\u0011\u0003\u0003Y\u000ba\u0001P5oSRtDC\u0001\u001a4!\u0011Q\u0003!L\u000e\t\u000b!\u0012\u0001\u0019A\u0015\u0002\u000b%tG-\u001a=\u0016\u0003Y\u0002\"AI\u001c\n\u0005a\u001a\"aA%oi\u0006I\u0011N\u001c3fq~#S-\u001d\u000b\u0003wy\u0002\"A\t\u001f\n\u0005u\u001a\"\u0001B+oSRDqa\u0010\u0003\u0002\u0002\u0003\u0007a\'A\u0002yIE\na!\u001b8eKb\u0004\u0013A\u00022vM\u001a,\'/F\u0001D!\r\u0011CIR\u0005\u0003\u000bN\u0011Q!\u0011:sCf\u0004\"AI$\n\u0005!\u001b\"AB!osJ+g-\u0001\u0006ck\u001a4WM]0%KF$\"aO&\t\u000f}:\u0011\u0011!a\u0001\u0007\u00069!-\u001e4gKJ\u0004\u0013a\u00019paV\t\u0011&\u0001\u0003qkNDGCA\u001eR\u0011\u0015\u0011&\u00021\u0001*\u0003\u0005A\u0018a\u0002<bYV,wJ\u001a\u000b\u00037UCQAV\u0006A\u0002]\u000b1\u0001^5q!\rA6,\f\b\u0003UeK!AW\b\u0002\r%sG/T1q\u0013\taVLA\u0002USBT!AW\b\u0002\u000f!\f7OT3yiV\t\u0001\r\u0005\u0002#C&\u0011!m\u0005\u0002\b\u0005>|G.Z1o\u0003\u0011qW\r\u001f;\u0015\u0003mA#!\u00044\u0011\u0005\u001dTW\"\u00015\u000b\u0005%\u001c\u0012AC1o]>$\u0018\r^5p]&\u00111\u000e\u001b\u0002\bi\u0006LGN]3d\u0001
   #10 = Utf8               scala/collection/immutable/IntMap$Bin
   #11 = Class              #10           // scala/collection/immutable/IntMap$Bin
   #12 = Utf8               scala/collection/immutable/IntMap
   #13 = Class              #12           // scala/collection/immutable/IntMap
   #14 = Utf8               Bin
   #15 = Utf8               scala/collection/immutable/IntMap$Nil$
   #16 = Class              #15           // scala/collection/immutable/IntMap$Nil$
   #17 = Utf8               Nil$
   #18 = Utf8               scala/collection/immutable/IntMap$Tip
   #19 = Class              #18           // scala/collection/immutable/IntMap$Tip
   #20 = Utf8               Tip
   #21 = Utf8               index
   #22 = Utf8               I
   #23 = Utf8               buffer
   #24 = Utf8               [Ljava/lang/Object;
   #25 = Utf8               ()I
   #26 = NameAndType        #21:#22       // index:I
   #27 = Fieldref           #2.#26        // scala/collection/immutable/IntMapIterator.index:I
   #28 = Utf8               this
   #29 = Utf8               Lscala/collection/immutable/IntMapIterator;
   #30 = Utf8               index_$eq
   #31 = Utf8               (I)V
   #32 = Utf8               x$1
   #33 = Utf8               ()[Ljava/lang/Object;
   #34 = NameAndType        #23:#24       // buffer:[Ljava/lang/Object;
   #35 = Fieldref           #2.#34        // scala/collection/immutable/IntMapIterator.buffer:[Ljava/lang/Object;
   #36 = Utf8               buffer_$eq
   #37 = Utf8               ([Ljava/lang/Object;)V
   #38 = Utf8               pop
   #39 = Utf8               ()Lscala/collection/immutable/IntMap;
   #40 = Utf8               ()Lscala/collection/immutable/IntMap<TV;>;
   #41 = NameAndType        #21:#25       // index:()I
   #42 = Methodref          #2.#41        // scala/collection/immutable/IntMapIterator.index:()I
   #43 = NameAndType        #30:#31       // index_$eq:(I)V
   #44 = Methodref          #2.#43        // scala/collection/immutable/IntMapIterator.index_$eq:(I)V
   #45 = NameAndType        #23:#33       // buffer:()[Ljava/lang/Object;
   #46 = Methodref          #2.#45        // scala/collection/immutable/IntMapIterator.buffer:()[Ljava/lang/Object;
   #47 = Utf8               push
   #48 = Utf8               (Lscala/collection/immutable/IntMap;)V
   #49 = Utf8               (Lscala/collection/immutable/IntMap<TV;>;)V
   #50 = Utf8               x
   #51 = Utf8               Lscala/collection/immutable/IntMap;
   #52 = Utf8               valueOf
   #53 = Utf8               (Lscala/collection/immutable/IntMap$Tip;)Ljava/lang/Object;
   #54 = Utf8               (Lscala/collection/immutable/IntMap$Tip<TV;>;)TT;
   #55 = Utf8               tip
   #56 = Utf8               hasNext
   #57 = Utf8               ()Z
   #58 = Utf8               next
   #59 = Utf8               ()Ljava/lang/Object;
   #60 = Utf8               ()TT;
   #61 = NameAndType        #38:#39       // pop:()Lscala/collection/immutable/IntMap;
   #62 = Methodref          #2.#61        // scala/collection/immutable/IntMapIterator.pop:()Lscala/collection/immutable/IntMap;
   #63 = Utf8               left
   #64 = NameAndType        #63:#39       // left:()Lscala/collection/immutable/IntMap;
   #65 = Methodref          #11.#64       // scala/collection/immutable/IntMap$Bin.left:()Lscala/collection/immutable/IntMap;
   #66 = Utf8               right
   #67 = NameAndType        #66:#39       // right:()Lscala/collection/immutable/IntMap;
   #68 = Methodref          #11.#67       // scala/collection/immutable/IntMap$Bin.right:()Lscala/collection/immutable/IntMap;
   #69 = NameAndType        #47:#48       // push:(Lscala/collection/immutable/IntMap;)V
   #70 = Methodref          #2.#69        // scala/collection/immutable/IntMapIterator.push:(Lscala/collection/immutable/IntMap;)V
   #71 = NameAndType        #52:#53       // valueOf:(Lscala/collection/immutable/IntMap$Tip;)Ljava/lang/Object;
   #72 = Methodref          #2.#71        // scala/collection/immutable/IntMapIterator.valueOf:(Lscala/collection/immutable/IntMap$Tip;)Ljava/lang/Object;
   #73 = Utf8               MODULE$
   #74 = Utf8               Lscala/collection/immutable/IntMap$Nil$;
   #75 = NameAndType        #73:#74       // MODULE$:Lscala/collection/immutable/IntMap$Nil$;
   #76 = Fieldref           #16.#75       // scala/collection/immutable/IntMap$Nil$.MODULE$:Lscala/collection/immutable/IntMap$Nil$;
   #77 = Utf8               java/lang/Object
   #78 = Class              #77           // java/lang/Object
   #79 = Utf8               equals
   #80 = Utf8               (Ljava/lang/Object;)Z
   #81 = NameAndType        #79:#80       // equals:(Ljava/lang/Object;)Z
   #82 = Methodref          #78.#81       // java/lang/Object.equals:(Ljava/lang/Object;)Z
   #83 = Utf8               java/lang/IllegalStateException
   #84 = Class              #83           // java/lang/IllegalStateException
   #85 = Utf8               Empty maps not allowed as subtrees
   #86 = String             #85           // Empty maps not allowed as subtrees
   #87 = Utf8               <init>
   #88 = Utf8               (Ljava/lang/String;)V
   #89 = NameAndType        #87:#88       // "<init>":(Ljava/lang/String;)V
   #90 = Methodref          #84.#89       // java/lang/IllegalStateException."<init>":(Ljava/lang/String;)V
   #91 = Utf8               scala/MatchError
   #92 = Class              #91           // scala/MatchError
   #93 = Utf8               (Ljava/lang/Object;)V
   #94 = NameAndType        #87:#93       // "<init>":(Ljava/lang/Object;)V
   #95 = Methodref          #92.#94       // scala/MatchError."<init>":(Ljava/lang/Object;)V
   #96 = Utf8               t
   #97 = Utf8               it
   #98 = Utf8               ()V
   #99 = NameAndType        #87:#98       // "<init>":()V
  #100 = Methodref          #5.#99        // scala/collection/AbstractIterator."<init>":()V
  #101 = Utf8               Code
  #102 = Utf8               LineNumberTable
  #103 = Utf8               LocalVariableTable
  #104 = Utf8               MethodParameters
  #105 = Utf8               Signature
  #106 = Utf8               StackMapTable
  #107 = Utf8               InnerClasses
  #108 = Utf8               SourceFile
  #109 = Utf8               RuntimeVisibleAnnotations
  #110 = Utf8               ScalaInlineInfo
  #111 = Utf8               ScalaSig
{
  private int index;
    descriptor: I
    flags: (0x0002) ACC_PRIVATE

  private java.lang.Object[] buffer;
    descriptor: [Ljava/lang/Object;
    flags: (0x0002) ACC_PRIVATE

  public int index();
    descriptor: ()I
    flags: (0x0001) ACC_PUBLIC
    Code:
      stack=1, locals=1, args_size=1
         0: aload_0
         1: getfield      #27                 // Field index:I
         4: ireturn
      LineNumberTable:
        line 113: 0
      LocalVariableTable:
        Start  Length  Slot  Name   Signature
            0       5     0  this   Lscala/collection/immutable/IntMapIterator;

  public void index_$eq(int);
    descriptor: (I)V
    flags: (0x0001) ACC_PUBLIC
    Code:
      stack=2, locals=2, args_size=2
         0: aload_0
         1: iload_1
         2: putfield      #27                 // Field index:I
         5: return
      LineNumberTable:
        line 113: 0
      LocalVariableTable:
        Start  Length  Slot  Name   Signature
            0       6     0  this   Lscala/collection/immutable/IntMapIterator;
            0       6     1   x$1   I
    MethodParameters:
      Name                           Flags
      x$1                            final

  public java.lang.Object[] buffer();
    descriptor: ()[Ljava/lang/Object;
    flags: (0x0001) ACC_PUBLIC
    Code:
      stack=1, locals=1, args_size=1
         0: aload_0
         1: getfield      #35                 // Field buffer:[Ljava/lang/Object;
         4: areturn
      LineNumberTable:
        line 114: 0
      LocalVariableTable:
        Start  Length  Slot  Name   Signature
            0       5     0  this   Lscala/collection/immutable/IntMapIterator;

  public void buffer_$eq(java.lang.Object[]);
    descriptor: ([Ljava/lang/Object;)V
    flags: (0x0001) ACC_PUBLIC
    Code:
      stack=2, locals=2, args_size=2
         0: aload_0
         1: aload_1
         2: putfield      #35                 // Field buffer:[Ljava/lang/Object;
         5: return
      LineNumberTable:
        line 114: 0
      LocalVariableTable:
        Start  Length  Slot  Name   Signature
            0       6     0  this   Lscala/collection/immutable/IntMapIterator;
            0       6     1   x$1   [Ljava/lang/Object;
    MethodParameters:
      Name                           Flags
      x$1                            final

  public scala.collection.immutable.IntMap<V> pop();
    descriptor: ()Lscala/collection/immutable/IntMap;
    flags: (0x0001) ACC_PUBLIC
    Code:
      stack=3, locals=1, args_size=1
         0: aload_0
         1: aload_0
         2: invokevirtual #42                 // Method index:()I
         5: iconst_1
         6: isub
         7: invokevirtual #44                 // Method index_$eq:(I)V
        10: aload_0
        11: invokevirtual #46                 // Method buffer:()[Ljava/lang/Object;
        14: aload_0
        15: invokevirtual #42                 // Method index:()I
        18: aaload
        19: checkcast     #13                 // class scala/collection/immutable/IntMap
        22: areturn
      LineNumberTable:
        line 117: 0
        line 118: 10
      LocalVariableTable:
        Start  Length  Slot  Name   Signature
            0      23     0  this   Lscala/collection/immutable/IntMapIterator;
    Signature: #40                          // ()Lscala/collection/immutable/IntMap<TV;>;

  public void push(scala.collection.immutable.IntMap<V>);
    descriptor: (Lscala/collection/immutable/IntMap;)V
    flags: (0x0001) ACC_PUBLIC
    Code:
      stack=3, locals=2, args_size=2
         0: aload_0
         1: invokevirtual #46                 // Method buffer:()[Ljava/lang/Object;
         4: aload_0
         5: invokevirtual #42                 // Method index:()I
         8: aload_1
         9: aastore
        10: aload_0
        11: aload_0
        12: invokevirtual #42                 // Method index:()I
        15: iconst_1
        16: iadd
        17: invokevirtual #44                 // Method index_$eq:(I)V
        20: return
      LineNumberTable:
        line 122: 0
        line 123: 10
      LocalVariableTable:
        Start  Length  Slot  Name   Signature
            0      21     0  this   Lscala/collection/immutable/IntMapIterator;
            0      21     1     x   Lscala/collection/immutable/IntMap;
    Signature: #49                          // (Lscala/collection/immutable/IntMap<TV;>;)V
    MethodParameters:
      Name                           Flags
      x                              final

  public abstract T valueOf(scala.collection.immutable.IntMap$Tip<V>);
    descriptor: (Lscala/collection/immutable/IntMap$Tip;)Ljava/lang/Object;
    flags: (0x0401) ACC_PUBLIC, ACC_ABSTRACT
    Signature: #54                          // (Lscala/collection/immutable/IntMap$Tip<TV;>;)TT;
    MethodParameters:
      Name                           Flags
      tip                            final

  public boolean hasNext();
    descriptor: ()Z
    flags: (0x0001) ACC_PUBLIC
    Code:
      stack=2, locals=1, args_size=1
         0: aload_0
         1: invokevirtual #42                 // Method index:()I
         4: iconst_0
         5: if_icmpeq     10
         8: iconst_1
         9: ireturn
        10: iconst_0
        11: ireturn
      StackMapTable: number_of_entries = 1
        frame_type = 10 /* same */
      LineNumberTable:
        line 132: 0
      LocalVariableTable:
        Start  Length  Slot  Name   Signature
            0      12     0  this   Lscala/collection/immutable/IntMapIterator;

  public final T next();
    descriptor: ()Ljava/lang/Object;
    flags: (0x0011) ACC_PUBLIC, ACC_FINAL
    Code:
      stack=3, locals=11, args_size=1
         0: iconst_0
         1: istore_2
         2: aconst_null
         3: astore_3
         4: aload_0
         5: invokevirtual #62                 // Method pop:()Lscala/collection/immutable/IntMap;
         8: astore        4
        10: aload         4
        12: instanceof    #11                 // class scala/collection/immutable/IntMap$Bin
        15: ifeq          69
        18: iconst_1
        19: istore_2
        20: aload         4
        22: checkcast     #11                 // class scala/collection/immutable/IntMap$Bin
        25: astore_3
        26: aload_3
        27: invokevirtual #65                 // Method scala/collection/immutable/IntMap$Bin.left:()Lscala/collection/immutable/IntMap;
        30: astore        5
        32: aload_3
        33: invokevirtual #68                 // Method scala/collection/immutable/IntMap$Bin.right:()Lscala/collection/immutable/IntMap;
        36: astore        6
        38: aload         5
        40: instanceof    #19                 // class scala/collection/immutable/IntMap$Tip
        43: ifeq          69
        46: aload         5
        48: checkcast     #19                 // class scala/collection/immutable/IntMap$Tip
        51: astore        7
        53: aload_0
        54: aload         6
        56: invokevirtual #70                 // Method push:(Lscala/collection/immutable/IntMap;)V
        59: aload_0
        60: aload         7
        62: invokevirtual #72                 // Method valueOf:(Lscala/collection/immutable/IntMap$Tip;)Ljava/lang/Object;
        65: astore_1
        66: goto          156
        69: iload_2
        70: ifeq          100
        73: aload_3
        74: invokevirtual #65                 // Method scala/collection/immutable/IntMap$Bin.left:()Lscala/collection/immutable/IntMap;
        77: astore        8
        79: aload_3
        80: invokevirtual #68                 // Method scala/collection/immutable/IntMap$Bin.right:()Lscala/collection/immutable/IntMap;
        83: astore        9
        85: aload_0
        86: aload         9
        88: invokevirtual #70                 // Method push:(Lscala/collection/immutable/IntMap;)V
        91: aload_0
        92: aload         8
        94: invokevirtual #70                 // Method push:(Lscala/collection/immutable/IntMap;)V
        97: goto          0
       100: aload         4
       102: instanceof    #19                 // class scala/collection/immutable/IntMap$Tip
       105: ifeq          125
       108: aload         4
       110: checkcast     #19                 // class scala/collection/immutable/IntMap$Tip
       113: astore        10
       115: aload_0
       116: aload         10
       118: invokevirtual #72                 // Method valueOf:(Lscala/collection/immutable/IntMap$Tip;)Ljava/lang/Object;
       121: astore_1
       122: goto          156
       125: getstatic     #76                 // Field scala/collection/immutable/IntMap$Nil$.MODULE$:Lscala/collection/immutable/IntMap$Nil$;
       128: aload         4
       130: invokevirtual #82                 // Method java/lang/Object.equals:(Ljava/lang/Object;)Z
       133: ifeq          146
       136: new           #84                 // class java/lang/IllegalStateException
       139: dup
       140: ldc           #86                 // String Empty maps not allowed as subtrees
       142: invokespecial #90                 // Method java/lang/IllegalStateException."<init>":(Ljava/lang/String;)V
       145: athrow
       146: new           #92                 // class scala/MatchError
       149: dup
       150: aload         4
       152: invokespecial #95                 // Method scala/MatchError."<init>":(Ljava/lang/Object;)V
       155: athrow
       156: aload_1
       157: areturn
      StackMapTable: number_of_entries = 6
        frame_type = 0 /* same */
        frame_type = 255 /* full_frame */
          offset_delta = 68
          locals = [ class scala/collection/immutable/IntMapIterator, top, int, class scala/collection/immutable/IntMap$Bin, class scala/collection/immutable/IntMap ]
          stack = []
        frame_type = 30 /* same */
        frame_type = 24 /* same */
        frame_type = 20 /* same */
        frame_type = 255 /* full_frame */
          offset_delta = 9
          locals = [ class scala/collection/immutable/IntMapIterator, class java/lang/Object, int, class scala/collection/immutable/IntMap$Bin, class scala/collection/immutable/IntMap ]
          stack = []
      LineNumberTable:
        line 135: 0
        line 136: 10
        line 137: 53
        line 138: 59
        line 140: 69
        line 141: 85
        line 142: 91
        line 143: 97
        line 145: 100
        line 148: 125
        line 135: 146
      LocalVariableTable:
        Start  Length  Slot  Name   Signature
           32      37     5     t   Lscala/collection/immutable/IntMap;
           38      31     6 right   Lscala/collection/immutable/IntMap;
           79      21     8  left   Lscala/collection/immutable/IntMap;
           85      15     9 right   Lscala/collection/immutable/IntMap;
            0     158     0  this   Lscala/collection/immutable/IntMapIterator;
    Signature: #60                          // ()TT;

  public scala.collection.immutable.IntMapIterator(scala.collection.immutable.IntMap<V>);
    descriptor: (Lscala/collection/immutable/IntMap;)V
    flags: (0x0001) ACC_PUBLIC
    Code:
      stack=2, locals=2, args_size=2
         0: aload_0
         1: invokespecial #100                // Method scala/collection/AbstractIterator."<init>":()V
         4: aload_0
         5: iconst_0
         6: putfield      #27                 // Field index:I
         9: aload_0
        10: bipush        33
        12: anewarray     #78                 // class java/lang/Object
        15: putfield      #35                 // Field buffer:[Ljava/lang/Object;
        18: aload_0
        19: aload_1
        20: invokevirtual #70                 // Method push:(Lscala/collection/immutable/IntMap;)V
        23: return
      LineNumberTable:
        line 107: 0
        line 113: 4
        line 114: 9
        line 125: 18
        line 107: 23
      LocalVariableTable:
        Start  Length  Slot  Name   Signature
            0      24     0  this   Lscala/collection/immutable/IntMapIterator;
            0      24     1    it   Lscala/collection/immutable/IntMap;
    Signature: #49                          // (Lscala/collection/immutable/IntMap<TV;>;)V
    MethodParameters:
      Name                           Flags
      it                             final
}
InnerClasses:
  public static #14= #11 of #13;          // Bin=class scala/collection/immutable/IntMap$Bin of class scala/collection/immutable/IntMap
  public static #17= #16 of #13;          // Nil$=class scala/collection/immutable/IntMap$Nil$ of class scala/collection/immutable/IntMap
  public static #20= #19 of #13;          // Tip=class scala/collection/immutable/IntMap$Tip of class scala/collection/immutable/IntMap
Signature: #3                           // <V:Ljava/lang/Object;T:Ljava/lang/Object;>Lscala/collection/AbstractIterator<TT;>;
SourceFile: "IntMap.scala"
RuntimeVisibleAnnotations:
  0: #7(#8=s#9)
    scala.reflect.ScalaSignature(
      bytes="\u0006\u000514aAD\b\u0002\u0002=)\u0002\u0002\u0003\u0015\u0001\u0005\u0003\u0005\u000b\u0011B\u0015\t\u000bA\u0002A\u0011A\u0019\t\u000fQ\u0002\u0001\u0019!C\u0001k!9\u0011\b\u0001a\u0001\n\u0003Q\u0004B\u0002!\u0001A\u0003&a\u0007C\u0004B\u0001\u0001\u0007I\u0011\u0001\"\t\u000f%\u0003\u0001\u0019!C\u0001\u0015\"1A\n\u0001Q!\n\rCQ!\u0014\u0001\u0005\u00029CQa\u0014\u0001\u0005\u0002ACQa\u0015\u0001\u0007\u0002QCQA\u0018\u0001\u0005\u0002}CQa\u0019\u0001\u0005\u0006\u0011\u0014a\"\u00138u\u001b\u0006\u0004\u0018\n^3sCR|\'O\u0003\u0002\u0011#\u0005I\u0011.\\7vi\u0006\u0014G.\u001a\u0006\u0003%M\t!bY8mY\u0016\u001cG/[8o\u0015\u0005!\u0012!B:dC2\fWc\u0001\f/;M\u0011\u0001a\u0006\t\u00041eYR\"A\t\n\u0005i\t\"\u0001E!cgR\u0014\u0018m\u0019;Ji\u0016\u0014\u0018\r^8s!\taR\u0004\u0004\u0001\u0005\u000by\u0001!\u0019\u0001\u0011\u0003\u0003Q\u001b\u0001!\u0005\u0002\"KA\u0011!eI\u0007\u0002\'%\u0011Ae\u0005\u0002\b\u001d>$\b.\u001b8h!\t\u0011c%\u0003\u0002(\'\t\u0019\u0011I\\=\u0002\u0005%$\bc\u0001\u0016,[5\tq\"\u0003\u0002-\u001f\t1\u0011J\u001c;NCB\u0004\"\u0001\b\u0018\u0005\u000b=\u0002!\u0019\u0001\u0011\u0003\u0003Y\u000ba\u0001P5oSRtDC\u0001\u001a4!\u0011Q\u0003!L\u000e\t\u000b!\u0012\u0001\u0019A\u0015\u0002\u000b%tG-\u001a=\u0016\u0003Y\u0002\"AI\u001c\n\u0005a\u001a\"aA%oi\u0006I\u0011N\u001c3fq~#S-\u001d\u000b\u0003wy\u0002\"A\t\u001f\n\u0005u\u001a\"\u0001B+oSRDqa\u0010\u0003\u0002\u0002\u0003\u0007a\'A\u0002yIE\na!\u001b8eKb\u0004\u0013A\u00022vM\u001a,\'/F\u0001D!\r\u0011CIR\u0005\u0003\u000bN\u0011Q!\u0011:sCf\u0004\"AI$\n\u0005!\u001b\"AB!osJ+g-\u0001\u0006ck\u001a4WM]0%KF$\"aO&\t\u000f}:\u0011\u0011!a\u0001\u0007\u00069!-\u001e4gKJ\u0004\u0013a\u00019paV\t\u0011&\u0001\u0003qkNDGCA\u001eR\u0011\u0015\u0011&\u00021\u0001*\u0003\u0005A\u0018a\u0002<bYV,wJ\u001a\u000b\u00037UCQAV\u0006A\u0002]\u000b1\u0001^5q!\rA6,\f\b\u0003UeK!AW\b\u0002\r%sG/T1q\u0013\taVLA\u0002USBT!AW\b\u0002\u000f!\f7OT3yiV\t\u0001\r\u0005\u0002#C&\u0011!m\u0005\u0002\b\u0005>|G.Z1o\u0003\u0011qW\r\u001f;\u0015\u0003mA#!\u00044\u0011\u0005\u001dTW\"\u00015\u000b\u0005%\u001c\u0012AC1o]>$\u0018\r^5p]&\u00111\u000e\u001b\u0002\bi\u0006LGN]3d\u0001"
    )
  ScalaInlineInfo: length = 0x36 (unknown attribute)
   01 00 00 0A 00 57 00 30 00 00 17 00 21 00 00 24
   00 25 00 00 38 00 39 00 00 15 00 19 00 00 1E 00
   1F 00 00 3A 00 3B 01 00 26 00 27 00 00 2F 00 30
   00 00 34 00 35 00
  ScalaSig: length = 0x3 (unknown attribute)
   05 02 00
