Classfile /Users/mw/Projects/slang-braindump/.jar/jar8/assemble/slang-braindump/assemble/content/scala/collection/immutable/Iterable.class
  Last modified May 29, 2022; size 8837 bytes
  SHA-256 checksum 3fcf40b147a27f35a6a61dfd25c39859daea33807abb58237983924f2a83554b
  Compiled from "Iterable.scala"
public interface scala.collection.immutable.Iterable<A extends java.lang.Object> extends scala.collection.Iterable<A>
  minor version: 0
  major version: 52
  flags: (0x0601) ACC_PUBLIC, ACC_INTERFACE, ACC_ABSTRACT
  this_class: #2                          // scala/collection/immutable/Iterable
  super_class: #5                         // java/lang/Object
  interfaces: 1, fields: 0, methods: 21, attributes: 7
Constant pool:
    #1 = Utf8               scala/collection/immutable/Iterable
    #2 = Class              #1            // scala/collection/immutable/Iterable
    #3 = Utf8               <A:Ljava/lang/Object;>Ljava/lang/Object;Lscala/collection/Iterable<TA;>;
    #4 = Utf8               java/lang/Object
    #5 = Class              #4            // java/lang/Object
    #6 = Utf8               scala/collection/Iterable
    #7 = Class              #6            // scala/collection/Iterable
    #8 = Utf8               Iterable.scala
    #9 = Utf8               Lscala/reflect/ScalaSignature;
   #10 = Utf8               bytes
   #11 = Utf8               \u0006\u0005%4q\u0001C\u0005\u0011\u0002\u0007\u0005\u0001\u0003C\u0003.\u0001\u0011\u0005a\u0006C\u00033\u0001\u0011\u00053gB\u00038\u0013!\u0005\u0001HB\u0003\t\u0013!\u0005\u0011\bC\u0003B\t\u0011\u0005!\tC\u0003D\t\u0011\u0005C\tC\u0004Y\t\u0005\u0005I\u0011B-\u0003\u0011%#XM]1cY\u0016T!AC\u0006\u0002\u0013%lW.\u001e;bE2,\'B\u0001\u0007\u000e\u0003)\u0019w\u000e\u001c7fGRLwN\u001c\u0006\u0002\u001d\u0005)1oY1mC\u000e\u0001QCA\t\u001c\'\u0015\u0001!C\u0006\u0013+!\t\u0019B#D\u0001\u000e\u0013\t)RB\u0001\u0004B]f\u0014VM\u001a\t\u0004/aIR\"A\u0006\n\u0005!Y\u0001C\u0001\u000e\u001c\u0019\u0001!a\u0001\b\u0001\u0005\u0006\u0004i\"!A!\u0012\u0005y\t\u0003CA\n \u0013\t\u0001SBA\u0004O_RD\u0017N\\4\u0011\u0005M\u0011\u0013BA\u0012\u000e\u0005\r\te.\u001f\t\u0006/\u0015Jr%K\u0005\u0003M-\u00111\"\u0013;fe\u0006\u0014G.Z(qgB\u0011\u0001\u0006A\u0007\u0002\u0013A\u0019\u0001\u0006A\r\u0011\t]Y\u0013dJ\u0005\u0003Y-\u0011q#\u0013;fe\u0006\u0014G.\u001a$bGR|\'/\u001f#fM\u0006,H\u000e^:\u0002\r\u0011Jg.\u001b;%)\u0005y\u0003CA\n1\u0013\t\tTB\u0001\u0003V]&$\u0018aD5uKJ\f\'\r\\3GC\u000e$xN]=\u0016\u0003Q\u00022aF\u001b(\u0013\t14BA\bJi\u0016\u0014\u0018M\u00197f\r\u0006\u001cGo\u001c:z\u0003!IE/\u001a:bE2,\u0007C\u0001\u0015\u0005\'\t!!\bE\u0002<}\u001dr!a\u0006\u001f\n\u0005uZ\u0011aD%uKJ\f\'\r\\3GC\u000e$xN]=\n\u0005}\u0002%\u0001\u0003#fY\u0016<\u0017\r^3\u000b\u0005uZ\u0011A\u0002\u001fj]&$h\bF\u00019\u0003\u00111\'o\\7\u0016\u0005\u0015CEC\u0001$K!\rA\u0003a\u0012\t\u00035!#Q!\u0013\u0004C\u0002u\u0011\u0011!\u0012\u0005\u0006\u0017\u001a\u0001\r\u0001T\u0001\u0003SR\u00042!T+H\u001d\tq5K\u0004\u0002P%6\t\u0001K\u0003\u0002R\u001f\u00051AH]8pizJ\u0011AD\u0005\u0003)6\tq\u0001]1dW\u0006<W-\u0003\u0002W/\na\u0011\n^3sC\ndWm\u00148dK*\u0011A+D\u0001\roJLG/\u001a*fa2\f7-\u001a\u000b\u00025B\u00111\fY\u0007\u00029*\u0011QLX\u0001\u0005Y\u0006twMC\u0001`\u0003\u0011Q\u0017M^1\n\u0005\u0005d&AB(cU\u0016\u001cG\u000f\u000b\u0003\u0005G\u001a<\u0007CA\ne\u0013\t)WB\u0001\tTKJL\u0017\r\u001c,feNLwN\\+J\t\u0006)a/\u00197vKz\t1\u0001\u000b\u0003\u0004G\u001a<\u0007
   #12 = Utf8               java/lang/invoke/MethodHandles$Lookup
   #13 = Class              #12           // java/lang/invoke/MethodHandles$Lookup
   #14 = Utf8               java/lang/invoke/MethodHandles
   #15 = Class              #14           // java/lang/invoke/MethodHandles
   #16 = Utf8               Lookup
   #17 = Utf8               scala/collection/View$Fill
   #18 = Class              #17           // scala/collection/View$Fill
   #19 = Utf8               scala/collection/View
   #20 = Class              #19           // scala/collection/View
   #21 = Utf8               Fill
   #22 = Utf8               scala/collection/View$Iterate
   #23 = Class              #22           // scala/collection/View$Iterate
   #24 = Utf8               Iterate
   #25 = Utf8               scala/collection/View$Tabulate
   #26 = Class              #25           // scala/collection/View$Tabulate
   #27 = Utf8               Tabulate
   #28 = Utf8               scala/collection/View$Unfold
   #29 = Class              #28           // scala/collection/View$Unfold
   #30 = Utf8               Unfold
   #31 = Utf8               from
   #32 = Utf8               (Lscala/collection/IterableOnce;)Lscala/collection/immutable/Iterable;
   #33 = Utf8               <E:Ljava/lang/Object;>(Lscala/collection/IterableOnce<TE;>;)Lscala/collection/immutable/Iterable<TE;>;
   #34 = Utf8               it
   #35 = Utf8               scala/collection/immutable/Iterable$
   #36 = Class              #35           // scala/collection/immutable/Iterable$
   #37 = Utf8               MODULE$
   #38 = Utf8               Lscala/collection/immutable/Iterable$;
   #39 = NameAndType        #37:#38       // MODULE$:Lscala/collection/immutable/Iterable$;
   #40 = Fieldref           #36.#39       // scala/collection/immutable/Iterable$.MODULE$:Lscala/collection/immutable/Iterable$;
   #41 = NameAndType        #31:#32       // from:(Lscala/collection/IterableOnce;)Lscala/collection/immutable/Iterable;
   #42 = Methodref          #36.#41       // scala/collection/immutable/Iterable$.from:(Lscala/collection/IterableOnce;)Lscala/collection/immutable/Iterable;
   #43 = Utf8               Lscala/collection/IterableOnce;
   #44 = Utf8               newBuilder
   #45 = Utf8               ()Lscala/collection/mutable/Builder;
   #46 = Utf8               <A:Ljava/lang/Object;>()Lscala/collection/mutable/Builder<TA;Lscala/collection/immutable/Iterable<TA;>;>;
   #47 = NameAndType        #44:#45       // newBuilder:()Lscala/collection/mutable/Builder;
   #48 = Methodref          #36.#47       // scala/collection/immutable/Iterable$.newBuilder:()Lscala/collection/mutable/Builder;
   #49 = Utf8               apply
   #50 = Utf8               (Lscala/collection/immutable/Seq;)Ljava/lang/Object;
   #51 = Utf8               elems
   #52 = NameAndType        #49:#50       // apply:(Lscala/collection/immutable/Seq;)Ljava/lang/Object;
   #53 = Methodref          #36.#52       // scala/collection/immutable/Iterable$.apply:(Lscala/collection/immutable/Seq;)Ljava/lang/Object;
   #54 = Utf8               Lscala/collection/immutable/Seq;
   #55 = Utf8               tabulate
   #56 = Utf8               (IIIIILscala/Function5;)Ljava/lang/Object;
   #57 = Utf8               n1
   #58 = Utf8               n2
   #59 = Utf8               n3
   #60 = Utf8               n4
   #61 = Utf8               n5
   #62 = Utf8               f
   #63 = Utf8               (Ljava/lang/Object;)Ljava/lang/Object;
   #64 = MethodType         #63           //  (Ljava/lang/Object;)Ljava/lang/Object;
   #65 = Utf8               scala/collection/IterableFactory
   #66 = Class              #65           // scala/collection/IterableFactory
   #67 = Utf8               $anonfun$tabulate$7$adapted
   #68 = Utf8               (Lscala/collection/IterableFactory;IIIILscala/Function5;Ljava/lang/Object;)Ljava/lang/Object;
   #69 = NameAndType        #67:#68       // $anonfun$tabulate$7$adapted:(Lscala/collection/IterableFactory;IIIILscala/Function5;Ljava/lang/Object;)Ljava/lang/Object;
   #70 = InterfaceMethodref #66.#69       // scala/collection/IterableFactory.$anonfun$tabulate$7$adapted:(Lscala/collection/IterableFactory;IIIILscala/Function5;Ljava/lang/Object;)Ljava/lang/Object;
   #71 = MethodHandle       6:#70         // REF_invokeStatic scala/collection/IterableFactory.$anonfun$tabulate$7$adapted:(Lscala/collection/IterableFactory;IIIILscala/Function5;Ljava/lang/Object;)Ljava/lang/Object;
   #72 = Integer            1
   #73 = Utf8               java/lang/invoke/LambdaMetafactory
   #74 = Class              #73           // java/lang/invoke/LambdaMetafactory
   #75 = Utf8               altMetafactory
   #76 = Utf8               (Ljava/lang/invoke/MethodHandles$Lookup;Ljava/lang/String;Ljava/lang/invoke/MethodType;[Ljava/lang/Object;)Ljava/lang/invoke/CallSite;
   #77 = NameAndType        #75:#76       // altMetafactory:(Ljava/lang/invoke/MethodHandles$Lookup;Ljava/lang/String;Ljava/lang/invoke/MethodType;[Ljava/lang/Object;)Ljava/lang/invoke/CallSite;
   #78 = Methodref          #74.#77       // java/lang/invoke/LambdaMetafactory.altMetafactory:(Ljava/lang/invoke/MethodHandles$Lookup;Ljava/lang/String;Ljava/lang/invoke/MethodType;[Ljava/lang/Object;)Ljava/lang/invoke/CallSite;
   #79 = MethodHandle       6:#78         // REF_invokeStatic java/lang/invoke/LambdaMetafactory.altMetafactory:(Ljava/lang/invoke/MethodHandles$Lookup;Ljava/lang/String;Ljava/lang/invoke/MethodType;[Ljava/lang/Object;)Ljava/lang/invoke/CallSite;
   #80 = Utf8               (Lscala/collection/IterableFactory;IIIILscala/Function5;)Lscala/Function1;
   #81 = NameAndType        #49:#80       // apply:(Lscala/collection/IterableFactory;IIIILscala/Function5;)Lscala/Function1;
   #82 = InvokeDynamic      #0:#81        // #0:apply:(Lscala/collection/IterableFactory;IIIILscala/Function5;)Lscala/Function1;
   #83 = Utf8               (ILscala/Function1;)Ljava/lang/Object;
   #84 = NameAndType        #55:#83       // tabulate:(ILscala/Function1;)Ljava/lang/Object;
   #85 = InterfaceMethodref #66.#84       // scala/collection/IterableFactory.tabulate:(ILscala/Function1;)Ljava/lang/Object;
   #86 = Utf8               I
   #87 = Utf8               Lscala/Function5;
   #88 = Utf8               tabulate_this
   #89 = Utf8               Lscala/collection/IterableFactory$Delegate;
   #90 = Utf8               (IIIILscala/Function4;)Ljava/lang/Object;
   #91 = Utf8               $anonfun$tabulate$5$adapted
   #92 = Utf8               (Lscala/collection/IterableFactory;IIILscala/Function4;Ljava/lang/Object;)Ljava/lang/Object;
   #93 = NameAndType        #91:#92       // $anonfun$tabulate$5$adapted:(Lscala/collection/IterableFactory;IIILscala/Function4;Ljava/lang/Object;)Ljava/lang/Object;
   #94 = InterfaceMethodref #66.#93       // scala/collection/IterableFactory.$anonfun$tabulate$5$adapted:(Lscala/collection/IterableFactory;IIILscala/Function4;Ljava/lang/Object;)Ljava/lang/Object;
   #95 = MethodHandle       6:#94         // REF_invokeStatic scala/collection/IterableFactory.$anonfun$tabulate$5$adapted:(Lscala/collection/IterableFactory;IIILscala/Function4;Ljava/lang/Object;)Ljava/lang/Object;
   #96 = Utf8               (Lscala/collection/IterableFactory;IIILscala/Function4;)Lscala/Function1;
   #97 = NameAndType        #49:#96       // apply:(Lscala/collection/IterableFactory;IIILscala/Function4;)Lscala/Function1;
   #98 = InvokeDynamic      #1:#97        // #1:apply:(Lscala/collection/IterableFactory;IIILscala/Function4;)Lscala/Function1;
   #99 = Utf8               Lscala/Function4;
  #100 = Utf8               (IIILscala/Function3;)Ljava/lang/Object;
  #101 = Utf8               $anonfun$tabulate$3$adapted
  #102 = Utf8               (Lscala/collection/IterableFactory;IILscala/Function3;Ljava/lang/Object;)Ljava/lang/Object;
  #103 = NameAndType        #101:#102     // $anonfun$tabulate$3$adapted:(Lscala/collection/IterableFactory;IILscala/Function3;Ljava/lang/Object;)Ljava/lang/Object;
  #104 = InterfaceMethodref #66.#103      // scala/collection/IterableFactory.$anonfun$tabulate$3$adapted:(Lscala/collection/IterableFactory;IILscala/Function3;Ljava/lang/Object;)Ljava/lang/Object;
  #105 = MethodHandle       6:#104        // REF_invokeStatic scala/collection/IterableFactory.$anonfun$tabulate$3$adapted:(Lscala/collection/IterableFactory;IILscala/Function3;Ljava/lang/Object;)Ljava/lang/Object;
  #106 = Utf8               (Lscala/collection/IterableFactory;IILscala/Function3;)Lscala/Function1;
  #107 = NameAndType        #49:#106      // apply:(Lscala/collection/IterableFactory;IILscala/Function3;)Lscala/Function1;
  #108 = InvokeDynamic      #2:#107       // #2:apply:(Lscala/collection/IterableFactory;IILscala/Function3;)Lscala/Function1;
  #109 = Utf8               Lscala/Function3;
  #110 = Utf8               (IILscala/Function2;)Ljava/lang/Object;
  #111 = Utf8               $anonfun$tabulate$1$adapted
  #112 = Utf8               (Lscala/collection/IterableFactory;ILscala/Function2;Ljava/lang/Object;)Ljava/lang/Object;
  #113 = NameAndType        #111:#112     // $anonfun$tabulate$1$adapted:(Lscala/collection/IterableFactory;ILscala/Function2;Ljava/lang/Object;)Ljava/lang/Object;
  #114 = InterfaceMethodref #66.#113      // scala/collection/IterableFactory.$anonfun$tabulate$1$adapted:(Lscala/collection/IterableFactory;ILscala/Function2;Ljava/lang/Object;)Ljava/lang/Object;
  #115 = MethodHandle       6:#114        // REF_invokeStatic scala/collection/IterableFactory.$anonfun$tabulate$1$adapted:(Lscala/collection/IterableFactory;ILscala/Function2;Ljava/lang/Object;)Ljava/lang/Object;
  #116 = Utf8               (Lscala/collection/IterableFactory;ILscala/Function2;)Lscala/Function1;
  #117 = NameAndType        #49:#116      // apply:(Lscala/collection/IterableFactory;ILscala/Function2;)Lscala/Function1;
  #118 = InvokeDynamic      #3:#117       // #3:apply:(Lscala/collection/IterableFactory;ILscala/Function2;)Lscala/Function1;
  #119 = Utf8               Lscala/Function2;
  #120 = Utf8               n
  #121 = Utf8               <init>
  #122 = Utf8               (ILscala/Function1;)V
  #123 = NameAndType        #121:#122     // "<init>":(ILscala/Function1;)V
  #124 = Methodref          #26.#123      // scala/collection/View$Tabulate."<init>":(ILscala/Function1;)V
  #125 = Utf8               Lscala/Function1;
  #126 = Utf8               from_it
  #127 = Utf8               fill
  #128 = Utf8               (IIIIILscala/Function0;)Ljava/lang/Object;
  #129 = Utf8               elem
  #130 = Utf8               ()Ljava/lang/Object;
  #131 = MethodType         #130          //  ()Ljava/lang/Object;
  #132 = Utf8               $anonfun$fill$4
  #133 = Utf8               (Lscala/collection/IterableFactory;IIIILscala/Function0;)Ljava/lang/Object;
  #134 = NameAndType        #132:#133     // $anonfun$fill$4:(Lscala/collection/IterableFactory;IIIILscala/Function0;)Ljava/lang/Object;
  #135 = InterfaceMethodref #66.#134      // scala/collection/IterableFactory.$anonfun$fill$4:(Lscala/collection/IterableFactory;IIIILscala/Function0;)Ljava/lang/Object;
  #136 = MethodHandle       6:#135        // REF_invokeStatic scala/collection/IterableFactory.$anonfun$fill$4:(Lscala/collection/IterableFactory;IIIILscala/Function0;)Ljava/lang/Object;
  #137 = Utf8               (Lscala/collection/IterableFactory;IIIILscala/Function0;)Lscala/Function0;
  #138 = NameAndType        #49:#137      // apply:(Lscala/collection/IterableFactory;IIIILscala/Function0;)Lscala/Function0;
  #139 = InvokeDynamic      #4:#138       // #4:apply:(Lscala/collection/IterableFactory;IIIILscala/Function0;)Lscala/Function0;
  #140 = Utf8               (ILscala/Function0;)Ljava/lang/Object;
  #141 = NameAndType        #127:#140     // fill:(ILscala/Function0;)Ljava/lang/Object;
  #142 = InterfaceMethodref #66.#141      // scala/collection/IterableFactory.fill:(ILscala/Function0;)Ljava/lang/Object;
  #143 = Utf8               Lscala/Function0;
  #144 = Utf8               fill_this
  #145 = Utf8               (IIIILscala/Function0;)Ljava/lang/Object;
  #146 = Utf8               $anonfun$fill$3
  #147 = Utf8               (Lscala/collection/IterableFactory;IIILscala/Function0;)Ljava/lang/Object;
  #148 = NameAndType        #146:#147     // $anonfun$fill$3:(Lscala/collection/IterableFactory;IIILscala/Function0;)Ljava/lang/Object;
  #149 = InterfaceMethodref #66.#148      // scala/collection/IterableFactory.$anonfun$fill$3:(Lscala/collection/IterableFactory;IIILscala/Function0;)Ljava/lang/Object;
  #150 = MethodHandle       6:#149        // REF_invokeStatic scala/collection/IterableFactory.$anonfun$fill$3:(Lscala/collection/IterableFactory;IIILscala/Function0;)Ljava/lang/Object;
  #151 = Utf8               (Lscala/collection/IterableFactory;IIILscala/Function0;)Lscala/Function0;
  #152 = NameAndType        #49:#151      // apply:(Lscala/collection/IterableFactory;IIILscala/Function0;)Lscala/Function0;
  #153 = InvokeDynamic      #5:#152       // #5:apply:(Lscala/collection/IterableFactory;IIILscala/Function0;)Lscala/Function0;
  #154 = Utf8               (IIILscala/Function0;)Ljava/lang/Object;
  #155 = Utf8               $anonfun$fill$2
  #156 = Utf8               (Lscala/collection/IterableFactory;IILscala/Function0;)Ljava/lang/Object;
  #157 = NameAndType        #155:#156     // $anonfun$fill$2:(Lscala/collection/IterableFactory;IILscala/Function0;)Ljava/lang/Object;
  #158 = InterfaceMethodref #66.#157      // scala/collection/IterableFactory.$anonfun$fill$2:(Lscala/collection/IterableFactory;IILscala/Function0;)Ljava/lang/Object;
  #159 = MethodHandle       6:#158        // REF_invokeStatic scala/collection/IterableFactory.$anonfun$fill$2:(Lscala/collection/IterableFactory;IILscala/Function0;)Ljava/lang/Object;
  #160 = Utf8               (Lscala/collection/IterableFactory;IILscala/Function0;)Lscala/Function0;
  #161 = NameAndType        #49:#160      // apply:(Lscala/collection/IterableFactory;IILscala/Function0;)Lscala/Function0;
  #162 = InvokeDynamic      #6:#161       // #6:apply:(Lscala/collection/IterableFactory;IILscala/Function0;)Lscala/Function0;
  #163 = Utf8               (IILscala/Function0;)Ljava/lang/Object;
  #164 = Utf8               $anonfun$fill$1
  #165 = Utf8               (Lscala/collection/IterableFactory;ILscala/Function0;)Ljava/lang/Object;
  #166 = NameAndType        #164:#165     // $anonfun$fill$1:(Lscala/collection/IterableFactory;ILscala/Function0;)Ljava/lang/Object;
  #167 = InterfaceMethodref #66.#166      // scala/collection/IterableFactory.$anonfun$fill$1:(Lscala/collection/IterableFactory;ILscala/Function0;)Ljava/lang/Object;
  #168 = MethodHandle       6:#167        // REF_invokeStatic scala/collection/IterableFactory.$anonfun$fill$1:(Lscala/collection/IterableFactory;ILscala/Function0;)Ljava/lang/Object;
  #169 = Utf8               (Lscala/collection/IterableFactory;ILscala/Function0;)Lscala/Function0;
  #170 = NameAndType        #49:#169      // apply:(Lscala/collection/IterableFactory;ILscala/Function0;)Lscala/Function0;
  #171 = InvokeDynamic      #7:#170       // #7:apply:(Lscala/collection/IterableFactory;ILscala/Function0;)Lscala/Function0;
  #172 = Utf8               (ILscala/Function0;)V
  #173 = NameAndType        #121:#172     // "<init>":(ILscala/Function0;)V
  #174 = Methodref          #18.#173      // scala/collection/View$Fill."<init>":(ILscala/Function0;)V
  #175 = Utf8               range
  #176 = Utf8               (Ljava/lang/Object;Ljava/lang/Object;Ljava/lang/Object;Lscala/math/Integral;)Ljava/lang/Object;
  #177 = Utf8               start
  #178 = Utf8               end
  #179 = Utf8               step
  #180 = Utf8               evidence$4
  #181 = Utf8               range$
  #182 = Utf8               (Lscala/collection/IterableFactory;Ljava/lang/Object;Ljava/lang/Object;Ljava/lang/Object;Lscala/math/Integral;)Ljava/lang/Object;
  #183 = NameAndType        #181:#182     // range$:(Lscala/collection/IterableFactory;Ljava/lang/Object;Ljava/lang/Object;Ljava/lang/Object;Lscala/math/Integral;)Ljava/lang/Object;
  #184 = InterfaceMethodref #66.#183      // scala/collection/IterableFactory.range$:(Lscala/collection/IterableFactory;Ljava/lang/Object;Ljava/lang/Object;Ljava/lang/Object;Lscala/math/Integral;)Ljava/lang/Object;
  #185 = Utf8               Ljava/lang/Object;
  #186 = Utf8               Lscala/math/Integral;
  #187 = Utf8               (Ljava/lang/Object;Ljava/lang/Object;Lscala/math/Integral;)Ljava/lang/Object;
  #188 = Utf8               evidence$3
  #189 = Utf8               (Lscala/collection/IterableFactory;Ljava/lang/Object;Ljava/lang/Object;Lscala/math/Integral;)Ljava/lang/Object;
  #190 = NameAndType        #181:#189     // range$:(Lscala/collection/IterableFactory;Ljava/lang/Object;Ljava/lang/Object;Lscala/math/Integral;)Ljava/lang/Object;
  #191 = InterfaceMethodref #66.#190      // scala/collection/IterableFactory.range$:(Lscala/collection/IterableFactory;Ljava/lang/Object;Ljava/lang/Object;Lscala/math/Integral;)Ljava/lang/Object;
  #192 = Utf8               unfold
  #193 = Utf8               (Ljava/lang/Object;Lscala/Function1;)Ljava/lang/Object;
  #194 = Utf8               init
  #195 = Utf8               (Ljava/lang/Object;Lscala/Function1;)V
  #196 = NameAndType        #121:#195     // "<init>":(Ljava/lang/Object;Lscala/Function1;)V
  #197 = Methodref          #29.#196      // scala/collection/View$Unfold."<init>":(Ljava/lang/Object;Lscala/Function1;)V
  #198 = Utf8               unfold_this
  #199 = Utf8               iterate
  #200 = Utf8               (Ljava/lang/Object;ILscala/Function1;)Ljava/lang/Object;
  #201 = Utf8               len
  #202 = Utf8               (Ljava/lang/Object;ILscala/Function1;)V
  #203 = NameAndType        #121:#202     // "<init>":(Ljava/lang/Object;ILscala/Function1;)V
  #204 = Methodref          #23.#203      // scala/collection/View$Iterate."<init>":(Ljava/lang/Object;ILscala/Function1;)V
  #205 = Utf8               iterate_this
  #206 = Utf8               iterableFactory$
  #207 = Utf8               (Lscala/collection/immutable/Iterable;)Lscala/collection/IterableFactory;
  #208 = Utf8               $this
  #209 = Utf8               iterableFactory
  #210 = Utf8               ()Lscala/collection/IterableFactory;
  #211 = NameAndType        #209:#210     // iterableFactory:()Lscala/collection/IterableFactory;
  #212 = InterfaceMethodref #2.#211       // scala/collection/immutable/Iterable.iterableFactory:()Lscala/collection/IterableFactory;
  #213 = Utf8               Lscala/collection/immutable/Iterable;
  #214 = Utf8               ()Lscala/collection/IterableFactory<Lscala/collection/immutable/Iterable;>;
  #215 = Utf8               this
  #216 = Utf8               $init$
  #217 = Utf8               (Lscala/collection/immutable/Iterable;)V
  #218 = Utf8               $deserializeLambda$
  #219 = Utf8               (Ljava/lang/invoke/SerializedLambda;)Ljava/lang/Object;
  #220 = Utf8               scala/runtime/LambdaDeserialize
  #221 = Class              #220          // scala/runtime/LambdaDeserialize
  #222 = Utf8               bootstrap
  #223 = Utf8               (Ljava/lang/invoke/MethodHandles$Lookup;Ljava/lang/String;Ljava/lang/invoke/MethodType;[Ljava/lang/invoke/MethodHandle;)Ljava/lang/invoke/CallSite;
  #224 = NameAndType        #222:#223     // bootstrap:(Ljava/lang/invoke/MethodHandles$Lookup;Ljava/lang/String;Ljava/lang/invoke/MethodType;[Ljava/lang/invoke/MethodHandle;)Ljava/lang/invoke/CallSite;
  #225 = Methodref          #221.#224     // scala/runtime/LambdaDeserialize.bootstrap:(Ljava/lang/invoke/MethodHandles$Lookup;Ljava/lang/String;Ljava/lang/invoke/MethodType;[Ljava/lang/invoke/MethodHandle;)Ljava/lang/invoke/CallSite;
  #226 = MethodHandle       6:#225        // REF_invokeStatic scala/runtime/LambdaDeserialize.bootstrap:(Ljava/lang/invoke/MethodHandles$Lookup;Ljava/lang/String;Ljava/lang/invoke/MethodType;[Ljava/lang/invoke/MethodHandle;)Ljava/lang/invoke/CallSite;
  #227 = Utf8               lambdaDeserialize
  #228 = NameAndType        #227:#219     // lambdaDeserialize:(Ljava/lang/invoke/SerializedLambda;)Ljava/lang/Object;
  #229 = InvokeDynamic      #8:#228       // #8:lambdaDeserialize:(Ljava/lang/invoke/SerializedLambda;)Ljava/lang/Object;
  #230 = Utf8               Code
  #231 = Utf8               LocalVariableTable
  #232 = Utf8               Signature
  #233 = Utf8               MethodParameters
  #234 = Utf8               LineNumberTable
  #235 = Utf8               InnerClasses
  #236 = Utf8               SourceFile
  #237 = Utf8               RuntimeVisibleAnnotations
  #238 = Utf8               BootstrapMethods
  #239 = Utf8               ScalaInlineInfo
  #240 = Utf8               ScalaSig
{
  public static <E extends java.lang.Object> scala.collection.immutable.Iterable<E> from(scala.collection.IterableOnce<E>);
    descriptor: (Lscala/collection/IterableOnce;)Lscala/collection/immutable/Iterable;
    flags: (0x0009) ACC_PUBLIC, ACC_STATIC
    Code:
      stack=2, locals=1, args_size=1
         0: getstatic     #40                 // Field scala/collection/immutable/Iterable$.MODULE$:Lscala/collection/immutable/Iterable$;
         3: aload_0
         4: invokevirtual #42                 // Method scala/collection/immutable/Iterable$.from:(Lscala/collection/IterableOnce;)Lscala/collection/immutable/Iterable;
         7: areturn
      LocalVariableTable:
        Start  Length  Slot  Name   Signature
            0       8     0    it   Lscala/collection/IterableOnce;
    Signature: #33                          // <E:Ljava/lang/Object;>(Lscala/collection/IterableOnce<TE;>;)Lscala/collection/immutable/Iterable<TE;>;
    MethodParameters:
      Name                           Flags
      it                             final

  public static <A extends java.lang.Object> scala.collection.mutable.Builder<A, scala.collection.immutable.Iterable<A>> newBuilder();
    descriptor: ()Lscala/collection/mutable/Builder;
    flags: (0x0009) ACC_PUBLIC, ACC_STATIC
    Code:
      stack=1, locals=0, args_size=0
         0: getstatic     #40                 // Field scala/collection/immutable/Iterable$.MODULE$:Lscala/collection/immutable/Iterable$;
         3: invokevirtual #48                 // Method scala/collection/immutable/Iterable$.newBuilder:()Lscala/collection/mutable/Builder;
         6: areturn
    Signature: #46                          // <A:Ljava/lang/Object;>()Lscala/collection/mutable/Builder<TA;Lscala/collection/immutable/Iterable<TA;>;>;

  public static java.lang.Object apply(scala.collection.immutable.Seq);
    descriptor: (Lscala/collection/immutable/Seq;)Ljava/lang/Object;
    flags: (0x0009) ACC_PUBLIC, ACC_STATIC
    Code:
      stack=2, locals=1, args_size=1
         0: getstatic     #40                 // Field scala/collection/immutable/Iterable$.MODULE$:Lscala/collection/immutable/Iterable$;
         3: aload_0
         4: invokevirtual #53                 // Method scala/collection/immutable/Iterable$.apply:(Lscala/collection/immutable/Seq;)Ljava/lang/Object;
         7: areturn
      LocalVariableTable:
        Start  Length  Slot  Name   Signature
            0       8     0 elems   Lscala/collection/immutable/Seq;
    MethodParameters:
      Name                           Flags
      elems                          final

  public static java.lang.Object tabulate(int, int, int, int, int, scala.Function5);
    descriptor: (IIIIILscala/Function5;)Ljava/lang/Object;
    flags: (0x0009) ACC_PUBLIC, ACC_STATIC
    Code:
      stack=8, locals=7, args_size=6
         0: getstatic     #40                 // Field scala/collection/immutable/Iterable$.MODULE$:Lscala/collection/immutable/Iterable$;
         3: astore        6
         5: aload         6
         7: iload_0
         8: aload         6
        10: iload_1
        11: iload_2
        12: iload_3
        13: iload         4
        15: aload         5
        17: invokedynamic #82,  0             // InvokeDynamic #0:apply:(Lscala/collection/IterableFactory;IIIILscala/Function5;)Lscala/Function1;
        22: invokeinterface #85,  3           // InterfaceMethod scala/collection/IterableFactory.tabulate:(ILscala/Function1;)Ljava/lang/Object;
        27: areturn
      LocalVariableTable:
        Start  Length  Slot  Name   Signature
            0      28     0    n1   I
            0      28     1    n2   I
            0      28     2    n3   I
            0      28     3    n4   I
            0      28     4    n5   I
            0      28     5     f   Lscala/Function5;
            5      22     6 tabulate_this   Lscala/collection/IterableFactory$Delegate;
    MethodParameters:
      Name                           Flags
      n1                             final
      n2                             final
      n3                             final
      n4                             final
      n5                             final
      f                              final

  public static java.lang.Object tabulate(int, int, int, int, scala.Function4);
    descriptor: (IIIILscala/Function4;)Ljava/lang/Object;
    flags: (0x0009) ACC_PUBLIC, ACC_STATIC
    Code:
      stack=7, locals=6, args_size=5
         0: getstatic     #40                 // Field scala/collection/immutable/Iterable$.MODULE$:Lscala/collection/immutable/Iterable$;
         3: astore        5
         5: aload         5
         7: iload_0
         8: aload         5
        10: iload_1
        11: iload_2
        12: iload_3
        13: aload         4
        15: invokedynamic #98,  0             // InvokeDynamic #1:apply:(Lscala/collection/IterableFactory;IIILscala/Function4;)Lscala/Function1;
        20: invokeinterface #85,  3           // InterfaceMethod scala/collection/IterableFactory.tabulate:(ILscala/Function1;)Ljava/lang/Object;
        25: areturn
      LocalVariableTable:
        Start  Length  Slot  Name   Signature
            0      26     0    n1   I
            0      26     1    n2   I
            0      26     2    n3   I
            0      26     3    n4   I
            0      26     4     f   Lscala/Function4;
            5      20     5 tabulate_this   Lscala/collection/IterableFactory$Delegate;
    MethodParameters:
      Name                           Flags
      n1                             final
      n2                             final
      n3                             final
      n4                             final
      f                              final

  public static java.lang.Object tabulate(int, int, int, scala.Function3);
    descriptor: (IIILscala/Function3;)Ljava/lang/Object;
    flags: (0x0009) ACC_PUBLIC, ACC_STATIC
    Code:
      stack=6, locals=5, args_size=4
         0: getstatic     #40                 // Field scala/collection/immutable/Iterable$.MODULE$:Lscala/collection/immutable/Iterable$;
         3: astore        4
         5: aload         4
         7: iload_0
         8: aload         4
        10: iload_1
        11: iload_2
        12: aload_3
        13: invokedynamic #108,  0            // InvokeDynamic #2:apply:(Lscala/collection/IterableFactory;IILscala/Function3;)Lscala/Function1;
        18: invokeinterface #85,  3           // InterfaceMethod scala/collection/IterableFactory.tabulate:(ILscala/Function1;)Ljava/lang/Object;
        23: areturn
      LocalVariableTable:
        Start  Length  Slot  Name   Signature
            0      24     0    n1   I
            0      24     1    n2   I
            0      24     2    n3   I
            0      24     3     f   Lscala/Function3;
            5      18     4 tabulate_this   Lscala/collection/IterableFactory$Delegate;
    MethodParameters:
      Name                           Flags
      n1                             final
      n2                             final
      n3                             final
      f                              final

  public static java.lang.Object tabulate(int, int, scala.Function2);
    descriptor: (IILscala/Function2;)Ljava/lang/Object;
    flags: (0x0009) ACC_PUBLIC, ACC_STATIC
    Code:
      stack=5, locals=4, args_size=3
         0: getstatic     #40                 // Field scala/collection/immutable/Iterable$.MODULE$:Lscala/collection/immutable/Iterable$;
         3: astore_3
         4: aload_3
         5: iload_0
         6: aload_3
         7: iload_1
         8: aload_2
         9: invokedynamic #118,  0            // InvokeDynamic #3:apply:(Lscala/collection/IterableFactory;ILscala/Function2;)Lscala/Function1;
        14: invokeinterface #85,  3           // InterfaceMethod scala/collection/IterableFactory.tabulate:(ILscala/Function1;)Ljava/lang/Object;
        19: areturn
      LocalVariableTable:
        Start  Length  Slot  Name   Signature
            0      20     0    n1   I
            0      20     1    n2   I
            0      20     2     f   Lscala/Function2;
            4      15     3 tabulate_this   Lscala/collection/IterableFactory$Delegate;
    MethodParameters:
      Name                           Flags
      n1                             final
      n2                             final
      f                              final

  public static java.lang.Object tabulate(int, scala.Function1);
    descriptor: (ILscala/Function1;)Ljava/lang/Object;
    flags: (0x0009) ACC_PUBLIC, ACC_STATIC
    Code:
      stack=4, locals=4, args_size=2
         0: getstatic     #40                 // Field scala/collection/immutable/Iterable$.MODULE$:Lscala/collection/immutable/Iterable$;
         3: astore_2
         4: new           #26                 // class scala/collection/View$Tabulate
         7: dup
         8: iload_0
         9: aload_1
        10: invokespecial #124                // Method scala/collection/View$Tabulate."<init>":(ILscala/Function1;)V
        13: astore_3
        14: aload_2
        15: aload_3
        16: invokevirtual #42                 // Method scala/collection/immutable/Iterable$.from:(Lscala/collection/IterableOnce;)Lscala/collection/immutable/Iterable;
        19: areturn
      LineNumberTable:
        line 32: 14
      LocalVariableTable:
        Start  Length  Slot  Name   Signature
            0      20     0     n   I
            0      20     1     f   Lscala/Function1;
            4      15     2 tabulate_this   Lscala/collection/IterableFactory$Delegate;
           14       5     3 from_it   Lscala/collection/IterableOnce;
    MethodParameters:
      Name                           Flags
      n                              final
      f                              final

  public static java.lang.Object fill(int, int, int, int, int, scala.Function0);
    descriptor: (IIIIILscala/Function0;)Ljava/lang/Object;
    flags: (0x0009) ACC_PUBLIC, ACC_STATIC
    Code:
      stack=8, locals=7, args_size=6
         0: getstatic     #40                 // Field scala/collection/immutable/Iterable$.MODULE$:Lscala/collection/immutable/Iterable$;
         3: astore        6
         5: aload         6
         7: iload_0
         8: aload         6
        10: iload_1
        11: iload_2
        12: iload_3
        13: iload         4
        15: aload         5
        17: invokedynamic #139,  0            // InvokeDynamic #4:apply:(Lscala/collection/IterableFactory;IIIILscala/Function0;)Lscala/Function0;
        22: invokeinterface #142,  3          // InterfaceMethod scala/collection/IterableFactory.fill:(ILscala/Function0;)Ljava/lang/Object;
        27: areturn
      LocalVariableTable:
        Start  Length  Slot  Name   Signature
            0      28     0    n1   I
            0      28     1    n2   I
            0      28     2    n3   I
            0      28     3    n4   I
            0      28     4    n5   I
            0      28     5  elem   Lscala/Function0;
            5      22     6 fill_this   Lscala/collection/IterableFactory$Delegate;
    MethodParameters:
      Name                           Flags
      n1                             final
      n2                             final
      n3                             final
      n4                             final
      n5                             final
      elem                           final

  public static java.lang.Object fill(int, int, int, int, scala.Function0);
    descriptor: (IIIILscala/Function0;)Ljava/lang/Object;
    flags: (0x0009) ACC_PUBLIC, ACC_STATIC
    Code:
      stack=7, locals=6, args_size=5
         0: getstatic     #40                 // Field scala/collection/immutable/Iterable$.MODULE$:Lscala/collection/immutable/Iterable$;
         3: astore        5
         5: aload         5
         7: iload_0
         8: aload         5
        10: iload_1
        11: iload_2
        12: iload_3
        13: aload         4
        15: invokedynamic #153,  0            // InvokeDynamic #5:apply:(Lscala/collection/IterableFactory;IIILscala/Function0;)Lscala/Function0;
        20: invokeinterface #142,  3          // InterfaceMethod scala/collection/IterableFactory.fill:(ILscala/Function0;)Ljava/lang/Object;
        25: areturn
      LocalVariableTable:
        Start  Length  Slot  Name   Signature
            0      26     0    n1   I
            0      26     1    n2   I
            0      26     2    n3   I
            0      26     3    n4   I
            0      26     4  elem   Lscala/Function0;
            5      20     5 fill_this   Lscala/collection/IterableFactory$Delegate;
    MethodParameters:
      Name                           Flags
      n1                             final
      n2                             final
      n3                             final
      n4                             final
      elem                           final

  public static java.lang.Object fill(int, int, int, scala.Function0);
    descriptor: (IIILscala/Function0;)Ljava/lang/Object;
    flags: (0x0009) ACC_PUBLIC, ACC_STATIC
    Code:
      stack=6, locals=5, args_size=4
         0: getstatic     #40                 // Field scala/collection/immutable/Iterable$.MODULE$:Lscala/collection/immutable/Iterable$;
         3: astore        4
         5: aload         4
         7: iload_0
         8: aload         4
        10: iload_1
        11: iload_2
        12: aload_3
        13: invokedynamic #162,  0            // InvokeDynamic #6:apply:(Lscala/collection/IterableFactory;IILscala/Function0;)Lscala/Function0;
        18: invokeinterface #142,  3          // InterfaceMethod scala/collection/IterableFactory.fill:(ILscala/Function0;)Ljava/lang/Object;
        23: areturn
      LocalVariableTable:
        Start  Length  Slot  Name   Signature
            0      24     0    n1   I
            0      24     1    n2   I
            0      24     2    n3   I
            0      24     3  elem   Lscala/Function0;
            5      18     4 fill_this   Lscala/collection/IterableFactory$Delegate;
    MethodParameters:
      Name                           Flags
      n1                             final
      n2                             final
      n3                             final
      elem                           final

  public static java.lang.Object fill(int, int, scala.Function0);
    descriptor: (IILscala/Function0;)Ljava/lang/Object;
    flags: (0x0009) ACC_PUBLIC, ACC_STATIC
    Code:
      stack=5, locals=4, args_size=3
         0: getstatic     #40                 // Field scala/collection/immutable/Iterable$.MODULE$:Lscala/collection/immutable/Iterable$;
         3: astore_3
         4: aload_3
         5: iload_0
         6: aload_3
         7: iload_1
         8: aload_2
         9: invokedynamic #171,  0            // InvokeDynamic #7:apply:(Lscala/collection/IterableFactory;ILscala/Function0;)Lscala/Function0;
        14: invokeinterface #142,  3          // InterfaceMethod scala/collection/IterableFactory.fill:(ILscala/Function0;)Ljava/lang/Object;
        19: areturn
      LocalVariableTable:
        Start  Length  Slot  Name   Signature
            0      20     0    n1   I
            0      20     1    n2   I
            0      20     2  elem   Lscala/Function0;
            4      15     3 fill_this   Lscala/collection/IterableFactory$Delegate;
    MethodParameters:
      Name                           Flags
      n1                             final
      n2                             final
      elem                           final

  public static java.lang.Object fill(int, scala.Function0);
    descriptor: (ILscala/Function0;)Ljava/lang/Object;
    flags: (0x0009) ACC_PUBLIC, ACC_STATIC
    Code:
      stack=4, locals=4, args_size=2
         0: getstatic     #40                 // Field scala/collection/immutable/Iterable$.MODULE$:Lscala/collection/immutable/Iterable$;
         3: astore_2
         4: new           #18                 // class scala/collection/View$Fill
         7: dup
         8: iload_0
         9: aload_1
        10: invokespecial #174                // Method scala/collection/View$Fill."<init>":(ILscala/Function0;)V
        13: astore_3
        14: aload_2
        15: aload_3
        16: invokevirtual #42                 // Method scala/collection/immutable/Iterable$.from:(Lscala/collection/IterableOnce;)Lscala/collection/immutable/Iterable;
        19: areturn
      LineNumberTable:
        line 32: 14
      LocalVariableTable:
        Start  Length  Slot  Name   Signature
            0      20     0     n   I
            0      20     1  elem   Lscala/Function0;
            4      15     2 fill_this   Lscala/collection/IterableFactory$Delegate;
           14       5     3 from_it   Lscala/collection/IterableOnce;
    MethodParameters:
      Name                           Flags
      n                              final
      elem                           final

  public static java.lang.Object range(java.lang.Object, java.lang.Object, java.lang.Object, scala.math.Integral);
    descriptor: (Ljava/lang/Object;Ljava/lang/Object;Ljava/lang/Object;Lscala/math/Integral;)Ljava/lang/Object;
    flags: (0x0009) ACC_PUBLIC, ACC_STATIC
    Code:
      stack=5, locals=4, args_size=4
         0: getstatic     #40                 // Field scala/collection/immutable/Iterable$.MODULE$:Lscala/collection/immutable/Iterable$;
         3: aload_0
         4: aload_1
         5: aload_2
         6: aload_3
         7: invokestatic  #184                // InterfaceMethod scala/collection/IterableFactory.range$:(Lscala/collection/IterableFactory;Ljava/lang/Object;Ljava/lang/Object;Ljava/lang/Object;Lscala/math/Integral;)Ljava/lang/Object;
        10: areturn
      LocalVariableTable:
        Start  Length  Slot  Name   Signature
            0      11     0 start   Ljava/lang/Object;
            0      11     1   end   Ljava/lang/Object;
            0      11     2  step   Ljava/lang/Object;
            0      11     3 evidence$4   Lscala/math/Integral;
    MethodParameters:
      Name                           Flags
      start                          final
      end                            final
      step                           final
      evidence$4                     final

  public static java.lang.Object range(java.lang.Object, java.lang.Object, scala.math.Integral);
    descriptor: (Ljava/lang/Object;Ljava/lang/Object;Lscala/math/Integral;)Ljava/lang/Object;
    flags: (0x0009) ACC_PUBLIC, ACC_STATIC
    Code:
      stack=4, locals=3, args_size=3
         0: getstatic     #40                 // Field scala/collection/immutable/Iterable$.MODULE$:Lscala/collection/immutable/Iterable$;
         3: aload_0
         4: aload_1
         5: aload_2
         6: invokestatic  #191                // InterfaceMethod scala/collection/IterableFactory.range$:(Lscala/collection/IterableFactory;Ljava/lang/Object;Ljava/lang/Object;Lscala/math/Integral;)Ljava/lang/Object;
         9: areturn
      LocalVariableTable:
        Start  Length  Slot  Name   Signature
            0      10     0 start   Ljava/lang/Object;
            0      10     1   end   Ljava/lang/Object;
            0      10     2 evidence$3   Lscala/math/Integral;
    MethodParameters:
      Name                           Flags
      start                          final
      end                            final
      evidence$3                     final

  public static java.lang.Object unfold(java.lang.Object, scala.Function1);
    descriptor: (Ljava/lang/Object;Lscala/Function1;)Ljava/lang/Object;
    flags: (0x0009) ACC_PUBLIC, ACC_STATIC
    Code:
      stack=4, locals=4, args_size=2
         0: getstatic     #40                 // Field scala/collection/immutable/Iterable$.MODULE$:Lscala/collection/immutable/Iterable$;
         3: astore_2
         4: new           #29                 // class scala/collection/View$Unfold
         7: dup
         8: aload_0
         9: aload_1
        10: invokespecial #197                // Method scala/collection/View$Unfold."<init>":(Ljava/lang/Object;Lscala/Function1;)V
        13: astore_3
        14: aload_2
        15: aload_3
        16: invokevirtual #42                 // Method scala/collection/immutable/Iterable$.from:(Lscala/collection/IterableOnce;)Lscala/collection/immutable/Iterable;
        19: areturn
      LineNumberTable:
        line 32: 14
      LocalVariableTable:
        Start  Length  Slot  Name   Signature
            0      20     0  init   Ljava/lang/Object;
            0      20     1     f   Lscala/Function1;
            4      15     2 unfold_this   Lscala/collection/IterableFactory$Delegate;
           14       5     3 from_it   Lscala/collection/IterableOnce;
    MethodParameters:
      Name                           Flags
      init                           final
      f                              final

  public static java.lang.Object iterate(java.lang.Object, int, scala.Function1);
    descriptor: (Ljava/lang/Object;ILscala/Function1;)Ljava/lang/Object;
    flags: (0x0009) ACC_PUBLIC, ACC_STATIC
    Code:
      stack=5, locals=5, args_size=3
         0: getstatic     #40                 // Field scala/collection/immutable/Iterable$.MODULE$:Lscala/collection/immutable/Iterable$;
         3: astore_3
         4: new           #23                 // class scala/collection/View$Iterate
         7: dup
         8: aload_0
         9: iload_1
        10: aload_2
        11: invokespecial #204                // Method scala/collection/View$Iterate."<init>":(Ljava/lang/Object;ILscala/Function1;)V
        14: astore        4
        16: aload_3
        17: aload         4
        19: invokevirtual #42                 // Method scala/collection/immutable/Iterable$.from:(Lscala/collection/IterableOnce;)Lscala/collection/immutable/Iterable;
        22: areturn
      LineNumberTable:
        line 32: 16
      LocalVariableTable:
        Start  Length  Slot  Name   Signature
            0      23     0 start   Ljava/lang/Object;
            0      23     1   len   I
            0      23     2     f   Lscala/Function1;
            4      18     3 iterate_this   Lscala/collection/IterableFactory$Delegate;
           16       6     4 from_it   Lscala/collection/IterableOnce;
    MethodParameters:
      Name                           Flags
      start                          final
      len                            final
      f                              final

  public static scala.collection.IterableFactory iterableFactory$(scala.collection.immutable.Iterable);
    descriptor: (Lscala/collection/immutable/Iterable;)Lscala/collection/IterableFactory;
    flags: (0x1009) ACC_PUBLIC, ACC_STATIC, ACC_SYNTHETIC
    Code:
      stack=1, locals=1, args_size=1
         0: aload_0
         1: invokespecial #212                // InterfaceMethod iterableFactory:()Lscala/collection/IterableFactory;
         4: areturn
      LineNumberTable:
        line 28: 0
      LocalVariableTable:
        Start  Length  Slot  Name   Signature
            0       5     0 $this   Lscala/collection/immutable/Iterable;
    MethodParameters:
      Name                           Flags
      $this                          final synthetic

  public default scala.collection.IterableFactory<scala.collection.immutable.Iterable> iterableFactory();
    descriptor: ()Lscala/collection/IterableFactory;
    flags: (0x0001) ACC_PUBLIC
    Code:
      stack=1, locals=1, args_size=1
         0: getstatic     #40                 // Field scala/collection/immutable/Iterable$.MODULE$:Lscala/collection/immutable/Iterable$;
         3: areturn
      LineNumberTable:
        line 28: 0
      LocalVariableTable:
        Start  Length  Slot  Name   Signature
            0       4     0  this   Lscala/collection/immutable/Iterable;
    Signature: #214                         // ()Lscala/collection/IterableFactory<Lscala/collection/immutable/Iterable;>;

  public static void $init$(scala.collection.immutable.Iterable);
    descriptor: (Lscala/collection/immutable/Iterable;)V
    flags: (0x0009) ACC_PUBLIC, ACC_STATIC
    Code:
      stack=0, locals=1, args_size=1
         0: return
      LineNumberTable:
        line 24: 0
      LocalVariableTable:
        Start  Length  Slot  Name   Signature
            0       1     0 $this   Lscala/collection/immutable/Iterable;
    MethodParameters:
      Name                           Flags
      $this                          final synthetic

  private static java.lang.Object $deserializeLambda$(java.lang.invoke.SerializedLambda);
    descriptor: (Ljava/lang/invoke/SerializedLambda;)Ljava/lang/Object;
    flags: (0x100a) ACC_PRIVATE, ACC_STATIC, ACC_SYNTHETIC
    Code:
      stack=1, locals=1, args_size=1
         0: aload_0
         1: invokedynamic #229,  0            // InvokeDynamic #8:lambdaDeserialize:(Ljava/lang/invoke/SerializedLambda;)Ljava/lang/Object;
         6: areturn
}
InnerClasses:
  public static final #16= #13 of #15;    // Lookup=class java/lang/invoke/MethodHandles$Lookup of class java/lang/invoke/MethodHandles
  public static #21= #18 of #20;          // Fill=class scala/collection/View$Fill of class scala/collection/View
  public static #24= #23 of #20;          // Iterate=class scala/collection/View$Iterate of class scala/collection/View
  public static #27= #26 of #20;          // Tabulate=class scala/collection/View$Tabulate of class scala/collection/View
  public static #30= #29 of #20;          // Unfold=class scala/collection/View$Unfold of class scala/collection/View
Signature: #3                           // <A:Ljava/lang/Object;>Ljava/lang/Object;Lscala/collection/Iterable<TA;>;
SourceFile: "Iterable.scala"
RuntimeVisibleAnnotations:
  0: #9(#10=s#11)
    scala.reflect.ScalaSignature(
      bytes="\u0006\u0005%4q\u0001C\u0005\u0011\u0002\u0007\u0005\u0001\u0003C\u0003.\u0001\u0011\u0005a\u0006C\u00033\u0001\u0011\u00053gB\u00038\u0013!\u0005\u0001HB\u0003\t\u0013!\u0005\u0011\bC\u0003B\t\u0011\u0005!\tC\u0003D\t\u0011\u0005C\tC\u0004Y\t\u0005\u0005I\u0011B-\u0003\u0011%#XM]1cY\u0016T!AC\u0006\u0002\u0013%lW.\u001e;bE2,\'B\u0001\u0007\u000e\u0003)\u0019w\u000e\u001c7fGRLwN\u001c\u0006\u0002\u001d\u0005)1oY1mC\u000e\u0001QCA\t\u001c\'\u0015\u0001!C\u0006\u0013+!\t\u0019B#D\u0001\u000e\u0013\t)RB\u0001\u0004B]f\u0014VM\u001a\t\u0004/aIR\"A\u0006\n\u0005!Y\u0001C\u0001\u000e\u001c\u0019\u0001!a\u0001\b\u0001\u0005\u0006\u0004i\"!A!\u0012\u0005y\t\u0003CA\n \u0013\t\u0001SBA\u0004O_RD\u0017N\\4\u0011\u0005M\u0011\u0013BA\u0012\u000e\u0005\r\te.\u001f\t\u0006/\u0015Jr%K\u0005\u0003M-\u00111\"\u0013;fe\u0006\u0014G.Z(qgB\u0011\u0001\u0006A\u0007\u0002\u0013A\u0019\u0001\u0006A\r\u0011\t]Y\u0013dJ\u0005\u0003Y-\u0011q#\u0013;fe\u0006\u0014G.\u001a$bGR|\'/\u001f#fM\u0006,H\u000e^:\u0002\r\u0011Jg.\u001b;%)\u0005y\u0003CA\n1\u0013\t\tTB\u0001\u0003V]&$\u0018aD5uKJ\f\'\r\\3GC\u000e$xN]=\u0016\u0003Q\u00022aF\u001b(\u0013\t14BA\bJi\u0016\u0014\u0018M\u00197f\r\u0006\u001cGo\u001c:z\u0003!IE/\u001a:bE2,\u0007C\u0001\u0015\u0005\'\t!!\bE\u0002<}\u001dr!a\u0006\u001f\n\u0005uZ\u0011aD%uKJ\f\'\r\\3GC\u000e$xN]=\n\u0005}\u0002%\u0001\u0003#fY\u0016<\u0017\r^3\u000b\u0005uZ\u0011A\u0002\u001fj]&$h\bF\u00019\u0003\u00111\'o\\7\u0016\u0005\u0015CEC\u0001$K!\rA\u0003a\u0012\t\u00035!#Q!\u0013\u0004C\u0002u\u0011\u0011!\u0012\u0005\u0006\u0017\u001a\u0001\r\u0001T\u0001\u0003SR\u00042!T+H\u001d\tq5K\u0004\u0002P%6\t\u0001K\u0003\u0002R\u001f\u00051AH]8pizJ\u0011AD\u0005\u0003)6\tq\u0001]1dW\u0006<W-\u0003\u0002W/\na\u0011\n^3sC\ndWm\u00148dK*\u0011A+D\u0001\roJLG/\u001a*fa2\f7-\u001a\u000b\u00025B\u00111\fY\u0007\u00029*\u0011QLX\u0001\u0005Y\u0006twMC\u0001`\u0003\u0011Q\u0017M^1\n\u0005\u0005d&AB(cU\u0016\u001cG\u000f\u000b\u0003\u0005G\u001a<\u0007CA\ne\u0013\t)WB\u0001\tTKJL\u0017\r\u001c,feNLwN\\+J\t\u0006)a/\u00197vKz\t1\u0001\u000b\u0003\u0004G\u001a<\u0007"
    )
BootstrapMethods:
  0: #79 REF_invokeStatic java/lang/invoke/LambdaMetafactory.altMetafactory:(Ljava/lang/invoke/MethodHandles$Lookup;Ljava/lang/String;Ljava/lang/invoke/MethodType;[Ljava/lang/Object;)Ljava/lang/invoke/CallSite;
    Method arguments:
      #64 (Ljava/lang/Object;)Ljava/lang/Object;
      #71 REF_invokeStatic scala/collection/IterableFactory.$anonfun$tabulate$7$adapted:(Lscala/collection/IterableFactory;IIIILscala/Function5;Ljava/lang/Object;)Ljava/lang/Object;
      #64 (Ljava/lang/Object;)Ljava/lang/Object;
      #72 1
  1: #79 REF_invokeStatic java/lang/invoke/LambdaMetafactory.altMetafactory:(Ljava/lang/invoke/MethodHandles$Lookup;Ljava/lang/String;Ljava/lang/invoke/MethodType;[Ljava/lang/Object;)Ljava/lang/invoke/CallSite;
    Method arguments:
      #64 (Ljava/lang/Object;)Ljava/lang/Object;
      #95 REF_invokeStatic scala/collection/IterableFactory.$anonfun$tabulate$5$adapted:(Lscala/collection/IterableFactory;IIILscala/Function4;Ljava/lang/Object;)Ljava/lang/Object;
      #64 (Ljava/lang/Object;)Ljava/lang/Object;
      #72 1
  2: #79 REF_invokeStatic java/lang/invoke/LambdaMetafactory.altMetafactory:(Ljava/lang/invoke/MethodHandles$Lookup;Ljava/lang/String;Ljava/lang/invoke/MethodType;[Ljava/lang/Object;)Ljava/lang/invoke/CallSite;
    Method arguments:
      #64 (Ljava/lang/Object;)Ljava/lang/Object;
      #105 REF_invokeStatic scala/collection/IterableFactory.$anonfun$tabulate$3$adapted:(Lscala/collection/IterableFactory;IILscala/Function3;Ljava/lang/Object;)Ljava/lang/Object;
      #64 (Ljava/lang/Object;)Ljava/lang/Object;
      #72 1
  3: #79 REF_invokeStatic java/lang/invoke/LambdaMetafactory.altMetafactory:(Ljava/lang/invoke/MethodHandles$Lookup;Ljava/lang/String;Ljava/lang/invoke/MethodType;[Ljava/lang/Object;)Ljava/lang/invoke/CallSite;
    Method arguments:
      #64 (Ljava/lang/Object;)Ljava/lang/Object;
      #115 REF_invokeStatic scala/collection/IterableFactory.$anonfun$tabulate$1$adapted:(Lscala/collection/IterableFactory;ILscala/Function2;Ljava/lang/Object;)Ljava/lang/Object;
      #64 (Ljava/lang/Object;)Ljava/lang/Object;
      #72 1
  4: #79 REF_invokeStatic java/lang/invoke/LambdaMetafactory.altMetafactory:(Ljava/lang/invoke/MethodHandles$Lookup;Ljava/lang/String;Ljava/lang/invoke/MethodType;[Ljava/lang/Object;)Ljava/lang/invoke/CallSite;
    Method arguments:
      #131 ()Ljava/lang/Object;
      #136 REF_invokeStatic scala/collection/IterableFactory.$anonfun$fill$4:(Lscala/collection/IterableFactory;IIIILscala/Function0;)Ljava/lang/Object;
      #131 ()Ljava/lang/Object;
      #72 1
  5: #79 REF_invokeStatic java/lang/invoke/LambdaMetafactory.altMetafactory:(Ljava/lang/invoke/MethodHandles$Lookup;Ljava/lang/String;Ljava/lang/invoke/MethodType;[Ljava/lang/Object;)Ljava/lang/invoke/CallSite;
    Method arguments:
      #131 ()Ljava/lang/Object;
      #150 REF_invokeStatic scala/collection/IterableFactory.$anonfun$fill$3:(Lscala/collection/IterableFactory;IIILscala/Function0;)Ljava/lang/Object;
      #131 ()Ljava/lang/Object;
      #72 1
  6: #79 REF_invokeStatic java/lang/invoke/LambdaMetafactory.altMetafactory:(Ljava/lang/invoke/MethodHandles$Lookup;Ljava/lang/String;Ljava/lang/invoke/MethodType;[Ljava/lang/Object;)Ljava/lang/invoke/CallSite;
    Method arguments:
      #131 ()Ljava/lang/Object;
      #159 REF_invokeStatic scala/collection/IterableFactory.$anonfun$fill$2:(Lscala/collection/IterableFactory;IILscala/Function0;)Ljava/lang/Object;
      #131 ()Ljava/lang/Object;
      #72 1
  7: #79 REF_invokeStatic java/lang/invoke/LambdaMetafactory.altMetafactory:(Ljava/lang/invoke/MethodHandles$Lookup;Ljava/lang/String;Ljava/lang/invoke/MethodType;[Ljava/lang/Object;)Ljava/lang/invoke/CallSite;
    Method arguments:
      #131 ()Ljava/lang/Object;
      #168 REF_invokeStatic scala/collection/IterableFactory.$anonfun$fill$1:(Lscala/collection/IterableFactory;ILscala/Function0;)Ljava/lang/Object;
      #131 ()Ljava/lang/Object;
      #72 1
  8: #226 REF_invokeStatic scala/runtime/LambdaDeserialize.bootstrap:(Ljava/lang/invoke/MethodHandles$Lookup;Ljava/lang/String;Ljava/lang/invoke/MethodType;[Ljava/lang/invoke/MethodHandle;)Ljava/lang/invoke/CallSite;
    Method arguments:
      #168 REF_invokeStatic scala/collection/IterableFactory.$anonfun$fill$1:(Lscala/collection/IterableFactory;ILscala/Function0;)Ljava/lang/Object;
      #159 REF_invokeStatic scala/collection/IterableFactory.$anonfun$fill$2:(Lscala/collection/IterableFactory;IILscala/Function0;)Ljava/lang/Object;
      #150 REF_invokeStatic scala/collection/IterableFactory.$anonfun$fill$3:(Lscala/collection/IterableFactory;IIILscala/Function0;)Ljava/lang/Object;
      #136 REF_invokeStatic scala/collection/IterableFactory.$anonfun$fill$4:(Lscala/collection/IterableFactory;IIIILscala/Function0;)Ljava/lang/Object;
      #115 REF_invokeStatic scala/collection/IterableFactory.$anonfun$tabulate$1$adapted:(Lscala/collection/IterableFactory;ILscala/Function2;Ljava/lang/Object;)Ljava/lang/Object;
      #105 REF_invokeStatic scala/collection/IterableFactory.$anonfun$tabulate$3$adapted:(Lscala/collection/IterableFactory;IILscala/Function3;Ljava/lang/Object;)Ljava/lang/Object;
      #95 REF_invokeStatic scala/collection/IterableFactory.$anonfun$tabulate$5$adapted:(Lscala/collection/IterableFactory;IIILscala/Function4;Ljava/lang/Object;)Ljava/lang/Object;
      #71 REF_invokeStatic scala/collection/IterableFactory.$anonfun$tabulate$7$adapted:(Lscala/collection/IterableFactory;IIIILscala/Function5;Ljava/lang/Object;)Ljava/lang/Object;
  ScalaInlineInfo: length = 0x13 (unknown attribute)
   01 00 00 03 00 D8 00 D9 01 00 D1 00 D2 00 00 CE
   00 CF 01
  ScalaSig: length = 0x3 (unknown attribute)
   05 02 00
