Classfile /Users/mw/Projects/slang-braindump/.jar/jar8/assemble/slang-braindump/assemble/content/scala/collection/immutable/LazyList$.class
  Last modified May 29, 2022; size 28103 bytes
  SHA-256 checksum 9badd7463a19c40df1351df966e6138ace54b0f5c338b03d7b429c0deb9a2455
  Compiled from "LazyList.scala"
public final class scala.collection.immutable.LazyList$ extends java.lang.Object implements scala.collection.SeqFactory<scala.collection.immutable.LazyList>
  minor version: 0
  major version: 52
  flags: (0x0031) ACC_PUBLIC, ACC_FINAL, ACC_SUPER
  this_class: #2                          // scala/collection/immutable/LazyList$
  super_class: #5                         // java/lang/Object
  interfaces: 1, fields: 4, methods: 71, attributes: 6
Constant pool:
    #1 = Utf8               scala/collection/immutable/LazyList$
    #2 = Class              #1            // scala/collection/immutable/LazyList$
    #3 = Utf8               Ljava/lang/Object;Lscala/collection/SeqFactory<Lscala/collection/immutable/LazyList;>;
    #4 = Utf8               java/lang/Object
    #5 = Class              #4            // java/lang/Object
    #6 = Utf8               scala/collection/SeqFactory
    #7 = Class              #6            // scala/collection/SeqFactory
    #8 = Utf8               LazyList.scala
    #9 = Utf8               java/lang/invoke/MethodHandles$Lookup
   #10 = Class              #9            // java/lang/invoke/MethodHandles$Lookup
   #11 = Utf8               java/lang/invoke/MethodHandles
   #12 = Class              #11           // java/lang/invoke/MethodHandles
   #13 = Utf8               Lookup
   #14 = Utf8               scala/collection/immutable/LazyList$LazyBuilder
   #15 = Class              #14           // scala/collection/immutable/LazyList$LazyBuilder
   #16 = Utf8               scala/collection/immutable/LazyList
   #17 = Class              #16           // scala/collection/immutable/LazyList
   #18 = Utf8               LazyBuilder
   #19 = Utf8               scala/collection/immutable/LazyList$State
   #20 = Class              #19           // scala/collection/immutable/LazyList$State
   #21 = Utf8               State
   #22 = Utf8               scala/collection/immutable/LazyList$State$
   #23 = Class              #22           // scala/collection/immutable/LazyList$State$
   #24 = Utf8               State$
   #25 = Utf8               scala/collection/immutable/LazyList$State$Cons
   #26 = Class              #25           // scala/collection/immutable/LazyList$State$Cons
   #27 = Utf8               Cons
   #28 = Utf8               scala/collection/immutable/LazyList$State$Empty$
   #29 = Class              #28           // scala/collection/immutable/LazyList$State$Empty$
   #30 = Utf8               Empty$
   #31 = Utf8               MODULE$
   #32 = Utf8               Lscala/collection/immutable/LazyList$;
   #33 = Utf8               serialVersionUID
   #34 = Utf8               J
   #35 = Long               3l
   #37 = Utf8               _empty
   #38 = Utf8               Lscala/collection/immutable/LazyList;
   #39 = Utf8               Lscala/collection/immutable/LazyList<Lscala/runtime/Nothing$;>;
   #40 = Utf8               scala$collection$immutable$LazyList$$anyToMarker
   #41 = Utf8               Lscala/Function1;
   #42 = Utf8               Lscala/Function1<Ljava/lang/Object;Ljava/lang/Object;>;
   #43 = Utf8               <clinit>
   #44 = Utf8               ()V
   #45 = Utf8               <init>
   #46 = NameAndType        #45:#44       // "<init>":()V
   #47 = Methodref          #2.#46        // scala/collection/immutable/LazyList$."<init>":()V
   #48 = NameAndType        #31:#32       // MODULE$:Lscala/collection/immutable/LazyList$;
   #49 = Fieldref           #2.#48        // scala/collection/immutable/LazyList$.MODULE$:Lscala/collection/immutable/LazyList$;
   #50 = Utf8               ()Ljava/lang/Object;
   #51 = MethodType         #50           //  ()Ljava/lang/Object;
   #52 = Utf8               $anonfun$_empty$1
   #53 = Utf8               ()Lscala/collection/immutable/LazyList$State$Empty$;
   #54 = NameAndType        #52:#53       // $anonfun$_empty$1:()Lscala/collection/immutable/LazyList$State$Empty$;
   #55 = Methodref          #2.#54        // scala/collection/immutable/LazyList$.$anonfun$_empty$1:()Lscala/collection/immutable/LazyList$State$Empty$;
   #56 = MethodHandle       6:#55         // REF_invokeStatic scala/collection/immutable/LazyList$.$anonfun$_empty$1:()Lscala/collection/immutable/LazyList$State$Empty$;
   #57 = MethodType         #53           //  ()Lscala/collection/immutable/LazyList$State$Empty$;
   #58 = Integer            5
   #59 = Integer            1
   #60 = Utf8               java/lang/invoke/LambdaMetafactory
   #61 = Class              #60           // java/lang/invoke/LambdaMetafactory
   #62 = Utf8               altMetafactory
   #63 = Utf8               (Ljava/lang/invoke/MethodHandles$Lookup;Ljava/lang/String;Ljava/lang/invoke/MethodType;[Ljava/lang/Object;)Ljava/lang/invoke/CallSite;
   #64 = NameAndType        #62:#63       // altMetafactory:(Ljava/lang/invoke/MethodHandles$Lookup;Ljava/lang/String;Ljava/lang/invoke/MethodType;[Ljava/lang/Object;)Ljava/lang/invoke/CallSite;
   #65 = Methodref          #61.#64       // java/lang/invoke/LambdaMetafactory.altMetafactory:(Ljava/lang/invoke/MethodHandles$Lookup;Ljava/lang/String;Ljava/lang/invoke/MethodType;[Ljava/lang/Object;)Ljava/lang/invoke/CallSite;
   #66 = MethodHandle       6:#65         // REF_invokeStatic java/lang/invoke/LambdaMetafactory.altMetafactory:(Ljava/lang/invoke/MethodHandles$Lookup;Ljava/lang/String;Ljava/lang/invoke/MethodType;[Ljava/lang/Object;)Ljava/lang/invoke/CallSite;
   #67 = Utf8               apply
   #68 = Utf8               ()Lscala/Function0;
   #69 = NameAndType        #67:#68       // apply:()Lscala/Function0;
   #70 = InvokeDynamic      #0:#69        // #0:apply:()Lscala/Function0;
   #71 = Utf8               (Lscala/Function0;)V
   #72 = NameAndType        #45:#71       // "<init>":(Lscala/Function0;)V
   #73 = Methodref          #17.#72       // scala/collection/immutable/LazyList."<init>":(Lscala/Function0;)V
   #74 = Utf8               force
   #75 = Utf8               ()Lscala/collection/immutable/LazyList;
   #76 = NameAndType        #74:#75       // force:()Lscala/collection/immutable/LazyList;
   #77 = Methodref          #17.#76       // scala/collection/immutable/LazyList.force:()Lscala/collection/immutable/LazyList;
   #78 = NameAndType        #37:#38       // _empty:Lscala/collection/immutable/LazyList;
   #79 = Fieldref           #2.#78        // scala/collection/immutable/LazyList$._empty:Lscala/collection/immutable/LazyList;
   #80 = Utf8               (Ljava/lang/Object;)Ljava/lang/Object;
   #81 = MethodType         #80           //  (Ljava/lang/Object;)Ljava/lang/Object;
   #82 = Utf8               $anonfun$anyToMarker$1
   #83 = NameAndType        #82:#80       // $anonfun$anyToMarker$1:(Ljava/lang/Object;)Ljava/lang/Object;
   #84 = Methodref          #2.#83        // scala/collection/immutable/LazyList$.$anonfun$anyToMarker$1:(Ljava/lang/Object;)Ljava/lang/Object;
   #85 = MethodHandle       6:#84         // REF_invokeStatic scala/collection/immutable/LazyList$.$anonfun$anyToMarker$1:(Ljava/lang/Object;)Ljava/lang/Object;
   #86 = Utf8               ()Lscala/Function1;
   #87 = NameAndType        #67:#86       // apply:()Lscala/Function1;
   #88 = InvokeDynamic      #1:#87        // #1:apply:()Lscala/Function1;
   #89 = NameAndType        #40:#41       // scala$collection$immutable$LazyList$$anyToMarker:Lscala/Function1;
   #90 = Fieldref           #2.#89        // scala/collection/immutable/LazyList$.scala$collection$immutable$LazyList$$anyToMarker:Lscala/Function1;
   #91 = Utf8               scala$collection$immutable$LazyList$$newLL_state
   #92 = Utf8               Lscala/Function0;
   #93 = Utf8               unapplySeq
   #94 = Utf8               (Lscala/collection/SeqOps;)Lscala/collection/SeqOps;
   #95 = Utf8               x
   #96 = Utf8               unapplySeq$
   #97 = Utf8               (Lscala/collection/SeqFactory;Lscala/collection/SeqOps;)Lscala/collection/SeqOps;
   #98 = NameAndType        #96:#97       // unapplySeq$:(Lscala/collection/SeqFactory;Lscala/collection/SeqOps;)Lscala/collection/SeqOps;
   #99 = InterfaceMethodref #7.#98        // scala/collection/SeqFactory.unapplySeq$:(Lscala/collection/SeqFactory;Lscala/collection/SeqOps;)Lscala/collection/SeqOps;
  #100 = Utf8               this
  #101 = Utf8               Lscala/collection/SeqOps;
  #102 = Utf8               (Lscala/collection/immutable/Seq;)Ljava/lang/Object;
  #103 = Utf8               elems
  #104 = Utf8               scala/collection/IterableFactory
  #105 = Class              #104          // scala/collection/IterableFactory
  #106 = Utf8               apply$
  #107 = Utf8               (Lscala/collection/IterableFactory;Lscala/collection/immutable/Seq;)Ljava/lang/Object;
  #108 = NameAndType        #106:#107     // apply$:(Lscala/collection/IterableFactory;Lscala/collection/immutable/Seq;)Ljava/lang/Object;
  #109 = InterfaceMethodref #105.#108     // scala/collection/IterableFactory.apply$:(Lscala/collection/IterableFactory;Lscala/collection/immutable/Seq;)Ljava/lang/Object;
  #110 = Utf8               Lscala/collection/immutable/Seq;
  #111 = Utf8               iterate
  #112 = Utf8               (Ljava/lang/Object;ILscala/Function1;)Ljava/lang/Object;
  #113 = Utf8               start
  #114 = Utf8               len
  #115 = Utf8               f
  #116 = Utf8               iterate$
  #117 = Utf8               (Lscala/collection/IterableFactory;Ljava/lang/Object;ILscala/Function1;)Ljava/lang/Object;
  #118 = NameAndType        #116:#117     // iterate$:(Lscala/collection/IterableFactory;Ljava/lang/Object;ILscala/Function1;)Ljava/lang/Object;
  #119 = InterfaceMethodref #105.#118     // scala/collection/IterableFactory.iterate$:(Lscala/collection/IterableFactory;Ljava/lang/Object;ILscala/Function1;)Ljava/lang/Object;
  #120 = Utf8               Ljava/lang/Object;
  #121 = Utf8               I
  #122 = Utf8               range
  #123 = Utf8               (Ljava/lang/Object;Ljava/lang/Object;Lscala/math/Integral;)Ljava/lang/Object;
  #124 = Utf8               end
  #125 = Utf8               evidence$3
  #126 = Utf8               range$
  #127 = Utf8               (Lscala/collection/IterableFactory;Ljava/lang/Object;Ljava/lang/Object;Lscala/math/Integral;)Ljava/lang/Object;
  #128 = NameAndType        #126:#127     // range$:(Lscala/collection/IterableFactory;Ljava/lang/Object;Ljava/lang/Object;Lscala/math/Integral;)Ljava/lang/Object;
  #129 = InterfaceMethodref #105.#128     // scala/collection/IterableFactory.range$:(Lscala/collection/IterableFactory;Ljava/lang/Object;Ljava/lang/Object;Lscala/math/Integral;)Ljava/lang/Object;
  #130 = Utf8               Lscala/math/Integral;
  #131 = Utf8               (Ljava/lang/Object;Ljava/lang/Object;Ljava/lang/Object;Lscala/math/Integral;)Ljava/lang/Object;
  #132 = Utf8               step
  #133 = Utf8               evidence$4
  #134 = Utf8               (Lscala/collection/IterableFactory;Ljava/lang/Object;Ljava/lang/Object;Ljava/lang/Object;Lscala/math/Integral;)Ljava/lang/Object;
  #135 = NameAndType        #126:#134     // range$:(Lscala/collection/IterableFactory;Ljava/lang/Object;Ljava/lang/Object;Ljava/lang/Object;Lscala/math/Integral;)Ljava/lang/Object;
  #136 = InterfaceMethodref #105.#135     // scala/collection/IterableFactory.range$:(Lscala/collection/IterableFactory;Ljava/lang/Object;Ljava/lang/Object;Ljava/lang/Object;Lscala/math/Integral;)Ljava/lang/Object;
  #137 = Utf8               fill
  #138 = Utf8               (IILscala/Function0;)Ljava/lang/Object;
  #139 = Utf8               n1
  #140 = Utf8               n2
  #141 = Utf8               elem
  #142 = Utf8               fill$
  #143 = Utf8               (Lscala/collection/IterableFactory;IILscala/Function0;)Ljava/lang/Object;
  #144 = NameAndType        #142:#143     // fill$:(Lscala/collection/IterableFactory;IILscala/Function0;)Ljava/lang/Object;
  #145 = InterfaceMethodref #105.#144     // scala/collection/IterableFactory.fill$:(Lscala/collection/IterableFactory;IILscala/Function0;)Ljava/lang/Object;
  #146 = Utf8               (IIILscala/Function0;)Ljava/lang/Object;
  #147 = Utf8               n3
  #148 = Utf8               (Lscala/collection/IterableFactory;IIILscala/Function0;)Ljava/lang/Object;
  #149 = NameAndType        #142:#148     // fill$:(Lscala/collection/IterableFactory;IIILscala/Function0;)Ljava/lang/Object;
  #150 = InterfaceMethodref #105.#149     // scala/collection/IterableFactory.fill$:(Lscala/collection/IterableFactory;IIILscala/Function0;)Ljava/lang/Object;
  #151 = Utf8               (IIIILscala/Function0;)Ljava/lang/Object;
  #152 = Utf8               n4
  #153 = Utf8               (Lscala/collection/IterableFactory;IIIILscala/Function0;)Ljava/lang/Object;
  #154 = NameAndType        #142:#153     // fill$:(Lscala/collection/IterableFactory;IIIILscala/Function0;)Ljava/lang/Object;
  #155 = InterfaceMethodref #105.#154     // scala/collection/IterableFactory.fill$:(Lscala/collection/IterableFactory;IIIILscala/Function0;)Ljava/lang/Object;
  #156 = Utf8               (IIIIILscala/Function0;)Ljava/lang/Object;
  #157 = Utf8               n5
  #158 = Utf8               (Lscala/collection/IterableFactory;IIIIILscala/Function0;)Ljava/lang/Object;
  #159 = NameAndType        #142:#158     // fill$:(Lscala/collection/IterableFactory;IIIIILscala/Function0;)Ljava/lang/Object;
  #160 = InterfaceMethodref #105.#159     // scala/collection/IterableFactory.fill$:(Lscala/collection/IterableFactory;IIIIILscala/Function0;)Ljava/lang/Object;
  #161 = Utf8               tabulate
  #162 = Utf8               (IILscala/Function2;)Ljava/lang/Object;
  #163 = Utf8               tabulate$
  #164 = Utf8               (Lscala/collection/IterableFactory;IILscala/Function2;)Ljava/lang/Object;
  #165 = NameAndType        #163:#164     // tabulate$:(Lscala/collection/IterableFactory;IILscala/Function2;)Ljava/lang/Object;
  #166 = InterfaceMethodref #105.#165     // scala/collection/IterableFactory.tabulate$:(Lscala/collection/IterableFactory;IILscala/Function2;)Ljava/lang/Object;
  #167 = Utf8               Lscala/Function2;
  #168 = Utf8               (IIILscala/Function3;)Ljava/lang/Object;
  #169 = Utf8               (Lscala/collection/IterableFactory;IIILscala/Function3;)Ljava/lang/Object;
  #170 = NameAndType        #163:#169     // tabulate$:(Lscala/collection/IterableFactory;IIILscala/Function3;)Ljava/lang/Object;
  #171 = InterfaceMethodref #105.#170     // scala/collection/IterableFactory.tabulate$:(Lscala/collection/IterableFactory;IIILscala/Function3;)Ljava/lang/Object;
  #172 = Utf8               Lscala/Function3;
  #173 = Utf8               (IIIILscala/Function4;)Ljava/lang/Object;
  #174 = Utf8               (Lscala/collection/IterableFactory;IIIILscala/Function4;)Ljava/lang/Object;
  #175 = NameAndType        #163:#174     // tabulate$:(Lscala/collection/IterableFactory;IIIILscala/Function4;)Ljava/lang/Object;
  #176 = InterfaceMethodref #105.#175     // scala/collection/IterableFactory.tabulate$:(Lscala/collection/IterableFactory;IIIILscala/Function4;)Ljava/lang/Object;
  #177 = Utf8               Lscala/Function4;
  #178 = Utf8               (IIIIILscala/Function5;)Ljava/lang/Object;
  #179 = Utf8               (Lscala/collection/IterableFactory;IIIIILscala/Function5;)Ljava/lang/Object;
  #180 = NameAndType        #163:#179     // tabulate$:(Lscala/collection/IterableFactory;IIIIILscala/Function5;)Ljava/lang/Object;
  #181 = InterfaceMethodref #105.#180     // scala/collection/IterableFactory.tabulate$:(Lscala/collection/IterableFactory;IIIIILscala/Function5;)Ljava/lang/Object;
  #182 = Utf8               Lscala/Function5;
  #183 = Utf8               iterableFactory
  #184 = Utf8               ()Lscala/collection/Factory;
  #185 = Utf8               <A:Ljava/lang/Object;>()Lscala/collection/Factory<TA;Lscala/collection/immutable/LazyList<TA;>;>;
  #186 = Utf8               iterableFactory$
  #187 = Utf8               (Lscala/collection/IterableFactory;)Lscala/collection/Factory;
  #188 = NameAndType        #186:#187     // iterableFactory$:(Lscala/collection/IterableFactory;)Lscala/collection/Factory;
  #189 = InterfaceMethodref #105.#188     // scala/collection/IterableFactory.iterableFactory$:(Lscala/collection/IterableFactory;)Lscala/collection/Factory;
  #190 = Utf8               scala$collection$immutable$LazyList$$newLL
  #191 = Utf8               (Lscala/Function0;)Lscala/collection/immutable/LazyList;
  #192 = Utf8               <A:Ljava/lang/Object;>(Lscala/Function0<Lscala/collection/immutable/LazyList$State<TA;>;>;)Lscala/collection/immutable/LazyList<TA;>;
  #193 = Utf8               state
  #194 = Utf8               scala$collection$immutable$LazyList$$sCons
  #195 = Utf8               (Ljava/lang/Object;Lscala/collection/immutable/LazyList;)Lscala/collection/immutable/LazyList$State;
  #196 = Utf8               <A:Ljava/lang/Object;>(TA;Lscala/collection/immutable/LazyList<TA;>;)Lscala/collection/immutable/LazyList$State<TA;>;
  #197 = Utf8               hd
  #198 = Utf8               tl
  #199 = Utf8               (Ljava/lang/Object;Lscala/collection/immutable/LazyList;)V
  #200 = NameAndType        #45:#199      // "<init>":(Ljava/lang/Object;Lscala/collection/immutable/LazyList;)V
  #201 = Methodref          #26.#200      // scala/collection/immutable/LazyList$State$Cons."<init>":(Ljava/lang/Object;Lscala/collection/immutable/LazyList;)V
  #202 = Utf8               ()Lscala/Function1<Ljava/lang/Object;Ljava/lang/Object;>;
  #203 = Utf8               scala$collection$immutable$LazyList$$filterImpl
  #204 = Utf8               (Lscala/collection/immutable/LazyList;Lscala/Function1;Z)Lscala/collection/immutable/LazyList;
  #205 = Utf8               <A:Ljava/lang/Object;>(Lscala/collection/immutable/LazyList<TA;>;Lscala/Function1<TA;Ljava/lang/Object;>;Z)Lscala/collection/immutable/LazyList<TA;>;
  #206 = Utf8               ll
  #207 = Utf8               p
  #208 = Utf8               isFlipped
  #209 = Utf8               scala/runtime/ObjectRef
  #210 = Class              #209          // scala/runtime/ObjectRef
  #211 = Utf8               (Ljava/lang/Object;)V
  #212 = NameAndType        #45:#211      // "<init>":(Ljava/lang/Object;)V
  #213 = Methodref          #210.#212     // scala/runtime/ObjectRef."<init>":(Ljava/lang/Object;)V
  #214 = Utf8               $anonfun$filterImpl$1
  #215 = Utf8               (Lscala/runtime/ObjectRef;Lscala/Function1;Z)Lscala/collection/immutable/LazyList$State;
  #216 = NameAndType        #214:#215     // $anonfun$filterImpl$1:(Lscala/runtime/ObjectRef;Lscala/Function1;Z)Lscala/collection/immutable/LazyList$State;
  #217 = Methodref          #2.#216       // scala/collection/immutable/LazyList$.$anonfun$filterImpl$1:(Lscala/runtime/ObjectRef;Lscala/Function1;Z)Lscala/collection/immutable/LazyList$State;
  #218 = MethodHandle       6:#217        // REF_invokeStatic scala/collection/immutable/LazyList$.$anonfun$filterImpl$1:(Lscala/runtime/ObjectRef;Lscala/Function1;Z)Lscala/collection/immutable/LazyList$State;
  #219 = Utf8               ()Lscala/collection/immutable/LazyList$State;
  #220 = MethodType         #219          //  ()Lscala/collection/immutable/LazyList$State;
  #221 = Utf8               (Lscala/runtime/ObjectRef;Lscala/Function1;Z)Lscala/Function0;
  #222 = NameAndType        #67:#221      // apply:(Lscala/runtime/ObjectRef;Lscala/Function1;Z)Lscala/Function0;
  #223 = InvokeDynamic      #2:#222       // #2:apply:(Lscala/runtime/ObjectRef;Lscala/Function1;Z)Lscala/Function0;
  #224 = Utf8               Z
  #225 = Utf8               scala$collection$immutable$LazyList$$collectImpl
  #226 = Utf8               (Lscala/collection/immutable/LazyList;Lscala/PartialFunction;)Lscala/collection/immutable/LazyList;
  #227 = Utf8               <A:Ljava/lang/Object;B:Ljava/lang/Object;>(Lscala/collection/immutable/LazyList<TA;>;Lscala/PartialFunction<TA;TB;>;)Lscala/collection/immutable/LazyList<TB;>;
  #228 = Utf8               pf
  #229 = Utf8               $anonfun$collectImpl$1
  #230 = Utf8               (Lscala/runtime/ObjectRef;Lscala/PartialFunction;)Lscala/collection/immutable/LazyList$State;
  #231 = NameAndType        #229:#230     // $anonfun$collectImpl$1:(Lscala/runtime/ObjectRef;Lscala/PartialFunction;)Lscala/collection/immutable/LazyList$State;
  #232 = Methodref          #2.#231       // scala/collection/immutable/LazyList$.$anonfun$collectImpl$1:(Lscala/runtime/ObjectRef;Lscala/PartialFunction;)Lscala/collection/immutable/LazyList$State;
  #233 = MethodHandle       6:#232        // REF_invokeStatic scala/collection/immutable/LazyList$.$anonfun$collectImpl$1:(Lscala/runtime/ObjectRef;Lscala/PartialFunction;)Lscala/collection/immutable/LazyList$State;
  #234 = Utf8               (Lscala/runtime/ObjectRef;Lscala/PartialFunction;)Lscala/Function0;
  #235 = NameAndType        #67:#234      // apply:(Lscala/runtime/ObjectRef;Lscala/PartialFunction;)Lscala/Function0;
  #236 = InvokeDynamic      #3:#235       // #3:apply:(Lscala/runtime/ObjectRef;Lscala/PartialFunction;)Lscala/Function0;
  #237 = Utf8               Lscala/PartialFunction;
  #238 = Utf8               scala$collection$immutable$LazyList$$flatMapImpl
  #239 = Utf8               (Lscala/collection/immutable/LazyList;Lscala/Function1;)Lscala/collection/immutable/LazyList;
  #240 = Utf8               <A:Ljava/lang/Object;B:Ljava/lang/Object;>(Lscala/collection/immutable/LazyList<TA;>;Lscala/Function1<TA;Lscala/collection/IterableOnce<TB;>;>;)Lscala/collection/immutable/LazyList<TB;>;
  #241 = Utf8               $anonfun$flatMapImpl$1
  #242 = Utf8               (Lscala/runtime/ObjectRef;Lscala/Function1;)Lscala/collection/immutable/LazyList$State;
  #243 = NameAndType        #241:#242     // $anonfun$flatMapImpl$1:(Lscala/runtime/ObjectRef;Lscala/Function1;)Lscala/collection/immutable/LazyList$State;
  #244 = Methodref          #2.#243       // scala/collection/immutable/LazyList$.$anonfun$flatMapImpl$1:(Lscala/runtime/ObjectRef;Lscala/Function1;)Lscala/collection/immutable/LazyList$State;
  #245 = MethodHandle       6:#244        // REF_invokeStatic scala/collection/immutable/LazyList$.$anonfun$flatMapImpl$1:(Lscala/runtime/ObjectRef;Lscala/Function1;)Lscala/collection/immutable/LazyList$State;
  #246 = Utf8               (Lscala/runtime/ObjectRef;Lscala/Function1;)Lscala/Function0;
  #247 = NameAndType        #67:#246      // apply:(Lscala/runtime/ObjectRef;Lscala/Function1;)Lscala/Function0;
  #248 = InvokeDynamic      #4:#247       // #4:apply:(Lscala/runtime/ObjectRef;Lscala/Function1;)Lscala/Function0;
  #249 = Utf8               scala$collection$immutable$LazyList$$dropImpl
  #250 = Utf8               (Lscala/collection/immutable/LazyList;I)Lscala/collection/immutable/LazyList;
  #251 = Utf8               <A:Ljava/lang/Object;>(Lscala/collection/immutable/LazyList<TA;>;I)Lscala/collection/immutable/LazyList<TA;>;
  #252 = Utf8               n
  #253 = Utf8               scala/runtime/IntRef
  #254 = Class              #253          // scala/runtime/IntRef
  #255 = Utf8               (I)V
  #256 = NameAndType        #45:#255      // "<init>":(I)V
  #257 = Methodref          #254.#256     // scala/runtime/IntRef."<init>":(I)V
  #258 = Utf8               $anonfun$dropImpl$1
  #259 = Utf8               (Lscala/runtime/ObjectRef;Lscala/runtime/IntRef;)Lscala/collection/immutable/LazyList$State;
  #260 = NameAndType        #258:#259     // $anonfun$dropImpl$1:(Lscala/runtime/ObjectRef;Lscala/runtime/IntRef;)Lscala/collection/immutable/LazyList$State;
  #261 = Methodref          #2.#260       // scala/collection/immutable/LazyList$.$anonfun$dropImpl$1:(Lscala/runtime/ObjectRef;Lscala/runtime/IntRef;)Lscala/collection/immutable/LazyList$State;
  #262 = MethodHandle       6:#261        // REF_invokeStatic scala/collection/immutable/LazyList$.$anonfun$dropImpl$1:(Lscala/runtime/ObjectRef;Lscala/runtime/IntRef;)Lscala/collection/immutable/LazyList$State;
  #263 = Utf8               (Lscala/runtime/ObjectRef;Lscala/runtime/IntRef;)Lscala/Function0;
  #264 = NameAndType        #67:#263      // apply:(Lscala/runtime/ObjectRef;Lscala/runtime/IntRef;)Lscala/Function0;
  #265 = InvokeDynamic      #5:#264       // #5:apply:(Lscala/runtime/ObjectRef;Lscala/runtime/IntRef;)Lscala/Function0;
  #266 = Utf8               restRef
  #267 = Utf8               Lscala/runtime/ObjectRef;
  #268 = Utf8               iRef
  #269 = Utf8               Lscala/runtime/IntRef;
  #270 = Utf8               scala$collection$immutable$LazyList$$dropWhileImpl
  #271 = Utf8               <A:Ljava/lang/Object;>(Lscala/collection/immutable/LazyList<TA;>;Lscala/Function1<TA;Ljava/lang/Object;>;)Lscala/collection/immutable/LazyList<TA;>;
  #272 = Utf8               $anonfun$dropWhileImpl$1
  #273 = NameAndType        #272:#242     // $anonfun$dropWhileImpl$1:(Lscala/runtime/ObjectRef;Lscala/Function1;)Lscala/collection/immutable/LazyList$State;
  #274 = Methodref          #2.#273       // scala/collection/immutable/LazyList$.$anonfun$dropWhileImpl$1:(Lscala/runtime/ObjectRef;Lscala/Function1;)Lscala/collection/immutable/LazyList$State;
  #275 = MethodHandle       6:#274        // REF_invokeStatic scala/collection/immutable/LazyList$.$anonfun$dropWhileImpl$1:(Lscala/runtime/ObjectRef;Lscala/Function1;)Lscala/collection/immutable/LazyList$State;
  #276 = InvokeDynamic      #6:#247       // #6:apply:(Lscala/runtime/ObjectRef;Lscala/Function1;)Lscala/Function0;
  #277 = Utf8               scala$collection$immutable$LazyList$$takeRightImpl
  #278 = Utf8               $anonfun$takeRightImpl$1
  #279 = Utf8               (Lscala/runtime/ObjectRef;Lscala/runtime/IntRef;Lscala/runtime/ObjectRef;)Lscala/collection/immutable/LazyList$State;
  #280 = NameAndType        #278:#279     // $anonfun$takeRightImpl$1:(Lscala/runtime/ObjectRef;Lscala/runtime/IntRef;Lscala/runtime/ObjectRef;)Lscala/collection/immutable/LazyList$State;
  #281 = Methodref          #2.#280       // scala/collection/immutable/LazyList$.$anonfun$takeRightImpl$1:(Lscala/runtime/ObjectRef;Lscala/runtime/IntRef;Lscala/runtime/ObjectRef;)Lscala/collection/immutable/LazyList$State;
  #282 = MethodHandle       6:#281        // REF_invokeStatic scala/collection/immutable/LazyList$.$anonfun$takeRightImpl$1:(Lscala/runtime/ObjectRef;Lscala/runtime/IntRef;Lscala/runtime/ObjectRef;)Lscala/collection/immutable/LazyList$State;
  #283 = Utf8               (Lscala/runtime/ObjectRef;Lscala/runtime/IntRef;Lscala/runtime/ObjectRef;)Lscala/Function0;
  #284 = NameAndType        #67:#283      // apply:(Lscala/runtime/ObjectRef;Lscala/runtime/IntRef;Lscala/runtime/ObjectRef;)Lscala/Function0;
  #285 = InvokeDynamic      #7:#284       // #7:apply:(Lscala/runtime/ObjectRef;Lscala/runtime/IntRef;Lscala/runtime/ObjectRef;)Lscala/Function0;
  #286 = Utf8               scoutRef
  #287 = Utf8               remainingRef
  #288 = Utf8               toDeferrer
  #289 = Utf8               (Lscala/Function0;)Lscala/Function0;
  #290 = Utf8               <A:Ljava/lang/Object;>(Lscala/Function0<Lscala/collection/immutable/LazyList<TA;>;>;)Lscala/Function0<Lscala/collection/immutable/LazyList<TA;>;>;
  #291 = Utf8               l
  #292 = Utf8               from
  #293 = Utf8               (Lscala/collection/IterableOnce;)Lscala/collection/immutable/LazyList;
  #294 = Utf8               <A:Ljava/lang/Object;>(Lscala/collection/IterableOnce<TA;>;)Lscala/collection/immutable/LazyList<TA;>;
  #295 = Utf8               coll
  #296 = Utf8               scala/collection/IterableOnce
  #297 = Class              #296          // scala/collection/IterableOnce
  #298 = Utf8               knownSize
  #299 = Utf8               ()I
  #300 = NameAndType        #298:#299     // knownSize:()I
  #301 = InterfaceMethodref #297.#300     // scala/collection/IterableOnce.knownSize:()I
  #302 = Utf8               empty
  #303 = NameAndType        #302:#75      // empty:()Lscala/collection/immutable/LazyList;
  #304 = Methodref          #2.#303       // scala/collection/immutable/LazyList$.empty:()Lscala/collection/immutable/LazyList;
  #305 = Utf8               $anonfun$from$1
  #306 = Utf8               (Lscala/collection/IterableOnce;)Lscala/collection/immutable/LazyList$State;
  #307 = NameAndType        #305:#306     // $anonfun$from$1:(Lscala/collection/IterableOnce;)Lscala/collection/immutable/LazyList$State;
  #308 = Methodref          #2.#307       // scala/collection/immutable/LazyList$.$anonfun$from$1:(Lscala/collection/IterableOnce;)Lscala/collection/immutable/LazyList$State;
  #309 = MethodHandle       6:#308        // REF_invokeStatic scala/collection/immutable/LazyList$.$anonfun$from$1:(Lscala/collection/IterableOnce;)Lscala/collection/immutable/LazyList$State;
  #310 = Utf8               (Lscala/collection/IterableOnce;)Lscala/Function0;
  #311 = NameAndType        #67:#310      // apply:(Lscala/collection/IterableOnce;)Lscala/Function0;
  #312 = InvokeDynamic      #8:#311       // #8:apply:(Lscala/collection/IterableOnce;)Lscala/Function0;
  #313 = Utf8               Lscala/collection/IterableOnce;
  #314 = Utf8               <A:Ljava/lang/Object;>()Lscala/collection/immutable/LazyList<TA;>;
  #315 = Utf8               scala$collection$immutable$LazyList$$stateFromIteratorConcatSuffix
  #316 = Utf8               (Lscala/collection/Iterator;Lscala/Function0;)Lscala/collection/immutable/LazyList$State;
  #317 = Utf8               <A:Ljava/lang/Object;>(Lscala/collection/Iterator<TA;>;Lscala/Function0<Lscala/collection/immutable/LazyList$State<TA;>;>;)Lscala/collection/immutable/LazyList$State<TA;>;
  #318 = Utf8               it
  #319 = Utf8               suffix
  #320 = Utf8               scala/collection/Iterator
  #321 = Class              #320          // scala/collection/Iterator
  #322 = Utf8               hasNext
  #323 = Utf8               ()Z
  #324 = NameAndType        #322:#323     // hasNext:()Z
  #325 = InterfaceMethodref #321.#324     // scala/collection/Iterator.hasNext:()Z
  #326 = Utf8               next
  #327 = NameAndType        #326:#50      // next:()Ljava/lang/Object;
  #328 = InterfaceMethodref #321.#327     // scala/collection/Iterator.next:()Ljava/lang/Object;
  #329 = Utf8               $anonfun$stateFromIteratorConcatSuffix$1
  #330 = NameAndType        #329:#316     // $anonfun$stateFromIteratorConcatSuffix$1:(Lscala/collection/Iterator;Lscala/Function0;)Lscala/collection/immutable/LazyList$State;
  #331 = Methodref          #2.#330       // scala/collection/immutable/LazyList$.$anonfun$stateFromIteratorConcatSuffix$1:(Lscala/collection/Iterator;Lscala/Function0;)Lscala/collection/immutable/LazyList$State;
  #332 = MethodHandle       6:#331        // REF_invokeStatic scala/collection/immutable/LazyList$.$anonfun$stateFromIteratorConcatSuffix$1:(Lscala/collection/Iterator;Lscala/Function0;)Lscala/collection/immutable/LazyList$State;
  #333 = Utf8               (Lscala/collection/Iterator;Lscala/Function0;)Lscala/Function0;
  #334 = NameAndType        #67:#333      // apply:(Lscala/collection/Iterator;Lscala/Function0;)Lscala/Function0;
  #335 = InvokeDynamic      #9:#334       // #9:apply:(Lscala/collection/Iterator;Lscala/Function0;)Lscala/Function0;
  #336 = Utf8               scala/Function0
  #337 = Class              #336          // scala/Function0
  #338 = NameAndType        #67:#50       // apply:()Ljava/lang/Object;
  #339 = InterfaceMethodref #337.#338     // scala/Function0.apply:()Ljava/lang/Object;
  #340 = Utf8               Lscala/collection/Iterator;
  #341 = Utf8               scala$collection$immutable$LazyList$$sCons_hd
  #342 = Utf8               scala$collection$immutable$LazyList$$sCons_tl
  #343 = Utf8               scala$collection$immutable$LazyList$$stateFromIterator
  #344 = Utf8               (Lscala/collection/Iterator;)Lscala/collection/immutable/LazyList$State;
  #345 = Utf8               <A:Ljava/lang/Object;>(Lscala/collection/Iterator<TA;>;)Lscala/collection/immutable/LazyList$State<TA;>;
  #346 = Utf8               $anonfun$stateFromIterator$1
  #347 = NameAndType        #346:#344     // $anonfun$stateFromIterator$1:(Lscala/collection/Iterator;)Lscala/collection/immutable/LazyList$State;
  #348 = Methodref          #2.#347       // scala/collection/immutable/LazyList$.$anonfun$stateFromIterator$1:(Lscala/collection/Iterator;)Lscala/collection/immutable/LazyList$State;
  #349 = MethodHandle       6:#348        // REF_invokeStatic scala/collection/immutable/LazyList$.$anonfun$stateFromIterator$1:(Lscala/collection/Iterator;)Lscala/collection/immutable/LazyList$State;
  #350 = Utf8               (Lscala/collection/Iterator;)Lscala/Function0;
  #351 = NameAndType        #67:#350      // apply:(Lscala/collection/Iterator;)Lscala/Function0;
  #352 = InvokeDynamic      #10:#351      // #10:apply:(Lscala/collection/Iterator;)Lscala/Function0;
  #353 = Utf8               Lscala/collection/immutable/LazyList$State$Empty$;
  #354 = NameAndType        #31:#353      // MODULE$:Lscala/collection/immutable/LazyList$State$Empty$;
  #355 = Fieldref           #29.#354      // scala/collection/immutable/LazyList$State$Empty$.MODULE$:Lscala/collection/immutable/LazyList$State$Empty$;
  #356 = Utf8               concat
  #357 = Utf8               (Lscala/collection/immutable/Seq;)Lscala/collection/immutable/LazyList;
  #358 = Utf8               <A:Ljava/lang/Object;>(Lscala/collection/immutable/Seq<Lscala/collection/Iterable<TA;>;>;)Lscala/collection/immutable/LazyList<TA;>;
  #359 = Utf8               xss
  #360 = Utf8               scala/collection/immutable/Seq
  #361 = Class              #360          // scala/collection/immutable/Seq
  #362 = InterfaceMethodref #361.#300     // scala/collection/immutable/Seq.knownSize:()I
  #363 = Utf8               $anonfun$concat$1
  #364 = Utf8               (Lscala/collection/immutable/Seq;)Lscala/collection/immutable/LazyList$State;
  #365 = NameAndType        #363:#364     // $anonfun$concat$1:(Lscala/collection/immutable/Seq;)Lscala/collection/immutable/LazyList$State;
  #366 = Methodref          #2.#365       // scala/collection/immutable/LazyList$.$anonfun$concat$1:(Lscala/collection/immutable/Seq;)Lscala/collection/immutable/LazyList$State;
  #367 = MethodHandle       6:#366        // REF_invokeStatic scala/collection/immutable/LazyList$.$anonfun$concat$1:(Lscala/collection/immutable/Seq;)Lscala/collection/immutable/LazyList$State;
  #368 = Utf8               (Lscala/collection/immutable/Seq;)Lscala/Function0;
  #369 = NameAndType        #67:#368      // apply:(Lscala/collection/immutable/Seq;)Lscala/Function0;
  #370 = InvokeDynamic      #11:#369      // #11:apply:(Lscala/collection/immutable/Seq;)Lscala/Function0;
  #371 = Utf8               concatIterator
  #372 = Utf8               <A:Ljava/lang/Object;>(Lscala/collection/Iterator<Lscala/collection/Iterable<TA;>;>;)Lscala/collection/immutable/LazyList$State<TA;>;
  #373 = Utf8               iterator
  #374 = Utf8               ()Lscala/collection/Iterator;
  #375 = NameAndType        #373:#374     // iterator:()Lscala/collection/Iterator;
  #376 = InterfaceMethodref #297.#375     // scala/collection/IterableOnce.iterator:()Lscala/collection/Iterator;
  #377 = Utf8               $anonfun$concatIterator$1
  #378 = NameAndType        #377:#344     // $anonfun$concatIterator$1:(Lscala/collection/Iterator;)Lscala/collection/immutable/LazyList$State;
  #379 = Methodref          #2.#378       // scala/collection/immutable/LazyList$.$anonfun$concatIterator$1:(Lscala/collection/Iterator;)Lscala/collection/immutable/LazyList$State;
  #380 = MethodHandle       6:#379        // REF_invokeStatic scala/collection/immutable/LazyList$.$anonfun$concatIterator$1:(Lscala/collection/Iterator;)Lscala/collection/immutable/LazyList$State;
  #381 = InvokeDynamic      #12:#351      // #12:apply:(Lscala/collection/Iterator;)Lscala/Function0;
  #382 = Utf8               scala$collection$immutable$LazyList$$stateFromIteratorConcatSuffix_it
  #383 = Utf8               scala$collection$immutable$LazyList$$stateFromIteratorConcatSuffix_suffix
  #384 = Utf8               scala$collection$immutable$LazyList$$stateFromIteratorConcatSuffix_scala$collection$immutable$LazyList$$newLL_state
  #385 = Utf8               scala$collection$immutable$LazyList$$stateFromIteratorConcatSuffix_scala$collection$immutable$LazyList$$sCons_hd
  #386 = Utf8               scala$collection$immutable$LazyList$$stateFromIteratorConcatSuffix_scala$collection$immutable$LazyList$$sCons_tl
  #387 = Utf8               (Lscala/Function0;Lscala/Function1;)Lscala/collection/immutable/LazyList;
  #388 = Utf8               <A:Ljava/lang/Object;>(Lscala/Function0<TA;>;Lscala/Function1<TA;TA;>;)Lscala/collection/immutable/LazyList<TA;>;
  #389 = Utf8               $anonfun$iterate$1
  #390 = Utf8               (Lscala/Function0;Lscala/Function1;)Lscala/collection/immutable/LazyList$State;
  #391 = NameAndType        #389:#390     // $anonfun$iterate$1:(Lscala/Function0;Lscala/Function1;)Lscala/collection/immutable/LazyList$State;
  #392 = Methodref          #2.#391       // scala/collection/immutable/LazyList$.$anonfun$iterate$1:(Lscala/Function0;Lscala/Function1;)Lscala/collection/immutable/LazyList$State;
  #393 = MethodHandle       6:#392        // REF_invokeStatic scala/collection/immutable/LazyList$.$anonfun$iterate$1:(Lscala/Function0;Lscala/Function1;)Lscala/collection/immutable/LazyList$State;
  #394 = Utf8               (Lscala/Function0;Lscala/Function1;)Lscala/Function0;
  #395 = NameAndType        #67:#394      // apply:(Lscala/Function0;Lscala/Function1;)Lscala/Function0;
  #396 = InvokeDynamic      #13:#395      // #13:apply:(Lscala/Function0;Lscala/Function1;)Lscala/Function0;
  #397 = Utf8               (II)Lscala/collection/immutable/LazyList;
  #398 = Utf8               (II)Lscala/collection/immutable/LazyList<Ljava/lang/Object;>;
  #399 = Utf8               $anonfun$from$2
  #400 = Utf8               (II)Lscala/collection/immutable/LazyList$State;
  #401 = NameAndType        #399:#400     // $anonfun$from$2:(II)Lscala/collection/immutable/LazyList$State;
  #402 = Methodref          #2.#401       // scala/collection/immutable/LazyList$.$anonfun$from$2:(II)Lscala/collection/immutable/LazyList$State;
  #403 = MethodHandle       6:#402        // REF_invokeStatic scala/collection/immutable/LazyList$.$anonfun$from$2:(II)Lscala/collection/immutable/LazyList$State;
  #404 = Utf8               (II)Lscala/Function0;
  #405 = NameAndType        #67:#404      // apply:(II)Lscala/Function0;
  #406 = InvokeDynamic      #14:#405      // #14:apply:(II)Lscala/Function0;
  #407 = Utf8               (I)Lscala/collection/immutable/LazyList;
  #408 = Utf8               (I)Lscala/collection/immutable/LazyList<Ljava/lang/Object;>;
  #409 = NameAndType        #292:#397     // from:(II)Lscala/collection/immutable/LazyList;
  #410 = Methodref          #2.#409       // scala/collection/immutable/LazyList$.from:(II)Lscala/collection/immutable/LazyList;
  #411 = Utf8               continually
  #412 = Utf8               <A:Ljava/lang/Object;>(Lscala/Function0<TA;>;)Lscala/collection/immutable/LazyList<TA;>;
  #413 = Utf8               $anonfun$continually$1
  #414 = Utf8               (Lscala/Function0;)Lscala/collection/immutable/LazyList$State;
  #415 = NameAndType        #413:#414     // $anonfun$continually$1:(Lscala/Function0;)Lscala/collection/immutable/LazyList$State;
  #416 = Methodref          #2.#415       // scala/collection/immutable/LazyList$.$anonfun$continually$1:(Lscala/Function0;)Lscala/collection/immutable/LazyList$State;
  #417 = MethodHandle       6:#416        // REF_invokeStatic scala/collection/immutable/LazyList$.$anonfun$continually$1:(Lscala/Function0;)Lscala/collection/immutable/LazyList$State;
  #418 = NameAndType        #67:#289      // apply:(Lscala/Function0;)Lscala/Function0;
  #419 = InvokeDynamic      #15:#418      // #15:apply:(Lscala/Function0;)Lscala/Function0;
  #420 = Utf8               (ILscala/Function0;)Lscala/collection/immutable/LazyList;
  #421 = Utf8               <A:Ljava/lang/Object;>(ILscala/Function0<TA;>;)Lscala/collection/immutable/LazyList<TA;>;
  #422 = Utf8               $anonfun$fill$1
  #423 = Utf8               (Lscala/Function0;I)Lscala/collection/immutable/LazyList$State;
  #424 = NameAndType        #422:#423     // $anonfun$fill$1:(Lscala/Function0;I)Lscala/collection/immutable/LazyList$State;
  #425 = Methodref          #2.#424       // scala/collection/immutable/LazyList$.$anonfun$fill$1:(Lscala/Function0;I)Lscala/collection/immutable/LazyList$State;
  #426 = MethodHandle       6:#425        // REF_invokeStatic scala/collection/immutable/LazyList$.$anonfun$fill$1:(Lscala/Function0;I)Lscala/collection/immutable/LazyList$State;
  #427 = Utf8               (Lscala/Function0;I)Lscala/Function0;
  #428 = NameAndType        #67:#427      // apply:(Lscala/Function0;I)Lscala/Function0;
  #429 = InvokeDynamic      #16:#428      // #16:apply:(Lscala/Function0;I)Lscala/Function0;
  #430 = Utf8               (ILscala/Function1;)Lscala/collection/immutable/LazyList;
  #431 = Utf8               <A:Ljava/lang/Object;>(ILscala/Function1<Ljava/lang/Object;TA;>;)Lscala/collection/immutable/LazyList<TA;>;
  #432 = Utf8               $anonfun$tabulate$1
  #433 = Utf8               (Lscala/collection/immutable/LazyList$;Lscala/Function1;II)Lscala/collection/immutable/LazyList$State;
  #434 = NameAndType        #432:#433     // $anonfun$tabulate$1:(Lscala/collection/immutable/LazyList$;Lscala/Function1;II)Lscala/collection/immutable/LazyList$State;
  #435 = Methodref          #2.#434       // scala/collection/immutable/LazyList$.$anonfun$tabulate$1:(Lscala/collection/immutable/LazyList$;Lscala/Function1;II)Lscala/collection/immutable/LazyList$State;
  #436 = MethodHandle       6:#435        // REF_invokeStatic scala/collection/immutable/LazyList$.$anonfun$tabulate$1:(Lscala/collection/immutable/LazyList$;Lscala/Function1;II)Lscala/collection/immutable/LazyList$State;
  #437 = Utf8               (Lscala/collection/immutable/LazyList$;Lscala/Function1;II)Lscala/Function0;
  #438 = NameAndType        #67:#437      // apply:(Lscala/collection/immutable/LazyList$;Lscala/Function1;II)Lscala/Function0;
  #439 = InvokeDynamic      #17:#438      // #17:apply:(Lscala/collection/immutable/LazyList$;Lscala/Function1;II)Lscala/Function0;
  #440 = Utf8               at$1_index
  #441 = Utf8               at$1_scala$collection$immutable$LazyList$$newLL_state
  #442 = Utf8               unfold
  #443 = Utf8               (Ljava/lang/Object;Lscala/Function1;)Lscala/collection/immutable/LazyList;
  #444 = Utf8               <A:Ljava/lang/Object;S:Ljava/lang/Object;>(TS;Lscala/Function1<TS;Lscala/Option<Lscala/Tuple2<TA;TS;>;>;>;)Lscala/collection/immutable/LazyList<TA;>;
  #445 = Utf8               init
  #446 = Utf8               $anonfun$unfold$1
  #447 = Utf8               (Lscala/Function1;Ljava/lang/Object;)Lscala/collection/immutable/LazyList$State;
  #448 = NameAndType        #446:#447     // $anonfun$unfold$1:(Lscala/Function1;Ljava/lang/Object;)Lscala/collection/immutable/LazyList$State;
  #449 = Methodref          #2.#448       // scala/collection/immutable/LazyList$.$anonfun$unfold$1:(Lscala/Function1;Ljava/lang/Object;)Lscala/collection/immutable/LazyList$State;
  #450 = MethodHandle       6:#449        // REF_invokeStatic scala/collection/immutable/LazyList$.$anonfun$unfold$1:(Lscala/Function1;Ljava/lang/Object;)Lscala/collection/immutable/LazyList$State;
  #451 = Utf8               (Lscala/Function1;Ljava/lang/Object;)Lscala/Function0;
  #452 = NameAndType        #67:#451      // apply:(Lscala/Function1;Ljava/lang/Object;)Lscala/Function0;
  #453 = InvokeDynamic      #18:#452      // #18:apply:(Lscala/Function1;Ljava/lang/Object;)Lscala/Function0;
  #454 = Utf8               newBuilder
  #455 = Utf8               ()Lscala/collection/mutable/Builder;
  #456 = Utf8               <A:Ljava/lang/Object;>()Lscala/collection/mutable/Builder<TA;Lscala/collection/immutable/LazyList<TA;>;>;
  #457 = Methodref          #15.#46       // scala/collection/immutable/LazyList$LazyBuilder."<init>":()V
  #458 = Utf8               writeReplace
  #459 = Utf8               scala/runtime/ModuleSerializationProxy
  #460 = Class              #459          // scala/runtime/ModuleSerializationProxy
  #461 = Utf8               (Ljava/lang/Class;)V
  #462 = NameAndType        #45:#461      // "<init>":(Ljava/lang/Class;)V
  #463 = Methodref          #460.#462     // scala/runtime/ModuleSerializationProxy."<init>":(Ljava/lang/Class;)V
  #464 = Utf8               (Ljava/lang/Object;Lscala/Function1;)Ljava/lang/Object;
  #465 = NameAndType        #442:#443     // unfold:(Ljava/lang/Object;Lscala/Function1;)Lscala/collection/immutable/LazyList;
  #466 = Methodref          #2.#465       // scala/collection/immutable/LazyList$.unfold:(Ljava/lang/Object;Lscala/Function1;)Lscala/collection/immutable/LazyList;
  #467 = Utf8               (ILscala/Function1;)Ljava/lang/Object;
  #468 = NameAndType        #161:#430     // tabulate:(ILscala/Function1;)Lscala/collection/immutable/LazyList;
  #469 = Methodref          #2.#468       // scala/collection/immutable/LazyList$.tabulate:(ILscala/Function1;)Lscala/collection/immutable/LazyList;
  #470 = Utf8               (ILscala/Function0;)Ljava/lang/Object;
  #471 = NameAndType        #137:#420     // fill:(ILscala/Function0;)Lscala/collection/immutable/LazyList;
  #472 = Methodref          #2.#471       // scala/collection/immutable/LazyList$.fill:(ILscala/Function0;)Lscala/collection/immutable/LazyList;
  #473 = NameAndType        #356:#357     // concat:(Lscala/collection/immutable/Seq;)Lscala/collection/immutable/LazyList;
  #474 = Methodref          #2.#473       // scala/collection/immutable/LazyList$.concat:(Lscala/collection/immutable/Seq;)Lscala/collection/immutable/LazyList;
  #475 = Utf8               (Lscala/collection/IterableOnce;)Ljava/lang/Object;
  #476 = Utf8               source
  #477 = NameAndType        #292:#293     // from:(Lscala/collection/IterableOnce;)Lscala/collection/immutable/LazyList;
  #478 = Methodref          #2.#477       // scala/collection/immutable/LazyList$.from:(Lscala/collection/IterableOnce;)Lscala/collection/immutable/LazyList;
  #479 = Utf8               x$10
  #480 = Utf8               scala/runtime/Statics
  #481 = Class              #480          // scala/runtime/Statics
  #482 = Utf8               pfMarker
  #483 = NameAndType        #482:#120     // pfMarker:Ljava/lang/Object;
  #484 = Fieldref           #481.#483     // scala/runtime/Statics.pfMarker:Ljava/lang/Object;
  #485 = Utf8               restRef$1
  #486 = Utf8               p$2
  #487 = Utf8               isFlipped$1
  #488 = NameAndType        #141:#120     // elem:Ljava/lang/Object;
  #489 = Fieldref           #210.#488     // scala/runtime/ObjectRef.elem:Ljava/lang/Object;
  #490 = Utf8               isEmpty
  #491 = NameAndType        #490:#323     // isEmpty:()Z
  #492 = Methodref          #17.#491      // scala/collection/immutable/LazyList.isEmpty:()Z
  #493 = Utf8               head
  #494 = NameAndType        #493:#50      // head:()Ljava/lang/Object;
  #495 = Methodref          #17.#494      // scala/collection/immutable/LazyList.head:()Ljava/lang/Object;
  #496 = Utf8               scala/Function1
  #497 = Class              #496          // scala/Function1
  #498 = NameAndType        #67:#80       // apply:(Ljava/lang/Object;)Ljava/lang/Object;
  #499 = InterfaceMethodref #497.#498     // scala/Function1.apply:(Ljava/lang/Object;)Ljava/lang/Object;
  #500 = Utf8               scala/runtime/BoxesRunTime
  #501 = Class              #500          // scala/runtime/BoxesRunTime
  #502 = Utf8               unboxToBoolean
  #503 = Utf8               (Ljava/lang/Object;)Z
  #504 = NameAndType        #502:#503     // unboxToBoolean:(Ljava/lang/Object;)Z
  #505 = Methodref          #501.#504     // scala/runtime/BoxesRunTime.unboxToBoolean:(Ljava/lang/Object;)Z
  #506 = Utf8               tail
  #507 = NameAndType        #506:#75      // tail:()Lscala/collection/immutable/LazyList;
  #508 = Methodref          #17.#507      // scala/collection/immutable/LazyList.tail:()Lscala/collection/immutable/LazyList;
  #509 = Utf8               found
  #510 = Utf8               rest
  #511 = Utf8               scala$collection$immutable$LazyList$$filterImpl_restRef
  #512 = Utf8               scala$collection$immutable$LazyList$$filterImpl_scala$collection$immutable$LazyList$$newLL_state
  #513 = Utf8               restRef$2
  #514 = Utf8               pf$1
  #515 = NameAndType        #40:#86       // scala$collection$immutable$LazyList$$anyToMarker:()Lscala/Function1;
  #516 = Methodref          #2.#515       // scala/collection/immutable/LazyList$.scala$collection$immutable$LazyList$$anyToMarker:()Lscala/Function1;
  #517 = Utf8               scala/PartialFunction
  #518 = Class              #517          // scala/PartialFunction
  #519 = Utf8               applyOrElse
  #520 = NameAndType        #519:#464     // applyOrElse:(Ljava/lang/Object;Lscala/Function1;)Ljava/lang/Object;
  #521 = InterfaceMethodref #518.#520     // scala/PartialFunction.applyOrElse:(Ljava/lang/Object;Lscala/Function1;)Ljava/lang/Object;
  #522 = NameAndType        #225:#226     // scala$collection$immutable$LazyList$$collectImpl:(Lscala/collection/immutable/LazyList;Lscala/PartialFunction;)Lscala/collection/immutable/LazyList;
  #523 = Methodref          #2.#522       // scala/collection/immutable/LazyList$.scala$collection$immutable$LazyList$$collectImpl:(Lscala/collection/immutable/LazyList;Lscala/PartialFunction;)Lscala/collection/immutable/LazyList;
  #524 = Utf8               marker
  #525 = Utf8               toMarker
  #526 = Utf8               res
  #527 = Utf8               $anonfun$flatMapImpl$3
  #528 = Utf8               rest$1
  #529 = Utf8               f$3
  #530 = Utf8               scala$collection$immutable$LazyList$$state
  #531 = NameAndType        #530:#219     // scala$collection$immutable$LazyList$$state:()Lscala/collection/immutable/LazyList$State;
  #532 = Methodref          #17.#531      // scala/collection/immutable/LazyList.scala$collection$immutable$LazyList$$state:()Lscala/collection/immutable/LazyList$State;
  #533 = Utf8               scala$collection$immutable$LazyList$$flatMapImpl_ll
  #534 = Utf8               scala$collection$immutable$LazyList$$flatMapImpl_scala$collection$immutable$LazyList$$newLL_state
  #535 = Utf8               $anonfun$flatMapImpl$2
  #536 = Utf8               (Lscala/runtime/ObjectRef;Lscala/runtime/ObjectRef;Lscala/Function1;)Lscala/collection/immutable/LazyList$State;
  #537 = Utf8               it$3
  #538 = NameAndType        #527:#242     // $anonfun$flatMapImpl$3:(Lscala/runtime/ObjectRef;Lscala/Function1;)Lscala/collection/immutable/LazyList$State;
  #539 = Methodref          #2.#538       // scala/collection/immutable/LazyList$.$anonfun$flatMapImpl$3:(Lscala/runtime/ObjectRef;Lscala/Function1;)Lscala/collection/immutable/LazyList$State;
  #540 = MethodHandle       6:#539        // REF_invokeStatic scala/collection/immutable/LazyList$.$anonfun$flatMapImpl$3:(Lscala/runtime/ObjectRef;Lscala/Function1;)Lscala/collection/immutable/LazyList$State;
  #541 = InvokeDynamic      #19:#247      // #19:apply:(Lscala/runtime/ObjectRef;Lscala/Function1;)Lscala/Function0;
  #542 = Utf8               $anonfun$flatMapImpl$3_scala$collection$immutable$LazyList$$flatMapImpl_ll
  #543 = Utf8               $anonfun$flatMapImpl$3_scala$collection$immutable$LazyList$$flatMapImpl_scala$collection$immutable$LazyList$$newLL_state
  #544 = Utf8               restRef$3
  #545 = NameAndType        #535:#536     // $anonfun$flatMapImpl$2:(Lscala/runtime/ObjectRef;Lscala/runtime/ObjectRef;Lscala/Function1;)Lscala/collection/immutable/LazyList$State;
  #546 = Methodref          #2.#545       // scala/collection/immutable/LazyList$.$anonfun$flatMapImpl$2:(Lscala/runtime/ObjectRef;Lscala/runtime/ObjectRef;Lscala/Function1;)Lscala/collection/immutable/LazyList$State;
  #547 = MethodHandle       6:#546        // REF_invokeStatic scala/collection/immutable/LazyList$.$anonfun$flatMapImpl$2:(Lscala/runtime/ObjectRef;Lscala/runtime/ObjectRef;Lscala/Function1;)Lscala/collection/immutable/LazyList$State;
  #548 = Utf8               (Lscala/runtime/ObjectRef;Lscala/runtime/ObjectRef;Lscala/Function1;)Lscala/Function0;
  #549 = NameAndType        #67:#548      // apply:(Lscala/runtime/ObjectRef;Lscala/runtime/ObjectRef;Lscala/Function1;)Lscala/Function0;
  #550 = InvokeDynamic      #20:#549      // #20:apply:(Lscala/runtime/ObjectRef;Lscala/runtime/ObjectRef;Lscala/Function1;)Lscala/Function0;
  #551 = Utf8               itHasNext
  #552 = Utf8               create_e
  #553 = Utf8               TU;
  #554 = Utf8               restRef$4
  #555 = Utf8               iRef$1
  #556 = NameAndType        #141:#121     // elem:I
  #557 = Fieldref           #254.#556     // scala/runtime/IntRef.elem:I
  #558 = Utf8               i
  #559 = Utf8               restRef$5
  #560 = Utf8               p$3
  #561 = Utf8               scoutRef$1
  #562 = Utf8               remainingRef$1
  #563 = Utf8               restRef$6
  #564 = Utf8               scout
  #565 = Utf8               remaining
  #566 = Utf8               coll$1
  #567 = NameAndType        #343:#344     // scala$collection$immutable$LazyList$$stateFromIterator:(Lscala/collection/Iterator;)Lscala/collection/immutable/LazyList$State;
  #568 = Methodref          #2.#567       // scala/collection/immutable/LazyList$.scala$collection$immutable$LazyList$$stateFromIterator:(Lscala/collection/Iterator;)Lscala/collection/immutable/LazyList$State;
  #569 = Utf8               it$4
  #570 = Utf8               suffix$3
  #571 = NameAndType        #315:#316     // scala$collection$immutable$LazyList$$stateFromIteratorConcatSuffix:(Lscala/collection/Iterator;Lscala/Function0;)Lscala/collection/immutable/LazyList$State;
  #572 = Methodref          #2.#571       // scala/collection/immutable/LazyList$.scala$collection$immutable$LazyList$$stateFromIteratorConcatSuffix:(Lscala/collection/Iterator;Lscala/Function0;)Lscala/collection/immutable/LazyList$State;
  #573 = Utf8               it$5
  #574 = Utf8               xss$1
  #575 = InterfaceMethodref #361.#375     // scala/collection/immutable/Seq.iterator:()Lscala/collection/Iterator;
  #576 = NameAndType        #371:#344     // concatIterator:(Lscala/collection/Iterator;)Lscala/collection/immutable/LazyList$State;
  #577 = Methodref          #2.#576       // scala/collection/immutable/LazyList$.concatIterator:(Lscala/collection/Iterator;)Lscala/collection/immutable/LazyList$State;
  #578 = Utf8               it$6
  #579 = Utf8               $anonfun$iterate$2
  #580 = Utf8               (Lscala/Function1;Ljava/lang/Object;)Ljava/lang/Object;
  #581 = Utf8               f$4
  #582 = Utf8               head$1
  #583 = Utf8               start$1
  #584 = NameAndType        #579:#580     // $anonfun$iterate$2:(Lscala/Function1;Ljava/lang/Object;)Ljava/lang/Object;
  #585 = Methodref          #2.#584       // scala/collection/immutable/LazyList$.$anonfun$iterate$2:(Lscala/Function1;Ljava/lang/Object;)Ljava/lang/Object;
  #586 = MethodHandle       6:#585        // REF_invokeStatic scala/collection/immutable/LazyList$.$anonfun$iterate$2:(Lscala/Function1;Ljava/lang/Object;)Ljava/lang/Object;
  #587 = InvokeDynamic      #21:#452      // #21:apply:(Lscala/Function1;Ljava/lang/Object;)Lscala/Function0;
  #588 = Utf8               iterate_start
  #589 = Utf8               iterate_scala$collection$immutable$LazyList$$newLL_state
  #590 = Utf8               start$2
  #591 = Utf8               step$2
  #592 = Utf8               java/lang/Integer
  #593 = Class              #592          // java/lang/Integer
  #594 = Utf8               valueOf
  #595 = Utf8               (I)Ljava/lang/Integer;
  #596 = NameAndType        #594:#595     // valueOf:(I)Ljava/lang/Integer;
  #597 = Methodref          #593.#596     // java/lang/Integer.valueOf:(I)Ljava/lang/Integer;
  #598 = Utf8               elem$6
  #599 = Utf8               continually_scala$collection$immutable$LazyList$$newLL_state
  #600 = Utf8               elem$7
  #601 = Utf8               n$3
  #602 = Utf8               fill_this
  #603 = Utf8               fill_n
  #604 = Utf8               fill_scala$collection$immutable$LazyList$$newLL_state
  #605 = Utf8               $this
  #606 = Utf8               f$5
  #607 = Utf8               index$2
  #608 = Utf8               n$4
  #609 = Utf8               at$1
  #610 = Utf8               (IILscala/Function1;)Lscala/collection/immutable/LazyList;
  #611 = Utf8               index
  #612 = Utf8               f$6
  #613 = Utf8               init$1
  #614 = Utf8               scala/Option
  #615 = Class              #614          // scala/Option
  #616 = Utf8               scala/Some
  #617 = Class              #616          // scala/Some
  #618 = Utf8               value
  #619 = NameAndType        #618:#50      // value:()Ljava/lang/Object;
  #620 = Methodref          #617.#619     // scala/Some.value:()Ljava/lang/Object;
  #621 = Utf8               scala/Tuple2
  #622 = Class              #621          // scala/Tuple2
  #623 = Utf8               _1
  #624 = NameAndType        #623:#50      // _1:()Ljava/lang/Object;
  #625 = Methodref          #622.#624     // scala/Tuple2._1:()Ljava/lang/Object;
  #626 = Utf8               _2
  #627 = NameAndType        #626:#50      // _2:()Ljava/lang/Object;
  #628 = Methodref          #622.#627     // scala/Tuple2._2:()Ljava/lang/Object;
  #629 = Utf8               scala/None$
  #630 = Class              #629          // scala/None$
  #631 = Utf8               Lscala/None$;
  #632 = NameAndType        #31:#631      // MODULE$:Lscala/None$;
  #633 = Fieldref           #630.#632     // scala/None$.MODULE$:Lscala/None$;
  #634 = Utf8               equals
  #635 = NameAndType        #634:#503     // equals:(Ljava/lang/Object;)Z
  #636 = Methodref          #5.#635       // java/lang/Object.equals:(Ljava/lang/Object;)Z
  #637 = Utf8               scala/MatchError
  #638 = Class              #637          // scala/MatchError
  #639 = Methodref          #638.#212     // scala/MatchError."<init>":(Ljava/lang/Object;)V
  #640 = Utf8               unfold_scala$collection$immutable$LazyList$$newLL_state
  #641 = Methodref          #5.#46        // java/lang/Object."<init>":()V
  #642 = Utf8               $deserializeLambda$
  #643 = Utf8               (Ljava/lang/invoke/SerializedLambda;)Ljava/lang/Object;
  #644 = Utf8               scala/runtime/LambdaDeserialize
  #645 = Class              #644          // scala/runtime/LambdaDeserialize
  #646 = Utf8               bootstrap
  #647 = Utf8               (Ljava/lang/invoke/MethodHandles$Lookup;Ljava/lang/String;Ljava/lang/invoke/MethodType;[Ljava/lang/invoke/MethodHandle;)Ljava/lang/invoke/CallSite;
  #648 = NameAndType        #646:#647     // bootstrap:(Ljava/lang/invoke/MethodHandles$Lookup;Ljava/lang/String;Ljava/lang/invoke/MethodType;[Ljava/lang/invoke/MethodHandle;)Ljava/lang/invoke/CallSite;
  #649 = Methodref          #645.#648     // scala/runtime/LambdaDeserialize.bootstrap:(Ljava/lang/invoke/MethodHandles$Lookup;Ljava/lang/String;Ljava/lang/invoke/MethodType;[Ljava/lang/invoke/MethodHandle;)Ljava/lang/invoke/CallSite;
  #650 = MethodHandle       6:#649        // REF_invokeStatic scala/runtime/LambdaDeserialize.bootstrap:(Ljava/lang/invoke/MethodHandles$Lookup;Ljava/lang/String;Ljava/lang/invoke/MethodType;[Ljava/lang/invoke/MethodHandle;)Ljava/lang/invoke/CallSite;
  #651 = Utf8               lambdaDeserialize
  #652 = NameAndType        #651:#643     // lambdaDeserialize:(Ljava/lang/invoke/SerializedLambda;)Ljava/lang/Object;
  #653 = InvokeDynamic      #22:#652      // #22:lambdaDeserialize:(Ljava/lang/invoke/SerializedLambda;)Ljava/lang/Object;
  #654 = Utf8               ConstantValue
  #655 = Utf8               Signature
  #656 = Utf8               Code
  #657 = Utf8               LineNumberTable
  #658 = Utf8               LocalVariableTable
  #659 = Utf8               MethodParameters
  #660 = Utf8               StackMapTable
  #661 = Utf8               LocalVariableTypeTable
  #662 = Utf8               InnerClasses
  #663 = Utf8               SourceFile
  #664 = Utf8               BootstrapMethods
  #665 = Utf8               ScalaInlineInfo
  #666 = Utf8               Scala
{
  public static final scala.collection.immutable.LazyList$ MODULE$;
    descriptor: Lscala/collection/immutable/LazyList$;
    flags: (0x0019) ACC_PUBLIC, ACC_STATIC, ACC_FINAL

  private static final long serialVersionUID;
    descriptor: J
    flags: (0x001a) ACC_PRIVATE, ACC_STATIC, ACC_FINAL
    ConstantValue: long 3l

  private static final scala.collection.immutable.LazyList<scala.runtime.Nothing$> _empty;
    descriptor: Lscala/collection/immutable/LazyList;
    flags: (0x001a) ACC_PRIVATE, ACC_STATIC, ACC_FINAL
    Signature: #39                          // Lscala/collection/immutable/LazyList<Lscala/runtime/Nothing$;>;

  private static final scala.Function1<java.lang.Object, java.lang.Object> scala$collection$immutable$LazyList$$anyToMarker;
    descriptor: Lscala/Function1;
    flags: (0x001a) ACC_PRIVATE, ACC_STATIC, ACC_FINAL
    Signature: #42                          // Lscala/Function1<Ljava/lang/Object;Ljava/lang/Object;>;

  public static {};
    descriptor: ()V
    flags: (0x0009) ACC_PUBLIC, ACC_STATIC
    Code:
      stack=3, locals=1, args_size=0
         0: new           #2                  // class scala/collection/immutable/LazyList$
         3: dup
         4: invokespecial #47                 // Method "<init>":()V
         7: putstatic     #49                 // Field MODULE$:Lscala/collection/immutable/LazyList$;
        10: getstatic     #49                 // Field MODULE$:Lscala/collection/immutable/LazyList$;
        13: pop
        14: getstatic     #49                 // Field MODULE$:Lscala/collection/immutable/LazyList$;
        17: pop
        18: getstatic     #49                 // Field MODULE$:Lscala/collection/immutable/LazyList$;
        21: pop
        22: invokedynamic #70,  0             // InvokeDynamic #0:apply:()Lscala/Function0;
        27: astore_0
        28: new           #17                 // class scala/collection/immutable/LazyList
        31: dup
        32: aload_0
        33: invokespecial #73                 // Method scala/collection/immutable/LazyList."<init>":(Lscala/Function0;)V
        36: aconst_null
        37: astore_0
        38: invokevirtual #77                 // Method scala/collection/immutable/LazyList.force:()Lscala/collection/immutable/LazyList;
        41: putstatic     #79                 // Field _empty:Lscala/collection/immutable/LazyList;
        44: invokedynamic #88,  0             // InvokeDynamic #1:apply:()Lscala/Function1;
        49: putstatic     #90                 // Field scala$collection$immutable$LazyList$$anyToMarker:Lscala/Function1;
        52: return
      LineNumberTable:
        line 969: 0
        line 971: 18
        line 990: 28
        line 971: 36
        line 995: 44
        line 969: 52
      LocalVariableTable:
        Start  Length  Slot  Name   Signature
           28       8     0 scala$collection$immutable$LazyList$$newLL_state   Lscala/Function0;

  public final scala.collection.SeqOps unapplySeq(scala.collection.SeqOps);
    descriptor: (Lscala/collection/SeqOps;)Lscala/collection/SeqOps;
    flags: (0x0011) ACC_PUBLIC, ACC_FINAL
    Code:
      stack=2, locals=2, args_size=2
         0: aload_0
         1: aload_1
         2: invokestatic  #99                 // InterfaceMethod scala/collection/SeqFactory.unapplySeq$:(Lscala/collection/SeqFactory;Lscala/collection/SeqOps;)Lscala/collection/SeqOps;
         5: areturn
      LineNumberTable:
        line 969: 0
      LocalVariableTable:
        Start  Length  Slot  Name   Signature
            0       6     0  this   Lscala/collection/immutable/LazyList$;
            0       6     1     x   Lscala/collection/SeqOps;
    MethodParameters:
      Name                           Flags
      x                              final

  public java.lang.Object apply(scala.collection.immutable.Seq);
    descriptor: (Lscala/collection/immutable/Seq;)Ljava/lang/Object;
    flags: (0x0001) ACC_PUBLIC
    Code:
      stack=2, locals=2, args_size=2
         0: aload_0
         1: aload_1
         2: invokestatic  #109                // InterfaceMethod scala/collection/IterableFactory.apply$:(Lscala/collection/IterableFactory;Lscala/collection/immutable/Seq;)Ljava/lang/Object;
         5: areturn
      LineNumberTable:
        line 969: 0
      LocalVariableTable:
        Start  Length  Slot  Name   Signature
            0       6     0  this   Lscala/collection/immutable/LazyList$;
            0       6     1 elems   Lscala/collection/immutable/Seq;
    MethodParameters:
      Name                           Flags
      elems                          final

  public java.lang.Object iterate(java.lang.Object, int, scala.Function1);
    descriptor: (Ljava/lang/Object;ILscala/Function1;)Ljava/lang/Object;
    flags: (0x0001) ACC_PUBLIC
    Code:
      stack=4, locals=4, args_size=4
         0: aload_0
         1: aload_1
         2: iload_2
         3: aload_3
         4: invokestatic  #119                // InterfaceMethod scala/collection/IterableFactory.iterate$:(Lscala/collection/IterableFactory;Ljava/lang/Object;ILscala/Function1;)Ljava/lang/Object;
         7: areturn
      LineNumberTable:
        line 969: 0
      LocalVariableTable:
        Start  Length  Slot  Name   Signature
            0       8     0  this   Lscala/collection/immutable/LazyList$;
            0       8     1 start   Ljava/lang/Object;
            0       8     2   len   I
            0       8     3     f   Lscala/Function1;
    MethodParameters:
      Name                           Flags
      start                          final
      len                            final
      f                              final

  public java.lang.Object range(java.lang.Object, java.lang.Object, scala.math.Integral);
    descriptor: (Ljava/lang/Object;Ljava/lang/Object;Lscala/math/Integral;)Ljava/lang/Object;
    flags: (0x0001) ACC_PUBLIC
    Code:
      stack=4, locals=4, args_size=4
         0: aload_0
         1: aload_1
         2: aload_2
         3: aload_3
         4: invokestatic  #129                // InterfaceMethod scala/collection/IterableFactory.range$:(Lscala/collection/IterableFactory;Ljava/lang/Object;Ljava/lang/Object;Lscala/math/Integral;)Ljava/lang/Object;
         7: areturn
      LineNumberTable:
        line 969: 0
      LocalVariableTable:
        Start  Length  Slot  Name   Signature
            0       8     0  this   Lscala/collection/immutable/LazyList$;
            0       8     1 start   Ljava/lang/Object;
            0       8     2   end   Ljava/lang/Object;
            0       8     3 evidence$3   Lscala/math/Integral;
    MethodParameters:
      Name                           Flags
      start                          final
      end                            final
      evidence$3                     final

  public java.lang.Object range(java.lang.Object, java.lang.Object, java.lang.Object, scala.math.Integral);
    descriptor: (Ljava/lang/Object;Ljava/lang/Object;Ljava/lang/Object;Lscala/math/Integral;)Ljava/lang/Object;
    flags: (0x0001) ACC_PUBLIC
    Code:
      stack=5, locals=5, args_size=5
         0: aload_0
         1: aload_1
         2: aload_2
         3: aload_3
         4: aload         4
         6: invokestatic  #136                // InterfaceMethod scala/collection/IterableFactory.range$:(Lscala/collection/IterableFactory;Ljava/lang/Object;Ljava/lang/Object;Ljava/lang/Object;Lscala/math/Integral;)Ljava/lang/Object;
         9: areturn
      LineNumberTable:
        line 969: 0
      LocalVariableTable:
        Start  Length  Slot  Name   Signature
            0      10     0  this   Lscala/collection/immutable/LazyList$;
            0      10     1 start   Ljava/lang/Object;
            0      10     2   end   Ljava/lang/Object;
            0      10     3  step   Ljava/lang/Object;
            0      10     4 evidence$4   Lscala/math/Integral;
    MethodParameters:
      Name                           Flags
      start                          final
      end                            final
      step                           final
      evidence$4                     final

  public java.lang.Object fill(int, int, scala.Function0);
    descriptor: (IILscala/Function0;)Ljava/lang/Object;
    flags: (0x0001) ACC_PUBLIC
    Code:
      stack=4, locals=4, args_size=4
         0: aload_0
         1: iload_1
         2: iload_2
         3: aload_3
         4: invokestatic  #145                // InterfaceMethod scala/collection/IterableFactory.fill$:(Lscala/collection/IterableFactory;IILscala/Function0;)Ljava/lang/Object;
         7: areturn
      LineNumberTable:
        line 969: 0
      LocalVariableTable:
        Start  Length  Slot  Name   Signature
            0       8     0  this   Lscala/collection/immutable/LazyList$;
            0       8     1    n1   I
            0       8     2    n2   I
            0       8     3  elem   Lscala/Function0;
    MethodParameters:
      Name                           Flags
      n1                             final
      n2                             final
      elem                           final

  public java.lang.Object fill(int, int, int, scala.Function0);
    descriptor: (IIILscala/Function0;)Ljava/lang/Object;
    flags: (0x0001) ACC_PUBLIC
    Code:
      stack=5, locals=5, args_size=5
         0: aload_0
         1: iload_1
         2: iload_2
         3: iload_3
         4: aload         4
         6: invokestatic  #150                // InterfaceMethod scala/collection/IterableFactory.fill$:(Lscala/collection/IterableFactory;IIILscala/Function0;)Ljava/lang/Object;
         9: areturn
      LineNumberTable:
        line 969: 0
      LocalVariableTable:
        Start  Length  Slot  Name   Signature
            0      10     0  this   Lscala/collection/immutable/LazyList$;
            0      10     1    n1   I
            0      10     2    n2   I
            0      10     3    n3   I
            0      10     4  elem   Lscala/Function0;
    MethodParameters:
      Name                           Flags
      n1                             final
      n2                             final
      n3                             final
      elem                           final

  public java.lang.Object fill(int, int, int, int, scala.Function0);
    descriptor: (IIIILscala/Function0;)Ljava/lang/Object;
    flags: (0x0001) ACC_PUBLIC
    Code:
      stack=6, locals=6, args_size=6
         0: aload_0
         1: iload_1
         2: iload_2
         3: iload_3
         4: iload         4
         6: aload         5
         8: invokestatic  #155                // InterfaceMethod scala/collection/IterableFactory.fill$:(Lscala/collection/IterableFactory;IIIILscala/Function0;)Ljava/lang/Object;
        11: areturn
      LineNumberTable:
        line 969: 0
      LocalVariableTable:
        Start  Length  Slot  Name   Signature
            0      12     0  this   Lscala/collection/immutable/LazyList$;
            0      12     1    n1   I
            0      12     2    n2   I
            0      12     3    n3   I
            0      12     4    n4   I
            0      12     5  elem   Lscala/Function0;
    MethodParameters:
      Name                           Flags
      n1                             final
      n2                             final
      n3                             final
      n4                             final
      elem                           final

  public java.lang.Object fill(int, int, int, int, int, scala.Function0);
    descriptor: (IIIIILscala/Function0;)Ljava/lang/Object;
    flags: (0x0001) ACC_PUBLIC
    Code:
      stack=7, locals=7, args_size=7
         0: aload_0
         1: iload_1
         2: iload_2
         3: iload_3
         4: iload         4
         6: iload         5
         8: aload         6
        10: invokestatic  #160                // InterfaceMethod scala/collection/IterableFactory.fill$:(Lscala/collection/IterableFactory;IIIIILscala/Function0;)Ljava/lang/Object;
        13: areturn
      LineNumberTable:
        line 969: 0
      LocalVariableTable:
        Start  Length  Slot  Name   Signature
            0      14     0  this   Lscala/collection/immutable/LazyList$;
            0      14     1    n1   I
            0      14     2    n2   I
            0      14     3    n3   I
            0      14     4    n4   I
            0      14     5    n5   I
            0      14     6  elem   Lscala/Function0;
    MethodParameters:
      Name                           Flags
      n1                             final
      n2                             final
      n3                             final
      n4                             final
      n5                             final
      elem                           final

  public java.lang.Object tabulate(int, int, scala.Function2);
    descriptor: (IILscala/Function2;)Ljava/lang/Object;
    flags: (0x0001) ACC_PUBLIC
    Code:
      stack=4, locals=4, args_size=4
         0: aload_0
         1: iload_1
         2: iload_2
         3: aload_3
         4: invokestatic  #166                // InterfaceMethod scala/collection/IterableFactory.tabulate$:(Lscala/collection/IterableFactory;IILscala/Function2;)Ljava/lang/Object;
         7: areturn
      LineNumberTable:
        line 969: 0
      LocalVariableTable:
        Start  Length  Slot  Name   Signature
            0       8     0  this   Lscala/collection/immutable/LazyList$;
            0       8     1    n1   I
            0       8     2    n2   I
            0       8     3     f   Lscala/Function2;
    MethodParameters:
      Name                           Flags
      n1                             final
      n2                             final
      f                              final

  public java.lang.Object tabulate(int, int, int, scala.Function3);
    descriptor: (IIILscala/Function3;)Ljava/lang/Object;
    flags: (0x0001) ACC_PUBLIC
    Code:
      stack=5, locals=5, args_size=5
         0: aload_0
         1: iload_1
         2: iload_2
         3: iload_3
         4: aload         4
         6: invokestatic  #171                // InterfaceMethod scala/collection/IterableFactory.tabulate$:(Lscala/collection/IterableFactory;IIILscala/Function3;)Ljava/lang/Object;
         9: areturn
      LineNumberTable:
        line 969: 0
      LocalVariableTable:
        Start  Length  Slot  Name   Signature
            0      10     0  this   Lscala/collection/immutable/LazyList$;
            0      10     1    n1   I
            0      10     2    n2   I
            0      10     3    n3   I
            0      10     4     f   Lscala/Function3;
    MethodParameters:
      Name                           Flags
      n1                             final
      n2                             final
      n3                             final
      f                              final

  public java.lang.Object tabulate(int, int, int, int, scala.Function4);
    descriptor: (IIIILscala/Function4;)Ljava/lang/Object;
    flags: (0x0001) ACC_PUBLIC
    Code:
      stack=6, locals=6, args_size=6
         0: aload_0
         1: iload_1
         2: iload_2
         3: iload_3
         4: iload         4
         6: aload         5
         8: invokestatic  #176                // InterfaceMethod scala/collection/IterableFactory.tabulate$:(Lscala/collection/IterableFactory;IIIILscala/Function4;)Ljava/lang/Object;
        11: areturn
      LineNumberTable:
        line 969: 0
      LocalVariableTable:
        Start  Length  Slot  Name   Signature
            0      12     0  this   Lscala/collection/immutable/LazyList$;
            0      12     1    n1   I
            0      12     2    n2   I
            0      12     3    n3   I
            0      12     4    n4   I
            0      12     5     f   Lscala/Function4;
    MethodParameters:
      Name                           Flags
      n1                             final
      n2                             final
      n3                             final
      n4                             final
      f                              final

  public java.lang.Object tabulate(int, int, int, int, int, scala.Function5);
    descriptor: (IIIIILscala/Function5;)Ljava/lang/Object;
    flags: (0x0001) ACC_PUBLIC
    Code:
      stack=7, locals=7, args_size=7
         0: aload_0
         1: iload_1
         2: iload_2
         3: iload_3
         4: iload         4
         6: iload         5
         8: aload         6
        10: invokestatic  #181                // InterfaceMethod scala/collection/IterableFactory.tabulate$:(Lscala/collection/IterableFactory;IIIIILscala/Function5;)Ljava/lang/Object;
        13: areturn
      LineNumberTable:
        line 969: 0
      LocalVariableTable:
        Start  Length  Slot  Name   Signature
            0      14     0  this   Lscala/collection/immutable/LazyList$;
            0      14     1    n1   I
            0      14     2    n2   I
            0      14     3    n3   I
            0      14     4    n4   I
            0      14     5    n5   I
            0      14     6     f   Lscala/Function5;
    MethodParameters:
      Name                           Flags
      n1                             final
      n2                             final
      n3                             final
      n4                             final
      n5                             final
      f                              final

  public <A extends java.lang.Object> scala.collection.Factory<A, scala.collection.immutable.LazyList<A>> iterableFactory();
    descriptor: ()Lscala/collection/Factory;
    flags: (0x0001) ACC_PUBLIC
    Code:
      stack=1, locals=1, args_size=1
         0: aload_0
         1: invokestatic  #189                // InterfaceMethod scala/collection/IterableFactory.iterableFactory$:(Lscala/collection/IterableFactory;)Lscala/collection/Factory;
         4: areturn
      LineNumberTable:
        line 969: 0
      LocalVariableTable:
        Start  Length  Slot  Name   Signature
            0       5     0  this   Lscala/collection/immutable/LazyList$;
    Signature: #185                         // <A:Ljava/lang/Object;>()Lscala/collection/Factory<TA;Lscala/collection/immutable/LazyList<TA;>;>;

  public <A extends java.lang.Object> scala.collection.immutable.LazyList<A> scala$collection$immutable$LazyList$$newLL(scala.Function0<scala.collection.immutable.LazyList$State<A>>);
    descriptor: (Lscala/Function0;)Lscala/collection/immutable/LazyList;
    flags: (0x0001) ACC_PUBLIC
    Code:
      stack=3, locals=2, args_size=2
         0: new           #17                 // class scala/collection/immutable/LazyList
         3: dup
         4: aload_1
         5: invokespecial #73                 // Method scala/collection/immutable/LazyList."<init>":(Lscala/Function0;)V
         8: areturn
      LineNumberTable:
        line 990: 0
      LocalVariableTable:
        Start  Length  Slot  Name   Signature
            0       9     0  this   Lscala/collection/immutable/LazyList$;
            0       9     1 state   Lscala/Function0;
    Signature: #192                         // <A:Ljava/lang/Object;>(Lscala/Function0<Lscala/collection/immutable/LazyList$State<TA;>;>;)Lscala/collection/immutable/LazyList<TA;>;
    MethodParameters:
      Name                           Flags
      state                          final

  public <A extends java.lang.Object> scala.collection.immutable.LazyList$State<A> scala$collection$immutable$LazyList$$sCons(A, scala.collection.immutable.LazyList<A>);
    descriptor: (Ljava/lang/Object;Lscala/collection/immutable/LazyList;)Lscala/collection/immutable/LazyList$State;
    flags: (0x0001) ACC_PUBLIC
    Code:
      stack=4, locals=3, args_size=3
         0: new           #26                 // class scala/collection/immutable/LazyList$State$Cons
         3: dup
         4: aload_1
         5: aload_2
         6: invokespecial #201                // Method scala/collection/immutable/LazyList$State$Cons."<init>":(Ljava/lang/Object;Lscala/collection/immutable/LazyList;)V
         9: areturn
      LineNumberTable:
        line 993: 0
      LocalVariableTable:
        Start  Length  Slot  Name   Signature
            0      10     0  this   Lscala/collection/immutable/LazyList$;
            0      10     1    hd   Ljava/lang/Object;
            0      10     2    tl   Lscala/collection/immutable/LazyList;
    Signature: #196                         // <A:Ljava/lang/Object;>(TA;Lscala/collection/immutable/LazyList<TA;>;)Lscala/collection/immutable/LazyList$State<TA;>;
    MethodParameters:
      Name                           Flags
      hd                             final
      tl                             final

  public scala.Function1<java.lang.Object, java.lang.Object> scala$collection$immutable$LazyList$$anyToMarker();
    descriptor: ()Lscala/Function1;
    flags: (0x0001) ACC_PUBLIC
    Code:
      stack=1, locals=1, args_size=1
         0: getstatic     #90                 // Field scala$collection$immutable$LazyList$$anyToMarker:Lscala/Function1;
         3: areturn
      LineNumberTable:
        line 995: 0
      LocalVariableTable:
        Start  Length  Slot  Name   Signature
            0       4     0  this   Lscala/collection/immutable/LazyList$;
    Signature: #202                         // ()Lscala/Function1<Ljava/lang/Object;Ljava/lang/Object;>;

  public <A extends java.lang.Object> scala.collection.immutable.LazyList<A> scala$collection$immutable$LazyList$$filterImpl(scala.collection.immutable.LazyList<A>, scala.Function1<A, java.lang.Object>, boolean);
    descriptor: (Lscala/collection/immutable/LazyList;Lscala/Function1;Z)Lscala/collection/immutable/LazyList;
    flags: (0x0001) ACC_PUBLIC
    Code:
      stack=3, locals=5, args_size=4
         0: new           #210                // class scala/runtime/ObjectRef
         3: dup
         4: aload_1
         5: invokespecial #213                // Method scala/runtime/ObjectRef."<init>":(Ljava/lang/Object;)V
         8: aload_2
         9: iload_3
        10: invokedynamic #223,  0            // InvokeDynamic #2:apply:(Lscala/runtime/ObjectRef;Lscala/Function1;Z)Lscala/Function0;
        15: astore        4
        17: new           #17                 // class scala/collection/immutable/LazyList
        20: dup
        21: aload         4
        23: invokespecial #73                 // Method scala/collection/immutable/LazyList."<init>":(Lscala/Function0;)V
        26: areturn
      LineNumberTable:
        line 1007: 0
        line 1008: 8
        line 990: 17
        line 1008: 26
      LocalVariableTable:
        Start  Length  Slot  Name   Signature
            0      27     0  this   Lscala/collection/immutable/LazyList$;
            0      27     1    ll   Lscala/collection/immutable/LazyList;
            0      27     2     p   Lscala/Function1;
            0      27     3 isFlipped   Z
           17       9     4 scala$collection$immutable$LazyList$$newLL_state   Lscala/Function0;
    Signature: #205                         // <A:Ljava/lang/Object;>(Lscala/collection/immutable/LazyList<TA;>;Lscala/Function1<TA;Ljava/lang/Object;>;Z)Lscala/collection/immutable/LazyList<TA;>;
    MethodParameters:
      Name                           Flags
      ll                             final
      p                              final
      isFlipped                      final

  public <A extends java.lang.Object, B extends java.lang.Object> scala.collection.immutable.LazyList<B> scala$collection$immutable$LazyList$$collectImpl(scala.collection.immutable.LazyList<A>, scala.PartialFunction<A, B>);
    descriptor: (Lscala/collection/immutable/LazyList;Lscala/PartialFunction;)Lscala/collection/immutable/LazyList;
    flags: (0x0001) ACC_PUBLIC
    Code:
      stack=3, locals=4, args_size=3
         0: new           #210                // class scala/runtime/ObjectRef
         3: dup
         4: aload_1
         5: invokespecial #213                // Method scala/runtime/ObjectRef."<init>":(Ljava/lang/Object;)V
         8: aload_2
         9: invokedynamic #236,  0            // InvokeDynamic #3:apply:(Lscala/runtime/ObjectRef;Lscala/PartialFunction;)Lscala/Function0;
        14: astore_3
        15: new           #17                 // class scala/collection/immutable/LazyList
        18: dup
        19: aload_3
        20: invokespecial #73                 // Method scala/collection/immutable/LazyList."<init>":(Lscala/Function0;)V
        23: areturn
      LineNumberTable:
        line 1024: 0
        line 1025: 8
        line 990: 15
        line 1025: 23
      LocalVariableTable:
        Start  Length  Slot  Name   Signature
            0      24     0  this   Lscala/collection/immutable/LazyList$;
            0      24     1    ll   Lscala/collection/immutable/LazyList;
            0      24     2    pf   Lscala/PartialFunction;
           15       8     3 scala$collection$immutable$LazyList$$newLL_state   Lscala/Function0;
    Signature: #227                         // <A:Ljava/lang/Object;B:Ljava/lang/Object;>(Lscala/collection/immutable/LazyList<TA;>;Lscala/PartialFunction<TA;TB;>;)Lscala/collection/immutable/LazyList<TB;>;
    MethodParameters:
      Name                           Flags
      ll                             final
      pf                             final

  public <A extends java.lang.Object, B extends java.lang.Object> scala.collection.immutable.LazyList<B> scala$collection$immutable$LazyList$$flatMapImpl(scala.collection.immutable.LazyList<A>, scala.Function1<A, scala.collection.IterableOnce<B>>);
    descriptor: (Lscala/collection/immutable/LazyList;Lscala/Function1;)Lscala/collection/immutable/LazyList;
    flags: (0x0001) ACC_PUBLIC
    Code:
      stack=3, locals=4, args_size=3
         0: new           #210                // class scala/runtime/ObjectRef
         3: dup
         4: aload_1
         5: invokespecial #213                // Method scala/runtime/ObjectRef."<init>":(Ljava/lang/Object;)V
         8: aload_2
         9: invokedynamic #248,  0            // InvokeDynamic #4:apply:(Lscala/runtime/ObjectRef;Lscala/Function1;)Lscala/Function0;
        14: astore_3
        15: new           #17                 // class scala/collection/immutable/LazyList
        18: dup
        19: aload_3
        20: invokespecial #73                 // Method scala/collection/immutable/LazyList."<init>":(Lscala/Function0;)V
        23: areturn
      LineNumberTable:
        line 1043: 0
        line 1044: 8
        line 990: 15
        line 1044: 23
      LocalVariableTable:
        Start  Length  Slot  Name   Signature
            0      24     0  this   Lscala/collection/immutable/LazyList$;
            0      24     1    ll   Lscala/collection/immutable/LazyList;
            0      24     2     f   Lscala/Function1;
           15       8     3 scala$collection$immutable$LazyList$$newLL_state   Lscala/Function0;
    Signature: #240                         // <A:Ljava/lang/Object;B:Ljava/lang/Object;>(Lscala/collection/immutable/LazyList<TA;>;Lscala/Function1<TA;Lscala/collection/IterableOnce<TB;>;>;)Lscala/collection/immutable/LazyList<TB;>;
    MethodParameters:
      Name                           Flags
      ll                             final
      f                              final

  public <A extends java.lang.Object> scala.collection.immutable.LazyList<A> scala$collection$immutable$LazyList$$dropImpl(scala.collection.immutable.LazyList<A>, int);
    descriptor: (Lscala/collection/immutable/LazyList;I)Lscala/collection/immutable/LazyList;
    flags: (0x0001) ACC_PUBLIC
    Code:
      stack=3, locals=8, args_size=3
         0: new           #210                // class scala/runtime/ObjectRef
         3: dup
         4: aload_1
         5: invokespecial #213                // Method scala/runtime/ObjectRef."<init>":(Ljava/lang/Object;)V
         8: astore        6
        10: aload         6
        12: aconst_null
        13: astore        6
        15: astore_3
        16: new           #254                // class scala/runtime/IntRef
        19: dup
        20: iload_2
        21: invokespecial #257                // Method scala/runtime/IntRef."<init>":(I)V
        24: astore        7
        26: aload         7
        28: aconst_null
        29: astore        7
        31: astore        4
        33: aload_3
        34: aload         4
        36: invokedynamic #265,  0            // InvokeDynamic #5:apply:(Lscala/runtime/ObjectRef;Lscala/runtime/IntRef;)Lscala/Function0;
        41: astore        5
        43: new           #17                 // class scala/collection/immutable/LazyList
        46: dup
        47: aload         5
        49: invokespecial #73                 // Method scala/collection/immutable/LazyList."<init>":(Lscala/Function0;)V
        52: areturn
      LineNumberTable:
        line 1067: 0
        line 1068: 16
        line 1069: 33
        line 990: 43
        line 1069: 52
      LocalVariableTable:
        Start  Length  Slot  Name   Signature
           16      36     3 restRef   Lscala/runtime/ObjectRef;
           33      19     4  iRef   Lscala/runtime/IntRef;
            0      53     0  this   Lscala/collection/immutable/LazyList$;
            0      53     1    ll   Lscala/collection/immutable/LazyList;
            0      53     2     n   I
           43       9     5 scala$collection$immutable$LazyList$$newLL_state   Lscala/Function0;
    Signature: #251                         // <A:Ljava/lang/Object;>(Lscala/collection/immutable/LazyList<TA;>;I)Lscala/collection/immutable/LazyList<TA;>;
    MethodParameters:
      Name                           Flags
      ll                             final
      n                              final

  public <A extends java.lang.Object> scala.collection.immutable.LazyList<A> scala$collection$immutable$LazyList$$dropWhileImpl(scala.collection.immutable.LazyList<A>, scala.Function1<A, java.lang.Object>);
    descriptor: (Lscala/collection/immutable/LazyList;Lscala/Function1;)Lscala/collection/immutable/LazyList;
    flags: (0x0001) ACC_PUBLIC
    Code:
      stack=3, locals=4, args_size=3
         0: new           #210                // class scala/runtime/ObjectRef
         3: dup
         4: aload_1
         5: invokespecial #213                // Method scala/runtime/ObjectRef."<init>":(Ljava/lang/Object;)V
         8: aload_2
         9: invokedynamic #276,  0            // InvokeDynamic #6:apply:(Lscala/runtime/ObjectRef;Lscala/Function1;)Lscala/Function0;
        14: astore_3
        15: new           #17                 // class scala/collection/immutable/LazyList
        18: dup
        19: aload_3
        20: invokespecial #73                 // Method scala/collection/immutable/LazyList."<init>":(Lscala/Function0;)V
        23: areturn
      LineNumberTable:
        line 1084: 0
        line 1085: 8
        line 990: 15
        line 1085: 23
      LocalVariableTable:
        Start  Length  Slot  Name   Signature
            0      24     0  this   Lscala/collection/immutable/LazyList$;
            0      24     1    ll   Lscala/collection/immutable/LazyList;
            0      24     2     p   Lscala/Function1;
           15       8     3 scala$collection$immutable$LazyList$$newLL_state   Lscala/Function0;
    Signature: #271                         // <A:Ljava/lang/Object;>(Lscala/collection/immutable/LazyList<TA;>;Lscala/Function1<TA;Ljava/lang/Object;>;)Lscala/collection/immutable/LazyList<TA;>;
    MethodParameters:
      Name                           Flags
      ll                             final
      p                              final

  public <A extends java.lang.Object> scala.collection.immutable.LazyList<A> scala$collection$immutable$LazyList$$takeRightImpl(scala.collection.immutable.LazyList<A>, int);
    descriptor: (Lscala/collection/immutable/LazyList;I)Lscala/collection/immutable/LazyList;
    flags: (0x0001) ACC_PUBLIC
    Code:
      stack=3, locals=10, args_size=3
         0: new           #210                // class scala/runtime/ObjectRef
         3: dup
         4: aload_1
         5: invokespecial #213                // Method scala/runtime/ObjectRef."<init>":(Ljava/lang/Object;)V
         8: astore        7
        10: aload         7
        12: aconst_null
        13: astore        7
        15: astore_3
        16: new           #210                // class scala/runtime/ObjectRef
        19: dup
        20: aload_1
        21: invokespecial #213                // Method scala/runtime/ObjectRef."<init>":(Ljava/lang/Object;)V
        24: astore        8
        26: aload         8
        28: aconst_null
        29: astore        8
        31: astore        4
        33: new           #254                // class scala/runtime/IntRef
        36: dup
        37: iload_2
        38: invokespecial #257                // Method scala/runtime/IntRef."<init>":(I)V
        41: astore        9
        43: aload         9
        45: aconst_null
        46: astore        9
        48: astore        5
        50: aload         4
        52: aload         5
        54: aload_3
        55: invokedynamic #285,  0            // InvokeDynamic #7:apply:(Lscala/runtime/ObjectRef;Lscala/runtime/IntRef;Lscala/runtime/ObjectRef;)Lscala/Function0;
        60: astore        6
        62: new           #17                 // class scala/collection/immutable/LazyList
        65: dup
        66: aload         6
        68: invokespecial #73                 // Method scala/collection/immutable/LazyList."<init>":(Lscala/Function0;)V
        71: areturn
      LineNumberTable:
        line 1097: 0
        line 1098: 16
        line 1099: 33
        line 1100: 50
        line 990: 62
        line 1100: 71
      LocalVariableTable:
        Start  Length  Slot  Name   Signature
           16      55     3 restRef   Lscala/runtime/ObjectRef;
           33      38     4 scoutRef   Lscala/runtime/ObjectRef;
           50      21     5 remainingRef   Lscala/runtime/IntRef;
            0      72     0  this   Lscala/collection/immutable/LazyList$;
            0      72     1    ll   Lscala/collection/immutable/LazyList;
            0      72     2     n   I
           62       9     6 scala$collection$immutable$LazyList$$newLL_state   Lscala/Function0;
    Signature: #251                         // <A:Ljava/lang/Object;>(Lscala/collection/immutable/LazyList<TA;>;I)Lscala/collection/immutable/LazyList<TA;>;
    MethodParameters:
      Name                           Flags
      ll                             final
      n                              final

  public <A extends java.lang.Object> scala.Function0<scala.collection.immutable.LazyList<A>> toDeferrer(scala.Function0<scala.collection.immutable.LazyList<A>>);
    descriptor: (Lscala/Function0;)Lscala/Function0;
    flags: (0x0001) ACC_PUBLIC
    Code:
      stack=1, locals=2, args_size=2
         0: aload_1
         1: areturn
      LineNumberTable:
        line 1136: 0
      LocalVariableTable:
        Start  Length  Slot  Name   Signature
            0       2     0  this   Lscala/collection/immutable/LazyList$;
            0       2     1     l   Lscala/Function0;
    Signature: #290                         // <A:Ljava/lang/Object;>(Lscala/Function0<Lscala/collection/immutable/LazyList<TA;>;>;)Lscala/Function0<Lscala/collection/immutable/LazyList<TA;>;>;
    MethodParameters:
      Name                           Flags
      l                              final

  public <A extends java.lang.Object> scala.collection.immutable.LazyList<A> from(scala.collection.IterableOnce<A>);
    descriptor: (Lscala/collection/IterableOnce;)Lscala/collection/immutable/LazyList;
    flags: (0x0001) ACC_PUBLIC
    Code:
      stack=3, locals=4, args_size=2
         0: aload_1
         1: instanceof    #17                 // class scala/collection/immutable/LazyList
         4: ifeq          15
         7: aload_1
         8: checkcast     #17                 // class scala/collection/immutable/LazyList
        11: astore_2
        12: goto          49
        15: aload_1
        16: invokeinterface #301,  1          // InterfaceMethod scala/collection/IterableOnce.knownSize:()I
        21: iconst_0
        22: if_icmpne     33
        25: aload_0
        26: invokevirtual #304                // Method empty:()Lscala/collection/immutable/LazyList;
        29: astore_2
        30: goto          49
        33: aload_1
        34: invokedynamic #312,  0            // InvokeDynamic #8:apply:(Lscala/collection/IterableOnce;)Lscala/Function0;
        39: astore_3
        40: new           #17                 // class scala/collection/immutable/LazyList
        43: dup
        44: aload_3
        45: invokespecial #73                 // Method scala/collection/immutable/LazyList."<init>":(Lscala/Function0;)V
        48: astore_2
        49: aload_2
        50: areturn
      StackMapTable: number_of_entries = 3
        frame_type = 15 /* same */
        frame_type = 17 /* same */
        frame_type = 252 /* append */
          offset_delta = 15
          locals = [ class scala/collection/immutable/LazyList ]
      LineNumberTable:
        line 1155: 0
        line 1156: 15
        line 1157: 33
        line 990: 40
        line 1157: 48
        line 1154: 49
      LocalVariableTable:
        Start  Length  Slot  Name   Signature
            0      51     0  this   Lscala/collection/immutable/LazyList$;
            0      51     1  coll   Lscala/collection/IterableOnce;
           40       8     3 scala$collection$immutable$LazyList$$newLL_state   Lscala/Function0;
    Signature: #294                         // <A:Ljava/lang/Object;>(Lscala/collection/IterableOnce<TA;>;)Lscala/collection/immutable/LazyList<TA;>;
    MethodParameters:
      Name                           Flags
      coll                           final

  public <A extends java.lang.Object> scala.collection.immutable.LazyList<A> empty();
    descriptor: ()Lscala/collection/immutable/LazyList;
    flags: (0x0001) ACC_PUBLIC
    Code:
      stack=1, locals=1, args_size=1
         0: getstatic     #79                 // Field _empty:Lscala/collection/immutable/LazyList;
         3: areturn
      LineNumberTable:
        line 1160: 0
      LocalVariableTable:
        Start  Length  Slot  Name   Signature
            0       4     0  this   Lscala/collection/immutable/LazyList$;
    Signature: #314                         // <A:Ljava/lang/Object;>()Lscala/collection/immutable/LazyList<TA;>;

  public <A extends java.lang.Object> scala.collection.immutable.LazyList$State<A> scala$collection$immutable$LazyList$$stateFromIteratorConcatSuffix(scala.collection.Iterator<A>, scala.Function0<scala.collection.immutable.LazyList$State<A>>);
    descriptor: (Lscala/collection/Iterator;Lscala/Function0;)Lscala/collection/immutable/LazyList$State;
    flags: (0x0001) ACC_PUBLIC
    Code:
      stack=4, locals=7, args_size=3
         0: aload_1
         1: invokeinterface #325,  1          // InterfaceMethod scala/collection/Iterator.hasNext:()Z
         6: ifeq          56
         9: aload_1
        10: invokeinterface #328,  1          // InterfaceMethod scala/collection/Iterator.next:()Ljava/lang/Object;
        15: aload_1
        16: aload_2
        17: invokedynamic #335,  0            // InvokeDynamic #9:apply:(Lscala/collection/Iterator;Lscala/Function0;)Lscala/Function0;
        22: astore_3
        23: new           #17                 // class scala/collection/immutable/LazyList
        26: dup
        27: aload_3
        28: invokespecial #73                 // Method scala/collection/immutable/LazyList."<init>":(Lscala/Function0;)V
        31: astore        4
        33: aload         4
        35: aconst_null
        36: astore_3
        37: aconst_null
        38: astore        4
        40: astore        6
        42: astore        5
        44: new           #26                 // class scala/collection/immutable/LazyList$State$Cons
        47: dup
        48: aload         5
        50: aload         6
        52: invokespecial #201                // Method scala/collection/immutable/LazyList$State$Cons."<init>":(Ljava/lang/Object;Lscala/collection/immutable/LazyList;)V
        55: areturn
        56: aload_2
        57: invokeinterface #339,  1          // InterfaceMethod scala/Function0.apply:()Ljava/lang/Object;
        62: checkcast     #20                 // class scala/collection/immutable/LazyList$State
        65: areturn
      StackMapTable: number_of_entries = 1
        frame_type = 56 /* same */
      LineNumberTable:
        line 1166: 0
        line 990: 23
        line 1166: 33
        line 993: 44
        line 1166: 55
        line 1167: 56
      LocalVariableTable:
        Start  Length  Slot  Name   Signature
            0      66     0  this   Lscala/collection/immutable/LazyList$;
            0      66     1    it   Lscala/collection/Iterator;
            0      66     2 suffix   Lscala/Function0;
           23      10     3 scala$collection$immutable$LazyList$$newLL_state   Lscala/Function0;
           44      11     5 scala$collection$immutable$LazyList$$sCons_hd   Ljava/lang/Object;
           44      11     6 scala$collection$immutable$LazyList$$sCons_tl   Lscala/collection/immutable/LazyList;
    Signature: #317                         // <A:Ljava/lang/Object;>(Lscala/collection/Iterator<TA;>;Lscala/Function0<Lscala/collection/immutable/LazyList$State<TA;>;>;)Lscala/collection/immutable/LazyList$State<TA;>;
    MethodParameters:
      Name                           Flags
      it                             final
      suffix                         final

  public <A extends java.lang.Object> scala.collection.immutable.LazyList$State<A> scala$collection$immutable$LazyList$$stateFromIterator(scala.collection.Iterator<A>);
    descriptor: (Lscala/collection/Iterator;)Lscala/collection/immutable/LazyList$State;
    flags: (0x0001) ACC_PUBLIC
    Code:
      stack=4, locals=6, args_size=2
         0: aload_1
         1: invokeinterface #325,  1          // InterfaceMethod scala/collection/Iterator.hasNext:()Z
         6: ifeq          52
         9: aload_1
        10: invokeinterface #328,  1          // InterfaceMethod scala/collection/Iterator.next:()Ljava/lang/Object;
        15: aload_1
        16: invokedynamic #352,  0            // InvokeDynamic #10:apply:(Lscala/collection/Iterator;)Lscala/Function0;
        21: astore_2
        22: new           #17                 // class scala/collection/immutable/LazyList
        25: dup
        26: aload_2
        27: invokespecial #73                 // Method scala/collection/immutable/LazyList."<init>":(Lscala/Function0;)V
        30: astore_3
        31: aload_3
        32: aconst_null
        33: astore_2
        34: aconst_null
        35: astore_3
        36: astore        5
        38: astore        4
        40: new           #26                 // class scala/collection/immutable/LazyList$State$Cons
        43: dup
        44: aload         4
        46: aload         5
        48: invokespecial #201                // Method scala/collection/immutable/LazyList$State$Cons."<init>":(Ljava/lang/Object;Lscala/collection/immutable/LazyList;)V
        51: areturn
        52: getstatic     #355                // Field scala/collection/immutable/LazyList$State$Empty$.MODULE$:Lscala/collection/immutable/LazyList$State$Empty$;
        55: areturn
      StackMapTable: number_of_entries = 1
        frame_type = 52 /* same */
      LineNumberTable:
        line 1171: 0
        line 990: 22
        line 1171: 31
        line 993: 40
        line 1171: 51
        line 1172: 52
      LocalVariableTable:
        Start  Length  Slot  Name   Signature
            0      56     0  this   Lscala/collection/immutable/LazyList$;
            0      56     1    it   Lscala/collection/Iterator;
           22       9     2 scala$collection$immutable$LazyList$$newLL_state   Lscala/Function0;
           40      11     4 scala$collection$immutable$LazyList$$sCons_hd   Ljava/lang/Object;
           40      11     5 scala$collection$immutable$LazyList$$sCons_tl   Lscala/collection/immutable/LazyList;
    Signature: #345                         // <A:Ljava/lang/Object;>(Lscala/collection/Iterator<TA;>;)Lscala/collection/immutable/LazyList$State<TA;>;
    MethodParameters:
      Name                           Flags
      it                             final

  public <A extends java.lang.Object> scala.collection.immutable.LazyList<A> concat(scala.collection.immutable.Seq<scala.collection.Iterable<A>>);
    descriptor: (Lscala/collection/immutable/Seq;)Lscala/collection/immutable/LazyList;
    flags: (0x0001) ACC_PUBLIC
    Code:
      stack=3, locals=3, args_size=2
         0: aload_1
         1: invokeinterface #362,  1          // InterfaceMethod scala/collection/immutable/Seq.knownSize:()I
         6: iconst_0
         7: if_icmpne     15
        10: aload_0
        11: invokevirtual #304                // Method empty:()Lscala/collection/immutable/LazyList;
        14: areturn
        15: aload_1
        16: invokedynamic #370,  0            // InvokeDynamic #11:apply:(Lscala/collection/immutable/Seq;)Lscala/Function0;
        21: astore_2
        22: new           #17                 // class scala/collection/immutable/LazyList
        25: dup
        26: aload_2
        27: invokespecial #73                 // Method scala/collection/immutable/LazyList."<init>":(Lscala/Function0;)V
        30: areturn
      StackMapTable: number_of_entries = 1
        frame_type = 15 /* same */
      LineNumberTable:
        line 1175: 0
        line 1176: 15
        line 990: 22
        line 1176: 30
      LocalVariableTable:
        Start  Length  Slot  Name   Signature
            0      31     0  this   Lscala/collection/immutable/LazyList$;
            0      31     1   xss   Lscala/collection/immutable/Seq;
           22       8     2 scala$collection$immutable$LazyList$$newLL_state   Lscala/Function0;
    Signature: #358                         // <A:Ljava/lang/Object;>(Lscala/collection/immutable/Seq<Lscala/collection/Iterable<TA;>;>;)Lscala/collection/immutable/LazyList<TA;>;
    MethodParameters:
      Name                           Flags
      xss                            final

  private <A extends java.lang.Object> scala.collection.immutable.LazyList$State<A> concatIterator(scala.collection.Iterator<scala.collection.Iterable<A>>);
    descriptor: (Lscala/collection/Iterator;)Lscala/collection/immutable/LazyList$State;
    flags: (0x0002) ACC_PRIVATE
    Code:
      stack=4, locals=8, args_size=2
         0: aload_1
         1: invokeinterface #325,  1          // InterfaceMethod scala/collection/Iterator.hasNext:()Z
         6: ifne          13
         9: getstatic     #355                // Field scala/collection/immutable/LazyList$State$Empty$.MODULE$:Lscala/collection/immutable/LazyList$State$Empty$;
        12: areturn
        13: aload_1
        14: invokeinterface #328,  1          // InterfaceMethod scala/collection/Iterator.next:()Ljava/lang/Object;
        19: checkcast     #297                // class scala/collection/IterableOnce
        22: invokeinterface #376,  1          // InterfaceMethod scala/collection/IterableOnce.iterator:()Lscala/collection/Iterator;
        27: aload_1
        28: invokedynamic #381,  0            // InvokeDynamic #12:apply:(Lscala/collection/Iterator;)Lscala/Function0;
        33: astore_3
        34: astore_2
        35: aload_2
        36: invokeinterface #325,  1          // InterfaceMethod scala/collection/Iterator.hasNext:()Z
        41: ifeq          100
        44: aload_2
        45: invokeinterface #328,  1          // InterfaceMethod scala/collection/Iterator.next:()Ljava/lang/Object;
        50: aload_2
        51: aload_3
        52: invokedynamic #335,  0            // InvokeDynamic #9:apply:(Lscala/collection/Iterator;Lscala/Function0;)Lscala/Function0;
        57: astore        4
        59: new           #17                 // class scala/collection/immutable/LazyList
        62: dup
        63: aload         4
        65: invokespecial #73                 // Method scala/collection/immutable/LazyList."<init>":(Lscala/Function0;)V
        68: astore        5
        70: aload         5
        72: aconst_null
        73: astore        4
        75: aconst_null
        76: astore        5
        78: astore        7
        80: astore        6
        82: new           #26                 // class scala/collection/immutable/LazyList$State$Cons
        85: dup
        86: aload         6
        88: aload         7
        90: invokespecial #201                // Method scala/collection/immutable/LazyList$State$Cons."<init>":(Ljava/lang/Object;Lscala/collection/immutable/LazyList;)V
        93: aconst_null
        94: astore        6
        96: aconst_null
        97: astore        7
        99: areturn
       100: aload_1
       101: invokestatic  #379                // Method $anonfun$concatIterator$1:(Lscala/collection/Iterator;)Lscala/collection/immutable/LazyList$State;
       104: areturn
      StackMapTable: number_of_entries = 2
        frame_type = 13 /* same */
        frame_type = 253 /* append */
          offset_delta = 86
          locals = [ class scala/collection/Iterator, class scala/Function0 ]
      LineNumberTable:
        line 1179: 0
        line 1180: 13
        line 1166: 35
        line 990: 59
        line 1166: 70
        line 993: 82
        line 1166: 93
        line 1167: 100
        line 1180: 104
      LocalVariableTable:
        Start  Length  Slot  Name   Signature
            0     105     0  this   Lscala/collection/immutable/LazyList$;
            0     105     1    it   Lscala/collection/Iterator;
           35      69     2 scala$collection$immutable$LazyList$$stateFromIteratorConcatSuffix_it   Lscala/collection/Iterator;
           35      69     3 scala$collection$immutable$LazyList$$stateFromIteratorConcatSuffix_suffix   Lscala/Function0;
           59      11     4 scala$collection$immutable$LazyList$$stateFromIteratorConcatSuffix_scala$collection$immutable$LazyList$$newLL_state   Lscala/Function0;
           82      11     6 scala$collection$immutable$LazyList$$stateFromIteratorConcatSuffix_scala$collection$immutable$LazyList$$sCons_hd   Ljava/lang/Object;
           82      11     7 scala$collection$immutable$LazyList$$stateFromIteratorConcatSuffix_scala$collection$immutable$LazyList$$sCons_tl   Lscala/collection/immutable/LazyList;
    Signature: #372                         // <A:Ljava/lang/Object;>(Lscala/collection/Iterator<Lscala/collection/Iterable<TA;>;>;)Lscala/collection/immutable/LazyList$State<TA;>;
    MethodParameters:
      Name                           Flags
      it                             final

  public <A extends java.lang.Object> scala.collection.immutable.LazyList<A> iterate(scala.Function0<A>, scala.Function1<A, A>);
    descriptor: (Lscala/Function0;Lscala/Function1;)Lscala/collection/immutable/LazyList;
    flags: (0x0001) ACC_PUBLIC
    Code:
      stack=3, locals=4, args_size=3
         0: aload_1
         1: aload_2
         2: invokedynamic #396,  0            // InvokeDynamic #13:apply:(Lscala/Function0;Lscala/Function1;)Lscala/Function0;
         7: astore_3
         8: new           #17                 // class scala/collection/immutable/LazyList
        11: dup
        12: aload_3
        13: invokespecial #73                 // Method scala/collection/immutable/LazyList."<init>":(Lscala/Function0;)V
        16: areturn
      LineNumberTable:
        line 1189: 0
        line 990: 8
        line 1189: 16
      LocalVariableTable:
        Start  Length  Slot  Name   Signature
            0      17     0  this   Lscala/collection/immutable/LazyList$;
            0      17     1 start   Lscala/Function0;
            0      17     2     f   Lscala/Function1;
            8       8     3 scala$collection$immutable$LazyList$$newLL_state   Lscala/Function0;
    Signature: #388                         // <A:Ljava/lang/Object;>(Lscala/Function0<TA;>;Lscala/Function1<TA;TA;>;)Lscala/collection/immutable/LazyList<TA;>;
    MethodParameters:
      Name                           Flags
      start                          final
      f                              final

  public scala.collection.immutable.LazyList<java.lang.Object> from(int, int);
    descriptor: (II)Lscala/collection/immutable/LazyList;
    flags: (0x0001) ACC_PUBLIC
    Code:
      stack=3, locals=4, args_size=3
         0: iload_1
         1: iload_2
         2: invokedynamic #406,  0            // InvokeDynamic #14:apply:(II)Lscala/Function0;
         7: astore_3
         8: new           #17                 // class scala/collection/immutable/LazyList
        11: dup
        12: aload_3
        13: invokespecial #73                 // Method scala/collection/immutable/LazyList."<init>":(Lscala/Function0;)V
        16: areturn
      LineNumberTable:
        line 1203: 0
        line 990: 8
        line 1203: 16
      LocalVariableTable:
        Start  Length  Slot  Name   Signature
            0      17     0  this   Lscala/collection/immutable/LazyList$;
            0      17     1 start   I
            0      17     2  step   I
            8       8     3 scala$collection$immutable$LazyList$$newLL_state   Lscala/Function0;
    Signature: #398                         // (II)Lscala/collection/immutable/LazyList<Ljava/lang/Object;>;
    MethodParameters:
      Name                           Flags
      start                          final
      step                           final

  public scala.collection.immutable.LazyList<java.lang.Object> from(int);
    descriptor: (I)Lscala/collection/immutable/LazyList;
    flags: (0x0001) ACC_PUBLIC
    Code:
      stack=3, locals=2, args_size=2
         0: aload_0
         1: iload_1
         2: iconst_1
         3: invokevirtual #410                // Method from:(II)Lscala/collection/immutable/LazyList;
         6: areturn
      LineNumberTable:
        line 1211: 0
      LocalVariableTable:
        Start  Length  Slot  Name   Signature
            0       7     0  this   Lscala/collection/immutable/LazyList$;
            0       7     1 start   I
    Signature: #408                         // (I)Lscala/collection/immutable/LazyList<Ljava/lang/Object;>;
    MethodParameters:
      Name                           Flags
      start                          final

  public <A extends java.lang.Object> scala.collection.immutable.LazyList<A> continually(scala.Function0<A>);
    descriptor: (Lscala/Function0;)Lscala/collection/immutable/LazyList;
    flags: (0x0001) ACC_PUBLIC
    Code:
      stack=3, locals=3, args_size=2
         0: aload_1
         1: invokedynamic #419,  0            // InvokeDynamic #15:apply:(Lscala/Function0;)Lscala/Function0;
         6: astore_2
         7: new           #17                 // class scala/collection/immutable/LazyList
        10: dup
        11: aload_2
        12: invokespecial #73                 // Method scala/collection/immutable/LazyList."<init>":(Lscala/Function0;)V
        15: areturn
      LineNumberTable:
        line 1220: 0
        line 990: 7
        line 1220: 15
      LocalVariableTable:
        Start  Length  Slot  Name   Signature
            0      16     0  this   Lscala/collection/immutable/LazyList$;
            0      16     1  elem   Lscala/Function0;
            7       8     2 scala$collection$immutable$LazyList$$newLL_state   Lscala/Function0;
    Signature: #412                         // <A:Ljava/lang/Object;>(Lscala/Function0<TA;>;)Lscala/collection/immutable/LazyList<TA;>;
    MethodParameters:
      Name                           Flags
      elem                           final

  public <A extends java.lang.Object> scala.collection.immutable.LazyList<A> fill(int, scala.Function0<A>);
    descriptor: (ILscala/Function0;)Lscala/collection/immutable/LazyList;
    flags: (0x0001) ACC_PUBLIC
    Code:
      stack=3, locals=4, args_size=3
         0: iload_1
         1: iconst_0
         2: if_icmple     22
         5: aload_2
         6: iload_1
         7: invokedynamic #429,  0            // InvokeDynamic #16:apply:(Lscala/Function0;I)Lscala/Function0;
        12: astore_3
        13: new           #17                 // class scala/collection/immutable/LazyList
        16: dup
        17: aload_3
        18: invokespecial #73                 // Method scala/collection/immutable/LazyList."<init>":(Lscala/Function0;)V
        21: areturn
        22: aload_0
        23: invokevirtual #304                // Method empty:()Lscala/collection/immutable/LazyList;
        26: areturn
      StackMapTable: number_of_entries = 1
        frame_type = 22 /* same */
      LineNumberTable:
        line 1223: 0
        line 990: 13
        line 1223: 21
      LocalVariableTable:
        Start  Length  Slot  Name   Signature
            0      27     0  this   Lscala/collection/immutable/LazyList$;
            0      27     1     n   I
            0      27     2  elem   Lscala/Function0;
           13       8     3 scala$collection$immutable$LazyList$$newLL_state   Lscala/Function0;
    Signature: #421                         // <A:Ljava/lang/Object;>(ILscala/Function0<TA;>;)Lscala/collection/immutable/LazyList<TA;>;
    MethodParameters:
      Name                           Flags
      n                              final
      elem                           final

  public <A extends java.lang.Object> scala.collection.immutable.LazyList<A> tabulate(int, scala.Function1<java.lang.Object, A>);
    descriptor: (ILscala/Function1;)Lscala/collection/immutable/LazyList;
    flags: (0x0001) ACC_PUBLIC
    Code:
      stack=4, locals=5, args_size=3
         0: iconst_0
         1: istore_3
         2: iload_3
         3: iload_1
         4: if_icmpge     31
         7: aload_0
         8: aload_2
         9: iload_3
        10: iload_1
        11: invokedynamic #439,  0            // InvokeDynamic #17:apply:(Lscala/collection/immutable/LazyList$;Lscala/Function1;II)Lscala/Function0;
        16: astore        4
        18: new           #17                 // class scala/collection/immutable/LazyList
        21: dup
        22: aload         4
        24: invokespecial #73                 // Method scala/collection/immutable/LazyList."<init>":(Lscala/Function0;)V
        27: aconst_null
        28: astore        4
        30: areturn
        31: aload_0
        32: invokevirtual #304                // Method empty:()Lscala/collection/immutable/LazyList;
        35: areturn
      StackMapTable: number_of_entries = 1
        frame_type = 252 /* append */
          offset_delta = 31
          locals = [ int ]
      LineNumberTable:
        line 1229: 0
        line 1227: 2
        line 990: 18
        line 1227: 27
        line 1229: 35
      LocalVariableTable:
        Start  Length  Slot  Name   Signature
            0      36     0  this   Lscala/collection/immutable/LazyList$;
            0      36     1     n   I
            0      36     2     f   Lscala/Function1;
            2      33     3 at$1_index   I
           18       9     4 at$1_scala$collection$immutable$LazyList$$newLL_state   Lscala/Function0;
    Signature: #431                         // <A:Ljava/lang/Object;>(ILscala/Function1<Ljava/lang/Object;TA;>;)Lscala/collection/immutable/LazyList<TA;>;
    MethodParameters:
      Name                           Flags
      n                              final
      f                              final

  public <A extends java.lang.Object, S extends java.lang.Object> scala.collection.immutable.LazyList<A> unfold(S, scala.Function1<S, scala.Option<scala.Tuple2<A, S>>>);
    descriptor: (Ljava/lang/Object;Lscala/Function1;)Lscala/collection/immutable/LazyList;
    flags: (0x0001) ACC_PUBLIC
    Code:
      stack=3, locals=4, args_size=3
         0: aload_2
         1: aload_1
         2: invokedynamic #453,  0            // InvokeDynamic #18:apply:(Lscala/Function1;Ljava/lang/Object;)Lscala/Function0;
         7: astore_3
         8: new           #17                 // class scala/collection/immutable/LazyList
        11: dup
        12: aload_3
        13: invokespecial #73                 // Method scala/collection/immutable/LazyList."<init>":(Lscala/Function0;)V
        16: areturn
      LineNumberTable:
        line 1235: 0
        line 990: 8
        line 1235: 16
      LocalVariableTable:
        Start  Length  Slot  Name   Signature
            0      17     0  this   Lscala/collection/immutable/LazyList$;
            0      17     1  init   Ljava/lang/Object;
            0      17     2     f   Lscala/Function1;
            8       8     3 scala$collection$immutable$LazyList$$newLL_state   Lscala/Function0;
    Signature: #444                         // <A:Ljava/lang/Object;S:Ljava/lang/Object;>(TS;Lscala/Function1<TS;Lscala/Option<Lscala/Tuple2<TA;TS;>;>;>;)Lscala/collection/immutable/LazyList<TA;>;
    MethodParameters:
      Name                           Flags
      init                           final
      f                              final

  public <A extends java.lang.Object> scala.collection.mutable.Builder<A, scala.collection.immutable.LazyList<A>> newBuilder();
    descriptor: ()Lscala/collection/mutable/Builder;
    flags: (0x0001) ACC_PUBLIC
    Code:
      stack=2, locals=1, args_size=1
         0: new           #15                 // class scala/collection/immutable/LazyList$LazyBuilder
         3: dup
         4: invokespecial #457                // Method scala/collection/immutable/LazyList$LazyBuilder."<init>":()V
         7: areturn
      LineNumberTable:
        line 1247: 0
      LocalVariableTable:
        Start  Length  Slot  Name   Signature
            0       8     0  this   Lscala/collection/immutable/LazyList$;
    Signature: #456                         // <A:Ljava/lang/Object;>()Lscala/collection/mutable/Builder<TA;Lscala/collection/immutable/LazyList<TA;>;>;

  private java.lang.Object writeReplace();
    descriptor: ()Ljava/lang/Object;
    flags: (0x0002) ACC_PRIVATE
    Code:
      stack=3, locals=1, args_size=1
         0: new           #460                // class scala/runtime/ModuleSerializationProxy
         3: dup
         4: ldc           #2                  // class scala/collection/immutable/LazyList$
         6: invokespecial #463                // Method scala/runtime/ModuleSerializationProxy."<init>":(Ljava/lang/Class;)V
         9: areturn
      LineNumberTable:
        line 969: 0
      LocalVariableTable:
        Start  Length  Slot  Name   Signature
            0      10     0  this   Lscala/collection/immutable/LazyList$;

  public java.lang.Object unfold(java.lang.Object, scala.Function1);
    descriptor: (Ljava/lang/Object;Lscala/Function1;)Ljava/lang/Object;
    flags: (0x1041) ACC_PUBLIC, ACC_BRIDGE, ACC_SYNTHETIC
    Code:
      stack=3, locals=3, args_size=3
         0: aload_0
         1: aload_1
         2: aload_2
         3: invokevirtual #466                // Method unfold:(Ljava/lang/Object;Lscala/Function1;)Lscala/collection/immutable/LazyList;
         6: areturn
      LineNumberTable:
        line 969: 0
      LocalVariableTable:
        Start  Length  Slot  Name   Signature
            0       7     0  this   Lscala/collection/immutable/LazyList$;
            0       7     1  init   Ljava/lang/Object;
            0       7     2     f   Lscala/Function1;
    MethodParameters:
      Name                           Flags
      init                           final
      f                              final

  public java.lang.Object tabulate(int, scala.Function1);
    descriptor: (ILscala/Function1;)Ljava/lang/Object;
    flags: (0x1041) ACC_PUBLIC, ACC_BRIDGE, ACC_SYNTHETIC
    Code:
      stack=3, locals=3, args_size=3
         0: aload_0
         1: iload_1
         2: aload_2
         3: invokevirtual #469                // Method tabulate:(ILscala/Function1;)Lscala/collection/immutable/LazyList;
         6: areturn
      LineNumberTable:
        line 969: 0
      LocalVariableTable:
        Start  Length  Slot  Name   Signature
            0       7     0  this   Lscala/collection/immutable/LazyList$;
            0       7     1     n   I
            0       7     2     f   Lscala/Function1;
    MethodParameters:
      Name                           Flags
      n                              final
      f                              final

  public java.lang.Object fill(int, scala.Function0);
    descriptor: (ILscala/Function0;)Ljava/lang/Object;
    flags: (0x1041) ACC_PUBLIC, ACC_BRIDGE, ACC_SYNTHETIC
    Code:
      stack=3, locals=3, args_size=3
         0: aload_0
         1: iload_1
         2: aload_2
         3: invokevirtual #472                // Method fill:(ILscala/Function0;)Lscala/collection/immutable/LazyList;
         6: areturn
      LineNumberTable:
        line 969: 0
      LocalVariableTable:
        Start  Length  Slot  Name   Signature
            0       7     0  this   Lscala/collection/immutable/LazyList$;
            0       7     1     n   I
            0       7     2  elem   Lscala/Function0;
    MethodParameters:
      Name                           Flags
      n                              final
      elem                           final

  public java.lang.Object concat(scala.collection.immutable.Seq);
    descriptor: (Lscala/collection/immutable/Seq;)Ljava/lang/Object;
    flags: (0x1041) ACC_PUBLIC, ACC_BRIDGE, ACC_SYNTHETIC
    Code:
      stack=2, locals=2, args_size=2
         0: aload_0
         1: aload_1
         2: invokevirtual #474                // Method concat:(Lscala/collection/immutable/Seq;)Lscala/collection/immutable/LazyList;
         5: areturn
      LineNumberTable:
        line 969: 0
      LocalVariableTable:
        Start  Length  Slot  Name   Signature
            0       6     0  this   Lscala/collection/immutable/LazyList$;
            0       6     1   xss   Lscala/collection/immutable/Seq;
    MethodParameters:
      Name                           Flags
      xss                            final

  public java.lang.Object empty();
    descriptor: ()Ljava/lang/Object;
    flags: (0x1041) ACC_PUBLIC, ACC_BRIDGE, ACC_SYNTHETIC
    Code:
      stack=1, locals=1, args_size=1
         0: aload_0
         1: invokevirtual #304                // Method empty:()Lscala/collection/immutable/LazyList;
         4: areturn
      LineNumberTable:
        line 969: 0
      LocalVariableTable:
        Start  Length  Slot  Name   Signature
            0       5     0  this   Lscala/collection/immutable/LazyList$;

  public java.lang.Object from(scala.collection.IterableOnce);
    descriptor: (Lscala/collection/IterableOnce;)Ljava/lang/Object;
    flags: (0x1041) ACC_PUBLIC, ACC_BRIDGE, ACC_SYNTHETIC
    Code:
      stack=2, locals=2, args_size=2
         0: aload_0
         1: aload_1
         2: invokevirtual #478                // Method from:(Lscala/collection/IterableOnce;)Lscala/collection/immutable/LazyList;
         5: areturn
      LineNumberTable:
        line 969: 0
      LocalVariableTable:
        Start  Length  Slot  Name   Signature
            0       6     0  this   Lscala/collection/immutable/LazyList$;
            0       6     1 source   Lscala/collection/IterableOnce;
    MethodParameters:
      Name                           Flags
      source                         final

  public static final scala.collection.immutable.LazyList$State$Empty$ $anonfun$_empty$1();
    descriptor: ()Lscala/collection/immutable/LazyList$State$Empty$;
    flags: (0x1019) ACC_PUBLIC, ACC_STATIC, ACC_FINAL, ACC_SYNTHETIC
    Code:
      stack=1, locals=0, args_size=0
         0: getstatic     #355                // Field scala/collection/immutable/LazyList$State$Empty$.MODULE$:Lscala/collection/immutable/LazyList$State$Empty$;
         3: areturn
      LineNumberTable:
        line 971: 0

  public static final java.lang.Object $anonfun$anyToMarker$1(java.lang.Object);
    descriptor: (Ljava/lang/Object;)Ljava/lang/Object;
    flags: (0x1019) ACC_PUBLIC, ACC_STATIC, ACC_FINAL, ACC_SYNTHETIC
    Code:
      stack=1, locals=1, args_size=1
         0: getstatic     #484                // Field scala/runtime/Statics.pfMarker:Ljava/lang/Object;
         3: areturn
      LineNumberTable:
        line 995: 0
      LocalVariableTable:
        Start  Length  Slot  Name   Signature
            0       4     0  x$10   Ljava/lang/Object;
    MethodParameters:
      Name                           Flags
      x$10                           final

  public static final scala.collection.immutable.LazyList$State $anonfun$filterImpl$1(scala.runtime.ObjectRef, scala.Function1, boolean);
    descriptor: (Lscala/runtime/ObjectRef;Lscala/Function1;Z)Lscala/collection/immutable/LazyList$State;
    flags: (0x1019) ACC_PUBLIC, ACC_STATIC, ACC_FINAL, ACC_SYNTHETIC
    Code:
      stack=4, locals=11, args_size=3
         0: aconst_null
         1: astore_3
         2: iconst_0
         3: istore        4
         5: aload_0
         6: getfield      #489                // Field scala/runtime/ObjectRef.elem:Ljava/lang/Object;
         9: checkcast     #17                 // class scala/collection/immutable/LazyList
        12: astore        5
        14: iload         4
        16: ifne          70
        19: aload         5
        21: invokevirtual #492                // Method scala/collection/immutable/LazyList.isEmpty:()Z
        24: ifne          70
        27: aload         5
        29: invokevirtual #495                // Method scala/collection/immutable/LazyList.head:()Ljava/lang/Object;
        32: astore_3
        33: aload_1
        34: aload_3
        35: invokeinterface #499,  2          // InterfaceMethod scala/Function1.apply:(Ljava/lang/Object;)Ljava/lang/Object;
        40: invokestatic  #505                // Method scala/runtime/BoxesRunTime.unboxToBoolean:(Ljava/lang/Object;)Z
        43: iload_2
        44: if_icmpeq     51
        47: iconst_1
        48: goto          52
        51: iconst_0
        52: istore        4
        54: aload         5
        56: invokevirtual #508                // Method scala/collection/immutable/LazyList.tail:()Lscala/collection/immutable/LazyList;
        59: astore        5
        61: aload_0
        62: aload         5
        64: putfield      #489                // Field scala/runtime/ObjectRef.elem:Ljava/lang/Object;
        67: goto          14
        70: iload         4
        72: ifeq          147
        75: getstatic     #49                 // Field MODULE$:Lscala/collection/immutable/LazyList$;
        78: pop
        79: getstatic     #49                 // Field MODULE$:Lscala/collection/immutable/LazyList$;
        82: pop
        83: new           #210                // class scala/runtime/ObjectRef
        86: dup
        87: aload         5
        89: invokespecial #213                // Method scala/runtime/ObjectRef."<init>":(Ljava/lang/Object;)V
        92: astore        7
        94: aload         7
        96: aload_1
        97: iload_2
        98: invokedynamic #223,  0            // InvokeDynamic #2:apply:(Lscala/runtime/ObjectRef;Lscala/Function1;Z)Lscala/Function0;
       103: astore        8
       105: new           #17                 // class scala/collection/immutable/LazyList
       108: dup
       109: aload         8
       111: invokespecial #73                 // Method scala/collection/immutable/LazyList."<init>":(Lscala/Function0;)V
       114: astore        9
       116: aload         9
       118: aconst_null
       119: astore        8
       121: aconst_null
       122: astore        9
       124: astore        10
       126: aload         10
       128: aconst_null
       129: astore        7
       131: aconst_null
       132: astore        10
       134: astore        6
       136: new           #26                 // class scala/collection/immutable/LazyList$State$Cons
       139: dup
       140: aload_3
       141: aload         6
       143: invokespecial #201                // Method scala/collection/immutable/LazyList$State$Cons."<init>":(Ljava/lang/Object;Lscala/collection/immutable/LazyList;)V
       146: areturn
       147: getstatic     #355                // Field scala/collection/immutable/LazyList$State$Empty$.MODULE$:Lscala/collection/immutable/LazyList$State$Empty$;
       150: areturn
      StackMapTable: number_of_entries = 5
        frame_type = 254 /* append */
          offset_delta = 14
          locals = [ class java/lang/Object, int, class scala/collection/immutable/LazyList ]
        frame_type = 36 /* same */
        frame_type = 64 /* same_locals_1_stack_item */
          stack = [ int ]
        frame_type = 17 /* same */
        frame_type = 251 /* same_frame_extended */
          offset_delta = 76
      LineNumberTable:
        line 1009: 0
        line 1010: 2
        line 1011: 5
        line 1012: 14
        line 1013: 27
        line 1014: 33
        line 1015: 54
        line 1016: 61
        line 1012: 67
        line 1018: 70
        line 1007: 83
        line 1008: 94
        line 990: 105
        line 1008: 116
        line 1018: 126
        line 993: 136
        line 1018: 146
      LocalVariableTable:
        Start  Length  Slot  Name   Signature
            2     148     3  elem   Ljava/lang/Object;
            5     145     4 found   Z
           14     136     5  rest   Lscala/collection/immutable/LazyList;
            0     151     0 restRef$1   Lscala/runtime/ObjectRef;
            0     151     1   p$2   Lscala/Function1;
            0     151     2 isFlipped$1   Z
          136      10     6 scala$collection$immutable$LazyList$$sCons_tl   Lscala/collection/immutable/LazyList;
           94      30     7 scala$collection$immutable$LazyList$$filterImpl_restRef   Lscala/runtime/ObjectRef;
          105      11     8 scala$collection$immutable$LazyList$$filterImpl_scala$collection$immutable$LazyList$$newLL_state   Lscala/Function0;
    MethodParameters:
      Name                           Flags
      restRef$1                      final
      p$2                            final
      isFlipped$1                    final

  public static final scala.collection.immutable.LazyList$State $anonfun$collectImpl$1(scala.runtime.ObjectRef, scala.PartialFunction);
    descriptor: (Lscala/runtime/ObjectRef;Lscala/PartialFunction;)Lscala/collection/immutable/LazyList$State;
    flags: (0x1019) ACC_PUBLIC, ACC_STATIC, ACC_FINAL, ACC_SYNTHETIC
    Code:
      stack=4, locals=7, args_size=2
         0: getstatic     #484                // Field scala/runtime/Statics.pfMarker:Ljava/lang/Object;
         3: astore_2
         4: getstatic     #49                 // Field MODULE$:Lscala/collection/immutable/LazyList$;
         7: invokevirtual #516                // Method scala$collection$immutable$LazyList$$anyToMarker:()Lscala/Function1;
        10: astore_3
        11: aload_2
        12: astore        4
        14: aload_0
        15: getfield      #489                // Field scala/runtime/ObjectRef.elem:Ljava/lang/Object;
        18: checkcast     #17                 // class scala/collection/immutable/LazyList
        21: astore        5
        23: aload         4
        25: aload_2
        26: if_acmpne     67
        29: aload         5
        31: invokevirtual #492                // Method scala/collection/immutable/LazyList.isEmpty:()Z
        34: ifne          67
        37: aload_1
        38: aload         5
        40: invokevirtual #495                // Method scala/collection/immutable/LazyList.head:()Ljava/lang/Object;
        43: aload_3
        44: invokeinterface #521,  3          // InterfaceMethod scala/PartialFunction.applyOrElse:(Ljava/lang/Object;Lscala/Function1;)Ljava/lang/Object;
        49: astore        4
        51: aload         5
        53: invokevirtual #508                // Method scala/collection/immutable/LazyList.tail:()Lscala/collection/immutable/LazyList;
        56: astore        5
        58: aload_0
        59: aload         5
        61: putfield      #489                // Field scala/runtime/ObjectRef.elem:Ljava/lang/Object;
        64: goto          23
        67: aload         4
        69: aload_2
        70: if_acmpne     77
        73: getstatic     #355                // Field scala/collection/immutable/LazyList$State$Empty$.MODULE$:Lscala/collection/immutable/LazyList$State$Empty$;
        76: areturn
        77: getstatic     #49                 // Field MODULE$:Lscala/collection/immutable/LazyList$;
        80: pop
        81: getstatic     #49                 // Field MODULE$:Lscala/collection/immutable/LazyList$;
        84: aload         5
        86: aload_1
        87: invokevirtual #523                // Method scala$collection$immutable$LazyList$$collectImpl:(Lscala/collection/immutable/LazyList;Lscala/PartialFunction;)Lscala/collection/immutable/LazyList;
        90: astore        6
        92: new           #26                 // class scala/collection/immutable/LazyList$State$Cons
        95: dup
        96: aload         4
        98: aload         6
       100: invokespecial #201                // Method scala/collection/immutable/LazyList$State$Cons."<init>":(Ljava/lang/Object;Lscala/collection/immutable/LazyList;)V
       103: areturn
      StackMapTable: number_of_entries = 3
        frame_type = 255 /* full_frame */
          offset_delta = 23
          locals = [ class scala/runtime/ObjectRef, class scala/PartialFunction, class java/lang/Object, class scala/Function1, class java/lang/Object, class scala/collection/immutable/LazyList ]
          stack = []
        frame_type = 43 /* same */
        frame_type = 9 /* same */
      LineNumberTable:
        line 1026: 0
        line 1027: 4
        line 1029: 11
        line 1030: 14
        line 1031: 23
        line 1032: 37
        line 1033: 51
        line 1034: 58
        line 1031: 64
        line 1036: 67
        line 1037: 77
        line 993: 92
        line 1037: 103
      LocalVariableTable:
        Start  Length  Slot  Name   Signature
            4      99     2 marker   Ljava/lang/Object;
           11      92     3 toMarker   Lscala/Function1;
           14      89     4   res   Ljava/lang/Object;
           23      80     5  rest   Lscala/collection/immutable/LazyList;
            0     104     0 restRef$2   Lscala/runtime/ObjectRef;
            0     104     1  pf$1   Lscala/PartialFunction;
           92      11     6 scala$collection$immutable$LazyList$$sCons_tl   Lscala/collection/immutable/LazyList;
    MethodParameters:
      Name                           Flags
      restRef$2                      final
      pf$1                           final

  public static final scala.collection.immutable.LazyList$State $anonfun$flatMapImpl$3(scala.runtime.ObjectRef, scala.Function1);
    descriptor: (Lscala/runtime/ObjectRef;Lscala/Function1;)Lscala/collection/immutable/LazyList$State;
    flags: (0x1019) ACC_PUBLIC, ACC_STATIC, ACC_FINAL, ACC_SYNTHETIC
    Code:
      stack=3, locals=4, args_size=2
         0: getstatic     #49                 // Field MODULE$:Lscala/collection/immutable/LazyList$;
         3: pop
         4: aload_0
         5: getfield      #489                // Field scala/runtime/ObjectRef.elem:Ljava/lang/Object;
         8: checkcast     #17                 // class scala/collection/immutable/LazyList
        11: astore_2
        12: new           #210                // class scala/runtime/ObjectRef
        15: dup
        16: aload_2
        17: invokespecial #213                // Method scala/runtime/ObjectRef."<init>":(Ljava/lang/Object;)V
        20: aload_1
        21: invokedynamic #248,  0            // InvokeDynamic #4:apply:(Lscala/runtime/ObjectRef;Lscala/Function1;)Lscala/Function0;
        26: astore_3
        27: new           #17                 // class scala/collection/immutable/LazyList
        30: dup
        31: aload_3
        32: invokespecial #73                 // Method scala/collection/immutable/LazyList."<init>":(Lscala/Function0;)V
        35: aconst_null
        36: astore_3
        37: aconst_null
        38: astore_2
        39: invokevirtual #532                // Method scala/collection/immutable/LazyList.scala$collection$immutable$LazyList$$state:()Lscala/collection/immutable/LazyList$State;
        42: areturn
      LineNumberTable:
        line 1060: 0
        line 1043: 12
        line 1044: 20
        line 990: 27
        line 1044: 35
        line 1060: 37
      LocalVariableTable:
        Start  Length  Slot  Name   Signature
            0      43     0 rest$1   Lscala/runtime/ObjectRef;
            0      43     1   f$3   Lscala/Function1;
           12      25     2 scala$collection$immutable$LazyList$$flatMapImpl_ll   Lscala/collection/immutable/LazyList;
           27       8     3 scala$collection$immutable$LazyList$$flatMapImpl_scala$collection$immutable$LazyList$$newLL_state   Lscala/Function0;
    MethodParameters:
      Name                           Flags
      rest$1                         final
      f$3                            final

  public static final scala.collection.immutable.LazyList$State $anonfun$flatMapImpl$2(scala.runtime.ObjectRef, scala.runtime.ObjectRef, scala.Function1);
    descriptor: (Lscala/runtime/ObjectRef;Lscala/runtime/ObjectRef;Lscala/Function1;)Lscala/collection/immutable/LazyList$State;
    flags: (0x1019) ACC_PUBLIC, ACC_STATIC, ACC_FINAL, ACC_SYNTHETIC
    Code:
      stack=4, locals=11, args_size=3
         0: getstatic     #49                 // Field MODULE$:Lscala/collection/immutable/LazyList$;
         3: pop
         4: aload_0
         5: getfield      #489                // Field scala/runtime/ObjectRef.elem:Ljava/lang/Object;
         8: checkcast     #321                // class scala/collection/Iterator
        11: aload_1
        12: aload_2
        13: invokedynamic #541,  0            // InvokeDynamic #19:apply:(Lscala/runtime/ObjectRef;Lscala/Function1;)Lscala/Function0;
        18: astore        4
        20: astore_3
        21: aload_3
        22: invokeinterface #325,  1          // InterfaceMethod scala/collection/Iterator.hasNext:()Z
        27: ifeq          81
        30: aload_3
        31: invokeinterface #328,  1          // InterfaceMethod scala/collection/Iterator.next:()Ljava/lang/Object;
        36: aload_3
        37: aload         4
        39: invokedynamic #335,  0            // InvokeDynamic #9:apply:(Lscala/collection/Iterator;Lscala/Function0;)Lscala/Function0;
        44: astore        5
        46: new           #17                 // class scala/collection/immutable/LazyList
        49: dup
        50: aload         5
        52: invokespecial #73                 // Method scala/collection/immutable/LazyList."<init>":(Lscala/Function0;)V
        55: astore        6
        57: aload         6
        59: aconst_null
        60: astore        5
        62: aconst_null
        63: astore        6
        65: astore        8
        67: astore        7
        69: new           #26                 // class scala/collection/immutable/LazyList$State$Cons
        72: dup
        73: aload         7
        75: aload         8
        77: invokespecial #201                // Method scala/collection/immutable/LazyList$State$Cons."<init>":(Ljava/lang/Object;Lscala/collection/immutable/LazyList;)V
        80: areturn
        81: getstatic     #49                 // Field MODULE$:Lscala/collection/immutable/LazyList$;
        84: pop
        85: aload_1
        86: getfield      #489                // Field scala/runtime/ObjectRef.elem:Ljava/lang/Object;
        89: checkcast     #17                 // class scala/collection/immutable/LazyList
        92: astore        9
        94: new           #210                // class scala/runtime/ObjectRef
        97: dup
        98: aload         9
       100: invokespecial #213                // Method scala/runtime/ObjectRef."<init>":(Ljava/lang/Object;)V
       103: aload_2
       104: invokedynamic #248,  0            // InvokeDynamic #4:apply:(Lscala/runtime/ObjectRef;Lscala/Function1;)Lscala/Function0;
       109: astore        10
       111: new           #17                 // class scala/collection/immutable/LazyList
       114: dup
       115: aload         10
       117: invokespecial #73                 // Method scala/collection/immutable/LazyList."<init>":(Lscala/Function0;)V
       120: aconst_null
       121: astore        10
       123: aconst_null
       124: astore        9
       126: invokevirtual #532                // Method scala/collection/immutable/LazyList.scala$collection$immutable$LazyList$$state:()Lscala/collection/immutable/LazyList$State;
       129: areturn
      StackMapTable: number_of_entries = 1
        frame_type = 253 /* append */
          offset_delta = 81
          locals = [ class scala/collection/Iterator, class scala/Function0 ]
      LineNumberTable:
        line 1060: 0
        line 1166: 21
        line 990: 46
        line 1166: 57
        line 993: 69
        line 1166: 80
        line 1060: 81
        line 1043: 94
        line 1044: 103
        line 990: 111
        line 1044: 120
        line 1060: 123
        line 1060: 129
      LocalVariableTable:
        Start  Length  Slot  Name   Signature
            0     130     0  it$3   Lscala/runtime/ObjectRef;
            0     130     1 rest$1   Lscala/runtime/ObjectRef;
            0     130     2   f$3   Lscala/Function1;
           21     108     3 scala$collection$immutable$LazyList$$stateFromIteratorConcatSuffix_it   Lscala/collection/Iterator;
           21     108     4 scala$collection$immutable$LazyList$$stateFromIteratorConcatSuffix_suffix   Lscala/Function0;
           46      11     5 scala$collection$immutable$LazyList$$stateFromIteratorConcatSuffix_scala$collection$immutable$LazyList$$newLL_state   Lscala/Function0;
           69      11     7 scala$collection$immutable$LazyList$$stateFromIteratorConcatSuffix_scala$collection$immutable$LazyList$$sCons_hd   Ljava/lang/Object;
           69      11     8 scala$collection$immutable$LazyList$$stateFromIteratorConcatSuffix_scala$collection$immutable$LazyList$$sCons_tl   Lscala/collection/immutable/LazyList;
           94      29     9 $anonfun$flatMapImpl$3_scala$collection$immutable$LazyList$$flatMapImpl_ll   Lscala/collection/immutable/LazyList;
          111       9    10 $anonfun$flatMapImpl$3_scala$collection$immutable$LazyList$$flatMapImpl_scala$collection$immutable$LazyList$$newLL_state   Lscala/Function0;
    MethodParameters:
      Name                           Flags
      it$3                           final
      rest$1                         final
      f$3                            final

  public static final scala.collection.immutable.LazyList$State $anonfun$flatMapImpl$1(scala.runtime.ObjectRef, scala.Function1);
    descriptor: (Lscala/runtime/ObjectRef;Lscala/Function1;)Lscala/collection/immutable/LazyList$State;
    flags: (0x1019) ACC_PUBLIC, ACC_STATIC, ACC_FINAL, ACC_SYNTHETIC
    Code:
      stack=4, locals=12, args_size=2
         0: new           #210                // class scala/runtime/ObjectRef
         3: dup
         4: aconst_null
         5: invokespecial #213                // Method scala/runtime/ObjectRef."<init>":(Ljava/lang/Object;)V
         8: astore        9
        10: aload         9
        12: aconst_null
        13: astore        9
        15: astore_2
        16: iconst_0
        17: istore_3
        18: aload_0
        19: getfield      #489                // Field scala/runtime/ObjectRef.elem:Ljava/lang/Object;
        22: checkcast     #17                 // class scala/collection/immutable/LazyList
        25: astore        10
        27: new           #210                // class scala/runtime/ObjectRef
        30: dup
        31: aload         10
        33: invokespecial #213                // Method scala/runtime/ObjectRef."<init>":(Ljava/lang/Object;)V
        36: astore        11
        38: aload         11
        40: aconst_null
        41: astore        10
        43: aconst_null
        44: astore        11
        46: astore        4
        48: iload_3
        49: ifne          143
        52: aload         4
        54: getfield      #489                // Field scala/runtime/ObjectRef.elem:Ljava/lang/Object;
        57: checkcast     #17                 // class scala/collection/immutable/LazyList
        60: invokevirtual #492                // Method scala/collection/immutable/LazyList.isEmpty:()Z
        63: ifne          143
        66: aload_2
        67: aload_1
        68: aload         4
        70: getfield      #489                // Field scala/runtime/ObjectRef.elem:Ljava/lang/Object;
        73: checkcast     #17                 // class scala/collection/immutable/LazyList
        76: invokevirtual #495                // Method scala/collection/immutable/LazyList.head:()Ljava/lang/Object;
        79: invokeinterface #499,  2          // InterfaceMethod scala/Function1.apply:(Ljava/lang/Object;)Ljava/lang/Object;
        84: checkcast     #297                // class scala/collection/IterableOnce
        87: invokeinterface #376,  1          // InterfaceMethod scala/collection/IterableOnce.iterator:()Lscala/collection/Iterator;
        92: putfield      #489                // Field scala/runtime/ObjectRef.elem:Ljava/lang/Object;
        95: aload_2
        96: getfield      #489                // Field scala/runtime/ObjectRef.elem:Ljava/lang/Object;
        99: checkcast     #321                // class scala/collection/Iterator
       102: invokeinterface #325,  1          // InterfaceMethod scala/collection/Iterator.hasNext:()Z
       107: istore_3
       108: iload_3
       109: ifne          48
       112: aload         4
       114: aload         4
       116: getfield      #489                // Field scala/runtime/ObjectRef.elem:Ljava/lang/Object;
       119: checkcast     #17                 // class scala/collection/immutable/LazyList
       122: invokevirtual #508                // Method scala/collection/immutable/LazyList.tail:()Lscala/collection/immutable/LazyList;
       125: putfield      #489                // Field scala/runtime/ObjectRef.elem:Ljava/lang/Object;
       128: aload_0
       129: aload         4
       131: getfield      #489                // Field scala/runtime/ObjectRef.elem:Ljava/lang/Object;
       134: checkcast     #17                 // class scala/collection/immutable/LazyList
       137: putfield      #489                // Field scala/runtime/ObjectRef.elem:Ljava/lang/Object;
       140: goto          48
       143: iload_3
       144: ifeq          241
       147: aload_2
       148: getfield      #489                // Field scala/runtime/ObjectRef.elem:Ljava/lang/Object;
       151: checkcast     #321                // class scala/collection/Iterator
       154: invokeinterface #328,  1          // InterfaceMethod scala/collection/Iterator.next:()Ljava/lang/Object;
       159: astore        5
       161: aload         4
       163: aload         4
       165: getfield      #489                // Field scala/runtime/ObjectRef.elem:Ljava/lang/Object;
       168: checkcast     #17                 // class scala/collection/immutable/LazyList
       171: invokevirtual #508                // Method scala/collection/immutable/LazyList.tail:()Lscala/collection/immutable/LazyList;
       174: putfield      #489                // Field scala/runtime/ObjectRef.elem:Ljava/lang/Object;
       177: aload_0
       178: aload         4
       180: getfield      #489                // Field scala/runtime/ObjectRef.elem:Ljava/lang/Object;
       183: checkcast     #17                 // class scala/collection/immutable/LazyList
       186: putfield      #489                // Field scala/runtime/ObjectRef.elem:Ljava/lang/Object;
       189: getstatic     #49                 // Field MODULE$:Lscala/collection/immutable/LazyList$;
       192: pop
       193: getstatic     #49                 // Field MODULE$:Lscala/collection/immutable/LazyList$;
       196: pop
       197: aload_2
       198: aload         4
       200: aload_1
       201: invokedynamic #550,  0            // InvokeDynamic #20:apply:(Lscala/runtime/ObjectRef;Lscala/runtime/ObjectRef;Lscala/Function1;)Lscala/Function0;
       206: astore        6
       208: new           #17                 // class scala/collection/immutable/LazyList
       211: dup
       212: aload         6
       214: invokespecial #73                 // Method scala/collection/immutable/LazyList."<init>":(Lscala/Function0;)V
       217: astore        7
       219: aload         7
       221: aconst_null
       222: astore        6
       224: aconst_null
       225: astore        7
       227: astore        8
       229: new           #26                 // class scala/collection/immutable/LazyList$State$Cons
       232: dup
       233: aload         5
       235: aload         8
       237: invokespecial #201                // Method scala/collection/immutable/LazyList$State$Cons."<init>":(Ljava/lang/Object;Lscala/collection/immutable/LazyList;)V
       240: areturn
       241: getstatic     #355                // Field scala/collection/immutable/LazyList$State$Empty$.MODULE$:Lscala/collection/immutable/LazyList$State$Empty$;
       244: areturn
      StackMapTable: number_of_entries = 3
        frame_type = 255 /* full_frame */
          offset_delta = 48
          locals = [ class scala/runtime/ObjectRef, class scala/Function1, class scala/runtime/ObjectRef, int, class scala/runtime/ObjectRef, top, top, top, top, null, null, null ]
          stack = []
        frame_type = 251 /* same_frame_extended */
          offset_delta = 94
        frame_type = 251 /* same_frame_extended */
          offset_delta = 97
      LineNumberTable:
        line 1045: 0
        line 1046: 16
        line 1047: 18
        line 1048: 48
        line 1049: 66
        line 1050: 95
        line 1051: 108
        line 1052: 112
        line 1053: 128
        line 1056: 143
        line 1057: 147
        line 1058: 161
        line 1059: 177
        line 1060: 189
        line 990: 208
        line 1060: 219
        line 993: 229
        line 1060: 240
        line 1061: 241
      LocalVariableTable:
        Start  Length  Slot  Name   Signature
          161      79     5  head   Ljava/lang/Object;
           16     228     2    it   Lscala/runtime/ObjectRef;
           18     226     3 itHasNext   Z
           48     196     4  rest   Lscala/runtime/ObjectRef;
            0     245     0 restRef$3   Lscala/runtime/ObjectRef;
            0     245     1   f$3   Lscala/Function1;
          208      11     6 scala$collection$immutable$LazyList$$newLL_state   Lscala/Function0;
          229      11     8 scala$collection$immutable$LazyList$$sCons_tl   Lscala/collection/immutable/LazyList;
           27      11    10 create_e   Ljava/lang/Object;
      LocalVariableTypeTable:
        Start  Length  Slot  Name   Signature
           27      11    10 create_e   TU;
    MethodParameters:
      Name                           Flags
      restRef$3                      final
      f$3                            final

  public static final scala.collection.immutable.LazyList$State $anonfun$dropImpl$1(scala.runtime.ObjectRef, scala.runtime.IntRef);
    descriptor: (Lscala/runtime/ObjectRef;Lscala/runtime/IntRef;)Lscala/collection/immutable/LazyList$State;
    flags: (0x1019) ACC_PUBLIC, ACC_STATIC, ACC_FINAL, ACC_SYNTHETIC
    Code:
      stack=2, locals=4, args_size=2
         0: aload_0
         1: getfield      #489                // Field scala/runtime/ObjectRef.elem:Ljava/lang/Object;
         4: checkcast     #17                 // class scala/collection/immutable/LazyList
         7: astore_2
         8: aload_1
         9: getfield      #557                // Field scala/runtime/IntRef.elem:I
        12: istore_3
        13: iload_3
        14: iconst_0
        15: if_icmple     46
        18: aload_2
        19: invokevirtual #492                // Method scala/collection/immutable/LazyList.isEmpty:()Z
        22: ifne          46
        25: aload_2
        26: invokevirtual #508                // Method scala/collection/immutable/LazyList.tail:()Lscala/collection/immutable/LazyList;
        29: astore_2
        30: aload_0
        31: aload_2
        32: putfield      #489                // Field scala/runtime/ObjectRef.elem:Ljava/lang/Object;
        35: iinc          3, -1
        38: aload_1
        39: iload_3
        40: putfield      #557                // Field scala/runtime/IntRef.elem:I
        43: goto          13
        46: aload_2
        47: invokevirtual #532                // Method scala/collection/immutable/LazyList.scala$collection$immutable$LazyList$$state:()Lscala/collection/immutable/LazyList$State;
        50: areturn
      StackMapTable: number_of_entries = 2
        frame_type = 253 /* append */
          offset_delta = 13
          locals = [ class scala/collection/immutable/LazyList, int ]
        frame_type = 32 /* same */
      LineNumberTable:
        line 1070: 0
        line 1071: 8
        line 1072: 13
        line 1073: 25
        line 1074: 30
        line 1075: 35
        line 1076: 38
        line 1072: 43
        line 1078: 46
      LocalVariableTable:
        Start  Length  Slot  Name   Signature
            8      42     2  rest   Lscala/collection/immutable/LazyList;
           13      37     3     i   I
            0      51     0 restRef$4   Lscala/runtime/ObjectRef;
            0      51     1 iRef$1   Lscala/runtime/IntRef;
    MethodParameters:
      Name                           Flags
      restRef$4                      final
      iRef$1                         final

  public static final scala.collection.immutable.LazyList$State $anonfun$dropWhileImpl$1(scala.runtime.ObjectRef, scala.Function1);
    descriptor: (Lscala/runtime/ObjectRef;Lscala/Function1;)Lscala/collection/immutable/LazyList$State;
    flags: (0x1019) ACC_PUBLIC, ACC_STATIC, ACC_FINAL, ACC_SYNTHETIC
    Code:
      stack=2, locals=3, args_size=2
         0: aload_0
         1: getfield      #489                // Field scala/runtime/ObjectRef.elem:Ljava/lang/Object;
         4: checkcast     #17                 // class scala/collection/immutable/LazyList
         7: astore_2
         8: aload_2
         9: invokevirtual #492                // Method scala/collection/immutable/LazyList.isEmpty:()Z
        12: ifne          44
        15: aload_1
        16: aload_2
        17: invokevirtual #495                // Method scala/collection/immutable/LazyList.head:()Ljava/lang/Object;
        20: invokeinterface #499,  2          // InterfaceMethod scala/Function1.apply:(Ljava/lang/Object;)Ljava/lang/Object;
        25: invokestatic  #505                // Method scala/runtime/BoxesRunTime.unboxToBoolean:(Ljava/lang/Object;)Z
        28: ifeq          44
        31: aload_2
        32: invokevirtual #508                // Method scala/collection/immutable/LazyList.tail:()Lscala/collection/immutable/LazyList;
        35: astore_2
        36: aload_0
        37: aload_2
        38: putfield      #489                // Field scala/runtime/ObjectRef.elem:Ljava/lang/Object;
        41: goto          8
        44: aload_2
        45: invokevirtual #532                // Method scala/collection/immutable/LazyList.scala$collection$immutable$LazyList$$state:()Lscala/collection/immutable/LazyList$State;
        48: areturn
      StackMapTable: number_of_entries = 2
        frame_type = 252 /* append */
          offset_delta = 8
          locals = [ class scala/collection/immutable/LazyList ]
        frame_type = 35 /* same */
      LineNumberTable:
        line 1086: 0
        line 1087: 8
        line 1088: 31
        line 1089: 36
        line 1087: 41
        line 1091: 44
      LocalVariableTable:
        Start  Length  Slot  Name   Signature
            8      40     2  rest   Lscala/collection/immutable/LazyList;
            0      49     0 restRef$5   Lscala/runtime/ObjectRef;
            0      49     1   p$3   Lscala/Function1;
    MethodParameters:
      Name                           Flags
      restRef$5                      final
      p$3                            final

  public static final scala.collection.immutable.LazyList$State $anonfun$takeRightImpl$1(scala.runtime.ObjectRef, scala.runtime.IntRef, scala.runtime.ObjectRef);
    descriptor: (Lscala/runtime/ObjectRef;Lscala/runtime/IntRef;Lscala/runtime/ObjectRef;)Lscala/collection/immutable/LazyList$State;
    flags: (0x1019) ACC_PUBLIC, ACC_STATIC, ACC_FINAL, ACC_SYNTHETIC
    Code:
      stack=2, locals=6, args_size=3
         0: aload_0
         1: getfield      #489                // Field scala/runtime/ObjectRef.elem:Ljava/lang/Object;
         4: checkcast     #17                 // class scala/collection/immutable/LazyList
         7: astore_3
         8: aload_1
         9: getfield      #557                // Field scala/runtime/IntRef.elem:I
        12: istore        4
        14: iload         4
        16: iconst_0
        17: if_icmple     49
        20: aload_3
        21: invokevirtual #492                // Method scala/collection/immutable/LazyList.isEmpty:()Z
        24: ifne          49
        27: aload_3
        28: invokevirtual #508                // Method scala/collection/immutable/LazyList.tail:()Lscala/collection/immutable/LazyList;
        31: astore_3
        32: aload_0
        33: aload_3
        34: putfield      #489                // Field scala/runtime/ObjectRef.elem:Ljava/lang/Object;
        37: iinc          4, -1
        40: aload_1
        41: iload         4
        43: putfield      #557                // Field scala/runtime/IntRef.elem:I
        46: goto          14
        49: aload_2
        50: getfield      #489                // Field scala/runtime/ObjectRef.elem:Ljava/lang/Object;
        53: checkcast     #17                 // class scala/collection/immutable/LazyList
        56: astore        5
        58: aload_3
        59: invokevirtual #492                // Method scala/collection/immutable/LazyList.isEmpty:()Z
        62: ifne          91
        65: aload_3
        66: invokevirtual #508                // Method scala/collection/immutable/LazyList.tail:()Lscala/collection/immutable/LazyList;
        69: astore_3
        70: aload_0
        71: aload_3
        72: putfield      #489                // Field scala/runtime/ObjectRef.elem:Ljava/lang/Object;
        75: aload         5
        77: invokevirtual #508                // Method scala/collection/immutable/LazyList.tail:()Lscala/collection/immutable/LazyList;
        80: astore        5
        82: aload_2
        83: aload         5
        85: putfield      #489                // Field scala/runtime/ObjectRef.elem:Ljava/lang/Object;
        88: goto          58
        91: aload         5
        93: invokevirtual #532                // Method scala/collection/immutable/LazyList.scala$collection$immutable$LazyList$$state:()Lscala/collection/immutable/LazyList$State;
        96: areturn
      StackMapTable: number_of_entries = 4
        frame_type = 253 /* append */
          offset_delta = 14
          locals = [ class scala/collection/immutable/LazyList, int ]
        frame_type = 34 /* same */
        frame_type = 252 /* append */
          offset_delta = 8
          locals = [ class scala/collection/immutable/LazyList ]
        frame_type = 32 /* same */
      LineNumberTable:
        line 1101: 0
        line 1102: 8
        line 1104: 14
        line 1105: 27
        line 1106: 32
        line 1107: 37
        line 1108: 40
        line 1104: 46
        line 1110: 49
        line 1112: 58
        line 1113: 65
        line 1114: 70
        line 1115: 75
        line 1116: 82
        line 1112: 88
        line 1119: 91
      LocalVariableTable:
        Start  Length  Slot  Name   Signature
            8      88     3 scout   Lscala/collection/immutable/LazyList;
           14      82     4 remaining   I
           58      38     5  rest   Lscala/collection/immutable/LazyList;
            0      97     0 scoutRef$1   Lscala/runtime/ObjectRef;
            0      97     1 remainingRef$1   Lscala/runtime/IntRef;
            0      97     2 restRef$6   Lscala/runtime/ObjectRef;
    MethodParameters:
      Name                           Flags
      scoutRef$1                     final
      remainingRef$1                 final
      restRef$6                      final

  public static final scala.collection.immutable.LazyList$State $anonfun$from$1(scala.collection.IterableOnce);
    descriptor: (Lscala/collection/IterableOnce;)Lscala/collection/immutable/LazyList$State;
    flags: (0x1019) ACC_PUBLIC, ACC_STATIC, ACC_FINAL, ACC_SYNTHETIC
    Code:
      stack=2, locals=1, args_size=1
         0: getstatic     #49                 // Field MODULE$:Lscala/collection/immutable/LazyList$;
         3: aload_0
         4: invokeinterface #376,  1          // InterfaceMethod scala/collection/IterableOnce.iterator:()Lscala/collection/Iterator;
         9: invokevirtual #568                // Method scala$collection$immutable$LazyList$$stateFromIterator:(Lscala/collection/Iterator;)Lscala/collection/immutable/LazyList$State;
        12: areturn
      LineNumberTable:
        line 1157: 0
      LocalVariableTable:
        Start  Length  Slot  Name   Signature
            0      13     0 coll$1   Lscala/collection/IterableOnce;
    MethodParameters:
      Name                           Flags
      coll$1                         final

  public static final scala.collection.immutable.LazyList$State $anonfun$stateFromIteratorConcatSuffix$1(scala.collection.Iterator, scala.Function0);
    descriptor: (Lscala/collection/Iterator;Lscala/Function0;)Lscala/collection/immutable/LazyList$State;
    flags: (0x1019) ACC_PUBLIC, ACC_STATIC, ACC_FINAL, ACC_SYNTHETIC
    Code:
      stack=3, locals=2, args_size=2
         0: getstatic     #49                 // Field MODULE$:Lscala/collection/immutable/LazyList$;
         3: aload_0
         4: aload_1
         5: invokevirtual #572                // Method scala$collection$immutable$LazyList$$stateFromIteratorConcatSuffix:(Lscala/collection/Iterator;Lscala/Function0;)Lscala/collection/immutable/LazyList$State;
         8: areturn
      LineNumberTable:
        line 1166: 0
      LocalVariableTable:
        Start  Length  Slot  Name   Signature
            0       9     0  it$4   Lscala/collection/Iterator;
            0       9     1 suffix$3   Lscala/Function0;
    MethodParameters:
      Name                           Flags
      it$4                           final
      suffix$3                       final

  public static final scala.collection.immutable.LazyList$State $anonfun$stateFromIterator$1(scala.collection.Iterator);
    descriptor: (Lscala/collection/Iterator;)Lscala/collection/immutable/LazyList$State;
    flags: (0x1019) ACC_PUBLIC, ACC_STATIC, ACC_FINAL, ACC_SYNTHETIC
    Code:
      stack=2, locals=1, args_size=1
         0: getstatic     #49                 // Field MODULE$:Lscala/collection/immutable/LazyList$;
         3: aload_0
         4: invokevirtual #568                // Method scala$collection$immutable$LazyList$$stateFromIterator:(Lscala/collection/Iterator;)Lscala/collection/immutable/LazyList$State;
         7: areturn
      LineNumberTable:
        line 1171: 0
      LocalVariableTable:
        Start  Length  Slot  Name   Signature
            0       8     0  it$5   Lscala/collection/Iterator;
    MethodParameters:
      Name                           Flags
      it$5                           final

  public static final scala.collection.immutable.LazyList$State $anonfun$concat$1(scala.collection.immutable.Seq);
    descriptor: (Lscala/collection/immutable/Seq;)Lscala/collection/immutable/LazyList$State;
    flags: (0x1019) ACC_PUBLIC, ACC_STATIC, ACC_FINAL, ACC_SYNTHETIC
    Code:
      stack=2, locals=1, args_size=1
         0: getstatic     #49                 // Field MODULE$:Lscala/collection/immutable/LazyList$;
         3: aload_0
         4: invokeinterface #575,  1          // InterfaceMethod scala/collection/immutable/Seq.iterator:()Lscala/collection/Iterator;
         9: invokespecial #577                // Method concatIterator:(Lscala/collection/Iterator;)Lscala/collection/immutable/LazyList$State;
        12: areturn
      LineNumberTable:
        line 1176: 0
      LocalVariableTable:
        Start  Length  Slot  Name   Signature
            0      13     0 xss$1   Lscala/collection/immutable/Seq;
    MethodParameters:
      Name                           Flags
      xss$1                          final

  public static final scala.collection.immutable.LazyList$State $anonfun$concatIterator$1(scala.collection.Iterator);
    descriptor: (Lscala/collection/Iterator;)Lscala/collection/immutable/LazyList$State;
    flags: (0x1019) ACC_PUBLIC, ACC_STATIC, ACC_FINAL, ACC_SYNTHETIC
    Code:
      stack=2, locals=1, args_size=1
         0: getstatic     #49                 // Field MODULE$:Lscala/collection/immutable/LazyList$;
         3: aload_0
         4: invokespecial #577                // Method concatIterator:(Lscala/collection/Iterator;)Lscala/collection/immutable/LazyList$State;
         7: areturn
      LineNumberTable:
        line 1180: 0
      LocalVariableTable:
        Start  Length  Slot  Name   Signature
            0       8     0  it$6   Lscala/collection/Iterator;
    MethodParameters:
      Name                           Flags
      it$6                           final

  public static final java.lang.Object $anonfun$iterate$2(scala.Function1, java.lang.Object);
    descriptor: (Lscala/Function1;Ljava/lang/Object;)Ljava/lang/Object;
    flags: (0x1019) ACC_PUBLIC, ACC_STATIC, ACC_FINAL, ACC_SYNTHETIC
    Code:
      stack=2, locals=2, args_size=2
         0: aload_0
         1: aload_1
         2: invokeinterface #499,  2          // InterfaceMethod scala/Function1.apply:(Ljava/lang/Object;)Ljava/lang/Object;
         7: areturn
      LineNumberTable:
        line 1191: 0
      LocalVariableTable:
        Start  Length  Slot  Name   Signature
            0       8     0   f$4   Lscala/Function1;
            0       8     1 head$1   Ljava/lang/Object;
    MethodParameters:
      Name                           Flags
      f$4                            final
      head$1                         final

  public static final scala.collection.immutable.LazyList$State $anonfun$iterate$1(scala.Function0, scala.Function1);
    descriptor: (Lscala/Function0;Lscala/Function1;)Lscala/collection/immutable/LazyList$State;
    flags: (0x1019) ACC_PUBLIC, ACC_STATIC, ACC_FINAL, ACC_SYNTHETIC
    Code:
      stack=4, locals=8, args_size=2
         0: aload_0
         1: invokeinterface #339,  1          // InterfaceMethod scala/Function0.apply:()Ljava/lang/Object;
         6: astore_2
         7: getstatic     #49                 // Field MODULE$:Lscala/collection/immutable/LazyList$;
        10: pop
        11: getstatic     #49                 // Field MODULE$:Lscala/collection/immutable/LazyList$;
        14: pop
        15: aload_1
        16: aload_2
        17: invokedynamic #587,  0            // InvokeDynamic #21:apply:(Lscala/Function1;Ljava/lang/Object;)Lscala/Function0;
        22: astore        4
        24: aload         4
        26: aload_1
        27: invokedynamic #396,  0            // InvokeDynamic #13:apply:(Lscala/Function0;Lscala/Function1;)Lscala/Function0;
        32: astore        5
        34: new           #17                 // class scala/collection/immutable/LazyList
        37: dup
        38: aload         5
        40: invokespecial #73                 // Method scala/collection/immutable/LazyList."<init>":(Lscala/Function0;)V
        43: astore        6
        45: aload         6
        47: aconst_null
        48: astore        5
        50: aconst_null
        51: astore        6
        53: astore        7
        55: aload         7
        57: aconst_null
        58: astore        4
        60: aconst_null
        61: astore        7
        63: astore_3
        64: new           #26                 // class scala/collection/immutable/LazyList$State$Cons
        67: dup
        68: aload_2
        69: aload_3
        70: invokespecial #201                // Method scala/collection/immutable/LazyList$State$Cons."<init>":(Ljava/lang/Object;Lscala/collection/immutable/LazyList;)V
        73: areturn
      LineNumberTable:
        line 1190: 0
        line 1191: 7
        line 1189: 24
        line 990: 34
        line 1189: 45
        line 1191: 55
        line 993: 64
        line 1191: 73
      LocalVariableTable:
        Start  Length  Slot  Name   Signature
            7      66     2  head   Ljava/lang/Object;
            0      74     0 start$1   Lscala/Function0;
            0      74     1   f$4   Lscala/Function1;
           64       9     3 scala$collection$immutable$LazyList$$sCons_tl   Lscala/collection/immutable/LazyList;
           24      31     4 iterate_start   Lscala/Function0;
           34      11     5 iterate_scala$collection$immutable$LazyList$$newLL_state   Lscala/Function0;
    MethodParameters:
      Name                           Flags
      start$1                        final
      f$4                            final

  public static final scala.collection.immutable.LazyList$State $anonfun$from$2(int, int);
    descriptor: (II)Lscala/collection/immutable/LazyList$State;
    flags: (0x1019) ACC_PUBLIC, ACC_STATIC, ACC_FINAL, ACC_SYNTHETIC
    Code:
      stack=4, locals=4, args_size=2
         0: getstatic     #49                 // Field MODULE$:Lscala/collection/immutable/LazyList$;
         3: pop
         4: iload_0
         5: invokestatic  #597                // Method java/lang/Integer.valueOf:(I)Ljava/lang/Integer;
         8: getstatic     #49                 // Field MODULE$:Lscala/collection/immutable/LazyList$;
        11: iload_0
        12: iload_1
        13: iadd
        14: iload_1
        15: invokevirtual #410                // Method from:(II)Lscala/collection/immutable/LazyList;
        18: astore_3
        19: astore_2
        20: new           #26                 // class scala/collection/immutable/LazyList$State$Cons
        23: dup
        24: aload_2
        25: aload_3
        26: invokespecial #201                // Method scala/collection/immutable/LazyList$State$Cons."<init>":(Ljava/lang/Object;Lscala/collection/immutable/LazyList;)V
        29: areturn
      LineNumberTable:
        line 1203: 0
        line 993: 20
        line 1203: 29
      LocalVariableTable:
        Start  Length  Slot  Name   Signature
            0      30     0 start$2   I
            0      30     1 step$2   I
           20       9     2 scala$collection$immutable$LazyList$$sCons_hd   Ljava/lang/Object;
           20       9     3 scala$collection$immutable$LazyList$$sCons_tl   Lscala/collection/immutable/LazyList;
    MethodParameters:
      Name                           Flags
      start$2                        final
      step$2                         final

  public static final scala.collection.immutable.LazyList$State $anonfun$continually$1(scala.Function0);
    descriptor: (Lscala/Function0;)Lscala/collection/immutable/LazyList$State;
    flags: (0x1019) ACC_PUBLIC, ACC_STATIC, ACC_FINAL, ACC_SYNTHETIC
    Code:
      stack=4, locals=6, args_size=1
         0: getstatic     #49                 // Field MODULE$:Lscala/collection/immutable/LazyList$;
         3: pop
         4: aload_0
         5: invokeinterface #339,  1          // InterfaceMethod scala/Function0.apply:()Ljava/lang/Object;
        10: getstatic     #49                 // Field MODULE$:Lscala/collection/immutable/LazyList$;
        13: pop
        14: aload_0
        15: invokedynamic #419,  0            // InvokeDynamic #15:apply:(Lscala/Function0;)Lscala/Function0;
        20: astore_3
        21: new           #17                 // class scala/collection/immutable/LazyList
        24: dup
        25: aload_3
        26: invokespecial #73                 // Method scala/collection/immutable/LazyList."<init>":(Lscala/Function0;)V
        29: astore        4
        31: aload         4
        33: aconst_null
        34: astore_3
        35: aconst_null
        36: astore        4
        38: astore        5
        40: aload         5
        42: aconst_null
        43: astore        5
        45: astore_2
        46: astore_1
        47: new           #26                 // class scala/collection/immutable/LazyList$State$Cons
        50: dup
        51: aload_1
        52: aload_2
        53: invokespecial #201                // Method scala/collection/immutable/LazyList$State$Cons."<init>":(Ljava/lang/Object;Lscala/collection/immutable/LazyList;)V
        56: areturn
      LineNumberTable:
        line 1220: 0
        line 1220: 14
        line 990: 21
        line 1220: 31
        line 1220: 40
        line 993: 47
        line 1220: 56
      LocalVariableTable:
        Start  Length  Slot  Name   Signature
            0      57     0 elem$6   Lscala/Function0;
           47       9     1 scala$collection$immutable$LazyList$$sCons_hd   Ljava/lang/Object;
           47       9     2 scala$collection$immutable$LazyList$$sCons_tl   Lscala/collection/immutable/LazyList;
           21      10     3 continually_scala$collection$immutable$LazyList$$newLL_state   Lscala/Function0;
    MethodParameters:
      Name                           Flags
      elem$6                         final

  public static final scala.collection.immutable.LazyList$State $anonfun$fill$1(scala.Function0, int);
    descriptor: (Lscala/Function0;I)Lscala/collection/immutable/LazyList$State;
    flags: (0x1019) ACC_PUBLIC, ACC_STATIC, ACC_FINAL, ACC_SYNTHETIC
    Code:
      stack=4, locals=9, args_size=2
         0: getstatic     #49                 // Field MODULE$:Lscala/collection/immutable/LazyList$;
         3: pop
         4: aload_0
         5: invokeinterface #339,  1          // InterfaceMethod scala/Function0.apply:()Ljava/lang/Object;
        10: getstatic     #49                 // Field MODULE$:Lscala/collection/immutable/LazyList$;
        13: iload_1
        14: iconst_1
        15: isub
        16: istore        5
        18: astore        4
        20: iload         5
        22: iconst_0
        23: if_icmple     58
        26: aload_0
        27: iload         5
        29: invokedynamic #429,  0            // InvokeDynamic #16:apply:(Lscala/Function0;I)Lscala/Function0;
        34: astore        6
        36: new           #17                 // class scala/collection/immutable/LazyList
        39: dup
        40: aload         6
        42: invokespecial #73                 // Method scala/collection/immutable/LazyList."<init>":(Lscala/Function0;)V
        45: astore        7
        47: aload         7
        49: aconst_null
        50: astore        6
        52: aconst_null
        53: astore        7
        55: goto          63
        58: aload         4
        60: invokevirtual #304                // Method empty:()Lscala/collection/immutable/LazyList;
        63: astore        8
        65: aload         8
        67: aconst_null
        68: astore        4
        70: aconst_null
        71: astore        6
        73: aconst_null
        74: astore        7
        76: aconst_null
        77: astore        8
        79: astore_3
        80: astore_2
        81: new           #26                 // class scala/collection/immutable/LazyList$State$Cons
        84: dup
        85: aload_2
        86: aload_3
        87: invokespecial #201                // Method scala/collection/immutable/LazyList$State$Cons."<init>":(Ljava/lang/Object;Lscala/collection/immutable/LazyList;)V
        90: areturn
      StackMapTable: number_of_entries = 2
        frame_type = 255 /* full_frame */
          offset_delta = 58
          locals = [ class scala/Function0, int, top, top, class scala/collection/immutable/LazyList$, int ]
          stack = [ class java/lang/Object ]
        frame_type = 255 /* full_frame */
          offset_delta = 4
          locals = [ class scala/Function0, int, top, top, class scala/collection/immutable/LazyList$, int ]
          stack = [ class java/lang/Object, class scala/collection/immutable/LazyList ]
      LineNumberTable:
        line 1223: 0
        line 1223: 20
        line 990: 36
        line 1223: 47
        line 1223: 65
        line 993: 81
        line 1223: 90
      LocalVariableTable:
        Start  Length  Slot  Name   Signature
            0      91     0 elem$7   Lscala/Function0;
            0      91     1   n$3   I
           81       9     2 scala$collection$immutable$LazyList$$sCons_hd   Ljava/lang/Object;
           81       9     3 scala$collection$immutable$LazyList$$sCons_tl   Lscala/collection/immutable/LazyList;
           20      45     4 fill_this   Lscala/collection/immutable/LazyList$;
           20      45     5 fill_n   I
           36      11     6 fill_scala$collection$immutable$LazyList$$newLL_state   Lscala/Function0;
    MethodParameters:
      Name                           Flags
      elem$7                         final
      n$3                            final

  public static final scala.collection.immutable.LazyList$State $anonfun$tabulate$1(scala.collection.immutable.LazyList$, scala.Function1, int, int);
    descriptor: (Lscala/collection/immutable/LazyList$;Lscala/Function1;II)Lscala/collection/immutable/LazyList$State;
    flags: (0x1019) ACC_PUBLIC, ACC_STATIC, ACC_FINAL, ACC_SYNTHETIC
    Code:
      stack=5, locals=10, args_size=4
         0: getstatic     #49                 // Field MODULE$:Lscala/collection/immutable/LazyList$;
         3: pop
         4: aload_1
         5: iload_2
         6: invokestatic  #597                // Method java/lang/Integer.valueOf:(I)Ljava/lang/Integer;
         9: invokeinterface #499,  2          // InterfaceMethod scala/Function1.apply:(Ljava/lang/Object;)Ljava/lang/Object;
        14: iload_2
        15: iconst_1
        16: iadd
        17: istore        6
        19: iload         6
        21: iload_3
        22: if_icmpge     59
        25: aload_0
        26: aload_1
        27: iload         6
        29: iload_3
        30: invokedynamic #439,  0            // InvokeDynamic #17:apply:(Lscala/collection/immutable/LazyList$;Lscala/Function1;II)Lscala/Function0;
        35: astore        7
        37: new           #17                 // class scala/collection/immutable/LazyList
        40: dup
        41: aload         7
        43: invokespecial #73                 // Method scala/collection/immutable/LazyList."<init>":(Lscala/Function0;)V
        46: astore        8
        48: aload         8
        50: aconst_null
        51: astore        7
        53: aconst_null
        54: astore        8
        56: goto          63
        59: aload_0
        60: invokevirtual #304                // Method empty:()Lscala/collection/immutable/LazyList;
        63: astore        9
        65: aload         9
        67: aconst_null
        68: astore        7
        70: aconst_null
        71: astore        8
        73: aconst_null
        74: astore        9
        76: astore        5
        78: astore        4
        80: new           #26                 // class scala/collection/immutable/LazyList$State$Cons
        83: dup
        84: aload         4
        86: aload         5
        88: invokespecial #201                // Method scala/collection/immutable/LazyList$State$Cons."<init>":(Ljava/lang/Object;Lscala/collection/immutable/LazyList;)V
        91: areturn
      StackMapTable: number_of_entries = 2
        frame_type = 255 /* full_frame */
          offset_delta = 59
          locals = [ class scala/collection/immutable/LazyList$, class scala/Function1, int, int, top, top, int ]
          stack = [ class java/lang/Object ]
        frame_type = 255 /* full_frame */
          offset_delta = 3
          locals = [ class scala/collection/immutable/LazyList$, class scala/Function1, int, int, top, top, int ]
          stack = [ class java/lang/Object, class scala/collection/immutable/LazyList ]
      LineNumberTable:
        line 1227: 0
        line 1227: 19
        line 990: 37
        line 1227: 48
        line 1227: 65
        line 993: 80
        line 1227: 91
      LocalVariableTable:
        Start  Length  Slot  Name   Signature
            0      92     0 $this   Lscala/collection/immutable/LazyList$;
            0      92     1   f$5   Lscala/Function1;
            0      92     2 index$2   I
            0      92     3   n$4   I
           80      11     4 scala$collection$immutable$LazyList$$sCons_hd   Ljava/lang/Object;
           80      11     5 scala$collection$immutable$LazyList$$sCons_tl   Lscala/collection/immutable/LazyList;
           19      46     6 at$1_index   I
           37      11     7 at$1_scala$collection$immutable$LazyList$$newLL_state   Lscala/Function0;
    MethodParameters:
      Name                           Flags
      $this                          final synthetic
      f$5                            final
      index$2                        final
      n$4                            final

  private final scala.collection.immutable.LazyList at$1(int, int, scala.Function1);
    descriptor: (IILscala/Function1;)Lscala/collection/immutable/LazyList;
    flags: (0x0012) ACC_PRIVATE, ACC_FINAL
    Code:
      stack=4, locals=5, args_size=4
         0: iload_1
         1: iload_2
         2: if_icmpge     26
         5: aload_0
         6: aload_3
         7: iload_1
         8: iload_2
         9: invokedynamic #439,  0            // InvokeDynamic #17:apply:(Lscala/collection/immutable/LazyList$;Lscala/Function1;II)Lscala/Function0;
        14: astore        4
        16: new           #17                 // class scala/collection/immutable/LazyList
        19: dup
        20: aload         4
        22: invokespecial #73                 // Method scala/collection/immutable/LazyList."<init>":(Lscala/Function0;)V
        25: areturn
        26: aload_0
        27: invokevirtual #304                // Method empty:()Lscala/collection/immutable/LazyList;
        30: areturn
      StackMapTable: number_of_entries = 1
        frame_type = 26 /* same */
      LineNumberTable:
        line 1227: 0
        line 990: 16
        line 1227: 25
      LocalVariableTable:
        Start  Length  Slot  Name   Signature
            0      31     0  this   Lscala/collection/immutable/LazyList$;
            0      31     1 index   I
            0      31     2   n$4   I
            0      31     3   f$5   Lscala/Function1;
           16       9     4 scala$collection$immutable$LazyList$$newLL_state   Lscala/Function0;
    MethodParameters:
      Name                           Flags
      index                          final
      n$4                            final
      f$5                            final

  public static final scala.collection.immutable.LazyList$State $anonfun$unfold$1(scala.Function1, java.lang.Object);
    descriptor: (Lscala/Function1;Ljava/lang/Object;)Lscala/collection/immutable/LazyList$State;
    flags: (0x1019) ACC_PUBLIC, ACC_STATIC, ACC_FINAL, ACC_SYNTHETIC
    Code:
      stack=4, locals=12, args_size=2
         0: aload_0
         1: aload_1
         2: invokeinterface #499,  2          // InterfaceMethod scala/Function1.apply:(Ljava/lang/Object;)Ljava/lang/Object;
         7: checkcast     #615                // class scala/Option
        10: astore_3
        11: aload_3
        12: instanceof    #617                // class scala/Some
        15: ifeq          120
        18: aload_3
        19: checkcast     #617                // class scala/Some
        22: invokevirtual #620                // Method scala/Some.value:()Ljava/lang/Object;
        25: checkcast     #622                // class scala/Tuple2
        28: astore        4
        30: aload         4
        32: ifnull        120
        35: aload         4
        37: invokevirtual #625                // Method scala/Tuple2._1:()Ljava/lang/Object;
        40: astore        5
        42: aload         4
        44: invokevirtual #628                // Method scala/Tuple2._2:()Ljava/lang/Object;
        47: astore        6
        49: getstatic     #49                 // Field MODULE$:Lscala/collection/immutable/LazyList$;
        52: pop
        53: getstatic     #49                 // Field MODULE$:Lscala/collection/immutable/LazyList$;
        56: pop
        57: aload_0
        58: aload         6
        60: invokedynamic #453,  0            // InvokeDynamic #18:apply:(Lscala/Function1;Ljava/lang/Object;)Lscala/Function0;
        65: astore        9
        67: new           #17                 // class scala/collection/immutable/LazyList
        70: dup
        71: aload         9
        73: invokespecial #73                 // Method scala/collection/immutable/LazyList."<init>":(Lscala/Function0;)V
        76: astore        10
        78: aload         10
        80: aconst_null
        81: astore        9
        83: aconst_null
        84: astore        10
        86: astore        11
        88: aload         11
        90: aconst_null
        91: astore        11
        93: astore        7
        95: new           #26                 // class scala/collection/immutable/LazyList$State$Cons
        98: dup
        99: aload         5
       101: aload         7
       103: invokespecial #201                // Method scala/collection/immutable/LazyList$State$Cons."<init>":(Ljava/lang/Object;Lscala/collection/immutable/LazyList;)V
       106: astore        8
       108: aload         8
       110: aconst_null
       111: astore        7
       113: aconst_null
       114: astore        8
       116: astore_2
       117: goto          146
       120: getstatic     #633                // Field scala/None$.MODULE$:Lscala/None$;
       123: aload_3
       124: invokevirtual #636                // Method java/lang/Object.equals:(Ljava/lang/Object;)Z
       127: ifeq          137
       130: getstatic     #355                // Field scala/collection/immutable/LazyList$State$Empty$.MODULE$:Lscala/collection/immutable/LazyList$State$Empty$;
       133: astore_2
       134: goto          146
       137: new           #638                // class scala/MatchError
       140: dup
       141: aload_3
       142: invokespecial #639                // Method scala/MatchError."<init>":(Ljava/lang/Object;)V
       145: athrow
       146: aload_2
       147: areturn
      StackMapTable: number_of_entries = 3
        frame_type = 253 /* append */
          offset_delta = 120
          locals = [ top, class scala/Option ]
        frame_type = 16 /* same */
        frame_type = 255 /* full_frame */
          offset_delta = 8
          locals = [ class scala/Function1, class java/lang/Object, class java/lang/Object, class scala/Option ]
          stack = []
      LineNumberTable:
        line 1235: 0
        line 1236: 11
        line 1235: 57
        line 990: 67
        line 1235: 78
        line 1236: 88
        line 993: 95
        line 1236: 108
        line 1237: 120
        line 1235: 137
      LocalVariableTable:
        Start  Length  Slot  Name   Signature
           42      78     5  elem   Ljava/lang/Object;
           49      71     6 state   Ljava/lang/Object;
            0     148     0   f$6   Lscala/Function1;
            0     148     1 init$1   Ljava/lang/Object;
           95      13     7 scala$collection$immutable$LazyList$$sCons_tl   Lscala/collection/immutable/LazyList;
           67      11     9 unfold_scala$collection$immutable$LazyList$$newLL_state   Lscala/Function0;
    MethodParameters:
      Name                           Flags
      f$6                            final
      init$1                         final

  private scala.collection.immutable.LazyList$();
    descriptor: ()V
    flags: (0x0002) ACC_PRIVATE
    Code:
      stack=1, locals=1, args_size=1
         0: aload_0
         1: invokespecial #641                // Method java/lang/Object."<init>":()V
         4: return
      LineNumberTable:
        line 969: 0
      LocalVariableTable:
        Start  Length  Slot  Name   Signature
            0       5     0  this   Lscala/collection/immutable/LazyList$;

  private static java.lang.Object $deserializeLambda$(java.lang.invoke.SerializedLambda);
    descriptor: (Ljava/lang/invoke/SerializedLambda;)Ljava/lang/Object;
    flags: (0x100a) ACC_PRIVATE, ACC_STATIC, ACC_SYNTHETIC
    Code:
      stack=1, locals=1, args_size=1
         0: aload_0
         1: invokedynamic #653,  0            // InvokeDynamic #22:lambdaDeserialize:(Ljava/lang/invoke/SerializedLambda;)Ljava/lang/Object;
         6: areturn
}
InnerClasses:
  public static final #13= #10 of #12;    // Lookup=class java/lang/invoke/MethodHandles$Lookup of class java/lang/invoke/MethodHandles
  private static final #18= #15 of #17;   // LazyBuilder=class scala/collection/immutable/LazyList$LazyBuilder of class scala/collection/immutable/LazyList
  private static #21= #20 of #17;         // State=class scala/collection/immutable/LazyList$State of class scala/collection/immutable/LazyList
  private static #24= #23 of #17;         // State$=class scala/collection/immutable/LazyList$State$ of class scala/collection/immutable/LazyList
  public static final #27= #26 of #23;    // Cons=class scala/collection/immutable/LazyList$State$Cons of class scala/collection/immutable/LazyList$State$
  public static #30= #29 of #23;          // Empty$=class scala/collection/immutable/LazyList$State$Empty$ of class scala/collection/immutable/LazyList$State$
Signature: #3                           // Ljava/lang/Object;Lscala/collection/SeqFactory<Lscala/collection/immutable/LazyList;>;
SourceFile: "LazyList.scala"
BootstrapMethods:
  0: #66 REF_invokeStatic java/lang/invoke/LambdaMetafactory.altMetafactory:(Ljava/lang/invoke/MethodHandles$Lookup;Ljava/lang/String;Ljava/lang/invoke/MethodType;[Ljava/lang/Object;)Ljava/lang/invoke/CallSite;
    Method arguments:
      #51 ()Ljava/lang/Object;
      #56 REF_invokeStatic scala/collection/immutable/LazyList$.$anonfun$_empty$1:()Lscala/collection/immutable/LazyList$State$Empty$;
      #57 ()Lscala/collection/immutable/LazyList$State$Empty$;
      #58 5
      #59 1
      #57 ()Lscala/collection/immutable/LazyList$State$Empty$;
  1: #66 REF_invokeStatic java/lang/invoke/LambdaMetafactory.altMetafactory:(Ljava/lang/invoke/MethodHandles$Lookup;Ljava/lang/String;Ljava/lang/invoke/MethodType;[Ljava/lang/Object;)Ljava/lang/invoke/CallSite;
    Method arguments:
      #81 (Ljava/lang/Object;)Ljava/lang/Object;
      #85 REF_invokeStatic scala/collection/immutable/LazyList$.$anonfun$anyToMarker$1:(Ljava/lang/Object;)Ljava/lang/Object;
      #81 (Ljava/lang/Object;)Ljava/lang/Object;
      #59 1
  2: #66 REF_invokeStatic java/lang/invoke/LambdaMetafactory.altMetafactory:(Ljava/lang/invoke/MethodHandles$Lookup;Ljava/lang/String;Ljava/lang/invoke/MethodType;[Ljava/lang/Object;)Ljava/lang/invoke/CallSite;
    Method arguments:
      #51 ()Ljava/lang/Object;
      #218 REF_invokeStatic scala/collection/immutable/LazyList$.$anonfun$filterImpl$1:(Lscala/runtime/ObjectRef;Lscala/Function1;Z)Lscala/collection/immutable/LazyList$State;
      #220 ()Lscala/collection/immutable/LazyList$State;
      #58 5
      #59 1
      #220 ()Lscala/collection/immutable/LazyList$State;
  3: #66 REF_invokeStatic java/lang/invoke/LambdaMetafactory.altMetafactory:(Ljava/lang/invoke/MethodHandles$Lookup;Ljava/lang/String;Ljava/lang/invoke/MethodType;[Ljava/lang/Object;)Ljava/lang/invoke/CallSite;
    Method arguments:
      #51 ()Ljava/lang/Object;
      #233 REF_invokeStatic scala/collection/immutable/LazyList$.$anonfun$collectImpl$1:(Lscala/runtime/ObjectRef;Lscala/PartialFunction;)Lscala/collection/immutable/LazyList$State;
      #220 ()Lscala/collection/immutable/LazyList$State;
      #58 5
      #59 1
      #220 ()Lscala/collection/immutable/LazyList$State;
  4: #66 REF_invokeStatic java/lang/invoke/LambdaMetafactory.altMetafactory:(Ljava/lang/invoke/MethodHandles$Lookup;Ljava/lang/String;Ljava/lang/invoke/MethodType;[Ljava/lang/Object;)Ljava/lang/invoke/CallSite;
    Method arguments:
      #51 ()Ljava/lang/Object;
      #245 REF_invokeStatic scala/collection/immutable/LazyList$.$anonfun$flatMapImpl$1:(Lscala/runtime/ObjectRef;Lscala/Function1;)Lscala/collection/immutable/LazyList$State;
      #220 ()Lscala/collection/immutable/LazyList$State;
      #58 5
      #59 1
      #220 ()Lscala/collection/immutable/LazyList$State;
  5: #66 REF_invokeStatic java/lang/invoke/LambdaMetafactory.altMetafactory:(Ljava/lang/invoke/MethodHandles$Lookup;Ljava/lang/String;Ljava/lang/invoke/MethodType;[Ljava/lang/Object;)Ljava/lang/invoke/CallSite;
    Method arguments:
      #51 ()Ljava/lang/Object;
      #262 REF_invokeStatic scala/collection/immutable/LazyList$.$anonfun$dropImpl$1:(Lscala/runtime/ObjectRef;Lscala/runtime/IntRef;)Lscala/collection/immutable/LazyList$State;
      #220 ()Lscala/collection/immutable/LazyList$State;
      #58 5
      #59 1
      #220 ()Lscala/collection/immutable/LazyList$State;
  6: #66 REF_invokeStatic java/lang/invoke/LambdaMetafactory.altMetafactory:(Ljava/lang/invoke/MethodHandles$Lookup;Ljava/lang/String;Ljava/lang/invoke/MethodType;[Ljava/lang/Object;)Ljava/lang/invoke/CallSite;
    Method arguments:
      #51 ()Ljava/lang/Object;
      #275 REF_invokeStatic scala/collection/immutable/LazyList$.$anonfun$dropWhileImpl$1:(Lscala/runtime/ObjectRef;Lscala/Function1;)Lscala/collection/immutable/LazyList$State;
      #220 ()Lscala/collection/immutable/LazyList$State;
      #58 5
      #59 1
      #220 ()Lscala/collection/immutable/LazyList$State;
  7: #66 REF_invokeStatic java/lang/invoke/LambdaMetafactory.altMetafactory:(Ljava/lang/invoke/MethodHandles$Lookup;Ljava/lang/String;Ljava/lang/invoke/MethodType;[Ljava/lang/Object;)Ljava/lang/invoke/CallSite;
    Method arguments:
      #51 ()Ljava/lang/Object;
      #282 REF_invokeStatic scala/collection/immutable/LazyList$.$anonfun$takeRightImpl$1:(Lscala/runtime/ObjectRef;Lscala/runtime/IntRef;Lscala/runtime/ObjectRef;)Lscala/collection/immutable/LazyList$State;
      #220 ()Lscala/collection/immutable/LazyList$State;
      #58 5
      #59 1
      #220 ()Lscala/collection/immutable/LazyList$State;
  8: #66 REF_invokeStatic java/lang/invoke/LambdaMetafactory.altMetafactory:(Ljava/lang/invoke/MethodHandles$Lookup;Ljava/lang/String;Ljava/lang/invoke/MethodType;[Ljava/lang/Object;)Ljava/lang/invoke/CallSite;
    Method arguments:
      #51 ()Ljava/lang/Object;
      #309 REF_invokeStatic scala/collection/immutable/LazyList$.$anonfun$from$1:(Lscala/collection/IterableOnce;)Lscala/collection/immutable/LazyList$State;
      #220 ()Lscala/collection/immutable/LazyList$State;
      #58 5
      #59 1
      #220 ()Lscala/collection/immutable/LazyList$State;
  9: #66 REF_invokeStatic java/lang/invoke/LambdaMetafactory.altMetafactory:(Ljava/lang/invoke/MethodHandles$Lookup;Ljava/lang/String;Ljava/lang/invoke/MethodType;[Ljava/lang/Object;)Ljava/lang/invoke/CallSite;
    Method arguments:
      #51 ()Ljava/lang/Object;
      #332 REF_invokeStatic scala/collection/immutable/LazyList$.$anonfun$stateFromIteratorConcatSuffix$1:(Lscala/collection/Iterator;Lscala/Function0;)Lscala/collection/immutable/LazyList$State;
      #220 ()Lscala/collection/immutable/LazyList$State;
      #58 5
      #59 1
      #220 ()Lscala/collection/immutable/LazyList$State;
  10: #66 REF_invokeStatic java/lang/invoke/LambdaMetafactory.altMetafactory:(Ljava/lang/invoke/MethodHandles$Lookup;Ljava/lang/String;Ljava/lang/invoke/MethodType;[Ljava/lang/Object;)Ljava/lang/invoke/CallSite;
    Method arguments:
      #51 ()Ljava/lang/Object;
      #349 REF_invokeStatic scala/collection/immutable/LazyList$.$anonfun$stateFromIterator$1:(Lscala/collection/Iterator;)Lscala/collection/immutable/LazyList$State;
      #220 ()Lscala/collection/immutable/LazyList$State;
      #58 5
      #59 1
      #220 ()Lscala/collection/immutable/LazyList$State;
  11: #66 REF_invokeStatic java/lang/invoke/LambdaMetafactory.altMetafactory:(Ljava/lang/invoke/MethodHandles$Lookup;Ljava/lang/String;Ljava/lang/invoke/MethodType;[Ljava/lang/Object;)Ljava/lang/invoke/CallSite;
    Method arguments:
      #51 ()Ljava/lang/Object;
      #367 REF_invokeStatic scala/collection/immutable/LazyList$.$anonfun$concat$1:(Lscala/collection/immutable/Seq;)Lscala/collection/immutable/LazyList$State;
      #220 ()Lscala/collection/immutable/LazyList$State;
      #58 5
      #59 1
      #220 ()Lscala/collection/immutable/LazyList$State;
  12: #66 REF_invokeStatic java/lang/invoke/LambdaMetafactory.altMetafactory:(Ljava/lang/invoke/MethodHandles$Lookup;Ljava/lang/String;Ljava/lang/invoke/MethodType;[Ljava/lang/Object;)Ljava/lang/invoke/CallSite;
    Method arguments:
      #51 ()Ljava/lang/Object;
      #380 REF_invokeStatic scala/collection/immutable/LazyList$.$anonfun$concatIterator$1:(Lscala/collection/Iterator;)Lscala/collection/immutable/LazyList$State;
      #220 ()Lscala/collection/immutable/LazyList$State;
      #58 5
      #59 1
      #220 ()Lscala/collection/immutable/LazyList$State;
  13: #66 REF_invokeStatic java/lang/invoke/LambdaMetafactory.altMetafactory:(Ljava/lang/invoke/MethodHandles$Lookup;Ljava/lang/String;Ljava/lang/invoke/MethodType;[Ljava/lang/Object;)Ljava/lang/invoke/CallSite;
    Method arguments:
      #51 ()Ljava/lang/Object;
      #393 REF_invokeStatic scala/collection/immutable/LazyList$.$anonfun$iterate$1:(Lscala/Function0;Lscala/Function1;)Lscala/collection/immutable/LazyList$State;
      #220 ()Lscala/collection/immutable/LazyList$State;
      #58 5
      #59 1
      #220 ()Lscala/collection/immutable/LazyList$State;
  14: #66 REF_invokeStatic java/lang/invoke/LambdaMetafactory.altMetafactory:(Ljava/lang/invoke/MethodHandles$Lookup;Ljava/lang/String;Ljava/lang/invoke/MethodType;[Ljava/lang/Object;)Ljava/lang/invoke/CallSite;
    Method arguments:
      #51 ()Ljava/lang/Object;
      #403 REF_invokeStatic scala/collection/immutable/LazyList$.$anonfun$from$2:(II)Lscala/collection/immutable/LazyList$State;
      #220 ()Lscala/collection/immutable/LazyList$State;
      #58 5
      #59 1
      #220 ()Lscala/collection/immutable/LazyList$State;
  15: #66 REF_invokeStatic java/lang/invoke/LambdaMetafactory.altMetafactory:(Ljava/lang/invoke/MethodHandles$Lookup;Ljava/lang/String;Ljava/lang/invoke/MethodType;[Ljava/lang/Object;)Ljava/lang/invoke/CallSite;
    Method arguments:
      #51 ()Ljava/lang/Object;
      #417 REF_invokeStatic scala/collection/immutable/LazyList$.$anonfun$continually$1:(Lscala/Function0;)Lscala/collection/immutable/LazyList$State;
      #220 ()Lscala/collection/immutable/LazyList$State;
      #58 5
      #59 1
      #220 ()Lscala/collection/immutable/LazyList$State;
  16: #66 REF_invokeStatic java/lang/invoke/LambdaMetafactory.altMetafactory:(Ljava/lang/invoke/MethodHandles$Lookup;Ljava/lang/String;Ljava/lang/invoke/MethodType;[Ljava/lang/Object;)Ljava/lang/invoke/CallSite;
    Method arguments:
      #51 ()Ljava/lang/Object;
      #426 REF_invokeStatic scala/collection/immutable/LazyList$.$anonfun$fill$1:(Lscala/Function0;I)Lscala/collection/immutable/LazyList$State;
      #220 ()Lscala/collection/immutable/LazyList$State;
      #58 5
      #59 1
      #220 ()Lscala/collection/immutable/LazyList$State;
  17: #66 REF_invokeStatic java/lang/invoke/LambdaMetafactory.altMetafactory:(Ljava/lang/invoke/MethodHandles$Lookup;Ljava/lang/String;Ljava/lang/invoke/MethodType;[Ljava/lang/Object;)Ljava/lang/invoke/CallSite;
    Method arguments:
      #51 ()Ljava/lang/Object;
      #436 REF_invokeStatic scala/collection/immutable/LazyList$.$anonfun$tabulate$1:(Lscala/collection/immutable/LazyList$;Lscala/Function1;II)Lscala/collection/immutable/LazyList$State;
      #220 ()Lscala/collection/immutable/LazyList$State;
      #58 5
      #59 1
      #220 ()Lscala/collection/immutable/LazyList$State;
  18: #66 REF_invokeStatic java/lang/invoke/LambdaMetafactory.altMetafactory:(Ljava/lang/invoke/MethodHandles$Lookup;Ljava/lang/String;Ljava/lang/invoke/MethodType;[Ljava/lang/Object;)Ljava/lang/invoke/CallSite;
    Method arguments:
      #51 ()Ljava/lang/Object;
      #450 REF_invokeStatic scala/collection/immutable/LazyList$.$anonfun$unfold$1:(Lscala/Function1;Ljava/lang/Object;)Lscala/collection/immutable/LazyList$State;
      #220 ()Lscala/collection/immutable/LazyList$State;
      #58 5
      #59 1
      #220 ()Lscala/collection/immutable/LazyList$State;
  19: #66 REF_invokeStatic java/lang/invoke/LambdaMetafactory.altMetafactory:(Ljava/lang/invoke/MethodHandles$Lookup;Ljava/lang/String;Ljava/lang/invoke/MethodType;[Ljava/lang/Object;)Ljava/lang/invoke/CallSite;
    Method arguments:
      #51 ()Ljava/lang/Object;
      #540 REF_invokeStatic scala/collection/immutable/LazyList$.$anonfun$flatMapImpl$3:(Lscala/runtime/ObjectRef;Lscala/Function1;)Lscala/collection/immutable/LazyList$State;
      #220 ()Lscala/collection/immutable/LazyList$State;
      #58 5
      #59 1
      #220 ()Lscala/collection/immutable/LazyList$State;
  20: #66 REF_invokeStatic java/lang/invoke/LambdaMetafactory.altMetafactory:(Ljava/lang/invoke/MethodHandles$Lookup;Ljava/lang/String;Ljava/lang/invoke/MethodType;[Ljava/lang/Object;)Ljava/lang/invoke/CallSite;
    Method arguments:
      #51 ()Ljava/lang/Object;
      #547 REF_invokeStatic scala/collection/immutable/LazyList$.$anonfun$flatMapImpl$2:(Lscala/runtime/ObjectRef;Lscala/runtime/ObjectRef;Lscala/Function1;)Lscala/collection/immutable/LazyList$State;
      #220 ()Lscala/collection/immutable/LazyList$State;
      #58 5
      #59 1
      #220 ()Lscala/collection/immutable/LazyList$State;
  21: #66 REF_invokeStatic java/lang/invoke/LambdaMetafactory.altMetafactory:(Ljava/lang/invoke/MethodHandles$Lookup;Ljava/lang/String;Ljava/lang/invoke/MethodType;[Ljava/lang/Object;)Ljava/lang/invoke/CallSite;
    Method arguments:
      #51 ()Ljava/lang/Object;
      #586 REF_invokeStatic scala/collection/immutable/LazyList$.$anonfun$iterate$2:(Lscala/Function1;Ljava/lang/Object;)Ljava/lang/Object;
      #51 ()Ljava/lang/Object;
      #59 1
  22: #650 REF_invokeStatic scala/runtime/LambdaDeserialize.bootstrap:(Ljava/lang/invoke/MethodHandles$Lookup;Ljava/lang/String;Ljava/lang/invoke/MethodType;[Ljava/lang/invoke/MethodHandle;)Ljava/lang/invoke/CallSite;
    Method arguments:
      #56 REF_invokeStatic scala/collection/immutable/LazyList$.$anonfun$_empty$1:()Lscala/collection/immutable/LazyList$State$Empty$;
      #85 REF_invokeStatic scala/collection/immutable/LazyList$.$anonfun$anyToMarker$1:(Ljava/lang/Object;)Ljava/lang/Object;
      #233 REF_invokeStatic scala/collection/immutable/LazyList$.$anonfun$collectImpl$1:(Lscala/runtime/ObjectRef;Lscala/PartialFunction;)Lscala/collection/immutable/LazyList$State;
      #367 REF_invokeStatic scala/collection/immutable/LazyList$.$anonfun$concat$1:(Lscala/collection/immutable/Seq;)Lscala/collection/immutable/LazyList$State;
      #380 REF_invokeStatic scala/collection/immutable/LazyList$.$anonfun$concatIterator$1:(Lscala/collection/Iterator;)Lscala/collection/immutable/LazyList$State;
      #417 REF_invokeStatic scala/collection/immutable/LazyList$.$anonfun$continually$1:(Lscala/Function0;)Lscala/collection/immutable/LazyList$State;
      #262 REF_invokeStatic scala/collection/immutable/LazyList$.$anonfun$dropImpl$1:(Lscala/runtime/ObjectRef;Lscala/runtime/IntRef;)Lscala/collection/immutable/LazyList$State;
      #275 REF_invokeStatic scala/collection/immutable/LazyList$.$anonfun$dropWhileImpl$1:(Lscala/runtime/ObjectRef;Lscala/Function1;)Lscala/collection/immutable/LazyList$State;
      #426 REF_invokeStatic scala/collection/immutable/LazyList$.$anonfun$fill$1:(Lscala/Function0;I)Lscala/collection/immutable/LazyList$State;
      #218 REF_invokeStatic scala/collection/immutable/LazyList$.$anonfun$filterImpl$1:(Lscala/runtime/ObjectRef;Lscala/Function1;Z)Lscala/collection/immutable/LazyList$State;
      #245 REF_invokeStatic scala/collection/immutable/LazyList$.$anonfun$flatMapImpl$1:(Lscala/runtime/ObjectRef;Lscala/Function1;)Lscala/collection/immutable/LazyList$State;
      #547 REF_invokeStatic scala/collection/immutable/LazyList$.$anonfun$flatMapImpl$2:(Lscala/runtime/ObjectRef;Lscala/runtime/ObjectRef;Lscala/Function1;)Lscala/collection/immutable/LazyList$State;
      #540 REF_invokeStatic scala/collection/immutable/LazyList$.$anonfun$flatMapImpl$3:(Lscala/runtime/ObjectRef;Lscala/Function1;)Lscala/collection/immutable/LazyList$State;
      #309 REF_invokeStatic scala/collection/immutable/LazyList$.$anonfun$from$1:(Lscala/collection/IterableOnce;)Lscala/collection/immutable/LazyList$State;
      #403 REF_invokeStatic scala/collection/immutable/LazyList$.$anonfun$from$2:(II)Lscala/collection/immutable/LazyList$State;
      #393 REF_invokeStatic scala/collection/immutable/LazyList$.$anonfun$iterate$1:(Lscala/Function0;Lscala/Function1;)Lscala/collection/immutable/LazyList$State;
      #586 REF_invokeStatic scala/collection/immutable/LazyList$.$anonfun$iterate$2:(Lscala/Function1;Ljava/lang/Object;)Ljava/lang/Object;
      #349 REF_invokeStatic scala/collection/immutable/LazyList$.$anonfun$stateFromIterator$1:(Lscala/collection/Iterator;)Lscala/collection/immutable/LazyList$State;
      #332 REF_invokeStatic scala/collection/immutable/LazyList$.$anonfun$stateFromIteratorConcatSuffix$1:(Lscala/collection/Iterator;Lscala/Function0;)Lscala/collection/immutable/LazyList$State;
      #436 REF_invokeStatic scala/collection/immutable/LazyList$.$anonfun$tabulate$1:(Lscala/collection/immutable/LazyList$;Lscala/Function1;II)Lscala/collection/immutable/LazyList$State;
      #282 REF_invokeStatic scala/collection/immutable/LazyList$.$anonfun$takeRightImpl$1:(Lscala/runtime/ObjectRef;Lscala/runtime/IntRef;Lscala/runtime/ObjectRef;)Lscala/collection/immutable/LazyList$State;
      #450 REF_invokeStatic scala/collection/immutable/LazyList$.$anonfun$unfold$1:(Lscala/Function1;Ljava/lang/Object;)Lscala/collection/immutable/LazyList$State;
  ScalaInlineInfo: length = 0x15D (unknown attribute)
   01 01 00 45 00 34 00 35 01 00 52 00 50 01 00 E5
   00 E6 01 01 6B 01 6C 01 01 79 01 58 01 01 9D 01
   9E 01 01 02 01 03 01 01 10 00 F2 01 01 A6 01 A7
   01 00 D6 00 D7 01 00 F1 00 F2 01 02 17 02 18 01
   02 0F 00 F2 01 01 31 01 32 01 01 8F 01 90 01 01
   85 01 86 01 02 43 02 44 01 01 5A 01 58 01 01 49
   01 3C 01 01 B0 01 B1 01 01 16 01 17 01 01 BE 01
   BF 01 00 2D 00 2C 01 00 43 00 66 01 02 61 02 62
   01 01 64 00 66 01 01 64 01 65 01 01 73 01 58 01
   01 9B 00 BF 01 01 2E 00 32 01 01 2E 00 4B 01 00
   89 00 9C 01 00 89 00 97 01 00 89 00 92 01 00 89
   00 8A 01 00 89 01 D6 01 00 89 01 A4 01 01 24 01
   97 01 01 24 01 8D 01 01 24 01 DB 01 01 24 01 25
   01 00 B7 00 B8 01 00 6F 00 70 01 00 6F 01 83 01
   01 C6 01 C7 01 00 7A 00 83 01 00 7A 00 7B 01 00
   28 00 56 01 00 E1 00 E2 01 00 F9 00 FA 01 01 0E
   00 EF 01 00 CB 00 CC 01 00 EE 00 EF 01 00 BE 00
   BF 05 00 C2 00 C3 05 01 57 01 58 01 01 3B 01 3C
   01 01 15 00 FA 01 00 A1 00 B2 01 00 A1 00 AD 01
   00 A1 00 A8 01 00 A1 00 A2 01 00 A1 01 D3 01 00
   A1 01 AE 01 01 20 01 21 01 00 5D 00 5E 01 01 BA
   01 D0 01 01 BA 01 BB 01 01 CA 00 32 01
  Scala: length = 0x0 (unknown attribute)

