Classfile /Users/mw/Projects/slang-braindump/.jar/jar8/assemble/slang-braindump/assemble/content/scala/collection/immutable/LazyList$WithFilter.class
  Last modified May 29, 2022; size 5447 bytes
  SHA-256 checksum 456a386b37612a2a6418387362561ca9aed23aea277698c587a661f54e0417a2
  Compiled from "LazyList.scala"
public final class scala.collection.immutable.LazyList$WithFilter<A extends java.lang.Object> extends scala.collection.WithFilter<A, scala.collection.immutable.LazyList>
  minor version: 0
  major version: 52
  flags: (0x0031) ACC_PUBLIC, ACC_FINAL, ACC_SUPER
  this_class: #2                          // scala/collection/immutable/LazyList$WithFilter
  super_class: #5                         // scala/collection/WithFilter
  interfaces: 0, fields: 1, methods: 8, attributes: 6
Constant pool:
    #1 = Utf8               scala/collection/immutable/LazyList$WithFilter
    #2 = Class              #1            // scala/collection/immutable/LazyList$WithFilter
    #3 = Utf8               <A:Ljava/lang/Object;>Lscala/collection/WithFilter<TA;Lscala/collection/immutable/LazyList;>;
    #4 = Utf8               scala/collection/WithFilter
    #5 = Class              #4            // scala/collection/WithFilter
    #6 = Utf8               LazyList.scala
    #7 = Utf8               java/lang/invoke/MethodHandles$Lookup
    #8 = Class              #7            // java/lang/invoke/MethodHandles$Lookup
    #9 = Utf8               java/lang/invoke/MethodHandles
   #10 = Class              #9            // java/lang/invoke/MethodHandles
   #11 = Utf8               Lookup
   #12 = Utf8               scala/collection/immutable/LazyList$State
   #13 = Class              #12           // scala/collection/immutable/LazyList$State
   #14 = Utf8               scala/collection/immutable/LazyList
   #15 = Class              #14           // scala/collection/immutable/LazyList
   #16 = Utf8               State
   #17 = Utf8               scala/collection/immutable/LazyList$State$
   #18 = Class              #17           // scala/collection/immutable/LazyList$State$
   #19 = Utf8               State$
   #20 = Utf8               scala/collection/immutable/LazyList$State$Empty$
   #21 = Class              #20           // scala/collection/immutable/LazyList$State$Empty$
   #22 = Utf8               Empty$
   #23 = Utf8               WithFilter
   #24 = Utf8               filtered
   #25 = Utf8               Lscala/collection/immutable/LazyList;
   #26 = Utf8               Lscala/collection/immutable/LazyList<TA;>;
   #27 = Utf8               map
   #28 = Utf8               (Lscala/Function1;)Lscala/collection/immutable/LazyList;
   #29 = Utf8               <B:Ljava/lang/Object;>(Lscala/Function1<TA;TB;>;)Lscala/collection/immutable/LazyList<TB;>;
   #30 = Utf8               f
   #31 = NameAndType        #24:#25       // filtered:Lscala/collection/immutable/LazyList;
   #32 = Fieldref           #2.#31        // scala/collection/immutable/LazyList$WithFilter.filtered:Lscala/collection/immutable/LazyList;
   #33 = Utf8               scala$collection$immutable$LazyList$$stateEvaluated
   #34 = Utf8               Z
   #35 = NameAndType        #33:#34       // scala$collection$immutable$LazyList$$stateEvaluated:Z
   #36 = Fieldref           #15.#35       // scala/collection/immutable/LazyList.scala$collection$immutable$LazyList$$stateEvaluated:Z
   #37 = Utf8               scala$collection$immutable$LazyList$$state
   #38 = Utf8               ()Lscala/collection/immutable/LazyList$State;
   #39 = NameAndType        #37:#38       // scala$collection$immutable$LazyList$$state:()Lscala/collection/immutable/LazyList$State;
   #40 = Methodref          #15.#39       // scala/collection/immutable/LazyList.scala$collection$immutable$LazyList$$state:()Lscala/collection/immutable/LazyList$State;
   #41 = Utf8               MODULE$
   #42 = Utf8               Lscala/collection/immutable/LazyList$State$Empty$;
   #43 = NameAndType        #41:#42       // MODULE$:Lscala/collection/immutable/LazyList$State$Empty$;
   #44 = Fieldref           #21.#43       // scala/collection/immutable/LazyList$State$Empty$.MODULE$:Lscala/collection/immutable/LazyList$State$Empty$;
   #45 = Utf8               scala/collection/immutable/LazyList$
   #46 = Class              #45           // scala/collection/immutable/LazyList$
   #47 = Utf8               Lscala/collection/immutable/LazyList$;
   #48 = NameAndType        #41:#47       // MODULE$:Lscala/collection/immutable/LazyList$;
   #49 = Fieldref           #46.#48       // scala/collection/immutable/LazyList$.MODULE$:Lscala/collection/immutable/LazyList$;
   #50 = Utf8               empty
   #51 = Utf8               ()Lscala/collection/immutable/LazyList;
   #52 = NameAndType        #50:#51       // empty:()Lscala/collection/immutable/LazyList;
   #53 = Methodref          #46.#52       // scala/collection/immutable/LazyList$.empty:()Lscala/collection/immutable/LazyList;
   #54 = Utf8               ()Ljava/lang/Object;
   #55 = MethodType         #54           //  ()Ljava/lang/Object;
   #56 = Utf8               $anonfun$mapImpl$1
   #57 = Utf8               (Lscala/collection/immutable/LazyList;Lscala/Function1;)Lscala/collection/immutable/LazyList$State;
   #58 = NameAndType        #56:#57       // $anonfun$mapImpl$1:(Lscala/collection/immutable/LazyList;Lscala/Function1;)Lscala/collection/immutable/LazyList$State;
   #59 = Methodref          #15.#58       // scala/collection/immutable/LazyList.$anonfun$mapImpl$1:(Lscala/collection/immutable/LazyList;Lscala/Function1;)Lscala/collection/immutable/LazyList$State;
   #60 = MethodHandle       6:#59         // REF_invokeStatic scala/collection/immutable/LazyList.$anonfun$mapImpl$1:(Lscala/collection/immutable/LazyList;Lscala/Function1;)Lscala/collection/immutable/LazyList$State;
   #61 = MethodType         #38           //  ()Lscala/collection/immutable/LazyList$State;
   #62 = Integer            5
   #63 = Integer            1
   #64 = Utf8               java/lang/invoke/LambdaMetafactory
   #65 = Class              #64           // java/lang/invoke/LambdaMetafactory
   #66 = Utf8               altMetafactory
   #67 = Utf8               (Ljava/lang/invoke/MethodHandles$Lookup;Ljava/lang/String;Ljava/lang/invoke/MethodType;[Ljava/lang/Object;)Ljava/lang/invoke/CallSite;
   #68 = NameAndType        #66:#67       // altMetafactory:(Ljava/lang/invoke/MethodHandles$Lookup;Ljava/lang/String;Ljava/lang/invoke/MethodType;[Ljava/lang/Object;)Ljava/lang/invoke/CallSite;
   #69 = Methodref          #65.#68       // java/lang/invoke/LambdaMetafactory.altMetafactory:(Ljava/lang/invoke/MethodHandles$Lookup;Ljava/lang/String;Ljava/lang/invoke/MethodType;[Ljava/lang/Object;)Ljava/lang/invoke/CallSite;
   #70 = MethodHandle       6:#69         // REF_invokeStatic java/lang/invoke/LambdaMetafactory.altMetafactory:(Ljava/lang/invoke/MethodHandles$Lookup;Ljava/lang/String;Ljava/lang/invoke/MethodType;[Ljava/lang/Object;)Ljava/lang/invoke/CallSite;
   #71 = Utf8               apply
   #72 = Utf8               (Lscala/collection/immutable/LazyList;Lscala/Function1;)Lscala/Function0;
   #73 = NameAndType        #71:#72       // apply:(Lscala/collection/immutable/LazyList;Lscala/Function1;)Lscala/Function0;
   #74 = InvokeDynamic      #0:#73        // #0:apply:(Lscala/collection/immutable/LazyList;Lscala/Function1;)Lscala/Function0;
   #75 = Utf8               <init>
   #76 = Utf8               (Lscala/Function0;)V
   #77 = NameAndType        #75:#76       // "<init>":(Lscala/Function0;)V
   #78 = Methodref          #15.#77       // scala/collection/immutable/LazyList."<init>":(Lscala/Function0;)V
   #79 = Utf8               this
   #80 = Utf8               Lscala/collection/immutable/LazyList$WithFilter;
   #81 = Utf8               Lscala/Function1;
   #82 = Utf8               map_this
   #83 = Utf8               map_mapImpl_scala$collection$immutable$LazyList$$newLL_state
   #84 = Utf8               Lscala/Function0;
   #85 = Utf8               flatMap
   #86 = Utf8               <B:Ljava/lang/Object;>(Lscala/Function1<TA;Lscala/collection/IterableOnce<TB;>;>;)Lscala/collection/immutable/LazyList<TB;>;
   #87 = Utf8               scala/runtime/ObjectRef
   #88 = Class              #87           // scala/runtime/ObjectRef
   #89 = Utf8               (Ljava/lang/Object;)V
   #90 = NameAndType        #75:#89       // "<init>":(Ljava/lang/Object;)V
   #91 = Methodref          #88.#90       // scala/runtime/ObjectRef."<init>":(Ljava/lang/Object;)V
   #92 = Utf8               $anonfun$flatMapImpl$1
   #93 = Utf8               (Lscala/runtime/ObjectRef;Lscala/Function1;)Lscala/collection/immutable/LazyList$State;
   #94 = NameAndType        #92:#93       // $anonfun$flatMapImpl$1:(Lscala/runtime/ObjectRef;Lscala/Function1;)Lscala/collection/immutable/LazyList$State;
   #95 = Methodref          #46.#94       // scala/collection/immutable/LazyList$.$anonfun$flatMapImpl$1:(Lscala/runtime/ObjectRef;Lscala/Function1;)Lscala/collection/immutable/LazyList$State;
   #96 = MethodHandle       6:#95         // REF_invokeStatic scala/collection/immutable/LazyList$.$anonfun$flatMapImpl$1:(Lscala/runtime/ObjectRef;Lscala/Function1;)Lscala/collection/immutable/LazyList$State;
   #97 = Utf8               (Lscala/runtime/ObjectRef;Lscala/Function1;)Lscala/Function0;
   #98 = NameAndType        #71:#97       // apply:(Lscala/runtime/ObjectRef;Lscala/Function1;)Lscala/Function0;
   #99 = InvokeDynamic      #1:#98        // #1:apply:(Lscala/runtime/ObjectRef;Lscala/Function1;)Lscala/Function0;
  #100 = Utf8               flatMap_this
  #101 = Utf8               flatMap_scala$collection$immutable$LazyList$$flatMapImpl_scala$collection$immutable$LazyList$$newLL_state
  #102 = Utf8               foreach
  #103 = Utf8               (Lscala/Function1;)V
  #104 = Utf8               <U:Ljava/lang/Object;>(Lscala/Function1<TA;TU;>;)V
  #105 = Utf8               isEmpty
  #106 = Utf8               ()Z
  #107 = NameAndType        #105:#106     // isEmpty:()Z
  #108 = Methodref          #15.#107      // scala/collection/immutable/LazyList.isEmpty:()Z
  #109 = Utf8               head
  #110 = NameAndType        #109:#54      // head:()Ljava/lang/Object;
  #111 = Methodref          #15.#110      // scala/collection/immutable/LazyList.head:()Ljava/lang/Object;
  #112 = Utf8               scala/Function1
  #113 = Class              #112          // scala/Function1
  #114 = Utf8               (Ljava/lang/Object;)Ljava/lang/Object;
  #115 = NameAndType        #71:#114      // apply:(Ljava/lang/Object;)Ljava/lang/Object;
  #116 = InterfaceMethodref #113.#115     // scala/Function1.apply:(Ljava/lang/Object;)Ljava/lang/Object;
  #117 = Utf8               tail
  #118 = NameAndType        #117:#51      // tail:()Lscala/collection/immutable/LazyList;
  #119 = Methodref          #15.#118      // scala/collection/immutable/LazyList.tail:()Lscala/collection/immutable/LazyList;
  #120 = Utf8               foreach_this
  #121 = Utf8               withFilter
  #122 = Utf8               (Lscala/Function1;)Lscala/collection/WithFilter;
  #123 = Utf8               (Lscala/Function1<TA;Ljava/lang/Object;>;)Lscala/collection/WithFilter<TA;Lscala/collection/immutable/LazyList;>;
  #124 = Utf8               q
  #125 = Utf8               (Lscala/collection/immutable/LazyList;Lscala/Function1;)V
  #126 = NameAndType        #75:#125      // "<init>":(Lscala/collection/immutable/LazyList;Lscala/Function1;)V
  #127 = Methodref          #2.#126       // scala/collection/immutable/LazyList$WithFilter."<init>":(Lscala/collection/immutable/LazyList;Lscala/Function1;)V
  #128 = Utf8               (Lscala/Function1;)Ljava/lang/Object;
  #129 = NameAndType        #85:#28       // flatMap:(Lscala/Function1;)Lscala/collection/immutable/LazyList;
  #130 = Methodref          #2.#129       // scala/collection/immutable/LazyList$WithFilter.flatMap:(Lscala/Function1;)Lscala/collection/immutable/LazyList;
  #131 = NameAndType        #27:#28       // map:(Lscala/Function1;)Lscala/collection/immutable/LazyList;
  #132 = Methodref          #2.#131       // scala/collection/immutable/LazyList$WithFilter.map:(Lscala/Function1;)Lscala/collection/immutable/LazyList;
  #133 = Utf8               (Lscala/collection/immutable/LazyList<TA;>;Lscala/Function1<TA;Ljava/lang/Object;>;)V
  #134 = Utf8               lazyList
  #135 = Utf8               p
  #136 = Utf8               ()V
  #137 = NameAndType        #75:#136      // "<init>":()V
  #138 = Methodref          #5.#137       // scala/collection/WithFilter."<init>":()V
  #139 = Utf8               $anonfun$filterImpl$1
  #140 = Utf8               (Lscala/runtime/ObjectRef;Lscala/Function1;Z)Lscala/collection/immutable/LazyList$State;
  #141 = NameAndType        #139:#140     // $anonfun$filterImpl$1:(Lscala/runtime/ObjectRef;Lscala/Function1;Z)Lscala/collection/immutable/LazyList$State;
  #142 = Methodref          #46.#141      // scala/collection/immutable/LazyList$.$anonfun$filterImpl$1:(Lscala/runtime/ObjectRef;Lscala/Function1;Z)Lscala/collection/immutable/LazyList$State;
  #143 = MethodHandle       6:#142        // REF_invokeStatic scala/collection/immutable/LazyList$.$anonfun$filterImpl$1:(Lscala/runtime/ObjectRef;Lscala/Function1;Z)Lscala/collection/immutable/LazyList$State;
  #144 = Utf8               (Lscala/runtime/ObjectRef;Lscala/Function1;Z)Lscala/Function0;
  #145 = NameAndType        #71:#144      // apply:(Lscala/runtime/ObjectRef;Lscala/Function1;Z)Lscala/Function0;
  #146 = InvokeDynamic      #2:#145       // #2:apply:(Lscala/runtime/ObjectRef;Lscala/Function1;Z)Lscala/Function0;
  #147 = Utf8               filter_scala$collection$immutable$LazyList$$filterImpl_isFlipped
  #148 = Utf8               filter_scala$collection$immutable$LazyList$$filterImpl_scala$collection$immutable$LazyList$$newLL_state
  #149 = Utf8               $deserializeLambda$
  #150 = Utf8               (Ljava/lang/invoke/SerializedLambda;)Ljava/lang/Object;
  #151 = Utf8               scala/runtime/LambdaDeserialize
  #152 = Class              #151          // scala/runtime/LambdaDeserialize
  #153 = Utf8               bootstrap
  #154 = Utf8               (Ljava/lang/invoke/MethodHandles$Lookup;Ljava/lang/String;Ljava/lang/invoke/MethodType;[Ljava/lang/invoke/MethodHandle;)Ljava/lang/invoke/CallSite;
  #155 = NameAndType        #153:#154     // bootstrap:(Ljava/lang/invoke/MethodHandles$Lookup;Ljava/lang/String;Ljava/lang/invoke/MethodType;[Ljava/lang/invoke/MethodHandle;)Ljava/lang/invoke/CallSite;
  #156 = Methodref          #152.#155     // scala/runtime/LambdaDeserialize.bootstrap:(Ljava/lang/invoke/MethodHandles$Lookup;Ljava/lang/String;Ljava/lang/invoke/MethodType;[Ljava/lang/invoke/MethodHandle;)Ljava/lang/invoke/CallSite;
  #157 = MethodHandle       6:#156        // REF_invokeStatic scala/runtime/LambdaDeserialize.bootstrap:(Ljava/lang/invoke/MethodHandles$Lookup;Ljava/lang/String;Ljava/lang/invoke/MethodType;[Ljava/lang/invoke/MethodHandle;)Ljava/lang/invoke/CallSite;
  #158 = Utf8               lambdaDeserialize
  #159 = NameAndType        #158:#150     // lambdaDeserialize:(Ljava/lang/invoke/SerializedLambda;)Ljava/lang/Object;
  #160 = InvokeDynamic      #3:#159       // #3:lambdaDeserialize:(Ljava/lang/invoke/SerializedLambda;)Ljava/lang/Object;
  #161 = Utf8               Signature
  #162 = Utf8               Code
  #163 = Utf8               StackMapTable
  #164 = Utf8               LineNumberTable
  #165 = Utf8               LocalVariableTable
  #166 = Utf8               MethodParameters
  #167 = Utf8               InnerClasses
  #168 = Utf8               SourceFile
  #169 = Utf8               BootstrapMethods
  #170 = Utf8               ScalaInlineInfo
  #171 = Utf8               Scala
{
  private final scala.collection.immutable.LazyList<A> filtered;
    descriptor: Lscala/collection/immutable/LazyList;
    flags: (0x0012) ACC_PRIVATE, ACC_FINAL
    Signature: #26                          // Lscala/collection/immutable/LazyList<TA;>;

  public <B extends java.lang.Object> scala.collection.immutable.LazyList<B> map(scala.Function1<A, B>);
    descriptor: (Lscala/Function1;)Lscala/collection/immutable/LazyList;
    flags: (0x0001) ACC_PUBLIC
    Code:
      stack=3, locals=4, args_size=2
         0: aload_0
         1: getfield      #32                 // Field filtered:Lscala/collection/immutable/LazyList;
         4: dup
         5: ifnonnull     10
         8: aconst_null
         9: athrow
        10: astore_2
        11: aload_2
        12: getfield      #36                 // Field scala/collection/immutable/LazyList.scala$collection$immutable$LazyList$$stateEvaluated:Z
        15: ifeq          40
        18: aload_2
        19: invokevirtual #40                 // Method scala/collection/immutable/LazyList.scala$collection$immutable$LazyList$$state:()Lscala/collection/immutable/LazyList$State;
        22: getstatic     #44                 // Field scala/collection/immutable/LazyList$State$Empty$.MODULE$:Lscala/collection/immutable/LazyList$State$Empty$;
        25: if_acmpne     32
        28: iconst_1
        29: goto          33
        32: iconst_0
        33: ifeq          40
        36: iconst_1
        37: goto          41
        40: iconst_0
        41: ifeq          51
        44: getstatic     #49                 // Field scala/collection/immutable/LazyList$.MODULE$:Lscala/collection/immutable/LazyList$;
        47: invokevirtual #53                 // Method scala/collection/immutable/LazyList$.empty:()Lscala/collection/immutable/LazyList;
        50: areturn
        51: getstatic     #49                 // Field scala/collection/immutable/LazyList$.MODULE$:Lscala/collection/immutable/LazyList$;
        54: pop
        55: aload_2
        56: aload_1
        57: invokedynamic #74,  0             // InvokeDynamic #0:apply:(Lscala/collection/immutable/LazyList;Lscala/Function1;)Lscala/Function0;
        62: astore_3
        63: new           #15                 // class scala/collection/immutable/LazyList
        66: dup
        67: aload_3
        68: invokespecial #78                 // Method scala/collection/immutable/LazyList."<init>":(Lscala/Function0;)V
        71: areturn
      StackMapTable: number_of_entries = 6
        frame_type = 74 /* same_locals_1_stack_item */
          stack = [ class scala/collection/immutable/LazyList ]
        frame_type = 252 /* append */
          offset_delta = 21
          locals = [ class scala/collection/immutable/LazyList ]
        frame_type = 64 /* same_locals_1_stack_item */
          stack = [ int ]
        frame_type = 6 /* same */
        frame_type = 64 /* same_locals_1_stack_item */
          stack = [ int ]
        frame_type = 9 /* same */
      LineNumberTable:
        line 1284: 0
        line 281: 11
        line 269: 18
        line 281: 33
        line 505: 41
        line 515: 51
        line 516: 55
        line 990: 63
        line 1284: 71
      LocalVariableTable:
        Start  Length  Slot  Name   Signature
            0      72     0  this   Lscala/collection/immutable/LazyList$WithFilter;
            0      72     1     f   Lscala/Function1;
           11      60     2 map_this   Lscala/collection/immutable/LazyList;
           63       8     3 map_mapImpl_scala$collection$immutable$LazyList$$newLL_state   Lscala/Function0;
    Signature: #29                          // <B:Ljava/lang/Object;>(Lscala/Function1<TA;TB;>;)Lscala/collection/immutable/LazyList<TB;>;
    MethodParameters:
      Name                           Flags
      f                              final

  public <B extends java.lang.Object> scala.collection.immutable.LazyList<B> flatMap(scala.Function1<A, scala.collection.IterableOnce<B>>);
    descriptor: (Lscala/Function1;)Lscala/collection/immutable/LazyList;
    flags: (0x0001) ACC_PUBLIC
    Code:
      stack=3, locals=4, args_size=2
         0: aload_0
         1: getfield      #32                 // Field filtered:Lscala/collection/immutable/LazyList;
         4: dup
         5: ifnonnull     10
         8: aconst_null
         9: athrow
        10: astore_2
        11: aload_2
        12: getfield      #36                 // Field scala/collection/immutable/LazyList.scala$collection$immutable$LazyList$$stateEvaluated:Z
        15: ifeq          40
        18: aload_2
        19: invokevirtual #40                 // Method scala/collection/immutable/LazyList.scala$collection$immutable$LazyList$$state:()Lscala/collection/immutable/LazyList$State;
        22: getstatic     #44                 // Field scala/collection/immutable/LazyList$State$Empty$.MODULE$:Lscala/collection/immutable/LazyList$State$Empty$;
        25: if_acmpne     32
        28: iconst_1
        29: goto          33
        32: iconst_0
        33: ifeq          40
        36: iconst_1
        37: goto          41
        40: iconst_0
        41: ifeq          51
        44: getstatic     #49                 // Field scala/collection/immutable/LazyList$.MODULE$:Lscala/collection/immutable/LazyList$;
        47: invokevirtual #53                 // Method scala/collection/immutable/LazyList$.empty:()Lscala/collection/immutable/LazyList;
        50: areturn
        51: getstatic     #49                 // Field scala/collection/immutable/LazyList$.MODULE$:Lscala/collection/immutable/LazyList$;
        54: pop
        55: new           #88                 // class scala/runtime/ObjectRef
        58: dup
        59: aload_2
        60: invokespecial #91                 // Method scala/runtime/ObjectRef."<init>":(Ljava/lang/Object;)V
        63: aload_1
        64: invokedynamic #99,  0             // InvokeDynamic #1:apply:(Lscala/runtime/ObjectRef;Lscala/Function1;)Lscala/Function0;
        69: astore_3
        70: new           #15                 // class scala/collection/immutable/LazyList
        73: dup
        74: aload_3
        75: invokespecial #78                 // Method scala/collection/immutable/LazyList."<init>":(Lscala/Function0;)V
        78: areturn
      StackMapTable: number_of_entries = 6
        frame_type = 74 /* same_locals_1_stack_item */
          stack = [ class scala/collection/immutable/LazyList ]
        frame_type = 252 /* append */
          offset_delta = 21
          locals = [ class scala/collection/immutable/LazyList ]
        frame_type = 64 /* same_locals_1_stack_item */
          stack = [ int ]
        frame_type = 6 /* same */
        frame_type = 64 /* same_locals_1_stack_item */
          stack = [ int ]
        frame_type = 9 /* same */
      LineNumberTable:
        line 1285: 0
        line 281: 11
        line 269: 18
        line 281: 33
        line 563: 41
        line 564: 51
        line 1043: 55
        line 1044: 63
        line 990: 70
        line 1285: 78
      LocalVariableTable:
        Start  Length  Slot  Name   Signature
            0      79     0  this   Lscala/collection/immutable/LazyList$WithFilter;
            0      79     1     f   Lscala/Function1;
           11      67     2 flatMap_this   Lscala/collection/immutable/LazyList;
           70       8     3 flatMap_scala$collection$immutable$LazyList$$flatMapImpl_scala$collection$immutable$LazyList$$newLL_state   Lscala/Function0;
    Signature: #86                          // <B:Ljava/lang/Object;>(Lscala/Function1<TA;Lscala/collection/IterableOnce<TB;>;>;)Lscala/collection/immutable/LazyList<TB;>;
    MethodParameters:
      Name                           Flags
      f                              final

  public <U extends java.lang.Object> void foreach(scala.Function1<A, U>);
    descriptor: (Lscala/Function1;)V
    flags: (0x0001) ACC_PUBLIC
    Code:
      stack=2, locals=3, args_size=2
         0: aload_0
         1: getfield      #32                 // Field filtered:Lscala/collection/immutable/LazyList;
         4: dup
         5: ifnonnull     10
         8: aconst_null
         9: athrow
        10: astore_2
        11: aload_2
        12: invokevirtual #108                // Method scala/collection/immutable/LazyList.isEmpty:()Z
        15: ifne          37
        18: aload_1
        19: aload_2
        20: invokevirtual #111                // Method scala/collection/immutable/LazyList.head:()Ljava/lang/Object;
        23: invokeinterface #116,  2          // InterfaceMethod scala/Function1.apply:(Ljava/lang/Object;)Ljava/lang/Object;
        28: pop
        29: aload_2
        30: invokevirtual #119                // Method scala/collection/immutable/LazyList.tail:()Lscala/collection/immutable/LazyList;
        33: astore_2
        34: goto          11
        37: return
      StackMapTable: number_of_entries = 3
        frame_type = 74 /* same_locals_1_stack_item */
          stack = [ class scala/collection/immutable/LazyList ]
        frame_type = 252 /* append */
          offset_delta = 0
          locals = [ class scala/collection/immutable/LazyList ]
        frame_type = 25 /* same */
      LineNumberTable:
        line 1286: 0
        line 342: 11
        line 343: 18
        line 344: 29
        line 1286: 37
      LocalVariableTable:
        Start  Length  Slot  Name   Signature
            0      38     0  this   Lscala/collection/immutable/LazyList$WithFilter;
            0      38     1     f   Lscala/Function1;
           11      26     2 foreach_this   Lscala/collection/immutable/LazyList;
    Signature: #104                         // <U:Ljava/lang/Object;>(Lscala/Function1<TA;TU;>;)V
    MethodParameters:
      Name                           Flags
      f                              final

  public scala.collection.WithFilter<A, scala.collection.immutable.LazyList> withFilter(scala.Function1<A, java.lang.Object>);
    descriptor: (Lscala/Function1;)Lscala/collection/WithFilter;
    flags: (0x0001) ACC_PUBLIC
    Code:
      stack=4, locals=2, args_size=2
         0: new           #2                  // class scala/collection/immutable/LazyList$WithFilter
         3: dup
         4: aload_0
         5: getfield      #32                 // Field filtered:Lscala/collection/immutable/LazyList;
         8: aload_1
         9: invokespecial #127                // Method "<init>":(Lscala/collection/immutable/LazyList;Lscala/Function1;)V
        12: areturn
      LineNumberTable:
        line 1287: 0
      LocalVariableTable:
        Start  Length  Slot  Name   Signature
            0      13     0  this   Lscala/collection/immutable/LazyList$WithFilter;
            0      13     1     q   Lscala/Function1;
    Signature: #123                         // (Lscala/Function1<TA;Ljava/lang/Object;>;)Lscala/collection/WithFilter<TA;Lscala/collection/immutable/LazyList;>;
    MethodParameters:
      Name                           Flags
      q                              final

  public java.lang.Object flatMap(scala.Function1);
    descriptor: (Lscala/Function1;)Ljava/lang/Object;
    flags: (0x1041) ACC_PUBLIC, ACC_BRIDGE, ACC_SYNTHETIC
    Code:
      stack=2, locals=2, args_size=2
         0: aload_0
         1: aload_1
         2: invokevirtual #130                // Method flatMap:(Lscala/Function1;)Lscala/collection/immutable/LazyList;
         5: areturn
      LineNumberTable:
        line 1281: 0
      LocalVariableTable:
        Start  Length  Slot  Name   Signature
            0       6     0  this   Lscala/collection/immutable/LazyList$WithFilter;
            0       6     1     f   Lscala/Function1;
    MethodParameters:
      Name                           Flags
      f                              final

  public java.lang.Object map(scala.Function1);
    descriptor: (Lscala/Function1;)Ljava/lang/Object;
    flags: (0x1041) ACC_PUBLIC, ACC_BRIDGE, ACC_SYNTHETIC
    Code:
      stack=2, locals=2, args_size=2
         0: aload_0
         1: aload_1
         2: invokevirtual #132                // Method map:(Lscala/Function1;)Lscala/collection/immutable/LazyList;
         5: areturn
      LineNumberTable:
        line 1281: 0
      LocalVariableTable:
        Start  Length  Slot  Name   Signature
            0       6     0  this   Lscala/collection/immutable/LazyList$WithFilter;
            0       6     1     f   Lscala/Function1;
    MethodParameters:
      Name                           Flags
      f                              final

  public scala.collection.immutable.LazyList$WithFilter(scala.collection.immutable.LazyList<A>, scala.Function1<A, java.lang.Object>);
    descriptor: (Lscala/collection/immutable/LazyList;Lscala/Function1;)V
    flags: (0x0001) ACC_PUBLIC
    Code:
      stack=4, locals=5, args_size=3
         0: aload_0
         1: invokespecial #138                // Method scala/collection/WithFilter."<init>":()V
         4: aload_0
         5: aload_1
         6: ifnonnull     11
         9: aconst_null
        10: athrow
        11: aload_1
        12: getfield      #36                 // Field scala/collection/immutable/LazyList.scala$collection$immutable$LazyList$$stateEvaluated:Z
        15: ifeq          40
        18: aload_1
        19: invokevirtual #40                 // Method scala/collection/immutable/LazyList.scala$collection$immutable$LazyList$$state:()Lscala/collection/immutable/LazyList$State;
        22: getstatic     #44                 // Field scala/collection/immutable/LazyList$State$Empty$.MODULE$:Lscala/collection/immutable/LazyList$State$Empty$;
        25: if_acmpne     32
        28: iconst_1
        29: goto          33
        32: iconst_0
        33: ifeq          40
        36: iconst_1
        37: goto          41
        40: iconst_0
        41: ifeq          53
        44: getstatic     #49                 // Field scala/collection/immutable/LazyList$.MODULE$:Lscala/collection/immutable/LazyList$;
        47: invokevirtual #53                 // Method scala/collection/immutable/LazyList$.empty:()Lscala/collection/immutable/LazyList;
        50: goto          85
        53: getstatic     #49                 // Field scala/collection/immutable/LazyList$.MODULE$:Lscala/collection/immutable/LazyList$;
        56: pop
        57: iconst_0
        58: istore_3
        59: new           #88                 // class scala/runtime/ObjectRef
        62: dup
        63: aload_1
        64: invokespecial #91                 // Method scala/runtime/ObjectRef."<init>":(Ljava/lang/Object;)V
        67: aload_2
        68: iload_3
        69: invokedynamic #146,  0            // InvokeDynamic #2:apply:(Lscala/runtime/ObjectRef;Lscala/Function1;Z)Lscala/Function0;
        74: astore        4
        76: new           #15                 // class scala/collection/immutable/LazyList
        79: dup
        80: aload         4
        82: invokespecial #78                 // Method scala/collection/immutable/LazyList."<init>":(Lscala/Function0;)V
        85: putfield      #32                 // Field filtered:Lscala/collection/immutable/LazyList;
        88: return
      StackMapTable: number_of_entries = 7
        frame_type = 255 /* full_frame */
          offset_delta = 11
          locals = [ class scala/collection/immutable/LazyList$WithFilter, class scala/collection/immutable/LazyList, class scala/Function1 ]
          stack = [ class scala/collection/immutable/LazyList$WithFilter ]
        frame_type = 84 /* same_locals_1_stack_item */
          stack = [ class scala/collection/immutable/LazyList$WithFilter ]
        frame_type = 255 /* full_frame */
          offset_delta = 0
          locals = [ class scala/collection/immutable/LazyList$WithFilter, class scala/collection/immutable/LazyList, class scala/Function1 ]
          stack = [ class scala/collection/immutable/LazyList$WithFilter, int ]
        frame_type = 70 /* same_locals_1_stack_item */
          stack = [ class scala/collection/immutable/LazyList$WithFilter ]
        frame_type = 255 /* full_frame */
          offset_delta = 0
          locals = [ class scala/collection/immutable/LazyList$WithFilter, class scala/collection/immutable/LazyList, class scala/Function1 ]
          stack = [ class scala/collection/immutable/LazyList$WithFilter, int ]
        frame_type = 75 /* same_locals_1_stack_item */
          stack = [ class scala/collection/immutable/LazyList$WithFilter ]
        frame_type = 255 /* full_frame */
          offset_delta = 31
          locals = [ class scala/collection/immutable/LazyList$WithFilter, class scala/collection/immutable/LazyList, class scala/Function1 ]
          stack = [ class scala/collection/immutable/LazyList$WithFilter, class scala/collection/immutable/LazyList ]
      LineNumberTable:
        line 1282: 0
        line 1283: 4
        line 281: 11
        line 269: 18
        line 281: 33
        line 463: 41
        line 464: 53
        line 1007: 59
        line 1008: 67
        line 990: 76
        line 1283: 85
        line 1281: 88
      LocalVariableTable:
        Start  Length  Slot  Name   Signature
            0      89     0  this   Lscala/collection/immutable/LazyList$WithFilter;
            0      89     1 lazyList   Lscala/collection/immutable/LazyList;
            0      89     2     p   Lscala/Function1;
           59      26     3 filter_scala$collection$immutable$LazyList$$filterImpl_isFlipped   Z
           76       9     4 filter_scala$collection$immutable$LazyList$$filterImpl_scala$collection$immutable$LazyList$$newLL_state   Lscala/Function0;
    Signature: #133                         // (Lscala/collection/immutable/LazyList<TA;>;Lscala/Function1<TA;Ljava/lang/Object;>;)V
    MethodParameters:
      Name                           Flags
      lazyList                       final
      p                              final

  private static java.lang.Object $deserializeLambda$(java.lang.invoke.SerializedLambda);
    descriptor: (Ljava/lang/invoke/SerializedLambda;)Ljava/lang/Object;
    flags: (0x100a) ACC_PRIVATE, ACC_STATIC, ACC_SYNTHETIC
    Code:
      stack=1, locals=1, args_size=1
         0: aload_0
         1: invokedynamic #160,  0            // InvokeDynamic #3:lambdaDeserialize:(Ljava/lang/invoke/SerializedLambda;)Ljava/lang/Object;
         6: areturn
}
InnerClasses:
  public static final #11= #8 of #10;     // Lookup=class java/lang/invoke/MethodHandles$Lookup of class java/lang/invoke/MethodHandles
  private static #16= #13 of #15;         // State=class scala/collection/immutable/LazyList$State of class scala/collection/immutable/LazyList
  private static #19= #18 of #15;         // State$=class scala/collection/immutable/LazyList$State$ of class scala/collection/immutable/LazyList
  public static #22= #21 of #18;          // Empty$=class scala/collection/immutable/LazyList$State$Empty$ of class scala/collection/immutable/LazyList$State$
  private static final #23= #2 of #15;    // WithFilter=class scala/collection/immutable/LazyList$WithFilter of class scala/collection/immutable/LazyList
Signature: #3                           // <A:Ljava/lang/Object;>Lscala/collection/WithFilter<TA;Lscala/collection/immutable/LazyList;>;
SourceFile: "LazyList.scala"
BootstrapMethods:
  0: #70 REF_invokeStatic java/lang/invoke/LambdaMetafactory.altMetafactory:(Ljava/lang/invoke/MethodHandles$Lookup;Ljava/lang/String;Ljava/lang/invoke/MethodType;[Ljava/lang/Object;)Ljava/lang/invoke/CallSite;
    Method arguments:
      #55 ()Ljava/lang/Object;
      #60 REF_invokeStatic scala/collection/immutable/LazyList.$anonfun$mapImpl$1:(Lscala/collection/immutable/LazyList;Lscala/Function1;)Lscala/collection/immutable/LazyList$State;
      #61 ()Lscala/collection/immutable/LazyList$State;
      #62 5
      #63 1
      #61 ()Lscala/collection/immutable/LazyList$State;
  1: #70 REF_invokeStatic java/lang/invoke/LambdaMetafactory.altMetafactory:(Ljava/lang/invoke/MethodHandles$Lookup;Ljava/lang/String;Ljava/lang/invoke/MethodType;[Ljava/lang/Object;)Ljava/lang/invoke/CallSite;
    Method arguments:
      #55 ()Ljava/lang/Object;
      #96 REF_invokeStatic scala/collection/immutable/LazyList$.$anonfun$flatMapImpl$1:(Lscala/runtime/ObjectRef;Lscala/Function1;)Lscala/collection/immutable/LazyList$State;
      #61 ()Lscala/collection/immutable/LazyList$State;
      #62 5
      #63 1
      #61 ()Lscala/collection/immutable/LazyList$State;
  2: #70 REF_invokeStatic java/lang/invoke/LambdaMetafactory.altMetafactory:(Ljava/lang/invoke/MethodHandles$Lookup;Ljava/lang/String;Ljava/lang/invoke/MethodType;[Ljava/lang/Object;)Ljava/lang/invoke/CallSite;
    Method arguments:
      #55 ()Ljava/lang/Object;
      #143 REF_invokeStatic scala/collection/immutable/LazyList$.$anonfun$filterImpl$1:(Lscala/runtime/ObjectRef;Lscala/Function1;Z)Lscala/collection/immutable/LazyList$State;
      #61 ()Lscala/collection/immutable/LazyList$State;
      #62 5
      #63 1
      #61 ()Lscala/collection/immutable/LazyList$State;
  3: #157 REF_invokeStatic scala/runtime/LambdaDeserialize.bootstrap:(Ljava/lang/invoke/MethodHandles$Lookup;Ljava/lang/String;Ljava/lang/invoke/MethodType;[Ljava/lang/invoke/MethodHandle;)Ljava/lang/invoke/CallSite;
    Method arguments:
      #60 REF_invokeStatic scala/collection/immutable/LazyList.$anonfun$mapImpl$1:(Lscala/collection/immutable/LazyList;Lscala/Function1;)Lscala/collection/immutable/LazyList$State;
      #143 REF_invokeStatic scala/collection/immutable/LazyList$.$anonfun$filterImpl$1:(Lscala/runtime/ObjectRef;Lscala/Function1;Z)Lscala/collection/immutable/LazyList$State;
      #96 REF_invokeStatic scala/collection/immutable/LazyList$.$anonfun$flatMapImpl$1:(Lscala/runtime/ObjectRef;Lscala/Function1;)Lscala/collection/immutable/LazyList$State;
  ScalaInlineInfo: length = 0x27 (unknown attribute)
   01 01 00 07 00 4B 00 7D 01 00 55 00 80 01 00 55
   00 1C 01 00 66 00 67 01 00 1B 00 80 01 00 1B 00
   1C 01 00 79 00 7A 01
  Scala: length = 0x0 (unknown attribute)

