Classfile /Users/mw/Projects/slang-braindump/.jar/jar8/assemble/slang-braindump/assemble/content/scala/collection/immutable/LongMap$Bin.class
  Last modified May 29, 2022; size 3989 bytes
  SHA-256 checksum 5dd13ec58694d4d6594aa9ff03b6396358143cb7ccc025300d713dda5ffbd29f
  Compiled from "LongMap.scala"
public class scala.collection.immutable.LongMap$Bin<T extends java.lang.Object> extends scala.collection.immutable.LongMap<T> implements scala.Product
  minor version: 0
  major version: 52
  flags: (0x0021) ACC_PUBLIC, ACC_SUPER
  this_class: #2                          // scala/collection/immutable/LongMap$Bin
  super_class: #5                         // scala/collection/immutable/LongMap
  interfaces: 1, fields: 4, methods: 17, attributes: 5
Constant pool:
    #1 = Utf8               scala/collection/immutable/LongMap$Bin
    #2 = Class              #1            // scala/collection/immutable/LongMap$Bin
    #3 = Utf8               <T:Ljava/lang/Object;>Lscala/collection/immutable/LongMap<TT;>;Lscala/Product;
    #4 = Utf8               scala/collection/immutable/LongMap
    #5 = Class              #4            // scala/collection/immutable/LongMap
    #6 = Utf8               scala/Product
    #7 = Class              #6            // scala/Product
    #8 = Utf8               LongMap.scala
    #9 = Utf8               Bin
   #10 = Utf8               scala/runtime/ScalaRunTime$$anon$1
   #11 = Class              #10           // scala/runtime/ScalaRunTime$$anon$1
   #12 = Utf8               prefix
   #13 = Utf8               J
   #14 = Utf8               mask
   #15 = Utf8               left
   #16 = Utf8               Lscala/collection/immutable/LongMap;
   #17 = Utf8               Lscala/collection/immutable/LongMap<TT;>;
   #18 = Utf8               right
   #19 = Utf8               productElementNames
   #20 = Utf8               ()Lscala/collection/Iterator;
   #21 = Utf8               ()Lscala/collection/Iterator<Ljava/lang/String;>;
   #22 = Utf8               productElementNames$
   #23 = Utf8               (Lscala/Product;)Lscala/collection/Iterator;
   #24 = NameAndType        #22:#23       // productElementNames$:(Lscala/Product;)Lscala/collection/Iterator;
   #25 = InterfaceMethodref #7.#24        // scala/Product.productElementNames$:(Lscala/Product;)Lscala/collection/Iterator;
   #26 = Utf8               this
   #27 = Utf8               Lscala/collection/immutable/LongMap$Bin;
   #28 = Utf8               ()J
   #29 = NameAndType        #12:#13       // prefix:J
   #30 = Fieldref           #2.#29        // scala/collection/immutable/LongMap$Bin.prefix:J
   #31 = NameAndType        #14:#13       // mask:J
   #32 = Fieldref           #2.#31        // scala/collection/immutable/LongMap$Bin.mask:J
   #33 = Utf8               ()Lscala/collection/immutable/LongMap;
   #34 = Utf8               ()Lscala/collection/immutable/LongMap<TT;>;
   #35 = NameAndType        #15:#16       // left:Lscala/collection/immutable/LongMap;
   #36 = Fieldref           #2.#35        // scala/collection/immutable/LongMap$Bin.left:Lscala/collection/immutable/LongMap;
   #37 = NameAndType        #18:#16       // right:Lscala/collection/immutable/LongMap;
   #38 = Fieldref           #2.#37        // scala/collection/immutable/LongMap$Bin.right:Lscala/collection/immutable/LongMap;
   #39 = Utf8               bin
   #40 = Utf8               (Lscala/collection/immutable/LongMap;Lscala/collection/immutable/LongMap;)Lscala/collection/immutable/LongMap;
   #41 = Utf8               <S:Ljava/lang/Object;>(Lscala/collection/immutable/LongMap<TS;>;Lscala/collection/immutable/LongMap<TS;>;)Lscala/collection/immutable/LongMap<TS;>;
   #42 = NameAndType        #15:#33       // left:()Lscala/collection/immutable/LongMap;
   #43 = Methodref          #2.#42        // scala/collection/immutable/LongMap$Bin.left:()Lscala/collection/immutable/LongMap;
   #44 = NameAndType        #18:#33       // right:()Lscala/collection/immutable/LongMap;
   #45 = Methodref          #2.#44        // scala/collection/immutable/LongMap$Bin.right:()Lscala/collection/immutable/LongMap;
   #46 = NameAndType        #12:#28       // prefix:()J
   #47 = Methodref          #2.#46        // scala/collection/immutable/LongMap$Bin.prefix:()J
   #48 = NameAndType        #14:#28       // mask:()J
   #49 = Methodref          #2.#48        // scala/collection/immutable/LongMap$Bin.mask:()J
   #50 = Utf8               <init>
   #51 = Utf8               (JJLscala/collection/immutable/LongMap;Lscala/collection/immutable/LongMap;)V
   #52 = NameAndType        #50:#51       // "<init>":(JJLscala/collection/immutable/LongMap;Lscala/collection/immutable/LongMap;)V
   #53 = Methodref          #2.#52        // scala/collection/immutable/LongMap$Bin."<init>":(JJLscala/collection/immutable/LongMap;Lscala/collection/immutable/LongMap;)V
   #54 = Utf8               copy
   #55 = Utf8               (JJLscala/collection/immutable/LongMap;Lscala/collection/immutable/LongMap;)Lscala/collection/immutable/LongMap$Bin;
   #56 = Utf8               <T:Ljava/lang/Object;>(JJLscala/collection/immutable/LongMap<TT;>;Lscala/collection/immutable/LongMap<TT;>;)Lscala/collection/immutable/LongMap$Bin<TT;>;
   #57 = Utf8               copy$default$1
   #58 = Utf8               <T:Ljava/lang/Object;>()J
   #59 = Utf8               copy$default$2
   #60 = Utf8               copy$default$3
   #61 = Utf8               <T:Ljava/lang/Object;>()Lscala/collection/immutable/LongMap<TT;>;
   #62 = Utf8               copy$default$4
   #63 = Utf8               productPrefix
   #64 = Utf8               ()Ljava/lang/String;
   #65 = String             #9            // Bin
   #66 = Utf8               productArity
   #67 = Utf8               ()I
   #68 = Utf8               productElement
   #69 = Utf8               (I)Ljava/lang/Object;
   #70 = Utf8               x$1
   #71 = Utf8               java/lang/Long
   #72 = Class              #71           // java/lang/Long
   #73 = Utf8               valueOf
   #74 = Utf8               (J)Ljava/lang/Long;
   #75 = NameAndType        #73:#74       // valueOf:(J)Ljava/lang/Long;
   #76 = Methodref          #72.#75       // java/lang/Long.valueOf:(J)Ljava/lang/Long;
   #77 = Utf8               scala/runtime/Statics
   #78 = Class              #77           // scala/runtime/Statics
   #79 = Utf8               ioobe
   #80 = NameAndType        #79:#69       // ioobe:(I)Ljava/lang/Object;
   #81 = Methodref          #78.#80       // scala/runtime/Statics.ioobe:(I)Ljava/lang/Object;
   #82 = Utf8               I
   #83 = Utf8               productIterator
   #84 = Utf8               ()Lscala/collection/Iterator<Ljava/lang/Object;>;
   #85 = Utf8               (Lscala/Product;)V
   #86 = NameAndType        #50:#85       // "<init>":(Lscala/Product;)V
   #87 = Methodref          #11.#86       // scala/runtime/ScalaRunTime$$anon$1."<init>":(Lscala/Product;)V
   #88 = Utf8               productElementName
   #89 = Utf8               (I)Ljava/lang/String;
   #90 = String             #12           // prefix
   #91 = String             #14           // mask
   #92 = String             #15           // left
   #93 = String             #18           // right
   #94 = Utf8               java/lang/String
   #95 = Class              #94           // java/lang/String
   #96 = Utf8               (JJLscala/collection/immutable/LongMap<TT;>;Lscala/collection/immutable/LongMap<TT;>;)V
   #97 = Utf8               ()V
   #98 = NameAndType        #50:#97       // "<init>":()V
   #99 = Methodref          #5.#98        // scala/collection/immutable/LongMap."<init>":()V
  #100 = Utf8               Signature
  #101 = Utf8               Code
  #102 = Utf8               LineNumberTable
  #103 = Utf8               LocalVariableTable
  #104 = Utf8               StackMapTable
  #105 = Utf8               MethodParameters
  #106 = Utf8               InnerClasses
  #107 = Utf8               SourceFile
  #108 = Utf8               ScalaInlineInfo
  #109 = Utf8               Scala
{
  private final long prefix;
    descriptor: J
    flags: (0x0012) ACC_PRIVATE, ACC_FINAL

  private final long mask;
    descriptor: J
    flags: (0x0012) ACC_PRIVATE, ACC_FINAL

  private final scala.collection.immutable.LongMap<T> left;
    descriptor: Lscala/collection/immutable/LongMap;
    flags: (0x0012) ACC_PRIVATE, ACC_FINAL
    Signature: #17                          // Lscala/collection/immutable/LongMap<TT;>;

  private final scala.collection.immutable.LongMap<T> right;
    descriptor: Lscala/collection/immutable/LongMap;
    flags: (0x0012) ACC_PRIVATE, ACC_FINAL
    Signature: #17                          // Lscala/collection/immutable/LongMap<TT;>;

  public scala.collection.Iterator<java.lang.String> productElementNames();
    descriptor: ()Lscala/collection/Iterator;
    flags: (0x0001) ACC_PUBLIC
    Code:
      stack=1, locals=1, args_size=1
         0: aload_0
         1: invokestatic  #25                 // InterfaceMethod scala/Product.productElementNames$:(Lscala/Product;)Lscala/collection/Iterator;
         4: areturn
      LineNumberTable:
        line 78: 0
      LocalVariableTable:
        Start  Length  Slot  Name   Signature
            0       5     0  this   Lscala/collection/immutable/LongMap$Bin;
    Signature: #21                          // ()Lscala/collection/Iterator<Ljava/lang/String;>;

  public long prefix();
    descriptor: ()J
    flags: (0x0001) ACC_PUBLIC
    Code:
      stack=2, locals=1, args_size=1
         0: aload_0
         1: getfield      #30                 // Field prefix:J
         4: lreturn
      LineNumberTable:
        line 78: 0
      LocalVariableTable:
        Start  Length  Slot  Name   Signature
            0       5     0  this   Lscala/collection/immutable/LongMap$Bin;

  public long mask();
    descriptor: ()J
    flags: (0x0001) ACC_PUBLIC
    Code:
      stack=2, locals=1, args_size=1
         0: aload_0
         1: getfield      #32                 // Field mask:J
         4: lreturn
      LineNumberTable:
        line 78: 0
      LocalVariableTable:
        Start  Length  Slot  Name   Signature
            0       5     0  this   Lscala/collection/immutable/LongMap$Bin;

  public scala.collection.immutable.LongMap<T> left();
    descriptor: ()Lscala/collection/immutable/LongMap;
    flags: (0x0001) ACC_PUBLIC
    Code:
      stack=1, locals=1, args_size=1
         0: aload_0
         1: getfield      #36                 // Field left:Lscala/collection/immutable/LongMap;
         4: areturn
      LineNumberTable:
        line 78: 0
      LocalVariableTable:
        Start  Length  Slot  Name   Signature
            0       5     0  this   Lscala/collection/immutable/LongMap$Bin;
    Signature: #34                          // ()Lscala/collection/immutable/LongMap<TT;>;

  public scala.collection.immutable.LongMap<T> right();
    descriptor: ()Lscala/collection/immutable/LongMap;
    flags: (0x0001) ACC_PUBLIC
    Code:
      stack=1, locals=1, args_size=1
         0: aload_0
         1: getfield      #38                 // Field right:Lscala/collection/immutable/LongMap;
         4: areturn
      LineNumberTable:
        line 78: 0
      LocalVariableTable:
        Start  Length  Slot  Name   Signature
            0       5     0  this   Lscala/collection/immutable/LongMap$Bin;
    Signature: #34                          // ()Lscala/collection/immutable/LongMap<TT;>;

  public <S extends java.lang.Object> scala.collection.immutable.LongMap<S> bin(scala.collection.immutable.LongMap<S>, scala.collection.immutable.LongMap<S>);
    descriptor: (Lscala/collection/immutable/LongMap;Lscala/collection/immutable/LongMap;)Lscala/collection/immutable/LongMap;
    flags: (0x0001) ACC_PUBLIC
    Code:
      stack=8, locals=3, args_size=3
         0: aload_0
         1: invokevirtual #43                 // Method left:()Lscala/collection/immutable/LongMap;
         4: aload_1
         5: if_acmpne     18
         8: aload_0
         9: invokevirtual #45                 // Method right:()Lscala/collection/immutable/LongMap;
        12: aload_2
        13: if_acmpne     18
        16: aload_0
        17: areturn
        18: new           #2                  // class scala/collection/immutable/LongMap$Bin
        21: dup
        22: aload_0
        23: invokevirtual #47                 // Method prefix:()J
        26: aload_0
        27: invokevirtual #49                 // Method mask:()J
        30: aload_1
        31: aload_2
        32: invokespecial #53                 // Method "<init>":(JJLscala/collection/immutable/LongMap;Lscala/collection/immutable/LongMap;)V
        35: areturn
      StackMapTable: number_of_entries = 1
        frame_type = 18 /* same */
      LineNumberTable:
        line 80: 0
        line 81: 18
      LocalVariableTable:
        Start  Length  Slot  Name   Signature
            0      36     0  this   Lscala/collection/immutable/LongMap$Bin;
            0      36     1  left   Lscala/collection/immutable/LongMap;
            0      36     2 right   Lscala/collection/immutable/LongMap;
    Signature: #41                          // <S:Ljava/lang/Object;>(Lscala/collection/immutable/LongMap<TS;>;Lscala/collection/immutable/LongMap<TS;>;)Lscala/collection/immutable/LongMap<TS;>;
    MethodParameters:
      Name                           Flags
      left                           final
      right                          final

  public <T extends java.lang.Object> scala.collection.immutable.LongMap$Bin<T> copy(long, long, scala.collection.immutable.LongMap<T>, scala.collection.immutable.LongMap<T>);
    descriptor: (JJLscala/collection/immutable/LongMap;Lscala/collection/immutable/LongMap;)Lscala/collection/immutable/LongMap$Bin;
    flags: (0x0001) ACC_PUBLIC
    Code:
      stack=8, locals=7, args_size=5
         0: new           #2                  // class scala/collection/immutable/LongMap$Bin
         3: dup
         4: lload_1
         5: lload_3
         6: aload         5
         8: aload         6
        10: invokespecial #53                 // Method "<init>":(JJLscala/collection/immutable/LongMap;Lscala/collection/immutable/LongMap;)V
        13: areturn
      LineNumberTable:
        line 78: 0
      LocalVariableTable:
        Start  Length  Slot  Name   Signature
            0      14     0  this   Lscala/collection/immutable/LongMap$Bin;
            0      14     1 prefix   J
            0      14     3  mask   J
            0      14     5  left   Lscala/collection/immutable/LongMap;
            0      14     6 right   Lscala/collection/immutable/LongMap;
    Signature: #56                          // <T:Ljava/lang/Object;>(JJLscala/collection/immutable/LongMap<TT;>;Lscala/collection/immutable/LongMap<TT;>;)Lscala/collection/immutable/LongMap$Bin<TT;>;
    MethodParameters:
      Name                           Flags
      prefix                         final
      mask                           final
      left                           final
      right                          final

  public <T extends java.lang.Object> long copy$default$1();
    descriptor: ()J
    flags: (0x0001) ACC_PUBLIC
    Code:
      stack=2, locals=1, args_size=1
         0: aload_0
         1: invokevirtual #47                 // Method prefix:()J
         4: lreturn
      LineNumberTable:
        line 78: 0
      LocalVariableTable:
        Start  Length  Slot  Name   Signature
            0       5     0  this   Lscala/collection/immutable/LongMap$Bin;
    Signature: #58                          // <T:Ljava/lang/Object;>()J

  public <T extends java.lang.Object> long copy$default$2();
    descriptor: ()J
    flags: (0x0001) ACC_PUBLIC
    Code:
      stack=2, locals=1, args_size=1
         0: aload_0
         1: invokevirtual #49                 // Method mask:()J
         4: lreturn
      LineNumberTable:
        line 78: 0
      LocalVariableTable:
        Start  Length  Slot  Name   Signature
            0       5     0  this   Lscala/collection/immutable/LongMap$Bin;
    Signature: #58                          // <T:Ljava/lang/Object;>()J

  public <T extends java.lang.Object> scala.collection.immutable.LongMap<T> copy$default$3();
    descriptor: ()Lscala/collection/immutable/LongMap;
    flags: (0x0001) ACC_PUBLIC
    Code:
      stack=1, locals=1, args_size=1
         0: aload_0
         1: invokevirtual #43                 // Method left:()Lscala/collection/immutable/LongMap;
         4: areturn
      LineNumberTable:
        line 78: 0
      LocalVariableTable:
        Start  Length  Slot  Name   Signature
            0       5     0  this   Lscala/collection/immutable/LongMap$Bin;
    Signature: #61                          // <T:Ljava/lang/Object;>()Lscala/collection/immutable/LongMap<TT;>;

  public <T extends java.lang.Object> scala.collection.immutable.LongMap<T> copy$default$4();
    descriptor: ()Lscala/collection/immutable/LongMap;
    flags: (0x0001) ACC_PUBLIC
    Code:
      stack=1, locals=1, args_size=1
         0: aload_0
         1: invokevirtual #45                 // Method right:()Lscala/collection/immutable/LongMap;
         4: areturn
      LineNumberTable:
        line 78: 0
      LocalVariableTable:
        Start  Length  Slot  Name   Signature
            0       5     0  this   Lscala/collection/immutable/LongMap$Bin;
    Signature: #61                          // <T:Ljava/lang/Object;>()Lscala/collection/immutable/LongMap<TT;>;

  public java.lang.String productPrefix();
    descriptor: ()Ljava/lang/String;
    flags: (0x0001) ACC_PUBLIC
    Code:
      stack=1, locals=1, args_size=1
         0: ldc           #65                 // String Bin
         2: areturn
      LineNumberTable:
        line 78: 0
      LocalVariableTable:
        Start  Length  Slot  Name   Signature
            0       3     0  this   Lscala/collection/immutable/LongMap$Bin;

  public int productArity();
    descriptor: ()I
    flags: (0x0001) ACC_PUBLIC
    Code:
      stack=1, locals=1, args_size=1
         0: iconst_4
         1: ireturn
      LineNumberTable:
        line 78: 0
      LocalVariableTable:
        Start  Length  Slot  Name   Signature
            0       2     0  this   Lscala/collection/immutable/LongMap$Bin;

  public java.lang.Object productElement(int);
    descriptor: (I)Ljava/lang/Object;
    flags: (0x0001) ACC_PUBLIC
    Code:
      stack=2, locals=2, args_size=2
         0: iload_1
         1: tableswitch   { // 0 to 3
                       0: 32
                       1: 40
                       2: 48
                       3: 53
                 default: 58
            }
        32: aload_0
        33: invokevirtual #47                 // Method prefix:()J
        36: invokestatic  #76                 // Method java/lang/Long.valueOf:(J)Ljava/lang/Long;
        39: areturn
        40: aload_0
        41: invokevirtual #49                 // Method mask:()J
        44: invokestatic  #76                 // Method java/lang/Long.valueOf:(J)Ljava/lang/Long;
        47: areturn
        48: aload_0
        49: invokevirtual #43                 // Method left:()Lscala/collection/immutable/LongMap;
        52: areturn
        53: aload_0
        54: invokevirtual #45                 // Method right:()Lscala/collection/immutable/LongMap;
        57: areturn
        58: iload_1
        59: invokestatic  #81                 // Method scala/runtime/Statics.ioobe:(I)Ljava/lang/Object;
        62: areturn
      StackMapTable: number_of_entries = 5
        frame_type = 32 /* same */
        frame_type = 7 /* same */
        frame_type = 7 /* same */
        frame_type = 4 /* same */
        frame_type = 4 /* same */
      LineNumberTable:
        line 78: 0
      LocalVariableTable:
        Start  Length  Slot  Name   Signature
            0      63     0  this   Lscala/collection/immutable/LongMap$Bin;
            0      63     1   x$1   I
    MethodParameters:
      Name                           Flags
      x$1                            final

  public scala.collection.Iterator<java.lang.Object> productIterator();
    descriptor: ()Lscala/collection/Iterator;
    flags: (0x0001) ACC_PUBLIC
    Code:
      stack=3, locals=1, args_size=1
         0: new           #11                 // class scala/runtime/ScalaRunTime$$anon$1
         3: dup
         4: aload_0
         5: invokespecial #87                 // Method scala/runtime/ScalaRunTime$$anon$1."<init>":(Lscala/Product;)V
         8: areturn
      LineNumberTable:
        line 78: 0
      LocalVariableTable:
        Start  Length  Slot  Name   Signature
            0       9     0  this   Lscala/collection/immutable/LongMap$Bin;
    Signature: #84                          // ()Lscala/collection/Iterator<Ljava/lang/Object;>;

  public java.lang.String productElementName(int);
    descriptor: (I)Ljava/lang/String;
    flags: (0x0001) ACC_PUBLIC
    Code:
      stack=1, locals=2, args_size=2
         0: iload_1
         1: tableswitch   { // 0 to 3
                       0: 32
                       1: 35
                       2: 38
                       3: 41
                 default: 44
            }
        32: ldc           #90                 // String prefix
        34: areturn
        35: ldc           #91                 // String mask
        37: areturn
        38: ldc           #92                 // String left
        40: areturn
        41: ldc           #93                 // String right
        43: areturn
        44: iload_1
        45: invokestatic  #81                 // Method scala/runtime/Statics.ioobe:(I)Ljava/lang/Object;
        48: checkcast     #95                 // class java/lang/String
        51: areturn
      StackMapTable: number_of_entries = 5
        frame_type = 32 /* same */
        frame_type = 2 /* same */
        frame_type = 2 /* same */
        frame_type = 2 /* same */
        frame_type = 2 /* same */
      LineNumberTable:
        line 78: 0
      LocalVariableTable:
        Start  Length  Slot  Name   Signature
            0      52     0  this   Lscala/collection/immutable/LongMap$Bin;
            0      52     1   x$1   I
    MethodParameters:
      Name                           Flags
      x$1                            final

  public scala.collection.immutable.LongMap$Bin(long, long, scala.collection.immutable.LongMap<T>, scala.collection.immutable.LongMap<T>);
    descriptor: (JJLscala/collection/immutable/LongMap;Lscala/collection/immutable/LongMap;)V
    flags: (0x0001) ACC_PUBLIC
    Code:
      stack=3, locals=7, args_size=5
         0: aload_0
         1: lload_1
         2: putfield      #30                 // Field prefix:J
         5: aload_0
         6: lload_3
         7: putfield      #32                 // Field mask:J
        10: aload_0
        11: aload         5
        13: putfield      #36                 // Field left:Lscala/collection/immutable/LongMap;
        16: aload_0
        17: aload         6
        19: putfield      #38                 // Field right:Lscala/collection/immutable/LongMap;
        22: aload_0
        23: invokespecial #99                 // Method scala/collection/immutable/LongMap."<init>":()V
        26: return
      LineNumberTable:
        line 78: 0
      LocalVariableTable:
        Start  Length  Slot  Name   Signature
            0      27     0  this   Lscala/collection/immutable/LongMap$Bin;
            0      27     1 prefix   J
            0      27     3  mask   J
            0      27     5  left   Lscala/collection/immutable/LongMap;
            0      27     6 right   Lscala/collection/immutable/LongMap;
    Signature: #96                          // (JJLscala/collection/immutable/LongMap<TT;>;Lscala/collection/immutable/LongMap<TT;>;)V
    MethodParameters:
      Name                           Flags
      prefix                         final
      mask                           final
      left                           final
      right                          final
}
InnerClasses:
  public static #9= #2 of #5;             // Bin=class scala/collection/immutable/LongMap$Bin of class scala/collection/immutable/LongMap
  public final #11;                       // class scala/runtime/ScalaRunTime$$anon$1
Signature: #3                           // <T:Ljava/lang/Object;>Lscala/collection/immutable/LongMap<TT;>;Lscala/Product;
SourceFile: "LongMap.scala"
  ScalaInlineInfo: length = 0x59 (unknown attribute)
   01 00 00 11 00 32 00 33 00 00 27 00 28 00 00 36
   00 37 00 00 39 00 1C 00 00 3B 00 1C 00 00 3C 00
   21 00 00 3E 00 21 00 00 0F 00 21 00 00 0E 00 1C
   00 00 0C 00 1C 00 00 42 00 43 00 00 44 00 45 00
   00 58 00 59 00 00 13 00 14 00 00 53 00 14 00 00
   3F 00 40 00 00 12 00 21 00
  Scala: length = 0x0 (unknown attribute)

