Classfile /Users/mw/Projects/slang-braindump/.jar/jar8/assemble/slang-braindump/assemble/content/scala/collection/immutable/LongMap$.class
  Last modified May 29, 2022; size 5540 bytes
  SHA-256 checksum 03db6d33f3170c20d68a7caf7b0577933222536da1fa6910f8a8a023e98f8b2c
  Compiled from "LongMap.scala"
public final class scala.collection.immutable.LongMap$ implements java.io.Serializable
  minor version: 0
  major version: 52
  flags: (0x0031) ACC_PUBLIC, ACC_FINAL, ACC_SUPER
  this_class: #2                          // scala/collection/immutable/LongMap$
  super_class: #4                         // java/lang/Object
  interfaces: 1, fields: 1, methods: 14, attributes: 5
Constant pool:
    #1 = Utf8               scala/collection/immutable/LongMap$
    #2 = Class              #1            // scala/collection/immutable/LongMap$
    #3 = Utf8               java/lang/Object
    #4 = Class              #3            // java/lang/Object
    #5 = Utf8               java/io/Serializable
    #6 = Class              #5            // java/io/Serializable
    #7 = Utf8               LongMap.scala
    #8 = Utf8               java/lang/invoke/MethodHandles$Lookup
    #9 = Class              #8            // java/lang/invoke/MethodHandles$Lookup
   #10 = Utf8               java/lang/invoke/MethodHandles
   #11 = Class              #10           // java/lang/invoke/MethodHandles
   #12 = Utf8               Lookup
   #13 = Utf8               scala/collection/immutable/LongMap$$anon$1
   #14 = Class              #13           // scala/collection/immutable/LongMap$$anon$1
   #15 = Utf8               scala/collection/immutable/LongMap$Nil$
   #16 = Class              #15           // scala/collection/immutable/LongMap$Nil$
   #17 = Utf8               scala/collection/immutable/LongMap
   #18 = Class              #17           // scala/collection/immutable/LongMap
   #19 = Utf8               Nil$
   #20 = Utf8               scala/collection/immutable/LongMap$Tip
   #21 = Class              #20           // scala/collection/immutable/LongMap$Tip
   #22 = Utf8               Tip
   #23 = Utf8               scala/collection/immutable/LongMap$ToBuildFrom$
   #24 = Class              #23           // scala/collection/immutable/LongMap$ToBuildFrom$
   #25 = Utf8               ToBuildFrom$
   #26 = Utf8               scala/collection/immutable/LongMap$ToFactory$
   #27 = Class              #26           // scala/collection/immutable/LongMap$ToFactory$
   #28 = Utf8               ToFactory$
   #29 = Utf8               MODULE$
   #30 = Utf8               Lscala/collection/immutable/LongMap$;
   #31 = Utf8               <clinit>
   #32 = Utf8               ()V
   #33 = Utf8               <init>
   #34 = NameAndType        #33:#32       // "<init>":()V
   #35 = Methodref          #2.#34        // scala/collection/immutable/LongMap$."<init>":()V
   #36 = NameAndType        #29:#30       // MODULE$:Lscala/collection/immutable/LongMap$;
   #37 = Fieldref           #2.#36        // scala/collection/immutable/LongMap$.MODULE$:Lscala/collection/immutable/LongMap$;
   #38 = Utf8               empty
   #39 = Utf8               ()Lscala/collection/immutable/LongMap;
   #40 = Utf8               <T:Ljava/lang/Object;>()Lscala/collection/immutable/LongMap<TT;>;
   #41 = Utf8               Lscala/collection/immutable/LongMap$Nil$;
   #42 = NameAndType        #29:#41       // MODULE$:Lscala/collection/immutable/LongMap$Nil$;
   #43 = Fieldref           #16.#42       // scala/collection/immutable/LongMap$Nil$.MODULE$:Lscala/collection/immutable/LongMap$Nil$;
   #44 = Utf8               this
   #45 = Utf8               singleton
   #46 = Utf8               (JLjava/lang/Object;)Lscala/collection/immutable/LongMap;
   #47 = Utf8               <T:Ljava/lang/Object;>(JTT;)Lscala/collection/immutable/LongMap<TT;>;
   #48 = Utf8               key
   #49 = Utf8               value
   #50 = Utf8               (JLjava/lang/Object;)V
   #51 = NameAndType        #33:#50       // "<init>":(JLjava/lang/Object;)V
   #52 = Methodref          #21.#51       // scala/collection/immutable/LongMap$Tip."<init>":(JLjava/lang/Object;)V
   #53 = Utf8               J
   #54 = Utf8               Ljava/lang/Object;
   #55 = Utf8               apply
   #56 = Utf8               (Lscala/collection/immutable/Seq;)Lscala/collection/immutable/LongMap;
   #57 = Utf8               <T:Ljava/lang/Object;>(Lscala/collection/immutable/Seq<Lscala/Tuple2<Ljava/lang/Object;TT;>;>;)Lscala/collection/immutable/LongMap<TT;>;
   #58 = Utf8               elems
   #59 = Utf8               (Ljava/lang/Object;Ljava/lang/Object;)Ljava/lang/Object;
   #60 = MethodType         #59           //  (Ljava/lang/Object;Ljava/lang/Object;)Ljava/lang/Object;
   #61 = Utf8               $anonfun$apply$1
   #62 = Utf8               (Lscala/collection/immutable/LongMap;Lscala/Tuple2;)Lscala/collection/immutable/LongMap;
   #63 = NameAndType        #61:#62       // $anonfun$apply$1:(Lscala/collection/immutable/LongMap;Lscala/Tuple2;)Lscala/collection/immutable/LongMap;
   #64 = Methodref          #2.#63        // scala/collection/immutable/LongMap$.$anonfun$apply$1:(Lscala/collection/immutable/LongMap;Lscala/Tuple2;)Lscala/collection/immutable/LongMap;
   #65 = MethodHandle       6:#64         // REF_invokeStatic scala/collection/immutable/LongMap$.$anonfun$apply$1:(Lscala/collection/immutable/LongMap;Lscala/Tuple2;)Lscala/collection/immutable/LongMap;
   #66 = MethodType         #62           //  (Lscala/collection/immutable/LongMap;Lscala/Tuple2;)Lscala/collection/immutable/LongMap;
   #67 = Integer            5
   #68 = Integer            1
   #69 = Utf8               java/lang/invoke/LambdaMetafactory
   #70 = Class              #69           // java/lang/invoke/LambdaMetafactory
   #71 = Utf8               altMetafactory
   #72 = Utf8               (Ljava/lang/invoke/MethodHandles$Lookup;Ljava/lang/String;Ljava/lang/invoke/MethodType;[Ljava/lang/Object;)Ljava/lang/invoke/CallSite;
   #73 = NameAndType        #71:#72       // altMetafactory:(Ljava/lang/invoke/MethodHandles$Lookup;Ljava/lang/String;Ljava/lang/invoke/MethodType;[Ljava/lang/Object;)Ljava/lang/invoke/CallSite;
   #74 = Methodref          #70.#73       // java/lang/invoke/LambdaMetafactory.altMetafactory:(Ljava/lang/invoke/MethodHandles$Lookup;Ljava/lang/String;Ljava/lang/invoke/MethodType;[Ljava/lang/Object;)Ljava/lang/invoke/CallSite;
   #75 = MethodHandle       6:#74         // REF_invokeStatic java/lang/invoke/LambdaMetafactory.altMetafactory:(Ljava/lang/invoke/MethodHandles$Lookup;Ljava/lang/String;Ljava/lang/invoke/MethodType;[Ljava/lang/Object;)Ljava/lang/invoke/CallSite;
   #76 = Utf8               ()Lscala/Function2;
   #77 = NameAndType        #55:#76       // apply:()Lscala/Function2;
   #78 = InvokeDynamic      #0:#77        // #0:apply:()Lscala/Function2;
   #79 = Utf8               scala/collection/immutable/Seq
   #80 = Class              #79           // scala/collection/immutable/Seq
   #81 = Utf8               foldLeft
   #82 = Utf8               (Ljava/lang/Object;Lscala/Function2;)Ljava/lang/Object;
   #83 = NameAndType        #81:#82       // foldLeft:(Ljava/lang/Object;Lscala/Function2;)Ljava/lang/Object;
   #84 = InterfaceMethodref #80.#83       // scala/collection/immutable/Seq.foldLeft:(Ljava/lang/Object;Lscala/Function2;)Ljava/lang/Object;
   #85 = Utf8               Lscala/collection/immutable/Seq;
   #86 = Utf8               from
   #87 = Utf8               (Lscala/collection/IterableOnce;)Lscala/collection/immutable/LongMap;
   #88 = Utf8               <V:Ljava/lang/Object;>(Lscala/collection/IterableOnce<Lscala/Tuple2<Ljava/lang/Object;TV;>;>;)Lscala/collection/immutable/LongMap<TV;>;
   #89 = Utf8               coll
   #90 = Methodref          #14.#34       // scala/collection/immutable/LongMap$$anon$1."<init>":()V
   #91 = Utf8               scala/collection/mutable/Builder
   #92 = Class              #91           // scala/collection/mutable/Builder
   #93 = Utf8               addAll
   #94 = Utf8               (Lscala/collection/IterableOnce;)Lscala/collection/mutable/Growable;
   #95 = NameAndType        #93:#94       // addAll:(Lscala/collection/IterableOnce;)Lscala/collection/mutable/Growable;
   #96 = InterfaceMethodref #92.#95       // scala/collection/mutable/Builder.addAll:(Lscala/collection/IterableOnce;)Lscala/collection/mutable/Growable;
   #97 = Utf8               result
   #98 = Utf8               ()Ljava/lang/Object;
   #99 = NameAndType        #97:#98       // result:()Ljava/lang/Object;
  #100 = InterfaceMethodref #92.#99       // scala/collection/mutable/Builder.result:()Ljava/lang/Object;
  #101 = Utf8               Lscala/collection/IterableOnce;
  #102 = Utf8               newBuilder
  #103 = Utf8               ()Lscala/collection/mutable/Builder;
  #104 = Utf8               <V:Ljava/lang/Object;>()Lscala/collection/mutable/Builder<Lscala/Tuple2<Ljava/lang/Object;TV;>;Lscala/collection/immutable/LongMap<TV;>;>;
  #105 = Utf8               toFactory
  #106 = Utf8               (Lscala/collection/immutable/LongMap$;)Lscala/collection/Factory;
  #107 = Utf8               <V:Ljava/lang/Object;>(Lscala/collection/immutable/LongMap$;)Lscala/collection/Factory<Lscala/Tuple2<Ljava/lang/Object;TV;>;Lscala/collection/immutable/LongMap<TV;>;>;
  #108 = Utf8               dummy
  #109 = Utf8               Lscala/collection/immutable/LongMap$ToFactory$;
  #110 = NameAndType        #29:#109      // MODULE$:Lscala/collection/immutable/LongMap$ToFactory$;
  #111 = Fieldref           #27.#110      // scala/collection/immutable/LongMap$ToFactory$.MODULE$:Lscala/collection/immutable/LongMap$ToFactory$;
  #112 = Utf8               toBuildFrom
  #113 = Utf8               (Lscala/collection/immutable/LongMap$;)Lscala/collection/BuildFrom;
  #114 = Utf8               <V:Ljava/lang/Object;>(Lscala/collection/immutable/LongMap$;)Lscala/collection/BuildFrom<Ljava/lang/Object;Lscala/Tuple2<Ljava/lang/Object;TV;>;Lscala/collection/immutable/LongMap<TV;>;>;
  #115 = Utf8               factory
  #116 = Utf8               Lscala/collection/immutable/LongMap$ToBuildFrom$;
  #117 = NameAndType        #29:#116      // MODULE$:Lscala/collection/immutable/LongMap$ToBuildFrom$;
  #118 = Fieldref           #24.#117      // scala/collection/immutable/LongMap$ToBuildFrom$.MODULE$:Lscala/collection/immutable/LongMap$ToBuildFrom$;
  #119 = Utf8               iterableFactory
  #120 = Utf8               ()Lscala/collection/Factory;
  #121 = Utf8               <V:Ljava/lang/Object;>()Lscala/collection/Factory<Lscala/Tuple2<Ljava/lang/Object;TV;>;Lscala/collection/immutable/LongMap<TV;>;>;
  #122 = Utf8               buildFromLongMap
  #123 = Utf8               ()Lscala/collection/BuildFrom;
  #124 = Utf8               <V:Ljava/lang/Object;>()Lscala/collection/BuildFrom<Lscala/collection/immutable/LongMap<*>;Lscala/Tuple2<Ljava/lang/Object;TV;>;Lscala/collection/immutable/LongMap<TV;>;>;
  #125 = Utf8               writeReplace
  #126 = Utf8               scala/runtime/ModuleSerializationProxy
  #127 = Class              #126          // scala/runtime/ModuleSerializationProxy
  #128 = Utf8               (Ljava/lang/Class;)V
  #129 = NameAndType        #33:#128      // "<init>":(Ljava/lang/Class;)V
  #130 = Methodref          #127.#129     // scala/runtime/ModuleSerializationProxy."<init>":(Ljava/lang/Class;)V
  #131 = Utf8               x
  #132 = Utf8               y
  #133 = Utf8               scala/Tuple2
  #134 = Class              #133          // scala/Tuple2
  #135 = Utf8               _1$mcJ$sp
  #136 = Utf8               ()J
  #137 = NameAndType        #135:#136     // _1$mcJ$sp:()J
  #138 = Methodref          #134.#137     // scala/Tuple2._1$mcJ$sp:()J
  #139 = Utf8               _2
  #140 = NameAndType        #139:#98      // _2:()Ljava/lang/Object;
  #141 = Methodref          #134.#140     // scala/Tuple2._2:()Ljava/lang/Object;
  #142 = Utf8               updated
  #143 = NameAndType        #142:#46      // updated:(JLjava/lang/Object;)Lscala/collection/immutable/LongMap;
  #144 = Methodref          #18.#143      // scala/collection/immutable/LongMap.updated:(JLjava/lang/Object;)Lscala/collection/immutable/LongMap;
  #145 = Utf8               Lscala/collection/immutable/LongMap;
  #146 = Utf8               Lscala/Tuple2;
  #147 = Methodref          #4.#34        // java/lang/Object."<init>":()V
  #148 = Utf8               $deserializeLambda$
  #149 = Utf8               (Ljava/lang/invoke/SerializedLambda;)Ljava/lang/Object;
  #150 = Utf8               scala/runtime/LambdaDeserialize
  #151 = Class              #150          // scala/runtime/LambdaDeserialize
  #152 = Utf8               bootstrap
  #153 = Utf8               (Ljava/lang/invoke/MethodHandles$Lookup;Ljava/lang/String;Ljava/lang/invoke/MethodType;[Ljava/lang/invoke/MethodHandle;)Ljava/lang/invoke/CallSite;
  #154 = NameAndType        #152:#153     // bootstrap:(Ljava/lang/invoke/MethodHandles$Lookup;Ljava/lang/String;Ljava/lang/invoke/MethodType;[Ljava/lang/invoke/MethodHandle;)Ljava/lang/invoke/CallSite;
  #155 = Methodref          #151.#154     // scala/runtime/LambdaDeserialize.bootstrap:(Ljava/lang/invoke/MethodHandles$Lookup;Ljava/lang/String;Ljava/lang/invoke/MethodType;[Ljava/lang/invoke/MethodHandle;)Ljava/lang/invoke/CallSite;
  #156 = MethodHandle       6:#155        // REF_invokeStatic scala/runtime/LambdaDeserialize.bootstrap:(Ljava/lang/invoke/MethodHandles$Lookup;Ljava/lang/String;Ljava/lang/invoke/MethodType;[Ljava/lang/invoke/MethodHandle;)Ljava/lang/invoke/CallSite;
  #157 = Utf8               lambdaDeserialize
  #158 = NameAndType        #157:#149     // lambdaDeserialize:(Ljava/lang/invoke/SerializedLambda;)Ljava/lang/Object;
  #159 = InvokeDynamic      #1:#158       // #1:lambdaDeserialize:(Ljava/lang/invoke/SerializedLambda;)Ljava/lang/Object;
  #160 = Utf8               Code
  #161 = Utf8               LineNumberTable
  #162 = Utf8               LocalVariableTable
  #163 = Utf8               Signature
  #164 = Utf8               MethodParameters
  #165 = Utf8               InnerClasses
  #166 = Utf8               SourceFile
  #167 = Utf8               BootstrapMethods
  #168 = Utf8               ScalaInlineInfo
  #169 = Utf8               Scala
{
  public static final scala.collection.immutable.LongMap$ MODULE$;
    descriptor: Lscala/collection/immutable/LongMap$;
    flags: (0x0019) ACC_PUBLIC, ACC_STATIC, ACC_FINAL

  public static {};
    descriptor: ()V
    flags: (0x0009) ACC_PUBLIC, ACC_STATIC
    Code:
      stack=2, locals=0, args_size=0
         0: new           #2                  // class scala/collection/immutable/LongMap$
         3: dup
         4: invokespecial #35                 // Method "<init>":()V
         7: putstatic     #37                 // Field MODULE$:Lscala/collection/immutable/LongMap$;
        10: return
      LineNumberTable:
        line 49: 0

  public <T extends java.lang.Object> scala.collection.immutable.LongMap<T> empty();
    descriptor: ()Lscala/collection/immutable/LongMap;
    flags: (0x0001) ACC_PUBLIC
    Code:
      stack=1, locals=1, args_size=1
         0: getstatic     #43                 // Field scala/collection/immutable/LongMap$Nil$.MODULE$:Lscala/collection/immutable/LongMap$Nil$;
         3: areturn
      LineNumberTable:
        line 50: 0
      LocalVariableTable:
        Start  Length  Slot  Name   Signature
            0       4     0  this   Lscala/collection/immutable/LongMap$;
    Signature: #40                          // <T:Ljava/lang/Object;>()Lscala/collection/immutable/LongMap<TT;>;

  public <T extends java.lang.Object> scala.collection.immutable.LongMap<T> singleton(long, T);
    descriptor: (JLjava/lang/Object;)Lscala/collection/immutable/LongMap;
    flags: (0x0001) ACC_PUBLIC
    Code:
      stack=5, locals=4, args_size=3
         0: new           #21                 // class scala/collection/immutable/LongMap$Tip
         3: dup
         4: lload_1
         5: aload_3
         6: invokespecial #52                 // Method scala/collection/immutable/LongMap$Tip."<init>":(JLjava/lang/Object;)V
         9: areturn
      LineNumberTable:
        line 51: 0
      LocalVariableTable:
        Start  Length  Slot  Name   Signature
            0      10     0  this   Lscala/collection/immutable/LongMap$;
            0      10     1   key   J
            0      10     3 value   Ljava/lang/Object;
    Signature: #47                          // <T:Ljava/lang/Object;>(JTT;)Lscala/collection/immutable/LongMap<TT;>;
    MethodParameters:
      Name                           Flags
      key                            final
      value                          final

  public <T extends java.lang.Object> scala.collection.immutable.LongMap<T> apply(scala.collection.immutable.Seq<scala.Tuple2<java.lang.Object, T>>);
    descriptor: (Lscala/collection/immutable/Seq;)Lscala/collection/immutable/LongMap;
    flags: (0x0001) ACC_PUBLIC
    Code:
      stack=3, locals=2, args_size=2
         0: aload_1
         1: getstatic     #43                 // Field scala/collection/immutable/LongMap$Nil$.MODULE$:Lscala/collection/immutable/LongMap$Nil$;
         4: invokedynamic #78,  0             // InvokeDynamic #0:apply:()Lscala/Function2;
         9: invokeinterface #84,  3           // InterfaceMethod scala/collection/immutable/Seq.foldLeft:(Ljava/lang/Object;Lscala/Function2;)Ljava/lang/Object;
        14: checkcast     #18                 // class scala/collection/immutable/LongMap
        17: areturn
      LineNumberTable:
        line 53: 0
        line 50: 1
        line 53: 4
      LocalVariableTable:
        Start  Length  Slot  Name   Signature
            0      18     0  this   Lscala/collection/immutable/LongMap$;
            0      18     1 elems   Lscala/collection/immutable/Seq;
    Signature: #57                          // <T:Ljava/lang/Object;>(Lscala/collection/immutable/Seq<Lscala/Tuple2<Ljava/lang/Object;TT;>;>;)Lscala/collection/immutable/LongMap<TT;>;
    MethodParameters:
      Name                           Flags
      elems                          final

  public <V extends java.lang.Object> scala.collection.immutable.LongMap<V> from(scala.collection.IterableOnce<scala.Tuple2<java.lang.Object, V>>);
    descriptor: (Lscala/collection/IterableOnce;)Lscala/collection/immutable/LongMap;
    flags: (0x0001) ACC_PUBLIC
    Code:
      stack=2, locals=2, args_size=2
         0: new           #14                 // class scala/collection/immutable/LongMap$$anon$1
         3: dup
         4: invokespecial #90                 // Method scala/collection/immutable/LongMap$$anon$1."<init>":()V
         7: aload_1
         8: invokeinterface #96,  2           // InterfaceMethod scala/collection/mutable/Builder.addAll:(Lscala/collection/IterableOnce;)Lscala/collection/mutable/Growable;
        13: checkcast     #92                 // class scala/collection/mutable/Builder
        16: invokeinterface #100,  1          // InterfaceMethod scala/collection/mutable/Builder.result:()Ljava/lang/Object;
        21: checkcast     #18                 // class scala/collection/immutable/LongMap
        24: areturn
      LineNumberTable:
        line 59: 0
        line 56: 7
      LocalVariableTable:
        Start  Length  Slot  Name   Signature
            0      25     0  this   Lscala/collection/immutable/LongMap$;
            0      25     1  coll   Lscala/collection/IterableOnce;
    Signature: #88                          // <V:Ljava/lang/Object;>(Lscala/collection/IterableOnce<Lscala/Tuple2<Ljava/lang/Object;TV;>;>;)Lscala/collection/immutable/LongMap<TV;>;
    MethodParameters:
      Name                           Flags
      coll                           final

  public <V extends java.lang.Object> scala.collection.mutable.Builder<scala.Tuple2<java.lang.Object, V>, scala.collection.immutable.LongMap<V>> newBuilder();
    descriptor: ()Lscala/collection/mutable/Builder;
    flags: (0x0001) ACC_PUBLIC
    Code:
      stack=2, locals=1, args_size=1
         0: new           #14                 // class scala/collection/immutable/LongMap$$anon$1
         3: dup
         4: invokespecial #90                 // Method scala/collection/immutable/LongMap$$anon$1."<init>":()V
         7: areturn
      LineNumberTable:
        line 59: 0
      LocalVariableTable:
        Start  Length  Slot  Name   Signature
            0       8     0  this   Lscala/collection/immutable/LongMap$;
    Signature: #104                         // <V:Ljava/lang/Object;>()Lscala/collection/mutable/Builder<Lscala/Tuple2<Ljava/lang/Object;TV;>;Lscala/collection/immutable/LongMap<TV;>;>;

  public <V extends java.lang.Object> scala.collection.Factory<scala.Tuple2<java.lang.Object, V>, scala.collection.immutable.LongMap<V>> toFactory(scala.collection.immutable.LongMap$);
    descriptor: (Lscala/collection/immutable/LongMap$;)Lscala/collection/Factory;
    flags: (0x0001) ACC_PUBLIC
    Code:
      stack=1, locals=2, args_size=2
         0: getstatic     #111                // Field scala/collection/immutable/LongMap$ToFactory$.MODULE$:Lscala/collection/immutable/LongMap$ToFactory$;
         3: areturn
      LineNumberTable:
        line 85: 0
      LocalVariableTable:
        Start  Length  Slot  Name   Signature
            0       4     0  this   Lscala/collection/immutable/LongMap$;
            0       4     1 dummy   Lscala/collection/immutable/LongMap$;
    Signature: #107                         // <V:Ljava/lang/Object;>(Lscala/collection/immutable/LongMap$;)Lscala/collection/Factory<Lscala/Tuple2<Ljava/lang/Object;TV;>;Lscala/collection/immutable/LongMap<TV;>;>;
    MethodParameters:
      Name                           Flags
      dummy                          final

  public <V extends java.lang.Object> scala.collection.BuildFrom<java.lang.Object, scala.Tuple2<java.lang.Object, V>, scala.collection.immutable.LongMap<V>> toBuildFrom(scala.collection.immutable.LongMap$);
    descriptor: (Lscala/collection/immutable/LongMap$;)Lscala/collection/BuildFrom;
    flags: (0x0001) ACC_PUBLIC
    Code:
      stack=1, locals=2, args_size=2
         0: getstatic     #118                // Field scala/collection/immutable/LongMap$ToBuildFrom$.MODULE$:Lscala/collection/immutable/LongMap$ToBuildFrom$;
         3: areturn
      LineNumberTable:
        line 93: 0
      LocalVariableTable:
        Start  Length  Slot  Name   Signature
            0       4     0  this   Lscala/collection/immutable/LongMap$;
            0       4     1 factory   Lscala/collection/immutable/LongMap$;
    Signature: #114                         // <V:Ljava/lang/Object;>(Lscala/collection/immutable/LongMap$;)Lscala/collection/BuildFrom<Ljava/lang/Object;Lscala/Tuple2<Ljava/lang/Object;TV;>;Lscala/collection/immutable/LongMap<TV;>;>;
    MethodParameters:
      Name                           Flags
      factory                        final

  public <V extends java.lang.Object> scala.collection.Factory<scala.Tuple2<java.lang.Object, V>, scala.collection.immutable.LongMap<V>> iterableFactory();
    descriptor: ()Lscala/collection/Factory;
    flags: (0x0001) ACC_PUBLIC
    Code:
      stack=1, locals=1, args_size=1
         0: getstatic     #111                // Field scala/collection/immutable/LongMap$ToFactory$.MODULE$:Lscala/collection/immutable/LongMap$ToFactory$;
         3: areturn
      LineNumberTable:
        line 85: 0
        line 99: 3
      LocalVariableTable:
        Start  Length  Slot  Name   Signature
            0       4     0  this   Lscala/collection/immutable/LongMap$;
    Signature: #121                         // <V:Ljava/lang/Object;>()Lscala/collection/Factory<Lscala/Tuple2<Ljava/lang/Object;TV;>;Lscala/collection/immutable/LongMap<TV;>;>;

  public <V extends java.lang.Object> scala.collection.BuildFrom<scala.collection.immutable.LongMap<?>, scala.Tuple2<java.lang.Object, V>, scala.collection.immutable.LongMap<V>> buildFromLongMap();
    descriptor: ()Lscala/collection/BuildFrom;
    flags: (0x0001) ACC_PUBLIC
    Code:
      stack=1, locals=1, args_size=1
         0: getstatic     #118                // Field scala/collection/immutable/LongMap$ToBuildFrom$.MODULE$:Lscala/collection/immutable/LongMap$ToBuildFrom$;
         3: areturn
      LineNumberTable:
        line 93: 0
        line 100: 3
      LocalVariableTable:
        Start  Length  Slot  Name   Signature
            0       4     0  this   Lscala/collection/immutable/LongMap$;
    Signature: #124                         // <V:Ljava/lang/Object;>()Lscala/collection/BuildFrom<Lscala/collection/immutable/LongMap<*>;Lscala/Tuple2<Ljava/lang/Object;TV;>;Lscala/collection/immutable/LongMap<TV;>;>;

  private java.lang.Object writeReplace();
    descriptor: ()Ljava/lang/Object;
    flags: (0x0002) ACC_PRIVATE
    Code:
      stack=3, locals=1, args_size=1
         0: new           #127                // class scala/runtime/ModuleSerializationProxy
         3: dup
         4: ldc           #2                  // class scala/collection/immutable/LongMap$
         6: invokespecial #130                // Method scala/runtime/ModuleSerializationProxy."<init>":(Ljava/lang/Class;)V
         9: areturn
      LineNumberTable:
        line 49: 0
      LocalVariableTable:
        Start  Length  Slot  Name   Signature
            0      10     0  this   Lscala/collection/immutable/LongMap$;

  public static final scala.collection.immutable.LongMap $anonfun$apply$1(scala.collection.immutable.LongMap, scala.Tuple2);
    descriptor: (Lscala/collection/immutable/LongMap;Lscala/Tuple2;)Lscala/collection/immutable/LongMap;
    flags: (0x1019) ACC_PUBLIC, ACC_STATIC, ACC_FINAL, ACC_SYNTHETIC
    Code:
      stack=4, locals=2, args_size=2
         0: aload_0
         1: aload_1
         2: invokevirtual #138                // Method scala/Tuple2._1$mcJ$sp:()J
         5: aload_1
         6: invokevirtual #141                // Method scala/Tuple2._2:()Ljava/lang/Object;
         9: invokevirtual #144                // Method scala/collection/immutable/LongMap.updated:(JLjava/lang/Object;)Lscala/collection/immutable/LongMap;
        12: areturn
      LineNumberTable:
        line 53: 0
      LocalVariableTable:
        Start  Length  Slot  Name   Signature
            0      13     0     x   Lscala/collection/immutable/LongMap;
            0      13     1     y   Lscala/Tuple2;
    MethodParameters:
      Name                           Flags
      x                              final
      y                              final

  private scala.collection.immutable.LongMap$();
    descriptor: ()V
    flags: (0x0002) ACC_PRIVATE
    Code:
      stack=1, locals=1, args_size=1
         0: aload_0
         1: invokespecial #147                // Method java/lang/Object."<init>":()V
         4: return
      LineNumberTable:
        line 49: 0
      LocalVariableTable:
        Start  Length  Slot  Name   Signature
            0       5     0  this   Lscala/collection/immutable/LongMap$;

  private static java.lang.Object $deserializeLambda$(java.lang.invoke.SerializedLambda);
    descriptor: (Ljava/lang/invoke/SerializedLambda;)Ljava/lang/Object;
    flags: (0x100a) ACC_PRIVATE, ACC_STATIC, ACC_SYNTHETIC
    Code:
      stack=1, locals=1, args_size=1
         0: aload_0
         1: invokedynamic #159,  0            // InvokeDynamic #1:lambdaDeserialize:(Ljava/lang/invoke/SerializedLambda;)Ljava/lang/Object;
         6: areturn
}
InnerClasses:
  public static final #12= #9 of #11;     // Lookup=class java/lang/invoke/MethodHandles$Lookup of class java/lang/invoke/MethodHandles
  public final #14;                       // class scala/collection/immutable/LongMap$$anon$1
  public static #19= #16 of #18;          // Nil$=class scala/collection/immutable/LongMap$Nil$ of class scala/collection/immutable/LongMap
  public static #22= #21 of #18;          // Tip=class scala/collection/immutable/LongMap$Tip of class scala/collection/immutable/LongMap
  private static #25= #24 of #18;         // ToBuildFrom$=class scala/collection/immutable/LongMap$ToBuildFrom$ of class scala/collection/immutable/LongMap
  private static #28= #27 of #18;         // ToFactory$=class scala/collection/immutable/LongMap$ToFactory$ of class scala/collection/immutable/LongMap
SourceFile: "LongMap.scala"
BootstrapMethods:
  0: #75 REF_invokeStatic java/lang/invoke/LambdaMetafactory.altMetafactory:(Ljava/lang/invoke/MethodHandles$Lookup;Ljava/lang/String;Ljava/lang/invoke/MethodType;[Ljava/lang/Object;)Ljava/lang/invoke/CallSite;
    Method arguments:
      #60 (Ljava/lang/Object;Ljava/lang/Object;)Ljava/lang/Object;
      #65 REF_invokeStatic scala/collection/immutable/LongMap$.$anonfun$apply$1:(Lscala/collection/immutable/LongMap;Lscala/Tuple2;)Lscala/collection/immutable/LongMap;
      #66 (Lscala/collection/immutable/LongMap;Lscala/Tuple2;)Lscala/collection/immutable/LongMap;
      #67 5
      #68 1
      #66 (Lscala/collection/immutable/LongMap;Lscala/Tuple2;)Lscala/collection/immutable/LongMap;
  1: #156 REF_invokeStatic scala/runtime/LambdaDeserialize.bootstrap:(Ljava/lang/invoke/MethodHandles$Lookup;Ljava/lang/String;Ljava/lang/invoke/MethodType;[Ljava/lang/invoke/MethodHandle;)Ljava/lang/invoke/CallSite;
    Method arguments:
      #65 REF_invokeStatic scala/collection/immutable/LongMap$.$anonfun$apply$1:(Lscala/collection/immutable/LongMap;Lscala/Tuple2;)Lscala/collection/immutable/LongMap;
  ScalaInlineInfo: length = 0x40 (unknown attribute)
   01 01 00 0C 00 3D 00 3E 01 00 21 00 20 01 00 37
   00 38 01 00 7A 00 7B 01 00 26 00 27 01 00 56 00
   57 01 00 77 00 78 01 00 66 00 67 01 00 2D 00 2E
   01 00 70 00 71 01 00 69 00 6A 01 00 7D 00 62 01

  Scala: length = 0x0 (unknown attribute)

