Classfile /Users/mw/Projects/slang-braindump/.jar/jar8/assemble/slang-braindump/assemble/content/scala/collection/immutable/LongMapEntryIterator.class
  Last modified May 29, 2022; size 2025 bytes
  SHA-256 checksum a7163dd693fdd55465c150b22d1b11f37689e8fb205f0d162afbe637f6d3ce15
  Compiled from "LongMap.scala"
public class scala.collection.immutable.LongMapEntryIterator<V extends java.lang.Object> extends scala.collection.immutable.LongMapIterator<V, scala.Tuple2<java.lang.Object, V>>
  minor version: 0
  major version: 52
  flags: (0x0021) ACC_PUBLIC, ACC_SUPER
  this_class: #2                          // scala/collection/immutable/LongMapEntryIterator
  super_class: #5                         // scala/collection/immutable/LongMapIterator
  interfaces: 0, fields: 0, methods: 3, attributes: 6
Constant pool:
   #1 = Utf8               scala/collection/immutable/LongMapEntryIterator
   #2 = Class              #1             // scala/collection/immutable/LongMapEntryIterator
   #3 = Utf8               <V:Ljava/lang/Object;>Lscala/collection/immutable/LongMapIterator<TV;Lscala/Tuple2<Ljava/lang/Object;TV;>;>;
   #4 = Utf8               scala/collection/immutable/LongMapIterator
   #5 = Class              #4             // scala/collection/immutable/LongMapIterator
   #6 = Utf8               LongMap.scala
   #7 = Utf8               Lscala/reflect/ScalaSignature;
   #8 = Utf8               bytes
   #9 = Utf8               \u0006\u0005}2Q\u0001B\u0003\u0001\u000b-A\u0001\u0002\f\u0001\u0003\u0002\u0003\u0006I!\f\u0005\u0006a\u0001!\t!\r\u0005\u0006i\u0001!\t!\u000e\u0002\u0015\u0019>tw-T1q\u000b:$(/_%uKJ\fGo\u001c:\u000b\u0005\u00199\u0011!C5n[V$\u0018M\u00197f\u0015\tA\u0011\"\u0001\u0006d_2dWm\u0019;j_:T\u0011AC\u0001\u0006g\u000e\fG.Y\u000b\u0003\u0019M\u0019\"\u0001A\u0007\u0011\t9y\u0011CH\u0007\u0002\u000b%\u0011\u0001#\u0002\u0002\u0010\u0019>tw-T1q\u0013R,\'/\u0019;peB\u0011!c\u0005\u0007\u0001\t\u0015!\u0002A1\u0001\u0017\u0005\u000516\u0001A\t\u0003/m\u0001\"\u0001G\r\u000e\u0003%I!AG\u0005\u0003\u000f9{G\u000f[5oOB\u0011\u0001\u0004H\u0005\u0003;%\u00111!\u00118z!\u0011Ar$I\t\n\u0005\u0001J!A\u0002+va2,\'\u0007\u0005\u0002#K9\u0011abI\u0005\u0003I\u0015\tA\u0002T8oO6\u000b\u0007/\u0016;jYNL!AJ\u0014\u0003\t1{gnZ\u0005\u0003M!R!!\u000b\u0016\u0002\u001b\tKGo\u00149fe\u0006$\u0018n\u001c8t\u0015\tYs!A\u0004hK:,\'/[2\u0002\u0005%$\bc\u0001\b/#%\u0011q&\u0002\u0002\b\u0019>tw-T1q\u0003\u0019a\u0014N\\5u}Q\u0011!g\r\t\u0004\u001d\u0001\t\u0002\"\u0002\u0017\u0003\u0001\u0004i\u0013a\u0002<bYV,wJ\u001a\u000b\u0003=YBQaN\u0002A\u0002a\n1\u0001^5q!\rID(\u0005\b\u0003\u001diJ!aO\u0003\u0002\u000f1{gnZ\'ba&\u0011QH\u0010\u0002\u0004)&\u0004(BA\u001e\u0006\u0001
  #10 = Utf8               scala/collection/immutable/LongMap$Tip
  #11 = Class              #10            // scala/collection/immutable/LongMap$Tip
  #12 = Utf8               scala/collection/immutable/LongMap
  #13 = Class              #12            // scala/collection/immutable/LongMap
  #14 = Utf8               Tip
  #15 = Utf8               valueOf
  #16 = Utf8               (Lscala/collection/immutable/LongMap$Tip;)Lscala/Tuple2;
  #17 = Utf8               (Lscala/collection/immutable/LongMap$Tip<TV;>;)Lscala/Tuple2<Ljava/lang/Object;TV;>;
  #18 = Utf8               tip
  #19 = Utf8               scala/Tuple2
  #20 = Class              #19            // scala/Tuple2
  #21 = Utf8               key
  #22 = Utf8               ()J
  #23 = NameAndType        #21:#22        // key:()J
  #24 = Methodref          #11.#23        // scala/collection/immutable/LongMap$Tip.key:()J
  #25 = Utf8               java/lang/Long
  #26 = Class              #25            // java/lang/Long
  #27 = Utf8               (J)Ljava/lang/Long;
  #28 = NameAndType        #15:#27        // valueOf:(J)Ljava/lang/Long;
  #29 = Methodref          #26.#28        // java/lang/Long.valueOf:(J)Ljava/lang/Long;
  #30 = Utf8               value
  #31 = Utf8               ()Ljava/lang/Object;
  #32 = NameAndType        #30:#31        // value:()Ljava/lang/Object;
  #33 = Methodref          #11.#32        // scala/collection/immutable/LongMap$Tip.value:()Ljava/lang/Object;
  #34 = Utf8               <init>
  #35 = Utf8               (Ljava/lang/Object;Ljava/lang/Object;)V
  #36 = NameAndType        #34:#35        // "<init>":(Ljava/lang/Object;Ljava/lang/Object;)V
  #37 = Methodref          #20.#36        // scala/Tuple2."<init>":(Ljava/lang/Object;Ljava/lang/Object;)V
  #38 = Utf8               this
  #39 = Utf8               Lscala/collection/immutable/LongMapEntryIterator;
  #40 = Utf8               Lscala/collection/immutable/LongMap$Tip;
  #41 = Utf8               (Lscala/collection/immutable/LongMap$Tip;)Ljava/lang/Object;
  #42 = NameAndType        #15:#16        // valueOf:(Lscala/collection/immutable/LongMap$Tip;)Lscala/Tuple2;
  #43 = Methodref          #2.#42         // scala/collection/immutable/LongMapEntryIterator.valueOf:(Lscala/collection/immutable/LongMap$Tip;)Lscala/Tuple2;
  #44 = Utf8               (Lscala/collection/immutable/LongMap;)V
  #45 = Utf8               (Lscala/collection/immutable/LongMap<TV;>;)V
  #46 = Utf8               it
  #47 = NameAndType        #34:#44        // "<init>":(Lscala/collection/immutable/LongMap;)V
  #48 = Methodref          #5.#47         // scala/collection/immutable/LongMapIterator."<init>":(Lscala/collection/immutable/LongMap;)V
  #49 = Utf8               Lscala/collection/immutable/LongMap;
  #50 = Utf8               Code
  #51 = Utf8               LineNumberTable
  #52 = Utf8               LocalVariableTable
  #53 = Utf8               Signature
  #54 = Utf8               MethodParameters
  #55 = Utf8               InnerClasses
  #56 = Utf8               SourceFile
  #57 = Utf8               RuntimeVisibleAnnotations
  #58 = Utf8               ScalaInlineInfo
  #59 = Utf8               ScalaSig
{
  public scala.Tuple2<java.lang.Object, V> valueOf(scala.collection.immutable.LongMap$Tip<V>);
    descriptor: (Lscala/collection/immutable/LongMap$Tip;)Lscala/Tuple2;
    flags: (0x0001) ACC_PUBLIC
    Code:
      stack=4, locals=2, args_size=2
         0: new           #20                 // class scala/Tuple2
         3: dup
         4: aload_1
         5: invokevirtual #24                 // Method scala/collection/immutable/LongMap$Tip.key:()J
         8: invokestatic  #29                 // Method java/lang/Long.valueOf:(J)Ljava/lang/Long;
        11: aload_1
        12: invokevirtual #33                 // Method scala/collection/immutable/LongMap$Tip.value:()Ljava/lang/Object;
        15: invokespecial #37                 // Method scala/Tuple2."<init>":(Ljava/lang/Object;Ljava/lang/Object;)V
        18: areturn
      LineNumberTable:
        line 150: 0
      LocalVariableTable:
        Start  Length  Slot  Name   Signature
            0      19     0  this   Lscala/collection/immutable/LongMapEntryIterator;
            0      19     1   tip   Lscala/collection/immutable/LongMap$Tip;
    Signature: #17                          // (Lscala/collection/immutable/LongMap$Tip<TV;>;)Lscala/Tuple2<Ljava/lang/Object;TV;>;
    MethodParameters:
      Name                           Flags
      tip                            final

  public java.lang.Object valueOf(scala.collection.immutable.LongMap$Tip);
    descriptor: (Lscala/collection/immutable/LongMap$Tip;)Ljava/lang/Object;
    flags: (0x1041) ACC_PUBLIC, ACC_BRIDGE, ACC_SYNTHETIC
    Code:
      stack=2, locals=2, args_size=2
         0: aload_0
         1: aload_1
         2: invokevirtual #43                 // Method valueOf:(Lscala/collection/immutable/LongMap$Tip;)Lscala/Tuple2;
         5: areturn
      LineNumberTable:
        line 149: 0
      LocalVariableTable:
        Start  Length  Slot  Name   Signature
            0       6     0  this   Lscala/collection/immutable/LongMapEntryIterator;
            0       6     1   tip   Lscala/collection/immutable/LongMap$Tip;
    MethodParameters:
      Name                           Flags
      tip                            final

  public scala.collection.immutable.LongMapEntryIterator(scala.collection.immutable.LongMap<V>);
    descriptor: (Lscala/collection/immutable/LongMap;)V
    flags: (0x0001) ACC_PUBLIC
    Code:
      stack=2, locals=2, args_size=2
         0: aload_0
         1: aload_1
         2: invokespecial #48                 // Method scala/collection/immutable/LongMapIterator."<init>":(Lscala/collection/immutable/LongMap;)V
         5: return
      LineNumberTable:
        line 149: 0
      LocalVariableTable:
        Start  Length  Slot  Name   Signature
            0       6     0  this   Lscala/collection/immutable/LongMapEntryIterator;
            0       6     1    it   Lscala/collection/immutable/LongMap;
    Signature: #45                          // (Lscala/collection/immutable/LongMap<TV;>;)V
    MethodParameters:
      Name                           Flags
      it                             final
}
InnerClasses:
  public static #14= #11 of #13;          // Tip=class scala/collection/immutable/LongMap$Tip of class scala/collection/immutable/LongMap
Signature: #3                           // <V:Ljava/lang/Object;>Lscala/collection/immutable/LongMapIterator<TV;Lscala/Tuple2<Ljava/lang/Object;TV;>;>;
SourceFile: "LongMap.scala"
RuntimeVisibleAnnotations:
  0: #7(#8=s#9)
    scala.reflect.ScalaSignature(
      bytes="\u0006\u0005}2Q\u0001B\u0003\u0001\u000b-A\u0001\u0002\f\u0001\u0003\u0002\u0003\u0006I!\f\u0005\u0006a\u0001!\t!\r\u0005\u0006i\u0001!\t!\u000e\u0002\u0015\u0019>tw-T1q\u000b:$(/_%uKJ\fGo\u001c:\u000b\u0005\u00199\u0011!C5n[V$\u0018M\u00197f\u0015\tA\u0011\"\u0001\u0006d_2dWm\u0019;j_:T\u0011AC\u0001\u0006g\u000e\fG.Y\u000b\u0003\u0019M\u0019\"\u0001A\u0007\u0011\t9y\u0011CH\u0007\u0002\u000b%\u0011\u0001#\u0002\u0002\u0010\u0019>tw-T1q\u0013R,\'/\u0019;peB\u0011!c\u0005\u0007\u0001\t\u0015!\u0002A1\u0001\u0017\u0005\u000516\u0001A\t\u0003/m\u0001\"\u0001G\r\u000e\u0003%I!AG\u0005\u0003\u000f9{G\u000f[5oOB\u0011\u0001\u0004H\u0005\u0003;%\u00111!\u00118z!\u0011Ar$I\t\n\u0005\u0001J!A\u0002+va2,\'\u0007\u0005\u0002#K9\u0011abI\u0005\u0003I\u0015\tA\u0002T8oO6\u000b\u0007/\u0016;jYNL!AJ\u0014\u0003\t1{gnZ\u0005\u0003M!R!!\u000b\u0016\u0002\u001b\tKGo\u00149fe\u0006$\u0018n\u001c8t\u0015\tYs!A\u0004hK:,\'/[2\u0002\u0005%$\bc\u0001\b/#%\u0011q&\u0002\u0002\b\u0019>tw-T1q\u0003\u0019a\u0014N\\5u}Q\u0011!g\r\t\u0004\u001d\u0001\t\u0002\"\u0002\u0017\u0003\u0001\u0004i\u0013a\u0002<bYV,wJ\u001a\u000b\u0003=YBQaN\u0002A\u0002a\n1\u0001^5q!\rID(\u0005\b\u0003\u001diJ!aO\u0003\u0002\u000f1{gnZ\'ba&\u0011QH\u0010\u0002\u0004)&\u0004(BA\u001e\u0006\u0001"
    )
  ScalaInlineInfo: length = 0x13 (unknown attribute)
   01 00 00 03 00 22 00 2C 00 00 0F 00 29 00 00 0F
   00 10 00
  ScalaSig: length = 0x3 (unknown attribute)
   05 02 00
