Classfile /Users/mw/Projects/slang-braindump/.jar/jar8/assemble/slang-braindump/assemble/content/scala/collection/immutable/Map$Map3$$anon$4.class
  Last modified May 29, 2022; size 1334 bytes
  SHA-256 checksum c52ae1c5831f4af965a452ff5d522ddc5d0d3ab8f3e5a21666d5a471ebb9f094
  Compiled from "Map.scala"
public final class scala.collection.immutable.Map$Map3$$anon$4 extends scala.collection.immutable.Map$Map3<K, V>.Map3Iterator<scala.Tuple2<K, V>>
  minor version: 0
  major version: 52
  flags: (0x0031) ACC_PUBLIC, ACC_FINAL, ACC_SUPER
  this_class: #2                          // scala/collection/immutable/Map$Map3$$anon$4
  super_class: #5                         // scala/collection/immutable/Map$Map3$Map3Iterator
  interfaces: 0, fields: 0, methods: 3, attributes: 6
Constant pool:
   #1 = Utf8               scala/collection/immutable/Map$Map3$$anon$4
   #2 = Class              #1             // scala/collection/immutable/Map$Map3$$anon$4
   #3 = Utf8               Lscala/collection/immutable/Map$Map3<TK;TV;>.Map3Iterator<Lscala/Tuple2<TK;TV;>;>;
   #4 = Utf8               scala/collection/immutable/Map$Map3$Map3Iterator
   #5 = Class              #4             // scala/collection/immutable/Map$Map3$Map3Iterator
   #6 = Utf8               Map.scala
   #7 = Utf8               scala/collection/immutable/Map$Map3
   #8 = Class              #7             // scala/collection/immutable/Map$Map3
   #9 = Utf8               iterator
  #10 = Utf8               ()Lscala/collection/Iterator;
  #11 = NameAndType        #9:#10         // iterator:()Lscala/collection/Iterator;
  #12 = Utf8               scala/collection/immutable/Map
  #13 = Class              #12            // scala/collection/immutable/Map
  #14 = Utf8               Map3
  #15 = Utf8               Map3Iterator
  #16 = Utf8               nextResult
  #17 = Utf8               (Ljava/lang/Object;Ljava/lang/Object;)Lscala/Tuple2;
  #18 = Utf8               (TK;TV;)Lscala/Tuple2<TK;TV;>;
  #19 = Utf8               k
  #20 = Utf8               v
  #21 = Utf8               scala/Tuple2
  #22 = Class              #21            // scala/Tuple2
  #23 = Utf8               <init>
  #24 = Utf8               (Ljava/lang/Object;Ljava/lang/Object;)V
  #25 = NameAndType        #23:#24        // "<init>":(Ljava/lang/Object;Ljava/lang/Object;)V
  #26 = Methodref          #22.#25        // scala/Tuple2."<init>":(Ljava/lang/Object;Ljava/lang/Object;)V
  #27 = Utf8               this
  #28 = Utf8               Lscala/collection/immutable/Map$Map3$$anon$4;
  #29 = Utf8               Ljava/lang/Object;
  #30 = Utf8               (Ljava/lang/Object;Ljava/lang/Object;)Ljava/lang/Object;
  #31 = NameAndType        #16:#17        // nextResult:(Ljava/lang/Object;Ljava/lang/Object;)Lscala/Tuple2;
  #32 = Methodref          #2.#31         // scala/collection/immutable/Map$Map3$$anon$4.nextResult:(Ljava/lang/Object;Ljava/lang/Object;)Lscala/Tuple2;
  #33 = Utf8               (Lscala/collection/immutable/Map$Map3;)V
  #34 = Utf8               $outer
  #35 = NameAndType        #23:#33        // "<init>":(Lscala/collection/immutable/Map$Map3;)V
  #36 = Methodref          #5.#35         // scala/collection/immutable/Map$Map3$Map3Iterator."<init>":(Lscala/collection/immutable/Map$Map3;)V
  #37 = Utf8               Lscala/collection/immutable/Map$Map3;
  #38 = Utf8               Code
  #39 = Utf8               LineNumberTable
  #40 = Utf8               LocalVariableTable
  #41 = Utf8               Signature
  #42 = Utf8               MethodParameters
  #43 = Utf8               InnerClasses
  #44 = Utf8               EnclosingMethod
  #45 = Utf8               SourceFile
  #46 = Utf8               ScalaInlineInfo
  #47 = Utf8               Scala
{
  public scala.Tuple2<K, V> nextResult(K, V);
    descriptor: (Ljava/lang/Object;Ljava/lang/Object;)Lscala/Tuple2;
    flags: (0x0001) ACC_PUBLIC
    Code:
      stack=4, locals=3, args_size=3
         0: new           #22                 // class scala/Tuple2
         3: dup
         4: aload_1
         5: aload_2
         6: invokespecial #26                 // Method scala/Tuple2."<init>":(Ljava/lang/Object;Ljava/lang/Object;)V
         9: areturn
      LineNumberTable:
        line 412: 0
      LocalVariableTable:
        Start  Length  Slot  Name   Signature
            0      10     0  this   Lscala/collection/immutable/Map$Map3$$anon$4;
            0      10     1     k   Ljava/lang/Object;
            0      10     2     v   Ljava/lang/Object;
    Signature: #18                          // (TK;TV;)Lscala/Tuple2<TK;TV;>;
    MethodParameters:
      Name                           Flags
      k                              final
      v                              final

  public java.lang.Object nextResult(java.lang.Object, java.lang.Object);
    descriptor: (Ljava/lang/Object;Ljava/lang/Object;)Ljava/lang/Object;
    flags: (0x1041) ACC_PUBLIC, ACC_BRIDGE, ACC_SYNTHETIC
    Code:
      stack=3, locals=3, args_size=3
         0: aload_0
         1: aload_1
         2: aload_2
         3: invokevirtual #32                 // Method nextResult:(Ljava/lang/Object;Ljava/lang/Object;)Lscala/Tuple2;
         6: areturn
      LineNumberTable:
        line 411: 0
      LocalVariableTable:
        Start  Length  Slot  Name   Signature
            0       7     0  this   Lscala/collection/immutable/Map$Map3$$anon$4;
            0       7     1     k   Ljava/lang/Object;
            0       7     2     v   Ljava/lang/Object;
    MethodParameters:
      Name                           Flags
      k                              final
      v                              final

  public scala.collection.immutable.Map$Map3$$anon$4(scala.collection.immutable.Map$Map3);
    descriptor: (Lscala/collection/immutable/Map$Map3;)V
    flags: (0x0001) ACC_PUBLIC
    Code:
      stack=2, locals=2, args_size=2
         0: aload_0
         1: aload_1
         2: invokespecial #36                 // Method scala/collection/immutable/Map$Map3$Map3Iterator."<init>":(Lscala/collection/immutable/Map$Map3;)V
         5: return
      LineNumberTable:
        line 411: 0
      LocalVariableTable:
        Start  Length  Slot  Name   Signature
            0       6     0  this   Lscala/collection/immutable/Map$Map3$$anon$4;
            0       6     1 $outer   Lscala/collection/immutable/Map$Map3;
    MethodParameters:
      Name                           Flags
      $outer                         final synthetic
}
InnerClasses:
  public static #14= #8 of #13;           // Map3=class scala/collection/immutable/Map$Map3 of class scala/collection/immutable/Map
  public final #2;                        // class scala/collection/immutable/Map$Map3$$anon$4
  private abstract #15= #5 of #8;         // Map3Iterator=class scala/collection/immutable/Map$Map3$Map3Iterator of class scala/collection/immutable/Map$Map3
EnclosingMethod: #8.#11                 // scala.collection.immutable.Map$Map3.iterator
Signature: #3                           // Lscala/collection/immutable/Map$Map3<TK;TV;>.Map3Iterator<Lscala/Tuple2<TK;TV;>;>;
SourceFile: "Map.scala"
  ScalaInlineInfo: length = 0x13 (unknown attribute)
   01 01 00 03 00 17 00 21 01 00 10 00 1E 01 00 10
   00 11 01
  Scala: length = 0x0 (unknown attribute)

