Classfile /Users/mw/Projects/slang-braindump/.jar/jar8/assemble/slang-braindump/assemble/content/scala/collection/immutable/NewVectorIterator.class
  Last modified May 29, 2022; size 34916 bytes
  SHA-256 checksum 4fa26f17063a786157cc4467f633b062bf73ebe16b19fa045d7b66889c5df665
  Compiled from "Vector.scala"
public final class scala.collection.immutable.NewVectorIterator<A extends java.lang.Object> extends java.lang.Object implements scala.collection.Iterator<A>, java.lang.Cloneable
  minor version: 0
  major version: 52
  flags: (0x0031) ACC_PUBLIC, ACC_FINAL, ACC_SUPER
  this_class: #2                          // scala/collection/immutable/NewVectorIterator
  super_class: #5                         // java/lang/Object
  interfaces: 2, fields: 17, methods: 125, attributes: 6
Constant pool:
    #1 = Utf8               scala/collection/immutable/NewVectorIterator
    #2 = Class              #1            // scala/collection/immutable/NewVectorIterator
    #3 = Utf8               <A:Ljava/lang/Object;>Ljava/lang/Object;Lscala/collection/Iterator<TA;>;Ljava/lang/Cloneable;
    #4 = Utf8               java/lang/Object
    #5 = Class              #4            // java/lang/Object
    #6 = Utf8               scala/collection/Iterator
    #7 = Class              #6            // scala/collection/Iterator
    #8 = Utf8               java/lang/Cloneable
    #9 = Class              #8            // java/lang/Cloneable
   #10 = Utf8               Vector.scala
   #11 = Utf8               Lscala/reflect/ScalaSignature;
   #12 = Utf8               bytes
   #13 = Utf8               \u0006\u0005\u0005\u001de\u0001\u0002\u0011\"\r!B\u0001\"\u0012\u0001\u0003\u0002\u0003\u0006IA\u0012\u0005\t\u0015\u0002\u0011\t\u0011)Q\u0005\u0017\"Aa\n\u0001B\u0001B\u0003%1\nC\u0003P\u0001\u0011\u0005\u0001\u000b\u0003\u0004V\u0001\u0001\u0006KA\u0016\u0005\nM\u0002\u0001\r\u0011!Q!\n\u001dD\u0011B\u001b\u0001A\u0002\u0003\u0005\u000b\u0015B6\t\u00139\u0004\u0001\u0019!A!B\u0013y\u0007\"\u0003:\u0001\u0001\u0004\u0005\t\u0015)\u0003t\u0011%1\b\u00011A\u0001B\u0003&q\u000f\u0003\u0004{\u0001\u0001\u0006Ka\u0013\u0005\rw\u0002!\t\u0011!B\u0001\u0002\u0003\u0006Ka\u0013\u0005\u0007y\u0002\u0001\u000b\u0015B&\t\u0019u\u0004A\u0011!A\u0003\u0002\u0003\u0005\u000b\u0015B&\t\ry\u0004\u0001\u0015)\u0003L\u0011\u0019y\b\u0001)Q\u0005\u0017\"9\u0011\u0011\u0001\u0001!B\u0013Y\u0005bBA\u0002\u0001\u0001\u0006Ka\u0013\u0005\b\u0003\u000b\u0001A\u0011IA\u0004\u0011\u001d\t\t\u0002\u0001C\u0001\u0003\'Aq!!\b\u0001\t\u0003\ty\u0002\u0003\u0005\u0002\"\u0001\u0001K\u0011BA\u0012\u0011!\tY\u0003\u0001Q\u0005\n\u0005\r\u0002\u0002CA\u0017\u0001\u0001&I!a\f\t\u0011\u0005e\u0002\u0001)C\u0005\u0003wAq!!\u0011\u0001\t\u0003\n\u0019\u0005C\u0004\u0002J\u0001!\t%a\u0013\t\u000f\u0005=\u0003\u0001\"\u0011\u0002R!9\u00111\f\u0001\u0005B\u0005u\u0003bBA>\u0001\u0011\u0005\u0013Q\u0010\u0005\t\u0003\u007f\u0002A\u0011C\u0011\u0002\u0002\n\tb*Z<WK\u000e$xN]%uKJ\fGo\u001c:\u000b\u0005\t\u001a\u0013!C5n[V$\u0018M\u00197f\u0015\t!S%\u0001\u0006d_2dWm\u0019;j_:T\u0011AJ\u0001\u0006g\u000e\fG.Y\u0002\u0001+\tICg\u0005\u0003\u0001U9j\u0004CA\u0016-\u001b\u0005)\u0013BA\u0017&\u0005\u0019\te.\u001f*fMB\u0019q\u0006\r\u001a\u000e\u0003\rJ!!M\u0012\u0003\u0011%#XM]1u_J\u0004\"a\r\u001b\r\u0001\u0011)Q\u0007\u0001b\u0001m\t\t\u0011)\u0005\u00028uA\u00111\u0006O\u0005\u0003s\u0015\u0012qAT8uQ&tw\r\u0005\u0002,w%\u0011A(\n\u0002\u0004\u0003:L\bC\u0001 D\u001b\u0005y$B\u0001!B\u0003\u0011a\u0017M\\4\u000b\u0003\t\u000bAA[1wC&\u0011Ai\u0010\u0002\n\u00072|g.Z1cY\u0016\f\u0011A\u001e\t\u0004\u000f\"\u0013T\"A\u0011\n\u0005%\u000b#A\u0002,fGR|\'/A\u0006u_R\fG\u000eT3oORD\u0007CA\u0016M\u0013\tiUEA\u0002J]R\f!b\u001d7jG\u0016\u001cu.\u001e8u\u0003\u0019a\u0014N\\5u}Q!\u0011KU*U!\r9\u0005A\r\u0005\u0006\u000b\u0012\u0001\rA\u0012\u0005\u0006\u0015\u0012\u0001\ra\u0013\u0005\u0006\u001d\u0012\u0001\raS\u0001\u0003CF\u0002\"aV2\u000f\u0005a\u000bgBA-a\u001d\tQvL\u0004\u0002\\=6\tAL\u0003\u0002^O\u00051AH]8pizJ\u0011AJ\u0005\u0003I\u0015J!AI\u0012\n\u0005\t\f\u0013\u0001\u0004,fGR|\'/\u00138mS:,\u0017B\u00013f\u0005\u0011\t%O]\u0019\u000b\u0005\t\f\u0013AA13!\t9\u0006.\u0003\u0002jK\n!\u0011I\u001d:3\u0003\t\t7\u0007\u0005\u0002XY&\u0011Q.\u001a\u0002\u0005\u0003J\u00148\'\u0001\u0002biA\u0011q\u000b]\u0005\u0003c\u0016\u0014A!\u0011:si\u0005\u0011\u0011-\u000e\t\u0003/RL!!^3\u0003\t\u0005\u0013(/N\u0001\u0003CZ\u0002\"a\u0016=\n\u0005e,\'\u0001B!seZ\nQ!Y\u0019mK:\f\u0001g]2bY\u0006$3m\u001c7mK\u000e$\u0018n\u001c8%S6lW\u000f^1cY\u0016$c*Z<WK\u000e$xN]%uKJ\fGo\u001c:%I%\f\u0014AB8mIB{7/\u0001\u001atG\u0006d\u0017\rJ2pY2,7\r^5p]\u0012JW.\\;uC\ndW\r\n(foZ+7\r^8s\u0013R,\'/\u0019;pe\u0012\"C.\u001a82\u0003!\u0019H.[2f\u0013\u0012D\u0018\u0001C:mS\u000e,G)[7\u0002\u0015Md\u0017nY3Ti\u0006\u0014H/\u0001\u0005tY&\u001cW-\u00128e\u0003%Ygn\\<o\'&TX-F\u0001LQ\r\u0019\u00121\u0002\t\u0004W\u00055\u0011bAA\bK\t1\u0011N\u001c7j]\u0016\fq\u0001[1t\u001d\u0016DH/\u0006\u0002\u0002\u0016A\u00191&a\u0006\n\u0007\u0005eQEA\u0004C_>dW-\u00198)\u0007Q\tY!\u0001\u0003oKb$H#\u0001\u001a\u0002\u0019\u0005$g/\u00198dKNc\u0017nY3\u0015\u0005\u0005\u0015\u0002cA\u0016\u0002(%\u0019\u0011\u0011F\u0013\u0003\tUs\u0017\u000e^\u0001\bC\u00124\u0018M\\2f\u0003!\tGM^1oG\u0016\fECBA\u0013\u0003c\t)\u0004\u0003\u0004\u00024a\u0001\raS\u0001\u0003S>Da!a\u000e\u0019\u0001\u0004Y\u0015a\u0001=pe\u0006!1/\u001a;B)\u0019\t)#!\u0010\u0002@!1\u00111G\rA\u0002-Ca!a\u000e\u001a\u0001\u0004Y\u0015\u0001\u00023s_B$2ALA#\u0011\u0019\t9E\u0007a\u0001\u0017\u0006\ta.\u0001\u0003uC.,Gc\u0001\u0018\u0002N!1\u0011qI\u000eA\u0002-\u000bQa\u001d7jG\u0016$RALA*\u0003/Ba!!\u0016\u001d\u0001\u0004Y\u0015\u0001\u00024s_6Da!!\u0017\u001d\u0001\u0004Y\u0015!B;oi&d\u0017aC2paf$v.\u0011:sCf,B!a\u0018\u0002nQ91*!\u0019\u0002t\u0005]\u0004bBA2;\u0001\u0007\u0011QM\u0001\u0003qN\u0004RaKA4\u0003WJ1!!\u001b&\u0005\u0015\t%O]1z!\r\u0019\u0014Q\u000e\u0003\b\u0003_j\"\u0019AA9\u0005\u0005\u0011\u0015C\u0001\u001a;\u0011\u0019\t)(\ba\u0001\u0017\u0006)1\u000f^1si\"1\u0011\u0011P\u000fA\u0002-\u000b1\u0001\\3o\u0003!!xNV3di>\u0014X#\u0001$\u0002\u000bM\u0004H.\u001b;\u0015\u0007E\u000b\u0019\t\u0003\u0004\u0002\u0006~\u0001\raS\u0001\u0003CR\u0004
   #14 = Utf8               scala/collection/Iterator$GroupedIterator
   #15 = Class              #14           // scala/collection/Iterator$GroupedIterator
   #16 = Utf8               GroupedIterator
   #17 = Utf8               v
   #18 = Utf8               Lscala/collection/immutable/Vector;
   #19 = Utf8               Lscala/collection/immutable/Vector<TA;>;
   #20 = Utf8               totalLength
   #21 = Utf8               I
   #22 = Utf8               sliceCount
   #23 = Utf8               a1
   #24 = Utf8               [Ljava/lang/Object;
   #25 = Utf8               a2
   #26 = Utf8               [[Ljava/lang/Object;
   #27 = Utf8               a3
   #28 = Utf8               [[[Ljava/lang/Object;
   #29 = Utf8               a4
   #30 = Utf8               [[[[Ljava/lang/Object;
   #31 = Utf8               a5
   #32 = Utf8               [[[[[Ljava/lang/Object;
   #33 = Utf8               a6
   #34 = Utf8               [[[[[[Ljava/lang/Object;
   #35 = Utf8               a1len
   #36 = Utf8               scala$collection$immutable$NewVectorIterator$$i1
   #37 = Utf8               oldPos
   #38 = Utf8               scala$collection$immutable$NewVectorIterator$$len1
   #39 = Utf8               sliceIdx
   #40 = Utf8               sliceDim
   #41 = Utf8               sliceStart
   #42 = Utf8               sliceEnd
   #43 = Utf8               hasDefiniteSize
   #44 = Utf8               ()Z
   #45 = Utf8               hasDefiniteSize$
   #46 = Utf8               (Lscala/collection/Iterator;)Z
   #47 = NameAndType        #45:#46       // hasDefiniteSize$:(Lscala/collection/Iterator;)Z
   #48 = InterfaceMethodref #7.#47        // scala/collection/Iterator.hasDefiniteSize$:(Lscala/collection/Iterator;)Z
   #49 = Utf8               this
   #50 = Utf8               Lscala/collection/immutable/NewVectorIterator;
   #51 = Utf8               iterator
   #52 = Utf8               ()Lscala/collection/Iterator;
   #53 = Utf8               ()Lscala/collection/Iterator<TA;>;
   #54 = Utf8               iterator$
   #55 = Utf8               (Lscala/collection/Iterator;)Lscala/collection/Iterator;
   #56 = NameAndType        #54:#55       // iterator$:(Lscala/collection/Iterator;)Lscala/collection/Iterator;
   #57 = InterfaceMethodref #7.#56        // scala/collection/Iterator.iterator$:(Lscala/collection/Iterator;)Lscala/collection/Iterator;
   #58 = Utf8               nextOption
   #59 = Utf8               ()Lscala/Option;
   #60 = Utf8               ()Lscala/Option<TA;>;
   #61 = Utf8               nextOption$
   #62 = Utf8               (Lscala/collection/Iterator;)Lscala/Option;
   #63 = NameAndType        #61:#62       // nextOption$:(Lscala/collection/Iterator;)Lscala/Option;
   #64 = InterfaceMethodref #7.#63        // scala/collection/Iterator.nextOption$:(Lscala/collection/Iterator;)Lscala/Option;
   #65 = Utf8               contains
   #66 = Utf8               (Ljava/lang/Object;)Z
   #67 = Utf8               elem
   #68 = Utf8               contains$
   #69 = Utf8               (Lscala/collection/Iterator;Ljava/lang/Object;)Z
   #70 = NameAndType        #68:#69       // contains$:(Lscala/collection/Iterator;Ljava/lang/Object;)Z
   #71 = InterfaceMethodref #7.#70        // scala/collection/Iterator.contains$:(Lscala/collection/Iterator;Ljava/lang/Object;)Z
   #72 = Utf8               Ljava/lang/Object;
   #73 = Utf8               buffered
   #74 = Utf8               ()Lscala/collection/BufferedIterator;
   #75 = Utf8               ()Lscala/collection/BufferedIterator<TA;>;
   #76 = Utf8               buffered$
   #77 = Utf8               (Lscala/collection/Iterator;)Lscala/collection/BufferedIterator;
   #78 = NameAndType        #76:#77       // buffered$:(Lscala/collection/Iterator;)Lscala/collection/BufferedIterator;
   #79 = InterfaceMethodref #7.#78        // scala/collection/Iterator.buffered$:(Lscala/collection/Iterator;)Lscala/collection/BufferedIterator;
   #80 = Utf8               padTo
   #81 = Utf8               (ILjava/lang/Object;)Lscala/collection/Iterator;
   #82 = Utf8               <B:Ljava/lang/Object;>(ITB;)Lscala/collection/Iterator<TB;>;
   #83 = Utf8               len
   #84 = Utf8               padTo$
   #85 = Utf8               (Lscala/collection/Iterator;ILjava/lang/Object;)Lscala/collection/Iterator;
   #86 = NameAndType        #84:#85       // padTo$:(Lscala/collection/Iterator;ILjava/lang/Object;)Lscala/collection/Iterator;
   #87 = InterfaceMethodref #7.#86        // scala/collection/Iterator.padTo$:(Lscala/collection/Iterator;ILjava/lang/Object;)Lscala/collection/Iterator;
   #88 = Utf8               partition
   #89 = Utf8               (Lscala/Function1;)Lscala/Tuple2;
   #90 = Utf8               (Lscala/Function1<TA;Ljava/lang/Object;>;)Lscala/Tuple2<Lscala/collection/Iterator<TA;>;Lscala/collection/Iterator<TA;>;>;
   #91 = Utf8               p
   #92 = Utf8               partition$
   #93 = Utf8               (Lscala/collection/Iterator;Lscala/Function1;)Lscala/Tuple2;
   #94 = NameAndType        #92:#93       // partition$:(Lscala/collection/Iterator;Lscala/Function1;)Lscala/Tuple2;
   #95 = InterfaceMethodref #7.#94        // scala/collection/Iterator.partition$:(Lscala/collection/Iterator;Lscala/Function1;)Lscala/Tuple2;
   #96 = Utf8               Lscala/Function1;
   #97 = Utf8               grouped
   #98 = Utf8               (I)Lscala/collection/Iterator$GroupedIterator;
   #99 = Utf8               <B:Ljava/lang/Object;>(I)Lscala/collection/Iterator<TA;>.GroupedIterator<TB;>;
  #100 = Utf8               size
  #101 = Utf8               grouped$
  #102 = Utf8               (Lscala/collection/Iterator;I)Lscala/collection/Iterator$GroupedIterator;
  #103 = NameAndType        #101:#102     // grouped$:(Lscala/collection/Iterator;I)Lscala/collection/Iterator$GroupedIterator;
  #104 = InterfaceMethodref #7.#103       // scala/collection/Iterator.grouped$:(Lscala/collection/Iterator;I)Lscala/collection/Iterator$GroupedIterator;
  #105 = Utf8               sliding
  #106 = Utf8               (II)Lscala/collection/Iterator$GroupedIterator;
  #107 = Utf8               <B:Ljava/lang/Object;>(II)Lscala/collection/Iterator<TA;>.GroupedIterator<TB;>;
  #108 = Utf8               step
  #109 = Utf8               sliding$
  #110 = Utf8               (Lscala/collection/Iterator;II)Lscala/collection/Iterator$GroupedIterator;
  #111 = NameAndType        #109:#110     // sliding$:(Lscala/collection/Iterator;II)Lscala/collection/Iterator$GroupedIterator;
  #112 = InterfaceMethodref #7.#111       // scala/collection/Iterator.sliding$:(Lscala/collection/Iterator;II)Lscala/collection/Iterator$GroupedIterator;
  #113 = Utf8               sliding$default$2
  #114 = Utf8               ()I
  #115 = Utf8               <B:Ljava/lang/Object;>()I
  #116 = Utf8               sliding$default$2$
  #117 = Utf8               (Lscala/collection/Iterator;)I
  #118 = NameAndType        #116:#117     // sliding$default$2$:(Lscala/collection/Iterator;)I
  #119 = InterfaceMethodref #7.#118       // scala/collection/Iterator.sliding$default$2$:(Lscala/collection/Iterator;)I
  #120 = Utf8               scanLeft
  #121 = Utf8               (Ljava/lang/Object;Lscala/Function2;)Lscala/collection/Iterator;
  #122 = Utf8               <B:Ljava/lang/Object;>(TB;Lscala/Function2<TB;TA;TB;>;)Lscala/collection/Iterator<TB;>;
  #123 = Utf8               z
  #124 = Utf8               op
  #125 = Utf8               scanLeft$
  #126 = Utf8               (Lscala/collection/Iterator;Ljava/lang/Object;Lscala/Function2;)Lscala/collection/Iterator;
  #127 = NameAndType        #125:#126     // scanLeft$:(Lscala/collection/Iterator;Ljava/lang/Object;Lscala/Function2;)Lscala/collection/Iterator;
  #128 = InterfaceMethodref #7.#127       // scala/collection/Iterator.scanLeft$:(Lscala/collection/Iterator;Ljava/lang/Object;Lscala/Function2;)Lscala/collection/Iterator;
  #129 = Utf8               Lscala/Function2;
  #130 = Utf8               scanRight
  #131 = Utf8               <B:Ljava/lang/Object;>(TB;Lscala/Function2<TA;TB;TB;>;)Lscala/collection/Iterator<TB;>;
  #132 = Utf8               scanRight$
  #133 = NameAndType        #132:#126     // scanRight$:(Lscala/collection/Iterator;Ljava/lang/Object;Lscala/Function2;)Lscala/collection/Iterator;
  #134 = InterfaceMethodref #7.#133       // scala/collection/Iterator.scanRight$:(Lscala/collection/Iterator;Ljava/lang/Object;Lscala/Function2;)Lscala/collection/Iterator;
  #135 = Utf8               indexWhere
  #136 = Utf8               (Lscala/Function1;I)I
  #137 = Utf8               (Lscala/Function1<TA;Ljava/lang/Object;>;I)I
  #138 = Utf8               from
  #139 = Utf8               indexWhere$
  #140 = Utf8               (Lscala/collection/Iterator;Lscala/Function1;I)I
  #141 = NameAndType        #139:#140     // indexWhere$:(Lscala/collection/Iterator;Lscala/Function1;I)I
  #142 = InterfaceMethodref #7.#141       // scala/collection/Iterator.indexWhere$:(Lscala/collection/Iterator;Lscala/Function1;I)I
  #143 = Utf8               indexWhere$default$2
  #144 = Utf8               indexWhere$default$2$
  #145 = NameAndType        #144:#117     // indexWhere$default$2$:(Lscala/collection/Iterator;)I
  #146 = InterfaceMethodref #7.#145       // scala/collection/Iterator.indexWhere$default$2$:(Lscala/collection/Iterator;)I
  #147 = Utf8               indexOf
  #148 = Utf8               (Ljava/lang/Object;)I
  #149 = Utf8               <B:Ljava/lang/Object;>(TB;)I
  #150 = Utf8               indexOf$
  #151 = Utf8               (Lscala/collection/Iterator;Ljava/lang/Object;)I
  #152 = NameAndType        #150:#151     // indexOf$:(Lscala/collection/Iterator;Ljava/lang/Object;)I
  #153 = InterfaceMethodref #7.#152       // scala/collection/Iterator.indexOf$:(Lscala/collection/Iterator;Ljava/lang/Object;)I
  #154 = Utf8               (Ljava/lang/Object;I)I
  #155 = Utf8               <B:Ljava/lang/Object;>(TB;I)I
  #156 = Utf8               (Lscala/collection/Iterator;Ljava/lang/Object;I)I
  #157 = NameAndType        #150:#156     // indexOf$:(Lscala/collection/Iterator;Ljava/lang/Object;I)I
  #158 = InterfaceMethodref #7.#157       // scala/collection/Iterator.indexOf$:(Lscala/collection/Iterator;Ljava/lang/Object;I)I
  #159 = Utf8               length
  #160 = Utf8               length$
  #161 = NameAndType        #160:#117     // length$:(Lscala/collection/Iterator;)I
  #162 = InterfaceMethodref #7.#161       // scala/collection/Iterator.length$:(Lscala/collection/Iterator;)I
  #163 = Utf8               isEmpty
  #164 = Utf8               isEmpty$
  #165 = NameAndType        #164:#46      // isEmpty$:(Lscala/collection/Iterator;)Z
  #166 = InterfaceMethodref #7.#165       // scala/collection/Iterator.isEmpty$:(Lscala/collection/Iterator;)Z
  #167 = Utf8               filter
  #168 = Utf8               (Lscala/Function1;)Lscala/collection/Iterator;
  #169 = Utf8               (Lscala/Function1<TA;Ljava/lang/Object;>;)Lscala/collection/Iterator<TA;>;
  #170 = Utf8               filter$
  #171 = Utf8               (Lscala/collection/Iterator;Lscala/Function1;)Lscala/collection/Iterator;
  #172 = NameAndType        #170:#171     // filter$:(Lscala/collection/Iterator;Lscala/Function1;)Lscala/collection/Iterator;
  #173 = InterfaceMethodref #7.#172       // scala/collection/Iterator.filter$:(Lscala/collection/Iterator;Lscala/Function1;)Lscala/collection/Iterator;
  #174 = Utf8               filterNot
  #175 = Utf8               filterNot$
  #176 = NameAndType        #175:#171     // filterNot$:(Lscala/collection/Iterator;Lscala/Function1;)Lscala/collection/Iterator;
  #177 = InterfaceMethodref #7.#176       // scala/collection/Iterator.filterNot$:(Lscala/collection/Iterator;Lscala/Function1;)Lscala/collection/Iterator;
  #178 = Utf8               filterImpl
  #179 = Utf8               (Lscala/Function1;Z)Lscala/collection/Iterator;
  #180 = Utf8               (Lscala/Function1<TA;Ljava/lang/Object;>;Z)Lscala/collection/Iterator<TA;>;
  #181 = Utf8               isFlipped
  #182 = Utf8               filterImpl$
  #183 = Utf8               (Lscala/collection/Iterator;Lscala/Function1;Z)Lscala/collection/Iterator;
  #184 = NameAndType        #182:#183     // filterImpl$:(Lscala/collection/Iterator;Lscala/Function1;Z)Lscala/collection/Iterator;
  #185 = InterfaceMethodref #7.#184       // scala/collection/Iterator.filterImpl$:(Lscala/collection/Iterator;Lscala/Function1;Z)Lscala/collection/Iterator;
  #186 = Utf8               Z
  #187 = Utf8               withFilter
  #188 = Utf8               withFilter$
  #189 = NameAndType        #188:#171     // withFilter$:(Lscala/collection/Iterator;Lscala/Function1;)Lscala/collection/Iterator;
  #190 = InterfaceMethodref #7.#189       // scala/collection/Iterator.withFilter$:(Lscala/collection/Iterator;Lscala/Function1;)Lscala/collection/Iterator;
  #191 = Utf8               collect
  #192 = Utf8               (Lscala/PartialFunction;)Lscala/collection/Iterator;
  #193 = Utf8               <B:Ljava/lang/Object;>(Lscala/PartialFunction<TA;TB;>;)Lscala/collection/Iterator<TB;>;
  #194 = Utf8               pf
  #195 = Utf8               collect$
  #196 = Utf8               (Lscala/collection/Iterator;Lscala/PartialFunction;)Lscala/collection/Iterator;
  #197 = NameAndType        #195:#196     // collect$:(Lscala/collection/Iterator;Lscala/PartialFunction;)Lscala/collection/Iterator;
  #198 = InterfaceMethodref #7.#197       // scala/collection/Iterator.collect$:(Lscala/collection/Iterator;Lscala/PartialFunction;)Lscala/collection/Iterator;
  #199 = Utf8               Lscala/PartialFunction;
  #200 = Utf8               distinct
  #201 = Utf8               distinct$
  #202 = NameAndType        #201:#55      // distinct$:(Lscala/collection/Iterator;)Lscala/collection/Iterator;
  #203 = InterfaceMethodref #7.#202       // scala/collection/Iterator.distinct$:(Lscala/collection/Iterator;)Lscala/collection/Iterator;
  #204 = Utf8               distinctBy
  #205 = Utf8               <B:Ljava/lang/Object;>(Lscala/Function1<TA;TB;>;)Lscala/collection/Iterator<TA;>;
  #206 = Utf8               f
  #207 = Utf8               distinctBy$
  #208 = NameAndType        #207:#171     // distinctBy$:(Lscala/collection/Iterator;Lscala/Function1;)Lscala/collection/Iterator;
  #209 = InterfaceMethodref #7.#208       // scala/collection/Iterator.distinctBy$:(Lscala/collection/Iterator;Lscala/Function1;)Lscala/collection/Iterator;
  #210 = Utf8               map
  #211 = Utf8               <B:Ljava/lang/Object;>(Lscala/Function1<TA;TB;>;)Lscala/collection/Iterator<TB;>;
  #212 = Utf8               map$
  #213 = NameAndType        #212:#171     // map$:(Lscala/collection/Iterator;Lscala/Function1;)Lscala/collection/Iterator;
  #214 = InterfaceMethodref #7.#213       // scala/collection/Iterator.map$:(Lscala/collection/Iterator;Lscala/Function1;)Lscala/collection/Iterator;
  #215 = Utf8               flatMap
  #216 = Utf8               <B:Ljava/lang/Object;>(Lscala/Function1<TA;Lscala/collection/IterableOnce<TB;>;>;)Lscala/collection/Iterator<TB;>;
  #217 = Utf8               flatMap$
  #218 = NameAndType        #217:#171     // flatMap$:(Lscala/collection/Iterator;Lscala/Function1;)Lscala/collection/Iterator;
  #219 = InterfaceMethodref #7.#218       // scala/collection/Iterator.flatMap$:(Lscala/collection/Iterator;Lscala/Function1;)Lscala/collection/Iterator;
  #220 = Utf8               flatten
  #221 = Utf8               ev
  #222 = Utf8               flatten$
  #223 = NameAndType        #222:#171     // flatten$:(Lscala/collection/Iterator;Lscala/Function1;)Lscala/collection/Iterator;
  #224 = InterfaceMethodref #7.#223       // scala/collection/Iterator.flatten$:(Lscala/collection/Iterator;Lscala/Function1;)Lscala/collection/Iterator;
  #225 = Utf8               concat
  #226 = Utf8               (Lscala/Function0;)Lscala/collection/Iterator;
  #227 = Utf8               <B:Ljava/lang/Object;>(Lscala/Function0<Lscala/collection/IterableOnce<TB;>;>;)Lscala/collection/Iterator<TB;>;
  #228 = Utf8               xs
  #229 = Utf8               concat$
  #230 = Utf8               (Lscala/collection/Iterator;Lscala/Function0;)Lscala/collection/Iterator;
  #231 = NameAndType        #229:#230     // concat$:(Lscala/collection/Iterator;Lscala/Function0;)Lscala/collection/Iterator;
  #232 = InterfaceMethodref #7.#231       // scala/collection/Iterator.concat$:(Lscala/collection/Iterator;Lscala/Function0;)Lscala/collection/Iterator;
  #233 = Utf8               Lscala/Function0;
  #234 = Utf8               $plus$plus
  #235 = Utf8               $plus$plus$
  #236 = NameAndType        #235:#230     // $plus$plus$:(Lscala/collection/Iterator;Lscala/Function0;)Lscala/collection/Iterator;
  #237 = InterfaceMethodref #7.#236       // scala/collection/Iterator.$plus$plus$:(Lscala/collection/Iterator;Lscala/Function0;)Lscala/collection/Iterator;
  #238 = Utf8               takeWhile
  #239 = Utf8               takeWhile$
  #240 = NameAndType        #239:#171     // takeWhile$:(Lscala/collection/Iterator;Lscala/Function1;)Lscala/collection/Iterator;
  #241 = InterfaceMethodref #7.#240       // scala/collection/Iterator.takeWhile$:(Lscala/collection/Iterator;Lscala/Function1;)Lscala/collection/Iterator;
  #242 = Utf8               dropWhile
  #243 = Utf8               dropWhile$
  #244 = NameAndType        #243:#171     // dropWhile$:(Lscala/collection/Iterator;Lscala/Function1;)Lscala/collection/Iterator;
  #245 = InterfaceMethodref #7.#244       // scala/collection/Iterator.dropWhile$:(Lscala/collection/Iterator;Lscala/Function1;)Lscala/collection/Iterator;
  #246 = Utf8               span
  #247 = Utf8               span$
  #248 = NameAndType        #247:#93      // span$:(Lscala/collection/Iterator;Lscala/Function1;)Lscala/Tuple2;
  #249 = InterfaceMethodref #7.#248       // scala/collection/Iterator.span$:(Lscala/collection/Iterator;Lscala/Function1;)Lscala/Tuple2;
  #250 = Utf8               sliceIterator
  #251 = Utf8               (II)Lscala/collection/Iterator;
  #252 = Utf8               (II)Lscala/collection/Iterator<TA;>;
  #253 = Utf8               until
  #254 = Utf8               sliceIterator$
  #255 = Utf8               (Lscala/collection/Iterator;II)Lscala/collection/Iterator;
  #256 = NameAndType        #254:#255     // sliceIterator$:(Lscala/collection/Iterator;II)Lscala/collection/Iterator;
  #257 = InterfaceMethodref #7.#256       // scala/collection/Iterator.sliceIterator$:(Lscala/collection/Iterator;II)Lscala/collection/Iterator;
  #258 = Utf8               zip
  #259 = Utf8               (Lscala/collection/IterableOnce;)Lscala/collection/Iterator;
  #260 = Utf8               <B:Ljava/lang/Object;>(Lscala/collection/IterableOnce<TB;>;)Lscala/collection/Iterator<Lscala/Tuple2<TA;TB;>;>;
  #261 = Utf8               that
  #262 = Utf8               zip$
  #263 = Utf8               (Lscala/collection/Iterator;Lscala/collection/IterableOnce;)Lscala/collection/Iterator;
  #264 = NameAndType        #262:#263     // zip$:(Lscala/collection/Iterator;Lscala/collection/IterableOnce;)Lscala/collection/Iterator;
  #265 = InterfaceMethodref #7.#264       // scala/collection/Iterator.zip$:(Lscala/collection/Iterator;Lscala/collection/IterableOnce;)Lscala/collection/Iterator;
  #266 = Utf8               Lscala/collection/IterableOnce;
  #267 = Utf8               zipAll
  #268 = Utf8               (Lscala/collection/IterableOnce;Ljava/lang/Object;Ljava/lang/Object;)Lscala/collection/Iterator;
  #269 = Utf8               <A1:Ljava/lang/Object;B:Ljava/lang/Object;>(Lscala/collection/IterableOnce<TB;>;TA1;TB;)Lscala/collection/Iterator<Lscala/Tuple2<TA1;TB;>;>;
  #270 = Utf8               thisElem
  #271 = Utf8               thatElem
  #272 = Utf8               zipAll$
  #273 = Utf8               (Lscala/collection/Iterator;Lscala/collection/IterableOnce;Ljava/lang/Object;Ljava/lang/Object;)Lscala/collection/Iterator;
  #274 = NameAndType        #272:#273     // zipAll$:(Lscala/collection/Iterator;Lscala/collection/IterableOnce;Ljava/lang/Object;Ljava/lang/Object;)Lscala/collection/Iterator;
  #275 = InterfaceMethodref #7.#274       // scala/collection/Iterator.zipAll$:(Lscala/collection/Iterator;Lscala/collection/IterableOnce;Ljava/lang/Object;Ljava/lang/Object;)Lscala/collection/Iterator;
  #276 = Utf8               zipWithIndex
  #277 = Utf8               ()Lscala/collection/Iterator<Lscala/Tuple2<TA;Ljava/lang/Object;>;>;
  #278 = Utf8               zipWithIndex$
  #279 = NameAndType        #278:#55      // zipWithIndex$:(Lscala/collection/Iterator;)Lscala/collection/Iterator;
  #280 = InterfaceMethodref #7.#279       // scala/collection/Iterator.zipWithIndex$:(Lscala/collection/Iterator;)Lscala/collection/Iterator;
  #281 = Utf8               sameElements
  #282 = Utf8               (Lscala/collection/IterableOnce;)Z
  #283 = Utf8               <B:Ljava/lang/Object;>(Lscala/collection/IterableOnce<TB;>;)Z
  #284 = Utf8               sameElements$
  #285 = Utf8               (Lscala/collection/Iterator;Lscala/collection/IterableOnce;)Z
  #286 = NameAndType        #284:#285     // sameElements$:(Lscala/collection/Iterator;Lscala/collection/IterableOnce;)Z
  #287 = InterfaceMethodref #7.#286       // scala/collection/Iterator.sameElements$:(Lscala/collection/Iterator;Lscala/collection/IterableOnce;)Z
  #288 = Utf8               duplicate
  #289 = Utf8               ()Lscala/Tuple2;
  #290 = Utf8               ()Lscala/Tuple2<Lscala/collection/Iterator<TA;>;Lscala/collection/Iterator<TA;>;>;
  #291 = Utf8               duplicate$
  #292 = Utf8               (Lscala/collection/Iterator;)Lscala/Tuple2;
  #293 = NameAndType        #291:#292     // duplicate$:(Lscala/collection/Iterator;)Lscala/Tuple2;
  #294 = InterfaceMethodref #7.#293       // scala/collection/Iterator.duplicate$:(Lscala/collection/Iterator;)Lscala/Tuple2;
  #295 = Utf8               patch
  #296 = Utf8               (ILscala/collection/Iterator;I)Lscala/collection/Iterator;
  #297 = Utf8               <B:Ljava/lang/Object;>(ILscala/collection/Iterator<TB;>;I)Lscala/collection/Iterator<TB;>;
  #298 = Utf8               patchElems
  #299 = Utf8               replaced
  #300 = Utf8               patch$
  #301 = Utf8               (Lscala/collection/Iterator;ILscala/collection/Iterator;I)Lscala/collection/Iterator;
  #302 = NameAndType        #300:#301     // patch$:(Lscala/collection/Iterator;ILscala/collection/Iterator;I)Lscala/collection/Iterator;
  #303 = InterfaceMethodref #7.#302       // scala/collection/Iterator.patch$:(Lscala/collection/Iterator;ILscala/collection/Iterator;I)Lscala/collection/Iterator;
  #304 = Utf8               Lscala/collection/Iterator;
  #305 = Utf8               tapEach
  #306 = Utf8               <U:Ljava/lang/Object;>(Lscala/Function1<TA;TU;>;)Lscala/collection/Iterator<TA;>;
  #307 = Utf8               tapEach$
  #308 = NameAndType        #307:#171     // tapEach$:(Lscala/collection/Iterator;Lscala/Function1;)Lscala/collection/Iterator;
  #309 = InterfaceMethodref #7.#308       // scala/collection/Iterator.tapEach$:(Lscala/collection/Iterator;Lscala/Function1;)Lscala/collection/Iterator;
  #310 = Utf8               toString
  #311 = Utf8               ()Ljava/lang/String;
  #312 = Utf8               toString$
  #313 = Utf8               (Lscala/collection/Iterator;)Ljava/lang/String;
  #314 = NameAndType        #312:#313     // toString$:(Lscala/collection/Iterator;)Ljava/lang/String;
  #315 = InterfaceMethodref #7.#314       // scala/collection/Iterator.toString$:(Lscala/collection/Iterator;)Ljava/lang/String;
  #316 = Utf8               seq
  #317 = Utf8               seq$
  #318 = NameAndType        #317:#55      // seq$:(Lscala/collection/Iterator;)Lscala/collection/Iterator;
  #319 = InterfaceMethodref #7.#318       // scala/collection/Iterator.seq$:(Lscala/collection/Iterator;)Lscala/collection/Iterator;
  #320 = Utf8               splitAt
  #321 = Utf8               (I)Lscala/Tuple2;
  #322 = Utf8               (I)Lscala/Tuple2<Lscala/collection/Iterator<TA;>;Lscala/collection/Iterator<TA;>;>;
  #323 = Utf8               n
  #324 = Utf8               scala/collection/IterableOnceOps
  #325 = Class              #324          // scala/collection/IterableOnceOps
  #326 = Utf8               splitAt$
  #327 = Utf8               (Lscala/collection/IterableOnceOps;I)Lscala/Tuple2;
  #328 = NameAndType        #326:#327     // splitAt$:(Lscala/collection/IterableOnceOps;I)Lscala/Tuple2;
  #329 = InterfaceMethodref #325.#328     // scala/collection/IterableOnceOps.splitAt$:(Lscala/collection/IterableOnceOps;I)Lscala/Tuple2;
  #330 = Utf8               isTraversableAgain
  #331 = Utf8               isTraversableAgain$
  #332 = Utf8               (Lscala/collection/IterableOnceOps;)Z
  #333 = NameAndType        #331:#332     // isTraversableAgain$:(Lscala/collection/IterableOnceOps;)Z
  #334 = InterfaceMethodref #325.#333     // scala/collection/IterableOnceOps.isTraversableAgain$:(Lscala/collection/IterableOnceOps;)Z
  #335 = Utf8               foreach
  #336 = Utf8               (Lscala/Function1;)V
  #337 = Utf8               <U:Ljava/lang/Object;>(Lscala/Function1<TA;TU;>;)V
  #338 = Utf8               foreach$
  #339 = Utf8               (Lscala/collection/IterableOnceOps;Lscala/Function1;)V
  #340 = NameAndType        #338:#339     // foreach$:(Lscala/collection/IterableOnceOps;Lscala/Function1;)V
  #341 = InterfaceMethodref #325.#340     // scala/collection/IterableOnceOps.foreach$:(Lscala/collection/IterableOnceOps;Lscala/Function1;)V
  #342 = Utf8               forall
  #343 = Utf8               (Lscala/Function1;)Z
  #344 = Utf8               (Lscala/Function1<TA;Ljava/lang/Object;>;)Z
  #345 = Utf8               forall$
  #346 = Utf8               (Lscala/collection/IterableOnceOps;Lscala/Function1;)Z
  #347 = NameAndType        #345:#346     // forall$:(Lscala/collection/IterableOnceOps;Lscala/Function1;)Z
  #348 = InterfaceMethodref #325.#347     // scala/collection/IterableOnceOps.forall$:(Lscala/collection/IterableOnceOps;Lscala/Function1;)Z
  #349 = Utf8               exists
  #350 = Utf8               exists$
  #351 = NameAndType        #350:#346     // exists$:(Lscala/collection/IterableOnceOps;Lscala/Function1;)Z
  #352 = InterfaceMethodref #325.#351     // scala/collection/IterableOnceOps.exists$:(Lscala/collection/IterableOnceOps;Lscala/Function1;)Z
  #353 = Utf8               count
  #354 = Utf8               (Lscala/Function1;)I
  #355 = Utf8               (Lscala/Function1<TA;Ljava/lang/Object;>;)I
  #356 = Utf8               count$
  #357 = Utf8               (Lscala/collection/IterableOnceOps;Lscala/Function1;)I
  #358 = NameAndType        #356:#357     // count$:(Lscala/collection/IterableOnceOps;Lscala/Function1;)I
  #359 = InterfaceMethodref #325.#358     // scala/collection/IterableOnceOps.count$:(Lscala/collection/IterableOnceOps;Lscala/Function1;)I
  #360 = Utf8               find
  #361 = Utf8               (Lscala/Function1;)Lscala/Option;
  #362 = Utf8               (Lscala/Function1<TA;Ljava/lang/Object;>;)Lscala/Option<TA;>;
  #363 = Utf8               find$
  #364 = Utf8               (Lscala/collection/IterableOnceOps;Lscala/Function1;)Lscala/Option;
  #365 = NameAndType        #363:#364     // find$:(Lscala/collection/IterableOnceOps;Lscala/Function1;)Lscala/Option;
  #366 = InterfaceMethodref #325.#365     // scala/collection/IterableOnceOps.find$:(Lscala/collection/IterableOnceOps;Lscala/Function1;)Lscala/Option;
  #367 = Utf8               foldLeft
  #368 = Utf8               (Ljava/lang/Object;Lscala/Function2;)Ljava/lang/Object;
  #369 = Utf8               <B:Ljava/lang/Object;>(TB;Lscala/Function2<TB;TA;TB;>;)TB;
  #370 = Utf8               foldLeft$
  #371 = Utf8               (Lscala/collection/IterableOnceOps;Ljava/lang/Object;Lscala/Function2;)Ljava/lang/Object;
  #372 = NameAndType        #370:#371     // foldLeft$:(Lscala/collection/IterableOnceOps;Ljava/lang/Object;Lscala/Function2;)Ljava/lang/Object;
  #373 = InterfaceMethodref #325.#372     // scala/collection/IterableOnceOps.foldLeft$:(Lscala/collection/IterableOnceOps;Ljava/lang/Object;Lscala/Function2;)Ljava/lang/Object;
  #374 = Utf8               foldRight
  #375 = Utf8               <B:Ljava/lang/Object;>(TB;Lscala/Function2<TA;TB;TB;>;)TB;
  #376 = Utf8               foldRight$
  #377 = NameAndType        #376:#371     // foldRight$:(Lscala/collection/IterableOnceOps;Ljava/lang/Object;Lscala/Function2;)Ljava/lang/Object;
  #378 = InterfaceMethodref #325.#377     // scala/collection/IterableOnceOps.foldRight$:(Lscala/collection/IterableOnceOps;Ljava/lang/Object;Lscala/Function2;)Ljava/lang/Object;
  #379 = Utf8               $div$colon
  #380 = Utf8               $div$colon$
  #381 = NameAndType        #380:#371     // $div$colon$:(Lscala/collection/IterableOnceOps;Ljava/lang/Object;Lscala/Function2;)Ljava/lang/Object;
  #382 = InterfaceMethodref #325.#381     // scala/collection/IterableOnceOps.$div$colon$:(Lscala/collection/IterableOnceOps;Ljava/lang/Object;Lscala/Function2;)Ljava/lang/Object;
  #383 = Utf8               $colon$bslash
  #384 = Utf8               $colon$bslash$
  #385 = NameAndType        #384:#371     // $colon$bslash$:(Lscala/collection/IterableOnceOps;Ljava/lang/Object;Lscala/Function2;)Ljava/lang/Object;
  #386 = InterfaceMethodref #325.#385     // scala/collection/IterableOnceOps.$colon$bslash$:(Lscala/collection/IterableOnceOps;Ljava/lang/Object;Lscala/Function2;)Ljava/lang/Object;
  #387 = Utf8               fold
  #388 = Utf8               <A1:Ljava/lang/Object;>(TA1;Lscala/Function2<TA1;TA1;TA1;>;)TA1;
  #389 = Utf8               fold$
  #390 = NameAndType        #389:#371     // fold$:(Lscala/collection/IterableOnceOps;Ljava/lang/Object;Lscala/Function2;)Ljava/lang/Object;
  #391 = InterfaceMethodref #325.#390     // scala/collection/IterableOnceOps.fold$:(Lscala/collection/IterableOnceOps;Ljava/lang/Object;Lscala/Function2;)Ljava/lang/Object;
  #392 = Utf8               reduce
  #393 = Utf8               (Lscala/Function2;)Ljava/lang/Object;
  #394 = Utf8               <B:Ljava/lang/Object;>(Lscala/Function2<TB;TB;TB;>;)TB;
  #395 = Utf8               reduce$
  #396 = Utf8               (Lscala/collection/IterableOnceOps;Lscala/Function2;)Ljava/lang/Object;
  #397 = NameAndType        #395:#396     // reduce$:(Lscala/collection/IterableOnceOps;Lscala/Function2;)Ljava/lang/Object;
  #398 = InterfaceMethodref #325.#397     // scala/collection/IterableOnceOps.reduce$:(Lscala/collection/IterableOnceOps;Lscala/Function2;)Ljava/lang/Object;
  #399 = Utf8               reduceOption
  #400 = Utf8               (Lscala/Function2;)Lscala/Option;
  #401 = Utf8               <B:Ljava/lang/Object;>(Lscala/Function2<TB;TB;TB;>;)Lscala/Option<TB;>;
  #402 = Utf8               reduceOption$
  #403 = Utf8               (Lscala/collection/IterableOnceOps;Lscala/Function2;)Lscala/Option;
  #404 = NameAndType        #402:#403     // reduceOption$:(Lscala/collection/IterableOnceOps;Lscala/Function2;)Lscala/Option;
  #405 = InterfaceMethodref #325.#404     // scala/collection/IterableOnceOps.reduceOption$:(Lscala/collection/IterableOnceOps;Lscala/Function2;)Lscala/Option;
  #406 = Utf8               reduceLeft
  #407 = Utf8               <B:Ljava/lang/Object;>(Lscala/Function2<TB;TA;TB;>;)TB;
  #408 = Utf8               reduceLeft$
  #409 = NameAndType        #408:#396     // reduceLeft$:(Lscala/collection/IterableOnceOps;Lscala/Function2;)Ljava/lang/Object;
  #410 = InterfaceMethodref #325.#409     // scala/collection/IterableOnceOps.reduceLeft$:(Lscala/collection/IterableOnceOps;Lscala/Function2;)Ljava/lang/Object;
  #411 = Utf8               reduceRight
  #412 = Utf8               <B:Ljava/lang/Object;>(Lscala/Function2<TA;TB;TB;>;)TB;
  #413 = Utf8               reduceRight$
  #414 = NameAndType        #413:#396     // reduceRight$:(Lscala/collection/IterableOnceOps;Lscala/Function2;)Ljava/lang/Object;
  #415 = InterfaceMethodref #325.#414     // scala/collection/IterableOnceOps.reduceRight$:(Lscala/collection/IterableOnceOps;Lscala/Function2;)Ljava/lang/Object;
  #416 = Utf8               reduceLeftOption
  #417 = Utf8               <B:Ljava/lang/Object;>(Lscala/Function2<TB;TA;TB;>;)Lscala/Option<TB;>;
  #418 = Utf8               reduceLeftOption$
  #419 = NameAndType        #418:#403     // reduceLeftOption$:(Lscala/collection/IterableOnceOps;Lscala/Function2;)Lscala/Option;
  #420 = InterfaceMethodref #325.#419     // scala/collection/IterableOnceOps.reduceLeftOption$:(Lscala/collection/IterableOnceOps;Lscala/Function2;)Lscala/Option;
  #421 = Utf8               reduceRightOption
  #422 = Utf8               <B:Ljava/lang/Object;>(Lscala/Function2<TA;TB;TB;>;)Lscala/Option<TB;>;
  #423 = Utf8               reduceRightOption$
  #424 = NameAndType        #423:#403     // reduceRightOption$:(Lscala/collection/IterableOnceOps;Lscala/Function2;)Lscala/Option;
  #425 = InterfaceMethodref #325.#424     // scala/collection/IterableOnceOps.reduceRightOption$:(Lscala/collection/IterableOnceOps;Lscala/Function2;)Lscala/Option;
  #426 = Utf8               nonEmpty
  #427 = Utf8               nonEmpty$
  #428 = NameAndType        #427:#332     // nonEmpty$:(Lscala/collection/IterableOnceOps;)Z
  #429 = InterfaceMethodref #325.#428     // scala/collection/IterableOnceOps.nonEmpty$:(Lscala/collection/IterableOnceOps;)Z
  #430 = Utf8               size$
  #431 = Utf8               (Lscala/collection/IterableOnceOps;)I
  #432 = NameAndType        #430:#431     // size$:(Lscala/collection/IterableOnceOps;)I
  #433 = InterfaceMethodref #325.#432     // scala/collection/IterableOnceOps.size$:(Lscala/collection/IterableOnceOps;)I
  #434 = Utf8               copyToBuffer
  #435 = Utf8               (Lscala/collection/mutable/Buffer;)V
  #436 = Utf8               <B:Ljava/lang/Object;>(Lscala/collection/mutable/Buffer<TB;>;)V
  #437 = Utf8               dest
  #438 = Utf8               copyToBuffer$
  #439 = Utf8               (Lscala/collection/IterableOnceOps;Lscala/collection/mutable/Buffer;)V
  #440 = NameAndType        #438:#439     // copyToBuffer$:(Lscala/collection/IterableOnceOps;Lscala/collection/mutable/Buffer;)V
  #441 = InterfaceMethodref #325.#440     // scala/collection/IterableOnceOps.copyToBuffer$:(Lscala/collection/IterableOnceOps;Lscala/collection/mutable/Buffer;)V
  #442 = Utf8               Lscala/collection/mutable/Buffer;
  #443 = Utf8               copyToArray
  #444 = Utf8               <B:Ljava/lang/Object;>(Ljava/lang/Object;)I
  #445 = Utf8               copyToArray$
  #446 = Utf8               (Lscala/collection/IterableOnceOps;Ljava/lang/Object;)I
  #447 = NameAndType        #445:#446     // copyToArray$:(Lscala/collection/IterableOnceOps;Ljava/lang/Object;)I
  #448 = InterfaceMethodref #325.#447     // scala/collection/IterableOnceOps.copyToArray$:(Lscala/collection/IterableOnceOps;Ljava/lang/Object;)I
  #449 = Utf8               <B:Ljava/lang/Object;>(Ljava/lang/Object;I)I
  #450 = Utf8               start
  #451 = Utf8               (Lscala/collection/IterableOnceOps;Ljava/lang/Object;I)I
  #452 = NameAndType        #445:#451     // copyToArray$:(Lscala/collection/IterableOnceOps;Ljava/lang/Object;I)I
  #453 = InterfaceMethodref #325.#452     // scala/collection/IterableOnceOps.copyToArray$:(Lscala/collection/IterableOnceOps;Ljava/lang/Object;I)I
  #454 = Utf8               sum
  #455 = Utf8               (Lscala/math/Numeric;)Ljava/lang/Object;
  #456 = Utf8               <B:Ljava/lang/Object;>(Lscala/math/Numeric<TB;>;)TB;
  #457 = Utf8               num
  #458 = Utf8               sum$
  #459 = Utf8               (Lscala/collection/IterableOnceOps;Lscala/math/Numeric;)Ljava/lang/Object;
  #460 = NameAndType        #458:#459     // sum$:(Lscala/collection/IterableOnceOps;Lscala/math/Numeric;)Ljava/lang/Object;
  #461 = InterfaceMethodref #325.#460     // scala/collection/IterableOnceOps.sum$:(Lscala/collection/IterableOnceOps;Lscala/math/Numeric;)Ljava/lang/Object;
  #462 = Utf8               Lscala/math/Numeric;
  #463 = Utf8               product
  #464 = Utf8               product$
  #465 = NameAndType        #464:#459     // product$:(Lscala/collection/IterableOnceOps;Lscala/math/Numeric;)Ljava/lang/Object;
  #466 = InterfaceMethodref #325.#465     // scala/collection/IterableOnceOps.product$:(Lscala/collection/IterableOnceOps;Lscala/math/Numeric;)Ljava/lang/Object;
  #467 = Utf8               min
  #468 = Utf8               (Lscala/math/Ordering;)Ljava/lang/Object;
  #469 = Utf8               <B:Ljava/lang/Object;>(Lscala/math/Ordering<TB;>;)TA;
  #470 = Utf8               ord
  #471 = Utf8               min$
  #472 = Utf8               (Lscala/collection/IterableOnceOps;Lscala/math/Ordering;)Ljava/lang/Object;
  #473 = NameAndType        #471:#472     // min$:(Lscala/collection/IterableOnceOps;Lscala/math/Ordering;)Ljava/lang/Object;
  #474 = InterfaceMethodref #325.#473     // scala/collection/IterableOnceOps.min$:(Lscala/collection/IterableOnceOps;Lscala/math/Ordering;)Ljava/lang/Object;
  #475 = Utf8               Lscala/math/Ordering;
  #476 = Utf8               minOption
  #477 = Utf8               (Lscala/math/Ordering;)Lscala/Option;
  #478 = Utf8               <B:Ljava/lang/Object;>(Lscala/math/Ordering<TB;>;)Lscala/Option<TA;>;
  #479 = Utf8               minOption$
  #480 = Utf8               (Lscala/collection/IterableOnceOps;Lscala/math/Ordering;)Lscala/Option;
  #481 = NameAndType        #479:#480     // minOption$:(Lscala/collection/IterableOnceOps;Lscala/math/Ordering;)Lscala/Option;
  #482 = InterfaceMethodref #325.#481     // scala/collection/IterableOnceOps.minOption$:(Lscala/collection/IterableOnceOps;Lscala/math/Ordering;)Lscala/Option;
  #483 = Utf8               max
  #484 = Utf8               max$
  #485 = NameAndType        #484:#472     // max$:(Lscala/collection/IterableOnceOps;Lscala/math/Ordering;)Ljava/lang/Object;
  #486 = InterfaceMethodref #325.#485     // scala/collection/IterableOnceOps.max$:(Lscala/collection/IterableOnceOps;Lscala/math/Ordering;)Ljava/lang/Object;
  #487 = Utf8               maxOption
  #488 = Utf8               maxOption$
  #489 = NameAndType        #488:#480     // maxOption$:(Lscala/collection/IterableOnceOps;Lscala/math/Ordering;)Lscala/Option;
  #490 = InterfaceMethodref #325.#489     // scala/collection/IterableOnceOps.maxOption$:(Lscala/collection/IterableOnceOps;Lscala/math/Ordering;)Lscala/Option;
  #491 = Utf8               maxBy
  #492 = Utf8               (Lscala/Function1;Lscala/math/Ordering;)Ljava/lang/Object;
  #493 = Utf8               <B:Ljava/lang/Object;>(Lscala/Function1<TA;TB;>;Lscala/math/Ordering<TB;>;)TA;
  #494 = Utf8               cmp
  #495 = Utf8               maxBy$
  #496 = Utf8               (Lscala/collection/IterableOnceOps;Lscala/Function1;Lscala/math/Ordering;)Ljava/lang/Object;
  #497 = NameAndType        #495:#496     // maxBy$:(Lscala/collection/IterableOnceOps;Lscala/Function1;Lscala/math/Ordering;)Ljava/lang/Object;
  #498 = InterfaceMethodref #325.#497     // scala/collection/IterableOnceOps.maxBy$:(Lscala/collection/IterableOnceOps;Lscala/Function1;Lscala/math/Ordering;)Ljava/lang/Object;
  #499 = Utf8               maxByOption
  #500 = Utf8               (Lscala/Function1;Lscala/math/Ordering;)Lscala/Option;
  #501 = Utf8               <B:Ljava/lang/Object;>(Lscala/Function1<TA;TB;>;Lscala/math/Ordering<TB;>;)Lscala/Option<TA;>;
  #502 = Utf8               maxByOption$
  #503 = Utf8               (Lscala/collection/IterableOnceOps;Lscala/Function1;Lscala/math/Ordering;)Lscala/Option;
  #504 = NameAndType        #502:#503     // maxByOption$:(Lscala/collection/IterableOnceOps;Lscala/Function1;Lscala/math/Ordering;)Lscala/Option;
  #505 = InterfaceMethodref #325.#504     // scala/collection/IterableOnceOps.maxByOption$:(Lscala/collection/IterableOnceOps;Lscala/Function1;Lscala/math/Ordering;)Lscala/Option;
  #506 = Utf8               minBy
  #507 = Utf8               minBy$
  #508 = NameAndType        #507:#496     // minBy$:(Lscala/collection/IterableOnceOps;Lscala/Function1;Lscala/math/Ordering;)Ljava/lang/Object;
  #509 = InterfaceMethodref #325.#508     // scala/collection/IterableOnceOps.minBy$:(Lscala/collection/IterableOnceOps;Lscala/Function1;Lscala/math/Ordering;)Ljava/lang/Object;
  #510 = Utf8               minByOption
  #511 = Utf8               minByOption$
  #512 = NameAndType        #511:#503     // minByOption$:(Lscala/collection/IterableOnceOps;Lscala/Function1;Lscala/math/Ordering;)Lscala/Option;
  #513 = InterfaceMethodref #325.#512     // scala/collection/IterableOnceOps.minByOption$:(Lscala/collection/IterableOnceOps;Lscala/Function1;Lscala/math/Ordering;)Lscala/Option;
  #514 = Utf8               collectFirst
  #515 = Utf8               (Lscala/PartialFunction;)Lscala/Option;
  #516 = Utf8               <B:Ljava/lang/Object;>(Lscala/PartialFunction<TA;TB;>;)Lscala/Option<TB;>;
  #517 = Utf8               collectFirst$
  #518 = Utf8               (Lscala/collection/IterableOnceOps;Lscala/PartialFunction;)Lscala/Option;
  #519 = NameAndType        #517:#518     // collectFirst$:(Lscala/collection/IterableOnceOps;Lscala/PartialFunction;)Lscala/Option;
  #520 = InterfaceMethodref #325.#519     // scala/collection/IterableOnceOps.collectFirst$:(Lscala/collection/IterableOnceOps;Lscala/PartialFunction;)Lscala/Option;
  #521 = Utf8               aggregate
  #522 = Utf8               (Lscala/Function0;Lscala/Function2;Lscala/Function2;)Ljava/lang/Object;
  #523 = Utf8               <B:Ljava/lang/Object;>(Lscala/Function0<TB;>;Lscala/Function2<TB;TA;TB;>;Lscala/Function2<TB;TB;TB;>;)TB;
  #524 = Utf8               seqop
  #525 = Utf8               combop
  #526 = Utf8               aggregate$
  #527 = Utf8               (Lscala/collection/IterableOnceOps;Lscala/Function0;Lscala/Function2;Lscala/Function2;)Ljava/lang/Object;
  #528 = NameAndType        #526:#527     // aggregate$:(Lscala/collection/IterableOnceOps;Lscala/Function0;Lscala/Function2;Lscala/Function2;)Ljava/lang/Object;
  #529 = InterfaceMethodref #325.#528     // scala/collection/IterableOnceOps.aggregate$:(Lscala/collection/IterableOnceOps;Lscala/Function0;Lscala/Function2;Lscala/Function2;)Ljava/lang/Object;
  #530 = Utf8               corresponds
  #531 = Utf8               (Lscala/collection/IterableOnce;Lscala/Function2;)Z
  #532 = Utf8               <B:Ljava/lang/Object;>(Lscala/collection/IterableOnce<TB;>;Lscala/Function2<TA;TB;Ljava/lang/Object;>;)Z
  #533 = Utf8               corresponds$
  #534 = Utf8               (Lscala/collection/IterableOnceOps;Lscala/collection/IterableOnce;Lscala/Function2;)Z
  #535 = NameAndType        #533:#534     // corresponds$:(Lscala/collection/IterableOnceOps;Lscala/collection/IterableOnce;Lscala/Function2;)Z
  #536 = InterfaceMethodref #325.#535     // scala/collection/IterableOnceOps.corresponds$:(Lscala/collection/IterableOnceOps;Lscala/collection/IterableOnce;Lscala/Function2;)Z
  #537 = Utf8               mkString
  #538 = Utf8               (Ljava/lang/String;Ljava/lang/String;Ljava/lang/String;)Ljava/lang/String;
  #539 = Utf8               sep
  #540 = Utf8               end
  #541 = Utf8               mkString$
  #542 = Utf8               (Lscala/collection/IterableOnceOps;Ljava/lang/String;Ljava/lang/String;Ljava/lang/String;)Ljava/lang/String;
  #543 = NameAndType        #541:#542     // mkString$:(Lscala/collection/IterableOnceOps;Ljava/lang/String;Ljava/lang/String;Ljava/lang/String;)Ljava/lang/String;
  #544 = InterfaceMethodref #325.#543     // scala/collection/IterableOnceOps.mkString$:(Lscala/collection/IterableOnceOps;Ljava/lang/String;Ljava/lang/String;Ljava/lang/String;)Ljava/lang/String;
  #545 = Utf8               Ljava/lang/String;
  #546 = Utf8               (Ljava/lang/String;)Ljava/lang/String;
  #547 = Utf8               (Lscala/collection/IterableOnceOps;Ljava/lang/String;)Ljava/lang/String;
  #548 = NameAndType        #541:#547     // mkString$:(Lscala/collection/IterableOnceOps;Ljava/lang/String;)Ljava/lang/String;
  #549 = InterfaceMethodref #325.#548     // scala/collection/IterableOnceOps.mkString$:(Lscala/collection/IterableOnceOps;Ljava/lang/String;)Ljava/lang/String;
  #550 = Utf8               (Lscala/collection/IterableOnceOps;)Ljava/lang/String;
  #551 = NameAndType        #541:#550     // mkString$:(Lscala/collection/IterableOnceOps;)Ljava/lang/String;
  #552 = InterfaceMethodref #325.#551     // scala/collection/IterableOnceOps.mkString$:(Lscala/collection/IterableOnceOps;)Ljava/lang/String;
  #553 = Utf8               addString
  #554 = Utf8               (Lscala/collection/mutable/StringBuilder;Ljava/lang/String;Ljava/lang/String;Ljava/lang/String;)Lscala/collection/mutable/StringBuilder;
  #555 = Utf8               b
  #556 = Utf8               addString$
  #557 = Utf8               (Lscala/collection/IterableOnceOps;Lscala/collection/mutable/StringBuilder;Ljava/lang/String;Ljava/lang/String;Ljava/lang/String;)Lscala/collection/mutable/StringBuilder;
  #558 = NameAndType        #556:#557     // addString$:(Lscala/collection/IterableOnceOps;Lscala/collection/mutable/StringBuilder;Ljava/lang/String;Ljava/lang/String;Ljava/lang/String;)Lscala/collection/mutable/StringBuilder;
  #559 = InterfaceMethodref #325.#558     // scala/collection/IterableOnceOps.addString$:(Lscala/collection/IterableOnceOps;Lscala/collection/mutable/StringBuilder;Ljava/lang/String;Ljava/lang/String;Ljava/lang/String;)Lscala/collection/mutable/StringBuilder;
  #560 = Utf8               Lscala/collection/mutable/StringBuilder;
  #561 = Utf8               (Lscala/collection/mutable/StringBuilder;Ljava/lang/String;)Lscala/collection/mutable/StringBuilder;
  #562 = Utf8               (Lscala/collection/IterableOnceOps;Lscala/collection/mutable/StringBuilder;Ljava/lang/String;)Lscala/collection/mutable/StringBuilder;
  #563 = NameAndType        #556:#562     // addString$:(Lscala/collection/IterableOnceOps;Lscala/collection/mutable/StringBuilder;Ljava/lang/String;)Lscala/collection/mutable/StringBuilder;
  #564 = InterfaceMethodref #325.#563     // scala/collection/IterableOnceOps.addString$:(Lscala/collection/IterableOnceOps;Lscala/collection/mutable/StringBuilder;Ljava/lang/String;)Lscala/collection/mutable/StringBuilder;
  #565 = Utf8               (Lscala/collection/mutable/StringBuilder;)Lscala/collection/mutable/StringBuilder;
  #566 = Utf8               (Lscala/collection/IterableOnceOps;Lscala/collection/mutable/StringBuilder;)Lscala/collection/mutable/StringBuilder;
  #567 = NameAndType        #556:#566     // addString$:(Lscala/collection/IterableOnceOps;Lscala/collection/mutable/StringBuilder;)Lscala/collection/mutable/StringBuilder;
  #568 = InterfaceMethodref #325.#567     // scala/collection/IterableOnceOps.addString$:(Lscala/collection/IterableOnceOps;Lscala/collection/mutable/StringBuilder;)Lscala/collection/mutable/StringBuilder;
  #569 = Utf8               to
  #570 = Utf8               (Lscala/collection/Factory;)Ljava/lang/Object;
  #571 = Utf8               <C1:Ljava/lang/Object;>(Lscala/collection/Factory<TA;TC1;>;)TC1;
  #572 = Utf8               factory
  #573 = Utf8               to$
  #574 = Utf8               (Lscala/collection/IterableOnceOps;Lscala/collection/Factory;)Ljava/lang/Object;
  #575 = NameAndType        #573:#574     // to$:(Lscala/collection/IterableOnceOps;Lscala/collection/Factory;)Ljava/lang/Object;
  #576 = InterfaceMethodref #325.#575     // scala/collection/IterableOnceOps.to$:(Lscala/collection/IterableOnceOps;Lscala/collection/Factory;)Ljava/lang/Object;
  #577 = Utf8               Lscala/collection/Factory;
  #578 = Utf8               toIterator
  #579 = Utf8               toIterator$
  #580 = Utf8               (Lscala/collection/IterableOnceOps;)Lscala/collection/Iterator;
  #581 = NameAndType        #579:#580     // toIterator$:(Lscala/collection/IterableOnceOps;)Lscala/collection/Iterator;
  #582 = InterfaceMethodref #325.#581     // scala/collection/IterableOnceOps.toIterator$:(Lscala/collection/IterableOnceOps;)Lscala/collection/Iterator;
  #583 = Utf8               toList
  #584 = Utf8               ()Lscala/collection/immutable/List;
  #585 = Utf8               ()Lscala/collection/immutable/List<TA;>;
  #586 = Utf8               toList$
  #587 = Utf8               (Lscala/collection/IterableOnceOps;)Lscala/collection/immutable/List;
  #588 = NameAndType        #586:#587     // toList$:(Lscala/collection/IterableOnceOps;)Lscala/collection/immutable/List;
  #589 = InterfaceMethodref #325.#588     // scala/collection/IterableOnceOps.toList$:(Lscala/collection/IterableOnceOps;)Lscala/collection/immutable/List;
  #590 = Utf8               toMap
  #591 = Utf8               (Lscala/$less$colon$less;)Lscala/collection/immutable/Map;
  #592 = Utf8               <K$:Ljava/lang/Object;V$:Ljava/lang/Object;>(Lscala/$less$colon$less<TA;Lscala/Tuple2<TK$;TV$;>;>;)Lscala/collection/immutable/Map<TK$;TV$;>;
  #593 = Utf8               toMap$
  #594 = Utf8               (Lscala/collection/IterableOnceOps;Lscala/$less$colon$less;)Lscala/collection/immutable/Map;
  #595 = NameAndType        #593:#594     // toMap$:(Lscala/collection/IterableOnceOps;Lscala/$less$colon$less;)Lscala/collection/immutable/Map;
  #596 = InterfaceMethodref #325.#595     // scala/collection/IterableOnceOps.toMap$:(Lscala/collection/IterableOnceOps;Lscala/$less$colon$less;)Lscala/collection/immutable/Map;
  #597 = Utf8               Lscala/$less$colon$less;
  #598 = Utf8               toSet
  #599 = Utf8               ()Lscala/collection/immutable/Set;
  #600 = Utf8               <B:Ljava/lang/Object;>()Lscala/collection/immutable/Set<TB;>;
  #601 = Utf8               toSet$
  #602 = Utf8               (Lscala/collection/IterableOnceOps;)Lscala/collection/immutable/Set;
  #603 = NameAndType        #601:#602     // toSet$:(Lscala/collection/IterableOnceOps;)Lscala/collection/immutable/Set;
  #604 = InterfaceMethodref #325.#603     // scala/collection/IterableOnceOps.toSet$:(Lscala/collection/IterableOnceOps;)Lscala/collection/immutable/Set;
  #605 = Utf8               toSeq
  #606 = Utf8               ()Lscala/collection/immutable/Seq;
  #607 = Utf8               ()Lscala/collection/immutable/Seq<TA;>;
  #608 = Utf8               toSeq$
  #609 = Utf8               (Lscala/collection/IterableOnceOps;)Lscala/collection/immutable/Seq;
  #610 = NameAndType        #608:#609     // toSeq$:(Lscala/collection/IterableOnceOps;)Lscala/collection/immutable/Seq;
  #611 = InterfaceMethodref #325.#610     // scala/collection/IterableOnceOps.toSeq$:(Lscala/collection/IterableOnceOps;)Lscala/collection/immutable/Seq;
  #612 = Utf8               toIndexedSeq
  #613 = Utf8               ()Lscala/collection/immutable/IndexedSeq;
  #614 = Utf8               ()Lscala/collection/immutable/IndexedSeq<TA;>;
  #615 = Utf8               toIndexedSeq$
  #616 = Utf8               (Lscala/collection/IterableOnceOps;)Lscala/collection/immutable/IndexedSeq;
  #617 = NameAndType        #615:#616     // toIndexedSeq$:(Lscala/collection/IterableOnceOps;)Lscala/collection/immutable/IndexedSeq;
  #618 = InterfaceMethodref #325.#617     // scala/collection/IterableOnceOps.toIndexedSeq$:(Lscala/collection/IterableOnceOps;)Lscala/collection/immutable/IndexedSeq;
  #619 = Utf8               toStream
  #620 = Utf8               ()Lscala/collection/immutable/Stream;
  #621 = Utf8               ()Lscala/collection/immutable/Stream<TA;>;
  #622 = Utf8               toStream$
  #623 = Utf8               (Lscala/collection/IterableOnceOps;)Lscala/collection/immutable/Stream;
  #624 = NameAndType        #622:#623     // toStream$:(Lscala/collection/IterableOnceOps;)Lscala/collection/immutable/Stream;
  #625 = InterfaceMethodref #325.#624     // scala/collection/IterableOnceOps.toStream$:(Lscala/collection/IterableOnceOps;)Lscala/collection/immutable/Stream;
  #626 = Utf8               toBuffer
  #627 = Utf8               ()Lscala/collection/mutable/Buffer;
  #628 = Utf8               <B:Ljava/lang/Object;>()Lscala/collection/mutable/Buffer<TB;>;
  #629 = Utf8               toBuffer$
  #630 = Utf8               (Lscala/collection/IterableOnceOps;)Lscala/collection/mutable/Buffer;
  #631 = NameAndType        #629:#630     // toBuffer$:(Lscala/collection/IterableOnceOps;)Lscala/collection/mutable/Buffer;
  #632 = InterfaceMethodref #325.#631     // scala/collection/IterableOnceOps.toBuffer$:(Lscala/collection/IterableOnceOps;)Lscala/collection/mutable/Buffer;
  #633 = Utf8               toArray
  #634 = Utf8               (Lscala/reflect/ClassTag;)Ljava/lang/Object;
  #635 = Utf8               <B:Ljava/lang/Object;>(Lscala/reflect/ClassTag<TB;>;)Ljava/lang/Object;
  #636 = Utf8               evidence$2
  #637 = Utf8               toArray$
  #638 = Utf8               (Lscala/collection/IterableOnceOps;Lscala/reflect/ClassTag;)Ljava/lang/Object;
  #639 = NameAndType        #637:#638     // toArray$:(Lscala/collection/IterableOnceOps;Lscala/reflect/ClassTag;)Ljava/lang/Object;
  #640 = InterfaceMethodref #325.#639     // scala/collection/IterableOnceOps.toArray$:(Lscala/collection/IterableOnceOps;Lscala/reflect/ClassTag;)Ljava/lang/Object;
  #641 = Utf8               Lscala/reflect/ClassTag;
  #642 = Utf8               reversed
  #643 = Utf8               ()Lscala/collection/Iterable;
  #644 = Utf8               ()Lscala/collection/Iterable<TA;>;
  #645 = Utf8               reversed$
  #646 = Utf8               (Lscala/collection/IterableOnceOps;)Lscala/collection/Iterable;
  #647 = NameAndType        #645:#646     // reversed$:(Lscala/collection/IterableOnceOps;)Lscala/collection/Iterable;
  #648 = InterfaceMethodref #325.#647     // scala/collection/IterableOnceOps.reversed$:(Lscala/collection/IterableOnceOps;)Lscala/collection/Iterable;
  #649 = Utf8               stepper
  #650 = Utf8               (Lscala/collection/StepperShape;)Lscala/collection/Stepper;
  #651 = Utf8               <S::Lscala/collection/Stepper<*>;>(Lscala/collection/StepperShape<TA;TS;>;)TS;
  #652 = Utf8               shape
  #653 = Utf8               scala/collection/IterableOnce
  #654 = Class              #653          // scala/collection/IterableOnce
  #655 = Utf8               stepper$
  #656 = Utf8               (Lscala/collection/IterableOnce;Lscala/collection/StepperShape;)Lscala/collection/Stepper;
  #657 = NameAndType        #655:#656     // stepper$:(Lscala/collection/IterableOnce;Lscala/collection/StepperShape;)Lscala/collection/Stepper;
  #658 = InterfaceMethodref #654.#657     // scala/collection/IterableOnce.stepper$:(Lscala/collection/IterableOnce;Lscala/collection/StepperShape;)Lscala/collection/Stepper;
  #659 = Utf8               Lscala/collection/StepperShape;
  #660 = Utf8               knownSize
  #661 = NameAndType        #38:#21       // scala$collection$immutable$NewVectorIterator$$len1:I
  #662 = Fieldref           #2.#661       // scala/collection/immutable/NewVectorIterator.scala$collection$immutable$NewVectorIterator$$len1:I
  #663 = NameAndType        #36:#21       // scala$collection$immutable$NewVectorIterator$$i1:I
  #664 = Fieldref           #2.#663       // scala/collection/immutable/NewVectorIterator.scala$collection$immutable$NewVectorIterator$$i1:I
  #665 = Utf8               hasNext
  #666 = Utf8               next
  #667 = Utf8               ()Ljava/lang/Object;
  #668 = Utf8               ()TA;
  #669 = NameAndType        #35:#21       // a1len:I
  #670 = Fieldref           #2.#669       // scala/collection/immutable/NewVectorIterator.a1len:I
  #671 = Utf8               advance
  #672 = Utf8               ()V
  #673 = NameAndType        #671:#672     // advance:()V
  #674 = Methodref          #2.#673       // scala/collection/immutable/NewVectorIterator.advance:()V
  #675 = NameAndType        #23:#24       // a1:[Ljava/lang/Object;
  #676 = Fieldref           #2.#675       // scala/collection/immutable/NewVectorIterator.a1:[Ljava/lang/Object;
  #677 = Utf8               r
  #678 = Utf8               advanceSlice
  #679 = Utf8               scala/collection/Iterator$
  #680 = Class              #679          // scala/collection/Iterator$
  #681 = Utf8               MODULE$
  #682 = Utf8               Lscala/collection/Iterator$;
  #683 = NameAndType        #681:#682     // MODULE$:Lscala/collection/Iterator$;
  #684 = Fieldref           #680.#683     // scala/collection/Iterator$.MODULE$:Lscala/collection/Iterator$;
  #685 = Utf8               scala$collection$Iterator$$_empty
  #686 = NameAndType        #685:#304     // scala$collection$Iterator$$_empty:Lscala/collection/Iterator;
  #687 = Fieldref           #680.#686     // scala/collection/Iterator$.scala$collection$Iterator$$_empty:Lscala/collection/Iterator;
  #688 = NameAndType        #666:#667     // next:()Ljava/lang/Object;
  #689 = InterfaceMethodref #7.#688       // scala/collection/Iterator.next:()Ljava/lang/Object;
  #690 = NameAndType        #39:#21       // sliceIdx:I
  #691 = Fieldref           #2.#690       // scala/collection/immutable/NewVectorIterator.sliceIdx:I
  #692 = NameAndType        #17:#18       // v:Lscala/collection/immutable/Vector;
  #693 = Fieldref           #2.#692       // scala/collection/immutable/NewVectorIterator.v:Lscala/collection/immutable/Vector;
  #694 = Utf8               scala/collection/immutable/Vector
  #695 = Class              #694          // scala/collection/immutable/Vector
  #696 = Utf8               vectorSlice
  #697 = Utf8               (I)[Ljava/lang/Object;
  #698 = NameAndType        #696:#697     // vectorSlice:(I)[Ljava/lang/Object;
  #699 = Methodref          #695.#698     // scala/collection/immutable/Vector.vectorSlice:(I)[Ljava/lang/Object;
  #700 = NameAndType        #42:#21       // sliceEnd:I
  #701 = Fieldref           #2.#700       // scala/collection/immutable/NewVectorIterator.sliceEnd:I
  #702 = NameAndType        #41:#21       // sliceStart:I
  #703 = Fieldref           #2.#702       // scala/collection/immutable/NewVectorIterator.sliceStart:I
  #704 = Utf8               scala/collection/immutable/VectorInline$
  #705 = Class              #704          // scala/collection/immutable/VectorInline$
  #706 = Utf8               Lscala/collection/immutable/VectorInline$;
  #707 = NameAndType        #681:#706     // MODULE$:Lscala/collection/immutable/VectorInline$;
  #708 = Fieldref           #705.#707     // scala/collection/immutable/VectorInline$.MODULE$:Lscala/collection/immutable/VectorInline$;
  #709 = NameAndType        #22:#21       // sliceCount:I
  #710 = Fieldref           #2.#709       // scala/collection/immutable/NewVectorIterator.sliceCount:I
  #711 = Utf8               java/lang/Math
  #712 = Class              #711          // java/lang/Math
  #713 = Utf8               abs
  #714 = Utf8               (I)I
  #715 = NameAndType        #713:#714     // abs:(I)I
  #716 = Methodref          #712.#715     // java/lang/Math.abs:(I)I
  #717 = NameAndType        #40:#21       // sliceDim:I
  #718 = Fieldref           #2.#717       // scala/collection/immutable/NewVectorIterator.sliceDim:I
  #719 = Class              #26           // "[[Ljava/lang/Object;"
  #720 = NameAndType        #25:#26       // a2:[[Ljava/lang/Object;
  #721 = Fieldref           #2.#720       // scala/collection/immutable/NewVectorIterator.a2:[[Ljava/lang/Object;
  #722 = Class              #28           // "[[[Ljava/lang/Object;"
  #723 = NameAndType        #27:#28       // a3:[[[Ljava/lang/Object;
  #724 = Fieldref           #2.#723       // scala/collection/immutable/NewVectorIterator.a3:[[[Ljava/lang/Object;
  #725 = Class              #30           // "[[[[Ljava/lang/Object;"
  #726 = NameAndType        #29:#30       // a4:[[[[Ljava/lang/Object;
  #727 = Fieldref           #2.#726       // scala/collection/immutable/NewVectorIterator.a4:[[[[Ljava/lang/Object;
  #728 = Class              #32           // "[[[[[Ljava/lang/Object;"
  #729 = NameAndType        #31:#32       // a5:[[[[[Ljava/lang/Object;
  #730 = Fieldref           #2.#729       // scala/collection/immutable/NewVectorIterator.a5:[[[[[Ljava/lang/Object;
  #731 = Class              #34           // "[[[[[[Ljava/lang/Object;"
  #732 = NameAndType        #33:#34       // a6:[[[[[[Ljava/lang/Object;
  #733 = Fieldref           #2.#732       // scala/collection/immutable/NewVectorIterator.a6:[[[[[[Ljava/lang/Object;
  #734 = Utf8               scala/MatchError
  #735 = Class              #734          // scala/MatchError
  #736 = Utf8               java/lang/Integer
  #737 = Class              #736          // java/lang/Integer
  #738 = Utf8               valueOf
  #739 = Utf8               (I)Ljava/lang/Integer;
  #740 = NameAndType        #738:#739     // valueOf:(I)Ljava/lang/Integer;
  #741 = Methodref          #737.#740     // java/lang/Integer.valueOf:(I)Ljava/lang/Integer;
  #742 = Utf8               <init>
  #743 = Utf8               (Ljava/lang/Object;)V
  #744 = NameAndType        #742:#743     // "<init>":(Ljava/lang/Object;)V
  #745 = Methodref          #735.#744     // scala/MatchError."<init>":(Ljava/lang/Object;)V
  #746 = NameAndType        #20:#21       // totalLength:I
  #747 = Fieldref           #2.#746       // scala/collection/immutable/NewVectorIterator.totalLength:I
  #748 = NameAndType        #37:#21       // oldPos:I
  #749 = Fieldref           #2.#748       // scala/collection/immutable/NewVectorIterator.oldPos:I
  #750 = Utf8               slice
  #751 = Utf8               vectorSliceDim_c
  #752 = Utf8               vectorSliceDim_idx
  #753 = Class              #24           // "[Ljava/lang/Object;"
  #754 = NameAndType        #678:#672     // advanceSlice:()V
  #755 = Methodref          #2.#754       // scala/collection/immutable/NewVectorIterator.advanceSlice:()V
  #756 = Utf8               advanceA
  #757 = Utf8               (II)V
  #758 = NameAndType        #756:#757     // advanceA:(II)V
  #759 = Methodref          #2.#758       // scala/collection/immutable/NewVectorIterator.advanceA:(II)V
  #760 = Utf8               (II)I
  #761 = NameAndType        #467:#760     // min:(II)I
  #762 = Methodref          #712.#761     // java/lang/Math.min:(II)I
  #763 = Utf8               io
  #764 = Utf8               xor
  #765 = Utf8               pos
  #766 = Integer            32768
  #767 = Integer            1048576
  #768 = Integer            33554432
  #769 = Utf8               setA
  #770 = Utf8               drop
  #771 = Utf8               (I)Lscala/collection/Iterator;
  #772 = Utf8               (I)Lscala/collection/Iterator<TA;>;
  #773 = NameAndType        #769:#757     // setA:(II)V
  #774 = Methodref          #2.#773       // scala/collection/immutable/NewVectorIterator.setA:(II)V
  #775 = Utf8               newpos
  #776 = Utf8               take
  #777 = NameAndType        #483:#760     // max:(II)I
  #778 = Methodref          #712.#777     // java/lang/Math.max:(II)I
  #779 = Utf8               trunc
  #780 = NameAndType        #770:#771     // drop:(I)Lscala/collection/Iterator;
  #781 = Methodref          #2.#780       // scala/collection/immutable/NewVectorIterator.drop:(I)Lscala/collection/Iterator;
  #782 = NameAndType        #776:#771     // take:(I)Lscala/collection/Iterator;
  #783 = Methodref          #2.#782       // scala/collection/immutable/NewVectorIterator.take:(I)Lscala/collection/Iterator;
  #784 = Utf8               _until
  #785 = Utf8               (Ljava/lang/Object;II)I
  #786 = Utf8               <B:Ljava/lang/Object;>(Ljava/lang/Object;II)I
  #787 = Utf8               java/lang/reflect/Array
  #788 = Class              #787          // java/lang/reflect/Array
  #789 = Utf8               getLength
  #790 = NameAndType        #789:#148     // getLength:(Ljava/lang/Object;)I
  #791 = Methodref          #788.#790     // java/lang/reflect/Array.getLength:(Ljava/lang/Object;)I
  #792 = Utf8               scala/collection/IterableOnce$
  #793 = Class              #792          // scala/collection/IterableOnce$
  #794 = Utf8               Lscala/collection/IterableOnce$;
  #795 = NameAndType        #681:#794     // MODULE$:Lscala/collection/IterableOnce$;
  #796 = Fieldref           #793.#795     // scala/collection/IterableOnce$.MODULE$:Lscala/collection/IterableOnce$;
  #797 = Utf8               scala/math/package$
  #798 = Class              #797          // scala/math/package$
  #799 = Utf8               Lscala/math/package$;
  #800 = NameAndType        #681:#799     // MODULE$:Lscala/math/package$;
  #801 = Fieldref           #798.#800     // scala/math/package$.MODULE$:Lscala/math/package$;
  #802 = Utf8               java/lang/System
  #803 = Class              #802          // java/lang/System
  #804 = Utf8               arraycopy
  #805 = Utf8               (Ljava/lang/Object;ILjava/lang/Object;II)V
  #806 = NameAndType        #804:#805     // arraycopy:(Ljava/lang/Object;ILjava/lang/Object;II)V
  #807 = Methodref          #803.#806     // java/lang/System.arraycopy:(Ljava/lang/Object;ILjava/lang/Object;II)V
  #808 = Utf8               scala/Array$
  #809 = Class              #808          // scala/Array$
  #810 = Utf8               Lscala/Array$;
  #811 = NameAndType        #681:#810     // MODULE$:Lscala/Array$;
  #812 = Fieldref           #809.#811     // scala/Array$.MODULE$:Lscala/Array$;
  #813 = Utf8               copy
  #814 = NameAndType        #813:#805     // copy:(Ljava/lang/Object;ILjava/lang/Object;II)V
  #815 = Methodref          #809.#814     // scala/Array$.copy:(Ljava/lang/Object;ILjava/lang/Object;II)V
  #816 = Utf8               copied
  #817 = Utf8               isBoxed
  #818 = Utf8               elemsToCopyToArray_min_y
  #819 = Utf8               elemsToCopyToArray_max_y
  #820 = Utf8               toVector
  #821 = Utf8               ()Lscala/collection/immutable/Vector;
  #822 = Utf8               ()Lscala/collection/immutable/Vector<TA;>;
  #823 = Utf8               (II)Ljava/lang/Object;
  #824 = NameAndType        #750:#823     // slice:(II)Ljava/lang/Object;
  #825 = Methodref          #695.#824     // scala/collection/immutable/Vector.slice:(II)Ljava/lang/Object;
  #826 = Utf8               split
  #827 = Utf8               (I)Lscala/collection/immutable/NewVectorIterator;
  #828 = Utf8               (I)Lscala/collection/immutable/NewVectorIterator<TA;>;
  #829 = Utf8               at
  #830 = Utf8               clone
  #831 = NameAndType        #830:#667     // clone:()Ljava/lang/Object;
  #832 = Methodref          #2.#831       // scala/collection/immutable/NewVectorIterator.clone:()Ljava/lang/Object;
  #833 = Utf8               it2
  #834 = Utf8               (Lscala/Function1;)Ljava/lang/Object;
  #835 = NameAndType        #305:#168     // tapEach:(Lscala/Function1;)Lscala/collection/Iterator;
  #836 = Methodref          #2.#835       // scala/collection/immutable/NewVectorIterator.tapEach:(Lscala/Function1;)Lscala/collection/Iterator;
  #837 = NameAndType        #276:#52      // zipWithIndex:()Lscala/collection/Iterator;
  #838 = Methodref          #2.#837       // scala/collection/immutable/NewVectorIterator.zipWithIndex:()Lscala/collection/Iterator;
  #839 = NameAndType        #242:#168     // dropWhile:(Lscala/Function1;)Lscala/collection/Iterator;
  #840 = Methodref          #2.#839       // scala/collection/immutable/NewVectorIterator.dropWhile:(Lscala/Function1;)Lscala/collection/Iterator;
  #841 = NameAndType        #238:#168     // takeWhile:(Lscala/Function1;)Lscala/collection/Iterator;
  #842 = Methodref          #2.#841       // scala/collection/immutable/NewVectorIterator.takeWhile:(Lscala/Function1;)Lscala/collection/Iterator;
  #843 = Utf8               asIterable
  #844 = NameAndType        #220:#168     // flatten:(Lscala/Function1;)Lscala/collection/Iterator;
  #845 = Methodref          #2.#844       // scala/collection/immutable/NewVectorIterator.flatten:(Lscala/Function1;)Lscala/collection/Iterator;
  #846 = NameAndType        #215:#168     // flatMap:(Lscala/Function1;)Lscala/collection/Iterator;
  #847 = Methodref          #2.#846       // scala/collection/immutable/NewVectorIterator.flatMap:(Lscala/Function1;)Lscala/collection/Iterator;
  #848 = NameAndType        #210:#168     // map:(Lscala/Function1;)Lscala/collection/Iterator;
  #849 = Methodref          #2.#848       // scala/collection/immutable/NewVectorIterator.map:(Lscala/Function1;)Lscala/collection/Iterator;
  #850 = Utf8               (Lscala/PartialFunction;)Ljava/lang/Object;
  #851 = NameAndType        #191:#192     // collect:(Lscala/PartialFunction;)Lscala/collection/Iterator;
  #852 = Methodref          #2.#851       // scala/collection/immutable/NewVectorIterator.collect:(Lscala/PartialFunction;)Lscala/collection/Iterator;
  #853 = Utf8               pred
  #854 = NameAndType        #174:#168     // filterNot:(Lscala/Function1;)Lscala/collection/Iterator;
  #855 = Methodref          #2.#854       // scala/collection/immutable/NewVectorIterator.filterNot:(Lscala/Function1;)Lscala/collection/Iterator;
  #856 = NameAndType        #167:#168     // filter:(Lscala/Function1;)Lscala/collection/Iterator;
  #857 = Methodref          #2.#856       // scala/collection/immutable/NewVectorIterator.filter:(Lscala/Function1;)Lscala/collection/Iterator;
  #858 = NameAndType        #120:#121     // scanLeft:(Ljava/lang/Object;Lscala/Function2;)Lscala/collection/Iterator;
  #859 = Methodref          #2.#858       // scala/collection/immutable/NewVectorIterator.scanLeft:(Ljava/lang/Object;Lscala/Function2;)Lscala/collection/Iterator;
  #860 = NameAndType        #750:#251     // slice:(II)Lscala/collection/Iterator;
  #861 = Methodref          #2.#860       // scala/collection/immutable/NewVectorIterator.slice:(II)Lscala/collection/Iterator;
  #862 = Utf8               (I)Ljava/lang/Object;
  #863 = Utf8               (Lscala/collection/immutable/Vector;II)V
  #864 = Utf8               (Lscala/collection/immutable/Vector<TA;>;II)V
  #865 = NameAndType        #742:#672     // "<init>":()V
  #866 = Methodref          #5.#865       // java/lang/Object."<init>":()V
  #867 = Utf8               prefix1
  #868 = Utf8               ()[Ljava/lang/Object;
  #869 = NameAndType        #867:#868     // prefix1:()[Ljava/lang/Object;
  #870 = Methodref          #695.#869     // scala/collection/immutable/Vector.prefix1:()[Ljava/lang/Object;
  #871 = Utf8               Signature
  #872 = Utf8               Code
  #873 = Utf8               LineNumberTable
  #874 = Utf8               LocalVariableTable
  #875 = Utf8               Deprecated
  #876 = Utf8               MethodParameters
  #877 = Utf8               StackMapTable
  #878 = Utf8               InnerClasses
  #879 = Utf8               SourceFile
  #880 = Utf8               RuntimeVisibleAnnotations
  #881 = Utf8               ScalaInlineInfo
  #882 = Utf8               ScalaSig
{
  private final scala.collection.immutable.Vector<A> v;
    descriptor: Lscala/collection/immutable/Vector;
    flags: (0x0012) ACC_PRIVATE, ACC_FINAL
    Signature: #19                          // Lscala/collection/immutable/Vector<TA;>;

  private int totalLength;
    descriptor: I
    flags: (0x0002) ACC_PRIVATE

  private final int sliceCount;
    descriptor: I
    flags: (0x0012) ACC_PRIVATE, ACC_FINAL

  private java.lang.Object[] a1;
    descriptor: [Ljava/lang/Object;
    flags: (0x0002) ACC_PRIVATE

  private java.lang.Object[][] a2;
    descriptor: [[Ljava/lang/Object;
    flags: (0x0002) ACC_PRIVATE

  private java.lang.Object[][][] a3;
    descriptor: [[[Ljava/lang/Object;
    flags: (0x0002) ACC_PRIVATE

  private java.lang.Object[][][][] a4;
    descriptor: [[[[Ljava/lang/Object;
    flags: (0x0002) ACC_PRIVATE

  private java.lang.Object[][][][][] a5;
    descriptor: [[[[[Ljava/lang/Object;
    flags: (0x0002) ACC_PRIVATE

  private java.lang.Object[][][][][][] a6;
    descriptor: [[[[[[Ljava/lang/Object;
    flags: (0x0002) ACC_PRIVATE

  private int a1len;
    descriptor: I
    flags: (0x0002) ACC_PRIVATE

  public int scala$collection$immutable$NewVectorIterator$$i1;
    descriptor: I
    flags: (0x0001) ACC_PUBLIC

  private int oldPos;
    descriptor: I
    flags: (0x0002) ACC_PRIVATE

  public int scala$collection$immutable$NewVectorIterator$$len1;
    descriptor: I
    flags: (0x0001) ACC_PUBLIC

  private int sliceIdx;
    descriptor: I
    flags: (0x0002) ACC_PRIVATE

  private int sliceDim;
    descriptor: I
    flags: (0x0002) ACC_PRIVATE

  private int sliceStart;
    descriptor: I
    flags: (0x0002) ACC_PRIVATE

  private int sliceEnd;
    descriptor: I
    flags: (0x0002) ACC_PRIVATE

  public final boolean hasDefiniteSize();
    descriptor: ()Z
    flags: (0x0011) ACC_PUBLIC, ACC_FINAL
    Code:
      stack=1, locals=1, args_size=1
         0: aload_0
         1: invokestatic  #48                 // InterfaceMethod scala/collection/Iterator.hasDefiniteSize$:(Lscala/collection/Iterator;)Z
         4: ireturn
      LineNumberTable:
        line 1966: 0
      LocalVariableTable:
        Start  Length  Slot  Name   Signature
            0       5     0  this   Lscala/collection/immutable/NewVectorIterator;
    Deprecated: true

  public final scala.collection.Iterator<A> iterator();
    descriptor: ()Lscala/collection/Iterator;
    flags: (0x0011) ACC_PUBLIC, ACC_FINAL
    Code:
      stack=1, locals=1, args_size=1
         0: aload_0
         1: invokestatic  #57                 // InterfaceMethod scala/collection/Iterator.iterator$:(Lscala/collection/Iterator;)Lscala/collection/Iterator;
         4: areturn
      LineNumberTable:
        line 1966: 0
      LocalVariableTable:
        Start  Length  Slot  Name   Signature
            0       5     0  this   Lscala/collection/immutable/NewVectorIterator;
    Signature: #53                          // ()Lscala/collection/Iterator<TA;>;

  public scala.Option<A> nextOption();
    descriptor: ()Lscala/Option;
    flags: (0x0001) ACC_PUBLIC
    Code:
      stack=1, locals=1, args_size=1
         0: aload_0
         1: invokestatic  #64                 // InterfaceMethod scala/collection/Iterator.nextOption$:(Lscala/collection/Iterator;)Lscala/Option;
         4: areturn
      LineNumberTable:
        line 1966: 0
      LocalVariableTable:
        Start  Length  Slot  Name   Signature
            0       5     0  this   Lscala/collection/immutable/NewVectorIterator;
    Signature: #60                          // ()Lscala/Option<TA;>;

  public boolean contains(java.lang.Object);
    descriptor: (Ljava/lang/Object;)Z
    flags: (0x0001) ACC_PUBLIC
    Code:
      stack=2, locals=2, args_size=2
         0: aload_0
         1: aload_1
         2: invokestatic  #71                 // InterfaceMethod scala/collection/Iterator.contains$:(Lscala/collection/Iterator;Ljava/lang/Object;)Z
         5: ireturn
      LineNumberTable:
        line 1966: 0
      LocalVariableTable:
        Start  Length  Slot  Name   Signature
            0       6     0  this   Lscala/collection/immutable/NewVectorIterator;
            0       6     1  elem   Ljava/lang/Object;
    MethodParameters:
      Name                           Flags
      elem                           final

  public scala.collection.BufferedIterator<A> buffered();
    descriptor: ()Lscala/collection/BufferedIterator;
    flags: (0x0001) ACC_PUBLIC
    Code:
      stack=1, locals=1, args_size=1
         0: aload_0
         1: invokestatic  #79                 // InterfaceMethod scala/collection/Iterator.buffered$:(Lscala/collection/Iterator;)Lscala/collection/BufferedIterator;
         4: areturn
      LineNumberTable:
        line 1966: 0
      LocalVariableTable:
        Start  Length  Slot  Name   Signature
            0       5     0  this   Lscala/collection/immutable/NewVectorIterator;
    Signature: #75                          // ()Lscala/collection/BufferedIterator<TA;>;

  public <B extends java.lang.Object> scala.collection.Iterator<B> padTo(int, B);
    descriptor: (ILjava/lang/Object;)Lscala/collection/Iterator;
    flags: (0x0001) ACC_PUBLIC
    Code:
      stack=3, locals=3, args_size=3
         0: aload_0
         1: iload_1
         2: aload_2
         3: invokestatic  #87                 // InterfaceMethod scala/collection/Iterator.padTo$:(Lscala/collection/Iterator;ILjava/lang/Object;)Lscala/collection/Iterator;
         6: areturn
      LineNumberTable:
        line 1966: 0
      LocalVariableTable:
        Start  Length  Slot  Name   Signature
            0       7     0  this   Lscala/collection/immutable/NewVectorIterator;
            0       7     1   len   I
            0       7     2  elem   Ljava/lang/Object;
    Signature: #82                          // <B:Ljava/lang/Object;>(ITB;)Lscala/collection/Iterator<TB;>;
    MethodParameters:
      Name                           Flags
      len                            final
      elem                           final

  public scala.Tuple2<scala.collection.Iterator<A>, scala.collection.Iterator<A>> partition(scala.Function1<A, java.lang.Object>);
    descriptor: (Lscala/Function1;)Lscala/Tuple2;
    flags: (0x0001) ACC_PUBLIC
    Code:
      stack=2, locals=2, args_size=2
         0: aload_0
         1: aload_1
         2: invokestatic  #95                 // InterfaceMethod scala/collection/Iterator.partition$:(Lscala/collection/Iterator;Lscala/Function1;)Lscala/Tuple2;
         5: areturn
      LineNumberTable:
        line 1966: 0
      LocalVariableTable:
        Start  Length  Slot  Name   Signature
            0       6     0  this   Lscala/collection/immutable/NewVectorIterator;
            0       6     1     p   Lscala/Function1;
    Signature: #90                          // (Lscala/Function1<TA;Ljava/lang/Object;>;)Lscala/Tuple2<Lscala/collection/Iterator<TA;>;Lscala/collection/Iterator<TA;>;>;
    MethodParameters:
      Name                           Flags
      p                              final

  public <B extends java.lang.Object> scala.collection.Iterator<A>.GroupedIterator<B> grouped(int);
    descriptor: (I)Lscala/collection/Iterator$GroupedIterator;
    flags: (0x0001) ACC_PUBLIC
    Code:
      stack=2, locals=2, args_size=2
         0: aload_0
         1: iload_1
         2: invokestatic  #104                // InterfaceMethod scala/collection/Iterator.grouped$:(Lscala/collection/Iterator;I)Lscala/collection/Iterator$GroupedIterator;
         5: areturn
      LineNumberTable:
        line 1966: 0
      LocalVariableTable:
        Start  Length  Slot  Name   Signature
            0       6     0  this   Lscala/collection/immutable/NewVectorIterator;
            0       6     1  size   I
    Signature: #99                          // <B:Ljava/lang/Object;>(I)Lscala/collection/Iterator<TA;>.GroupedIterator<TB;>;
    MethodParameters:
      Name                           Flags
      size                           final

  public <B extends java.lang.Object> scala.collection.Iterator<A>.GroupedIterator<B> sliding(int, int);
    descriptor: (II)Lscala/collection/Iterator$GroupedIterator;
    flags: (0x0001) ACC_PUBLIC
    Code:
      stack=3, locals=3, args_size=3
         0: aload_0
         1: iload_1
         2: iload_2
         3: invokestatic  #112                // InterfaceMethod scala/collection/Iterator.sliding$:(Lscala/collection/Iterator;II)Lscala/collection/Iterator$GroupedIterator;
         6: areturn
      LineNumberTable:
        line 1966: 0
      LocalVariableTable:
        Start  Length  Slot  Name   Signature
            0       7     0  this   Lscala/collection/immutable/NewVectorIterator;
            0       7     1  size   I
            0       7     2  step   I
    Signature: #107                         // <B:Ljava/lang/Object;>(II)Lscala/collection/Iterator<TA;>.GroupedIterator<TB;>;
    MethodParameters:
      Name                           Flags
      size                           final
      step                           final

  public <B extends java.lang.Object> int sliding$default$2();
    descriptor: ()I
    flags: (0x0001) ACC_PUBLIC
    Code:
      stack=1, locals=1, args_size=1
         0: aload_0
         1: invokestatic  #119                // InterfaceMethod scala/collection/Iterator.sliding$default$2$:(Lscala/collection/Iterator;)I
         4: ireturn
      LineNumberTable:
        line 1966: 0
      LocalVariableTable:
        Start  Length  Slot  Name   Signature
            0       5     0  this   Lscala/collection/immutable/NewVectorIterator;
    Signature: #115                         // <B:Ljava/lang/Object;>()I

  public <B extends java.lang.Object> scala.collection.Iterator<B> scanLeft(B, scala.Function2<B, A, B>);
    descriptor: (Ljava/lang/Object;Lscala/Function2;)Lscala/collection/Iterator;
    flags: (0x0001) ACC_PUBLIC
    Code:
      stack=3, locals=3, args_size=3
         0: aload_0
         1: aload_1
         2: aload_2
         3: invokestatic  #128                // InterfaceMethod scala/collection/Iterator.scanLeft$:(Lscala/collection/Iterator;Ljava/lang/Object;Lscala/Function2;)Lscala/collection/Iterator;
         6: areturn
      LineNumberTable:
        line 1966: 0
      LocalVariableTable:
        Start  Length  Slot  Name   Signature
            0       7     0  this   Lscala/collection/immutable/NewVectorIterator;
            0       7     1     z   Ljava/lang/Object;
            0       7     2    op   Lscala/Function2;
    Signature: #122                         // <B:Ljava/lang/Object;>(TB;Lscala/Function2<TB;TA;TB;>;)Lscala/collection/Iterator<TB;>;
    MethodParameters:
      Name                           Flags
      z                              final
      op                             final

  public <B extends java.lang.Object> scala.collection.Iterator<B> scanRight(B, scala.Function2<A, B, B>);
    descriptor: (Ljava/lang/Object;Lscala/Function2;)Lscala/collection/Iterator;
    flags: (0x0001) ACC_PUBLIC
    Code:
      stack=3, locals=3, args_size=3
         0: aload_0
         1: aload_1
         2: aload_2
         3: invokestatic  #134                // InterfaceMethod scala/collection/Iterator.scanRight$:(Lscala/collection/Iterator;Ljava/lang/Object;Lscala/Function2;)Lscala/collection/Iterator;
         6: areturn
      LineNumberTable:
        line 1966: 0
      LocalVariableTable:
        Start  Length  Slot  Name   Signature
            0       7     0  this   Lscala/collection/immutable/NewVectorIterator;
            0       7     1     z   Ljava/lang/Object;
            0       7     2    op   Lscala/Function2;
    Signature: #131                         // <B:Ljava/lang/Object;>(TB;Lscala/Function2<TA;TB;TB;>;)Lscala/collection/Iterator<TB;>;
    Deprecated: true
    MethodParameters:
      Name                           Flags
      z                              final
      op                             final

  public int indexWhere(scala.Function1<A, java.lang.Object>, int);
    descriptor: (Lscala/Function1;I)I
    flags: (0x0001) ACC_PUBLIC
    Code:
      stack=3, locals=3, args_size=3
         0: aload_0
         1: aload_1
         2: iload_2
         3: invokestatic  #142                // InterfaceMethod scala/collection/Iterator.indexWhere$:(Lscala/collection/Iterator;Lscala/Function1;I)I
         6: ireturn
      LineNumberTable:
        line 1966: 0
      LocalVariableTable:
        Start  Length  Slot  Name   Signature
            0       7     0  this   Lscala/collection/immutable/NewVectorIterator;
            0       7     1     p   Lscala/Function1;
            0       7     2  from   I
    Signature: #137                         // (Lscala/Function1<TA;Ljava/lang/Object;>;I)I
    MethodParameters:
      Name                           Flags
      p                              final
      from                           final

  public int indexWhere$default$2();
    descriptor: ()I
    flags: (0x0001) ACC_PUBLIC
    Code:
      stack=1, locals=1, args_size=1
         0: aload_0
         1: invokestatic  #146                // InterfaceMethod scala/collection/Iterator.indexWhere$default$2$:(Lscala/collection/Iterator;)I
         4: ireturn
      LineNumberTable:
        line 1966: 0
      LocalVariableTable:
        Start  Length  Slot  Name   Signature
            0       5     0  this   Lscala/collection/immutable/NewVectorIterator;

  public <B extends java.lang.Object> int indexOf(B);
    descriptor: (Ljava/lang/Object;)I
    flags: (0x0001) ACC_PUBLIC
    Code:
      stack=2, locals=2, args_size=2
         0: aload_0
         1: aload_1
         2: invokestatic  #153                // InterfaceMethod scala/collection/Iterator.indexOf$:(Lscala/collection/Iterator;Ljava/lang/Object;)I
         5: ireturn
      LineNumberTable:
        line 1966: 0
      LocalVariableTable:
        Start  Length  Slot  Name   Signature
            0       6     0  this   Lscala/collection/immutable/NewVectorIterator;
            0       6     1  elem   Ljava/lang/Object;
    Signature: #149                         // <B:Ljava/lang/Object;>(TB;)I
    MethodParameters:
      Name                           Flags
      elem                           final

  public <B extends java.lang.Object> int indexOf(B, int);
    descriptor: (Ljava/lang/Object;I)I
    flags: (0x0001) ACC_PUBLIC
    Code:
      stack=3, locals=3, args_size=3
         0: aload_0
         1: aload_1
         2: iload_2
         3: invokestatic  #158                // InterfaceMethod scala/collection/Iterator.indexOf$:(Lscala/collection/Iterator;Ljava/lang/Object;I)I
         6: ireturn
      LineNumberTable:
        line 1966: 0
      LocalVariableTable:
        Start  Length  Slot  Name   Signature
            0       7     0  this   Lscala/collection/immutable/NewVectorIterator;
            0       7     1  elem   Ljava/lang/Object;
            0       7     2  from   I
    Signature: #155                         // <B:Ljava/lang/Object;>(TB;I)I
    MethodParameters:
      Name                           Flags
      elem                           final
      from                           final

  public final int length();
    descriptor: ()I
    flags: (0x0011) ACC_PUBLIC, ACC_FINAL
    Code:
      stack=1, locals=1, args_size=1
         0: aload_0
         1: invokestatic  #162                // InterfaceMethod scala/collection/Iterator.length$:(Lscala/collection/Iterator;)I
         4: ireturn
      LineNumberTable:
        line 1966: 0
      LocalVariableTable:
        Start  Length  Slot  Name   Signature
            0       5     0  this   Lscala/collection/immutable/NewVectorIterator;

  public boolean isEmpty();
    descriptor: ()Z
    flags: (0x0001) ACC_PUBLIC
    Code:
      stack=1, locals=1, args_size=1
         0: aload_0
         1: invokestatic  #166                // InterfaceMethod scala/collection/Iterator.isEmpty$:(Lscala/collection/Iterator;)Z
         4: ireturn
      LineNumberTable:
        line 1966: 0
      LocalVariableTable:
        Start  Length  Slot  Name   Signature
            0       5     0  this   Lscala/collection/immutable/NewVectorIterator;

  public scala.collection.Iterator<A> filter(scala.Function1<A, java.lang.Object>);
    descriptor: (Lscala/Function1;)Lscala/collection/Iterator;
    flags: (0x0001) ACC_PUBLIC
    Code:
      stack=2, locals=2, args_size=2
         0: aload_0
         1: aload_1
         2: invokestatic  #173                // InterfaceMethod scala/collection/Iterator.filter$:(Lscala/collection/Iterator;Lscala/Function1;)Lscala/collection/Iterator;
         5: areturn
      LineNumberTable:
        line 1966: 0
      LocalVariableTable:
        Start  Length  Slot  Name   Signature
            0       6     0  this   Lscala/collection/immutable/NewVectorIterator;
            0       6     1     p   Lscala/Function1;
    Signature: #169                         // (Lscala/Function1<TA;Ljava/lang/Object;>;)Lscala/collection/Iterator<TA;>;
    MethodParameters:
      Name                           Flags
      p                              final

  public scala.collection.Iterator<A> filterNot(scala.Function1<A, java.lang.Object>);
    descriptor: (Lscala/Function1;)Lscala/collection/Iterator;
    flags: (0x0001) ACC_PUBLIC
    Code:
      stack=2, locals=2, args_size=2
         0: aload_0
         1: aload_1
         2: invokestatic  #177                // InterfaceMethod scala/collection/Iterator.filterNot$:(Lscala/collection/Iterator;Lscala/Function1;)Lscala/collection/Iterator;
         5: areturn
      LineNumberTable:
        line 1966: 0
      LocalVariableTable:
        Start  Length  Slot  Name   Signature
            0       6     0  this   Lscala/collection/immutable/NewVectorIterator;
            0       6     1     p   Lscala/Function1;
    Signature: #169                         // (Lscala/Function1<TA;Ljava/lang/Object;>;)Lscala/collection/Iterator<TA;>;
    MethodParameters:
      Name                           Flags
      p                              final

  public scala.collection.Iterator<A> filterImpl(scala.Function1<A, java.lang.Object>, boolean);
    descriptor: (Lscala/Function1;Z)Lscala/collection/Iterator;
    flags: (0x0001) ACC_PUBLIC
    Code:
      stack=3, locals=3, args_size=3
         0: aload_0
         1: aload_1
         2: iload_2
         3: invokestatic  #185                // InterfaceMethod scala/collection/Iterator.filterImpl$:(Lscala/collection/Iterator;Lscala/Function1;Z)Lscala/collection/Iterator;
         6: areturn
      LineNumberTable:
        line 1966: 0
      LocalVariableTable:
        Start  Length  Slot  Name   Signature
            0       7     0  this   Lscala/collection/immutable/NewVectorIterator;
            0       7     1     p   Lscala/Function1;
            0       7     2 isFlipped   Z
    Signature: #180                         // (Lscala/Function1<TA;Ljava/lang/Object;>;Z)Lscala/collection/Iterator<TA;>;
    MethodParameters:
      Name                           Flags
      p                              final
      isFlipped                      final

  public scala.collection.Iterator<A> withFilter(scala.Function1<A, java.lang.Object>);
    descriptor: (Lscala/Function1;)Lscala/collection/Iterator;
    flags: (0x0001) ACC_PUBLIC
    Code:
      stack=2, locals=2, args_size=2
         0: aload_0
         1: aload_1
         2: invokestatic  #190                // InterfaceMethod scala/collection/Iterator.withFilter$:(Lscala/collection/Iterator;Lscala/Function1;)Lscala/collection/Iterator;
         5: areturn
      LineNumberTable:
        line 1966: 0
      LocalVariableTable:
        Start  Length  Slot  Name   Signature
            0       6     0  this   Lscala/collection/immutable/NewVectorIterator;
            0       6     1     p   Lscala/Function1;
    Signature: #169                         // (Lscala/Function1<TA;Ljava/lang/Object;>;)Lscala/collection/Iterator<TA;>;
    MethodParameters:
      Name                           Flags
      p                              final

  public <B extends java.lang.Object> scala.collection.Iterator<B> collect(scala.PartialFunction<A, B>);
    descriptor: (Lscala/PartialFunction;)Lscala/collection/Iterator;
    flags: (0x0001) ACC_PUBLIC
    Code:
      stack=2, locals=2, args_size=2
         0: aload_0
         1: aload_1
         2: invokestatic  #198                // InterfaceMethod scala/collection/Iterator.collect$:(Lscala/collection/Iterator;Lscala/PartialFunction;)Lscala/collection/Iterator;
         5: areturn
      LineNumberTable:
        line 1966: 0
      LocalVariableTable:
        Start  Length  Slot  Name   Signature
            0       6     0  this   Lscala/collection/immutable/NewVectorIterator;
            0       6     1    pf   Lscala/PartialFunction;
    Signature: #193                         // <B:Ljava/lang/Object;>(Lscala/PartialFunction<TA;TB;>;)Lscala/collection/Iterator<TB;>;
    MethodParameters:
      Name                           Flags
      pf                             final

  public scala.collection.Iterator<A> distinct();
    descriptor: ()Lscala/collection/Iterator;
    flags: (0x0001) ACC_PUBLIC
    Code:
      stack=1, locals=1, args_size=1
         0: aload_0
         1: invokestatic  #203                // InterfaceMethod scala/collection/Iterator.distinct$:(Lscala/collection/Iterator;)Lscala/collection/Iterator;
         4: areturn
      LineNumberTable:
        line 1966: 0
      LocalVariableTable:
        Start  Length  Slot  Name   Signature
            0       5     0  this   Lscala/collection/immutable/NewVectorIterator;
    Signature: #53                          // ()Lscala/collection/Iterator<TA;>;

  public <B extends java.lang.Object> scala.collection.Iterator<A> distinctBy(scala.Function1<A, B>);
    descriptor: (Lscala/Function1;)Lscala/collection/Iterator;
    flags: (0x0001) ACC_PUBLIC
    Code:
      stack=2, locals=2, args_size=2
         0: aload_0
         1: aload_1
         2: invokestatic  #209                // InterfaceMethod scala/collection/Iterator.distinctBy$:(Lscala/collection/Iterator;Lscala/Function1;)Lscala/collection/Iterator;
         5: areturn
      LineNumberTable:
        line 1966: 0
      LocalVariableTable:
        Start  Length  Slot  Name   Signature
            0       6     0  this   Lscala/collection/immutable/NewVectorIterator;
            0       6     1     f   Lscala/Function1;
    Signature: #205                         // <B:Ljava/lang/Object;>(Lscala/Function1<TA;TB;>;)Lscala/collection/Iterator<TA;>;
    MethodParameters:
      Name                           Flags
      f                              final

  public <B extends java.lang.Object> scala.collection.Iterator<B> map(scala.Function1<A, B>);
    descriptor: (Lscala/Function1;)Lscala/collection/Iterator;
    flags: (0x0001) ACC_PUBLIC
    Code:
      stack=2, locals=2, args_size=2
         0: aload_0
         1: aload_1
         2: invokestatic  #214                // InterfaceMethod scala/collection/Iterator.map$:(Lscala/collection/Iterator;Lscala/Function1;)Lscala/collection/Iterator;
         5: areturn
      LineNumberTable:
        line 1966: 0
      LocalVariableTable:
        Start  Length  Slot  Name   Signature
            0       6     0  this   Lscala/collection/immutable/NewVectorIterator;
            0       6     1     f   Lscala/Function1;
    Signature: #211                         // <B:Ljava/lang/Object;>(Lscala/Function1<TA;TB;>;)Lscala/collection/Iterator<TB;>;
    MethodParameters:
      Name                           Flags
      f                              final

  public <B extends java.lang.Object> scala.collection.Iterator<B> flatMap(scala.Function1<A, scala.collection.IterableOnce<B>>);
    descriptor: (Lscala/Function1;)Lscala/collection/Iterator;
    flags: (0x0001) ACC_PUBLIC
    Code:
      stack=2, locals=2, args_size=2
         0: aload_0
         1: aload_1
         2: invokestatic  #219                // InterfaceMethod scala/collection/Iterator.flatMap$:(Lscala/collection/Iterator;Lscala/Function1;)Lscala/collection/Iterator;
         5: areturn
      LineNumberTable:
        line 1966: 0
      LocalVariableTable:
        Start  Length  Slot  Name   Signature
            0       6     0  this   Lscala/collection/immutable/NewVectorIterator;
            0       6     1     f   Lscala/Function1;
    Signature: #216                         // <B:Ljava/lang/Object;>(Lscala/Function1<TA;Lscala/collection/IterableOnce<TB;>;>;)Lscala/collection/Iterator<TB;>;
    MethodParameters:
      Name                           Flags
      f                              final

  public <B extends java.lang.Object> scala.collection.Iterator<B> flatten(scala.Function1<A, scala.collection.IterableOnce<B>>);
    descriptor: (Lscala/Function1;)Lscala/collection/Iterator;
    flags: (0x0001) ACC_PUBLIC
    Code:
      stack=2, locals=2, args_size=2
         0: aload_0
         1: aload_1
         2: invokestatic  #224                // InterfaceMethod scala/collection/Iterator.flatten$:(Lscala/collection/Iterator;Lscala/Function1;)Lscala/collection/Iterator;
         5: areturn
      LineNumberTable:
        line 1966: 0
      LocalVariableTable:
        Start  Length  Slot  Name   Signature
            0       6     0  this   Lscala/collection/immutable/NewVectorIterator;
            0       6     1    ev   Lscala/Function1;
    Signature: #216                         // <B:Ljava/lang/Object;>(Lscala/Function1<TA;Lscala/collection/IterableOnce<TB;>;>;)Lscala/collection/Iterator<TB;>;
    MethodParameters:
      Name                           Flags
      ev                             final

  public <B extends java.lang.Object> scala.collection.Iterator<B> concat(scala.Function0<scala.collection.IterableOnce<B>>);
    descriptor: (Lscala/Function0;)Lscala/collection/Iterator;
    flags: (0x0001) ACC_PUBLIC
    Code:
      stack=2, locals=2, args_size=2
         0: aload_0
         1: aload_1
         2: invokestatic  #232                // InterfaceMethod scala/collection/Iterator.concat$:(Lscala/collection/Iterator;Lscala/Function0;)Lscala/collection/Iterator;
         5: areturn
      LineNumberTable:
        line 1966: 0
      LocalVariableTable:
        Start  Length  Slot  Name   Signature
            0       6     0  this   Lscala/collection/immutable/NewVectorIterator;
            0       6     1    xs   Lscala/Function0;
    Signature: #227                         // <B:Ljava/lang/Object;>(Lscala/Function0<Lscala/collection/IterableOnce<TB;>;>;)Lscala/collection/Iterator<TB;>;
    MethodParameters:
      Name                           Flags
      xs                             final

  public final <B extends java.lang.Object> scala.collection.Iterator<B> $plus$plus(scala.Function0<scala.collection.IterableOnce<B>>);
    descriptor: (Lscala/Function0;)Lscala/collection/Iterator;
    flags: (0x0011) ACC_PUBLIC, ACC_FINAL
    Code:
      stack=2, locals=2, args_size=2
         0: aload_0
         1: aload_1
         2: invokestatic  #237                // InterfaceMethod scala/collection/Iterator.$plus$plus$:(Lscala/collection/Iterator;Lscala/Function0;)Lscala/collection/Iterator;
         5: areturn
      LineNumberTable:
        line 1966: 0
      LocalVariableTable:
        Start  Length  Slot  Name   Signature
            0       6     0  this   Lscala/collection/immutable/NewVectorIterator;
            0       6     1    xs   Lscala/Function0;
    Signature: #227                         // <B:Ljava/lang/Object;>(Lscala/Function0<Lscala/collection/IterableOnce<TB;>;>;)Lscala/collection/Iterator<TB;>;
    MethodParameters:
      Name                           Flags
      xs                             final

  public scala.collection.Iterator<A> takeWhile(scala.Function1<A, java.lang.Object>);
    descriptor: (Lscala/Function1;)Lscala/collection/Iterator;
    flags: (0x0001) ACC_PUBLIC
    Code:
      stack=2, locals=2, args_size=2
         0: aload_0
         1: aload_1
         2: invokestatic  #241                // InterfaceMethod scala/collection/Iterator.takeWhile$:(Lscala/collection/Iterator;Lscala/Function1;)Lscala/collection/Iterator;
         5: areturn
      LineNumberTable:
        line 1966: 0
      LocalVariableTable:
        Start  Length  Slot  Name   Signature
            0       6     0  this   Lscala/collection/immutable/NewVectorIterator;
            0       6     1     p   Lscala/Function1;
    Signature: #169                         // (Lscala/Function1<TA;Ljava/lang/Object;>;)Lscala/collection/Iterator<TA;>;
    MethodParameters:
      Name                           Flags
      p                              final

  public scala.collection.Iterator<A> dropWhile(scala.Function1<A, java.lang.Object>);
    descriptor: (Lscala/Function1;)Lscala/collection/Iterator;
    flags: (0x0001) ACC_PUBLIC
    Code:
      stack=2, locals=2, args_size=2
         0: aload_0
         1: aload_1
         2: invokestatic  #245                // InterfaceMethod scala/collection/Iterator.dropWhile$:(Lscala/collection/Iterator;Lscala/Function1;)Lscala/collection/Iterator;
         5: areturn
      LineNumberTable:
        line 1966: 0
      LocalVariableTable:
        Start  Length  Slot  Name   Signature
            0       6     0  this   Lscala/collection/immutable/NewVectorIterator;
            0       6     1     p   Lscala/Function1;
    Signature: #169                         // (Lscala/Function1<TA;Ljava/lang/Object;>;)Lscala/collection/Iterator<TA;>;
    MethodParameters:
      Name                           Flags
      p                              final

  public scala.Tuple2<scala.collection.Iterator<A>, scala.collection.Iterator<A>> span(scala.Function1<A, java.lang.Object>);
    descriptor: (Lscala/Function1;)Lscala/Tuple2;
    flags: (0x0001) ACC_PUBLIC
    Code:
      stack=2, locals=2, args_size=2
         0: aload_0
         1: aload_1
         2: invokestatic  #249                // InterfaceMethod scala/collection/Iterator.span$:(Lscala/collection/Iterator;Lscala/Function1;)Lscala/Tuple2;
         5: areturn
      LineNumberTable:
        line 1966: 0
      LocalVariableTable:
        Start  Length  Slot  Name   Signature
            0       6     0  this   Lscala/collection/immutable/NewVectorIterator;
            0       6     1     p   Lscala/Function1;
    Signature: #90                          // (Lscala/Function1<TA;Ljava/lang/Object;>;)Lscala/Tuple2<Lscala/collection/Iterator<TA;>;Lscala/collection/Iterator<TA;>;>;
    MethodParameters:
      Name                           Flags
      p                              final

  public scala.collection.Iterator<A> sliceIterator(int, int);
    descriptor: (II)Lscala/collection/Iterator;
    flags: (0x0001) ACC_PUBLIC
    Code:
      stack=3, locals=3, args_size=3
         0: aload_0
         1: iload_1
         2: iload_2
         3: invokestatic  #257                // InterfaceMethod scala/collection/Iterator.sliceIterator$:(Lscala/collection/Iterator;II)Lscala/collection/Iterator;
         6: areturn
      LineNumberTable:
        line 1966: 0
      LocalVariableTable:
        Start  Length  Slot  Name   Signature
            0       7     0  this   Lscala/collection/immutable/NewVectorIterator;
            0       7     1  from   I
            0       7     2 until   I
    Signature: #252                         // (II)Lscala/collection/Iterator<TA;>;
    MethodParameters:
      Name                           Flags
      from                           final
      until                          final

  public <B extends java.lang.Object> scala.collection.Iterator<scala.Tuple2<A, B>> zip(scala.collection.IterableOnce<B>);
    descriptor: (Lscala/collection/IterableOnce;)Lscala/collection/Iterator;
    flags: (0x0001) ACC_PUBLIC
    Code:
      stack=2, locals=2, args_size=2
         0: aload_0
         1: aload_1
         2: invokestatic  #265                // InterfaceMethod scala/collection/Iterator.zip$:(Lscala/collection/Iterator;Lscala/collection/IterableOnce;)Lscala/collection/Iterator;
         5: areturn
      LineNumberTable:
        line 1966: 0
      LocalVariableTable:
        Start  Length  Slot  Name   Signature
            0       6     0  this   Lscala/collection/immutable/NewVectorIterator;
            0       6     1  that   Lscala/collection/IterableOnce;
    Signature: #260                         // <B:Ljava/lang/Object;>(Lscala/collection/IterableOnce<TB;>;)Lscala/collection/Iterator<Lscala/Tuple2<TA;TB;>;>;
    MethodParameters:
      Name                           Flags
      that                           final

  public <A1 extends java.lang.Object, B extends java.lang.Object> scala.collection.Iterator<scala.Tuple2<A1, B>> zipAll(scala.collection.IterableOnce<B>, A1, B);
    descriptor: (Lscala/collection/IterableOnce;Ljava/lang/Object;Ljava/lang/Object;)Lscala/collection/Iterator;
    flags: (0x0001) ACC_PUBLIC
    Code:
      stack=4, locals=4, args_size=4
         0: aload_0
         1: aload_1
         2: aload_2
         3: aload_3
         4: invokestatic  #275                // InterfaceMethod scala/collection/Iterator.zipAll$:(Lscala/collection/Iterator;Lscala/collection/IterableOnce;Ljava/lang/Object;Ljava/lang/Object;)Lscala/collection/Iterator;
         7: areturn
      LineNumberTable:
        line 1966: 0
      LocalVariableTable:
        Start  Length  Slot  Name   Signature
            0       8     0  this   Lscala/collection/immutable/NewVectorIterator;
            0       8     1  that   Lscala/collection/IterableOnce;
            0       8     2 thisElem   Ljava/lang/Object;
            0       8     3 thatElem   Ljava/lang/Object;
    Signature: #269                         // <A1:Ljava/lang/Object;B:Ljava/lang/Object;>(Lscala/collection/IterableOnce<TB;>;TA1;TB;)Lscala/collection/Iterator<Lscala/Tuple2<TA1;TB;>;>;
    MethodParameters:
      Name                           Flags
      that                           final
      thisElem                       final
      thatElem                       final

  public scala.collection.Iterator<scala.Tuple2<A, java.lang.Object>> zipWithIndex();
    descriptor: ()Lscala/collection/Iterator;
    flags: (0x0001) ACC_PUBLIC
    Code:
      stack=1, locals=1, args_size=1
         0: aload_0
         1: invokestatic  #280                // InterfaceMethod scala/collection/Iterator.zipWithIndex$:(Lscala/collection/Iterator;)Lscala/collection/Iterator;
         4: areturn
      LineNumberTable:
        line 1966: 0
      LocalVariableTable:
        Start  Length  Slot  Name   Signature
            0       5     0  this   Lscala/collection/immutable/NewVectorIterator;
    Signature: #277                         // ()Lscala/collection/Iterator<Lscala/Tuple2<TA;Ljava/lang/Object;>;>;

  public <B extends java.lang.Object> boolean sameElements(scala.collection.IterableOnce<B>);
    descriptor: (Lscala/collection/IterableOnce;)Z
    flags: (0x0001) ACC_PUBLIC
    Code:
      stack=2, locals=2, args_size=2
         0: aload_0
         1: aload_1
         2: invokestatic  #287                // InterfaceMethod scala/collection/Iterator.sameElements$:(Lscala/collection/Iterator;Lscala/collection/IterableOnce;)Z
         5: ireturn
      LineNumberTable:
        line 1966: 0
      LocalVariableTable:
        Start  Length  Slot  Name   Signature
            0       6     0  this   Lscala/collection/immutable/NewVectorIterator;
            0       6     1  that   Lscala/collection/IterableOnce;
    Signature: #283                         // <B:Ljava/lang/Object;>(Lscala/collection/IterableOnce<TB;>;)Z
    MethodParameters:
      Name                           Flags
      that                           final

  public scala.Tuple2<scala.collection.Iterator<A>, scala.collection.Iterator<A>> duplicate();
    descriptor: ()Lscala/Tuple2;
    flags: (0x0001) ACC_PUBLIC
    Code:
      stack=1, locals=1, args_size=1
         0: aload_0
         1: invokestatic  #294                // InterfaceMethod scala/collection/Iterator.duplicate$:(Lscala/collection/Iterator;)Lscala/Tuple2;
         4: areturn
      LineNumberTable:
        line 1966: 0
      LocalVariableTable:
        Start  Length  Slot  Name   Signature
            0       5     0  this   Lscala/collection/immutable/NewVectorIterator;
    Signature: #290                         // ()Lscala/Tuple2<Lscala/collection/Iterator<TA;>;Lscala/collection/Iterator<TA;>;>;

  public <B extends java.lang.Object> scala.collection.Iterator<B> patch(int, scala.collection.Iterator<B>, int);
    descriptor: (ILscala/collection/Iterator;I)Lscala/collection/Iterator;
    flags: (0x0001) ACC_PUBLIC
    Code:
      stack=4, locals=4, args_size=4
         0: aload_0
         1: iload_1
         2: aload_2
         3: iload_3
         4: invokestatic  #303                // InterfaceMethod scala/collection/Iterator.patch$:(Lscala/collection/Iterator;ILscala/collection/Iterator;I)Lscala/collection/Iterator;
         7: areturn
      LineNumberTable:
        line 1966: 0
      LocalVariableTable:
        Start  Length  Slot  Name   Signature
            0       8     0  this   Lscala/collection/immutable/NewVectorIterator;
            0       8     1  from   I
            0       8     2 patchElems   Lscala/collection/Iterator;
            0       8     3 replaced   I
    Signature: #297                         // <B:Ljava/lang/Object;>(ILscala/collection/Iterator<TB;>;I)Lscala/collection/Iterator<TB;>;
    MethodParameters:
      Name                           Flags
      from                           final
      patchElems                     final
      replaced                       final

  public <U extends java.lang.Object> scala.collection.Iterator<A> tapEach(scala.Function1<A, U>);
    descriptor: (Lscala/Function1;)Lscala/collection/Iterator;
    flags: (0x0001) ACC_PUBLIC
    Code:
      stack=2, locals=2, args_size=2
         0: aload_0
         1: aload_1
         2: invokestatic  #309                // InterfaceMethod scala/collection/Iterator.tapEach$:(Lscala/collection/Iterator;Lscala/Function1;)Lscala/collection/Iterator;
         5: areturn
      LineNumberTable:
        line 1966: 0
      LocalVariableTable:
        Start  Length  Slot  Name   Signature
            0       6     0  this   Lscala/collection/immutable/NewVectorIterator;
            0       6     1     f   Lscala/Function1;
    Signature: #306                         // <U:Ljava/lang/Object;>(Lscala/Function1<TA;TU;>;)Lscala/collection/Iterator<TA;>;
    MethodParameters:
      Name                           Flags
      f                              final

  public java.lang.String toString();
    descriptor: ()Ljava/lang/String;
    flags: (0x0001) ACC_PUBLIC
    Code:
      stack=1, locals=1, args_size=1
         0: aload_0
         1: invokestatic  #315                // InterfaceMethod scala/collection/Iterator.toString$:(Lscala/collection/Iterator;)Ljava/lang/String;
         4: areturn
      LineNumberTable:
        line 1966: 0
      LocalVariableTable:
        Start  Length  Slot  Name   Signature
            0       5     0  this   Lscala/collection/immutable/NewVectorIterator;

  public scala.collection.Iterator<A> seq();
    descriptor: ()Lscala/collection/Iterator;
    flags: (0x0001) ACC_PUBLIC
    Code:
      stack=1, locals=1, args_size=1
         0: aload_0
         1: invokestatic  #319                // InterfaceMethod scala/collection/Iterator.seq$:(Lscala/collection/Iterator;)Lscala/collection/Iterator;
         4: areturn
      LineNumberTable:
        line 1966: 0
      LocalVariableTable:
        Start  Length  Slot  Name   Signature
            0       5     0  this   Lscala/collection/immutable/NewVectorIterator;
    Signature: #53                          // ()Lscala/collection/Iterator<TA;>;
    Deprecated: true

  public scala.Tuple2<scala.collection.Iterator<A>, scala.collection.Iterator<A>> splitAt(int);
    descriptor: (I)Lscala/Tuple2;
    flags: (0x0001) ACC_PUBLIC
    Code:
      stack=2, locals=2, args_size=2
         0: aload_0
         1: iload_1
         2: invokestatic  #329                // InterfaceMethod scala/collection/IterableOnceOps.splitAt$:(Lscala/collection/IterableOnceOps;I)Lscala/Tuple2;
         5: areturn
      LineNumberTable:
        line 1966: 0
      LocalVariableTable:
        Start  Length  Slot  Name   Signature
            0       6     0  this   Lscala/collection/immutable/NewVectorIterator;
            0       6     1     n   I
    Signature: #322                         // (I)Lscala/Tuple2<Lscala/collection/Iterator<TA;>;Lscala/collection/Iterator<TA;>;>;
    MethodParameters:
      Name                           Flags
      n                              final

  public boolean isTraversableAgain();
    descriptor: ()Z
    flags: (0x0001) ACC_PUBLIC
    Code:
      stack=1, locals=1, args_size=1
         0: aload_0
         1: invokestatic  #334                // InterfaceMethod scala/collection/IterableOnceOps.isTraversableAgain$:(Lscala/collection/IterableOnceOps;)Z
         4: ireturn
      LineNumberTable:
        line 1966: 0
      LocalVariableTable:
        Start  Length  Slot  Name   Signature
            0       5     0  this   Lscala/collection/immutable/NewVectorIterator;

  public <U extends java.lang.Object> void foreach(scala.Function1<A, U>);
    descriptor: (Lscala/Function1;)V
    flags: (0x0001) ACC_PUBLIC
    Code:
      stack=2, locals=2, args_size=2
         0: aload_0
         1: aload_1
         2: invokestatic  #341                // InterfaceMethod scala/collection/IterableOnceOps.foreach$:(Lscala/collection/IterableOnceOps;Lscala/Function1;)V
         5: return
      LineNumberTable:
        line 1966: 0
      LocalVariableTable:
        Start  Length  Slot  Name   Signature
            0       6     0  this   Lscala/collection/immutable/NewVectorIterator;
            0       6     1     f   Lscala/Function1;
    Signature: #337                         // <U:Ljava/lang/Object;>(Lscala/Function1<TA;TU;>;)V
    MethodParameters:
      Name                           Flags
      f                              final

  public boolean forall(scala.Function1<A, java.lang.Object>);
    descriptor: (Lscala/Function1;)Z
    flags: (0x0001) ACC_PUBLIC
    Code:
      stack=2, locals=2, args_size=2
         0: aload_0
         1: aload_1
         2: invokestatic  #348                // InterfaceMethod scala/collection/IterableOnceOps.forall$:(Lscala/collection/IterableOnceOps;Lscala/Function1;)Z
         5: ireturn
      LineNumberTable:
        line 1966: 0
      LocalVariableTable:
        Start  Length  Slot  Name   Signature
            0       6     0  this   Lscala/collection/immutable/NewVectorIterator;
            0       6     1     p   Lscala/Function1;
    Signature: #344                         // (Lscala/Function1<TA;Ljava/lang/Object;>;)Z
    MethodParameters:
      Name                           Flags
      p                              final

  public boolean exists(scala.Function1<A, java.lang.Object>);
    descriptor: (Lscala/Function1;)Z
    flags: (0x0001) ACC_PUBLIC
    Code:
      stack=2, locals=2, args_size=2
         0: aload_0
         1: aload_1
         2: invokestatic  #352                // InterfaceMethod scala/collection/IterableOnceOps.exists$:(Lscala/collection/IterableOnceOps;Lscala/Function1;)Z
         5: ireturn
      LineNumberTable:
        line 1966: 0
      LocalVariableTable:
        Start  Length  Slot  Name   Signature
            0       6     0  this   Lscala/collection/immutable/NewVectorIterator;
            0       6     1     p   Lscala/Function1;
    Signature: #344                         // (Lscala/Function1<TA;Ljava/lang/Object;>;)Z
    MethodParameters:
      Name                           Flags
      p                              final

  public int count(scala.Function1<A, java.lang.Object>);
    descriptor: (Lscala/Function1;)I
    flags: (0x0001) ACC_PUBLIC
    Code:
      stack=2, locals=2, args_size=2
         0: aload_0
         1: aload_1
         2: invokestatic  #359                // InterfaceMethod scala/collection/IterableOnceOps.count$:(Lscala/collection/IterableOnceOps;Lscala/Function1;)I
         5: ireturn
      LineNumberTable:
        line 1966: 0
      LocalVariableTable:
        Start  Length  Slot  Name   Signature
            0       6     0  this   Lscala/collection/immutable/NewVectorIterator;
            0       6     1     p   Lscala/Function1;
    Signature: #355                         // (Lscala/Function1<TA;Ljava/lang/Object;>;)I
    MethodParameters:
      Name                           Flags
      p                              final

  public scala.Option<A> find(scala.Function1<A, java.lang.Object>);
    descriptor: (Lscala/Function1;)Lscala/Option;
    flags: (0x0001) ACC_PUBLIC
    Code:
      stack=2, locals=2, args_size=2
         0: aload_0
         1: aload_1
         2: invokestatic  #366                // InterfaceMethod scala/collection/IterableOnceOps.find$:(Lscala/collection/IterableOnceOps;Lscala/Function1;)Lscala/Option;
         5: areturn
      LineNumberTable:
        line 1966: 0
      LocalVariableTable:
        Start  Length  Slot  Name   Signature
            0       6     0  this   Lscala/collection/immutable/NewVectorIterator;
            0       6     1     p   Lscala/Function1;
    Signature: #362                         // (Lscala/Function1<TA;Ljava/lang/Object;>;)Lscala/Option<TA;>;
    MethodParameters:
      Name                           Flags
      p                              final

  public <B extends java.lang.Object> B foldLeft(B, scala.Function2<B, A, B>);
    descriptor: (Ljava/lang/Object;Lscala/Function2;)Ljava/lang/Object;
    flags: (0x0001) ACC_PUBLIC
    Code:
      stack=3, locals=3, args_size=3
         0: aload_0
         1: aload_1
         2: aload_2
         3: invokestatic  #373                // InterfaceMethod scala/collection/IterableOnceOps.foldLeft$:(Lscala/collection/IterableOnceOps;Ljava/lang/Object;Lscala/Function2;)Ljava/lang/Object;
         6: areturn
      LineNumberTable:
        line 1966: 0
      LocalVariableTable:
        Start  Length  Slot  Name   Signature
            0       7     0  this   Lscala/collection/immutable/NewVectorIterator;
            0       7     1     z   Ljava/lang/Object;
            0       7     2    op   Lscala/Function2;
    Signature: #369                         // <B:Ljava/lang/Object;>(TB;Lscala/Function2<TB;TA;TB;>;)TB;
    MethodParameters:
      Name                           Flags
      z                              final
      op                             final

  public <B extends java.lang.Object> B foldRight(B, scala.Function2<A, B, B>);
    descriptor: (Ljava/lang/Object;Lscala/Function2;)Ljava/lang/Object;
    flags: (0x0001) ACC_PUBLIC
    Code:
      stack=3, locals=3, args_size=3
         0: aload_0
         1: aload_1
         2: aload_2
         3: invokestatic  #378                // InterfaceMethod scala/collection/IterableOnceOps.foldRight$:(Lscala/collection/IterableOnceOps;Ljava/lang/Object;Lscala/Function2;)Ljava/lang/Object;
         6: areturn
      LineNumberTable:
        line 1966: 0
      LocalVariableTable:
        Start  Length  Slot  Name   Signature
            0       7     0  this   Lscala/collection/immutable/NewVectorIterator;
            0       7     1     z   Ljava/lang/Object;
            0       7     2    op   Lscala/Function2;
    Signature: #375                         // <B:Ljava/lang/Object;>(TB;Lscala/Function2<TA;TB;TB;>;)TB;
    MethodParameters:
      Name                           Flags
      z                              final
      op                             final

  public final <B extends java.lang.Object> B $div$colon(B, scala.Function2<B, A, B>);
    descriptor: (Ljava/lang/Object;Lscala/Function2;)Ljava/lang/Object;
    flags: (0x0011) ACC_PUBLIC, ACC_FINAL
    Code:
      stack=3, locals=3, args_size=3
         0: aload_0
         1: aload_1
         2: aload_2
         3: invokestatic  #382                // InterfaceMethod scala/collection/IterableOnceOps.$div$colon$:(Lscala/collection/IterableOnceOps;Ljava/lang/Object;Lscala/Function2;)Ljava/lang/Object;
         6: areturn
      LineNumberTable:
        line 1966: 0
      LocalVariableTable:
        Start  Length  Slot  Name   Signature
            0       7     0  this   Lscala/collection/immutable/NewVectorIterator;
            0       7     1     z   Ljava/lang/Object;
            0       7     2    op   Lscala/Function2;
    Signature: #369                         // <B:Ljava/lang/Object;>(TB;Lscala/Function2<TB;TA;TB;>;)TB;
    Deprecated: true
    MethodParameters:
      Name                           Flags
      z                              final
      op                             final

  public final <B extends java.lang.Object> B $colon$bslash(B, scala.Function2<A, B, B>);
    descriptor: (Ljava/lang/Object;Lscala/Function2;)Ljava/lang/Object;
    flags: (0x0011) ACC_PUBLIC, ACC_FINAL
    Code:
      stack=3, locals=3, args_size=3
         0: aload_0
         1: aload_1
         2: aload_2
         3: invokestatic  #386                // InterfaceMethod scala/collection/IterableOnceOps.$colon$bslash$:(Lscala/collection/IterableOnceOps;Ljava/lang/Object;Lscala/Function2;)Ljava/lang/Object;
         6: areturn
      LineNumberTable:
        line 1966: 0
      LocalVariableTable:
        Start  Length  Slot  Name   Signature
            0       7     0  this   Lscala/collection/immutable/NewVectorIterator;
            0       7     1     z   Ljava/lang/Object;
            0       7     2    op   Lscala/Function2;
    Signature: #375                         // <B:Ljava/lang/Object;>(TB;Lscala/Function2<TA;TB;TB;>;)TB;
    Deprecated: true
    MethodParameters:
      Name                           Flags
      z                              final
      op                             final

  public <A1 extends java.lang.Object> A1 fold(A1, scala.Function2<A1, A1, A1>);
    descriptor: (Ljava/lang/Object;Lscala/Function2;)Ljava/lang/Object;
    flags: (0x0001) ACC_PUBLIC
    Code:
      stack=3, locals=3, args_size=3
         0: aload_0
         1: aload_1
         2: aload_2
         3: invokestatic  #391                // InterfaceMethod scala/collection/IterableOnceOps.fold$:(Lscala/collection/IterableOnceOps;Ljava/lang/Object;Lscala/Function2;)Ljava/lang/Object;
         6: areturn
      LineNumberTable:
        line 1966: 0
      LocalVariableTable:
        Start  Length  Slot  Name   Signature
            0       7     0  this   Lscala/collection/immutable/NewVectorIterator;
            0       7     1     z   Ljava/lang/Object;
            0       7     2    op   Lscala/Function2;
    Signature: #388                         // <A1:Ljava/lang/Object;>(TA1;Lscala/Function2<TA1;TA1;TA1;>;)TA1;
    MethodParameters:
      Name                           Flags
      z                              final
      op                             final

  public <B extends java.lang.Object> B reduce(scala.Function2<B, B, B>);
    descriptor: (Lscala/Function2;)Ljava/lang/Object;
    flags: (0x0001) ACC_PUBLIC
    Code:
      stack=2, locals=2, args_size=2
         0: aload_0
         1: aload_1
         2: invokestatic  #398                // InterfaceMethod scala/collection/IterableOnceOps.reduce$:(Lscala/collection/IterableOnceOps;Lscala/Function2;)Ljava/lang/Object;
         5: areturn
      LineNumberTable:
        line 1966: 0
      LocalVariableTable:
        Start  Length  Slot  Name   Signature
            0       6     0  this   Lscala/collection/immutable/NewVectorIterator;
            0       6     1    op   Lscala/Function2;
    Signature: #394                         // <B:Ljava/lang/Object;>(Lscala/Function2<TB;TB;TB;>;)TB;
    MethodParameters:
      Name                           Flags
      op                             final

  public <B extends java.lang.Object> scala.Option<B> reduceOption(scala.Function2<B, B, B>);
    descriptor: (Lscala/Function2;)Lscala/Option;
    flags: (0x0001) ACC_PUBLIC
    Code:
      stack=2, locals=2, args_size=2
         0: aload_0
         1: aload_1
         2: invokestatic  #405                // InterfaceMethod scala/collection/IterableOnceOps.reduceOption$:(Lscala/collection/IterableOnceOps;Lscala/Function2;)Lscala/Option;
         5: areturn
      LineNumberTable:
        line 1966: 0
      LocalVariableTable:
        Start  Length  Slot  Name   Signature
            0       6     0  this   Lscala/collection/immutable/NewVectorIterator;
            0       6     1    op   Lscala/Function2;
    Signature: #401                         // <B:Ljava/lang/Object;>(Lscala/Function2<TB;TB;TB;>;)Lscala/Option<TB;>;
    MethodParameters:
      Name                           Flags
      op                             final

  public <B extends java.lang.Object> B reduceLeft(scala.Function2<B, A, B>);
    descriptor: (Lscala/Function2;)Ljava/lang/Object;
    flags: (0x0001) ACC_PUBLIC
    Code:
      stack=2, locals=2, args_size=2
         0: aload_0
         1: aload_1
         2: invokestatic  #410                // InterfaceMethod scala/collection/IterableOnceOps.reduceLeft$:(Lscala/collection/IterableOnceOps;Lscala/Function2;)Ljava/lang/Object;
         5: areturn
      LineNumberTable:
        line 1966: 0
      LocalVariableTable:
        Start  Length  Slot  Name   Signature
            0       6     0  this   Lscala/collection/immutable/NewVectorIterator;
            0       6     1    op   Lscala/Function2;
    Signature: #407                         // <B:Ljava/lang/Object;>(Lscala/Function2<TB;TA;TB;>;)TB;
    MethodParameters:
      Name                           Flags
      op                             final

  public <B extends java.lang.Object> B reduceRight(scala.Function2<A, B, B>);
    descriptor: (Lscala/Function2;)Ljava/lang/Object;
    flags: (0x0001) ACC_PUBLIC
    Code:
      stack=2, locals=2, args_size=2
         0: aload_0
         1: aload_1
         2: invokestatic  #415                // InterfaceMethod scala/collection/IterableOnceOps.reduceRight$:(Lscala/collection/IterableOnceOps;Lscala/Function2;)Ljava/lang/Object;
         5: areturn
      LineNumberTable:
        line 1966: 0
      LocalVariableTable:
        Start  Length  Slot  Name   Signature
            0       6     0  this   Lscala/collection/immutable/NewVectorIterator;
            0       6     1    op   Lscala/Function2;
    Signature: #412                         // <B:Ljava/lang/Object;>(Lscala/Function2<TA;TB;TB;>;)TB;
    MethodParameters:
      Name                           Flags
      op                             final

  public <B extends java.lang.Object> scala.Option<B> reduceLeftOption(scala.Function2<B, A, B>);
    descriptor: (Lscala/Function2;)Lscala/Option;
    flags: (0x0001) ACC_PUBLIC
    Code:
      stack=2, locals=2, args_size=2
         0: aload_0
         1: aload_1
         2: invokestatic  #420                // InterfaceMethod scala/collection/IterableOnceOps.reduceLeftOption$:(Lscala/collection/IterableOnceOps;Lscala/Function2;)Lscala/Option;
         5: areturn
      LineNumberTable:
        line 1966: 0
      LocalVariableTable:
        Start  Length  Slot  Name   Signature
            0       6     0  this   Lscala/collection/immutable/NewVectorIterator;
            0       6     1    op   Lscala/Function2;
    Signature: #417                         // <B:Ljava/lang/Object;>(Lscala/Function2<TB;TA;TB;>;)Lscala/Option<TB;>;
    MethodParameters:
      Name                           Flags
      op                             final

  public <B extends java.lang.Object> scala.Option<B> reduceRightOption(scala.Function2<A, B, B>);
    descriptor: (Lscala/Function2;)Lscala/Option;
    flags: (0x0001) ACC_PUBLIC
    Code:
      stack=2, locals=2, args_size=2
         0: aload_0
         1: aload_1
         2: invokestatic  #425                // InterfaceMethod scala/collection/IterableOnceOps.reduceRightOption$:(Lscala/collection/IterableOnceOps;Lscala/Function2;)Lscala/Option;
         5: areturn
      LineNumberTable:
        line 1966: 0
      LocalVariableTable:
        Start  Length  Slot  Name   Signature
            0       6     0  this   Lscala/collection/immutable/NewVectorIterator;
            0       6     1    op   Lscala/Function2;
    Signature: #422                         // <B:Ljava/lang/Object;>(Lscala/Function2<TA;TB;TB;>;)Lscala/Option<TB;>;
    MethodParameters:
      Name                           Flags
      op                             final

  public boolean nonEmpty();
    descriptor: ()Z
    flags: (0x0001) ACC_PUBLIC
    Code:
      stack=1, locals=1, args_size=1
         0: aload_0
         1: invokestatic  #429                // InterfaceMethod scala/collection/IterableOnceOps.nonEmpty$:(Lscala/collection/IterableOnceOps;)Z
         4: ireturn
      LineNumberTable:
        line 1966: 0
      LocalVariableTable:
        Start  Length  Slot  Name   Signature
            0       5     0  this   Lscala/collection/immutable/NewVectorIterator;

  public int size();
    descriptor: ()I
    flags: (0x0001) ACC_PUBLIC
    Code:
      stack=1, locals=1, args_size=1
         0: aload_0
         1: invokestatic  #433                // InterfaceMethod scala/collection/IterableOnceOps.size$:(Lscala/collection/IterableOnceOps;)I
         4: ireturn
      LineNumberTable:
        line 1966: 0
      LocalVariableTable:
        Start  Length  Slot  Name   Signature
            0       5     0  this   Lscala/collection/immutable/NewVectorIterator;

  public final <B extends java.lang.Object> void copyToBuffer(scala.collection.mutable.Buffer<B>);
    descriptor: (Lscala/collection/mutable/Buffer;)V
    flags: (0x0011) ACC_PUBLIC, ACC_FINAL
    Code:
      stack=2, locals=2, args_size=2
         0: aload_0
         1: aload_1
         2: invokestatic  #441                // InterfaceMethod scala/collection/IterableOnceOps.copyToBuffer$:(Lscala/collection/IterableOnceOps;Lscala/collection/mutable/Buffer;)V
         5: return
      LineNumberTable:
        line 1966: 0
      LocalVariableTable:
        Start  Length  Slot  Name   Signature
            0       6     0  this   Lscala/collection/immutable/NewVectorIterator;
            0       6     1  dest   Lscala/collection/mutable/Buffer;
    Signature: #436                         // <B:Ljava/lang/Object;>(Lscala/collection/mutable/Buffer<TB;>;)V
    Deprecated: true
    MethodParameters:
      Name                           Flags
      dest                           final

  public <B extends java.lang.Object> int copyToArray(java.lang.Object);
    descriptor: (Ljava/lang/Object;)I
    flags: (0x0001) ACC_PUBLIC
    Code:
      stack=2, locals=2, args_size=2
         0: aload_0
         1: aload_1
         2: invokestatic  #448                // InterfaceMethod scala/collection/IterableOnceOps.copyToArray$:(Lscala/collection/IterableOnceOps;Ljava/lang/Object;)I
         5: ireturn
      LineNumberTable:
        line 1966: 0
      LocalVariableTable:
        Start  Length  Slot  Name   Signature
            0       6     0  this   Lscala/collection/immutable/NewVectorIterator;
            0       6     1    xs   Ljava/lang/Object;
    Signature: #444                         // <B:Ljava/lang/Object;>(Ljava/lang/Object;)I
    MethodParameters:
      Name                           Flags
      xs                             final

  public <B extends java.lang.Object> int copyToArray(java.lang.Object, int);
    descriptor: (Ljava/lang/Object;I)I
    flags: (0x0001) ACC_PUBLIC
    Code:
      stack=3, locals=3, args_size=3
         0: aload_0
         1: aload_1
         2: iload_2
         3: invokestatic  #453                // InterfaceMethod scala/collection/IterableOnceOps.copyToArray$:(Lscala/collection/IterableOnceOps;Ljava/lang/Object;I)I
         6: ireturn
      LineNumberTable:
        line 1966: 0
      LocalVariableTable:
        Start  Length  Slot  Name   Signature
            0       7     0  this   Lscala/collection/immutable/NewVectorIterator;
            0       7     1    xs   Ljava/lang/Object;
            0       7     2 start   I
    Signature: #449                         // <B:Ljava/lang/Object;>(Ljava/lang/Object;I)I
    MethodParameters:
      Name                           Flags
      xs                             final
      start                          final

  public <B extends java.lang.Object> B sum(scala.math.Numeric<B>);
    descriptor: (Lscala/math/Numeric;)Ljava/lang/Object;
    flags: (0x0001) ACC_PUBLIC
    Code:
      stack=2, locals=2, args_size=2
         0: aload_0
         1: aload_1
         2: invokestatic  #461                // InterfaceMethod scala/collection/IterableOnceOps.sum$:(Lscala/collection/IterableOnceOps;Lscala/math/Numeric;)Ljava/lang/Object;
         5: areturn
      LineNumberTable:
        line 1966: 0
      LocalVariableTable:
        Start  Length  Slot  Name   Signature
            0       6     0  this   Lscala/collection/immutable/NewVectorIterator;
            0       6     1   num   Lscala/math/Numeric;
    Signature: #456                         // <B:Ljava/lang/Object;>(Lscala/math/Numeric<TB;>;)TB;
    MethodParameters:
      Name                           Flags
      num                            final

  public <B extends java.lang.Object> B product(scala.math.Numeric<B>);
    descriptor: (Lscala/math/Numeric;)Ljava/lang/Object;
    flags: (0x0001) ACC_PUBLIC
    Code:
      stack=2, locals=2, args_size=2
         0: aload_0
         1: aload_1
         2: invokestatic  #466                // InterfaceMethod scala/collection/IterableOnceOps.product$:(Lscala/collection/IterableOnceOps;Lscala/math/Numeric;)Ljava/lang/Object;
         5: areturn
      LineNumberTable:
        line 1966: 0
      LocalVariableTable:
        Start  Length  Slot  Name   Signature
            0       6     0  this   Lscala/collection/immutable/NewVectorIterator;
            0       6     1   num   Lscala/math/Numeric;
    Signature: #456                         // <B:Ljava/lang/Object;>(Lscala/math/Numeric<TB;>;)TB;
    MethodParameters:
      Name                           Flags
      num                            final

  public <B extends java.lang.Object> A min(scala.math.Ordering<B>);
    descriptor: (Lscala/math/Ordering;)Ljava/lang/Object;
    flags: (0x0001) ACC_PUBLIC
    Code:
      stack=2, locals=2, args_size=2
         0: aload_0
         1: aload_1
         2: invokestatic  #474                // InterfaceMethod scala/collection/IterableOnceOps.min$:(Lscala/collection/IterableOnceOps;Lscala/math/Ordering;)Ljava/lang/Object;
         5: areturn
      LineNumberTable:
        line 1966: 0
      LocalVariableTable:
        Start  Length  Slot  Name   Signature
            0       6     0  this   Lscala/collection/immutable/NewVectorIterator;
            0       6     1   ord   Lscala/math/Ordering;
    Signature: #469                         // <B:Ljava/lang/Object;>(Lscala/math/Ordering<TB;>;)TA;
    MethodParameters:
      Name                           Flags
      ord                            final

  public <B extends java.lang.Object> scala.Option<A> minOption(scala.math.Ordering<B>);
    descriptor: (Lscala/math/Ordering;)Lscala/Option;
    flags: (0x0001) ACC_PUBLIC
    Code:
      stack=2, locals=2, args_size=2
         0: aload_0
         1: aload_1
         2: invokestatic  #482                // InterfaceMethod scala/collection/IterableOnceOps.minOption$:(Lscala/collection/IterableOnceOps;Lscala/math/Ordering;)Lscala/Option;
         5: areturn
      LineNumberTable:
        line 1966: 0
      LocalVariableTable:
        Start  Length  Slot  Name   Signature
            0       6     0  this   Lscala/collection/immutable/NewVectorIterator;
            0       6     1   ord   Lscala/math/Ordering;
    Signature: #478                         // <B:Ljava/lang/Object;>(Lscala/math/Ordering<TB;>;)Lscala/Option<TA;>;
    MethodParameters:
      Name                           Flags
      ord                            final

  public <B extends java.lang.Object> A max(scala.math.Ordering<B>);
    descriptor: (Lscala/math/Ordering;)Ljava/lang/Object;
    flags: (0x0001) ACC_PUBLIC
    Code:
      stack=2, locals=2, args_size=2
         0: aload_0
         1: aload_1
         2: invokestatic  #486                // InterfaceMethod scala/collection/IterableOnceOps.max$:(Lscala/collection/IterableOnceOps;Lscala/math/Ordering;)Ljava/lang/Object;
         5: areturn
      LineNumberTable:
        line 1966: 0
      LocalVariableTable:
        Start  Length  Slot  Name   Signature
            0       6     0  this   Lscala/collection/immutable/NewVectorIterator;
            0       6     1   ord   Lscala/math/Ordering;
    Signature: #469                         // <B:Ljava/lang/Object;>(Lscala/math/Ordering<TB;>;)TA;
    MethodParameters:
      Name                           Flags
      ord                            final

  public <B extends java.lang.Object> scala.Option<A> maxOption(scala.math.Ordering<B>);
    descriptor: (Lscala/math/Ordering;)Lscala/Option;
    flags: (0x0001) ACC_PUBLIC
    Code:
      stack=2, locals=2, args_size=2
         0: aload_0
         1: aload_1
         2: invokestatic  #490                // InterfaceMethod scala/collection/IterableOnceOps.maxOption$:(Lscala/collection/IterableOnceOps;Lscala/math/Ordering;)Lscala/Option;
         5: areturn
      LineNumberTable:
        line 1966: 0
      LocalVariableTable:
        Start  Length  Slot  Name   Signature
            0       6     0  this   Lscala/collection/immutable/NewVectorIterator;
            0       6     1   ord   Lscala/math/Ordering;
    Signature: #478                         // <B:Ljava/lang/Object;>(Lscala/math/Ordering<TB;>;)Lscala/Option<TA;>;
    MethodParameters:
      Name                           Flags
      ord                            final

  public <B extends java.lang.Object> A maxBy(scala.Function1<A, B>, scala.math.Ordering<B>);
    descriptor: (Lscala/Function1;Lscala/math/Ordering;)Ljava/lang/Object;
    flags: (0x0001) ACC_PUBLIC
    Code:
      stack=3, locals=3, args_size=3
         0: aload_0
         1: aload_1
         2: aload_2
         3: invokestatic  #498                // InterfaceMethod scala/collection/IterableOnceOps.maxBy$:(Lscala/collection/IterableOnceOps;Lscala/Function1;Lscala/math/Ordering;)Ljava/lang/Object;
         6: areturn
      LineNumberTable:
        line 1966: 0
      LocalVariableTable:
        Start  Length  Slot  Name   Signature
            0       7     0  this   Lscala/collection/immutable/NewVectorIterator;
            0       7     1     f   Lscala/Function1;
            0       7     2   cmp   Lscala/math/Ordering;
    Signature: #493                         // <B:Ljava/lang/Object;>(Lscala/Function1<TA;TB;>;Lscala/math/Ordering<TB;>;)TA;
    MethodParameters:
      Name                           Flags
      f                              final
      cmp                            final

  public <B extends java.lang.Object> scala.Option<A> maxByOption(scala.Function1<A, B>, scala.math.Ordering<B>);
    descriptor: (Lscala/Function1;Lscala/math/Ordering;)Lscala/Option;
    flags: (0x0001) ACC_PUBLIC
    Code:
      stack=3, locals=3, args_size=3
         0: aload_0
         1: aload_1
         2: aload_2
         3: invokestatic  #505                // InterfaceMethod scala/collection/IterableOnceOps.maxByOption$:(Lscala/collection/IterableOnceOps;Lscala/Function1;Lscala/math/Ordering;)Lscala/Option;
         6: areturn
      LineNumberTable:
        line 1966: 0
      LocalVariableTable:
        Start  Length  Slot  Name   Signature
            0       7     0  this   Lscala/collection/immutable/NewVectorIterator;
            0       7     1     f   Lscala/Function1;
            0       7     2   cmp   Lscala/math/Ordering;
    Signature: #501                         // <B:Ljava/lang/Object;>(Lscala/Function1<TA;TB;>;Lscala/math/Ordering<TB;>;)Lscala/Option<TA;>;
    MethodParameters:
      Name                           Flags
      f                              final
      cmp                            final

  public <B extends java.lang.Object> A minBy(scala.Function1<A, B>, scala.math.Ordering<B>);
    descriptor: (Lscala/Function1;Lscala/math/Ordering;)Ljava/lang/Object;
    flags: (0x0001) ACC_PUBLIC
    Code:
      stack=3, locals=3, args_size=3
         0: aload_0
         1: aload_1
         2: aload_2
         3: invokestatic  #509                // InterfaceMethod scala/collection/IterableOnceOps.minBy$:(Lscala/collection/IterableOnceOps;Lscala/Function1;Lscala/math/Ordering;)Ljava/lang/Object;
         6: areturn
      LineNumberTable:
        line 1966: 0
      LocalVariableTable:
        Start  Length  Slot  Name   Signature
            0       7     0  this   Lscala/collection/immutable/NewVectorIterator;
            0       7     1     f   Lscala/Function1;
            0       7     2   cmp   Lscala/math/Ordering;
    Signature: #493                         // <B:Ljava/lang/Object;>(Lscala/Function1<TA;TB;>;Lscala/math/Ordering<TB;>;)TA;
    MethodParameters:
      Name                           Flags
      f                              final
      cmp                            final

  public <B extends java.lang.Object> scala.Option<A> minByOption(scala.Function1<A, B>, scala.math.Ordering<B>);
    descriptor: (Lscala/Function1;Lscala/math/Ordering;)Lscala/Option;
    flags: (0x0001) ACC_PUBLIC
    Code:
      stack=3, locals=3, args_size=3
         0: aload_0
         1: aload_1
         2: aload_2
         3: invokestatic  #513                // InterfaceMethod scala/collection/IterableOnceOps.minByOption$:(Lscala/collection/IterableOnceOps;Lscala/Function1;Lscala/math/Ordering;)Lscala/Option;
         6: areturn
      LineNumberTable:
        line 1966: 0
      LocalVariableTable:
        Start  Length  Slot  Name   Signature
            0       7     0  this   Lscala/collection/immutable/NewVectorIterator;
            0       7     1     f   Lscala/Function1;
            0       7     2   cmp   Lscala/math/Ordering;
    Signature: #501                         // <B:Ljava/lang/Object;>(Lscala/Function1<TA;TB;>;Lscala/math/Ordering<TB;>;)Lscala/Option<TA;>;
    MethodParameters:
      Name                           Flags
      f                              final
      cmp                            final

  public <B extends java.lang.Object> scala.Option<B> collectFirst(scala.PartialFunction<A, B>);
    descriptor: (Lscala/PartialFunction;)Lscala/Option;
    flags: (0x0001) ACC_PUBLIC
    Code:
      stack=2, locals=2, args_size=2
         0: aload_0
         1: aload_1
         2: invokestatic  #520                // InterfaceMethod scala/collection/IterableOnceOps.collectFirst$:(Lscala/collection/IterableOnceOps;Lscala/PartialFunction;)Lscala/Option;
         5: areturn
      LineNumberTable:
        line 1966: 0
      LocalVariableTable:
        Start  Length  Slot  Name   Signature
            0       6     0  this   Lscala/collection/immutable/NewVectorIterator;
            0       6     1    pf   Lscala/PartialFunction;
    Signature: #516                         // <B:Ljava/lang/Object;>(Lscala/PartialFunction<TA;TB;>;)Lscala/Option<TB;>;
    MethodParameters:
      Name                           Flags
      pf                             final

  public <B extends java.lang.Object> B aggregate(scala.Function0<B>, scala.Function2<B, A, B>, scala.Function2<B, B, B>);
    descriptor: (Lscala/Function0;Lscala/Function2;Lscala/Function2;)Ljava/lang/Object;
    flags: (0x0001) ACC_PUBLIC
    Code:
      stack=4, locals=4, args_size=4
         0: aload_0
         1: aload_1
         2: aload_2
         3: aload_3
         4: invokestatic  #529                // InterfaceMethod scala/collection/IterableOnceOps.aggregate$:(Lscala/collection/IterableOnceOps;Lscala/Function0;Lscala/Function2;Lscala/Function2;)Ljava/lang/Object;
         7: areturn
      LineNumberTable:
        line 1966: 0
      LocalVariableTable:
        Start  Length  Slot  Name   Signature
            0       8     0  this   Lscala/collection/immutable/NewVectorIterator;
            0       8     1     z   Lscala/Function0;
            0       8     2 seqop   Lscala/Function2;
            0       8     3 combop   Lscala/Function2;
    Signature: #523                         // <B:Ljava/lang/Object;>(Lscala/Function0<TB;>;Lscala/Function2<TB;TA;TB;>;Lscala/Function2<TB;TB;TB;>;)TB;
    Deprecated: true
    MethodParameters:
      Name                           Flags
      z                              final
      seqop                          final
      combop                         final

  public <B extends java.lang.Object> boolean corresponds(scala.collection.IterableOnce<B>, scala.Function2<A, B, java.lang.Object>);
    descriptor: (Lscala/collection/IterableOnce;Lscala/Function2;)Z
    flags: (0x0001) ACC_PUBLIC
    Code:
      stack=3, locals=3, args_size=3
         0: aload_0
         1: aload_1
         2: aload_2
         3: invokestatic  #536                // InterfaceMethod scala/collection/IterableOnceOps.corresponds$:(Lscala/collection/IterableOnceOps;Lscala/collection/IterableOnce;Lscala/Function2;)Z
         6: ireturn
      LineNumberTable:
        line 1966: 0
      LocalVariableTable:
        Start  Length  Slot  Name   Signature
            0       7     0  this   Lscala/collection/immutable/NewVectorIterator;
            0       7     1  that   Lscala/collection/IterableOnce;
            0       7     2     p   Lscala/Function2;
    Signature: #532                         // <B:Ljava/lang/Object;>(Lscala/collection/IterableOnce<TB;>;Lscala/Function2<TA;TB;Ljava/lang/Object;>;)Z
    MethodParameters:
      Name                           Flags
      that                           final
      p                              final

  public final java.lang.String mkString(java.lang.String, java.lang.String, java.lang.String);
    descriptor: (Ljava/lang/String;Ljava/lang/String;Ljava/lang/String;)Ljava/lang/String;
    flags: (0x0011) ACC_PUBLIC, ACC_FINAL
    Code:
      stack=4, locals=4, args_size=4
         0: aload_0
         1: aload_1
         2: aload_2
         3: aload_3
         4: invokestatic  #544                // InterfaceMethod scala/collection/IterableOnceOps.mkString$:(Lscala/collection/IterableOnceOps;Ljava/lang/String;Ljava/lang/String;Ljava/lang/String;)Ljava/lang/String;
         7: areturn
      LineNumberTable:
        line 1966: 0
      LocalVariableTable:
        Start  Length  Slot  Name   Signature
            0       8     0  this   Lscala/collection/immutable/NewVectorIterator;
            0       8     1 start   Ljava/lang/String;
            0       8     2   sep   Ljava/lang/String;
            0       8     3   end   Ljava/lang/String;
    MethodParameters:
      Name                           Flags
      start                          final
      sep                            final
      end                            final

  public final java.lang.String mkString(java.lang.String);
    descriptor: (Ljava/lang/String;)Ljava/lang/String;
    flags: (0x0011) ACC_PUBLIC, ACC_FINAL
    Code:
      stack=2, locals=2, args_size=2
         0: aload_0
         1: aload_1
         2: invokestatic  #549                // InterfaceMethod scala/collection/IterableOnceOps.mkString$:(Lscala/collection/IterableOnceOps;Ljava/lang/String;)Ljava/lang/String;
         5: areturn
      LineNumberTable:
        line 1966: 0
      LocalVariableTable:
        Start  Length  Slot  Name   Signature
            0       6     0  this   Lscala/collection/immutable/NewVectorIterator;
            0       6     1   sep   Ljava/lang/String;
    MethodParameters:
      Name                           Flags
      sep                            final

  public final java.lang.String mkString();
    descriptor: ()Ljava/lang/String;
    flags: (0x0011) ACC_PUBLIC, ACC_FINAL
    Code:
      stack=1, locals=1, args_size=1
         0: aload_0
         1: invokestatic  #552                // InterfaceMethod scala/collection/IterableOnceOps.mkString$:(Lscala/collection/IterableOnceOps;)Ljava/lang/String;
         4: areturn
      LineNumberTable:
        line 1966: 0
      LocalVariableTable:
        Start  Length  Slot  Name   Signature
            0       5     0  this   Lscala/collection/immutable/NewVectorIterator;

  public scala.collection.mutable.StringBuilder addString(scala.collection.mutable.StringBuilder, java.lang.String, java.lang.String, java.lang.String);
    descriptor: (Lscala/collection/mutable/StringBuilder;Ljava/lang/String;Ljava/lang/String;Ljava/lang/String;)Lscala/collection/mutable/StringBuilder;
    flags: (0x0001) ACC_PUBLIC
    Code:
      stack=5, locals=5, args_size=5
         0: aload_0
         1: aload_1
         2: aload_2
         3: aload_3
         4: aload         4
         6: invokestatic  #559                // InterfaceMethod scala/collection/IterableOnceOps.addString$:(Lscala/collection/IterableOnceOps;Lscala/collection/mutable/StringBuilder;Ljava/lang/String;Ljava/lang/String;Ljava/lang/String;)Lscala/collection/mutable/StringBuilder;
         9: areturn
      LineNumberTable:
        line 1966: 0
      LocalVariableTable:
        Start  Length  Slot  Name   Signature
            0      10     0  this   Lscala/collection/immutable/NewVectorIterator;
            0      10     1     b   Lscala/collection/mutable/StringBuilder;
            0      10     2 start   Ljava/lang/String;
            0      10     3   sep   Ljava/lang/String;
            0      10     4   end   Ljava/lang/String;
    MethodParameters:
      Name                           Flags
      b                              final
      start                          final
      sep                            final
      end                            final

  public final scala.collection.mutable.StringBuilder addString(scala.collection.mutable.StringBuilder, java.lang.String);
    descriptor: (Lscala/collection/mutable/StringBuilder;Ljava/lang/String;)Lscala/collection/mutable/StringBuilder;
    flags: (0x0011) ACC_PUBLIC, ACC_FINAL
    Code:
      stack=3, locals=3, args_size=3
         0: aload_0
         1: aload_1
         2: aload_2
         3: invokestatic  #564                // InterfaceMethod scala/collection/IterableOnceOps.addString$:(Lscala/collection/IterableOnceOps;Lscala/collection/mutable/StringBuilder;Ljava/lang/String;)Lscala/collection/mutable/StringBuilder;
         6: areturn
      LineNumberTable:
        line 1966: 0
      LocalVariableTable:
        Start  Length  Slot  Name   Signature
            0       7     0  this   Lscala/collection/immutable/NewVectorIterator;
            0       7     1     b   Lscala/collection/mutable/StringBuilder;
            0       7     2   sep   Ljava/lang/String;
    MethodParameters:
      Name                           Flags
      b                              final
      sep                            final

  public final scala.collection.mutable.StringBuilder addString(scala.collection.mutable.StringBuilder);
    descriptor: (Lscala/collection/mutable/StringBuilder;)Lscala/collection/mutable/StringBuilder;
    flags: (0x0011) ACC_PUBLIC, ACC_FINAL
    Code:
      stack=2, locals=2, args_size=2
         0: aload_0
         1: aload_1
         2: invokestatic  #568                // InterfaceMethod scala/collection/IterableOnceOps.addString$:(Lscala/collection/IterableOnceOps;Lscala/collection/mutable/StringBuilder;)Lscala/collection/mutable/StringBuilder;
         5: areturn
      LineNumberTable:
        line 1966: 0
      LocalVariableTable:
        Start  Length  Slot  Name   Signature
            0       6     0  this   Lscala/collection/immutable/NewVectorIterator;
            0       6     1     b   Lscala/collection/mutable/StringBuilder;
    MethodParameters:
      Name                           Flags
      b                              final

  public <C1 extends java.lang.Object> C1 to(scala.collection.Factory<A, C1>);
    descriptor: (Lscala/collection/Factory;)Ljava/lang/Object;
    flags: (0x0001) ACC_PUBLIC
    Code:
      stack=2, locals=2, args_size=2
         0: aload_0
         1: aload_1
         2: invokestatic  #576                // InterfaceMethod scala/collection/IterableOnceOps.to$:(Lscala/collection/IterableOnceOps;Lscala/collection/Factory;)Ljava/lang/Object;
         5: areturn
      LineNumberTable:
        line 1966: 0
      LocalVariableTable:
        Start  Length  Slot  Name   Signature
            0       6     0  this   Lscala/collection/immutable/NewVectorIterator;
            0       6     1 factory   Lscala/collection/Factory;
    Signature: #571                         // <C1:Ljava/lang/Object;>(Lscala/collection/Factory<TA;TC1;>;)TC1;
    MethodParameters:
      Name                           Flags
      factory                        final

  public final scala.collection.Iterator<A> toIterator();
    descriptor: ()Lscala/collection/Iterator;
    flags: (0x0011) ACC_PUBLIC, ACC_FINAL
    Code:
      stack=1, locals=1, args_size=1
         0: aload_0
         1: invokestatic  #582                // InterfaceMethod scala/collection/IterableOnceOps.toIterator$:(Lscala/collection/IterableOnceOps;)Lscala/collection/Iterator;
         4: areturn
      LineNumberTable:
        line 1966: 0
      LocalVariableTable:
        Start  Length  Slot  Name   Signature
            0       5     0  this   Lscala/collection/immutable/NewVectorIterator;
    Signature: #53                          // ()Lscala/collection/Iterator<TA;>;
    Deprecated: true

  public scala.collection.immutable.List<A> toList();
    descriptor: ()Lscala/collection/immutable/List;
    flags: (0x0001) ACC_PUBLIC
    Code:
      stack=1, locals=1, args_size=1
         0: aload_0
         1: invokestatic  #589                // InterfaceMethod scala/collection/IterableOnceOps.toList$:(Lscala/collection/IterableOnceOps;)Lscala/collection/immutable/List;
         4: areturn
      LineNumberTable:
        line 1966: 0
      LocalVariableTable:
        Start  Length  Slot  Name   Signature
            0       5     0  this   Lscala/collection/immutable/NewVectorIterator;
    Signature: #585                         // ()Lscala/collection/immutable/List<TA;>;

  public <K$ extends java.lang.Object, V$ extends java.lang.Object> scala.collection.immutable.Map<K$, V$> toMap(scala.$less$colon$less<A, scala.Tuple2<K$, V$>>);
    descriptor: (Lscala/$less$colon$less;)Lscala/collection/immutable/Map;
    flags: (0x0001) ACC_PUBLIC
    Code:
      stack=2, locals=2, args_size=2
         0: aload_0
         1: aload_1
         2: invokestatic  #596                // InterfaceMethod scala/collection/IterableOnceOps.toMap$:(Lscala/collection/IterableOnceOps;Lscala/$less$colon$less;)Lscala/collection/immutable/Map;
         5: areturn
      LineNumberTable:
        line 1966: 0
      LocalVariableTable:
        Start  Length  Slot  Name   Signature
            0       6     0  this   Lscala/collection/immutable/NewVectorIterator;
            0       6     1    ev   Lscala/$less$colon$less;
    Signature: #592                         // <K$:Ljava/lang/Object;V$:Ljava/lang/Object;>(Lscala/$less$colon$less<TA;Lscala/Tuple2<TK$;TV$;>;>;)Lscala/collection/immutable/Map<TK$;TV$;>;
    MethodParameters:
      Name                           Flags
      ev                             final

  public <B extends java.lang.Object> scala.collection.immutable.Set<B> toSet();
    descriptor: ()Lscala/collection/immutable/Set;
    flags: (0x0001) ACC_PUBLIC
    Code:
      stack=1, locals=1, args_size=1
         0: aload_0
         1: invokestatic  #604                // InterfaceMethod scala/collection/IterableOnceOps.toSet$:(Lscala/collection/IterableOnceOps;)Lscala/collection/immutable/Set;
         4: areturn
      LineNumberTable:
        line 1966: 0
      LocalVariableTable:
        Start  Length  Slot  Name   Signature
            0       5     0  this   Lscala/collection/immutable/NewVectorIterator;
    Signature: #600                         // <B:Ljava/lang/Object;>()Lscala/collection/immutable/Set<TB;>;

  public scala.collection.immutable.Seq<A> toSeq();
    descriptor: ()Lscala/collection/immutable/Seq;
    flags: (0x0001) ACC_PUBLIC
    Code:
      stack=1, locals=1, args_size=1
         0: aload_0
         1: invokestatic  #611                // InterfaceMethod scala/collection/IterableOnceOps.toSeq$:(Lscala/collection/IterableOnceOps;)Lscala/collection/immutable/Seq;
         4: areturn
      LineNumberTable:
        line 1966: 0
      LocalVariableTable:
        Start  Length  Slot  Name   Signature
            0       5     0  this   Lscala/collection/immutable/NewVectorIterator;
    Signature: #607                         // ()Lscala/collection/immutable/Seq<TA;>;

  public scala.collection.immutable.IndexedSeq<A> toIndexedSeq();
    descriptor: ()Lscala/collection/immutable/IndexedSeq;
    flags: (0x0001) ACC_PUBLIC
    Code:
      stack=1, locals=1, args_size=1
         0: aload_0
         1: invokestatic  #618                // InterfaceMethod scala/collection/IterableOnceOps.toIndexedSeq$:(Lscala/collection/IterableOnceOps;)Lscala/collection/immutable/IndexedSeq;
         4: areturn
      LineNumberTable:
        line 1966: 0
      LocalVariableTable:
        Start  Length  Slot  Name   Signature
            0       5     0  this   Lscala/collection/immutable/NewVectorIterator;
    Signature: #614                         // ()Lscala/collection/immutable/IndexedSeq<TA;>;

  public final scala.collection.immutable.Stream<A> toStream();
    descriptor: ()Lscala/collection/immutable/Stream;
    flags: (0x0011) ACC_PUBLIC, ACC_FINAL
    Code:
      stack=1, locals=1, args_size=1
         0: aload_0
         1: invokestatic  #625                // InterfaceMethod scala/collection/IterableOnceOps.toStream$:(Lscala/collection/IterableOnceOps;)Lscala/collection/immutable/Stream;
         4: areturn
      LineNumberTable:
        line 1966: 0
      LocalVariableTable:
        Start  Length  Slot  Name   Signature
            0       5     0  this   Lscala/collection/immutable/NewVectorIterator;
    Signature: #621                         // ()Lscala/collection/immutable/Stream<TA;>;
    Deprecated: true

  public final <B extends java.lang.Object> scala.collection.mutable.Buffer<B> toBuffer();
    descriptor: ()Lscala/collection/mutable/Buffer;
    flags: (0x0011) ACC_PUBLIC, ACC_FINAL
    Code:
      stack=1, locals=1, args_size=1
         0: aload_0
         1: invokestatic  #632                // InterfaceMethod scala/collection/IterableOnceOps.toBuffer$:(Lscala/collection/IterableOnceOps;)Lscala/collection/mutable/Buffer;
         4: areturn
      LineNumberTable:
        line 1966: 0
      LocalVariableTable:
        Start  Length  Slot  Name   Signature
            0       5     0  this   Lscala/collection/immutable/NewVectorIterator;
    Signature: #628                         // <B:Ljava/lang/Object;>()Lscala/collection/mutable/Buffer<TB;>;

  public <B extends java.lang.Object> java.lang.Object toArray(scala.reflect.ClassTag<B>);
    descriptor: (Lscala/reflect/ClassTag;)Ljava/lang/Object;
    flags: (0x0001) ACC_PUBLIC
    Code:
      stack=2, locals=2, args_size=2
         0: aload_0
         1: aload_1
         2: invokestatic  #640                // InterfaceMethod scala/collection/IterableOnceOps.toArray$:(Lscala/collection/IterableOnceOps;Lscala/reflect/ClassTag;)Ljava/lang/Object;
         5: areturn
      LineNumberTable:
        line 1966: 0
      LocalVariableTable:
        Start  Length  Slot  Name   Signature
            0       6     0  this   Lscala/collection/immutable/NewVectorIterator;
            0       6     1 evidence$2   Lscala/reflect/ClassTag;
    Signature: #635                         // <B:Ljava/lang/Object;>(Lscala/reflect/ClassTag<TB;>;)Ljava/lang/Object;
    MethodParameters:
      Name                           Flags
      evidence$2                     final

  public scala.collection.Iterable<A> reversed();
    descriptor: ()Lscala/collection/Iterable;
    flags: (0x0001) ACC_PUBLIC
    Code:
      stack=1, locals=1, args_size=1
         0: aload_0
         1: invokestatic  #648                // InterfaceMethod scala/collection/IterableOnceOps.reversed$:(Lscala/collection/IterableOnceOps;)Lscala/collection/Iterable;
         4: areturn
      LineNumberTable:
        line 1966: 0
      LocalVariableTable:
        Start  Length  Slot  Name   Signature
            0       5     0  this   Lscala/collection/immutable/NewVectorIterator;
    Signature: #644                         // ()Lscala/collection/Iterable<TA;>;

  public <S extends scala.collection.Stepper<?>> S stepper(scala.collection.StepperShape<A, S>);
    descriptor: (Lscala/collection/StepperShape;)Lscala/collection/Stepper;
    flags: (0x0001) ACC_PUBLIC
    Code:
      stack=2, locals=2, args_size=2
         0: aload_0
         1: aload_1
         2: invokestatic  #658                // InterfaceMethod scala/collection/IterableOnce.stepper$:(Lscala/collection/IterableOnce;Lscala/collection/StepperShape;)Lscala/collection/Stepper;
         5: areturn
      LineNumberTable:
        line 1966: 0
      LocalVariableTable:
        Start  Length  Slot  Name   Signature
            0       6     0  this   Lscala/collection/immutable/NewVectorIterator;
            0       6     1 shape   Lscala/collection/StepperShape;
    Signature: #651                         // <S::Lscala/collection/Stepper<*>;>(Lscala/collection/StepperShape<TA;TS;>;)TS;
    MethodParameters:
      Name                           Flags
      shape                          final

  public int knownSize();
    descriptor: ()I
    flags: (0x0001) ACC_PUBLIC
    Code:
      stack=2, locals=1, args_size=1
         0: aload_0
         1: getfield      #662                // Field scala$collection$immutable$NewVectorIterator$$len1:I
         4: aload_0
         5: getfield      #664                // Field scala$collection$immutable$NewVectorIterator$$i1:I
         8: isub
         9: ireturn
      LineNumberTable:
        line 1987: 0
      LocalVariableTable:
        Start  Length  Slot  Name   Signature
            0      10     0  this   Lscala/collection/immutable/NewVectorIterator;

  public boolean hasNext();
    descriptor: ()Z
    flags: (0x0001) ACC_PUBLIC
    Code:
      stack=2, locals=1, args_size=1
         0: aload_0
         1: getfield      #662                // Field scala$collection$immutable$NewVectorIterator$$len1:I
         4: aload_0
         5: getfield      #664                // Field scala$collection$immutable$NewVectorIterator$$i1:I
         8: if_icmple     13
        11: iconst_1
        12: ireturn
        13: iconst_0
        14: ireturn
      StackMapTable: number_of_entries = 1
        frame_type = 13 /* same */
      LineNumberTable:
        line 1989: 0
      LocalVariableTable:
        Start  Length  Slot  Name   Signature
            0      15     0  this   Lscala/collection/immutable/NewVectorIterator;

  public A next();
    descriptor: ()Ljava/lang/Object;
    flags: (0x0001) ACC_PUBLIC
    Code:
      stack=3, locals=2, args_size=1
         0: aload_0
         1: getfield      #664                // Field scala$collection$immutable$NewVectorIterator$$i1:I
         4: aload_0
         5: getfield      #670                // Field a1len:I
         8: if_icmpne     15
        11: aload_0
        12: invokespecial #674                // Method advance:()V
        15: aload_0
        16: getfield      #676                // Field a1:[Ljava/lang/Object;
        19: aload_0
        20: getfield      #664                // Field scala$collection$immutable$NewVectorIterator$$i1:I
        23: aaload
        24: astore_1
        25: aload_0
        26: aload_0
        27: getfield      #664                // Field scala$collection$immutable$NewVectorIterator$$i1:I
        30: iconst_1
        31: iadd
        32: putfield      #664                // Field scala$collection$immutable$NewVectorIterator$$i1:I
        35: aload_1
        36: areturn
      StackMapTable: number_of_entries = 1
        frame_type = 15 /* same */
      LineNumberTable:
        line 1992: 0
        line 1993: 15
        line 1994: 25
        line 1995: 35
      LocalVariableTable:
        Start  Length  Slot  Name   Signature
           25      11     1     r   Ljava/lang/Object;
            0      37     0  this   Lscala/collection/immutable/NewVectorIterator;
    Signature: #668                         // ()TA;

  private void advanceSlice();
    descriptor: ()V
    flags: (0x0002) ACC_PRIVATE
    Code:
      stack=7, locals=5, args_size=1
         0: aload_0
         1: getfield      #662                // Field scala$collection$immutable$NewVectorIterator$$len1:I
         4: aload_0
         5: getfield      #664                // Field scala$collection$immutable$NewVectorIterator$$i1:I
         8: if_icmple     15
        11: iconst_1
        12: goto          16
        15: iconst_0
        16: ifne          32
        19: getstatic     #684                // Field scala/collection/Iterator$.MODULE$:Lscala/collection/Iterator$;
        22: pop
        23: getstatic     #687                // Field scala/collection/Iterator$.scala$collection$Iterator$$_empty:Lscala/collection/Iterator;
        26: invokeinterface #689,  1          // InterfaceMethod scala/collection/Iterator.next:()Ljava/lang/Object;
        31: pop
        32: aload_0
        33: aload_0
        34: getfield      #691                // Field sliceIdx:I
        37: iconst_1
        38: iadd
        39: putfield      #691                // Field sliceIdx:I
        42: aload_0
        43: getfield      #693                // Field v:Lscala/collection/immutable/Vector;
        46: aload_0
        47: getfield      #691                // Field sliceIdx:I
        50: invokevirtual #699                // Method scala/collection/immutable/Vector.vectorSlice:(I)[Ljava/lang/Object;
        53: astore_1
        54: aload_1
        55: arraylength
        56: iconst_0
        57: if_icmpne     85
        60: aload_0
        61: aload_0
        62: getfield      #691                // Field sliceIdx:I
        65: iconst_1
        66: iadd
        67: putfield      #691                // Field sliceIdx:I
        70: aload_0
        71: getfield      #693                // Field v:Lscala/collection/immutable/Vector;
        74: aload_0
        75: getfield      #691                // Field sliceIdx:I
        78: invokevirtual #699                // Method scala/collection/immutable/Vector.vectorSlice:(I)[Ljava/lang/Object;
        81: astore_1
        82: goto          54
        85: aload_0
        86: aload_0
        87: getfield      #701                // Field sliceEnd:I
        90: putfield      #703                // Field sliceStart:I
        93: aload_0
        94: getstatic     #708                // Field scala/collection/immutable/VectorInline$.MODULE$:Lscala/collection/immutable/VectorInline$;
        97: pop
        98: aload_0
        99: getfield      #710                // Field sliceCount:I
       102: aload_0
       103: getfield      #691                // Field sliceIdx:I
       106: istore_3
       107: iconst_2
       108: idiv
       109: istore        4
       111: iload         4
       113: iconst_1
       114: iadd
       115: iload_3
       116: iload         4
       118: isub
       119: invokestatic  #716                // Method java/lang/Math.abs:(I)I
       122: isub
       123: putfield      #718                // Field sliceDim:I
       126: aload_0
       127: getfield      #718                // Field sliceDim:I
       130: istore_2
       131: iload_2
       132: tableswitch   { // 1 to 6
                       1: 172
                       2: 180
                       3: 191
                       4: 202
                       5: 213
                       6: 224
                 default: 235
            }
       172: aload_0
       173: aload_1
       174: putfield      #676                // Field a1:[Ljava/lang/Object;
       177: goto          247
       180: aload_0
       181: aload_1
       182: checkcast     #719                // class "[[Ljava/lang/Object;"
       185: putfield      #721                // Field a2:[[Ljava/lang/Object;
       188: goto          247
       191: aload_0
       192: aload_1
       193: checkcast     #722                // class "[[[Ljava/lang/Object;"
       196: putfield      #724                // Field a3:[[[Ljava/lang/Object;
       199: goto          247
       202: aload_0
       203: aload_1
       204: checkcast     #725                // class "[[[[Ljava/lang/Object;"
       207: putfield      #727                // Field a4:[[[[Ljava/lang/Object;
       210: goto          247
       213: aload_0
       214: aload_1
       215: checkcast     #728                // class "[[[[[Ljava/lang/Object;"
       218: putfield      #730                // Field a5:[[[[[Ljava/lang/Object;
       221: goto          247
       224: aload_0
       225: aload_1
       226: checkcast     #731                // class "[[[[[[Ljava/lang/Object;"
       229: putfield      #733                // Field a6:[[[[[[Ljava/lang/Object;
       232: goto          247
       235: new           #735                // class scala/MatchError
       238: dup
       239: iload_2
       240: invokestatic  #741                // Method java/lang/Integer.valueOf:(I)Ljava/lang/Integer;
       243: invokespecial #745                // Method scala/MatchError."<init>":(Ljava/lang/Object;)V
       246: athrow
       247: aload_0
       248: aload_0
       249: getfield      #703                // Field sliceStart:I
       252: aload_1
       253: arraylength
       254: iconst_1
       255: iconst_5
       256: aload_0
       257: getfield      #718                // Field sliceDim:I
       260: iconst_1
       261: isub
       262: imul
       263: ishl
       264: imul
       265: iadd
       266: putfield      #701                // Field sliceEnd:I
       269: aload_0
       270: getfield      #701                // Field sliceEnd:I
       273: aload_0
       274: getfield      #747                // Field totalLength:I
       277: if_icmple     288
       280: aload_0
       281: aload_0
       282: getfield      #747                // Field totalLength:I
       285: putfield      #701                // Field sliceEnd:I
       288: aload_0
       289: getfield      #718                // Field sliceDim:I
       292: iconst_1
       293: if_icmple     310
       296: aload_0
       297: iconst_1
       298: iconst_5
       299: aload_0
       300: getfield      #718                // Field sliceDim:I
       303: imul
       304: ishl
       305: iconst_1
       306: isub
       307: putfield      #749                // Field oldPos:I
       310: return
      StackMapTable: number_of_entries = 15
        frame_type = 15 /* same */
        frame_type = 64 /* same_locals_1_stack_item */
          stack = [ int ]
        frame_type = 15 /* same */
        frame_type = 252 /* append */
          offset_delta = 21
          locals = [ class "[Ljava/lang/Object;" ]
        frame_type = 30 /* same */
        frame_type = 254 /* append */
          offset_delta = 86
          locals = [ int, int, int ]
        frame_type = 7 /* same */
        frame_type = 10 /* same */
        frame_type = 10 /* same */
        frame_type = 10 /* same */
        frame_type = 10 /* same */
        frame_type = 10 /* same */
        frame_type = 11 /* same */
        frame_type = 40 /* same */
        frame_type = 21 /* same */
      LineNumberTable:
        line 1989: 0
        line 1999: 16
        line 2000: 32
        line 2001: 42
        line 2002: 54
        line 2003: 60
        line 2004: 70
        line 2002: 82
        line 2006: 85
        line 2007: 93
        line 1749: 107
        line 1750: 111
        line 2007: 123
        line 2008: 126
        line 2009: 172
        line 2010: 180
        line 2011: 191
        line 2012: 202
        line 2013: 213
        line 2014: 224
        line 2008: 235
        line 2016: 247
        line 2017: 269
        line 2018: 288
      LocalVariableTable:
        Start  Length  Slot  Name   Signature
           54     256     1 slice   [Ljava/lang/Object;
            0     311     0  this   Lscala/collection/immutable/NewVectorIterator;
          111      12     4 vectorSliceDim_c   I
          107      16     3 vectorSliceDim_idx   I

  private void advance();
    descriptor: ()V
    flags: (0x0002) ACC_PRIVATE
    Code:
      stack=3, locals=4, args_size=1
         0: aload_0
         1: getfield      #664                // Field scala$collection$immutable$NewVectorIterator$$i1:I
         4: aload_0
         5: getfield      #662                // Field scala$collection$immutable$NewVectorIterator$$len1:I
         8: isub
         9: aload_0
        10: getfield      #747                // Field totalLength:I
        13: iadd
        14: istore_1
        15: iload_1
        16: aload_0
        17: getfield      #701                // Field sliceEnd:I
        20: if_icmpne     27
        23: aload_0
        24: invokespecial #755                // Method advanceSlice:()V
        27: aload_0
        28: getfield      #718                // Field sliceDim:I
        31: iconst_1
        32: if_icmple     60
        35: iload_1
        36: aload_0
        37: getfield      #703                // Field sliceStart:I
        40: isub
        41: istore_2
        42: aload_0
        43: getfield      #749                // Field oldPos:I
        46: iload_2
        47: ixor
        48: istore_3
        49: aload_0
        50: iload_2
        51: iload_3
        52: invokespecial #759                // Method advanceA:(II)V
        55: aload_0
        56: iload_2
        57: putfield      #749                // Field oldPos:I
        60: aload_0
        61: aload_0
        62: getfield      #662                // Field scala$collection$immutable$NewVectorIterator$$len1:I
        65: aload_0
        66: getfield      #664                // Field scala$collection$immutable$NewVectorIterator$$i1:I
        69: isub
        70: putfield      #662                // Field scala$collection$immutable$NewVectorIterator$$len1:I
        73: aload_0
        74: aload_0
        75: getfield      #676                // Field a1:[Ljava/lang/Object;
        78: arraylength
        79: aload_0
        80: getfield      #662                // Field scala$collection$immutable$NewVectorIterator$$len1:I
        83: invokestatic  #762                // Method java/lang/Math.min:(II)I
        86: putfield      #670                // Field a1len:I
        89: aload_0
        90: iconst_0
        91: putfield      #664                // Field scala$collection$immutable$NewVectorIterator$$i1:I
        94: return
      StackMapTable: number_of_entries = 2
        frame_type = 252 /* append */
          offset_delta = 27
          locals = [ int ]
        frame_type = 32 /* same */
      LineNumberTable:
        line 2022: 0
        line 2023: 15
        line 2024: 27
        line 2025: 35
        line 2026: 42
        line 2027: 49
        line 2028: 55
        line 2030: 60
        line 2031: 73
        line 2032: 89
      LocalVariableTable:
        Start  Length  Slot  Name   Signature
           42      18     2    io   I
           49      11     3   xor   I
           15      79     1   pos   I
            0      95     0  this   Lscala/collection/immutable/NewVectorIterator;

  private void advanceA(int, int);
    descriptor: (II)V
    flags: (0x0002) ACC_PRIVATE
    Code:
      stack=4, locals=3, args_size=3
         0: iload_2
         1: sipush        1024
         4: if_icmpge     23
         7: aload_0
         8: aload_0
         9: getfield      #721                // Field a2:[[Ljava/lang/Object;
        12: iload_1
        13: iconst_5
        14: iushr
        15: bipush        31
        17: iand
        18: aaload
        19: putfield      #676                // Field a1:[Ljava/lang/Object;
        22: return
        23: iload_2
        24: ldc_w         #766                // int 32768
        27: if_icmpge     57
        30: aload_0
        31: aload_0
        32: getfield      #724                // Field a3:[[[Ljava/lang/Object;
        35: iload_1
        36: bipush        10
        38: iushr
        39: bipush        31
        41: iand
        42: aaload
        43: putfield      #721                // Field a2:[[Ljava/lang/Object;
        46: aload_0
        47: aload_0
        48: getfield      #721                // Field a2:[[Ljava/lang/Object;
        51: iconst_0
        52: aaload
        53: putfield      #676                // Field a1:[Ljava/lang/Object;
        56: return
        57: iload_2
        58: ldc_w         #767                // int 1048576
        61: if_icmpge     101
        64: aload_0
        65: aload_0
        66: getfield      #727                // Field a4:[[[[Ljava/lang/Object;
        69: iload_1
        70: bipush        15
        72: iushr
        73: bipush        31
        75: iand
        76: aaload
        77: putfield      #724                // Field a3:[[[Ljava/lang/Object;
        80: aload_0
        81: aload_0
        82: getfield      #724                // Field a3:[[[Ljava/lang/Object;
        85: iconst_0
        86: aaload
        87: putfield      #721                // Field a2:[[Ljava/lang/Object;
        90: aload_0
        91: aload_0
        92: getfield      #721                // Field a2:[[Ljava/lang/Object;
        95: iconst_0
        96: aaload
        97: putfield      #676                // Field a1:[Ljava/lang/Object;
       100: return
       101: iload_2
       102: ldc_w         #768                // int 33554432
       105: if_icmpge     155
       108: aload_0
       109: aload_0
       110: getfield      #730                // Field a5:[[[[[Ljava/lang/Object;
       113: iload_1
       114: bipush        20
       116: iushr
       117: bipush        31
       119: iand
       120: aaload
       121: putfield      #727                // Field a4:[[[[Ljava/lang/Object;
       124: aload_0
       125: aload_0
       126: getfield      #727                // Field a4:[[[[Ljava/lang/Object;
       129: iconst_0
       130: aaload
       131: putfield      #724                // Field a3:[[[Ljava/lang/Object;
       134: aload_0
       135: aload_0
       136: getfield      #724                // Field a3:[[[Ljava/lang/Object;
       139: iconst_0
       140: aaload
       141: putfield      #721                // Field a2:[[Ljava/lang/Object;
       144: aload_0
       145: aload_0
       146: getfield      #721                // Field a2:[[Ljava/lang/Object;
       149: iconst_0
       150: aaload
       151: putfield      #676                // Field a1:[Ljava/lang/Object;
       154: return
       155: aload_0
       156: aload_0
       157: getfield      #733                // Field a6:[[[[[[Ljava/lang/Object;
       160: iload_1
       161: bipush        25
       163: iushr
       164: aaload
       165: putfield      #730                // Field a5:[[[[[Ljava/lang/Object;
       168: aload_0
       169: aload_0
       170: getfield      #730                // Field a5:[[[[[Ljava/lang/Object;
       173: iconst_0
       174: aaload
       175: putfield      #727                // Field a4:[[[[Ljava/lang/Object;
       178: aload_0
       179: aload_0
       180: getfield      #727                // Field a4:[[[[Ljava/lang/Object;
       183: iconst_0
       184: aaload
       185: putfield      #724                // Field a3:[[[Ljava/lang/Object;
       188: aload_0
       189: aload_0
       190: getfield      #724                // Field a3:[[[Ljava/lang/Object;
       193: iconst_0
       194: aaload
       195: putfield      #721                // Field a2:[[Ljava/lang/Object;
       198: aload_0
       199: aload_0
       200: getfield      #721                // Field a2:[[Ljava/lang/Object;
       203: iconst_0
       204: aaload
       205: putfield      #676                // Field a1:[Ljava/lang/Object;
       208: return
      StackMapTable: number_of_entries = 4
        frame_type = 23 /* same */
        frame_type = 33 /* same */
        frame_type = 43 /* same */
        frame_type = 53 /* same */
      LineNumberTable:
        line 2036: 0
        line 2037: 7
        line 2038: 23
        line 2039: 30
        line 2040: 46
        line 2041: 57
        line 2042: 64
        line 2043: 80
        line 2044: 90
        line 2045: 101
        line 2046: 108
        line 2047: 124
        line 2048: 134
        line 2049: 144
        line 2051: 155
        line 2052: 168
        line 2053: 178
        line 2054: 188
        line 2055: 198
      LocalVariableTable:
        Start  Length  Slot  Name   Signature
            0     209     0  this   Lscala/collection/immutable/NewVectorIterator;
            0     209     1    io   I
            0     209     2   xor   I
    MethodParameters:
      Name                           Flags
      io                             final
      xor                            final

  private void setA(int, int);
    descriptor: (II)V
    flags: (0x0002) ACC_PRIVATE
    Code:
      stack=4, locals=3, args_size=3
         0: iload_2
         1: sipush        1024
         4: if_icmpge     23
         7: aload_0
         8: aload_0
         9: getfield      #721                // Field a2:[[Ljava/lang/Object;
        12: iload_1
        13: iconst_5
        14: iushr
        15: bipush        31
        17: iand
        18: aaload
        19: putfield      #676                // Field a1:[Ljava/lang/Object;
        22: return
        23: iload_2
        24: ldc_w         #766                // int 32768
        27: if_icmpge     62
        30: aload_0
        31: aload_0
        32: getfield      #724                // Field a3:[[[Ljava/lang/Object;
        35: iload_1
        36: bipush        10
        38: iushr
        39: bipush        31
        41: iand
        42: aaload
        43: putfield      #721                // Field a2:[[Ljava/lang/Object;
        46: aload_0
        47: aload_0
        48: getfield      #721                // Field a2:[[Ljava/lang/Object;
        51: iload_1
        52: iconst_5
        53: iushr
        54: bipush        31
        56: iand
        57: aaload
        58: putfield      #676                // Field a1:[Ljava/lang/Object;
        61: return
        62: iload_2
        63: ldc_w         #767                // int 1048576
        66: if_icmpge     117
        69: aload_0
        70: aload_0
        71: getfield      #727                // Field a4:[[[[Ljava/lang/Object;
        74: iload_1
        75: bipush        15
        77: iushr
        78: bipush        31
        80: iand
        81: aaload
        82: putfield      #724                // Field a3:[[[Ljava/lang/Object;
        85: aload_0
        86: aload_0
        87: getfield      #724                // Field a3:[[[Ljava/lang/Object;
        90: iload_1
        91: bipush        10
        93: iushr
        94: bipush        31
        96: iand
        97: aaload
        98: putfield      #721                // Field a2:[[Ljava/lang/Object;
       101: aload_0
       102: aload_0
       103: getfield      #721                // Field a2:[[Ljava/lang/Object;
       106: iload_1
       107: iconst_5
       108: iushr
       109: bipush        31
       111: iand
       112: aaload
       113: putfield      #676                // Field a1:[Ljava/lang/Object;
       116: return
       117: iload_2
       118: ldc_w         #768                // int 33554432
       121: if_icmpge     188
       124: aload_0
       125: aload_0
       126: getfield      #730                // Field a5:[[[[[Ljava/lang/Object;
       129: iload_1
       130: bipush        20
       132: iushr
       133: bipush        31
       135: iand
       136: aaload
       137: putfield      #727                // Field a4:[[[[Ljava/lang/Object;
       140: aload_0
       141: aload_0
       142: getfield      #727                // Field a4:[[[[Ljava/lang/Object;
       145: iload_1
       146: bipush        15
       148: iushr
       149: bipush        31
       151: iand
       152: aaload
       153: putfield      #724                // Field a3:[[[Ljava/lang/Object;
       156: aload_0
       157: aload_0
       158: getfield      #724                // Field a3:[[[Ljava/lang/Object;
       161: iload_1
       162: bipush        10
       164: iushr
       165: bipush        31
       167: iand
       168: aaload
       169: putfield      #721                // Field a2:[[Ljava/lang/Object;
       172: aload_0
       173: aload_0
       174: getfield      #721                // Field a2:[[Ljava/lang/Object;
       177: iload_1
       178: iconst_5
       179: iushr
       180: bipush        31
       182: iand
       183: aaload
       184: putfield      #676                // Field a1:[Ljava/lang/Object;
       187: return
       188: aload_0
       189: aload_0
       190: getfield      #733                // Field a6:[[[[[[Ljava/lang/Object;
       193: iload_1
       194: bipush        25
       196: iushr
       197: aaload
       198: putfield      #730                // Field a5:[[[[[Ljava/lang/Object;
       201: aload_0
       202: aload_0
       203: getfield      #730                // Field a5:[[[[[Ljava/lang/Object;
       206: iload_1
       207: bipush        20
       209: iushr
       210: bipush        31
       212: iand
       213: aaload
       214: putfield      #727                // Field a4:[[[[Ljava/lang/Object;
       217: aload_0
       218: aload_0
       219: getfield      #727                // Field a4:[[[[Ljava/lang/Object;
       222: iload_1
       223: bipush        15
       225: iushr
       226: bipush        31
       228: iand
       229: aaload
       230: putfield      #724                // Field a3:[[[Ljava/lang/Object;
       233: aload_0
       234: aload_0
       235: getfield      #724                // Field a3:[[[Ljava/lang/Object;
       238: iload_1
       239: bipush        10
       241: iushr
       242: bipush        31
       244: iand
       245: aaload
       246: putfield      #721                // Field a2:[[Ljava/lang/Object;
       249: aload_0
       250: aload_0
       251: getfield      #721                // Field a2:[[Ljava/lang/Object;
       254: iload_1
       255: iconst_5
       256: iushr
       257: bipush        31
       259: iand
       260: aaload
       261: putfield      #676                // Field a1:[Ljava/lang/Object;
       264: return
      StackMapTable: number_of_entries = 4
        frame_type = 23 /* same */
        frame_type = 38 /* same */
        frame_type = 54 /* same */
        frame_type = 251 /* same_frame_extended */
          offset_delta = 70
      LineNumberTable:
        line 2060: 0
        line 2061: 7
        line 2062: 23
        line 2063: 30
        line 2064: 46
        line 2065: 62
        line 2066: 69
        line 2067: 85
        line 2068: 101
        line 2069: 117
        line 2070: 124
        line 2071: 140
        line 2072: 156
        line 2073: 172
        line 2075: 188
        line 2076: 201
        line 2077: 217
        line 2078: 233
        line 2079: 249
      LocalVariableTable:
        Start  Length  Slot  Name   Signature
            0     265     0  this   Lscala/collection/immutable/NewVectorIterator;
            0     265     1    io   I
            0     265     2   xor   I
    MethodParameters:
      Name                           Flags
      io                             final
      xor                            final

  public scala.collection.Iterator<A> drop(int);
    descriptor: (I)Lscala/collection/Iterator;
    flags: (0x0001) ACC_PUBLIC
    Code:
      stack=4, locals=5, args_size=2
         0: iload_1
         1: iconst_0
         2: if_icmple     156
         5: aload_0
         6: getfield      #664                // Field scala$collection$immutable$NewVectorIterator$$i1:I
         9: aload_0
        10: getfield      #662                // Field scala$collection$immutable$NewVectorIterator$$len1:I
        13: isub
        14: aload_0
        15: getfield      #747                // Field totalLength:I
        18: iadd
        19: iload_1
        20: iadd
        21: aload_0
        22: getfield      #747                // Field totalLength:I
        25: invokestatic  #762                // Method java/lang/Math.min:(II)I
        28: istore_2
        29: iload_2
        30: aload_0
        31: getfield      #747                // Field totalLength:I
        34: if_icmpne     55
        37: aload_0
        38: iconst_0
        39: putfield      #664                // Field scala$collection$immutable$NewVectorIterator$$i1:I
        42: aload_0
        43: iconst_0
        44: putfield      #662                // Field scala$collection$immutable$NewVectorIterator$$len1:I
        47: aload_0
        48: iconst_0
        49: putfield      #670                // Field a1len:I
        52: goto          156
        55: iload_2
        56: aload_0
        57: getfield      #701                // Field sliceEnd:I
        60: if_icmplt     70
        63: aload_0
        64: invokespecial #755                // Method advanceSlice:()V
        67: goto          55
        70: iload_2
        71: aload_0
        72: getfield      #703                // Field sliceStart:I
        75: isub
        76: istore_3
        77: aload_0
        78: getfield      #718                // Field sliceDim:I
        81: iconst_1
        82: if_icmple     105
        85: aload_0
        86: getfield      #749                // Field oldPos:I
        89: iload_3
        90: ixor
        91: istore        4
        93: aload_0
        94: iload_3
        95: iload         4
        97: invokespecial #774                // Method setA:(II)V
       100: aload_0
       101: iload_3
       102: putfield      #749                // Field oldPos:I
       105: aload_0
       106: aload_0
       107: getfield      #676                // Field a1:[Ljava/lang/Object;
       110: arraylength
       111: putfield      #670                // Field a1len:I
       114: aload_0
       115: iload_3
       116: bipush        31
       118: iand
       119: putfield      #664                // Field scala$collection$immutable$NewVectorIterator$$i1:I
       122: aload_0
       123: aload_0
       124: getfield      #664                // Field scala$collection$immutable$NewVectorIterator$$i1:I
       127: aload_0
       128: getfield      #747                // Field totalLength:I
       131: iload_2
       132: isub
       133: iadd
       134: putfield      #662                // Field scala$collection$immutable$NewVectorIterator$$len1:I
       137: aload_0
       138: getfield      #670                // Field a1len:I
       141: aload_0
       142: getfield      #662                // Field scala$collection$immutable$NewVectorIterator$$len1:I
       145: if_icmple     156
       148: aload_0
       149: aload_0
       150: getfield      #662                // Field scala$collection$immutable$NewVectorIterator$$len1:I
       153: putfield      #670                // Field a1len:I
       156: aload_0
       157: areturn
      StackMapTable: number_of_entries = 4
        frame_type = 252 /* append */
          offset_delta = 55
          locals = [ int ]
        frame_type = 14 /* same */
        frame_type = 252 /* append */
          offset_delta = 34
          locals = [ int ]
        frame_type = 249 /* chop */
          offset_delta = 50
      LineNumberTable:
        line 2084: 0
        line 2085: 5
        line 2086: 19
        line 2087: 29
        line 2088: 37
        line 2089: 42
        line 2090: 47
        line 2092: 55
        line 2093: 70
        line 2094: 77
        line 2095: 85
        line 2096: 93
        line 2097: 100
        line 2099: 105
        line 2100: 114
        line 2101: 122
        line 2102: 137
        line 2105: 156
      LocalVariableTable:
        Start  Length  Slot  Name   Signature
           93      12     4   xor   I
           77      79     3    io   I
           29     127     2 newpos   I
            0     158     0  this   Lscala/collection/immutable/NewVectorIterator;
            0     158     1     n   I
    Signature: #772                         // (I)Lscala/collection/Iterator<TA;>;
    MethodParameters:
      Name                           Flags
      n                              final

  public scala.collection.Iterator<A> take(int);
    descriptor: (I)Lscala/collection/Iterator;
    flags: (0x0001) ACC_PUBLIC
    Code:
      stack=3, locals=3, args_size=2
         0: iload_1
         1: aload_0
         2: getfield      #662                // Field scala$collection$immutable$NewVectorIterator$$len1:I
         5: aload_0
         6: getfield      #664                // Field scala$collection$immutable$NewVectorIterator$$i1:I
         9: isub
        10: if_icmpge     87
        13: aload_0
        14: getfield      #662                // Field scala$collection$immutable$NewVectorIterator$$len1:I
        17: aload_0
        18: getfield      #664                // Field scala$collection$immutable$NewVectorIterator$$i1:I
        21: isub
        22: iconst_0
        23: iload_1
        24: invokestatic  #778                // Method java/lang/Math.max:(II)I
        27: isub
        28: istore_2
        29: aload_0
        30: aload_0
        31: getfield      #747                // Field totalLength:I
        34: iload_2
        35: isub
        36: putfield      #747                // Field totalLength:I
        39: aload_0
        40: aload_0
        41: getfield      #662                // Field scala$collection$immutable$NewVectorIterator$$len1:I
        44: iload_2
        45: isub
        46: putfield      #662                // Field scala$collection$immutable$NewVectorIterator$$len1:I
        49: aload_0
        50: getfield      #662                // Field scala$collection$immutable$NewVectorIterator$$len1:I
        53: aload_0
        54: getfield      #670                // Field a1len:I
        57: if_icmpge     68
        60: aload_0
        61: aload_0
        62: getfield      #662                // Field scala$collection$immutable$NewVectorIterator$$len1:I
        65: putfield      #670                // Field a1len:I
        68: aload_0
        69: getfield      #747                // Field totalLength:I
        72: aload_0
        73: getfield      #701                // Field sliceEnd:I
        76: if_icmpge     87
        79: aload_0
        80: aload_0
        81: getfield      #747                // Field totalLength:I
        84: putfield      #701                // Field sliceEnd:I
        87: aload_0
        88: areturn
      StackMapTable: number_of_entries = 2
        frame_type = 252 /* append */
          offset_delta = 68
          locals = [ int ]
        frame_type = 250 /* chop */
          offset_delta = 18
      LineNumberTable:
        line 2109: 0
        line 1987: 1
        line 2109: 10
        line 1987: 13
        line 2110: 22
        line 2111: 29
        line 2112: 39
        line 2113: 49
        line 2114: 68
        line 2116: 87
      LocalVariableTable:
        Start  Length  Slot  Name   Signature
           29      58     2 trunc   I
            0      89     0  this   Lscala/collection/immutable/NewVectorIterator;
            0      89     1     n   I
    Signature: #772                         // (I)Lscala/collection/Iterator<TA;>;
    MethodParameters:
      Name                           Flags
      n                              final

  public scala.collection.Iterator<A> slice(int, int);
    descriptor: (II)Lscala/collection/Iterator;
    flags: (0x0001) ACC_PUBLIC
    Code:
      stack=2, locals=4, args_size=3
         0: iload_1
         1: iconst_0
         2: if_icmple     17
         5: aload_0
         6: iload_1
         7: invokevirtual #781                // Method drop:(I)Lscala/collection/Iterator;
        10: pop
        11: iload_2
        12: iload_1
        13: isub
        14: goto          18
        17: iload_2
        18: istore_3
        19: aload_0
        20: iload_3
        21: invokevirtual #783                // Method take:(I)Lscala/collection/Iterator;
        24: areturn
      StackMapTable: number_of_entries = 2
        frame_type = 17 /* same */
        frame_type = 64 /* same_locals_1_stack_item */
          stack = [ int ]
      LineNumberTable:
        line 2121: 0
        line 2122: 5
        line 2123: 11
        line 2124: 17
        line 2125: 19
      LocalVariableTable:
        Start  Length  Slot  Name   Signature
           19       5     3 _until   I
            0      25     0  this   Lscala/collection/immutable/NewVectorIterator;
            0      25     1  from   I
            0      25     2 until   I
    Signature: #252                         // (II)Lscala/collection/Iterator<TA;>;
    MethodParameters:
      Name                           Flags
      from                           final
      until                          final

  public <B extends java.lang.Object> int copyToArray(java.lang.Object, int, int);
    descriptor: (Ljava/lang/Object;II)I
    flags: (0x0001) ACC_PUBLIC
    Code:
      stack=6, locals=14, args_size=4
         0: aload_1
         1: invokestatic  #791                // Method java/lang/reflect/Array.getLength:(Ljava/lang/Object;)I
         4: istore        7
         6: getstatic     #796                // Field scala/collection/IterableOnce$.MODULE$:Lscala/collection/IterableOnce$;
         9: pop
        10: aload_0
        11: getfield      #662                // Field scala$collection$immutable$NewVectorIterator$$len1:I
        14: aload_0
        15: getfield      #664                // Field scala$collection$immutable$NewVectorIterator$$i1:I
        18: isub
        19: istore        8
        21: getstatic     #801                // Field scala/math/package$.MODULE$:Lscala/math/package$;
        24: pop
        25: getstatic     #801                // Field scala/math/package$.MODULE$:Lscala/math/package$;
        28: pop
        29: getstatic     #801                // Field scala/math/package$.MODULE$:Lscala/math/package$;
        32: pop
        33: iload_3
        34: iload         8
        36: invokestatic  #762                // Method java/lang/Math.min:(II)I
        39: istore        9
        41: iload         7
        43: iload_2
        44: isub
        45: istore        10
        47: iload         9
        49: iload         10
        51: invokestatic  #762                // Method java/lang/Math.min:(II)I
        54: istore        11
        56: iconst_0
        57: istore        12
        59: iload         11
        61: iload         12
        63: invokestatic  #778                // Method java/lang/Math.max:(II)I
        66: istore        13
        68: iconst_0
        69: istore        4
        71: aload_1
        72: instanceof    #753                // class "[Ljava/lang/Object;"
        75: istore        5
        77: iload         4
        79: iload         13
        81: if_icmpge     187
        84: aload_0
        85: getfield      #664                // Field scala$collection$immutable$NewVectorIterator$$i1:I
        88: aload_0
        89: getfield      #670                // Field a1len:I
        92: if_icmpne     99
        95: aload_0
        96: invokespecial #674                // Method advance:()V
        99: iload         13
       101: iload         4
       103: isub
       104: aload_0
       105: getfield      #676                // Field a1:[Ljava/lang/Object;
       108: arraylength
       109: aload_0
       110: getfield      #664                // Field scala$collection$immutable$NewVectorIterator$$i1:I
       113: isub
       114: invokestatic  #762                // Method java/lang/Math.min:(II)I
       117: istore        6
       119: iload         5
       121: ifeq          145
       124: aload_0
       125: getfield      #676                // Field a1:[Ljava/lang/Object;
       128: aload_0
       129: getfield      #664                // Field scala$collection$immutable$NewVectorIterator$$i1:I
       132: aload_1
       133: iload_2
       134: iload         4
       136: iadd
       137: iload         6
       139: invokestatic  #807                // Method java/lang/System.arraycopy:(Ljava/lang/Object;ILjava/lang/Object;II)V
       142: goto          166
       145: getstatic     #812                // Field scala/Array$.MODULE$:Lscala/Array$;
       148: aload_0
       149: getfield      #676                // Field a1:[Ljava/lang/Object;
       152: aload_0
       153: getfield      #664                // Field scala$collection$immutable$NewVectorIterator$$i1:I
       156: aload_1
       157: iload_2
       158: iload         4
       160: iadd
       161: iload         6
       163: invokevirtual #815                // Method scala/Array$.copy:(Ljava/lang/Object;ILjava/lang/Object;II)V
       166: aload_0
       167: aload_0
       168: getfield      #664                // Field scala$collection$immutable$NewVectorIterator$$i1:I
       171: iload         6
       173: iadd
       174: putfield      #664                // Field scala$collection$immutable$NewVectorIterator$$i1:I
       177: iload         4
       179: iload         6
       181: iadd
       182: istore        4
       184: goto          77
       187: iload         13
       189: ireturn
      StackMapTable: number_of_entries = 5
        frame_type = 255 /* full_frame */
          offset_delta = 77
          locals = [ class scala/collection/immutable/NewVectorIterator, class java/lang/Object, int, int, int, int, top, int, int, int, int, int, int, int ]
          stack = []
        frame_type = 21 /* same */
        frame_type = 255 /* full_frame */
          offset_delta = 45
          locals = [ class scala/collection/immutable/NewVectorIterator, class java/lang/Object, int, int, int, int, int, int, int, int, int, int, int, int ]
          stack = []
        frame_type = 20 /* same */
        frame_type = 255 /* full_frame */
          offset_delta = 20
          locals = [ class scala/collection/immutable/NewVectorIterator, class java/lang/Object, int, int, int, int, top, int, int, int, int, int, int, int ]
          stack = []
      LineNumberTable:
        line 2129: 0
        line 2130: 6
        line 1987: 10
        line 2130: 21
        line 2131: 68
        line 2132: 71
        line 2133: 77
        line 2134: 84
        line 2135: 99
        line 2136: 119
        line 2137: 145
        line 2138: 166
        line 2139: 177
        line 2133: 184
        line 2141: 187
      LocalVariableTable:
        Start  Length  Slot  Name   Signature
          119      65     6 count   I
           71     118     4 copied   I
           77     112     5 isBoxed   Z
            0     190     0  this   Lscala/collection/immutable/NewVectorIterator;
            0     190     1    xs   Ljava/lang/Object;
            0     190     2 start   I
            0     190     3   len   I
           47       9    10 elemsToCopyToArray_min_y   I
           59       9    12 elemsToCopyToArray_max_y   I
    Signature: #786                         // <B:Ljava/lang/Object;>(Ljava/lang/Object;II)I
    MethodParameters:
      Name                           Flags
      xs                             final
      start                          final
      len                            final

  public scala.collection.immutable.Vector<A> toVector();
    descriptor: ()Lscala/collection/immutable/Vector;
    flags: (0x0001) ACC_PUBLIC
    Code:
      stack=3, locals=1, args_size=1
         0: aload_0
         1: getfield      #693                // Field v:Lscala/collection/immutable/Vector;
         4: aload_0
         5: getfield      #664                // Field scala$collection$immutable$NewVectorIterator$$i1:I
         8: aload_0
         9: getfield      #662                // Field scala$collection$immutable$NewVectorIterator$$len1:I
        12: isub
        13: aload_0
        14: getfield      #747                // Field totalLength:I
        17: iadd
        18: aload_0
        19: getfield      #747                // Field totalLength:I
        22: invokevirtual #825                // Method scala/collection/immutable/Vector.slice:(II)Ljava/lang/Object;
        25: checkcast     #695                // class scala/collection/immutable/Vector
        28: areturn
      LineNumberTable:
        line 2145: 0
      LocalVariableTable:
        Start  Length  Slot  Name   Signature
            0      29     0  this   Lscala/collection/immutable/NewVectorIterator;
    Signature: #822                         // ()Lscala/collection/immutable/Vector<TA;>;

  public scala.collection.immutable.NewVectorIterator<A> split(int);
    descriptor: (I)Lscala/collection/immutable/NewVectorIterator;
    flags: (0x0001) ACC_PUBLIC
    Code:
      stack=2, locals=3, args_size=2
         0: aload_0
         1: invokevirtual #832                // Method clone:()Ljava/lang/Object;
         4: checkcast     #2                  // class scala/collection/immutable/NewVectorIterator
         7: astore_2
         8: aload_2
         9: iload_1
        10: invokevirtual #783                // Method take:(I)Lscala/collection/Iterator;
        13: pop
        14: aload_0
        15: iload_1
        16: invokevirtual #781                // Method drop:(I)Lscala/collection/Iterator;
        19: pop
        20: aload_2
        21: areturn
      LineNumberTable:
        line 2148: 0
        line 2149: 8
        line 2150: 14
        line 2151: 20
      LocalVariableTable:
        Start  Length  Slot  Name   Signature
            8      13     2   it2   Lscala/collection/immutable/NewVectorIterator;
            0      22     0  this   Lscala/collection/immutable/NewVectorIterator;
            0      22     1    at   I
    Signature: #828                         // (I)Lscala/collection/immutable/NewVectorIterator<TA;>;
    MethodParameters:
      Name                           Flags
      at                             final

  public java.lang.Object tapEach(scala.Function1);
    descriptor: (Lscala/Function1;)Ljava/lang/Object;
    flags: (0x1041) ACC_PUBLIC, ACC_BRIDGE, ACC_SYNTHETIC
    Code:
      stack=2, locals=2, args_size=2
         0: aload_0
         1: aload_1
         2: invokevirtual #836                // Method tapEach:(Lscala/Function1;)Lscala/collection/Iterator;
         5: areturn
      LineNumberTable:
        line 1966: 0
      LocalVariableTable:
        Start  Length  Slot  Name   Signature
            0       6     0  this   Lscala/collection/immutable/NewVectorIterator;
            0       6     1     f   Lscala/Function1;
    MethodParameters:
      Name                           Flags
      f                              final

  public java.lang.Object zipWithIndex();
    descriptor: ()Ljava/lang/Object;
    flags: (0x1041) ACC_PUBLIC, ACC_BRIDGE, ACC_SYNTHETIC
    Code:
      stack=1, locals=1, args_size=1
         0: aload_0
         1: invokevirtual #838                // Method zipWithIndex:()Lscala/collection/Iterator;
         4: areturn
      LineNumberTable:
        line 1966: 0
      LocalVariableTable:
        Start  Length  Slot  Name   Signature
            0       5     0  this   Lscala/collection/immutable/NewVectorIterator;

  public java.lang.Object dropWhile(scala.Function1);
    descriptor: (Lscala/Function1;)Ljava/lang/Object;
    flags: (0x1041) ACC_PUBLIC, ACC_BRIDGE, ACC_SYNTHETIC
    Code:
      stack=2, locals=2, args_size=2
         0: aload_0
         1: aload_1
         2: invokevirtual #840                // Method dropWhile:(Lscala/Function1;)Lscala/collection/Iterator;
         5: areturn
      LineNumberTable:
        line 1966: 0
      LocalVariableTable:
        Start  Length  Slot  Name   Signature
            0       6     0  this   Lscala/collection/immutable/NewVectorIterator;
            0       6     1     p   Lscala/Function1;
    MethodParameters:
      Name                           Flags
      p                              final

  public java.lang.Object takeWhile(scala.Function1);
    descriptor: (Lscala/Function1;)Ljava/lang/Object;
    flags: (0x1041) ACC_PUBLIC, ACC_BRIDGE, ACC_SYNTHETIC
    Code:
      stack=2, locals=2, args_size=2
         0: aload_0
         1: aload_1
         2: invokevirtual #842                // Method takeWhile:(Lscala/Function1;)Lscala/collection/Iterator;
         5: areturn
      LineNumberTable:
        line 1966: 0
      LocalVariableTable:
        Start  Length  Slot  Name   Signature
            0       6     0  this   Lscala/collection/immutable/NewVectorIterator;
            0       6     1     p   Lscala/Function1;
    MethodParameters:
      Name                           Flags
      p                              final

  public java.lang.Object flatten(scala.Function1);
    descriptor: (Lscala/Function1;)Ljava/lang/Object;
    flags: (0x1041) ACC_PUBLIC, ACC_BRIDGE, ACC_SYNTHETIC
    Code:
      stack=2, locals=2, args_size=2
         0: aload_0
         1: aload_1
         2: invokevirtual #845                // Method flatten:(Lscala/Function1;)Lscala/collection/Iterator;
         5: areturn
      LineNumberTable:
        line 1966: 0
      LocalVariableTable:
        Start  Length  Slot  Name   Signature
            0       6     0  this   Lscala/collection/immutable/NewVectorIterator;
            0       6     1 asIterable   Lscala/Function1;
    MethodParameters:
      Name                           Flags
      asIterable                     final

  public java.lang.Object flatMap(scala.Function1);
    descriptor: (Lscala/Function1;)Ljava/lang/Object;
    flags: (0x1041) ACC_PUBLIC, ACC_BRIDGE, ACC_SYNTHETIC
    Code:
      stack=2, locals=2, args_size=2
         0: aload_0
         1: aload_1
         2: invokevirtual #847                // Method flatMap:(Lscala/Function1;)Lscala/collection/Iterator;
         5: areturn
      LineNumberTable:
        line 1966: 0
      LocalVariableTable:
        Start  Length  Slot  Name   Signature
            0       6     0  this   Lscala/collection/immutable/NewVectorIterator;
            0       6     1     f   Lscala/Function1;
    MethodParameters:
      Name                           Flags
      f                              final

  public java.lang.Object map(scala.Function1);
    descriptor: (Lscala/Function1;)Ljava/lang/Object;
    flags: (0x1041) ACC_PUBLIC, ACC_BRIDGE, ACC_SYNTHETIC
    Code:
      stack=2, locals=2, args_size=2
         0: aload_0
         1: aload_1
         2: invokevirtual #849                // Method map:(Lscala/Function1;)Lscala/collection/Iterator;
         5: areturn
      LineNumberTable:
        line 1966: 0
      LocalVariableTable:
        Start  Length  Slot  Name   Signature
            0       6     0  this   Lscala/collection/immutable/NewVectorIterator;
            0       6     1     f   Lscala/Function1;
    MethodParameters:
      Name                           Flags
      f                              final

  public java.lang.Object collect(scala.PartialFunction);
    descriptor: (Lscala/PartialFunction;)Ljava/lang/Object;
    flags: (0x1041) ACC_PUBLIC, ACC_BRIDGE, ACC_SYNTHETIC
    Code:
      stack=2, locals=2, args_size=2
         0: aload_0
         1: aload_1
         2: invokevirtual #852                // Method collect:(Lscala/PartialFunction;)Lscala/collection/Iterator;
         5: areturn
      LineNumberTable:
        line 1966: 0
      LocalVariableTable:
        Start  Length  Slot  Name   Signature
            0       6     0  this   Lscala/collection/immutable/NewVectorIterator;
            0       6     1    pf   Lscala/PartialFunction;
    MethodParameters:
      Name                           Flags
      pf                             final

  public java.lang.Object filterNot(scala.Function1);
    descriptor: (Lscala/Function1;)Ljava/lang/Object;
    flags: (0x1041) ACC_PUBLIC, ACC_BRIDGE, ACC_SYNTHETIC
    Code:
      stack=2, locals=2, args_size=2
         0: aload_0
         1: aload_1
         2: invokevirtual #855                // Method filterNot:(Lscala/Function1;)Lscala/collection/Iterator;
         5: areturn
      LineNumberTable:
        line 1966: 0
      LocalVariableTable:
        Start  Length  Slot  Name   Signature
            0       6     0  this   Lscala/collection/immutable/NewVectorIterator;
            0       6     1  pred   Lscala/Function1;
    MethodParameters:
      Name                           Flags
      pred                           final

  public java.lang.Object filter(scala.Function1);
    descriptor: (Lscala/Function1;)Ljava/lang/Object;
    flags: (0x1041) ACC_PUBLIC, ACC_BRIDGE, ACC_SYNTHETIC
    Code:
      stack=2, locals=2, args_size=2
         0: aload_0
         1: aload_1
         2: invokevirtual #857                // Method filter:(Lscala/Function1;)Lscala/collection/Iterator;
         5: areturn
      LineNumberTable:
        line 1966: 0
      LocalVariableTable:
        Start  Length  Slot  Name   Signature
            0       6     0  this   Lscala/collection/immutable/NewVectorIterator;
            0       6     1     p   Lscala/Function1;
    MethodParameters:
      Name                           Flags
      p                              final

  public java.lang.Object scanLeft(java.lang.Object, scala.Function2);
    descriptor: (Ljava/lang/Object;Lscala/Function2;)Ljava/lang/Object;
    flags: (0x1041) ACC_PUBLIC, ACC_BRIDGE, ACC_SYNTHETIC
    Code:
      stack=3, locals=3, args_size=3
         0: aload_0
         1: aload_1
         2: aload_2
         3: invokevirtual #859                // Method scanLeft:(Ljava/lang/Object;Lscala/Function2;)Lscala/collection/Iterator;
         6: areturn
      LineNumberTable:
        line 1966: 0
      LocalVariableTable:
        Start  Length  Slot  Name   Signature
            0       7     0  this   Lscala/collection/immutable/NewVectorIterator;
            0       7     1     z   Ljava/lang/Object;
            0       7     2    op   Lscala/Function2;
    MethodParameters:
      Name                           Flags
      z                              final
      op                             final

  public java.lang.Object slice(int, int);
    descriptor: (II)Ljava/lang/Object;
    flags: (0x1041) ACC_PUBLIC, ACC_BRIDGE, ACC_SYNTHETIC
    Code:
      stack=3, locals=3, args_size=3
         0: aload_0
         1: iload_1
         2: iload_2
         3: invokevirtual #861                // Method slice:(II)Lscala/collection/Iterator;
         6: areturn
      LineNumberTable:
        line 1966: 0
      LocalVariableTable:
        Start  Length  Slot  Name   Signature
            0       7     0  this   Lscala/collection/immutable/NewVectorIterator;
            0       7     1  from   I
            0       7     2 until   I
    MethodParameters:
      Name                           Flags
      from                           final
      until                          final

  public java.lang.Object take(int);
    descriptor: (I)Ljava/lang/Object;
    flags: (0x1041) ACC_PUBLIC, ACC_BRIDGE, ACC_SYNTHETIC
    Code:
      stack=2, locals=2, args_size=2
         0: aload_0
         1: iload_1
         2: invokevirtual #783                // Method take:(I)Lscala/collection/Iterator;
         5: areturn
      LineNumberTable:
        line 1966: 0
      LocalVariableTable:
        Start  Length  Slot  Name   Signature
            0       6     0  this   Lscala/collection/immutable/NewVectorIterator;
            0       6     1     n   I
    MethodParameters:
      Name                           Flags
      n                              final

  public java.lang.Object drop(int);
    descriptor: (I)Ljava/lang/Object;
    flags: (0x1041) ACC_PUBLIC, ACC_BRIDGE, ACC_SYNTHETIC
    Code:
      stack=2, locals=2, args_size=2
         0: aload_0
         1: iload_1
         2: invokevirtual #781                // Method drop:(I)Lscala/collection/Iterator;
         5: areturn
      LineNumberTable:
        line 1966: 0
      LocalVariableTable:
        Start  Length  Slot  Name   Signature
            0       6     0  this   Lscala/collection/immutable/NewVectorIterator;
            0       6     1     n   I
    MethodParameters:
      Name                           Flags
      n                              final

  public scala.collection.immutable.NewVectorIterator(scala.collection.immutable.Vector<A>, int, int);
    descriptor: (Lscala/collection/immutable/Vector;II)V
    flags: (0x0001) ACC_PUBLIC
    Code:
      stack=2, locals=4, args_size=4
         0: aload_0
         1: aload_1
         2: putfield      #693                // Field v:Lscala/collection/immutable/Vector;
         5: aload_0
         6: iload_2
         7: putfield      #747                // Field totalLength:I
        10: aload_0
        11: iload_3
        12: putfield      #710                // Field sliceCount:I
        15: aload_0
        16: invokespecial #866                // Method java/lang/Object."<init>":()V
        19: aload_0
        20: aload_1
        21: invokevirtual #870                // Method scala/collection/immutable/Vector.prefix1:()[Ljava/lang/Object;
        24: putfield      #676                // Field a1:[Ljava/lang/Object;
        27: aload_0
        28: aload_0
        29: getfield      #676                // Field a1:[Ljava/lang/Object;
        32: arraylength
        33: putfield      #670                // Field a1len:I
        36: aload_0
        37: iconst_0
        38: putfield      #664                // Field scala$collection$immutable$NewVectorIterator$$i1:I
        41: aload_0
        42: iconst_0
        43: putfield      #749                // Field oldPos:I
        46: aload_0
        47: aload_0
        48: getfield      #747                // Field totalLength:I
        51: putfield      #662                // Field scala$collection$immutable$NewVectorIterator$$len1:I
        54: aload_0
        55: iconst_0
        56: putfield      #691                // Field sliceIdx:I
        59: aload_0
        60: iconst_1
        61: putfield      #718                // Field sliceDim:I
        64: aload_0
        65: iconst_0
        66: putfield      #703                // Field sliceStart:I
        69: aload_0
        70: aload_0
        71: getfield      #670                // Field a1len:I
        74: putfield      #701                // Field sliceEnd:I
        77: return
      LineNumberTable:
        line 1966: 0
        line 1968: 19
        line 1974: 27
        line 1975: 36
        line 1976: 41
        line 1977: 46
        line 1979: 54
        line 1980: 59
        line 1981: 64
        line 1982: 69
        line 1966: 77
      LocalVariableTable:
        Start  Length  Slot  Name   Signature
            0      78     0  this   Lscala/collection/immutable/NewVectorIterator;
            0      78     1     v   Lscala/collection/immutable/Vector;
            0      78     2 totalLength   I
            0      78     3 sliceCount   I
    Signature: #864                         // (Lscala/collection/immutable/Vector<TA;>;II)V
    MethodParameters:
      Name                           Flags
      v                              final
      totalLength                    final
      sliceCount                     final
}
InnerClasses:
  public #16= #15 of #7;                  // GroupedIterator=class scala/collection/Iterator$GroupedIterator of class scala/collection/Iterator
Signature: #3                           // <A:Ljava/lang/Object;>Ljava/lang/Object;Lscala/collection/Iterator<TA;>;Ljava/lang/Cloneable;
SourceFile: "Vector.scala"
RuntimeVisibleAnnotations:
  0: #11(#12=s#13)
    scala.reflect.ScalaSignature(
      bytes="\u0006\u0005\u0005\u001de\u0001\u0002\u0011\"\r!B\u0001\"\u0012\u0001\u0003\u0002\u0003\u0006IA\u0012\u0005\t\u0015\u0002\u0011\t\u0011)Q\u0005\u0017\"Aa\n\u0001B\u0001B\u0003%1\nC\u0003P\u0001\u0011\u0005\u0001\u000b\u0003\u0004V\u0001\u0001\u0006KA\u0016\u0005\nM\u0002\u0001\r\u0011!Q!\n\u001dD\u0011B\u001b\u0001A\u0002\u0003\u0005\u000b\u0015B6\t\u00139\u0004\u0001\u0019!A!B\u0013y\u0007\"\u0003:\u0001\u0001\u0004\u0005\t\u0015)\u0003t\u0011%1\b\u00011A\u0001B\u0003&q\u000f\u0003\u0004{\u0001\u0001\u0006Ka\u0013\u0005\rw\u0002!\t\u0011!B\u0001\u0002\u0003\u0006Ka\u0013\u0005\u0007y\u0002\u0001\u000b\u0015B&\t\u0019u\u0004A\u0011!A\u0003\u0002\u0003\u0005\u000b\u0015B&\t\ry\u0004\u0001\u0015)\u0003L\u0011\u0019y\b\u0001)Q\u0005\u0017\"9\u0011\u0011\u0001\u0001!B\u0013Y\u0005bBA\u0002\u0001\u0001\u0006Ka\u0013\u0005\b\u0003\u000b\u0001A\u0011IA\u0004\u0011\u001d\t\t\u0002\u0001C\u0001\u0003\'Aq!!\b\u0001\t\u0003\ty\u0002\u0003\u0005\u0002\"\u0001\u0001K\u0011BA\u0012\u0011!\tY\u0003\u0001Q\u0005\n\u0005\r\u0002\u0002CA\u0017\u0001\u0001&I!a\f\t\u0011\u0005e\u0002\u0001)C\u0005\u0003wAq!!\u0011\u0001\t\u0003\n\u0019\u0005C\u0004\u0002J\u0001!\t%a\u0013\t\u000f\u0005=\u0003\u0001\"\u0011\u0002R!9\u00111\f\u0001\u0005B\u0005u\u0003bBA>\u0001\u0011\u0005\u0013Q\u0010\u0005\t\u0003\u007f\u0002A\u0011C\u0011\u0002\u0002\n\tb*Z<WK\u000e$xN]%uKJ\fGo\u001c:\u000b\u0005\t\u001a\u0013!C5n[V$\u0018M\u00197f\u0015\t!S%\u0001\u0006d_2dWm\u0019;j_:T\u0011AJ\u0001\u0006g\u000e\fG.Y\u0002\u0001+\tICg\u0005\u0003\u0001U9j\u0004CA\u0016-\u001b\u0005)\u0013BA\u0017&\u0005\u0019\te.\u001f*fMB\u0019q\u0006\r\u001a\u000e\u0003\rJ!!M\u0012\u0003\u0011%#XM]1u_J\u0004\"a\r\u001b\r\u0001\u0011)Q\u0007\u0001b\u0001m\t\t\u0011)\u0005\u00028uA\u00111\u0006O\u0005\u0003s\u0015\u0012qAT8uQ&tw\r\u0005\u0002,w%\u0011A(\n\u0002\u0004\u0003:L\bC\u0001 D\u001b\u0005y$B\u0001!B\u0003\u0011a\u0017M\\4\u000b\u0003\t\u000bAA[1wC&\u0011Ai\u0010\u0002\n\u00072|g.Z1cY\u0016\f\u0011A\u001e\t\u0004\u000f\"\u0013T\"A\u0011\n\u0005%\u000b#A\u0002,fGR|\'/A\u0006u_R\fG\u000eT3oORD\u0007CA\u0016M\u0013\tiUEA\u0002J]R\f!b\u001d7jG\u0016\u001cu.\u001e8u\u0003\u0019a\u0014N\\5u}Q!\u0011KU*U!\r9\u0005A\r\u0005\u0006\u000b\u0012\u0001\rA\u0012\u0005\u0006\u0015\u0012\u0001\ra\u0013\u0005\u0006\u001d\u0012\u0001\raS\u0001\u0003CF\u0002\"aV2\u000f\u0005a\u000bgBA-a\u001d\tQvL\u0004\u0002\\=6\tAL\u0003\u0002^O\u00051AH]8pizJ\u0011AJ\u0005\u0003I\u0015J!AI\u0012\n\u0005\t\f\u0013\u0001\u0004,fGR|\'/\u00138mS:,\u0017B\u00013f\u0005\u0011\t%O]\u0019\u000b\u0005\t\f\u0013AA13!\t9\u0006.\u0003\u0002jK\n!\u0011I\u001d:3\u0003\t\t7\u0007\u0005\u0002XY&\u0011Q.\u001a\u0002\u0005\u0003J\u00148\'\u0001\u0002biA\u0011q\u000b]\u0005\u0003c\u0016\u0014A!\u0011:si\u0005\u0011\u0011-\u000e\t\u0003/RL!!^3\u0003\t\u0005\u0013(/N\u0001\u0003CZ\u0002\"a\u0016=\n\u0005e,\'\u0001B!seZ\nQ!Y\u0019mK:\f\u0001g]2bY\u0006$3m\u001c7mK\u000e$\u0018n\u001c8%S6lW\u000f^1cY\u0016$c*Z<WK\u000e$xN]%uKJ\fGo\u001c:%I%\f\u0014AB8mIB{7/\u0001\u001atG\u0006d\u0017\rJ2pY2,7\r^5p]\u0012JW.\\;uC\ndW\r\n(foZ+7\r^8s\u0013R,\'/\u0019;pe\u0012\"C.\u001a82\u0003!\u0019H.[2f\u0013\u0012D\u0018\u0001C:mS\u000e,G)[7\u0002\u0015Md\u0017nY3Ti\u0006\u0014H/\u0001\u0005tY&\u001cW-\u00128e\u0003%Ygn\\<o\'&TX-F\u0001LQ\r\u0019\u00121\u0002\t\u0004W\u00055\u0011bAA\bK\t1\u0011N\u001c7j]\u0016\fq\u0001[1t\u001d\u0016DH/\u0006\u0002\u0002\u0016A\u00191&a\u0006\n\u0007\u0005eQEA\u0004C_>dW-\u00198)\u0007Q\tY!\u0001\u0003oKb$H#\u0001\u001a\u0002\u0019\u0005$g/\u00198dKNc\u0017nY3\u0015\u0005\u0005\u0015\u0002cA\u0016\u0002(%\u0019\u0011\u0011F\u0013\u0003\tUs\u0017\u000e^\u0001\bC\u00124\u0018M\\2f\u0003!\tGM^1oG\u0016\fECBA\u0013\u0003c\t)\u0004\u0003\u0004\u00024a\u0001\raS\u0001\u0003S>Da!a\u000e\u0019\u0001\u0004Y\u0015a\u0001=pe\u0006!1/\u001a;B)\u0019\t)#!\u0010\u0002@!1\u00111G\rA\u0002-Ca!a\u000e\u001a\u0001\u0004Y\u0015\u0001\u00023s_B$2ALA#\u0011\u0019\t9E\u0007a\u0001\u0017\u0006\ta.\u0001\u0003uC.,Gc\u0001\u0018\u0002N!1\u0011qI\u000eA\u0002-\u000bQa\u001d7jG\u0016$RALA*\u0003/Ba!!\u0016\u001d\u0001\u0004Y\u0015\u0001\u00024s_6Da!!\u0017\u001d\u0001\u0004Y\u0015!B;oi&d\u0017aC2paf$v.\u0011:sCf,B!a\u0018\u0002nQ91*!\u0019\u0002t\u0005]\u0004bBA2;\u0001\u0007\u0011QM\u0001\u0003qN\u0004RaKA4\u0003WJ1!!\u001b&\u0005\u0015\t%O]1z!\r\u0019\u0014Q\u000e\u0003\b\u0003_j\"\u0019AA9\u0005\u0005\u0011\u0015C\u0001\u001a;\u0011\u0019\t)(\ba\u0001\u0017\u0006)1\u000f^1si\"1\u0011\u0011P\u000fA\u0002-\u000b1\u0001\\3o\u0003!!xNV3di>\u0014X#\u0001$\u0002\u000bM\u0004H.\u001b;\u0015\u0007E\u000b\u0019\t\u0003\u0004\u0002\u0006~\u0001\raS\u0001\u0003CR\u0004"
    )
  ScalaInlineInfo: length = 0x275 (unknown attribute)
   01 01 00 7D 01 7F 01 70 05 01 7B 01 70 05 00 EA
   00 E2 05 02 E6 03 5F 01 02 29 02 35 05 02 29 02
   31 05 02 29 02 2A 01 02 9F 02 A0 01 02 F4 02 F5
   01 02 A6 02 A0 01 02 09 02 0A 01 00 49 00 4A 01
   00 BF 03 52 01 00 BF 00 C0 01 02 02 02 03 01 00
   E1 00 E2 01 00 41 00 42 01 01 BB 00 94 01 01 BB
   00 9A 01 01 BB 03 11 01 01 B2 01 B3 05 02 12 02
   13 01 01 61 01 62 01 00 C8 00 34 01 00 CC 00 A8
   01 03 02 03 5E 01 03 02 03 03 01 00 F2 03 42 01
   00 F2 00 A8 01 01 20 01 21 01 01 5D 01 57 01 00
   A7 03 42 01 00 A7 00 A8 01 00 B2 00 B3 01 00 AE
   03 42 01 00 AE 00 A8 01 01 68 01 69 01 00 D7 03
   42 01 00 D7 00 A8 01 00 DC 03 42 01 00 DC 00 A8
   01 01 83 01 70 01 01 6F 01 70 01 01 76 01 70 01
   01 56 01 57 01 01 4F 01 50 01 00 61 00 62 01 00
   2B 00 2C 05 02 99 00 2C 05 00 93 00 94 01 00 93
   00 9A 01 00 87 00 88 01 00 8F 00 72 01 00 A3 00
   2C 01 01 4A 00 2C 01 00 33 00 34 05 02 94 00 72
   05 00 9F 00 72 05 00 D2 03 42 01 00 D2 00 A8 01
   01 E3 01 D4 01 01 EB 01 EC 01 01 F3 01 F4 01 01
   E7 01 DD 01 01 D3 01 D4 01 01 FA 01 EC 01 01 FE
   01 F4 01 01 DC 01 DD 01 02 19 01 37 05 02 19 02
   22 05 02 19 02 1A 01 02 9A 02 9B 01 00 3A 00 3B
   01 01 AA 00 2C 01 00 50 00 51 01 00 58 00 59 01
   01 27 01 28 01 01 CF 01 C7 01 01 88 01 89 01 01
   96 01 89 01 01 A0 01 90 01 01 8F 01 90 01 01 9B
   01 89 01 01 A5 01 90 01 02 82 02 83 01 01 19 01
   1A 01 00 78 01 70 01 00 78 00 79 01 00 82 00 79
   01 01 3C 00 34 01 03 01 02 F5 01 00 64 00 72 01
   02 EE 03 37 01 02 EE 00 FB 01 00 FA 00 FB 01 00
   69 00 6A 01 00 71 00 72 01 00 F6 00 59 01 03 3A
   03 3B 01 01 40 01 41 01 02 89 02 8A 01 01 C6 01
   C7 01 03 08 03 5E 01 03 08 03 03 01 00 EE 03 42
   01 00 EE 00 A8 01 01 31 03 42 01 01 31 00 A8 01
   02 39 02 3A 01 02 79 02 7A 01 02 72 02 73 05 02
   64 02 65 01 02 42 00 34 05 02 47 02 48 01 02 4E
   02 4F 01 02 5D 02 5E 01 02 56 02 57 01 02 6B 02
   6C 05 01 36 01 37 01 03 34 03 35 01 00 BB 00 A8
   01 01 02 01 03 01 01 0B 01 0C 01 01 14 02 9B 01
   01 14 00 34 01
  ScalaSig: length = 0x3 (unknown attribute)
   05 02 00
