Classfile /Users/mw/Projects/slang-braindump/.jar/jar8/assemble/slang-braindump/assemble/content/scala/collection/immutable/NumericRange$NumericRangeIterator.class
  Last modified May 29, 2022; size 2662 bytes
  SHA-256 checksum f3f67a7b2b2dc90a61d55d4a790b9794df227faa1bd47a08c30da1206de12f82
  Compiled from "NumericRange.scala"
public final class scala.collection.immutable.NumericRange$NumericRangeIterator<T extends java.lang.Object> extends scala.collection.AbstractIterator<T> implements java.io.Serializable
  minor version: 0
  major version: 52
  flags: (0x0031) ACC_PUBLIC, ACC_FINAL, ACC_SUPER
  this_class: #2                          // scala/collection/immutable/NumericRange$NumericRangeIterator
  super_class: #5                         // scala/collection/AbstractIterator
  interfaces: 1, fields: 6, methods: 4, attributes: 5
Constant pool:
    #1 = Utf8               scala/collection/immutable/NumericRange$NumericRangeIterator
    #2 = Class              #1            // scala/collection/immutable/NumericRange$NumericRangeIterator
    #3 = Utf8               <T:Ljava/lang/Object;>Lscala/collection/AbstractIterator<TT;>;Ljava/io/Serializable;
    #4 = Utf8               scala/collection/AbstractIterator
    #5 = Class              #4            // scala/collection/AbstractIterator
    #6 = Utf8               java/io/Serializable
    #7 = Class              #6            // java/io/Serializable
    #8 = Utf8               NumericRange.scala
    #9 = Utf8               scala/collection/immutable/NumericRange
   #10 = Class              #9            // scala/collection/immutable/NumericRange
   #11 = Utf8               NumericRangeIterator
   #12 = Utf8               scala/math/Integral$IntegralOps
   #13 = Class              #12           // scala/math/Integral$IntegralOps
   #14 = Utf8               scala/math/Integral
   #15 = Class              #14           // scala/math/Integral
   #16 = Utf8               IntegralOps
   #17 = Utf8               serialVersionUID
   #18 = Utf8               J
   #19 = Long               3l
   #21 = Utf8               self
   #22 = Utf8               Lscala/collection/immutable/NumericRange;
   #23 = Utf8               Lscala/collection/immutable/NumericRange<TT;>;
   #24 = Utf8               num
   #25 = Utf8               Lscala/math/Integral;
   #26 = Utf8               Lscala/math/Integral<TT;>;
   #27 = Utf8               _hasNext
   #28 = Utf8               Z
   #29 = Utf8               _next
   #30 = Utf8               Ljava/lang/Object;
   #31 = Utf8               TT;
   #32 = Utf8               lastElement
   #33 = Utf8               knownSize
   #34 = Utf8               ()I
   #35 = NameAndType        #27:#28       // _hasNext:Z
   #36 = Fieldref           #2.#35        // scala/collection/immutable/NumericRange$NumericRangeIterator._hasNext:Z
   #37 = NameAndType        #24:#25       // num:Lscala/math/Integral;
   #38 = Fieldref           #2.#37        // scala/collection/immutable/NumericRange$NumericRangeIterator.num:Lscala/math/Integral;
   #39 = NameAndType        #32:#30       // lastElement:Ljava/lang/Object;
   #40 = Fieldref           #2.#39        // scala/collection/immutable/NumericRange$NumericRangeIterator.lastElement:Ljava/lang/Object;
   #41 = Utf8               mkNumericOps
   #42 = Utf8               (Ljava/lang/Object;)Lscala/math/Integral$IntegralOps;
   #43 = NameAndType        #41:#42       // mkNumericOps:(Ljava/lang/Object;)Lscala/math/Integral$IntegralOps;
   #44 = InterfaceMethodref #15.#43       // scala/math/Integral.mkNumericOps:(Ljava/lang/Object;)Lscala/math/Integral$IntegralOps;
   #45 = NameAndType        #29:#30       // _next:Ljava/lang/Object;
   #46 = Fieldref           #2.#45        // scala/collection/immutable/NumericRange$NumericRangeIterator._next:Ljava/lang/Object;
   #47 = Utf8               $minus
   #48 = Utf8               (Ljava/lang/Object;)Ljava/lang/Object;
   #49 = NameAndType        #47:#48       // $minus:(Ljava/lang/Object;)Ljava/lang/Object;
   #50 = Methodref          #13.#49       // scala/math/Integral$IntegralOps.$minus:(Ljava/lang/Object;)Ljava/lang/Object;
   #51 = NameAndType        #21:#22       // self:Lscala/collection/immutable/NumericRange;
   #52 = Fieldref           #2.#51        // scala/collection/immutable/NumericRange$NumericRangeIterator.self:Lscala/collection/immutable/NumericRange;
   #53 = Utf8               step
   #54 = Utf8               ()Ljava/lang/Object;
   #55 = NameAndType        #53:#54       // step:()Ljava/lang/Object;
   #56 = Methodref          #10.#55       // scala/collection/immutable/NumericRange.step:()Ljava/lang/Object;
   #57 = Utf8               $div
   #58 = NameAndType        #57:#48       // $div:(Ljava/lang/Object;)Ljava/lang/Object;
   #59 = Methodref          #13.#58       // scala/math/Integral$IntegralOps.$div:(Ljava/lang/Object;)Ljava/lang/Object;
   #60 = Utf8               toInt
   #61 = Utf8               (Ljava/lang/Object;)I
   #62 = NameAndType        #60:#61       // toInt:(Ljava/lang/Object;)I
   #63 = InterfaceMethodref #15.#62       // scala/math/Integral.toInt:(Ljava/lang/Object;)I
   #64 = Utf8               this
   #65 = Utf8               Lscala/collection/immutable/NumericRange$NumericRangeIterator;
   #66 = Utf8               hasNext
   #67 = Utf8               ()Z
   #68 = Utf8               next
   #69 = Utf8               ()TT;
   #70 = Utf8               scala/collection/Iterator$
   #71 = Class              #70           // scala/collection/Iterator$
   #72 = Utf8               MODULE$
   #73 = Utf8               Lscala/collection/Iterator$;
   #74 = NameAndType        #72:#73       // MODULE$:Lscala/collection/Iterator$;
   #75 = Fieldref           #71.#74       // scala/collection/Iterator$.MODULE$:Lscala/collection/Iterator$;
   #76 = Utf8               scala$collection$Iterator$$_empty
   #77 = Utf8               Lscala/collection/Iterator;
   #78 = NameAndType        #76:#77       // scala$collection$Iterator$$_empty:Lscala/collection/Iterator;
   #79 = Fieldref           #71.#78       // scala/collection/Iterator$.scala$collection$Iterator$$_empty:Lscala/collection/Iterator;
   #80 = Utf8               scala/collection/Iterator
   #81 = Class              #80           // scala/collection/Iterator
   #82 = NameAndType        #68:#54       // next:()Ljava/lang/Object;
   #83 = InterfaceMethodref #81.#82       // scala/collection/Iterator.next:()Ljava/lang/Object;
   #84 = Utf8               scala/runtime/BoxesRunTime
   #85 = Class              #84           // scala/runtime/BoxesRunTime
   #86 = Utf8               equals
   #87 = Utf8               (Ljava/lang/Object;Ljava/lang/Object;)Z
   #88 = NameAndType        #86:#87       // equals:(Ljava/lang/Object;Ljava/lang/Object;)Z
   #89 = Methodref          #85.#88       // scala/runtime/BoxesRunTime.equals:(Ljava/lang/Object;Ljava/lang/Object;)Z
   #90 = Utf8               plus
   #91 = Utf8               (Ljava/lang/Object;Ljava/lang/Object;)Ljava/lang/Object;
   #92 = NameAndType        #90:#91       // plus:(Ljava/lang/Object;Ljava/lang/Object;)Ljava/lang/Object;
   #93 = InterfaceMethodref #15.#92       // scala/math/Integral.plus:(Ljava/lang/Object;Ljava/lang/Object;)Ljava/lang/Object;
   #94 = Utf8               value
   #95 = Utf8               java/lang/Object
   #96 = Class              #95           // java/lang/Object
   #97 = Utf8               <init>
   #98 = Utf8               (Lscala/collection/immutable/NumericRange;Lscala/math/Integral;)V
   #99 = Utf8               (Lscala/collection/immutable/NumericRange<TT;>;Lscala/math/Integral<TT;>;)V
  #100 = Utf8               ()V
  #101 = NameAndType        #97:#100      // "<init>":()V
  #102 = Methodref          #5.#101       // scala/collection/AbstractIterator."<init>":()V
  #103 = Utf8               isEmpty
  #104 = NameAndType        #103:#67      // isEmpty:()Z
  #105 = Methodref          #10.#104      // scala/collection/immutable/NumericRange.isEmpty:()Z
  #106 = Utf8               start
  #107 = NameAndType        #106:#54      // start:()Ljava/lang/Object;
  #108 = Methodref          #10.#107      // scala/collection/immutable/NumericRange.start:()Ljava/lang/Object;
  #109 = Utf8               last
  #110 = NameAndType        #109:#54      // last:()Ljava/lang/Object;
  #111 = Methodref          #10.#110      // scala/collection/immutable/NumericRange.last:()Ljava/lang/Object;
  #112 = Utf8               ConstantValue
  #113 = Utf8               Signature
  #114 = Utf8               Code
  #115 = Utf8               StackMapTable
  #116 = Utf8               LineNumberTable
  #117 = Utf8               LocalVariableTable
  #118 = Utf8               MethodParameters
  #119 = Utf8               InnerClasses
  #120 = Utf8               SourceFile
  #121 = Utf8               ScalaInlineInfo
  #122 = Utf8               Scala
{
  private static final long serialVersionUID;
    descriptor: J
    flags: (0x001a) ACC_PRIVATE, ACC_STATIC, ACC_FINAL
    ConstantValue: long 3l

  private final scala.collection.immutable.NumericRange<T> self;
    descriptor: Lscala/collection/immutable/NumericRange;
    flags: (0x0012) ACC_PRIVATE, ACC_FINAL
    Signature: #23                          // Lscala/collection/immutable/NumericRange<TT;>;

  private final scala.math.Integral<T> num;
    descriptor: Lscala/math/Integral;
    flags: (0x0012) ACC_PRIVATE, ACC_FINAL
    Signature: #26                          // Lscala/math/Integral<TT;>;

  private boolean _hasNext;
    descriptor: Z
    flags: (0x0002) ACC_PRIVATE

  private T _next;
    descriptor: Ljava/lang/Object;
    flags: (0x0002) ACC_PRIVATE
    Signature: #31                          // TT;

  private final T lastElement;
    descriptor: Ljava/lang/Object;
    flags: (0x0012) ACC_PRIVATE, ACC_FINAL
    Signature: #31                          // TT;

  public int knownSize();
    descriptor: ()I
    flags: (0x0001) ACC_PUBLIC
    Code:
      stack=4, locals=1, args_size=1
         0: aload_0
         1: getfield      #36                 // Field _hasNext:Z
         4: ifeq          58
         7: aload_0
         8: getfield      #38                 // Field num:Lscala/math/Integral;
        11: aload_0
        12: getfield      #38                 // Field num:Lscala/math/Integral;
        15: aload_0
        16: getfield      #38                 // Field num:Lscala/math/Integral;
        19: aload_0
        20: getfield      #40                 // Field lastElement:Ljava/lang/Object;
        23: invokeinterface #44,  2           // InterfaceMethod scala/math/Integral.mkNumericOps:(Ljava/lang/Object;)Lscala/math/Integral$IntegralOps;
        28: aload_0
        29: getfield      #46                 // Field _next:Ljava/lang/Object;
        32: invokevirtual #50                 // Method scala/math/Integral$IntegralOps.$minus:(Ljava/lang/Object;)Ljava/lang/Object;
        35: invokeinterface #44,  2           // InterfaceMethod scala/math/Integral.mkNumericOps:(Ljava/lang/Object;)Lscala/math/Integral$IntegralOps;
        40: aload_0
        41: getfield      #52                 // Field self:Lscala/collection/immutable/NumericRange;
        44: invokevirtual #56                 // Method scala/collection/immutable/NumericRange.step:()Ljava/lang/Object;
        47: invokevirtual #59                 // Method scala/math/Integral$IntegralOps.$div:(Ljava/lang/Object;)Ljava/lang/Object;
        50: invokeinterface #63,  2           // InterfaceMethod scala/math/Integral.toInt:(Ljava/lang/Object;)I
        55: iconst_1
        56: iadd
        57: ireturn
        58: iconst_0
        59: ireturn
      StackMapTable: number_of_entries = 1
        frame_type = 58 /* same */
      LineNumberTable:
        line 422: 0
      LocalVariableTable:
        Start  Length  Slot  Name   Signature
            0      60     0  this   Lscala/collection/immutable/NumericRange$NumericRangeIterator;

  public boolean hasNext();
    descriptor: ()Z
    flags: (0x0001) ACC_PUBLIC
    Code:
      stack=1, locals=1, args_size=1
         0: aload_0
         1: getfield      #36                 // Field _hasNext:Z
         4: ireturn
      LineNumberTable:
        line 423: 0
      LocalVariableTable:
        Start  Length  Slot  Name   Signature
            0       5     0  this   Lscala/collection/immutable/NumericRange$NumericRangeIterator;

  public T next();
    descriptor: ()Ljava/lang/Object;
    flags: (0x0001) ACC_PUBLIC
    Code:
      stack=4, locals=2, args_size=1
         0: aload_0
         1: getfield      #36                 // Field _hasNext:Z
         4: ifne          20
         7: getstatic     #75                 // Field scala/collection/Iterator$.MODULE$:Lscala/collection/Iterator$;
        10: pop
        11: getstatic     #79                 // Field scala/collection/Iterator$.scala$collection$Iterator$$_empty:Lscala/collection/Iterator;
        14: invokeinterface #83,  1           // InterfaceMethod scala/collection/Iterator.next:()Ljava/lang/Object;
        19: pop
        20: aload_0
        21: getfield      #46                 // Field _next:Ljava/lang/Object;
        24: astore_1
        25: aload_0
        26: aload_1
        27: aload_0
        28: getfield      #40                 // Field lastElement:Ljava/lang/Object;
        31: invokestatic  #89                 // Method scala/runtime/BoxesRunTime.equals:(Ljava/lang/Object;Ljava/lang/Object;)Z
        34: ifne          41
        37: iconst_1
        38: goto          42
        41: iconst_0
        42: putfield      #36                 // Field _hasNext:Z
        45: aload_0
        46: aload_0
        47: getfield      #38                 // Field num:Lscala/math/Integral;
        50: aload_1
        51: aload_0
        52: getfield      #52                 // Field self:Lscala/collection/immutable/NumericRange;
        55: invokevirtual #56                 // Method scala/collection/immutable/NumericRange.step:()Ljava/lang/Object;
        58: invokeinterface #93,  3           // InterfaceMethod scala/math/Integral.plus:(Ljava/lang/Object;Ljava/lang/Object;)Ljava/lang/Object;
        63: putfield      #46                 // Field _next:Ljava/lang/Object;
        66: aload_1
        67: areturn
      StackMapTable: number_of_entries = 3
        frame_type = 20 /* same */
        frame_type = 255 /* full_frame */
          offset_delta = 20
          locals = [ class scala/collection/immutable/NumericRange$NumericRangeIterator, class java/lang/Object ]
          stack = [ class scala/collection/immutable/NumericRange$NumericRangeIterator ]
        frame_type = 255 /* full_frame */
          offset_delta = 0
          locals = [ class scala/collection/immutable/NumericRange$NumericRangeIterator, class java/lang/Object ]
          stack = [ class scala/collection/immutable/NumericRange$NumericRangeIterator, int ]
      LineNumberTable:
        line 425: 0
        line 426: 20
        line 427: 25
        line 428: 45
        line 429: 66
      LocalVariableTable:
        Start  Length  Slot  Name   Signature
           25      42     1 value   Ljava/lang/Object;
            0      68     0  this   Lscala/collection/immutable/NumericRange$NumericRangeIterator;
    Signature: #69                          // ()TT;

  public scala.collection.immutable.NumericRange$NumericRangeIterator(scala.collection.immutable.NumericRange<T>, scala.math.Integral<T>);
    descriptor: (Lscala/collection/immutable/NumericRange;Lscala/math/Integral;)V
    flags: (0x0001) ACC_PUBLIC
    Code:
      stack=2, locals=3, args_size=3
         0: aload_0
         1: aload_1
         2: putfield      #52                 // Field self:Lscala/collection/immutable/NumericRange;
         5: aload_0
         6: aload_2
         7: putfield      #38                 // Field num:Lscala/math/Integral;
        10: aload_0
        11: invokespecial #102                // Method scala/collection/AbstractIterator."<init>":()V
        14: aload_0
        15: aload_1
        16: invokevirtual #105                // Method scala/collection/immutable/NumericRange.isEmpty:()Z
        19: ifne          26
        22: iconst_1
        23: goto          27
        26: iconst_0
        27: putfield      #36                 // Field _hasNext:Z
        30: aload_0
        31: aload_1
        32: invokevirtual #108                // Method scala/collection/immutable/NumericRange.start:()Ljava/lang/Object;
        35: putfield      #46                 // Field _next:Ljava/lang/Object;
        38: aload_0
        39: aload_0
        40: getfield      #36                 // Field _hasNext:Z
        43: ifeq          53
        46: aload_1
        47: invokevirtual #111                // Method scala/collection/immutable/NumericRange.last:()Ljava/lang/Object;
        50: goto          57
        53: aload_1
        54: invokevirtual #108                // Method scala/collection/immutable/NumericRange.start:()Ljava/lang/Object;
        57: putfield      #40                 // Field lastElement:Ljava/lang/Object;
        60: return
      StackMapTable: number_of_entries = 4
        frame_type = 255 /* full_frame */
          offset_delta = 26
          locals = [ class scala/collection/immutable/NumericRange$NumericRangeIterator, class scala/collection/immutable/NumericRange, class scala/math/Integral ]
          stack = [ class scala/collection/immutable/NumericRange$NumericRangeIterator ]
        frame_type = 255 /* full_frame */
          offset_delta = 0
          locals = [ class scala/collection/immutable/NumericRange$NumericRangeIterator, class scala/collection/immutable/NumericRange, class scala/math/Integral ]
          stack = [ class scala/collection/immutable/NumericRange$NumericRangeIterator, int ]
        frame_type = 89 /* same_locals_1_stack_item */
          stack = [ class scala/collection/immutable/NumericRange$NumericRangeIterator ]
        frame_type = 255 /* full_frame */
          offset_delta = 3
          locals = [ class scala/collection/immutable/NumericRange$NumericRangeIterator, class scala/collection/immutable/NumericRange, class scala/math/Integral ]
          stack = [ class scala/collection/immutable/NumericRange$NumericRangeIterator, class java/lang/Object ]
      LineNumberTable:
        line 416: 0
        line 419: 14
        line 420: 30
        line 421: 38
        line 416: 60
      LocalVariableTable:
        Start  Length  Slot  Name   Signature
            0      61     0  this   Lscala/collection/immutable/NumericRange$NumericRangeIterator;
            0      61     1  self   Lscala/collection/immutable/NumericRange;
            0      61     2   num   Lscala/math/Integral;
    Signature: #99                          // (Lscala/collection/immutable/NumericRange<TT;>;Lscala/math/Integral<TT;>;)V
    MethodParameters:
      Name                           Flags
      self                           final
      num                            final
}
InnerClasses:
  private static final #11= #2 of #10;    // NumericRangeIterator=class scala/collection/immutable/NumericRange$NumericRangeIterator of class scala/collection/immutable/NumericRange
  public #16= #13 of #15;                 // IntegralOps=class scala/math/Integral$IntegralOps of class scala/math/Integral
Signature: #3                           // <T:Ljava/lang/Object;>Lscala/collection/AbstractIterator<TT;>;Ljava/io/Serializable;
SourceFile: "NumericRange.scala"
  ScalaInlineInfo: length = 0x18 (unknown attribute)
   01 01 00 04 00 61 00 62 01 00 42 00 43 01 00 21
   00 22 01 00 44 00 36 01
  Scala: length = 0x0 (unknown attribute)

