Classfile /Users/mw/Projects/slang-braindump/.jar/jar8/assemble/slang-braindump/assemble/content/scala/collection/immutable/OldHashSet$OldHashSet1.class
  Last modified May 29, 2022; size 6844 bytes
  SHA-256 checksum e87c3a4bc4587c55b933620545c752424f3f2e61ed3e693cba0bccbe5e31e1b9
  Compiled from "OldHashSet.scala"
public final class scala.collection.immutable.OldHashSet$OldHashSet1<A extends java.lang.Object> extends scala.collection.immutable.OldHashSet$LeafOldHashSet<A>
  minor version: 0
  major version: 52
  flags: (0x0031) ACC_PUBLIC, ACC_FINAL, ACC_SUPER
  this_class: #2                          // scala/collection/immutable/OldHashSet$OldHashSet1
  super_class: #5                         // scala/collection/immutable/OldHashSet$LeafOldHashSet
  interfaces: 0, fields: 2, methods: 25, attributes: 5
Constant pool:
    #1 = Utf8               scala/collection/immutable/OldHashSet$OldHashSet1
    #2 = Class              #1            // scala/collection/immutable/OldHashSet$OldHashSet1
    #3 = Utf8               <A:Ljava/lang/Object;>Lscala/collection/immutable/OldHashSet$LeafOldHashSet<TA;>;
    #4 = Utf8               scala/collection/immutable/OldHashSet$LeafOldHashSet
    #5 = Class              #4            // scala/collection/immutable/OldHashSet$LeafOldHashSet
    #6 = Utf8               OldHashSet.scala
    #7 = Utf8               scala/collection/immutable/OldHashSet$HashTrieSet
    #8 = Class              #7            // scala/collection/immutable/OldHashSet$HashTrieSet
    #9 = Utf8               scala/collection/immutable/OldHashSet
   #10 = Class              #9            // scala/collection/immutable/OldHashSet
   #11 = Utf8               HashTrieSet
   #12 = Utf8               LeafOldHashSet
   #13 = Utf8               OldHashSet1
   #14 = Utf8               scala/collection/immutable/OldHashSet$OldHashSetCollision1
   #15 = Class              #14           // scala/collection/immutable/OldHashSet$OldHashSetCollision1
   #16 = Utf8               OldHashSetCollision1
   #17 = Utf8               key
   #18 = Utf8               Ljava/lang/Object;
   #19 = Utf8               TA;
   #20 = Utf8               hash
   #21 = Utf8               I
   #22 = Utf8               ()Ljava/lang/Object;
   #23 = Utf8               ()TA;
   #24 = NameAndType        #17:#18       // key:Ljava/lang/Object;
   #25 = Fieldref           #2.#24        // scala/collection/immutable/OldHashSet$OldHashSet1.key:Ljava/lang/Object;
   #26 = Utf8               this
   #27 = Utf8               Lscala/collection/immutable/OldHashSet$OldHashSet1;
   #28 = Utf8               ()I
   #29 = NameAndType        #20:#21       // hash:I
   #30 = Fieldref           #2.#29        // scala/collection/immutable/OldHashSet$OldHashSet1.hash:I
   #31 = Utf8               isEmpty
   #32 = Utf8               ()Z
   #33 = Utf8               knownSize
   #34 = Utf8               iterator
   #35 = Utf8               ()Lscala/collection/Iterator;
   #36 = Utf8               ()Lscala/collection/Iterator<TA;>;
   #37 = Utf8               scala/collection/Iterator$
   #38 = Class              #37           // scala/collection/Iterator$
   #39 = Utf8               MODULE$
   #40 = Utf8               Lscala/collection/Iterator$;
   #41 = NameAndType        #39:#40       // MODULE$:Lscala/collection/Iterator$;
   #42 = Fieldref           #38.#41       // scala/collection/Iterator$.MODULE$:Lscala/collection/Iterator$;
   #43 = NameAndType        #17:#22       // key:()Ljava/lang/Object;
   #44 = Methodref          #2.#43        // scala/collection/immutable/OldHashSet$OldHashSet1.key:()Ljava/lang/Object;
   #45 = Utf8               single
   #46 = Utf8               (Ljava/lang/Object;)Lscala/collection/Iterator;
   #47 = NameAndType        #45:#46       // single:(Ljava/lang/Object;)Lscala/collection/Iterator;
   #48 = Methodref          #38.#47       // scala/collection/Iterator$.single:(Ljava/lang/Object;)Lscala/collection/Iterator;
   #49 = Utf8               foreach
   #50 = Utf8               (Lscala/Function1;)V
   #51 = Utf8               <U:Ljava/lang/Object;>(Lscala/Function1<TA;TU;>;)V
   #52 = Utf8               f
   #53 = Utf8               scala/Function1
   #54 = Class              #53           // scala/Function1
   #55 = Utf8               apply
   #56 = Utf8               (Ljava/lang/Object;)Ljava/lang/Object;
   #57 = NameAndType        #55:#56       // apply:(Ljava/lang/Object;)Ljava/lang/Object;
   #58 = InterfaceMethodref #54.#57       // scala/Function1.apply:(Ljava/lang/Object;)Ljava/lang/Object;
   #59 = Utf8               Lscala/Function1;
   #60 = Utf8               head
   #61 = Utf8               headOption
   #62 = Utf8               ()Lscala/Some;
   #63 = Utf8               ()Lscala/Some<TA;>;
   #64 = Utf8               scala/Some
   #65 = Class              #64           // scala/Some
   #66 = Utf8               <init>
   #67 = Utf8               (Ljava/lang/Object;)V
   #68 = NameAndType        #66:#67       // "<init>":(Ljava/lang/Object;)V
   #69 = Methodref          #65.#68       // scala/Some."<init>":(Ljava/lang/Object;)V
   #70 = Utf8               tail
   #71 = Utf8               ()Lscala/collection/immutable/OldHashSet;
   #72 = Utf8               ()Lscala/collection/immutable/OldHashSet<TA;>;
   #73 = Utf8               scala/collection/immutable/OldHashSet$
   #74 = Class              #73           // scala/collection/immutable/OldHashSet$
   #75 = Utf8               Lscala/collection/immutable/OldHashSet$;
   #76 = NameAndType        #39:#75       // MODULE$:Lscala/collection/immutable/OldHashSet$;
   #77 = Fieldref           #74.#76       // scala/collection/immutable/OldHashSet$.MODULE$:Lscala/collection/immutable/OldHashSet$;
   #78 = Utf8               empty
   #79 = NameAndType        #78:#71       // empty:()Lscala/collection/immutable/OldHashSet;
   #80 = Methodref          #74.#79       // scala/collection/immutable/OldHashSet$.empty:()Lscala/collection/immutable/OldHashSet;
   #81 = Utf8               last
   #82 = Utf8               init
   #83 = Utf8               size
   #84 = Utf8               get0
   #85 = Utf8               (Ljava/lang/Object;II)Z
   #86 = Utf8               (TA;II)Z
   #87 = Utf8               level
   #88 = NameAndType        #20:#28       // hash:()I
   #89 = Methodref          #2.#88        // scala/collection/immutable/OldHashSet$OldHashSet1.hash:()I
   #90 = Utf8               scala/runtime/BoxesRunTime
   #91 = Class              #90           // scala/runtime/BoxesRunTime
   #92 = Utf8               equals
   #93 = Utf8               (Ljava/lang/Object;Ljava/lang/Object;)Z
   #94 = NameAndType        #92:#93       // equals:(Ljava/lang/Object;Ljava/lang/Object;)Z
   #95 = Methodref          #91.#94       // scala/runtime/BoxesRunTime.equals:(Ljava/lang/Object;Ljava/lang/Object;)Z
   #96 = Utf8               updated0
   #97 = Utf8               (Ljava/lang/Object;II)Lscala/collection/immutable/OldHashSet;
   #98 = Utf8               (TA;II)Lscala/collection/immutable/OldHashSet<TA;>;
   #99 = Utf8               (Ljava/lang/Object;I)V
  #100 = NameAndType        #66:#99       // "<init>":(Ljava/lang/Object;I)V
  #101 = Methodref          #2.#100       // scala/collection/immutable/OldHashSet$OldHashSet1."<init>":(Ljava/lang/Object;I)V
  #102 = Utf8               scala$collection$immutable$OldHashSet$$makeHashTrieSet
  #103 = Utf8               (ILscala/collection/immutable/OldHashSet;ILscala/collection/immutable/OldHashSet;I)Lscala/collection/immutable/OldHashSet$HashTrieSet;
  #104 = NameAndType        #102:#103     // scala$collection$immutable$OldHashSet$$makeHashTrieSet:(ILscala/collection/immutable/OldHashSet;ILscala/collection/immutable/OldHashSet;I)Lscala/collection/immutable/OldHashSet$HashTrieSet;
  #105 = Methodref          #74.#104      // scala/collection/immutable/OldHashSet$.scala$collection$immutable$OldHashSet$$makeHashTrieSet:(ILscala/collection/immutable/OldHashSet;ILscala/collection/immutable/OldHashSet;I)Lscala/collection/immutable/OldHashSet$HashTrieSet;
  #106 = Utf8               scala/collection/immutable/ListSet$
  #107 = Class              #106          // scala/collection/immutable/ListSet$
  #108 = Utf8               Lscala/collection/immutable/ListSet$;
  #109 = NameAndType        #39:#108      // MODULE$:Lscala/collection/immutable/ListSet$;
  #110 = Fieldref           #107.#109     // scala/collection/immutable/ListSet$.MODULE$:Lscala/collection/immutable/ListSet$;
  #111 = Utf8               ()Lscala/collection/immutable/ListSet;
  #112 = NameAndType        #78:#111      // empty:()Lscala/collection/immutable/ListSet;
  #113 = Methodref          #107.#112     // scala/collection/immutable/ListSet$.empty:()Lscala/collection/immutable/ListSet;
  #114 = Utf8               scala/collection/immutable/ListSet
  #115 = Class              #114          // scala/collection/immutable/ListSet
  #116 = Utf8               $plus
  #117 = Utf8               (Ljava/lang/Object;)Lscala/collection/immutable/SetOps;
  #118 = NameAndType        #116:#117     // $plus:(Ljava/lang/Object;)Lscala/collection/immutable/SetOps;
  #119 = Methodref          #115.#118     // scala/collection/immutable/ListSet.$plus:(Ljava/lang/Object;)Lscala/collection/immutable/SetOps;
  #120 = Utf8               scala/collection/immutable/SetOps
  #121 = Class              #120          // scala/collection/immutable/SetOps
  #122 = InterfaceMethodref #121.#118     // scala/collection/immutable/SetOps.$plus:(Ljava/lang/Object;)Lscala/collection/immutable/SetOps;
  #123 = Utf8               (ILscala/collection/immutable/ListSet;)V
  #124 = NameAndType        #66:#123      // "<init>":(ILscala/collection/immutable/ListSet;)V
  #125 = Methodref          #15.#124      // scala/collection/immutable/OldHashSet$OldHashSetCollision1."<init>":(ILscala/collection/immutable/ListSet;)V
  #126 = Utf8               removed0
  #127 = Utf8               subsetOf0
  #128 = Utf8               (Lscala/collection/immutable/OldHashSet;I)Z
  #129 = Utf8               (Lscala/collection/immutable/OldHashSet<TA;>;I)Z
  #130 = Utf8               that
  #131 = NameAndType        #84:#85       // get0:(Ljava/lang/Object;II)Z
  #132 = Methodref          #10.#131      // scala/collection/immutable/OldHashSet.get0:(Ljava/lang/Object;II)Z
  #133 = Utf8               Lscala/collection/immutable/OldHashSet;
  #134 = Utf8               union0
  #135 = Utf8               (Lscala/collection/immutable/OldHashSet$LeafOldHashSet;I)Lscala/collection/immutable/OldHashSet;
  #136 = Utf8               (Lscala/collection/immutable/OldHashSet$LeafOldHashSet<TA;>;I)Lscala/collection/immutable/OldHashSet<TA;>;
  #137 = Methodref          #5.#88        // scala/collection/immutable/OldHashSet$LeafOldHashSet.hash:()I
  #138 = Utf8               ks
  #139 = NameAndType        #138:#111     // ks:()Lscala/collection/immutable/ListSet;
  #140 = Methodref          #15.#139      // scala/collection/immutable/OldHashSet$OldHashSetCollision1.ks:()Lscala/collection/immutable/ListSet;
  #141 = NameAndType        #83:#28       // size:()I
  #142 = Methodref          #115.#141     // scala/collection/immutable/ListSet.size:()I
  #143 = Utf8               scala/MatchError
  #144 = Class              #143          // scala/MatchError
  #145 = Methodref          #144.#68      // scala/MatchError."<init>":(Ljava/lang/Object;)V
  #146 = Utf8               ks1
  #147 = Utf8               Lscala/collection/immutable/ListSet;
  #148 = Utf8               Lscala/collection/immutable/OldHashSet$LeafOldHashSet;
  #149 = Utf8               (Lscala/collection/immutable/OldHashSet;I[Lscala/collection/immutable/OldHashSet;I)Lscala/collection/immutable/OldHashSet;
  #150 = Utf8               (Lscala/collection/immutable/OldHashSet<TA;>;I[Lscala/collection/immutable/OldHashSet<TA;>;I)Lscala/collection/immutable/OldHashSet<TA;>;
  #151 = Utf8               buffer
  #152 = Utf8               offset0
  #153 = NameAndType        #134:#135     // union0:(Lscala/collection/immutable/OldHashSet$LeafOldHashSet;I)Lscala/collection/immutable/OldHashSet;
  #154 = Methodref          #10.#153      // scala/collection/immutable/OldHashSet.union0:(Lscala/collection/immutable/OldHashSet$LeafOldHashSet;I)Lscala/collection/immutable/OldHashSet;
  #155 = Utf8               [Lscala/collection/immutable/OldHashSet;
  #156 = Utf8               intersect0
  #157 = Utf8               diff0
  #158 = Utf8               filter0
  #159 = Utf8               (Lscala/Function1;ZI[Lscala/collection/immutable/OldHashSet;I)Lscala/collection/immutable/OldHashSet;
  #160 = Utf8               (Lscala/Function1<TA;Ljava/lang/Object;>;ZI[Lscala/collection/immutable/OldHashSet<TA;>;I)Lscala/collection/immutable/OldHashSet<TA;>;
  #161 = Utf8               p
  #162 = Utf8               negate
  #163 = Utf8               unboxToBoolean
  #164 = Utf8               (Ljava/lang/Object;)Z
  #165 = NameAndType        #163:#164     // unboxToBoolean:(Ljava/lang/Object;)Z
  #166 = Methodref          #91.#165      // scala/runtime/BoxesRunTime.unboxToBoolean:(Ljava/lang/Object;)Z
  #167 = Utf8               Z
  #168 = NameAndType        #82:#71       // init:()Lscala/collection/immutable/OldHashSet;
  #169 = Methodref          #2.#168       // scala/collection/immutable/OldHashSet$OldHashSet1.init:()Lscala/collection/immutable/OldHashSet;
  #170 = NameAndType        #70:#71       // tail:()Lscala/collection/immutable/OldHashSet;
  #171 = Methodref          #2.#170       // scala/collection/immutable/OldHashSet$OldHashSet1.tail:()Lscala/collection/immutable/OldHashSet;
  #172 = Utf8               ()Lscala/Option;
  #173 = NameAndType        #61:#62       // headOption:()Lscala/Some;
  #174 = Methodref          #2.#173       // scala/collection/immutable/OldHashSet$OldHashSet1.headOption:()Lscala/Some;
  #175 = Utf8               (TA;I)V
  #176 = Utf8               ()V
  #177 = NameAndType        #66:#176      // "<init>":()V
  #178 = Methodref          #5.#177       // scala/collection/immutable/OldHashSet$LeafOldHashSet."<init>":()V
  #179 = Utf8               Signature
  #180 = Utf8               Code
  #181 = Utf8               LineNumberTable
  #182 = Utf8               LocalVariableTable
  #183 = Utf8               MethodParameters
  #184 = Utf8               StackMapTable
  #185 = Utf8               InnerClasses
  #186 = Utf8               SourceFile
  #187 = Utf8               ScalaInlineInfo
  #188 = Utf8               Scala
{
  private final A key;
    descriptor: Ljava/lang/Object;
    flags: (0x0012) ACC_PRIVATE, ACC_FINAL
    Signature: #19                          // TA;

  private final int hash;
    descriptor: I
    flags: (0x0012) ACC_PRIVATE, ACC_FINAL

  public A key();
    descriptor: ()Ljava/lang/Object;
    flags: (0x0001) ACC_PUBLIC
    Code:
      stack=1, locals=1, args_size=1
         0: aload_0
         1: getfield      #25                 // Field key:Ljava/lang/Object;
         4: areturn
      LineNumberTable:
        line 228: 0
      LocalVariableTable:
        Start  Length  Slot  Name   Signature
            0       5     0  this   Lscala/collection/immutable/OldHashSet$OldHashSet1;
    Signature: #23                          // ()TA;

  public int hash();
    descriptor: ()I
    flags: (0x0001) ACC_PUBLIC
    Code:
      stack=1, locals=1, args_size=1
         0: aload_0
         1: getfield      #30                 // Field hash:I
         4: ireturn
      LineNumberTable:
        line 228: 0
      LocalVariableTable:
        Start  Length  Slot  Name   Signature
            0       5     0  this   Lscala/collection/immutable/OldHashSet$OldHashSet1;

  public boolean isEmpty();
    descriptor: ()Z
    flags: (0x0001) ACC_PUBLIC
    Code:
      stack=1, locals=1, args_size=1
         0: iconst_0
         1: ireturn
      LineNumberTable:
        line 229: 0
      LocalVariableTable:
        Start  Length  Slot  Name   Signature
            0       2     0  this   Lscala/collection/immutable/OldHashSet$OldHashSet1;

  public int knownSize();
    descriptor: ()I
    flags: (0x0001) ACC_PUBLIC
    Code:
      stack=1, locals=1, args_size=1
         0: iconst_1
         1: ireturn
      LineNumberTable:
        line 230: 0
      LocalVariableTable:
        Start  Length  Slot  Name   Signature
            0       2     0  this   Lscala/collection/immutable/OldHashSet$OldHashSet1;

  public scala.collection.Iterator<A> iterator();
    descriptor: ()Lscala/collection/Iterator;
    flags: (0x0001) ACC_PUBLIC
    Code:
      stack=2, locals=1, args_size=1
         0: getstatic     #42                 // Field scala/collection/Iterator$.MODULE$:Lscala/collection/Iterator$;
         3: aload_0
         4: invokevirtual #44                 // Method key:()Ljava/lang/Object;
         7: invokevirtual #48                 // Method scala/collection/Iterator$.single:(Ljava/lang/Object;)Lscala/collection/Iterator;
        10: areturn
      LineNumberTable:
        line 231: 0
      LocalVariableTable:
        Start  Length  Slot  Name   Signature
            0      11     0  this   Lscala/collection/immutable/OldHashSet$OldHashSet1;
    Signature: #36                          // ()Lscala/collection/Iterator<TA;>;

  public <U extends java.lang.Object> void foreach(scala.Function1<A, U>);
    descriptor: (Lscala/Function1;)V
    flags: (0x0001) ACC_PUBLIC
    Code:
      stack=2, locals=2, args_size=2
         0: aload_1
         1: aload_0
         2: invokevirtual #44                 // Method key:()Ljava/lang/Object;
         5: invokeinterface #58,  2           // InterfaceMethod scala/Function1.apply:(Ljava/lang/Object;)Ljava/lang/Object;
        10: pop
        11: return
      LineNumberTable:
        line 233: 0
      LocalVariableTable:
        Start  Length  Slot  Name   Signature
            0      12     0  this   Lscala/collection/immutable/OldHashSet$OldHashSet1;
            0      12     1     f   Lscala/Function1;
    Signature: #51                          // <U:Ljava/lang/Object;>(Lscala/Function1<TA;TU;>;)V
    MethodParameters:
      Name                           Flags
      f                              final

  public A head();
    descriptor: ()Ljava/lang/Object;
    flags: (0x0001) ACC_PUBLIC
    Code:
      stack=1, locals=1, args_size=1
         0: aload_0
         1: invokevirtual #44                 // Method key:()Ljava/lang/Object;
         4: areturn
      LineNumberTable:
        line 235: 0
      LocalVariableTable:
        Start  Length  Slot  Name   Signature
            0       5     0  this   Lscala/collection/immutable/OldHashSet$OldHashSet1;
    Signature: #23                          // ()TA;

  public scala.Some<A> headOption();
    descriptor: ()Lscala/Some;
    flags: (0x0001) ACC_PUBLIC
    Code:
      stack=3, locals=1, args_size=1
         0: new           #65                 // class scala/Some
         3: dup
         4: aload_0
         5: invokevirtual #44                 // Method key:()Ljava/lang/Object;
         8: invokespecial #69                 // Method scala/Some."<init>":(Ljava/lang/Object;)V
        11: areturn
      LineNumberTable:
        line 237: 0
      LocalVariableTable:
        Start  Length  Slot  Name   Signature
            0      12     0  this   Lscala/collection/immutable/OldHashSet$OldHashSet1;
    Signature: #63                          // ()Lscala/Some<TA;>;

  public scala.collection.immutable.OldHashSet<A> tail();
    descriptor: ()Lscala/collection/immutable/OldHashSet;
    flags: (0x0001) ACC_PUBLIC
    Code:
      stack=1, locals=1, args_size=1
         0: getstatic     #77                 // Field scala/collection/immutable/OldHashSet$.MODULE$:Lscala/collection/immutable/OldHashSet$;
         3: invokevirtual #80                 // Method scala/collection/immutable/OldHashSet$.empty:()Lscala/collection/immutable/OldHashSet;
         6: areturn
      LineNumberTable:
        line 239: 0
      LocalVariableTable:
        Start  Length  Slot  Name   Signature
            0       7     0  this   Lscala/collection/immutable/OldHashSet$OldHashSet1;
    Signature: #72                          // ()Lscala/collection/immutable/OldHashSet<TA;>;

  public A last();
    descriptor: ()Ljava/lang/Object;
    flags: (0x0001) ACC_PUBLIC
    Code:
      stack=1, locals=1, args_size=1
         0: aload_0
         1: invokevirtual #44                 // Method key:()Ljava/lang/Object;
         4: areturn
      LineNumberTable:
        line 241: 0
      LocalVariableTable:
        Start  Length  Slot  Name   Signature
            0       5     0  this   Lscala/collection/immutable/OldHashSet$OldHashSet1;
    Signature: #23                          // ()TA;

  public scala.collection.immutable.OldHashSet<A> init();
    descriptor: ()Lscala/collection/immutable/OldHashSet;
    flags: (0x0001) ACC_PUBLIC
    Code:
      stack=1, locals=1, args_size=1
         0: getstatic     #77                 // Field scala/collection/immutable/OldHashSet$.MODULE$:Lscala/collection/immutable/OldHashSet$;
         3: invokevirtual #80                 // Method scala/collection/immutable/OldHashSet$.empty:()Lscala/collection/immutable/OldHashSet;
         6: areturn
      LineNumberTable:
        line 243: 0
      LocalVariableTable:
        Start  Length  Slot  Name   Signature
            0       7     0  this   Lscala/collection/immutable/OldHashSet$OldHashSet1;
    Signature: #72                          // ()Lscala/collection/immutable/OldHashSet<TA;>;

  public int size();
    descriptor: ()I
    flags: (0x0001) ACC_PUBLIC
    Code:
      stack=1, locals=1, args_size=1
         0: iconst_1
         1: ireturn
      LineNumberTable:
        line 245: 0
      LocalVariableTable:
        Start  Length  Slot  Name   Signature
            0       2     0  this   Lscala/collection/immutable/OldHashSet$OldHashSet1;

  public boolean get0(A, int, int);
    descriptor: (Ljava/lang/Object;II)Z
    flags: (0x0001) ACC_PUBLIC
    Code:
      stack=2, locals=4, args_size=4
         0: iload_2
         1: aload_0
         2: invokevirtual #89                 // Method hash:()I
         5: if_icmpne     23
         8: aload_1
         9: aload_0
        10: invokevirtual #44                 // Method key:()Ljava/lang/Object;
        13: invokestatic  #95                 // Method scala/runtime/BoxesRunTime.equals:(Ljava/lang/Object;Ljava/lang/Object;)Z
        16: ifeq          23
        19: iconst_1
        20: goto          24
        23: iconst_0
        24: ireturn
      StackMapTable: number_of_entries = 2
        frame_type = 23 /* same */
        frame_type = 64 /* same_locals_1_stack_item */
          stack = [ int ]
      LineNumberTable:
        line 248: 0
      LocalVariableTable:
        Start  Length  Slot  Name   Signature
            0      25     0  this   Lscala/collection/immutable/OldHashSet$OldHashSet1;
            0      25     1   key   Ljava/lang/Object;
            0      25     2  hash   I
            0      25     3 level   I
    Signature: #86                          // (TA;II)Z
    MethodParameters:
      Name                           Flags
      key                            final
      hash                           final
      level                          final

  public scala.collection.immutable.OldHashSet<A> updated0(A, int, int);
    descriptor: (Ljava/lang/Object;II)Lscala/collection/immutable/OldHashSet;
    flags: (0x0001) ACC_PUBLIC
    Code:
      stack=8, locals=4, args_size=4
         0: iload_2
         1: aload_0
         2: invokevirtual #89                 // Method hash:()I
         5: if_icmpne     23
         8: aload_1
         9: aload_0
        10: invokevirtual #44                 // Method key:()Ljava/lang/Object;
        13: invokestatic  #95                 // Method scala/runtime/BoxesRunTime.equals:(Ljava/lang/Object;Ljava/lang/Object;)Z
        16: ifeq          23
        19: aload_0
        20: goto          86
        23: iload_2
        24: aload_0
        25: invokevirtual #89                 // Method hash:()I
        28: if_icmpeq     56
        31: getstatic     #77                 // Field scala/collection/immutable/OldHashSet$.MODULE$:Lscala/collection/immutable/OldHashSet$;
        34: aload_0
        35: invokevirtual #89                 // Method hash:()I
        38: aload_0
        39: iload_2
        40: new           #2                  // class scala/collection/immutable/OldHashSet$OldHashSet1
        43: dup
        44: aload_1
        45: iload_2
        46: invokespecial #101                // Method "<init>":(Ljava/lang/Object;I)V
        49: iload_3
        50: invokevirtual #105                // Method scala/collection/immutable/OldHashSet$.scala$collection$immutable$OldHashSet$$makeHashTrieSet:(ILscala/collection/immutable/OldHashSet;ILscala/collection/immutable/OldHashSet;I)Lscala/collection/immutable/OldHashSet$HashTrieSet;
        53: goto          86
        56: new           #15                 // class scala/collection/immutable/OldHashSet$OldHashSetCollision1
        59: dup
        60: iload_2
        61: getstatic     #110                // Field scala/collection/immutable/ListSet$.MODULE$:Lscala/collection/immutable/ListSet$;
        64: invokevirtual #113                // Method scala/collection/immutable/ListSet$.empty:()Lscala/collection/immutable/ListSet;
        67: aload_0
        68: invokevirtual #44                 // Method key:()Ljava/lang/Object;
        71: invokevirtual #119                // Method scala/collection/immutable/ListSet.$plus:(Ljava/lang/Object;)Lscala/collection/immutable/SetOps;
        74: aload_1
        75: invokeinterface #122,  2          // InterfaceMethod scala/collection/immutable/SetOps.$plus:(Ljava/lang/Object;)Lscala/collection/immutable/SetOps;
        80: checkcast     #115                // class scala/collection/immutable/ListSet
        83: invokespecial #125                // Method scala/collection/immutable/OldHashSet$OldHashSetCollision1."<init>":(ILscala/collection/immutable/ListSet;)V
        86: areturn
      StackMapTable: number_of_entries = 3
        frame_type = 23 /* same */
        frame_type = 32 /* same */
        frame_type = 93 /* same_locals_1_stack_item */
          stack = [ class scala/collection/immutable/OldHashSet ]
      LineNumberTable:
        line 251: 0
        line 253: 23
        line 254: 31
        line 257: 56
      LocalVariableTable:
        Start  Length  Slot  Name   Signature
            0      87     0  this   Lscala/collection/immutable/OldHashSet$OldHashSet1;
            0      87     1   key   Ljava/lang/Object;
            0      87     2  hash   I
            0      87     3 level   I
    Signature: #98                          // (TA;II)Lscala/collection/immutable/OldHashSet<TA;>;
    MethodParameters:
      Name                           Flags
      key                            final
      hash                           final
      level                          final

  public scala.collection.immutable.OldHashSet<A> removed0(A, int, int);
    descriptor: (Ljava/lang/Object;II)Lscala/collection/immutable/OldHashSet;
    flags: (0x0001) ACC_PUBLIC
    Code:
      stack=2, locals=4, args_size=4
         0: iload_2
         1: aload_0
         2: invokevirtual #89                 // Method hash:()I
         5: if_icmpne     23
         8: aload_1
         9: aload_0
        10: invokevirtual #44                 // Method key:()Ljava/lang/Object;
        13: invokestatic  #95                 // Method scala/runtime/BoxesRunTime.equals:(Ljava/lang/Object;Ljava/lang/Object;)Z
        16: ifeq          23
        19: aconst_null
        20: goto          24
        23: aload_0
        24: areturn
      StackMapTable: number_of_entries = 2
        frame_type = 23 /* same */
        frame_type = 64 /* same_locals_1_stack_item */
          stack = [ class scala/collection/immutable/OldHashSet$OldHashSet1 ]
      LineNumberTable:
        line 262: 0
      LocalVariableTable:
        Start  Length  Slot  Name   Signature
            0      25     0  this   Lscala/collection/immutable/OldHashSet$OldHashSet1;
            0      25     1   key   Ljava/lang/Object;
            0      25     2  hash   I
            0      25     3 level   I
    Signature: #98                          // (TA;II)Lscala/collection/immutable/OldHashSet<TA;>;
    MethodParameters:
      Name                           Flags
      key                            final
      hash                           final
      level                          final

  public boolean subsetOf0(scala.collection.immutable.OldHashSet<A>, int);
    descriptor: (Lscala/collection/immutable/OldHashSet;I)Z
    flags: (0x0001) ACC_PUBLIC
    Code:
      stack=4, locals=3, args_size=3
         0: aload_1
         1: aload_0
         2: invokevirtual #44                 // Method key:()Ljava/lang/Object;
         5: aload_0
         6: invokevirtual #89                 // Method hash:()I
         9: iload_2
        10: invokevirtual #132                // Method scala/collection/immutable/OldHashSet.get0:(Ljava/lang/Object;II)Z
        13: ireturn
      LineNumberTable:
        line 269: 0
      LocalVariableTable:
        Start  Length  Slot  Name   Signature
            0      14     0  this   Lscala/collection/immutable/OldHashSet$OldHashSet1;
            0      14     1  that   Lscala/collection/immutable/OldHashSet;
            0      14     2 level   I
    Signature: #129                         // (Lscala/collection/immutable/OldHashSet<TA;>;I)Z
    MethodParameters:
      Name                           Flags
      that                           final
      level                          final

  public scala.collection.immutable.OldHashSet<A> union0(scala.collection.immutable.OldHashSet$LeafOldHashSet<A>, int);
    descriptor: (Lscala/collection/immutable/OldHashSet$LeafOldHashSet;I)Lscala/collection/immutable/OldHashSet;
    flags: (0x0001) ACC_PUBLIC
    Code:
      stack=6, locals=8, args_size=3
         0: aload_1
         1: astore        4
         3: aload         4
         5: invokevirtual #137                // Method scala/collection/immutable/OldHashSet$LeafOldHashSet.hash:()I
         8: aload_0
         9: invokevirtual #89                 // Method hash:()I
        12: if_icmpeq     38
        15: getstatic     #77                 // Field scala/collection/immutable/OldHashSet$.MODULE$:Lscala/collection/immutable/OldHashSet$;
        18: aload_0
        19: invokevirtual #89                 // Method hash:()I
        22: aload_0
        23: aload         4
        25: invokevirtual #137                // Method scala/collection/immutable/OldHashSet$LeafOldHashSet.hash:()I
        28: aload         4
        30: iload_2
        31: invokevirtual #105                // Method scala/collection/immutable/OldHashSet$.scala$collection$immutable$OldHashSet$$makeHashTrieSet:(ILscala/collection/immutable/OldHashSet;ILscala/collection/immutable/OldHashSet;I)Lscala/collection/immutable/OldHashSet$HashTrieSet;
        34: astore_3
        35: goto          202
        38: goto          41
        41: aload         4
        43: instanceof    #2                  // class scala/collection/immutable/OldHashSet$OldHashSet1
        46: ifeq          116
        49: aload         4
        51: checkcast     #2                  // class scala/collection/immutable/OldHashSet$OldHashSet1
        54: astore        5
        56: aload_0
        57: invokevirtual #44                 // Method key:()Ljava/lang/Object;
        60: aload         5
        62: invokevirtual #44                 // Method key:()Ljava/lang/Object;
        65: invokestatic  #95                 // Method scala/runtime/BoxesRunTime.equals:(Ljava/lang/Object;Ljava/lang/Object;)Z
        68: ifeq          75
        71: aload_0
        72: goto          112
        75: new           #15                 // class scala/collection/immutable/OldHashSet$OldHashSetCollision1
        78: dup
        79: aload_0
        80: invokevirtual #89                 // Method hash:()I
        83: getstatic     #110                // Field scala/collection/immutable/ListSet$.MODULE$:Lscala/collection/immutable/ListSet$;
        86: invokevirtual #113                // Method scala/collection/immutable/ListSet$.empty:()Lscala/collection/immutable/ListSet;
        89: aload_0
        90: invokevirtual #44                 // Method key:()Ljava/lang/Object;
        93: invokevirtual #119                // Method scala/collection/immutable/ListSet.$plus:(Ljava/lang/Object;)Lscala/collection/immutable/SetOps;
        96: aload         5
        98: invokevirtual #44                 // Method key:()Ljava/lang/Object;
       101: invokeinterface #122,  2          // InterfaceMethod scala/collection/immutable/SetOps.$plus:(Ljava/lang/Object;)Lscala/collection/immutable/SetOps;
       106: checkcast     #115                // class scala/collection/immutable/ListSet
       109: invokespecial #125                // Method scala/collection/immutable/OldHashSet$OldHashSetCollision1."<init>":(ILscala/collection/immutable/ListSet;)V
       112: astore_3
       113: goto          202
       116: goto          119
       119: aload         4
       121: instanceof    #15                 // class scala/collection/immutable/OldHashSet$OldHashSetCollision1
       124: ifeq          189
       127: aload         4
       129: checkcast     #15                 // class scala/collection/immutable/OldHashSet$OldHashSetCollision1
       132: astore        6
       134: aload         6
       136: invokevirtual #140                // Method scala/collection/immutable/OldHashSet$OldHashSetCollision1.ks:()Lscala/collection/immutable/ListSet;
       139: aload_0
       140: invokevirtual #44                 // Method key:()Ljava/lang/Object;
       143: invokevirtual #119                // Method scala/collection/immutable/ListSet.$plus:(Ljava/lang/Object;)Lscala/collection/immutable/SetOps;
       146: checkcast     #115                // class scala/collection/immutable/ListSet
       149: astore        7
       151: aload         7
       153: invokevirtual #142                // Method scala/collection/immutable/ListSet.size:()I
       156: aload         6
       158: invokevirtual #140                // Method scala/collection/immutable/OldHashSet$OldHashSetCollision1.ks:()Lscala/collection/immutable/ListSet;
       161: invokevirtual #142                // Method scala/collection/immutable/ListSet.size:()I
       164: if_icmpne     172
       167: aload         6
       169: goto          185
       172: new           #15                 // class scala/collection/immutable/OldHashSet$OldHashSetCollision1
       175: dup
       176: aload_0
       177: invokevirtual #89                 // Method hash:()I
       180: aload         7
       182: invokespecial #125                // Method scala/collection/immutable/OldHashSet$OldHashSetCollision1."<init>":(ILscala/collection/immutable/ListSet;)V
       185: astore_3
       186: goto          202
       189: goto          192
       192: new           #144                // class scala/MatchError
       195: dup
       196: aload         4
       198: invokespecial #145                // Method scala/MatchError."<init>":(Ljava/lang/Object;)V
       201: athrow
       202: aload_3
       203: areturn
      StackMapTable: number_of_entries = 11
        frame_type = 253 /* append */
          offset_delta = 38
          locals = [ top, class scala/collection/immutable/OldHashSet$LeafOldHashSet ]
        frame_type = 2 /* same */
        frame_type = 252 /* append */
          offset_delta = 33
          locals = [ class scala/collection/immutable/OldHashSet$OldHashSet1 ]
        frame_type = 100 /* same_locals_1_stack_item */
          stack = [ class scala/collection/immutable/OldHashSet$LeafOldHashSet ]
        frame_type = 250 /* chop */
          offset_delta = 3
        frame_type = 2 /* same */
        frame_type = 254 /* append */
          offset_delta = 52
          locals = [ top, class scala/collection/immutable/OldHashSet$OldHashSetCollision1, class scala/collection/immutable/ListSet ]
        frame_type = 76 /* same_locals_1_stack_item */
          stack = [ class scala/collection/immutable/OldHashSet$OldHashSetCollision1 ]
        frame_type = 248 /* chop */
          offset_delta = 3
        frame_type = 2 /* same */
        frame_type = 255 /* full_frame */
          offset_delta = 9
          locals = [ class scala/collection/immutable/OldHashSet$OldHashSet1, class scala/collection/immutable/OldHashSet$LeafOldHashSet, int, class scala/collection/immutable/OldHashSet, class scala/collection/immutable/OldHashSet$LeafOldHashSet ]
          stack = []
      LineNumberTable:
        line 272: 0
        line 273: 3
        line 276: 15
        line 272: 38
        line 277: 41
        line 278: 56
        line 279: 71
        line 282: 75
        line 277: 116
        line 284: 119
        line 285: 134
        line 287: 151
        line 288: 167
        line 290: 172
        line 284: 189
        line 272: 192
      LocalVariableTable:
        Start  Length  Slot  Name   Signature
          151      34     7   ks1   Lscala/collection/immutable/ListSet;
            0     204     0  this   Lscala/collection/immutable/OldHashSet$OldHashSet1;
            0     204     1  that   Lscala/collection/immutable/OldHashSet$LeafOldHashSet;
            0     204     2 level   I
    Signature: #136                         // (Lscala/collection/immutable/OldHashSet$LeafOldHashSet<TA;>;I)Lscala/collection/immutable/OldHashSet<TA;>;
    MethodParameters:
      Name                           Flags
      that                           final
      level                          final

  public scala.collection.immutable.OldHashSet<A> union0(scala.collection.immutable.OldHashSet<A>, int, scala.collection.immutable.OldHashSet<A>[], int);
    descriptor: (Lscala/collection/immutable/OldHashSet;I[Lscala/collection/immutable/OldHashSet;I)Lscala/collection/immutable/OldHashSet;
    flags: (0x0001) ACC_PUBLIC
    Code:
      stack=3, locals=5, args_size=5
         0: aload_1
         1: aload_0
         2: iload_2
         3: invokevirtual #154                // Method scala/collection/immutable/OldHashSet.union0:(Lscala/collection/immutable/OldHashSet$LeafOldHashSet;I)Lscala/collection/immutable/OldHashSet;
         6: areturn
      LineNumberTable:
        line 297: 0
      LocalVariableTable:
        Start  Length  Slot  Name   Signature
            0       7     0  this   Lscala/collection/immutable/OldHashSet$OldHashSet1;
            0       7     1  that   Lscala/collection/immutable/OldHashSet;
            0       7     2 level   I
            0       7     3 buffer   [Lscala/collection/immutable/OldHashSet;
            0       7     4 offset0   I
    Signature: #150                         // (Lscala/collection/immutable/OldHashSet<TA;>;I[Lscala/collection/immutable/OldHashSet<TA;>;I)Lscala/collection/immutable/OldHashSet<TA;>;
    MethodParameters:
      Name                           Flags
      that                           final
      level                          final
      buffer                         final
      offset0                        final

  public scala.collection.immutable.OldHashSet<A> intersect0(scala.collection.immutable.OldHashSet<A>, int, scala.collection.immutable.OldHashSet<A>[], int);
    descriptor: (Lscala/collection/immutable/OldHashSet;I[Lscala/collection/immutable/OldHashSet;I)Lscala/collection/immutable/OldHashSet;
    flags: (0x0001) ACC_PUBLIC
    Code:
      stack=4, locals=5, args_size=5
         0: aload_1
         1: aload_0
         2: invokevirtual #44                 // Method key:()Ljava/lang/Object;
         5: aload_0
         6: invokevirtual #89                 // Method hash:()I
         9: iload_2
        10: invokevirtual #132                // Method scala/collection/immutable/OldHashSet.get0:(Ljava/lang/Object;II)Z
        13: ifeq          20
        16: aload_0
        17: goto          21
        20: aconst_null
        21: areturn
      StackMapTable: number_of_entries = 2
        frame_type = 20 /* same */
        frame_type = 64 /* same_locals_1_stack_item */
          stack = [ class scala/collection/immutable/OldHashSet$OldHashSet1 ]
      LineNumberTable:
        line 301: 0
      LocalVariableTable:
        Start  Length  Slot  Name   Signature
            0      22     0  this   Lscala/collection/immutable/OldHashSet$OldHashSet1;
            0      22     1  that   Lscala/collection/immutable/OldHashSet;
            0      22     2 level   I
            0      22     3 buffer   [Lscala/collection/immutable/OldHashSet;
            0      22     4 offset0   I
    Signature: #150                         // (Lscala/collection/immutable/OldHashSet<TA;>;I[Lscala/collection/immutable/OldHashSet<TA;>;I)Lscala/collection/immutable/OldHashSet<TA;>;
    MethodParameters:
      Name                           Flags
      that                           final
      level                          final
      buffer                         final
      offset0                        final

  public scala.collection.immutable.OldHashSet<A> diff0(scala.collection.immutable.OldHashSet<A>, int, scala.collection.immutable.OldHashSet<A>[], int);
    descriptor: (Lscala/collection/immutable/OldHashSet;I[Lscala/collection/immutable/OldHashSet;I)Lscala/collection/immutable/OldHashSet;
    flags: (0x0001) ACC_PUBLIC
    Code:
      stack=4, locals=5, args_size=5
         0: aload_1
         1: aload_0
         2: invokevirtual #44                 // Method key:()Ljava/lang/Object;
         5: aload_0
         6: invokevirtual #89                 // Method hash:()I
         9: iload_2
        10: invokevirtual #132                // Method scala/collection/immutable/OldHashSet.get0:(Ljava/lang/Object;II)Z
        13: ifeq          20
        16: aconst_null
        17: goto          21
        20: aload_0
        21: areturn
      StackMapTable: number_of_entries = 2
        frame_type = 20 /* same */
        frame_type = 64 /* same_locals_1_stack_item */
          stack = [ class scala/collection/immutable/OldHashSet$OldHashSet1 ]
      LineNumberTable:
        line 304: 0
      LocalVariableTable:
        Start  Length  Slot  Name   Signature
            0      22     0  this   Lscala/collection/immutable/OldHashSet$OldHashSet1;
            0      22     1  that   Lscala/collection/immutable/OldHashSet;
            0      22     2 level   I
            0      22     3 buffer   [Lscala/collection/immutable/OldHashSet;
            0      22     4 offset0   I
    Signature: #150                         // (Lscala/collection/immutable/OldHashSet<TA;>;I[Lscala/collection/immutable/OldHashSet<TA;>;I)Lscala/collection/immutable/OldHashSet<TA;>;
    MethodParameters:
      Name                           Flags
      that                           final
      level                          final
      buffer                         final
      offset0                        final

  public scala.collection.immutable.OldHashSet<A> filter0(scala.Function1<A, java.lang.Object>, boolean, int, scala.collection.immutable.OldHashSet<A>[], int);
    descriptor: (Lscala/Function1;ZI[Lscala/collection/immutable/OldHashSet;I)Lscala/collection/immutable/OldHashSet;
    flags: (0x0001) ACC_PUBLIC
    Code:
      stack=3, locals=6, args_size=6
         0: iload_2
         1: aload_1
         2: aload_0
         3: invokevirtual #44                 // Method key:()Ljava/lang/Object;
         6: invokeinterface #58,  2           // InterfaceMethod scala/Function1.apply:(Ljava/lang/Object;)Ljava/lang/Object;
        11: invokestatic  #166                // Method scala/runtime/BoxesRunTime.unboxToBoolean:(Ljava/lang/Object;)Z
        14: ixor
        15: ifeq          22
        18: aload_0
        19: goto          23
        22: aconst_null
        23: areturn
      StackMapTable: number_of_entries = 2
        frame_type = 22 /* same */
        frame_type = 64 /* same_locals_1_stack_item */
          stack = [ class scala/collection/immutable/OldHashSet$OldHashSet1 ]
      LineNumberTable:
        line 307: 0
      LocalVariableTable:
        Start  Length  Slot  Name   Signature
            0      24     0  this   Lscala/collection/immutable/OldHashSet$OldHashSet1;
            0      24     1     p   Lscala/Function1;
            0      24     2 negate   Z
            0      24     3 level   I
            0      24     4 buffer   [Lscala/collection/immutable/OldHashSet;
            0      24     5 offset0   I
    Signature: #160                         // (Lscala/Function1<TA;Ljava/lang/Object;>;ZI[Lscala/collection/immutable/OldHashSet<TA;>;I)Lscala/collection/immutable/OldHashSet<TA;>;
    MethodParameters:
      Name                           Flags
      p                              final
      negate                         final
      level                          final
      buffer                         final
      offset0                        final

  public java.lang.Object init();
    descriptor: ()Ljava/lang/Object;
    flags: (0x1041) ACC_PUBLIC, ACC_BRIDGE, ACC_SYNTHETIC
    Code:
      stack=1, locals=1, args_size=1
         0: aload_0
         1: invokevirtual #169                // Method init:()Lscala/collection/immutable/OldHashSet;
         4: areturn
      LineNumberTable:
        line 228: 0
      LocalVariableTable:
        Start  Length  Slot  Name   Signature
            0       5     0  this   Lscala/collection/immutable/OldHashSet$OldHashSet1;

  public java.lang.Object tail();
    descriptor: ()Ljava/lang/Object;
    flags: (0x1041) ACC_PUBLIC, ACC_BRIDGE, ACC_SYNTHETIC
    Code:
      stack=1, locals=1, args_size=1
         0: aload_0
         1: invokevirtual #171                // Method tail:()Lscala/collection/immutable/OldHashSet;
         4: areturn
      LineNumberTable:
        line 228: 0
      LocalVariableTable:
        Start  Length  Slot  Name   Signature
            0       5     0  this   Lscala/collection/immutable/OldHashSet$OldHashSet1;

  public scala.Option headOption();
    descriptor: ()Lscala/Option;
    flags: (0x1041) ACC_PUBLIC, ACC_BRIDGE, ACC_SYNTHETIC
    Code:
      stack=1, locals=1, args_size=1
         0: aload_0
         1: invokevirtual #174                // Method headOption:()Lscala/Some;
         4: areturn
      LineNumberTable:
        line 228: 0
      LocalVariableTable:
        Start  Length  Slot  Name   Signature
            0       5     0  this   Lscala/collection/immutable/OldHashSet$OldHashSet1;

  public scala.collection.immutable.OldHashSet$OldHashSet1(A, int);
    descriptor: (Ljava/lang/Object;I)V
    flags: (0x0001) ACC_PUBLIC
    Code:
      stack=2, locals=3, args_size=3
         0: aload_0
         1: aload_1
         2: putfield      #25                 // Field key:Ljava/lang/Object;
         5: aload_0
         6: iload_2
         7: putfield      #30                 // Field hash:I
        10: aload_0
        11: invokespecial #178                // Method scala/collection/immutable/OldHashSet$LeafOldHashSet."<init>":()V
        14: return
      LineNumberTable:
        line 228: 0
      LocalVariableTable:
        Start  Length  Slot  Name   Signature
            0      15     0  this   Lscala/collection/immutable/OldHashSet$OldHashSet1;
            0      15     1   key   Ljava/lang/Object;
            0      15     2  hash   I
    Signature: #175                         // (TA;I)V
    MethodParameters:
      Name                           Flags
      key                            final
      hash                           final
}
InnerClasses:
  public static final #11= #8 of #10;     // HashTrieSet=class scala/collection/immutable/OldHashSet$HashTrieSet of class scala/collection/immutable/OldHashSet
  public static abstract #12= #5 of #10;  // LeafOldHashSet=class scala/collection/immutable/OldHashSet$LeafOldHashSet of class scala/collection/immutable/OldHashSet
  public static final #13= #2 of #10;     // OldHashSet1=class scala/collection/immutable/OldHashSet$OldHashSet1 of class scala/collection/immutable/OldHashSet
  public static final #16= #15 of #10;    // OldHashSetCollision1=class scala/collection/immutable/OldHashSet$OldHashSetCollision1 of class scala/collection/immutable/OldHashSet
Signature: #3                           // <A:Ljava/lang/Object;>Lscala/collection/immutable/OldHashSet$LeafOldHashSet<TA;>;
SourceFile: "OldHashSet.scala"
  ScalaInlineInfo: length = 0x81 (unknown attribute)
   01 01 00 19 00 42 00 63 01 00 9D 00 95 01 00 9E
   00 9F 01 00 31 00 32 01 00 54 00 55 01 00 14 00
   1C 01 00 3C 00 16 01 00 3D 00 AC 01 00 3D 00 3E
   01 00 52 00 16 01 00 52 00 47 01 00 9C 00 95 01
   00 1F 00 20 01 00 22 00 23 01 00 11 00 16 01 00
   21 00 1C 01 00 51 00 16 01 00 7E 00 61 01 00 53
   00 1C 01 00 7F 00 80 01 00 46 00 16 01 00 46 00
   47 01 00 86 00 87 01 00 86 00 95 01 00 60 00 61
   01
  Scala: length = 0x0 (unknown attribute)

