Classfile /Users/mw/Projects/slang-braindump/.jar/jar8/assemble/slang-braindump/assemble/content/scala/collection/immutable/OldHashSet.class
  Last modified May 29, 2022; size 24354 bytes
  SHA-256 checksum 80f12fbe76620524745c2c4e4abafc5661b0a3e81b6c36c8a7b4a42026c0a68a
  Compiled from "OldHashSet.scala"
public abstract class scala.collection.immutable.OldHashSet<A extends java.lang.Object> extends scala.collection.immutable.AbstractSet<A> implements scala.collection.StrictOptimizedIterableOps<A, scala.collection.immutable.OldHashSet, scala.collection.immutable.OldHashSet<A>>, java.io.Serializable
  minor version: 0
  major version: 52
  flags: (0x0421) ACC_PUBLIC, ACC_SUPER, ACC_ABSTRACT
  this_class: #2                          // scala/collection/immutable/OldHashSet
  super_class: #5                         // scala/collection/immutable/AbstractSet
  interfaces: 2, fields: 0, methods: 72, attributes: 6
Constant pool:
    #1 = Utf8               scala/collection/immutable/OldHashSet
    #2 = Class              #1            // scala/collection/immutable/OldHashSet
    #3 = Utf8               <A:Ljava/lang/Object;>Lscala/collection/immutable/AbstractSet<TA;>;Lscala/collection/StrictOptimizedIterableOps<TA;Lscala/collection/immutable/OldHashSet;Lscala/collection/immutable/OldHashSet<TA;>;>;Ljava/io/Serializable;
    #4 = Utf8               scala/collection/immutable/AbstractSet
    #5 = Class              #4            // scala/collection/immutable/AbstractSet
    #6 = Utf8               scala/collection/StrictOptimizedIterableOps
    #7 = Class              #6            // scala/collection/StrictOptimizedIterableOps
    #8 = Utf8               java/io/Serializable
    #9 = Class              #8            // java/io/Serializable
   #10 = Utf8               OldHashSet.scala
   #11 = Utf8               Lscala/reflect/ScalaSignature;
   #12 = Utf8               bytes
   #13 = Utf8               \u0006\u0005\u0015Md\u0001CA\u0002\u0003\u000b\t\t#a\u0005\t\u000f\u0005u\u0003\u0001\"\u0001\u0002`!A\u0011\u0011\r\u0001!\n#\n\u0019\u0007C\u0004\u0002|\u0001!\t%! \t\u000f\u0011]\u0007\u0001\"\u0001\u0005Z\"9AQ\u001c\u0001\u0005\u0002\u0011}\u0007b\u0002Cr\u0001\u0011\u0005AQ\u001d\u0005\b\tS\u0004A\u0011\tCv\u0011\u001d!)\u0010\u0001C!\toDq\u0001\"@\u0001\t\u0003\"y\u0010C\u0004\u0006\u0004\u0001!\t%\"\u0002\t\u000f\u0015%\u0001\u0001\"\u0011\u0006\f!9Q\u0011\u0003\u0001\u0005B\u0015M\u0001b\u0002B\u0011\u0001\u0011\u0005Sq\u0003\u0005\b\u0005K\u0001A\u0011IC\f\u0011\u001d\u0011I\u0003\u0001D\t\u000b3A\u0011Ba\u0011\u0001\r#\tI!\"\t\t\u000f\t%\u0006A\"\u0005\u0006*!9!\u0011\u001c\u0001\u0007\u0012\u0015E\u0002b\u0002B\u001d\u0001\u0019EQq\b\u0005\n\u0005{\u0004a\u0011AA\u0003\u000b\u000bBqA!@\u0001\r#)\u0019\u0006C\u0004\u0004\u0010\u00011\t\"\"\u0018\t\u000f\rm\u0001A\"\u0005\u0006h\u001dAQQJA\u0003\u0011\u0003\tyH\u0002\u0005\u0002\u0004\u0005\u0015\u0001\u0012AAA\u0011\u001d\ti&\u0007C\u0001\u0003\u001fCq!!%\u001a\t\u0003\t\u0019\nC\u0004\u0002(f!\t!!+\t\u000f\u0005M\u0016\u0004\"\u0001\u00026\u001e9\u00111Z\r\t\n\u00055gaBAi3!%\u00111\u001b\u0005\b\u0003;zB\u0011AAl\u0011\u001d\tIn\bC\u0001\u00037Dq!a9 \t\u0003\n)\u000fC\u0004\u0002n~!\t%a<\t\u000f\u0005]x\u0004\"\u0011\u0002z\"9!1C\u0010\u0005B\tU\u0001b\u0002B\f?\u0011\u0005#\u0011\u0004\u0005\b\u0005CyB\u0011\tB\u0012\u0011\u001d\u0011)c\bC!\u0005GAqAa\n \t\u0003\ny\u000fC\u0004\u0003*}!\tBa\u000b\t\u000f\ter\u0004\"\u0005\u0003<!I!1I\u0010\u0005\u0012\u0005%!Q\t\u0005\b\u0005S{B\u0011CBW\u0011%\u0011ip\bC\u0001\u0003\u000b\u0019)\fC\u0004\u0003~~!\tb!0\t\u000f\r=q\u0004\"\u0005\u0004J\"911D\u0010\u0005\u0012\rM\u0007b\u0002Bm?\u0011E1Q\u001c\u0005\n\u0007W|\u0012\u0011!C\u0005\u0007[4\u0011B!\u0015\u001a\u0003C\t)Aa\u0015\t\u000f\u0005uC\u0007\"\u0001\u0003^!A!1\u0007\u001b\u0007\u0002e\tyO\u0002\u0005\u0003Je\u0011\u0011Q\u0001B&\u0011-\u0011Ij\u000eBC\u0002\u0013\u0005\u0011da\u000b\t\u0015\r5rG!A!\u0002\u0013\u00199\u0003C\u0006\u00034]\u0012)\u0019!C\u00013\u0005=\bB\u0003B8o\t\u0005\t\u0015!\u0003\u0002r\"9\u0011QL\u001c\u0005\u0002\r=\u0002bBAro\u0011\u0005\u0013Q\u001d\u0005\b\u0003[<D\u0011IAx\u0011\u001d\tIn\u000eC\u0001\u0007oAq!a>8\t\u0003\u001aY\u0004C\u0004\u0003\u0014]\"\tea\u000b\t\u000f\t]q\u0007\"\u0011\u0004H!9!\u0011E\u001c\u0005B\r=\u0003bBB*o\u0011\u000531\u0006\u0005\b\u0005K9D\u0011IB(\u0011\u001d\u00119c\u000eC!\u0003_DqA!\u000b8\t#\u0019)\u0006C\u0005\u0003D]\"\t\"!\u0003\u0004^!9!\u0011V\u001c\u0005\u0012\r\u0015\u0004b\u0002B\u001do\u0011E1Q\u000e\u0005\n\u0005{<D\u0011AA\u0003\u0007gBqA!@8\t#\u0019I\bC\u0004\u0004\u0010]\"\tb!\"\t\u000f\rmq\u0007\"\u0005\u0004\u0010\"9!\u0011\\\u001c\u0005\u0012\ree\u0001\u0003B23\t\t)A!\u001a\t\u0017\tM\u0002K!b\u0001\n\u0003I\u0012q\u001e\u0005\u000b\u0005_\u0002&\u0011!Q\u0001\n\u0005E\bB\u0003B9!\n\u0015\r\u0011\"\u0001\u0003t!Q!1\u0010)\u0003\u0002\u0003\u0006IA!\u001e\t\u000f\u0005u\u0003\u000b\"\u0001\u0003~!9\u00111\u001d)\u0005B\u0005\u0015\bb\u0002B\u0014!\u0012\u0005\u0013q\u001e\u0005\b\u00033\u0004F\u0011\u0001BC\u0011\u001d\t9\u0010\u0015C!\u0005\u0013CqA!\u000bQ\t#\u0011)\nC\u0005\u0003DA#\t\"!\u0003\u0003 \"9!\u0011\u0016)\u0005\u0012\t-\u0006b\u0002BZ!\u0012%!Q\u0017\u0005\b\u0005\u0017\u0004F\u0011\u0002Bg\u0011\u001d\u0011I\u000e\u0015C\t\u00057DqA!\u000fQ\t#\u00119\u0010C\u0005\u0003~B#\t!!\u0002\u0003\u0000\"9!Q )\u0005\u0012\r\u0015\u0001bBB\b!\u0012E1\u0011\u0003\u0005\b\u00077\u0001F\u0011CB\u000f\r!\u0019Y0\u0007\u0002\u0002\n\ru\bB\u0003C\u0004K\n\u0015\r\u0011\"\u0003\u0002p\"QA\u0011B3\u0003\u0002\u0003\u0006I!!=\t\u0019\u0011-QM!b\u0001\n\u0003\tI\u0001\"\u0004\t\u0015\u0011EQM!A!\u0002\u0013!y\u0001\u0003\u0006\u0005\u0014\u0015\u0014)\u0019!C\u0005\u0003_D!\u0002\"\u0006f\u0005\u0003\u0005\u000b\u0011BAy\u0011\u001d\ti&\u001aC\u0001\t/AqAa\nf\t\u0003\ny\u000fC\u0004\u0002d\u0016$\t%!:\t\u000f\u00055X\r\"\u0011\u0002p\"9\u0011\u0011\\3\u0005\u0002\u0011\u0005\u0002bBA|K\u0012\u0005CQ\u0005\u0005\b\u0005S)G\u0011\u0003C\u0019\u0011%\u0011\u0019%\u001aC\t\u0003\u0013!I\u0004C\u0004\u0003*\u0016$\t\u0002\"\u0011\t\u0013\tuX\r\"\u0001\u0002\u0006\u0011%\u0003b\u0002B\u007fK\u0012EA\u0011\u000b\u0005\b\u0007\u001f)G\u0011\u0003C.\u0011\u001d\u0019Y\"\u001aC\t\tKBqA!\u000ff\t#!y\u0007C\u0004\u0003Z\u0016$\t\u0002\"\u001e\t\u000f\u0011\r\u0015\u0004\"\u0003\u0005\u0006\"9A1U\r\u0005\n\u0011\u0015\u0006b\u0002CY3\u0011%A1\u0017\u0005\t\u0005gK\u0002\u0015\"\u0003\u0005D\"A!1Z\r!\n\u0013!9\rC\u0005\u0004lf\t\t\u0011\"\u0003\u0004n\nQq\n\u001c3ICND7+\u001a;\u000b\t\u0005\u001d\u0011\u0011B\u0001\nS6lW\u000f^1cY\u0016TA!a\u0003\u0002\u000e\u0005Q1m\u001c7mK\u000e$\u0018n\u001c8\u000b\u0005\u0005=\u0011!B:dC2\f7\u0001A\u000b\u0005\u0003+\t\u0019cE\u0006\u0001\u0003/\t9$!\u0011\u0002J\u0005=\u0003CBA\r\u00037\ty\"\u0004\u0002\u0002\u0006%!\u0011QDA\u0003\u0005-\t%m\u001d;sC\u000e$8+\u001a;\u0011\t\u0005\u0005\u00121\u0005\u0007\u0001\t\u001d\t)\u0003\u0001b\u0001\u0003O\u0011\u0011!Q\t\u0005\u0003S\t\t\u0004\u0005\u0003\u0002,\u00055RBAA\u0007\u0013\u0011\ty#!\u0004\u0003\u000f9{G\u000f[5oOB!\u00111FA\u001a\u0013\u0011\t)$!\u0004\u0003\u0007\u0005s\u0017\u0010\u0005\u0006\u0002\u001a\u0005e\u0012qDA\u001f\u0003\u007fIA!a\u000f\u0002\u0006\t11+\u001a;PaN\u00042!!\u0007\u0001!\u0015\tI\u0002AA\u0010!)\t\u0019%!\u0012\u0002 \u0005u\u0012qH\u0007\u0003\u0003\u0013IA!a\u0012\u0002\n\tQ2\u000b\u001e:jGR|\u0005\u000f^5nSj,G-\u0013;fe\u0006\u0014G.Z(qgBA\u00111IA&\u0003?\ti$\u0003\u0003\u0002N\u0005%!aF%uKJ\f\'\r\\3GC\u000e$xN]=EK\u001a\fW\u000f\u001c;t!\u0011\t\t&a\u0016\u000f\t\u0005-\u00121K\u0005\u0005\u0003+\ni!A\u0004qC\u000e\\\u0017mZ3\n\t\u0005e\u00131\f\u0002\r\'\u0016\u0014\u0018.\u00197ju\u0006\u0014G.\u001a\u0006\u0005\u0003+\ni!\u0001\u0004=S:LGO\u0010\u000b\u0003\u0003\u007f\t\u0011b\u00197bgNt\u0015-\\3\u0016\u0005\u0005\u0015\u0004\u0003BA4\u0003krA!!\u001b\u0002rA!\u00111NA\u0007\u001b\t\tiG\u0003\u0003\u0002p\u0005E\u0011A\u0002\u001fs_>$h(\u0003\u0003\u0002t\u00055\u0011A\u0002)sK\u0012,g-\u0003\u0003\u0002x\u0005e$AB*ue&twM\u0003\u0003\u0002t\u00055\u0011aD5uKJ\f\'\r\\3GC\u000e$xN]=\u0016\u0005\u0005}\u0004cAA\r3M)\u0011$a!\u0002\nB!\u00111FAC\u0013\u0011\t9)!\u0004\u0003\r\u0005s\u0017PU3g!\u0019\t\u0019%a#\u0002>%!\u0011QRA\u0005\u0005=IE/\u001a:bE2,g)Y2u_JLHCAA@\u0003\u00111\'o\\7\u0016\t\u0005U\u00151\u0014\u000b\u0005\u0003/\u000bi\nE\u0003\u0002\u001a\u0001\tI\n\u0005\u0003\u0002\"\u0005mEaBA\u00137\t\u0007\u0011q\u0005\u0005\b\u0003?[\u0002\u0019AAQ\u0003\tIG\u000f\u0005\u0004\u0002D\u0005\r\u0016\u0011T\u0005\u0005\u0003K\u000bIA\u0001\u0007Ji\u0016\u0014\u0018M\u00197f\u001f:\u001cW-A\u0003f[B$\u00180\u0006\u0003\u0002,\u0006EVCAAW!\u0015\tI\u0002AAX!\u0011\t\t#!-\u0005\u000f\u0005\u0015BD1\u0001\u0002(\u0005Qa.Z<Ck&dG-\u001a:\u0016\t\u0005]\u0016qY\u000b\u0003\u0003s\u0003\u0002\"a/\u0002B\u0006\u0015\u0017\u0011Z\u0007\u0003\u0003{SA!a0\u0002\n\u00059Q.\u001e;bE2,\u0017\u0002BAb\u0003{\u0013qAQ;jY\u0012,\'\u000f\u0005\u0003\u0002\"\u0005\u001dGaBA\u0013;\t\u0007\u0011q\u0005\t\u0006\u00033\u0001\u0011QY\u0001\u0010\u000b6\u0004H/_(mI\"\u000b7\u000f[*fiB\u0019\u0011qZ\u0010\u000e\u0003e\u0011q\"R7qif|E\u000e\u001a%bg\"\u001cV\r^\n\u0004?\u0005U\u0007#BA\r\u0001\u0005EBCAAg\u0003!IG/\u001a:bi>\u0014XCAAo!\u0019\t\u0019%a8\u00022%!\u0011\u0011]A\u0005\u0005!IE/\u001a:bi>\u0014\u0018aB5t\u000b6\u0004H/_\u000b\u0003\u0003O\u0004B!a\u000b\u0002j&!\u00111^A\u0007\u0005\u001d\u0011un\u001c7fC:\f\u0011b\u001b8po:\u001c\u0016N_3\u0016\u0005\u0005E\b\u0003BA\u0016\u0003gLA!!>\u0002\u000e\t\u0019\u0011J\u001c;\u0002\u000f\u0019|\'/Z1dQV!\u00111 B\b)\u0011\tiPa\u0001\u0011\t\u0005-\u0012q`\u0005\u0005\u0005\u0003\tiA\u0001\u0003V]&$\bb\u0002B\u0003I\u0001\u0007!qA\u0001\u0002MBA\u00111\u0006B\u0005\u0003c\u0011i!\u0003\u0003\u0003\f\u00055!!\u0003$v]\u000e$\u0018n\u001c82!\u0011\t\tCa\u0004\u0005\u000f\tEAE1\u0001\u0002(\t\tQ+\u0001\u0003iK\u0006$WCAA\u0019\u0003)AW-\u00193PaRLwN\\\u000b\u0003\u00057qA!a\u000b\u0003\u001e%!!qDA\u0007\u0003\u0011quN\\3\u0002\tQ\f\u0017\u000e\\\u000b\u0003\u0003+\fA!\u001b8ji\u0006!1/\u001b>f\u0003\u00119W\r\u001e\u0019\u0015\u0011\u0005\u001d(Q\u0006B\u0019\u0005kAqAa\f+\u0001\u0004\t\t$\u0001\u0003fY\u0016l\u0007b\u0002B\u001aU\u0001\u0007\u0011\u0011_\u0001\u0005Q\u0006\u001c\b\u000eC\u0004\u00038)\u0002\r!!=\u0002\u000b1,g/\u001a7\u0002\u0013M,(m]3u\u001f\u001a\u0004DCBAt\u0005{\u0011\t\u0005C\u0004\u0003@-\u0002\r!!6\u0002\tQD\u0017\r\u001e\u0005\b\u0005oY\u0003\u0019AAy\u0003!)\b\u000fZ1uK\u0012\u0004D\u0003\u0003B$\u0007O\u001bIka+\u0011\u000b\u0005=w\'!\r\u0003\u0017=cG\rS1tQN+G/M\u000b\u0005\u0005\u001b\u001aIcE\u00028\u0005\u001f\u0002R!a45\u0007O\u0011a\u0002T3bM>cG\rS1tQN+G/\u0006\u0003\u0003V\tm3c\u0001\u001b\u0003XA)\u0011\u0011\u0004\u0001\u0003ZA!\u0011\u0011\u0005B.\t\u001d\t)\u0003\u000eb\u0001\u0003O!\"Aa\u0018\u0011\u000b\u0005=GG!\u0017*\u0007Q:\u0004K\u0001\u000bPY\u0012D\u0015m\u001d5TKR\u001cu\u000e\u001c7jg&|g.M\u000b\u0005\u0005O\u0012igE\u0002Q\u0005S\u0002R!a45\u0005W\u0002B!!\t\u0003n\u00119\u0011Q\u0005)C\u0002\u0005\u001d\u0012!\u00025bg\"\u0004\u0013AA6t+\t\u0011)\b\u0005\u0004\u0002\u001a\t]$1N\u0005\u0005\u0005s\n)AA\u0004MSN$8+\u001a;\u0002\u0007-\u001c\b\u0005\u0006\u0004\u0003\u0000\t\u0005%1\u0011\t\u0006\u0003\u001f\u0004&1\u000e\u0005\b\u0005g)\u0006\u0019AAy\u0011\u001d\u0011\t(\u0016a\u0001\u0005k*\"Aa\"\u0011\r\u0005\r\u0013q\u001cB6+\u0011\u0011YIa%\u0015\t\u0005u(Q\u0012\u0005\b\u0005\u000bI\u0006\u0019\u0001BH!!\tYC!\u0003\u0003l\tE\u0005\u0003BA\u0011\u0005\'#qA!\u0005Z\u0005\u0004\t9\u0003\u0006\u0005\u0002h\n]%1\u0014BO\u0011\u001d\u0011IJ\u0017a\u0001\u0005W\n1a[3z\u0011\u001d\u0011\u0019D\u0017a\u0001\u0003cDqAa\u000e[\u0001\u0004\t\t\u0010\u0006\u0005\u0003\"\n\r&Q\u0015BT!\u0015\tI\u0002\u0001B6\u0011\u001d\u0011Ij\u0017a\u0001\u0005WBqAa\r\\\u0001\u0004\t\t\u0010C\u0004\u00038m\u0003\r!!=\u0002\u0011I,Wn\u001c<fIB\"\u0002B!)\u0003.\n=&\u0011\u0017\u0005\b\u00053c\u0006\u0019\u0001B6\u0011\u001d\u0011\u0019\u0004\u0018a\u0001\u0003cDqAa\u000e]\u0001\u0004\t\t0A\u0006xe&$Xm\u00142kK\u000e$H\u0003BA\u007f\u0005oCqA!/^\u0001\u0004\u0011Y,A\u0002pkR\u0004BA!0\u0003H6\u0011!q\u0018\u0006\u0005\u0005\u0003\u0014\u0019-\u0001\u0002j_*\u0011!QY\u0001\u0005U\u00064\u0018-\u0003\u0003\u0003J\n}&AE(cU\u0016\u001cGoT;uaV$8\u000b\u001e:fC6\f!B]3bI>\u0013\'.Z2u)\u0011\tiPa4\t\u000f\tEg\f1\u0001\u0003T\u0006\u0011\u0011N\u001c\t\u0005\u0005{\u0013).\u0003\u0003\u0003X\n}&!E(cU\u0016\u001cG/\u00138qkR\u001cFO]3b[\u00069a-\u001b7uKJ\u0004D\u0003\u0004BQ\u0005;\u0014\u0019Oa:\u0003j\nM\bb\u0002Bp?\u0002\u0007!\u0011]\u0001\u0002aBA\u00111\u0006B\u0005\u0005W\n9\u000fC\u0004\u0003f~\u0003\r!a:\u0002\r9,w-\u0019;f\u0011\u001d\u00119d\u0018a\u0001\u0003cDqAa;`\u0001\u0004\u0011i/\u0001\u0004ck\u001a4WM\u001d\t\u0007\u0003W\u0011yO!)\n\t\tE\u0018Q\u0002\u0002\u0006\u0003J\u0014\u0018-\u001f\u0005\b\u0005k|\u0006\u0019AAy\u0003\u001dygMZ:fiB\"b!a:\u0003z\nm\bb\u0002B A\u0002\u0007!\u0011\u0015\u0005\b\u0005o\u0001\u0007\u0019AAy\u0003\u0019)h.[8oaQ1!\u0011UB\u0001\u0007\u0007AqAa\u0010b\u0001\u0004\u0011I\u0007C\u0004\u00038\u0005\u0004\r!!=\u0015\u0015\t\u00056qAB\u0005\u0007\u0017\u0019i\u0001C\u0004\u0003@\t\u0004\rA!)\t\u000f\t]\"\r1\u0001\u0002r\"9!1\u001e2A\u0002\t5\bb\u0002B{E\u0002\u0007\u0011\u0011_\u0001\u000bS:$XM]:fGR\u0004DC\u0003BQ\u0007\'\u0019)ba\u0006\u0004\u001a!9!qH2A\u0002\t\u0005\u0006b\u0002B\u001cG\u0002\u0007\u0011\u0011\u001f\u0005\b\u0005W\u001c\u0007\u0019\u0001Bw\u0011\u001d\u0011)p\u0019a\u0001\u0003c\fQ\u0001Z5gMB\"\"B!)\u0004 \r\u000521EB\u0013\u0011\u001d\u0011y\u0004\u001aa\u0001\u0005CCqAa\u000ee\u0001\u0004\t\t\u0010C\u0004\u0003l\u0012\u0004\rA!<\t\u000f\tUH\r1\u0001\u0002rB!\u0011\u0011EB\u0015\t\u001d\t)c\u000eb\u0001\u0003O)\"aa\n\u0002\t-,\u0017\u0010\t\u000b\u0007\u0007c\u0019\u0019d!\u000e\u0011\u000b\u0005=wga\n\t\u000f\teE\b1\u0001\u0004(!9!1\u0007\u001fA\u0002\u0005EXCAB\u001d!\u0019\t\u0019%a8\u0004(U!1QHB#)\u0011\tipa\u0010\t\u000f\t\u0015\u0001\t1\u0001\u0004BAA\u00111\u0006B\u0005\u0007O\u0019\u0019\u0005\u0005\u0003\u0002\"\r\u0015Ca\u0002B\t\u0001\n\u0007\u0011qE\u000b\u0003\u0007\u0013\u0002b!a\u000b\u0004L\r\u001d\u0012\u0002BB\'\u0003\u001b\u0011AaU8nKV\u00111\u0011\u000b\t\u0006\u00033\u00011qE\u0001\u0005Y\u0006\u001cH\u000f\u0006\u0005\u0002h\u000e]3\u0011LB.\u0011\u001d\u0011Ij\u0012a\u0001\u0007OAqAa\rH\u0001\u0004\t\t\u0010C\u0004\u00038\u001d\u0003\r!!=\u0015\u0011\rE3qLB1\u0007GBqA!\'I\u0001\u0004\u00199\u0003C\u0004\u00034!\u0003\r!!=\t\u000f\t]\u0002\n1\u0001\u0002rRA1\u0011KB4\u0007S\u001aY\u0007C\u0004\u0003\u001a&\u0003\raa\n\t\u000f\tM\u0012\n1\u0001\u0002r\"9!qG%A\u0002\u0005EHCBAt\u0007_\u001a\t\bC\u0004\u0003@)\u0003\ra!\u0015\t\u000f\t]\"\n1\u0001\u0002rR11\u0011KB;\u0007oBqAa\u0010L\u0001\u0004\u0011y\u0005C\u0004\u00038-\u0003\r!!=\u0015\u0015\rE31PB?\u0007\u007f\u001a\u0019\tC\u0004\u0003@1\u0003\ra!\u0015\t\u000f\t]B\n1\u0001\u0002r\"9!1\u001e\'A\u0002\r\u0005\u0005CBA\u0016\u0005_\u001c\t\u0006C\u0004\u0003v2\u0003\r!!=\u0015\u0015\rE3qQBE\u0007\u0017\u001bi\tC\u0004\u0003@5\u0003\ra!\u0015\t\u000f\t]R\n1\u0001\u0002r\"9!1^\'A\u0002\r\u0005\u0005b\u0002B{\u001b\u0002\u0007\u0011\u0011\u001f\u000b\u000b\u0007#\u001a\tja%\u0004\u0016\u000e]\u0005b\u0002B \u001d\u0002\u00071\u0011\u000b\u0005\b\u0005oq\u0005\u0019AAy\u0011\u001d\u0011YO\u0014a\u0001\u0007\u0003CqA!>O\u0001\u0004\t\t\u0010\u0006\u0007\u0004R\rm5qTBQ\u0007G\u001b)\u000bC\u0004\u0003`>\u0003\ra!(\u0011\u0011\u0005-\"\u0011BB\u0014\u0003ODqA!:P\u0001\u0004\t9\u000fC\u0004\u00038=\u0003\r!!=\t\u000f\t-x\n1\u0001\u0004\u0002\"9!Q_(A\u0002\u0005E\bb\u0002B\u0018Y\u0001\u0007\u0011\u0011\u0007\u0005\b\u0005ga\u0003\u0019AAy\u0011\u001d\u00119\u0004\fa\u0001\u0003c$\u0002\"!4\u00040\u000eE61\u0017\u0005\b\u00053k\u0003\u0019AA\u0019\u0011\u001d\u0011\u0019$\fa\u0001\u0003cDqAa\u000e.\u0001\u0004\t\t\u0010\u0006\u0004\u0002V\u000e]61\u0018\u0005\b\u0005\u007fq\u0003\u0019AB]!\u0015\ty\rNA\u0019\u0011\u001d\u00119D\fa\u0001\u0003c$\"\"!6\u0004@\u000e\u000571YBd\u0011\u001d\u0011yd\fa\u0001\u0003+DqAa\u000e0\u0001\u0004\t\t\u0010C\u0004\u0003l>\u0002\ra!2\u0011\r\u0005-\"q^Ak\u0011\u001d\u0011)p\fa\u0001\u0003c$\"\"!6\u0004L\u000e57qZBi\u0011\u001d\u0011y\u0004\ra\u0001\u0003+DqAa\u000e1\u0001\u0004\t\t\u0010C\u0004\u0003lB\u0002\ra!2\t\u000f\tU\b\u00071\u0001\u0002rRQ\u0011Q[Bk\u0007/\u001cIna7\t\u000f\t}\u0012\u00071\u0001\u0002V\"9!qG\u0019A\u0002\u0005E\bb\u0002Bvc\u0001\u00071Q\u0019\u0005\b\u0005k\f\u0004\u0019AAy)1\t)na8\u0004d\u000e\u00158q]Bu\u0011\u001d\u0011yN\ra\u0001\u0007C\u0004\u0002\"a\u000b\u0003\n\u0005E\u0012q\u001d\u0005\b\u0005K\u0014\u0004\u0019AAt\u0011\u001d\u00119D\ra\u0001\u0003cDqAa;3\u0001\u0004\u0019)\rC\u0004\u0003vJ\u0002\r!!=\u0002\u0019]\u0014\u0018\u000e^3SKBd\u0017mY3\u0015\u0005\r=\b\u0003BBy\u0007ol!aa=\u000b\t\rU(1Y\u0001\u0005Y\u0006tw-\u0003\u0003\u0004z\u000eM(AB(cU\u0016\u001cGOA\u0006ICNDGK]5f\'\u0016$X\u0003BB\u0000\t\u000b\u00192!\u001aC\u0001!\u0015\tI\u0002\u0001C\u0002!\u0011\t\t\u0003\"\u0002\u0005\u000f\u0005\u0015RM1\u0001\u0002(\u00051!-\u001b;nCB\fqAY5u[\u0006\u0004\b%A\u0003fY\u0016l7/\u0006\u0002\u0005\u0010A1\u00111\u0006Bx\t\u0003\ta!\u001a7f[N\u0004\u0013!B:ju\u0016\u0004\u0014AB:ju\u0016\u0004\u0004\u0005\u0006\u0005\u0005\u001a\u0011mAQ\u0004C\u0010!\u0015\ty-\u001aC\u0002\u0011\u001d!9\u0001\u001ca\u0001\u0003cDq\u0001b\u0003m\u0001\u0004!y\u0001C\u0004\u0005\u00141\u0004\r!!=\u0016\u0005\u0011\r\u0002CBA\"\u0003?$\u0019!\u0006\u0003\u0005(\u0011=B\u0003BA\u007f\tSAqA!\u0002r\u0001\u0004!Y\u0003\u0005\u0005\u0002,\t%A1\u0001C\u0017!\u0011\t\t\u0003b\f\u0005\u000f\tE\u0011O1\u0001\u0002(QA\u0011q\u001dC\u001a\tk!9\u0004C\u0004\u0003\u001aJ\u0004\r\u0001b\u0001\t\u000f\tM\"\u000f1\u0001\u0002r\"9!q\u0007:A\u0002\u0005EH\u0003\u0003C\u0001\tw!i\u0004b\u0010\t\u000f\te5\u000f1\u0001\u0005\u0004!9!1G:A\u0002\u0005E\bb\u0002B\u001cg\u0002\u0007\u0011\u0011\u001f\u000b\t\t\u0003!\u0019\u0005\"\u0012\u0005H!9!\u0011\u0014;A\u0002\u0011\r\u0001b\u0002B\u001ai\u0002\u0007\u0011\u0011\u001f\u0005\b\u0005o!\b\u0019AAy)\u0019!\t\u0001b\u0013\u0005P!9!qH;A\u0002\u00115\u0003#BAhi\u0011\r\u0001b\u0002B\u001ck\u0002\u0007\u0011\u0011\u001f\u000b\u000b\t\u0003!\u0019\u0006\"\u0016\u0005X\u0011e\u0003b\u0002B m\u0002\u0007A\u0011\u0001\u0005\b\u0005o1\b\u0019AAy\u0011\u001d\u0011YO\u001ea\u0001\t\u001fAqA!>w\u0001\u0004\t\t\u0010\u0006\u0006\u0005\u0002\u0011uCq\fC1\tGBqAa\u0010x\u0001\u0004!\t\u0001C\u0004\u00038]\u0004\r!!=\t\u000f\t-x\u000f1\u0001\u0005\u0010!9!Q_<A\u0002\u0005EHC\u0003C\u0001\tO\"I\u0007b\u001b\u0005n!9!q\b=A\u0002\u0011\u0005\u0001b\u0002B\u001cq\u0002\u0007\u0011\u0011\u001f\u0005\b\u0005WD\b\u0019\u0001C\b\u0011\u001d\u0011)\u0010\u001fa\u0001\u0003c$b!a:\u0005r\u0011M\u0004b\u0002B s\u0002\u0007A\u0011\u0001\u0005\b\u0005oI\b\u0019AAy)1!\t\u0001b\u001e\u0005|\u0011uDq\u0010CA\u0011\u001d\u0011yN\u001fa\u0001\ts\u0002\u0002\"a\u000b\u0003\n\u0011\r\u0011q\u001d\u0005\b\u0005KT\b\u0019AAt\u0011\u001d\u00119D\u001fa\u0001\u0003cDqAa;{\u0001\u0004!y\u0001C\u0004\u0003vj\u0004\r!!=\u0002\u001f5\f7.\u001a%bg\"$&/[3TKR,B\u0001b\"\u0005\u000eRaA\u0011\u0012CH\t\'#I\n\"(\u0005\"B)\u0011qZ3\u0005\fB!\u0011\u0011\u0005CG\t\u001d\t)c\u001fb\u0001\u0003OAq\u0001\"%|\u0001\u0004\t\t0A\u0003iCND\u0007\u0007C\u0004\u0005\u0016n\u0004\r\u0001b&\u0002\u000b\u0015dW-\u001c\u0019\u0011\u000b\u0005e\u0001\u0001b#\t\u000f\u0011m5\u00101\u0001\u0002r\u0006)\u0001.Y:ic!9AqT>A\u0002\u0011]\u0015!B3mK6\f\u0004b\u0002B\u001cw\u0002\u0007\u0011\u0011_\u0001\u000bEV4g-\u001a:TSj,G\u0003BAy\tOCqAa\n}\u0001\u0004\t\t\u0010K\u0002}\tW\u0003B!a\u000b\u0005.&!AqVA\u0007\u0005\u0019Ig\u000e\\5oK\u0006Ya.\u001e7m)>,U\u000e\u001d;z+\u0011!)\fb/\u0015\t\u0011]FQ\u0018\t\u0006\u00033\u0001A\u0011\u0018\t\u0005\u0003C!Y\fB\u0004\u0002&u\u0014\r!a\n\t\u000f\u0011}V\u00101\u0001\u00058\u0006\t1\u000fK\u0002~\tW#B!!@\u0005F\"9!\u0011\u0018@A\u0002\tmF\u0003BA\u007f\t\u0013DqA!5\u0000\u0001\u0004\u0011\u0019\u000eK\u0004\u001a\t\u001b$\u0019\u000e\"6\u0011\t\u0005-BqZ\u0005\u0005\t#\fiA\u0001\tTKJL\u0017\r\u001c,feNLwN\\+J\t\u0006)a/\u00197vKz\t1!\u0001\u0005d_:$\u0018-\u001b8t)\u0011\t9\u000fb7\t\u000f\t=B\u00011\u0001\u0002 \u0005!\u0011N\\2m)\u0011\ty\u0004\"9\t\u000f\t=R\u00011\u0001\u0002 \u0005!Q\r_2m)\u0011\ty\u0004b:\t\u000f\t=b\u00011\u0001\u0002 \u0005A1/\u001e2tKR|e\r\u0006\u0003\u0002h\u00125\bb\u0002B \u000f\u0001\u0007Aq\u001e\t\u0007\u0003\u0007\"\t0a\b\n\t\u0011M\u0018\u0011\u0002\u0002\u0004\'\u0016$\u0018AB2p]\u000e\fG\u000f\u0006\u0003\u0002@\u0011e\bb\u0002B \u0011\u0001\u0007A1 \t\u0007\u0003\u0007\n\u0019+a\b\u0002\u0013%tG/\u001a:tK\u000e$H\u0003BA \u000b\u0003AqAa\u0010\n\u0001\u0004!y/\u0001\u0003eS\u001a4G\u0003BA \u000b\u000fAqAa\u0010\u000b\u0001\u0004!y/\u0001\u0004gS2$XM\u001d\u000b\u0005\u0003\u007f)i\u0001C\u0004\u0003`.\u0001\r!b\u0004\u0011\u0011\u0005-\"\u0011BA\u0010\u0003O\f\u0011BZ5mi\u0016\u0014hj\u001c;\u0015\t\u0005}RQ\u0003\u0005\b\u0005?d\u0001\u0019AC\b+\t\ty\u0004\u0006\u0005\u0002h\u0016mQQDC\u0010\u0011\u001d\u0011Ij\u0004a\u0001\u0003?AqAa\r\u0010\u0001\u0004\t\t\u0010C\u0004\u00038=\u0001\r!!=\u0015\u0011\u0005}R1EC\u0013\u000bOAqA!\'\u0011\u0001\u0004\ty\u0002C\u0004\u00034A\u0001\r!!=\t\u000f\t]\u0002\u00031\u0001\u0002rRA\u0011qHC\u0016\u000b[)y\u0003C\u0004\u0003\u001aF\u0001\r!a\b\t\u000f\tM\u0012\u00031\u0001\u0002r\"9!qG\tA\u0002\u0005EH\u0003DA \u000bg))$b\u000e\u0006:\u0015u\u0002b\u0002Bp%\u0001\u0007Qq\u0002\u0005\b\u0005K\u0014\u0002\u0019AAt\u0011\u001d\u00119D\u0005a\u0001\u0003cDqAa;\u0013\u0001\u0004)Y\u0004\u0005\u0004\u0002,\t=\u0018q\b\u0005\b\u0005k\u0014\u0002\u0019AAy)\u0019\t9/\"\u0011\u0006D!9!qH\nA\u0002\u0005}\u0002b\u0002B\u001c\'\u0001\u0007\u0011\u0011\u001f\u000b\u0007\u0003\u007f)9%\"\u0015\t\u000f\t}B\u00031\u0001\u0006JA)Q1\n\u001b\u0002 9\u0019\u0011\u0011\u0004\r\u0002\u0015=cG\rS1tQN+G\u000fK\u0004\u0019\t\u001b$\u0019\u000e\"6\t\u000f\t]B\u00031\u0001\u0002rRQ\u0011qHC+\u000b/*I&b\u0017\t\u000f\t}R\u00031\u0001\u0002@!9!qG\u000bA\u0002\u0005E\bb\u0002Bv+\u0001\u0007Q1\b\u0005\b\u0005k,\u0002\u0019AAy))\ty$b\u0018\u0006b\u0015\rTQ\r\u0005\b\u0005\u007f1\u0002\u0019AA \u0011\u001d\u00119D\u0006a\u0001\u0003cDqAa;\u0017\u0001\u0004)Y\u0004C\u0004\u0003vZ\u0001\r!!=\u0015\u0015\u0005}R\u0011NC6\u000b[*y\u0007C\u0004\u0003@]\u0001\r!a\u0010\t\u000f\t]r\u00031\u0001\u0002r\"9!1^\fA\u0002\u0015m\u0002b\u0002B{/\u0001\u0007\u0011\u0011_\u0015\u0005\u0001})G\u0007
   #14 = Utf8               scala/collection/immutable/OldHashSet$EmptyOldHashSet$
   #15 = Class              #14           // scala/collection/immutable/OldHashSet$EmptyOldHashSet$
   #16 = Utf8               EmptyOldHashSet$
   #17 = Utf8               scala/collection/immutable/OldHashSet$HashTrieSet
   #18 = Class              #17           // scala/collection/immutable/OldHashSet$HashTrieSet
   #19 = Utf8               HashTrieSet
   #20 = Utf8               scala/collection/immutable/OldHashSet$LeafOldHashSet
   #21 = Class              #20           // scala/collection/immutable/OldHashSet$LeafOldHashSet
   #22 = Utf8               LeafOldHashSet
   #23 = Utf8               scala/collection/immutable/OldHashSet$OldHashSet1
   #24 = Class              #23           // scala/collection/immutable/OldHashSet$OldHashSet1
   #25 = Utf8               OldHashSet1
   #26 = Utf8               scala/collection/immutable/OldHashSet$OldHashSetCollision1
   #27 = Class              #26           // scala/collection/immutable/OldHashSet$OldHashSetCollision1
   #28 = Utf8               OldHashSetCollision1
   #29 = Utf8               newBuilder
   #30 = Utf8               ()Lscala/collection/mutable/Builder;
   #31 = Utf8               <A:Ljava/lang/Object;>()Lscala/collection/mutable/Builder<TA;Lscala/collection/immutable/OldHashSet<TA;>;>;
   #32 = Utf8               scala/collection/immutable/OldHashSet$
   #33 = Class              #32           // scala/collection/immutable/OldHashSet$
   #34 = Utf8               MODULE$
   #35 = Utf8               Lscala/collection/immutable/OldHashSet$;
   #36 = NameAndType        #34:#35       // MODULE$:Lscala/collection/immutable/OldHashSet$;
   #37 = Fieldref           #33.#36       // scala/collection/immutable/OldHashSet$.MODULE$:Lscala/collection/immutable/OldHashSet$;
   #38 = NameAndType        #29:#30       // newBuilder:()Lscala/collection/mutable/Builder;
   #39 = Methodref          #33.#38       // scala/collection/immutable/OldHashSet$.newBuilder:()Lscala/collection/mutable/Builder;
   #40 = Utf8               from
   #41 = Utf8               (Lscala/collection/IterableOnce;)Lscala/collection/immutable/OldHashSet;
   #42 = Utf8               <A:Ljava/lang/Object;>(Lscala/collection/IterableOnce<TA;>;)Lscala/collection/immutable/OldHashSet<TA;>;
   #43 = Utf8               it
   #44 = NameAndType        #40:#41       // from:(Lscala/collection/IterableOnce;)Lscala/collection/immutable/OldHashSet;
   #45 = Methodref          #33.#44       // scala/collection/immutable/OldHashSet$.from:(Lscala/collection/IterableOnce;)Lscala/collection/immutable/OldHashSet;
   #46 = Utf8               Lscala/collection/IterableOnce;
   #47 = Utf8               tabulate
   #48 = Utf8               (IIIIILscala/Function5;)Ljava/lang/Object;
   #49 = Utf8               n1
   #50 = Utf8               n2
   #51 = Utf8               n3
   #52 = Utf8               n4
   #53 = Utf8               n5
   #54 = Utf8               f
   #55 = NameAndType        #47:#48       // tabulate:(IIIIILscala/Function5;)Ljava/lang/Object;
   #56 = Methodref          #33.#55       // scala/collection/immutable/OldHashSet$.tabulate:(IIIIILscala/Function5;)Ljava/lang/Object;
   #57 = Utf8               I
   #58 = Utf8               Lscala/Function5;
   #59 = Utf8               (IIIILscala/Function4;)Ljava/lang/Object;
   #60 = NameAndType        #47:#59       // tabulate:(IIIILscala/Function4;)Ljava/lang/Object;
   #61 = Methodref          #33.#60       // scala/collection/immutable/OldHashSet$.tabulate:(IIIILscala/Function4;)Ljava/lang/Object;
   #62 = Utf8               Lscala/Function4;
   #63 = Utf8               (IIILscala/Function3;)Ljava/lang/Object;
   #64 = NameAndType        #47:#63       // tabulate:(IIILscala/Function3;)Ljava/lang/Object;
   #65 = Methodref          #33.#64       // scala/collection/immutable/OldHashSet$.tabulate:(IIILscala/Function3;)Ljava/lang/Object;
   #66 = Utf8               Lscala/Function3;
   #67 = Utf8               (IILscala/Function2;)Ljava/lang/Object;
   #68 = NameAndType        #47:#67       // tabulate:(IILscala/Function2;)Ljava/lang/Object;
   #69 = Methodref          #33.#68       // scala/collection/immutable/OldHashSet$.tabulate:(IILscala/Function2;)Ljava/lang/Object;
   #70 = Utf8               Lscala/Function2;
   #71 = Utf8               (ILscala/Function1;)Ljava/lang/Object;
   #72 = Utf8               n
   #73 = NameAndType        #47:#71       // tabulate:(ILscala/Function1;)Ljava/lang/Object;
   #74 = Methodref          #33.#73       // scala/collection/immutable/OldHashSet$.tabulate:(ILscala/Function1;)Ljava/lang/Object;
   #75 = Utf8               Lscala/Function1;
   #76 = Utf8               fill
   #77 = Utf8               (IIIIILscala/Function0;)Ljava/lang/Object;
   #78 = Utf8               elem
   #79 = NameAndType        #76:#77       // fill:(IIIIILscala/Function0;)Ljava/lang/Object;
   #80 = Methodref          #33.#79       // scala/collection/immutable/OldHashSet$.fill:(IIIIILscala/Function0;)Ljava/lang/Object;
   #81 = Utf8               Lscala/Function0;
   #82 = Utf8               (IIIILscala/Function0;)Ljava/lang/Object;
   #83 = NameAndType        #76:#82       // fill:(IIIILscala/Function0;)Ljava/lang/Object;
   #84 = Methodref          #33.#83       // scala/collection/immutable/OldHashSet$.fill:(IIIILscala/Function0;)Ljava/lang/Object;
   #85 = Utf8               (IIILscala/Function0;)Ljava/lang/Object;
   #86 = NameAndType        #76:#85       // fill:(IIILscala/Function0;)Ljava/lang/Object;
   #87 = Methodref          #33.#86       // scala/collection/immutable/OldHashSet$.fill:(IIILscala/Function0;)Ljava/lang/Object;
   #88 = Utf8               (IILscala/Function0;)Ljava/lang/Object;
   #89 = NameAndType        #76:#88       // fill:(IILscala/Function0;)Ljava/lang/Object;
   #90 = Methodref          #33.#89       // scala/collection/immutable/OldHashSet$.fill:(IILscala/Function0;)Ljava/lang/Object;
   #91 = Utf8               (ILscala/Function0;)Ljava/lang/Object;
   #92 = NameAndType        #76:#91       // fill:(ILscala/Function0;)Ljava/lang/Object;
   #93 = Methodref          #33.#92       // scala/collection/immutable/OldHashSet$.fill:(ILscala/Function0;)Ljava/lang/Object;
   #94 = Utf8               range
   #95 = Utf8               (Ljava/lang/Object;Ljava/lang/Object;Ljava/lang/Object;Lscala/math/Integral;)Ljava/lang/Object;
   #96 = Utf8               start
   #97 = Utf8               end
   #98 = Utf8               step
   #99 = Utf8               evidence$4
  #100 = NameAndType        #94:#95       // range:(Ljava/lang/Object;Ljava/lang/Object;Ljava/lang/Object;Lscala/math/Integral;)Ljava/lang/Object;
  #101 = Methodref          #33.#100      // scala/collection/immutable/OldHashSet$.range:(Ljava/lang/Object;Ljava/lang/Object;Ljava/lang/Object;Lscala/math/Integral;)Ljava/lang/Object;
  #102 = Utf8               Ljava/lang/Object;
  #103 = Utf8               Lscala/math/Integral;
  #104 = Utf8               (Ljava/lang/Object;Ljava/lang/Object;Lscala/math/Integral;)Ljava/lang/Object;
  #105 = Utf8               evidence$3
  #106 = NameAndType        #94:#104      // range:(Ljava/lang/Object;Ljava/lang/Object;Lscala/math/Integral;)Ljava/lang/Object;
  #107 = Methodref          #33.#106      // scala/collection/immutable/OldHashSet$.range:(Ljava/lang/Object;Ljava/lang/Object;Lscala/math/Integral;)Ljava/lang/Object;
  #108 = Utf8               unfold
  #109 = Utf8               (Ljava/lang/Object;Lscala/Function1;)Ljava/lang/Object;
  #110 = Utf8               init
  #111 = NameAndType        #108:#109     // unfold:(Ljava/lang/Object;Lscala/Function1;)Ljava/lang/Object;
  #112 = Methodref          #33.#111      // scala/collection/immutable/OldHashSet$.unfold:(Ljava/lang/Object;Lscala/Function1;)Ljava/lang/Object;
  #113 = Utf8               iterate
  #114 = Utf8               (Ljava/lang/Object;ILscala/Function1;)Ljava/lang/Object;
  #115 = Utf8               len
  #116 = NameAndType        #113:#114     // iterate:(Ljava/lang/Object;ILscala/Function1;)Ljava/lang/Object;
  #117 = Methodref          #33.#116      // scala/collection/immutable/OldHashSet$.iterate:(Ljava/lang/Object;ILscala/Function1;)Ljava/lang/Object;
  #118 = Utf8               partition
  #119 = Utf8               (Lscala/Function1;)Lscala/Tuple2;
  #120 = Utf8               (Lscala/Function1<TA;Ljava/lang/Object;>;)Lscala/Tuple2<Lscala/collection/immutable/OldHashSet<TA;>;Lscala/collection/immutable/OldHashSet<TA;>;>;
  #121 = Utf8               p
  #122 = Utf8               partition$
  #123 = Utf8               (Lscala/collection/StrictOptimizedIterableOps;Lscala/Function1;)Lscala/Tuple2;
  #124 = NameAndType        #122:#123     // partition$:(Lscala/collection/StrictOptimizedIterableOps;Lscala/Function1;)Lscala/Tuple2;
  #125 = InterfaceMethodref #7.#124       // scala/collection/StrictOptimizedIterableOps.partition$:(Lscala/collection/StrictOptimizedIterableOps;Lscala/Function1;)Lscala/Tuple2;
  #126 = Utf8               this
  #127 = Utf8               Lscala/collection/immutable/OldHashSet;
  #128 = Utf8               span
  #129 = Utf8               span$
  #130 = NameAndType        #129:#123     // span$:(Lscala/collection/StrictOptimizedIterableOps;Lscala/Function1;)Lscala/Tuple2;
  #131 = InterfaceMethodref #7.#130       // scala/collection/StrictOptimizedIterableOps.span$:(Lscala/collection/StrictOptimizedIterableOps;Lscala/Function1;)Lscala/Tuple2;
  #132 = Utf8               unzip
  #133 = Utf8               <A1:Ljava/lang/Object;A2:Ljava/lang/Object;>(Lscala/Function1<TA;Lscala/Tuple2<TA1;TA2;>;>;)Lscala/Tuple2<Lscala/collection/immutable/OldHashSet<TA1;>;Lscala/collection/immutable/OldHashSet<TA2;>;>;
  #134 = Utf8               asPair
  #135 = Utf8               unzip$
  #136 = NameAndType        #135:#123     // unzip$:(Lscala/collection/StrictOptimizedIterableOps;Lscala/Function1;)Lscala/Tuple2;
  #137 = InterfaceMethodref #7.#136       // scala/collection/StrictOptimizedIterableOps.unzip$:(Lscala/collection/StrictOptimizedIterableOps;Lscala/Function1;)Lscala/Tuple2;
  #138 = Utf8               unzip3
  #139 = Utf8               (Lscala/Function1;)Lscala/Tuple3;
  #140 = Utf8               <A1:Ljava/lang/Object;A2:Ljava/lang/Object;A3:Ljava/lang/Object;>(Lscala/Function1<TA;Lscala/Tuple3<TA1;TA2;TA3;>;>;)Lscala/Tuple3<Lscala/collection/immutable/OldHashSet<TA1;>;Lscala/collection/immutable/OldHashSet<TA2;>;Lscala/collection/immutable/OldHashSet<TA3;>;>;
  #141 = Utf8               asTriple
  #142 = Utf8               unzip3$
  #143 = Utf8               (Lscala/collection/StrictOptimizedIterableOps;Lscala/Function1;)Lscala/Tuple3;
  #144 = NameAndType        #142:#143     // unzip3$:(Lscala/collection/StrictOptimizedIterableOps;Lscala/Function1;)Lscala/Tuple3;
  #145 = InterfaceMethodref #7.#144       // scala/collection/StrictOptimizedIterableOps.unzip3$:(Lscala/collection/StrictOptimizedIterableOps;Lscala/Function1;)Lscala/Tuple3;
  #146 = Utf8               map
  #147 = Utf8               (Lscala/Function1;)Ljava/lang/Object;
  #148 = Utf8               map$
  #149 = Utf8               (Lscala/collection/StrictOptimizedIterableOps;Lscala/Function1;)Ljava/lang/Object;
  #150 = NameAndType        #148:#149     // map$:(Lscala/collection/StrictOptimizedIterableOps;Lscala/Function1;)Ljava/lang/Object;
  #151 = InterfaceMethodref #7.#150       // scala/collection/StrictOptimizedIterableOps.map$:(Lscala/collection/StrictOptimizedIterableOps;Lscala/Function1;)Ljava/lang/Object;
  #152 = Utf8               strictOptimizedMap
  #153 = Utf8               (Lscala/collection/mutable/Builder;Lscala/Function1;)Ljava/lang/Object;
  #154 = Utf8               <B:Ljava/lang/Object;C2:Ljava/lang/Object;>(Lscala/collection/mutable/Builder<TB;TC2;>;Lscala/Function1<TA;TB;>;)TC2;
  #155 = Utf8               b
  #156 = Utf8               strictOptimizedMap$
  #157 = Utf8               (Lscala/collection/StrictOptimizedIterableOps;Lscala/collection/mutable/Builder;Lscala/Function1;)Ljava/lang/Object;
  #158 = NameAndType        #156:#157     // strictOptimizedMap$:(Lscala/collection/StrictOptimizedIterableOps;Lscala/collection/mutable/Builder;Lscala/Function1;)Ljava/lang/Object;
  #159 = InterfaceMethodref #7.#158       // scala/collection/StrictOptimizedIterableOps.strictOptimizedMap$:(Lscala/collection/StrictOptimizedIterableOps;Lscala/collection/mutable/Builder;Lscala/Function1;)Ljava/lang/Object;
  #160 = Utf8               Lscala/collection/mutable/Builder;
  #161 = Utf8               flatMap
  #162 = Utf8               flatMap$
  #163 = NameAndType        #162:#149     // flatMap$:(Lscala/collection/StrictOptimizedIterableOps;Lscala/Function1;)Ljava/lang/Object;
  #164 = InterfaceMethodref #7.#163       // scala/collection/StrictOptimizedIterableOps.flatMap$:(Lscala/collection/StrictOptimizedIterableOps;Lscala/Function1;)Ljava/lang/Object;
  #165 = Utf8               strictOptimizedFlatMap
  #166 = Utf8               <B:Ljava/lang/Object;C2:Ljava/lang/Object;>(Lscala/collection/mutable/Builder<TB;TC2;>;Lscala/Function1<TA;Lscala/collection/IterableOnce<TB;>;>;)TC2;
  #167 = Utf8               strictOptimizedFlatMap$
  #168 = NameAndType        #167:#157     // strictOptimizedFlatMap$:(Lscala/collection/StrictOptimizedIterableOps;Lscala/collection/mutable/Builder;Lscala/Function1;)Ljava/lang/Object;
  #169 = InterfaceMethodref #7.#168       // scala/collection/StrictOptimizedIterableOps.strictOptimizedFlatMap$:(Lscala/collection/StrictOptimizedIterableOps;Lscala/collection/mutable/Builder;Lscala/Function1;)Ljava/lang/Object;
  #170 = Utf8               strictOptimizedConcat
  #171 = Utf8               (Lscala/collection/IterableOnce;Lscala/collection/mutable/Builder;)Ljava/lang/Object;
  #172 = Utf8               <B:Ljava/lang/Object;C2:Ljava/lang/Object;>(Lscala/collection/IterableOnce<TB;>;Lscala/collection/mutable/Builder<TB;TC2;>;)TC2;
  #173 = Utf8               that
  #174 = Utf8               strictOptimizedConcat$
  #175 = Utf8               (Lscala/collection/StrictOptimizedIterableOps;Lscala/collection/IterableOnce;Lscala/collection/mutable/Builder;)Ljava/lang/Object;
  #176 = NameAndType        #174:#175     // strictOptimizedConcat$:(Lscala/collection/StrictOptimizedIterableOps;Lscala/collection/IterableOnce;Lscala/collection/mutable/Builder;)Ljava/lang/Object;
  #177 = InterfaceMethodref #7.#176       // scala/collection/StrictOptimizedIterableOps.strictOptimizedConcat$:(Lscala/collection/StrictOptimizedIterableOps;Lscala/collection/IterableOnce;Lscala/collection/mutable/Builder;)Ljava/lang/Object;
  #178 = Utf8               collect
  #179 = Utf8               (Lscala/PartialFunction;)Ljava/lang/Object;
  #180 = Utf8               pf
  #181 = Utf8               collect$
  #182 = Utf8               (Lscala/collection/StrictOptimizedIterableOps;Lscala/PartialFunction;)Ljava/lang/Object;
  #183 = NameAndType        #181:#182     // collect$:(Lscala/collection/StrictOptimizedIterableOps;Lscala/PartialFunction;)Ljava/lang/Object;
  #184 = InterfaceMethodref #7.#183       // scala/collection/StrictOptimizedIterableOps.collect$:(Lscala/collection/StrictOptimizedIterableOps;Lscala/PartialFunction;)Ljava/lang/Object;
  #185 = Utf8               Lscala/PartialFunction;
  #186 = Utf8               strictOptimizedCollect
  #187 = Utf8               (Lscala/collection/mutable/Builder;Lscala/PartialFunction;)Ljava/lang/Object;
  #188 = Utf8               <B:Ljava/lang/Object;C2:Ljava/lang/Object;>(Lscala/collection/mutable/Builder<TB;TC2;>;Lscala/PartialFunction<TA;TB;>;)TC2;
  #189 = Utf8               strictOptimizedCollect$
  #190 = Utf8               (Lscala/collection/StrictOptimizedIterableOps;Lscala/collection/mutable/Builder;Lscala/PartialFunction;)Ljava/lang/Object;
  #191 = NameAndType        #189:#190     // strictOptimizedCollect$:(Lscala/collection/StrictOptimizedIterableOps;Lscala/collection/mutable/Builder;Lscala/PartialFunction;)Ljava/lang/Object;
  #192 = InterfaceMethodref #7.#191       // scala/collection/StrictOptimizedIterableOps.strictOptimizedCollect$:(Lscala/collection/StrictOptimizedIterableOps;Lscala/collection/mutable/Builder;Lscala/PartialFunction;)Ljava/lang/Object;
  #193 = Utf8               flatten
  #194 = Utf8               toIterableOnce
  #195 = Utf8               flatten$
  #196 = NameAndType        #195:#149     // flatten$:(Lscala/collection/StrictOptimizedIterableOps;Lscala/Function1;)Ljava/lang/Object;
  #197 = InterfaceMethodref #7.#196       // scala/collection/StrictOptimizedIterableOps.flatten$:(Lscala/collection/StrictOptimizedIterableOps;Lscala/Function1;)Ljava/lang/Object;
  #198 = Utf8               strictOptimizedFlatten
  #199 = Utf8               strictOptimizedFlatten$
  #200 = NameAndType        #199:#157     // strictOptimizedFlatten$:(Lscala/collection/StrictOptimizedIterableOps;Lscala/collection/mutable/Builder;Lscala/Function1;)Ljava/lang/Object;
  #201 = InterfaceMethodref #7.#200       // scala/collection/StrictOptimizedIterableOps.strictOptimizedFlatten$:(Lscala/collection/StrictOptimizedIterableOps;Lscala/collection/mutable/Builder;Lscala/Function1;)Ljava/lang/Object;
  #202 = Utf8               zip
  #203 = Utf8               (Lscala/collection/IterableOnce;)Ljava/lang/Object;
  #204 = Utf8               zip$
  #205 = Utf8               (Lscala/collection/StrictOptimizedIterableOps;Lscala/collection/IterableOnce;)Ljava/lang/Object;
  #206 = NameAndType        #204:#205     // zip$:(Lscala/collection/StrictOptimizedIterableOps;Lscala/collection/IterableOnce;)Ljava/lang/Object;
  #207 = InterfaceMethodref #7.#206       // scala/collection/StrictOptimizedIterableOps.zip$:(Lscala/collection/StrictOptimizedIterableOps;Lscala/collection/IterableOnce;)Ljava/lang/Object;
  #208 = Utf8               strictOptimizedZip
  #209 = Utf8               <B:Ljava/lang/Object;C2:Ljava/lang/Object;>(Lscala/collection/IterableOnce<TB;>;Lscala/collection/mutable/Builder<Lscala/Tuple2<TA;TB;>;TC2;>;)TC2;
  #210 = Utf8               strictOptimizedZip$
  #211 = NameAndType        #210:#175     // strictOptimizedZip$:(Lscala/collection/StrictOptimizedIterableOps;Lscala/collection/IterableOnce;Lscala/collection/mutable/Builder;)Ljava/lang/Object;
  #212 = InterfaceMethodref #7.#211       // scala/collection/StrictOptimizedIterableOps.strictOptimizedZip$:(Lscala/collection/StrictOptimizedIterableOps;Lscala/collection/IterableOnce;Lscala/collection/mutable/Builder;)Ljava/lang/Object;
  #213 = Utf8               zipWithIndex
  #214 = Utf8               ()Ljava/lang/Object;
  #215 = Utf8               zipWithIndex$
  #216 = Utf8               (Lscala/collection/StrictOptimizedIterableOps;)Ljava/lang/Object;
  #217 = NameAndType        #215:#216     // zipWithIndex$:(Lscala/collection/StrictOptimizedIterableOps;)Ljava/lang/Object;
  #218 = InterfaceMethodref #7.#217       // scala/collection/StrictOptimizedIterableOps.zipWithIndex$:(Lscala/collection/StrictOptimizedIterableOps;)Ljava/lang/Object;
  #219 = Utf8               scanLeft
  #220 = Utf8               (Ljava/lang/Object;Lscala/Function2;)Ljava/lang/Object;
  #221 = Utf8               z
  #222 = Utf8               op
  #223 = Utf8               scanLeft$
  #224 = Utf8               (Lscala/collection/StrictOptimizedIterableOps;Ljava/lang/Object;Lscala/Function2;)Ljava/lang/Object;
  #225 = NameAndType        #223:#224     // scanLeft$:(Lscala/collection/StrictOptimizedIterableOps;Ljava/lang/Object;Lscala/Function2;)Ljava/lang/Object;
  #226 = InterfaceMethodref #7.#225       // scala/collection/StrictOptimizedIterableOps.scanLeft$:(Lscala/collection/StrictOptimizedIterableOps;Ljava/lang/Object;Lscala/Function2;)Ljava/lang/Object;
  #227 = Utf8               filterImpl
  #228 = Utf8               (Lscala/Function1;Z)Ljava/lang/Object;
  #229 = Utf8               pred
  #230 = Utf8               isFlipped
  #231 = Utf8               filterImpl$
  #232 = Utf8               (Lscala/collection/StrictOptimizedIterableOps;Lscala/Function1;Z)Ljava/lang/Object;
  #233 = NameAndType        #231:#232     // filterImpl$:(Lscala/collection/StrictOptimizedIterableOps;Lscala/Function1;Z)Ljava/lang/Object;
  #234 = InterfaceMethodref #7.#233       // scala/collection/StrictOptimizedIterableOps.filterImpl$:(Lscala/collection/StrictOptimizedIterableOps;Lscala/Function1;Z)Ljava/lang/Object;
  #235 = Utf8               Z
  #236 = Utf8               partitionMap
  #237 = Utf8               <A1:Ljava/lang/Object;A2:Ljava/lang/Object;>(Lscala/Function1<TA;Lscala/util/Either<TA1;TA2;>;>;)Lscala/Tuple2<Lscala/collection/immutable/OldHashSet<TA1;>;Lscala/collection/immutable/OldHashSet<TA2;>;>;
  #238 = Utf8               partitionMap$
  #239 = NameAndType        #238:#123     // partitionMap$:(Lscala/collection/StrictOptimizedIterableOps;Lscala/Function1;)Lscala/Tuple2;
  #240 = InterfaceMethodref #7.#239       // scala/collection/StrictOptimizedIterableOps.partitionMap$:(Lscala/collection/StrictOptimizedIterableOps;Lscala/Function1;)Lscala/Tuple2;
  #241 = Utf8               tapEach
  #242 = Utf8               tapEach$
  #243 = NameAndType        #242:#149     // tapEach$:(Lscala/collection/StrictOptimizedIterableOps;Lscala/Function1;)Ljava/lang/Object;
  #244 = InterfaceMethodref #7.#243       // scala/collection/StrictOptimizedIterableOps.tapEach$:(Lscala/collection/StrictOptimizedIterableOps;Lscala/Function1;)Ljava/lang/Object;
  #245 = Utf8               takeRight
  #246 = Utf8               (I)Ljava/lang/Object;
  #247 = Utf8               takeRight$
  #248 = Utf8               (Lscala/collection/StrictOptimizedIterableOps;I)Ljava/lang/Object;
  #249 = NameAndType        #247:#248     // takeRight$:(Lscala/collection/StrictOptimizedIterableOps;I)Ljava/lang/Object;
  #250 = InterfaceMethodref #7.#249       // scala/collection/StrictOptimizedIterableOps.takeRight$:(Lscala/collection/StrictOptimizedIterableOps;I)Ljava/lang/Object;
  #251 = Utf8               dropRight
  #252 = Utf8               dropRight$
  #253 = NameAndType        #252:#248     // dropRight$:(Lscala/collection/StrictOptimizedIterableOps;I)Ljava/lang/Object;
  #254 = InterfaceMethodref #7.#253       // scala/collection/StrictOptimizedIterableOps.dropRight$:(Lscala/collection/StrictOptimizedIterableOps;I)Ljava/lang/Object;
  #255 = Utf8               className
  #256 = Utf8               ()Ljava/lang/String;
  #257 = Utf8               OldHashSet
  #258 = String             #257          // OldHashSet
  #259 = Utf8               iterableFactory
  #260 = Utf8               ()Lscala/collection/immutable/OldHashSet$;
  #261 = Utf8               contains
  #262 = Utf8               (Ljava/lang/Object;)Z
  #263 = Utf8               (TA;)Z
  #264 = Utf8               scala/collection/Hashing$
  #265 = Class              #264          // scala/collection/Hashing$
  #266 = Utf8               Lscala/collection/Hashing$;
  #267 = NameAndType        #34:#266      // MODULE$:Lscala/collection/Hashing$;
  #268 = Fieldref           #265.#267     // scala/collection/Hashing$.MODULE$:Lscala/collection/Hashing$;
  #269 = Utf8               computeHash
  #270 = Utf8               (Ljava/lang/Object;)I
  #271 = NameAndType        #269:#270     // computeHash:(Ljava/lang/Object;)I
  #272 = Methodref          #265.#271     // scala/collection/Hashing$.computeHash:(Ljava/lang/Object;)I
  #273 = Utf8               get0
  #274 = Utf8               (Ljava/lang/Object;II)Z
  #275 = NameAndType        #273:#274     // get0:(Ljava/lang/Object;II)Z
  #276 = Methodref          #2.#275       // scala/collection/immutable/OldHashSet.get0:(Ljava/lang/Object;II)Z
  #277 = Utf8               incl
  #278 = Utf8               (Ljava/lang/Object;)Lscala/collection/immutable/OldHashSet;
  #279 = Utf8               (TA;)Lscala/collection/immutable/OldHashSet<TA;>;
  #280 = Utf8               updated0
  #281 = Utf8               (Ljava/lang/Object;II)Lscala/collection/immutable/OldHashSet;
  #282 = NameAndType        #280:#281     // updated0:(Ljava/lang/Object;II)Lscala/collection/immutable/OldHashSet;
  #283 = Methodref          #2.#282       // scala/collection/immutable/OldHashSet.updated0:(Ljava/lang/Object;II)Lscala/collection/immutable/OldHashSet;
  #284 = Utf8               excl
  #285 = Utf8               removed0
  #286 = NameAndType        #285:#281     // removed0:(Ljava/lang/Object;II)Lscala/collection/immutable/OldHashSet;
  #287 = Methodref          #2.#286       // scala/collection/immutable/OldHashSet.removed0:(Ljava/lang/Object;II)Lscala/collection/immutable/OldHashSet;
  #288 = Utf8               scala$collection$immutable$OldHashSet$$nullToEmpty
  #289 = Utf8               (Lscala/collection/immutable/OldHashSet;)Lscala/collection/immutable/OldHashSet;
  #290 = NameAndType        #288:#289     // scala$collection$immutable$OldHashSet$$nullToEmpty:(Lscala/collection/immutable/OldHashSet;)Lscala/collection/immutable/OldHashSet;
  #291 = Methodref          #33.#290      // scala/collection/immutable/OldHashSet$.scala$collection$immutable$OldHashSet$$nullToEmpty:(Lscala/collection/immutable/OldHashSet;)Lscala/collection/immutable/OldHashSet;
  #292 = Utf8               subsetOf
  #293 = Utf8               (Lscala/collection/Set;)Z
  #294 = Utf8               (Lscala/collection/Set<TA;>;)Z
  #295 = Utf8               subsetOf0
  #296 = Utf8               (Lscala/collection/immutable/OldHashSet;I)Z
  #297 = NameAndType        #295:#296     // subsetOf0:(Lscala/collection/immutable/OldHashSet;I)Z
  #298 = Methodref          #2.#297       // scala/collection/immutable/OldHashSet.subsetOf0:(Lscala/collection/immutable/OldHashSet;I)Z
  #299 = Utf8               scala/collection/SetOps
  #300 = Class              #299          // scala/collection/SetOps
  #301 = Utf8               subsetOf$
  #302 = Utf8               (Lscala/collection/SetOps;Lscala/collection/Set;)Z
  #303 = NameAndType        #301:#302     // subsetOf$:(Lscala/collection/SetOps;Lscala/collection/Set;)Z
  #304 = InterfaceMethodref #300.#303     // scala/collection/SetOps.subsetOf$:(Lscala/collection/SetOps;Lscala/collection/Set;)Z
  #305 = Utf8               Lscala/collection/Set;
  #306 = Utf8               scala/collection/Set
  #307 = Class              #306          // scala/collection/Set
  #308 = Utf8               concat
  #309 = Utf8               (Lscala/collection/IterableOnce<TA;>;)Lscala/collection/immutable/OldHashSet<TA;>;
  #310 = Utf8               size
  #311 = Utf8               ()I
  #312 = NameAndType        #310:#311     // size:()I
  #313 = Methodref          #2.#312       // scala/collection/immutable/OldHashSet.size:()I
  #314 = Utf8               scala$collection$immutable$OldHashSet$$bufferSize
  #315 = Utf8               (I)I
  #316 = NameAndType        #314:#315     // scala$collection$immutable$OldHashSet$$bufferSize:(I)I
  #317 = Methodref          #33.#316      // scala/collection/immutable/OldHashSet$.scala$collection$immutable$OldHashSet$$bufferSize:(I)I
  #318 = Utf8               union0
  #319 = Utf8               (Lscala/collection/immutable/OldHashSet;I[Lscala/collection/immutable/OldHashSet;I)Lscala/collection/immutable/OldHashSet;
  #320 = NameAndType        #318:#319     // union0:(Lscala/collection/immutable/OldHashSet;I[Lscala/collection/immutable/OldHashSet;I)Lscala/collection/immutable/OldHashSet;
  #321 = Methodref          #2.#320       // scala/collection/immutable/OldHashSet.union0:(Lscala/collection/immutable/OldHashSet;I[Lscala/collection/immutable/OldHashSet;I)Lscala/collection/immutable/OldHashSet;
  #322 = Utf8               concat$
  #323 = Utf8               (Lscala/collection/SetOps;Lscala/collection/IterableOnce;)Lscala/collection/SetOps;
  #324 = NameAndType        #322:#323     // concat$:(Lscala/collection/SetOps;Lscala/collection/IterableOnce;)Lscala/collection/SetOps;
  #325 = InterfaceMethodref #300.#324     // scala/collection/SetOps.concat$:(Lscala/collection/SetOps;Lscala/collection/IterableOnce;)Lscala/collection/SetOps;
  #326 = Utf8               buffer
  #327 = Utf8               [Lscala/collection/immutable/OldHashSet;
  #328 = Utf8               scala/collection/IterableOnce
  #329 = Class              #328          // scala/collection/IterableOnce
  #330 = Utf8               intersect
  #331 = Utf8               (Lscala/collection/Set;)Lscala/collection/immutable/OldHashSet;
  #332 = Utf8               (Lscala/collection/Set<TA;>;)Lscala/collection/immutable/OldHashSet<TA;>;
  #333 = Utf8               scala/runtime/RichInt$
  #334 = Class              #333          // scala/runtime/RichInt$
  #335 = Utf8               Lscala/runtime/RichInt$;
  #336 = NameAndType        #34:#335      // MODULE$:Lscala/runtime/RichInt$;
  #337 = Fieldref           #334.#336     // scala/runtime/RichInt$.MODULE$:Lscala/runtime/RichInt$;
  #338 = Utf8               scala/Predef$
  #339 = Class              #338          // scala/Predef$
  #340 = Utf8               Lscala/Predef$;
  #341 = NameAndType        #34:#340      // MODULE$:Lscala/Predef$;
  #342 = Fieldref           #339.#341     // scala/Predef$.MODULE$:Lscala/Predef$;
  #343 = Utf8               intWrapper
  #344 = NameAndType        #343:#315     // intWrapper:(I)I
  #345 = Methodref          #339.#344     // scala/Predef$.intWrapper:(I)I
  #346 = Utf8               min$extension
  #347 = Utf8               (II)I
  #348 = NameAndType        #346:#347     // min$extension:(II)I
  #349 = Methodref          #334.#348     // scala/runtime/RichInt$.min$extension:(II)I
  #350 = Utf8               intersect0
  #351 = NameAndType        #350:#319     // intersect0:(Lscala/collection/immutable/OldHashSet;I[Lscala/collection/immutable/OldHashSet;I)Lscala/collection/immutable/OldHashSet;
  #352 = Methodref          #2.#351       // scala/collection/immutable/OldHashSet.intersect0:(Lscala/collection/immutable/OldHashSet;I[Lscala/collection/immutable/OldHashSet;I)Lscala/collection/immutable/OldHashSet;
  #353 = Utf8               intersect$
  #354 = Utf8               (Lscala/collection/SetOps;Lscala/collection/Set;)Lscala/collection/SetOps;
  #355 = NameAndType        #353:#354     // intersect$:(Lscala/collection/SetOps;Lscala/collection/Set;)Lscala/collection/SetOps;
  #356 = InterfaceMethodref #300.#355     // scala/collection/SetOps.intersect$:(Lscala/collection/SetOps;Lscala/collection/Set;)Lscala/collection/SetOps;
  #357 = Utf8               diff
  #358 = Utf8               diff0
  #359 = NameAndType        #358:#319     // diff0:(Lscala/collection/immutable/OldHashSet;I[Lscala/collection/immutable/OldHashSet;I)Lscala/collection/immutable/OldHashSet;
  #360 = Methodref          #2.#359       // scala/collection/immutable/OldHashSet.diff0:(Lscala/collection/immutable/OldHashSet;I[Lscala/collection/immutable/OldHashSet;I)Lscala/collection/immutable/OldHashSet;
  #361 = Utf8               scala/collection/immutable/SetOps
  #362 = Class              #361          // scala/collection/immutable/SetOps
  #363 = Utf8               diff$
  #364 = Utf8               (Lscala/collection/immutable/SetOps;Lscala/collection/Set;)Lscala/collection/immutable/SetOps;
  #365 = NameAndType        #363:#364     // diff$:(Lscala/collection/immutable/SetOps;Lscala/collection/Set;)Lscala/collection/immutable/SetOps;
  #366 = InterfaceMethodref #362.#365     // scala/collection/immutable/SetOps.diff$:(Lscala/collection/immutable/SetOps;Lscala/collection/Set;)Lscala/collection/immutable/SetOps;
  #367 = Utf8               filter
  #368 = Utf8               (Lscala/Function1;)Lscala/collection/immutable/OldHashSet;
  #369 = Utf8               (Lscala/Function1<TA;Ljava/lang/Object;>;)Lscala/collection/immutable/OldHashSet<TA;>;
  #370 = Utf8               filter0
  #371 = Utf8               (Lscala/Function1;ZI[Lscala/collection/immutable/OldHashSet;I)Lscala/collection/immutable/OldHashSet;
  #372 = NameAndType        #370:#371     // filter0:(Lscala/Function1;ZI[Lscala/collection/immutable/OldHashSet;I)Lscala/collection/immutable/OldHashSet;
  #373 = Methodref          #2.#372       // scala/collection/immutable/OldHashSet.filter0:(Lscala/Function1;ZI[Lscala/collection/immutable/OldHashSet;I)Lscala/collection/immutable/OldHashSet;
  #374 = Utf8               filterNot
  #375 = Utf8               tail
  #376 = Utf8               ()Lscala/collection/immutable/OldHashSet;
  #377 = Utf8               ()Lscala/collection/immutable/OldHashSet<TA;>;
  #378 = Utf8               head
  #379 = NameAndType        #378:#214     // head:()Ljava/lang/Object;
  #380 = Methodref          #2.#379       // scala/collection/immutable/OldHashSet.head:()Ljava/lang/Object;
  #381 = Utf8               $minus
  #382 = Utf8               (Ljava/lang/Object;)Lscala/collection/immutable/SetOps;
  #383 = NameAndType        #381:#382     // $minus:(Ljava/lang/Object;)Lscala/collection/immutable/SetOps;
  #384 = Methodref          #2.#383       // scala/collection/immutable/OldHashSet.$minus:(Ljava/lang/Object;)Lscala/collection/immutable/SetOps;
  #385 = Utf8               last
  #386 = NameAndType        #385:#214     // last:()Ljava/lang/Object;
  #387 = Methodref          #2.#386       // scala/collection/immutable/OldHashSet.last:()Ljava/lang/Object;
  #388 = Utf8               (TA;II)Z
  #389 = Utf8               key
  #390 = Utf8               hash
  #391 = Utf8               level
  #392 = Utf8               (TA;II)Lscala/collection/immutable/OldHashSet<TA;>;
  #393 = Utf8               (Lscala/Function1<TA;Ljava/lang/Object;>;ZI[Lscala/collection/immutable/OldHashSet<TA;>;I)Lscala/collection/immutable/OldHashSet<TA;>;
  #394 = Utf8               negate
  #395 = Utf8               offset0
  #396 = Utf8               (Lscala/collection/immutable/OldHashSet<TA;>;I)Z
  #397 = Utf8               (Lscala/collection/immutable/OldHashSet$LeafOldHashSet;I)Lscala/collection/immutable/OldHashSet;
  #398 = Utf8               (Lscala/collection/immutable/OldHashSet$LeafOldHashSet<TA;>;I)Lscala/collection/immutable/OldHashSet<TA;>;
  #399 = Utf8               (Lscala/collection/immutable/OldHashSet<TA;>;I[Lscala/collection/immutable/OldHashSet<TA;>;I)Lscala/collection/immutable/OldHashSet<TA;>;
  #400 = NameAndType        #110:#376     // init:()Lscala/collection/immutable/OldHashSet;
  #401 = Methodref          #2.#400       // scala/collection/immutable/OldHashSet.init:()Lscala/collection/immutable/OldHashSet;
  #402 = NameAndType        #375:#376     // tail:()Lscala/collection/immutable/OldHashSet;
  #403 = Methodref          #2.#402       // scala/collection/immutable/OldHashSet.tail:()Lscala/collection/immutable/OldHashSet;
  #404 = NameAndType        #374:#368     // filterNot:(Lscala/Function1;)Lscala/collection/immutable/OldHashSet;
  #405 = Methodref          #2.#404       // scala/collection/immutable/OldHashSet.filterNot:(Lscala/Function1;)Lscala/collection/immutable/OldHashSet;
  #406 = NameAndType        #367:#368     // filter:(Lscala/Function1;)Lscala/collection/immutable/OldHashSet;
  #407 = Methodref          #2.#406       // scala/collection/immutable/OldHashSet.filter:(Lscala/Function1;)Lscala/collection/immutable/OldHashSet;
  #408 = Utf8               (Lscala/collection/Set;)Lscala/collection/SetOps;
  #409 = NameAndType        #357:#331     // diff:(Lscala/collection/Set;)Lscala/collection/immutable/OldHashSet;
  #410 = Methodref          #2.#409       // scala/collection/immutable/OldHashSet.diff:(Lscala/collection/Set;)Lscala/collection/immutable/OldHashSet;
  #411 = Utf8               (Lscala/collection/Set;)Lscala/collection/immutable/SetOps;
  #412 = NameAndType        #330:#331     // intersect:(Lscala/collection/Set;)Lscala/collection/immutable/OldHashSet;
  #413 = Methodref          #2.#412       // scala/collection/immutable/OldHashSet.intersect:(Lscala/collection/Set;)Lscala/collection/immutable/OldHashSet;
  #414 = Utf8               (Lscala/collection/IterableOnce;)Lscala/collection/SetOps;
  #415 = NameAndType        #308:#41      // concat:(Lscala/collection/IterableOnce;)Lscala/collection/immutable/OldHashSet;
  #416 = Methodref          #2.#415       // scala/collection/immutable/OldHashSet.concat:(Lscala/collection/IterableOnce;)Lscala/collection/immutable/OldHashSet;
  #417 = NameAndType        #284:#278     // excl:(Ljava/lang/Object;)Lscala/collection/immutable/OldHashSet;
  #418 = Methodref          #2.#417       // scala/collection/immutable/OldHashSet.excl:(Ljava/lang/Object;)Lscala/collection/immutable/OldHashSet;
  #419 = NameAndType        #277:#278     // incl:(Ljava/lang/Object;)Lscala/collection/immutable/OldHashSet;
  #420 = Methodref          #2.#419       // scala/collection/immutable/OldHashSet.incl:(Ljava/lang/Object;)Lscala/collection/immutable/OldHashSet;
  #421 = Utf8               ()Lscala/collection/IterableFactory;
  #422 = NameAndType        #259:#260     // iterableFactory:()Lscala/collection/immutable/OldHashSet$;
  #423 = Methodref          #2.#422       // scala/collection/immutable/OldHashSet.iterableFactory:()Lscala/collection/immutable/OldHashSet$;
  #424 = Utf8               <init>
  #425 = Utf8               ()V
  #426 = NameAndType        #424:#425     // "<init>":()V
  #427 = Methodref          #5.#426       // scala/collection/immutable/AbstractSet."<init>":()V
  #428 = Utf8               $init$
  #429 = Utf8               (Lscala/collection/StrictOptimizedIterableOps;)V
  #430 = NameAndType        #428:#429     // $init$:(Lscala/collection/StrictOptimizedIterableOps;)V
  #431 = InterfaceMethodref #7.#430       // scala/collection/StrictOptimizedIterableOps.$init$:(Lscala/collection/StrictOptimizedIterableOps;)V
  #432 = Utf8               Code
  #433 = Utf8               Signature
  #434 = Utf8               LocalVariableTable
  #435 = Utf8               MethodParameters
  #436 = Utf8               LineNumberTable
  #437 = Utf8               StackMapTable
  #438 = Utf8               InnerClasses
  #439 = Utf8               SourceFile
  #440 = Utf8               RuntimeVisibleAnnotations
  #441 = Utf8               ScalaInlineInfo
  #442 = Utf8               ScalaSig
{
  public static <A extends java.lang.Object> scala.collection.mutable.Builder<A, scala.collection.immutable.OldHashSet<A>> newBuilder();
    descriptor: ()Lscala/collection/mutable/Builder;
    flags: (0x0009) ACC_PUBLIC, ACC_STATIC
    Code:
      stack=1, locals=0, args_size=0
         0: getstatic     #37                 // Field scala/collection/immutable/OldHashSet$.MODULE$:Lscala/collection/immutable/OldHashSet$;
         3: invokevirtual #39                 // Method scala/collection/immutable/OldHashSet$.newBuilder:()Lscala/collection/mutable/Builder;
         6: areturn
    Signature: #31                          // <A:Ljava/lang/Object;>()Lscala/collection/mutable/Builder<TA;Lscala/collection/immutable/OldHashSet<TA;>;>;

  public static <A extends java.lang.Object> scala.collection.immutable.OldHashSet<A> from(scala.collection.IterableOnce<A>);
    descriptor: (Lscala/collection/IterableOnce;)Lscala/collection/immutable/OldHashSet;
    flags: (0x0009) ACC_PUBLIC, ACC_STATIC
    Code:
      stack=2, locals=1, args_size=1
         0: getstatic     #37                 // Field scala/collection/immutable/OldHashSet$.MODULE$:Lscala/collection/immutable/OldHashSet$;
         3: aload_0
         4: invokevirtual #45                 // Method scala/collection/immutable/OldHashSet$.from:(Lscala/collection/IterableOnce;)Lscala/collection/immutable/OldHashSet;
         7: areturn
      LocalVariableTable:
        Start  Length  Slot  Name   Signature
            0       8     0    it   Lscala/collection/IterableOnce;
    Signature: #42                          // <A:Ljava/lang/Object;>(Lscala/collection/IterableOnce<TA;>;)Lscala/collection/immutable/OldHashSet<TA;>;
    MethodParameters:
      Name                           Flags
      it                             final

  public static java.lang.Object tabulate(int, int, int, int, int, scala.Function5);
    descriptor: (IIIIILscala/Function5;)Ljava/lang/Object;
    flags: (0x0009) ACC_PUBLIC, ACC_STATIC
    Code:
      stack=7, locals=6, args_size=6
         0: getstatic     #37                 // Field scala/collection/immutable/OldHashSet$.MODULE$:Lscala/collection/immutable/OldHashSet$;
         3: iload_0
         4: iload_1
         5: iload_2
         6: iload_3
         7: iload         4
         9: aload         5
        11: invokevirtual #56                 // Method scala/collection/immutable/OldHashSet$.tabulate:(IIIIILscala/Function5;)Ljava/lang/Object;
        14: areturn
      LocalVariableTable:
        Start  Length  Slot  Name   Signature
            0      15     0    n1   I
            0      15     1    n2   I
            0      15     2    n3   I
            0      15     3    n4   I
            0      15     4    n5   I
            0      15     5     f   Lscala/Function5;
    MethodParameters:
      Name                           Flags
      n1                             final
      n2                             final
      n3                             final
      n4                             final
      n5                             final
      f                              final

  public static java.lang.Object tabulate(int, int, int, int, scala.Function4);
    descriptor: (IIIILscala/Function4;)Ljava/lang/Object;
    flags: (0x0009) ACC_PUBLIC, ACC_STATIC
    Code:
      stack=6, locals=5, args_size=5
         0: getstatic     #37                 // Field scala/collection/immutable/OldHashSet$.MODULE$:Lscala/collection/immutable/OldHashSet$;
         3: iload_0
         4: iload_1
         5: iload_2
         6: iload_3
         7: aload         4
         9: invokevirtual #61                 // Method scala/collection/immutable/OldHashSet$.tabulate:(IIIILscala/Function4;)Ljava/lang/Object;
        12: areturn
      LocalVariableTable:
        Start  Length  Slot  Name   Signature
            0      13     0    n1   I
            0      13     1    n2   I
            0      13     2    n3   I
            0      13     3    n4   I
            0      13     4     f   Lscala/Function4;
    MethodParameters:
      Name                           Flags
      n1                             final
      n2                             final
      n3                             final
      n4                             final
      f                              final

  public static java.lang.Object tabulate(int, int, int, scala.Function3);
    descriptor: (IIILscala/Function3;)Ljava/lang/Object;
    flags: (0x0009) ACC_PUBLIC, ACC_STATIC
    Code:
      stack=5, locals=4, args_size=4
         0: getstatic     #37                 // Field scala/collection/immutable/OldHashSet$.MODULE$:Lscala/collection/immutable/OldHashSet$;
         3: iload_0
         4: iload_1
         5: iload_2
         6: aload_3
         7: invokevirtual #65                 // Method scala/collection/immutable/OldHashSet$.tabulate:(IIILscala/Function3;)Ljava/lang/Object;
        10: areturn
      LocalVariableTable:
        Start  Length  Slot  Name   Signature
            0      11     0    n1   I
            0      11     1    n2   I
            0      11     2    n3   I
            0      11     3     f   Lscala/Function3;
    MethodParameters:
      Name                           Flags
      n1                             final
      n2                             final
      n3                             final
      f                              final

  public static java.lang.Object tabulate(int, int, scala.Function2);
    descriptor: (IILscala/Function2;)Ljava/lang/Object;
    flags: (0x0009) ACC_PUBLIC, ACC_STATIC
    Code:
      stack=4, locals=3, args_size=3
         0: getstatic     #37                 // Field scala/collection/immutable/OldHashSet$.MODULE$:Lscala/collection/immutable/OldHashSet$;
         3: iload_0
         4: iload_1
         5: aload_2
         6: invokevirtual #69                 // Method scala/collection/immutable/OldHashSet$.tabulate:(IILscala/Function2;)Ljava/lang/Object;
         9: areturn
      LocalVariableTable:
        Start  Length  Slot  Name   Signature
            0      10     0    n1   I
            0      10     1    n2   I
            0      10     2     f   Lscala/Function2;
    MethodParameters:
      Name                           Flags
      n1                             final
      n2                             final
      f                              final

  public static java.lang.Object tabulate(int, scala.Function1);
    descriptor: (ILscala/Function1;)Ljava/lang/Object;
    flags: (0x0009) ACC_PUBLIC, ACC_STATIC
    Code:
      stack=3, locals=2, args_size=2
         0: getstatic     #37                 // Field scala/collection/immutable/OldHashSet$.MODULE$:Lscala/collection/immutable/OldHashSet$;
         3: iload_0
         4: aload_1
         5: invokevirtual #74                 // Method scala/collection/immutable/OldHashSet$.tabulate:(ILscala/Function1;)Ljava/lang/Object;
         8: areturn
      LocalVariableTable:
        Start  Length  Slot  Name   Signature
            0       9     0     n   I
            0       9     1     f   Lscala/Function1;
    MethodParameters:
      Name                           Flags
      n                              final
      f                              final

  public static java.lang.Object fill(int, int, int, int, int, scala.Function0);
    descriptor: (IIIIILscala/Function0;)Ljava/lang/Object;
    flags: (0x0009) ACC_PUBLIC, ACC_STATIC
    Code:
      stack=7, locals=6, args_size=6
         0: getstatic     #37                 // Field scala/collection/immutable/OldHashSet$.MODULE$:Lscala/collection/immutable/OldHashSet$;
         3: iload_0
         4: iload_1
         5: iload_2
         6: iload_3
         7: iload         4
         9: aload         5
        11: invokevirtual #80                 // Method scala/collection/immutable/OldHashSet$.fill:(IIIIILscala/Function0;)Ljava/lang/Object;
        14: areturn
      LocalVariableTable:
        Start  Length  Slot  Name   Signature
            0      15     0    n1   I
            0      15     1    n2   I
            0      15     2    n3   I
            0      15     3    n4   I
            0      15     4    n5   I
            0      15     5  elem   Lscala/Function0;
    MethodParameters:
      Name                           Flags
      n1                             final
      n2                             final
      n3                             final
      n4                             final
      n5                             final
      elem                           final

  public static java.lang.Object fill(int, int, int, int, scala.Function0);
    descriptor: (IIIILscala/Function0;)Ljava/lang/Object;
    flags: (0x0009) ACC_PUBLIC, ACC_STATIC
    Code:
      stack=6, locals=5, args_size=5
         0: getstatic     #37                 // Field scala/collection/immutable/OldHashSet$.MODULE$:Lscala/collection/immutable/OldHashSet$;
         3: iload_0
         4: iload_1
         5: iload_2
         6: iload_3
         7: aload         4
         9: invokevirtual #84                 // Method scala/collection/immutable/OldHashSet$.fill:(IIIILscala/Function0;)Ljava/lang/Object;
        12: areturn
      LocalVariableTable:
        Start  Length  Slot  Name   Signature
            0      13     0    n1   I
            0      13     1    n2   I
            0      13     2    n3   I
            0      13     3    n4   I
            0      13     4  elem   Lscala/Function0;
    MethodParameters:
      Name                           Flags
      n1                             final
      n2                             final
      n3                             final
      n4                             final
      elem                           final

  public static java.lang.Object fill(int, int, int, scala.Function0);
    descriptor: (IIILscala/Function0;)Ljava/lang/Object;
    flags: (0x0009) ACC_PUBLIC, ACC_STATIC
    Code:
      stack=5, locals=4, args_size=4
         0: getstatic     #37                 // Field scala/collection/immutable/OldHashSet$.MODULE$:Lscala/collection/immutable/OldHashSet$;
         3: iload_0
         4: iload_1
         5: iload_2
         6: aload_3
         7: invokevirtual #87                 // Method scala/collection/immutable/OldHashSet$.fill:(IIILscala/Function0;)Ljava/lang/Object;
        10: areturn
      LocalVariableTable:
        Start  Length  Slot  Name   Signature
            0      11     0    n1   I
            0      11     1    n2   I
            0      11     2    n3   I
            0      11     3  elem   Lscala/Function0;
    MethodParameters:
      Name                           Flags
      n1                             final
      n2                             final
      n3                             final
      elem                           final

  public static java.lang.Object fill(int, int, scala.Function0);
    descriptor: (IILscala/Function0;)Ljava/lang/Object;
    flags: (0x0009) ACC_PUBLIC, ACC_STATIC
    Code:
      stack=4, locals=3, args_size=3
         0: getstatic     #37                 // Field scala/collection/immutable/OldHashSet$.MODULE$:Lscala/collection/immutable/OldHashSet$;
         3: iload_0
         4: iload_1
         5: aload_2
         6: invokevirtual #90                 // Method scala/collection/immutable/OldHashSet$.fill:(IILscala/Function0;)Ljava/lang/Object;
         9: areturn
      LocalVariableTable:
        Start  Length  Slot  Name   Signature
            0      10     0    n1   I
            0      10     1    n2   I
            0      10     2  elem   Lscala/Function0;
    MethodParameters:
      Name                           Flags
      n1                             final
      n2                             final
      elem                           final

  public static java.lang.Object fill(int, scala.Function0);
    descriptor: (ILscala/Function0;)Ljava/lang/Object;
    flags: (0x0009) ACC_PUBLIC, ACC_STATIC
    Code:
      stack=3, locals=2, args_size=2
         0: getstatic     #37                 // Field scala/collection/immutable/OldHashSet$.MODULE$:Lscala/collection/immutable/OldHashSet$;
         3: iload_0
         4: aload_1
         5: invokevirtual #93                 // Method scala/collection/immutable/OldHashSet$.fill:(ILscala/Function0;)Ljava/lang/Object;
         8: areturn
      LocalVariableTable:
        Start  Length  Slot  Name   Signature
            0       9     0     n   I
            0       9     1  elem   Lscala/Function0;
    MethodParameters:
      Name                           Flags
      n                              final
      elem                           final

  public static java.lang.Object range(java.lang.Object, java.lang.Object, java.lang.Object, scala.math.Integral);
    descriptor: (Ljava/lang/Object;Ljava/lang/Object;Ljava/lang/Object;Lscala/math/Integral;)Ljava/lang/Object;
    flags: (0x0009) ACC_PUBLIC, ACC_STATIC
    Code:
      stack=5, locals=4, args_size=4
         0: getstatic     #37                 // Field scala/collection/immutable/OldHashSet$.MODULE$:Lscala/collection/immutable/OldHashSet$;
         3: aload_0
         4: aload_1
         5: aload_2
         6: aload_3
         7: invokevirtual #101                // Method scala/collection/immutable/OldHashSet$.range:(Ljava/lang/Object;Ljava/lang/Object;Ljava/lang/Object;Lscala/math/Integral;)Ljava/lang/Object;
        10: areturn
      LocalVariableTable:
        Start  Length  Slot  Name   Signature
            0      11     0 start   Ljava/lang/Object;
            0      11     1   end   Ljava/lang/Object;
            0      11     2  step   Ljava/lang/Object;
            0      11     3 evidence$4   Lscala/math/Integral;
    MethodParameters:
      Name                           Flags
      start                          final
      end                            final
      step                           final
      evidence$4                     final

  public static java.lang.Object range(java.lang.Object, java.lang.Object, scala.math.Integral);
    descriptor: (Ljava/lang/Object;Ljava/lang/Object;Lscala/math/Integral;)Ljava/lang/Object;
    flags: (0x0009) ACC_PUBLIC, ACC_STATIC
    Code:
      stack=4, locals=3, args_size=3
         0: getstatic     #37                 // Field scala/collection/immutable/OldHashSet$.MODULE$:Lscala/collection/immutable/OldHashSet$;
         3: aload_0
         4: aload_1
         5: aload_2
         6: invokevirtual #107                // Method scala/collection/immutable/OldHashSet$.range:(Ljava/lang/Object;Ljava/lang/Object;Lscala/math/Integral;)Ljava/lang/Object;
         9: areturn
      LocalVariableTable:
        Start  Length  Slot  Name   Signature
            0      10     0 start   Ljava/lang/Object;
            0      10     1   end   Ljava/lang/Object;
            0      10     2 evidence$3   Lscala/math/Integral;
    MethodParameters:
      Name                           Flags
      start                          final
      end                            final
      evidence$3                     final

  public static java.lang.Object unfold(java.lang.Object, scala.Function1);
    descriptor: (Ljava/lang/Object;Lscala/Function1;)Ljava/lang/Object;
    flags: (0x0009) ACC_PUBLIC, ACC_STATIC
    Code:
      stack=3, locals=2, args_size=2
         0: getstatic     #37                 // Field scala/collection/immutable/OldHashSet$.MODULE$:Lscala/collection/immutable/OldHashSet$;
         3: aload_0
         4: aload_1
         5: invokevirtual #112                // Method scala/collection/immutable/OldHashSet$.unfold:(Ljava/lang/Object;Lscala/Function1;)Ljava/lang/Object;
         8: areturn
      LocalVariableTable:
        Start  Length  Slot  Name   Signature
            0       9     0  init   Ljava/lang/Object;
            0       9     1     f   Lscala/Function1;
    MethodParameters:
      Name                           Flags
      init                           final
      f                              final

  public static java.lang.Object iterate(java.lang.Object, int, scala.Function1);
    descriptor: (Ljava/lang/Object;ILscala/Function1;)Ljava/lang/Object;
    flags: (0x0009) ACC_PUBLIC, ACC_STATIC
    Code:
      stack=4, locals=3, args_size=3
         0: getstatic     #37                 // Field scala/collection/immutable/OldHashSet$.MODULE$:Lscala/collection/immutable/OldHashSet$;
         3: aload_0
         4: iload_1
         5: aload_2
         6: invokevirtual #117                // Method scala/collection/immutable/OldHashSet$.iterate:(Ljava/lang/Object;ILscala/Function1;)Ljava/lang/Object;
         9: areturn
      LocalVariableTable:
        Start  Length  Slot  Name   Signature
            0      10     0 start   Ljava/lang/Object;
            0      10     1   len   I
            0      10     2     f   Lscala/Function1;
    MethodParameters:
      Name                           Flags
      start                          final
      len                            final
      f                              final

  public scala.Tuple2<scala.collection.immutable.OldHashSet<A>, scala.collection.immutable.OldHashSet<A>> partition(scala.Function1<A, java.lang.Object>);
    descriptor: (Lscala/Function1;)Lscala/Tuple2;
    flags: (0x0001) ACC_PUBLIC
    Code:
      stack=2, locals=2, args_size=2
         0: aload_0
         1: aload_1
         2: invokestatic  #125                // InterfaceMethod scala/collection/StrictOptimizedIterableOps.partition$:(Lscala/collection/StrictOptimizedIterableOps;Lscala/Function1;)Lscala/Tuple2;
         5: areturn
      LineNumberTable:
        line 35: 0
      LocalVariableTable:
        Start  Length  Slot  Name   Signature
            0       6     0  this   Lscala/collection/immutable/OldHashSet;
            0       6     1     p   Lscala/Function1;
    Signature: #120                         // (Lscala/Function1<TA;Ljava/lang/Object;>;)Lscala/Tuple2<Lscala/collection/immutable/OldHashSet<TA;>;Lscala/collection/immutable/OldHashSet<TA;>;>;
    MethodParameters:
      Name                           Flags
      p                              final

  public scala.Tuple2<scala.collection.immutable.OldHashSet<A>, scala.collection.immutable.OldHashSet<A>> span(scala.Function1<A, java.lang.Object>);
    descriptor: (Lscala/Function1;)Lscala/Tuple2;
    flags: (0x0001) ACC_PUBLIC
    Code:
      stack=2, locals=2, args_size=2
         0: aload_0
         1: aload_1
         2: invokestatic  #131                // InterfaceMethod scala/collection/StrictOptimizedIterableOps.span$:(Lscala/collection/StrictOptimizedIterableOps;Lscala/Function1;)Lscala/Tuple2;
         5: areturn
      LineNumberTable:
        line 35: 0
      LocalVariableTable:
        Start  Length  Slot  Name   Signature
            0       6     0  this   Lscala/collection/immutable/OldHashSet;
            0       6     1     p   Lscala/Function1;
    Signature: #120                         // (Lscala/Function1<TA;Ljava/lang/Object;>;)Lscala/Tuple2<Lscala/collection/immutable/OldHashSet<TA;>;Lscala/collection/immutable/OldHashSet<TA;>;>;
    MethodParameters:
      Name                           Flags
      p                              final

  public <A1 extends java.lang.Object, A2 extends java.lang.Object> scala.Tuple2<scala.collection.immutable.OldHashSet<A1>, scala.collection.immutable.OldHashSet<A2>> unzip(scala.Function1<A, scala.Tuple2<A1, A2>>);
    descriptor: (Lscala/Function1;)Lscala/Tuple2;
    flags: (0x0001) ACC_PUBLIC
    Code:
      stack=2, locals=2, args_size=2
         0: aload_0
         1: aload_1
         2: invokestatic  #137                // InterfaceMethod scala/collection/StrictOptimizedIterableOps.unzip$:(Lscala/collection/StrictOptimizedIterableOps;Lscala/Function1;)Lscala/Tuple2;
         5: areturn
      LineNumberTable:
        line 35: 0
      LocalVariableTable:
        Start  Length  Slot  Name   Signature
            0       6     0  this   Lscala/collection/immutable/OldHashSet;
            0       6     1 asPair   Lscala/Function1;
    Signature: #133                         // <A1:Ljava/lang/Object;A2:Ljava/lang/Object;>(Lscala/Function1<TA;Lscala/Tuple2<TA1;TA2;>;>;)Lscala/Tuple2<Lscala/collection/immutable/OldHashSet<TA1;>;Lscala/collection/immutable/OldHashSet<TA2;>;>;
    MethodParameters:
      Name                           Flags
      asPair                         final

  public <A1 extends java.lang.Object, A2 extends java.lang.Object, A3 extends java.lang.Object> scala.Tuple3<scala.collection.immutable.OldHashSet<A1>, scala.collection.immutable.OldHashSet<A2>, scala.collection.immutable.OldHashSet<A3>> unzip3(scala.Function1<A, scala.Tuple3<A1, A2, A3>>);
    descriptor: (Lscala/Function1;)Lscala/Tuple3;
    flags: (0x0001) ACC_PUBLIC
    Code:
      stack=2, locals=2, args_size=2
         0: aload_0
         1: aload_1
         2: invokestatic  #145                // InterfaceMethod scala/collection/StrictOptimizedIterableOps.unzip3$:(Lscala/collection/StrictOptimizedIterableOps;Lscala/Function1;)Lscala/Tuple3;
         5: areturn
      LineNumberTable:
        line 35: 0
      LocalVariableTable:
        Start  Length  Slot  Name   Signature
            0       6     0  this   Lscala/collection/immutable/OldHashSet;
            0       6     1 asTriple   Lscala/Function1;
    Signature: #140                         // <A1:Ljava/lang/Object;A2:Ljava/lang/Object;A3:Ljava/lang/Object;>(Lscala/Function1<TA;Lscala/Tuple3<TA1;TA2;TA3;>;>;)Lscala/Tuple3<Lscala/collection/immutable/OldHashSet<TA1;>;Lscala/collection/immutable/OldHashSet<TA2;>;Lscala/collection/immutable/OldHashSet<TA3;>;>;
    MethodParameters:
      Name                           Flags
      asTriple                       final

  public java.lang.Object map(scala.Function1);
    descriptor: (Lscala/Function1;)Ljava/lang/Object;
    flags: (0x0001) ACC_PUBLIC
    Code:
      stack=2, locals=2, args_size=2
         0: aload_0
         1: aload_1
         2: invokestatic  #151                // InterfaceMethod scala/collection/StrictOptimizedIterableOps.map$:(Lscala/collection/StrictOptimizedIterableOps;Lscala/Function1;)Ljava/lang/Object;
         5: areturn
      LineNumberTable:
        line 35: 0
      LocalVariableTable:
        Start  Length  Slot  Name   Signature
            0       6     0  this   Lscala/collection/immutable/OldHashSet;
            0       6     1     f   Lscala/Function1;
    MethodParameters:
      Name                           Flags
      f                              final

  public final <B extends java.lang.Object, C2 extends java.lang.Object> C2 strictOptimizedMap(scala.collection.mutable.Builder<B, C2>, scala.Function1<A, B>);
    descriptor: (Lscala/collection/mutable/Builder;Lscala/Function1;)Ljava/lang/Object;
    flags: (0x0011) ACC_PUBLIC, ACC_FINAL
    Code:
      stack=3, locals=3, args_size=3
         0: aload_0
         1: aload_1
         2: aload_2
         3: invokestatic  #159                // InterfaceMethod scala/collection/StrictOptimizedIterableOps.strictOptimizedMap$:(Lscala/collection/StrictOptimizedIterableOps;Lscala/collection/mutable/Builder;Lscala/Function1;)Ljava/lang/Object;
         6: areturn
      LineNumberTable:
        line 35: 0
      LocalVariableTable:
        Start  Length  Slot  Name   Signature
            0       7     0  this   Lscala/collection/immutable/OldHashSet;
            0       7     1     b   Lscala/collection/mutable/Builder;
            0       7     2     f   Lscala/Function1;
    Signature: #154                         // <B:Ljava/lang/Object;C2:Ljava/lang/Object;>(Lscala/collection/mutable/Builder<TB;TC2;>;Lscala/Function1<TA;TB;>;)TC2;
    MethodParameters:
      Name                           Flags
      b                              final
      f                              final

  public java.lang.Object flatMap(scala.Function1);
    descriptor: (Lscala/Function1;)Ljava/lang/Object;
    flags: (0x0001) ACC_PUBLIC
    Code:
      stack=2, locals=2, args_size=2
         0: aload_0
         1: aload_1
         2: invokestatic  #164                // InterfaceMethod scala/collection/StrictOptimizedIterableOps.flatMap$:(Lscala/collection/StrictOptimizedIterableOps;Lscala/Function1;)Ljava/lang/Object;
         5: areturn
      LineNumberTable:
        line 35: 0
      LocalVariableTable:
        Start  Length  Slot  Name   Signature
            0       6     0  this   Lscala/collection/immutable/OldHashSet;
            0       6     1     f   Lscala/Function1;
    MethodParameters:
      Name                           Flags
      f                              final

  public final <B extends java.lang.Object, C2 extends java.lang.Object> C2 strictOptimizedFlatMap(scala.collection.mutable.Builder<B, C2>, scala.Function1<A, scala.collection.IterableOnce<B>>);
    descriptor: (Lscala/collection/mutable/Builder;Lscala/Function1;)Ljava/lang/Object;
    flags: (0x0011) ACC_PUBLIC, ACC_FINAL
    Code:
      stack=3, locals=3, args_size=3
         0: aload_0
         1: aload_1
         2: aload_2
         3: invokestatic  #169                // InterfaceMethod scala/collection/StrictOptimizedIterableOps.strictOptimizedFlatMap$:(Lscala/collection/StrictOptimizedIterableOps;Lscala/collection/mutable/Builder;Lscala/Function1;)Ljava/lang/Object;
         6: areturn
      LineNumberTable:
        line 35: 0
      LocalVariableTable:
        Start  Length  Slot  Name   Signature
            0       7     0  this   Lscala/collection/immutable/OldHashSet;
            0       7     1     b   Lscala/collection/mutable/Builder;
            0       7     2     f   Lscala/Function1;
    Signature: #166                         // <B:Ljava/lang/Object;C2:Ljava/lang/Object;>(Lscala/collection/mutable/Builder<TB;TC2;>;Lscala/Function1<TA;Lscala/collection/IterableOnce<TB;>;>;)TC2;
    MethodParameters:
      Name                           Flags
      b                              final
      f                              final

  public final <B extends java.lang.Object, C2 extends java.lang.Object> C2 strictOptimizedConcat(scala.collection.IterableOnce<B>, scala.collection.mutable.Builder<B, C2>);
    descriptor: (Lscala/collection/IterableOnce;Lscala/collection/mutable/Builder;)Ljava/lang/Object;
    flags: (0x0011) ACC_PUBLIC, ACC_FINAL
    Code:
      stack=3, locals=3, args_size=3
         0: aload_0
         1: aload_1
         2: aload_2
         3: invokestatic  #177                // InterfaceMethod scala/collection/StrictOptimizedIterableOps.strictOptimizedConcat$:(Lscala/collection/StrictOptimizedIterableOps;Lscala/collection/IterableOnce;Lscala/collection/mutable/Builder;)Ljava/lang/Object;
         6: areturn
      LineNumberTable:
        line 35: 0
      LocalVariableTable:
        Start  Length  Slot  Name   Signature
            0       7     0  this   Lscala/collection/immutable/OldHashSet;
            0       7     1  that   Lscala/collection/IterableOnce;
            0       7     2     b   Lscala/collection/mutable/Builder;
    Signature: #172                         // <B:Ljava/lang/Object;C2:Ljava/lang/Object;>(Lscala/collection/IterableOnce<TB;>;Lscala/collection/mutable/Builder<TB;TC2;>;)TC2;
    MethodParameters:
      Name                           Flags
      that                           final
      b                              final

  public java.lang.Object collect(scala.PartialFunction);
    descriptor: (Lscala/PartialFunction;)Ljava/lang/Object;
    flags: (0x0001) ACC_PUBLIC
    Code:
      stack=2, locals=2, args_size=2
         0: aload_0
         1: aload_1
         2: invokestatic  #184                // InterfaceMethod scala/collection/StrictOptimizedIterableOps.collect$:(Lscala/collection/StrictOptimizedIterableOps;Lscala/PartialFunction;)Ljava/lang/Object;
         5: areturn
      LineNumberTable:
        line 35: 0
      LocalVariableTable:
        Start  Length  Slot  Name   Signature
            0       6     0  this   Lscala/collection/immutable/OldHashSet;
            0       6     1    pf   Lscala/PartialFunction;
    MethodParameters:
      Name                           Flags
      pf                             final

  public final <B extends java.lang.Object, C2 extends java.lang.Object> C2 strictOptimizedCollect(scala.collection.mutable.Builder<B, C2>, scala.PartialFunction<A, B>);
    descriptor: (Lscala/collection/mutable/Builder;Lscala/PartialFunction;)Ljava/lang/Object;
    flags: (0x0011) ACC_PUBLIC, ACC_FINAL
    Code:
      stack=3, locals=3, args_size=3
         0: aload_0
         1: aload_1
         2: aload_2
         3: invokestatic  #192                // InterfaceMethod scala/collection/StrictOptimizedIterableOps.strictOptimizedCollect$:(Lscala/collection/StrictOptimizedIterableOps;Lscala/collection/mutable/Builder;Lscala/PartialFunction;)Ljava/lang/Object;
         6: areturn
      LineNumberTable:
        line 35: 0
      LocalVariableTable:
        Start  Length  Slot  Name   Signature
            0       7     0  this   Lscala/collection/immutable/OldHashSet;
            0       7     1     b   Lscala/collection/mutable/Builder;
            0       7     2    pf   Lscala/PartialFunction;
    Signature: #188                         // <B:Ljava/lang/Object;C2:Ljava/lang/Object;>(Lscala/collection/mutable/Builder<TB;TC2;>;Lscala/PartialFunction<TA;TB;>;)TC2;
    MethodParameters:
      Name                           Flags
      b                              final
      pf                             final

  public java.lang.Object flatten(scala.Function1);
    descriptor: (Lscala/Function1;)Ljava/lang/Object;
    flags: (0x0001) ACC_PUBLIC
    Code:
      stack=2, locals=2, args_size=2
         0: aload_0
         1: aload_1
         2: invokestatic  #197                // InterfaceMethod scala/collection/StrictOptimizedIterableOps.flatten$:(Lscala/collection/StrictOptimizedIterableOps;Lscala/Function1;)Ljava/lang/Object;
         5: areturn
      LineNumberTable:
        line 35: 0
      LocalVariableTable:
        Start  Length  Slot  Name   Signature
            0       6     0  this   Lscala/collection/immutable/OldHashSet;
            0       6     1 toIterableOnce   Lscala/Function1;
    MethodParameters:
      Name                           Flags
      toIterableOnce                 final

  public final <B extends java.lang.Object, C2 extends java.lang.Object> C2 strictOptimizedFlatten(scala.collection.mutable.Builder<B, C2>, scala.Function1<A, scala.collection.IterableOnce<B>>);
    descriptor: (Lscala/collection/mutable/Builder;Lscala/Function1;)Ljava/lang/Object;
    flags: (0x0011) ACC_PUBLIC, ACC_FINAL
    Code:
      stack=3, locals=3, args_size=3
         0: aload_0
         1: aload_1
         2: aload_2
         3: invokestatic  #201                // InterfaceMethod scala/collection/StrictOptimizedIterableOps.strictOptimizedFlatten$:(Lscala/collection/StrictOptimizedIterableOps;Lscala/collection/mutable/Builder;Lscala/Function1;)Ljava/lang/Object;
         6: areturn
      LineNumberTable:
        line 35: 0
      LocalVariableTable:
        Start  Length  Slot  Name   Signature
            0       7     0  this   Lscala/collection/immutable/OldHashSet;
            0       7     1     b   Lscala/collection/mutable/Builder;
            0       7     2 toIterableOnce   Lscala/Function1;
    Signature: #166                         // <B:Ljava/lang/Object;C2:Ljava/lang/Object;>(Lscala/collection/mutable/Builder<TB;TC2;>;Lscala/Function1<TA;Lscala/collection/IterableOnce<TB;>;>;)TC2;
    MethodParameters:
      Name                           Flags
      b                              final
      toIterableOnce                 final

  public java.lang.Object zip(scala.collection.IterableOnce);
    descriptor: (Lscala/collection/IterableOnce;)Ljava/lang/Object;
    flags: (0x0001) ACC_PUBLIC
    Code:
      stack=2, locals=2, args_size=2
         0: aload_0
         1: aload_1
         2: invokestatic  #207                // InterfaceMethod scala/collection/StrictOptimizedIterableOps.zip$:(Lscala/collection/StrictOptimizedIterableOps;Lscala/collection/IterableOnce;)Ljava/lang/Object;
         5: areturn
      LineNumberTable:
        line 35: 0
      LocalVariableTable:
        Start  Length  Slot  Name   Signature
            0       6     0  this   Lscala/collection/immutable/OldHashSet;
            0       6     1  that   Lscala/collection/IterableOnce;
    MethodParameters:
      Name                           Flags
      that                           final

  public final <B extends java.lang.Object, C2 extends java.lang.Object> C2 strictOptimizedZip(scala.collection.IterableOnce<B>, scala.collection.mutable.Builder<scala.Tuple2<A, B>, C2>);
    descriptor: (Lscala/collection/IterableOnce;Lscala/collection/mutable/Builder;)Ljava/lang/Object;
    flags: (0x0011) ACC_PUBLIC, ACC_FINAL
    Code:
      stack=3, locals=3, args_size=3
         0: aload_0
         1: aload_1
         2: aload_2
         3: invokestatic  #212                // InterfaceMethod scala/collection/StrictOptimizedIterableOps.strictOptimizedZip$:(Lscala/collection/StrictOptimizedIterableOps;Lscala/collection/IterableOnce;Lscala/collection/mutable/Builder;)Ljava/lang/Object;
         6: areturn
      LineNumberTable:
        line 35: 0
      LocalVariableTable:
        Start  Length  Slot  Name   Signature
            0       7     0  this   Lscala/collection/immutable/OldHashSet;
            0       7     1  that   Lscala/collection/IterableOnce;
            0       7     2     b   Lscala/collection/mutable/Builder;
    Signature: #209                         // <B:Ljava/lang/Object;C2:Ljava/lang/Object;>(Lscala/collection/IterableOnce<TB;>;Lscala/collection/mutable/Builder<Lscala/Tuple2<TA;TB;>;TC2;>;)TC2;
    MethodParameters:
      Name                           Flags
      that                           final
      b                              final

  public java.lang.Object zipWithIndex();
    descriptor: ()Ljava/lang/Object;
    flags: (0x0001) ACC_PUBLIC
    Code:
      stack=1, locals=1, args_size=1
         0: aload_0
         1: invokestatic  #218                // InterfaceMethod scala/collection/StrictOptimizedIterableOps.zipWithIndex$:(Lscala/collection/StrictOptimizedIterableOps;)Ljava/lang/Object;
         4: areturn
      LineNumberTable:
        line 35: 0
      LocalVariableTable:
        Start  Length  Slot  Name   Signature
            0       5     0  this   Lscala/collection/immutable/OldHashSet;

  public java.lang.Object scanLeft(java.lang.Object, scala.Function2);
    descriptor: (Ljava/lang/Object;Lscala/Function2;)Ljava/lang/Object;
    flags: (0x0001) ACC_PUBLIC
    Code:
      stack=3, locals=3, args_size=3
         0: aload_0
         1: aload_1
         2: aload_2
         3: invokestatic  #226                // InterfaceMethod scala/collection/StrictOptimizedIterableOps.scanLeft$:(Lscala/collection/StrictOptimizedIterableOps;Ljava/lang/Object;Lscala/Function2;)Ljava/lang/Object;
         6: areturn
      LineNumberTable:
        line 35: 0
      LocalVariableTable:
        Start  Length  Slot  Name   Signature
            0       7     0  this   Lscala/collection/immutable/OldHashSet;
            0       7     1     z   Ljava/lang/Object;
            0       7     2    op   Lscala/Function2;
    MethodParameters:
      Name                           Flags
      z                              final
      op                             final

  public java.lang.Object filterImpl(scala.Function1, boolean);
    descriptor: (Lscala/Function1;Z)Ljava/lang/Object;
    flags: (0x0001) ACC_PUBLIC
    Code:
      stack=3, locals=3, args_size=3
         0: aload_0
         1: aload_1
         2: iload_2
         3: invokestatic  #234                // InterfaceMethod scala/collection/StrictOptimizedIterableOps.filterImpl$:(Lscala/collection/StrictOptimizedIterableOps;Lscala/Function1;Z)Ljava/lang/Object;
         6: areturn
      LineNumberTable:
        line 35: 0
      LocalVariableTable:
        Start  Length  Slot  Name   Signature
            0       7     0  this   Lscala/collection/immutable/OldHashSet;
            0       7     1  pred   Lscala/Function1;
            0       7     2 isFlipped   Z
    MethodParameters:
      Name                           Flags
      pred                           final
      isFlipped                      final

  public <A1 extends java.lang.Object, A2 extends java.lang.Object> scala.Tuple2<scala.collection.immutable.OldHashSet<A1>, scala.collection.immutable.OldHashSet<A2>> partitionMap(scala.Function1<A, scala.util.Either<A1, A2>>);
    descriptor: (Lscala/Function1;)Lscala/Tuple2;
    flags: (0x0001) ACC_PUBLIC
    Code:
      stack=2, locals=2, args_size=2
         0: aload_0
         1: aload_1
         2: invokestatic  #240                // InterfaceMethod scala/collection/StrictOptimizedIterableOps.partitionMap$:(Lscala/collection/StrictOptimizedIterableOps;Lscala/Function1;)Lscala/Tuple2;
         5: areturn
      LineNumberTable:
        line 35: 0
      LocalVariableTable:
        Start  Length  Slot  Name   Signature
            0       6     0  this   Lscala/collection/immutable/OldHashSet;
            0       6     1     f   Lscala/Function1;
    Signature: #237                         // <A1:Ljava/lang/Object;A2:Ljava/lang/Object;>(Lscala/Function1<TA;Lscala/util/Either<TA1;TA2;>;>;)Lscala/Tuple2<Lscala/collection/immutable/OldHashSet<TA1;>;Lscala/collection/immutable/OldHashSet<TA2;>;>;
    MethodParameters:
      Name                           Flags
      f                              final

  public java.lang.Object tapEach(scala.Function1);
    descriptor: (Lscala/Function1;)Ljava/lang/Object;
    flags: (0x0001) ACC_PUBLIC
    Code:
      stack=2, locals=2, args_size=2
         0: aload_0
         1: aload_1
         2: invokestatic  #244                // InterfaceMethod scala/collection/StrictOptimizedIterableOps.tapEach$:(Lscala/collection/StrictOptimizedIterableOps;Lscala/Function1;)Ljava/lang/Object;
         5: areturn
      LineNumberTable:
        line 35: 0
      LocalVariableTable:
        Start  Length  Slot  Name   Signature
            0       6     0  this   Lscala/collection/immutable/OldHashSet;
            0       6     1     f   Lscala/Function1;
    MethodParameters:
      Name                           Flags
      f                              final

  public java.lang.Object takeRight(int);
    descriptor: (I)Ljava/lang/Object;
    flags: (0x0001) ACC_PUBLIC
    Code:
      stack=2, locals=2, args_size=2
         0: aload_0
         1: iload_1
         2: invokestatic  #250                // InterfaceMethod scala/collection/StrictOptimizedIterableOps.takeRight$:(Lscala/collection/StrictOptimizedIterableOps;I)Ljava/lang/Object;
         5: areturn
      LineNumberTable:
        line 35: 0
      LocalVariableTable:
        Start  Length  Slot  Name   Signature
            0       6     0  this   Lscala/collection/immutable/OldHashSet;
            0       6     1     n   I
    MethodParameters:
      Name                           Flags
      n                              final

  public java.lang.Object dropRight(int);
    descriptor: (I)Ljava/lang/Object;
    flags: (0x0001) ACC_PUBLIC
    Code:
      stack=2, locals=2, args_size=2
         0: aload_0
         1: iload_1
         2: invokestatic  #254                // InterfaceMethod scala/collection/StrictOptimizedIterableOps.dropRight$:(Lscala/collection/StrictOptimizedIterableOps;I)Ljava/lang/Object;
         5: areturn
      LineNumberTable:
        line 35: 0
      LocalVariableTable:
        Start  Length  Slot  Name   Signature
            0       6     0  this   Lscala/collection/immutable/OldHashSet;
            0       6     1     n   I
    MethodParameters:
      Name                           Flags
      n                              final

  public java.lang.String className();
    descriptor: ()Ljava/lang/String;
    flags: (0x0001) ACC_PUBLIC
    Code:
      stack=1, locals=1, args_size=1
         0: ldc_w         #258                // String OldHashSet
         3: areturn
      LineNumberTable:
        line 44: 0
      LocalVariableTable:
        Start  Length  Slot  Name   Signature
            0       4     0  this   Lscala/collection/immutable/OldHashSet;

  public scala.collection.immutable.OldHashSet$ iterableFactory();
    descriptor: ()Lscala/collection/immutable/OldHashSet$;
    flags: (0x0001) ACC_PUBLIC
    Code:
      stack=1, locals=1, args_size=1
         0: getstatic     #37                 // Field scala/collection/immutable/OldHashSet$.MODULE$:Lscala/collection/immutable/OldHashSet$;
         3: areturn
      LineNumberTable:
        line 46: 0
      LocalVariableTable:
        Start  Length  Slot  Name   Signature
            0       4     0  this   Lscala/collection/immutable/OldHashSet;

  public boolean contains(A);
    descriptor: (Ljava/lang/Object;)Z
    flags: (0x0001) ACC_PUBLIC
    Code:
      stack=4, locals=2, args_size=2
         0: aload_0
         1: aload_1
         2: getstatic     #268                // Field scala/collection/Hashing$.MODULE$:Lscala/collection/Hashing$;
         5: aload_1
         6: invokevirtual #272                // Method scala/collection/Hashing$.computeHash:(Ljava/lang/Object;)I
         9: iconst_0
        10: invokevirtual #276                // Method get0:(Ljava/lang/Object;II)Z
        13: ireturn
      LineNumberTable:
        line 48: 0
      LocalVariableTable:
        Start  Length  Slot  Name   Signature
            0      14     0  this   Lscala/collection/immutable/OldHashSet;
            0      14     1  elem   Ljava/lang/Object;
    Signature: #263                         // (TA;)Z
    MethodParameters:
      Name                           Flags
      elem                           final

  public scala.collection.immutable.OldHashSet<A> incl(A);
    descriptor: (Ljava/lang/Object;)Lscala/collection/immutable/OldHashSet;
    flags: (0x0001) ACC_PUBLIC
    Code:
      stack=4, locals=2, args_size=2
         0: aload_0
         1: aload_1
         2: getstatic     #268                // Field scala/collection/Hashing$.MODULE$:Lscala/collection/Hashing$;
         5: aload_1
         6: invokevirtual #272                // Method scala/collection/Hashing$.computeHash:(Ljava/lang/Object;)I
         9: iconst_0
        10: invokevirtual #283                // Method updated0:(Ljava/lang/Object;II)Lscala/collection/immutable/OldHashSet;
        13: areturn
      LineNumberTable:
        line 50: 0
      LocalVariableTable:
        Start  Length  Slot  Name   Signature
            0      14     0  this   Lscala/collection/immutable/OldHashSet;
            0      14     1  elem   Ljava/lang/Object;
    Signature: #279                         // (TA;)Lscala/collection/immutable/OldHashSet<TA;>;
    MethodParameters:
      Name                           Flags
      elem                           final

  public scala.collection.immutable.OldHashSet<A> excl(A);
    descriptor: (Ljava/lang/Object;)Lscala/collection/immutable/OldHashSet;
    flags: (0x0001) ACC_PUBLIC
    Code:
      stack=5, locals=2, args_size=2
         0: getstatic     #37                 // Field scala/collection/immutable/OldHashSet$.MODULE$:Lscala/collection/immutable/OldHashSet$;
         3: aload_0
         4: aload_1
         5: getstatic     #268                // Field scala/collection/Hashing$.MODULE$:Lscala/collection/Hashing$;
         8: aload_1
         9: invokevirtual #272                // Method scala/collection/Hashing$.computeHash:(Ljava/lang/Object;)I
        12: iconst_0
        13: invokevirtual #287                // Method removed0:(Ljava/lang/Object;II)Lscala/collection/immutable/OldHashSet;
        16: invokevirtual #291                // Method scala/collection/immutable/OldHashSet$.scala$collection$immutable$OldHashSet$$nullToEmpty:(Lscala/collection/immutable/OldHashSet;)Lscala/collection/immutable/OldHashSet;
        19: areturn
      LineNumberTable:
        line 52: 0
      LocalVariableTable:
        Start  Length  Slot  Name   Signature
            0      20     0  this   Lscala/collection/immutable/OldHashSet;
            0      20     1  elem   Ljava/lang/Object;
    Signature: #279                         // (TA;)Lscala/collection/immutable/OldHashSet<TA;>;
    MethodParameters:
      Name                           Flags
      elem                           final

  public boolean subsetOf(scala.collection.Set<A>);
    descriptor: (Lscala/collection/Set;)Z
    flags: (0x0001) ACC_PUBLIC
    Code:
      stack=3, locals=5, args_size=2
         0: aload_1
         1: astore_3
         2: aload_3
         3: instanceof    #2                  // class scala/collection/immutable/OldHashSet
         6: ifeq          26
         9: aload_3
        10: checkcast     #2                  // class scala/collection/immutable/OldHashSet
        13: astore        4
        15: aload_0
        16: aload         4
        18: iconst_0
        19: invokevirtual #298                // Method subsetOf0:(Lscala/collection/immutable/OldHashSet;I)Z
        22: istore_2
        23: goto          38
        26: goto          29
        29: aload_0
        30: aload_1
        31: invokestatic  #304                // InterfaceMethod scala/collection/SetOps.subsetOf$:(Lscala/collection/SetOps;Lscala/collection/Set;)Z
        34: istore_2
        35: goto          38
        38: iload_2
        39: ireturn
      StackMapTable: number_of_entries = 3
        frame_type = 253 /* append */
          offset_delta = 26
          locals = [ top, class scala/collection/Set ]
        frame_type = 2 /* same */
        frame_type = 255 /* full_frame */
          offset_delta = 8
          locals = [ class scala/collection/immutable/OldHashSet, class scala/collection/Set, int, class scala/collection/Set ]
          stack = []
      LineNumberTable:
        line 54: 0
        line 55: 2
        line 57: 15
        line 55: 26
        line 60: 29
        line 54: 38
      LocalVariableTable:
        Start  Length  Slot  Name   Signature
            0      40     0  this   Lscala/collection/immutable/OldHashSet;
            0      40     1  that   Lscala/collection/Set;
    Signature: #294                         // (Lscala/collection/Set<TA;>;)Z
    MethodParameters:
      Name                           Flags
      that                           final

  public scala.collection.immutable.OldHashSet<A> concat(scala.collection.IterableOnce<A>);
    descriptor: (Lscala/collection/IterableOnce;)Lscala/collection/immutable/OldHashSet;
    flags: (0x0001) ACC_PUBLIC
    Code:
      stack=6, locals=6, args_size=2
         0: aload_1
         1: astore_3
         2: aload_3
         3: instanceof    #2                  // class scala/collection/immutable/OldHashSet
         6: ifeq          56
         9: aload_3
        10: checkcast     #2                  // class scala/collection/immutable/OldHashSet
        13: astore        4
        15: getstatic     #37                 // Field scala/collection/immutable/OldHashSet$.MODULE$:Lscala/collection/immutable/OldHashSet$;
        18: aload_0
        19: invokevirtual #313                // Method size:()I
        22: aload         4
        24: invokevirtual #313                // Method size:()I
        27: iadd
        28: invokevirtual #317                // Method scala/collection/immutable/OldHashSet$.scala$collection$immutable$OldHashSet$$bufferSize:(I)I
        31: anewarray     #2                  // class scala/collection/immutable/OldHashSet
        34: astore        5
        36: getstatic     #37                 // Field scala/collection/immutable/OldHashSet$.MODULE$:Lscala/collection/immutable/OldHashSet$;
        39: aload_0
        40: aload         4
        42: iconst_0
        43: aload         5
        45: iconst_0
        46: invokevirtual #321                // Method union0:(Lscala/collection/immutable/OldHashSet;I[Lscala/collection/immutable/OldHashSet;I)Lscala/collection/immutable/OldHashSet;
        49: invokevirtual #291                // Method scala/collection/immutable/OldHashSet$.scala$collection$immutable$OldHashSet$$nullToEmpty:(Lscala/collection/immutable/OldHashSet;)Lscala/collection/immutable/OldHashSet;
        52: astore_2
        53: goto          71
        56: goto          59
        59: aload_0
        60: aload_1
        61: invokestatic  #325                // InterfaceMethod scala/collection/SetOps.concat$:(Lscala/collection/SetOps;Lscala/collection/IterableOnce;)Lscala/collection/SetOps;
        64: checkcast     #2                  // class scala/collection/immutable/OldHashSet
        67: astore_2
        68: goto          71
        71: aload_2
        72: areturn
      StackMapTable: number_of_entries = 3
        frame_type = 253 /* append */
          offset_delta = 56
          locals = [ top, class scala/collection/IterableOnce ]
        frame_type = 2 /* same */
        frame_type = 255 /* full_frame */
          offset_delta = 11
          locals = [ class scala/collection/immutable/OldHashSet, class scala/collection/IterableOnce, class scala/collection/immutable/OldHashSet, class scala/collection/IterableOnce ]
          stack = []
      LineNumberTable:
        line 63: 0
        line 64: 2
        line 65: 15
        line 66: 36
        line 64: 56
        line 67: 59
        line 63: 71
      LocalVariableTable:
        Start  Length  Slot  Name   Signature
           36      16     5 buffer   [Lscala/collection/immutable/OldHashSet;
            0      73     0  this   Lscala/collection/immutable/OldHashSet;
            0      73     1  that   Lscala/collection/IterableOnce;
    Signature: #309                         // (Lscala/collection/IterableOnce<TA;>;)Lscala/collection/immutable/OldHashSet<TA;>;
    MethodParameters:
      Name                           Flags
      that                           final

  public scala.collection.immutable.OldHashSet<A> intersect(scala.collection.Set<A>);
    descriptor: (Lscala/collection/Set;)Lscala/collection/immutable/OldHashSet;
    flags: (0x0001) ACC_PUBLIC
    Code:
      stack=6, locals=6, args_size=2
         0: aload_1
         1: astore_3
         2: aload_3
         3: instanceof    #2                  // class scala/collection/immutable/OldHashSet
         6: ifeq          67
         9: aload_3
        10: checkcast     #2                  // class scala/collection/immutable/OldHashSet
        13: astore        4
        15: getstatic     #37                 // Field scala/collection/immutable/OldHashSet$.MODULE$:Lscala/collection/immutable/OldHashSet$;
        18: getstatic     #337                // Field scala/runtime/RichInt$.MODULE$:Lscala/runtime/RichInt$;
        21: getstatic     #342                // Field scala/Predef$.MODULE$:Lscala/Predef$;
        24: aload_0
        25: invokevirtual #313                // Method size:()I
        28: invokevirtual #345                // Method scala/Predef$.intWrapper:(I)I
        31: aload         4
        33: invokevirtual #313                // Method size:()I
        36: invokevirtual #349                // Method scala/runtime/RichInt$.min$extension:(II)I
        39: invokevirtual #317                // Method scala/collection/immutable/OldHashSet$.scala$collection$immutable$OldHashSet$$bufferSize:(I)I
        42: anewarray     #2                  // class scala/collection/immutable/OldHashSet
        45: astore        5
        47: getstatic     #37                 // Field scala/collection/immutable/OldHashSet$.MODULE$:Lscala/collection/immutable/OldHashSet$;
        50: aload_0
        51: aload         4
        53: iconst_0
        54: aload         5
        56: iconst_0
        57: invokevirtual #352                // Method intersect0:(Lscala/collection/immutable/OldHashSet;I[Lscala/collection/immutable/OldHashSet;I)Lscala/collection/immutable/OldHashSet;
        60: invokevirtual #291                // Method scala/collection/immutable/OldHashSet$.scala$collection$immutable$OldHashSet$$nullToEmpty:(Lscala/collection/immutable/OldHashSet;)Lscala/collection/immutable/OldHashSet;
        63: astore_2
        64: goto          82
        67: goto          70
        70: aload_0
        71: aload_1
        72: invokestatic  #356                // InterfaceMethod scala/collection/SetOps.intersect$:(Lscala/collection/SetOps;Lscala/collection/Set;)Lscala/collection/SetOps;
        75: checkcast     #2                  // class scala/collection/immutable/OldHashSet
        78: astore_2
        79: goto          82
        82: aload_2
        83: areturn
      StackMapTable: number_of_entries = 3
        frame_type = 253 /* append */
          offset_delta = 67
          locals = [ top, class scala/collection/Set ]
        frame_type = 2 /* same */
        frame_type = 255 /* full_frame */
          offset_delta = 11
          locals = [ class scala/collection/immutable/OldHashSet, class scala/collection/Set, class scala/collection/immutable/OldHashSet, class scala/collection/Set ]
          stack = []
      LineNumberTable:
        line 70: 0
        line 71: 2
        line 72: 15
        line 73: 47
        line 71: 67
        line 74: 70
        line 70: 82
      LocalVariableTable:
        Start  Length  Slot  Name   Signature
           47      16     5 buffer   [Lscala/collection/immutable/OldHashSet;
            0      84     0  this   Lscala/collection/immutable/OldHashSet;
            0      84     1  that   Lscala/collection/Set;
    Signature: #332                         // (Lscala/collection/Set<TA;>;)Lscala/collection/immutable/OldHashSet<TA;>;
    MethodParameters:
      Name                           Flags
      that                           final

  public scala.collection.immutable.OldHashSet<A> diff(scala.collection.Set<A>);
    descriptor: (Lscala/collection/Set;)Lscala/collection/immutable/OldHashSet;
    flags: (0x0001) ACC_PUBLIC
    Code:
      stack=6, locals=6, args_size=2
         0: aload_1
         1: astore_3
         2: aload_3
         3: instanceof    #2                  // class scala/collection/immutable/OldHashSet
         6: ifeq          50
         9: aload_3
        10: checkcast     #2                  // class scala/collection/immutable/OldHashSet
        13: astore        4
        15: getstatic     #37                 // Field scala/collection/immutable/OldHashSet$.MODULE$:Lscala/collection/immutable/OldHashSet$;
        18: aload_0
        19: invokevirtual #313                // Method size:()I
        22: invokevirtual #317                // Method scala/collection/immutable/OldHashSet$.scala$collection$immutable$OldHashSet$$bufferSize:(I)I
        25: anewarray     #2                  // class scala/collection/immutable/OldHashSet
        28: astore        5
        30: getstatic     #37                 // Field scala/collection/immutable/OldHashSet$.MODULE$:Lscala/collection/immutable/OldHashSet$;
        33: aload_0
        34: aload         4
        36: iconst_0
        37: aload         5
        39: iconst_0
        40: invokevirtual #360                // Method diff0:(Lscala/collection/immutable/OldHashSet;I[Lscala/collection/immutable/OldHashSet;I)Lscala/collection/immutable/OldHashSet;
        43: invokevirtual #291                // Method scala/collection/immutable/OldHashSet$.scala$collection$immutable$OldHashSet$$nullToEmpty:(Lscala/collection/immutable/OldHashSet;)Lscala/collection/immutable/OldHashSet;
        46: astore_2
        47: goto          65
        50: goto          53
        53: aload_0
        54: aload_1
        55: invokestatic  #366                // InterfaceMethod scala/collection/immutable/SetOps.diff$:(Lscala/collection/immutable/SetOps;Lscala/collection/Set;)Lscala/collection/immutable/SetOps;
        58: checkcast     #2                  // class scala/collection/immutable/OldHashSet
        61: astore_2
        62: goto          65
        65: aload_2
        66: areturn
      StackMapTable: number_of_entries = 3
        frame_type = 253 /* append */
          offset_delta = 50
          locals = [ top, class scala/collection/Set ]
        frame_type = 2 /* same */
        frame_type = 255 /* full_frame */
          offset_delta = 11
          locals = [ class scala/collection/immutable/OldHashSet, class scala/collection/Set, class scala/collection/immutable/OldHashSet, class scala/collection/Set ]
          stack = []
      LineNumberTable:
        line 77: 0
        line 78: 2
        line 79: 15
        line 80: 30
        line 78: 50
        line 81: 53
        line 77: 65
      LocalVariableTable:
        Start  Length  Slot  Name   Signature
           30      16     5 buffer   [Lscala/collection/immutable/OldHashSet;
            0      67     0  this   Lscala/collection/immutable/OldHashSet;
            0      67     1  that   Lscala/collection/Set;
    Signature: #332                         // (Lscala/collection/Set<TA;>;)Lscala/collection/immutable/OldHashSet<TA;>;
    MethodParameters:
      Name                           Flags
      that                           final

  public scala.collection.immutable.OldHashSet<A> filter(scala.Function1<A, java.lang.Object>);
    descriptor: (Lscala/Function1;)Lscala/collection/immutable/OldHashSet;
    flags: (0x0001) ACC_PUBLIC
    Code:
      stack=7, locals=3, args_size=2
         0: getstatic     #37                 // Field scala/collection/immutable/OldHashSet$.MODULE$:Lscala/collection/immutable/OldHashSet$;
         3: aload_0
         4: invokevirtual #313                // Method size:()I
         7: invokevirtual #317                // Method scala/collection/immutable/OldHashSet$.scala$collection$immutable$OldHashSet$$bufferSize:(I)I
        10: anewarray     #2                  // class scala/collection/immutable/OldHashSet
        13: astore_2
        14: getstatic     #37                 // Field scala/collection/immutable/OldHashSet$.MODULE$:Lscala/collection/immutable/OldHashSet$;
        17: aload_0
        18: aload_1
        19: iconst_0
        20: iconst_0
        21: aload_2
        22: iconst_0
        23: invokevirtual #373                // Method filter0:(Lscala/Function1;ZI[Lscala/collection/immutable/OldHashSet;I)Lscala/collection/immutable/OldHashSet;
        26: invokevirtual #291                // Method scala/collection/immutable/OldHashSet$.scala$collection$immutable$OldHashSet$$nullToEmpty:(Lscala/collection/immutable/OldHashSet;)Lscala/collection/immutable/OldHashSet;
        29: areturn
      LineNumberTable:
        line 85: 0
        line 86: 14
      LocalVariableTable:
        Start  Length  Slot  Name   Signature
           14      15     2 buffer   [Lscala/collection/immutable/OldHashSet;
            0      30     0  this   Lscala/collection/immutable/OldHashSet;
            0      30     1     p   Lscala/Function1;
    Signature: #369                         // (Lscala/Function1<TA;Ljava/lang/Object;>;)Lscala/collection/immutable/OldHashSet<TA;>;
    MethodParameters:
      Name                           Flags
      p                              final

  public scala.collection.immutable.OldHashSet<A> filterNot(scala.Function1<A, java.lang.Object>);
    descriptor: (Lscala/Function1;)Lscala/collection/immutable/OldHashSet;
    flags: (0x0001) ACC_PUBLIC
    Code:
      stack=7, locals=3, args_size=2
         0: getstatic     #37                 // Field scala/collection/immutable/OldHashSet$.MODULE$:Lscala/collection/immutable/OldHashSet$;
         3: aload_0
         4: invokevirtual #313                // Method size:()I
         7: invokevirtual #317                // Method scala/collection/immutable/OldHashSet$.scala$collection$immutable$OldHashSet$$bufferSize:(I)I
        10: anewarray     #2                  // class scala/collection/immutable/OldHashSet
        13: astore_2
        14: getstatic     #37                 // Field scala/collection/immutable/OldHashSet$.MODULE$:Lscala/collection/immutable/OldHashSet$;
        17: aload_0
        18: aload_1
        19: iconst_1
        20: iconst_0
        21: aload_2
        22: iconst_0
        23: invokevirtual #373                // Method filter0:(Lscala/Function1;ZI[Lscala/collection/immutable/OldHashSet;I)Lscala/collection/immutable/OldHashSet;
        26: invokevirtual #291                // Method scala/collection/immutable/OldHashSet$.scala$collection$immutable$OldHashSet$$nullToEmpty:(Lscala/collection/immutable/OldHashSet;)Lscala/collection/immutable/OldHashSet;
        29: areturn
      LineNumberTable:
        line 90: 0
        line 91: 14
      LocalVariableTable:
        Start  Length  Slot  Name   Signature
           14      15     2 buffer   [Lscala/collection/immutable/OldHashSet;
            0      30     0  this   Lscala/collection/immutable/OldHashSet;
            0      30     1     p   Lscala/Function1;
    Signature: #369                         // (Lscala/Function1<TA;Ljava/lang/Object;>;)Lscala/collection/immutable/OldHashSet<TA;>;
    MethodParameters:
      Name                           Flags
      p                              final

  public scala.collection.immutable.OldHashSet<A> tail();
    descriptor: ()Lscala/collection/immutable/OldHashSet;
    flags: (0x0001) ACC_PUBLIC
    Code:
      stack=2, locals=1, args_size=1
         0: aload_0
         1: aload_0
         2: invokevirtual #380                // Method head:()Ljava/lang/Object;
         5: invokevirtual #384                // Method $minus:(Ljava/lang/Object;)Lscala/collection/immutable/SetOps;
         8: checkcast     #2                  // class scala/collection/immutable/OldHashSet
        11: areturn
      LineNumberTable:
        line 94: 0
      LocalVariableTable:
        Start  Length  Slot  Name   Signature
            0      12     0  this   Lscala/collection/immutable/OldHashSet;
    Signature: #377                         // ()Lscala/collection/immutable/OldHashSet<TA;>;

  public scala.collection.immutable.OldHashSet<A> init();
    descriptor: ()Lscala/collection/immutable/OldHashSet;
    flags: (0x0001) ACC_PUBLIC
    Code:
      stack=2, locals=1, args_size=1
         0: aload_0
         1: aload_0
         2: invokevirtual #387                // Method last:()Ljava/lang/Object;
         5: invokevirtual #384                // Method $minus:(Ljava/lang/Object;)Lscala/collection/immutable/SetOps;
         8: checkcast     #2                  // class scala/collection/immutable/OldHashSet
        11: areturn
      LineNumberTable:
        line 96: 0
      LocalVariableTable:
        Start  Length  Slot  Name   Signature
            0      12     0  this   Lscala/collection/immutable/OldHashSet;
    Signature: #377                         // ()Lscala/collection/immutable/OldHashSet<TA;>;

  public abstract boolean get0(A, int, int);
    descriptor: (Ljava/lang/Object;II)Z
    flags: (0x0401) ACC_PUBLIC, ACC_ABSTRACT
    Signature: #388                         // (TA;II)Z
    MethodParameters:
      Name                           Flags
      key                            final
      hash                           final
      level                          final

  public abstract scala.collection.immutable.OldHashSet<A> updated0(A, int, int);
    descriptor: (Ljava/lang/Object;II)Lscala/collection/immutable/OldHashSet;
    flags: (0x0401) ACC_PUBLIC, ACC_ABSTRACT
    Signature: #392                         // (TA;II)Lscala/collection/immutable/OldHashSet<TA;>;
    MethodParameters:
      Name                           Flags
      key                            final
      hash                           final
      level                          final

  public abstract scala.collection.immutable.OldHashSet<A> removed0(A, int, int);
    descriptor: (Ljava/lang/Object;II)Lscala/collection/immutable/OldHashSet;
    flags: (0x0401) ACC_PUBLIC, ACC_ABSTRACT
    Signature: #392                         // (TA;II)Lscala/collection/immutable/OldHashSet<TA;>;
    MethodParameters:
      Name                           Flags
      key                            final
      hash                           final
      level                          final

  public abstract scala.collection.immutable.OldHashSet<A> filter0(scala.Function1<A, java.lang.Object>, boolean, int, scala.collection.immutable.OldHashSet<A>[], int);
    descriptor: (Lscala/Function1;ZI[Lscala/collection/immutable/OldHashSet;I)Lscala/collection/immutable/OldHashSet;
    flags: (0x0401) ACC_PUBLIC, ACC_ABSTRACT
    Signature: #393                         // (Lscala/Function1<TA;Ljava/lang/Object;>;ZI[Lscala/collection/immutable/OldHashSet<TA;>;I)Lscala/collection/immutable/OldHashSet<TA;>;
    MethodParameters:
      Name                           Flags
      p                              final
      negate                         final
      level                          final
      buffer                         final
      offset0                        final

  public abstract boolean subsetOf0(scala.collection.immutable.OldHashSet<A>, int);
    descriptor: (Lscala/collection/immutable/OldHashSet;I)Z
    flags: (0x0401) ACC_PUBLIC, ACC_ABSTRACT
    Signature: #396                         // (Lscala/collection/immutable/OldHashSet<TA;>;I)Z
    MethodParameters:
      Name                           Flags
      that                           final
      level                          final

  public abstract scala.collection.immutable.OldHashSet<A> union0(scala.collection.immutable.OldHashSet$LeafOldHashSet<A>, int);
    descriptor: (Lscala/collection/immutable/OldHashSet$LeafOldHashSet;I)Lscala/collection/immutable/OldHashSet;
    flags: (0x0401) ACC_PUBLIC, ACC_ABSTRACT
    Signature: #398                         // (Lscala/collection/immutable/OldHashSet$LeafOldHashSet<TA;>;I)Lscala/collection/immutable/OldHashSet<TA;>;
    MethodParameters:
      Name                           Flags
      that                           final
      level                          final

  public abstract scala.collection.immutable.OldHashSet<A> union0(scala.collection.immutable.OldHashSet<A>, int, scala.collection.immutable.OldHashSet<A>[], int);
    descriptor: (Lscala/collection/immutable/OldHashSet;I[Lscala/collection/immutable/OldHashSet;I)Lscala/collection/immutable/OldHashSet;
    flags: (0x0401) ACC_PUBLIC, ACC_ABSTRACT
    Signature: #399                         // (Lscala/collection/immutable/OldHashSet<TA;>;I[Lscala/collection/immutable/OldHashSet<TA;>;I)Lscala/collection/immutable/OldHashSet<TA;>;
    MethodParameters:
      Name                           Flags
      that                           final
      level                          final
      buffer                         final
      offset0                        final

  public abstract scala.collection.immutable.OldHashSet<A> intersect0(scala.collection.immutable.OldHashSet<A>, int, scala.collection.immutable.OldHashSet<A>[], int);
    descriptor: (Lscala/collection/immutable/OldHashSet;I[Lscala/collection/immutable/OldHashSet;I)Lscala/collection/immutable/OldHashSet;
    flags: (0x0401) ACC_PUBLIC, ACC_ABSTRACT
    Signature: #399                         // (Lscala/collection/immutable/OldHashSet<TA;>;I[Lscala/collection/immutable/OldHashSet<TA;>;I)Lscala/collection/immutable/OldHashSet<TA;>;
    MethodParameters:
      Name                           Flags
      that                           final
      level                          final
      buffer                         final
      offset0                        final

  public abstract scala.collection.immutable.OldHashSet<A> diff0(scala.collection.immutable.OldHashSet<A>, int, scala.collection.immutable.OldHashSet<A>[], int);
    descriptor: (Lscala/collection/immutable/OldHashSet;I[Lscala/collection/immutable/OldHashSet;I)Lscala/collection/immutable/OldHashSet;
    flags: (0x0401) ACC_PUBLIC, ACC_ABSTRACT
    Signature: #399                         // (Lscala/collection/immutable/OldHashSet<TA;>;I[Lscala/collection/immutable/OldHashSet<TA;>;I)Lscala/collection/immutable/OldHashSet<TA;>;
    MethodParameters:
      Name                           Flags
      that                           final
      level                          final
      buffer                         final
      offset0                        final

  public java.lang.Object init();
    descriptor: ()Ljava/lang/Object;
    flags: (0x1041) ACC_PUBLIC, ACC_BRIDGE, ACC_SYNTHETIC
    Code:
      stack=1, locals=1, args_size=1
         0: aload_0
         1: invokevirtual #401                // Method init:()Lscala/collection/immutable/OldHashSet;
         4: areturn
      LineNumberTable:
        line 35: 0
      LocalVariableTable:
        Start  Length  Slot  Name   Signature
            0       5     0  this   Lscala/collection/immutable/OldHashSet;

  public java.lang.Object tail();
    descriptor: ()Ljava/lang/Object;
    flags: (0x1041) ACC_PUBLIC, ACC_BRIDGE, ACC_SYNTHETIC
    Code:
      stack=1, locals=1, args_size=1
         0: aload_0
         1: invokevirtual #403                // Method tail:()Lscala/collection/immutable/OldHashSet;
         4: areturn
      LineNumberTable:
        line 35: 0
      LocalVariableTable:
        Start  Length  Slot  Name   Signature
            0       5     0  this   Lscala/collection/immutable/OldHashSet;

  public java.lang.Object filterNot(scala.Function1);
    descriptor: (Lscala/Function1;)Ljava/lang/Object;
    flags: (0x1041) ACC_PUBLIC, ACC_BRIDGE, ACC_SYNTHETIC
    Code:
      stack=2, locals=2, args_size=2
         0: aload_0
         1: aload_1
         2: invokevirtual #405                // Method filterNot:(Lscala/Function1;)Lscala/collection/immutable/OldHashSet;
         5: areturn
      LineNumberTable:
        line 35: 0
      LocalVariableTable:
        Start  Length  Slot  Name   Signature
            0       6     0  this   Lscala/collection/immutable/OldHashSet;
            0       6     1  pred   Lscala/Function1;
    MethodParameters:
      Name                           Flags
      pred                           final

  public java.lang.Object filter(scala.Function1);
    descriptor: (Lscala/Function1;)Ljava/lang/Object;
    flags: (0x1041) ACC_PUBLIC, ACC_BRIDGE, ACC_SYNTHETIC
    Code:
      stack=2, locals=2, args_size=2
         0: aload_0
         1: aload_1
         2: invokevirtual #407                // Method filter:(Lscala/Function1;)Lscala/collection/immutable/OldHashSet;
         5: areturn
      LineNumberTable:
        line 35: 0
      LocalVariableTable:
        Start  Length  Slot  Name   Signature
            0       6     0  this   Lscala/collection/immutable/OldHashSet;
            0       6     1  pred   Lscala/Function1;
    MethodParameters:
      Name                           Flags
      pred                           final

  public scala.collection.SetOps diff(scala.collection.Set);
    descriptor: (Lscala/collection/Set;)Lscala/collection/SetOps;
    flags: (0x1041) ACC_PUBLIC, ACC_BRIDGE, ACC_SYNTHETIC
    Code:
      stack=2, locals=2, args_size=2
         0: aload_0
         1: aload_1
         2: invokevirtual #410                // Method diff:(Lscala/collection/Set;)Lscala/collection/immutable/OldHashSet;
         5: areturn
      LineNumberTable:
        line 35: 0
      LocalVariableTable:
        Start  Length  Slot  Name   Signature
            0       6     0  this   Lscala/collection/immutable/OldHashSet;
            0       6     1  that   Lscala/collection/Set;
    MethodParameters:
      Name                           Flags
      that                           final

  public scala.collection.immutable.SetOps diff(scala.collection.Set);
    descriptor: (Lscala/collection/Set;)Lscala/collection/immutable/SetOps;
    flags: (0x1041) ACC_PUBLIC, ACC_BRIDGE, ACC_SYNTHETIC
    Code:
      stack=2, locals=2, args_size=2
         0: aload_0
         1: aload_1
         2: invokevirtual #410                // Method diff:(Lscala/collection/Set;)Lscala/collection/immutable/OldHashSet;
         5: areturn
      LineNumberTable:
        line 35: 0
      LocalVariableTable:
        Start  Length  Slot  Name   Signature
            0       6     0  this   Lscala/collection/immutable/OldHashSet;
            0       6     1  that   Lscala/collection/Set;
    MethodParameters:
      Name                           Flags
      that                           final

  public scala.collection.SetOps intersect(scala.collection.Set);
    descriptor: (Lscala/collection/Set;)Lscala/collection/SetOps;
    flags: (0x1041) ACC_PUBLIC, ACC_BRIDGE, ACC_SYNTHETIC
    Code:
      stack=2, locals=2, args_size=2
         0: aload_0
         1: aload_1
         2: invokevirtual #413                // Method intersect:(Lscala/collection/Set;)Lscala/collection/immutable/OldHashSet;
         5: areturn
      LineNumberTable:
        line 35: 0
      LocalVariableTable:
        Start  Length  Slot  Name   Signature
            0       6     0  this   Lscala/collection/immutable/OldHashSet;
            0       6     1  that   Lscala/collection/Set;
    MethodParameters:
      Name                           Flags
      that                           final

  public scala.collection.SetOps concat(scala.collection.IterableOnce);
    descriptor: (Lscala/collection/IterableOnce;)Lscala/collection/SetOps;
    flags: (0x1041) ACC_PUBLIC, ACC_BRIDGE, ACC_SYNTHETIC
    Code:
      stack=2, locals=2, args_size=2
         0: aload_0
         1: aload_1
         2: invokevirtual #416                // Method concat:(Lscala/collection/IterableOnce;)Lscala/collection/immutable/OldHashSet;
         5: areturn
      LineNumberTable:
        line 35: 0
      LocalVariableTable:
        Start  Length  Slot  Name   Signature
            0       6     0  this   Lscala/collection/immutable/OldHashSet;
            0       6     1  that   Lscala/collection/IterableOnce;
    MethodParameters:
      Name                           Flags
      that                           final

  public scala.collection.immutable.SetOps excl(java.lang.Object);
    descriptor: (Ljava/lang/Object;)Lscala/collection/immutable/SetOps;
    flags: (0x1041) ACC_PUBLIC, ACC_BRIDGE, ACC_SYNTHETIC
    Code:
      stack=2, locals=2, args_size=2
         0: aload_0
         1: aload_1
         2: invokevirtual #418                // Method excl:(Ljava/lang/Object;)Lscala/collection/immutable/OldHashSet;
         5: areturn
      LineNumberTable:
        line 35: 0
      LocalVariableTable:
        Start  Length  Slot  Name   Signature
            0       6     0  this   Lscala/collection/immutable/OldHashSet;
            0       6     1  elem   Ljava/lang/Object;
    MethodParameters:
      Name                           Flags
      elem                           final

  public scala.collection.immutable.SetOps incl(java.lang.Object);
    descriptor: (Ljava/lang/Object;)Lscala/collection/immutable/SetOps;
    flags: (0x1041) ACC_PUBLIC, ACC_BRIDGE, ACC_SYNTHETIC
    Code:
      stack=2, locals=2, args_size=2
         0: aload_0
         1: aload_1
         2: invokevirtual #420                // Method incl:(Ljava/lang/Object;)Lscala/collection/immutable/OldHashSet;
         5: areturn
      LineNumberTable:
        line 35: 0
      LocalVariableTable:
        Start  Length  Slot  Name   Signature
            0       6     0  this   Lscala/collection/immutable/OldHashSet;
            0       6     1  elem   Ljava/lang/Object;
    MethodParameters:
      Name                           Flags
      elem                           final

  public scala.collection.IterableFactory iterableFactory();
    descriptor: ()Lscala/collection/IterableFactory;
    flags: (0x1041) ACC_PUBLIC, ACC_BRIDGE, ACC_SYNTHETIC
    Code:
      stack=1, locals=1, args_size=1
         0: aload_0
         1: invokevirtual #423                // Method iterableFactory:()Lscala/collection/immutable/OldHashSet$;
         4: areturn
      LineNumberTable:
        line 35: 0
      LocalVariableTable:
        Start  Length  Slot  Name   Signature
            0       5     0  this   Lscala/collection/immutable/OldHashSet;

  public scala.collection.immutable.OldHashSet();
    descriptor: ()V
    flags: (0x0001) ACC_PUBLIC
    Code:
      stack=1, locals=1, args_size=1
         0: aload_0
         1: invokespecial #427                // Method scala/collection/immutable/AbstractSet."<init>":()V
         4: aload_0
         5: invokestatic  #431                // InterfaceMethod scala/collection/StrictOptimizedIterableOps.$init$:(Lscala/collection/StrictOptimizedIterableOps;)V
         8: return
      LineNumberTable:
        line 36: 0
      LocalVariableTable:
        Start  Length  Slot  Name   Signature
            0       9     0  this   Lscala/collection/immutable/OldHashSet;
}
InnerClasses:
  private static #16= #15 of #2;          // EmptyOldHashSet$=class scala/collection/immutable/OldHashSet$EmptyOldHashSet$ of class scala/collection/immutable/OldHashSet
  public static final #19= #18 of #2;     // HashTrieSet=class scala/collection/immutable/OldHashSet$HashTrieSet of class scala/collection/immutable/OldHashSet
  public static abstract #22= #21 of #2;  // LeafOldHashSet=class scala/collection/immutable/OldHashSet$LeafOldHashSet of class scala/collection/immutable/OldHashSet
  public static final #25= #24 of #2;     // OldHashSet1=class scala/collection/immutable/OldHashSet$OldHashSet1 of class scala/collection/immutable/OldHashSet
  public static final #28= #27 of #2;     // OldHashSetCollision1=class scala/collection/immutable/OldHashSet$OldHashSetCollision1 of class scala/collection/immutable/OldHashSet
Signature: #3                           // <A:Ljava/lang/Object;>Lscala/collection/immutable/AbstractSet<TA;>;Lscala/collection/StrictOptimizedIterableOps<TA;Lscala/collection/immutable/OldHashSet;Lscala/collection/immutable/OldHashSet<TA;>;>;Ljava/io/Serializable;
SourceFile: "OldHashSet.scala"
RuntimeVisibleAnnotations:
  0: #11(#12=s#13)
    scala.reflect.ScalaSignature(
      bytes="\u0006\u0005\u0015Md\u0001CA\u0002\u0003\u000b\t\t#a\u0005\t\u000f\u0005u\u0003\u0001\"\u0001\u0002`!A\u0011\u0011\r\u0001!\n#\n\u0019\u0007C\u0004\u0002|\u0001!\t%! \t\u000f\u0011]\u0007\u0001\"\u0001\u0005Z\"9AQ\u001c\u0001\u0005\u0002\u0011}\u0007b\u0002Cr\u0001\u0011\u0005AQ\u001d\u0005\b\tS\u0004A\u0011\tCv\u0011\u001d!)\u0010\u0001C!\toDq\u0001\"@\u0001\t\u0003\"y\u0010C\u0004\u0006\u0004\u0001!\t%\"\u0002\t\u000f\u0015%\u0001\u0001\"\u0011\u0006\f!9Q\u0011\u0003\u0001\u0005B\u0015M\u0001b\u0002B\u0011\u0001\u0011\u0005Sq\u0003\u0005\b\u0005K\u0001A\u0011IC\f\u0011\u001d\u0011I\u0003\u0001D\t\u000b3A\u0011Ba\u0011\u0001\r#\tI!\"\t\t\u000f\t%\u0006A\"\u0005\u0006*!9!\u0011\u001c\u0001\u0007\u0012\u0015E\u0002b\u0002B\u001d\u0001\u0019EQq\b\u0005\n\u0005{\u0004a\u0011AA\u0003\u000b\u000bBqA!@\u0001\r#)\u0019\u0006C\u0004\u0004\u0010\u00011\t\"\"\u0018\t\u000f\rm\u0001A\"\u0005\u0006h\u001dAQQJA\u0003\u0011\u0003\tyH\u0002\u0005\u0002\u0004\u0005\u0015\u0001\u0012AAA\u0011\u001d\ti&\u0007C\u0001\u0003\u001fCq!!%\u001a\t\u0003\t\u0019\nC\u0004\u0002(f!\t!!+\t\u000f\u0005M\u0016\u0004\"\u0001\u00026\u001e9\u00111Z\r\t\n\u00055gaBAi3!%\u00111\u001b\u0005\b\u0003;zB\u0011AAl\u0011\u001d\tIn\bC\u0001\u00037Dq!a9 \t\u0003\n)\u000fC\u0004\u0002n~!\t%a<\t\u000f\u0005]x\u0004\"\u0011\u0002z\"9!1C\u0010\u0005B\tU\u0001b\u0002B\f?\u0011\u0005#\u0011\u0004\u0005\b\u0005CyB\u0011\tB\u0012\u0011\u001d\u0011)c\bC!\u0005GAqAa\n \t\u0003\ny\u000fC\u0004\u0003*}!\tBa\u000b\t\u000f\ter\u0004\"\u0005\u0003<!I!1I\u0010\u0005\u0012\u0005%!Q\t\u0005\b\u0005S{B\u0011CBW\u0011%\u0011ip\bC\u0001\u0003\u000b\u0019)\fC\u0004\u0003~~!\tb!0\t\u000f\r=q\u0004\"\u0005\u0004J\"911D\u0010\u0005\u0012\rM\u0007b\u0002Bm?\u0011E1Q\u001c\u0005\n\u0007W|\u0012\u0011!C\u0005\u0007[4\u0011B!\u0015\u001a\u0003C\t)Aa\u0015\t\u000f\u0005uC\u0007\"\u0001\u0003^!A!1\u0007\u001b\u0007\u0002e\tyO\u0002\u0005\u0003Je\u0011\u0011Q\u0001B&\u0011-\u0011Ij\u000eBC\u0002\u0013\u0005\u0011da\u000b\t\u0015\r5rG!A!\u0002\u0013\u00199\u0003C\u0006\u00034]\u0012)\u0019!C\u00013\u0005=\bB\u0003B8o\t\u0005\t\u0015!\u0003\u0002r\"9\u0011QL\u001c\u0005\u0002\r=\u0002bBAro\u0011\u0005\u0013Q\u001d\u0005\b\u0003[<D\u0011IAx\u0011\u001d\tIn\u000eC\u0001\u0007oAq!a>8\t\u0003\u001aY\u0004C\u0004\u0003\u0014]\"\tea\u000b\t\u000f\t]q\u0007\"\u0011\u0004H!9!\u0011E\u001c\u0005B\r=\u0003bBB*o\u0011\u000531\u0006\u0005\b\u0005K9D\u0011IB(\u0011\u001d\u00119c\u000eC!\u0003_DqA!\u000b8\t#\u0019)\u0006C\u0005\u0003D]\"\t\"!\u0003\u0004^!9!\u0011V\u001c\u0005\u0012\r\u0015\u0004b\u0002B\u001do\u0011E1Q\u000e\u0005\n\u0005{<D\u0011AA\u0003\u0007gBqA!@8\t#\u0019I\bC\u0004\u0004\u0010]\"\tb!\"\t\u000f\rmq\u0007\"\u0005\u0004\u0010\"9!\u0011\\\u001c\u0005\u0012\ree\u0001\u0003B23\t\t)A!\u001a\t\u0017\tM\u0002K!b\u0001\n\u0003I\u0012q\u001e\u0005\u000b\u0005_\u0002&\u0011!Q\u0001\n\u0005E\bB\u0003B9!\n\u0015\r\u0011\"\u0001\u0003t!Q!1\u0010)\u0003\u0002\u0003\u0006IA!\u001e\t\u000f\u0005u\u0003\u000b\"\u0001\u0003~!9\u00111\u001d)\u0005B\u0005\u0015\bb\u0002B\u0014!\u0012\u0005\u0013q\u001e\u0005\b\u00033\u0004F\u0011\u0001BC\u0011\u001d\t9\u0010\u0015C!\u0005\u0013CqA!\u000bQ\t#\u0011)\nC\u0005\u0003DA#\t\"!\u0003\u0003 \"9!\u0011\u0016)\u0005\u0012\t-\u0006b\u0002BZ!\u0012%!Q\u0017\u0005\b\u0005\u0017\u0004F\u0011\u0002Bg\u0011\u001d\u0011I\u000e\u0015C\t\u00057DqA!\u000fQ\t#\u00119\u0010C\u0005\u0003~B#\t!!\u0002\u0003\u0000\"9!Q )\u0005\u0012\r\u0015\u0001bBB\b!\u0012E1\u0011\u0003\u0005\b\u00077\u0001F\u0011CB\u000f\r!\u0019Y0\u0007\u0002\u0002\n\ru\bB\u0003C\u0004K\n\u0015\r\u0011\"\u0003\u0002p\"QA\u0011B3\u0003\u0002\u0003\u0006I!!=\t\u0019\u0011-QM!b\u0001\n\u0003\tI\u0001\"\u0004\t\u0015\u0011EQM!A!\u0002\u0013!y\u0001\u0003\u0006\u0005\u0014\u0015\u0014)\u0019!C\u0005\u0003_D!\u0002\"\u0006f\u0005\u0003\u0005\u000b\u0011BAy\u0011\u001d\ti&\u001aC\u0001\t/AqAa\nf\t\u0003\ny\u000fC\u0004\u0002d\u0016$\t%!:\t\u000f\u00055X\r\"\u0011\u0002p\"9\u0011\u0011\\3\u0005\u0002\u0011\u0005\u0002bBA|K\u0012\u0005CQ\u0005\u0005\b\u0005S)G\u0011\u0003C\u0019\u0011%\u0011\u0019%\u001aC\t\u0003\u0013!I\u0004C\u0004\u0003*\u0016$\t\u0002\"\u0011\t\u0013\tuX\r\"\u0001\u0002\u0006\u0011%\u0003b\u0002B\u007fK\u0012EA\u0011\u000b\u0005\b\u0007\u001f)G\u0011\u0003C.\u0011\u001d\u0019Y\"\u001aC\t\tKBqA!\u000ff\t#!y\u0007C\u0004\u0003Z\u0016$\t\u0002\"\u001e\t\u000f\u0011\r\u0015\u0004\"\u0003\u0005\u0006\"9A1U\r\u0005\n\u0011\u0015\u0006b\u0002CY3\u0011%A1\u0017\u0005\t\u0005gK\u0002\u0015\"\u0003\u0005D\"A!1Z\r!\n\u0013!9\rC\u0005\u0004lf\t\t\u0011\"\u0003\u0004n\nQq\n\u001c3ICND7+\u001a;\u000b\t\u0005\u001d\u0011\u0011B\u0001\nS6lW\u000f^1cY\u0016TA!a\u0003\u0002\u000e\u0005Q1m\u001c7mK\u000e$\u0018n\u001c8\u000b\u0005\u0005=\u0011!B:dC2\f7\u0001A\u000b\u0005\u0003+\t\u0019cE\u0006\u0001\u0003/\t9$!\u0011\u0002J\u0005=\u0003CBA\r\u00037\ty\"\u0004\u0002\u0002\u0006%!\u0011QDA\u0003\u0005-\t%m\u001d;sC\u000e$8+\u001a;\u0011\t\u0005\u0005\u00121\u0005\u0007\u0001\t\u001d\t)\u0003\u0001b\u0001\u0003O\u0011\u0011!Q\t\u0005\u0003S\t\t\u0004\u0005\u0003\u0002,\u00055RBAA\u0007\u0013\u0011\ty#!\u0004\u0003\u000f9{G\u000f[5oOB!\u00111FA\u001a\u0013\u0011\t)$!\u0004\u0003\u0007\u0005s\u0017\u0010\u0005\u0006\u0002\u001a\u0005e\u0012qDA\u001f\u0003\u007fIA!a\u000f\u0002\u0006\t11+\u001a;PaN\u00042!!\u0007\u0001!\u0015\tI\u0002AA\u0010!)\t\u0019%!\u0012\u0002 \u0005u\u0012qH\u0007\u0003\u0003\u0013IA!a\u0012\u0002\n\tQ2\u000b\u001e:jGR|\u0005\u000f^5nSj,G-\u0013;fe\u0006\u0014G.Z(qgBA\u00111IA&\u0003?\ti$\u0003\u0003\u0002N\u0005%!aF%uKJ\f\'\r\\3GC\u000e$xN]=EK\u001a\fW\u000f\u001c;t!\u0011\t\t&a\u0016\u000f\t\u0005-\u00121K\u0005\u0005\u0003+\ni!A\u0004qC\u000e\\\u0017mZ3\n\t\u0005e\u00131\f\u0002\r\'\u0016\u0014\u0018.\u00197ju\u0006\u0014G.\u001a\u0006\u0005\u0003+\ni!\u0001\u0004=S:LGO\u0010\u000b\u0003\u0003\u007f\t\u0011b\u00197bgNt\u0015-\\3\u0016\u0005\u0005\u0015\u0004\u0003BA4\u0003krA!!\u001b\u0002rA!\u00111NA\u0007\u001b\t\tiG\u0003\u0003\u0002p\u0005E\u0011A\u0002\u001fs_>$h(\u0003\u0003\u0002t\u00055\u0011A\u0002)sK\u0012,g-\u0003\u0003\u0002x\u0005e$AB*ue&twM\u0003\u0003\u0002t\u00055\u0011aD5uKJ\f\'\r\\3GC\u000e$xN]=\u0016\u0005\u0005}\u0004cAA\r3M)\u0011$a!\u0002\nB!\u00111FAC\u0013\u0011\t9)!\u0004\u0003\r\u0005s\u0017PU3g!\u0019\t\u0019%a#\u0002>%!\u0011QRA\u0005\u0005=IE/\u001a:bE2,g)Y2u_JLHCAA@\u0003\u00111\'o\\7\u0016\t\u0005U\u00151\u0014\u000b\u0005\u0003/\u000bi\nE\u0003\u0002\u001a\u0001\tI\n\u0005\u0003\u0002\"\u0005mEaBA\u00137\t\u0007\u0011q\u0005\u0005\b\u0003?[\u0002\u0019AAQ\u0003\tIG\u000f\u0005\u0004\u0002D\u0005\r\u0016\u0011T\u0005\u0005\u0003K\u000bIA\u0001\u0007Ji\u0016\u0014\u0018M\u00197f\u001f:\u001cW-A\u0003f[B$\u00180\u0006\u0003\u0002,\u0006EVCAAW!\u0015\tI\u0002AAX!\u0011\t\t#!-\u0005\u000f\u0005\u0015BD1\u0001\u0002(\u0005Qa.Z<Ck&dG-\u001a:\u0016\t\u0005]\u0016qY\u000b\u0003\u0003s\u0003\u0002\"a/\u0002B\u0006\u0015\u0017\u0011Z\u0007\u0003\u0003{SA!a0\u0002\n\u00059Q.\u001e;bE2,\u0017\u0002BAb\u0003{\u0013qAQ;jY\u0012,\'\u000f\u0005\u0003\u0002\"\u0005\u001dGaBA\u0013;\t\u0007\u0011q\u0005\t\u0006\u00033\u0001\u0011QY\u0001\u0010\u000b6\u0004H/_(mI\"\u000b7\u000f[*fiB\u0019\u0011qZ\u0010\u000e\u0003e\u0011q\"R7qif|E\u000e\u001a%bg\"\u001cV\r^\n\u0004?\u0005U\u0007#BA\r\u0001\u0005EBCAAg\u0003!IG/\u001a:bi>\u0014XCAAo!\u0019\t\u0019%a8\u00022%!\u0011\u0011]A\u0005\u0005!IE/\u001a:bi>\u0014\u0018aB5t\u000b6\u0004H/_\u000b\u0003\u0003O\u0004B!a\u000b\u0002j&!\u00111^A\u0007\u0005\u001d\u0011un\u001c7fC:\f\u0011b\u001b8po:\u001c\u0016N_3\u0016\u0005\u0005E\b\u0003BA\u0016\u0003gLA!!>\u0002\u000e\t\u0019\u0011J\u001c;\u0002\u000f\u0019|\'/Z1dQV!\u00111 B\b)\u0011\tiPa\u0001\u0011\t\u0005-\u0012q`\u0005\u0005\u0005\u0003\tiA\u0001\u0003V]&$\bb\u0002B\u0003I\u0001\u0007!qA\u0001\u0002MBA\u00111\u0006B\u0005\u0003c\u0011i!\u0003\u0003\u0003\f\u00055!!\u0003$v]\u000e$\u0018n\u001c82!\u0011\t\tCa\u0004\u0005\u000f\tEAE1\u0001\u0002(\t\tQ+\u0001\u0003iK\u0006$WCAA\u0019\u0003)AW-\u00193PaRLwN\\\u000b\u0003\u00057qA!a\u000b\u0003\u001e%!!qDA\u0007\u0003\u0011quN\\3\u0002\tQ\f\u0017\u000e\\\u000b\u0003\u0003+\fA!\u001b8ji\u0006!1/\u001b>f\u0003\u00119W\r\u001e\u0019\u0015\u0011\u0005\u001d(Q\u0006B\u0019\u0005kAqAa\f+\u0001\u0004\t\t$\u0001\u0003fY\u0016l\u0007b\u0002B\u001aU\u0001\u0007\u0011\u0011_\u0001\u0005Q\u0006\u001c\b\u000eC\u0004\u00038)\u0002\r!!=\u0002\u000b1,g/\u001a7\u0002\u0013M,(m]3u\u001f\u001a\u0004DCBAt\u0005{\u0011\t\u0005C\u0004\u0003@-\u0002\r!!6\u0002\tQD\u0017\r\u001e\u0005\b\u0005oY\u0003\u0019AAy\u0003!)\b\u000fZ1uK\u0012\u0004D\u0003\u0003B$\u0007O\u001bIka+\u0011\u000b\u0005=w\'!\r\u0003\u0017=cG\rS1tQN+G/M\u000b\u0005\u0005\u001b\u001aIcE\u00028\u0005\u001f\u0002R!a45\u0007O\u0011a\u0002T3bM>cG\rS1tQN+G/\u0006\u0003\u0003V\tm3c\u0001\u001b\u0003XA)\u0011\u0011\u0004\u0001\u0003ZA!\u0011\u0011\u0005B.\t\u001d\t)\u0003\u000eb\u0001\u0003O!\"Aa\u0018\u0011\u000b\u0005=GG!\u0017*\u0007Q:\u0004K\u0001\u000bPY\u0012D\u0015m\u001d5TKR\u001cu\u000e\u001c7jg&|g.M\u000b\u0005\u0005O\u0012igE\u0002Q\u0005S\u0002R!a45\u0005W\u0002B!!\t\u0003n\u00119\u0011Q\u0005)C\u0002\u0005\u001d\u0012!\u00025bg\"\u0004\u0013AA6t+\t\u0011)\b\u0005\u0004\u0002\u001a\t]$1N\u0005\u0005\u0005s\n)AA\u0004MSN$8+\u001a;\u0002\u0007-\u001c\b\u0005\u0006\u0004\u0003\u0000\t\u0005%1\u0011\t\u0006\u0003\u001f\u0004&1\u000e\u0005\b\u0005g)\u0006\u0019AAy\u0011\u001d\u0011\t(\u0016a\u0001\u0005k*\"Aa\"\u0011\r\u0005\r\u0013q\u001cB6+\u0011\u0011YIa%\u0015\t\u0005u(Q\u0012\u0005\b\u0005\u000bI\u0006\u0019\u0001BH!!\tYC!\u0003\u0003l\tE\u0005\u0003BA\u0011\u0005\'#qA!\u0005Z\u0005\u0004\t9\u0003\u0006\u0005\u0002h\n]%1\u0014BO\u0011\u001d\u0011IJ\u0017a\u0001\u0005W\n1a[3z\u0011\u001d\u0011\u0019D\u0017a\u0001\u0003cDqAa\u000e[\u0001\u0004\t\t\u0010\u0006\u0005\u0003\"\n\r&Q\u0015BT!\u0015\tI\u0002\u0001B6\u0011\u001d\u0011Ij\u0017a\u0001\u0005WBqAa\r\\\u0001\u0004\t\t\u0010C\u0004\u00038m\u0003\r!!=\u0002\u0011I,Wn\u001c<fIB\"\u0002B!)\u0003.\n=&\u0011\u0017\u0005\b\u00053c\u0006\u0019\u0001B6\u0011\u001d\u0011\u0019\u0004\u0018a\u0001\u0003cDqAa\u000e]\u0001\u0004\t\t0A\u0006xe&$Xm\u00142kK\u000e$H\u0003BA\u007f\u0005oCqA!/^\u0001\u0004\u0011Y,A\u0002pkR\u0004BA!0\u0003H6\u0011!q\u0018\u0006\u0005\u0005\u0003\u0014\u0019-\u0001\u0002j_*\u0011!QY\u0001\u0005U\u00064\u0018-\u0003\u0003\u0003J\n}&AE(cU\u0016\u001cGoT;uaV$8\u000b\u001e:fC6\f!B]3bI>\u0013\'.Z2u)\u0011\tiPa4\t\u000f\tEg\f1\u0001\u0003T\u0006\u0011\u0011N\u001c\t\u0005\u0005{\u0013).\u0003\u0003\u0003X\n}&!E(cU\u0016\u001cG/\u00138qkR\u001cFO]3b[\u00069a-\u001b7uKJ\u0004D\u0003\u0004BQ\u0005;\u0014\u0019Oa:\u0003j\nM\bb\u0002Bp?\u0002\u0007!\u0011]\u0001\u0002aBA\u00111\u0006B\u0005\u0005W\n9\u000fC\u0004\u0003f~\u0003\r!a:\u0002\r9,w-\u0019;f\u0011\u001d\u00119d\u0018a\u0001\u0003cDqAa;`\u0001\u0004\u0011i/\u0001\u0004ck\u001a4WM\u001d\t\u0007\u0003W\u0011yO!)\n\t\tE\u0018Q\u0002\u0002\u0006\u0003J\u0014\u0018-\u001f\u0005\b\u0005k|\u0006\u0019AAy\u0003\u001dygMZ:fiB\"b!a:\u0003z\nm\bb\u0002B A\u0002\u0007!\u0011\u0015\u0005\b\u0005o\u0001\u0007\u0019AAy\u0003\u0019)h.[8oaQ1!\u0011UB\u0001\u0007\u0007AqAa\u0010b\u0001\u0004\u0011I\u0007C\u0004\u00038\u0005\u0004\r!!=\u0015\u0015\t\u00056qAB\u0005\u0007\u0017\u0019i\u0001C\u0004\u0003@\t\u0004\rA!)\t\u000f\t]\"\r1\u0001\u0002r\"9!1\u001e2A\u0002\t5\bb\u0002B{E\u0002\u0007\u0011\u0011_\u0001\u000bS:$XM]:fGR\u0004DC\u0003BQ\u0007\'\u0019)ba\u0006\u0004\u001a!9!qH2A\u0002\t\u0005\u0006b\u0002B\u001cG\u0002\u0007\u0011\u0011\u001f\u0005\b\u0005W\u001c\u0007\u0019\u0001Bw\u0011\u001d\u0011)p\u0019a\u0001\u0003c\fQ\u0001Z5gMB\"\"B!)\u0004 \r\u000521EB\u0013\u0011\u001d\u0011y\u0004\u001aa\u0001\u0005CCqAa\u000ee\u0001\u0004\t\t\u0010C\u0004\u0003l\u0012\u0004\rA!<\t\u000f\tUH\r1\u0001\u0002rB!\u0011\u0011EB\u0015\t\u001d\t)c\u000eb\u0001\u0003O)\"aa\n\u0002\t-,\u0017\u0010\t\u000b\u0007\u0007c\u0019\u0019d!\u000e\u0011\u000b\u0005=wga\n\t\u000f\teE\b1\u0001\u0004(!9!1\u0007\u001fA\u0002\u0005EXCAB\u001d!\u0019\t\u0019%a8\u0004(U!1QHB#)\u0011\tipa\u0010\t\u000f\t\u0015\u0001\t1\u0001\u0004BAA\u00111\u0006B\u0005\u0007O\u0019\u0019\u0005\u0005\u0003\u0002\"\r\u0015Ca\u0002B\t\u0001\n\u0007\u0011qE\u000b\u0003\u0007\u0013\u0002b!a\u000b\u0004L\r\u001d\u0012\u0002BB\'\u0003\u001b\u0011AaU8nKV\u00111\u0011\u000b\t\u0006\u00033\u00011qE\u0001\u0005Y\u0006\u001cH\u000f\u0006\u0005\u0002h\u000e]3\u0011LB.\u0011\u001d\u0011Ij\u0012a\u0001\u0007OAqAa\rH\u0001\u0004\t\t\u0010C\u0004\u00038\u001d\u0003\r!!=\u0015\u0011\rE3qLB1\u0007GBqA!\'I\u0001\u0004\u00199\u0003C\u0004\u00034!\u0003\r!!=\t\u000f\t]\u0002\n1\u0001\u0002rRA1\u0011KB4\u0007S\u001aY\u0007C\u0004\u0003\u001a&\u0003\raa\n\t\u000f\tM\u0012\n1\u0001\u0002r\"9!qG%A\u0002\u0005EHCBAt\u0007_\u001a\t\bC\u0004\u0003@)\u0003\ra!\u0015\t\u000f\t]\"\n1\u0001\u0002rR11\u0011KB;\u0007oBqAa\u0010L\u0001\u0004\u0011y\u0005C\u0004\u00038-\u0003\r!!=\u0015\u0015\rE31PB?\u0007\u007f\u001a\u0019\tC\u0004\u0003@1\u0003\ra!\u0015\t\u000f\t]B\n1\u0001\u0002r\"9!1\u001e\'A\u0002\r\u0005\u0005CBA\u0016\u0005_\u001c\t\u0006C\u0004\u0003v2\u0003\r!!=\u0015\u0015\rE3qQBE\u0007\u0017\u001bi\tC\u0004\u0003@5\u0003\ra!\u0015\t\u000f\t]R\n1\u0001\u0002r\"9!1^\'A\u0002\r\u0005\u0005b\u0002B{\u001b\u0002\u0007\u0011\u0011\u001f\u000b\u000b\u0007#\u001a\tja%\u0004\u0016\u000e]\u0005b\u0002B \u001d\u0002\u00071\u0011\u000b\u0005\b\u0005oq\u0005\u0019AAy\u0011\u001d\u0011YO\u0014a\u0001\u0007\u0003CqA!>O\u0001\u0004\t\t\u0010\u0006\u0007\u0004R\rm5qTBQ\u0007G\u001b)\u000bC\u0004\u0003`>\u0003\ra!(\u0011\u0011\u0005-\"\u0011BB\u0014\u0003ODqA!:P\u0001\u0004\t9\u000fC\u0004\u00038=\u0003\r!!=\t\u000f\t-x\n1\u0001\u0004\u0002\"9!Q_(A\u0002\u0005E\bb\u0002B\u0018Y\u0001\u0007\u0011\u0011\u0007\u0005\b\u0005ga\u0003\u0019AAy\u0011\u001d\u00119\u0004\fa\u0001\u0003c$\u0002\"!4\u00040\u000eE61\u0017\u0005\b\u00053k\u0003\u0019AA\u0019\u0011\u001d\u0011\u0019$\fa\u0001\u0003cDqAa\u000e.\u0001\u0004\t\t\u0010\u0006\u0004\u0002V\u000e]61\u0018\u0005\b\u0005\u007fq\u0003\u0019AB]!\u0015\ty\rNA\u0019\u0011\u001d\u00119D\fa\u0001\u0003c$\"\"!6\u0004@\u000e\u000571YBd\u0011\u001d\u0011yd\fa\u0001\u0003+DqAa\u000e0\u0001\u0004\t\t\u0010C\u0004\u0003l>\u0002\ra!2\u0011\r\u0005-\"q^Ak\u0011\u001d\u0011)p\fa\u0001\u0003c$\"\"!6\u0004L\u000e57qZBi\u0011\u001d\u0011y\u0004\ra\u0001\u0003+DqAa\u000e1\u0001\u0004\t\t\u0010C\u0004\u0003lB\u0002\ra!2\t\u000f\tU\b\u00071\u0001\u0002rRQ\u0011Q[Bk\u0007/\u001cIna7\t\u000f\t}\u0012\u00071\u0001\u0002V\"9!qG\u0019A\u0002\u0005E\bb\u0002Bvc\u0001\u00071Q\u0019\u0005\b\u0005k\f\u0004\u0019AAy)1\t)na8\u0004d\u000e\u00158q]Bu\u0011\u001d\u0011yN\ra\u0001\u0007C\u0004\u0002\"a\u000b\u0003\n\u0005E\u0012q\u001d\u0005\b\u0005K\u0014\u0004\u0019AAt\u0011\u001d\u00119D\ra\u0001\u0003cDqAa;3\u0001\u0004\u0019)\rC\u0004\u0003vJ\u0002\r!!=\u0002\u0019]\u0014\u0018\u000e^3SKBd\u0017mY3\u0015\u0005\r=\b\u0003BBy\u0007ol!aa=\u000b\t\rU(1Y\u0001\u0005Y\u0006tw-\u0003\u0003\u0004z\u000eM(AB(cU\u0016\u001cGOA\u0006ICNDGK]5f\'\u0016$X\u0003BB\u0000\t\u000b\u00192!\u001aC\u0001!\u0015\tI\u0002\u0001C\u0002!\u0011\t\t\u0003\"\u0002\u0005\u000f\u0005\u0015RM1\u0001\u0002(\u00051!-\u001b;nCB\fqAY5u[\u0006\u0004\b%A\u0003fY\u0016l7/\u0006\u0002\u0005\u0010A1\u00111\u0006Bx\t\u0003\ta!\u001a7f[N\u0004\u0013!B:ju\u0016\u0004\u0014AB:ju\u0016\u0004\u0004\u0005\u0006\u0005\u0005\u001a\u0011mAQ\u0004C\u0010!\u0015\ty-\u001aC\u0002\u0011\u001d!9\u0001\u001ca\u0001\u0003cDq\u0001b\u0003m\u0001\u0004!y\u0001C\u0004\u0005\u00141\u0004\r!!=\u0016\u0005\u0011\r\u0002CBA\"\u0003?$\u0019!\u0006\u0003\u0005(\u0011=B\u0003BA\u007f\tSAqA!\u0002r\u0001\u0004!Y\u0003\u0005\u0005\u0002,\t%A1\u0001C\u0017!\u0011\t\t\u0003b\f\u0005\u000f\tE\u0011O1\u0001\u0002(QA\u0011q\u001dC\u001a\tk!9\u0004C\u0004\u0003\u001aJ\u0004\r\u0001b\u0001\t\u000f\tM\"\u000f1\u0001\u0002r\"9!q\u0007:A\u0002\u0005EH\u0003\u0003C\u0001\tw!i\u0004b\u0010\t\u000f\te5\u000f1\u0001\u0005\u0004!9!1G:A\u0002\u0005E\bb\u0002B\u001cg\u0002\u0007\u0011\u0011\u001f\u000b\t\t\u0003!\u0019\u0005\"\u0012\u0005H!9!\u0011\u0014;A\u0002\u0011\r\u0001b\u0002B\u001ai\u0002\u0007\u0011\u0011\u001f\u0005\b\u0005o!\b\u0019AAy)\u0019!\t\u0001b\u0013\u0005P!9!qH;A\u0002\u00115\u0003#BAhi\u0011\r\u0001b\u0002B\u001ck\u0002\u0007\u0011\u0011\u001f\u000b\u000b\t\u0003!\u0019\u0006\"\u0016\u0005X\u0011e\u0003b\u0002B m\u0002\u0007A\u0011\u0001\u0005\b\u0005o1\b\u0019AAy\u0011\u001d\u0011YO\u001ea\u0001\t\u001fAqA!>w\u0001\u0004\t\t\u0010\u0006\u0006\u0005\u0002\u0011uCq\fC1\tGBqAa\u0010x\u0001\u0004!\t\u0001C\u0004\u00038]\u0004\r!!=\t\u000f\t-x\u000f1\u0001\u0005\u0010!9!Q_<A\u0002\u0005EHC\u0003C\u0001\tO\"I\u0007b\u001b\u0005n!9!q\b=A\u0002\u0011\u0005\u0001b\u0002B\u001cq\u0002\u0007\u0011\u0011\u001f\u0005\b\u0005WD\b\u0019\u0001C\b\u0011\u001d\u0011)\u0010\u001fa\u0001\u0003c$b!a:\u0005r\u0011M\u0004b\u0002B s\u0002\u0007A\u0011\u0001\u0005\b\u0005oI\b\u0019AAy)1!\t\u0001b\u001e\u0005|\u0011uDq\u0010CA\u0011\u001d\u0011yN\u001fa\u0001\ts\u0002\u0002\"a\u000b\u0003\n\u0011\r\u0011q\u001d\u0005\b\u0005KT\b\u0019AAt\u0011\u001d\u00119D\u001fa\u0001\u0003cDqAa;{\u0001\u0004!y\u0001C\u0004\u0003vj\u0004\r!!=\u0002\u001f5\f7.\u001a%bg\"$&/[3TKR,B\u0001b\"\u0005\u000eRaA\u0011\u0012CH\t\'#I\n\"(\u0005\"B)\u0011qZ3\u0005\fB!\u0011\u0011\u0005CG\t\u001d\t)c\u001fb\u0001\u0003OAq\u0001\"%|\u0001\u0004\t\t0A\u0003iCND\u0007\u0007C\u0004\u0005\u0016n\u0004\r\u0001b&\u0002\u000b\u0015dW-\u001c\u0019\u0011\u000b\u0005e\u0001\u0001b#\t\u000f\u0011m5\u00101\u0001\u0002r\u0006)\u0001.Y:ic!9AqT>A\u0002\u0011]\u0015!B3mK6\f\u0004b\u0002B\u001cw\u0002\u0007\u0011\u0011_\u0001\u000bEV4g-\u001a:TSj,G\u0003BAy\tOCqAa\n}\u0001\u0004\t\t\u0010K\u0002}\tW\u0003B!a\u000b\u0005.&!AqVA\u0007\u0005\u0019Ig\u000e\\5oK\u0006Ya.\u001e7m)>,U\u000e\u001d;z+\u0011!)\fb/\u0015\t\u0011]FQ\u0018\t\u0006\u00033\u0001A\u0011\u0018\t\u0005\u0003C!Y\fB\u0004\u0002&u\u0014\r!a\n\t\u000f\u0011}V\u00101\u0001\u00058\u0006\t1\u000fK\u0002~\tW#B!!@\u0005F\"9!\u0011\u0018@A\u0002\tmF\u0003BA\u007f\t\u0013DqA!5\u0000\u0001\u0004\u0011\u0019\u000eK\u0004\u001a\t\u001b$\u0019\u000e\"6\u0011\t\u0005-BqZ\u0005\u0005\t#\fiA\u0001\tTKJL\u0017\r\u001c,feNLwN\\+J\t\u0006)a/\u00197vKz\t1!\u0001\u0005d_:$\u0018-\u001b8t)\u0011\t9\u000fb7\t\u000f\t=B\u00011\u0001\u0002 \u0005!\u0011N\\2m)\u0011\ty\u0004\"9\t\u000f\t=R\u00011\u0001\u0002 \u0005!Q\r_2m)\u0011\ty\u0004b:\t\u000f\t=b\u00011\u0001\u0002 \u0005A1/\u001e2tKR|e\r\u0006\u0003\u0002h\u00125\bb\u0002B \u000f\u0001\u0007Aq\u001e\t\u0007\u0003\u0007\"\t0a\b\n\t\u0011M\u0018\u0011\u0002\u0002\u0004\'\u0016$\u0018AB2p]\u000e\fG\u000f\u0006\u0003\u0002@\u0011e\bb\u0002B \u0011\u0001\u0007A1 \t\u0007\u0003\u0007\n\u0019+a\b\u0002\u0013%tG/\u001a:tK\u000e$H\u0003BA \u000b\u0003AqAa\u0010\n\u0001\u0004!y/\u0001\u0003eS\u001a4G\u0003BA \u000b\u000fAqAa\u0010\u000b\u0001\u0004!y/\u0001\u0004gS2$XM\u001d\u000b\u0005\u0003\u007f)i\u0001C\u0004\u0003`.\u0001\r!b\u0004\u0011\u0011\u0005-\"\u0011BA\u0010\u0003O\f\u0011BZ5mi\u0016\u0014hj\u001c;\u0015\t\u0005}RQ\u0003\u0005\b\u0005?d\u0001\u0019AC\b+\t\ty\u0004\u0006\u0005\u0002h\u0016mQQDC\u0010\u0011\u001d\u0011Ij\u0004a\u0001\u0003?AqAa\r\u0010\u0001\u0004\t\t\u0010C\u0004\u00038=\u0001\r!!=\u0015\u0011\u0005}R1EC\u0013\u000bOAqA!\'\u0011\u0001\u0004\ty\u0002C\u0004\u00034A\u0001\r!!=\t\u000f\t]\u0002\u00031\u0001\u0002rRA\u0011qHC\u0016\u000b[)y\u0003C\u0004\u0003\u001aF\u0001\r!a\b\t\u000f\tM\u0012\u00031\u0001\u0002r\"9!qG\tA\u0002\u0005EH\u0003DA \u000bg))$b\u000e\u0006:\u0015u\u0002b\u0002Bp%\u0001\u0007Qq\u0002\u0005\b\u0005K\u0014\u0002\u0019AAt\u0011\u001d\u00119D\u0005a\u0001\u0003cDqAa;\u0013\u0001\u0004)Y\u0004\u0005\u0004\u0002,\t=\u0018q\b\u0005\b\u0005k\u0014\u0002\u0019AAy)\u0019\t9/\"\u0011\u0006D!9!qH\nA\u0002\u0005}\u0002b\u0002B\u001c\'\u0001\u0007\u0011\u0011\u001f\u000b\u0007\u0003\u007f)9%\"\u0015\t\u000f\t}B\u00031\u0001\u0006JA)Q1\n\u001b\u0002 9\u0019\u0011\u0011\u0004\r\u0002\u0015=cG\rS1tQN+G\u000fK\u0004\u0019\t\u001b$\u0019\u000e\"6\t\u000f\t]B\u00031\u0001\u0002rRQ\u0011qHC+\u000b/*I&b\u0017\t\u000f\t}R\u00031\u0001\u0002@!9!qG\u000bA\u0002\u0005E\bb\u0002Bv+\u0001\u0007Q1\b\u0005\b\u0005k,\u0002\u0019AAy))\ty$b\u0018\u0006b\u0015\rTQ\r\u0005\b\u0005\u007f1\u0002\u0019AA \u0011\u001d\u00119D\u0006a\u0001\u0003cDqAa;\u0017\u0001\u0004)Y\u0004C\u0004\u0003vZ\u0001\r!!=\u0015\u0015\u0005}R\u0011NC6\u000b[*y\u0007C\u0004\u0003@]\u0001\r!a\u0010\t\u000f\t]r\u00031\u0001\u0002r\"9!1^\fA\u0002\u0015m\u0002b\u0002B{/\u0001\u0007\u0011\u0011_\u0015\u0005\u0001})G\u0007"
    )
  ScalaInlineInfo: length = 0x11C (unknown attribute)
   01 00 00 38 01 A8 01 A9 00 00 FF 01 00 00 00 B2
   00 B3 00 01 34 01 9E 00 01 34 00 29 00 01 05 01
   06 00 01 65 01 98 00 01 65 01 4B 00 01 65 01 9B
   00 01 66 01 3F 00 00 FB 00 F6 00 01 1C 01 16 00
   01 1C 01 7E 00 01 6F 00 93 00 01 6F 01 70 00 01
   72 01 73 00 00 E3 00 E4 00 01 76 00 93 00 01 76
   01 70 00 00 A1 00 93 00 00 C1 00 93 00 01 11 01
   12 00 01 15 01 16 00 01 15 01 7E 00 00 6E 00 D6
   00 00 6E 01 78 00 01 4A 01 98 00 01 4A 01 4B 00
   01 5E 01 3F 00 01 03 01 A5 00 01 03 01 04 00 00
   92 00 93 00 00 76 00 77 00 00 EC 00 77 00 01 1D
   01 19 00 00 DB 00 DC 00 00 80 00 77 00 00 BA 00
   BB 05 00 AA 00 AB 05 00 A5 00 99 05 00 C6 00 99
   05 00 98 00 99 05 00 D0 00 AB 05 01 24 01 25 00
   01 27 01 28 00 01 77 00 D6 00 01 77 01 78 00 00
   F5 00 F6 00 00 F1 00 93 00 01 3E 01 8D 00 01 3E
   01 3F 00 00 84 00 77 00 00 8A 00 8B 00 01 18 01
   19 00 00 CA 00 CB 00 00 D5 00 D6 00
  ScalaSig: length = 0x3 (unknown attribute)
   05 02 00
