Classfile /Users/mw/Projects/slang-braindump/.jar/jar8/assemble/slang-braindump/assemble/content/scala/collection/immutable/Range$$anon$3.class
  Last modified May 29, 2022; size 1587 bytes
  SHA-256 checksum e12c55cadb9e08aab5e8ec2e9e44d63749f7dd7f1fd7f0124c323e94d57dd517
  Compiled from "Range.scala"
public final class scala.collection.immutable.Range$$anon$3 extends scala.collection.AbstractIterator<scala.collection.immutable.Range>
  minor version: 0
  major version: 52
  flags: (0x0031) ACC_PUBLIC, ACC_FINAL, ACC_SUPER
  this_class: #2                          // scala/collection/immutable/Range$$anon$3
  super_class: #5                         // scala/collection/AbstractIterator
  interfaces: 0, fields: 3, methods: 4, attributes: 6
Constant pool:
   #1 = Utf8               scala/collection/immutable/Range$$anon$3
   #2 = Class              #1             // scala/collection/immutable/Range$$anon$3
   #3 = Utf8               Lscala/collection/AbstractIterator<Lscala/collection/immutable/Range;>;
   #4 = Utf8               scala/collection/AbstractIterator
   #5 = Class              #4             // scala/collection/AbstractIterator
   #6 = Utf8               Range.scala
   #7 = Utf8               scala/collection/immutable/Range
   #8 = Class              #7             // scala/collection/immutable/Range
   #9 = Utf8               grouped
  #10 = Utf8               (I)Lscala/collection/Iterator;
  #11 = NameAndType        #9:#10         // grouped:(I)Lscala/collection/Iterator;
  #12 = Utf8               i
  #13 = Utf8               I
  #14 = Utf8               $outer
  #15 = Utf8               Lscala/collection/immutable/Range;
  #16 = Utf8               s$1
  #17 = Utf8               hasNext
  #18 = Utf8               ()Z
  #19 = NameAndType        #14:#15        // $outer:Lscala/collection/immutable/Range;
  #20 = Fieldref           #2.#19         // scala/collection/immutable/Range$$anon$3.$outer:Lscala/collection/immutable/Range;
  #21 = Utf8               length
  #22 = Utf8               ()I
  #23 = NameAndType        #21:#22        // length:()I
  #24 = Methodref          #8.#23         // scala/collection/immutable/Range.length:()I
  #25 = NameAndType        #12:#13        // i:I
  #26 = Fieldref           #2.#25         // scala/collection/immutable/Range$$anon$3.i:I
  #27 = Utf8               this
  #28 = Utf8               Lscala/collection/immutable/Range$$anon$3;
  #29 = Utf8               next
  #30 = Utf8               ()Lscala/collection/immutable/Range;
  #31 = NameAndType        #17:#18        // hasNext:()Z
  #32 = Methodref          #2.#31         // scala/collection/immutable/Range$$anon$3.hasNext:()Z
  #33 = NameAndType        #16:#13        // s$1:I
  #34 = Fieldref           #2.#33         // scala/collection/immutable/Range$$anon$3.s$1:I
  #35 = Utf8               slice
  #36 = Utf8               (II)Lscala/collection/immutable/Range;
  #37 = NameAndType        #35:#36        // slice:(II)Lscala/collection/immutable/Range;
  #38 = Methodref          #8.#37         // scala/collection/immutable/Range.slice:(II)Lscala/collection/immutable/Range;
  #39 = Utf8               scala/collection/Iterator$
  #40 = Class              #39            // scala/collection/Iterator$
  #41 = Utf8               MODULE$
  #42 = Utf8               Lscala/collection/Iterator$;
  #43 = NameAndType        #41:#42        // MODULE$:Lscala/collection/Iterator$;
  #44 = Fieldref           #40.#43        // scala/collection/Iterator$.MODULE$:Lscala/collection/Iterator$;
  #45 = Utf8               scala$collection$Iterator$$_empty
  #46 = Utf8               Lscala/collection/Iterator;
  #47 = NameAndType        #45:#46        // scala$collection$Iterator$$_empty:Lscala/collection/Iterator;
  #48 = Fieldref           #40.#47        // scala/collection/Iterator$.scala$collection$Iterator$$_empty:Lscala/collection/Iterator;
  #49 = Utf8               scala/collection/Iterator
  #50 = Class              #49            // scala/collection/Iterator
  #51 = Utf8               ()Ljava/lang/Object;
  #52 = NameAndType        #29:#51        // next:()Ljava/lang/Object;
  #53 = InterfaceMethodref #50.#52        // scala/collection/Iterator.next:()Ljava/lang/Object;
  #54 = Utf8               x
  #55 = NameAndType        #29:#30        // next:()Lscala/collection/immutable/Range;
  #56 = Methodref          #2.#55         // scala/collection/immutable/Range$$anon$3.next:()Lscala/collection/immutable/Range;
  #57 = Utf8               <init>
  #58 = Utf8               (Lscala/collection/immutable/Range;I)V
  #59 = Utf8               ()V
  #60 = NameAndType        #57:#59        // "<init>":()V
  #61 = Methodref          #5.#60         // scala/collection/AbstractIterator."<init>":()V
  #62 = Utf8               Code
  #63 = Utf8               StackMapTable
  #64 = Utf8               LineNumberTable
  #65 = Utf8               LocalVariableTable
  #66 = Utf8               MethodParameters
  #67 = Utf8               InnerClasses
  #68 = Utf8               EnclosingMethod
  #69 = Utf8               Signature
  #70 = Utf8               SourceFile
  #71 = Utf8               ScalaInlineInfo
  #72 = Utf8               Scala
{
  private int i;
    descriptor: I
    flags: (0x0002) ACC_PRIVATE

  private final scala.collection.immutable.Range $outer;
    descriptor: Lscala/collection/immutable/Range;
    flags: (0x1012) ACC_PRIVATE, ACC_FINAL, ACC_SYNTHETIC

  private final int s$1;
    descriptor: I
    flags: (0x0012) ACC_PRIVATE, ACC_FINAL

  public boolean hasNext();
    descriptor: ()Z
    flags: (0x0001) ACC_PUBLIC
    Code:
      stack=2, locals=1, args_size=1
         0: aload_0
         1: getfield      #20                 // Field $outer:Lscala/collection/immutable/Range;
         4: invokevirtual #24                 // Method scala/collection/immutable/Range.length:()I
         7: aload_0
         8: getfield      #26                 // Field i:I
        11: if_icmple     16
        14: iconst_1
        15: ireturn
        16: iconst_0
        17: ireturn
      StackMapTable: number_of_entries = 1
        frame_type = 16 /* same */
      LineNumberTable:
        line 498: 0
      LocalVariableTable:
        Start  Length  Slot  Name   Signature
            0      18     0  this   Lscala/collection/immutable/Range$$anon$3;

  public scala.collection.immutable.Range next();
    descriptor: ()Lscala/collection/immutable/Range;
    flags: (0x0001) ACC_PUBLIC
    Code:
      stack=4, locals=2, args_size=1
         0: aload_0
         1: invokevirtual #32                 // Method hasNext:()Z
         4: ifeq          43
         7: aload_0
         8: getfield      #20                 // Field $outer:Lscala/collection/immutable/Range;
        11: aload_0
        12: getfield      #26                 // Field i:I
        15: aload_0
        16: getfield      #26                 // Field i:I
        19: aload_0
        20: getfield      #34                 // Field s$1:I
        23: iadd
        24: invokevirtual #38                 // Method scala/collection/immutable/Range.slice:(II)Lscala/collection/immutable/Range;
        27: astore_1
        28: aload_0
        29: aload_0
        30: getfield      #26                 // Field i:I
        33: aload_0
        34: getfield      #34                 // Field s$1:I
        37: iadd
        38: putfield      #26                 // Field i:I
        41: aload_1
        42: areturn
        43: getstatic     #44                 // Field scala/collection/Iterator$.MODULE$:Lscala/collection/Iterator$;
        46: pop
        47: getstatic     #48                 // Field scala/collection/Iterator$.scala$collection$Iterator$$_empty:Lscala/collection/Iterator;
        50: invokeinterface #53,  1           // InterfaceMethod scala/collection/Iterator.next:()Ljava/lang/Object;
        55: checkcast     #8                  // class scala/collection/immutable/Range
        58: areturn
      StackMapTable: number_of_entries = 1
        frame_type = 43 /* same */
      LineNumberTable:
        line 500: 0
        line 501: 7
        line 502: 28
        line 503: 41
        line 505: 43
      LocalVariableTable:
        Start  Length  Slot  Name   Signature
           28      14     1     x   Lscala/collection/immutable/Range;
            0      59     0  this   Lscala/collection/immutable/Range$$anon$3;

  public java.lang.Object next();
    descriptor: ()Ljava/lang/Object;
    flags: (0x1041) ACC_PUBLIC, ACC_BRIDGE, ACC_SYNTHETIC
    Code:
      stack=1, locals=1, args_size=1
         0: aload_0
         1: invokevirtual #56                 // Method next:()Lscala/collection/immutable/Range;
         4: areturn
      LineNumberTable:
        line 496: 0
      LocalVariableTable:
        Start  Length  Slot  Name   Signature
            0       5     0  this   Lscala/collection/immutable/Range$$anon$3;

  public scala.collection.immutable.Range$$anon$3(scala.collection.immutable.Range, int);
    descriptor: (Lscala/collection/immutable/Range;I)V
    flags: (0x0001) ACC_PUBLIC
    Code:
      stack=2, locals=3, args_size=3
         0: aload_1
         1: ifnonnull     6
         4: aconst_null
         5: athrow
         6: aload_0
         7: aload_1
         8: putfield      #20                 // Field $outer:Lscala/collection/immutable/Range;
        11: aload_0
        12: iload_2
        13: putfield      #34                 // Field s$1:I
        16: aload_0
        17: invokespecial #61                 // Method scala/collection/AbstractIterator."<init>":()V
        20: aload_0
        21: iconst_0
        22: putfield      #26                 // Field i:I
        25: return
      StackMapTable: number_of_entries = 1
        frame_type = 6 /* same */
      LineNumberTable:
        line 496: 0
        line 495: 11
        line 496: 16
        line 497: 20
        line 496: 25
      LocalVariableTable:
        Start  Length  Slot  Name   Signature
            0      26     0  this   Lscala/collection/immutable/Range$$anon$3;
            0      26     1 $outer   Lscala/collection/immutable/Range;
            0      26     2   s$1   I
    MethodParameters:
      Name                           Flags
      $outer                         final synthetic
      s$1                            final
}
InnerClasses:
  public final #2;                        // class scala/collection/immutable/Range$$anon$3
EnclosingMethod: #8.#11                 // scala.collection.immutable.Range.grouped
Signature: #3                           // Lscala/collection/AbstractIterator<Lscala/collection/immutable/Range;>;
SourceFile: "Range.scala"
  ScalaInlineInfo: length = 0x18 (unknown attribute)
   01 01 00 04 00 39 00 3A 01 00 11 00 12 01 00 1D
   00 33 01 00 1D 00 1E 01
  Scala: length = 0x0 (unknown attribute)

