Classfile /Users/mw/Projects/slang-braindump/.jar/jar8/assemble/slang-braindump/assemble/content/scala/collection/immutable/SetNode.class
  Last modified May 29, 2022; size 4176 bytes
  SHA-256 checksum cf9c7d0df0d72f6aa14aed4924c01263b5cabb710c42e7c45e2dce1ff9dbf1d0
  Compiled from "HashSet.scala"
public abstract class scala.collection.immutable.SetNode<A extends java.lang.Object> extends scala.collection.immutable.Node<scala.collection.immutable.SetNode<A>>
  minor version: 0
  major version: 52
  flags: (0x0421) ACC_PUBLIC, ACC_SUPER, ACC_ABSTRACT
  this_class: #2                          // scala/collection/immutable/SetNode
  super_class: #5                         // scala/collection/immutable/Node
  interfaces: 0, fields: 0, methods: 21, attributes: 5
Constant pool:
   #1 = Utf8               scala/collection/immutable/SetNode
   #2 = Class              #1             // scala/collection/immutable/SetNode
   #3 = Utf8               <A:Ljava/lang/Object;>Lscala/collection/immutable/Node<Lscala/collection/immutable/SetNode<TA;>;>;
   #4 = Utf8               scala/collection/immutable/Node
   #5 = Class              #4             // scala/collection/immutable/Node
   #6 = Utf8               HashSet.scala
   #7 = Utf8               Lscala/reflect/ScalaSignature;
   #8 = Utf8               bytes
   #9 = Utf8               \u0006\u0005\u0005]sA\u0002\u000f\u001e\u0011\u0003i2E\u0002\u0004&;!\u0005QD\n\u0005\u0006W\u0005!\t!\f\u0005\b]\u0005\u0011\r\u0011\"\u00040\u0011\u00191\u0014\u0001)A\u0007a!)q\'\u0001C\u0001q!91)\u0001b\u0001\n\u000b!\u0005BB$\u0002A\u00035QI\u0002\u0004&;\u0005\u0005R\u0004\u0013\u0005\u0006W!!\t\u0001\u0015\u0005\u0006#\"1\tA\u0015\u0005\u0006C\"1\tA\u0019\u0005\u0006O\"1\t\u0001\u001b\u0005\u0006[\"1\tA\u001c\u0005\u0006_\"1\t\u0001\u001d\u0005\u0006c\"1\tA\u001d\u0005\u0006k\"1\tA\u001c\u0005\u0006m\"1\t\u0001\u001d\u0005\u0006o\"1\t\u0001\u001f\u0005\u0006u\"1\t\u0001\u001d\u0005\u0006w\"1\t\u0001 \u0005\b\u0003\'Aa\u0011AA\u000b\u0011\u0019\ti\u0002\u0003D\u0001!\"9\u0011q\u0004\u0005\u0007\u0002\u0005\u0005\u0002bBA\u0017\u0011\u0019\u0005\u0011q\u0006\u0005\b\u0003kAa\u0011AA\u001c\u0011\u001d\ti\u0004\u0003D\u0001\u0003\u007fAq!!\u0013\t\r\u0003\tY%A\u0004TKRtu\u000eZ3\u000b\u0005yy\u0012!C5n[V$\u0018M\u00197f\u0015\t\u0001\u0013%\u0001\u0006d_2dWm\u0019;j_:T\u0011AI\u0001\u0006g\u000e\fG.\u0019\t\u0003I\u0005i\u0011!\b\u0002\b\'\u0016$hj\u001c3f\'\t\tq\u0005\u0005\u0002)S5\t\u0011%\u0003\u0002+C\t1\u0011I\\=SK\u001a\fa\u0001P5oSRt4\u0001\u0001\u000b\u0002G\u0005aQ)\u001c9usN+GOT8eKV\t\u0001\u0007E\u0002%cMJ!AM\u000f\u0003)\tKG/\\1q\u0013:$W\r_3e\'\u0016$hj\u001c3f!\tAC\'\u0003\u00026C\t9aj\u001c;iS:<\u0017!D#naRL8+\u001a;O_\u0012,\u0007%A\u0003f[B$\u00180\u0006\u0002:{U\t!\bE\u0002%cm\u0002\"\u0001P\u001f\r\u0001\u0011)a(\u0002b\u0001\u007f\t\t\u0011)\u0005\u00024\u0001B\u0011\u0001&Q\u0005\u0003\u0005\u0006\u00121!\u00118z\u0003-!V\u000f\u001d7f\u0019\u0016tw\r\u001e5\u0016\u0003\u0015{\u0011AR\u000f\u0002\u0003\u0005aA+\u001e9mK2+gn\u001a;iAU\u0011\u0011jT\n\u0003\u0011)\u00032\u0001J&N\u0013\taUD\u0001\u0003O_\u0012,\u0007c\u0001\u0013\t\u001dB\u0011Ah\u0014\u0003\u0006}!\u0011\ra\u0010\u000b\u0002\u001b\u0006A1m\u001c8uC&t7\u000fF\u0003T-bkv\f\u0005\u0002))&\u0011Q+\t\u0002\b\u0005>|G.Z1o\u0011\u00159&\u00021\u0001O\u0003\u001d)G.Z7f]RDQ!\u0017\u0006A\u0002i\u000bAb\u001c:jO&t\u0017\r\u001c%bg\"\u0004\"\u0001K.\n\u0005q\u000b#aA%oi\")aL\u0003a\u00015\u0006!\u0001.Y:i\u0011\u0015\u0001\'\u00021\u0001[\u0003\u0015\u0019\b.\u001b4u\u0003\u001d)\b\u000fZ1uK\u0012$R!T2eK\u001aDQaV\u0006A\u00029CQ!W\u0006A\u0002iCQAX\u0006A\u0002iCQ\u0001Y\u0006A\u0002i\u000bqA]3n_Z,G\rF\u0003NS*\\G\u000eC\u0003X\u0019\u0001\u0007a\nC\u0003Z\u0019\u0001\u0007!\fC\u0003_\u0019\u0001\u0007!\fC\u0003a\u0019\u0001\u0007!,\u0001\u0005iCNtu\u000eZ3t+\u0005\u0019\u0016!\u00038pI\u0016\f%/\u001b;z+\u0005Q\u0016aB4fi:{G-\u001a\u000b\u0003\u001bNDQ\u0001^\bA\u0002i\u000bQ!\u001b8eKb\f!\u0002[1t!\u0006LHn\\1e\u00031\u0001\u0018-\u001f7pC\u0012\f%/\u001b;z\u0003)9W\r\u001e)bs2|\u0017\r\u001a\u000b\u0003\u001dfDQ\u0001\u001e\nA\u0002i\u000bAa]5{K\u00069am\u001c:fC\u000eDWcA?\u0002\u0010Q\u0019a0a\u0001\u0011\u0005!z\u0018bAA\u0001C\t!QK\\5u\u0011\u001d\t)\u0001\u0006a\u0001\u0003\u000f\t\u0011A\u001a\t\u0007Q\u0005%a*!\u0004\n\u0007\u0005-\u0011EA\u0005Gk:\u001cG/[8ocA\u0019A(a\u0004\u0005\r\u0005EAC1\u0001@\u0005\u0005)\u0016\u0001C:vEN,Go\u00144\u0015\u000bM\u000b9\"a\u0007\t\r\u0005eQ\u00031\u0001N\u0003\u0011!\b.\u0019;\t\u000b\u0001,\u0002\u0019\u0001.\u0002\t\r|\u0007/_\u0001\u000bM&dG/\u001a:J[BdG#B\'\u0002$\u0005%\u0002bBA\u0013/\u0001\u0007\u0011qE\u0001\u0005aJ,G\rE\u0003)\u0003\u0013q5\u000b\u0003\u0004\u0002,]\u0001\raU\u0001\bM2L\u0007\u000f]3e\u0003\u0011!\u0017N\u001a4\u0015\u000b5\u000b\t$a\r\t\r\u0005e\u0001\u00041\u0001N\u0011\u0015\u0001\u0007\u00041\u0001[\u0003\u0019\u0019wN\\2biR)Q*!\u000f\u0002<!1\u0011\u0011D\rA\u00025CQ\u0001Y\rA\u0002i\u000bqBZ8sK\u0006\u001c\u0007nV5uQ\"\u000b7\u000f\u001b\u000b\u0004}\u0006\u0005\u0003bBA\u00035\u0001\u0007\u00111\t\t\u0007Q\u0005\u0015cJ\u0017@\n\u0007\u0005\u001d\u0013EA\u0005Gk:\u001cG/[8oe\u0005!bm\u001c:fC\u000eDw+\u001b;i\u0011\u0006\u001c\bn\u00165jY\u0016$2aUA\'\u0011\u001d\t)a\u0007a\u0001\u0003\u001f\u0002b\u0001KA#\u001dj\u001b\u0016\u0006\u0002\u00052\u0003\'J1!!\u0016\u001e\u0005QA\u0015m\u001d5D_2d\u0017n]5p]N+GOT8eK\u0002
  #10 = Utf8               TupleLength
  #11 = Utf8               ()I
  #12 = Utf8               scala/collection/immutable/SetNode$
  #13 = Class              #12            // scala/collection/immutable/SetNode$
  #14 = Utf8               MODULE$
  #15 = Utf8               Lscala/collection/immutable/SetNode$;
  #16 = NameAndType        #14:#15        // MODULE$:Lscala/collection/immutable/SetNode$;
  #17 = Fieldref           #13.#16        // scala/collection/immutable/SetNode$.MODULE$:Lscala/collection/immutable/SetNode$;
  #18 = Utf8               empty
  #19 = Utf8               ()Lscala/collection/immutable/BitmapIndexedSetNode;
  #20 = Utf8               <A:Ljava/lang/Object;>()Lscala/collection/immutable/BitmapIndexedSetNode<TA;>;
  #21 = NameAndType        #18:#19        // empty:()Lscala/collection/immutable/BitmapIndexedSetNode;
  #22 = Methodref          #13.#21        // scala/collection/immutable/SetNode$.empty:()Lscala/collection/immutable/BitmapIndexedSetNode;
  #23 = Utf8               contains
  #24 = Utf8               (Ljava/lang/Object;III)Z
  #25 = Utf8               (TA;III)Z
  #26 = Utf8               element
  #27 = Utf8               originalHash
  #28 = Utf8               hash
  #29 = Utf8               shift
  #30 = Utf8               updated
  #31 = Utf8               (Ljava/lang/Object;III)Lscala/collection/immutable/SetNode;
  #32 = Utf8               (TA;III)Lscala/collection/immutable/SetNode<TA;>;
  #33 = Utf8               removed
  #34 = Utf8               hasNodes
  #35 = Utf8               ()Z
  #36 = Utf8               nodeArity
  #37 = Utf8               getNode
  #38 = Utf8               (I)Lscala/collection/immutable/SetNode;
  #39 = Utf8               (I)Lscala/collection/immutable/SetNode<TA;>;
  #40 = Utf8               index
  #41 = Utf8               hasPayload
  #42 = Utf8               payloadArity
  #43 = Utf8               getPayload
  #44 = Utf8               (I)Ljava/lang/Object;
  #45 = Utf8               (I)TA;
  #46 = Utf8               size
  #47 = Utf8               foreach
  #48 = Utf8               (Lscala/Function1;)V
  #49 = Utf8               <U:Ljava/lang/Object;>(Lscala/Function1<TA;TU;>;)V
  #50 = Utf8               f
  #51 = Utf8               subsetOf
  #52 = Utf8               (Lscala/collection/immutable/SetNode;I)Z
  #53 = Utf8               (Lscala/collection/immutable/SetNode<TA;>;I)Z
  #54 = Utf8               that
  #55 = Utf8               copy
  #56 = Utf8               ()Lscala/collection/immutable/SetNode;
  #57 = Utf8               ()Lscala/collection/immutable/SetNode<TA;>;
  #58 = Utf8               filterImpl
  #59 = Utf8               (Lscala/Function1;Z)Lscala/collection/immutable/SetNode;
  #60 = Utf8               (Lscala/Function1<TA;Ljava/lang/Object;>;Z)Lscala/collection/immutable/SetNode<TA;>;
  #61 = Utf8               pred
  #62 = Utf8               flipped
  #63 = Utf8               diff
  #64 = Utf8               (Lscala/collection/immutable/SetNode;I)Lscala/collection/immutable/SetNode;
  #65 = Utf8               (Lscala/collection/immutable/SetNode<TA;>;I)Lscala/collection/immutable/SetNode<TA;>;
  #66 = Utf8               concat
  #67 = Utf8               foreachWithHash
  #68 = Utf8               (Lscala/Function2;)V
  #69 = Utf8               (Lscala/Function2<TA;Ljava/lang/Object;Lscala/runtime/BoxedUnit;>;)V
  #70 = Utf8               foreachWithHashWhile
  #71 = Utf8               (Lscala/Function2;)Z
  #72 = Utf8               (Lscala/Function2<TA;Ljava/lang/Object;Ljava/lang/Object;>;)Z
  #73 = Utf8               <init>
  #74 = Utf8               ()V
  #75 = NameAndType        #73:#74        // "<init>":()V
  #76 = Methodref          #5.#75         // scala/collection/immutable/Node."<init>":()V
  #77 = Utf8               this
  #78 = Utf8               Lscala/collection/immutable/SetNode;
  #79 = Utf8               Code
  #80 = Utf8               Signature
  #81 = Utf8               MethodParameters
  #82 = Utf8               LineNumberTable
  #83 = Utf8               LocalVariableTable
  #84 = Utf8               SourceFile
  #85 = Utf8               RuntimeVisibleAnnotations
  #86 = Utf8               ScalaInlineInfo
  #87 = Utf8               ScalaSig
{
  public static int TupleLength();
    descriptor: ()I
    flags: (0x0009) ACC_PUBLIC, ACC_STATIC
    Code:
      stack=1, locals=0, args_size=0
         0: getstatic     #17                 // Field scala/collection/immutable/SetNode$.MODULE$:Lscala/collection/immutable/SetNode$;
         3: pop
         4: iconst_1
         5: ireturn

  public static <A extends java.lang.Object> scala.collection.immutable.BitmapIndexedSetNode<A> empty();
    descriptor: ()Lscala/collection/immutable/BitmapIndexedSetNode;
    flags: (0x0009) ACC_PUBLIC, ACC_STATIC
    Code:
      stack=1, locals=0, args_size=0
         0: getstatic     #17                 // Field scala/collection/immutable/SetNode$.MODULE$:Lscala/collection/immutable/SetNode$;
         3: invokevirtual #22                 // Method scala/collection/immutable/SetNode$.empty:()Lscala/collection/immutable/BitmapIndexedSetNode;
         6: areturn
    Signature: #20                          // <A:Ljava/lang/Object;>()Lscala/collection/immutable/BitmapIndexedSetNode<TA;>;

  public abstract boolean contains(A, int, int, int);
    descriptor: (Ljava/lang/Object;III)Z
    flags: (0x0401) ACC_PUBLIC, ACC_ABSTRACT
    Signature: #25                          // (TA;III)Z
    MethodParameters:
      Name                           Flags
      element                        final
      originalHash                   final
      hash                           final
      shift                          final

  public abstract scala.collection.immutable.SetNode<A> updated(A, int, int, int);
    descriptor: (Ljava/lang/Object;III)Lscala/collection/immutable/SetNode;
    flags: (0x0401) ACC_PUBLIC, ACC_ABSTRACT
    Signature: #32                          // (TA;III)Lscala/collection/immutable/SetNode<TA;>;
    MethodParameters:
      Name                           Flags
      element                        final
      originalHash                   final
      hash                           final
      shift                          final

  public abstract scala.collection.immutable.SetNode<A> removed(A, int, int, int);
    descriptor: (Ljava/lang/Object;III)Lscala/collection/immutable/SetNode;
    flags: (0x0401) ACC_PUBLIC, ACC_ABSTRACT
    Signature: #32                          // (TA;III)Lscala/collection/immutable/SetNode<TA;>;
    MethodParameters:
      Name                           Flags
      element                        final
      originalHash                   final
      hash                           final
      shift                          final

  public abstract boolean hasNodes();
    descriptor: ()Z
    flags: (0x0401) ACC_PUBLIC, ACC_ABSTRACT

  public abstract int nodeArity();
    descriptor: ()I
    flags: (0x0401) ACC_PUBLIC, ACC_ABSTRACT

  public abstract scala.collection.immutable.SetNode<A> getNode(int);
    descriptor: (I)Lscala/collection/immutable/SetNode;
    flags: (0x0401) ACC_PUBLIC, ACC_ABSTRACT
    Signature: #39                          // (I)Lscala/collection/immutable/SetNode<TA;>;
    MethodParameters:
      Name                           Flags
      index                          final

  public abstract boolean hasPayload();
    descriptor: ()Z
    flags: (0x0401) ACC_PUBLIC, ACC_ABSTRACT

  public abstract int payloadArity();
    descriptor: ()I
    flags: (0x0401) ACC_PUBLIC, ACC_ABSTRACT

  public abstract A getPayload(int);
    descriptor: (I)Ljava/lang/Object;
    flags: (0x0401) ACC_PUBLIC, ACC_ABSTRACT
    Signature: #45                          // (I)TA;
    MethodParameters:
      Name                           Flags
      index                          final

  public abstract int size();
    descriptor: ()I
    flags: (0x0401) ACC_PUBLIC, ACC_ABSTRACT

  public abstract <U extends java.lang.Object> void foreach(scala.Function1<A, U>);
    descriptor: (Lscala/Function1;)V
    flags: (0x0401) ACC_PUBLIC, ACC_ABSTRACT
    Signature: #49                          // <U:Ljava/lang/Object;>(Lscala/Function1<TA;TU;>;)V
    MethodParameters:
      Name                           Flags
      f                              final

  public abstract boolean subsetOf(scala.collection.immutable.SetNode<A>, int);
    descriptor: (Lscala/collection/immutable/SetNode;I)Z
    flags: (0x0401) ACC_PUBLIC, ACC_ABSTRACT
    Signature: #53                          // (Lscala/collection/immutable/SetNode<TA;>;I)Z
    MethodParameters:
      Name                           Flags
      that                           final
      shift                          final

  public abstract scala.collection.immutable.SetNode<A> copy();
    descriptor: ()Lscala/collection/immutable/SetNode;
    flags: (0x0401) ACC_PUBLIC, ACC_ABSTRACT
    Signature: #57                          // ()Lscala/collection/immutable/SetNode<TA;>;

  public abstract scala.collection.immutable.SetNode<A> filterImpl(scala.Function1<A, java.lang.Object>, boolean);
    descriptor: (Lscala/Function1;Z)Lscala/collection/immutable/SetNode;
    flags: (0x0401) ACC_PUBLIC, ACC_ABSTRACT
    Signature: #60                          // (Lscala/Function1<TA;Ljava/lang/Object;>;Z)Lscala/collection/immutable/SetNode<TA;>;
    MethodParameters:
      Name                           Flags
      pred                           final
      flipped                        final

  public abstract scala.collection.immutable.SetNode<A> diff(scala.collection.immutable.SetNode<A>, int);
    descriptor: (Lscala/collection/immutable/SetNode;I)Lscala/collection/immutable/SetNode;
    flags: (0x0401) ACC_PUBLIC, ACC_ABSTRACT
    Signature: #65                          // (Lscala/collection/immutable/SetNode<TA;>;I)Lscala/collection/immutable/SetNode<TA;>;
    MethodParameters:
      Name                           Flags
      that                           final
      shift                          final

  public abstract scala.collection.immutable.SetNode<A> concat(scala.collection.immutable.SetNode<A>, int);
    descriptor: (Lscala/collection/immutable/SetNode;I)Lscala/collection/immutable/SetNode;
    flags: (0x0401) ACC_PUBLIC, ACC_ABSTRACT
    Signature: #65                          // (Lscala/collection/immutable/SetNode<TA;>;I)Lscala/collection/immutable/SetNode<TA;>;
    MethodParameters:
      Name                           Flags
      that                           final
      shift                          final

  public abstract void foreachWithHash(scala.Function2<A, java.lang.Object, scala.runtime.BoxedUnit>);
    descriptor: (Lscala/Function2;)V
    flags: (0x0401) ACC_PUBLIC, ACC_ABSTRACT
    Signature: #69                          // (Lscala/Function2<TA;Ljava/lang/Object;Lscala/runtime/BoxedUnit;>;)V
    MethodParameters:
      Name                           Flags
      f                              final

  public abstract boolean foreachWithHashWhile(scala.Function2<A, java.lang.Object, java.lang.Object>);
    descriptor: (Lscala/Function2;)Z
    flags: (0x0401) ACC_PUBLIC, ACC_ABSTRACT
    Signature: #72                          // (Lscala/Function2<TA;Ljava/lang/Object;Ljava/lang/Object;>;)Z
    MethodParameters:
      Name                           Flags
      f                              final

  public scala.collection.immutable.SetNode();
    descriptor: ()V
    flags: (0x0001) ACC_PUBLIC
    Code:
      stack=1, locals=1, args_size=1
         0: aload_0
         1: invokespecial #76                 // Method scala/collection/immutable/Node."<init>":()V
         4: return
      LineNumberTable:
        line 367: 0
      LocalVariableTable:
        Start  Length  Slot  Name   Signature
            0       5     0  this   Lscala/collection/immutable/SetNode;
}
Signature: #3                           // <A:Ljava/lang/Object;>Lscala/collection/immutable/Node<Lscala/collection/immutable/SetNode<TA;>;>;
SourceFile: "HashSet.scala"
RuntimeVisibleAnnotations:
  0: #7(#8=s#9)
    scala.reflect.ScalaSignature(
      bytes="\u0006\u0005\u0005]sA\u0002\u000f\u001e\u0011\u0003i2E\u0002\u0004&;!\u0005QD\n\u0005\u0006W\u0005!\t!\f\u0005\b]\u0005\u0011\r\u0011\"\u00040\u0011\u00191\u0014\u0001)A\u0007a!)q\'\u0001C\u0001q!91)\u0001b\u0001\n\u000b!\u0005BB$\u0002A\u00035QI\u0002\u0004&;\u0005\u0005R\u0004\u0013\u0005\u0006W!!\t\u0001\u0015\u0005\u0006#\"1\tA\u0015\u0005\u0006C\"1\tA\u0019\u0005\u0006O\"1\t\u0001\u001b\u0005\u0006[\"1\tA\u001c\u0005\u0006_\"1\t\u0001\u001d\u0005\u0006c\"1\tA\u001d\u0005\u0006k\"1\tA\u001c\u0005\u0006m\"1\t\u0001\u001d\u0005\u0006o\"1\t\u0001\u001f\u0005\u0006u\"1\t\u0001\u001d\u0005\u0006w\"1\t\u0001 \u0005\b\u0003\'Aa\u0011AA\u000b\u0011\u0019\ti\u0002\u0003D\u0001!\"9\u0011q\u0004\u0005\u0007\u0002\u0005\u0005\u0002bBA\u0017\u0011\u0019\u0005\u0011q\u0006\u0005\b\u0003kAa\u0011AA\u001c\u0011\u001d\ti\u0004\u0003D\u0001\u0003\u007fAq!!\u0013\t\r\u0003\tY%A\u0004TKRtu\u000eZ3\u000b\u0005yy\u0012!C5n[V$\u0018M\u00197f\u0015\t\u0001\u0013%\u0001\u0006d_2dWm\u0019;j_:T\u0011AI\u0001\u0006g\u000e\fG.\u0019\t\u0003I\u0005i\u0011!\b\u0002\b\'\u0016$hj\u001c3f\'\t\tq\u0005\u0005\u0002)S5\t\u0011%\u0003\u0002+C\t1\u0011I\\=SK\u001a\fa\u0001P5oSRt4\u0001\u0001\u000b\u0002G\u0005aQ)\u001c9usN+GOT8eKV\t\u0001\u0007E\u0002%cMJ!AM\u000f\u0003)\tKG/\\1q\u0013:$W\r_3e\'\u0016$hj\u001c3f!\tAC\'\u0003\u00026C\t9aj\u001c;iS:<\u0017!D#naRL8+\u001a;O_\u0012,\u0007%A\u0003f[B$\u00180\u0006\u0002:{U\t!\bE\u0002%cm\u0002\"\u0001P\u001f\r\u0001\u0011)a(\u0002b\u0001\u007f\t\t\u0011)\u0005\u00024\u0001B\u0011\u0001&Q\u0005\u0003\u0005\u0006\u00121!\u00118z\u0003-!V\u000f\u001d7f\u0019\u0016tw\r\u001e5\u0016\u0003\u0015{\u0011AR\u000f\u0002\u0003\u0005aA+\u001e9mK2+gn\u001a;iAU\u0011\u0011jT\n\u0003\u0011)\u00032\u0001J&N\u0013\taUD\u0001\u0003O_\u0012,\u0007c\u0001\u0013\t\u001dB\u0011Ah\u0014\u0003\u0006}!\u0011\ra\u0010\u000b\u0002\u001b\u0006A1m\u001c8uC&t7\u000fF\u0003T-bkv\f\u0005\u0002))&\u0011Q+\t\u0002\b\u0005>|G.Z1o\u0011\u00159&\u00021\u0001O\u0003\u001d)G.Z7f]RDQ!\u0017\u0006A\u0002i\u000bAb\u001c:jO&t\u0017\r\u001c%bg\"\u0004\"\u0001K.\n\u0005q\u000b#aA%oi\")aL\u0003a\u00015\u0006!\u0001.Y:i\u0011\u0015\u0001\'\u00021\u0001[\u0003\u0015\u0019\b.\u001b4u\u0003\u001d)\b\u000fZ1uK\u0012$R!T2eK\u001aDQaV\u0006A\u00029CQ!W\u0006A\u0002iCQAX\u0006A\u0002iCQ\u0001Y\u0006A\u0002i\u000bqA]3n_Z,G\rF\u0003NS*\\G\u000eC\u0003X\u0019\u0001\u0007a\nC\u0003Z\u0019\u0001\u0007!\fC\u0003_\u0019\u0001\u0007!\fC\u0003a\u0019\u0001\u0007!,\u0001\u0005iCNtu\u000eZ3t+\u0005\u0019\u0016!\u00038pI\u0016\f%/\u001b;z+\u0005Q\u0016aB4fi:{G-\u001a\u000b\u0003\u001bNDQ\u0001^\bA\u0002i\u000bQ!\u001b8eKb\f!\u0002[1t!\u0006LHn\\1e\u00031\u0001\u0018-\u001f7pC\u0012\f%/\u001b;z\u0003)9W\r\u001e)bs2|\u0017\r\u001a\u000b\u0003\u001dfDQ\u0001\u001e\nA\u0002i\u000bAa]5{K\u00069am\u001c:fC\u000eDWcA?\u0002\u0010Q\u0019a0a\u0001\u0011\u0005!z\u0018bAA\u0001C\t!QK\\5u\u0011\u001d\t)\u0001\u0006a\u0001\u0003\u000f\t\u0011A\u001a\t\u0007Q\u0005%a*!\u0004\n\u0007\u0005-\u0011EA\u0005Gk:\u001cG/[8ocA\u0019A(a\u0004\u0005\r\u0005EAC1\u0001@\u0005\u0005)\u0016\u0001C:vEN,Go\u00144\u0015\u000bM\u000b9\"a\u0007\t\r\u0005eQ\u00031\u0001N\u0003\u0011!\b.\u0019;\t\u000b\u0001,\u0002\u0019\u0001.\u0002\t\r|\u0007/_\u0001\u000bM&dG/\u001a:J[BdG#B\'\u0002$\u0005%\u0002bBA\u0013/\u0001\u0007\u0011qE\u0001\u0005aJ,G\rE\u0003)\u0003\u0013q5\u000b\u0003\u0004\u0002,]\u0001\raU\u0001\bM2L\u0007\u000f]3e\u0003\u0011!\u0017N\u001a4\u0015\u000b5\u000b\t$a\r\t\r\u0005e\u0001\u00041\u0001N\u0011\u0015\u0001\u0007\u00041\u0001[\u0003\u0019\u0019wN\\2biR)Q*!\u000f\u0002<!1\u0011\u0011D\rA\u00025CQ\u0001Y\rA\u0002i\u000bqBZ8sK\u0006\u001c\u0007nV5uQ\"\u000b7\u000f\u001b\u000b\u0004}\u0006\u0005\u0003bBA\u00035\u0001\u0007\u00111\t\t\u0007Q\u0005\u0015cJ\u0017@\n\u0007\u0005\u001d\u0013EA\u0005Gk:\u001cG/[8oe\u0005!bm\u001c:fC\u000eDw+\u001b;i\u0011\u0006\u001c\bn\u00165jY\u0016$2aUA\'\u0011\u001d\t)a\u0007a\u0001\u0003\u001f\u0002b\u0001KA#\u001dj\u001b\u0016\u0006\u0002\u00052\u0003\'J1!!\u0016\u001e\u0005QA\u0015m\u001d5D_2d\u0017n]5p]N+GOT8eK\u0002"
    )
  ScalaInlineInfo: length = 0x63 (unknown attribute)
   01 00 00 13 00 49 00 4A 01 00 42 00 40 00 00 17
   00 18 00 00 37 00 38 00 00 3F 00 40 00 00 3A 00
   3B 00 00 2F 00 30 00 00 43 00 44 00 00 46 00 47
   00 00 25 00 26 00 00 2B 00 2C 00 00 22 00 23 00
   00 29 00 23 00 00 24 00 0B 00 00 2A 00 0B 00 00
   21 00 1F 00 00 2E 00 0B 00 00 33 00 34 00 00 1E
   00 1F 00
  ScalaSig: length = 0x3 (unknown attribute)
   05 02 00
