Classfile /Users/mw/Projects/slang-braindump/.jar/jar8/assemble/slang-braindump/assemble/content/scala/collection/immutable/SortedMapOps.class
  Last modified May 29, 2022; size 6866 bytes
  SHA-256 checksum f63d31180d0eaea0d32dee66291da062c3a08259560585be02bb7f5864645fab
  Compiled from "SortedMap.scala"
public interface scala.collection.immutable.SortedMapOps<K extends java.lang.Object, V extends java.lang.Object, CC extends scala.collection.immutable.Map<java.lang.Object, java.lang.Object>, C extends scala.collection.immutable.SortedMapOps<K, V, CC, C>> extends scala.collection.immutable.MapOps<K, V, scala.collection.immutable.Map, C>, scala.collection.SortedMapOps<K, V, CC, C>
  minor version: 0
  major version: 52
  flags: (0x0601) ACC_PUBLIC, ACC_INTERFACE, ACC_ABSTRACT
  this_class: #2                          // scala/collection/immutable/SortedMapOps
  super_class: #5                         // java/lang/Object
  interfaces: 2, fields: 0, methods: 14, attributes: 7
Constant pool:
    #1 = Utf8               scala/collection/immutable/SortedMapOps
    #2 = Class              #1            // scala/collection/immutable/SortedMapOps
    #3 = Utf8               <K:Ljava/lang/Object;V:Ljava/lang/Object;CC:Lscala/collection/immutable/Map<Ljava/lang/Object;Ljava/lang/Object;>;C::Lscala/collection/immutable/SortedMapOps<TK;TV;TCC;TC;>;>Ljava/lang/Object;Lscala/collection/immutable/MapOps<TK;TV;Lscala/collection/immutable/Map;TC;>;Lscala/collection/SortedMapOps<TK;TV;TCC;TC;>;
    #4 = Utf8               java/lang/Object
    #5 = Class              #4            // java/lang/Object
    #6 = Utf8               scala/collection/immutable/MapOps
    #7 = Class              #6            // scala/collection/immutable/MapOps
    #8 = Utf8               scala/collection/SortedMapOps
    #9 = Class              #8            // scala/collection/SortedMapOps
   #10 = Utf8               SortedMap.scala
   #11 = Utf8               Lscala/reflect/ScalaSignature;
   #12 = Utf8               bytes
   #13 = Utf8               \u0006\u0005\u0005-da\u0002\b\u0010!\u0003\r\tA\u0006\u0005\u0006\u001b\u0002!\tA\u0014\u0005\u0006%\u00021\tb\u0015\u0005\u0006/\u00021\t\u0001\u0017\u0005\u00065\u0002!\te\u0017\u0004\u0005?\u0002A\u0001\rC\u0003m\u000b\u0011\u0005Q\u000eC\u0003p\u000b\u0011\u0005\u0001\u000fC\u0003y\u000b\u0011\u0005\u0011\u0010C\u0003}\u000b\u0011\u0005Q\u0010\u0003\u0004\u0000\u0001\u0019\u0005\u0011\u0011\u0001\u0005\b\u0003/\u0001AQIA\r\u0011\u001d\t)\u0004\u0001C!\u0003oAq!a\u0015\u0001\t\u0003\n)F\u0001\u0007T_J$X\rZ\'ba>\u00038O\u0003\u0002\u0011#\u0005I\u0011.\\7vi\u0006\u0014G.\u001a\u0006\u0003%M\t!bY8mY\u0016\u001cG/[8o\u0015\u0005!\u0012!B:dC2\f7\u0001A\u000b\u0006/\tbsGM\n\u0005\u0001aa\"\n\u0005\u0002\u001a55\t1#\u0003\u0002\u001c\'\t1\u0011I\\=SK\u001a\u0004b!\b\u0010!W9\nT\"A\b\n\u0005}y!AB\'ba>\u00038\u000f\u0005\u0002\"E1\u0001A!B\u0012\u0001\u0005\u0004!#!A&\u0012\u0005\u0015B\u0003CA\r\'\u0013\t93CA\u0004O_RD\u0017N\\4\u0011\u0005eI\u0013B\u0001\u0016\u0014\u0005\r\te.\u001f\t\u0003C1\"a!\f\u0001\u0005\u0006\u0004!#!\u0001,\u0011\u0005uy\u0013B\u0001\u0019\u0010\u0005\ri\u0015\r\u001d\t\u0003CI\"aa\r\u0001\u0005\u0006\u0004!$!A\"\u0012\u0005\u0015*\u0004CB\u000f\u0001A-2\u0014\u0007\u0005\u0002\"o\u00111\u0001\b\u0001CC\u0002e\u0012!aQ\"\u0016\u0007i\u00025)\u0005\u0002&wI\u0019AHP#\u0007\tu\u0002\u0001a\u000f\u0002\ryI,g-\u001b8f[\u0016tGO\u0010\t\u0005;=z$\t\u0005\u0002\"\u0001\u0012)\u0011i\u000eb\u0001I\t\t\u0001\f\u0005\u0002\"\u0007\u00121Ai\u000eCC\u0002\u0011\u0012\u0011!\u0017\u0019\u0003\r\"\u0003b!\b\u0001@\u0005Z:\u0005CA\u0011I\t%Iu\'!A\u0001\u0002\u000b\u0005AEA\u0002`IE\u0002ba\u0013\'!WY\nT\"A\t\n\u00059\t\u0012A\u0002\u0013j]&$H\u0005F\u0001P!\tI\u0002+\u0003\u0002R\'\t!QK\\5u\u0003\u0011\u0019w\u000e\u001c7\u0016\u0003Q\u00132!V\u0019W\r\u0011i\u0004\u0001\u0001+\u0011\t\u0005:\u0004eK\u0001\tk:\u001cxN\u001d;fIV\t\u0011\f\u0005\u0003\u001e_\u0001Z\u0013AB6fsN+G/F\u0001]!\riR\fI\u0005\u0003=>\u0011\u0011bU8si\u0016$7+\u001a;\u0003+%kW.\u001e;bE2,7*Z=T_J$X\rZ*fiN)Q!\u0019/eSB\u0019QD\u0019\u0011\n\u0005\r|!aC!cgR\u0014\u0018m\u0019;TKR\u0004\"!\u001a4\u000e\u0003\u0001I!a\u001a5\u0003\u0013\u001d+gnS3z\'\u0016$\u0018BA\u0010\u0012!\t)\'.\u0003\u0002l\u0019\nyq)\u001a8LKf\u001cvN\u001d;fIN+G/\u0001\u0004=S:LGO\u0010\u000b\u0002]B\u0011Q-B\u0001\ne\u0006tw-Z%na2$2\u0001X9w\u0011\u0015\u0011x\u00011\u0001t\u0003\u00111\'o\\7\u0011\u0007e!\b%\u0003\u0002v\'\t1q\n\u001d;j_:DQa^\u0004A\u0002M\fQ!\u001e8uS2\fA!\u001b8dYR\u0011AL\u001f\u0005\u0006w\"\u0001\r\u0001I\u0001\u0005K2,W.\u0001\u0003fq\u000edGC\u0001/\u007f\u0011\u0015Y\u0018\u00021\u0001!\u0003\u001d)\b\u000fZ1uK\u0012,B!a\u0001\u0002\nQ1\u0011QAA\b\u0003\'\u0001R!I\u001c!\u0003\u000f\u00012!IA\u0005\t\u001d\tYA\u0003b\u0001\u0003\u001b\u0011!AV\u0019\u0012\u0005-B\u0003BBA\t\u0015\u0001\u0007\u0001%A\u0002lKfDq!!\u0006\u000b\u0001\u0004\t9!A\u0003wC2,X-A\u0003%a2,8/\u0006\u0003\u0002\u001c\u0005\u0005B\u0003BA\u000f\u0003G\u0001R!I\u001c!\u0003?\u00012!IA\u0011\t\u001d\tYa\u0003b\u0001\u0003\u001bAq!!\n\f\u0001\u0004\t9#\u0001\u0002lmB1\u0011$!\u000b!\u0003?I1!a\u000b\u0014\u0005\u0019!V\u000f\u001d7fe!\u001a1\"a\f\u0011\u0007e\t\t$C\u0002\u00024M\u0011a!\u001b8mS:,\u0017aC;qI\u0006$X\rZ,ji\",B!!\u000f\u0002BQ!\u00111HA))\u0011\ti$a\u0011\u0011\u000b\u0005:\u0004%a\u0010\u0011\u0007\u0005\n\t\u0005B\u0004\u0002\f1\u0011\r!!\u0004\t\u000f\u0005\u0015C\u00021\u0001\u0002H\u0005\t\"/Z7baBLgn\u001a$v]\u000e$\u0018n\u001c8\u0011\u000fe\tI%!\u0014\u0002P%\u0019\u00111J\n\u0003\u0013\u0019+hn\u0019;j_:\f\u0004cA\ruWA!\u0011\u0004^A \u0011\u0019\t\t\u0002\u0004a\u0001A\u0005IAO]1og\u001a|\'/\\\u000b\u0005\u0003/\ni\u0006\u0006\u0003\u0002Z\u0005\u0005\u0004#B\u00118A\u0005m\u0003cA\u0011\u0002^\u00111\u0011qL\u0007C\u0002\u0011\u0012\u0011a\u0016\u0005\b\u0003Gj\u0001\u0019AA3\u0003\u00051\u0007cB\r\u0002h\u0001Z\u00131L\u0005\u0004\u0003S\u001a\"!\u0003$v]\u000e$\u0018n\u001c83\u0001
   #14 = Utf8               java/lang/invoke/MethodHandles$Lookup
   #15 = Class              #14           // java/lang/invoke/MethodHandles$Lookup
   #16 = Utf8               java/lang/invoke/MethodHandles
   #17 = Class              #16           // java/lang/invoke/MethodHandles
   #18 = Utf8               Lookup
   #19 = Utf8               scala/collection/immutable/SortedMapOps$ImmutableKeySortedSet
   #20 = Class              #19           // scala/collection/immutable/SortedMapOps$ImmutableKeySortedSet
   #21 = Utf8               ImmutableKeySortedSet
   #22 = Utf8               coll
   #23 = Utf8               ()Lscala/collection/immutable/SortedMapOps;
   #24 = Utf8               ()TC;
   #25 = Utf8               unsorted
   #26 = Utf8               ()Lscala/collection/immutable/Map;
   #27 = Utf8               ()Lscala/collection/immutable/Map<TK;TV;>;
   #28 = Utf8               keySet$
   #29 = Utf8               (Lscala/collection/immutable/SortedMapOps;)Lscala/collection/immutable/SortedSet;
   #30 = Utf8               $this
   #31 = Utf8               keySet
   #32 = Utf8               ()Lscala/collection/immutable/SortedSet;
   #33 = NameAndType        #31:#32       // keySet:()Lscala/collection/immutable/SortedSet;
   #34 = InterfaceMethodref #2.#33        // scala/collection/immutable/SortedMapOps.keySet:()Lscala/collection/immutable/SortedSet;
   #35 = Utf8               Lscala/collection/immutable/SortedMapOps;
   #36 = Utf8               ()Lscala/collection/immutable/SortedSet<TK;>;
   #37 = Utf8               <init>
   #38 = Utf8               (Lscala/collection/immutable/SortedMapOps;)V
   #39 = NameAndType        #37:#38       // "<init>":(Lscala/collection/immutable/SortedMapOps;)V
   #40 = Methodref          #20.#39       // scala/collection/immutable/SortedMapOps$ImmutableKeySortedSet."<init>":(Lscala/collection/immutable/SortedMapOps;)V
   #41 = Utf8               this
   #42 = Utf8               updated
   #43 = Utf8               (Ljava/lang/Object;Ljava/lang/Object;)Lscala/collection/immutable/Map;
   #44 = Utf8               <V1:Ljava/lang/Object;>(TK;TV1;)TCC;
   #45 = Utf8               key
   #46 = Utf8               value
   #47 = Utf8               $plus$
   #48 = Utf8               (Lscala/collection/immutable/SortedMapOps;Lscala/Tuple2;)Lscala/collection/immutable/Map;
   #49 = Utf8               kv
   #50 = Utf8               $plus
   #51 = Utf8               (Lscala/Tuple2;)Lscala/collection/immutable/Map;
   #52 = NameAndType        #50:#51       // $plus:(Lscala/Tuple2;)Lscala/collection/immutable/Map;
   #53 = InterfaceMethodref #2.#52        // scala/collection/immutable/SortedMapOps.$plus:(Lscala/Tuple2;)Lscala/collection/immutable/Map;
   #54 = Utf8               Lscala/Tuple2;
   #55 = Utf8               <V1:Ljava/lang/Object;>(Lscala/Tuple2<TK;TV1;>;)TCC;
   #56 = Utf8               scala/Tuple2
   #57 = Class              #56           // scala/Tuple2
   #58 = Utf8               _1
   #59 = Utf8               ()Ljava/lang/Object;
   #60 = NameAndType        #58:#59       // _1:()Ljava/lang/Object;
   #61 = Methodref          #57.#60       // scala/Tuple2._1:()Ljava/lang/Object;
   #62 = Utf8               _2
   #63 = NameAndType        #62:#59       // _2:()Ljava/lang/Object;
   #64 = Methodref          #57.#63       // scala/Tuple2._2:()Ljava/lang/Object;
   #65 = NameAndType        #42:#43       // updated:(Ljava/lang/Object;Ljava/lang/Object;)Lscala/collection/immutable/Map;
   #66 = InterfaceMethodref #2.#65        // scala/collection/immutable/SortedMapOps.updated:(Ljava/lang/Object;Ljava/lang/Object;)Lscala/collection/immutable/Map;
   #67 = Utf8               updatedWith$
   #68 = Utf8               (Lscala/collection/immutable/SortedMapOps;Ljava/lang/Object;Lscala/Function1;)Lscala/collection/immutable/Map;
   #69 = Utf8               remappingFunction
   #70 = Utf8               updatedWith
   #71 = Utf8               (Ljava/lang/Object;Lscala/Function1;)Lscala/collection/immutable/Map;
   #72 = NameAndType        #70:#71       // updatedWith:(Ljava/lang/Object;Lscala/Function1;)Lscala/collection/immutable/Map;
   #73 = InterfaceMethodref #2.#72        // scala/collection/immutable/SortedMapOps.updatedWith:(Ljava/lang/Object;Lscala/Function1;)Lscala/collection/immutable/Map;
   #74 = Utf8               Ljava/lang/Object;
   #75 = Utf8               Lscala/Function1;
   #76 = Utf8               <V1:Ljava/lang/Object;>(TK;Lscala/Function1<Lscala/Option<TV;>;Lscala/Option<TV1;>;>;)TCC;
   #77 = Utf8               get
   #78 = Utf8               (Ljava/lang/Object;)Lscala/Option;
   #79 = NameAndType        #77:#78       // get:(Ljava/lang/Object;)Lscala/Option;
   #80 = InterfaceMethodref #2.#79        // scala/collection/immutable/SortedMapOps.get:(Ljava/lang/Object;)Lscala/Option;
   #81 = Utf8               scala/Function1
   #82 = Class              #81           // scala/Function1
   #83 = Utf8               apply
   #84 = Utf8               (Ljava/lang/Object;)Ljava/lang/Object;
   #85 = NameAndType        #83:#84       // apply:(Ljava/lang/Object;)Ljava/lang/Object;
   #86 = InterfaceMethodref #82.#85       // scala/Function1.apply:(Ljava/lang/Object;)Ljava/lang/Object;
   #87 = Utf8               scala/Option
   #88 = Class              #87           // scala/Option
   #89 = Utf8               (Ljava/lang/Object;Ljava/lang/Object;)V
   #90 = NameAndType        #37:#89       // "<init>":(Ljava/lang/Object;Ljava/lang/Object;)V
   #91 = Methodref          #57.#90       // scala/Tuple2."<init>":(Ljava/lang/Object;Ljava/lang/Object;)V
   #92 = Utf8               scala/None$
   #93 = Class              #92           // scala/None$
   #94 = Utf8               MODULE$
   #95 = Utf8               Lscala/None$;
   #96 = NameAndType        #94:#95       // MODULE$:Lscala/None$;
   #97 = Fieldref           #93.#96       // scala/None$.MODULE$:Lscala/None$;
   #98 = Utf8               equals
   #99 = Utf8               (Ljava/lang/Object;)Z
  #100 = NameAndType        #98:#99       // equals:(Ljava/lang/Object;)Z
  #101 = Methodref          #5.#100       // java/lang/Object.equals:(Ljava/lang/Object;)Z
  #102 = NameAndType        #22:#23       // coll:()Lscala/collection/immutable/SortedMapOps;
  #103 = InterfaceMethodref #2.#102       // scala/collection/immutable/SortedMapOps.coll:()Lscala/collection/immutable/SortedMapOps;
  #104 = Utf8               scala/collection/immutable/Map
  #105 = Class              #104          // scala/collection/immutable/Map
  #106 = Utf8               scala/Some
  #107 = Class              #106          // scala/Some
  #108 = Utf8               removed
  #109 = Utf8               (Ljava/lang/Object;)Lscala/collection/immutable/MapOps;
  #110 = NameAndType        #108:#109     // removed:(Ljava/lang/Object;)Lscala/collection/immutable/MapOps;
  #111 = InterfaceMethodref #2.#110       // scala/collection/immutable/SortedMapOps.removed:(Ljava/lang/Object;)Lscala/collection/immutable/MapOps;
  #112 = NameAndType        #46:#59       // value:()Ljava/lang/Object;
  #113 = Methodref          #107.#112     // scala/Some.value:()Ljava/lang/Object;
  #114 = Utf8               scala/MatchError
  #115 = Class              #114          // scala/MatchError
  #116 = Utf8               (Ljava/lang/Object;)V
  #117 = NameAndType        #37:#116      // "<init>":(Ljava/lang/Object;)V
  #118 = Methodref          #115.#117     // scala/MatchError."<init>":(Ljava/lang/Object;)V
  #119 = Utf8               v
  #120 = Utf8               previousValue
  #121 = Utf8               Lscala/Option;
  #122 = Utf8               nextValue
  #123 = Utf8               transform$
  #124 = Utf8               (Lscala/collection/immutable/SortedMapOps;Lscala/Function2;)Lscala/collection/immutable/Map;
  #125 = Utf8               f
  #126 = Utf8               transform
  #127 = Utf8               (Lscala/Function2;)Lscala/collection/immutable/Map;
  #128 = NameAndType        #126:#127     // transform:(Lscala/Function2;)Lscala/collection/immutable/Map;
  #129 = InterfaceMethodref #2.#128       // scala/collection/immutable/SortedMapOps.transform:(Lscala/Function2;)Lscala/collection/immutable/Map;
  #130 = Utf8               Lscala/Function2;
  #131 = Utf8               <W:Ljava/lang/Object;>(Lscala/Function2<TK;TV;TW;>;)TCC;
  #132 = MethodType         #84           //  (Ljava/lang/Object;)Ljava/lang/Object;
  #133 = Utf8               $anonfun$transform$1
  #134 = Utf8               (Lscala/Function2;Lscala/Tuple2;)Lscala/Tuple2;
  #135 = NameAndType        #133:#134     // $anonfun$transform$1:(Lscala/Function2;Lscala/Tuple2;)Lscala/Tuple2;
  #136 = InterfaceMethodref #2.#135       // scala/collection/immutable/SortedMapOps.$anonfun$transform$1:(Lscala/Function2;Lscala/Tuple2;)Lscala/Tuple2;
  #137 = MethodHandle       6:#136        // REF_invokeStatic scala/collection/immutable/SortedMapOps.$anonfun$transform$1:(Lscala/Function2;Lscala/Tuple2;)Lscala/Tuple2;
  #138 = Utf8               (Lscala/Tuple2;)Lscala/Tuple2;
  #139 = MethodType         #138          //  (Lscala/Tuple2;)Lscala/Tuple2;
  #140 = Integer            5
  #141 = Integer            1
  #142 = Utf8               java/lang/invoke/LambdaMetafactory
  #143 = Class              #142          // java/lang/invoke/LambdaMetafactory
  #144 = Utf8               altMetafactory
  #145 = Utf8               (Ljava/lang/invoke/MethodHandles$Lookup;Ljava/lang/String;Ljava/lang/invoke/MethodType;[Ljava/lang/Object;)Ljava/lang/invoke/CallSite;
  #146 = NameAndType        #144:#145     // altMetafactory:(Ljava/lang/invoke/MethodHandles$Lookup;Ljava/lang/String;Ljava/lang/invoke/MethodType;[Ljava/lang/Object;)Ljava/lang/invoke/CallSite;
  #147 = Methodref          #143.#146     // java/lang/invoke/LambdaMetafactory.altMetafactory:(Ljava/lang/invoke/MethodHandles$Lookup;Ljava/lang/String;Ljava/lang/invoke/MethodType;[Ljava/lang/Object;)Ljava/lang/invoke/CallSite;
  #148 = MethodHandle       6:#147        // REF_invokeStatic java/lang/invoke/LambdaMetafactory.altMetafactory:(Ljava/lang/invoke/MethodHandles$Lookup;Ljava/lang/String;Ljava/lang/invoke/MethodType;[Ljava/lang/Object;)Ljava/lang/invoke/CallSite;
  #149 = Utf8               (Lscala/Function2;)Lscala/Function1;
  #150 = NameAndType        #83:#149      // apply:(Lscala/Function2;)Lscala/Function1;
  #151 = InvokeDynamic      #0:#150       // #0:apply:(Lscala/Function2;)Lscala/Function1;
  #152 = Utf8               ordering
  #153 = Utf8               ()Lscala/math/Ordering;
  #154 = NameAndType        #152:#153     // ordering:()Lscala/math/Ordering;
  #155 = InterfaceMethodref #2.#154       // scala/collection/immutable/SortedMapOps.ordering:()Lscala/math/Ordering;
  #156 = Utf8               map
  #157 = Utf8               (Lscala/Function1;Lscala/math/Ordering;)Lscala/collection/Map;
  #158 = NameAndType        #156:#157     // map:(Lscala/Function1;Lscala/math/Ordering;)Lscala/collection/Map;
  #159 = InterfaceMethodref #2.#158       // scala/collection/immutable/SortedMapOps.map:(Lscala/Function1;Lscala/math/Ordering;)Lscala/collection/Map;
  #160 = Utf8               f$1
  #161 = Utf8               x0$1
  #162 = Utf8               scala/Function2
  #163 = Class              #162          // scala/Function2
  #164 = Utf8               (Ljava/lang/Object;Ljava/lang/Object;)Ljava/lang/Object;
  #165 = NameAndType        #83:#164      // apply:(Ljava/lang/Object;Ljava/lang/Object;)Ljava/lang/Object;
  #166 = InterfaceMethodref #163.#165     // scala/Function2.apply:(Ljava/lang/Object;Ljava/lang/Object;)Ljava/lang/Object;
  #167 = Utf8               k
  #168 = Utf8               $init$
  #169 = Utf8               $deserializeLambda$
  #170 = Utf8               (Ljava/lang/invoke/SerializedLambda;)Ljava/lang/Object;
  #171 = Utf8               scala/runtime/LambdaDeserialize
  #172 = Class              #171          // scala/runtime/LambdaDeserialize
  #173 = Utf8               bootstrap
  #174 = Utf8               (Ljava/lang/invoke/MethodHandles$Lookup;Ljava/lang/String;Ljava/lang/invoke/MethodType;[Ljava/lang/invoke/MethodHandle;)Ljava/lang/invoke/CallSite;
  #175 = NameAndType        #173:#174     // bootstrap:(Ljava/lang/invoke/MethodHandles$Lookup;Ljava/lang/String;Ljava/lang/invoke/MethodType;[Ljava/lang/invoke/MethodHandle;)Ljava/lang/invoke/CallSite;
  #176 = Methodref          #172.#175     // scala/runtime/LambdaDeserialize.bootstrap:(Ljava/lang/invoke/MethodHandles$Lookup;Ljava/lang/String;Ljava/lang/invoke/MethodType;[Ljava/lang/invoke/MethodHandle;)Ljava/lang/invoke/CallSite;
  #177 = MethodHandle       6:#176        // REF_invokeStatic scala/runtime/LambdaDeserialize.bootstrap:(Ljava/lang/invoke/MethodHandles$Lookup;Ljava/lang/String;Ljava/lang/invoke/MethodType;[Ljava/lang/invoke/MethodHandle;)Ljava/lang/invoke/CallSite;
  #178 = Utf8               lambdaDeserialize
  #179 = NameAndType        #178:#170     // lambdaDeserialize:(Ljava/lang/invoke/SerializedLambda;)Ljava/lang/Object;
  #180 = InvokeDynamic      #1:#179       // #1:lambdaDeserialize:(Ljava/lang/invoke/SerializedLambda;)Ljava/lang/Object;
  #181 = Utf8               Signature
  #182 = Utf8               Code
  #183 = Utf8               LineNumberTable
  #184 = Utf8               LocalVariableTable
  #185 = Utf8               MethodParameters
  #186 = Utf8               StackMapTable
  #187 = Utf8               InnerClasses
  #188 = Utf8               SourceFile
  #189 = Utf8               RuntimeVisibleAnnotations
  #190 = Utf8               BootstrapMethods
  #191 = Utf8               ScalaInlineInfo
  #192 = Utf8               ScalaSig
{
  public abstract C coll();
    descriptor: ()Lscala/collection/immutable/SortedMapOps;
    flags: (0x0401) ACC_PUBLIC, ACC_ABSTRACT
    Signature: #24                          // ()TC;

  public abstract scala.collection.immutable.Map<K, V> unsorted();
    descriptor: ()Lscala/collection/immutable/Map;
    flags: (0x0401) ACC_PUBLIC, ACC_ABSTRACT
    Signature: #27                          // ()Lscala/collection/immutable/Map<TK;TV;>;

  public static scala.collection.immutable.SortedSet keySet$(scala.collection.immutable.SortedMapOps);
    descriptor: (Lscala/collection/immutable/SortedMapOps;)Lscala/collection/immutable/SortedSet;
    flags: (0x1009) ACC_PUBLIC, ACC_STATIC, ACC_SYNTHETIC
    Code:
      stack=1, locals=1, args_size=1
         0: aload_0
         1: invokespecial #34                 // InterfaceMethod keySet:()Lscala/collection/immutable/SortedSet;
         4: areturn
      LineNumberTable:
        line 93: 0
      LocalVariableTable:
        Start  Length  Slot  Name   Signature
            0       5     0 $this   Lscala/collection/immutable/SortedMapOps;
    MethodParameters:
      Name                           Flags
      $this                          final synthetic

  public default scala.collection.immutable.SortedSet<K> keySet();
    descriptor: ()Lscala/collection/immutable/SortedSet;
    flags: (0x0001) ACC_PUBLIC
    Code:
      stack=3, locals=1, args_size=1
         0: new           #20                 // class scala/collection/immutable/SortedMapOps$ImmutableKeySortedSet
         3: dup
         4: aload_0
         5: invokespecial #40                 // Method scala/collection/immutable/SortedMapOps$ImmutableKeySortedSet."<init>":(Lscala/collection/immutable/SortedMapOps;)V
         8: areturn
      LineNumberTable:
        line 93: 0
      LocalVariableTable:
        Start  Length  Slot  Name   Signature
            0       9     0  this   Lscala/collection/immutable/SortedMapOps;
    Signature: #36                          // ()Lscala/collection/immutable/SortedSet<TK;>;

  public abstract <V1 extends java.lang.Object> CC updated(K, V1);
    descriptor: (Ljava/lang/Object;Ljava/lang/Object;)Lscala/collection/immutable/Map;
    flags: (0x0401) ACC_PUBLIC, ACC_ABSTRACT
    Signature: #44                          // <V1:Ljava/lang/Object;>(TK;TV1;)TCC;
    MethodParameters:
      Name                           Flags
      key                            final
      value                          final

  public static scala.collection.immutable.Map $plus$(scala.collection.immutable.SortedMapOps, scala.Tuple2);
    descriptor: (Lscala/collection/immutable/SortedMapOps;Lscala/Tuple2;)Lscala/collection/immutable/Map;
    flags: (0x1009) ACC_PUBLIC, ACC_STATIC, ACC_SYNTHETIC
    Code:
      stack=2, locals=2, args_size=2
         0: aload_0
         1: aload_1
         2: invokespecial #53                 // InterfaceMethod $plus:(Lscala/Tuple2;)Lscala/collection/immutable/Map;
         5: areturn
      LineNumberTable:
        line 107: 0
      LocalVariableTable:
        Start  Length  Slot  Name   Signature
            0       6     0 $this   Lscala/collection/immutable/SortedMapOps;
            0       6     1    kv   Lscala/Tuple2;
    MethodParameters:
      Name                           Flags
      $this                          final synthetic
      kv                             final

  public default <V1 extends java.lang.Object> CC $plus(scala.Tuple2<K, V1>);
    descriptor: (Lscala/Tuple2;)Lscala/collection/immutable/Map;
    flags: (0x0001) ACC_PUBLIC
    Code:
      stack=3, locals=2, args_size=2
         0: aload_0
         1: aload_1
         2: invokevirtual #61                 // Method scala/Tuple2._1:()Ljava/lang/Object;
         5: aload_1
         6: invokevirtual #64                 // Method scala/Tuple2._2:()Ljava/lang/Object;
         9: invokeinterface #66,  3           // InterfaceMethod updated:(Ljava/lang/Object;Ljava/lang/Object;)Lscala/collection/immutable/Map;
        14: areturn
      LineNumberTable:
        line 107: 0
      LocalVariableTable:
        Start  Length  Slot  Name   Signature
            0      15     0  this   Lscala/collection/immutable/SortedMapOps;
            0      15     1    kv   Lscala/Tuple2;
    Signature: #55                          // <V1:Ljava/lang/Object;>(Lscala/Tuple2<TK;TV1;>;)TCC;
    MethodParameters:
      Name                           Flags
      kv                             final

  public static scala.collection.immutable.Map updatedWith$(scala.collection.immutable.SortedMapOps, java.lang.Object, scala.Function1);
    descriptor: (Lscala/collection/immutable/SortedMapOps;Ljava/lang/Object;Lscala/Function1;)Lscala/collection/immutable/Map;
    flags: (0x1009) ACC_PUBLIC, ACC_STATIC, ACC_SYNTHETIC
    Code:
      stack=3, locals=3, args_size=3
         0: aload_0
         1: aload_1
         2: aload_2
         3: invokespecial #73                 // InterfaceMethod updatedWith:(Ljava/lang/Object;Lscala/Function1;)Lscala/collection/immutable/Map;
         6: areturn
      LineNumberTable:
        line 108: 0
      LocalVariableTable:
        Start  Length  Slot  Name   Signature
            0       7     0 $this   Lscala/collection/immutable/SortedMapOps;
            0       7     1   key   Ljava/lang/Object;
            0       7     2 remappingFunction   Lscala/Function1;
    MethodParameters:
      Name                           Flags
      $this                          final synthetic
      key                            final
      remappingFunction              final

  public default <V1 extends java.lang.Object> CC updatedWith(K, scala.Function1<scala.Option<V>, scala.Option<V1>>);
    descriptor: (Ljava/lang/Object;Lscala/Function1;)Lscala/collection/immutable/Map;
    flags: (0x0001) ACC_PUBLIC
    Code:
      stack=4, locals=8, args_size=3
         0: aload_0
         1: aload_1
         2: invokeinterface #80,  2           // InterfaceMethod get:(Ljava/lang/Object;)Lscala/Option;
         7: astore        4
         9: aload_2
        10: aload         4
        12: invokeinterface #86,  2           // InterfaceMethod scala/Function1.apply:(Ljava/lang/Object;)Ljava/lang/Object;
        17: checkcast     #88                 // class scala/Option
        20: astore        5
        22: new           #57                 // class scala/Tuple2
        25: dup
        26: aload         4
        28: aload         5
        30: invokespecial #91                 // Method scala/Tuple2."<init>":(Ljava/lang/Object;Ljava/lang/Object;)V
        33: astore        6
        35: getstatic     #97                 // Field scala/None$.MODULE$:Lscala/None$;
        38: aload         4
        40: invokevirtual #101                // Method java/lang/Object.equals:(Ljava/lang/Object;)Z
        43: ifeq          70
        46: getstatic     #97                 // Field scala/None$.MODULE$:Lscala/None$;
        49: aload         5
        51: invokevirtual #101                // Method java/lang/Object.equals:(Ljava/lang/Object;)Z
        54: ifeq          70
        57: aload_0
        58: invokeinterface #103,  1          // InterfaceMethod coll:()Lscala/collection/immutable/SortedMapOps;
        63: checkcast     #105                // class scala/collection/immutable/Map
        66: astore_3
        67: goto          152
        70: aload         4
        72: instanceof    #107                // class scala/Some
        75: ifeq          111
        78: getstatic     #97                 // Field scala/None$.MODULE$:Lscala/None$;
        81: aload         5
        83: invokevirtual #101                // Method java/lang/Object.equals:(Ljava/lang/Object;)Z
        86: ifeq          111
        89: aload_0
        90: aload_1
        91: invokeinterface #111,  2          // InterfaceMethod removed:(Ljava/lang/Object;)Lscala/collection/immutable/MapOps;
        96: checkcast     #2                  // class scala/collection/immutable/SortedMapOps
        99: invokeinterface #103,  1          // InterfaceMethod coll:()Lscala/collection/immutable/SortedMapOps;
       104: checkcast     #105                // class scala/collection/immutable/Map
       107: astore_3
       108: goto          152
       111: aload         5
       113: instanceof    #107                // class scala/Some
       116: ifeq          142
       119: aload         5
       121: checkcast     #107                // class scala/Some
       124: invokevirtual #113                // Method scala/Some.value:()Ljava/lang/Object;
       127: astore        7
       129: aload_0
       130: aload_1
       131: aload         7
       133: invokeinterface #66,  3           // InterfaceMethod updated:(Ljava/lang/Object;Ljava/lang/Object;)Lscala/collection/immutable/Map;
       138: astore_3
       139: goto          152
       142: new           #115                // class scala/MatchError
       145: dup
       146: aload         6
       148: invokespecial #118                // Method scala/MatchError."<init>":(Ljava/lang/Object;)V
       151: athrow
       152: aload_3
       153: areturn
      StackMapTable: number_of_entries = 4
        frame_type = 255 /* full_frame */
          offset_delta = 70
          locals = [ class scala/collection/immutable/SortedMapOps, class java/lang/Object, class scala/Function1, top, class scala/Option, class scala/Option, class scala/Tuple2 ]
          stack = []
        frame_type = 40 /* same */
        frame_type = 30 /* same */
        frame_type = 255 /* full_frame */
          offset_delta = 9
          locals = [ class scala/collection/immutable/SortedMapOps, class java/lang/Object, class scala/Function1, class scala/collection/immutable/Map, class scala/Option, class scala/Option, class scala/Tuple2 ]
          stack = []
      LineNumberTable:
        line 110: 0
        line 111: 9
        line 112: 22
        line 113: 35
        line 114: 70
        line 115: 111
        line 112: 142
      LocalVariableTable:
        Start  Length  Slot  Name   Signature
          129      13     7     v   Ljava/lang/Object;
            9     144     4 previousValue   Lscala/Option;
           22     131     5 nextValue   Lscala/Option;
            0     154     0  this   Lscala/collection/immutable/SortedMapOps;
            0     154     1   key   Ljava/lang/Object;
            0     154     2 remappingFunction   Lscala/Function1;
    Signature: #76                          // <V1:Ljava/lang/Object;>(TK;Lscala/Function1<Lscala/Option<TV;>;Lscala/Option<TV1;>;>;)TCC;
    MethodParameters:
      Name                           Flags
      key                            final
      remappingFunction              final

  public static scala.collection.immutable.Map transform$(scala.collection.immutable.SortedMapOps, scala.Function2);
    descriptor: (Lscala/collection/immutable/SortedMapOps;Lscala/Function2;)Lscala/collection/immutable/Map;
    flags: (0x1009) ACC_PUBLIC, ACC_STATIC, ACC_SYNTHETIC
    Code:
      stack=2, locals=2, args_size=2
         0: aload_0
         1: aload_1
         2: invokespecial #129                // InterfaceMethod transform:(Lscala/Function2;)Lscala/collection/immutable/Map;
         5: areturn
      LineNumberTable:
        line 118: 0
      LocalVariableTable:
        Start  Length  Slot  Name   Signature
            0       6     0 $this   Lscala/collection/immutable/SortedMapOps;
            0       6     1     f   Lscala/Function2;
    MethodParameters:
      Name                           Flags
      $this                          final synthetic
      f                              final

  public default <W extends java.lang.Object> CC transform(scala.Function2<K, V, W>);
    descriptor: (Lscala/Function2;)Lscala/collection/immutable/Map;
    flags: (0x0001) ACC_PUBLIC
    Code:
      stack=3, locals=2, args_size=2
         0: aload_0
         1: aload_1
         2: invokedynamic #151,  0            // InvokeDynamic #0:apply:(Lscala/Function2;)Lscala/Function1;
         7: aload_0
         8: invokeinterface #155,  1          // InterfaceMethod ordering:()Lscala/math/Ordering;
        13: invokeinterface #159,  3          // InterfaceMethod map:(Lscala/Function1;Lscala/math/Ordering;)Lscala/collection/Map;
        18: checkcast     #105                // class scala/collection/immutable/Map
        21: areturn
      LineNumberTable:
        line 118: 0
      LocalVariableTable:
        Start  Length  Slot  Name   Signature
            0      22     0  this   Lscala/collection/immutable/SortedMapOps;
            0      22     1     f   Lscala/Function2;
    Signature: #131                         // <W:Ljava/lang/Object;>(Lscala/Function2<TK;TV;TW;>;)TCC;
    MethodParameters:
      Name                           Flags
      f                              final

  public static scala.Tuple2 $anonfun$transform$1(scala.Function2, scala.Tuple2);
    descriptor: (Lscala/Function2;Lscala/Tuple2;)Lscala/Tuple2;
    flags: (0x1009) ACC_PUBLIC, ACC_STATIC, ACC_SYNTHETIC
    Code:
      stack=6, locals=5, args_size=2
         0: aload_1
         1: ifnull        36
         4: aload_1
         5: invokevirtual #61                 // Method scala/Tuple2._1:()Ljava/lang/Object;
         8: astore_3
         9: aload_1
        10: invokevirtual #64                 // Method scala/Tuple2._2:()Ljava/lang/Object;
        13: astore        4
        15: new           #57                 // class scala/Tuple2
        18: dup
        19: aload_3
        20: aload_0
        21: aload_3
        22: aload         4
        24: invokeinterface #166,  3          // InterfaceMethod scala/Function2.apply:(Ljava/lang/Object;Ljava/lang/Object;)Ljava/lang/Object;
        29: invokespecial #91                 // Method scala/Tuple2."<init>":(Ljava/lang/Object;Ljava/lang/Object;)V
        32: astore_2
        33: goto          45
        36: new           #115                // class scala/MatchError
        39: dup
        40: aconst_null
        41: invokespecial #118                // Method scala/MatchError."<init>":(Ljava/lang/Object;)V
        44: athrow
        45: aload_2
        46: areturn
      StackMapTable: number_of_entries = 2
        frame_type = 36 /* same */
        frame_type = 254 /* append */
          offset_delta = 8
          locals = [ class scala/Tuple2, class java/lang/Object, class java/lang/Object ]
      LineNumberTable:
        line 118: 0
      LocalVariableTable:
        Start  Length  Slot  Name   Signature
            9      27     3     k   Ljava/lang/Object;
           15      21     4     v   Ljava/lang/Object;
            0      47     0   f$1   Lscala/Function2;
            0      47     1  x0$1   Lscala/Tuple2;
    MethodParameters:
      Name                           Flags
      f$1                            final
      x0$1                           final

  public static void $init$(scala.collection.immutable.SortedMapOps);
    descriptor: (Lscala/collection/immutable/SortedMapOps;)V
    flags: (0x0009) ACC_PUBLIC, ACC_STATIC
    Code:
      stack=0, locals=1, args_size=1
         0: return
      LineNumberTable:
        line 87: 0
      LocalVariableTable:
        Start  Length  Slot  Name   Signature
            0       1     0 $this   Lscala/collection/immutable/SortedMapOps;
    MethodParameters:
      Name                           Flags
      $this                          final synthetic

  private static java.lang.Object $deserializeLambda$(java.lang.invoke.SerializedLambda);
    descriptor: (Ljava/lang/invoke/SerializedLambda;)Ljava/lang/Object;
    flags: (0x100a) ACC_PRIVATE, ACC_STATIC, ACC_SYNTHETIC
    Code:
      stack=1, locals=1, args_size=1
         0: aload_0
         1: invokedynamic #180,  0            // InvokeDynamic #1:lambdaDeserialize:(Ljava/lang/invoke/SerializedLambda;)Ljava/lang/Object;
         6: areturn
}
InnerClasses:
  public static final #18= #15 of #17;    // Lookup=class java/lang/invoke/MethodHandles$Lookup of class java/lang/invoke/MethodHandles
  public #21= #20 of #2;                  // ImmutableKeySortedSet=class scala/collection/immutable/SortedMapOps$ImmutableKeySortedSet of class scala/collection/immutable/SortedMapOps
Signature: #3                           // <K:Ljava/lang/Object;V:Ljava/lang/Object;CC:Lscala/collection/immutable/Map<Ljava/lang/Object;Ljava/lang/Object;>;C::Lscala/collection/immutable/SortedMapOps<TK;TV;TCC;TC;>;>Ljava/lang/Object;Lscala/collection/immutable/MapOps<TK;TV;Lscala/collection/immutable/Map;TC;>;Lscala/collection/SortedMapOps<TK;TV;TCC;TC;>;
SourceFile: "SortedMap.scala"
RuntimeVisibleAnnotations:
  0: #11(#12=s#13)
    scala.reflect.ScalaSignature(
      bytes="\u0006\u0005\u0005-da\u0002\b\u0010!\u0003\r\tA\u0006\u0005\u0006\u001b\u0002!\tA\u0014\u0005\u0006%\u00021\tb\u0015\u0005\u0006/\u00021\t\u0001\u0017\u0005\u00065\u0002!\te\u0017\u0004\u0005?\u0002A\u0001\rC\u0003m\u000b\u0011\u0005Q\u000eC\u0003p\u000b\u0011\u0005\u0001\u000fC\u0003y\u000b\u0011\u0005\u0011\u0010C\u0003}\u000b\u0011\u0005Q\u0010\u0003\u0004\u0000\u0001\u0019\u0005\u0011\u0011\u0001\u0005\b\u0003/\u0001AQIA\r\u0011\u001d\t)\u0004\u0001C!\u0003oAq!a\u0015\u0001\t\u0003\n)F\u0001\u0007T_J$X\rZ\'ba>\u00038O\u0003\u0002\u0011#\u0005I\u0011.\\7vi\u0006\u0014G.\u001a\u0006\u0003%M\t!bY8mY\u0016\u001cG/[8o\u0015\u0005!\u0012!B:dC2\f7\u0001A\u000b\u0006/\tbsGM\n\u0005\u0001aa\"\n\u0005\u0002\u001a55\t1#\u0003\u0002\u001c\'\t1\u0011I\\=SK\u001a\u0004b!\b\u0010!W9\nT\"A\b\n\u0005}y!AB\'ba>\u00038\u000f\u0005\u0002\"E1\u0001A!B\u0012\u0001\u0005\u0004!#!A&\u0012\u0005\u0015B\u0003CA\r\'\u0013\t93CA\u0004O_RD\u0017N\\4\u0011\u0005eI\u0013B\u0001\u0016\u0014\u0005\r\te.\u001f\t\u0003C1\"a!\f\u0001\u0005\u0006\u0004!#!\u0001,\u0011\u0005uy\u0013B\u0001\u0019\u0010\u0005\ri\u0015\r\u001d\t\u0003CI\"aa\r\u0001\u0005\u0006\u0004!$!A\"\u0012\u0005\u0015*\u0004CB\u000f\u0001A-2\u0014\u0007\u0005\u0002\"o\u00111\u0001\b\u0001CC\u0002e\u0012!aQ\"\u0016\u0007i\u00025)\u0005\u0002&wI\u0019AHP#\u0007\tu\u0002\u0001a\u000f\u0002\ryI,g-\u001b8f[\u0016tGO\u0010\t\u0005;=z$\t\u0005\u0002\"\u0001\u0012)\u0011i\u000eb\u0001I\t\t\u0001\f\u0005\u0002\"\u0007\u00121Ai\u000eCC\u0002\u0011\u0012\u0011!\u0017\u0019\u0003\r\"\u0003b!\b\u0001@\u0005Z:\u0005CA\u0011I\t%Iu\'!A\u0001\u0002\u000b\u0005AEA\u0002`IE\u0002ba\u0013\'!WY\nT\"A\t\n\u00059\t\u0012A\u0002\u0013j]&$H\u0005F\u0001P!\tI\u0002+\u0003\u0002R\'\t!QK\\5u\u0003\u0011\u0019w\u000e\u001c7\u0016\u0003Q\u00132!V\u0019W\r\u0011i\u0004\u0001\u0001+\u0011\t\u0005:\u0004eK\u0001\tk:\u001cxN\u001d;fIV\t\u0011\f\u0005\u0003\u001e_\u0001Z\u0013AB6fsN+G/F\u0001]!\riR\fI\u0005\u0003=>\u0011\u0011bU8si\u0016$7+\u001a;\u0003+%kW.\u001e;bE2,7*Z=T_J$X\rZ*fiN)Q!\u0019/eSB\u0019QD\u0019\u0011\n\u0005\r|!aC!cgR\u0014\u0018m\u0019;TKR\u0004\"!\u001a4\u000e\u0003\u0001I!a\u001a5\u0003\u0013\u001d+gnS3z\'\u0016$\u0018BA\u0010\u0012!\t)\'.\u0003\u0002l\u0019\nyq)\u001a8LKf\u001cvN\u001d;fIN+G/\u0001\u0004=S:LGO\u0010\u000b\u0002]B\u0011Q-B\u0001\ne\u0006tw-Z%na2$2\u0001X9w\u0011\u0015\u0011x\u00011\u0001t\u0003\u00111\'o\\7\u0011\u0007e!\b%\u0003\u0002v\'\t1q\n\u001d;j_:DQa^\u0004A\u0002M\fQ!\u001e8uS2\fA!\u001b8dYR\u0011AL\u001f\u0005\u0006w\"\u0001\r\u0001I\u0001\u0005K2,W.\u0001\u0003fq\u000edGC\u0001/\u007f\u0011\u0015Y\u0018\u00021\u0001!\u0003\u001d)\b\u000fZ1uK\u0012,B!a\u0001\u0002\nQ1\u0011QAA\b\u0003\'\u0001R!I\u001c!\u0003\u000f\u00012!IA\u0005\t\u001d\tYA\u0003b\u0001\u0003\u001b\u0011!AV\u0019\u0012\u0005-B\u0003BBA\t\u0015\u0001\u0007\u0001%A\u0002lKfDq!!\u0006\u000b\u0001\u0004\t9!A\u0003wC2,X-A\u0003%a2,8/\u0006\u0003\u0002\u001c\u0005\u0005B\u0003BA\u000f\u0003G\u0001R!I\u001c!\u0003?\u00012!IA\u0011\t\u001d\tYa\u0003b\u0001\u0003\u001bAq!!\n\f\u0001\u0004\t9#\u0001\u0002lmB1\u0011$!\u000b!\u0003?I1!a\u000b\u0014\u0005\u0019!V\u000f\u001d7fe!\u001a1\"a\f\u0011\u0007e\t\t$C\u0002\u00024M\u0011a!\u001b8mS:,\u0017aC;qI\u0006$X\rZ,ji\",B!!\u000f\u0002BQ!\u00111HA))\u0011\ti$a\u0011\u0011\u000b\u0005:\u0004%a\u0010\u0011\u0007\u0005\n\t\u0005B\u0004\u0002\f1\u0011\r!!\u0004\t\u000f\u0005\u0015C\u00021\u0001\u0002H\u0005\t\"/Z7baBLgn\u001a$v]\u000e$\u0018n\u001c8\u0011\u000fe\tI%!\u0014\u0002P%\u0019\u00111J\n\u0003\u0013\u0019+hn\u0019;j_:\f\u0004cA\ruWA!\u0011\u0004^A \u0011\u0019\t\t\u0002\u0004a\u0001A\u0005IAO]1og\u001a|\'/\\\u000b\u0005\u0003/\ni\u0006\u0006\u0003\u0002Z\u0005\u0005\u0004#B\u00118A\u0005m\u0003cA\u0011\u0002^\u00111\u0011qL\u0007C\u0002\u0011\u0012\u0011a\u0016\u0005\b\u0003Gj\u0001\u0019AA3\u0003\u00051\u0007cB\r\u0002h\u0001Z\u00131L\u0005\u0004\u0003S\u001a\"!\u0003$v]\u000e$\u0018n\u001c83\u0001"
    )
BootstrapMethods:
  0: #148 REF_invokeStatic java/lang/invoke/LambdaMetafactory.altMetafactory:(Ljava/lang/invoke/MethodHandles$Lookup;Ljava/lang/String;Ljava/lang/invoke/MethodType;[Ljava/lang/Object;)Ljava/lang/invoke/CallSite;
    Method arguments:
      #132 (Ljava/lang/Object;)Ljava/lang/Object;
      #137 REF_invokeStatic scala/collection/immutable/SortedMapOps.$anonfun$transform$1:(Lscala/Function2;Lscala/Tuple2;)Lscala/Tuple2;
      #139 (Lscala/Tuple2;)Lscala/Tuple2;
      #140 5
      #141 1
      #139 (Lscala/Tuple2;)Lscala/Tuple2;
  1: #177 REF_invokeStatic scala/runtime/LambdaDeserialize.bootstrap:(Ljava/lang/invoke/MethodHandles$Lookup;Ljava/lang/String;Ljava/lang/invoke/MethodType;[Ljava/lang/invoke/MethodHandle;)Ljava/lang/invoke/CallSite;
    Method arguments:
      #137 REF_invokeStatic scala/collection/immutable/SortedMapOps.$anonfun$transform$1:(Lscala/Function2;Lscala/Tuple2;)Lscala/Tuple2;
  ScalaInlineInfo: length = 0x45 (unknown attribute)
   01 00 00 0D 00 85 00 86 01 00 A8 00 26 01 00 32
   00 33 05 00 2F 00 30 05 00 16 00 17 00 00 1F 00
   20 00 00 1C 00 1D 01 00 7E 00 7F 00 00 7B 00 7C
   01 00 19 00 1A 00 00 2A 00 2B 00 00 46 00 47 00
   00 43 00 44 01
  ScalaSig: length = 0x3 (unknown attribute)
   05 02 00
