Classfile /Users/mw/Projects/slang-braindump/.jar/jar8/assemble/slang-braindump/assemble/content/scala/collection/immutable/TreeMap$TreeMapBuilder.class
  Last modified May 29, 2022; size 7770 bytes
  SHA-256 checksum 8d645007ee1d24decfc7a926887a2749f24373ce72ef72be1445b362044b863f
  Compiled from "TreeMap.scala"
public class scala.collection.immutable.TreeMap$TreeMapBuilder<K extends java.lang.Object, V extends java.lang.Object> extends scala.collection.immutable.RedBlackTree$MapHelper<K, V> implements scala.collection.mutable.ReusableBuilder<scala.Tuple2<K, V>, scala.collection.immutable.TreeMap<K, V>>
  minor version: 0
  major version: 52
  flags: (0x0021) ACC_PUBLIC, ACC_SUPER
  this_class: #2                          // scala/collection/immutable/TreeMap$TreeMapBuilder
  super_class: #5                         // scala/collection/immutable/RedBlackTree$MapHelper
  interfaces: 1, fields: 2, methods: 21, attributes: 5
Constant pool:
    #1 = Utf8               scala/collection/immutable/TreeMap$TreeMapBuilder
    #2 = Class              #1            // scala/collection/immutable/TreeMap$TreeMapBuilder
    #3 = Utf8               <K:Ljava/lang/Object;V:Ljava/lang/Object;>Lscala/collection/immutable/RedBlackTree$MapHelper<TK;TV;>;Lscala/collection/mutable/ReusableBuilder<Lscala/Tuple2<TK;TV;>;Lscala/collection/immutable/TreeMap<TK;TV;>;>;
    #4 = Utf8               scala/collection/immutable/RedBlackTree$MapHelper
    #5 = Class              #4            // scala/collection/immutable/RedBlackTree$MapHelper
    #6 = Utf8               scala/collection/mutable/ReusableBuilder
    #7 = Class              #6            // scala/collection/mutable/ReusableBuilder
    #8 = Utf8               TreeMap.scala
    #9 = Utf8               scala/collection/immutable/RedBlackTree$Helper
   #10 = Class              #9            // scala/collection/immutable/RedBlackTree$Helper
   #11 = Utf8               scala/collection/immutable/RedBlackTree
   #12 = Class              #11           // scala/collection/immutable/RedBlackTree
   #13 = Utf8               Helper
   #14 = Utf8               MapHelper
   #15 = Utf8               scala/collection/immutable/RedBlackTree$Tree
   #16 = Class              #15           // scala/collection/immutable/RedBlackTree$Tree
   #17 = Utf8               Tree
   #18 = Utf8               scala/collection/immutable/TreeMap
   #19 = Class              #18           // scala/collection/immutable/TreeMap
   #20 = Utf8               TreeMapBuilder
   #21 = Utf8               scala/collection/immutable/TreeMap$TreeMapBuilder$adder$
   #22 = Class              #21           // scala/collection/immutable/TreeMap$TreeMapBuilder$adder$
   #23 = Utf8               adder$
   #24 = Utf8               adder$module
   #25 = Utf8               Lscala/collection/immutable/TreeMap$TreeMapBuilder$adder$;
   #26 = Utf8               Lscala/collection/immutable/TreeMap$TreeMapBuilder<TK;TV;>.adder$;
   #27 = Utf8               scala$collection$immutable$TreeMap$TreeMapBuilder$$tree
   #28 = Utf8               Lscala/collection/immutable/RedBlackTree$Tree;
   #29 = Utf8               Lscala/collection/immutable/RedBlackTree$Tree<TK;TV;>;
   #30 = Utf8               sizeHint
   #31 = Utf8               (I)V
   #32 = Utf8               size
   #33 = Utf8               scala/collection/mutable/Builder
   #34 = Class              #33           // scala/collection/mutable/Builder
   #35 = Utf8               sizeHint$
   #36 = Utf8               (Lscala/collection/mutable/Builder;I)V
   #37 = NameAndType        #35:#36       // sizeHint$:(Lscala/collection/mutable/Builder;I)V
   #38 = InterfaceMethodref #34.#37       // scala/collection/mutable/Builder.sizeHint$:(Lscala/collection/mutable/Builder;I)V
   #39 = Utf8               this
   #40 = Utf8               Lscala/collection/immutable/TreeMap$TreeMapBuilder;
   #41 = Utf8               I
   #42 = Utf8               (Lscala/collection/IterableOnce;I)V
   #43 = Utf8               (Lscala/collection/IterableOnce<*>;I)V
   #44 = Utf8               coll
   #45 = Utf8               delta
   #46 = Utf8               (Lscala/collection/mutable/Builder;Lscala/collection/IterableOnce;I)V
   #47 = NameAndType        #35:#46       // sizeHint$:(Lscala/collection/mutable/Builder;Lscala/collection/IterableOnce;I)V
   #48 = InterfaceMethodref #34.#47       // scala/collection/mutable/Builder.sizeHint$:(Lscala/collection/mutable/Builder;Lscala/collection/IterableOnce;I)V
   #49 = Utf8               Lscala/collection/IterableOnce;
   #50 = Utf8               sizeHint$default$2
   #51 = Utf8               ()I
   #52 = Utf8               sizeHint$default$2$
   #53 = Utf8               (Lscala/collection/mutable/Builder;)I
   #54 = NameAndType        #52:#53       // sizeHint$default$2$:(Lscala/collection/mutable/Builder;)I
   #55 = InterfaceMethodref #34.#54       // scala/collection/mutable/Builder.sizeHint$default$2$:(Lscala/collection/mutable/Builder;)I
   #56 = Utf8               sizeHintBounded
   #57 = Utf8               (ILscala/collection/Iterable;)V
   #58 = Utf8               (ILscala/collection/Iterable<*>;)V
   #59 = Utf8               boundingColl
   #60 = Utf8               sizeHintBounded$
   #61 = Utf8               (Lscala/collection/mutable/Builder;ILscala/collection/Iterable;)V
   #62 = NameAndType        #60:#61       // sizeHintBounded$:(Lscala/collection/mutable/Builder;ILscala/collection/Iterable;)V
   #63 = InterfaceMethodref #34.#62       // scala/collection/mutable/Builder.sizeHintBounded$:(Lscala/collection/mutable/Builder;ILscala/collection/Iterable;)V
   #64 = Utf8               Lscala/collection/Iterable;
   #65 = Utf8               mapResult
   #66 = Utf8               (Lscala/Function1;)Lscala/collection/mutable/Builder;
   #67 = Utf8               <NewTo:Ljava/lang/Object;>(Lscala/Function1<Lscala/collection/immutable/TreeMap<TK;TV;>;TNewTo;>;)Lscala/collection/mutable/Builder<Lscala/Tuple2<TK;TV;>;TNewTo;>;
   #68 = Utf8               f
   #69 = Utf8               mapResult$
   #70 = Utf8               (Lscala/collection/mutable/Builder;Lscala/Function1;)Lscala/collection/mutable/Builder;
   #71 = NameAndType        #69:#70       // mapResult$:(Lscala/collection/mutable/Builder;Lscala/Function1;)Lscala/collection/mutable/Builder;
   #72 = InterfaceMethodref #34.#71       // scala/collection/mutable/Builder.mapResult$:(Lscala/collection/mutable/Builder;Lscala/Function1;)Lscala/collection/mutable/Builder;
   #73 = Utf8               Lscala/Function1;
   #74 = Utf8               $plus$eq
   #75 = Utf8               (Ljava/lang/Object;)Lscala/collection/mutable/Growable;
   #76 = Utf8               elem
   #77 = Utf8               scala/collection/mutable/Growable
   #78 = Class              #77           // scala/collection/mutable/Growable
   #79 = Utf8               $plus$eq$
   #80 = Utf8               (Lscala/collection/mutable/Growable;Ljava/lang/Object;)Lscala/collection/mutable/Growable;
   #81 = NameAndType        #79:#80       // $plus$eq$:(Lscala/collection/mutable/Growable;Ljava/lang/Object;)Lscala/collection/mutable/Growable;
   #82 = InterfaceMethodref #78.#81       // scala/collection/mutable/Growable.$plus$eq$:(Lscala/collection/mutable/Growable;Ljava/lang/Object;)Lscala/collection/mutable/Growable;
   #83 = Utf8               Ljava/lang/Object;
   #84 = Utf8               (Ljava/lang/Object;Ljava/lang/Object;Lscala/collection/immutable/Seq;)Lscala/collection/mutable/Growable;
   #85 = Utf8               elem1
   #86 = Utf8               elem2
   #87 = Utf8               elems
   #88 = Utf8               (Lscala/collection/mutable/Growable;Ljava/lang/Object;Ljava/lang/Object;Lscala/collection/immutable/Seq;)Lscala/collection/mutable/Growable;
   #89 = NameAndType        #79:#88       // $plus$eq$:(Lscala/collection/mutable/Growable;Ljava/lang/Object;Ljava/lang/Object;Lscala/collection/immutable/Seq;)Lscala/collection/mutable/Growable;
   #90 = InterfaceMethodref #78.#89       // scala/collection/mutable/Growable.$plus$eq$:(Lscala/collection/mutable/Growable;Ljava/lang/Object;Ljava/lang/Object;Lscala/collection/immutable/Seq;)Lscala/collection/mutable/Growable;
   #91 = Utf8               Lscala/collection/immutable/Seq;
   #92 = Utf8               $plus$plus$eq
   #93 = Utf8               (Lscala/collection/IterableOnce;)Lscala/collection/mutable/Growable;
   #94 = Utf8               (Lscala/collection/IterableOnce<Lscala/Tuple2<TK;TV;>;>;)Lscala/collection/mutable/Growable<Lscala/Tuple2<TK;TV;>;>;
   #95 = Utf8               xs
   #96 = Utf8               $plus$plus$eq$
   #97 = Utf8               (Lscala/collection/mutable/Growable;Lscala/collection/IterableOnce;)Lscala/collection/mutable/Growable;
   #98 = NameAndType        #96:#97       // $plus$plus$eq$:(Lscala/collection/mutable/Growable;Lscala/collection/IterableOnce;)Lscala/collection/mutable/Growable;
   #99 = InterfaceMethodref #78.#98       // scala/collection/mutable/Growable.$plus$plus$eq$:(Lscala/collection/mutable/Growable;Lscala/collection/IterableOnce;)Lscala/collection/mutable/Growable;
  #100 = Utf8               knownSize
  #101 = Utf8               knownSize$
  #102 = Utf8               (Lscala/collection/mutable/Growable;)I
  #103 = NameAndType        #101:#102     // knownSize$:(Lscala/collection/mutable/Growable;)I
  #104 = InterfaceMethodref #78.#103      // scala/collection/mutable/Growable.knownSize$:(Lscala/collection/mutable/Growable;)I
  #105 = Utf8               adder
  #106 = Utf8               ()Lscala/collection/immutable/TreeMap$TreeMapBuilder$adder$;
  #107 = Utf8               ()Lscala/collection/immutable/TreeMap$TreeMapBuilder<TK;TV;>.adder$;
  #108 = NameAndType        #24:#25       // adder$module:Lscala/collection/immutable/TreeMap$TreeMapBuilder$adder$;
  #109 = Fieldref           #2.#108       // scala/collection/immutable/TreeMap$TreeMapBuilder.adder$module:Lscala/collection/immutable/TreeMap$TreeMapBuilder$adder$;
  #110 = Utf8               adder$lzycompute$1
  #111 = Utf8               ()V
  #112 = NameAndType        #110:#111     // adder$lzycompute$1:()V
  #113 = Methodref          #2.#112       // scala/collection/immutable/TreeMap$TreeMapBuilder.adder$lzycompute$1:()V
  #114 = Utf8               ()Lscala/collection/immutable/RedBlackTree$Tree;
  #115 = Utf8               ()Lscala/collection/immutable/RedBlackTree$Tree<TK;TV;>;
  #116 = NameAndType        #27:#28       // scala$collection$immutable$TreeMap$TreeMapBuilder$$tree:Lscala/collection/immutable/RedBlackTree$Tree;
  #117 = Fieldref           #2.#116       // scala/collection/immutable/TreeMap$TreeMapBuilder.scala$collection$immutable$TreeMap$TreeMapBuilder$$tree:Lscala/collection/immutable/RedBlackTree$Tree;
  #118 = Utf8               scala$collection$immutable$TreeMap$TreeMapBuilder$$tree_$eq
  #119 = Utf8               (Lscala/collection/immutable/RedBlackTree$Tree;)V
  #120 = Utf8               (Lscala/collection/immutable/RedBlackTree$Tree<TK;TV;>;)V
  #121 = Utf8               x$1
  #122 = Utf8               addOne
  #123 = Utf8               (Lscala/Tuple2;)Lscala/collection/immutable/TreeMap$TreeMapBuilder;
  #124 = Utf8               (Lscala/Tuple2<TK;TV;>;)Lscala/collection/immutable/TreeMap$TreeMapBuilder<TK;TV;>;
  #125 = NameAndType        #27:#114      // scala$collection$immutable$TreeMap$TreeMapBuilder$$tree:()Lscala/collection/immutable/RedBlackTree$Tree;
  #126 = Methodref          #2.#125       // scala/collection/immutable/TreeMap$TreeMapBuilder.scala$collection$immutable$TreeMap$TreeMapBuilder$$tree:()Lscala/collection/immutable/RedBlackTree$Tree;
  #127 = Utf8               scala/Tuple2
  #128 = Class              #127          // scala/Tuple2
  #129 = Utf8               _1
  #130 = Utf8               ()Ljava/lang/Object;
  #131 = NameAndType        #129:#130     // _1:()Ljava/lang/Object;
  #132 = Methodref          #128.#131     // scala/Tuple2._1:()Ljava/lang/Object;
  #133 = Utf8               _2
  #134 = NameAndType        #133:#130     // _2:()Ljava/lang/Object;
  #135 = Methodref          #128.#134     // scala/Tuple2._2:()Ljava/lang/Object;
  #136 = Utf8               mutableUpd
  #137 = Utf8               (Lscala/collection/immutable/RedBlackTree$Tree;Ljava/lang/Object;Ljava/lang/Object;)Lscala/collection/immutable/RedBlackTree$Tree;
  #138 = NameAndType        #136:#137     // mutableUpd:(Lscala/collection/immutable/RedBlackTree$Tree;Ljava/lang/Object;Ljava/lang/Object;)Lscala/collection/immutable/RedBlackTree$Tree;
  #139 = Methodref          #2.#138       // scala/collection/immutable/TreeMap$TreeMapBuilder.mutableUpd:(Lscala/collection/immutable/RedBlackTree$Tree;Ljava/lang/Object;Ljava/lang/Object;)Lscala/collection/immutable/RedBlackTree$Tree;
  #140 = NameAndType        #118:#119     // scala$collection$immutable$TreeMap$TreeMapBuilder$$tree_$eq:(Lscala/collection/immutable/RedBlackTree$Tree;)V
  #141 = Methodref          #2.#140       // scala/collection/immutable/TreeMap$TreeMapBuilder.scala$collection$immutable$TreeMap$TreeMapBuilder$$tree_$eq:(Lscala/collection/immutable/RedBlackTree$Tree;)V
  #142 = Utf8               Lscala/Tuple2;
  #143 = Utf8               addAll
  #144 = Utf8               (Lscala/collection/IterableOnce;)Lscala/collection/immutable/TreeMap$TreeMapBuilder;
  #145 = Utf8               (Lscala/collection/IterableOnce<Lscala/Tuple2<TK;TV;>;>;)Lscala/collection/immutable/TreeMap$TreeMapBuilder<TK;TV;>;
  #146 = Utf8               ordering
  #147 = Utf8               ()Lscala/math/Ordering;
  #148 = NameAndType        #146:#147     // ordering:()Lscala/math/Ordering;
  #149 = Methodref          #19.#148      // scala/collection/immutable/TreeMap.ordering:()Lscala/math/Ordering;
  #150 = Methodref          #10.#148      // scala/collection/immutable/RedBlackTree$Helper.ordering:()Lscala/math/Ordering;
  #151 = Utf8               java/lang/Object
  #152 = Class              #151          // java/lang/Object
  #153 = Utf8               equals
  #154 = Utf8               (Ljava/lang/Object;)Z
  #155 = NameAndType        #153:#154     // equals:(Ljava/lang/Object;)Z
  #156 = Methodref          #152.#155     // java/lang/Object.equals:(Ljava/lang/Object;)Z
  #157 = Utf8               tree0
  #158 = NameAndType        #157:#114     // tree0:()Lscala/collection/immutable/RedBlackTree$Tree;
  #159 = Methodref          #19.#158      // scala/collection/immutable/TreeMap.tree0:()Lscala/collection/immutable/RedBlackTree$Tree;
  #160 = Utf8               scala/collection/immutable/RedBlackTree$
  #161 = Class              #160          // scala/collection/immutable/RedBlackTree$
  #162 = Utf8               MODULE$
  #163 = Utf8               Lscala/collection/immutable/RedBlackTree$;
  #164 = NameAndType        #162:#163     // MODULE$:Lscala/collection/immutable/RedBlackTree$;
  #165 = Fieldref           #161.#164     // scala/collection/immutable/RedBlackTree$.MODULE$:Lscala/collection/immutable/RedBlackTree$;
  #166 = Utf8               beforePublish
  #167 = Utf8               (Lscala/collection/immutable/RedBlackTree$Tree;)Lscala/collection/immutable/RedBlackTree$Tree;
  #168 = NameAndType        #166:#167     // beforePublish:(Lscala/collection/immutable/RedBlackTree$Tree;)Lscala/collection/immutable/RedBlackTree$Tree;
  #169 = Methodref          #2.#168       // scala/collection/immutable/TreeMap$TreeMapBuilder.beforePublish:(Lscala/collection/immutable/RedBlackTree$Tree;)Lscala/collection/immutable/RedBlackTree$Tree;
  #170 = Utf8               union
  #171 = Utf8               (Lscala/collection/immutable/RedBlackTree$Tree;Lscala/collection/immutable/RedBlackTree$Tree;Lscala/math/Ordering;)Lscala/collection/immutable/RedBlackTree$Tree;
  #172 = NameAndType        #170:#171     // union:(Lscala/collection/immutable/RedBlackTree$Tree;Lscala/collection/immutable/RedBlackTree$Tree;Lscala/math/Ordering;)Lscala/collection/immutable/RedBlackTree$Tree;
  #173 = Methodref          #161.#172     // scala/collection/immutable/RedBlackTree$.union:(Lscala/collection/immutable/RedBlackTree$Tree;Lscala/collection/immutable/RedBlackTree$Tree;Lscala/math/Ordering;)Lscala/collection/immutable/RedBlackTree$Tree;
  #174 = Utf8               scala/collection/Map
  #175 = Class              #174          // scala/collection/Map
  #176 = NameAndType        #105:#106     // adder:()Lscala/collection/immutable/TreeMap$TreeMapBuilder$adder$;
  #177 = Methodref          #2.#176       // scala/collection/immutable/TreeMap$TreeMapBuilder.adder:()Lscala/collection/immutable/TreeMap$TreeMapBuilder$adder$;
  #178 = Utf8               addForEach
  #179 = Utf8               (Lscala/collection/Map;)V
  #180 = NameAndType        #178:#179     // addForEach:(Lscala/collection/Map;)V
  #181 = Methodref          #22.#180      // scala/collection/immutable/TreeMap$TreeMapBuilder$adder$.addForEach:(Lscala/collection/Map;)V
  #182 = Utf8               addAll$
  #183 = NameAndType        #182:#97      // addAll$:(Lscala/collection/mutable/Growable;Lscala/collection/IterableOnce;)Lscala/collection/mutable/Growable;
  #184 = InterfaceMethodref #78.#183      // scala/collection/mutable/Growable.addAll$:(Lscala/collection/mutable/Growable;Lscala/collection/IterableOnce;)Lscala/collection/mutable/Growable;
  #185 = Utf8               scala/collection/IterableOnce
  #186 = Class              #185          // scala/collection/IterableOnce
  #187 = Utf8               scala/math/Ordering
  #188 = Class              #187          // scala/math/Ordering
  #189 = Utf8               clear
  #190 = Utf8               result
  #191 = Utf8               ()Lscala/collection/immutable/TreeMap;
  #192 = Utf8               ()Lscala/collection/immutable/TreeMap<TK;TV;>;
  #193 = Utf8               <init>
  #194 = Utf8               (Lscala/collection/immutable/RedBlackTree$Tree;Lscala/math/Ordering;)V
  #195 = NameAndType        #193:#194     // "<init>":(Lscala/collection/immutable/RedBlackTree$Tree;Lscala/math/Ordering;)V
  #196 = Methodref          #19.#195      // scala/collection/immutable/TreeMap."<init>":(Lscala/collection/immutable/RedBlackTree$Tree;Lscala/math/Ordering;)V
  #197 = NameAndType        #190:#191     // result:()Lscala/collection/immutable/TreeMap;
  #198 = Methodref          #2.#197       // scala/collection/immutable/TreeMap$TreeMapBuilder.result:()Lscala/collection/immutable/TreeMap;
  #199 = NameAndType        #143:#144     // addAll:(Lscala/collection/IterableOnce;)Lscala/collection/immutable/TreeMap$TreeMapBuilder;
  #200 = Methodref          #2.#199       // scala/collection/immutable/TreeMap$TreeMapBuilder.addAll:(Lscala/collection/IterableOnce;)Lscala/collection/immutable/TreeMap$TreeMapBuilder;
  #201 = NameAndType        #122:#123     // addOne:(Lscala/Tuple2;)Lscala/collection/immutable/TreeMap$TreeMapBuilder;
  #202 = Methodref          #2.#201       // scala/collection/immutable/TreeMap$TreeMapBuilder.addOne:(Lscala/Tuple2;)Lscala/collection/immutable/TreeMap$TreeMapBuilder;
  #203 = Utf8               (Lscala/collection/immutable/TreeMap$TreeMapBuilder;)V
  #204 = NameAndType        #193:#203     // "<init>":(Lscala/collection/immutable/TreeMap$TreeMapBuilder;)V
  #205 = Methodref          #22.#204      // scala/collection/immutable/TreeMap$TreeMapBuilder$adder$."<init>":(Lscala/collection/immutable/TreeMap$TreeMapBuilder;)V
  #206 = Utf8               java/lang/Throwable
  #207 = Class              #206          // java/lang/Throwable
  #208 = Utf8               (Lscala/math/Ordering;)V
  #209 = Utf8               (Lscala/math/Ordering<TK;>;)V
  #210 = NameAndType        #193:#208     // "<init>":(Lscala/math/Ordering;)V
  #211 = Methodref          #5.#210       // scala/collection/immutable/RedBlackTree$MapHelper."<init>":(Lscala/math/Ordering;)V
  #212 = Utf8               Lscala/math/Ordering;
  #213 = Utf8               Signature
  #214 = Utf8               Code
  #215 = Utf8               LineNumberTable
  #216 = Utf8               LocalVariableTable
  #217 = Utf8               MethodParameters
  #218 = Utf8               Deprecated
  #219 = Utf8               StackMapTable
  #220 = Utf8               InnerClasses
  #221 = Utf8               SourceFile
  #222 = Utf8               ScalaInlineInfo
  #223 = Utf8               Scala
{
  private volatile scala.collection.immutable.TreeMap$TreeMapBuilder<K, V>.adder$ adder$module;
    descriptor: Lscala/collection/immutable/TreeMap$TreeMapBuilder$adder$;
    flags: (0x0042) ACC_PRIVATE, ACC_VOLATILE
    Signature: #26                          // Lscala/collection/immutable/TreeMap$TreeMapBuilder<TK;TV;>.adder$;

  private scala.collection.immutable.RedBlackTree$Tree<K, V> scala$collection$immutable$TreeMap$TreeMapBuilder$$tree;
    descriptor: Lscala/collection/immutable/RedBlackTree$Tree;
    flags: (0x0002) ACC_PRIVATE
    Signature: #29                          // Lscala/collection/immutable/RedBlackTree$Tree<TK;TV;>;

  public void sizeHint(int);
    descriptor: (I)V
    flags: (0x0001) ACC_PUBLIC
    Code:
      stack=2, locals=2, args_size=2
         0: aload_0
         1: iload_1
         2: invokestatic  #38                 // InterfaceMethod scala/collection/mutable/Builder.sizeHint$:(Lscala/collection/mutable/Builder;I)V
         5: return
      LineNumberTable:
        line 319: 0
      LocalVariableTable:
        Start  Length  Slot  Name   Signature
            0       6     0  this   Lscala/collection/immutable/TreeMap$TreeMapBuilder;
            0       6     1  size   I
    MethodParameters:
      Name                           Flags
      size                           final

  public final void sizeHint(scala.collection.IterableOnce<?>, int);
    descriptor: (Lscala/collection/IterableOnce;I)V
    flags: (0x0011) ACC_PUBLIC, ACC_FINAL
    Code:
      stack=3, locals=3, args_size=3
         0: aload_0
         1: aload_1
         2: iload_2
         3: invokestatic  #48                 // InterfaceMethod scala/collection/mutable/Builder.sizeHint$:(Lscala/collection/mutable/Builder;Lscala/collection/IterableOnce;I)V
         6: return
      LineNumberTable:
        line 319: 0
      LocalVariableTable:
        Start  Length  Slot  Name   Signature
            0       7     0  this   Lscala/collection/immutable/TreeMap$TreeMapBuilder;
            0       7     1  coll   Lscala/collection/IterableOnce;
            0       7     2 delta   I
    Signature: #43                          // (Lscala/collection/IterableOnce<*>;I)V
    MethodParameters:
      Name                           Flags
      coll                           final
      delta                          final

  public final int sizeHint$default$2();
    descriptor: ()I
    flags: (0x0011) ACC_PUBLIC, ACC_FINAL
    Code:
      stack=1, locals=1, args_size=1
         0: aload_0
         1: invokestatic  #55                 // InterfaceMethod scala/collection/mutable/Builder.sizeHint$default$2$:(Lscala/collection/mutable/Builder;)I
         4: ireturn
      LineNumberTable:
        line 319: 0
      LocalVariableTable:
        Start  Length  Slot  Name   Signature
            0       5     0  this   Lscala/collection/immutable/TreeMap$TreeMapBuilder;

  public final void sizeHintBounded(int, scala.collection.Iterable<?>);
    descriptor: (ILscala/collection/Iterable;)V
    flags: (0x0011) ACC_PUBLIC, ACC_FINAL
    Code:
      stack=3, locals=3, args_size=3
         0: aload_0
         1: iload_1
         2: aload_2
         3: invokestatic  #63                 // InterfaceMethod scala/collection/mutable/Builder.sizeHintBounded$:(Lscala/collection/mutable/Builder;ILscala/collection/Iterable;)V
         6: return
      LineNumberTable:
        line 319: 0
      LocalVariableTable:
        Start  Length  Slot  Name   Signature
            0       7     0  this   Lscala/collection/immutable/TreeMap$TreeMapBuilder;
            0       7     1  size   I
            0       7     2 boundingColl   Lscala/collection/Iterable;
    Signature: #58                          // (ILscala/collection/Iterable<*>;)V
    MethodParameters:
      Name                           Flags
      size                           final
      boundingColl                   final

  public <NewTo extends java.lang.Object> scala.collection.mutable.Builder<scala.Tuple2<K, V>, NewTo> mapResult(scala.Function1<scala.collection.immutable.TreeMap<K, V>, NewTo>);
    descriptor: (Lscala/Function1;)Lscala/collection/mutable/Builder;
    flags: (0x0001) ACC_PUBLIC
    Code:
      stack=2, locals=2, args_size=2
         0: aload_0
         1: aload_1
         2: invokestatic  #72                 // InterfaceMethod scala/collection/mutable/Builder.mapResult$:(Lscala/collection/mutable/Builder;Lscala/Function1;)Lscala/collection/mutable/Builder;
         5: areturn
      LineNumberTable:
        line 319: 0
      LocalVariableTable:
        Start  Length  Slot  Name   Signature
            0       6     0  this   Lscala/collection/immutable/TreeMap$TreeMapBuilder;
            0       6     1     f   Lscala/Function1;
    Signature: #67                          // <NewTo:Ljava/lang/Object;>(Lscala/Function1<Lscala/collection/immutable/TreeMap<TK;TV;>;TNewTo;>;)Lscala/collection/mutable/Builder<Lscala/Tuple2<TK;TV;>;TNewTo;>;
    MethodParameters:
      Name                           Flags
      f                              final

  public final scala.collection.mutable.Growable $plus$eq(java.lang.Object);
    descriptor: (Ljava/lang/Object;)Lscala/collection/mutable/Growable;
    flags: (0x0011) ACC_PUBLIC, ACC_FINAL
    Code:
      stack=2, locals=2, args_size=2
         0: aload_0
         1: aload_1
         2: invokestatic  #82                 // InterfaceMethod scala/collection/mutable/Growable.$plus$eq$:(Lscala/collection/mutable/Growable;Ljava/lang/Object;)Lscala/collection/mutable/Growable;
         5: areturn
      LineNumberTable:
        line 319: 0
      LocalVariableTable:
        Start  Length  Slot  Name   Signature
            0       6     0  this   Lscala/collection/immutable/TreeMap$TreeMapBuilder;
            0       6     1  elem   Ljava/lang/Object;
    MethodParameters:
      Name                           Flags
      elem                           final

  public final scala.collection.mutable.Growable $plus$eq(java.lang.Object, java.lang.Object, scala.collection.immutable.Seq);
    descriptor: (Ljava/lang/Object;Ljava/lang/Object;Lscala/collection/immutable/Seq;)Lscala/collection/mutable/Growable;
    flags: (0x0011) ACC_PUBLIC, ACC_FINAL
    Code:
      stack=4, locals=4, args_size=4
         0: aload_0
         1: aload_1
         2: aload_2
         3: aload_3
         4: invokestatic  #90                 // InterfaceMethod scala/collection/mutable/Growable.$plus$eq$:(Lscala/collection/mutable/Growable;Ljava/lang/Object;Ljava/lang/Object;Lscala/collection/immutable/Seq;)Lscala/collection/mutable/Growable;
         7: areturn
      LineNumberTable:
        line 319: 0
      LocalVariableTable:
        Start  Length  Slot  Name   Signature
            0       8     0  this   Lscala/collection/immutable/TreeMap$TreeMapBuilder;
            0       8     1 elem1   Ljava/lang/Object;
            0       8     2 elem2   Ljava/lang/Object;
            0       8     3 elems   Lscala/collection/immutable/Seq;
    Deprecated: true
    MethodParameters:
      Name                           Flags
      elem1                          final
      elem2                          final
      elems                          final

  public final scala.collection.mutable.Growable<scala.Tuple2<K, V>> $plus$plus$eq(scala.collection.IterableOnce<scala.Tuple2<K, V>>);
    descriptor: (Lscala/collection/IterableOnce;)Lscala/collection/mutable/Growable;
    flags: (0x0011) ACC_PUBLIC, ACC_FINAL
    Code:
      stack=2, locals=2, args_size=2
         0: aload_0
         1: aload_1
         2: invokestatic  #99                 // InterfaceMethod scala/collection/mutable/Growable.$plus$plus$eq$:(Lscala/collection/mutable/Growable;Lscala/collection/IterableOnce;)Lscala/collection/mutable/Growable;
         5: areturn
      LineNumberTable:
        line 319: 0
      LocalVariableTable:
        Start  Length  Slot  Name   Signature
            0       6     0  this   Lscala/collection/immutable/TreeMap$TreeMapBuilder;
            0       6     1    xs   Lscala/collection/IterableOnce;
    Signature: #94                          // (Lscala/collection/IterableOnce<Lscala/Tuple2<TK;TV;>;>;)Lscala/collection/mutable/Growable<Lscala/Tuple2<TK;TV;>;>;
    MethodParameters:
      Name                           Flags
      xs                             final

  public int knownSize();
    descriptor: ()I
    flags: (0x0001) ACC_PUBLIC
    Code:
      stack=1, locals=1, args_size=1
         0: aload_0
         1: invokestatic  #104                // InterfaceMethod scala/collection/mutable/Growable.knownSize$:(Lscala/collection/mutable/Growable;)I
         4: ireturn
      LineNumberTable:
        line 319: 0
      LocalVariableTable:
        Start  Length  Slot  Name   Signature
            0       5     0  this   Lscala/collection/immutable/TreeMap$TreeMapBuilder;

  private scala.collection.immutable.TreeMap$TreeMapBuilder<K, V>.adder$ adder();
    descriptor: ()Lscala/collection/immutable/TreeMap$TreeMapBuilder$adder$;
    flags: (0x0002) ACC_PRIVATE
    Code:
      stack=1, locals=1, args_size=1
         0: aload_0
         1: getfield      #109                // Field adder$module:Lscala/collection/immutable/TreeMap$TreeMapBuilder$adder$;
         4: ifnonnull     11
         7: aload_0
         8: invokespecial #113                // Method adder$lzycompute$1:()V
        11: aload_0
        12: getfield      #109                // Field adder$module:Lscala/collection/immutable/TreeMap$TreeMapBuilder$adder$;
        15: areturn
      StackMapTable: number_of_entries = 1
        frame_type = 11 /* same */
      LineNumberTable:
        line 329: 0
      LocalVariableTable:
        Start  Length  Slot  Name   Signature
            0      16     0  this   Lscala/collection/immutable/TreeMap$TreeMapBuilder;
    Signature: #107                         // ()Lscala/collection/immutable/TreeMap$TreeMapBuilder<TK;TV;>.adder$;

  public scala.collection.immutable.RedBlackTree$Tree<K, V> scala$collection$immutable$TreeMap$TreeMapBuilder$$tree();
    descriptor: ()Lscala/collection/immutable/RedBlackTree$Tree;
    flags: (0x0001) ACC_PUBLIC
    Code:
      stack=1, locals=1, args_size=1
         0: aload_0
         1: getfield      #117                // Field scala$collection$immutable$TreeMap$TreeMapBuilder$$tree:Lscala/collection/immutable/RedBlackTree$Tree;
         4: areturn
      LineNumberTable:
        line 323: 0
      LocalVariableTable:
        Start  Length  Slot  Name   Signature
            0       5     0  this   Lscala/collection/immutable/TreeMap$TreeMapBuilder;
    Signature: #115                         // ()Lscala/collection/immutable/RedBlackTree$Tree<TK;TV;>;

  public void scala$collection$immutable$TreeMap$TreeMapBuilder$$tree_$eq(scala.collection.immutable.RedBlackTree$Tree<K, V>);
    descriptor: (Lscala/collection/immutable/RedBlackTree$Tree;)V
    flags: (0x0001) ACC_PUBLIC
    Code:
      stack=2, locals=2, args_size=2
         0: aload_0
         1: aload_1
         2: putfield      #117                // Field scala$collection$immutable$TreeMap$TreeMapBuilder$$tree:Lscala/collection/immutable/RedBlackTree$Tree;
         5: return
      LineNumberTable:
        line 323: 0
      LocalVariableTable:
        Start  Length  Slot  Name   Signature
            0       6     0  this   Lscala/collection/immutable/TreeMap$TreeMapBuilder;
            0       6     1   x$1   Lscala/collection/immutable/RedBlackTree$Tree;
    Signature: #120                         // (Lscala/collection/immutable/RedBlackTree$Tree<TK;TV;>;)V
    MethodParameters:
      Name                           Flags
      x$1                            final

  public scala.collection.immutable.TreeMap$TreeMapBuilder<K, V> addOne(scala.Tuple2<K, V>);
    descriptor: (Lscala/Tuple2;)Lscala/collection/immutable/TreeMap$TreeMapBuilder;
    flags: (0x0001) ACC_PUBLIC
    Code:
      stack=5, locals=2, args_size=2
         0: aload_0
         1: aload_0
         2: aload_0
         3: invokevirtual #126                // Method scala$collection$immutable$TreeMap$TreeMapBuilder$$tree:()Lscala/collection/immutable/RedBlackTree$Tree;
         6: aload_1
         7: invokevirtual #132                // Method scala/Tuple2._1:()Ljava/lang/Object;
        10: aload_1
        11: invokevirtual #135                // Method scala/Tuple2._2:()Ljava/lang/Object;
        14: invokevirtual #139                // Method mutableUpd:(Lscala/collection/immutable/RedBlackTree$Tree;Ljava/lang/Object;Ljava/lang/Object;)Lscala/collection/immutable/RedBlackTree$Tree;
        17: invokevirtual #141                // Method scala$collection$immutable$TreeMap$TreeMapBuilder$$tree_$eq:(Lscala/collection/immutable/RedBlackTree$Tree;)V
        20: aload_0
        21: areturn
      LineNumberTable:
        line 326: 0
        line 327: 20
      LocalVariableTable:
        Start  Length  Slot  Name   Signature
            0      22     0  this   Lscala/collection/immutable/TreeMap$TreeMapBuilder;
            0      22     1  elem   Lscala/Tuple2;
    Signature: #124                         // (Lscala/Tuple2<TK;TV;>;)Lscala/collection/immutable/TreeMap$TreeMapBuilder<TK;TV;>;
    MethodParameters:
      Name                           Flags
      elem                           final

  public scala.collection.immutable.TreeMap$TreeMapBuilder<K, V> addAll(scala.collection.IterableOnce<scala.Tuple2<K, V>>);
    descriptor: (Lscala/collection/IterableOnce;)Lscala/collection/immutable/TreeMap$TreeMapBuilder;
    flags: (0x0001) ACC_PUBLIC
    Code:
      stack=5, locals=5, args_size=2
         0: aload_1
         1: instanceof    #19                 // class scala/collection/immutable/TreeMap
         4: ifeq          87
         7: aload_1
         8: checkcast     #19                 // class scala/collection/immutable/TreeMap
        11: astore_2
        12: aload_2
        13: invokevirtual #149                // Method scala/collection/immutable/TreeMap.ordering:()Lscala/math/Ordering;
        16: aload_0
        17: invokespecial #150                // Method scala/collection/immutable/RedBlackTree$Helper.ordering:()Lscala/math/Ordering;
        20: astore_3
        21: dup
        22: ifnonnull     33
        25: pop
        26: aload_3
        27: ifnull        40
        30: goto          87
        33: aload_3
        34: invokevirtual #156                // Method java/lang/Object.equals:(Ljava/lang/Object;)Z
        37: ifeq          87
        40: aload_0
        41: invokevirtual #126                // Method scala$collection$immutable$TreeMap$TreeMapBuilder$$tree:()Lscala/collection/immutable/RedBlackTree$Tree;
        44: ifnonnull     58
        47: aload_0
        48: aload_2
        49: invokevirtual #159                // Method scala/collection/immutable/TreeMap.tree0:()Lscala/collection/immutable/RedBlackTree$Tree;
        52: invokevirtual #141                // Method scala$collection$immutable$TreeMap$TreeMapBuilder$$tree_$eq:(Lscala/collection/immutable/RedBlackTree$Tree;)V
        55: goto          118
        58: aload_0
        59: getstatic     #165                // Field scala/collection/immutable/RedBlackTree$.MODULE$:Lscala/collection/immutable/RedBlackTree$;
        62: aload_0
        63: aload_0
        64: invokevirtual #126                // Method scala$collection$immutable$TreeMap$TreeMapBuilder$$tree:()Lscala/collection/immutable/RedBlackTree$Tree;
        67: invokevirtual #169                // Method beforePublish:(Lscala/collection/immutable/RedBlackTree$Tree;)Lscala/collection/immutable/RedBlackTree$Tree;
        70: aload_2
        71: invokevirtual #159                // Method scala/collection/immutable/TreeMap.tree0:()Lscala/collection/immutable/RedBlackTree$Tree;
        74: aload_0
        75: invokespecial #150                // Method scala/collection/immutable/RedBlackTree$Helper.ordering:()Lscala/math/Ordering;
        78: invokevirtual #173                // Method scala/collection/immutable/RedBlackTree$.union:(Lscala/collection/immutable/RedBlackTree$Tree;Lscala/collection/immutable/RedBlackTree$Tree;Lscala/math/Ordering;)Lscala/collection/immutable/RedBlackTree$Tree;
        81: invokevirtual #141                // Method scala$collection$immutable$TreeMap$TreeMapBuilder$$tree_$eq:(Lscala/collection/immutable/RedBlackTree$Tree;)V
        84: goto          118
        87: aload_1
        88: instanceof    #175                // class scala/collection/Map
        91: ifeq          112
        94: aload_1
        95: checkcast     #175                // class scala/collection/Map
        98: astore        4
       100: aload_0
       101: invokespecial #177                // Method adder:()Lscala/collection/immutable/TreeMap$TreeMapBuilder$adder$;
       104: aload         4
       106: invokevirtual #181                // Method scala/collection/immutable/TreeMap$TreeMapBuilder$adder$.addForEach:(Lscala/collection/Map;)V
       109: goto          118
       112: aload_0
       113: aload_1
       114: invokestatic  #184                // InterfaceMethod scala/collection/mutable/Growable.addAll$:(Lscala/collection/mutable/Growable;Lscala/collection/IterableOnce;)Lscala/collection/mutable/Growable;
       117: pop
       118: aload_0
       119: areturn
      StackMapTable: number_of_entries = 6
        frame_type = 255 /* full_frame */
          offset_delta = 33
          locals = [ class scala/collection/immutable/TreeMap$TreeMapBuilder, class scala/collection/IterableOnce, class scala/collection/immutable/TreeMap, class scala/math/Ordering ]
          stack = [ class scala/math/Ordering ]
        frame_type = 6 /* same */
        frame_type = 17 /* same */
        frame_type = 249 /* chop */
          offset_delta = 28
        frame_type = 24 /* same */
        frame_type = 5 /* same */
      LineNumberTable:
        line 352: 0
        line 353: 40
        line 354: 58
        line 355: 87
        line 357: 100
        line 359: 112
        line 361: 118
      LocalVariableTable:
        Start  Length  Slot  Name   Signature
            0     120     0  this   Lscala/collection/immutable/TreeMap$TreeMapBuilder;
            0     120     1    xs   Lscala/collection/IterableOnce;
    Signature: #145                         // (Lscala/collection/IterableOnce<Lscala/Tuple2<TK;TV;>;>;)Lscala/collection/immutable/TreeMap$TreeMapBuilder<TK;TV;>;
    MethodParameters:
      Name                           Flags
      xs                             final

  public void clear();
    descriptor: ()V
    flags: (0x0001) ACC_PUBLIC
    Code:
      stack=2, locals=1, args_size=1
         0: aload_0
         1: aconst_null
         2: invokevirtual #141                // Method scala$collection$immutable$TreeMap$TreeMapBuilder$$tree_$eq:(Lscala/collection/immutable/RedBlackTree$Tree;)V
         5: return
      LineNumberTable:
        line 365: 0
      LocalVariableTable:
        Start  Length  Slot  Name   Signature
            0       6     0  this   Lscala/collection/immutable/TreeMap$TreeMapBuilder;

  public scala.collection.immutable.TreeMap<K, V> result();
    descriptor: ()Lscala/collection/immutable/TreeMap;
    flags: (0x0001) ACC_PUBLIC
    Code:
      stack=4, locals=1, args_size=1
         0: new           #19                 // class scala/collection/immutable/TreeMap
         3: dup
         4: aload_0
         5: aload_0
         6: invokevirtual #126                // Method scala$collection$immutable$TreeMap$TreeMapBuilder$$tree:()Lscala/collection/immutable/RedBlackTree$Tree;
         9: invokevirtual #169                // Method beforePublish:(Lscala/collection/immutable/RedBlackTree$Tree;)Lscala/collection/immutable/RedBlackTree$Tree;
        12: aload_0
        13: invokespecial #150                // Method scala/collection/immutable/RedBlackTree$Helper.ordering:()Lscala/math/Ordering;
        16: invokespecial #196                // Method scala/collection/immutable/TreeMap."<init>":(Lscala/collection/immutable/RedBlackTree$Tree;Lscala/math/Ordering;)V
        19: areturn
      LineNumberTable:
        line 368: 0
      LocalVariableTable:
        Start  Length  Slot  Name   Signature
            0      20     0  this   Lscala/collection/immutable/TreeMap$TreeMapBuilder;
    Signature: #192                         // ()Lscala/collection/immutable/TreeMap<TK;TV;>;

  public java.lang.Object result();
    descriptor: ()Ljava/lang/Object;
    flags: (0x1041) ACC_PUBLIC, ACC_BRIDGE, ACC_SYNTHETIC
    Code:
      stack=1, locals=1, args_size=1
         0: aload_0
         1: invokevirtual #198                // Method result:()Lscala/collection/immutable/TreeMap;
         4: areturn
      LineNumberTable:
        line 319: 0
      LocalVariableTable:
        Start  Length  Slot  Name   Signature
            0       5     0  this   Lscala/collection/immutable/TreeMap$TreeMapBuilder;

  public scala.collection.mutable.Growable addAll(scala.collection.IterableOnce);
    descriptor: (Lscala/collection/IterableOnce;)Lscala/collection/mutable/Growable;
    flags: (0x1041) ACC_PUBLIC, ACC_BRIDGE, ACC_SYNTHETIC
    Code:
      stack=2, locals=2, args_size=2
         0: aload_0
         1: aload_1
         2: invokevirtual #200                // Method addAll:(Lscala/collection/IterableOnce;)Lscala/collection/immutable/TreeMap$TreeMapBuilder;
         5: areturn
      LineNumberTable:
        line 319: 0
      LocalVariableTable:
        Start  Length  Slot  Name   Signature
            0       6     0  this   Lscala/collection/immutable/TreeMap$TreeMapBuilder;
            0       6     1    xs   Lscala/collection/IterableOnce;
    MethodParameters:
      Name                           Flags
      xs                             final

  public scala.collection.mutable.Growable addOne(java.lang.Object);
    descriptor: (Ljava/lang/Object;)Lscala/collection/mutable/Growable;
    flags: (0x1041) ACC_PUBLIC, ACC_BRIDGE, ACC_SYNTHETIC
    Code:
      stack=2, locals=2, args_size=2
         0: aload_0
         1: aload_1
         2: checkcast     #128                // class scala/Tuple2
         5: invokevirtual #202                // Method addOne:(Lscala/Tuple2;)Lscala/collection/immutable/TreeMap$TreeMapBuilder;
         8: areturn
      LineNumberTable:
        line 319: 0
      LocalVariableTable:
        Start  Length  Slot  Name   Signature
            0       9     0  this   Lscala/collection/immutable/TreeMap$TreeMapBuilder;
            0       9     1  elem   Ljava/lang/Object;
    MethodParameters:
      Name                           Flags
      elem                           final

  private final void adder$lzycompute$1();
    descriptor: ()V
    flags: (0x0012) ACC_PRIVATE, ACC_FINAL
    Code:
      stack=4, locals=1, args_size=1
         0: aload_0
         1: monitorenter
         2: aload_0
         3: getfield      #109                // Field adder$module:Lscala/collection/immutable/TreeMap$TreeMapBuilder$adder$;
         6: ifnonnull     21
         9: aload_0
        10: new           #22                 // class scala/collection/immutable/TreeMap$TreeMapBuilder$adder$
        13: dup
        14: aload_0
        15: invokespecial #205                // Method scala/collection/immutable/TreeMap$TreeMapBuilder$adder$."<init>":(Lscala/collection/immutable/TreeMap$TreeMapBuilder;)V
        18: putfield      #109                // Field adder$module:Lscala/collection/immutable/TreeMap$TreeMapBuilder$adder$;
        21: aload_0
        22: monitorexit
        23: return
        24: aload_0
        25: monitorexit
        26: athrow
      Exception table:
         from    to  target type
             2    21    24   any
      StackMapTable: number_of_entries = 2
        frame_type = 21 /* same */
        frame_type = 66 /* same_locals_1_stack_item */
          stack = [ class java/lang/Throwable ]
      LineNumberTable:
        line 329: 0
      LocalVariableTable:
        Start  Length  Slot  Name   Signature
            0      27     0  this   Lscala/collection/immutable/TreeMap$TreeMapBuilder;

  public scala.collection.immutable.TreeMap$TreeMapBuilder(scala.math.Ordering<K>);
    descriptor: (Lscala/math/Ordering;)V
    flags: (0x0001) ACC_PUBLIC
    Code:
      stack=2, locals=2, args_size=2
         0: aload_0
         1: aload_1
         2: invokespecial #211                // Method scala/collection/immutable/RedBlackTree$MapHelper."<init>":(Lscala/math/Ordering;)V
         5: aload_0
         6: aconst_null
         7: putfield      #117                // Field scala$collection$immutable$TreeMap$TreeMapBuilder$$tree:Lscala/collection/immutable/RedBlackTree$Tree;
        10: return
      LineNumberTable:
        line 320: 0
        line 323: 5
        line 319: 10
      LocalVariableTable:
        Start  Length  Slot  Name   Signature
            0      11     0  this   Lscala/collection/immutable/TreeMap$TreeMapBuilder;
            0      11     1 ordering   Lscala/math/Ordering;
    Signature: #209                         // (Lscala/math/Ordering<TK;>;)V
    MethodParameters:
      Name                           Flags
      ordering                       final
}
InnerClasses:
  public static abstract #13= #10 of #12; // Helper=class scala/collection/immutable/RedBlackTree$Helper of class scala/collection/immutable/RedBlackTree
  public static #14= #5 of #12;           // MapHelper=class scala/collection/immutable/RedBlackTree$MapHelper of class scala/collection/immutable/RedBlackTree
  public static final #17= #16 of #12;    // Tree=class scala/collection/immutable/RedBlackTree$Tree of class scala/collection/immutable/RedBlackTree
  private static #20= #2 of #19;          // TreeMapBuilder=class scala/collection/immutable/TreeMap$TreeMapBuilder of class scala/collection/immutable/TreeMap
  private #23= #22 of #2;                 // adder$=class scala/collection/immutable/TreeMap$TreeMapBuilder$adder$ of class scala/collection/immutable/TreeMap$TreeMapBuilder
Signature: #3                           // <K:Ljava/lang/Object;V:Ljava/lang/Object;>Lscala/collection/immutable/RedBlackTree$MapHelper<TK;TV;>;Lscala/collection/mutable/ReusableBuilder<Lscala/Tuple2<TK;TV;>;Lscala/collection/immutable/TreeMap<TK;TV;>;>;
SourceFile: "TreeMap.scala"
  ScalaInlineInfo: length = 0x6D (unknown attribute)
   01 00 00 15 00 4A 00 4B 05 00 4A 00 54 05 00 5C
   00 5D 05 00 C1 00 D0 00 00 8F 00 90 00 00 8F 00
   5D 00 00 7A 00 4B 00 00 7A 00 7B 00 00 69 00 6A
   01 00 6E 00 6F 01 00 BD 00 6F 00 00 64 00 33 00
   00 41 00 42 00 00 BE 00 82 00 00 BE 00 BF 00 00
   1B 00 72 01 00 76 00 77 01 00 1E 00 1F 00 00 1E
   00 2A 01 00 32 00 33 01 00 38 00 39 01
  Scala: length = 0x0 (unknown attribute)

