Classfile /Users/mw/Projects/slang-braindump/.jar/jar8/assemble/slang-braindump/assemble/content/scala/collection/immutable/TreeSet$sub$1$.class
  Last modified May 29, 2022; size 2328 bytes
  SHA-256 checksum 1daeb644929b1c4e6b7037fff751d542012de3a4c6d0b3d978b3ecda4d7058a6
  Compiled from "TreeSet.scala"
public class scala.collection.immutable.TreeSet$sub$1$ extends scala.runtime.AbstractFunction1<A, scala.runtime.BoxedUnit>
  minor version: 0
  major version: 52
  flags: (0x0021) ACC_PUBLIC, ACC_SUPER
  this_class: #2                          // scala/collection/immutable/TreeSet$sub$1$
  super_class: #5                         // scala/runtime/AbstractFunction1
  interfaces: 0, fields: 2, methods: 5, attributes: 6
Constant pool:
   #1 = Utf8               scala/collection/immutable/TreeSet$sub$1$
   #2 = Class              #1             // scala/collection/immutable/TreeSet$sub$1$
   #3 = Utf8               Lscala/runtime/AbstractFunction1<TA;Lscala/runtime/BoxedUnit;>;
   #4 = Utf8               scala/runtime/AbstractFunction1
   #5 = Class              #4             // scala/runtime/AbstractFunction1
   #6 = Utf8               TreeSet.scala
   #7 = Utf8               scala/collection/immutable/TreeSet
   #8 = Class              #7             // scala/collection/immutable/TreeSet
   #9 = Utf8               removedAll
  #10 = Utf8               (Lscala/collection/IterableOnce;)Lscala/collection/immutable/TreeSet;
  #11 = NameAndType        #9:#10         // removedAll:(Lscala/collection/IterableOnce;)Lscala/collection/immutable/TreeSet;
  #12 = Utf8               scala/collection/immutable/RedBlackTree$Tree
  #13 = Class              #12            // scala/collection/immutable/RedBlackTree$Tree
  #14 = Utf8               scala/collection/immutable/RedBlackTree
  #15 = Class              #14            // scala/collection/immutable/RedBlackTree
  #16 = Utf8               Tree
  #17 = Utf8               sub$1$
  #18 = Utf8               currentTree
  #19 = Utf8               Lscala/collection/immutable/RedBlackTree$Tree;
  #20 = Utf8               Lscala/collection/immutable/RedBlackTree$Tree<TA;Ljava/lang/Object;>;
  #21 = Utf8               $outer
  #22 = Utf8               Lscala/collection/immutable/TreeSet;
  #23 = Utf8               ()Lscala/collection/immutable/RedBlackTree$Tree;
  #24 = Utf8               ()Lscala/collection/immutable/RedBlackTree$Tree<TA;Ljava/lang/Object;>;
  #25 = NameAndType        #18:#19        // currentTree:Lscala/collection/immutable/RedBlackTree$Tree;
  #26 = Fieldref           #2.#25         // scala/collection/immutable/TreeSet$sub$1$.currentTree:Lscala/collection/immutable/RedBlackTree$Tree;
  #27 = Utf8               this
  #28 = Utf8               Lscala/collection/immutable/TreeSet$sub$1$;
  #29 = Utf8               currentTree_$eq
  #30 = Utf8               (Lscala/collection/immutable/RedBlackTree$Tree;)V
  #31 = Utf8               (Lscala/collection/immutable/RedBlackTree$Tree<TA;Ljava/lang/Object;>;)V
  #32 = Utf8               x$1
  #33 = Utf8               apply
  #34 = Utf8               (Ljava/lang/Object;)V
  #35 = Utf8               (TA;)V
  #36 = Utf8               k
  #37 = Utf8               scala/collection/immutable/RedBlackTree$
  #38 = Class              #37            // scala/collection/immutable/RedBlackTree$
  #39 = Utf8               MODULE$
  #40 = Utf8               Lscala/collection/immutable/RedBlackTree$;
  #41 = NameAndType        #39:#40        // MODULE$:Lscala/collection/immutable/RedBlackTree$;
  #42 = Fieldref           #38.#41        // scala/collection/immutable/RedBlackTree$.MODULE$:Lscala/collection/immutable/RedBlackTree$;
  #43 = NameAndType        #18:#23        // currentTree:()Lscala/collection/immutable/RedBlackTree$Tree;
  #44 = Methodref          #2.#43         // scala/collection/immutable/TreeSet$sub$1$.currentTree:()Lscala/collection/immutable/RedBlackTree$Tree;
  #45 = NameAndType        #21:#22        // $outer:Lscala/collection/immutable/TreeSet;
  #46 = Fieldref           #2.#45         // scala/collection/immutable/TreeSet$sub$1$.$outer:Lscala/collection/immutable/TreeSet;
  #47 = Utf8               ordering
  #48 = Utf8               ()Lscala/math/Ordering;
  #49 = NameAndType        #47:#48        // ordering:()Lscala/math/Ordering;
  #50 = Methodref          #8.#49         // scala/collection/immutable/TreeSet.ordering:()Lscala/math/Ordering;
  #51 = Utf8               delete
  #52 = Utf8               (Lscala/collection/immutable/RedBlackTree$Tree;Ljava/lang/Object;Lscala/math/Ordering;)Lscala/collection/immutable/RedBlackTree$Tree;
  #53 = NameAndType        #51:#52        // delete:(Lscala/collection/immutable/RedBlackTree$Tree;Ljava/lang/Object;Lscala/math/Ordering;)Lscala/collection/immutable/RedBlackTree$Tree;
  #54 = Methodref          #38.#53        // scala/collection/immutable/RedBlackTree$.delete:(Lscala/collection/immutable/RedBlackTree$Tree;Ljava/lang/Object;Lscala/math/Ordering;)Lscala/collection/immutable/RedBlackTree$Tree;
  #55 = NameAndType        #29:#30        // currentTree_$eq:(Lscala/collection/immutable/RedBlackTree$Tree;)V
  #56 = Methodref          #2.#55         // scala/collection/immutable/TreeSet$sub$1$.currentTree_$eq:(Lscala/collection/immutable/RedBlackTree$Tree;)V
  #57 = Utf8               Ljava/lang/Object;
  #58 = Utf8               (Ljava/lang/Object;)Ljava/lang/Object;
  #59 = Utf8               v1
  #60 = NameAndType        #33:#34        // apply:(Ljava/lang/Object;)V
  #61 = Methodref          #2.#60         // scala/collection/immutable/TreeSet$sub$1$.apply:(Ljava/lang/Object;)V
  #62 = Utf8               scala/runtime/BoxedUnit
  #63 = Class              #62            // scala/runtime/BoxedUnit
  #64 = Utf8               UNIT
  #65 = Utf8               Lscala/runtime/BoxedUnit;
  #66 = NameAndType        #64:#65        // UNIT:Lscala/runtime/BoxedUnit;
  #67 = Fieldref           #63.#66        // scala/runtime/BoxedUnit.UNIT:Lscala/runtime/BoxedUnit;
  #68 = Utf8               <init>
  #69 = Utf8               (Lscala/collection/immutable/TreeSet;)V
  #70 = Utf8               ()V
  #71 = NameAndType        #68:#70        // "<init>":()V
  #72 = Methodref          #5.#71         // scala/runtime/AbstractFunction1."<init>":()V
  #73 = Utf8               tree
  #74 = NameAndType        #73:#23        // tree:()Lscala/collection/immutable/RedBlackTree$Tree;
  #75 = Methodref          #8.#74         // scala/collection/immutable/TreeSet.tree:()Lscala/collection/immutable/RedBlackTree$Tree;
  #76 = Utf8               Signature
  #77 = Utf8               Code
  #78 = Utf8               LineNumberTable
  #79 = Utf8               LocalVariableTable
  #80 = Utf8               MethodParameters
  #81 = Utf8               StackMapTable
  #82 = Utf8               InnerClasses
  #83 = Utf8               EnclosingMethod
  #84 = Utf8               SourceFile
  #85 = Utf8               ScalaInlineInfo
  #86 = Utf8               Scala
{
  private scala.collection.immutable.RedBlackTree$Tree<A, java.lang.Object> currentTree;
    descriptor: Lscala/collection/immutable/RedBlackTree$Tree;
    flags: (0x0002) ACC_PRIVATE
    Signature: #20                          // Lscala/collection/immutable/RedBlackTree$Tree<TA;Ljava/lang/Object;>;

  private final scala.collection.immutable.TreeSet $outer;
    descriptor: Lscala/collection/immutable/TreeSet;
    flags: (0x1012) ACC_PRIVATE, ACC_FINAL, ACC_SYNTHETIC

  public scala.collection.immutable.RedBlackTree$Tree<A, java.lang.Object> currentTree();
    descriptor: ()Lscala/collection/immutable/RedBlackTree$Tree;
    flags: (0x0001) ACC_PUBLIC
    Code:
      stack=1, locals=1, args_size=1
         0: aload_0
         1: getfield      #26                 // Field currentTree:Lscala/collection/immutable/RedBlackTree$Tree;
         4: areturn
      LineNumberTable:
        line 193: 0
      LocalVariableTable:
        Start  Length  Slot  Name   Signature
            0       5     0  this   Lscala/collection/immutable/TreeSet$sub$1$;
    Signature: #24                          // ()Lscala/collection/immutable/RedBlackTree$Tree<TA;Ljava/lang/Object;>;

  public void currentTree_$eq(scala.collection.immutable.RedBlackTree$Tree<A, java.lang.Object>);
    descriptor: (Lscala/collection/immutable/RedBlackTree$Tree;)V
    flags: (0x0001) ACC_PUBLIC
    Code:
      stack=2, locals=2, args_size=2
         0: aload_0
         1: aload_1
         2: putfield      #26                 // Field currentTree:Lscala/collection/immutable/RedBlackTree$Tree;
         5: return
      LineNumberTable:
        line 193: 0
      LocalVariableTable:
        Start  Length  Slot  Name   Signature
            0       6     0  this   Lscala/collection/immutable/TreeSet$sub$1$;
            0       6     1   x$1   Lscala/collection/immutable/RedBlackTree$Tree;
    Signature: #31                          // (Lscala/collection/immutable/RedBlackTree$Tree<TA;Ljava/lang/Object;>;)V
    MethodParameters:
      Name                           Flags
      x$1                            final

  public void apply(A);
    descriptor: (Ljava/lang/Object;)V
    flags: (0x0001) ACC_PUBLIC
    Code:
      stack=5, locals=2, args_size=2
         0: aload_0
         1: getstatic     #42                 // Field scala/collection/immutable/RedBlackTree$.MODULE$:Lscala/collection/immutable/RedBlackTree$;
         4: aload_0
         5: invokevirtual #44                 // Method currentTree:()Lscala/collection/immutable/RedBlackTree$Tree;
         8: aload_1
         9: aload_0
        10: getfield      #46                 // Field $outer:Lscala/collection/immutable/TreeSet;
        13: invokevirtual #50                 // Method scala/collection/immutable/TreeSet.ordering:()Lscala/math/Ordering;
        16: invokevirtual #54                 // Method scala/collection/immutable/RedBlackTree$.delete:(Lscala/collection/immutable/RedBlackTree$Tree;Ljava/lang/Object;Lscala/math/Ordering;)Lscala/collection/immutable/RedBlackTree$Tree;
        19: invokevirtual #56                 // Method currentTree_$eq:(Lscala/collection/immutable/RedBlackTree$Tree;)V
        22: return
      LineNumberTable:
        line 195: 0
      LocalVariableTable:
        Start  Length  Slot  Name   Signature
            0      23     0  this   Lscala/collection/immutable/TreeSet$sub$1$;
            0      23     1     k   Ljava/lang/Object;
    Signature: #35                          // (TA;)V
    MethodParameters:
      Name                           Flags
      k                              final

  public java.lang.Object apply(java.lang.Object);
    descriptor: (Ljava/lang/Object;)Ljava/lang/Object;
    flags: (0x1041) ACC_PUBLIC, ACC_BRIDGE, ACC_SYNTHETIC
    Code:
      stack=2, locals=2, args_size=2
         0: aload_0
         1: aload_1
         2: invokevirtual #61                 // Method apply:(Ljava/lang/Object;)V
         5: getstatic     #67                 // Field scala/runtime/BoxedUnit.UNIT:Lscala/runtime/BoxedUnit;
         8: areturn
      LineNumberTable:
        line 192: 0
      LocalVariableTable:
        Start  Length  Slot  Name   Signature
            0       9     0  this   Lscala/collection/immutable/TreeSet$sub$1$;
            0       9     1    v1   Ljava/lang/Object;
    MethodParameters:
      Name                           Flags
      v1                             final

  public scala.collection.immutable.TreeSet$sub$1$(scala.collection.immutable.TreeSet);
    descriptor: (Lscala/collection/immutable/TreeSet;)V
    flags: (0x0001) ACC_PUBLIC
    Code:
      stack=2, locals=2, args_size=2
         0: aload_1
         1: ifnonnull     6
         4: aconst_null
         5: athrow
         6: aload_0
         7: aload_1
         8: putfield      #46                 // Field $outer:Lscala/collection/immutable/TreeSet;
        11: aload_0
        12: invokespecial #72                 // Method scala/runtime/AbstractFunction1."<init>":()V
        15: aload_0
        16: aload_1
        17: invokevirtual #75                 // Method scala/collection/immutable/TreeSet.tree:()Lscala/collection/immutable/RedBlackTree$Tree;
        20: putfield      #26                 // Field currentTree:Lscala/collection/immutable/RedBlackTree$Tree;
        23: return
      StackMapTable: number_of_entries = 1
        frame_type = 6 /* same */
      LineNumberTable:
        line 192: 0
        line 193: 15
        line 192: 23
      LocalVariableTable:
        Start  Length  Slot  Name   Signature
            0      24     0  this   Lscala/collection/immutable/TreeSet$sub$1$;
            0      24     1 $outer   Lscala/collection/immutable/TreeSet;
    MethodParameters:
      Name                           Flags
      $outer                         final synthetic
}
InnerClasses:
  public static final #16= #13 of #15;    // Tree=class scala/collection/immutable/RedBlackTree$Tree of class scala/collection/immutable/RedBlackTree
  public #17= #2;                         // sub$1$=class scala/collection/immutable/TreeSet$sub$1$
EnclosingMethod: #8.#11                 // scala.collection.immutable.TreeSet.removedAll
Signature: #3                           // Lscala/runtime/AbstractFunction1<TA;Lscala/runtime/BoxedUnit;>;
SourceFile: "TreeSet.scala"
  ScalaInlineInfo: length = 0x1D (unknown attribute)
   01 01 00 05 00 44 00 45 01 00 21 00 3A 01 00 21
   00 22 01 00 12 00 17 01 00 1D 00 1E 01
  Scala: length = 0x0 (unknown attribute)

