Classfile /Users/mw/Projects/slang-braindump/.jar/jar8/assemble/slang-braindump/assemble/content/scala/collection/immutable/TreeSeqMap$Ordering$Iterator.class
  Last modified May 29, 2022; size 2580 bytes
  SHA-256 checksum 6b885ae6d17378cce78c7d35d775629579e5277d6eaf245d7330480a30c849e8
  Compiled from "TreeSeqMap.scala"
public final class scala.collection.immutable.TreeSeqMap$Ordering$Iterator<V extends java.lang.Object> extends java.lang.Object
  minor version: 0
  major version: 52
  flags: (0x0031) ACC_PUBLIC, ACC_FINAL, ACC_SUPER
  this_class: #2                          // scala/collection/immutable/TreeSeqMap$Ordering$Iterator
  super_class: #5                         // java/lang/Object
  interfaces: 0, fields: 2, methods: 5, attributes: 5
Constant pool:
   #1 = Utf8               scala/collection/immutable/TreeSeqMap$Ordering$Iterator
   #2 = Class              #1             // scala/collection/immutable/TreeSeqMap$Ordering$Iterator
   #3 = Utf8               <V:Ljava/lang/Object;>Ljava/lang/Object;
   #4 = Utf8               java/lang/Object
   #5 = Class              #4             // java/lang/Object
   #6 = Utf8               TreeSeqMap.scala
   #7 = Utf8               scala/collection/immutable/TreeSeqMap$Ordering
   #8 = Class              #7             // scala/collection/immutable/TreeSeqMap$Ordering
   #9 = Utf8               scala/collection/immutable/TreeSeqMap
  #10 = Class              #9             // scala/collection/immutable/TreeSeqMap
  #11 = Utf8               Ordering
  #12 = Utf8               scala/collection/immutable/TreeSeqMap$Ordering$
  #13 = Class              #12            // scala/collection/immutable/TreeSeqMap$Ordering$
  #14 = Utf8               Ordering$
  #15 = Utf8               scala/collection/immutable/TreeSeqMap$Ordering$Bin
  #16 = Class              #15            // scala/collection/immutable/TreeSeqMap$Ordering$Bin
  #17 = Utf8               Bin
  #18 = Utf8               Iterator
  #19 = Utf8               scala/collection/immutable/TreeSeqMap$Ordering$Tip
  #20 = Class              #19            // scala/collection/immutable/TreeSeqMap$Ordering$Tip
  #21 = Utf8               Tip
  #22 = Utf8               scala/collection/immutable/TreeSeqMap$Ordering$Zero$
  #23 = Class              #22            // scala/collection/immutable/TreeSeqMap$Ordering$Zero$
  #24 = Utf8               Zero$
  #25 = Utf8               index
  #26 = Utf8               I
  #27 = Utf8               buffer
  #28 = Utf8               [Ljava/lang/Object;
  #29 = Utf8               pop
  #30 = Utf8               ()Lscala/collection/immutable/TreeSeqMap$Ordering;
  #31 = Utf8               ()Lscala/collection/immutable/TreeSeqMap$Ordering<TV;>;
  #32 = NameAndType        #25:#26        // index:I
  #33 = Fieldref           #2.#32         // scala/collection/immutable/TreeSeqMap$Ordering$Iterator.index:I
  #34 = NameAndType        #27:#28        // buffer:[Ljava/lang/Object;
  #35 = Fieldref           #2.#34         // scala/collection/immutable/TreeSeqMap$Ordering$Iterator.buffer:[Ljava/lang/Object;
  #36 = Utf8               this
  #37 = Utf8               Lscala/collection/immutable/TreeSeqMap$Ordering$Iterator;
  #38 = Utf8               push
  #39 = Utf8               (Lscala/collection/immutable/TreeSeqMap$Ordering;)V
  #40 = Utf8               <V2:Ljava/lang/Object;>(Lscala/collection/immutable/TreeSeqMap$Ordering<TV2;>;)V
  #41 = Utf8               x
  #42 = Utf8               Lscala/collection/immutable/TreeSeqMap$Ordering;
  #43 = Utf8               hasNext
  #44 = Utf8               ()Z
  #45 = Utf8               next
  #46 = Utf8               ()Ljava/lang/Object;
  #47 = Utf8               ()TV;
  #48 = NameAndType        #29:#30        // pop:()Lscala/collection/immutable/TreeSeqMap$Ordering;
  #49 = Methodref          #2.#48         // scala/collection/immutable/TreeSeqMap$Ordering$Iterator.pop:()Lscala/collection/immutable/TreeSeqMap$Ordering;
  #50 = Utf8               left
  #51 = NameAndType        #50:#30        // left:()Lscala/collection/immutable/TreeSeqMap$Ordering;
  #52 = Methodref          #16.#51        // scala/collection/immutable/TreeSeqMap$Ordering$Bin.left:()Lscala/collection/immutable/TreeSeqMap$Ordering;
  #53 = Utf8               right
  #54 = NameAndType        #53:#30        // right:()Lscala/collection/immutable/TreeSeqMap$Ordering;
  #55 = Methodref          #16.#54        // scala/collection/immutable/TreeSeqMap$Ordering$Bin.right:()Lscala/collection/immutable/TreeSeqMap$Ordering;
  #56 = Utf8               value
  #57 = NameAndType        #56:#46        // value:()Ljava/lang/Object;
  #58 = Methodref          #20.#57        // scala/collection/immutable/TreeSeqMap$Ordering$Tip.value:()Ljava/lang/Object;
  #59 = NameAndType        #38:#39        // push:(Lscala/collection/immutable/TreeSeqMap$Ordering;)V
  #60 = Methodref          #2.#59         // scala/collection/immutable/TreeSeqMap$Ordering$Iterator.push:(Lscala/collection/immutable/TreeSeqMap$Ordering;)V
  #61 = Utf8               MODULE$
  #62 = Utf8               Lscala/collection/immutable/TreeSeqMap$Ordering$Zero$;
  #63 = NameAndType        #61:#62        // MODULE$:Lscala/collection/immutable/TreeSeqMap$Ordering$Zero$;
  #64 = Fieldref           #23.#63        // scala/collection/immutable/TreeSeqMap$Ordering$Zero$.MODULE$:Lscala/collection/immutable/TreeSeqMap$Ordering$Zero$;
  #65 = Utf8               equals
  #66 = Utf8               (Ljava/lang/Object;)Z
  #67 = NameAndType        #65:#66        // equals:(Ljava/lang/Object;)Z
  #68 = Methodref          #5.#67         // java/lang/Object.equals:(Ljava/lang/Object;)Z
  #69 = Utf8               java/lang/IllegalStateException
  #70 = Class              #69            // java/lang/IllegalStateException
  #71 = Utf8               empty subtree not allowed
  #72 = String             #71            // empty subtree not allowed
  #73 = Utf8               <init>
  #74 = Utf8               (Ljava/lang/String;)V
  #75 = NameAndType        #73:#74        // "<init>":(Ljava/lang/String;)V
  #76 = Methodref          #70.#75        // java/lang/IllegalStateException."<init>":(Ljava/lang/String;)V
  #77 = Utf8               scala/MatchError
  #78 = Class              #77            // scala/MatchError
  #79 = Utf8               (Ljava/lang/Object;)V
  #80 = NameAndType        #73:#79        // "<init>":(Ljava/lang/Object;)V
  #81 = Methodref          #78.#80        // scala/MatchError."<init>":(Ljava/lang/Object;)V
  #82 = Utf8               v
  #83 = Utf8               Ljava/lang/Object;
  #84 = Utf8               (Lscala/collection/immutable/TreeSeqMap$Ordering<TV;>;)V
  #85 = Utf8               it
  #86 = Utf8               ()V
  #87 = NameAndType        #73:#86        // "<init>":()V
  #88 = Methodref          #5.#87         // java/lang/Object."<init>":()V
  #89 = Utf8               Code
  #90 = Utf8               LineNumberTable
  #91 = Utf8               LocalVariableTable
  #92 = Utf8               Signature
  #93 = Utf8               MethodParameters
  #94 = Utf8               StackMapTable
  #95 = Utf8               InnerClasses
  #96 = Utf8               SourceFile
  #97 = Utf8               ScalaInlineInfo
  #98 = Utf8               Scala
{
  private int index;
    descriptor: I
    flags: (0x0002) ACC_PRIVATE

  private final java.lang.Object[] buffer;
    descriptor: [Ljava/lang/Object;
    flags: (0x0012) ACC_PRIVATE, ACC_FINAL

  private scala.collection.immutable.TreeSeqMap$Ordering<V> pop();
    descriptor: ()Lscala/collection/immutable/TreeSeqMap$Ordering;
    flags: (0x0002) ACC_PRIVATE
    Code:
      stack=3, locals=1, args_size=1
         0: aload_0
         1: aload_0
         2: getfield      #33                 // Field index:I
         5: iconst_1
         6: isub
         7: putfield      #33                 // Field index:I
        10: aload_0
        11: getfield      #35                 // Field buffer:[Ljava/lang/Object;
        14: aload_0
        15: getfield      #33                 // Field index:I
        18: aaload
        19: checkcast     #8                  // class scala/collection/immutable/TreeSeqMap$Ordering
        22: areturn
      LineNumberTable:
        line 384: 0
        line 385: 10
      LocalVariableTable:
        Start  Length  Slot  Name   Signature
            0      23     0  this   Lscala/collection/immutable/TreeSeqMap$Ordering$Iterator;
    Signature: #31                          // ()Lscala/collection/immutable/TreeSeqMap$Ordering<TV;>;

  private <V2 extends java.lang.Object> void push(scala.collection.immutable.TreeSeqMap$Ordering<V2>);
    descriptor: (Lscala/collection/immutable/TreeSeqMap$Ordering;)V
    flags: (0x0002) ACC_PRIVATE
    Code:
      stack=3, locals=2, args_size=2
         0: aload_0
         1: getfield      #35                 // Field buffer:[Ljava/lang/Object;
         4: aload_0
         5: getfield      #33                 // Field index:I
         8: aload_1
         9: aastore
        10: aload_0
        11: aload_0
        12: getfield      #33                 // Field index:I
        15: iconst_1
        16: iadd
        17: putfield      #33                 // Field index:I
        20: return
      LineNumberTable:
        line 389: 0
        line 390: 10
      LocalVariableTable:
        Start  Length  Slot  Name   Signature
            0      21     0  this   Lscala/collection/immutable/TreeSeqMap$Ordering$Iterator;
            0      21     1     x   Lscala/collection/immutable/TreeSeqMap$Ordering;
    Signature: #40                          // <V2:Ljava/lang/Object;>(Lscala/collection/immutable/TreeSeqMap$Ordering<TV2;>;)V
    MethodParameters:
      Name                           Flags
      x                              final

  public boolean hasNext();
    descriptor: ()Z
    flags: (0x0001) ACC_PUBLIC
    Code:
      stack=2, locals=1, args_size=1
         0: aload_0
         1: getfield      #33                 // Field index:I
         4: iconst_0
         5: if_icmpeq     10
         8: iconst_1
         9: ireturn
        10: iconst_0
        11: ireturn
      StackMapTable: number_of_entries = 1
        frame_type = 10 /* same */
      LineNumberTable:
        line 395: 0
      LocalVariableTable:
        Start  Length  Slot  Name   Signature
            0      12     0  this   Lscala/collection/immutable/TreeSeqMap$Ordering$Iterator;

  public V next();
    descriptor: ()Ljava/lang/Object;
    flags: (0x0001) ACC_PUBLIC
    Code:
      stack=3, locals=10, args_size=1
         0: iconst_0
         1: istore_2
         2: aconst_null
         3: astore_3
         4: aload_0
         5: invokespecial #49                 // Method pop:()Lscala/collection/immutable/TreeSeqMap$Ordering;
         8: astore        4
        10: aload         4
        12: instanceof    #16                 // class scala/collection/immutable/TreeSeqMap$Ordering$Bin
        15: ifeq          68
        18: iconst_1
        19: istore_2
        20: aload         4
        22: checkcast     #16                 // class scala/collection/immutable/TreeSeqMap$Ordering$Bin
        25: astore_3
        26: aload_3
        27: invokevirtual #52                 // Method scala/collection/immutable/TreeSeqMap$Ordering$Bin.left:()Lscala/collection/immutable/TreeSeqMap$Ordering;
        30: astore        5
        32: aload_3
        33: invokevirtual #55                 // Method scala/collection/immutable/TreeSeqMap$Ordering$Bin.right:()Lscala/collection/immutable/TreeSeqMap$Ordering;
        36: astore        6
        38: aload         5
        40: instanceof    #20                 // class scala/collection/immutable/TreeSeqMap$Ordering$Tip
        43: ifeq          68
        46: aload         5
        48: checkcast     #20                 // class scala/collection/immutable/TreeSeqMap$Ordering$Tip
        51: invokevirtual #58                 // Method scala/collection/immutable/TreeSeqMap$Ordering$Tip.value:()Ljava/lang/Object;
        54: astore        7
        56: aload_0
        57: aload         6
        59: invokespecial #60                 // Method push:(Lscala/collection/immutable/TreeSeqMap$Ordering;)V
        62: aload         7
        64: astore_1
        65: goto          150
        68: iload_2
        69: ifeq          99
        72: aload_3
        73: invokevirtual #52                 // Method scala/collection/immutable/TreeSeqMap$Ordering$Bin.left:()Lscala/collection/immutable/TreeSeqMap$Ordering;
        76: astore        8
        78: aload_3
        79: invokevirtual #55                 // Method scala/collection/immutable/TreeSeqMap$Ordering$Bin.right:()Lscala/collection/immutable/TreeSeqMap$Ordering;
        82: astore        9
        84: aload_0
        85: aload         9
        87: invokespecial #60                 // Method push:(Lscala/collection/immutable/TreeSeqMap$Ordering;)V
        90: aload_0
        91: aload         8
        93: invokespecial #60                 // Method push:(Lscala/collection/immutable/TreeSeqMap$Ordering;)V
        96: goto          0
        99: aload         4
       101: instanceof    #20                 // class scala/collection/immutable/TreeSeqMap$Ordering$Tip
       104: ifeq          119
       107: aload         4
       109: checkcast     #20                 // class scala/collection/immutable/TreeSeqMap$Ordering$Tip
       112: invokevirtual #58                 // Method scala/collection/immutable/TreeSeqMap$Ordering$Tip.value:()Ljava/lang/Object;
       115: astore_1
       116: goto          150
       119: getstatic     #64                 // Field scala/collection/immutable/TreeSeqMap$Ordering$Zero$.MODULE$:Lscala/collection/immutable/TreeSeqMap$Ordering$Zero$;
       122: aload         4
       124: invokevirtual #68                 // Method java/lang/Object.equals:(Ljava/lang/Object;)Z
       127: ifeq          140
       130: new           #70                 // class java/lang/IllegalStateException
       133: dup
       134: ldc           #72                 // String empty subtree not allowed
       136: invokespecial #76                 // Method java/lang/IllegalStateException."<init>":(Ljava/lang/String;)V
       139: athrow
       140: new           #78                 // class scala/MatchError
       143: dup
       144: aload         4
       146: invokespecial #81                 // Method scala/MatchError."<init>":(Ljava/lang/Object;)V
       149: athrow
       150: aload_1
       151: areturn
      StackMapTable: number_of_entries = 6
        frame_type = 0 /* same */
        frame_type = 255 /* full_frame */
          offset_delta = 67
          locals = [ class scala/collection/immutable/TreeSeqMap$Ordering$Iterator, top, int, class scala/collection/immutable/TreeSeqMap$Ordering$Bin, class scala/collection/immutable/TreeSeqMap$Ordering ]
          stack = []
        frame_type = 30 /* same */
        frame_type = 19 /* same */
        frame_type = 20 /* same */
        frame_type = 255 /* full_frame */
          offset_delta = 9
          locals = [ class scala/collection/immutable/TreeSeqMap$Ordering$Iterator, class java/lang/Object, int, class scala/collection/immutable/TreeSeqMap$Ordering$Bin, class scala/collection/immutable/TreeSeqMap$Ordering ]
          stack = []
      LineNumberTable:
        line 398: 0
        line 399: 10
        line 400: 56
        line 401: 62
        line 402: 68
        line 403: 84
        line 404: 90
        line 405: 96
        line 406: 99
        line 409: 119
        line 398: 140
      LocalVariableTable:
        Start  Length  Slot  Name   Signature
           56      12     7     v   Ljava/lang/Object;
           38      30     6 right   Lscala/collection/immutable/TreeSeqMap$Ordering;
           78      21     8  left   Lscala/collection/immutable/TreeSeqMap$Ordering;
           84      15     9 right   Lscala/collection/immutable/TreeSeqMap$Ordering;
            0     152     0  this   Lscala/collection/immutable/TreeSeqMap$Ordering$Iterator;
    Signature: #47                          // ()TV;

  public scala.collection.immutable.TreeSeqMap$Ordering$Iterator(scala.collection.immutable.TreeSeqMap$Ordering<V>);
    descriptor: (Lscala/collection/immutable/TreeSeqMap$Ordering;)V
    flags: (0x0001) ACC_PUBLIC
    Code:
      stack=2, locals=3, args_size=2
         0: aload_0
         1: invokespecial #88                 // Method java/lang/Object."<init>":()V
         4: aload_0
         5: iconst_0
         6: putfield      #33                 // Field index:I
         9: aload_0
        10: bipush        33
        12: anewarray     #5                  // class java/lang/Object
        15: putfield      #35                 // Field buffer:[Ljava/lang/Object;
        18: aload_1
        19: getstatic     #64                 // Field scala/collection/immutable/TreeSeqMap$Ordering$Zero$.MODULE$:Lscala/collection/immutable/TreeSeqMap$Ordering$Zero$;
        22: astore_2
        23: dup
        24: ifnonnull     31
        27: pop
        28: goto          38
        31: aload_2
        32: invokevirtual #68                 // Method java/lang/Object.equals:(Ljava/lang/Object;)Z
        35: ifne          43
        38: aload_0
        39: aload_1
        40: invokespecial #60                 // Method push:(Lscala/collection/immutable/TreeSeqMap$Ordering;)V
        43: return
      StackMapTable: number_of_entries = 3
        frame_type = 255 /* full_frame */
          offset_delta = 31
          locals = [ class scala/collection/immutable/TreeSeqMap$Ordering$Iterator, class scala/collection/immutable/TreeSeqMap$Ordering, class scala/collection/immutable/TreeSeqMap$Ordering$Zero$ ]
          stack = [ class scala/collection/immutable/TreeSeqMap$Ordering ]
        frame_type = 6 /* same */
        frame_type = 4 /* same */
      LineNumberTable:
        line 375: 0
        line 380: 4
        line 381: 9
        line 393: 18
        line 375: 43
      LocalVariableTable:
        Start  Length  Slot  Name   Signature
            0      44     0  this   Lscala/collection/immutable/TreeSeqMap$Ordering$Iterator;
            0      44     1    it   Lscala/collection/immutable/TreeSeqMap$Ordering;
    Signature: #84                          // (Lscala/collection/immutable/TreeSeqMap$Ordering<TV;>;)V
    MethodParameters:
      Name                           Flags
      it                             final
}
InnerClasses:
  public static abstract #11= #8 of #10;  // Ordering=class scala/collection/immutable/TreeSeqMap$Ordering of class scala/collection/immutable/TreeSeqMap
  public static #14= #13 of #10;          // Ordering$=class scala/collection/immutable/TreeSeqMap$Ordering$ of class scala/collection/immutable/TreeSeqMap
  public static final #17= #16 of #13;    // Bin=class scala/collection/immutable/TreeSeqMap$Ordering$Bin of class scala/collection/immutable/TreeSeqMap$Ordering$
  public static final #18= #2 of #13;     // Iterator=class scala/collection/immutable/TreeSeqMap$Ordering$Iterator of class scala/collection/immutable/TreeSeqMap$Ordering$
  public static final #21= #20 of #13;    // Tip=class scala/collection/immutable/TreeSeqMap$Ordering$Tip of class scala/collection/immutable/TreeSeqMap$Ordering$
  public static #24= #23 of #13;          // Zero$=class scala/collection/immutable/TreeSeqMap$Ordering$Zero$ of class scala/collection/immutable/TreeSeqMap$Ordering$
Signature: #3                           // <V:Ljava/lang/Object;>Ljava/lang/Object;
SourceFile: "TreeSeqMap.scala"
  ScalaInlineInfo: length = 0x1D (unknown attribute)
   01 01 00 05 00 49 00 27 01 00 2B 00 2C 01 00 2D
   00 2E 01 00 1D 00 1E 01 00 26 00 27 01
  Scala: length = 0x0 (unknown attribute)

