Classfile /Users/mw/Projects/slang-braindump/.jar/jar8/assemble/slang-braindump/assemble/content/scala/collection/immutable/TreeMap$TreeMapBuilder$adder$.class
  Last modified May 29, 2022; size 2342 bytes
  SHA-256 checksum ed514bfc6afb6e8a3cf88d92801fffcdea2117ed07d24baa74ff9be057cd6f98
  Compiled from "TreeMap.scala"
public class scala.collection.immutable.TreeMap$TreeMapBuilder$adder$ extends scala.runtime.AbstractFunction2<K, V, scala.runtime.BoxedUnit>
  minor version: 0
  major version: 52
  flags: (0x0021) ACC_PUBLIC, ACC_SUPER
  this_class: #2                          // scala/collection/immutable/TreeMap$TreeMapBuilder$adder$
  super_class: #5                         // scala/runtime/AbstractFunction2
  interfaces: 0, fields: 2, methods: 4, attributes: 5
Constant pool:
   #1 = Utf8               scala/collection/immutable/TreeMap$TreeMapBuilder$adder$
   #2 = Class              #1             // scala/collection/immutable/TreeMap$TreeMapBuilder$adder$
   #3 = Utf8               Lscala/runtime/AbstractFunction2<TK;TV;Lscala/runtime/BoxedUnit;>;
   #4 = Utf8               scala/runtime/AbstractFunction2
   #5 = Class              #4             // scala/runtime/AbstractFunction2
   #6 = Utf8               TreeMap.scala
   #7 = Utf8               scala/collection/immutable/RedBlackTree$Tree
   #8 = Class              #7             // scala/collection/immutable/RedBlackTree$Tree
   #9 = Utf8               scala/collection/immutable/RedBlackTree
  #10 = Class              #9             // scala/collection/immutable/RedBlackTree
  #11 = Utf8               Tree
  #12 = Utf8               scala/collection/immutable/TreeMap$TreeMapBuilder
  #13 = Class              #12            // scala/collection/immutable/TreeMap$TreeMapBuilder
  #14 = Utf8               scala/collection/immutable/TreeMap
  #15 = Class              #14            // scala/collection/immutable/TreeMap
  #16 = Utf8               TreeMapBuilder
  #17 = Utf8               adder$
  #18 = Utf8               accumulator
  #19 = Utf8               Lscala/collection/immutable/RedBlackTree$Tree;
  #20 = Utf8               Lscala/collection/immutable/RedBlackTree$Tree<TK;TV;>;
  #21 = Utf8               $outer
  #22 = Utf8               Lscala/collection/immutable/TreeMap$TreeMapBuilder;
  #23 = Utf8               addForEach
  #24 = Utf8               (Lscala/collection/Map;)V
  #25 = Utf8               (Lscala/collection/Map<TK;TV;>;)V
  #26 = Utf8               hasForEach
  #27 = NameAndType        #21:#22        // $outer:Lscala/collection/immutable/TreeMap$TreeMapBuilder;
  #28 = Fieldref           #2.#27         // scala/collection/immutable/TreeMap$TreeMapBuilder$adder$.$outer:Lscala/collection/immutable/TreeMap$TreeMapBuilder;
  #29 = Utf8               scala$collection$immutable$TreeMap$TreeMapBuilder$$tree
  #30 = Utf8               ()Lscala/collection/immutable/RedBlackTree$Tree;
  #31 = NameAndType        #29:#30        // scala$collection$immutable$TreeMap$TreeMapBuilder$$tree:()Lscala/collection/immutable/RedBlackTree$Tree;
  #32 = Methodref          #13.#31        // scala/collection/immutable/TreeMap$TreeMapBuilder.scala$collection$immutable$TreeMap$TreeMapBuilder$$tree:()Lscala/collection/immutable/RedBlackTree$Tree;
  #33 = NameAndType        #18:#19        // accumulator:Lscala/collection/immutable/RedBlackTree$Tree;
  #34 = Fieldref           #2.#33         // scala/collection/immutable/TreeMap$TreeMapBuilder$adder$.accumulator:Lscala/collection/immutable/RedBlackTree$Tree;
  #35 = Utf8               scala/collection/Map
  #36 = Class              #35            // scala/collection/Map
  #37 = Utf8               foreachEntry
  #38 = Utf8               (Lscala/Function2;)V
  #39 = NameAndType        #37:#38        // foreachEntry:(Lscala/Function2;)V
  #40 = InterfaceMethodref #36.#39        // scala/collection/Map.foreachEntry:(Lscala/Function2;)V
  #41 = Utf8               scala$collection$immutable$TreeMap$TreeMapBuilder$$tree_$eq
  #42 = Utf8               (Lscala/collection/immutable/RedBlackTree$Tree;)V
  #43 = NameAndType        #41:#42        // scala$collection$immutable$TreeMap$TreeMapBuilder$$tree_$eq:(Lscala/collection/immutable/RedBlackTree$Tree;)V
  #44 = Methodref          #13.#43        // scala/collection/immutable/TreeMap$TreeMapBuilder.scala$collection$immutable$TreeMap$TreeMapBuilder$$tree_$eq:(Lscala/collection/immutable/RedBlackTree$Tree;)V
  #45 = Utf8               this
  #46 = Utf8               Lscala/collection/immutable/TreeMap$TreeMapBuilder$adder$;
  #47 = Utf8               Lscala/collection/Map;
  #48 = Utf8               apply
  #49 = Utf8               (Ljava/lang/Object;Ljava/lang/Object;)V
  #50 = Utf8               (TK;TV;)V
  #51 = Utf8               key
  #52 = Utf8               value
  #53 = Utf8               mutableUpd
  #54 = Utf8               (Lscala/collection/immutable/RedBlackTree$Tree;Ljava/lang/Object;Ljava/lang/Object;)Lscala/collection/immutable/RedBlackTree$Tree;
  #55 = NameAndType        #53:#54        // mutableUpd:(Lscala/collection/immutable/RedBlackTree$Tree;Ljava/lang/Object;Ljava/lang/Object;)Lscala/collection/immutable/RedBlackTree$Tree;
  #56 = Methodref          #13.#55        // scala/collection/immutable/TreeMap$TreeMapBuilder.mutableUpd:(Lscala/collection/immutable/RedBlackTree$Tree;Ljava/lang/Object;Ljava/lang/Object;)Lscala/collection/immutable/RedBlackTree$Tree;
  #57 = Utf8               Ljava/lang/Object;
  #58 = Utf8               (Ljava/lang/Object;Ljava/lang/Object;)Ljava/lang/Object;
  #59 = Utf8               v1
  #60 = Utf8               v2
  #61 = NameAndType        #48:#49        // apply:(Ljava/lang/Object;Ljava/lang/Object;)V
  #62 = Methodref          #2.#61         // scala/collection/immutable/TreeMap$TreeMapBuilder$adder$.apply:(Ljava/lang/Object;Ljava/lang/Object;)V
  #63 = Utf8               scala/runtime/BoxedUnit
  #64 = Class              #63            // scala/runtime/BoxedUnit
  #65 = Utf8               UNIT
  #66 = Utf8               Lscala/runtime/BoxedUnit;
  #67 = NameAndType        #65:#66        // UNIT:Lscala/runtime/BoxedUnit;
  #68 = Fieldref           #64.#67        // scala/runtime/BoxedUnit.UNIT:Lscala/runtime/BoxedUnit;
  #69 = Utf8               <init>
  #70 = Utf8               (Lscala/collection/immutable/TreeMap$TreeMapBuilder;)V
  #71 = Utf8               ()V
  #72 = NameAndType        #69:#71        // "<init>":()V
  #73 = Methodref          #5.#72         // scala/runtime/AbstractFunction2."<init>":()V
  #74 = Utf8               Signature
  #75 = Utf8               Code
  #76 = Utf8               LineNumberTable
  #77 = Utf8               LocalVariableTable
  #78 = Utf8               MethodParameters
  #79 = Utf8               StackMapTable
  #80 = Utf8               InnerClasses
  #81 = Utf8               SourceFile
  #82 = Utf8               ScalaInlineInfo
  #83 = Utf8               Scala
{
  private scala.collection.immutable.RedBlackTree$Tree<K, V> accumulator;
    descriptor: Lscala/collection/immutable/RedBlackTree$Tree;
    flags: (0x0002) ACC_PRIVATE
    Signature: #20                          // Lscala/collection/immutable/RedBlackTree$Tree<TK;TV;>;

  private final scala.collection.immutable.TreeMap$TreeMapBuilder $outer;
    descriptor: Lscala/collection/immutable/TreeMap$TreeMapBuilder;
    flags: (0x1012) ACC_PRIVATE, ACC_FINAL, ACC_SYNTHETIC

  public void addForEach(scala.collection.Map<K, V>);
    descriptor: (Lscala/collection/Map;)V
    flags: (0x0001) ACC_PUBLIC
    Code:
      stack=2, locals=2, args_size=2
         0: aload_0
         1: aload_0
         2: getfield      #28                 // Field $outer:Lscala/collection/immutable/TreeMap$TreeMapBuilder;
         5: invokevirtual #32                 // Method scala/collection/immutable/TreeMap$TreeMapBuilder.scala$collection$immutable$TreeMap$TreeMapBuilder$$tree:()Lscala/collection/immutable/RedBlackTree$Tree;
         8: putfield      #34                 // Field accumulator:Lscala/collection/immutable/RedBlackTree$Tree;
        11: aload_1
        12: aload_0
        13: invokeinterface #40,  2           // InterfaceMethod scala/collection/Map.foreachEntry:(Lscala/Function2;)V
        18: aload_0
        19: getfield      #28                 // Field $outer:Lscala/collection/immutable/TreeMap$TreeMapBuilder;
        22: aload_0
        23: getfield      #34                 // Field accumulator:Lscala/collection/immutable/RedBlackTree$Tree;
        26: invokevirtual #44                 // Method scala/collection/immutable/TreeMap$TreeMapBuilder.scala$collection$immutable$TreeMap$TreeMapBuilder$$tree_$eq:(Lscala/collection/immutable/RedBlackTree$Tree;)V
        29: aload_0
        30: aconst_null
        31: putfield      #34                 // Field accumulator:Lscala/collection/immutable/RedBlackTree$Tree;
        34: return
      LineNumberTable:
        line 334: 0
        line 335: 11
        line 336: 18
        line 338: 29
      LocalVariableTable:
        Start  Length  Slot  Name   Signature
            0      35     0  this   Lscala/collection/immutable/TreeMap$TreeMapBuilder$adder$;
            0      35     1 hasForEach   Lscala/collection/Map;
    Signature: #25                          // (Lscala/collection/Map<TK;TV;>;)V
    MethodParameters:
      Name                           Flags
      hasForEach                     final

  public void apply(K, V);
    descriptor: (Ljava/lang/Object;Ljava/lang/Object;)V
    flags: (0x0001) ACC_PUBLIC
    Code:
      stack=5, locals=3, args_size=3
         0: aload_0
         1: aload_0
         2: getfield      #28                 // Field $outer:Lscala/collection/immutable/TreeMap$TreeMapBuilder;
         5: aload_0
         6: getfield      #34                 // Field accumulator:Lscala/collection/immutable/RedBlackTree$Tree;
         9: aload_1
        10: aload_2
        11: invokevirtual #56                 // Method scala/collection/immutable/TreeMap$TreeMapBuilder.mutableUpd:(Lscala/collection/immutable/RedBlackTree$Tree;Ljava/lang/Object;Ljava/lang/Object;)Lscala/collection/immutable/RedBlackTree$Tree;
        14: putfield      #34                 // Field accumulator:Lscala/collection/immutable/RedBlackTree$Tree;
        17: return
      LineNumberTable:
        line 342: 0
      LocalVariableTable:
        Start  Length  Slot  Name   Signature
            0      18     0  this   Lscala/collection/immutable/TreeMap$TreeMapBuilder$adder$;
            0      18     1   key   Ljava/lang/Object;
            0      18     2 value   Ljava/lang/Object;
    Signature: #50                          // (TK;TV;)V
    MethodParameters:
      Name                           Flags
      key                            final
      value                          final

  public java.lang.Object apply(java.lang.Object, java.lang.Object);
    descriptor: (Ljava/lang/Object;Ljava/lang/Object;)Ljava/lang/Object;
    flags: (0x1041) ACC_PUBLIC, ACC_BRIDGE, ACC_SYNTHETIC
    Code:
      stack=3, locals=3, args_size=3
         0: aload_0
         1: aload_1
         2: aload_2
         3: invokevirtual #62                 // Method apply:(Ljava/lang/Object;Ljava/lang/Object;)V
         6: getstatic     #68                 // Field scala/runtime/BoxedUnit.UNIT:Lscala/runtime/BoxedUnit;
         9: areturn
      LineNumberTable:
        line 329: 0
      LocalVariableTable:
        Start  Length  Slot  Name   Signature
            0      10     0  this   Lscala/collection/immutable/TreeMap$TreeMapBuilder$adder$;
            0      10     1    v1   Ljava/lang/Object;
            0      10     2    v2   Ljava/lang/Object;
    MethodParameters:
      Name                           Flags
      v1                             final
      v2                             final

  public scala.collection.immutable.TreeMap$TreeMapBuilder$adder$(scala.collection.immutable.TreeMap$TreeMapBuilder);
    descriptor: (Lscala/collection/immutable/TreeMap$TreeMapBuilder;)V
    flags: (0x0001) ACC_PUBLIC
    Code:
      stack=2, locals=2, args_size=2
         0: aload_1
         1: ifnonnull     6
         4: aconst_null
         5: athrow
         6: aload_0
         7: aload_1
         8: putfield      #28                 // Field $outer:Lscala/collection/immutable/TreeMap$TreeMapBuilder;
        11: aload_0
        12: invokespecial #73                 // Method scala/runtime/AbstractFunction2."<init>":()V
        15: aload_0
        16: aconst_null
        17: putfield      #34                 // Field accumulator:Lscala/collection/immutable/RedBlackTree$Tree;
        20: return
      StackMapTable: number_of_entries = 1
        frame_type = 6 /* same */
      LineNumberTable:
        line 329: 0
        line 332: 15
        line 329: 20
      LocalVariableTable:
        Start  Length  Slot  Name   Signature
            0      21     0  this   Lscala/collection/immutable/TreeMap$TreeMapBuilder$adder$;
            0      21     1 $outer   Lscala/collection/immutable/TreeMap$TreeMapBuilder;
    MethodParameters:
      Name                           Flags
      $outer                         final synthetic
}
InnerClasses:
  public static final #11= #8 of #10;     // Tree=class scala/collection/immutable/RedBlackTree$Tree of class scala/collection/immutable/RedBlackTree
  private static #16= #13 of #15;         // TreeMapBuilder=class scala/collection/immutable/TreeMap$TreeMapBuilder of class scala/collection/immutable/TreeMap
  private #17= #2 of #13;                 // adder$=class scala/collection/immutable/TreeMap$TreeMapBuilder$adder$ of class scala/collection/immutable/TreeMap$TreeMapBuilder
Signature: #3                           // Lscala/runtime/AbstractFunction2<TK;TV;Lscala/runtime/BoxedUnit;>;
SourceFile: "TreeMap.scala"
  ScalaInlineInfo: length = 0x18 (unknown attribute)
   01 01 00 04 00 45 00 46 01 00 17 00 18 01 00 30
   00 3A 01 00 30 00 31 01
  Scala: length = 0x0 (unknown attribute)

