Classfile /Users/mw/Projects/slang-braindump/.jar/jar8/assemble/slang-braindump/assemble/content/scala/collection/immutable/VectorStepperBase.class
  Last modified May 29, 2022; size 4889 bytes
  SHA-256 checksum 7abf189a112fcc31ac3490ffbda6c2366a9c90a61804f07b50d349c8f29bc518
  Compiled from "Vector.scala"
public abstract class scala.collection.immutable.VectorStepperBase<A extends java.lang.Object, Sub extends scala.collection.Stepper<A>, Semi extends Sub> extends java.lang.Object implements scala.collection.Stepper<A>, scala.collection.Stepper$EfficientSplit
  minor version: 0
  major version: 52
  flags: (0x0421) ACC_PUBLIC, ACC_SUPER, ACC_ABSTRACT
  this_class: #2                          // scala/collection/immutable/VectorStepperBase
  super_class: #5                         // java/lang/Object
  interfaces: 2, fields: 1, methods: 19, attributes: 6
Constant pool:
    #1 = Utf8               scala/collection/immutable/VectorStepperBase
    #2 = Class              #1            // scala/collection/immutable/VectorStepperBase
    #3 = Utf8               <A:Ljava/lang/Object;Sub::Lscala/collection/Stepper<TA;>;Semi:TSub;>Ljava/lang/Object;Lscala/collection/Stepper<TA;>;Lscala/collection/Stepper$EfficientSplit;
    #4 = Utf8               java/lang/Object
    #5 = Class              #4            // java/lang/Object
    #6 = Utf8               scala/collection/Stepper
    #7 = Class              #6            // scala/collection/Stepper
    #8 = Utf8               scala/collection/Stepper$EfficientSplit
    #9 = Class              #8            // scala/collection/Stepper$EfficientSplit
   #10 = Utf8               Vector.scala
   #11 = Utf8               Lscala/reflect/ScalaSignature;
   #12 = Utf8               bytes
   #13 = Utf8               \u0006\u0005\u00054Q!\u0003\u0006\u0002\nEA\u0001\u0002\u000e\u0001\u0003\u0002\u0003\u0006I!\u000e\u0005\u0006s\u0001!\tA\u000f\u0005\u0007\u0011\u0002\u0001k\u0011C%\t\u000b-\u0003AQ\u0001\'\t\u000bA\u0003AQA)\t\u000bU\u0003AQ\u0001,\t\u000bi\u0003A\u0011A.\t\u000bq\u0003AQI/\u0003#Y+7\r^8s\'R,\u0007\u000f]3s\u0005\u0006\u001cXM\u0003\u0002\f\u0019\u0005I\u0011.\\7vi\u0006\u0014G.\u001a\u0006\u0003\u001b9\t!bY8mY\u0016\u001cG/[8o\u0015\u0005y\u0011!B:dC2\f7\u0001A\u000b\u0005%uiDi\u0005\u0003\u0001\']1\u0003C\u0001\u000b\u0016\u001b\u0005q\u0011B\u0001\f\u000f\u0005\u0019\te.\u001f*fMB\u0019\u0001$G\u000e\u000e\u00031I!A\u0007\u0007\u0003\u000fM#X\r\u001d9feB\u0011A$\b\u0007\u0001\t\u0015q\u0002A1\u0001 \u0005\u0005\t\u0015C\u0001\u0011$!\t!\u0012%\u0003\u0002#\u001d\t9aj\u001c;iS:<\u0007C\u0001\u000b%\u0013\t)cBA\u0002B]f\u0004\"aJ\u0019\u000f\u0005!zcBA\u0015/\u001d\tQS&D\u0001,\u0015\ta\u0003#\u0001\u0004=e>|GOP\u0005\u0002\u001f%\u0011QBD\u0005\u0003a1\tqa\u0015;faB,\'/\u0003\u00023g\tqQI\u001a4jG&,g\u000e^*qY&$(B\u0001\u0019\r\u0003\tIG\u000fE\u00027omi\u0011AC\u0005\u0003q)\u0011\u0011CT3x-\u0016\u001cGo\u001c:Ji\u0016\u0014\u0018\r^8s\u0003\u0019a\u0014N\\5u}Q\u00111h\u0012\t\u0006m\u0001YBh\u0011\t\u00039u\"QA\u0010\u0001C\u0002}\u00121aU;c#\t\u0001u\u0003\u0005\u0002\u0015\u0003&\u0011!I\u0004\u0002\u0005\u001dVdG\u000e\u0005\u0002\u001d\t\u0012)Q\t\u0001b\u0001\r\n!1+Z7j#\t\u0001C\bC\u00035\u0005\u0001\u0007Q\'A\u0003ck&dG\r\u0006\u0002D\u0015\")Ag\u0001a\u0001k\u00059\u0001.Y:Ti\u0016\u0004X#A\'\u0011\u0005Qq\u0015BA(\u000f\u0005\u001d\u0011un\u001c7fC:\fqb\u00195be\u0006\u001cG/\u001a:jgRL7m]\u000b\u0002%B\u0011AcU\u0005\u0003):\u00111!\u00138u\u00031)7\u000f^5nCR,7+\u001b>f+\u00059\u0006C\u0001\u000bY\u0013\tIfB\u0001\u0003M_:<\u0017\u0001\u0003;ssN\u0003H.\u001b;\u0015\u0003q\n\u0001\"\u001b;fe\u0006$xN]\u000b\u0002=B\u0019\u0001dX\u000e\n\u0005\u0001d!\u0001C%uKJ\fGo\u001c:
   #14 = Utf8               EfficientSplit
   #15 = Utf8               it
   #16 = Utf8               Lscala/collection/immutable/NewVectorIterator;
   #17 = Utf8               Lscala/collection/immutable/NewVectorIterator<TA;>;
   #18 = Utf8               nextStep$mcD$sp
   #19 = Utf8               ()D
   #20 = Utf8               nextStep$mcD$sp$
   #21 = Utf8               (Lscala/collection/Stepper;)D
   #22 = NameAndType        #20:#21       // nextStep$mcD$sp$:(Lscala/collection/Stepper;)D
   #23 = InterfaceMethodref #7.#22        // scala/collection/Stepper.nextStep$mcD$sp$:(Lscala/collection/Stepper;)D
   #24 = Utf8               this
   #25 = Utf8               Lscala/collection/immutable/VectorStepperBase;
   #26 = Utf8               nextStep$mcI$sp
   #27 = Utf8               ()I
   #28 = Utf8               nextStep$mcI$sp$
   #29 = Utf8               (Lscala/collection/Stepper;)I
   #30 = NameAndType        #28:#29       // nextStep$mcI$sp$:(Lscala/collection/Stepper;)I
   #31 = InterfaceMethodref #7.#30        // scala/collection/Stepper.nextStep$mcI$sp$:(Lscala/collection/Stepper;)I
   #32 = Utf8               nextStep$mcJ$sp
   #33 = Utf8               ()J
   #34 = Utf8               nextStep$mcJ$sp$
   #35 = Utf8               (Lscala/collection/Stepper;)J
   #36 = NameAndType        #34:#35       // nextStep$mcJ$sp$:(Lscala/collection/Stepper;)J
   #37 = InterfaceMethodref #7.#36        // scala/collection/Stepper.nextStep$mcJ$sp$:(Lscala/collection/Stepper;)J
   #38 = Utf8               trySplit$mcD$sp
   #39 = Utf8               ()Lscala/collection/Stepper;
   #40 = Utf8               ()Lscala/collection/Stepper<Ljava/lang/Object;>;
   #41 = Utf8               trySplit$mcD$sp$
   #42 = Utf8               (Lscala/collection/Stepper;)Lscala/collection/Stepper;
   #43 = NameAndType        #41:#42       // trySplit$mcD$sp$:(Lscala/collection/Stepper;)Lscala/collection/Stepper;
   #44 = InterfaceMethodref #7.#43        // scala/collection/Stepper.trySplit$mcD$sp$:(Lscala/collection/Stepper;)Lscala/collection/Stepper;
   #45 = Utf8               trySplit$mcI$sp
   #46 = Utf8               trySplit$mcI$sp$
   #47 = NameAndType        #46:#42       // trySplit$mcI$sp$:(Lscala/collection/Stepper;)Lscala/collection/Stepper;
   #48 = InterfaceMethodref #7.#47        // scala/collection/Stepper.trySplit$mcI$sp$:(Lscala/collection/Stepper;)Lscala/collection/Stepper;
   #49 = Utf8               trySplit$mcJ$sp
   #50 = Utf8               trySplit$mcJ$sp$
   #51 = NameAndType        #50:#42       // trySplit$mcJ$sp$:(Lscala/collection/Stepper;)Lscala/collection/Stepper;
   #52 = InterfaceMethodref #7.#51        // scala/collection/Stepper.trySplit$mcJ$sp$:(Lscala/collection/Stepper;)Lscala/collection/Stepper;
   #53 = Utf8               spliterator$mcD$sp
   #54 = Utf8               ()Ljava/util/Spliterator;
   #55 = Utf8               <B:Ljava/lang/Object;>()Ljava/util/Spliterator<*>;
   #56 = Utf8               spliterator$mcD$sp$
   #57 = Utf8               (Lscala/collection/Stepper;)Ljava/util/Spliterator;
   #58 = NameAndType        #56:#57       // spliterator$mcD$sp$:(Lscala/collection/Stepper;)Ljava/util/Spliterator;
   #59 = InterfaceMethodref #7.#58        // scala/collection/Stepper.spliterator$mcD$sp$:(Lscala/collection/Stepper;)Ljava/util/Spliterator;
   #60 = Utf8               spliterator$mcI$sp
   #61 = Utf8               spliterator$mcI$sp$
   #62 = NameAndType        #61:#57       // spliterator$mcI$sp$:(Lscala/collection/Stepper;)Ljava/util/Spliterator;
   #63 = InterfaceMethodref #7.#62        // scala/collection/Stepper.spliterator$mcI$sp$:(Lscala/collection/Stepper;)Ljava/util/Spliterator;
   #64 = Utf8               spliterator$mcJ$sp
   #65 = Utf8               spliterator$mcJ$sp$
   #66 = NameAndType        #65:#57       // spliterator$mcJ$sp$:(Lscala/collection/Stepper;)Ljava/util/Spliterator;
   #67 = InterfaceMethodref #7.#66        // scala/collection/Stepper.spliterator$mcJ$sp$:(Lscala/collection/Stepper;)Ljava/util/Spliterator;
   #68 = Utf8               javaIterator$mcD$sp
   #69 = Utf8               ()Ljava/util/Iterator;
   #70 = Utf8               <B:Ljava/lang/Object;>()Ljava/util/Iterator<*>;
   #71 = Utf8               javaIterator$mcD$sp$
   #72 = Utf8               (Lscala/collection/Stepper;)Ljava/util/Iterator;
   #73 = NameAndType        #71:#72       // javaIterator$mcD$sp$:(Lscala/collection/Stepper;)Ljava/util/Iterator;
   #74 = InterfaceMethodref #7.#73        // scala/collection/Stepper.javaIterator$mcD$sp$:(Lscala/collection/Stepper;)Ljava/util/Iterator;
   #75 = Utf8               javaIterator$mcI$sp
   #76 = Utf8               javaIterator$mcI$sp$
   #77 = NameAndType        #76:#72       // javaIterator$mcI$sp$:(Lscala/collection/Stepper;)Ljava/util/Iterator;
   #78 = InterfaceMethodref #7.#77        // scala/collection/Stepper.javaIterator$mcI$sp$:(Lscala/collection/Stepper;)Ljava/util/Iterator;
   #79 = Utf8               javaIterator$mcJ$sp
   #80 = Utf8               javaIterator$mcJ$sp$
   #81 = NameAndType        #80:#72       // javaIterator$mcJ$sp$:(Lscala/collection/Stepper;)Ljava/util/Iterator;
   #82 = InterfaceMethodref #7.#81        // scala/collection/Stepper.javaIterator$mcJ$sp$:(Lscala/collection/Stepper;)Ljava/util/Iterator;
   #83 = Utf8               build
   #84 = Utf8               (Lscala/collection/immutable/NewVectorIterator;)Lscala/collection/Stepper;
   #85 = Utf8               (Lscala/collection/immutable/NewVectorIterator<TA;>;)TSemi;
   #86 = Utf8               hasStep
   #87 = Utf8               ()Z
   #88 = NameAndType        #15:#16       // it:Lscala/collection/immutable/NewVectorIterator;
   #89 = Fieldref           #2.#88        // scala/collection/immutable/VectorStepperBase.it:Lscala/collection/immutable/NewVectorIterator;
   #90 = Utf8               scala/collection/immutable/NewVectorIterator
   #91 = Class              #90           // scala/collection/immutable/NewVectorIterator
   #92 = Utf8               scala$collection$immutable$NewVectorIterator$$len1
   #93 = Utf8               I
   #94 = NameAndType        #92:#93       // scala$collection$immutable$NewVectorIterator$$len1:I
   #95 = Fieldref           #91.#94       // scala/collection/immutable/NewVectorIterator.scala$collection$immutable$NewVectorIterator$$len1:I
   #96 = Utf8               scala$collection$immutable$NewVectorIterator$$i1
   #97 = NameAndType        #96:#93       // scala$collection$immutable$NewVectorIterator$$i1:I
   #98 = Fieldref           #91.#97       // scala/collection/immutable/NewVectorIterator.scala$collection$immutable$NewVectorIterator$$i1:I
   #99 = Utf8               hasNext_this
  #100 = Utf8               characteristics
  #101 = Utf8               estimateSize
  #102 = Utf8               knownSize_this
  #103 = Utf8               trySplit
  #104 = Utf8               ()TSub;
  #105 = Utf8               split
  #106 = Utf8               (I)Lscala/collection/immutable/NewVectorIterator;
  #107 = NameAndType        #105:#106     // split:(I)Lscala/collection/immutable/NewVectorIterator;
  #108 = Methodref          #91.#107      // scala/collection/immutable/NewVectorIterator.split:(I)Lscala/collection/immutable/NewVectorIterator;
  #109 = NameAndType        #83:#84       // build:(Lscala/collection/immutable/NewVectorIterator;)Lscala/collection/Stepper;
  #110 = Methodref          #2.#109       // scala/collection/immutable/VectorStepperBase.build:(Lscala/collection/immutable/NewVectorIterator;)Lscala/collection/Stepper;
  #111 = Utf8               iterator
  #112 = Utf8               ()Lscala/collection/Iterator;
  #113 = Utf8               ()Lscala/collection/Iterator<TA;>;
  #114 = Utf8               <init>
  #115 = Utf8               (Lscala/collection/immutable/NewVectorIterator;)V
  #116 = Utf8               (Lscala/collection/immutable/NewVectorIterator<TA;>;)V
  #117 = Utf8               ()V
  #118 = NameAndType        #114:#117     // "<init>":()V
  #119 = Methodref          #5.#118       // java/lang/Object."<init>":()V
  #120 = Utf8               Signature
  #121 = Utf8               Code
  #122 = Utf8               LineNumberTable
  #123 = Utf8               LocalVariableTable
  #124 = Utf8               MethodParameters
  #125 = Utf8               StackMapTable
  #126 = Utf8               InnerClasses
  #127 = Utf8               SourceFile
  #128 = Utf8               RuntimeVisibleAnnotations
  #129 = Utf8               ScalaInlineInfo
  #130 = Utf8               ScalaSig
{
  private final scala.collection.immutable.NewVectorIterator<A> it;
    descriptor: Lscala/collection/immutable/NewVectorIterator;
    flags: (0x0012) ACC_PRIVATE, ACC_FINAL
    Signature: #17                          // Lscala/collection/immutable/NewVectorIterator<TA;>;

  public double nextStep$mcD$sp();
    descriptor: ()D
    flags: (0x0001) ACC_PUBLIC
    Code:
      stack=2, locals=1, args_size=1
         0: aload_0
         1: invokestatic  #23                 // InterfaceMethod scala/collection/Stepper.nextStep$mcD$sp$:(Lscala/collection/Stepper;)D
         4: dreturn
      LineNumberTable:
        line 2156: 0
      LocalVariableTable:
        Start  Length  Slot  Name   Signature
            0       5     0  this   Lscala/collection/immutable/VectorStepperBase;

  public int nextStep$mcI$sp();
    descriptor: ()I
    flags: (0x0001) ACC_PUBLIC
    Code:
      stack=1, locals=1, args_size=1
         0: aload_0
         1: invokestatic  #31                 // InterfaceMethod scala/collection/Stepper.nextStep$mcI$sp$:(Lscala/collection/Stepper;)I
         4: ireturn
      LineNumberTable:
        line 2156: 0
      LocalVariableTable:
        Start  Length  Slot  Name   Signature
            0       5     0  this   Lscala/collection/immutable/VectorStepperBase;

  public long nextStep$mcJ$sp();
    descriptor: ()J
    flags: (0x0001) ACC_PUBLIC
    Code:
      stack=2, locals=1, args_size=1
         0: aload_0
         1: invokestatic  #37                 // InterfaceMethod scala/collection/Stepper.nextStep$mcJ$sp$:(Lscala/collection/Stepper;)J
         4: lreturn
      LineNumberTable:
        line 2156: 0
      LocalVariableTable:
        Start  Length  Slot  Name   Signature
            0       5     0  this   Lscala/collection/immutable/VectorStepperBase;

  public scala.collection.Stepper<java.lang.Object> trySplit$mcD$sp();
    descriptor: ()Lscala/collection/Stepper;
    flags: (0x0001) ACC_PUBLIC
    Code:
      stack=1, locals=1, args_size=1
         0: aload_0
         1: invokestatic  #44                 // InterfaceMethod scala/collection/Stepper.trySplit$mcD$sp$:(Lscala/collection/Stepper;)Lscala/collection/Stepper;
         4: areturn
      LineNumberTable:
        line 2156: 0
      LocalVariableTable:
        Start  Length  Slot  Name   Signature
            0       5     0  this   Lscala/collection/immutable/VectorStepperBase;
    Signature: #40                          // ()Lscala/collection/Stepper<Ljava/lang/Object;>;

  public scala.collection.Stepper<java.lang.Object> trySplit$mcI$sp();
    descriptor: ()Lscala/collection/Stepper;
    flags: (0x0001) ACC_PUBLIC
    Code:
      stack=1, locals=1, args_size=1
         0: aload_0
         1: invokestatic  #48                 // InterfaceMethod scala/collection/Stepper.trySplit$mcI$sp$:(Lscala/collection/Stepper;)Lscala/collection/Stepper;
         4: areturn
      LineNumberTable:
        line 2156: 0
      LocalVariableTable:
        Start  Length  Slot  Name   Signature
            0       5     0  this   Lscala/collection/immutable/VectorStepperBase;
    Signature: #40                          // ()Lscala/collection/Stepper<Ljava/lang/Object;>;

  public scala.collection.Stepper<java.lang.Object> trySplit$mcJ$sp();
    descriptor: ()Lscala/collection/Stepper;
    flags: (0x0001) ACC_PUBLIC
    Code:
      stack=1, locals=1, args_size=1
         0: aload_0
         1: invokestatic  #52                 // InterfaceMethod scala/collection/Stepper.trySplit$mcJ$sp$:(Lscala/collection/Stepper;)Lscala/collection/Stepper;
         4: areturn
      LineNumberTable:
        line 2156: 0
      LocalVariableTable:
        Start  Length  Slot  Name   Signature
            0       5     0  this   Lscala/collection/immutable/VectorStepperBase;
    Signature: #40                          // ()Lscala/collection/Stepper<Ljava/lang/Object;>;

  public <B extends java.lang.Object> java.util.Spliterator<?> spliterator$mcD$sp();
    descriptor: ()Ljava/util/Spliterator;
    flags: (0x0001) ACC_PUBLIC
    Code:
      stack=1, locals=1, args_size=1
         0: aload_0
         1: invokestatic  #59                 // InterfaceMethod scala/collection/Stepper.spliterator$mcD$sp$:(Lscala/collection/Stepper;)Ljava/util/Spliterator;
         4: areturn
      LineNumberTable:
        line 2156: 0
      LocalVariableTable:
        Start  Length  Slot  Name   Signature
            0       5     0  this   Lscala/collection/immutable/VectorStepperBase;
    Signature: #55                          // <B:Ljava/lang/Object;>()Ljava/util/Spliterator<*>;

  public <B extends java.lang.Object> java.util.Spliterator<?> spliterator$mcI$sp();
    descriptor: ()Ljava/util/Spliterator;
    flags: (0x0001) ACC_PUBLIC
    Code:
      stack=1, locals=1, args_size=1
         0: aload_0
         1: invokestatic  #63                 // InterfaceMethod scala/collection/Stepper.spliterator$mcI$sp$:(Lscala/collection/Stepper;)Ljava/util/Spliterator;
         4: areturn
      LineNumberTable:
        line 2156: 0
      LocalVariableTable:
        Start  Length  Slot  Name   Signature
            0       5     0  this   Lscala/collection/immutable/VectorStepperBase;
    Signature: #55                          // <B:Ljava/lang/Object;>()Ljava/util/Spliterator<*>;

  public <B extends java.lang.Object> java.util.Spliterator<?> spliterator$mcJ$sp();
    descriptor: ()Ljava/util/Spliterator;
    flags: (0x0001) ACC_PUBLIC
    Code:
      stack=1, locals=1, args_size=1
         0: aload_0
         1: invokestatic  #67                 // InterfaceMethod scala/collection/Stepper.spliterator$mcJ$sp$:(Lscala/collection/Stepper;)Ljava/util/Spliterator;
         4: areturn
      LineNumberTable:
        line 2156: 0
      LocalVariableTable:
        Start  Length  Slot  Name   Signature
            0       5     0  this   Lscala/collection/immutable/VectorStepperBase;
    Signature: #55                          // <B:Ljava/lang/Object;>()Ljava/util/Spliterator<*>;

  public <B extends java.lang.Object> java.util.Iterator<?> javaIterator$mcD$sp();
    descriptor: ()Ljava/util/Iterator;
    flags: (0x0001) ACC_PUBLIC
    Code:
      stack=1, locals=1, args_size=1
         0: aload_0
         1: invokestatic  #74                 // InterfaceMethod scala/collection/Stepper.javaIterator$mcD$sp$:(Lscala/collection/Stepper;)Ljava/util/Iterator;
         4: areturn
      LineNumberTable:
        line 2156: 0
      LocalVariableTable:
        Start  Length  Slot  Name   Signature
            0       5     0  this   Lscala/collection/immutable/VectorStepperBase;
    Signature: #70                          // <B:Ljava/lang/Object;>()Ljava/util/Iterator<*>;

  public <B extends java.lang.Object> java.util.Iterator<?> javaIterator$mcI$sp();
    descriptor: ()Ljava/util/Iterator;
    flags: (0x0001) ACC_PUBLIC
    Code:
      stack=1, locals=1, args_size=1
         0: aload_0
         1: invokestatic  #78                 // InterfaceMethod scala/collection/Stepper.javaIterator$mcI$sp$:(Lscala/collection/Stepper;)Ljava/util/Iterator;
         4: areturn
      LineNumberTable:
        line 2156: 0
      LocalVariableTable:
        Start  Length  Slot  Name   Signature
            0       5     0  this   Lscala/collection/immutable/VectorStepperBase;
    Signature: #70                          // <B:Ljava/lang/Object;>()Ljava/util/Iterator<*>;

  public <B extends java.lang.Object> java.util.Iterator<?> javaIterator$mcJ$sp();
    descriptor: ()Ljava/util/Iterator;
    flags: (0x0001) ACC_PUBLIC
    Code:
      stack=1, locals=1, args_size=1
         0: aload_0
         1: invokestatic  #82                 // InterfaceMethod scala/collection/Stepper.javaIterator$mcJ$sp$:(Lscala/collection/Stepper;)Ljava/util/Iterator;
         4: areturn
      LineNumberTable:
        line 2156: 0
      LocalVariableTable:
        Start  Length  Slot  Name   Signature
            0       5     0  this   Lscala/collection/immutable/VectorStepperBase;
    Signature: #70                          // <B:Ljava/lang/Object;>()Ljava/util/Iterator<*>;

  public abstract Semi build(scala.collection.immutable.NewVectorIterator<A>);
    descriptor: (Lscala/collection/immutable/NewVectorIterator;)Lscala/collection/Stepper;
    flags: (0x0401) ACC_PUBLIC, ACC_ABSTRACT
    Signature: #85                          // (Lscala/collection/immutable/NewVectorIterator<TA;>;)TSemi;
    MethodParameters:
      Name                           Flags
      it                             final

  public final boolean hasStep();
    descriptor: ()Z
    flags: (0x0011) ACC_PUBLIC, ACC_FINAL
    Code:
      stack=2, locals=2, args_size=1
         0: aload_0
         1: getfield      #89                 // Field it:Lscala/collection/immutable/NewVectorIterator;
         4: dup
         5: ifnonnull     10
         8: aconst_null
         9: athrow
        10: astore_1
        11: aload_1
        12: getfield      #95                 // Field scala/collection/immutable/NewVectorIterator.scala$collection$immutable$NewVectorIterator$$len1:I
        15: aload_1
        16: getfield      #98                 // Field scala/collection/immutable/NewVectorIterator.scala$collection$immutable$NewVectorIterator$$i1:I
        19: if_icmple     24
        22: iconst_1
        23: ireturn
        24: iconst_0
        25: ireturn
      StackMapTable: number_of_entries = 2
        frame_type = 74 /* same_locals_1_stack_item */
          stack = [ class scala/collection/immutable/NewVectorIterator ]
        frame_type = 252 /* append */
          offset_delta = 13
          locals = [ class scala/collection/immutable/NewVectorIterator ]
      LineNumberTable:
        line 2161: 0
        line 1989: 11
        line 2161: 25
      LocalVariableTable:
        Start  Length  Slot  Name   Signature
            0      26     0  this   Lscala/collection/immutable/VectorStepperBase;
           11      14     1 hasNext_this   Lscala/collection/immutable/NewVectorIterator;

  public final int characteristics();
    descriptor: ()I
    flags: (0x0011) ACC_PUBLIC, ACC_FINAL
    Code:
      stack=1, locals=1, args_size=1
         0: sipush        16464
         3: ireturn
      LineNumberTable:
        line 2163: 0
      LocalVariableTable:
        Start  Length  Slot  Name   Signature
            0       4     0  this   Lscala/collection/immutable/VectorStepperBase;

  public final long estimateSize();
    descriptor: ()J
    flags: (0x0011) ACC_PUBLIC, ACC_FINAL
    Code:
      stack=2, locals=2, args_size=1
         0: aload_0
         1: getfield      #89                 // Field it:Lscala/collection/immutable/NewVectorIterator;
         4: dup
         5: ifnonnull     10
         8: aconst_null
         9: athrow
        10: astore_1
        11: aload_1
        12: getfield      #95                 // Field scala/collection/immutable/NewVectorIterator.scala$collection$immutable$NewVectorIterator$$len1:I
        15: aload_1
        16: getfield      #98                 // Field scala/collection/immutable/NewVectorIterator.scala$collection$immutable$NewVectorIterator$$i1:I
        19: isub
        20: i2l
        21: lreturn
      StackMapTable: number_of_entries = 1
        frame_type = 74 /* same_locals_1_stack_item */
          stack = [ class scala/collection/immutable/NewVectorIterator ]
      LineNumberTable:
        line 2165: 0
        line 1987: 11
        line 2165: 20
      LocalVariableTable:
        Start  Length  Slot  Name   Signature
            0      22     0  this   Lscala/collection/immutable/VectorStepperBase;
           11       9     1 knownSize_this   Lscala/collection/immutable/NewVectorIterator;

  public Sub trySplit();
    descriptor: ()Lscala/collection/Stepper;
    flags: (0x0001) ACC_PUBLIC
    Code:
      stack=4, locals=3, args_size=1
         0: aload_0
         1: getfield      #89                 // Field it:Lscala/collection/immutable/NewVectorIterator;
         4: dup
         5: ifnonnull     10
         8: aconst_null
         9: athrow
        10: astore_1
        11: aload_1
        12: getfield      #95                 // Field scala/collection/immutable/NewVectorIterator.scala$collection$immutable$NewVectorIterator$$len1:I
        15: aload_1
        16: getfield      #98                 // Field scala/collection/immutable/NewVectorIterator.scala$collection$immutable$NewVectorIterator$$i1:I
        19: isub
        20: istore_2
        21: aconst_null
        22: astore_1
        23: iload_2
        24: iconst_1
        25: if_icmple     43
        28: aload_0
        29: aload_0
        30: getfield      #89                 // Field it:Lscala/collection/immutable/NewVectorIterator;
        33: iload_2
        34: iconst_1
        35: iushr
        36: invokevirtual #108                // Method scala/collection/immutable/NewVectorIterator.split:(I)Lscala/collection/immutable/NewVectorIterator;
        39: invokevirtual #110                // Method build:(Lscala/collection/immutable/NewVectorIterator;)Lscala/collection/Stepper;
        42: areturn
        43: aconst_null
        44: areturn
      StackMapTable: number_of_entries = 2
        frame_type = 74 /* same_locals_1_stack_item */
          stack = [ class scala/collection/immutable/NewVectorIterator ]
        frame_type = 253 /* append */
          offset_delta = 32
          locals = [ null, int ]
      LineNumberTable:
        line 2168: 0
        line 1987: 11
        line 2168: 21
        line 2169: 23
        line 2170: 43
      LocalVariableTable:
        Start  Length  Slot  Name   Signature
            0      45     0  this   Lscala/collection/immutable/VectorStepperBase;
           11      10     1 knownSize_this   Lscala/collection/immutable/NewVectorIterator;
    Signature: #104                         // ()TSub;

  public final scala.collection.Iterator<A> iterator();
    descriptor: ()Lscala/collection/Iterator;
    flags: (0x0011) ACC_PUBLIC, ACC_FINAL
    Code:
      stack=1, locals=1, args_size=1
         0: aload_0
         1: getfield      #89                 // Field it:Lscala/collection/immutable/NewVectorIterator;
         4: areturn
      LineNumberTable:
        line 2173: 0
      LocalVariableTable:
        Start  Length  Slot  Name   Signature
            0       5     0  this   Lscala/collection/immutable/VectorStepperBase;
    Signature: #113                         // ()Lscala/collection/Iterator<TA;>;

  public scala.collection.immutable.VectorStepperBase(scala.collection.immutable.NewVectorIterator<A>);
    descriptor: (Lscala/collection/immutable/NewVectorIterator;)V
    flags: (0x0001) ACC_PUBLIC
    Code:
      stack=2, locals=2, args_size=2
         0: aload_0
         1: aload_1
         2: putfield      #89                 // Field it:Lscala/collection/immutable/NewVectorIterator;
         5: aload_0
         6: invokespecial #119                // Method java/lang/Object."<init>":()V
         9: return
      LineNumberTable:
        line 2156: 0
        line 2157: 5
        line 2156: 9
      LocalVariableTable:
        Start  Length  Slot  Name   Signature
            0      10     0  this   Lscala/collection/immutable/VectorStepperBase;
            0      10     1    it   Lscala/collection/immutable/NewVectorIterator;
    Signature: #116                         // (Lscala/collection/immutable/NewVectorIterator<TA;>;)V
    MethodParameters:
      Name                           Flags
      it                             final
}
InnerClasses:
  public static #14= #9 of #7;            // EfficientSplit=class scala/collection/Stepper$EfficientSplit of class scala/collection/Stepper
Signature: #3                           // <A:Ljava/lang/Object;Sub::Lscala/collection/Stepper<TA;>;Semi:TSub;>Ljava/lang/Object;Lscala/collection/Stepper<TA;>;Lscala/collection/Stepper$EfficientSplit;
SourceFile: "Vector.scala"
RuntimeVisibleAnnotations:
  0: #11(#12=s#13)
    scala.reflect.ScalaSignature(
      bytes="\u0006\u0005\u00054Q!\u0003\u0006\u0002\nEA\u0001\u0002\u000e\u0001\u0003\u0002\u0003\u0006I!\u000e\u0005\u0006s\u0001!\tA\u000f\u0005\u0007\u0011\u0002\u0001k\u0011C%\t\u000b-\u0003AQ\u0001\'\t\u000bA\u0003AQA)\t\u000bU\u0003AQ\u0001,\t\u000bi\u0003A\u0011A.\t\u000bq\u0003AQI/\u0003#Y+7\r^8s\'R,\u0007\u000f]3s\u0005\u0006\u001cXM\u0003\u0002\f\u0019\u0005I\u0011.\\7vi\u0006\u0014G.\u001a\u0006\u0003\u001b9\t!bY8mY\u0016\u001cG/[8o\u0015\u0005y\u0011!B:dC2\f7\u0001A\u000b\u0005%uiDi\u0005\u0003\u0001\']1\u0003C\u0001\u000b\u0016\u001b\u0005q\u0011B\u0001\f\u000f\u0005\u0019\te.\u001f*fMB\u0019\u0001$G\u000e\u000e\u00031I!A\u0007\u0007\u0003\u000fM#X\r\u001d9feB\u0011A$\b\u0007\u0001\t\u0015q\u0002A1\u0001 \u0005\u0005\t\u0015C\u0001\u0011$!\t!\u0012%\u0003\u0002#\u001d\t9aj\u001c;iS:<\u0007C\u0001\u000b%\u0013\t)cBA\u0002B]f\u0004\"aJ\u0019\u000f\u0005!zcBA\u0015/\u001d\tQS&D\u0001,\u0015\ta\u0003#\u0001\u0004=e>|GOP\u0005\u0002\u001f%\u0011QBD\u0005\u0003a1\tqa\u0015;faB,\'/\u0003\u00023g\tqQI\u001a4jG&,g\u000e^*qY&$(B\u0001\u0019\r\u0003\tIG\u000fE\u00027omi\u0011AC\u0005\u0003q)\u0011\u0011CT3x-\u0016\u001cGo\u001c:Ji\u0016\u0014\u0018\r^8s\u0003\u0019a\u0014N\\5u}Q\u00111h\u0012\t\u0006m\u0001YBh\u0011\t\u00039u\"QA\u0010\u0001C\u0002}\u00121aU;c#\t\u0001u\u0003\u0005\u0002\u0015\u0003&\u0011!I\u0004\u0002\u0005\u001dVdG\u000e\u0005\u0002\u001d\t\u0012)Q\t\u0001b\u0001\r\n!1+Z7j#\t\u0001C\bC\u00035\u0005\u0001\u0007Q\'A\u0003ck&dG\r\u0006\u0002D\u0015\")Ag\u0001a\u0001k\u00059\u0001.Y:Ti\u0016\u0004X#A\'\u0011\u0005Qq\u0015BA(\u000f\u0005\u001d\u0011un\u001c7fC:\fqb\u00195be\u0006\u001cG/\u001a:jgRL7m]\u000b\u0002%B\u0011AcU\u0005\u0003):\u00111!\u00138u\u00031)7\u000f^5nCR,7+\u001b>f+\u00059\u0006C\u0001\u000bY\u0013\tIfB\u0001\u0003M_:<\u0017\u0001\u0003;ssN\u0003H.\u001b;\u0015\u0003q\n\u0001\"\u001b;fe\u0006$xN]\u000b\u0002=B\u0019\u0001dX\u000e\n\u0005\u0001d!\u0001C%uKJ\fGo\u001c:"
    )
  ScalaInlineInfo: length = 0x63 (unknown attribute)
   01 00 00 13 00 72 00 73 00 00 53 00 54 00 00 64
   00 1B 01 00 65 00 21 01 00 56 00 57 01 00 6F 00
   70 01 00 44 00 45 00 00 4B 00 45 00 00 4F 00 45
   00 00 12 00 13 00 00 1A 00 1B 00 00 20 00 21 00
   00 35 00 36 00 00 3C 00 36 00 00 40 00 36 00 00
   67 00 27 00 00 26 00 27 00 00 2D 00 27 00 00 31
   00 27 00
  ScalaSig: length = 0x3 (unknown attribute)
   05 02 00
