Classfile /Users/mw/Projects/slang-braindump/.jar/jar8/assemble/slang-braindump/assemble/content/scala/collection/immutable/Vector3.class
  Last modified May 29, 2022; size 24766 bytes
  SHA-256 checksum 27d869aedb29d938c4f5e008f66d99f11cfad383ad1b1966016ceee8756511e7
  Compiled from "Vector.scala"
public final class scala.collection.immutable.Vector3<A extends java.lang.Object> extends scala.collection.immutable.BigVector<A>
  minor version: 0
  major version: 52
  flags: (0x0031) ACC_PUBLIC, ACC_FINAL, ACC_SUPER
  this_class: #2                          // scala/collection/immutable/Vector3
  super_class: #5                         // scala/collection/immutable/BigVector
  interfaces: 0, fields: 5, methods: 35, attributes: 5
Constant pool:
    #1 = Utf8               scala/collection/immutable/Vector3
    #2 = Class              #1            // scala/collection/immutable/Vector3
    #3 = Utf8               <A:Ljava/lang/Object;>Lscala/collection/immutable/BigVector<TA;>;
    #4 = Utf8               scala/collection/immutable/BigVector
    #5 = Class              #4            // scala/collection/immutable/BigVector
    #6 = Utf8               Vector.scala
    #7 = Utf8               Lscala/reflect/ScalaSignature;
    #8 = Utf8               bytes
    #9 = Utf8               \u0006\u0005\t\ra\u0001B\u0013\'\r5B\u0011b\u0010\u0001\u0003\u0002\u0003\u0006I\u0001\u0011)\t\u0013Q\u0003!Q1A\u0005\u0002\u0019*\u0006\u0002C-\u0001\u0005\u0003\u0005\u000b\u0011\u0002,\t\u0013i\u0003!Q1A\u0005\u0002\u0019Z\u0006\u0002C0\u0001\u0005\u0003\u0005\u000b\u0011\u0002/\t\u0013\u0001\u0004!Q1A\u0005\u0002\u0019*\u0006\u0002C1\u0001\u0005\u0003\u0005\u000b\u0011\u0002,\t\u0013\t\u0004!Q1A\u0005\u0002\u0019\u001a\u0007\u0002C4\u0001\u0005\u0003\u0005\u000b\u0011\u00023\t\u0013!\u0004!Q1A\u0005\u0002\u0019Z\u0006\u0002C5\u0001\u0005\u0003\u0005\u000b\u0011\u0002/\t\u0013)\u0004!\u0011!Q\u0001\n\u0001[\u0007\"C7\u0001\u0005\u0003\u0005\u000b\u0011\u0002,o\u0011\u0015\u0001\b\u0001\"\u0001r\u0011\u0019Y\b\u0001)C\u0005y\"I\u0011Q\u0003\u0001\u0012\u0002\u0013%\u0011q\u0003\u0005\n\u0003[\u0001\u0011\u0013!C\u0005\u0003_A\u0011\"a\r\u0001#\u0003%I!!\u000e\t\u0013\u0005e\u0002!%A\u0005\n\u0005=\u0002\"CA\u001e\u0001E\u0005I\u0011BA\u001f\u0011%\t\t\u0005AI\u0001\n\u0013\t)\u0004C\u0005\u0002D\u0001\t\n\u0011\"\u0003\u0002\u0018!I\u0011Q\t\u0001\u0012\u0002\u0013%\u0011q\u0006\u0005\b\u0003\u000f\u0002A\u0011AA%\u0011\u001d\t\t\u0006\u0001C!\u0003\'Bq!a\u001a\u0001\t\u0003\nI\u0007C\u0004\u0002v\u0001!\t%a\u001e\t\u000f\u0005\r\u0005\u0001\"\u0011\u0002\u0006\"A\u0011\u0011\u0014\u0001!\n#\tY\nC\u0004\u0002(\u0002!\t%!+\t\u000f\u0005-\u0006\u0001\"\u0011\u0002*\"9\u0011Q\u0016\u0001\u0005\u0012\u0019*\u0006\u0002CAX\u0001\u0011Ea%!-\t\u0011\u00055\u0007\u0001\"\u0005\'\u0003\u001fD\u0001\"a5\u0001A\u0013E\u0013Q\u001b\u0005\t\u0003_\u0004\u0001\u0015\"\u0015\u0002r\n9a+Z2u_J\u001c$BA\u0014)\u0003%IW.\\;uC\ndWM\u0003\u0002*U\u0005Q1m\u001c7mK\u000e$\u0018n\u001c8\u000b\u0003-\nQa]2bY\u0006\u001c\u0001!\u0006\u0002/kM\u0011\u0001a\f\t\u0004aE\u001aT\"\u0001\u0014\n\u0005I2#!\u0003\"jOZ+7\r^8s!\t!T\u0007\u0004\u0001\u0005\rY\u0002AQ1\u00018\u0005\u0005\t\u0015C\u0001\u001d=!\tI$(D\u0001+\u0013\tY$FA\u0004O_RD\u0017N\\4\u0011\u0005ej\u0014B\u0001 +\u0005\r\te._\u0001\t?B\u0014XMZ5ycA\u0011\u0011)\u0014\b\u0003\u0005.s!a\u0011&\u000f\u0005\u0011KeBA#I\u001b\u00051%BA$-\u0003\u0019a$o\\8u}%\t1&\u0003\u0002*U%\u0011q\u0005K\u0005\u0003\u0019\u001a\nABV3di>\u0014\u0018J\u001c7j]\u0016L!AT(\u0003\t\u0005\u0013(/\r\u0006\u0003\u0019\u001aJ!!\u0015*\u0002\u000fA\u0014XMZ5yc%\u00111K\n\u0002\u0007-\u0016\u001cGo\u001c:\u0002\t1,g.M\u000b\u0002-B\u0011\u0011hV\u0005\u00031*\u00121!\u00138u\u0003\u0015aWM\\\u0019!\u0003\u001d\u0001(/\u001a4jqJ*\u0012\u0001\u0018\t\u0003\u0003vK!AX(\u0003\t\u0005\u0013(OM\u0001\taJ,g-\u001b=3A\u0005)A.\u001a82e\u00051A.\u001a82e\u0001\nQ\u0001Z1uCN*\u0012\u0001\u001a\t\u0003\u0003\u0016L!AZ(\u0003\t\u0005\u0013(oM\u0001\u0007I\u0006$\u0018m\r\u0011\u0002\u000fM,hMZ5ye\u0005A1/\u001e4gSb\u0014\u0004%\u0001\u0005`gV4g-\u001b=2\u0013\ta\u0017\'A\u0004tk\u001a4\u0017\u000e_\u0019\u0002\u0011}cWM\\4uQBJ!a\\\u0019\u0002\u000f1,gn\u001a;ia\u00051A(\u001b8jiz\"\u0012B]:ukZ<\b0\u001f>\u0011\u0007A\u00021\u0007C\u0003@\u001d\u0001\u0007\u0001\tC\u0003U\u001d\u0001\u0007a\u000bC\u0003[\u001d\u0001\u0007A\fC\u0003a\u001d\u0001\u0007a\u000bC\u0003c\u001d\u0001\u0007A\rC\u0003i\u001d\u0001\u0007A\fC\u0003k\u001d\u0001\u0007\u0001\tC\u0003n\u001d\u0001\u0007a+\u0001\u0003d_BLHcD?\u007f\u007f\u0006\u0005\u00111AA\u0003\u0003\u000f\tI!a\u0003\u0011\u0007A\u0002\u0001\bC\u0004R\u001fA\u0005\t\u0019\u0001!\t\u000fQ{\u0001\u0013!a\u0001-\"9!l\u0004I\u0001\u0002\u0004a\u0006b\u00021\u0010!\u0003\u0005\rA\u0016\u0005\bE>\u0001\n\u00111\u0001e\u0011\u001dAw\u0002%AA\u0002qCq\u0001\\\b\u0011\u0002\u0003\u0007\u0001\tC\u0004p\u001fA\u0005\t\u0019\u0001,)\u0007=\ty\u0001E\u0002:\u0003#I1!a\u0005+\u0005\u0019Ig\u000e\\5oK\u0006q1m\u001c9zI\u0011,g-Y;mi\u0012\nTCAA\rU\r\u0001\u00151D\u0016\u0003\u0003;\u0001B!a\b\u0002*5\u0011\u0011\u0011\u0005\u0006\u0005\u0003G\t)#A\u0005v]\u000eDWmY6fI*\u0019\u0011q\u0005\u0016\u0002\u0015\u0005tgn\u001c;bi&|g.\u0003\u0003\u0002,\u0005\u0005\"!E;oG\",7m[3e-\u0006\u0014\u0018.\u00198dK\u0006q1m\u001c9zI\u0011,g-Y;mi\u0012\u0012TCAA\u0019U\r1\u00161D\u0001\u000fG>\u0004\u0018\u0010\n3fM\u0006,H\u000e\u001e\u00134+\t\t9DK\u0002]\u00037\tabY8qs\u0012\"WMZ1vYR$C\'\u0001\bd_BLH\u0005Z3gCVdG\u000fJ\u001b\u0016\u0005\u0005}\"f\u00013\u0002\u001c\u0005q1m\u001c9zI\u0011,g-Y;mi\u00122\u0014AD2paf$C-\u001a4bk2$HeN\u0001\u000fG>\u0004\u0018\u0010\n3fM\u0006,H\u000e\u001e\u00139\u0003\u0015\t\u0007\u000f\u001d7z)\r\u0019\u00141\n\u0005\u0007\u0003\u001bB\u0002\u0019\u0001,\u0002\u000b%tG-\u001a=)\u0007a\ty!A\u0004va\u0012\fG/\u001a3\u0016\t\u0005U\u00131\f\u000b\u0007\u0003/\n\t\'a\u0019\u0011\tA\u0012\u0016\u0011\f\t\u0004i\u0005mCaBA/3\t\u0007\u0011q\f\u0002\u0002\u0005F\u00111\u0007\u0010\u0005\u0007\u0003\u001bJ\u0002\u0019\u0001,\t\u000f\u0005\u0015\u0014\u00041\u0001\u0002Z\u0005!Q\r\\3n\u0003!\t\u0007\u000f]3oI\u0016$W\u0003BA6\u0003c\"B!!\u001c\u0002tA!\u0001GUA8!\r!\u0014\u0011\u000f\u0003\b\u0003;R\"\u0019AA0\u0011\u001d\t)G\u0007a\u0001\u0003_\n\u0011\u0002\u001d:fa\u0016tG-\u001a3\u0016\t\u0005e\u0014q\u0010\u000b\u0005\u0003w\n\t\t\u0005\u00031%\u0006u\u0004c\u0001\u001b\u0002\u0000\u00119\u0011QL\u000eC\u0002\u0005}\u0003bBA37\u0001\u0007\u0011QP\u0001\u0004[\u0006\u0004X\u0003BAD\u0003\u001b#B!!#\u0002\u0010B!\u0001GUAF!\r!\u0014Q\u0012\u0003\u0007\u0003;b\"\u0019A\u001c\t\u000f\u0005EE\u00041\u0001\u0002\u0014\u0006\ta\r\u0005\u0004:\u0003+\u001b\u00141R\u0005\u0004\u0003/S#!\u0003$v]\u000e$\u0018n\u001c82\u0003\u0019\u0019H.[2faQ1\u0011QTAP\u0003G\u00032\u0001\r*4\u0011\u0019\t\t+\ba\u0001-\u0006\u0011An\u001c\u0005\u0007\u0003Kk\u0002\u0019\u0001,\u0002\u0005!L\u0017\u0001\u0002;bS2,\"!!(\u0002\t%t\u0017\u000e^\u0001\u0011m\u0016\u001cGo\u001c:TY&\u001cWmQ8v]R\f1B^3di>\u00148\u000b\\5dKR!\u00111WAea\u0011\t),!0\u0011\u000be\n9,a/\n\u0007\u0005e&FA\u0003BeJ\f\u0017\u0010E\u00025\u0003{#1\"a0\"\u0003\u0003\u0005\tQ!\u0001\u0002B\n!q\fJ\u00195#\rA\u00141\u0019\t\u0004s\u0005\u0015\u0017bAAdU\t1\u0011I\\=SK\u001aDa!a3\"\u0001\u00041\u0016aA5eq\u00069b/Z2u_J\u001cF.[2f!J,g-\u001b=MK:<G\u000f\u001b\u000b\u0004-\u0006E\u0007BBAfE\u0001\u0007a+A\u0007qe\u0016\u0004XM\u001c3fI\u0006cG\u000eM\u000b\u0005\u0003/\fi\u000e\u0006\u0004\u0002Z\u0006}\u00171\u001e\t\u0005aI\u000bY\u000eE\u00025\u0003;$q!!\u0018$\u0005\u0004\ty\u0006C\u0004\u0002b\u000e\u0002\r!a9\u0002\rA\u0014XMZ5y!\u0019\t)/a:\u0002\\6\t\u0001&C\u0002\u0002j\"\u0012A\"\u0013;fe\u0006\u0014G.Z(oG\u0016Da!!<$\u0001\u00041\u0016!A6\u0002\u0019\u0005\u0004\b/\u001a8eK\u0012\fE\u000e\u001c\u0019\u0016\t\u0005M\u0018\u0011 \u000b\u0007\u0003k\fYP!\u0001\u0011\tA\u0012\u0016q\u001f\t\u0004i\u0005eHaBA/I\t\u0007\u0011q\f\u0005\b\u0003{$\u0003\u0019AA\u0000\u0003\u0019\u0019XO\u001a4jqB1\u0011Q]At\u0003oDa!!<%\u0001\u00041\u0006
   #10 = Utf8               len1
   #11 = Utf8               I
   #12 = Utf8               prefix2
   #13 = Utf8               [[Ljava/lang/Object;
   #14 = Utf8               len12
   #15 = Utf8               data3
   #16 = Utf8               [[[Ljava/lang/Object;
   #17 = Utf8               suffix2
   #18 = Utf8               ()I
   #19 = NameAndType        #10:#11       // len1:I
   #20 = Fieldref           #2.#19        // scala/collection/immutable/Vector3.len1:I
   #21 = Utf8               this
   #22 = Utf8               Lscala/collection/immutable/Vector3;
   #23 = Utf8               ()[[Ljava/lang/Object;
   #24 = NameAndType        #12:#13       // prefix2:[[Ljava/lang/Object;
   #25 = Fieldref           #2.#24        // scala/collection/immutable/Vector3.prefix2:[[Ljava/lang/Object;
   #26 = NameAndType        #14:#11       // len12:I
   #27 = Fieldref           #2.#26        // scala/collection/immutable/Vector3.len12:I
   #28 = Utf8               ()[[[Ljava/lang/Object;
   #29 = NameAndType        #15:#16       // data3:[[[Ljava/lang/Object;
   #30 = Fieldref           #2.#29        // scala/collection/immutable/Vector3.data3:[[[Ljava/lang/Object;
   #31 = NameAndType        #17:#13       // suffix2:[[Ljava/lang/Object;
   #32 = Fieldref           #2.#31        // scala/collection/immutable/Vector3.suffix2:[[Ljava/lang/Object;
   #33 = Utf8               copy
   #34 = Utf8               ([Ljava/lang/Object;I[[Ljava/lang/Object;I[[[Ljava/lang/Object;[[Ljava/lang/Object;[Ljava/lang/Object;I)Lscala/collection/immutable/Vector3;
   #35 = Utf8               ([Ljava/lang/Object;I[[Ljava/lang/Object;I[[[Ljava/lang/Object;[[Ljava/lang/Object;[Ljava/lang/Object;I)Lscala/collection/immutable/Vector3<Lscala/runtime/Nothing$;>;
   #36 = Utf8               prefix1
   #37 = Utf8               suffix1
   #38 = Utf8               length0
   #39 = Utf8               <init>
   #40 = Utf8               ([Ljava/lang/Object;I[[Ljava/lang/Object;I[[[Ljava/lang/Object;[[Ljava/lang/Object;[Ljava/lang/Object;I)V
   #41 = NameAndType        #39:#40       // "<init>":([Ljava/lang/Object;I[[Ljava/lang/Object;I[[[Ljava/lang/Object;[[Ljava/lang/Object;[Ljava/lang/Object;I)V
   #42 = Methodref          #2.#41        // scala/collection/immutable/Vector3."<init>":([Ljava/lang/Object;I[[Ljava/lang/Object;I[[[Ljava/lang/Object;[[Ljava/lang/Object;[Ljava/lang/Object;I)V
   #43 = Utf8               [Ljava/lang/Object;
   #44 = Utf8               copy$default$1
   #45 = Utf8               ()[Ljava/lang/Object;
   #46 = NameAndType        #36:#45       // prefix1:()[Ljava/lang/Object;
   #47 = Methodref          #2.#46        // scala/collection/immutable/Vector3.prefix1:()[Ljava/lang/Object;
   #48 = Utf8               copy$default$2
   #49 = NameAndType        #10:#18       // len1:()I
   #50 = Methodref          #2.#49        // scala/collection/immutable/Vector3.len1:()I
   #51 = Utf8               copy$default$3
   #52 = NameAndType        #12:#23       // prefix2:()[[Ljava/lang/Object;
   #53 = Methodref          #2.#52        // scala/collection/immutable/Vector3.prefix2:()[[Ljava/lang/Object;
   #54 = Utf8               copy$default$4
   #55 = NameAndType        #14:#18       // len12:()I
   #56 = Methodref          #2.#55        // scala/collection/immutable/Vector3.len12:()I
   #57 = Utf8               copy$default$5
   #58 = NameAndType        #15:#28       // data3:()[[[Ljava/lang/Object;
   #59 = Methodref          #2.#58        // scala/collection/immutable/Vector3.data3:()[[[Ljava/lang/Object;
   #60 = Utf8               copy$default$6
   #61 = NameAndType        #17:#23       // suffix2:()[[Ljava/lang/Object;
   #62 = Methodref          #2.#61        // scala/collection/immutable/Vector3.suffix2:()[[Ljava/lang/Object;
   #63 = Utf8               copy$default$7
   #64 = NameAndType        #37:#45       // suffix1:()[Ljava/lang/Object;
   #65 = Methodref          #2.#64        // scala/collection/immutable/Vector3.suffix1:()[Ljava/lang/Object;
   #66 = Utf8               copy$default$8
   #67 = NameAndType        #38:#18       // length0:()I
   #68 = Methodref          #2.#67        // scala/collection/immutable/Vector3.length0:()I
   #69 = Utf8               apply
   #70 = Utf8               (I)Ljava/lang/Object;
   #71 = Utf8               (I)TA;
   #72 = Utf8               index
   #73 = Utf8               ioob
   #74 = Utf8               (I)Ljava/lang/IndexOutOfBoundsException;
   #75 = NameAndType        #73:#74       // ioob:(I)Ljava/lang/IndexOutOfBoundsException;
   #76 = Methodref          #2.#75        // scala/collection/immutable/Vector3.ioob:(I)Ljava/lang/IndexOutOfBoundsException;
   #77 = Utf8               i3
   #78 = Utf8               i2
   #79 = Utf8               i1
   #80 = Utf8               io
   #81 = Utf8               updated
   #82 = Utf8               (ILjava/lang/Object;)Lscala/collection/immutable/Vector;
   #83 = Utf8               <B:Ljava/lang/Object;>(ITB;)Lscala/collection/immutable/Vector<TB;>;
   #84 = Utf8               elem
   #85 = Utf8               scala/collection/immutable/VectorInline$
   #86 = Class              #85           // scala/collection/immutable/VectorInline$
   #87 = Utf8               MODULE$
   #88 = Utf8               Lscala/collection/immutable/VectorInline$;
   #89 = NameAndType        #87:#88       // MODULE$:Lscala/collection/immutable/VectorInline$;
   #90 = Fieldref           #86.#89       // scala/collection/immutable/VectorInline$.MODULE$:Lscala/collection/immutable/VectorInline$;
   #91 = Class              #16           // "[[[Ljava/lang/Object;"
   #92 = Utf8               clone
   #93 = Utf8               ()Ljava/lang/Object;
   #94 = NameAndType        #92:#93       // clone:()Ljava/lang/Object;
   #95 = Methodref          #91.#94       // "[[[Ljava/lang/Object;".clone:()Ljava/lang/Object;
   #96 = Class              #13           // "[[Ljava/lang/Object;"
   #97 = Methodref          #96.#94       // "[[Ljava/lang/Object;".clone:()Ljava/lang/Object;
   #98 = Class              #43           // "[Ljava/lang/Object;"
   #99 = Methodref          #98.#94       // "[Ljava/lang/Object;".clone:()Ljava/lang/Object;
  #100 = Utf8               x$1
  #101 = Utf8               x$2
  #102 = Utf8               x$4
  #103 = Utf8               x$6
  #104 = Utf8               x$7
  #105 = Utf8               x$9
  #106 = Utf8               x$10
  #107 = Utf8               x$12
  #108 = Utf8               x$14
  #109 = Utf8               x$15
  #110 = Utf8               x$17
  #111 = Utf8               x$18
  #112 = Utf8               x$20
  #113 = Utf8               x$22
  #114 = Utf8               x$23
  #115 = Utf8               x$25
  #116 = Utf8               x$26
  #117 = Utf8               x$29
  #118 = Utf8               x$30
  #119 = Utf8               x$31
  #120 = Utf8               Ljava/lang/Object;
  #121 = Utf8               copyUpdate_a3c
  #122 = Utf8               copyUpdate_a3
  #123 = Utf8               copyUpdate_copyUpdate_a2c
  #124 = Utf8               copyUpdate_copyUpdate_copyUpdate_a1c
  #125 = Utf8               copyUpdate_a2c
  #126 = Utf8               copyUpdate_a2
  #127 = Utf8               copyUpdate_copyUpdate_a1c
  #128 = Utf8               copyUpdate_a1c
  #129 = Utf8               copyUpdate_a1
  #130 = Utf8               copyUpdate_idx2
  #131 = Utf8               copyUpdate_idx1
  #132 = Utf8               copy_prefix1
  #133 = Utf8               copy_prefix2
  #134 = Utf8               copy_data3
  #135 = Utf8               copy_suffix2
  #136 = Utf8               copy_suffix1
  #137 = Utf8               java/lang/Object
  #138 = Class              #137          // java/lang/Object
  #139 = Utf8               appended
  #140 = Utf8               (Ljava/lang/Object;)Lscala/collection/immutable/Vector;
  #141 = Utf8               <B:Ljava/lang/Object;>(TB;)Lscala/collection/immutable/Vector<TB;>;
  #142 = Utf8               scala/collection/immutable/VectorStatics$
  #143 = Class              #142          // scala/collection/immutable/VectorStatics$
  #144 = Utf8               Lscala/collection/immutable/VectorStatics$;
  #145 = NameAndType        #87:#144      // MODULE$:Lscala/collection/immutable/VectorStatics$;
  #146 = Fieldref           #143.#145     // scala/collection/immutable/VectorStatics$.MODULE$:Lscala/collection/immutable/VectorStatics$;
  #147 = Utf8               copyAppend1
  #148 = Utf8               ([Ljava/lang/Object;Ljava/lang/Object;)[Ljava/lang/Object;
  #149 = NameAndType        #147:#148     // copyAppend1:([Ljava/lang/Object;Ljava/lang/Object;)[Ljava/lang/Object;
  #150 = Methodref          #143.#149     // scala/collection/immutable/VectorStatics$.copyAppend1:([Ljava/lang/Object;Ljava/lang/Object;)[Ljava/lang/Object;
  #151 = Utf8               copyAppend
  #152 = NameAndType        #151:#148     // copyAppend:([Ljava/lang/Object;Ljava/lang/Object;)[Ljava/lang/Object;
  #153 = Methodref          #143.#152     // scala/collection/immutable/VectorStatics$.copyAppend:([Ljava/lang/Object;Ljava/lang/Object;)[Ljava/lang/Object;
  #154 = Utf8               empty2
  #155 = NameAndType        #154:#23      // empty2:()[[Ljava/lang/Object;
  #156 = Methodref          #143.#155     // scala/collection/immutable/VectorStatics$.empty2:()[[Ljava/lang/Object;
  #157 = Utf8               scala/collection/immutable/Vector4
  #158 = Class              #157          // scala/collection/immutable/Vector4
  #159 = Utf8               empty4
  #160 = Utf8               ()[[[[Ljava/lang/Object;
  #161 = NameAndType        #159:#160     // empty4:()[[[[Ljava/lang/Object;
  #162 = Methodref          #143.#161     // scala/collection/immutable/VectorStatics$.empty4:()[[[[Ljava/lang/Object;
  #163 = Utf8               ([Ljava/lang/Object;I[[Ljava/lang/Object;I[[[Ljava/lang/Object;I[[[[Ljava/lang/Object;[[[Ljava/lang/Object;[[Ljava/lang/Object;[Ljava/lang/Object;I)V
  #164 = NameAndType        #39:#163      // "<init>":([Ljava/lang/Object;I[[Ljava/lang/Object;I[[[Ljava/lang/Object;I[[[[Ljava/lang/Object;[[[Ljava/lang/Object;[[Ljava/lang/Object;[Ljava/lang/Object;I)V
  #165 = Methodref          #158.#164     // scala/collection/immutable/Vector4."<init>":([Ljava/lang/Object;I[[Ljava/lang/Object;I[[[Ljava/lang/Object;I[[[[Ljava/lang/Object;[[[Ljava/lang/Object;[[Ljava/lang/Object;[Ljava/lang/Object;I)V
  #166 = Utf8               x$3
  #167 = Utf8               x$5
  #168 = Utf8               x$8
  #169 = Utf8               x$11
  #170 = Utf8               x$16
  #171 = Utf8               x$19
  #172 = Utf8               x$21
  #173 = Utf8               wrap1_a
  #174 = Utf8               wrap3_a
  #175 = Utf8               wrap3_x
  #176 = Utf8               prepended
  #177 = Utf8               copyPrepend1
  #178 = Utf8               (Ljava/lang/Object;[Ljava/lang/Object;)[Ljava/lang/Object;
  #179 = NameAndType        #177:#178     // copyPrepend1:(Ljava/lang/Object;[Ljava/lang/Object;)[Ljava/lang/Object;
  #180 = Methodref          #143.#179     // scala/collection/immutable/VectorStatics$.copyPrepend1:(Ljava/lang/Object;[Ljava/lang/Object;)[Ljava/lang/Object;
  #181 = Utf8               copyPrepend
  #182 = NameAndType        #181:#178     // copyPrepend:(Ljava/lang/Object;[Ljava/lang/Object;)[Ljava/lang/Object;
  #183 = Methodref          #143.#182     // scala/collection/immutable/VectorStatics$.copyPrepend:(Ljava/lang/Object;[Ljava/lang/Object;)[Ljava/lang/Object;
  #184 = Utf8               x$13
  #185 = Utf8               x$24
  #186 = Utf8               copy_len1
  #187 = Utf8               copy_len12
  #188 = Utf8               map
  #189 = Utf8               (Lscala/Function1;)Lscala/collection/immutable/Vector;
  #190 = Utf8               <B:Ljava/lang/Object;>(Lscala/Function1<TA;TB;>;)Lscala/collection/immutable/Vector<TB;>;
  #191 = Utf8               f
  #192 = Utf8               scala/Function1
  #193 = Class              #192          // scala/Function1
  #194 = Utf8               (Ljava/lang/Object;)Ljava/lang/Object;
  #195 = NameAndType        #69:#194      // apply:(Ljava/lang/Object;)Ljava/lang/Object;
  #196 = InterfaceMethodref #193.#195     // scala/Function1.apply:(Ljava/lang/Object;)Ljava/lang/Object;
  #197 = Utf8               java/lang/System
  #198 = Class              #197          // java/lang/System
  #199 = Utf8               arraycopy
  #200 = Utf8               (Ljava/lang/Object;ILjava/lang/Object;II)V
  #201 = NameAndType        #199:#200     // arraycopy:(Ljava/lang/Object;ILjava/lang/Object;II)V
  #202 = Methodref          #198.#201     // java/lang/System.arraycopy:(Ljava/lang/Object;ILjava/lang/Object;II)V
  #203 = Utf8               mapElems
  #204 = Utf8               (I[Ljava/lang/Object;Lscala/Function1;)[Ljava/lang/Object;
  #205 = NameAndType        #203:#204     // mapElems:(I[Ljava/lang/Object;Lscala/Function1;)[Ljava/lang/Object;
  #206 = Methodref          #143.#205     // scala/collection/immutable/VectorStatics$.mapElems:(I[Ljava/lang/Object;Lscala/Function1;)[Ljava/lang/Object;
  #207 = Utf8               getClass
  #208 = Utf8               ()Ljava/lang/Class;
  #209 = NameAndType        #207:#208     // getClass:()Ljava/lang/Class;
  #210 = Methodref          #138.#209     // java/lang/Object.getClass:()Ljava/lang/Class;
  #211 = Utf8               java/lang/Class
  #212 = Class              #211          // java/lang/Class
  #213 = Utf8               getComponentType
  #214 = NameAndType        #213:#208     // getComponentType:()Ljava/lang/Class;
  #215 = Methodref          #212.#214     // java/lang/Class.getComponentType:()Ljava/lang/Class;
  #216 = Utf8               java/lang/reflect/Array
  #217 = Class              #216          // java/lang/reflect/Array
  #218 = Utf8               newInstance
  #219 = Utf8               (Ljava/lang/Class;I)Ljava/lang/Object;
  #220 = NameAndType        #218:#219     // newInstance:(Ljava/lang/Class;I)Ljava/lang/Object;
  #221 = Methodref          #217.#220     // java/lang/reflect/Array.newInstance:(Ljava/lang/Class;I)Ljava/lang/Object;
  #222 = Utf8               mapElemsRest
  #223 = Utf8               (I[Ljava/lang/Object;Lscala/Function1;ILjava/lang/Object;)[Ljava/lang/Object;
  #224 = NameAndType        #222:#223     // mapElemsRest:(I[Ljava/lang/Object;Lscala/Function1;ILjava/lang/Object;)[Ljava/lang/Object;
  #225 = Methodref          #143.#224     // scala/collection/immutable/VectorStatics$.mapElemsRest:(I[Ljava/lang/Object;Lscala/Function1;ILjava/lang/Object;)[Ljava/lang/Object;
  #226 = Utf8               Lscala/Function1;
  #227 = Utf8               mapElems1_v1
  #228 = Utf8               mapElems1_v2
  #229 = Utf8               mapElems1_i
  #230 = Utf8               mapElems1_a
  #231 = Utf8               mapElems1_mapElems1Rest_ac
  #232 = Utf8               mapElems1_mapElems1Rest_i
  #233 = Utf8               mapElems_v1
  #234 = Utf8               mapElems_v2
  #235 = Utf8               mapElems_i
  #236 = Utf8               mapElems_this
  #237 = Utf8               mapElems_n
  #238 = Utf8               mapElems_a
  #239 = Utf8               mapElems_mapElems1_v1
  #240 = Utf8               mapElems_mapElems1_v2
  #241 = Utf8               mapElems_mapElems1_i
  #242 = Utf8               mapElems_mapElems1_mapElems1Rest_ac
  #243 = Utf8               mapElems_mapElems1_mapElems1Rest_i
  #244 = Utf8               mapElemsRest_ac
  #245 = Utf8               mapElemsRest_i
  #246 = Utf8               mapElemsRest_mapElems_v1
  #247 = Utf8               mapElemsRest_mapElems_v2
  #248 = Utf8               mapElemsRest_mapElems_i
  #249 = Utf8               mapElemsRest_mapElems_n
  #250 = Utf8               mapElemsRest_mapElems_a
  #251 = Utf8               mapElemsRest_mapElems_mapElems1_v1
  #252 = Utf8               mapElemsRest_mapElems_mapElems1_v2
  #253 = Utf8               mapElemsRest_mapElems_mapElems1_i
  #254 = Utf8               mapElemsRest_mapElems_mapElems1_mapElems1Rest_ac
  #255 = Utf8               mapElemsRest_mapElems_mapElems1_mapElems1Rest_i
  #256 = Utf8               slice0
  #257 = Utf8               (II)Lscala/collection/immutable/Vector;
  #258 = Utf8               (II)Lscala/collection/immutable/Vector<TA;>;
  #259 = Utf8               lo
  #260 = Utf8               hi
  #261 = Utf8               scala/collection/immutable/VectorSliceBuilder
  #262 = Class              #261          // scala/collection/immutable/VectorSliceBuilder
  #263 = Utf8               (II)V
  #264 = NameAndType        #39:#263      // "<init>":(II)V
  #265 = Methodref          #262.#264     // scala/collection/immutable/VectorSliceBuilder."<init>":(II)V
  #266 = Utf8               consider
  #267 = Utf8               (I[Ljava/lang/Object;)V
  #268 = NameAndType        #266:#267     // consider:(I[Ljava/lang/Object;)V
  #269 = Methodref          #262.#268     // scala/collection/immutable/VectorSliceBuilder.consider:(I[Ljava/lang/Object;)V
  #270 = Utf8               result
  #271 = Utf8               ()Lscala/collection/immutable/Vector;
  #272 = NameAndType        #270:#271     // result:()Lscala/collection/immutable/Vector;
  #273 = Methodref          #262.#272     // scala/collection/immutable/VectorSliceBuilder.result:()Lscala/collection/immutable/Vector;
  #274 = Utf8               b
  #275 = Utf8               Lscala/collection/immutable/VectorSliceBuilder;
  #276 = Utf8               tail
  #277 = Utf8               ()Lscala/collection/immutable/Vector<TA;>;
  #278 = Utf8               java/util/Arrays
  #279 = Class              #278          // java/util/Arrays
  #280 = Utf8               copyOfRange
  #281 = Utf8               ([Ljava/lang/Object;II)[Ljava/lang/Object;
  #282 = NameAndType        #280:#281     // copyOfRange:([Ljava/lang/Object;II)[Ljava/lang/Object;
  #283 = Methodref          #279.#282     // java/util/Arrays.copyOfRange:([Ljava/lang/Object;II)[Ljava/lang/Object;
  #284 = NameAndType        #256:#257     // slice0:(II)Lscala/collection/immutable/Vector;
  #285 = Methodref          #2.#284       // scala/collection/immutable/Vector3.slice0:(II)Lscala/collection/immutable/Vector;
  #286 = Utf8               copyTail_a
  #287 = Utf8               init
  #288 = Utf8               copyInit_a
  #289 = Utf8               vectorSliceCount
  #290 = Utf8               vectorSlice
  #291 = Utf8               (I)[Ljava/lang/Object;
  #292 = Utf8               idx
  #293 = Utf8               scala/MatchError
  #294 = Class              #293          // scala/MatchError
  #295 = Utf8               java/lang/Integer
  #296 = Class              #295          // java/lang/Integer
  #297 = Utf8               valueOf
  #298 = Utf8               (I)Ljava/lang/Integer;
  #299 = NameAndType        #297:#298     // valueOf:(I)Ljava/lang/Integer;
  #300 = Methodref          #296.#299     // java/lang/Integer.valueOf:(I)Ljava/lang/Integer;
  #301 = Utf8               (Ljava/lang/Object;)V
  #302 = NameAndType        #39:#301      // "<init>":(Ljava/lang/Object;)V
  #303 = Methodref          #294.#302     // scala/MatchError."<init>":(Ljava/lang/Object;)V
  #304 = Utf8               vectorSlicePrefixLength
  #305 = Utf8               (I)I
  #306 = Utf8               prependedAll0
  #307 = Utf8               (Lscala/collection/IterableOnce;I)Lscala/collection/immutable/Vector;
  #308 = Utf8               <B:Ljava/lang/Object;>(Lscala/collection/IterableOnce<TB;>;I)Lscala/collection/immutable/Vector<TB;>;
  #309 = Utf8               prefix
  #310 = Utf8               k
  #311 = Utf8               prepend1IfSpace
  #312 = Utf8               ([Ljava/lang/Object;Lscala/collection/IterableOnce;)[Ljava/lang/Object;
  #313 = NameAndType        #311:#312     // prepend1IfSpace:([Ljava/lang/Object;Lscala/collection/IterableOnce;)[Ljava/lang/Object;
  #314 = Methodref          #143.#313     // scala/collection/immutable/VectorStatics$.prepend1IfSpace:([Ljava/lang/Object;Lscala/collection/IterableOnce;)[Ljava/lang/Object;
  #315 = Utf8               scala/collection/immutable/Vector
  #316 = Class              #315          // scala/collection/immutable/Vector
  #317 = NameAndType        #306:#307     // prependedAll0:(Lscala/collection/IterableOnce;I)Lscala/collection/immutable/Vector;
  #318 = Methodref          #316.#317     // scala/collection/immutable/Vector.prependedAll0:(Lscala/collection/IterableOnce;I)Lscala/collection/immutable/Vector;
  #319 = Utf8               prefix1b
  #320 = Utf8               Lscala/collection/IterableOnce;
  #321 = Utf8               appendedAll0
  #322 = Utf8               suffix
  #323 = Utf8               append1IfSpace
  #324 = NameAndType        #323:#312     // append1IfSpace:([Ljava/lang/Object;Lscala/collection/IterableOnce;)[Ljava/lang/Object;
  #325 = Methodref          #143.#324     // scala/collection/immutable/VectorStatics$.append1IfSpace:([Ljava/lang/Object;Lscala/collection/IterableOnce;)[Ljava/lang/Object;
  #326 = NameAndType        #321:#307     // appendedAll0:(Lscala/collection/IterableOnce;I)Lscala/collection/immutable/Vector;
  #327 = Methodref          #316.#326     // scala/collection/immutable/Vector.appendedAll0:(Lscala/collection/IterableOnce;I)Lscala/collection/immutable/Vector;
  #328 = Utf8               suffix1b
  #329 = NameAndType        #287:#271     // init:()Lscala/collection/immutable/Vector;
  #330 = Methodref          #2.#329       // scala/collection/immutable/Vector3.init:()Lscala/collection/immutable/Vector;
  #331 = NameAndType        #276:#271     // tail:()Lscala/collection/immutable/Vector;
  #332 = Methodref          #2.#331       // scala/collection/immutable/Vector3.tail:()Lscala/collection/immutable/Vector;
  #333 = Utf8               (Lscala/Function1;)Ljava/lang/Object;
  #334 = NameAndType        #188:#189     // map:(Lscala/Function1;)Lscala/collection/immutable/Vector;
  #335 = Methodref          #2.#334       // scala/collection/immutable/Vector3.map:(Lscala/Function1;)Lscala/collection/immutable/Vector;
  #336 = NameAndType        #176:#140     // prepended:(Ljava/lang/Object;)Lscala/collection/immutable/Vector;
  #337 = Methodref          #2.#336       // scala/collection/immutable/Vector3.prepended:(Ljava/lang/Object;)Lscala/collection/immutable/Vector;
  #338 = NameAndType        #139:#140     // appended:(Ljava/lang/Object;)Lscala/collection/immutable/Vector;
  #339 = Methodref          #2.#338       // scala/collection/immutable/Vector3.appended:(Ljava/lang/Object;)Lscala/collection/immutable/Vector;
  #340 = Utf8               (ILjava/lang/Object;)Ljava/lang/Object;
  #341 = NameAndType        #81:#82       // updated:(ILjava/lang/Object;)Lscala/collection/immutable/Vector;
  #342 = Methodref          #2.#341       // scala/collection/immutable/Vector3.updated:(ILjava/lang/Object;)Lscala/collection/immutable/Vector;
  #343 = Utf8               v1
  #344 = Utf8               scala/runtime/BoxesRunTime
  #345 = Class              #344          // scala/runtime/BoxesRunTime
  #346 = Utf8               unboxToInt
  #347 = Utf8               (Ljava/lang/Object;)I
  #348 = NameAndType        #346:#347     // unboxToInt:(Ljava/lang/Object;)I
  #349 = Methodref          #345.#348     // scala/runtime/BoxesRunTime.unboxToInt:(Ljava/lang/Object;)I
  #350 = NameAndType        #69:#70       // apply:(I)Ljava/lang/Object;
  #351 = Methodref          #2.#350       // scala/collection/immutable/Vector3.apply:(I)Ljava/lang/Object;
  #352 = Utf8               _prefix1
  #353 = Utf8               _suffix1
  #354 = Utf8               _length0
  #355 = Utf8               ([Ljava/lang/Object;[Ljava/lang/Object;I)V
  #356 = NameAndType        #39:#355      // "<init>":([Ljava/lang/Object;[Ljava/lang/Object;I)V
  #357 = Methodref          #5.#356       // scala/collection/immutable/BigVector."<init>":([Ljava/lang/Object;[Ljava/lang/Object;I)V
  #358 = Utf8               Code
  #359 = Utf8               LineNumberTable
  #360 = Utf8               LocalVariableTable
  #361 = Utf8               Signature
  #362 = Utf8               MethodParameters
  #363 = Utf8               StackMapTable
  #364 = Utf8               SourceFile
  #365 = Utf8               RuntimeVisibleAnnotations
  #366 = Utf8               ScalaInlineInfo
  #367 = Utf8               ScalaSig
{
  private final int len1;
    descriptor: I
    flags: (0x0012) ACC_PRIVATE, ACC_FINAL

  private final java.lang.Object[][] prefix2;
    descriptor: [[Ljava/lang/Object;
    flags: (0x0012) ACC_PRIVATE, ACC_FINAL

  private final int len12;
    descriptor: I
    flags: (0x0012) ACC_PRIVATE, ACC_FINAL

  private final java.lang.Object[][][] data3;
    descriptor: [[[Ljava/lang/Object;
    flags: (0x0012) ACC_PRIVATE, ACC_FINAL

  private final java.lang.Object[][] suffix2;
    descriptor: [[Ljava/lang/Object;
    flags: (0x0012) ACC_PRIVATE, ACC_FINAL

  public int len1();
    descriptor: ()I
    flags: (0x0001) ACC_PUBLIC
    Code:
      stack=1, locals=1, args_size=1
         0: aload_0
         1: getfield      #20                 // Field len1:I
         4: ireturn
      LineNumberTable:
        line 527: 0
      LocalVariableTable:
        Start  Length  Slot  Name   Signature
            0       5     0  this   Lscala/collection/immutable/Vector3;

  public java.lang.Object[][] prefix2();
    descriptor: ()[[Ljava/lang/Object;
    flags: (0x0001) ACC_PUBLIC
    Code:
      stack=1, locals=1, args_size=1
         0: aload_0
         1: getfield      #25                 // Field prefix2:[[Ljava/lang/Object;
         4: areturn
      LineNumberTable:
        line 528: 0
      LocalVariableTable:
        Start  Length  Slot  Name   Signature
            0       5     0  this   Lscala/collection/immutable/Vector3;

  public int len12();
    descriptor: ()I
    flags: (0x0001) ACC_PUBLIC
    Code:
      stack=1, locals=1, args_size=1
         0: aload_0
         1: getfield      #27                 // Field len12:I
         4: ireturn
      LineNumberTable:
        line 528: 0
      LocalVariableTable:
        Start  Length  Slot  Name   Signature
            0       5     0  this   Lscala/collection/immutable/Vector3;

  public java.lang.Object[][][] data3();
    descriptor: ()[[[Ljava/lang/Object;
    flags: (0x0001) ACC_PUBLIC
    Code:
      stack=1, locals=1, args_size=1
         0: aload_0
         1: getfield      #30                 // Field data3:[[[Ljava/lang/Object;
         4: areturn
      LineNumberTable:
        line 529: 0
      LocalVariableTable:
        Start  Length  Slot  Name   Signature
            0       5     0  this   Lscala/collection/immutable/Vector3;

  public java.lang.Object[][] suffix2();
    descriptor: ()[[Ljava/lang/Object;
    flags: (0x0001) ACC_PUBLIC
    Code:
      stack=1, locals=1, args_size=1
         0: aload_0
         1: getfield      #32                 // Field suffix2:[[Ljava/lang/Object;
         4: areturn
      LineNumberTable:
        line 530: 0
      LocalVariableTable:
        Start  Length  Slot  Name   Signature
            0       5     0  this   Lscala/collection/immutable/Vector3;

  private scala.collection.immutable.Vector3<scala.runtime.Nothing$> copy(java.lang.Object[], int, java.lang.Object[][], int, java.lang.Object[][][], java.lang.Object[][], java.lang.Object[], int);
    descriptor: ([Ljava/lang/Object;I[[Ljava/lang/Object;I[[[Ljava/lang/Object;[[Ljava/lang/Object;[Ljava/lang/Object;I)Lscala/collection/immutable/Vector3;
    flags: (0x0002) ACC_PRIVATE
    Code:
      stack=10, locals=9, args_size=9
         0: new           #2                  // class scala/collection/immutable/Vector3
         3: dup
         4: aload_1
         5: iload_2
         6: aload_3
         7: iload         4
         9: aload         5
        11: aload         6
        13: aload         7
        15: iload         8
        17: invokespecial #42                 // Method "<init>":([Ljava/lang/Object;I[[Ljava/lang/Object;I[[[Ljava/lang/Object;[[Ljava/lang/Object;[Ljava/lang/Object;I)V
        20: areturn
      LineNumberTable:
        line 538: 0
      LocalVariableTable:
        Start  Length  Slot  Name   Signature
            0      21     0  this   Lscala/collection/immutable/Vector3;
            0      21     1 prefix1   [Ljava/lang/Object;
            0      21     2  len1   I
            0      21     3 prefix2   [[Ljava/lang/Object;
            0      21     4 len12   I
            0      21     5 data3   [[[Ljava/lang/Object;
            0      21     6 suffix2   [[Ljava/lang/Object;
            0      21     7 suffix1   [Ljava/lang/Object;
            0      21     8 length0   I
    Signature: #35                          // ([Ljava/lang/Object;I[[Ljava/lang/Object;I[[[Ljava/lang/Object;[[Ljava/lang/Object;[Ljava/lang/Object;I)Lscala/collection/immutable/Vector3<Lscala/runtime/Nothing$;>;
    MethodParameters:
      Name                           Flags
      prefix1                        final
      len1                           final
      prefix2                        final
      len12                          final
      data3                          final
      suffix2                        final
      suffix1                        final
      length0                        final

  private java.lang.Object[] copy$default$1();
    descriptor: ()[Ljava/lang/Object;
    flags: (0x0002) ACC_PRIVATE
    Code:
      stack=1, locals=1, args_size=1
         0: aload_0
         1: invokevirtual #47                 // Method prefix1:()[Ljava/lang/Object;
         4: areturn
      LineNumberTable:
        line 533: 0
      LocalVariableTable:
        Start  Length  Slot  Name   Signature
            0       5     0  this   Lscala/collection/immutable/Vector3;

  private int copy$default$2();
    descriptor: ()I
    flags: (0x0002) ACC_PRIVATE
    Code:
      stack=1, locals=1, args_size=1
         0: aload_0
         1: invokevirtual #50                 // Method len1:()I
         4: ireturn
      LineNumberTable:
        line 533: 0
      LocalVariableTable:
        Start  Length  Slot  Name   Signature
            0       5     0  this   Lscala/collection/immutable/Vector3;

  private java.lang.Object[][] copy$default$3();
    descriptor: ()[[Ljava/lang/Object;
    flags: (0x0002) ACC_PRIVATE
    Code:
      stack=1, locals=1, args_size=1
         0: aload_0
         1: invokevirtual #53                 // Method prefix2:()[[Ljava/lang/Object;
         4: areturn
      LineNumberTable:
        line 534: 0
      LocalVariableTable:
        Start  Length  Slot  Name   Signature
            0       5     0  this   Lscala/collection/immutable/Vector3;

  private int copy$default$4();
    descriptor: ()I
    flags: (0x0002) ACC_PRIVATE
    Code:
      stack=1, locals=1, args_size=1
         0: aload_0
         1: invokevirtual #56                 // Method len12:()I
         4: ireturn
      LineNumberTable:
        line 534: 0
      LocalVariableTable:
        Start  Length  Slot  Name   Signature
            0       5     0  this   Lscala/collection/immutable/Vector3;

  private java.lang.Object[][][] copy$default$5();
    descriptor: ()[[[Ljava/lang/Object;
    flags: (0x0002) ACC_PRIVATE
    Code:
      stack=1, locals=1, args_size=1
         0: aload_0
         1: invokevirtual #59                 // Method data3:()[[[Ljava/lang/Object;
         4: areturn
      LineNumberTable:
        line 535: 0
      LocalVariableTable:
        Start  Length  Slot  Name   Signature
            0       5     0  this   Lscala/collection/immutable/Vector3;

  private java.lang.Object[][] copy$default$6();
    descriptor: ()[[Ljava/lang/Object;
    flags: (0x0002) ACC_PRIVATE
    Code:
      stack=1, locals=1, args_size=1
         0: aload_0
         1: invokevirtual #62                 // Method suffix2:()[[Ljava/lang/Object;
         4: areturn
      LineNumberTable:
        line 536: 0
      LocalVariableTable:
        Start  Length  Slot  Name   Signature
            0       5     0  this   Lscala/collection/immutable/Vector3;

  private java.lang.Object[] copy$default$7();
    descriptor: ()[Ljava/lang/Object;
    flags: (0x0002) ACC_PRIVATE
    Code:
      stack=1, locals=1, args_size=1
         0: aload_0
         1: invokevirtual #65                 // Method suffix1:()[Ljava/lang/Object;
         4: areturn
      LineNumberTable:
        line 536: 0
      LocalVariableTable:
        Start  Length  Slot  Name   Signature
            0       5     0  this   Lscala/collection/immutable/Vector3;

  private int copy$default$8();
    descriptor: ()I
    flags: (0x0002) ACC_PRIVATE
    Code:
      stack=1, locals=1, args_size=1
         0: aload_0
         1: invokevirtual #68                 // Method length0:()I
         4: ireturn
      LineNumberTable:
        line 537: 0
      LocalVariableTable:
        Start  Length  Slot  Name   Signature
            0       5     0  this   Lscala/collection/immutable/Vector3;

  public A apply(int);
    descriptor: (I)Ljava/lang/Object;
    flags: (0x0001) ACC_PUBLIC
    Code:
      stack=3, locals=7, args_size=2
         0: iload_1
         1: iconst_0
         2: if_icmplt     134
         5: iload_1
         6: aload_0
         7: invokevirtual #68                 // Method length0:()I
        10: if_icmpge     134
        13: iload_1
        14: aload_0
        15: invokevirtual #56                 // Method len12:()I
        18: isub
        19: istore_2
        20: iload_2
        21: iconst_0
        22: if_icmplt     95
        25: iload_2
        26: bipush        10
        28: iushr
        29: istore_3
        30: iload_2
        31: iconst_5
        32: iushr
        33: bipush        31
        35: iand
        36: istore        4
        38: iload_2
        39: bipush        31
        41: iand
        42: istore        5
        44: iload_3
        45: aload_0
        46: invokevirtual #59                 // Method data3:()[[[Ljava/lang/Object;
        49: arraylength
        50: if_icmpge     66
        53: aload_0
        54: invokevirtual #59                 // Method data3:()[[[Ljava/lang/Object;
        57: iload_3
        58: aaload
        59: iload         4
        61: aaload
        62: iload         5
        64: aaload
        65: areturn
        66: iload         4
        68: aload_0
        69: invokevirtual #62                 // Method suffix2:()[[Ljava/lang/Object;
        72: arraylength
        73: if_icmpge     87
        76: aload_0
        77: invokevirtual #62                 // Method suffix2:()[[Ljava/lang/Object;
        80: iload         4
        82: aaload
        83: iload         5
        85: aaload
        86: areturn
        87: aload_0
        88: invokevirtual #65                 // Method suffix1:()[Ljava/lang/Object;
        91: iload         5
        93: aaload
        94: areturn
        95: iload_1
        96: aload_0
        97: invokevirtual #50                 // Method len1:()I
       100: if_icmplt     127
       103: iload_1
       104: aload_0
       105: invokevirtual #50                 // Method len1:()I
       108: isub
       109: istore        6
       111: aload_0
       112: invokevirtual #53                 // Method prefix2:()[[Ljava/lang/Object;
       115: iload         6
       117: iconst_5
       118: iushr
       119: aaload
       120: iload         6
       122: bipush        31
       124: iand
       125: aaload
       126: areturn
       127: aload_0
       128: invokevirtual #47                 // Method prefix1:()[Ljava/lang/Object;
       131: iload_1
       132: aaload
       133: areturn
       134: aload_0
       135: iload_1
       136: invokevirtual #76                 // Method ioob:(I)Ljava/lang/IndexOutOfBoundsException;
       139: athrow
      StackMapTable: number_of_entries = 5
        frame_type = 255 /* full_frame */
          offset_delta = 66
          locals = [ class scala/collection/immutable/Vector3, int, int, int, int, int ]
          stack = []
        frame_type = 20 /* same */
        frame_type = 248 /* chop */
          offset_delta = 7
        frame_type = 31 /* same */
        frame_type = 250 /* chop */
          offset_delta = 6
      LineNumberTable:
        line 541: 0
        line 542: 13
        line 543: 20
        line 544: 25
        line 545: 30
        line 546: 38
        line 547: 44
        line 548: 66
        line 549: 87
        line 550: 95
        line 551: 103
        line 552: 111
        line 553: 127
        line 554: 134
      LocalVariableTable:
        Start  Length  Slot  Name   Signature
           30      64     3    i3   I
           38      56     4    i2   I
           44      50     5    i1   I
          111      15     6    io   I
           20     113     2    io   I
            0     140     0  this   Lscala/collection/immutable/Vector3;
            0     140     1 index   I
    Signature: #71                          // (I)TA;
    MethodParameters:
      Name                           Flags
      index                          final

  public <B extends java.lang.Object> scala.collection.immutable.Vector<B> updated(int, B);
    descriptor: (ILjava/lang/Object;)Lscala/collection/immutable/Vector;
    flags: (0x0001) ACC_PUBLIC
    Code:
      stack=10, locals=79, args_size=3
         0: iload_1
         1: iconst_0
         2: if_icmplt     803
         5: iload_1
         6: aload_0
         7: invokevirtual #68                 // Method length0:()I
        10: if_icmpge     803
        13: iload_1
        14: aload_0
        15: invokevirtual #56                 // Method len12:()I
        18: if_icmplt     527
        21: iload_1
        22: aload_0
        23: invokevirtual #56                 // Method len12:()I
        26: isub
        27: istore_3
        28: iload_3
        29: bipush        10
        31: iushr
        32: istore        4
        34: iload_3
        35: iconst_5
        36: iushr
        37: bipush        31
        39: iand
        40: istore        5
        42: iload_3
        43: bipush        31
        45: iand
        46: istore        6
        48: iload         4
        50: aload_0
        51: invokevirtual #59                 // Method data3:()[[[Ljava/lang/Object;
        54: arraylength
        55: if_icmpge     234
        58: getstatic     #90                 // Field scala/collection/immutable/VectorInline$.MODULE$:Lscala/collection/immutable/VectorInline$;
        61: pop
        62: aload_0
        63: invokevirtual #59                 // Method data3:()[[[Ljava/lang/Object;
        66: astore        28
        68: aload         28
        70: invokevirtual #95                 // Method "[[[Ljava/lang/Object;".clone:()Ljava/lang/Object;
        73: checkcast     #91                 // class "[[[Ljava/lang/Object;"
        76: astore        29
        78: aload         29
        80: iload         4
        82: aload         29
        84: iload         4
        86: aaload
        87: invokevirtual #97                 // Method "[[Ljava/lang/Object;".clone:()Ljava/lang/Object;
        90: checkcast     #96                 // class "[[Ljava/lang/Object;"
        93: astore        30
        95: aload         30
        97: iload         5
        99: aload         30
       101: iload         5
       103: aaload
       104: invokevirtual #99                 // Method "[Ljava/lang/Object;".clone:()Ljava/lang/Object;
       107: checkcast     #98                 // class "[Ljava/lang/Object;"
       110: astore        31
       112: aload         31
       114: iload         6
       116: aload_2
       117: aastore
       118: aload         31
       120: aconst_null
       121: astore        31
       123: aastore
       124: aload         30
       126: aconst_null
       127: astore        30
       129: aastore
       130: aload         29
       132: aconst_null
       133: astore        28
       135: aconst_null
       136: astore        29
       138: astore        7
       140: aload_0
       141: invokevirtual #47                 // Method prefix1:()[Ljava/lang/Object;
       144: astore        48
       146: aload         48
       148: aconst_null
       149: astore        48
       151: astore        8
       153: aload_0
       154: invokevirtual #50                 // Method len1:()I
       157: istore        49
       159: aload_0
       160: invokevirtual #53                 // Method prefix2:()[[Ljava/lang/Object;
       163: astore        50
       165: aload         50
       167: aconst_null
       168: astore        50
       170: astore        9
       172: aload_0
       173: invokevirtual #56                 // Method len12:()I
       176: istore        51
       178: aload_0
       179: invokevirtual #62                 // Method suffix2:()[[Ljava/lang/Object;
       182: astore        52
       184: aload         52
       186: aconst_null
       187: astore        52
       189: astore        10
       191: aload_0
       192: invokevirtual #65                 // Method suffix1:()[Ljava/lang/Object;
       195: astore        53
       197: aload         53
       199: aconst_null
       200: astore        53
       202: astore        11
       204: aload_0
       205: invokevirtual #68                 // Method length0:()I
       208: istore        54
       210: new           #2                  // class scala/collection/immutable/Vector3
       213: dup
       214: aload         8
       216: iload         49
       218: aload         9
       220: iload         51
       222: aload         7
       224: aload         10
       226: aload         11
       228: iload         54
       230: invokespecial #42                 // Method "<init>":([Ljava/lang/Object;I[[Ljava/lang/Object;I[[[Ljava/lang/Object;[[Ljava/lang/Object;[Ljava/lang/Object;I)V
       233: areturn
       234: iload         5
       236: aload_0
       237: invokevirtual #62                 // Method suffix2:()[[Ljava/lang/Object;
       240: arraylength
       241: if_icmpge     397
       244: getstatic     #90                 // Field scala/collection/immutable/VectorInline$.MODULE$:Lscala/collection/immutable/VectorInline$;
       247: pop
       248: aload_0
       249: invokevirtual #62                 // Method suffix2:()[[Ljava/lang/Object;
       252: astore        32
       254: aload         32
       256: invokevirtual #97                 // Method "[[Ljava/lang/Object;".clone:()Ljava/lang/Object;
       259: checkcast     #96                 // class "[[Ljava/lang/Object;"
       262: astore        33
       264: aload         33
       266: iload         5
       268: aload         33
       270: iload         5
       272: aaload
       273: invokevirtual #99                 // Method "[Ljava/lang/Object;".clone:()Ljava/lang/Object;
       276: checkcast     #98                 // class "[Ljava/lang/Object;"
       279: astore        34
       281: aload         34
       283: iload         6
       285: aload_2
       286: aastore
       287: aload         34
       289: aconst_null
       290: astore        34
       292: aastore
       293: aload         33
       295: aconst_null
       296: astore        32
       298: aconst_null
       299: astore        33
       301: astore        12
       303: aload_0
       304: invokevirtual #47                 // Method prefix1:()[Ljava/lang/Object;
       307: astore        55
       309: aload         55
       311: aconst_null
       312: astore        55
       314: astore        13
       316: aload_0
       317: invokevirtual #50                 // Method len1:()I
       320: istore        56
       322: aload_0
       323: invokevirtual #53                 // Method prefix2:()[[Ljava/lang/Object;
       326: astore        57
       328: aload         57
       330: aconst_null
       331: astore        57
       333: astore        14
       335: aload_0
       336: invokevirtual #56                 // Method len12:()I
       339: istore        58
       341: aload_0
       342: invokevirtual #59                 // Method data3:()[[[Ljava/lang/Object;
       345: astore        59
       347: aload         59
       349: aconst_null
       350: astore        59
       352: astore        15
       354: aload_0
       355: invokevirtual #65                 // Method suffix1:()[Ljava/lang/Object;
       358: astore        60
       360: aload         60
       362: aconst_null
       363: astore        60
       365: astore        16
       367: aload_0
       368: invokevirtual #68                 // Method length0:()I
       371: istore        61
       373: new           #2                  // class scala/collection/immutable/Vector3
       376: dup
       377: aload         13
       379: iload         56
       381: aload         14
       383: iload         58
       385: aload         15
       387: aload         12
       389: aload         16
       391: iload         61
       393: invokespecial #42                 // Method "<init>":([Ljava/lang/Object;I[[Ljava/lang/Object;I[[[Ljava/lang/Object;[[Ljava/lang/Object;[Ljava/lang/Object;I)V
       396: areturn
       397: getstatic     #90                 // Field scala/collection/immutable/VectorInline$.MODULE$:Lscala/collection/immutable/VectorInline$;
       400: pop
       401: aload_0
       402: invokevirtual #65                 // Method suffix1:()[Ljava/lang/Object;
       405: astore        35
       407: aload         35
       409: invokevirtual #99                 // Method "[Ljava/lang/Object;".clone:()Ljava/lang/Object;
       412: checkcast     #98                 // class "[Ljava/lang/Object;"
       415: astore        36
       417: aload         36
       419: iload         6
       421: aload_2
       422: aastore
       423: aload         36
       425: aconst_null
       426: astore        35
       428: aconst_null
       429: astore        36
       431: astore        17
       433: aload_0
       434: invokevirtual #47                 // Method prefix1:()[Ljava/lang/Object;
       437: astore        62
       439: aload         62
       441: aconst_null
       442: astore        62
       444: astore        18
       446: aload_0
       447: invokevirtual #50                 // Method len1:()I
       450: istore        63
       452: aload_0
       453: invokevirtual #53                 // Method prefix2:()[[Ljava/lang/Object;
       456: astore        64
       458: aload         64
       460: aconst_null
       461: astore        64
       463: astore        19
       465: aload_0
       466: invokevirtual #56                 // Method len12:()I
       469: istore        65
       471: aload_0
       472: invokevirtual #59                 // Method data3:()[[[Ljava/lang/Object;
       475: astore        66
       477: aload         66
       479: aconst_null
       480: astore        66
       482: astore        20
       484: aload_0
       485: invokevirtual #62                 // Method suffix2:()[[Ljava/lang/Object;
       488: astore        67
       490: aload         67
       492: aconst_null
       493: astore        67
       495: astore        21
       497: aload_0
       498: invokevirtual #68                 // Method length0:()I
       501: istore        68
       503: new           #2                  // class scala/collection/immutable/Vector3
       506: dup
       507: aload         18
       509: iload         63
       511: aload         19
       513: iload         65
       515: aload         20
       517: aload         21
       519: aload         17
       521: iload         68
       523: invokespecial #42                 // Method "<init>":([Ljava/lang/Object;I[[Ljava/lang/Object;I[[[Ljava/lang/Object;[[Ljava/lang/Object;[Ljava/lang/Object;I)V
       526: areturn
       527: iload_1
       528: aload_0
       529: invokevirtual #50                 // Method len1:()I
       532: if_icmplt     709
       535: iload_1
       536: aload_0
       537: invokevirtual #50                 // Method len1:()I
       540: isub
       541: istore        22
       543: getstatic     #90                 // Field scala/collection/immutable/VectorInline$.MODULE$:Lscala/collection/immutable/VectorInline$;
       546: pop
       547: aload_0
       548: invokevirtual #53                 // Method prefix2:()[[Ljava/lang/Object;
       551: iload         22
       553: iconst_5
       554: iushr
       555: iload         22
       557: bipush        31
       559: iand
       560: istore        39
       562: istore        38
       564: astore        37
       566: aload         37
       568: invokevirtual #97                 // Method "[[Ljava/lang/Object;".clone:()Ljava/lang/Object;
       571: checkcast     #96                 // class "[[Ljava/lang/Object;"
       574: astore        40
       576: aload         40
       578: iload         38
       580: aload         40
       582: iload         38
       584: aaload
       585: invokevirtual #99                 // Method "[Ljava/lang/Object;".clone:()Ljava/lang/Object;
       588: checkcast     #98                 // class "[Ljava/lang/Object;"
       591: astore        41
       593: aload         41
       595: iload         39
       597: aload_2
       598: aastore
       599: aload         41
       601: aconst_null
       602: astore        41
       604: aastore
       605: aload         40
       607: aconst_null
       608: astore        37
       610: aconst_null
       611: astore        40
       613: astore        23
       615: aload_0
       616: invokevirtual #47                 // Method prefix1:()[Ljava/lang/Object;
       619: astore        69
       621: aload         69
       623: aconst_null
       624: astore        69
       626: astore        24
       628: aload_0
       629: invokevirtual #50                 // Method len1:()I
       632: istore        70
       634: aload_0
       635: invokevirtual #56                 // Method len12:()I
       638: istore        71
       640: aload_0
       641: invokevirtual #59                 // Method data3:()[[[Ljava/lang/Object;
       644: astore        72
       646: aload         72
       648: aconst_null
       649: astore        72
       651: astore        25
       653: aload_0
       654: invokevirtual #62                 // Method suffix2:()[[Ljava/lang/Object;
       657: astore        73
       659: aload         73
       661: aconst_null
       662: astore        73
       664: astore        26
       666: aload_0
       667: invokevirtual #65                 // Method suffix1:()[Ljava/lang/Object;
       670: astore        74
       672: aload         74
       674: aconst_null
       675: astore        74
       677: astore        27
       679: aload_0
       680: invokevirtual #68                 // Method length0:()I
       683: istore        75
       685: new           #2                  // class scala/collection/immutable/Vector3
       688: dup
       689: aload         24
       691: iload         70
       693: aload         23
       695: iload         71
       697: aload         25
       699: aload         26
       701: aload         27
       703: iload         75
       705: invokespecial #42                 // Method "<init>":([Ljava/lang/Object;I[[Ljava/lang/Object;I[[[Ljava/lang/Object;[[Ljava/lang/Object;[Ljava/lang/Object;I)V
       708: areturn
       709: getstatic     #90                 // Field scala/collection/immutable/VectorInline$.MODULE$:Lscala/collection/immutable/VectorInline$;
       712: pop
       713: aload_0
       714: invokevirtual #47                 // Method prefix1:()[Ljava/lang/Object;
       717: invokevirtual #99                 // Method "[Ljava/lang/Object;".clone:()Ljava/lang/Object;
       720: checkcast     #98                 // class "[Ljava/lang/Object;"
       723: astore        42
       725: aload         42
       727: iload_1
       728: aload_2
       729: aastore
       730: aload         42
       732: aconst_null
       733: astore        42
       735: aload_0
       736: invokevirtual #50                 // Method len1:()I
       739: istore        76
       741: aload_0
       742: invokevirtual #53                 // Method prefix2:()[[Ljava/lang/Object;
       745: aload_0
       746: invokevirtual #56                 // Method len12:()I
       749: istore        77
       751: aload_0
       752: invokevirtual #59                 // Method data3:()[[[Ljava/lang/Object;
       755: aload_0
       756: invokevirtual #62                 // Method suffix2:()[[Ljava/lang/Object;
       759: aload_0
       760: invokevirtual #65                 // Method suffix1:()[Ljava/lang/Object;
       763: aload_0
       764: invokevirtual #68                 // Method length0:()I
       767: istore        78
       769: astore        47
       771: astore        46
       773: astore        45
       775: astore        44
       777: astore        43
       779: new           #2                  // class scala/collection/immutable/Vector3
       782: dup
       783: aload         43
       785: iload         76
       787: aload         44
       789: iload         77
       791: aload         45
       793: aload         46
       795: aload         47
       797: iload         78
       799: invokespecial #42                 // Method "<init>":([Ljava/lang/Object;I[[Ljava/lang/Object;I[[[Ljava/lang/Object;[[Ljava/lang/Object;[Ljava/lang/Object;I)V
       802: areturn
       803: aload_0
       804: iload_1
       805: invokevirtual #76                 // Method ioob:(I)Ljava/lang/IndexOutOfBoundsException;
       808: athrow
      StackMapTable: number_of_entries = 5
        frame_type = 255 /* full_frame */
          offset_delta = 234
          locals = [ class scala/collection/immutable/Vector3, int, class java/lang/Object, int, int, int, int ]
          stack = []
        frame_type = 251 /* same_frame_extended */
          offset_delta = 162
        frame_type = 255 /* full_frame */
          offset_delta = 129
          locals = [ class scala/collection/immutable/Vector3, int, class java/lang/Object ]
          stack = []
        frame_type = 251 /* same_frame_extended */
          offset_delta = 181
        frame_type = 251 /* same_frame_extended */
          offset_delta = 93
      LineNumberTable:
        line 558: 0
        line 559: 13
        line 560: 21
        line 561: 28
        line 562: 34
        line 563: 42
        line 564: 48
        line 1782: 68
        line 1783: 78
        line 1776: 87
        line 1777: 95
        line 1770: 104
        line 1771: 112
        line 1772: 118
        line 1777: 118
        line 1778: 124
        line 1783: 124
        line 1784: 130
        line 564: 130
        line 533: 140
        line 564: 146
        line 533: 153
        line 534: 159
        line 564: 165
        line 534: 172
        line 536: 178
        line 564: 184
        line 536: 191
        line 564: 197
        line 537: 204
        line 538: 210
        line 564: 233
        line 565: 234
        line 1776: 254
        line 1777: 264
        line 1770: 273
        line 1771: 281
        line 1772: 287
        line 1777: 287
        line 1778: 293
        line 565: 293
        line 533: 303
        line 565: 309
        line 533: 316
        line 534: 322
        line 565: 328
        line 534: 335
        line 535: 341
        line 565: 347
        line 536: 354
        line 565: 360
        line 537: 367
        line 538: 373
        line 565: 396
        line 566: 397
        line 1770: 407
        line 1771: 417
        line 1772: 423
        line 566: 423
        line 533: 433
        line 566: 439
        line 533: 446
        line 534: 452
        line 566: 458
        line 534: 465
        line 535: 471
        line 566: 477
        line 536: 484
        line 566: 490
        line 537: 497
        line 538: 503
        line 566: 526
        line 567: 527
        line 568: 535
        line 569: 543
        line 1776: 566
        line 1777: 576
        line 1770: 585
        line 1771: 593
        line 1772: 599
        line 1777: 599
        line 1778: 605
        line 569: 605
        line 533: 615
        line 569: 621
        line 533: 628
        line 534: 634
        line 535: 640
        line 569: 646
        line 536: 653
        line 569: 659
        line 536: 666
        line 569: 672
        line 537: 679
        line 538: 685
        line 569: 708
        line 571: 709
        line 1770: 717
        line 1771: 725
        line 1772: 730
        line 571: 730
        line 533: 735
        line 534: 741
        line 534: 745
        line 535: 751
        line 536: 755
        line 536: 759
        line 537: 763
        line 571: 769
        line 538: 779
        line 571: 802
        line 573: 803
      LocalVariableTable:
        Start  Length  Slot  Name   Signature
          140      93     7   x$1   [[[Ljava/lang/Object;
          153      80     8   x$2   [Ljava/lang/Object;
          172      61     9   x$4   [[Ljava/lang/Object;
          191      42    10   x$6   [[Ljava/lang/Object;
          204      29    11   x$7   [Ljava/lang/Object;
          303      93    12   x$9   [[Ljava/lang/Object;
          316      80    13  x$10   [Ljava/lang/Object;
          335      61    14  x$12   [[Ljava/lang/Object;
          354      42    15  x$14   [[[Ljava/lang/Object;
          367      29    16  x$15   [Ljava/lang/Object;
          433      93    17  x$17   [Ljava/lang/Object;
          446      80    18  x$18   [Ljava/lang/Object;
          465      61    19  x$20   [[Ljava/lang/Object;
          484      42    20  x$22   [[[Ljava/lang/Object;
          497      29    21  x$23   [[Ljava/lang/Object;
           28     498     3    io   I
           34     492     4    i3   I
           42     484     5    i2   I
           48     478     6    i1   I
          615      93    23  x$25   [[Ljava/lang/Object;
          628      80    24  x$26   [Ljava/lang/Object;
          653      55    25  x$29   [[[Ljava/lang/Object;
          666      42    26  x$30   [[Ljava/lang/Object;
          679      29    27  x$31   [Ljava/lang/Object;
          543     165    22    io   I
            0     809     0  this   Lscala/collection/immutable/Vector3;
            0     809     1 index   I
            0     809     2  elem   Ljava/lang/Object;
           78      52    29 copyUpdate_a3c   [[[Ljava/lang/Object;
           68      62    28 copyUpdate_a3   [[[Ljava/lang/Object;
           95      29    30 copyUpdate_copyUpdate_a2c   [[Ljava/lang/Object;
          112       6    31 copyUpdate_copyUpdate_copyUpdate_a1c   [Ljava/lang/Object;
          264      29    33 copyUpdate_a2c   [[Ljava/lang/Object;
          254      39    32 copyUpdate_a2   [[Ljava/lang/Object;
          281       6    34 copyUpdate_copyUpdate_a1c   [Ljava/lang/Object;
          417       6    36 copyUpdate_a1c   [Ljava/lang/Object;
          407      16    35 copyUpdate_a1   [Ljava/lang/Object;
          576      29    40 copyUpdate_a2c   [[Ljava/lang/Object;
          566      39    37 copyUpdate_a2   [[Ljava/lang/Object;
          566      39    38 copyUpdate_idx2   I
          566      39    39 copyUpdate_idx1   I
          593       6    41 copyUpdate_copyUpdate_a1c   [Ljava/lang/Object;
          725       5    42 copyUpdate_a1c   [Ljava/lang/Object;
          779      23    43 copy_prefix1   [Ljava/lang/Object;
          779      23    44 copy_prefix2   [[Ljava/lang/Object;
          779      23    45 copy_data3   [[[Ljava/lang/Object;
          779      23    46 copy_suffix2   [[Ljava/lang/Object;
          779      23    47 copy_suffix1   [Ljava/lang/Object;
    Signature: #83                          // <B:Ljava/lang/Object;>(ITB;)Lscala/collection/immutable/Vector<TB;>;
    MethodParameters:
      Name                           Flags
      index                          final
      elem                           final

  public <B extends java.lang.Object> scala.collection.immutable.Vector<B> appended(B);
    descriptor: (Ljava/lang/Object;)Lscala/collection/immutable/Vector;
    flags: (0x0001) ACC_PUBLIC
    Code:
      stack=14, locals=40, args_size=2
         0: aload_0
         1: invokevirtual #65                 // Method suffix1:()[Ljava/lang/Object;
         4: arraylength
         5: bipush        32
         7: if_icmpge     115
        10: getstatic     #146                // Field scala/collection/immutable/VectorStatics$.MODULE$:Lscala/collection/immutable/VectorStatics$;
        13: aload_0
        14: invokevirtual #65                 // Method suffix1:()[Ljava/lang/Object;
        17: aload_1
        18: invokevirtual #150                // Method scala/collection/immutable/VectorStatics$.copyAppend1:([Ljava/lang/Object;Ljava/lang/Object;)[Ljava/lang/Object;
        21: astore_2
        22: aload_0
        23: invokevirtual #68                 // Method length0:()I
        26: iconst_1
        27: iadd
        28: istore_3
        29: aload_0
        30: invokevirtual #47                 // Method prefix1:()[Ljava/lang/Object;
        33: astore        25
        35: aload         25
        37: aconst_null
        38: astore        25
        40: astore        4
        42: aload_0
        43: invokevirtual #50                 // Method len1:()I
        46: istore        26
        48: aload_0
        49: invokevirtual #53                 // Method prefix2:()[[Ljava/lang/Object;
        52: astore        27
        54: aload         27
        56: aconst_null
        57: astore        27
        59: astore        5
        61: aload_0
        62: invokevirtual #56                 // Method len12:()I
        65: istore        28
        67: aload_0
        68: invokevirtual #59                 // Method data3:()[[[Ljava/lang/Object;
        71: astore        29
        73: aload         29
        75: aconst_null
        76: astore        29
        78: astore        6
        80: aload_0
        81: invokevirtual #62                 // Method suffix2:()[[Ljava/lang/Object;
        84: astore        30
        86: aload         30
        88: aconst_null
        89: astore        30
        91: astore        7
        93: new           #2                  // class scala/collection/immutable/Vector3
        96: dup
        97: aload         4
        99: iload         26
       101: aload         5
       103: iload         28
       105: aload         6
       107: aload         7
       109: aload_2
       110: iload_3
       111: invokespecial #42                 // Method "<init>":([Ljava/lang/Object;I[[Ljava/lang/Object;I[[[Ljava/lang/Object;[[Ljava/lang/Object;[Ljava/lang/Object;I)V
       114: areturn
       115: aload_0
       116: invokevirtual #62                 // Method suffix2:()[[Ljava/lang/Object;
       119: arraylength
       120: bipush        31
       122: if_icmpge     249
       125: getstatic     #146                // Field scala/collection/immutable/VectorStatics$.MODULE$:Lscala/collection/immutable/VectorStatics$;
       128: aload_0
       129: invokevirtual #62                 // Method suffix2:()[[Ljava/lang/Object;
       132: aload_0
       133: invokevirtual #65                 // Method suffix1:()[Ljava/lang/Object;
       136: invokevirtual #153                // Method scala/collection/immutable/VectorStatics$.copyAppend:([Ljava/lang/Object;Ljava/lang/Object;)[Ljava/lang/Object;
       139: checkcast     #96                 // class "[[Ljava/lang/Object;"
       142: astore        8
       144: getstatic     #90                 // Field scala/collection/immutable/VectorInline$.MODULE$:Lscala/collection/immutable/VectorInline$;
       147: pop
       148: iconst_1
       149: anewarray     #138                // class java/lang/Object
       152: astore        20
       154: aload         20
       156: iconst_0
       157: aload_1
       158: aastore
       159: aload         20
       161: aconst_null
       162: astore        20
       164: astore        9
       166: aload_0
       167: invokevirtual #68                 // Method length0:()I
       170: iconst_1
       171: iadd
       172: istore        10
       174: aload_0
       175: invokevirtual #47                 // Method prefix1:()[Ljava/lang/Object;
       178: astore        31
       180: aload         31
       182: aconst_null
       183: astore        31
       185: astore        11
       187: aload_0
       188: invokevirtual #50                 // Method len1:()I
       191: istore        32
       193: aload_0
       194: invokevirtual #53                 // Method prefix2:()[[Ljava/lang/Object;
       197: astore        33
       199: aload         33
       201: aconst_null
       202: astore        33
       204: astore        12
       206: aload_0
       207: invokevirtual #56                 // Method len12:()I
       210: istore        34
       212: aload_0
       213: invokevirtual #59                 // Method data3:()[[[Ljava/lang/Object;
       216: astore        35
       218: aload         35
       220: aconst_null
       221: astore        35
       223: astore        13
       225: new           #2                  // class scala/collection/immutable/Vector3
       228: dup
       229: aload         11
       231: iload         32
       233: aload         12
       235: iload         34
       237: aload         13
       239: aload         8
       241: aload         9
       243: iload         10
       245: invokespecial #42                 // Method "<init>":([Ljava/lang/Object;I[[Ljava/lang/Object;I[[[Ljava/lang/Object;[[Ljava/lang/Object;[Ljava/lang/Object;I)V
       248: areturn
       249: aload_0
       250: invokevirtual #59                 // Method data3:()[[[Ljava/lang/Object;
       253: arraylength
       254: bipush        30
       256: if_icmpge     388
       259: getstatic     #146                // Field scala/collection/immutable/VectorStatics$.MODULE$:Lscala/collection/immutable/VectorStatics$;
       262: aload_0
       263: invokevirtual #59                 // Method data3:()[[[Ljava/lang/Object;
       266: getstatic     #146                // Field scala/collection/immutable/VectorStatics$.MODULE$:Lscala/collection/immutable/VectorStatics$;
       269: aload_0
       270: invokevirtual #62                 // Method suffix2:()[[Ljava/lang/Object;
       273: aload_0
       274: invokevirtual #65                 // Method suffix1:()[Ljava/lang/Object;
       277: invokevirtual #153                // Method scala/collection/immutable/VectorStatics$.copyAppend:([Ljava/lang/Object;Ljava/lang/Object;)[Ljava/lang/Object;
       280: invokevirtual #153                // Method scala/collection/immutable/VectorStatics$.copyAppend:([Ljava/lang/Object;Ljava/lang/Object;)[Ljava/lang/Object;
       283: checkcast     #91                 // class "[[[Ljava/lang/Object;"
       286: astore        14
       288: getstatic     #146                // Field scala/collection/immutable/VectorStatics$.MODULE$:Lscala/collection/immutable/VectorStatics$;
       291: invokevirtual #156                // Method scala/collection/immutable/VectorStatics$.empty2:()[[Ljava/lang/Object;
       294: astore        15
       296: getstatic     #90                 // Field scala/collection/immutable/VectorInline$.MODULE$:Lscala/collection/immutable/VectorInline$;
       299: pop
       300: iconst_1
       301: anewarray     #138                // class java/lang/Object
       304: astore        21
       306: aload         21
       308: iconst_0
       309: aload_1
       310: aastore
       311: aload         21
       313: aconst_null
       314: astore        21
       316: astore        16
       318: aload_0
       319: invokevirtual #68                 // Method length0:()I
       322: iconst_1
       323: iadd
       324: istore        17
       326: aload_0
       327: invokevirtual #47                 // Method prefix1:()[Ljava/lang/Object;
       330: astore        36
       332: aload         36
       334: aconst_null
       335: astore        36
       337: astore        18
       339: aload_0
       340: invokevirtual #50                 // Method len1:()I
       343: istore        37
       345: aload_0
       346: invokevirtual #53                 // Method prefix2:()[[Ljava/lang/Object;
       349: astore        38
       351: aload         38
       353: aconst_null
       354: astore        38
       356: astore        19
       358: aload_0
       359: invokevirtual #56                 // Method len12:()I
       362: istore        39
       364: new           #2                  // class scala/collection/immutable/Vector3
       367: dup
       368: aload         18
       370: iload         37
       372: aload         19
       374: iload         39
       376: aload         14
       378: aload         15
       380: aload         16
       382: iload         17
       384: invokespecial #42                 // Method "<init>":([Ljava/lang/Object;I[[Ljava/lang/Object;I[[[Ljava/lang/Object;[[Ljava/lang/Object;[Ljava/lang/Object;I)V
       387: areturn
       388: new           #158                // class scala/collection/immutable/Vector4
       391: dup
       392: aload_0
       393: invokevirtual #47                 // Method prefix1:()[Ljava/lang/Object;
       396: aload_0
       397: invokevirtual #50                 // Method len1:()I
       400: aload_0
       401: invokevirtual #53                 // Method prefix2:()[[Ljava/lang/Object;
       404: aload_0
       405: invokevirtual #56                 // Method len12:()I
       408: aload_0
       409: invokevirtual #59                 // Method data3:()[[[Ljava/lang/Object;
       412: sipush        30720
       415: aload_0
       416: invokevirtual #56                 // Method len12:()I
       419: iadd
       420: getstatic     #146                // Field scala/collection/immutable/VectorStatics$.MODULE$:Lscala/collection/immutable/VectorStatics$;
       423: invokevirtual #162                // Method scala/collection/immutable/VectorStatics$.empty4:()[[[[Ljava/lang/Object;
       426: getstatic     #90                 // Field scala/collection/immutable/VectorInline$.MODULE$:Lscala/collection/immutable/VectorInline$;
       429: pop
       430: getstatic     #146                // Field scala/collection/immutable/VectorStatics$.MODULE$:Lscala/collection/immutable/VectorStatics$;
       433: aload_0
       434: invokevirtual #62                 // Method suffix2:()[[Ljava/lang/Object;
       437: aload_0
       438: invokevirtual #65                 // Method suffix1:()[Ljava/lang/Object;
       441: invokevirtual #153                // Method scala/collection/immutable/VectorStatics$.copyAppend:([Ljava/lang/Object;Ljava/lang/Object;)[Ljava/lang/Object;
       444: checkcast     #96                 // class "[[Ljava/lang/Object;"
       447: astore        22
       449: iconst_1
       450: anewarray     #96                 // class "[[Ljava/lang/Object;"
       453: astore        23
       455: aload         23
       457: iconst_0
       458: aload         22
       460: aastore
       461: aload         23
       463: aconst_null
       464: astore        22
       466: aconst_null
       467: astore        23
       469: getstatic     #146                // Field scala/collection/immutable/VectorStatics$.MODULE$:Lscala/collection/immutable/VectorStatics$;
       472: invokevirtual #156                // Method scala/collection/immutable/VectorStatics$.empty2:()[[Ljava/lang/Object;
       475: getstatic     #90                 // Field scala/collection/immutable/VectorInline$.MODULE$:Lscala/collection/immutable/VectorInline$;
       478: pop
       479: iconst_1
       480: anewarray     #138                // class java/lang/Object
       483: astore        24
       485: aload         24
       487: iconst_0
       488: aload_1
       489: aastore
       490: aload         24
       492: aconst_null
       493: astore        24
       495: aload_0
       496: invokevirtual #68                 // Method length0:()I
       499: iconst_1
       500: iadd
       501: invokespecial #165                // Method scala/collection/immutable/Vector4."<init>":([Ljava/lang/Object;I[[Ljava/lang/Object;I[[[Ljava/lang/Object;I[[[[Ljava/lang/Object;[[[Ljava/lang/Object;[[Ljava/lang/Object;[Ljava/lang/Object;I)V
       504: areturn
      StackMapTable: number_of_entries = 3
        frame_type = 251 /* same_frame_extended */
          offset_delta = 115
        frame_type = 251 /* same_frame_extended */
          offset_delta = 133
        frame_type = 251 /* same_frame_extended */
          offset_delta = 138
      LineNumberTable:
        line 577: 0
        line 533: 29
        line 577: 35
        line 533: 42
        line 534: 48
        line 577: 54
        line 534: 61
        line 535: 67
        line 577: 73
        line 536: 80
        line 577: 86
        line 538: 93
        line 577: 114
        line 578: 115
        line 1763: 148
        line 578: 159
        line 533: 174
        line 578: 180
        line 533: 187
        line 534: 193
        line 578: 199
        line 534: 206
        line 535: 212
        line 578: 218
        line 538: 225
        line 578: 248
        line 579: 249
        line 1763: 300
        line 579: 311
        line 533: 326
        line 579: 332
        line 533: 339
        line 534: 345
        line 579: 351
        line 534: 358
        line 538: 364
        line 579: 387
        line 580: 388
        line 1765: 449
        line 580: 461
        line 1763: 479
        line 580: 490
      LocalVariableTable:
        Start  Length  Slot  Name   Signature
           22      92     2   x$1   [Ljava/lang/Object;
           29      85     3   x$2   I
           42      72     4   x$3   [Ljava/lang/Object;
           61      53     5   x$5   [[Ljava/lang/Object;
           80      34     6   x$7   [[[Ljava/lang/Object;
           93      21     7   x$8   [[Ljava/lang/Object;
          144     104     8   x$9   [[Ljava/lang/Object;
          166      82     9  x$10   [Ljava/lang/Object;
          174      74    10  x$11   I
          187      61    11  x$12   [Ljava/lang/Object;
          206      42    12  x$14   [[Ljava/lang/Object;
          225      23    13  x$16   [[[Ljava/lang/Object;
          288      99    14  x$17   [[[Ljava/lang/Object;
          296      91    15  x$18   [[Ljava/lang/Object;
          318      69    16  x$19   [Ljava/lang/Object;
          326      61    17  x$20   I
          339      48    18  x$21   [Ljava/lang/Object;
          358      29    19  x$23   [[Ljava/lang/Object;
            0     505     0  this   Lscala/collection/immutable/Vector3;
            0     505     1  elem   Ljava/lang/Object;
          154       5    20 wrap1_a   [Ljava/lang/Object;
          306       5    21 wrap1_a   [Ljava/lang/Object;
          455       6    23 wrap3_a   [[[Ljava/lang/Object;
          449      12    22 wrap3_x   [[Ljava/lang/Object;
          485       5    24 wrap1_a   [Ljava/lang/Object;
    Signature: #141                         // <B:Ljava/lang/Object;>(TB;)Lscala/collection/immutable/Vector<TB;>;
    MethodParameters:
      Name                           Flags
      elem                           final

  public <B extends java.lang.Object> scala.collection.immutable.Vector<B> prepended(B);
    descriptor: (Ljava/lang/Object;)Lscala/collection/immutable/Vector;
    flags: (0x0001) ACC_PUBLIC
    Code:
      stack=14, locals=40, args_size=2
         0: aload_0
         1: invokevirtual #50                 // Method len1:()I
         4: bipush        32
         6: if_icmpge     118
         9: getstatic     #146                // Field scala/collection/immutable/VectorStatics$.MODULE$:Lscala/collection/immutable/VectorStatics$;
        12: aload_1
        13: aload_0
        14: invokevirtual #47                 // Method prefix1:()[Ljava/lang/Object;
        17: invokevirtual #180                // Method scala/collection/immutable/VectorStatics$.copyPrepend1:(Ljava/lang/Object;[Ljava/lang/Object;)[Ljava/lang/Object;
        20: astore_2
        21: aload_0
        22: invokevirtual #50                 // Method len1:()I
        25: iconst_1
        26: iadd
        27: istore_3
        28: aload_0
        29: invokevirtual #56                 // Method len12:()I
        32: iconst_1
        33: iadd
        34: istore        4
        36: aload_0
        37: invokevirtual #68                 // Method length0:()I
        40: iconst_1
        41: iadd
        42: istore        5
        44: aload_0
        45: invokevirtual #53                 // Method prefix2:()[[Ljava/lang/Object;
        48: astore        31
        50: aload         31
        52: aconst_null
        53: astore        31
        55: astore        6
        57: aload_0
        58: invokevirtual #59                 // Method data3:()[[[Ljava/lang/Object;
        61: astore        32
        63: aload         32
        65: aconst_null
        66: astore        32
        68: astore        7
        70: aload_0
        71: invokevirtual #62                 // Method suffix2:()[[Ljava/lang/Object;
        74: astore        33
        76: aload         33
        78: aconst_null
        79: astore        33
        81: astore        8
        83: aload_0
        84: invokevirtual #65                 // Method suffix1:()[Ljava/lang/Object;
        87: astore        34
        89: aload         34
        91: aconst_null
        92: astore        34
        94: astore        9
        96: new           #2                  // class scala/collection/immutable/Vector3
        99: dup
       100: aload_2
       101: iload_3
       102: aload         6
       104: iload         4
       106: aload         7
       108: aload         8
       110: aload         9
       112: iload         5
       114: invokespecial #42                 // Method "<init>":([Ljava/lang/Object;I[[Ljava/lang/Object;I[[[Ljava/lang/Object;[[Ljava/lang/Object;[Ljava/lang/Object;I)V
       117: areturn
       118: aload_0
       119: invokevirtual #56                 // Method len12:()I
       122: sipush        1024
       125: if_icmpge     251
       128: getstatic     #90                 // Field scala/collection/immutable/VectorInline$.MODULE$:Lscala/collection/immutable/VectorInline$;
       131: pop
       132: iconst_1
       133: anewarray     #138                // class java/lang/Object
       136: astore        23
       138: aload         23
       140: iconst_0
       141: aload_1
       142: aastore
       143: aload         23
       145: aconst_null
       146: astore        23
       148: astore        10
       150: getstatic     #146                // Field scala/collection/immutable/VectorStatics$.MODULE$:Lscala/collection/immutable/VectorStatics$;
       153: aload_0
       154: invokevirtual #47                 // Method prefix1:()[Ljava/lang/Object;
       157: aload_0
       158: invokevirtual #53                 // Method prefix2:()[[Ljava/lang/Object;
       161: invokevirtual #183                // Method scala/collection/immutable/VectorStatics$.copyPrepend:(Ljava/lang/Object;[Ljava/lang/Object;)[Ljava/lang/Object;
       164: checkcast     #96                 // class "[[Ljava/lang/Object;"
       167: astore        11
       169: aload_0
       170: invokevirtual #56                 // Method len12:()I
       173: iconst_1
       174: iadd
       175: istore        12
       177: aload_0
       178: invokevirtual #68                 // Method length0:()I
       181: iconst_1
       182: iadd
       183: istore        13
       185: aload_0
       186: invokevirtual #59                 // Method data3:()[[[Ljava/lang/Object;
       189: astore        35
       191: aload         35
       193: aconst_null
       194: astore        35
       196: astore        14
       198: aload_0
       199: invokevirtual #62                 // Method suffix2:()[[Ljava/lang/Object;
       202: astore        36
       204: aload         36
       206: aconst_null
       207: astore        36
       209: astore        15
       211: aload_0
       212: invokevirtual #65                 // Method suffix1:()[Ljava/lang/Object;
       215: astore        37
       217: aload         37
       219: aconst_null
       220: astore        37
       222: astore        16
       224: iconst_1
       225: istore        24
       227: new           #2                  // class scala/collection/immutable/Vector3
       230: dup
       231: aload         10
       233: iload         24
       235: aload         11
       237: iload         12
       239: aload         14
       241: aload         15
       243: aload         16
       245: iload         13
       247: invokespecial #42                 // Method "<init>":([Ljava/lang/Object;I[[Ljava/lang/Object;I[[[Ljava/lang/Object;[[Ljava/lang/Object;[Ljava/lang/Object;I)V
       250: areturn
       251: aload_0
       252: invokevirtual #59                 // Method data3:()[[[Ljava/lang/Object;
       255: arraylength
       256: bipush        30
       258: if_icmpge     384
       261: getstatic     #90                 // Field scala/collection/immutable/VectorInline$.MODULE$:Lscala/collection/immutable/VectorInline$;
       264: pop
       265: iconst_1
       266: anewarray     #138                // class java/lang/Object
       269: astore        25
       271: aload         25
       273: iconst_0
       274: aload_1
       275: aastore
       276: aload         25
       278: aconst_null
       279: astore        25
       281: astore        17
       283: getstatic     #146                // Field scala/collection/immutable/VectorStatics$.MODULE$:Lscala/collection/immutable/VectorStatics$;
       286: invokevirtual #156                // Method scala/collection/immutable/VectorStatics$.empty2:()[[Ljava/lang/Object;
       289: astore        18
       291: getstatic     #146                // Field scala/collection/immutable/VectorStatics$.MODULE$:Lscala/collection/immutable/VectorStatics$;
       294: getstatic     #146                // Field scala/collection/immutable/VectorStatics$.MODULE$:Lscala/collection/immutable/VectorStatics$;
       297: aload_0
       298: invokevirtual #47                 // Method prefix1:()[Ljava/lang/Object;
       301: aload_0
       302: invokevirtual #53                 // Method prefix2:()[[Ljava/lang/Object;
       305: invokevirtual #183                // Method scala/collection/immutable/VectorStatics$.copyPrepend:(Ljava/lang/Object;[Ljava/lang/Object;)[Ljava/lang/Object;
       308: aload_0
       309: invokevirtual #59                 // Method data3:()[[[Ljava/lang/Object;
       312: invokevirtual #183                // Method scala/collection/immutable/VectorStatics$.copyPrepend:(Ljava/lang/Object;[Ljava/lang/Object;)[Ljava/lang/Object;
       315: checkcast     #91                 // class "[[[Ljava/lang/Object;"
       318: astore        19
       320: aload_0
       321: invokevirtual #68                 // Method length0:()I
       324: iconst_1
       325: iadd
       326: istore        20
       328: aload_0
       329: invokevirtual #62                 // Method suffix2:()[[Ljava/lang/Object;
       332: astore        38
       334: aload         38
       336: aconst_null
       337: astore        38
       339: astore        21
       341: aload_0
       342: invokevirtual #65                 // Method suffix1:()[Ljava/lang/Object;
       345: astore        39
       347: aload         39
       349: aconst_null
       350: astore        39
       352: astore        22
       354: iconst_1
       355: iconst_1
       356: istore        27
       358: istore        26
       360: new           #2                  // class scala/collection/immutable/Vector3
       363: dup
       364: aload         17
       366: iload         26
       368: aload         18
       370: iload         27
       372: aload         19
       374: aload         21
       376: aload         22
       378: iload         20
       380: invokespecial #42                 // Method "<init>":([Ljava/lang/Object;I[[Ljava/lang/Object;I[[[Ljava/lang/Object;[[Ljava/lang/Object;[Ljava/lang/Object;I)V
       383: areturn
       384: new           #158                // class scala/collection/immutable/Vector4
       387: dup
       388: getstatic     #90                 // Field scala/collection/immutable/VectorInline$.MODULE$:Lscala/collection/immutable/VectorInline$;
       391: pop
       392: iconst_1
       393: anewarray     #138                // class java/lang/Object
       396: astore        28
       398: aload         28
       400: iconst_0
       401: aload_1
       402: aastore
       403: aload         28
       405: aconst_null
       406: astore        28
       408: iconst_1
       409: getstatic     #146                // Field scala/collection/immutable/VectorStatics$.MODULE$:Lscala/collection/immutable/VectorStatics$;
       412: invokevirtual #156                // Method scala/collection/immutable/VectorStatics$.empty2:()[[Ljava/lang/Object;
       415: iconst_1
       416: getstatic     #90                 // Field scala/collection/immutable/VectorInline$.MODULE$:Lscala/collection/immutable/VectorInline$;
       419: pop
       420: getstatic     #146                // Field scala/collection/immutable/VectorStatics$.MODULE$:Lscala/collection/immutable/VectorStatics$;
       423: aload_0
       424: invokevirtual #47                 // Method prefix1:()[Ljava/lang/Object;
       427: aload_0
       428: invokevirtual #53                 // Method prefix2:()[[Ljava/lang/Object;
       431: invokevirtual #183                // Method scala/collection/immutable/VectorStatics$.copyPrepend:(Ljava/lang/Object;[Ljava/lang/Object;)[Ljava/lang/Object;
       434: checkcast     #96                 // class "[[Ljava/lang/Object;"
       437: astore        29
       439: iconst_1
       440: anewarray     #96                 // class "[[Ljava/lang/Object;"
       443: astore        30
       445: aload         30
       447: iconst_0
       448: aload         29
       450: aastore
       451: aload         30
       453: aconst_null
       454: astore        29
       456: aconst_null
       457: astore        30
       459: aload_0
       460: invokevirtual #56                 // Method len12:()I
       463: iconst_1
       464: iadd
       465: getstatic     #146                // Field scala/collection/immutable/VectorStatics$.MODULE$:Lscala/collection/immutable/VectorStatics$;
       468: invokevirtual #162                // Method scala/collection/immutable/VectorStatics$.empty4:()[[[[Ljava/lang/Object;
       471: aload_0
       472: invokevirtual #59                 // Method data3:()[[[Ljava/lang/Object;
       475: aload_0
       476: invokevirtual #62                 // Method suffix2:()[[Ljava/lang/Object;
       479: aload_0
       480: invokevirtual #65                 // Method suffix1:()[Ljava/lang/Object;
       483: aload_0
       484: invokevirtual #68                 // Method length0:()I
       487: iconst_1
       488: iadd
       489: invokespecial #165                // Method scala/collection/immutable/Vector4."<init>":([Ljava/lang/Object;I[[Ljava/lang/Object;I[[[Ljava/lang/Object;I[[[[Ljava/lang/Object;[[[Ljava/lang/Object;[[Ljava/lang/Object;[Ljava/lang/Object;I)V
       492: areturn
      StackMapTable: number_of_entries = 3
        frame_type = 251 /* same_frame_extended */
          offset_delta = 118
        frame_type = 251 /* same_frame_extended */
          offset_delta = 132
        frame_type = 251 /* same_frame_extended */
          offset_delta = 132
      LineNumberTable:
        line 584: 0
        line 534: 44
        line 584: 50
        line 535: 57
        line 584: 63
        line 536: 70
        line 584: 76
        line 536: 83
        line 584: 89
        line 538: 96
        line 584: 117
        line 585: 118
        line 1763: 132
        line 585: 143
        line 535: 185
        line 585: 191
        line 536: 198
        line 585: 204
        line 536: 211
        line 585: 217
        line 538: 227
        line 585: 250
        line 586: 251
        line 1763: 265
        line 586: 276
        line 536: 328
        line 586: 334
        line 536: 341
        line 586: 347
        line 538: 360
        line 586: 383
        line 587: 384
        line 1763: 392
        line 587: 403
        line 1765: 439
        line 587: 451
      LocalVariableTable:
        Start  Length  Slot  Name   Signature
           21      96     2   x$1   [Ljava/lang/Object;
           28      89     3   x$2   I
           36      81     4   x$3   I
           44      73     5   x$4   I
           57      60     6   x$5   [[Ljava/lang/Object;
           70      47     7   x$6   [[[Ljava/lang/Object;
           83      34     8   x$7   [[Ljava/lang/Object;
           96      21     9   x$8   [Ljava/lang/Object;
          150     100    10   x$9   [Ljava/lang/Object;
          169      81    11  x$11   [[Ljava/lang/Object;
          177      73    12  x$12   I
          185      65    13  x$13   I
          198      52    14  x$14   [[[Ljava/lang/Object;
          211      39    15  x$15   [[Ljava/lang/Object;
          224      26    16  x$16   [Ljava/lang/Object;
          283     100    17  x$17   [Ljava/lang/Object;
          291      92    18  x$19   [[Ljava/lang/Object;
          320      63    19  x$21   [[[Ljava/lang/Object;
          328      55    20  x$22   I
          341      42    21  x$23   [[Ljava/lang/Object;
          354      29    22  x$24   [Ljava/lang/Object;
            0     493     0  this   Lscala/collection/immutable/Vector3;
            0     493     1  elem   Ljava/lang/Object;
          138       5    23 wrap1_a   [Ljava/lang/Object;
          227      23    24 copy_len1   I
          271       5    25 wrap1_a   [Ljava/lang/Object;
          360      23    26 copy_len1   I
          360      23    27 copy_len12   I
          398       5    28 wrap1_a   [Ljava/lang/Object;
          445       6    30 wrap3_a   [[[Ljava/lang/Object;
          439      12    29 wrap3_x   [[Ljava/lang/Object;
    Signature: #141                         // <B:Ljava/lang/Object;>(TB;)Lscala/collection/immutable/Vector<TB;>;
    MethodParameters:
      Name                           Flags
      elem                           final

  public <B extends java.lang.Object> scala.collection.immutable.Vector<B> map(scala.Function1<A, B>);
    descriptor: (Lscala/Function1;)Lscala/collection/immutable/Vector;
    flags: (0x0001) ACC_PUBLIC
    Code:
      stack=10, locals=91, args_size=2
         0: getstatic     #146                // Field scala/collection/immutable/VectorStatics$.MODULE$:Lscala/collection/immutable/VectorStatics$;
         3: pop
         4: aload_0
         5: invokevirtual #47                 // Method prefix1:()[Ljava/lang/Object;
         8: astore        7
        10: iconst_0
        11: istore        8
        13: iload         8
        15: aload         7
        17: arraylength
        18: if_icmpge     129
        21: aload         7
        23: iload         8
        25: aaload
        26: astore        9
        28: aload_1
        29: aload         9
        31: invokeinterface #196,  2          // InterfaceMethod scala/Function1.apply:(Ljava/lang/Object;)Ljava/lang/Object;
        36: astore        10
        38: aload         9
        40: aload         10
        42: if_acmpeq     123
        45: aload         7
        47: arraylength
        48: anewarray     #138                // class java/lang/Object
        51: astore        11
        53: iload         8
        55: iconst_0
        56: if_icmple     70
        59: aload         7
        61: iconst_0
        62: aload         11
        64: iconst_0
        65: iload         8
        67: invokestatic  #202                // Method java/lang/System.arraycopy:(Ljava/lang/Object;ILjava/lang/Object;II)V
        70: aload         11
        72: iload         8
        74: aload         10
        76: aastore
        77: iload         8
        79: iconst_1
        80: iadd
        81: istore        12
        83: iload         12
        85: aload         7
        87: arraylength
        88: if_icmpge     113
        91: aload         11
        93: iload         12
        95: aload_1
        96: aload         7
        98: iload         12
       100: aaload
       101: invokeinterface #196,  2          // InterfaceMethod scala/Function1.apply:(Ljava/lang/Object;)Ljava/lang/Object;
       106: aastore
       107: iinc          12, 1
       110: goto          83
       113: aload         11
       115: aconst_null
       116: astore        11
       118: astore        13
       120: goto          133
       123: iinc          8, 1
       126: goto          13
       129: aload         7
       131: astore        13
       133: aload         13
       135: aconst_null
       136: astore        7
       138: aconst_null
       139: astore        9
       141: aconst_null
       142: astore        10
       144: aconst_null
       145: astore        11
       147: aconst_null
       148: astore        13
       150: astore_2
       151: getstatic     #146                // Field scala/collection/immutable/VectorStatics$.MODULE$:Lscala/collection/immutable/VectorStatics$;
       154: iconst_2
       155: aload_0
       156: invokevirtual #53                 // Method prefix2:()[[Ljava/lang/Object;
       159: astore        16
       161: istore        15
       163: astore        14
       165: iload         15
       167: iconst_1
       168: if_icmpne     311
       171: iconst_0
       172: istore        20
       174: iload         20
       176: aload         16
       178: arraylength
       179: if_icmpge     290
       182: aload         16
       184: iload         20
       186: aaload
       187: astore        21
       189: aload_1
       190: aload         21
       192: invokeinterface #196,  2          // InterfaceMethod scala/Function1.apply:(Ljava/lang/Object;)Ljava/lang/Object;
       197: astore        22
       199: aload         21
       201: aload         22
       203: if_acmpeq     284
       206: aload         16
       208: arraylength
       209: anewarray     #138                // class java/lang/Object
       212: astore        23
       214: iload         20
       216: iconst_0
       217: if_icmple     231
       220: aload         16
       222: iconst_0
       223: aload         23
       225: iconst_0
       226: iload         20
       228: invokestatic  #202                // Method java/lang/System.arraycopy:(Ljava/lang/Object;ILjava/lang/Object;II)V
       231: aload         23
       233: iload         20
       235: aload         22
       237: aastore
       238: iload         20
       240: iconst_1
       241: iadd
       242: istore        24
       244: iload         24
       246: aload         16
       248: arraylength
       249: if_icmpge     274
       252: aload         23
       254: iload         24
       256: aload_1
       257: aload         16
       259: iload         24
       261: aaload
       262: invokeinterface #196,  2          // InterfaceMethod scala/Function1.apply:(Ljava/lang/Object;)Ljava/lang/Object;
       267: aastore
       268: iinc          24, 1
       271: goto          244
       274: aload         23
       276: aconst_null
       277: astore        23
       279: astore        25
       281: goto          294
       284: iinc          20, 1
       287: goto          174
       290: aload         16
       292: astore        25
       294: aload         25
       296: aconst_null
       297: astore        21
       299: aconst_null
       300: astore        22
       302: aconst_null
       303: astore        23
       305: aconst_null
       306: astore        25
       308: goto          716
       311: iconst_0
       312: istore        17
       314: iload         17
       316: aload         16
       318: arraylength
       319: if_icmpge     714
       322: aload         16
       324: iload         17
       326: aaload
       327: astore        18
       329: aload         14
       331: iload         15
       333: iconst_1
       334: isub
       335: aload         18
       337: aload_1
       338: invokevirtual #206                // Method scala/collection/immutable/VectorStatics$.mapElems:(I[Ljava/lang/Object;Lscala/Function1;)[Ljava/lang/Object;
       341: astore        19
       343: aload         18
       345: aload         19
       347: if_acmpeq     708
       350: aload         16
       352: invokevirtual #210                // Method java/lang/Object.getClass:()Ljava/lang/Class;
       355: invokevirtual #215                // Method java/lang/Class.getComponentType:()Ljava/lang/Class;
       358: aload         16
       360: arraylength
       361: invokestatic  #221                // Method java/lang/reflect/Array.newInstance:(Ljava/lang/Class;I)Ljava/lang/Object;
       364: checkcast     #98                 // class "[Ljava/lang/Object;"
       367: astore        63
       369: iload         17
       371: iconst_0
       372: if_icmple     386
       375: aload         16
       377: iconst_0
       378: aload         63
       380: iconst_0
       381: iload         17
       383: invokestatic  #202                // Method java/lang/System.arraycopy:(Ljava/lang/Object;ILjava/lang/Object;II)V
       386: aload         63
       388: iload         17
       390: aload         19
       392: aastore
       393: iload         17
       395: iconst_1
       396: iadd
       397: istore        64
       399: iload         64
       401: aload         16
       403: arraylength
       404: if_icmpge     674
       407: aload         63
       409: iload         64
       411: iload         15
       413: iconst_1
       414: isub
       415: aload         16
       417: iload         64
       419: aaload
       420: astore        66
       422: istore        65
       424: iload         65
       426: iconst_1
       427: if_icmpne     570
       430: iconst_0
       431: istore        70
       433: iload         70
       435: aload         66
       437: arraylength
       438: if_icmpge     549
       441: aload         66
       443: iload         70
       445: aaload
       446: astore        71
       448: aload_1
       449: aload         71
       451: invokeinterface #196,  2          // InterfaceMethod scala/Function1.apply:(Ljava/lang/Object;)Ljava/lang/Object;
       456: astore        72
       458: aload         71
       460: aload         72
       462: if_acmpeq     543
       465: aload         66
       467: arraylength
       468: anewarray     #138                // class java/lang/Object
       471: astore        73
       473: iload         70
       475: iconst_0
       476: if_icmple     490
       479: aload         66
       481: iconst_0
       482: aload         73
       484: iconst_0
       485: iload         70
       487: invokestatic  #202                // Method java/lang/System.arraycopy:(Ljava/lang/Object;ILjava/lang/Object;II)V
       490: aload         73
       492: iload         70
       494: aload         72
       496: aastore
       497: iload         70
       499: iconst_1
       500: iadd
       501: istore        74
       503: iload         74
       505: aload         66
       507: arraylength
       508: if_icmpge     533
       511: aload         73
       513: iload         74
       515: aload_1
       516: aload         66
       518: iload         74
       520: aaload
       521: invokeinterface #196,  2          // InterfaceMethod scala/Function1.apply:(Ljava/lang/Object;)Ljava/lang/Object;
       526: aastore
       527: iinc          74, 1
       530: goto          503
       533: aload         73
       535: aconst_null
       536: astore        73
       538: astore        75
       540: goto          553
       543: iinc          70, 1
       546: goto          433
       549: aload         66
       551: astore        75
       553: aload         75
       555: aconst_null
       556: astore        71
       558: aconst_null
       559: astore        72
       561: aconst_null
       562: astore        73
       564: aconst_null
       565: astore        75
       567: goto          639
       570: iconst_0
       571: istore        67
       573: iload         67
       575: aload         66
       577: arraylength
       578: if_icmpge     637
       581: aload         66
       583: iload         67
       585: aaload
       586: astore        68
       588: aload         14
       590: iload         65
       592: iconst_1
       593: isub
       594: aload         68
       596: checkcast     #98                 // class "[Ljava/lang/Object;"
       599: aload_1
       600: invokevirtual #206                // Method scala/collection/immutable/VectorStatics$.mapElems:(I[Ljava/lang/Object;Lscala/Function1;)[Ljava/lang/Object;
       603: astore        69
       605: aload         68
       607: aload         69
       609: if_acmpeq     631
       612: aload         14
       614: iload         65
       616: aload         66
       618: aload_1
       619: iload         67
       621: aload         69
       623: invokevirtual #225                // Method scala/collection/immutable/VectorStatics$.mapElemsRest:(I[Ljava/lang/Object;Lscala/Function1;ILjava/lang/Object;)[Ljava/lang/Object;
       626: astore        76
       628: goto          641
       631: iinc          67, 1
       634: goto          573
       637: aload         66
       639: astore        76
       641: aload         76
       643: aconst_null
       644: astore        66
       646: aconst_null
       647: astore        68
       649: aconst_null
       650: astore        69
       652: aconst_null
       653: astore        71
       655: aconst_null
       656: astore        72
       658: aconst_null
       659: astore        73
       661: aconst_null
       662: astore        75
       664: aconst_null
       665: astore        76
       667: aastore
       668: iinc          64, 1
       671: goto          399
       674: aload         63
       676: aconst_null
       677: astore        63
       679: aconst_null
       680: astore        66
       682: aconst_null
       683: astore        68
       685: aconst_null
       686: astore        69
       688: aconst_null
       689: astore        71
       691: aconst_null
       692: astore        72
       694: aconst_null
       695: astore        73
       697: aconst_null
       698: astore        75
       700: aconst_null
       701: astore        76
       703: astore        26
       705: goto          718
       708: iinc          17, 1
       711: goto          314
       714: aload         16
       716: astore        26
       718: aload         26
       720: aconst_null
       721: astore        14
       723: aconst_null
       724: astore        16
       726: aconst_null
       727: astore        18
       729: aconst_null
       730: astore        19
       732: aconst_null
       733: astore        21
       735: aconst_null
       736: astore        22
       738: aconst_null
       739: astore        23
       741: aconst_null
       742: astore        25
       744: aconst_null
       745: astore        26
       747: checkcast     #96                 // class "[[Ljava/lang/Object;"
       750: astore_3
       751: getstatic     #146                // Field scala/collection/immutable/VectorStatics$.MODULE$:Lscala/collection/immutable/VectorStatics$;
       754: iconst_3
       755: aload_0
       756: invokevirtual #59                 // Method data3:()[[[Ljava/lang/Object;
       759: astore        29
       761: istore        28
       763: astore        27
       765: iload         28
       767: iconst_1
       768: if_icmpne     911
       771: iconst_0
       772: istore        33
       774: iload         33
       776: aload         29
       778: arraylength
       779: if_icmpge     890
       782: aload         29
       784: iload         33
       786: aaload
       787: astore        34
       789: aload_1
       790: aload         34
       792: invokeinterface #196,  2          // InterfaceMethod scala/Function1.apply:(Ljava/lang/Object;)Ljava/lang/Object;
       797: astore        35
       799: aload         34
       801: aload         35
       803: if_acmpeq     884
       806: aload         29
       808: arraylength
       809: anewarray     #138                // class java/lang/Object
       812: astore        36
       814: iload         33
       816: iconst_0
       817: if_icmple     831
       820: aload         29
       822: iconst_0
       823: aload         36
       825: iconst_0
       826: iload         33
       828: invokestatic  #202                // Method java/lang/System.arraycopy:(Ljava/lang/Object;ILjava/lang/Object;II)V
       831: aload         36
       833: iload         33
       835: aload         35
       837: aastore
       838: iload         33
       840: iconst_1
       841: iadd
       842: istore        37
       844: iload         37
       846: aload         29
       848: arraylength
       849: if_icmpge     874
       852: aload         36
       854: iload         37
       856: aload_1
       857: aload         29
       859: iload         37
       861: aaload
       862: invokeinterface #196,  2          // InterfaceMethod scala/Function1.apply:(Ljava/lang/Object;)Ljava/lang/Object;
       867: aastore
       868: iinc          37, 1
       871: goto          844
       874: aload         36
       876: aconst_null
       877: astore        36
       879: astore        38
       881: goto          894
       884: iinc          33, 1
       887: goto          774
       890: aload         29
       892: astore        38
       894: aload         38
       896: aconst_null
       897: astore        34
       899: aconst_null
       900: astore        35
       902: aconst_null
       903: astore        36
       905: aconst_null
       906: astore        38
       908: goto          1316
       911: iconst_0
       912: istore        30
       914: iload         30
       916: aload         29
       918: arraylength
       919: if_icmpge     1314
       922: aload         29
       924: iload         30
       926: aaload
       927: astore        31
       929: aload         27
       931: iload         28
       933: iconst_1
       934: isub
       935: aload         31
       937: aload_1
       938: invokevirtual #206                // Method scala/collection/immutable/VectorStatics$.mapElems:(I[Ljava/lang/Object;Lscala/Function1;)[Ljava/lang/Object;
       941: astore        32
       943: aload         31
       945: aload         32
       947: if_acmpeq     1308
       950: aload         29
       952: invokevirtual #210                // Method java/lang/Object.getClass:()Ljava/lang/Class;
       955: invokevirtual #215                // Method java/lang/Class.getComponentType:()Ljava/lang/Class;
       958: aload         29
       960: arraylength
       961: invokestatic  #221                // Method java/lang/reflect/Array.newInstance:(Ljava/lang/Class;I)Ljava/lang/Object;
       964: checkcast     #98                 // class "[Ljava/lang/Object;"
       967: astore        77
       969: iload         30
       971: iconst_0
       972: if_icmple     986
       975: aload         29
       977: iconst_0
       978: aload         77
       980: iconst_0
       981: iload         30
       983: invokestatic  #202                // Method java/lang/System.arraycopy:(Ljava/lang/Object;ILjava/lang/Object;II)V
       986: aload         77
       988: iload         30
       990: aload         32
       992: aastore
       993: iload         30
       995: iconst_1
       996: iadd
       997: istore        78
       999: iload         78
      1001: aload         29
      1003: arraylength
      1004: if_icmpge     1274
      1007: aload         77
      1009: iload         78
      1011: iload         28
      1013: iconst_1
      1014: isub
      1015: aload         29
      1017: iload         78
      1019: aaload
      1020: astore        80
      1022: istore        79
      1024: iload         79
      1026: iconst_1
      1027: if_icmpne     1170
      1030: iconst_0
      1031: istore        84
      1033: iload         84
      1035: aload         80
      1037: arraylength
      1038: if_icmpge     1149
      1041: aload         80
      1043: iload         84
      1045: aaload
      1046: astore        85
      1048: aload_1
      1049: aload         85
      1051: invokeinterface #196,  2          // InterfaceMethod scala/Function1.apply:(Ljava/lang/Object;)Ljava/lang/Object;
      1056: astore        86
      1058: aload         85
      1060: aload         86
      1062: if_acmpeq     1143
      1065: aload         80
      1067: arraylength
      1068: anewarray     #138                // class java/lang/Object
      1071: astore        87
      1073: iload         84
      1075: iconst_0
      1076: if_icmple     1090
      1079: aload         80
      1081: iconst_0
      1082: aload         87
      1084: iconst_0
      1085: iload         84
      1087: invokestatic  #202                // Method java/lang/System.arraycopy:(Ljava/lang/Object;ILjava/lang/Object;II)V
      1090: aload         87
      1092: iload         84
      1094: aload         86
      1096: aastore
      1097: iload         84
      1099: iconst_1
      1100: iadd
      1101: istore        88
      1103: iload         88
      1105: aload         80
      1107: arraylength
      1108: if_icmpge     1133
      1111: aload         87
      1113: iload         88
      1115: aload_1
      1116: aload         80
      1118: iload         88
      1120: aaload
      1121: invokeinterface #196,  2          // InterfaceMethod scala/Function1.apply:(Ljava/lang/Object;)Ljava/lang/Object;
      1126: aastore
      1127: iinc          88, 1
      1130: goto          1103
      1133: aload         87
      1135: aconst_null
      1136: astore        87
      1138: astore        89
      1140: goto          1153
      1143: iinc          84, 1
      1146: goto          1033
      1149: aload         80
      1151: astore        89
      1153: aload         89
      1155: aconst_null
      1156: astore        85
      1158: aconst_null
      1159: astore        86
      1161: aconst_null
      1162: astore        87
      1164: aconst_null
      1165: astore        89
      1167: goto          1239
      1170: iconst_0
      1171: istore        81
      1173: iload         81
      1175: aload         80
      1177: arraylength
      1178: if_icmpge     1237
      1181: aload         80
      1183: iload         81
      1185: aaload
      1186: astore        82
      1188: aload         27
      1190: iload         79
      1192: iconst_1
      1193: isub
      1194: aload         82
      1196: checkcast     #98                 // class "[Ljava/lang/Object;"
      1199: aload_1
      1200: invokevirtual #206                // Method scala/collection/immutable/VectorStatics$.mapElems:(I[Ljava/lang/Object;Lscala/Function1;)[Ljava/lang/Object;
      1203: astore        83
      1205: aload         82
      1207: aload         83
      1209: if_acmpeq     1231
      1212: aload         27
      1214: iload         79
      1216: aload         80
      1218: aload_1
      1219: iload         81
      1221: aload         83
      1223: invokevirtual #225                // Method scala/collection/immutable/VectorStatics$.mapElemsRest:(I[Ljava/lang/Object;Lscala/Function1;ILjava/lang/Object;)[Ljava/lang/Object;
      1226: astore        90
      1228: goto          1241
      1231: iinc          81, 1
      1234: goto          1173
      1237: aload         80
      1239: astore        90
      1241: aload         90
      1243: aconst_null
      1244: astore        80
      1246: aconst_null
      1247: astore        82
      1249: aconst_null
      1250: astore        83
      1252: aconst_null
      1253: astore        85
      1255: aconst_null
      1256: astore        86
      1258: aconst_null
      1259: astore        87
      1261: aconst_null
      1262: astore        89
      1264: aconst_null
      1265: astore        90
      1267: aastore
      1268: iinc          78, 1
      1271: goto          999
      1274: aload         77
      1276: aconst_null
      1277: astore        77
      1279: aconst_null
      1280: astore        80
      1282: aconst_null
      1283: astore        82
      1285: aconst_null
      1286: astore        83
      1288: aconst_null
      1289: astore        85
      1291: aconst_null
      1292: astore        86
      1294: aconst_null
      1295: astore        87
      1297: aconst_null
      1298: astore        89
      1300: aconst_null
      1301: astore        90
      1303: astore        39
      1305: goto          1318
      1308: iinc          30, 1
      1311: goto          914
      1314: aload         29
      1316: astore        39
      1318: aload         39
      1320: aconst_null
      1321: astore        27
      1323: aconst_null
      1324: astore        29
      1326: aconst_null
      1327: astore        31
      1329: aconst_null
      1330: astore        32
      1332: aconst_null
      1333: astore        34
      1335: aconst_null
      1336: astore        35
      1338: aconst_null
      1339: astore        36
      1341: aconst_null
      1342: astore        38
      1344: aconst_null
      1345: astore        39
      1347: checkcast     #91                 // class "[[[Ljava/lang/Object;"
      1350: astore        4
      1352: getstatic     #146                // Field scala/collection/immutable/VectorStatics$.MODULE$:Lscala/collection/immutable/VectorStatics$;
      1355: iconst_2
      1356: aload_0
      1357: invokevirtual #62                 // Method suffix2:()[[Ljava/lang/Object;
      1360: astore        42
      1362: istore        41
      1364: astore        40
      1366: iload         41
      1368: iconst_1
      1369: if_icmpne     1512
      1372: iconst_0
      1373: istore        46
      1375: iload         46
      1377: aload         42
      1379: arraylength
      1380: if_icmpge     1491
      1383: aload         42
      1385: iload         46
      1387: aaload
      1388: astore        47
      1390: aload_1
      1391: aload         47
      1393: invokeinterface #196,  2          // InterfaceMethod scala/Function1.apply:(Ljava/lang/Object;)Ljava/lang/Object;
      1398: astore        48
      1400: aload         47
      1402: aload         48
      1404: if_acmpeq     1485
      1407: aload         42
      1409: arraylength
      1410: anewarray     #138                // class java/lang/Object
      1413: astore        49
      1415: iload         46
      1417: iconst_0
      1418: if_icmple     1432
      1421: aload         42
      1423: iconst_0
      1424: aload         49
      1426: iconst_0
      1427: iload         46
      1429: invokestatic  #202                // Method java/lang/System.arraycopy:(Ljava/lang/Object;ILjava/lang/Object;II)V
      1432: aload         49
      1434: iload         46
      1436: aload         48
      1438: aastore
      1439: iload         46
      1441: iconst_1
      1442: iadd
      1443: istore        50
      1445: iload         50
      1447: aload         42
      1449: arraylength
      1450: if_icmpge     1475
      1453: aload         49
      1455: iload         50
      1457: aload_1
      1458: aload         42
      1460: iload         50
      1462: aaload
      1463: invokeinterface #196,  2          // InterfaceMethod scala/Function1.apply:(Ljava/lang/Object;)Ljava/lang/Object;
      1468: aastore
      1469: iinc          50, 1
      1472: goto          1445
      1475: aload         49
      1477: aconst_null
      1478: astore        49
      1480: astore        51
      1482: goto          1495
      1485: iinc          46, 1
      1488: goto          1375
      1491: aload         42
      1493: astore        51
      1495: aload         51
      1497: aconst_null
      1498: astore        47
      1500: aconst_null
      1501: astore        48
      1503: aconst_null
      1504: astore        49
      1506: aconst_null
      1507: astore        51
      1509: goto          1578
      1512: iconst_0
      1513: istore        43
      1515: iload         43
      1517: aload         42
      1519: arraylength
      1520: if_icmpge     1576
      1523: aload         42
      1525: iload         43
      1527: aaload
      1528: astore        44
      1530: aload         40
      1532: iload         41
      1534: iconst_1
      1535: isub
      1536: aload         44
      1538: aload_1
      1539: invokevirtual #206                // Method scala/collection/immutable/VectorStatics$.mapElems:(I[Ljava/lang/Object;Lscala/Function1;)[Ljava/lang/Object;
      1542: astore        45
      1544: aload         44
      1546: aload         45
      1548: if_acmpeq     1570
      1551: aload         40
      1553: iload         41
      1555: aload         42
      1557: aload_1
      1558: iload         43
      1560: aload         45
      1562: invokevirtual #225                // Method scala/collection/immutable/VectorStatics$.mapElemsRest:(I[Ljava/lang/Object;Lscala/Function1;ILjava/lang/Object;)[Ljava/lang/Object;
      1565: astore        52
      1567: goto          1580
      1570: iinc          43, 1
      1573: goto          1515
      1576: aload         42
      1578: astore        52
      1580: aload         52
      1582: aconst_null
      1583: astore        40
      1585: aconst_null
      1586: astore        42
      1588: aconst_null
      1589: astore        44
      1591: aconst_null
      1592: astore        45
      1594: aconst_null
      1595: astore        47
      1597: aconst_null
      1598: astore        48
      1600: aconst_null
      1601: astore        49
      1603: aconst_null
      1604: astore        51
      1606: aconst_null
      1607: astore        52
      1609: checkcast     #96                 // class "[[Ljava/lang/Object;"
      1612: astore        5
      1614: getstatic     #146                // Field scala/collection/immutable/VectorStatics$.MODULE$:Lscala/collection/immutable/VectorStatics$;
      1617: pop
      1618: aload_0
      1619: invokevirtual #65                 // Method suffix1:()[Ljava/lang/Object;
      1622: astore        53
      1624: iconst_0
      1625: istore        54
      1627: iload         54
      1629: aload         53
      1631: arraylength
      1632: if_icmpge     1743
      1635: aload         53
      1637: iload         54
      1639: aaload
      1640: astore        55
      1642: aload_1
      1643: aload         55
      1645: invokeinterface #196,  2          // InterfaceMethod scala/Function1.apply:(Ljava/lang/Object;)Ljava/lang/Object;
      1650: astore        56
      1652: aload         55
      1654: aload         56
      1656: if_acmpeq     1737
      1659: aload         53
      1661: arraylength
      1662: anewarray     #138                // class java/lang/Object
      1665: astore        57
      1667: iload         54
      1669: iconst_0
      1670: if_icmple     1684
      1673: aload         53
      1675: iconst_0
      1676: aload         57
      1678: iconst_0
      1679: iload         54
      1681: invokestatic  #202                // Method java/lang/System.arraycopy:(Ljava/lang/Object;ILjava/lang/Object;II)V
      1684: aload         57
      1686: iload         54
      1688: aload         56
      1690: aastore
      1691: iload         54
      1693: iconst_1
      1694: iadd
      1695: istore        58
      1697: iload         58
      1699: aload         53
      1701: arraylength
      1702: if_icmpge     1727
      1705: aload         57
      1707: iload         58
      1709: aload_1
      1710: aload         53
      1712: iload         58
      1714: aaload
      1715: invokeinterface #196,  2          // InterfaceMethod scala/Function1.apply:(Ljava/lang/Object;)Ljava/lang/Object;
      1720: aastore
      1721: iinc          58, 1
      1724: goto          1697
      1727: aload         57
      1729: aconst_null
      1730: astore        57
      1732: astore        59
      1734: goto          1747
      1737: iinc          54, 1
      1740: goto          1627
      1743: aload         53
      1745: astore        59
      1747: aload         59
      1749: aconst_null
      1750: astore        53
      1752: aconst_null
      1753: astore        55
      1755: aconst_null
      1756: astore        56
      1758: aconst_null
      1759: astore        57
      1761: aconst_null
      1762: astore        59
      1764: astore        6
      1766: aload_0
      1767: invokevirtual #50                 // Method len1:()I
      1770: istore        60
      1772: aload_0
      1773: invokevirtual #56                 // Method len12:()I
      1776: istore        61
      1778: aload_0
      1779: invokevirtual #68                 // Method length0:()I
      1782: istore        62
      1784: new           #2                  // class scala/collection/immutable/Vector3
      1787: dup
      1788: aload_2
      1789: iload         60
      1791: aload_3
      1792: iload         61
      1794: aload         4
      1796: aload         5
      1798: aload         6
      1800: iload         62
      1802: invokespecial #42                 // Method "<init>":([Ljava/lang/Object;I[[Ljava/lang/Object;I[[[Ljava/lang/Object;[[Ljava/lang/Object;[Ljava/lang/Object;I)V
      1805: areturn
      StackMapTable: number_of_entries = 85
        frame_type = 255 /* full_frame */
          offset_delta = 13
          locals = [ class scala/collection/immutable/Vector3, class scala/Function1, top, top, top, top, top, class "[Ljava/lang/Object;", int ]
          stack = []
        frame_type = 254 /* append */
          offset_delta = 56
          locals = [ class java/lang/Object, class java/lang/Object, class "[Ljava/lang/Object;" ]
        frame_type = 252 /* append */
          offset_delta = 12
          locals = [ int ]
        frame_type = 29 /* same */
        frame_type = 249 /* chop */
          offset_delta = 9
        frame_type = 249 /* chop */
          offset_delta = 5
        frame_type = 255 /* full_frame */
          offset_delta = 3
          locals = [ class scala/collection/immutable/Vector3, class scala/Function1, top, top, top, top, top, class "[Ljava/lang/Object;", int, top, top, top, top, class "[Ljava/lang/Object;" ]
          stack = []
        frame_type = 255 /* full_frame */
          offset_delta = 40
          locals = [ class scala/collection/immutable/Vector3, class scala/Function1, class "[Ljava/lang/Object;", top, top, top, top, null, int, null, null, null, top, null, class scala/collection/immutable/VectorStatics$, int, class "[[Ljava/lang/Object;", top, top, top, int ]
          stack = []
        frame_type = 254 /* append */
          offset_delta = 56
          locals = [ class "[Ljava/lang/Object;", class java/lang/Object, class "[Ljava/lang/Object;" ]
        frame_type = 252 /* append */
          offset_delta = 12
          locals = [ int ]
        frame_type = 29 /* same */
        frame_type = 249 /* chop */
          offset_delta = 9
        frame_type = 249 /* chop */
          offset_delta = 5
        frame_type = 255 /* full_frame */
          offset_delta = 3
          locals = [ class scala/collection/immutable/Vector3, class scala/Function1, class "[Ljava/lang/Object;", top, top, top, top, null, int, null, null, null, top, null, class scala/collection/immutable/VectorStatics$, int, class "[[Ljava/lang/Object;", top, top, top, int, top, top, top, top, class "[Ljava/lang/Object;" ]
          stack = []
        frame_type = 255 /* full_frame */
          offset_delta = 16
          locals = [ class scala/collection/immutable/Vector3, class scala/Function1, class "[Ljava/lang/Object;", top, top, top, top, null, int, null, null, null, top, null, class scala/collection/immutable/VectorStatics$, int, class "[[Ljava/lang/Object;" ]
          stack = []
        frame_type = 252 /* append */
          offset_delta = 2
          locals = [ int ]
        frame_type = 255 /* full_frame */
          offset_delta = 71
          locals = [ class scala/collection/immutable/Vector3, class scala/Function1, class "[Ljava/lang/Object;", top, top, top, top, null, int, null, null, null, top, null, class scala/collection/immutable/VectorStatics$, int, class "[[Ljava/lang/Object;", int, class "[Ljava/lang/Object;", class "[Ljava/lang/Object;", top, top, top, top, top, top, top, top, top, top, top, top, top, top, top, top, top, top, top, top, top, top, top, top, top, top, top, top, top, top, top, top, top, top, top, top, top, top, top, top, top, top, top, class "[Ljava/lang/Object;" ]
          stack = []
        frame_type = 252 /* append */
          offset_delta = 12
          locals = [ int ]
        frame_type = 255 /* full_frame */
          offset_delta = 33
          locals = [ class scala/collection/immutable/Vector3, class scala/Function1, class "[Ljava/lang/Object;", top, top, top, top, null, int, null, null, null, top, null, class scala/collection/immutable/VectorStatics$, int, class "[[Ljava/lang/Object;", int, class "[Ljava/lang/Object;", class "[Ljava/lang/Object;", top, top, top, top, top, top, top, top, top, top, top, top, top, top, top, top, top, top, top, top, top, top, top, top, top, top, top, top, top, top, top, top, top, top, top, top, top, top, top, top, top, top, top, class "[Ljava/lang/Object;", int, int, class "[Ljava/lang/Object;", top, top, top, int ]
          stack = [ class "[Ljava/lang/Object;", int ]
        frame_type = 255 /* full_frame */
          offset_delta = 56
          locals = [ class scala/collection/immutable/Vector3, class scala/Function1, class "[Ljava/lang/Object;", top, top, top, top, null, int, null, null, null, top, null, class scala/collection/immutable/VectorStatics$, int, class "[[Ljava/lang/Object;", int, class "[Ljava/lang/Object;", class "[Ljava/lang/Object;", top, top, top, top, top, top, top, top, top, top, top, top, top, top, top, top, top, top, top, top, top, top, top, top, top, top, top, top, top, top, top, top, top, top, top, top, top, top, top, top, top, top, top, class "[Ljava/lang/Object;", int, int, class "[Ljava/lang/Object;", top, top, top, int, class java/lang/Object, class java/lang/Object, class "[Ljava/lang/Object;" ]
          stack = [ class "[Ljava/lang/Object;", int ]
        frame_type = 255 /* full_frame */
          offset_delta = 12
          locals = [ class scala/collection/immutable/Vector3, class scala/Function1, class "[Ljava/lang/Object;", top, top, top, top, null, int, null, null, null, top, null, class scala/collection/immutable/VectorStatics$, int, class "[[Ljava/lang/Object;", int, class "[Ljava/lang/Object;", class "[Ljava/lang/Object;", top, top, top, top, top, top, top, top, top, top, top, top, top, top, top, top, top, top, top, top, top, top, top, top, top, top, top, top, top, top, top, top, top, top, top, top, top, top, top, top, top, top, top, class "[Ljava/lang/Object;", int, int, class "[Ljava/lang/Object;", top, top, top, int, class java/lang/Object, class java/lang/Object, class "[Ljava/lang/Object;", int ]
          stack = [ class "[Ljava/lang/Object;", int ]
        frame_type = 255 /* full_frame */
          offset_delta = 29
          locals = [ class scala/collection/immutable/Vector3, class scala/Function1, class "[Ljava/lang/Object;", top, top, top, top, null, int, null, null, null, top, null, class scala/collection/immutable/VectorStatics$, int, class "[[Ljava/lang/Object;", int, class "[Ljava/lang/Object;", class "[Ljava/lang/Object;", top, top, top, top, top, top, top, top, top, top, top, top, top, top, top, top, top, top, top, top, top, top, top, top, top, top, top, top, top, top, top, top, top, top, top, top, top, top, top, top, top, top, top, class "[Ljava/lang/Object;", int, int, class "[Ljava/lang/Object;", top, top, top, int, class java/lang/Object, class java/lang/Object, class "[Ljava/lang/Object;", int ]
          stack = [ class "[Ljava/lang/Object;", int ]
        frame_type = 255 /* full_frame */
          offset_delta = 9
          locals = [ class scala/collection/immutable/Vector3, class scala/Function1, class "[Ljava/lang/Object;", top, top, top, top, null, int, null, null, null, top, null, class scala/collection/immutable/VectorStatics$, int, class "[[Ljava/lang/Object;", int, class "[Ljava/lang/Object;", class "[Ljava/lang/Object;", top, top, top, top, top, top, top, top, top, top, top, top, top, top, top, top, top, top, top, top, top, top, top, top, top, top, top, top, top, top, top, top, top, top, top, top, top, top, top, top, top, top, top, class "[Ljava/lang/Object;", int, int, class "[Ljava/lang/Object;", top, top, top, int, class java/lang/Object, class java/lang/Object ]
          stack = [ class "[Ljava/lang/Object;", int ]
        frame_type = 255 /* full_frame */
          offset_delta = 5
          locals = [ class scala/collection/immutable/Vector3, class scala/Function1, class "[Ljava/lang/Object;", top, top, top, top, null, int, null, null, null, top, null, class scala/collection/immutable/VectorStatics$, int, class "[[Ljava/lang/Object;", int, class "[Ljava/lang/Object;", class "[Ljava/lang/Object;", top, top, top, top, top, top, top, top, top, top, top, top, top, top, top, top, top, top, top, top, top, top, top, top, top, top, top, top, top, top, top, top, top, top, top, top, top, top, top, top, top, top, top, class "[Ljava/lang/Object;", int, int, class "[Ljava/lang/Object;", top, top, top, int ]
          stack = [ class "[Ljava/lang/Object;", int ]
        frame_type = 255 /* full_frame */
          offset_delta = 3
          locals = [ class scala/collection/immutable/Vector3, class scala/Function1, class "[Ljava/lang/Object;", top, top, top, top, null, int, null, null, null, top, null, class scala/collection/immutable/VectorStatics$, int, class "[[Ljava/lang/Object;", int, class "[Ljava/lang/Object;", class "[Ljava/lang/Object;", top, top, top, top, top, top, top, top, top, top, top, top, top, top, top, top, top, top, top, top, top, top, top, top, top, top, top, top, top, top, top, top, top, top, top, top, top, top, top, top, top, top, top, class "[Ljava/lang/Object;", int, int, class "[Ljava/lang/Object;", top, top, top, int, top, top, top, top, class "[Ljava/lang/Object;" ]
          stack = [ class "[Ljava/lang/Object;", int ]
        frame_type = 255 /* full_frame */
          offset_delta = 16
          locals = [ class scala/collection/immutable/Vector3, class scala/Function1, class "[Ljava/lang/Object;", top, top, top, top, null, int, null, null, null, top, null, class scala/collection/immutable/VectorStatics$, int, class "[[Ljava/lang/Object;", int, class "[Ljava/lang/Object;", class "[Ljava/lang/Object;", top, top, top, top, top, top, top, top, top, top, top, top, top, top, top, top, top, top, top, top, top, top, top, top, top, top, top, top, top, top, top, top, top, top, top, top, top, top, top, top, top, top, top, class "[Ljava/lang/Object;", int, int, class "[Ljava/lang/Object;" ]
          stack = [ class "[Ljava/lang/Object;", int ]
        frame_type = 255 /* full_frame */
          offset_delta = 2
          locals = [ class scala/collection/immutable/Vector3, class scala/Function1, class "[Ljava/lang/Object;", top, top, top, top, null, int, null, null, null, top, null, class scala/collection/immutable/VectorStatics$, int, class "[[Ljava/lang/Object;", int, class "[Ljava/lang/Object;", class "[Ljava/lang/Object;", top, top, top, top, top, top, top, top, top, top, top, top, top, top, top, top, top, top, top, top, top, top, top, top, top, top, top, top, top, top, top, top, top, top, top, top, top, top, top, top, top, top, top, class "[Ljava/lang/Object;", int, int, class "[Ljava/lang/Object;", int ]
          stack = [ class "[Ljava/lang/Object;", int ]
        frame_type = 255 /* full_frame */
          offset_delta = 57
          locals = [ class scala/collection/immutable/Vector3, class scala/Function1, class "[Ljava/lang/Object;", top, top, top, top, null, int, null, null, null, top, null, class scala/collection/immutable/VectorStatics$, int, class "[[Ljava/lang/Object;", int, class "[Ljava/lang/Object;", class "[Ljava/lang/Object;", top, top, top, top, top, top, top, top, top, top, top, top, top, top, top, top, top, top, top, top, top, top, top, top, top, top, top, top, top, top, top, top, top, top, top, top, top, top, top, top, top, top, top, class "[Ljava/lang/Object;", int, int, class "[Ljava/lang/Object;", int, class java/lang/Object, class "[Ljava/lang/Object;" ]
          stack = [ class "[Ljava/lang/Object;", int ]
        frame_type = 255 /* full_frame */
          offset_delta = 5
          locals = [ class scala/collection/immutable/Vector3, class scala/Function1, class "[Ljava/lang/Object;", top, top, top, top, null, int, null, null, null, top, null, class scala/collection/immutable/VectorStatics$, int, class "[[Ljava/lang/Object;", int, class "[Ljava/lang/Object;", class "[Ljava/lang/Object;", top, top, top, top, top, top, top, top, top, top, top, top, top, top, top, top, top, top, top, top, top, top, top, top, top, top, top, top, top, top, top, top, top, top, top, top, top, top, top, top, top, top, top, class "[Ljava/lang/Object;", int, int, class "[Ljava/lang/Object;", int ]
          stack = [ class "[Ljava/lang/Object;", int ]
        frame_type = 255 /* full_frame */
          offset_delta = 1
          locals = [ class scala/collection/immutable/Vector3, class scala/Function1, class "[Ljava/lang/Object;", top, top, top, top, null, int, null, null, null, top, null, class scala/collection/immutable/VectorStatics$, int, class "[[Ljava/lang/Object;", int, class "[Ljava/lang/Object;", class "[Ljava/lang/Object;", top, top, top, top, top, top, top, top, top, top, top, top, top, top, top, top, top, top, top, top, top, top, top, top, top, top, top, top, top, top, top, top, top, top, top, top, top, top, top, top, top, top, top, class "[Ljava/lang/Object;", int, int, class "[Ljava/lang/Object;" ]
          stack = [ class "[Ljava/lang/Object;", int, class "[Ljava/lang/Object;" ]
        frame_type = 255 /* full_frame */
          offset_delta = 1
          locals = [ class scala/collection/immutable/Vector3, class scala/Function1, class "[Ljava/lang/Object;", top, top, top, top, null, int, null, null, null, top, null, class scala/collection/immutable/VectorStatics$, int, class "[[Ljava/lang/Object;", int, class "[Ljava/lang/Object;", class "[Ljava/lang/Object;", top, top, top, top, top, top, top, top, top, top, top, top, top, top, top, top, top, top, top, top, top, top, top, top, top, top, top, top, top, top, top, top, top, top, top, top, top, top, top, top, top, top, top, class "[Ljava/lang/Object;", int, int, class "[Ljava/lang/Object;", top, top, top, top, top, top, top, top, top, class "[Ljava/lang/Object;" ]
          stack = [ class "[Ljava/lang/Object;", int ]
        frame_type = 255 /* full_frame */
          offset_delta = 32
          locals = [ class scala/collection/immutable/Vector3, class scala/Function1, class "[Ljava/lang/Object;", top, top, top, top, null, int, null, null, null, top, null, class scala/collection/immutable/VectorStatics$, int, class "[[Ljava/lang/Object;", int, class "[Ljava/lang/Object;", class "[Ljava/lang/Object;", top, top, top, top, top, top, top, top, top, top, top, top, top, top, top, top, top, top, top, top, top, top, top, top, top, top, top, top, top, top, top, top, top, top, top, top, top, top, top, top, top, top, top, class "[Ljava/lang/Object;", int ]
          stack = []
        frame_type = 255 /* full_frame */
          offset_delta = 33
          locals = [ class scala/collection/immutable/Vector3, class scala/Function1, class "[Ljava/lang/Object;", top, top, top, top, null, int, null, null, null, top, null, class scala/collection/immutable/VectorStatics$, int, class "[[Ljava/lang/Object;", int, class "[Ljava/lang/Object;", class "[Ljava/lang/Object;" ]
          stack = []
        frame_type = 249 /* chop */
          offset_delta = 5
        frame_type = 255 /* full_frame */
          offset_delta = 1
          locals = [ class scala/collection/immutable/Vector3, class scala/Function1, class "[Ljava/lang/Object;", top, top, top, top, null, int, null, null, null, top, null, class scala/collection/immutable/VectorStatics$, int, class "[[Ljava/lang/Object;" ]
          stack = [ class "[Ljava/lang/Object;" ]
        frame_type = 255 /* full_frame */
          offset_delta = 1
          locals = [ class scala/collection/immutable/Vector3, class scala/Function1, class "[Ljava/lang/Object;", top, top, top, top, null, int, null, null, null, top, null, class scala/collection/immutable/VectorStatics$, int, class "[[Ljava/lang/Object;", top, top, top, top, top, top, top, top, top, class "[Ljava/lang/Object;" ]
          stack = []
        frame_type = 255 /* full_frame */
          offset_delta = 55
          locals = [ class scala/collection/immutable/Vector3, class scala/Function1, class "[Ljava/lang/Object;", class "[[Ljava/lang/Object;", top, top, top, null, int, null, null, null, top, null, null, int, null, top, null, null, top, null, null, null, top, null, null, class scala/collection/immutable/VectorStatics$, int, class "[[[Ljava/lang/Object;", top, top, top, int ]
          stack = []
        frame_type = 254 /* append */
          offset_delta = 56
          locals = [ class "[[Ljava/lang/Object;", class java/lang/Object, class "[Ljava/lang/Object;" ]
        frame_type = 252 /* append */
          offset_delta = 12
          locals = [ int ]
        frame_type = 29 /* same */
        frame_type = 249 /* chop */
          offset_delta = 9
        frame_type = 249 /* chop */
          offset_delta = 5
        frame_type = 255 /* full_frame */
          offset_delta = 3
          locals = [ class scala/collection/immutable/Vector3, class scala/Function1, class "[Ljava/lang/Object;", class "[[Ljava/lang/Object;", top, top, top, null, int, null, null, null, top, null, null, int, null, top, null, null, top, null, null, null, top, null, null, class scala/collection/immutable/VectorStatics$, int, class "[[[Ljava/lang/Object;", top, top, top, int, top, top, top, top, class "[Ljava/lang/Object;" ]
          stack = []
        frame_type = 255 /* full_frame */
          offset_delta = 16
          locals = [ class scala/collection/immutable/Vector3, class scala/Function1, class "[Ljava/lang/Object;", class "[[Ljava/lang/Object;", top, top, top, null, int, null, null, null, top, null, null, int, null, top, null, null, top, null, null, null, top, null, null, class scala/collection/immutable/VectorStatics$, int, class "[[[Ljava/lang/Object;" ]
          stack = []
        frame_type = 252 /* append */
          offset_delta = 2
          locals = [ int ]
        frame_type = 255 /* full_frame */
          offset_delta = 71
          locals = [ class scala/collection/immutable/Vector3, class scala/Function1, class "[Ljava/lang/Object;", class "[[Ljava/lang/Object;", top, top, top, null, int, null, null, null, top, null, null, int, null, top, null, null, top, null, null, null, top, null, null, class scala/collection/immutable/VectorStatics$, int, class "[[[Ljava/lang/Object;", int, class "[[Ljava/lang/Object;", class "[Ljava/lang/Object;", top, top, top, top, top, top, top, top, top, top, top, top, top, top, top, top, top, top, top, top, top, top, top, top, top, top, top, top, top, top, top, top, top, top, top, top, top, top, top, top, top, top, top, top, class "[Ljava/lang/Object;" ]
          stack = []
        frame_type = 252 /* append */
          offset_delta = 12
          locals = [ int ]
        frame_type = 255 /* full_frame */
          offset_delta = 33
          locals = [ class scala/collection/immutable/Vector3, class scala/Function1, class "[Ljava/lang/Object;", class "[[Ljava/lang/Object;", top, top, top, null, int, null, null, null, top, null, null, int, null, top, null, null, top, null, null, null, top, null, null, class scala/collection/immutable/VectorStatics$, int, class "[[[Ljava/lang/Object;", int, class "[[Ljava/lang/Object;", class "[Ljava/lang/Object;", top, top, top, top, top, top, top, top, top, top, top, top, top, top, top, top, top, top, top, top, top, top, top, top, top, top, top, top, top, top, top, top, top, top, top, top, top, top, top, top, top, top, top, top, class "[Ljava/lang/Object;", int, int, class "[[Ljava/lang/Object;", top, top, top, int ]
          stack = [ class "[Ljava/lang/Object;", int ]
        frame_type = 255 /* full_frame */
          offset_delta = 56
          locals = [ class scala/collection/immutable/Vector3, class scala/Function1, class "[Ljava/lang/Object;", class "[[Ljava/lang/Object;", top, top, top, null, int, null, null, null, top, null, null, int, null, top, null, null, top, null, null, null, top, null, null, class scala/collection/immutable/VectorStatics$, int, class "[[[Ljava/lang/Object;", int, class "[[Ljava/lang/Object;", class "[Ljava/lang/Object;", top, top, top, top, top, top, top, top, top, top, top, top, top, top, top, top, top, top, top, top, top, top, top, top, top, top, top, top, top, top, top, top, top, top, top, top, top, top, top, top, top, top, top, top, class "[Ljava/lang/Object;", int, int, class "[[Ljava/lang/Object;", top, top, top, int, class "[Ljava/lang/Object;", class java/lang/Object, class "[Ljava/lang/Object;" ]
          stack = [ class "[Ljava/lang/Object;", int ]
        frame_type = 255 /* full_frame */
          offset_delta = 12
          locals = [ class scala/collection/immutable/Vector3, class scala/Function1, class "[Ljava/lang/Object;", class "[[Ljava/lang/Object;", top, top, top, null, int, null, null, null, top, null, null, int, null, top, null, null, top, null, null, null, top, null, null, class scala/collection/immutable/VectorStatics$, int, class "[[[Ljava/lang/Object;", int, class "[[Ljava/lang/Object;", class "[Ljava/lang/Object;", top, top, top, top, top, top, top, top, top, top, top, top, top, top, top, top, top, top, top, top, top, top, top, top, top, top, top, top, top, top, top, top, top, top, top, top, top, top, top, top, top, top, top, top, class "[Ljava/lang/Object;", int, int, class "[[Ljava/lang/Object;", top, top, top, int, class "[Ljava/lang/Object;", class java/lang/Object, class "[Ljava/lang/Object;", int ]
          stack = [ class "[Ljava/lang/Object;", int ]
        frame_type = 255 /* full_frame */
          offset_delta = 29
          locals = [ class scala/collection/immutable/Vector3, class scala/Function1, class "[Ljava/lang/Object;", class "[[Ljava/lang/Object;", top, top, top, null, int, null, null, null, top, null, null, int, null, top, null, null, top, null, null, null, top, null, null, class scala/collection/immutable/VectorStatics$, int, class "[[[Ljava/lang/Object;", int, class "[[Ljava/lang/Object;", class "[Ljava/lang/Object;", top, top, top, top, top, top, top, top, top, top, top, top, top, top, top, top, top, top, top, top, top, top, top, top, top, top, top, top, top, top, top, top, top, top, top, top, top, top, top, top, top, top, top, top, class "[Ljava/lang/Object;", int, int, class "[[Ljava/lang/Object;", top, top, top, int, class "[Ljava/lang/Object;", class java/lang/Object, class "[Ljava/lang/Object;", int ]
          stack = [ class "[Ljava/lang/Object;", int ]
        frame_type = 255 /* full_frame */
          offset_delta = 9
          locals = [ class scala/collection/immutable/Vector3, class scala/Function1, class "[Ljava/lang/Object;", class "[[Ljava/lang/Object;", top, top, top, null, int, null, null, null, top, null, null, int, null, top, null, null, top, null, null, null, top, null, null, class scala/collection/immutable/VectorStatics$, int, class "[[[Ljava/lang/Object;", int, class "[[Ljava/lang/Object;", class "[Ljava/lang/Object;", top, top, top, top, top, top, top, top, top, top, top, top, top, top, top, top, top, top, top, top, top, top, top, top, top, top, top, top, top, top, top, top, top, top, top, top, top, top, top, top, top, top, top, top, class "[Ljava/lang/Object;", int, int, class "[[Ljava/lang/Object;", top, top, top, int, class "[Ljava/lang/Object;", class java/lang/Object ]
          stack = [ class "[Ljava/lang/Object;", int ]
        frame_type = 255 /* full_frame */
          offset_delta = 5
          locals = [ class scala/collection/immutable/Vector3, class scala/Function1, class "[Ljava/lang/Object;", class "[[Ljava/lang/Object;", top, top, top, null, int, null, null, null, top, null, null, int, null, top, null, null, top, null, null, null, top, null, null, class scala/collection/immutable/VectorStatics$, int, class "[[[Ljava/lang/Object;", int, class "[[Ljava/lang/Object;", class "[Ljava/lang/Object;", top, top, top, top, top, top, top, top, top, top, top, top, top, top, top, top, top, top, top, top, top, top, top, top, top, top, top, top, top, top, top, top, top, top, top, top, top, top, top, top, top, top, top, top, class "[Ljava/lang/Object;", int, int, class "[[Ljava/lang/Object;", top, top, top, int ]
          stack = [ class "[Ljava/lang/Object;", int ]
        frame_type = 255 /* full_frame */
          offset_delta = 3
          locals = [ class scala/collection/immutable/Vector3, class scala/Function1, class "[Ljava/lang/Object;", class "[[Ljava/lang/Object;", top, top, top, null, int, null, null, null, top, null, null, int, null, top, null, null, top, null, null, null, top, null, null, class scala/collection/immutable/VectorStatics$, int, class "[[[Ljava/lang/Object;", int, class "[[Ljava/lang/Object;", class "[Ljava/lang/Object;", top, top, top, top, top, top, top, top, top, top, top, top, top, top, top, top, top, top, top, top, top, top, top, top, top, top, top, top, top, top, top, top, top, top, top, top, top, top, top, top, top, top, top, top, class "[Ljava/lang/Object;", int, int, class "[[Ljava/lang/Object;", top, top, top, int, top, top, top, top, class "[Ljava/lang/Object;" ]
          stack = [ class "[Ljava/lang/Object;", int ]
        frame_type = 255 /* full_frame */
          offset_delta = 16
          locals = [ class scala/collection/immutable/Vector3, class scala/Function1, class "[Ljava/lang/Object;", class "[[Ljava/lang/Object;", top, top, top, null, int, null, null, null, top, null, null, int, null, top, null, null, top, null, null, null, top, null, null, class scala/collection/immutable/VectorStatics$, int, class "[[[Ljava/lang/Object;", int, class "[[Ljava/lang/Object;", class "[Ljava/lang/Object;", top, top, top, top, top, top, top, top, top, top, top, top, top, top, top, top, top, top, top, top, top, top, top, top, top, top, top, top, top, top, top, top, top, top, top, top, top, top, top, top, top, top, top, top, class "[Ljava/lang/Object;", int, int, class "[[Ljava/lang/Object;" ]
          stack = [ class "[Ljava/lang/Object;", int ]
        frame_type = 255 /* full_frame */
          offset_delta = 2
          locals = [ class scala/collection/immutable/Vector3, class scala/Function1, class "[Ljava/lang/Object;", class "[[Ljava/lang/Object;", top, top, top, null, int, null, null, null, top, null, null, int, null, top, null, null, top, null, null, null, top, null, null, class scala/collection/immutable/VectorStatics$, int, class "[[[Ljava/lang/Object;", int, class "[[Ljava/lang/Object;", class "[Ljava/lang/Object;", top, top, top, top, top, top, top, top, top, top, top, top, top, top, top, top, top, top, top, top, top, top, top, top, top, top, top, top, top, top, top, top, top, top, top, top, top, top, top, top, top, top, top, top, class "[Ljava/lang/Object;", int, int, class "[[Ljava/lang/Object;", int ]
          stack = [ class "[Ljava/lang/Object;", int ]
        frame_type = 255 /* full_frame */
          offset_delta = 57
          locals = [ class scala/collection/immutable/Vector3, class scala/Function1, class "[Ljava/lang/Object;", class "[[Ljava/lang/Object;", top, top, top, null, int, null, null, null, top, null, null, int, null, top, null, null, top, null, null, null, top, null, null, class scala/collection/immutable/VectorStatics$, int, class "[[[Ljava/lang/Object;", int, class "[[Ljava/lang/Object;", class "[Ljava/lang/Object;", top, top, top, top, top, top, top, top, top, top, top, top, top, top, top, top, top, top, top, top, top, top, top, top, top, top, top, top, top, top, top, top, top, top, top, top, top, top, top, top, top, top, top, top, class "[Ljava/lang/Object;", int, int, class "[[Ljava/lang/Object;", int, class "[Ljava/lang/Object;", class "[Ljava/lang/Object;" ]
          stack = [ class "[Ljava/lang/Object;", int ]
        frame_type = 255 /* full_frame */
          offset_delta = 5
          locals = [ class scala/collection/immutable/Vector3, class scala/Function1, class "[Ljava/lang/Object;", class "[[Ljava/lang/Object;", top, top, top, null, int, null, null, null, top, null, null, int, null, top, null, null, top, null, null, null, top, null, null, class scala/collection/immutable/VectorStatics$, int, class "[[[Ljava/lang/Object;", int, class "[[Ljava/lang/Object;", class "[Ljava/lang/Object;", top, top, top, top, top, top, top, top, top, top, top, top, top, top, top, top, top, top, top, top, top, top, top, top, top, top, top, top, top, top, top, top, top, top, top, top, top, top, top, top, top, top, top, top, class "[Ljava/lang/Object;", int, int, class "[[Ljava/lang/Object;", int ]
          stack = [ class "[Ljava/lang/Object;", int ]
        frame_type = 255 /* full_frame */
          offset_delta = 1
          locals = [ class scala/collection/immutable/Vector3, class scala/Function1, class "[Ljava/lang/Object;", class "[[Ljava/lang/Object;", top, top, top, null, int, null, null, null, top, null, null, int, null, top, null, null, top, null, null, null, top, null, null, class scala/collection/immutable/VectorStatics$, int, class "[[[Ljava/lang/Object;", int, class "[[Ljava/lang/Object;", class "[Ljava/lang/Object;", top, top, top, top, top, top, top, top, top, top, top, top, top, top, top, top, top, top, top, top, top, top, top, top, top, top, top, top, top, top, top, top, top, top, top, top, top, top, top, top, top, top, top, top, class "[Ljava/lang/Object;", int, int, class "[[Ljava/lang/Object;" ]
          stack = [ class "[Ljava/lang/Object;", int, class "[Ljava/lang/Object;" ]
        frame_type = 255 /* full_frame */
          offset_delta = 1
          locals = [ class scala/collection/immutable/Vector3, class scala/Function1, class "[Ljava/lang/Object;", class "[[Ljava/lang/Object;", top, top, top, null, int, null, null, null, top, null, null, int, null, top, null, null, top, null, null, null, top, null, null, class scala/collection/immutable/VectorStatics$, int, class "[[[Ljava/lang/Object;", int, class "[[Ljava/lang/Object;", class "[Ljava/lang/Object;", top, top, top, top, top, top, top, top, top, top, top, top, top, top, top, top, top, top, top, top, top, top, top, top, top, top, top, top, top, top, top, top, top, top, top, top, top, top, top, top, top, top, top, top, class "[Ljava/lang/Object;", int, int, class "[[Ljava/lang/Object;", top, top, top, top, top, top, top, top, top, class "[Ljava/lang/Object;" ]
          stack = [ class "[Ljava/lang/Object;", int ]
        frame_type = 255 /* full_frame */
          offset_delta = 32
          locals = [ class scala/collection/immutable/Vector3, class scala/Function1, class "[Ljava/lang/Object;", class "[[Ljava/lang/Object;", top, top, top, null, int, null, null, null, top, null, null, int, null, top, null, null, top, null, null, null, top, null, null, class scala/collection/immutable/VectorStatics$, int, class "[[[Ljava/lang/Object;", int, class "[[Ljava/lang/Object;", class "[Ljava/lang/Object;", top, top, top, top, top, top, top, top, top, top, top, top, top, top, top, top, top, top, top, top, top, top, top, top, top, top, top, top, top, top, top, top, top, top, top, top, top, top, top, top, top, top, top, top, class "[Ljava/lang/Object;", int ]
          stack = []
        frame_type = 255 /* full_frame */
          offset_delta = 33
          locals = [ class scala/collection/immutable/Vector3, class scala/Function1, class "[Ljava/lang/Object;", class "[[Ljava/lang/Object;", top, top, top, null, int, null, null, null, top, null, null, int, null, top, null, null, top, null, null, null, top, null, null, class scala/collection/immutable/VectorStatics$, int, class "[[[Ljava/lang/Object;", int, class "[[Ljava/lang/Object;", class "[Ljava/lang/Object;" ]
          stack = []
        frame_type = 249 /* chop */
          offset_delta = 5
        frame_type = 255 /* full_frame */
          offset_delta = 1
          locals = [ class scala/collection/immutable/Vector3, class scala/Function1, class "[Ljava/lang/Object;", class "[[Ljava/lang/Object;", top, top, top, null, int, null, null, null, top, null, null, int, null, top, null, null, top, null, null, null, top, null, null, class scala/collection/immutable/VectorStatics$, int, class "[[[Ljava/lang/Object;" ]
          stack = [ class "[Ljava/lang/Object;" ]
        frame_type = 255 /* full_frame */
          offset_delta = 1
          locals = [ class scala/collection/immutable/Vector3, class scala/Function1, class "[Ljava/lang/Object;", class "[[Ljava/lang/Object;", top, top, top, null, int, null, null, null, top, null, null, int, null, top, null, null, top, null, null, null, top, null, null, class scala/collection/immutable/VectorStatics$, int, class "[[[Ljava/lang/Object;", top, top, top, top, top, top, top, top, top, class "[Ljava/lang/Object;" ]
          stack = []
        frame_type = 255 /* full_frame */
          offset_delta = 56
          locals = [ class scala/collection/immutable/Vector3, class scala/Function1, class "[Ljava/lang/Object;", class "[[Ljava/lang/Object;", class "[[[Ljava/lang/Object;", top, top, null, int, null, null, null, top, null, null, int, null, top, null, null, top, null, null, null, top, null, null, null, int, null, top, null, null, top, null, null, null, top, null, null, class scala/collection/immutable/VectorStatics$, int, class "[[Ljava/lang/Object;", top, top, top, int ]
          stack = []
        frame_type = 254 /* append */
          offset_delta = 56
          locals = [ class "[Ljava/lang/Object;", class java/lang/Object, class "[Ljava/lang/Object;" ]
        frame_type = 252 /* append */
          offset_delta = 12
          locals = [ int ]
        frame_type = 29 /* same */
        frame_type = 249 /* chop */
          offset_delta = 9
        frame_type = 249 /* chop */
          offset_delta = 5
        frame_type = 255 /* full_frame */
          offset_delta = 3
          locals = [ class scala/collection/immutable/Vector3, class scala/Function1, class "[Ljava/lang/Object;", class "[[Ljava/lang/Object;", class "[[[Ljava/lang/Object;", top, top, null, int, null, null, null, top, null, null, int, null, top, null, null, top, null, null, null, top, null, null, null, int, null, top, null, null, top, null, null, null, top, null, null, class scala/collection/immutable/VectorStatics$, int, class "[[Ljava/lang/Object;", top, top, top, int, top, top, top, top, class "[Ljava/lang/Object;" ]
          stack = []
        frame_type = 255 /* full_frame */
          offset_delta = 16
          locals = [ class scala/collection/immutable/Vector3, class scala/Function1, class "[Ljava/lang/Object;", class "[[Ljava/lang/Object;", class "[[[Ljava/lang/Object;", top, top, null, int, null, null, null, top, null, null, int, null, top, null, null, top, null, null, null, top, null, null, null, int, null, top, null, null, top, null, null, null, top, null, null, class scala/collection/immutable/VectorStatics$, int, class "[[Ljava/lang/Object;" ]
          stack = []
        frame_type = 252 /* append */
          offset_delta = 2
          locals = [ int ]
        frame_type = 253 /* append */
          offset_delta = 54
          locals = [ class "[Ljava/lang/Object;", class "[Ljava/lang/Object;" ]
        frame_type = 249 /* chop */
          offset_delta = 5
        frame_type = 255 /* full_frame */
          offset_delta = 1
          locals = [ class scala/collection/immutable/Vector3, class scala/Function1, class "[Ljava/lang/Object;", class "[[Ljava/lang/Object;", class "[[[Ljava/lang/Object;", top, top, null, int, null, null, null, top, null, null, int, null, top, null, null, top, null, null, null, top, null, null, null, int, null, top, null, null, top, null, null, null, top, null, null, class scala/collection/immutable/VectorStatics$, int, class "[[Ljava/lang/Object;" ]
          stack = [ class "[Ljava/lang/Object;" ]
        frame_type = 255 /* full_frame */
          offset_delta = 1
          locals = [ class scala/collection/immutable/Vector3, class scala/Function1, class "[Ljava/lang/Object;", class "[[Ljava/lang/Object;", class "[[[Ljava/lang/Object;", top, top, null, int, null, null, null, top, null, null, int, null, top, null, null, top, null, null, null, top, null, null, null, int, null, top, null, null, top, null, null, null, top, null, null, class scala/collection/immutable/VectorStatics$, int, class "[[Ljava/lang/Object;", top, top, top, top, top, top, top, top, top, class "[Ljava/lang/Object;" ]
          stack = []
        frame_type = 255 /* full_frame */
          offset_delta = 46
          locals = [ class scala/collection/immutable/Vector3, class scala/Function1, class "[Ljava/lang/Object;", class "[[Ljava/lang/Object;", class "[[[Ljava/lang/Object;", class "[[Ljava/lang/Object;", top, null, int, null, null, null, top, null, null, int, null, top, null, null, top, null, null, null, top, null, null, null, int, null, top, null, null, top, null, null, null, top, null, null, null, int, null, top, null, null, top, null, null, null, top, null, null, class "[Ljava/lang/Object;", int ]
          stack = []
        frame_type = 254 /* append */
          offset_delta = 56
          locals = [ class java/lang/Object, class java/lang/Object, class "[Ljava/lang/Object;" ]
        frame_type = 252 /* append */
          offset_delta = 12
          locals = [ int ]
        frame_type = 29 /* same */
        frame_type = 249 /* chop */
          offset_delta = 9
        frame_type = 249 /* chop */
          offset_delta = 5
        frame_type = 255 /* full_frame */
          offset_delta = 3
          locals = [ class scala/collection/immutable/Vector3, class scala/Function1, class "[Ljava/lang/Object;", class "[[Ljava/lang/Object;", class "[[[Ljava/lang/Object;", class "[[Ljava/lang/Object;", top, null, int, null, null, null, top, null, null, int, null, top, null, null, top, null, null, null, top, null, null, null, int, null, top, null, null, top, null, null, null, top, null, null, null, int, null, top, null, null, top, null, null, null, top, null, null, class "[Ljava/lang/Object;", int, top, top, top, top, class "[Ljava/lang/Object;" ]
          stack = []
      LineNumberTable:
        line 591: 0
        line 1869: 10
        line 1870: 13
        line 1871: 21
        line 1872: 28
        line 1873: 38
        line 1881: 45
        line 1882: 53
        line 1883: 70
        line 1884: 77
        line 1885: 83
        line 1886: 91
        line 1887: 107
        line 1885: 110
        line 1889: 113
        line 1874: 113
        line 1875: 123
        line 1870: 126
        line 1877: 129
        line 591: 133
        line 1893: 165
        line 1869: 171
        line 1870: 174
        line 1871: 182
        line 1872: 189
        line 1873: 199
        line 1881: 206
        line 1882: 214
        line 1883: 231
        line 1884: 238
        line 1885: 244
        line 1886: 252
        line 1887: 268
        line 1885: 271
        line 1889: 274
        line 1874: 274
        line 1875: 284
        line 1870: 287
        line 1877: 290
        line 1894: 294
        line 1896: 311
        line 1897: 314
        line 1898: 322
        line 1899: 329
        line 1900: 343
        line 1909: 350
        line 1910: 369
        line 1911: 386
        line 1912: 393
        line 1913: 399
        line 1914: 407
        line 1893: 424
        line 1869: 430
        line 1870: 433
        line 1871: 441
        line 1872: 448
        line 1873: 458
        line 1881: 465
        line 1882: 473
        line 1883: 490
        line 1884: 497
        line 1885: 503
        line 1886: 511
        line 1887: 527
        line 1885: 530
        line 1889: 533
        line 1874: 533
        line 1875: 543
        line 1870: 546
        line 1877: 549
        line 1894: 553
        line 1896: 570
        line 1897: 573
        line 1898: 581
        line 1899: 588
        line 1900: 605
        line 1901: 612
        line 1902: 631
        line 1897: 634
        line 1904: 637
        line 1914: 641
        line 1915: 668
        line 1913: 671
        line 1917: 674
        line 1901: 674
        line 1902: 708
        line 1897: 711
        line 1904: 714
        line 591: 718
        line 592: 751
        line 1893: 765
        line 1869: 771
        line 1870: 774
        line 1871: 782
        line 1872: 789
        line 1873: 799
        line 1881: 806
        line 1882: 814
        line 1883: 831
        line 1884: 838
        line 1885: 844
        line 1886: 852
        line 1887: 868
        line 1885: 871
        line 1889: 874
        line 1874: 874
        line 1875: 884
        line 1870: 887
        line 1877: 890
        line 1894: 894
        line 1896: 911
        line 1897: 914
        line 1898: 922
        line 1899: 929
        line 1900: 943
        line 1909: 950
        line 1910: 969
        line 1911: 986
        line 1912: 993
        line 1913: 999
        line 1914: 1007
        line 1893: 1024
        line 1869: 1030
        line 1870: 1033
        line 1871: 1041
        line 1872: 1048
        line 1873: 1058
        line 1881: 1065
        line 1882: 1073
        line 1883: 1090
        line 1884: 1097
        line 1885: 1103
        line 1886: 1111
        line 1887: 1127
        line 1885: 1130
        line 1889: 1133
        line 1874: 1133
        line 1875: 1143
        line 1870: 1146
        line 1877: 1149
        line 1894: 1153
        line 1896: 1170
        line 1897: 1173
        line 1898: 1181
        line 1899: 1188
        line 1900: 1205
        line 1901: 1212
        line 1902: 1231
        line 1897: 1234
        line 1904: 1237
        line 1914: 1241
        line 1915: 1268
        line 1913: 1271
        line 1917: 1274
        line 1901: 1274
        line 1902: 1308
        line 1897: 1311
        line 1904: 1314
        line 592: 1318
        line 593: 1352
        line 1893: 1366
        line 1869: 1372
        line 1870: 1375
        line 1871: 1383
        line 1872: 1390
        line 1873: 1400
        line 1881: 1407
        line 1882: 1415
        line 1883: 1432
        line 1884: 1439
        line 1885: 1445
        line 1886: 1453
        line 1887: 1469
        line 1885: 1472
        line 1889: 1475
        line 1874: 1475
        line 1875: 1485
        line 1870: 1488
        line 1877: 1491
        line 1894: 1495
        line 1896: 1512
        line 1897: 1515
        line 1898: 1523
        line 1899: 1530
        line 1900: 1544
        line 1901: 1551
        line 1902: 1570
        line 1897: 1573
        line 1904: 1576
        line 593: 1580
        line 1869: 1624
        line 1870: 1627
        line 1871: 1635
        line 1872: 1642
        line 1873: 1652
        line 1881: 1659
        line 1882: 1667
        line 1883: 1684
        line 1884: 1691
        line 1885: 1697
        line 1886: 1705
        line 1887: 1721
        line 1885: 1724
        line 1889: 1727
        line 1874: 1727
        line 1875: 1737
        line 1870: 1740
        line 1877: 1743
        line 593: 1747
        line 533: 1766
        line 534: 1772
        line 537: 1778
        line 538: 1784
        line 591: 1805
      LocalVariableTable:
        Start  Length  Slot  Name   Signature
          151    1654     2   x$1   [Ljava/lang/Object;
          751    1054     3   x$2   [[Ljava/lang/Object;
         1352     453     4   x$3   [[[Ljava/lang/Object;
         1614     191     5   x$4   [[Ljava/lang/Object;
         1766      39     6   x$5   [Ljava/lang/Object;
            0    1806     0  this   Lscala/collection/immutable/Vector3;
            0    1806     1     f   Lscala/Function1;
           28      98     9 mapElems1_v1   Ljava/lang/Object;
           38      88    10 mapElems1_v2   Ljava/lang/Object;
           13     118     8 mapElems1_i   I
           10     123     7 mapElems1_a   [Ljava/lang/Object;
           53      60    11 mapElems1_mapElems1Rest_ac   [Ljava/lang/Object;
           83      30    12 mapElems1_mapElems1Rest_i   I
          329     382    18 mapElems_v1   Ljava/lang/Object;
          343     368    19 mapElems_v2   [Ljava/lang/Object;
          314     402    17 mapElems_i   I
          165     553    14 mapElems_this   Lscala/collection/immutable/VectorStatics$;
          165     553    15 mapElems_n   I
          165     553    16 mapElems_a   [Ljava/lang/Object;
          189      98    21 mapElems_mapElems1_v1   Ljava/lang/Object;
          199      88    22 mapElems_mapElems1_v2   Ljava/lang/Object;
          174     118    20 mapElems_mapElems1_i   I
          214      60    23 mapElems_mapElems1_mapElems1Rest_ac   [Ljava/lang/Object;
          244      30    24 mapElems_mapElems1_mapElems1Rest_i   I
          929     382    31 mapElems_v1   Ljava/lang/Object;
          943     368    32 mapElems_v2   [Ljava/lang/Object;
          914     402    30 mapElems_i   I
          765     553    27 mapElems_this   Lscala/collection/immutable/VectorStatics$;
          765     553    28 mapElems_n   I
          765     553    29 mapElems_a   [Ljava/lang/Object;
          789      98    34 mapElems_mapElems1_v1   Ljava/lang/Object;
          799      88    35 mapElems_mapElems1_v2   Ljava/lang/Object;
          774     118    33 mapElems_mapElems1_i   I
          814      60    36 mapElems_mapElems1_mapElems1Rest_ac   [Ljava/lang/Object;
          844      30    37 mapElems_mapElems1_mapElems1Rest_i   I
         1530      43    44 mapElems_v1   Ljava/lang/Object;
         1544      29    45 mapElems_v2   [Ljava/lang/Object;
         1515      63    43 mapElems_i   I
         1366     214    40 mapElems_this   Lscala/collection/immutable/VectorStatics$;
         1366     214    41 mapElems_n   I
         1366     214    42 mapElems_a   [Ljava/lang/Object;
         1390      98    47 mapElems_mapElems1_v1   Ljava/lang/Object;
         1400      88    48 mapElems_mapElems1_v2   Ljava/lang/Object;
         1375     118    46 mapElems_mapElems1_i   I
         1415      60    49 mapElems_mapElems1_mapElems1Rest_ac   [Ljava/lang/Object;
         1445      30    50 mapElems_mapElems1_mapElems1Rest_i   I
         1642      98    55 mapElems1_v1   Ljava/lang/Object;
         1652      88    56 mapElems1_v2   Ljava/lang/Object;
         1627     118    54 mapElems1_i   I
         1624     123    53 mapElems1_a   [Ljava/lang/Object;
         1667      60    57 mapElems1_mapElems1Rest_ac   [Ljava/lang/Object;
         1697      30    58 mapElems1_mapElems1Rest_i   I
          369     305    63 mapElemsRest_ac   [Ljava/lang/Object;
          399     275    64 mapElemsRest_i   I
          588      46    68 mapElemsRest_mapElems_v1   Ljava/lang/Object;
          605      29    69 mapElemsRest_mapElems_v2   [Ljava/lang/Object;
          573      66    67 mapElemsRest_mapElems_i   I
          424     217    65 mapElemsRest_mapElems_n   I
          424     217    66 mapElemsRest_mapElems_a   [Ljava/lang/Object;
          448      98    71 mapElemsRest_mapElems_mapElems1_v1   Ljava/lang/Object;
          458      88    72 mapElemsRest_mapElems_mapElems1_v2   Ljava/lang/Object;
          433     118    70 mapElemsRest_mapElems_mapElems1_i   I
          473      60    73 mapElemsRest_mapElems_mapElems1_mapElems1Rest_ac   [Ljava/lang/Object;
          503      30    74 mapElemsRest_mapElems_mapElems1_mapElems1Rest_i   I
          969     305    77 mapElemsRest_ac   [Ljava/lang/Object;
          999     275    78 mapElemsRest_i   I
         1188      46    82 mapElemsRest_mapElems_v1   Ljava/lang/Object;
         1205      29    83 mapElemsRest_mapElems_v2   [Ljava/lang/Object;
         1173      66    81 mapElemsRest_mapElems_i   I
         1024     217    79 mapElemsRest_mapElems_n   I
         1024     217    80 mapElemsRest_mapElems_a   [Ljava/lang/Object;
         1048      98    85 mapElemsRest_mapElems_mapElems1_v1   Ljava/lang/Object;
         1058      88    86 mapElemsRest_mapElems_mapElems1_v2   Ljava/lang/Object;
         1033     118    84 mapElemsRest_mapElems_mapElems1_i   I
         1073      60    87 mapElemsRest_mapElems_mapElems1_mapElems1Rest_ac   [Ljava/lang/Object;
         1103      30    88 mapElemsRest_mapElems_mapElems1_mapElems1Rest_i   I
    Signature: #190                         // <B:Ljava/lang/Object;>(Lscala/Function1<TA;TB;>;)Lscala/collection/immutable/Vector<TB;>;
    MethodParameters:
      Name                           Flags
      f                              final

  public scala.collection.immutable.Vector<A> slice0(int, int);
    descriptor: (II)Lscala/collection/immutable/Vector;
    flags: (0x0001) ACC_PUBLIC
    Code:
      stack=4, locals=4, args_size=3
         0: new           #262                // class scala/collection/immutable/VectorSliceBuilder
         3: dup
         4: iload_1
         5: iload_2
         6: invokespecial #265                // Method scala/collection/immutable/VectorSliceBuilder."<init>":(II)V
         9: astore_3
        10: aload_3
        11: iconst_1
        12: aload_0
        13: invokevirtual #47                 // Method prefix1:()[Ljava/lang/Object;
        16: invokevirtual #269                // Method scala/collection/immutable/VectorSliceBuilder.consider:(I[Ljava/lang/Object;)V
        19: aload_3
        20: iconst_2
        21: aload_0
        22: invokevirtual #53                 // Method prefix2:()[[Ljava/lang/Object;
        25: invokevirtual #269                // Method scala/collection/immutable/VectorSliceBuilder.consider:(I[Ljava/lang/Object;)V
        28: aload_3
        29: iconst_3
        30: aload_0
        31: invokevirtual #59                 // Method data3:()[[[Ljava/lang/Object;
        34: invokevirtual #269                // Method scala/collection/immutable/VectorSliceBuilder.consider:(I[Ljava/lang/Object;)V
        37: aload_3
        38: iconst_2
        39: aload_0
        40: invokevirtual #62                 // Method suffix2:()[[Ljava/lang/Object;
        43: invokevirtual #269                // Method scala/collection/immutable/VectorSliceBuilder.consider:(I[Ljava/lang/Object;)V
        46: aload_3
        47: iconst_1
        48: aload_0
        49: invokevirtual #65                 // Method suffix1:()[Ljava/lang/Object;
        52: invokevirtual #269                // Method scala/collection/immutable/VectorSliceBuilder.consider:(I[Ljava/lang/Object;)V
        55: aload_3
        56: invokevirtual #273                // Method scala/collection/immutable/VectorSliceBuilder.result:()Lscala/collection/immutable/Vector;
        59: areturn
      LineNumberTable:
        line 596: 0
        line 597: 10
        line 598: 19
        line 599: 28
        line 600: 37
        line 601: 46
        line 602: 55
      LocalVariableTable:
        Start  Length  Slot  Name   Signature
           10      49     3     b   Lscala/collection/immutable/VectorSliceBuilder;
            0      60     0  this   Lscala/collection/immutable/Vector3;
            0      60     1    lo   I
            0      60     2    hi   I
    Signature: #258                         // (II)Lscala/collection/immutable/Vector<TA;>;
    MethodParameters:
      Name                           Flags
      lo                             final
      hi                             final

  public scala.collection.immutable.Vector<A> tail();
    descriptor: ()Lscala/collection/immutable/Vector;
    flags: (0x0001) ACC_PUBLIC
    Code:
      stack=10, locals=15, args_size=1
         0: aload_0
         1: invokevirtual #50                 // Method len1:()I
         4: iconst_1
         5: if_icmple     133
         8: getstatic     #90                 // Field scala/collection/immutable/VectorInline$.MODULE$:Lscala/collection/immutable/VectorInline$;
        11: pop
        12: aload_0
        13: invokevirtual #47                 // Method prefix1:()[Ljava/lang/Object;
        16: astore        9
        18: aload         9
        20: iconst_1
        21: aload         9
        23: arraylength
        24: invokestatic  #283                // Method java/util/Arrays.copyOfRange:([Ljava/lang/Object;II)[Ljava/lang/Object;
        27: astore        10
        29: aload         10
        31: aconst_null
        32: astore        9
        34: aconst_null
        35: astore        10
        37: astore_1
        38: aload_0
        39: invokevirtual #50                 // Method len1:()I
        42: iconst_1
        43: isub
        44: istore_2
        45: aload_0
        46: invokevirtual #56                 // Method len12:()I
        49: iconst_1
        50: isub
        51: istore_3
        52: aload_0
        53: invokevirtual #68                 // Method length0:()I
        56: iconst_1
        57: isub
        58: istore        4
        60: aload_0
        61: invokevirtual #53                 // Method prefix2:()[[Ljava/lang/Object;
        64: astore        11
        66: aload         11
        68: aconst_null
        69: astore        11
        71: astore        5
        73: aload_0
        74: invokevirtual #59                 // Method data3:()[[[Ljava/lang/Object;
        77: astore        12
        79: aload         12
        81: aconst_null
        82: astore        12
        84: astore        6
        86: aload_0
        87: invokevirtual #62                 // Method suffix2:()[[Ljava/lang/Object;
        90: astore        13
        92: aload         13
        94: aconst_null
        95: astore        13
        97: astore        7
        99: aload_0
       100: invokevirtual #65                 // Method suffix1:()[Ljava/lang/Object;
       103: astore        14
       105: aload         14
       107: aconst_null
       108: astore        14
       110: astore        8
       112: new           #2                  // class scala/collection/immutable/Vector3
       115: dup
       116: aload_1
       117: iload_2
       118: aload         5
       120: iload_3
       121: aload         6
       123: aload         7
       125: aload         8
       127: iload         4
       129: invokespecial #42                 // Method "<init>":([Ljava/lang/Object;I[[Ljava/lang/Object;I[[[Ljava/lang/Object;[[Ljava/lang/Object;[Ljava/lang/Object;I)V
       132: areturn
       133: aload_0
       134: iconst_1
       135: aload_0
       136: invokevirtual #68                 // Method length0:()I
       139: invokevirtual #285                // Method slice0:(II)Lscala/collection/immutable/Vector;
       142: areturn
      StackMapTable: number_of_entries = 1
        frame_type = 251 /* same_frame_extended */
          offset_delta = 133
      LineNumberTable:
        line 606: 0
        line 1756: 18
        line 606: 29
        line 534: 60
        line 606: 66
        line 535: 73
        line 606: 79
        line 536: 86
        line 606: 92
        line 536: 99
        line 606: 105
        line 538: 112
        line 606: 132
        line 607: 133
      LocalVariableTable:
        Start  Length  Slot  Name   Signature
           38      94     1   x$1   [Ljava/lang/Object;
           45      87     2   x$2   I
           52      80     3   x$3   I
           60      72     4   x$4   I
           73      59     5   x$5   [[Ljava/lang/Object;
           86      46     6   x$6   [[[Ljava/lang/Object;
           99      33     7   x$7   [[Ljava/lang/Object;
          112      20     8   x$8   [Ljava/lang/Object;
            0     143     0  this   Lscala/collection/immutable/Vector3;
           18      11     9 copyTail_a   [Ljava/lang/Object;
    Signature: #277                         // ()Lscala/collection/immutable/Vector<TA;>;

  public scala.collection.immutable.Vector<A> init();
    descriptor: ()Lscala/collection/immutable/Vector;
    flags: (0x0001) ACC_PUBLIC
    Code:
      stack=10, locals=15, args_size=1
         0: aload_0
         1: invokevirtual #65                 // Method suffix1:()[Ljava/lang/Object;
         4: arraylength
         5: iconst_1
         6: if_icmple     132
         9: getstatic     #90                 // Field scala/collection/immutable/VectorInline$.MODULE$:Lscala/collection/immutable/VectorInline$;
        12: pop
        13: aload_0
        14: invokevirtual #65                 // Method suffix1:()[Ljava/lang/Object;
        17: astore        7
        19: aload         7
        21: iconst_0
        22: aload         7
        24: arraylength
        25: iconst_1
        26: isub
        27: invokestatic  #283                // Method java/util/Arrays.copyOfRange:([Ljava/lang/Object;II)[Ljava/lang/Object;
        30: astore        8
        32: aload         8
        34: aconst_null
        35: astore        7
        37: aconst_null
        38: astore        8
        40: astore_1
        41: aload_0
        42: invokevirtual #68                 // Method length0:()I
        45: iconst_1
        46: isub
        47: istore_2
        48: aload_0
        49: invokevirtual #47                 // Method prefix1:()[Ljava/lang/Object;
        52: astore        9
        54: aload         9
        56: aconst_null
        57: astore        9
        59: astore_3
        60: aload_0
        61: invokevirtual #50                 // Method len1:()I
        64: istore        10
        66: aload_0
        67: invokevirtual #53                 // Method prefix2:()[[Ljava/lang/Object;
        70: astore        11
        72: aload         11
        74: aconst_null
        75: astore        11
        77: astore        4
        79: aload_0
        80: invokevirtual #56                 // Method len12:()I
        83: istore        12
        85: aload_0
        86: invokevirtual #59                 // Method data3:()[[[Ljava/lang/Object;
        89: astore        13
        91: aload         13
        93: aconst_null
        94: astore        13
        96: astore        5
        98: aload_0
        99: invokevirtual #62                 // Method suffix2:()[[Ljava/lang/Object;
       102: astore        14
       104: aload         14
       106: aconst_null
       107: astore        14
       109: astore        6
       111: new           #2                  // class scala/collection/immutable/Vector3
       114: dup
       115: aload_3
       116: iload         10
       118: aload         4
       120: iload         12
       122: aload         5
       124: aload         6
       126: aload_1
       127: iload_2
       128: invokespecial #42                 // Method "<init>":([Ljava/lang/Object;I[[Ljava/lang/Object;I[[[Ljava/lang/Object;[[Ljava/lang/Object;[Ljava/lang/Object;I)V
       131: areturn
       132: aload_0
       133: iconst_0
       134: aload_0
       135: invokevirtual #68                 // Method length0:()I
       138: iconst_1
       139: isub
       140: invokevirtual #285                // Method slice0:(II)Lscala/collection/immutable/Vector;
       143: areturn
      StackMapTable: number_of_entries = 1
        frame_type = 251 /* same_frame_extended */
          offset_delta = 132
      LineNumberTable:
        line 610: 0
        line 1758: 19
        line 610: 32
        line 533: 48
        line 610: 54
        line 533: 60
        line 534: 66
        line 610: 72
        line 534: 79
        line 535: 85
        line 610: 91
        line 536: 98
        line 610: 104
        line 538: 111
        line 610: 131
        line 611: 132
      LocalVariableTable:
        Start  Length  Slot  Name   Signature
           41      90     1   x$1   [Ljava/lang/Object;
           48      83     2   x$2   I
           60      71     3   x$3   [Ljava/lang/Object;
           79      52     4   x$5   [[Ljava/lang/Object;
           98      33     5   x$7   [[[Ljava/lang/Object;
          111      20     6   x$8   [[Ljava/lang/Object;
            0     144     0  this   Lscala/collection/immutable/Vector3;
           19      13     7 copyInit_a   [Ljava/lang/Object;
    Signature: #277                         // ()Lscala/collection/immutable/Vector<TA;>;

  public int vectorSliceCount();
    descriptor: ()I
    flags: (0x0001) ACC_PUBLIC
    Code:
      stack=1, locals=1, args_size=1
         0: iconst_5
         1: ireturn
      LineNumberTable:
        line 613: 0
      LocalVariableTable:
        Start  Length  Slot  Name   Signature
            0       2     0  this   Lscala/collection/immutable/Vector3;

  public java.lang.Object[] vectorSlice(int);
    descriptor: (I)[Ljava/lang/Object;
    flags: (0x0001) ACC_PUBLIC
    Code:
      stack=3, locals=2, args_size=2
         0: iload_1
         1: tableswitch   { // 0 to 4
                       0: 36
                       1: 41
                       2: 46
                       3: 51
                       4: 56
                 default: 61
            }
        36: aload_0
        37: invokevirtual #47                 // Method prefix1:()[Ljava/lang/Object;
        40: areturn
        41: aload_0
        42: invokevirtual #53                 // Method prefix2:()[[Ljava/lang/Object;
        45: areturn
        46: aload_0
        47: invokevirtual #59                 // Method data3:()[[[Ljava/lang/Object;
        50: areturn
        51: aload_0
        52: invokevirtual #62                 // Method suffix2:()[[Ljava/lang/Object;
        55: areturn
        56: aload_0
        57: invokevirtual #65                 // Method suffix1:()[Ljava/lang/Object;
        60: areturn
        61: new           #294                // class scala/MatchError
        64: dup
        65: iload_1
        66: invokestatic  #300                // Method java/lang/Integer.valueOf:(I)Ljava/lang/Integer;
        69: invokespecial #303                // Method scala/MatchError."<init>":(Ljava/lang/Object;)V
        72: athrow
      StackMapTable: number_of_entries = 6
        frame_type = 36 /* same */
        frame_type = 4 /* same */
        frame_type = 4 /* same */
        frame_type = 4 /* same */
        frame_type = 4 /* same */
        frame_type = 4 /* same */
      LineNumberTable:
        line 614: 0
        line 615: 36
        line 616: 41
        line 617: 46
        line 618: 51
        line 619: 56
        line 614: 61
      LocalVariableTable:
        Start  Length  Slot  Name   Signature
            0      73     0  this   Lscala/collection/immutable/Vector3;
            0      73     1   idx   I
    Signature: #291                         // (I)[Ljava/lang/Object;
    MethodParameters:
      Name                           Flags
      idx                            final

  public int vectorSlicePrefixLength(int);
    descriptor: (I)I
    flags: (0x0001) ACC_PUBLIC
    Code:
      stack=3, locals=2, args_size=2
         0: iload_1
         1: tableswitch   { // 0 to 4
                       0: 36
                       1: 41
                       2: 46
                       3: 61
                       4: 72
                 default: 77
            }
        36: aload_0
        37: invokevirtual #50                 // Method len1:()I
        40: ireturn
        41: aload_0
        42: invokevirtual #56                 // Method len12:()I
        45: ireturn
        46: aload_0
        47: invokevirtual #56                 // Method len12:()I
        50: aload_0
        51: invokevirtual #59                 // Method data3:()[[[Ljava/lang/Object;
        54: arraylength
        55: sipush        1024
        58: imul
        59: iadd
        60: ireturn
        61: aload_0
        62: invokevirtual #68                 // Method length0:()I
        65: aload_0
        66: invokevirtual #65                 // Method suffix1:()[Ljava/lang/Object;
        69: arraylength
        70: isub
        71: ireturn
        72: aload_0
        73: invokevirtual #68                 // Method length0:()I
        76: ireturn
        77: new           #294                // class scala/MatchError
        80: dup
        81: iload_1
        82: invokestatic  #300                // Method java/lang/Integer.valueOf:(I)Ljava/lang/Integer;
        85: invokespecial #303                // Method scala/MatchError."<init>":(Ljava/lang/Object;)V
        88: athrow
      StackMapTable: number_of_entries = 6
        frame_type = 36 /* same */
        frame_type = 4 /* same */
        frame_type = 4 /* same */
        frame_type = 14 /* same */
        frame_type = 10 /* same */
        frame_type = 4 /* same */
      LineNumberTable:
        line 621: 0
        line 622: 36
        line 623: 41
        line 624: 46
        line 625: 61
        line 626: 72
        line 621: 77
      LocalVariableTable:
        Start  Length  Slot  Name   Signature
            0      89     0  this   Lscala/collection/immutable/Vector3;
            0      89     1   idx   I
    MethodParameters:
      Name                           Flags
      idx                            final

  public <B extends java.lang.Object> scala.collection.immutable.Vector<B> prependedAll0(scala.collection.IterableOnce<B>, int);
    descriptor: (Lscala/collection/IterableOnce;I)Lscala/collection/immutable/Vector;
    flags: (0x0001) ACC_PUBLIC
    Code:
      stack=10, locals=15, args_size=3
         0: getstatic     #146                // Field scala/collection/immutable/VectorStatics$.MODULE$:Lscala/collection/immutable/VectorStatics$;
         3: aload_0
         4: invokevirtual #47                 // Method prefix1:()[Ljava/lang/Object;
         7: aload_1
         8: invokevirtual #314                // Method scala/collection/immutable/VectorStatics$.prepend1IfSpace:([Ljava/lang/Object;Lscala/collection/IterableOnce;)[Ljava/lang/Object;
        11: astore_3
        12: aload_3
        13: ifnull        127
        16: aload_0
        17: invokevirtual #50                 // Method len1:()I
        20: aload_0
        21: invokevirtual #47                 // Method prefix1:()[Ljava/lang/Object;
        24: arraylength
        25: isub
        26: aload_3
        27: arraylength
        28: iadd
        29: istore        4
        31: aload_0
        32: invokevirtual #68                 // Method length0:()I
        35: aload_0
        36: invokevirtual #47                 // Method prefix1:()[Ljava/lang/Object;
        39: arraylength
        40: isub
        41: aload_3
        42: arraylength
        43: iadd
        44: istore        5
        46: aload_0
        47: invokevirtual #53                 // Method prefix2:()[[Ljava/lang/Object;
        50: astore        10
        52: aload         10
        54: aconst_null
        55: astore        10
        57: astore        6
        59: aload_0
        60: invokevirtual #56                 // Method len12:()I
        63: istore        11
        65: aload_0
        66: invokevirtual #59                 // Method data3:()[[[Ljava/lang/Object;
        69: astore        12
        71: aload         12
        73: aconst_null
        74: astore        12
        76: astore        7
        78: aload_0
        79: invokevirtual #62                 // Method suffix2:()[[Ljava/lang/Object;
        82: astore        13
        84: aload         13
        86: aconst_null
        87: astore        13
        89: astore        8
        91: aload_0
        92: invokevirtual #65                 // Method suffix1:()[Ljava/lang/Object;
        95: astore        14
        97: aload         14
        99: aconst_null
       100: astore        14
       102: astore        9
       104: new           #2                  // class scala/collection/immutable/Vector3
       107: dup
       108: aload_3
       109: iload         4
       111: aload         6
       113: iload         11
       115: aload         7
       117: aload         8
       119: aload         9
       121: iload         5
       123: invokespecial #42                 // Method "<init>":([Ljava/lang/Object;I[[Ljava/lang/Object;I[[[Ljava/lang/Object;[[Ljava/lang/Object;[Ljava/lang/Object;I)V
       126: areturn
       127: aload_0
       128: aload_1
       129: iload_2
       130: invokespecial #318                // Method scala/collection/immutable/Vector.prependedAll0:(Lscala/collection/IterableOnce;I)Lscala/collection/immutable/Vector;
       133: areturn
      StackMapTable: number_of_entries = 1
        frame_type = 252 /* append */
          offset_delta = 127
          locals = [ class "[Ljava/lang/Object;" ]
      LineNumberTable:
        line 630: 0
        line 631: 12
        line 534: 46
        line 631: 52
        line 534: 59
        line 535: 65
        line 631: 71
        line 536: 78
        line 631: 84
        line 536: 91
        line 631: 97
        line 538: 104
        line 631: 126
        line 632: 127
      LocalVariableTable:
        Start  Length  Slot  Name   Signature
           31      95     4   x$2   I
           46      80     5   x$3   I
           59      67     6   x$4   [[Ljava/lang/Object;
           78      48     7   x$6   [[[Ljava/lang/Object;
           91      35     8   x$7   [[Ljava/lang/Object;
          104      22     9   x$8   [Ljava/lang/Object;
           12     121     3 prefix1b   [Ljava/lang/Object;
            0     134     0  this   Lscala/collection/immutable/Vector3;
            0     134     1 prefix   Lscala/collection/IterableOnce;
            0     134     2     k   I
    Signature: #308                         // <B:Ljava/lang/Object;>(Lscala/collection/IterableOnce<TB;>;I)Lscala/collection/immutable/Vector<TB;>;
    MethodParameters:
      Name                           Flags
      prefix                         final
      k                              final

  public <B extends java.lang.Object> scala.collection.immutable.Vector<B> appendedAll0(scala.collection.IterableOnce<B>, int);
    descriptor: (Lscala/collection/IterableOnce;I)Lscala/collection/immutable/Vector;
    flags: (0x0001) ACC_PUBLIC
    Code:
      stack=10, locals=15, args_size=3
         0: getstatic     #146                // Field scala/collection/immutable/VectorStatics$.MODULE$:Lscala/collection/immutable/VectorStatics$;
         3: aload_0
         4: invokevirtual #65                 // Method suffix1:()[Ljava/lang/Object;
         7: aload_1
         8: invokevirtual #325                // Method scala/collection/immutable/VectorStatics$.append1IfSpace:([Ljava/lang/Object;Lscala/collection/IterableOnce;)[Ljava/lang/Object;
        11: astore_3
        12: aload_3
        13: ifnull        118
        16: aload_0
        17: invokevirtual #68                 // Method length0:()I
        20: aload_0
        21: invokevirtual #65                 // Method suffix1:()[Ljava/lang/Object;
        24: arraylength
        25: isub
        26: aload_3
        27: arraylength
        28: iadd
        29: istore        4
        31: aload_0
        32: invokevirtual #47                 // Method prefix1:()[Ljava/lang/Object;
        35: astore        9
        37: aload         9
        39: aconst_null
        40: astore        9
        42: astore        5
        44: aload_0
        45: invokevirtual #50                 // Method len1:()I
        48: istore        10
        50: aload_0
        51: invokevirtual #53                 // Method prefix2:()[[Ljava/lang/Object;
        54: astore        11
        56: aload         11
        58: aconst_null
        59: astore        11
        61: astore        6
        63: aload_0
        64: invokevirtual #56                 // Method len12:()I
        67: istore        12
        69: aload_0
        70: invokevirtual #59                 // Method data3:()[[[Ljava/lang/Object;
        73: astore        13
        75: aload         13
        77: aconst_null
        78: astore        13
        80: astore        7
        82: aload_0
        83: invokevirtual #62                 // Method suffix2:()[[Ljava/lang/Object;
        86: astore        14
        88: aload         14
        90: aconst_null
        91: astore        14
        93: astore        8
        95: new           #2                  // class scala/collection/immutable/Vector3
        98: dup
        99: aload         5
       101: iload         10
       103: aload         6
       105: iload         12
       107: aload         7
       109: aload         8
       111: aload_3
       112: iload         4
       114: invokespecial #42                 // Method "<init>":([Ljava/lang/Object;I[[Ljava/lang/Object;I[[[Ljava/lang/Object;[[Ljava/lang/Object;[Ljava/lang/Object;I)V
       117: areturn
       118: aload_0
       119: aload_1
       120: iload_2
       121: invokespecial #327                // Method scala/collection/immutable/Vector.appendedAll0:(Lscala/collection/IterableOnce;I)Lscala/collection/immutable/Vector;
       124: areturn
      StackMapTable: number_of_entries = 1
        frame_type = 252 /* append */
          offset_delta = 118
          locals = [ class "[Ljava/lang/Object;" ]
      LineNumberTable:
        line 635: 0
        line 636: 12
        line 533: 31
        line 636: 37
        line 533: 44
        line 534: 50
        line 636: 56
        line 534: 63
        line 535: 69
        line 636: 75
        line 536: 82
        line 636: 88
        line 538: 95
        line 636: 117
        line 637: 118
      LocalVariableTable:
        Start  Length  Slot  Name   Signature
           31      86     4   x$2   I
           44      73     5   x$3   [Ljava/lang/Object;
           63      54     6   x$5   [[Ljava/lang/Object;
           82      35     7   x$7   [[[Ljava/lang/Object;
           95      22     8   x$8   [[Ljava/lang/Object;
           12     112     3 suffix1b   [Ljava/lang/Object;
            0     125     0  this   Lscala/collection/immutable/Vector3;
            0     125     1 suffix   Lscala/collection/IterableOnce;
            0     125     2     k   I
    Signature: #308                         // <B:Ljava/lang/Object;>(Lscala/collection/IterableOnce<TB;>;I)Lscala/collection/immutable/Vector<TB;>;
    MethodParameters:
      Name                           Flags
      suffix                         final
      k                              final

  public java.lang.Object init();
    descriptor: ()Ljava/lang/Object;
    flags: (0x1041) ACC_PUBLIC, ACC_BRIDGE, ACC_SYNTHETIC
    Code:
      stack=1, locals=1, args_size=1
         0: aload_0
         1: invokevirtual #330                // Method init:()Lscala/collection/immutable/Vector;
         4: areturn
      LineNumberTable:
        line 527: 0
      LocalVariableTable:
        Start  Length  Slot  Name   Signature
            0       5     0  this   Lscala/collection/immutable/Vector3;

  public java.lang.Object tail();
    descriptor: ()Ljava/lang/Object;
    flags: (0x1041) ACC_PUBLIC, ACC_BRIDGE, ACC_SYNTHETIC
    Code:
      stack=1, locals=1, args_size=1
         0: aload_0
         1: invokevirtual #332                // Method tail:()Lscala/collection/immutable/Vector;
         4: areturn
      LineNumberTable:
        line 527: 0
      LocalVariableTable:
        Start  Length  Slot  Name   Signature
            0       5     0  this   Lscala/collection/immutable/Vector3;

  public java.lang.Object map(scala.Function1);
    descriptor: (Lscala/Function1;)Ljava/lang/Object;
    flags: (0x1041) ACC_PUBLIC, ACC_BRIDGE, ACC_SYNTHETIC
    Code:
      stack=2, locals=2, args_size=2
         0: aload_0
         1: aload_1
         2: invokevirtual #335                // Method map:(Lscala/Function1;)Lscala/collection/immutable/Vector;
         5: areturn
      LineNumberTable:
        line 527: 0
      LocalVariableTable:
        Start  Length  Slot  Name   Signature
            0       6     0  this   Lscala/collection/immutable/Vector3;
            0       6     1     f   Lscala/Function1;
    MethodParameters:
      Name                           Flags
      f                              final

  public java.lang.Object prepended(java.lang.Object);
    descriptor: (Ljava/lang/Object;)Ljava/lang/Object;
    flags: (0x1041) ACC_PUBLIC, ACC_BRIDGE, ACC_SYNTHETIC
    Code:
      stack=2, locals=2, args_size=2
         0: aload_0
         1: aload_1
         2: invokevirtual #337                // Method prepended:(Ljava/lang/Object;)Lscala/collection/immutable/Vector;
         5: areturn
      LineNumberTable:
        line 527: 0
      LocalVariableTable:
        Start  Length  Slot  Name   Signature
            0       6     0  this   Lscala/collection/immutable/Vector3;
            0       6     1  elem   Ljava/lang/Object;
    MethodParameters:
      Name                           Flags
      elem                           final

  public java.lang.Object appended(java.lang.Object);
    descriptor: (Ljava/lang/Object;)Ljava/lang/Object;
    flags: (0x1041) ACC_PUBLIC, ACC_BRIDGE, ACC_SYNTHETIC
    Code:
      stack=2, locals=2, args_size=2
         0: aload_0
         1: aload_1
         2: invokevirtual #339                // Method appended:(Ljava/lang/Object;)Lscala/collection/immutable/Vector;
         5: areturn
      LineNumberTable:
        line 527: 0
      LocalVariableTable:
        Start  Length  Slot  Name   Signature
            0       6     0  this   Lscala/collection/immutable/Vector3;
            0       6     1  elem   Ljava/lang/Object;
    MethodParameters:
      Name                           Flags
      elem                           final

  public java.lang.Object updated(int, java.lang.Object);
    descriptor: (ILjava/lang/Object;)Ljava/lang/Object;
    flags: (0x1041) ACC_PUBLIC, ACC_BRIDGE, ACC_SYNTHETIC
    Code:
      stack=3, locals=3, args_size=3
         0: aload_0
         1: iload_1
         2: aload_2
         3: invokevirtual #342                // Method updated:(ILjava/lang/Object;)Lscala/collection/immutable/Vector;
         6: areturn
      LineNumberTable:
        line 527: 0
      LocalVariableTable:
        Start  Length  Slot  Name   Signature
            0       7     0  this   Lscala/collection/immutable/Vector3;
            0       7     1 index   I
            0       7     2  elem   Ljava/lang/Object;
    MethodParameters:
      Name                           Flags
      index                          final
      elem                           final

  public java.lang.Object apply(java.lang.Object);
    descriptor: (Ljava/lang/Object;)Ljava/lang/Object;
    flags: (0x1041) ACC_PUBLIC, ACC_BRIDGE, ACC_SYNTHETIC
    Code:
      stack=2, locals=2, args_size=2
         0: aload_0
         1: aload_1
         2: invokestatic  #349                // Method scala/runtime/BoxesRunTime.unboxToInt:(Ljava/lang/Object;)I
         5: invokevirtual #351                // Method apply:(I)Ljava/lang/Object;
         8: areturn
      LineNumberTable:
        line 527: 0
      LocalVariableTable:
        Start  Length  Slot  Name   Signature
            0       9     0  this   Lscala/collection/immutable/Vector3;
            0       9     1    v1   Ljava/lang/Object;
    MethodParameters:
      Name                           Flags
      v1                             final

  public scala.collection.immutable.Vector3(java.lang.Object[], int, java.lang.Object[][], int, java.lang.Object[][][], java.lang.Object[][], java.lang.Object[], int);
    descriptor: ([Ljava/lang/Object;I[[Ljava/lang/Object;I[[[Ljava/lang/Object;[[Ljava/lang/Object;[Ljava/lang/Object;I)V
    flags: (0x0001) ACC_PUBLIC
    Code:
      stack=4, locals=9, args_size=9
         0: aload_0
         1: iload_2
         2: putfield      #20                 // Field len1:I
         5: aload_0
         6: aload_3
         7: putfield      #25                 // Field prefix2:[[Ljava/lang/Object;
        10: aload_0
        11: iload         4
        13: putfield      #27                 // Field len12:I
        16: aload_0
        17: aload         5
        19: putfield      #30                 // Field data3:[[[Ljava/lang/Object;
        22: aload_0
        23: aload         6
        25: putfield      #32                 // Field suffix2:[[Ljava/lang/Object;
        28: aload_0
        29: aload_1
        30: aload         7
        32: iload         8
        34: invokespecial #357                // Method scala/collection/immutable/BigVector."<init>":([Ljava/lang/Object;[Ljava/lang/Object;I)V
        37: return
      LineNumberTable:
        line 527: 0
        line 528: 5
        line 529: 16
        line 530: 22
        line 531: 28
        line 527: 37
      LocalVariableTable:
        Start  Length  Slot  Name   Signature
            0      38     0  this   Lscala/collection/immutable/Vector3;
            0      38     1 _prefix1   [Ljava/lang/Object;
            0      38     2  len1   I
            0      38     3 prefix2   [[Ljava/lang/Object;
            0      38     4 len12   I
            0      38     5 data3   [[[Ljava/lang/Object;
            0      38     6 suffix2   [[Ljava/lang/Object;
            0      38     7 _suffix1   [Ljava/lang/Object;
            0      38     8 _length0   I
    MethodParameters:
      Name                           Flags
      _prefix1                       final
      len1                           final
      prefix2                        final
      len12                          final
      data3                          final
      suffix2                        final
      _suffix1                       final
      _length0                       final
}
Signature: #3                           // <A:Ljava/lang/Object;>Lscala/collection/immutable/BigVector<TA;>;
SourceFile: "Vector.scala"
RuntimeVisibleAnnotations:
  0: #7(#8=s#9)
    scala.reflect.ScalaSignature(
      bytes="\u0006\u0005\t\ra\u0001B\u0013\'\r5B\u0011b\u0010\u0001\u0003\u0002\u0003\u0006I\u0001\u0011)\t\u0013Q\u0003!Q1A\u0005\u0002\u0019*\u0006\u0002C-\u0001\u0005\u0003\u0005\u000b\u0011\u0002,\t\u0013i\u0003!Q1A\u0005\u0002\u0019Z\u0006\u0002C0\u0001\u0005\u0003\u0005\u000b\u0011\u0002/\t\u0013\u0001\u0004!Q1A\u0005\u0002\u0019*\u0006\u0002C1\u0001\u0005\u0003\u0005\u000b\u0011\u0002,\t\u0013\t\u0004!Q1A\u0005\u0002\u0019\u001a\u0007\u0002C4\u0001\u0005\u0003\u0005\u000b\u0011\u00023\t\u0013!\u0004!Q1A\u0005\u0002\u0019Z\u0006\u0002C5\u0001\u0005\u0003\u0005\u000b\u0011\u0002/\t\u0013)\u0004!\u0011!Q\u0001\n\u0001[\u0007\"C7\u0001\u0005\u0003\u0005\u000b\u0011\u0002,o\u0011\u0015\u0001\b\u0001\"\u0001r\u0011\u0019Y\b\u0001)C\u0005y\"I\u0011Q\u0003\u0001\u0012\u0002\u0013%\u0011q\u0003\u0005\n\u0003[\u0001\u0011\u0013!C\u0005\u0003_A\u0011\"a\r\u0001#\u0003%I!!\u000e\t\u0013\u0005e\u0002!%A\u0005\n\u0005=\u0002\"CA\u001e\u0001E\u0005I\u0011BA\u001f\u0011%\t\t\u0005AI\u0001\n\u0013\t)\u0004C\u0005\u0002D\u0001\t\n\u0011\"\u0003\u0002\u0018!I\u0011Q\t\u0001\u0012\u0002\u0013%\u0011q\u0006\u0005\b\u0003\u000f\u0002A\u0011AA%\u0011\u001d\t\t\u0006\u0001C!\u0003\'Bq!a\u001a\u0001\t\u0003\nI\u0007C\u0004\u0002v\u0001!\t%a\u001e\t\u000f\u0005\r\u0005\u0001\"\u0011\u0002\u0006\"A\u0011\u0011\u0014\u0001!\n#\tY\nC\u0004\u0002(\u0002!\t%!+\t\u000f\u0005-\u0006\u0001\"\u0011\u0002*\"9\u0011Q\u0016\u0001\u0005\u0012\u0019*\u0006\u0002CAX\u0001\u0011Ea%!-\t\u0011\u00055\u0007\u0001\"\u0005\'\u0003\u001fD\u0001\"a5\u0001A\u0013E\u0013Q\u001b\u0005\t\u0003_\u0004\u0001\u0015\"\u0015\u0002r\n9a+Z2u_J\u001c$BA\u0014)\u0003%IW.\\;uC\ndWM\u0003\u0002*U\u0005Q1m\u001c7mK\u000e$\u0018n\u001c8\u000b\u0003-\nQa]2bY\u0006\u001c\u0001!\u0006\u0002/kM\u0011\u0001a\f\t\u0004aE\u001aT\"\u0001\u0014\n\u0005I2#!\u0003\"jOZ+7\r^8s!\t!T\u0007\u0004\u0001\u0005\rY\u0002AQ1\u00018\u0005\u0005\t\u0015C\u0001\u001d=!\tI$(D\u0001+\u0013\tY$FA\u0004O_RD\u0017N\\4\u0011\u0005ej\u0014B\u0001 +\u0005\r\te._\u0001\t?B\u0014XMZ5ycA\u0011\u0011)\u0014\b\u0003\u0005.s!a\u0011&\u000f\u0005\u0011KeBA#I\u001b\u00051%BA$-\u0003\u0019a$o\\8u}%\t1&\u0003\u0002*U%\u0011q\u0005K\u0005\u0003\u0019\u001a\nABV3di>\u0014\u0018J\u001c7j]\u0016L!AT(\u0003\t\u0005\u0013(/\r\u0006\u0003\u0019\u001aJ!!\u0015*\u0002\u000fA\u0014XMZ5yc%\u00111K\n\u0002\u0007-\u0016\u001cGo\u001c:\u0002\t1,g.M\u000b\u0002-B\u0011\u0011hV\u0005\u00031*\u00121!\u00138u\u0003\u0015aWM\\\u0019!\u0003\u001d\u0001(/\u001a4jqJ*\u0012\u0001\u0018\t\u0003\u0003vK!AX(\u0003\t\u0005\u0013(OM\u0001\taJ,g-\u001b=3A\u0005)A.\u001a82e\u00051A.\u001a82e\u0001\nQ\u0001Z1uCN*\u0012\u0001\u001a\t\u0003\u0003\u0016L!AZ(\u0003\t\u0005\u0013(oM\u0001\u0007I\u0006$\u0018m\r\u0011\u0002\u000fM,hMZ5ye\u0005A1/\u001e4gSb\u0014\u0004%\u0001\u0005`gV4g-\u001b=2\u0013\ta\u0017\'A\u0004tk\u001a4\u0017\u000e_\u0019\u0002\u0011}cWM\\4uQBJ!a\\\u0019\u0002\u000f1,gn\u001a;ia\u00051A(\u001b8jiz\"\u0012B]:ukZ<\b0\u001f>\u0011\u0007A\u00021\u0007C\u0003@\u001d\u0001\u0007\u0001\tC\u0003U\u001d\u0001\u0007a\u000bC\u0003[\u001d\u0001\u0007A\fC\u0003a\u001d\u0001\u0007a\u000bC\u0003c\u001d\u0001\u0007A\rC\u0003i\u001d\u0001\u0007A\fC\u0003k\u001d\u0001\u0007\u0001\tC\u0003n\u001d\u0001\u0007a+\u0001\u0003d_BLHcD?\u007f\u007f\u0006\u0005\u00111AA\u0003\u0003\u000f\tI!a\u0003\u0011\u0007A\u0002\u0001\bC\u0004R\u001fA\u0005\t\u0019\u0001!\t\u000fQ{\u0001\u0013!a\u0001-\"9!l\u0004I\u0001\u0002\u0004a\u0006b\u00021\u0010!\u0003\u0005\rA\u0016\u0005\bE>\u0001\n\u00111\u0001e\u0011\u001dAw\u0002%AA\u0002qCq\u0001\\\b\u0011\u0002\u0003\u0007\u0001\tC\u0004p\u001fA\u0005\t\u0019\u0001,)\u0007=\ty\u0001E\u0002:\u0003#I1!a\u0005+\u0005\u0019Ig\u000e\\5oK\u0006q1m\u001c9zI\u0011,g-Y;mi\u0012\nTCAA\rU\r\u0001\u00151D\u0016\u0003\u0003;\u0001B!a\b\u0002*5\u0011\u0011\u0011\u0005\u0006\u0005\u0003G\t)#A\u0005v]\u000eDWmY6fI*\u0019\u0011q\u0005\u0016\u0002\u0015\u0005tgn\u001c;bi&|g.\u0003\u0003\u0002,\u0005\u0005\"!E;oG\",7m[3e-\u0006\u0014\u0018.\u00198dK\u0006q1m\u001c9zI\u0011,g-Y;mi\u0012\u0012TCAA\u0019U\r1\u00161D\u0001\u000fG>\u0004\u0018\u0010\n3fM\u0006,H\u000e\u001e\u00134+\t\t9DK\u0002]\u00037\tabY8qs\u0012\"WMZ1vYR$C\'\u0001\bd_BLH\u0005Z3gCVdG\u000fJ\u001b\u0016\u0005\u0005}\"f\u00013\u0002\u001c\u0005q1m\u001c9zI\u0011,g-Y;mi\u00122\u0014AD2paf$C-\u001a4bk2$HeN\u0001\u000fG>\u0004\u0018\u0010\n3fM\u0006,H\u000e\u001e\u00139\u0003\u0015\t\u0007\u000f\u001d7z)\r\u0019\u00141\n\u0005\u0007\u0003\u001bB\u0002\u0019\u0001,\u0002\u000b%tG-\u001a=)\u0007a\ty!A\u0004va\u0012\fG/\u001a3\u0016\t\u0005U\u00131\f\u000b\u0007\u0003/\n\t\'a\u0019\u0011\tA\u0012\u0016\u0011\f\t\u0004i\u0005mCaBA/3\t\u0007\u0011q\f\u0002\u0002\u0005F\u00111\u0007\u0010\u0005\u0007\u0003\u001bJ\u0002\u0019\u0001,\t\u000f\u0005\u0015\u0014\u00041\u0001\u0002Z\u0005!Q\r\\3n\u0003!\t\u0007\u000f]3oI\u0016$W\u0003BA6\u0003c\"B!!\u001c\u0002tA!\u0001GUA8!\r!\u0014\u0011\u000f\u0003\b\u0003;R\"\u0019AA0\u0011\u001d\t)G\u0007a\u0001\u0003_\n\u0011\u0002\u001d:fa\u0016tG-\u001a3\u0016\t\u0005e\u0014q\u0010\u000b\u0005\u0003w\n\t\t\u0005\u00031%\u0006u\u0004c\u0001\u001b\u0002\u0000\u00119\u0011QL\u000eC\u0002\u0005}\u0003bBA37\u0001\u0007\u0011QP\u0001\u0004[\u0006\u0004X\u0003BAD\u0003\u001b#B!!#\u0002\u0010B!\u0001GUAF!\r!\u0014Q\u0012\u0003\u0007\u0003;b\"\u0019A\u001c\t\u000f\u0005EE\u00041\u0001\u0002\u0014\u0006\ta\r\u0005\u0004:\u0003+\u001b\u00141R\u0005\u0004\u0003/S#!\u0003$v]\u000e$\u0018n\u001c82\u0003\u0019\u0019H.[2faQ1\u0011QTAP\u0003G\u00032\u0001\r*4\u0011\u0019\t\t+\ba\u0001-\u0006\u0011An\u001c\u0005\u0007\u0003Kk\u0002\u0019\u0001,\u0002\u0005!L\u0017\u0001\u0002;bS2,\"!!(\u0002\t%t\u0017\u000e^\u0001\u0011m\u0016\u001cGo\u001c:TY&\u001cWmQ8v]R\f1B^3di>\u00148\u000b\\5dKR!\u00111WAea\u0011\t),!0\u0011\u000be\n9,a/\n\u0007\u0005e&FA\u0003BeJ\f\u0017\u0010E\u00025\u0003{#1\"a0\"\u0003\u0003\u0005\tQ!\u0001\u0002B\n!q\fJ\u00195#\rA\u00141\u0019\t\u0004s\u0005\u0015\u0017bAAdU\t1\u0011I\\=SK\u001aDa!a3\"\u0001\u00041\u0016aA5eq\u00069b/Z2u_J\u001cF.[2f!J,g-\u001b=MK:<G\u000f\u001b\u000b\u0004-\u0006E\u0007BBAfE\u0001\u0007a+A\u0007qe\u0016\u0004XM\u001c3fI\u0006cG\u000eM\u000b\u0005\u0003/\fi\u000e\u0006\u0004\u0002Z\u0006}\u00171\u001e\t\u0005aI\u000bY\u000eE\u00025\u0003;$q!!\u0018$\u0005\u0004\ty\u0006C\u0004\u0002b\u000e\u0002\r!a9\u0002\rA\u0014XMZ5y!\u0019\t)/a:\u0002\\6\t\u0001&C\u0002\u0002j\"\u0012A\"\u0013;fe\u0006\u0014G.Z(oG\u0016Da!!<$\u0001\u00041\u0016!A6\u0002\u0019\u0005\u0004\b/\u001a8eK\u0012\fE\u000e\u001c\u0019\u0016\t\u0005M\u0018\u0011 \u000b\u0007\u0003k\fYP!\u0001\u0011\tA\u0012\u0016q\u001f\t\u0004i\u0005eHaBA/I\t\u0007\u0011q\f\u0005\b\u0003{$\u0003\u0019AA\u0000\u0003\u0019\u0019XO\u001a4jqB1\u0011Q]At\u0003oDa!!<%\u0001\u00041\u0006"
    )
  ScalaInlineInfo: length = 0xB3 (unknown attribute)
   01 01 00 23 00 27 00 28 01 00 8B 00 C2 01 00 8B
   00 8C 01 01 41 01 33 01 00 45 00 46 05 00 45 00
   C2 05 00 21 00 22 05 00 2C 00 2D 01 00 30 00 12
   01 00 33 00 17 01 00 36 00 12 01 00 39 00 1C 01
   00 3C 00 17 01 00 3F 00 2D 01 00 42 00 12 01 00
   0F 00 1C 01 01 1F 00 5D 01 01 1F 01 0F 01 00 0A
   00 12 01 00 0E 00 12 01 00 BC 01 4D 01 00 BC 00
   BD 01 00 0C 00 17 01 00 B0 00 C2 01 00 B0 00 8C
   01 01 32 01 33 01 01 00 01 01 01 00 11 00 17 01
   01 14 00 5D 01 01 14 01 0F 01 00 51 01 54 01 00
   51 00 52 01 01 22 01 23 01 01 21 00 12 01 01 30
   01 31 01
  ScalaSig: length = 0x3 (unknown attribute)
   05 02 00
