Classfile /Users/mw/Projects/slang-braindump/.jar/jar8/assemble/slang-braindump/assemble/content/scala/collection/immutable/VectorStatics$.class
  Last modified May 29, 2022; size 10219 bytes
  SHA-256 checksum a8e6dfe7ba3bd9b8d4429142054a9c44620c6082e557092ed11a6ab82b9b3600
  Compiled from "Vector.scala"
public final class scala.collection.immutable.VectorStatics$
  minor version: 0
  major version: 52
  flags: (0x0031) ACC_PUBLIC, ACC_FINAL, ACC_SUPER
  this_class: #2                          // scala/collection/immutable/VectorStatics$
  super_class: #4                         // java/lang/Object
  interfaces: 0, fields: 7, methods: 19, attributes: 3
Constant pool:
    #1 = Utf8               scala/collection/immutable/VectorStatics$
    #2 = Class              #1            // scala/collection/immutable/VectorStatics$
    #3 = Utf8               java/lang/Object
    #4 = Class              #3            // java/lang/Object
    #5 = Utf8               Vector.scala
    #6 = Utf8               MODULE$
    #7 = Utf8               Lscala/collection/immutable/VectorStatics$;
    #8 = Utf8               empty1
    #9 = Utf8               [Ljava/lang/Object;
   #10 = Utf8               empty2
   #11 = Utf8               [[Ljava/lang/Object;
   #12 = Utf8               empty3
   #13 = Utf8               [[[Ljava/lang/Object;
   #14 = Utf8               empty4
   #15 = Utf8               [[[[Ljava/lang/Object;
   #16 = Utf8               empty5
   #17 = Utf8               [[[[[Ljava/lang/Object;
   #18 = Utf8               empty6
   #19 = Utf8               [[[[[[Ljava/lang/Object;
   #20 = Utf8               <clinit>
   #21 = Utf8               ()V
   #22 = Utf8               <init>
   #23 = NameAndType        #22:#21       // "<init>":()V
   #24 = Methodref          #2.#23        // scala/collection/immutable/VectorStatics$."<init>":()V
   #25 = NameAndType        #6:#7         // MODULE$:Lscala/collection/immutable/VectorStatics$;
   #26 = Fieldref           #2.#25        // scala/collection/immutable/VectorStatics$.MODULE$:Lscala/collection/immutable/VectorStatics$;
   #27 = NameAndType        #8:#9         // empty1:[Ljava/lang/Object;
   #28 = Fieldref           #2.#27        // scala/collection/immutable/VectorStatics$.empty1:[Ljava/lang/Object;
   #29 = Class              #9            // "[Ljava/lang/Object;"
   #30 = NameAndType        #10:#11       // empty2:[[Ljava/lang/Object;
   #31 = Fieldref           #2.#30        // scala/collection/immutable/VectorStatics$.empty2:[[Ljava/lang/Object;
   #32 = Class              #11           // "[[Ljava/lang/Object;"
   #33 = NameAndType        #12:#13       // empty3:[[[Ljava/lang/Object;
   #34 = Fieldref           #2.#33        // scala/collection/immutable/VectorStatics$.empty3:[[[Ljava/lang/Object;
   #35 = Class              #13           // "[[[Ljava/lang/Object;"
   #36 = NameAndType        #14:#15       // empty4:[[[[Ljava/lang/Object;
   #37 = Fieldref           #2.#36        // scala/collection/immutable/VectorStatics$.empty4:[[[[Ljava/lang/Object;
   #38 = Class              #15           // "[[[[Ljava/lang/Object;"
   #39 = NameAndType        #16:#17       // empty5:[[[[[Ljava/lang/Object;
   #40 = Fieldref           #2.#39        // scala/collection/immutable/VectorStatics$.empty5:[[[[[Ljava/lang/Object;
   #41 = Class              #17           // "[[[[[Ljava/lang/Object;"
   #42 = NameAndType        #18:#19       // empty6:[[[[[[Ljava/lang/Object;
   #43 = Fieldref           #2.#42        // scala/collection/immutable/VectorStatics$.empty6:[[[[[[Ljava/lang/Object;
   #44 = Utf8               copyAppend1
   #45 = Utf8               ([Ljava/lang/Object;Ljava/lang/Object;)[Ljava/lang/Object;
   #46 = Utf8               a
   #47 = Utf8               elem
   #48 = Utf8               java/lang/System
   #49 = Class              #48           // java/lang/System
   #50 = Utf8               arraycopy
   #51 = Utf8               (Ljava/lang/Object;ILjava/lang/Object;II)V
   #52 = NameAndType        #50:#51       // arraycopy:(Ljava/lang/Object;ILjava/lang/Object;II)V
   #53 = Methodref          #49.#52       // java/lang/System.arraycopy:(Ljava/lang/Object;ILjava/lang/Object;II)V
   #54 = Utf8               alen
   #55 = Utf8               I
   #56 = Utf8               ac
   #57 = Utf8               this
   #58 = Utf8               Ljava/lang/Object;
   #59 = Utf8               copyAppend
   #60 = Utf8               <T:Ljava/lang/Object;>([TT;TT;)[TT;
   #61 = Utf8               java/util/Arrays
   #62 = Class              #61           // java/util/Arrays
   #63 = Utf8               copyOf
   #64 = Utf8               ([Ljava/lang/Object;I)[Ljava/lang/Object;
   #65 = NameAndType        #63:#64       // copyOf:([Ljava/lang/Object;I)[Ljava/lang/Object;
   #66 = Methodref          #62.#65       // java/util/Arrays.copyOf:([Ljava/lang/Object;I)[Ljava/lang/Object;
   #67 = Utf8               copyPrepend1
   #68 = Utf8               (Ljava/lang/Object;[Ljava/lang/Object;)[Ljava/lang/Object;
   #69 = Utf8               copyPrepend
   #70 = Utf8               <T:Ljava/lang/Object;>(TT;[TT;)[TT;
   #71 = Utf8               getClass
   #72 = Utf8               ()Ljava/lang/Class;
   #73 = NameAndType        #71:#72       // getClass:()Ljava/lang/Class;
   #74 = Methodref          #4.#73        // java/lang/Object.getClass:()Ljava/lang/Class;
   #75 = Utf8               java/lang/Class
   #76 = Class              #75           // java/lang/Class
   #77 = Utf8               getComponentType
   #78 = NameAndType        #77:#72       // getComponentType:()Ljava/lang/Class;
   #79 = Methodref          #76.#78       // java/lang/Class.getComponentType:()Ljava/lang/Class;
   #80 = Utf8               java/lang/reflect/Array
   #81 = Class              #80           // java/lang/reflect/Array
   #82 = Utf8               newInstance
   #83 = Utf8               (Ljava/lang/Class;I)Ljava/lang/Object;
   #84 = NameAndType        #82:#83       // newInstance:(Ljava/lang/Class;I)Ljava/lang/Object;
   #85 = Methodref          #81.#84       // java/lang/reflect/Array.newInstance:(Ljava/lang/Class;I)Ljava/lang/Object;
   #86 = Utf8               ()[Ljava/lang/Object;
   #87 = Utf8               ()[[Ljava/lang/Object;
   #88 = Utf8               ()[[[Ljava/lang/Object;
   #89 = Utf8               ()[[[[Ljava/lang/Object;
   #90 = Utf8               ()[[[[[Ljava/lang/Object;
   #91 = Utf8               ()[[[[[[Ljava/lang/Object;
   #92 = Utf8               foreachRec
   #93 = Utf8               (I[Ljava/lang/Object;Lscala/Function1;)V
   #94 = Utf8               <T:Ljava/lang/Object;A:Ljava/lang/Object;U:Ljava/lang/Object;>(I[TT;Lscala/Function1<TA;TU;>;)V
   #95 = Utf8               level
   #96 = Utf8               f
   #97 = Utf8               scala/Function1
   #98 = Class              #97           // scala/Function1
   #99 = Utf8               apply
  #100 = Utf8               (Ljava/lang/Object;)Ljava/lang/Object;
  #101 = NameAndType        #99:#100      // apply:(Ljava/lang/Object;)Ljava/lang/Object;
  #102 = InterfaceMethodref #98.#101      // scala/Function1.apply:(Ljava/lang/Object;)Ljava/lang/Object;
  #103 = NameAndType        #92:#93       // foreachRec:(I[Ljava/lang/Object;Lscala/Function1;)V
  #104 = Methodref          #2.#103       // scala/collection/immutable/VectorStatics$.foreachRec:(I[Ljava/lang/Object;Lscala/Function1;)V
  #105 = Utf8               l
  #106 = Utf8               i
  #107 = Utf8               len
  #108 = Utf8               Lscala/Function1;
  #109 = Utf8               mapElems1
  #110 = Utf8               ([Ljava/lang/Object;Lscala/Function1;)[Ljava/lang/Object;
  #111 = Utf8               <A:Ljava/lang/Object;B:Ljava/lang/Object;>([Ljava/lang/Object;Lscala/Function1<TA;TB;>;)[Ljava/lang/Object;
  #112 = Utf8               v1
  #113 = Utf8               v2
  #114 = Utf8               mapElems1Rest_ac
  #115 = Utf8               mapElems1Rest_i
  #116 = Utf8               mapElems1Rest
  #117 = Utf8               ([Ljava/lang/Object;Lscala/Function1;ILjava/lang/Object;)[Ljava/lang/Object;
  #118 = Utf8               <A:Ljava/lang/Object;B:Ljava/lang/Object;>([Ljava/lang/Object;Lscala/Function1<TA;TB;>;ILjava/lang/Object;)[Ljava/lang/Object;
  #119 = Utf8               at
  #120 = Utf8               mapElems
  #121 = Utf8               (I[Ljava/lang/Object;Lscala/Function1;)[Ljava/lang/Object;
  #122 = Utf8               <A:Ljava/lang/Object;B:Ljava/lang/Object;T:Ljava/lang/Object;>(I[TT;Lscala/Function1<TA;TB;>;)[TT;
  #123 = Utf8               n
  #124 = NameAndType        #120:#121     // mapElems:(I[Ljava/lang/Object;Lscala/Function1;)[Ljava/lang/Object;
  #125 = Methodref          #2.#124       // scala/collection/immutable/VectorStatics$.mapElems:(I[Ljava/lang/Object;Lscala/Function1;)[Ljava/lang/Object;
  #126 = Utf8               mapElemsRest
  #127 = Utf8               (I[Ljava/lang/Object;Lscala/Function1;ILjava/lang/Object;)[Ljava/lang/Object;
  #128 = NameAndType        #126:#127     // mapElemsRest:(I[Ljava/lang/Object;Lscala/Function1;ILjava/lang/Object;)[Ljava/lang/Object;
  #129 = Methodref          #2.#128       // scala/collection/immutable/VectorStatics$.mapElemsRest:(I[Ljava/lang/Object;Lscala/Function1;ILjava/lang/Object;)[Ljava/lang/Object;
  #130 = Utf8               mapElems1_v1
  #131 = Utf8               mapElems1_v2
  #132 = Utf8               mapElems1_i
  #133 = Utf8               mapElems1_mapElems1Rest_ac
  #134 = Utf8               mapElems1_mapElems1Rest_i
  #135 = Utf8               mapElemsRest_ac
  #136 = Utf8               mapElemsRest_i
  #137 = Utf8               mapElemsRest_mapElems_v1
  #138 = Utf8               mapElemsRest_mapElems_v2
  #139 = Utf8               mapElemsRest_mapElems_i
  #140 = Utf8               mapElemsRest_mapElems_n
  #141 = Utf8               mapElemsRest_mapElems_a
  #142 = Utf8               mapElemsRest_mapElems_mapElems1_v1
  #143 = Utf8               mapElemsRest_mapElems_mapElems1_v2
  #144 = Utf8               mapElemsRest_mapElems_mapElems1_i
  #145 = Utf8               mapElemsRest_mapElems_mapElems1_mapElems1Rest_ac
  #146 = Utf8               mapElemsRest_mapElems_mapElems1_mapElems1Rest_i
  #147 = Utf8               <A:Ljava/lang/Object;B:Ljava/lang/Object;T:Ljava/lang/Object;>(I[TT;Lscala/Function1<TA;TB;>;ILjava/lang/Object;)[TT;
  #148 = Utf8               mapElems_v1
  #149 = Utf8               mapElems_v2
  #150 = Utf8               mapElems_i
  #151 = Utf8               mapElems_n
  #152 = Utf8               mapElems_a
  #153 = Utf8               mapElems_mapElems1_v1
  #154 = Utf8               mapElems_mapElems1_v2
  #155 = Utf8               mapElems_mapElems1_i
  #156 = Utf8               mapElems_mapElems1_mapElems1Rest_ac
  #157 = Utf8               mapElems_mapElems1_mapElems1Rest_i
  #158 = Utf8               prepend1IfSpace
  #159 = Utf8               ([Ljava/lang/Object;Lscala/collection/IterableOnce;)[Ljava/lang/Object;
  #160 = Utf8               ([Ljava/lang/Object;Lscala/collection/IterableOnce<*>;)[Ljava/lang/Object;
  #161 = Utf8               prefix1
  #162 = Utf8               xs
  #163 = Utf8               scala/collection/immutable/Iterable
  #164 = Class              #163          // scala/collection/immutable/Iterable
  #165 = Utf8               sizeCompare
  #166 = Utf8               (I)I
  #167 = NameAndType        #165:#166     // sizeCompare:(I)I
  #168 = InterfaceMethodref #164.#167     // scala/collection/immutable/Iterable.sizeCompare:(I)I
  #169 = Utf8               size
  #170 = Utf8               ()I
  #171 = NameAndType        #169:#170     // size:()I
  #172 = InterfaceMethodref #164.#171     // scala/collection/immutable/Iterable.size:()I
  #173 = Utf8               head
  #174 = Utf8               ()Ljava/lang/Object;
  #175 = NameAndType        #173:#174     // head:()Ljava/lang/Object;
  #176 = InterfaceMethodref #164.#175     // scala/collection/immutable/Iterable.head:()Ljava/lang/Object;
  #177 = NameAndType        #69:#68       // copyPrepend:(Ljava/lang/Object;[Ljava/lang/Object;)[Ljava/lang/Object;
  #178 = Methodref          #2.#177       // scala/collection/immutable/VectorStatics$.copyPrepend:(Ljava/lang/Object;[Ljava/lang/Object;)[Ljava/lang/Object;
  #179 = Utf8               copyToArray
  #180 = Utf8               (Ljava/lang/Object;I)I
  #181 = NameAndType        #179:#180     // copyToArray:(Ljava/lang/Object;I)I
  #182 = InterfaceMethodref #164.#181     // scala/collection/immutable/Iterable.copyToArray:(Ljava/lang/Object;I)I
  #183 = Utf8               scala/collection/IterableOnce
  #184 = Class              #183          // scala/collection/IterableOnce
  #185 = Utf8               knownSize
  #186 = NameAndType        #185:#170     // knownSize:()I
  #187 = InterfaceMethodref #184.#186     // scala/collection/IterableOnce.knownSize:()I
  #188 = Utf8               iterator
  #189 = Utf8               ()Lscala/collection/Iterator;
  #190 = NameAndType        #188:#189     // iterator:()Lscala/collection/Iterator;
  #191 = InterfaceMethodref #184.#190     // scala/collection/IterableOnce.iterator:()Lscala/collection/Iterator;
  #192 = Utf8               scala/collection/Iterator
  #193 = Class              #192          // scala/collection/Iterator
  #194 = InterfaceMethodref #193.#181     // scala/collection/Iterator.copyToArray:(Ljava/lang/Object;I)I
  #195 = Utf8               prefix1b
  #196 = Utf8               s
  #197 = Utf8               Lscala/collection/IterableOnce;
  #198 = Utf8               append1IfSpace
  #199 = Utf8               suffix1
  #200 = NameAndType        #59:#45       // copyAppend:([Ljava/lang/Object;Ljava/lang/Object;)[Ljava/lang/Object;
  #201 = Methodref          #2.#200       // scala/collection/immutable/VectorStatics$.copyAppend:([Ljava/lang/Object;Ljava/lang/Object;)[Ljava/lang/Object;
  #202 = Utf8               suffix1b
  #203 = Methodref          #4.#23        // java/lang/Object."<init>":()V
  #204 = Utf8               Code
  #205 = Utf8               LineNumberTable
  #206 = Utf8               LocalVariableTable
  #207 = Utf8               MethodParameters
  #208 = Utf8               Signature
  #209 = Utf8               StackMapTable
  #210 = Utf8               SourceFile
  #211 = Utf8               ScalaInlineInfo
  #212 = Utf8               Scala
{
  public static final scala.collection.immutable.VectorStatics$ MODULE$;
    descriptor: Lscala/collection/immutable/VectorStatics$;
    flags: (0x0019) ACC_PUBLIC, ACC_STATIC, ACC_FINAL

  private static final java.lang.Object[] empty1;
    descriptor: [Ljava/lang/Object;
    flags: (0x001a) ACC_PRIVATE, ACC_STATIC, ACC_FINAL

  private static final java.lang.Object[][] empty2;
    descriptor: [[Ljava/lang/Object;
    flags: (0x001a) ACC_PRIVATE, ACC_STATIC, ACC_FINAL

  private static final java.lang.Object[][][] empty3;
    descriptor: [[[Ljava/lang/Object;
    flags: (0x001a) ACC_PRIVATE, ACC_STATIC, ACC_FINAL

  private static final java.lang.Object[][][][] empty4;
    descriptor: [[[[Ljava/lang/Object;
    flags: (0x001a) ACC_PRIVATE, ACC_STATIC, ACC_FINAL

  private static final java.lang.Object[][][][][] empty5;
    descriptor: [[[[[Ljava/lang/Object;
    flags: (0x001a) ACC_PRIVATE, ACC_STATIC, ACC_FINAL

  private static final java.lang.Object[][][][][][] empty6;
    descriptor: [[[[[[Ljava/lang/Object;
    flags: (0x001a) ACC_PRIVATE, ACC_STATIC, ACC_FINAL

  public static {};
    descriptor: ()V
    flags: (0x0009) ACC_PUBLIC, ACC_STATIC
    Code:
      stack=2, locals=0, args_size=0
         0: new           #2                  // class scala/collection/immutable/VectorStatics$
         3: dup
         4: invokespecial #24                 // Method "<init>":()V
         7: putstatic     #26                 // Field MODULE$:Lscala/collection/immutable/VectorStatics$;
        10: iconst_0
        11: anewarray     #4                  // class java/lang/Object
        14: putstatic     #28                 // Field empty1:[Ljava/lang/Object;
        17: iconst_0
        18: anewarray     #29                 // class "[Ljava/lang/Object;"
        21: putstatic     #31                 // Field empty2:[[Ljava/lang/Object;
        24: iconst_0
        25: anewarray     #32                 // class "[[Ljava/lang/Object;"
        28: putstatic     #34                 // Field empty3:[[[Ljava/lang/Object;
        31: iconst_0
        32: anewarray     #35                 // class "[[[Ljava/lang/Object;"
        35: putstatic     #37                 // Field empty4:[[[[Ljava/lang/Object;
        38: iconst_0
        39: anewarray     #38                 // class "[[[[Ljava/lang/Object;"
        42: putstatic     #40                 // Field empty5:[[[[[Ljava/lang/Object;
        45: iconst_0
        46: anewarray     #41                 // class "[[[[[Ljava/lang/Object;"
        49: putstatic     #43                 // Field empty6:[[[[[[Ljava/lang/Object;
        52: return
      LineNumberTable:
        line 1814: 0
        line 1844: 10
        line 1845: 17
        line 1846: 24
        line 1847: 31
        line 1848: 38
        line 1849: 45
        line 1814: 52

  public final java.lang.Object[] copyAppend1(java.lang.Object[], java.lang.Object);
    descriptor: ([Ljava/lang/Object;Ljava/lang/Object;)[Ljava/lang/Object;
    flags: (0x0011) ACC_PUBLIC, ACC_FINAL
    Code:
      stack=5, locals=5, args_size=3
         0: aload_1
         1: arraylength
         2: istore_3
         3: iload_3
         4: iconst_1
         5: iadd
         6: anewarray     #4                  // class java/lang/Object
         9: astore        4
        11: aload_1
        12: iconst_0
        13: aload         4
        15: iconst_0
        16: iload_3
        17: invokestatic  #53                 // Method java/lang/System.arraycopy:(Ljava/lang/Object;ILjava/lang/Object;II)V
        20: aload         4
        22: iload_3
        23: aload_2
        24: aastore
        25: aload         4
        27: areturn
      LineNumberTable:
        line 1817: 0
        line 1818: 3
        line 1819: 11
        line 1820: 20
        line 1821: 25
      LocalVariableTable:
        Start  Length  Slot  Name   Signature
            3      24     3  alen   I
           11      16     4    ac   [Ljava/lang/Object;
            0      28     0  this   Lscala/collection/immutable/VectorStatics$;
            0      28     1     a   [Ljava/lang/Object;
            0      28     2  elem   Ljava/lang/Object;
    MethodParameters:
      Name                           Flags
      a                              final
      elem                           final

  public final <T extends java.lang.Object> T[] copyAppend(T[], T);
    descriptor: ([Ljava/lang/Object;Ljava/lang/Object;)[Ljava/lang/Object;
    flags: (0x0011) ACC_PUBLIC, ACC_FINAL
    Code:
      stack=3, locals=4, args_size=3
         0: aload_1
         1: aload_1
         2: arraylength
         3: iconst_1
         4: iadd
         5: invokestatic  #66                 // Method java/util/Arrays.copyOf:([Ljava/lang/Object;I)[Ljava/lang/Object;
         8: astore_3
         9: aload_3
        10: aload_3
        11: arraylength
        12: iconst_1
        13: isub
        14: aload_2
        15: aastore
        16: aload_3
        17: areturn
      LineNumberTable:
        line 1825: 0
        line 1826: 9
        line 1827: 16
      LocalVariableTable:
        Start  Length  Slot  Name   Signature
            9       8     3    ac   [Ljava/lang/Object;
            0      18     0  this   Lscala/collection/immutable/VectorStatics$;
            0      18     1     a   [Ljava/lang/Object;
            0      18     2  elem   Ljava/lang/Object;
    Signature: #60                          // <T:Ljava/lang/Object;>([TT;TT;)[TT;
    MethodParameters:
      Name                           Flags
      a                              final
      elem                           final

  public final java.lang.Object[] copyPrepend1(java.lang.Object, java.lang.Object[]);
    descriptor: (Ljava/lang/Object;[Ljava/lang/Object;)[Ljava/lang/Object;
    flags: (0x0011) ACC_PUBLIC, ACC_FINAL
    Code:
      stack=5, locals=4, args_size=3
         0: aload_2
         1: arraylength
         2: iconst_1
         3: iadd
         4: anewarray     #4                  // class java/lang/Object
         7: astore_3
         8: aload_2
         9: iconst_0
        10: aload_3
        11: iconst_1
        12: aload_2
        13: arraylength
        14: invokestatic  #53                 // Method java/lang/System.arraycopy:(Ljava/lang/Object;ILjava/lang/Object;II)V
        17: aload_3
        18: iconst_0
        19: aload_1
        20: aastore
        21: aload_3
        22: areturn
      LineNumberTable:
        line 1831: 0
        line 1832: 8
        line 1833: 17
        line 1834: 21
      LocalVariableTable:
        Start  Length  Slot  Name   Signature
            8      14     3    ac   [Ljava/lang/Object;
            0      23     0  this   Lscala/collection/immutable/VectorStatics$;
            0      23     1  elem   Ljava/lang/Object;
            0      23     2     a   [Ljava/lang/Object;
    MethodParameters:
      Name                           Flags
      elem                           final
      a                              final

  public final <T extends java.lang.Object> T[] copyPrepend(T, T[]);
    descriptor: (Ljava/lang/Object;[Ljava/lang/Object;)[Ljava/lang/Object;
    flags: (0x0011) ACC_PUBLIC, ACC_FINAL
    Code:
      stack=5, locals=4, args_size=3
         0: aload_2
         1: invokevirtual #74                 // Method java/lang/Object.getClass:()Ljava/lang/Class;
         4: invokevirtual #79                 // Method java/lang/Class.getComponentType:()Ljava/lang/Class;
         7: aload_2
         8: arraylength
         9: iconst_1
        10: iadd
        11: invokestatic  #85                 // Method java/lang/reflect/Array.newInstance:(Ljava/lang/Class;I)Ljava/lang/Object;
        14: checkcast     #29                 // class "[Ljava/lang/Object;"
        17: astore_3
        18: aload_2
        19: iconst_0
        20: aload_3
        21: iconst_1
        22: aload_2
        23: arraylength
        24: invokestatic  #53                 // Method java/lang/System.arraycopy:(Ljava/lang/Object;ILjava/lang/Object;II)V
        27: aload_3
        28: iconst_0
        29: aload_1
        30: aastore
        31: aload_3
        32: areturn
      LineNumberTable:
        line 1838: 0
        line 1839: 18
        line 1840: 27
        line 1841: 31
      LocalVariableTable:
        Start  Length  Slot  Name   Signature
           18      14     3    ac   [Ljava/lang/Object;
            0      33     0  this   Lscala/collection/immutable/VectorStatics$;
            0      33     1  elem   Ljava/lang/Object;
            0      33     2     a   [Ljava/lang/Object;
    Signature: #70                          // <T:Ljava/lang/Object;>(TT;[TT;)[TT;
    MethodParameters:
      Name                           Flags
      elem                           final
      a                              final

  public final java.lang.Object[] empty1();
    descriptor: ()[Ljava/lang/Object;
    flags: (0x0011) ACC_PUBLIC, ACC_FINAL
    Code:
      stack=1, locals=1, args_size=1
         0: getstatic     #28                 // Field empty1:[Ljava/lang/Object;
         3: areturn
      LineNumberTable:
        line 1844: 0
      LocalVariableTable:
        Start  Length  Slot  Name   Signature
            0       4     0  this   Lscala/collection/immutable/VectorStatics$;

  public final java.lang.Object[][] empty2();
    descriptor: ()[[Ljava/lang/Object;
    flags: (0x0011) ACC_PUBLIC, ACC_FINAL
    Code:
      stack=1, locals=1, args_size=1
         0: getstatic     #31                 // Field empty2:[[Ljava/lang/Object;
         3: areturn
      LineNumberTable:
        line 1845: 0
      LocalVariableTable:
        Start  Length  Slot  Name   Signature
            0       4     0  this   Lscala/collection/immutable/VectorStatics$;

  public final java.lang.Object[][][] empty3();
    descriptor: ()[[[Ljava/lang/Object;
    flags: (0x0011) ACC_PUBLIC, ACC_FINAL
    Code:
      stack=1, locals=1, args_size=1
         0: getstatic     #34                 // Field empty3:[[[Ljava/lang/Object;
         3: areturn
      LineNumberTable:
        line 1846: 0
      LocalVariableTable:
        Start  Length  Slot  Name   Signature
            0       4     0  this   Lscala/collection/immutable/VectorStatics$;

  public final java.lang.Object[][][][] empty4();
    descriptor: ()[[[[Ljava/lang/Object;
    flags: (0x0011) ACC_PUBLIC, ACC_FINAL
    Code:
      stack=1, locals=1, args_size=1
         0: getstatic     #37                 // Field empty4:[[[[Ljava/lang/Object;
         3: areturn
      LineNumberTable:
        line 1847: 0
      LocalVariableTable:
        Start  Length  Slot  Name   Signature
            0       4     0  this   Lscala/collection/immutable/VectorStatics$;

  public final java.lang.Object[][][][][] empty5();
    descriptor: ()[[[[[Ljava/lang/Object;
    flags: (0x0011) ACC_PUBLIC, ACC_FINAL
    Code:
      stack=1, locals=1, args_size=1
         0: getstatic     #40                 // Field empty5:[[[[[Ljava/lang/Object;
         3: areturn
      LineNumberTable:
        line 1848: 0
      LocalVariableTable:
        Start  Length  Slot  Name   Signature
            0       4     0  this   Lscala/collection/immutable/VectorStatics$;

  public final java.lang.Object[][][][][][] empty6();
    descriptor: ()[[[[[[Ljava/lang/Object;
    flags: (0x0011) ACC_PUBLIC, ACC_FINAL
    Code:
      stack=1, locals=1, args_size=1
         0: getstatic     #43                 // Field empty6:[[[[[[Ljava/lang/Object;
         3: areturn
      LineNumberTable:
        line 1849: 0
      LocalVariableTable:
        Start  Length  Slot  Name   Signature
            0       4     0  this   Lscala/collection/immutable/VectorStatics$;

  public final <T extends java.lang.Object, A extends java.lang.Object, U extends java.lang.Object> void foreachRec(int, T[], scala.Function1<A, U>);
    descriptor: (I[Ljava/lang/Object;Lscala/Function1;)V
    flags: (0x0011) ACC_PUBLIC, ACC_FINAL
    Code:
      stack=4, locals=7, args_size=4
         0: iconst_0
         1: istore        4
         3: aload_2
         4: arraylength
         5: istore        5
         7: iload_1
         8: iconst_0
         9: if_icmpne     36
        12: iload         4
        14: iload         5
        16: if_icmpge     68
        19: aload_3
        20: aload_2
        21: iload         4
        23: aaload
        24: invokeinterface #102,  2          // InterfaceMethod scala/Function1.apply:(Ljava/lang/Object;)Ljava/lang/Object;
        29: pop
        30: iinc          4, 1
        33: goto          12
        36: iload_1
        37: iconst_1
        38: isub
        39: istore        6
        41: iload         4
        43: iload         5
        45: if_icmpge     68
        48: aload_0
        49: iload         6
        51: aload_2
        52: iload         4
        54: aaload
        55: checkcast     #29                 // class "[Ljava/lang/Object;"
        58: aload_3
        59: invokevirtual #104                // Method foreachRec:(I[Ljava/lang/Object;Lscala/Function1;)V
        62: iinc          4, 1
        65: goto          41
        68: return
      StackMapTable: number_of_entries = 4
        frame_type = 253 /* append */
          offset_delta = 12
          locals = [ int, int ]
        frame_type = 23 /* same */
        frame_type = 252 /* append */
          offset_delta = 4
          locals = [ int ]
        frame_type = 250 /* chop */
          offset_delta = 26
      LineNumberTable:
        line 1852: 0
        line 1853: 3
        line 1854: 7
        line 1855: 12
        line 1856: 19
        line 1857: 30
        line 1855: 33
        line 1860: 36
        line 1861: 41
        line 1862: 48
        line 1863: 62
        line 1861: 65
      LocalVariableTable:
        Start  Length  Slot  Name   Signature
           41      27     6     l   I
            3      65     4     i   I
            7      61     5   len   I
            0      69     0  this   Lscala/collection/immutable/VectorStatics$;
            0      69     1 level   I
            0      69     2     a   [Ljava/lang/Object;
            0      69     3     f   Lscala/Function1;
    Signature: #94                          // <T:Ljava/lang/Object;A:Ljava/lang/Object;U:Ljava/lang/Object;>(I[TT;Lscala/Function1<TA;TU;>;)V
    MethodParameters:
      Name                           Flags
      level                          final
      a                              final
      f                              final

  public final <A extends java.lang.Object, B extends java.lang.Object> java.lang.Object[] mapElems1(java.lang.Object[], scala.Function1<A, B>);
    descriptor: ([Ljava/lang/Object;Lscala/Function1;)[Ljava/lang/Object;
    flags: (0x0011) ACC_PUBLIC, ACC_FINAL
    Code:
      stack=5, locals=8, args_size=3
         0: iconst_0
         1: istore_3
         2: iload_3
         3: aload_1
         4: arraylength
         5: if_icmpge     99
         8: aload_1
         9: iload_3
        10: aaload
        11: astore        4
        13: aload_2
        14: aload         4
        16: invokeinterface #102,  2          // InterfaceMethod scala/Function1.apply:(Ljava/lang/Object;)Ljava/lang/Object;
        21: astore        5
        23: aload         4
        25: aload         5
        27: if_acmpeq     93
        30: aload_1
        31: arraylength
        32: anewarray     #4                  // class java/lang/Object
        35: astore        6
        37: iload_3
        38: iconst_0
        39: if_icmple     51
        42: aload_1
        43: iconst_0
        44: aload         6
        46: iconst_0
        47: iload_3
        48: invokestatic  #53                 // Method java/lang/System.arraycopy:(Ljava/lang/Object;ILjava/lang/Object;II)V
        51: aload         6
        53: iload_3
        54: aload         5
        56: aastore
        57: iload_3
        58: iconst_1
        59: iadd
        60: istore        7
        62: iload         7
        64: aload_1
        65: arraylength
        66: if_icmpge     90
        69: aload         6
        71: iload         7
        73: aload_2
        74: aload_1
        75: iload         7
        77: aaload
        78: invokeinterface #102,  2          // InterfaceMethod scala/Function1.apply:(Ljava/lang/Object;)Ljava/lang/Object;
        83: aastore
        84: iinc          7, 1
        87: goto          62
        90: aload         6
        92: areturn
        93: iinc          3, 1
        96: goto          2
        99: aload_1
       100: areturn
      StackMapTable: number_of_entries = 6
        frame_type = 252 /* append */
          offset_delta = 2
          locals = [ int ]
        frame_type = 254 /* append */
          offset_delta = 48
          locals = [ class java/lang/Object, class java/lang/Object, class "[Ljava/lang/Object;" ]
        frame_type = 252 /* append */
          offset_delta = 10
          locals = [ int ]
        frame_type = 27 /* same */
        frame_type = 249 /* chop */
          offset_delta = 2
        frame_type = 249 /* chop */
          offset_delta = 5
      LineNumberTable:
        line 1869: 0
        line 1870: 2
        line 1871: 8
        line 1872: 13
        line 1873: 23
        line 1881: 30
        line 1882: 37
        line 1883: 51
        line 1884: 57
        line 1885: 62
        line 1886: 69
        line 1887: 84
        line 1885: 87
        line 1889: 90
        line 1874: 90
        line 1875: 93
        line 1870: 96
        line 1877: 99
      LocalVariableTable:
        Start  Length  Slot  Name   Signature
           13      83     4    v1   Ljava/lang/Object;
           23      73     5    v2   Ljava/lang/Object;
            2      98     3     i   I
            0     101     0  this   Lscala/collection/immutable/VectorStatics$;
            0     101     1     a   [Ljava/lang/Object;
            0     101     2     f   Lscala/Function1;
           37      53     6 mapElems1Rest_ac   [Ljava/lang/Object;
           62      28     7 mapElems1Rest_i   I
    Signature: #111                         // <A:Ljava/lang/Object;B:Ljava/lang/Object;>([Ljava/lang/Object;Lscala/Function1<TA;TB;>;)[Ljava/lang/Object;
    MethodParameters:
      Name                           Flags
      a                              final
      f                              final

  public final <A extends java.lang.Object, B extends java.lang.Object> java.lang.Object[] mapElems1Rest(java.lang.Object[], scala.Function1<A, B>, int, java.lang.Object);
    descriptor: ([Ljava/lang/Object;Lscala/Function1;ILjava/lang/Object;)[Ljava/lang/Object;
    flags: (0x0011) ACC_PUBLIC, ACC_FINAL
    Code:
      stack=5, locals=7, args_size=5
         0: aload_1
         1: arraylength
         2: anewarray     #4                  // class java/lang/Object
         5: astore        5
         7: iload_3
         8: iconst_0
         9: if_icmple     21
        12: aload_1
        13: iconst_0
        14: aload         5
        16: iconst_0
        17: iload_3
        18: invokestatic  #53                 // Method java/lang/System.arraycopy:(Ljava/lang/Object;ILjava/lang/Object;II)V
        21: aload         5
        23: iload_3
        24: aload         4
        26: aastore
        27: iload_3
        28: iconst_1
        29: iadd
        30: istore        6
        32: iload         6
        34: aload_1
        35: arraylength
        36: if_icmpge     60
        39: aload         5
        41: iload         6
        43: aload_2
        44: aload_1
        45: iload         6
        47: aaload
        48: invokeinterface #102,  2          // InterfaceMethod scala/Function1.apply:(Ljava/lang/Object;)Ljava/lang/Object;
        53: aastore
        54: iinc          6, 1
        57: goto          32
        60: aload         5
        62: areturn
      StackMapTable: number_of_entries = 3
        frame_type = 252 /* append */
          offset_delta = 21
          locals = [ class "[Ljava/lang/Object;" ]
        frame_type = 252 /* append */
          offset_delta = 10
          locals = [ int ]
        frame_type = 27 /* same */
      LineNumberTable:
        line 1881: 0
        line 1882: 7
        line 1883: 21
        line 1884: 27
        line 1885: 32
        line 1886: 39
        line 1887: 54
        line 1885: 57
        line 1889: 60
      LocalVariableTable:
        Start  Length  Slot  Name   Signature
            7      55     5    ac   [Ljava/lang/Object;
           32      30     6     i   I
            0      63     0  this   Lscala/collection/immutable/VectorStatics$;
            0      63     1     a   [Ljava/lang/Object;
            0      63     2     f   Lscala/Function1;
            0      63     3    at   I
            0      63     4    v2   Ljava/lang/Object;
    Signature: #118                         // <A:Ljava/lang/Object;B:Ljava/lang/Object;>([Ljava/lang/Object;Lscala/Function1<TA;TB;>;ILjava/lang/Object;)[Ljava/lang/Object;
    MethodParameters:
      Name                           Flags
      a                              final
      f                              final
      at                             final
      v2                             final

  public final <A extends java.lang.Object, B extends java.lang.Object, T extends java.lang.Object> T[] mapElems(int, T[], scala.Function1<A, B>);
    descriptor: (I[Ljava/lang/Object;Lscala/Function1;)[Ljava/lang/Object;
    flags: (0x0011) ACC_PUBLIC, ACC_FINAL
    Code:
      stack=8, locals=27, args_size=4
         0: iload_1
         1: iconst_1
         2: if_icmpne     124
         5: iconst_0
         6: istore        7
         8: iload         7
        10: aload_2
        11: arraylength
        12: if_icmpge     118
        15: aload_2
        16: iload         7
        18: aaload
        19: astore        8
        21: aload_3
        22: aload         8
        24: invokeinterface #102,  2          // InterfaceMethod scala/Function1.apply:(Ljava/lang/Object;)Ljava/lang/Object;
        29: astore        9
        31: aload         8
        33: aload         9
        35: if_acmpeq     112
        38: aload_2
        39: arraylength
        40: anewarray     #4                  // class java/lang/Object
        43: astore        10
        45: iload         7
        47: iconst_0
        48: if_icmple     61
        51: aload_2
        52: iconst_0
        53: aload         10
        55: iconst_0
        56: iload         7
        58: invokestatic  #53                 // Method java/lang/System.arraycopy:(Ljava/lang/Object;ILjava/lang/Object;II)V
        61: aload         10
        63: iload         7
        65: aload         9
        67: aastore
        68: iload         7
        70: iconst_1
        71: iadd
        72: istore        11
        74: iload         11
        76: aload_2
        77: arraylength
        78: if_icmpge     102
        81: aload         10
        83: iload         11
        85: aload_3
        86: aload_2
        87: iload         11
        89: aaload
        90: invokeinterface #102,  2          // InterfaceMethod scala/Function1.apply:(Ljava/lang/Object;)Ljava/lang/Object;
        95: aastore
        96: iinc          11, 1
        99: goto          74
       102: aload         10
       104: aconst_null
       105: astore        10
       107: astore        12
       109: goto          121
       112: iinc          7, 1
       115: goto          8
       118: aload_2
       119: astore        12
       121: aload         12
       123: areturn
       124: iconst_0
       125: istore        4
       127: iload         4
       129: aload_2
       130: arraylength
       131: if_icmpge     490
       134: aload_2
       135: iload         4
       137: aaload
       138: astore        5
       140: aload_0
       141: iload_1
       142: iconst_1
       143: isub
       144: aload         5
       146: checkcast     #29                 // class "[Ljava/lang/Object;"
       149: aload_3
       150: invokevirtual #125                // Method mapElems:(I[Ljava/lang/Object;Lscala/Function1;)[Ljava/lang/Object;
       153: astore        6
       155: aload         5
       157: aload         6
       159: if_acmpeq     484
       162: aload_2
       163: invokevirtual #74                 // Method java/lang/Object.getClass:()Ljava/lang/Class;
       166: invokevirtual #79                 // Method java/lang/Class.getComponentType:()Ljava/lang/Class;
       169: aload_2
       170: arraylength
       171: invokestatic  #85                 // Method java/lang/reflect/Array.newInstance:(Ljava/lang/Class;I)Ljava/lang/Object;
       174: checkcast     #29                 // class "[Ljava/lang/Object;"
       177: astore        13
       179: iload         4
       181: iconst_0
       182: if_icmple     195
       185: aload_2
       186: iconst_0
       187: aload         13
       189: iconst_0
       190: iload         4
       192: invokestatic  #53                 // Method java/lang/System.arraycopy:(Ljava/lang/Object;ILjava/lang/Object;II)V
       195: aload         13
       197: iload         4
       199: aload         6
       201: aastore
       202: iload         4
       204: iconst_1
       205: iadd
       206: istore        14
       208: iload         14
       210: aload_2
       211: arraylength
       212: if_icmpge     481
       215: aload         13
       217: iload         14
       219: iload_1
       220: iconst_1
       221: isub
       222: aload_2
       223: iload         14
       225: aaload
       226: checkcast     #29                 // class "[Ljava/lang/Object;"
       229: astore        16
       231: istore        15
       233: iload         15
       235: iconst_1
       236: if_icmpne     379
       239: iconst_0
       240: istore        20
       242: iload         20
       244: aload         16
       246: arraylength
       247: if_icmpge     358
       250: aload         16
       252: iload         20
       254: aaload
       255: astore        21
       257: aload_3
       258: aload         21
       260: invokeinterface #102,  2          // InterfaceMethod scala/Function1.apply:(Ljava/lang/Object;)Ljava/lang/Object;
       265: astore        22
       267: aload         21
       269: aload         22
       271: if_acmpeq     352
       274: aload         16
       276: arraylength
       277: anewarray     #4                  // class java/lang/Object
       280: astore        23
       282: iload         20
       284: iconst_0
       285: if_icmple     299
       288: aload         16
       290: iconst_0
       291: aload         23
       293: iconst_0
       294: iload         20
       296: invokestatic  #53                 // Method java/lang/System.arraycopy:(Ljava/lang/Object;ILjava/lang/Object;II)V
       299: aload         23
       301: iload         20
       303: aload         22
       305: aastore
       306: iload         20
       308: iconst_1
       309: iadd
       310: istore        24
       312: iload         24
       314: aload         16
       316: arraylength
       317: if_icmpge     342
       320: aload         23
       322: iload         24
       324: aload_3
       325: aload         16
       327: iload         24
       329: aaload
       330: invokeinterface #102,  2          // InterfaceMethod scala/Function1.apply:(Ljava/lang/Object;)Ljava/lang/Object;
       335: aastore
       336: iinc          24, 1
       339: goto          312
       342: aload         23
       344: aconst_null
       345: astore        23
       347: astore        25
       349: goto          362
       352: iinc          20, 1
       355: goto          242
       358: aload         16
       360: astore        25
       362: aload         25
       364: aconst_null
       365: astore        21
       367: aconst_null
       368: astore        22
       370: aconst_null
       371: astore        23
       373: aconst_null
       374: astore        25
       376: goto          446
       379: iconst_0
       380: istore        17
       382: iload         17
       384: aload         16
       386: arraylength
       387: if_icmpge     444
       390: aload         16
       392: iload         17
       394: aaload
       395: astore        18
       397: aload_0
       398: iload         15
       400: iconst_1
       401: isub
       402: aload         18
       404: checkcast     #29                 // class "[Ljava/lang/Object;"
       407: aload_3
       408: invokevirtual #125                // Method mapElems:(I[Ljava/lang/Object;Lscala/Function1;)[Ljava/lang/Object;
       411: astore        19
       413: aload         18
       415: aload         19
       417: if_acmpeq     438
       420: aload_0
       421: iload         15
       423: aload         16
       425: aload_3
       426: iload         17
       428: aload         19
       430: invokevirtual #129                // Method mapElemsRest:(I[Ljava/lang/Object;Lscala/Function1;ILjava/lang/Object;)[Ljava/lang/Object;
       433: astore        26
       435: goto          448
       438: iinc          17, 1
       441: goto          382
       444: aload         16
       446: astore        26
       448: aload         26
       450: aconst_null
       451: astore        16
       453: aconst_null
       454: astore        18
       456: aconst_null
       457: astore        19
       459: aconst_null
       460: astore        21
       462: aconst_null
       463: astore        22
       465: aconst_null
       466: astore        23
       468: aconst_null
       469: astore        25
       471: aconst_null
       472: astore        26
       474: aastore
       475: iinc          14, 1
       478: goto          208
       481: aload         13
       483: areturn
       484: iinc          4, 1
       487: goto          127
       490: aload_2
       491: areturn
      StackMapTable: number_of_entries = 27
        frame_type = 255 /* full_frame */
          offset_delta = 8
          locals = [ class scala/collection/immutable/VectorStatics$, int, class "[Ljava/lang/Object;", class scala/Function1, top, top, top, int ]
          stack = []
        frame_type = 254 /* append */
          offset_delta = 52
          locals = [ class java/lang/Object, class java/lang/Object, class "[Ljava/lang/Object;" ]
        frame_type = 252 /* append */
          offset_delta = 12
          locals = [ int ]
        frame_type = 27 /* same */
        frame_type = 249 /* chop */
          offset_delta = 9
        frame_type = 249 /* chop */
          offset_delta = 5
        frame_type = 255 /* full_frame */
          offset_delta = 2
          locals = [ class scala/collection/immutable/VectorStatics$, int, class "[Ljava/lang/Object;", class scala/Function1, top, top, top, int, top, top, top, top, class "[Ljava/lang/Object;" ]
          stack = []
        frame_type = 255 /* full_frame */
          offset_delta = 2
          locals = [ class scala/collection/immutable/VectorStatics$, int, class "[Ljava/lang/Object;", class scala/Function1 ]
          stack = []
        frame_type = 252 /* append */
          offset_delta = 2
          locals = [ int ]
        frame_type = 255 /* full_frame */
          offset_delta = 67
          locals = [ class scala/collection/immutable/VectorStatics$, int, class "[Ljava/lang/Object;", class scala/Function1, int, class java/lang/Object, class "[Ljava/lang/Object;", top, top, top, top, top, top, class "[Ljava/lang/Object;" ]
          stack = []
        frame_type = 252 /* append */
          offset_delta = 12
          locals = [ int ]
        frame_type = 255 /* full_frame */
          offset_delta = 33
          locals = [ class scala/collection/immutable/VectorStatics$, int, class "[Ljava/lang/Object;", class scala/Function1, int, class java/lang/Object, class "[Ljava/lang/Object;", top, top, top, top, top, top, class "[Ljava/lang/Object;", int, int, class "[Ljava/lang/Object;", top, top, top, int ]
          stack = [ class "[Ljava/lang/Object;", int ]
        frame_type = 255 /* full_frame */
          offset_delta = 56
          locals = [ class scala/collection/immutable/VectorStatics$, int, class "[Ljava/lang/Object;", class scala/Function1, int, class java/lang/Object, class "[Ljava/lang/Object;", top, top, top, top, top, top, class "[Ljava/lang/Object;", int, int, class "[Ljava/lang/Object;", top, top, top, int, class java/lang/Object, class java/lang/Object, class "[Ljava/lang/Object;" ]
          stack = [ class "[Ljava/lang/Object;", int ]
        frame_type = 255 /* full_frame */
          offset_delta = 12
          locals = [ class scala/collection/immutable/VectorStatics$, int, class "[Ljava/lang/Object;", class scala/Function1, int, class java/lang/Object, class "[Ljava/lang/Object;", top, top, top, top, top, top, class "[Ljava/lang/Object;", int, int, class "[Ljava/lang/Object;", top, top, top, int, class java/lang/Object, class java/lang/Object, class "[Ljava/lang/Object;", int ]
          stack = [ class "[Ljava/lang/Object;", int ]
        frame_type = 255 /* full_frame */
          offset_delta = 29
          locals = [ class scala/collection/immutable/VectorStatics$, int, class "[Ljava/lang/Object;", class scala/Function1, int, class java/lang/Object, class "[Ljava/lang/Object;", top, top, top, top, top, top, class "[Ljava/lang/Object;", int, int, class "[Ljava/lang/Object;", top, top, top, int, class java/lang/Object, class java/lang/Object, class "[Ljava/lang/Object;", int ]
          stack = [ class "[Ljava/lang/Object;", int ]
        frame_type = 255 /* full_frame */
          offset_delta = 9
          locals = [ class scala/collection/immutable/VectorStatics$, int, class "[Ljava/lang/Object;", class scala/Function1, int, class java/lang/Object, class "[Ljava/lang/Object;", top, top, top, top, top, top, class "[Ljava/lang/Object;", int, int, class "[Ljava/lang/Object;", top, top, top, int, class java/lang/Object, class java/lang/Object ]
          stack = [ class "[Ljava/lang/Object;", int ]
        frame_type = 255 /* full_frame */
          offset_delta = 5
          locals = [ class scala/collection/immutable/VectorStatics$, int, class "[Ljava/lang/Object;", class scala/Function1, int, class java/lang/Object, class "[Ljava/lang/Object;", top, top, top, top, top, top, class "[Ljava/lang/Object;", int, int, class "[Ljava/lang/Object;", top, top, top, int ]
          stack = [ class "[Ljava/lang/Object;", int ]
        frame_type = 255 /* full_frame */
          offset_delta = 3
          locals = [ class scala/collection/immutable/VectorStatics$, int, class "[Ljava/lang/Object;", class scala/Function1, int, class java/lang/Object, class "[Ljava/lang/Object;", top, top, top, top, top, top, class "[Ljava/lang/Object;", int, int, class "[Ljava/lang/Object;", top, top, top, int, top, top, top, top, class "[Ljava/lang/Object;" ]
          stack = [ class "[Ljava/lang/Object;", int ]
        frame_type = 255 /* full_frame */
          offset_delta = 16
          locals = [ class scala/collection/immutable/VectorStatics$, int, class "[Ljava/lang/Object;", class scala/Function1, int, class java/lang/Object, class "[Ljava/lang/Object;", top, top, top, top, top, top, class "[Ljava/lang/Object;", int, int, class "[Ljava/lang/Object;" ]
          stack = [ class "[Ljava/lang/Object;", int ]
        frame_type = 255 /* full_frame */
          offset_delta = 2
          locals = [ class scala/collection/immutable/VectorStatics$, int, class "[Ljava/lang/Object;", class scala/Function1, int, class java/lang/Object, class "[Ljava/lang/Object;", top, top, top, top, top, top, class "[Ljava/lang/Object;", int, int, class "[Ljava/lang/Object;", int ]
          stack = [ class "[Ljava/lang/Object;", int ]
        frame_type = 255 /* full_frame */
          offset_delta = 55
          locals = [ class scala/collection/immutable/VectorStatics$, int, class "[Ljava/lang/Object;", class scala/Function1, int, class java/lang/Object, class "[Ljava/lang/Object;", top, top, top, top, top, top, class "[Ljava/lang/Object;", int, int, class "[Ljava/lang/Object;", int, class java/lang/Object, class "[Ljava/lang/Object;" ]
          stack = [ class "[Ljava/lang/Object;", int ]
        frame_type = 255 /* full_frame */
          offset_delta = 5
          locals = [ class scala/collection/immutable/VectorStatics$, int, class "[Ljava/lang/Object;", class scala/Function1, int, class java/lang/Object, class "[Ljava/lang/Object;", top, top, top, top, top, top, class "[Ljava/lang/Object;", int, int, class "[Ljava/lang/Object;", int ]
          stack = [ class "[Ljava/lang/Object;", int ]
        frame_type = 255 /* full_frame */
          offset_delta = 1
          locals = [ class scala/collection/immutable/VectorStatics$, int, class "[Ljava/lang/Object;", class scala/Function1, int, class java/lang/Object, class "[Ljava/lang/Object;", top, top, top, top, top, top, class "[Ljava/lang/Object;", int, int, class "[Ljava/lang/Object;" ]
          stack = [ class "[Ljava/lang/Object;", int, class "[Ljava/lang/Object;" ]
        frame_type = 255 /* full_frame */
          offset_delta = 1
          locals = [ class scala/collection/immutable/VectorStatics$, int, class "[Ljava/lang/Object;", class scala/Function1, int, class java/lang/Object, class "[Ljava/lang/Object;", top, top, top, top, top, top, class "[Ljava/lang/Object;", int, int, class "[Ljava/lang/Object;", top, top, top, top, top, top, top, top, top, class "[Ljava/lang/Object;" ]
          stack = [ class "[Ljava/lang/Object;", int ]
        frame_type = 255 /* full_frame */
          offset_delta = 32
          locals = [ class scala/collection/immutable/VectorStatics$, int, class "[Ljava/lang/Object;", class scala/Function1, int, class java/lang/Object, class "[Ljava/lang/Object;", top, top, top, top, top, top, class "[Ljava/lang/Object;", int ]
          stack = []
        frame_type = 255 /* full_frame */
          offset_delta = 2
          locals = [ class scala/collection/immutable/VectorStatics$, int, class "[Ljava/lang/Object;", class scala/Function1, int, class java/lang/Object, class "[Ljava/lang/Object;" ]
          stack = []
        frame_type = 249 /* chop */
          offset_delta = 5
      LineNumberTable:
        line 1893: 0
        line 1869: 5
        line 1870: 8
        line 1871: 15
        line 1872: 21
        line 1873: 31
        line 1881: 38
        line 1882: 45
        line 1883: 61
        line 1884: 68
        line 1885: 74
        line 1886: 81
        line 1887: 96
        line 1885: 99
        line 1889: 102
        line 1874: 102
        line 1875: 112
        line 1870: 115
        line 1877: 118
        line 1894: 121
        line 1896: 124
        line 1897: 127
        line 1898: 134
        line 1899: 140
        line 1900: 155
        line 1909: 162
        line 1910: 179
        line 1911: 195
        line 1912: 202
        line 1913: 208
        line 1914: 215
        line 1893: 233
        line 1869: 239
        line 1870: 242
        line 1871: 250
        line 1872: 257
        line 1873: 267
        line 1881: 274
        line 1882: 282
        line 1883: 299
        line 1884: 306
        line 1885: 312
        line 1886: 320
        line 1887: 336
        line 1885: 339
        line 1889: 342
        line 1874: 342
        line 1875: 352
        line 1870: 355
        line 1877: 358
        line 1894: 362
        line 1896: 379
        line 1897: 382
        line 1898: 390
        line 1899: 397
        line 1900: 413
        line 1901: 420
        line 1902: 438
        line 1897: 441
        line 1904: 444
        line 1914: 448
        line 1915: 475
        line 1913: 478
        line 1917: 481
        line 1901: 481
        line 1902: 484
        line 1897: 487
        line 1904: 490
      LocalVariableTable:
        Start  Length  Slot  Name   Signature
          140     347     5    v1   Ljava/lang/Object;
          155     332     6    v2   [Ljava/lang/Object;
          127     364     4     i   I
            0     492     0  this   Lscala/collection/immutable/VectorStatics$;
            0     492     1     n   I
            0     492     2     a   [Ljava/lang/Object;
            0     492     3     f   Lscala/Function1;
           21      94     8 mapElems1_v1   Ljava/lang/Object;
           31      84     9 mapElems1_v2   Ljava/lang/Object;
            8     111     7 mapElems1_i   I
           45      57    10 mapElems1_mapElems1Rest_ac   [Ljava/lang/Object;
           74      28    11 mapElems1_mapElems1Rest_i   I
          179     302    13 mapElemsRest_ac   [Ljava/lang/Object;
          208     273    14 mapElemsRest_i   I
          397      44    18 mapElemsRest_mapElems_v1   Ljava/lang/Object;
          413      28    19 mapElemsRest_mapElems_v2   [Ljava/lang/Object;
          382      64    17 mapElemsRest_mapElems_i   I
          233     215    15 mapElemsRest_mapElems_n   I
          233     215    16 mapElemsRest_mapElems_a   [Ljava/lang/Object;
          257      98    21 mapElemsRest_mapElems_mapElems1_v1   Ljava/lang/Object;
          267      88    22 mapElemsRest_mapElems_mapElems1_v2   Ljava/lang/Object;
          242     118    20 mapElemsRest_mapElems_mapElems1_i   I
          282      60    23 mapElemsRest_mapElems_mapElems1_mapElems1Rest_ac   [Ljava/lang/Object;
          312      30    24 mapElemsRest_mapElems_mapElems1_mapElems1Rest_i   I
    Signature: #122                         // <A:Ljava/lang/Object;B:Ljava/lang/Object;T:Ljava/lang/Object;>(I[TT;Lscala/Function1<TA;TB;>;)[TT;
    MethodParameters:
      Name                           Flags
      n                              final
      a                              final
      f                              final

  public final <A extends java.lang.Object, B extends java.lang.Object, T extends java.lang.Object> T[] mapElemsRest(int, T[], scala.Function1<A, B>, int, java.lang.Object);
    descriptor: (I[Ljava/lang/Object;Lscala/Function1;ILjava/lang/Object;)[Ljava/lang/Object;
    flags: (0x0011) ACC_PUBLIC, ACC_FINAL
    Code:
      stack=8, locals=20, args_size=6
         0: aload_2
         1: invokevirtual #74                 // Method java/lang/Object.getClass:()Ljava/lang/Class;
         4: invokevirtual #79                 // Method java/lang/Class.getComponentType:()Ljava/lang/Class;
         7: aload_2
         8: arraylength
         9: invokestatic  #85                 // Method java/lang/reflect/Array.newInstance:(Ljava/lang/Class;I)Ljava/lang/Object;
        12: checkcast     #29                 // class "[Ljava/lang/Object;"
        15: astore        6
        17: iload         4
        19: iconst_0
        20: if_icmple     33
        23: aload_2
        24: iconst_0
        25: aload         6
        27: iconst_0
        28: iload         4
        30: invokestatic  #53                 // Method java/lang/System.arraycopy:(Ljava/lang/Object;ILjava/lang/Object;II)V
        33: aload         6
        35: iload         4
        37: aload         5
        39: aastore
        40: iload         4
        42: iconst_1
        43: iadd
        44: istore        7
        46: iload         7
        48: aload_2
        49: arraylength
        50: if_icmpge     319
        53: aload         6
        55: iload         7
        57: iload_1
        58: iconst_1
        59: isub
        60: aload_2
        61: iload         7
        63: aaload
        64: checkcast     #29                 // class "[Ljava/lang/Object;"
        67: astore        9
        69: istore        8
        71: iload         8
        73: iconst_1
        74: if_icmpne     217
        77: iconst_0
        78: istore        13
        80: iload         13
        82: aload         9
        84: arraylength
        85: if_icmpge     196
        88: aload         9
        90: iload         13
        92: aaload
        93: astore        14
        95: aload_3
        96: aload         14
        98: invokeinterface #102,  2          // InterfaceMethod scala/Function1.apply:(Ljava/lang/Object;)Ljava/lang/Object;
       103: astore        15
       105: aload         14
       107: aload         15
       109: if_acmpeq     190
       112: aload         9
       114: arraylength
       115: anewarray     #4                  // class java/lang/Object
       118: astore        16
       120: iload         13
       122: iconst_0
       123: if_icmple     137
       126: aload         9
       128: iconst_0
       129: aload         16
       131: iconst_0
       132: iload         13
       134: invokestatic  #53                 // Method java/lang/System.arraycopy:(Ljava/lang/Object;ILjava/lang/Object;II)V
       137: aload         16
       139: iload         13
       141: aload         15
       143: aastore
       144: iload         13
       146: iconst_1
       147: iadd
       148: istore        17
       150: iload         17
       152: aload         9
       154: arraylength
       155: if_icmpge     180
       158: aload         16
       160: iload         17
       162: aload_3
       163: aload         9
       165: iload         17
       167: aaload
       168: invokeinterface #102,  2          // InterfaceMethod scala/Function1.apply:(Ljava/lang/Object;)Ljava/lang/Object;
       173: aastore
       174: iinc          17, 1
       177: goto          150
       180: aload         16
       182: aconst_null
       183: astore        16
       185: astore        18
       187: goto          200
       190: iinc          13, 1
       193: goto          80
       196: aload         9
       198: astore        18
       200: aload         18
       202: aconst_null
       203: astore        14
       205: aconst_null
       206: astore        15
       208: aconst_null
       209: astore        16
       211: aconst_null
       212: astore        18
       214: goto          284
       217: iconst_0
       218: istore        10
       220: iload         10
       222: aload         9
       224: arraylength
       225: if_icmpge     282
       228: aload         9
       230: iload         10
       232: aaload
       233: astore        11
       235: aload_0
       236: iload         8
       238: iconst_1
       239: isub
       240: aload         11
       242: checkcast     #29                 // class "[Ljava/lang/Object;"
       245: aload_3
       246: invokevirtual #125                // Method mapElems:(I[Ljava/lang/Object;Lscala/Function1;)[Ljava/lang/Object;
       249: astore        12
       251: aload         11
       253: aload         12
       255: if_acmpeq     276
       258: aload_0
       259: iload         8
       261: aload         9
       263: aload_3
       264: iload         10
       266: aload         12
       268: invokevirtual #129                // Method mapElemsRest:(I[Ljava/lang/Object;Lscala/Function1;ILjava/lang/Object;)[Ljava/lang/Object;
       271: astore        19
       273: goto          286
       276: iinc          10, 1
       279: goto          220
       282: aload         9
       284: astore        19
       286: aload         19
       288: aconst_null
       289: astore        9
       291: aconst_null
       292: astore        11
       294: aconst_null
       295: astore        12
       297: aconst_null
       298: astore        14
       300: aconst_null
       301: astore        15
       303: aconst_null
       304: astore        16
       306: aconst_null
       307: astore        18
       309: aconst_null
       310: astore        19
       312: aastore
       313: iinc          7, 1
       316: goto          46
       319: aload         6
       321: areturn
      StackMapTable: number_of_entries = 16
        frame_type = 252 /* append */
          offset_delta = 33
          locals = [ class "[Ljava/lang/Object;" ]
        frame_type = 252 /* append */
          offset_delta = 12
          locals = [ int ]
        frame_type = 255 /* full_frame */
          offset_delta = 33
          locals = [ class scala/collection/immutable/VectorStatics$, int, class "[Ljava/lang/Object;", class scala/Function1, int, class java/lang/Object, class "[Ljava/lang/Object;", int, int, class "[Ljava/lang/Object;", top, top, top, int ]
          stack = [ class "[Ljava/lang/Object;", int ]
        frame_type = 255 /* full_frame */
          offset_delta = 56
          locals = [ class scala/collection/immutable/VectorStatics$, int, class "[Ljava/lang/Object;", class scala/Function1, int, class java/lang/Object, class "[Ljava/lang/Object;", int, int, class "[Ljava/lang/Object;", top, top, top, int, class java/lang/Object, class java/lang/Object, class "[Ljava/lang/Object;" ]
          stack = [ class "[Ljava/lang/Object;", int ]
        frame_type = 255 /* full_frame */
          offset_delta = 12
          locals = [ class scala/collection/immutable/VectorStatics$, int, class "[Ljava/lang/Object;", class scala/Function1, int, class java/lang/Object, class "[Ljava/lang/Object;", int, int, class "[Ljava/lang/Object;", top, top, top, int, class java/lang/Object, class java/lang/Object, class "[Ljava/lang/Object;", int ]
          stack = [ class "[Ljava/lang/Object;", int ]
        frame_type = 255 /* full_frame */
          offset_delta = 29
          locals = [ class scala/collection/immutable/VectorStatics$, int, class "[Ljava/lang/Object;", class scala/Function1, int, class java/lang/Object, class "[Ljava/lang/Object;", int, int, class "[Ljava/lang/Object;", top, top, top, int, class java/lang/Object, class java/lang/Object, class "[Ljava/lang/Object;", int ]
          stack = [ class "[Ljava/lang/Object;", int ]
        frame_type = 255 /* full_frame */
          offset_delta = 9
          locals = [ class scala/collection/immutable/VectorStatics$, int, class "[Ljava/lang/Object;", class scala/Function1, int, class java/lang/Object, class "[Ljava/lang/Object;", int, int, class "[Ljava/lang/Object;", top, top, top, int, class java/lang/Object, class java/lang/Object ]
          stack = [ class "[Ljava/lang/Object;", int ]
        frame_type = 255 /* full_frame */
          offset_delta = 5
          locals = [ class scala/collection/immutable/VectorStatics$, int, class "[Ljava/lang/Object;", class scala/Function1, int, class java/lang/Object, class "[Ljava/lang/Object;", int, int, class "[Ljava/lang/Object;", top, top, top, int ]
          stack = [ class "[Ljava/lang/Object;", int ]
        frame_type = 255 /* full_frame */
          offset_delta = 3
          locals = [ class scala/collection/immutable/VectorStatics$, int, class "[Ljava/lang/Object;", class scala/Function1, int, class java/lang/Object, class "[Ljava/lang/Object;", int, int, class "[Ljava/lang/Object;", top, top, top, int, top, top, top, top, class "[Ljava/lang/Object;" ]
          stack = [ class "[Ljava/lang/Object;", int ]
        frame_type = 255 /* full_frame */
          offset_delta = 16
          locals = [ class scala/collection/immutable/VectorStatics$, int, class "[Ljava/lang/Object;", class scala/Function1, int, class java/lang/Object, class "[Ljava/lang/Object;", int, int, class "[Ljava/lang/Object;" ]
          stack = [ class "[Ljava/lang/Object;", int ]
        frame_type = 255 /* full_frame */
          offset_delta = 2
          locals = [ class scala/collection/immutable/VectorStatics$, int, class "[Ljava/lang/Object;", class scala/Function1, int, class java/lang/Object, class "[Ljava/lang/Object;", int, int, class "[Ljava/lang/Object;", int ]
          stack = [ class "[Ljava/lang/Object;", int ]
        frame_type = 255 /* full_frame */
          offset_delta = 55
          locals = [ class scala/collection/immutable/VectorStatics$, int, class "[Ljava/lang/Object;", class scala/Function1, int, class java/lang/Object, class "[Ljava/lang/Object;", int, int, class "[Ljava/lang/Object;", int, class java/lang/Object, class "[Ljava/lang/Object;" ]
          stack = [ class "[Ljava/lang/Object;", int ]
        frame_type = 255 /* full_frame */
          offset_delta = 5
          locals = [ class scala/collection/immutable/VectorStatics$, int, class "[Ljava/lang/Object;", class scala/Function1, int, class java/lang/Object, class "[Ljava/lang/Object;", int, int, class "[Ljava/lang/Object;", int ]
          stack = [ class "[Ljava/lang/Object;", int ]
        frame_type = 255 /* full_frame */
          offset_delta = 1
          locals = [ class scala/collection/immutable/VectorStatics$, int, class "[Ljava/lang/Object;", class scala/Function1, int, class java/lang/Object, class "[Ljava/lang/Object;", int, int, class "[Ljava/lang/Object;" ]
          stack = [ class "[Ljava/lang/Object;", int, class "[Ljava/lang/Object;" ]
        frame_type = 255 /* full_frame */
          offset_delta = 1
          locals = [ class scala/collection/immutable/VectorStatics$, int, class "[Ljava/lang/Object;", class scala/Function1, int, class java/lang/Object, class "[Ljava/lang/Object;", int, int, class "[Ljava/lang/Object;", top, top, top, top, top, top, top, top, top, class "[Ljava/lang/Object;" ]
          stack = [ class "[Ljava/lang/Object;", int ]
        frame_type = 255 /* full_frame */
          offset_delta = 32
          locals = [ class scala/collection/immutable/VectorStatics$, int, class "[Ljava/lang/Object;", class scala/Function1, int, class java/lang/Object, class "[Ljava/lang/Object;", int ]
          stack = []
      LineNumberTable:
        line 1909: 0
        line 1910: 17
        line 1911: 33
        line 1912: 40
        line 1913: 46
        line 1914: 53
        line 1893: 71
        line 1869: 77
        line 1870: 80
        line 1871: 88
        line 1872: 95
        line 1873: 105
        line 1881: 112
        line 1882: 120
        line 1883: 137
        line 1884: 144
        line 1885: 150
        line 1886: 158
        line 1887: 174
        line 1885: 177
        line 1889: 180
        line 1874: 180
        line 1875: 190
        line 1870: 193
        line 1877: 196
        line 1894: 200
        line 1896: 217
        line 1897: 220
        line 1898: 228
        line 1899: 235
        line 1900: 251
        line 1901: 258
        line 1902: 276
        line 1897: 279
        line 1904: 282
        line 1914: 286
        line 1915: 313
        line 1913: 316
        line 1917: 319
      LocalVariableTable:
        Start  Length  Slot  Name   Signature
           17     304     6    ac   [Ljava/lang/Object;
           46     275     7     i   I
            0     322     0  this   Lscala/collection/immutable/VectorStatics$;
            0     322     1     n   I
            0     322     2     a   [Ljava/lang/Object;
            0     322     3     f   Lscala/Function1;
            0     322     4    at   I
            0     322     5    v2   Ljava/lang/Object;
          235      44    11 mapElems_v1   Ljava/lang/Object;
          251      28    12 mapElems_v2   [Ljava/lang/Object;
          220      64    10 mapElems_i   I
           71     215     8 mapElems_n   I
           71     215     9 mapElems_a   [Ljava/lang/Object;
           95      98    14 mapElems_mapElems1_v1   Ljava/lang/Object;
          105      88    15 mapElems_mapElems1_v2   Ljava/lang/Object;
           80     118    13 mapElems_mapElems1_i   I
          120      60    16 mapElems_mapElems1_mapElems1Rest_ac   [Ljava/lang/Object;
          150      30    17 mapElems_mapElems1_mapElems1Rest_i   I
    Signature: #147                         // <A:Ljava/lang/Object;B:Ljava/lang/Object;T:Ljava/lang/Object;>(I[TT;Lscala/Function1<TA;TB;>;ILjava/lang/Object;)[TT;
    MethodParameters:
      Name                           Flags
      n                              final
      a                              final
      f                              final
      at                             final
      v2                             final

  public final java.lang.Object[] prepend1IfSpace(java.lang.Object[], scala.collection.IterableOnce<?>);
    descriptor: ([Ljava/lang/Object;Lscala/collection/IterableOnce;)[Ljava/lang/Object;
    flags: (0x0011) ACC_PUBLIC, ACC_FINAL
    Code:
      stack=5, locals=9, args_size=3
         0: aload_2
         1: instanceof    #164                // class scala/collection/immutable/Iterable
         4: ifeq          125
         7: aload_2
         8: checkcast     #164                // class scala/collection/immutable/Iterable
        11: astore        4
        13: aload         4
        15: bipush        32
        17: aload_1
        18: arraylength
        19: isub
        20: invokeinterface #168,  2          // InterfaceMethod scala/collection/immutable/Iterable.sizeCompare:(I)I
        25: iconst_0
        26: if_icmpgt     120
        29: aload         4
        31: invokeinterface #172,  1          // InterfaceMethod scala/collection/immutable/Iterable.size:()I
        36: istore        5
        38: iload         5
        40: tableswitch   { // 0 to 1
                       0: 64
                       1: 68
                 default: 83
            }
        64: aconst_null
        65: goto          121
        68: aload_0
        69: aload         4
        71: invokeinterface #176,  1          // InterfaceMethod scala/collection/immutable/Iterable.head:()Ljava/lang/Object;
        76: aload_1
        77: invokevirtual #178                // Method copyPrepend:(Ljava/lang/Object;[Ljava/lang/Object;)[Ljava/lang/Object;
        80: goto          121
        83: aload_1
        84: arraylength
        85: iload         5
        87: iadd
        88: anewarray     #4                  // class java/lang/Object
        91: astore        6
        93: aload_1
        94: iconst_0
        95: aload         6
        97: iload         5
        99: aload_1
       100: arraylength
       101: invokestatic  #53                 // Method java/lang/System.arraycopy:(Ljava/lang/Object;ILjava/lang/Object;II)V
       104: aload         4
       106: aload         6
       108: iconst_0
       109: invokeinterface #182,  3          // InterfaceMethod scala/collection/immutable/Iterable.copyToArray:(Ljava/lang/Object;I)I
       114: pop
       115: aload         6
       117: goto          121
       120: aconst_null
       121: astore_3
       122: goto          192
       125: aload_2
       126: invokeinterface #187,  1          // InterfaceMethod scala/collection/IterableOnce.knownSize:()I
       131: istore        7
       133: iload         7
       135: iconst_0
       136: if_icmple     190
       139: iload         7
       141: bipush        32
       143: aload_1
       144: arraylength
       145: isub
       146: if_icmpgt     190
       149: aload_1
       150: arraylength
       151: iload         7
       153: iadd
       154: anewarray     #4                  // class java/lang/Object
       157: astore        8
       159: aload_1
       160: iconst_0
       161: aload         8
       163: iload         7
       165: aload_1
       166: arraylength
       167: invokestatic  #53                 // Method java/lang/System.arraycopy:(Ljava/lang/Object;ILjava/lang/Object;II)V
       170: aload_2
       171: invokeinterface #191,  1          // InterfaceMethod scala/collection/IterableOnce.iterator:()Lscala/collection/Iterator;
       176: aload         8
       178: iconst_0
       179: invokeinterface #194,  3          // InterfaceMethod scala/collection/Iterator.copyToArray:(Ljava/lang/Object;I)I
       184: pop
       185: aload         8
       187: goto          191
       190: aconst_null
       191: astore_3
       192: aload_3
       193: areturn
      StackMapTable: number_of_entries = 9
        frame_type = 254 /* append */
          offset_delta = 64
          locals = [ top, class scala/collection/immutable/Iterable, int ]
        frame_type = 3 /* same */
        frame_type = 14 /* same */
        frame_type = 250 /* chop */
          offset_delta = 36
        frame_type = 64 /* same_locals_1_stack_item */
          stack = [ class "[Ljava/lang/Object;" ]
        frame_type = 249 /* chop */
          offset_delta = 3
        frame_type = 255 /* full_frame */
          offset_delta = 64
          locals = [ class scala/collection/immutable/VectorStatics$, class "[Ljava/lang/Object;", class scala/collection/IterableOnce, top, top, top, top, int ]
          stack = []
        frame_type = 64 /* same_locals_1_stack_item */
          stack = [ class "[Ljava/lang/Object;" ]
        frame_type = 255 /* full_frame */
          offset_delta = 0
          locals = [ class scala/collection/immutable/VectorStatics$, class "[Ljava/lang/Object;", class scala/collection/IterableOnce, class "[Ljava/lang/Object;" ]
          stack = []
      LineNumberTable:
        line 1921: 0
        line 1922: 13
        line 1923: 29
        line 1924: 64
        line 1925: 68
        line 1927: 83
        line 1928: 93
        line 1929: 104
        line 1930: 115
        line 1932: 120
        line 1934: 125
        line 1935: 133
        line 1936: 149
        line 1937: 159
        line 1938: 170
        line 1939: 185
        line 1940: 190
        line 1920: 192
      LocalVariableTable:
        Start  Length  Slot  Name   Signature
           93      24     6 prefix1b   [Ljava/lang/Object;
          159      28     8 prefix1b   [Ljava/lang/Object;
          133      58     7     s   I
            0     194     0  this   Lscala/collection/immutable/VectorStatics$;
            0     194     1 prefix1   [Ljava/lang/Object;
            0     194     2    xs   Lscala/collection/IterableOnce;
    Signature: #160                         // ([Ljava/lang/Object;Lscala/collection/IterableOnce<*>;)[Ljava/lang/Object;
    MethodParameters:
      Name                           Flags
      prefix1                        final
      xs                             final

  public final java.lang.Object[] append1IfSpace(java.lang.Object[], scala.collection.IterableOnce<?>);
    descriptor: ([Ljava/lang/Object;Lscala/collection/IterableOnce;)[Ljava/lang/Object;
    flags: (0x0011) ACC_PUBLIC, ACC_FINAL
    Code:
      stack=3, locals=9, args_size=3
         0: aload_2
         1: instanceof    #164                // class scala/collection/immutable/Iterable
         4: ifeq          116
         7: aload_2
         8: checkcast     #164                // class scala/collection/immutable/Iterable
        11: astore        4
        13: aload         4
        15: bipush        32
        17: aload_1
        18: arraylength
        19: isub
        20: invokeinterface #168,  2          // InterfaceMethod scala/collection/immutable/Iterable.sizeCompare:(I)I
        25: iconst_0
        26: if_icmpgt     111
        29: aload         4
        31: invokeinterface #172,  1          // InterfaceMethod scala/collection/immutable/Iterable.size:()I
        36: istore        5
        38: iload         5
        40: tableswitch   { // 0 to 1
                       0: 64
                       1: 68
                 default: 83
            }
        64: aconst_null
        65: goto          112
        68: aload_0
        69: aload_1
        70: aload         4
        72: invokeinterface #176,  1          // InterfaceMethod scala/collection/immutable/Iterable.head:()Ljava/lang/Object;
        77: invokevirtual #201                // Method copyAppend:([Ljava/lang/Object;Ljava/lang/Object;)[Ljava/lang/Object;
        80: goto          112
        83: aload_1
        84: aload_1
        85: arraylength
        86: iload         5
        88: iadd
        89: invokestatic  #66                 // Method java/util/Arrays.copyOf:([Ljava/lang/Object;I)[Ljava/lang/Object;
        92: astore        6
        94: aload         4
        96: aload         6
        98: aload_1
        99: arraylength
       100: invokeinterface #182,  3          // InterfaceMethod scala/collection/immutable/Iterable.copyToArray:(Ljava/lang/Object;I)I
       105: pop
       106: aload         6
       108: goto          112
       111: aconst_null
       112: astore_3
       113: goto          174
       116: aload_2
       117: invokeinterface #187,  1          // InterfaceMethod scala/collection/IterableOnce.knownSize:()I
       122: istore        7
       124: iload         7
       126: iconst_0
       127: if_icmple     172
       130: iload         7
       132: bipush        32
       134: aload_1
       135: arraylength
       136: isub
       137: if_icmpgt     172
       140: aload_1
       141: aload_1
       142: arraylength
       143: iload         7
       145: iadd
       146: invokestatic  #66                 // Method java/util/Arrays.copyOf:([Ljava/lang/Object;I)[Ljava/lang/Object;
       149: astore        8
       151: aload_2
       152: invokeinterface #191,  1          // InterfaceMethod scala/collection/IterableOnce.iterator:()Lscala/collection/Iterator;
       157: aload         8
       159: aload_1
       160: arraylength
       161: invokeinterface #194,  3          // InterfaceMethod scala/collection/Iterator.copyToArray:(Ljava/lang/Object;I)I
       166: pop
       167: aload         8
       169: goto          173
       172: aconst_null
       173: astore_3
       174: aload_3
       175: areturn
      StackMapTable: number_of_entries = 9
        frame_type = 254 /* append */
          offset_delta = 64
          locals = [ top, class scala/collection/immutable/Iterable, int ]
        frame_type = 3 /* same */
        frame_type = 14 /* same */
        frame_type = 250 /* chop */
          offset_delta = 27
        frame_type = 64 /* same_locals_1_stack_item */
          stack = [ class "[Ljava/lang/Object;" ]
        frame_type = 249 /* chop */
          offset_delta = 3
        frame_type = 255 /* full_frame */
          offset_delta = 55
          locals = [ class scala/collection/immutable/VectorStatics$, class "[Ljava/lang/Object;", class scala/collection/IterableOnce, top, top, top, top, int ]
          stack = []
        frame_type = 64 /* same_locals_1_stack_item */
          stack = [ class "[Ljava/lang/Object;" ]
        frame_type = 255 /* full_frame */
          offset_delta = 0
          locals = [ class scala/collection/immutable/VectorStatics$, class "[Ljava/lang/Object;", class scala/collection/IterableOnce, class "[Ljava/lang/Object;" ]
          stack = []
      LineNumberTable:
        line 1944: 0
        line 1945: 13
        line 1946: 29
        line 1947: 64
        line 1948: 68
        line 1950: 83
        line 1951: 94
        line 1952: 106
        line 1954: 111
        line 1956: 116
        line 1957: 124
        line 1958: 140
        line 1959: 151
        line 1960: 167
        line 1961: 172
        line 1943: 174
      LocalVariableTable:
        Start  Length  Slot  Name   Signature
           94      14     6 suffix1b   [Ljava/lang/Object;
          151      18     8 suffix1b   [Ljava/lang/Object;
          124      49     7     s   I
            0     176     0  this   Lscala/collection/immutable/VectorStatics$;
            0     176     1 suffix1   [Ljava/lang/Object;
            0     176     2    xs   Lscala/collection/IterableOnce;
    Signature: #160                         // ([Ljava/lang/Object;Lscala/collection/IterableOnce<*>;)[Ljava/lang/Object;
    MethodParameters:
      Name                           Flags
      suffix1                        final
      xs                             final

  private scala.collection.immutable.VectorStatics$();
    descriptor: ()V
    flags: (0x0002) ACC_PRIVATE
    Code:
      stack=1, locals=1, args_size=1
         0: aload_0
         1: invokespecial #203                // Method java/lang/Object."<init>":()V
         4: return
      LineNumberTable:
        line 1814: 0
      LocalVariableTable:
        Start  Length  Slot  Name   Signature
            0       5     0  this   Lscala/collection/immutable/VectorStatics$;
}
SourceFile: "Vector.scala"
  ScalaInlineInfo: length = 0x5E (unknown attribute)
   01 01 00 12 00 16 00 15 01 00 C6 00 9F 01 00 3B
   00 2D 01 00 2C 00 2D 01 00 45 00 44 01 00 43 00
   44 01 00 08 00 56 01 00 0A 00 57 01 00 0C 00 58
   01 00 0E 00 59 01 00 10 00 5A 01 00 12 00 5B 01
   00 5C 00 5D 01 00 78 00 79 01 00 6D 00 6E 01 00
   74 00 75 01 00 7E 00 7F 01 00 9E 00 9F 01
  Scala: length = 0x0 (unknown attribute)

