Classfile /Users/mw/Projects/slang-braindump/.jar/jar8/assemble/slang-braindump/assemble/content/scala/collection/immutable/VectorImpl.class
  Last modified May 29, 2022; size 1770 bytes
  SHA-256 checksum f1f09c6d4a7d2db4f0fb4484b1fc43ff6ac14d4985d4177c074d56808fe655be
  Compiled from "Vector.scala"
public abstract class scala.collection.immutable.VectorImpl<A extends java.lang.Object> extends scala.collection.immutable.Vector<A>
  minor version: 0
  major version: 52
  flags: (0x0421) ACC_PUBLIC, ACC_SUPER, ACC_ABSTRACT
  this_class: #2                          // scala/collection/immutable/VectorImpl
  super_class: #5                         // scala/collection/immutable/Vector
  interfaces: 0, fields: 0, methods: 3, attributes: 5
Constant pool:
   #1 = Utf8               scala/collection/immutable/VectorImpl
   #2 = Class              #1             // scala/collection/immutable/VectorImpl
   #3 = Utf8               <A:Ljava/lang/Object;>Lscala/collection/immutable/Vector<TA;>;
   #4 = Utf8               scala/collection/immutable/Vector
   #5 = Class              #4             // scala/collection/immutable/Vector
   #6 = Utf8               Vector.scala
   #7 = Utf8               Lscala/reflect/ScalaSignature;
   #8 = Utf8               bytes
   #9 = Utf8               \u0006\u0005\r3Q\u0001B\u0003\u0002*1A\u0011B\b\u0001\u0003\u0002\u0003\u0006IaH\u0018\t\u000bE\u0002A\u0011\u0001\u001a\t\u000bU\u0002AQ\t\u001c\u0003\u0015Y+7\r^8s\u00136\u0004HN\u0003\u0002\u0007\u000f\u0005I\u0011.\\7vi\u0006\u0014G.\u001a\u0006\u0003\u0011%\t!bY8mY\u0016\u001cG/[8o\u0015\u0005Q\u0011!B:dC2\f7\u0001A\u000b\u0003\u001bQ\u0019\"\u0001\u0001\b\u0011\u0007=\u0001\"#D\u0001\u0006\u0013\t\tRA\u0001\u0004WK\u000e$xN\u001d\t\u0003\'Qa\u0001\u0001\u0002\u0004\u0016\u0001\u0011\u0015\rA\u0006\u0002\u0002\u0003F\u0011qc\u0007\t\u00031ei\u0011!C\u0005\u00035%\u0011qAT8uQ&tw\r\u0005\u0002\u00199%\u0011Q$\u0003\u0002\u0004\u0003:L\u0018\u0001C0qe\u00164\u0017\u000e_\u0019\u0011\u0005\u0001bcBA\u0011+\u001d\t\u0011\u0013F\u0004\u0002$Q9\u0011AeJ\u0007\u0002K)\u0011aeC\u0001\u0007yI|w\u000e\u001e \n\u0003)I!\u0001C\u0005\n\u0005\u00199\u0011BA\u0016\u0006\u000311Vm\u0019;pe&sG.\u001b8f\u0013\ticF\u0001\u0003BeJ\f$BA\u0016\u0006\u0013\t\u0001\u0004#A\u0004qe\u00164\u0017\u000e_\u0019\u0002\rqJg.\u001b;?)\t\u0019D\u0007E\u0002\u0010\u0001IAQA\b\u0002A\u0002}\tQa\u001d7jG\u0016$2AD\u001c=\u0011\u0015A4\u00011\u0001:\u0003\u00111\'o\\7\u0011\u0005aQ\u0014BA\u001e\n\u0005\rIe\u000e\u001e\u0005\u0006{\r\u0001\r!O\u0001\u0006k:$\u0018\u000e\\\u0015\u0004\u0001}\n\u0015B\u0001!\u0006\u0005%\u0011\u0015n\u001a,fGR|\'/\u0003\u0002C\u000b\t9a+Z2u_J\f\u0004
  #10 = Utf8               slice
  #11 = Utf8               (II)Lscala/collection/immutable/Vector;
  #12 = Utf8               (II)Lscala/collection/immutable/Vector<TA;>;
  #13 = Utf8               from
  #14 = Utf8               until
  #15 = Utf8               java/lang/Math
  #16 = Class              #15            // java/lang/Math
  #17 = Utf8               max
  #18 = Utf8               (II)I
  #19 = NameAndType        #17:#18        // max:(II)I
  #20 = Methodref          #16.#19        // java/lang/Math.max:(II)I
  #21 = Utf8               length
  #22 = Utf8               ()I
  #23 = NameAndType        #21:#22        // length:()I
  #24 = Methodref          #2.#23         // scala/collection/immutable/VectorImpl.length:()I
  #25 = Utf8               min
  #26 = NameAndType        #25:#18        // min:(II)I
  #27 = Methodref          #16.#26        // java/lang/Math.min:(II)I
  #28 = Utf8               scala/collection/immutable/Vector0$
  #29 = Class              #28            // scala/collection/immutable/Vector0$
  #30 = Utf8               MODULE$
  #31 = Utf8               Lscala/collection/immutable/Vector0$;
  #32 = NameAndType        #30:#31        // MODULE$:Lscala/collection/immutable/Vector0$;
  #33 = Fieldref           #29.#32        // scala/collection/immutable/Vector0$.MODULE$:Lscala/collection/immutable/Vector0$;
  #34 = Utf8               slice0
  #35 = NameAndType        #34:#11        // slice0:(II)Lscala/collection/immutable/Vector;
  #36 = Methodref          #2.#35         // scala/collection/immutable/VectorImpl.slice0:(II)Lscala/collection/immutable/Vector;
  #37 = Utf8               lo
  #38 = Utf8               I
  #39 = Utf8               hi
  #40 = Utf8               this
  #41 = Utf8               Lscala/collection/immutable/VectorImpl;
  #42 = Utf8               (II)Ljava/lang/Object;
  #43 = NameAndType        #10:#11        // slice:(II)Lscala/collection/immutable/Vector;
  #44 = Methodref          #2.#43         // scala/collection/immutable/VectorImpl.slice:(II)Lscala/collection/immutable/Vector;
  #45 = Utf8               <init>
  #46 = Utf8               ([Ljava/lang/Object;)V
  #47 = Utf8               _prefix1
  #48 = NameAndType        #45:#46        // "<init>":([Ljava/lang/Object;)V
  #49 = Methodref          #5.#48         // scala/collection/immutable/Vector."<init>":([Ljava/lang/Object;)V
  #50 = Utf8               [Ljava/lang/Object;
  #51 = Utf8               Code
  #52 = Utf8               StackMapTable
  #53 = Utf8               LineNumberTable
  #54 = Utf8               LocalVariableTable
  #55 = Utf8               Signature
  #56 = Utf8               MethodParameters
  #57 = Utf8               SourceFile
  #58 = Utf8               RuntimeVisibleAnnotations
  #59 = Utf8               ScalaInlineInfo
  #60 = Utf8               ScalaSig
{
  public final scala.collection.immutable.Vector<A> slice(int, int);
    descriptor: (II)Lscala/collection/immutable/Vector;
    flags: (0x0011) ACC_PUBLIC, ACC_FINAL
    Code:
      stack=3, locals=5, args_size=3
         0: iload_1
         1: iconst_0
         2: invokestatic  #20                 // Method java/lang/Math.max:(II)I
         5: istore_3
         6: iload_2
         7: aload_0
         8: invokevirtual #24                 // Method length:()I
        11: invokestatic  #27                 // Method java/lang/Math.min:(II)I
        14: istore        4
        16: iload         4
        18: iload_3
        19: isub
        20: aload_0
        21: invokevirtual #24                 // Method length:()I
        24: if_icmpne     29
        27: aload_0
        28: areturn
        29: iload         4
        31: iload_3
        32: if_icmpgt     39
        35: getstatic     #33                 // Field scala/collection/immutable/Vector0$.MODULE$:Lscala/collection/immutable/Vector0$;
        38: areturn
        39: aload_0
        40: iload_3
        41: iload         4
        43: invokevirtual #36                 // Method slice0:(II)Lscala/collection/immutable/Vector;
        46: areturn
      StackMapTable: number_of_entries = 2
        frame_type = 253 /* append */
          offset_delta = 29
          locals = [ int, int ]
        frame_type = 9 /* same */
      LineNumberTable:
        line 309: 0
        line 310: 6
        line 311: 16
        line 312: 20
        line 313: 29
        line 314: 39
      LocalVariableTable:
        Start  Length  Slot  Name   Signature
            6      40     3    lo   I
           16      30     4    hi   I
            0      47     0  this   Lscala/collection/immutable/VectorImpl;
            0      47     1  from   I
            0      47     2 until   I
    Signature: #12                          // (II)Lscala/collection/immutable/Vector<TA;>;
    MethodParameters:
      Name                           Flags
      from                           final
      until                          final

  public final java.lang.Object slice(int, int);
    descriptor: (II)Ljava/lang/Object;
    flags: (0x1051) ACC_PUBLIC, ACC_FINAL, ACC_BRIDGE, ACC_SYNTHETIC
    Code:
      stack=3, locals=3, args_size=3
         0: aload_0
         1: iload_1
         2: iload_2
         3: invokevirtual #44                 // Method slice:(II)Lscala/collection/immutable/Vector;
         6: areturn
      LineNumberTable:
        line 306: 0
      LocalVariableTable:
        Start  Length  Slot  Name   Signature
            0       7     0  this   Lscala/collection/immutable/VectorImpl;
            0       7     1  from   I
            0       7     2 until   I
    MethodParameters:
      Name                           Flags
      from                           final
      until                          final

  public scala.collection.immutable.VectorImpl(java.lang.Object[]);
    descriptor: ([Ljava/lang/Object;)V
    flags: (0x0001) ACC_PUBLIC
    Code:
      stack=2, locals=2, args_size=2
         0: aload_0
         1: aload_1
         2: invokespecial #49                 // Method scala/collection/immutable/Vector."<init>":([Ljava/lang/Object;)V
         5: return
      LineNumberTable:
        line 306: 0
      LocalVariableTable:
        Start  Length  Slot  Name   Signature
            0       6     0  this   Lscala/collection/immutable/VectorImpl;
            0       6     1 _prefix1   [Ljava/lang/Object;
    MethodParameters:
      Name                           Flags
      _prefix1                       final
}
Signature: #3                           // <A:Ljava/lang/Object;>Lscala/collection/immutable/Vector<TA;>;
SourceFile: "Vector.scala"
RuntimeVisibleAnnotations:
  0: #7(#8=s#9)
    scala.reflect.ScalaSignature(
      bytes="\u0006\u0005\r3Q\u0001B\u0003\u0002*1A\u0011B\b\u0001\u0003\u0002\u0003\u0006IaH\u0018\t\u000bE\u0002A\u0011\u0001\u001a\t\u000bU\u0002AQ\t\u001c\u0003\u0015Y+7\r^8s\u00136\u0004HN\u0003\u0002\u0007\u000f\u0005I\u0011.\\7vi\u0006\u0014G.\u001a\u0006\u0003\u0011%\t!bY8mY\u0016\u001cG/[8o\u0015\u0005Q\u0011!B:dC2\f7\u0001A\u000b\u0003\u001bQ\u0019\"\u0001\u0001\b\u0011\u0007=\u0001\"#D\u0001\u0006\u0013\t\tRA\u0001\u0004WK\u000e$xN\u001d\t\u0003\'Qa\u0001\u0001\u0002\u0004\u0016\u0001\u0011\u0015\rA\u0006\u0002\u0002\u0003F\u0011qc\u0007\t\u00031ei\u0011!C\u0005\u00035%\u0011qAT8uQ&tw\r\u0005\u0002\u00199%\u0011Q$\u0003\u0002\u0004\u0003:L\u0018\u0001C0qe\u00164\u0017\u000e_\u0019\u0011\u0005\u0001bcBA\u0011+\u001d\t\u0011\u0013F\u0004\u0002$Q9\u0011AeJ\u0007\u0002K)\u0011aeC\u0001\u0007yI|w\u000e\u001e \n\u0003)I!\u0001C\u0005\n\u0005\u00199\u0011BA\u0016\u0006\u000311Vm\u0019;pe&sG.\u001b8f\u0013\ticF\u0001\u0003BeJ\f$BA\u0016\u0006\u0013\t\u0001\u0004#A\u0004qe\u00164\u0017\u000e_\u0019\u0002\rqJg.\u001b;?)\t\u0019D\u0007E\u0002\u0010\u0001IAQA\b\u0002A\u0002}\tQa\u001d7jG\u0016$2AD\u001c=\u0011\u0015A4\u00011\u0001:\u0003\u00111\'o\\7\u0011\u0005aQ\u0014BA\u001e\n\u0005\rIe\u000e\u001e\u0005\u0006{\r\u0001\r!O\u0001\u0006k:$\u0018\u000e\\\u0015\u0004\u0001}\n\u0015B\u0001!\u0006\u0005%\u0011\u0015n\u001a,fGR|\'/\u0003\u0002C\u000b\t9a+Z2u_J\f\u0004"
    )
  ScalaInlineInfo: length = 0x13 (unknown attribute)
   01 00 00 03 00 2D 00 2E 00 00 0A 00 2A 01 00 0A
   00 0B 01
  ScalaSig: length = 0x3 (unknown attribute)
   05 02 00
