Classfile /Users/mw/Projects/slang-braindump/.jar/jar11/assemble/slang-braindump/assemble/content/org/apache/commons/lang3/time/TimeZones.class
  Last modified May 29, 2022; size 387 bytes
  SHA-256 checksum 9da83d9f7f50cbc80563f2deb3a8589387a80afd1c1527d1ab2c99a1e34bfb6c
  Compiled from "TimeZones.java"
public class org.apache.commons.lang3.time.TimeZones
  minor version: 0
  major version: 52
  flags: (0x0021) ACC_PUBLIC, ACC_SUPER
  this_class: #2                          // org/apache/commons/lang3/time/TimeZones
  super_class: #3                         // java/lang/Object
  interfaces: 0, fields: 1, methods: 1, attributes: 1
Constant pool:
   #1 = Methodref          #3.#17         // java/lang/Object."<init>":()V
   #2 = Class              #18            // org/apache/commons/lang3/time/TimeZones
   #3 = Class              #19            // java/lang/Object
   #4 = Utf8               GMT_ID
   #5 = Utf8               Ljava/lang/String;
   #6 = Utf8               ConstantValue
   #7 = String             #20            // GMT
   #8 = Utf8               <init>
   #9 = Utf8               ()V
  #10 = Utf8               Code
  #11 = Utf8               LineNumberTable
  #12 = Utf8               LocalVariableTable
  #13 = Utf8               this
  #14 = Utf8               Lorg/apache/commons/lang3/time/TimeZones;
  #15 = Utf8               SourceFile
  #16 = Utf8               TimeZones.java
  #17 = NameAndType        #8:#9          // "<init>":()V
  #18 = Utf8               org/apache/commons/lang3/time/TimeZones
  #19 = Utf8               java/lang/Object
  #20 = Utf8               GMT
{
  public static final java.lang.String GMT_ID;
    descriptor: Ljava/lang/String;
    flags: (0x0019) ACC_PUBLIC, ACC_STATIC, ACC_FINAL
    ConstantValue: String GMT

  private org.apache.commons.lang3.time.TimeZones();
    descriptor: ()V
    flags: (0x0002) ACC_PRIVATE
    Code:
      stack=1, locals=1, args_size=1
         0: aload_0
         1: invokespecial #1                  // Method java/lang/Object."<init>":()V
         4: return
      LineNumberTable:
        line 28: 0
        line 29: 4
      LocalVariableTable:
        Start  Length  Slot  Name   Signature
            0       5     0  this   Lorg/apache/commons/lang3/time/TimeZones;
}
SourceFile: "TimeZones.java"
