Classfile /Users/mw/Projects/slang-braindump/.jar/jar11/run/slang-braindump/modules/jar/classes/jar/JarApp.class
  Last modified May 29, 2022; size 1044 bytes
  SHA-256 checksum db547cc9fa0802f7a449c8471e0638b378074ab7ccaf6b33c357b996e8c9d825
  Compiled from "JarApp.scala"
public final class jar.JarApp
  minor version: 0
  major version: 55
  flags: (0x0031) ACC_PUBLIC, ACC_FINAL, ACC_SUPER
  this_class: #2                          // jar/JarApp
  super_class: #4                         // java/lang/Object
  interfaces: 0, fields: 0, methods: 3, attributes: 3
Constant pool:
   #1 = Utf8               jar/JarApp
   #2 = Class              #1             // jar/JarApp
   #3 = Utf8               java/lang/Object
   #4 = Class              #3             // java/lang/Object
   #5 = Utf8               JarApp.scala
   #6 = Utf8               Lscala/reflect/ScalaSignature;
   #7 = Utf8               bytes
   #8 = Utf8               \u0006\u0005]:Q\u0001B\u0003\t\u0002!1QAC\u0003\t\u0002-AQAG\u0001\u0005\u0002mAQ\u0001H\u0001\u0005\u0002u\taAS1s\u0003B\u0004(\"\u0001\u0004\u0002\u0007)\f\'o\u0001\u0001\u0011\u0005%\tQ\"A\u0003\u0003\r)\u000b\'/\u00119q\'\r\tAB\u0005\t\u0003\u001bAi\u0011A\u0004\u0006\u0002\u001f\u0005)1oY1mC&\u0011\u0011C\u0004\u0002\u0007\u0003:L(+\u001a4\u0011\u0005MAR\"\u0001\u000b\u000b\u0005U1\u0012AB:je\u0016,XNC\u0001\u0018\u0003\ry\'oZ\u0005\u00033Q\u00111!\u00119q\u0003\u0019a\u0014N\\5u}Q\t\u0001\"\u0001\u0003nC&tGC\u0001\u0010\"!\t\u0019r$\u0003\u0002!)\t\t!\fC\u0003#\u0007\u0001\u00071%\u0001\u0003be\u001e\u001c\bc\u0001\u0013/i9\u0011Q\u0005\f\b\u0003M-r!a\n\u0016\u000e\u0003!R!!K\u0004\u0002\rq\u0012xn\u001c;?\u0013\u00059\u0012BA\u000b\u0017\u0013\tiC#A\u0004qC\u000e\\\u0017mZ3\n\u0005=\u0002$aA%T5&\u0011\u0011G\r\u0002\r!\u0006\u001c7.Y4f)J\f\u0017\u000e\u001e\u0006\u0003gQ\t\u0011\u0002J5oi\u0016\u0014h.\u00197\u0011\u0005M)\u0014B\u0001\u001c\u0015\u0005\u0019\u0019FO]5oO\u0002
   #9 = Utf8               main
  #10 = Utf8               (Lorg/sireum/IS;)Lorg/sireum/Z;
  #11 = Utf8               (Lorg/sireum/IS<Lorg/sireum/Z;Lorg/sireum/String;>;)Lorg/sireum/Z;
  #12 = Utf8               args
  #13 = Utf8               jar/JarApp$
  #14 = Class              #13            // jar/JarApp$
  #15 = Utf8               MODULE$
  #16 = Utf8               Ljar/JarApp$;
  #17 = NameAndType        #15:#16        // MODULE$:Ljar/JarApp$;
  #18 = Fieldref           #14.#17        // jar/JarApp$.MODULE$:Ljar/JarApp$;
  #19 = NameAndType        #9:#10         // main:(Lorg/sireum/IS;)Lorg/sireum/Z;
  #20 = Methodref          #14.#19        // jar/JarApp$.main:(Lorg/sireum/IS;)Lorg/sireum/Z;
  #21 = Utf8               Lorg/sireum/IS;
  #22 = Utf8               atExit
  #23 = Utf8               ()V
  #24 = NameAndType        #22:#23        // atExit:()V
  #25 = Methodref          #14.#24        // jar/JarApp$.atExit:()V
  #26 = Utf8               ([Ljava/lang/String;)V
  #27 = NameAndType        #9:#26         // main:([Ljava/lang/String;)V
  #28 = Methodref          #14.#27        // jar/JarApp$.main:([Ljava/lang/String;)V
  #29 = Utf8               [Ljava/lang/String;
  #30 = Utf8               Code
  #31 = Utf8               LocalVariableTable
  #32 = Utf8               Signature
  #33 = Utf8               MethodParameters
  #34 = Utf8               SourceFile
  #35 = Utf8               RuntimeVisibleAnnotations
  #36 = Utf8               ScalaSig
{
  public static org.sireum.Z main(org.sireum.IS<org.sireum.Z, org.sireum.String>);
    descriptor: (Lorg/sireum/IS;)Lorg/sireum/Z;
    flags: (0x0009) ACC_PUBLIC, ACC_STATIC
    Code:
      stack=2, locals=1, args_size=1
         0: getstatic     #18                 // Field jar/JarApp$.MODULE$:Ljar/JarApp$;
         3: aload_0
         4: invokevirtual #20                 // Method jar/JarApp$.main:(Lorg/sireum/IS;)Lorg/sireum/Z;
         7: areturn
      LocalVariableTable:
        Start  Length  Slot  Name   Signature
            0       8     0  args   Lorg/sireum/IS;
    Signature: #11                          // (Lorg/sireum/IS<Lorg/sireum/Z;Lorg/sireum/String;>;)Lorg/sireum/Z;
    MethodParameters:
      Name                           Flags
      args                           final

  public static void atExit();
    descriptor: ()V
    flags: (0x0009) ACC_PUBLIC, ACC_STATIC
    Code:
      stack=1, locals=0, args_size=0
         0: getstatic     #18                 // Field jar/JarApp$.MODULE$:Ljar/JarApp$;
         3: invokevirtual #25                 // Method jar/JarApp$.atExit:()V
         6: return

  public static void main(java.lang.String[]);
    descriptor: ([Ljava/lang/String;)V
    flags: (0x0009) ACC_PUBLIC, ACC_STATIC
    Code:
      stack=2, locals=1, args_size=1
         0: getstatic     #18                 // Field jar/JarApp$.MODULE$:Ljar/JarApp$;
         3: aload_0
         4: invokevirtual #28                 // Method jar/JarApp$.main:([Ljava/lang/String;)V
         7: return
      LocalVariableTable:
        Start  Length  Slot  Name   Signature
            0       8     0  args   [Ljava/lang/String;
    MethodParameters:
      Name                           Flags
      args                           final
}
SourceFile: "JarApp.scala"
RuntimeVisibleAnnotations:
  0: #6(#7=s#8)
    scala.reflect.ScalaSignature(
      bytes="\u0006\u0005]:Q\u0001B\u0003\t\u0002!1QAC\u0003\t\u0002-AQAG\u0001\u0005\u0002mAQ\u0001H\u0001\u0005\u0002u\taAS1s\u0003B\u0004(\"\u0001\u0004\u0002\u0007)\f\'o\u0001\u0001\u0011\u0005%\tQ\"A\u0003\u0003\r)\u000b\'/\u00119q\'\r\tAB\u0005\t\u0003\u001bAi\u0011A\u0004\u0006\u0002\u001f\u0005)1oY1mC&\u0011\u0011C\u0004\u0002\u0007\u0003:L(+\u001a4\u0011\u0005MAR\"\u0001\u000b\u000b\u0005U1\u0012AB:je\u0016,XNC\u0001\u0018\u0003\ry\'oZ\u0005\u00033Q\u00111!\u00119q\u0003\u0019a\u0014N\\5u}Q\t\u0001\"\u0001\u0003nC&tGC\u0001\u0010\"!\t\u0019r$\u0003\u0002!)\t\t!\fC\u0003#\u0007\u0001\u00071%\u0001\u0003be\u001e\u001c\bc\u0001\u0013/i9\u0011Q\u0005\f\b\u0003M-r!a\n\u0016\u000e\u0003!R!!K\u0004\u0002\rq\u0012xn\u001c;?\u0013\u00059\u0012BA\u000b\u0017\u0013\tiC#A\u0004qC\u000e\\\u0017mZ3\n\u0005=\u0002$aA%T5&\u0011\u0011G\r\u0002\r!\u0006\u001c7.Y4f)J\f\u0017\u000e\u001e\u0006\u0003gQ\t\u0011\u0002J5oi\u0016\u0014h.\u00197\u0011\u0005M)\u0014B\u0001\u001c\u0015\u0005\u0019\u0019FO]5oO\u0002"
    )
  ScalaSig: length = 0x3 (unknown attribute)
   05 02 00
