Classfile /Users/mw/Projects/slang-braindump/.jar/jar8/assemble/slang-braindump/assemble/content/scala/collection/AbstractMapView.class
  Last modified May 29, 2022; size 17772 bytes
  SHA-256 checksum dd2d8ab179586d2d0752a25d3bb65dc529e65fbe4db0965e821c5b2baba759b7
  Compiled from "MapView.scala"
public abstract class scala.collection.AbstractMapView<K extends java.lang.Object, V extends java.lang.Object> extends scala.collection.AbstractView<scala.Tuple2<K, V>> implements scala.collection.MapView<K, V>
  minor version: 0
  major version: 52
  flags: (0x0421) ACC_PUBLIC, ACC_SUPER, ACC_ABSTRACT
  this_class: #2                          // scala/collection/AbstractMapView
  super_class: #5                         // scala/collection/AbstractView
  interfaces: 1, fields: 1, methods: 81, attributes: 6
Constant pool:
    #1 = Utf8               scala/collection/AbstractMapView
    #2 = Class              #1            // scala/collection/AbstractMapView
    #3 = Utf8               <K:Ljava/lang/Object;V:Ljava/lang/Object;>Lscala/collection/AbstractView<Lscala/Tuple2<TK;TV;>;>;Lscala/collection/MapView<TK;TV;>;
    #4 = Utf8               scala/collection/AbstractView
    #5 = Class              #4            // scala/collection/AbstractView
    #6 = Utf8               scala/collection/MapView
    #7 = Class              #6            // scala/collection/MapView
    #8 = Utf8               MapView.scala
    #9 = Utf8               Lscala/reflect/ScalaSignature;
   #10 = Utf8               bytes
   #11 = Utf8               \u0006\u000512QAA\u0002\u0002\u0002!AQa\t\u0001\u0005\u0002\u0011\u0012q\"\u00112tiJ\f7\r^\'baZKWm\u001e\u0006\u0003\t\u0015\t!bY8mY\u0016\u001cG/[8o\u0015\u00051\u0011!B:dC2\f7\u0001A\u000b\u0004\u0013Qq2c\u0001\u0001\u000bAA\u00191\u0002\u0004\b\u000e\u0003\rI!!D\u0002\u0003\u0019\u0005\u00137\u000f\u001e:bGR4\u0016.Z<\u0011\t=\u0001\"#H\u0007\u0002\u000b%\u0011\u0011#\u0002\u0002\u0007)V\u0004H.\u001a\u001a\u0011\u0005M!B\u0002\u0001\u0003\u0006+\u0001\u0011\rA\u0006\u0002\u0002\u0017F\u0011qC\u0007\t\u0003\u001faI!!G\u0003\u0003\u000f9{G\u000f[5oOB\u0011qbG\u0005\u00039\u0015\u00111!\u00118z!\t\u0019b\u0004\u0002\u0004 \u0001\u0011\u0015\rA\u0006\u0002\u0002-B!1\"\t\n\u001e\u0013\t\u00113AA\u0004NCB4\u0016.Z<\u0002\rqJg.\u001b;?)\u0005)\u0003\u0003B\u0006\u0001%uAC\u0001A\u0014+WA\u0011q\u0002K\u0005\u0003S\u0015\u0011\u0001cU3sS\u0006dg+\u001a:tS>tW+\u0013#\u0002\u000bY\fG.^3\u001f\u0003\r\u0001
   #12 = Utf8               scala/collection/MapOps$WithFilter
   #13 = Class              #12           // scala/collection/MapOps$WithFilter
   #14 = Utf8               scala/collection/MapOps
   #15 = Class              #14           // scala/collection/MapOps
   #16 = Utf8               WithFilter
   #17 = Utf8               serialVersionUID
   #18 = Utf8               J
   #19 = Long               3l
   #21 = Utf8               view
   #22 = Utf8               ()Lscala/collection/MapView;
   #23 = Utf8               ()Lscala/collection/MapView<TK;TV;>;
   #24 = Utf8               view$
   #25 = Utf8               (Lscala/collection/MapView;)Lscala/collection/MapView;
   #26 = NameAndType        #24:#25       // view$:(Lscala/collection/MapView;)Lscala/collection/MapView;
   #27 = InterfaceMethodref #7.#26        // scala/collection/MapView.view$:(Lscala/collection/MapView;)Lscala/collection/MapView;
   #28 = Utf8               this
   #29 = Utf8               Lscala/collection/AbstractMapView;
   #30 = Utf8               keys
   #31 = Utf8               ()Lscala/collection/Iterable;
   #32 = Utf8               ()Lscala/collection/Iterable<TK;>;
   #33 = Utf8               keys$
   #34 = Utf8               (Lscala/collection/MapView;)Lscala/collection/Iterable;
   #35 = NameAndType        #33:#34       // keys$:(Lscala/collection/MapView;)Lscala/collection/Iterable;
   #36 = InterfaceMethodref #7.#35        // scala/collection/MapView.keys$:(Lscala/collection/MapView;)Lscala/collection/Iterable;
   #37 = Utf8               values
   #38 = Utf8               ()Lscala/collection/Iterable<TV;>;
   #39 = Utf8               values$
   #40 = NameAndType        #39:#34       // values$:(Lscala/collection/MapView;)Lscala/collection/Iterable;
   #41 = InterfaceMethodref #7.#40        // scala/collection/MapView.values$:(Lscala/collection/MapView;)Lscala/collection/Iterable;
   #42 = Utf8               filterKeys
   #43 = Utf8               (Lscala/Function1;)Lscala/collection/MapView;
   #44 = Utf8               (Lscala/Function1<TK;Ljava/lang/Object;>;)Lscala/collection/MapView<TK;TV;>;
   #45 = Utf8               p
   #46 = Utf8               filterKeys$
   #47 = Utf8               (Lscala/collection/MapView;Lscala/Function1;)Lscala/collection/MapView;
   #48 = NameAndType        #46:#47       // filterKeys$:(Lscala/collection/MapView;Lscala/Function1;)Lscala/collection/MapView;
   #49 = InterfaceMethodref #7.#48        // scala/collection/MapView.filterKeys$:(Lscala/collection/MapView;Lscala/Function1;)Lscala/collection/MapView;
   #50 = Utf8               Lscala/Function1;
   #51 = Utf8               mapValues
   #52 = Utf8               <W:Ljava/lang/Object;>(Lscala/Function1<TV;TW;>;)Lscala/collection/MapView<TK;TW;>;
   #53 = Utf8               f
   #54 = Utf8               mapValues$
   #55 = NameAndType        #54:#47       // mapValues$:(Lscala/collection/MapView;Lscala/Function1;)Lscala/collection/MapView;
   #56 = InterfaceMethodref #7.#55        // scala/collection/MapView.mapValues$:(Lscala/collection/MapView;Lscala/Function1;)Lscala/collection/MapView;
   #57 = Utf8               filter
   #58 = Utf8               (Lscala/Function1<Lscala/Tuple2<TK;TV;>;Ljava/lang/Object;>;)Lscala/collection/MapView<TK;TV;>;
   #59 = Utf8               pred
   #60 = Utf8               filter$
   #61 = NameAndType        #60:#47       // filter$:(Lscala/collection/MapView;Lscala/Function1;)Lscala/collection/MapView;
   #62 = InterfaceMethodref #7.#61        // scala/collection/MapView.filter$:(Lscala/collection/MapView;Lscala/Function1;)Lscala/collection/MapView;
   #63 = Utf8               filterNot
   #64 = Utf8               filterNot$
   #65 = NameAndType        #64:#47       // filterNot$:(Lscala/collection/MapView;Lscala/Function1;)Lscala/collection/MapView;
   #66 = InterfaceMethodref #7.#65        // scala/collection/MapView.filterNot$:(Lscala/collection/MapView;Lscala/Function1;)Lscala/collection/MapView;
   #67 = Utf8               partition
   #68 = Utf8               (Lscala/Function1;)Lscala/Tuple2;
   #69 = Utf8               (Lscala/Function1<Lscala/Tuple2<TK;TV;>;Ljava/lang/Object;>;)Lscala/Tuple2<Lscala/collection/MapView<TK;TV;>;Lscala/collection/MapView<TK;TV;>;>;
   #70 = Utf8               partition$
   #71 = Utf8               (Lscala/collection/MapView;Lscala/Function1;)Lscala/Tuple2;
   #72 = NameAndType        #70:#71       // partition$:(Lscala/collection/MapView;Lscala/Function1;)Lscala/Tuple2;
   #73 = InterfaceMethodref #7.#72        // scala/collection/MapView.partition$:(Lscala/collection/MapView;Lscala/Function1;)Lscala/Tuple2;
   #74 = Utf8               tapEach
   #75 = Utf8               <U:Ljava/lang/Object;>(Lscala/Function1<Lscala/Tuple2<TK;TV;>;TU;>;)Lscala/collection/MapView<TK;TV;>;
   #76 = Utf8               tapEach$
   #77 = NameAndType        #76:#47       // tapEach$:(Lscala/collection/MapView;Lscala/Function1;)Lscala/collection/MapView;
   #78 = InterfaceMethodref #7.#77        // scala/collection/MapView.tapEach$:(Lscala/collection/MapView;Lscala/Function1;)Lscala/collection/MapView;
   #79 = Utf8               mapFactory
   #80 = Utf8               ()Lscala/collection/MapViewFactory;
   #81 = Utf8               mapFactory$
   #82 = Utf8               (Lscala/collection/MapView;)Lscala/collection/MapViewFactory;
   #83 = NameAndType        #81:#82       // mapFactory$:(Lscala/collection/MapView;)Lscala/collection/MapViewFactory;
   #84 = InterfaceMethodref #7.#83        // scala/collection/MapView.mapFactory$:(Lscala/collection/MapView;)Lscala/collection/MapViewFactory;
   #85 = Utf8               empty
   #86 = Utf8               empty$
   #87 = NameAndType        #86:#25       // empty$:(Lscala/collection/MapView;)Lscala/collection/MapView;
   #88 = InterfaceMethodref #7.#87        // scala/collection/MapView.empty$:(Lscala/collection/MapView;)Lscala/collection/MapView;
   #89 = Utf8               withFilter
   #90 = Utf8               (Lscala/Function1;)Lscala/collection/MapOps$WithFilter;
   #91 = Utf8               (Lscala/Function1<Lscala/Tuple2<TK;TV;>;Ljava/lang/Object;>;)Lscala/collection/MapOps$WithFilter<TK;TV;Lscala/collection/View;*>;
   #92 = Utf8               withFilter$
   #93 = Utf8               (Lscala/collection/MapView;Lscala/Function1;)Lscala/collection/MapOps$WithFilter;
   #94 = NameAndType        #92:#93       // withFilter$:(Lscala/collection/MapView;Lscala/Function1;)Lscala/collection/MapOps$WithFilter;
   #95 = InterfaceMethodref #7.#94        // scala/collection/MapView.withFilter$:(Lscala/collection/MapView;Lscala/Function1;)Lscala/collection/MapOps$WithFilter;
   #96 = Utf8               toString
   #97 = Utf8               ()Ljava/lang/String;
   #98 = Utf8               toString$
   #99 = Utf8               (Lscala/collection/MapView;)Ljava/lang/String;
  #100 = NameAndType        #98:#99       // toString$:(Lscala/collection/MapView;)Ljava/lang/String;
  #101 = InterfaceMethodref #7.#100       // scala/collection/MapView.toString$:(Lscala/collection/MapView;)Ljava/lang/String;
  #102 = Utf8               stringPrefix
  #103 = Utf8               stringPrefix$
  #104 = NameAndType        #103:#99      // stringPrefix$:(Lscala/collection/MapView;)Ljava/lang/String;
  #105 = InterfaceMethodref #7.#104       // scala/collection/MapView.stringPrefix$:(Lscala/collection/MapView;)Ljava/lang/String;
  #106 = Utf8               keyStepper
  #107 = Utf8               (Lscala/collection/StepperShape;)Lscala/collection/Stepper;
  #108 = Utf8               <S::Lscala/collection/Stepper<*>;>(Lscala/collection/StepperShape<TK;TS;>;)TS;
  #109 = Utf8               shape
  #110 = Utf8               keyStepper$
  #111 = Utf8               (Lscala/collection/MapOps;Lscala/collection/StepperShape;)Lscala/collection/Stepper;
  #112 = NameAndType        #110:#111     // keyStepper$:(Lscala/collection/MapOps;Lscala/collection/StepperShape;)Lscala/collection/Stepper;
  #113 = InterfaceMethodref #15.#112      // scala/collection/MapOps.keyStepper$:(Lscala/collection/MapOps;Lscala/collection/StepperShape;)Lscala/collection/Stepper;
  #114 = Utf8               Lscala/collection/StepperShape;
  #115 = Utf8               valueStepper
  #116 = Utf8               <S::Lscala/collection/Stepper<*>;>(Lscala/collection/StepperShape<TV;TS;>;)TS;
  #117 = Utf8               valueStepper$
  #118 = NameAndType        #117:#111     // valueStepper$:(Lscala/collection/MapOps;Lscala/collection/StepperShape;)Lscala/collection/Stepper;
  #119 = InterfaceMethodref #15.#118      // scala/collection/MapOps.valueStepper$:(Lscala/collection/MapOps;Lscala/collection/StepperShape;)Lscala/collection/Stepper;
  #120 = Utf8               mapFromIterable
  #121 = Utf8               (Lscala/collection/Iterable;)Lscala/collection/IterableOps;
  #122 = Utf8               it
  #123 = Utf8               mapFromIterable$
  #124 = Utf8               (Lscala/collection/MapOps;Lscala/collection/Iterable;)Lscala/collection/IterableOps;
  #125 = NameAndType        #123:#124     // mapFromIterable$:(Lscala/collection/MapOps;Lscala/collection/Iterable;)Lscala/collection/IterableOps;
  #126 = InterfaceMethodref #15.#125      // scala/collection/MapOps.mapFromIterable$:(Lscala/collection/MapOps;Lscala/collection/Iterable;)Lscala/collection/IterableOps;
  #127 = Utf8               Lscala/collection/Iterable;
  #128 = Utf8               getOrElse
  #129 = Utf8               (Ljava/lang/Object;Lscala/Function0;)Ljava/lang/Object;
  #130 = Utf8               <V1:Ljava/lang/Object;>(TK;Lscala/Function0<TV1;>;)TV1;
  #131 = Utf8               key
  #132 = Utf8               default
  #133 = Utf8               getOrElse$
  #134 = Utf8               (Lscala/collection/MapOps;Ljava/lang/Object;Lscala/Function0;)Ljava/lang/Object;
  #135 = NameAndType        #133:#134     // getOrElse$:(Lscala/collection/MapOps;Ljava/lang/Object;Lscala/Function0;)Ljava/lang/Object;
  #136 = InterfaceMethodref #15.#135      // scala/collection/MapOps.getOrElse$:(Lscala/collection/MapOps;Ljava/lang/Object;Lscala/Function0;)Ljava/lang/Object;
  #137 = Utf8               Ljava/lang/Object;
  #138 = Utf8               Lscala/Function0;
  #139 = Utf8               apply
  #140 = Utf8               (Ljava/lang/Object;)Ljava/lang/Object;
  #141 = Utf8               (TK;)TV;^Ljava/util/NoSuchElementException;
  #142 = Utf8               java/util/NoSuchElementException
  #143 = Class              #142          // java/util/NoSuchElementException
  #144 = Utf8               apply$
  #145 = Utf8               (Lscala/collection/MapOps;Ljava/lang/Object;)Ljava/lang/Object;
  #146 = NameAndType        #144:#145     // apply$:(Lscala/collection/MapOps;Ljava/lang/Object;)Ljava/lang/Object;
  #147 = InterfaceMethodref #15.#146      // scala/collection/MapOps.apply$:(Lscala/collection/MapOps;Ljava/lang/Object;)Ljava/lang/Object;
  #148 = Utf8               applyOrElse
  #149 = Utf8               (Ljava/lang/Object;Lscala/Function1;)Ljava/lang/Object;
  #150 = Utf8               <K1:TK;V1:Ljava/lang/Object;>(TK1;Lscala/Function1<TK1;TV1;>;)TV1;
  #151 = Utf8               x
  #152 = Utf8               applyOrElse$
  #153 = Utf8               (Lscala/collection/MapOps;Ljava/lang/Object;Lscala/Function1;)Ljava/lang/Object;
  #154 = NameAndType        #152:#153     // applyOrElse$:(Lscala/collection/MapOps;Ljava/lang/Object;Lscala/Function1;)Ljava/lang/Object;
  #155 = InterfaceMethodref #15.#154      // scala/collection/MapOps.applyOrElse$:(Lscala/collection/MapOps;Ljava/lang/Object;Lscala/Function1;)Ljava/lang/Object;
  #156 = Utf8               keySet
  #157 = Utf8               ()Lscala/collection/Set;
  #158 = Utf8               ()Lscala/collection/Set<TK;>;
  #159 = Utf8               keySet$
  #160 = Utf8               (Lscala/collection/MapOps;)Lscala/collection/Set;
  #161 = NameAndType        #159:#160     // keySet$:(Lscala/collection/MapOps;)Lscala/collection/Set;
  #162 = InterfaceMethodref #15.#161      // scala/collection/MapOps.keySet$:(Lscala/collection/MapOps;)Lscala/collection/Set;
  #163 = Utf8               keysIterator
  #164 = Utf8               ()Lscala/collection/Iterator;
  #165 = Utf8               ()Lscala/collection/Iterator<TK;>;
  #166 = Utf8               keysIterator$
  #167 = Utf8               (Lscala/collection/MapOps;)Lscala/collection/Iterator;
  #168 = NameAndType        #166:#167     // keysIterator$:(Lscala/collection/MapOps;)Lscala/collection/Iterator;
  #169 = InterfaceMethodref #15.#168      // scala/collection/MapOps.keysIterator$:(Lscala/collection/MapOps;)Lscala/collection/Iterator;
  #170 = Utf8               valuesIterator
  #171 = Utf8               ()Lscala/collection/Iterator<TV;>;
  #172 = Utf8               valuesIterator$
  #173 = NameAndType        #172:#167     // valuesIterator$:(Lscala/collection/MapOps;)Lscala/collection/Iterator;
  #174 = InterfaceMethodref #15.#173      // scala/collection/MapOps.valuesIterator$:(Lscala/collection/MapOps;)Lscala/collection/Iterator;
  #175 = Utf8               foreachEntry
  #176 = Utf8               (Lscala/Function2;)V
  #177 = Utf8               <U:Ljava/lang/Object;>(Lscala/Function2<TK;TV;TU;>;)V
  #178 = Utf8               foreachEntry$
  #179 = Utf8               (Lscala/collection/MapOps;Lscala/Function2;)V
  #180 = NameAndType        #178:#179     // foreachEntry$:(Lscala/collection/MapOps;Lscala/Function2;)V
  #181 = InterfaceMethodref #15.#180      // scala/collection/MapOps.foreachEntry$:(Lscala/collection/MapOps;Lscala/Function2;)V
  #182 = Utf8               Lscala/Function2;
  #183 = Utf8               default$
  #184 = NameAndType        #183:#145     // default$:(Lscala/collection/MapOps;Ljava/lang/Object;)Ljava/lang/Object;
  #185 = InterfaceMethodref #15.#184      // scala/collection/MapOps.default$:(Lscala/collection/MapOps;Ljava/lang/Object;)Ljava/lang/Object;
  #186 = Utf8               contains
  #187 = Utf8               (Ljava/lang/Object;)Z
  #188 = Utf8               (TK;)Z
  #189 = Utf8               contains$
  #190 = Utf8               (Lscala/collection/MapOps;Ljava/lang/Object;)Z
  #191 = NameAndType        #189:#190     // contains$:(Lscala/collection/MapOps;Ljava/lang/Object;)Z
  #192 = InterfaceMethodref #15.#191      // scala/collection/MapOps.contains$:(Lscala/collection/MapOps;Ljava/lang/Object;)Z
  #193 = Utf8               isDefinedAt
  #194 = Utf8               isDefinedAt$
  #195 = NameAndType        #194:#190     // isDefinedAt$:(Lscala/collection/MapOps;Ljava/lang/Object;)Z
  #196 = InterfaceMethodref #15.#195      // scala/collection/MapOps.isDefinedAt$:(Lscala/collection/MapOps;Ljava/lang/Object;)Z
  #197 = Utf8               map
  #198 = Utf8               (Lscala/Function1;)Lscala/collection/IterableOps;
  #199 = Utf8               map$
  #200 = Utf8               (Lscala/collection/MapOps;Lscala/Function1;)Lscala/collection/IterableOps;
  #201 = NameAndType        #199:#200     // map$:(Lscala/collection/MapOps;Lscala/Function1;)Lscala/collection/IterableOps;
  #202 = InterfaceMethodref #15.#201      // scala/collection/MapOps.map$:(Lscala/collection/MapOps;Lscala/Function1;)Lscala/collection/IterableOps;
  #203 = Utf8               collect
  #204 = Utf8               (Lscala/PartialFunction;)Lscala/collection/IterableOps;
  #205 = Utf8               pf
  #206 = Utf8               collect$
  #207 = Utf8               (Lscala/collection/MapOps;Lscala/PartialFunction;)Lscala/collection/IterableOps;
  #208 = NameAndType        #206:#207     // collect$:(Lscala/collection/MapOps;Lscala/PartialFunction;)Lscala/collection/IterableOps;
  #209 = InterfaceMethodref #15.#208      // scala/collection/MapOps.collect$:(Lscala/collection/MapOps;Lscala/PartialFunction;)Lscala/collection/IterableOps;
  #210 = Utf8               Lscala/PartialFunction;
  #211 = Utf8               flatMap
  #212 = Utf8               flatMap$
  #213 = NameAndType        #212:#200     // flatMap$:(Lscala/collection/MapOps;Lscala/Function1;)Lscala/collection/IterableOps;
  #214 = InterfaceMethodref #15.#213      // scala/collection/MapOps.flatMap$:(Lscala/collection/MapOps;Lscala/Function1;)Lscala/collection/IterableOps;
  #215 = Utf8               concat
  #216 = Utf8               (Lscala/collection/IterableOnce;)Lscala/collection/IterableOps;
  #217 = Utf8               suffix
  #218 = Utf8               concat$
  #219 = Utf8               (Lscala/collection/MapOps;Lscala/collection/IterableOnce;)Lscala/collection/IterableOps;
  #220 = NameAndType        #218:#219     // concat$:(Lscala/collection/MapOps;Lscala/collection/IterableOnce;)Lscala/collection/IterableOps;
  #221 = InterfaceMethodref #15.#220      // scala/collection/MapOps.concat$:(Lscala/collection/MapOps;Lscala/collection/IterableOnce;)Lscala/collection/IterableOps;
  #222 = Utf8               Lscala/collection/IterableOnce;
  #223 = Utf8               $plus$plus
  #224 = Utf8               xs
  #225 = Utf8               $plus$plus$
  #226 = NameAndType        #225:#219     // $plus$plus$:(Lscala/collection/MapOps;Lscala/collection/IterableOnce;)Lscala/collection/IterableOps;
  #227 = InterfaceMethodref #15.#226      // scala/collection/MapOps.$plus$plus$:(Lscala/collection/MapOps;Lscala/collection/IterableOnce;)Lscala/collection/IterableOps;
  #228 = Utf8               addString
  #229 = Utf8               (Lscala/collection/mutable/StringBuilder;Ljava/lang/String;Ljava/lang/String;Ljava/lang/String;)Lscala/collection/mutable/StringBuilder;
  #230 = Utf8               sb
  #231 = Utf8               start
  #232 = Utf8               sep
  #233 = Utf8               end
  #234 = Utf8               addString$
  #235 = Utf8               (Lscala/collection/MapOps;Lscala/collection/mutable/StringBuilder;Ljava/lang/String;Ljava/lang/String;Ljava/lang/String;)Lscala/collection/mutable/StringBuilder;
  #236 = NameAndType        #234:#235     // addString$:(Lscala/collection/MapOps;Lscala/collection/mutable/StringBuilder;Ljava/lang/String;Ljava/lang/String;Ljava/lang/String;)Lscala/collection/mutable/StringBuilder;
  #237 = InterfaceMethodref #15.#236      // scala/collection/MapOps.addString$:(Lscala/collection/MapOps;Lscala/collection/mutable/StringBuilder;Ljava/lang/String;Ljava/lang/String;Ljava/lang/String;)Lscala/collection/mutable/StringBuilder;
  #238 = Utf8               Lscala/collection/mutable/StringBuilder;
  #239 = Utf8               Ljava/lang/String;
  #240 = Utf8               $plus
  #241 = Utf8               (Lscala/Tuple2;)Lscala/collection/IterableOps;
  #242 = Utf8               kv
  #243 = Utf8               $plus$
  #244 = Utf8               (Lscala/collection/MapOps;Lscala/Tuple2;)Lscala/collection/IterableOps;
  #245 = NameAndType        #243:#244     // $plus$:(Lscala/collection/MapOps;Lscala/Tuple2;)Lscala/collection/IterableOps;
  #246 = InterfaceMethodref #15.#245      // scala/collection/MapOps.$plus$:(Lscala/collection/MapOps;Lscala/Tuple2;)Lscala/collection/IterableOps;
  #247 = Utf8               Lscala/Tuple2;
  #248 = Utf8               (Lscala/Tuple2;Lscala/Tuple2;Lscala/collection/immutable/Seq;)Lscala/collection/IterableOps;
  #249 = Utf8               elem1
  #250 = Utf8               elem2
  #251 = Utf8               elems
  #252 = Utf8               (Lscala/collection/MapOps;Lscala/Tuple2;Lscala/Tuple2;Lscala/collection/immutable/Seq;)Lscala/collection/IterableOps;
  #253 = NameAndType        #243:#252     // $plus$:(Lscala/collection/MapOps;Lscala/Tuple2;Lscala/Tuple2;Lscala/collection/immutable/Seq;)Lscala/collection/IterableOps;
  #254 = InterfaceMethodref #15.#253      // scala/collection/MapOps.$plus$:(Lscala/collection/MapOps;Lscala/Tuple2;Lscala/Tuple2;Lscala/collection/immutable/Seq;)Lscala/collection/IterableOps;
  #255 = Utf8               Lscala/collection/immutable/Seq;
  #256 = Utf8               $minus$minus
  #257 = Utf8               (Lscala/collection/IterableOnce;)Ljava/lang/Object;
  #258 = Utf8               $minus$minus$
  #259 = Utf8               (Lscala/collection/MapOps;Lscala/collection/IterableOnce;)Ljava/lang/Object;
  #260 = NameAndType        #258:#259     // $minus$minus$:(Lscala/collection/MapOps;Lscala/collection/IterableOnce;)Ljava/lang/Object;
  #261 = InterfaceMethodref #15.#260      // scala/collection/MapOps.$minus$minus$:(Lscala/collection/MapOps;Lscala/collection/IterableOnce;)Ljava/lang/Object;
  #262 = Utf8               $plus$plus$colon
  #263 = Utf8               that
  #264 = Utf8               $plus$plus$colon$
  #265 = NameAndType        #264:#219     // $plus$plus$colon$:(Lscala/collection/MapOps;Lscala/collection/IterableOnce;)Lscala/collection/IterableOps;
  #266 = InterfaceMethodref #15.#265      // scala/collection/MapOps.$plus$plus$colon$:(Lscala/collection/MapOps;Lscala/collection/IterableOnce;)Lscala/collection/IterableOps;
  #267 = Utf8               unapply
  #268 = Utf8               (Ljava/lang/Object;)Lscala/Option;
  #269 = Utf8               (TK;)Lscala/Option<TV;>;
  #270 = Utf8               a
  #271 = Utf8               scala/PartialFunction
  #272 = Class              #271          // scala/PartialFunction
  #273 = Utf8               unapply$
  #274 = Utf8               (Lscala/PartialFunction;Ljava/lang/Object;)Lscala/Option;
  #275 = NameAndType        #273:#274     // unapply$:(Lscala/PartialFunction;Ljava/lang/Object;)Lscala/Option;
  #276 = InterfaceMethodref #272.#275     // scala/PartialFunction.unapply$:(Lscala/PartialFunction;Ljava/lang/Object;)Lscala/Option;
  #277 = Utf8               elementWise
  #278 = Utf8               ()Lscala/PartialFunction;
  #279 = Utf8               ()Lscala/PartialFunction<TK;TV;>;
  #280 = Utf8               elementWise$
  #281 = Utf8               (Lscala/PartialFunction;)Lscala/PartialFunction;
  #282 = NameAndType        #280:#281     // elementWise$:(Lscala/PartialFunction;)Lscala/PartialFunction;
  #283 = InterfaceMethodref #272.#282     // scala/PartialFunction.elementWise$:(Lscala/PartialFunction;)Lscala/PartialFunction;
  #284 = Utf8               orElse
  #285 = Utf8               <A1:TK;B1:Ljava/lang/Object;>(Lscala/PartialFunction<TA1;TB1;>;)Lscala/PartialFunction<TA1;TB1;>;
  #286 = Utf8               orElse$
  #287 = Utf8               (Lscala/PartialFunction;Lscala/PartialFunction;)Lscala/PartialFunction;
  #288 = NameAndType        #286:#287     // orElse$:(Lscala/PartialFunction;Lscala/PartialFunction;)Lscala/PartialFunction;
  #289 = InterfaceMethodref #272.#288     // scala/PartialFunction.orElse$:(Lscala/PartialFunction;Lscala/PartialFunction;)Lscala/PartialFunction;
  #290 = Utf8               andThen
  #291 = Utf8               (Lscala/Function1;)Lscala/PartialFunction;
  #292 = Utf8               <C$:Ljava/lang/Object;>(Lscala/Function1<TV;TC$;>;)Lscala/PartialFunction<TK;TC$;>;
  #293 = Utf8               k
  #294 = Utf8               andThen$
  #295 = Utf8               (Lscala/PartialFunction;Lscala/Function1;)Lscala/PartialFunction;
  #296 = NameAndType        #294:#295     // andThen$:(Lscala/PartialFunction;Lscala/Function1;)Lscala/PartialFunction;
  #297 = InterfaceMethodref #272.#296     // scala/PartialFunction.andThen$:(Lscala/PartialFunction;Lscala/Function1;)Lscala/PartialFunction;
  #298 = Utf8               <C$:Ljava/lang/Object;>(Lscala/PartialFunction<TV;TC$;>;)Lscala/PartialFunction<TK;TC$;>;
  #299 = NameAndType        #294:#287     // andThen$:(Lscala/PartialFunction;Lscala/PartialFunction;)Lscala/PartialFunction;
  #300 = InterfaceMethodref #272.#299     // scala/PartialFunction.andThen$:(Lscala/PartialFunction;Lscala/PartialFunction;)Lscala/PartialFunction;
  #301 = Utf8               compose
  #302 = Utf8               <R$:Ljava/lang/Object;>(Lscala/PartialFunction<TR$;TK;>;)Lscala/PartialFunction<TR$;TV;>;
  #303 = Utf8               compose$
  #304 = NameAndType        #303:#287     // compose$:(Lscala/PartialFunction;Lscala/PartialFunction;)Lscala/PartialFunction;
  #305 = InterfaceMethodref #272.#304     // scala/PartialFunction.compose$:(Lscala/PartialFunction;Lscala/PartialFunction;)Lscala/PartialFunction;
  #306 = Utf8               lift
  #307 = Utf8               ()Lscala/Function1;
  #308 = Utf8               ()Lscala/Function1<TK;Lscala/Option<TV;>;>;
  #309 = Utf8               lift$
  #310 = Utf8               (Lscala/PartialFunction;)Lscala/Function1;
  #311 = NameAndType        #309:#310     // lift$:(Lscala/PartialFunction;)Lscala/Function1;
  #312 = InterfaceMethodref #272.#311     // scala/PartialFunction.lift$:(Lscala/PartialFunction;)Lscala/Function1;
  #313 = Utf8               runWith
  #314 = Utf8               (Lscala/Function1;)Lscala/Function1;
  #315 = Utf8               <U:Ljava/lang/Object;>(Lscala/Function1<TV;TU;>;)Lscala/Function1<TK;Ljava/lang/Object;>;
  #316 = Utf8               action
  #317 = Utf8               runWith$
  #318 = Utf8               (Lscala/PartialFunction;Lscala/Function1;)Lscala/Function1;
  #319 = NameAndType        #317:#318     // runWith$:(Lscala/PartialFunction;Lscala/Function1;)Lscala/Function1;
  #320 = InterfaceMethodref #272.#319     // scala/PartialFunction.runWith$:(Lscala/PartialFunction;Lscala/Function1;)Lscala/Function1;
  #321 = Utf8               apply$mcZD$sp
  #322 = Utf8               (D)Z
  #323 = Utf8               v1
  #324 = Utf8               scala/Function1
  #325 = Class              #324          // scala/Function1
  #326 = Utf8               apply$mcZD$sp$
  #327 = Utf8               (Lscala/Function1;D)Z
  #328 = NameAndType        #326:#327     // apply$mcZD$sp$:(Lscala/Function1;D)Z
  #329 = InterfaceMethodref #325.#328     // scala/Function1.apply$mcZD$sp$:(Lscala/Function1;D)Z
  #330 = Utf8               D
  #331 = Utf8               apply$mcDD$sp
  #332 = Utf8               (D)D
  #333 = Utf8               apply$mcDD$sp$
  #334 = Utf8               (Lscala/Function1;D)D
  #335 = NameAndType        #333:#334     // apply$mcDD$sp$:(Lscala/Function1;D)D
  #336 = InterfaceMethodref #325.#335     // scala/Function1.apply$mcDD$sp$:(Lscala/Function1;D)D
  #337 = Utf8               apply$mcFD$sp
  #338 = Utf8               (D)F
  #339 = Utf8               apply$mcFD$sp$
  #340 = Utf8               (Lscala/Function1;D)F
  #341 = NameAndType        #339:#340     // apply$mcFD$sp$:(Lscala/Function1;D)F
  #342 = InterfaceMethodref #325.#341     // scala/Function1.apply$mcFD$sp$:(Lscala/Function1;D)F
  #343 = Utf8               apply$mcID$sp
  #344 = Utf8               (D)I
  #345 = Utf8               apply$mcID$sp$
  #346 = Utf8               (Lscala/Function1;D)I
  #347 = NameAndType        #345:#346     // apply$mcID$sp$:(Lscala/Function1;D)I
  #348 = InterfaceMethodref #325.#347     // scala/Function1.apply$mcID$sp$:(Lscala/Function1;D)I
  #349 = Utf8               apply$mcJD$sp
  #350 = Utf8               (D)J
  #351 = Utf8               apply$mcJD$sp$
  #352 = Utf8               (Lscala/Function1;D)J
  #353 = NameAndType        #351:#352     // apply$mcJD$sp$:(Lscala/Function1;D)J
  #354 = InterfaceMethodref #325.#353     // scala/Function1.apply$mcJD$sp$:(Lscala/Function1;D)J
  #355 = Utf8               apply$mcVD$sp
  #356 = Utf8               (D)V
  #357 = Utf8               apply$mcVD$sp$
  #358 = Utf8               (Lscala/Function1;D)V
  #359 = NameAndType        #357:#358     // apply$mcVD$sp$:(Lscala/Function1;D)V
  #360 = InterfaceMethodref #325.#359     // scala/Function1.apply$mcVD$sp$:(Lscala/Function1;D)V
  #361 = Utf8               apply$mcZF$sp
  #362 = Utf8               (F)Z
  #363 = Utf8               apply$mcZF$sp$
  #364 = Utf8               (Lscala/Function1;F)Z
  #365 = NameAndType        #363:#364     // apply$mcZF$sp$:(Lscala/Function1;F)Z
  #366 = InterfaceMethodref #325.#365     // scala/Function1.apply$mcZF$sp$:(Lscala/Function1;F)Z
  #367 = Utf8               F
  #368 = Utf8               apply$mcDF$sp
  #369 = Utf8               (F)D
  #370 = Utf8               apply$mcDF$sp$
  #371 = Utf8               (Lscala/Function1;F)D
  #372 = NameAndType        #370:#371     // apply$mcDF$sp$:(Lscala/Function1;F)D
  #373 = InterfaceMethodref #325.#372     // scala/Function1.apply$mcDF$sp$:(Lscala/Function1;F)D
  #374 = Utf8               apply$mcFF$sp
  #375 = Utf8               (F)F
  #376 = Utf8               apply$mcFF$sp$
  #377 = Utf8               (Lscala/Function1;F)F
  #378 = NameAndType        #376:#377     // apply$mcFF$sp$:(Lscala/Function1;F)F
  #379 = InterfaceMethodref #325.#378     // scala/Function1.apply$mcFF$sp$:(Lscala/Function1;F)F
  #380 = Utf8               apply$mcIF$sp
  #381 = Utf8               (F)I
  #382 = Utf8               apply$mcIF$sp$
  #383 = Utf8               (Lscala/Function1;F)I
  #384 = NameAndType        #382:#383     // apply$mcIF$sp$:(Lscala/Function1;F)I
  #385 = InterfaceMethodref #325.#384     // scala/Function1.apply$mcIF$sp$:(Lscala/Function1;F)I
  #386 = Utf8               apply$mcJF$sp
  #387 = Utf8               (F)J
  #388 = Utf8               apply$mcJF$sp$
  #389 = Utf8               (Lscala/Function1;F)J
  #390 = NameAndType        #388:#389     // apply$mcJF$sp$:(Lscala/Function1;F)J
  #391 = InterfaceMethodref #325.#390     // scala/Function1.apply$mcJF$sp$:(Lscala/Function1;F)J
  #392 = Utf8               apply$mcVF$sp
  #393 = Utf8               (F)V
  #394 = Utf8               apply$mcVF$sp$
  #395 = Utf8               (Lscala/Function1;F)V
  #396 = NameAndType        #394:#395     // apply$mcVF$sp$:(Lscala/Function1;F)V
  #397 = InterfaceMethodref #325.#396     // scala/Function1.apply$mcVF$sp$:(Lscala/Function1;F)V
  #398 = Utf8               apply$mcZI$sp
  #399 = Utf8               (I)Z
  #400 = Utf8               apply$mcZI$sp$
  #401 = Utf8               (Lscala/Function1;I)Z
  #402 = NameAndType        #400:#401     // apply$mcZI$sp$:(Lscala/Function1;I)Z
  #403 = InterfaceMethodref #325.#402     // scala/Function1.apply$mcZI$sp$:(Lscala/Function1;I)Z
  #404 = Utf8               I
  #405 = Utf8               apply$mcDI$sp
  #406 = Utf8               (I)D
  #407 = Utf8               apply$mcDI$sp$
  #408 = Utf8               (Lscala/Function1;I)D
  #409 = NameAndType        #407:#408     // apply$mcDI$sp$:(Lscala/Function1;I)D
  #410 = InterfaceMethodref #325.#409     // scala/Function1.apply$mcDI$sp$:(Lscala/Function1;I)D
  #411 = Utf8               apply$mcFI$sp
  #412 = Utf8               (I)F
  #413 = Utf8               apply$mcFI$sp$
  #414 = Utf8               (Lscala/Function1;I)F
  #415 = NameAndType        #413:#414     // apply$mcFI$sp$:(Lscala/Function1;I)F
  #416 = InterfaceMethodref #325.#415     // scala/Function1.apply$mcFI$sp$:(Lscala/Function1;I)F
  #417 = Utf8               apply$mcII$sp
  #418 = Utf8               (I)I
  #419 = Utf8               apply$mcII$sp$
  #420 = Utf8               (Lscala/Function1;I)I
  #421 = NameAndType        #419:#420     // apply$mcII$sp$:(Lscala/Function1;I)I
  #422 = InterfaceMethodref #325.#421     // scala/Function1.apply$mcII$sp$:(Lscala/Function1;I)I
  #423 = Utf8               apply$mcJI$sp
  #424 = Utf8               (I)J
  #425 = Utf8               apply$mcJI$sp$
  #426 = Utf8               (Lscala/Function1;I)J
  #427 = NameAndType        #425:#426     // apply$mcJI$sp$:(Lscala/Function1;I)J
  #428 = InterfaceMethodref #325.#427     // scala/Function1.apply$mcJI$sp$:(Lscala/Function1;I)J
  #429 = Utf8               apply$mcVI$sp
  #430 = Utf8               (I)V
  #431 = Utf8               apply$mcVI$sp$
  #432 = Utf8               (Lscala/Function1;I)V
  #433 = NameAndType        #431:#432     // apply$mcVI$sp$:(Lscala/Function1;I)V
  #434 = InterfaceMethodref #325.#433     // scala/Function1.apply$mcVI$sp$:(Lscala/Function1;I)V
  #435 = Utf8               apply$mcZJ$sp
  #436 = Utf8               (J)Z
  #437 = Utf8               apply$mcZJ$sp$
  #438 = Utf8               (Lscala/Function1;J)Z
  #439 = NameAndType        #437:#438     // apply$mcZJ$sp$:(Lscala/Function1;J)Z
  #440 = InterfaceMethodref #325.#439     // scala/Function1.apply$mcZJ$sp$:(Lscala/Function1;J)Z
  #441 = Utf8               apply$mcDJ$sp
  #442 = Utf8               (J)D
  #443 = Utf8               apply$mcDJ$sp$
  #444 = Utf8               (Lscala/Function1;J)D
  #445 = NameAndType        #443:#444     // apply$mcDJ$sp$:(Lscala/Function1;J)D
  #446 = InterfaceMethodref #325.#445     // scala/Function1.apply$mcDJ$sp$:(Lscala/Function1;J)D
  #447 = Utf8               apply$mcFJ$sp
  #448 = Utf8               (J)F
  #449 = Utf8               apply$mcFJ$sp$
  #450 = Utf8               (Lscala/Function1;J)F
  #451 = NameAndType        #449:#450     // apply$mcFJ$sp$:(Lscala/Function1;J)F
  #452 = InterfaceMethodref #325.#451     // scala/Function1.apply$mcFJ$sp$:(Lscala/Function1;J)F
  #453 = Utf8               apply$mcIJ$sp
  #454 = Utf8               (J)I
  #455 = Utf8               apply$mcIJ$sp$
  #456 = Utf8               (Lscala/Function1;J)I
  #457 = NameAndType        #455:#456     // apply$mcIJ$sp$:(Lscala/Function1;J)I
  #458 = InterfaceMethodref #325.#457     // scala/Function1.apply$mcIJ$sp$:(Lscala/Function1;J)I
  #459 = Utf8               apply$mcJJ$sp
  #460 = Utf8               (J)J
  #461 = Utf8               apply$mcJJ$sp$
  #462 = Utf8               (Lscala/Function1;J)J
  #463 = NameAndType        #461:#462     // apply$mcJJ$sp$:(Lscala/Function1;J)J
  #464 = InterfaceMethodref #325.#463     // scala/Function1.apply$mcJJ$sp$:(Lscala/Function1;J)J
  #465 = Utf8               apply$mcVJ$sp
  #466 = Utf8               (J)V
  #467 = Utf8               apply$mcVJ$sp$
  #468 = Utf8               (Lscala/Function1;J)V
  #469 = NameAndType        #467:#468     // apply$mcVJ$sp$:(Lscala/Function1;J)V
  #470 = InterfaceMethodref #325.#469     // scala/Function1.apply$mcVJ$sp$:(Lscala/Function1;J)V
  #471 = Utf8               <A$:Ljava/lang/Object;>(Lscala/Function1<TA$;TK;>;)Lscala/Function1<TA$;TV;>;
  #472 = Utf8               g
  #473 = Utf8               (Lscala/Function1;Lscala/Function1;)Lscala/Function1;
  #474 = NameAndType        #303:#473     // compose$:(Lscala/Function1;Lscala/Function1;)Lscala/Function1;
  #475 = InterfaceMethodref #325.#474     // scala/Function1.compose$:(Lscala/Function1;Lscala/Function1;)Lscala/Function1;
  #476 = NameAndType        #290:#291     // andThen:(Lscala/Function1;)Lscala/PartialFunction;
  #477 = Methodref          #2.#476       // scala/collection/AbstractMapView.andThen:(Lscala/Function1;)Lscala/PartialFunction;
  #478 = Utf8               (Lscala/Function1;)Lscala/collection/WithFilter;
  #479 = NameAndType        #89:#90       // withFilter:(Lscala/Function1;)Lscala/collection/MapOps$WithFilter;
  #480 = Methodref          #2.#479       // scala/collection/AbstractMapView.withFilter:(Lscala/Function1;)Lscala/collection/MapOps$WithFilter;
  #481 = Utf8               ()Ljava/lang/Object;
  #482 = NameAndType        #85:#22       // empty:()Lscala/collection/MapView;
  #483 = Methodref          #2.#482       // scala/collection/AbstractMapView.empty:()Lscala/collection/MapView;
  #484 = Utf8               ()Lscala/collection/IterableOps;
  #485 = Utf8               ()Lscala/collection/View;
  #486 = Utf8               ()Lscala/collection/MapFactory;
  #487 = NameAndType        #79:#80       // mapFactory:()Lscala/collection/MapViewFactory;
  #488 = Methodref          #2.#487       // scala/collection/AbstractMapView.mapFactory:()Lscala/collection/MapViewFactory;
  #489 = Utf8               (Lscala/Function1;)Ljava/lang/Object;
  #490 = NameAndType        #74:#43       // tapEach:(Lscala/Function1;)Lscala/collection/MapView;
  #491 = Methodref          #2.#490       // scala/collection/AbstractMapView.tapEach:(Lscala/Function1;)Lscala/collection/MapView;
  #492 = NameAndType        #63:#43       // filterNot:(Lscala/Function1;)Lscala/collection/MapView;
  #493 = Methodref          #2.#492       // scala/collection/AbstractMapView.filterNot:(Lscala/Function1;)Lscala/collection/MapView;
  #494 = NameAndType        #57:#43       // filter:(Lscala/Function1;)Lscala/collection/MapView;
  #495 = Methodref          #2.#494       // scala/collection/AbstractMapView.filter:(Lscala/Function1;)Lscala/collection/MapView;
  #496 = NameAndType        #21:#22       // view:()Lscala/collection/MapView;
  #497 = Methodref          #2.#496       // scala/collection/AbstractMapView.view:()Lscala/collection/MapView;
  #498 = Utf8               <init>
  #499 = Utf8               ()V
  #500 = NameAndType        #498:#499     // "<init>":()V
  #501 = Methodref          #5.#500       // scala/collection/AbstractView."<init>":()V
  #502 = Utf8               ConstantValue
  #503 = Utf8               Code
  #504 = Utf8               LineNumberTable
  #505 = Utf8               LocalVariableTable
  #506 = Utf8               Signature
  #507 = Utf8               MethodParameters
  #508 = Utf8               Exceptions
  #509 = Utf8               Deprecated
  #510 = Utf8               InnerClasses
  #511 = Utf8               SourceFile
  #512 = Utf8               RuntimeVisibleAnnotations
  #513 = Utf8               ScalaInlineInfo
  #514 = Utf8               ScalaSig
{
  private static final long serialVersionUID;
    descriptor: J
    flags: (0x001a) ACC_PRIVATE, ACC_STATIC, ACC_FINAL
    ConstantValue: long 3l

  public scala.collection.MapView<K, V> view();
    descriptor: ()Lscala/collection/MapView;
    flags: (0x0001) ACC_PUBLIC
    Code:
      stack=1, locals=1, args_size=1
         0: aload_0
         1: invokestatic  #27                 // InterfaceMethod scala/collection/MapView.view$:(Lscala/collection/MapView;)Lscala/collection/MapView;
         4: areturn
      LineNumberTable:
        line 186: 0
      LocalVariableTable:
        Start  Length  Slot  Name   Signature
            0       5     0  this   Lscala/collection/AbstractMapView;
    Signature: #23                          // ()Lscala/collection/MapView<TK;TV;>;

  public scala.collection.Iterable<K> keys();
    descriptor: ()Lscala/collection/Iterable;
    flags: (0x0001) ACC_PUBLIC
    Code:
      stack=1, locals=1, args_size=1
         0: aload_0
         1: invokestatic  #36                 // InterfaceMethod scala/collection/MapView.keys$:(Lscala/collection/MapView;)Lscala/collection/Iterable;
         4: areturn
      LineNumberTable:
        line 186: 0
      LocalVariableTable:
        Start  Length  Slot  Name   Signature
            0       5     0  this   Lscala/collection/AbstractMapView;
    Signature: #32                          // ()Lscala/collection/Iterable<TK;>;

  public scala.collection.Iterable<V> values();
    descriptor: ()Lscala/collection/Iterable;
    flags: (0x0001) ACC_PUBLIC
    Code:
      stack=1, locals=1, args_size=1
         0: aload_0
         1: invokestatic  #41                 // InterfaceMethod scala/collection/MapView.values$:(Lscala/collection/MapView;)Lscala/collection/Iterable;
         4: areturn
      LineNumberTable:
        line 186: 0
      LocalVariableTable:
        Start  Length  Slot  Name   Signature
            0       5     0  this   Lscala/collection/AbstractMapView;
    Signature: #38                          // ()Lscala/collection/Iterable<TV;>;

  public scala.collection.MapView<K, V> filterKeys(scala.Function1<K, java.lang.Object>);
    descriptor: (Lscala/Function1;)Lscala/collection/MapView;
    flags: (0x0001) ACC_PUBLIC
    Code:
      stack=2, locals=2, args_size=2
         0: aload_0
         1: aload_1
         2: invokestatic  #49                 // InterfaceMethod scala/collection/MapView.filterKeys$:(Lscala/collection/MapView;Lscala/Function1;)Lscala/collection/MapView;
         5: areturn
      LineNumberTable:
        line 186: 0
      LocalVariableTable:
        Start  Length  Slot  Name   Signature
            0       6     0  this   Lscala/collection/AbstractMapView;
            0       6     1     p   Lscala/Function1;
    Signature: #44                          // (Lscala/Function1<TK;Ljava/lang/Object;>;)Lscala/collection/MapView<TK;TV;>;
    MethodParameters:
      Name                           Flags
      p                              final

  public <W extends java.lang.Object> scala.collection.MapView<K, W> mapValues(scala.Function1<V, W>);
    descriptor: (Lscala/Function1;)Lscala/collection/MapView;
    flags: (0x0001) ACC_PUBLIC
    Code:
      stack=2, locals=2, args_size=2
         0: aload_0
         1: aload_1
         2: invokestatic  #56                 // InterfaceMethod scala/collection/MapView.mapValues$:(Lscala/collection/MapView;Lscala/Function1;)Lscala/collection/MapView;
         5: areturn
      LineNumberTable:
        line 186: 0
      LocalVariableTable:
        Start  Length  Slot  Name   Signature
            0       6     0  this   Lscala/collection/AbstractMapView;
            0       6     1     f   Lscala/Function1;
    Signature: #52                          // <W:Ljava/lang/Object;>(Lscala/Function1<TV;TW;>;)Lscala/collection/MapView<TK;TW;>;
    MethodParameters:
      Name                           Flags
      f                              final

  public scala.collection.MapView<K, V> filter(scala.Function1<scala.Tuple2<K, V>, java.lang.Object>);
    descriptor: (Lscala/Function1;)Lscala/collection/MapView;
    flags: (0x0001) ACC_PUBLIC
    Code:
      stack=2, locals=2, args_size=2
         0: aload_0
         1: aload_1
         2: invokestatic  #62                 // InterfaceMethod scala/collection/MapView.filter$:(Lscala/collection/MapView;Lscala/Function1;)Lscala/collection/MapView;
         5: areturn
      LineNumberTable:
        line 186: 0
      LocalVariableTable:
        Start  Length  Slot  Name   Signature
            0       6     0  this   Lscala/collection/AbstractMapView;
            0       6     1  pred   Lscala/Function1;
    Signature: #58                          // (Lscala/Function1<Lscala/Tuple2<TK;TV;>;Ljava/lang/Object;>;)Lscala/collection/MapView<TK;TV;>;
    MethodParameters:
      Name                           Flags
      pred                           final

  public scala.collection.MapView<K, V> filterNot(scala.Function1<scala.Tuple2<K, V>, java.lang.Object>);
    descriptor: (Lscala/Function1;)Lscala/collection/MapView;
    flags: (0x0001) ACC_PUBLIC
    Code:
      stack=2, locals=2, args_size=2
         0: aload_0
         1: aload_1
         2: invokestatic  #66                 // InterfaceMethod scala/collection/MapView.filterNot$:(Lscala/collection/MapView;Lscala/Function1;)Lscala/collection/MapView;
         5: areturn
      LineNumberTable:
        line 186: 0
      LocalVariableTable:
        Start  Length  Slot  Name   Signature
            0       6     0  this   Lscala/collection/AbstractMapView;
            0       6     1  pred   Lscala/Function1;
    Signature: #58                          // (Lscala/Function1<Lscala/Tuple2<TK;TV;>;Ljava/lang/Object;>;)Lscala/collection/MapView<TK;TV;>;
    MethodParameters:
      Name                           Flags
      pred                           final

  public scala.Tuple2<scala.collection.MapView<K, V>, scala.collection.MapView<K, V>> partition(scala.Function1<scala.Tuple2<K, V>, java.lang.Object>);
    descriptor: (Lscala/Function1;)Lscala/Tuple2;
    flags: (0x0001) ACC_PUBLIC
    Code:
      stack=2, locals=2, args_size=2
         0: aload_0
         1: aload_1
         2: invokestatic  #73                 // InterfaceMethod scala/collection/MapView.partition$:(Lscala/collection/MapView;Lscala/Function1;)Lscala/Tuple2;
         5: areturn
      LineNumberTable:
        line 186: 0
      LocalVariableTable:
        Start  Length  Slot  Name   Signature
            0       6     0  this   Lscala/collection/AbstractMapView;
            0       6     1     p   Lscala/Function1;
    Signature: #69                          // (Lscala/Function1<Lscala/Tuple2<TK;TV;>;Ljava/lang/Object;>;)Lscala/Tuple2<Lscala/collection/MapView<TK;TV;>;Lscala/collection/MapView<TK;TV;>;>;
    MethodParameters:
      Name                           Flags
      p                              final

  public <U extends java.lang.Object> scala.collection.MapView<K, V> tapEach(scala.Function1<scala.Tuple2<K, V>, U>);
    descriptor: (Lscala/Function1;)Lscala/collection/MapView;
    flags: (0x0001) ACC_PUBLIC
    Code:
      stack=2, locals=2, args_size=2
         0: aload_0
         1: aload_1
         2: invokestatic  #78                 // InterfaceMethod scala/collection/MapView.tapEach$:(Lscala/collection/MapView;Lscala/Function1;)Lscala/collection/MapView;
         5: areturn
      LineNumberTable:
        line 186: 0
      LocalVariableTable:
        Start  Length  Slot  Name   Signature
            0       6     0  this   Lscala/collection/AbstractMapView;
            0       6     1     f   Lscala/Function1;
    Signature: #75                          // <U:Ljava/lang/Object;>(Lscala/Function1<Lscala/Tuple2<TK;TV;>;TU;>;)Lscala/collection/MapView<TK;TV;>;
    MethodParameters:
      Name                           Flags
      f                              final

  public scala.collection.MapViewFactory mapFactory();
    descriptor: ()Lscala/collection/MapViewFactory;
    flags: (0x0001) ACC_PUBLIC
    Code:
      stack=1, locals=1, args_size=1
         0: aload_0
         1: invokestatic  #84                 // InterfaceMethod scala/collection/MapView.mapFactory$:(Lscala/collection/MapView;)Lscala/collection/MapViewFactory;
         4: areturn
      LineNumberTable:
        line 186: 0
      LocalVariableTable:
        Start  Length  Slot  Name   Signature
            0       5     0  this   Lscala/collection/AbstractMapView;

  public scala.collection.MapView<K, V> empty();
    descriptor: ()Lscala/collection/MapView;
    flags: (0x0001) ACC_PUBLIC
    Code:
      stack=1, locals=1, args_size=1
         0: aload_0
         1: invokestatic  #88                 // InterfaceMethod scala/collection/MapView.empty$:(Lscala/collection/MapView;)Lscala/collection/MapView;
         4: areturn
      LineNumberTable:
        line 186: 0
      LocalVariableTable:
        Start  Length  Slot  Name   Signature
            0       5     0  this   Lscala/collection/AbstractMapView;
    Signature: #23                          // ()Lscala/collection/MapView<TK;TV;>;

  public scala.collection.MapOps$WithFilter<K, V, scala.collection.View, ?> withFilter(scala.Function1<scala.Tuple2<K, V>, java.lang.Object>);
    descriptor: (Lscala/Function1;)Lscala/collection/MapOps$WithFilter;
    flags: (0x0001) ACC_PUBLIC
    Code:
      stack=2, locals=2, args_size=2
         0: aload_0
         1: aload_1
         2: invokestatic  #95                 // InterfaceMethod scala/collection/MapView.withFilter$:(Lscala/collection/MapView;Lscala/Function1;)Lscala/collection/MapOps$WithFilter;
         5: areturn
      LineNumberTable:
        line 186: 0
      LocalVariableTable:
        Start  Length  Slot  Name   Signature
            0       6     0  this   Lscala/collection/AbstractMapView;
            0       6     1     p   Lscala/Function1;
    Signature: #91                          // (Lscala/Function1<Lscala/Tuple2<TK;TV;>;Ljava/lang/Object;>;)Lscala/collection/MapOps$WithFilter<TK;TV;Lscala/collection/View;*>;
    MethodParameters:
      Name                           Flags
      p                              final

  public java.lang.String toString();
    descriptor: ()Ljava/lang/String;
    flags: (0x0001) ACC_PUBLIC
    Code:
      stack=1, locals=1, args_size=1
         0: aload_0
         1: invokestatic  #101                // InterfaceMethod scala/collection/MapView.toString$:(Lscala/collection/MapView;)Ljava/lang/String;
         4: areturn
      LineNumberTable:
        line 186: 0
      LocalVariableTable:
        Start  Length  Slot  Name   Signature
            0       5     0  this   Lscala/collection/AbstractMapView;

  public java.lang.String stringPrefix();
    descriptor: ()Ljava/lang/String;
    flags: (0x0001) ACC_PUBLIC
    Code:
      stack=1, locals=1, args_size=1
         0: aload_0
         1: invokestatic  #105                // InterfaceMethod scala/collection/MapView.stringPrefix$:(Lscala/collection/MapView;)Ljava/lang/String;
         4: areturn
      LineNumberTable:
        line 186: 0
      LocalVariableTable:
        Start  Length  Slot  Name   Signature
            0       5     0  this   Lscala/collection/AbstractMapView;

  public <S extends scala.collection.Stepper<?>> S keyStepper(scala.collection.StepperShape<K, S>);
    descriptor: (Lscala/collection/StepperShape;)Lscala/collection/Stepper;
    flags: (0x0001) ACC_PUBLIC
    Code:
      stack=2, locals=2, args_size=2
         0: aload_0
         1: aload_1
         2: invokestatic  #113                // InterfaceMethod scala/collection/MapOps.keyStepper$:(Lscala/collection/MapOps;Lscala/collection/StepperShape;)Lscala/collection/Stepper;
         5: areturn
      LineNumberTable:
        line 186: 0
      LocalVariableTable:
        Start  Length  Slot  Name   Signature
            0       6     0  this   Lscala/collection/AbstractMapView;
            0       6     1 shape   Lscala/collection/StepperShape;
    Signature: #108                         // <S::Lscala/collection/Stepper<*>;>(Lscala/collection/StepperShape<TK;TS;>;)TS;
    MethodParameters:
      Name                           Flags
      shape                          final

  public <S extends scala.collection.Stepper<?>> S valueStepper(scala.collection.StepperShape<V, S>);
    descriptor: (Lscala/collection/StepperShape;)Lscala/collection/Stepper;
    flags: (0x0001) ACC_PUBLIC
    Code:
      stack=2, locals=2, args_size=2
         0: aload_0
         1: aload_1
         2: invokestatic  #119                // InterfaceMethod scala/collection/MapOps.valueStepper$:(Lscala/collection/MapOps;Lscala/collection/StepperShape;)Lscala/collection/Stepper;
         5: areturn
      LineNumberTable:
        line 186: 0
      LocalVariableTable:
        Start  Length  Slot  Name   Signature
            0       6     0  this   Lscala/collection/AbstractMapView;
            0       6     1 shape   Lscala/collection/StepperShape;
    Signature: #116                         // <S::Lscala/collection/Stepper<*>;>(Lscala/collection/StepperShape<TV;TS;>;)TS;
    MethodParameters:
      Name                           Flags
      shape                          final

  public final scala.collection.IterableOps mapFromIterable(scala.collection.Iterable);
    descriptor: (Lscala/collection/Iterable;)Lscala/collection/IterableOps;
    flags: (0x0011) ACC_PUBLIC, ACC_FINAL
    Code:
      stack=2, locals=2, args_size=2
         0: aload_0
         1: aload_1
         2: invokestatic  #126                // InterfaceMethod scala/collection/MapOps.mapFromIterable$:(Lscala/collection/MapOps;Lscala/collection/Iterable;)Lscala/collection/IterableOps;
         5: areturn
      LineNumberTable:
        line 186: 0
      LocalVariableTable:
        Start  Length  Slot  Name   Signature
            0       6     0  this   Lscala/collection/AbstractMapView;
            0       6     1    it   Lscala/collection/Iterable;
    MethodParameters:
      Name                           Flags
      it                             final

  public <V1 extends java.lang.Object> V1 getOrElse(K, scala.Function0<V1>);
    descriptor: (Ljava/lang/Object;Lscala/Function0;)Ljava/lang/Object;
    flags: (0x0001) ACC_PUBLIC
    Code:
      stack=3, locals=3, args_size=3
         0: aload_0
         1: aload_1
         2: aload_2
         3: invokestatic  #136                // InterfaceMethod scala/collection/MapOps.getOrElse$:(Lscala/collection/MapOps;Ljava/lang/Object;Lscala/Function0;)Ljava/lang/Object;
         6: areturn
      LineNumberTable:
        line 186: 0
      LocalVariableTable:
        Start  Length  Slot  Name   Signature
            0       7     0  this   Lscala/collection/AbstractMapView;
            0       7     1   key   Ljava/lang/Object;
            0       7     2 default   Lscala/Function0;
    Signature: #130                         // <V1:Ljava/lang/Object;>(TK;Lscala/Function0<TV1;>;)TV1;
    MethodParameters:
      Name                           Flags
      key                            final
      default                        final

  public V apply(K) throws java/util/NoSuchElementException;
    descriptor: (Ljava/lang/Object;)Ljava/lang/Object;
    flags: (0x0001) ACC_PUBLIC
    Code:
      stack=2, locals=2, args_size=2
         0: aload_0
         1: aload_1
         2: invokestatic  #147                // InterfaceMethod scala/collection/MapOps.apply$:(Lscala/collection/MapOps;Ljava/lang/Object;)Ljava/lang/Object;
         5: areturn
      LineNumberTable:
        line 186: 0
      LocalVariableTable:
        Start  Length  Slot  Name   Signature
            0       6     0  this   Lscala/collection/AbstractMapView;
            0       6     1   key   Ljava/lang/Object;
    Exceptions:
      throws java.util.NoSuchElementException
    Signature: #141                         // (TK;)TV;^Ljava/util/NoSuchElementException;
    MethodParameters:
      Name                           Flags
      key                            final

  public <K1 extends K, V1 extends java.lang.Object> V1 applyOrElse(K1, scala.Function1<K1, V1>);
    descriptor: (Ljava/lang/Object;Lscala/Function1;)Ljava/lang/Object;
    flags: (0x0001) ACC_PUBLIC
    Code:
      stack=3, locals=3, args_size=3
         0: aload_0
         1: aload_1
         2: aload_2
         3: invokestatic  #155                // InterfaceMethod scala/collection/MapOps.applyOrElse$:(Lscala/collection/MapOps;Ljava/lang/Object;Lscala/Function1;)Ljava/lang/Object;
         6: areturn
      LineNumberTable:
        line 186: 0
      LocalVariableTable:
        Start  Length  Slot  Name   Signature
            0       7     0  this   Lscala/collection/AbstractMapView;
            0       7     1     x   Ljava/lang/Object;
            0       7     2 default   Lscala/Function1;
    Signature: #150                         // <K1:TK;V1:Ljava/lang/Object;>(TK1;Lscala/Function1<TK1;TV1;>;)TV1;
    MethodParameters:
      Name                           Flags
      x                              final
      default                        final

  public scala.collection.Set<K> keySet();
    descriptor: ()Lscala/collection/Set;
    flags: (0x0001) ACC_PUBLIC
    Code:
      stack=1, locals=1, args_size=1
         0: aload_0
         1: invokestatic  #162                // InterfaceMethod scala/collection/MapOps.keySet$:(Lscala/collection/MapOps;)Lscala/collection/Set;
         4: areturn
      LineNumberTable:
        line 186: 0
      LocalVariableTable:
        Start  Length  Slot  Name   Signature
            0       5     0  this   Lscala/collection/AbstractMapView;
    Signature: #158                         // ()Lscala/collection/Set<TK;>;

  public scala.collection.Iterator<K> keysIterator();
    descriptor: ()Lscala/collection/Iterator;
    flags: (0x0001) ACC_PUBLIC
    Code:
      stack=1, locals=1, args_size=1
         0: aload_0
         1: invokestatic  #169                // InterfaceMethod scala/collection/MapOps.keysIterator$:(Lscala/collection/MapOps;)Lscala/collection/Iterator;
         4: areturn
      LineNumberTable:
        line 186: 0
      LocalVariableTable:
        Start  Length  Slot  Name   Signature
            0       5     0  this   Lscala/collection/AbstractMapView;
    Signature: #165                         // ()Lscala/collection/Iterator<TK;>;

  public scala.collection.Iterator<V> valuesIterator();
    descriptor: ()Lscala/collection/Iterator;
    flags: (0x0001) ACC_PUBLIC
    Code:
      stack=1, locals=1, args_size=1
         0: aload_0
         1: invokestatic  #174                // InterfaceMethod scala/collection/MapOps.valuesIterator$:(Lscala/collection/MapOps;)Lscala/collection/Iterator;
         4: areturn
      LineNumberTable:
        line 186: 0
      LocalVariableTable:
        Start  Length  Slot  Name   Signature
            0       5     0  this   Lscala/collection/AbstractMapView;
    Signature: #171                         // ()Lscala/collection/Iterator<TV;>;

  public <U extends java.lang.Object> void foreachEntry(scala.Function2<K, V, U>);
    descriptor: (Lscala/Function2;)V
    flags: (0x0001) ACC_PUBLIC
    Code:
      stack=2, locals=2, args_size=2
         0: aload_0
         1: aload_1
         2: invokestatic  #181                // InterfaceMethod scala/collection/MapOps.foreachEntry$:(Lscala/collection/MapOps;Lscala/Function2;)V
         5: return
      LineNumberTable:
        line 186: 0
      LocalVariableTable:
        Start  Length  Slot  Name   Signature
            0       6     0  this   Lscala/collection/AbstractMapView;
            0       6     1     f   Lscala/Function2;
    Signature: #177                         // <U:Ljava/lang/Object;>(Lscala/Function2<TK;TV;TU;>;)V
    MethodParameters:
      Name                           Flags
      f                              final

  public V default(K) throws java/util/NoSuchElementException;
    descriptor: (Ljava/lang/Object;)Ljava/lang/Object;
    flags: (0x0001) ACC_PUBLIC
    Code:
      stack=2, locals=2, args_size=2
         0: aload_0
         1: aload_1
         2: invokestatic  #185                // InterfaceMethod scala/collection/MapOps.default$:(Lscala/collection/MapOps;Ljava/lang/Object;)Ljava/lang/Object;
         5: areturn
      LineNumberTable:
        line 186: 0
      LocalVariableTable:
        Start  Length  Slot  Name   Signature
            0       6     0  this   Lscala/collection/AbstractMapView;
            0       6     1   key   Ljava/lang/Object;
    Exceptions:
      throws java.util.NoSuchElementException
    Signature: #141                         // (TK;)TV;^Ljava/util/NoSuchElementException;
    MethodParameters:
      Name                           Flags
      key                            final

  public boolean contains(K);
    descriptor: (Ljava/lang/Object;)Z
    flags: (0x0001) ACC_PUBLIC
    Code:
      stack=2, locals=2, args_size=2
         0: aload_0
         1: aload_1
         2: invokestatic  #192                // InterfaceMethod scala/collection/MapOps.contains$:(Lscala/collection/MapOps;Ljava/lang/Object;)Z
         5: ireturn
      LineNumberTable:
        line 186: 0
      LocalVariableTable:
        Start  Length  Slot  Name   Signature
            0       6     0  this   Lscala/collection/AbstractMapView;
            0       6     1   key   Ljava/lang/Object;
    Signature: #188                         // (TK;)Z
    MethodParameters:
      Name                           Flags
      key                            final

  public boolean isDefinedAt(K);
    descriptor: (Ljava/lang/Object;)Z
    flags: (0x0001) ACC_PUBLIC
    Code:
      stack=2, locals=2, args_size=2
         0: aload_0
         1: aload_1
         2: invokestatic  #196                // InterfaceMethod scala/collection/MapOps.isDefinedAt$:(Lscala/collection/MapOps;Ljava/lang/Object;)Z
         5: ireturn
      LineNumberTable:
        line 186: 0
      LocalVariableTable:
        Start  Length  Slot  Name   Signature
            0       6     0  this   Lscala/collection/AbstractMapView;
            0       6     1   key   Ljava/lang/Object;
    Signature: #188                         // (TK;)Z
    MethodParameters:
      Name                           Flags
      key                            final

  public scala.collection.IterableOps map(scala.Function1);
    descriptor: (Lscala/Function1;)Lscala/collection/IterableOps;
    flags: (0x0001) ACC_PUBLIC
    Code:
      stack=2, locals=2, args_size=2
         0: aload_0
         1: aload_1
         2: invokestatic  #202                // InterfaceMethod scala/collection/MapOps.map$:(Lscala/collection/MapOps;Lscala/Function1;)Lscala/collection/IterableOps;
         5: areturn
      LineNumberTable:
        line 186: 0
      LocalVariableTable:
        Start  Length  Slot  Name   Signature
            0       6     0  this   Lscala/collection/AbstractMapView;
            0       6     1     f   Lscala/Function1;
    MethodParameters:
      Name                           Flags
      f                              final

  public scala.collection.IterableOps collect(scala.PartialFunction);
    descriptor: (Lscala/PartialFunction;)Lscala/collection/IterableOps;
    flags: (0x0001) ACC_PUBLIC
    Code:
      stack=2, locals=2, args_size=2
         0: aload_0
         1: aload_1
         2: invokestatic  #209                // InterfaceMethod scala/collection/MapOps.collect$:(Lscala/collection/MapOps;Lscala/PartialFunction;)Lscala/collection/IterableOps;
         5: areturn
      LineNumberTable:
        line 186: 0
      LocalVariableTable:
        Start  Length  Slot  Name   Signature
            0       6     0  this   Lscala/collection/AbstractMapView;
            0       6     1    pf   Lscala/PartialFunction;
    MethodParameters:
      Name                           Flags
      pf                             final

  public scala.collection.IterableOps flatMap(scala.Function1);
    descriptor: (Lscala/Function1;)Lscala/collection/IterableOps;
    flags: (0x0001) ACC_PUBLIC
    Code:
      stack=2, locals=2, args_size=2
         0: aload_0
         1: aload_1
         2: invokestatic  #214                // InterfaceMethod scala/collection/MapOps.flatMap$:(Lscala/collection/MapOps;Lscala/Function1;)Lscala/collection/IterableOps;
         5: areturn
      LineNumberTable:
        line 186: 0
      LocalVariableTable:
        Start  Length  Slot  Name   Signature
            0       6     0  this   Lscala/collection/AbstractMapView;
            0       6     1     f   Lscala/Function1;
    MethodParameters:
      Name                           Flags
      f                              final

  public scala.collection.IterableOps concat(scala.collection.IterableOnce);
    descriptor: (Lscala/collection/IterableOnce;)Lscala/collection/IterableOps;
    flags: (0x0001) ACC_PUBLIC
    Code:
      stack=2, locals=2, args_size=2
         0: aload_0
         1: aload_1
         2: invokestatic  #221                // InterfaceMethod scala/collection/MapOps.concat$:(Lscala/collection/MapOps;Lscala/collection/IterableOnce;)Lscala/collection/IterableOps;
         5: areturn
      LineNumberTable:
        line 186: 0
      LocalVariableTable:
        Start  Length  Slot  Name   Signature
            0       6     0  this   Lscala/collection/AbstractMapView;
            0       6     1 suffix   Lscala/collection/IterableOnce;
    MethodParameters:
      Name                           Flags
      suffix                         final

  public scala.collection.IterableOps $plus$plus(scala.collection.IterableOnce);
    descriptor: (Lscala/collection/IterableOnce;)Lscala/collection/IterableOps;
    flags: (0x0001) ACC_PUBLIC
    Code:
      stack=2, locals=2, args_size=2
         0: aload_0
         1: aload_1
         2: invokestatic  #227                // InterfaceMethod scala/collection/MapOps.$plus$plus$:(Lscala/collection/MapOps;Lscala/collection/IterableOnce;)Lscala/collection/IterableOps;
         5: areturn
      LineNumberTable:
        line 186: 0
      LocalVariableTable:
        Start  Length  Slot  Name   Signature
            0       6     0  this   Lscala/collection/AbstractMapView;
            0       6     1    xs   Lscala/collection/IterableOnce;
    MethodParameters:
      Name                           Flags
      xs                             final

  public scala.collection.mutable.StringBuilder addString(scala.collection.mutable.StringBuilder, java.lang.String, java.lang.String, java.lang.String);
    descriptor: (Lscala/collection/mutable/StringBuilder;Ljava/lang/String;Ljava/lang/String;Ljava/lang/String;)Lscala/collection/mutable/StringBuilder;
    flags: (0x0001) ACC_PUBLIC
    Code:
      stack=5, locals=5, args_size=5
         0: aload_0
         1: aload_1
         2: aload_2
         3: aload_3
         4: aload         4
         6: invokestatic  #237                // InterfaceMethod scala/collection/MapOps.addString$:(Lscala/collection/MapOps;Lscala/collection/mutable/StringBuilder;Ljava/lang/String;Ljava/lang/String;Ljava/lang/String;)Lscala/collection/mutable/StringBuilder;
         9: areturn
      LineNumberTable:
        line 186: 0
      LocalVariableTable:
        Start  Length  Slot  Name   Signature
            0      10     0  this   Lscala/collection/AbstractMapView;
            0      10     1    sb   Lscala/collection/mutable/StringBuilder;
            0      10     2 start   Ljava/lang/String;
            0      10     3   sep   Ljava/lang/String;
            0      10     4   end   Ljava/lang/String;
    MethodParameters:
      Name                           Flags
      sb                             final
      start                          final
      sep                            final
      end                            final

  public scala.collection.IterableOps $plus(scala.Tuple2);
    descriptor: (Lscala/Tuple2;)Lscala/collection/IterableOps;
    flags: (0x0001) ACC_PUBLIC
    Code:
      stack=2, locals=2, args_size=2
         0: aload_0
         1: aload_1
         2: invokestatic  #246                // InterfaceMethod scala/collection/MapOps.$plus$:(Lscala/collection/MapOps;Lscala/Tuple2;)Lscala/collection/IterableOps;
         5: areturn
      LineNumberTable:
        line 186: 0
      LocalVariableTable:
        Start  Length  Slot  Name   Signature
            0       6     0  this   Lscala/collection/AbstractMapView;
            0       6     1    kv   Lscala/Tuple2;
    Deprecated: true
    MethodParameters:
      Name                           Flags
      kv                             final

  public scala.collection.IterableOps $plus(scala.Tuple2, scala.Tuple2, scala.collection.immutable.Seq);
    descriptor: (Lscala/Tuple2;Lscala/Tuple2;Lscala/collection/immutable/Seq;)Lscala/collection/IterableOps;
    flags: (0x0001) ACC_PUBLIC
    Code:
      stack=4, locals=4, args_size=4
         0: aload_0
         1: aload_1
         2: aload_2
         3: aload_3
         4: invokestatic  #254                // InterfaceMethod scala/collection/MapOps.$plus$:(Lscala/collection/MapOps;Lscala/Tuple2;Lscala/Tuple2;Lscala/collection/immutable/Seq;)Lscala/collection/IterableOps;
         7: areturn
      LineNumberTable:
        line 186: 0
      LocalVariableTable:
        Start  Length  Slot  Name   Signature
            0       8     0  this   Lscala/collection/AbstractMapView;
            0       8     1 elem1   Lscala/Tuple2;
            0       8     2 elem2   Lscala/Tuple2;
            0       8     3 elems   Lscala/collection/immutable/Seq;
    Deprecated: true
    MethodParameters:
      Name                           Flags
      elem1                          final
      elem2                          final
      elems                          final

  public java.lang.Object $minus$minus(scala.collection.IterableOnce);
    descriptor: (Lscala/collection/IterableOnce;)Ljava/lang/Object;
    flags: (0x0001) ACC_PUBLIC
    Code:
      stack=2, locals=2, args_size=2
         0: aload_0
         1: aload_1
         2: invokestatic  #261                // InterfaceMethod scala/collection/MapOps.$minus$minus$:(Lscala/collection/MapOps;Lscala/collection/IterableOnce;)Ljava/lang/Object;
         5: areturn
      LineNumberTable:
        line 186: 0
      LocalVariableTable:
        Start  Length  Slot  Name   Signature
            0       6     0  this   Lscala/collection/AbstractMapView;
            0       6     1  keys   Lscala/collection/IterableOnce;
    Deprecated: true
    MethodParameters:
      Name                           Flags
      keys                           final

  public scala.collection.IterableOps $plus$plus$colon(scala.collection.IterableOnce);
    descriptor: (Lscala/collection/IterableOnce;)Lscala/collection/IterableOps;
    flags: (0x0001) ACC_PUBLIC
    Code:
      stack=2, locals=2, args_size=2
         0: aload_0
         1: aload_1
         2: invokestatic  #266                // InterfaceMethod scala/collection/MapOps.$plus$plus$colon$:(Lscala/collection/MapOps;Lscala/collection/IterableOnce;)Lscala/collection/IterableOps;
         5: areturn
      LineNumberTable:
        line 186: 0
      LocalVariableTable:
        Start  Length  Slot  Name   Signature
            0       6     0  this   Lscala/collection/AbstractMapView;
            0       6     1  that   Lscala/collection/IterableOnce;
    Deprecated: true
    MethodParameters:
      Name                           Flags
      that                           final

  public scala.Option<V> unapply(K);
    descriptor: (Ljava/lang/Object;)Lscala/Option;
    flags: (0x0001) ACC_PUBLIC
    Code:
      stack=2, locals=2, args_size=2
         0: aload_0
         1: aload_1
         2: invokestatic  #276                // InterfaceMethod scala/PartialFunction.unapply$:(Lscala/PartialFunction;Ljava/lang/Object;)Lscala/Option;
         5: areturn
      LineNumberTable:
        line 186: 0
      LocalVariableTable:
        Start  Length  Slot  Name   Signature
            0       6     0  this   Lscala/collection/AbstractMapView;
            0       6     1     a   Ljava/lang/Object;
    Signature: #269                         // (TK;)Lscala/Option<TV;>;
    MethodParameters:
      Name                           Flags
      a                              final

  public scala.PartialFunction<K, V> elementWise();
    descriptor: ()Lscala/PartialFunction;
    flags: (0x0001) ACC_PUBLIC
    Code:
      stack=1, locals=1, args_size=1
         0: aload_0
         1: invokestatic  #283                // InterfaceMethod scala/PartialFunction.elementWise$:(Lscala/PartialFunction;)Lscala/PartialFunction;
         4: areturn
      LineNumberTable:
        line 186: 0
      LocalVariableTable:
        Start  Length  Slot  Name   Signature
            0       5     0  this   Lscala/collection/AbstractMapView;
    Signature: #279                         // ()Lscala/PartialFunction<TK;TV;>;

  public <A1 extends K, B1 extends java.lang.Object> scala.PartialFunction<A1, B1> orElse(scala.PartialFunction<A1, B1>);
    descriptor: (Lscala/PartialFunction;)Lscala/PartialFunction;
    flags: (0x0001) ACC_PUBLIC
    Code:
      stack=2, locals=2, args_size=2
         0: aload_0
         1: aload_1
         2: invokestatic  #289                // InterfaceMethod scala/PartialFunction.orElse$:(Lscala/PartialFunction;Lscala/PartialFunction;)Lscala/PartialFunction;
         5: areturn
      LineNumberTable:
        line 186: 0
      LocalVariableTable:
        Start  Length  Slot  Name   Signature
            0       6     0  this   Lscala/collection/AbstractMapView;
            0       6     1  that   Lscala/PartialFunction;
    Signature: #285                         // <A1:TK;B1:Ljava/lang/Object;>(Lscala/PartialFunction<TA1;TB1;>;)Lscala/PartialFunction<TA1;TB1;>;
    MethodParameters:
      Name                           Flags
      that                           final

  public <C$ extends java.lang.Object> scala.PartialFunction<K, C$> andThen(scala.Function1<V, C$>);
    descriptor: (Lscala/Function1;)Lscala/PartialFunction;
    flags: (0x0001) ACC_PUBLIC
    Code:
      stack=2, locals=2, args_size=2
         0: aload_0
         1: aload_1
         2: invokestatic  #297                // InterfaceMethod scala/PartialFunction.andThen$:(Lscala/PartialFunction;Lscala/Function1;)Lscala/PartialFunction;
         5: areturn
      LineNumberTable:
        line 186: 0
      LocalVariableTable:
        Start  Length  Slot  Name   Signature
            0       6     0  this   Lscala/collection/AbstractMapView;
            0       6     1     k   Lscala/Function1;
    Signature: #292                         // <C$:Ljava/lang/Object;>(Lscala/Function1<TV;TC$;>;)Lscala/PartialFunction<TK;TC$;>;
    MethodParameters:
      Name                           Flags
      k                              final

  public <C$ extends java.lang.Object> scala.PartialFunction<K, C$> andThen(scala.PartialFunction<V, C$>);
    descriptor: (Lscala/PartialFunction;)Lscala/PartialFunction;
    flags: (0x0001) ACC_PUBLIC
    Code:
      stack=2, locals=2, args_size=2
         0: aload_0
         1: aload_1
         2: invokestatic  #300                // InterfaceMethod scala/PartialFunction.andThen$:(Lscala/PartialFunction;Lscala/PartialFunction;)Lscala/PartialFunction;
         5: areturn
      LineNumberTable:
        line 186: 0
      LocalVariableTable:
        Start  Length  Slot  Name   Signature
            0       6     0  this   Lscala/collection/AbstractMapView;
            0       6     1     k   Lscala/PartialFunction;
    Signature: #298                         // <C$:Ljava/lang/Object;>(Lscala/PartialFunction<TV;TC$;>;)Lscala/PartialFunction<TK;TC$;>;
    MethodParameters:
      Name                           Flags
      k                              final

  public <R$ extends java.lang.Object> scala.PartialFunction<R$, V> compose(scala.PartialFunction<R$, K>);
    descriptor: (Lscala/PartialFunction;)Lscala/PartialFunction;
    flags: (0x0001) ACC_PUBLIC
    Code:
      stack=2, locals=2, args_size=2
         0: aload_0
         1: aload_1
         2: invokestatic  #305                // InterfaceMethod scala/PartialFunction.compose$:(Lscala/PartialFunction;Lscala/PartialFunction;)Lscala/PartialFunction;
         5: areturn
      LineNumberTable:
        line 186: 0
      LocalVariableTable:
        Start  Length  Slot  Name   Signature
            0       6     0  this   Lscala/collection/AbstractMapView;
            0       6     1     k   Lscala/PartialFunction;
    Signature: #302                         // <R$:Ljava/lang/Object;>(Lscala/PartialFunction<TR$;TK;>;)Lscala/PartialFunction<TR$;TV;>;
    MethodParameters:
      Name                           Flags
      k                              final

  public scala.Function1<K, scala.Option<V>> lift();
    descriptor: ()Lscala/Function1;
    flags: (0x0001) ACC_PUBLIC
    Code:
      stack=1, locals=1, args_size=1
         0: aload_0
         1: invokestatic  #312                // InterfaceMethod scala/PartialFunction.lift$:(Lscala/PartialFunction;)Lscala/Function1;
         4: areturn
      LineNumberTable:
        line 186: 0
      LocalVariableTable:
        Start  Length  Slot  Name   Signature
            0       5     0  this   Lscala/collection/AbstractMapView;
    Signature: #308                         // ()Lscala/Function1<TK;Lscala/Option<TV;>;>;

  public <U extends java.lang.Object> scala.Function1<K, java.lang.Object> runWith(scala.Function1<V, U>);
    descriptor: (Lscala/Function1;)Lscala/Function1;
    flags: (0x0001) ACC_PUBLIC
    Code:
      stack=2, locals=2, args_size=2
         0: aload_0
         1: aload_1
         2: invokestatic  #320                // InterfaceMethod scala/PartialFunction.runWith$:(Lscala/PartialFunction;Lscala/Function1;)Lscala/Function1;
         5: areturn
      LineNumberTable:
        line 186: 0
      LocalVariableTable:
        Start  Length  Slot  Name   Signature
            0       6     0  this   Lscala/collection/AbstractMapView;
            0       6     1 action   Lscala/Function1;
    Signature: #315                         // <U:Ljava/lang/Object;>(Lscala/Function1<TV;TU;>;)Lscala/Function1<TK;Ljava/lang/Object;>;
    MethodParameters:
      Name                           Flags
      action                         final

  public boolean apply$mcZD$sp(double);
    descriptor: (D)Z
    flags: (0x0001) ACC_PUBLIC
    Code:
      stack=3, locals=3, args_size=2
         0: aload_0
         1: dload_1
         2: invokestatic  #329                // InterfaceMethod scala/Function1.apply$mcZD$sp$:(Lscala/Function1;D)Z
         5: ireturn
      LineNumberTable:
        line 186: 0
      LocalVariableTable:
        Start  Length  Slot  Name   Signature
            0       6     0  this   Lscala/collection/AbstractMapView;
            0       6     1    v1   D
    MethodParameters:
      Name                           Flags
      v1                             final

  public double apply$mcDD$sp(double);
    descriptor: (D)D
    flags: (0x0001) ACC_PUBLIC
    Code:
      stack=3, locals=3, args_size=2
         0: aload_0
         1: dload_1
         2: invokestatic  #336                // InterfaceMethod scala/Function1.apply$mcDD$sp$:(Lscala/Function1;D)D
         5: dreturn
      LineNumberTable:
        line 186: 0
      LocalVariableTable:
        Start  Length  Slot  Name   Signature
            0       6     0  this   Lscala/collection/AbstractMapView;
            0       6     1    v1   D
    MethodParameters:
      Name                           Flags
      v1                             final

  public float apply$mcFD$sp(double);
    descriptor: (D)F
    flags: (0x0001) ACC_PUBLIC
    Code:
      stack=3, locals=3, args_size=2
         0: aload_0
         1: dload_1
         2: invokestatic  #342                // InterfaceMethod scala/Function1.apply$mcFD$sp$:(Lscala/Function1;D)F
         5: freturn
      LineNumberTable:
        line 186: 0
      LocalVariableTable:
        Start  Length  Slot  Name   Signature
            0       6     0  this   Lscala/collection/AbstractMapView;
            0       6     1    v1   D
    MethodParameters:
      Name                           Flags
      v1                             final

  public int apply$mcID$sp(double);
    descriptor: (D)I
    flags: (0x0001) ACC_PUBLIC
    Code:
      stack=3, locals=3, args_size=2
         0: aload_0
         1: dload_1
         2: invokestatic  #348                // InterfaceMethod scala/Function1.apply$mcID$sp$:(Lscala/Function1;D)I
         5: ireturn
      LineNumberTable:
        line 186: 0
      LocalVariableTable:
        Start  Length  Slot  Name   Signature
            0       6     0  this   Lscala/collection/AbstractMapView;
            0       6     1    v1   D
    MethodParameters:
      Name                           Flags
      v1                             final

  public long apply$mcJD$sp(double);
    descriptor: (D)J
    flags: (0x0001) ACC_PUBLIC
    Code:
      stack=3, locals=3, args_size=2
         0: aload_0
         1: dload_1
         2: invokestatic  #354                // InterfaceMethod scala/Function1.apply$mcJD$sp$:(Lscala/Function1;D)J
         5: lreturn
      LineNumberTable:
        line 186: 0
      LocalVariableTable:
        Start  Length  Slot  Name   Signature
            0       6     0  this   Lscala/collection/AbstractMapView;
            0       6     1    v1   D
    MethodParameters:
      Name                           Flags
      v1                             final

  public void apply$mcVD$sp(double);
    descriptor: (D)V
    flags: (0x0001) ACC_PUBLIC
    Code:
      stack=3, locals=3, args_size=2
         0: aload_0
         1: dload_1
         2: invokestatic  #360                // InterfaceMethod scala/Function1.apply$mcVD$sp$:(Lscala/Function1;D)V
         5: return
      LineNumberTable:
        line 186: 0
      LocalVariableTable:
        Start  Length  Slot  Name   Signature
            0       6     0  this   Lscala/collection/AbstractMapView;
            0       6     1    v1   D
    MethodParameters:
      Name                           Flags
      v1                             final

  public boolean apply$mcZF$sp(float);
    descriptor: (F)Z
    flags: (0x0001) ACC_PUBLIC
    Code:
      stack=2, locals=2, args_size=2
         0: aload_0
         1: fload_1
         2: invokestatic  #366                // InterfaceMethod scala/Function1.apply$mcZF$sp$:(Lscala/Function1;F)Z
         5: ireturn
      LineNumberTable:
        line 186: 0
      LocalVariableTable:
        Start  Length  Slot  Name   Signature
            0       6     0  this   Lscala/collection/AbstractMapView;
            0       6     1    v1   F
    MethodParameters:
      Name                           Flags
      v1                             final

  public double apply$mcDF$sp(float);
    descriptor: (F)D
    flags: (0x0001) ACC_PUBLIC
    Code:
      stack=2, locals=2, args_size=2
         0: aload_0
         1: fload_1
         2: invokestatic  #373                // InterfaceMethod scala/Function1.apply$mcDF$sp$:(Lscala/Function1;F)D
         5: dreturn
      LineNumberTable:
        line 186: 0
      LocalVariableTable:
        Start  Length  Slot  Name   Signature
            0       6     0  this   Lscala/collection/AbstractMapView;
            0       6     1    v1   F
    MethodParameters:
      Name                           Flags
      v1                             final

  public float apply$mcFF$sp(float);
    descriptor: (F)F
    flags: (0x0001) ACC_PUBLIC
    Code:
      stack=2, locals=2, args_size=2
         0: aload_0
         1: fload_1
         2: invokestatic  #379                // InterfaceMethod scala/Function1.apply$mcFF$sp$:(Lscala/Function1;F)F
         5: freturn
      LineNumberTable:
        line 186: 0
      LocalVariableTable:
        Start  Length  Slot  Name   Signature
            0       6     0  this   Lscala/collection/AbstractMapView;
            0       6     1    v1   F
    MethodParameters:
      Name                           Flags
      v1                             final

  public int apply$mcIF$sp(float);
    descriptor: (F)I
    flags: (0x0001) ACC_PUBLIC
    Code:
      stack=2, locals=2, args_size=2
         0: aload_0
         1: fload_1
         2: invokestatic  #385                // InterfaceMethod scala/Function1.apply$mcIF$sp$:(Lscala/Function1;F)I
         5: ireturn
      LineNumberTable:
        line 186: 0
      LocalVariableTable:
        Start  Length  Slot  Name   Signature
            0       6     0  this   Lscala/collection/AbstractMapView;
            0       6     1    v1   F
    MethodParameters:
      Name                           Flags
      v1                             final

  public long apply$mcJF$sp(float);
    descriptor: (F)J
    flags: (0x0001) ACC_PUBLIC
    Code:
      stack=2, locals=2, args_size=2
         0: aload_0
         1: fload_1
         2: invokestatic  #391                // InterfaceMethod scala/Function1.apply$mcJF$sp$:(Lscala/Function1;F)J
         5: lreturn
      LineNumberTable:
        line 186: 0
      LocalVariableTable:
        Start  Length  Slot  Name   Signature
            0       6     0  this   Lscala/collection/AbstractMapView;
            0       6     1    v1   F
    MethodParameters:
      Name                           Flags
      v1                             final

  public void apply$mcVF$sp(float);
    descriptor: (F)V
    flags: (0x0001) ACC_PUBLIC
    Code:
      stack=2, locals=2, args_size=2
         0: aload_0
         1: fload_1
         2: invokestatic  #397                // InterfaceMethod scala/Function1.apply$mcVF$sp$:(Lscala/Function1;F)V
         5: return
      LineNumberTable:
        line 186: 0
      LocalVariableTable:
        Start  Length  Slot  Name   Signature
            0       6     0  this   Lscala/collection/AbstractMapView;
            0       6     1    v1   F
    MethodParameters:
      Name                           Flags
      v1                             final

  public boolean apply$mcZI$sp(int);
    descriptor: (I)Z
    flags: (0x0001) ACC_PUBLIC
    Code:
      stack=2, locals=2, args_size=2
         0: aload_0
         1: iload_1
         2: invokestatic  #403                // InterfaceMethod scala/Function1.apply$mcZI$sp$:(Lscala/Function1;I)Z
         5: ireturn
      LineNumberTable:
        line 186: 0
      LocalVariableTable:
        Start  Length  Slot  Name   Signature
            0       6     0  this   Lscala/collection/AbstractMapView;
            0       6     1    v1   I
    MethodParameters:
      Name                           Flags
      v1                             final

  public double apply$mcDI$sp(int);
    descriptor: (I)D
    flags: (0x0001) ACC_PUBLIC
    Code:
      stack=2, locals=2, args_size=2
         0: aload_0
         1: iload_1
         2: invokestatic  #410                // InterfaceMethod scala/Function1.apply$mcDI$sp$:(Lscala/Function1;I)D
         5: dreturn
      LineNumberTable:
        line 186: 0
      LocalVariableTable:
        Start  Length  Slot  Name   Signature
            0       6     0  this   Lscala/collection/AbstractMapView;
            0       6     1    v1   I
    MethodParameters:
      Name                           Flags
      v1                             final

  public float apply$mcFI$sp(int);
    descriptor: (I)F
    flags: (0x0001) ACC_PUBLIC
    Code:
      stack=2, locals=2, args_size=2
         0: aload_0
         1: iload_1
         2: invokestatic  #416                // InterfaceMethod scala/Function1.apply$mcFI$sp$:(Lscala/Function1;I)F
         5: freturn
      LineNumberTable:
        line 186: 0
      LocalVariableTable:
        Start  Length  Slot  Name   Signature
            0       6     0  this   Lscala/collection/AbstractMapView;
            0       6     1    v1   I
    MethodParameters:
      Name                           Flags
      v1                             final

  public int apply$mcII$sp(int);
    descriptor: (I)I
    flags: (0x0001) ACC_PUBLIC
    Code:
      stack=2, locals=2, args_size=2
         0: aload_0
         1: iload_1
         2: invokestatic  #422                // InterfaceMethod scala/Function1.apply$mcII$sp$:(Lscala/Function1;I)I
         5: ireturn
      LineNumberTable:
        line 186: 0
      LocalVariableTable:
        Start  Length  Slot  Name   Signature
            0       6     0  this   Lscala/collection/AbstractMapView;
            0       6     1    v1   I
    MethodParameters:
      Name                           Flags
      v1                             final

  public long apply$mcJI$sp(int);
    descriptor: (I)J
    flags: (0x0001) ACC_PUBLIC
    Code:
      stack=2, locals=2, args_size=2
         0: aload_0
         1: iload_1
         2: invokestatic  #428                // InterfaceMethod scala/Function1.apply$mcJI$sp$:(Lscala/Function1;I)J
         5: lreturn
      LineNumberTable:
        line 186: 0
      LocalVariableTable:
        Start  Length  Slot  Name   Signature
            0       6     0  this   Lscala/collection/AbstractMapView;
            0       6     1    v1   I
    MethodParameters:
      Name                           Flags
      v1                             final

  public void apply$mcVI$sp(int);
    descriptor: (I)V
    flags: (0x0001) ACC_PUBLIC
    Code:
      stack=2, locals=2, args_size=2
         0: aload_0
         1: iload_1
         2: invokestatic  #434                // InterfaceMethod scala/Function1.apply$mcVI$sp$:(Lscala/Function1;I)V
         5: return
      LineNumberTable:
        line 186: 0
      LocalVariableTable:
        Start  Length  Slot  Name   Signature
            0       6     0  this   Lscala/collection/AbstractMapView;
            0       6     1    v1   I
    MethodParameters:
      Name                           Flags
      v1                             final

  public boolean apply$mcZJ$sp(long);
    descriptor: (J)Z
    flags: (0x0001) ACC_PUBLIC
    Code:
      stack=3, locals=3, args_size=2
         0: aload_0
         1: lload_1
         2: invokestatic  #440                // InterfaceMethod scala/Function1.apply$mcZJ$sp$:(Lscala/Function1;J)Z
         5: ireturn
      LineNumberTable:
        line 186: 0
      LocalVariableTable:
        Start  Length  Slot  Name   Signature
            0       6     0  this   Lscala/collection/AbstractMapView;
            0       6     1    v1   J
    MethodParameters:
      Name                           Flags
      v1                             final

  public double apply$mcDJ$sp(long);
    descriptor: (J)D
    flags: (0x0001) ACC_PUBLIC
    Code:
      stack=3, locals=3, args_size=2
         0: aload_0
         1: lload_1
         2: invokestatic  #446                // InterfaceMethod scala/Function1.apply$mcDJ$sp$:(Lscala/Function1;J)D
         5: dreturn
      LineNumberTable:
        line 186: 0
      LocalVariableTable:
        Start  Length  Slot  Name   Signature
            0       6     0  this   Lscala/collection/AbstractMapView;
            0       6     1    v1   J
    MethodParameters:
      Name                           Flags
      v1                             final

  public float apply$mcFJ$sp(long);
    descriptor: (J)F
    flags: (0x0001) ACC_PUBLIC
    Code:
      stack=3, locals=3, args_size=2
         0: aload_0
         1: lload_1
         2: invokestatic  #452                // InterfaceMethod scala/Function1.apply$mcFJ$sp$:(Lscala/Function1;J)F
         5: freturn
      LineNumberTable:
        line 186: 0
      LocalVariableTable:
        Start  Length  Slot  Name   Signature
            0       6     0  this   Lscala/collection/AbstractMapView;
            0       6     1    v1   J
    MethodParameters:
      Name                           Flags
      v1                             final

  public int apply$mcIJ$sp(long);
    descriptor: (J)I
    flags: (0x0001) ACC_PUBLIC
    Code:
      stack=3, locals=3, args_size=2
         0: aload_0
         1: lload_1
         2: invokestatic  #458                // InterfaceMethod scala/Function1.apply$mcIJ$sp$:(Lscala/Function1;J)I
         5: ireturn
      LineNumberTable:
        line 186: 0
      LocalVariableTable:
        Start  Length  Slot  Name   Signature
            0       6     0  this   Lscala/collection/AbstractMapView;
            0       6     1    v1   J
    MethodParameters:
      Name                           Flags
      v1                             final

  public long apply$mcJJ$sp(long);
    descriptor: (J)J
    flags: (0x0001) ACC_PUBLIC
    Code:
      stack=3, locals=3, args_size=2
         0: aload_0
         1: lload_1
         2: invokestatic  #464                // InterfaceMethod scala/Function1.apply$mcJJ$sp$:(Lscala/Function1;J)J
         5: lreturn
      LineNumberTable:
        line 186: 0
      LocalVariableTable:
        Start  Length  Slot  Name   Signature
            0       6     0  this   Lscala/collection/AbstractMapView;
            0       6     1    v1   J
    MethodParameters:
      Name                           Flags
      v1                             final

  public void apply$mcVJ$sp(long);
    descriptor: (J)V
    flags: (0x0001) ACC_PUBLIC
    Code:
      stack=3, locals=3, args_size=2
         0: aload_0
         1: lload_1
         2: invokestatic  #470                // InterfaceMethod scala/Function1.apply$mcVJ$sp$:(Lscala/Function1;J)V
         5: return
      LineNumberTable:
        line 186: 0
      LocalVariableTable:
        Start  Length  Slot  Name   Signature
            0       6     0  this   Lscala/collection/AbstractMapView;
            0       6     1    v1   J
    MethodParameters:
      Name                           Flags
      v1                             final

  public <A$ extends java.lang.Object> scala.Function1<A$, V> compose(scala.Function1<A$, K>);
    descriptor: (Lscala/Function1;)Lscala/Function1;
    flags: (0x0001) ACC_PUBLIC
    Code:
      stack=2, locals=2, args_size=2
         0: aload_0
         1: aload_1
         2: invokestatic  #475                // InterfaceMethod scala/Function1.compose$:(Lscala/Function1;Lscala/Function1;)Lscala/Function1;
         5: areturn
      LineNumberTable:
        line 186: 0
      LocalVariableTable:
        Start  Length  Slot  Name   Signature
            0       6     0  this   Lscala/collection/AbstractMapView;
            0       6     1     g   Lscala/Function1;
    Signature: #471                         // <A$:Ljava/lang/Object;>(Lscala/Function1<TA$;TK;>;)Lscala/Function1<TA$;TV;>;
    MethodParameters:
      Name                           Flags
      g                              final

  public scala.Function1 andThen(scala.Function1);
    descriptor: (Lscala/Function1;)Lscala/Function1;
    flags: (0x1041) ACC_PUBLIC, ACC_BRIDGE, ACC_SYNTHETIC
    Code:
      stack=2, locals=2, args_size=2
         0: aload_0
         1: aload_1
         2: invokevirtual #477                // Method andThen:(Lscala/Function1;)Lscala/PartialFunction;
         5: areturn
      LineNumberTable:
        line 186: 0
      LocalVariableTable:
        Start  Length  Slot  Name   Signature
            0       6     0  this   Lscala/collection/AbstractMapView;
            0       6     1     g   Lscala/Function1;
    MethodParameters:
      Name                           Flags
      g                              final

  public scala.collection.WithFilter withFilter(scala.Function1);
    descriptor: (Lscala/Function1;)Lscala/collection/WithFilter;
    flags: (0x1041) ACC_PUBLIC, ACC_BRIDGE, ACC_SYNTHETIC
    Code:
      stack=2, locals=2, args_size=2
         0: aload_0
         1: aload_1
         2: invokevirtual #480                // Method withFilter:(Lscala/Function1;)Lscala/collection/MapOps$WithFilter;
         5: areturn
      LineNumberTable:
        line 186: 0
      LocalVariableTable:
        Start  Length  Slot  Name   Signature
            0       6     0  this   Lscala/collection/AbstractMapView;
            0       6     1     p   Lscala/Function1;
    MethodParameters:
      Name                           Flags
      p                              final

  public java.lang.Object empty();
    descriptor: ()Ljava/lang/Object;
    flags: (0x1041) ACC_PUBLIC, ACC_BRIDGE, ACC_SYNTHETIC
    Code:
      stack=1, locals=1, args_size=1
         0: aload_0
         1: invokevirtual #483                // Method empty:()Lscala/collection/MapView;
         4: areturn
      LineNumberTable:
        line 186: 0
      LocalVariableTable:
        Start  Length  Slot  Name   Signature
            0       5     0  this   Lscala/collection/AbstractMapView;

  public scala.collection.IterableOps empty();
    descriptor: ()Lscala/collection/IterableOps;
    flags: (0x1041) ACC_PUBLIC, ACC_BRIDGE, ACC_SYNTHETIC
    Code:
      stack=1, locals=1, args_size=1
         0: aload_0
         1: invokevirtual #483                // Method empty:()Lscala/collection/MapView;
         4: areturn
      LineNumberTable:
        line 186: 0
      LocalVariableTable:
        Start  Length  Slot  Name   Signature
            0       5     0  this   Lscala/collection/AbstractMapView;

  public scala.collection.View empty();
    descriptor: ()Lscala/collection/View;
    flags: (0x1041) ACC_PUBLIC, ACC_BRIDGE, ACC_SYNTHETIC
    Code:
      stack=1, locals=1, args_size=1
         0: aload_0
         1: invokevirtual #483                // Method empty:()Lscala/collection/MapView;
         4: areturn
      LineNumberTable:
        line 186: 0
      LocalVariableTable:
        Start  Length  Slot  Name   Signature
            0       5     0  this   Lscala/collection/AbstractMapView;

  public scala.collection.MapFactory mapFactory();
    descriptor: ()Lscala/collection/MapFactory;
    flags: (0x1041) ACC_PUBLIC, ACC_BRIDGE, ACC_SYNTHETIC
    Code:
      stack=1, locals=1, args_size=1
         0: aload_0
         1: invokevirtual #488                // Method mapFactory:()Lscala/collection/MapViewFactory;
         4: areturn
      LineNumberTable:
        line 186: 0
      LocalVariableTable:
        Start  Length  Slot  Name   Signature
            0       5     0  this   Lscala/collection/AbstractMapView;

  public java.lang.Object tapEach(scala.Function1);
    descriptor: (Lscala/Function1;)Ljava/lang/Object;
    flags: (0x1041) ACC_PUBLIC, ACC_BRIDGE, ACC_SYNTHETIC
    Code:
      stack=2, locals=2, args_size=2
         0: aload_0
         1: aload_1
         2: invokevirtual #491                // Method tapEach:(Lscala/Function1;)Lscala/collection/MapView;
         5: areturn
      LineNumberTable:
        line 186: 0
      LocalVariableTable:
        Start  Length  Slot  Name   Signature
            0       6     0  this   Lscala/collection/AbstractMapView;
            0       6     1     f   Lscala/Function1;
    MethodParameters:
      Name                           Flags
      f                              final

  public java.lang.Object filterNot(scala.Function1);
    descriptor: (Lscala/Function1;)Ljava/lang/Object;
    flags: (0x1041) ACC_PUBLIC, ACC_BRIDGE, ACC_SYNTHETIC
    Code:
      stack=2, locals=2, args_size=2
         0: aload_0
         1: aload_1
         2: invokevirtual #493                // Method filterNot:(Lscala/Function1;)Lscala/collection/MapView;
         5: areturn
      LineNumberTable:
        line 186: 0
      LocalVariableTable:
        Start  Length  Slot  Name   Signature
            0       6     0  this   Lscala/collection/AbstractMapView;
            0       6     1  pred   Lscala/Function1;
    MethodParameters:
      Name                           Flags
      pred                           final

  public java.lang.Object filter(scala.Function1);
    descriptor: (Lscala/Function1;)Ljava/lang/Object;
    flags: (0x1041) ACC_PUBLIC, ACC_BRIDGE, ACC_SYNTHETIC
    Code:
      stack=2, locals=2, args_size=2
         0: aload_0
         1: aload_1
         2: invokevirtual #495                // Method filter:(Lscala/Function1;)Lscala/collection/MapView;
         5: areturn
      LineNumberTable:
        line 186: 0
      LocalVariableTable:
        Start  Length  Slot  Name   Signature
            0       6     0  this   Lscala/collection/AbstractMapView;
            0       6     1  pred   Lscala/Function1;
    MethodParameters:
      Name                           Flags
      pred                           final

  public scala.collection.View view();
    descriptor: ()Lscala/collection/View;
    flags: (0x1041) ACC_PUBLIC, ACC_BRIDGE, ACC_SYNTHETIC
    Code:
      stack=1, locals=1, args_size=1
         0: aload_0
         1: invokevirtual #497                // Method view:()Lscala/collection/MapView;
         4: areturn
      LineNumberTable:
        line 186: 0
      LocalVariableTable:
        Start  Length  Slot  Name   Signature
            0       5     0  this   Lscala/collection/AbstractMapView;

  public scala.collection.AbstractMapView();
    descriptor: ()V
    flags: (0x0001) ACC_PUBLIC
    Code:
      stack=1, locals=1, args_size=1
         0: aload_0
         1: invokespecial #501                // Method scala/collection/AbstractView."<init>":()V
         4: return
      LineNumberTable:
        line 186: 0
      LocalVariableTable:
        Start  Length  Slot  Name   Signature
            0       5     0  this   Lscala/collection/AbstractMapView;
}
InnerClasses:
  public static #16= #13 of #15;          // WithFilter=class scala/collection/MapOps$WithFilter of class scala/collection/MapOps
Signature: #3                           // <K:Ljava/lang/Object;V:Ljava/lang/Object;>Lscala/collection/AbstractView<Lscala/Tuple2<TK;TV;>;>;Lscala/collection/MapView<TK;TV;>;
SourceFile: "MapView.scala"
RuntimeVisibleAnnotations:
  0: #9(#10=s#11)
    scala.reflect.ScalaSignature(
      bytes="\u0006\u000512QAA\u0002\u0002\u0002!AQa\t\u0001\u0005\u0002\u0011\u0012q\"\u00112tiJ\f7\r^\'baZKWm\u001e\u0006\u0003\t\u0015\t!bY8mY\u0016\u001cG/[8o\u0015\u00051\u0011!B:dC2\f7\u0001A\u000b\u0004\u0013Qq2c\u0001\u0001\u000bAA\u00191\u0002\u0004\b\u000e\u0003\rI!!D\u0002\u0003\u0019\u0005\u00137\u000f\u001e:bGR4\u0016.Z<\u0011\t=\u0001\"#H\u0007\u0002\u000b%\u0011\u0011#\u0002\u0002\u0007)V\u0004H.\u001a\u001a\u0011\u0005M!B\u0002\u0001\u0003\u0006+\u0001\u0011\rA\u0006\u0002\u0002\u0017F\u0011qC\u0007\t\u0003\u001faI!!G\u0003\u0003\u000f9{G\u000f[5oOB\u0011qbG\u0005\u00039\u0015\u00111!\u00118z!\t\u0019b\u0004\u0002\u0004 \u0001\u0011\u0015\rA\u0006\u0002\u0002-B!1\"\t\n\u001e\u0013\t\u00113AA\u0004NCB4\u0016.Z<\u0002\rqJg.\u001b;?)\u0005)\u0003\u0003B\u0006\u0001%uAC\u0001A\u0014+WA\u0011q\u0002K\u0005\u0003S\u0015\u0011\u0001cU3sS\u0006dg+\u001a:tS>tW+\u0013#\u0002\u000bY\fG.^3\u001f\u0003\r\u0001"
    )
  ScalaInlineInfo: length = 0x199 (unknown attribute)
   01 00 00 51 01 00 01 01 04 00 F0 00 F1 00 00 F0
   00 F8 00 00 DF 00 D8 00 01 06 00 D8 00 01 F2 01
   F3 00 00 E4 00 E5 00 01 22 01 3A 00 01 22 01 23
   00 01 22 01 19 00 00 8B 00 8C 00 01 4B 01 4C 00
   01 70 01 71 00 01 95 01 96 00 01 B9 01 BA 00 01
   51 01 52 00 01 76 01 77 00 01 9B 01 9C 00 01 BF
   01 C0 00 01 57 01 58 00 01 7C 01 7D 00 01 A1 01
   A2 00 01 C5 01 C6 00 01 5D 01 5E 00 01 82 01 83
   00 01 A7 01 A8 00 01 CB 01 CC 00 01 63 01 64 00
   01 88 01 89 00 01 AD 01 AE 00 01 D1 01 D2 00 01
   41 01 42 00 01 69 01 6A 00 01 8E 01 8F 00 01 B3
   01 B4 00 00 94 00 95 00 00 CB 00 CC 00 01 2D 01
   3A 00 01 2D 01 19 00 00 D7 00 D8 00 00 BA 00 BB
   00 00 84 00 8C 00 01 15 01 16 00 00 55 01 E1 00
   00 55 01 E4 00 00 55 00 16 00 00 55 01 E5 00 00
   39 01 E9 00 00 39 00 2B 00 00 2A 00 2B 00 00 3F
   01 E9 00 00 3F 00 2B 00 00 D3 00 C6 00 00 AF 00
   B0 00 00 80 00 81 00 00 C1 00 BB 00 00 9C 00 9D
   00 00 6A 00 6B 00 00 1E 00 1F 00 00 A3 00 A4 00
   01 32 01 33 00 00 C5 00 C6 00 00 4F 01 E6 00 00
   4F 00 50 00 00 78 00 79 05 00 33 00 2B 00 01 1C
   01 19 00 00 43 00 44 00 01 39 01 3A 00 00 66 00
   61 00 00 4A 01 E9 00 00 4A 00 2B 00 00 60 00 61
   00 01 0B 01 0C 00 00 73 00 6B 00 00 25 00 1F 00
   00 AA 00 A4 00 00 15 00 16 00 00 15 01 E5 00 00
   59 00 5A 00 00 59 01 DE 00
  ScalaSig: length = 0x3 (unknown attribute)
   05 02 00
