Classfile /Users/mw/Projects/slang-braindump/.jar/jar8/assemble/slang-braindump/assemble/content/scala/collection/AbstractView.class
  Last modified May 29, 2022; size 2238 bytes
  SHA-256 checksum 823e5c5429a86d32be85e5ccfdbfaa412b959cdfaa39b23fb16fbca998c05eae
  Compiled from "View.scala"
public abstract class scala.collection.AbstractView<A extends java.lang.Object> extends scala.collection.AbstractIterable<A> implements scala.collection.View<A>
  minor version: 0
  major version: 52
  flags: (0x0421) ACC_PUBLIC, ACC_SUPER, ACC_ABSTRACT
  this_class: #2                          // scala/collection/AbstractView
  super_class: #5                         // scala/collection/AbstractIterable
  interfaces: 1, fields: 1, methods: 9, attributes: 5
Constant pool:
   #1 = Utf8               scala/collection/AbstractView
   #2 = Class              #1             // scala/collection/AbstractView
   #3 = Utf8               <A:Ljava/lang/Object;>Lscala/collection/AbstractIterable<TA;>;Lscala/collection/View<TA;>;
   #4 = Utf8               scala/collection/AbstractIterable
   #5 = Class              #4             // scala/collection/AbstractIterable
   #6 = Utf8               scala/collection/View
   #7 = Class              #6             // scala/collection/View
   #8 = Utf8               View.scala
   #9 = Utf8               Lscala/reflect/ScalaSignature;
  #10 = Utf8               bytes
  #11 = Utf8               \u0006\u0005\u00192QAA\u0002\u0002\u0002!AQ!\b\u0001\u0005\u0002y\u0011A\"\u00112tiJ\f7\r\u001e,jK^T!\u0001B\u0003\u0002\u0015\r|G\u000e\\3di&|gNC\u0001\u0007\u0003\u0015\u00198-\u00197b\u0007\u0001)\"!\u0003\t\u0014\u0007\u0001Q!\u0004E\u0002\f\u00199i\u0011aA\u0005\u0003\u001b\r\u0011\u0001#\u00112tiJ\f7\r^%uKJ\f\'\r\\3\u0011\u0005=\u0001B\u0002\u0001\u0003\u0007#\u0001!)\u0019\u0001\n\u0003\u0003\u0005\u000b\"aE\f\u0011\u0005Q)R\"A\u0003\n\u0005Y)!a\u0002(pi\"Lgn\u001a\t\u0003)aI!!G\u0003\u0003\u0007\u0005s\u0017\u0010E\u0002\f79I!\u0001H\u0002\u0003\tYKWm^\u0001\u0007y%t\u0017\u000e\u001e \u0015\u0003}\u00012a\u0003\u0001\u000fQ\u0011\u0001\u0011\u0005J\u0013\u0011\u0005Q\u0011\u0013BA\u0012\u0006\u0005A\u0019VM]5bYZ+\'o]5p]VKE)A\u0003wC2,XMH\u0001\u0004\u0001
  #12 = Utf8               serialVersionUID
  #13 = Utf8               J
  #14 = Long               3l
  #16 = Utf8               view
  #17 = Utf8               ()Lscala/collection/View;
  #18 = Utf8               ()Lscala/collection/View<TA;>;
  #19 = Utf8               view$
  #20 = Utf8               (Lscala/collection/View;)Lscala/collection/View;
  #21 = NameAndType        #19:#20        // view$:(Lscala/collection/View;)Lscala/collection/View;
  #22 = InterfaceMethodref #7.#21         // scala/collection/View.view$:(Lscala/collection/View;)Lscala/collection/View;
  #23 = Utf8               this
  #24 = Utf8               Lscala/collection/AbstractView;
  #25 = Utf8               iterableFactory
  #26 = Utf8               ()Lscala/collection/IterableFactory;
  #27 = Utf8               ()Lscala/collection/IterableFactory<Lscala/collection/View;>;
  #28 = Utf8               iterableFactory$
  #29 = Utf8               (Lscala/collection/View;)Lscala/collection/IterableFactory;
  #30 = NameAndType        #28:#29        // iterableFactory$:(Lscala/collection/View;)Lscala/collection/IterableFactory;
  #31 = InterfaceMethodref #7.#30         // scala/collection/View.iterableFactory$:(Lscala/collection/View;)Lscala/collection/IterableFactory;
  #32 = Utf8               empty
  #33 = Utf8               empty$
  #34 = NameAndType        #33:#20        // empty$:(Lscala/collection/View;)Lscala/collection/View;
  #35 = InterfaceMethodref #7.#34         // scala/collection/View.empty$:(Lscala/collection/View;)Lscala/collection/View;
  #36 = Utf8               toString
  #37 = Utf8               ()Ljava/lang/String;
  #38 = Utf8               toString$
  #39 = Utf8               (Lscala/collection/View;)Ljava/lang/String;
  #40 = NameAndType        #38:#39        // toString$:(Lscala/collection/View;)Ljava/lang/String;
  #41 = InterfaceMethodref #7.#40         // scala/collection/View.toString$:(Lscala/collection/View;)Ljava/lang/String;
  #42 = Utf8               stringPrefix
  #43 = Utf8               stringPrefix$
  #44 = NameAndType        #43:#39        // stringPrefix$:(Lscala/collection/View;)Ljava/lang/String;
  #45 = InterfaceMethodref #7.#44         // scala/collection/View.stringPrefix$:(Lscala/collection/View;)Ljava/lang/String;
  #46 = Utf8               force
  #47 = Utf8               ()Lscala/collection/IndexedSeq;
  #48 = Utf8               ()Lscala/collection/IndexedSeq<TA;>;
  #49 = Utf8               force$
  #50 = Utf8               (Lscala/collection/View;)Lscala/collection/IndexedSeq;
  #51 = NameAndType        #49:#50        // force$:(Lscala/collection/View;)Lscala/collection/IndexedSeq;
  #52 = InterfaceMethodref #7.#51         // scala/collection/View.force$:(Lscala/collection/View;)Lscala/collection/IndexedSeq;
  #53 = Utf8               ()Ljava/lang/Object;
  #54 = NameAndType        #32:#17        // empty:()Lscala/collection/View;
  #55 = Methodref          #2.#54         // scala/collection/AbstractView.empty:()Lscala/collection/View;
  #56 = Utf8               ()Lscala/collection/IterableOps;
  #57 = Utf8               <init>
  #58 = Utf8               ()V
  #59 = NameAndType        #57:#58        // "<init>":()V
  #60 = Methodref          #5.#59         // scala/collection/AbstractIterable."<init>":()V
  #61 = Utf8               ConstantValue
  #62 = Utf8               Code
  #63 = Utf8               LineNumberTable
  #64 = Utf8               LocalVariableTable
  #65 = Utf8               Signature
  #66 = Utf8               Deprecated
  #67 = Utf8               SourceFile
  #68 = Utf8               RuntimeVisibleAnnotations
  #69 = Utf8               ScalaInlineInfo
  #70 = Utf8               ScalaSig
{
  private static final long serialVersionUID;
    descriptor: J
    flags: (0x001a) ACC_PRIVATE, ACC_STATIC, ACC_FINAL
    ConstantValue: long 3l

  public scala.collection.View<A> view();
    descriptor: ()Lscala/collection/View;
    flags: (0x0001) ACC_PUBLIC
    Code:
      stack=1, locals=1, args_size=1
         0: aload_0
         1: invokestatic  #22                 // InterfaceMethod scala/collection/View.view$:(Lscala/collection/View;)Lscala/collection/View;
         4: areturn
      LineNumberTable:
        line 535: 0
      LocalVariableTable:
        Start  Length  Slot  Name   Signature
            0       5     0  this   Lscala/collection/AbstractView;
    Signature: #18                          // ()Lscala/collection/View<TA;>;

  public scala.collection.IterableFactory<scala.collection.View> iterableFactory();
    descriptor: ()Lscala/collection/IterableFactory;
    flags: (0x0001) ACC_PUBLIC
    Code:
      stack=1, locals=1, args_size=1
         0: aload_0
         1: invokestatic  #31                 // InterfaceMethod scala/collection/View.iterableFactory$:(Lscala/collection/View;)Lscala/collection/IterableFactory;
         4: areturn
      LineNumberTable:
        line 535: 0
      LocalVariableTable:
        Start  Length  Slot  Name   Signature
            0       5     0  this   Lscala/collection/AbstractView;
    Signature: #27                          // ()Lscala/collection/IterableFactory<Lscala/collection/View;>;

  public scala.collection.View<A> empty();
    descriptor: ()Lscala/collection/View;
    flags: (0x0001) ACC_PUBLIC
    Code:
      stack=1, locals=1, args_size=1
         0: aload_0
         1: invokestatic  #35                 // InterfaceMethod scala/collection/View.empty$:(Lscala/collection/View;)Lscala/collection/View;
         4: areturn
      LineNumberTable:
        line 535: 0
      LocalVariableTable:
        Start  Length  Slot  Name   Signature
            0       5     0  this   Lscala/collection/AbstractView;
    Signature: #18                          // ()Lscala/collection/View<TA;>;

  public java.lang.String toString();
    descriptor: ()Ljava/lang/String;
    flags: (0x0001) ACC_PUBLIC
    Code:
      stack=1, locals=1, args_size=1
         0: aload_0
         1: invokestatic  #41                 // InterfaceMethod scala/collection/View.toString$:(Lscala/collection/View;)Ljava/lang/String;
         4: areturn
      LineNumberTable:
        line 535: 0
      LocalVariableTable:
        Start  Length  Slot  Name   Signature
            0       5     0  this   Lscala/collection/AbstractView;

  public java.lang.String stringPrefix();
    descriptor: ()Ljava/lang/String;
    flags: (0x0001) ACC_PUBLIC
    Code:
      stack=1, locals=1, args_size=1
         0: aload_0
         1: invokestatic  #45                 // InterfaceMethod scala/collection/View.stringPrefix$:(Lscala/collection/View;)Ljava/lang/String;
         4: areturn
      LineNumberTable:
        line 535: 0
      LocalVariableTable:
        Start  Length  Slot  Name   Signature
            0       5     0  this   Lscala/collection/AbstractView;

  public scala.collection.IndexedSeq<A> force();
    descriptor: ()Lscala/collection/IndexedSeq;
    flags: (0x0001) ACC_PUBLIC
    Code:
      stack=1, locals=1, args_size=1
         0: aload_0
         1: invokestatic  #52                 // InterfaceMethod scala/collection/View.force$:(Lscala/collection/View;)Lscala/collection/IndexedSeq;
         4: areturn
      LineNumberTable:
        line 535: 0
      LocalVariableTable:
        Start  Length  Slot  Name   Signature
            0       5     0  this   Lscala/collection/AbstractView;
    Signature: #48                          // ()Lscala/collection/IndexedSeq<TA;>;
    Deprecated: true

  public java.lang.Object empty();
    descriptor: ()Ljava/lang/Object;
    flags: (0x1041) ACC_PUBLIC, ACC_BRIDGE, ACC_SYNTHETIC
    Code:
      stack=1, locals=1, args_size=1
         0: aload_0
         1: invokevirtual #55                 // Method empty:()Lscala/collection/View;
         4: areturn
      LineNumberTable:
        line 535: 0
      LocalVariableTable:
        Start  Length  Slot  Name   Signature
            0       5     0  this   Lscala/collection/AbstractView;

  public scala.collection.IterableOps empty();
    descriptor: ()Lscala/collection/IterableOps;
    flags: (0x1041) ACC_PUBLIC, ACC_BRIDGE, ACC_SYNTHETIC
    Code:
      stack=1, locals=1, args_size=1
         0: aload_0
         1: invokevirtual #55                 // Method empty:()Lscala/collection/View;
         4: areturn
      LineNumberTable:
        line 535: 0
      LocalVariableTable:
        Start  Length  Slot  Name   Signature
            0       5     0  this   Lscala/collection/AbstractView;

  public scala.collection.AbstractView();
    descriptor: ()V
    flags: (0x0001) ACC_PUBLIC
    Code:
      stack=1, locals=1, args_size=1
         0: aload_0
         1: invokespecial #60                 // Method scala/collection/AbstractIterable."<init>":()V
         4: return
      LineNumberTable:
        line 535: 0
        line 535: 4
      LocalVariableTable:
        Start  Length  Slot  Name   Signature
            0       5     0  this   Lscala/collection/AbstractView;
}
Signature: #3                           // <A:Ljava/lang/Object;>Lscala/collection/AbstractIterable<TA;>;Lscala/collection/View<TA;>;
SourceFile: "View.scala"
RuntimeVisibleAnnotations:
  0: #9(#10=s#11)
    scala.reflect.ScalaSignature(
      bytes="\u0006\u0005\u00192QAA\u0002\u0002\u0002!AQ!\b\u0001\u0005\u0002y\u0011A\"\u00112tiJ\f7\r\u001e,jK^T!\u0001B\u0003\u0002\u0015\r|G\u000e\\3di&|gNC\u0001\u0007\u0003\u0015\u00198-\u00197b\u0007\u0001)\"!\u0003\t\u0014\u0007\u0001Q!\u0004E\u0002\f\u00199i\u0011aA\u0005\u0003\u001b\r\u0011\u0001#\u00112tiJ\f7\r^%uKJ\f\'\r\\3\u0011\u0005=\u0001B\u0002\u0001\u0003\u0007#\u0001!)\u0019\u0001\n\u0003\u0003\u0005\u000b\"aE\f\u0011\u0005Q)R\"A\u0003\n\u0005Y)!a\u0002(pi\"Lgn\u001a\t\u0003)aI!!G\u0003\u0003\u0007\u0005s\u0017\u0010E\u0002\f79I!\u0001H\u0002\u0003\tYKWm^\u0001\u0007y%t\u0017\u000e\u001e \u0015\u0003}\u00012a\u0003\u0001\u000fQ\u0011\u0001\u0011\u0005J\u0013\u0011\u0005Q\u0011\u0013BA\u0012\u0006\u0005A\u0019VM]5bYZ+\'o]5p]VKE)A\u0003wC2,XMH\u0001\u0004\u0001"
    )
  ScalaInlineInfo: length = 0x31 (unknown attribute)
   01 00 00 09 00 39 00 3A 00 00 20 00 35 00 00 20
   00 38 00 00 20 00 11 00 00 2E 00 2F 04 00 19 00
   1A 00 00 2A 00 25 00 00 24 00 25 00 00 10 00 11
   00
  ScalaSig: length = 0x3 (unknown attribute)
   05 02 00
