Classfile /Users/mw/Projects/slang-braindump/.jar/jar8/assemble/slang-braindump/assemble/content/scala/collection/ArrayOps$ArrayIterator$mcJ$sp.class
  Last modified May 29, 2022; size 1588 bytes
  SHA-256 checksum 0ae21d978e27c0b45ebbac2569e13315f51741ef767058a4aa1e8b8da4da4e6f
  Compiled from "ArrayOps.scala"
public final class scala.collection.ArrayOps$ArrayIterator$mcJ$sp extends scala.collection.ArrayOps$ArrayIterator<java.lang.Object>
  minor version: 0
  major version: 52
  flags: (0x0031) ACC_PUBLIC, ACC_FINAL, ACC_SUPER
  this_class: #2                          // scala/collection/ArrayOps$ArrayIterator$mcJ$sp
  super_class: #5                         // scala/collection/ArrayOps$ArrayIterator
  interfaces: 0, fields: 2, methods: 4, attributes: 5
Constant pool:
   #1 = Utf8               scala/collection/ArrayOps$ArrayIterator$mcJ$sp
   #2 = Class              #1             // scala/collection/ArrayOps$ArrayIterator$mcJ$sp
   #3 = Utf8               Lscala/collection/ArrayOps$ArrayIterator<Ljava/lang/Object;>;
   #4 = Utf8               scala/collection/ArrayOps$ArrayIterator
   #5 = Class              #4             // scala/collection/ArrayOps$ArrayIterator
   #6 = Utf8               ArrayOps.scala
   #7 = Utf8               scala/collection/ArrayOps
   #8 = Class              #7             // scala/collection/ArrayOps
   #9 = Utf8               ArrayIterator
  #10 = Utf8               serialVersionUID
  #11 = Utf8               J
  #12 = Long               3l
  #14 = Utf8               xs$mcJ$sp
  #15 = Utf8               [J
  #16 = Utf8               next
  #17 = Utf8               ()J
  #18 = Utf8               next$mcJ$sp
  #19 = NameAndType        #18:#17        // next$mcJ$sp:()J
  #20 = Methodref          #2.#19         // scala/collection/ArrayOps$ArrayIterator$mcJ$sp.next$mcJ$sp:()J
  #21 = Utf8               this
  #22 = Utf8               Lscala/collection/ArrayOps$ArrayIterator$mcJ$sp;
  #23 = Utf8               java/lang/ArrayIndexOutOfBoundsException
  #24 = Class              #23            // java/lang/ArrayIndexOutOfBoundsException
  #25 = NameAndType        #14:#15        // xs$mcJ$sp:[J
  #26 = Fieldref           #2.#25         // scala/collection/ArrayOps$ArrayIterator$mcJ$sp.xs$mcJ$sp:[J
  #27 = Utf8               scala$collection$ArrayOps$ArrayIterator$$pos
  #28 = Utf8               I
  #29 = NameAndType        #27:#28        // scala$collection$ArrayOps$ArrayIterator$$pos:I
  #30 = Fieldref           #2.#29         // scala/collection/ArrayOps$ArrayIterator$mcJ$sp.scala$collection$ArrayOps$ArrayIterator$$pos:I
  #31 = Utf8               scala/collection/Iterator$
  #32 = Class              #31            // scala/collection/Iterator$
  #33 = Utf8               MODULE$
  #34 = Utf8               Lscala/collection/Iterator$;
  #35 = NameAndType        #33:#34        // MODULE$:Lscala/collection/Iterator$;
  #36 = Fieldref           #32.#35        // scala/collection/Iterator$.MODULE$:Lscala/collection/Iterator$;
  #37 = Utf8               scala$collection$Iterator$$_empty
  #38 = Utf8               Lscala/collection/Iterator;
  #39 = NameAndType        #37:#38        // scala$collection$Iterator$$_empty:Lscala/collection/Iterator;
  #40 = Fieldref           #32.#39        // scala/collection/Iterator$.scala$collection$Iterator$$_empty:Lscala/collection/Iterator;
  #41 = Utf8               scala/collection/Iterator
  #42 = Class              #41            // scala/collection/Iterator
  #43 = Utf8               ()Ljava/lang/Object;
  #44 = NameAndType        #16:#43        // next:()Ljava/lang/Object;
  #45 = InterfaceMethodref #42.#44        // scala/collection/Iterator.next:()Ljava/lang/Object;
  #46 = Utf8               scala/runtime/BoxesRunTime
  #47 = Class              #46            // scala/runtime/BoxesRunTime
  #48 = Utf8               unboxToLong
  #49 = Utf8               (Ljava/lang/Object;)J
  #50 = NameAndType        #48:#49        // unboxToLong:(Ljava/lang/Object;)J
  #51 = Methodref          #47.#50        // scala/runtime/BoxesRunTime.unboxToLong:(Ljava/lang/Object;)J
  #52 = Utf8               r
  #53 = NameAndType        #16:#17        // next:()J
  #54 = Methodref          #2.#53         // scala/collection/ArrayOps$ArrayIterator$mcJ$sp.next:()J
  #55 = Utf8               boxToLong
  #56 = Utf8               (J)Ljava/lang/Long;
  #57 = NameAndType        #55:#56        // boxToLong:(J)Ljava/lang/Long;
  #58 = Methodref          #47.#57        // scala/runtime/BoxesRunTime.boxToLong:(J)Ljava/lang/Long;
  #59 = Utf8               <init>
  #60 = Utf8               ([J)V
  #61 = Utf8               (Ljava/lang/Object;)V
  #62 = NameAndType        #59:#61        // "<init>":(Ljava/lang/Object;)V
  #63 = Methodref          #5.#62         // scala/collection/ArrayOps$ArrayIterator."<init>":(Ljava/lang/Object;)V
  #64 = Utf8               scala/runtime/Statics
  #65 = Class              #64            // scala/runtime/Statics
  #66 = Utf8               releaseFence
  #67 = Utf8               ()V
  #68 = NameAndType        #66:#67        // releaseFence:()V
  #69 = Methodref          #65.#68        // scala/runtime/Statics.releaseFence:()V
  #70 = Utf8               ConstantValue
  #71 = Utf8               Code
  #72 = Utf8               LineNumberTable
  #73 = Utf8               LocalVariableTable
  #74 = Utf8               StackMapTable
  #75 = Utf8               MethodParameters
  #76 = Utf8               InnerClasses
  #77 = Utf8               Signature
  #78 = Utf8               SourceFile
  #79 = Utf8               ScalaInlineInfo
  #80 = Utf8               Scala
{
  private static final long serialVersionUID;
    descriptor: J
    flags: (0x001a) ACC_PRIVATE, ACC_STATIC, ACC_FINAL
    ConstantValue: long 3l

  public final long[] xs$mcJ$sp;
    descriptor: [J
    flags: (0x0011) ACC_PUBLIC, ACC_FINAL

  public long next();
    descriptor: ()J
    flags: (0x0001) ACC_PUBLIC
    Code:
      stack=2, locals=1, args_size=1
         0: aload_0
         1: invokevirtual #20                 // Method next$mcJ$sp:()J
         4: lreturn
      LineNumberTable:
        line 128: 0
      LocalVariableTable:
        Start  Length  Slot  Name   Signature
            0       5     0  this   Lscala/collection/ArrayOps$ArrayIterator$mcJ$sp;

  public long next$mcJ$sp();
    descriptor: ()J
    flags: (0x0001) ACC_PUBLIC
    Code:
      stack=3, locals=3, args_size=1
         0: aload_0
         1: getfield      #26                 // Field xs$mcJ$sp:[J
         4: aload_0
         5: getfield      #30                 // Field scala$collection$ArrayOps$ArrayIterator$$pos:I
         8: laload
         9: lstore_1
        10: aload_0
        11: aload_0
        12: getfield      #30                 // Field scala$collection$ArrayOps$ArrayIterator$$pos:I
        15: iconst_1
        16: iadd
        17: putfield      #30                 // Field scala$collection$ArrayOps$ArrayIterator$$pos:I
        20: lload_1
        21: lreturn
        22: pop
        23: getstatic     #36                 // Field scala/collection/Iterator$.MODULE$:Lscala/collection/Iterator$;
        26: pop
        27: getstatic     #40                 // Field scala/collection/Iterator$.scala$collection$Iterator$$_empty:Lscala/collection/Iterator;
        30: invokeinterface #45,  1           // InterfaceMethod scala/collection/Iterator.next:()Ljava/lang/Object;
        35: invokestatic  #51                 // Method scala/runtime/BoxesRunTime.unboxToLong:(Ljava/lang/Object;)J
        38: lreturn
      Exception table:
         from    to  target type
             0    21    22   Class java/lang/ArrayIndexOutOfBoundsException
      StackMapTable: number_of_entries = 1
        frame_type = 86 /* same_locals_1_stack_item */
          stack = [ class java/lang/ArrayIndexOutOfBoundsException ]
      LineNumberTable:
        line 129: 0
        line 130: 10
        line 131: 20
        line 132: 23
      LocalVariableTable:
        Start  Length  Slot  Name   Signature
           10      11     1     r   J
            0      39     0  this   Lscala/collection/ArrayOps$ArrayIterator$mcJ$sp;

  public java.lang.Object next();
    descriptor: ()Ljava/lang/Object;
    flags: (0x1041) ACC_PUBLIC, ACC_BRIDGE, ACC_SYNTHETIC
    Code:
      stack=2, locals=1, args_size=1
         0: aload_0
         1: invokevirtual #54                 // Method next:()J
         4: invokestatic  #58                 // Method scala/runtime/BoxesRunTime.boxToLong:(J)Ljava/lang/Long;
         7: areturn
      LineNumberTable:
        line 123: 0
      LocalVariableTable:
        Start  Length  Slot  Name   Signature
            0       8     0  this   Lscala/collection/ArrayOps$ArrayIterator$mcJ$sp;

  public scala.collection.ArrayOps$ArrayIterator$mcJ$sp(long[]);
    descriptor: ([J)V
    flags: (0x0001) ACC_PUBLIC
    Code:
      stack=2, locals=2, args_size=2
         0: aload_0
         1: aload_1
         2: putfield      #26                 // Field xs$mcJ$sp:[J
         5: aload_0
         6: aload_1
         7: invokespecial #63                 // Method scala/collection/ArrayOps$ArrayIterator."<init>":(Ljava/lang/Object;)V
        10: invokestatic  #69                 // Method scala/runtime/Statics.releaseFence:()V
        13: return
      LineNumberTable:
        line 123: 0
      LocalVariableTable:
        Start  Length  Slot  Name   Signature
            0      14     0  this   Lscala/collection/ArrayOps$ArrayIterator$mcJ$sp;
            0      14     1 xs$mcJ$sp   [J
    MethodParameters:
      Name                           Flags
      xs$mcJ$sp                      final
}
InnerClasses:
  public static #9= #5 of #8;             // ArrayIterator=class scala/collection/ArrayOps$ArrayIterator of class scala/collection/ArrayOps
Signature: #3                           // Lscala/collection/ArrayOps$ArrayIterator<Ljava/lang/Object;>;
SourceFile: "ArrayOps.scala"
  ScalaInlineInfo: length = 0x18 (unknown attribute)
   01 01 00 04 00 3B 00 3C 01 00 10 00 11 01 00 10
   00 2B 01 00 12 00 11 01
  Scala: length = 0x0 (unknown attribute)

