Classfile /Users/mw/Projects/slang-braindump/.jar/jar8/assemble/slang-braindump/assemble/content/scala/collection/BitSetOps.class
  Last modified May 29, 2022; size 20236 bytes
  SHA-256 checksum f0fd7b13fb4a1fff53cec2404774605d7c6cc379fe6b43b2ace1be78ab7137e9
  Compiled from "BitSet.scala"
public interface scala.collection.BitSetOps<C extends scala.collection.BitSet & scala.collection.BitSetOps<C>> extends scala.collection.SortedSetOps<java.lang.Object, scala.collection.SortedSet, C>
  minor version: 0
  major version: 52
  flags: (0x0601) ACC_PUBLIC, ACC_INTERFACE, ACC_ABSTRACT
  this_class: #2                          // scala/collection/BitSetOps
  super_class: #5                         // java/lang/Object
  interfaces: 1, fields: 0, methods: 62, attributes: 7
Constant pool:
    #1 = Utf8               scala/collection/BitSetOps
    #2 = Class              #1            // scala/collection/BitSetOps
    #3 = Utf8               <C::Lscala/collection/BitSet;:Lscala/collection/BitSetOps<TC;>;>Ljava/lang/Object;Lscala/collection/SortedSetOps<Ljava/lang/Object;Lscala/collection/SortedSet;TC;>;
    #4 = Utf8               java/lang/Object
    #5 = Class              #4            // java/lang/Object
    #6 = Utf8               scala/collection/SortedSetOps
    #7 = Class              #6            // scala/collection/SortedSetOps
    #8 = Utf8               BitSet.scala
    #9 = Utf8               Lscala/reflect/ScalaSignature;
   #10 = Utf8               bytes
   #11 = Utf8               \u0006\u0005\t\u0015fa\u0002\u00180!\u0003\r\t\u0001\u000e\u0005\u0006\'\u0002!\t\u0001\u0016\u0005\u00061\u00021\t!\u0017\u0005\u0006;\u00021\tA\u0018\u0005\u0006E\u0002!)a\u0019\u0005\u0007W\u00021\tb\f7\t\r5\u0004a\u0011C\u0018o\u0011\u0019!\bA\"\u00050k\")1\u0010\u0001C\u0001y\"9\u0011Q\u0001\u0001\u0005\u0002\u0005\u001d\u0001bBA\b\u0001\u0011\u0005\u0011\u0011\u0003\u0005\b\u0003/\u0001A\u0011IA\r\u0011\u0019\t)\u0007\u0001C!Y\"9\u0011q\r\u0001\u0005B\u0005%\u0004bBA6\u0001\u0001&I\u0001\u001c\u0005\b\u0003k\u0002\u0001\u0015\"\u0003m\u0011\u001d\tI\b\u0001C!\u0003wBq!!$\u0001\t\u0003\ny\tC\u0004\u0002\u001c\u0002!\t%!(\t\u000f\u0005E\u0006\u0001\"\u0001\u00024\"9\u0011Q\u0017\u0001\u0005\u0002\u0005]\u0006bBAd\u0001\u0011\u0005\u0013\u0011\u001a\u0005\b\u0003+\u0004A\u0011IAl\u0011!\tY\u000e\u0001I\u0005\u0002\u0005u\u0007bBAq\u0001\u0011\u0005\u00111\u001d\u0005\b\u0003O\u0004AQAAu\u0011\u001d\ty\u000f\u0001C\u0001\u0003cDq!a>\u0001\t\u0003\tI\u0010C\u0004\u0002\u0000\u0002!\tA!\u0001\t\u000f\t5\u0001\u0001\"\u0011\u0003\u0010!q!Q\u0004\u0001\u0011\u0002\u0007\u0005\t\u0011\"\u0003\u0003 \t5\u0002B\u0004B\u0018\u0001A\u0005\u0019\u0011!A\u0005\n\tE\"Q\b\u0005\u000f\u0005\u007f\u0001\u0001\u0013aA\u0001\u0002\u0013%!\u0011\tB$\u00119\u0011i\u0005\u0001I\u0001\u0004\u0003\u0005I\u0011\u0002B(\u0005\'BaB!\u0016\u0001!\u0003\r\t\u0011!C\u0005\u0005/\u0012YfB\u0004\u0003^=B\tAa\u0018\u0007\r9z\u0003\u0012\u0001B1\u0011\u001d\u0011\u0019\u0007\nC\u0001\u0005KB!Ba\u001a%\u0005\u0004%)a\fB5\u0011!\u0011y\u0007\nQ\u0001\u000e\t-\u0004B\u0003B9I\t\u0007IQA\u0018\u0003t!A!\u0011\u0010\u0013!\u0002\u001b\u0011)\b\u0003\u0006\u0003|\u0011\u0012\r\u0011\"\u00020\u0005{B\u0001Ba!%A\u00035!q\u0010\u0005\t\u0005\u000b#C\u0011A\u0018\u0003\b\"A!\u0011\u0013\u0013\u0005\u0002=\u0012\u0019JA\u0005CSR\u001cV\r^(qg*\u0011\u0001\'M\u0001\u000bG>dG.Z2uS>t\'\"\u0001\u001a\u0002\u000bM\u001c\u0017\r\\1\u0004\u0001U\u0011QGR\n\u0004\u0001YR\u0004CA\u001c9\u001b\u0005\t\u0014BA\u001d2\u0005\u0019\te.\u001f*fMB)1\b\u0010 B\t6\tq&\u0003\u0002>_\ta1k\u001c:uK\u0012\u001cV\r^(qgB\u0011qgP\u0005\u0003\u0001F\u00121!\u00138u!\tY$)\u0003\u0002D_\tI1k\u001c:uK\u0012\u001cV\r\u001e\t\u0003\u000b\u001ac\u0001\u0001\u0002\u0004H\u0001\u0011\u0015\r\u0001\u0013\u0002\u0002\u0007F\u0011\u0011\n\u0014\t\u0003o)K!aS\u0019\u0003\u000f9{G\u000f[5oOJ\u0019Qj\u0014*\u0007\t9\u0003\u0001\u0001\u0014\u0002\ryI,g-\u001b8f[\u0016tGO\u0010\t\u0003wAK!!U\u0018\u0003\r\tKGoU3u!\rY\u0004\u0001R\u0001\u0007I%t\u0017\u000e\u001e\u0013\u0015\u0003U\u0003\"a\u000e,\n\u0005]\u000b$\u0001B+oSR\fQBY5u\'\u0016$h)Y2u_JLX#\u0001.\u0011\tmZf\bR\u0005\u00039>\u0012qc\u00159fG&4\u0017nY%uKJ\f\'\r\\3GC\u000e$xN]=\u0002\u0011Ut7o\u001c:uK\u0012,\u0012a\u0018\t\u0004w\u0001t\u0014BA10\u0005\r\u0019V\r^\u0001\t_J$WM]5oOV\tA\rE\u0002fQzr!a\u000e4\n\u0005\u001d\f\u0014a\u00029bG.\fw-Z\u0005\u0003S*\u0014\u0001b\u0014:eKJLgn\u001a\u0006\u0003OF\naA\\<pe\u0012\u001cX#\u0001 \u0002\t]|\'\u000f\u001a\u000b\u0003_J\u0004\"a\u000e9\n\u0005E\f$\u0001\u0002\'p]\u001eDQa\u001d\u0004A\u0002y\n1!\u001b3y\u0003E1\'o\\7CSRl\u0015m]6O_\u000e{\u0007/\u001f\u000b\u0003\tZDQa^\u0004A\u0002a\fQ!\u001a7f[N\u00042aN=p\u0013\tQ\u0018GA\u0003BeJ\f\u00170\u0001\u0005d_:$\u0018-\u001b8t)\ri\u0018\u0011\u0001\t\u0003oyL!a`\u0019\u0003\u000f\t{w\u000e\\3b]\"1\u00111\u0001\u0005A\u0002y\nA!\u001a7f[\u0006A\u0011\u000e^3sCR|\'/\u0006\u0002\u0002\nA!1(a\u0003?\u0013\r\tia\f\u0002\t\u0013R,\'/\u0019;pe\u0006a\u0011\u000e^3sCR|\'O\u0012:p[R!\u0011\u0011BA\n\u0011\u0019\t)B\u0003a\u0001}\u0005)1\u000f^1si\u000691\u000f^3qa\u0016\u0014X\u0003BA\u000e\u0003G!B!!\b\u0002\\I1\u0011qDA\u0011\u0003\u007f1QA\u0014\u0001\u0001\u0003;\u00012!RA\u0012\t\u001d\t)c\u0003b\u0001\u0003O\u0011\u0011aU\t\u0004\u0013\u0006%\u0002\u0007BA\u0016\u0003g\u0001RaOA\u0017\u0003cI1!a\f0\u0005\u001d\u0019F/\u001a9qKJ\u00042!RA\u001a\t1\t)$a\t\u0002\u0002\u0003\u0005)\u0011AA\u001c\u0005\ryF%M\t\u0004\u0013\u0006e\u0002cA\u001c\u0002<%\u0019\u0011QH\u0019\u0003\u0007\u0005s\u0017\u0010\u0005\u0003\u0002B\u0005Uc\u0002BA\"\u0003#rA!!\u0012\u0002P9!\u0011qIA\'\u001b\t\tIEC\u0002\u0002LM\na\u0001\u0010:p_Rt\u0014\"\u0001\u001a\n\u0005A\n\u0014bAA*_\u000591\u000b^3qa\u0016\u0014\u0018\u0002BA,\u00033\u0012a\"\u00124gS\u000eLWM\u001c;Ta2LGOC\u0002\u0002T=Bq!!\u0018\f\u0001\b\ty&A\u0003tQ\u0006\u0004X\r\u0005\u0004<\u0003Cr\u0014\u0011E\u0005\u0004\u0003Gz#\u0001D*uKB\u0004XM]*iCB,\u0017\u0001B:ju\u0016\fq![:F[B$\u00180F\u0001~\u0003-\u0019X.\u00197mKN$\u0018J\u001c;)\u00079\ty\u0007E\u00028\u0003cJ1!a\u001d2\u0005\u0019Ig\u000e\\5oK\u0006QA.\u0019:hKN$\u0018J\u001c;)\u0007=\ty\'A\u0002nCb,B!! \u0002\bR\u0019a(a \t\u000f\u0005\u0005\u0005\u0003q\u0001\u0002\u0004\u0006\u0019qN\u001d3\u0011\t\u0015D\u0017Q\u0011\t\u0004\u000b\u0006\u001dEaBAE!\t\u0007\u00111\u0012\u0002\u0002\u0005F\u0019a(!\u000f\u0002\u00075Lg.\u0006\u0003\u0002\u0012\u0006eEc\u0001 \u0002\u0014\"9\u0011\u0011Q\tA\u0004\u0005U\u0005\u0003B3i\u0003/\u00032!RAM\t\u001d\tI)\u0005b\u0001\u0003\u0017\u000bqAZ8sK\u0006\u001c\u0007.\u0006\u0003\u0002 \u00065FcA+\u0002\"\"9\u00111\u0015\nA\u0002\u0005\u0015\u0016!\u00014\u0011\r]\n9KPAV\u0013\r\tI+\r\u0002\n\rVt7\r^5p]F\u00022!RAW\t\u001d\tyK\u0005b\u0001\u0003o\u0011\u0011!V\u0001\ni>\u0014\u0015\u000e^\'bg.,\u0012\u0001_\u0001\ne\u0006tw-Z%na2$R\u0001RA]\u0003\u0007Dq!a/\u0015\u0001\u0004\ti,\u0001\u0003ge>l\u0007\u0003B\u001c\u0002@zJ1!!12\u0005\u0019y\u0005\u000f^5p]\"9\u0011Q\u0019\u000bA\u0002\u0005u\u0016!B;oi&d\u0017AB2p]\u000e\fG\u000fF\u0002E\u0003\u0017Dq!!4\u0016\u0001\u0004\ty-A\u0003pi\",\'\u000f\u0005\u0003<\u0003#t\u0014bAAj_\ta\u0011\n^3sC\ndWm\u00148dK\u0006I\u0011N\u001c;feN,7\r\u001e\u000b\u0004\t\u0006e\u0007BBAg-\u0001\u0007q,\u0001\u0003eS\u001a4Gc\u0001#\u0002`\"1\u0011QZ\fA\u0002}\u000b1\u0001_8s)\r!\u0015Q\u001d\u0005\u0007\u0003\u001bD\u0002\u0019A(\u0002\u0007\u0011*\b\u000fF\u0002E\u0003WDa!!4\u001a\u0001\u0004y\u0005fA\r\u0002p\u0005\u0019Q.\u00199\u0015\u0007\u0011\u000b\u0019\u0010C\u0004\u0002$j\u0001\r!!>\u0011\u000b]\n9K\u0010 \u0002\u000f\u0019d\u0017\r^\'baR\u0019A)a?\t\u000f\u0005\r6\u00041\u0001\u0002~B1q\'a*?\u0003\u001f\fqaY8mY\u0016\u001cG\u000fF\u0002E\u0005\u0007AqA!\u0002\u001d\u0001\u0004\u00119!\u0001\u0002qMB)qG!\u0003?}%\u0019!1B\u0019\u0003\u001fA\u000b\'\u000f^5bY\u001a+hn\u0019;j_:\f\u0011\u0002]1si&$\u0018n\u001c8\u0015\t\tE!q\u0003\t\u0006o\tMA\tR\u0005\u0004\u0005+\t$A\u0002+va2,\'\u0007C\u0004\u0003\u001au\u0001\rAa\u0007\u0002\u0003A\u0004RaNAT}u\f\u0011b];qKJ$S.\u0019=\u0016\t\t\u0005\"1\u0006\u000b\u0004}\t\r\u0002bBAA=\u0001\u000f!Q\u0005\t\u0006\u0005OA\'\u0011\u0006\b\u0004\u0003\u000b2\u0007cA#\u0003,\u00119\u0011\u0011\u0012\u0010C\u0002\u0005-\u0015bAA=y\u0005I1/\u001e9fe\u0012j\u0017N\\\u000b\u0005\u0005g\u0011Y\u0004F\u0002?\u0005kAq!!! \u0001\b\u00119\u0004E\u0003\u0003(!\u0014I\u0004E\u0002F\u0005w!q!!# \u0005\u0004\tY)C\u0002\u0002\u000er\nAb];qKJ$3m\u001c8dCR$2\u0001\u0012B\"\u0011\u001d\u0011)\u0005\ta\u0001\u0003\u001f\fA\u0001\u001e5bi&!\u0011q\u0019B%\u0013\r\u0011Ye\f\u0002\u0007\'\u0016$x\n]:\u0002\u001fM,\b/\u001a:%S:$XM]:fGR$2\u0001\u0012B)\u0011\u0019\u0011)%\ta\u0001?&!\u0011Q\u001bB%\u0003)\u0019X\u000f]3sI\u0011LgM\u001a\u000b\u0004\t\ne\u0003B\u0002B#E\u0001\u0007q,\u0003\u0003\u0002\\\n%\u0013!\u0003\"jiN+Go\u00149t!\tYDe\u0005\u0002%m\u00051A(\u001b8jiz\"\"Aa\u0018\u0002\u000b1{wm\u0016\'\u0016\u0005\t-tB\u0001B7;\u00051\u0011A\u0002\'pO^c\u0005%\u0001\u0006X_J$G*\u001a8hi\",\"A!\u001e\u0010\u0005\t]T$\u0001!\u0002\u0017]{\'\u000f\u001a\'f]\u001e$\b\u000eI\u0001\b\u001b\u0006D8+\u001b>f+\t\u0011yh\u0004\u0002\u0003\u0002v!!\u0001\u0001\u0001\u0001\u0003!i\u0015\r_*ju\u0016\u0004\u0013aC;qI\u0006$X-\u0011:sCf$r\u0001\u001fBE\u0005\u0017\u0013i\tC\u0003xY\u0001\u0007\u0001\u0010C\u0003tY\u0001\u0007a\b\u0003\u0004\u0003\u00102\u0002\ra\\\u0001\u0002o\u0006!2m\\7qkR,wk\u001c:e\r>\u0014h)\u001b7uKJ$\u0012b\u001cBK\u00053\u0013iJ!)\t\u000f\t]U\u00061\u0001\u0003\u001c\u0005!\u0001O]3e\u0011\u0019\u0011Y*\fa\u0001{\u0006I\u0011n\u001d$mSB\u0004X\r\u001a\u0005\u0007\u0005?k\u0003\u0019A8\u0002\u000f=dGmV8sI\"1!1U\u0017A\u0002y\n\u0011b^8sI&sG-\u001a=
   #12 = Utf8               java/lang/invoke/MethodHandles$Lookup
   #13 = Class              #12           // java/lang/invoke/MethodHandles$Lookup
   #14 = Utf8               java/lang/invoke/MethodHandles
   #15 = Class              #14           // java/lang/invoke/MethodHandles
   #16 = Utf8               Lookup
   #17 = Utf8               scala/collection/AnyStepper$$anon$4
   #18 = Class              #17           // scala/collection/AnyStepper$$anon$4
   #19 = Utf8               scala/collection/BitSetOps$$anon$1
   #20 = Class              #19           // scala/collection/BitSetOps$$anon$1
   #21 = Utf8               scala/collection/View$FlatMap
   #22 = Class              #21           // scala/collection/View$FlatMap
   #23 = Utf8               scala/collection/View
   #24 = Class              #23           // scala/collection/View
   #25 = Utf8               FlatMap
   #26 = Utf8               scala/collection/View$Map
   #27 = Class              #26           // scala/collection/View$Map
   #28 = Utf8               Map
   #29 = Utf8               scala/collection/immutable/Range$Exclusive
   #30 = Class              #29           // scala/collection/immutable/Range$Exclusive
   #31 = Utf8               scala/collection/immutable/Range
   #32 = Class              #31           // scala/collection/immutable/Range
   #33 = Utf8               Exclusive
   #34 = Utf8               scala/math/Ordering$CachedReverse
   #35 = Class              #34           // scala/math/Ordering$CachedReverse
   #36 = Utf8               scala/math/Ordering
   #37 = Class              #36           // scala/math/Ordering
   #38 = Utf8               CachedReverse
   #39 = Utf8               scala/math/Ordering$Int$
   #40 = Class              #39           // scala/math/Ordering$Int$
   #41 = Utf8               Int$
   #42 = Utf8               scala$collection$BitSetOps$$super$max
   #43 = Utf8               (Lscala/math/Ordering;)I
   #44 = Utf8               ord
   #45 = Utf8               scala$collection$BitSetOps$$super$min
   #46 = Utf8               scala$collection$BitSetOps$$super$concat
   #47 = Utf8               (Lscala/collection/IterableOnce;)Lscala/collection/BitSet;
   #48 = Utf8               that
   #49 = Utf8               scala$collection$BitSetOps$$super$intersect
   #50 = Utf8               (Lscala/collection/Set;)Lscala/collection/BitSet;
   #51 = Utf8               scala$collection$BitSetOps$$super$diff
   #52 = Utf8               bitSetFactory
   #53 = Utf8               ()Lscala/collection/SpecificIterableFactory;
   #54 = Utf8               ()Lscala/collection/SpecificIterableFactory<Ljava/lang/Object;TC;>;
   #55 = Utf8               unsorted
   #56 = Utf8               ()Lscala/collection/Set;
   #57 = Utf8               ()Lscala/collection/Set<Ljava/lang/Object;>;
   #58 = Utf8               ordering$
   #59 = Utf8               (Lscala/collection/BitSetOps;)Lscala/math/Ordering;
   #60 = Utf8               $this
   #61 = Utf8               ordering
   #62 = Utf8               ()Lscala/math/Ordering;
   #63 = NameAndType        #61:#62       // ordering:()Lscala/math/Ordering;
   #64 = InterfaceMethodref #2.#63        // scala/collection/BitSetOps.ordering:()Lscala/math/Ordering;
   #65 = Utf8               Lscala/collection/BitSetOps;
   #66 = Utf8               ()Lscala/math/Ordering<Ljava/lang/Object;>;
   #67 = Utf8               MODULE$
   #68 = Utf8               Lscala/math/Ordering$Int$;
   #69 = NameAndType        #67:#68       // MODULE$:Lscala/math/Ordering$Int$;
   #70 = Fieldref           #40.#69       // scala/math/Ordering$Int$.MODULE$:Lscala/math/Ordering$Int$;
   #71 = Utf8               this
   #72 = Utf8               nwords
   #73 = Utf8               ()I
   #74 = Utf8               word
   #75 = Utf8               (I)J
   #76 = Utf8               idx
   #77 = Utf8               fromBitMaskNoCopy
   #78 = Utf8               ([J)Lscala/collection/BitSet;
   #79 = Utf8               ([J)TC;
   #80 = Utf8               elems
   #81 = Utf8               contains$
   #82 = Utf8               (Lscala/collection/BitSetOps;I)Z
   #83 = Utf8               elem
   #84 = Utf8               contains
   #85 = Utf8               (I)Z
   #86 = NameAndType        #84:#85       // contains:(I)Z
   #87 = InterfaceMethodref #2.#86        // scala/collection/BitSetOps.contains:(I)Z
   #88 = Utf8               I
   #89 = NameAndType        #74:#75       // word:(I)J
   #90 = InterfaceMethodref #2.#89        // scala/collection/BitSetOps.word:(I)J
   #91 = Utf8               iterator$
   #92 = Utf8               (Lscala/collection/BitSetOps;)Lscala/collection/Iterator;
   #93 = Utf8               iterator
   #94 = Utf8               ()Lscala/collection/Iterator;
   #95 = NameAndType        #93:#94       // iterator:()Lscala/collection/Iterator;
   #96 = InterfaceMethodref #2.#95        // scala/collection/BitSetOps.iterator:()Lscala/collection/Iterator;
   #97 = Utf8               ()Lscala/collection/Iterator<Ljava/lang/Object;>;
   #98 = Utf8               iteratorFrom
   #99 = Utf8               (I)Lscala/collection/Iterator;
  #100 = NameAndType        #98:#99       // iteratorFrom:(I)Lscala/collection/Iterator;
  #101 = InterfaceMethodref #2.#100       // scala/collection/BitSetOps.iteratorFrom:(I)Lscala/collection/Iterator;
  #102 = Utf8               iteratorFrom$
  #103 = Utf8               (Lscala/collection/BitSetOps;I)Lscala/collection/Iterator;
  #104 = Utf8               start
  #105 = Utf8               (I)Lscala/collection/Iterator<Ljava/lang/Object;>;
  #106 = Utf8               <init>
  #107 = Utf8               (Lscala/collection/BitSetOps;I)V
  #108 = NameAndType        #106:#107     // "<init>":(Lscala/collection/BitSetOps;I)V
  #109 = Methodref          #20.#108      // scala/collection/BitSetOps$$anon$1."<init>":(Lscala/collection/BitSetOps;I)V
  #110 = Utf8               stepper$
  #111 = Utf8               (Lscala/collection/BitSetOps;Lscala/collection/StepperShape;)Lscala/collection/Stepper;
  #112 = Utf8               shape
  #113 = Utf8               stepper
  #114 = Utf8               (Lscala/collection/StepperShape;)Lscala/collection/Stepper;
  #115 = NameAndType        #113:#114     // stepper:(Lscala/collection/StepperShape;)Lscala/collection/Stepper;
  #116 = InterfaceMethodref #2.#115       // scala/collection/BitSetOps.stepper:(Lscala/collection/StepperShape;)Lscala/collection/Stepper;
  #117 = Utf8               Lscala/collection/StepperShape;
  #118 = Utf8               <S::Lscala/collection/Stepper<*>;>(Lscala/collection/StepperShape<Ljava/lang/Object;TS;>;)TS;
  #119 = Utf8               scala/collection/convert/impl/BitSetStepper$
  #120 = Class              #119          // scala/collection/convert/impl/BitSetStepper$
  #121 = Utf8               Lscala/collection/convert/impl/BitSetStepper$;
  #122 = NameAndType        #67:#121      // MODULE$:Lscala/collection/convert/impl/BitSetStepper$;
  #123 = Fieldref           #120.#122     // scala/collection/convert/impl/BitSetStepper$.MODULE$:Lscala/collection/convert/impl/BitSetStepper$;
  #124 = Utf8               from
  #125 = Utf8               (Lscala/collection/BitSetOps;)Lscala/collection/IntStepper;
  #126 = NameAndType        #124:#125     // from:(Lscala/collection/BitSetOps;)Lscala/collection/IntStepper;
  #127 = Methodref          #120.#126     // scala/collection/convert/impl/BitSetStepper$.from:(Lscala/collection/BitSetOps;)Lscala/collection/IntStepper;
  #128 = Utf8               scala/collection/StepperShape
  #129 = Class              #128          // scala/collection/StepperShape
  #130 = NameAndType        #112:#73      // shape:()I
  #131 = InterfaceMethodref #129.#130     // scala/collection/StepperShape.shape:()I
  #132 = Utf8               scala/collection/StepperShape$
  #133 = Class              #132          // scala/collection/StepperShape$
  #134 = Utf8               Lscala/collection/StepperShape$;
  #135 = NameAndType        #67:#134      // MODULE$:Lscala/collection/StepperShape$;
  #136 = Fieldref           #133.#135     // scala/collection/StepperShape$.MODULE$:Lscala/collection/StepperShape$;
  #137 = Utf8               IntShape
  #138 = NameAndType        #137:#73      // IntShape:()I
  #139 = Methodref          #133.#138     // scala/collection/StepperShape$.IntShape:()I
  #140 = Utf8               ReferenceShape
  #141 = NameAndType        #140:#73      // ReferenceShape:()I
  #142 = Methodref          #133.#141     // scala/collection/StepperShape$.ReferenceShape:()I
  #143 = Utf8               java/lang/AssertionError
  #144 = Class              #143          // java/lang/AssertionError
  #145 = Utf8               java/lang/StringBuilder
  #146 = Class              #145          // java/lang/StringBuilder
  #147 = Integer            18
  #148 = Utf8               (I)V
  #149 = NameAndType        #106:#148     // "<init>":(I)V
  #150 = Methodref          #146.#149     // java/lang/StringBuilder."<init>":(I)V
  #151 = Utf8               assertion failed:
  #152 = String             #151          // assertion failed:
  #153 = Utf8               append
  #154 = Utf8               (Ljava/lang/String;)Ljava/lang/StringBuilder;
  #155 = NameAndType        #153:#154     // append:(Ljava/lang/String;)Ljava/lang/StringBuilder;
  #156 = Methodref          #146.#155     // java/lang/StringBuilder.append:(Ljava/lang/String;)Ljava/lang/StringBuilder;
  #157 = Utf8               $anonfun$stepper$1
  #158 = Utf8               (Lscala/collection/StepperShape;)Ljava/lang/String;
  #159 = NameAndType        #157:#158     // $anonfun$stepper$1:(Lscala/collection/StepperShape;)Ljava/lang/String;
  #160 = InterfaceMethodref #2.#159       // scala/collection/BitSetOps.$anonfun$stepper$1:(Lscala/collection/StepperShape;)Ljava/lang/String;
  #161 = Utf8               (Ljava/lang/Object;)Ljava/lang/StringBuilder;
  #162 = NameAndType        #153:#161     // append:(Ljava/lang/Object;)Ljava/lang/StringBuilder;
  #163 = Methodref          #146.#162     // java/lang/StringBuilder.append:(Ljava/lang/Object;)Ljava/lang/StringBuilder;
  #164 = Utf8               toString
  #165 = Utf8               ()Ljava/lang/String;
  #166 = NameAndType        #164:#165     // toString:()Ljava/lang/String;
  #167 = Methodref          #146.#166     // java/lang/StringBuilder.toString:()Ljava/lang/String;
  #168 = Utf8               (Ljava/lang/Object;)V
  #169 = NameAndType        #106:#168     // "<init>":(Ljava/lang/Object;)V
  #170 = Methodref          #144.#169     // java/lang/AssertionError."<init>":(Ljava/lang/Object;)V
  #171 = Utf8               scala/collection/AnyStepper$
  #172 = Class              #171          // scala/collection/AnyStepper$
  #173 = Utf8               Lscala/collection/AnyStepper$;
  #174 = NameAndType        #67:#173      // MODULE$:Lscala/collection/AnyStepper$;
  #175 = Fieldref           #172.#174     // scala/collection/AnyStepper$.MODULE$:Lscala/collection/AnyStepper$;
  #176 = Utf8               (Lscala/collection/IntStepper;)V
  #177 = NameAndType        #106:#176     // "<init>":(Lscala/collection/IntStepper;)V
  #178 = Methodref          #18.#177      // scala/collection/AnyStepper$$anon$4."<init>":(Lscala/collection/IntStepper;)V
  #179 = Utf8               st
  #180 = Utf8               Lscala/collection/IntStepper;
  #181 = Utf8               scala/collection/IntStepper
  #182 = Class              #181          // scala/collection/IntStepper
  #183 = Utf8               size$
  #184 = Utf8               (Lscala/collection/BitSetOps;)I
  #185 = Utf8               size
  #186 = NameAndType        #185:#73      // size:()I
  #187 = InterfaceMethodref #2.#186       // scala/collection/BitSetOps.size:()I
  #188 = NameAndType        #72:#73       // nwords:()I
  #189 = InterfaceMethodref #2.#188       // scala/collection/BitSetOps.nwords:()I
  #190 = Utf8               java/lang/Long
  #191 = Class              #190          // java/lang/Long
  #192 = Utf8               bitCount
  #193 = Utf8               (J)I
  #194 = NameAndType        #192:#193     // bitCount:(J)I
  #195 = Methodref          #191.#194     // java/lang/Long.bitCount:(J)I
  #196 = Utf8               s
  #197 = Utf8               i
  #198 = Utf8               isEmpty$
  #199 = Utf8               (Lscala/collection/BitSetOps;)Z
  #200 = Utf8               isEmpty
  #201 = Utf8               ()Z
  #202 = NameAndType        #200:#201     // isEmpty:()Z
  #203 = InterfaceMethodref #2.#202       // scala/collection/BitSetOps.isEmpty:()Z
  #204 = Utf8               scala/runtime/RichInt$
  #205 = Class              #204          // scala/runtime/RichInt$
  #206 = Utf8               Lscala/runtime/RichInt$;
  #207 = NameAndType        #67:#206      // MODULE$:Lscala/runtime/RichInt$;
  #208 = Fieldref           #205.#207     // scala/runtime/RichInt$.MODULE$:Lscala/runtime/RichInt$;
  #209 = Utf8               scala/collection/immutable/Range$
  #210 = Class              #209          // scala/collection/immutable/Range$
  #211 = Utf8               Lscala/collection/immutable/Range$;
  #212 = NameAndType        #67:#211      // MODULE$:Lscala/collection/immutable/Range$;
  #213 = Fieldref           #210.#212     // scala/collection/immutable/Range$.MODULE$:Lscala/collection/immutable/Range$;
  #214 = Utf8               (III)V
  #215 = NameAndType        #106:#214     // "<init>":(III)V
  #216 = Methodref          #30.#215      // scala/collection/immutable/Range$Exclusive."<init>":(III)V
  #217 = MethodType         #85           //  (I)Z
  #218 = Utf8               $anonfun$isEmpty$1
  #219 = NameAndType        #218:#82      // $anonfun$isEmpty$1:(Lscala/collection/BitSetOps;I)Z
  #220 = InterfaceMethodref #2.#219       // scala/collection/BitSetOps.$anonfun$isEmpty$1:(Lscala/collection/BitSetOps;I)Z
  #221 = MethodHandle       6:#220        // REF_invokeStatic scala/collection/BitSetOps.$anonfun$isEmpty$1:(Lscala/collection/BitSetOps;I)Z
  #222 = Integer            1
  #223 = Utf8               java/lang/invoke/LambdaMetafactory
  #224 = Class              #223          // java/lang/invoke/LambdaMetafactory
  #225 = Utf8               altMetafactory
  #226 = Utf8               (Ljava/lang/invoke/MethodHandles$Lookup;Ljava/lang/String;Ljava/lang/invoke/MethodType;[Ljava/lang/Object;)Ljava/lang/invoke/CallSite;
  #227 = NameAndType        #225:#226     // altMetafactory:(Ljava/lang/invoke/MethodHandles$Lookup;Ljava/lang/String;Ljava/lang/invoke/MethodType;[Ljava/lang/Object;)Ljava/lang/invoke/CallSite;
  #228 = Methodref          #224.#227     // java/lang/invoke/LambdaMetafactory.altMetafactory:(Ljava/lang/invoke/MethodHandles$Lookup;Ljava/lang/String;Ljava/lang/invoke/MethodType;[Ljava/lang/Object;)Ljava/lang/invoke/CallSite;
  #229 = MethodHandle       6:#228        // REF_invokeStatic java/lang/invoke/LambdaMetafactory.altMetafactory:(Ljava/lang/invoke/MethodHandles$Lookup;Ljava/lang/String;Ljava/lang/invoke/MethodType;[Ljava/lang/Object;)Ljava/lang/invoke/CallSite;
  #230 = Utf8               apply$mcZI$sp
  #231 = Utf8               (Lscala/collection/BitSetOps;)Lscala/runtime/java8/JFunction1$mcZI$sp;
  #232 = NameAndType        #230:#231     // apply$mcZI$sp:(Lscala/collection/BitSetOps;)Lscala/runtime/java8/JFunction1$mcZI$sp;
  #233 = InvokeDynamic      #0:#232       // #0:apply$mcZI$sp:(Lscala/collection/BitSetOps;)Lscala/runtime/java8/JFunction1$mcZI$sp;
  #234 = Utf8               forall
  #235 = Utf8               (Lscala/Function1;)Z
  #236 = NameAndType        #234:#235     // forall:(Lscala/Function1;)Z
  #237 = Methodref          #32.#236      // scala/collection/immutable/Range.forall:(Lscala/Function1;)Z
  #238 = Utf8               until$extension_end
  #239 = Utf8               smallestInt
  #240 = Utf8               numberOfTrailingZeros
  #241 = NameAndType        #240:#193     // numberOfTrailingZeros:(J)I
  #242 = Methodref          #191.#241     // java/lang/Long.numberOfTrailingZeros:(J)I
  #243 = Utf8               java/lang/UnsupportedOperationException
  #244 = Class              #243          // java/lang/UnsupportedOperationException
  #245 = Utf8               empty.smallestInt
  #246 = String             #245          // empty.smallestInt
  #247 = Utf8               (Ljava/lang/String;)V
  #248 = NameAndType        #106:#247     // "<init>":(Ljava/lang/String;)V
  #249 = Methodref          #244.#248     // java/lang/UnsupportedOperationException."<init>":(Ljava/lang/String;)V
  #250 = Utf8               currentWord
  #251 = Utf8               J
  #252 = Utf8               thisnwords
  #253 = Utf8               largestInt
  #254 = Utf8               numberOfLeadingZeros
  #255 = NameAndType        #254:#193     // numberOfLeadingZeros:(J)I
  #256 = Methodref          #191.#255     // java/lang/Long.numberOfLeadingZeros:(J)I
  #257 = Utf8               empty.largestInt
  #258 = String             #257          // empty.largestInt
  #259 = Utf8               max$
  #260 = Utf8               (Lscala/collection/BitSetOps;Lscala/math/Ordering;)I
  #261 = Utf8               max
  #262 = NameAndType        #261:#43      // max:(Lscala/math/Ordering;)I
  #263 = InterfaceMethodref #2.#262       // scala/collection/BitSetOps.max:(Lscala/math/Ordering;)I
  #264 = Utf8               Lscala/math/Ordering;
  #265 = Utf8               <B:Ljava/lang/Object;>(Lscala/math/Ordering<TB;>;)I
  #266 = Utf8               isReverseOf$
  #267 = Utf8               (Lscala/math/Ordering$CachedReverse;Lscala/math/Ordering;)Z
  #268 = NameAndType        #266:#267     // isReverseOf$:(Lscala/math/Ordering$CachedReverse;Lscala/math/Ordering;)Z
  #269 = InterfaceMethodref #35.#268      // scala/math/Ordering$CachedReverse.isReverseOf$:(Lscala/math/Ordering$CachedReverse;Lscala/math/Ordering;)Z
  #270 = NameAndType        #42:#43       // scala$collection$BitSetOps$$super$max:(Lscala/math/Ordering;)I
  #271 = InterfaceMethodref #2.#270       // scala/collection/BitSetOps.scala$collection$BitSetOps$$super$max:(Lscala/math/Ordering;)I
  #272 = Utf8               largestInt_currentWord
  #273 = Utf8               largestInt_i
  #274 = Utf8               smallestInt_currentWord
  #275 = Utf8               smallestInt_thisnwords
  #276 = Utf8               smallestInt_i
  #277 = Utf8               min$
  #278 = Utf8               min
  #279 = NameAndType        #278:#43      // min:(Lscala/math/Ordering;)I
  #280 = InterfaceMethodref #2.#279       // scala/collection/BitSetOps.min:(Lscala/math/Ordering;)I
  #281 = NameAndType        #45:#43       // scala$collection$BitSetOps$$super$min:(Lscala/math/Ordering;)I
  #282 = InterfaceMethodref #2.#281       // scala/collection/BitSetOps.scala$collection$BitSetOps$$super$min:(Lscala/math/Ordering;)I
  #283 = Utf8               foreach$
  #284 = Utf8               (Lscala/collection/BitSetOps;Lscala/Function1;)V
  #285 = Utf8               f
  #286 = Utf8               foreach
  #287 = Utf8               (Lscala/Function1;)V
  #288 = NameAndType        #286:#287     // foreach:(Lscala/Function1;)V
  #289 = InterfaceMethodref #2.#288       // scala/collection/BitSetOps.foreach:(Lscala/Function1;)V
  #290 = Utf8               Lscala/Function1;
  #291 = Utf8               <U:Ljava/lang/Object;>(Lscala/Function1<Ljava/lang/Object;TU;>;)V
  #292 = Utf8               java/lang/Integer
  #293 = Class              #292          // java/lang/Integer
  #294 = Utf8               valueOf
  #295 = Utf8               (I)Ljava/lang/Integer;
  #296 = NameAndType        #294:#295     // valueOf:(I)Ljava/lang/Integer;
  #297 = Methodref          #293.#296     // java/lang/Integer.valueOf:(I)Ljava/lang/Integer;
  #298 = Utf8               scala/Function1
  #299 = Class              #298          // scala/Function1
  #300 = Utf8               apply
  #301 = Utf8               (Ljava/lang/Object;)Ljava/lang/Object;
  #302 = NameAndType        #300:#301     // apply:(Ljava/lang/Object;)Ljava/lang/Object;
  #303 = InterfaceMethodref #299.#302     // scala/Function1.apply:(Ljava/lang/Object;)Ljava/lang/Object;
  #304 = Utf8               w
  #305 = Utf8               j
  #306 = Utf8               toBitMask$
  #307 = Utf8               (Lscala/collection/BitSetOps;)[J
  #308 = Utf8               toBitMask
  #309 = Utf8               ()[J
  #310 = NameAndType        #308:#309     // toBitMask:()[J
  #311 = InterfaceMethodref #2.#310       // scala/collection/BitSetOps.toBitMask:()[J
  #312 = Utf8               a
  #313 = Utf8               [J
  #314 = Class              #313          // "[J"
  #315 = Utf8               rangeImpl$
  #316 = Utf8               (Lscala/collection/BitSetOps;Lscala/Option;Lscala/Option;)Lscala/collection/BitSet;
  #317 = Utf8               until
  #318 = Utf8               rangeImpl
  #319 = Utf8               (Lscala/Option;Lscala/Option;)Lscala/collection/BitSet;
  #320 = NameAndType        #318:#319     // rangeImpl:(Lscala/Option;Lscala/Option;)Lscala/collection/BitSet;
  #321 = InterfaceMethodref #2.#320       // scala/collection/BitSetOps.rangeImpl:(Lscala/Option;Lscala/Option;)Lscala/collection/BitSet;
  #322 = Utf8               Lscala/Option;
  #323 = Utf8               (Lscala/Option<Ljava/lang/Object;>;Lscala/Option<Ljava/lang/Object;>;)TC;
  #324 = Utf8               coll
  #325 = Utf8               ()Ljava/lang/Object;
  #326 = NameAndType        #324:#325     // coll:()Ljava/lang/Object;
  #327 = InterfaceMethodref #2.#326       // scala/collection/BitSetOps.coll:()Ljava/lang/Object;
  #328 = Utf8               scala/Option
  #329 = Class              #328          // scala/Option
  #330 = Utf8               isDefined
  #331 = NameAndType        #330:#201     // isDefined:()Z
  #332 = Methodref          #329.#331     // scala/Option.isDefined:()Z
  #333 = Utf8               get
  #334 = NameAndType        #333:#325     // get:()Ljava/lang/Object;
  #335 = Methodref          #329.#334     // scala/Option.get:()Ljava/lang/Object;
  #336 = Utf8               scala/runtime/BoxesRunTime
  #337 = Class              #336          // scala/runtime/BoxesRunTime
  #338 = Utf8               unboxToInt
  #339 = Utf8               (Ljava/lang/Object;)I
  #340 = NameAndType        #338:#339     // unboxToInt:(Ljava/lang/Object;)I
  #341 = Methodref          #337.#340     // scala/runtime/BoxesRunTime.unboxToInt:(Ljava/lang/Object;)I
  #342 = Utf8               scala/math/package$
  #343 = Class              #342          // scala/math/package$
  #344 = Utf8               Lscala/math/package$;
  #345 = NameAndType        #67:#344      // MODULE$:Lscala/math/package$;
  #346 = Fieldref           #343.#345     // scala/math/package$.MODULE$:Lscala/math/package$;
  #347 = Utf8               java/lang/Math
  #348 = Class              #347          // java/lang/Math
  #349 = Utf8               (II)I
  #350 = NameAndType        #278:#349     // min:(II)I
  #351 = Methodref          #348.#350     // java/lang/Math.min:(II)I
  #352 = Utf8               java/util/Arrays
  #353 = Class              #352          // java/util/Arrays
  #354 = Utf8               fill
  #355 = Utf8               ([JIIJ)V
  #356 = NameAndType        #354:#355     // fill:([JIIJ)V
  #357 = Methodref          #353.#356     // java/util/Arrays.fill:([JIIJ)V
  #358 = Long               -1l
  #360 = NameAndType        #261:#349     // max:(II)I
  #361 = Methodref          #348.#360     // java/lang/Math.max:(II)I
  #362 = NameAndType        #77:#78       // fromBitMaskNoCopy:([J)Lscala/collection/BitSet;
  #363 = InterfaceMethodref #2.#362       // scala/collection/BitSetOps.fromBitMaskNoCopy:([J)Lscala/collection/BitSet;
  #364 = Utf8               b
  #365 = Utf8               u
  #366 = Utf8               len
  #367 = Utf8               concat$
  #368 = Utf8               (Lscala/collection/BitSetOps;Lscala/collection/IterableOnce;)Lscala/collection/BitSet;
  #369 = Utf8               other
  #370 = Utf8               concat
  #371 = NameAndType        #370:#47      // concat:(Lscala/collection/IterableOnce;)Lscala/collection/BitSet;
  #372 = InterfaceMethodref #2.#371       // scala/collection/BitSetOps.concat:(Lscala/collection/IterableOnce;)Lscala/collection/BitSet;
  #373 = Utf8               Lscala/collection/IterableOnce;
  #374 = Utf8               (Lscala/collection/IterableOnce<Ljava/lang/Object;>;)TC;
  #375 = Utf8               scala/collection/BitSet
  #376 = Class              #375          // scala/collection/BitSet
  #377 = InterfaceMethodref #376.#188     // scala/collection/BitSet.nwords:()I
  #378 = Methodref          #32.#202      // scala/collection/immutable/Range.isEmpty:()Z
  #379 = NameAndType        #104:#73      // start:()I
  #380 = Methodref          #32.#379      // scala/collection/immutable/Range.start:()I
  #381 = Utf8               $anonfun$concat$1
  #382 = Utf8               (Lscala/collection/BitSetOps;[JLscala/collection/BitSet;I)V
  #383 = NameAndType        #381:#382     // $anonfun$concat$1:(Lscala/collection/BitSetOps;[JLscala/collection/BitSet;I)V
  #384 = InterfaceMethodref #2.#383       // scala/collection/BitSetOps.$anonfun$concat$1:(Lscala/collection/BitSetOps;[JLscala/collection/BitSet;I)V
  #385 = Utf8               scala$collection$immutable$Range$$lastElement
  #386 = NameAndType        #385:#88      // scala$collection$immutable$Range$$lastElement:I
  #387 = Fieldref           #32.#386      // scala/collection/immutable/Range.scala$collection$immutable$Range$$lastElement:I
  #388 = Utf8               step
  #389 = NameAndType        #388:#73      // step:()I
  #390 = Methodref          #32.#389      // scala/collection/immutable/Range.step:()I
  #391 = NameAndType        #46:#47       // scala$collection$BitSetOps$$super$concat:(Lscala/collection/IterableOnce;)Lscala/collection/BitSet;
  #392 = InterfaceMethodref #2.#391       // scala/collection/BitSetOps.scala$collection$BitSetOps$$super$concat:(Lscala/collection/IterableOnce;)Lscala/collection/BitSet;
  #393 = Utf8               words
  #394 = Utf8               foreach$mVc$sp_i
  #395 = Utf8               foreach$mVc$sp_this
  #396 = Utf8               Lscala/collection/immutable/Range;
  #397 = Utf8               max$extension_that
  #398 = Utf8               scala/collection/IterableOnce
  #399 = Class              #398          // scala/collection/IterableOnce
  #400 = Utf8               intersect$
  #401 = Utf8               (Lscala/collection/BitSetOps;Lscala/collection/Set;)Lscala/collection/BitSet;
  #402 = Utf8               intersect
  #403 = NameAndType        #402:#50      // intersect:(Lscala/collection/Set;)Lscala/collection/BitSet;
  #404 = InterfaceMethodref #2.#403       // scala/collection/BitSetOps.intersect:(Lscala/collection/Set;)Lscala/collection/BitSet;
  #405 = Utf8               Lscala/collection/Set;
  #406 = Utf8               (Lscala/collection/Set<Ljava/lang/Object;>;)TC;
  #407 = Utf8               $anonfun$intersect$1
  #408 = NameAndType        #407:#382     // $anonfun$intersect$1:(Lscala/collection/BitSetOps;[JLscala/collection/BitSet;I)V
  #409 = InterfaceMethodref #2.#408       // scala/collection/BitSetOps.$anonfun$intersect$1:(Lscala/collection/BitSetOps;[JLscala/collection/BitSet;I)V
  #410 = NameAndType        #49:#50       // scala$collection$BitSetOps$$super$intersect:(Lscala/collection/Set;)Lscala/collection/BitSet;
  #411 = InterfaceMethodref #2.#410       // scala/collection/BitSetOps.scala$collection$BitSetOps$$super$intersect:(Lscala/collection/Set;)Lscala/collection/BitSet;
  #412 = Utf8               min$extension_that
  #413 = Utf8               scala/collection/Set
  #414 = Class              #413          // scala/collection/Set
  #415 = Utf8               diff$
  #416 = Utf8               diff
  #417 = NameAndType        #416:#50      // diff:(Lscala/collection/Set;)Lscala/collection/BitSet;
  #418 = InterfaceMethodref #2.#417       // scala/collection/BitSetOps.diff:(Lscala/collection/Set;)Lscala/collection/BitSet;
  #419 = Utf8               $anonfun$diff$1
  #420 = NameAndType        #419:#382     // $anonfun$diff$1:(Lscala/collection/BitSetOps;[JLscala/collection/BitSet;I)V
  #421 = InterfaceMethodref #2.#420       // scala/collection/BitSetOps.$anonfun$diff$1:(Lscala/collection/BitSetOps;[JLscala/collection/BitSet;I)V
  #422 = NameAndType        #51:#50       // scala$collection$BitSetOps$$super$diff:(Lscala/collection/Set;)Lscala/collection/BitSet;
  #423 = InterfaceMethodref #2.#422       // scala/collection/BitSetOps.scala$collection$BitSetOps$$super$diff:(Lscala/collection/Set;)Lscala/collection/BitSet;
  #424 = Utf8               xor$
  #425 = Utf8               (Lscala/collection/BitSetOps;Lscala/collection/BitSet;)Lscala/collection/BitSet;
  #426 = Utf8               xor
  #427 = Utf8               (Lscala/collection/BitSet;)Lscala/collection/BitSet;
  #428 = NameAndType        #426:#427     // xor:(Lscala/collection/BitSet;)Lscala/collection/BitSet;
  #429 = InterfaceMethodref #2.#428       // scala/collection/BitSetOps.xor:(Lscala/collection/BitSet;)Lscala/collection/BitSet;
  #430 = Utf8               Lscala/collection/BitSet;
  #431 = Utf8               (Lscala/collection/BitSet;)TC;
  #432 = Utf8               $anonfun$xor$1
  #433 = NameAndType        #432:#382     // $anonfun$xor$1:(Lscala/collection/BitSetOps;[JLscala/collection/BitSet;I)V
  #434 = InterfaceMethodref #2.#433       // scala/collection/BitSetOps.$anonfun$xor$1:(Lscala/collection/BitSetOps;[JLscala/collection/BitSet;I)V
  #435 = Utf8               $up$
  #436 = Utf8               $up
  #437 = NameAndType        #436:#427     // $up:(Lscala/collection/BitSet;)Lscala/collection/BitSet;
  #438 = InterfaceMethodref #2.#437       // scala/collection/BitSetOps.$up:(Lscala/collection/BitSet;)Lscala/collection/BitSet;
  #439 = Utf8               map$
  #440 = Utf8               (Lscala/collection/BitSetOps;Lscala/Function1;)Lscala/collection/BitSet;
  #441 = Utf8               map
  #442 = Utf8               (Lscala/Function1;)Lscala/collection/BitSet;
  #443 = NameAndType        #441:#442     // map:(Lscala/Function1;)Lscala/collection/BitSet;
  #444 = InterfaceMethodref #2.#443       // scala/collection/BitSetOps.map:(Lscala/Function1;)Lscala/collection/BitSet;
  #445 = Utf8               (Lscala/Function1<Ljava/lang/Object;Ljava/lang/Object;>;)TC;
  #446 = Utf8               (Lscala/collection/IterableOps;Lscala/Function1;)V
  #447 = NameAndType        #106:#446     // "<init>":(Lscala/collection/IterableOps;Lscala/Function1;)V
  #448 = Methodref          #27.#447      // scala/collection/View$Map."<init>":(Lscala/collection/IterableOps;Lscala/Function1;)V
  #449 = Utf8               fromSpecific
  #450 = Utf8               (Lscala/collection/IterableOnce;)Ljava/lang/Object;
  #451 = NameAndType        #449:#450     // fromSpecific:(Lscala/collection/IterableOnce;)Ljava/lang/Object;
  #452 = InterfaceMethodref #2.#451       // scala/collection/BitSetOps.fromSpecific:(Lscala/collection/IterableOnce;)Ljava/lang/Object;
  #453 = Utf8               flatMap$
  #454 = Utf8               flatMap
  #455 = NameAndType        #454:#442     // flatMap:(Lscala/Function1;)Lscala/collection/BitSet;
  #456 = InterfaceMethodref #2.#455       // scala/collection/BitSetOps.flatMap:(Lscala/Function1;)Lscala/collection/BitSet;
  #457 = Utf8               (Lscala/Function1<Ljava/lang/Object;Lscala/collection/IterableOnce<Ljava/lang/Object;>;>;)TC;
  #458 = Methodref          #22.#447      // scala/collection/View$FlatMap."<init>":(Lscala/collection/IterableOps;Lscala/Function1;)V
  #459 = Utf8               collect$
  #460 = Utf8               (Lscala/collection/BitSetOps;Lscala/PartialFunction;)Lscala/collection/BitSet;
  #461 = Utf8               pf
  #462 = Utf8               collect
  #463 = Utf8               (Lscala/PartialFunction;)Lscala/collection/BitSet;
  #464 = NameAndType        #462:#463     // collect:(Lscala/PartialFunction;)Lscala/collection/BitSet;
  #465 = InterfaceMethodref #2.#464       // scala/collection/BitSetOps.collect:(Lscala/PartialFunction;)Lscala/collection/BitSet;
  #466 = Utf8               Lscala/PartialFunction;
  #467 = Utf8               (Lscala/PartialFunction<Ljava/lang/Object;Ljava/lang/Object;>;)TC;
  #468 = Utf8               (Lscala/collection/SortedSetOps;Lscala/PartialFunction;Lscala/math/Ordering;)Lscala/collection/SortedSet;
  #469 = NameAndType        #459:#468     // collect$:(Lscala/collection/SortedSetOps;Lscala/PartialFunction;Lscala/math/Ordering;)Lscala/collection/SortedSet;
  #470 = InterfaceMethodref #7.#469       // scala/collection/SortedSetOps.collect$:(Lscala/collection/SortedSetOps;Lscala/PartialFunction;Lscala/math/Ordering;)Lscala/collection/SortedSet;
  #471 = Utf8               partition$
  #472 = Utf8               (Lscala/collection/BitSetOps;Lscala/Function1;)Lscala/Tuple2;
  #473 = Utf8               p
  #474 = Utf8               partition
  #475 = Utf8               (Lscala/Function1;)Lscala/Tuple2;
  #476 = NameAndType        #474:#475     // partition:(Lscala/Function1;)Lscala/Tuple2;
  #477 = InterfaceMethodref #2.#476       // scala/collection/BitSetOps.partition:(Lscala/Function1;)Lscala/Tuple2;
  #478 = Utf8               (Lscala/Function1<Ljava/lang/Object;Ljava/lang/Object;>;)Lscala/Tuple2<TC;TC;>;
  #479 = Utf8               filter
  #480 = Utf8               (Lscala/Function1;)Ljava/lang/Object;
  #481 = NameAndType        #479:#480     // filter:(Lscala/Function1;)Ljava/lang/Object;
  #482 = InterfaceMethodref #2.#481       // scala/collection/BitSetOps.filter:(Lscala/Function1;)Ljava/lang/Object;
  #483 = Utf8               scala/Tuple2
  #484 = Class              #483          // scala/Tuple2
  #485 = Utf8               scala/collection/SetOps
  #486 = Class              #485          // scala/collection/SetOps
  #487 = Utf8               (Lscala/collection/Set;)Lscala/collection/SetOps;
  #488 = NameAndType        #416:#487     // diff:(Lscala/collection/Set;)Lscala/collection/SetOps;
  #489 = InterfaceMethodref #486.#488     // scala/collection/SetOps.diff:(Lscala/collection/Set;)Lscala/collection/SetOps;
  #490 = Utf8               (Ljava/lang/Object;Ljava/lang/Object;)V
  #491 = NameAndType        #106:#490     // "<init>":(Ljava/lang/Object;Ljava/lang/Object;)V
  #492 = Methodref          #484.#491     // scala/Tuple2."<init>":(Ljava/lang/Object;Ljava/lang/Object;)V
  #493 = Utf8               left
  #494 = Utf8               shape$1
  #495 = Integer            25
  #496 = Utf8               unexpected StepperShape:
  #497 = String             #496          // unexpected StepperShape:
  #498 = Utf8               words$1
  #499 = Utf8               x2$1
  #500 = InterfaceMethodref #376.#89      // scala/collection/BitSet.word:(I)J
  #501 = Utf8               words$2
  #502 = Utf8               x2$2
  #503 = Utf8               words$3
  #504 = Utf8               x2$3
  #505 = Utf8               words$4
  #506 = Utf8               other$1
  #507 = Utf8               $init$
  #508 = Utf8               (Lscala/collection/BitSetOps;)V
  #509 = Utf8               $deserializeLambda$
  #510 = Utf8               (Ljava/lang/invoke/SerializedLambda;)Ljava/lang/Object;
  #511 = Utf8               scala/runtime/LambdaDeserialize
  #512 = Class              #511          // scala/runtime/LambdaDeserialize
  #513 = Utf8               bootstrap
  #514 = Utf8               (Ljava/lang/invoke/MethodHandles$Lookup;Ljava/lang/String;Ljava/lang/invoke/MethodType;[Ljava/lang/invoke/MethodHandle;)Ljava/lang/invoke/CallSite;
  #515 = NameAndType        #513:#514     // bootstrap:(Ljava/lang/invoke/MethodHandles$Lookup;Ljava/lang/String;Ljava/lang/invoke/MethodType;[Ljava/lang/invoke/MethodHandle;)Ljava/lang/invoke/CallSite;
  #516 = Methodref          #512.#515     // scala/runtime/LambdaDeserialize.bootstrap:(Ljava/lang/invoke/MethodHandles$Lookup;Ljava/lang/String;Ljava/lang/invoke/MethodType;[Ljava/lang/invoke/MethodHandle;)Ljava/lang/invoke/CallSite;
  #517 = MethodHandle       6:#516        // REF_invokeStatic scala/runtime/LambdaDeserialize.bootstrap:(Ljava/lang/invoke/MethodHandles$Lookup;Ljava/lang/String;Ljava/lang/invoke/MethodType;[Ljava/lang/invoke/MethodHandle;)Ljava/lang/invoke/CallSite;
  #518 = Utf8               lambdaDeserialize
  #519 = NameAndType        #518:#510     // lambdaDeserialize:(Ljava/lang/invoke/SerializedLambda;)Ljava/lang/Object;
  #520 = InvokeDynamic      #1:#519       // #1:lambdaDeserialize:(Ljava/lang/invoke/SerializedLambda;)Ljava/lang/Object;
  #521 = Utf8               MethodParameters
  #522 = Utf8               Signature
  #523 = Utf8               Code
  #524 = Utf8               LineNumberTable
  #525 = Utf8               LocalVariableTable
  #526 = Utf8               StackMapTable
  #527 = Utf8               InnerClasses
  #528 = Utf8               SourceFile
  #529 = Utf8               RuntimeVisibleAnnotations
  #530 = Utf8               BootstrapMethods
  #531 = Utf8               ScalaInlineInfo
  #532 = Utf8               ScalaSig
{
  public abstract int scala$collection$BitSetOps$$super$max(scala.math.Ordering);
    descriptor: (Lscala/math/Ordering;)I
    flags: (0x1401) ACC_PUBLIC, ACC_ABSTRACT, ACC_SYNTHETIC
    MethodParameters:
      Name                           Flags
      ord                            final

  public abstract int scala$collection$BitSetOps$$super$min(scala.math.Ordering);
    descriptor: (Lscala/math/Ordering;)I
    flags: (0x1401) ACC_PUBLIC, ACC_ABSTRACT, ACC_SYNTHETIC
    MethodParameters:
      Name                           Flags
      ord                            final

  public abstract scala.collection.BitSet scala$collection$BitSetOps$$super$concat(scala.collection.IterableOnce);
    descriptor: (Lscala/collection/IterableOnce;)Lscala/collection/BitSet;
    flags: (0x1401) ACC_PUBLIC, ACC_ABSTRACT, ACC_SYNTHETIC
    MethodParameters:
      Name                           Flags
      that                           final

  public abstract scala.collection.BitSet scala$collection$BitSetOps$$super$intersect(scala.collection.Set);
    descriptor: (Lscala/collection/Set;)Lscala/collection/BitSet;
    flags: (0x1401) ACC_PUBLIC, ACC_ABSTRACT, ACC_SYNTHETIC
    MethodParameters:
      Name                           Flags
      that                           final

  public abstract scala.collection.BitSet scala$collection$BitSetOps$$super$diff(scala.collection.Set);
    descriptor: (Lscala/collection/Set;)Lscala/collection/BitSet;
    flags: (0x1401) ACC_PUBLIC, ACC_ABSTRACT, ACC_SYNTHETIC
    MethodParameters:
      Name                           Flags
      that                           final

  public abstract scala.collection.SpecificIterableFactory<java.lang.Object, C> bitSetFactory();
    descriptor: ()Lscala/collection/SpecificIterableFactory;
    flags: (0x0401) ACC_PUBLIC, ACC_ABSTRACT
    Signature: #54                          // ()Lscala/collection/SpecificIterableFactory<Ljava/lang/Object;TC;>;

  public abstract scala.collection.Set<java.lang.Object> unsorted();
    descriptor: ()Lscala/collection/Set;
    flags: (0x0401) ACC_PUBLIC, ACC_ABSTRACT
    Signature: #57                          // ()Lscala/collection/Set<Ljava/lang/Object;>;

  public static scala.math.Ordering ordering$(scala.collection.BitSetOps);
    descriptor: (Lscala/collection/BitSetOps;)Lscala/math/Ordering;
    flags: (0x1009) ACC_PUBLIC, ACC_STATIC, ACC_SYNTHETIC
    Code:
      stack=1, locals=1, args_size=1
         0: aload_0
         1: invokespecial #64                 // InterfaceMethod ordering:()Lscala/math/Ordering;
         4: areturn
      LineNumberTable:
        line 93: 0
      LocalVariableTable:
        Start  Length  Slot  Name   Signature
            0       5     0 $this   Lscala/collection/BitSetOps;
    MethodParameters:
      Name                           Flags
      $this                          final synthetic

  public default scala.math.Ordering<java.lang.Object> ordering();
    descriptor: ()Lscala/math/Ordering;
    flags: (0x0001) ACC_PUBLIC
    Code:
      stack=1, locals=1, args_size=1
         0: getstatic     #70                 // Field scala/math/Ordering$Int$.MODULE$:Lscala/math/Ordering$Int$;
         3: areturn
      LineNumberTable:
        line 93: 0
      LocalVariableTable:
        Start  Length  Slot  Name   Signature
            0       4     0  this   Lscala/collection/BitSetOps;
    Signature: #66                          // ()Lscala/math/Ordering<Ljava/lang/Object;>;

  public abstract int nwords();
    descriptor: ()I
    flags: (0x0401) ACC_PUBLIC, ACC_ABSTRACT

  public abstract long word(int);
    descriptor: (I)J
    flags: (0x0401) ACC_PUBLIC, ACC_ABSTRACT
    MethodParameters:
      Name                           Flags
      idx                            final

  public abstract C fromBitMaskNoCopy(long[]);
    descriptor: ([J)Lscala/collection/BitSet;
    flags: (0x0401) ACC_PUBLIC, ACC_ABSTRACT
    Signature: #79                          // ([J)TC;
    MethodParameters:
      Name                           Flags
      elems                          final

  public static boolean contains$(scala.collection.BitSetOps, int);
    descriptor: (Lscala/collection/BitSetOps;I)Z
    flags: (0x1009) ACC_PUBLIC, ACC_STATIC, ACC_SYNTHETIC
    Code:
      stack=2, locals=2, args_size=2
         0: aload_0
         1: iload_1
         2: invokespecial #87                 // InterfaceMethod contains:(I)Z
         5: ireturn
      LineNumberTable:
        line 107: 0
      LocalVariableTable:
        Start  Length  Slot  Name   Signature
            0       6     0 $this   Lscala/collection/BitSetOps;
            0       6     1  elem   I
    MethodParameters:
      Name                           Flags
      $this                          final synthetic
      elem                           final

  public default boolean contains(int);
    descriptor: (I)Z
    flags: (0x0001) ACC_PUBLIC
    Code:
      stack=5, locals=2, args_size=2
         0: iconst_0
         1: iload_1
         2: if_icmpgt     26
         5: aload_0
         6: iload_1
         7: bipush        6
         9: ishr
        10: invokeinterface #90,  2           // InterfaceMethod word:(I)J
        15: lconst_1
        16: iload_1
        17: lshl
        18: land
        19: lconst_0
        20: lcmp
        21: ifeq          26
        24: iconst_1
        25: ireturn
        26: iconst_0
        27: ireturn
      StackMapTable: number_of_entries = 1
        frame_type = 26 /* same */
      LineNumberTable:
        line 108: 0
      LocalVariableTable:
        Start  Length  Slot  Name   Signature
            0      28     0  this   Lscala/collection/BitSetOps;
            0      28     1  elem   I
    MethodParameters:
      Name                           Flags
      elem                           final

  public static scala.collection.Iterator iterator$(scala.collection.BitSetOps);
    descriptor: (Lscala/collection/BitSetOps;)Lscala/collection/Iterator;
    flags: (0x1009) ACC_PUBLIC, ACC_STATIC, ACC_SYNTHETIC
    Code:
      stack=1, locals=1, args_size=1
         0: aload_0
         1: invokespecial #96                 // InterfaceMethod iterator:()Lscala/collection/Iterator;
         4: areturn
      LineNumberTable:
        line 110: 0
      LocalVariableTable:
        Start  Length  Slot  Name   Signature
            0       5     0 $this   Lscala/collection/BitSetOps;
    MethodParameters:
      Name                           Flags
      $this                          final synthetic

  public default scala.collection.Iterator<java.lang.Object> iterator();
    descriptor: ()Lscala/collection/Iterator;
    flags: (0x0001) ACC_PUBLIC
    Code:
      stack=2, locals=1, args_size=1
         0: aload_0
         1: iconst_0
         2: invokeinterface #101,  2          // InterfaceMethod iteratorFrom:(I)Lscala/collection/Iterator;
         7: areturn
      LineNumberTable:
        line 110: 0
      LocalVariableTable:
        Start  Length  Slot  Name   Signature
            0       8     0  this   Lscala/collection/BitSetOps;
    Signature: #97                          // ()Lscala/collection/Iterator<Ljava/lang/Object;>;

  public static scala.collection.Iterator iteratorFrom$(scala.collection.BitSetOps, int);
    descriptor: (Lscala/collection/BitSetOps;I)Lscala/collection/Iterator;
    flags: (0x1009) ACC_PUBLIC, ACC_STATIC, ACC_SYNTHETIC
    Code:
      stack=2, locals=2, args_size=2
         0: aload_0
         1: iload_1
         2: invokespecial #101                // InterfaceMethod iteratorFrom:(I)Lscala/collection/Iterator;
         5: areturn
      LineNumberTable:
        line 112: 0
      LocalVariableTable:
        Start  Length  Slot  Name   Signature
            0       6     0 $this   Lscala/collection/BitSetOps;
            0       6     1 start   I
    MethodParameters:
      Name                           Flags
      $this                          final synthetic
      start                          final

  public default scala.collection.Iterator<java.lang.Object> iteratorFrom(int);
    descriptor: (I)Lscala/collection/Iterator;
    flags: (0x0001) ACC_PUBLIC
    Code:
      stack=4, locals=2, args_size=2
         0: new           #20                 // class scala/collection/BitSetOps$$anon$1
         3: dup
         4: aload_0
         5: iload_1
         6: invokespecial #109                // Method scala/collection/BitSetOps$$anon$1."<init>":(Lscala/collection/BitSetOps;I)V
         9: areturn
      LineNumberTable:
        line 112: 0
      LocalVariableTable:
        Start  Length  Slot  Name   Signature
            0      10     0  this   Lscala/collection/BitSetOps;
            0      10     1 start   I
    Signature: #105                         // (I)Lscala/collection/Iterator<Ljava/lang/Object;>;
    MethodParameters:
      Name                           Flags
      start                          final

  public static scala.collection.Stepper stepper$(scala.collection.BitSetOps, scala.collection.StepperShape);
    descriptor: (Lscala/collection/BitSetOps;Lscala/collection/StepperShape;)Lscala/collection/Stepper;
    flags: (0x1009) ACC_PUBLIC, ACC_STATIC, ACC_SYNTHETIC
    Code:
      stack=2, locals=2, args_size=2
         0: aload_0
         1: aload_1
         2: invokespecial #116                // InterfaceMethod stepper:(Lscala/collection/StepperShape;)Lscala/collection/Stepper;
         5: areturn
      LineNumberTable:
        line 132: 0
      LocalVariableTable:
        Start  Length  Slot  Name   Signature
            0       6     0 $this   Lscala/collection/BitSetOps;
            0       6     1 shape   Lscala/collection/StepperShape;
    MethodParameters:
      Name                           Flags
      $this                          final synthetic
      shape                          final

  public default <S extends scala.collection.Stepper<?>> S stepper(scala.collection.StepperShape<java.lang.Object, S>);
    descriptor: (Lscala/collection/StepperShape;)Lscala/collection/Stepper;
    flags: (0x0001) ACC_PUBLIC
    Code:
      stack=5, locals=3, args_size=2
         0: getstatic     #123                // Field scala/collection/convert/impl/BitSetStepper$.MODULE$:Lscala/collection/convert/impl/BitSetStepper$;
         3: aload_0
         4: invokevirtual #127                // Method scala/collection/convert/impl/BitSetStepper$.from:(Lscala/collection/BitSetOps;)Lscala/collection/IntStepper;
         7: astore_2
         8: aload_1
         9: invokeinterface #131,  1          // InterfaceMethod scala/collection/StepperShape.shape:()I
        14: getstatic     #136                // Field scala/collection/StepperShape$.MODULE$:Lscala/collection/StepperShape$;
        17: invokevirtual #139                // Method scala/collection/StepperShape$.IntShape:()I
        20: if_icmpne     25
        23: aload_2
        24: areturn
        25: aload_1
        26: invokeinterface #131,  1          // InterfaceMethod scala/collection/StepperShape.shape:()I
        31: getstatic     #136                // Field scala/collection/StepperShape$.MODULE$:Lscala/collection/StepperShape$;
        34: invokevirtual #142                // Method scala/collection/StepperShape$.ReferenceShape:()I
        37: if_icmpne     44
        40: iconst_1
        41: goto          45
        44: iconst_0
        45: ifne          80
        48: new           #144                // class java/lang/AssertionError
        51: dup
        52: new           #146                // class java/lang/StringBuilder
        55: dup
        56: ldc           #147                // int 18
        58: invokespecial #150                // Method java/lang/StringBuilder."<init>":(I)V
        61: ldc           #152                // String assertion failed:
        63: invokevirtual #156                // Method java/lang/StringBuilder.append:(Ljava/lang/String;)Ljava/lang/StringBuilder;
        66: aload_1
        67: invokestatic  #160                // InterfaceMethod $anonfun$stepper$1:(Lscala/collection/StepperShape;)Ljava/lang/String;
        70: invokevirtual #163                // Method java/lang/StringBuilder.append:(Ljava/lang/Object;)Ljava/lang/StringBuilder;
        73: invokevirtual #167                // Method java/lang/StringBuilder.toString:()Ljava/lang/String;
        76: invokespecial #170                // Method java/lang/AssertionError."<init>":(Ljava/lang/Object;)V
        79: athrow
        80: getstatic     #175                // Field scala/collection/AnyStepper$.MODULE$:Lscala/collection/AnyStepper$;
        83: pop
        84: new           #18                 // class scala/collection/AnyStepper$$anon$4
        87: dup
        88: aload_2
        89: invokespecial #178                // Method scala/collection/AnyStepper$$anon$4."<init>":(Lscala/collection/IntStepper;)V
        92: areturn
      StackMapTable: number_of_entries = 4
        frame_type = 252 /* append */
          offset_delta = 25
          locals = [ class scala/collection/IntStepper ]
        frame_type = 18 /* same */
        frame_type = 64 /* same_locals_1_stack_item */
          stack = [ int ]
        frame_type = 34 /* same */
      LineNumberTable:
        line 133: 0
        line 135: 8
        line 137: 25
        line 138: 80
        line 140: 92
      LocalVariableTable:
        Start  Length  Slot  Name   Signature
            8      84     2    st   Lscala/collection/IntStepper;
            0      93     0  this   Lscala/collection/BitSetOps;
            0      93     1 shape   Lscala/collection/StepperShape;
    Signature: #118                         // <S::Lscala/collection/Stepper<*>;>(Lscala/collection/StepperShape<Ljava/lang/Object;TS;>;)TS;
    MethodParameters:
      Name                           Flags
      shape                          final

  public static int size$(scala.collection.BitSetOps);
    descriptor: (Lscala/collection/BitSetOps;)I
    flags: (0x1009) ACC_PUBLIC, ACC_STATIC, ACC_SYNTHETIC
    Code:
      stack=1, locals=1, args_size=1
         0: aload_0
         1: invokespecial #187                // InterfaceMethod size:()I
         4: ireturn
      LineNumberTable:
        line 143: 0
      LocalVariableTable:
        Start  Length  Slot  Name   Signature
            0       5     0 $this   Lscala/collection/BitSetOps;
    MethodParameters:
      Name                           Flags
      $this                          final synthetic

  public default int size();
    descriptor: ()I
    flags: (0x0001) ACC_PUBLIC
    Code:
      stack=3, locals=3, args_size=1
         0: iconst_0
         1: istore_1
         2: aload_0
         3: invokeinterface #189,  1          // InterfaceMethod nwords:()I
         8: istore_2
         9: iload_2
        10: iconst_0
        11: if_icmple     33
        14: iinc          2, -1
        17: iload_1
        18: aload_0
        19: iload_2
        20: invokeinterface #90,  2           // InterfaceMethod word:(I)J
        25: invokestatic  #195                // Method java/lang/Long.bitCount:(J)I
        28: iadd
        29: istore_1
        30: goto          9
        33: iload_1
        34: ireturn
      StackMapTable: number_of_entries = 2
        frame_type = 253 /* append */
          offset_delta = 9
          locals = [ int, int ]
        frame_type = 23 /* same */
      LineNumberTable:
        line 144: 0
        line 145: 2
        line 146: 9
        line 147: 14
        line 148: 17
        line 146: 30
        line 150: 33
      LocalVariableTable:
        Start  Length  Slot  Name   Signature
            2      32     1     s   I
            9      25     2     i   I
            0      35     0  this   Lscala/collection/BitSetOps;

  public static boolean isEmpty$(scala.collection.BitSetOps);
    descriptor: (Lscala/collection/BitSetOps;)Z
    flags: (0x1009) ACC_PUBLIC, ACC_STATIC, ACC_SYNTHETIC
    Code:
      stack=1, locals=1, args_size=1
         0: aload_0
         1: invokespecial #203                // InterfaceMethod isEmpty:()Z
         4: ireturn
      LineNumberTable:
        line 153: 0
      LocalVariableTable:
        Start  Length  Slot  Name   Signature
            0       5     0 $this   Lscala/collection/BitSetOps;
    MethodParameters:
      Name                           Flags
      $this                          final synthetic

  public default boolean isEmpty();
    descriptor: ()Z
    flags: (0x0001) ACC_PUBLIC
    Code:
      stack=5, locals=3, args_size=1
         0: getstatic     #208                // Field scala/runtime/RichInt$.MODULE$:Lscala/runtime/RichInt$;
         3: pop
         4: iconst_0
         5: istore_1
         6: aload_0
         7: invokeinterface #189,  1          // InterfaceMethod nwords:()I
        12: istore_2
        13: getstatic     #213                // Field scala/collection/immutable/Range$.MODULE$:Lscala/collection/immutable/Range$;
        16: pop
        17: new           #30                 // class scala/collection/immutable/Range$Exclusive
        20: dup
        21: iload_1
        22: iload_2
        23: iconst_1
        24: invokespecial #216                // Method scala/collection/immutable/Range$Exclusive."<init>":(III)V
        27: aload_0
        28: invokedynamic #233,  0            // InvokeDynamic #0:apply$mcZI$sp:(Lscala/collection/BitSetOps;)Lscala/runtime/java8/JFunction1$mcZI$sp;
        33: invokevirtual #237                // Method scala/collection/immutable/Range.forall:(Lscala/Function1;)Z
        36: ireturn
      LineNumberTable:
        line 153: 0
      LocalVariableTable:
        Start  Length  Slot  Name   Signature
            0      37     0  this   Lscala/collection/BitSetOps;
           13      14     2 until$extension_end   I

  private int smallestInt();
    descriptor: ()I
    flags: (0x0002) ACC_PRIVATE
    Code:
      stack=4, locals=5, args_size=1
         0: aload_0
         1: invokeinterface #189,  1          // InterfaceMethod nwords:()I
         6: istore_1
         7: iconst_0
         8: istore_2
         9: iload_2
        10: iload_1
        11: if_icmpge     44
        14: aload_0
        15: iload_2
        16: invokeinterface #90,  2           // InterfaceMethod word:(I)J
        21: lstore_3
        22: lload_3
        23: lconst_0
        24: lcmp
        25: ifeq          38
        28: lload_3
        29: invokestatic  #242                // Method java/lang/Long.numberOfTrailingZeros:(J)I
        32: iload_2
        33: bipush        64
        35: imul
        36: iadd
        37: ireturn
        38: iinc          2, 1
        41: goto          9
        44: new           #244                // class java/lang/UnsupportedOperationException
        47: dup
        48: ldc           #246                // String empty.smallestInt
        50: invokespecial #249                // Method java/lang/UnsupportedOperationException."<init>":(Ljava/lang/String;)V
        53: athrow
      StackMapTable: number_of_entries = 3
        frame_type = 253 /* append */
          offset_delta = 9
          locals = [ int, int ]
        frame_type = 252 /* append */
          offset_delta = 28
          locals = [ long ]
        frame_type = 250 /* chop */
          offset_delta = 5
      LineNumberTable:
        line 156: 0
        line 157: 7
        line 158: 9
        line 159: 14
        line 160: 22
        line 161: 28
        line 163: 38
        line 158: 41
        line 165: 44
      LocalVariableTable:
        Start  Length  Slot  Name   Signature
           22      19     3 currentWord   J
            7      47     1 thisnwords   I
            9      45     2     i   I
            0      54     0  this   Lscala/collection/BitSetOps;

  private int largestInt();
    descriptor: ()I
    flags: (0x0002) ACC_PRIVATE
    Code:
      stack=4, locals=4, args_size=1
         0: aload_0
         1: invokeinterface #189,  1          // InterfaceMethod nwords:()I
         6: iconst_1
         7: isub
         8: istore_1
         9: iload_1
        10: iconst_0
        11: if_icmplt     48
        14: aload_0
        15: iload_1
        16: invokeinterface #90,  2           // InterfaceMethod word:(I)J
        21: lstore_2
        22: lload_2
        23: lconst_0
        24: lcmp
        25: ifeq          42
        28: iload_1
        29: iconst_1
        30: iadd
        31: bipush        64
        33: imul
        34: lload_2
        35: invokestatic  #256                // Method java/lang/Long.numberOfLeadingZeros:(J)I
        38: isub
        39: iconst_1
        40: isub
        41: ireturn
        42: iinc          1, -1
        45: goto          9
        48: new           #244                // class java/lang/UnsupportedOperationException
        51: dup
        52: ldc_w         #258                // String empty.largestInt
        55: invokespecial #249                // Method java/lang/UnsupportedOperationException."<init>":(Ljava/lang/String;)V
        58: athrow
      StackMapTable: number_of_entries = 3
        frame_type = 252 /* append */
          offset_delta = 9
          locals = [ int ]
        frame_type = 252 /* append */
          offset_delta = 32
          locals = [ long ]
        frame_type = 250 /* chop */
          offset_delta = 5
      LineNumberTable:
        line 169: 0
        line 170: 9
        line 171: 14
        line 172: 22
        line 173: 28
        line 175: 42
        line 170: 45
        line 177: 48
      LocalVariableTable:
        Start  Length  Slot  Name   Signature
           22      23     2 currentWord   J
            9      50     1     i   I
            0      59     0  this   Lscala/collection/BitSetOps;

  public static int max$(scala.collection.BitSetOps, scala.math.Ordering);
    descriptor: (Lscala/collection/BitSetOps;Lscala/math/Ordering;)I
    flags: (0x1009) ACC_PUBLIC, ACC_STATIC, ACC_SYNTHETIC
    Code:
      stack=2, locals=2, args_size=2
         0: aload_0
         1: aload_1
         2: invokespecial #263                // InterfaceMethod max:(Lscala/math/Ordering;)I
         5: ireturn
      LineNumberTable:
        line 180: 0
      LocalVariableTable:
        Start  Length  Slot  Name   Signature
            0       6     0 $this   Lscala/collection/BitSetOps;
            0       6     1   ord   Lscala/math/Ordering;
    MethodParameters:
      Name                           Flags
      $this                          final synthetic
      ord                            final

  public default <B extends java.lang.Object> int max(scala.math.Ordering<B>);
    descriptor: (Lscala/math/Ordering;)I
    flags: (0x0001) ACC_PUBLIC
    Code:
      stack=4, locals=11, args_size=2
         0: getstatic     #70                 // Field scala/math/Ordering$Int$.MODULE$:Lscala/math/Ordering$Int$;
         3: aload_1
         4: if_acmpne     73
         7: aload_0
         8: invokeinterface #189,  1          // InterfaceMethod nwords:()I
        13: iconst_1
        14: isub
        15: istore_2
        16: iload_2
        17: iconst_0
        18: if_icmplt     59
        21: aload_0
        22: iload_2
        23: invokeinterface #90,  2           // InterfaceMethod word:(I)J
        28: lstore_3
        29: lload_3
        30: lconst_0
        31: lcmp
        32: ifeq          53
        35: iload_2
        36: iconst_1
        37: iadd
        38: bipush        64
        40: imul
        41: lload_3
        42: invokestatic  #256                // Method java/lang/Long.numberOfLeadingZeros:(J)I
        45: isub
        46: iconst_1
        47: isub
        48: istore        5
        50: goto          70
        53: iinc          2, -1
        56: goto          16
        59: new           #244                // class java/lang/UnsupportedOperationException
        62: dup
        63: ldc_w         #258                // String empty.largestInt
        66: invokespecial #249                // Method java/lang/UnsupportedOperationException."<init>":(Ljava/lang/String;)V
        69: athrow
        70: iload         5
        72: ireturn
        73: getstatic     #70                 // Field scala/math/Ordering$Int$.MODULE$:Lscala/math/Ordering$Int$;
        76: aload_1
        77: invokestatic  #269                // InterfaceMethod scala/math/Ordering$CachedReverse.isReverseOf$:(Lscala/math/Ordering$CachedReverse;Lscala/math/Ordering;)Z
        80: ifeq          153
        83: aload_0
        84: invokeinterface #189,  1          // InterfaceMethod nwords:()I
        89: istore        6
        91: iconst_0
        92: istore        7
        94: iload         7
        96: iload         6
        98: if_icmpge     140
       101: aload_0
       102: iload         7
       104: invokeinterface #90,  2           // InterfaceMethod word:(I)J
       109: lstore        8
       111: lload         8
       113: lconst_0
       114: lcmp
       115: ifeq          134
       118: lload         8
       120: invokestatic  #242                // Method java/lang/Long.numberOfTrailingZeros:(J)I
       123: iload         7
       125: bipush        64
       127: imul
       128: iadd
       129: istore        10
       131: goto          150
       134: iinc          7, 1
       137: goto          94
       140: new           #244                // class java/lang/UnsupportedOperationException
       143: dup
       144: ldc           #246                // String empty.smallestInt
       146: invokespecial #249                // Method java/lang/UnsupportedOperationException."<init>":(Ljava/lang/String;)V
       149: athrow
       150: iload         10
       152: ireturn
       153: aload_0
       154: aload_1
       155: invokeinterface #271,  2          // InterfaceMethod scala$collection$BitSetOps$$super$max:(Lscala/math/Ordering;)I
       160: ireturn
      StackMapTable: number_of_entries = 10
        frame_type = 252 /* append */
          offset_delta = 16
          locals = [ int ]
        frame_type = 252 /* append */
          offset_delta = 36
          locals = [ long ]
        frame_type = 250 /* chop */
          offset_delta = 5
        frame_type = 253 /* append */
          offset_delta = 10
          locals = [ long, int ]
        frame_type = 248 /* chop */
          offset_delta = 2
        frame_type = 255 /* full_frame */
          offset_delta = 20
          locals = [ class scala/collection/BitSetOps, class scala/math/Ordering, top, top, top, top, int, int ]
          stack = []
        frame_type = 252 /* append */
          offset_delta = 39
          locals = [ long ]
        frame_type = 250 /* chop */
          offset_delta = 5
        frame_type = 253 /* append */
          offset_delta = 9
          locals = [ long, int ]
        frame_type = 255 /* full_frame */
          offset_delta = 2
          locals = [ class scala/collection/BitSetOps, class scala/math/Ordering ]
          stack = []
      LineNumberTable:
        line 181: 0
        line 169: 7
        line 170: 16
        line 171: 21
        line 172: 29
        line 173: 35
        line 175: 53
        line 170: 56
        line 177: 59
        line 181: 70
        line 182: 73
        line 156: 83
        line 157: 91
        line 158: 94
        line 159: 101
        line 160: 111
        line 161: 118
        line 163: 134
        line 158: 137
        line 165: 140
        line 182: 150
        line 183: 153
      LocalVariableTable:
        Start  Length  Slot  Name   Signature
            0     161     0  this   Lscala/collection/BitSetOps;
            0     161     1   ord   Lscala/math/Ordering;
           29      27     3 largestInt_currentWord   J
           16      54     2 largestInt_i   I
          111      26     8 smallestInt_currentWord   J
           91      59     6 smallestInt_thisnwords   I
           94      56     7 smallestInt_i   I
    Signature: #265                         // <B:Ljava/lang/Object;>(Lscala/math/Ordering<TB;>;)I
    MethodParameters:
      Name                           Flags
      ord                            final

  public static int min$(scala.collection.BitSetOps, scala.math.Ordering);
    descriptor: (Lscala/collection/BitSetOps;Lscala/math/Ordering;)I
    flags: (0x1009) ACC_PUBLIC, ACC_STATIC, ACC_SYNTHETIC
    Code:
      stack=2, locals=2, args_size=2
         0: aload_0
         1: aload_1
         2: invokespecial #280                // InterfaceMethod min:(Lscala/math/Ordering;)I
         5: ireturn
      LineNumberTable:
        line 186: 0
      LocalVariableTable:
        Start  Length  Slot  Name   Signature
            0       6     0 $this   Lscala/collection/BitSetOps;
            0       6     1   ord   Lscala/math/Ordering;
    MethodParameters:
      Name                           Flags
      $this                          final synthetic
      ord                            final

  public default <B extends java.lang.Object> int min(scala.math.Ordering<B>);
    descriptor: (Lscala/math/Ordering;)I
    flags: (0x0001) ACC_PUBLIC
    Code:
      stack=4, locals=11, args_size=2
         0: getstatic     #70                 // Field scala/math/Ordering$Int$.MODULE$:Lscala/math/Ordering$Int$;
         3: aload_1
         4: if_acmpne     71
         7: aload_0
         8: invokeinterface #189,  1          // InterfaceMethod nwords:()I
        13: istore_2
        14: iconst_0
        15: istore_3
        16: iload_3
        17: iload_2
        18: if_icmpge     58
        21: aload_0
        22: iload_3
        23: invokeinterface #90,  2           // InterfaceMethod word:(I)J
        28: lstore        4
        30: lload         4
        32: lconst_0
        33: lcmp
        34: ifeq          52
        37: lload         4
        39: invokestatic  #242                // Method java/lang/Long.numberOfTrailingZeros:(J)I
        42: iload_3
        43: bipush        64
        45: imul
        46: iadd
        47: istore        6
        49: goto          68
        52: iinc          3, 1
        55: goto          16
        58: new           #244                // class java/lang/UnsupportedOperationException
        61: dup
        62: ldc           #246                // String empty.smallestInt
        64: invokespecial #249                // Method java/lang/UnsupportedOperationException."<init>":(Ljava/lang/String;)V
        67: athrow
        68: iload         6
        70: ireturn
        71: getstatic     #70                 // Field scala/math/Ordering$Int$.MODULE$:Lscala/math/Ordering$Int$;
        74: aload_1
        75: invokestatic  #269                // InterfaceMethod scala/math/Ordering$CachedReverse.isReverseOf$:(Lscala/math/Ordering$CachedReverse;Lscala/math/Ordering;)Z
        78: ifeq          154
        81: aload_0
        82: invokeinterface #189,  1          // InterfaceMethod nwords:()I
        87: iconst_1
        88: isub
        89: istore        7
        91: iload         7
        93: iconst_0
        94: if_icmplt     140
        97: aload_0
        98: iload         7
       100: invokeinterface #90,  2           // InterfaceMethod word:(I)J
       105: lstore        8
       107: lload         8
       109: lconst_0
       110: lcmp
       111: ifeq          134
       114: iload         7
       116: iconst_1
       117: iadd
       118: bipush        64
       120: imul
       121: lload         8
       123: invokestatic  #256                // Method java/lang/Long.numberOfLeadingZeros:(J)I
       126: isub
       127: iconst_1
       128: isub
       129: istore        10
       131: goto          151
       134: iinc          7, -1
       137: goto          91
       140: new           #244                // class java/lang/UnsupportedOperationException
       143: dup
       144: ldc_w         #258                // String empty.largestInt
       147: invokespecial #249                // Method java/lang/UnsupportedOperationException."<init>":(Ljava/lang/String;)V
       150: athrow
       151: iload         10
       153: ireturn
       154: aload_0
       155: aload_1
       156: invokeinterface #282,  2          // InterfaceMethod scala$collection$BitSetOps$$super$min:(Lscala/math/Ordering;)I
       161: ireturn
      StackMapTable: number_of_entries = 10
        frame_type = 253 /* append */
          offset_delta = 16
          locals = [ int, int ]
        frame_type = 252 /* append */
          offset_delta = 35
          locals = [ long ]
        frame_type = 250 /* chop */
          offset_delta = 5
        frame_type = 253 /* append */
          offset_delta = 9
          locals = [ long, int ]
        frame_type = 255 /* full_frame */
          offset_delta = 2
          locals = [ class scala/collection/BitSetOps, class scala/math/Ordering ]
          stack = []
        frame_type = 255 /* full_frame */
          offset_delta = 19
          locals = [ class scala/collection/BitSetOps, class scala/math/Ordering, top, top, top, top, top, int ]
          stack = []
        frame_type = 252 /* append */
          offset_delta = 42
          locals = [ long ]
        frame_type = 250 /* chop */
          offset_delta = 5
        frame_type = 253 /* append */
          offset_delta = 10
          locals = [ long, int ]
        frame_type = 255 /* full_frame */
          offset_delta = 2
          locals = [ class scala/collection/BitSetOps, class scala/math/Ordering ]
          stack = []
      LineNumberTable:
        line 187: 0
        line 156: 7
        line 157: 14
        line 158: 16
        line 159: 21
        line 160: 30
        line 161: 37
        line 163: 52
        line 158: 55
        line 165: 58
        line 187: 68
        line 188: 71
        line 169: 81
        line 170: 91
        line 171: 97
        line 172: 107
        line 173: 114
        line 175: 134
        line 170: 137
        line 177: 140
        line 188: 151
        line 189: 154
      LocalVariableTable:
        Start  Length  Slot  Name   Signature
            0     162     0  this   Lscala/collection/BitSetOps;
            0     162     1   ord   Lscala/math/Ordering;
           30      25     4 smallestInt_currentWord   J
           14      54     2 smallestInt_thisnwords   I
           16      52     3 smallestInt_i   I
          107      30     8 largestInt_currentWord   J
           91      60     7 largestInt_i   I
    Signature: #265                         // <B:Ljava/lang/Object;>(Lscala/math/Ordering<TB;>;)I
    MethodParameters:
      Name                           Flags
      ord                            final

  public static void foreach$(scala.collection.BitSetOps, scala.Function1);
    descriptor: (Lscala/collection/BitSetOps;Lscala/Function1;)V
    flags: (0x1009) ACC_PUBLIC, ACC_STATIC, ACC_SYNTHETIC
    Code:
      stack=2, locals=2, args_size=2
         0: aload_0
         1: aload_1
         2: invokespecial #289                // InterfaceMethod foreach:(Lscala/Function1;)V
         5: return
      LineNumberTable:
        line 191: 0
      LocalVariableTable:
        Start  Length  Slot  Name   Signature
            0       6     0 $this   Lscala/collection/BitSetOps;
            0       6     1     f   Lscala/Function1;
    MethodParameters:
      Name                           Flags
      $this                          final synthetic
      f                              final

  public default <U extends java.lang.Object> void foreach(scala.Function1<java.lang.Object, U>);
    descriptor: (Lscala/Function1;)V
    flags: (0x0001) ACC_PUBLIC
    Code:
      stack=4, locals=6, args_size=2
         0: iconst_0
         1: istore_2
         2: iload_2
         3: aload_0
         4: invokeinterface #189,  1          // InterfaceMethod nwords:()I
         9: if_icmpge     68
        12: aload_0
        13: iload_2
        14: invokeinterface #90,  2           // InterfaceMethod word:(I)J
        19: lstore_3
        20: iload_2
        21: bipush        64
        23: imul
        24: istore        5
        26: lload_3
        27: lconst_0
        28: lcmp
        29: ifeq          62
        32: lload_3
        33: lconst_1
        34: land
        35: lconst_1
        36: lcmp
        37: ifne          52
        40: aload_1
        41: iload         5
        43: invokestatic  #297                // Method java/lang/Integer.valueOf:(I)Ljava/lang/Integer;
        46: invokeinterface #303,  2          // InterfaceMethod scala/Function1.apply:(Ljava/lang/Object;)Ljava/lang/Object;
        51: pop
        52: lload_3
        53: iconst_1
        54: lushr
        55: lstore_3
        56: iinc          5, 1
        59: goto          26
        62: iinc          2, 1
        65: goto          2
        68: return
      StackMapTable: number_of_entries = 5
        frame_type = 252 /* append */
          offset_delta = 2
          locals = [ int ]
        frame_type = 253 /* append */
          offset_delta = 23
          locals = [ long, int ]
        frame_type = 25 /* same */
        frame_type = 9 /* same */
        frame_type = 249 /* chop */
          offset_delta = 5
      LineNumberTable:
        line 196: 0
        line 197: 2
        line 198: 12
        line 199: 20
        line 200: 26
        line 201: 32
        line 202: 52
        line 203: 56
        line 200: 59
        line 205: 62
        line 197: 65
      LocalVariableTable:
        Start  Length  Slot  Name   Signature
           20      45     3     w   J
           26      39     5     j   I
            2      66     2     i   I
            0      69     0  this   Lscala/collection/BitSetOps;
            0      69     1     f   Lscala/Function1;
    Signature: #291                         // <U:Ljava/lang/Object;>(Lscala/Function1<Ljava/lang/Object;TU;>;)V
    MethodParameters:
      Name                           Flags
      f                              final

  public static long[] toBitMask$(scala.collection.BitSetOps);
    descriptor: (Lscala/collection/BitSetOps;)[J
    flags: (0x1009) ACC_PUBLIC, ACC_STATIC, ACC_SYNTHETIC
    Code:
      stack=1, locals=1, args_size=1
         0: aload_0
         1: invokespecial #311                // InterfaceMethod toBitMask:()[J
         4: areturn
      LineNumberTable:
        line 211: 0
      LocalVariableTable:
        Start  Length  Slot  Name   Signature
            0       5     0 $this   Lscala/collection/BitSetOps;
    MethodParameters:
      Name                           Flags
      $this                          final synthetic

  public default long[] toBitMask();
    descriptor: ()[J
    flags: (0x0001) ACC_PUBLIC
    Code:
      stack=4, locals=3, args_size=1
         0: aload_0
         1: invokeinterface #189,  1          // InterfaceMethod nwords:()I
         6: newarray       long
         8: astore_1
         9: aload_1
        10: arraylength
        11: istore_2
        12: iload_2
        13: iconst_0
        14: if_icmple     33
        17: iinc          2, -1
        20: aload_1
        21: iload_2
        22: aload_0
        23: iload_2
        24: invokeinterface #90,  2           // InterfaceMethod word:(I)J
        29: lastore
        30: goto          12
        33: aload_1
        34: areturn
      StackMapTable: number_of_entries = 2
        frame_type = 253 /* append */
          offset_delta = 12
          locals = [ class "[J", int ]
        frame_type = 20 /* same */
      LineNumberTable:
        line 212: 0
        line 213: 9
        line 214: 12
        line 215: 17
        line 216: 20
        line 214: 30
        line 218: 33
      LocalVariableTable:
        Start  Length  Slot  Name   Signature
            9      25     1     a   [J
           12      22     2     i   I
            0      35     0  this   Lscala/collection/BitSetOps;

  public static scala.collection.BitSet rangeImpl$(scala.collection.BitSetOps, scala.Option, scala.Option);
    descriptor: (Lscala/collection/BitSetOps;Lscala/Option;Lscala/Option;)Lscala/collection/BitSet;
    flags: (0x1009) ACC_PUBLIC, ACC_STATIC, ACC_SYNTHETIC
    Code:
      stack=3, locals=3, args_size=3
         0: aload_0
         1: aload_1
         2: aload_2
         3: invokespecial #321                // InterfaceMethod rangeImpl:(Lscala/Option;Lscala/Option;)Lscala/collection/BitSet;
         6: areturn
      LineNumberTable:
        line 221: 0
      LocalVariableTable:
        Start  Length  Slot  Name   Signature
            0       7     0 $this   Lscala/collection/BitSetOps;
            0       7     1  from   Lscala/Option;
            0       7     2 until   Lscala/Option;
    MethodParameters:
      Name                           Flags
      $this                          final synthetic
      from                           final
      until                          final

  public default C rangeImpl(scala.Option<java.lang.Object>, scala.Option<java.lang.Object>);
    descriptor: (Lscala/Option;Lscala/Option;)Lscala/collection/BitSet;
    flags: (0x0001) ACC_PUBLIC
    Code:
      stack=8, locals=11, args_size=3
         0: aload_0
         1: invokeinterface #327,  1          // InterfaceMethod coll:()Ljava/lang/Object;
         6: checkcast     #2                  // class scala/collection/BitSetOps
         9: invokeinterface #311,  1          // InterfaceMethod toBitMask:()[J
        14: astore_3
        15: aload_3
        16: arraylength
        17: istore        4
        19: aload_1
        20: invokevirtual #332                // Method scala/Option.isDefined:()Z
        23: ifeq          104
        26: aload_1
        27: invokevirtual #335                // Method scala/Option.get:()Ljava/lang/Object;
        30: invokestatic  #341                // Method scala/runtime/BoxesRunTime.unboxToInt:(Ljava/lang/Object;)I
        33: istore        5
        35: iload         5
        37: bipush        6
        39: ishr
        40: istore        6
        42: iload         5
        44: bipush        63
        46: iand
        47: istore        7
        49: iload         6
        51: iconst_0
        52: if_icmplt     104
        55: aload_3
        56: iconst_0
        57: getstatic     #346                // Field scala/math/package$.MODULE$:Lscala/math/package$;
        60: pop
        61: iload         6
        63: iload         4
        65: invokestatic  #351                // Method java/lang/Math.min:(II)I
        68: lconst_0
        69: invokestatic  #357                // Method java/util/Arrays.fill:([JIIJ)V
        72: iload         7
        74: iconst_0
        75: if_icmple     104
        78: iload         6
        80: iload         4
        82: if_icmpge     104
        85: aload_3
        86: iload         6
        88: aload_3
        89: iload         6
        91: laload
        92: lconst_1
        93: iload         7
        95: lshl
        96: lconst_1
        97: lsub
        98: ldc2_w        #358                // long -1l
       101: lxor
       102: land
       103: lastore
       104: aload_2
       105: invokevirtual #332                // Method scala/Option.isDefined:()Z
       108: ifeq          181
       111: aload_2
       112: invokevirtual #335                // Method scala/Option.get:()Ljava/lang/Object;
       115: invokestatic  #341                // Method scala/runtime/BoxesRunTime.unboxToInt:(Ljava/lang/Object;)I
       118: istore        8
       120: iload         8
       122: bipush        6
       124: ishr
       125: istore        9
       127: iload         8
       129: bipush        63
       131: iand
       132: istore        10
       134: iload         9
       136: iload         4
       138: if_icmpge     181
       141: aload_3
       142: getstatic     #346                // Field scala/math/package$.MODULE$:Lscala/math/package$;
       145: pop
       146: iload         9
       148: iconst_1
       149: iadd
       150: iconst_0
       151: invokestatic  #361                // Method java/lang/Math.max:(II)I
       154: iload         4
       156: lconst_0
       157: invokestatic  #357                // Method java/util/Arrays.fill:([JIIJ)V
       160: iload         9
       162: iconst_0
       163: if_icmplt     181
       166: aload_3
       167: iload         9
       169: aload_3
       170: iload         9
       172: laload
       173: lconst_1
       174: iload         10
       176: lshl
       177: lconst_1
       178: lsub
       179: land
       180: lastore
       181: aload_0
       182: invokeinterface #327,  1          // InterfaceMethod coll:()Ljava/lang/Object;
       187: checkcast     #2                  // class scala/collection/BitSetOps
       190: aload_3
       191: invokeinterface #363,  2          // InterfaceMethod fromBitMaskNoCopy:([J)Lscala/collection/BitSet;
       196: areturn
      StackMapTable: number_of_entries = 2
        frame_type = 253 /* append */
          offset_delta = 104
          locals = [ class "[J", int ]
        frame_type = 251 /* same_frame_extended */
          offset_delta = 76
      LineNumberTable:
        line 222: 0
        line 223: 15
        line 224: 19
        line 225: 26
        line 226: 35
        line 227: 42
        line 228: 49
        line 229: 55
        line 230: 72
        line 233: 104
        line 234: 111
        line 235: 120
        line 236: 127
        line 237: 134
        line 238: 141
        line 239: 160
        line 242: 181
      LocalVariableTable:
        Start  Length  Slot  Name   Signature
           35      69     5     f   I
           42      62     6     w   I
           49      55     7     b   I
          120      61     8     u   I
          127      54     9     w   I
          134      47    10     b   I
           15     181     3     a   [J
           19     177     4   len   I
            0     197     0  this   Lscala/collection/BitSetOps;
            0     197     1  from   Lscala/Option;
            0     197     2 until   Lscala/Option;
    Signature: #323                         // (Lscala/Option<Ljava/lang/Object;>;Lscala/Option<Ljava/lang/Object;>;)TC;
    MethodParameters:
      Name                           Flags
      from                           final
      until                          final

  public static scala.collection.BitSet concat$(scala.collection.BitSetOps, scala.collection.IterableOnce);
    descriptor: (Lscala/collection/BitSetOps;Lscala/collection/IterableOnce;)Lscala/collection/BitSet;
    flags: (0x1009) ACC_PUBLIC, ACC_STATIC, ACC_SYNTHETIC
    Code:
      stack=2, locals=2, args_size=2
         0: aload_0
         1: aload_1
         2: invokespecial #372                // InterfaceMethod concat:(Lscala/collection/IterableOnce;)Lscala/collection/BitSet;
         5: areturn
      LineNumberTable:
        line 245: 0
      LocalVariableTable:
        Start  Length  Slot  Name   Signature
            0       6     0 $this   Lscala/collection/BitSetOps;
            0       6     1 other   Lscala/collection/IterableOnce;
    MethodParameters:
      Name                           Flags
      $this                          final synthetic
      other                          final

  public default C concat(scala.collection.IterableOnce<java.lang.Object>);
    descriptor: (Lscala/collection/IterableOnce;)Lscala/collection/BitSet;
    flags: (0x0001) ACC_PUBLIC
    Code:
      stack=5, locals=11, args_size=2
         0: aload_1
         1: instanceof    #376                // class scala/collection/BitSet
         4: ifeq          146
         7: aload_1
         8: checkcast     #376                // class scala/collection/BitSet
        11: astore_3
        12: getstatic     #208                // Field scala/runtime/RichInt$.MODULE$:Lscala/runtime/RichInt$;
        15: pop
        16: aload_0
        17: invokeinterface #327,  1          // InterfaceMethod coll:()Ljava/lang/Object;
        22: checkcast     #2                  // class scala/collection/BitSetOps
        25: invokeinterface #189,  1          // InterfaceMethod nwords:()I
        30: istore        5
        32: aload_3
        33: invokeinterface #377,  1          // InterfaceMethod scala/collection/BitSet.nwords:()I
        38: istore        9
        40: getstatic     #346                // Field scala/math/package$.MODULE$:Lscala/math/package$;
        43: pop
        44: iload         5
        46: iload         9
        48: invokestatic  #361                // Method java/lang/Math.max:(II)I
        51: istore        10
        53: iload         10
        55: newarray       long
        57: astore        4
        59: getstatic     #208                // Field scala/runtime/RichInt$.MODULE$:Lscala/runtime/RichInt$;
        62: pop
        63: iconst_0
        64: istore        6
        66: getstatic     #213                // Field scala/collection/immutable/Range$.MODULE$:Lscala/collection/immutable/Range$;
        69: pop
        70: new           #30                 // class scala/collection/immutable/Range$Exclusive
        73: dup
        74: iload         6
        76: iload         10
        78: iconst_1
        79: invokespecial #216                // Method scala/collection/immutable/Range$Exclusive."<init>":(III)V
        82: astore        7
        84: aload         7
        86: invokevirtual #378                // Method scala/collection/immutable/Range.isEmpty:()Z
        89: ifne          131
        92: aload         7
        94: invokevirtual #380                // Method scala/collection/immutable/Range.start:()I
        97: istore        8
        99: aload_0
       100: aload         4
       102: aload_3
       103: iload         8
       105: invokestatic  #384                // InterfaceMethod $anonfun$concat$1:(Lscala/collection/BitSetOps;[JLscala/collection/BitSet;I)V
       108: iload         8
       110: aload         7
       112: getfield      #387                // Field scala/collection/immutable/Range.scala$collection$immutable$Range$$lastElement:I
       115: if_icmpeq     131
       118: iload         8
       120: aload         7
       122: invokevirtual #390                // Method scala/collection/immutable/Range.step:()I
       125: iadd
       126: istore        8
       128: goto          99
       131: aconst_null
       132: astore        7
       134: aload_0
       135: aload         4
       137: invokeinterface #363,  2          // InterfaceMethod fromBitMaskNoCopy:([J)Lscala/collection/BitSet;
       142: astore_2
       143: goto          154
       146: aload_0
       147: aload_1
       148: invokeinterface #392,  2          // InterfaceMethod scala$collection$BitSetOps$$super$concat:(Lscala/collection/IterableOnce;)Lscala/collection/BitSet;
       153: astore_2
       154: aload_2
       155: areturn
      StackMapTable: number_of_entries = 4
        frame_type = 255 /* full_frame */
          offset_delta = 99
          locals = [ class scala/collection/BitSetOps, class scala/collection/IterableOnce, top, class scala/collection/BitSet, class "[J", int, int, class scala/collection/immutable/Range$Exclusive, int, int, int ]
          stack = []
        frame_type = 255 /* full_frame */
          offset_delta = 31
          locals = [ class scala/collection/BitSetOps, class scala/collection/IterableOnce, top, class scala/collection/BitSet, class "[J", int, int, class scala/collection/immutable/Range$Exclusive, top, int, int ]
          stack = []
        frame_type = 255 /* full_frame */
          offset_delta = 14
          locals = [ class scala/collection/BitSetOps, class scala/collection/IterableOnce ]
          stack = []
        frame_type = 252 /* append */
          offset_delta = 7
          locals = [ class scala/collection/BitSet ]
      LineNumberTable:
        line 246: 0
        line 247: 12
        line 248: 53
        line 249: 59
        line 251: 134
        line 252: 146
        line 245: 154
      LocalVariableTable:
        Start  Length  Slot  Name   Signature
           59      83     4 words   [J
            0     156     0  this   Lscala/collection/BitSetOps;
            0     156     1 other   Lscala/collection/IterableOnce;
           99      32     8 foreach$mVc$sp_i   I
           84      47     7 foreach$mVc$sp_this   Lscala/collection/immutable/Range;
           40      13     9 max$extension_that   I
    Signature: #374                         // (Lscala/collection/IterableOnce<Ljava/lang/Object;>;)TC;
    MethodParameters:
      Name                           Flags
      other                          final

  public static scala.collection.BitSet intersect$(scala.collection.BitSetOps, scala.collection.Set);
    descriptor: (Lscala/collection/BitSetOps;Lscala/collection/Set;)Lscala/collection/BitSet;
    flags: (0x1009) ACC_PUBLIC, ACC_STATIC, ACC_SYNTHETIC
    Code:
      stack=2, locals=2, args_size=2
         0: aload_0
         1: aload_1
         2: invokespecial #404                // InterfaceMethod intersect:(Lscala/collection/Set;)Lscala/collection/BitSet;
         5: areturn
      LineNumberTable:
        line 255: 0
      LocalVariableTable:
        Start  Length  Slot  Name   Signature
            0       6     0 $this   Lscala/collection/BitSetOps;
            0       6     1 other   Lscala/collection/Set;
    MethodParameters:
      Name                           Flags
      $this                          final synthetic
      other                          final

  public default C intersect(scala.collection.Set<java.lang.Object>);
    descriptor: (Lscala/collection/Set;)Lscala/collection/BitSet;
    flags: (0x0001) ACC_PUBLIC
    Code:
      stack=5, locals=11, args_size=2
         0: aload_1
         1: instanceof    #376                // class scala/collection/BitSet
         4: ifeq          146
         7: aload_1
         8: checkcast     #376                // class scala/collection/BitSet
        11: astore_3
        12: getstatic     #208                // Field scala/runtime/RichInt$.MODULE$:Lscala/runtime/RichInt$;
        15: pop
        16: aload_0
        17: invokeinterface #327,  1          // InterfaceMethod coll:()Ljava/lang/Object;
        22: checkcast     #2                  // class scala/collection/BitSetOps
        25: invokeinterface #189,  1          // InterfaceMethod nwords:()I
        30: istore        5
        32: aload_3
        33: invokeinterface #377,  1          // InterfaceMethod scala/collection/BitSet.nwords:()I
        38: istore        9
        40: getstatic     #346                // Field scala/math/package$.MODULE$:Lscala/math/package$;
        43: pop
        44: iload         5
        46: iload         9
        48: invokestatic  #351                // Method java/lang/Math.min:(II)I
        51: istore        10
        53: iload         10
        55: newarray       long
        57: astore        4
        59: getstatic     #208                // Field scala/runtime/RichInt$.MODULE$:Lscala/runtime/RichInt$;
        62: pop
        63: iconst_0
        64: istore        6
        66: getstatic     #213                // Field scala/collection/immutable/Range$.MODULE$:Lscala/collection/immutable/Range$;
        69: pop
        70: new           #30                 // class scala/collection/immutable/Range$Exclusive
        73: dup
        74: iload         6
        76: iload         10
        78: iconst_1
        79: invokespecial #216                // Method scala/collection/immutable/Range$Exclusive."<init>":(III)V
        82: astore        7
        84: aload         7
        86: invokevirtual #378                // Method scala/collection/immutable/Range.isEmpty:()Z
        89: ifne          131
        92: aload         7
        94: invokevirtual #380                // Method scala/collection/immutable/Range.start:()I
        97: istore        8
        99: aload_0
       100: aload         4
       102: aload_3
       103: iload         8
       105: invokestatic  #409                // InterfaceMethod $anonfun$intersect$1:(Lscala/collection/BitSetOps;[JLscala/collection/BitSet;I)V
       108: iload         8
       110: aload         7
       112: getfield      #387                // Field scala/collection/immutable/Range.scala$collection$immutable$Range$$lastElement:I
       115: if_icmpeq     131
       118: iload         8
       120: aload         7
       122: invokevirtual #390                // Method scala/collection/immutable/Range.step:()I
       125: iadd
       126: istore        8
       128: goto          99
       131: aconst_null
       132: astore        7
       134: aload_0
       135: aload         4
       137: invokeinterface #363,  2          // InterfaceMethod fromBitMaskNoCopy:([J)Lscala/collection/BitSet;
       142: astore_2
       143: goto          154
       146: aload_0
       147: aload_1
       148: invokeinterface #411,  2          // InterfaceMethod scala$collection$BitSetOps$$super$intersect:(Lscala/collection/Set;)Lscala/collection/BitSet;
       153: astore_2
       154: aload_2
       155: areturn
      StackMapTable: number_of_entries = 4
        frame_type = 255 /* full_frame */
          offset_delta = 99
          locals = [ class scala/collection/BitSetOps, class scala/collection/Set, top, class scala/collection/BitSet, class "[J", int, int, class scala/collection/immutable/Range$Exclusive, int, int, int ]
          stack = []
        frame_type = 255 /* full_frame */
          offset_delta = 31
          locals = [ class scala/collection/BitSetOps, class scala/collection/Set, top, class scala/collection/BitSet, class "[J", int, int, class scala/collection/immutable/Range$Exclusive, top, int, int ]
          stack = []
        frame_type = 255 /* full_frame */
          offset_delta = 14
          locals = [ class scala/collection/BitSetOps, class scala/collection/Set ]
          stack = []
        frame_type = 252 /* append */
          offset_delta = 7
          locals = [ class scala/collection/BitSet ]
      LineNumberTable:
        line 256: 0
        line 257: 12
        line 258: 53
        line 259: 59
        line 261: 134
        line 262: 146
        line 255: 154
      LocalVariableTable:
        Start  Length  Slot  Name   Signature
           59      83     4 words   [J
            0     156     0  this   Lscala/collection/BitSetOps;
            0     156     1 other   Lscala/collection/Set;
           99      32     8 foreach$mVc$sp_i   I
           84      47     7 foreach$mVc$sp_this   Lscala/collection/immutable/Range;
           40      13     9 min$extension_that   I
    Signature: #406                         // (Lscala/collection/Set<Ljava/lang/Object;>;)TC;
    MethodParameters:
      Name                           Flags
      other                          final

  public static scala.collection.BitSet diff$(scala.collection.BitSetOps, scala.collection.Set);
    descriptor: (Lscala/collection/BitSetOps;Lscala/collection/Set;)Lscala/collection/BitSet;
    flags: (0x1009) ACC_PUBLIC, ACC_STATIC, ACC_SYNTHETIC
    Code:
      stack=2, locals=2, args_size=2
         0: aload_0
         1: aload_1
         2: invokespecial #418                // InterfaceMethod diff:(Lscala/collection/Set;)Lscala/collection/BitSet;
         5: areturn
      LineNumberTable:
        line 265: 0
      LocalVariableTable:
        Start  Length  Slot  Name   Signature
            0       6     0 $this   Lscala/collection/BitSetOps;
            0       6     1 other   Lscala/collection/Set;
    MethodParameters:
      Name                           Flags
      $this                          final synthetic
      other                          final

  public default C diff(scala.collection.Set<java.lang.Object>);
    descriptor: (Lscala/collection/Set;)Lscala/collection/BitSet;
    flags: (0x0001) ACC_PUBLIC
    Code:
      stack=5, locals=9, args_size=2
         0: aload_1
         1: instanceof    #376                // class scala/collection/BitSet
         4: ifeq          121
         7: aload_1
         8: checkcast     #376                // class scala/collection/BitSet
        11: astore_3
        12: aload_0
        13: invokeinterface #327,  1          // InterfaceMethod coll:()Ljava/lang/Object;
        18: checkcast     #2                  // class scala/collection/BitSetOps
        21: invokeinterface #189,  1          // InterfaceMethod nwords:()I
        26: istore        4
        28: iload         4
        30: newarray       long
        32: astore        5
        34: getstatic     #208                // Field scala/runtime/RichInt$.MODULE$:Lscala/runtime/RichInt$;
        37: pop
        38: iconst_0
        39: istore        6
        41: getstatic     #213                // Field scala/collection/immutable/Range$.MODULE$:Lscala/collection/immutable/Range$;
        44: pop
        45: new           #30                 // class scala/collection/immutable/Range$Exclusive
        48: dup
        49: iload         6
        51: iload         4
        53: iconst_1
        54: invokespecial #216                // Method scala/collection/immutable/Range$Exclusive."<init>":(III)V
        57: astore        7
        59: aload         7
        61: invokevirtual #378                // Method scala/collection/immutable/Range.isEmpty:()Z
        64: ifne          106
        67: aload         7
        69: invokevirtual #380                // Method scala/collection/immutable/Range.start:()I
        72: istore        8
        74: aload_0
        75: aload         5
        77: aload_3
        78: iload         8
        80: invokestatic  #421                // InterfaceMethod $anonfun$diff$1:(Lscala/collection/BitSetOps;[JLscala/collection/BitSet;I)V
        83: iload         8
        85: aload         7
        87: getfield      #387                // Field scala/collection/immutable/Range.scala$collection$immutable$Range$$lastElement:I
        90: if_icmpeq     106
        93: iload         8
        95: aload         7
        97: invokevirtual #390                // Method scala/collection/immutable/Range.step:()I
       100: iadd
       101: istore        8
       103: goto          74
       106: aconst_null
       107: astore        7
       109: aload_0
       110: aload         5
       112: invokeinterface #363,  2          // InterfaceMethod fromBitMaskNoCopy:([J)Lscala/collection/BitSet;
       117: astore_2
       118: goto          129
       121: aload_0
       122: aload_1
       123: invokeinterface #423,  2          // InterfaceMethod scala$collection$BitSetOps$$super$diff:(Lscala/collection/Set;)Lscala/collection/BitSet;
       128: astore_2
       129: aload_2
       130: areturn
      StackMapTable: number_of_entries = 4
        frame_type = 255 /* full_frame */
          offset_delta = 74
          locals = [ class scala/collection/BitSetOps, class scala/collection/Set, top, class scala/collection/BitSet, int, class "[J", int, class scala/collection/immutable/Range$Exclusive, int ]
          stack = []
        frame_type = 250 /* chop */
          offset_delta = 31
        frame_type = 255 /* full_frame */
          offset_delta = 14
          locals = [ class scala/collection/BitSetOps, class scala/collection/Set ]
          stack = []
        frame_type = 252 /* append */
          offset_delta = 7
          locals = [ class scala/collection/BitSet ]
      LineNumberTable:
        line 266: 0
        line 267: 12
        line 268: 28
        line 269: 34
        line 271: 109
        line 272: 121
        line 265: 129
      LocalVariableTable:
        Start  Length  Slot  Name   Signature
           28      89     4   len   I
           34      83     5 words   [J
            0     131     0  this   Lscala/collection/BitSetOps;
            0     131     1 other   Lscala/collection/Set;
           74      32     8 foreach$mVc$sp_i   I
           59      47     7 foreach$mVc$sp_this   Lscala/collection/immutable/Range;
    Signature: #406                         // (Lscala/collection/Set<Ljava/lang/Object;>;)TC;
    MethodParameters:
      Name                           Flags
      other                          final

  public static scala.collection.BitSet xor$(scala.collection.BitSetOps, scala.collection.BitSet);
    descriptor: (Lscala/collection/BitSetOps;Lscala/collection/BitSet;)Lscala/collection/BitSet;
    flags: (0x1009) ACC_PUBLIC, ACC_STATIC, ACC_SYNTHETIC
    Code:
      stack=2, locals=2, args_size=2
         0: aload_0
         1: aload_1
         2: invokespecial #429                // InterfaceMethod xor:(Lscala/collection/BitSet;)Lscala/collection/BitSet;
         5: areturn
      LineNumberTable:
        line 282: 0
      LocalVariableTable:
        Start  Length  Slot  Name   Signature
            0       6     0 $this   Lscala/collection/BitSetOps;
            0       6     1 other   Lscala/collection/BitSet;
    MethodParameters:
      Name                           Flags
      $this                          final synthetic
      other                          final

  public default C xor(scala.collection.BitSet);
    descriptor: (Lscala/collection/BitSet;)Lscala/collection/BitSet;
    flags: (0x0001) ACC_PUBLIC
    Code:
      stack=5, locals=9, args_size=2
         0: getstatic     #208                // Field scala/runtime/RichInt$.MODULE$:Lscala/runtime/RichInt$;
         3: pop
         4: aload_0
         5: invokeinterface #327,  1          // InterfaceMethod coll:()Ljava/lang/Object;
        10: checkcast     #2                  // class scala/collection/BitSetOps
        13: invokeinterface #189,  1          // InterfaceMethod nwords:()I
        18: istore_3
        19: aload_1
        20: invokeinterface #377,  1          // InterfaceMethod scala/collection/BitSet.nwords:()I
        25: istore        7
        27: getstatic     #346                // Field scala/math/package$.MODULE$:Lscala/math/package$;
        30: pop
        31: iload_3
        32: iload         7
        34: invokestatic  #361                // Method java/lang/Math.max:(II)I
        37: istore        8
        39: iload         8
        41: newarray       long
        43: astore_2
        44: getstatic     #208                // Field scala/runtime/RichInt$.MODULE$:Lscala/runtime/RichInt$;
        47: pop
        48: iconst_0
        49: istore        4
        51: getstatic     #213                // Field scala/collection/immutable/Range$.MODULE$:Lscala/collection/immutable/Range$;
        54: pop
        55: new           #30                 // class scala/collection/immutable/Range$Exclusive
        58: dup
        59: iload         4
        61: iload         8
        63: iconst_1
        64: invokespecial #216                // Method scala/collection/immutable/Range$Exclusive."<init>":(III)V
        67: astore        5
        69: aload         5
        71: invokevirtual #378                // Method scala/collection/immutable/Range.isEmpty:()Z
        74: ifne          115
        77: aload         5
        79: invokevirtual #380                // Method scala/collection/immutable/Range.start:()I
        82: istore        6
        84: aload_0
        85: aload_2
        86: aload_1
        87: iload         6
        89: invokestatic  #434                // InterfaceMethod $anonfun$xor$1:(Lscala/collection/BitSetOps;[JLscala/collection/BitSet;I)V
        92: iload         6
        94: aload         5
        96: getfield      #387                // Field scala/collection/immutable/Range.scala$collection$immutable$Range$$lastElement:I
        99: if_icmpeq     115
       102: iload         6
       104: aload         5
       106: invokevirtual #390                // Method scala/collection/immutable/Range.step:()I
       109: iadd
       110: istore        6
       112: goto          84
       115: aconst_null
       116: astore        5
       118: aload_0
       119: invokeinterface #327,  1          // InterfaceMethod coll:()Ljava/lang/Object;
       124: checkcast     #2                  // class scala/collection/BitSetOps
       127: aload_2
       128: invokeinterface #363,  2          // InterfaceMethod fromBitMaskNoCopy:([J)Lscala/collection/BitSet;
       133: areturn
      StackMapTable: number_of_entries = 2
        frame_type = 255 /* full_frame */
          offset_delta = 84
          locals = [ class scala/collection/BitSetOps, class scala/collection/BitSet, class "[J", int, int, class scala/collection/immutable/Range$Exclusive, int, int, int ]
          stack = []
        frame_type = 255 /* full_frame */
          offset_delta = 30
          locals = [ class scala/collection/BitSetOps, class scala/collection/BitSet, class "[J", int, int, class scala/collection/immutable/Range$Exclusive, top, int, int ]
          stack = []
      LineNumberTable:
        line 283: 0
        line 284: 39
        line 285: 44
        line 287: 118
      LocalVariableTable:
        Start  Length  Slot  Name   Signature
           44      89     2 words   [J
            0     134     0  this   Lscala/collection/BitSetOps;
            0     134     1 other   Lscala/collection/BitSet;
           84      31     6 foreach$mVc$sp_i   I
           69      46     5 foreach$mVc$sp_this   Lscala/collection/immutable/Range;
           27      12     7 max$extension_that   I
    Signature: #431                         // (Lscala/collection/BitSet;)TC;
    MethodParameters:
      Name                           Flags
      other                          final

  public static scala.collection.BitSet $up$(scala.collection.BitSetOps, scala.collection.BitSet);
    descriptor: (Lscala/collection/BitSetOps;Lscala/collection/BitSet;)Lscala/collection/BitSet;
    flags: (0x1009) ACC_PUBLIC, ACC_STATIC, ACC_SYNTHETIC
    Code:
      stack=2, locals=2, args_size=2
         0: aload_0
         1: aload_1
         2: invokespecial #438                // InterfaceMethod $up:(Lscala/collection/BitSet;)Lscala/collection/BitSet;
         5: areturn
      LineNumberTable:
        line 290: 0
      LocalVariableTable:
        Start  Length  Slot  Name   Signature
            0       6     0 $this   Lscala/collection/BitSetOps;
            0       6     1 other   Lscala/collection/BitSet;
    MethodParameters:
      Name                           Flags
      $this                          final synthetic
      other                          final

  public default C $up(scala.collection.BitSet);
    descriptor: (Lscala/collection/BitSet;)Lscala/collection/BitSet;
    flags: (0x0001) ACC_PUBLIC
    Code:
      stack=2, locals=2, args_size=2
         0: aload_0
         1: aload_1
         2: invokeinterface #429,  2          // InterfaceMethod xor:(Lscala/collection/BitSet;)Lscala/collection/BitSet;
         7: areturn
      LineNumberTable:
        line 290: 0
      LocalVariableTable:
        Start  Length  Slot  Name   Signature
            0       8     0  this   Lscala/collection/BitSetOps;
            0       8     1 other   Lscala/collection/BitSet;
    Signature: #431                         // (Lscala/collection/BitSet;)TC;
    MethodParameters:
      Name                           Flags
      other                          final

  public static scala.collection.BitSet map$(scala.collection.BitSetOps, scala.Function1);
    descriptor: (Lscala/collection/BitSetOps;Lscala/Function1;)Lscala/collection/BitSet;
    flags: (0x1009) ACC_PUBLIC, ACC_STATIC, ACC_SYNTHETIC
    Code:
      stack=2, locals=2, args_size=2
         0: aload_0
         1: aload_1
         2: invokespecial #444                // InterfaceMethod map:(Lscala/Function1;)Lscala/collection/BitSet;
         5: areturn
      LineNumberTable:
        line 298: 0
      LocalVariableTable:
        Start  Length  Slot  Name   Signature
            0       6     0 $this   Lscala/collection/BitSetOps;
            0       6     1     f   Lscala/Function1;
    MethodParameters:
      Name                           Flags
      $this                          final synthetic
      f                              final

  public default C map(scala.Function1<java.lang.Object, java.lang.Object>);
    descriptor: (Lscala/Function1;)Lscala/collection/BitSet;
    flags: (0x0001) ACC_PUBLIC
    Code:
      stack=5, locals=2, args_size=2
         0: aload_0
         1: new           #27                 // class scala/collection/View$Map
         4: dup
         5: aload_0
         6: aload_1
         7: invokespecial #448                // Method scala/collection/View$Map."<init>":(Lscala/collection/IterableOps;Lscala/Function1;)V
        10: invokeinterface #452,  2          // InterfaceMethod fromSpecific:(Lscala/collection/IterableOnce;)Ljava/lang/Object;
        15: checkcast     #376                // class scala/collection/BitSet
        18: areturn
      LineNumberTable:
        line 298: 0
      LocalVariableTable:
        Start  Length  Slot  Name   Signature
            0      19     0  this   Lscala/collection/BitSetOps;
            0      19     1     f   Lscala/Function1;
    Signature: #445                         // (Lscala/Function1<Ljava/lang/Object;Ljava/lang/Object;>;)TC;
    MethodParameters:
      Name                           Flags
      f                              final

  public static scala.collection.BitSet flatMap$(scala.collection.BitSetOps, scala.Function1);
    descriptor: (Lscala/collection/BitSetOps;Lscala/Function1;)Lscala/collection/BitSet;
    flags: (0x1009) ACC_PUBLIC, ACC_STATIC, ACC_SYNTHETIC
    Code:
      stack=2, locals=2, args_size=2
         0: aload_0
         1: aload_1
         2: invokespecial #456                // InterfaceMethod flatMap:(Lscala/Function1;)Lscala/collection/BitSet;
         5: areturn
      LineNumberTable:
        line 300: 0
      LocalVariableTable:
        Start  Length  Slot  Name   Signature
            0       6     0 $this   Lscala/collection/BitSetOps;
            0       6     1     f   Lscala/Function1;
    MethodParameters:
      Name                           Flags
      $this                          final synthetic
      f                              final

  public default C flatMap(scala.Function1<java.lang.Object, scala.collection.IterableOnce<java.lang.Object>>);
    descriptor: (Lscala/Function1;)Lscala/collection/BitSet;
    flags: (0x0001) ACC_PUBLIC
    Code:
      stack=5, locals=2, args_size=2
         0: aload_0
         1: new           #22                 // class scala/collection/View$FlatMap
         4: dup
         5: aload_0
         6: aload_1
         7: invokespecial #458                // Method scala/collection/View$FlatMap."<init>":(Lscala/collection/IterableOps;Lscala/Function1;)V
        10: invokeinterface #452,  2          // InterfaceMethod fromSpecific:(Lscala/collection/IterableOnce;)Ljava/lang/Object;
        15: checkcast     #376                // class scala/collection/BitSet
        18: areturn
      LineNumberTable:
        line 300: 0
      LocalVariableTable:
        Start  Length  Slot  Name   Signature
            0      19     0  this   Lscala/collection/BitSetOps;
            0      19     1     f   Lscala/Function1;
    Signature: #457                         // (Lscala/Function1<Ljava/lang/Object;Lscala/collection/IterableOnce<Ljava/lang/Object;>;>;)TC;
    MethodParameters:
      Name                           Flags
      f                              final

  public static scala.collection.BitSet collect$(scala.collection.BitSetOps, scala.PartialFunction);
    descriptor: (Lscala/collection/BitSetOps;Lscala/PartialFunction;)Lscala/collection/BitSet;
    flags: (0x1009) ACC_PUBLIC, ACC_STATIC, ACC_SYNTHETIC
    Code:
      stack=2, locals=2, args_size=2
         0: aload_0
         1: aload_1
         2: invokespecial #465                // InterfaceMethod collect:(Lscala/PartialFunction;)Lscala/collection/BitSet;
         5: areturn
      LineNumberTable:
        line 302: 0
      LocalVariableTable:
        Start  Length  Slot  Name   Signature
            0       6     0 $this   Lscala/collection/BitSetOps;
            0       6     1    pf   Lscala/PartialFunction;
    MethodParameters:
      Name                           Flags
      $this                          final synthetic
      pf                             final

  public default C collect(scala.PartialFunction<java.lang.Object, java.lang.Object>);
    descriptor: (Lscala/PartialFunction;)Lscala/collection/BitSet;
    flags: (0x0001) ACC_PUBLIC
    Code:
      stack=4, locals=2, args_size=2
         0: aload_0
         1: aload_0
         2: aload_1
         3: getstatic     #70                 // Field scala/math/Ordering$Int$.MODULE$:Lscala/math/Ordering$Int$;
         6: invokestatic  #470                // InterfaceMethod scala/collection/SortedSetOps.collect$:(Lscala/collection/SortedSetOps;Lscala/PartialFunction;Lscala/math/Ordering;)Lscala/collection/SortedSet;
         9: invokeinterface #452,  2          // InterfaceMethod fromSpecific:(Lscala/collection/IterableOnce;)Ljava/lang/Object;
        14: checkcast     #376                // class scala/collection/BitSet
        17: areturn
      LineNumberTable:
        line 302: 0
      LocalVariableTable:
        Start  Length  Slot  Name   Signature
            0      18     0  this   Lscala/collection/BitSetOps;
            0      18     1    pf   Lscala/PartialFunction;
    Signature: #467                         // (Lscala/PartialFunction<Ljava/lang/Object;Ljava/lang/Object;>;)TC;
    MethodParameters:
      Name                           Flags
      pf                             final

  public static scala.Tuple2 partition$(scala.collection.BitSetOps, scala.Function1);
    descriptor: (Lscala/collection/BitSetOps;Lscala/Function1;)Lscala/Tuple2;
    flags: (0x1009) ACC_PUBLIC, ACC_STATIC, ACC_SYNTHETIC
    Code:
      stack=2, locals=2, args_size=2
         0: aload_0
         1: aload_1
         2: invokespecial #477                // InterfaceMethod partition:(Lscala/Function1;)Lscala/Tuple2;
         5: areturn
      LineNumberTable:
        line 304: 0
      LocalVariableTable:
        Start  Length  Slot  Name   Signature
            0       6     0 $this   Lscala/collection/BitSetOps;
            0       6     1     p   Lscala/Function1;
    MethodParameters:
      Name                           Flags
      $this                          final synthetic
      p                              final

  public default scala.Tuple2<C, C> partition(scala.Function1<java.lang.Object, java.lang.Object>);
    descriptor: (Lscala/Function1;)Lscala/Tuple2;
    flags: (0x0001) ACC_PUBLIC
    Code:
      stack=5, locals=3, args_size=2
         0: aload_0
         1: aload_1
         2: invokeinterface #482,  2          // InterfaceMethod filter:(Lscala/Function1;)Ljava/lang/Object;
         7: checkcast     #376                // class scala/collection/BitSet
        10: astore_2
        11: new           #484                // class scala/Tuple2
        14: dup
        15: aload_2
        16: aload_0
        17: aload_2
        18: invokeinterface #489,  2          // InterfaceMethod scala/collection/SetOps.diff:(Lscala/collection/Set;)Lscala/collection/SetOps;
        23: invokespecial #492                // Method scala/Tuple2."<init>":(Ljava/lang/Object;Ljava/lang/Object;)V
        26: areturn
      LineNumberTable:
        line 305: 0
        line 306: 11
      LocalVariableTable:
        Start  Length  Slot  Name   Signature
           11      15     2  left   Lscala/collection/BitSet;
            0      27     0  this   Lscala/collection/BitSetOps;
            0      27     1     p   Lscala/Function1;
    Signature: #478                         // (Lscala/Function1<Ljava/lang/Object;Ljava/lang/Object;>;)Lscala/Tuple2<TC;TC;>;
    MethodParameters:
      Name                           Flags
      p                              final

  public static java.lang.String $anonfun$stepper$1(scala.collection.StepperShape);
    descriptor: (Lscala/collection/StepperShape;)Ljava/lang/String;
    flags: (0x1009) ACC_PUBLIC, ACC_STATIC, ACC_SYNTHETIC
    Code:
      stack=3, locals=1, args_size=1
         0: new           #146                // class java/lang/StringBuilder
         3: dup
         4: ldc_w         #495                // int 25
         7: invokespecial #150                // Method java/lang/StringBuilder."<init>":(I)V
        10: ldc_w         #497                // String unexpected StepperShape:
        13: invokevirtual #156                // Method java/lang/StringBuilder.append:(Ljava/lang/String;)Ljava/lang/StringBuilder;
        16: aload_0
        17: invokevirtual #163                // Method java/lang/StringBuilder.append:(Ljava/lang/Object;)Ljava/lang/StringBuilder;
        20: invokevirtual #167                // Method java/lang/StringBuilder.toString:()Ljava/lang/String;
        23: areturn
      LineNumberTable:
        line 137: 0
      LocalVariableTable:
        Start  Length  Slot  Name   Signature
            0      24     0 shape$1   Lscala/collection/StepperShape;
    MethodParameters:
      Name                           Flags
      shape$1                        final

  public static boolean $anonfun$isEmpty$1(scala.collection.BitSetOps, int);
    descriptor: (Lscala/collection/BitSetOps;I)Z
    flags: (0x1009) ACC_PUBLIC, ACC_STATIC, ACC_SYNTHETIC
    Code:
      stack=4, locals=2, args_size=2
         0: aload_0
         1: iload_1
         2: invokeinterface #90,  2           // InterfaceMethod word:(I)J
         7: lconst_0
         8: lcmp
         9: ifne          14
        12: iconst_1
        13: ireturn
        14: iconst_0
        15: ireturn
      StackMapTable: number_of_entries = 1
        frame_type = 14 /* same */
      LineNumberTable:
        line 153: 0
      LocalVariableTable:
        Start  Length  Slot  Name   Signature
            0      16     0 $this   Lscala/collection/BitSetOps;
            0      16     1     i   I
    MethodParameters:
      Name                           Flags
      $this                          final synthetic
      i                              final

  public static void $anonfun$concat$1(scala.collection.BitSetOps, long[], scala.collection.BitSet, int);
    descriptor: (Lscala/collection/BitSetOps;[JLscala/collection/BitSet;I)V
    flags: (0x1009) ACC_PUBLIC, ACC_STATIC, ACC_SYNTHETIC
    Code:
      stack=6, locals=4, args_size=4
         0: aload_1
         1: iload_3
         2: aload_0
         3: iload_3
         4: invokeinterface #90,  2           // InterfaceMethod word:(I)J
         9: aload_2
        10: iload_3
        11: invokeinterface #500,  2          // InterfaceMethod scala/collection/BitSet.word:(I)J
        16: lor
        17: lastore
        18: return
      LineNumberTable:
        line 250: 0
      LocalVariableTable:
        Start  Length  Slot  Name   Signature
            0      19     0 $this   Lscala/collection/BitSetOps;
            0      19     1 words$1   [J
            0      19     2  x2$1   Lscala/collection/BitSet;
            0      19     3   idx   I
    MethodParameters:
      Name                           Flags
      $this                          final synthetic
      words$1                        final
      x2$1                           final
      idx                            final

  public static void $anonfun$intersect$1(scala.collection.BitSetOps, long[], scala.collection.BitSet, int);
    descriptor: (Lscala/collection/BitSetOps;[JLscala/collection/BitSet;I)V
    flags: (0x1009) ACC_PUBLIC, ACC_STATIC, ACC_SYNTHETIC
    Code:
      stack=6, locals=4, args_size=4
         0: aload_1
         1: iload_3
         2: aload_0
         3: iload_3
         4: invokeinterface #90,  2           // InterfaceMethod word:(I)J
         9: aload_2
        10: iload_3
        11: invokeinterface #500,  2          // InterfaceMethod scala/collection/BitSet.word:(I)J
        16: land
        17: lastore
        18: return
      LineNumberTable:
        line 260: 0
      LocalVariableTable:
        Start  Length  Slot  Name   Signature
            0      19     0 $this   Lscala/collection/BitSetOps;
            0      19     1 words$2   [J
            0      19     2  x2$2   Lscala/collection/BitSet;
            0      19     3   idx   I
    MethodParameters:
      Name                           Flags
      $this                          final synthetic
      words$2                        final
      x2$2                           final
      idx                            final

  public static void $anonfun$diff$1(scala.collection.BitSetOps, long[], scala.collection.BitSet, int);
    descriptor: (Lscala/collection/BitSetOps;[JLscala/collection/BitSet;I)V
    flags: (0x1009) ACC_PUBLIC, ACC_STATIC, ACC_SYNTHETIC
    Code:
      stack=8, locals=4, args_size=4
         0: aload_1
         1: iload_3
         2: aload_0
         3: iload_3
         4: invokeinterface #90,  2           // InterfaceMethod word:(I)J
         9: aload_2
        10: iload_3
        11: invokeinterface #500,  2          // InterfaceMethod scala/collection/BitSet.word:(I)J
        16: ldc2_w        #358                // long -1l
        19: lxor
        20: land
        21: lastore
        22: return
      LineNumberTable:
        line 270: 0
      LocalVariableTable:
        Start  Length  Slot  Name   Signature
            0      23     0 $this   Lscala/collection/BitSetOps;
            0      23     1 words$3   [J
            0      23     2  x2$3   Lscala/collection/BitSet;
            0      23     3   idx   I
    MethodParameters:
      Name                           Flags
      $this                          final synthetic
      words$3                        final
      x2$3                           final
      idx                            final

  public static void $anonfun$xor$1(scala.collection.BitSetOps, long[], scala.collection.BitSet, int);
    descriptor: (Lscala/collection/BitSetOps;[JLscala/collection/BitSet;I)V
    flags: (0x1009) ACC_PUBLIC, ACC_STATIC, ACC_SYNTHETIC
    Code:
      stack=6, locals=4, args_size=4
         0: aload_1
         1: iload_3
         2: aload_0
         3: invokeinterface #327,  1          // InterfaceMethod coll:()Ljava/lang/Object;
         8: checkcast     #2                  // class scala/collection/BitSetOps
        11: iload_3
        12: invokeinterface #90,  2           // InterfaceMethod word:(I)J
        17: aload_2
        18: iload_3
        19: invokeinterface #500,  2          // InterfaceMethod scala/collection/BitSet.word:(I)J
        24: lxor
        25: lastore
        26: return
      LineNumberTable:
        line 286: 0
      LocalVariableTable:
        Start  Length  Slot  Name   Signature
            0      27     0 $this   Lscala/collection/BitSetOps;
            0      27     1 words$4   [J
            0      27     2 other$1   Lscala/collection/BitSet;
            0      27     3   idx   I
    MethodParameters:
      Name                           Flags
      $this                          final synthetic
      words$4                        final
      other$1                        final
      idx                            final

  public static void $init$(scala.collection.BitSetOps);
    descriptor: (Lscala/collection/BitSetOps;)V
    flags: (0x0009) ACC_PUBLIC, ACC_STATIC
    Code:
      stack=0, locals=1, args_size=1
         0: return
      LineNumberTable:
        line 86: 0
      LocalVariableTable:
        Start  Length  Slot  Name   Signature
            0       1     0 $this   Lscala/collection/BitSetOps;
    MethodParameters:
      Name                           Flags
      $this                          final synthetic

  private static java.lang.Object $deserializeLambda$(java.lang.invoke.SerializedLambda);
    descriptor: (Ljava/lang/invoke/SerializedLambda;)Ljava/lang/Object;
    flags: (0x100a) ACC_PRIVATE, ACC_STATIC, ACC_SYNTHETIC
    Code:
      stack=1, locals=1, args_size=1
         0: aload_0
         1: invokedynamic #520,  0            // InvokeDynamic #1:lambdaDeserialize:(Ljava/lang/invoke/SerializedLambda;)Ljava/lang/Object;
         6: areturn
}
InnerClasses:
  public static final #16= #13 of #15;    // Lookup=class java/lang/invoke/MethodHandles$Lookup of class java/lang/invoke/MethodHandles
  public final #18;                       // class scala/collection/AnyStepper$$anon$4
  public final #20;                       // class scala/collection/BitSetOps$$anon$1
  public static #25= #22 of #24;          // FlatMap=class scala/collection/View$FlatMap of class scala/collection/View
  public static #28= #27 of #24;          // Map=class scala/collection/View$Map of class scala/collection/View
  public static final #33= #30 of #32;    // Exclusive=class scala/collection/immutable/Range$Exclusive of class scala/collection/immutable/Range
  public static #38= #35 of #37;          // CachedReverse=class scala/math/Ordering$CachedReverse of class scala/math/Ordering
  public static #41= #40 of #37;          // Int$=class scala/math/Ordering$Int$ of class scala/math/Ordering
Signature: #3                           // <C::Lscala/collection/BitSet;:Lscala/collection/BitSetOps<TC;>;>Ljava/lang/Object;Lscala/collection/SortedSetOps<Ljava/lang/Object;Lscala/collection/SortedSet;TC;>;
SourceFile: "BitSet.scala"
RuntimeVisibleAnnotations:
  0: #9(#10=s#11)
    scala.reflect.ScalaSignature(
      bytes="\u0006\u0005\t\u0015fa\u0002\u00180!\u0003\r\t\u0001\u000e\u0005\u0006\'\u0002!\t\u0001\u0016\u0005\u00061\u00021\t!\u0017\u0005\u0006;\u00021\tA\u0018\u0005\u0006E\u0002!)a\u0019\u0005\u0007W\u00021\tb\f7\t\r5\u0004a\u0011C\u0018o\u0011\u0019!\bA\"\u00050k\")1\u0010\u0001C\u0001y\"9\u0011Q\u0001\u0001\u0005\u0002\u0005\u001d\u0001bBA\b\u0001\u0011\u0005\u0011\u0011\u0003\u0005\b\u0003/\u0001A\u0011IA\r\u0011\u0019\t)\u0007\u0001C!Y\"9\u0011q\r\u0001\u0005B\u0005%\u0004bBA6\u0001\u0001&I\u0001\u001c\u0005\b\u0003k\u0002\u0001\u0015\"\u0003m\u0011\u001d\tI\b\u0001C!\u0003wBq!!$\u0001\t\u0003\ny\tC\u0004\u0002\u001c\u0002!\t%!(\t\u000f\u0005E\u0006\u0001\"\u0001\u00024\"9\u0011Q\u0017\u0001\u0005\u0002\u0005]\u0006bBAd\u0001\u0011\u0005\u0013\u0011\u001a\u0005\b\u0003+\u0004A\u0011IAl\u0011!\tY\u000e\u0001I\u0005\u0002\u0005u\u0007bBAq\u0001\u0011\u0005\u00111\u001d\u0005\b\u0003O\u0004AQAAu\u0011\u001d\ty\u000f\u0001C\u0001\u0003cDq!a>\u0001\t\u0003\tI\u0010C\u0004\u0002\u0000\u0002!\tA!\u0001\t\u000f\t5\u0001\u0001\"\u0011\u0003\u0010!q!Q\u0004\u0001\u0011\u0002\u0007\u0005\t\u0011\"\u0003\u0003 \t5\u0002B\u0004B\u0018\u0001A\u0005\u0019\u0011!A\u0005\n\tE\"Q\b\u0005\u000f\u0005\u007f\u0001\u0001\u0013aA\u0001\u0002\u0013%!\u0011\tB$\u00119\u0011i\u0005\u0001I\u0001\u0004\u0003\u0005I\u0011\u0002B(\u0005\'BaB!\u0016\u0001!\u0003\r\t\u0011!C\u0005\u0005/\u0012YfB\u0004\u0003^=B\tAa\u0018\u0007\r9z\u0003\u0012\u0001B1\u0011\u001d\u0011\u0019\u0007\nC\u0001\u0005KB!Ba\u001a%\u0005\u0004%)a\fB5\u0011!\u0011y\u0007\nQ\u0001\u000e\t-\u0004B\u0003B9I\t\u0007IQA\u0018\u0003t!A!\u0011\u0010\u0013!\u0002\u001b\u0011)\b\u0003\u0006\u0003|\u0011\u0012\r\u0011\"\u00020\u0005{B\u0001Ba!%A\u00035!q\u0010\u0005\t\u0005\u000b#C\u0011A\u0018\u0003\b\"A!\u0011\u0013\u0013\u0005\u0002=\u0012\u0019JA\u0005CSR\u001cV\r^(qg*\u0011\u0001\'M\u0001\u000bG>dG.Z2uS>t\'\"\u0001\u001a\u0002\u000bM\u001c\u0017\r\\1\u0004\u0001U\u0011QGR\n\u0004\u0001YR\u0004CA\u001c9\u001b\u0005\t\u0014BA\u001d2\u0005\u0019\te.\u001f*fMB)1\b\u0010 B\t6\tq&\u0003\u0002>_\ta1k\u001c:uK\u0012\u001cV\r^(qgB\u0011qgP\u0005\u0003\u0001F\u00121!\u00138u!\tY$)\u0003\u0002D_\tI1k\u001c:uK\u0012\u001cV\r\u001e\t\u0003\u000b\u001ac\u0001\u0001\u0002\u0004H\u0001\u0011\u0015\r\u0001\u0013\u0002\u0002\u0007F\u0011\u0011\n\u0014\t\u0003o)K!aS\u0019\u0003\u000f9{G\u000f[5oOJ\u0019Qj\u0014*\u0007\t9\u0003\u0001\u0001\u0014\u0002\ryI,g-\u001b8f[\u0016tGO\u0010\t\u0003wAK!!U\u0018\u0003\r\tKGoU3u!\rY\u0004\u0001R\u0001\u0007I%t\u0017\u000e\u001e\u0013\u0015\u0003U\u0003\"a\u000e,\n\u0005]\u000b$\u0001B+oSR\fQBY5u\'\u0016$h)Y2u_JLX#\u0001.\u0011\tmZf\bR\u0005\u00039>\u0012qc\u00159fG&4\u0017nY%uKJ\f\'\r\\3GC\u000e$xN]=\u0002\u0011Ut7o\u001c:uK\u0012,\u0012a\u0018\t\u0004w\u0001t\u0014BA10\u0005\r\u0019V\r^\u0001\t_J$WM]5oOV\tA\rE\u0002fQzr!a\u000e4\n\u0005\u001d\f\u0014a\u00029bG.\fw-Z\u0005\u0003S*\u0014\u0001b\u0014:eKJLgn\u001a\u0006\u0003OF\naA\\<pe\u0012\u001cX#\u0001 \u0002\t]|\'\u000f\u001a\u000b\u0003_J\u0004\"a\u000e9\n\u0005E\f$\u0001\u0002\'p]\u001eDQa\u001d\u0004A\u0002y\n1!\u001b3y\u0003E1\'o\\7CSRl\u0015m]6O_\u000e{\u0007/\u001f\u000b\u0003\tZDQa^\u0004A\u0002a\fQ!\u001a7f[N\u00042aN=p\u0013\tQ\u0018GA\u0003BeJ\f\u00170\u0001\u0005d_:$\u0018-\u001b8t)\ri\u0018\u0011\u0001\t\u0003oyL!a`\u0019\u0003\u000f\t{w\u000e\\3b]\"1\u00111\u0001\u0005A\u0002y\nA!\u001a7f[\u0006A\u0011\u000e^3sCR|\'/\u0006\u0002\u0002\nA!1(a\u0003?\u0013\r\tia\f\u0002\t\u0013R,\'/\u0019;pe\u0006a\u0011\u000e^3sCR|\'O\u0012:p[R!\u0011\u0011BA\n\u0011\u0019\t)B\u0003a\u0001}\u0005)1\u000f^1si\u000691\u000f^3qa\u0016\u0014X\u0003BA\u000e\u0003G!B!!\b\u0002\\I1\u0011qDA\u0011\u0003\u007f1QA\u0014\u0001\u0001\u0003;\u00012!RA\u0012\t\u001d\t)c\u0003b\u0001\u0003O\u0011\u0011aU\t\u0004\u0013\u0006%\u0002\u0007BA\u0016\u0003g\u0001RaOA\u0017\u0003cI1!a\f0\u0005\u001d\u0019F/\u001a9qKJ\u00042!RA\u001a\t1\t)$a\t\u0002\u0002\u0003\u0005)\u0011AA\u001c\u0005\ryF%M\t\u0004\u0013\u0006e\u0002cA\u001c\u0002<%\u0019\u0011QH\u0019\u0003\u0007\u0005s\u0017\u0010\u0005\u0003\u0002B\u0005Uc\u0002BA\"\u0003#rA!!\u0012\u0002P9!\u0011qIA\'\u001b\t\tIEC\u0002\u0002LM\na\u0001\u0010:p_Rt\u0014\"\u0001\u001a\n\u0005A\n\u0014bAA*_\u000591\u000b^3qa\u0016\u0014\u0018\u0002BA,\u00033\u0012a\"\u00124gS\u000eLWM\u001c;Ta2LGOC\u0002\u0002T=Bq!!\u0018\f\u0001\b\ty&A\u0003tQ\u0006\u0004X\r\u0005\u0004<\u0003Cr\u0014\u0011E\u0005\u0004\u0003Gz#\u0001D*uKB\u0004XM]*iCB,\u0017\u0001B:ju\u0016\fq![:F[B$\u00180F\u0001~\u0003-\u0019X.\u00197mKN$\u0018J\u001c;)\u00079\ty\u0007E\u00028\u0003cJ1!a\u001d2\u0005\u0019Ig\u000e\\5oK\u0006QA.\u0019:hKN$\u0018J\u001c;)\u0007=\ty\'A\u0002nCb,B!! \u0002\bR\u0019a(a \t\u000f\u0005\u0005\u0005\u0003q\u0001\u0002\u0004\u0006\u0019qN\u001d3\u0011\t\u0015D\u0017Q\u0011\t\u0004\u000b\u0006\u001dEaBAE!\t\u0007\u00111\u0012\u0002\u0002\u0005F\u0019a(!\u000f\u0002\u00075Lg.\u0006\u0003\u0002\u0012\u0006eEc\u0001 \u0002\u0014\"9\u0011\u0011Q\tA\u0004\u0005U\u0005\u0003B3i\u0003/\u00032!RAM\t\u001d\tI)\u0005b\u0001\u0003\u0017\u000bqAZ8sK\u0006\u001c\u0007.\u0006\u0003\u0002 \u00065FcA+\u0002\"\"9\u00111\u0015\nA\u0002\u0005\u0015\u0016!\u00014\u0011\r]\n9KPAV\u0013\r\tI+\r\u0002\n\rVt7\r^5p]F\u00022!RAW\t\u001d\tyK\u0005b\u0001\u0003o\u0011\u0011!V\u0001\ni>\u0014\u0015\u000e^\'bg.,\u0012\u0001_\u0001\ne\u0006tw-Z%na2$R\u0001RA]\u0003\u0007Dq!a/\u0015\u0001\u0004\ti,\u0001\u0003ge>l\u0007\u0003B\u001c\u0002@zJ1!!12\u0005\u0019y\u0005\u000f^5p]\"9\u0011Q\u0019\u000bA\u0002\u0005u\u0016!B;oi&d\u0017AB2p]\u000e\fG\u000fF\u0002E\u0003\u0017Dq!!4\u0016\u0001\u0004\ty-A\u0003pi\",\'\u000f\u0005\u0003<\u0003#t\u0014bAAj_\ta\u0011\n^3sC\ndWm\u00148dK\u0006I\u0011N\u001c;feN,7\r\u001e\u000b\u0004\t\u0006e\u0007BBAg-\u0001\u0007q,\u0001\u0003eS\u001a4Gc\u0001#\u0002`\"1\u0011QZ\fA\u0002}\u000b1\u0001_8s)\r!\u0015Q\u001d\u0005\u0007\u0003\u001bD\u0002\u0019A(\u0002\u0007\u0011*\b\u000fF\u0002E\u0003WDa!!4\u001a\u0001\u0004y\u0005fA\r\u0002p\u0005\u0019Q.\u00199\u0015\u0007\u0011\u000b\u0019\u0010C\u0004\u0002$j\u0001\r!!>\u0011\u000b]\n9K\u0010 \u0002\u000f\u0019d\u0017\r^\'baR\u0019A)a?\t\u000f\u0005\r6\u00041\u0001\u0002~B1q\'a*?\u0003\u001f\fqaY8mY\u0016\u001cG\u000fF\u0002E\u0005\u0007AqA!\u0002\u001d\u0001\u0004\u00119!\u0001\u0002qMB)qG!\u0003?}%\u0019!1B\u0019\u0003\u001fA\u000b\'\u000f^5bY\u001a+hn\u0019;j_:\f\u0011\u0002]1si&$\u0018n\u001c8\u0015\t\tE!q\u0003\t\u0006o\tMA\tR\u0005\u0004\u0005+\t$A\u0002+va2,\'\u0007C\u0004\u0003\u001au\u0001\rAa\u0007\u0002\u0003A\u0004RaNAT}u\f\u0011b];qKJ$S.\u0019=\u0016\t\t\u0005\"1\u0006\u000b\u0004}\t\r\u0002bBAA=\u0001\u000f!Q\u0005\t\u0006\u0005OA\'\u0011\u0006\b\u0004\u0003\u000b2\u0007cA#\u0003,\u00119\u0011\u0011\u0012\u0010C\u0002\u0005-\u0015bAA=y\u0005I1/\u001e9fe\u0012j\u0017N\\\u000b\u0005\u0005g\u0011Y\u0004F\u0002?\u0005kAq!!! \u0001\b\u00119\u0004E\u0003\u0003(!\u0014I\u0004E\u0002F\u0005w!q!!# \u0005\u0004\tY)C\u0002\u0002\u000er\nAb];qKJ$3m\u001c8dCR$2\u0001\u0012B\"\u0011\u001d\u0011)\u0005\ta\u0001\u0003\u001f\fA\u0001\u001e5bi&!\u0011q\u0019B%\u0013\r\u0011Ye\f\u0002\u0007\'\u0016$x\n]:\u0002\u001fM,\b/\u001a:%S:$XM]:fGR$2\u0001\u0012B)\u0011\u0019\u0011)%\ta\u0001?&!\u0011Q\u001bB%\u0003)\u0019X\u000f]3sI\u0011LgM\u001a\u000b\u0004\t\ne\u0003B\u0002B#E\u0001\u0007q,\u0003\u0003\u0002\\\n%\u0013!\u0003\"jiN+Go\u00149t!\tYDe\u0005\u0002%m\u00051A(\u001b8jiz\"\"Aa\u0018\u0002\u000b1{wm\u0016\'\u0016\u0005\t-tB\u0001B7;\u00051\u0011A\u0002\'pO^c\u0005%\u0001\u0006X_J$G*\u001a8hi\",\"A!\u001e\u0010\u0005\t]T$\u0001!\u0002\u0017]{\'\u000f\u001a\'f]\u001e$\b\u000eI\u0001\b\u001b\u0006D8+\u001b>f+\t\u0011yh\u0004\u0002\u0003\u0002v!!\u0001\u0001\u0001\u0001\u0003!i\u0015\r_*ju\u0016\u0004\u0013aC;qI\u0006$X-\u0011:sCf$r\u0001\u001fBE\u0005\u0017\u0013i\tC\u0003xY\u0001\u0007\u0001\u0010C\u0003tY\u0001\u0007a\b\u0003\u0004\u0003\u00102\u0002\ra\\\u0001\u0002o\u0006!2m\\7qkR,wk\u001c:e\r>\u0014h)\u001b7uKJ$\u0012b\u001cBK\u00053\u0013iJ!)\t\u000f\t]U\u00061\u0001\u0003\u001c\u0005!\u0001O]3e\u0011\u0019\u0011Y*\fa\u0001{\u0006I\u0011n\u001d$mSB\u0004X\r\u001a\u0005\u0007\u0005?k\u0003\u0019A8\u0002\u000f=dGmV8sI\"1!1U\u0017A\u0002y\n\u0011b^8sI&sG-\u001a="
    )
BootstrapMethods:
  0: #229 REF_invokeStatic java/lang/invoke/LambdaMetafactory.altMetafactory:(Ljava/lang/invoke/MethodHandles$Lookup;Ljava/lang/String;Ljava/lang/invoke/MethodType;[Ljava/lang/Object;)Ljava/lang/invoke/CallSite;
    Method arguments:
      #217 (I)Z
      #221 REF_invokeStatic scala/collection/BitSetOps.$anonfun$isEmpty$1:(Lscala/collection/BitSetOps;I)Z
      #217 (I)Z
      #222 1
  1: #517 REF_invokeStatic scala/runtime/LambdaDeserialize.bootstrap:(Ljava/lang/invoke/MethodHandles$Lookup;Ljava/lang/String;Ljava/lang/invoke/MethodType;[Ljava/lang/invoke/MethodHandle;)Ljava/lang/invoke/CallSite;
    Method arguments:
      #221 REF_invokeStatic scala/collection/BitSetOps.$anonfun$isEmpty$1:(Lscala/collection/BitSetOps;I)Z
  ScalaInlineInfo: length = 0x135 (unknown attribute)
   01 00 00 3D 01 7D 01 7E 01 01 A3 01 7E 01 01 97
   01 7E 01 00 DA 00 52 01 00 9D 00 9E 01 01 B0 01
   7E 01 01 FB 01 FC 01 01 B4 01 AB 05 01 B3 01 A9
   05 00 34 00 35 00 01 CE 01 CF 00 01 CB 01 CC 01
   01 72 00 2F 00 01 6F 01 70 01 00 54 00 55 00 00
   51 00 52 01 01 A0 00 32 00 01 9F 01 91 01 01 C6
   01 BA 00 01 C5 01 B8 01 01 1E 01 1F 00 01 1B 01
   1C 01 00 4D 00 4E 00 01 92 00 32 00 01 90 01 91
   01 00 C8 00 C9 00 00 C6 00 C7 01 00 5D 00 5E 00
   00 5B 00 5C 01 00 62 00 63 00 00 66 00 67 01 00
   FD 00 49 05 01 B9 01 BA 00 01 B7 01 B8 01 01 05
   00 2B 00 01 03 01 04 01 01 16 00 2B 00 01 15 01
   04 01 00 48 00 49 00 00 3D 00 3E 01 00 3A 00 3B
   01 01 DA 01 DB 00 01 D7 01 D8 01 01 3E 01 3F 00
   01 3B 01 3C 01 00 2E 00 2F 01 00 33 00 32 01 00
   31 00 32 01 00 2A 00 2B 01 00 2D 00 2B 01 00 B9
   00 49 00 00 B7 00 B8 01 00 EF 00 49 05 00 71 00
   72 00 00 6E 00 6F 01 01 34 01 35 00 01 32 01 33
   01 00 37 00 38 00 00 4A 00 4B 00 01 AA 01 AB 00
   01 A8 01 A9 01
  ScalaSig: length = 0x3 (unknown attribute)
   05 02 00
