Classfile /Users/mw/Projects/slang-braindump/.jar/jar8/assemble/slang-braindump/assemble/content/scala/collection/BitSet$SerializationProxy.class
  Last modified May 29, 2022; size 1901 bytes
  SHA-256 checksum 194bc82af21c514edee35ea375d5cbe3b30fa4597ce7e14022b2ac55827c24fd
  Compiled from "BitSet.scala"
public abstract class scala.collection.BitSet$SerializationProxy implements java.io.Serializable
  minor version: 0
  major version: 52
  flags: (0x0421) ACC_PUBLIC, ACC_SUPER, ACC_ABSTRACT
  this_class: #2                          // scala/collection/BitSet$SerializationProxy
  super_class: #4                         // java/lang/Object
  interfaces: 1, fields: 3, methods: 7, attributes: 4
Constant pool:
   #1 = Utf8               scala/collection/BitSet$SerializationProxy
   #2 = Class              #1             // scala/collection/BitSet$SerializationProxy
   #3 = Utf8               java/lang/Object
   #4 = Class              #3             // java/lang/Object
   #5 = Utf8               java/io/Serializable
   #6 = Class              #5             // java/io/Serializable
   #7 = Utf8               BitSet.scala
   #8 = Utf8               scala/collection/BitSet
   #9 = Class              #8             // scala/collection/BitSet
  #10 = Utf8               SerializationProxy
  #11 = Utf8               serialVersionUID
  #12 = Utf8               J
  #13 = Long               3l
  #15 = Utf8               coll
  #16 = Utf8               Lscala/collection/BitSet;
  #17 = Utf8               elems
  #18 = Utf8               [J
  #19 = Utf8               ()Lscala/collection/BitSet;
  #20 = NameAndType        #15:#16        // coll:Lscala/collection/BitSet;
  #21 = Fieldref           #2.#20         // scala/collection/BitSet$SerializationProxy.coll:Lscala/collection/BitSet;
  #22 = Utf8               this
  #23 = Utf8               Lscala/collection/BitSet$SerializationProxy;
  #24 = Utf8               ()[J
  #25 = NameAndType        #17:#18        // elems:[J
  #26 = Fieldref           #2.#25         // scala/collection/BitSet$SerializationProxy.elems:[J
  #27 = Utf8               elems_$eq
  #28 = Utf8               ([J)V
  #29 = Utf8               x$1
  #30 = Utf8               writeObject
  #31 = Utf8               (Ljava/io/ObjectOutputStream;)V
  #32 = Utf8               out
  #33 = Utf8               java/io/ObjectOutputStream
  #34 = Class              #33            // java/io/ObjectOutputStream
  #35 = Utf8               defaultWriteObject
  #36 = Utf8               ()V
  #37 = NameAndType        #35:#36        // defaultWriteObject:()V
  #38 = Methodref          #34.#37        // java/io/ObjectOutputStream.defaultWriteObject:()V
  #39 = NameAndType        #15:#19        // coll:()Lscala/collection/BitSet;
  #40 = Methodref          #2.#39         // scala/collection/BitSet$SerializationProxy.coll:()Lscala/collection/BitSet;
  #41 = Utf8               nwords
  #42 = Utf8               ()I
  #43 = NameAndType        #41:#42        // nwords:()I
  #44 = InterfaceMethodref #9.#43         // scala/collection/BitSet.nwords:()I
  #45 = Utf8               writeInt
  #46 = Utf8               (I)V
  #47 = NameAndType        #45:#46        // writeInt:(I)V
  #48 = Methodref          #34.#47        // java/io/ObjectOutputStream.writeInt:(I)V
  #49 = Utf8               word
  #50 = Utf8               (I)J
  #51 = NameAndType        #49:#50        // word:(I)J
  #52 = InterfaceMethodref #9.#51         // scala/collection/BitSet.word:(I)J
  #53 = Utf8               writeLong
  #54 = Utf8               (J)V
  #55 = NameAndType        #53:#54        // writeLong:(J)V
  #56 = Methodref          #34.#55        // java/io/ObjectOutputStream.writeLong:(J)V
  #57 = Utf8               I
  #58 = Utf8               i
  #59 = Utf8               Ljava/io/ObjectOutputStream;
  #60 = Utf8               readObject
  #61 = Utf8               (Ljava/io/ObjectInputStream;)V
  #62 = Utf8               in
  #63 = Utf8               java/io/ObjectInputStream
  #64 = Class              #63            // java/io/ObjectInputStream
  #65 = Utf8               defaultReadObject
  #66 = NameAndType        #65:#36        // defaultReadObject:()V
  #67 = Methodref          #64.#66        // java/io/ObjectInputStream.defaultReadObject:()V
  #68 = Utf8               readInt
  #69 = NameAndType        #68:#42        // readInt:()I
  #70 = Methodref          #64.#69        // java/io/ObjectInputStream.readInt:()I
  #71 = NameAndType        #27:#28        // elems_$eq:([J)V
  #72 = Methodref          #2.#71         // scala/collection/BitSet$SerializationProxy.elems_$eq:([J)V
  #73 = NameAndType        #17:#24        // elems:()[J
  #74 = Methodref          #2.#73         // scala/collection/BitSet$SerializationProxy.elems:()[J
  #75 = Utf8               readLong
  #76 = Utf8               ()J
  #77 = NameAndType        #75:#76        // readLong:()J
  #78 = Methodref          #64.#77        // java/io/ObjectInputStream.readLong:()J
  #79 = Utf8               Ljava/io/ObjectInputStream;
  #80 = Utf8               readResolve
  #81 = Utf8               ()Ljava/lang/Object;
  #82 = Utf8               <init>
  #83 = Utf8               (Lscala/collection/BitSet;)V
  #84 = NameAndType        #82:#36        // "<init>":()V
  #85 = Methodref          #4.#84         // java/lang/Object."<init>":()V
  #86 = Utf8               ConstantValue
  #87 = Utf8               Code
  #88 = Utf8               LineNumberTable
  #89 = Utf8               LocalVariableTable
  #90 = Utf8               MethodParameters
  #91 = Utf8               StackMapTable
  #92 = Utf8               InnerClasses
  #93 = Utf8               SourceFile
  #94 = Utf8               ScalaInlineInfo
  #95 = Utf8               Scala
{
  private static final long serialVersionUID;
    descriptor: J
    flags: (0x001a) ACC_PRIVATE, ACC_STATIC, ACC_FINAL
    ConstantValue: long 3l

  private final transient scala.collection.BitSet coll;
    descriptor: Lscala/collection/BitSet;
    flags: (0x0092) ACC_PRIVATE, ACC_FINAL, ACC_TRANSIENT

  private transient long[] elems;
    descriptor: [J
    flags: (0x0082) ACC_PRIVATE, ACC_TRANSIENT

  public scala.collection.BitSet coll();
    descriptor: ()Lscala/collection/BitSet;
    flags: (0x0001) ACC_PUBLIC
    Code:
      stack=1, locals=1, args_size=1
         0: aload_0
         1: getfield      #21                 // Field coll:Lscala/collection/BitSet;
         4: areturn
      LineNumberTable:
        line 54: 0
      LocalVariableTable:
        Start  Length  Slot  Name   Signature
            0       5     0  this   Lscala/collection/BitSet$SerializationProxy;

  public long[] elems();
    descriptor: ()[J
    flags: (0x0001) ACC_PUBLIC
    Code:
      stack=1, locals=1, args_size=1
         0: aload_0
         1: getfield      #26                 // Field elems:[J
         4: areturn
      LineNumberTable:
        line 56: 0
      LocalVariableTable:
        Start  Length  Slot  Name   Signature
            0       5     0  this   Lscala/collection/BitSet$SerializationProxy;

  public void elems_$eq(long[]);
    descriptor: ([J)V
    flags: (0x0001) ACC_PUBLIC
    Code:
      stack=2, locals=2, args_size=2
         0: aload_0
         1: aload_1
         2: putfield      #26                 // Field elems:[J
         5: return
      LineNumberTable:
        line 56: 0
      LocalVariableTable:
        Start  Length  Slot  Name   Signature
            0       6     0  this   Lscala/collection/BitSet$SerializationProxy;
            0       6     1   x$1   [J
    MethodParameters:
      Name                           Flags
      x$1                            final

  private void writeObject(java.io.ObjectOutputStream);
    descriptor: (Ljava/io/ObjectOutputStream;)V
    flags: (0x0002) ACC_PRIVATE
    Code:
      stack=3, locals=4, args_size=2
         0: aload_1
         1: invokevirtual #38                 // Method java/io/ObjectOutputStream.defaultWriteObject:()V
         4: aload_0
         5: invokevirtual #40                 // Method coll:()Lscala/collection/BitSet;
         8: invokeinterface #44,  1           // InterfaceMethod scala/collection/BitSet.nwords:()I
        13: istore_2
        14: aload_1
        15: iload_2
        16: invokevirtual #48                 // Method java/io/ObjectOutputStream.writeInt:(I)V
        19: iconst_0
        20: istore_3
        21: iload_3
        22: iload_2
        23: if_icmpge     46
        26: aload_1
        27: aload_0
        28: invokevirtual #40                 // Method coll:()Lscala/collection/BitSet;
        31: iload_3
        32: invokeinterface #52,  2           // InterfaceMethod scala/collection/BitSet.word:(I)J
        37: invokevirtual #56                 // Method java/io/ObjectOutputStream.writeLong:(J)V
        40: iinc          3, 1
        43: goto          21
        46: return
      StackMapTable: number_of_entries = 2
        frame_type = 253 /* append */
          offset_delta = 21
          locals = [ int, int ]
        frame_type = 24 /* same */
      LineNumberTable:
        line 59: 0
        line 60: 4
        line 61: 14
        line 62: 19
        line 63: 21
        line 64: 26
        line 65: 40
        line 63: 43
      LocalVariableTable:
        Start  Length  Slot  Name   Signature
           14      32     2 nwords   I
           21      25     3     i   I
            0      47     0  this   Lscala/collection/BitSet$SerializationProxy;
            0      47     1   out   Ljava/io/ObjectOutputStream;
    MethodParameters:
      Name                           Flags
      out                            final

  private void readObject(java.io.ObjectInputStream);
    descriptor: (Ljava/io/ObjectInputStream;)V
    flags: (0x0002) ACC_PRIVATE
    Code:
      stack=4, locals=4, args_size=2
         0: aload_1
         1: invokevirtual #67                 // Method java/io/ObjectInputStream.defaultReadObject:()V
         4: aload_1
         5: invokevirtual #70                 // Method java/io/ObjectInputStream.readInt:()I
         8: istore_2
         9: aload_0
        10: iload_2
        11: newarray       long
        13: invokevirtual #72                 // Method elems_$eq:([J)V
        16: iconst_0
        17: istore_3
        18: iload_3
        19: iload_2
        20: if_icmpge     39
        23: aload_0
        24: invokevirtual #74                 // Method elems:()[J
        27: iload_3
        28: aload_1
        29: invokevirtual #78                 // Method java/io/ObjectInputStream.readLong:()J
        32: lastore
        33: iinc          3, 1
        36: goto          18
        39: return
      StackMapTable: number_of_entries = 2
        frame_type = 253 /* append */
          offset_delta = 18
          locals = [ int, int ]
        frame_type = 20 /* same */
      LineNumberTable:
        line 70: 0
        line 71: 4
        line 72: 9
        line 73: 16
        line 74: 18
        line 75: 23
        line 76: 33
        line 74: 36
      LocalVariableTable:
        Start  Length  Slot  Name   Signature
            9      30     2 nwords   I
           18      21     3     i   I
            0      40     0  this   Lscala/collection/BitSet$SerializationProxy;
            0      40     1    in   Ljava/io/ObjectInputStream;
    MethodParameters:
      Name                           Flags
      in                             final

  public abstract java.lang.Object readResolve();
    descriptor: ()Ljava/lang/Object;
    flags: (0x0401) ACC_PUBLIC, ACC_ABSTRACT

  public scala.collection.BitSet$SerializationProxy(scala.collection.BitSet);
    descriptor: (Lscala/collection/BitSet;)V
    flags: (0x0001) ACC_PUBLIC
    Code:
      stack=2, locals=2, args_size=2
         0: aload_0
         1: aload_1
         2: putfield      #21                 // Field coll:Lscala/collection/BitSet;
         5: aload_0
         6: invokespecial #85                 // Method java/lang/Object."<init>":()V
         9: return
      LineNumberTable:
        line 54: 0
      LocalVariableTable:
        Start  Length  Slot  Name   Signature
            0      10     0  this   Lscala/collection/BitSet$SerializationProxy;
            0      10     1  coll   Lscala/collection/BitSet;
    MethodParameters:
      Name                           Flags
      coll                           final
}
InnerClasses:
  public static abstract #10= #2 of #9;   // SerializationProxy=class scala/collection/BitSet$SerializationProxy of class scala/collection/BitSet
SourceFile: "BitSet.scala"
  ScalaInlineInfo: length = 0x27 (unknown attribute)
   01 00 00 07 00 52 00 53 00 00 0F 00 13 00 00 11
   00 18 00 00 1B 00 1C 00 00 3C 00 3D 01 00 50 00
   51 00 00 1E 00 1F 01
  Scala: length = 0x0 (unknown attribute)

