Classfile /Users/mw/Projects/slang-braindump/.jar/jar8/assemble/slang-braindump/assemble/content/scala/collection/BuildFrom$$anon$1.class
  Last modified May 29, 2022; size 1455 bytes
  SHA-256 checksum 96b160f8c7a78562dd48b9f8dd89107e99b40b0a686442994a7faa1850f67225
  Compiled from "BuildFrom.scala"
public final class scala.collection.BuildFrom$$anon$1 extends java.lang.Object implements scala.collection.Factory<A, C>
  minor version: 0
  major version: 52
  flags: (0x0031) ACC_PUBLIC, ACC_FINAL, ACC_SUPER
  this_class: #2                          // scala/collection/BuildFrom$$anon$1
  super_class: #5                         // java/lang/Object
  interfaces: 1, fields: 2, methods: 3, attributes: 6
Constant pool:
   #1 = Utf8               scala/collection/BuildFrom$$anon$1
   #2 = Class              #1             // scala/collection/BuildFrom$$anon$1
   #3 = Utf8               Ljava/lang/Object;Lscala/collection/Factory<TA;TC;>;
   #4 = Utf8               java/lang/Object
   #5 = Class              #4             // java/lang/Object
   #6 = Utf8               scala/collection/Factory
   #7 = Class              #6             // scala/collection/Factory
   #8 = Utf8               BuildFrom.scala
   #9 = Utf8               scala/collection/BuildFrom
  #10 = Class              #9             // scala/collection/BuildFrom
  #11 = Utf8               toFactory
  #12 = Utf8               (Ljava/lang/Object;)Lscala/collection/Factory;
  #13 = NameAndType        #11:#12        // toFactory:(Ljava/lang/Object;)Lscala/collection/Factory;
  #14 = Utf8               $outer
  #15 = Utf8               Lscala/collection/BuildFrom;
  #16 = Utf8               from$1
  #17 = Utf8               Ljava/lang/Object;
  #18 = Utf8               fromSpecific
  #19 = Utf8               (Lscala/collection/IterableOnce;)Ljava/lang/Object;
  #20 = Utf8               (Lscala/collection/IterableOnce<TA;>;)TC;
  #21 = Utf8               it
  #22 = NameAndType        #14:#15        // $outer:Lscala/collection/BuildFrom;
  #23 = Fieldref           #2.#22         // scala/collection/BuildFrom$$anon$1.$outer:Lscala/collection/BuildFrom;
  #24 = NameAndType        #16:#17        // from$1:Ljava/lang/Object;
  #25 = Fieldref           #2.#24         // scala/collection/BuildFrom$$anon$1.from$1:Ljava/lang/Object;
  #26 = Utf8               (Ljava/lang/Object;Lscala/collection/IterableOnce;)Ljava/lang/Object;
  #27 = NameAndType        #18:#26        // fromSpecific:(Ljava/lang/Object;Lscala/collection/IterableOnce;)Ljava/lang/Object;
  #28 = InterfaceMethodref #10.#27        // scala/collection/BuildFrom.fromSpecific:(Ljava/lang/Object;Lscala/collection/IterableOnce;)Ljava/lang/Object;
  #29 = Utf8               this
  #30 = Utf8               Lscala/collection/BuildFrom$$anon$1;
  #31 = Utf8               Lscala/collection/IterableOnce;
  #32 = Utf8               newBuilder
  #33 = Utf8               ()Lscala/collection/mutable/Builder;
  #34 = Utf8               ()Lscala/collection/mutable/Builder<TA;TC;>;
  #35 = Utf8               (Ljava/lang/Object;)Lscala/collection/mutable/Builder;
  #36 = NameAndType        #32:#35        // newBuilder:(Ljava/lang/Object;)Lscala/collection/mutable/Builder;
  #37 = InterfaceMethodref #10.#36        // scala/collection/BuildFrom.newBuilder:(Ljava/lang/Object;)Lscala/collection/mutable/Builder;
  #38 = Utf8               <init>
  #39 = Utf8               (Lscala/collection/BuildFrom;Ljava/lang/Object;)V
  #40 = Utf8               ()V
  #41 = NameAndType        #38:#40        // "<init>":()V
  #42 = Methodref          #5.#41         // java/lang/Object."<init>":()V
  #43 = Utf8               Code
  #44 = Utf8               LineNumberTable
  #45 = Utf8               LocalVariableTable
  #46 = Utf8               Signature
  #47 = Utf8               MethodParameters
  #48 = Utf8               StackMapTable
  #49 = Utf8               InnerClasses
  #50 = Utf8               EnclosingMethod
  #51 = Utf8               SourceFile
  #52 = Utf8               ScalaInlineInfo
  #53 = Utf8               Scala
{
  private final scala.collection.BuildFrom $outer;
    descriptor: Lscala/collection/BuildFrom;
    flags: (0x1012) ACC_PRIVATE, ACC_FINAL, ACC_SYNTHETIC

  private final java.lang.Object from$1;
    descriptor: Ljava/lang/Object;
    flags: (0x0012) ACC_PRIVATE, ACC_FINAL

  public C fromSpecific(scala.collection.IterableOnce<A>);
    descriptor: (Lscala/collection/IterableOnce;)Ljava/lang/Object;
    flags: (0x0001) ACC_PUBLIC
    Code:
      stack=3, locals=2, args_size=2
         0: aload_0
         1: getfield      #23                 // Field $outer:Lscala/collection/BuildFrom;
         4: aload_0
         5: getfield      #25                 // Field from$1:Ljava/lang/Object;
         8: aload_1
         9: invokeinterface #28,  3           // InterfaceMethod scala/collection/BuildFrom.fromSpecific:(Ljava/lang/Object;Lscala/collection/IterableOnce;)Ljava/lang/Object;
        14: areturn
      LineNumberTable:
        line 40: 0
      LocalVariableTable:
        Start  Length  Slot  Name   Signature
            0      15     0  this   Lscala/collection/BuildFrom$$anon$1;
            0      15     1    it   Lscala/collection/IterableOnce;
    Signature: #20                          // (Lscala/collection/IterableOnce<TA;>;)TC;
    MethodParameters:
      Name                           Flags
      it                             final

  public scala.collection.mutable.Builder<A, C> newBuilder();
    descriptor: ()Lscala/collection/mutable/Builder;
    flags: (0x0001) ACC_PUBLIC
    Code:
      stack=2, locals=1, args_size=1
         0: aload_0
         1: getfield      #23                 // Field $outer:Lscala/collection/BuildFrom;
         4: aload_0
         5: getfield      #25                 // Field from$1:Ljava/lang/Object;
         8: invokeinterface #37,  2           // InterfaceMethod scala/collection/BuildFrom.newBuilder:(Ljava/lang/Object;)Lscala/collection/mutable/Builder;
        13: areturn
      LineNumberTable:
        line 41: 0
      LocalVariableTable:
        Start  Length  Slot  Name   Signature
            0      14     0  this   Lscala/collection/BuildFrom$$anon$1;
    Signature: #34                          // ()Lscala/collection/mutable/Builder<TA;TC;>;

  public scala.collection.BuildFrom$$anon$1(scala.collection.BuildFrom, java.lang.Object);
    descriptor: (Lscala/collection/BuildFrom;Ljava/lang/Object;)V
    flags: (0x0001) ACC_PUBLIC
    Code:
      stack=2, locals=3, args_size=3
         0: aload_1
         1: ifnonnull     6
         4: aconst_null
         5: athrow
         6: aload_0
         7: aload_1
         8: putfield      #23                 // Field $outer:Lscala/collection/BuildFrom;
        11: aload_0
        12: aload_2
        13: putfield      #25                 // Field from$1:Ljava/lang/Object;
        16: aload_0
        17: invokespecial #42                 // Method java/lang/Object."<init>":()V
        20: return
      StackMapTable: number_of_entries = 1
        frame_type = 6 /* same */
      LineNumberTable:
        line 39: 0
      LocalVariableTable:
        Start  Length  Slot  Name   Signature
            0      21     0  this   Lscala/collection/BuildFrom$$anon$1;
            0      21     1 $outer   Lscala/collection/BuildFrom;
            0      21     2 from$1   Ljava/lang/Object;
    MethodParameters:
      Name                           Flags
      $outer                         final synthetic
      from$1                         final
}
InnerClasses:
  public final #2;                        // class scala/collection/BuildFrom$$anon$1
EnclosingMethod: #10.#13                // scala.collection.BuildFrom.toFactory
Signature: #3                           // Ljava/lang/Object;Lscala/collection/Factory<TA;TC;>;
SourceFile: "BuildFrom.scala"
  ScalaInlineInfo: length = 0x13 (unknown attribute)
   01 01 00 03 00 26 00 27 01 00 12 00 13 01 00 20
   00 21 01
  Scala: length = 0x0 (unknown attribute)

