Classfile /Users/mw/Projects/slang-braindump/.jar/jar8/assemble/slang-braindump/assemble/content/scala/collection/ClassTagIterableFactory.class
  Last modified May 29, 2022; size 21417 bytes
  SHA-256 checksum 24834aaa17fb21070b76713b0fc50eaea384bfe8b7c682cec78be9b5199d64b8
  Compiled from "Factory.scala"
public interface scala.collection.ClassTagIterableFactory<CC extends java.lang.Object> extends scala.collection.EvidenceIterableFactory<CC, scala.reflect.ClassTag>
  minor version: 0
  major version: 52
  flags: (0x0601) ACC_PUBLIC, ACC_INTERFACE, ACC_ABSTRACT
  this_class: #2                          // scala/collection/ClassTagIterableFactory
  super_class: #5                         // java/lang/Object
  interfaces: 1, fields: 0, methods: 43, attributes: 7
Constant pool:
    #1 = Utf8               scala/collection/ClassTagIterableFactory
    #2 = Class              #1            // scala/collection/ClassTagIterableFactory
    #3 = Utf8               <CC:Ljava/lang/Object;>Ljava/lang/Object;Lscala/collection/EvidenceIterableFactory<TCC;Lscala/reflect/ClassTag;>;
    #4 = Utf8               java/lang/Object
    #5 = Class              #4            // java/lang/Object
    #6 = Utf8               scala/collection/EvidenceIterableFactory
    #7 = Class              #6            // scala/collection/EvidenceIterableFactory
    #8 = Utf8               Factory.scala
    #9 = Utf8               Lscala/reflect/ScalaSignature;
   #10 = Utf8               bytes
   #11 = Utf8               \u0006\u0005\rEgaB\u0011#!\u0003\r\ta\n\u0005\u0006\u000b\u0002!\tA\u0012\u0005\u0007\u0015\u0002\u0001K1B&\t\u000bY\u0003A\u0011A,\t\u000bY\u0003A\u0011\u00018\t\u000by\u0004A\u0011A@\t\ry\u0004A\u0011AA!\u0011\u0019q\b\u0001\"\u0001\u0002h!1a\u0010\u0001C\u0001\u0003#Cq!a0\u0001\t\u0003\t\t\rC\u0004\u0002@\u0002!\t!a:\t\u000f\u0005}\u0006\u0001\"\u0001\u0003\u0010!9\u0011q\u0018\u0001\u0005\u0002\tmra\u0002B6E!\u0005!Q\u000e\u0004\u0007C\tB\tAa\u001c\t\u000f\t\u0005e\u0002\"\u0001\u0003\u0004\u001a1!Q\u0011\b\u0001\u0005\u000fC!Ba)\u0011\u0005\u0003\u0005\u000b\u0011\u0002BS\u0011\u001d\u0011\t\t\u0005C\u0001\u0005O3aAa/\u000f\u0001\tu\u0006B\u0003BR\'\t\u0005\t\u0015!\u0003\u0003R\"9!\u0011Q\n\u0005\u0002\tM\u0007b\u0002Bm\'\u0011\u0005!1\u001c\u0005\b\u0005K\u001cB\u0011\u0001Bt\u0011\u001d\u0011Yp\u0005C\u0001\u0005{Dqaa\u0005\u0014\t\u0003\u001a)\u0002C\u0004\u0004*M!\tea\u000b\t\u000f\r\u00153\u0003\"\u0011\u0004H!1ak\u0005C!\u0007[BaAV\n\u0005B\r\r\u0005B\u0002@\u0014\t\u0003\u001aI\nC\u0004\u0002@N!\te!,\t\u0013\r\u0005g\"!A\u0005\n\r\r\'aF\"mCN\u001cH+Y4Ji\u0016\u0014\u0018M\u00197f\r\u0006\u001cGo\u001c:z\u0015\t\u0019C%\u0001\u0006d_2dWm\u0019;j_:T\u0011!J\u0001\u0006g\u000e\fG.Y\u0002\u0001+\tA3gE\u0002\u0001S5\u0002\"AK\u0016\u000e\u0003\u0011J!\u0001\f\u0013\u0003\r\u0005s\u0017PU3g!\u0011qs&M \u000e\u0003\tJ!\u0001\r\u0012\u0003/\u00153\u0018\u000eZ3oG\u0016LE/\u001a:bE2,g)Y2u_JL\bC\u0001\u001a4\u0019\u0001!a\u0001\u000e\u0001\u0005\u0006\u0004)$AA\"D+\t1T(\u0005\u00028uA\u0011!\u0006O\u0005\u0003s\u0011\u0012qAT8uQ&tw\r\u0005\u0002+w%\u0011A\b\n\u0002\u0004\u0003:LH!\u0002 4\u0005\u00041$!B0%IM\u0002\u0004C\u0001!D\u001b\u0005\t%B\u0001\"%\u0003\u001d\u0011XM\u001a7fGRL!\u0001R!\u0003\u0011\rc\u0017m]:UC\u001e\fa\u0001J5oSR$C#A$\u0011\u0005)B\u0015BA%%\u0005\u0011)f.\u001b;\u0002\u0015\r\u001c7\t\\1tgR\u000bw-\u0006\u0002M!V\tQ\nE\u0002A\u0007:\u00032AM\u001aP!\t\u0011\u0004\u000bB\u0003R\u0005\t\u0007aGA\u0001YQ\t\u00111\u000b\u0005\u0002+)&\u0011Q\u000b\n\u0002\u0007S:d\u0017N\\3\u0002\u000bI\fgnZ3\u0016\u0005acFcA-kYR\u0019!LX4\u0011\u0007I\u001a4\f\u0005\u000239\u0012)Ql\u0001b\u0001m\t\t\u0011\tC\u0004`\u0007\u0005\u0005\t9\u00011\u0002\u0017\u00154\u0018\u000eZ3oG\u0016$#G\r\t\u0004C\u0012\\fB\u0001\u0016c\u0013\t\u0019G%A\u0004qC\u000e\\\u0017mZ3\n\u0005\u00154\'\u0001C%oi\u0016<\'/\u00197\u000b\u0005\r$\u0003b\u00025\u0004\u0003\u0003\u0005\u001d![\u0001\fKZLG-\u001a8dK\u0012\u00124\u0007E\u0002A\u0007nCQa[\u0002A\u0002m\u000bQa\u001d;beRDQ!\\\u0002A\u0002m\u000b1!\u001a8e+\ty7\u000f\u0006\u0003qundHcA9uoB\u0019!g\r:\u0011\u0005I\u001aH!B/\u0005\u0005\u00041\u0004bB;\u0005\u0003\u0003\u0005\u001dA^\u0001\fKZLG-\u001a8dK\u0012\u0012D\u0007E\u0002bIJDq\u0001\u001f\u0003\u0002\u0002\u0003\u000f\u00110A\u0006fm&$WM\\2fII*\u0004c\u0001!De\")1\u000e\u0002a\u0001e\")Q\u000e\u0002a\u0001e\")Q\u0010\u0002a\u0001e\u0006!1\u000f^3q\u0003\u00111\u0017\u000e\u001c7\u0016\t\u0005\u0005\u0011q\u0002\u000b\u0007\u0003\u0007\t\u0019$!\u0010\u0015\t\u0005\u0015\u0011\u0011\u0006\u000b\u0005\u0003\u000f\t\u0019\u0003\u0005\u00033g\u0005%!\u0006BA\u0006\u0003#\u0001BAM\u001a\u0002\u000eA\u0019!\'a\u0004\u0005\u000bu+!\u0019\u0001\u001c,\u0005\u0005M\u0001\u0003BA\u000b\u0003?i!!a\u0006\u000b\t\u0005e\u00111D\u0001\nk:\u001c\u0007.Z2lK\u0012T1!!\b%\u0003)\tgN\\8uCRLwN\\\u0005\u0005\u0003C\t9BA\tv]\u000eDWmY6fIZ\u000b\'/[1oG\u0016D\u0011\"!\n\u0006\u0003\u0003\u0005\u001d!a\n\u0002\u0017\u00154\u0018\u000eZ3oG\u0016$#G\u000e\t\u0005\u0001\u000e\u000bi\u0001\u0003\u0005\u0002,\u0015!\t\u0019AA\u0017\u0003\u0011)G.Z7\u0011\u000b)\ny#!\u0004\n\u0007\u0005EBE\u0001\u0005=Eft\u0017-\\3?\u0011\u001d\t)$\u0002a\u0001\u0003o\t!A\\\u0019\u0011\u0007)\nI$C\u0002\u0002<\u0011\u00121!\u00138u\u0011\u001d\ty$\u0002a\u0001\u0003o\t!A\u001c\u001a\u0016\t\u0005\r\u00131\u000b\u000b\t\u0003\u000b\ny&!\u0019\u0002dQ!\u0011qIA.)\u0011\tI%!\u0016\u0011\tI\u001a\u00141\n\u0016\u0005\u0003\u001b\n\t\u0002\u0005\u00033g\u0005=\u0003\u0003\u0002\u001a4\u0003#\u00022AMA*\t\u0015ifA1\u00017\u0011%\t9FBA\u0001\u0002\b\tI&A\u0006fm&$WM\\2fII:\u0004\u0003\u0002!D\u0003#B\u0001\"a\u000b\u0007\t\u0003\u0007\u0011Q\f\t\u0006U\u0005=\u0012\u0011\u000b\u0005\b\u0003k1\u0001\u0019AA\u001c\u0011\u001d\tyD\u0002a\u0001\u0003oAq!!\u001a\u0007\u0001\u0004\t9$\u0001\u0002ogU!\u0011\u0011NA>))\tY\'a\"\u0002\n\u0006-\u0015Q\u0012\u000b\u0005\u0003[\n\u0019\t\u0006\u0003\u0002p\u0005u\u0004\u0003\u0002\u001a4\u0003cRC!a\u001d\u0002\u0012A!!gMA;!\u0011\u00114\'a\u001e\u0011\tI\u001a\u0014\u0011\u0010\t\u0004e\u0005mD!B/\b\u0005\u00041\u0004\"CA@\u000f\u0005\u0005\t9AAA\u0003-)g/\u001b3f]\u000e,GE\r\u001d\u0011\t\u0001\u001b\u0015\u0011\u0010\u0005\t\u0003W9A\u00111\u0001\u0002\u0006B)!&a\f\u0002z!9\u0011QG\u0004A\u0002\u0005]\u0002bBA \u000f\u0001\u0007\u0011q\u0007\u0005\b\u0003K:\u0001\u0019AA\u001c\u0011\u001d\tyi\u0002a\u0001\u0003o\t!A\u001c\u001b\u0016\t\u0005M\u0015q\u0015\u000b\r\u0003+\u000b\u0019,!.\u00028\u0006e\u00161\u0018\u000b\u0005\u0003/\u000by\u000b\u0006\u0003\u0002\u001a\u0006%\u0006\u0003\u0002\u001a4\u00037SC!!(\u0002\u0012A!!gMAP!\u0011\u00114\'!)\u0011\tI\u001a\u00141\u0015\t\u0005eM\n)\u000bE\u00023\u0003O#Q!\u0018\u0005C\u0002YB\u0011\"a+\t\u0003\u0003\u0005\u001d!!,\u0002\u0017\u00154\u0018\u000eZ3oG\u0016$#\'\u000f\t\u0005\u0001\u000e\u000b)\u000b\u0003\u0005\u0002,!!\t\u0019AAY!\u0015Q\u0013qFAS\u0011\u001d\t)\u0004\u0003a\u0001\u0003oAq!a\u0010\t\u0001\u0004\t9\u0004C\u0004\u0002f!\u0001\r!a\u000e\t\u000f\u0005=\u0005\u00021\u0001\u00028!9\u0011Q\u0018\u0005A\u0002\u0005]\u0012A\u000186\u0003!!\u0018MY;mCR,W\u0003BAb\u0003#$b!!2\u0002d\u0006\u0015H\u0003BAd\u00033$B!!3\u0002TB!!gMAfU\u0011\ti-!\u0005\u0011\tI\u001a\u0014q\u001a\t\u0004e\u0005EG!B/\n\u0005\u00041\u0004\"CAk\u0013\u0005\u0005\t9AAl\u0003-)g/\u001b3f]\u000e,Ge\r\u0019\u0011\t\u0001\u001b\u0015q\u001a\u0005\b\u00037L\u0001\u0019AAo\u0003\u00051\u0007#\u0003\u0016\u0002`\u0006]\u0012qGAh\u0013\r\t\t\u000f\n\u0002\n\rVt7\r^5p]JBq!!\u000e\n\u0001\u0004\t9\u0004C\u0004\u0002@%\u0001\r!a\u000e\u0016\t\u0005%\u0018\u0011 \u000b\t\u0003W\u0014IAa\u0003\u0003\u000eQ!\u0011Q\u001eB\u0001)\u0011\ty/a?\u0011\tI\u001a\u0014\u0011\u001f\u0016\u0005\u0003g\f\t\u0002\u0005\u00033g\u0005U\b\u0003\u0002\u001a4\u0003o\u00042AMA}\t\u0015i&B1\u00017\u0011%\tiPCA\u0001\u0002\b\ty0A\u0006fm&$WM\\2fIM\n\u0004\u0003\u0002!D\u0003oDq!a7\u000b\u0001\u0004\u0011\u0019\u0001E\u0006+\u0005\u000b\t9$a\u000e\u00028\u0005]\u0018b\u0001B\u0004I\tIa)\u001e8di&|gn\r\u0005\b\u0003kQ\u0001\u0019AA\u001c\u0011\u001d\tyD\u0003a\u0001\u0003oAq!!\u001a\u000b\u0001\u0004\t9$\u0006\u0003\u0003\u0012\t\rBC\u0003B\n\u0005g\u0011)Da\u000e\u0003:Q!!Q\u0003B\u0016)\u0011\u00119B!\n\u0011\tI\u001a$\u0011\u0004\u0016\u0005\u00057\t\t\u0002\u0005\u00033g\tu\u0001\u0003\u0002\u001a4\u0005?\u0001BAM\u001a\u0003\"A\u0019!Ga\t\u0005\u000bu[!\u0019\u0001\u001c\t\u0013\t\u001d2\"!AA\u0004\t%\u0012aC3wS\u0012,gnY3%gI\u0002B\u0001Q\"\u0003\"!9\u00111\\\u0006A\u0002\t5\u0002#\u0004\u0016\u00030\u0005]\u0012qGA\u001c\u0003o\u0011\t#C\u0002\u00032\u0011\u0012\u0011BR;oGRLwN\u001c\u001b\t\u000f\u0005U2\u00021\u0001\u00028!9\u0011qH\u0006A\u0002\u0005]\u0002bBA3\u0017\u0001\u0007\u0011q\u0007\u0005\b\u0003\u001f[\u0001\u0019AA\u001c+\u0011\u0011iD!\u0015\u0015\u0019\t}\"\u0011\rB2\u0005K\u00129G!\u001b\u0015\t\t\u0005#\u0011\f\u000b\u0005\u0005\u0007\u0012\u0019\u0006\u0005\u00033g\t\u0015#\u0006\u0002B$\u0003#\u0001BAM\u001a\u0003JA!!g\rB&!\u0011\u00114G!\u0014\u0011\tI\u001a$q\n\t\u0004e\tEC!B/\r\u0005\u00041\u0004\"\u0003B+\u0019\u0005\u0005\t9\u0001B,\u0003-)g/\u001b3f]\u000e,GeM\u001a\u0011\t\u0001\u001b%q\n\u0005\b\u00037d\u0001\u0019\u0001B.!=Q#QLA\u001c\u0003o\t9$a\u000e\u00028\t=\u0013b\u0001B0I\tIa)\u001e8di&|g.\u000e\u0005\b\u0003ka\u0001\u0019AA\u001c\u0011\u001d\ty\u0004\u0004a\u0001\u0003oAq!!\u001a\r\u0001\u0004\t9\u0004C\u0004\u0002\u00102\u0001\r!a\u000e\t\u000f\u0005uF\u00021\u0001\u00028\u000592\t\\1tgR\u000bw-\u0013;fe\u0006\u0014G.\u001a$bGR|\'/\u001f\t\u0003]9\u0019BAD\u0015\u0003rA!!1\u000fB?\u001b\t\u0011)H\u0003\u0003\u0003x\te\u0014AA5p\u0015\t\u0011Y(\u0001\u0003kCZ\f\u0017\u0002\u0002B@\u0005k\u0012AbU3sS\u0006d\u0017N_1cY\u0016\fa\u0001P5oSRtDC\u0001B7\u0005!!U\r\\3hCR,W\u0003\u0002BE\u00053\u001bR\u0001\u0005BF\u0005C\u0003rA!$\u0003\u0014\n]uHD\u0002/\u0005\u001fK1A!%#\u0003])e/\u001b3f]\u000e,\u0017\n^3sC\ndWMR1di>\u0014\u00180\u0003\u0003\u0003\u0006\nU%b\u0001BIEA\u0019!G!\'\u0005\rQ\u0002\"\u0019\u0001BN+\r1$Q\u0014\u0003\b\u0005?\u0013IJ1\u00017\u0005\u0015yF\u0005J\u001a2!\u0011q\u0003Aa&\u0002\u0011\u0011,G.Z4bi\u0016\u0004RAL\u0018\u0003\u0018~\"BA!+\u0003.B)!1\u0016\t\u0003\u00186\ta\u0002C\u0004\u0003$J\u0001\rA!*)\u000fA\u0011\tLa.\u0003:B\u0019!Fa-\n\u0007\tUFE\u0001\tTKJL\u0017\r\u001c,feNLwN\\+J\t\u0006)a/\u00197vKz\t1AA\nB]fLE/\u001a:bE2,G)\u001a7fO\u0006$X-\u0006\u0003\u0003@\n%7\u0003B\n*\u0005\u0003\u0004RA\fBb\u0005\u000fL1A!2#\u0005=IE/\u001a:bE2,g)Y2u_JL\bc\u0001\u001a\u0003J\u00121Ag\u0005b\u0001\u0005\u0017,2A\u000eBg\t\u001d\u0011yM!3C\u0002Y\u0012Qa\u0018\u0013%gI\u0002BA\f\u0001\u0003HR!!Q\u001bBl!\u0015\u0011Yk\u0005Bd\u0011\u001d\u0011\u0019+\u0006a\u0001\u0005#\fQ!Z7qif,BA!8\u0003dV\u0011!q\u001c\t\u0006e\t%\'\u0011\u001d\t\u0004e\t\rH!B/\u0017\u0005\u00041\u0014\u0001\u00024s_6,BA!;\u0003pR!!1\u001eBy!\u0015\u0011$\u0011\u001aBw!\r\u0011$q\u001e\u0003\u0006;^\u0011\rA\u000e\u0005\b\u0005g<\u0002\u0019\u0001B{\u0003\tIG\u000fE\u0003/\u0005o\u0014i/C\u0002\u0003z\n\u0012A\"\u0013;fe\u0006\u0014G.Z(oG\u0016\f!B\\3x\u0005VLG\u000eZ3s+\u0011\u0011ypa\u0004\u0016\u0005\r\u0005\u0001\u0003CB\u0002\u0007\u0013\u0019ia!\u0005\u000e\u0005\r\u0015!bAB\u0004E\u00059Q.\u001e;bE2,\u0017\u0002BB\u0006\u0007\u000b\u0011qAQ;jY\u0012,\'\u000fE\u00023\u0007\u001f!Q!\u0018\rC\u0002Y\u0002RA\rBe\u0007\u001b\tQ!\u00199qYf,Baa\u0006\u0004\u001eQ!1\u0011DB\u0010!\u0015\u0011$\u0011ZB\u000e!\r\u00114Q\u0004\u0003\u0006;f\u0011\rA\u000e\u0005\b\u0007CI\u0002\u0019AB\u0012\u0003\u0015)G.Z7t!\u0015Q3QEB\u000e\u0013\r\u00199\u0003\n\u0002\u000byI,\u0007/Z1uK\u0012t\u0014aB5uKJ\fG/Z\u000b\u0005\u0007[\u0019)\u0004\u0006\u0004\u00040\r}2\u0011\t\u000b\u0005\u0007c\u00199\u0004E\u00033\u0005\u0013\u001c\u0019\u0004E\u00023\u0007k!Q!\u0018\u000eC\u0002YBq!a7\u001b\u0001\u0004\u0019I\u0004E\u0004+\u0007w\u0019\u0019da\r\n\u0007\ruBEA\u0005Gk:\u001cG/[8oc!11N\u0007a\u0001\u0007gAqaa\u0011\u001b\u0001\u0004\t9$A\u0002mK:\fa!\u001e8g_2$WCBB%\u0007#\u001aI\u0006\u0006\u0003\u0004L\r%D\u0003BB\'\u0007\'\u0002RA\rBe\u0007\u001f\u00022AMB)\t\u0015i6D1\u00017\u0011\u001d\tYn\u0007a\u0001\u0007+\u0002rAKB\u001e\u0007/\u001ai\u0006E\u00023\u00073\"aaa\u0017\u001c\u0005\u00041$!A*\u0011\u000b)\u001ayfa\u0019\n\u0007\r\u0005DE\u0001\u0004PaRLwN\u001c\t\bU\r\u00154qJB,\u0013\r\u00199\u0007\n\u0002\u0007)V\u0004H.\u001a\u001a\t\u000f\r-4\u00041\u0001\u0004X\u0005!\u0011N\\5u+\u0011\u0019yga\u001e\u0015\r\rE4qPBA)\u0011\u0019\u0019h!\u001f\u0011\u000bI\u0012Im!\u001e\u0011\u0007I\u001a9\bB\u0003^9\t\u0007a\u0007C\u0004\u0004|q\u0001\u001da! \u0002\u0003%\u0004B!\u00193\u0004v!11\u000e\ba\u0001\u0007kBa!\u001c\u000fA\u0002\rUT\u0003BBC\u0007\u001b#\u0002ba\"\u0004\u0014\u000eU5q\u0013\u000b\u0005\u0007\u0013\u001by\tE\u00033\u0005\u0013\u001cY\tE\u00023\u0007\u001b#Q!X\u000fC\u0002YBqaa\u001f\u001e\u0001\b\u0019\t\n\u0005\u0003bI\u000e-\u0005BB6\u001e\u0001\u0004\u0019Y\t\u0003\u0004n;\u0001\u000711\u0012\u0005\u0007{v\u0001\raa#\u0016\t\rm51\u0015\u000b\u0005\u0007;\u001bI\u000b\u0006\u0003\u0004 \u000e\u0015\u0006#\u0002\u001a\u0003J\u000e\u0005\u0006c\u0001\u001a\u0004$\u0012)QL\bb\u0001m!A\u00111\u0006\u0010\u0005\u0002\u0004\u00199\u000bE\u0003+\u0003_\u0019\t\u000bC\u0004\u0004,z\u0001\r!a\u000e\u0002\u00039,Baa,\u00048R!1\u0011WB_)\u0011\u0019\u0019l!/\u0011\u000bI\u0012Im!.\u0011\u0007I\u001a9\fB\u0003^?\t\u0007a\u0007C\u0004\u0002\\~\u0001\raa/\u0011\u000f)\u001aY$a\u000e\u00046\"911V\u0010A\u0002\u0005]\u0002fB\n\u00032\n]&\u0011X\u0001\roJLG/\u001a*fa2\f7-\u001a\u000b\u0003\u0007\u000b\u0004Baa2\u0004N6\u00111\u0011\u001a\u0006\u0005\u0007\u0017\u0014I(\u0001\u0003mC:<\u0017\u0002BBh\u0007\u0013\u0014aa\u00142kK\u000e$\b
   #12 = Utf8               java/lang/invoke/MethodHandles$Lookup
   #13 = Class              #12           // java/lang/invoke/MethodHandles$Lookup
   #14 = Utf8               java/lang/invoke/MethodHandles
   #15 = Class              #14           // java/lang/invoke/MethodHandles
   #16 = Utf8               Lookup
   #17 = Utf8               scala/collection/ClassTagIterableFactory$AnyIterableDelegate
   #18 = Class              #17           // scala/collection/ClassTagIterableFactory$AnyIterableDelegate
   #19 = Utf8               AnyIterableDelegate
   #20 = Utf8               scala/collection/ClassTagIterableFactory$Delegate
   #21 = Class              #20           // scala/collection/ClassTagIterableFactory$Delegate
   #22 = Utf8               Delegate
   #23 = Utf8               scala/collection/immutable/NumericRange$Exclusive
   #24 = Class              #23           // scala/collection/immutable/NumericRange$Exclusive
   #25 = Utf8               scala/collection/immutable/NumericRange
   #26 = Class              #25           // scala/collection/immutable/NumericRange
   #27 = Utf8               Exclusive
   #28 = Utf8               ccClassTag
   #29 = Utf8               ()Lscala/reflect/ClassTag;
   #30 = Utf8               <X:Ljava/lang/Object;>()Lscala/reflect/ClassTag<TCC;>;
   #31 = Utf8               scala/reflect/ClassTag$
   #32 = Class              #31           // scala/reflect/ClassTag$
   #33 = Utf8               MODULE$
   #34 = Utf8               Lscala/reflect/ClassTag$;
   #35 = NameAndType        #33:#34       // MODULE$:Lscala/reflect/ClassTag$;
   #36 = Fieldref           #32.#35       // scala/reflect/ClassTag$.MODULE$:Lscala/reflect/ClassTag$;
   #37 = Utf8               AnyRef
   #38 = NameAndType        #37:#29       // AnyRef:()Lscala/reflect/ClassTag;
   #39 = Methodref          #32.#38       // scala/reflect/ClassTag$.AnyRef:()Lscala/reflect/ClassTag;
   #40 = Utf8               this
   #41 = Utf8               Lscala/collection/ClassTagIterableFactory;
   #42 = Utf8               range$
   #43 = Utf8               (Lscala/collection/ClassTagIterableFactory;Ljava/lang/Object;Ljava/lang/Object;Lscala/math/Integral;Lscala/reflect/ClassTag;)Ljava/lang/Object;
   #44 = Utf8               $this
   #45 = Utf8               start
   #46 = Utf8               end
   #47 = Utf8               evidence$22
   #48 = Utf8               evidence$23
   #49 = Utf8               range
   #50 = Utf8               (Ljava/lang/Object;Ljava/lang/Object;Lscala/math/Integral;Lscala/reflect/ClassTag;)Ljava/lang/Object;
   #51 = NameAndType        #49:#50       // range:(Ljava/lang/Object;Ljava/lang/Object;Lscala/math/Integral;Lscala/reflect/ClassTag;)Ljava/lang/Object;
   #52 = InterfaceMethodref #2.#51        // scala/collection/ClassTagIterableFactory.range:(Ljava/lang/Object;Ljava/lang/Object;Lscala/math/Integral;Lscala/reflect/ClassTag;)Ljava/lang/Object;
   #53 = Utf8               Ljava/lang/Object;
   #54 = Utf8               Lscala/math/Integral;
   #55 = Utf8               Lscala/reflect/ClassTag;
   #56 = Utf8               <A:Ljava/lang/Object;>(TA;TA;Lscala/math/Integral<TA;>;Lscala/reflect/ClassTag<TA;>;)TCC;
   #57 = Utf8               scala/collection/immutable/NumericRange$
   #58 = Class              #57           // scala/collection/immutable/NumericRange$
   #59 = Utf8               Lscala/collection/immutable/NumericRange$;
   #60 = NameAndType        #33:#59       // MODULE$:Lscala/collection/immutable/NumericRange$;
   #61 = Fieldref           #58.#60       // scala/collection/immutable/NumericRange$.MODULE$:Lscala/collection/immutable/NumericRange$;
   #62 = Utf8               scala/math/Numeric
   #63 = Class              #62           // scala/math/Numeric
   #64 = Utf8               one
   #65 = Utf8               ()Ljava/lang/Object;
   #66 = NameAndType        #64:#65       // one:()Ljava/lang/Object;
   #67 = InterfaceMethodref #63.#66       // scala/math/Numeric.one:()Ljava/lang/Object;
   #68 = Utf8               <init>
   #69 = Utf8               (Ljava/lang/Object;Ljava/lang/Object;Ljava/lang/Object;Lscala/math/Integral;)V
   #70 = NameAndType        #68:#69       // "<init>":(Ljava/lang/Object;Ljava/lang/Object;Ljava/lang/Object;Lscala/math/Integral;)V
   #71 = Methodref          #24.#70       // scala/collection/immutable/NumericRange$Exclusive."<init>":(Ljava/lang/Object;Ljava/lang/Object;Ljava/lang/Object;Lscala/math/Integral;)V
   #72 = Utf8               from
   #73 = Utf8               (Lscala/collection/IterableOnce;Ljava/lang/Object;)Ljava/lang/Object;
   #74 = NameAndType        #72:#73       // from:(Lscala/collection/IterableOnce;Ljava/lang/Object;)Ljava/lang/Object;
   #75 = InterfaceMethodref #2.#74        // scala/collection/ClassTagIterableFactory.from:(Lscala/collection/IterableOnce;Ljava/lang/Object;)Ljava/lang/Object;
   #76 = Utf8               apply_step
   #77 = Utf8               (Lscala/collection/ClassTagIterableFactory;Ljava/lang/Object;Ljava/lang/Object;Ljava/lang/Object;Lscala/math/Integral;Lscala/reflect/ClassTag;)Ljava/lang/Object;
   #78 = Utf8               step
   #79 = Utf8               evidence$24
   #80 = Utf8               evidence$25
   #81 = Utf8               (Ljava/lang/Object;Ljava/lang/Object;Ljava/lang/Object;Lscala/math/Integral;Lscala/reflect/ClassTag;)Ljava/lang/Object;
   #82 = NameAndType        #49:#81       // range:(Ljava/lang/Object;Ljava/lang/Object;Ljava/lang/Object;Lscala/math/Integral;Lscala/reflect/ClassTag;)Ljava/lang/Object;
   #83 = InterfaceMethodref #2.#82        // scala/collection/ClassTagIterableFactory.range:(Ljava/lang/Object;Ljava/lang/Object;Ljava/lang/Object;Lscala/math/Integral;Lscala/reflect/ClassTag;)Ljava/lang/Object;
   #84 = Utf8               <A:Ljava/lang/Object;>(TA;TA;TA;Lscala/math/Integral<TA;>;Lscala/reflect/ClassTag<TA;>;)TCC;
   #85 = Utf8               fill$
   #86 = Utf8               (Lscala/collection/ClassTagIterableFactory;IILscala/Function0;Lscala/reflect/ClassTag;)Ljava/lang/Object;
   #87 = Utf8               n1
   #88 = Utf8               n2
   #89 = Utf8               elem
   #90 = Utf8               evidence$26
   #91 = Utf8               fill
   #92 = Utf8               (IILscala/Function0;Lscala/reflect/ClassTag;)Ljava/lang/Object;
   #93 = NameAndType        #91:#92       // fill:(IILscala/Function0;Lscala/reflect/ClassTag;)Ljava/lang/Object;
   #94 = InterfaceMethodref #2.#93        // scala/collection/ClassTagIterableFactory.fill:(IILscala/Function0;Lscala/reflect/ClassTag;)Ljava/lang/Object;
   #95 = Utf8               I
   #96 = Utf8               Lscala/Function0;
   #97 = Utf8               <A:Ljava/lang/Object;>(IILscala/Function0<TA;>;Lscala/reflect/ClassTag<TA;>;)TCC;
   #98 = MethodType         #65           //  ()Ljava/lang/Object;
   #99 = Utf8               $anonfun$fill$5
  #100 = Utf8               (Lscala/collection/ClassTagIterableFactory;ILscala/Function0;Lscala/reflect/ClassTag;)Ljava/lang/Object;
  #101 = NameAndType        #99:#100      // $anonfun$fill$5:(Lscala/collection/ClassTagIterableFactory;ILscala/Function0;Lscala/reflect/ClassTag;)Ljava/lang/Object;
  #102 = InterfaceMethodref #2.#101       // scala/collection/ClassTagIterableFactory.$anonfun$fill$5:(Lscala/collection/ClassTagIterableFactory;ILscala/Function0;Lscala/reflect/ClassTag;)Ljava/lang/Object;
  #103 = MethodHandle       6:#102        // REF_invokeStatic scala/collection/ClassTagIterableFactory.$anonfun$fill$5:(Lscala/collection/ClassTagIterableFactory;ILscala/Function0;Lscala/reflect/ClassTag;)Ljava/lang/Object;
  #104 = Integer            1
  #105 = Utf8               java/lang/invoke/LambdaMetafactory
  #106 = Class              #105          // java/lang/invoke/LambdaMetafactory
  #107 = Utf8               altMetafactory
  #108 = Utf8               (Ljava/lang/invoke/MethodHandles$Lookup;Ljava/lang/String;Ljava/lang/invoke/MethodType;[Ljava/lang/Object;)Ljava/lang/invoke/CallSite;
  #109 = NameAndType        #107:#108     // altMetafactory:(Ljava/lang/invoke/MethodHandles$Lookup;Ljava/lang/String;Ljava/lang/invoke/MethodType;[Ljava/lang/Object;)Ljava/lang/invoke/CallSite;
  #110 = Methodref          #106.#109     // java/lang/invoke/LambdaMetafactory.altMetafactory:(Ljava/lang/invoke/MethodHandles$Lookup;Ljava/lang/String;Ljava/lang/invoke/MethodType;[Ljava/lang/Object;)Ljava/lang/invoke/CallSite;
  #111 = MethodHandle       6:#110        // REF_invokeStatic java/lang/invoke/LambdaMetafactory.altMetafactory:(Ljava/lang/invoke/MethodHandles$Lookup;Ljava/lang/String;Ljava/lang/invoke/MethodType;[Ljava/lang/Object;)Ljava/lang/invoke/CallSite;
  #112 = Utf8               apply
  #113 = Utf8               (Lscala/collection/ClassTagIterableFactory;ILscala/Function0;Lscala/reflect/ClassTag;)Lscala/Function0;
  #114 = NameAndType        #112:#113     // apply:(Lscala/collection/ClassTagIterableFactory;ILscala/Function0;Lscala/reflect/ClassTag;)Lscala/Function0;
  #115 = InvokeDynamic      #0:#114       // #0:apply:(Lscala/collection/ClassTagIterableFactory;ILscala/Function0;Lscala/reflect/ClassTag;)Lscala/Function0;
  #116 = Utf8               (ILscala/Function0;Ljava/lang/Object;)Ljava/lang/Object;
  #117 = NameAndType        #91:#116      // fill:(ILscala/Function0;Ljava/lang/Object;)Ljava/lang/Object;
  #118 = InterfaceMethodref #2.#117       // scala/collection/ClassTagIterableFactory.fill:(ILscala/Function0;Ljava/lang/Object;)Ljava/lang/Object;
  #119 = Utf8               (Lscala/collection/ClassTagIterableFactory;IIILscala/Function0;Lscala/reflect/ClassTag;)Ljava/lang/Object;
  #120 = Utf8               n3
  #121 = Utf8               evidence$27
  #122 = Utf8               (IIILscala/Function0;Lscala/reflect/ClassTag;)Ljava/lang/Object;
  #123 = NameAndType        #91:#122      // fill:(IIILscala/Function0;Lscala/reflect/ClassTag;)Ljava/lang/Object;
  #124 = InterfaceMethodref #2.#123       // scala/collection/ClassTagIterableFactory.fill:(IIILscala/Function0;Lscala/reflect/ClassTag;)Ljava/lang/Object;
  #125 = Utf8               <A:Ljava/lang/Object;>(IIILscala/Function0<TA;>;Lscala/reflect/ClassTag<TA;>;)TCC;
  #126 = Utf8               $anonfun$fill$6
  #127 = NameAndType        #126:#86      // $anonfun$fill$6:(Lscala/collection/ClassTagIterableFactory;IILscala/Function0;Lscala/reflect/ClassTag;)Ljava/lang/Object;
  #128 = InterfaceMethodref #2.#127       // scala/collection/ClassTagIterableFactory.$anonfun$fill$6:(Lscala/collection/ClassTagIterableFactory;IILscala/Function0;Lscala/reflect/ClassTag;)Ljava/lang/Object;
  #129 = MethodHandle       6:#128        // REF_invokeStatic scala/collection/ClassTagIterableFactory.$anonfun$fill$6:(Lscala/collection/ClassTagIterableFactory;IILscala/Function0;Lscala/reflect/ClassTag;)Ljava/lang/Object;
  #130 = Utf8               (Lscala/collection/ClassTagIterableFactory;IILscala/Function0;Lscala/reflect/ClassTag;)Lscala/Function0;
  #131 = NameAndType        #112:#130     // apply:(Lscala/collection/ClassTagIterableFactory;IILscala/Function0;Lscala/reflect/ClassTag;)Lscala/Function0;
  #132 = InvokeDynamic      #1:#131       // #1:apply:(Lscala/collection/ClassTagIterableFactory;IILscala/Function0;Lscala/reflect/ClassTag;)Lscala/Function0;
  #133 = Utf8               (Lscala/collection/ClassTagIterableFactory;IIIILscala/Function0;Lscala/reflect/ClassTag;)Ljava/lang/Object;
  #134 = Utf8               n4
  #135 = Utf8               evidence$28
  #136 = Utf8               (IIIILscala/Function0;Lscala/reflect/ClassTag;)Ljava/lang/Object;
  #137 = NameAndType        #91:#136      // fill:(IIIILscala/Function0;Lscala/reflect/ClassTag;)Ljava/lang/Object;
  #138 = InterfaceMethodref #2.#137       // scala/collection/ClassTagIterableFactory.fill:(IIIILscala/Function0;Lscala/reflect/ClassTag;)Ljava/lang/Object;
  #139 = Utf8               <A:Ljava/lang/Object;>(IIIILscala/Function0<TA;>;Lscala/reflect/ClassTag<TA;>;)TCC;
  #140 = Utf8               $anonfun$fill$7
  #141 = NameAndType        #140:#119     // $anonfun$fill$7:(Lscala/collection/ClassTagIterableFactory;IIILscala/Function0;Lscala/reflect/ClassTag;)Ljava/lang/Object;
  #142 = InterfaceMethodref #2.#141       // scala/collection/ClassTagIterableFactory.$anonfun$fill$7:(Lscala/collection/ClassTagIterableFactory;IIILscala/Function0;Lscala/reflect/ClassTag;)Ljava/lang/Object;
  #143 = MethodHandle       6:#142        // REF_invokeStatic scala/collection/ClassTagIterableFactory.$anonfun$fill$7:(Lscala/collection/ClassTagIterableFactory;IIILscala/Function0;Lscala/reflect/ClassTag;)Ljava/lang/Object;
  #144 = Utf8               (Lscala/collection/ClassTagIterableFactory;IIILscala/Function0;Lscala/reflect/ClassTag;)Lscala/Function0;
  #145 = NameAndType        #112:#144     // apply:(Lscala/collection/ClassTagIterableFactory;IIILscala/Function0;Lscala/reflect/ClassTag;)Lscala/Function0;
  #146 = InvokeDynamic      #2:#145       // #2:apply:(Lscala/collection/ClassTagIterableFactory;IIILscala/Function0;Lscala/reflect/ClassTag;)Lscala/Function0;
  #147 = Utf8               (Lscala/collection/ClassTagIterableFactory;IIIIILscala/Function0;Lscala/reflect/ClassTag;)Ljava/lang/Object;
  #148 = Utf8               n5
  #149 = Utf8               evidence$29
  #150 = Utf8               (IIIIILscala/Function0;Lscala/reflect/ClassTag;)Ljava/lang/Object;
  #151 = NameAndType        #91:#150      // fill:(IIIIILscala/Function0;Lscala/reflect/ClassTag;)Ljava/lang/Object;
  #152 = InterfaceMethodref #2.#151       // scala/collection/ClassTagIterableFactory.fill:(IIIIILscala/Function0;Lscala/reflect/ClassTag;)Ljava/lang/Object;
  #153 = Utf8               <A:Ljava/lang/Object;>(IIIIILscala/Function0<TA;>;Lscala/reflect/ClassTag<TA;>;)TCC;
  #154 = Utf8               $anonfun$fill$8
  #155 = NameAndType        #154:#133     // $anonfun$fill$8:(Lscala/collection/ClassTagIterableFactory;IIIILscala/Function0;Lscala/reflect/ClassTag;)Ljava/lang/Object;
  #156 = InterfaceMethodref #2.#155       // scala/collection/ClassTagIterableFactory.$anonfun$fill$8:(Lscala/collection/ClassTagIterableFactory;IIIILscala/Function0;Lscala/reflect/ClassTag;)Ljava/lang/Object;
  #157 = MethodHandle       6:#156        // REF_invokeStatic scala/collection/ClassTagIterableFactory.$anonfun$fill$8:(Lscala/collection/ClassTagIterableFactory;IIIILscala/Function0;Lscala/reflect/ClassTag;)Ljava/lang/Object;
  #158 = Utf8               (Lscala/collection/ClassTagIterableFactory;IIIILscala/Function0;Lscala/reflect/ClassTag;)Lscala/Function0;
  #159 = NameAndType        #112:#158     // apply:(Lscala/collection/ClassTagIterableFactory;IIIILscala/Function0;Lscala/reflect/ClassTag;)Lscala/Function0;
  #160 = InvokeDynamic      #3:#159       // #3:apply:(Lscala/collection/ClassTagIterableFactory;IIIILscala/Function0;Lscala/reflect/ClassTag;)Lscala/Function0;
  #161 = Utf8               tabulate$
  #162 = Utf8               (Lscala/collection/ClassTagIterableFactory;IILscala/Function2;Lscala/reflect/ClassTag;)Ljava/lang/Object;
  #163 = Utf8               f
  #164 = Utf8               evidence$30
  #165 = Utf8               tabulate
  #166 = Utf8               (IILscala/Function2;Lscala/reflect/ClassTag;)Ljava/lang/Object;
  #167 = NameAndType        #165:#166     // tabulate:(IILscala/Function2;Lscala/reflect/ClassTag;)Ljava/lang/Object;
  #168 = InterfaceMethodref #2.#167       // scala/collection/ClassTagIterableFactory.tabulate:(IILscala/Function2;Lscala/reflect/ClassTag;)Ljava/lang/Object;
  #169 = Utf8               Lscala/Function2;
  #170 = Utf8               <A:Ljava/lang/Object;>(IILscala/Function2<Ljava/lang/Object;Ljava/lang/Object;TA;>;Lscala/reflect/ClassTag<TA;>;)TCC;
  #171 = Utf8               (Ljava/lang/Object;)Ljava/lang/Object;
  #172 = MethodType         #171          //  (Ljava/lang/Object;)Ljava/lang/Object;
  #173 = Utf8               $anonfun$tabulate$9$adapted
  #174 = Utf8               (Lscala/collection/ClassTagIterableFactory;ILscala/Function2;Lscala/reflect/ClassTag;Ljava/lang/Object;)Ljava/lang/Object;
  #175 = NameAndType        #173:#174     // $anonfun$tabulate$9$adapted:(Lscala/collection/ClassTagIterableFactory;ILscala/Function2;Lscala/reflect/ClassTag;Ljava/lang/Object;)Ljava/lang/Object;
  #176 = InterfaceMethodref #2.#175       // scala/collection/ClassTagIterableFactory.$anonfun$tabulate$9$adapted:(Lscala/collection/ClassTagIterableFactory;ILscala/Function2;Lscala/reflect/ClassTag;Ljava/lang/Object;)Ljava/lang/Object;
  #177 = MethodHandle       6:#176        // REF_invokeStatic scala/collection/ClassTagIterableFactory.$anonfun$tabulate$9$adapted:(Lscala/collection/ClassTagIterableFactory;ILscala/Function2;Lscala/reflect/ClassTag;Ljava/lang/Object;)Ljava/lang/Object;
  #178 = Utf8               (Lscala/collection/ClassTagIterableFactory;ILscala/Function2;Lscala/reflect/ClassTag;)Lscala/Function1;
  #179 = NameAndType        #112:#178     // apply:(Lscala/collection/ClassTagIterableFactory;ILscala/Function2;Lscala/reflect/ClassTag;)Lscala/Function1;
  #180 = InvokeDynamic      #4:#179       // #4:apply:(Lscala/collection/ClassTagIterableFactory;ILscala/Function2;Lscala/reflect/ClassTag;)Lscala/Function1;
  #181 = Utf8               (ILscala/Function1;Ljava/lang/Object;)Ljava/lang/Object;
  #182 = NameAndType        #165:#181     // tabulate:(ILscala/Function1;Ljava/lang/Object;)Ljava/lang/Object;
  #183 = InterfaceMethodref #2.#182       // scala/collection/ClassTagIterableFactory.tabulate:(ILscala/Function1;Ljava/lang/Object;)Ljava/lang/Object;
  #184 = Utf8               (Lscala/collection/ClassTagIterableFactory;IIILscala/Function3;Lscala/reflect/ClassTag;)Ljava/lang/Object;
  #185 = Utf8               evidence$31
  #186 = Utf8               (IIILscala/Function3;Lscala/reflect/ClassTag;)Ljava/lang/Object;
  #187 = NameAndType        #165:#186     // tabulate:(IIILscala/Function3;Lscala/reflect/ClassTag;)Ljava/lang/Object;
  #188 = InterfaceMethodref #2.#187       // scala/collection/ClassTagIterableFactory.tabulate:(IIILscala/Function3;Lscala/reflect/ClassTag;)Ljava/lang/Object;
  #189 = Utf8               Lscala/Function3;
  #190 = Utf8               <A:Ljava/lang/Object;>(IIILscala/Function3<Ljava/lang/Object;Ljava/lang/Object;Ljava/lang/Object;TA;>;Lscala/reflect/ClassTag<TA;>;)TCC;
  #191 = Utf8               $anonfun$tabulate$11$adapted
  #192 = Utf8               (Lscala/collection/ClassTagIterableFactory;IILscala/Function3;Lscala/reflect/ClassTag;Ljava/lang/Object;)Ljava/lang/Object;
  #193 = NameAndType        #191:#192     // $anonfun$tabulate$11$adapted:(Lscala/collection/ClassTagIterableFactory;IILscala/Function3;Lscala/reflect/ClassTag;Ljava/lang/Object;)Ljava/lang/Object;
  #194 = InterfaceMethodref #2.#193       // scala/collection/ClassTagIterableFactory.$anonfun$tabulate$11$adapted:(Lscala/collection/ClassTagIterableFactory;IILscala/Function3;Lscala/reflect/ClassTag;Ljava/lang/Object;)Ljava/lang/Object;
  #195 = MethodHandle       6:#194        // REF_invokeStatic scala/collection/ClassTagIterableFactory.$anonfun$tabulate$11$adapted:(Lscala/collection/ClassTagIterableFactory;IILscala/Function3;Lscala/reflect/ClassTag;Ljava/lang/Object;)Ljava/lang/Object;
  #196 = Utf8               (Lscala/collection/ClassTagIterableFactory;IILscala/Function3;Lscala/reflect/ClassTag;)Lscala/Function1;
  #197 = NameAndType        #112:#196     // apply:(Lscala/collection/ClassTagIterableFactory;IILscala/Function3;Lscala/reflect/ClassTag;)Lscala/Function1;
  #198 = InvokeDynamic      #5:#197       // #5:apply:(Lscala/collection/ClassTagIterableFactory;IILscala/Function3;Lscala/reflect/ClassTag;)Lscala/Function1;
  #199 = Utf8               (Lscala/collection/ClassTagIterableFactory;IIIILscala/Function4;Lscala/reflect/ClassTag;)Ljava/lang/Object;
  #200 = Utf8               evidence$32
  #201 = Utf8               (IIIILscala/Function4;Lscala/reflect/ClassTag;)Ljava/lang/Object;
  #202 = NameAndType        #165:#201     // tabulate:(IIIILscala/Function4;Lscala/reflect/ClassTag;)Ljava/lang/Object;
  #203 = InterfaceMethodref #2.#202       // scala/collection/ClassTagIterableFactory.tabulate:(IIIILscala/Function4;Lscala/reflect/ClassTag;)Ljava/lang/Object;
  #204 = Utf8               Lscala/Function4;
  #205 = Utf8               <A:Ljava/lang/Object;>(IIIILscala/Function4<Ljava/lang/Object;Ljava/lang/Object;Ljava/lang/Object;Ljava/lang/Object;TA;>;Lscala/reflect/ClassTag<TA;>;)TCC;
  #206 = Utf8               $anonfun$tabulate$13$adapted
  #207 = Utf8               (Lscala/collection/ClassTagIterableFactory;IIILscala/Function4;Lscala/reflect/ClassTag;Ljava/lang/Object;)Ljava/lang/Object;
  #208 = NameAndType        #206:#207     // $anonfun$tabulate$13$adapted:(Lscala/collection/ClassTagIterableFactory;IIILscala/Function4;Lscala/reflect/ClassTag;Ljava/lang/Object;)Ljava/lang/Object;
  #209 = InterfaceMethodref #2.#208       // scala/collection/ClassTagIterableFactory.$anonfun$tabulate$13$adapted:(Lscala/collection/ClassTagIterableFactory;IIILscala/Function4;Lscala/reflect/ClassTag;Ljava/lang/Object;)Ljava/lang/Object;
  #210 = MethodHandle       6:#209        // REF_invokeStatic scala/collection/ClassTagIterableFactory.$anonfun$tabulate$13$adapted:(Lscala/collection/ClassTagIterableFactory;IIILscala/Function4;Lscala/reflect/ClassTag;Ljava/lang/Object;)Ljava/lang/Object;
  #211 = Utf8               (Lscala/collection/ClassTagIterableFactory;IIILscala/Function4;Lscala/reflect/ClassTag;)Lscala/Function1;
  #212 = NameAndType        #112:#211     // apply:(Lscala/collection/ClassTagIterableFactory;IIILscala/Function4;Lscala/reflect/ClassTag;)Lscala/Function1;
  #213 = InvokeDynamic      #6:#212       // #6:apply:(Lscala/collection/ClassTagIterableFactory;IIILscala/Function4;Lscala/reflect/ClassTag;)Lscala/Function1;
  #214 = Utf8               (Lscala/collection/ClassTagIterableFactory;IIIIILscala/Function5;Lscala/reflect/ClassTag;)Ljava/lang/Object;
  #215 = Utf8               evidence$33
  #216 = Utf8               (IIIIILscala/Function5;Lscala/reflect/ClassTag;)Ljava/lang/Object;
  #217 = NameAndType        #165:#216     // tabulate:(IIIIILscala/Function5;Lscala/reflect/ClassTag;)Ljava/lang/Object;
  #218 = InterfaceMethodref #2.#217       // scala/collection/ClassTagIterableFactory.tabulate:(IIIIILscala/Function5;Lscala/reflect/ClassTag;)Ljava/lang/Object;
  #219 = Utf8               Lscala/Function5;
  #220 = Utf8               <A:Ljava/lang/Object;>(IIIIILscala/Function5<Ljava/lang/Object;Ljava/lang/Object;Ljava/lang/Object;Ljava/lang/Object;Ljava/lang/Object;TA;>;Lscala/reflect/ClassTag<TA;>;)TCC;
  #221 = Utf8               $anonfun$tabulate$15$adapted
  #222 = Utf8               (Lscala/collection/ClassTagIterableFactory;IIIILscala/Function5;Lscala/reflect/ClassTag;Ljava/lang/Object;)Ljava/lang/Object;
  #223 = NameAndType        #221:#222     // $anonfun$tabulate$15$adapted:(Lscala/collection/ClassTagIterableFactory;IIIILscala/Function5;Lscala/reflect/ClassTag;Ljava/lang/Object;)Ljava/lang/Object;
  #224 = InterfaceMethodref #2.#223       // scala/collection/ClassTagIterableFactory.$anonfun$tabulate$15$adapted:(Lscala/collection/ClassTagIterableFactory;IIIILscala/Function5;Lscala/reflect/ClassTag;Ljava/lang/Object;)Ljava/lang/Object;
  #225 = MethodHandle       6:#224        // REF_invokeStatic scala/collection/ClassTagIterableFactory.$anonfun$tabulate$15$adapted:(Lscala/collection/ClassTagIterableFactory;IIIILscala/Function5;Lscala/reflect/ClassTag;Ljava/lang/Object;)Ljava/lang/Object;
  #226 = Utf8               (Lscala/collection/ClassTagIterableFactory;IIIILscala/Function5;Lscala/reflect/ClassTag;)Lscala/Function1;
  #227 = NameAndType        #112:#226     // apply:(Lscala/collection/ClassTagIterableFactory;IIIILscala/Function5;Lscala/reflect/ClassTag;)Lscala/Function1;
  #228 = InvokeDynamic      #7:#227       // #7:apply:(Lscala/collection/ClassTagIterableFactory;IIIILscala/Function5;Lscala/reflect/ClassTag;)Lscala/Function1;
  #229 = Utf8               n2$9
  #230 = Utf8               elem$5
  #231 = Utf8               evidence$26$1
  #232 = Utf8               n2$10
  #233 = Utf8               n3$7
  #234 = Utf8               elem$6
  #235 = Utf8               evidence$27$1
  #236 = Utf8               n2$11
  #237 = Utf8               n3$8
  #238 = Utf8               n4$5
  #239 = Utf8               elem$7
  #240 = Utf8               evidence$28$1
  #241 = Utf8               n2$12
  #242 = Utf8               n3$9
  #243 = Utf8               n4$6
  #244 = Utf8               n5$3
  #245 = Utf8               elem$8
  #246 = Utf8               evidence$29$1
  #247 = Utf8               $anonfun$tabulate$10
  #248 = Utf8               (Lscala/Function2;II)Ljava/lang/Object;
  #249 = Utf8               f$5
  #250 = Utf8               i1$5
  #251 = Utf8               x$15
  #252 = Utf8               scala/runtime/BoxesRunTime
  #253 = Class              #252          // scala/runtime/BoxesRunTime
  #254 = Utf8               boxToInteger
  #255 = Utf8               (I)Ljava/lang/Integer;
  #256 = NameAndType        #254:#255     // boxToInteger:(I)Ljava/lang/Integer;
  #257 = Methodref          #253.#256     // scala/runtime/BoxesRunTime.boxToInteger:(I)Ljava/lang/Integer;
  #258 = Utf8               scala/Function2
  #259 = Class              #258          // scala/Function2
  #260 = Utf8               (Ljava/lang/Object;Ljava/lang/Object;)Ljava/lang/Object;
  #261 = NameAndType        #112:#260     // apply:(Ljava/lang/Object;Ljava/lang/Object;)Ljava/lang/Object;
  #262 = InterfaceMethodref #259.#261     // scala/Function2.apply:(Ljava/lang/Object;Ljava/lang/Object;)Ljava/lang/Object;
  #263 = Utf8               $anonfun$tabulate$9
  #264 = Utf8               (Lscala/collection/ClassTagIterableFactory;ILscala/Function2;Lscala/reflect/ClassTag;I)Ljava/lang/Object;
  #265 = Utf8               n2$13
  #266 = Utf8               evidence$30$1
  #267 = Utf8               i1
  #268 = Utf8               $anonfun$tabulate$10$adapted
  #269 = Utf8               (Lscala/Function2;ILjava/lang/Object;)Ljava/lang/Object;
  #270 = NameAndType        #268:#269     // $anonfun$tabulate$10$adapted:(Lscala/Function2;ILjava/lang/Object;)Ljava/lang/Object;
  #271 = InterfaceMethodref #2.#270       // scala/collection/ClassTagIterableFactory.$anonfun$tabulate$10$adapted:(Lscala/Function2;ILjava/lang/Object;)Ljava/lang/Object;
  #272 = MethodHandle       6:#271        // REF_invokeStatic scala/collection/ClassTagIterableFactory.$anonfun$tabulate$10$adapted:(Lscala/Function2;ILjava/lang/Object;)Ljava/lang/Object;
  #273 = Utf8               (Lscala/Function2;I)Lscala/Function1;
  #274 = NameAndType        #112:#273     // apply:(Lscala/Function2;I)Lscala/Function1;
  #275 = InvokeDynamic      #8:#274       // #8:apply:(Lscala/Function2;I)Lscala/Function1;
  #276 = Utf8               $anonfun$tabulate$12
  #277 = Utf8               (Lscala/Function3;III)Ljava/lang/Object;
  #278 = Utf8               f$6
  #279 = Utf8               i1$6
  #280 = Utf8               x$16
  #281 = Utf8               x$17
  #282 = Utf8               scala/Function3
  #283 = Class              #282          // scala/Function3
  #284 = Utf8               (Ljava/lang/Object;Ljava/lang/Object;Ljava/lang/Object;)Ljava/lang/Object;
  #285 = NameAndType        #112:#284     // apply:(Ljava/lang/Object;Ljava/lang/Object;Ljava/lang/Object;)Ljava/lang/Object;
  #286 = InterfaceMethodref #283.#285     // scala/Function3.apply:(Ljava/lang/Object;Ljava/lang/Object;Ljava/lang/Object;)Ljava/lang/Object;
  #287 = Utf8               $anonfun$tabulate$11
  #288 = Utf8               (Lscala/collection/ClassTagIterableFactory;IILscala/Function3;Lscala/reflect/ClassTag;I)Ljava/lang/Object;
  #289 = Utf8               n2$14
  #290 = Utf8               n3$10
  #291 = Utf8               evidence$31$1
  #292 = MethodType         #260          //  (Ljava/lang/Object;Ljava/lang/Object;)Ljava/lang/Object;
  #293 = Utf8               $anonfun$tabulate$12$adapted
  #294 = Utf8               (Lscala/Function3;ILjava/lang/Object;Ljava/lang/Object;)Ljava/lang/Object;
  #295 = NameAndType        #293:#294     // $anonfun$tabulate$12$adapted:(Lscala/Function3;ILjava/lang/Object;Ljava/lang/Object;)Ljava/lang/Object;
  #296 = InterfaceMethodref #2.#295       // scala/collection/ClassTagIterableFactory.$anonfun$tabulate$12$adapted:(Lscala/Function3;ILjava/lang/Object;Ljava/lang/Object;)Ljava/lang/Object;
  #297 = MethodHandle       6:#296        // REF_invokeStatic scala/collection/ClassTagIterableFactory.$anonfun$tabulate$12$adapted:(Lscala/Function3;ILjava/lang/Object;Ljava/lang/Object;)Ljava/lang/Object;
  #298 = Utf8               (Lscala/Function3;I)Lscala/Function2;
  #299 = NameAndType        #112:#298     // apply:(Lscala/Function3;I)Lscala/Function2;
  #300 = InvokeDynamic      #9:#299       // #9:apply:(Lscala/Function3;I)Lscala/Function2;
  #301 = Utf8               $anonfun$tabulate$14
  #302 = Utf8               (Lscala/Function4;IIII)Ljava/lang/Object;
  #303 = Utf8               f$7
  #304 = Utf8               i1$7
  #305 = Utf8               x$18
  #306 = Utf8               x$19
  #307 = Utf8               x$20
  #308 = Utf8               scala/Function4
  #309 = Class              #308          // scala/Function4
  #310 = Utf8               (Ljava/lang/Object;Ljava/lang/Object;Ljava/lang/Object;Ljava/lang/Object;)Ljava/lang/Object;
  #311 = NameAndType        #112:#310     // apply:(Ljava/lang/Object;Ljava/lang/Object;Ljava/lang/Object;Ljava/lang/Object;)Ljava/lang/Object;
  #312 = InterfaceMethodref #309.#311     // scala/Function4.apply:(Ljava/lang/Object;Ljava/lang/Object;Ljava/lang/Object;Ljava/lang/Object;)Ljava/lang/Object;
  #313 = Utf8               $anonfun$tabulate$13
  #314 = Utf8               (Lscala/collection/ClassTagIterableFactory;IIILscala/Function4;Lscala/reflect/ClassTag;I)Ljava/lang/Object;
  #315 = Utf8               n2$15
  #316 = Utf8               n3$11
  #317 = Utf8               n4$7
  #318 = Utf8               evidence$32$1
  #319 = MethodType         #284          //  (Ljava/lang/Object;Ljava/lang/Object;Ljava/lang/Object;)Ljava/lang/Object;
  #320 = Utf8               $anonfun$tabulate$14$adapted
  #321 = Utf8               (Lscala/Function4;ILjava/lang/Object;Ljava/lang/Object;Ljava/lang/Object;)Ljava/lang/Object;
  #322 = NameAndType        #320:#321     // $anonfun$tabulate$14$adapted:(Lscala/Function4;ILjava/lang/Object;Ljava/lang/Object;Ljava/lang/Object;)Ljava/lang/Object;
  #323 = InterfaceMethodref #2.#322       // scala/collection/ClassTagIterableFactory.$anonfun$tabulate$14$adapted:(Lscala/Function4;ILjava/lang/Object;Ljava/lang/Object;Ljava/lang/Object;)Ljava/lang/Object;
  #324 = MethodHandle       6:#323        // REF_invokeStatic scala/collection/ClassTagIterableFactory.$anonfun$tabulate$14$adapted:(Lscala/Function4;ILjava/lang/Object;Ljava/lang/Object;Ljava/lang/Object;)Ljava/lang/Object;
  #325 = Utf8               (Lscala/Function4;I)Lscala/Function3;
  #326 = NameAndType        #112:#325     // apply:(Lscala/Function4;I)Lscala/Function3;
  #327 = InvokeDynamic      #10:#326      // #10:apply:(Lscala/Function4;I)Lscala/Function3;
  #328 = Utf8               $anonfun$tabulate$16
  #329 = Utf8               (Lscala/Function5;IIIII)Ljava/lang/Object;
  #330 = Utf8               f$8
  #331 = Utf8               i1$8
  #332 = Utf8               x$21
  #333 = Utf8               x$22
  #334 = Utf8               x$23
  #335 = Utf8               x$24
  #336 = Utf8               scala/Function5
  #337 = Class              #336          // scala/Function5
  #338 = Utf8               (Ljava/lang/Object;Ljava/lang/Object;Ljava/lang/Object;Ljava/lang/Object;Ljava/lang/Object;)Ljava/lang/Object;
  #339 = NameAndType        #112:#338     // apply:(Ljava/lang/Object;Ljava/lang/Object;Ljava/lang/Object;Ljava/lang/Object;Ljava/lang/Object;)Ljava/lang/Object;
  #340 = InterfaceMethodref #337.#339     // scala/Function5.apply:(Ljava/lang/Object;Ljava/lang/Object;Ljava/lang/Object;Ljava/lang/Object;Ljava/lang/Object;)Ljava/lang/Object;
  #341 = Utf8               $anonfun$tabulate$15
  #342 = Utf8               (Lscala/collection/ClassTagIterableFactory;IIIILscala/Function5;Lscala/reflect/ClassTag;I)Ljava/lang/Object;
  #343 = Utf8               n2$16
  #344 = Utf8               n3$12
  #345 = Utf8               n4$8
  #346 = Utf8               n5$4
  #347 = Utf8               evidence$33$1
  #348 = MethodType         #310          //  (Ljava/lang/Object;Ljava/lang/Object;Ljava/lang/Object;Ljava/lang/Object;)Ljava/lang/Object;
  #349 = Utf8               $anonfun$tabulate$16$adapted
  #350 = Utf8               (Lscala/Function5;ILjava/lang/Object;Ljava/lang/Object;Ljava/lang/Object;Ljava/lang/Object;)Ljava/lang/Object;
  #351 = NameAndType        #349:#350     // $anonfun$tabulate$16$adapted:(Lscala/Function5;ILjava/lang/Object;Ljava/lang/Object;Ljava/lang/Object;Ljava/lang/Object;)Ljava/lang/Object;
  #352 = InterfaceMethodref #2.#351       // scala/collection/ClassTagIterableFactory.$anonfun$tabulate$16$adapted:(Lscala/Function5;ILjava/lang/Object;Ljava/lang/Object;Ljava/lang/Object;Ljava/lang/Object;)Ljava/lang/Object;
  #353 = MethodHandle       6:#352        // REF_invokeStatic scala/collection/ClassTagIterableFactory.$anonfun$tabulate$16$adapted:(Lscala/Function5;ILjava/lang/Object;Ljava/lang/Object;Ljava/lang/Object;Ljava/lang/Object;)Ljava/lang/Object;
  #354 = Utf8               (Lscala/Function5;I)Lscala/Function4;
  #355 = NameAndType        #112:#354     // apply:(Lscala/Function5;I)Lscala/Function4;
  #356 = InvokeDynamic      #11:#355      // #11:apply:(Lscala/Function5;I)Lscala/Function4;
  #357 = Utf8               $init$
  #358 = Utf8               (Lscala/collection/ClassTagIterableFactory;)V
  #359 = Utf8               unboxToInt
  #360 = Utf8               (Ljava/lang/Object;)I
  #361 = NameAndType        #359:#360     // unboxToInt:(Ljava/lang/Object;)I
  #362 = Methodref          #253.#361     // scala/runtime/BoxesRunTime.unboxToInt:(Ljava/lang/Object;)I
  #363 = NameAndType        #263:#264     // $anonfun$tabulate$9:(Lscala/collection/ClassTagIterableFactory;ILscala/Function2;Lscala/reflect/ClassTag;I)Ljava/lang/Object;
  #364 = InterfaceMethodref #2.#363       // scala/collection/ClassTagIterableFactory.$anonfun$tabulate$9:(Lscala/collection/ClassTagIterableFactory;ILscala/Function2;Lscala/reflect/ClassTag;I)Ljava/lang/Object;
  #365 = NameAndType        #287:#288     // $anonfun$tabulate$11:(Lscala/collection/ClassTagIterableFactory;IILscala/Function3;Lscala/reflect/ClassTag;I)Ljava/lang/Object;
  #366 = InterfaceMethodref #2.#365       // scala/collection/ClassTagIterableFactory.$anonfun$tabulate$11:(Lscala/collection/ClassTagIterableFactory;IILscala/Function3;Lscala/reflect/ClassTag;I)Ljava/lang/Object;
  #367 = NameAndType        #313:#314     // $anonfun$tabulate$13:(Lscala/collection/ClassTagIterableFactory;IIILscala/Function4;Lscala/reflect/ClassTag;I)Ljava/lang/Object;
  #368 = InterfaceMethodref #2.#367       // scala/collection/ClassTagIterableFactory.$anonfun$tabulate$13:(Lscala/collection/ClassTagIterableFactory;IIILscala/Function4;Lscala/reflect/ClassTag;I)Ljava/lang/Object;
  #369 = NameAndType        #341:#342     // $anonfun$tabulate$15:(Lscala/collection/ClassTagIterableFactory;IIIILscala/Function5;Lscala/reflect/ClassTag;I)Ljava/lang/Object;
  #370 = InterfaceMethodref #2.#369       // scala/collection/ClassTagIterableFactory.$anonfun$tabulate$15:(Lscala/collection/ClassTagIterableFactory;IIIILscala/Function5;Lscala/reflect/ClassTag;I)Ljava/lang/Object;
  #371 = NameAndType        #247:#248     // $anonfun$tabulate$10:(Lscala/Function2;II)Ljava/lang/Object;
  #372 = InterfaceMethodref #2.#371       // scala/collection/ClassTagIterableFactory.$anonfun$tabulate$10:(Lscala/Function2;II)Ljava/lang/Object;
  #373 = NameAndType        #276:#277     // $anonfun$tabulate$12:(Lscala/Function3;III)Ljava/lang/Object;
  #374 = InterfaceMethodref #2.#373       // scala/collection/ClassTagIterableFactory.$anonfun$tabulate$12:(Lscala/Function3;III)Ljava/lang/Object;
  #375 = NameAndType        #301:#302     // $anonfun$tabulate$14:(Lscala/Function4;IIII)Ljava/lang/Object;
  #376 = InterfaceMethodref #2.#375       // scala/collection/ClassTagIterableFactory.$anonfun$tabulate$14:(Lscala/Function4;IIII)Ljava/lang/Object;
  #377 = NameAndType        #328:#329     // $anonfun$tabulate$16:(Lscala/Function5;IIIII)Ljava/lang/Object;
  #378 = InterfaceMethodref #2.#377       // scala/collection/ClassTagIterableFactory.$anonfun$tabulate$16:(Lscala/Function5;IIIII)Ljava/lang/Object;
  #379 = Utf8               $deserializeLambda$
  #380 = Utf8               (Ljava/lang/invoke/SerializedLambda;)Ljava/lang/Object;
  #381 = Utf8               scala/runtime/LambdaDeserialize
  #382 = Class              #381          // scala/runtime/LambdaDeserialize
  #383 = Utf8               bootstrap
  #384 = Utf8               (Ljava/lang/invoke/MethodHandles$Lookup;Ljava/lang/String;Ljava/lang/invoke/MethodType;[Ljava/lang/invoke/MethodHandle;)Ljava/lang/invoke/CallSite;
  #385 = NameAndType        #383:#384     // bootstrap:(Ljava/lang/invoke/MethodHandles$Lookup;Ljava/lang/String;Ljava/lang/invoke/MethodType;[Ljava/lang/invoke/MethodHandle;)Ljava/lang/invoke/CallSite;
  #386 = Methodref          #382.#385     // scala/runtime/LambdaDeserialize.bootstrap:(Ljava/lang/invoke/MethodHandles$Lookup;Ljava/lang/String;Ljava/lang/invoke/MethodType;[Ljava/lang/invoke/MethodHandle;)Ljava/lang/invoke/CallSite;
  #387 = MethodHandle       6:#386        // REF_invokeStatic scala/runtime/LambdaDeserialize.bootstrap:(Ljava/lang/invoke/MethodHandles$Lookup;Ljava/lang/String;Ljava/lang/invoke/MethodType;[Ljava/lang/invoke/MethodHandle;)Ljava/lang/invoke/CallSite;
  #388 = Utf8               lambdaDeserialize
  #389 = NameAndType        #388:#380     // lambdaDeserialize:(Ljava/lang/invoke/SerializedLambda;)Ljava/lang/Object;
  #390 = InvokeDynamic      #12:#389      // #12:lambdaDeserialize:(Ljava/lang/invoke/SerializedLambda;)Ljava/lang/Object;
  #391 = Utf8               Code
  #392 = Utf8               LineNumberTable
  #393 = Utf8               LocalVariableTable
  #394 = Utf8               Signature
  #395 = Utf8               MethodParameters
  #396 = Utf8               InnerClasses
  #397 = Utf8               SourceFile
  #398 = Utf8               RuntimeVisibleAnnotations
  #399 = Utf8               BootstrapMethods
  #400 = Utf8               ScalaInlineInfo
  #401 = Utf8               ScalaSig
{
  private <X extends java.lang.Object> scala.reflect.ClassTag<CC> ccClassTag();
    descriptor: ()Lscala/reflect/ClassTag;
    flags: (0x0002) ACC_PRIVATE
    Code:
      stack=1, locals=1, args_size=1
         0: getstatic     #36                 // Field scala/reflect/ClassTag$.MODULE$:Lscala/reflect/ClassTag$;
         3: invokevirtual #39                 // Method scala/reflect/ClassTag$.AnyRef:()Lscala/reflect/ClassTag;
         6: areturn
      LineNumberTable:
        line 556: 0
      LocalVariableTable:
        Start  Length  Slot  Name   Signature
            0       7     0  this   Lscala/collection/ClassTagIterableFactory;
    Signature: #30                          // <X:Ljava/lang/Object;>()Lscala/reflect/ClassTag<TCC;>;

  public static java.lang.Object range$(scala.collection.ClassTagIterableFactory, java.lang.Object, java.lang.Object, scala.math.Integral, scala.reflect.ClassTag);
    descriptor: (Lscala/collection/ClassTagIterableFactory;Ljava/lang/Object;Ljava/lang/Object;Lscala/math/Integral;Lscala/reflect/ClassTag;)Ljava/lang/Object;
    flags: (0x1009) ACC_PUBLIC, ACC_STATIC, ACC_SYNTHETIC
    Code:
      stack=5, locals=5, args_size=5
         0: aload_0
         1: aload_1
         2: aload_2
         3: aload_3
         4: aload         4
         6: invokespecial #52                 // InterfaceMethod range:(Ljava/lang/Object;Ljava/lang/Object;Lscala/math/Integral;Lscala/reflect/ClassTag;)Ljava/lang/Object;
         9: areturn
      LineNumberTable:
        line 564: 0
      LocalVariableTable:
        Start  Length  Slot  Name   Signature
            0      10     0 $this   Lscala/collection/ClassTagIterableFactory;
            0      10     1 start   Ljava/lang/Object;
            0      10     2   end   Ljava/lang/Object;
            0      10     3 evidence$22   Lscala/math/Integral;
            0      10     4 evidence$23   Lscala/reflect/ClassTag;
    MethodParameters:
      Name                           Flags
      $this                          final synthetic
      start                          final
      end                            final
      evidence$22                    final
      evidence$23                    final

  public default <A extends java.lang.Object> CC range(A, A, scala.math.Integral<A>, scala.reflect.ClassTag<A>);
    descriptor: (Ljava/lang/Object;Ljava/lang/Object;Lscala/math/Integral;Lscala/reflect/ClassTag;)Ljava/lang/Object;
    flags: (0x0001) ACC_PUBLIC
    Code:
      stack=7, locals=6, args_size=5
         0: aload_0
         1: getstatic     #61                 // Field scala/collection/immutable/NumericRange$.MODULE$:Lscala/collection/immutable/NumericRange$;
         4: pop
         5: aload_3
         6: invokeinterface #67,  1           // InterfaceMethod scala/math/Numeric.one:()Ljava/lang/Object;
        11: astore        5
        13: new           #24                 // class scala/collection/immutable/NumericRange$Exclusive
        16: dup
        17: aload_1
        18: aload_2
        19: aload         5
        21: aload_3
        22: invokespecial #71                 // Method scala/collection/immutable/NumericRange$Exclusive."<init>":(Ljava/lang/Object;Ljava/lang/Object;Ljava/lang/Object;Lscala/math/Integral;)V
        25: aconst_null
        26: astore        5
        28: aload         4
        30: invokeinterface #75,  3           // InterfaceMethod from:(Lscala/collection/IterableOnce;Ljava/lang/Object;)Ljava/lang/Object;
        35: areturn
      LineNumberTable:
        line 564: 0
      LocalVariableTable:
        Start  Length  Slot  Name   Signature
            0      36     0  this   Lscala/collection/ClassTagIterableFactory;
            0      36     1 start   Ljava/lang/Object;
            0      36     2   end   Ljava/lang/Object;
            0      36     3 evidence$22   Lscala/math/Integral;
            0      36     4 evidence$23   Lscala/reflect/ClassTag;
           13      12     5 apply_step   Ljava/lang/Object;
    Signature: #56                          // <A:Ljava/lang/Object;>(TA;TA;Lscala/math/Integral<TA;>;Lscala/reflect/ClassTag<TA;>;)TCC;
    MethodParameters:
      Name                           Flags
      start                          final
      end                            final
      evidence$22                    final
      evidence$23                    final

  public static java.lang.Object range$(scala.collection.ClassTagIterableFactory, java.lang.Object, java.lang.Object, java.lang.Object, scala.math.Integral, scala.reflect.ClassTag);
    descriptor: (Lscala/collection/ClassTagIterableFactory;Ljava/lang/Object;Ljava/lang/Object;Ljava/lang/Object;Lscala/math/Integral;Lscala/reflect/ClassTag;)Ljava/lang/Object;
    flags: (0x1009) ACC_PUBLIC, ACC_STATIC, ACC_SYNTHETIC
    Code:
      stack=6, locals=6, args_size=6
         0: aload_0
         1: aload_1
         2: aload_2
         3: aload_3
         4: aload         4
         6: aload         5
         8: invokespecial #83                 // InterfaceMethod range:(Ljava/lang/Object;Ljava/lang/Object;Ljava/lang/Object;Lscala/math/Integral;Lscala/reflect/ClassTag;)Ljava/lang/Object;
        11: areturn
      LineNumberTable:
        line 572: 0
      LocalVariableTable:
        Start  Length  Slot  Name   Signature
            0      12     0 $this   Lscala/collection/ClassTagIterableFactory;
            0      12     1 start   Ljava/lang/Object;
            0      12     2   end   Ljava/lang/Object;
            0      12     3  step   Ljava/lang/Object;
            0      12     4 evidence$24   Lscala/math/Integral;
            0      12     5 evidence$25   Lscala/reflect/ClassTag;
    MethodParameters:
      Name                           Flags
      $this                          final synthetic
      start                          final
      end                            final
      step                           final
      evidence$24                    final
      evidence$25                    final

  public default <A extends java.lang.Object> CC range(A, A, A, scala.math.Integral<A>, scala.reflect.ClassTag<A>);
    descriptor: (Ljava/lang/Object;Ljava/lang/Object;Ljava/lang/Object;Lscala/math/Integral;Lscala/reflect/ClassTag;)Ljava/lang/Object;
    flags: (0x0001) ACC_PUBLIC
    Code:
      stack=7, locals=6, args_size=6
         0: aload_0
         1: getstatic     #61                 // Field scala/collection/immutable/NumericRange$.MODULE$:Lscala/collection/immutable/NumericRange$;
         4: pop
         5: new           #24                 // class scala/collection/immutable/NumericRange$Exclusive
         8: dup
         9: aload_1
        10: aload_2
        11: aload_3
        12: aload         4
        14: invokespecial #71                 // Method scala/collection/immutable/NumericRange$Exclusive."<init>":(Ljava/lang/Object;Ljava/lang/Object;Ljava/lang/Object;Lscala/math/Integral;)V
        17: aload         5
        19: invokeinterface #75,  3           // InterfaceMethod from:(Lscala/collection/IterableOnce;Ljava/lang/Object;)Ljava/lang/Object;
        24: areturn
      LineNumberTable:
        line 572: 0
      LocalVariableTable:
        Start  Length  Slot  Name   Signature
            0      25     0  this   Lscala/collection/ClassTagIterableFactory;
            0      25     1 start   Ljava/lang/Object;
            0      25     2   end   Ljava/lang/Object;
            0      25     3  step   Ljava/lang/Object;
            0      25     4 evidence$24   Lscala/math/Integral;
            0      25     5 evidence$25   Lscala/reflect/ClassTag;
    Signature: #84                          // <A:Ljava/lang/Object;>(TA;TA;TA;Lscala/math/Integral<TA;>;Lscala/reflect/ClassTag<TA;>;)TCC;
    MethodParameters:
      Name                           Flags
      start                          final
      end                            final
      step                           final
      evidence$24                    final
      evidence$25                    final

  public static java.lang.Object fill$(scala.collection.ClassTagIterableFactory, int, int, scala.Function0, scala.reflect.ClassTag);
    descriptor: (Lscala/collection/ClassTagIterableFactory;IILscala/Function0;Lscala/reflect/ClassTag;)Ljava/lang/Object;
    flags: (0x1009) ACC_PUBLIC, ACC_STATIC, ACC_SYNTHETIC
    Code:
      stack=5, locals=5, args_size=5
         0: aload_0
         1: iload_1
         2: iload_2
         3: aload_3
         4: aload         4
         6: invokespecial #94                 // InterfaceMethod fill:(IILscala/Function0;Lscala/reflect/ClassTag;)Ljava/lang/Object;
         9: areturn
      LineNumberTable:
        line 580: 0
      LocalVariableTable:
        Start  Length  Slot  Name   Signature
            0      10     0 $this   Lscala/collection/ClassTagIterableFactory;
            0      10     1    n1   I
            0      10     2    n2   I
            0      10     3  elem   Lscala/Function0;
            0      10     4 evidence$26   Lscala/reflect/ClassTag;
    MethodParameters:
      Name                           Flags
      $this                          final synthetic
      n1                             final
      n2                             final
      elem                           final
      evidence$26                    final

  public default <A extends java.lang.Object> CC fill(int, int, scala.Function0<A>, scala.reflect.ClassTag<A>);
    descriptor: (IILscala/Function0;Lscala/reflect/ClassTag;)Ljava/lang/Object;
    flags: (0x0001) ACC_PUBLIC
    Code:
      stack=6, locals=5, args_size=5
         0: aload_0
         1: iload_1
         2: aload_0
         3: iload_2
         4: aload_3
         5: aload         4
         7: invokedynamic #115,  0            // InvokeDynamic #0:apply:(Lscala/collection/ClassTagIterableFactory;ILscala/Function0;Lscala/reflect/ClassTag;)Lscala/Function0;
        12: getstatic     #36                 // Field scala/reflect/ClassTag$.MODULE$:Lscala/reflect/ClassTag$;
        15: invokevirtual #39                 // Method scala/reflect/ClassTag$.AnyRef:()Lscala/reflect/ClassTag;
        18: invokeinterface #118,  4          // InterfaceMethod fill:(ILscala/Function0;Ljava/lang/Object;)Ljava/lang/Object;
        23: areturn
      LineNumberTable:
        line 580: 0
        line 556: 12
        line 580: 18
      LocalVariableTable:
        Start  Length  Slot  Name   Signature
            0      24     0  this   Lscala/collection/ClassTagIterableFactory;
            0      24     1    n1   I
            0      24     2    n2   I
            0      24     3  elem   Lscala/Function0;
            0      24     4 evidence$26   Lscala/reflect/ClassTag;
    Signature: #97                          // <A:Ljava/lang/Object;>(IILscala/Function0<TA;>;Lscala/reflect/ClassTag<TA;>;)TCC;
    MethodParameters:
      Name                           Flags
      n1                             final
      n2                             final
      elem                           final
      evidence$26                    final

  public static java.lang.Object fill$(scala.collection.ClassTagIterableFactory, int, int, int, scala.Function0, scala.reflect.ClassTag);
    descriptor: (Lscala/collection/ClassTagIterableFactory;IIILscala/Function0;Lscala/reflect/ClassTag;)Ljava/lang/Object;
    flags: (0x1009) ACC_PUBLIC, ACC_STATIC, ACC_SYNTHETIC
    Code:
      stack=6, locals=6, args_size=6
         0: aload_0
         1: iload_1
         2: iload_2
         3: iload_3
         4: aload         4
         6: aload         5
         8: invokespecial #124                // InterfaceMethod fill:(IIILscala/Function0;Lscala/reflect/ClassTag;)Ljava/lang/Object;
        11: areturn
      LineNumberTable:
        line 589: 0
      LocalVariableTable:
        Start  Length  Slot  Name   Signature
            0      12     0 $this   Lscala/collection/ClassTagIterableFactory;
            0      12     1    n1   I
            0      12     2    n2   I
            0      12     3    n3   I
            0      12     4  elem   Lscala/Function0;
            0      12     5 evidence$27   Lscala/reflect/ClassTag;
    MethodParameters:
      Name                           Flags
      $this                          final synthetic
      n1                             final
      n2                             final
      n3                             final
      elem                           final
      evidence$27                    final

  public default <A extends java.lang.Object> CC fill(int, int, int, scala.Function0<A>, scala.reflect.ClassTag<A>);
    descriptor: (IIILscala/Function0;Lscala/reflect/ClassTag;)Ljava/lang/Object;
    flags: (0x0001) ACC_PUBLIC
    Code:
      stack=7, locals=6, args_size=6
         0: aload_0
         1: iload_1
         2: aload_0
         3: iload_2
         4: iload_3
         5: aload         4
         7: aload         5
         9: invokedynamic #132,  0            // InvokeDynamic #1:apply:(Lscala/collection/ClassTagIterableFactory;IILscala/Function0;Lscala/reflect/ClassTag;)Lscala/Function0;
        14: getstatic     #36                 // Field scala/reflect/ClassTag$.MODULE$:Lscala/reflect/ClassTag$;
        17: invokevirtual #39                 // Method scala/reflect/ClassTag$.AnyRef:()Lscala/reflect/ClassTag;
        20: invokeinterface #118,  4          // InterfaceMethod fill:(ILscala/Function0;Ljava/lang/Object;)Ljava/lang/Object;
        25: areturn
      LineNumberTable:
        line 589: 0
        line 556: 14
        line 589: 20
      LocalVariableTable:
        Start  Length  Slot  Name   Signature
            0      26     0  this   Lscala/collection/ClassTagIterableFactory;
            0      26     1    n1   I
            0      26     2    n2   I
            0      26     3    n3   I
            0      26     4  elem   Lscala/Function0;
            0      26     5 evidence$27   Lscala/reflect/ClassTag;
    Signature: #125                         // <A:Ljava/lang/Object;>(IIILscala/Function0<TA;>;Lscala/reflect/ClassTag<TA;>;)TCC;
    MethodParameters:
      Name                           Flags
      n1                             final
      n2                             final
      n3                             final
      elem                           final
      evidence$27                    final

  public static java.lang.Object fill$(scala.collection.ClassTagIterableFactory, int, int, int, int, scala.Function0, scala.reflect.ClassTag);
    descriptor: (Lscala/collection/ClassTagIterableFactory;IIIILscala/Function0;Lscala/reflect/ClassTag;)Ljava/lang/Object;
    flags: (0x1009) ACC_PUBLIC, ACC_STATIC, ACC_SYNTHETIC
    Code:
      stack=7, locals=7, args_size=7
         0: aload_0
         1: iload_1
         2: iload_2
         3: iload_3
         4: iload         4
         6: aload         5
         8: aload         6
        10: invokespecial #138                // InterfaceMethod fill:(IIIILscala/Function0;Lscala/reflect/ClassTag;)Ljava/lang/Object;
        13: areturn
      LineNumberTable:
        line 599: 0
      LocalVariableTable:
        Start  Length  Slot  Name   Signature
            0      14     0 $this   Lscala/collection/ClassTagIterableFactory;
            0      14     1    n1   I
            0      14     2    n2   I
            0      14     3    n3   I
            0      14     4    n4   I
            0      14     5  elem   Lscala/Function0;
            0      14     6 evidence$28   Lscala/reflect/ClassTag;
    MethodParameters:
      Name                           Flags
      $this                          final synthetic
      n1                             final
      n2                             final
      n3                             final
      n4                             final
      elem                           final
      evidence$28                    final

  public default <A extends java.lang.Object> CC fill(int, int, int, int, scala.Function0<A>, scala.reflect.ClassTag<A>);
    descriptor: (IIIILscala/Function0;Lscala/reflect/ClassTag;)Ljava/lang/Object;
    flags: (0x0001) ACC_PUBLIC
    Code:
      stack=8, locals=7, args_size=7
         0: aload_0
         1: iload_1
         2: aload_0
         3: iload_2
         4: iload_3
         5: iload         4
         7: aload         5
         9: aload         6
        11: invokedynamic #146,  0            // InvokeDynamic #2:apply:(Lscala/collection/ClassTagIterableFactory;IIILscala/Function0;Lscala/reflect/ClassTag;)Lscala/Function0;
        16: getstatic     #36                 // Field scala/reflect/ClassTag$.MODULE$:Lscala/reflect/ClassTag$;
        19: invokevirtual #39                 // Method scala/reflect/ClassTag$.AnyRef:()Lscala/reflect/ClassTag;
        22: invokeinterface #118,  4          // InterfaceMethod fill:(ILscala/Function0;Ljava/lang/Object;)Ljava/lang/Object;
        27: areturn
      LineNumberTable:
        line 600: 0
        line 556: 16
        line 600: 22
      LocalVariableTable:
        Start  Length  Slot  Name   Signature
            0      28     0  this   Lscala/collection/ClassTagIterableFactory;
            0      28     1    n1   I
            0      28     2    n2   I
            0      28     3    n3   I
            0      28     4    n4   I
            0      28     5  elem   Lscala/Function0;
            0      28     6 evidence$28   Lscala/reflect/ClassTag;
    Signature: #139                         // <A:Ljava/lang/Object;>(IIIILscala/Function0<TA;>;Lscala/reflect/ClassTag<TA;>;)TCC;
    MethodParameters:
      Name                           Flags
      n1                             final
      n2                             final
      n3                             final
      n4                             final
      elem                           final
      evidence$28                    final

  public static java.lang.Object fill$(scala.collection.ClassTagIterableFactory, int, int, int, int, int, scala.Function0, scala.reflect.ClassTag);
    descriptor: (Lscala/collection/ClassTagIterableFactory;IIIIILscala/Function0;Lscala/reflect/ClassTag;)Ljava/lang/Object;
    flags: (0x1009) ACC_PUBLIC, ACC_STATIC, ACC_SYNTHETIC
    Code:
      stack=8, locals=8, args_size=8
         0: aload_0
         1: iload_1
         2: iload_2
         3: iload_3
         4: iload         4
         6: iload         5
         8: aload         6
        10: aload         7
        12: invokespecial #152                // InterfaceMethod fill:(IIIIILscala/Function0;Lscala/reflect/ClassTag;)Ljava/lang/Object;
        15: areturn
      LineNumberTable:
        line 611: 0
      LocalVariableTable:
        Start  Length  Slot  Name   Signature
            0      16     0 $this   Lscala/collection/ClassTagIterableFactory;
            0      16     1    n1   I
            0      16     2    n2   I
            0      16     3    n3   I
            0      16     4    n4   I
            0      16     5    n5   I
            0      16     6  elem   Lscala/Function0;
            0      16     7 evidence$29   Lscala/reflect/ClassTag;
    MethodParameters:
      Name                           Flags
      $this                          final synthetic
      n1                             final
      n2                             final
      n3                             final
      n4                             final
      n5                             final
      elem                           final
      evidence$29                    final

  public default <A extends java.lang.Object> CC fill(int, int, int, int, int, scala.Function0<A>, scala.reflect.ClassTag<A>);
    descriptor: (IIIIILscala/Function0;Lscala/reflect/ClassTag;)Ljava/lang/Object;
    flags: (0x0001) ACC_PUBLIC
    Code:
      stack=9, locals=8, args_size=8
         0: aload_0
         1: iload_1
         2: aload_0
         3: iload_2
         4: iload_3
         5: iload         4
         7: iload         5
         9: aload         6
        11: aload         7
        13: invokedynamic #160,  0            // InvokeDynamic #3:apply:(Lscala/collection/ClassTagIterableFactory;IIIILscala/Function0;Lscala/reflect/ClassTag;)Lscala/Function0;
        18: getstatic     #36                 // Field scala/reflect/ClassTag$.MODULE$:Lscala/reflect/ClassTag$;
        21: invokevirtual #39                 // Method scala/reflect/ClassTag$.AnyRef:()Lscala/reflect/ClassTag;
        24: invokeinterface #118,  4          // InterfaceMethod fill:(ILscala/Function0;Ljava/lang/Object;)Ljava/lang/Object;
        29: areturn
      LineNumberTable:
        line 612: 0
        line 556: 18
        line 612: 24
      LocalVariableTable:
        Start  Length  Slot  Name   Signature
            0      30     0  this   Lscala/collection/ClassTagIterableFactory;
            0      30     1    n1   I
            0      30     2    n2   I
            0      30     3    n3   I
            0      30     4    n4   I
            0      30     5    n5   I
            0      30     6  elem   Lscala/Function0;
            0      30     7 evidence$29   Lscala/reflect/ClassTag;
    Signature: #153                         // <A:Ljava/lang/Object;>(IIIIILscala/Function0<TA;>;Lscala/reflect/ClassTag<TA;>;)TCC;
    MethodParameters:
      Name                           Flags
      n1                             final
      n2                             final
      n3                             final
      n4                             final
      n5                             final
      elem                           final
      evidence$29                    final

  public static java.lang.Object tabulate$(scala.collection.ClassTagIterableFactory, int, int, scala.Function2, scala.reflect.ClassTag);
    descriptor: (Lscala/collection/ClassTagIterableFactory;IILscala/Function2;Lscala/reflect/ClassTag;)Ljava/lang/Object;
    flags: (0x1009) ACC_PUBLIC, ACC_STATIC, ACC_SYNTHETIC
    Code:
      stack=5, locals=5, args_size=5
         0: aload_0
         1: iload_1
         2: iload_2
         3: aload_3
         4: aload         4
         6: invokespecial #168                // InterfaceMethod tabulate:(IILscala/Function2;Lscala/reflect/ClassTag;)Ljava/lang/Object;
         9: areturn
      LineNumberTable:
        line 621: 0
      LocalVariableTable:
        Start  Length  Slot  Name   Signature
            0      10     0 $this   Lscala/collection/ClassTagIterableFactory;
            0      10     1    n1   I
            0      10     2    n2   I
            0      10     3     f   Lscala/Function2;
            0      10     4 evidence$30   Lscala/reflect/ClassTag;
    MethodParameters:
      Name                           Flags
      $this                          final synthetic
      n1                             final
      n2                             final
      f                              final
      evidence$30                    final

  public default <A extends java.lang.Object> CC tabulate(int, int, scala.Function2<java.lang.Object, java.lang.Object, A>, scala.reflect.ClassTag<A>);
    descriptor: (IILscala/Function2;Lscala/reflect/ClassTag;)Ljava/lang/Object;
    flags: (0x0001) ACC_PUBLIC
    Code:
      stack=6, locals=5, args_size=5
         0: aload_0
         1: iload_1
         2: aload_0
         3: iload_2
         4: aload_3
         5: aload         4
         7: invokedynamic #180,  0            // InvokeDynamic #4:apply:(Lscala/collection/ClassTagIterableFactory;ILscala/Function2;Lscala/reflect/ClassTag;)Lscala/Function1;
        12: getstatic     #36                 // Field scala/reflect/ClassTag$.MODULE$:Lscala/reflect/ClassTag$;
        15: invokevirtual #39                 // Method scala/reflect/ClassTag$.AnyRef:()Lscala/reflect/ClassTag;
        18: invokeinterface #183,  4          // InterfaceMethod tabulate:(ILscala/Function1;Ljava/lang/Object;)Ljava/lang/Object;
        23: areturn
      LineNumberTable:
        line 622: 0
        line 556: 12
        line 622: 18
      LocalVariableTable:
        Start  Length  Slot  Name   Signature
            0      24     0  this   Lscala/collection/ClassTagIterableFactory;
            0      24     1    n1   I
            0      24     2    n2   I
            0      24     3     f   Lscala/Function2;
            0      24     4 evidence$30   Lscala/reflect/ClassTag;
    Signature: #170                         // <A:Ljava/lang/Object;>(IILscala/Function2<Ljava/lang/Object;Ljava/lang/Object;TA;>;Lscala/reflect/ClassTag<TA;>;)TCC;
    MethodParameters:
      Name                           Flags
      n1                             final
      n2                             final
      f                              final
      evidence$30                    final

  public static java.lang.Object tabulate$(scala.collection.ClassTagIterableFactory, int, int, int, scala.Function3, scala.reflect.ClassTag);
    descriptor: (Lscala/collection/ClassTagIterableFactory;IIILscala/Function3;Lscala/reflect/ClassTag;)Ljava/lang/Object;
    flags: (0x1009) ACC_PUBLIC, ACC_STATIC, ACC_SYNTHETIC
    Code:
      stack=6, locals=6, args_size=6
         0: aload_0
         1: iload_1
         2: iload_2
         3: iload_3
         4: aload         4
         6: aload         5
         8: invokespecial #188                // InterfaceMethod tabulate:(IIILscala/Function3;Lscala/reflect/ClassTag;)Ljava/lang/Object;
        11: areturn
      LineNumberTable:
        line 632: 0
      LocalVariableTable:
        Start  Length  Slot  Name   Signature
            0      12     0 $this   Lscala/collection/ClassTagIterableFactory;
            0      12     1    n1   I
            0      12     2    n2   I
            0      12     3    n3   I
            0      12     4     f   Lscala/Function3;
            0      12     5 evidence$31   Lscala/reflect/ClassTag;
    MethodParameters:
      Name                           Flags
      $this                          final synthetic
      n1                             final
      n2                             final
      n3                             final
      f                              final
      evidence$31                    final

  public default <A extends java.lang.Object> CC tabulate(int, int, int, scala.Function3<java.lang.Object, java.lang.Object, java.lang.Object, A>, scala.reflect.ClassTag<A>);
    descriptor: (IIILscala/Function3;Lscala/reflect/ClassTag;)Ljava/lang/Object;
    flags: (0x0001) ACC_PUBLIC
    Code:
      stack=7, locals=6, args_size=6
         0: aload_0
         1: iload_1
         2: aload_0
         3: iload_2
         4: iload_3
         5: aload         4
         7: aload         5
         9: invokedynamic #198,  0            // InvokeDynamic #5:apply:(Lscala/collection/ClassTagIterableFactory;IILscala/Function3;Lscala/reflect/ClassTag;)Lscala/Function1;
        14: getstatic     #36                 // Field scala/reflect/ClassTag$.MODULE$:Lscala/reflect/ClassTag$;
        17: invokevirtual #39                 // Method scala/reflect/ClassTag$.AnyRef:()Lscala/reflect/ClassTag;
        20: invokeinterface #183,  4          // InterfaceMethod tabulate:(ILscala/Function1;Ljava/lang/Object;)Ljava/lang/Object;
        25: areturn
      LineNumberTable:
        line 633: 0
        line 556: 14
        line 633: 20
      LocalVariableTable:
        Start  Length  Slot  Name   Signature
            0      26     0  this   Lscala/collection/ClassTagIterableFactory;
            0      26     1    n1   I
            0      26     2    n2   I
            0      26     3    n3   I
            0      26     4     f   Lscala/Function3;
            0      26     5 evidence$31   Lscala/reflect/ClassTag;
    Signature: #190                         // <A:Ljava/lang/Object;>(IIILscala/Function3<Ljava/lang/Object;Ljava/lang/Object;Ljava/lang/Object;TA;>;Lscala/reflect/ClassTag<TA;>;)TCC;
    MethodParameters:
      Name                           Flags
      n1                             final
      n2                             final
      n3                             final
      f                              final
      evidence$31                    final

  public static java.lang.Object tabulate$(scala.collection.ClassTagIterableFactory, int, int, int, int, scala.Function4, scala.reflect.ClassTag);
    descriptor: (Lscala/collection/ClassTagIterableFactory;IIIILscala/Function4;Lscala/reflect/ClassTag;)Ljava/lang/Object;
    flags: (0x1009) ACC_PUBLIC, ACC_STATIC, ACC_SYNTHETIC
    Code:
      stack=7, locals=7, args_size=7
         0: aload_0
         1: iload_1
         2: iload_2
         3: iload_3
         4: iload         4
         6: aload         5
         8: aload         6
        10: invokespecial #203                // InterfaceMethod tabulate:(IIIILscala/Function4;Lscala/reflect/ClassTag;)Ljava/lang/Object;
        13: areturn
      LineNumberTable:
        line 644: 0
      LocalVariableTable:
        Start  Length  Slot  Name   Signature
            0      14     0 $this   Lscala/collection/ClassTagIterableFactory;
            0      14     1    n1   I
            0      14     2    n2   I
            0      14     3    n3   I
            0      14     4    n4   I
            0      14     5     f   Lscala/Function4;
            0      14     6 evidence$32   Lscala/reflect/ClassTag;
    MethodParameters:
      Name                           Flags
      $this                          final synthetic
      n1                             final
      n2                             final
      n3                             final
      n4                             final
      f                              final
      evidence$32                    final

  public default <A extends java.lang.Object> CC tabulate(int, int, int, int, scala.Function4<java.lang.Object, java.lang.Object, java.lang.Object, java.lang.Object, A>, scala.reflect.ClassTag<A>);
    descriptor: (IIIILscala/Function4;Lscala/reflect/ClassTag;)Ljava/lang/Object;
    flags: (0x0001) ACC_PUBLIC
    Code:
      stack=8, locals=7, args_size=7
         0: aload_0
         1: iload_1
         2: aload_0
         3: iload_2
         4: iload_3
         5: iload         4
         7: aload         5
         9: aload         6
        11: invokedynamic #213,  0            // InvokeDynamic #6:apply:(Lscala/collection/ClassTagIterableFactory;IIILscala/Function4;Lscala/reflect/ClassTag;)Lscala/Function1;
        16: getstatic     #36                 // Field scala/reflect/ClassTag$.MODULE$:Lscala/reflect/ClassTag$;
        19: invokevirtual #39                 // Method scala/reflect/ClassTag$.AnyRef:()Lscala/reflect/ClassTag;
        22: invokeinterface #183,  4          // InterfaceMethod tabulate:(ILscala/Function1;Ljava/lang/Object;)Ljava/lang/Object;
        27: areturn
      LineNumberTable:
        line 645: 0
        line 556: 16
        line 645: 22
      LocalVariableTable:
        Start  Length  Slot  Name   Signature
            0      28     0  this   Lscala/collection/ClassTagIterableFactory;
            0      28     1    n1   I
            0      28     2    n2   I
            0      28     3    n3   I
            0      28     4    n4   I
            0      28     5     f   Lscala/Function4;
            0      28     6 evidence$32   Lscala/reflect/ClassTag;
    Signature: #205                         // <A:Ljava/lang/Object;>(IIIILscala/Function4<Ljava/lang/Object;Ljava/lang/Object;Ljava/lang/Object;Ljava/lang/Object;TA;>;Lscala/reflect/ClassTag<TA;>;)TCC;
    MethodParameters:
      Name                           Flags
      n1                             final
      n2                             final
      n3                             final
      n4                             final
      f                              final
      evidence$32                    final

  public static java.lang.Object tabulate$(scala.collection.ClassTagIterableFactory, int, int, int, int, int, scala.Function5, scala.reflect.ClassTag);
    descriptor: (Lscala/collection/ClassTagIterableFactory;IIIIILscala/Function5;Lscala/reflect/ClassTag;)Ljava/lang/Object;
    flags: (0x1009) ACC_PUBLIC, ACC_STATIC, ACC_SYNTHETIC
    Code:
      stack=8, locals=8, args_size=8
         0: aload_0
         1: iload_1
         2: iload_2
         3: iload_3
         4: iload         4
         6: iload         5
         8: aload         6
        10: aload         7
        12: invokespecial #218                // InterfaceMethod tabulate:(IIIIILscala/Function5;Lscala/reflect/ClassTag;)Ljava/lang/Object;
        15: areturn
      LineNumberTable:
        line 657: 0
      LocalVariableTable:
        Start  Length  Slot  Name   Signature
            0      16     0 $this   Lscala/collection/ClassTagIterableFactory;
            0      16     1    n1   I
            0      16     2    n2   I
            0      16     3    n3   I
            0      16     4    n4   I
            0      16     5    n5   I
            0      16     6     f   Lscala/Function5;
            0      16     7 evidence$33   Lscala/reflect/ClassTag;
    MethodParameters:
      Name                           Flags
      $this                          final synthetic
      n1                             final
      n2                             final
      n3                             final
      n4                             final
      n5                             final
      f                              final
      evidence$33                    final

  public default <A extends java.lang.Object> CC tabulate(int, int, int, int, int, scala.Function5<java.lang.Object, java.lang.Object, java.lang.Object, java.lang.Object, java.lang.Object, A>, scala.reflect.ClassTag<A>);
    descriptor: (IIIIILscala/Function5;Lscala/reflect/ClassTag;)Ljava/lang/Object;
    flags: (0x0001) ACC_PUBLIC
    Code:
      stack=9, locals=8, args_size=8
         0: aload_0
         1: iload_1
         2: aload_0
         3: iload_2
         4: iload_3
         5: iload         4
         7: iload         5
         9: aload         6
        11: aload         7
        13: invokedynamic #228,  0            // InvokeDynamic #7:apply:(Lscala/collection/ClassTagIterableFactory;IIIILscala/Function5;Lscala/reflect/ClassTag;)Lscala/Function1;
        18: getstatic     #36                 // Field scala/reflect/ClassTag$.MODULE$:Lscala/reflect/ClassTag$;
        21: invokevirtual #39                 // Method scala/reflect/ClassTag$.AnyRef:()Lscala/reflect/ClassTag;
        24: invokeinterface #183,  4          // InterfaceMethod tabulate:(ILscala/Function1;Ljava/lang/Object;)Ljava/lang/Object;
        29: areturn
      LineNumberTable:
        line 658: 0
        line 556: 18
        line 658: 24
      LocalVariableTable:
        Start  Length  Slot  Name   Signature
            0      30     0  this   Lscala/collection/ClassTagIterableFactory;
            0      30     1    n1   I
            0      30     2    n2   I
            0      30     3    n3   I
            0      30     4    n4   I
            0      30     5    n5   I
            0      30     6     f   Lscala/Function5;
            0      30     7 evidence$33   Lscala/reflect/ClassTag;
    Signature: #220                         // <A:Ljava/lang/Object;>(IIIIILscala/Function5<Ljava/lang/Object;Ljava/lang/Object;Ljava/lang/Object;Ljava/lang/Object;Ljava/lang/Object;TA;>;Lscala/reflect/ClassTag<TA;>;)TCC;
    MethodParameters:
      Name                           Flags
      n1                             final
      n2                             final
      n3                             final
      n4                             final
      n5                             final
      f                              final
      evidence$33                    final

  public static java.lang.Object $anonfun$fill$5(scala.collection.ClassTagIterableFactory, int, scala.Function0, scala.reflect.ClassTag);
    descriptor: (Lscala/collection/ClassTagIterableFactory;ILscala/Function0;Lscala/reflect/ClassTag;)Ljava/lang/Object;
    flags: (0x1009) ACC_PUBLIC, ACC_STATIC, ACC_SYNTHETIC
    Code:
      stack=4, locals=4, args_size=4
         0: aload_0
         1: iload_1
         2: aload_2
         3: aload_3
         4: invokeinterface #118,  4          // InterfaceMethod fill:(ILscala/Function0;Ljava/lang/Object;)Ljava/lang/Object;
         9: areturn
      LineNumberTable:
        line 580: 0
      LocalVariableTable:
        Start  Length  Slot  Name   Signature
            0      10     0 $this   Lscala/collection/ClassTagIterableFactory;
            0      10     1  n2$9   I
            0      10     2 elem$5   Lscala/Function0;
            0      10     3 evidence$26$1   Lscala/reflect/ClassTag;
    MethodParameters:
      Name                           Flags
      $this                          final synthetic
      n2$9                           final
      elem$5                         final
      evidence$26$1                  final

  public static java.lang.Object $anonfun$fill$6(scala.collection.ClassTagIterableFactory, int, int, scala.Function0, scala.reflect.ClassTag);
    descriptor: (Lscala/collection/ClassTagIterableFactory;IILscala/Function0;Lscala/reflect/ClassTag;)Ljava/lang/Object;
    flags: (0x1009) ACC_PUBLIC, ACC_STATIC, ACC_SYNTHETIC
    Code:
      stack=5, locals=5, args_size=5
         0: aload_0
         1: iload_1
         2: iload_2
         3: aload_3
         4: aload         4
         6: invokeinterface #94,  5           // InterfaceMethod fill:(IILscala/Function0;Lscala/reflect/ClassTag;)Ljava/lang/Object;
        11: areturn
      LineNumberTable:
        line 589: 0
      LocalVariableTable:
        Start  Length  Slot  Name   Signature
            0      12     0 $this   Lscala/collection/ClassTagIterableFactory;
            0      12     1 n2$10   I
            0      12     2  n3$7   I
            0      12     3 elem$6   Lscala/Function0;
            0      12     4 evidence$27$1   Lscala/reflect/ClassTag;
    MethodParameters:
      Name                           Flags
      $this                          final synthetic
      n2$10                          final
      n3$7                           final
      elem$6                         final
      evidence$27$1                  final

  public static java.lang.Object $anonfun$fill$7(scala.collection.ClassTagIterableFactory, int, int, int, scala.Function0, scala.reflect.ClassTag);
    descriptor: (Lscala/collection/ClassTagIterableFactory;IIILscala/Function0;Lscala/reflect/ClassTag;)Ljava/lang/Object;
    flags: (0x1009) ACC_PUBLIC, ACC_STATIC, ACC_SYNTHETIC
    Code:
      stack=6, locals=6, args_size=6
         0: aload_0
         1: iload_1
         2: iload_2
         3: iload_3
         4: aload         4
         6: aload         5
         8: invokeinterface #124,  6          // InterfaceMethod fill:(IIILscala/Function0;Lscala/reflect/ClassTag;)Ljava/lang/Object;
        13: areturn
      LineNumberTable:
        line 600: 0
      LocalVariableTable:
        Start  Length  Slot  Name   Signature
            0      14     0 $this   Lscala/collection/ClassTagIterableFactory;
            0      14     1 n2$11   I
            0      14     2  n3$8   I
            0      14     3  n4$5   I
            0      14     4 elem$7   Lscala/Function0;
            0      14     5 evidence$28$1   Lscala/reflect/ClassTag;
    MethodParameters:
      Name                           Flags
      $this                          final synthetic
      n2$11                          final
      n3$8                           final
      n4$5                           final
      elem$7                         final
      evidence$28$1                  final

  public static java.lang.Object $anonfun$fill$8(scala.collection.ClassTagIterableFactory, int, int, int, int, scala.Function0, scala.reflect.ClassTag);
    descriptor: (Lscala/collection/ClassTagIterableFactory;IIIILscala/Function0;Lscala/reflect/ClassTag;)Ljava/lang/Object;
    flags: (0x1009) ACC_PUBLIC, ACC_STATIC, ACC_SYNTHETIC
    Code:
      stack=7, locals=7, args_size=7
         0: aload_0
         1: iload_1
         2: iload_2
         3: iload_3
         4: iload         4
         6: aload         5
         8: aload         6
        10: invokeinterface #138,  7          // InterfaceMethod fill:(IIIILscala/Function0;Lscala/reflect/ClassTag;)Ljava/lang/Object;
        15: areturn
      LineNumberTable:
        line 612: 0
      LocalVariableTable:
        Start  Length  Slot  Name   Signature
            0      16     0 $this   Lscala/collection/ClassTagIterableFactory;
            0      16     1 n2$12   I
            0      16     2  n3$9   I
            0      16     3  n4$6   I
            0      16     4  n5$3   I
            0      16     5 elem$8   Lscala/Function0;
            0      16     6 evidence$29$1   Lscala/reflect/ClassTag;
    MethodParameters:
      Name                           Flags
      $this                          final synthetic
      n2$12                          final
      n3$9                           final
      n4$6                           final
      n5$3                           final
      elem$8                         final
      evidence$29$1                  final

  public static java.lang.Object $anonfun$tabulate$10(scala.Function2, int, int);
    descriptor: (Lscala/Function2;II)Ljava/lang/Object;
    flags: (0x1009) ACC_PUBLIC, ACC_STATIC, ACC_SYNTHETIC
    Code:
      stack=3, locals=3, args_size=3
         0: aload_0
         1: iload_1
         2: invokestatic  #257                // Method scala/runtime/BoxesRunTime.boxToInteger:(I)Ljava/lang/Integer;
         5: iload_2
         6: invokestatic  #257                // Method scala/runtime/BoxesRunTime.boxToInteger:(I)Ljava/lang/Integer;
         9: invokeinterface #262,  3          // InterfaceMethod scala/Function2.apply:(Ljava/lang/Object;Ljava/lang/Object;)Ljava/lang/Object;
        14: areturn
      LineNumberTable:
        line 622: 0
      LocalVariableTable:
        Start  Length  Slot  Name   Signature
            0      15     0   f$5   Lscala/Function2;
            0      15     1  i1$5   I
            0      15     2  x$15   I
    MethodParameters:
      Name                           Flags
      f$5                            final
      i1$5                           final
      x$15                           final

  public static java.lang.Object $anonfun$tabulate$9(scala.collection.ClassTagIterableFactory, int, scala.Function2, scala.reflect.ClassTag, int);
    descriptor: (Lscala/collection/ClassTagIterableFactory;ILscala/Function2;Lscala/reflect/ClassTag;I)Ljava/lang/Object;
    flags: (0x1009) ACC_PUBLIC, ACC_STATIC, ACC_SYNTHETIC
    Code:
      stack=4, locals=5, args_size=5
         0: aload_0
         1: iload_1
         2: aload_2
         3: iload         4
         5: invokedynamic #275,  0            // InvokeDynamic #8:apply:(Lscala/Function2;I)Lscala/Function1;
        10: aload_3
        11: invokeinterface #183,  4          // InterfaceMethod tabulate:(ILscala/Function1;Ljava/lang/Object;)Ljava/lang/Object;
        16: areturn
      LineNumberTable:
        line 622: 0
      LocalVariableTable:
        Start  Length  Slot  Name   Signature
            0      17     0 $this   Lscala/collection/ClassTagIterableFactory;
            0      17     1 n2$13   I
            0      17     2   f$5   Lscala/Function2;
            0      17     3 evidence$30$1   Lscala/reflect/ClassTag;
            0      17     4    i1   I
    MethodParameters:
      Name                           Flags
      $this                          final synthetic
      n2$13                          final
      f$5                            final
      evidence$30$1                  final
      i1                             final

  public static java.lang.Object $anonfun$tabulate$12(scala.Function3, int, int, int);
    descriptor: (Lscala/Function3;III)Ljava/lang/Object;
    flags: (0x1009) ACC_PUBLIC, ACC_STATIC, ACC_SYNTHETIC
    Code:
      stack=4, locals=4, args_size=4
         0: aload_0
         1: iload_1
         2: invokestatic  #257                // Method scala/runtime/BoxesRunTime.boxToInteger:(I)Ljava/lang/Integer;
         5: iload_2
         6: invokestatic  #257                // Method scala/runtime/BoxesRunTime.boxToInteger:(I)Ljava/lang/Integer;
         9: iload_3
        10: invokestatic  #257                // Method scala/runtime/BoxesRunTime.boxToInteger:(I)Ljava/lang/Integer;
        13: invokeinterface #286,  4          // InterfaceMethod scala/Function3.apply:(Ljava/lang/Object;Ljava/lang/Object;Ljava/lang/Object;)Ljava/lang/Object;
        18: areturn
      LineNumberTable:
        line 633: 0
      LocalVariableTable:
        Start  Length  Slot  Name   Signature
            0      19     0   f$6   Lscala/Function3;
            0      19     1  i1$6   I
            0      19     2  x$16   I
            0      19     3  x$17   I
    MethodParameters:
      Name                           Flags
      f$6                            final
      i1$6                           final
      x$16                           final
      x$17                           final

  public static java.lang.Object $anonfun$tabulate$11(scala.collection.ClassTagIterableFactory, int, int, scala.Function3, scala.reflect.ClassTag, int);
    descriptor: (Lscala/collection/ClassTagIterableFactory;IILscala/Function3;Lscala/reflect/ClassTag;I)Ljava/lang/Object;
    flags: (0x1009) ACC_PUBLIC, ACC_STATIC, ACC_SYNTHETIC
    Code:
      stack=5, locals=6, args_size=6
         0: aload_0
         1: iload_1
         2: iload_2
         3: aload_3
         4: iload         5
         6: invokedynamic #300,  0            // InvokeDynamic #9:apply:(Lscala/Function3;I)Lscala/Function2;
        11: aload         4
        13: invokeinterface #168,  5          // InterfaceMethod tabulate:(IILscala/Function2;Lscala/reflect/ClassTag;)Ljava/lang/Object;
        18: areturn
      LineNumberTable:
        line 633: 0
      LocalVariableTable:
        Start  Length  Slot  Name   Signature
            0      19     0 $this   Lscala/collection/ClassTagIterableFactory;
            0      19     1 n2$14   I
            0      19     2 n3$10   I
            0      19     3   f$6   Lscala/Function3;
            0      19     4 evidence$31$1   Lscala/reflect/ClassTag;
            0      19     5    i1   I
    MethodParameters:
      Name                           Flags
      $this                          final synthetic
      n2$14                          final
      n3$10                          final
      f$6                            final
      evidence$31$1                  final
      i1                             final

  public static java.lang.Object $anonfun$tabulate$14(scala.Function4, int, int, int, int);
    descriptor: (Lscala/Function4;IIII)Ljava/lang/Object;
    flags: (0x1009) ACC_PUBLIC, ACC_STATIC, ACC_SYNTHETIC
    Code:
      stack=5, locals=5, args_size=5
         0: aload_0
         1: iload_1
         2: invokestatic  #257                // Method scala/runtime/BoxesRunTime.boxToInteger:(I)Ljava/lang/Integer;
         5: iload_2
         6: invokestatic  #257                // Method scala/runtime/BoxesRunTime.boxToInteger:(I)Ljava/lang/Integer;
         9: iload_3
        10: invokestatic  #257                // Method scala/runtime/BoxesRunTime.boxToInteger:(I)Ljava/lang/Integer;
        13: iload         4
        15: invokestatic  #257                // Method scala/runtime/BoxesRunTime.boxToInteger:(I)Ljava/lang/Integer;
        18: invokeinterface #312,  5          // InterfaceMethod scala/Function4.apply:(Ljava/lang/Object;Ljava/lang/Object;Ljava/lang/Object;Ljava/lang/Object;)Ljava/lang/Object;
        23: areturn
      LineNumberTable:
        line 645: 0
      LocalVariableTable:
        Start  Length  Slot  Name   Signature
            0      24     0   f$7   Lscala/Function4;
            0      24     1  i1$7   I
            0      24     2  x$18   I
            0      24     3  x$19   I
            0      24     4  x$20   I
    MethodParameters:
      Name                           Flags
      f$7                            final
      i1$7                           final
      x$18                           final
      x$19                           final
      x$20                           final

  public static java.lang.Object $anonfun$tabulate$13(scala.collection.ClassTagIterableFactory, int, int, int, scala.Function4, scala.reflect.ClassTag, int);
    descriptor: (Lscala/collection/ClassTagIterableFactory;IIILscala/Function4;Lscala/reflect/ClassTag;I)Ljava/lang/Object;
    flags: (0x1009) ACC_PUBLIC, ACC_STATIC, ACC_SYNTHETIC
    Code:
      stack=6, locals=7, args_size=7
         0: aload_0
         1: iload_1
         2: iload_2
         3: iload_3
         4: aload         4
         6: iload         6
         8: invokedynamic #327,  0            // InvokeDynamic #10:apply:(Lscala/Function4;I)Lscala/Function3;
        13: aload         5
        15: invokeinterface #188,  6          // InterfaceMethod tabulate:(IIILscala/Function3;Lscala/reflect/ClassTag;)Ljava/lang/Object;
        20: areturn
      LineNumberTable:
        line 645: 0
      LocalVariableTable:
        Start  Length  Slot  Name   Signature
            0      21     0 $this   Lscala/collection/ClassTagIterableFactory;
            0      21     1 n2$15   I
            0      21     2 n3$11   I
            0      21     3  n4$7   I
            0      21     4   f$7   Lscala/Function4;
            0      21     5 evidence$32$1   Lscala/reflect/ClassTag;
            0      21     6    i1   I
    MethodParameters:
      Name                           Flags
      $this                          final synthetic
      n2$15                          final
      n3$11                          final
      n4$7                           final
      f$7                            final
      evidence$32$1                  final
      i1                             final

  public static java.lang.Object $anonfun$tabulate$16(scala.Function5, int, int, int, int, int);
    descriptor: (Lscala/Function5;IIIII)Ljava/lang/Object;
    flags: (0x1009) ACC_PUBLIC, ACC_STATIC, ACC_SYNTHETIC
    Code:
      stack=6, locals=6, args_size=6
         0: aload_0
         1: iload_1
         2: invokestatic  #257                // Method scala/runtime/BoxesRunTime.boxToInteger:(I)Ljava/lang/Integer;
         5: iload_2
         6: invokestatic  #257                // Method scala/runtime/BoxesRunTime.boxToInteger:(I)Ljava/lang/Integer;
         9: iload_3
        10: invokestatic  #257                // Method scala/runtime/BoxesRunTime.boxToInteger:(I)Ljava/lang/Integer;
        13: iload         4
        15: invokestatic  #257                // Method scala/runtime/BoxesRunTime.boxToInteger:(I)Ljava/lang/Integer;
        18: iload         5
        20: invokestatic  #257                // Method scala/runtime/BoxesRunTime.boxToInteger:(I)Ljava/lang/Integer;
        23: invokeinterface #340,  6          // InterfaceMethod scala/Function5.apply:(Ljava/lang/Object;Ljava/lang/Object;Ljava/lang/Object;Ljava/lang/Object;Ljava/lang/Object;)Ljava/lang/Object;
        28: areturn
      LineNumberTable:
        line 658: 0
      LocalVariableTable:
        Start  Length  Slot  Name   Signature
            0      29     0   f$8   Lscala/Function5;
            0      29     1  i1$8   I
            0      29     2  x$21   I
            0      29     3  x$22   I
            0      29     4  x$23   I
            0      29     5  x$24   I
    MethodParameters:
      Name                           Flags
      f$8                            final
      i1$8                           final
      x$21                           final
      x$22                           final
      x$23                           final
      x$24                           final

  public static java.lang.Object $anonfun$tabulate$15(scala.collection.ClassTagIterableFactory, int, int, int, int, scala.Function5, scala.reflect.ClassTag, int);
    descriptor: (Lscala/collection/ClassTagIterableFactory;IIIILscala/Function5;Lscala/reflect/ClassTag;I)Ljava/lang/Object;
    flags: (0x1009) ACC_PUBLIC, ACC_STATIC, ACC_SYNTHETIC
    Code:
      stack=7, locals=8, args_size=8
         0: aload_0
         1: iload_1
         2: iload_2
         3: iload_3
         4: iload         4
         6: aload         5
         8: iload         7
        10: invokedynamic #356,  0            // InvokeDynamic #11:apply:(Lscala/Function5;I)Lscala/Function4;
        15: aload         6
        17: invokeinterface #203,  7          // InterfaceMethod tabulate:(IIIILscala/Function4;Lscala/reflect/ClassTag;)Ljava/lang/Object;
        22: areturn
      LineNumberTable:
        line 658: 0
      LocalVariableTable:
        Start  Length  Slot  Name   Signature
            0      23     0 $this   Lscala/collection/ClassTagIterableFactory;
            0      23     1 n2$16   I
            0      23     2 n3$12   I
            0      23     3  n4$8   I
            0      23     4  n5$4   I
            0      23     5   f$8   Lscala/Function5;
            0      23     6 evidence$33$1   Lscala/reflect/ClassTag;
            0      23     7    i1   I
    MethodParameters:
      Name                           Flags
      $this                          final synthetic
      n2$16                          final
      n3$12                          final
      n4$8                           final
      n5$4                           final
      f$8                            final
      evidence$33$1                  final
      i1                             final

  public static void $init$(scala.collection.ClassTagIterableFactory);
    descriptor: (Lscala/collection/ClassTagIterableFactory;)V
    flags: (0x0009) ACC_PUBLIC, ACC_STATIC
    Code:
      stack=0, locals=1, args_size=1
         0: return
      LineNumberTable:
        line 553: 0
      LocalVariableTable:
        Start  Length  Slot  Name   Signature
            0       1     0 $this   Lscala/collection/ClassTagIterableFactory;
    MethodParameters:
      Name                           Flags
      $this                          final synthetic

  public static java.lang.Object $anonfun$tabulate$9$adapted(scala.collection.ClassTagIterableFactory, int, scala.Function2, scala.reflect.ClassTag, java.lang.Object);
    descriptor: (Lscala/collection/ClassTagIterableFactory;ILscala/Function2;Lscala/reflect/ClassTag;Ljava/lang/Object;)Ljava/lang/Object;
    flags: (0x1009) ACC_PUBLIC, ACC_STATIC, ACC_SYNTHETIC
    Code:
      stack=5, locals=5, args_size=5
         0: aload_0
         1: iload_1
         2: aload_2
         3: aload_3
         4: aload         4
         6: invokestatic  #362                // Method scala/runtime/BoxesRunTime.unboxToInt:(Ljava/lang/Object;)I
         9: invokestatic  #364                // InterfaceMethod $anonfun$tabulate$9:(Lscala/collection/ClassTagIterableFactory;ILscala/Function2;Lscala/reflect/ClassTag;I)Ljava/lang/Object;
        12: areturn
      LineNumberTable:
        line 622: 0
      LocalVariableTable:
        Start  Length  Slot  Name   Signature
            0      13     0 $this   Lscala/collection/ClassTagIterableFactory;
            0      13     1 n2$13   I
            0      13     2   f$5   Lscala/Function2;
            0      13     3 evidence$30$1   Lscala/reflect/ClassTag;
            0      13     4    i1   Ljava/lang/Object;
    MethodParameters:
      Name                           Flags
      $this                          final
      n2$13                          final
      f$5                            final
      evidence$30$1                  final
      i1                             final

  public static java.lang.Object $anonfun$tabulate$11$adapted(scala.collection.ClassTagIterableFactory, int, int, scala.Function3, scala.reflect.ClassTag, java.lang.Object);
    descriptor: (Lscala/collection/ClassTagIterableFactory;IILscala/Function3;Lscala/reflect/ClassTag;Ljava/lang/Object;)Ljava/lang/Object;
    flags: (0x1009) ACC_PUBLIC, ACC_STATIC, ACC_SYNTHETIC
    Code:
      stack=6, locals=6, args_size=6
         0: aload_0
         1: iload_1
         2: iload_2
         3: aload_3
         4: aload         4
         6: aload         5
         8: invokestatic  #362                // Method scala/runtime/BoxesRunTime.unboxToInt:(Ljava/lang/Object;)I
        11: invokestatic  #366                // InterfaceMethod $anonfun$tabulate$11:(Lscala/collection/ClassTagIterableFactory;IILscala/Function3;Lscala/reflect/ClassTag;I)Ljava/lang/Object;
        14: areturn
      LineNumberTable:
        line 633: 0
      LocalVariableTable:
        Start  Length  Slot  Name   Signature
            0      15     0 $this   Lscala/collection/ClassTagIterableFactory;
            0      15     1 n2$14   I
            0      15     2 n3$10   I
            0      15     3   f$6   Lscala/Function3;
            0      15     4 evidence$31$1   Lscala/reflect/ClassTag;
            0      15     5    i1   Ljava/lang/Object;
    MethodParameters:
      Name                           Flags
      $this                          final
      n2$14                          final
      n3$10                          final
      f$6                            final
      evidence$31$1                  final
      i1                             final

  public static java.lang.Object $anonfun$tabulate$13$adapted(scala.collection.ClassTagIterableFactory, int, int, int, scala.Function4, scala.reflect.ClassTag, java.lang.Object);
    descriptor: (Lscala/collection/ClassTagIterableFactory;IIILscala/Function4;Lscala/reflect/ClassTag;Ljava/lang/Object;)Ljava/lang/Object;
    flags: (0x1009) ACC_PUBLIC, ACC_STATIC, ACC_SYNTHETIC
    Code:
      stack=7, locals=7, args_size=7
         0: aload_0
         1: iload_1
         2: iload_2
         3: iload_3
         4: aload         4
         6: aload         5
         8: aload         6
        10: invokestatic  #362                // Method scala/runtime/BoxesRunTime.unboxToInt:(Ljava/lang/Object;)I
        13: invokestatic  #368                // InterfaceMethod $anonfun$tabulate$13:(Lscala/collection/ClassTagIterableFactory;IIILscala/Function4;Lscala/reflect/ClassTag;I)Ljava/lang/Object;
        16: areturn
      LineNumberTable:
        line 645: 0
      LocalVariableTable:
        Start  Length  Slot  Name   Signature
            0      17     0 $this   Lscala/collection/ClassTagIterableFactory;
            0      17     1 n2$15   I
            0      17     2 n3$11   I
            0      17     3  n4$7   I
            0      17     4   f$7   Lscala/Function4;
            0      17     5 evidence$32$1   Lscala/reflect/ClassTag;
            0      17     6    i1   Ljava/lang/Object;
    MethodParameters:
      Name                           Flags
      $this                          final
      n2$15                          final
      n3$11                          final
      n4$7                           final
      f$7                            final
      evidence$32$1                  final
      i1                             final

  public static java.lang.Object $anonfun$tabulate$15$adapted(scala.collection.ClassTagIterableFactory, int, int, int, int, scala.Function5, scala.reflect.ClassTag, java.lang.Object);
    descriptor: (Lscala/collection/ClassTagIterableFactory;IIIILscala/Function5;Lscala/reflect/ClassTag;Ljava/lang/Object;)Ljava/lang/Object;
    flags: (0x1009) ACC_PUBLIC, ACC_STATIC, ACC_SYNTHETIC
    Code:
      stack=8, locals=8, args_size=8
         0: aload_0
         1: iload_1
         2: iload_2
         3: iload_3
         4: iload         4
         6: aload         5
         8: aload         6
        10: aload         7
        12: invokestatic  #362                // Method scala/runtime/BoxesRunTime.unboxToInt:(Ljava/lang/Object;)I
        15: invokestatic  #370                // InterfaceMethod $anonfun$tabulate$15:(Lscala/collection/ClassTagIterableFactory;IIIILscala/Function5;Lscala/reflect/ClassTag;I)Ljava/lang/Object;
        18: areturn
      LineNumberTable:
        line 658: 0
      LocalVariableTable:
        Start  Length  Slot  Name   Signature
            0      19     0 $this   Lscala/collection/ClassTagIterableFactory;
            0      19     1 n2$16   I
            0      19     2 n3$12   I
            0      19     3  n4$8   I
            0      19     4  n5$4   I
            0      19     5   f$8   Lscala/Function5;
            0      19     6 evidence$33$1   Lscala/reflect/ClassTag;
            0      19     7    i1   Ljava/lang/Object;
    MethodParameters:
      Name                           Flags
      $this                          final
      n2$16                          final
      n3$12                          final
      n4$8                           final
      n5$4                           final
      f$8                            final
      evidence$33$1                  final
      i1                             final

  public static java.lang.Object $anonfun$tabulate$10$adapted(scala.Function2, int, java.lang.Object);
    descriptor: (Lscala/Function2;ILjava/lang/Object;)Ljava/lang/Object;
    flags: (0x1009) ACC_PUBLIC, ACC_STATIC, ACC_SYNTHETIC
    Code:
      stack=3, locals=3, args_size=3
         0: aload_0
         1: iload_1
         2: aload_2
         3: invokestatic  #362                // Method scala/runtime/BoxesRunTime.unboxToInt:(Ljava/lang/Object;)I
         6: invokestatic  #372                // InterfaceMethod $anonfun$tabulate$10:(Lscala/Function2;II)Ljava/lang/Object;
         9: areturn
      LineNumberTable:
        line 622: 0
      LocalVariableTable:
        Start  Length  Slot  Name   Signature
            0      10     0   f$5   Lscala/Function2;
            0      10     1  i1$5   I
            0      10     2  x$15   Ljava/lang/Object;
    MethodParameters:
      Name                           Flags
      f$5                            final
      i1$5                           final
      x$15                           final

  public static java.lang.Object $anonfun$tabulate$12$adapted(scala.Function3, int, java.lang.Object, java.lang.Object);
    descriptor: (Lscala/Function3;ILjava/lang/Object;Ljava/lang/Object;)Ljava/lang/Object;
    flags: (0x1009) ACC_PUBLIC, ACC_STATIC, ACC_SYNTHETIC
    Code:
      stack=4, locals=4, args_size=4
         0: aload_0
         1: iload_1
         2: aload_2
         3: invokestatic  #362                // Method scala/runtime/BoxesRunTime.unboxToInt:(Ljava/lang/Object;)I
         6: aload_3
         7: invokestatic  #362                // Method scala/runtime/BoxesRunTime.unboxToInt:(Ljava/lang/Object;)I
        10: invokestatic  #374                // InterfaceMethod $anonfun$tabulate$12:(Lscala/Function3;III)Ljava/lang/Object;
        13: areturn
      LineNumberTable:
        line 633: 0
      LocalVariableTable:
        Start  Length  Slot  Name   Signature
            0      14     0   f$6   Lscala/Function3;
            0      14     1  i1$6   I
            0      14     2  x$16   Ljava/lang/Object;
            0      14     3  x$17   Ljava/lang/Object;
    MethodParameters:
      Name                           Flags
      f$6                            final
      i1$6                           final
      x$16                           final
      x$17                           final

  public static java.lang.Object $anonfun$tabulate$14$adapted(scala.Function4, int, java.lang.Object, java.lang.Object, java.lang.Object);
    descriptor: (Lscala/Function4;ILjava/lang/Object;Ljava/lang/Object;Ljava/lang/Object;)Ljava/lang/Object;
    flags: (0x1009) ACC_PUBLIC, ACC_STATIC, ACC_SYNTHETIC
    Code:
      stack=5, locals=5, args_size=5
         0: aload_0
         1: iload_1
         2: aload_2
         3: invokestatic  #362                // Method scala/runtime/BoxesRunTime.unboxToInt:(Ljava/lang/Object;)I
         6: aload_3
         7: invokestatic  #362                // Method scala/runtime/BoxesRunTime.unboxToInt:(Ljava/lang/Object;)I
        10: aload         4
        12: invokestatic  #362                // Method scala/runtime/BoxesRunTime.unboxToInt:(Ljava/lang/Object;)I
        15: invokestatic  #376                // InterfaceMethod $anonfun$tabulate$14:(Lscala/Function4;IIII)Ljava/lang/Object;
        18: areturn
      LineNumberTable:
        line 645: 0
      LocalVariableTable:
        Start  Length  Slot  Name   Signature
            0      19     0   f$7   Lscala/Function4;
            0      19     1  i1$7   I
            0      19     2  x$18   Ljava/lang/Object;
            0      19     3  x$19   Ljava/lang/Object;
            0      19     4  x$20   Ljava/lang/Object;
    MethodParameters:
      Name                           Flags
      f$7                            final
      i1$7                           final
      x$18                           final
      x$19                           final
      x$20                           final

  public static java.lang.Object $anonfun$tabulate$16$adapted(scala.Function5, int, java.lang.Object, java.lang.Object, java.lang.Object, java.lang.Object);
    descriptor: (Lscala/Function5;ILjava/lang/Object;Ljava/lang/Object;Ljava/lang/Object;Ljava/lang/Object;)Ljava/lang/Object;
    flags: (0x1009) ACC_PUBLIC, ACC_STATIC, ACC_SYNTHETIC
    Code:
      stack=6, locals=6, args_size=6
         0: aload_0
         1: iload_1
         2: aload_2
         3: invokestatic  #362                // Method scala/runtime/BoxesRunTime.unboxToInt:(Ljava/lang/Object;)I
         6: aload_3
         7: invokestatic  #362                // Method scala/runtime/BoxesRunTime.unboxToInt:(Ljava/lang/Object;)I
        10: aload         4
        12: invokestatic  #362                // Method scala/runtime/BoxesRunTime.unboxToInt:(Ljava/lang/Object;)I
        15: aload         5
        17: invokestatic  #362                // Method scala/runtime/BoxesRunTime.unboxToInt:(Ljava/lang/Object;)I
        20: invokestatic  #378                // InterfaceMethod $anonfun$tabulate$16:(Lscala/Function5;IIIII)Ljava/lang/Object;
        23: areturn
      LineNumberTable:
        line 658: 0
      LocalVariableTable:
        Start  Length  Slot  Name   Signature
            0      24     0   f$8   Lscala/Function5;
            0      24     1  i1$8   I
            0      24     2  x$21   Ljava/lang/Object;
            0      24     3  x$22   Ljava/lang/Object;
            0      24     4  x$23   Ljava/lang/Object;
            0      24     5  x$24   Ljava/lang/Object;
    MethodParameters:
      Name                           Flags
      f$8                            final
      i1$8                           final
      x$21                           final
      x$22                           final
      x$23                           final
      x$24                           final

  private static java.lang.Object $deserializeLambda$(java.lang.invoke.SerializedLambda);
    descriptor: (Ljava/lang/invoke/SerializedLambda;)Ljava/lang/Object;
    flags: (0x100a) ACC_PRIVATE, ACC_STATIC, ACC_SYNTHETIC
    Code:
      stack=1, locals=1, args_size=1
         0: aload_0
         1: invokedynamic #390,  0            // InvokeDynamic #12:lambdaDeserialize:(Ljava/lang/invoke/SerializedLambda;)Ljava/lang/Object;
         6: areturn
}
InnerClasses:
  public static final #16= #13 of #15;    // Lookup=class java/lang/invoke/MethodHandles$Lookup of class java/lang/invoke/MethodHandles
  public static #19= #18 of #2;           // AnyIterableDelegate=class scala/collection/ClassTagIterableFactory$AnyIterableDelegate of class scala/collection/ClassTagIterableFactory
  public static #22= #21 of #2;           // Delegate=class scala/collection/ClassTagIterableFactory$Delegate of class scala/collection/ClassTagIterableFactory
  public static #27= #24 of #26;          // Exclusive=class scala/collection/immutable/NumericRange$Exclusive of class scala/collection/immutable/NumericRange
Signature: #3                           // <CC:Ljava/lang/Object;>Ljava/lang/Object;Lscala/collection/EvidenceIterableFactory<TCC;Lscala/reflect/ClassTag;>;
SourceFile: "Factory.scala"
RuntimeVisibleAnnotations:
  0: #9(#10=s#11)
    scala.reflect.ScalaSignature(
      bytes="\u0006\u0005\rEgaB\u0011#!\u0003\r\ta\n\u0005\u0006\u000b\u0002!\tA\u0012\u0005\u0007\u0015\u0002\u0001K1B&\t\u000bY\u0003A\u0011A,\t\u000bY\u0003A\u0011\u00018\t\u000by\u0004A\u0011A@\t\ry\u0004A\u0011AA!\u0011\u0019q\b\u0001\"\u0001\u0002h!1a\u0010\u0001C\u0001\u0003#Cq!a0\u0001\t\u0003\t\t\rC\u0004\u0002@\u0002!\t!a:\t\u000f\u0005}\u0006\u0001\"\u0001\u0003\u0010!9\u0011q\u0018\u0001\u0005\u0002\tmra\u0002B6E!\u0005!Q\u000e\u0004\u0007C\tB\tAa\u001c\t\u000f\t\u0005e\u0002\"\u0001\u0003\u0004\u001a1!Q\u0011\b\u0001\u0005\u000fC!Ba)\u0011\u0005\u0003\u0005\u000b\u0011\u0002BS\u0011\u001d\u0011\t\t\u0005C\u0001\u0005O3aAa/\u000f\u0001\tu\u0006B\u0003BR\'\t\u0005\t\u0015!\u0003\u0003R\"9!\u0011Q\n\u0005\u0002\tM\u0007b\u0002Bm\'\u0011\u0005!1\u001c\u0005\b\u0005K\u001cB\u0011\u0001Bt\u0011\u001d\u0011Yp\u0005C\u0001\u0005{Dqaa\u0005\u0014\t\u0003\u001a)\u0002C\u0004\u0004*M!\tea\u000b\t\u000f\r\u00153\u0003\"\u0011\u0004H!1ak\u0005C!\u0007[BaAV\n\u0005B\r\r\u0005B\u0002@\u0014\t\u0003\u001aI\nC\u0004\u0002@N!\te!,\t\u0013\r\u0005g\"!A\u0005\n\r\r\'aF\"mCN\u001cH+Y4Ji\u0016\u0014\u0018M\u00197f\r\u0006\u001cGo\u001c:z\u0015\t\u0019C%\u0001\u0006d_2dWm\u0019;j_:T\u0011!J\u0001\u0006g\u000e\fG.Y\u0002\u0001+\tA3gE\u0002\u0001S5\u0002\"AK\u0016\u000e\u0003\u0011J!\u0001\f\u0013\u0003\r\u0005s\u0017PU3g!\u0011qs&M \u000e\u0003\tJ!\u0001\r\u0012\u0003/\u00153\u0018\u000eZ3oG\u0016LE/\u001a:bE2,g)Y2u_JL\bC\u0001\u001a4\u0019\u0001!a\u0001\u000e\u0001\u0005\u0006\u0004)$AA\"D+\t1T(\u0005\u00028uA\u0011!\u0006O\u0005\u0003s\u0011\u0012qAT8uQ&tw\r\u0005\u0002+w%\u0011A\b\n\u0002\u0004\u0003:LH!\u0002 4\u0005\u00041$!B0%IM\u0002\u0004C\u0001!D\u001b\u0005\t%B\u0001\"%\u0003\u001d\u0011XM\u001a7fGRL!\u0001R!\u0003\u0011\rc\u0017m]:UC\u001e\fa\u0001J5oSR$C#A$\u0011\u0005)B\u0015BA%%\u0005\u0011)f.\u001b;\u0002\u0015\r\u001c7\t\\1tgR\u000bw-\u0006\u0002M!V\tQ\nE\u0002A\u0007:\u00032AM\u001aP!\t\u0011\u0004\u000bB\u0003R\u0005\t\u0007aGA\u0001YQ\t\u00111\u000b\u0005\u0002+)&\u0011Q\u000b\n\u0002\u0007S:d\u0017N\\3\u0002\u000bI\fgnZ3\u0016\u0005acFcA-kYR\u0019!LX4\u0011\u0007I\u001a4\f\u0005\u000239\u0012)Ql\u0001b\u0001m\t\t\u0011\tC\u0004`\u0007\u0005\u0005\t9\u00011\u0002\u0017\u00154\u0018\u000eZ3oG\u0016$#G\r\t\u0004C\u0012\\fB\u0001\u0016c\u0013\t\u0019G%A\u0004qC\u000e\\\u0017mZ3\n\u0005\u00154\'\u0001C%oi\u0016<\'/\u00197\u000b\u0005\r$\u0003b\u00025\u0004\u0003\u0003\u0005\u001d![\u0001\fKZLG-\u001a8dK\u0012\u00124\u0007E\u0002A\u0007nCQa[\u0002A\u0002m\u000bQa\u001d;beRDQ!\\\u0002A\u0002m\u000b1!\u001a8e+\ty7\u000f\u0006\u0003qundHcA9uoB\u0019!g\r:\u0011\u0005I\u001aH!B/\u0005\u0005\u00041\u0004bB;\u0005\u0003\u0003\u0005\u001dA^\u0001\fKZLG-\u001a8dK\u0012\u0012D\u0007E\u0002bIJDq\u0001\u001f\u0003\u0002\u0002\u0003\u000f\u00110A\u0006fm&$WM\\2fII*\u0004c\u0001!De\")1\u000e\u0002a\u0001e\")Q\u000e\u0002a\u0001e\")Q\u0010\u0002a\u0001e\u0006!1\u000f^3q\u0003\u00111\u0017\u000e\u001c7\u0016\t\u0005\u0005\u0011q\u0002\u000b\u0007\u0003\u0007\t\u0019$!\u0010\u0015\t\u0005\u0015\u0011\u0011\u0006\u000b\u0005\u0003\u000f\t\u0019\u0003\u0005\u00033g\u0005%!\u0006BA\u0006\u0003#\u0001BAM\u001a\u0002\u000eA\u0019!\'a\u0004\u0005\u000bu+!\u0019\u0001\u001c,\u0005\u0005M\u0001\u0003BA\u000b\u0003?i!!a\u0006\u000b\t\u0005e\u00111D\u0001\nk:\u001c\u0007.Z2lK\u0012T1!!\b%\u0003)\tgN\\8uCRLwN\\\u0005\u0005\u0003C\t9BA\tv]\u000eDWmY6fIZ\u000b\'/[1oG\u0016D\u0011\"!\n\u0006\u0003\u0003\u0005\u001d!a\n\u0002\u0017\u00154\u0018\u000eZ3oG\u0016$#G\u000e\t\u0005\u0001\u000e\u000bi\u0001\u0003\u0005\u0002,\u0015!\t\u0019AA\u0017\u0003\u0011)G.Z7\u0011\u000b)\ny#!\u0004\n\u0007\u0005EBE\u0001\u0005=Eft\u0017-\\3?\u0011\u001d\t)$\u0002a\u0001\u0003o\t!A\\\u0019\u0011\u0007)\nI$C\u0002\u0002<\u0011\u00121!\u00138u\u0011\u001d\ty$\u0002a\u0001\u0003o\t!A\u001c\u001a\u0016\t\u0005\r\u00131\u000b\u000b\t\u0003\u000b\ny&!\u0019\u0002dQ!\u0011qIA.)\u0011\tI%!\u0016\u0011\tI\u001a\u00141\n\u0016\u0005\u0003\u001b\n\t\u0002\u0005\u00033g\u0005=\u0003\u0003\u0002\u001a4\u0003#\u00022AMA*\t\u0015ifA1\u00017\u0011%\t9FBA\u0001\u0002\b\tI&A\u0006fm&$WM\\2fII:\u0004\u0003\u0002!D\u0003#B\u0001\"a\u000b\u0007\t\u0003\u0007\u0011Q\f\t\u0006U\u0005=\u0012\u0011\u000b\u0005\b\u0003k1\u0001\u0019AA\u001c\u0011\u001d\tyD\u0002a\u0001\u0003oAq!!\u001a\u0007\u0001\u0004\t9$\u0001\u0002ogU!\u0011\u0011NA>))\tY\'a\"\u0002\n\u0006-\u0015Q\u0012\u000b\u0005\u0003[\n\u0019\t\u0006\u0003\u0002p\u0005u\u0004\u0003\u0002\u001a4\u0003cRC!a\u001d\u0002\u0012A!!gMA;!\u0011\u00114\'a\u001e\u0011\tI\u001a\u0014\u0011\u0010\t\u0004e\u0005mD!B/\b\u0005\u00041\u0004\"CA@\u000f\u0005\u0005\t9AAA\u0003-)g/\u001b3f]\u000e,GE\r\u001d\u0011\t\u0001\u001b\u0015\u0011\u0010\u0005\t\u0003W9A\u00111\u0001\u0002\u0006B)!&a\f\u0002z!9\u0011QG\u0004A\u0002\u0005]\u0002bBA \u000f\u0001\u0007\u0011q\u0007\u0005\b\u0003K:\u0001\u0019AA\u001c\u0011\u001d\tyi\u0002a\u0001\u0003o\t!A\u001c\u001b\u0016\t\u0005M\u0015q\u0015\u000b\r\u0003+\u000b\u0019,!.\u00028\u0006e\u00161\u0018\u000b\u0005\u0003/\u000by\u000b\u0006\u0003\u0002\u001a\u0006%\u0006\u0003\u0002\u001a4\u00037SC!!(\u0002\u0012A!!gMAP!\u0011\u00114\'!)\u0011\tI\u001a\u00141\u0015\t\u0005eM\n)\u000bE\u00023\u0003O#Q!\u0018\u0005C\u0002YB\u0011\"a+\t\u0003\u0003\u0005\u001d!!,\u0002\u0017\u00154\u0018\u000eZ3oG\u0016$#\'\u000f\t\u0005\u0001\u000e\u000b)\u000b\u0003\u0005\u0002,!!\t\u0019AAY!\u0015Q\u0013qFAS\u0011\u001d\t)\u0004\u0003a\u0001\u0003oAq!a\u0010\t\u0001\u0004\t9\u0004C\u0004\u0002f!\u0001\r!a\u000e\t\u000f\u0005=\u0005\u00021\u0001\u00028!9\u0011Q\u0018\u0005A\u0002\u0005]\u0012A\u000186\u0003!!\u0018MY;mCR,W\u0003BAb\u0003#$b!!2\u0002d\u0006\u0015H\u0003BAd\u00033$B!!3\u0002TB!!gMAfU\u0011\ti-!\u0005\u0011\tI\u001a\u0014q\u001a\t\u0004e\u0005EG!B/\n\u0005\u00041\u0004\"CAk\u0013\u0005\u0005\t9AAl\u0003-)g/\u001b3f]\u000e,Ge\r\u0019\u0011\t\u0001\u001b\u0015q\u001a\u0005\b\u00037L\u0001\u0019AAo\u0003\u00051\u0007#\u0003\u0016\u0002`\u0006]\u0012qGAh\u0013\r\t\t\u000f\n\u0002\n\rVt7\r^5p]JBq!!\u000e\n\u0001\u0004\t9\u0004C\u0004\u0002@%\u0001\r!a\u000e\u0016\t\u0005%\u0018\u0011 \u000b\t\u0003W\u0014IAa\u0003\u0003\u000eQ!\u0011Q\u001eB\u0001)\u0011\ty/a?\u0011\tI\u001a\u0014\u0011\u001f\u0016\u0005\u0003g\f\t\u0002\u0005\u00033g\u0005U\b\u0003\u0002\u001a4\u0003o\u00042AMA}\t\u0015i&B1\u00017\u0011%\tiPCA\u0001\u0002\b\ty0A\u0006fm&$WM\\2fIM\n\u0004\u0003\u0002!D\u0003oDq!a7\u000b\u0001\u0004\u0011\u0019\u0001E\u0006+\u0005\u000b\t9$a\u000e\u00028\u0005]\u0018b\u0001B\u0004I\tIa)\u001e8di&|gn\r\u0005\b\u0003kQ\u0001\u0019AA\u001c\u0011\u001d\tyD\u0003a\u0001\u0003oAq!!\u001a\u000b\u0001\u0004\t9$\u0006\u0003\u0003\u0012\t\rBC\u0003B\n\u0005g\u0011)Da\u000e\u0003:Q!!Q\u0003B\u0016)\u0011\u00119B!\n\u0011\tI\u001a$\u0011\u0004\u0016\u0005\u00057\t\t\u0002\u0005\u00033g\tu\u0001\u0003\u0002\u001a4\u0005?\u0001BAM\u001a\u0003\"A\u0019!Ga\t\u0005\u000bu[!\u0019\u0001\u001c\t\u0013\t\u001d2\"!AA\u0004\t%\u0012aC3wS\u0012,gnY3%gI\u0002B\u0001Q\"\u0003\"!9\u00111\\\u0006A\u0002\t5\u0002#\u0004\u0016\u00030\u0005]\u0012qGA\u001c\u0003o\u0011\t#C\u0002\u00032\u0011\u0012\u0011BR;oGRLwN\u001c\u001b\t\u000f\u0005U2\u00021\u0001\u00028!9\u0011qH\u0006A\u0002\u0005]\u0002bBA3\u0017\u0001\u0007\u0011q\u0007\u0005\b\u0003\u001f[\u0001\u0019AA\u001c+\u0011\u0011iD!\u0015\u0015\u0019\t}\"\u0011\rB2\u0005K\u00129G!\u001b\u0015\t\t\u0005#\u0011\f\u000b\u0005\u0005\u0007\u0012\u0019\u0006\u0005\u00033g\t\u0015#\u0006\u0002B$\u0003#\u0001BAM\u001a\u0003JA!!g\rB&!\u0011\u00114G!\u0014\u0011\tI\u001a$q\n\t\u0004e\tEC!B/\r\u0005\u00041\u0004\"\u0003B+\u0019\u0005\u0005\t9\u0001B,\u0003-)g/\u001b3f]\u000e,GeM\u001a\u0011\t\u0001\u001b%q\n\u0005\b\u00037d\u0001\u0019\u0001B.!=Q#QLA\u001c\u0003o\t9$a\u000e\u00028\t=\u0013b\u0001B0I\tIa)\u001e8di&|g.\u000e\u0005\b\u0003ka\u0001\u0019AA\u001c\u0011\u001d\ty\u0004\u0004a\u0001\u0003oAq!!\u001a\r\u0001\u0004\t9\u0004C\u0004\u0002\u00102\u0001\r!a\u000e\t\u000f\u0005uF\u00021\u0001\u00028\u000592\t\\1tgR\u000bw-\u0013;fe\u0006\u0014G.\u001a$bGR|\'/\u001f\t\u0003]9\u0019BAD\u0015\u0003rA!!1\u000fB?\u001b\t\u0011)H\u0003\u0003\u0003x\te\u0014AA5p\u0015\t\u0011Y(\u0001\u0003kCZ\f\u0017\u0002\u0002B@\u0005k\u0012AbU3sS\u0006d\u0017N_1cY\u0016\fa\u0001P5oSRtDC\u0001B7\u0005!!U\r\\3hCR,W\u0003\u0002BE\u00053\u001bR\u0001\u0005BF\u0005C\u0003rA!$\u0003\u0014\n]uHD\u0002/\u0005\u001fK1A!%#\u0003])e/\u001b3f]\u000e,\u0017\n^3sC\ndWMR1di>\u0014\u00180\u0003\u0003\u0003\u0006\nU%b\u0001BIEA\u0019!G!\'\u0005\rQ\u0002\"\u0019\u0001BN+\r1$Q\u0014\u0003\b\u0005?\u0013IJ1\u00017\u0005\u0015yF\u0005J\u001a2!\u0011q\u0003Aa&\u0002\u0011\u0011,G.Z4bi\u0016\u0004RAL\u0018\u0003\u0018~\"BA!+\u0003.B)!1\u0016\t\u0003\u00186\ta\u0002C\u0004\u0003$J\u0001\rA!*)\u000fA\u0011\tLa.\u0003:B\u0019!Fa-\n\u0007\tUFE\u0001\tTKJL\u0017\r\u001c,feNLwN\\+J\t\u0006)a/\u00197vKz\t1AA\nB]fLE/\u001a:bE2,G)\u001a7fO\u0006$X-\u0006\u0003\u0003@\n%7\u0003B\n*\u0005\u0003\u0004RA\fBb\u0005\u000fL1A!2#\u0005=IE/\u001a:bE2,g)Y2u_JL\bc\u0001\u001a\u0003J\u00121Ag\u0005b\u0001\u0005\u0017,2A\u000eBg\t\u001d\u0011yM!3C\u0002Y\u0012Qa\u0018\u0013%gI\u0002BA\f\u0001\u0003HR!!Q\u001bBl!\u0015\u0011Yk\u0005Bd\u0011\u001d\u0011\u0019+\u0006a\u0001\u0005#\fQ!Z7qif,BA!8\u0003dV\u0011!q\u001c\t\u0006e\t%\'\u0011\u001d\t\u0004e\t\rH!B/\u0017\u0005\u00041\u0014\u0001\u00024s_6,BA!;\u0003pR!!1\u001eBy!\u0015\u0011$\u0011\u001aBw!\r\u0011$q\u001e\u0003\u0006;^\u0011\rA\u000e\u0005\b\u0005g<\u0002\u0019\u0001B{\u0003\tIG\u000fE\u0003/\u0005o\u0014i/C\u0002\u0003z\n\u0012A\"\u0013;fe\u0006\u0014G.Z(oG\u0016\f!B\\3x\u0005VLG\u000eZ3s+\u0011\u0011ypa\u0004\u0016\u0005\r\u0005\u0001\u0003CB\u0002\u0007\u0013\u0019ia!\u0005\u000e\u0005\r\u0015!bAB\u0004E\u00059Q.\u001e;bE2,\u0017\u0002BB\u0006\u0007\u000b\u0011qAQ;jY\u0012,\'\u000fE\u00023\u0007\u001f!Q!\u0018\rC\u0002Y\u0002RA\rBe\u0007\u001b\tQ!\u00199qYf,Baa\u0006\u0004\u001eQ!1\u0011DB\u0010!\u0015\u0011$\u0011ZB\u000e!\r\u00114Q\u0004\u0003\u0006;f\u0011\rA\u000e\u0005\b\u0007CI\u0002\u0019AB\u0012\u0003\u0015)G.Z7t!\u0015Q3QEB\u000e\u0013\r\u00199\u0003\n\u0002\u000byI,\u0007/Z1uK\u0012t\u0014aB5uKJ\fG/Z\u000b\u0005\u0007[\u0019)\u0004\u0006\u0004\u00040\r}2\u0011\t\u000b\u0005\u0007c\u00199\u0004E\u00033\u0005\u0013\u001c\u0019\u0004E\u00023\u0007k!Q!\u0018\u000eC\u0002YBq!a7\u001b\u0001\u0004\u0019I\u0004E\u0004+\u0007w\u0019\u0019da\r\n\u0007\ruBEA\u0005Gk:\u001cG/[8oc!11N\u0007a\u0001\u0007gAqaa\u0011\u001b\u0001\u0004\t9$A\u0002mK:\fa!\u001e8g_2$WCBB%\u0007#\u001aI\u0006\u0006\u0003\u0004L\r%D\u0003BB\'\u0007\'\u0002RA\rBe\u0007\u001f\u00022AMB)\t\u0015i6D1\u00017\u0011\u001d\tYn\u0007a\u0001\u0007+\u0002rAKB\u001e\u0007/\u001ai\u0006E\u00023\u00073\"aaa\u0017\u001c\u0005\u00041$!A*\u0011\u000b)\u001ayfa\u0019\n\u0007\r\u0005DE\u0001\u0004PaRLwN\u001c\t\bU\r\u00154qJB,\u0013\r\u00199\u0007\n\u0002\u0007)V\u0004H.\u001a\u001a\t\u000f\r-4\u00041\u0001\u0004X\u0005!\u0011N\\5u+\u0011\u0019yga\u001e\u0015\r\rE4qPBA)\u0011\u0019\u0019h!\u001f\u0011\u000bI\u0012Im!\u001e\u0011\u0007I\u001a9\bB\u0003^9\t\u0007a\u0007C\u0004\u0004|q\u0001\u001da! \u0002\u0003%\u0004B!\u00193\u0004v!11\u000e\ba\u0001\u0007kBa!\u001c\u000fA\u0002\rUT\u0003BBC\u0007\u001b#\u0002ba\"\u0004\u0014\u000eU5q\u0013\u000b\u0005\u0007\u0013\u001by\tE\u00033\u0005\u0013\u001cY\tE\u00023\u0007\u001b#Q!X\u000fC\u0002YBqaa\u001f\u001e\u0001\b\u0019\t\n\u0005\u0003bI\u000e-\u0005BB6\u001e\u0001\u0004\u0019Y\t\u0003\u0004n;\u0001\u000711\u0012\u0005\u0007{v\u0001\raa#\u0016\t\rm51\u0015\u000b\u0005\u0007;\u001bI\u000b\u0006\u0003\u0004 \u000e\u0015\u0006#\u0002\u001a\u0003J\u000e\u0005\u0006c\u0001\u001a\u0004$\u0012)QL\bb\u0001m!A\u00111\u0006\u0010\u0005\u0002\u0004\u00199\u000bE\u0003+\u0003_\u0019\t\u000bC\u0004\u0004,z\u0001\r!a\u000e\u0002\u00039,Baa,\u00048R!1\u0011WB_)\u0011\u0019\u0019l!/\u0011\u000bI\u0012Im!.\u0011\u0007I\u001a9\fB\u0003^?\t\u0007a\u0007C\u0004\u0002\\~\u0001\raa/\u0011\u000f)\u001aY$a\u000e\u00046\"911V\u0010A\u0002\u0005]\u0002fB\n\u00032\n]&\u0011X\u0001\roJLG/\u001a*fa2\f7-\u001a\u000b\u0003\u0007\u000b\u0004Baa2\u0004N6\u00111\u0011\u001a\u0006\u0005\u0007\u0017\u0014I(\u0001\u0003mC:<\u0017\u0002BBh\u0007\u0013\u0014aa\u00142kK\u000e$\b"
    )
BootstrapMethods:
  0: #111 REF_invokeStatic java/lang/invoke/LambdaMetafactory.altMetafactory:(Ljava/lang/invoke/MethodHandles$Lookup;Ljava/lang/String;Ljava/lang/invoke/MethodType;[Ljava/lang/Object;)Ljava/lang/invoke/CallSite;
    Method arguments:
      #98 ()Ljava/lang/Object;
      #103 REF_invokeStatic scala/collection/ClassTagIterableFactory.$anonfun$fill$5:(Lscala/collection/ClassTagIterableFactory;ILscala/Function0;Lscala/reflect/ClassTag;)Ljava/lang/Object;
      #98 ()Ljava/lang/Object;
      #104 1
  1: #111 REF_invokeStatic java/lang/invoke/LambdaMetafactory.altMetafactory:(Ljava/lang/invoke/MethodHandles$Lookup;Ljava/lang/String;Ljava/lang/invoke/MethodType;[Ljava/lang/Object;)Ljava/lang/invoke/CallSite;
    Method arguments:
      #98 ()Ljava/lang/Object;
      #129 REF_invokeStatic scala/collection/ClassTagIterableFactory.$anonfun$fill$6:(Lscala/collection/ClassTagIterableFactory;IILscala/Function0;Lscala/reflect/ClassTag;)Ljava/lang/Object;
      #98 ()Ljava/lang/Object;
      #104 1
  2: #111 REF_invokeStatic java/lang/invoke/LambdaMetafactory.altMetafactory:(Ljava/lang/invoke/MethodHandles$Lookup;Ljava/lang/String;Ljava/lang/invoke/MethodType;[Ljava/lang/Object;)Ljava/lang/invoke/CallSite;
    Method arguments:
      #98 ()Ljava/lang/Object;
      #143 REF_invokeStatic scala/collection/ClassTagIterableFactory.$anonfun$fill$7:(Lscala/collection/ClassTagIterableFactory;IIILscala/Function0;Lscala/reflect/ClassTag;)Ljava/lang/Object;
      #98 ()Ljava/lang/Object;
      #104 1
  3: #111 REF_invokeStatic java/lang/invoke/LambdaMetafactory.altMetafactory:(Ljava/lang/invoke/MethodHandles$Lookup;Ljava/lang/String;Ljava/lang/invoke/MethodType;[Ljava/lang/Object;)Ljava/lang/invoke/CallSite;
    Method arguments:
      #98 ()Ljava/lang/Object;
      #157 REF_invokeStatic scala/collection/ClassTagIterableFactory.$anonfun$fill$8:(Lscala/collection/ClassTagIterableFactory;IIIILscala/Function0;Lscala/reflect/ClassTag;)Ljava/lang/Object;
      #98 ()Ljava/lang/Object;
      #104 1
  4: #111 REF_invokeStatic java/lang/invoke/LambdaMetafactory.altMetafactory:(Ljava/lang/invoke/MethodHandles$Lookup;Ljava/lang/String;Ljava/lang/invoke/MethodType;[Ljava/lang/Object;)Ljava/lang/invoke/CallSite;
    Method arguments:
      #172 (Ljava/lang/Object;)Ljava/lang/Object;
      #177 REF_invokeStatic scala/collection/ClassTagIterableFactory.$anonfun$tabulate$9$adapted:(Lscala/collection/ClassTagIterableFactory;ILscala/Function2;Lscala/reflect/ClassTag;Ljava/lang/Object;)Ljava/lang/Object;
      #172 (Ljava/lang/Object;)Ljava/lang/Object;
      #104 1
  5: #111 REF_invokeStatic java/lang/invoke/LambdaMetafactory.altMetafactory:(Ljava/lang/invoke/MethodHandles$Lookup;Ljava/lang/String;Ljava/lang/invoke/MethodType;[Ljava/lang/Object;)Ljava/lang/invoke/CallSite;
    Method arguments:
      #172 (Ljava/lang/Object;)Ljava/lang/Object;
      #195 REF_invokeStatic scala/collection/ClassTagIterableFactory.$anonfun$tabulate$11$adapted:(Lscala/collection/ClassTagIterableFactory;IILscala/Function3;Lscala/reflect/ClassTag;Ljava/lang/Object;)Ljava/lang/Object;
      #172 (Ljava/lang/Object;)Ljava/lang/Object;
      #104 1
  6: #111 REF_invokeStatic java/lang/invoke/LambdaMetafactory.altMetafactory:(Ljava/lang/invoke/MethodHandles$Lookup;Ljava/lang/String;Ljava/lang/invoke/MethodType;[Ljava/lang/Object;)Ljava/lang/invoke/CallSite;
    Method arguments:
      #172 (Ljava/lang/Object;)Ljava/lang/Object;
      #210 REF_invokeStatic scala/collection/ClassTagIterableFactory.$anonfun$tabulate$13$adapted:(Lscala/collection/ClassTagIterableFactory;IIILscala/Function4;Lscala/reflect/ClassTag;Ljava/lang/Object;)Ljava/lang/Object;
      #172 (Ljava/lang/Object;)Ljava/lang/Object;
      #104 1
  7: #111 REF_invokeStatic java/lang/invoke/LambdaMetafactory.altMetafactory:(Ljava/lang/invoke/MethodHandles$Lookup;Ljava/lang/String;Ljava/lang/invoke/MethodType;[Ljava/lang/Object;)Ljava/lang/invoke/CallSite;
    Method arguments:
      #172 (Ljava/lang/Object;)Ljava/lang/Object;
      #225 REF_invokeStatic scala/collection/ClassTagIterableFactory.$anonfun$tabulate$15$adapted:(Lscala/collection/ClassTagIterableFactory;IIIILscala/Function5;Lscala/reflect/ClassTag;Ljava/lang/Object;)Ljava/lang/Object;
      #172 (Ljava/lang/Object;)Ljava/lang/Object;
      #104 1
  8: #111 REF_invokeStatic java/lang/invoke/LambdaMetafactory.altMetafactory:(Ljava/lang/invoke/MethodHandles$Lookup;Ljava/lang/String;Ljava/lang/invoke/MethodType;[Ljava/lang/Object;)Ljava/lang/invoke/CallSite;
    Method arguments:
      #172 (Ljava/lang/Object;)Ljava/lang/Object;
      #272 REF_invokeStatic scala/collection/ClassTagIterableFactory.$anonfun$tabulate$10$adapted:(Lscala/Function2;ILjava/lang/Object;)Ljava/lang/Object;
      #172 (Ljava/lang/Object;)Ljava/lang/Object;
      #104 1
  9: #111 REF_invokeStatic java/lang/invoke/LambdaMetafactory.altMetafactory:(Ljava/lang/invoke/MethodHandles$Lookup;Ljava/lang/String;Ljava/lang/invoke/MethodType;[Ljava/lang/Object;)Ljava/lang/invoke/CallSite;
    Method arguments:
      #292 (Ljava/lang/Object;Ljava/lang/Object;)Ljava/lang/Object;
      #297 REF_invokeStatic scala/collection/ClassTagIterableFactory.$anonfun$tabulate$12$adapted:(Lscala/Function3;ILjava/lang/Object;Ljava/lang/Object;)Ljava/lang/Object;
      #292 (Ljava/lang/Object;Ljava/lang/Object;)Ljava/lang/Object;
      #104 1
  10: #111 REF_invokeStatic java/lang/invoke/LambdaMetafactory.altMetafactory:(Ljava/lang/invoke/MethodHandles$Lookup;Ljava/lang/String;Ljava/lang/invoke/MethodType;[Ljava/lang/Object;)Ljava/lang/invoke/CallSite;
    Method arguments:
      #319 (Ljava/lang/Object;Ljava/lang/Object;Ljava/lang/Object;)Ljava/lang/Object;
      #324 REF_invokeStatic scala/collection/ClassTagIterableFactory.$anonfun$tabulate$14$adapted:(Lscala/Function4;ILjava/lang/Object;Ljava/lang/Object;Ljava/lang/Object;)Ljava/lang/Object;
      #319 (Ljava/lang/Object;Ljava/lang/Object;Ljava/lang/Object;)Ljava/lang/Object;
      #104 1
  11: #111 REF_invokeStatic java/lang/invoke/LambdaMetafactory.altMetafactory:(Ljava/lang/invoke/MethodHandles$Lookup;Ljava/lang/String;Ljava/lang/invoke/MethodType;[Ljava/lang/Object;)Ljava/lang/invoke/CallSite;
    Method arguments:
      #348 (Ljava/lang/Object;Ljava/lang/Object;Ljava/lang/Object;Ljava/lang/Object;)Ljava/lang/Object;
      #353 REF_invokeStatic scala/collection/ClassTagIterableFactory.$anonfun$tabulate$16$adapted:(Lscala/Function5;ILjava/lang/Object;Ljava/lang/Object;Ljava/lang/Object;Ljava/lang/Object;)Ljava/lang/Object;
      #348 (Ljava/lang/Object;Ljava/lang/Object;Ljava/lang/Object;Ljava/lang/Object;)Ljava/lang/Object;
      #104 1
  12: #387 REF_invokeStatic scala/runtime/LambdaDeserialize.bootstrap:(Ljava/lang/invoke/MethodHandles$Lookup;Ljava/lang/String;Ljava/lang/invoke/MethodType;[Ljava/lang/invoke/MethodHandle;)Ljava/lang/invoke/CallSite;
    Method arguments:
      #103 REF_invokeStatic scala/collection/ClassTagIterableFactory.$anonfun$fill$5:(Lscala/collection/ClassTagIterableFactory;ILscala/Function0;Lscala/reflect/ClassTag;)Ljava/lang/Object;
      #129 REF_invokeStatic scala/collection/ClassTagIterableFactory.$anonfun$fill$6:(Lscala/collection/ClassTagIterableFactory;IILscala/Function0;Lscala/reflect/ClassTag;)Ljava/lang/Object;
      #143 REF_invokeStatic scala/collection/ClassTagIterableFactory.$anonfun$fill$7:(Lscala/collection/ClassTagIterableFactory;IIILscala/Function0;Lscala/reflect/ClassTag;)Ljava/lang/Object;
      #157 REF_invokeStatic scala/collection/ClassTagIterableFactory.$anonfun$fill$8:(Lscala/collection/ClassTagIterableFactory;IIIILscala/Function0;Lscala/reflect/ClassTag;)Ljava/lang/Object;
      #272 REF_invokeStatic scala/collection/ClassTagIterableFactory.$anonfun$tabulate$10$adapted:(Lscala/Function2;ILjava/lang/Object;)Ljava/lang/Object;
      #195 REF_invokeStatic scala/collection/ClassTagIterableFactory.$anonfun$tabulate$11$adapted:(Lscala/collection/ClassTagIterableFactory;IILscala/Function3;Lscala/reflect/ClassTag;Ljava/lang/Object;)Ljava/lang/Object;
      #297 REF_invokeStatic scala/collection/ClassTagIterableFactory.$anonfun$tabulate$12$adapted:(Lscala/Function3;ILjava/lang/Object;Ljava/lang/Object;)Ljava/lang/Object;
      #210 REF_invokeStatic scala/collection/ClassTagIterableFactory.$anonfun$tabulate$13$adapted:(Lscala/collection/ClassTagIterableFactory;IIILscala/Function4;Lscala/reflect/ClassTag;Ljava/lang/Object;)Ljava/lang/Object;
      #324 REF_invokeStatic scala/collection/ClassTagIterableFactory.$anonfun$tabulate$14$adapted:(Lscala/Function4;ILjava/lang/Object;Ljava/lang/Object;Ljava/lang/Object;)Ljava/lang/Object;
      #225 REF_invokeStatic scala/collection/ClassTagIterableFactory.$anonfun$tabulate$15$adapted:(Lscala/collection/ClassTagIterableFactory;IIIILscala/Function5;Lscala/reflect/ClassTag;Ljava/lang/Object;)Ljava/lang/Object;
      #353 REF_invokeStatic scala/collection/ClassTagIterableFactory.$anonfun$tabulate$16$adapted:(Lscala/Function5;ILjava/lang/Object;Ljava/lang/Object;Ljava/lang/Object;Ljava/lang/Object;)Ljava/lang/Object;
      #177 REF_invokeStatic scala/collection/ClassTagIterableFactory.$anonfun$tabulate$9$adapted:(Lscala/collection/ClassTagIterableFactory;ILscala/Function2;Lscala/reflect/ClassTag;Ljava/lang/Object;)Ljava/lang/Object;
  ScalaInlineInfo: length = 0xD6 (unknown attribute)
   01 00 00 2A 00 63 00 64 01 00 7E 00 56 01 00 8C
   00 77 01 00 9A 00 85 01 00 F7 00 F8 01 01 0C 01
   0D 01 01 1F 01 20 01 00 BF 00 C0 01 01 14 01 15
   01 01 25 01 26 01 01 39 01 3A 01 00 CE 00 CF 01
   01 2D 01 2E 01 01 40 01 41 01 01 55 01 56 01 00
   DD 00 DE 01 01 48 01 49 01 01 5D 01 5E 01 01 07
   01 08 01 00 AD 00 AE 01 01 65 01 66 01 00 1C 00
   1D 05 00 5B 00 96 00 00 5B 00 88 00 00 5B 00 7A
   00 00 5B 00 5C 00 00 55 00 93 01 00 55 00 85 01
   00 55 00 77 01 00 55 00 56 01 00 31 00 51 00 00
   31 00 32 00 00 2A 00 4D 01 00 2A 00 2B 01 00 A5
   00 D8 00 00 A5 00 C9 00 00 A5 00 BA 00 00 A5 00
   A6 00 00 A1 00 D6 01 00 A1 00 C7 01 00 A1 00 B8
   01 00 A1 00 A2 01
  ScalaSig: length = 0x3 (unknown attribute)
   05 02 00
