Classfile /Users/mw/Projects/slang-braindump/.jar/jar8/assemble/slang-braindump/assemble/content/scala/collection/ClassTagIterableFactory$AnyIterableDelegate.class
  Last modified May 29, 2022; size 8329 bytes
  SHA-256 checksum 9b2749182ff49cdd0607c1dc542624587a96766a3efa3c169fe672c4d33f24a6
  Compiled from "Factory.scala"
public class scala.collection.ClassTagIterableFactory$AnyIterableDelegate<CC extends java.lang.Object> extends java.lang.Object implements scala.collection.IterableFactory<CC>
  minor version: 0
  major version: 52
  flags: (0x0021) ACC_PUBLIC, ACC_SUPER
  this_class: #2                          // scala/collection/ClassTagIterableFactory$AnyIterableDelegate
  super_class: #5                         // java/lang/Object
  interfaces: 1, fields: 2, methods: 21, attributes: 5
Constant pool:
    #1 = Utf8               scala/collection/ClassTagIterableFactory$AnyIterableDelegate
    #2 = Class              #1            // scala/collection/ClassTagIterableFactory$AnyIterableDelegate
    #3 = Utf8               <CC:Ljava/lang/Object;>Ljava/lang/Object;Lscala/collection/IterableFactory<TCC;>;
    #4 = Utf8               java/lang/Object
    #5 = Class              #4            // java/lang/Object
    #6 = Utf8               scala/collection/IterableFactory
    #7 = Class              #6            // scala/collection/IterableFactory
    #8 = Utf8               Factory.scala
    #9 = Utf8               scala/collection/ClassTagIterableFactory
   #10 = Class              #9            // scala/collection/ClassTagIterableFactory
   #11 = Utf8               AnyIterableDelegate
   #12 = Utf8               serialVersionUID
   #13 = Utf8               J
   #14 = Long               3l
   #16 = Utf8               delegate
   #17 = Utf8               Lscala/collection/ClassTagIterableFactory;
   #18 = Utf8               Lscala/collection/ClassTagIterableFactory<TCC;>;
   #19 = Utf8               fill
   #20 = Utf8               (IILscala/Function0;)Ljava/lang/Object;
   #21 = Utf8               <A:Ljava/lang/Object;>(IILscala/Function0<TA;>;)TCC;
   #22 = Utf8               n1
   #23 = Utf8               n2
   #24 = Utf8               elem
   #25 = Utf8               fill$
   #26 = Utf8               (Lscala/collection/IterableFactory;IILscala/Function0;)Ljava/lang/Object;
   #27 = NameAndType        #25:#26       // fill$:(Lscala/collection/IterableFactory;IILscala/Function0;)Ljava/lang/Object;
   #28 = InterfaceMethodref #7.#27        // scala/collection/IterableFactory.fill$:(Lscala/collection/IterableFactory;IILscala/Function0;)Ljava/lang/Object;
   #29 = Utf8               this
   #30 = Utf8               Lscala/collection/ClassTagIterableFactory$AnyIterableDelegate;
   #31 = Utf8               I
   #32 = Utf8               Lscala/Function0;
   #33 = Utf8               (IIILscala/Function0;)Ljava/lang/Object;
   #34 = Utf8               <A:Ljava/lang/Object;>(IIILscala/Function0<TA;>;)TCC;
   #35 = Utf8               n3
   #36 = Utf8               (Lscala/collection/IterableFactory;IIILscala/Function0;)Ljava/lang/Object;
   #37 = NameAndType        #25:#36       // fill$:(Lscala/collection/IterableFactory;IIILscala/Function0;)Ljava/lang/Object;
   #38 = InterfaceMethodref #7.#37        // scala/collection/IterableFactory.fill$:(Lscala/collection/IterableFactory;IIILscala/Function0;)Ljava/lang/Object;
   #39 = Utf8               (IIIILscala/Function0;)Ljava/lang/Object;
   #40 = Utf8               <A:Ljava/lang/Object;>(IIIILscala/Function0<TA;>;)TCC;
   #41 = Utf8               n4
   #42 = Utf8               (Lscala/collection/IterableFactory;IIIILscala/Function0;)Ljava/lang/Object;
   #43 = NameAndType        #25:#42       // fill$:(Lscala/collection/IterableFactory;IIIILscala/Function0;)Ljava/lang/Object;
   #44 = InterfaceMethodref #7.#43        // scala/collection/IterableFactory.fill$:(Lscala/collection/IterableFactory;IIIILscala/Function0;)Ljava/lang/Object;
   #45 = Utf8               (IIIIILscala/Function0;)Ljava/lang/Object;
   #46 = Utf8               <A:Ljava/lang/Object;>(IIIIILscala/Function0<TA;>;)TCC;
   #47 = Utf8               n5
   #48 = Utf8               (Lscala/collection/IterableFactory;IIIIILscala/Function0;)Ljava/lang/Object;
   #49 = NameAndType        #25:#48       // fill$:(Lscala/collection/IterableFactory;IIIIILscala/Function0;)Ljava/lang/Object;
   #50 = InterfaceMethodref #7.#49        // scala/collection/IterableFactory.fill$:(Lscala/collection/IterableFactory;IIIIILscala/Function0;)Ljava/lang/Object;
   #51 = Utf8               tabulate
   #52 = Utf8               (IILscala/Function2;)Ljava/lang/Object;
   #53 = Utf8               <A:Ljava/lang/Object;>(IILscala/Function2<Ljava/lang/Object;Ljava/lang/Object;TA;>;)TCC;
   #54 = Utf8               f
   #55 = Utf8               tabulate$
   #56 = Utf8               (Lscala/collection/IterableFactory;IILscala/Function2;)Ljava/lang/Object;
   #57 = NameAndType        #55:#56       // tabulate$:(Lscala/collection/IterableFactory;IILscala/Function2;)Ljava/lang/Object;
   #58 = InterfaceMethodref #7.#57        // scala/collection/IterableFactory.tabulate$:(Lscala/collection/IterableFactory;IILscala/Function2;)Ljava/lang/Object;
   #59 = Utf8               Lscala/Function2;
   #60 = Utf8               (IIILscala/Function3;)Ljava/lang/Object;
   #61 = Utf8               <A:Ljava/lang/Object;>(IIILscala/Function3<Ljava/lang/Object;Ljava/lang/Object;Ljava/lang/Object;TA;>;)TCC;
   #62 = Utf8               (Lscala/collection/IterableFactory;IIILscala/Function3;)Ljava/lang/Object;
   #63 = NameAndType        #55:#62       // tabulate$:(Lscala/collection/IterableFactory;IIILscala/Function3;)Ljava/lang/Object;
   #64 = InterfaceMethodref #7.#63        // scala/collection/IterableFactory.tabulate$:(Lscala/collection/IterableFactory;IIILscala/Function3;)Ljava/lang/Object;
   #65 = Utf8               Lscala/Function3;
   #66 = Utf8               (IIIILscala/Function4;)Ljava/lang/Object;
   #67 = Utf8               <A:Ljava/lang/Object;>(IIIILscala/Function4<Ljava/lang/Object;Ljava/lang/Object;Ljava/lang/Object;Ljava/lang/Object;TA;>;)TCC;
   #68 = Utf8               (Lscala/collection/IterableFactory;IIIILscala/Function4;)Ljava/lang/Object;
   #69 = NameAndType        #55:#68       // tabulate$:(Lscala/collection/IterableFactory;IIIILscala/Function4;)Ljava/lang/Object;
   #70 = InterfaceMethodref #7.#69        // scala/collection/IterableFactory.tabulate$:(Lscala/collection/IterableFactory;IIIILscala/Function4;)Ljava/lang/Object;
   #71 = Utf8               Lscala/Function4;
   #72 = Utf8               (IIIIILscala/Function5;)Ljava/lang/Object;
   #73 = Utf8               <A:Ljava/lang/Object;>(IIIIILscala/Function5<Ljava/lang/Object;Ljava/lang/Object;Ljava/lang/Object;Ljava/lang/Object;Ljava/lang/Object;TA;>;)TCC;
   #74 = Utf8               (Lscala/collection/IterableFactory;IIIIILscala/Function5;)Ljava/lang/Object;
   #75 = NameAndType        #55:#74       // tabulate$:(Lscala/collection/IterableFactory;IIIIILscala/Function5;)Ljava/lang/Object;
   #76 = InterfaceMethodref #7.#75        // scala/collection/IterableFactory.tabulate$:(Lscala/collection/IterableFactory;IIIIILscala/Function5;)Ljava/lang/Object;
   #77 = Utf8               Lscala/Function5;
   #78 = Utf8               concat
   #79 = Utf8               (Lscala/collection/immutable/Seq;)Ljava/lang/Object;
   #80 = Utf8               <A:Ljava/lang/Object;>(Lscala/collection/immutable/Seq<Lscala/collection/Iterable<TA;>;>;)TCC;
   #81 = Utf8               xss
   #82 = Utf8               concat$
   #83 = Utf8               (Lscala/collection/IterableFactory;Lscala/collection/immutable/Seq;)Ljava/lang/Object;
   #84 = NameAndType        #82:#83       // concat$:(Lscala/collection/IterableFactory;Lscala/collection/immutable/Seq;)Ljava/lang/Object;
   #85 = InterfaceMethodref #7.#84        // scala/collection/IterableFactory.concat$:(Lscala/collection/IterableFactory;Lscala/collection/immutable/Seq;)Ljava/lang/Object;
   #86 = Utf8               Lscala/collection/immutable/Seq;
   #87 = Utf8               iterableFactory
   #88 = Utf8               ()Lscala/collection/Factory;
   #89 = Utf8               <A:Ljava/lang/Object;>()Lscala/collection/Factory<TA;TCC;>;
   #90 = Utf8               iterableFactory$
   #91 = Utf8               (Lscala/collection/IterableFactory;)Lscala/collection/Factory;
   #92 = NameAndType        #90:#91       // iterableFactory$:(Lscala/collection/IterableFactory;)Lscala/collection/Factory;
   #93 = InterfaceMethodref #7.#92        // scala/collection/IterableFactory.iterableFactory$:(Lscala/collection/IterableFactory;)Lscala/collection/Factory;
   #94 = Utf8               empty
   #95 = Utf8               ()Ljava/lang/Object;
   #96 = Utf8               <A:Ljava/lang/Object;>()TCC;
   #97 = NameAndType        #16:#17       // delegate:Lscala/collection/ClassTagIterableFactory;
   #98 = Fieldref           #2.#97        // scala/collection/ClassTagIterableFactory$AnyIterableDelegate.delegate:Lscala/collection/ClassTagIterableFactory;
   #99 = Utf8               scala/reflect/ClassTag$
  #100 = Class              #99           // scala/reflect/ClassTag$
  #101 = Utf8               MODULE$
  #102 = Utf8               Lscala/reflect/ClassTag$;
  #103 = NameAndType        #101:#102     // MODULE$:Lscala/reflect/ClassTag$;
  #104 = Fieldref           #100.#103     // scala/reflect/ClassTag$.MODULE$:Lscala/reflect/ClassTag$;
  #105 = Utf8               Any
  #106 = Utf8               ()Lscala/reflect/ClassTag;
  #107 = NameAndType        #105:#106     // Any:()Lscala/reflect/ClassTag;
  #108 = Methodref          #100.#107     // scala/reflect/ClassTag$.Any:()Lscala/reflect/ClassTag;
  #109 = Utf8               (Ljava/lang/Object;)Ljava/lang/Object;
  #110 = NameAndType        #94:#109      // empty:(Ljava/lang/Object;)Ljava/lang/Object;
  #111 = InterfaceMethodref #10.#110      // scala/collection/ClassTagIterableFactory.empty:(Ljava/lang/Object;)Ljava/lang/Object;
  #112 = Utf8               from
  #113 = Utf8               (Lscala/collection/IterableOnce;)Ljava/lang/Object;
  #114 = Utf8               <A:Ljava/lang/Object;>(Lscala/collection/IterableOnce<TA;>;)TCC;
  #115 = Utf8               it
  #116 = Utf8               (Lscala/collection/IterableOnce;Ljava/lang/Object;)Ljava/lang/Object;
  #117 = NameAndType        #112:#116     // from:(Lscala/collection/IterableOnce;Ljava/lang/Object;)Ljava/lang/Object;
  #118 = InterfaceMethodref #10.#117      // scala/collection/ClassTagIterableFactory.from:(Lscala/collection/IterableOnce;Ljava/lang/Object;)Ljava/lang/Object;
  #119 = Utf8               Lscala/collection/IterableOnce;
  #120 = Utf8               newBuilder
  #121 = Utf8               ()Lscala/collection/mutable/Builder;
  #122 = Utf8               <A:Ljava/lang/Object;>()Lscala/collection/mutable/Builder<TA;TCC;>;
  #123 = Utf8               (Ljava/lang/Object;)Lscala/collection/mutable/Builder;
  #124 = NameAndType        #120:#123     // newBuilder:(Ljava/lang/Object;)Lscala/collection/mutable/Builder;
  #125 = InterfaceMethodref #10.#124      // scala/collection/ClassTagIterableFactory.newBuilder:(Ljava/lang/Object;)Lscala/collection/mutable/Builder;
  #126 = Utf8               apply
  #127 = Utf8               <A:Ljava/lang/Object;>(Lscala/collection/immutable/Seq<TA;>;)TCC;
  #128 = Utf8               elems
  #129 = Utf8               (Lscala/collection/immutable/Seq;Ljava/lang/Object;)Ljava/lang/Object;
  #130 = NameAndType        #126:#129     // apply:(Lscala/collection/immutable/Seq;Ljava/lang/Object;)Ljava/lang/Object;
  #131 = InterfaceMethodref #10.#130      // scala/collection/ClassTagIterableFactory.apply:(Lscala/collection/immutable/Seq;Ljava/lang/Object;)Ljava/lang/Object;
  #132 = Utf8               iterate
  #133 = Utf8               (Ljava/lang/Object;ILscala/Function1;)Ljava/lang/Object;
  #134 = Utf8               <A:Ljava/lang/Object;>(TA;ILscala/Function1<TA;TA;>;)TCC;
  #135 = Utf8               start
  #136 = Utf8               len
  #137 = Utf8               (Ljava/lang/Object;ILscala/Function1;Ljava/lang/Object;)Ljava/lang/Object;
  #138 = NameAndType        #132:#137     // iterate:(Ljava/lang/Object;ILscala/Function1;Ljava/lang/Object;)Ljava/lang/Object;
  #139 = InterfaceMethodref #10.#138      // scala/collection/ClassTagIterableFactory.iterate:(Ljava/lang/Object;ILscala/Function1;Ljava/lang/Object;)Ljava/lang/Object;
  #140 = Utf8               Ljava/lang/Object;
  #141 = Utf8               Lscala/Function1;
  #142 = Utf8               unfold
  #143 = Utf8               (Ljava/lang/Object;Lscala/Function1;)Ljava/lang/Object;
  #144 = Utf8               <A:Ljava/lang/Object;S:Ljava/lang/Object;>(TS;Lscala/Function1<TS;Lscala/Option<Lscala/Tuple2<TA;TS;>;>;>;)TCC;
  #145 = Utf8               init
  #146 = Utf8               (Ljava/lang/Object;Lscala/Function1;Ljava/lang/Object;)Ljava/lang/Object;
  #147 = NameAndType        #142:#146     // unfold:(Ljava/lang/Object;Lscala/Function1;Ljava/lang/Object;)Ljava/lang/Object;
  #148 = InterfaceMethodref #10.#147      // scala/collection/ClassTagIterableFactory.unfold:(Ljava/lang/Object;Lscala/Function1;Ljava/lang/Object;)Ljava/lang/Object;
  #149 = Utf8               range
  #150 = Utf8               (Ljava/lang/Object;Ljava/lang/Object;Lscala/math/Integral;)Ljava/lang/Object;
  #151 = Utf8               <A:Ljava/lang/Object;>(TA;TA;Lscala/math/Integral<TA;>;)TCC;
  #152 = Utf8               end
  #153 = Utf8               i
  #154 = Utf8               (Ljava/lang/Object;Ljava/lang/Object;Lscala/math/Integral;Lscala/reflect/ClassTag;)Ljava/lang/Object;
  #155 = NameAndType        #149:#154     // range:(Ljava/lang/Object;Ljava/lang/Object;Lscala/math/Integral;Lscala/reflect/ClassTag;)Ljava/lang/Object;
  #156 = InterfaceMethodref #10.#155      // scala/collection/ClassTagIterableFactory.range:(Ljava/lang/Object;Ljava/lang/Object;Lscala/math/Integral;Lscala/reflect/ClassTag;)Ljava/lang/Object;
  #157 = Utf8               Lscala/math/Integral;
  #158 = Utf8               (Ljava/lang/Object;Ljava/lang/Object;Ljava/lang/Object;Lscala/math/Integral;)Ljava/lang/Object;
  #159 = Utf8               <A:Ljava/lang/Object;>(TA;TA;TA;Lscala/math/Integral<TA;>;)TCC;
  #160 = Utf8               step
  #161 = Utf8               (Ljava/lang/Object;Ljava/lang/Object;Ljava/lang/Object;Lscala/math/Integral;Lscala/reflect/ClassTag;)Ljava/lang/Object;
  #162 = NameAndType        #149:#161     // range:(Ljava/lang/Object;Ljava/lang/Object;Ljava/lang/Object;Lscala/math/Integral;Lscala/reflect/ClassTag;)Ljava/lang/Object;
  #163 = InterfaceMethodref #10.#162      // scala/collection/ClassTagIterableFactory.range:(Ljava/lang/Object;Ljava/lang/Object;Ljava/lang/Object;Lscala/math/Integral;Lscala/reflect/ClassTag;)Ljava/lang/Object;
  #164 = Utf8               (ILscala/Function0;)Ljava/lang/Object;
  #165 = Utf8               <A:Ljava/lang/Object;>(ILscala/Function0<TA;>;)TCC;
  #166 = Utf8               n
  #167 = Utf8               (ILscala/Function0;Ljava/lang/Object;)Ljava/lang/Object;
  #168 = NameAndType        #19:#167      // fill:(ILscala/Function0;Ljava/lang/Object;)Ljava/lang/Object;
  #169 = InterfaceMethodref #10.#168      // scala/collection/ClassTagIterableFactory.fill:(ILscala/Function0;Ljava/lang/Object;)Ljava/lang/Object;
  #170 = Utf8               (ILscala/Function1;)Ljava/lang/Object;
  #171 = Utf8               <A:Ljava/lang/Object;>(ILscala/Function1<Ljava/lang/Object;TA;>;)TCC;
  #172 = Utf8               (ILscala/Function1;Ljava/lang/Object;)Ljava/lang/Object;
  #173 = NameAndType        #51:#172      // tabulate:(ILscala/Function1;Ljava/lang/Object;)Ljava/lang/Object;
  #174 = InterfaceMethodref #10.#173      // scala/collection/ClassTagIterableFactory.tabulate:(ILscala/Function1;Ljava/lang/Object;)Ljava/lang/Object;
  #175 = Utf8               <init>
  #176 = Utf8               (Lscala/collection/ClassTagIterableFactory;)V
  #177 = Utf8               (Lscala/collection/ClassTagIterableFactory<TCC;>;)V
  #178 = Utf8               ()V
  #179 = NameAndType        #175:#178     // "<init>":()V
  #180 = Methodref          #5.#179       // java/lang/Object."<init>":()V
  #181 = Utf8               ConstantValue
  #182 = Utf8               Signature
  #183 = Utf8               Code
  #184 = Utf8               LineNumberTable
  #185 = Utf8               LocalVariableTable
  #186 = Utf8               MethodParameters
  #187 = Utf8               InnerClasses
  #188 = Utf8               SourceFile
  #189 = Utf8               ScalaInlineInfo
  #190 = Utf8               Scala
{
  private static final long serialVersionUID;
    descriptor: J
    flags: (0x001a) ACC_PRIVATE, ACC_STATIC, ACC_FINAL
    ConstantValue: long 3l

  private final scala.collection.ClassTagIterableFactory<CC> delegate;
    descriptor: Lscala/collection/ClassTagIterableFactory;
    flags: (0x0012) ACC_PRIVATE, ACC_FINAL
    Signature: #18                          // Lscala/collection/ClassTagIterableFactory<TCC;>;

  public <A extends java.lang.Object> CC fill(int, int, scala.Function0<A>);
    descriptor: (IILscala/Function0;)Ljava/lang/Object;
    flags: (0x0001) ACC_PUBLIC
    Code:
      stack=4, locals=4, args_size=4
         0: aload_0
         1: iload_1
         2: iload_2
         3: aload_3
         4: invokestatic  #28                 // InterfaceMethod scala/collection/IterableFactory.fill$:(Lscala/collection/IterableFactory;IILscala/Function0;)Ljava/lang/Object;
         7: areturn
      LineNumberTable:
        line 669: 0
      LocalVariableTable:
        Start  Length  Slot  Name   Signature
            0       8     0  this   Lscala/collection/ClassTagIterableFactory$AnyIterableDelegate;
            0       8     1    n1   I
            0       8     2    n2   I
            0       8     3  elem   Lscala/Function0;
    Signature: #21                          // <A:Ljava/lang/Object;>(IILscala/Function0<TA;>;)TCC;
    MethodParameters:
      Name                           Flags
      n1                             final
      n2                             final
      elem                           final

  public <A extends java.lang.Object> CC fill(int, int, int, scala.Function0<A>);
    descriptor: (IIILscala/Function0;)Ljava/lang/Object;
    flags: (0x0001) ACC_PUBLIC
    Code:
      stack=5, locals=5, args_size=5
         0: aload_0
         1: iload_1
         2: iload_2
         3: iload_3
         4: aload         4
         6: invokestatic  #38                 // InterfaceMethod scala/collection/IterableFactory.fill$:(Lscala/collection/IterableFactory;IIILscala/Function0;)Ljava/lang/Object;
         9: areturn
      LineNumberTable:
        line 669: 0
      LocalVariableTable:
        Start  Length  Slot  Name   Signature
            0      10     0  this   Lscala/collection/ClassTagIterableFactory$AnyIterableDelegate;
            0      10     1    n1   I
            0      10     2    n2   I
            0      10     3    n3   I
            0      10     4  elem   Lscala/Function0;
    Signature: #34                          // <A:Ljava/lang/Object;>(IIILscala/Function0<TA;>;)TCC;
    MethodParameters:
      Name                           Flags
      n1                             final
      n2                             final
      n3                             final
      elem                           final

  public <A extends java.lang.Object> CC fill(int, int, int, int, scala.Function0<A>);
    descriptor: (IIIILscala/Function0;)Ljava/lang/Object;
    flags: (0x0001) ACC_PUBLIC
    Code:
      stack=6, locals=6, args_size=6
         0: aload_0
         1: iload_1
         2: iload_2
         3: iload_3
         4: iload         4
         6: aload         5
         8: invokestatic  #44                 // InterfaceMethod scala/collection/IterableFactory.fill$:(Lscala/collection/IterableFactory;IIIILscala/Function0;)Ljava/lang/Object;
        11: areturn
      LineNumberTable:
        line 669: 0
      LocalVariableTable:
        Start  Length  Slot  Name   Signature
            0      12     0  this   Lscala/collection/ClassTagIterableFactory$AnyIterableDelegate;
            0      12     1    n1   I
            0      12     2    n2   I
            0      12     3    n3   I
            0      12     4    n4   I
            0      12     5  elem   Lscala/Function0;
    Signature: #40                          // <A:Ljava/lang/Object;>(IIIILscala/Function0<TA;>;)TCC;
    MethodParameters:
      Name                           Flags
      n1                             final
      n2                             final
      n3                             final
      n4                             final
      elem                           final

  public <A extends java.lang.Object> CC fill(int, int, int, int, int, scala.Function0<A>);
    descriptor: (IIIIILscala/Function0;)Ljava/lang/Object;
    flags: (0x0001) ACC_PUBLIC
    Code:
      stack=7, locals=7, args_size=7
         0: aload_0
         1: iload_1
         2: iload_2
         3: iload_3
         4: iload         4
         6: iload         5
         8: aload         6
        10: invokestatic  #50                 // InterfaceMethod scala/collection/IterableFactory.fill$:(Lscala/collection/IterableFactory;IIIIILscala/Function0;)Ljava/lang/Object;
        13: areturn
      LineNumberTable:
        line 669: 0
      LocalVariableTable:
        Start  Length  Slot  Name   Signature
            0      14     0  this   Lscala/collection/ClassTagIterableFactory$AnyIterableDelegate;
            0      14     1    n1   I
            0      14     2    n2   I
            0      14     3    n3   I
            0      14     4    n4   I
            0      14     5    n5   I
            0      14     6  elem   Lscala/Function0;
    Signature: #46                          // <A:Ljava/lang/Object;>(IIIIILscala/Function0<TA;>;)TCC;
    MethodParameters:
      Name                           Flags
      n1                             final
      n2                             final
      n3                             final
      n4                             final
      n5                             final
      elem                           final

  public <A extends java.lang.Object> CC tabulate(int, int, scala.Function2<java.lang.Object, java.lang.Object, A>);
    descriptor: (IILscala/Function2;)Ljava/lang/Object;
    flags: (0x0001) ACC_PUBLIC
    Code:
      stack=4, locals=4, args_size=4
         0: aload_0
         1: iload_1
         2: iload_2
         3: aload_3
         4: invokestatic  #58                 // InterfaceMethod scala/collection/IterableFactory.tabulate$:(Lscala/collection/IterableFactory;IILscala/Function2;)Ljava/lang/Object;
         7: areturn
      LineNumberTable:
        line 669: 0
      LocalVariableTable:
        Start  Length  Slot  Name   Signature
            0       8     0  this   Lscala/collection/ClassTagIterableFactory$AnyIterableDelegate;
            0       8     1    n1   I
            0       8     2    n2   I
            0       8     3     f   Lscala/Function2;
    Signature: #53                          // <A:Ljava/lang/Object;>(IILscala/Function2<Ljava/lang/Object;Ljava/lang/Object;TA;>;)TCC;
    MethodParameters:
      Name                           Flags
      n1                             final
      n2                             final
      f                              final

  public <A extends java.lang.Object> CC tabulate(int, int, int, scala.Function3<java.lang.Object, java.lang.Object, java.lang.Object, A>);
    descriptor: (IIILscala/Function3;)Ljava/lang/Object;
    flags: (0x0001) ACC_PUBLIC
    Code:
      stack=5, locals=5, args_size=5
         0: aload_0
         1: iload_1
         2: iload_2
         3: iload_3
         4: aload         4
         6: invokestatic  #64                 // InterfaceMethod scala/collection/IterableFactory.tabulate$:(Lscala/collection/IterableFactory;IIILscala/Function3;)Ljava/lang/Object;
         9: areturn
      LineNumberTable:
        line 669: 0
      LocalVariableTable:
        Start  Length  Slot  Name   Signature
            0      10     0  this   Lscala/collection/ClassTagIterableFactory$AnyIterableDelegate;
            0      10     1    n1   I
            0      10     2    n2   I
            0      10     3    n3   I
            0      10     4     f   Lscala/Function3;
    Signature: #61                          // <A:Ljava/lang/Object;>(IIILscala/Function3<Ljava/lang/Object;Ljava/lang/Object;Ljava/lang/Object;TA;>;)TCC;
    MethodParameters:
      Name                           Flags
      n1                             final
      n2                             final
      n3                             final
      f                              final

  public <A extends java.lang.Object> CC tabulate(int, int, int, int, scala.Function4<java.lang.Object, java.lang.Object, java.lang.Object, java.lang.Object, A>);
    descriptor: (IIIILscala/Function4;)Ljava/lang/Object;
    flags: (0x0001) ACC_PUBLIC
    Code:
      stack=6, locals=6, args_size=6
         0: aload_0
         1: iload_1
         2: iload_2
         3: iload_3
         4: iload         4
         6: aload         5
         8: invokestatic  #70                 // InterfaceMethod scala/collection/IterableFactory.tabulate$:(Lscala/collection/IterableFactory;IIIILscala/Function4;)Ljava/lang/Object;
        11: areturn
      LineNumberTable:
        line 669: 0
      LocalVariableTable:
        Start  Length  Slot  Name   Signature
            0      12     0  this   Lscala/collection/ClassTagIterableFactory$AnyIterableDelegate;
            0      12     1    n1   I
            0      12     2    n2   I
            0      12     3    n3   I
            0      12     4    n4   I
            0      12     5     f   Lscala/Function4;
    Signature: #67                          // <A:Ljava/lang/Object;>(IIIILscala/Function4<Ljava/lang/Object;Ljava/lang/Object;Ljava/lang/Object;Ljava/lang/Object;TA;>;)TCC;
    MethodParameters:
      Name                           Flags
      n1                             final
      n2                             final
      n3                             final
      n4                             final
      f                              final

  public <A extends java.lang.Object> CC tabulate(int, int, int, int, int, scala.Function5<java.lang.Object, java.lang.Object, java.lang.Object, java.lang.Object, java.lang.Object, A>);
    descriptor: (IIIIILscala/Function5;)Ljava/lang/Object;
    flags: (0x0001) ACC_PUBLIC
    Code:
      stack=7, locals=7, args_size=7
         0: aload_0
         1: iload_1
         2: iload_2
         3: iload_3
         4: iload         4
         6: iload         5
         8: aload         6
        10: invokestatic  #76                 // InterfaceMethod scala/collection/IterableFactory.tabulate$:(Lscala/collection/IterableFactory;IIIIILscala/Function5;)Ljava/lang/Object;
        13: areturn
      LineNumberTable:
        line 669: 0
      LocalVariableTable:
        Start  Length  Slot  Name   Signature
            0      14     0  this   Lscala/collection/ClassTagIterableFactory$AnyIterableDelegate;
            0      14     1    n1   I
            0      14     2    n2   I
            0      14     3    n3   I
            0      14     4    n4   I
            0      14     5    n5   I
            0      14     6     f   Lscala/Function5;
    Signature: #73                          // <A:Ljava/lang/Object;>(IIIIILscala/Function5<Ljava/lang/Object;Ljava/lang/Object;Ljava/lang/Object;Ljava/lang/Object;Ljava/lang/Object;TA;>;)TCC;
    MethodParameters:
      Name                           Flags
      n1                             final
      n2                             final
      n3                             final
      n4                             final
      n5                             final
      f                              final

  public <A extends java.lang.Object> CC concat(scala.collection.immutable.Seq<scala.collection.Iterable<A>>);
    descriptor: (Lscala/collection/immutable/Seq;)Ljava/lang/Object;
    flags: (0x0001) ACC_PUBLIC
    Code:
      stack=2, locals=2, args_size=2
         0: aload_0
         1: aload_1
         2: invokestatic  #85                 // InterfaceMethod scala/collection/IterableFactory.concat$:(Lscala/collection/IterableFactory;Lscala/collection/immutable/Seq;)Ljava/lang/Object;
         5: areturn
      LineNumberTable:
        line 669: 0
      LocalVariableTable:
        Start  Length  Slot  Name   Signature
            0       6     0  this   Lscala/collection/ClassTagIterableFactory$AnyIterableDelegate;
            0       6     1   xss   Lscala/collection/immutable/Seq;
    Signature: #80                          // <A:Ljava/lang/Object;>(Lscala/collection/immutable/Seq<Lscala/collection/Iterable<TA;>;>;)TCC;
    MethodParameters:
      Name                           Flags
      xss                            final

  public <A extends java.lang.Object> scala.collection.Factory<A, CC> iterableFactory();
    descriptor: ()Lscala/collection/Factory;
    flags: (0x0001) ACC_PUBLIC
    Code:
      stack=1, locals=1, args_size=1
         0: aload_0
         1: invokestatic  #93                 // InterfaceMethod scala/collection/IterableFactory.iterableFactory$:(Lscala/collection/IterableFactory;)Lscala/collection/Factory;
         4: areturn
      LineNumberTable:
        line 669: 0
      LocalVariableTable:
        Start  Length  Slot  Name   Signature
            0       5     0  this   Lscala/collection/ClassTagIterableFactory$AnyIterableDelegate;
    Signature: #89                          // <A:Ljava/lang/Object;>()Lscala/collection/Factory<TA;TCC;>;

  public <A extends java.lang.Object> CC empty();
    descriptor: ()Ljava/lang/Object;
    flags: (0x0001) ACC_PUBLIC
    Code:
      stack=2, locals=1, args_size=1
         0: aload_0
         1: getfield      #98                 // Field delegate:Lscala/collection/ClassTagIterableFactory;
         4: getstatic     #104                // Field scala/reflect/ClassTag$.MODULE$:Lscala/reflect/ClassTag$;
         7: invokevirtual #108                // Method scala/reflect/ClassTag$.Any:()Lscala/reflect/ClassTag;
        10: invokeinterface #111,  2          // InterfaceMethod scala/collection/ClassTagIterableFactory.empty:(Ljava/lang/Object;)Ljava/lang/Object;
        15: areturn
      LineNumberTable:
        line 670: 0
      LocalVariableTable:
        Start  Length  Slot  Name   Signature
            0      16     0  this   Lscala/collection/ClassTagIterableFactory$AnyIterableDelegate;
    Signature: #96                          // <A:Ljava/lang/Object;>()TCC;

  public <A extends java.lang.Object> CC from(scala.collection.IterableOnce<A>);
    descriptor: (Lscala/collection/IterableOnce;)Ljava/lang/Object;
    flags: (0x0001) ACC_PUBLIC
    Code:
      stack=3, locals=2, args_size=2
         0: aload_0
         1: getfield      #98                 // Field delegate:Lscala/collection/ClassTagIterableFactory;
         4: aload_1
         5: getstatic     #104                // Field scala/reflect/ClassTag$.MODULE$:Lscala/reflect/ClassTag$;
         8: invokevirtual #108                // Method scala/reflect/ClassTag$.Any:()Lscala/reflect/ClassTag;
        11: invokeinterface #118,  3          // InterfaceMethod scala/collection/ClassTagIterableFactory.from:(Lscala/collection/IterableOnce;Ljava/lang/Object;)Ljava/lang/Object;
        16: areturn
      LineNumberTable:
        line 671: 0
      LocalVariableTable:
        Start  Length  Slot  Name   Signature
            0      17     0  this   Lscala/collection/ClassTagIterableFactory$AnyIterableDelegate;
            0      17     1    it   Lscala/collection/IterableOnce;
    Signature: #114                         // <A:Ljava/lang/Object;>(Lscala/collection/IterableOnce<TA;>;)TCC;
    MethodParameters:
      Name                           Flags
      it                             final

  public <A extends java.lang.Object> scala.collection.mutable.Builder<A, CC> newBuilder();
    descriptor: ()Lscala/collection/mutable/Builder;
    flags: (0x0001) ACC_PUBLIC
    Code:
      stack=2, locals=1, args_size=1
         0: aload_0
         1: getfield      #98                 // Field delegate:Lscala/collection/ClassTagIterableFactory;
         4: getstatic     #104                // Field scala/reflect/ClassTag$.MODULE$:Lscala/reflect/ClassTag$;
         7: invokevirtual #108                // Method scala/reflect/ClassTag$.Any:()Lscala/reflect/ClassTag;
        10: invokeinterface #125,  2          // InterfaceMethod scala/collection/ClassTagIterableFactory.newBuilder:(Ljava/lang/Object;)Lscala/collection/mutable/Builder;
        15: areturn
      LineNumberTable:
        line 672: 0
      LocalVariableTable:
        Start  Length  Slot  Name   Signature
            0      16     0  this   Lscala/collection/ClassTagIterableFactory$AnyIterableDelegate;
    Signature: #122                         // <A:Ljava/lang/Object;>()Lscala/collection/mutable/Builder<TA;TCC;>;

  public <A extends java.lang.Object> CC apply(scala.collection.immutable.Seq<A>);
    descriptor: (Lscala/collection/immutable/Seq;)Ljava/lang/Object;
    flags: (0x0001) ACC_PUBLIC
    Code:
      stack=3, locals=2, args_size=2
         0: aload_0
         1: getfield      #98                 // Field delegate:Lscala/collection/ClassTagIterableFactory;
         4: aload_1
         5: getstatic     #104                // Field scala/reflect/ClassTag$.MODULE$:Lscala/reflect/ClassTag$;
         8: invokevirtual #108                // Method scala/reflect/ClassTag$.Any:()Lscala/reflect/ClassTag;
        11: invokeinterface #131,  3          // InterfaceMethod scala/collection/ClassTagIterableFactory.apply:(Lscala/collection/immutable/Seq;Ljava/lang/Object;)Ljava/lang/Object;
        16: areturn
      LineNumberTable:
        line 673: 0
      LocalVariableTable:
        Start  Length  Slot  Name   Signature
            0      17     0  this   Lscala/collection/ClassTagIterableFactory$AnyIterableDelegate;
            0      17     1 elems   Lscala/collection/immutable/Seq;
    Signature: #127                         // <A:Ljava/lang/Object;>(Lscala/collection/immutable/Seq<TA;>;)TCC;
    MethodParameters:
      Name                           Flags
      elems                          final

  public <A extends java.lang.Object> CC iterate(A, int, scala.Function1<A, A>);
    descriptor: (Ljava/lang/Object;ILscala/Function1;)Ljava/lang/Object;
    flags: (0x0001) ACC_PUBLIC
    Code:
      stack=5, locals=4, args_size=4
         0: aload_0
         1: getfield      #98                 // Field delegate:Lscala/collection/ClassTagIterableFactory;
         4: aload_1
         5: iload_2
         6: aload_3
         7: getstatic     #104                // Field scala/reflect/ClassTag$.MODULE$:Lscala/reflect/ClassTag$;
        10: invokevirtual #108                // Method scala/reflect/ClassTag$.Any:()Lscala/reflect/ClassTag;
        13: invokeinterface #139,  5          // InterfaceMethod scala/collection/ClassTagIterableFactory.iterate:(Ljava/lang/Object;ILscala/Function1;Ljava/lang/Object;)Ljava/lang/Object;
        18: areturn
      LineNumberTable:
        line 674: 0
      LocalVariableTable:
        Start  Length  Slot  Name   Signature
            0      19     0  this   Lscala/collection/ClassTagIterableFactory$AnyIterableDelegate;
            0      19     1 start   Ljava/lang/Object;
            0      19     2   len   I
            0      19     3     f   Lscala/Function1;
    Signature: #134                         // <A:Ljava/lang/Object;>(TA;ILscala/Function1<TA;TA;>;)TCC;
    MethodParameters:
      Name                           Flags
      start                          final
      len                            final
      f                              final

  public <A extends java.lang.Object, S extends java.lang.Object> CC unfold(S, scala.Function1<S, scala.Option<scala.Tuple2<A, S>>>);
    descriptor: (Ljava/lang/Object;Lscala/Function1;)Ljava/lang/Object;
    flags: (0x0001) ACC_PUBLIC
    Code:
      stack=4, locals=3, args_size=3
         0: aload_0
         1: getfield      #98                 // Field delegate:Lscala/collection/ClassTagIterableFactory;
         4: aload_1
         5: aload_2
         6: getstatic     #104                // Field scala/reflect/ClassTag$.MODULE$:Lscala/reflect/ClassTag$;
         9: invokevirtual #108                // Method scala/reflect/ClassTag$.Any:()Lscala/reflect/ClassTag;
        12: invokeinterface #148,  4          // InterfaceMethod scala/collection/ClassTagIterableFactory.unfold:(Ljava/lang/Object;Lscala/Function1;Ljava/lang/Object;)Ljava/lang/Object;
        17: areturn
      LineNumberTable:
        line 675: 0
      LocalVariableTable:
        Start  Length  Slot  Name   Signature
            0      18     0  this   Lscala/collection/ClassTagIterableFactory$AnyIterableDelegate;
            0      18     1  init   Ljava/lang/Object;
            0      18     2     f   Lscala/Function1;
    Signature: #144                         // <A:Ljava/lang/Object;S:Ljava/lang/Object;>(TS;Lscala/Function1<TS;Lscala/Option<Lscala/Tuple2<TA;TS;>;>;>;)TCC;
    MethodParameters:
      Name                           Flags
      init                           final
      f                              final

  public <A extends java.lang.Object> CC range(A, A, scala.math.Integral<A>);
    descriptor: (Ljava/lang/Object;Ljava/lang/Object;Lscala/math/Integral;)Ljava/lang/Object;
    flags: (0x0001) ACC_PUBLIC
    Code:
      stack=5, locals=4, args_size=4
         0: aload_0
         1: getfield      #98                 // Field delegate:Lscala/collection/ClassTagIterableFactory;
         4: aload_1
         5: aload_2
         6: aload_3
         7: getstatic     #104                // Field scala/reflect/ClassTag$.MODULE$:Lscala/reflect/ClassTag$;
        10: invokevirtual #108                // Method scala/reflect/ClassTag$.Any:()Lscala/reflect/ClassTag;
        13: invokeinterface #156,  5          // InterfaceMethod scala/collection/ClassTagIterableFactory.range:(Ljava/lang/Object;Ljava/lang/Object;Lscala/math/Integral;Lscala/reflect/ClassTag;)Ljava/lang/Object;
        18: areturn
      LineNumberTable:
        line 676: 0
      LocalVariableTable:
        Start  Length  Slot  Name   Signature
            0      19     0  this   Lscala/collection/ClassTagIterableFactory$AnyIterableDelegate;
            0      19     1 start   Ljava/lang/Object;
            0      19     2   end   Ljava/lang/Object;
            0      19     3     i   Lscala/math/Integral;
    Signature: #151                         // <A:Ljava/lang/Object;>(TA;TA;Lscala/math/Integral<TA;>;)TCC;
    MethodParameters:
      Name                           Flags
      start                          final
      end                            final
      i                              final

  public <A extends java.lang.Object> CC range(A, A, A, scala.math.Integral<A>);
    descriptor: (Ljava/lang/Object;Ljava/lang/Object;Ljava/lang/Object;Lscala/math/Integral;)Ljava/lang/Object;
    flags: (0x0001) ACC_PUBLIC
    Code:
      stack=6, locals=5, args_size=5
         0: aload_0
         1: getfield      #98                 // Field delegate:Lscala/collection/ClassTagIterableFactory;
         4: aload_1
         5: aload_2
         6: aload_3
         7: aload         4
         9: getstatic     #104                // Field scala/reflect/ClassTag$.MODULE$:Lscala/reflect/ClassTag$;
        12: invokevirtual #108                // Method scala/reflect/ClassTag$.Any:()Lscala/reflect/ClassTag;
        15: invokeinterface #163,  6          // InterfaceMethod scala/collection/ClassTagIterableFactory.range:(Ljava/lang/Object;Ljava/lang/Object;Ljava/lang/Object;Lscala/math/Integral;Lscala/reflect/ClassTag;)Ljava/lang/Object;
        20: areturn
      LineNumberTable:
        line 677: 0
      LocalVariableTable:
        Start  Length  Slot  Name   Signature
            0      21     0  this   Lscala/collection/ClassTagIterableFactory$AnyIterableDelegate;
            0      21     1 start   Ljava/lang/Object;
            0      21     2   end   Ljava/lang/Object;
            0      21     3  step   Ljava/lang/Object;
            0      21     4     i   Lscala/math/Integral;
    Signature: #159                         // <A:Ljava/lang/Object;>(TA;TA;TA;Lscala/math/Integral<TA;>;)TCC;
    MethodParameters:
      Name                           Flags
      start                          final
      end                            final
      step                           final
      i                              final

  public <A extends java.lang.Object> CC fill(int, scala.Function0<A>);
    descriptor: (ILscala/Function0;)Ljava/lang/Object;
    flags: (0x0001) ACC_PUBLIC
    Code:
      stack=4, locals=3, args_size=3
         0: aload_0
         1: getfield      #98                 // Field delegate:Lscala/collection/ClassTagIterableFactory;
         4: iload_1
         5: aload_2
         6: getstatic     #104                // Field scala/reflect/ClassTag$.MODULE$:Lscala/reflect/ClassTag$;
         9: invokevirtual #108                // Method scala/reflect/ClassTag$.Any:()Lscala/reflect/ClassTag;
        12: invokeinterface #169,  4          // InterfaceMethod scala/collection/ClassTagIterableFactory.fill:(ILscala/Function0;Ljava/lang/Object;)Ljava/lang/Object;
        17: areturn
      LineNumberTable:
        line 678: 0
      LocalVariableTable:
        Start  Length  Slot  Name   Signature
            0      18     0  this   Lscala/collection/ClassTagIterableFactory$AnyIterableDelegate;
            0      18     1     n   I
            0      18     2  elem   Lscala/Function0;
    Signature: #165                         // <A:Ljava/lang/Object;>(ILscala/Function0<TA;>;)TCC;
    MethodParameters:
      Name                           Flags
      n                              final
      elem                           final

  public <A extends java.lang.Object> CC tabulate(int, scala.Function1<java.lang.Object, A>);
    descriptor: (ILscala/Function1;)Ljava/lang/Object;
    flags: (0x0001) ACC_PUBLIC
    Code:
      stack=4, locals=3, args_size=3
         0: aload_0
         1: getfield      #98                 // Field delegate:Lscala/collection/ClassTagIterableFactory;
         4: iload_1
         5: aload_2
         6: getstatic     #104                // Field scala/reflect/ClassTag$.MODULE$:Lscala/reflect/ClassTag$;
         9: invokevirtual #108                // Method scala/reflect/ClassTag$.Any:()Lscala/reflect/ClassTag;
        12: invokeinterface #174,  4          // InterfaceMethod scala/collection/ClassTagIterableFactory.tabulate:(ILscala/Function1;Ljava/lang/Object;)Ljava/lang/Object;
        17: areturn
      LineNumberTable:
        line 679: 0
      LocalVariableTable:
        Start  Length  Slot  Name   Signature
            0      18     0  this   Lscala/collection/ClassTagIterableFactory$AnyIterableDelegate;
            0      18     1     n   I
            0      18     2     f   Lscala/Function1;
    Signature: #171                         // <A:Ljava/lang/Object;>(ILscala/Function1<Ljava/lang/Object;TA;>;)TCC;
    MethodParameters:
      Name                           Flags
      n                              final
      f                              final

  public scala.collection.ClassTagIterableFactory$AnyIterableDelegate(scala.collection.ClassTagIterableFactory<CC>);
    descriptor: (Lscala/collection/ClassTagIterableFactory;)V
    flags: (0x0001) ACC_PUBLIC
    Code:
      stack=2, locals=2, args_size=2
         0: aload_0
         1: aload_1
         2: putfield      #98                 // Field delegate:Lscala/collection/ClassTagIterableFactory;
         5: aload_0
         6: invokespecial #180                // Method java/lang/Object."<init>":()V
         9: return
      LineNumberTable:
        line 669: 0
        line 669: 9
      LocalVariableTable:
        Start  Length  Slot  Name   Signature
            0      10     0  this   Lscala/collection/ClassTagIterableFactory$AnyIterableDelegate;
            0      10     1 delegate   Lscala/collection/ClassTagIterableFactory;
    Signature: #177                         // (Lscala/collection/ClassTagIterableFactory<TCC;>;)V
    MethodParameters:
      Name                           Flags
      delegate                       final
}
InnerClasses:
  public static #11= #2 of #10;           // AnyIterableDelegate=class scala/collection/ClassTagIterableFactory$AnyIterableDelegate of class scala/collection/ClassTagIterableFactory
Signature: #3                           // <CC:Ljava/lang/Object;>Ljava/lang/Object;Lscala/collection/IterableFactory<TCC;>;
SourceFile: "Factory.scala"
  ScalaInlineInfo: length = 0x6D (unknown attribute)
   01 00 00 15 00 AF 00 B0 00 00 7E 00 4F 00 00 4E
   00 4F 00 00 5E 00 5F 00 00 13 00 2D 00 00 13 00
   27 00 00 13 00 21 00 00 13 00 14 00 00 13 00 A4
   00 00 70 00 71 00 00 57 00 58 00 00 84 00 85 00
   00 78 00 79 00 00 95 00 9E 00 00 95 00 96 00 00
   33 00 48 00 00 33 00 42 00 00 33 00 3C 00 00 33
   00 34 00 00 33 00 AA 00 00 8E 00 8F 00
  Scala: length = 0x0 (unknown attribute)

