Classfile /Users/mw/Projects/slang-braindump/.jar/jar8/assemble/slang-braindump/assemble/content/scala/collection/DoubleStepper.class
  Last modified May 29, 2022; size 3397 bytes
  SHA-256 checksum 444ae7d2939c95908d1980e382e27169c56676041c6a5411d9eb659c49950036
  Compiled from "Stepper.scala"
public interface scala.collection.DoubleStepper extends scala.collection.Stepper$mcD$sp
  minor version: 0
  major version: 52
  flags: (0x0601) ACC_PUBLIC, ACC_INTERFACE, ACC_ABSTRACT
  this_class: #2                          // scala/collection/DoubleStepper
  super_class: #4                         // java/lang/Object
  interfaces: 1, fields: 0, methods: 10, attributes: 5
Constant pool:
   #1 = Utf8               scala/collection/DoubleStepper
   #2 = Class              #1             // scala/collection/DoubleStepper
   #3 = Utf8               java/lang/Object
   #4 = Class              #3             // java/lang/Object
   #5 = Utf8               scala/collection/Stepper$mcD$sp
   #6 = Class              #5             // scala/collection/Stepper$mcD$sp
   #7 = Utf8               Stepper.scala
   #8 = Utf8               Lscala/reflect/ScalaSignature;
   #9 = Utf8               bytes
  #10 = Utf8               \u0006\u0005\u0005eaa\u0002\n\u0014!\u0003\r\t\u0001\u0007\u0005\u0006I\u0001!\t!\n\u0005\u0006S\u00011\tA\u000b\u0005\u0006Y\u0001!\t!\f\u0005\u0006\u0003\u0002!\tAQ\u0004\u0006\u0017NA\t\u0001\u0014\u0004\u0006%MA\t!\u0014\u0005\u0006\u001d\u001a!\ta\u0014\u0004\u0005!\u001a\u0001\u0011\u000b\u0003\u0005Y\u0011\t\u0005\t\u0015!\u0003,\u0011\u0015q\u0005\u0002\"\u0001Z\u0011\u0015i\u0006\u0002\"\u0001_\u0011\u0015i\u0006\u0002\"\u0011k\u0011\u0015I\u0003\u0002\"\u0011x\u0011\u0015A\b\u0002\"\u0001z\u0011\u0015i\b\u0002\"\u0001\u007f\u0011\u001d\t)\u0001\u0003C!\u0003\u000fAq!!\u0002\t\t\u0003\nYAA\u0007E_V\u0014G.Z*uKB\u0004XM\u001d\u0006\u0003)U\t!bY8mY\u0016\u001cG/[8o\u0015\u00051\u0012!B:dC2\f7\u0001A\n\u0004\u0001ei\u0002C\u0001\u000e\u001c\u001b\u0005)\u0012B\u0001\u000f\u0016\u0005\u0019\te.\u001f*fMB\u0019adH\u0011\u000e\u0003MI!\u0001I\n\u0003\u000fM#X\r\u001d9feB\u0011!DI\u0005\u0003GU\u0011a\u0001R8vE2,\u0017A\u0002\u0013j]&$H\u0005F\u0001\'!\tQr%\u0003\u0002)+\t!QK\\5u\u0003!!(/_*qY&$H#A\u0016\u0011\u0005y\u0001\u0011aC:qY&$XM]1u_J,\"AL\u001e\u0016\u0003=\u0002\"\u0001\r\u001d\u000f\u0005E2T\"\u0001\u001a\u000b\u0005M\"\u0014\u0001B;uS2T\u0011!N\u0001\u0005U\u00064\u0018-\u0003\u00028e\u0005Y1\u000b\u001d7ji\u0016\u0014\u0018\r^8s\u0013\tI$H\u0001\u0005PM\u0012{WO\u00197f\u0015\t9$\u0007B\u0003=\u0007\t\u0007QHA\u0001C#\t\tc\b\u0005\u0002\u001b\u007f%\u0011\u0001)\u0006\u0002\u0004\u0003:L\u0018\u0001\u00046bm\u0006LE/\u001a:bi>\u0014XCA\"K+\u0005!\u0005CA#I\u001d\t\td)\u0003\u0002He\u0005\t\u0002K]5nSRLg/Z%uKJ\fGo\u001c:\n\u0005eJ%BA$3\t\u0015aDA1\u0001>\u00035!u.\u001e2mKN#X\r\u001d9feB\u0011aDB\n\u0003\re\ta\u0001P5oSRtD#\u0001\'\u00031\u0011{WO\u00197f\'R,\u0007\u000f]3s\'Bd\u0017\u000e^3sCR|\'oE\u0002\t%>\u0002\"a\u0015,\u000e\u0003QS!!\u0016\u001b\u0002\t1\fgnZ\u0005\u0003/R\u0013aa\u00142kK\u000e$\u0018!A:\u0015\u0005ic\u0006CA.\t\u001b\u00051\u0001\"\u0002-\u000b\u0001\u0004Y\u0013A\u0003;ss\u0006#g/\u00198dKR\u0011qL\u0019\t\u00035\u0001L!!Y\u000b\u0003\u000f\t{w\u000e\\3b]\")1m\u0003a\u0001I\u0006\t1\r\u0005\u0002fQ6\taM\u0003\u0002he\u0005Aa-\u001e8di&|g.\u0003\u0002jM\nqAi\\;cY\u0016\u001cuN\\:v[\u0016\u0014HCA0l\u0011\u0015\u0019G\u00021\u0001ma\ti\'\u000fE\u0002f]BL!a\u001c4\u0003\u0011\r{gn];nKJ\u0004\"!\u001d:\r\u0001\u0011I1o[A\u0001\u0002\u0003\u0015\t\u0001\u001e\u0002\u0004?\u0012:\u0014CA;?!\t\u0019f/\u0003\u0002$)R\tq&\u0001\u0007fgRLW.\u0019;f\'&TX\rF\u0001{!\tQ20\u0003\u0002}+\t!Aj\u001c8h\u0003=\u0019\u0007.\u0019:bGR,\'/[:uS\u000e\u001cH#A@\u0011\u0007i\t\t!C\u0002\u0002\u0004U\u00111!\u00138u\u0003A1wN]#bG\"\u0014V-\\1j]&tw\rF\u0002\'\u0003\u0013AQa\u0019\tA\u0002\u0011$2AJA\u0007\u0011\u0019\u0019\u0017\u00031\u0001\u0002\u0010A\"\u0011\u0011CA\u000b!\u0011)g.a\u0005\u0011\u0007E\f)\u0002B\u0006\u0002\u0018\u00055\u0011\u0011!A\u0001\u0006\u0003!(aA0%q\u0001
  #11 = Utf8               java/util/PrimitiveIterator$OfDouble
  #12 = Class              #11            // java/util/PrimitiveIterator$OfDouble
  #13 = Utf8               java/util/PrimitiveIterator
  #14 = Class              #13            // java/util/PrimitiveIterator
  #15 = Utf8               OfDouble
  #16 = Utf8               java/util/Spliterator$OfDouble
  #17 = Class              #16            // java/util/Spliterator$OfDouble
  #18 = Utf8               java/util/Spliterator
  #19 = Class              #18            // java/util/Spliterator
  #20 = Utf8               scala/collection/DoubleStepper$$anon$7
  #21 = Class              #20            // scala/collection/DoubleStepper$$anon$7
  #22 = Utf8               scala/collection/DoubleStepper$DoubleStepperSpliterator
  #23 = Class              #22            // scala/collection/DoubleStepper$DoubleStepperSpliterator
  #24 = Utf8               DoubleStepperSpliterator
  #25 = Utf8               trySplit
  #26 = Utf8               ()Lscala/collection/DoubleStepper;
  #27 = Utf8               spliterator$
  #28 = Utf8               (Lscala/collection/DoubleStepper;)Ljava/util/Spliterator$OfDouble;
  #29 = Utf8               $this
  #30 = Utf8               spliterator
  #31 = Utf8               ()Ljava/util/Spliterator$OfDouble;
  #32 = NameAndType        #30:#31        // spliterator:()Ljava/util/Spliterator$OfDouble;
  #33 = InterfaceMethodref #2.#32         // scala/collection/DoubleStepper.spliterator:()Ljava/util/Spliterator$OfDouble;
  #34 = Utf8               Lscala/collection/DoubleStepper;
  #35 = Utf8               <B:Ljava/lang/Object;>()Ljava/util/Spliterator$OfDouble;
  #36 = Utf8               spliterator$mcD$sp
  #37 = Utf8               ()Ljava/util/Spliterator;
  #38 = NameAndType        #36:#37        // spliterator$mcD$sp:()Ljava/util/Spliterator;
  #39 = InterfaceMethodref #2.#38         // scala/collection/DoubleStepper.spliterator$mcD$sp:()Ljava/util/Spliterator;
  #40 = Utf8               this
  #41 = Utf8               javaIterator$
  #42 = Utf8               (Lscala/collection/DoubleStepper;)Ljava/util/PrimitiveIterator$OfDouble;
  #43 = Utf8               javaIterator
  #44 = Utf8               ()Ljava/util/PrimitiveIterator$OfDouble;
  #45 = NameAndType        #43:#44        // javaIterator:()Ljava/util/PrimitiveIterator$OfDouble;
  #46 = InterfaceMethodref #2.#45         // scala/collection/DoubleStepper.javaIterator:()Ljava/util/PrimitiveIterator$OfDouble;
  #47 = Utf8               <B:Ljava/lang/Object;>()Ljava/util/PrimitiveIterator$OfDouble;
  #48 = Utf8               javaIterator$mcD$sp
  #49 = Utf8               ()Ljava/util/Iterator;
  #50 = NameAndType        #48:#49        // javaIterator$mcD$sp:()Ljava/util/Iterator;
  #51 = InterfaceMethodref #2.#50         // scala/collection/DoubleStepper.javaIterator$mcD$sp:()Ljava/util/Iterator;
  #52 = Utf8               spliterator$mcD$sp$
  #53 = Utf8               (Lscala/collection/DoubleStepper;)Ljava/util/Spliterator;
  #54 = Utf8               <B:Ljava/lang/Object;>()Ljava/util/Spliterator<*>;
  #55 = Utf8               <init>
  #56 = Utf8               (Lscala/collection/DoubleStepper;)V
  #57 = NameAndType        #55:#56        // "<init>":(Lscala/collection/DoubleStepper;)V
  #58 = Methodref          #23.#57        // scala/collection/DoubleStepper$DoubleStepperSpliterator."<init>":(Lscala/collection/DoubleStepper;)V
  #59 = Utf8               javaIterator$mcD$sp$
  #60 = Utf8               (Lscala/collection/DoubleStepper;)Ljava/util/Iterator;
  #61 = Utf8               <B:Ljava/lang/Object;>()Ljava/util/Iterator<*>;
  #62 = Methodref          #21.#57        // scala/collection/DoubleStepper$$anon$7."<init>":(Lscala/collection/DoubleStepper;)V
  #63 = Utf8               $init$
  #64 = Utf8               Code
  #65 = Utf8               LineNumberTable
  #66 = Utf8               LocalVariableTable
  #67 = Utf8               MethodParameters
  #68 = Utf8               Signature
  #69 = Utf8               InnerClasses
  #70 = Utf8               SourceFile
  #71 = Utf8               RuntimeVisibleAnnotations
  #72 = Utf8               ScalaInlineInfo
  #73 = Utf8               ScalaSig
{
  public abstract scala.collection.DoubleStepper trySplit();
    descriptor: ()Lscala/collection/DoubleStepper;
    flags: (0x0401) ACC_PUBLIC, ACC_ABSTRACT

  public static java.util.Spliterator$OfDouble spliterator$(scala.collection.DoubleStepper);
    descriptor: (Lscala/collection/DoubleStepper;)Ljava/util/Spliterator$OfDouble;
    flags: (0x1009) ACC_PUBLIC, ACC_STATIC, ACC_SYNTHETIC
    Code:
      stack=1, locals=1, args_size=1
         0: aload_0
         1: invokespecial #33                 // InterfaceMethod spliterator:()Ljava/util/Spliterator$OfDouble;
         4: areturn
      LineNumberTable:
        line 296: 0
      LocalVariableTable:
        Start  Length  Slot  Name   Signature
            0       5     0 $this   Lscala/collection/DoubleStepper;
    MethodParameters:
      Name                           Flags
      $this                          final synthetic

  public default <B extends java.lang.Object> java.util.Spliterator$OfDouble spliterator();
    descriptor: ()Ljava/util/Spliterator$OfDouble;
    flags: (0x0001) ACC_PUBLIC
    Code:
      stack=1, locals=1, args_size=1
         0: aload_0
         1: invokeinterface #39,  1           // InterfaceMethod spliterator$mcD$sp:()Ljava/util/Spliterator;
         6: checkcast     #17                 // class java/util/Spliterator$OfDouble
         9: areturn
      LineNumberTable:
        line 296: 0
      LocalVariableTable:
        Start  Length  Slot  Name   Signature
            0      10     0  this   Lscala/collection/DoubleStepper;
    Signature: #35                          // <B:Ljava/lang/Object;>()Ljava/util/Spliterator$OfDouble;

  public static java.util.PrimitiveIterator$OfDouble javaIterator$(scala.collection.DoubleStepper);
    descriptor: (Lscala/collection/DoubleStepper;)Ljava/util/PrimitiveIterator$OfDouble;
    flags: (0x1009) ACC_PUBLIC, ACC_STATIC, ACC_SYNTHETIC
    Code:
      stack=1, locals=1, args_size=1
         0: aload_0
         1: invokespecial #46                 // InterfaceMethod javaIterator:()Ljava/util/PrimitiveIterator$OfDouble;
         4: areturn
      LineNumberTable:
        line 298: 0
      LocalVariableTable:
        Start  Length  Slot  Name   Signature
            0       5     0 $this   Lscala/collection/DoubleStepper;
    MethodParameters:
      Name                           Flags
      $this                          final synthetic

  public default <B extends java.lang.Object> java.util.PrimitiveIterator$OfDouble javaIterator();
    descriptor: ()Ljava/util/PrimitiveIterator$OfDouble;
    flags: (0x0001) ACC_PUBLIC
    Code:
      stack=1, locals=1, args_size=1
         0: aload_0
         1: invokeinterface #51,  1           // InterfaceMethod javaIterator$mcD$sp:()Ljava/util/Iterator;
         6: checkcast     #12                 // class java/util/PrimitiveIterator$OfDouble
         9: areturn
      LineNumberTable:
        line 298: 0
      LocalVariableTable:
        Start  Length  Slot  Name   Signature
            0      10     0  this   Lscala/collection/DoubleStepper;
    Signature: #47                          // <B:Ljava/lang/Object;>()Ljava/util/PrimitiveIterator$OfDouble;

  public static java.util.Spliterator spliterator$mcD$sp$(scala.collection.DoubleStepper);
    descriptor: (Lscala/collection/DoubleStepper;)Ljava/util/Spliterator;
    flags: (0x1009) ACC_PUBLIC, ACC_STATIC, ACC_SYNTHETIC
    Code:
      stack=1, locals=1, args_size=1
         0: aload_0
         1: invokespecial #39                 // InterfaceMethod spliterator$mcD$sp:()Ljava/util/Spliterator;
         4: areturn
      LineNumberTable:
        line 296: 0
      LocalVariableTable:
        Start  Length  Slot  Name   Signature
            0       5     0 $this   Lscala/collection/DoubleStepper;
    MethodParameters:
      Name                           Flags
      $this                          final synthetic

  public default <B extends java.lang.Object> java.util.Spliterator<?> spliterator$mcD$sp();
    descriptor: ()Ljava/util/Spliterator;
    flags: (0x0001) ACC_PUBLIC
    Code:
      stack=3, locals=1, args_size=1
         0: new           #23                 // class scala/collection/DoubleStepper$DoubleStepperSpliterator
         3: dup
         4: aload_0
         5: invokespecial #58                 // Method scala/collection/DoubleStepper$DoubleStepperSpliterator."<init>":(Lscala/collection/DoubleStepper;)V
         8: areturn
      LineNumberTable:
        line 296: 0
      LocalVariableTable:
        Start  Length  Slot  Name   Signature
            0       9     0  this   Lscala/collection/DoubleStepper;
    Signature: #54                          // <B:Ljava/lang/Object;>()Ljava/util/Spliterator<*>;

  public static java.util.Iterator javaIterator$mcD$sp$(scala.collection.DoubleStepper);
    descriptor: (Lscala/collection/DoubleStepper;)Ljava/util/Iterator;
    flags: (0x1009) ACC_PUBLIC, ACC_STATIC, ACC_SYNTHETIC
    Code:
      stack=1, locals=1, args_size=1
         0: aload_0
         1: invokespecial #51                 // InterfaceMethod javaIterator$mcD$sp:()Ljava/util/Iterator;
         4: areturn
      LineNumberTable:
        line 298: 0
      LocalVariableTable:
        Start  Length  Slot  Name   Signature
            0       5     0 $this   Lscala/collection/DoubleStepper;
    MethodParameters:
      Name                           Flags
      $this                          final synthetic

  public default <B extends java.lang.Object> java.util.Iterator<?> javaIterator$mcD$sp();
    descriptor: ()Ljava/util/Iterator;
    flags: (0x0001) ACC_PUBLIC
    Code:
      stack=3, locals=1, args_size=1
         0: new           #21                 // class scala/collection/DoubleStepper$$anon$7
         3: dup
         4: aload_0
         5: invokespecial #62                 // Method scala/collection/DoubleStepper$$anon$7."<init>":(Lscala/collection/DoubleStepper;)V
         8: areturn
      LineNumberTable:
        line 298: 0
      LocalVariableTable:
        Start  Length  Slot  Name   Signature
            0       9     0  this   Lscala/collection/DoubleStepper;
    Signature: #61                          // <B:Ljava/lang/Object;>()Ljava/util/Iterator<*>;

  public static void $init$(scala.collection.DoubleStepper);
    descriptor: (Lscala/collection/DoubleStepper;)V
    flags: (0x0009) ACC_PUBLIC, ACC_STATIC
    Code:
      stack=0, locals=1, args_size=1
         0: return
      LineNumberTable:
        line 293: 0
      LocalVariableTable:
        Start  Length  Slot  Name   Signature
            0       1     0 $this   Lscala/collection/DoubleStepper;
    MethodParameters:
      Name                           Flags
      $this                          final synthetic
}
InnerClasses:
  public static #15= #12 of #14;          // OfDouble=class java/util/PrimitiveIterator$OfDouble of class java/util/PrimitiveIterator
  public static #15= #17 of #19;          // OfDouble=class java/util/Spliterator$OfDouble of class java/util/Spliterator
  public final #21;                       // class scala/collection/DoubleStepper$$anon$7
  public static #24= #23 of #2;           // DoubleStepperSpliterator=class scala/collection/DoubleStepper$DoubleStepperSpliterator of class scala/collection/DoubleStepper
SourceFile: "Stepper.scala"
RuntimeVisibleAnnotations:
  0: #8(#9=s#10)
    scala.reflect.ScalaSignature(
      bytes="\u0006\u0005\u0005eaa\u0002\n\u0014!\u0003\r\t\u0001\u0007\u0005\u0006I\u0001!\t!\n\u0005\u0006S\u00011\tA\u000b\u0005\u0006Y\u0001!\t!\f\u0005\u0006\u0003\u0002!\tAQ\u0004\u0006\u0017NA\t\u0001\u0014\u0004\u0006%MA\t!\u0014\u0005\u0006\u001d\u001a!\ta\u0014\u0004\u0005!\u001a\u0001\u0011\u000b\u0003\u0005Y\u0011\t\u0005\t\u0015!\u0003,\u0011\u0015q\u0005\u0002\"\u0001Z\u0011\u0015i\u0006\u0002\"\u0001_\u0011\u0015i\u0006\u0002\"\u0011k\u0011\u0015I\u0003\u0002\"\u0011x\u0011\u0015A\b\u0002\"\u0001z\u0011\u0015i\b\u0002\"\u0001\u007f\u0011\u001d\t)\u0001\u0003C!\u0003\u000fAq!!\u0002\t\t\u0003\nYAA\u0007E_V\u0014G.Z*uKB\u0004XM\u001d\u0006\u0003)U\t!bY8mY\u0016\u001cG/[8o\u0015\u00051\u0012!B:dC2\f7\u0001A\n\u0004\u0001ei\u0002C\u0001\u000e\u001c\u001b\u0005)\u0012B\u0001\u000f\u0016\u0005\u0019\te.\u001f*fMB\u0019adH\u0011\u000e\u0003MI!\u0001I\n\u0003\u000fM#X\r\u001d9feB\u0011!DI\u0005\u0003GU\u0011a\u0001R8vE2,\u0017A\u0002\u0013j]&$H\u0005F\u0001\'!\tQr%\u0003\u0002)+\t!QK\\5u\u0003!!(/_*qY&$H#A\u0016\u0011\u0005y\u0001\u0011aC:qY&$XM]1u_J,\"AL\u001e\u0016\u0003=\u0002\"\u0001\r\u001d\u000f\u0005E2T\"\u0001\u001a\u000b\u0005M\"\u0014\u0001B;uS2T\u0011!N\u0001\u0005U\u00064\u0018-\u0003\u00028e\u0005Y1\u000b\u001d7ji\u0016\u0014\u0018\r^8s\u0013\tI$H\u0001\u0005PM\u0012{WO\u00197f\u0015\t9$\u0007B\u0003=\u0007\t\u0007QHA\u0001C#\t\tc\b\u0005\u0002\u001b\u007f%\u0011\u0001)\u0006\u0002\u0004\u0003:L\u0018\u0001\u00046bm\u0006LE/\u001a:bi>\u0014XCA\"K+\u0005!\u0005CA#I\u001d\t\td)\u0003\u0002He\u0005\t\u0002K]5nSRLg/Z%uKJ\fGo\u001c:\n\u0005eJ%BA$3\t\u0015aDA1\u0001>\u00035!u.\u001e2mKN#X\r\u001d9feB\u0011aDB\n\u0003\re\ta\u0001P5oSRtD#\u0001\'\u00031\u0011{WO\u00197f\'R,\u0007\u000f]3s\'Bd\u0017\u000e^3sCR|\'oE\u0002\t%>\u0002\"a\u0015,\u000e\u0003QS!!\u0016\u001b\u0002\t1\fgnZ\u0005\u0003/R\u0013aa\u00142kK\u000e$\u0018!A:\u0015\u0005ic\u0006CA.\t\u001b\u00051\u0001\"\u0002-\u000b\u0001\u0004Y\u0013A\u0003;ss\u0006#g/\u00198dKR\u0011qL\u0019\t\u00035\u0001L!!Y\u000b\u0003\u000f\t{w\u000e\\3b]\")1m\u0003a\u0001I\u0006\t1\r\u0005\u0002fQ6\taM\u0003\u0002he\u0005Aa-\u001e8di&|g.\u0003\u0002jM\nqAi\\;cY\u0016\u001cuN\\:v[\u0016\u0014HCA0l\u0011\u0015\u0019G\u00021\u0001ma\ti\'\u000fE\u0002f]BL!a\u001c4\u0003\u0011\r{gn];nKJ\u0004\"!\u001d:\r\u0001\u0011I1o[A\u0001\u0002\u0003\u0015\t\u0001\u001e\u0002\u0004?\u0012:\u0014CA;?!\t\u0019f/\u0003\u0002$)R\tq&\u0001\u0007fgRLW.\u0019;f\'&TX\rF\u0001{!\tQ20\u0003\u0002}+\t!Aj\u001c8h\u0003=\u0019\u0007.\u0019:bGR,\'/[:uS\u000e\u001cH#A@\u0011\u0007i\t\t!C\u0002\u0002\u0004U\u00111!\u00138u\u0003A1wN]#bG\"\u0014V-\\1j]&tw\rF\u0002\'\u0003\u0013AQa\u0019\tA\u0002\u0011$2AJA\u0007\u0011\u0019\u0019\u0017\u00031\u0001\u0002\u0010A\"\u0011\u0011CA\u000b!\u0011)g.a\u0005\u0011\u0007E\f)\u0002B\u0006\u0002\u0018\u00055\u0011\u0011!A\u0001\u0006\u0003!(aA0%q\u0001"
    )
  ScalaInlineInfo: length = 0x36 (unknown attribute)
   01 00 00 0A 00 3F 00 38 01 00 2B 00 2C 00 00 29
   00 2A 01 00 30 00 31 00 00 3B 00 3C 01 00 1E 00
   1F 00 00 1B 00 1C 01 00 24 00 25 00 00 34 00 35
   01 00 19 00 1A 00
  ScalaSig: length = 0x3 (unknown attribute)
   05 02 00
