Classfile /Users/mw/Projects/slang-braindump/.jar/jar8/assemble/slang-braindump/assemble/content/scala/collection/EvidenceIterableFactory$Delegate.class
  Last modified May 29, 2022; size 4307 bytes
  SHA-256 checksum 63958a673a2ba95fdc4dc29cfaddab72f4b46d8dcb5eeeec217b63b3980bdd51
  Compiled from "Factory.scala"
public class scala.collection.EvidenceIterableFactory$Delegate<CC extends java.lang.Object, Ev extends java.lang.Object> extends java.lang.Object implements scala.collection.EvidenceIterableFactory<CC, Ev>
  minor version: 0
  major version: 52
  flags: (0x0021) ACC_PUBLIC, ACC_SUPER
  this_class: #2                          // scala/collection/EvidenceIterableFactory$Delegate
  super_class: #5                         // java/lang/Object
  interfaces: 1, fields: 2, methods: 10, attributes: 5
Constant pool:
    #1 = Utf8               scala/collection/EvidenceIterableFactory$Delegate
    #2 = Class              #1            // scala/collection/EvidenceIterableFactory$Delegate
    #3 = Utf8               <CC:Ljava/lang/Object;Ev:Ljava/lang/Object;>Ljava/lang/Object;Lscala/collection/EvidenceIterableFactory<TCC;TEv;>;
    #4 = Utf8               java/lang/Object
    #5 = Class              #4            // java/lang/Object
    #6 = Utf8               scala/collection/EvidenceIterableFactory
    #7 = Class              #6            // scala/collection/EvidenceIterableFactory
    #8 = Utf8               Factory.scala
    #9 = Utf8               Delegate
   #10 = Utf8               serialVersionUID
   #11 = Utf8               J
   #12 = Long               3l
   #14 = Utf8               delegate
   #15 = Utf8               Lscala/collection/EvidenceIterableFactory;
   #16 = Utf8               Lscala/collection/EvidenceIterableFactory<TCC;TEv;>;
   #17 = Utf8               fill
   #18 = Utf8               (ILscala/Function0;Ljava/lang/Object;)Ljava/lang/Object;
   #19 = Utf8               <A:Ljava/lang/Object;>(ILscala/Function0<TA;>;TEv;)TCC;
   #20 = Utf8               n
   #21 = Utf8               elem
   #22 = Utf8               evidence$8
   #23 = Utf8               fill$
   #24 = Utf8               (Lscala/collection/EvidenceIterableFactory;ILscala/Function0;Ljava/lang/Object;)Ljava/lang/Object;
   #25 = NameAndType        #23:#24       // fill$:(Lscala/collection/EvidenceIterableFactory;ILscala/Function0;Ljava/lang/Object;)Ljava/lang/Object;
   #26 = InterfaceMethodref #7.#25        // scala/collection/EvidenceIterableFactory.fill$:(Lscala/collection/EvidenceIterableFactory;ILscala/Function0;Ljava/lang/Object;)Ljava/lang/Object;
   #27 = Utf8               this
   #28 = Utf8               Lscala/collection/EvidenceIterableFactory$Delegate;
   #29 = Utf8               I
   #30 = Utf8               Lscala/Function0;
   #31 = Utf8               Ljava/lang/Object;
   #32 = Utf8               tabulate
   #33 = Utf8               (ILscala/Function1;Ljava/lang/Object;)Ljava/lang/Object;
   #34 = Utf8               <A:Ljava/lang/Object;>(ILscala/Function1<Ljava/lang/Object;TA;>;TEv;)TCC;
   #35 = Utf8               f
   #36 = Utf8               evidence$9
   #37 = Utf8               tabulate$
   #38 = Utf8               (Lscala/collection/EvidenceIterableFactory;ILscala/Function1;Ljava/lang/Object;)Ljava/lang/Object;
   #39 = NameAndType        #37:#38       // tabulate$:(Lscala/collection/EvidenceIterableFactory;ILscala/Function1;Ljava/lang/Object;)Ljava/lang/Object;
   #40 = InterfaceMethodref #7.#39        // scala/collection/EvidenceIterableFactory.tabulate$:(Lscala/collection/EvidenceIterableFactory;ILscala/Function1;Ljava/lang/Object;)Ljava/lang/Object;
   #41 = Utf8               Lscala/Function1;
   #42 = Utf8               iterate
   #43 = Utf8               (Ljava/lang/Object;ILscala/Function1;Ljava/lang/Object;)Ljava/lang/Object;
   #44 = Utf8               <A:Ljava/lang/Object;>(TA;ILscala/Function1<TA;TA;>;TEv;)TCC;
   #45 = Utf8               start
   #46 = Utf8               len
   #47 = Utf8               evidence$10
   #48 = Utf8               iterate$
   #49 = Utf8               (Lscala/collection/EvidenceIterableFactory;Ljava/lang/Object;ILscala/Function1;Ljava/lang/Object;)Ljava/lang/Object;
   #50 = NameAndType        #48:#49       // iterate$:(Lscala/collection/EvidenceIterableFactory;Ljava/lang/Object;ILscala/Function1;Ljava/lang/Object;)Ljava/lang/Object;
   #51 = InterfaceMethodref #7.#50        // scala/collection/EvidenceIterableFactory.iterate$:(Lscala/collection/EvidenceIterableFactory;Ljava/lang/Object;ILscala/Function1;Ljava/lang/Object;)Ljava/lang/Object;
   #52 = Utf8               unfold
   #53 = Utf8               (Ljava/lang/Object;Lscala/Function1;Ljava/lang/Object;)Ljava/lang/Object;
   #54 = Utf8               <A:Ljava/lang/Object;S:Ljava/lang/Object;>(TS;Lscala/Function1<TS;Lscala/Option<Lscala/Tuple2<TA;TS;>;>;>;TEv;)TCC;
   #55 = Utf8               init
   #56 = Utf8               evidence$11
   #57 = Utf8               unfold$
   #58 = Utf8               (Lscala/collection/EvidenceIterableFactory;Ljava/lang/Object;Lscala/Function1;Ljava/lang/Object;)Ljava/lang/Object;
   #59 = NameAndType        #57:#58       // unfold$:(Lscala/collection/EvidenceIterableFactory;Ljava/lang/Object;Lscala/Function1;Ljava/lang/Object;)Ljava/lang/Object;
   #60 = InterfaceMethodref #7.#59        // scala/collection/EvidenceIterableFactory.unfold$:(Lscala/collection/EvidenceIterableFactory;Ljava/lang/Object;Lscala/Function1;Ljava/lang/Object;)Ljava/lang/Object;
   #61 = Utf8               evidenceIterableFactory
   #62 = Utf8               (Ljava/lang/Object;)Lscala/collection/Factory;
   #63 = Utf8               <A:Ljava/lang/Object;>(TEv;)Lscala/collection/Factory<TA;TCC;>;
   #64 = Utf8               evidence$13
   #65 = Utf8               evidenceIterableFactory$
   #66 = Utf8               (Lscala/collection/EvidenceIterableFactory;Ljava/lang/Object;)Lscala/collection/Factory;
   #67 = NameAndType        #65:#66       // evidenceIterableFactory$:(Lscala/collection/EvidenceIterableFactory;Ljava/lang/Object;)Lscala/collection/Factory;
   #68 = InterfaceMethodref #7.#67        // scala/collection/EvidenceIterableFactory.evidenceIterableFactory$:(Lscala/collection/EvidenceIterableFactory;Ljava/lang/Object;)Lscala/collection/Factory;
   #69 = Utf8               apply
   #70 = Utf8               (Lscala/collection/immutable/Seq;Ljava/lang/Object;)Ljava/lang/Object;
   #71 = Utf8               <A:Ljava/lang/Object;>(Lscala/collection/immutable/Seq<TA;>;TEv;)TCC;
   #72 = Utf8               xs
   #73 = Utf8               evidence$18
   #74 = NameAndType        #14:#15       // delegate:Lscala/collection/EvidenceIterableFactory;
   #75 = Fieldref           #2.#74        // scala/collection/EvidenceIterableFactory$Delegate.delegate:Lscala/collection/EvidenceIterableFactory;
   #76 = NameAndType        #69:#70       // apply:(Lscala/collection/immutable/Seq;Ljava/lang/Object;)Ljava/lang/Object;
   #77 = InterfaceMethodref #7.#76        // scala/collection/EvidenceIterableFactory.apply:(Lscala/collection/immutable/Seq;Ljava/lang/Object;)Ljava/lang/Object;
   #78 = Utf8               Lscala/collection/immutable/Seq;
   #79 = Utf8               empty
   #80 = Utf8               (Ljava/lang/Object;)Ljava/lang/Object;
   #81 = Utf8               <A:Ljava/lang/Object;>(TEv;)TCC;
   #82 = Utf8               evidence$19
   #83 = NameAndType        #79:#80       // empty:(Ljava/lang/Object;)Ljava/lang/Object;
   #84 = InterfaceMethodref #7.#83        // scala/collection/EvidenceIterableFactory.empty:(Ljava/lang/Object;)Ljava/lang/Object;
   #85 = Utf8               from
   #86 = Utf8               (Lscala/collection/IterableOnce;Ljava/lang/Object;)Ljava/lang/Object;
   #87 = Utf8               <E:Ljava/lang/Object;>(Lscala/collection/IterableOnce<TE;>;TEv;)TCC;
   #88 = Utf8               it
   #89 = Utf8               evidence$20
   #90 = NameAndType        #85:#86       // from:(Lscala/collection/IterableOnce;Ljava/lang/Object;)Ljava/lang/Object;
   #91 = InterfaceMethodref #7.#90        // scala/collection/EvidenceIterableFactory.from:(Lscala/collection/IterableOnce;Ljava/lang/Object;)Ljava/lang/Object;
   #92 = Utf8               Lscala/collection/IterableOnce;
   #93 = Utf8               newBuilder
   #94 = Utf8               (Ljava/lang/Object;)Lscala/collection/mutable/Builder;
   #95 = Utf8               <A:Ljava/lang/Object;>(TEv;)Lscala/collection/mutable/Builder<TA;TCC;>;
   #96 = Utf8               evidence$21
   #97 = NameAndType        #93:#94       // newBuilder:(Ljava/lang/Object;)Lscala/collection/mutable/Builder;
   #98 = InterfaceMethodref #7.#97        // scala/collection/EvidenceIterableFactory.newBuilder:(Ljava/lang/Object;)Lscala/collection/mutable/Builder;
   #99 = Utf8               <init>
  #100 = Utf8               (Lscala/collection/EvidenceIterableFactory;)V
  #101 = Utf8               (Lscala/collection/EvidenceIterableFactory<TCC;TEv;>;)V
  #102 = Utf8               ()V
  #103 = NameAndType        #99:#102      // "<init>":()V
  #104 = Methodref          #5.#103       // java/lang/Object."<init>":()V
  #105 = Utf8               ConstantValue
  #106 = Utf8               Signature
  #107 = Utf8               Code
  #108 = Utf8               LineNumberTable
  #109 = Utf8               LocalVariableTable
  #110 = Utf8               MethodParameters
  #111 = Utf8               InnerClasses
  #112 = Utf8               SourceFile
  #113 = Utf8               ScalaInlineInfo
  #114 = Utf8               Scala
{
  private static final long serialVersionUID;
    descriptor: J
    flags: (0x001a) ACC_PRIVATE, ACC_STATIC, ACC_FINAL
    ConstantValue: long 3l

  private final scala.collection.EvidenceIterableFactory<CC, Ev> delegate;
    descriptor: Lscala/collection/EvidenceIterableFactory;
    flags: (0x0012) ACC_PRIVATE, ACC_FINAL
    Signature: #16                          // Lscala/collection/EvidenceIterableFactory<TCC;TEv;>;

  public <A extends java.lang.Object> CC fill(int, scala.Function0<A>, Ev);
    descriptor: (ILscala/Function0;Ljava/lang/Object;)Ljava/lang/Object;
    flags: (0x0001) ACC_PUBLIC
    Code:
      stack=4, locals=4, args_size=4
         0: aload_0
         1: iload_1
         2: aload_2
         3: aload_3
         4: invokestatic  #26                 // InterfaceMethod scala/collection/EvidenceIterableFactory.fill$:(Lscala/collection/EvidenceIterableFactory;ILscala/Function0;Ljava/lang/Object;)Ljava/lang/Object;
         7: areturn
      LineNumberTable:
        line 531: 0
      LocalVariableTable:
        Start  Length  Slot  Name   Signature
            0       8     0  this   Lscala/collection/EvidenceIterableFactory$Delegate;
            0       8     1     n   I
            0       8     2  elem   Lscala/Function0;
            0       8     3 evidence$8   Ljava/lang/Object;
    Signature: #19                          // <A:Ljava/lang/Object;>(ILscala/Function0<TA;>;TEv;)TCC;
    MethodParameters:
      Name                           Flags
      n                              final
      elem                           final
      evidence$8                     final

  public <A extends java.lang.Object> CC tabulate(int, scala.Function1<java.lang.Object, A>, Ev);
    descriptor: (ILscala/Function1;Ljava/lang/Object;)Ljava/lang/Object;
    flags: (0x0001) ACC_PUBLIC
    Code:
      stack=4, locals=4, args_size=4
         0: aload_0
         1: iload_1
         2: aload_2
         3: aload_3
         4: invokestatic  #40                 // InterfaceMethod scala/collection/EvidenceIterableFactory.tabulate$:(Lscala/collection/EvidenceIterableFactory;ILscala/Function1;Ljava/lang/Object;)Ljava/lang/Object;
         7: areturn
      LineNumberTable:
        line 531: 0
      LocalVariableTable:
        Start  Length  Slot  Name   Signature
            0       8     0  this   Lscala/collection/EvidenceIterableFactory$Delegate;
            0       8     1     n   I
            0       8     2     f   Lscala/Function1;
            0       8     3 evidence$9   Ljava/lang/Object;
    Signature: #34                          // <A:Ljava/lang/Object;>(ILscala/Function1<Ljava/lang/Object;TA;>;TEv;)TCC;
    MethodParameters:
      Name                           Flags
      n                              final
      f                              final
      evidence$9                     final

  public <A extends java.lang.Object> CC iterate(A, int, scala.Function1<A, A>, Ev);
    descriptor: (Ljava/lang/Object;ILscala/Function1;Ljava/lang/Object;)Ljava/lang/Object;
    flags: (0x0001) ACC_PUBLIC
    Code:
      stack=5, locals=5, args_size=5
         0: aload_0
         1: aload_1
         2: iload_2
         3: aload_3
         4: aload         4
         6: invokestatic  #51                 // InterfaceMethod scala/collection/EvidenceIterableFactory.iterate$:(Lscala/collection/EvidenceIterableFactory;Ljava/lang/Object;ILscala/Function1;Ljava/lang/Object;)Ljava/lang/Object;
         9: areturn
      LineNumberTable:
        line 531: 0
      LocalVariableTable:
        Start  Length  Slot  Name   Signature
            0      10     0  this   Lscala/collection/EvidenceIterableFactory$Delegate;
            0      10     1 start   Ljava/lang/Object;
            0      10     2   len   I
            0      10     3     f   Lscala/Function1;
            0      10     4 evidence$10   Ljava/lang/Object;
    Signature: #44                          // <A:Ljava/lang/Object;>(TA;ILscala/Function1<TA;TA;>;TEv;)TCC;
    MethodParameters:
      Name                           Flags
      start                          final
      len                            final
      f                              final
      evidence$10                    final

  public <A extends java.lang.Object, S extends java.lang.Object> CC unfold(S, scala.Function1<S, scala.Option<scala.Tuple2<A, S>>>, Ev);
    descriptor: (Ljava/lang/Object;Lscala/Function1;Ljava/lang/Object;)Ljava/lang/Object;
    flags: (0x0001) ACC_PUBLIC
    Code:
      stack=4, locals=4, args_size=4
         0: aload_0
         1: aload_1
         2: aload_2
         3: aload_3
         4: invokestatic  #60                 // InterfaceMethod scala/collection/EvidenceIterableFactory.unfold$:(Lscala/collection/EvidenceIterableFactory;Ljava/lang/Object;Lscala/Function1;Ljava/lang/Object;)Ljava/lang/Object;
         7: areturn
      LineNumberTable:
        line 531: 0
      LocalVariableTable:
        Start  Length  Slot  Name   Signature
            0       8     0  this   Lscala/collection/EvidenceIterableFactory$Delegate;
            0       8     1  init   Ljava/lang/Object;
            0       8     2     f   Lscala/Function1;
            0       8     3 evidence$11   Ljava/lang/Object;
    Signature: #54                          // <A:Ljava/lang/Object;S:Ljava/lang/Object;>(TS;Lscala/Function1<TS;Lscala/Option<Lscala/Tuple2<TA;TS;>;>;>;TEv;)TCC;
    MethodParameters:
      Name                           Flags
      init                           final
      f                              final
      evidence$11                    final

  public <A extends java.lang.Object> scala.collection.Factory<A, CC> evidenceIterableFactory(Ev);
    descriptor: (Ljava/lang/Object;)Lscala/collection/Factory;
    flags: (0x0001) ACC_PUBLIC
    Code:
      stack=2, locals=2, args_size=2
         0: aload_0
         1: aload_1
         2: invokestatic  #68                 // InterfaceMethod scala/collection/EvidenceIterableFactory.evidenceIterableFactory$:(Lscala/collection/EvidenceIterableFactory;Ljava/lang/Object;)Lscala/collection/Factory;
         5: areturn
      LineNumberTable:
        line 531: 0
      LocalVariableTable:
        Start  Length  Slot  Name   Signature
            0       6     0  this   Lscala/collection/EvidenceIterableFactory$Delegate;
            0       6     1 evidence$13   Ljava/lang/Object;
    Signature: #63                          // <A:Ljava/lang/Object;>(TEv;)Lscala/collection/Factory<TA;TCC;>;
    MethodParameters:
      Name                           Flags
      evidence$13                    final

  public <A extends java.lang.Object> CC apply(scala.collection.immutable.Seq<A>, Ev);
    descriptor: (Lscala/collection/immutable/Seq;Ljava/lang/Object;)Ljava/lang/Object;
    flags: (0x0001) ACC_PUBLIC
    Code:
      stack=3, locals=3, args_size=3
         0: aload_0
         1: getfield      #75                 // Field delegate:Lscala/collection/EvidenceIterableFactory;
         4: aload_1
         5: aload_2
         6: invokeinterface #77,  3           // InterfaceMethod scala/collection/EvidenceIterableFactory.apply:(Lscala/collection/immutable/Seq;Ljava/lang/Object;)Ljava/lang/Object;
        11: areturn
      LineNumberTable:
        line 532: 0
      LocalVariableTable:
        Start  Length  Slot  Name   Signature
            0      12     0  this   Lscala/collection/EvidenceIterableFactory$Delegate;
            0      12     1    xs   Lscala/collection/immutable/Seq;
            0      12     2 evidence$18   Ljava/lang/Object;
    Signature: #71                          // <A:Ljava/lang/Object;>(Lscala/collection/immutable/Seq<TA;>;TEv;)TCC;
    MethodParameters:
      Name                           Flags
      xs                             final
      evidence$18                    final

  public <A extends java.lang.Object> CC empty(Ev);
    descriptor: (Ljava/lang/Object;)Ljava/lang/Object;
    flags: (0x0001) ACC_PUBLIC
    Code:
      stack=2, locals=2, args_size=2
         0: aload_0
         1: getfield      #75                 // Field delegate:Lscala/collection/EvidenceIterableFactory;
         4: aload_1
         5: invokeinterface #84,  2           // InterfaceMethod scala/collection/EvidenceIterableFactory.empty:(Ljava/lang/Object;)Ljava/lang/Object;
        10: areturn
      LineNumberTable:
        line 533: 0
      LocalVariableTable:
        Start  Length  Slot  Name   Signature
            0      11     0  this   Lscala/collection/EvidenceIterableFactory$Delegate;
            0      11     1 evidence$19   Ljava/lang/Object;
    Signature: #81                          // <A:Ljava/lang/Object;>(TEv;)TCC;
    MethodParameters:
      Name                           Flags
      evidence$19                    final

  public <E extends java.lang.Object> CC from(scala.collection.IterableOnce<E>, Ev);
    descriptor: (Lscala/collection/IterableOnce;Ljava/lang/Object;)Ljava/lang/Object;
    flags: (0x0001) ACC_PUBLIC
    Code:
      stack=3, locals=3, args_size=3
         0: aload_0
         1: getfield      #75                 // Field delegate:Lscala/collection/EvidenceIterableFactory;
         4: aload_1
         5: aload_2
         6: invokeinterface #91,  3           // InterfaceMethod scala/collection/EvidenceIterableFactory.from:(Lscala/collection/IterableOnce;Ljava/lang/Object;)Ljava/lang/Object;
        11: areturn
      LineNumberTable:
        line 534: 0
      LocalVariableTable:
        Start  Length  Slot  Name   Signature
            0      12     0  this   Lscala/collection/EvidenceIterableFactory$Delegate;
            0      12     1    it   Lscala/collection/IterableOnce;
            0      12     2 evidence$20   Ljava/lang/Object;
    Signature: #87                          // <E:Ljava/lang/Object;>(Lscala/collection/IterableOnce<TE;>;TEv;)TCC;
    MethodParameters:
      Name                           Flags
      it                             final
      evidence$20                    final

  public <A extends java.lang.Object> scala.collection.mutable.Builder<A, CC> newBuilder(Ev);
    descriptor: (Ljava/lang/Object;)Lscala/collection/mutable/Builder;
    flags: (0x0001) ACC_PUBLIC
    Code:
      stack=2, locals=2, args_size=2
         0: aload_0
         1: getfield      #75                 // Field delegate:Lscala/collection/EvidenceIterableFactory;
         4: aload_1
         5: invokeinterface #98,  2           // InterfaceMethod scala/collection/EvidenceIterableFactory.newBuilder:(Ljava/lang/Object;)Lscala/collection/mutable/Builder;
        10: areturn
      LineNumberTable:
        line 535: 0
      LocalVariableTable:
        Start  Length  Slot  Name   Signature
            0      11     0  this   Lscala/collection/EvidenceIterableFactory$Delegate;
            0      11     1 evidence$21   Ljava/lang/Object;
    Signature: #95                          // <A:Ljava/lang/Object;>(TEv;)Lscala/collection/mutable/Builder<TA;TCC;>;
    MethodParameters:
      Name                           Flags
      evidence$21                    final

  public scala.collection.EvidenceIterableFactory$Delegate(scala.collection.EvidenceIterableFactory<CC, Ev>);
    descriptor: (Lscala/collection/EvidenceIterableFactory;)V
    flags: (0x0001) ACC_PUBLIC
    Code:
      stack=2, locals=2, args_size=2
         0: aload_0
         1: aload_1
         2: putfield      #75                 // Field delegate:Lscala/collection/EvidenceIterableFactory;
         5: aload_0
         6: invokespecial #104                // Method java/lang/Object."<init>":()V
         9: return
      LineNumberTable:
        line 531: 0
        line 531: 9
      LocalVariableTable:
        Start  Length  Slot  Name   Signature
            0      10     0  this   Lscala/collection/EvidenceIterableFactory$Delegate;
            0      10     1 delegate   Lscala/collection/EvidenceIterableFactory;
    Signature: #101                         // (Lscala/collection/EvidenceIterableFactory<TCC;TEv;>;)V
    MethodParameters:
      Name                           Flags
      delegate                       final
}
InnerClasses:
  public static #9= #2 of #7;             // Delegate=class scala/collection/EvidenceIterableFactory$Delegate of class scala/collection/EvidenceIterableFactory
Signature: #3                           // <CC:Ljava/lang/Object;Ev:Ljava/lang/Object;>Ljava/lang/Object;Lscala/collection/EvidenceIterableFactory<TCC;TEv;>;
SourceFile: "Factory.scala"
  ScalaInlineInfo: length = 0x36 (unknown attribute)
   01 00 00 0A 00 63 00 64 00 00 45 00 46 00 00 4F
   00 50 00 00 3D 00 3E 00 00 11 00 12 00 00 55 00
   56 00 00 2A 00 2B 00 00 5D 00 5E 00 00 20 00 21
   00 00 34 00 35 00
  Scala: length = 0x0 (unknown attribute)

