Classfile /Users/mw/Projects/slang-braindump/.jar/jar8/assemble/slang-braindump/assemble/content/scala/collection/EvidenceIterableFactory$EvidenceIterableFactoryToBuildFrom.class
  Last modified May 29, 2022; size 2331 bytes
  SHA-256 checksum e0ad2627087c00eb4f7c154f7f8139b71b39ae9bc766480d46da3009b29331c0
  Compiled from "Factory.scala"
public class scala.collection.EvidenceIterableFactory$EvidenceIterableFactoryToBuildFrom<Ev extends java.lang.Object, A extends java.lang.Object, CC extends java.lang.Object> extends java.lang.Object implements scala.collection.BuildFrom<java.lang.Object, A, CC>
  minor version: 0
  major version: 52
  flags: (0x0021) ACC_PUBLIC, ACC_SUPER
  this_class: #2                          // scala/collection/EvidenceIterableFactory$EvidenceIterableFactoryToBuildFrom
  super_class: #5                         // java/lang/Object
  interfaces: 1, fields: 2, methods: 5, attributes: 5
Constant pool:
   #1 = Utf8               scala/collection/EvidenceIterableFactory$EvidenceIterableFactoryToBuildFrom
   #2 = Class              #1             // scala/collection/EvidenceIterableFactory$EvidenceIterableFactoryToBuildFrom
   #3 = Utf8               <Ev:Ljava/lang/Object;A:Ljava/lang/Object;CC:Ljava/lang/Object;>Ljava/lang/Object;Lscala/collection/BuildFrom<Ljava/lang/Object;TA;TCC;>;
   #4 = Utf8               java/lang/Object
   #5 = Class              #4             // java/lang/Object
   #6 = Utf8               scala/collection/BuildFrom
   #7 = Class              #6             // scala/collection/BuildFrom
   #8 = Utf8               Factory.scala
   #9 = Utf8               scala/collection/EvidenceIterableFactory
  #10 = Class              #9             // scala/collection/EvidenceIterableFactory
  #11 = Utf8               EvidenceIterableFactoryToBuildFrom
  #12 = Utf8               factory
  #13 = Utf8               Lscala/collection/EvidenceIterableFactory;
  #14 = Utf8               Lscala/collection/EvidenceIterableFactory<TCC;TEv;>;
  #15 = Utf8               evidence$17
  #16 = Utf8               Ljava/lang/Object;
  #17 = Utf8               TEv;
  #18 = Utf8               apply
  #19 = Utf8               (Ljava/lang/Object;)Lscala/collection/mutable/Builder;
  #20 = Utf8               (Ljava/lang/Object;)Lscala/collection/mutable/Builder<TA;TCC;>;
  #21 = Utf8               from
  #22 = Utf8               apply$
  #23 = Utf8               (Lscala/collection/BuildFrom;Ljava/lang/Object;)Lscala/collection/mutable/Builder;
  #24 = NameAndType        #22:#23        // apply$:(Lscala/collection/BuildFrom;Ljava/lang/Object;)Lscala/collection/mutable/Builder;
  #25 = InterfaceMethodref #7.#24         // scala/collection/BuildFrom.apply$:(Lscala/collection/BuildFrom;Ljava/lang/Object;)Lscala/collection/mutable/Builder;
  #26 = Utf8               this
  #27 = Utf8               Lscala/collection/EvidenceIterableFactory$EvidenceIterableFactoryToBuildFrom;
  #28 = Utf8               toFactory
  #29 = Utf8               (Ljava/lang/Object;)Lscala/collection/Factory;
  #30 = Utf8               (Ljava/lang/Object;)Lscala/collection/Factory<TA;TCC;>;
  #31 = Utf8               toFactory$
  #32 = Utf8               (Lscala/collection/BuildFrom;Ljava/lang/Object;)Lscala/collection/Factory;
  #33 = NameAndType        #31:#32        // toFactory$:(Lscala/collection/BuildFrom;Ljava/lang/Object;)Lscala/collection/Factory;
  #34 = InterfaceMethodref #7.#33         // scala/collection/BuildFrom.toFactory$:(Lscala/collection/BuildFrom;Ljava/lang/Object;)Lscala/collection/Factory;
  #35 = Utf8               fromSpecific
  #36 = Utf8               (Ljava/lang/Object;Lscala/collection/IterableOnce;)Ljava/lang/Object;
  #37 = Utf8               (Ljava/lang/Object;Lscala/collection/IterableOnce<TA;>;)TCC;
  #38 = Utf8               it
  #39 = NameAndType        #12:#13        // factory:Lscala/collection/EvidenceIterableFactory;
  #40 = Fieldref           #2.#39         // scala/collection/EvidenceIterableFactory$EvidenceIterableFactoryToBuildFrom.factory:Lscala/collection/EvidenceIterableFactory;
  #41 = NameAndType        #15:#16        // evidence$17:Ljava/lang/Object;
  #42 = Fieldref           #2.#41         // scala/collection/EvidenceIterableFactory$EvidenceIterableFactoryToBuildFrom.evidence$17:Ljava/lang/Object;
  #43 = Utf8               (Lscala/collection/IterableOnce;Ljava/lang/Object;)Ljava/lang/Object;
  #44 = NameAndType        #21:#43        // from:(Lscala/collection/IterableOnce;Ljava/lang/Object;)Ljava/lang/Object;
  #45 = InterfaceMethodref #10.#44        // scala/collection/EvidenceIterableFactory.from:(Lscala/collection/IterableOnce;Ljava/lang/Object;)Ljava/lang/Object;
  #46 = Utf8               Lscala/collection/IterableOnce;
  #47 = Utf8               newBuilder
  #48 = NameAndType        #47:#19        // newBuilder:(Ljava/lang/Object;)Lscala/collection/mutable/Builder;
  #49 = InterfaceMethodref #10.#48        // scala/collection/EvidenceIterableFactory.newBuilder:(Ljava/lang/Object;)Lscala/collection/mutable/Builder;
  #50 = Utf8               <init>
  #51 = Utf8               (Lscala/collection/EvidenceIterableFactory;Ljava/lang/Object;)V
  #52 = Utf8               (Lscala/collection/EvidenceIterableFactory<TCC;TEv;>;TEv;)V
  #53 = Utf8               ()V
  #54 = NameAndType        #50:#53        // "<init>":()V
  #55 = Methodref          #5.#54         // java/lang/Object."<init>":()V
  #56 = Utf8               Signature
  #57 = Utf8               Code
  #58 = Utf8               LineNumberTable
  #59 = Utf8               LocalVariableTable
  #60 = Utf8               Deprecated
  #61 = Utf8               MethodParameters
  #62 = Utf8               InnerClasses
  #63 = Utf8               SourceFile
  #64 = Utf8               ScalaInlineInfo
  #65 = Utf8               Scala
{
  private final scala.collection.EvidenceIterableFactory<CC, Ev> factory;
    descriptor: Lscala/collection/EvidenceIterableFactory;
    flags: (0x0012) ACC_PRIVATE, ACC_FINAL
    Signature: #14                          // Lscala/collection/EvidenceIterableFactory<TCC;TEv;>;

  private final Ev evidence$17;
    descriptor: Ljava/lang/Object;
    flags: (0x0012) ACC_PRIVATE, ACC_FINAL
    Signature: #17                          // TEv;

  public scala.collection.mutable.Builder<A, CC> apply(java.lang.Object);
    descriptor: (Ljava/lang/Object;)Lscala/collection/mutable/Builder;
    flags: (0x0001) ACC_PUBLIC
    Code:
      stack=2, locals=2, args_size=2
         0: aload_0
         1: aload_1
         2: invokestatic  #25                 // InterfaceMethod scala/collection/BuildFrom.apply$:(Lscala/collection/BuildFrom;Ljava/lang/Object;)Lscala/collection/mutable/Builder;
         5: areturn
      LineNumberTable:
        line 525: 0
      LocalVariableTable:
        Start  Length  Slot  Name   Signature
            0       6     0  this   Lscala/collection/EvidenceIterableFactory$EvidenceIterableFactoryToBuildFrom;
            0       6     1  from   Ljava/lang/Object;
    Signature: #20                          // (Ljava/lang/Object;)Lscala/collection/mutable/Builder<TA;TCC;>;
    Deprecated: true
    MethodParameters:
      Name                           Flags
      from                           final

  public scala.collection.Factory<A, CC> toFactory(java.lang.Object);
    descriptor: (Ljava/lang/Object;)Lscala/collection/Factory;
    flags: (0x0001) ACC_PUBLIC
    Code:
      stack=2, locals=2, args_size=2
         0: aload_0
         1: aload_1
         2: invokestatic  #34                 // InterfaceMethod scala/collection/BuildFrom.toFactory$:(Lscala/collection/BuildFrom;Ljava/lang/Object;)Lscala/collection/Factory;
         5: areturn
      LineNumberTable:
        line 525: 0
      LocalVariableTable:
        Start  Length  Slot  Name   Signature
            0       6     0  this   Lscala/collection/EvidenceIterableFactory$EvidenceIterableFactoryToBuildFrom;
            0       6     1  from   Ljava/lang/Object;
    Signature: #30                          // (Ljava/lang/Object;)Lscala/collection/Factory<TA;TCC;>;
    MethodParameters:
      Name                           Flags
      from                           final

  public CC fromSpecific(java.lang.Object, scala.collection.IterableOnce<A>);
    descriptor: (Ljava/lang/Object;Lscala/collection/IterableOnce;)Ljava/lang/Object;
    flags: (0x0001) ACC_PUBLIC
    Code:
      stack=3, locals=3, args_size=3
         0: aload_0
         1: getfield      #40                 // Field factory:Lscala/collection/EvidenceIterableFactory;
         4: aload_2
         5: aload_0
         6: getfield      #42                 // Field evidence$17:Ljava/lang/Object;
         9: invokeinterface #45,  3           // InterfaceMethod scala/collection/EvidenceIterableFactory.from:(Lscala/collection/IterableOnce;Ljava/lang/Object;)Ljava/lang/Object;
        14: areturn
      LineNumberTable:
        line 526: 0
      LocalVariableTable:
        Start  Length  Slot  Name   Signature
            0      15     0  this   Lscala/collection/EvidenceIterableFactory$EvidenceIterableFactoryToBuildFrom;
            0      15     1  from   Ljava/lang/Object;
            0      15     2    it   Lscala/collection/IterableOnce;
    Signature: #37                          // (Ljava/lang/Object;Lscala/collection/IterableOnce<TA;>;)TCC;
    MethodParameters:
      Name                           Flags
      from                           final
      it                             final

  public scala.collection.mutable.Builder<A, CC> newBuilder(java.lang.Object);
    descriptor: (Ljava/lang/Object;)Lscala/collection/mutable/Builder;
    flags: (0x0001) ACC_PUBLIC
    Code:
      stack=2, locals=2, args_size=2
         0: aload_0
         1: getfield      #40                 // Field factory:Lscala/collection/EvidenceIterableFactory;
         4: aload_0
         5: getfield      #42                 // Field evidence$17:Ljava/lang/Object;
         8: invokeinterface #49,  2           // InterfaceMethod scala/collection/EvidenceIterableFactory.newBuilder:(Ljava/lang/Object;)Lscala/collection/mutable/Builder;
        13: areturn
      LineNumberTable:
        line 527: 0
      LocalVariableTable:
        Start  Length  Slot  Name   Signature
            0      14     0  this   Lscala/collection/EvidenceIterableFactory$EvidenceIterableFactoryToBuildFrom;
            0      14     1  from   Ljava/lang/Object;
    Signature: #20                          // (Ljava/lang/Object;)Lscala/collection/mutable/Builder<TA;TCC;>;
    MethodParameters:
      Name                           Flags
      from                           final

  public scala.collection.EvidenceIterableFactory$EvidenceIterableFactoryToBuildFrom(scala.collection.EvidenceIterableFactory<CC, Ev>, Ev);
    descriptor: (Lscala/collection/EvidenceIterableFactory;Ljava/lang/Object;)V
    flags: (0x0001) ACC_PUBLIC
    Code:
      stack=2, locals=3, args_size=3
         0: aload_0
         1: aload_1
         2: putfield      #40                 // Field factory:Lscala/collection/EvidenceIterableFactory;
         5: aload_0
         6: aload_2
         7: putfield      #42                 // Field evidence$17:Ljava/lang/Object;
        10: aload_0
        11: invokespecial #55                 // Method java/lang/Object."<init>":()V
        14: return
      LineNumberTable:
        line 525: 0
      LocalVariableTable:
        Start  Length  Slot  Name   Signature
            0      15     0  this   Lscala/collection/EvidenceIterableFactory$EvidenceIterableFactoryToBuildFrom;
            0      15     1 factory   Lscala/collection/EvidenceIterableFactory;
            0      15     2 evidence$17   Ljava/lang/Object;
    Signature: #52                          // (Lscala/collection/EvidenceIterableFactory<TCC;TEv;>;TEv;)V
    MethodParameters:
      Name                           Flags
      factory                        final
      evidence$17                    final
}
InnerClasses:
  private static #11= #2 of #10;          // EvidenceIterableFactoryToBuildFrom=class scala/collection/EvidenceIterableFactory$EvidenceIterableFactoryToBuildFrom of class scala/collection/EvidenceIterableFactory
Signature: #3                           // <Ev:Ljava/lang/Object;A:Ljava/lang/Object;CC:Ljava/lang/Object;>Ljava/lang/Object;Lscala/collection/BuildFrom<Ljava/lang/Object;TA;TCC;>;
SourceFile: "Factory.scala"
  ScalaInlineInfo: length = 0x1D (unknown attribute)
   01 00 00 05 00 32 00 33 00 00 12 00 13 04 00 23
   00 24 00 00 2F 00 13 00 00 1C 00 1D 00
  Scala: length = 0x0 (unknown attribute)

