Classfile /Users/mw/Projects/slang-braindump/.jar/jar8/assemble/slang-braindump/assemble/content/scala/collection/IndexedSeqOps.class
  Last modified May 29, 2022; size 13769 bytes
  SHA-256 checksum 83423e3713ae4afa6c54220dd35cd0cf617f31f87ab8525b92571ab5142ab591
  Compiled from "IndexedSeq.scala"
public interface scala.collection.IndexedSeqOps<A extends java.lang.Object, CC extends java.lang.Object, C extends java.lang.Object> extends scala.collection.SeqOps<A, CC, C>
  minor version: 0
  major version: 52
  flags: (0x0601) ACC_PUBLIC, ACC_INTERFACE, ACC_ABSTRACT
  this_class: #2                          // scala/collection/IndexedSeqOps
  super_class: #5                         // java/lang/Object
  interfaces: 1, fields: 0, methods: 48, attributes: 6
Constant pool:
    #1 = Utf8               scala/collection/IndexedSeqOps
    #2 = Class              #1            // scala/collection/IndexedSeqOps
    #3 = Utf8               <A:Ljava/lang/Object;CC:Ljava/lang/Object;C:Ljava/lang/Object;>Ljava/lang/Object;Lscala/collection/SeqOps<TA;TCC;TC;>;
    #4 = Utf8               java/lang/Object
    #5 = Class              #4            // java/lang/Object
    #6 = Utf8               scala/collection/SeqOps
    #7 = Class              #6            // scala/collection/SeqOps
    #8 = Utf8               IndexedSeq.scala
    #9 = Utf8               Lscala/reflect/ScalaSignature;
   #10 = Utf8               bytes
   #11 = Utf8               \u0006\u0005\t%aa\u0002\u000e\u001c!\u0003\r\t\u0001\t\u0005\u0006w\u0001!\t\u0001\u0010\u0005\u0006\u0001\u0002!\t!\u0011\u0005\u0006\u000b\u0002!\tE\u0012\u0005\u0006S\u0002!\t%\u0011\u0005\u0006U\u0002!\te\u001b\u0005\u0006q\u0002!\t%\u001f\u0005\u0006q\u0002!\t% \u0005\b\u0003?\u0001A\u0011KA\u0011\u0011\u001d\tI\u0003\u0001C!\u0003WAq!a\u000f\u0001\t\u0003\ni\u0004C\u0004\u0002D\u0001!\t%!\u0012\t\u000f\u0005%\u0003\u0001\"\u0011\u0002L!9\u0011q\n\u0001\u0005B\u0005E\u0003bBA+\u0001\u0011\u0005\u0013q\u000b\u0005\b\u0003W\u0002A\u0011IA7\u0011\u001d\ty\u0007\u0001C!\u0003cBq!a\u001e\u0001\t\u0003\nI\bC\u0004\u0002|\u0001!\t%! \t\u000f\u0005\u0015\u0005\u0001\"\u0011\u0002z!9\u0011q\u0011\u0001\u0005F\u0005%\u0005bBAH\u0001\u0011\u0005\u0013\u0011\u0013\u0005\b\u0003\u000f\u0003AQIAJ\u0011\u001d\t\u0019\u000b\u0001C!\u0003KCq!a)\u0001\t\u0003\ny\r\u0003\u0005\u0002f\u0002\u0001K\u0011BAt\u00055Ie\u000eZ3yK\u0012\u001cV-](qg*\u0011A$H\u0001\u000bG>dG.Z2uS>t\'\"\u0001\u0010\u0002\u000bM\u001c\u0017\r\\1\u0004\u0001U!\u0011\u0005L\u001a:\'\r\u0001!E\n\t\u0003G\u0011j\u0011!H\u0005\u0003Ku\u00111!\u00118z!\u00159\u0003F\u000b\u001a9\u001b\u0005Y\u0012BA\u0015\u001c\u0005\u0019\u0019V-](qgB\u00111\u0006\f\u0007\u0001\t\u0019i\u0003\u0001\"b\u0001]\t\t\u0011)\u0005\u00020EA\u00111\u0005M\u0005\u0003cu\u0011qAT8uQ&tw\r\u0005\u0002,g\u00111A\u0007\u0001CC\u0002U\u0012!aQ\"\u0016\u000592D!B\u001c4\u0005\u0004q#\u0001B0%IE\u0002\"aK\u001d\u0005\ri\u0002AQ1\u0001/\u0005\u0005\u0019\u0015A\u0002\u0013j]&$H\u0005F\u0001>!\t\u0019c(\u0003\u0002@;\t!QK\\5u\u0003!IG/\u001a:bi>\u0014X#\u0001\"\u0011\u0007\u001d\u001a%&\u0003\u0002E7\tA\u0011\n^3sCR|\'/A\u0004ti\u0016\u0004\b/\u001a:\u0016\u0005\u001dcEC\u0001%e%\rI5J\u0016\u0004\u0005\u0015\u0002\u0001\u0001J\u0001\u0007=e\u00164\u0017N\\3nK:$h\b\u0005\u0002,\u0019\u0012)Qj\u0001b\u0001\u001d\n\t1+\u0005\u00020\u001fB\u0012\u0001\u000b\u0016\t\u0004OE\u001b\u0016B\u0001*\u001c\u0005\u001d\u0019F/\u001a9qKJ\u0004\"a\u000b+\u0005\u0013Uc\u0015\u0011!A\u0001\u0006\u0003q#aA0%cA\u0011q+\u0019\b\u00031~s!!\u00170\u000f\u0005ikV\"A.\u000b\u0005q{\u0012A\u0002\u001fs_>$h(C\u0001\u001f\u0013\taR$\u0003\u0002a7\u000591\u000b^3qa\u0016\u0014\u0018B\u00012d\u00059)eMZ5dS\u0016tGo\u00159mSRT!\u0001Y\u000e\t\u000b\u0015\u001c\u00019\u00014\u0002\u000bMD\u0017\r]3\u0011\t\u001d:\'fS\u0005\u0003Qn\u0011Ab\u0015;faB,\'o\u00155ba\u0016\fqB]3wKJ\u001cX-\u0013;fe\u0006$xN]\u0001\nM>dGMU5hQR,\"\u0001\\8\u0015\u000554HC\u00018r!\tYs\u000eB\u0003q\u000b\t\u0007aFA\u0001C\u0011\u0015\u0011X\u00011\u0001t\u0003\ty\u0007\u000fE\u0003$i*rg.\u0003\u0002v;\tIa)\u001e8di&|gN\r\u0005\u0006o\u0016\u0001\rA\\\u0001\u0002u\u0006!a/[3x+\u0005Q\bcA\u0014|U%\u0011Ap\u0007\u0002\u000f\u0013:$W\r_3e\'\u0016\fh+[3x)\u0011Qh0a\u0002\t\r}<\u0001\u0019AA\u0001\u0003\u00111\'o\\7\u0011\u0007\r\n\u0019!C\u0002\u0002\u0006u\u00111!\u00138u\u0011\u001d\tIa\u0002a\u0001\u0003\u0003\tQ!\u001e8uS2D3bBA\u0007\u0003\'\t)\"!\u0007\u0002\u001cA\u00191%a\u0004\n\u0007\u0005EQD\u0001\u0006eKB\u0014XmY1uK\u0012\fq!\\3tg\u0006<W-\t\u0002\u0002\u0018\u0005QTk]3!]YLWm\u001e\u0018tY&\u001cW\r\u000b4s_6d\u0003%\u001e8uS2L\u0003%\u001b8ti\u0016\fG\rI8gA92\u0018.Z<)MJ|W\u000e\f\u0011v]RLG.K\u0001\u0006g&t7-Z\u0011\u0003\u0003;\taA\r\u00182g9\u0002\u0014\u0001\u0003:fm\u0016\u00148/\u001a3\u0016\u0005\u0005\r\u0002\u0003B\u0014\u0002&)J1!a\n\u001c\u0005!IE/\u001a:bE2,\u0017!\u00039sKB,g\u000eZ3e+\u0011\ti#a\r\u0015\t\u0005=\u0012q\u0007\t\u0005WM\n\t\u0004E\u0002,\u0003g!a\u0001]\u0005C\u0002\u0005U\u0012C\u0001\u0016#\u0011\u001d\tI$\u0003a\u0001\u0003c\tA!\u001a7f[\u0006!A/Y6f)\rA\u0014q\b\u0005\b\u0003\u0003R\u0001\u0019AA\u0001\u0003\u0005q\u0017!\u0003;bW\u0016\u0014\u0016n\u001a5u)\rA\u0014q\t\u0005\b\u0003\u0003Z\u0001\u0019AA\u0001\u0003\u0011!\'o\u001c9\u0015\u0007a\ni\u0005C\u0004\u0002B1\u0001\r!!\u0001\u0002\u0013\u0011\u0014x\u000e\u001d*jO\"$Hc\u0001\u001d\u0002T!9\u0011\u0011I\u0007A\u0002\u0005\u0005\u0011aA7baV!\u0011\u0011LA0)\u0011\tY&!\u0019\u0011\t-\u001a\u0014Q\f\t\u0004W\u0005}C!\u00029\u000f\u0005\u0004q\u0003bBA2\u001d\u0001\u0007\u0011QM\u0001\u0002MB11%a\u001a+\u0003;J1!!\u001b\u001e\u0005%1UO\\2uS>t\u0017\'A\u0004sKZ,\'o]3\u0016\u0003a\nQa\u001d7jG\u0016$R\u0001OA:\u0003kBaa \tA\u0002\u0005\u0005\u0001bBA\u0005!\u0001\u0007\u0011\u0011A\u0001\u0005Q\u0016\fG-F\u0001+\u0003)AW-\u00193PaRLwN\\\u000b\u0003\u0003\u007f\u0002BaIAAU%\u0019\u00111Q\u000f\u0003\r=\u0003H/[8o\u0003\u0011a\u0017m\u001d;\u0002\u001b1,gn\u001a;i\u0007>l\u0007/\u0019:f)\u0011\t\t!a#\t\u000f\u00055E\u00031\u0001\u0002\u0002\u0005\u0019A.\u001a8\u0002\u0013-twn\u001e8TSj,WCAA\u0001)\u0011\t\t!!&\t\u000f\u0005]e\u00031\u0001\u0002\u001a\u0006!A\u000f[1ua\u0011\tY*a(\u0011\u000b\u001d\n)#!(\u0011\u0007-\ny\nB\u0006\u0002\"\u0006U\u0015\u0011!A\u0001\u0006\u0003q#aA0%k\u000511/Z1sG\",B!a*\u0002LR!\u0011\u0011VAg)\u0011\tY+!/\u0011\t\u00055\u00161\u0017\b\u00041\u0006=\u0016bAAY7\u0005I1+Z1sG\"LgnZ\u0005\u0005\u0003k\u000b9L\u0001\u0007TK\u0006\u00148\r\u001b*fgVdGOC\u0002\u00022nAq!a/\u0018\u0001\b\ti,A\u0002pe\u0012\u0004b!a0\u0002F\u0006%WBAAa\u0015\r\t\u0019-H\u0001\u0005[\u0006$\b.\u0003\u0003\u0002H\u0006\u0005\'\u0001C(sI\u0016\u0014\u0018N\\4\u0011\u0007-\nY\r\u0002\u0004q/\t\u0007\u0011Q\u0007\u0005\b\u0003s9\u0002\u0019AAe+\u0011\t\t.a7\u0015\u0011\u0005M\u0017Q\\Ap\u0003C$B!a+\u0002V\"9\u00111\u0018\rA\u0004\u0005]\u0007CBA`\u0003\u000b\fI\u000eE\u0002,\u00037$a\u0001\u001d\rC\u0002\u0005U\u0002bBA\u001d1\u0001\u0007\u0011\u0011\u001c\u0005\u0007\u007fb\u0001\r!!\u0001\t\u000f\u0005\r\b\u00041\u0001\u0002\u0002\u0005\u0011Ao\\\u0001\rE&t\u0017M]=TK\u0006\u00148\r[\u000b\u0005\u0003S\f\u0019\u0010\u0006\u0005\u0002l\u0006U\u0018q_A})\u0011\tY+!<\t\u000f\u0005m\u0016\u0004q\u0001\u0002pB1\u0011qXAc\u0003c\u00042aKAz\t\u0019\u0001\u0018D1\u0001\u00026!9\u0011\u0011H\rA\u0002\u0005E\bBB@\u001a\u0001\u0004\t\t\u0001C\u0004\u0002df\u0001\r!!\u0001)\u0007e\ti\u0010\u0005\u0003\u0002\u0000\n\u0015QB\u0001B\u0001\u0015\r\u0011\u0019!H\u0001\u000bC:tw\u000e^1uS>t\u0017\u0002\u0002B\u0004\u0005\u0003\u0011q\u0001^1jYJ,7\r
   #12 = Utf8               scala/collection/IndexedSeqView$Drop
   #13 = Class              #12           // scala/collection/IndexedSeqView$Drop
   #14 = Utf8               scala/collection/IndexedSeqView
   #15 = Class              #14           // scala/collection/IndexedSeqView
   #16 = Utf8               Drop
   #17 = Utf8               scala/collection/IndexedSeqView$DropRight
   #18 = Class              #17           // scala/collection/IndexedSeqView$DropRight
   #19 = Utf8               DropRight
   #20 = Utf8               scala/collection/IndexedSeqView$Id
   #21 = Class              #20           // scala/collection/IndexedSeqView$Id
   #22 = Utf8               Id
   #23 = Utf8               scala/collection/IndexedSeqView$Map
   #24 = Class              #23           // scala/collection/IndexedSeqView$Map
   #25 = Utf8               Map
   #26 = Utf8               scala/collection/IndexedSeqView$Prepended
   #27 = Class              #26           // scala/collection/IndexedSeqView$Prepended
   #28 = Utf8               Prepended
   #29 = Utf8               scala/collection/IndexedSeqView$Reverse
   #30 = Class              #29           // scala/collection/IndexedSeqView$Reverse
   #31 = Utf8               Reverse
   #32 = Utf8               scala/collection/IndexedSeqView$Slice
   #33 = Class              #32           // scala/collection/IndexedSeqView$Slice
   #34 = Utf8               Slice
   #35 = Utf8               scala/collection/IndexedSeqView$Take
   #36 = Class              #35           // scala/collection/IndexedSeqView$Take
   #37 = Utf8               Take
   #38 = Utf8               scala/collection/IndexedSeqView$TakeRight
   #39 = Class              #38           // scala/collection/IndexedSeqView$TakeRight
   #40 = Utf8               TakeRight
   #41 = Utf8               scala/collection/Searching$Found
   #42 = Class              #41           // scala/collection/Searching$Found
   #43 = Utf8               scala/collection/Searching
   #44 = Class              #43           // scala/collection/Searching
   #45 = Utf8               Found
   #46 = Utf8               scala/collection/Searching$InsertionPoint
   #47 = Class              #46           // scala/collection/Searching$InsertionPoint
   #48 = Utf8               InsertionPoint
   #49 = Utf8               scala/collection/Searching$SearchResult
   #50 = Class              #49           // scala/collection/Searching$SearchResult
   #51 = Utf8               SearchResult
   #52 = Utf8               iterator$
   #53 = Utf8               (Lscala/collection/IndexedSeqOps;)Lscala/collection/Iterator;
   #54 = Utf8               $this
   #55 = Utf8               iterator
   #56 = Utf8               ()Lscala/collection/Iterator;
   #57 = NameAndType        #55:#56       // iterator:()Lscala/collection/Iterator;
   #58 = InterfaceMethodref #2.#57        // scala/collection/IndexedSeqOps.iterator:()Lscala/collection/Iterator;
   #59 = Utf8               Lscala/collection/IndexedSeqOps;
   #60 = Utf8               ()Lscala/collection/Iterator<TA;>;
   #61 = Utf8               view
   #62 = Utf8               ()Lscala/collection/IndexedSeqView;
   #63 = NameAndType        #61:#62       // view:()Lscala/collection/IndexedSeqView;
   #64 = InterfaceMethodref #2.#63        // scala/collection/IndexedSeqOps.view:()Lscala/collection/IndexedSeqView;
   #65 = InterfaceMethodref #15.#57       // scala/collection/IndexedSeqView.iterator:()Lscala/collection/Iterator;
   #66 = Utf8               this
   #67 = Utf8               stepper$
   #68 = Utf8               (Lscala/collection/IndexedSeqOps;Lscala/collection/StepperShape;)Lscala/collection/Stepper;
   #69 = Utf8               shape
   #70 = Utf8               stepper
   #71 = Utf8               (Lscala/collection/StepperShape;)Lscala/collection/Stepper;
   #72 = NameAndType        #70:#71       // stepper:(Lscala/collection/StepperShape;)Lscala/collection/Stepper;
   #73 = InterfaceMethodref #2.#72        // scala/collection/IndexedSeqOps.stepper:(Lscala/collection/StepperShape;)Lscala/collection/Stepper;
   #74 = Utf8               Lscala/collection/StepperShape;
   #75 = Utf8               <S::Lscala/collection/Stepper<*>;>(Lscala/collection/StepperShape<TA;TS;>;)TS;
   #76 = Utf8               scala/collection/StepperShape
   #77 = Class              #76           // scala/collection/StepperShape
   #78 = Utf8               ()I
   #79 = NameAndType        #69:#78       // shape:()I
   #80 = InterfaceMethodref #77.#79       // scala/collection/StepperShape.shape:()I
   #81 = Utf8               scala/collection/StepperShape$
   #82 = Class              #81           // scala/collection/StepperShape$
   #83 = Utf8               MODULE$
   #84 = Utf8               Lscala/collection/StepperShape$;
   #85 = NameAndType        #83:#84       // MODULE$:Lscala/collection/StepperShape$;
   #86 = Fieldref           #82.#85       // scala/collection/StepperShape$.MODULE$:Lscala/collection/StepperShape$;
   #87 = Utf8               IntShape
   #88 = NameAndType        #87:#78       // IntShape:()I
   #89 = Methodref          #82.#88       // scala/collection/StepperShape$.IntShape:()I
   #90 = Utf8               scala/collection/convert/impl/IntIndexedSeqStepper
   #91 = Class              #90           // scala/collection/convert/impl/IntIndexedSeqStepper
   #92 = Utf8               length
   #93 = NameAndType        #92:#78       // length:()I
   #94 = InterfaceMethodref #2.#93        // scala/collection/IndexedSeqOps.length:()I
   #95 = Utf8               <init>
   #96 = Utf8               (Lscala/collection/IndexedSeqOps;II)V
   #97 = NameAndType        #95:#96       // "<init>":(Lscala/collection/IndexedSeqOps;II)V
   #98 = Methodref          #91.#97       // scala/collection/convert/impl/IntIndexedSeqStepper."<init>":(Lscala/collection/IndexedSeqOps;II)V
   #99 = Utf8               LongShape
  #100 = NameAndType        #99:#78       // LongShape:()I
  #101 = Methodref          #82.#100      // scala/collection/StepperShape$.LongShape:()I
  #102 = Utf8               scala/collection/convert/impl/LongIndexedSeqStepper
  #103 = Class              #102          // scala/collection/convert/impl/LongIndexedSeqStepper
  #104 = Methodref          #103.#97      // scala/collection/convert/impl/LongIndexedSeqStepper."<init>":(Lscala/collection/IndexedSeqOps;II)V
  #105 = Utf8               DoubleShape
  #106 = NameAndType        #105:#78      // DoubleShape:()I
  #107 = Methodref          #82.#106      // scala/collection/StepperShape$.DoubleShape:()I
  #108 = Utf8               scala/collection/convert/impl/DoubleIndexedSeqStepper
  #109 = Class              #108          // scala/collection/convert/impl/DoubleIndexedSeqStepper
  #110 = Methodref          #109.#97      // scala/collection/convert/impl/DoubleIndexedSeqStepper."<init>":(Lscala/collection/IndexedSeqOps;II)V
  #111 = Utf8               scala/collection/convert/impl/AnyIndexedSeqStepper
  #112 = Class              #111          // scala/collection/convert/impl/AnyIndexedSeqStepper
  #113 = Methodref          #112.#97      // scala/collection/convert/impl/AnyIndexedSeqStepper."<init>":(Lscala/collection/IndexedSeqOps;II)V
  #114 = Utf8               parUnbox
  #115 = Utf8               (Lscala/collection/AnyStepper;)Lscala/collection/Stepper;
  #116 = NameAndType        #114:#115     // parUnbox:(Lscala/collection/AnyStepper;)Lscala/collection/Stepper;
  #117 = InterfaceMethodref #77.#116      // scala/collection/StepperShape.parUnbox:(Lscala/collection/AnyStepper;)Lscala/collection/Stepper;
  #118 = Utf8               scala/collection/Stepper
  #119 = Class              #118          // scala/collection/Stepper
  #120 = Utf8               reverseIterator$
  #121 = Utf8               reverseIterator
  #122 = NameAndType        #121:#56      // reverseIterator:()Lscala/collection/Iterator;
  #123 = InterfaceMethodref #2.#122       // scala/collection/IndexedSeqOps.reverseIterator:()Lscala/collection/Iterator;
  #124 = InterfaceMethodref #15.#122      // scala/collection/IndexedSeqView.reverseIterator:()Lscala/collection/Iterator;
  #125 = Utf8               foldRight$
  #126 = Utf8               (Lscala/collection/IndexedSeqOps;Ljava/lang/Object;Lscala/Function2;)Ljava/lang/Object;
  #127 = Utf8               z
  #128 = Utf8               op
  #129 = Utf8               foldRight
  #130 = Utf8               (Ljava/lang/Object;Lscala/Function2;)Ljava/lang/Object;
  #131 = NameAndType        #129:#130     // foldRight:(Ljava/lang/Object;Lscala/Function2;)Ljava/lang/Object;
  #132 = InterfaceMethodref #2.#131       // scala/collection/IndexedSeqOps.foldRight:(Ljava/lang/Object;Lscala/Function2;)Ljava/lang/Object;
  #133 = Utf8               Ljava/lang/Object;
  #134 = Utf8               Lscala/Function2;
  #135 = Utf8               <B$:Ljava/lang/Object;>(TB$;Lscala/Function2<TA;TB$;TB$;>;)TB$;
  #136 = Utf8               scala/collection/Iterator
  #137 = Class              #136          // scala/collection/Iterator
  #138 = Utf8               hasNext
  #139 = Utf8               ()Z
  #140 = NameAndType        #138:#139     // hasNext:()Z
  #141 = InterfaceMethodref #137.#140     // scala/collection/Iterator.hasNext:()Z
  #142 = Utf8               next
  #143 = Utf8               ()Ljava/lang/Object;
  #144 = NameAndType        #142:#143     // next:()Ljava/lang/Object;
  #145 = InterfaceMethodref #137.#144     // scala/collection/Iterator.next:()Ljava/lang/Object;
  #146 = Utf8               scala/Function2
  #147 = Class              #146          // scala/Function2
  #148 = Utf8               apply
  #149 = Utf8               (Ljava/lang/Object;Ljava/lang/Object;)Ljava/lang/Object;
  #150 = NameAndType        #148:#149     // apply:(Ljava/lang/Object;Ljava/lang/Object;)Ljava/lang/Object;
  #151 = InterfaceMethodref #147.#150     // scala/Function2.apply:(Ljava/lang/Object;Ljava/lang/Object;)Ljava/lang/Object;
  #152 = Utf8               it
  #153 = Utf8               Lscala/collection/Iterator;
  #154 = Utf8               b
  #155 = Utf8               view$
  #156 = Utf8               (Lscala/collection/IndexedSeqOps;)Lscala/collection/IndexedSeqView;
  #157 = Utf8               ()Lscala/collection/IndexedSeqView<TA;>;
  #158 = Utf8               (Lscala/collection/IndexedSeqOps;)V
  #159 = NameAndType        #95:#158      // "<init>":(Lscala/collection/IndexedSeqOps;)V
  #160 = Methodref          #21.#159      // scala/collection/IndexedSeqView$Id."<init>":(Lscala/collection/IndexedSeqOps;)V
  #161 = Utf8               (Lscala/collection/IndexedSeqOps;II)Lscala/collection/IndexedSeqView;
  #162 = Utf8               from
  #163 = Utf8               until
  #164 = Utf8               (II)Lscala/collection/IndexedSeqView;
  #165 = NameAndType        #61:#164      // view:(II)Lscala/collection/IndexedSeqView;
  #166 = InterfaceMethodref #2.#165       // scala/collection/IndexedSeqOps.view:(II)Lscala/collection/IndexedSeqView;
  #167 = Utf8               I
  #168 = Utf8               (II)Lscala/collection/IndexedSeqView<TA;>;
  #169 = Utf8               slice
  #170 = NameAndType        #169:#164     // slice:(II)Lscala/collection/IndexedSeqView;
  #171 = InterfaceMethodref #15.#170      // scala/collection/IndexedSeqView.slice:(II)Lscala/collection/IndexedSeqView;
  #172 = Utf8               reversed$
  #173 = Utf8               (Lscala/collection/IndexedSeqOps;)Lscala/collection/Iterable;
  #174 = Utf8               reversed
  #175 = Utf8               ()Lscala/collection/Iterable;
  #176 = NameAndType        #174:#175     // reversed:()Lscala/collection/Iterable;
  #177 = InterfaceMethodref #2.#176       // scala/collection/IndexedSeqOps.reversed:()Lscala/collection/Iterable;
  #178 = Utf8               ()Lscala/collection/Iterable<TA;>;
  #179 = Methodref          #30.#159      // scala/collection/IndexedSeqView$Reverse."<init>":(Lscala/collection/IndexedSeqOps;)V
  #180 = Utf8               prepended$
  #181 = Utf8               (Lscala/collection/IndexedSeqOps;Ljava/lang/Object;)Ljava/lang/Object;
  #182 = Utf8               elem
  #183 = Utf8               prepended
  #184 = Utf8               (Ljava/lang/Object;)Ljava/lang/Object;
  #185 = NameAndType        #183:#184     // prepended:(Ljava/lang/Object;)Ljava/lang/Object;
  #186 = InterfaceMethodref #2.#185       // scala/collection/IndexedSeqOps.prepended:(Ljava/lang/Object;)Ljava/lang/Object;
  #187 = Utf8               <B:Ljava/lang/Object;>(TB;)TCC;
  #188 = Utf8               iterableFactory
  #189 = Utf8               ()Lscala/collection/IterableFactory;
  #190 = NameAndType        #188:#189     // iterableFactory:()Lscala/collection/IterableFactory;
  #191 = InterfaceMethodref #2.#190       // scala/collection/IndexedSeqOps.iterableFactory:()Lscala/collection/IterableFactory;
  #192 = Utf8               (Ljava/lang/Object;Lscala/collection/IndexedSeqOps;)V
  #193 = NameAndType        #95:#192      // "<init>":(Ljava/lang/Object;Lscala/collection/IndexedSeqOps;)V
  #194 = Methodref          #27.#193      // scala/collection/IndexedSeqView$Prepended."<init>":(Ljava/lang/Object;Lscala/collection/IndexedSeqOps;)V
  #195 = Utf8               scala/collection/IterableFactory
  #196 = Class              #195          // scala/collection/IterableFactory
  #197 = Utf8               (Lscala/collection/IterableOnce;)Ljava/lang/Object;
  #198 = NameAndType        #162:#197     // from:(Lscala/collection/IterableOnce;)Ljava/lang/Object;
  #199 = InterfaceMethodref #196.#198     // scala/collection/IterableFactory.from:(Lscala/collection/IterableOnce;)Ljava/lang/Object;
  #200 = Utf8               take$
  #201 = Utf8               (Lscala/collection/IndexedSeqOps;I)Ljava/lang/Object;
  #202 = Utf8               n
  #203 = Utf8               take
  #204 = Utf8               (I)Ljava/lang/Object;
  #205 = NameAndType        #203:#204     // take:(I)Ljava/lang/Object;
  #206 = InterfaceMethodref #2.#205       // scala/collection/IndexedSeqOps.take:(I)Ljava/lang/Object;
  #207 = Utf8               (I)TC;
  #208 = Utf8               (Lscala/collection/IndexedSeqOps;I)V
  #209 = NameAndType        #95:#208      // "<init>":(Lscala/collection/IndexedSeqOps;I)V
  #210 = Methodref          #36.#209      // scala/collection/IndexedSeqView$Take."<init>":(Lscala/collection/IndexedSeqOps;I)V
  #211 = Utf8               fromSpecific
  #212 = NameAndType        #211:#197     // fromSpecific:(Lscala/collection/IterableOnce;)Ljava/lang/Object;
  #213 = InterfaceMethodref #2.#212       // scala/collection/IndexedSeqOps.fromSpecific:(Lscala/collection/IterableOnce;)Ljava/lang/Object;
  #214 = Utf8               takeRight$
  #215 = Utf8               takeRight
  #216 = NameAndType        #215:#204     // takeRight:(I)Ljava/lang/Object;
  #217 = InterfaceMethodref #2.#216       // scala/collection/IndexedSeqOps.takeRight:(I)Ljava/lang/Object;
  #218 = Methodref          #39.#209      // scala/collection/IndexedSeqView$TakeRight."<init>":(Lscala/collection/IndexedSeqOps;I)V
  #219 = Utf8               drop$
  #220 = Utf8               drop
  #221 = NameAndType        #220:#204     // drop:(I)Ljava/lang/Object;
  #222 = InterfaceMethodref #2.#221       // scala/collection/IndexedSeqOps.drop:(I)Ljava/lang/Object;
  #223 = Methodref          #13.#209      // scala/collection/IndexedSeqView$Drop."<init>":(Lscala/collection/IndexedSeqOps;I)V
  #224 = Utf8               dropRight$
  #225 = Utf8               dropRight
  #226 = NameAndType        #225:#204     // dropRight:(I)Ljava/lang/Object;
  #227 = InterfaceMethodref #2.#226       // scala/collection/IndexedSeqOps.dropRight:(I)Ljava/lang/Object;
  #228 = Methodref          #18.#209      // scala/collection/IndexedSeqView$DropRight."<init>":(Lscala/collection/IndexedSeqOps;I)V
  #229 = Utf8               map$
  #230 = Utf8               (Lscala/collection/IndexedSeqOps;Lscala/Function1;)Ljava/lang/Object;
  #231 = Utf8               f
  #232 = Utf8               map
  #233 = Utf8               (Lscala/Function1;)Ljava/lang/Object;
  #234 = NameAndType        #232:#233     // map:(Lscala/Function1;)Ljava/lang/Object;
  #235 = InterfaceMethodref #2.#234       // scala/collection/IndexedSeqOps.map:(Lscala/Function1;)Ljava/lang/Object;
  #236 = Utf8               Lscala/Function1;
  #237 = Utf8               <B:Ljava/lang/Object;>(Lscala/Function1<TA;TB;>;)TCC;
  #238 = Utf8               (Lscala/collection/IndexedSeqOps;Lscala/Function1;)V
  #239 = NameAndType        #95:#238      // "<init>":(Lscala/collection/IndexedSeqOps;Lscala/Function1;)V
  #240 = Methodref          #24.#239      // scala/collection/IndexedSeqView$Map."<init>":(Lscala/collection/IndexedSeqOps;Lscala/Function1;)V
  #241 = Utf8               reverse$
  #242 = Utf8               (Lscala/collection/IndexedSeqOps;)Ljava/lang/Object;
  #243 = Utf8               reverse
  #244 = NameAndType        #243:#143     // reverse:()Ljava/lang/Object;
  #245 = InterfaceMethodref #2.#244       // scala/collection/IndexedSeqOps.reverse:()Ljava/lang/Object;
  #246 = Utf8               ()TC;
  #247 = Utf8               slice$
  #248 = Utf8               (Lscala/collection/IndexedSeqOps;II)Ljava/lang/Object;
  #249 = Utf8               (II)Ljava/lang/Object;
  #250 = NameAndType        #169:#249     // slice:(II)Ljava/lang/Object;
  #251 = InterfaceMethodref #2.#250       // scala/collection/IndexedSeqOps.slice:(II)Ljava/lang/Object;
  #252 = Utf8               (II)TC;
  #253 = Methodref          #33.#97       // scala/collection/IndexedSeqView$Slice."<init>":(Lscala/collection/IndexedSeqOps;II)V
  #254 = Utf8               head$
  #255 = Utf8               head
  #256 = NameAndType        #255:#143     // head:()Ljava/lang/Object;
  #257 = InterfaceMethodref #2.#256       // scala/collection/IndexedSeqOps.head:()Ljava/lang/Object;
  #258 = Utf8               ()TA;
  #259 = NameAndType        #148:#204     // apply:(I)Ljava/lang/Object;
  #260 = InterfaceMethodref #2.#259       // scala/collection/IndexedSeqOps.apply:(I)Ljava/lang/Object;
  #261 = Utf8               headOption$
  #262 = Utf8               (Lscala/collection/IndexedSeqOps;)Lscala/Option;
  #263 = Utf8               headOption
  #264 = Utf8               ()Lscala/Option;
  #265 = NameAndType        #263:#264     // headOption:()Lscala/Option;
  #266 = InterfaceMethodref #2.#265       // scala/collection/IndexedSeqOps.headOption:()Lscala/Option;
  #267 = Utf8               ()Lscala/Option<TA;>;
  #268 = Utf8               isEmpty
  #269 = NameAndType        #268:#139     // isEmpty:()Z
  #270 = InterfaceMethodref #2.#269       // scala/collection/IndexedSeqOps.isEmpty:()Z
  #271 = Utf8               scala/None$
  #272 = Class              #271          // scala/None$
  #273 = Utf8               Lscala/None$;
  #274 = NameAndType        #83:#273      // MODULE$:Lscala/None$;
  #275 = Fieldref           #272.#274     // scala/None$.MODULE$:Lscala/None$;
  #276 = Utf8               scala/Some
  #277 = Class              #276          // scala/Some
  #278 = Utf8               (Ljava/lang/Object;)V
  #279 = NameAndType        #95:#278      // "<init>":(Ljava/lang/Object;)V
  #280 = Methodref          #277.#279     // scala/Some."<init>":(Ljava/lang/Object;)V
  #281 = Utf8               last$
  #282 = Utf8               last
  #283 = NameAndType        #282:#143     // last:()Ljava/lang/Object;
  #284 = InterfaceMethodref #2.#283       // scala/collection/IndexedSeqOps.last:()Ljava/lang/Object;
  #285 = Utf8               lengthCompare$
  #286 = Utf8               (Lscala/collection/IndexedSeqOps;I)I
  #287 = Utf8               len
  #288 = Utf8               lengthCompare
  #289 = Utf8               (I)I
  #290 = NameAndType        #288:#289     // lengthCompare:(I)I
  #291 = InterfaceMethodref #2.#290       // scala/collection/IndexedSeqOps.lengthCompare:(I)I
  #292 = Utf8               java/lang/Integer
  #293 = Class              #292          // java/lang/Integer
  #294 = Utf8               compare
  #295 = Utf8               (II)I
  #296 = NameAndType        #294:#295     // compare:(II)I
  #297 = Methodref          #293.#296     // java/lang/Integer.compare:(II)I
  #298 = Utf8               knownSize$
  #299 = Utf8               (Lscala/collection/IndexedSeqOps;)I
  #300 = Utf8               knownSize
  #301 = NameAndType        #300:#78      // knownSize:()I
  #302 = InterfaceMethodref #2.#301       // scala/collection/IndexedSeqOps.knownSize:()I
  #303 = Utf8               (Lscala/collection/IndexedSeqOps;Lscala/collection/Iterable;)I
  #304 = Utf8               that
  #305 = Utf8               (Lscala/collection/Iterable;)I
  #306 = NameAndType        #288:#305     // lengthCompare:(Lscala/collection/Iterable;)I
  #307 = InterfaceMethodref #2.#306       // scala/collection/IndexedSeqOps.lengthCompare:(Lscala/collection/Iterable;)I
  #308 = Utf8               Lscala/collection/Iterable;
  #309 = Utf8               (Lscala/collection/Iterable<*>;)I
  #310 = Utf8               scala/collection/Iterable
  #311 = Class              #310          // scala/collection/Iterable
  #312 = Utf8               sizeCompare
  #313 = NameAndType        #312:#289     // sizeCompare:(I)I
  #314 = InterfaceMethodref #311.#313     // scala/collection/Iterable.sizeCompare:(I)I
  #315 = Integer            -2147483648
  #316 = Utf8               res
  #317 = Utf8               search$
  #318 = Utf8               (Lscala/collection/IndexedSeqOps;Ljava/lang/Object;Lscala/math/Ordering;)Lscala/collection/Searching$SearchResult;
  #319 = Utf8               ord
  #320 = Utf8               search
  #321 = Utf8               (Ljava/lang/Object;Lscala/math/Ordering;)Lscala/collection/Searching$SearchResult;
  #322 = NameAndType        #320:#321     // search:(Ljava/lang/Object;Lscala/math/Ordering;)Lscala/collection/Searching$SearchResult;
  #323 = InterfaceMethodref #2.#322       // scala/collection/IndexedSeqOps.search:(Ljava/lang/Object;Lscala/math/Ordering;)Lscala/collection/Searching$SearchResult;
  #324 = Utf8               Lscala/math/Ordering;
  #325 = Utf8               <B:Ljava/lang/Object;>(TB;Lscala/math/Ordering<TB;>;)Lscala/collection/Searching$SearchResult;
  #326 = Utf8               binarySearch
  #327 = Utf8               (Ljava/lang/Object;IILscala/math/Ordering;)Lscala/collection/Searching$SearchResult;
  #328 = NameAndType        #326:#327     // binarySearch:(Ljava/lang/Object;IILscala/math/Ordering;)Lscala/collection/Searching$SearchResult;
  #329 = InterfaceMethodref #2.#328       // scala/collection/IndexedSeqOps.binarySearch:(Ljava/lang/Object;IILscala/math/Ordering;)Lscala/collection/Searching$SearchResult;
  #330 = Utf8               (Lscala/collection/IndexedSeqOps;Ljava/lang/Object;IILscala/math/Ordering;)Lscala/collection/Searching$SearchResult;
  #331 = Utf8               to
  #332 = NameAndType        #320:#327     // search:(Ljava/lang/Object;IILscala/math/Ordering;)Lscala/collection/Searching$SearchResult;
  #333 = InterfaceMethodref #2.#332       // scala/collection/IndexedSeqOps.search:(Ljava/lang/Object;IILscala/math/Ordering;)Lscala/collection/Searching$SearchResult;
  #334 = Utf8               <B:Ljava/lang/Object;>(TB;IILscala/math/Ordering<TB;>;)Lscala/collection/Searching$SearchResult;
  #335 = Utf8               (I)V
  #336 = NameAndType        #95:#335      // "<init>":(I)V
  #337 = Methodref          #47.#336      // scala/collection/Searching$InsertionPoint."<init>":(I)V
  #338 = Utf8               scala/math/package$
  #339 = Class              #338          // scala/math/package$
  #340 = Utf8               Lscala/math/package$;
  #341 = NameAndType        #83:#340      // MODULE$:Lscala/math/package$;
  #342 = Fieldref           #339.#341     // scala/math/package$.MODULE$:Lscala/math/package$;
  #343 = Utf8               scala/math/Ordering
  #344 = Class              #343          // scala/math/Ordering
  #345 = Utf8               (Ljava/lang/Object;Ljava/lang/Object;)I
  #346 = NameAndType        #294:#345     // compare:(Ljava/lang/Object;Ljava/lang/Object;)I
  #347 = InterfaceMethodref #344.#346     // scala/math/Ordering.compare:(Ljava/lang/Object;Ljava/lang/Object;)I
  #348 = Utf8               signum
  #349 = NameAndType        #348:#289     // signum:(I)I
  #350 = Methodref          #293.#349     // java/lang/Integer.signum:(I)I
  #351 = Methodref          #42.#336      // scala/collection/Searching$Found."<init>":(I)V
  #352 = Utf8               idx
  #353 = Utf8               $init$
  #354 = Utf8               Code
  #355 = Utf8               LineNumberTable
  #356 = Utf8               LocalVariableTable
  #357 = Utf8               MethodParameters
  #358 = Utf8               Signature
  #359 = Utf8               StackMapTable
  #360 = Utf8               Deprecated
  #361 = Utf8               InnerClasses
  #362 = Utf8               SourceFile
  #363 = Utf8               RuntimeVisibleAnnotations
  #364 = Utf8               ScalaInlineInfo
  #365 = Utf8               ScalaSig
{
  public static scala.collection.Iterator iterator$(scala.collection.IndexedSeqOps);
    descriptor: (Lscala/collection/IndexedSeqOps;)Lscala/collection/Iterator;
    flags: (0x1009) ACC_PUBLIC, ACC_STATIC, ACC_SYNTHETIC
    Code:
      stack=1, locals=1, args_size=1
         0: aload_0
         1: invokespecial #58                 // InterfaceMethod iterator:()Lscala/collection/Iterator;
         4: areturn
      LineNumberTable:
        line 37: 0
      LocalVariableTable:
        Start  Length  Slot  Name   Signature
            0       5     0 $this   Lscala/collection/IndexedSeqOps;
    MethodParameters:
      Name                           Flags
      $this                          final synthetic

  public default scala.collection.Iterator<A> iterator();
    descriptor: ()Lscala/collection/Iterator;
    flags: (0x0001) ACC_PUBLIC
    Code:
      stack=1, locals=1, args_size=1
         0: aload_0
         1: invokeinterface #64,  1           // InterfaceMethod view:()Lscala/collection/IndexedSeqView;
         6: invokeinterface #65,  1           // InterfaceMethod scala/collection/IndexedSeqView.iterator:()Lscala/collection/Iterator;
        11: areturn
      LineNumberTable:
        line 37: 0
      LocalVariableTable:
        Start  Length  Slot  Name   Signature
            0      12     0  this   Lscala/collection/IndexedSeqOps;
    Signature: #60                          // ()Lscala/collection/Iterator<TA;>;

  public static scala.collection.Stepper stepper$(scala.collection.IndexedSeqOps, scala.collection.StepperShape);
    descriptor: (Lscala/collection/IndexedSeqOps;Lscala/collection/StepperShape;)Lscala/collection/Stepper;
    flags: (0x1009) ACC_PUBLIC, ACC_STATIC, ACC_SYNTHETIC
    Code:
      stack=2, locals=2, args_size=2
         0: aload_0
         1: aload_1
         2: invokespecial #73                 // InterfaceMethod stepper:(Lscala/collection/StepperShape;)Lscala/collection/Stepper;
         5: areturn
      LineNumberTable:
        line 39: 0
      LocalVariableTable:
        Start  Length  Slot  Name   Signature
            0       6     0 $this   Lscala/collection/IndexedSeqOps;
            0       6     1 shape   Lscala/collection/StepperShape;
    MethodParameters:
      Name                           Flags
      $this                          final synthetic
      shape                          final

  public default <S extends scala.collection.Stepper<?>> S stepper(scala.collection.StepperShape<A, S>);
    descriptor: (Lscala/collection/StepperShape;)Lscala/collection/Stepper;
    flags: (0x0001) ACC_PUBLIC
    Code:
      stack=6, locals=4, args_size=2
         0: aload_1
         1: invokeinterface #80,  1           // InterfaceMethod scala/collection/StepperShape.shape:()I
         6: istore_3
         7: getstatic     #86                 // Field scala/collection/StepperShape$.MODULE$:Lscala/collection/StepperShape$;
        10: invokevirtual #89                 // Method scala/collection/StepperShape$.IntShape:()I
        13: iload_3
        14: if_icmpne     36
        17: new           #91                 // class scala/collection/convert/impl/IntIndexedSeqStepper
        20: dup
        21: aload_0
        22: iconst_0
        23: aload_0
        24: invokeinterface #94,  1           // InterfaceMethod length:()I
        29: invokespecial #98                 // Method scala/collection/convert/impl/IntIndexedSeqStepper."<init>":(Lscala/collection/IndexedSeqOps;II)V
        32: astore_2
        33: goto          116
        36: getstatic     #86                 // Field scala/collection/StepperShape$.MODULE$:Lscala/collection/StepperShape$;
        39: invokevirtual #101                // Method scala/collection/StepperShape$.LongShape:()I
        42: iload_3
        43: if_icmpne     65
        46: new           #103                // class scala/collection/convert/impl/LongIndexedSeqStepper
        49: dup
        50: aload_0
        51: iconst_0
        52: aload_0
        53: invokeinterface #94,  1           // InterfaceMethod length:()I
        58: invokespecial #104                // Method scala/collection/convert/impl/LongIndexedSeqStepper."<init>":(Lscala/collection/IndexedSeqOps;II)V
        61: astore_2
        62: goto          116
        65: getstatic     #86                 // Field scala/collection/StepperShape$.MODULE$:Lscala/collection/StepperShape$;
        68: invokevirtual #107                // Method scala/collection/StepperShape$.DoubleShape:()I
        71: iload_3
        72: if_icmpne     94
        75: new           #109                // class scala/collection/convert/impl/DoubleIndexedSeqStepper
        78: dup
        79: aload_0
        80: iconst_0
        81: aload_0
        82: invokeinterface #94,  1           // InterfaceMethod length:()I
        87: invokespecial #110                // Method scala/collection/convert/impl/DoubleIndexedSeqStepper."<init>":(Lscala/collection/IndexedSeqOps;II)V
        90: astore_2
        91: goto          116
        94: aload_1
        95: new           #112                // class scala/collection/convert/impl/AnyIndexedSeqStepper
        98: dup
        99: aload_0
       100: iconst_0
       101: aload_0
       102: invokeinterface #94,  1           // InterfaceMethod length:()I
       107: invokespecial #113                // Method scala/collection/convert/impl/AnyIndexedSeqStepper."<init>":(Lscala/collection/IndexedSeqOps;II)V
       110: invokeinterface #117,  2          // InterfaceMethod scala/collection/StepperShape.parUnbox:(Lscala/collection/AnyStepper;)Lscala/collection/Stepper;
       115: astore_2
       116: aload_2
       117: areturn
      StackMapTable: number_of_entries = 4
        frame_type = 253 /* append */
          offset_delta = 36
          locals = [ top, int ]
        frame_type = 28 /* same */
        frame_type = 28 /* same */
        frame_type = 255 /* full_frame */
          offset_delta = 21
          locals = [ class scala/collection/IndexedSeqOps, class scala/collection/StepperShape, class scala/collection/Stepper, int ]
          stack = []
      LineNumberTable:
        line 41: 0
        line 42: 7
        line 43: 36
        line 44: 65
        line 45: 94
        line 47: 116
      LocalVariableTable:
        Start  Length  Slot  Name   Signature
            0     118     0  this   Lscala/collection/IndexedSeqOps;
            0     118     1 shape   Lscala/collection/StepperShape;
    Signature: #75                          // <S::Lscala/collection/Stepper<*>;>(Lscala/collection/StepperShape<TA;TS;>;)TS;
    MethodParameters:
      Name                           Flags
      shape                          final

  public static scala.collection.Iterator reverseIterator$(scala.collection.IndexedSeqOps);
    descriptor: (Lscala/collection/IndexedSeqOps;)Lscala/collection/Iterator;
    flags: (0x1009) ACC_PUBLIC, ACC_STATIC, ACC_SYNTHETIC
    Code:
      stack=1, locals=1, args_size=1
         0: aload_0
         1: invokespecial #123                // InterfaceMethod reverseIterator:()Lscala/collection/Iterator;
         4: areturn
      LineNumberTable:
        line 50: 0
      LocalVariableTable:
        Start  Length  Slot  Name   Signature
            0       5     0 $this   Lscala/collection/IndexedSeqOps;
    MethodParameters:
      Name                           Flags
      $this                          final synthetic

  public default scala.collection.Iterator<A> reverseIterator();
    descriptor: ()Lscala/collection/Iterator;
    flags: (0x0001) ACC_PUBLIC
    Code:
      stack=1, locals=1, args_size=1
         0: aload_0
         1: invokeinterface #64,  1           // InterfaceMethod view:()Lscala/collection/IndexedSeqView;
         6: invokeinterface #124,  1          // InterfaceMethod scala/collection/IndexedSeqView.reverseIterator:()Lscala/collection/Iterator;
        11: areturn
      LineNumberTable:
        line 50: 0
      LocalVariableTable:
        Start  Length  Slot  Name   Signature
            0      12     0  this   Lscala/collection/IndexedSeqOps;
    Signature: #60                          // ()Lscala/collection/Iterator<TA;>;

  public static java.lang.Object foldRight$(scala.collection.IndexedSeqOps, java.lang.Object, scala.Function2);
    descriptor: (Lscala/collection/IndexedSeqOps;Ljava/lang/Object;Lscala/Function2;)Ljava/lang/Object;
    flags: (0x1009) ACC_PUBLIC, ACC_STATIC, ACC_SYNTHETIC
    Code:
      stack=3, locals=3, args_size=3
         0: aload_0
         1: aload_1
         2: aload_2
         3: invokespecial #132                // InterfaceMethod foldRight:(Ljava/lang/Object;Lscala/Function2;)Ljava/lang/Object;
         6: areturn
      LineNumberTable:
        line 52: 0
      LocalVariableTable:
        Start  Length  Slot  Name   Signature
            0       7     0 $this   Lscala/collection/IndexedSeqOps;
            0       7     1     z   Ljava/lang/Object;
            0       7     2    op   Lscala/Function2;
    MethodParameters:
      Name                           Flags
      $this                          final synthetic
      z                              final
      op                             final

  public default <B$ extends java.lang.Object> B$ foldRight(B$, scala.Function2<A, B$, B$>);
    descriptor: (Ljava/lang/Object;Lscala/Function2;)Ljava/lang/Object;
    flags: (0x0001) ACC_PUBLIC
    Code:
      stack=3, locals=5, args_size=3
         0: aload_0
         1: invokeinterface #123,  1          // InterfaceMethod reverseIterator:()Lscala/collection/Iterator;
         6: astore_3
         7: aload_1
         8: astore        4
        10: aload_3
        11: invokeinterface #141,  1          // InterfaceMethod scala/collection/Iterator.hasNext:()Z
        16: ifeq          38
        19: aload_2
        20: aload_3
        21: invokeinterface #145,  1          // InterfaceMethod scala/collection/Iterator.next:()Ljava/lang/Object;
        26: aload         4
        28: invokeinterface #151,  3          // InterfaceMethod scala/Function2.apply:(Ljava/lang/Object;Ljava/lang/Object;)Ljava/lang/Object;
        33: astore        4
        35: goto          10
        38: aload         4
        40: areturn
      StackMapTable: number_of_entries = 2
        frame_type = 253 /* append */
          offset_delta = 10
          locals = [ class scala/collection/Iterator, class java/lang/Object ]
        frame_type = 27 /* same */
      LineNumberTable:
        line 53: 0
        line 54: 7
        line 55: 10
        line 56: 19
        line 57: 38
      LocalVariableTable:
        Start  Length  Slot  Name   Signature
            7      33     3    it   Lscala/collection/Iterator;
           10      30     4     b   Ljava/lang/Object;
            0      41     0  this   Lscala/collection/IndexedSeqOps;
            0      41     1     z   Ljava/lang/Object;
            0      41     2    op   Lscala/Function2;
    Signature: #135                         // <B$:Ljava/lang/Object;>(TB$;Lscala/Function2<TA;TB$;TB$;>;)TB$;
    MethodParameters:
      Name                           Flags
      z                              final
      op                             final

  public static scala.collection.IndexedSeqView view$(scala.collection.IndexedSeqOps);
    descriptor: (Lscala/collection/IndexedSeqOps;)Lscala/collection/IndexedSeqView;
    flags: (0x1009) ACC_PUBLIC, ACC_STATIC, ACC_SYNTHETIC
    Code:
      stack=1, locals=1, args_size=1
         0: aload_0
         1: invokespecial #64                 // InterfaceMethod view:()Lscala/collection/IndexedSeqView;
         4: areturn
      LineNumberTable:
        line 60: 0
      LocalVariableTable:
        Start  Length  Slot  Name   Signature
            0       5     0 $this   Lscala/collection/IndexedSeqOps;
    MethodParameters:
      Name                           Flags
      $this                          final synthetic

  public default scala.collection.IndexedSeqView<A> view();
    descriptor: ()Lscala/collection/IndexedSeqView;
    flags: (0x0001) ACC_PUBLIC
    Code:
      stack=3, locals=1, args_size=1
         0: new           #21                 // class scala/collection/IndexedSeqView$Id
         3: dup
         4: aload_0
         5: invokespecial #160                // Method scala/collection/IndexedSeqView$Id."<init>":(Lscala/collection/IndexedSeqOps;)V
         8: areturn
      LineNumberTable:
        line 60: 0
      LocalVariableTable:
        Start  Length  Slot  Name   Signature
            0       9     0  this   Lscala/collection/IndexedSeqOps;
    Signature: #157                         // ()Lscala/collection/IndexedSeqView<TA;>;

  public static scala.collection.IndexedSeqView view$(scala.collection.IndexedSeqOps, int, int);
    descriptor: (Lscala/collection/IndexedSeqOps;II)Lscala/collection/IndexedSeqView;
    flags: (0x1009) ACC_PUBLIC, ACC_STATIC, ACC_SYNTHETIC
    Code:
      stack=3, locals=3, args_size=3
         0: aload_0
         1: iload_1
         2: iload_2
         3: invokespecial #166                // InterfaceMethod view:(II)Lscala/collection/IndexedSeqView;
         6: areturn
      LineNumberTable:
        line 63: 0
      LocalVariableTable:
        Start  Length  Slot  Name   Signature
            0       7     0 $this   Lscala/collection/IndexedSeqOps;
            0       7     1  from   I
            0       7     2 until   I
    MethodParameters:
      Name                           Flags
      $this                          final synthetic
      from                           final
      until                          final

  public default scala.collection.IndexedSeqView<A> view(int, int);
    descriptor: (II)Lscala/collection/IndexedSeqView;
    flags: (0x0001) ACC_PUBLIC
    Code:
      stack=3, locals=3, args_size=3
         0: aload_0
         1: invokeinterface #64,  1           // InterfaceMethod view:()Lscala/collection/IndexedSeqView;
         6: iload_1
         7: iload_2
         8: invokeinterface #171,  3          // InterfaceMethod scala/collection/IndexedSeqView.slice:(II)Lscala/collection/IndexedSeqView;
        13: areturn
      LineNumberTable:
        line 63: 0
      LocalVariableTable:
        Start  Length  Slot  Name   Signature
            0      14     0  this   Lscala/collection/IndexedSeqOps;
            0      14     1  from   I
            0      14     2 until   I
    Signature: #168                         // (II)Lscala/collection/IndexedSeqView<TA;>;
    Deprecated: true
    MethodParameters:
      Name                           Flags
      from                           final
      until                          final

  public static scala.collection.Iterable reversed$(scala.collection.IndexedSeqOps);
    descriptor: (Lscala/collection/IndexedSeqOps;)Lscala/collection/Iterable;
    flags: (0x1009) ACC_PUBLIC, ACC_STATIC, ACC_SYNTHETIC
    Code:
      stack=1, locals=1, args_size=1
         0: aload_0
         1: invokespecial #177                // InterfaceMethod reversed:()Lscala/collection/Iterable;
         4: areturn
      LineNumberTable:
        line 65: 0
      LocalVariableTable:
        Start  Length  Slot  Name   Signature
            0       5     0 $this   Lscala/collection/IndexedSeqOps;
    MethodParameters:
      Name                           Flags
      $this                          final synthetic

  public default scala.collection.Iterable<A> reversed();
    descriptor: ()Lscala/collection/Iterable;
    flags: (0x0001) ACC_PUBLIC
    Code:
      stack=3, locals=1, args_size=1
         0: new           #30                 // class scala/collection/IndexedSeqView$Reverse
         3: dup
         4: aload_0
         5: invokespecial #179                // Method scala/collection/IndexedSeqView$Reverse."<init>":(Lscala/collection/IndexedSeqOps;)V
         8: areturn
      LineNumberTable:
        line 65: 0
      LocalVariableTable:
        Start  Length  Slot  Name   Signature
            0       9     0  this   Lscala/collection/IndexedSeqOps;
    Signature: #178                         // ()Lscala/collection/Iterable<TA;>;

  public static java.lang.Object prepended$(scala.collection.IndexedSeqOps, java.lang.Object);
    descriptor: (Lscala/collection/IndexedSeqOps;Ljava/lang/Object;)Ljava/lang/Object;
    flags: (0x1009) ACC_PUBLIC, ACC_STATIC, ACC_SYNTHETIC
    Code:
      stack=2, locals=2, args_size=2
         0: aload_0
         1: aload_1
         2: invokespecial #186                // InterfaceMethod prepended:(Ljava/lang/Object;)Ljava/lang/Object;
         5: areturn
      LineNumberTable:
        line 68: 0
      LocalVariableTable:
        Start  Length  Slot  Name   Signature
            0       6     0 $this   Lscala/collection/IndexedSeqOps;
            0       6     1  elem   Ljava/lang/Object;
    MethodParameters:
      Name                           Flags
      $this                          final synthetic
      elem                           final

  public default <B extends java.lang.Object> CC prepended(B);
    descriptor: (Ljava/lang/Object;)Ljava/lang/Object;
    flags: (0x0001) ACC_PUBLIC
    Code:
      stack=5, locals=2, args_size=2
         0: aload_0
         1: invokeinterface #191,  1          // InterfaceMethod iterableFactory:()Lscala/collection/IterableFactory;
         6: new           #27                 // class scala/collection/IndexedSeqView$Prepended
         9: dup
        10: aload_1
        11: aload_0
        12: invokespecial #194                // Method scala/collection/IndexedSeqView$Prepended."<init>":(Ljava/lang/Object;Lscala/collection/IndexedSeqOps;)V
        15: invokeinterface #199,  2          // InterfaceMethod scala/collection/IterableFactory.from:(Lscala/collection/IterableOnce;)Ljava/lang/Object;
        20: areturn
      LineNumberTable:
        line 68: 0
      LocalVariableTable:
        Start  Length  Slot  Name   Signature
            0      21     0  this   Lscala/collection/IndexedSeqOps;
            0      21     1  elem   Ljava/lang/Object;
    Signature: #187                         // <B:Ljava/lang/Object;>(TB;)TCC;
    MethodParameters:
      Name                           Flags
      elem                           final

  public static java.lang.Object take$(scala.collection.IndexedSeqOps, int);
    descriptor: (Lscala/collection/IndexedSeqOps;I)Ljava/lang/Object;
    flags: (0x1009) ACC_PUBLIC, ACC_STATIC, ACC_SYNTHETIC
    Code:
      stack=2, locals=2, args_size=2
         0: aload_0
         1: iload_1
         2: invokespecial #206                // InterfaceMethod take:(I)Ljava/lang/Object;
         5: areturn
      LineNumberTable:
        line 70: 0
      LocalVariableTable:
        Start  Length  Slot  Name   Signature
            0       6     0 $this   Lscala/collection/IndexedSeqOps;
            0       6     1     n   I
    MethodParameters:
      Name                           Flags
      $this                          final synthetic
      n                              final

  public default C take(int);
    descriptor: (I)Ljava/lang/Object;
    flags: (0x0001) ACC_PUBLIC
    Code:
      stack=5, locals=2, args_size=2
         0: aload_0
         1: new           #36                 // class scala/collection/IndexedSeqView$Take
         4: dup
         5: aload_0
         6: iload_1
         7: invokespecial #210                // Method scala/collection/IndexedSeqView$Take."<init>":(Lscala/collection/IndexedSeqOps;I)V
        10: invokeinterface #213,  2          // InterfaceMethod fromSpecific:(Lscala/collection/IterableOnce;)Ljava/lang/Object;
        15: areturn
      LineNumberTable:
        line 70: 0
      LocalVariableTable:
        Start  Length  Slot  Name   Signature
            0      16     0  this   Lscala/collection/IndexedSeqOps;
            0      16     1     n   I
    Signature: #207                         // (I)TC;
    MethodParameters:
      Name                           Flags
      n                              final

  public static java.lang.Object takeRight$(scala.collection.IndexedSeqOps, int);
    descriptor: (Lscala/collection/IndexedSeqOps;I)Ljava/lang/Object;
    flags: (0x1009) ACC_PUBLIC, ACC_STATIC, ACC_SYNTHETIC
    Code:
      stack=2, locals=2, args_size=2
         0: aload_0
         1: iload_1
         2: invokespecial #217                // InterfaceMethod takeRight:(I)Ljava/lang/Object;
         5: areturn
      LineNumberTable:
        line 72: 0
      LocalVariableTable:
        Start  Length  Slot  Name   Signature
            0       6     0 $this   Lscala/collection/IndexedSeqOps;
            0       6     1     n   I
    MethodParameters:
      Name                           Flags
      $this                          final synthetic
      n                              final

  public default C takeRight(int);
    descriptor: (I)Ljava/lang/Object;
    flags: (0x0001) ACC_PUBLIC
    Code:
      stack=5, locals=2, args_size=2
         0: aload_0
         1: new           #39                 // class scala/collection/IndexedSeqView$TakeRight
         4: dup
         5: aload_0
         6: iload_1
         7: invokespecial #218                // Method scala/collection/IndexedSeqView$TakeRight."<init>":(Lscala/collection/IndexedSeqOps;I)V
        10: invokeinterface #213,  2          // InterfaceMethod fromSpecific:(Lscala/collection/IterableOnce;)Ljava/lang/Object;
        15: areturn
      LineNumberTable:
        line 72: 0
      LocalVariableTable:
        Start  Length  Slot  Name   Signature
            0      16     0  this   Lscala/collection/IndexedSeqOps;
            0      16     1     n   I
    Signature: #207                         // (I)TC;
    MethodParameters:
      Name                           Flags
      n                              final

  public static java.lang.Object drop$(scala.collection.IndexedSeqOps, int);
    descriptor: (Lscala/collection/IndexedSeqOps;I)Ljava/lang/Object;
    flags: (0x1009) ACC_PUBLIC, ACC_STATIC, ACC_SYNTHETIC
    Code:
      stack=2, locals=2, args_size=2
         0: aload_0
         1: iload_1
         2: invokespecial #222                // InterfaceMethod drop:(I)Ljava/lang/Object;
         5: areturn
      LineNumberTable:
        line 74: 0
      LocalVariableTable:
        Start  Length  Slot  Name   Signature
            0       6     0 $this   Lscala/collection/IndexedSeqOps;
            0       6     1     n   I
    MethodParameters:
      Name                           Flags
      $this                          final synthetic
      n                              final

  public default C drop(int);
    descriptor: (I)Ljava/lang/Object;
    flags: (0x0001) ACC_PUBLIC
    Code:
      stack=5, locals=2, args_size=2
         0: aload_0
         1: new           #13                 // class scala/collection/IndexedSeqView$Drop
         4: dup
         5: aload_0
         6: iload_1
         7: invokespecial #223                // Method scala/collection/IndexedSeqView$Drop."<init>":(Lscala/collection/IndexedSeqOps;I)V
        10: invokeinterface #213,  2          // InterfaceMethod fromSpecific:(Lscala/collection/IterableOnce;)Ljava/lang/Object;
        15: areturn
      LineNumberTable:
        line 74: 0
      LocalVariableTable:
        Start  Length  Slot  Name   Signature
            0      16     0  this   Lscala/collection/IndexedSeqOps;
            0      16     1     n   I
    Signature: #207                         // (I)TC;
    MethodParameters:
      Name                           Flags
      n                              final

  public static java.lang.Object dropRight$(scala.collection.IndexedSeqOps, int);
    descriptor: (Lscala/collection/IndexedSeqOps;I)Ljava/lang/Object;
    flags: (0x1009) ACC_PUBLIC, ACC_STATIC, ACC_SYNTHETIC
    Code:
      stack=2, locals=2, args_size=2
         0: aload_0
         1: iload_1
         2: invokespecial #227                // InterfaceMethod dropRight:(I)Ljava/lang/Object;
         5: areturn
      LineNumberTable:
        line 76: 0
      LocalVariableTable:
        Start  Length  Slot  Name   Signature
            0       6     0 $this   Lscala/collection/IndexedSeqOps;
            0       6     1     n   I
    MethodParameters:
      Name                           Flags
      $this                          final synthetic
      n                              final

  public default C dropRight(int);
    descriptor: (I)Ljava/lang/Object;
    flags: (0x0001) ACC_PUBLIC
    Code:
      stack=5, locals=2, args_size=2
         0: aload_0
         1: new           #18                 // class scala/collection/IndexedSeqView$DropRight
         4: dup
         5: aload_0
         6: iload_1
         7: invokespecial #228                // Method scala/collection/IndexedSeqView$DropRight."<init>":(Lscala/collection/IndexedSeqOps;I)V
        10: invokeinterface #213,  2          // InterfaceMethod fromSpecific:(Lscala/collection/IterableOnce;)Ljava/lang/Object;
        15: areturn
      LineNumberTable:
        line 76: 0
      LocalVariableTable:
        Start  Length  Slot  Name   Signature
            0      16     0  this   Lscala/collection/IndexedSeqOps;
            0      16     1     n   I
    Signature: #207                         // (I)TC;
    MethodParameters:
      Name                           Flags
      n                              final

  public static java.lang.Object map$(scala.collection.IndexedSeqOps, scala.Function1);
    descriptor: (Lscala/collection/IndexedSeqOps;Lscala/Function1;)Ljava/lang/Object;
    flags: (0x1009) ACC_PUBLIC, ACC_STATIC, ACC_SYNTHETIC
    Code:
      stack=2, locals=2, args_size=2
         0: aload_0
         1: aload_1
         2: invokespecial #235                // InterfaceMethod map:(Lscala/Function1;)Ljava/lang/Object;
         5: areturn
      LineNumberTable:
        line 78: 0
      LocalVariableTable:
        Start  Length  Slot  Name   Signature
            0       6     0 $this   Lscala/collection/IndexedSeqOps;
            0       6     1     f   Lscala/Function1;
    MethodParameters:
      Name                           Flags
      $this                          final synthetic
      f                              final

  public default <B extends java.lang.Object> CC map(scala.Function1<A, B>);
    descriptor: (Lscala/Function1;)Ljava/lang/Object;
    flags: (0x0001) ACC_PUBLIC
    Code:
      stack=5, locals=2, args_size=2
         0: aload_0
         1: invokeinterface #191,  1          // InterfaceMethod iterableFactory:()Lscala/collection/IterableFactory;
         6: new           #24                 // class scala/collection/IndexedSeqView$Map
         9: dup
        10: aload_0
        11: aload_1
        12: invokespecial #240                // Method scala/collection/IndexedSeqView$Map."<init>":(Lscala/collection/IndexedSeqOps;Lscala/Function1;)V
        15: invokeinterface #199,  2          // InterfaceMethod scala/collection/IterableFactory.from:(Lscala/collection/IterableOnce;)Ljava/lang/Object;
        20: areturn
      LineNumberTable:
        line 78: 0
      LocalVariableTable:
        Start  Length  Slot  Name   Signature
            0      21     0  this   Lscala/collection/IndexedSeqOps;
            0      21     1     f   Lscala/Function1;
    Signature: #237                         // <B:Ljava/lang/Object;>(Lscala/Function1<TA;TB;>;)TCC;
    MethodParameters:
      Name                           Flags
      f                              final

  public static java.lang.Object reverse$(scala.collection.IndexedSeqOps);
    descriptor: (Lscala/collection/IndexedSeqOps;)Ljava/lang/Object;
    flags: (0x1009) ACC_PUBLIC, ACC_STATIC, ACC_SYNTHETIC
    Code:
      stack=1, locals=1, args_size=1
         0: aload_0
         1: invokespecial #245                // InterfaceMethod reverse:()Ljava/lang/Object;
         4: areturn
      LineNumberTable:
        line 80: 0
      LocalVariableTable:
        Start  Length  Slot  Name   Signature
            0       5     0 $this   Lscala/collection/IndexedSeqOps;
    MethodParameters:
      Name                           Flags
      $this                          final synthetic

  public default C reverse();
    descriptor: ()Ljava/lang/Object;
    flags: (0x0001) ACC_PUBLIC
    Code:
      stack=4, locals=1, args_size=1
         0: aload_0
         1: new           #30                 // class scala/collection/IndexedSeqView$Reverse
         4: dup
         5: aload_0
         6: invokespecial #179                // Method scala/collection/IndexedSeqView$Reverse."<init>":(Lscala/collection/IndexedSeqOps;)V
         9: invokeinterface #213,  2          // InterfaceMethod fromSpecific:(Lscala/collection/IterableOnce;)Ljava/lang/Object;
        14: areturn
      LineNumberTable:
        line 80: 0
      LocalVariableTable:
        Start  Length  Slot  Name   Signature
            0      15     0  this   Lscala/collection/IndexedSeqOps;
    Signature: #246                         // ()TC;

  public static java.lang.Object slice$(scala.collection.IndexedSeqOps, int, int);
    descriptor: (Lscala/collection/IndexedSeqOps;II)Ljava/lang/Object;
    flags: (0x1009) ACC_PUBLIC, ACC_STATIC, ACC_SYNTHETIC
    Code:
      stack=3, locals=3, args_size=3
         0: aload_0
         1: iload_1
         2: iload_2
         3: invokespecial #251                // InterfaceMethod slice:(II)Ljava/lang/Object;
         6: areturn
      LineNumberTable:
        line 82: 0
      LocalVariableTable:
        Start  Length  Slot  Name   Signature
            0       7     0 $this   Lscala/collection/IndexedSeqOps;
            0       7     1  from   I
            0       7     2 until   I
    MethodParameters:
      Name                           Flags
      $this                          final synthetic
      from                           final
      until                          final

  public default C slice(int, int);
    descriptor: (II)Ljava/lang/Object;
    flags: (0x0001) ACC_PUBLIC
    Code:
      stack=6, locals=3, args_size=3
         0: aload_0
         1: new           #33                 // class scala/collection/IndexedSeqView$Slice
         4: dup
         5: aload_0
         6: iload_1
         7: iload_2
         8: invokespecial #253                // Method scala/collection/IndexedSeqView$Slice."<init>":(Lscala/collection/IndexedSeqOps;II)V
        11: invokeinterface #213,  2          // InterfaceMethod fromSpecific:(Lscala/collection/IterableOnce;)Ljava/lang/Object;
        16: areturn
      LineNumberTable:
        line 82: 0
      LocalVariableTable:
        Start  Length  Slot  Name   Signature
            0      17     0  this   Lscala/collection/IndexedSeqOps;
            0      17     1  from   I
            0      17     2 until   I
    Signature: #252                         // (II)TC;
    MethodParameters:
      Name                           Flags
      from                           final
      until                          final

  public static java.lang.Object head$(scala.collection.IndexedSeqOps);
    descriptor: (Lscala/collection/IndexedSeqOps;)Ljava/lang/Object;
    flags: (0x1009) ACC_PUBLIC, ACC_STATIC, ACC_SYNTHETIC
    Code:
      stack=1, locals=1, args_size=1
         0: aload_0
         1: invokespecial #257                // InterfaceMethod head:()Ljava/lang/Object;
         4: areturn
      LineNumberTable:
        line 84: 0
      LocalVariableTable:
        Start  Length  Slot  Name   Signature
            0       5     0 $this   Lscala/collection/IndexedSeqOps;
    MethodParameters:
      Name                           Flags
      $this                          final synthetic

  public default A head();
    descriptor: ()Ljava/lang/Object;
    flags: (0x0001) ACC_PUBLIC
    Code:
      stack=2, locals=1, args_size=1
         0: aload_0
         1: iconst_0
         2: invokeinterface #260,  2          // InterfaceMethod apply:(I)Ljava/lang/Object;
         7: areturn
      LineNumberTable:
        line 84: 0
      LocalVariableTable:
        Start  Length  Slot  Name   Signature
            0       8     0  this   Lscala/collection/IndexedSeqOps;
    Signature: #258                         // ()TA;

  public static scala.Option headOption$(scala.collection.IndexedSeqOps);
    descriptor: (Lscala/collection/IndexedSeqOps;)Lscala/Option;
    flags: (0x1009) ACC_PUBLIC, ACC_STATIC, ACC_SYNTHETIC
    Code:
      stack=1, locals=1, args_size=1
         0: aload_0
         1: invokespecial #266                // InterfaceMethod headOption:()Lscala/Option;
         4: areturn
      LineNumberTable:
        line 86: 0
      LocalVariableTable:
        Start  Length  Slot  Name   Signature
            0       5     0 $this   Lscala/collection/IndexedSeqOps;
    MethodParameters:
      Name                           Flags
      $this                          final synthetic

  public default scala.Option<A> headOption();
    descriptor: ()Lscala/Option;
    flags: (0x0001) ACC_PUBLIC
    Code:
      stack=3, locals=1, args_size=1
         0: aload_0
         1: invokeinterface #270,  1          // InterfaceMethod isEmpty:()Z
         6: ifeq          13
         9: getstatic     #275                // Field scala/None$.MODULE$:Lscala/None$;
        12: areturn
        13: new           #277                // class scala/Some
        16: dup
        17: aload_0
        18: invokeinterface #257,  1          // InterfaceMethod head:()Ljava/lang/Object;
        23: invokespecial #280                // Method scala/Some."<init>":(Ljava/lang/Object;)V
        26: areturn
      StackMapTable: number_of_entries = 1
        frame_type = 13 /* same */
      LineNumberTable:
        line 86: 0
      LocalVariableTable:
        Start  Length  Slot  Name   Signature
            0      27     0  this   Lscala/collection/IndexedSeqOps;
    Signature: #267                         // ()Lscala/Option<TA;>;

  public static java.lang.Object last$(scala.collection.IndexedSeqOps);
    descriptor: (Lscala/collection/IndexedSeqOps;)Ljava/lang/Object;
    flags: (0x1009) ACC_PUBLIC, ACC_STATIC, ACC_SYNTHETIC
    Code:
      stack=1, locals=1, args_size=1
         0: aload_0
         1: invokespecial #284                // InterfaceMethod last:()Ljava/lang/Object;
         4: areturn
      LineNumberTable:
        line 88: 0
      LocalVariableTable:
        Start  Length  Slot  Name   Signature
            0       5     0 $this   Lscala/collection/IndexedSeqOps;
    MethodParameters:
      Name                           Flags
      $this                          final synthetic

  public default A last();
    descriptor: ()Ljava/lang/Object;
    flags: (0x0001) ACC_PUBLIC
    Code:
      stack=3, locals=1, args_size=1
         0: aload_0
         1: aload_0
         2: invokeinterface #94,  1           // InterfaceMethod length:()I
         7: iconst_1
         8: isub
         9: invokeinterface #260,  2          // InterfaceMethod apply:(I)Ljava/lang/Object;
        14: areturn
      LineNumberTable:
        line 88: 0
      LocalVariableTable:
        Start  Length  Slot  Name   Signature
            0      15     0  this   Lscala/collection/IndexedSeqOps;
    Signature: #258                         // ()TA;

  public static int lengthCompare$(scala.collection.IndexedSeqOps, int);
    descriptor: (Lscala/collection/IndexedSeqOps;I)I
    flags: (0x1009) ACC_PUBLIC, ACC_STATIC, ACC_SYNTHETIC
    Code:
      stack=2, locals=2, args_size=2
         0: aload_0
         1: iload_1
         2: invokespecial #291                // InterfaceMethod lengthCompare:(I)I
         5: ireturn
      LineNumberTable:
        line 92: 0
      LocalVariableTable:
        Start  Length  Slot  Name   Signature
            0       6     0 $this   Lscala/collection/IndexedSeqOps;
            0       6     1   len   I
    MethodParameters:
      Name                           Flags
      $this                          final synthetic
      len                            final

  public default int lengthCompare(int);
    descriptor: (I)I
    flags: (0x0001) ACC_PUBLIC
    Code:
      stack=2, locals=2, args_size=2
         0: aload_0
         1: invokeinterface #94,  1           // InterfaceMethod length:()I
         6: iload_1
         7: invokestatic  #297                // Method java/lang/Integer.compare:(II)I
        10: ireturn
      LineNumberTable:
        line 92: 0
      LocalVariableTable:
        Start  Length  Slot  Name   Signature
            0      11     0  this   Lscala/collection/IndexedSeqOps;
            0      11     1   len   I
    MethodParameters:
      Name                           Flags
      len                            final

  public static int knownSize$(scala.collection.IndexedSeqOps);
    descriptor: (Lscala/collection/IndexedSeqOps;)I
    flags: (0x1009) ACC_PUBLIC, ACC_STATIC, ACC_SYNTHETIC
    Code:
      stack=1, locals=1, args_size=1
         0: aload_0
         1: invokespecial #302                // InterfaceMethod knownSize:()I
         4: ireturn
      LineNumberTable:
        line 94: 0
      LocalVariableTable:
        Start  Length  Slot  Name   Signature
            0       5     0 $this   Lscala/collection/IndexedSeqOps;
    MethodParameters:
      Name                           Flags
      $this                          final synthetic

  public default int knownSize();
    descriptor: ()I
    flags: (0x0001) ACC_PUBLIC
    Code:
      stack=1, locals=1, args_size=1
         0: aload_0
         1: invokeinterface #94,  1           // InterfaceMethod length:()I
         6: ireturn
      LineNumberTable:
        line 94: 0
      LocalVariableTable:
        Start  Length  Slot  Name   Signature
            0       7     0  this   Lscala/collection/IndexedSeqOps;

  public static int lengthCompare$(scala.collection.IndexedSeqOps, scala.collection.Iterable);
    descriptor: (Lscala/collection/IndexedSeqOps;Lscala/collection/Iterable;)I
    flags: (0x1009) ACC_PUBLIC, ACC_STATIC, ACC_SYNTHETIC
    Code:
      stack=2, locals=2, args_size=2
         0: aload_0
         1: aload_1
         2: invokespecial #307                // InterfaceMethod lengthCompare:(Lscala/collection/Iterable;)I
         5: ireturn
      LineNumberTable:
        line 96: 0
      LocalVariableTable:
        Start  Length  Slot  Name   Signature
            0       6     0 $this   Lscala/collection/IndexedSeqOps;
            0       6     1  that   Lscala/collection/Iterable;
    MethodParameters:
      Name                           Flags
      $this                          final synthetic
      that                           final

  public default int lengthCompare(scala.collection.Iterable<?>);
    descriptor: (Lscala/collection/Iterable;)I
    flags: (0x0001) ACC_PUBLIC
    Code:
      stack=2, locals=3, args_size=2
         0: aload_1
         1: aload_0
         2: invokeinterface #94,  1           // InterfaceMethod length:()I
         7: invokeinterface #314,  2          // InterfaceMethod scala/collection/Iterable.sizeCompare:(I)I
        12: istore_2
        13: iload_2
        14: ldc_w         #315                // int -2147483648
        17: if_icmpne     22
        20: iconst_1
        21: ireturn
        22: iload_2
        23: ineg
        24: ireturn
      StackMapTable: number_of_entries = 1
        frame_type = 252 /* append */
          offset_delta = 22
          locals = [ int ]
      LineNumberTable:
        line 97: 0
        line 99: 13
      LocalVariableTable:
        Start  Length  Slot  Name   Signature
           13      11     2   res   I
            0      25     0  this   Lscala/collection/IndexedSeqOps;
            0      25     1  that   Lscala/collection/Iterable;
    Signature: #309                         // (Lscala/collection/Iterable<*>;)I
    MethodParameters:
      Name                           Flags
      that                           final

  public static scala.collection.Searching$SearchResult search$(scala.collection.IndexedSeqOps, java.lang.Object, scala.math.Ordering);
    descriptor: (Lscala/collection/IndexedSeqOps;Ljava/lang/Object;Lscala/math/Ordering;)Lscala/collection/Searching$SearchResult;
    flags: (0x1009) ACC_PUBLIC, ACC_STATIC, ACC_SYNTHETIC
    Code:
      stack=3, locals=3, args_size=3
         0: aload_0
         1: aload_1
         2: aload_2
         3: invokespecial #323                // InterfaceMethod search:(Ljava/lang/Object;Lscala/math/Ordering;)Lscala/collection/Searching$SearchResult;
         6: areturn
      LineNumberTable:
        line 102: 0
      LocalVariableTable:
        Start  Length  Slot  Name   Signature
            0       7     0 $this   Lscala/collection/IndexedSeqOps;
            0       7     1  elem   Ljava/lang/Object;
            0       7     2   ord   Lscala/math/Ordering;
    MethodParameters:
      Name                           Flags
      $this                          final synthetic
      elem                           final
      ord                            final

  public default <B extends java.lang.Object> scala.collection.Searching$SearchResult search(B, scala.math.Ordering<B>);
    descriptor: (Ljava/lang/Object;Lscala/math/Ordering;)Lscala/collection/Searching$SearchResult;
    flags: (0x0001) ACC_PUBLIC
    Code:
      stack=5, locals=3, args_size=3
         0: aload_0
         1: aload_1
         2: iconst_0
         3: aload_0
         4: invokeinterface #94,  1           // InterfaceMethod length:()I
         9: aload_2
        10: invokespecial #329                // InterfaceMethod binarySearch:(Ljava/lang/Object;IILscala/math/Ordering;)Lscala/collection/Searching$SearchResult;
        13: areturn
      LineNumberTable:
        line 103: 0
      LocalVariableTable:
        Start  Length  Slot  Name   Signature
            0      14     0  this   Lscala/collection/IndexedSeqOps;
            0      14     1  elem   Ljava/lang/Object;
            0      14     2   ord   Lscala/math/Ordering;
    Signature: #325                         // <B:Ljava/lang/Object;>(TB;Lscala/math/Ordering<TB;>;)Lscala/collection/Searching$SearchResult;
    MethodParameters:
      Name                           Flags
      elem                           final
      ord                            final

  public static scala.collection.Searching$SearchResult search$(scala.collection.IndexedSeqOps, java.lang.Object, int, int, scala.math.Ordering);
    descriptor: (Lscala/collection/IndexedSeqOps;Ljava/lang/Object;IILscala/math/Ordering;)Lscala/collection/Searching$SearchResult;
    flags: (0x1009) ACC_PUBLIC, ACC_STATIC, ACC_SYNTHETIC
    Code:
      stack=5, locals=5, args_size=5
         0: aload_0
         1: aload_1
         2: iload_2
         3: iload_3
         4: aload         4
         6: invokespecial #333                // InterfaceMethod search:(Ljava/lang/Object;IILscala/math/Ordering;)Lscala/collection/Searching$SearchResult;
         9: areturn
      LineNumberTable:
        line 105: 0
      LocalVariableTable:
        Start  Length  Slot  Name   Signature
            0      10     0 $this   Lscala/collection/IndexedSeqOps;
            0      10     1  elem   Ljava/lang/Object;
            0      10     2  from   I
            0      10     3    to   I
            0      10     4   ord   Lscala/math/Ordering;
    MethodParameters:
      Name                           Flags
      $this                          final synthetic
      elem                           final
      from                           final
      to                             final
      ord                            final

  public default <B extends java.lang.Object> scala.collection.Searching$SearchResult search(B, int, int, scala.math.Ordering<B>);
    descriptor: (Ljava/lang/Object;IILscala/math/Ordering;)Lscala/collection/Searching$SearchResult;
    flags: (0x0001) ACC_PUBLIC
    Code:
      stack=5, locals=5, args_size=5
         0: aload_0
         1: aload_1
         2: iload_2
         3: iload_3
         4: aload         4
         6: invokespecial #329                // InterfaceMethod binarySearch:(Ljava/lang/Object;IILscala/math/Ordering;)Lscala/collection/Searching$SearchResult;
         9: areturn
      LineNumberTable:
        line 106: 0
      LocalVariableTable:
        Start  Length  Slot  Name   Signature
            0      10     0  this   Lscala/collection/IndexedSeqOps;
            0      10     1  elem   Ljava/lang/Object;
            0      10     2  from   I
            0      10     3    to   I
            0      10     4   ord   Lscala/math/Ordering;
    Signature: #334                         // <B:Ljava/lang/Object;>(TB;IILscala/math/Ordering<TB;>;)Lscala/collection/Searching$SearchResult;
    MethodParameters:
      Name                           Flags
      elem                           final
      from                           final
      to                             final
      ord                            final

  private <B extends java.lang.Object> scala.collection.Searching$SearchResult binarySearch(B, int, int, scala.math.Ordering<B>);
    descriptor: (Ljava/lang/Object;IILscala/math/Ordering;)Lscala/collection/Searching$SearchResult;
    flags: (0x0002) ACC_PRIVATE
    Code:
      stack=4, locals=6, args_size=5
         0: iload_2
         1: iconst_0
         2: if_icmpge     18
         5: aload_1
         6: iconst_0
         7: iload_3
         8: aload         4
        10: astore        4
        12: istore_3
        13: istore_2
        14: astore_1
        15: goto          0
        18: iload_3
        19: aload_0
        20: invokeinterface #94,  1           // InterfaceMethod length:()I
        25: if_icmple     46
        28: aload_1
        29: iload_2
        30: aload_0
        31: invokeinterface #94,  1           // InterfaceMethod length:()I
        36: aload         4
        38: astore        4
        40: istore_3
        41: istore_2
        42: astore_1
        43: goto          0
        46: iload_3
        47: iload_2
        48: if_icmpgt     60
        51: new           #47                 // class scala/collection/Searching$InsertionPoint
        54: dup
        55: iload_2
        56: invokespecial #337                // Method scala/collection/Searching$InsertionPoint."<init>":(I)V
        59: areturn
        60: iload_2
        61: iload_3
        62: iload_2
        63: isub
        64: iconst_1
        65: isub
        66: iconst_2
        67: idiv
        68: iadd
        69: istore        5
        71: getstatic     #342                // Field scala/math/package$.MODULE$:Lscala/math/package$;
        74: pop
        75: aload         4
        77: aload_1
        78: aload_0
        79: iload         5
        81: invokeinterface #260,  2          // InterfaceMethod apply:(I)Ljava/lang/Object;
        86: invokeinterface #347,  3          // InterfaceMethod scala/math/Ordering.compare:(Ljava/lang/Object;Ljava/lang/Object;)I
        91: invokestatic  #350                // Method java/lang/Integer.signum:(I)I
        94: lookupswitch  { // 2
                      -1: 120
                       1: 134
                 default: 150
            }
       120: aload_1
       121: iload_2
       122: iload         5
       124: aload         4
       126: astore        4
       128: istore_3
       129: istore_2
       130: astore_1
       131: goto          0
       134: aload_1
       135: iload         5
       137: iconst_1
       138: iadd
       139: iload_3
       140: aload         4
       142: astore        4
       144: istore_3
       145: istore_2
       146: astore_1
       147: goto          0
       150: new           #42                 // class scala/collection/Searching$Found
       153: dup
       154: iload         5
       156: invokespecial #351                // Method scala/collection/Searching$Found."<init>":(I)V
       159: areturn
      StackMapTable: number_of_entries = 7
        frame_type = 0 /* same */
        frame_type = 17 /* same */
        frame_type = 27 /* same */
        frame_type = 13 /* same */
        frame_type = 252 /* append */
          offset_delta = 59
          locals = [ int ]
        frame_type = 13 /* same */
        frame_type = 15 /* same */
      LineNumberTable:
        line 111: 0
        line 112: 18
        line 113: 46
        line 115: 60
        line 116: 71
        line 117: 120
        line 118: 134
        line 119: 150
      LocalVariableTable:
        Start  Length  Slot  Name   Signature
           71      88     5   idx   I
            0     160     0  this   Lscala/collection/IndexedSeqOps;
            0     160     1  elem   Ljava/lang/Object;
            0     160     2  from   I
            0     160     3    to   I
            0     160     4   ord   Lscala/math/Ordering;
    Signature: #334                         // <B:Ljava/lang/Object;>(TB;IILscala/math/Ordering<TB;>;)Lscala/collection/Searching$SearchResult;
    MethodParameters:
      Name                           Flags
      elem                           final
      from                           final
      to                             final
      ord                            final

  public static void $init$(scala.collection.IndexedSeqOps);
    descriptor: (Lscala/collection/IndexedSeqOps;)V
    flags: (0x0009) ACC_PUBLIC, ACC_STATIC
    Code:
      stack=0, locals=1, args_size=1
         0: return
      LineNumberTable:
        line 35: 0
      LocalVariableTable:
        Start  Length  Slot  Name   Signature
            0       1     0 $this   Lscala/collection/IndexedSeqOps;
    MethodParameters:
      Name                           Flags
      $this                          final synthetic
}
InnerClasses:
  public static #16= #13 of #15;          // Drop=class scala/collection/IndexedSeqView$Drop of class scala/collection/IndexedSeqView
  public static #19= #18 of #15;          // DropRight=class scala/collection/IndexedSeqView$DropRight of class scala/collection/IndexedSeqView
  public static #22= #21 of #15;          // Id=class scala/collection/IndexedSeqView$Id of class scala/collection/IndexedSeqView
  public static #25= #24 of #15;          // Map=class scala/collection/IndexedSeqView$Map of class scala/collection/IndexedSeqView
  public static #28= #27 of #15;          // Prepended=class scala/collection/IndexedSeqView$Prepended of class scala/collection/IndexedSeqView
  public static #31= #30 of #15;          // Reverse=class scala/collection/IndexedSeqView$Reverse of class scala/collection/IndexedSeqView
  public static #34= #33 of #15;          // Slice=class scala/collection/IndexedSeqView$Slice of class scala/collection/IndexedSeqView
  public static #37= #36 of #15;          // Take=class scala/collection/IndexedSeqView$Take of class scala/collection/IndexedSeqView
  public static #40= #39 of #15;          // TakeRight=class scala/collection/IndexedSeqView$TakeRight of class scala/collection/IndexedSeqView
  public static #45= #42 of #44;          // Found=class scala/collection/Searching$Found of class scala/collection/Searching
  public static #48= #47 of #44;          // InsertionPoint=class scala/collection/Searching$InsertionPoint of class scala/collection/Searching
  public static abstract #51= #50 of #44; // SearchResult=class scala/collection/Searching$SearchResult of class scala/collection/Searching
Signature: #3                           // <A:Ljava/lang/Object;CC:Ljava/lang/Object;C:Ljava/lang/Object;>Ljava/lang/Object;Lscala/collection/SeqOps<TA;TCC;TC;>;
SourceFile: "IndexedSeq.scala"
RuntimeVisibleAnnotations:
  0: #9(#10=s#11)
    scala.reflect.ScalaSignature(
      bytes="\u0006\u0005\t%aa\u0002\u000e\u001c!\u0003\r\t\u0001\t\u0005\u0006w\u0001!\t\u0001\u0010\u0005\u0006\u0001\u0002!\t!\u0011\u0005\u0006\u000b\u0002!\tE\u0012\u0005\u0006S\u0002!\t%\u0011\u0005\u0006U\u0002!\te\u001b\u0005\u0006q\u0002!\t%\u001f\u0005\u0006q\u0002!\t% \u0005\b\u0003?\u0001A\u0011KA\u0011\u0011\u001d\tI\u0003\u0001C!\u0003WAq!a\u000f\u0001\t\u0003\ni\u0004C\u0004\u0002D\u0001!\t%!\u0012\t\u000f\u0005%\u0003\u0001\"\u0011\u0002L!9\u0011q\n\u0001\u0005B\u0005E\u0003bBA+\u0001\u0011\u0005\u0013q\u000b\u0005\b\u0003W\u0002A\u0011IA7\u0011\u001d\ty\u0007\u0001C!\u0003cBq!a\u001e\u0001\t\u0003\nI\bC\u0004\u0002|\u0001!\t%! \t\u000f\u0005\u0015\u0005\u0001\"\u0011\u0002z!9\u0011q\u0011\u0001\u0005F\u0005%\u0005bBAH\u0001\u0011\u0005\u0013\u0011\u0013\u0005\b\u0003\u000f\u0003AQIAJ\u0011\u001d\t\u0019\u000b\u0001C!\u0003KCq!a)\u0001\t\u0003\ny\r\u0003\u0005\u0002f\u0002\u0001K\u0011BAt\u00055Ie\u000eZ3yK\u0012\u001cV-](qg*\u0011A$H\u0001\u000bG>dG.Z2uS>t\'\"\u0001\u0010\u0002\u000bM\u001c\u0017\r\\1\u0004\u0001U!\u0011\u0005L\u001a:\'\r\u0001!E\n\t\u0003G\u0011j\u0011!H\u0005\u0003Ku\u00111!\u00118z!\u00159\u0003F\u000b\u001a9\u001b\u0005Y\u0012BA\u0015\u001c\u0005\u0019\u0019V-](qgB\u00111\u0006\f\u0007\u0001\t\u0019i\u0003\u0001\"b\u0001]\t\t\u0011)\u0005\u00020EA\u00111\u0005M\u0005\u0003cu\u0011qAT8uQ&tw\r\u0005\u0002,g\u00111A\u0007\u0001CC\u0002U\u0012!aQ\"\u0016\u000592D!B\u001c4\u0005\u0004q#\u0001B0%IE\u0002\"aK\u001d\u0005\ri\u0002AQ1\u0001/\u0005\u0005\u0019\u0015A\u0002\u0013j]&$H\u0005F\u0001>!\t\u0019c(\u0003\u0002@;\t!QK\\5u\u0003!IG/\u001a:bi>\u0014X#\u0001\"\u0011\u0007\u001d\u001a%&\u0003\u0002E7\tA\u0011\n^3sCR|\'/A\u0004ti\u0016\u0004\b/\u001a:\u0016\u0005\u001dcEC\u0001%e%\rI5J\u0016\u0004\u0005\u0015\u0002\u0001\u0001J\u0001\u0007=e\u00164\u0017N\\3nK:$h\b\u0005\u0002,\u0019\u0012)Qj\u0001b\u0001\u001d\n\t1+\u0005\u00020\u001fB\u0012\u0001\u000b\u0016\t\u0004OE\u001b\u0016B\u0001*\u001c\u0005\u001d\u0019F/\u001a9qKJ\u0004\"a\u000b+\u0005\u0013Uc\u0015\u0011!A\u0001\u0006\u0003q#aA0%cA\u0011q+\u0019\b\u00031~s!!\u00170\u000f\u0005ikV\"A.\u000b\u0005q{\u0012A\u0002\u001fs_>$h(C\u0001\u001f\u0013\taR$\u0003\u0002a7\u000591\u000b^3qa\u0016\u0014\u0018B\u00012d\u00059)eMZ5dS\u0016tGo\u00159mSRT!\u0001Y\u000e\t\u000b\u0015\u001c\u00019\u00014\u0002\u000bMD\u0017\r]3\u0011\t\u001d:\'fS\u0005\u0003Qn\u0011Ab\u0015;faB,\'o\u00155ba\u0016\fqB]3wKJ\u001cX-\u0013;fe\u0006$xN]\u0001\nM>dGMU5hQR,\"\u0001\\8\u0015\u000554HC\u00018r!\tYs\u000eB\u0003q\u000b\t\u0007aFA\u0001C\u0011\u0015\u0011X\u00011\u0001t\u0003\ty\u0007\u000fE\u0003$i*rg.\u0003\u0002v;\tIa)\u001e8di&|gN\r\u0005\u0006o\u0016\u0001\rA\\\u0001\u0002u\u0006!a/[3x+\u0005Q\bcA\u0014|U%\u0011Ap\u0007\u0002\u000f\u0013:$W\r_3e\'\u0016\fh+[3x)\u0011Qh0a\u0002\t\r}<\u0001\u0019AA\u0001\u0003\u00111\'o\\7\u0011\u0007\r\n\u0019!C\u0002\u0002\u0006u\u00111!\u00138u\u0011\u001d\tIa\u0002a\u0001\u0003\u0003\tQ!\u001e8uS2D3bBA\u0007\u0003\'\t)\"!\u0007\u0002\u001cA\u00191%a\u0004\n\u0007\u0005EQD\u0001\u0006eKB\u0014XmY1uK\u0012\fq!\\3tg\u0006<W-\t\u0002\u0002\u0018\u0005QTk]3!]YLWm\u001e\u0018tY&\u001cW\r\u000b4s_6d\u0003%\u001e8uS2L\u0003%\u001b8ti\u0016\fG\rI8gA92\u0018.Z<)MJ|W\u000e\f\u0011v]RLG.K\u0001\u0006g&t7-Z\u0011\u0003\u0003;\taA\r\u00182g9\u0002\u0014\u0001\u0003:fm\u0016\u00148/\u001a3\u0016\u0005\u0005\r\u0002\u0003B\u0014\u0002&)J1!a\n\u001c\u0005!IE/\u001a:bE2,\u0017!\u00039sKB,g\u000eZ3e+\u0011\ti#a\r\u0015\t\u0005=\u0012q\u0007\t\u0005WM\n\t\u0004E\u0002,\u0003g!a\u0001]\u0005C\u0002\u0005U\u0012C\u0001\u0016#\u0011\u001d\tI$\u0003a\u0001\u0003c\tA!\u001a7f[\u0006!A/Y6f)\rA\u0014q\b\u0005\b\u0003\u0003R\u0001\u0019AA\u0001\u0003\u0005q\u0017!\u0003;bW\u0016\u0014\u0016n\u001a5u)\rA\u0014q\t\u0005\b\u0003\u0003Z\u0001\u0019AA\u0001\u0003\u0011!\'o\u001c9\u0015\u0007a\ni\u0005C\u0004\u0002B1\u0001\r!!\u0001\u0002\u0013\u0011\u0014x\u000e\u001d*jO\"$Hc\u0001\u001d\u0002T!9\u0011\u0011I\u0007A\u0002\u0005\u0005\u0011aA7baV!\u0011\u0011LA0)\u0011\tY&!\u0019\u0011\t-\u001a\u0014Q\f\t\u0004W\u0005}C!\u00029\u000f\u0005\u0004q\u0003bBA2\u001d\u0001\u0007\u0011QM\u0001\u0002MB11%a\u001a+\u0003;J1!!\u001b\u001e\u0005%1UO\\2uS>t\u0017\'A\u0004sKZ,\'o]3\u0016\u0003a\nQa\u001d7jG\u0016$R\u0001OA:\u0003kBaa \tA\u0002\u0005\u0005\u0001bBA\u0005!\u0001\u0007\u0011\u0011A\u0001\u0005Q\u0016\fG-F\u0001+\u0003)AW-\u00193PaRLwN\\\u000b\u0003\u0003\u007f\u0002BaIAAU%\u0019\u00111Q\u000f\u0003\r=\u0003H/[8o\u0003\u0011a\u0017m\u001d;\u0002\u001b1,gn\u001a;i\u0007>l\u0007/\u0019:f)\u0011\t\t!a#\t\u000f\u00055E\u00031\u0001\u0002\u0002\u0005\u0019A.\u001a8\u0002\u0013-twn\u001e8TSj,WCAA\u0001)\u0011\t\t!!&\t\u000f\u0005]e\u00031\u0001\u0002\u001a\u0006!A\u000f[1ua\u0011\tY*a(\u0011\u000b\u001d\n)#!(\u0011\u0007-\ny\nB\u0006\u0002\"\u0006U\u0015\u0011!A\u0001\u0006\u0003q#aA0%k\u000511/Z1sG\",B!a*\u0002LR!\u0011\u0011VAg)\u0011\tY+!/\u0011\t\u00055\u00161\u0017\b\u00041\u0006=\u0016bAAY7\u0005I1+Z1sG\"LgnZ\u0005\u0005\u0003k\u000b9L\u0001\u0007TK\u0006\u00148\r\u001b*fgVdGOC\u0002\u00022nAq!a/\u0018\u0001\b\ti,A\u0002pe\u0012\u0004b!a0\u0002F\u0006%WBAAa\u0015\r\t\u0019-H\u0001\u0005[\u0006$\b.\u0003\u0003\u0002H\u0006\u0005\'\u0001C(sI\u0016\u0014\u0018N\\4\u0011\u0007-\nY\r\u0002\u0004q/\t\u0007\u0011Q\u0007\u0005\b\u0003s9\u0002\u0019AAe+\u0011\t\t.a7\u0015\u0011\u0005M\u0017Q\\Ap\u0003C$B!a+\u0002V\"9\u00111\u0018\rA\u0004\u0005]\u0007CBA`\u0003\u000b\fI\u000eE\u0002,\u00037$a\u0001\u001d\rC\u0002\u0005U\u0002bBA\u001d1\u0001\u0007\u0011\u0011\u001c\u0005\u0007\u007fb\u0001\r!!\u0001\t\u000f\u0005\r\b\u00041\u0001\u0002\u0002\u0005\u0011Ao\\\u0001\rE&t\u0017M]=TK\u0006\u00148\r[\u000b\u0005\u0003S\f\u0019\u0010\u0006\u0005\u0002l\u0006U\u0018q_A})\u0011\tY+!<\t\u000f\u0005m\u0016\u0004q\u0001\u0002pB1\u0011qXAc\u0003c\u00042aKAz\t\u0019\u0001\u0018D1\u0001\u00026!9\u0011\u0011H\rA\u0002\u0005E\bBB@\u001a\u0001\u0004\t\t\u0001C\u0004\u0002df\u0001\r!!\u0001)\u0007e\ti\u0010\u0005\u0003\u0002\u0000\n\u0015QB\u0001B\u0001\u0015\r\u0011\u0019!H\u0001\u000bC:tw\u000e^1uS>t\u0017\u0002\u0002B\u0004\u0005\u0003\u0011q\u0001^1jYJ,7\r"
    )
  ScalaInlineInfo: length = 0xF4 (unknown attribute)
   01 00 00 30 01 61 00 9E 01 01 46 01 47 01 00 DC
   00 CC 00 00 DB 00 C9 01 00 E1 00 CC 00 00 E0 00
   C9 01 00 81 00 82 00 00 7D 00 7E 01 00 FF 00 8F
   00 00 FE 00 F2 01 01 07 01 08 00 01 05 01 06 01
   00 37 00 38 00 00 34 00 35 01 01 2C 00 4E 00 01
   2A 01 2B 01 01 1A 00 8F 00 01 19 00 F2 01 01 20
   01 21 01 01 20 01 31 01 01 1D 01 1E 01 01 1D 01
   2F 01 00 E8 00 E9 00 00 E5 00 E6 01 00 B7 00 B8
   00 00 B4 00 B5 01 00 F3 00 8F 00 00 F1 00 F2 01
   00 79 00 38 00 00 78 00 35 01 00 AE 00 AF 00 00
   AC 00 AD 01 01 40 01 47 00 01 40 01 41 00 01 3D
   01 4A 01 01 3D 01 3E 01 00 A9 00 F9 00 00 F7 00
   F8 01 00 46 00 47 00 00 43 00 44 01 00 CB 00 CC
   00 00 C8 00 C9 01 00 D7 00 CC 00 00 D6 00 C9 01
   00 3D 00 3E 00 00 3D 00 A4 00 00 9B 00 9C 01 00
   9B 00 A1 01
  ScalaSig: length = 0x3 (unknown attribute)
   05 02 00
