Classfile /Users/mw/Projects/slang-braindump/.jar/jar8/assemble/slang-braindump/assemble/content/scala/collection/IterableFactory$.class
  Last modified May 29, 2022; size 1591 bytes
  SHA-256 checksum 4a4ec03bbced16d60dc5545114fa45adc6bfd13577eb2cdae624c79760f18d34
  Compiled from "Factory.scala"
public final class scala.collection.IterableFactory$ implements java.io.Serializable
  minor version: 0
  major version: 52
  flags: (0x0031) ACC_PUBLIC, ACC_FINAL, ACC_SUPER
  this_class: #2                          // scala/collection/IterableFactory$
  super_class: #4                         // java/lang/Object
  interfaces: 1, fields: 1, methods: 5, attributes: 4
Constant pool:
   #1 = Utf8               scala/collection/IterableFactory$
   #2 = Class              #1             // scala/collection/IterableFactory$
   #3 = Utf8               java/lang/Object
   #4 = Class              #3             // java/lang/Object
   #5 = Utf8               java/io/Serializable
   #6 = Class              #5             // java/io/Serializable
   #7 = Utf8               Factory.scala
   #8 = Utf8               scala/collection/IterableFactory$$anon$1
   #9 = Class              #8             // scala/collection/IterableFactory$$anon$1
  #10 = Utf8               scala/collection/IterableFactory$ToFactory
  #11 = Class              #10            // scala/collection/IterableFactory$ToFactory
  #12 = Utf8               scala/collection/IterableFactory
  #13 = Class              #12            // scala/collection/IterableFactory
  #14 = Utf8               ToFactory
  #15 = Utf8               MODULE$
  #16 = Utf8               Lscala/collection/IterableFactory$;
  #17 = Utf8               <clinit>
  #18 = Utf8               ()V
  #19 = Utf8               <init>
  #20 = NameAndType        #19:#18        // "<init>":()V
  #21 = Methodref          #2.#20         // scala/collection/IterableFactory$."<init>":()V
  #22 = NameAndType        #15:#16        // MODULE$:Lscala/collection/IterableFactory$;
  #23 = Fieldref           #2.#22         // scala/collection/IterableFactory$.MODULE$:Lscala/collection/IterableFactory$;
  #24 = Utf8               toFactory
  #25 = Utf8               (Lscala/collection/IterableFactory;)Lscala/collection/Factory;
  #26 = Utf8               <A:Ljava/lang/Object;CC:Ljava/lang/Object;>(Lscala/collection/IterableFactory<TCC;>;)Lscala/collection/Factory<TA;TCC;>;
  #27 = Utf8               factory
  #28 = Utf8               (Lscala/collection/IterableFactory;)V
  #29 = NameAndType        #19:#28        // "<init>":(Lscala/collection/IterableFactory;)V
  #30 = Methodref          #11.#29        // scala/collection/IterableFactory$ToFactory."<init>":(Lscala/collection/IterableFactory;)V
  #31 = Utf8               this
  #32 = Utf8               Lscala/collection/IterableFactory;
  #33 = Utf8               toBuildFrom
  #34 = Utf8               (Lscala/collection/IterableFactory;)Lscala/collection/BuildFrom;
  #35 = Utf8               <A:Ljava/lang/Object;CC:Ljava/lang/Object;>(Lscala/collection/IterableFactory<TCC;>;)Lscala/collection/BuildFrom<Ljava/lang/Object;TA;TCC;>;
  #36 = Methodref          #9.#29         // scala/collection/IterableFactory$$anon$1."<init>":(Lscala/collection/IterableFactory;)V
  #37 = Utf8               writeReplace
  #38 = Utf8               ()Ljava/lang/Object;
  #39 = Utf8               scala/runtime/ModuleSerializationProxy
  #40 = Class              #39            // scala/runtime/ModuleSerializationProxy
  #41 = Utf8               (Ljava/lang/Class;)V
  #42 = NameAndType        #19:#41        // "<init>":(Ljava/lang/Class;)V
  #43 = Methodref          #40.#42        // scala/runtime/ModuleSerializationProxy."<init>":(Ljava/lang/Class;)V
  #44 = Methodref          #4.#20         // java/lang/Object."<init>":()V
  #45 = Utf8               Code
  #46 = Utf8               LineNumberTable
  #47 = Utf8               LocalVariableTable
  #48 = Utf8               Signature
  #49 = Utf8               MethodParameters
  #50 = Utf8               InnerClasses
  #51 = Utf8               SourceFile
  #52 = Utf8               ScalaInlineInfo
  #53 = Utf8               Scala
{
  public static final scala.collection.IterableFactory$ MODULE$;
    descriptor: Lscala/collection/IterableFactory$;
    flags: (0x0019) ACC_PUBLIC, ACC_STATIC, ACC_FINAL

  public static {};
    descriptor: ()V
    flags: (0x0009) ACC_PUBLIC, ACC_STATIC
    Code:
      stack=2, locals=0, args_size=0
         0: new           #2                  // class scala/collection/IterableFactory$
         3: dup
         4: invokespecial #21                 // Method "<init>":()V
         7: putstatic     #23                 // Field MODULE$:Lscala/collection/IterableFactory$;
        10: return
      LineNumberTable:
        line 260: 0

  public <A extends java.lang.Object, CC extends java.lang.Object> scala.collection.Factory<A, CC> toFactory(scala.collection.IterableFactory<CC>);
    descriptor: (Lscala/collection/IterableFactory;)Lscala/collection/Factory;
    flags: (0x0001) ACC_PUBLIC
    Code:
      stack=3, locals=2, args_size=2
         0: new           #11                 // class scala/collection/IterableFactory$ToFactory
         3: dup
         4: aload_1
         5: invokespecial #30                 // Method scala/collection/IterableFactory$ToFactory."<init>":(Lscala/collection/IterableFactory;)V
         8: areturn
      LineNumberTable:
        line 270: 0
      LocalVariableTable:
        Start  Length  Slot  Name   Signature
            0       9     0  this   Lscala/collection/IterableFactory$;
            0       9     1 factory   Lscala/collection/IterableFactory;
    Signature: #26                          // <A:Ljava/lang/Object;CC:Ljava/lang/Object;>(Lscala/collection/IterableFactory<TCC;>;)Lscala/collection/Factory<TA;TCC;>;
    MethodParameters:
      Name                           Flags
      factory                        final

  public <A extends java.lang.Object, CC extends java.lang.Object> scala.collection.BuildFrom<java.lang.Object, A, CC> toBuildFrom(scala.collection.IterableFactory<CC>);
    descriptor: (Lscala/collection/IterableFactory;)Lscala/collection/BuildFrom;
    flags: (0x0001) ACC_PUBLIC
    Code:
      stack=3, locals=2, args_size=2
         0: new           #9                  // class scala/collection/IterableFactory$$anon$1
         3: dup
         4: aload_1
         5: invokespecial #36                 // Method scala/collection/IterableFactory$$anon$1."<init>":(Lscala/collection/IterableFactory;)V
         8: areturn
      LineNumberTable:
        line 279: 0
      LocalVariableTable:
        Start  Length  Slot  Name   Signature
            0       9     0  this   Lscala/collection/IterableFactory$;
            0       9     1 factory   Lscala/collection/IterableFactory;
    Signature: #35                          // <A:Ljava/lang/Object;CC:Ljava/lang/Object;>(Lscala/collection/IterableFactory<TCC;>;)Lscala/collection/BuildFrom<Ljava/lang/Object;TA;TCC;>;
    MethodParameters:
      Name                           Flags
      factory                        final

  private java.lang.Object writeReplace();
    descriptor: ()Ljava/lang/Object;
    flags: (0x0002) ACC_PRIVATE
    Code:
      stack=3, locals=1, args_size=1
         0: new           #40                 // class scala/runtime/ModuleSerializationProxy
         3: dup
         4: ldc           #2                  // class scala/collection/IterableFactory$
         6: invokespecial #43                 // Method scala/runtime/ModuleSerializationProxy."<init>":(Ljava/lang/Class;)V
         9: areturn
      LineNumberTable:
        line 260: 0
      LocalVariableTable:
        Start  Length  Slot  Name   Signature
            0      10     0  this   Lscala/collection/IterableFactory$;

  private scala.collection.IterableFactory$();
    descriptor: ()V
    flags: (0x0002) ACC_PRIVATE
    Code:
      stack=1, locals=1, args_size=1
         0: aload_0
         1: invokespecial #44                 // Method java/lang/Object."<init>":()V
         4: return
      LineNumberTable:
        line 260: 0
      LocalVariableTable:
        Start  Length  Slot  Name   Signature
            0       5     0  this   Lscala/collection/IterableFactory$;
}
InnerClasses:
  public final #9;                        // class scala/collection/IterableFactory$$anon$1
  private static #14= #11 of #13;         // ToFactory=class scala/collection/IterableFactory$ToFactory of class scala/collection/IterableFactory
SourceFile: "Factory.scala"
  ScalaInlineInfo: length = 0x18 (unknown attribute)
   01 01 00 04 00 13 00 12 01 00 21 00 22 01 00 18
   00 19 01 00 25 00 26 01
  Scala: length = 0x0 (unknown attribute)

