Classfile /Users/mw/Projects/slang-braindump/.jar/jar8/assemble/slang-braindump/assemble/content/scala/collection/IterableOnceExtensionMethods$.class
  Last modified May 29, 2022; size 18194 bytes
  SHA-256 checksum 2e198f36f921bba549994330ee2318cdbb5b34bf78c8da3444d2057996a95886
  Compiled from "IterableOnce.scala"
public final class scala.collection.IterableOnceExtensionMethods$
  minor version: 0
  major version: 52
  flags: (0x0031) ACC_PUBLIC, ACC_FINAL, ACC_SUPER
  this_class: #2                          // scala/collection/IterableOnceExtensionMethods$
  super_class: #4                         // java/lang/Object
  interfaces: 0, fields: 1, methods: 52, attributes: 3
Constant pool:
    #1 = Utf8               scala/collection/IterableOnceExtensionMethods$
    #2 = Class              #1            // scala/collection/IterableOnceExtensionMethods$
    #3 = Utf8               java/lang/Object
    #4 = Class              #3            // java/lang/Object
    #5 = Utf8               IterableOnce.scala
    #6 = Utf8               MODULE$
    #7 = Utf8               Lscala/collection/IterableOnceExtensionMethods$;
    #8 = Utf8               <clinit>
    #9 = Utf8               ()V
   #10 = Utf8               <init>
   #11 = NameAndType        #10:#9        // "<init>":()V
   #12 = Methodref          #2.#11        // scala/collection/IterableOnceExtensionMethods$."<init>":()V
   #13 = NameAndType        #6:#7         // MODULE$:Lscala/collection/IterableOnceExtensionMethods$;
   #14 = Fieldref           #2.#13        // scala/collection/IterableOnceExtensionMethods$.MODULE$:Lscala/collection/IterableOnceExtensionMethods$;
   #15 = Utf8               withFilter$extension
   #16 = Utf8               (Lscala/collection/IterableOnce;Lscala/Function1;)Lscala/collection/Iterator;
   #17 = Utf8               <A:Ljava/lang/Object;>(Lscala/collection/IterableOnce<TA;>;Lscala/Function1<TA;Ljava/lang/Object;>;)Lscala/collection/Iterator<TA;>;
   #18 = Utf8               $this
   #19 = Utf8               f
   #20 = Utf8               scala/collection/IterableOnce
   #21 = Class              #20           // scala/collection/IterableOnce
   #22 = Utf8               iterator
   #23 = Utf8               ()Lscala/collection/Iterator;
   #24 = NameAndType        #22:#23       // iterator:()Lscala/collection/Iterator;
   #25 = InterfaceMethodref #21.#24       // scala/collection/IterableOnce.iterator:()Lscala/collection/Iterator;
   #26 = Utf8               scala/collection/Iterator
   #27 = Class              #26           // scala/collection/Iterator
   #28 = Utf8               withFilter
   #29 = Utf8               (Lscala/Function1;)Lscala/collection/Iterator;
   #30 = NameAndType        #28:#29       // withFilter:(Lscala/Function1;)Lscala/collection/Iterator;
   #31 = InterfaceMethodref #27.#30       // scala/collection/Iterator.withFilter:(Lscala/Function1;)Lscala/collection/Iterator;
   #32 = Utf8               this
   #33 = Utf8               Lscala/collection/IterableOnce;
   #34 = Utf8               Lscala/Function1;
   #35 = Utf8               reduceLeftOption$extension
   #36 = Utf8               (Lscala/collection/IterableOnce;Lscala/Function2;)Lscala/Option;
   #37 = Utf8               <A:Ljava/lang/Object;>(Lscala/collection/IterableOnce<TA;>;Lscala/Function2<TA;TA;TA;>;)Lscala/Option<TA;>;
   #38 = Utf8               reduceLeftOption
   #39 = Utf8               (Lscala/Function2;)Lscala/Option;
   #40 = NameAndType        #38:#39       // reduceLeftOption:(Lscala/Function2;)Lscala/Option;
   #41 = InterfaceMethodref #27.#40       // scala/collection/Iterator.reduceLeftOption:(Lscala/Function2;)Lscala/Option;
   #42 = Utf8               Lscala/Function2;
   #43 = Utf8               min$extension
   #44 = Utf8               (Lscala/collection/IterableOnce;Lscala/math/Ordering;)Ljava/lang/Object;
   #45 = Utf8               <A:Ljava/lang/Object;>(Lscala/collection/IterableOnce<TA;>;Lscala/math/Ordering<TA;>;)TA;
   #46 = Utf8               ord
   #47 = Utf8               min
   #48 = Utf8               (Lscala/math/Ordering;)Ljava/lang/Object;
   #49 = NameAndType        #47:#48       // min:(Lscala/math/Ordering;)Ljava/lang/Object;
   #50 = InterfaceMethodref #27.#49       // scala/collection/Iterator.min:(Lscala/math/Ordering;)Ljava/lang/Object;
   #51 = Utf8               Lscala/math/Ordering;
   #52 = Utf8               nonEmpty$extension
   #53 = Utf8               (Lscala/collection/IterableOnce;)Z
   #54 = Utf8               <A:Ljava/lang/Object;>(Lscala/collection/IterableOnce<TA;>;)Z
   #55 = Utf8               nonEmpty
   #56 = Utf8               ()Z
   #57 = NameAndType        #55:#56       // nonEmpty:()Z
   #58 = InterfaceMethodref #27.#57       // scala/collection/Iterator.nonEmpty:()Z
   #59 = Utf8               max$extension
   #60 = Utf8               max
   #61 = NameAndType        #60:#48       // max:(Lscala/math/Ordering;)Ljava/lang/Object;
   #62 = InterfaceMethodref #27.#61       // scala/collection/Iterator.max:(Lscala/math/Ordering;)Ljava/lang/Object;
   #63 = Utf8               reduceRight$extension
   #64 = Utf8               (Lscala/collection/IterableOnce;Lscala/Function2;)Ljava/lang/Object;
   #65 = Utf8               <A:Ljava/lang/Object;>(Lscala/collection/IterableOnce<TA;>;Lscala/Function2<TA;TA;TA;>;)TA;
   #66 = Utf8               reduceRight
   #67 = Utf8               (Lscala/Function2;)Ljava/lang/Object;
   #68 = NameAndType        #66:#67       // reduceRight:(Lscala/Function2;)Ljava/lang/Object;
   #69 = InterfaceMethodref #27.#68       // scala/collection/Iterator.reduceRight:(Lscala/Function2;)Ljava/lang/Object;
   #70 = Utf8               maxBy$extension
   #71 = Utf8               (Lscala/collection/IterableOnce;Lscala/Function1;Lscala/math/Ordering;)Ljava/lang/Object;
   #72 = Utf8               <B:Ljava/lang/Object;A:Ljava/lang/Object;>(Lscala/collection/IterableOnce<TA;>;Lscala/Function1<TA;TB;>;Lscala/math/Ordering<TB;>;)TA;
   #73 = Utf8               cmp
   #74 = Utf8               maxBy
   #75 = Utf8               (Lscala/Function1;Lscala/math/Ordering;)Ljava/lang/Object;
   #76 = NameAndType        #74:#75       // maxBy:(Lscala/Function1;Lscala/math/Ordering;)Ljava/lang/Object;
   #77 = InterfaceMethodref #27.#76       // scala/collection/Iterator.maxBy:(Lscala/Function1;Lscala/math/Ordering;)Ljava/lang/Object;
   #78 = Utf8               reduceLeft$extension
   #79 = Utf8               reduceLeft
   #80 = NameAndType        #79:#67       // reduceLeft:(Lscala/Function2;)Ljava/lang/Object;
   #81 = InterfaceMethodref #27.#80       // scala/collection/Iterator.reduceLeft:(Lscala/Function2;)Ljava/lang/Object;
   #82 = Utf8               sum$extension
   #83 = Utf8               (Lscala/collection/IterableOnce;Lscala/math/Numeric;)Ljava/lang/Object;
   #84 = Utf8               <A:Ljava/lang/Object;>(Lscala/collection/IterableOnce<TA;>;Lscala/math/Numeric<TA;>;)TA;
   #85 = Utf8               num
   #86 = Utf8               sum
   #87 = Utf8               (Lscala/math/Numeric;)Ljava/lang/Object;
   #88 = NameAndType        #86:#87       // sum:(Lscala/math/Numeric;)Ljava/lang/Object;
   #89 = InterfaceMethodref #27.#88       // scala/collection/Iterator.sum:(Lscala/math/Numeric;)Ljava/lang/Object;
   #90 = Utf8               Lscala/math/Numeric;
   #91 = Utf8               product$extension
   #92 = Utf8               product
   #93 = NameAndType        #92:#87       // product:(Lscala/math/Numeric;)Ljava/lang/Object;
   #94 = InterfaceMethodref #27.#93       // scala/collection/Iterator.product:(Lscala/math/Numeric;)Ljava/lang/Object;
   #95 = Utf8               count$extension
   #96 = Utf8               (Lscala/collection/IterableOnce;Lscala/Function1;)I
   #97 = Utf8               <A:Ljava/lang/Object;>(Lscala/collection/IterableOnce<TA;>;Lscala/Function1<TA;Ljava/lang/Object;>;)I
   #98 = Utf8               count
   #99 = Utf8               (Lscala/Function1;)I
  #100 = NameAndType        #98:#99       // count:(Lscala/Function1;)I
  #101 = InterfaceMethodref #27.#100      // scala/collection/Iterator.count:(Lscala/Function1;)I
  #102 = Utf8               reduceOption$extension
  #103 = Utf8               reduceOption
  #104 = NameAndType        #103:#39      // reduceOption:(Lscala/Function2;)Lscala/Option;
  #105 = InterfaceMethodref #27.#104      // scala/collection/Iterator.reduceOption:(Lscala/Function2;)Lscala/Option;
  #106 = Utf8               minBy$extension
  #107 = Utf8               minBy
  #108 = NameAndType        #107:#75      // minBy:(Lscala/Function1;Lscala/math/Ordering;)Ljava/lang/Object;
  #109 = InterfaceMethodref #27.#108      // scala/collection/Iterator.minBy:(Lscala/Function1;Lscala/math/Ordering;)Ljava/lang/Object;
  #110 = Utf8               size$extension
  #111 = Utf8               (Lscala/collection/IterableOnce;)I
  #112 = Utf8               <A:Ljava/lang/Object;>(Lscala/collection/IterableOnce<TA;>;)I
  #113 = Utf8               size
  #114 = Utf8               ()I
  #115 = NameAndType        #113:#114     // size:()I
  #116 = InterfaceMethodref #27.#115      // scala/collection/Iterator.size:()I
  #117 = Utf8               forall$extension
  #118 = Utf8               (Lscala/collection/IterableOnce;Lscala/Function1;)Z
  #119 = Utf8               <A:Ljava/lang/Object;>(Lscala/collection/IterableOnce<TA;>;Lscala/Function1<TA;Ljava/lang/Object;>;)Z
  #120 = Utf8               forall
  #121 = Utf8               (Lscala/Function1;)Z
  #122 = NameAndType        #120:#121     // forall:(Lscala/Function1;)Z
  #123 = InterfaceMethodref #27.#122      // scala/collection/Iterator.forall:(Lscala/Function1;)Z
  #124 = Utf8               collectFirst$extension
  #125 = Utf8               (Lscala/collection/IterableOnce;Lscala/PartialFunction;)Lscala/Option;
  #126 = Utf8               <B:Ljava/lang/Object;A:Ljava/lang/Object;>(Lscala/collection/IterableOnce<TA;>;Lscala/PartialFunction<TA;TB;>;)Lscala/Option<TB;>;
  #127 = Utf8               collectFirst
  #128 = Utf8               (Lscala/PartialFunction;)Lscala/Option;
  #129 = NameAndType        #127:#128     // collectFirst:(Lscala/PartialFunction;)Lscala/Option;
  #130 = InterfaceMethodref #27.#129      // scala/collection/Iterator.collectFirst:(Lscala/PartialFunction;)Lscala/Option;
  #131 = Utf8               Lscala/PartialFunction;
  #132 = Utf8               filter$extension
  #133 = Utf8               filter
  #134 = NameAndType        #133:#29      // filter:(Lscala/Function1;)Lscala/collection/Iterator;
  #135 = InterfaceMethodref #27.#134      // scala/collection/Iterator.filter:(Lscala/Function1;)Lscala/collection/Iterator;
  #136 = Utf8               exists$extension
  #137 = Utf8               exists
  #138 = NameAndType        #137:#121     // exists:(Lscala/Function1;)Z
  #139 = InterfaceMethodref #27.#138      // scala/collection/Iterator.exists:(Lscala/Function1;)Z
  #140 = Utf8               copyToBuffer$extension
  #141 = Utf8               (Lscala/collection/IterableOnce;Lscala/collection/mutable/Buffer;)V
  #142 = Utf8               <A:Ljava/lang/Object;>(Lscala/collection/IterableOnce<TA;>;Lscala/collection/mutable/Buffer<TA;>;)V
  #143 = Utf8               dest
  #144 = Utf8               scala/collection/mutable/Growable
  #145 = Class              #144          // scala/collection/mutable/Growable
  #146 = Utf8               addAll
  #147 = Utf8               (Lscala/collection/IterableOnce;)Lscala/collection/mutable/Growable;
  #148 = NameAndType        #146:#147     // addAll:(Lscala/collection/IterableOnce;)Lscala/collection/mutable/Growable;
  #149 = InterfaceMethodref #145.#148     // scala/collection/mutable/Growable.addAll:(Lscala/collection/IterableOnce;)Lscala/collection/mutable/Growable;
  #150 = Utf8               Lscala/collection/mutable/Buffer;
  #151 = Utf8               copyToBuffer_this
  #152 = Utf8               Lscala/collection/IterableOnceOps;
  #153 = Utf8               reduce$extension
  #154 = Utf8               reduce
  #155 = NameAndType        #154:#67      // reduce:(Lscala/Function2;)Ljava/lang/Object;
  #156 = InterfaceMethodref #27.#155      // scala/collection/Iterator.reduce:(Lscala/Function2;)Ljava/lang/Object;
  #157 = Utf8               reduceRightOption$extension
  #158 = Utf8               reduceRightOption
  #159 = NameAndType        #158:#39      // reduceRightOption:(Lscala/Function2;)Lscala/Option;
  #160 = InterfaceMethodref #27.#159      // scala/collection/Iterator.reduceRightOption:(Lscala/Function2;)Lscala/Option;
  #161 = Utf8               toIndexedSeq$extension
  #162 = Utf8               (Lscala/collection/IterableOnce;)Lscala/collection/IndexedSeq;
  #163 = Utf8               <A:Ljava/lang/Object;>(Lscala/collection/IterableOnce<TA;>;)Lscala/collection/IndexedSeq<TA;>;
  #164 = Utf8               toIndexedSeq
  #165 = Utf8               ()Lscala/collection/immutable/IndexedSeq;
  #166 = NameAndType        #164:#165     // toIndexedSeq:()Lscala/collection/immutable/IndexedSeq;
  #167 = InterfaceMethodref #27.#166      // scala/collection/Iterator.toIndexedSeq:()Lscala/collection/immutable/IndexedSeq;
  #168 = Utf8               foreach$extension
  #169 = Utf8               (Lscala/collection/IterableOnce;Lscala/Function1;)V
  #170 = Utf8               <U:Ljava/lang/Object;A:Ljava/lang/Object;>(Lscala/collection/IterableOnce<TA;>;Lscala/Function1<TA;TU;>;)V
  #171 = Utf8               scala/collection/Iterable
  #172 = Class              #171          // scala/collection/Iterable
  #173 = Utf8               foreach
  #174 = Utf8               (Lscala/Function1;)V
  #175 = NameAndType        #173:#174     // foreach:(Lscala/Function1;)V
  #176 = InterfaceMethodref #172.#175     // scala/collection/Iterable.foreach:(Lscala/Function1;)V
  #177 = InterfaceMethodref #27.#175      // scala/collection/Iterator.foreach:(Lscala/Function1;)V
  #178 = Utf8               to$extension
  #179 = Utf8               (Lscala/collection/IterableOnce;Lscala/collection/Factory;)Ljava/lang/Object;
  #180 = Utf8               <C1:Ljava/lang/Object;A:Ljava/lang/Object;>(Lscala/collection/IterableOnce<TA;>;Lscala/collection/Factory<TA;TC1;>;)TC1;
  #181 = Utf8               factory
  #182 = Utf8               scala/collection/Factory
  #183 = Class              #182          // scala/collection/Factory
  #184 = Utf8               fromSpecific
  #185 = Utf8               (Lscala/collection/IterableOnce;)Ljava/lang/Object;
  #186 = NameAndType        #184:#185     // fromSpecific:(Lscala/collection/IterableOnce;)Ljava/lang/Object;
  #187 = InterfaceMethodref #183.#186     // scala/collection/Factory.fromSpecific:(Lscala/collection/IterableOnce;)Ljava/lang/Object;
  #188 = Utf8               Lscala/collection/Factory;
  #189 = Utf8               toBuffer$extension
  #190 = Utf8               (Lscala/collection/IterableOnce;)Lscala/collection/mutable/Buffer;
  #191 = Utf8               <B:Ljava/lang/Object;A:Ljava/lang/Object;>(Lscala/collection/IterableOnce<TA;>;)Lscala/collection/mutable/Buffer<TB;>;
  #192 = Utf8               scala/collection/mutable/ArrayBuffer$
  #193 = Class              #192          // scala/collection/mutable/ArrayBuffer$
  #194 = Utf8               Lscala/collection/mutable/ArrayBuffer$;
  #195 = NameAndType        #6:#194       // MODULE$:Lscala/collection/mutable/ArrayBuffer$;
  #196 = Fieldref           #193.#195     // scala/collection/mutable/ArrayBuffer$.MODULE$:Lscala/collection/mutable/ArrayBuffer$;
  #197 = Utf8               from
  #198 = Utf8               (Lscala/collection/IterableOnce;)Lscala/collection/mutable/ArrayBuffer;
  #199 = NameAndType        #197:#198     // from:(Lscala/collection/IterableOnce;)Lscala/collection/mutable/ArrayBuffer;
  #200 = Methodref          #193.#199     // scala/collection/mutable/ArrayBuffer$.from:(Lscala/collection/IterableOnce;)Lscala/collection/mutable/ArrayBuffer;
  #201 = Utf8               toArray$extension
  #202 = Utf8               (Lscala/collection/IterableOnce;Lscala/reflect/ClassTag;)Ljava/lang/Object;
  #203 = Utf8               <B:Ljava/lang/Object;A:Ljava/lang/Object;>(Lscala/collection/IterableOnce<TA;>;Lscala/reflect/ClassTag<TB;>;)Ljava/lang/Object;
  #204 = Utf8               evidence$1
  #205 = Utf8               toArray
  #206 = Utf8               (Lscala/reflect/ClassTag;)Ljava/lang/Object;
  #207 = NameAndType        #205:#206     // toArray:(Lscala/reflect/ClassTag;)Ljava/lang/Object;
  #208 = InterfaceMethodref #172.#207     // scala/collection/Iterable.toArray:(Lscala/reflect/ClassTag;)Ljava/lang/Object;
  #209 = InterfaceMethodref #27.#207      // scala/collection/Iterator.toArray:(Lscala/reflect/ClassTag;)Ljava/lang/Object;
  #210 = Utf8               Lscala/reflect/ClassTag;
  #211 = Utf8               toList$extension
  #212 = Utf8               (Lscala/collection/IterableOnce;)Lscala/collection/immutable/List;
  #213 = Utf8               <A:Ljava/lang/Object;>(Lscala/collection/IterableOnce<TA;>;)Lscala/collection/immutable/List<TA;>;
  #214 = Utf8               scala/collection/immutable/List$
  #215 = Class              #214          // scala/collection/immutable/List$
  #216 = Utf8               Lscala/collection/immutable/List$;
  #217 = NameAndType        #6:#216       // MODULE$:Lscala/collection/immutable/List$;
  #218 = Fieldref           #215.#217     // scala/collection/immutable/List$.MODULE$:Lscala/collection/immutable/List$;
  #219 = Utf8               scala/collection/immutable/Nil$
  #220 = Class              #219          // scala/collection/immutable/Nil$
  #221 = Utf8               Lscala/collection/immutable/Nil$;
  #222 = NameAndType        #6:#221       // MODULE$:Lscala/collection/immutable/Nil$;
  #223 = Fieldref           #220.#222     // scala/collection/immutable/Nil$.MODULE$:Lscala/collection/immutable/Nil$;
  #224 = Utf8               prependedAll
  #225 = NameAndType        #224:#212     // prependedAll:(Lscala/collection/IterableOnce;)Lscala/collection/immutable/List;
  #226 = Methodref          #220.#225     // scala/collection/immutable/Nil$.prependedAll:(Lscala/collection/IterableOnce;)Lscala/collection/immutable/List;
  #227 = Utf8               toSet$extension
  #228 = Utf8               (Lscala/collection/IterableOnce;)Lscala/collection/immutable/Set;
  #229 = Utf8               <B:Ljava/lang/Object;A:Ljava/lang/Object;>(Lscala/collection/IterableOnce<TA;>;)Lscala/collection/immutable/Set<TB;>;
  #230 = Utf8               scala/collection/immutable/Set$
  #231 = Class              #230          // scala/collection/immutable/Set$
  #232 = Utf8               Lscala/collection/immutable/Set$;
  #233 = NameAndType        #6:#232       // MODULE$:Lscala/collection/immutable/Set$;
  #234 = Fieldref           #231.#233     // scala/collection/immutable/Set$.MODULE$:Lscala/collection/immutable/Set$;
  #235 = NameAndType        #197:#228     // from:(Lscala/collection/IterableOnce;)Lscala/collection/immutable/Set;
  #236 = Methodref          #231.#235     // scala/collection/immutable/Set$.from:(Lscala/collection/IterableOnce;)Lscala/collection/immutable/Set;
  #237 = Utf8               toTraversable$extension
  #238 = Utf8               (Lscala/collection/IterableOnce;)Lscala/collection/Iterable;
  #239 = Utf8               <A:Ljava/lang/Object;>(Lscala/collection/IterableOnce<TA;>;)Lscala/collection/Iterable<TA;>;
  #240 = Utf8               scala/collection/Iterable$
  #241 = Class              #240          // scala/collection/Iterable$
  #242 = Utf8               Lscala/collection/Iterable$;
  #243 = NameAndType        #6:#242       // MODULE$:Lscala/collection/Iterable$;
  #244 = Fieldref           #241.#243     // scala/collection/Iterable$.MODULE$:Lscala/collection/Iterable$;
  #245 = NameAndType        #197:#185     // from:(Lscala/collection/IterableOnce;)Ljava/lang/Object;
  #246 = Methodref          #241.#245     // scala/collection/Iterable$.from:(Lscala/collection/IterableOnce;)Ljava/lang/Object;
  #247 = Utf8               toIterable$extension
  #248 = Utf8               toSeq$extension
  #249 = Utf8               (Lscala/collection/IterableOnce;)Lscala/collection/immutable/Seq;
  #250 = Utf8               <A:Ljava/lang/Object;>(Lscala/collection/IterableOnce<TA;>;)Lscala/collection/immutable/Seq<TA;>;
  #251 = Utf8               scala/collection/immutable/Seq$
  #252 = Class              #251          // scala/collection/immutable/Seq$
  #253 = Utf8               Lscala/collection/immutable/Seq$;
  #254 = NameAndType        #6:#253       // MODULE$:Lscala/collection/immutable/Seq$;
  #255 = Fieldref           #252.#254     // scala/collection/immutable/Seq$.MODULE$:Lscala/collection/immutable/Seq$;
  #256 = NameAndType        #197:#249     // from:(Lscala/collection/IterableOnce;)Lscala/collection/immutable/Seq;
  #257 = Methodref          #252.#256     // scala/collection/immutable/Seq$.from:(Lscala/collection/IterableOnce;)Lscala/collection/immutable/Seq;
  #258 = Utf8               toStream$extension
  #259 = Utf8               (Lscala/collection/IterableOnce;)Lscala/collection/immutable/Stream;
  #260 = Utf8               <A:Ljava/lang/Object;>(Lscala/collection/IterableOnce<TA;>;)Lscala/collection/immutable/Stream<TA;>;
  #261 = Utf8               scala/collection/immutable/Stream$
  #262 = Class              #261          // scala/collection/immutable/Stream$
  #263 = Utf8               Lscala/collection/immutable/Stream$;
  #264 = NameAndType        #6:#263       // MODULE$:Lscala/collection/immutable/Stream$;
  #265 = Fieldref           #262.#264     // scala/collection/immutable/Stream$.MODULE$:Lscala/collection/immutable/Stream$;
  #266 = NameAndType        #197:#259     // from:(Lscala/collection/IterableOnce;)Lscala/collection/immutable/Stream;
  #267 = Methodref          #262.#266     // scala/collection/immutable/Stream$.from:(Lscala/collection/IterableOnce;)Lscala/collection/immutable/Stream;
  #268 = Utf8               toVector$extension
  #269 = Utf8               (Lscala/collection/IterableOnce;)Lscala/collection/immutable/Vector;
  #270 = Utf8               <A:Ljava/lang/Object;>(Lscala/collection/IterableOnce<TA;>;)Lscala/collection/immutable/Vector<TA;>;
  #271 = Utf8               scala/collection/immutable/Vector$
  #272 = Class              #271          // scala/collection/immutable/Vector$
  #273 = Utf8               Lscala/collection/immutable/Vector$;
  #274 = NameAndType        #6:#273       // MODULE$:Lscala/collection/immutable/Vector$;
  #275 = Fieldref           #272.#274     // scala/collection/immutable/Vector$.MODULE$:Lscala/collection/immutable/Vector$;
  #276 = NameAndType        #197:#269     // from:(Lscala/collection/IterableOnce;)Lscala/collection/immutable/Vector;
  #277 = Methodref          #272.#276     // scala/collection/immutable/Vector$.from:(Lscala/collection/IterableOnce;)Lscala/collection/immutable/Vector;
  #278 = Utf8               toMap$extension
  #279 = Utf8               (Lscala/collection/IterableOnce;Lscala/$less$colon$less;)Lscala/collection/immutable/Map;
  #280 = Utf8               <K:Ljava/lang/Object;V:Ljava/lang/Object;A:Ljava/lang/Object;>(Lscala/collection/IterableOnce<TA;>;Lscala/$less$colon$less<TA;Lscala/Tuple2<TK;TV;>;>;)Lscala/collection/immutable/Map<TK;TV;>;
  #281 = Utf8               ev
  #282 = Utf8               scala/collection/immutable/Map$
  #283 = Class              #282          // scala/collection/immutable/Map$
  #284 = Utf8               Lscala/collection/immutable/Map$;
  #285 = NameAndType        #6:#284       // MODULE$:Lscala/collection/immutable/Map$;
  #286 = Fieldref           #283.#285     // scala/collection/immutable/Map$.MODULE$:Lscala/collection/immutable/Map$;
  #287 = Utf8               (Lscala/collection/IterableOnce;)Lscala/collection/immutable/Map;
  #288 = NameAndType        #197:#287     // from:(Lscala/collection/IterableOnce;)Lscala/collection/immutable/Map;
  #289 = Methodref          #283.#288     // scala/collection/immutable/Map$.from:(Lscala/collection/IterableOnce;)Lscala/collection/immutable/Map;
  #290 = Utf8               Lscala/$less$colon$less;
  #291 = Utf8               toIterator$extension
  #292 = Utf8               (Lscala/collection/IterableOnce;)Lscala/collection/Iterator;
  #293 = Utf8               <A:Ljava/lang/Object;>(Lscala/collection/IterableOnce<TA;>;)Lscala/collection/Iterator<TA;>;
  #294 = Utf8               isEmpty$extension
  #295 = Utf8               isEmpty
  #296 = NameAndType        #295:#56      // isEmpty:()Z
  #297 = InterfaceMethodref #172.#296     // scala/collection/Iterable.isEmpty:()Z
  #298 = InterfaceMethodref #27.#296      // scala/collection/Iterator.isEmpty:()Z
  #299 = Utf8               mkString$extension
  #300 = Utf8               (Lscala/collection/IterableOnce;Ljava/lang/String;Ljava/lang/String;Ljava/lang/String;)Ljava/lang/String;
  #301 = Utf8               <A:Ljava/lang/Object;>(Lscala/collection/IterableOnce<TA;>;Ljava/lang/String;Ljava/lang/String;Ljava/lang/String;)Ljava/lang/String;
  #302 = Utf8               start
  #303 = Utf8               sep
  #304 = Utf8               end
  #305 = Utf8               mkString
  #306 = Utf8               (Ljava/lang/String;Ljava/lang/String;Ljava/lang/String;)Ljava/lang/String;
  #307 = NameAndType        #305:#306     // mkString:(Ljava/lang/String;Ljava/lang/String;Ljava/lang/String;)Ljava/lang/String;
  #308 = InterfaceMethodref #172.#307     // scala/collection/Iterable.mkString:(Ljava/lang/String;Ljava/lang/String;Ljava/lang/String;)Ljava/lang/String;
  #309 = InterfaceMethodref #27.#307      // scala/collection/Iterator.mkString:(Ljava/lang/String;Ljava/lang/String;Ljava/lang/String;)Ljava/lang/String;
  #310 = Utf8               Ljava/lang/String;
  #311 = Utf8               java/lang/String
  #312 = Class              #311          // java/lang/String
  #313 = Utf8               (Lscala/collection/IterableOnce;Ljava/lang/String;)Ljava/lang/String;
  #314 = Utf8               <A:Ljava/lang/Object;>(Lscala/collection/IterableOnce<TA;>;Ljava/lang/String;)Ljava/lang/String;
  #315 = Utf8
  #316 = String             #315          //
  #317 = Utf8               scala/collection/IterableOnceOps
  #318 = Class              #317          // scala/collection/IterableOnceOps
  #319 = InterfaceMethodref #318.#307     // scala/collection/IterableOnceOps.mkString:(Ljava/lang/String;Ljava/lang/String;Ljava/lang/String;)Ljava/lang/String;
  #320 = Utf8               (Lscala/collection/IterableOnce;)Ljava/lang/String;
  #321 = Utf8               <A:Ljava/lang/Object;>(Lscala/collection/IterableOnce<TA;>;)Ljava/lang/String;
  #322 = Utf8               mkString_mkString_sep
  #323 = Utf8               mkString_this
  #324 = Utf8               find$extension
  #325 = Utf8               (Lscala/collection/IterableOnce;Lscala/Function1;)Lscala/Option;
  #326 = Utf8               <A:Ljava/lang/Object;>(Lscala/collection/IterableOnce<TA;>;Lscala/Function1<TA;Ljava/lang/Object;>;)Lscala/Option<TA;>;
  #327 = Utf8               p
  #328 = Utf8               find
  #329 = Utf8               (Lscala/Function1;)Lscala/Option;
  #330 = NameAndType        #328:#329     // find:(Lscala/Function1;)Lscala/Option;
  #331 = InterfaceMethodref #27.#330      // scala/collection/Iterator.find:(Lscala/Function1;)Lscala/Option;
  #332 = Utf8               foldLeft$extension
  #333 = Utf8               (Lscala/collection/IterableOnce;Ljava/lang/Object;Lscala/Function2;)Ljava/lang/Object;
  #334 = Utf8               <B:Ljava/lang/Object;A:Ljava/lang/Object;>(Lscala/collection/IterableOnce<TA;>;TB;Lscala/Function2<TB;TA;TB;>;)TB;
  #335 = Utf8               z
  #336 = Utf8               op
  #337 = Utf8               foldLeft
  #338 = Utf8               (Ljava/lang/Object;Lscala/Function2;)Ljava/lang/Object;
  #339 = NameAndType        #337:#338     // foldLeft:(Ljava/lang/Object;Lscala/Function2;)Ljava/lang/Object;
  #340 = InterfaceMethodref #27.#339      // scala/collection/Iterator.foldLeft:(Ljava/lang/Object;Lscala/Function2;)Ljava/lang/Object;
  #341 = Utf8               Ljava/lang/Object;
  #342 = Utf8               foldRight$extension
  #343 = Utf8               <B:Ljava/lang/Object;A:Ljava/lang/Object;>(Lscala/collection/IterableOnce<TA;>;TB;Lscala/Function2<TA;TB;TB;>;)TB;
  #344 = Utf8               foldRight
  #345 = NameAndType        #344:#338     // foldRight:(Ljava/lang/Object;Lscala/Function2;)Ljava/lang/Object;
  #346 = InterfaceMethodref #27.#345      // scala/collection/Iterator.foldRight:(Ljava/lang/Object;Lscala/Function2;)Ljava/lang/Object;
  #347 = Utf8               fold$extension
  #348 = Utf8               <A1:Ljava/lang/Object;A:Ljava/lang/Object;>(Lscala/collection/IterableOnce<TA;>;TA1;Lscala/Function2<TA1;TA1;TA1;>;)TA1;
  #349 = Utf8               fold
  #350 = NameAndType        #349:#338     // fold:(Ljava/lang/Object;Lscala/Function2;)Ljava/lang/Object;
  #351 = InterfaceMethodref #27.#350      // scala/collection/Iterator.fold:(Ljava/lang/Object;Lscala/Function2;)Ljava/lang/Object;
  #352 = Utf8               $div$colon$extension
  #353 = Utf8               $colon$bslash$extension
  #354 = Utf8               map$extension
  #355 = Utf8               (Lscala/collection/IterableOnce;Lscala/Function1;)Lscala/collection/IterableOnce;
  #356 = Utf8               <B:Ljava/lang/Object;A:Ljava/lang/Object;>(Lscala/collection/IterableOnce<TA;>;Lscala/Function1<TA;TB;>;)Lscala/collection/IterableOnce<TB;>;
  #357 = Utf8               map
  #358 = Utf8               (Lscala/Function1;)Ljava/lang/Object;
  #359 = NameAndType        #357:#358     // map:(Lscala/Function1;)Ljava/lang/Object;
  #360 = InterfaceMethodref #172.#359     // scala/collection/Iterable.map:(Lscala/Function1;)Ljava/lang/Object;
  #361 = NameAndType        #357:#29      // map:(Lscala/Function1;)Lscala/collection/Iterator;
  #362 = InterfaceMethodref #27.#361      // scala/collection/Iterator.map:(Lscala/Function1;)Lscala/collection/Iterator;
  #363 = Utf8               flatMap$extension
  #364 = Utf8               <B:Ljava/lang/Object;A:Ljava/lang/Object;>(Lscala/collection/IterableOnce<TA;>;Lscala/Function1<TA;Lscala/collection/IterableOnce<TB;>;>;)Lscala/collection/IterableOnce<TB;>;
  #365 = Utf8               flatMap
  #366 = NameAndType        #365:#358     // flatMap:(Lscala/Function1;)Ljava/lang/Object;
  #367 = InterfaceMethodref #172.#366     // scala/collection/Iterable.flatMap:(Lscala/Function1;)Ljava/lang/Object;
  #368 = NameAndType        #365:#29      // flatMap:(Lscala/Function1;)Lscala/collection/Iterator;
  #369 = InterfaceMethodref #27.#368      // scala/collection/Iterator.flatMap:(Lscala/Function1;)Lscala/collection/Iterator;
  #370 = Utf8               sameElements$extension
  #371 = Utf8               (Lscala/collection/IterableOnce;Lscala/collection/IterableOnce;)Z
  #372 = Utf8               <B:Ljava/lang/Object;A:Ljava/lang/Object;>(Lscala/collection/IterableOnce<TA;>;Lscala/collection/IterableOnce<TB;>;)Z
  #373 = Utf8               that
  #374 = Utf8               sameElements
  #375 = NameAndType        #374:#53      // sameElements:(Lscala/collection/IterableOnce;)Z
  #376 = InterfaceMethodref #27.#375      // scala/collection/Iterator.sameElements:(Lscala/collection/IterableOnce;)Z
  #377 = Utf8               hashCode$extension
  #378 = Utf8               hashCode
  #379 = NameAndType        #378:#114     // hashCode:()I
  #380 = Methodref          #4.#379       // java/lang/Object.hashCode:()I
  #381 = Utf8               equals$extension
  #382 = Utf8               (Lscala/collection/IterableOnce;Ljava/lang/Object;)Z
  #383 = Utf8               <A:Ljava/lang/Object;>(Lscala/collection/IterableOnce<TA;>;Ljava/lang/Object;)Z
  #384 = Utf8               x$1
  #385 = Utf8               scala/collection/IterableOnceExtensionMethods
  #386 = Class              #385          // scala/collection/IterableOnceExtensionMethods
  #387 = Utf8               scala$collection$IterableOnceExtensionMethods$$it
  #388 = Utf8               ()Lscala/collection/IterableOnce;
  #389 = NameAndType        #387:#388     // scala$collection$IterableOnceExtensionMethods$$it:()Lscala/collection/IterableOnce;
  #390 = Methodref          #386.#389     // scala/collection/IterableOnceExtensionMethods.scala$collection$IterableOnceExtensionMethods$$it:()Lscala/collection/IterableOnce;
  #391 = Utf8               equals
  #392 = Utf8               (Ljava/lang/Object;)Z
  #393 = NameAndType        #391:#392     // equals:(Ljava/lang/Object;)Z
  #394 = Methodref          #4.#393       // java/lang/Object.equals:(Ljava/lang/Object;)Z
  #395 = Methodref          #4.#11        // java/lang/Object."<init>":()V
  #396 = Utf8               Code
  #397 = Utf8               LineNumberTable
  #398 = Utf8               LocalVariableTable
  #399 = Utf8               Signature
  #400 = Utf8               Deprecated
  #401 = Utf8               MethodParameters
  #402 = Utf8               StackMapTable
  #403 = Utf8               SourceFile
  #404 = Utf8               ScalaInlineInfo
  #405 = Utf8               Scala
{
  public static final scala.collection.IterableOnceExtensionMethods$ MODULE$;
    descriptor: Lscala/collection/IterableOnceExtensionMethods$;
    flags: (0x0019) ACC_PUBLIC, ACC_STATIC, ACC_FINAL

  public static {};
    descriptor: ()V
    flags: (0x0009) ACC_PUBLIC, ACC_STATIC
    Code:
      stack=2, locals=0, args_size=0
         0: new           #2                  // class scala/collection/IterableOnceExtensionMethods$
         3: dup
         4: invokespecial #12                 // Method "<init>":()V
         7: putstatic     #14                 // Field MODULE$:Lscala/collection/IterableOnceExtensionMethods$;
        10: return
      LineNumberTable:
        line 83: 0

  public final <A extends java.lang.Object> scala.collection.Iterator<A> withFilter$extension(scala.collection.IterableOnce<A>, scala.Function1<A, java.lang.Object>);
    descriptor: (Lscala/collection/IterableOnce;Lscala/Function1;)Lscala/collection/Iterator;
    flags: (0x0011) ACC_PUBLIC, ACC_FINAL
    Code:
      stack=2, locals=3, args_size=3
         0: aload_1
         1: invokeinterface #25,  1           // InterfaceMethod scala/collection/IterableOnce.iterator:()Lscala/collection/Iterator;
         6: aload_2
         7: invokeinterface #31,  2           // InterfaceMethod scala/collection/Iterator.withFilter:(Lscala/Function1;)Lscala/collection/Iterator;
        12: areturn
      LineNumberTable:
        line 85: 0
      LocalVariableTable:
        Start  Length  Slot  Name   Signature
            0      13     0  this   Lscala/collection/IterableOnceExtensionMethods$;
            0      13     1 $this   Lscala/collection/IterableOnce;
            0      13     2     f   Lscala/Function1;
    Signature: #17                          // <A:Ljava/lang/Object;>(Lscala/collection/IterableOnce<TA;>;Lscala/Function1<TA;Ljava/lang/Object;>;)Lscala/collection/Iterator<TA;>;
    Deprecated: true
    MethodParameters:
      Name                           Flags
      $this                          final
      f                              final

  public final <A extends java.lang.Object> scala.Option<A> reduceLeftOption$extension(scala.collection.IterableOnce<A>, scala.Function2<A, A, A>);
    descriptor: (Lscala/collection/IterableOnce;Lscala/Function2;)Lscala/Option;
    flags: (0x0011) ACC_PUBLIC, ACC_FINAL
    Code:
      stack=2, locals=3, args_size=3
         0: aload_1
         1: invokeinterface #25,  1           // InterfaceMethod scala/collection/IterableOnce.iterator:()Lscala/collection/Iterator;
         6: aload_2
         7: invokeinterface #41,  2           // InterfaceMethod scala/collection/Iterator.reduceLeftOption:(Lscala/Function2;)Lscala/Option;
        12: areturn
      LineNumberTable:
        line 88: 0
      LocalVariableTable:
        Start  Length  Slot  Name   Signature
            0      13     0  this   Lscala/collection/IterableOnceExtensionMethods$;
            0      13     1 $this   Lscala/collection/IterableOnce;
            0      13     2     f   Lscala/Function2;
    Signature: #37                          // <A:Ljava/lang/Object;>(Lscala/collection/IterableOnce<TA;>;Lscala/Function2<TA;TA;TA;>;)Lscala/Option<TA;>;
    Deprecated: true
    MethodParameters:
      Name                           Flags
      $this                          final
      f                              final

  public final <A extends java.lang.Object> A min$extension(scala.collection.IterableOnce<A>, scala.math.Ordering<A>);
    descriptor: (Lscala/collection/IterableOnce;Lscala/math/Ordering;)Ljava/lang/Object;
    flags: (0x0011) ACC_PUBLIC, ACC_FINAL
    Code:
      stack=2, locals=3, args_size=3
         0: aload_1
         1: invokeinterface #25,  1           // InterfaceMethod scala/collection/IterableOnce.iterator:()Lscala/collection/Iterator;
         6: aload_2
         7: invokeinterface #50,  2           // InterfaceMethod scala/collection/Iterator.min:(Lscala/math/Ordering;)Ljava/lang/Object;
        12: areturn
      LineNumberTable:
        line 91: 0
      LocalVariableTable:
        Start  Length  Slot  Name   Signature
            0      13     0  this   Lscala/collection/IterableOnceExtensionMethods$;
            0      13     1 $this   Lscala/collection/IterableOnce;
            0      13     2   ord   Lscala/math/Ordering;
    Signature: #45                          // <A:Ljava/lang/Object;>(Lscala/collection/IterableOnce<TA;>;Lscala/math/Ordering<TA;>;)TA;
    Deprecated: true
    MethodParameters:
      Name                           Flags
      $this                          final
      ord                            final

  public final <A extends java.lang.Object> boolean nonEmpty$extension(scala.collection.IterableOnce<A>);
    descriptor: (Lscala/collection/IterableOnce;)Z
    flags: (0x0011) ACC_PUBLIC, ACC_FINAL
    Code:
      stack=1, locals=2, args_size=2
         0: aload_1
         1: invokeinterface #25,  1           // InterfaceMethod scala/collection/IterableOnce.iterator:()Lscala/collection/Iterator;
         6: invokeinterface #58,  1           // InterfaceMethod scala/collection/Iterator.nonEmpty:()Z
        11: ireturn
      LineNumberTable:
        line 94: 0
      LocalVariableTable:
        Start  Length  Slot  Name   Signature
            0      12     0  this   Lscala/collection/IterableOnceExtensionMethods$;
            0      12     1 $this   Lscala/collection/IterableOnce;
    Signature: #54                          // <A:Ljava/lang/Object;>(Lscala/collection/IterableOnce<TA;>;)Z
    Deprecated: true
    MethodParameters:
      Name                           Flags
      $this                          final

  public final <A extends java.lang.Object> A max$extension(scala.collection.IterableOnce<A>, scala.math.Ordering<A>);
    descriptor: (Lscala/collection/IterableOnce;Lscala/math/Ordering;)Ljava/lang/Object;
    flags: (0x0011) ACC_PUBLIC, ACC_FINAL
    Code:
      stack=2, locals=3, args_size=3
         0: aload_1
         1: invokeinterface #25,  1           // InterfaceMethod scala/collection/IterableOnce.iterator:()Lscala/collection/Iterator;
         6: aload_2
         7: invokeinterface #62,  2           // InterfaceMethod scala/collection/Iterator.max:(Lscala/math/Ordering;)Ljava/lang/Object;
        12: areturn
      LineNumberTable:
        line 97: 0
      LocalVariableTable:
        Start  Length  Slot  Name   Signature
            0      13     0  this   Lscala/collection/IterableOnceExtensionMethods$;
            0      13     1 $this   Lscala/collection/IterableOnce;
            0      13     2   ord   Lscala/math/Ordering;
    Signature: #45                          // <A:Ljava/lang/Object;>(Lscala/collection/IterableOnce<TA;>;Lscala/math/Ordering<TA;>;)TA;
    Deprecated: true
    MethodParameters:
      Name                           Flags
      $this                          final
      ord                            final

  public final <A extends java.lang.Object> A reduceRight$extension(scala.collection.IterableOnce<A>, scala.Function2<A, A, A>);
    descriptor: (Lscala/collection/IterableOnce;Lscala/Function2;)Ljava/lang/Object;
    flags: (0x0011) ACC_PUBLIC, ACC_FINAL
    Code:
      stack=2, locals=3, args_size=3
         0: aload_1
         1: invokeinterface #25,  1           // InterfaceMethod scala/collection/IterableOnce.iterator:()Lscala/collection/Iterator;
         6: aload_2
         7: invokeinterface #69,  2           // InterfaceMethod scala/collection/Iterator.reduceRight:(Lscala/Function2;)Ljava/lang/Object;
        12: areturn
      LineNumberTable:
        line 100: 0
      LocalVariableTable:
        Start  Length  Slot  Name   Signature
            0      13     0  this   Lscala/collection/IterableOnceExtensionMethods$;
            0      13     1 $this   Lscala/collection/IterableOnce;
            0      13     2     f   Lscala/Function2;
    Signature: #65                          // <A:Ljava/lang/Object;>(Lscala/collection/IterableOnce<TA;>;Lscala/Function2<TA;TA;TA;>;)TA;
    Deprecated: true
    MethodParameters:
      Name                           Flags
      $this                          final
      f                              final

  public final <B extends java.lang.Object, A extends java.lang.Object> A maxBy$extension(scala.collection.IterableOnce<A>, scala.Function1<A, B>, scala.math.Ordering<B>);
    descriptor: (Lscala/collection/IterableOnce;Lscala/Function1;Lscala/math/Ordering;)Ljava/lang/Object;
    flags: (0x0011) ACC_PUBLIC, ACC_FINAL
    Code:
      stack=3, locals=4, args_size=4
         0: aload_1
         1: invokeinterface #25,  1           // InterfaceMethod scala/collection/IterableOnce.iterator:()Lscala/collection/Iterator;
         6: aload_2
         7: aload_3
         8: invokeinterface #77,  3           // InterfaceMethod scala/collection/Iterator.maxBy:(Lscala/Function1;Lscala/math/Ordering;)Ljava/lang/Object;
        13: areturn
      LineNumberTable:
        line 103: 0
      LocalVariableTable:
        Start  Length  Slot  Name   Signature
            0      14     0  this   Lscala/collection/IterableOnceExtensionMethods$;
            0      14     1 $this   Lscala/collection/IterableOnce;
            0      14     2     f   Lscala/Function1;
            0      14     3   cmp   Lscala/math/Ordering;
    Signature: #72                          // <B:Ljava/lang/Object;A:Ljava/lang/Object;>(Lscala/collection/IterableOnce<TA;>;Lscala/Function1<TA;TB;>;Lscala/math/Ordering<TB;>;)TA;
    Deprecated: true
    MethodParameters:
      Name                           Flags
      $this                          final
      f                              final
      cmp                            final

  public final <A extends java.lang.Object> A reduceLeft$extension(scala.collection.IterableOnce<A>, scala.Function2<A, A, A>);
    descriptor: (Lscala/collection/IterableOnce;Lscala/Function2;)Ljava/lang/Object;
    flags: (0x0011) ACC_PUBLIC, ACC_FINAL
    Code:
      stack=2, locals=3, args_size=3
         0: aload_1
         1: invokeinterface #25,  1           // InterfaceMethod scala/collection/IterableOnce.iterator:()Lscala/collection/Iterator;
         6: aload_2
         7: invokeinterface #81,  2           // InterfaceMethod scala/collection/Iterator.reduceLeft:(Lscala/Function2;)Ljava/lang/Object;
        12: areturn
      LineNumberTable:
        line 106: 0
      LocalVariableTable:
        Start  Length  Slot  Name   Signature
            0      13     0  this   Lscala/collection/IterableOnceExtensionMethods$;
            0      13     1 $this   Lscala/collection/IterableOnce;
            0      13     2     f   Lscala/Function2;
    Signature: #65                          // <A:Ljava/lang/Object;>(Lscala/collection/IterableOnce<TA;>;Lscala/Function2<TA;TA;TA;>;)TA;
    Deprecated: true
    MethodParameters:
      Name                           Flags
      $this                          final
      f                              final

  public final <A extends java.lang.Object> A sum$extension(scala.collection.IterableOnce<A>, scala.math.Numeric<A>);
    descriptor: (Lscala/collection/IterableOnce;Lscala/math/Numeric;)Ljava/lang/Object;
    flags: (0x0011) ACC_PUBLIC, ACC_FINAL
    Code:
      stack=2, locals=3, args_size=3
         0: aload_1
         1: invokeinterface #25,  1           // InterfaceMethod scala/collection/IterableOnce.iterator:()Lscala/collection/Iterator;
         6: aload_2
         7: invokeinterface #89,  2           // InterfaceMethod scala/collection/Iterator.sum:(Lscala/math/Numeric;)Ljava/lang/Object;
        12: areturn
      LineNumberTable:
        line 109: 0
      LocalVariableTable:
        Start  Length  Slot  Name   Signature
            0      13     0  this   Lscala/collection/IterableOnceExtensionMethods$;
            0      13     1 $this   Lscala/collection/IterableOnce;
            0      13     2   num   Lscala/math/Numeric;
    Signature: #84                          // <A:Ljava/lang/Object;>(Lscala/collection/IterableOnce<TA;>;Lscala/math/Numeric<TA;>;)TA;
    Deprecated: true
    MethodParameters:
      Name                           Flags
      $this                          final
      num                            final

  public final <A extends java.lang.Object> A product$extension(scala.collection.IterableOnce<A>, scala.math.Numeric<A>);
    descriptor: (Lscala/collection/IterableOnce;Lscala/math/Numeric;)Ljava/lang/Object;
    flags: (0x0011) ACC_PUBLIC, ACC_FINAL
    Code:
      stack=2, locals=3, args_size=3
         0: aload_1
         1: invokeinterface #25,  1           // InterfaceMethod scala/collection/IterableOnce.iterator:()Lscala/collection/Iterator;
         6: aload_2
         7: invokeinterface #94,  2           // InterfaceMethod scala/collection/Iterator.product:(Lscala/math/Numeric;)Ljava/lang/Object;
        12: areturn
      LineNumberTable:
        line 112: 0
      LocalVariableTable:
        Start  Length  Slot  Name   Signature
            0      13     0  this   Lscala/collection/IterableOnceExtensionMethods$;
            0      13     1 $this   Lscala/collection/IterableOnce;
            0      13     2   num   Lscala/math/Numeric;
    Signature: #84                          // <A:Ljava/lang/Object;>(Lscala/collection/IterableOnce<TA;>;Lscala/math/Numeric<TA;>;)TA;
    Deprecated: true
    MethodParameters:
      Name                           Flags
      $this                          final
      num                            final

  public final <A extends java.lang.Object> int count$extension(scala.collection.IterableOnce<A>, scala.Function1<A, java.lang.Object>);
    descriptor: (Lscala/collection/IterableOnce;Lscala/Function1;)I
    flags: (0x0011) ACC_PUBLIC, ACC_FINAL
    Code:
      stack=2, locals=3, args_size=3
         0: aload_1
         1: invokeinterface #25,  1           // InterfaceMethod scala/collection/IterableOnce.iterator:()Lscala/collection/Iterator;
         6: aload_2
         7: invokeinterface #101,  2          // InterfaceMethod scala/collection/Iterator.count:(Lscala/Function1;)I
        12: ireturn
      LineNumberTable:
        line 115: 0
      LocalVariableTable:
        Start  Length  Slot  Name   Signature
            0      13     0  this   Lscala/collection/IterableOnceExtensionMethods$;
            0      13     1 $this   Lscala/collection/IterableOnce;
            0      13     2     f   Lscala/Function1;
    Signature: #97                          // <A:Ljava/lang/Object;>(Lscala/collection/IterableOnce<TA;>;Lscala/Function1<TA;Ljava/lang/Object;>;)I
    Deprecated: true
    MethodParameters:
      Name                           Flags
      $this                          final
      f                              final

  public final <A extends java.lang.Object> scala.Option<A> reduceOption$extension(scala.collection.IterableOnce<A>, scala.Function2<A, A, A>);
    descriptor: (Lscala/collection/IterableOnce;Lscala/Function2;)Lscala/Option;
    flags: (0x0011) ACC_PUBLIC, ACC_FINAL
    Code:
      stack=2, locals=3, args_size=3
         0: aload_1
         1: invokeinterface #25,  1           // InterfaceMethod scala/collection/IterableOnce.iterator:()Lscala/collection/Iterator;
         6: aload_2
         7: invokeinterface #105,  2          // InterfaceMethod scala/collection/Iterator.reduceOption:(Lscala/Function2;)Lscala/Option;
        12: areturn
      LineNumberTable:
        line 118: 0
      LocalVariableTable:
        Start  Length  Slot  Name   Signature
            0      13     0  this   Lscala/collection/IterableOnceExtensionMethods$;
            0      13     1 $this   Lscala/collection/IterableOnce;
            0      13     2     f   Lscala/Function2;
    Signature: #37                          // <A:Ljava/lang/Object;>(Lscala/collection/IterableOnce<TA;>;Lscala/Function2<TA;TA;TA;>;)Lscala/Option<TA;>;
    Deprecated: true
    MethodParameters:
      Name                           Flags
      $this                          final
      f                              final

  public final <B extends java.lang.Object, A extends java.lang.Object> A minBy$extension(scala.collection.IterableOnce<A>, scala.Function1<A, B>, scala.math.Ordering<B>);
    descriptor: (Lscala/collection/IterableOnce;Lscala/Function1;Lscala/math/Ordering;)Ljava/lang/Object;
    flags: (0x0011) ACC_PUBLIC, ACC_FINAL
    Code:
      stack=3, locals=4, args_size=4
         0: aload_1
         1: invokeinterface #25,  1           // InterfaceMethod scala/collection/IterableOnce.iterator:()Lscala/collection/Iterator;
         6: aload_2
         7: aload_3
         8: invokeinterface #109,  3          // InterfaceMethod scala/collection/Iterator.minBy:(Lscala/Function1;Lscala/math/Ordering;)Ljava/lang/Object;
        13: areturn
      LineNumberTable:
        line 121: 0
      LocalVariableTable:
        Start  Length  Slot  Name   Signature
            0      14     0  this   Lscala/collection/IterableOnceExtensionMethods$;
            0      14     1 $this   Lscala/collection/IterableOnce;
            0      14     2     f   Lscala/Function1;
            0      14     3   cmp   Lscala/math/Ordering;
    Signature: #72                          // <B:Ljava/lang/Object;A:Ljava/lang/Object;>(Lscala/collection/IterableOnce<TA;>;Lscala/Function1<TA;TB;>;Lscala/math/Ordering<TB;>;)TA;
    Deprecated: true
    MethodParameters:
      Name                           Flags
      $this                          final
      f                              final
      cmp                            final

  public final <A extends java.lang.Object> int size$extension(scala.collection.IterableOnce<A>);
    descriptor: (Lscala/collection/IterableOnce;)I
    flags: (0x0011) ACC_PUBLIC, ACC_FINAL
    Code:
      stack=1, locals=2, args_size=2
         0: aload_1
         1: invokeinterface #25,  1           // InterfaceMethod scala/collection/IterableOnce.iterator:()Lscala/collection/Iterator;
         6: invokeinterface #116,  1          // InterfaceMethod scala/collection/Iterator.size:()I
        11: ireturn
      LineNumberTable:
        line 124: 0
      LocalVariableTable:
        Start  Length  Slot  Name   Signature
            0      12     0  this   Lscala/collection/IterableOnceExtensionMethods$;
            0      12     1 $this   Lscala/collection/IterableOnce;
    Signature: #112                         // <A:Ljava/lang/Object;>(Lscala/collection/IterableOnce<TA;>;)I
    Deprecated: true
    MethodParameters:
      Name                           Flags
      $this                          final

  public final <A extends java.lang.Object> boolean forall$extension(scala.collection.IterableOnce<A>, scala.Function1<A, java.lang.Object>);
    descriptor: (Lscala/collection/IterableOnce;Lscala/Function1;)Z
    flags: (0x0011) ACC_PUBLIC, ACC_FINAL
    Code:
      stack=2, locals=3, args_size=3
         0: aload_1
         1: invokeinterface #25,  1           // InterfaceMethod scala/collection/IterableOnce.iterator:()Lscala/collection/Iterator;
         6: aload_2
         7: invokeinterface #123,  2          // InterfaceMethod scala/collection/Iterator.forall:(Lscala/Function1;)Z
        12: ireturn
      LineNumberTable:
        line 127: 0
      LocalVariableTable:
        Start  Length  Slot  Name   Signature
            0      13     0  this   Lscala/collection/IterableOnceExtensionMethods$;
            0      13     1 $this   Lscala/collection/IterableOnce;
            0      13     2     f   Lscala/Function1;
    Signature: #119                         // <A:Ljava/lang/Object;>(Lscala/collection/IterableOnce<TA;>;Lscala/Function1<TA;Ljava/lang/Object;>;)Z
    Deprecated: true
    MethodParameters:
      Name                           Flags
      $this                          final
      f                              final

  public final <B extends java.lang.Object, A extends java.lang.Object> scala.Option<B> collectFirst$extension(scala.collection.IterableOnce<A>, scala.PartialFunction<A, B>);
    descriptor: (Lscala/collection/IterableOnce;Lscala/PartialFunction;)Lscala/Option;
    flags: (0x0011) ACC_PUBLIC, ACC_FINAL
    Code:
      stack=2, locals=3, args_size=3
         0: aload_1
         1: invokeinterface #25,  1           // InterfaceMethod scala/collection/IterableOnce.iterator:()Lscala/collection/Iterator;
         6: aload_2
         7: invokeinterface #130,  2          // InterfaceMethod scala/collection/Iterator.collectFirst:(Lscala/PartialFunction;)Lscala/Option;
        12: areturn
      LineNumberTable:
        line 130: 0
      LocalVariableTable:
        Start  Length  Slot  Name   Signature
            0      13     0  this   Lscala/collection/IterableOnceExtensionMethods$;
            0      13     1 $this   Lscala/collection/IterableOnce;
            0      13     2     f   Lscala/PartialFunction;
    Signature: #126                         // <B:Ljava/lang/Object;A:Ljava/lang/Object;>(Lscala/collection/IterableOnce<TA;>;Lscala/PartialFunction<TA;TB;>;)Lscala/Option<TB;>;
    Deprecated: true
    MethodParameters:
      Name                           Flags
      $this                          final
      f                              final

  public final <A extends java.lang.Object> scala.collection.Iterator<A> filter$extension(scala.collection.IterableOnce<A>, scala.Function1<A, java.lang.Object>);
    descriptor: (Lscala/collection/IterableOnce;Lscala/Function1;)Lscala/collection/Iterator;
    flags: (0x0011) ACC_PUBLIC, ACC_FINAL
    Code:
      stack=2, locals=3, args_size=3
         0: aload_1
         1: invokeinterface #25,  1           // InterfaceMethod scala/collection/IterableOnce.iterator:()Lscala/collection/Iterator;
         6: aload_2
         7: invokeinterface #135,  2          // InterfaceMethod scala/collection/Iterator.filter:(Lscala/Function1;)Lscala/collection/Iterator;
        12: areturn
      LineNumberTable:
        line 133: 0
      LocalVariableTable:
        Start  Length  Slot  Name   Signature
            0      13     0  this   Lscala/collection/IterableOnceExtensionMethods$;
            0      13     1 $this   Lscala/collection/IterableOnce;
            0      13     2     f   Lscala/Function1;
    Signature: #17                          // <A:Ljava/lang/Object;>(Lscala/collection/IterableOnce<TA;>;Lscala/Function1<TA;Ljava/lang/Object;>;)Lscala/collection/Iterator<TA;>;
    Deprecated: true
    MethodParameters:
      Name                           Flags
      $this                          final
      f                              final

  public final <A extends java.lang.Object> boolean exists$extension(scala.collection.IterableOnce<A>, scala.Function1<A, java.lang.Object>);
    descriptor: (Lscala/collection/IterableOnce;Lscala/Function1;)Z
    flags: (0x0011) ACC_PUBLIC, ACC_FINAL
    Code:
      stack=2, locals=3, args_size=3
         0: aload_1
         1: invokeinterface #25,  1           // InterfaceMethod scala/collection/IterableOnce.iterator:()Lscala/collection/Iterator;
         6: aload_2
         7: invokeinterface #139,  2          // InterfaceMethod scala/collection/Iterator.exists:(Lscala/Function1;)Z
        12: ireturn
      LineNumberTable:
        line 136: 0
      LocalVariableTable:
        Start  Length  Slot  Name   Signature
            0      13     0  this   Lscala/collection/IterableOnceExtensionMethods$;
            0      13     1 $this   Lscala/collection/IterableOnce;
            0      13     2     f   Lscala/Function1;
    Signature: #119                         // <A:Ljava/lang/Object;>(Lscala/collection/IterableOnce<TA;>;Lscala/Function1<TA;Ljava/lang/Object;>;)Z
    Deprecated: true
    MethodParameters:
      Name                           Flags
      $this                          final
      f                              final

  public final <A extends java.lang.Object> void copyToBuffer$extension(scala.collection.IterableOnce<A>, scala.collection.mutable.Buffer<A>);
    descriptor: (Lscala/collection/IterableOnce;Lscala/collection/mutable/Buffer;)V
    flags: (0x0011) ACC_PUBLIC, ACC_FINAL
    Code:
      stack=2, locals=4, args_size=3
         0: aload_1
         1: invokeinterface #25,  1           // InterfaceMethod scala/collection/IterableOnce.iterator:()Lscala/collection/Iterator;
         6: dup
         7: ifnonnull     12
        10: aconst_null
        11: athrow
        12: astore_3
        13: aload_2
        14: ifnonnull     19
        17: aconst_null
        18: athrow
        19: aload_2
        20: aload_3
        21: invokeinterface #149,  2          // InterfaceMethod scala/collection/mutable/Growable.addAll:(Lscala/collection/IterableOnce;)Lscala/collection/mutable/Growable;
        26: pop
        27: return
      StackMapTable: number_of_entries = 2
        frame_type = 76 /* same_locals_1_stack_item */
          stack = [ class scala/collection/Iterator ]
        frame_type = 252 /* append */
          offset_delta = 6
          locals = [ class scala/collection/Iterator ]
      LineNumberTable:
        line 139: 0
        line 819: 13
        line 139: 27
      LocalVariableTable:
        Start  Length  Slot  Name   Signature
            0      28     0  this   Lscala/collection/IterableOnceExtensionMethods$;
            0      28     1 $this   Lscala/collection/IterableOnce;
            0      28     2  dest   Lscala/collection/mutable/Buffer;
           13      14     3 copyToBuffer_this   Lscala/collection/IterableOnceOps;
    Signature: #142                         // <A:Ljava/lang/Object;>(Lscala/collection/IterableOnce<TA;>;Lscala/collection/mutable/Buffer<TA;>;)V
    Deprecated: true
    MethodParameters:
      Name                           Flags
      $this                          final
      dest                           final

  public final <A extends java.lang.Object> A reduce$extension(scala.collection.IterableOnce<A>, scala.Function2<A, A, A>);
    descriptor: (Lscala/collection/IterableOnce;Lscala/Function2;)Ljava/lang/Object;
    flags: (0x0011) ACC_PUBLIC, ACC_FINAL
    Code:
      stack=2, locals=3, args_size=3
         0: aload_1
         1: invokeinterface #25,  1           // InterfaceMethod scala/collection/IterableOnce.iterator:()Lscala/collection/Iterator;
         6: aload_2
         7: invokeinterface #156,  2          // InterfaceMethod scala/collection/Iterator.reduce:(Lscala/Function2;)Ljava/lang/Object;
        12: areturn
      LineNumberTable:
        line 142: 0
      LocalVariableTable:
        Start  Length  Slot  Name   Signature
            0      13     0  this   Lscala/collection/IterableOnceExtensionMethods$;
            0      13     1 $this   Lscala/collection/IterableOnce;
            0      13     2     f   Lscala/Function2;
    Signature: #65                          // <A:Ljava/lang/Object;>(Lscala/collection/IterableOnce<TA;>;Lscala/Function2<TA;TA;TA;>;)TA;
    Deprecated: true
    MethodParameters:
      Name                           Flags
      $this                          final
      f                              final

  public final <A extends java.lang.Object> scala.Option<A> reduceRightOption$extension(scala.collection.IterableOnce<A>, scala.Function2<A, A, A>);
    descriptor: (Lscala/collection/IterableOnce;Lscala/Function2;)Lscala/Option;
    flags: (0x0011) ACC_PUBLIC, ACC_FINAL
    Code:
      stack=2, locals=3, args_size=3
         0: aload_1
         1: invokeinterface #25,  1           // InterfaceMethod scala/collection/IterableOnce.iterator:()Lscala/collection/Iterator;
         6: aload_2
         7: invokeinterface #160,  2          // InterfaceMethod scala/collection/Iterator.reduceRightOption:(Lscala/Function2;)Lscala/Option;
        12: areturn
      LineNumberTable:
        line 145: 0
      LocalVariableTable:
        Start  Length  Slot  Name   Signature
            0      13     0  this   Lscala/collection/IterableOnceExtensionMethods$;
            0      13     1 $this   Lscala/collection/IterableOnce;
            0      13     2     f   Lscala/Function2;
    Signature: #37                          // <A:Ljava/lang/Object;>(Lscala/collection/IterableOnce<TA;>;Lscala/Function2<TA;TA;TA;>;)Lscala/Option<TA;>;
    Deprecated: true
    MethodParameters:
      Name                           Flags
      $this                          final
      f                              final

  public final <A extends java.lang.Object> scala.collection.IndexedSeq<A> toIndexedSeq$extension(scala.collection.IterableOnce<A>);
    descriptor: (Lscala/collection/IterableOnce;)Lscala/collection/IndexedSeq;
    flags: (0x0011) ACC_PUBLIC, ACC_FINAL
    Code:
      stack=1, locals=2, args_size=2
         0: aload_1
         1: invokeinterface #25,  1           // InterfaceMethod scala/collection/IterableOnce.iterator:()Lscala/collection/Iterator;
         6: invokeinterface #167,  1          // InterfaceMethod scala/collection/Iterator.toIndexedSeq:()Lscala/collection/immutable/IndexedSeq;
        11: areturn
      LineNumberTable:
        line 148: 0
      LocalVariableTable:
        Start  Length  Slot  Name   Signature
            0      12     0  this   Lscala/collection/IterableOnceExtensionMethods$;
            0      12     1 $this   Lscala/collection/IterableOnce;
    Signature: #163                         // <A:Ljava/lang/Object;>(Lscala/collection/IterableOnce<TA;>;)Lscala/collection/IndexedSeq<TA;>;
    Deprecated: true
    MethodParameters:
      Name                           Flags
      $this                          final

  public final <U extends java.lang.Object, A extends java.lang.Object> void foreach$extension(scala.collection.IterableOnce<A>, scala.Function1<A, U>);
    descriptor: (Lscala/collection/IterableOnce;Lscala/Function1;)V
    flags: (0x0011) ACC_PUBLIC, ACC_FINAL
    Code:
      stack=2, locals=3, args_size=3
         0: aload_1
         1: instanceof    #172                // class scala/collection/Iterable
         4: ifeq          18
         7: aload_1
         8: checkcast     #172                // class scala/collection/Iterable
        11: aload_2
        12: invokeinterface #176,  2          // InterfaceMethod scala/collection/Iterable.foreach:(Lscala/Function1;)V
        17: return
        18: aload_1
        19: invokeinterface #25,  1           // InterfaceMethod scala/collection/IterableOnce.iterator:()Lscala/collection/Iterator;
        24: aload_2
        25: invokeinterface #177,  2          // InterfaceMethod scala/collection/Iterator.foreach:(Lscala/Function1;)V
        30: return
      StackMapTable: number_of_entries = 1
        frame_type = 18 /* same */
      LineNumberTable:
        line 152: 0
        line 151: 18
        line 153: 24
        line 151: 30
      LocalVariableTable:
        Start  Length  Slot  Name   Signature
            0      31     0  this   Lscala/collection/IterableOnceExtensionMethods$;
            0      31     1 $this   Lscala/collection/IterableOnce;
            0      31     2     f   Lscala/Function1;
    Signature: #170                         // <U:Ljava/lang/Object;A:Ljava/lang/Object;>(Lscala/collection/IterableOnce<TA;>;Lscala/Function1<TA;TU;>;)V
    Deprecated: true
    MethodParameters:
      Name                           Flags
      $this                          final
      f                              final

  public final <C1 extends java.lang.Object, A extends java.lang.Object> C1 to$extension(scala.collection.IterableOnce<A>, scala.collection.Factory<A, C1>);
    descriptor: (Lscala/collection/IterableOnce;Lscala/collection/Factory;)Ljava/lang/Object;
    flags: (0x0011) ACC_PUBLIC, ACC_FINAL
    Code:
      stack=2, locals=3, args_size=3
         0: aload_2
         1: aload_1
         2: invokeinterface #187,  2          // InterfaceMethod scala/collection/Factory.fromSpecific:(Lscala/collection/IterableOnce;)Ljava/lang/Object;
         7: areturn
      LineNumberTable:
        line 157: 0
      LocalVariableTable:
        Start  Length  Slot  Name   Signature
            0       8     0  this   Lscala/collection/IterableOnceExtensionMethods$;
            0       8     1 $this   Lscala/collection/IterableOnce;
            0       8     2 factory   Lscala/collection/Factory;
    Signature: #180                         // <C1:Ljava/lang/Object;A:Ljava/lang/Object;>(Lscala/collection/IterableOnce<TA;>;Lscala/collection/Factory<TA;TC1;>;)TC1;
    Deprecated: true
    MethodParameters:
      Name                           Flags
      $this                          final
      factory                        final

  public final <B extends java.lang.Object, A extends java.lang.Object> scala.collection.mutable.Buffer<B> toBuffer$extension(scala.collection.IterableOnce<A>);
    descriptor: (Lscala/collection/IterableOnce;)Lscala/collection/mutable/Buffer;
    flags: (0x0011) ACC_PUBLIC, ACC_FINAL
    Code:
      stack=2, locals=2, args_size=2
         0: getstatic     #196                // Field scala/collection/mutable/ArrayBuffer$.MODULE$:Lscala/collection/mutable/ArrayBuffer$;
         3: aload_1
         4: invokevirtual #200                // Method scala/collection/mutable/ArrayBuffer$.from:(Lscala/collection/IterableOnce;)Lscala/collection/mutable/ArrayBuffer;
         7: areturn
      LineNumberTable:
        line 160: 0
      LocalVariableTable:
        Start  Length  Slot  Name   Signature
            0       8     0  this   Lscala/collection/IterableOnceExtensionMethods$;
            0       8     1 $this   Lscala/collection/IterableOnce;
    Signature: #191                         // <B:Ljava/lang/Object;A:Ljava/lang/Object;>(Lscala/collection/IterableOnce<TA;>;)Lscala/collection/mutable/Buffer<TB;>;
    Deprecated: true
    MethodParameters:
      Name                           Flags
      $this                          final

  public final <B extends java.lang.Object, A extends java.lang.Object> java.lang.Object toArray$extension(scala.collection.IterableOnce<A>, scala.reflect.ClassTag<B>);
    descriptor: (Lscala/collection/IterableOnce;Lscala/reflect/ClassTag;)Ljava/lang/Object;
    flags: (0x0011) ACC_PUBLIC, ACC_FINAL
    Code:
      stack=2, locals=4, args_size=3
         0: aload_1
         1: instanceof    #172                // class scala/collection/Iterable
         4: ifeq          21
         7: aload_1
         8: checkcast     #172                // class scala/collection/Iterable
        11: aload_2
        12: invokeinterface #208,  2          // InterfaceMethod scala/collection/Iterable.toArray:(Lscala/reflect/ClassTag;)Ljava/lang/Object;
        17: astore_3
        18: goto          34
        21: aload_1
        22: invokeinterface #25,  1           // InterfaceMethod scala/collection/IterableOnce.iterator:()Lscala/collection/Iterator;
        27: aload_2
        28: invokeinterface #209,  2          // InterfaceMethod scala/collection/Iterator.toArray:(Lscala/reflect/ClassTag;)Ljava/lang/Object;
        33: astore_3
        34: aload_3
        35: areturn
      StackMapTable: number_of_entries = 2
        frame_type = 21 /* same */
        frame_type = 252 /* append */
          offset_delta = 12
          locals = [ class java/lang/Object ]
      LineNumberTable:
        line 164: 0
        line 163: 21
        line 165: 27
        line 163: 34
      LocalVariableTable:
        Start  Length  Slot  Name   Signature
            0      36     0  this   Lscala/collection/IterableOnceExtensionMethods$;
            0      36     1 $this   Lscala/collection/IterableOnce;
            0      36     2 evidence$1   Lscala/reflect/ClassTag;
    Signature: #203                         // <B:Ljava/lang/Object;A:Ljava/lang/Object;>(Lscala/collection/IterableOnce<TA;>;Lscala/reflect/ClassTag<TB;>;)Ljava/lang/Object;
    Deprecated: true
    MethodParameters:
      Name                           Flags
      $this                          final
      evidence$1                     final

  public final <A extends java.lang.Object> scala.collection.immutable.List<A> toList$extension(scala.collection.IterableOnce<A>);
    descriptor: (Lscala/collection/IterableOnce;)Lscala/collection/immutable/List;
    flags: (0x0011) ACC_PUBLIC, ACC_FINAL
    Code:
      stack=2, locals=2, args_size=2
         0: getstatic     #218                // Field scala/collection/immutable/List$.MODULE$:Lscala/collection/immutable/List$;
         3: pop
         4: getstatic     #223                // Field scala/collection/immutable/Nil$.MODULE$:Lscala/collection/immutable/Nil$;
         7: aload_1
         8: invokevirtual #226                // Method scala/collection/immutable/Nil$.prependedAll:(Lscala/collection/IterableOnce;)Lscala/collection/immutable/List;
        11: areturn
      LineNumberTable:
        line 169: 0
      LocalVariableTable:
        Start  Length  Slot  Name   Signature
            0      12     0  this   Lscala/collection/IterableOnceExtensionMethods$;
            0      12     1 $this   Lscala/collection/IterableOnce;
    Signature: #213                         // <A:Ljava/lang/Object;>(Lscala/collection/IterableOnce<TA;>;)Lscala/collection/immutable/List<TA;>;
    Deprecated: true
    MethodParameters:
      Name                           Flags
      $this                          final

  public final <B extends java.lang.Object, A extends java.lang.Object> scala.collection.immutable.Set<B> toSet$extension(scala.collection.IterableOnce<A>);
    descriptor: (Lscala/collection/IterableOnce;)Lscala/collection/immutable/Set;
    flags: (0x0011) ACC_PUBLIC, ACC_FINAL
    Code:
      stack=2, locals=2, args_size=2
         0: getstatic     #234                // Field scala/collection/immutable/Set$.MODULE$:Lscala/collection/immutable/Set$;
         3: aload_1
         4: invokevirtual #236                // Method scala/collection/immutable/Set$.from:(Lscala/collection/IterableOnce;)Lscala/collection/immutable/Set;
         7: areturn
      LineNumberTable:
        line 172: 0
      LocalVariableTable:
        Start  Length  Slot  Name   Signature
            0       8     0  this   Lscala/collection/IterableOnceExtensionMethods$;
            0       8     1 $this   Lscala/collection/IterableOnce;
    Signature: #229                         // <B:Ljava/lang/Object;A:Ljava/lang/Object;>(Lscala/collection/IterableOnce<TA;>;)Lscala/collection/immutable/Set<TB;>;
    Deprecated: true
    MethodParameters:
      Name                           Flags
      $this                          final

  public final <A extends java.lang.Object> scala.collection.Iterable<A> toTraversable$extension(scala.collection.IterableOnce<A>);
    descriptor: (Lscala/collection/IterableOnce;)Lscala/collection/Iterable;
    flags: (0x0011) ACC_PUBLIC, ACC_FINAL
    Code:
      stack=2, locals=2, args_size=2
         0: getstatic     #244                // Field scala/collection/Iterable$.MODULE$:Lscala/collection/Iterable$;
         3: aload_1
         4: invokevirtual #246                // Method scala/collection/Iterable$.from:(Lscala/collection/IterableOnce;)Ljava/lang/Object;
         7: checkcast     #172                // class scala/collection/Iterable
        10: areturn
      LineNumberTable:
        line 178: 0
      LocalVariableTable:
        Start  Length  Slot  Name   Signature
            0      11     0  this   Lscala/collection/IterableOnceExtensionMethods$;
            0      11     1 $this   Lscala/collection/IterableOnce;
    Signature: #239                         // <A:Ljava/lang/Object;>(Lscala/collection/IterableOnce<TA;>;)Lscala/collection/Iterable<TA;>;
    Deprecated: true
    MethodParameters:
      Name                           Flags
      $this                          final

  public final <A extends java.lang.Object> scala.collection.Iterable<A> toIterable$extension(scala.collection.IterableOnce<A>);
    descriptor: (Lscala/collection/IterableOnce;)Lscala/collection/Iterable;
    flags: (0x0011) ACC_PUBLIC, ACC_FINAL
    Code:
      stack=2, locals=2, args_size=2
         0: getstatic     #244                // Field scala/collection/Iterable$.MODULE$:Lscala/collection/Iterable$;
         3: aload_1
         4: invokevirtual #246                // Method scala/collection/Iterable$.from:(Lscala/collection/IterableOnce;)Ljava/lang/Object;
         7: checkcast     #172                // class scala/collection/Iterable
        10: areturn
      LineNumberTable:
        line 178: 0
      LocalVariableTable:
        Start  Length  Slot  Name   Signature
            0      11     0  this   Lscala/collection/IterableOnceExtensionMethods$;
            0      11     1 $this   Lscala/collection/IterableOnce;
    Signature: #239                         // <A:Ljava/lang/Object;>(Lscala/collection/IterableOnce<TA;>;)Lscala/collection/Iterable<TA;>;
    Deprecated: true
    MethodParameters:
      Name                           Flags
      $this                          final

  public final <A extends java.lang.Object> scala.collection.immutable.Seq<A> toSeq$extension(scala.collection.IterableOnce<A>);
    descriptor: (Lscala/collection/IterableOnce;)Lscala/collection/immutable/Seq;
    flags: (0x0011) ACC_PUBLIC, ACC_FINAL
    Code:
      stack=2, locals=2, args_size=2
         0: getstatic     #255                // Field scala/collection/immutable/Seq$.MODULE$:Lscala/collection/immutable/Seq$;
         3: aload_1
         4: invokevirtual #257                // Method scala/collection/immutable/Seq$.from:(Lscala/collection/IterableOnce;)Lscala/collection/immutable/Seq;
         7: areturn
      LineNumberTable:
        line 181: 0
      LocalVariableTable:
        Start  Length  Slot  Name   Signature
            0       8     0  this   Lscala/collection/IterableOnceExtensionMethods$;
            0       8     1 $this   Lscala/collection/IterableOnce;
    Signature: #250                         // <A:Ljava/lang/Object;>(Lscala/collection/IterableOnce<TA;>;)Lscala/collection/immutable/Seq<TA;>;
    Deprecated: true
    MethodParameters:
      Name                           Flags
      $this                          final

  public final <A extends java.lang.Object> scala.collection.immutable.Stream<A> toStream$extension(scala.collection.IterableOnce<A>);
    descriptor: (Lscala/collection/IterableOnce;)Lscala/collection/immutable/Stream;
    flags: (0x0011) ACC_PUBLIC, ACC_FINAL
    Code:
      stack=2, locals=2, args_size=2
         0: getstatic     #265                // Field scala/collection/immutable/Stream$.MODULE$:Lscala/collection/immutable/Stream$;
         3: aload_1
         4: invokevirtual #267                // Method scala/collection/immutable/Stream$.from:(Lscala/collection/IterableOnce;)Lscala/collection/immutable/Stream;
         7: areturn
      LineNumberTable:
        line 184: 0
      LocalVariableTable:
        Start  Length  Slot  Name   Signature
            0       8     0  this   Lscala/collection/IterableOnceExtensionMethods$;
            0       8     1 $this   Lscala/collection/IterableOnce;
    Signature: #260                         // <A:Ljava/lang/Object;>(Lscala/collection/IterableOnce<TA;>;)Lscala/collection/immutable/Stream<TA;>;
    Deprecated: true
    MethodParameters:
      Name                           Flags
      $this                          final

  public final <A extends java.lang.Object> scala.collection.immutable.Vector<A> toVector$extension(scala.collection.IterableOnce<A>);
    descriptor: (Lscala/collection/IterableOnce;)Lscala/collection/immutable/Vector;
    flags: (0x0011) ACC_PUBLIC, ACC_FINAL
    Code:
      stack=2, locals=2, args_size=2
         0: getstatic     #275                // Field scala/collection/immutable/Vector$.MODULE$:Lscala/collection/immutable/Vector$;
         3: aload_1
         4: invokevirtual #277                // Method scala/collection/immutable/Vector$.from:(Lscala/collection/IterableOnce;)Lscala/collection/immutable/Vector;
         7: areturn
      LineNumberTable:
        line 187: 0
      LocalVariableTable:
        Start  Length  Slot  Name   Signature
            0       8     0  this   Lscala/collection/IterableOnceExtensionMethods$;
            0       8     1 $this   Lscala/collection/IterableOnce;
    Signature: #270                         // <A:Ljava/lang/Object;>(Lscala/collection/IterableOnce<TA;>;)Lscala/collection/immutable/Vector<TA;>;
    Deprecated: true
    MethodParameters:
      Name                           Flags
      $this                          final

  public final <K extends java.lang.Object, V extends java.lang.Object, A extends java.lang.Object> scala.collection.immutable.Map<K, V> toMap$extension(scala.collection.IterableOnce<A>, scala.$less$colon$less<A, scala.Tuple2<K, V>>);
    descriptor: (Lscala/collection/IterableOnce;Lscala/$less$colon$less;)Lscala/collection/immutable/Map;
    flags: (0x0011) ACC_PUBLIC, ACC_FINAL
    Code:
      stack=2, locals=3, args_size=3
         0: getstatic     #286                // Field scala/collection/immutable/Map$.MODULE$:Lscala/collection/immutable/Map$;
         3: aload_1
         4: invokevirtual #289                // Method scala/collection/immutable/Map$.from:(Lscala/collection/IterableOnce;)Lscala/collection/immutable/Map;
         7: areturn
      LineNumberTable:
        line 191: 0
      LocalVariableTable:
        Start  Length  Slot  Name   Signature
            0       8     0  this   Lscala/collection/IterableOnceExtensionMethods$;
            0       8     1 $this   Lscala/collection/IterableOnce;
            0       8     2    ev   Lscala/$less$colon$less;
    Signature: #280                         // <K:Ljava/lang/Object;V:Ljava/lang/Object;A:Ljava/lang/Object;>(Lscala/collection/IterableOnce<TA;>;Lscala/$less$colon$less<TA;Lscala/Tuple2<TK;TV;>;>;)Lscala/collection/immutable/Map<TK;TV;>;
    Deprecated: true
    MethodParameters:
      Name                           Flags
      $this                          final
      ev                             final

  public final <A extends java.lang.Object> scala.collection.Iterator<A> toIterator$extension(scala.collection.IterableOnce<A>);
    descriptor: (Lscala/collection/IterableOnce;)Lscala/collection/Iterator;
    flags: (0x0011) ACC_PUBLIC, ACC_FINAL
    Code:
      stack=1, locals=2, args_size=2
         0: aload_1
         1: invokeinterface #25,  1           // InterfaceMethod scala/collection/IterableOnce.iterator:()Lscala/collection/Iterator;
         6: areturn
      LineNumberTable:
        line 194: 0
      LocalVariableTable:
        Start  Length  Slot  Name   Signature
            0       7     0  this   Lscala/collection/IterableOnceExtensionMethods$;
            0       7     1 $this   Lscala/collection/IterableOnce;
    Signature: #293                         // <A:Ljava/lang/Object;>(Lscala/collection/IterableOnce<TA;>;)Lscala/collection/Iterator<TA;>;
    Deprecated: true
    MethodParameters:
      Name                           Flags
      $this                          final

  public final <A extends java.lang.Object> boolean isEmpty$extension(scala.collection.IterableOnce<A>);
    descriptor: (Lscala/collection/IterableOnce;)Z
    flags: (0x0011) ACC_PUBLIC, ACC_FINAL
    Code:
      stack=1, locals=3, args_size=2
         0: aload_1
         1: instanceof    #172                // class scala/collection/Iterable
         4: ifeq          20
         7: aload_1
         8: checkcast     #172                // class scala/collection/Iterable
        11: invokeinterface #297,  1          // InterfaceMethod scala/collection/Iterable.isEmpty:()Z
        16: istore_2
        17: goto          32
        20: aload_1
        21: invokeinterface #25,  1           // InterfaceMethod scala/collection/IterableOnce.iterator:()Lscala/collection/Iterator;
        26: invokeinterface #298,  1          // InterfaceMethod scala/collection/Iterator.isEmpty:()Z
        31: istore_2
        32: iload_2
        33: ireturn
      StackMapTable: number_of_entries = 2
        frame_type = 20 /* same */
        frame_type = 252 /* append */
          offset_delta = 11
          locals = [ int ]
      LineNumberTable:
        line 198: 0
        line 197: 20
      LocalVariableTable:
        Start  Length  Slot  Name   Signature
            0      34     0  this   Lscala/collection/IterableOnceExtensionMethods$;
            0      34     1 $this   Lscala/collection/IterableOnce;
    Signature: #54                          // <A:Ljava/lang/Object;>(Lscala/collection/IterableOnce<TA;>;)Z
    Deprecated: true
    MethodParameters:
      Name                           Flags
      $this                          final

  public final <A extends java.lang.Object> java.lang.String mkString$extension(scala.collection.IterableOnce<A>, java.lang.String, java.lang.String, java.lang.String);
    descriptor: (Lscala/collection/IterableOnce;Ljava/lang/String;Ljava/lang/String;Ljava/lang/String;)Ljava/lang/String;
    flags: (0x0011) ACC_PUBLIC, ACC_FINAL
    Code:
      stack=4, locals=6, args_size=5
         0: aload_1
         1: instanceof    #172                // class scala/collection/Iterable
         4: ifeq          25
         7: aload_1
         8: checkcast     #172                // class scala/collection/Iterable
        11: aload_2
        12: aload_3
        13: aload         4
        15: invokeinterface #308,  4          // InterfaceMethod scala/collection/Iterable.mkString:(Ljava/lang/String;Ljava/lang/String;Ljava/lang/String;)Ljava/lang/String;
        20: astore        5
        22: goto          42
        25: aload_1
        26: invokeinterface #25,  1           // InterfaceMethod scala/collection/IterableOnce.iterator:()Lscala/collection/Iterator;
        31: aload_2
        32: aload_3
        33: aload         4
        35: invokeinterface #309,  4          // InterfaceMethod scala/collection/Iterator.mkString:(Ljava/lang/String;Ljava/lang/String;Ljava/lang/String;)Ljava/lang/String;
        40: astore        5
        42: aload         5
        44: areturn
      StackMapTable: number_of_entries = 2
        frame_type = 25 /* same */
        frame_type = 252 /* append */
          offset_delta = 16
          locals = [ class java/lang/String ]
      LineNumberTable:
        line 204: 0
        line 203: 25
        line 205: 31
        line 203: 42
      LocalVariableTable:
        Start  Length  Slot  Name   Signature
            0      45     0  this   Lscala/collection/IterableOnceExtensionMethods$;
            0      45     1 $this   Lscala/collection/IterableOnce;
            0      45     2 start   Ljava/lang/String;
            0      45     3   sep   Ljava/lang/String;
            0      45     4   end   Ljava/lang/String;
    Signature: #301                         // <A:Ljava/lang/Object;>(Lscala/collection/IterableOnce<TA;>;Ljava/lang/String;Ljava/lang/String;Ljava/lang/String;)Ljava/lang/String;
    Deprecated: true
    MethodParameters:
      Name                           Flags
      $this                          final
      start                          final
      sep                            final
      end                            final

  public final <A extends java.lang.Object> java.lang.String mkString$extension(scala.collection.IterableOnce<A>, java.lang.String);
    descriptor: (Lscala/collection/IterableOnce;Ljava/lang/String;)Ljava/lang/String;
    flags: (0x0011) ACC_PUBLIC, ACC_FINAL
    Code:
      stack=4, locals=6, args_size=3
         0: aload_1
         1: instanceof    #172                // class scala/collection/Iterable
         4: ifeq          45
         7: aload_1
         8: checkcast     #172                // class scala/collection/Iterable
        11: astore        4
        13: aload         4
        15: ifnonnull     20
        18: aconst_null
        19: athrow
        20: aload         4
        22: ldc_w         #316                // String
        25: aload_2
        26: ldc_w         #316                // String
        29: invokeinterface #319,  4          // InterfaceMethod scala/collection/IterableOnceOps.mkString:(Ljava/lang/String;Ljava/lang/String;Ljava/lang/String;)Ljava/lang/String;
        34: astore        5
        36: aload         5
        38: aconst_null
        39: astore        5
        41: astore_3
        42: goto          70
        45: aload_1
        46: invokeinterface #25,  1           // InterfaceMethod scala/collection/IterableOnce.iterator:()Lscala/collection/Iterator;
        51: dup
        52: ifnonnull     57
        55: aconst_null
        56: athrow
        57: ldc_w         #316                // String
        60: aload_2
        61: ldc_w         #316                // String
        64: invokeinterface #319,  4          // InterfaceMethod scala/collection/IterableOnceOps.mkString:(Ljava/lang/String;Ljava/lang/String;Ljava/lang/String;)Ljava/lang/String;
        69: astore_3
        70: aload_3
        71: areturn
      StackMapTable: number_of_entries = 4
        frame_type = 253 /* append */
          offset_delta = 20
          locals = [ top, class scala/collection/Iterable ]
        frame_type = 249 /* chop */
          offset_delta = 24
        frame_type = 75 /* same_locals_1_stack_item */
          stack = [ class scala/collection/Iterator ]
        frame_type = 252 /* append */
          offset_delta = 12
          locals = [ class java/lang/String ]
      LineNumberTable:
        line 210: 0
        line 1142: 20
        line 210: 36
        line 209: 45
        line 211: 51
        line 1142: 57
        line 211: 69
        line 209: 70
      LocalVariableTable:
        Start  Length  Slot  Name   Signature
            0      72     0  this   Lscala/collection/IterableOnceExtensionMethods$;
            0      72     1 $this   Lscala/collection/IterableOnce;
            0      72     2   sep   Ljava/lang/String;
    Signature: #314                         // <A:Ljava/lang/Object;>(Lscala/collection/IterableOnce<TA;>;Ljava/lang/String;)Ljava/lang/String;
    Deprecated: true
    MethodParameters:
      Name                           Flags
      $this                          final
      sep                            final

  public final <A extends java.lang.Object> java.lang.String mkString$extension(scala.collection.IterableOnce<A>);
    descriptor: (Lscala/collection/IterableOnce;)Ljava/lang/String;
    flags: (0x0011) ACC_PUBLIC, ACC_FINAL
    Code:
      stack=4, locals=9, args_size=2
         0: aload_1
         1: instanceof    #172                // class scala/collection/Iterable
         4: ifeq          58
         7: aload_1
         8: checkcast     #172                // class scala/collection/Iterable
        11: astore_3
        12: aload_3
        13: ifnonnull     18
        16: aconst_null
        17: athrow
        18: ldc_w         #316                // String
        21: astore        4
        23: aload_3
        24: ldc_w         #316                // String
        27: aload         4
        29: ldc_w         #316                // String
        32: invokeinterface #319,  4          // InterfaceMethod scala/collection/IterableOnceOps.mkString:(Ljava/lang/String;Ljava/lang/String;Ljava/lang/String;)Ljava/lang/String;
        37: astore        5
        39: aload         5
        41: aconst_null
        42: astore        4
        44: aconst_null
        45: astore        5
        47: astore        6
        49: aload         6
        51: aconst_null
        52: astore        6
        54: astore_2
        55: goto          93
        58: aload_1
        59: invokeinterface #25,  1           // InterfaceMethod scala/collection/IterableOnce.iterator:()Lscala/collection/Iterator;
        64: dup
        65: ifnonnull     70
        68: aconst_null
        69: athrow
        70: astore        7
        72: ldc_w         #316                // String
        75: astore        8
        77: aload         7
        79: ldc_w         #316                // String
        82: aload         8
        84: ldc_w         #316                // String
        87: invokeinterface #319,  4          // InterfaceMethod scala/collection/IterableOnceOps.mkString:(Ljava/lang/String;Ljava/lang/String;Ljava/lang/String;)Ljava/lang/String;
        92: astore_2
        93: aload_2
        94: areturn
      StackMapTable: number_of_entries = 4
        frame_type = 253 /* append */
          offset_delta = 18
          locals = [ top, class scala/collection/Iterable ]
        frame_type = 249 /* chop */
          offset_delta = 39
        frame_type = 75 /* same_locals_1_stack_item */
          stack = [ class scala/collection/Iterator ]
        frame_type = 252 /* append */
          offset_delta = 22
          locals = [ class java/lang/String ]
      LineNumberTable:
        line 216: 0
        line 1153: 18
        line 1142: 23
        line 1153: 39
        line 216: 49
        line 215: 58
        line 1153: 72
        line 1142: 77
        line 215: 92
      LocalVariableTable:
        Start  Length  Slot  Name   Signature
            0      95     0  this   Lscala/collection/IterableOnceExtensionMethods$;
            0      95     1 $this   Lscala/collection/IterableOnce;
           23      16     4 mkString_mkString_sep   Ljava/lang/String;
           72      20     7 mkString_this   Lscala/collection/IterableOnceOps;
           77      15     8 mkString_mkString_sep   Ljava/lang/String;
    Signature: #321                         // <A:Ljava/lang/Object;>(Lscala/collection/IterableOnce<TA;>;)Ljava/lang/String;
    Deprecated: true
    MethodParameters:
      Name                           Flags
      $this                          final

  public final <A extends java.lang.Object> scala.Option<A> find$extension(scala.collection.IterableOnce<A>, scala.Function1<A, java.lang.Object>);
    descriptor: (Lscala/collection/IterableOnce;Lscala/Function1;)Lscala/Option;
    flags: (0x0011) ACC_PUBLIC, ACC_FINAL
    Code:
      stack=2, locals=3, args_size=3
         0: aload_1
         1: invokeinterface #25,  1           // InterfaceMethod scala/collection/IterableOnce.iterator:()Lscala/collection/Iterator;
         6: aload_2
         7: invokeinterface #331,  2          // InterfaceMethod scala/collection/Iterator.find:(Lscala/Function1;)Lscala/Option;
        12: areturn
      LineNumberTable:
        line 221: 0
      LocalVariableTable:
        Start  Length  Slot  Name   Signature
            0      13     0  this   Lscala/collection/IterableOnceExtensionMethods$;
            0      13     1 $this   Lscala/collection/IterableOnce;
            0      13     2     p   Lscala/Function1;
    Signature: #326                         // <A:Ljava/lang/Object;>(Lscala/collection/IterableOnce<TA;>;Lscala/Function1<TA;Ljava/lang/Object;>;)Lscala/Option<TA;>;
    Deprecated: true
    MethodParameters:
      Name                           Flags
      $this                          final
      p                              final

  public final <B extends java.lang.Object, A extends java.lang.Object> B foldLeft$extension(scala.collection.IterableOnce<A>, B, scala.Function2<B, A, B>);
    descriptor: (Lscala/collection/IterableOnce;Ljava/lang/Object;Lscala/Function2;)Ljava/lang/Object;
    flags: (0x0011) ACC_PUBLIC, ACC_FINAL
    Code:
      stack=3, locals=4, args_size=4
         0: aload_1
         1: invokeinterface #25,  1           // InterfaceMethod scala/collection/IterableOnce.iterator:()Lscala/collection/Iterator;
         6: aload_2
         7: aload_3
         8: invokeinterface #340,  3          // InterfaceMethod scala/collection/Iterator.foldLeft:(Ljava/lang/Object;Lscala/Function2;)Ljava/lang/Object;
        13: areturn
      LineNumberTable:
        line 224: 0
      LocalVariableTable:
        Start  Length  Slot  Name   Signature
            0      14     0  this   Lscala/collection/IterableOnceExtensionMethods$;
            0      14     1 $this   Lscala/collection/IterableOnce;
            0      14     2     z   Ljava/lang/Object;
            0      14     3    op   Lscala/Function2;
    Signature: #334                         // <B:Ljava/lang/Object;A:Ljava/lang/Object;>(Lscala/collection/IterableOnce<TA;>;TB;Lscala/Function2<TB;TA;TB;>;)TB;
    Deprecated: true
    MethodParameters:
      Name                           Flags
      $this                          final
      z                              final
      op                             final

  public final <B extends java.lang.Object, A extends java.lang.Object> B foldRight$extension(scala.collection.IterableOnce<A>, B, scala.Function2<A, B, B>);
    descriptor: (Lscala/collection/IterableOnce;Ljava/lang/Object;Lscala/Function2;)Ljava/lang/Object;
    flags: (0x0011) ACC_PUBLIC, ACC_FINAL
    Code:
      stack=3, locals=4, args_size=4
         0: aload_1
         1: invokeinterface #25,  1           // InterfaceMethod scala/collection/IterableOnce.iterator:()Lscala/collection/Iterator;
         6: aload_2
         7: aload_3
         8: invokeinterface #346,  3          // InterfaceMethod scala/collection/Iterator.foldRight:(Ljava/lang/Object;Lscala/Function2;)Ljava/lang/Object;
        13: areturn
      LineNumberTable:
        line 227: 0
      LocalVariableTable:
        Start  Length  Slot  Name   Signature
            0      14     0  this   Lscala/collection/IterableOnceExtensionMethods$;
            0      14     1 $this   Lscala/collection/IterableOnce;
            0      14     2     z   Ljava/lang/Object;
            0      14     3    op   Lscala/Function2;
    Signature: #343                         // <B:Ljava/lang/Object;A:Ljava/lang/Object;>(Lscala/collection/IterableOnce<TA;>;TB;Lscala/Function2<TA;TB;TB;>;)TB;
    Deprecated: true
    MethodParameters:
      Name                           Flags
      $this                          final
      z                              final
      op                             final

  public final <A1 extends java.lang.Object, A extends java.lang.Object> A1 fold$extension(scala.collection.IterableOnce<A>, A1, scala.Function2<A1, A1, A1>);
    descriptor: (Lscala/collection/IterableOnce;Ljava/lang/Object;Lscala/Function2;)Ljava/lang/Object;
    flags: (0x0011) ACC_PUBLIC, ACC_FINAL
    Code:
      stack=3, locals=4, args_size=4
         0: aload_1
         1: invokeinterface #25,  1           // InterfaceMethod scala/collection/IterableOnce.iterator:()Lscala/collection/Iterator;
         6: aload_2
         7: aload_3
         8: invokeinterface #351,  3          // InterfaceMethod scala/collection/Iterator.fold:(Ljava/lang/Object;Lscala/Function2;)Ljava/lang/Object;
        13: areturn
      LineNumberTable:
        line 230: 0
      LocalVariableTable:
        Start  Length  Slot  Name   Signature
            0      14     0  this   Lscala/collection/IterableOnceExtensionMethods$;
            0      14     1 $this   Lscala/collection/IterableOnce;
            0      14     2     z   Ljava/lang/Object;
            0      14     3    op   Lscala/Function2;
    Signature: #348                         // <A1:Ljava/lang/Object;A:Ljava/lang/Object;>(Lscala/collection/IterableOnce<TA;>;TA1;Lscala/Function2<TA1;TA1;TA1;>;)TA1;
    Deprecated: true
    MethodParameters:
      Name                           Flags
      $this                          final
      z                              final
      op                             final

  public final <B extends java.lang.Object, A extends java.lang.Object> B $div$colon$extension(scala.collection.IterableOnce<A>, B, scala.Function2<B, A, B>);
    descriptor: (Lscala/collection/IterableOnce;Ljava/lang/Object;Lscala/Function2;)Ljava/lang/Object;
    flags: (0x0011) ACC_PUBLIC, ACC_FINAL
    Code:
      stack=3, locals=4, args_size=4
         0: aload_1
         1: invokeinterface #25,  1           // InterfaceMethod scala/collection/IterableOnce.iterator:()Lscala/collection/Iterator;
         6: aload_2
         7: aload_3
         8: invokeinterface #340,  3          // InterfaceMethod scala/collection/Iterator.foldLeft:(Ljava/lang/Object;Lscala/Function2;)Ljava/lang/Object;
        13: areturn
      LineNumberTable:
        line 224: 0
        line 233: 13
      LocalVariableTable:
        Start  Length  Slot  Name   Signature
            0      14     0  this   Lscala/collection/IterableOnceExtensionMethods$;
            0      14     1 $this   Lscala/collection/IterableOnce;
            0      14     2     z   Ljava/lang/Object;
            0      14     3    op   Lscala/Function2;
    Signature: #334                         // <B:Ljava/lang/Object;A:Ljava/lang/Object;>(Lscala/collection/IterableOnce<TA;>;TB;Lscala/Function2<TB;TA;TB;>;)TB;
    Deprecated: true
    MethodParameters:
      Name                           Flags
      $this                          final
      z                              final
      op                             final

  public final <B extends java.lang.Object, A extends java.lang.Object> B $colon$bslash$extension(scala.collection.IterableOnce<A>, B, scala.Function2<A, B, B>);
    descriptor: (Lscala/collection/IterableOnce;Ljava/lang/Object;Lscala/Function2;)Ljava/lang/Object;
    flags: (0x0011) ACC_PUBLIC, ACC_FINAL
    Code:
      stack=3, locals=4, args_size=4
         0: aload_1
         1: invokeinterface #25,  1           // InterfaceMethod scala/collection/IterableOnce.iterator:()Lscala/collection/Iterator;
         6: aload_2
         7: aload_3
         8: invokeinterface #346,  3          // InterfaceMethod scala/collection/Iterator.foldRight:(Ljava/lang/Object;Lscala/Function2;)Ljava/lang/Object;
        13: areturn
      LineNumberTable:
        line 227: 0
        line 236: 13
      LocalVariableTable:
        Start  Length  Slot  Name   Signature
            0      14     0  this   Lscala/collection/IterableOnceExtensionMethods$;
            0      14     1 $this   Lscala/collection/IterableOnce;
            0      14     2     z   Ljava/lang/Object;
            0      14     3    op   Lscala/Function2;
    Signature: #343                         // <B:Ljava/lang/Object;A:Ljava/lang/Object;>(Lscala/collection/IterableOnce<TA;>;TB;Lscala/Function2<TA;TB;TB;>;)TB;
    Deprecated: true
    MethodParameters:
      Name                           Flags
      $this                          final
      z                              final
      op                             final

  public final <B extends java.lang.Object, A extends java.lang.Object> scala.collection.IterableOnce<B> map$extension(scala.collection.IterableOnce<A>, scala.Function1<A, B>);
    descriptor: (Lscala/collection/IterableOnce;Lscala/Function1;)Lscala/collection/IterableOnce;
    flags: (0x0011) ACC_PUBLIC, ACC_FINAL
    Code:
      stack=2, locals=4, args_size=3
         0: aload_1
         1: instanceof    #172                // class scala/collection/Iterable
         4: ifeq          24
         7: aload_1
         8: checkcast     #172                // class scala/collection/Iterable
        11: aload_2
        12: invokeinterface #360,  2          // InterfaceMethod scala/collection/Iterable.map:(Lscala/Function1;)Ljava/lang/Object;
        17: checkcast     #21                 // class scala/collection/IterableOnce
        20: astore_3
        21: goto          37
        24: aload_1
        25: invokeinterface #25,  1           // InterfaceMethod scala/collection/IterableOnce.iterator:()Lscala/collection/Iterator;
        30: aload_2
        31: invokeinterface #362,  2          // InterfaceMethod scala/collection/Iterator.map:(Lscala/Function1;)Lscala/collection/Iterator;
        36: astore_3
        37: aload_3
        38: areturn
      StackMapTable: number_of_entries = 2
        frame_type = 24 /* same */
        frame_type = 252 /* append */
          offset_delta = 12
          locals = [ class scala/collection/IterableOnce ]
      LineNumberTable:
        line 240: 0
        line 239: 24
        line 241: 30
        line 239: 37
      LocalVariableTable:
        Start  Length  Slot  Name   Signature
            0      39     0  this   Lscala/collection/IterableOnceExtensionMethods$;
            0      39     1 $this   Lscala/collection/IterableOnce;
            0      39     2     f   Lscala/Function1;
    Signature: #356                         // <B:Ljava/lang/Object;A:Ljava/lang/Object;>(Lscala/collection/IterableOnce<TA;>;Lscala/Function1<TA;TB;>;)Lscala/collection/IterableOnce<TB;>;
    Deprecated: true
    MethodParameters:
      Name                           Flags
      $this                          final
      f                              final

  public final <B extends java.lang.Object, A extends java.lang.Object> scala.collection.IterableOnce<B> flatMap$extension(scala.collection.IterableOnce<A>, scala.Function1<A, scala.collection.IterableOnce<B>>);
    descriptor: (Lscala/collection/IterableOnce;Lscala/Function1;)Lscala/collection/IterableOnce;
    flags: (0x0011) ACC_PUBLIC, ACC_FINAL
    Code:
      stack=2, locals=4, args_size=3
         0: aload_1
         1: instanceof    #172                // class scala/collection/Iterable
         4: ifeq          24
         7: aload_1
         8: checkcast     #172                // class scala/collection/Iterable
        11: aload_2
        12: invokeinterface #367,  2          // InterfaceMethod scala/collection/Iterable.flatMap:(Lscala/Function1;)Ljava/lang/Object;
        17: checkcast     #21                 // class scala/collection/IterableOnce
        20: astore_3
        21: goto          37
        24: aload_1
        25: invokeinterface #25,  1           // InterfaceMethod scala/collection/IterableOnce.iterator:()Lscala/collection/Iterator;
        30: aload_2
        31: invokeinterface #369,  2          // InterfaceMethod scala/collection/Iterator.flatMap:(Lscala/Function1;)Lscala/collection/Iterator;
        36: astore_3
        37: aload_3
        38: areturn
      StackMapTable: number_of_entries = 2
        frame_type = 24 /* same */
        frame_type = 252 /* append */
          offset_delta = 12
          locals = [ class scala/collection/IterableOnce ]
      LineNumberTable:
        line 246: 0
        line 245: 24
        line 247: 30
        line 245: 37
      LocalVariableTable:
        Start  Length  Slot  Name   Signature
            0      39     0  this   Lscala/collection/IterableOnceExtensionMethods$;
            0      39     1 $this   Lscala/collection/IterableOnce;
            0      39     2     f   Lscala/Function1;
    Signature: #364                         // <B:Ljava/lang/Object;A:Ljava/lang/Object;>(Lscala/collection/IterableOnce<TA;>;Lscala/Function1<TA;Lscala/collection/IterableOnce<TB;>;>;)Lscala/collection/IterableOnce<TB;>;
    Deprecated: true
    MethodParameters:
      Name                           Flags
      $this                          final
      f                              final

  public final <B extends java.lang.Object, A extends java.lang.Object> boolean sameElements$extension(scala.collection.IterableOnce<A>, scala.collection.IterableOnce<B>);
    descriptor: (Lscala/collection/IterableOnce;Lscala/collection/IterableOnce;)Z
    flags: (0x0011) ACC_PUBLIC, ACC_FINAL
    Code:
      stack=2, locals=3, args_size=3
         0: aload_1
         1: invokeinterface #25,  1           // InterfaceMethod scala/collection/IterableOnce.iterator:()Lscala/collection/Iterator;
         6: aload_2
         7: invokeinterface #376,  2          // InterfaceMethod scala/collection/Iterator.sameElements:(Lscala/collection/IterableOnce;)Z
        12: ireturn
      LineNumberTable:
        line 251: 0
      LocalVariableTable:
        Start  Length  Slot  Name   Signature
            0      13     0  this   Lscala/collection/IterableOnceExtensionMethods$;
            0      13     1 $this   Lscala/collection/IterableOnce;
            0      13     2  that   Lscala/collection/IterableOnce;
    Signature: #372                         // <B:Ljava/lang/Object;A:Ljava/lang/Object;>(Lscala/collection/IterableOnce<TA;>;Lscala/collection/IterableOnce<TB;>;)Z
    Deprecated: true
    MethodParameters:
      Name                           Flags
      $this                          final
      that                           final

  public final <A extends java.lang.Object> int hashCode$extension(scala.collection.IterableOnce<A>);
    descriptor: (Lscala/collection/IterableOnce;)I
    flags: (0x0011) ACC_PUBLIC, ACC_FINAL
    Code:
      stack=1, locals=2, args_size=2
         0: aload_1
         1: invokevirtual #380                // Method java/lang/Object.hashCode:()I
         4: ireturn
      LineNumberTable:
        line 83: 0
      LocalVariableTable:
        Start  Length  Slot  Name   Signature
            0       5     0  this   Lscala/collection/IterableOnceExtensionMethods$;
            0       5     1 $this   Lscala/collection/IterableOnce;
    Signature: #112                         // <A:Ljava/lang/Object;>(Lscala/collection/IterableOnce<TA;>;)I
    MethodParameters:
      Name                           Flags
      $this                          final

  public final <A extends java.lang.Object> boolean equals$extension(scala.collection.IterableOnce<A>, java.lang.Object);
    descriptor: (Lscala/collection/IterableOnce;Ljava/lang/Object;)Z
    flags: (0x0011) ACC_PUBLIC, ACC_FINAL
    Code:
      stack=2, locals=5, args_size=3
         0: aload_2
         1: instanceof    #386                // class scala/collection/IterableOnceExtensionMethods
         4: ifeq          12
         7: iconst_1
         8: istore_3
         9: goto          14
        12: iconst_0
        13: istore_3
        14: iload_3
        15: ifeq          67
        18: aload_2
        19: ifnonnull     26
        22: aconst_null
        23: goto          33
        26: aload_2
        27: checkcast     #386                // class scala/collection/IterableOnceExtensionMethods
        30: invokevirtual #390                // Method scala/collection/IterableOnceExtensionMethods.scala$collection$IterableOnceExtensionMethods$$it:()Lscala/collection/IterableOnce;
        33: astore        4
        35: aload_1
        36: dup
        37: ifnonnull     49
        40: pop
        41: aload         4
        43: ifnull        57
        46: goto          61
        49: aload         4
        51: invokevirtual #394                // Method java/lang/Object.equals:(Ljava/lang/Object;)Z
        54: ifeq          61
        57: iconst_1
        58: goto          62
        61: iconst_0
        62: ifeq          67
        65: iconst_1
        66: ireturn
        67: iconst_0
        68: ireturn
      StackMapTable: number_of_entries = 9
        frame_type = 12 /* same */
        frame_type = 252 /* append */
          offset_delta = 1
          locals = [ int ]
        frame_type = 11 /* same */
        frame_type = 70 /* same_locals_1_stack_item */
          stack = [ class scala/collection/IterableOnce ]
        frame_type = 255 /* full_frame */
          offset_delta = 15
          locals = [ class scala/collection/IterableOnceExtensionMethods$, class scala/collection/IterableOnce, class java/lang/Object, int, class scala/collection/IterableOnce ]
          stack = [ class scala/collection/IterableOnce ]
        frame_type = 7 /* same */
        frame_type = 3 /* same */
        frame_type = 64 /* same_locals_1_stack_item */
          stack = [ int ]
        frame_type = 250 /* chop */
          offset_delta = 4
      LineNumberTable:
        line 83: 0
      LocalVariableTable:
        Start  Length  Slot  Name   Signature
            0      69     0  this   Lscala/collection/IterableOnceExtensionMethods$;
            0      69     1 $this   Lscala/collection/IterableOnce;
            0      69     2   x$1   Ljava/lang/Object;
    Signature: #383                         // <A:Ljava/lang/Object;>(Lscala/collection/IterableOnce<TA;>;Ljava/lang/Object;)Z
    MethodParameters:
      Name                           Flags
      $this                          final
      x$1                            final

  private scala.collection.IterableOnceExtensionMethods$();
    descriptor: ()V
    flags: (0x0002) ACC_PRIVATE
    Code:
      stack=1, locals=1, args_size=1
         0: aload_0
         1: invokespecial #395                // Method java/lang/Object."<init>":()V
         4: return
      LineNumberTable:
        line 83: 0
      LocalVariableTable:
        Start  Length  Slot  Name   Signature
            0       5     0  this   Lscala/collection/IterableOnceExtensionMethods$;
}
SourceFile: "IterableOnce.scala"
  ScalaInlineInfo: length = 0x103 (unknown attribute)
   01 01 00 33 01 61 01 4D 05 01 60 01 4D 05 00 0A
   00 09 01 00 7C 00 7D 01 00 8C 00 8D 01 00 5F 00
   60 01 01 7D 01 7E 01 00 88 00 76 01 00 84 00 10
   01 01 44 01 45 01 01 6B 01 63 01 01 5B 01 4D 01
   01 4C 01 4D 05 01 56 01 4D 05 00 75 00 76 01 00
   A8 00 A9 05 01 79 00 6F 01 01 26 00 35 01 01 62
   01 63 01 00 3B 00 2C 01 00 46 00 47 01 00 2B 00
   2C 01 00 6A 00 47 01 01 2B 01 40 01 01 2B 01 39
   01 01 2B 01 2C 01 00 34 00 35 01 00 5B 00 53 01
   00 99 00 40 01 00 4E 00 40 01 00 23 00 24 01 00
   66 00 24 01 00 3F 00 40 01 00 9D 00 24 01 01 72
   01 73 01 00 6E 00 6F 01 00 52 00 53 01 00 B2 00
   B3 01 00 C9 00 CA 01 00 BD 00 BE 01 00 A1 00 A2
   01 00 F7 00 EE 05 01 23 01 24 05 00 D3 00 D4 01
   01 16 01 17 01 00 F8 00 F9 05 00 E3 00 E4 05 01
   02 01 03 05 00 ED 00 EE 05 01 0C 01 0D 05 00 0F
   00 10 01
  Scala: length = 0x0 (unknown attribute)

