Classfile /Users/mw/Projects/slang-braindump/.jar/jar8/assemble/slang-braindump/assemble/content/scala/collection/IterableFactoryDefaults.class
  Last modified May 29, 2022; size 2683 bytes
  SHA-256 checksum dfa2d1938d4c211382ba095bc0ad996b220ad2a2470621b930b55528a4d900ac
  Compiled from "Iterable.scala"
public interface scala.collection.IterableFactoryDefaults<A extends java.lang.Object, CC extends scala.collection.IterableOps<java.lang.Object, CC, CC>> extends scala.collection.IterableOps<A, CC, CC>
  minor version: 0
  major version: 52
  flags: (0x0601) ACC_PUBLIC, ACC_INTERFACE, ACC_ABSTRACT
  this_class: #2                          // scala/collection/IterableFactoryDefaults
  super_class: #5                         // java/lang/Object
  interfaces: 1, fields: 0, methods: 7, attributes: 5
Constant pool:
   #1 = Utf8               scala/collection/IterableFactoryDefaults
   #2 = Class              #1             // scala/collection/IterableFactoryDefaults
   #3 = Utf8               <A:Ljava/lang/Object;CC::Lscala/collection/IterableOps<Ljava/lang/Object;TCC;TCC;>;>Ljava/lang/Object;Lscala/collection/IterableOps<TA;TCC;TCC;>;
   #4 = Utf8               java/lang/Object
   #5 = Class              #4             // java/lang/Object
   #6 = Utf8               scala/collection/IterableOps
   #7 = Class              #6             // scala/collection/IterableOps
   #8 = Utf8               Iterable.scala
   #9 = Utf8               Lscala/reflect/ScalaSignature;
  #10 = Utf8               bytes
  #11 = Utf8               \u0006\u0005-3q!\u0002\u0004\u0011\u0002\u0007\u00051\u0002C\u00036\u0001\u0011\u0005a\u0007C\u0003;\u0001\u0011E1\bC\u0003B\u0001\u0011E!\tC\u0003J\u0001\u0011\u0005#JA\fJi\u0016\u0014\u0018M\u00197f\r\u0006\u001cGo\u001c:z\t\u00164\u0017-\u001e7ug*\u0011q\u0001C\u0001\u000bG>dG.Z2uS>t\'\"A\u0005\u0002\u000bM\u001c\u0017\r\\1\u0004\u0001U\u0019AbF\u0011\u0014\u0007\u0001i\u0011\u0003\u0005\u0002\u000f\u001f5\t\u0001\"\u0003\u0002\u0011\u0011\t1\u0011I\\=SK\u001a\u0004RAE\n\u0016A)j\u0011AB\u0005\u0003)\u0019\u00111\"\u0013;fe\u0006\u0014G.Z(qgB\u0011ac\u0006\u0007\u0001\t\u0019A\u0002\u0001\"b\u00013\t\t\u0011)\u0005\u0002\u001b;A\u0011abG\u0005\u00039!\u0011qAT8uQ&tw\r\u0005\u0002\u000f=%\u0011q\u0004\u0003\u0002\u0004\u0003:L\bC\u0001\f\"\t\u0019\u0011\u0003\u0001\"b\u0001G\t\u00111iQ\u000b\u0003I\u001d\n\"AG\u0013\u0011\u000bI\u0019b\u0005I\u0015\u0011\u0005Y9C!\u0002\u0015\"\u0005\u0004I\"!\u0001=\u0011\u0007Y\tc\u0005E\u0002\u0017C-R#!\u0006\u0017,\u00035\u0002\"AL\u001a\u000e\u0003=R!\u0001M\u0019\u0002\u0013Ut7\r[3dW\u0016$\'B\u0001\u001a\t\u0003)\tgN\\8uCRLwN\\\u0005\u0003i=\u0012\u0011#\u001e8dQ\u0016\u001c7.\u001a3WCJL\u0017M\\2f\u0003\u0019!\u0013N\\5uIQ\tq\u0007\u0005\u0002\u000fq%\u0011\u0011\b\u0003\u0002\u0005+:LG/\u0001\u0007ge>l7\u000b]3dS\u001aL7\r\u0006\u0002+y!)QH\u0001a\u0001}\u0005!1m\u001c7m!\r\u0011rhK\u0005\u0003\u0001\u001a\u0011A\"\u0013;fe\u0006\u0014G.Z(oG\u0016\f!C\\3x\'B,7-\u001b4jG\n+\u0018\u000e\u001c3feV\t1\t\u0005\u0003E\u000f.RS\"A#\u000b\u0005\u00193\u0011aB7vi\u0006\u0014G.Z\u0005\u0003\u0011\u0016\u0013qAQ;jY\u0012,\'/A\u0003f[B$\u00180F\u0001+\u0001
  #12 = Utf8               fromSpecific$
  #13 = Utf8               (Lscala/collection/IterableFactoryDefaults;Lscala/collection/IterableOnce;)Lscala/collection/IterableOps;
  #14 = Utf8               $this
  #15 = Utf8               coll
  #16 = Utf8               fromSpecific
  #17 = Utf8               (Lscala/collection/IterableOnce;)Lscala/collection/IterableOps;
  #18 = NameAndType        #16:#17        // fromSpecific:(Lscala/collection/IterableOnce;)Lscala/collection/IterableOps;
  #19 = InterfaceMethodref #2.#18         // scala/collection/IterableFactoryDefaults.fromSpecific:(Lscala/collection/IterableOnce;)Lscala/collection/IterableOps;
  #20 = Utf8               Lscala/collection/IterableFactoryDefaults;
  #21 = Utf8               Lscala/collection/IterableOnce;
  #22 = Utf8               (Lscala/collection/IterableOnce<TA;>;)TCC;
  #23 = Utf8               iterableFactory
  #24 = Utf8               ()Lscala/collection/IterableFactory;
  #25 = NameAndType        #23:#24        // iterableFactory:()Lscala/collection/IterableFactory;
  #26 = InterfaceMethodref #2.#25         // scala/collection/IterableFactoryDefaults.iterableFactory:()Lscala/collection/IterableFactory;
  #27 = Utf8               scala/collection/IterableFactory
  #28 = Class              #27            // scala/collection/IterableFactory
  #29 = Utf8               from
  #30 = Utf8               (Lscala/collection/IterableOnce;)Ljava/lang/Object;
  #31 = NameAndType        #29:#30        // from:(Lscala/collection/IterableOnce;)Ljava/lang/Object;
  #32 = InterfaceMethodref #28.#31        // scala/collection/IterableFactory.from:(Lscala/collection/IterableOnce;)Ljava/lang/Object;
  #33 = Utf8               this
  #34 = Utf8               newSpecificBuilder$
  #35 = Utf8               (Lscala/collection/IterableFactoryDefaults;)Lscala/collection/mutable/Builder;
  #36 = Utf8               newSpecificBuilder
  #37 = Utf8               ()Lscala/collection/mutable/Builder;
  #38 = NameAndType        #36:#37        // newSpecificBuilder:()Lscala/collection/mutable/Builder;
  #39 = InterfaceMethodref #2.#38         // scala/collection/IterableFactoryDefaults.newSpecificBuilder:()Lscala/collection/mutable/Builder;
  #40 = Utf8               ()Lscala/collection/mutable/Builder<TA;TCC;>;
  #41 = Utf8               newBuilder
  #42 = NameAndType        #41:#37        // newBuilder:()Lscala/collection/mutable/Builder;
  #43 = InterfaceMethodref #28.#42        // scala/collection/IterableFactory.newBuilder:()Lscala/collection/mutable/Builder;
  #44 = Utf8               empty$
  #45 = Utf8               (Lscala/collection/IterableFactoryDefaults;)Lscala/collection/IterableOps;
  #46 = Utf8               empty
  #47 = Utf8               ()Lscala/collection/IterableOps;
  #48 = NameAndType        #46:#47        // empty:()Lscala/collection/IterableOps;
  #49 = InterfaceMethodref #2.#48         // scala/collection/IterableFactoryDefaults.empty:()Lscala/collection/IterableOps;
  #50 = Utf8               ()TCC;
  #51 = Utf8               ()Ljava/lang/Object;
  #52 = NameAndType        #46:#51        // empty:()Ljava/lang/Object;
  #53 = InterfaceMethodref #28.#52        // scala/collection/IterableFactory.empty:()Ljava/lang/Object;
  #54 = Utf8               $init$
  #55 = Utf8               (Lscala/collection/IterableFactoryDefaults;)V
  #56 = Utf8               Code
  #57 = Utf8               LineNumberTable
  #58 = Utf8               LocalVariableTable
  #59 = Utf8               MethodParameters
  #60 = Utf8               Signature
  #61 = Utf8               SourceFile
  #62 = Utf8               RuntimeVisibleAnnotations
  #63 = Utf8               ScalaInlineInfo
  #64 = Utf8               ScalaSig
{
  public static scala.collection.IterableOps fromSpecific$(scala.collection.IterableFactoryDefaults, scala.collection.IterableOnce);
    descriptor: (Lscala/collection/IterableFactoryDefaults;Lscala/collection/IterableOnce;)Lscala/collection/IterableOps;
    flags: (0x1009) ACC_PUBLIC, ACC_STATIC, ACC_SYNTHETIC
    Code:
      stack=2, locals=2, args_size=2
         0: aload_0
         1: aload_1
         2: invokespecial #19                 // InterfaceMethod fromSpecific:(Lscala/collection/IterableOnce;)Lscala/collection/IterableOps;
         5: areturn
      LineNumberTable:
        line 936: 0
      LocalVariableTable:
        Start  Length  Slot  Name   Signature
            0       6     0 $this   Lscala/collection/IterableFactoryDefaults;
            0       6     1  coll   Lscala/collection/IterableOnce;
    MethodParameters:
      Name                           Flags
      $this                          final synthetic
      coll                           final

  public default CC fromSpecific(scala.collection.IterableOnce<A>);
    descriptor: (Lscala/collection/IterableOnce;)Lscala/collection/IterableOps;
    flags: (0x0001) ACC_PUBLIC
    Code:
      stack=2, locals=2, args_size=2
         0: aload_0
         1: invokeinterface #26,  1           // InterfaceMethod iterableFactory:()Lscala/collection/IterableFactory;
         6: aload_1
         7: invokeinterface #32,  2           // InterfaceMethod scala/collection/IterableFactory.from:(Lscala/collection/IterableOnce;)Ljava/lang/Object;
        12: checkcast     #7                  // class scala/collection/IterableOps
        15: areturn
      LineNumberTable:
        line 936: 0
      LocalVariableTable:
        Start  Length  Slot  Name   Signature
            0      16     0  this   Lscala/collection/IterableFactoryDefaults;
            0      16     1  coll   Lscala/collection/IterableOnce;
    Signature: #22                          // (Lscala/collection/IterableOnce<TA;>;)TCC;
    MethodParameters:
      Name                           Flags
      coll                           final

  public static scala.collection.mutable.Builder newSpecificBuilder$(scala.collection.IterableFactoryDefaults);
    descriptor: (Lscala/collection/IterableFactoryDefaults;)Lscala/collection/mutable/Builder;
    flags: (0x1009) ACC_PUBLIC, ACC_STATIC, ACC_SYNTHETIC
    Code:
      stack=1, locals=1, args_size=1
         0: aload_0
         1: invokespecial #39                 // InterfaceMethod newSpecificBuilder:()Lscala/collection/mutable/Builder;
         4: areturn
      LineNumberTable:
        line 937: 0
      LocalVariableTable:
        Start  Length  Slot  Name   Signature
            0       5     0 $this   Lscala/collection/IterableFactoryDefaults;
    MethodParameters:
      Name                           Flags
      $this                          final synthetic

  public default scala.collection.mutable.Builder<A, CC> newSpecificBuilder();
    descriptor: ()Lscala/collection/mutable/Builder;
    flags: (0x0001) ACC_PUBLIC
    Code:
      stack=1, locals=1, args_size=1
         0: aload_0
         1: invokeinterface #26,  1           // InterfaceMethod iterableFactory:()Lscala/collection/IterableFactory;
         6: invokeinterface #43,  1           // InterfaceMethod scala/collection/IterableFactory.newBuilder:()Lscala/collection/mutable/Builder;
        11: areturn
      LineNumberTable:
        line 937: 0
      LocalVariableTable:
        Start  Length  Slot  Name   Signature
            0      12     0  this   Lscala/collection/IterableFactoryDefaults;
    Signature: #40                          // ()Lscala/collection/mutable/Builder<TA;TCC;>;

  public static scala.collection.IterableOps empty$(scala.collection.IterableFactoryDefaults);
    descriptor: (Lscala/collection/IterableFactoryDefaults;)Lscala/collection/IterableOps;
    flags: (0x1009) ACC_PUBLIC, ACC_STATIC, ACC_SYNTHETIC
    Code:
      stack=1, locals=1, args_size=1
         0: aload_0
         1: invokespecial #49                 // InterfaceMethod empty:()Lscala/collection/IterableOps;
         4: areturn
      LineNumberTable:
        line 940: 0
      LocalVariableTable:
        Start  Length  Slot  Name   Signature
            0       5     0 $this   Lscala/collection/IterableFactoryDefaults;
    MethodParameters:
      Name                           Flags
      $this                          final synthetic

  public default CC empty();
    descriptor: ()Lscala/collection/IterableOps;
    flags: (0x0001) ACC_PUBLIC
    Code:
      stack=1, locals=1, args_size=1
         0: aload_0
         1: invokeinterface #26,  1           // InterfaceMethod iterableFactory:()Lscala/collection/IterableFactory;
         6: invokeinterface #53,  1           // InterfaceMethod scala/collection/IterableFactory.empty:()Ljava/lang/Object;
        11: checkcast     #7                  // class scala/collection/IterableOps
        14: areturn
      LineNumberTable:
        line 940: 0
      LocalVariableTable:
        Start  Length  Slot  Name   Signature
            0      15     0  this   Lscala/collection/IterableFactoryDefaults;
    Signature: #50                          // ()TCC;

  public static void $init$(scala.collection.IterableFactoryDefaults);
    descriptor: (Lscala/collection/IterableFactoryDefaults;)V
    flags: (0x0009) ACC_PUBLIC, ACC_STATIC
    Code:
      stack=0, locals=1, args_size=1
         0: return
      LineNumberTable:
        line 935: 0
      LocalVariableTable:
        Start  Length  Slot  Name   Signature
            0       1     0 $this   Lscala/collection/IterableFactoryDefaults;
    MethodParameters:
      Name                           Flags
      $this                          final synthetic
}
Signature: #3                           // <A:Ljava/lang/Object;CC::Lscala/collection/IterableOps<Ljava/lang/Object;TCC;TCC;>;>Ljava/lang/Object;Lscala/collection/IterableOps<TA;TCC;TCC;>;
SourceFile: "Iterable.scala"
RuntimeVisibleAnnotations:
  0: #9(#10=s#11)
    scala.reflect.ScalaSignature(
      bytes="\u0006\u0005-3q!\u0002\u0004\u0011\u0002\u0007\u00051\u0002C\u00036\u0001\u0011\u0005a\u0007C\u0003;\u0001\u0011E1\bC\u0003B\u0001\u0011E!\tC\u0003J\u0001\u0011\u0005#JA\fJi\u0016\u0014\u0018M\u00197f\r\u0006\u001cGo\u001c:z\t\u00164\u0017-\u001e7ug*\u0011q\u0001C\u0001\u000bG>dG.Z2uS>t\'\"A\u0005\u0002\u000bM\u001c\u0017\r\\1\u0004\u0001U\u0019AbF\u0011\u0014\u0007\u0001i\u0011\u0003\u0005\u0002\u000f\u001f5\t\u0001\"\u0003\u0002\u0011\u0011\t1\u0011I\\=SK\u001a\u0004RAE\n\u0016A)j\u0011AB\u0005\u0003)\u0019\u00111\"\u0013;fe\u0006\u0014G.Z(qgB\u0011ac\u0006\u0007\u0001\t\u0019A\u0002\u0001\"b\u00013\t\t\u0011)\u0005\u0002\u001b;A\u0011abG\u0005\u00039!\u0011qAT8uQ&tw\r\u0005\u0002\u000f=%\u0011q\u0004\u0003\u0002\u0004\u0003:L\bC\u0001\f\"\t\u0019\u0011\u0003\u0001\"b\u0001G\t\u00111iQ\u000b\u0003I\u001d\n\"AG\u0013\u0011\u000bI\u0019b\u0005I\u0015\u0011\u0005Y9C!\u0002\u0015\"\u0005\u0004I\"!\u0001=\u0011\u0007Y\tc\u0005E\u0002\u0017C-R#!\u0006\u0017,\u00035\u0002\"AL\u001a\u000e\u0003=R!\u0001M\u0019\u0002\u0013Ut7\r[3dW\u0016$\'B\u0001\u001a\t\u0003)\tgN\\8uCRLwN\\\u0005\u0003i=\u0012\u0011#\u001e8dQ\u0016\u001c7.\u001a3WCJL\u0017M\\2f\u0003\u0019!\u0013N\\5uIQ\tq\u0007\u0005\u0002\u000fq%\u0011\u0011\b\u0003\u0002\u0005+:LG/\u0001\u0007ge>l7\u000b]3dS\u001aL7\r\u0006\u0002+y!)QH\u0001a\u0001}\u0005!1m\u001c7m!\r\u0011rhK\u0005\u0003\u0001\u001a\u0011A\"\u0013;fe\u0006\u0014G.Z(oG\u0016\f!C\\3x\'B,7-\u001b4jG\n+\u0018\u000e\u001c3feV\t1\t\u0005\u0003E\u000f.RS\"A#\u000b\u0005\u00193\u0011aB7vi\u0006\u0014G.Z\u0005\u0003\u0011\u0016\u0013qAQ;jY\u0012,\'/A\u0003f[B$\u00180F\u0001+\u0001"
    )
  ScalaInlineInfo: length = 0x27 (unknown attribute)
   01 00 00 07 00 36 00 37 01 00 2E 00 2F 00 00 2C
   00 2D 01 00 10 00 11 00 00 0C 00 0D 01 00 24 00
   25 00 00 22 00 23 01
  ScalaSig: length = 0x3 (unknown attribute)
   05 02 00
