Classfile /Users/mw/Projects/slang-braindump/.jar/jar8/assemble/slang-braindump/assemble/content/scala/collection/JavaConverters$AsJavaCollection.class
  Last modified May 29, 2022; size 1187 bytes
  SHA-256 checksum 4e106e50774aca19c7cc7b3e98ce6ae4b8752fcd6ba6a5b394e52feffb40db30
  Compiled from "JavaConverters.scala"
public class scala.collection.JavaConverters$AsJavaCollection<A extends java.lang.Object> extends java.lang.Object
  minor version: 0
  major version: 52
  flags: (0x0021) ACC_PUBLIC, ACC_SUPER
  this_class: #2                          // scala/collection/JavaConverters$AsJavaCollection
  super_class: #5                         // java/lang/Object
  interfaces: 0, fields: 1, methods: 2, attributes: 5
Constant pool:
   #1 = Utf8               scala/collection/JavaConverters$AsJavaCollection
   #2 = Class              #1             // scala/collection/JavaConverters$AsJavaCollection
   #3 = Utf8               <A:Ljava/lang/Object;>Ljava/lang/Object;
   #4 = Utf8               java/lang/Object
   #5 = Class              #4             // java/lang/Object
   #6 = Utf8               JavaConverters.scala
   #7 = Utf8               scala/collection/JavaConverters
   #8 = Class              #7             // scala/collection/JavaConverters
   #9 = Utf8               AsJavaCollection
  #10 = Utf8               i
  #11 = Utf8               Lscala/collection/Iterable;
  #12 = Utf8               Lscala/collection/Iterable<TA;>;
  #13 = Utf8               asJavaCollection
  #14 = Utf8               ()Ljava/util/Collection;
  #15 = Utf8               ()Ljava/util/Collection<TA;>;
  #16 = Utf8               scala/collection/JavaConverters$
  #17 = Class              #16            // scala/collection/JavaConverters$
  #18 = Utf8               MODULE$
  #19 = Utf8               Lscala/collection/JavaConverters$;
  #20 = NameAndType        #18:#19        // MODULE$:Lscala/collection/JavaConverters$;
  #21 = Fieldref           #17.#20        // scala/collection/JavaConverters$.MODULE$:Lscala/collection/JavaConverters$;
  #22 = NameAndType        #10:#11        // i:Lscala/collection/Iterable;
  #23 = Fieldref           #2.#22         // scala/collection/JavaConverters$AsJavaCollection.i:Lscala/collection/Iterable;
  #24 = Utf8               scala/collection/convert/AsJavaConverters
  #25 = Class              #24            // scala/collection/convert/AsJavaConverters
  #26 = Utf8               asJavaCollection$
  #27 = Utf8               (Lscala/collection/convert/AsJavaConverters;Lscala/collection/Iterable;)Ljava/util/Collection;
  #28 = NameAndType        #26:#27        // asJavaCollection$:(Lscala/collection/convert/AsJavaConverters;Lscala/collection/Iterable;)Ljava/util/Collection;
  #29 = InterfaceMethodref #25.#28        // scala/collection/convert/AsJavaConverters.asJavaCollection$:(Lscala/collection/convert/AsJavaConverters;Lscala/collection/Iterable;)Ljava/util/Collection;
  #30 = Utf8               this
  #31 = Utf8               Lscala/collection/JavaConverters$AsJavaCollection;
  #32 = Utf8               <init>
  #33 = Utf8               (Lscala/collection/Iterable;)V
  #34 = Utf8               (Lscala/collection/Iterable<TA;>;)V
  #35 = Utf8               ()V
  #36 = NameAndType        #32:#35        // "<init>":()V
  #37 = Methodref          #5.#36         // java/lang/Object."<init>":()V
  #38 = Utf8               Signature
  #39 = Utf8               Code
  #40 = Utf8               LineNumberTable
  #41 = Utf8               LocalVariableTable
  #42 = Utf8               MethodParameters
  #43 = Utf8               InnerClasses
  #44 = Utf8               SourceFile
  #45 = Utf8               ScalaInlineInfo
  #46 = Utf8               Scala
{
  private final scala.collection.Iterable<A> i;
    descriptor: Lscala/collection/Iterable;
    flags: (0x0012) ACC_PRIVATE, ACC_FINAL
    Signature: #12                          // Lscala/collection/Iterable<TA;>;

  public java.util.Collection<A> asJavaCollection();
    descriptor: ()Ljava/util/Collection;
    flags: (0x0001) ACC_PUBLIC
    Code:
      stack=2, locals=1, args_size=1
         0: getstatic     #21                 // Field scala/collection/JavaConverters$.MODULE$:Lscala/collection/JavaConverters$;
         3: aload_0
         4: getfield      #23                 // Field i:Lscala/collection/Iterable;
         7: invokestatic  #29                 // InterfaceMethod scala/collection/convert/AsJavaConverters.asJavaCollection$:(Lscala/collection/convert/AsJavaConverters;Lscala/collection/Iterable;)Ljava/util/Collection;
        10: areturn
      LineNumberTable:
        line 321: 0
        line 79: 7
        line 321: 10
      LocalVariableTable:
        Start  Length  Slot  Name   Signature
            0      11     0  this   Lscala/collection/JavaConverters$AsJavaCollection;
    Signature: #15                          // ()Ljava/util/Collection<TA;>;

  public scala.collection.JavaConverters$AsJavaCollection(scala.collection.Iterable<A>);
    descriptor: (Lscala/collection/Iterable;)V
    flags: (0x0001) ACC_PUBLIC
    Code:
      stack=2, locals=2, args_size=2
         0: aload_0
         1: aload_1
         2: putfield      #23                 // Field i:Lscala/collection/Iterable;
         5: aload_0
         6: invokespecial #37                 // Method java/lang/Object."<init>":()V
         9: return
      LineNumberTable:
        line 319: 0
      LocalVariableTable:
        Start  Length  Slot  Name   Signature
            0      10     0  this   Lscala/collection/JavaConverters$AsJavaCollection;
            0      10     1     i   Lscala/collection/Iterable;
    Signature: #34                          // (Lscala/collection/Iterable<TA;>;)V
    MethodParameters:
      Name                           Flags
      i                              final
}
InnerClasses:
  public static #9= #2 of #8;             // AsJavaCollection=class scala/collection/JavaConverters$AsJavaCollection of class scala/collection/JavaConverters
Signature: #3                           // <A:Ljava/lang/Object;>Ljava/lang/Object;
SourceFile: "JavaConverters.scala"
  ScalaInlineInfo: length = 0xE (unknown attribute)
   01 00 00 02 00 20 00 21 00 00 0D 00 0E 00
  Scala: length = 0x0 (unknown attribute)

