Classfile /Users/mw/Projects/slang-braindump/.jar/jar8/assemble/slang-braindump/assemble/content/scala/collection/LazyZip4$$anon$21.class
  Last modified May 29, 2022; size 1998 bytes
  SHA-256 checksum 78318d8dfc0803a41adf58739eefb92c24e76cdf3ec16ca00432b1434ea7ce5e
  Compiled from "LazyZipOps.scala"
public final class scala.collection.LazyZip4$$anon$21 extends scala.collection.AbstractView<scala.Tuple4<El1, El2, El3, El4>>
  minor version: 0
  major version: 52
  flags: (0x0031) ACC_PUBLIC, ACC_FINAL, ACC_SUPER
  this_class: #2                          // scala/collection/LazyZip4$$anon$21
  super_class: #5                         // scala/collection/AbstractView
  interfaces: 0, fields: 2, methods: 6, attributes: 6
Constant pool:
   #1 = Utf8               scala/collection/LazyZip4$$anon$21
   #2 = Class              #1             // scala/collection/LazyZip4$$anon$21
   #3 = Utf8               Lscala/collection/AbstractView<Lscala/Tuple4<TEl1;TEl2;TEl3;TEl4;>;>;
   #4 = Utf8               scala/collection/AbstractView
   #5 = Class              #4             // scala/collection/AbstractView
   #6 = Utf8               LazyZipOps.scala
   #7 = Utf8               scala/collection/LazyZip4
   #8 = Class              #7             // scala/collection/LazyZip4
   #9 = Utf8               filter
  #10 = Utf8               (Lscala/Function4;Lscala/collection/BuildFrom;)Ljava/lang/Object;
  #11 = NameAndType        #9:#10         // filter:(Lscala/Function4;Lscala/collection/BuildFrom;)Ljava/lang/Object;
  #12 = Utf8               scala/collection/LazyZip4$$anon$21$$anon$22
  #13 = Class              #12            // scala/collection/LazyZip4$$anon$21$$anon$22
  #14 = Utf8               $outer
  #15 = Utf8               Lscala/collection/LazyZip4;
  #16 = Utf8               p$5
  #17 = Utf8               Lscala/Function4;
  #18 = Utf8               iterator
  #19 = Utf8               ()Lscala/collection/AbstractIterator;
  #20 = Utf8               ()Lscala/collection/AbstractIterator<Lscala/Tuple4<TEl1;TEl2;TEl3;TEl4;>;>;
  #21 = Utf8               <init>
  #22 = Utf8               (Lscala/collection/LazyZip4$$anon$21;)V
  #23 = NameAndType        #21:#22        // "<init>":(Lscala/collection/LazyZip4$$anon$21;)V
  #24 = Methodref          #13.#23        // scala/collection/LazyZip4$$anon$21$$anon$22."<init>":(Lscala/collection/LazyZip4$$anon$21;)V
  #25 = Utf8               this
  #26 = Utf8               Lscala/collection/LazyZip4$$anon$21;
  #27 = Utf8               knownSize
  #28 = Utf8               ()I
  #29 = NameAndType        #14:#15        // $outer:Lscala/collection/LazyZip4;
  #30 = Fieldref           #2.#29         // scala/collection/LazyZip4$$anon$21.$outer:Lscala/collection/LazyZip4;
  #31 = Utf8               scala$collection$LazyZip4$$coll1
  #32 = Utf8               Lscala/collection/Iterable;
  #33 = NameAndType        #31:#32        // scala$collection$LazyZip4$$coll1:Lscala/collection/Iterable;
  #34 = Fieldref           #8.#33         // scala/collection/LazyZip4.scala$collection$LazyZip4$$coll1:Lscala/collection/Iterable;
  #35 = Utf8               scala/collection/Iterable
  #36 = Class              #35            // scala/collection/Iterable
  #37 = NameAndType        #27:#28        // knownSize:()I
  #38 = InterfaceMethodref #36.#37        // scala/collection/Iterable.knownSize:()I
  #39 = Utf8               scala$collection$LazyZip4$$coll2
  #40 = NameAndType        #39:#32        // scala$collection$LazyZip4$$coll2:Lscala/collection/Iterable;
  #41 = Fieldref           #8.#40         // scala/collection/LazyZip4.scala$collection$LazyZip4$$coll2:Lscala/collection/Iterable;
  #42 = Utf8               scala$collection$LazyZip4$$coll3
  #43 = NameAndType        #42:#32        // scala$collection$LazyZip4$$coll3:Lscala/collection/Iterable;
  #44 = Fieldref           #8.#43         // scala/collection/LazyZip4.scala$collection$LazyZip4$$coll3:Lscala/collection/Iterable;
  #45 = Utf8               scala$collection$LazyZip4$$coll4
  #46 = NameAndType        #45:#32        // scala$collection$LazyZip4$$coll4:Lscala/collection/Iterable;
  #47 = Fieldref           #8.#46         // scala/collection/LazyZip4.scala$collection$LazyZip4$$coll4:Lscala/collection/Iterable;
  #48 = Utf8               isEmpty
  #49 = Utf8               ()Z
  #50 = Utf8               scala/collection/AbstractIterator
  #51 = Class              #50            // scala/collection/AbstractIterator
  #52 = NameAndType        #48:#49        // isEmpty:()Z
  #53 = Methodref          #51.#52        // scala/collection/AbstractIterator.isEmpty:()Z
  #54 = Utf8               scala$collection$LazyZip4$$anon$$$outer
  #55 = Utf8               ()Lscala/collection/LazyZip4;
  #56 = Utf8               ()Lscala/collection/Iterator;
  #57 = NameAndType        #18:#19        // iterator:()Lscala/collection/AbstractIterator;
  #58 = Methodref          #2.#57         // scala/collection/LazyZip4$$anon$21.iterator:()Lscala/collection/AbstractIterator;
  #59 = Utf8               (Lscala/collection/LazyZip4;Lscala/Function4;)V
  #60 = NameAndType        #16:#17        // p$5:Lscala/Function4;
  #61 = Fieldref           #2.#60         // scala/collection/LazyZip4$$anon$21.p$5:Lscala/Function4;
  #62 = Utf8               ()V
  #63 = NameAndType        #21:#62        // "<init>":()V
  #64 = Methodref          #5.#63         // scala/collection/AbstractView."<init>":()V
  #65 = Utf8               Code
  #66 = Utf8               LineNumberTable
  #67 = Utf8               LocalVariableTable
  #68 = Utf8               Signature
  #69 = Utf8               StackMapTable
  #70 = Utf8               MethodParameters
  #71 = Utf8               InnerClasses
  #72 = Utf8               EnclosingMethod
  #73 = Utf8               SourceFile
  #74 = Utf8               ScalaInlineInfo
  #75 = Utf8               Scala
{
  private final scala.collection.LazyZip4 $outer;
    descriptor: Lscala/collection/LazyZip4;
    flags: (0x1012) ACC_PRIVATE, ACC_FINAL, ACC_SYNTHETIC

  public final scala.Function4 p$5;
    descriptor: Lscala/Function4;
    flags: (0x0011) ACC_PUBLIC, ACC_FINAL

  public scala.collection.AbstractIterator<scala.Tuple4<El1, El2, El3, El4>> iterator();
    descriptor: ()Lscala/collection/AbstractIterator;
    flags: (0x0001) ACC_PUBLIC
    Code:
      stack=3, locals=1, args_size=1
         0: new           #13                 // class scala/collection/LazyZip4$$anon$21$$anon$22
         3: dup
         4: aload_0
         5: invokespecial #24                 // Method scala/collection/LazyZip4$$anon$21$$anon$22."<init>":(Lscala/collection/LazyZip4$$anon$21;)V
         8: areturn
      LineNumberTable:
        line 334: 0
      LocalVariableTable:
        Start  Length  Slot  Name   Signature
            0       9     0  this   Lscala/collection/LazyZip4$$anon$21;
    Signature: #20                          // ()Lscala/collection/AbstractIterator<Lscala/Tuple4<TEl1;TEl2;TEl3;TEl4;>;>;

  public int knownSize();
    descriptor: ()I
    flags: (0x0001) ACC_PUBLIC
    Code:
      stack=2, locals=1, args_size=1
         0: aload_0
         1: getfield      #30                 // Field $outer:Lscala/collection/LazyZip4;
         4: getfield      #34                 // Field scala/collection/LazyZip4.scala$collection$LazyZip4$$coll1:Lscala/collection/Iterable;
         7: invokeinterface #38,  1           // InterfaceMethod scala/collection/Iterable.knownSize:()I
        12: iconst_0
        13: if_icmpeq     64
        16: aload_0
        17: getfield      #30                 // Field $outer:Lscala/collection/LazyZip4;
        20: getfield      #41                 // Field scala/collection/LazyZip4.scala$collection$LazyZip4$$coll2:Lscala/collection/Iterable;
        23: invokeinterface #38,  1           // InterfaceMethod scala/collection/Iterable.knownSize:()I
        28: iconst_0
        29: if_icmpeq     64
        32: aload_0
        33: getfield      #30                 // Field $outer:Lscala/collection/LazyZip4;
        36: getfield      #44                 // Field scala/collection/LazyZip4.scala$collection$LazyZip4$$coll3:Lscala/collection/Iterable;
        39: invokeinterface #38,  1           // InterfaceMethod scala/collection/Iterable.knownSize:()I
        44: iconst_0
        45: if_icmpeq     64
        48: aload_0
        49: getfield      #30                 // Field $outer:Lscala/collection/LazyZip4;
        52: getfield      #47                 // Field scala/collection/LazyZip4.scala$collection$LazyZip4$$coll4:Lscala/collection/Iterable;
        55: invokeinterface #38,  1           // InterfaceMethod scala/collection/Iterable.knownSize:()I
        60: iconst_0
        61: if_icmpne     66
        64: iconst_0
        65: ireturn
        66: iconst_m1
        67: ireturn
      StackMapTable: number_of_entries = 2
        frame_type = 251 /* same_frame_extended */
          offset_delta = 64
        frame_type = 1 /* same */
      LineNumberTable:
        line 359: 0
      LocalVariableTable:
        Start  Length  Slot  Name   Signature
            0      68     0  this   Lscala/collection/LazyZip4$$anon$21;

  public boolean isEmpty();
    descriptor: ()Z
    flags: (0x0001) ACC_PUBLIC
    Code:
      stack=3, locals=1, args_size=1
         0: new           #13                 // class scala/collection/LazyZip4$$anon$21$$anon$22
         3: dup
         4: aload_0
         5: invokespecial #24                 // Method scala/collection/LazyZip4$$anon$21$$anon$22."<init>":(Lscala/collection/LazyZip4$$anon$21;)V
         8: invokevirtual #53                 // Method scala/collection/AbstractIterator.isEmpty:()Z
        11: ireturn
      LineNumberTable:
        line 334: 0
        line 360: 8
      LocalVariableTable:
        Start  Length  Slot  Name   Signature
            0      12     0  this   Lscala/collection/LazyZip4$$anon$21;

  public scala.collection.LazyZip4 scala$collection$LazyZip4$$anon$$$outer();
    descriptor: ()Lscala/collection/LazyZip4;
    flags: (0x1001) ACC_PUBLIC, ACC_SYNTHETIC
    Code:
      stack=1, locals=1, args_size=1
         0: aload_0
         1: getfield      #30                 // Field $outer:Lscala/collection/LazyZip4;
         4: areturn
      LineNumberTable:
        line 333: 0
      LocalVariableTable:
        Start  Length  Slot  Name   Signature
            0       5     0  this   Lscala/collection/LazyZip4$$anon$21;

  public scala.collection.Iterator iterator();
    descriptor: ()Lscala/collection/Iterator;
    flags: (0x1041) ACC_PUBLIC, ACC_BRIDGE, ACC_SYNTHETIC
    Code:
      stack=1, locals=1, args_size=1
         0: aload_0
         1: invokevirtual #58                 // Method iterator:()Lscala/collection/AbstractIterator;
         4: areturn
      LineNumberTable:
        line 333: 0
      LocalVariableTable:
        Start  Length  Slot  Name   Signature
            0       5     0  this   Lscala/collection/LazyZip4$$anon$21;

  public scala.collection.LazyZip4$$anon$21(scala.collection.LazyZip4, scala.Function4);
    descriptor: (Lscala/collection/LazyZip4;Lscala/Function4;)V
    flags: (0x0001) ACC_PUBLIC
    Code:
      stack=2, locals=3, args_size=3
         0: aload_1
         1: ifnonnull     6
         4: aconst_null
         5: athrow
         6: aload_0
         7: aload_1
         8: putfield      #30                 // Field $outer:Lscala/collection/LazyZip4;
        11: aload_0
        12: aload_2
        13: putfield      #61                 // Field p$5:Lscala/Function4;
        16: aload_0
        17: invokespecial #64                 // Method scala/collection/AbstractView."<init>":()V
        20: return
      StackMapTable: number_of_entries = 1
        frame_type = 6 /* same */
      LineNumberTable:
        line 333: 0
        line 332: 11
        line 333: 16
      LocalVariableTable:
        Start  Length  Slot  Name   Signature
            0      21     0  this   Lscala/collection/LazyZip4$$anon$21;
            0      21     1 $outer   Lscala/collection/LazyZip4;
            0      21     2   p$5   Lscala/Function4;
    MethodParameters:
      Name                           Flags
      $outer                         final synthetic
      p$5                            final
}
InnerClasses:
  public final #2;                        // class scala/collection/LazyZip4$$anon$21
  public final #13;                       // class scala/collection/LazyZip4$$anon$21$$anon$22
EnclosingMethod: #8.#11                 // scala.collection.LazyZip4.filter
Signature: #3                           // Lscala/collection/AbstractView<Lscala/Tuple4<TEl1;TEl2;TEl3;TEl4;>;>;
SourceFile: "LazyZipOps.scala"
  ScalaInlineInfo: length = 0x22 (unknown attribute)
   01 01 00 06 00 15 00 3B 01 00 30 00 31 01 00 12
   00 13 01 00 12 00 38 01 00 1B 00 1C 01 00 36 00
   37 01
  Scala: length = 0x0 (unknown attribute)

