Classfile /Users/mw/Projects/slang-braindump/.jar/jar8/assemble/slang-braindump/assemble/content/scala/collection/LinearSeqIterator.class
  Last modified May 29, 2022; size 3596 bytes
  SHA-256 checksum 03e1a41240765b5514fef39ce9e0df3abf285eeec9416894e713b407c91f0694
  Compiled from "LinearSeq.scala"
public final class scala.collection.LinearSeqIterator<A extends java.lang.Object> extends scala.collection.AbstractIterator<A>
  minor version: 0
  major version: 52
  flags: (0x0031) ACC_PUBLIC, ACC_FINAL, ACC_SUPER
  this_class: #2                          // scala/collection/LinearSeqIterator
  super_class: #5                         // scala/collection/AbstractIterator
  interfaces: 0, fields: 1, methods: 6, attributes: 7
Constant pool:
    #1 = Utf8               scala/collection/LinearSeqIterator
    #2 = Class              #1            // scala/collection/LinearSeqIterator
    #3 = Utf8               <A:Ljava/lang/Object;>Lscala/collection/AbstractIterator<TA;>;
    #4 = Utf8               scala/collection/AbstractIterator
    #5 = Class              #4            // scala/collection/AbstractIterator
    #6 = Utf8               LinearSeq.scala
    #7 = Utf8               Lscala/reflect/ScalaSignature;
    #8 = Utf8               bytes
    #9 = Utf8               \u0006\u0005\u00153QAC\u0006\u0003\u0017=A\u0001B\t\u0001\u0003\u0002\u0003\u0006Ia\t\u0005\u0006U\u0001!\ta\u000b\u0004\u0007]\u0001\u0001\u000bQB\u0018\t\u0011M\u001a!\u0011!S\u0001\nQBQAK\u0002\u0005\u0002]B\u0001bO\u0002\t\u0006\u0004%\t\u0001\u0010\u0005\u0007{\u0001\u0001\u000b\u0015\u0002\u001d\t\u000by\u0002A\u0011A \t\u000b\r\u0003A\u0011\u0001#\u0003#1Kg.Z1s\'\u0016\f\u0018\n^3sCR|\'O\u0003\u0002\r\u001b\u0005Q1m\u001c7mK\u000e$\u0018n\u001c8\u000b\u00039\tQa]2bY\u0006,\"\u0001E\f\u0014\u0005\u0001\t\u0002c\u0001\n\u0014+5\t1\"\u0003\u0002\u0015\u0017\t\u0001\u0012IY:ue\u0006\u001cG/\u0013;fe\u0006$xN\u001d\t\u0003-]a\u0001\u0001B\u0003\u0019\u0001\t\u0007!DA\u0001B\u0007\u0001\t\"aG\u0010\u0011\u0005qiR\"A\u0007\n\u0005yi!a\u0002(pi\"Lgn\u001a\t\u00039\u0001J!!I\u0007\u0003\u0007\u0005s\u00170\u0001\u0003d_2d\u0007#\u0002\n%+\u0019J\u0013BA\u0013\f\u00051a\u0015N\\3beN+\u0017o\u00149t!\t\u0011r%\u0003\u0002)\u0017\tIA*\u001b8fCJ\u001cV-\u001d\t\u0004%\u001d*\u0012A\u0002\u001fj]&$h\b\u0006\u0002-[A\u0019!\u0003A\u000b\t\u000b\t\u0012\u0001\u0019A\u0012\u0003\u00111\u000b\'0_\"fY2\u001c\"a\u0001\u0019\u0011\u0005q\t\u0014B\u0001\u001a\u000e\u0005\u0019\te.\u001f*fM\u0006\u00111\u000f\u001e\t\u00049U\u001a\u0013B\u0001\u001c\u000e\u0005!a$-\u001f8b[\u0016tDC\u0001\u001d;!\tI4!D\u0001\u0001\u0011\u0019\u0019T\u0001\"a\u0001i\u0005\ta/F\u0001$\u0003\u0015!\b.Z:f\u0003\u001dA\u0017m\u001d(fqR,\u0012\u0001\u0011\t\u00039\u0005K!AQ\u0007\u0003\u000f\t{w\u000e\\3b]\u0006!a.\u001a=u)\u0005)\u0002
   #10 = Utf8               java/lang/invoke/MethodHandles$Lookup
   #11 = Class              #10           // java/lang/invoke/MethodHandles$Lookup
   #12 = Utf8               java/lang/invoke/MethodHandles
   #13 = Class              #12           // java/lang/invoke/MethodHandles
   #14 = Utf8               Lookup
   #15 = Utf8               scala/collection/LinearSeqIterator$LazyCell
   #16 = Class              #15           // scala/collection/LinearSeqIterator$LazyCell
   #17 = Utf8               LazyCell
   #18 = Utf8               these
   #19 = Utf8               Lscala/collection/LinearSeqIterator$LazyCell;
   #20 = Utf8               Lscala/collection/LinearSeqIterator<TA;>.LazyCell;
   #21 = Utf8               hasNext
   #22 = Utf8               ()Z
   #23 = NameAndType        #18:#19       // these:Lscala/collection/LinearSeqIterator$LazyCell;
   #24 = Fieldref           #2.#23        // scala/collection/LinearSeqIterator.these:Lscala/collection/LinearSeqIterator$LazyCell;
   #25 = Utf8               v
   #26 = Utf8               ()Lscala/collection/LinearSeqOps;
   #27 = NameAndType        #25:#26       // v:()Lscala/collection/LinearSeqOps;
   #28 = Methodref          #16.#27       // scala/collection/LinearSeqIterator$LazyCell.v:()Lscala/collection/LinearSeqOps;
   #29 = Utf8               scala/collection/LinearSeqOps
   #30 = Class              #29           // scala/collection/LinearSeqOps
   #31 = Utf8               nonEmpty
   #32 = NameAndType        #31:#22       // nonEmpty:()Z
   #33 = InterfaceMethodref #30.#32       // scala/collection/LinearSeqOps.nonEmpty:()Z
   #34 = Utf8               this
   #35 = Utf8               Lscala/collection/LinearSeqIterator;
   #36 = Utf8               next
   #37 = Utf8               ()Ljava/lang/Object;
   #38 = Utf8               ()TA;
   #39 = Utf8               scala/collection/Iterator
   #40 = Class              #39           // scala/collection/Iterator
   #41 = Utf8               isEmpty$
   #42 = Utf8               (Lscala/collection/Iterator;)Z
   #43 = NameAndType        #41:#42       // isEmpty$:(Lscala/collection/Iterator;)Z
   #44 = InterfaceMethodref #40.#43       // scala/collection/Iterator.isEmpty$:(Lscala/collection/Iterator;)Z
   #45 = Utf8               scala/collection/Iterator$
   #46 = Class              #45           // scala/collection/Iterator$
   #47 = Utf8               MODULE$
   #48 = Utf8               Lscala/collection/Iterator$;
   #49 = NameAndType        #47:#48       // MODULE$:Lscala/collection/Iterator$;
   #50 = Fieldref           #46.#49       // scala/collection/Iterator$.MODULE$:Lscala/collection/Iterator$;
   #51 = Utf8               scala$collection$Iterator$$_empty
   #52 = Utf8               Lscala/collection/Iterator;
   #53 = NameAndType        #51:#52       // scala$collection$Iterator$$_empty:Lscala/collection/Iterator;
   #54 = Fieldref           #46.#53       // scala/collection/Iterator$.scala$collection$Iterator$$_empty:Lscala/collection/Iterator;
   #55 = NameAndType        #36:#37       // next:()Ljava/lang/Object;
   #56 = InterfaceMethodref #40.#55       // scala/collection/Iterator.next:()Ljava/lang/Object;
   #57 = Utf8               head
   #58 = NameAndType        #57:#37       // head:()Ljava/lang/Object;
   #59 = InterfaceMethodref #30.#58       // scala/collection/LinearSeqOps.head:()Ljava/lang/Object;
   #60 = MethodType         #37           //  ()Ljava/lang/Object;
   #61 = Utf8               $anonfun$next$1
   #62 = Utf8               (Lscala/collection/LinearSeqOps;)Lscala/collection/LinearSeq;
   #63 = NameAndType        #61:#62       // $anonfun$next$1:(Lscala/collection/LinearSeqOps;)Lscala/collection/LinearSeq;
   #64 = Methodref          #2.#63        // scala/collection/LinearSeqIterator.$anonfun$next$1:(Lscala/collection/LinearSeqOps;)Lscala/collection/LinearSeq;
   #65 = MethodHandle       6:#64         // REF_invokeStatic scala/collection/LinearSeqIterator.$anonfun$next$1:(Lscala/collection/LinearSeqOps;)Lscala/collection/LinearSeq;
   #66 = Utf8               ()Lscala/collection/LinearSeq;
   #67 = MethodType         #66           //  ()Lscala/collection/LinearSeq;
   #68 = Integer            5
   #69 = Integer            1
   #70 = Utf8               java/lang/invoke/LambdaMetafactory
   #71 = Class              #70           // java/lang/invoke/LambdaMetafactory
   #72 = Utf8               altMetafactory
   #73 = Utf8               (Ljava/lang/invoke/MethodHandles$Lookup;Ljava/lang/String;Ljava/lang/invoke/MethodType;[Ljava/lang/Object;)Ljava/lang/invoke/CallSite;
   #74 = NameAndType        #72:#73       // altMetafactory:(Ljava/lang/invoke/MethodHandles$Lookup;Ljava/lang/String;Ljava/lang/invoke/MethodType;[Ljava/lang/Object;)Ljava/lang/invoke/CallSite;
   #75 = Methodref          #71.#74       // java/lang/invoke/LambdaMetafactory.altMetafactory:(Ljava/lang/invoke/MethodHandles$Lookup;Ljava/lang/String;Ljava/lang/invoke/MethodType;[Ljava/lang/Object;)Ljava/lang/invoke/CallSite;
   #76 = MethodHandle       6:#75         // REF_invokeStatic java/lang/invoke/LambdaMetafactory.altMetafactory:(Ljava/lang/invoke/MethodHandles$Lookup;Ljava/lang/String;Ljava/lang/invoke/MethodType;[Ljava/lang/Object;)Ljava/lang/invoke/CallSite;
   #77 = Utf8               apply
   #78 = Utf8               (Lscala/collection/LinearSeqOps;)Lscala/Function0;
   #79 = NameAndType        #77:#78       // apply:(Lscala/collection/LinearSeqOps;)Lscala/Function0;
   #80 = InvokeDynamic      #0:#79        // #0:apply:(Lscala/collection/LinearSeqOps;)Lscala/Function0;
   #81 = Utf8               <init>
   #82 = Utf8               (Lscala/collection/LinearSeqIterator;Lscala/Function0;)V
   #83 = NameAndType        #81:#82       // "<init>":(Lscala/collection/LinearSeqIterator;Lscala/Function0;)V
   #84 = Methodref          #16.#83       // scala/collection/LinearSeqIterator$LazyCell."<init>":(Lscala/collection/LinearSeqIterator;Lscala/Function0;)V
   #85 = Utf8               cur
   #86 = Utf8               Lscala/collection/LinearSeqOps;
   #87 = Utf8               result
   #88 = Utf8               Ljava/lang/Object;
   #89 = Utf8               $anonfun$these$1
   #90 = Utf8               (Lscala/collection/LinearSeqOps;)Lscala/collection/LinearSeqOps;
   #91 = Utf8               initialHead$1
   #92 = Utf8               cur$1
   #93 = Utf8               tail
   #94 = NameAndType        #93:#37       // tail:()Ljava/lang/Object;
   #95 = InterfaceMethodref #30.#94       // scala/collection/LinearSeqOps.tail:()Ljava/lang/Object;
   #96 = Utf8               scala/collection/LinearSeq
   #97 = Class              #96           // scala/collection/LinearSeq
   #98 = Utf8               (Lscala/collection/LinearSeqOps;)V
   #99 = Utf8               (Lscala/collection/LinearSeqOps<TA;Lscala/collection/LinearSeq;Lscala/collection/LinearSeq<TA;>;>;)V
  #100 = Utf8               coll
  #101 = Utf8               ()V
  #102 = NameAndType        #81:#101      // "<init>":()V
  #103 = Methodref          #5.#102       // scala/collection/AbstractIterator."<init>":()V
  #104 = NameAndType        #89:#90       // $anonfun$these$1:(Lscala/collection/LinearSeqOps;)Lscala/collection/LinearSeqOps;
  #105 = Methodref          #2.#104       // scala/collection/LinearSeqIterator.$anonfun$these$1:(Lscala/collection/LinearSeqOps;)Lscala/collection/LinearSeqOps;
  #106 = MethodHandle       6:#105        // REF_invokeStatic scala/collection/LinearSeqIterator.$anonfun$these$1:(Lscala/collection/LinearSeqOps;)Lscala/collection/LinearSeqOps;
  #107 = MethodType         #26           //  ()Lscala/collection/LinearSeqOps;
  #108 = InvokeDynamic      #1:#79        // #1:apply:(Lscala/collection/LinearSeqOps;)Lscala/Function0;
  #109 = Utf8               $deserializeLambda$
  #110 = Utf8               (Ljava/lang/invoke/SerializedLambda;)Ljava/lang/Object;
  #111 = Utf8               scala/runtime/LambdaDeserialize
  #112 = Class              #111          // scala/runtime/LambdaDeserialize
  #113 = Utf8               bootstrap
  #114 = Utf8               (Ljava/lang/invoke/MethodHandles$Lookup;Ljava/lang/String;Ljava/lang/invoke/MethodType;[Ljava/lang/invoke/MethodHandle;)Ljava/lang/invoke/CallSite;
  #115 = NameAndType        #113:#114     // bootstrap:(Ljava/lang/invoke/MethodHandles$Lookup;Ljava/lang/String;Ljava/lang/invoke/MethodType;[Ljava/lang/invoke/MethodHandle;)Ljava/lang/invoke/CallSite;
  #116 = Methodref          #112.#115     // scala/runtime/LambdaDeserialize.bootstrap:(Ljava/lang/invoke/MethodHandles$Lookup;Ljava/lang/String;Ljava/lang/invoke/MethodType;[Ljava/lang/invoke/MethodHandle;)Ljava/lang/invoke/CallSite;
  #117 = MethodHandle       6:#116        // REF_invokeStatic scala/runtime/LambdaDeserialize.bootstrap:(Ljava/lang/invoke/MethodHandles$Lookup;Ljava/lang/String;Ljava/lang/invoke/MethodType;[Ljava/lang/invoke/MethodHandle;)Ljava/lang/invoke/CallSite;
  #118 = Utf8               lambdaDeserialize
  #119 = NameAndType        #118:#110     // lambdaDeserialize:(Ljava/lang/invoke/SerializedLambda;)Ljava/lang/Object;
  #120 = InvokeDynamic      #2:#119       // #2:lambdaDeserialize:(Ljava/lang/invoke/SerializedLambda;)Ljava/lang/Object;
  #121 = Utf8               Signature
  #122 = Utf8               Code
  #123 = Utf8               LineNumberTable
  #124 = Utf8               LocalVariableTable
  #125 = Utf8               StackMapTable
  #126 = Utf8               MethodParameters
  #127 = Utf8               InnerClasses
  #128 = Utf8               SourceFile
  #129 = Utf8               RuntimeVisibleAnnotations
  #130 = Utf8               BootstrapMethods
  #131 = Utf8               ScalaInlineInfo
  #132 = Utf8               ScalaSig
{
  private scala.collection.LinearSeqIterator<A>.LazyCell these;
    descriptor: Lscala/collection/LinearSeqIterator$LazyCell;
    flags: (0x0002) ACC_PRIVATE
    Signature: #20                          // Lscala/collection/LinearSeqIterator<TA;>.LazyCell;

  public boolean hasNext();
    descriptor: ()Z
    flags: (0x0001) ACC_PUBLIC
    Code:
      stack=1, locals=1, args_size=1
         0: aload_0
         1: getfield      #24                 // Field these:Lscala/collection/LinearSeqIterator$LazyCell;
         4: invokevirtual #28                 // Method scala/collection/LinearSeqIterator$LazyCell.v:()Lscala/collection/LinearSeqOps;
         7: invokeinterface #33,  1           // InterfaceMethod scala/collection/LinearSeqOps.nonEmpty:()Z
        12: ireturn
      LineNumberTable:
        line 286: 0
      LocalVariableTable:
        Start  Length  Slot  Name   Signature
            0      13     0  this   Lscala/collection/LinearSeqIterator;

  public A next();
    descriptor: ()Ljava/lang/Object;
    flags: (0x0001) ACC_PUBLIC
    Code:
      stack=5, locals=3, args_size=1
         0: aload_0
         1: invokestatic  #44                 // InterfaceMethod scala/collection/Iterator.isEmpty$:(Lscala/collection/Iterator;)Z
         4: ifeq          20
         7: getstatic     #50                 // Field scala/collection/Iterator$.MODULE$:Lscala/collection/Iterator$;
        10: pop
        11: getstatic     #54                 // Field scala/collection/Iterator$.scala$collection$Iterator$$_empty:Lscala/collection/Iterator;
        14: invokeinterface #56,  1           // InterfaceMethod scala/collection/Iterator.next:()Ljava/lang/Object;
        19: areturn
        20: aload_0
        21: getfield      #24                 // Field these:Lscala/collection/LinearSeqIterator$LazyCell;
        24: invokevirtual #28                 // Method scala/collection/LinearSeqIterator$LazyCell.v:()Lscala/collection/LinearSeqOps;
        27: astore_1
        28: aload_1
        29: invokeinterface #59,  1           // InterfaceMethod scala/collection/LinearSeqOps.head:()Ljava/lang/Object;
        34: astore_2
        35: aload_0
        36: new           #16                 // class scala/collection/LinearSeqIterator$LazyCell
        39: dup
        40: aload_0
        41: aload_1
        42: invokedynamic #80,  0             // InvokeDynamic #0:apply:(Lscala/collection/LinearSeqOps;)Lscala/Function0;
        47: invokespecial #84                 // Method scala/collection/LinearSeqIterator$LazyCell."<init>":(Lscala/collection/LinearSeqIterator;Lscala/Function0;)V
        50: putfield      #24                 // Field these:Lscala/collection/LinearSeqIterator$LazyCell;
        53: aload_2
        54: areturn
      StackMapTable: number_of_entries = 1
        frame_type = 20 /* same */
      LineNumberTable:
        line 289: 0
        line 291: 20
        line 292: 28
        line 293: 35
        line 294: 53
      LocalVariableTable:
        Start  Length  Slot  Name   Signature
           28      26     1   cur   Lscala/collection/LinearSeqOps;
           35      19     2 result   Ljava/lang/Object;
            0      55     0  this   Lscala/collection/LinearSeqIterator;
    Signature: #38                          // ()TA;

  public static final scala.collection.LinearSeqOps $anonfun$these$1(scala.collection.LinearSeqOps);
    descriptor: (Lscala/collection/LinearSeqOps;)Lscala/collection/LinearSeqOps;
    flags: (0x1019) ACC_PUBLIC, ACC_STATIC, ACC_FINAL, ACC_SYNTHETIC
    Code:
      stack=1, locals=1, args_size=1
         0: aload_0
         1: areturn
      LineNumberTable:
        line 283: 0
      LocalVariableTable:
        Start  Length  Slot  Name   Signature
            0       2     0 initialHead$1   Lscala/collection/LinearSeqOps;
    MethodParameters:
      Name                           Flags
      initialHead$1                  final

  public static final scala.collection.LinearSeq $anonfun$next$1(scala.collection.LinearSeqOps);
    descriptor: (Lscala/collection/LinearSeqOps;)Lscala/collection/LinearSeq;
    flags: (0x1019) ACC_PUBLIC, ACC_STATIC, ACC_FINAL, ACC_SYNTHETIC
    Code:
      stack=1, locals=1, args_size=1
         0: aload_0
         1: invokeinterface #95,  1           // InterfaceMethod scala/collection/LinearSeqOps.tail:()Ljava/lang/Object;
         6: checkcast     #97                 // class scala/collection/LinearSeq
         9: areturn
      LineNumberTable:
        line 293: 0
      LocalVariableTable:
        Start  Length  Slot  Name   Signature
            0      10     0 cur$1   Lscala/collection/LinearSeqOps;
    MethodParameters:
      Name                           Flags
      cur$1                          final

  public scala.collection.LinearSeqIterator(scala.collection.LinearSeqOps<A, scala.collection.LinearSeq, scala.collection.LinearSeq<A>>);
    descriptor: (Lscala/collection/LinearSeqOps;)V
    flags: (0x0001) ACC_PUBLIC
    Code:
      stack=5, locals=2, args_size=2
         0: aload_0
         1: invokespecial #103                // Method scala/collection/AbstractIterator."<init>":()V
         4: aload_0
         5: new           #16                 // class scala/collection/LinearSeqIterator$LazyCell
         8: dup
         9: aload_0
        10: aload_1
        11: invokedynamic #108,  0            // InvokeDynamic #1:apply:(Lscala/collection/LinearSeqOps;)Lscala/Function0;
        16: invokespecial #84                 // Method scala/collection/LinearSeqIterator$LazyCell."<init>":(Lscala/collection/LinearSeqIterator;Lscala/Function0;)V
        19: putfield      #24                 // Field these:Lscala/collection/LinearSeqIterator$LazyCell;
        22: return
      LineNumberTable:
        line 275: 0
        line 279: 4
        line 283: 5
        line 279: 19
        line 275: 22
      LocalVariableTable:
        Start  Length  Slot  Name   Signature
            0      23     0  this   Lscala/collection/LinearSeqIterator;
            0      23     1  coll   Lscala/collection/LinearSeqOps;
    Signature: #99                          // (Lscala/collection/LinearSeqOps<TA;Lscala/collection/LinearSeq;Lscala/collection/LinearSeq<TA;>;>;)V
    MethodParameters:
      Name                           Flags
      coll                           final

  private static java.lang.Object $deserializeLambda$(java.lang.invoke.SerializedLambda);
    descriptor: (Ljava/lang/invoke/SerializedLambda;)Ljava/lang/Object;
    flags: (0x100a) ACC_PRIVATE, ACC_STATIC, ACC_SYNTHETIC
    Code:
      stack=1, locals=1, args_size=1
         0: aload_0
         1: invokedynamic #120,  0            // InvokeDynamic #2:lambdaDeserialize:(Ljava/lang/invoke/SerializedLambda;)Ljava/lang/Object;
         6: areturn
}
InnerClasses:
  public static final #14= #11 of #13;    // Lookup=class java/lang/invoke/MethodHandles$Lookup of class java/lang/invoke/MethodHandles
  private final #17= #16 of #2;           // LazyCell=class scala/collection/LinearSeqIterator$LazyCell of class scala/collection/LinearSeqIterator
Signature: #3                           // <A:Ljava/lang/Object;>Lscala/collection/AbstractIterator<TA;>;
SourceFile: "LinearSeq.scala"
RuntimeVisibleAnnotations:
  0: #7(#8=s#9)
    scala.reflect.ScalaSignature(
      bytes="\u0006\u0005\u00153QAC\u0006\u0003\u0017=A\u0001B\t\u0001\u0003\u0002\u0003\u0006Ia\t\u0005\u0006U\u0001!\ta\u000b\u0004\u0007]\u0001\u0001\u000bQB\u0018\t\u0011M\u001a!\u0011!S\u0001\nQBQAK\u0002\u0005\u0002]B\u0001bO\u0002\t\u0006\u0004%\t\u0001\u0010\u0005\u0007{\u0001\u0001\u000b\u0015\u0002\u001d\t\u000by\u0002A\u0011A \t\u000b\r\u0003A\u0011\u0001#\u0003#1Kg.Z1s\'\u0016\f\u0018\n^3sCR|\'O\u0003\u0002\r\u001b\u0005Q1m\u001c7mK\u000e$\u0018n\u001c8\u000b\u00039\tQa]2bY\u0006,\"\u0001E\f\u0014\u0005\u0001\t\u0002c\u0001\n\u0014+5\t1\"\u0003\u0002\u0015\u0017\t\u0001\u0012IY:ue\u0006\u001cG/\u0013;fe\u0006$xN\u001d\t\u0003-]a\u0001\u0001B\u0003\u0019\u0001\t\u0007!DA\u0001B\u0007\u0001\t\"aG\u0010\u0011\u0005qiR\"A\u0007\n\u0005yi!a\u0002(pi\"Lgn\u001a\t\u00039\u0001J!!I\u0007\u0003\u0007\u0005s\u00170\u0001\u0003d_2d\u0007#\u0002\n%+\u0019J\u0013BA\u0013\f\u00051a\u0015N\\3beN+\u0017o\u00149t!\t\u0011r%\u0003\u0002)\u0017\tIA*\u001b8fCJ\u001cV-\u001d\t\u0004%\u001d*\u0012A\u0002\u001fj]&$h\b\u0006\u0002-[A\u0019!\u0003A\u000b\t\u000b\t\u0012\u0001\u0019A\u0012\u0003\u00111\u000b\'0_\"fY2\u001c\"a\u0001\u0019\u0011\u0005q\t\u0014B\u0001\u001a\u000e\u0005\u0019\te.\u001f*fM\u0006\u00111\u000f\u001e\t\u00049U\u001a\u0013B\u0001\u001c\u000e\u0005!a$-\u001f8b[\u0016tDC\u0001\u001d;!\tI4!D\u0001\u0001\u0011\u0019\u0019T\u0001\"a\u0001i\u0005\ta/F\u0001$\u0003\u0015!\b.Z:f\u0003\u001dA\u0017m\u001d(fqR,\u0012\u0001\u0011\t\u00039\u0005K!AQ\u0007\u0003\u000f\t{w\u000e\\3b]\u0006!a.\u001a=u)\u0005)\u0002"
    )
BootstrapMethods:
  0: #76 REF_invokeStatic java/lang/invoke/LambdaMetafactory.altMetafactory:(Ljava/lang/invoke/MethodHandles$Lookup;Ljava/lang/String;Ljava/lang/invoke/MethodType;[Ljava/lang/Object;)Ljava/lang/invoke/CallSite;
    Method arguments:
      #60 ()Ljava/lang/Object;
      #65 REF_invokeStatic scala/collection/LinearSeqIterator.$anonfun$next$1:(Lscala/collection/LinearSeqOps;)Lscala/collection/LinearSeq;
      #67 ()Lscala/collection/LinearSeq;
      #68 5
      #69 1
      #67 ()Lscala/collection/LinearSeq;
  1: #76 REF_invokeStatic java/lang/invoke/LambdaMetafactory.altMetafactory:(Ljava/lang/invoke/MethodHandles$Lookup;Ljava/lang/String;Ljava/lang/invoke/MethodType;[Ljava/lang/Object;)Ljava/lang/invoke/CallSite;
    Method arguments:
      #60 ()Ljava/lang/Object;
      #106 REF_invokeStatic scala/collection/LinearSeqIterator.$anonfun$these$1:(Lscala/collection/LinearSeqOps;)Lscala/collection/LinearSeqOps;
      #107 ()Lscala/collection/LinearSeqOps;
      #68 5
      #69 1
      #107 ()Lscala/collection/LinearSeqOps;
  2: #117 REF_invokeStatic scala/runtime/LambdaDeserialize.bootstrap:(Ljava/lang/invoke/MethodHandles$Lookup;Ljava/lang/String;Ljava/lang/invoke/MethodType;[Ljava/lang/invoke/MethodHandle;)Ljava/lang/invoke/CallSite;
    Method arguments:
      #65 REF_invokeStatic scala/collection/LinearSeqIterator.$anonfun$next$1:(Lscala/collection/LinearSeqOps;)Lscala/collection/LinearSeq;
      #106 REF_invokeStatic scala/collection/LinearSeqIterator.$anonfun$these$1:(Lscala/collection/LinearSeqOps;)Lscala/collection/LinearSeqOps;
  ScalaInlineInfo: length = 0x1D (unknown attribute)
   01 01 00 05 00 3D 00 3E 01 00 59 00 5A 01 00 51
   00 62 01 00 15 00 16 01 00 24 00 25 01
  ScalaSig: length = 0x3 (unknown attribute)
   05 02 00
