Classfile /Users/mw/Projects/slang-braindump/.jar/jar8/assemble/slang-braindump/assemble/content/scala/collection/Map.class
  Last modified May 29, 2022; size 6622 bytes
  SHA-256 checksum d6f860c33a63cad1429a5fbf5d2e5639a524e1685b4df5f2453db1f5b50281c4
  Compiled from "Map.scala"
public interface scala.collection.Map<K extends java.lang.Object, V extends java.lang.Object> extends scala.collection.Iterable<scala.Tuple2<K, V>>, scala.collection.MapFactoryDefaults<K, V, scala.collection.Map, scala.collection.Iterable>, scala.Equals
  minor version: 0
  major version: 52
  flags: (0x0601) ACC_PUBLIC, ACC_INTERFACE, ACC_ABSTRACT
  this_class: #2                          // scala/collection/Map
  super_class: #5                         // java/lang/Object
  interfaces: 3, fields: 0, methods: 20, attributes: 7
Constant pool:
    #1 = Utf8               scala/collection/Map
    #2 = Class              #1            // scala/collection/Map
    #3 = Utf8               <K:Ljava/lang/Object;V:Ljava/lang/Object;>Ljava/lang/Object;Lscala/collection/Iterable<Lscala/Tuple2<TK;TV;>;>;Lscala/collection/MapFactoryDefaults<TK;TV;Lscala/collection/Map;Lscala/collection/Iterable;>;Lscala/Equals;
    #4 = Utf8               java/lang/Object
    #5 = Class              #4            // java/lang/Object
    #6 = Utf8               scala/collection/Iterable
    #7 = Class              #6            // scala/collection/Iterable
    #8 = Utf8               scala/collection/MapFactoryDefaults
    #9 = Class              #8            // scala/collection/MapFactoryDefaults
   #10 = Utf8               scala/Equals
   #11 = Class              #10           // scala/Equals
   #12 = Utf8               Map.scala
   #13 = Utf8               Lscala/reflect/ScalaSignature;
   #14 = Utf8               bytes
   #15 = Utf8               \u0006\u0005\u0005Mca\u0002\n\u0014!\u0003\r\t\u0001\u0007\u0005\u0006\u007f\u0001!\t\u0001\u0011\u0005\u0006\t\u0002!\t!\u0012\u0005\u0006\u0013\u0002!\tA\u0013\u0005\u0006!\u0002!\t%\u0015\u0005\u0006)\u0002!\t%\u0016\u0005\u00063\u00021\tA\u0017\u0005\u00063\u00021\ta\u001a\u0005\u0007i\u0002\u0001K\u0011K;\t\u000f\u0005\r\u0001\u0001\"\u0011\u0002\u0006\u001d9\u0011qA\n\t\u0002\u0005%aA\u0002\n\u0014\u0011\u0003\tY\u0001C\u0004\u0002\u001c-!\t!!\b\t\u0013\u0005}1B1A\u0005\n\u0005\u0005\u0002bBA\u0012\u0017\u0001\u0006IA\u0007\u0005\n\u0003KY!\u0019!C\u0005\u0003OA\u0001\"a\f\fA\u0003%\u0011\u0011\u0006\u0005\n\u0003cY\u0011\u0011!C\u0005\u0003g\u00111!T1q\u0015\t!R#\u0001\u0006d_2dWm\u0019;j_:T\u0011AF\u0001\u0006g\u000e\fG.Y\u0002\u0001+\rIr%M\n\u0007\u0001iq2\u0007\u000f\u001f\u0011\u0005maR\"A\u000b\n\u0005u)\"AB!osJ+g\rE\u0002 A\tj\u0011aE\u0005\u0003CM\u0011\u0001\"\u0013;fe\u0006\u0014G.\u001a\t\u00057\r*\u0003\'\u0003\u0002%+\t1A+\u001e9mKJ\u0002\"AJ\u0014\r\u0001\u0011)\u0001\u0006\u0001b\u0001S\t\t1*\u0005\u0002+[A\u00111dK\u0005\u0003YU\u0011qAT8uQ&tw\r\u0005\u0002\u001c]%\u0011q&\u0006\u0002\u0004\u0003:L\bC\u0001\u00142\t\u0019\u0011\u0004\u0001\"b\u0001S\t\ta\u000b\u0005\u0004 i\u0015\u0002dgN\u0005\u0003kM\u0011a!T1q\u001fB\u001c\bCA\u0010\u0001!\u0011y\u0002!\n\u0019\u0011\r}IT\u0005\r\u001c<\u0013\tQ4C\u0001\nNCB4\u0015m\u0019;pef$UMZ1vYR\u001c\bCA\u0010!!\tYR(\u0003\u0002?+\t1Q)];bYN\fa\u0001J5oSR$C#A!\u0011\u0005m\u0011\u0015BA\"\u0016\u0005\u0011)f.\u001b;\u0002\u00155\f\u0007OR1di>\u0014\u00180F\u0001G!\ryrIN\u0005\u0003\u0011N\u0011!\"T1q\r\u0006\u001cGo\u001c:z\u0003!\u0019\u0017M\\#rk\u0006dGCA&O!\tYB*\u0003\u0002N+\t9!i\\8mK\u0006t\u0007\"B(\u0004\u0001\u0004i\u0013\u0001\u0002;iCR\fa!Z9vC2\u001cHCA&S\u0011\u0015\u0019F\u00011\u0001.\u0003\u0005y\u0017\u0001\u00035bg\"\u001cu\u000eZ3\u0015\u0003Y\u0003\"aG,\n\u0005a+\"aA%oi\u00061A%\\5okN$\"aN.\t\u000bq3\u0001\u0019A\u0013\u0002\u0007-,\u0017\u0010\u000b\u0004\u0007=\u0006\u0014G-\u001a\t\u00037}K!\u0001Y\u000b\u0003\u0015\u0011,\u0007O]3dCR,G-A\u0004nKN\u001c\u0018mZ3\"\u0003\r\fA%V:fA5\u0002sN\u001d\u0011sK6|g/\u001a3!_:\u0004\u0013M\u001c\u0011j[6,H/\u00192mK\u0002j\u0015\r]\u0001\u0006g&t7-Z\u0011\u0002M\u00061!GL\u00194]A\"Ba\u000e5kY\")\u0011n\u0002a\u0001K\u0005!1.Z=2\u0011\u0015Yw\u00011\u0001&\u0003\u0011YW-\u001f\u001a\t\u000b5<\u0001\u0019\u00018\u0002\t-,\u0017p\u001d\t\u00047=,\u0013B\u00019\u0016\u0005)a$/\u001a9fCR,GM\u0010\u0015\u0007\u000fy\u000b\'\u000fZ3\"\u0003M\f\u0001&V:fA5j\u0003e\u001c:!e\u0016lwN^3e\u00032d\u0007e\u001c8!C:\u0004\u0013.\\7vi\u0006\u0014G.\u001a\u0011NCB\fAb\u001d;sS:<\u0007K]3gSb,\u0012A\u001e\t\u0003ozt!\u0001\u001f?\u0011\u0005e,R\"\u0001>\u000b\u0005m<\u0012A\u0002\u001fs_>$h(\u0003\u0002~+\u00051\u0001K]3eK\u001aL1a`A\u0001\u0005\u0019\u0019FO]5oO*\u0011Q0F\u0001\ti>\u001cFO]5oOR\ta/A\u0002NCB\u0004\"aH\u0006\u0014\u0007-\ti\u0001E\u0003\u0002\u0010\u0005UaGD\u0002 \u0003#I1!a\u0005\u0014\u0003)i\u0015\r\u001d$bGR|\'/_\u0005\u0005\u0003/\tIB\u0001\u0005EK2,w-\u0019;f\u0015\r\t\u0019bE\u0001\u0007y%t\u0017\u000e\u001e \u0015\u0005\u0005%\u0011a\u0004#fM\u0006,H\u000e^*f]RLg.\u001a7\u0016\u0003i\t\u0001\u0003R3gCVdGoU3oi&tW\r\u001c\u0011\u0002#\u0011+g-Y;miN+g\u000e^5oK24e.\u0006\u0002\u0002*A!1$a\u000b\u001b\u0013\r\ti#\u0006\u0002\n\rVt7\r^5p]B\n!\u0003R3gCVdGoU3oi&tW\r\u001c$oA\u0005aqO]5uKJ+\u0007\u000f\\1dKR\u0011\u0011Q\u0007\t\u0005\u0003o\t\t%\u0004\u0002\u0002:)!\u00111HA\u001f\u0003\u0011a\u0017M\\4\u000b\u0005\u0005}\u0012\u0001\u00026bm\u0006LA!a\u0011\u0002:\t1qJ\u00196fGRDsaCA$\u0003\u001b\ny\u0005E\u0002\u001c\u0003\u0013J1!a\u0013\u0016\u0005A\u0019VM]5bYZ+\'o]5p]VKE)A\u0003wC2,XMH\u0001\u0004Q\u001dQ\u0011qIA\'\u0003\u001f\u0002
   #16 = Utf8               java/lang/invoke/MethodHandles$Lookup
   #17 = Class              #16           // java/lang/invoke/MethodHandles$Lookup
   #18 = Utf8               java/lang/invoke/MethodHandles
   #19 = Class              #18           // java/lang/invoke/MethodHandles
   #20 = Utf8               Lookup
   #21 = Utf8               newBuilder
   #22 = Utf8               ()Lscala/collection/mutable/Builder;
   #23 = Utf8               <K:Ljava/lang/Object;V:Ljava/lang/Object;>()Lscala/collection/mutable/Builder<Lscala/Tuple2<TK;TV;>;Lscala/collection/Map<TK;TV;>;>;
   #24 = Utf8               scala/collection/Map$
   #25 = Class              #24           // scala/collection/Map$
   #26 = Utf8               MODULE$
   #27 = Utf8               Lscala/collection/Map$;
   #28 = NameAndType        #26:#27       // MODULE$:Lscala/collection/Map$;
   #29 = Fieldref           #25.#28       // scala/collection/Map$.MODULE$:Lscala/collection/Map$;
   #30 = NameAndType        #21:#22       // newBuilder:()Lscala/collection/mutable/Builder;
   #31 = Methodref          #25.#30       // scala/collection/Map$.newBuilder:()Lscala/collection/mutable/Builder;
   #32 = Utf8               from
   #33 = Utf8               (Lscala/collection/IterableOnce;)Ljava/lang/Object;
   #34 = Utf8               it
   #35 = NameAndType        #32:#33       // from:(Lscala/collection/IterableOnce;)Ljava/lang/Object;
   #36 = Methodref          #25.#35       // scala/collection/Map$.from:(Lscala/collection/IterableOnce;)Ljava/lang/Object;
   #37 = Utf8               Lscala/collection/IterableOnce;
   #38 = Utf8               mapFactory$
   #39 = Utf8               (Lscala/collection/Map;)Lscala/collection/MapFactory;
   #40 = Utf8               $this
   #41 = Utf8               mapFactory
   #42 = Utf8               ()Lscala/collection/MapFactory;
   #43 = NameAndType        #41:#42       // mapFactory:()Lscala/collection/MapFactory;
   #44 = InterfaceMethodref #2.#43        // scala/collection/Map.mapFactory:()Lscala/collection/MapFactory;
   #45 = Utf8               Lscala/collection/Map;
   #46 = Utf8               ()Lscala/collection/MapFactory<Lscala/collection/Map;>;
   #47 = Utf8               this
   #48 = Utf8               canEqual$
   #49 = Utf8               (Lscala/collection/Map;Ljava/lang/Object;)Z
   #50 = Utf8               that
   #51 = Utf8               canEqual
   #52 = Utf8               (Ljava/lang/Object;)Z
   #53 = NameAndType        #51:#52       // canEqual:(Ljava/lang/Object;)Z
   #54 = InterfaceMethodref #2.#53        // scala/collection/Map.canEqual:(Ljava/lang/Object;)Z
   #55 = Utf8               Ljava/lang/Object;
   #56 = Utf8               equals$
   #57 = Utf8               o
   #58 = Utf8               equals
   #59 = NameAndType        #58:#52       // equals:(Ljava/lang/Object;)Z
   #60 = InterfaceMethodref #2.#59        // scala/collection/Map.equals:(Ljava/lang/Object;)Z
   #61 = Utf8               java/lang/ClassCastException
   #62 = Class              #61           // java/lang/ClassCastException
   #63 = Utf8               size
   #64 = Utf8               ()I
   #65 = NameAndType        #63:#64       // size:()I
   #66 = InterfaceMethodref #2.#65        // scala/collection/Map.size:()I
   #67 = Utf8               (Ljava/lang/Object;)Ljava/lang/Object;
   #68 = MethodType         #67           //  (Ljava/lang/Object;)Ljava/lang/Object;
   #69 = Utf8               $anonfun$equals$1$adapted
   #70 = Utf8               (Lscala/collection/Map;Lscala/Tuple2;)Ljava/lang/Object;
   #71 = NameAndType        #69:#70       // $anonfun$equals$1$adapted:(Lscala/collection/Map;Lscala/Tuple2;)Ljava/lang/Object;
   #72 = InterfaceMethodref #2.#71        // scala/collection/Map.$anonfun$equals$1$adapted:(Lscala/collection/Map;Lscala/Tuple2;)Ljava/lang/Object;
   #73 = MethodHandle       6:#72         // REF_invokeStatic scala/collection/Map.$anonfun$equals$1$adapted:(Lscala/collection/Map;Lscala/Tuple2;)Ljava/lang/Object;
   #74 = Utf8               (Lscala/Tuple2;)Ljava/lang/Object;
   #75 = MethodType         #74           //  (Lscala/Tuple2;)Ljava/lang/Object;
   #76 = Integer            5
   #77 = Integer            1
   #78 = Utf8               java/lang/invoke/LambdaMetafactory
   #79 = Class              #78           // java/lang/invoke/LambdaMetafactory
   #80 = Utf8               altMetafactory
   #81 = Utf8               (Ljava/lang/invoke/MethodHandles$Lookup;Ljava/lang/String;Ljava/lang/invoke/MethodType;[Ljava/lang/Object;)Ljava/lang/invoke/CallSite;
   #82 = NameAndType        #80:#81       // altMetafactory:(Ljava/lang/invoke/MethodHandles$Lookup;Ljava/lang/String;Ljava/lang/invoke/MethodType;[Ljava/lang/Object;)Ljava/lang/invoke/CallSite;
   #83 = Methodref          #79.#82       // java/lang/invoke/LambdaMetafactory.altMetafactory:(Ljava/lang/invoke/MethodHandles$Lookup;Ljava/lang/String;Ljava/lang/invoke/MethodType;[Ljava/lang/Object;)Ljava/lang/invoke/CallSite;
   #84 = MethodHandle       6:#83         // REF_invokeStatic java/lang/invoke/LambdaMetafactory.altMetafactory:(Ljava/lang/invoke/MethodHandles$Lookup;Ljava/lang/String;Ljava/lang/invoke/MethodType;[Ljava/lang/Object;)Ljava/lang/invoke/CallSite;
   #85 = Utf8               apply
   #86 = Utf8               (Lscala/collection/Map;)Lscala/Function1;
   #87 = NameAndType        #85:#86       // apply:(Lscala/collection/Map;)Lscala/Function1;
   #88 = InvokeDynamic      #0:#87        // #0:apply:(Lscala/collection/Map;)Lscala/Function1;
   #89 = Utf8               forall
   #90 = Utf8               (Lscala/Function1;)Z
   #91 = NameAndType        #89:#90       // forall:(Lscala/Function1;)Z
   #92 = InterfaceMethodref #2.#91        // scala/collection/Map.forall:(Lscala/Function1;)Z
   #93 = Utf8               hashCode$
   #94 = Utf8               (Lscala/collection/Map;)I
   #95 = Utf8               hashCode
   #96 = NameAndType        #95:#64       // hashCode:()I
   #97 = InterfaceMethodref #2.#96        // scala/collection/Map.hashCode:()I
   #98 = Utf8               scala/util/hashing/MurmurHash3$
   #99 = Class              #98           // scala/util/hashing/MurmurHash3$
  #100 = Utf8               Lscala/util/hashing/MurmurHash3$;
  #101 = NameAndType        #26:#100      // MODULE$:Lscala/util/hashing/MurmurHash3$;
  #102 = Fieldref           #99.#101      // scala/util/hashing/MurmurHash3$.MODULE$:Lscala/util/hashing/MurmurHash3$;
  #103 = Utf8               mapHash
  #104 = NameAndType        #103:#94      // mapHash:(Lscala/collection/Map;)I
  #105 = Methodref          #99.#104      // scala/util/hashing/MurmurHash3$.mapHash:(Lscala/collection/Map;)I
  #106 = Utf8               $minus
  #107 = Utf8               (Ljava/lang/Object;)Lscala/collection/Map;
  #108 = Utf8               (TK;)Lscala/collection/Map<TK;TV;>;
  #109 = Utf8               key
  #110 = Utf8               (Ljava/lang/Object;Ljava/lang/Object;Lscala/collection/immutable/Seq;)Lscala/collection/Map;
  #111 = Utf8               (TK;TK;Lscala/collection/immutable/Seq<TK;>;)Lscala/collection/Map<TK;TV;>;
  #112 = Utf8               key1
  #113 = Utf8               key2
  #114 = Utf8               keys
  #115 = Utf8               stringPrefix$
  #116 = Utf8               (Lscala/collection/Map;)Ljava/lang/String;
  #117 = Utf8               stringPrefix
  #118 = Utf8               ()Ljava/lang/String;
  #119 = NameAndType        #117:#118     // stringPrefix:()Ljava/lang/String;
  #120 = InterfaceMethodref #2.#119       // scala/collection/Map.stringPrefix:()Ljava/lang/String;
  #121 = Utf8               Map
  #122 = String             #121          // Map
  #123 = Utf8               toString$
  #124 = Utf8               toString
  #125 = NameAndType        #124:#118     // toString:()Ljava/lang/String;
  #126 = InterfaceMethodref #2.#125       // scala/collection/Map.toString:()Ljava/lang/String;
  #127 = Utf8               (Lscala/collection/Iterable;)Ljava/lang/String;
  #128 = NameAndType        #123:#127     // toString$:(Lscala/collection/Iterable;)Ljava/lang/String;
  #129 = InterfaceMethodref #7.#128       // scala/collection/Iterable.toString$:(Lscala/collection/Iterable;)Ljava/lang/String;
  #130 = Utf8               $anonfun$equals$1
  #131 = Utf8               (Lscala/collection/Map;Lscala/Tuple2;)Z
  #132 = Utf8               x2$1
  #133 = Utf8               kv
  #134 = Utf8               scala/Tuple2
  #135 = Class              #134          // scala/Tuple2
  #136 = Utf8               _1
  #137 = Utf8               ()Ljava/lang/Object;
  #138 = NameAndType        #136:#137     // _1:()Ljava/lang/Object;
  #139 = Methodref          #135.#138     // scala/Tuple2._1:()Ljava/lang/Object;
  #140 = Utf8               scala$collection$Map$$DefaultSentinelFn
  #141 = Utf8               ()Lscala/Function0;
  #142 = NameAndType        #140:#141     // scala$collection$Map$$DefaultSentinelFn:()Lscala/Function0;
  #143 = Methodref          #25.#142      // scala/collection/Map$.scala$collection$Map$$DefaultSentinelFn:()Lscala/Function0;
  #144 = Utf8               getOrElse
  #145 = Utf8               (Ljava/lang/Object;Lscala/Function0;)Ljava/lang/Object;
  #146 = NameAndType        #144:#145     // getOrElse:(Ljava/lang/Object;Lscala/Function0;)Ljava/lang/Object;
  #147 = InterfaceMethodref #2.#146       // scala/collection/Map.getOrElse:(Ljava/lang/Object;Lscala/Function0;)Ljava/lang/Object;
  #148 = Utf8               _2
  #149 = NameAndType        #148:#137     // _2:()Ljava/lang/Object;
  #150 = Methodref          #135.#149     // scala/Tuple2._2:()Ljava/lang/Object;
  #151 = Utf8               scala/runtime/BoxesRunTime
  #152 = Class              #151          // scala/runtime/BoxesRunTime
  #153 = Utf8               (Ljava/lang/Object;Ljava/lang/Object;)Z
  #154 = NameAndType        #58:#153      // equals:(Ljava/lang/Object;Ljava/lang/Object;)Z
  #155 = Methodref          #152.#154     // scala/runtime/BoxesRunTime.equals:(Ljava/lang/Object;Ljava/lang/Object;)Z
  #156 = Utf8               Lscala/Tuple2;
  #157 = Utf8               $init$
  #158 = Utf8               (Lscala/collection/Map;)V
  #159 = NameAndType        #130:#131     // $anonfun$equals$1:(Lscala/collection/Map;Lscala/Tuple2;)Z
  #160 = InterfaceMethodref #2.#159       // scala/collection/Map.$anonfun$equals$1:(Lscala/collection/Map;Lscala/Tuple2;)Z
  #161 = Utf8               boxToBoolean
  #162 = Utf8               (Z)Ljava/lang/Boolean;
  #163 = NameAndType        #161:#162     // boxToBoolean:(Z)Ljava/lang/Boolean;
  #164 = Methodref          #152.#163     // scala/runtime/BoxesRunTime.boxToBoolean:(Z)Ljava/lang/Boolean;
  #165 = Utf8               $deserializeLambda$
  #166 = Utf8               (Ljava/lang/invoke/SerializedLambda;)Ljava/lang/Object;
  #167 = Utf8               scala/runtime/LambdaDeserialize
  #168 = Class              #167          // scala/runtime/LambdaDeserialize
  #169 = Utf8               bootstrap
  #170 = Utf8               (Ljava/lang/invoke/MethodHandles$Lookup;Ljava/lang/String;Ljava/lang/invoke/MethodType;[Ljava/lang/invoke/MethodHandle;)Ljava/lang/invoke/CallSite;
  #171 = NameAndType        #169:#170     // bootstrap:(Ljava/lang/invoke/MethodHandles$Lookup;Ljava/lang/String;Ljava/lang/invoke/MethodType;[Ljava/lang/invoke/MethodHandle;)Ljava/lang/invoke/CallSite;
  #172 = Methodref          #168.#171     // scala/runtime/LambdaDeserialize.bootstrap:(Ljava/lang/invoke/MethodHandles$Lookup;Ljava/lang/String;Ljava/lang/invoke/MethodType;[Ljava/lang/invoke/MethodHandle;)Ljava/lang/invoke/CallSite;
  #173 = MethodHandle       6:#172        // REF_invokeStatic scala/runtime/LambdaDeserialize.bootstrap:(Ljava/lang/invoke/MethodHandles$Lookup;Ljava/lang/String;Ljava/lang/invoke/MethodType;[Ljava/lang/invoke/MethodHandle;)Ljava/lang/invoke/CallSite;
  #174 = Utf8               lambdaDeserialize
  #175 = NameAndType        #174:#166     // lambdaDeserialize:(Ljava/lang/invoke/SerializedLambda;)Ljava/lang/Object;
  #176 = InvokeDynamic      #1:#175       // #1:lambdaDeserialize:(Ljava/lang/invoke/SerializedLambda;)Ljava/lang/Object;
  #177 = Utf8               Code
  #178 = Utf8               Signature
  #179 = Utf8               LocalVariableTable
  #180 = Utf8               MethodParameters
  #181 = Utf8               LineNumberTable
  #182 = Utf8               StackMapTable
  #183 = Utf8               Deprecated
  #184 = Utf8               InnerClasses
  #185 = Utf8               SourceFile
  #186 = Utf8               RuntimeVisibleAnnotations
  #187 = Utf8               BootstrapMethods
  #188 = Utf8               ScalaInlineInfo
  #189 = Utf8               ScalaSig
{
  public static <K extends java.lang.Object, V extends java.lang.Object> scala.collection.mutable.Builder<scala.Tuple2<K, V>, scala.collection.Map<K, V>> newBuilder();
    descriptor: ()Lscala/collection/mutable/Builder;
    flags: (0x0009) ACC_PUBLIC, ACC_STATIC
    Code:
      stack=1, locals=0, args_size=0
         0: getstatic     #29                 // Field scala/collection/Map$.MODULE$:Lscala/collection/Map$;
         3: invokevirtual #31                 // Method scala/collection/Map$.newBuilder:()Lscala/collection/mutable/Builder;
         6: areturn
    Signature: #23                          // <K:Ljava/lang/Object;V:Ljava/lang/Object;>()Lscala/collection/mutable/Builder<Lscala/Tuple2<TK;TV;>;Lscala/collection/Map<TK;TV;>;>;

  public static java.lang.Object from(scala.collection.IterableOnce);
    descriptor: (Lscala/collection/IterableOnce;)Ljava/lang/Object;
    flags: (0x0009) ACC_PUBLIC, ACC_STATIC
    Code:
      stack=2, locals=1, args_size=1
         0: getstatic     #29                 // Field scala/collection/Map$.MODULE$:Lscala/collection/Map$;
         3: aload_0
         4: invokevirtual #36                 // Method scala/collection/Map$.from:(Lscala/collection/IterableOnce;)Ljava/lang/Object;
         7: areturn
      LocalVariableTable:
        Start  Length  Slot  Name   Signature
            0       8     0    it   Lscala/collection/IterableOnce;
    MethodParameters:
      Name                           Flags
      it                             final

  public static scala.collection.MapFactory mapFactory$(scala.collection.Map);
    descriptor: (Lscala/collection/Map;)Lscala/collection/MapFactory;
    flags: (0x1009) ACC_PUBLIC, ACC_STATIC, ACC_SYNTHETIC
    Code:
      stack=1, locals=1, args_size=1
         0: aload_0
         1: invokespecial #44                 // InterfaceMethod mapFactory:()Lscala/collection/MapFactory;
         4: areturn
      LineNumberTable:
        line 28: 0
      LocalVariableTable:
        Start  Length  Slot  Name   Signature
            0       5     0 $this   Lscala/collection/Map;
    MethodParameters:
      Name                           Flags
      $this                          final synthetic

  public default scala.collection.MapFactory<scala.collection.Map> mapFactory();
    descriptor: ()Lscala/collection/MapFactory;
    flags: (0x0001) ACC_PUBLIC
    Code:
      stack=1, locals=1, args_size=1
         0: getstatic     #29                 // Field scala/collection/Map$.MODULE$:Lscala/collection/Map$;
         3: areturn
      LineNumberTable:
        line 28: 0
      LocalVariableTable:
        Start  Length  Slot  Name   Signature
            0       4     0  this   Lscala/collection/Map;
    Signature: #46                          // ()Lscala/collection/MapFactory<Lscala/collection/Map;>;

  public static boolean canEqual$(scala.collection.Map, java.lang.Object);
    descriptor: (Lscala/collection/Map;Ljava/lang/Object;)Z
    flags: (0x1009) ACC_PUBLIC, ACC_STATIC, ACC_SYNTHETIC
    Code:
      stack=2, locals=2, args_size=2
         0: aload_0
         1: aload_1
         2: invokespecial #54                 // InterfaceMethod canEqual:(Ljava/lang/Object;)Z
         5: ireturn
      LineNumberTable:
        line 30: 0
      LocalVariableTable:
        Start  Length  Slot  Name   Signature
            0       6     0 $this   Lscala/collection/Map;
            0       6     1  that   Ljava/lang/Object;
    MethodParameters:
      Name                           Flags
      $this                          final synthetic
      that                           final

  public default boolean canEqual(java.lang.Object);
    descriptor: (Ljava/lang/Object;)Z
    flags: (0x0001) ACC_PUBLIC
    Code:
      stack=1, locals=2, args_size=2
         0: iconst_1
         1: ireturn
      LineNumberTable:
        line 30: 0
      LocalVariableTable:
        Start  Length  Slot  Name   Signature
            0       2     0  this   Lscala/collection/Map;
            0       2     1  that   Ljava/lang/Object;
    MethodParameters:
      Name                           Flags
      that                           final

  public static boolean equals$(scala.collection.Map, java.lang.Object);
    descriptor: (Lscala/collection/Map;Ljava/lang/Object;)Z
    flags: (0x1009) ACC_PUBLIC, ACC_STATIC, ACC_SYNTHETIC
    Code:
      stack=2, locals=2, args_size=2
         0: aload_0
         1: aload_1
         2: invokespecial #60                 // InterfaceMethod equals:(Ljava/lang/Object;)Z
         5: ireturn
      LineNumberTable:
        line 63: 0
      LocalVariableTable:
        Start  Length  Slot  Name   Signature
            0       6     0 $this   Lscala/collection/Map;
            0       6     1     o   Ljava/lang/Object;
    MethodParameters:
      Name                           Flags
      $this                          final synthetic
      o                              final

  public default boolean equals(java.lang.Object);
    descriptor: (Ljava/lang/Object;)Z
    flags: (0x0001) ACC_PUBLIC
    Code:
      stack=2, locals=4, args_size=2
         0: aload_0
         1: aload_1
         2: if_acmpeq     77
         5: aload_1
         6: instanceof    #2                  // class scala/collection/Map
         9: ifeq          71
        12: aload_1
        13: checkcast     #2                  // class scala/collection/Map
        16: astore_3
        17: aload_3
        18: aload_0
        19: invokeinterface #54,  2           // InterfaceMethod canEqual:(Ljava/lang/Object;)Z
        24: ifeq          71
        27: aload_0
        28: invokeinterface #66,  1           // InterfaceMethod size:()I
        33: aload_3
        34: invokeinterface #66,  1           // InterfaceMethod size:()I
        39: if_icmpne     66
        42: aload_0
        43: aload_3
        44: invokedynamic #88,  0             // InvokeDynamic #0:apply:(Lscala/collection/Map;)Lscala/Function1;
        49: invokeinterface #92,  2           // InterfaceMethod forall:(Lscala/Function1;)Z
        54: goto          59
        57: pop
        58: iconst_0
        59: ifeq          66
        62: iconst_1
        63: goto          67
        66: iconst_0
        67: istore_2
        68: goto          73
        71: iconst_0
        72: istore_2
        73: iload_2
        74: ifeq          79
        77: iconst_1
        78: ireturn
        79: iconst_0
        80: ireturn
      Exception table:
         from    to  target type
            42    54    57   Class java/lang/ClassCastException
      StackMapTable: number_of_entries = 8
        frame_type = 255 /* full_frame */
          offset_delta = 57
          locals = [ class scala/collection/Map, class java/lang/Object, top, class scala/collection/Map ]
          stack = [ class java/lang/ClassCastException ]
        frame_type = 65 /* same_locals_1_stack_item */
          stack = [ int ]
        frame_type = 6 /* same */
        frame_type = 64 /* same_locals_1_stack_item */
          stack = [ int ]
        frame_type = 249 /* chop */
          offset_delta = 3
        frame_type = 252 /* append */
          offset_delta = 1
          locals = [ int ]
        frame_type = 250 /* chop */
          offset_delta = 3
        frame_type = 252 /* append */
          offset_delta = 1
          locals = [ int ]
      LineNumberTable:
        line 64: 0
        line 65: 5
        line 66: 27
        line 67: 42
        line 68: 58
        line 71: 71
        line 64: 73
      LocalVariableTable:
        Start  Length  Slot  Name   Signature
            0      81     0  this   Lscala/collection/Map;
            0      81     1     o   Ljava/lang/Object;
    MethodParameters:
      Name                           Flags
      o                              final

  public static int hashCode$(scala.collection.Map);
    descriptor: (Lscala/collection/Map;)I
    flags: (0x1009) ACC_PUBLIC, ACC_STATIC, ACC_SYNTHETIC
    Code:
      stack=1, locals=1, args_size=1
         0: aload_0
         1: invokespecial #97                 // InterfaceMethod hashCode:()I
         4: ireturn
      LineNumberTable:
        line 74: 0
      LocalVariableTable:
        Start  Length  Slot  Name   Signature
            0       5     0 $this   Lscala/collection/Map;
    MethodParameters:
      Name                           Flags
      $this                          final synthetic

  public default int hashCode();
    descriptor: ()I
    flags: (0x0001) ACC_PUBLIC
    Code:
      stack=2, locals=1, args_size=1
         0: getstatic     #102                // Field scala/util/hashing/MurmurHash3$.MODULE$:Lscala/util/hashing/MurmurHash3$;
         3: aload_0
         4: invokevirtual #105                // Method scala/util/hashing/MurmurHash3$.mapHash:(Lscala/collection/Map;)I
         7: ireturn
      LineNumberTable:
        line 74: 0
      LocalVariableTable:
        Start  Length  Slot  Name   Signature
            0       8     0  this   Lscala/collection/Map;

  public abstract scala.collection.Map<K, V> $minus(K);
    descriptor: (Ljava/lang/Object;)Lscala/collection/Map;
    flags: (0x0401) ACC_PUBLIC, ACC_ABSTRACT
    Signature: #108                         // (TK;)Lscala/collection/Map<TK;TV;>;
    Deprecated: true
    MethodParameters:
      Name                           Flags
      key                            final

  public abstract scala.collection.Map<K, V> $minus(K, K, scala.collection.immutable.Seq<K>);
    descriptor: (Ljava/lang/Object;Ljava/lang/Object;Lscala/collection/immutable/Seq;)Lscala/collection/Map;
    flags: (0x0401) ACC_PUBLIC, ACC_ABSTRACT
    Signature: #111                         // (TK;TK;Lscala/collection/immutable/Seq<TK;>;)Lscala/collection/Map<TK;TV;>;
    Deprecated: true
    MethodParameters:
      Name                           Flags
      key1                           final
      key2                           final
      keys                           final

  public static java.lang.String stringPrefix$(scala.collection.Map);
    descriptor: (Lscala/collection/Map;)Ljava/lang/String;
    flags: (0x1009) ACC_PUBLIC, ACC_STATIC, ACC_SYNTHETIC
    Code:
      stack=1, locals=1, args_size=1
         0: aload_0
         1: invokespecial #120                // InterfaceMethod stringPrefix:()Ljava/lang/String;
         4: areturn
      LineNumberTable:
        line 83: 0
      LocalVariableTable:
        Start  Length  Slot  Name   Signature
            0       5     0 $this   Lscala/collection/Map;
    MethodParameters:
      Name                           Flags
      $this                          final synthetic

  public default java.lang.String stringPrefix();
    descriptor: ()Ljava/lang/String;
    flags: (0x0001) ACC_PUBLIC
    Code:
      stack=1, locals=1, args_size=1
         0: ldc           #122                // String Map
         2: areturn
      LineNumberTable:
        line 83: 0
      LocalVariableTable:
        Start  Length  Slot  Name   Signature
            0       3     0  this   Lscala/collection/Map;

  public static java.lang.String toString$(scala.collection.Map);
    descriptor: (Lscala/collection/Map;)Ljava/lang/String;
    flags: (0x1009) ACC_PUBLIC, ACC_STATIC, ACC_SYNTHETIC
    Code:
      stack=1, locals=1, args_size=1
         0: aload_0
         1: invokespecial #126                // InterfaceMethod toString:()Ljava/lang/String;
         4: areturn
      LineNumberTable:
        line 85: 0
      LocalVariableTable:
        Start  Length  Slot  Name   Signature
            0       5     0 $this   Lscala/collection/Map;
    MethodParameters:
      Name                           Flags
      $this                          final synthetic

  public default java.lang.String toString();
    descriptor: ()Ljava/lang/String;
    flags: (0x0001) ACC_PUBLIC
    Code:
      stack=1, locals=1, args_size=1
         0: aload_0
         1: invokestatic  #129                // InterfaceMethod scala/collection/Iterable.toString$:(Lscala/collection/Iterable;)Ljava/lang/String;
         4: areturn
      LineNumberTable:
        line 85: 0
      LocalVariableTable:
        Start  Length  Slot  Name   Signature
            0       5     0  this   Lscala/collection/Map;

  public static boolean $anonfun$equals$1(scala.collection.Map, scala.Tuple2);
    descriptor: (Lscala/collection/Map;Lscala/Tuple2;)Z
    flags: (0x1009) ACC_PUBLIC, ACC_STATIC, ACC_SYNTHETIC
    Code:
      stack=3, locals=2, args_size=2
         0: aload_0
         1: aload_1
         2: invokevirtual #139                // Method scala/Tuple2._1:()Ljava/lang/Object;
         5: getstatic     #29                 // Field scala/collection/Map$.MODULE$:Lscala/collection/Map$;
         8: invokevirtual #143                // Method scala/collection/Map$.scala$collection$Map$$DefaultSentinelFn:()Lscala/Function0;
        11: invokeinterface #147,  3          // InterfaceMethod getOrElse:(Ljava/lang/Object;Lscala/Function0;)Ljava/lang/Object;
        16: aload_1
        17: invokevirtual #150                // Method scala/Tuple2._2:()Ljava/lang/Object;
        20: invokestatic  #155                // Method scala/runtime/BoxesRunTime.equals:(Ljava/lang/Object;Ljava/lang/Object;)Z
        23: ifeq          28
        26: iconst_1
        27: ireturn
        28: iconst_0
        29: ireturn
      StackMapTable: number_of_entries = 1
        frame_type = 28 /* same */
      LineNumberTable:
        line 67: 0
      LocalVariableTable:
        Start  Length  Slot  Name   Signature
            0      30     0  x2$1   Lscala/collection/Map;
            0      30     1    kv   Lscala/Tuple2;
    MethodParameters:
      Name                           Flags
      x2$1                           final
      kv                             final

  public static void $init$(scala.collection.Map);
    descriptor: (Lscala/collection/Map;)V
    flags: (0x0009) ACC_PUBLIC, ACC_STATIC
    Code:
      stack=0, locals=1, args_size=1
         0: return
      LineNumberTable:
        line 23: 0
      LocalVariableTable:
        Start  Length  Slot  Name   Signature
            0       1     0 $this   Lscala/collection/Map;
    MethodParameters:
      Name                           Flags
      $this                          final synthetic

  public static java.lang.Object $anonfun$equals$1$adapted(scala.collection.Map, scala.Tuple2);
    descriptor: (Lscala/collection/Map;Lscala/Tuple2;)Ljava/lang/Object;
    flags: (0x1009) ACC_PUBLIC, ACC_STATIC, ACC_SYNTHETIC
    Code:
      stack=2, locals=2, args_size=2
         0: aload_0
         1: aload_1
         2: invokestatic  #160                // InterfaceMethod $anonfun$equals$1:(Lscala/collection/Map;Lscala/Tuple2;)Z
         5: invokestatic  #164                // Method scala/runtime/BoxesRunTime.boxToBoolean:(Z)Ljava/lang/Boolean;
         8: areturn
      LineNumberTable:
        line 67: 0
      LocalVariableTable:
        Start  Length  Slot  Name   Signature
            0       9     0  x2$1   Lscala/collection/Map;
            0       9     1    kv   Lscala/Tuple2;
    MethodParameters:
      Name                           Flags
      x2$1                           final
      kv                             final

  private static java.lang.Object $deserializeLambda$(java.lang.invoke.SerializedLambda);
    descriptor: (Ljava/lang/invoke/SerializedLambda;)Ljava/lang/Object;
    flags: (0x100a) ACC_PRIVATE, ACC_STATIC, ACC_SYNTHETIC
    Code:
      stack=1, locals=1, args_size=1
         0: aload_0
         1: invokedynamic #176,  0            // InvokeDynamic #1:lambdaDeserialize:(Ljava/lang/invoke/SerializedLambda;)Ljava/lang/Object;
         6: areturn
}
InnerClasses:
  public static final #20= #17 of #19;    // Lookup=class java/lang/invoke/MethodHandles$Lookup of class java/lang/invoke/MethodHandles
Signature: #3                           // <K:Ljava/lang/Object;V:Ljava/lang/Object;>Ljava/lang/Object;Lscala/collection/Iterable<Lscala/Tuple2<TK;TV;>;>;Lscala/collection/MapFactoryDefaults<TK;TV;Lscala/collection/Map;Lscala/collection/Iterable;>;Lscala/Equals;
SourceFile: "Map.scala"
RuntimeVisibleAnnotations:
  0: #13(#14=s#15)
    scala.reflect.ScalaSignature(
      bytes="\u0006\u0005\u0005Mca\u0002\n\u0014!\u0003\r\t\u0001\u0007\u0005\u0006\u007f\u0001!\t\u0001\u0011\u0005\u0006\t\u0002!\t!\u0012\u0005\u0006\u0013\u0002!\tA\u0013\u0005\u0006!\u0002!\t%\u0015\u0005\u0006)\u0002!\t%\u0016\u0005\u00063\u00021\tA\u0017\u0005\u00063\u00021\ta\u001a\u0005\u0007i\u0002\u0001K\u0011K;\t\u000f\u0005\r\u0001\u0001\"\u0011\u0002\u0006\u001d9\u0011qA\n\t\u0002\u0005%aA\u0002\n\u0014\u0011\u0003\tY\u0001C\u0004\u0002\u001c-!\t!!\b\t\u0013\u0005}1B1A\u0005\n\u0005\u0005\u0002bBA\u0012\u0017\u0001\u0006IA\u0007\u0005\n\u0003KY!\u0019!C\u0005\u0003OA\u0001\"a\f\fA\u0003%\u0011\u0011\u0006\u0005\n\u0003cY\u0011\u0011!C\u0005\u0003g\u00111!T1q\u0015\t!R#\u0001\u0006d_2dWm\u0019;j_:T\u0011AF\u0001\u0006g\u000e\fG.Y\u0002\u0001+\rIr%M\n\u0007\u0001iq2\u0007\u000f\u001f\u0011\u0005maR\"A\u000b\n\u0005u)\"AB!osJ+g\rE\u0002 A\tj\u0011aE\u0005\u0003CM\u0011\u0001\"\u0013;fe\u0006\u0014G.\u001a\t\u00057\r*\u0003\'\u0003\u0002%+\t1A+\u001e9mKJ\u0002\"AJ\u0014\r\u0001\u0011)\u0001\u0006\u0001b\u0001S\t\t1*\u0005\u0002+[A\u00111dK\u0005\u0003YU\u0011qAT8uQ&tw\r\u0005\u0002\u001c]%\u0011q&\u0006\u0002\u0004\u0003:L\bC\u0001\u00142\t\u0019\u0011\u0004\u0001\"b\u0001S\t\ta\u000b\u0005\u0004 i\u0015\u0002dgN\u0005\u0003kM\u0011a!T1q\u001fB\u001c\bCA\u0010\u0001!\u0011y\u0002!\n\u0019\u0011\r}IT\u0005\r\u001c<\u0013\tQ4C\u0001\nNCB4\u0015m\u0019;pef$UMZ1vYR\u001c\bCA\u0010!!\tYR(\u0003\u0002?+\t1Q)];bYN\fa\u0001J5oSR$C#A!\u0011\u0005m\u0011\u0015BA\"\u0016\u0005\u0011)f.\u001b;\u0002\u00155\f\u0007OR1di>\u0014\u00180F\u0001G!\ryrIN\u0005\u0003\u0011N\u0011!\"T1q\r\u0006\u001cGo\u001c:z\u0003!\u0019\u0017M\\#rk\u0006dGCA&O!\tYB*\u0003\u0002N+\t9!i\\8mK\u0006t\u0007\"B(\u0004\u0001\u0004i\u0013\u0001\u0002;iCR\fa!Z9vC2\u001cHCA&S\u0011\u0015\u0019F\u00011\u0001.\u0003\u0005y\u0017\u0001\u00035bg\"\u001cu\u000eZ3\u0015\u0003Y\u0003\"aG,\n\u0005a+\"aA%oi\u00061A%\\5okN$\"aN.\t\u000bq3\u0001\u0019A\u0013\u0002\u0007-,\u0017\u0010\u000b\u0004\u0007=\u0006\u0014G-\u001a\t\u00037}K!\u0001Y\u000b\u0003\u0015\u0011,\u0007O]3dCR,G-A\u0004nKN\u001c\u0018mZ3\"\u0003\r\fA%V:fA5\u0002sN\u001d\u0011sK6|g/\u001a3!_:\u0004\u0013M\u001c\u0011j[6,H/\u00192mK\u0002j\u0015\r]\u0001\u0006g&t7-Z\u0011\u0002M\u00061!GL\u00194]A\"Ba\u000e5kY\")\u0011n\u0002a\u0001K\u0005!1.Z=2\u0011\u0015Yw\u00011\u0001&\u0003\u0011YW-\u001f\u001a\t\u000b5<\u0001\u0019\u00018\u0002\t-,\u0017p\u001d\t\u00047=,\u0013B\u00019\u0016\u0005)a$/\u001a9fCR,GM\u0010\u0015\u0007\u000fy\u000b\'\u000fZ3\"\u0003M\f\u0001&V:fA5j\u0003e\u001c:!e\u0016lwN^3e\u00032d\u0007e\u001c8!C:\u0004\u0013.\\7vi\u0006\u0014G.\u001a\u0011NCB\fAb\u001d;sS:<\u0007K]3gSb,\u0012A\u001e\t\u0003ozt!\u0001\u001f?\u0011\u0005e,R\"\u0001>\u000b\u0005m<\u0012A\u0002\u001fs_>$h(\u0003\u0002~+\u00051\u0001K]3eK\u001aL1a`A\u0001\u0005\u0019\u0019FO]5oO*\u0011Q0F\u0001\ti>\u001cFO]5oOR\ta/A\u0002NCB\u0004\"aH\u0006\u0014\u0007-\ti\u0001E\u0003\u0002\u0010\u0005UaGD\u0002 \u0003#I1!a\u0005\u0014\u0003)i\u0015\r\u001d$bGR|\'/_\u0005\u0005\u0003/\tIB\u0001\u0005EK2,w-\u0019;f\u0015\r\t\u0019bE\u0001\u0007y%t\u0017\u000e\u001e \u0015\u0005\u0005%\u0011a\u0004#fM\u0006,H\u000e^*f]RLg.\u001a7\u0016\u0003i\t\u0001\u0003R3gCVdGoU3oi&tW\r\u001c\u0011\u0002#\u0011+g-Y;miN+g\u000e^5oK24e.\u0006\u0002\u0002*A!1$a\u000b\u001b\u0013\r\ti#\u0006\u0002\n\rVt7\r^5p]B\n!\u0003R3gCVdGoU3oi&tW\r\u001c$oA\u0005aqO]5uKJ+\u0007\u000f\\1dKR\u0011\u0011Q\u0007\t\u0005\u0003o\t\t%\u0004\u0002\u0002:)!\u00111HA\u001f\u0003\u0011a\u0017M\\4\u000b\u0005\u0005}\u0012\u0001\u00026bm\u0006LA!a\u0011\u0002:\t1qJ\u00196fGRDsaCA$\u0003\u001b\ny\u0005E\u0002\u001c\u0003\u0013J1!a\u0013\u0016\u0005A\u0019VM]5bYZ+\'o]5p]VKE)A\u0003wC2,XMH\u0001\u0004Q\u001dQ\u0011qIA\'\u0003\u001f\u0002"
    )
BootstrapMethods:
  0: #84 REF_invokeStatic java/lang/invoke/LambdaMetafactory.altMetafactory:(Ljava/lang/invoke/MethodHandles$Lookup;Ljava/lang/String;Ljava/lang/invoke/MethodType;[Ljava/lang/Object;)Ljava/lang/invoke/CallSite;
    Method arguments:
      #68 (Ljava/lang/Object;)Ljava/lang/Object;
      #73 REF_invokeStatic scala/collection/Map.$anonfun$equals$1$adapted:(Lscala/collection/Map;Lscala/Tuple2;)Ljava/lang/Object;
      #75 (Lscala/Tuple2;)Ljava/lang/Object;
      #76 5
      #77 1
      #75 (Lscala/Tuple2;)Ljava/lang/Object;
  1: #173 REF_invokeStatic scala/runtime/LambdaDeserialize.bootstrap:(Ljava/lang/invoke/MethodHandles$Lookup;Ljava/lang/String;Ljava/lang/invoke/MethodType;[Ljava/lang/invoke/MethodHandle;)Ljava/lang/invoke/CallSite;
    Method arguments:
      #73 REF_invokeStatic scala/collection/Map.$anonfun$equals$1$adapted:(Lscala/collection/Map;Lscala/Tuple2;)Ljava/lang/Object;
  ScalaInlineInfo: length = 0x59 (unknown attribute)
   01 00 00 11 00 82 00 83 01 00 45 00 46 01 00 9D
   00 9E 01 00 6A 00 6B 00 00 6A 00 6E 00 00 33 00
   34 00 00 30 00 31 01 00 3A 00 34 00 00 38 00 31
   01 00 5F 00 40 00 00 5D 00 5E 01 00 29 00 2A 00
   00 26 00 27 01 00 75 00 76 00 00 73 00 74 01 00
   7C 00 76 00 00 7B 00 74 01
  ScalaSig: length = 0x3 (unknown attribute)
   05 02 00
