Classfile /Users/mw/Projects/slang-braindump/.jar/jar8/assemble/slang-braindump/assemble/content/scala/collection/MapFactory.class
  Last modified May 29, 2022; size 5080 bytes
  SHA-256 checksum 203774c71994852864d2d4e05fea6402b1afa981f9926c74b0de4a8f699eef3b
  Compiled from "Factory.scala"
public interface scala.collection.MapFactory<CC extends java.lang.Object> extends java.io.Serializable
  minor version: 0
  major version: 52
  flags: (0x0601) ACC_PUBLIC, ACC_INTERFACE, ACC_ABSTRACT
  this_class: #2                          // scala/collection/MapFactory
  super_class: #5                         // java/lang/Object
  interfaces: 1, fields: 0, methods: 10, attributes: 6
Constant pool:
   #1 = Utf8               scala/collection/MapFactory
   #2 = Class              #1             // scala/collection/MapFactory
   #3 = Utf8               <CC:Ljava/lang/Object;>Ljava/lang/Object;Ljava/io/Serializable;
   #4 = Utf8               java/lang/Object
   #5 = Class              #4             // java/lang/Object
   #6 = Utf8               java/io/Serializable
   #7 = Class              #6             // java/io/Serializable
   #8 = Utf8               Factory.scala
   #9 = Utf8               Lscala/reflect/ScalaSignature;
  #10 = Utf8               bytes
  #11 = Utf8               \u0006\u0005\tEbaB\r\u001b!\u0003\r\ta\b\u0005\u0006Y\u0001!\t!\f\u0005\u0006c\u00011\tA\r\u0005\u0006\u0015\u00021\ta\u0013\u0005\u00067\u0002!\t\u0001\u0018\u0005\u0006S\u00021\tA\u001b\u0005\u0006q\u0002!\u0019!_\u0004\b\u0003\u0013Q\u0002\u0012AA\u0006\r\u0019I\"\u0004#\u0001\u0002\u000e!9\u0011Q\u0004\u0005\u0005\u0002\u0005}\u0001bBA\u0011\u0011\u0011\r\u00111\u0005\u0004\t\u0003\u0013B\u0001\u0015!\u0003\u0002L!Q\u00111I\u0006\u0003\u0002\u0003\u0006I!!\u001b\t\u000f\u0005u1\u0002\"\u0001\u0002n!9\u0011QO\u0006\u0005\u0002\u0005]\u0004BB5\f\t\u0003\ti\bC\u0004\u0002\u000e\"!\u0019!a$\u0007\r\u0005]\u0006\u0002AA]\u0011)\ty-\u0005B\u0001B\u0003%\u0011Q\u0018\u0005\b\u0003;\tB\u0011AAi\u0011\u0019Y\u0016\u0003\"\u0011\u0002X\"1!*\u0005C\u0001\u0003WDa!M\t\u0005\u0002\u0005}\bBB5\u0012\t\u0003\u0011i\u0001C\u0005\u0003\"!\t\t\u0011\"\u0003\u0003$\tQQ*\u00199GC\u000e$xN]=\u000b\u0005ma\u0012AC2pY2,7\r^5p]*\tQ$A\u0003tG\u0006d\u0017m\u0001\u0001\u0016\u0005\u000124c\u0001\u0001\"KA\u0011!eI\u0007\u00029%\u0011A\u0005\b\u0002\u0007\u0003:L(+\u001a4\u0011\u0005\u0019JcB\u0001\u0012(\u0013\tAC$A\u0004qC\u000e\\\u0017mZ3\n\u0005)Z#\u0001D*fe&\fG.\u001b>bE2,\'B\u0001\u0015\u001d\u0003\u0019!\u0013N\\5uIQ\ta\u0006\u0005\u0002#_%\u0011\u0001\u0007\b\u0002\u0005+:LG/A\u0003f[B$\u00180F\u00024\u000b\"+\u0012\u0001\u000e\t\u0005kY\"u\t\u0004\u0001\u0005\r]\u0002AQ1\u00019\u0005\t\u00195)F\u0002:\u0001\n\u000b\"AO\u001f\u0011\u0005\tZ\u0014B\u0001\u001f\u001d\u0005\u001dqu\u000e\u001e5j]\u001e\u0004\"A\t \n\u0005}b\"aA!os\u0012)\u0011I\u000eb\u0001s\t!q\f\n\u00137\t\u0015\u0019eG1\u0001:\u0005\u0011yF\u0005J\u001c\u0011\u0005U*E!\u0002$\u0003\u0005\u0004I$!A&\u0011\u0005UBE!B%\u0003\u0005\u0004I$!\u0001,\u0002\t\u0019\u0014x.\\\u000b\u0004\u0019>\u000bFCA\'S!\u0011)dG\u0014)\u0011\u0005UzE!\u0002$\u0004\u0005\u0004I\u0004CA\u001bR\t\u0015I5A1\u0001:\u0011\u0015\u00196\u00011\u0001U\u0003\tIG\u000fE\u0002V-bk\u0011AG\u0005\u0003/j\u0011A\"\u0013;fe\u0006\u0014G.Z(oG\u0016\u0004BAI-O!&\u0011!\f\b\u0002\u0007)V\u0004H.\u001a\u001a\u0002\u000b\u0005\u0004\b\u000f\\=\u0016\u0007u\u0003\'\r\u0006\u0002_GB!QGN0b!\t)\u0004\rB\u0003G\t\t\u0007\u0011\b\u0005\u00026E\u0012)\u0011\n\u0002b\u0001s!)A\r\u0002a\u0001K\u0006)Q\r\\3ngB\u0019!E\u001a5\n\u0005\u001dd\"A\u0003\u001fsKB,\u0017\r^3e}A!!%W0b\u0003)qWm\u001e\"vS2$WM]\u000b\u0004WR4X#\u00017\u0011\t5\u0004(o^\u0007\u0002]*\u0011qNG\u0001\b[V$\u0018M\u00197f\u0013\t\thNA\u0004Ck&dG-\u001a:\u0011\t\tJ6/\u001e\t\u0003kQ$QAR\u0003C\u0002e\u0002\"!\u000e<\u0005\u000b%+!\u0019A\u001d\u0011\tU24/^\u0001\u000b[\u0006\u0004h)Y2u_JLX#\u0002>\u0002\u0002\u0005\u0015Q#A>\u0011\u000bUch0a\u0002\n\u0005uT\"a\u0002$bGR|\'/\u001f\t\u0006Ee{\u00181\u0001\t\u0004k\u0005\u0005A!\u0002$\u0007\u0005\u0004I\u0004cA\u001b\u0002\u0006\u0011)\u0011J\u0002b\u0001sA)QGN@\u0002\u0004\u0005QQ*\u00199GC\u000e$xN]=\u0011\u0005UC1\u0003\u0002\u0005\"\u0003\u001f\u0001B!!\u0005\u0002\u001c5\u0011\u00111\u0003\u0006\u0005\u0003+\t9\"\u0001\u0002j_*\u0011\u0011\u0011D\u0001\u0005U\u00064\u0018-C\u0002+\u0003\'\ta\u0001P5oSRtDCAA\u0006\u0003%!xNR1di>\u0014\u00180\u0006\u0005\u0002&\u00055\u0012\u0011GA\u001b)\u0011\t9#!\u0011\u0011\rUc\u0018\u0011FA\u001a!\u0019\u0011\u0013,a\u000b\u00020A\u0019Q\'!\f\u0005\u000b\u0019S!\u0019A\u001d\u0011\u0007U\n\t\u0004B\u0003J\u0015\t\u0007\u0011\bE\u00046\u0003k\tY#a\f\u0005\r]R!\u0019AA\u001c+\u0015I\u0014\u0011HA\u001f\t\u001d\tY$!\u000eC\u0002e\u0012Aa\u0018\u0013%q\u00119\u0011qHA\u001b\u0005\u0004I$\u0001B0%IeBq!a\u0011\u000b\u0001\u0004\t)%A\u0004gC\u000e$xN]=\u0011\tU\u0003\u0011q\t\t\u0004k\u0005U\"!\u0003+p\r\u0006\u001cGo\u001c:z+!\ti%!\u0016\u0002Z\u0005u3#B\u0006\"\u0003\u001f*\u0003CB+}\u0003#\nY\u0006\u0005\u0004#3\u0006M\u0013q\u000b\t\u0004k\u0005UC!\u0002$\f\u0005\u0004I\u0004cA\u001b\u0002Z\u0011)\u0011j\u0003b\u0001sA9Q\'!\u0018\u0002T\u0005]CAB\u001c\f\u0005\u0004\ty&F\u0003:\u0003C\n)\u0007B\u0004\u0002d\u0005u#\u0019A\u001d\u0003\u000b}#C%\r\u0019\u0005\u000f\u0005\u001d\u0014Q\fb\u0001s\t)q\f\n\u00132cA!Q\u000bAA6!\r)\u0014Q\f\u000b\u0005\u0003_\n\u0019\bE\u0005\u0002r-\t\u0019&a\u0016\u0002l5\t\u0001\u0002C\u0004\u0002D5\u0001\r!!\u001b\u0002\u0019\u0019\u0014x.\\*qK\u000eLg-[2\u0015\t\u0005m\u0013\u0011\u0010\u0005\u0007\':\u0001\r!a\u001f\u0011\tU3\u0016\u0011K\u000b\u0003\u0003\u007f\u0002b!\u001c9\u0002R\u0005m\u0003fB\u0006\u0002\u0004\u0006%\u00151\u0012\t\u0004E\u0005\u0015\u0015bAAD9\t\u00012+\u001a:jC24VM]:j_:,\u0016\nR\u0001\u0006m\u0006dW/\u001a\u0010\u0002\u0007\u0005YAo\u001c\"vS2$gI]8n+!\t\t*!(\u0002\"\u0006\u0015F\u0003BAJ\u0003c\u0003\u0002\"VAK{\u0005e\u00151U\u0005\u0004\u0003/S\"!\u0003\"vS2$gI]8n!\u0019\u0011\u0013,a\'\u0002 B\u0019Q\'!(\u0005\u000b\u0019\u0003\"\u0019A\u001d\u0011\u0007U\n\t\u000bB\u0003J!\t\u0007\u0011\bE\u00046\u0003K\u000bY*a(\u0005\r]\u0002\"\u0019AAT+\u0015I\u0014\u0011VAW\t\u001d\tY+!*C\u0002e\u0012Qa\u0018\u0013%cI\"q!a,\u0002&\n\u0007\u0011HA\u0003`I\u0011\n4\u0007C\u0004\u0002DA\u0001\r!a-\u0011\tU\u0003\u0011Q\u0017\t\u0004k\u0005\u0015&\u0001\u0003#fY\u0016<\u0017\r^3\u0016\t\u0005m\u0016\u0011Y\n\u0005#\u0005\ni\f\u0005\u0003V\u0001\u0005}\u0006cA\u001b\u0002B\u00129\u00111Y\tC\u0002\u0005\u0015\'!A\"\u0016\u000be\n9-a3\u0005\u000f\u0005%\u0017\u0011\u0019b\u0001s\t)q\f\n\u00132i\u00119\u0011QZAa\u0005\u0004I$!B0%IE*\u0014\u0001\u00033fY\u0016<\u0017\r^3\u0015\t\u0005M\u0017Q\u001b\t\u0006\u0003c\n\u0012q\u0018\u0005\b\u0003\u001f\u001c\u0002\u0019AA_+\u0019\tI.a8\u0002dR!\u00111\\As!\u001d)\u0014\u0011YAo\u0003C\u00042!NAp\t\u00151EC1\u0001:!\r)\u00141\u001d\u0003\u0006\u0013R\u0011\r!\u000f\u0005\u0007IR\u0001\r!a:\u0011\t\t2\u0017\u0011\u001e\t\u0007Ee\u000bi.!9\u0016\r\u00055\u00181_A|)\u0011\ty/!?\u0011\u000fU\n\t-!=\u0002vB\u0019Q\'a=\u0005\u000b\u0019+\"\u0019A\u001d\u0011\u0007U\n9\u0010B\u0003J+\t\u0007\u0011\b\u0003\u0004T+\u0001\u0007\u00111 \t\u0005+Z\u000bi\u0010\u0005\u0004#3\u0006E\u0018Q_\u000b\u0007\u0005\u0003\u00119Aa\u0003\u0016\u0005\t\r\u0001cB\u001b\u0002B\n\u0015!\u0011\u0002\t\u0004k\t\u001dA!\u0002$\u0017\u0005\u0004I\u0004cA\u001b\u0003\f\u0011)\u0011J\u0006b\u0001sU1!q\u0002B\f\u00057)\"A!\u0005\u0011\r5\u0004(1\u0003B\u000f!\u0019\u0011\u0013L!\u0006\u0003\u001aA\u0019QGa\u0006\u0005\u000b\u0019;\"\u0019A\u001d\u0011\u0007U\u0012Y\u0002B\u0003J/\t\u0007\u0011\bE\u00046\u0003\u0003\u0014)B!\u0007)\u000fE\t\u0019)!#\u0002\f\u0006aqO]5uKJ+\u0007\u000f\\1dKR\u0011!Q\u0005\t\u0005\u0005O\u0011i#\u0004\u0002\u0003*)!!1FA\f\u0003\u0011a\u0017M\\4\n\t\t=\"\u0011\u0006\u0002\u0007\u001f\nTWm\u0019;
  #12 = Utf8               scala/collection/MapFactory$$anon$2
  #13 = Class              #12            // scala/collection/MapFactory$$anon$2
  #14 = Utf8               scala/collection/MapFactory$Delegate
  #15 = Class              #14            // scala/collection/MapFactory$Delegate
  #16 = Utf8               Delegate
  #17 = Utf8               scala/collection/MapFactory$ToFactory
  #18 = Class              #17            // scala/collection/MapFactory$ToFactory
  #19 = Utf8               ToFactory
  #20 = Utf8               toBuildFrom
  #21 = Utf8               (Lscala/collection/MapFactory;)Lscala/collection/BuildFrom;
  #22 = Utf8               <K:Ljava/lang/Object;V:Ljava/lang/Object;CC:Ljava/lang/Object;>(Lscala/collection/MapFactory<TCC;>;)Lscala/collection/BuildFrom<Ljava/lang/Object;Lscala/Tuple2<TK;TV;>;TCC;>;
  #23 = Utf8               factory
  #24 = Utf8               scala/collection/MapFactory$
  #25 = Class              #24            // scala/collection/MapFactory$
  #26 = Utf8               MODULE$
  #27 = Utf8               Lscala/collection/MapFactory$;
  #28 = NameAndType        #26:#27        // MODULE$:Lscala/collection/MapFactory$;
  #29 = Fieldref           #25.#28        // scala/collection/MapFactory$.MODULE$:Lscala/collection/MapFactory$;
  #30 = Utf8               <init>
  #31 = Utf8               (Lscala/collection/MapFactory;)V
  #32 = NameAndType        #30:#31        // "<init>":(Lscala/collection/MapFactory;)V
  #33 = Methodref          #13.#32        // scala/collection/MapFactory$$anon$2."<init>":(Lscala/collection/MapFactory;)V
  #34 = Utf8               Lscala/collection/MapFactory;
  #35 = Utf8               toFactory
  #36 = Utf8               (Lscala/collection/MapFactory;)Lscala/collection/Factory;
  #37 = Utf8               <K:Ljava/lang/Object;V:Ljava/lang/Object;CC:Ljava/lang/Object;>(Lscala/collection/MapFactory<TCC;>;)Lscala/collection/Factory<Lscala/Tuple2<TK;TV;>;TCC;>;
  #38 = Methodref          #18.#32        // scala/collection/MapFactory$ToFactory."<init>":(Lscala/collection/MapFactory;)V
  #39 = Utf8               empty
  #40 = Utf8               ()Ljava/lang/Object;
  #41 = Utf8               <K:Ljava/lang/Object;V:Ljava/lang/Object;>()TCC;
  #42 = Utf8               from
  #43 = Utf8               (Lscala/collection/IterableOnce;)Ljava/lang/Object;
  #44 = Utf8               <K:Ljava/lang/Object;V:Ljava/lang/Object;>(Lscala/collection/IterableOnce<Lscala/Tuple2<TK;TV;>;>;)TCC;
  #45 = Utf8               it
  #46 = Utf8               apply$
  #47 = Utf8               (Lscala/collection/MapFactory;Lscala/collection/immutable/Seq;)Ljava/lang/Object;
  #48 = Utf8               $this
  #49 = Utf8               elems
  #50 = Utf8               apply
  #51 = Utf8               (Lscala/collection/immutable/Seq;)Ljava/lang/Object;
  #52 = NameAndType        #50:#51        // apply:(Lscala/collection/immutable/Seq;)Ljava/lang/Object;
  #53 = InterfaceMethodref #2.#52         // scala/collection/MapFactory.apply:(Lscala/collection/immutable/Seq;)Ljava/lang/Object;
  #54 = Utf8               Lscala/collection/immutable/Seq;
  #55 = Utf8               <K:Ljava/lang/Object;V:Ljava/lang/Object;>(Lscala/collection/immutable/Seq<Lscala/Tuple2<TK;TV;>;>;)TCC;
  #56 = NameAndType        #42:#43        // from:(Lscala/collection/IterableOnce;)Ljava/lang/Object;
  #57 = InterfaceMethodref #2.#56         // scala/collection/MapFactory.from:(Lscala/collection/IterableOnce;)Ljava/lang/Object;
  #58 = Utf8               this
  #59 = Utf8               newBuilder
  #60 = Utf8               ()Lscala/collection/mutable/Builder;
  #61 = Utf8               <K:Ljava/lang/Object;V:Ljava/lang/Object;>()Lscala/collection/mutable/Builder<Lscala/Tuple2<TK;TV;>;TCC;>;
  #62 = Utf8               mapFactory$
  #63 = Utf8               mapFactory
  #64 = Utf8               ()Lscala/collection/Factory;
  #65 = NameAndType        #63:#64        // mapFactory:()Lscala/collection/Factory;
  #66 = InterfaceMethodref #2.#65         // scala/collection/MapFactory.mapFactory:()Lscala/collection/Factory;
  #67 = Utf8               <K:Ljava/lang/Object;V:Ljava/lang/Object;>()Lscala/collection/Factory<Lscala/Tuple2<TK;TV;>;TCC;>;
  #68 = Utf8               $init$
  #69 = Utf8               Code
  #70 = Utf8               LineNumberTable
  #71 = Utf8               LocalVariableTable
  #72 = Utf8               Signature
  #73 = Utf8               MethodParameters
  #74 = Utf8               InnerClasses
  #75 = Utf8               SourceFile
  #76 = Utf8               RuntimeVisibleAnnotations
  #77 = Utf8               ScalaInlineInfo
  #78 = Utf8               ScalaSig
{
  public static <K extends java.lang.Object, V extends java.lang.Object, CC extends java.lang.Object> scala.collection.BuildFrom<java.lang.Object, scala.Tuple2<K, V>, CC> toBuildFrom(scala.collection.MapFactory<CC>);
    descriptor: (Lscala/collection/MapFactory;)Lscala/collection/BuildFrom;
    flags: (0x0009) ACC_PUBLIC, ACC_STATIC
    Code:
      stack=3, locals=1, args_size=1
         0: getstatic     #29                 // Field scala/collection/MapFactory$.MODULE$:Lscala/collection/MapFactory$;
         3: pop
         4: new           #13                 // class scala/collection/MapFactory$$anon$2
         7: dup
         8: aload_0
         9: invokespecial #33                 // Method scala/collection/MapFactory$$anon$2."<init>":(Lscala/collection/MapFactory;)V
        12: areturn
      LineNumberTable:
        line 432: 4
      LocalVariableTable:
        Start  Length  Slot  Name   Signature
            0      13     0 factory   Lscala/collection/MapFactory;
    Signature: #22                          // <K:Ljava/lang/Object;V:Ljava/lang/Object;CC:Ljava/lang/Object;>(Lscala/collection/MapFactory<TCC;>;)Lscala/collection/BuildFrom<Ljava/lang/Object;Lscala/Tuple2<TK;TV;>;TCC;>;
    MethodParameters:
      Name                           Flags
      factory                        final

  public static <K extends java.lang.Object, V extends java.lang.Object, CC extends java.lang.Object> scala.collection.Factory<scala.Tuple2<K, V>, CC> toFactory(scala.collection.MapFactory<CC>);
    descriptor: (Lscala/collection/MapFactory;)Lscala/collection/Factory;
    flags: (0x0009) ACC_PUBLIC, ACC_STATIC
    Code:
      stack=3, locals=1, args_size=1
         0: getstatic     #29                 // Field scala/collection/MapFactory$.MODULE$:Lscala/collection/MapFactory$;
         3: pop
         4: new           #18                 // class scala/collection/MapFactory$ToFactory
         7: dup
         8: aload_0
         9: invokespecial #38                 // Method scala/collection/MapFactory$ToFactory."<init>":(Lscala/collection/MapFactory;)V
        12: areturn
      LineNumberTable:
        line 423: 4
      LocalVariableTable:
        Start  Length  Slot  Name   Signature
            0      13     0 factory   Lscala/collection/MapFactory;
    Signature: #37                          // <K:Ljava/lang/Object;V:Ljava/lang/Object;CC:Ljava/lang/Object;>(Lscala/collection/MapFactory<TCC;>;)Lscala/collection/Factory<Lscala/Tuple2<TK;TV;>;TCC;>;
    MethodParameters:
      Name                           Flags
      factory                        final

  public abstract <K extends java.lang.Object, V extends java.lang.Object> CC empty();
    descriptor: ()Ljava/lang/Object;
    flags: (0x0401) ACC_PUBLIC, ACC_ABSTRACT
    Signature: #41                          // <K:Ljava/lang/Object;V:Ljava/lang/Object;>()TCC;

  public abstract <K extends java.lang.Object, V extends java.lang.Object> CC from(scala.collection.IterableOnce<scala.Tuple2<K, V>>);
    descriptor: (Lscala/collection/IterableOnce;)Ljava/lang/Object;
    flags: (0x0401) ACC_PUBLIC, ACC_ABSTRACT
    Signature: #44                          // <K:Ljava/lang/Object;V:Ljava/lang/Object;>(Lscala/collection/IterableOnce<Lscala/Tuple2<TK;TV;>;>;)TCC;
    MethodParameters:
      Name                           Flags
      it                             final

  public static java.lang.Object apply$(scala.collection.MapFactory, scala.collection.immutable.Seq);
    descriptor: (Lscala/collection/MapFactory;Lscala/collection/immutable/Seq;)Ljava/lang/Object;
    flags: (0x1009) ACC_PUBLIC, ACC_STATIC, ACC_SYNTHETIC
    Code:
      stack=2, locals=2, args_size=2
         0: aload_0
         1: aload_1
         2: invokespecial #53                 // InterfaceMethod apply:(Lscala/collection/immutable/Seq;)Ljava/lang/Object;
         5: areturn
      LineNumberTable:
        line 399: 0
      LocalVariableTable:
        Start  Length  Slot  Name   Signature
            0       6     0 $this   Lscala/collection/MapFactory;
            0       6     1 elems   Lscala/collection/immutable/Seq;
    MethodParameters:
      Name                           Flags
      $this                          final synthetic
      elems                          final

  public default <K extends java.lang.Object, V extends java.lang.Object> CC apply(scala.collection.immutable.Seq<scala.Tuple2<K, V>>);
    descriptor: (Lscala/collection/immutable/Seq;)Ljava/lang/Object;
    flags: (0x0001) ACC_PUBLIC
    Code:
      stack=2, locals=2, args_size=2
         0: aload_0
         1: aload_1
         2: invokeinterface #57,  2           // InterfaceMethod from:(Lscala/collection/IterableOnce;)Ljava/lang/Object;
         7: areturn
      LineNumberTable:
        line 399: 0
      LocalVariableTable:
        Start  Length  Slot  Name   Signature
            0       8     0  this   Lscala/collection/MapFactory;
            0       8     1 elems   Lscala/collection/immutable/Seq;
    Signature: #55                          // <K:Ljava/lang/Object;V:Ljava/lang/Object;>(Lscala/collection/immutable/Seq<Lscala/Tuple2<TK;TV;>;>;)TCC;
    MethodParameters:
      Name                           Flags
      elems                          final

  public abstract <K extends java.lang.Object, V extends java.lang.Object> scala.collection.mutable.Builder<scala.Tuple2<K, V>, CC> newBuilder();
    descriptor: ()Lscala/collection/mutable/Builder;
    flags: (0x0401) ACC_PUBLIC, ACC_ABSTRACT
    Signature: #61                          // <K:Ljava/lang/Object;V:Ljava/lang/Object;>()Lscala/collection/mutable/Builder<Lscala/Tuple2<TK;TV;>;TCC;>;

  public static scala.collection.Factory mapFactory$(scala.collection.MapFactory);
    descriptor: (Lscala/collection/MapFactory;)Lscala/collection/Factory;
    flags: (0x1009) ACC_PUBLIC, ACC_STATIC, ACC_SYNTHETIC
    Code:
      stack=1, locals=1, args_size=1
         0: aload_0
         1: invokespecial #66                 // InterfaceMethod mapFactory:()Lscala/collection/Factory;
         4: areturn
      LineNumberTable:
        line 409: 0
      LocalVariableTable:
        Start  Length  Slot  Name   Signature
            0       5     0 $this   Lscala/collection/MapFactory;
    MethodParameters:
      Name                           Flags
      $this                          final synthetic

  public default <K extends java.lang.Object, V extends java.lang.Object> scala.collection.Factory<scala.Tuple2<K, V>, CC> mapFactory();
    descriptor: ()Lscala/collection/Factory;
    flags: (0x0001) ACC_PUBLIC
    Code:
      stack=3, locals=1, args_size=1
         0: getstatic     #29                 // Field scala/collection/MapFactory$.MODULE$:Lscala/collection/MapFactory$;
         3: pop
         4: new           #18                 // class scala/collection/MapFactory$ToFactory
         7: dup
         8: aload_0
         9: invokespecial #38                 // Method scala/collection/MapFactory$ToFactory."<init>":(Lscala/collection/MapFactory;)V
        12: areturn
      LineNumberTable:
        line 409: 0
        line 423: 4
        line 409: 12
      LocalVariableTable:
        Start  Length  Slot  Name   Signature
            0      13     0  this   Lscala/collection/MapFactory;
    Signature: #67                          // <K:Ljava/lang/Object;V:Ljava/lang/Object;>()Lscala/collection/Factory<Lscala/Tuple2<TK;TV;>;TCC;>;

  public static void $init$(scala.collection.MapFactory);
    descriptor: (Lscala/collection/MapFactory;)V
    flags: (0x0009) ACC_PUBLIC, ACC_STATIC
    Code:
      stack=0, locals=1, args_size=1
         0: return
      LineNumberTable:
        line 384: 0
      LocalVariableTable:
        Start  Length  Slot  Name   Signature
            0       1     0 $this   Lscala/collection/MapFactory;
    MethodParameters:
      Name                           Flags
      $this                          final synthetic
}
InnerClasses:
  public final #13;                       // class scala/collection/MapFactory$$anon$2
  public static #16= #15 of #2;           // Delegate=class scala/collection/MapFactory$Delegate of class scala/collection/MapFactory
  private static #19= #18 of #2;          // ToFactory=class scala/collection/MapFactory$ToFactory of class scala/collection/MapFactory
Signature: #3                           // <CC:Ljava/lang/Object;>Ljava/lang/Object;Ljava/io/Serializable;
SourceFile: "Factory.scala"
RuntimeVisibleAnnotations:
  0: #9(#10=s#11)
    scala.reflect.ScalaSignature(
      bytes="\u0006\u0005\tEbaB\r\u001b!\u0003\r\ta\b\u0005\u0006Y\u0001!\t!\f\u0005\u0006c\u00011\tA\r\u0005\u0006\u0015\u00021\ta\u0013\u0005\u00067\u0002!\t\u0001\u0018\u0005\u0006S\u00021\tA\u001b\u0005\u0006q\u0002!\u0019!_\u0004\b\u0003\u0013Q\u0002\u0012AA\u0006\r\u0019I\"\u0004#\u0001\u0002\u000e!9\u0011Q\u0004\u0005\u0005\u0002\u0005}\u0001bBA\u0011\u0011\u0011\r\u00111\u0005\u0004\t\u0003\u0013B\u0001\u0015!\u0003\u0002L!Q\u00111I\u0006\u0003\u0002\u0003\u0006I!!\u001b\t\u000f\u0005u1\u0002\"\u0001\u0002n!9\u0011QO\u0006\u0005\u0002\u0005]\u0004BB5\f\t\u0003\ti\bC\u0004\u0002\u000e\"!\u0019!a$\u0007\r\u0005]\u0006\u0002AA]\u0011)\ty-\u0005B\u0001B\u0003%\u0011Q\u0018\u0005\b\u0003;\tB\u0011AAi\u0011\u0019Y\u0016\u0003\"\u0011\u0002X\"1!*\u0005C\u0001\u0003WDa!M\t\u0005\u0002\u0005}\bBB5\u0012\t\u0003\u0011i\u0001C\u0005\u0003\"!\t\t\u0011\"\u0003\u0003$\tQQ*\u00199GC\u000e$xN]=\u000b\u0005ma\u0012AC2pY2,7\r^5p]*\tQ$A\u0003tG\u0006d\u0017m\u0001\u0001\u0016\u0005\u000124c\u0001\u0001\"KA\u0011!eI\u0007\u00029%\u0011A\u0005\b\u0002\u0007\u0003:L(+\u001a4\u0011\u0005\u0019JcB\u0001\u0012(\u0013\tAC$A\u0004qC\u000e\\\u0017mZ3\n\u0005)Z#\u0001D*fe&\fG.\u001b>bE2,\'B\u0001\u0015\u001d\u0003\u0019!\u0013N\\5uIQ\ta\u0006\u0005\u0002#_%\u0011\u0001\u0007\b\u0002\u0005+:LG/A\u0003f[B$\u00180F\u00024\u000b\"+\u0012\u0001\u000e\t\u0005kY\"u\t\u0004\u0001\u0005\r]\u0002AQ1\u00019\u0005\t\u00195)F\u0002:\u0001\n\u000b\"AO\u001f\u0011\u0005\tZ\u0014B\u0001\u001f\u001d\u0005\u001dqu\u000e\u001e5j]\u001e\u0004\"A\t \n\u0005}b\"aA!os\u0012)\u0011I\u000eb\u0001s\t!q\f\n\u00137\t\u0015\u0019eG1\u0001:\u0005\u0011yF\u0005J\u001c\u0011\u0005U*E!\u0002$\u0003\u0005\u0004I$!A&\u0011\u0005UBE!B%\u0003\u0005\u0004I$!\u0001,\u0002\t\u0019\u0014x.\\\u000b\u0004\u0019>\u000bFCA\'S!\u0011)dG\u0014)\u0011\u0005UzE!\u0002$\u0004\u0005\u0004I\u0004CA\u001bR\t\u0015I5A1\u0001:\u0011\u0015\u00196\u00011\u0001U\u0003\tIG\u000fE\u0002V-bk\u0011AG\u0005\u0003/j\u0011A\"\u0013;fe\u0006\u0014G.Z(oG\u0016\u0004BAI-O!&\u0011!\f\b\u0002\u0007)V\u0004H.\u001a\u001a\u0002\u000b\u0005\u0004\b\u000f\\=\u0016\u0007u\u0003\'\r\u0006\u0002_GB!QGN0b!\t)\u0004\rB\u0003G\t\t\u0007\u0011\b\u0005\u00026E\u0012)\u0011\n\u0002b\u0001s!)A\r\u0002a\u0001K\u0006)Q\r\\3ngB\u0019!E\u001a5\n\u0005\u001dd\"A\u0003\u001fsKB,\u0017\r^3e}A!!%W0b\u0003)qWm\u001e\"vS2$WM]\u000b\u0004WR4X#\u00017\u0011\t5\u0004(o^\u0007\u0002]*\u0011qNG\u0001\b[V$\u0018M\u00197f\u0013\t\thNA\u0004Ck&dG-\u001a:\u0011\t\tJ6/\u001e\t\u0003kQ$QAR\u0003C\u0002e\u0002\"!\u000e<\u0005\u000b%+!\u0019A\u001d\u0011\tU24/^\u0001\u000b[\u0006\u0004h)Y2u_JLX#\u0002>\u0002\u0002\u0005\u0015Q#A>\u0011\u000bUch0a\u0002\n\u0005uT\"a\u0002$bGR|\'/\u001f\t\u0006Ee{\u00181\u0001\t\u0004k\u0005\u0005A!\u0002$\u0007\u0005\u0004I\u0004cA\u001b\u0002\u0006\u0011)\u0011J\u0002b\u0001sA)QGN@\u0002\u0004\u0005QQ*\u00199GC\u000e$xN]=\u0011\u0005UC1\u0003\u0002\u0005\"\u0003\u001f\u0001B!!\u0005\u0002\u001c5\u0011\u00111\u0003\u0006\u0005\u0003+\t9\"\u0001\u0002j_*\u0011\u0011\u0011D\u0001\u0005U\u00064\u0018-C\u0002+\u0003\'\ta\u0001P5oSRtDCAA\u0006\u0003%!xNR1di>\u0014\u00180\u0006\u0005\u0002&\u00055\u0012\u0011GA\u001b)\u0011\t9#!\u0011\u0011\rUc\u0018\u0011FA\u001a!\u0019\u0011\u0013,a\u000b\u00020A\u0019Q\'!\f\u0005\u000b\u0019S!\u0019A\u001d\u0011\u0007U\n\t\u0004B\u0003J\u0015\t\u0007\u0011\bE\u00046\u0003k\tY#a\f\u0005\r]R!\u0019AA\u001c+\u0015I\u0014\u0011HA\u001f\t\u001d\tY$!\u000eC\u0002e\u0012Aa\u0018\u0013%q\u00119\u0011qHA\u001b\u0005\u0004I$\u0001B0%IeBq!a\u0011\u000b\u0001\u0004\t)%A\u0004gC\u000e$xN]=\u0011\tU\u0003\u0011q\t\t\u0004k\u0005U\"!\u0003+p\r\u0006\u001cGo\u001c:z+!\ti%!\u0016\u0002Z\u0005u3#B\u0006\"\u0003\u001f*\u0003CB+}\u0003#\nY\u0006\u0005\u0004#3\u0006M\u0013q\u000b\t\u0004k\u0005UC!\u0002$\f\u0005\u0004I\u0004cA\u001b\u0002Z\u0011)\u0011j\u0003b\u0001sA9Q\'!\u0018\u0002T\u0005]CAB\u001c\f\u0005\u0004\ty&F\u0003:\u0003C\n)\u0007B\u0004\u0002d\u0005u#\u0019A\u001d\u0003\u000b}#C%\r\u0019\u0005\u000f\u0005\u001d\u0014Q\fb\u0001s\t)q\f\n\u00132cA!Q\u000bAA6!\r)\u0014Q\f\u000b\u0005\u0003_\n\u0019\bE\u0005\u0002r-\t\u0019&a\u0016\u0002l5\t\u0001\u0002C\u0004\u0002D5\u0001\r!!\u001b\u0002\u0019\u0019\u0014x.\\*qK\u000eLg-[2\u0015\t\u0005m\u0013\u0011\u0010\u0005\u0007\':\u0001\r!a\u001f\u0011\tU3\u0016\u0011K\u000b\u0003\u0003\u007f\u0002b!\u001c9\u0002R\u0005m\u0003fB\u0006\u0002\u0004\u0006%\u00151\u0012\t\u0004E\u0005\u0015\u0015bAAD9\t\u00012+\u001a:jC24VM]:j_:,\u0016\nR\u0001\u0006m\u0006dW/\u001a\u0010\u0002\u0007\u0005YAo\u001c\"vS2$gI]8n+!\t\t*!(\u0002\"\u0006\u0015F\u0003BAJ\u0003c\u0003\u0002\"VAK{\u0005e\u00151U\u0005\u0004\u0003/S\"!\u0003\"vS2$gI]8n!\u0019\u0011\u0013,a\'\u0002 B\u0019Q\'!(\u0005\u000b\u0019\u0003\"\u0019A\u001d\u0011\u0007U\n\t\u000bB\u0003J!\t\u0007\u0011\bE\u00046\u0003K\u000bY*a(\u0005\r]\u0002\"\u0019AAT+\u0015I\u0014\u0011VAW\t\u001d\tY+!*C\u0002e\u0012Qa\u0018\u0013%cI\"q!a,\u0002&\n\u0007\u0011HA\u0003`I\u0011\n4\u0007C\u0004\u0002DA\u0001\r!a-\u0011\tU\u0003\u0011Q\u0017\t\u0004k\u0005\u0015&\u0001\u0003#fY\u0016<\u0017\r^3\u0016\t\u0005m\u0016\u0011Y\n\u0005#\u0005\ni\f\u0005\u0003V\u0001\u0005}\u0006cA\u001b\u0002B\u00129\u00111Y\tC\u0002\u0005\u0015\'!A\"\u0016\u000be\n9-a3\u0005\u000f\u0005%\u0017\u0011\u0019b\u0001s\t)q\f\n\u00132i\u00119\u0011QZAa\u0005\u0004I$!B0%IE*\u0014\u0001\u00033fY\u0016<\u0017\r^3\u0015\t\u0005M\u0017Q\u001b\t\u0006\u0003c\n\u0012q\u0018\u0005\b\u0003\u001f\u001c\u0002\u0019AA_+\u0019\tI.a8\u0002dR!\u00111\\As!\u001d)\u0014\u0011YAo\u0003C\u00042!NAp\t\u00151EC1\u0001:!\r)\u00141\u001d\u0003\u0006\u0013R\u0011\r!\u000f\u0005\u0007IR\u0001\r!a:\u0011\t\t2\u0017\u0011\u001e\t\u0007Ee\u000bi.!9\u0016\r\u00055\u00181_A|)\u0011\ty/!?\u0011\u000fU\n\t-!=\u0002vB\u0019Q\'a=\u0005\u000b\u0019+\"\u0019A\u001d\u0011\u0007U\n9\u0010B\u0003J+\t\u0007\u0011\b\u0003\u0004T+\u0001\u0007\u00111 \t\u0005+Z\u000bi\u0010\u0005\u0004#3\u0006E\u0018Q_\u000b\u0007\u0005\u0003\u00119Aa\u0003\u0016\u0005\t\r\u0001cB\u001b\u0002B\n\u0015!\u0011\u0002\t\u0004k\t\u001dA!\u0002$\u0017\u0005\u0004I\u0004cA\u001b\u0003\f\u0011)\u0011J\u0006b\u0001sU1!q\u0002B\f\u00057)\"A!\u0005\u0011\r5\u0004(1\u0003B\u000f!\u0019\u0011\u0013L!\u0006\u0003\u001aA\u0019QGa\u0006\u0005\u000b\u0019;\"\u0019A\u001d\u0011\u0007U\u0012Y\u0002B\u0003J/\t\u0007\u0011\bE\u00046\u0003\u0003\u0014)B!\u0007)\u000fE\t\u0019)!#\u0002\f\u0006aqO]5uKJ+\u0007\u000f\\1dKR\u0011!Q\u0005\t\u0005\u0005O\u0011i#\u0004\u0002\u0003*)!!1FA\f\u0003\u0011a\u0017M\\4\n\t\t=\"\u0011\u0006\u0002\u0007\u001f\nTWm\u0019;"
    )
  ScalaInlineInfo: length = 0x2C (unknown attribute)
   01 00 00 08 00 44 00 1F 01 00 32 00 33 00 00 2E
   00 2F 01 00 27 00 28 00 00 2A 00 2B 00 00 3F 00
   40 00 00 3E 00 24 01 00 3B 00 3C 00
  ScalaSig: length = 0x3 (unknown attribute)
   05 02 00
