Classfile /Users/mw/Projects/slang-braindump/.jar/jar8/assemble/slang-braindump/assemble/content/scala/collection/MapOps$$anon$1.class
  Last modified May 29, 2022; size 1296 bytes
  SHA-256 checksum 83cf1a1e50da0ccaa3de8624784c05fdde71a04df0595342968d2dbe59617616
  Compiled from "Map.scala"
public final class scala.collection.MapOps$$anon$1 extends scala.collection.AbstractIterable<V> implements scala.collection.generic.DefaultSerializable
  minor version: 0
  major version: 52
  flags: (0x0031) ACC_PUBLIC, ACC_FINAL, ACC_SUPER
  this_class: #2                          // scala/collection/MapOps$$anon$1
  super_class: #5                         // scala/collection/AbstractIterable
  interfaces: 1, fields: 1, methods: 4, attributes: 6
Constant pool:
   #1 = Utf8               scala/collection/MapOps$$anon$1
   #2 = Class              #1             // scala/collection/MapOps$$anon$1
   #3 = Utf8               Lscala/collection/AbstractIterable<TV;>;Lscala/collection/generic/DefaultSerializable;
   #4 = Utf8               scala/collection/AbstractIterable
   #5 = Class              #4             // scala/collection/AbstractIterable
   #6 = Utf8               scala/collection/generic/DefaultSerializable
   #7 = Class              #6             // scala/collection/generic/DefaultSerializable
   #8 = Utf8               Map.scala
   #9 = Utf8               scala/collection/MapOps
  #10 = Class              #9             // scala/collection/MapOps
  #11 = Utf8               values
  #12 = Utf8               ()Lscala/collection/Iterable;
  #13 = NameAndType        #11:#12        // values:()Lscala/collection/Iterable;
  #14 = Utf8               $outer
  #15 = Utf8               Lscala/collection/MapOps;
  #16 = Utf8               writeReplace
  #17 = Utf8               ()Ljava/lang/Object;
  #18 = Utf8               writeReplace$
  #19 = Utf8               (Lscala/collection/generic/DefaultSerializable;)Ljava/lang/Object;
  #20 = NameAndType        #18:#19        // writeReplace$:(Lscala/collection/generic/DefaultSerializable;)Ljava/lang/Object;
  #21 = InterfaceMethodref #7.#20         // scala/collection/generic/DefaultSerializable.writeReplace$:(Lscala/collection/generic/DefaultSerializable;)Ljava/lang/Object;
  #22 = Utf8               this
  #23 = Utf8               Lscala/collection/MapOps$$anon$1;
  #24 = Utf8               knownSize
  #25 = Utf8               ()I
  #26 = NameAndType        #14:#15        // $outer:Lscala/collection/MapOps;
  #27 = Fieldref           #2.#26         // scala/collection/MapOps$$anon$1.$outer:Lscala/collection/MapOps;
  #28 = NameAndType        #24:#25        // knownSize:()I
  #29 = InterfaceMethodref #10.#28        // scala/collection/MapOps.knownSize:()I
  #30 = Utf8               iterator
  #31 = Utf8               ()Lscala/collection/Iterator;
  #32 = Utf8               ()Lscala/collection/Iterator<TV;>;
  #33 = Utf8               valuesIterator
  #34 = NameAndType        #33:#31        // valuesIterator:()Lscala/collection/Iterator;
  #35 = InterfaceMethodref #10.#34        // scala/collection/MapOps.valuesIterator:()Lscala/collection/Iterator;
  #36 = Utf8               <init>
  #37 = Utf8               (Lscala/collection/MapOps;)V
  #38 = Utf8               ()V
  #39 = NameAndType        #36:#38        // "<init>":()V
  #40 = Methodref          #5.#39         // scala/collection/AbstractIterable."<init>":()V
  #41 = Utf8               Code
  #42 = Utf8               LineNumberTable
  #43 = Utf8               LocalVariableTable
  #44 = Utf8               Signature
  #45 = Utf8               StackMapTable
  #46 = Utf8               MethodParameters
  #47 = Utf8               InnerClasses
  #48 = Utf8               EnclosingMethod
  #49 = Utf8               SourceFile
  #50 = Utf8               ScalaInlineInfo
  #51 = Utf8               Scala
{
  private final scala.collection.MapOps $outer;
    descriptor: Lscala/collection/MapOps;
    flags: (0x1012) ACC_PRIVATE, ACC_FINAL, ACC_SYNTHETIC

  public java.lang.Object writeReplace();
    descriptor: ()Ljava/lang/Object;
    flags: (0x0001) ACC_PUBLIC
    Code:
      stack=1, locals=1, args_size=1
         0: aload_0
         1: invokestatic  #21                 // InterfaceMethod scala/collection/generic/DefaultSerializable.writeReplace$:(Lscala/collection/generic/DefaultSerializable;)Ljava/lang/Object;
         4: areturn
      LineNumberTable:
        line 212: 0
      LocalVariableTable:
        Start  Length  Slot  Name   Signature
            0       5     0  this   Lscala/collection/MapOps$$anon$1;

  public int knownSize();
    descriptor: ()I
    flags: (0x0001) ACC_PUBLIC
    Code:
      stack=1, locals=1, args_size=1
         0: aload_0
         1: getfield      #27                 // Field $outer:Lscala/collection/MapOps;
         4: invokeinterface #29,  1           // InterfaceMethod scala/collection/MapOps.knownSize:()I
         9: ireturn
      LineNumberTable:
        line 213: 0
      LocalVariableTable:
        Start  Length  Slot  Name   Signature
            0      10     0  this   Lscala/collection/MapOps$$anon$1;

  public scala.collection.Iterator<V> iterator();
    descriptor: ()Lscala/collection/Iterator;
    flags: (0x0001) ACC_PUBLIC
    Code:
      stack=1, locals=1, args_size=1
         0: aload_0
         1: getfield      #27                 // Field $outer:Lscala/collection/MapOps;
         4: invokeinterface #35,  1           // InterfaceMethod scala/collection/MapOps.valuesIterator:()Lscala/collection/Iterator;
         9: areturn
      LineNumberTable:
        line 214: 0
      LocalVariableTable:
        Start  Length  Slot  Name   Signature
            0      10     0  this   Lscala/collection/MapOps$$anon$1;
    Signature: #32                          // ()Lscala/collection/Iterator<TV;>;

  public scala.collection.MapOps$$anon$1(scala.collection.MapOps);
    descriptor: (Lscala/collection/MapOps;)V
    flags: (0x0001) ACC_PUBLIC
    Code:
      stack=2, locals=2, args_size=2
         0: aload_1
         1: ifnonnull     6
         4: aconst_null
         5: athrow
         6: aload_0
         7: aload_1
         8: putfield      #27                 // Field $outer:Lscala/collection/MapOps;
        11: aload_0
        12: invokespecial #40                 // Method scala/collection/AbstractIterable."<init>":()V
        15: return
      StackMapTable: number_of_entries = 1
        frame_type = 6 /* same */
      LineNumberTable:
        line 212: 0
      LocalVariableTable:
        Start  Length  Slot  Name   Signature
            0      16     0  this   Lscala/collection/MapOps$$anon$1;
            0      16     1 $outer   Lscala/collection/MapOps;
    MethodParameters:
      Name                           Flags
      $outer                         final synthetic
}
InnerClasses:
  public final #2;                        // class scala/collection/MapOps$$anon$1
EnclosingMethod: #10.#13                // scala.collection.MapOps.values
Signature: #3                           // Lscala/collection/AbstractIterable<TV;>;Lscala/collection/generic/DefaultSerializable;
SourceFile: "Map.scala"
  ScalaInlineInfo: length = 0x18 (unknown attribute)
   01 01 00 04 00 24 00 25 01 00 1E 00 1F 01 00 18
   00 19 01 00 10 00 11 01
  Scala: length = 0x0 (unknown attribute)

