Classfile /Users/mw/Projects/slang-braindump/.jar/jar8/assemble/slang-braindump/assemble/content/scala/collection/MapViewFactory.class
  Last modified May 29, 2022; size 2821 bytes
  SHA-256 checksum db5af1cf2d9adfd0c4d394637f4818270b884accfe9cd5c7efba74df55b313d2
  Compiled from "MapView.scala"
public interface scala.collection.MapViewFactory extends scala.collection.MapFactory<?>
  minor version: 0
  major version: 52
  flags: (0x0601) ACC_PUBLIC, ACC_INTERFACE, ACC_ABSTRACT
  this_class: #2                          // scala/collection/MapViewFactory
  super_class: #5                         // java/lang/Object
  interfaces: 1, fields: 0, methods: 6, attributes: 5
Constant pool:
   #1 = Utf8               scala/collection/MapViewFactory
   #2 = Class              #1             // scala/collection/MapViewFactory
   #3 = Utf8               Ljava/lang/Object;Lscala/collection/MapFactory<*>;
   #4 = Utf8               java/lang/Object
   #5 = Class              #4             // java/lang/Object
   #6 = Utf8               scala/collection/MapFactory
   #7 = Class              #6             // scala/collection/MapFactory
   #8 = Utf8               MapView.scala
   #9 = Utf8               Lscala/reflect/ScalaSignature;
  #10 = Utf8               bytes
  #11 = Utf8               \u0006\u0005}4qAB\u0004\u0011\u0002\u0007\u0005A\u0002C\u0003:\u0001\u0011\u0005!\bC\u0003?\u0001\u0019\u0005q\bC\u0003P\u0001\u0019\u0005\u0001\u000bC\u0003X\u0001\u0019\u0005\u0001\fC\u0003r\u0001\u0011\u0005#O\u0001\bNCB4\u0016.Z<GC\u000e$xN]=\u000b\u0005!I\u0011AC2pY2,7\r^5p]*\t!\"A\u0003tG\u0006d\u0017m\u0001\u0001\u0014\u0007\u0001i\u0011\u0003\u0005\u0002\u000f\u001f5\t\u0011\"\u0003\u0002\u0011\u0013\t1\u0011I\\=SK\u001a\u00042AE\n\u0016\u001b\u00059\u0011B\u0001\u000b\b\u0005)i\u0015\r\u001d$bGR|\'/_\u000b\u0004-yA\u0004c\u0001\n\u00183%\u0011\u0001d\u0002\u0002\u0005-&,w\u000f\u0005\u0003\u000f5q9\u0014BA\u000e\n\u0005\u0019!V\u000f\u001d7feA\u0011QD\b\u0007\u0001\t\u0015y\u0002E1\u0001-\u0005\u0005A\u0006\u0002B\u0011#\u0001Y\n\u0011\u0002\u00107pG\u0006d\u0007\u0005\u001c \u0006\t\r\"\u0003a\n\u0002\u0002Y\u001a!Q\u0005\u0001\u0001\'\u00051a$/\u001a4j]\u0016lWM\u001c;?%\t!S\"F\u0002)WQ\u00022AE\f*!\u0011q!DK\u001a\u0011\u0005uYC!B\u0010#\u0005\u0004a\u0013CA\u00171!\tqa&\u0003\u00020\u0013\t9aj\u001c;iS:<\u0007C\u0001\b2\u0013\t\u0011\u0014BA\u0002B]f\u0004\"!\b\u001b\u0005\u000bU\u0012#\u0019\u0001\u0017\u0003\u0003e[\u0001\u0001\u0005\u0002\u001eq\u0011)Q\u0007\tb\u0001Y\u00051A%\u001b8ji\u0012\"\u0012a\u000f\t\u0003\u001dqJ!!P\u0005\u0003\tUs\u0017\u000e^\u0001\u000b]\u0016<()^5mI\u0016\u0014Xc\u0001!J\u0017V\t\u0011\t\u0005\u0003C\u000b\u001ecU\"A\"\u000b\u0005\u0011;\u0011aB7vi\u0006\u0014G.Z\u0005\u0003\r\u000e\u0013qAQ;jY\u0012,\'\u000f\u0005\u0003\u000f5!S\u0005CA\u000fJ\t\u0015y\"A1\u0001-!\ti2\nB\u00036\u0005\t\u0007A\u0006\u0005\u0003\u0013\u001b\"S\u0015B\u0001(\b\u0005\u001di\u0015\r\u001d,jK^\fQ!Z7qif,2!\u0015+W+\u0005\u0011\u0006\u0003\u0002\nN\'V\u0003\"!\b+\u0005\u000b}\u0019!\u0019\u0001\u0017\u0011\u0005u1F!B\u001b\u0004\u0005\u0004a\u0013\u0001\u00024s_6,2!\u0017/`)\tQ\u0016\r\u0005\u0003\u0013\u001bns\u0006CA\u000f]\t\u0015iFA1\u0001-\u0005\u0005Y\u0005CA\u000f`\t\u0015\u0001GA1\u0001-\u0005\u00051\u0006\"\u00022\u0005\u0001\u0004\u0019\u0017AA5u!\u0011!gn\u00170\u000f\u0005\u0015dgB\u00014l\u001d\t9\'.D\u0001i\u0015\tI7\"\u0001\u0004=e>|GOP\u0005\u0002\u0015%\u0011\u0001\"C\u0005\u0003[\u001e\tq!T1q-&,w/\u0003\u0002pa\nQ1k\\7f\u001b\u0006\u0004x\n]:\u000b\u00055<\u0011!B1qa2LXcA:wqR\u0011A/\u001f\t\u0005%5+x\u000f\u0005\u0002\u001em\u0012)Q,\u0002b\u0001YA\u0011Q\u0004\u001f\u0003\u0006A\u0016\u0011\r\u0001\f\u0005\u0006u\u0016\u0001\ra_\u0001\u0006K2,Wn\u001d\t\u0004\u001dqt\u0018BA?\n\u0005)a$/\u001a9fCR,GM\u0010\t\u0005\u001di)x\u000f
  #12 = Utf8               newBuilder
  #13 = Utf8               ()Lscala/collection/mutable/Builder;
  #14 = Utf8               <X:Ljava/lang/Object;Y:Ljava/lang/Object;>()Lscala/collection/mutable/Builder<Lscala/Tuple2<TX;TY;>;Lscala/collection/MapView<TX;TY;>;>;
  #15 = Utf8               empty
  #16 = Utf8               ()Lscala/collection/MapView;
  #17 = Utf8               <X:Ljava/lang/Object;Y:Ljava/lang/Object;>()Lscala/collection/MapView<TX;TY;>;
  #18 = Utf8               from
  #19 = Utf8               (Lscala/collection/MapOps;)Lscala/collection/MapView;
  #20 = Utf8               <K:Ljava/lang/Object;V:Ljava/lang/Object;>(Lscala/collection/MapOps<TK;TV;*Ljava/lang/Object;>;)Lscala/collection/MapView<TK;TV;>;
  #21 = Utf8               it
  #22 = Utf8               apply$
  #23 = Utf8               (Lscala/collection/MapViewFactory;Lscala/collection/immutable/Seq;)Lscala/collection/MapView;
  #24 = Utf8               $this
  #25 = Utf8               elems
  #26 = Utf8               apply
  #27 = Utf8               (Lscala/collection/immutable/Seq;)Lscala/collection/MapView;
  #28 = NameAndType        #26:#27        // apply:(Lscala/collection/immutable/Seq;)Lscala/collection/MapView;
  #29 = InterfaceMethodref #2.#28         // scala/collection/MapViewFactory.apply:(Lscala/collection/immutable/Seq;)Lscala/collection/MapView;
  #30 = Utf8               Lscala/collection/MapViewFactory;
  #31 = Utf8               Lscala/collection/immutable/Seq;
  #32 = Utf8               <K:Ljava/lang/Object;V:Ljava/lang/Object;>(Lscala/collection/immutable/Seq<Lscala/Tuple2<TK;TV;>;>;)Lscala/collection/MapView<TK;TV;>;
  #33 = Utf8               scala/$less$colon$less$
  #34 = Class              #33            // scala/$less$colon$less$
  #35 = Utf8               MODULE$
  #36 = Utf8               Lscala/$less$colon$less$;
  #37 = NameAndType        #35:#36        // MODULE$:Lscala/$less$colon$less$;
  #38 = Fieldref           #34.#37        // scala/$less$colon$less$.MODULE$:Lscala/$less$colon$less$;
  #39 = Utf8               refl
  #40 = Utf8               ()Lscala/$eq$colon$eq;
  #41 = NameAndType        #39:#40        // refl:()Lscala/$eq$colon$eq;
  #42 = Methodref          #34.#41        // scala/$less$colon$less$.refl:()Lscala/$eq$colon$eq;
  #43 = Utf8               scala/collection/immutable/Seq
  #44 = Class              #43            // scala/collection/immutable/Seq
  #45 = Utf8               toMap
  #46 = Utf8               (Lscala/$less$colon$less;)Lscala/collection/immutable/Map;
  #47 = NameAndType        #45:#46        // toMap:(Lscala/$less$colon$less;)Lscala/collection/immutable/Map;
  #48 = InterfaceMethodref #44.#47        // scala/collection/immutable/Seq.toMap:(Lscala/$less$colon$less;)Lscala/collection/immutable/Map;
  #49 = NameAndType        #18:#19        // from:(Lscala/collection/MapOps;)Lscala/collection/MapView;
  #50 = InterfaceMethodref #2.#49         // scala/collection/MapViewFactory.from:(Lscala/collection/MapOps;)Lscala/collection/MapView;
  #51 = Utf8               this
  #52 = Utf8               $init$
  #53 = Utf8               (Lscala/collection/MapViewFactory;)V
  #54 = Utf8               Signature
  #55 = Utf8               MethodParameters
  #56 = Utf8               Code
  #57 = Utf8               LineNumberTable
  #58 = Utf8               LocalVariableTable
  #59 = Utf8               SourceFile
  #60 = Utf8               RuntimeVisibleAnnotations
  #61 = Utf8               ScalaInlineInfo
  #62 = Utf8               ScalaSig
{
  public abstract <X extends java.lang.Object, Y extends java.lang.Object> scala.collection.mutable.Builder<scala.Tuple2<X, Y>, scala.collection.MapView<X, Y>> newBuilder();
    descriptor: ()Lscala/collection/mutable/Builder;
    flags: (0x0401) ACC_PUBLIC, ACC_ABSTRACT
    Signature: #14                          // <X:Ljava/lang/Object;Y:Ljava/lang/Object;>()Lscala/collection/mutable/Builder<Lscala/Tuple2<TX;TY;>;Lscala/collection/MapView<TX;TY;>;>;

  public abstract <X extends java.lang.Object, Y extends java.lang.Object> scala.collection.MapView<X, Y> empty();
    descriptor: ()Lscala/collection/MapView;
    flags: (0x0401) ACC_PUBLIC, ACC_ABSTRACT
    Signature: #17                          // <X:Ljava/lang/Object;Y:Ljava/lang/Object;>()Lscala/collection/MapView<TX;TY;>;

  public abstract <K extends java.lang.Object, V extends java.lang.Object> scala.collection.MapView<K, V> from(scala.collection.MapOps<K, V, ?, java.lang.Object>);
    descriptor: (Lscala/collection/MapOps;)Lscala/collection/MapView;
    flags: (0x0401) ACC_PUBLIC, ACC_ABSTRACT
    Signature: #20                          // <K:Ljava/lang/Object;V:Ljava/lang/Object;>(Lscala/collection/MapOps<TK;TV;*Ljava/lang/Object;>;)Lscala/collection/MapView<TK;TV;>;
    MethodParameters:
      Name                           Flags
      it                             final

  public static scala.collection.MapView apply$(scala.collection.MapViewFactory, scala.collection.immutable.Seq);
    descriptor: (Lscala/collection/MapViewFactory;Lscala/collection/immutable/Seq;)Lscala/collection/MapView;
    flags: (0x1009) ACC_PUBLIC, ACC_STATIC, ACC_SYNTHETIC
    Code:
      stack=2, locals=2, args_size=2
         0: aload_0
         1: aload_1
         2: invokespecial #29                 // InterfaceMethod apply:(Lscala/collection/immutable/Seq;)Lscala/collection/MapView;
         5: areturn
      LineNumberTable:
        line 181: 0
      LocalVariableTable:
        Start  Length  Slot  Name   Signature
            0       6     0 $this   Lscala/collection/MapViewFactory;
            0       6     1 elems   Lscala/collection/immutable/Seq;
    MethodParameters:
      Name                           Flags
      $this                          final synthetic
      elems                          final

  public default <K extends java.lang.Object, V extends java.lang.Object> scala.collection.MapView<K, V> apply(scala.collection.immutable.Seq<scala.Tuple2<K, V>>);
    descriptor: (Lscala/collection/immutable/Seq;)Lscala/collection/MapView;
    flags: (0x0001) ACC_PUBLIC
    Code:
      stack=3, locals=2, args_size=2
         0: aload_0
         1: aload_1
         2: getstatic     #38                 // Field scala/$less$colon$less$.MODULE$:Lscala/$less$colon$less$;
         5: invokevirtual #42                 // Method scala/$less$colon$less$.refl:()Lscala/$eq$colon$eq;
         8: invokeinterface #48,  2           // InterfaceMethod scala/collection/immutable/Seq.toMap:(Lscala/$less$colon$less;)Lscala/collection/immutable/Map;
        13: invokeinterface #50,  2           // InterfaceMethod from:(Lscala/collection/MapOps;)Lscala/collection/MapView;
        18: areturn
      LineNumberTable:
        line 181: 0
      LocalVariableTable:
        Start  Length  Slot  Name   Signature
            0      19     0  this   Lscala/collection/MapViewFactory;
            0      19     1 elems   Lscala/collection/immutable/Seq;
    Signature: #32                          // <K:Ljava/lang/Object;V:Ljava/lang/Object;>(Lscala/collection/immutable/Seq<Lscala/Tuple2<TK;TV;>;>;)Lscala/collection/MapView<TK;TV;>;
    MethodParameters:
      Name                           Flags
      elems                          final

  public static void $init$(scala.collection.MapViewFactory);
    descriptor: (Lscala/collection/MapViewFactory;)V
    flags: (0x0009) ACC_PUBLIC, ACC_STATIC
    Code:
      stack=0, locals=1, args_size=1
         0: return
      LineNumberTable:
        line 173: 0
      LocalVariableTable:
        Start  Length  Slot  Name   Signature
            0       1     0 $this   Lscala/collection/MapViewFactory;
    MethodParameters:
      Name                           Flags
      $this                          final synthetic
}
Signature: #3                           // Ljava/lang/Object;Lscala/collection/MapFactory<*>;
SourceFile: "MapView.scala"
RuntimeVisibleAnnotations:
  0: #9(#10=s#11)
    scala.reflect.ScalaSignature(
      bytes="\u0006\u0005}4qAB\u0004\u0011\u0002\u0007\u0005A\u0002C\u0003:\u0001\u0011\u0005!\bC\u0003?\u0001\u0019\u0005q\bC\u0003P\u0001\u0019\u0005\u0001\u000bC\u0003X\u0001\u0019\u0005\u0001\fC\u0003r\u0001\u0011\u0005#O\u0001\bNCB4\u0016.Z<GC\u000e$xN]=\u000b\u0005!I\u0011AC2pY2,7\r^5p]*\t!\"A\u0003tG\u0006d\u0017m\u0001\u0001\u0014\u0007\u0001i\u0011\u0003\u0005\u0002\u000f\u001f5\t\u0011\"\u0003\u0002\u0011\u0013\t1\u0011I\\=SK\u001a\u00042AE\n\u0016\u001b\u00059\u0011B\u0001\u000b\b\u0005)i\u0015\r\u001d$bGR|\'/_\u000b\u0004-yA\u0004c\u0001\n\u00183%\u0011\u0001d\u0002\u0002\u0005-&,w\u000f\u0005\u0003\u000f5q9\u0014BA\u000e\n\u0005\u0019!V\u000f\u001d7feA\u0011QD\b\u0007\u0001\t\u0015y\u0002E1\u0001-\u0005\u0005A\u0006\u0002B\u0011#\u0001Y\n\u0011\u0002\u00107pG\u0006d\u0007\u0005\u001c \u0006\t\r\"\u0003a\n\u0002\u0002Y\u001a!Q\u0005\u0001\u0001\'\u00051a$/\u001a4j]\u0016lWM\u001c;?%\t!S\"F\u0002)WQ\u00022AE\f*!\u0011q!DK\u001a\u0011\u0005uYC!B\u0010#\u0005\u0004a\u0013CA\u00171!\tqa&\u0003\u00020\u0013\t9aj\u001c;iS:<\u0007C\u0001\b2\u0013\t\u0011\u0014BA\u0002B]f\u0004\"!\b\u001b\u0005\u000bU\u0012#\u0019\u0001\u0017\u0003\u0003e[\u0001\u0001\u0005\u0002\u001eq\u0011)Q\u0007\tb\u0001Y\u00051A%\u001b8ji\u0012\"\u0012a\u000f\t\u0003\u001dqJ!!P\u0005\u0003\tUs\u0017\u000e^\u0001\u000b]\u0016<()^5mI\u0016\u0014Xc\u0001!J\u0017V\t\u0011\t\u0005\u0003C\u000b\u001ecU\"A\"\u000b\u0005\u0011;\u0011aB7vi\u0006\u0014G.Z\u0005\u0003\r\u000e\u0013qAQ;jY\u0012,\'\u000f\u0005\u0003\u000f5!S\u0005CA\u000fJ\t\u0015y\"A1\u0001-!\ti2\nB\u00036\u0005\t\u0007A\u0006\u0005\u0003\u0013\u001b\"S\u0015B\u0001(\b\u0005\u001di\u0015\r\u001d,jK^\fQ!Z7qif,2!\u0015+W+\u0005\u0011\u0006\u0003\u0002\nN\'V\u0003\"!\b+\u0005\u000b}\u0019!\u0019\u0001\u0017\u0011\u0005u1F!B\u001b\u0004\u0005\u0004a\u0013\u0001\u00024s_6,2!\u0017/`)\tQ\u0016\r\u0005\u0003\u0013\u001bns\u0006CA\u000f]\t\u0015iFA1\u0001-\u0005\u0005Y\u0005CA\u000f`\t\u0015\u0001GA1\u0001-\u0005\u00051\u0006\"\u00022\u0005\u0001\u0004\u0019\u0017AA5u!\u0011!gn\u00170\u000f\u0005\u0015dgB\u00014l\u001d\t9\'.D\u0001i\u0015\tI7\"\u0001\u0004=e>|GOP\u0005\u0002\u0015%\u0011\u0001\"C\u0005\u0003[\u001e\tq!T1q-&,w/\u0003\u0002pa\nQ1k\\7f\u001b\u0006\u0004x\n]:\u000b\u00055<\u0011!B1qa2LXcA:wqR\u0011A/\u001f\t\u0005%5+x\u000f\u0005\u0002\u001em\u0012)Q,\u0002b\u0001YA\u0011Q\u0004\u001f\u0003\u0006A\u0016\u0011\r\u0001\f\u0005\u0006u\u0016\u0001\ra_\u0001\u0006K2,Wn\u001d\t\u0004\u001dqt\u0018BA?\n\u0005)a$/\u001a9fCR,GM\u0010\t\u0005\u001di)x\u000f"
    )
  ScalaInlineInfo: length = 0x22 (unknown attribute)
   01 00 00 06 00 34 00 35 01 00 1A 00 1B 00 00 16
   00 17 01 00 0F 00 10 00 00 12 00 13 00 00 0C 00
   0D 00
  ScalaSig: length = 0x3 (unknown attribute)
   05 02 00
