Classfile /Users/mw/Projects/slang-braindump/.jar/jar8/assemble/slang-braindump/assemble/content/scala/collection/MapView$Filter.class
  Last modified May 29, 2022; size 2404 bytes
  SHA-256 checksum d139c3f00d29b9080f367b29625e8b364bd2b528d89245255b7df4426fac92d2
  Compiled from "MapView.scala"
public class scala.collection.MapView$Filter<K extends java.lang.Object, V extends java.lang.Object> extends scala.collection.AbstractMapView<K, V>
  minor version: 0
  major version: 52
  flags: (0x0021) ACC_PUBLIC, ACC_SUPER
  this_class: #2                          // scala/collection/MapView$Filter
  super_class: #5                         // scala/collection/AbstractMapView
  interfaces: 0, fields: 4, methods: 5, attributes: 5
Constant pool:
    #1 = Utf8               scala/collection/MapView$Filter
    #2 = Class              #1            // scala/collection/MapView$Filter
    #3 = Utf8               <K:Ljava/lang/Object;V:Ljava/lang/Object;>Lscala/collection/AbstractMapView<TK;TV;>;
    #4 = Utf8               scala/collection/AbstractMapView
    #5 = Class              #4            // scala/collection/AbstractMapView
    #6 = Utf8               MapView.scala
    #7 = Utf8               scala/collection/MapView
    #8 = Class              #7            // scala/collection/MapView
    #9 = Utf8               Filter
   #10 = Utf8               serialVersionUID
   #11 = Utf8               J
   #12 = Long               3l
   #14 = Utf8               underlying
   #15 = Utf8               Lscala/collection/MapOps;
   #16 = Utf8               Lscala/collection/MapOps<TK;TV;*Ljava/lang/Object;>;
   #17 = Utf8               isFlipped
   #18 = Utf8               Z
   #19 = Utf8               p
   #20 = Utf8               Lscala/Function1;
   #21 = Utf8               Lscala/Function1<Lscala/Tuple2<TK;TV;>;Ljava/lang/Object;>;
   #22 = Utf8               iterator
   #23 = Utf8               ()Lscala/collection/Iterator;
   #24 = Utf8               ()Lscala/collection/Iterator<Lscala/Tuple2<TK;TV;>;>;
   #25 = NameAndType        #14:#15       // underlying:Lscala/collection/MapOps;
   #26 = Fieldref           #2.#25        // scala/collection/MapView$Filter.underlying:Lscala/collection/MapOps;
   #27 = Utf8               scala/collection/MapOps
   #28 = Class              #27           // scala/collection/MapOps
   #29 = NameAndType        #22:#23       // iterator:()Lscala/collection/Iterator;
   #30 = InterfaceMethodref #28.#29       // scala/collection/MapOps.iterator:()Lscala/collection/Iterator;
   #31 = NameAndType        #19:#20       // p:Lscala/Function1;
   #32 = Fieldref           #2.#31        // scala/collection/MapView$Filter.p:Lscala/Function1;
   #33 = NameAndType        #17:#18       // isFlipped:Z
   #34 = Fieldref           #2.#33        // scala/collection/MapView$Filter.isFlipped:Z
   #35 = Utf8               scala/collection/Iterator
   #36 = Class              #35           // scala/collection/Iterator
   #37 = Utf8               filterImpl
   #38 = Utf8               (Lscala/Function1;Z)Lscala/collection/Iterator;
   #39 = NameAndType        #37:#38       // filterImpl:(Lscala/Function1;Z)Lscala/collection/Iterator;
   #40 = InterfaceMethodref #36.#39       // scala/collection/Iterator.filterImpl:(Lscala/Function1;Z)Lscala/collection/Iterator;
   #41 = Utf8               this
   #42 = Utf8               Lscala/collection/MapView$Filter;
   #43 = Utf8               get
   #44 = Utf8               (Ljava/lang/Object;)Lscala/Option;
   #45 = Utf8               (TK;)Lscala/Option<TV;>;
   #46 = Utf8               key
   #47 = NameAndType        #43:#44       // get:(Ljava/lang/Object;)Lscala/Option;
   #48 = InterfaceMethodref #28.#47       // scala/collection/MapOps.get:(Ljava/lang/Object;)Lscala/Option;
   #49 = Utf8               scala/Some
   #50 = Class              #49           // scala/Some
   #51 = Utf8               value
   #52 = Utf8               ()Ljava/lang/Object;
   #53 = NameAndType        #51:#52       // value:()Ljava/lang/Object;
   #54 = Methodref          #50.#53       // scala/Some.value:()Ljava/lang/Object;
   #55 = Utf8               scala/Tuple2
   #56 = Class              #55           // scala/Tuple2
   #57 = Utf8               <init>
   #58 = Utf8               (Ljava/lang/Object;Ljava/lang/Object;)V
   #59 = NameAndType        #57:#58       // "<init>":(Ljava/lang/Object;Ljava/lang/Object;)V
   #60 = Methodref          #56.#59       // scala/Tuple2."<init>":(Ljava/lang/Object;Ljava/lang/Object;)V
   #61 = Utf8               scala/Function1
   #62 = Class              #61           // scala/Function1
   #63 = Utf8               apply
   #64 = Utf8               (Ljava/lang/Object;)Ljava/lang/Object;
   #65 = NameAndType        #63:#64       // apply:(Ljava/lang/Object;)Ljava/lang/Object;
   #66 = InterfaceMethodref #62.#65       // scala/Function1.apply:(Ljava/lang/Object;)Ljava/lang/Object;
   #67 = Utf8               scala/runtime/BoxesRunTime
   #68 = Class              #67           // scala/runtime/BoxesRunTime
   #69 = Utf8               unboxToBoolean
   #70 = Utf8               (Ljava/lang/Object;)Z
   #71 = NameAndType        #69:#70       // unboxToBoolean:(Ljava/lang/Object;)Z
   #72 = Methodref          #68.#71       // scala/runtime/BoxesRunTime.unboxToBoolean:(Ljava/lang/Object;)Z
   #73 = Utf8               scala/None$
   #74 = Class              #73           // scala/None$
   #75 = Utf8               MODULE$
   #76 = Utf8               Lscala/None$;
   #77 = NameAndType        #75:#76       // MODULE$:Lscala/None$;
   #78 = Fieldref           #74.#77       // scala/None$.MODULE$:Lscala/None$;
   #79 = Utf8               v
   #80 = Utf8               Ljava/lang/Object;
   #81 = Utf8               scala/Option
   #82 = Class              #81           // scala/Option
   #83 = Utf8               java/lang/Object
   #84 = Class              #83           // java/lang/Object
   #85 = Utf8               knownSize
   #86 = Utf8               ()I
   #87 = NameAndType        #85:#86       // knownSize:()I
   #88 = InterfaceMethodref #28.#87       // scala/collection/MapOps.knownSize:()I
   #89 = Utf8               isEmpty
   #90 = Utf8               ()Z
   #91 = Methodref          #2.#29        // scala/collection/MapView$Filter.iterator:()Lscala/collection/Iterator;
   #92 = NameAndType        #89:#90       // isEmpty:()Z
   #93 = InterfaceMethodref #36.#92       // scala/collection/Iterator.isEmpty:()Z
   #94 = Utf8               (Lscala/collection/MapOps;ZLscala/Function1;)V
   #95 = Utf8               (Lscala/collection/MapOps<TK;TV;*Ljava/lang/Object;>;ZLscala/Function1<Lscala/Tuple2<TK;TV;>;Ljava/lang/Object;>;)V
   #96 = Utf8               ()V
   #97 = NameAndType        #57:#96       // "<init>":()V
   #98 = Methodref          #5.#97        // scala/collection/AbstractMapView."<init>":()V
   #99 = Utf8               ConstantValue
  #100 = Utf8               Signature
  #101 = Utf8               Code
  #102 = Utf8               LineNumberTable
  #103 = Utf8               LocalVariableTable
  #104 = Utf8               StackMapTable
  #105 = Utf8               MethodParameters
  #106 = Utf8               InnerClasses
  #107 = Utf8               SourceFile
  #108 = Utf8               ScalaInlineInfo
  #109 = Utf8               Scala
{
  private static final long serialVersionUID;
    descriptor: J
    flags: (0x001a) ACC_PRIVATE, ACC_STATIC, ACC_FINAL
    ConstantValue: long 3l

  private final scala.collection.MapOps<K, V, ?, java.lang.Object> underlying;
    descriptor: Lscala/collection/MapOps;
    flags: (0x0012) ACC_PRIVATE, ACC_FINAL
    Signature: #16                          // Lscala/collection/MapOps<TK;TV;*Ljava/lang/Object;>;

  private final boolean isFlipped;
    descriptor: Z
    flags: (0x0012) ACC_PRIVATE, ACC_FINAL

  private final scala.Function1<scala.Tuple2<K, V>, java.lang.Object> p;
    descriptor: Lscala/Function1;
    flags: (0x0012) ACC_PRIVATE, ACC_FINAL
    Signature: #21                          // Lscala/Function1<Lscala/Tuple2<TK;TV;>;Ljava/lang/Object;>;

  public scala.collection.Iterator<scala.Tuple2<K, V>> iterator();
    descriptor: ()Lscala/collection/Iterator;
    flags: (0x0001) ACC_PUBLIC
    Code:
      stack=3, locals=1, args_size=1
         0: aload_0
         1: getfield      #26                 // Field underlying:Lscala/collection/MapOps;
         4: invokeinterface #30,  1           // InterfaceMethod scala/collection/MapOps.iterator:()Lscala/collection/Iterator;
         9: aload_0
        10: getfield      #32                 // Field p:Lscala/Function1;
        13: aload_0
        14: getfield      #34                 // Field isFlipped:Z
        17: invokeinterface #40,  3           // InterfaceMethod scala/collection/Iterator.filterImpl:(Lscala/Function1;Z)Lscala/collection/Iterator;
        22: areturn
      LineNumberTable:
        line 135: 0
      LocalVariableTable:
        Start  Length  Slot  Name   Signature
            0      23     0  this   Lscala/collection/MapView$Filter;
    Signature: #24                          // ()Lscala/collection/Iterator<Lscala/Tuple2<TK;TV;>;>;

  public scala.Option<V> get(K);
    descriptor: (Ljava/lang/Object;)Lscala/Option;
    flags: (0x0001) ACC_PUBLIC
    Code:
      stack=5, locals=6, args_size=2
         0: aload_0
         1: getfield      #26                 // Field underlying:Lscala/collection/MapOps;
         4: aload_1
         5: invokeinterface #48,  2           // InterfaceMethod scala/collection/MapOps.get:(Ljava/lang/Object;)Lscala/Option;
        10: astore_3
        11: aload_3
        12: instanceof    #50                 // class scala/Some
        15: ifeq          66
        18: aload_3
        19: checkcast     #50                 // class scala/Some
        22: astore        4
        24: aload         4
        26: invokevirtual #54                 // Method scala/Some.value:()Ljava/lang/Object;
        29: astore        5
        31: aload_0
        32: getfield      #32                 // Field p:Lscala/Function1;
        35: new           #56                 // class scala/Tuple2
        38: dup
        39: aload_1
        40: aload         5
        42: invokespecial #60                 // Method scala/Tuple2."<init>":(Ljava/lang/Object;Ljava/lang/Object;)V
        45: invokeinterface #66,  2           // InterfaceMethod scala/Function1.apply:(Ljava/lang/Object;)Ljava/lang/Object;
        50: invokestatic  #72                 // Method scala/runtime/BoxesRunTime.unboxToBoolean:(Ljava/lang/Object;)Z
        53: aload_0
        54: getfield      #34                 // Field isFlipped:Z
        57: if_icmpeq     66
        60: aload         4
        62: astore_2
        63: goto          70
        66: getstatic     #78                 // Field scala/None$.MODULE$:Lscala/None$;
        69: astore_2
        70: aload_2
        71: areturn
      StackMapTable: number_of_entries = 2
        frame_type = 253 /* append */
          offset_delta = 66
          locals = [ top, class scala/Option ]
        frame_type = 255 /* full_frame */
          offset_delta = 3
          locals = [ class scala/collection/MapView$Filter, class java/lang/Object, class scala/Option, class scala/Option ]
          stack = []
      LineNumberTable:
        line 136: 0
        line 137: 11
        line 138: 66
        line 136: 70
      LocalVariableTable:
        Start  Length  Slot  Name   Signature
           31      35     5     v   Ljava/lang/Object;
            0      72     0  this   Lscala/collection/MapView$Filter;
            0      72     1   key   Ljava/lang/Object;
    Signature: #45                          // (TK;)Lscala/Option<TV;>;
    MethodParameters:
      Name                           Flags
      key                            final

  public int knownSize();
    descriptor: ()I
    flags: (0x0001) ACC_PUBLIC
    Code:
      stack=2, locals=1, args_size=1
         0: aload_0
         1: getfield      #26                 // Field underlying:Lscala/collection/MapOps;
         4: invokeinterface #88,  1           // InterfaceMethod scala/collection/MapOps.knownSize:()I
         9: iconst_0
        10: if_icmpne     15
        13: iconst_0
        14: ireturn
        15: iconst_m1
        16: ireturn
      StackMapTable: number_of_entries = 1
        frame_type = 15 /* same */
      LineNumberTable:
        line 140: 0
      LocalVariableTable:
        Start  Length  Slot  Name   Signature
            0      17     0  this   Lscala/collection/MapView$Filter;

  public boolean isEmpty();
    descriptor: ()Z
    flags: (0x0001) ACC_PUBLIC
    Code:
      stack=1, locals=1, args_size=1
         0: aload_0
         1: invokevirtual #91                 // Method iterator:()Lscala/collection/Iterator;
         4: invokeinterface #93,  1           // InterfaceMethod scala/collection/Iterator.isEmpty:()Z
         9: ireturn
      LineNumberTable:
        line 141: 0
      LocalVariableTable:
        Start  Length  Slot  Name   Signature
            0      10     0  this   Lscala/collection/MapView$Filter;

  public scala.collection.MapView$Filter(scala.collection.MapOps<K, V, ?, java.lang.Object>, boolean, scala.Function1<scala.Tuple2<K, V>, java.lang.Object>);
    descriptor: (Lscala/collection/MapOps;ZLscala/Function1;)V
    flags: (0x0001) ACC_PUBLIC
    Code:
      stack=2, locals=4, args_size=4
         0: aload_0
         1: aload_1
         2: putfield      #26                 // Field underlying:Lscala/collection/MapOps;
         5: aload_0
         6: iload_2
         7: putfield      #34                 // Field isFlipped:Z
        10: aload_0
        11: aload_3
        12: putfield      #32                 // Field p:Lscala/Function1;
        15: aload_0
        16: invokespecial #98                 // Method scala/collection/AbstractMapView."<init>":()V
        19: return
      LineNumberTable:
        line 134: 0
      LocalVariableTable:
        Start  Length  Slot  Name   Signature
            0      20     0  this   Lscala/collection/MapView$Filter;
            0      20     1 underlying   Lscala/collection/MapOps;
            0      20     2 isFlipped   Z
            0      20     3     p   Lscala/Function1;
    Signature: #95                          // (Lscala/collection/MapOps<TK;TV;*Ljava/lang/Object;>;ZLscala/Function1<Lscala/Tuple2<TK;TV;>;Ljava/lang/Object;>;)V
    MethodParameters:
      Name                           Flags
      underlying                     final
      isFlipped                      final
      p                              final
}
InnerClasses:
  public static #9= #2 of #8;             // Filter=class scala/collection/MapView$Filter of class scala/collection/MapView
Signature: #3                           // <K:Ljava/lang/Object;V:Ljava/lang/Object;>Lscala/collection/AbstractMapView<TK;TV;>;
SourceFile: "MapView.scala"
  ScalaInlineInfo: length = 0x1D (unknown attribute)
   01 00 00 05 00 39 00 5E 00 00 2B 00 2C 00 00 59
   00 5A 00 00 16 00 17 00 00 55 00 56 00
  Scala: length = 0x0 (unknown attribute)

