Classfile /Users/mw/Projects/slang-braindump/.jar/jar8/assemble/slang-braindump/assemble/content/scala/collection/Searching$SearchResult.class
  Last modified May 29, 2022; size 474 bytes
  SHA-256 checksum 8792e25e144ab905838746fa5eea085e89cbcc2e6102dcfcde09ee0ae9ced4d0
  Compiled from "Searching.scala"
public abstract class scala.collection.Searching$SearchResult
  minor version: 0
  major version: 52
  flags: (0x0421) ACC_PUBLIC, ACC_SUPER, ACC_ABSTRACT
  this_class: #2                          // scala/collection/Searching$SearchResult
  super_class: #4                         // java/lang/Object
  interfaces: 0, fields: 0, methods: 2, attributes: 4
Constant pool:
   #1 = Utf8               scala/collection/Searching$SearchResult
   #2 = Class              #1             // scala/collection/Searching$SearchResult
   #3 = Utf8               java/lang/Object
   #4 = Class              #3             // java/lang/Object
   #5 = Utf8               Searching.scala
   #6 = Utf8               scala/collection/Searching
   #7 = Class              #6             // scala/collection/Searching
   #8 = Utf8               SearchResult
   #9 = Utf8               insertionPoint
  #10 = Utf8               ()I
  #11 = Utf8               <init>
  #12 = Utf8               ()V
  #13 = NameAndType        #11:#12        // "<init>":()V
  #14 = Methodref          #4.#13         // java/lang/Object."<init>":()V
  #15 = Utf8               this
  #16 = Utf8               Lscala/collection/Searching$SearchResult;
  #17 = Utf8               Code
  #18 = Utf8               LineNumberTable
  #19 = Utf8               LocalVariableTable
  #20 = Utf8               InnerClasses
  #21 = Utf8               SourceFile
  #22 = Utf8               ScalaInlineInfo
  #23 = Utf8               Scala
{
  public abstract int insertionPoint();
    descriptor: ()I
    flags: (0x0401) ACC_PUBLIC, ACC_ABSTRACT

  public scala.collection.Searching$SearchResult();
    descriptor: ()V
    flags: (0x0001) ACC_PUBLIC
    Code:
      stack=1, locals=1, args_size=1
         0: aload_0
         1: invokespecial #14                 // Method java/lang/Object."<init>":()V
         4: return
      LineNumberTable:
        line 31: 0
      LocalVariableTable:
        Start  Length  Slot  Name   Signature
            0       5     0  this   Lscala/collection/Searching$SearchResult;
}
InnerClasses:
  public static abstract #8= #2 of #7;    // SearchResult=class scala/collection/Searching$SearchResult of class scala/collection/Searching
SourceFile: "Searching.scala"
  ScalaInlineInfo: length = 0xE (unknown attribute)
   01 00 00 02 00 0B 00 0C 00 00 09 00 0A 00
  Scala: length = 0x0 (unknown attribute)

