Classfile /Users/mw/Projects/slang-braindump/.jar/jar8/assemble/slang-braindump/assemble/content/scala/collection/SeqOps$$anon$3.class
  Last modified May 29, 2022; size 2060 bytes
  SHA-256 checksum ee2b2e3ca9974c946f4b19ca2434a74ed8725c1e64aa4bf67ac4ac1aab5290c6
  Compiled from "Seq.scala"
public final class scala.collection.SeqOps$$anon$3 extends scala.collection.AbstractIndexedSeqView<B>
  minor version: 0
  major version: 52
  flags: (0x0031) ACC_PUBLIC, ACC_FINAL, ACC_SUPER
  this_class: #2                          // scala/collection/SeqOps$$anon$3
  super_class: #5                         // scala/collection/AbstractIndexedSeqView
  interfaces: 0, fields: 6, methods: 6, attributes: 6
Constant pool:
   #1 = Utf8               scala/collection/SeqOps$$anon$3
   #2 = Class              #1             // scala/collection/SeqOps$$anon$3
   #3 = Utf8               Lscala/collection/AbstractIndexedSeqView<TB;>;
   #4 = Utf8               scala/collection/AbstractIndexedSeqView
   #5 = Class              #4             // scala/collection/AbstractIndexedSeqView
   #6 = Utf8               Seq.scala
   #7 = Utf8               scala/collection/SeqOps$
   #8 = Class              #7             // scala/collection/SeqOps$
   #9 = Utf8               kmpOptimizeWord
  #10 = Utf8               (Lscala/collection/Seq;IIZ)Lscala/collection/IndexedSeqView;
  #11 = NameAndType        #9:#10         // kmpOptimizeWord:(Lscala/collection/Seq;IIZ)Lscala/collection/IndexedSeqView;
  #12 = Utf8               Warr
  #13 = Utf8               [Ljava/lang/Object;
  #14 = Utf8               delta
  #15 = Utf8               I
  #16 = Utf8               done
  #17 = Utf8               wit
  #18 = Utf8               Lscala/collection/Iterator;
  #19 = Utf8               Lscala/collection/Iterator<TB;>;
  #20 = Utf8               i
  #21 = Utf8               length
  #22 = Utf8               ()Lscala/collection/Iterator;
  #23 = Utf8               ()Lscala/collection/Iterator<TB;>;
  #24 = NameAndType        #17:#18        // wit:Lscala/collection/Iterator;
  #25 = Fieldref           #2.#24         // scala/collection/SeqOps$$anon$3.wit:Lscala/collection/Iterator;
  #26 = Utf8               this
  #27 = Utf8               Lscala/collection/SeqOps$$anon$3;
  #28 = Utf8               ()I
  #29 = NameAndType        #20:#15        // i:I
  #30 = Fieldref           #2.#29         // scala/collection/SeqOps$$anon$3.i:I
  #31 = Utf8               i_$eq
  #32 = Utf8               (I)V
  #33 = Utf8               x$1
  #34 = NameAndType        #21:#15        // length:I
  #35 = Fieldref           #2.#34         // scala/collection/SeqOps$$anon$3.length:I
  #36 = Utf8               apply
  #37 = Utf8               (I)Ljava/lang/Object;
  #38 = Utf8               (I)TB;
  #39 = Utf8               x
  #40 = NameAndType        #12:#13        // Warr:[Ljava/lang/Object;
  #41 = Fieldref           #2.#40         // scala/collection/SeqOps$$anon$3.Warr:[Ljava/lang/Object;
  #42 = Utf8               <init>
  #43 = Utf8               (IIZLscala/collection/Seq;)V
  #44 = Utf8               n1$1
  #45 = Utf8               n0$1
  #46 = Utf8               forward$1
  #47 = Utf8               W$1
  #48 = Utf8               ()V
  #49 = NameAndType        #42:#48        // "<init>":()V
  #50 = Methodref          #5.#49         // scala/collection/AbstractIndexedSeqView."<init>":()V
  #51 = Utf8               java/lang/Object
  #52 = Class              #51            // java/lang/Object
  #53 = NameAndType        #14:#15        // delta:I
  #54 = Fieldref           #2.#53         // scala/collection/SeqOps$$anon$3.delta:I
  #55 = NameAndType        #16:#15        // done:I
  #56 = Fieldref           #2.#55         // scala/collection/SeqOps$$anon$3.done:I
  #57 = Utf8               scala/collection/Seq
  #58 = Class              #57            // scala/collection/Seq
  #59 = Utf8               iterator
  #60 = NameAndType        #59:#22        // iterator:()Lscala/collection/Iterator;
  #61 = InterfaceMethodref #58.#60        // scala/collection/Seq.iterator:()Lscala/collection/Iterator;
  #62 = Utf8               scala/collection/Iterator
  #63 = Class              #62            // scala/collection/Iterator
  #64 = Utf8               drop
  #65 = Utf8               (I)Lscala/collection/Iterator;
  #66 = NameAndType        #64:#65        // drop:(I)Lscala/collection/Iterator;
  #67 = InterfaceMethodref #63.#66        // scala/collection/Iterator.drop:(I)Lscala/collection/Iterator;
  #68 = NameAndType        #20:#28        // i:()I
  #69 = Methodref          #2.#68         // scala/collection/SeqOps$$anon$3.i:()I
  #70 = NameAndType        #17:#22        // wit:()Lscala/collection/Iterator;
  #71 = Methodref          #2.#70         // scala/collection/SeqOps$$anon$3.wit:()Lscala/collection/Iterator;
  #72 = Utf8               next
  #73 = Utf8               ()Ljava/lang/Object;
  #74 = NameAndType        #72:#73        // next:()Ljava/lang/Object;
  #75 = InterfaceMethodref #63.#74        // scala/collection/Iterator.next:()Ljava/lang/Object;
  #76 = NameAndType        #31:#32        // i_$eq:(I)V
  #77 = Methodref          #2.#76         // scala/collection/SeqOps$$anon$3.i_$eq:(I)V
  #78 = Utf8               Z
  #79 = Utf8               Lscala/collection/Seq;
  #80 = Utf8               Signature
  #81 = Utf8               Code
  #82 = Utf8               LineNumberTable
  #83 = Utf8               LocalVariableTable
  #84 = Utf8               MethodParameters
  #85 = Utf8               StackMapTable
  #86 = Utf8               InnerClasses
  #87 = Utf8               EnclosingMethod
  #88 = Utf8               SourceFile
  #89 = Utf8               ScalaInlineInfo
  #90 = Utf8               Scala
{
  private final java.lang.Object[] Warr;
    descriptor: [Ljava/lang/Object;
    flags: (0x0012) ACC_PRIVATE, ACC_FINAL

  private final int delta;
    descriptor: I
    flags: (0x0012) ACC_PRIVATE, ACC_FINAL

  private final int done;
    descriptor: I
    flags: (0x0012) ACC_PRIVATE, ACC_FINAL

  private final scala.collection.Iterator<B> wit;
    descriptor: Lscala/collection/Iterator;
    flags: (0x0012) ACC_PRIVATE, ACC_FINAL
    Signature: #19                          // Lscala/collection/Iterator<TB;>;

  private int i;
    descriptor: I
    flags: (0x0002) ACC_PRIVATE

  private final int length;
    descriptor: I
    flags: (0x0012) ACC_PRIVATE, ACC_FINAL

  private scala.collection.Iterator<B> wit();
    descriptor: ()Lscala/collection/Iterator;
    flags: (0x0002) ACC_PRIVATE
    Code:
      stack=1, locals=1, args_size=1
         0: aload_0
         1: getfield      #25                 // Field wit:Lscala/collection/Iterator;
         4: areturn
      LineNumberTable:
        line 1118: 0
      LocalVariableTable:
        Start  Length  Slot  Name   Signature
            0       5     0  this   Lscala/collection/SeqOps$$anon$3;
    Signature: #23                          // ()Lscala/collection/Iterator<TB;>;

  private int i();
    descriptor: ()I
    flags: (0x0002) ACC_PRIVATE
    Code:
      stack=1, locals=1, args_size=1
         0: aload_0
         1: getfield      #30                 // Field i:I
         4: ireturn
      LineNumberTable:
        line 1119: 0
      LocalVariableTable:
        Start  Length  Slot  Name   Signature
            0       5     0  this   Lscala/collection/SeqOps$$anon$3;

  private void i_$eq(int);
    descriptor: (I)V
    flags: (0x0002) ACC_PRIVATE
    Code:
      stack=2, locals=2, args_size=2
         0: aload_0
         1: iload_1
         2: putfield      #30                 // Field i:I
         5: return
      LineNumberTable:
        line 1119: 0
      LocalVariableTable:
        Start  Length  Slot  Name   Signature
            0       6     0  this   Lscala/collection/SeqOps$$anon$3;
            0       6     1   x$1   I
    MethodParameters:
      Name                           Flags
      x$1                            final

  public int length();
    descriptor: ()I
    flags: (0x0001) ACC_PUBLIC
    Code:
      stack=1, locals=1, args_size=1
         0: aload_0
         1: getfield      #35                 // Field length:I
         4: ireturn
      LineNumberTable:
        line 1125: 0
      LocalVariableTable:
        Start  Length  Slot  Name   Signature
            0       5     0  this   Lscala/collection/SeqOps$$anon$3;

  public B apply(int);
    descriptor: (I)Ljava/lang/Object;
    flags: (0x0001) ACC_PUBLIC
    Code:
      stack=2, locals=2, args_size=2
         0: aload_0
         1: getfield      #41                 // Field Warr:[Ljava/lang/Object;
         4: iload_1
         5: aaload
         6: areturn
      LineNumberTable:
        line 1126: 0
      LocalVariableTable:
        Start  Length  Slot  Name   Signature
            0       7     0  this   Lscala/collection/SeqOps$$anon$3;
            0       7     1     x   I
    Signature: #38                          // (I)TB;
    MethodParameters:
      Name                           Flags
      x                              final

  public scala.collection.SeqOps$$anon$3(int, int, boolean, scala.collection.Seq);
    descriptor: (IIZLscala/collection/Seq;)V
    flags: (0x0001) ACC_PUBLIC
    Code:
      stack=3, locals=5, args_size=5
         0: aload_0
         1: invokespecial #50                 // Method scala/collection/AbstractIndexedSeqView."<init>":()V
         4: aload_0
         5: iload_1
         6: iload_2
         7: isub
         8: anewarray     #52                 // class java/lang/Object
        11: putfield      #41                 // Field Warr:[Ljava/lang/Object;
        14: aload_0
        15: iload_3
        16: ifeq          23
        19: iconst_1
        20: goto          24
        23: iconst_m1
        24: putfield      #54                 // Field delta:I
        27: aload_0
        28: iload_3
        29: ifeq          38
        32: iload_1
        33: iload_2
        34: isub
        35: goto          39
        38: iconst_m1
        39: putfield      #56                 // Field done:I
        42: aload_0
        43: aload         4
        45: invokeinterface #61,  1           // InterfaceMethod scala/collection/Seq.iterator:()Lscala/collection/Iterator;
        50: iload_2
        51: invokeinterface #67,  2           // InterfaceMethod scala/collection/Iterator.drop:(I)Lscala/collection/Iterator;
        56: putfield      #25                 // Field wit:Lscala/collection/Iterator;
        59: aload_0
        60: iload_3
        61: ifeq          68
        64: iconst_0
        65: goto          73
        68: iload_1
        69: iload_2
        70: isub
        71: iconst_1
        72: isub
        73: putfield      #30                 // Field i:I
        76: aload_0
        77: invokespecial #69                 // Method i:()I
        80: aload_0
        81: getfield      #56                 // Field done:I
        84: if_icmpeq     121
        87: aload_0
        88: getfield      #41                 // Field Warr:[Ljava/lang/Object;
        91: aload_0
        92: invokespecial #69                 // Method i:()I
        95: aload_0
        96: invokespecial #71                 // Method wit:()Lscala/collection/Iterator;
        99: invokeinterface #75,  1           // InterfaceMethod scala/collection/Iterator.next:()Ljava/lang/Object;
       104: aastore
       105: aload_0
       106: aload_0
       107: invokespecial #69                 // Method i:()I
       110: aload_0
       111: getfield      #54                 // Field delta:I
       114: iadd
       115: invokespecial #77                 // Method i_$eq:(I)V
       118: goto          76
       121: aload_0
       122: iload_1
       123: iload_2
       124: isub
       125: putfield      #35                 // Field length:I
       128: return
      StackMapTable: number_of_entries = 8
        frame_type = 255 /* full_frame */
          offset_delta = 23
          locals = [ class scala/collection/SeqOps$$anon$3, int, int, int, class scala/collection/Seq ]
          stack = [ class scala/collection/SeqOps$$anon$3 ]
        frame_type = 255 /* full_frame */
          offset_delta = 0
          locals = [ class scala/collection/SeqOps$$anon$3, int, int, int, class scala/collection/Seq ]
          stack = [ class scala/collection/SeqOps$$anon$3, int ]
        frame_type = 77 /* same_locals_1_stack_item */
          stack = [ class scala/collection/SeqOps$$anon$3 ]
        frame_type = 255 /* full_frame */
          offset_delta = 0
          locals = [ class scala/collection/SeqOps$$anon$3, int, int, int, class scala/collection/Seq ]
          stack = [ class scala/collection/SeqOps$$anon$3, int ]
        frame_type = 92 /* same_locals_1_stack_item */
          stack = [ class scala/collection/SeqOps$$anon$3 ]
        frame_type = 255 /* full_frame */
          offset_delta = 4
          locals = [ class scala/collection/SeqOps$$anon$3, int, int, int, class scala/collection/Seq ]
          stack = [ class scala/collection/SeqOps$$anon$3, int ]
        frame_type = 2 /* same */
        frame_type = 44 /* same */
      LineNumberTable:
        line 1114: 0
        line 1115: 4
        line 1116: 14
        line 1117: 27
        line 1118: 42
        line 1119: 59
        line 1120: 76
        line 1121: 87
        line 1122: 105
        line 1120: 118
        line 1125: 121
        line 1114: 128
      LocalVariableTable:
        Start  Length  Slot  Name   Signature
            0     129     0  this   Lscala/collection/SeqOps$$anon$3;
            0     129     1  n1$1   I
            0     129     2  n0$1   I
            0     129     3 forward$1   Z
            0     129     4   W$1   Lscala/collection/Seq;
    MethodParameters:
      Name                           Flags
      n1$1                           final
      n0$1                           final
      forward$1                      final
      W$1                            final
}
InnerClasses:
  public final #2;                        // class scala/collection/SeqOps$$anon$3
EnclosingMethod: #8.#11                 // scala.collection.SeqOps$.kmpOptimizeWord
Signature: #3                           // Lscala/collection/AbstractIndexedSeqView<TB;>;
SourceFile: "Seq.scala"
  ScalaInlineInfo: length = 0x22 (unknown attribute)
   01 01 00 06 00 2A 00 2B 01 00 24 00 25 01 00 14
   00 1C 01 00 1F 00 20 01 00 15 00 1C 01 00 11 00
   16 01
  Scala: length = 0x0 (unknown attribute)

