Classfile /Users/mw/Projects/slang-braindump/.jar/jar8/assemble/slang-braindump/assemble/content/scala/collection/SortedSetOps$.class
  Last modified May 29, 2022; size 857 bytes
  SHA-256 checksum dbfcb460f1a3261898b1d56fa7f96a65e210eec4874e45ef1f51e77abd3e04ad
  Compiled from "SortedSet.scala"
public final class scala.collection.SortedSetOps$
  minor version: 0
  major version: 52
  flags: (0x0031) ACC_PUBLIC, ACC_FINAL, ACC_SUPER
  this_class: #2                          // scala/collection/SortedSetOps$
  super_class: #4                         // java/lang/Object
  interfaces: 0, fields: 1, methods: 4, attributes: 3
Constant pool:
   #1 = Utf8               scala/collection/SortedSetOps$
   #2 = Class              #1             // scala/collection/SortedSetOps$
   #3 = Utf8               java/lang/Object
   #4 = Class              #3             // java/lang/Object
   #5 = Utf8               SortedSet.scala
   #6 = Utf8               MODULE$
   #7 = Utf8               Lscala/collection/SortedSetOps$;
   #8 = Utf8               <clinit>
   #9 = Utf8               ()V
  #10 = Utf8               <init>
  #11 = NameAndType        #10:#9         // "<init>":()V
  #12 = Methodref          #2.#11         // scala/collection/SortedSetOps$."<init>":()V
  #13 = NameAndType        #6:#7          // MODULE$:Lscala/collection/SortedSetOps$;
  #14 = Fieldref           #2.#13         // scala/collection/SortedSetOps$.MODULE$:Lscala/collection/SortedSetOps$;
  #15 = Utf8               ordMsg
  #16 = Utf8               ()Ljava/lang/String;
  #17 = Utf8               No implicit Ordering[${B}] found to build a SortedSet[${B}]. You may want to upcast to a Set[${A}] first by calling `unsorted`.
  #18 = String             #17            // No implicit Ordering[${B}] found to build a SortedSet[${B}]. You may want to upcast to a Set[${A}] first by calling `unsorted`.
  #19 = Utf8               this
  #20 = Utf8               zipOrdMsg
  #21 = Utf8               No implicit Ordering[${B}] found to build a SortedSet[(${A}, ${B})]. You may want to upcast to a Set[${A}] first by calling `unsorted`.
  #22 = String             #21            // No implicit Ordering[${B}] found to build a SortedSet[(${A}, ${B})]. You may want to upcast to a Set[${A}] first by calling `unsorted`.
  #23 = Methodref          #4.#11         // java/lang/Object."<init>":()V
  #24 = Utf8               Code
  #25 = Utf8               LineNumberTable
  #26 = Utf8               LocalVariableTable
  #27 = Utf8               SourceFile
  #28 = Utf8               ScalaInlineInfo
  #29 = Utf8               Scala
{
  public static final scala.collection.SortedSetOps$ MODULE$;
    descriptor: Lscala/collection/SortedSetOps$;
    flags: (0x0019) ACC_PUBLIC, ACC_STATIC, ACC_FINAL

  public static {};
    descriptor: ()V
    flags: (0x0009) ACC_PUBLIC, ACC_STATIC
    Code:
      stack=2, locals=0, args_size=0
         0: new           #2                  // class scala/collection/SortedSetOps$
         3: dup
         4: invokespecial #12                 // Method "<init>":()V
         7: putstatic     #14                 // Field MODULE$:Lscala/collection/SortedSetOps$;
        10: return
      LineNumberTable:
        line 162: 0

  public final java.lang.String ordMsg();
    descriptor: ()Ljava/lang/String;
    flags: (0x0011) ACC_PUBLIC, ACC_FINAL
    Code:
      stack=1, locals=1, args_size=1
         0: ldc           #18                 // String No implicit Ordering[${B}] found to build a SortedSet[${B}]. You may want to upcast to a Set[${A}] first by calling `unsorted`.
         2: areturn
      LocalVariableTable:
        Start  Length  Slot  Name   Signature
            0       3     0  this   Lscala/collection/SortedSetOps$;

  public final java.lang.String zipOrdMsg();
    descriptor: ()Ljava/lang/String;
    flags: (0x0011) ACC_PUBLIC, ACC_FINAL
    Code:
      stack=1, locals=1, args_size=1
         0: ldc           #22                 // String No implicit Ordering[${B}] found to build a SortedSet[(${A}, ${B})]. You may want to upcast to a Set[${A}] first by calling `unsorted`.
         2: areturn
      LocalVariableTable:
        Start  Length  Slot  Name   Signature
            0       3     0  this   Lscala/collection/SortedSetOps$;

  private scala.collection.SortedSetOps$();
    descriptor: ()V
    flags: (0x0002) ACC_PRIVATE
    Code:
      stack=1, locals=1, args_size=1
         0: aload_0
         1: invokespecial #23                 // Method java/lang/Object."<init>":()V
         4: return
      LineNumberTable:
        line 162: 0
      LocalVariableTable:
        Start  Length  Slot  Name   Signature
            0       5     0  this   Lscala/collection/SortedSetOps$;
}
SourceFile: "SortedSet.scala"
  ScalaInlineInfo: length = 0x13 (unknown attribute)
   01 01 00 03 00 0A 00 09 01 00 0F 00 10 01 00 14
   00 10 01
  Scala: length = 0x0 (unknown attribute)

