Classfile /Users/mw/Projects/slang-braindump/.jar/jar8/assemble/slang-braindump/assemble/content/scala/collection/SortedSet.class
  Last modified May 29, 2022; size 5590 bytes
  SHA-256 checksum 5480adfd729871e100ac246abf9f1cd977115dde98ac0766ea42551d7c33f289
  Compiled from "SortedSet.scala"
public interface scala.collection.SortedSet<A extends java.lang.Object> extends scala.collection.Set<A>, scala.collection.SortedSetFactoryDefaults<A, scala.collection.SortedSet, scala.collection.Set>
  minor version: 0
  major version: 52
  flags: (0x0601) ACC_PUBLIC, ACC_INTERFACE, ACC_ABSTRACT
  this_class: #2                          // scala/collection/SortedSet
  super_class: #5                         // java/lang/Object
  interfaces: 2, fields: 0, methods: 16, attributes: 6
Constant pool:
    #1 = Utf8               scala/collection/SortedSet
    #2 = Class              #1            // scala/collection/SortedSet
    #3 = Utf8               <A:Ljava/lang/Object;>Ljava/lang/Object;Lscala/collection/Set<TA;>;Lscala/collection/SortedSetFactoryDefaults<TA;Lscala/collection/SortedSet;Lscala/collection/Set;>;
    #4 = Utf8               java/lang/Object
    #5 = Class              #4            // java/lang/Object
    #6 = Utf8               scala/collection/Set
    #7 = Class              #6            // scala/collection/Set
    #8 = Utf8               scala/collection/SortedSetFactoryDefaults
    #9 = Class              #8            // scala/collection/SortedSetFactoryDefaults
   #10 = Utf8               SortedSet.scala
   #11 = Utf8               Lscala/reflect/ScalaSignature;
   #12 = Utf8               bytes
   #13 = Utf8               \u0006\u0005A4qa\u0003\u0007\u0011\u0002\u0007\u0005\u0011\u0003C\u00030\u0001\u0011\u0005\u0001\u0007C\u00035\u0001\u0011\u0005Q\u0007C\u00037\u0001\u0011\u0005q\u0007\u0003\u0004<\u0001\u0001&\t\u0006\u0010\u0005\u0006\u0011\u0002!\t%\u0013\u0005\f\u001f\u0002\u0001\n1!A\u0001\n\u0013\u0001&kB\u0003T\u0019!\u0005AKB\u0003\f\u0019!\u0005Q\u000bC\u0003^\u0011\u0011\u0005a\fC\u0004`\u0011\u0005\u0005I\u0011\u00021\u0003\u0013M{\'\u000f^3e\'\u0016$(BA\u0007\u000f\u0003)\u0019w\u000e\u001c7fGRLwN\u001c\u0006\u0002\u001f\u0005)1oY1mC\u000e\u0001QC\u0001\n\u001e\'\u0015\u00011c\u0006\u0014,!\t!R#D\u0001\u000f\u0013\t1bB\u0001\u0004B]f\u0014VM\u001a\t\u00041eYR\"\u0001\u0007\n\u0005ia!aA*fiB\u0011A$\b\u0007\u0001\t\u0015q\u0002A1\u0001 \u0005\u0005\t\u0015C\u0001\u0011$!\t!\u0012%\u0003\u0002#\u001d\t9aj\u001c;iS:<\u0007C\u0001\u000b%\u0013\t)cBA\u0002B]f\u0004R\u0001G\u0014\u001cS)J!\u0001\u000b\u0007\u0003\u0019M{\'\u000f^3e\'\u0016$x\n]:\u0011\u0005a\u0001\u0001c\u0001\r\u00017A)\u0001\u0004L\u000e*]%\u0011Q\u0006\u0004\u0002\u0019\'>\u0014H/\u001a3TKR4\u0015m\u0019;pef$UMZ1vYR\u001c\bC\u0001\r\u001a\u0003\u0019!\u0013N\\5uIQ\t\u0011\u0007\u0005\u0002\u0015e%\u00111G\u0004\u0002\u0005+:LG/\u0001\u0005v]N|\'\u000f^3e+\u00059\u0012!F:peR,G-\u0013;fe\u0006\u0014G.\u001a$bGR|\'/_\u000b\u0002qA\u0019\u0001$O\u0015\n\u0005ib!!F*peR,G-\u0013;fe\u0006\u0014G.\u001a$bGR|\'/_\u0001\rgR\u0014\u0018N\\4Qe\u00164\u0017\u000e_\u000b\u0002{A\u0011a(\u0012\b\u0003\u007f\r\u0003\"\u0001\u0011\b\u000e\u0003\u0005S!A\u0011\t\u0002\rq\u0012xn\u001c;?\u0013\t!e\"\u0001\u0004Qe\u0016$WMZ\u0005\u0003\r\u001e\u0013aa\u0015;sS:<\'B\u0001#\u000f\u0003\u0019)\u0017/^1mgR\u0011!*\u0014\t\u0003)-K!\u0001\u0014\b\u0003\u000f\t{w\u000e\\3b]\")a*\u0002a\u0001G\u0005!A\u000f[1u\u00031\u0019X\u000f]3sI\u0015\fX/\u00197t)\tQ\u0015\u000bC\u0003O\r\u0001\u00071%\u0003\u0002I3\u0005I1k\u001c:uK\u0012\u001cV\r\u001e\t\u00031!\u0019\"\u0001\u0003,\u0011\u0007]S\u0016F\u0004\u0002\u00191&\u0011\u0011\fD\u0001\u0016\'>\u0014H/\u001a3Ji\u0016\u0014\u0018M\u00197f\r\u0006\u001cGo\u001c:z\u0013\tYFL\u0001\u0005EK2,w-\u0019;f\u0015\tIF\"\u0001\u0004=S:LGO\u0010\u000b\u0002)\u0006aqO]5uKJ+\u0007\u000f\\1dKR\t\u0011\r\u0005\u0002cO6\t1M\u0003\u0002eK\u0006!A.\u00198h\u0015\u00051\u0017\u0001\u00026bm\u0006L!\u0001[2\u0003\r=\u0013\'.Z2uQ\u0011A!.\u001c8\u0011\u0005QY\u0017B\u00017\u000f\u0005A\u0019VM]5bYZ+\'o]5p]VKE)A\u0003wC2,XMH\u0001\u0004Q\u00119!.\u001c8
   #14 = Utf8               scala/collection/View$Fill
   #15 = Class              #14           // scala/collection/View$Fill
   #16 = Utf8               scala/collection/View
   #17 = Class              #16           // scala/collection/View
   #18 = Utf8               Fill
   #19 = Utf8               scala/collection/View$Iterate
   #20 = Class              #19           // scala/collection/View$Iterate
   #21 = Utf8               Iterate
   #22 = Utf8               scala/collection/View$Tabulate
   #23 = Class              #22           // scala/collection/View$Tabulate
   #24 = Utf8               Tabulate
   #25 = Utf8               scala/collection/View$Unfold
   #26 = Class              #25           // scala/collection/View$Unfold
   #27 = Utf8               Unfold
   #28 = Utf8               newBuilder
   #29 = Utf8               (Ljava/lang/Object;)Lscala/collection/mutable/Builder;
   #30 = Utf8               evidence$21
   #31 = Utf8               scala/collection/SortedSet$
   #32 = Class              #31           // scala/collection/SortedSet$
   #33 = Utf8               MODULE$
   #34 = Utf8               Lscala/collection/SortedSet$;
   #35 = NameAndType        #33:#34       // MODULE$:Lscala/collection/SortedSet$;
   #36 = Fieldref           #32.#35       // scala/collection/SortedSet$.MODULE$:Lscala/collection/SortedSet$;
   #37 = NameAndType        #28:#29       // newBuilder:(Ljava/lang/Object;)Lscala/collection/mutable/Builder;
   #38 = Methodref          #32.#37       // scala/collection/SortedSet$.newBuilder:(Ljava/lang/Object;)Lscala/collection/mutable/Builder;
   #39 = Utf8               Ljava/lang/Object;
   #40 = Utf8               evidenceIterableFactory
   #41 = Utf8               (Ljava/lang/Object;)Lscala/collection/Factory;
   #42 = Utf8               evidence$13
   #43 = Utf8               scala/collection/EvidenceIterableFactory
   #44 = Class              #43           // scala/collection/EvidenceIterableFactory
   #45 = Utf8               evidenceIterableFactory$
   #46 = Utf8               (Lscala/collection/EvidenceIterableFactory;Ljava/lang/Object;)Lscala/collection/Factory;
   #47 = NameAndType        #45:#46       // evidenceIterableFactory$:(Lscala/collection/EvidenceIterableFactory;Ljava/lang/Object;)Lscala/collection/Factory;
   #48 = InterfaceMethodref #44.#47       // scala/collection/EvidenceIterableFactory.evidenceIterableFactory$:(Lscala/collection/EvidenceIterableFactory;Ljava/lang/Object;)Lscala/collection/Factory;
   #49 = Utf8               unfold
   #50 = Utf8               (Ljava/lang/Object;Lscala/Function1;Ljava/lang/Object;)Ljava/lang/Object;
   #51 = Utf8               init
   #52 = Utf8               f
   #53 = Utf8               evidence$11
   #54 = Utf8               <init>
   #55 = Utf8               (Ljava/lang/Object;Lscala/Function1;)V
   #56 = NameAndType        #54:#55       // "<init>":(Ljava/lang/Object;Lscala/Function1;)V
   #57 = Methodref          #26.#56       // scala/collection/View$Unfold."<init>":(Ljava/lang/Object;Lscala/Function1;)V
   #58 = Utf8               from
   #59 = Utf8               (Lscala/collection/IterableOnce;Ljava/lang/Object;)Ljava/lang/Object;
   #60 = NameAndType        #58:#59       // from:(Lscala/collection/IterableOnce;Ljava/lang/Object;)Ljava/lang/Object;
   #61 = InterfaceMethodref #44.#60       // scala/collection/EvidenceIterableFactory.from:(Lscala/collection/IterableOnce;Ljava/lang/Object;)Ljava/lang/Object;
   #62 = Utf8               Lscala/Function1;
   #63 = Utf8               iterate
   #64 = Utf8               (Ljava/lang/Object;ILscala/Function1;Ljava/lang/Object;)Ljava/lang/Object;
   #65 = Utf8               start
   #66 = Utf8               len
   #67 = Utf8               evidence$10
   #68 = Utf8               (Ljava/lang/Object;ILscala/Function1;)V
   #69 = NameAndType        #54:#68       // "<init>":(Ljava/lang/Object;ILscala/Function1;)V
   #70 = Methodref          #20.#69       // scala/collection/View$Iterate."<init>":(Ljava/lang/Object;ILscala/Function1;)V
   #71 = Utf8               I
   #72 = Utf8               tabulate
   #73 = Utf8               (ILscala/Function1;Ljava/lang/Object;)Ljava/lang/Object;
   #74 = Utf8               n
   #75 = Utf8               evidence$9
   #76 = Utf8               (ILscala/Function1;)V
   #77 = NameAndType        #54:#76       // "<init>":(ILscala/Function1;)V
   #78 = Methodref          #23.#77       // scala/collection/View$Tabulate."<init>":(ILscala/Function1;)V
   #79 = Utf8               fill
   #80 = Utf8               (ILscala/Function0;Ljava/lang/Object;)Ljava/lang/Object;
   #81 = Utf8               elem
   #82 = Utf8               evidence$8
   #83 = Utf8               (ILscala/Function0;)V
   #84 = NameAndType        #54:#83       // "<init>":(ILscala/Function0;)V
   #85 = Methodref          #15.#84       // scala/collection/View$Fill."<init>":(ILscala/Function0;)V
   #86 = Utf8               Lscala/Function0;
   #87 = Utf8               scala$collection$SortedSet$$super$equals
   #88 = Utf8               (Ljava/lang/Object;)Z
   #89 = Utf8               that
   #90 = Utf8               unsorted$
   #91 = Utf8               (Lscala/collection/SortedSet;)Lscala/collection/Set;
   #92 = Utf8               $this
   #93 = Utf8               unsorted
   #94 = Utf8               ()Lscala/collection/Set;
   #95 = NameAndType        #93:#94       // unsorted:()Lscala/collection/Set;
   #96 = InterfaceMethodref #2.#95        // scala/collection/SortedSet.unsorted:()Lscala/collection/Set;
   #97 = Utf8               Lscala/collection/SortedSet;
   #98 = Utf8               ()Lscala/collection/Set<TA;>;
   #99 = Utf8               this
  #100 = Utf8               sortedIterableFactory$
  #101 = Utf8               (Lscala/collection/SortedSet;)Lscala/collection/SortedIterableFactory;
  #102 = Utf8               sortedIterableFactory
  #103 = Utf8               ()Lscala/collection/SortedIterableFactory;
  #104 = NameAndType        #102:#103     // sortedIterableFactory:()Lscala/collection/SortedIterableFactory;
  #105 = InterfaceMethodref #2.#104       // scala/collection/SortedSet.sortedIterableFactory:()Lscala/collection/SortedIterableFactory;
  #106 = Utf8               ()Lscala/collection/SortedIterableFactory<Lscala/collection/SortedSet;>;
  #107 = Utf8               stringPrefix$
  #108 = Utf8               (Lscala/collection/SortedSet;)Ljava/lang/String;
  #109 = Utf8               stringPrefix
  #110 = Utf8               ()Ljava/lang/String;
  #111 = NameAndType        #109:#110     // stringPrefix:()Ljava/lang/String;
  #112 = InterfaceMethodref #2.#111       // scala/collection/SortedSet.stringPrefix:()Ljava/lang/String;
  #113 = Utf8               SortedSet
  #114 = String             #113          // SortedSet
  #115 = Utf8               equals$
  #116 = Utf8               (Lscala/collection/SortedSet;Ljava/lang/Object;)Z
  #117 = Utf8               equals
  #118 = NameAndType        #117:#88      // equals:(Ljava/lang/Object;)Z
  #119 = InterfaceMethodref #2.#118       // scala/collection/SortedSet.equals:(Ljava/lang/Object;)Z
  #120 = Utf8               ordering
  #121 = Utf8               ()Lscala/math/Ordering;
  #122 = NameAndType        #120:#121     // ordering:()Lscala/math/Ordering;
  #123 = InterfaceMethodref #2.#122       // scala/collection/SortedSet.ordering:()Lscala/math/Ordering;
  #124 = Methodref          #5.#118       // java/lang/Object.equals:(Ljava/lang/Object;)Z
  #125 = Utf8               canEqual
  #126 = NameAndType        #125:#88      // canEqual:(Ljava/lang/Object;)Z
  #127 = InterfaceMethodref #2.#126       // scala/collection/SortedSet.canEqual:(Ljava/lang/Object;)Z
  #128 = Utf8               size
  #129 = Utf8               ()I
  #130 = NameAndType        #128:#129     // size:()I
  #131 = InterfaceMethodref #2.#130       // scala/collection/SortedSet.size:()I
  #132 = Utf8               iterator
  #133 = Utf8               ()Lscala/collection/Iterator;
  #134 = NameAndType        #132:#133     // iterator:()Lscala/collection/Iterator;
  #135 = InterfaceMethodref #2.#134       // scala/collection/SortedSet.iterator:()Lscala/collection/Iterator;
  #136 = Utf8               scala/collection/Iterator
  #137 = Class              #136          // scala/collection/Iterator
  #138 = Utf8               hasNext
  #139 = Utf8               ()Z
  #140 = NameAndType        #138:#139     // hasNext:()Z
  #141 = InterfaceMethodref #137.#140     // scala/collection/Iterator.hasNext:()Z
  #142 = Utf8               next
  #143 = Utf8               ()Ljava/lang/Object;
  #144 = NameAndType        #142:#143     // next:()Ljava/lang/Object;
  #145 = InterfaceMethodref #137.#144     // scala/collection/Iterator.next:()Ljava/lang/Object;
  #146 = Utf8               scala/math/Ordering
  #147 = Class              #146          // scala/math/Ordering
  #148 = Utf8               equiv
  #149 = Utf8               (Ljava/lang/Object;Ljava/lang/Object;)Z
  #150 = NameAndType        #148:#149     // equiv:(Ljava/lang/Object;Ljava/lang/Object;)Z
  #151 = InterfaceMethodref #147.#150     // scala/math/Ordering.equiv:(Ljava/lang/Object;Ljava/lang/Object;)Z
  #152 = NameAndType        #87:#88       // scala$collection$SortedSet$$super$equals:(Ljava/lang/Object;)Z
  #153 = InterfaceMethodref #2.#152       // scala/collection/SortedSet.scala$collection$SortedSet$$super$equals:(Ljava/lang/Object;)Z
  #154 = Utf8               i1
  #155 = Utf8               Lscala/collection/Iterator;
  #156 = Utf8               i2
  #157 = Utf8               allEqual
  #158 = Utf8               Z
  #159 = Utf8               $init$
  #160 = Utf8               (Lscala/collection/SortedSet;)V
  #161 = Utf8               Code
  #162 = Utf8               LocalVariableTable
  #163 = Utf8               MethodParameters
  #164 = Utf8               LineNumberTable
  #165 = Utf8               Signature
  #166 = Utf8               StackMapTable
  #167 = Utf8               InnerClasses
  #168 = Utf8               SourceFile
  #169 = Utf8               RuntimeVisibleAnnotations
  #170 = Utf8               ScalaInlineInfo
  #171 = Utf8               ScalaSig
{
  public static scala.collection.mutable.Builder newBuilder(java.lang.Object);
    descriptor: (Ljava/lang/Object;)Lscala/collection/mutable/Builder;
    flags: (0x0009) ACC_PUBLIC, ACC_STATIC
    Code:
      stack=2, locals=1, args_size=1
         0: getstatic     #36                 // Field scala/collection/SortedSet$.MODULE$:Lscala/collection/SortedSet$;
         3: aload_0
         4: invokevirtual #38                 // Method scala/collection/SortedSet$.newBuilder:(Ljava/lang/Object;)Lscala/collection/mutable/Builder;
         7: areturn
      LocalVariableTable:
        Start  Length  Slot  Name   Signature
            0       8     0 evidence$21   Ljava/lang/Object;
    MethodParameters:
      Name                           Flags
      evidence$21                    final

  public static scala.collection.Factory evidenceIterableFactory(java.lang.Object);
    descriptor: (Ljava/lang/Object;)Lscala/collection/Factory;
    flags: (0x0009) ACC_PUBLIC, ACC_STATIC
    Code:
      stack=2, locals=1, args_size=1
         0: getstatic     #36                 // Field scala/collection/SortedSet$.MODULE$:Lscala/collection/SortedSet$;
         3: aload_0
         4: invokestatic  #48                 // InterfaceMethod scala/collection/EvidenceIterableFactory.evidenceIterableFactory$:(Lscala/collection/EvidenceIterableFactory;Ljava/lang/Object;)Lscala/collection/Factory;
         7: areturn
      LocalVariableTable:
        Start  Length  Slot  Name   Signature
            0       8     0 evidence$13   Ljava/lang/Object;
    MethodParameters:
      Name                           Flags
      evidence$13                    final

  public static java.lang.Object unfold(java.lang.Object, scala.Function1, java.lang.Object);
    descriptor: (Ljava/lang/Object;Lscala/Function1;Ljava/lang/Object;)Ljava/lang/Object;
    flags: (0x0009) ACC_PUBLIC, ACC_STATIC
    Code:
      stack=5, locals=3, args_size=3
         0: getstatic     #36                 // Field scala/collection/SortedSet$.MODULE$:Lscala/collection/SortedSet$;
         3: new           #26                 // class scala/collection/View$Unfold
         6: dup
         7: aload_0
         8: aload_1
         9: invokespecial #57                 // Method scala/collection/View$Unfold."<init>":(Ljava/lang/Object;Lscala/Function1;)V
        12: aload_2
        13: invokeinterface #61,  3           // InterfaceMethod scala/collection/EvidenceIterableFactory.from:(Lscala/collection/IterableOnce;Ljava/lang/Object;)Ljava/lang/Object;
        18: areturn
      LocalVariableTable:
        Start  Length  Slot  Name   Signature
            0      19     0  init   Ljava/lang/Object;
            0      19     1     f   Lscala/Function1;
            0      19     2 evidence$11   Ljava/lang/Object;
    MethodParameters:
      Name                           Flags
      init                           final
      f                              final
      evidence$11                    final

  public static java.lang.Object iterate(java.lang.Object, int, scala.Function1, java.lang.Object);
    descriptor: (Ljava/lang/Object;ILscala/Function1;Ljava/lang/Object;)Ljava/lang/Object;
    flags: (0x0009) ACC_PUBLIC, ACC_STATIC
    Code:
      stack=6, locals=4, args_size=4
         0: getstatic     #36                 // Field scala/collection/SortedSet$.MODULE$:Lscala/collection/SortedSet$;
         3: new           #20                 // class scala/collection/View$Iterate
         6: dup
         7: aload_0
         8: iload_1
         9: aload_2
        10: invokespecial #70                 // Method scala/collection/View$Iterate."<init>":(Ljava/lang/Object;ILscala/Function1;)V
        13: aload_3
        14: invokeinterface #61,  3           // InterfaceMethod scala/collection/EvidenceIterableFactory.from:(Lscala/collection/IterableOnce;Ljava/lang/Object;)Ljava/lang/Object;
        19: areturn
      LocalVariableTable:
        Start  Length  Slot  Name   Signature
            0      20     0 start   Ljava/lang/Object;
            0      20     1   len   I
            0      20     2     f   Lscala/Function1;
            0      20     3 evidence$10   Ljava/lang/Object;
    MethodParameters:
      Name                           Flags
      start                          final
      len                            final
      f                              final
      evidence$10                    final

  public static java.lang.Object tabulate(int, scala.Function1, java.lang.Object);
    descriptor: (ILscala/Function1;Ljava/lang/Object;)Ljava/lang/Object;
    flags: (0x0009) ACC_PUBLIC, ACC_STATIC
    Code:
      stack=5, locals=3, args_size=3
         0: getstatic     #36                 // Field scala/collection/SortedSet$.MODULE$:Lscala/collection/SortedSet$;
         3: new           #23                 // class scala/collection/View$Tabulate
         6: dup
         7: iload_0
         8: aload_1
         9: invokespecial #78                 // Method scala/collection/View$Tabulate."<init>":(ILscala/Function1;)V
        12: aload_2
        13: invokeinterface #61,  3           // InterfaceMethod scala/collection/EvidenceIterableFactory.from:(Lscala/collection/IterableOnce;Ljava/lang/Object;)Ljava/lang/Object;
        18: areturn
      LocalVariableTable:
        Start  Length  Slot  Name   Signature
            0      19     0     n   I
            0      19     1     f   Lscala/Function1;
            0      19     2 evidence$9   Ljava/lang/Object;
    MethodParameters:
      Name                           Flags
      n                              final
      f                              final
      evidence$9                     final

  public static java.lang.Object fill(int, scala.Function0, java.lang.Object);
    descriptor: (ILscala/Function0;Ljava/lang/Object;)Ljava/lang/Object;
    flags: (0x0009) ACC_PUBLIC, ACC_STATIC
    Code:
      stack=5, locals=3, args_size=3
         0: getstatic     #36                 // Field scala/collection/SortedSet$.MODULE$:Lscala/collection/SortedSet$;
         3: new           #15                 // class scala/collection/View$Fill
         6: dup
         7: iload_0
         8: aload_1
         9: invokespecial #85                 // Method scala/collection/View$Fill."<init>":(ILscala/Function0;)V
        12: aload_2
        13: invokeinterface #61,  3           // InterfaceMethod scala/collection/EvidenceIterableFactory.from:(Lscala/collection/IterableOnce;Ljava/lang/Object;)Ljava/lang/Object;
        18: areturn
      LocalVariableTable:
        Start  Length  Slot  Name   Signature
            0      19     0     n   I
            0      19     1  elem   Lscala/Function0;
            0      19     2 evidence$8   Ljava/lang/Object;
    MethodParameters:
      Name                           Flags
      n                              final
      elem                           final
      evidence$8                     final

  public abstract boolean scala$collection$SortedSet$$super$equals(java.lang.Object);
    descriptor: (Ljava/lang/Object;)Z
    flags: (0x1401) ACC_PUBLIC, ACC_ABSTRACT, ACC_SYNTHETIC
    MethodParameters:
      Name                           Flags
      that                           final

  public static scala.collection.Set unsorted$(scala.collection.SortedSet);
    descriptor: (Lscala/collection/SortedSet;)Lscala/collection/Set;
    flags: (0x1009) ACC_PUBLIC, ACC_STATIC, ACC_SYNTHETIC
    Code:
      stack=1, locals=1, args_size=1
         0: aload_0
         1: invokespecial #96                 // InterfaceMethod unsorted:()Lscala/collection/Set;
         4: areturn
      LineNumberTable:
        line 23: 0
      LocalVariableTable:
        Start  Length  Slot  Name   Signature
            0       5     0 $this   Lscala/collection/SortedSet;
    MethodParameters:
      Name                           Flags
      $this                          final synthetic

  public default scala.collection.Set<A> unsorted();
    descriptor: ()Lscala/collection/Set;
    flags: (0x0001) ACC_PUBLIC
    Code:
      stack=1, locals=1, args_size=1
         0: aload_0
         1: areturn
      LineNumberTable:
        line 23: 0
      LocalVariableTable:
        Start  Length  Slot  Name   Signature
            0       2     0  this   Lscala/collection/SortedSet;
    Signature: #98                          // ()Lscala/collection/Set<TA;>;

  public static scala.collection.SortedIterableFactory sortedIterableFactory$(scala.collection.SortedSet);
    descriptor: (Lscala/collection/SortedSet;)Lscala/collection/SortedIterableFactory;
    flags: (0x1009) ACC_PUBLIC, ACC_STATIC, ACC_SYNTHETIC
    Code:
      stack=1, locals=1, args_size=1
         0: aload_0
         1: invokespecial #105                // InterfaceMethod sortedIterableFactory:()Lscala/collection/SortedIterableFactory;
         4: areturn
      LineNumberTable:
        line 25: 0
      LocalVariableTable:
        Start  Length  Slot  Name   Signature
            0       5     0 $this   Lscala/collection/SortedSet;
    MethodParameters:
      Name                           Flags
      $this                          final synthetic

  public default scala.collection.SortedIterableFactory<scala.collection.SortedSet> sortedIterableFactory();
    descriptor: ()Lscala/collection/SortedIterableFactory;
    flags: (0x0001) ACC_PUBLIC
    Code:
      stack=1, locals=1, args_size=1
         0: getstatic     #36                 // Field scala/collection/SortedSet$.MODULE$:Lscala/collection/SortedSet$;
         3: areturn
      LineNumberTable:
        line 25: 0
      LocalVariableTable:
        Start  Length  Slot  Name   Signature
            0       4     0  this   Lscala/collection/SortedSet;
    Signature: #106                         // ()Lscala/collection/SortedIterableFactory<Lscala/collection/SortedSet;>;

  public static java.lang.String stringPrefix$(scala.collection.SortedSet);
    descriptor: (Lscala/collection/SortedSet;)Ljava/lang/String;
    flags: (0x1009) ACC_PUBLIC, ACC_STATIC, ACC_SYNTHETIC
    Code:
      stack=1, locals=1, args_size=1
         0: aload_0
         1: invokespecial #112                // InterfaceMethod stringPrefix:()Ljava/lang/String;
         4: areturn
      LineNumberTable:
        line 28: 0
      LocalVariableTable:
        Start  Length  Slot  Name   Signature
            0       5     0 $this   Lscala/collection/SortedSet;
    MethodParameters:
      Name                           Flags
      $this                          final synthetic

  public default java.lang.String stringPrefix();
    descriptor: ()Ljava/lang/String;
    flags: (0x0001) ACC_PUBLIC
    Code:
      stack=1, locals=1, args_size=1
         0: ldc           #114                // String SortedSet
         2: areturn
      LineNumberTable:
        line 28: 0
      LocalVariableTable:
        Start  Length  Slot  Name   Signature
            0       3     0  this   Lscala/collection/SortedSet;

  public static boolean equals$(scala.collection.SortedSet, java.lang.Object);
    descriptor: (Lscala/collection/SortedSet;Ljava/lang/Object;)Z
    flags: (0x1009) ACC_PUBLIC, ACC_STATIC, ACC_SYNTHETIC
    Code:
      stack=2, locals=2, args_size=2
         0: aload_0
         1: aload_1
         2: invokespecial #119                // InterfaceMethod equals:(Ljava/lang/Object;)Z
         5: ireturn
      LineNumberTable:
        line 30: 0
      LocalVariableTable:
        Start  Length  Slot  Name   Signature
            0       6     0 $this   Lscala/collection/SortedSet;
            0       6     1  that   Ljava/lang/Object;
    MethodParameters:
      Name                           Flags
      $this                          final synthetic
      that                           final

  public default boolean equals(java.lang.Object);
    descriptor: (Ljava/lang/Object;)Z
    flags: (0x0001) ACC_PUBLIC
    Code:
      stack=3, locals=8, args_size=2
         0: aload_0
         1: aload_1
         2: if_acmpne     10
         5: iconst_1
         6: istore_2
         7: goto          168
        10: aload_1
        11: instanceof    #2                  // class scala/collection/SortedSet
        14: ifeq          160
        17: aload_1
        18: checkcast     #2                  // class scala/collection/SortedSet
        21: astore_3
        22: aload_3
        23: invokeinterface #123,  1          // InterfaceMethod ordering:()Lscala/math/Ordering;
        28: aload_0
        29: invokeinterface #123,  1          // InterfaceMethod ordering:()Lscala/math/Ordering;
        34: astore        4
        36: dup
        37: ifnonnull     49
        40: pop
        41: aload         4
        43: ifnull        57
        46: goto          160
        49: aload         4
        51: invokevirtual #124                // Method java/lang/Object.equals:(Ljava/lang/Object;)Z
        54: ifeq          160
        57: aload_3
        58: aload_0
        59: invokeinterface #127,  2          // InterfaceMethod canEqual:(Ljava/lang/Object;)Z
        64: ifeq          155
        67: aload_0
        68: invokeinterface #131,  1          // InterfaceMethod size:()I
        73: aload_3
        74: invokeinterface #131,  1          // InterfaceMethod size:()I
        79: if_icmpne     155
        82: aload_0
        83: invokeinterface #135,  1          // InterfaceMethod iterator:()Lscala/collection/Iterator;
        88: astore        5
        90: aload_3
        91: invokeinterface #135,  1          // InterfaceMethod iterator:()Lscala/collection/Iterator;
        96: astore        6
        98: iconst_1
        99: istore        7
       101: iload         7
       103: ifeq          146
       106: aload         5
       108: invokeinterface #141,  1          // InterfaceMethod scala/collection/Iterator.hasNext:()Z
       113: ifeq          146
       116: aload_0
       117: invokeinterface #123,  1          // InterfaceMethod ordering:()Lscala/math/Ordering;
       122: aload         5
       124: invokeinterface #145,  1          // InterfaceMethod scala/collection/Iterator.next:()Ljava/lang/Object;
       129: aload         6
       131: invokeinterface #145,  1          // InterfaceMethod scala/collection/Iterator.next:()Ljava/lang/Object;
       136: invokeinterface #151,  3          // InterfaceMethod scala/math/Ordering.equiv:(Ljava/lang/Object;Ljava/lang/Object;)Z
       141: istore        7
       143: goto          101
       146: iload         7
       148: ifeq          155
       151: iconst_1
       152: goto          156
       155: iconst_0
       156: istore_2
       157: goto          168
       160: aload_0
       161: aload_1
       162: invokeinterface #153,  2          // InterfaceMethod scala$collection$SortedSet$$super$equals:(Ljava/lang/Object;)Z
       167: istore_2
       168: iload_2
       169: ireturn
      StackMapTable: number_of_entries = 9
        frame_type = 10 /* same */
        frame_type = 255 /* full_frame */
          offset_delta = 38
          locals = [ class scala/collection/SortedSet, class java/lang/Object, top, class scala/collection/SortedSet, class scala/math/Ordering ]
          stack = [ class scala/math/Ordering ]
        frame_type = 7 /* same */
        frame_type = 254 /* append */
          offset_delta = 43
          locals = [ class scala/collection/Iterator, class scala/collection/Iterator, int ]
        frame_type = 44 /* same */
        frame_type = 248 /* chop */
          offset_delta = 8
        frame_type = 64 /* same_locals_1_stack_item */
          stack = [ int ]
        frame_type = 248 /* chop */
          offset_delta = 3
        frame_type = 252 /* append */
          offset_delta = 7
          locals = [ int ]
      LineNumberTable:
        line 31: 0
        line 32: 10
        line 33: 57
        line 34: 67
        line 35: 82
        line 36: 90
        line 37: 98
        line 38: 101
        line 39: 116
        line 40: 146
        line 43: 160
        line 30: 168
      LocalVariableTable:
        Start  Length  Slot  Name   Signature
           90      58     5    i1   Lscala/collection/Iterator;
           98      50     6    i2   Lscala/collection/Iterator;
          101      47     7 allEqual   Z
            0     170     0  this   Lscala/collection/SortedSet;
            0     170     1  that   Ljava/lang/Object;
    MethodParameters:
      Name                           Flags
      that                           final

  public static void $init$(scala.collection.SortedSet);
    descriptor: (Lscala/collection/SortedSet;)V
    flags: (0x0009) ACC_PUBLIC, ACC_STATIC
    Code:
      stack=0, locals=1, args_size=1
         0: return
      LineNumberTable:
        line 19: 0
      LocalVariableTable:
        Start  Length  Slot  Name   Signature
            0       1     0 $this   Lscala/collection/SortedSet;
    MethodParameters:
      Name                           Flags
      $this                          final synthetic
}
InnerClasses:
  public static #18= #15 of #17;          // Fill=class scala/collection/View$Fill of class scala/collection/View
  public static #21= #20 of #17;          // Iterate=class scala/collection/View$Iterate of class scala/collection/View
  public static #24= #23 of #17;          // Tabulate=class scala/collection/View$Tabulate of class scala/collection/View
  public static #27= #26 of #17;          // Unfold=class scala/collection/View$Unfold of class scala/collection/View
Signature: #3                           // <A:Ljava/lang/Object;>Ljava/lang/Object;Lscala/collection/Set<TA;>;Lscala/collection/SortedSetFactoryDefaults<TA;Lscala/collection/SortedSet;Lscala/collection/Set;>;
SourceFile: "SortedSet.scala"
RuntimeVisibleAnnotations:
  0: #11(#12=s#13)
    scala.reflect.ScalaSignature(
      bytes="\u0006\u0005A4qa\u0003\u0007\u0011\u0002\u0007\u0005\u0011\u0003C\u00030\u0001\u0011\u0005\u0001\u0007C\u00035\u0001\u0011\u0005Q\u0007C\u00037\u0001\u0011\u0005q\u0007\u0003\u0004<\u0001\u0001&\t\u0006\u0010\u0005\u0006\u0011\u0002!\t%\u0013\u0005\f\u001f\u0002\u0001\n1!A\u0001\n\u0013\u0001&kB\u0003T\u0019!\u0005AKB\u0003\f\u0019!\u0005Q\u000bC\u0003^\u0011\u0011\u0005a\fC\u0004`\u0011\u0005\u0005I\u0011\u00021\u0003\u0013M{\'\u000f^3e\'\u0016$(BA\u0007\u000f\u0003)\u0019w\u000e\u001c7fGRLwN\u001c\u0006\u0002\u001f\u0005)1oY1mC\u000e\u0001QC\u0001\n\u001e\'\u0015\u00011c\u0006\u0014,!\t!R#D\u0001\u000f\u0013\t1bB\u0001\u0004B]f\u0014VM\u001a\t\u00041eYR\"\u0001\u0007\n\u0005ia!aA*fiB\u0011A$\b\u0007\u0001\t\u0015q\u0002A1\u0001 \u0005\u0005\t\u0015C\u0001\u0011$!\t!\u0012%\u0003\u0002#\u001d\t9aj\u001c;iS:<\u0007C\u0001\u000b%\u0013\t)cBA\u0002B]f\u0004R\u0001G\u0014\u001cS)J!\u0001\u000b\u0007\u0003\u0019M{\'\u000f^3e\'\u0016$x\n]:\u0011\u0005a\u0001\u0001c\u0001\r\u00017A)\u0001\u0004L\u000e*]%\u0011Q\u0006\u0004\u0002\u0019\'>\u0014H/\u001a3TKR4\u0015m\u0019;pef$UMZ1vYR\u001c\bC\u0001\r\u001a\u0003\u0019!\u0013N\\5uIQ\t\u0011\u0007\u0005\u0002\u0015e%\u00111G\u0004\u0002\u0005+:LG/\u0001\u0005v]N|\'\u000f^3e+\u00059\u0012!F:peR,G-\u0013;fe\u0006\u0014G.\u001a$bGR|\'/_\u000b\u0002qA\u0019\u0001$O\u0015\n\u0005ib!!F*peR,G-\u0013;fe\u0006\u0014G.\u001a$bGR|\'/_\u0001\rgR\u0014\u0018N\\4Qe\u00164\u0017\u000e_\u000b\u0002{A\u0011a(\u0012\b\u0003\u007f\r\u0003\"\u0001\u0011\b\u000e\u0003\u0005S!A\u0011\t\u0002\rq\u0012xn\u001c;?\u0013\t!e\"\u0001\u0004Qe\u0016$WMZ\u0005\u0003\r\u001e\u0013aa\u0015;sS:<\'B\u0001#\u000f\u0003\u0019)\u0017/^1mgR\u0011!*\u0014\t\u0003)-K!\u0001\u0014\b\u0003\u000f\t{w\u000e\\3b]\")a*\u0002a\u0001G\u0005!A\u000f[1u\u00031\u0019X\u000f]3sI\u0015\fX/\u00197t)\tQ\u0015\u000bC\u0003O\r\u0001\u00071%\u0003\u0002I3\u0005I1k\u001c:uK\u0012\u001cV\r\u001e\t\u00031!\u0019\"\u0001\u0003,\u0011\u0007]S\u0016F\u0004\u0002\u00191&\u0011\u0011\fD\u0001\u0016\'>\u0014H/\u001a3Ji\u0016\u0014\u0018M\u00197f\r\u0006\u001cGo\u001c:z\u0013\tYFL\u0001\u0005EK2,w-\u0019;f\u0015\tIF\"\u0001\u0004=S:LGO\u0010\u000b\u0002)\u0006aqO]5uKJ+\u0007\u000f\\1dKR\t\u0011\r\u0005\u0002cO6\t1M\u0003\u0002eK\u0006!A.\u00198h\u0015\u00051\u0017\u0001\u00026bm\u0006L!\u0001[2\u0003\r=\u0013\'.Z2uQ\u0011A!.\u001c8\u0011\u0005QY\u0017B\u00017\u000f\u0005A\u0019VM]5bYZ+\'o]5p]VKE)A\u0003wC2,XMH\u0001\u0004Q\u00119!.\u001c8"
    )
  ScalaInlineInfo: length = 0x36 (unknown attribute)
   01 00 00 0A 00 9F 00 A0 01 00 75 00 58 00 00 73
   00 74 01 00 57 00 58 01 00 66 00 67 00 00 64 00
   65 01 00 6D 00 6E 00 00 6B 00 6C 01 00 5D 00 5E
   00 00 5A 00 5B 01
  ScalaSig: length = 0x3 (unknown attribute)
   05 02 00
