Classfile /Users/mw/Projects/slang-braindump/.jar/jar8/assemble/slang-braindump/assemble/content/scala/collection/SortedMapFactory$SortedMapFactoryToBuildFrom.class
  Last modified May 29, 2022; size 2462 bytes
  SHA-256 checksum 9bbbf194efcae4da416d910e7d457a286c58a455bdab3078c81c668395c19297
  Compiled from "Factory.scala"
public class scala.collection.SortedMapFactory$SortedMapFactoryToBuildFrom<K extends java.lang.Object, V extends java.lang.Object, CC extends java.lang.Object> extends java.lang.Object implements scala.collection.BuildFrom<java.lang.Object, scala.Tuple2<K, V>, CC>
  minor version: 0
  major version: 52
  flags: (0x0021) ACC_PUBLIC, ACC_SUPER
  this_class: #2                          // scala/collection/SortedMapFactory$SortedMapFactoryToBuildFrom
  super_class: #5                         // java/lang/Object
  interfaces: 1, fields: 2, methods: 5, attributes: 5
Constant pool:
   #1 = Utf8               scala/collection/SortedMapFactory$SortedMapFactoryToBuildFrom
   #2 = Class              #1             // scala/collection/SortedMapFactory$SortedMapFactoryToBuildFrom
   #3 = Utf8               <K:Ljava/lang/Object;V:Ljava/lang/Object;CC:Ljava/lang/Object;>Ljava/lang/Object;Lscala/collection/BuildFrom<Ljava/lang/Object;Lscala/Tuple2<TK;TV;>;TCC;>;
   #4 = Utf8               java/lang/Object
   #5 = Class              #4             // java/lang/Object
   #6 = Utf8               scala/collection/BuildFrom
   #7 = Class              #6             // scala/collection/BuildFrom
   #8 = Utf8               Factory.scala
   #9 = Utf8               scala/collection/SortedMapFactory
  #10 = Class              #9             // scala/collection/SortedMapFactory
  #11 = Utf8               SortedMapFactoryToBuildFrom
  #12 = Utf8               factory
  #13 = Utf8               Lscala/collection/SortedMapFactory;
  #14 = Utf8               Lscala/collection/SortedMapFactory<TCC;>;
  #15 = Utf8               evidence$44
  #16 = Utf8               Lscala/math/Ordering;
  #17 = Utf8               Lscala/math/Ordering<TK;>;
  #18 = Utf8               apply
  #19 = Utf8               (Ljava/lang/Object;)Lscala/collection/mutable/Builder;
  #20 = Utf8               (Ljava/lang/Object;)Lscala/collection/mutable/Builder<Lscala/Tuple2<TK;TV;>;TCC;>;
  #21 = Utf8               from
  #22 = Utf8               apply$
  #23 = Utf8               (Lscala/collection/BuildFrom;Ljava/lang/Object;)Lscala/collection/mutable/Builder;
  #24 = NameAndType        #22:#23        // apply$:(Lscala/collection/BuildFrom;Ljava/lang/Object;)Lscala/collection/mutable/Builder;
  #25 = InterfaceMethodref #7.#24         // scala/collection/BuildFrom.apply$:(Lscala/collection/BuildFrom;Ljava/lang/Object;)Lscala/collection/mutable/Builder;
  #26 = Utf8               this
  #27 = Utf8               Lscala/collection/SortedMapFactory$SortedMapFactoryToBuildFrom;
  #28 = Utf8               Ljava/lang/Object;
  #29 = Utf8               toFactory
  #30 = Utf8               (Ljava/lang/Object;)Lscala/collection/Factory;
  #31 = Utf8               (Ljava/lang/Object;)Lscala/collection/Factory<Lscala/Tuple2<TK;TV;>;TCC;>;
  #32 = Utf8               toFactory$
  #33 = Utf8               (Lscala/collection/BuildFrom;Ljava/lang/Object;)Lscala/collection/Factory;
  #34 = NameAndType        #32:#33        // toFactory$:(Lscala/collection/BuildFrom;Ljava/lang/Object;)Lscala/collection/Factory;
  #35 = InterfaceMethodref #7.#34         // scala/collection/BuildFrom.toFactory$:(Lscala/collection/BuildFrom;Ljava/lang/Object;)Lscala/collection/Factory;
  #36 = Utf8               fromSpecific
  #37 = Utf8               (Ljava/lang/Object;Lscala/collection/IterableOnce;)Ljava/lang/Object;
  #38 = Utf8               (Ljava/lang/Object;Lscala/collection/IterableOnce<Lscala/Tuple2<TK;TV;>;>;)TCC;
  #39 = Utf8               it
  #40 = NameAndType        #12:#13        // factory:Lscala/collection/SortedMapFactory;
  #41 = Fieldref           #2.#40         // scala/collection/SortedMapFactory$SortedMapFactoryToBuildFrom.factory:Lscala/collection/SortedMapFactory;
  #42 = NameAndType        #15:#16        // evidence$44:Lscala/math/Ordering;
  #43 = Fieldref           #2.#42         // scala/collection/SortedMapFactory$SortedMapFactoryToBuildFrom.evidence$44:Lscala/math/Ordering;
  #44 = Utf8               (Lscala/collection/IterableOnce;Lscala/math/Ordering;)Ljava/lang/Object;
  #45 = NameAndType        #21:#44        // from:(Lscala/collection/IterableOnce;Lscala/math/Ordering;)Ljava/lang/Object;
  #46 = InterfaceMethodref #10.#45        // scala/collection/SortedMapFactory.from:(Lscala/collection/IterableOnce;Lscala/math/Ordering;)Ljava/lang/Object;
  #47 = Utf8               Lscala/collection/IterableOnce;
  #48 = Utf8               newBuilder
  #49 = Utf8               (Lscala/math/Ordering;)Lscala/collection/mutable/Builder;
  #50 = NameAndType        #48:#49        // newBuilder:(Lscala/math/Ordering;)Lscala/collection/mutable/Builder;
  #51 = InterfaceMethodref #10.#50        // scala/collection/SortedMapFactory.newBuilder:(Lscala/math/Ordering;)Lscala/collection/mutable/Builder;
  #52 = Utf8               <init>
  #53 = Utf8               (Lscala/collection/SortedMapFactory;Lscala/math/Ordering;)V
  #54 = Utf8               (Lscala/collection/SortedMapFactory<TCC;>;Lscala/math/Ordering<TK;>;)V
  #55 = Utf8               ()V
  #56 = NameAndType        #52:#55        // "<init>":()V
  #57 = Methodref          #5.#56         // java/lang/Object."<init>":()V
  #58 = Utf8               Signature
  #59 = Utf8               Code
  #60 = Utf8               LineNumberTable
  #61 = Utf8               LocalVariableTable
  #62 = Utf8               Deprecated
  #63 = Utf8               MethodParameters
  #64 = Utf8               InnerClasses
  #65 = Utf8               SourceFile
  #66 = Utf8               ScalaInlineInfo
  #67 = Utf8               Scala
{
  private final scala.collection.SortedMapFactory<CC> factory;
    descriptor: Lscala/collection/SortedMapFactory;
    flags: (0x0012) ACC_PRIVATE, ACC_FINAL
    Signature: #14                          // Lscala/collection/SortedMapFactory<TCC;>;

  private final scala.math.Ordering<K> evidence$44;
    descriptor: Lscala/math/Ordering;
    flags: (0x0012) ACC_PRIVATE, ACC_FINAL
    Signature: #17                          // Lscala/math/Ordering<TK;>;

  public scala.collection.mutable.Builder<scala.Tuple2<K, V>, CC> apply(java.lang.Object);
    descriptor: (Ljava/lang/Object;)Lscala/collection/mutable/Builder;
    flags: (0x0001) ACC_PUBLIC
    Code:
      stack=2, locals=2, args_size=2
         0: aload_0
         1: aload_1
         2: invokestatic  #25                 // InterfaceMethod scala/collection/BuildFrom.apply$:(Lscala/collection/BuildFrom;Ljava/lang/Object;)Lscala/collection/mutable/Builder;
         5: areturn
      LineNumberTable:
        line 772: 0
      LocalVariableTable:
        Start  Length  Slot  Name   Signature
            0       6     0  this   Lscala/collection/SortedMapFactory$SortedMapFactoryToBuildFrom;
            0       6     1  from   Ljava/lang/Object;
    Signature: #20                          // (Ljava/lang/Object;)Lscala/collection/mutable/Builder<Lscala/Tuple2<TK;TV;>;TCC;>;
    Deprecated: true
    MethodParameters:
      Name                           Flags
      from                           final

  public scala.collection.Factory<scala.Tuple2<K, V>, CC> toFactory(java.lang.Object);
    descriptor: (Ljava/lang/Object;)Lscala/collection/Factory;
    flags: (0x0001) ACC_PUBLIC
    Code:
      stack=2, locals=2, args_size=2
         0: aload_0
         1: aload_1
         2: invokestatic  #35                 // InterfaceMethod scala/collection/BuildFrom.toFactory$:(Lscala/collection/BuildFrom;Ljava/lang/Object;)Lscala/collection/Factory;
         5: areturn
      LineNumberTable:
        line 772: 0
      LocalVariableTable:
        Start  Length  Slot  Name   Signature
            0       6     0  this   Lscala/collection/SortedMapFactory$SortedMapFactoryToBuildFrom;
            0       6     1  from   Ljava/lang/Object;
    Signature: #31                          // (Ljava/lang/Object;)Lscala/collection/Factory<Lscala/Tuple2<TK;TV;>;TCC;>;
    MethodParameters:
      Name                           Flags
      from                           final

  public CC fromSpecific(java.lang.Object, scala.collection.IterableOnce<scala.Tuple2<K, V>>);
    descriptor: (Ljava/lang/Object;Lscala/collection/IterableOnce;)Ljava/lang/Object;
    flags: (0x0001) ACC_PUBLIC
    Code:
      stack=3, locals=3, args_size=3
         0: aload_0
         1: getfield      #41                 // Field factory:Lscala/collection/SortedMapFactory;
         4: aload_2
         5: aload_0
         6: getfield      #43                 // Field evidence$44:Lscala/math/Ordering;
         9: invokeinterface #46,  3           // InterfaceMethod scala/collection/SortedMapFactory.from:(Lscala/collection/IterableOnce;Lscala/math/Ordering;)Ljava/lang/Object;
        14: areturn
      LineNumberTable:
        line 773: 0
      LocalVariableTable:
        Start  Length  Slot  Name   Signature
            0      15     0  this   Lscala/collection/SortedMapFactory$SortedMapFactoryToBuildFrom;
            0      15     1  from   Ljava/lang/Object;
            0      15     2    it   Lscala/collection/IterableOnce;
    Signature: #38                          // (Ljava/lang/Object;Lscala/collection/IterableOnce<Lscala/Tuple2<TK;TV;>;>;)TCC;
    MethodParameters:
      Name                           Flags
      from                           final
      it                             final

  public scala.collection.mutable.Builder<scala.Tuple2<K, V>, CC> newBuilder(java.lang.Object);
    descriptor: (Ljava/lang/Object;)Lscala/collection/mutable/Builder;
    flags: (0x0001) ACC_PUBLIC
    Code:
      stack=2, locals=2, args_size=2
         0: aload_0
         1: getfield      #41                 // Field factory:Lscala/collection/SortedMapFactory;
         4: aload_0
         5: getfield      #43                 // Field evidence$44:Lscala/math/Ordering;
         8: invokeinterface #51,  2           // InterfaceMethod scala/collection/SortedMapFactory.newBuilder:(Lscala/math/Ordering;)Lscala/collection/mutable/Builder;
        13: areturn
      LineNumberTable:
        line 774: 0
      LocalVariableTable:
        Start  Length  Slot  Name   Signature
            0      14     0  this   Lscala/collection/SortedMapFactory$SortedMapFactoryToBuildFrom;
            0      14     1  from   Ljava/lang/Object;
    Signature: #20                          // (Ljava/lang/Object;)Lscala/collection/mutable/Builder<Lscala/Tuple2<TK;TV;>;TCC;>;
    MethodParameters:
      Name                           Flags
      from                           final

  public scala.collection.SortedMapFactory$SortedMapFactoryToBuildFrom(scala.collection.SortedMapFactory<CC>, scala.math.Ordering<K>);
    descriptor: (Lscala/collection/SortedMapFactory;Lscala/math/Ordering;)V
    flags: (0x0001) ACC_PUBLIC
    Code:
      stack=2, locals=3, args_size=3
         0: aload_0
         1: aload_1
         2: putfield      #41                 // Field factory:Lscala/collection/SortedMapFactory;
         5: aload_0
         6: aload_2
         7: putfield      #43                 // Field evidence$44:Lscala/math/Ordering;
        10: aload_0
        11: invokespecial #57                 // Method java/lang/Object."<init>":()V
        14: return
      LineNumberTable:
        line 772: 0
      LocalVariableTable:
        Start  Length  Slot  Name   Signature
            0      15     0  this   Lscala/collection/SortedMapFactory$SortedMapFactoryToBuildFrom;
            0      15     1 factory   Lscala/collection/SortedMapFactory;
            0      15     2 evidence$44   Lscala/math/Ordering;
    Signature: #54                          // (Lscala/collection/SortedMapFactory<TCC;>;Lscala/math/Ordering<TK;>;)V
    MethodParameters:
      Name                           Flags
      factory                        final
      evidence$44                    final
}
InnerClasses:
  private static #11= #2 of #10;          // SortedMapFactoryToBuildFrom=class scala/collection/SortedMapFactory$SortedMapFactoryToBuildFrom of class scala/collection/SortedMapFactory
Signature: #3                           // <K:Ljava/lang/Object;V:Ljava/lang/Object;CC:Ljava/lang/Object;>Ljava/lang/Object;Lscala/collection/BuildFrom<Ljava/lang/Object;Lscala/Tuple2<TK;TV;>;TCC;>;
SourceFile: "Factory.scala"
  ScalaInlineInfo: length = 0x1D (unknown attribute)
   01 00 00 05 00 34 00 35 00 00 12 00 13 04 00 24
   00 25 00 00 30 00 13 00 00 1D 00 1E 00
  Scala: length = 0x0 (unknown attribute)

