Classfile /Users/mw/Projects/slang-braindump/.jar/jar8/assemble/slang-braindump/assemble/content/scala/collection/SortedMap.class
  Last modified May 29, 2022; size 4350 bytes
  SHA-256 checksum 7524ad3707d3b0640af10b05d1d81037fc70bc9a3a2a2d3f255a65d249fccf9a
  Compiled from "SortedMap.scala"
public interface scala.collection.SortedMap<K extends java.lang.Object, V extends java.lang.Object> extends scala.collection.Map<K, V>, scala.collection.SortedMapFactoryDefaults<K, V, scala.collection.SortedMap, scala.collection.Iterable, scala.collection.Map>
  minor version: 0
  major version: 52
  flags: (0x0601) ACC_PUBLIC, ACC_INTERFACE, ACC_ABSTRACT
  this_class: #2                          // scala/collection/SortedMap
  super_class: #5                         // java/lang/Object
  interfaces: 2, fields: 0, methods: 11, attributes: 5
Constant pool:
    #1 = Utf8               scala/collection/SortedMap
    #2 = Class              #1            // scala/collection/SortedMap
    #3 = Utf8               <K:Ljava/lang/Object;V:Ljava/lang/Object;>Ljava/lang/Object;Lscala/collection/Map<TK;TV;>;Lscala/collection/SortedMapFactoryDefaults<TK;TV;Lscala/collection/SortedMap;Lscala/collection/Iterable;Lscala/collection/Map;>;
    #4 = Utf8               java/lang/Object
    #5 = Class              #4            // java/lang/Object
    #6 = Utf8               scala/collection/Map
    #7 = Class              #6            // scala/collection/Map
    #8 = Utf8               scala/collection/SortedMapFactoryDefaults
    #9 = Class              #8            // scala/collection/SortedMapFactoryDefaults
   #10 = Utf8               SortedMap.scala
   #11 = Utf8               Lscala/reflect/ScalaSignature;
   #12 = Utf8               bytes
   #13 = Utf8               \u0006\u0005]4qa\u0003\u0007\u0011\u0002\u0007\u0005\u0011\u0003C\u00036\u0001\u0011\u0005a\u0007C\u0003;\u0001\u0011\u00051\bC\u0003=\u0001\u0011\u0005Q\b\u0003\u0004B\u0001\u0001&\tF\u0011\u0005\u0006\u001d\u0002!\te\u0014\u0005\f+\u0002\u0001\n1!A\u0001\n\u00131\u0016lB\u0003[\u0019!\u00051LB\u0003\f\u0019!\u0005A\fC\u0003e\u0011\u0011\u0005Q\rC\u0004g\u0011\u0005\u0005I\u0011B4\u0003\u0013M{\'\u000f^3e\u001b\u0006\u0004(BA\u0007\u000f\u0003)\u0019w\u000e\u001c7fGRLwN\u001c\u0006\u0002\u001f\u0005)1oY1mC\u000e\u0001Qc\u0001\n\u001eOM)\u0001aE\f*]A\u0011A#F\u0007\u0002\u001d%\u0011aC\u0004\u0002\u0007\u0003:L(+\u001a4\u0011\taI2DJ\u0007\u0002\u0019%\u0011!\u0004\u0004\u0002\u0004\u001b\u0006\u0004\bC\u0001\u000f\u001e\u0019\u0001!QA\b\u0001C\u0002}\u0011\u0011aS\t\u0003A\r\u0002\"\u0001F\u0011\n\u0005\tr!a\u0002(pi\"Lgn\u001a\t\u0003)\u0011J!!\n\b\u0003\u0007\u0005s\u0017\u0010\u0005\u0002\u001dO\u00111\u0001\u0006\u0001CC\u0002}\u0011\u0011A\u0016\t\u00071)Zb\u0005L\u0017\n\u0005-b!\u0001D*peR,G-T1q\u001fB\u001c\bC\u0001\r\u0001!\u0011A\u0002a\u0007\u0014\u0011\u000fay3D\n\u00172i%\u0011\u0001\u0007\u0004\u0002\u0019\'>\u0014H/\u001a3NCB4\u0015m\u0019;pef$UMZ1vYR\u001c\bC\u0001\r3\u0013\t\u0019DB\u0001\u0005Ji\u0016\u0014\u0018M\u00197f!\tA\u0012$\u0001\u0004%S:LG\u000f\n\u000b\u0002oA\u0011A\u0003O\u0005\u0003s9\u0011A!\u00168ji\u0006AQO\\:peR,G-F\u0001\u0018\u0003A\u0019xN\u001d;fI6\u000b\u0007OR1di>\u0014\u00180F\u0001?!\rAr\bL\u0005\u0003\u00012\u0011\u0001cU8si\u0016$W*\u00199GC\u000e$xN]=\u0002\u0019M$(/\u001b8h!J,g-\u001b=\u0016\u0003\r\u0003\"\u0001R&\u000f\u0005\u0015K\u0005C\u0001$\u000f\u001b\u00059%B\u0001%\u0011\u0003\u0019a$o\\8u}%\u0011!JD\u0001\u0007!J,G-\u001a4\n\u00051k%AB*ue&twM\u0003\u0002K\u001d\u00051Q-];bYN$\"\u0001U*\u0011\u0005Q\t\u0016B\u0001*\u000f\u0005\u001d\u0011un\u001c7fC:DQ\u0001V\u0003A\u0002\r\nA\u0001\u001e5bi\u0006a1/\u001e9fe\u0012*\u0017/^1mgR\u0011\u0001k\u0016\u0005\u00061\u001a\u0001\raI\u0001\u0002_&\u0011a*G\u0001\n\'>\u0014H/\u001a3NCB\u0004\"\u0001\u0007\u0005\u0014\u0005!i\u0006c\u00010bY9\u0011\u0001dX\u0005\u0003A2\t\u0001cU8si\u0016$W*\u00199GC\u000e$xN]=\n\u0005\t\u001c\'\u0001\u0003#fY\u0016<\u0017\r^3\u000b\u0005\u0001d\u0011A\u0002\u001fj]&$h\bF\u0001\\\u000319(/\u001b;f%\u0016\u0004H.Y2f)\u0005A\u0007CA5o\u001b\u0005Q\'BA6m\u0003\u0011a\u0017M\\4\u000b\u00035\fAA[1wC&\u0011qN\u001b\u0002\u0007\u001f\nTWm\u0019;)\t!\tH/\u001e\t\u0003)IL!a\u001d\b\u0003!M+\'/[1m-\u0016\u00148/[8o+&#\u0015!\u0002<bYV,g$A\u0002)\t\u001d\tH/\u001e
   #14 = Utf8               newBuilder
   #15 = Utf8               (Lscala/math/Ordering;)Lscala/collection/mutable/Builder;
   #16 = Utf8               <K:Ljava/lang/Object;V:Ljava/lang/Object;>(Lscala/math/Ordering<TK;>;)Lscala/collection/mutable/Builder<Lscala/Tuple2<TK;TV;>;Lscala/collection/SortedMap<TK;TV;>;>;
   #17 = Utf8               evidence$48
   #18 = Utf8               scala/collection/SortedMap$
   #19 = Class              #18           // scala/collection/SortedMap$
   #20 = Utf8               MODULE$
   #21 = Utf8               Lscala/collection/SortedMap$;
   #22 = NameAndType        #20:#21       // MODULE$:Lscala/collection/SortedMap$;
   #23 = Fieldref           #19.#22       // scala/collection/SortedMap$.MODULE$:Lscala/collection/SortedMap$;
   #24 = NameAndType        #14:#15       // newBuilder:(Lscala/math/Ordering;)Lscala/collection/mutable/Builder;
   #25 = Methodref          #19.#24       // scala/collection/SortedMap$.newBuilder:(Lscala/math/Ordering;)Lscala/collection/mutable/Builder;
   #26 = Utf8               Lscala/math/Ordering;
   #27 = Utf8               scala$collection$SortedMap$$super$equals
   #28 = Utf8               (Ljava/lang/Object;)Z
   #29 = Utf8               o
   #30 = Utf8               unsorted$
   #31 = Utf8               (Lscala/collection/SortedMap;)Lscala/collection/Map;
   #32 = Utf8               $this
   #33 = Utf8               unsorted
   #34 = Utf8               ()Lscala/collection/Map;
   #35 = NameAndType        #33:#34       // unsorted:()Lscala/collection/Map;
   #36 = InterfaceMethodref #2.#35        // scala/collection/SortedMap.unsorted:()Lscala/collection/Map;
   #37 = Utf8               Lscala/collection/SortedMap;
   #38 = Utf8               ()Lscala/collection/Map<TK;TV;>;
   #39 = Utf8               this
   #40 = Utf8               sortedMapFactory$
   #41 = Utf8               (Lscala/collection/SortedMap;)Lscala/collection/SortedMapFactory;
   #42 = Utf8               sortedMapFactory
   #43 = Utf8               ()Lscala/collection/SortedMapFactory;
   #44 = NameAndType        #42:#43       // sortedMapFactory:()Lscala/collection/SortedMapFactory;
   #45 = InterfaceMethodref #2.#44        // scala/collection/SortedMap.sortedMapFactory:()Lscala/collection/SortedMapFactory;
   #46 = Utf8               ()Lscala/collection/SortedMapFactory<Lscala/collection/SortedMap;>;
   #47 = Utf8               stringPrefix$
   #48 = Utf8               (Lscala/collection/SortedMap;)Ljava/lang/String;
   #49 = Utf8               stringPrefix
   #50 = Utf8               ()Ljava/lang/String;
   #51 = NameAndType        #49:#50       // stringPrefix:()Ljava/lang/String;
   #52 = InterfaceMethodref #2.#51        // scala/collection/SortedMap.stringPrefix:()Ljava/lang/String;
   #53 = Utf8               SortedMap
   #54 = String             #53           // SortedMap
   #55 = Utf8               equals$
   #56 = Utf8               (Lscala/collection/SortedMap;Ljava/lang/Object;)Z
   #57 = Utf8               that
   #58 = Utf8               equals
   #59 = NameAndType        #58:#28       // equals:(Ljava/lang/Object;)Z
   #60 = InterfaceMethodref #2.#59        // scala/collection/SortedMap.equals:(Ljava/lang/Object;)Z
   #61 = Utf8               Ljava/lang/Object;
   #62 = Utf8               ordering
   #63 = Utf8               ()Lscala/math/Ordering;
   #64 = NameAndType        #62:#63       // ordering:()Lscala/math/Ordering;
   #65 = InterfaceMethodref #2.#64        // scala/collection/SortedMap.ordering:()Lscala/math/Ordering;
   #66 = Methodref          #5.#59        // java/lang/Object.equals:(Ljava/lang/Object;)Z
   #67 = Utf8               canEqual
   #68 = NameAndType        #67:#28       // canEqual:(Ljava/lang/Object;)Z
   #69 = InterfaceMethodref #2.#68        // scala/collection/SortedMap.canEqual:(Ljava/lang/Object;)Z
   #70 = Utf8               size
   #71 = Utf8               ()I
   #72 = NameAndType        #70:#71       // size:()I
   #73 = InterfaceMethodref #2.#72        // scala/collection/SortedMap.size:()I
   #74 = Utf8               iterator
   #75 = Utf8               ()Lscala/collection/Iterator;
   #76 = NameAndType        #74:#75       // iterator:()Lscala/collection/Iterator;
   #77 = InterfaceMethodref #2.#76        // scala/collection/SortedMap.iterator:()Lscala/collection/Iterator;
   #78 = Utf8               scala/collection/Iterator
   #79 = Class              #78           // scala/collection/Iterator
   #80 = Utf8               hasNext
   #81 = Utf8               ()Z
   #82 = NameAndType        #80:#81       // hasNext:()Z
   #83 = InterfaceMethodref #79.#82       // scala/collection/Iterator.hasNext:()Z
   #84 = Utf8               next
   #85 = Utf8               ()Ljava/lang/Object;
   #86 = NameAndType        #84:#85       // next:()Ljava/lang/Object;
   #87 = InterfaceMethodref #79.#86       // scala/collection/Iterator.next:()Ljava/lang/Object;
   #88 = Utf8               scala/Tuple2
   #89 = Class              #88           // scala/Tuple2
   #90 = Utf8               _1
   #91 = NameAndType        #90:#85       // _1:()Ljava/lang/Object;
   #92 = Methodref          #89.#91       // scala/Tuple2._1:()Ljava/lang/Object;
   #93 = Utf8               scala/math/Ordering
   #94 = Class              #93           // scala/math/Ordering
   #95 = Utf8               equiv
   #96 = Utf8               (Ljava/lang/Object;Ljava/lang/Object;)Z
   #97 = NameAndType        #95:#96       // equiv:(Ljava/lang/Object;Ljava/lang/Object;)Z
   #98 = InterfaceMethodref #94.#97       // scala/math/Ordering.equiv:(Ljava/lang/Object;Ljava/lang/Object;)Z
   #99 = Utf8               _2
  #100 = NameAndType        #99:#85       // _2:()Ljava/lang/Object;
  #101 = Methodref          #89.#100      // scala/Tuple2._2:()Ljava/lang/Object;
  #102 = Utf8               scala/runtime/BoxesRunTime
  #103 = Class              #102          // scala/runtime/BoxesRunTime
  #104 = NameAndType        #58:#96       // equals:(Ljava/lang/Object;Ljava/lang/Object;)Z
  #105 = Methodref          #103.#104     // scala/runtime/BoxesRunTime.equals:(Ljava/lang/Object;Ljava/lang/Object;)Z
  #106 = NameAndType        #27:#28       // scala$collection$SortedMap$$super$equals:(Ljava/lang/Object;)Z
  #107 = InterfaceMethodref #2.#106       // scala/collection/SortedMap.scala$collection$SortedMap$$super$equals:(Ljava/lang/Object;)Z
  #108 = Utf8               kv1
  #109 = Utf8               Lscala/Tuple2;
  #110 = Utf8               kv2
  #111 = Utf8               i1
  #112 = Utf8               Lscala/collection/Iterator;
  #113 = Utf8               i2
  #114 = Utf8               allEqual
  #115 = Utf8               Z
  #116 = Utf8               $init$
  #117 = Utf8               (Lscala/collection/SortedMap;)V
  #118 = Utf8               Code
  #119 = Utf8               LocalVariableTable
  #120 = Utf8               Signature
  #121 = Utf8               MethodParameters
  #122 = Utf8               LineNumberTable
  #123 = Utf8               StackMapTable
  #124 = Utf8               SourceFile
  #125 = Utf8               RuntimeVisibleAnnotations
  #126 = Utf8               ScalaInlineInfo
  #127 = Utf8               ScalaSig
{
  public static <K extends java.lang.Object, V extends java.lang.Object> scala.collection.mutable.Builder<scala.Tuple2<K, V>, scala.collection.SortedMap<K, V>> newBuilder(scala.math.Ordering<K>);
    descriptor: (Lscala/math/Ordering;)Lscala/collection/mutable/Builder;
    flags: (0x0009) ACC_PUBLIC, ACC_STATIC
    Code:
      stack=2, locals=1, args_size=1
         0: getstatic     #23                 // Field scala/collection/SortedMap$.MODULE$:Lscala/collection/SortedMap$;
         3: aload_0
         4: invokevirtual #25                 // Method scala/collection/SortedMap$.newBuilder:(Lscala/math/Ordering;)Lscala/collection/mutable/Builder;
         7: areturn
      LocalVariableTable:
        Start  Length  Slot  Name   Signature
            0       8     0 evidence$48   Lscala/math/Ordering;
    Signature: #16                          // <K:Ljava/lang/Object;V:Ljava/lang/Object;>(Lscala/math/Ordering<TK;>;)Lscala/collection/mutable/Builder<Lscala/Tuple2<TK;TV;>;Lscala/collection/SortedMap<TK;TV;>;>;
    MethodParameters:
      Name                           Flags
      evidence$48                    final

  public abstract boolean scala$collection$SortedMap$$super$equals(java.lang.Object);
    descriptor: (Ljava/lang/Object;)Z
    flags: (0x1401) ACC_PUBLIC, ACC_ABSTRACT, ACC_SYNTHETIC
    MethodParameters:
      Name                           Flags
      o                              final

  public static scala.collection.Map unsorted$(scala.collection.SortedMap);
    descriptor: (Lscala/collection/SortedMap;)Lscala/collection/Map;
    flags: (0x1009) ACC_PUBLIC, ACC_STATIC, ACC_SYNTHETIC
    Code:
      stack=1, locals=1, args_size=1
         0: aload_0
         1: invokespecial #36                 // InterfaceMethod unsorted:()Lscala/collection/Map;
         4: areturn
      LineNumberTable:
        line 24: 0
      LocalVariableTable:
        Start  Length  Slot  Name   Signature
            0       5     0 $this   Lscala/collection/SortedMap;
    MethodParameters:
      Name                           Flags
      $this                          final synthetic

  public default scala.collection.Map<K, V> unsorted();
    descriptor: ()Lscala/collection/Map;
    flags: (0x0001) ACC_PUBLIC
    Code:
      stack=1, locals=1, args_size=1
         0: aload_0
         1: areturn
      LineNumberTable:
        line 24: 0
      LocalVariableTable:
        Start  Length  Slot  Name   Signature
            0       2     0  this   Lscala/collection/SortedMap;
    Signature: #38                          // ()Lscala/collection/Map<TK;TV;>;

  public static scala.collection.SortedMapFactory sortedMapFactory$(scala.collection.SortedMap);
    descriptor: (Lscala/collection/SortedMap;)Lscala/collection/SortedMapFactory;
    flags: (0x1009) ACC_PUBLIC, ACC_STATIC, ACC_SYNTHETIC
    Code:
      stack=1, locals=1, args_size=1
         0: aload_0
         1: invokespecial #45                 // InterfaceMethod sortedMapFactory:()Lscala/collection/SortedMapFactory;
         4: areturn
      LineNumberTable:
        line 26: 0
      LocalVariableTable:
        Start  Length  Slot  Name   Signature
            0       5     0 $this   Lscala/collection/SortedMap;
    MethodParameters:
      Name                           Flags
      $this                          final synthetic

  public default scala.collection.SortedMapFactory<scala.collection.SortedMap> sortedMapFactory();
    descriptor: ()Lscala/collection/SortedMapFactory;
    flags: (0x0001) ACC_PUBLIC
    Code:
      stack=1, locals=1, args_size=1
         0: getstatic     #23                 // Field scala/collection/SortedMap$.MODULE$:Lscala/collection/SortedMap$;
         3: areturn
      LineNumberTable:
        line 26: 0
      LocalVariableTable:
        Start  Length  Slot  Name   Signature
            0       4     0  this   Lscala/collection/SortedMap;
    Signature: #46                          // ()Lscala/collection/SortedMapFactory<Lscala/collection/SortedMap;>;

  public static java.lang.String stringPrefix$(scala.collection.SortedMap);
    descriptor: (Lscala/collection/SortedMap;)Ljava/lang/String;
    flags: (0x1009) ACC_PUBLIC, ACC_STATIC, ACC_SYNTHETIC
    Code:
      stack=1, locals=1, args_size=1
         0: aload_0
         1: invokespecial #52                 // InterfaceMethod stringPrefix:()Ljava/lang/String;
         4: areturn
      LineNumberTable:
        line 29: 0
      LocalVariableTable:
        Start  Length  Slot  Name   Signature
            0       5     0 $this   Lscala/collection/SortedMap;
    MethodParameters:
      Name                           Flags
      $this                          final synthetic

  public default java.lang.String stringPrefix();
    descriptor: ()Ljava/lang/String;
    flags: (0x0001) ACC_PUBLIC
    Code:
      stack=1, locals=1, args_size=1
         0: ldc           #54                 // String SortedMap
         2: areturn
      LineNumberTable:
        line 29: 0
      LocalVariableTable:
        Start  Length  Slot  Name   Signature
            0       3     0  this   Lscala/collection/SortedMap;

  public static boolean equals$(scala.collection.SortedMap, java.lang.Object);
    descriptor: (Lscala/collection/SortedMap;Ljava/lang/Object;)Z
    flags: (0x1009) ACC_PUBLIC, ACC_STATIC, ACC_SYNTHETIC
    Code:
      stack=2, locals=2, args_size=2
         0: aload_0
         1: aload_1
         2: invokespecial #60                 // InterfaceMethod equals:(Ljava/lang/Object;)Z
         5: ireturn
      LineNumberTable:
        line 31: 0
      LocalVariableTable:
        Start  Length  Slot  Name   Signature
            0       6     0 $this   Lscala/collection/SortedMap;
            0       6     1  that   Ljava/lang/Object;
    MethodParameters:
      Name                           Flags
      $this                          final synthetic
      that                           final

  public default boolean equals(java.lang.Object);
    descriptor: (Ljava/lang/Object;)Z
    flags: (0x0001) ACC_PUBLIC
    Code:
      stack=3, locals=10, args_size=2
         0: aload_0
         1: aload_1
         2: if_acmpne     10
         5: iconst_1
         6: istore_2
         7: goto          212
        10: aload_1
        11: instanceof    #2                  // class scala/collection/SortedMap
        14: ifeq          204
        17: aload_1
        18: checkcast     #2                  // class scala/collection/SortedMap
        21: astore_3
        22: aload_3
        23: invokeinterface #65,  1           // InterfaceMethod ordering:()Lscala/math/Ordering;
        28: aload_0
        29: invokeinterface #65,  1           // InterfaceMethod ordering:()Lscala/math/Ordering;
        34: astore        4
        36: dup
        37: ifnonnull     49
        40: pop
        41: aload         4
        43: ifnull        57
        46: goto          204
        49: aload         4
        51: invokevirtual #66                 // Method java/lang/Object.equals:(Ljava/lang/Object;)Z
        54: ifeq          204
        57: aload_3
        58: aload_0
        59: invokeinterface #69,  2           // InterfaceMethod canEqual:(Ljava/lang/Object;)Z
        64: ifeq          199
        67: aload_0
        68: invokeinterface #73,  1           // InterfaceMethod size:()I
        73: aload_3
        74: invokeinterface #73,  1           // InterfaceMethod size:()I
        79: if_icmpne     199
        82: aload_0
        83: invokeinterface #77,  1           // InterfaceMethod iterator:()Lscala/collection/Iterator;
        88: astore        5
        90: aload_3
        91: invokeinterface #77,  1           // InterfaceMethod iterator:()Lscala/collection/Iterator;
        96: astore        6
        98: iconst_1
        99: istore        7
       101: iload         7
       103: ifeq          190
       106: aload         5
       108: invokeinterface #83,  1           // InterfaceMethod scala/collection/Iterator.hasNext:()Z
       113: ifeq          190
       116: aload         5
       118: invokeinterface #87,  1           // InterfaceMethod scala/collection/Iterator.next:()Ljava/lang/Object;
       123: checkcast     #89                 // class scala/Tuple2
       126: astore        8
       128: aload         6
       130: invokeinterface #87,  1           // InterfaceMethod scala/collection/Iterator.next:()Ljava/lang/Object;
       135: checkcast     #89                 // class scala/Tuple2
       138: astore        9
       140: aload_0
       141: invokeinterface #65,  1           // InterfaceMethod ordering:()Lscala/math/Ordering;
       146: aload         8
       148: invokevirtual #92                 // Method scala/Tuple2._1:()Ljava/lang/Object;
       151: aload         9
       153: invokevirtual #92                 // Method scala/Tuple2._1:()Ljava/lang/Object;
       156: invokeinterface #98,  3           // InterfaceMethod scala/math/Ordering.equiv:(Ljava/lang/Object;Ljava/lang/Object;)Z
       161: ifeq          184
       164: aload         8
       166: invokevirtual #101                // Method scala/Tuple2._2:()Ljava/lang/Object;
       169: aload         9
       171: invokevirtual #101                // Method scala/Tuple2._2:()Ljava/lang/Object;
       174: invokestatic  #105                // Method scala/runtime/BoxesRunTime.equals:(Ljava/lang/Object;Ljava/lang/Object;)Z
       177: ifeq          184
       180: iconst_1
       181: goto          185
       184: iconst_0
       185: istore        7
       187: goto          101
       190: iload         7
       192: ifeq          199
       195: iconst_1
       196: goto          200
       199: iconst_0
       200: istore_2
       201: goto          212
       204: aload_0
       205: aload_1
       206: invokeinterface #107,  2          // InterfaceMethod scala$collection$SortedMap$$super$equals:(Ljava/lang/Object;)Z
       211: istore_2
       212: iload_2
       213: ireturn
      StackMapTable: number_of_entries = 11
        frame_type = 10 /* same */
        frame_type = 255 /* full_frame */
          offset_delta = 38
          locals = [ class scala/collection/SortedMap, class java/lang/Object, top, class scala/collection/SortedMap, class scala/math/Ordering ]
          stack = [ class scala/math/Ordering ]
        frame_type = 7 /* same */
        frame_type = 254 /* append */
          offset_delta = 43
          locals = [ class scala/collection/Iterator, class scala/collection/Iterator, int ]
        frame_type = 253 /* append */
          offset_delta = 82
          locals = [ class scala/Tuple2, class scala/Tuple2 ]
        frame_type = 64 /* same_locals_1_stack_item */
          stack = [ int ]
        frame_type = 249 /* chop */
          offset_delta = 4
        frame_type = 248 /* chop */
          offset_delta = 8
        frame_type = 64 /* same_locals_1_stack_item */
          stack = [ int ]
        frame_type = 248 /* chop */
          offset_delta = 3
        frame_type = 252 /* append */
          offset_delta = 7
          locals = [ int ]
      LineNumberTable:
        line 32: 0
        line 33: 10
        line 34: 57
        line 35: 67
        line 36: 82
        line 37: 90
        line 38: 98
        line 39: 101
        line 40: 116
        line 41: 128
        line 42: 140
        line 39: 187
        line 44: 190
        line 46: 204
        line 31: 212
      LocalVariableTable:
        Start  Length  Slot  Name   Signature
          128      59     8   kv1   Lscala/Tuple2;
          140      47     9   kv2   Lscala/Tuple2;
           90     102     5    i1   Lscala/collection/Iterator;
           98      94     6    i2   Lscala/collection/Iterator;
          101      91     7 allEqual   Z
            0     214     0  this   Lscala/collection/SortedMap;
            0     214     1  that   Ljava/lang/Object;
    MethodParameters:
      Name                           Flags
      that                           final

  public static void $init$(scala.collection.SortedMap);
    descriptor: (Lscala/collection/SortedMap;)V
    flags: (0x0009) ACC_PUBLIC, ACC_STATIC
    Code:
      stack=0, locals=1, args_size=1
         0: return
      LineNumberTable:
        line 20: 0
      LocalVariableTable:
        Start  Length  Slot  Name   Signature
            0       1     0 $this   Lscala/collection/SortedMap;
    MethodParameters:
      Name                           Flags
      $this                          final synthetic
}
Signature: #3                           // <K:Ljava/lang/Object;V:Ljava/lang/Object;>Ljava/lang/Object;Lscala/collection/Map<TK;TV;>;Lscala/collection/SortedMapFactoryDefaults<TK;TV;Lscala/collection/SortedMap;Lscala/collection/Iterable;Lscala/collection/Map;>;
SourceFile: "SortedMap.scala"
RuntimeVisibleAnnotations:
  0: #11(#12=s#13)
    scala.reflect.ScalaSignature(
      bytes="\u0006\u0005]4qa\u0003\u0007\u0011\u0002\u0007\u0005\u0011\u0003C\u00036\u0001\u0011\u0005a\u0007C\u0003;\u0001\u0011\u00051\bC\u0003=\u0001\u0011\u0005Q\b\u0003\u0004B\u0001\u0001&\tF\u0011\u0005\u0006\u001d\u0002!\te\u0014\u0005\f+\u0002\u0001\n1!A\u0001\n\u00131\u0016lB\u0003[\u0019!\u00051LB\u0003\f\u0019!\u0005A\fC\u0003e\u0011\u0011\u0005Q\rC\u0004g\u0011\u0005\u0005I\u0011B4\u0003\u0013M{\'\u000f^3e\u001b\u0006\u0004(BA\u0007\u000f\u0003)\u0019w\u000e\u001c7fGRLwN\u001c\u0006\u0002\u001f\u0005)1oY1mC\u000e\u0001Qc\u0001\n\u001eOM)\u0001aE\f*]A\u0011A#F\u0007\u0002\u001d%\u0011aC\u0004\u0002\u0007\u0003:L(+\u001a4\u0011\taI2DJ\u0007\u0002\u0019%\u0011!\u0004\u0004\u0002\u0004\u001b\u0006\u0004\bC\u0001\u000f\u001e\u0019\u0001!QA\b\u0001C\u0002}\u0011\u0011aS\t\u0003A\r\u0002\"\u0001F\u0011\n\u0005\tr!a\u0002(pi\"Lgn\u001a\t\u0003)\u0011J!!\n\b\u0003\u0007\u0005s\u0017\u0010\u0005\u0002\u001dO\u00111\u0001\u0006\u0001CC\u0002}\u0011\u0011A\u0016\t\u00071)Zb\u0005L\u0017\n\u0005-b!\u0001D*peR,G-T1q\u001fB\u001c\bC\u0001\r\u0001!\u0011A\u0002a\u0007\u0014\u0011\u000fay3D\n\u00172i%\u0011\u0001\u0007\u0004\u0002\u0019\'>\u0014H/\u001a3NCB4\u0015m\u0019;pef$UMZ1vYR\u001c\bC\u0001\r3\u0013\t\u0019DB\u0001\u0005Ji\u0016\u0014\u0018M\u00197f!\tA\u0012$\u0001\u0004%S:LG\u000f\n\u000b\u0002oA\u0011A\u0003O\u0005\u0003s9\u0011A!\u00168ji\u0006AQO\\:peR,G-F\u0001\u0018\u0003A\u0019xN\u001d;fI6\u000b\u0007OR1di>\u0014\u00180F\u0001?!\rAr\bL\u0005\u0003\u00012\u0011\u0001cU8si\u0016$W*\u00199GC\u000e$xN]=\u0002\u0019M$(/\u001b8h!J,g-\u001b=\u0016\u0003\r\u0003\"\u0001R&\u000f\u0005\u0015K\u0005C\u0001$\u000f\u001b\u00059%B\u0001%\u0011\u0003\u0019a$o\\8u}%\u0011!JD\u0001\u0007!J,G-\u001a4\n\u00051k%AB*ue&twM\u0003\u0002K\u001d\u00051Q-];bYN$\"\u0001U*\u0011\u0005Q\t\u0016B\u0001*\u000f\u0005\u001d\u0011un\u001c7fC:DQ\u0001V\u0003A\u0002\r\nA\u0001\u001e5bi\u0006a1/\u001e9fe\u0012*\u0017/^1mgR\u0011\u0001k\u0016\u0005\u00061\u001a\u0001\raI\u0001\u0002_&\u0011a*G\u0001\n\'>\u0014H/\u001a3NCB\u0004\"\u0001\u0007\u0005\u0014\u0005!i\u0006c\u00010bY9\u0011\u0001dX\u0005\u0003A2\t\u0001cU8si\u0016$W*\u00199GC\u000e$xN]=\n\u0005\t\u001c\'\u0001\u0003#fY\u0016<\u0017\r^3\u000b\u0005\u0001d\u0011A\u0002\u001fj]&$h\bF\u0001\\\u000319(/\u001b;f%\u0016\u0004H.Y2f)\u0005A\u0007CA5o\u001b\u0005Q\'BA6m\u0003\u0011a\u0017M\\4\u000b\u00035\fAA[1wC&\u0011qN\u001b\u0002\u0007\u001f\nTWm\u0019;)\t!\tH/\u001e\t\u0003)IL!a\u001d\b\u0003!M+\'/[1m-\u0016\u00148/[8o+&#\u0015!\u0002<bYV,g$A\u0002)\t\u001d\tH/\u001e"
    )
  ScalaInlineInfo: length = 0x36 (unknown attribute)
   01 00 00 0A 00 74 00 75 01 00 3A 00 1C 00 00 37
   00 38 01 00 1B 00 1C 01 00 2A 00 2B 00 00 28 00
   29 01 00 31 00 32 00 00 2F 00 30 01 00 21 00 22
   00 00 1E 00 1F 01
  ScalaSig: length = 0x3 (unknown attribute)
   05 02 00
