Classfile /Users/mw/Projects/slang-braindump/.jar/jar8/assemble/slang-braindump/assemble/content/scala/collection/SortedMapOps$WithFilter.class
  Last modified May 29, 2022; size 4995 bytes
  SHA-256 checksum 9bf36dc8adb6ec2f4327ce73f7dcbbf98f5c98ff5a12685ecf552eae4adb2cfe
  Compiled from "SortedMap.scala"
public class scala.collection.SortedMapOps$WithFilter<K extends java.lang.Object, V extends java.lang.Object, IterableCC extends java.lang.Object, MapCC extends scala.collection.Map<java.lang.Object, java.lang.Object>, CC extends scala.collection.Map<java.lang.Object, java.lang.Object>> extends scala.collection.MapOps$WithFilter<K, V, IterableCC, MapCC>
  minor version: 0
  major version: 52
  flags: (0x0021) ACC_PUBLIC, ACC_SUPER
  this_class: #2                          // scala/collection/SortedMapOps$WithFilter
  super_class: #5                         // scala/collection/MapOps$WithFilter
  interfaces: 0, fields: 2, methods: 10, attributes: 6
Constant pool:
    #1 = Utf8               scala/collection/SortedMapOps$WithFilter
    #2 = Class              #1            // scala/collection/SortedMapOps$WithFilter
    #3 = Utf8               <K:Ljava/lang/Object;V:Ljava/lang/Object;IterableCC:Ljava/lang/Object;MapCC::Lscala/collection/Map<Ljava/lang/Object;Ljava/lang/Object;>;CC:Lscala/collection/Map<Ljava/lang/Object;Ljava/lang/Object;>;>Lscala/collection/MapOps$WithFilter<TK;TV;TIterableCC;TMapCC;>;
    #4 = Utf8               scala/collection/MapOps$WithFilter
    #5 = Class              #4            // scala/collection/MapOps$WithFilter
    #6 = Utf8               SortedMap.scala
    #7 = Utf8               java/lang/invoke/MethodHandles$Lookup
    #8 = Class              #7            // java/lang/invoke/MethodHandles$Lookup
    #9 = Utf8               java/lang/invoke/MethodHandles
   #10 = Class              #9            // java/lang/invoke/MethodHandles
   #11 = Utf8               Lookup
   #12 = Utf8               scala/collection/IterableOps$WithFilter
   #13 = Class              #12           // scala/collection/IterableOps$WithFilter
   #14 = Utf8               scala/collection/IterableOps
   #15 = Class              #14           // scala/collection/IterableOps
   #16 = Utf8               WithFilter
   #17 = Utf8               scala/collection/MapOps
   #18 = Class              #17           // scala/collection/MapOps
   #19 = Utf8               scala/collection/SortedMapOps
   #20 = Class              #19           // scala/collection/SortedMapOps
   #21 = Utf8               scala/collection/View$FlatMap
   #22 = Class              #21           // scala/collection/View$FlatMap
   #23 = Utf8               scala/collection/View
   #24 = Class              #23           // scala/collection/View
   #25 = Utf8               FlatMap
   #26 = Utf8               scala/collection/View$Map
   #27 = Class              #26           // scala/collection/View$Map
   #28 = Utf8               Map
   #29 = Utf8               self
   #30 = Utf8               Lscala/collection/SortedMapOps;
   #31 = Utf8               Lscala/collection/SortedMapOps<TK;TV;TCC;*>;
   #32 = Utf8               p
   #33 = Utf8               Lscala/Function1;
   #34 = Utf8               Lscala/Function1<Lscala/Tuple2<TK;TV;>;Ljava/lang/Object;>;
   #35 = Utf8               map
   #36 = Utf8               (Lscala/Function1;Lscala/math/Ordering;)Lscala/collection/Map;
   #37 = Utf8               <K2:Ljava/lang/Object;V2:Ljava/lang/Object;>(Lscala/Function1<Lscala/Tuple2<TK;TV;>;Lscala/Tuple2<TK2;TV2;>;>;Lscala/math/Ordering<TK2;>;)TCC;
   #38 = Utf8               f
   #39 = Utf8               evidence$1
   #40 = NameAndType        #29:#30       // self:Lscala/collection/SortedMapOps;
   #41 = Fieldref           #2.#40        // scala/collection/SortedMapOps$WithFilter.self:Lscala/collection/SortedMapOps;
   #42 = Utf8               sortedMapFactory
   #43 = Utf8               ()Lscala/collection/SortedMapFactory;
   #44 = NameAndType        #42:#43       // sortedMapFactory:()Lscala/collection/SortedMapFactory;
   #45 = InterfaceMethodref #20.#44       // scala/collection/SortedMapOps.sortedMapFactory:()Lscala/collection/SortedMapFactory;
   #46 = Utf8               filtered
   #47 = Utf8               ()Lscala/collection/Iterable;
   #48 = NameAndType        #46:#47       // filtered:()Lscala/collection/Iterable;
   #49 = Methodref          #2.#48        // scala/collection/SortedMapOps$WithFilter.filtered:()Lscala/collection/Iterable;
   #50 = Utf8               <init>
   #51 = Utf8               (Lscala/collection/IterableOps;Lscala/Function1;)V
   #52 = NameAndType        #50:#51       // "<init>":(Lscala/collection/IterableOps;Lscala/Function1;)V
   #53 = Methodref          #27.#52       // scala/collection/View$Map."<init>":(Lscala/collection/IterableOps;Lscala/Function1;)V
   #54 = Utf8               scala/collection/SortedMapFactory
   #55 = Class              #54           // scala/collection/SortedMapFactory
   #56 = Utf8               from
   #57 = Utf8               (Lscala/collection/IterableOnce;Lscala/math/Ordering;)Ljava/lang/Object;
   #58 = NameAndType        #56:#57       // from:(Lscala/collection/IterableOnce;Lscala/math/Ordering;)Ljava/lang/Object;
   #59 = InterfaceMethodref #55.#58       // scala/collection/SortedMapFactory.from:(Lscala/collection/IterableOnce;Lscala/math/Ordering;)Ljava/lang/Object;
   #60 = Utf8               scala/collection/Map
   #61 = Class              #60           // scala/collection/Map
   #62 = Utf8               this
   #63 = Utf8               Lscala/collection/SortedMapOps$WithFilter;
   #64 = Utf8               Lscala/math/Ordering;
   #65 = Utf8               flatMap
   #66 = Utf8               <K2:Ljava/lang/Object;V2:Ljava/lang/Object;>(Lscala/Function1<Lscala/Tuple2<TK;TV;>;Lscala/collection/IterableOnce<Lscala/Tuple2<TK2;TV2;>;>;>;Lscala/math/Ordering<TK2;>;)TCC;
   #67 = Utf8               evidence$2
   #68 = Methodref          #22.#52       // scala/collection/View$FlatMap."<init>":(Lscala/collection/IterableOps;Lscala/Function1;)V
   #69 = Utf8               withFilter
   #70 = Utf8               (Lscala/Function1;)Lscala/collection/SortedMapOps$WithFilter;
   #71 = Utf8               (Lscala/Function1<Lscala/Tuple2<TK;TV;>;Ljava/lang/Object;>;)Lscala/collection/SortedMapOps$WithFilter<TK;TV;TIterableCC;TMapCC;TCC;>;
   #72 = Utf8               q
   #73 = Utf8               (Ljava/lang/Object;)Ljava/lang/Object;
   #74 = MethodType         #73           //  (Ljava/lang/Object;)Ljava/lang/Object;
   #75 = Utf8               $anonfun$withFilter$1$adapted
   #76 = Utf8               (Lscala/collection/SortedMapOps$WithFilter;Lscala/Function1;Lscala/Tuple2;)Ljava/lang/Object;
   #77 = NameAndType        #75:#76       // $anonfun$withFilter$1$adapted:(Lscala/collection/SortedMapOps$WithFilter;Lscala/Function1;Lscala/Tuple2;)Ljava/lang/Object;
   #78 = Methodref          #2.#77        // scala/collection/SortedMapOps$WithFilter.$anonfun$withFilter$1$adapted:(Lscala/collection/SortedMapOps$WithFilter;Lscala/Function1;Lscala/Tuple2;)Ljava/lang/Object;
   #79 = MethodHandle       6:#78         // REF_invokeStatic scala/collection/SortedMapOps$WithFilter.$anonfun$withFilter$1$adapted:(Lscala/collection/SortedMapOps$WithFilter;Lscala/Function1;Lscala/Tuple2;)Ljava/lang/Object;
   #80 = Utf8               (Lscala/Tuple2;)Ljava/lang/Object;
   #81 = MethodType         #80           //  (Lscala/Tuple2;)Ljava/lang/Object;
   #82 = Integer            5
   #83 = Integer            1
   #84 = Utf8               java/lang/invoke/LambdaMetafactory
   #85 = Class              #84           // java/lang/invoke/LambdaMetafactory
   #86 = Utf8               altMetafactory
   #87 = Utf8               (Ljava/lang/invoke/MethodHandles$Lookup;Ljava/lang/String;Ljava/lang/invoke/MethodType;[Ljava/lang/Object;)Ljava/lang/invoke/CallSite;
   #88 = NameAndType        #86:#87       // altMetafactory:(Ljava/lang/invoke/MethodHandles$Lookup;Ljava/lang/String;Ljava/lang/invoke/MethodType;[Ljava/lang/Object;)Ljava/lang/invoke/CallSite;
   #89 = Methodref          #85.#88       // java/lang/invoke/LambdaMetafactory.altMetafactory:(Ljava/lang/invoke/MethodHandles$Lookup;Ljava/lang/String;Ljava/lang/invoke/MethodType;[Ljava/lang/Object;)Ljava/lang/invoke/CallSite;
   #90 = MethodHandle       6:#89         // REF_invokeStatic java/lang/invoke/LambdaMetafactory.altMetafactory:(Ljava/lang/invoke/MethodHandles$Lookup;Ljava/lang/String;Ljava/lang/invoke/MethodType;[Ljava/lang/Object;)Ljava/lang/invoke/CallSite;
   #91 = Utf8               apply
   #92 = Utf8               (Lscala/collection/SortedMapOps$WithFilter;Lscala/Function1;)Lscala/Function1;
   #93 = NameAndType        #91:#92       // apply:(Lscala/collection/SortedMapOps$WithFilter;Lscala/Function1;)Lscala/Function1;
   #94 = InvokeDynamic      #0:#93        // #0:apply:(Lscala/collection/SortedMapOps$WithFilter;Lscala/Function1;)Lscala/Function1;
   #95 = Utf8               (Lscala/collection/SortedMapOps;Lscala/Function1;)V
   #96 = NameAndType        #50:#95       // "<init>":(Lscala/collection/SortedMapOps;Lscala/Function1;)V
   #97 = Methodref          #2.#96        // scala/collection/SortedMapOps$WithFilter."<init>":(Lscala/collection/SortedMapOps;Lscala/Function1;)V
   #98 = Utf8               (Lscala/Function1;)Lscala/collection/WithFilter;
   #99 = NameAndType        #69:#70       // withFilter:(Lscala/Function1;)Lscala/collection/SortedMapOps$WithFilter;
  #100 = Methodref          #2.#99        // scala/collection/SortedMapOps$WithFilter.withFilter:(Lscala/Function1;)Lscala/collection/SortedMapOps$WithFilter;
  #101 = Utf8               (Lscala/Function1;)Lscala/collection/IterableOps$WithFilter;
  #102 = Utf8               (Lscala/Function1;)Lscala/collection/MapOps$WithFilter;
  #103 = Utf8               $anonfun$withFilter$1
  #104 = Utf8               (Lscala/collection/SortedMapOps$WithFilter;Lscala/Function1;Lscala/Tuple2;)Z
  #105 = Utf8               $this
  #106 = Utf8               q$1
  #107 = Utf8               kv
  #108 = NameAndType        #32:#33       // p:Lscala/Function1;
  #109 = Fieldref           #2.#108       // scala/collection/SortedMapOps$WithFilter.p:Lscala/Function1;
  #110 = Utf8               scala/Function1
  #111 = Class              #110          // scala/Function1
  #112 = NameAndType        #91:#73       // apply:(Ljava/lang/Object;)Ljava/lang/Object;
  #113 = InterfaceMethodref #111.#112     // scala/Function1.apply:(Ljava/lang/Object;)Ljava/lang/Object;
  #114 = Utf8               scala/runtime/BoxesRunTime
  #115 = Class              #114          // scala/runtime/BoxesRunTime
  #116 = Utf8               unboxToBoolean
  #117 = Utf8               (Ljava/lang/Object;)Z
  #118 = NameAndType        #116:#117     // unboxToBoolean:(Ljava/lang/Object;)Z
  #119 = Methodref          #115.#118     // scala/runtime/BoxesRunTime.unboxToBoolean:(Ljava/lang/Object;)Z
  #120 = Utf8               Lscala/Tuple2;
  #121 = Utf8               (Lscala/collection/SortedMapOps<TK;TV;TCC;*>;Lscala/Function1<Lscala/Tuple2<TK;TV;>;Ljava/lang/Object;>;)V
  #122 = Utf8               (Lscala/collection/MapOps;Lscala/Function1;)V
  #123 = NameAndType        #50:#122      // "<init>":(Lscala/collection/MapOps;Lscala/Function1;)V
  #124 = Methodref          #5.#123       // scala/collection/MapOps$WithFilter."<init>":(Lscala/collection/MapOps;Lscala/Function1;)V
  #125 = NameAndType        #103:#104     // $anonfun$withFilter$1:(Lscala/collection/SortedMapOps$WithFilter;Lscala/Function1;Lscala/Tuple2;)Z
  #126 = Methodref          #2.#125       // scala/collection/SortedMapOps$WithFilter.$anonfun$withFilter$1:(Lscala/collection/SortedMapOps$WithFilter;Lscala/Function1;Lscala/Tuple2;)Z
  #127 = Utf8               boxToBoolean
  #128 = Utf8               (Z)Ljava/lang/Boolean;
  #129 = NameAndType        #127:#128     // boxToBoolean:(Z)Ljava/lang/Boolean;
  #130 = Methodref          #115.#129     // scala/runtime/BoxesRunTime.boxToBoolean:(Z)Ljava/lang/Boolean;
  #131 = Utf8               $deserializeLambda$
  #132 = Utf8               (Ljava/lang/invoke/SerializedLambda;)Ljava/lang/Object;
  #133 = Utf8               scala/runtime/LambdaDeserialize
  #134 = Class              #133          // scala/runtime/LambdaDeserialize
  #135 = Utf8               bootstrap
  #136 = Utf8               (Ljava/lang/invoke/MethodHandles$Lookup;Ljava/lang/String;Ljava/lang/invoke/MethodType;[Ljava/lang/invoke/MethodHandle;)Ljava/lang/invoke/CallSite;
  #137 = NameAndType        #135:#136     // bootstrap:(Ljava/lang/invoke/MethodHandles$Lookup;Ljava/lang/String;Ljava/lang/invoke/MethodType;[Ljava/lang/invoke/MethodHandle;)Ljava/lang/invoke/CallSite;
  #138 = Methodref          #134.#137     // scala/runtime/LambdaDeserialize.bootstrap:(Ljava/lang/invoke/MethodHandles$Lookup;Ljava/lang/String;Ljava/lang/invoke/MethodType;[Ljava/lang/invoke/MethodHandle;)Ljava/lang/invoke/CallSite;
  #139 = MethodHandle       6:#138        // REF_invokeStatic scala/runtime/LambdaDeserialize.bootstrap:(Ljava/lang/invoke/MethodHandles$Lookup;Ljava/lang/String;Ljava/lang/invoke/MethodType;[Ljava/lang/invoke/MethodHandle;)Ljava/lang/invoke/CallSite;
  #140 = Utf8               lambdaDeserialize
  #141 = NameAndType        #140:#132     // lambdaDeserialize:(Ljava/lang/invoke/SerializedLambda;)Ljava/lang/Object;
  #142 = InvokeDynamic      #1:#141       // #1:lambdaDeserialize:(Ljava/lang/invoke/SerializedLambda;)Ljava/lang/Object;
  #143 = Utf8               Signature
  #144 = Utf8               Code
  #145 = Utf8               LineNumberTable
  #146 = Utf8               LocalVariableTable
  #147 = Utf8               MethodParameters
  #148 = Utf8               StackMapTable
  #149 = Utf8               InnerClasses
  #150 = Utf8               SourceFile
  #151 = Utf8               BootstrapMethods
  #152 = Utf8               ScalaInlineInfo
  #153 = Utf8               Scala
{
  private final scala.collection.SortedMapOps<K, V, CC, ?> self;
    descriptor: Lscala/collection/SortedMapOps;
    flags: (0x0012) ACC_PRIVATE, ACC_FINAL
    Signature: #31                          // Lscala/collection/SortedMapOps<TK;TV;TCC;*>;

  private final scala.Function1<scala.Tuple2<K, V>, java.lang.Object> p;
    descriptor: Lscala/Function1;
    flags: (0x0012) ACC_PRIVATE, ACC_FINAL
    Signature: #34                          // Lscala/Function1<Lscala/Tuple2<TK;TV;>;Ljava/lang/Object;>;

  public <K2 extends java.lang.Object, V2 extends java.lang.Object> CC map(scala.Function1<scala.Tuple2<K, V>, scala.Tuple2<K2, V2>>, scala.math.Ordering<K2>);
    descriptor: (Lscala/Function1;Lscala/math/Ordering;)Lscala/collection/Map;
    flags: (0x0001) ACC_PUBLIC
    Code:
      stack=5, locals=3, args_size=3
         0: aload_0
         1: getfield      #41                 // Field self:Lscala/collection/SortedMapOps;
         4: invokeinterface #45,  1           // InterfaceMethod scala/collection/SortedMapOps.sortedMapFactory:()Lscala/collection/SortedMapFactory;
         9: new           #27                 // class scala/collection/View$Map
        12: dup
        13: aload_0
        14: invokevirtual #49                 // Method filtered:()Lscala/collection/Iterable;
        17: aload_1
        18: invokespecial #53                 // Method scala/collection/View$Map."<init>":(Lscala/collection/IterableOps;Lscala/Function1;)V
        21: aload_2
        22: invokeinterface #59,  3           // InterfaceMethod scala/collection/SortedMapFactory.from:(Lscala/collection/IterableOnce;Lscala/math/Ordering;)Ljava/lang/Object;
        27: checkcast     #61                 // class scala/collection/Map
        30: areturn
      LineNumberTable:
        line 207: 0
      LocalVariableTable:
        Start  Length  Slot  Name   Signature
            0      31     0  this   Lscala/collection/SortedMapOps$WithFilter;
            0      31     1     f   Lscala/Function1;
            0      31     2 evidence$1   Lscala/math/Ordering;
    Signature: #37                          // <K2:Ljava/lang/Object;V2:Ljava/lang/Object;>(Lscala/Function1<Lscala/Tuple2<TK;TV;>;Lscala/Tuple2<TK2;TV2;>;>;Lscala/math/Ordering<TK2;>;)TCC;
    MethodParameters:
      Name                           Flags
      f                              final
      evidence$1                     final

  public <K2 extends java.lang.Object, V2 extends java.lang.Object> CC flatMap(scala.Function1<scala.Tuple2<K, V>, scala.collection.IterableOnce<scala.Tuple2<K2, V2>>>, scala.math.Ordering<K2>);
    descriptor: (Lscala/Function1;Lscala/math/Ordering;)Lscala/collection/Map;
    flags: (0x0001) ACC_PUBLIC
    Code:
      stack=5, locals=3, args_size=3
         0: aload_0
         1: getfield      #41                 // Field self:Lscala/collection/SortedMapOps;
         4: invokeinterface #45,  1           // InterfaceMethod scala/collection/SortedMapOps.sortedMapFactory:()Lscala/collection/SortedMapFactory;
         9: new           #22                 // class scala/collection/View$FlatMap
        12: dup
        13: aload_0
        14: invokevirtual #49                 // Method filtered:()Lscala/collection/Iterable;
        17: aload_1
        18: invokespecial #68                 // Method scala/collection/View$FlatMap."<init>":(Lscala/collection/IterableOps;Lscala/Function1;)V
        21: aload_2
        22: invokeinterface #59,  3           // InterfaceMethod scala/collection/SortedMapFactory.from:(Lscala/collection/IterableOnce;Lscala/math/Ordering;)Ljava/lang/Object;
        27: checkcast     #61                 // class scala/collection/Map
        30: areturn
      LineNumberTable:
        line 210: 0
      LocalVariableTable:
        Start  Length  Slot  Name   Signature
            0      31     0  this   Lscala/collection/SortedMapOps$WithFilter;
            0      31     1     f   Lscala/Function1;
            0      31     2 evidence$2   Lscala/math/Ordering;
    Signature: #66                          // <K2:Ljava/lang/Object;V2:Ljava/lang/Object;>(Lscala/Function1<Lscala/Tuple2<TK;TV;>;Lscala/collection/IterableOnce<Lscala/Tuple2<TK2;TV2;>;>;>;Lscala/math/Ordering<TK2;>;)TCC;
    MethodParameters:
      Name                           Flags
      f                              final
      evidence$2                     final

  public scala.collection.SortedMapOps$WithFilter<K, V, IterableCC, MapCC, CC> withFilter(scala.Function1<scala.Tuple2<K, V>, java.lang.Object>);
    descriptor: (Lscala/Function1;)Lscala/collection/SortedMapOps$WithFilter;
    flags: (0x0001) ACC_PUBLIC
    Code:
      stack=5, locals=2, args_size=2
         0: new           #2                  // class scala/collection/SortedMapOps$WithFilter
         3: dup
         4: aload_0
         5: getfield      #41                 // Field self:Lscala/collection/SortedMapOps;
         8: aload_0
         9: aload_1
        10: invokedynamic #94,  0             // InvokeDynamic #0:apply:(Lscala/collection/SortedMapOps$WithFilter;Lscala/Function1;)Lscala/Function1;
        15: invokespecial #97                 // Method "<init>":(Lscala/collection/SortedMapOps;Lscala/Function1;)V
        18: areturn
      LineNumberTable:
        line 213: 0
      LocalVariableTable:
        Start  Length  Slot  Name   Signature
            0      19     0  this   Lscala/collection/SortedMapOps$WithFilter;
            0      19     1     q   Lscala/Function1;
    Signature: #71                          // (Lscala/Function1<Lscala/Tuple2<TK;TV;>;Ljava/lang/Object;>;)Lscala/collection/SortedMapOps$WithFilter<TK;TV;TIterableCC;TMapCC;TCC;>;
    MethodParameters:
      Name                           Flags
      q                              final

  public scala.collection.WithFilter withFilter(scala.Function1);
    descriptor: (Lscala/Function1;)Lscala/collection/WithFilter;
    flags: (0x1041) ACC_PUBLIC, ACC_BRIDGE, ACC_SYNTHETIC
    Code:
      stack=2, locals=2, args_size=2
         0: aload_0
         1: aload_1
         2: invokevirtual #100                // Method withFilter:(Lscala/Function1;)Lscala/collection/SortedMapOps$WithFilter;
         5: areturn
      LineNumberTable:
        line 201: 0
      LocalVariableTable:
        Start  Length  Slot  Name   Signature
            0       6     0  this   Lscala/collection/SortedMapOps$WithFilter;
            0       6     1     q   Lscala/Function1;
    MethodParameters:
      Name                           Flags
      q                              final

  public scala.collection.IterableOps$WithFilter withFilter(scala.Function1);
    descriptor: (Lscala/Function1;)Lscala/collection/IterableOps$WithFilter;
    flags: (0x1041) ACC_PUBLIC, ACC_BRIDGE, ACC_SYNTHETIC
    Code:
      stack=2, locals=2, args_size=2
         0: aload_0
         1: aload_1
         2: invokevirtual #100                // Method withFilter:(Lscala/Function1;)Lscala/collection/SortedMapOps$WithFilter;
         5: areturn
      LineNumberTable:
        line 201: 0
      LocalVariableTable:
        Start  Length  Slot  Name   Signature
            0       6     0  this   Lscala/collection/SortedMapOps$WithFilter;
            0       6     1     q   Lscala/Function1;
    MethodParameters:
      Name                           Flags
      q                              final

  public scala.collection.MapOps$WithFilter withFilter(scala.Function1);
    descriptor: (Lscala/Function1;)Lscala/collection/MapOps$WithFilter;
    flags: (0x1041) ACC_PUBLIC, ACC_BRIDGE, ACC_SYNTHETIC
    Code:
      stack=2, locals=2, args_size=2
         0: aload_0
         1: aload_1
         2: invokevirtual #100                // Method withFilter:(Lscala/Function1;)Lscala/collection/SortedMapOps$WithFilter;
         5: areturn
      LineNumberTable:
        line 201: 0
      LocalVariableTable:
        Start  Length  Slot  Name   Signature
            0       6     0  this   Lscala/collection/SortedMapOps$WithFilter;
            0       6     1     q   Lscala/Function1;
    MethodParameters:
      Name                           Flags
      q                              final

  public static final boolean $anonfun$withFilter$1(scala.collection.SortedMapOps$WithFilter, scala.Function1, scala.Tuple2);
    descriptor: (Lscala/collection/SortedMapOps$WithFilter;Lscala/Function1;Lscala/Tuple2;)Z
    flags: (0x1019) ACC_PUBLIC, ACC_STATIC, ACC_FINAL, ACC_SYNTHETIC
    Code:
      stack=2, locals=3, args_size=3
         0: aload_0
         1: getfield      #109                // Field p:Lscala/Function1;
         4: aload_2
         5: invokeinterface #113,  2          // InterfaceMethod scala/Function1.apply:(Ljava/lang/Object;)Ljava/lang/Object;
        10: invokestatic  #119                // Method scala/runtime/BoxesRunTime.unboxToBoolean:(Ljava/lang/Object;)Z
        13: ifeq          31
        16: aload_1
        17: aload_2
        18: invokeinterface #113,  2          // InterfaceMethod scala/Function1.apply:(Ljava/lang/Object;)Ljava/lang/Object;
        23: invokestatic  #119                // Method scala/runtime/BoxesRunTime.unboxToBoolean:(Ljava/lang/Object;)Z
        26: ifeq          31
        29: iconst_1
        30: ireturn
        31: iconst_0
        32: ireturn
      StackMapTable: number_of_entries = 1
        frame_type = 31 /* same */
      LineNumberTable:
        line 213: 0
      LocalVariableTable:
        Start  Length  Slot  Name   Signature
            0      33     0 $this   Lscala/collection/SortedMapOps$WithFilter;
            0      33     1   q$1   Lscala/Function1;
            0      33     2    kv   Lscala/Tuple2;
    MethodParameters:
      Name                           Flags
      $this                          final synthetic
      q$1                            final
      kv                             final

  public scala.collection.SortedMapOps$WithFilter(scala.collection.SortedMapOps<K, V, CC, ?>, scala.Function1<scala.Tuple2<K, V>, java.lang.Object>);
    descriptor: (Lscala/collection/SortedMapOps;Lscala/Function1;)V
    flags: (0x0001) ACC_PUBLIC
    Code:
      stack=3, locals=3, args_size=3
         0: aload_0
         1: aload_1
         2: putfield      #41                 // Field self:Lscala/collection/SortedMapOps;
         5: aload_0
         6: aload_2
         7: putfield      #109                // Field p:Lscala/Function1;
        10: aload_0
        11: aload_1
        12: aload_2
        13: invokespecial #124                // Method scala/collection/MapOps$WithFilter."<init>":(Lscala/collection/MapOps;Lscala/Function1;)V
        16: return
      LineNumberTable:
        line 202: 0
        line 203: 5
        line 204: 10
        line 201: 16
      LocalVariableTable:
        Start  Length  Slot  Name   Signature
            0      17     0  this   Lscala/collection/SortedMapOps$WithFilter;
            0      17     1  self   Lscala/collection/SortedMapOps;
            0      17     2     p   Lscala/Function1;
    Signature: #121                         // (Lscala/collection/SortedMapOps<TK;TV;TCC;*>;Lscala/Function1<Lscala/Tuple2<TK;TV;>;Ljava/lang/Object;>;)V
    MethodParameters:
      Name                           Flags
      self                           final
      p                              final

  public static final java.lang.Object $anonfun$withFilter$1$adapted(scala.collection.SortedMapOps$WithFilter, scala.Function1, scala.Tuple2);
    descriptor: (Lscala/collection/SortedMapOps$WithFilter;Lscala/Function1;Lscala/Tuple2;)Ljava/lang/Object;
    flags: (0x1019) ACC_PUBLIC, ACC_STATIC, ACC_FINAL, ACC_SYNTHETIC
    Code:
      stack=3, locals=3, args_size=3
         0: aload_0
         1: aload_1
         2: aload_2
         3: invokestatic  #126                // Method $anonfun$withFilter$1:(Lscala/collection/SortedMapOps$WithFilter;Lscala/Function1;Lscala/Tuple2;)Z
         6: invokestatic  #130                // Method scala/runtime/BoxesRunTime.boxToBoolean:(Z)Ljava/lang/Boolean;
         9: areturn
      LineNumberTable:
        line 213: 0
      LocalVariableTable:
        Start  Length  Slot  Name   Signature
            0      10     0 $this   Lscala/collection/SortedMapOps$WithFilter;
            0      10     1   q$1   Lscala/Function1;
            0      10     2    kv   Lscala/Tuple2;
    MethodParameters:
      Name                           Flags
      $this                          final
      q$1                            final
      kv                             final

  private static java.lang.Object $deserializeLambda$(java.lang.invoke.SerializedLambda);
    descriptor: (Ljava/lang/invoke/SerializedLambda;)Ljava/lang/Object;
    flags: (0x100a) ACC_PRIVATE, ACC_STATIC, ACC_SYNTHETIC
    Code:
      stack=1, locals=1, args_size=1
         0: aload_0
         1: invokedynamic #142,  0            // InvokeDynamic #1:lambdaDeserialize:(Ljava/lang/invoke/SerializedLambda;)Ljava/lang/Object;
         6: areturn
}
InnerClasses:
  public static final #11= #8 of #10;     // Lookup=class java/lang/invoke/MethodHandles$Lookup of class java/lang/invoke/MethodHandles
  public static #16= #13 of #15;          // WithFilter=class scala/collection/IterableOps$WithFilter of class scala/collection/IterableOps
  public static #16= #5 of #18;           // WithFilter=class scala/collection/MapOps$WithFilter of class scala/collection/MapOps
  public static #16= #2 of #20;           // WithFilter=class scala/collection/SortedMapOps$WithFilter of class scala/collection/SortedMapOps
  public static #25= #22 of #24;          // FlatMap=class scala/collection/View$FlatMap of class scala/collection/View
  public static #28= #27 of #24;          // Map=class scala/collection/View$Map of class scala/collection/View
Signature: #3                           // <K:Ljava/lang/Object;V:Ljava/lang/Object;IterableCC:Ljava/lang/Object;MapCC::Lscala/collection/Map<Ljava/lang/Object;Ljava/lang/Object;>;CC:Lscala/collection/Map<Ljava/lang/Object;Ljava/lang/Object;>;>Lscala/collection/MapOps$WithFilter<TK;TV;TIterableCC;TMapCC;>;
SourceFile: "SortedMap.scala"
BootstrapMethods:
  0: #90 REF_invokeStatic java/lang/invoke/LambdaMetafactory.altMetafactory:(Ljava/lang/invoke/MethodHandles$Lookup;Ljava/lang/String;Ljava/lang/invoke/MethodType;[Ljava/lang/Object;)Ljava/lang/invoke/CallSite;
    Method arguments:
      #74 (Ljava/lang/Object;)Ljava/lang/Object;
      #79 REF_invokeStatic scala/collection/SortedMapOps$WithFilter.$anonfun$withFilter$1$adapted:(Lscala/collection/SortedMapOps$WithFilter;Lscala/Function1;Lscala/Tuple2;)Ljava/lang/Object;
      #81 (Lscala/Tuple2;)Ljava/lang/Object;
      #82 5
      #83 1
      #81 (Lscala/Tuple2;)Ljava/lang/Object;
  1: #139 REF_invokeStatic scala/runtime/LambdaDeserialize.bootstrap:(Ljava/lang/invoke/MethodHandles$Lookup;Ljava/lang/String;Ljava/lang/invoke/MethodType;[Ljava/lang/invoke/MethodHandle;)Ljava/lang/invoke/CallSite;
    Method arguments:
      #79 REF_invokeStatic scala/collection/SortedMapOps$WithFilter.$anonfun$withFilter$1$adapted:(Lscala/collection/SortedMapOps$WithFilter;Lscala/Function1;Lscala/Tuple2;)Ljava/lang/Object;
  ScalaInlineInfo: length = 0x31 (unknown attribute)
   01 00 00 09 00 67 00 68 01 00 4B 00 4C 01 00 32
   00 5F 00 00 41 00 24 00 00 23 00 24 00 00 45 00
   65 00 00 45 00 66 00 00 45 00 46 00 00 45 00 62
   00
  Scala: length = 0x0 (unknown attribute)

