Classfile /Users/mw/Projects/slang-braindump/.jar/jar8/assemble/slang-braindump/assemble/content/scala/collection/Stepper$.class
  Last modified May 29, 2022; size 626 bytes
  SHA-256 checksum 0a40fb320dea7c155ffdf66cf7fc563406a631cf738d21383f7e7f43d87d8b52
  Compiled from "Stepper.scala"
public final class scala.collection.Stepper$
  minor version: 0
  major version: 52
  flags: (0x0031) ACC_PUBLIC, ACC_FINAL, ACC_SUPER
  this_class: #2                          // scala/collection/Stepper$
  super_class: #4                         // java/lang/Object
  interfaces: 0, fields: 1, methods: 3, attributes: 3
Constant pool:
   #1 = Utf8               scala/collection/Stepper$
   #2 = Class              #1             // scala/collection/Stepper$
   #3 = Utf8               java/lang/Object
   #4 = Class              #3             // java/lang/Object
   #5 = Utf8               Stepper.scala
   #6 = Utf8               MODULE$
   #7 = Utf8               Lscala/collection/Stepper$;
   #8 = Utf8               <clinit>
   #9 = Utf8               ()V
  #10 = Utf8               <init>
  #11 = NameAndType        #10:#9         // "<init>":()V
  #12 = Methodref          #2.#11         // scala/collection/Stepper$."<init>":()V
  #13 = NameAndType        #6:#7          // MODULE$:Lscala/collection/Stepper$;
  #14 = Fieldref           #2.#13         // scala/collection/Stepper$.MODULE$:Lscala/collection/Stepper$;
  #15 = Utf8               throwNSEE
  #16 = Utf8               ()Lscala/runtime/Nothing$;
  #17 = Utf8               java/util/NoSuchElementException
  #18 = Class              #17            // java/util/NoSuchElementException
  #19 = Utf8               Empty Stepper
  #20 = String             #19            // Empty Stepper
  #21 = Utf8               (Ljava/lang/String;)V
  #22 = NameAndType        #10:#21        // "<init>":(Ljava/lang/String;)V
  #23 = Methodref          #18.#22        // java/util/NoSuchElementException."<init>":(Ljava/lang/String;)V
  #24 = Utf8               this
  #25 = Methodref          #4.#11         // java/lang/Object."<init>":()V
  #26 = Utf8               Code
  #27 = Utf8               LineNumberTable
  #28 = Utf8               LocalVariableTable
  #29 = Utf8               SourceFile
  #30 = Utf8               ScalaInlineInfo
  #31 = Utf8               Scala
{
  public static final scala.collection.Stepper$ MODULE$;
    descriptor: Lscala/collection/Stepper$;
    flags: (0x0019) ACC_PUBLIC, ACC_STATIC, ACC_FINAL

  public static {};
    descriptor: ()V
    flags: (0x0009) ACC_PUBLIC, ACC_STATIC
    Code:
      stack=2, locals=0, args_size=0
         0: new           #2                  // class scala/collection/Stepper$
         3: dup
         4: invokespecial #12                 // Method "<init>":()V
         7: putstatic     #14                 // Field MODULE$:Lscala/collection/Stepper$;
        10: return
      LineNumberTable:
        line 91: 0

  public final scala.runtime.Nothing$ throwNSEE();
    descriptor: ()Lscala/runtime/Nothing$;
    flags: (0x0011) ACC_PUBLIC, ACC_FINAL
    Code:
      stack=3, locals=1, args_size=1
         0: new           #18                 // class java/util/NoSuchElementException
         3: dup
         4: ldc           #20                 // String Empty Stepper
         6: invokespecial #23                 // Method java/util/NoSuchElementException."<init>":(Ljava/lang/String;)V
         9: athrow
      LineNumberTable:
        line 99: 0
      LocalVariableTable:
        Start  Length  Slot  Name   Signature
            0      10     0  this   Lscala/collection/Stepper$;

  private scala.collection.Stepper$();
    descriptor: ()V
    flags: (0x0002) ACC_PRIVATE
    Code:
      stack=1, locals=1, args_size=1
         0: aload_0
         1: invokespecial #25                 // Method java/lang/Object."<init>":()V
         4: return
      LineNumberTable:
        line 91: 0
      LocalVariableTable:
        Start  Length  Slot  Name   Signature
            0       5     0  this   Lscala/collection/Stepper$;
}
SourceFile: "Stepper.scala"
  ScalaInlineInfo: length = 0xE (unknown attribute)
   01 01 00 02 00 0A 00 09 01 00 0F 00 10 01
  Scala: length = 0x0 (unknown attribute)

