Classfile /Users/mw/Projects/slang-braindump/.jar/jar8/assemble/slang-braindump/assemble/content/scala/collection/StrictOptimizedSortedSetOps.class
  Last modified May 29, 2022; size 7411 bytes
  SHA-256 checksum 3577b70db5f1839a77e3b1cf9bc909c86a438d410f9219c070b70f33bb964573
  Compiled from "StrictOptimizedSortedSetOps.scala"
public interface scala.collection.StrictOptimizedSortedSetOps<A extends java.lang.Object, CC extends scala.collection.SortedSet<java.lang.Object>, C extends scala.collection.SortedSetOps<A, CC, C>> extends scala.collection.SortedSetOps<A, CC, C>, scala.collection.StrictOptimizedSetOps<A, scala.collection.Set, C>
  minor version: 0
  major version: 52
  flags: (0x0601) ACC_PUBLIC, ACC_INTERFACE, ACC_ABSTRACT
  this_class: #2                          // scala/collection/StrictOptimizedSortedSetOps
  super_class: #5                         // java/lang/Object
  interfaces: 2, fields: 0, methods: 10, attributes: 7
Constant pool:
    #1 = Utf8               scala/collection/StrictOptimizedSortedSetOps
    #2 = Class              #1            // scala/collection/StrictOptimizedSortedSetOps
    #3 = Utf8               <A:Ljava/lang/Object;CC::Lscala/collection/SortedSet<Ljava/lang/Object;>;C::Lscala/collection/SortedSetOps<TA;TCC;TC;>;>Ljava/lang/Object;Lscala/collection/SortedSetOps<TA;TCC;TC;>;Lscala/collection/StrictOptimizedSetOps<TA;Lscala/collection/Set;TC;>;
    #4 = Utf8               java/lang/Object
    #5 = Class              #4            // java/lang/Object
    #6 = Utf8               scala/collection/SortedSetOps
    #7 = Class              #6            // scala/collection/SortedSetOps
    #8 = Utf8               scala/collection/StrictOptimizedSetOps
    #9 = Class              #8            // scala/collection/StrictOptimizedSetOps
   #10 = Utf8               StrictOptimizedSortedSetOps.scala
   #11 = Utf8               Lscala/reflect/ScalaSignature;
   #12 = Utf8               bytes
   #13 = Utf8               \u0006\u0005\u0005\u001dba\u0002\u0004\b!\u0003\r\t\u0001\u0004\u0005\u0006m\u0001!\ta\u000e\u0005\u0006w\u0001!\t\u0005\u0010\u0005\u00067\u0002!\t\u0005\u0018\u0005\u0006U\u0002!\te\u001b\u0005\b\u0003\u0013\u0001A\u0011IA\u0006\u0005m\u0019FO]5di>\u0003H/[7ju\u0016$7k\u001c:uK\u0012\u001cV\r^(qg*\u0011\u0001\"C\u0001\u000bG>dG.Z2uS>t\'\"\u0001\u0006\u0002\u000bM\u001c\u0017\r\\1\u0004\u0001U!Q\u0002\u0007\u0012.\'\u0011\u0001aB\u0005\u0019\u0011\u0005=\u0001R\"A\u0005\n\u0005EI!AB!osJ+g\rE\u0003\u0014)Y\tC&D\u0001\b\u0013\t)rA\u0001\u0007T_J$X\rZ*fi>\u00038\u000f\u0005\u0002\u001811\u0001A!B\r\u0001\u0005\u0004Q\"!A!\u0012\u0005mq\u0002CA\b\u001d\u0013\ti\u0012BA\u0004O_RD\u0017N\\4\u0011\u0005=y\u0012B\u0001\u0011\n\u0005\r\te.\u001f\t\u0003/\t\"aa\t\u0001\u0005\u0006\u0004!#AA\"D+\t)#&\u0005\u0002\u001cMA\u00191cJ\u0015\n\u0005!:!!C*peR,GmU3u!\t9\"\u0006B\u0003,E\t\u0007!DA\u0001Y!\t9R\u0006\u0002\u0004/\u0001\u0011\u0015\ra\f\u0002\u0002\u0007F\u00111D\u0005\t\u0006\'E22\u0007L\u0005\u0003e\u001d\u0011Qc\u0015;sS\u000e$x\n\u001d;j[&TX\rZ*fi>\u00038\u000f\u0005\u0002\u0014i%\u0011Qg\u0002\u0002\u0004\'\u0016$\u0018A\u0002\u0013j]&$H\u0005F\u00019!\ty\u0011(\u0003\u0002;\u0013\t!QK\\5u\u0003\ri\u0017\r]\u000b\u0003{\u0005#\"A\u0010,\u0015\u0005}\u001a\u0005cA\f#\u0001B\u0011q#\u0011\u0003\u0006\u0005\n\u0011\rA\u0007\u0002\u0002\u0005\")AI\u0001a\u0002\u000b\u0006\u0011QM\u001e\t\u0004\r&\u0003eBA\bH\u0013\tA\u0015\"A\u0004qC\u000e\\\u0017mZ3\n\u0005)[%\u0001C(sI\u0016\u0014\u0018N\\4\u000b\u0005!K\u0001\u0006B\"N\'R\u0003\"AT)\u000e\u0003=S!\u0001U\u0005\u0002\u0015\u0005tgn\u001c;bi&|g.\u0003\u0002S\u001f\n\u0001\u0012.\u001c9mS\u000eLGOT8u\r>,h\u000eZ\u0001\u0004[N<\u0017%A+\u0002\u007f:{\u0007%[7qY&\u001c\u0017\u000e\u001e\u0011Pe\u0012,\'/\u001b8h7\u0012Z()`/!M>,h\u000e\u001a\u0011u_\u0002\u0012W/\u001b7eA\u0005\u00043k\u001c:uK\u0012\u001cV\r^.%w\nkXL\f\u0011Z_V\u0004S.Y=!o\u0006tG\u000f\t;pAU\u00048-Y:uAQ|\u0007%\u0019\u0011TKR\\Fe_!~;\u00022\u0017N]:uA\tL\beY1mY&tw\r\t1v]N|\'\u000f^3eA:BQa\u0016\u0002A\u0002a\u000b\u0011A\u001a\t\u0005\u001fe3\u0002)\u0003\u0002[\u0013\tIa)\u001e8di&|g.M\u0001\bM2\fG/T1q+\ti\u0016\r\u0006\u0002_KR\u0011qL\u0019\t\u0004/\t\u0002\u0007CA\fb\t\u0015\u00115A1\u0001\u001b\u0011\u0015!5\u0001q\u0001d!\r1\u0015\n\u0019\u0015\u0005E6\u001bF\u000bC\u0003X\u0007\u0001\u0007a\r\u0005\u0003\u00103Z9\u0007cA\niA&\u0011\u0011n\u0002\u0002\r\u0013R,\'/\u00192mK>s7-Z\u0001\u0004u&\u0004XC\u00017|)\ri\u00171\u0001\u000b\u0003]r\u00042a\u0006\u0012p!\u0011y\u0001O\u001d>\n\u0005EL!A\u0002+va2,\'G\u000b\u0002\u0017g.\nA\u000f\u0005\u0002vq6\taO\u0003\u0002x\u001f\u0006IQO\\2iK\u000e\\W\rZ\u0005\u0003sZ\u0014\u0011#\u001e8dQ\u0016\u001c7.\u001a3WCJL\u0017M\\2f!\t92\u0010B\u0003C\t\t\u0007!\u0004C\u0003E\t\u0001\u000fQ\u0010E\u0002G\u0013>DC\u0001`\'T\u007f\u0006\u0012\u0011\u0011A\u0001\u0002\u00109{\u0007%[7qY&\u001c\u0017\u000e\u001e\u0011Pe\u0012,\'/\u001b8h7\u0012Z()`/!M>,h\u000e\u001a\u0011u_\u0002\u0012W/\u001b7eA\u0005\u00043k\u001c:uK\u0012\u001cV\r^.)Im\fU\u0010\f\u0011%w\nk\u0018&\u0018\u0018!3>,\b%\\1zA]\fg\u000e\u001e\u0011u_\u0002*\boY1ti\u0002\"x\u000eI1!\'\u0016$8\fJ>B{v\u0003c-\u001b:ti\u0002\u0012\u0017\u0010I2bY2Lgn\u001a\u0011ak:\u001cxN\u001d;fI\u0002t\u0003bBA\u0003\t\u0001\u0007\u0011qA\u0001\u0005i\"\fG\u000fE\u0002\u0014Qj\fqaY8mY\u0016\u001cG/\u0006\u0003\u0002\u000e\u0005UA\u0003BA\b\u0003;!B!!\u0005\u0002\u0018A!qCIA\n!\r9\u0012Q\u0003\u0003\u0006\u0005\u0016\u0011\rA\u0007\u0005\u0007\t\u0016\u0001\u001d!!\u0007\u0011\t\u0019K\u00151\u0003\u0015\u0006\u0003/i5\u000b\u0016\u0005\b\u0003?)\u0001\u0019AA\u0011\u0003\t\u0001h\r\u0005\u0004\u0010\u0003G1\u00121C\u0005\u0004\u0003KI!a\u0004)beRL\u0017\r\u001c$v]\u000e$\u0018n\u001c8
   #14 = Utf8               java/lang/invoke/MethodHandles$Lookup
   #15 = Class              #14           // java/lang/invoke/MethodHandles$Lookup
   #16 = Utf8               java/lang/invoke/MethodHandles
   #17 = Class              #16           // java/lang/invoke/MethodHandles
   #18 = Utf8               Lookup
   #19 = Utf8               map$
   #20 = Utf8               (Lscala/collection/StrictOptimizedSortedSetOps;Lscala/Function1;Lscala/math/Ordering;)Lscala/collection/SortedSet;
   #21 = Utf8               $this
   #22 = Utf8               f
   #23 = Utf8               ev
   #24 = Utf8               map
   #25 = Utf8               (Lscala/Function1;Lscala/math/Ordering;)Lscala/collection/SortedSet;
   #26 = NameAndType        #24:#25       // map:(Lscala/Function1;Lscala/math/Ordering;)Lscala/collection/SortedSet;
   #27 = InterfaceMethodref #2.#26        // scala/collection/StrictOptimizedSortedSetOps.map:(Lscala/Function1;Lscala/math/Ordering;)Lscala/collection/SortedSet;
   #28 = Utf8               Lscala/collection/StrictOptimizedSortedSetOps;
   #29 = Utf8               Lscala/Function1;
   #30 = Utf8               Lscala/math/Ordering;
   #31 = Utf8               <B:Ljava/lang/Object;>(Lscala/Function1<TA;TB;>;Lscala/math/Ordering<TB;>;)TCC;
   #32 = Utf8               sortedIterableFactory
   #33 = Utf8               ()Lscala/collection/SortedIterableFactory;
   #34 = NameAndType        #32:#33       // sortedIterableFactory:()Lscala/collection/SortedIterableFactory;
   #35 = InterfaceMethodref #2.#34        // scala/collection/StrictOptimizedSortedSetOps.sortedIterableFactory:()Lscala/collection/SortedIterableFactory;
   #36 = Utf8               scala/collection/SortedIterableFactory
   #37 = Class              #36           // scala/collection/SortedIterableFactory
   #38 = Utf8               newBuilder
   #39 = Utf8               (Ljava/lang/Object;)Lscala/collection/mutable/Builder;
   #40 = NameAndType        #38:#39       // newBuilder:(Ljava/lang/Object;)Lscala/collection/mutable/Builder;
   #41 = InterfaceMethodref #37.#40       // scala/collection/SortedIterableFactory.newBuilder:(Ljava/lang/Object;)Lscala/collection/mutable/Builder;
   #42 = Utf8               scala/collection/StrictOptimizedIterableOps
   #43 = Class              #42           // scala/collection/StrictOptimizedIterableOps
   #44 = Utf8               iterator
   #45 = Utf8               ()Lscala/collection/Iterator;
   #46 = NameAndType        #44:#45       // iterator:()Lscala/collection/Iterator;
   #47 = InterfaceMethodref #43.#46       // scala/collection/StrictOptimizedIterableOps.iterator:()Lscala/collection/Iterator;
   #48 = Utf8               scala/collection/Iterator
   #49 = Class              #48           // scala/collection/Iterator
   #50 = Utf8               hasNext
   #51 = Utf8               ()Z
   #52 = NameAndType        #50:#51       // hasNext:()Z
   #53 = InterfaceMethodref #49.#52       // scala/collection/Iterator.hasNext:()Z
   #54 = Utf8               next
   #55 = Utf8               ()Ljava/lang/Object;
   #56 = NameAndType        #54:#55       // next:()Ljava/lang/Object;
   #57 = InterfaceMethodref #49.#56       // scala/collection/Iterator.next:()Ljava/lang/Object;
   #58 = Utf8               scala/Function1
   #59 = Class              #58           // scala/Function1
   #60 = Utf8               apply
   #61 = Utf8               (Ljava/lang/Object;)Ljava/lang/Object;
   #62 = NameAndType        #60:#61       // apply:(Ljava/lang/Object;)Ljava/lang/Object;
   #63 = InterfaceMethodref #59.#62       // scala/Function1.apply:(Ljava/lang/Object;)Ljava/lang/Object;
   #64 = Utf8               scala/collection/mutable/Growable
   #65 = Class              #64           // scala/collection/mutable/Growable
   #66 = Utf8               addOne
   #67 = Utf8               (Ljava/lang/Object;)Lscala/collection/mutable/Growable;
   #68 = NameAndType        #66:#67       // addOne:(Ljava/lang/Object;)Lscala/collection/mutable/Growable;
   #69 = InterfaceMethodref #65.#68       // scala/collection/mutable/Growable.addOne:(Ljava/lang/Object;)Lscala/collection/mutable/Growable;
   #70 = Utf8               scala/collection/mutable/Builder
   #71 = Class              #70           // scala/collection/mutable/Builder
   #72 = Utf8               result
   #73 = NameAndType        #72:#55       // result:()Ljava/lang/Object;
   #74 = InterfaceMethodref #71.#73       // scala/collection/mutable/Builder.result:()Ljava/lang/Object;
   #75 = Utf8               scala/collection/SortedSet
   #76 = Class              #75           // scala/collection/SortedSet
   #77 = Utf8               this
   #78 = Utf8               strictOptimizedMap_it
   #79 = Utf8               Lscala/collection/Iterator;
   #80 = Utf8               strictOptimizedMap_b
   #81 = Utf8               Lscala/collection/mutable/Builder;
   #82 = Utf8               strictOptimizedMap_$plus$eq_elem
   #83 = Utf8               Ljava/lang/Object;
   #84 = Utf8               flatMap$
   #85 = Utf8               flatMap
   #86 = NameAndType        #85:#25       // flatMap:(Lscala/Function1;Lscala/math/Ordering;)Lscala/collection/SortedSet;
   #87 = InterfaceMethodref #2.#86        // scala/collection/StrictOptimizedSortedSetOps.flatMap:(Lscala/Function1;Lscala/math/Ordering;)Lscala/collection/SortedSet;
   #88 = Utf8               <B:Ljava/lang/Object;>(Lscala/Function1<TA;Lscala/collection/IterableOnce<TB;>;>;Lscala/math/Ordering<TB;>;)TCC;
   #89 = Utf8               scala/collection/IterableOnce
   #90 = Class              #89           // scala/collection/IterableOnce
   #91 = Utf8               addAll
   #92 = Utf8               (Lscala/collection/IterableOnce;)Lscala/collection/mutable/Growable;
   #93 = NameAndType        #91:#92       // addAll:(Lscala/collection/IterableOnce;)Lscala/collection/mutable/Growable;
   #94 = InterfaceMethodref #65.#93       // scala/collection/mutable/Growable.addAll:(Lscala/collection/IterableOnce;)Lscala/collection/mutable/Growable;
   #95 = Utf8               strictOptimizedFlatMap_it
   #96 = Utf8               strictOptimizedFlatMap_b
   #97 = Utf8               strictOptimizedFlatMap_$plus$plus$eq_xs
   #98 = Utf8               Lscala/collection/IterableOnce;
   #99 = Utf8               zip$
  #100 = Utf8               (Lscala/collection/StrictOptimizedSortedSetOps;Lscala/collection/IterableOnce;Lscala/math/Ordering;)Lscala/collection/SortedSet;
  #101 = Utf8               that
  #102 = Utf8               zip
  #103 = Utf8               (Lscala/collection/IterableOnce;Lscala/math/Ordering;)Lscala/collection/SortedSet;
  #104 = NameAndType        #102:#103     // zip:(Lscala/collection/IterableOnce;Lscala/math/Ordering;)Lscala/collection/SortedSet;
  #105 = InterfaceMethodref #2.#104       // scala/collection/StrictOptimizedSortedSetOps.zip:(Lscala/collection/IterableOnce;Lscala/math/Ordering;)Lscala/collection/SortedSet;
  #106 = Utf8               <B:Ljava/lang/Object;>(Lscala/collection/IterableOnce<TB;>;Lscala/math/Ordering<Lscala/Tuple2<TA;TB;>;>;)TCC;
  #107 = InterfaceMethodref #90.#46       // scala/collection/IterableOnce.iterator:()Lscala/collection/Iterator;
  #108 = Utf8               scala/Tuple2
  #109 = Class              #108          // scala/Tuple2
  #110 = Utf8               <init>
  #111 = Utf8               (Ljava/lang/Object;Ljava/lang/Object;)V
  #112 = NameAndType        #110:#111     // "<init>":(Ljava/lang/Object;Ljava/lang/Object;)V
  #113 = Methodref          #109.#112     // scala/Tuple2."<init>":(Ljava/lang/Object;Ljava/lang/Object;)V
  #114 = Utf8               strictOptimizedZip_it1
  #115 = Utf8               strictOptimizedZip_it2
  #116 = Utf8               strictOptimizedZip_b
  #117 = Utf8               strictOptimizedZip_$plus$eq_elem
  #118 = Utf8               collect$
  #119 = Utf8               (Lscala/collection/StrictOptimizedSortedSetOps;Lscala/PartialFunction;Lscala/math/Ordering;)Lscala/collection/SortedSet;
  #120 = Utf8               pf
  #121 = Utf8               collect
  #122 = Utf8               (Lscala/PartialFunction;Lscala/math/Ordering;)Lscala/collection/SortedSet;
  #123 = NameAndType        #121:#122     // collect:(Lscala/PartialFunction;Lscala/math/Ordering;)Lscala/collection/SortedSet;
  #124 = InterfaceMethodref #2.#123       // scala/collection/StrictOptimizedSortedSetOps.collect:(Lscala/PartialFunction;Lscala/math/Ordering;)Lscala/collection/SortedSet;
  #125 = Utf8               Lscala/PartialFunction;
  #126 = Utf8               <B:Ljava/lang/Object;>(Lscala/PartialFunction<TA;TB;>;Lscala/math/Ordering<TB;>;)TCC;
  #127 = Utf8               scala/runtime/Statics
  #128 = Class              #127          // scala/runtime/Statics
  #129 = Utf8               pfMarker
  #130 = NameAndType        #129:#83      // pfMarker:Ljava/lang/Object;
  #131 = Fieldref           #128.#130     // scala/runtime/Statics.pfMarker:Ljava/lang/Object;
  #132 = MethodType         #61           //  (Ljava/lang/Object;)Ljava/lang/Object;
  #133 = Utf8               $anonfun$strictOptimizedCollect$1
  #134 = Utf8               (Ljava/lang/Object;Ljava/lang/Object;)Ljava/lang/Object;
  #135 = NameAndType        #133:#134     // $anonfun$strictOptimizedCollect$1:(Ljava/lang/Object;Ljava/lang/Object;)Ljava/lang/Object;
  #136 = InterfaceMethodref #43.#135      // scala/collection/StrictOptimizedIterableOps.$anonfun$strictOptimizedCollect$1:(Ljava/lang/Object;Ljava/lang/Object;)Ljava/lang/Object;
  #137 = MethodHandle       6:#136        // REF_invokeStatic scala/collection/StrictOptimizedIterableOps.$anonfun$strictOptimizedCollect$1:(Ljava/lang/Object;Ljava/lang/Object;)Ljava/lang/Object;
  #138 = Integer            1
  #139 = Utf8               java/lang/invoke/LambdaMetafactory
  #140 = Class              #139          // java/lang/invoke/LambdaMetafactory
  #141 = Utf8               altMetafactory
  #142 = Utf8               (Ljava/lang/invoke/MethodHandles$Lookup;Ljava/lang/String;Ljava/lang/invoke/MethodType;[Ljava/lang/Object;)Ljava/lang/invoke/CallSite;
  #143 = NameAndType        #141:#142     // altMetafactory:(Ljava/lang/invoke/MethodHandles$Lookup;Ljava/lang/String;Ljava/lang/invoke/MethodType;[Ljava/lang/Object;)Ljava/lang/invoke/CallSite;
  #144 = Methodref          #140.#143     // java/lang/invoke/LambdaMetafactory.altMetafactory:(Ljava/lang/invoke/MethodHandles$Lookup;Ljava/lang/String;Ljava/lang/invoke/MethodType;[Ljava/lang/Object;)Ljava/lang/invoke/CallSite;
  #145 = MethodHandle       6:#144        // REF_invokeStatic java/lang/invoke/LambdaMetafactory.altMetafactory:(Ljava/lang/invoke/MethodHandles$Lookup;Ljava/lang/String;Ljava/lang/invoke/MethodType;[Ljava/lang/Object;)Ljava/lang/invoke/CallSite;
  #146 = Utf8               (Ljava/lang/Object;)Lscala/Function1;
  #147 = NameAndType        #60:#146      // apply:(Ljava/lang/Object;)Lscala/Function1;
  #148 = InvokeDynamic      #0:#147       // #0:apply:(Ljava/lang/Object;)Lscala/Function1;
  #149 = Utf8               scala/PartialFunction
  #150 = Class              #149          // scala/PartialFunction
  #151 = Utf8               applyOrElse
  #152 = Utf8               (Ljava/lang/Object;Lscala/Function1;)Ljava/lang/Object;
  #153 = NameAndType        #151:#152     // applyOrElse:(Ljava/lang/Object;Lscala/Function1;)Ljava/lang/Object;
  #154 = InterfaceMethodref #150.#153     // scala/PartialFunction.applyOrElse:(Ljava/lang/Object;Lscala/Function1;)Ljava/lang/Object;
  #155 = Utf8               strictOptimizedCollect_elem
  #156 = Utf8               strictOptimizedCollect_v
  #157 = Utf8               strictOptimizedCollect_marker
  #158 = Utf8               strictOptimizedCollect_it
  #159 = Utf8               strictOptimizedCollect_b
  #160 = Utf8               $init$
  #161 = Utf8               (Lscala/collection/StrictOptimizedSortedSetOps;)V
  #162 = Utf8               $deserializeLambda$
  #163 = Utf8               (Ljava/lang/invoke/SerializedLambda;)Ljava/lang/Object;
  #164 = Utf8               scala/runtime/LambdaDeserialize
  #165 = Class              #164          // scala/runtime/LambdaDeserialize
  #166 = Utf8               bootstrap
  #167 = Utf8               (Ljava/lang/invoke/MethodHandles$Lookup;Ljava/lang/String;Ljava/lang/invoke/MethodType;[Ljava/lang/invoke/MethodHandle;)Ljava/lang/invoke/CallSite;
  #168 = NameAndType        #166:#167     // bootstrap:(Ljava/lang/invoke/MethodHandles$Lookup;Ljava/lang/String;Ljava/lang/invoke/MethodType;[Ljava/lang/invoke/MethodHandle;)Ljava/lang/invoke/CallSite;
  #169 = Methodref          #165.#168     // scala/runtime/LambdaDeserialize.bootstrap:(Ljava/lang/invoke/MethodHandles$Lookup;Ljava/lang/String;Ljava/lang/invoke/MethodType;[Ljava/lang/invoke/MethodHandle;)Ljava/lang/invoke/CallSite;
  #170 = MethodHandle       6:#169        // REF_invokeStatic scala/runtime/LambdaDeserialize.bootstrap:(Ljava/lang/invoke/MethodHandles$Lookup;Ljava/lang/String;Ljava/lang/invoke/MethodType;[Ljava/lang/invoke/MethodHandle;)Ljava/lang/invoke/CallSite;
  #171 = Utf8               lambdaDeserialize
  #172 = NameAndType        #171:#163     // lambdaDeserialize:(Ljava/lang/invoke/SerializedLambda;)Ljava/lang/Object;
  #173 = InvokeDynamic      #1:#172       // #1:lambdaDeserialize:(Ljava/lang/invoke/SerializedLambda;)Ljava/lang/Object;
  #174 = Utf8               Code
  #175 = Utf8               LineNumberTable
  #176 = Utf8               LocalVariableTable
  #177 = Utf8               MethodParameters
  #178 = Utf8               StackMapTable
  #179 = Utf8               Signature
  #180 = Utf8               InnerClasses
  #181 = Utf8               SourceFile
  #182 = Utf8               RuntimeVisibleAnnotations
  #183 = Utf8               BootstrapMethods
  #184 = Utf8               ScalaInlineInfo
  #185 = Utf8               ScalaSig
{
  public static scala.collection.SortedSet map$(scala.collection.StrictOptimizedSortedSetOps, scala.Function1, scala.math.Ordering);
    descriptor: (Lscala/collection/StrictOptimizedSortedSetOps;Lscala/Function1;Lscala/math/Ordering;)Lscala/collection/SortedSet;
    flags: (0x1009) ACC_PUBLIC, ACC_STATIC, ACC_SYNTHETIC
    Code:
      stack=3, locals=3, args_size=3
         0: aload_0
         1: aload_1
         2: aload_2
         3: invokespecial #27                 // InterfaceMethod map:(Lscala/Function1;Lscala/math/Ordering;)Lscala/collection/SortedSet;
         6: areturn
      LineNumberTable:
        line 30: 0
      LocalVariableTable:
        Start  Length  Slot  Name   Signature
            0       7     0 $this   Lscala/collection/StrictOptimizedSortedSetOps;
            0       7     1     f   Lscala/Function1;
            0       7     2    ev   Lscala/math/Ordering;
    MethodParameters:
      Name                           Flags
      $this                          final synthetic
      f                              final
      ev                             final

  public default <B extends java.lang.Object> CC map(scala.Function1<A, B>, scala.math.Ordering<B>);
    descriptor: (Lscala/Function1;Lscala/math/Ordering;)Lscala/collection/SortedSet;
    flags: (0x0001) ACC_PUBLIC
    Code:
      stack=3, locals=6, args_size=3
         0: aload_0
         1: invokeinterface #35,  1           // InterfaceMethod sortedIterableFactory:()Lscala/collection/SortedIterableFactory;
         6: aload_2
         7: invokeinterface #41,  2           // InterfaceMethod scala/collection/SortedIterableFactory.newBuilder:(Ljava/lang/Object;)Lscala/collection/mutable/Builder;
        12: astore_3
        13: aload_0
        14: invokeinterface #47,  1           // InterfaceMethod scala/collection/StrictOptimizedIterableOps.iterator:()Lscala/collection/Iterator;
        19: astore        4
        21: aload         4
        23: invokeinterface #53,  1           // InterfaceMethod scala/collection/Iterator.hasNext:()Z
        28: ifeq          67
        31: aload_3
        32: aload_1
        33: aload         4
        35: invokeinterface #57,  1           // InterfaceMethod scala/collection/Iterator.next:()Ljava/lang/Object;
        40: invokeinterface #63,  2           // InterfaceMethod scala/Function1.apply:(Ljava/lang/Object;)Ljava/lang/Object;
        45: astore        5
        47: ifnonnull     52
        50: aconst_null
        51: athrow
        52: aload_3
        53: aload         5
        55: invokeinterface #69,  2           // InterfaceMethod scala/collection/mutable/Growable.addOne:(Ljava/lang/Object;)Lscala/collection/mutable/Growable;
        60: pop
        61: aconst_null
        62: astore        5
        64: goto          21
        67: aload_3
        68: invokeinterface #74,  1           // InterfaceMethod scala/collection/mutable/Builder.result:()Ljava/lang/Object;
        73: checkcast     #76                 // class scala/collection/SortedSet
        76: areturn
      StackMapTable: number_of_entries = 3
        frame_type = 253 /* append */
          offset_delta = 21
          locals = [ class scala/collection/mutable/Builder, class scala/collection/Iterator ]
        frame_type = 252 /* append */
          offset_delta = 30
          locals = [ class java/lang/Object ]
        frame_type = 250 /* chop */
          offset_delta = 14
      LineNumberTable:
        line 31: 0
      LocalVariableTable:
        Start  Length  Slot  Name   Signature
            0      77     0  this   Lscala/collection/StrictOptimizedSortedSetOps;
            0      77     1     f   Lscala/Function1;
            0      77     2    ev   Lscala/math/Ordering;
           21      52     4 strictOptimizedMap_it   Lscala/collection/Iterator;
           13      60     3 strictOptimizedMap_b   Lscala/collection/mutable/Builder;
           52       9     5 strictOptimizedMap_$plus$eq_elem   Ljava/lang/Object;
    Signature: #31                          // <B:Ljava/lang/Object;>(Lscala/Function1<TA;TB;>;Lscala/math/Ordering<TB;>;)TCC;
    MethodParameters:
      Name                           Flags
      f                              final
      ev                             final

  public static scala.collection.SortedSet flatMap$(scala.collection.StrictOptimizedSortedSetOps, scala.Function1, scala.math.Ordering);
    descriptor: (Lscala/collection/StrictOptimizedSortedSetOps;Lscala/Function1;Lscala/math/Ordering;)Lscala/collection/SortedSet;
    flags: (0x1009) ACC_PUBLIC, ACC_STATIC, ACC_SYNTHETIC
    Code:
      stack=3, locals=3, args_size=3
         0: aload_0
         1: aload_1
         2: aload_2
         3: invokespecial #87                 // InterfaceMethod flatMap:(Lscala/Function1;Lscala/math/Ordering;)Lscala/collection/SortedSet;
         6: areturn
      LineNumberTable:
        line 33: 0
      LocalVariableTable:
        Start  Length  Slot  Name   Signature
            0       7     0 $this   Lscala/collection/StrictOptimizedSortedSetOps;
            0       7     1     f   Lscala/Function1;
            0       7     2    ev   Lscala/math/Ordering;
    MethodParameters:
      Name                           Flags
      $this                          final synthetic
      f                              final
      ev                             final

  public default <B extends java.lang.Object> CC flatMap(scala.Function1<A, scala.collection.IterableOnce<B>>, scala.math.Ordering<B>);
    descriptor: (Lscala/Function1;Lscala/math/Ordering;)Lscala/collection/SortedSet;
    flags: (0x0001) ACC_PUBLIC
    Code:
      stack=3, locals=6, args_size=3
         0: aload_0
         1: invokeinterface #35,  1           // InterfaceMethod sortedIterableFactory:()Lscala/collection/SortedIterableFactory;
         6: aload_2
         7: invokeinterface #41,  2           // InterfaceMethod scala/collection/SortedIterableFactory.newBuilder:(Ljava/lang/Object;)Lscala/collection/mutable/Builder;
        12: astore_3
        13: aload_0
        14: invokeinterface #47,  1           // InterfaceMethod scala/collection/StrictOptimizedIterableOps.iterator:()Lscala/collection/Iterator;
        19: astore        4
        21: aload         4
        23: invokeinterface #53,  1           // InterfaceMethod scala/collection/Iterator.hasNext:()Z
        28: ifeq          70
        31: aload_3
        32: aload_1
        33: aload         4
        35: invokeinterface #57,  1           // InterfaceMethod scala/collection/Iterator.next:()Ljava/lang/Object;
        40: invokeinterface #63,  2           // InterfaceMethod scala/Function1.apply:(Ljava/lang/Object;)Ljava/lang/Object;
        45: checkcast     #90                 // class scala/collection/IterableOnce
        48: astore        5
        50: ifnonnull     55
        53: aconst_null
        54: athrow
        55: aload_3
        56: aload         5
        58: invokeinterface #94,  2           // InterfaceMethod scala/collection/mutable/Growable.addAll:(Lscala/collection/IterableOnce;)Lscala/collection/mutable/Growable;
        63: pop
        64: aconst_null
        65: astore        5
        67: goto          21
        70: aload_3
        71: invokeinterface #74,  1           // InterfaceMethod scala/collection/mutable/Builder.result:()Ljava/lang/Object;
        76: checkcast     #76                 // class scala/collection/SortedSet
        79: areturn
      StackMapTable: number_of_entries = 3
        frame_type = 253 /* append */
          offset_delta = 21
          locals = [ class scala/collection/mutable/Builder, class scala/collection/Iterator ]
        frame_type = 252 /* append */
          offset_delta = 33
          locals = [ class scala/collection/IterableOnce ]
        frame_type = 250 /* chop */
          offset_delta = 14
      LineNumberTable:
        line 34: 0
      LocalVariableTable:
        Start  Length  Slot  Name   Signature
            0      80     0  this   Lscala/collection/StrictOptimizedSortedSetOps;
            0      80     1     f   Lscala/Function1;
            0      80     2    ev   Lscala/math/Ordering;
           21      55     4 strictOptimizedFlatMap_it   Lscala/collection/Iterator;
           13      63     3 strictOptimizedFlatMap_b   Lscala/collection/mutable/Builder;
           55       9     5 strictOptimizedFlatMap_$plus$plus$eq_xs   Lscala/collection/IterableOnce;
    Signature: #88                          // <B:Ljava/lang/Object;>(Lscala/Function1<TA;Lscala/collection/IterableOnce<TB;>;>;Lscala/math/Ordering<TB;>;)TCC;
    MethodParameters:
      Name                           Flags
      f                              final
      ev                             final

  public static scala.collection.SortedSet zip$(scala.collection.StrictOptimizedSortedSetOps, scala.collection.IterableOnce, scala.math.Ordering);
    descriptor: (Lscala/collection/StrictOptimizedSortedSetOps;Lscala/collection/IterableOnce;Lscala/math/Ordering;)Lscala/collection/SortedSet;
    flags: (0x1009) ACC_PUBLIC, ACC_STATIC, ACC_SYNTHETIC
    Code:
      stack=3, locals=3, args_size=3
         0: aload_0
         1: aload_1
         2: aload_2
         3: invokespecial #105                // InterfaceMethod zip:(Lscala/collection/IterableOnce;Lscala/math/Ordering;)Lscala/collection/SortedSet;
         6: areturn
      LineNumberTable:
        line 36: 0
      LocalVariableTable:
        Start  Length  Slot  Name   Signature
            0       7     0 $this   Lscala/collection/StrictOptimizedSortedSetOps;
            0       7     1  that   Lscala/collection/IterableOnce;
            0       7     2    ev   Lscala/math/Ordering;
    MethodParameters:
      Name                           Flags
      $this                          final synthetic
      that                           final
      ev                             final

  public default <B extends java.lang.Object> CC zip(scala.collection.IterableOnce<B>, scala.math.Ordering<scala.Tuple2<A, B>>);
    descriptor: (Lscala/collection/IterableOnce;Lscala/math/Ordering;)Lscala/collection/SortedSet;
    flags: (0x0001) ACC_PUBLIC
    Code:
      stack=5, locals=7, args_size=3
         0: aload_0
         1: invokeinterface #35,  1           // InterfaceMethod sortedIterableFactory:()Lscala/collection/SortedIterableFactory;
         6: aload_2
         7: invokeinterface #41,  2           // InterfaceMethod scala/collection/SortedIterableFactory.newBuilder:(Ljava/lang/Object;)Lscala/collection/mutable/Builder;
        12: astore_3
        13: aload_0
        14: invokeinterface #47,  1           // InterfaceMethod scala/collection/StrictOptimizedIterableOps.iterator:()Lscala/collection/Iterator;
        19: astore        4
        21: aload_1
        22: invokeinterface #107,  1          // InterfaceMethod scala/collection/IterableOnce.iterator:()Lscala/collection/Iterator;
        27: astore        5
        29: aload         4
        31: invokeinterface #53,  1           // InterfaceMethod scala/collection/Iterator.hasNext:()Z
        36: ifeq          93
        39: aload         5
        41: invokeinterface #53,  1           // InterfaceMethod scala/collection/Iterator.hasNext:()Z
        46: ifeq          93
        49: aload_3
        50: new           #109                // class scala/Tuple2
        53: dup
        54: aload         4
        56: invokeinterface #57,  1           // InterfaceMethod scala/collection/Iterator.next:()Ljava/lang/Object;
        61: aload         5
        63: invokeinterface #57,  1           // InterfaceMethod scala/collection/Iterator.next:()Ljava/lang/Object;
        68: invokespecial #113                // Method scala/Tuple2."<init>":(Ljava/lang/Object;Ljava/lang/Object;)V
        71: astore        6
        73: ifnonnull     78
        76: aconst_null
        77: athrow
        78: aload_3
        79: aload         6
        81: invokeinterface #69,  2           // InterfaceMethod scala/collection/mutable/Growable.addOne:(Ljava/lang/Object;)Lscala/collection/mutable/Growable;
        86: pop
        87: aconst_null
        88: astore        6
        90: goto          29
        93: aload_3
        94: invokeinterface #74,  1           // InterfaceMethod scala/collection/mutable/Builder.result:()Ljava/lang/Object;
        99: checkcast     #76                 // class scala/collection/SortedSet
       102: areturn
      StackMapTable: number_of_entries = 3
        frame_type = 254 /* append */
          offset_delta = 29
          locals = [ class scala/collection/mutable/Builder, class scala/collection/Iterator, class scala/collection/Iterator ]
        frame_type = 252 /* append */
          offset_delta = 48
          locals = [ class scala/Tuple2 ]
        frame_type = 250 /* chop */
          offset_delta = 14
      LineNumberTable:
        line 37: 0
      LocalVariableTable:
        Start  Length  Slot  Name   Signature
            0     103     0  this   Lscala/collection/StrictOptimizedSortedSetOps;
            0     103     1  that   Lscala/collection/IterableOnce;
            0     103     2    ev   Lscala/math/Ordering;
           21      78     4 strictOptimizedZip_it1   Lscala/collection/Iterator;
           29      70     5 strictOptimizedZip_it2   Lscala/collection/Iterator;
           13      86     3 strictOptimizedZip_b   Lscala/collection/mutable/Builder;
           78       9     6 strictOptimizedZip_$plus$eq_elem   Ljava/lang/Object;
    Signature: #106                         // <B:Ljava/lang/Object;>(Lscala/collection/IterableOnce<TB;>;Lscala/math/Ordering<Lscala/Tuple2<TA;TB;>;>;)TCC;
    MethodParameters:
      Name                           Flags
      that                           final
      ev                             final

  public static scala.collection.SortedSet collect$(scala.collection.StrictOptimizedSortedSetOps, scala.PartialFunction, scala.math.Ordering);
    descriptor: (Lscala/collection/StrictOptimizedSortedSetOps;Lscala/PartialFunction;Lscala/math/Ordering;)Lscala/collection/SortedSet;
    flags: (0x1009) ACC_PUBLIC, ACC_STATIC, ACC_SYNTHETIC
    Code:
      stack=3, locals=3, args_size=3
         0: aload_0
         1: aload_1
         2: aload_2
         3: invokespecial #124                // InterfaceMethod collect:(Lscala/PartialFunction;Lscala/math/Ordering;)Lscala/collection/SortedSet;
         6: areturn
      LineNumberTable:
        line 39: 0
      LocalVariableTable:
        Start  Length  Slot  Name   Signature
            0       7     0 $this   Lscala/collection/StrictOptimizedSortedSetOps;
            0       7     1    pf   Lscala/PartialFunction;
            0       7     2    ev   Lscala/math/Ordering;
    MethodParameters:
      Name                           Flags
      $this                          final synthetic
      pf                             final
      ev                             final

  public default <B extends java.lang.Object> CC collect(scala.PartialFunction<A, B>, scala.math.Ordering<B>);
    descriptor: (Lscala/PartialFunction;Lscala/math/Ordering;)Lscala/collection/SortedSet;
    flags: (0x0001) ACC_PUBLIC
    Code:
      stack=3, locals=8, args_size=3
         0: aload_0
         1: invokeinterface #35,  1           // InterfaceMethod sortedIterableFactory:()Lscala/collection/SortedIterableFactory;
         6: aload_2
         7: invokeinterface #41,  2           // InterfaceMethod scala/collection/SortedIterableFactory.newBuilder:(Ljava/lang/Object;)Lscala/collection/mutable/Builder;
        12: astore_3
        13: getstatic     #131                // Field scala/runtime/Statics.pfMarker:Ljava/lang/Object;
        16: astore        4
        18: aload_0
        19: invokeinterface #47,  1           // InterfaceMethod scala/collection/StrictOptimizedIterableOps.iterator:()Lscala/collection/Iterator;
        24: astore        5
        26: aload         5
        28: invokeinterface #53,  1           // InterfaceMethod scala/collection/Iterator.hasNext:()Z
        33: ifeq          87
        36: aload         5
        38: invokeinterface #57,  1           // InterfaceMethod scala/collection/Iterator.next:()Ljava/lang/Object;
        43: astore        6
        45: aload_1
        46: aload         6
        48: aload         4
        50: invokedynamic #148,  0            // InvokeDynamic #0:apply:(Ljava/lang/Object;)Lscala/Function1;
        55: invokeinterface #154,  3          // InterfaceMethod scala/PartialFunction.applyOrElse:(Ljava/lang/Object;Lscala/Function1;)Ljava/lang/Object;
        60: astore        7
        62: aload         4
        64: aload         7
        66: if_acmpeq     26
        69: aload_3
        70: ifnonnull     75
        73: aconst_null
        74: athrow
        75: aload_3
        76: aload         7
        78: invokeinterface #69,  2           // InterfaceMethod scala/collection/mutable/Growable.addOne:(Ljava/lang/Object;)Lscala/collection/mutable/Growable;
        83: pop
        84: goto          26
        87: aload_3
        88: invokeinterface #74,  1           // InterfaceMethod scala/collection/mutable/Builder.result:()Ljava/lang/Object;
        93: checkcast     #76                 // class scala/collection/SortedSet
        96: areturn
      StackMapTable: number_of_entries = 3
        frame_type = 254 /* append */
          offset_delta = 26
          locals = [ class scala/collection/mutable/Builder, class java/lang/Object, class scala/collection/Iterator ]
        frame_type = 253 /* append */
          offset_delta = 48
          locals = [ class java/lang/Object, class java/lang/Object ]
        frame_type = 249 /* chop */
          offset_delta = 11
      LineNumberTable:
        line 40: 0
      LocalVariableTable:
        Start  Length  Slot  Name   Signature
            0      97     0  this   Lscala/collection/StrictOptimizedSortedSetOps;
            0      97     1    pf   Lscala/PartialFunction;
            0      97     2    ev   Lscala/math/Ordering;
           45      42     6 strictOptimizedCollect_elem   Ljava/lang/Object;
           62      25     7 strictOptimizedCollect_v   Ljava/lang/Object;
           18      75     4 strictOptimizedCollect_marker   Ljava/lang/Object;
           26      67     5 strictOptimizedCollect_it   Lscala/collection/Iterator;
           13      80     3 strictOptimizedCollect_b   Lscala/collection/mutable/Builder;
    Signature: #126                         // <B:Ljava/lang/Object;>(Lscala/PartialFunction<TA;TB;>;Lscala/math/Ordering<TB;>;)TCC;
    MethodParameters:
      Name                           Flags
      pf                             final
      ev                             final

  public static void $init$(scala.collection.StrictOptimizedSortedSetOps);
    descriptor: (Lscala/collection/StrictOptimizedSortedSetOps;)V
    flags: (0x0009) ACC_PUBLIC, ACC_STATIC
    Code:
      stack=0, locals=1, args_size=1
         0: return
      LineNumberTable:
        line 27: 0
      LocalVariableTable:
        Start  Length  Slot  Name   Signature
            0       1     0 $this   Lscala/collection/StrictOptimizedSortedSetOps;
    MethodParameters:
      Name                           Flags
      $this                          final synthetic

  private static java.lang.Object $deserializeLambda$(java.lang.invoke.SerializedLambda);
    descriptor: (Ljava/lang/invoke/SerializedLambda;)Ljava/lang/Object;
    flags: (0x100a) ACC_PRIVATE, ACC_STATIC, ACC_SYNTHETIC
    Code:
      stack=1, locals=1, args_size=1
         0: aload_0
         1: invokedynamic #173,  0            // InvokeDynamic #1:lambdaDeserialize:(Ljava/lang/invoke/SerializedLambda;)Ljava/lang/Object;
         6: areturn
}
InnerClasses:
  public static final #18= #15 of #17;    // Lookup=class java/lang/invoke/MethodHandles$Lookup of class java/lang/invoke/MethodHandles
Signature: #3                           // <A:Ljava/lang/Object;CC::Lscala/collection/SortedSet<Ljava/lang/Object;>;C::Lscala/collection/SortedSetOps<TA;TCC;TC;>;>Ljava/lang/Object;Lscala/collection/SortedSetOps<TA;TCC;TC;>;Lscala/collection/StrictOptimizedSetOps<TA;Lscala/collection/Set;TC;>;
SourceFile: "StrictOptimizedSortedSetOps.scala"
RuntimeVisibleAnnotations:
  0: #11(#12=s#13)
    scala.reflect.ScalaSignature(
      bytes="\u0006\u0005\u0005\u001dba\u0002\u0004\b!\u0003\r\t\u0001\u0004\u0005\u0006m\u0001!\ta\u000e\u0005\u0006w\u0001!\t\u0005\u0010\u0005\u00067\u0002!\t\u0005\u0018\u0005\u0006U\u0002!\te\u001b\u0005\b\u0003\u0013\u0001A\u0011IA\u0006\u0005m\u0019FO]5di>\u0003H/[7ju\u0016$7k\u001c:uK\u0012\u001cV\r^(qg*\u0011\u0001\"C\u0001\u000bG>dG.Z2uS>t\'\"\u0001\u0006\u0002\u000bM\u001c\u0017\r\\1\u0004\u0001U!Q\u0002\u0007\u0012.\'\u0011\u0001aB\u0005\u0019\u0011\u0005=\u0001R\"A\u0005\n\u0005EI!AB!osJ+g\rE\u0003\u0014)Y\tC&D\u0001\b\u0013\t)rA\u0001\u0007T_J$X\rZ*fi>\u00038\u000f\u0005\u0002\u001811\u0001A!B\r\u0001\u0005\u0004Q\"!A!\u0012\u0005mq\u0002CA\b\u001d\u0013\ti\u0012BA\u0004O_RD\u0017N\\4\u0011\u0005=y\u0012B\u0001\u0011\n\u0005\r\te.\u001f\t\u0003/\t\"aa\t\u0001\u0005\u0006\u0004!#AA\"D+\t)#&\u0005\u0002\u001cMA\u00191cJ\u0015\n\u0005!:!!C*peR,GmU3u!\t9\"\u0006B\u0003,E\t\u0007!DA\u0001Y!\t9R\u0006\u0002\u0004/\u0001\u0011\u0015\ra\f\u0002\u0002\u0007F\u00111D\u0005\t\u0006\'E22\u0007L\u0005\u0003e\u001d\u0011Qc\u0015;sS\u000e$x\n\u001d;j[&TX\rZ*fi>\u00038\u000f\u0005\u0002\u0014i%\u0011Qg\u0002\u0002\u0004\'\u0016$\u0018A\u0002\u0013j]&$H\u0005F\u00019!\ty\u0011(\u0003\u0002;\u0013\t!QK\\5u\u0003\ri\u0017\r]\u000b\u0003{\u0005#\"A\u0010,\u0015\u0005}\u001a\u0005cA\f#\u0001B\u0011q#\u0011\u0003\u0006\u0005\n\u0011\rA\u0007\u0002\u0002\u0005\")AI\u0001a\u0002\u000b\u0006\u0011QM\u001e\t\u0004\r&\u0003eBA\bH\u0013\tA\u0015\"A\u0004qC\u000e\\\u0017mZ3\n\u0005)[%\u0001C(sI\u0016\u0014\u0018N\\4\u000b\u0005!K\u0001\u0006B\"N\'R\u0003\"AT)\u000e\u0003=S!\u0001U\u0005\u0002\u0015\u0005tgn\u001c;bi&|g.\u0003\u0002S\u001f\n\u0001\u0012.\u001c9mS\u000eLGOT8u\r>,h\u000eZ\u0001\u0004[N<\u0017%A+\u0002\u007f:{\u0007%[7qY&\u001c\u0017\u000e\u001e\u0011Pe\u0012,\'/\u001b8h7\u0012Z()`/!M>,h\u000e\u001a\u0011u_\u0002\u0012W/\u001b7eA\u0005\u00043k\u001c:uK\u0012\u001cV\r^.%w\nkXL\f\u0011Z_V\u0004S.Y=!o\u0006tG\u000f\t;pAU\u00048-Y:uAQ|\u0007%\u0019\u0011TKR\\Fe_!~;\u00022\u0017N]:uA\tL\beY1mY&tw\r\t1v]N|\'\u000f^3eA:BQa\u0016\u0002A\u0002a\u000b\u0011A\u001a\t\u0005\u001fe3\u0002)\u0003\u0002[\u0013\tIa)\u001e8di&|g.M\u0001\bM2\fG/T1q+\ti\u0016\r\u0006\u0002_KR\u0011qL\u0019\t\u0004/\t\u0002\u0007CA\fb\t\u0015\u00115A1\u0001\u001b\u0011\u0015!5\u0001q\u0001d!\r1\u0015\n\u0019\u0015\u0005E6\u001bF\u000bC\u0003X\u0007\u0001\u0007a\r\u0005\u0003\u00103Z9\u0007cA\niA&\u0011\u0011n\u0002\u0002\r\u0013R,\'/\u00192mK>s7-Z\u0001\u0004u&\u0004XC\u00017|)\ri\u00171\u0001\u000b\u0003]r\u00042a\u0006\u0012p!\u0011y\u0001O\u001d>\n\u0005EL!A\u0002+va2,\'G\u000b\u0002\u0017g.\nA\u000f\u0005\u0002vq6\taO\u0003\u0002x\u001f\u0006IQO\\2iK\u000e\\W\rZ\u0005\u0003sZ\u0014\u0011#\u001e8dQ\u0016\u001c7.\u001a3WCJL\u0017M\\2f!\t92\u0010B\u0003C\t\t\u0007!\u0004C\u0003E\t\u0001\u000fQ\u0010E\u0002G\u0013>DC\u0001`\'T\u007f\u0006\u0012\u0011\u0011A\u0001\u0002\u00109{\u0007%[7qY&\u001c\u0017\u000e\u001e\u0011Pe\u0012,\'/\u001b8h7\u0012Z()`/!M>,h\u000e\u001a\u0011u_\u0002\u0012W/\u001b7eA\u0005\u00043k\u001c:uK\u0012\u001cV\r^.)Im\fU\u0010\f\u0011%w\nk\u0018&\u0018\u0018!3>,\b%\\1zA]\fg\u000e\u001e\u0011u_\u0002*\boY1ti\u0002\"x\u000eI1!\'\u0016$8\fJ>B{v\u0003c-\u001b:ti\u0002\u0012\u0017\u0010I2bY2Lgn\u001a\u0011ak:\u001cxN\u001d;fI\u0002t\u0003bBA\u0003\t\u0001\u0007\u0011qA\u0001\u0005i\"\fG\u000fE\u0002\u0014Qj\fqaY8mY\u0016\u001cG/\u0006\u0003\u0002\u000e\u0005UA\u0003BA\b\u0003;!B!!\u0005\u0002\u0018A!qCIA\n!\r9\u0012Q\u0003\u0003\u0006\u0005\u0016\u0011\rA\u0007\u0005\u0007\t\u0016\u0001\u001d!!\u0007\u0011\t\u0019K\u00151\u0003\u0015\u0006\u0003/i5\u000b\u0016\u0005\b\u0003?)\u0001\u0019AA\u0011\u0003\t\u0001h\r\u0005\u0004\u0010\u0003G1\u00121C\u0005\u0004\u0003KI!a\u0004)beRL\u0017\r\u001c$v]\u000e$\u0018n\u001c8"
    )
BootstrapMethods:
  0: #145 REF_invokeStatic java/lang/invoke/LambdaMetafactory.altMetafactory:(Ljava/lang/invoke/MethodHandles$Lookup;Ljava/lang/String;Ljava/lang/invoke/MethodType;[Ljava/lang/Object;)Ljava/lang/invoke/CallSite;
    Method arguments:
      #132 (Ljava/lang/Object;)Ljava/lang/Object;
      #137 REF_invokeStatic scala/collection/StrictOptimizedIterableOps.$anonfun$strictOptimizedCollect$1:(Ljava/lang/Object;Ljava/lang/Object;)Ljava/lang/Object;
      #132 (Ljava/lang/Object;)Ljava/lang/Object;
      #138 1
  1: #170 REF_invokeStatic scala/runtime/LambdaDeserialize.bootstrap:(Ljava/lang/invoke/MethodHandles$Lookup;Ljava/lang/String;Ljava/lang/invoke/MethodType;[Ljava/lang/invoke/MethodHandle;)Ljava/lang/invoke/CallSite;
    Method arguments:
      #137 REF_invokeStatic scala/collection/StrictOptimizedIterableOps.$anonfun$strictOptimizedCollect$1:(Ljava/lang/Object;Ljava/lang/Object;)Ljava/lang/Object;
  ScalaInlineInfo: length = 0x31 (unknown attribute)
   01 00 00 09 00 A0 00 A1 01 00 79 00 7A 00 00 76
   00 77 01 00 55 00 19 00 00 54 00 14 01 00 18 00
   19 00 00 13 00 14 01 00 66 00 67 00 00 63 00 64
   01
  ScalaSig: length = 0x3 (unknown attribute)
   05 02 00
