Classfile /Users/mw/Projects/slang-braindump/.jar/jar8/assemble/slang-braindump/assemble/content/scala/collection/View$$anon$1.class
  Last modified May 29, 2022; size 935 bytes
  SHA-256 checksum b307486ffa51c144dd65eb6402b5cb1df70fd38ff3911b1352ceda4b9afc1d75
  Compiled from "View.scala"
public final class scala.collection.View$$anon$1 extends scala.collection.AbstractView<A>
  minor version: 0
  major version: 52
  flags: (0x0031) ACC_PUBLIC, ACC_FINAL, ACC_SUPER
  this_class: #2                          // scala/collection/View$$anon$1
  super_class: #5                         // scala/collection/AbstractView
  interfaces: 0, fields: 1, methods: 2, attributes: 6
Constant pool:
   #1 = Utf8               scala/collection/View$$anon$1
   #2 = Class              #1             // scala/collection/View$$anon$1
   #3 = Utf8               Lscala/collection/AbstractView<TA;>;
   #4 = Utf8               scala/collection/AbstractView
   #5 = Class              #4             // scala/collection/AbstractView
   #6 = Utf8               View.scala
   #7 = Utf8               scala/collection/View$
   #8 = Class              #7             // scala/collection/View$
   #9 = Utf8               fromIteratorProvider
  #10 = Utf8               (Lscala/Function0;)Lscala/collection/View;
  #11 = NameAndType        #9:#10         // fromIteratorProvider:(Lscala/Function0;)Lscala/collection/View;
  #12 = Utf8               it$1
  #13 = Utf8               Lscala/Function0;
  #14 = Utf8               iterator
  #15 = Utf8               ()Lscala/collection/Iterator;
  #16 = Utf8               ()Lscala/collection/Iterator<TA;>;
  #17 = NameAndType        #12:#13        // it$1:Lscala/Function0;
  #18 = Fieldref           #2.#17         // scala/collection/View$$anon$1.it$1:Lscala/Function0;
  #19 = Utf8               scala/Function0
  #20 = Class              #19            // scala/Function0
  #21 = Utf8               apply
  #22 = Utf8               ()Ljava/lang/Object;
  #23 = NameAndType        #21:#22        // apply:()Ljava/lang/Object;
  #24 = InterfaceMethodref #20.#23        // scala/Function0.apply:()Ljava/lang/Object;
  #25 = Utf8               scala/collection/Iterator
  #26 = Class              #25            // scala/collection/Iterator
  #27 = Utf8               this
  #28 = Utf8               Lscala/collection/View$$anon$1;
  #29 = Utf8               <init>
  #30 = Utf8               (Lscala/Function0;)V
  #31 = Utf8               ()V
  #32 = NameAndType        #29:#31        // "<init>":()V
  #33 = Methodref          #5.#32         // scala/collection/AbstractView."<init>":()V
  #34 = Utf8               Code
  #35 = Utf8               LineNumberTable
  #36 = Utf8               LocalVariableTable
  #37 = Utf8               Signature
  #38 = Utf8               MethodParameters
  #39 = Utf8               InnerClasses
  #40 = Utf8               EnclosingMethod
  #41 = Utf8               SourceFile
  #42 = Utf8               ScalaInlineInfo
  #43 = Utf8               Scala
{
  private final scala.Function0 it$1;
    descriptor: Lscala/Function0;
    flags: (0x0012) ACC_PRIVATE, ACC_FINAL

  public scala.collection.Iterator<A> iterator();
    descriptor: ()Lscala/collection/Iterator;
    flags: (0x0001) ACC_PUBLIC
    Code:
      stack=1, locals=1, args_size=1
         0: aload_0
         1: getfield      #18                 // Field it$1:Lscala/Function0;
         4: invokeinterface #24,  1           // InterfaceMethod scala/Function0.apply:()Ljava/lang/Object;
         9: checkcast     #26                 // class scala/collection/Iterator
        12: areturn
      LineNumberTable:
        line 59: 0
      LocalVariableTable:
        Start  Length  Slot  Name   Signature
            0      13     0  this   Lscala/collection/View$$anon$1;
    Signature: #16                          // ()Lscala/collection/Iterator<TA;>;

  public scala.collection.View$$anon$1(scala.Function0);
    descriptor: (Lscala/Function0;)V
    flags: (0x0001) ACC_PUBLIC
    Code:
      stack=2, locals=2, args_size=2
         0: aload_0
         1: aload_1
         2: putfield      #18                 // Field it$1:Lscala/Function0;
         5: aload_0
         6: invokespecial #33                 // Method scala/collection/AbstractView."<init>":()V
         9: return
      LineNumberTable:
        line 58: 0
      LocalVariableTable:
        Start  Length  Slot  Name   Signature
            0      10     0  this   Lscala/collection/View$$anon$1;
            0      10     1  it$1   Lscala/Function0;
    MethodParameters:
      Name                           Flags
      it$1                           final
}
InnerClasses:
  public final #2;                        // class scala/collection/View$$anon$1
EnclosingMethod: #8.#11                 // scala.collection.View$.fromIteratorProvider
Signature: #3                           // Lscala/collection/AbstractView<TA;>;
SourceFile: "View.scala"
  ScalaInlineInfo: length = 0xE (unknown attribute)
   01 01 00 02 00 1D 00 1E 01 00 0E 00 0F 01
  Scala: length = 0x0 (unknown attribute)

