Classfile /Users/mw/Projects/slang-braindump/.jar/jar8/assemble/slang-braindump/assemble/content/scala/collection/View$Filter$.class
  Last modified May 29, 2022; size 3024 bytes
  SHA-256 checksum b6b567fdc7bb1db2a359a72c8f7816649d61f15cad1e51b7535da5e8fc50e1e3
  Compiled from "View.scala"
public class scala.collection.View$Filter$ implements java.io.Serializable
  minor version: 0
  major version: 52
  flags: (0x0021) ACC_PUBLIC, ACC_SUPER
  this_class: #2                          // scala/collection/View$Filter$
  super_class: #4                         // java/lang/Object
  interfaces: 1, fields: 1, methods: 7, attributes: 5
Constant pool:
    #1 = Utf8               scala/collection/View$Filter$
    #2 = Class              #1            // scala/collection/View$Filter$
    #3 = Utf8               java/lang/Object
    #4 = Class              #3            // java/lang/Object
    #5 = Utf8               java/io/Serializable
    #6 = Class              #5            // java/io/Serializable
    #7 = Utf8               View.scala
    #8 = Utf8               java/lang/invoke/MethodHandles$Lookup
    #9 = Class              #8            // java/lang/invoke/MethodHandles$Lookup
   #10 = Utf8               java/lang/invoke/MethodHandles
   #11 = Class              #10           // java/lang/invoke/MethodHandles
   #12 = Utf8               Lookup
   #13 = Utf8               scala/collection/View$Filter
   #14 = Class              #13           // scala/collection/View$Filter
   #15 = Utf8               scala/collection/View
   #16 = Class              #15           // scala/collection/View
   #17 = Utf8               Filter
   #18 = Utf8               Filter$
   #19 = Utf8               MODULE$
   #20 = Utf8               Lscala/collection/View$Filter$;
   #21 = Utf8               <clinit>
   #22 = Utf8               ()V
   #23 = Utf8               <init>
   #24 = NameAndType        #23:#22       // "<init>":()V
   #25 = Methodref          #2.#24        // scala/collection/View$Filter$."<init>":()V
   #26 = NameAndType        #19:#20       // MODULE$:Lscala/collection/View$Filter$;
   #27 = Fieldref           #2.#26        // scala/collection/View$Filter$.MODULE$:Lscala/collection/View$Filter$;
   #28 = Utf8               apply
   #29 = Utf8               (Lscala/collection/Iterable;Lscala/Function1;Z)Lscala/collection/View$Filter;
   #30 = Utf8               <A:Ljava/lang/Object;>(Lscala/collection/Iterable<TA;>;Lscala/Function1<TA;Ljava/lang/Object;>;Z)Lscala/collection/View$Filter<TA;>;
   #31 = Utf8               underlying
   #32 = Utf8               p
   #33 = Utf8               isFlipped
   #34 = Utf8               ()Z
   #35 = NameAndType        #33:#34       // isFlipped:()Z
   #36 = Methodref          #14.#35       // scala/collection/View$Filter.isFlipped:()Z
   #37 = Utf8               ()Lscala/collection/IterableOps;
   #38 = NameAndType        #31:#37       // underlying:()Lscala/collection/IterableOps;
   #39 = Methodref          #14.#38       // scala/collection/View$Filter.underlying:()Lscala/collection/IterableOps;
   #40 = Utf8               (Ljava/lang/Object;)Ljava/lang/Object;
   #41 = MethodType         #40           //  (Ljava/lang/Object;)Ljava/lang/Object;
   #42 = Utf8               $anonfun$apply$1$adapted
   #43 = Utf8               (Lscala/collection/View$Filter;Lscala/Function1;Ljava/lang/Object;)Ljava/lang/Object;
   #44 = NameAndType        #42:#43       // $anonfun$apply$1$adapted:(Lscala/collection/View$Filter;Lscala/Function1;Ljava/lang/Object;)Ljava/lang/Object;
   #45 = Methodref          #2.#44        // scala/collection/View$Filter$.$anonfun$apply$1$adapted:(Lscala/collection/View$Filter;Lscala/Function1;Ljava/lang/Object;)Ljava/lang/Object;
   #46 = MethodHandle       6:#45         // REF_invokeStatic scala/collection/View$Filter$.$anonfun$apply$1$adapted:(Lscala/collection/View$Filter;Lscala/Function1;Ljava/lang/Object;)Ljava/lang/Object;
   #47 = Integer            1
   #48 = Utf8               java/lang/invoke/LambdaMetafactory
   #49 = Class              #48           // java/lang/invoke/LambdaMetafactory
   #50 = Utf8               altMetafactory
   #51 = Utf8               (Ljava/lang/invoke/MethodHandles$Lookup;Ljava/lang/String;Ljava/lang/invoke/MethodType;[Ljava/lang/Object;)Ljava/lang/invoke/CallSite;
   #52 = NameAndType        #50:#51       // altMetafactory:(Ljava/lang/invoke/MethodHandles$Lookup;Ljava/lang/String;Ljava/lang/invoke/MethodType;[Ljava/lang/Object;)Ljava/lang/invoke/CallSite;
   #53 = Methodref          #49.#52       // java/lang/invoke/LambdaMetafactory.altMetafactory:(Ljava/lang/invoke/MethodHandles$Lookup;Ljava/lang/String;Ljava/lang/invoke/MethodType;[Ljava/lang/Object;)Ljava/lang/invoke/CallSite;
   #54 = MethodHandle       6:#53         // REF_invokeStatic java/lang/invoke/LambdaMetafactory.altMetafactory:(Ljava/lang/invoke/MethodHandles$Lookup;Ljava/lang/String;Ljava/lang/invoke/MethodType;[Ljava/lang/Object;)Ljava/lang/invoke/CallSite;
   #55 = Utf8               (Lscala/collection/View$Filter;Lscala/Function1;)Lscala/Function1;
   #56 = NameAndType        #28:#55       // apply:(Lscala/collection/View$Filter;Lscala/Function1;)Lscala/Function1;
   #57 = InvokeDynamic      #0:#56        // #0:apply:(Lscala/collection/View$Filter;Lscala/Function1;)Lscala/Function1;
   #58 = Utf8               (Lscala/collection/IterableOps;Lscala/Function1;Z)V
   #59 = NameAndType        #23:#58       // "<init>":(Lscala/collection/IterableOps;Lscala/Function1;Z)V
   #60 = Methodref          #14.#59       // scala/collection/View$Filter."<init>":(Lscala/collection/IterableOps;Lscala/Function1;Z)V
   #61 = Utf8               this
   #62 = Utf8               Lscala/collection/Iterable;
   #63 = Utf8               Lscala/Function1;
   #64 = Utf8               Z
   #65 = Utf8               writeReplace
   #66 = Utf8               ()Ljava/lang/Object;
   #67 = Utf8               scala/runtime/ModuleSerializationProxy
   #68 = Class              #67           // scala/runtime/ModuleSerializationProxy
   #69 = Utf8               (Ljava/lang/Class;)V
   #70 = NameAndType        #23:#69       // "<init>":(Ljava/lang/Class;)V
   #71 = Methodref          #68.#70       // scala/runtime/ModuleSerializationProxy."<init>":(Ljava/lang/Class;)V
   #72 = Utf8               $anonfun$apply$1
   #73 = Utf8               (Lscala/collection/View$Filter;Lscala/Function1;Ljava/lang/Object;)Z
   #74 = Utf8               x2$1
   #75 = Utf8               p$1
   #76 = Utf8               a
   #77 = Utf8               ()Lscala/Function1;
   #78 = NameAndType        #32:#77       // p:()Lscala/Function1;
   #79 = Methodref          #14.#78       // scala/collection/View$Filter.p:()Lscala/Function1;
   #80 = Utf8               scala/Function1
   #81 = Class              #80           // scala/Function1
   #82 = NameAndType        #28:#40       // apply:(Ljava/lang/Object;)Ljava/lang/Object;
   #83 = InterfaceMethodref #81.#82       // scala/Function1.apply:(Ljava/lang/Object;)Ljava/lang/Object;
   #84 = Utf8               scala/runtime/BoxesRunTime
   #85 = Class              #84           // scala/runtime/BoxesRunTime
   #86 = Utf8               unboxToBoolean
   #87 = Utf8               (Ljava/lang/Object;)Z
   #88 = NameAndType        #86:#87       // unboxToBoolean:(Ljava/lang/Object;)Z
   #89 = Methodref          #85.#88       // scala/runtime/BoxesRunTime.unboxToBoolean:(Ljava/lang/Object;)Z
   #90 = Utf8               Lscala/collection/View$Filter;
   #91 = Utf8               Ljava/lang/Object;
   #92 = Methodref          #4.#24        // java/lang/Object."<init>":()V
   #93 = NameAndType        #72:#73       // $anonfun$apply$1:(Lscala/collection/View$Filter;Lscala/Function1;Ljava/lang/Object;)Z
   #94 = Methodref          #2.#93        // scala/collection/View$Filter$.$anonfun$apply$1:(Lscala/collection/View$Filter;Lscala/Function1;Ljava/lang/Object;)Z
   #95 = Utf8               boxToBoolean
   #96 = Utf8               (Z)Ljava/lang/Boolean;
   #97 = NameAndType        #95:#96       // boxToBoolean:(Z)Ljava/lang/Boolean;
   #98 = Methodref          #85.#97       // scala/runtime/BoxesRunTime.boxToBoolean:(Z)Ljava/lang/Boolean;
   #99 = Utf8               $deserializeLambda$
  #100 = Utf8               (Ljava/lang/invoke/SerializedLambda;)Ljava/lang/Object;
  #101 = Utf8               scala/runtime/LambdaDeserialize
  #102 = Class              #101          // scala/runtime/LambdaDeserialize
  #103 = Utf8               bootstrap
  #104 = Utf8               (Ljava/lang/invoke/MethodHandles$Lookup;Ljava/lang/String;Ljava/lang/invoke/MethodType;[Ljava/lang/invoke/MethodHandle;)Ljava/lang/invoke/CallSite;
  #105 = NameAndType        #103:#104     // bootstrap:(Ljava/lang/invoke/MethodHandles$Lookup;Ljava/lang/String;Ljava/lang/invoke/MethodType;[Ljava/lang/invoke/MethodHandle;)Ljava/lang/invoke/CallSite;
  #106 = Methodref          #102.#105     // scala/runtime/LambdaDeserialize.bootstrap:(Ljava/lang/invoke/MethodHandles$Lookup;Ljava/lang/String;Ljava/lang/invoke/MethodType;[Ljava/lang/invoke/MethodHandle;)Ljava/lang/invoke/CallSite;
  #107 = MethodHandle       6:#106        // REF_invokeStatic scala/runtime/LambdaDeserialize.bootstrap:(Ljava/lang/invoke/MethodHandles$Lookup;Ljava/lang/String;Ljava/lang/invoke/MethodType;[Ljava/lang/invoke/MethodHandle;)Ljava/lang/invoke/CallSite;
  #108 = Utf8               lambdaDeserialize
  #109 = NameAndType        #108:#100     // lambdaDeserialize:(Ljava/lang/invoke/SerializedLambda;)Ljava/lang/Object;
  #110 = InvokeDynamic      #1:#109       // #1:lambdaDeserialize:(Ljava/lang/invoke/SerializedLambda;)Ljava/lang/Object;
  #111 = Utf8               Code
  #112 = Utf8               LineNumberTable
  #113 = Utf8               StackMapTable
  #114 = Utf8               LocalVariableTable
  #115 = Utf8               Signature
  #116 = Utf8               MethodParameters
  #117 = Utf8               InnerClasses
  #118 = Utf8               SourceFile
  #119 = Utf8               BootstrapMethods
  #120 = Utf8               ScalaInlineInfo
  #121 = Utf8               Scala
{
  public static final scala.collection.View$Filter$ MODULE$;
    descriptor: Lscala/collection/View$Filter$;
    flags: (0x0019) ACC_PUBLIC, ACC_STATIC, ACC_FINAL

  public static {};
    descriptor: ()V
    flags: (0x0009) ACC_PUBLIC, ACC_STATIC
    Code:
      stack=2, locals=0, args_size=0
         0: new           #2                  // class scala/collection/View$Filter$
         3: dup
         4: invokespecial #25                 // Method "<init>":()V
         7: putstatic     #27                 // Field MODULE$:Lscala/collection/View$Filter$;
        10: return
      LineNumberTable:
        line 149: 0

  public <A extends java.lang.Object> scala.collection.View$Filter<A> apply(scala.collection.Iterable<A>, scala.Function1<A, java.lang.Object>, boolean);
    descriptor: (Lscala/collection/Iterable;Lscala/Function1;Z)Lscala/collection/View$Filter;
    flags: (0x0001) ACC_PUBLIC
    Code:
      stack=5, locals=6, args_size=4
         0: aload_1
         1: instanceof    #14                 // class scala/collection/View$Filter
         4: ifeq          48
         7: aload_1
         8: checkcast     #14                 // class scala/collection/View$Filter
        11: astore        5
        13: aload         5
        15: invokevirtual #36                 // Method scala/collection/View$Filter.isFlipped:()Z
        18: iload_3
        19: if_icmpne     48
        22: new           #14                 // class scala/collection/View$Filter
        25: dup
        26: aload         5
        28: invokevirtual #39                 // Method scala/collection/View$Filter.underlying:()Lscala/collection/IterableOps;
        31: aload         5
        33: aload_2
        34: invokedynamic #57,  0             // InvokeDynamic #0:apply:(Lscala/collection/View$Filter;Lscala/Function1;)Lscala/Function1;
        39: iload_3
        40: invokespecial #60                 // Method scala/collection/View$Filter."<init>":(Lscala/collection/IterableOps;Lscala/Function1;Z)V
        43: astore        4
        45: goto          60
        48: new           #14                 // class scala/collection/View$Filter
        51: dup
        52: aload_1
        53: aload_2
        54: iload_3
        55: invokespecial #60                 // Method scala/collection/View$Filter."<init>":(Lscala/collection/IterableOps;Lscala/Function1;Z)V
        58: astore        4
        60: aload         4
        62: areturn
      StackMapTable: number_of_entries = 2
        frame_type = 48 /* same */
        frame_type = 252 /* append */
          offset_delta = 11
          locals = [ class scala/collection/View$Filter ]
      LineNumberTable:
        line 152: 0
        line 153: 48
        line 151: 60
      LocalVariableTable:
        Start  Length  Slot  Name   Signature
            0      63     0  this   Lscala/collection/View$Filter$;
            0      63     1 underlying   Lscala/collection/Iterable;
            0      63     2     p   Lscala/Function1;
            0      63     3 isFlipped   Z
    Signature: #30                          // <A:Ljava/lang/Object;>(Lscala/collection/Iterable<TA;>;Lscala/Function1<TA;Ljava/lang/Object;>;Z)Lscala/collection/View$Filter<TA;>;
    MethodParameters:
      Name                           Flags
      underlying                     final
      p                              final
      isFlipped                      final

  private java.lang.Object writeReplace();
    descriptor: ()Ljava/lang/Object;
    flags: (0x0002) ACC_PRIVATE
    Code:
      stack=3, locals=1, args_size=1
         0: new           #68                 // class scala/runtime/ModuleSerializationProxy
         3: dup
         4: ldc           #2                  // class scala/collection/View$Filter$
         6: invokespecial #71                 // Method scala/runtime/ModuleSerializationProxy."<init>":(Ljava/lang/Class;)V
         9: areturn
      LineNumberTable:
        line 149: 0
      LocalVariableTable:
        Start  Length  Slot  Name   Signature
            0      10     0  this   Lscala/collection/View$Filter$;

  public static final boolean $anonfun$apply$1(scala.collection.View$Filter, scala.Function1, java.lang.Object);
    descriptor: (Lscala/collection/View$Filter;Lscala/Function1;Ljava/lang/Object;)Z
    flags: (0x1019) ACC_PUBLIC, ACC_STATIC, ACC_FINAL, ACC_SYNTHETIC
    Code:
      stack=2, locals=3, args_size=3
         0: aload_0
         1: invokevirtual #79                 // Method scala/collection/View$Filter.p:()Lscala/Function1;
         4: aload_2
         5: invokeinterface #83,  2           // InterfaceMethod scala/Function1.apply:(Ljava/lang/Object;)Ljava/lang/Object;
        10: invokestatic  #89                 // Method scala/runtime/BoxesRunTime.unboxToBoolean:(Ljava/lang/Object;)Z
        13: ifeq          31
        16: aload_1
        17: aload_2
        18: invokeinterface #83,  2           // InterfaceMethod scala/Function1.apply:(Ljava/lang/Object;)Ljava/lang/Object;
        23: invokestatic  #89                 // Method scala/runtime/BoxesRunTime.unboxToBoolean:(Ljava/lang/Object;)Z
        26: ifeq          31
        29: iconst_1
        30: ireturn
        31: iconst_0
        32: ireturn
      StackMapTable: number_of_entries = 1
        frame_type = 31 /* same */
      LineNumberTable:
        line 152: 0
      LocalVariableTable:
        Start  Length  Slot  Name   Signature
            0      33     0  x2$1   Lscala/collection/View$Filter;
            0      33     1   p$1   Lscala/Function1;
            0      33     2     a   Ljava/lang/Object;
    MethodParameters:
      Name                           Flags
      x2$1                           final
      p$1                            final
      a                              final

  public scala.collection.View$Filter$();
    descriptor: ()V
    flags: (0x0001) ACC_PUBLIC
    Code:
      stack=1, locals=1, args_size=1
         0: aload_0
         1: invokespecial #92                 // Method java/lang/Object."<init>":()V
         4: return
      LineNumberTable:
        line 149: 0
      LocalVariableTable:
        Start  Length  Slot  Name   Signature
            0       5     0  this   Lscala/collection/View$Filter$;

  public static final java.lang.Object $anonfun$apply$1$adapted(scala.collection.View$Filter, scala.Function1, java.lang.Object);
    descriptor: (Lscala/collection/View$Filter;Lscala/Function1;Ljava/lang/Object;)Ljava/lang/Object;
    flags: (0x1019) ACC_PUBLIC, ACC_STATIC, ACC_FINAL, ACC_SYNTHETIC
    Code:
      stack=3, locals=3, args_size=3
         0: aload_0
         1: aload_1
         2: aload_2
         3: invokestatic  #94                 // Method $anonfun$apply$1:(Lscala/collection/View$Filter;Lscala/Function1;Ljava/lang/Object;)Z
         6: invokestatic  #98                 // Method scala/runtime/BoxesRunTime.boxToBoolean:(Z)Ljava/lang/Boolean;
         9: areturn
      LineNumberTable:
        line 152: 0
      LocalVariableTable:
        Start  Length  Slot  Name   Signature
            0      10     0  x2$1   Lscala/collection/View$Filter;
            0      10     1   p$1   Lscala/Function1;
            0      10     2     a   Ljava/lang/Object;
    MethodParameters:
      Name                           Flags
      x2$1                           final
      p$1                            final
      a                              final

  private static java.lang.Object $deserializeLambda$(java.lang.invoke.SerializedLambda);
    descriptor: (Ljava/lang/invoke/SerializedLambda;)Ljava/lang/Object;
    flags: (0x100a) ACC_PRIVATE, ACC_STATIC, ACC_SYNTHETIC
    Code:
      stack=1, locals=1, args_size=1
         0: aload_0
         1: invokedynamic #110,  0            // InvokeDynamic #1:lambdaDeserialize:(Ljava/lang/invoke/SerializedLambda;)Ljava/lang/Object;
         6: areturn
}
InnerClasses:
  public static final #12= #9 of #11;     // Lookup=class java/lang/invoke/MethodHandles$Lookup of class java/lang/invoke/MethodHandles
  public static #17= #14 of #16;          // Filter=class scala/collection/View$Filter of class scala/collection/View
  public static #18= #2 of #16;           // Filter$=class scala/collection/View$Filter$ of class scala/collection/View
SourceFile: "View.scala"
BootstrapMethods:
  0: #54 REF_invokeStatic java/lang/invoke/LambdaMetafactory.altMetafactory:(Ljava/lang/invoke/MethodHandles$Lookup;Ljava/lang/String;Ljava/lang/invoke/MethodType;[Ljava/lang/Object;)Ljava/lang/invoke/CallSite;
    Method arguments:
      #41 (Ljava/lang/Object;)Ljava/lang/Object;
      #46 REF_invokeStatic scala/collection/View$Filter$.$anonfun$apply$1$adapted:(Lscala/collection/View$Filter;Lscala/Function1;Ljava/lang/Object;)Ljava/lang/Object;
      #41 (Ljava/lang/Object;)Ljava/lang/Object;
      #47 1
  1: #107 REF_invokeStatic scala/runtime/LambdaDeserialize.bootstrap:(Ljava/lang/invoke/MethodHandles$Lookup;Ljava/lang/String;Ljava/lang/invoke/MethodType;[Ljava/lang/invoke/MethodHandle;)Ljava/lang/invoke/CallSite;
    Method arguments:
      #46 REF_invokeStatic scala/collection/View$Filter$.$anonfun$apply$1$adapted:(Lscala/collection/View$Filter;Lscala/Function1;Ljava/lang/Object;)Ljava/lang/Object;
  ScalaInlineInfo: length = 0x1D (unknown attribute)
   01 01 00 05 00 48 00 49 01 00 2A 00 2B 01 00 17
   00 16 01 00 1C 00 1D 01 00 41 00 42 01
  Scala: length = 0x0 (unknown attribute)

