Classfile /Users/mw/Projects/slang-braindump/.jar/jar8/assemble/slang-braindump/assemble/content/scala/collection/View$TakeRightIterator.class
  Last modified May 29, 2022; size 2920 bytes
  SHA-256 checksum a602d2978ee6fd4003ef1572c4ac220e844957bdd42e9d5033e4967e3259778e
  Compiled from "View.scala"
public final class scala.collection.View$TakeRightIterator<A extends java.lang.Object> extends scala.collection.AbstractIterator<A>
  minor version: 0
  major version: 52
  flags: (0x0031) ACC_PUBLIC, ACC_FINAL, ACC_SUPER
  this_class: #2                          // scala/collection/View$TakeRightIterator
  super_class: #5                         // scala/collection/AbstractIterator
  interfaces: 0, fields: 5, methods: 7, attributes: 5
Constant pool:
    #1 = Utf8               scala/collection/View$TakeRightIterator
    #2 = Class              #1            // scala/collection/View$TakeRightIterator
    #3 = Utf8               <A:Ljava/lang/Object;>Lscala/collection/AbstractIterator<TA;>;
    #4 = Utf8               scala/collection/AbstractIterator
    #5 = Class              #4            // scala/collection/AbstractIterator
    #6 = Utf8               View.scala
    #7 = Utf8               scala/collection/View
    #8 = Class              #7            // scala/collection/View
    #9 = Utf8               TakeRightIterator
   #10 = Utf8               underlying
   #11 = Utf8               Lscala/collection/Iterator;
   #12 = Utf8               Lscala/collection/Iterator<TA;>;
   #13 = Utf8               maxlen
   #14 = Utf8               I
   #15 = Utf8               len
   #16 = Utf8               pos
   #17 = Utf8               buf
   #18 = Utf8               Lscala/collection/mutable/ArrayBuffer;
   #19 = Utf8               Lscala/collection/mutable/ArrayBuffer<Ljava/lang/Object;>;
   #20 = Utf8               init
   #21 = Utf8               ()V
   #22 = NameAndType        #17:#18       // buf:Lscala/collection/mutable/ArrayBuffer;
   #23 = Fieldref           #2.#22        // scala/collection/View$TakeRightIterator.buf:Lscala/collection/mutable/ArrayBuffer;
   #24 = Utf8               scala/collection/mutable/ArrayBuffer
   #25 = Class              #24           // scala/collection/mutable/ArrayBuffer
   #26 = Utf8               scala/runtime/RichInt$
   #27 = Class              #26           // scala/runtime/RichInt$
   #28 = Utf8               MODULE$
   #29 = Utf8               Lscala/runtime/RichInt$;
   #30 = NameAndType        #28:#29       // MODULE$:Lscala/runtime/RichInt$;
   #31 = Fieldref           #27.#30       // scala/runtime/RichInt$.MODULE$:Lscala/runtime/RichInt$;
   #32 = NameAndType        #13:#14       // maxlen:I
   #33 = Fieldref           #2.#32        // scala/collection/View$TakeRightIterator.maxlen:I
   #34 = Utf8               scala/math/package$
   #35 = Class              #34           // scala/math/package$
   #36 = Utf8               Lscala/math/package$;
   #37 = NameAndType        #28:#36       // MODULE$:Lscala/math/package$;
   #38 = Fieldref           #35.#37       // scala/math/package$.MODULE$:Lscala/math/package$;
   #39 = Utf8               java/lang/Math
   #40 = Class              #39           // java/lang/Math
   #41 = Utf8               min
   #42 = Utf8               (II)I
   #43 = NameAndType        #41:#42       // min:(II)I
   #44 = Methodref          #40.#43       // java/lang/Math.min:(II)I
   #45 = Utf8               <init>
   #46 = Utf8               (I)V
   #47 = NameAndType        #45:#46       // "<init>":(I)V
   #48 = Methodref          #25.#47       // scala/collection/mutable/ArrayBuffer."<init>":(I)V
   #49 = NameAndType        #15:#14       // len:I
   #50 = Fieldref           #2.#49        // scala/collection/View$TakeRightIterator.len:I
   #51 = NameAndType        #10:#11       // underlying:Lscala/collection/Iterator;
   #52 = Fieldref           #2.#51        // scala/collection/View$TakeRightIterator.underlying:Lscala/collection/Iterator;
   #53 = Utf8               scala/collection/Iterator
   #54 = Class              #53           // scala/collection/Iterator
   #55 = Utf8               hasNext
   #56 = Utf8               ()Z
   #57 = NameAndType        #55:#56       // hasNext:()Z
   #58 = InterfaceMethodref #54.#57       // scala/collection/Iterator.hasNext:()Z
   #59 = Utf8               next
   #60 = Utf8               ()Ljava/lang/Object;
   #61 = NameAndType        #59:#60       // next:()Ljava/lang/Object;
   #62 = InterfaceMethodref #54.#61       // scala/collection/Iterator.next:()Ljava/lang/Object;
   #63 = NameAndType        #16:#14       // pos:I
   #64 = Fieldref           #2.#63        // scala/collection/View$TakeRightIterator.pos:I
   #65 = Utf8               length
   #66 = Utf8               ()I
   #67 = NameAndType        #65:#66       // length:()I
   #68 = Methodref          #25.#67       // scala/collection/mutable/ArrayBuffer.length:()I
   #69 = Utf8               addOne
   #70 = Utf8               (Ljava/lang/Object;)Lscala/collection/mutable/ArrayBuffer;
   #71 = NameAndType        #69:#70       // addOne:(Ljava/lang/Object;)Lscala/collection/mutable/ArrayBuffer;
   #72 = Methodref          #25.#71       // scala/collection/mutable/ArrayBuffer.addOne:(Ljava/lang/Object;)Lscala/collection/mutable/ArrayBuffer;
   #73 = Utf8               update
   #74 = Utf8               (ILjava/lang/Object;)V
   #75 = NameAndType        #73:#74       // update:(ILjava/lang/Object;)V
   #76 = Methodref          #25.#75       // scala/collection/mutable/ArrayBuffer.update:(ILjava/lang/Object;)V
   #77 = Utf8               n
   #78 = Utf8               Ljava/lang/Object;
   #79 = Utf8               this
   #80 = Utf8               Lscala/collection/View$TakeRightIterator;
   #81 = Utf8               min$extension_that
   #82 = Utf8               java/lang/Object
   #83 = Class              #82           // java/lang/Object
   #84 = Utf8               knownSize
   #85 = NameAndType        #20:#21       // init:()V
   #86 = Methodref          #2.#85        // scala/collection/View$TakeRightIterator.init:()V
   #87 = Utf8               ()TA;
   #88 = Utf8               scala/collection/Iterator$
   #89 = Class              #88           // scala/collection/Iterator$
   #90 = Utf8               Lscala/collection/Iterator$;
   #91 = NameAndType        #28:#90       // MODULE$:Lscala/collection/Iterator$;
   #92 = Fieldref           #89.#91       // scala/collection/Iterator$.MODULE$:Lscala/collection/Iterator$;
   #93 = Utf8               scala$collection$Iterator$$_empty
   #94 = NameAndType        #93:#11       // scala$collection$Iterator$$_empty:Lscala/collection/Iterator;
   #95 = Fieldref           #89.#94       // scala/collection/Iterator$.scala$collection$Iterator$$_empty:Lscala/collection/Iterator;
   #96 = Utf8               apply
   #97 = Utf8               (I)Ljava/lang/Object;
   #98 = NameAndType        #96:#97       // apply:(I)Ljava/lang/Object;
   #99 = Methodref          #25.#98       // scala/collection/mutable/ArrayBuffer.apply:(I)Ljava/lang/Object;
  #100 = Utf8               x
  #101 = Utf8               drop
  #102 = Utf8               (I)Lscala/collection/Iterator;
  #103 = Utf8               (I)Lscala/collection/Iterator<TA;>;
  #104 = Utf8               max
  #105 = NameAndType        #104:#42      // max:(II)I
  #106 = Methodref          #40.#105      // java/lang/Math.max:(II)I
  #107 = Utf8               max$extension_that
  #108 = NameAndType        #101:#102     // drop:(I)Lscala/collection/Iterator;
  #109 = Methodref          #2.#108       // scala/collection/View$TakeRightIterator.drop:(I)Lscala/collection/Iterator;
  #110 = Utf8               (Lscala/collection/Iterator;I)V
  #111 = Utf8               (Lscala/collection/Iterator<TA;>;I)V
  #112 = NameAndType        #45:#21       // "<init>":()V
  #113 = Methodref          #5.#112       // scala/collection/AbstractIterator."<init>":()V
  #114 = Utf8               Signature
  #115 = Utf8               Code
  #116 = Utf8               StackMapTable
  #117 = Utf8               LineNumberTable
  #118 = Utf8               LocalVariableTable
  #119 = Utf8               MethodParameters
  #120 = Utf8               InnerClasses
  #121 = Utf8               SourceFile
  #122 = Utf8               ScalaInlineInfo
  #123 = Utf8               Scala
{
  private scala.collection.Iterator<A> underlying;
    descriptor: Lscala/collection/Iterator;
    flags: (0x0002) ACC_PRIVATE
    Signature: #12                          // Lscala/collection/Iterator<TA;>;

  private final int maxlen;
    descriptor: I
    flags: (0x0012) ACC_PRIVATE, ACC_FINAL

  private int len;
    descriptor: I
    flags: (0x0002) ACC_PRIVATE

  private int pos;
    descriptor: I
    flags: (0x0002) ACC_PRIVATE

  private scala.collection.mutable.ArrayBuffer<java.lang.Object> buf;
    descriptor: Lscala/collection/mutable/ArrayBuffer;
    flags: (0x0002) ACC_PRIVATE
    Signature: #19                          // Lscala/collection/mutable/ArrayBuffer<Ljava/lang/Object;>;

  public void init();
    descriptor: ()V
    flags: (0x0001) ACC_PUBLIC
    Code:
      stack=5, locals=4, args_size=1
         0: aload_0
         1: getfield      #23                 // Field buf:Lscala/collection/mutable/ArrayBuffer;
         4: ifnonnull     203
         7: aload_0
         8: new           #25                 // class scala/collection/mutable/ArrayBuffer
        11: dup
        12: getstatic     #31                 // Field scala/runtime/RichInt$.MODULE$:Lscala/runtime/RichInt$;
        15: pop
        16: aload_0
        17: getfield      #33                 // Field maxlen:I
        20: istore_2
        21: sipush        256
        24: istore_3
        25: getstatic     #38                 // Field scala/math/package$.MODULE$:Lscala/math/package$;
        28: pop
        29: iload_2
        30: iload_3
        31: invokestatic  #44                 // Method java/lang/Math.min:(II)I
        34: invokespecial #48                 // Method scala/collection/mutable/ArrayBuffer."<init>":(I)V
        37: putfield      #23                 // Field buf:Lscala/collection/mutable/ArrayBuffer;
        40: aload_0
        41: iconst_0
        42: putfield      #50                 // Field len:I
        45: aload_0
        46: getfield      #52                 // Field underlying:Lscala/collection/Iterator;
        49: invokeinterface #58,  1           // InterfaceMethod scala/collection/Iterator.hasNext:()Z
        54: ifeq          144
        57: aload_0
        58: getfield      #52                 // Field underlying:Lscala/collection/Iterator;
        61: invokeinterface #62,  1           // InterfaceMethod scala/collection/Iterator.next:()Ljava/lang/Object;
        66: astore_1
        67: aload_0
        68: getfield      #64                 // Field pos:I
        71: aload_0
        72: getfield      #23                 // Field buf:Lscala/collection/mutable/ArrayBuffer;
        75: invokevirtual #68                 // Method scala/collection/mutable/ArrayBuffer.length:()I
        78: if_icmplt     93
        81: aload_0
        82: getfield      #23                 // Field buf:Lscala/collection/mutable/ArrayBuffer;
        85: aload_1
        86: invokevirtual #72                 // Method scala/collection/mutable/ArrayBuffer.addOne:(Ljava/lang/Object;)Lscala/collection/mutable/ArrayBuffer;
        89: pop
        90: goto          105
        93: aload_0
        94: getfield      #23                 // Field buf:Lscala/collection/mutable/ArrayBuffer;
        97: aload_0
        98: getfield      #64                 // Field pos:I
       101: aload_1
       102: invokevirtual #76                 // Method scala/collection/mutable/ArrayBuffer.update:(ILjava/lang/Object;)V
       105: aload_0
       106: aload_0
       107: getfield      #64                 // Field pos:I
       110: iconst_1
       111: iadd
       112: putfield      #64                 // Field pos:I
       115: aload_0
       116: getfield      #64                 // Field pos:I
       119: aload_0
       120: getfield      #33                 // Field maxlen:I
       123: if_icmpne     131
       126: aload_0
       127: iconst_0
       128: putfield      #64                 // Field pos:I
       131: aload_0
       132: aload_0
       133: getfield      #50                 // Field len:I
       136: iconst_1
       137: iadd
       138: putfield      #50                 // Field len:I
       141: goto          45
       144: aload_0
       145: aconst_null
       146: putfield      #52                 // Field underlying:Lscala/collection/Iterator;
       149: aload_0
       150: getfield      #50                 // Field len:I
       153: aload_0
       154: getfield      #33                 // Field maxlen:I
       157: if_icmple     168
       160: aload_0
       161: aload_0
       162: getfield      #33                 // Field maxlen:I
       165: putfield      #50                 // Field len:I
       168: aload_0
       169: aload_0
       170: getfield      #64                 // Field pos:I
       173: aload_0
       174: getfield      #50                 // Field len:I
       177: isub
       178: putfield      #64                 // Field pos:I
       181: aload_0
       182: getfield      #64                 // Field pos:I
       185: iconst_0
       186: if_icmpge     203
       189: aload_0
       190: aload_0
       191: getfield      #64                 // Field pos:I
       194: aload_0
       195: getfield      #33                 // Field maxlen:I
       198: iadd
       199: putfield      #64                 // Field pos:I
       202: return
       203: return
      StackMapTable: number_of_entries = 7
        frame_type = 254 /* append */
          offset_delta = 45
          locals = [ top, int, int ]
        frame_type = 255 /* full_frame */
          offset_delta = 47
          locals = [ class scala/collection/View$TakeRightIterator, class java/lang/Object, int, int ]
          stack = []
        frame_type = 11 /* same */
        frame_type = 25 /* same */
        frame_type = 255 /* full_frame */
          offset_delta = 12
          locals = [ class scala/collection/View$TakeRightIterator, top, int, int ]
          stack = []
        frame_type = 23 /* same */
        frame_type = 248 /* chop */
          offset_delta = 34
      LineNumberTable:
        line 448: 0
        line 449: 7
        line 450: 40
        line 451: 45
        line 452: 57
        line 453: 67
        line 454: 93
        line 455: 105
        line 456: 115
        line 457: 131
        line 451: 141
        line 459: 144
        line 460: 149
        line 461: 168
        line 462: 181
        line 448: 203
      LocalVariableTable:
        Start  Length  Slot  Name   Signature
           67      74     1     n   Ljava/lang/Object;
            0     204     0  this   Lscala/collection/View$TakeRightIterator;
           25       9     3 min$extension_that   I

  public int knownSize();
    descriptor: ()I
    flags: (0x0001) ACC_PUBLIC
    Code:
      stack=1, locals=1, args_size=1
         0: aload_0
         1: getfield      #50                 // Field len:I
         4: ireturn
      LineNumberTable:
        line 464: 0
      LocalVariableTable:
        Start  Length  Slot  Name   Signature
            0       5     0  this   Lscala/collection/View$TakeRightIterator;

  public boolean hasNext();
    descriptor: ()Z
    flags: (0x0001) ACC_PUBLIC
    Code:
      stack=2, locals=1, args_size=1
         0: aload_0
         1: invokevirtual #86                 // Method init:()V
         4: aload_0
         5: getfield      #50                 // Field len:I
         8: iconst_0
         9: if_icmple     14
        12: iconst_1
        13: ireturn
        14: iconst_0
        15: ireturn
      StackMapTable: number_of_entries = 1
        frame_type = 14 /* same */
      LineNumberTable:
        line 466: 0
        line 467: 4
      LocalVariableTable:
        Start  Length  Slot  Name   Signature
            0      16     0  this   Lscala/collection/View$TakeRightIterator;

  public A next();
    descriptor: ()Ljava/lang/Object;
    flags: (0x0001) ACC_PUBLIC
    Code:
      stack=3, locals=2, args_size=1
         0: aload_0
         1: invokevirtual #86                 // Method init:()V
         4: aload_0
         5: getfield      #50                 // Field len:I
         8: iconst_0
         9: if_icmpne     25
        12: getstatic     #92                 // Field scala/collection/Iterator$.MODULE$:Lscala/collection/Iterator$;
        15: pop
        16: getstatic     #95                 // Field scala/collection/Iterator$.scala$collection$Iterator$$_empty:Lscala/collection/Iterator;
        19: invokeinterface #62,  1           // InterfaceMethod scala/collection/Iterator.next:()Ljava/lang/Object;
        24: areturn
        25: aload_0
        26: getfield      #23                 // Field buf:Lscala/collection/mutable/ArrayBuffer;
        29: aload_0
        30: getfield      #64                 // Field pos:I
        33: invokevirtual #99                 // Method scala/collection/mutable/ArrayBuffer.apply:(I)Ljava/lang/Object;
        36: astore_1
        37: aload_0
        38: aload_0
        39: getfield      #64                 // Field pos:I
        42: iconst_1
        43: iadd
        44: putfield      #64                 // Field pos:I
        47: aload_0
        48: getfield      #64                 // Field pos:I
        51: aload_0
        52: getfield      #33                 // Field maxlen:I
        55: if_icmpne     63
        58: aload_0
        59: iconst_0
        60: putfield      #64                 // Field pos:I
        63: aload_0
        64: aload_0
        65: getfield      #50                 // Field len:I
        68: iconst_1
        69: isub
        70: putfield      #50                 // Field len:I
        73: aload_1
        74: areturn
      StackMapTable: number_of_entries = 2
        frame_type = 25 /* same */
        frame_type = 252 /* append */
          offset_delta = 37
          locals = [ class java/lang/Object ]
      LineNumberTable:
        line 470: 0
        line 471: 4
        line 473: 25
        line 474: 37
        line 475: 47
        line 476: 63
        line 477: 73
      LocalVariableTable:
        Start  Length  Slot  Name   Signature
           37      37     1     x   Ljava/lang/Object;
            0      75     0  this   Lscala/collection/View$TakeRightIterator;
    Signature: #87                          // ()TA;

  public scala.collection.Iterator<A> drop(int);
    descriptor: (I)Lscala/collection/Iterator;
    flags: (0x0001) ACC_PUBLIC
    Code:
      stack=3, locals=4, args_size=2
         0: aload_0
         1: invokevirtual #86                 // Method init:()V
         4: iload_1
         5: iconst_0
         6: if_icmple     50
         9: aload_0
        10: getstatic     #31                 // Field scala/runtime/RichInt$.MODULE$:Lscala/runtime/RichInt$;
        13: pop
        14: aload_0
        15: getfield      #50                 // Field len:I
        18: iload_1
        19: isub
        20: istore_2
        21: iconst_0
        22: istore_3
        23: getstatic     #38                 // Field scala/math/package$.MODULE$:Lscala/math/package$;
        26: pop
        27: iload_2
        28: iload_3
        29: invokestatic  #106                // Method java/lang/Math.max:(II)I
        32: putfield      #50                 // Field len:I
        35: aload_0
        36: aload_0
        37: getfield      #64                 // Field pos:I
        40: iload_1
        41: iadd
        42: aload_0
        43: getfield      #33                 // Field maxlen:I
        46: irem
        47: putfield      #64                 // Field pos:I
        50: aload_0
        51: areturn
      StackMapTable: number_of_entries = 1
        frame_type = 50 /* same */
      LineNumberTable:
        line 481: 0
        line 482: 4
        line 483: 9
        line 484: 35
        line 486: 50
      LocalVariableTable:
        Start  Length  Slot  Name   Signature
            0      52     0  this   Lscala/collection/View$TakeRightIterator;
            0      52     1     n   I
           23       9     3 max$extension_that   I
    Signature: #103                         // (I)Lscala/collection/Iterator<TA;>;
    MethodParameters:
      Name                           Flags
      n                              final

  public java.lang.Object drop(int);
    descriptor: (I)Ljava/lang/Object;
    flags: (0x1041) ACC_PUBLIC, ACC_BRIDGE, ACC_SYNTHETIC
    Code:
      stack=2, locals=2, args_size=2
         0: aload_0
         1: iload_1
         2: invokevirtual #109                // Method drop:(I)Lscala/collection/Iterator;
         5: areturn
      LineNumberTable:
        line 444: 0
      LocalVariableTable:
        Start  Length  Slot  Name   Signature
            0       6     0  this   Lscala/collection/View$TakeRightIterator;
            0       6     1     n   I
    MethodParameters:
      Name                           Flags
      n                              final

  public scala.collection.View$TakeRightIterator(scala.collection.Iterator<A>, int);
    descriptor: (Lscala/collection/Iterator;I)V
    flags: (0x0001) ACC_PUBLIC
    Code:
      stack=2, locals=3, args_size=3
         0: aload_0
         1: aload_1
         2: putfield      #52                 // Field underlying:Lscala/collection/Iterator;
         5: aload_0
         6: iload_2
         7: putfield      #33                 // Field maxlen:I
        10: aload_0
        11: invokespecial #113                // Method scala/collection/AbstractIterator."<init>":()V
        14: aload_0
        15: iconst_m1
        16: putfield      #50                 // Field len:I
        19: aload_0
        20: iconst_0
        21: putfield      #64                 // Field pos:I
        24: return
      LineNumberTable:
        line 444: 0
        line 445: 14
        line 446: 19
        line 444: 24
      LocalVariableTable:
        Start  Length  Slot  Name   Signature
            0      25     0  this   Lscala/collection/View$TakeRightIterator;
            0      25     1 underlying   Lscala/collection/Iterator;
            0      25     2 maxlen   I
    Signature: #111                         // (Lscala/collection/Iterator<TA;>;I)V
    MethodParameters:
      Name                           Flags
      underlying                     final
      maxlen                         final
}
InnerClasses:
  private static final #9= #2 of #8;      // TakeRightIterator=class scala/collection/View$TakeRightIterator of class scala/collection/View
Signature: #3                           // <A:Ljava/lang/Object;>Lscala/collection/AbstractIterator<TA;>;
SourceFile: "View.scala"
  ScalaInlineInfo: length = 0x27 (unknown attribute)
   01 01 00 07 00 2D 00 6E 01 00 65 00 61 01 00 65
   00 66 01 00 37 00 38 01 00 14 00 15 01 00 54 00
   42 01 00 3B 00 3C 01
  Scala: length = 0x0 (unknown attribute)

