Classfile /Users/mw/Projects/slang-braindump/.jar/jar8/assemble/slang-braindump/assemble/content/scala/collection/WithFilter.class
  Last modified May 29, 2022; size 1864 bytes
  SHA-256 checksum c4da5957bd9ff2a80d080a72a6285f5f6b80c4bd06dba373823a3f769af80e54
  Compiled from "WithFilter.scala"
public abstract class scala.collection.WithFilter<A extends java.lang.Object, CC extends java.lang.Object> extends java.lang.Object implements java.io.Serializable
  minor version: 0
  major version: 52
  flags: (0x0421) ACC_PUBLIC, ACC_SUPER, ACC_ABSTRACT
  this_class: #2                          // scala/collection/WithFilter
  super_class: #5                         // java/lang/Object
  interfaces: 1, fields: 1, methods: 5, attributes: 5
Constant pool:
   #1 = Utf8               scala/collection/WithFilter
   #2 = Class              #1             // scala/collection/WithFilter
   #3 = Utf8               <A:Ljava/lang/Object;CC:Ljava/lang/Object;>Ljava/lang/Object;Ljava/io/Serializable;
   #4 = Utf8               java/lang/Object
   #5 = Class              #4             // java/lang/Object
   #6 = Utf8               java/io/Serializable
   #7 = Class              #6             // java/io/Serializable
   #8 = Utf8               WithFilter.scala
   #9 = Utf8               Lscala/reflect/ScalaSignature;
  #10 = Utf8               bytes
  #11 = Utf8               \u0006\u0005\r4QAB\u0004\u0002\u00021AQA\b\u0001\u0005\u0002}AQa\r\u0001\u0007\u0002QBQa\u0010\u0001\u0007\u0002\u0001CQA\u0013\u0001\u0007\u0002-CQ!\u0016\u0001\u0007\u0002Y\u0013!bV5uQ\u001aKG\u000e^3s\u0015\tA\u0011\"\u0001\u0006d_2dWm\u0019;j_:T\u0011AC\u0001\u0006g\u000e\fG.Y\u0002\u0001+\riAEL\n\u0004\u00019\u0011\u0002CA\b\u0011\u001b\u0005I\u0011BA\t\n\u0005\u0019\te.\u001f*fMB\u00111c\u0007\b\u0003)eq!!\u0006\r\u000e\u0003YQ!aF\u0006\u0002\rq\u0012xn\u001c;?\u0013\u0005Q\u0011B\u0001\u000e\n\u0003\u001d\u0001\u0018mY6bO\u0016L!\u0001H\u000f\u0003\u0019M+\'/[1mSj\f\'\r\\3\u000b\u0005iI\u0011A\u0002\u001fj]&$h\bF\u0001!!\u0011\t\u0003AI\u0017\u000e\u0003\u001d\u0001\"a\t\u0013\r\u0001\u00111Q\u0005\u0001CC\u0002\u0019\u0012\u0011!Q\t\u0003O)\u0002\"a\u0004\u0015\n\u0005%J!a\u0002(pi\"Lgn\u001a\t\u0003\u001f-J!\u0001L\u0005\u0003\u0007\u0005s\u0017\u0010\u0005\u0002$]\u00111q\u0006\u0001CC\u0002A\u0012!aQ\"\u0016\u0005\u0019\nD!\u0002\u001a/\u0005\u00041#\u0001B0%IE\n1!\\1q+\t)\u0004\b\u0006\u00027uA\u00191EL\u001c\u0011\u0005\rBD!B\u001d\u0003\u0005\u00041#!\u0001\"\t\u000bm\u0012\u0001\u0019\u0001\u001f\u0002\u0003\u0019\u0004BaD\u001f#o%\u0011a(\u0003\u0002\n\rVt7\r^5p]F\nqA\u001a7bi6\u000b\u0007/\u0006\u0002B\tR\u0011!)\u0012\t\u0004G9\u001a\u0005CA\u0012E\t\u0015I4A1\u0001\'\u0011\u0015Y4\u00011\u0001G!\u0011yQHI$\u0011\u0007\u0005B5)\u0003\u0002J\u000f\ta\u0011\n^3sC\ndWm\u00148dK\u00069am\u001c:fC\u000eDWC\u0001\'T)\ti\u0005\u000b\u0005\u0002\u0010\u001d&\u0011q*\u0003\u0002\u0005+:LG\u000fC\u0003<\t\u0001\u0007\u0011\u000b\u0005\u0003\u0010{\t\u0012\u0006CA\u0012T\t\u0015!FA1\u0001\'\u0005\u0005)\u0016AC<ji\"4\u0015\u000e\u001c;feR\u0011\u0001e\u0016\u0005\u00061\u0016\u0001\r!W\u0001\u0002cB!q\"\u0010\u0012[!\ty1,\u0003\u0002]\u0013\t9!i\\8mK\u0006t\u0007\u0006\u0002\u0001_C\n\u0004\"aD0\n\u0005\u0001L!\u0001E*fe&\fGNV3sg&|g.V%E\u0003\u00151\u0018\r\\;f=\u0005\u0019\u0001
  #12 = Utf8               serialVersionUID
  #13 = Utf8               J
  #14 = Long               3l
  #16 = Utf8               map
  #17 = Utf8               (Lscala/Function1;)Ljava/lang/Object;
  #18 = Utf8               <B:Ljava/lang/Object;>(Lscala/Function1<TA;TB;>;)TCC;
  #19 = Utf8               f
  #20 = Utf8               flatMap
  #21 = Utf8               <B:Ljava/lang/Object;>(Lscala/Function1<TA;Lscala/collection/IterableOnce<TB;>;>;)TCC;
  #22 = Utf8               foreach
  #23 = Utf8               (Lscala/Function1;)V
  #24 = Utf8               <U:Ljava/lang/Object;>(Lscala/Function1<TA;TU;>;)V
  #25 = Utf8               withFilter
  #26 = Utf8               (Lscala/Function1;)Lscala/collection/WithFilter;
  #27 = Utf8               (Lscala/Function1<TA;Ljava/lang/Object;>;)Lscala/collection/WithFilter<TA;TCC;>;
  #28 = Utf8               q
  #29 = Utf8               <init>
  #30 = Utf8               ()V
  #31 = NameAndType        #29:#30        // "<init>":()V
  #32 = Methodref          #5.#31         // java/lang/Object."<init>":()V
  #33 = Utf8               this
  #34 = Utf8               Lscala/collection/WithFilter;
  #35 = Utf8               ConstantValue
  #36 = Utf8               Signature
  #37 = Utf8               MethodParameters
  #38 = Utf8               Code
  #39 = Utf8               LineNumberTable
  #40 = Utf8               LocalVariableTable
  #41 = Utf8               SourceFile
  #42 = Utf8               RuntimeVisibleAnnotations
  #43 = Utf8               ScalaInlineInfo
  #44 = Utf8               ScalaSig
{
  private static final long serialVersionUID;
    descriptor: J
    flags: (0x001a) ACC_PRIVATE, ACC_STATIC, ACC_FINAL
    ConstantValue: long 3l

  public abstract <B extends java.lang.Object> CC map(scala.Function1<A, B>);
    descriptor: (Lscala/Function1;)Ljava/lang/Object;
    flags: (0x0401) ACC_PUBLIC, ACC_ABSTRACT
    Signature: #18                          // <B:Ljava/lang/Object;>(Lscala/Function1<TA;TB;>;)TCC;
    MethodParameters:
      Name                           Flags
      f                              final

  public abstract <B extends java.lang.Object> CC flatMap(scala.Function1<A, scala.collection.IterableOnce<B>>);
    descriptor: (Lscala/Function1;)Ljava/lang/Object;
    flags: (0x0401) ACC_PUBLIC, ACC_ABSTRACT
    Signature: #21                          // <B:Ljava/lang/Object;>(Lscala/Function1<TA;Lscala/collection/IterableOnce<TB;>;>;)TCC;
    MethodParameters:
      Name                           Flags
      f                              final

  public abstract <U extends java.lang.Object> void foreach(scala.Function1<A, U>);
    descriptor: (Lscala/Function1;)V
    flags: (0x0401) ACC_PUBLIC, ACC_ABSTRACT
    Signature: #24                          // <U:Ljava/lang/Object;>(Lscala/Function1<TA;TU;>;)V
    MethodParameters:
      Name                           Flags
      f                              final

  public abstract scala.collection.WithFilter<A, CC> withFilter(scala.Function1<A, java.lang.Object>);
    descriptor: (Lscala/Function1;)Lscala/collection/WithFilter;
    flags: (0x0401) ACC_PUBLIC, ACC_ABSTRACT
    Signature: #27                          // (Lscala/Function1<TA;Ljava/lang/Object;>;)Lscala/collection/WithFilter<TA;TCC;>;
    MethodParameters:
      Name                           Flags
      q                              final

  public scala.collection.WithFilter();
    descriptor: ()V
    flags: (0x0001) ACC_PUBLIC
    Code:
      stack=1, locals=1, args_size=1
         0: aload_0
         1: invokespecial #32                 // Method java/lang/Object."<init>":()V
         4: return
      LineNumberTable:
        line 24: 0
      LocalVariableTable:
        Start  Length  Slot  Name   Signature
            0       5     0  this   Lscala/collection/WithFilter;
}
Signature: #3                           // <A:Ljava/lang/Object;CC:Ljava/lang/Object;>Ljava/lang/Object;Ljava/io/Serializable;
SourceFile: "WithFilter.scala"
RuntimeVisibleAnnotations:
  0: #9(#10=s#11)
    scala.reflect.ScalaSignature(
      bytes="\u0006\u0005\r4QAB\u0004\u0002\u00021AQA\b\u0001\u0005\u0002}AQa\r\u0001\u0007\u0002QBQa\u0010\u0001\u0007\u0002\u0001CQA\u0013\u0001\u0007\u0002-CQ!\u0016\u0001\u0007\u0002Y\u0013!bV5uQ\u001aKG\u000e^3s\u0015\tA\u0011\"\u0001\u0006d_2dWm\u0019;j_:T\u0011AC\u0001\u0006g\u000e\fG.Y\u0002\u0001+\riAEL\n\u0004\u00019\u0011\u0002CA\b\u0011\u001b\u0005I\u0011BA\t\n\u0005\u0019\te.\u001f*fMB\u00111c\u0007\b\u0003)eq!!\u0006\r\u000e\u0003YQ!aF\u0006\u0002\rq\u0012xn\u001c;?\u0013\u0005Q\u0011B\u0001\u000e\n\u0003\u001d\u0001\u0018mY6bO\u0016L!\u0001H\u000f\u0003\u0019M+\'/[1mSj\f\'\r\\3\u000b\u0005iI\u0011A\u0002\u001fj]&$h\bF\u0001!!\u0011\t\u0003AI\u0017\u000e\u0003\u001d\u0001\"a\t\u0013\r\u0001\u00111Q\u0005\u0001CC\u0002\u0019\u0012\u0011!Q\t\u0003O)\u0002\"a\u0004\u0015\n\u0005%J!a\u0002(pi\"Lgn\u001a\t\u0003\u001f-J!\u0001L\u0005\u0003\u0007\u0005s\u0017\u0010\u0005\u0002$]\u00111q\u0006\u0001CC\u0002A\u0012!aQ\"\u0016\u0005\u0019\nD!\u0002\u001a/\u0005\u00041#\u0001B0%IE\n1!\\1q+\t)\u0004\b\u0006\u00027uA\u00191EL\u001c\u0011\u0005\rBD!B\u001d\u0003\u0005\u00041#!\u0001\"\t\u000bm\u0012\u0001\u0019\u0001\u001f\u0002\u0003\u0019\u0004BaD\u001f#o%\u0011a(\u0003\u0002\n\rVt7\r^5p]F\nqA\u001a7bi6\u000b\u0007/\u0006\u0002B\tR\u0011!)\u0012\t\u0004G9\u001a\u0005CA\u0012E\t\u0015I4A1\u0001\'\u0011\u0015Y4\u00011\u0001G!\u0011yQHI$\u0011\u0007\u0005B5)\u0003\u0002J\u000f\ta\u0011\n^3sC\ndWm\u00148dK\u00069am\u001c:fC\u000eDWC\u0001\'T)\ti\u0005\u000b\u0005\u0002\u0010\u001d&\u0011q*\u0003\u0002\u0005+:LG\u000fC\u0003<\t\u0001\u0007\u0011\u000b\u0005\u0003\u0010{\t\u0012\u0006CA\u0012T\t\u0015!FA1\u0001\'\u0005\u0005)\u0016AC<ji\"4\u0015\u000e\u001c;feR\u0011\u0001e\u0016\u0005\u00061\u0016\u0001\r!W\u0001\u0002cB!q\"\u0010\u0012[!\ty1,\u0003\u0002]\u0013\t9!i\\8mK\u0006t\u0007\u0006\u0002\u0001_C\n\u0004\"aD0\n\u0005\u0001L!\u0001E*fe&\fGNV3sg&|g.V%E\u0003\u00151\u0018\r\\;f=\u0005\u0019\u0001"
    )
  ScalaInlineInfo: length = 0x1D (unknown attribute)
   01 00 00 05 00 1D 00 1E 00 00 14 00 11 00 00 16
   00 17 00 00 10 00 11 00 00 19 00 1A 00
  ScalaSig: length = 0x3 (unknown attribute)
   05 02 00
