Classfile /Users/mw/Projects/slang-braindump/.jar/jar8/assemble/slang-braindump/assemble/content/coursier/maven/Pom.class
  Last modified May 29, 2022; size 6073 bytes
  SHA-256 checksum b82b5c870a00eb4edf9e019614de9f0f43bcdb3532b1fe9b16d6140a28bc9439
  Compiled from "Pom.scala"
public final class coursier.maven.Pom
  minor version: 0
  major version: 52
  flags: (0x0031) ACC_PUBLIC, ACC_FINAL, ACC_SUPER
  this_class: #2                          // coursier/maven/Pom
  super_class: #4                         // java/lang/Object
  interfaces: 0, fields: 0, methods: 19, attributes: 4
Constant pool:
    #1 = Utf8               coursier/maven/Pom
    #2 = Class              #1            // coursier/maven/Pom
    #3 = Utf8               java/lang/Object
    #4 = Class              #3            // java/lang/Object
    #5 = Utf8               Pom.scala
    #6 = Utf8               Lscala/reflect/ScalaSignature;
    #7 = Utf8               bytes
    #8 = Utf8               \u0006\u0005\tMq!\u0002\u0012$\u0011\u0003Ac!\u0002\u0016$\u0011\u0003Y\u0003\"\u0002\u001a\u0002\t\u0003\u0019\u0004\"\u0002\u001b\u0002\t\u0003)\u0004\"\u0002/\u0002\t\u0013i\u0006bB;\u0002#\u0003%IA\u001e\u0005\n\u0003\u0007\t\u0011\u0013!C\u0005\u0003\u000bAq!!\u0003\u0002\t\u0013\tY\u0001C\u0004\u0002\u001e\u0005!\t!a\b\t\u000f\u0005M\u0012\u0001\"\u0003\u00026!9\u0011\u0011J\u0001\u0005\u0002\u0005-\u0003bBA,\u0003\u0011\u0005\u0011\u0011\f\u0005\b\u0003O\nA\u0011AA5\u0011\u001d\t)(\u0001C\u0001\u0003oBq!a!\u0002\t\u0003\t)\tC\u0004\u0002\u0012\u0006!\t!a%\t\u000f\u0005\u001d\u0016\u0001\"\u0001\u0002*\"I\u0011QW\u0001C\u0002\u0013\u0005\u0011q\u0017\u0005\t\u0003s\u000b\u0001\u0015!\u0003\u0002\u000e!I\u00111X\u0001C\u0002\u0013\u0005\u0011q\u0017\u0005\t\u0003{\u000b\u0001\u0015!\u0003\u0002\u000e!I\u0011qX\u0001C\u0002\u0013\u0005\u0011q\u0017\u0005\t\u0003\u0003\f\u0001\u0015!\u0003\u0002\u000e!I\u00111Y\u0001C\u0002\u0013\u0005\u0011q\u0017\u0005\t\u0003\u000b\f\u0001\u0015!\u0003\u0002\u000e!I\u0011qY\u0001C\u0002\u0013\u0005\u0011q\u0017\u0005\t\u0003\u0013\f\u0001\u0015!\u0003\u0002\u000e!I\u00111Z\u0001C\u0002\u0013\u0005\u0011Q\u001a\u0005\t\u0003?\f\u0001\u0015!\u0003\u0002P\"I\u0011\u0011]\u0001C\u0002\u0013\u0005\u0011q\u0017\u0005\t\u0003G\f\u0001\u0015!\u0003\u0002\u000e!9\u0011Q]\u0001\u0005\u0002\u0005\u001d\bbBAy\u0003\u0011\u0005\u00111\u001f\u0005\b\u0003\u007f\fA\u0011\u0001B\u0001\u0003\r\u0001v.\u001c\u0006\u0003I\u0015\nQ!\\1wK:T\u0011AJ\u0001\tG>,(o]5fe\u000e\u0001\u0001CA\u0015\u0002\u001b\u0005\u0019#a\u0001)p[N\u0011\u0011\u0001\f\t\u0003[Aj\u0011A\f\u0006\u0002_\u0005)1oY1mC&\u0011\u0011G\f\u0002\u0007\u0003:L(+\u001a4\u0002\rqJg.\u001b;?)\u0005A\u0013\u0001\u00039s_B,\'\u000f^=\u0015\u0005Yj\u0005\u0003B\u001c@\u0005*s!\u0001O\u001f\u000f\u0005ebT\"\u0001\u001e\u000b\u0005m:\u0013A\u0002\u001fs_>$h(C\u00010\u0013\tqd&A\u0004qC\u000e\\\u0017mZ3\n\u0005\u0001\u000b%AB#ji\",\'O\u0003\u0002?]A\u00111i\u0012\b\u0003\t\u0016\u0003\"!\u000f\u0018\n\u0005\u0019s\u0013A\u0002)sK\u0012,g-\u0003\u0002I\u0013\n11\u000b\u001e:j]\u001eT!A\u0012\u0018\u0011\t5Z%IQ\u0005\u0003\u0019:\u0012a\u0001V;qY\u0016\u0014\u0004\"\u0002(\u0004\u0001\u0004y\u0015\u0001B3mK6\u0004\"\u0001U-\u000f\u0005E3fB\u0001*U\u001d\tI4+C\u0001\'\u0013\t)V%\u0001\u0003vi&d\u0017BA,Y\u0003\rAV\u000e\u001c\u0006\u0003+\u0016J!AW.\u0003\t9{G-\u001a\u0006\u0003/b\u000ba!\\8ek2,G\u0003\u00020fO>\u0004BaN C?B\u0011\u0001mY\u0007\u0002C*\u0011!-J\u0001\u0005G>\u0014X-\u0003\u0002eC\n1Qj\u001c3vY\u0016DQA\u001a\u0003A\u0002=\u000bAA\\8eK\"9\u0001\u000e\u0002I\u0001\u0002\u0004I\u0017A\u00043fM\u0006,H\u000e^$s_V\u0004\u0018\n\u001a\t\u0004[)d\u0017BA6/\u0005\u0019y\u0005\u000f^5p]B\u0011\u0001-\\\u0005\u0003]\u0006\u0014Ab\u0014:hC:L\'0\u0019;j_:Dq\u0001\u001d\u0003\u0011\u0002\u0003\u0007\u0011/A\teK\u001a\fW\u000f\u001c;BeRLg-Y2u\u0013\u0012\u00042!\f6s!\t\u00017/\u0003\u0002uC\nQQj\u001c3vY\u0016t\u0015-\\3\u0002!5|G-\u001e7fI\u0011,g-Y;mi\u0012\u0012T#A<+\u0005%D8&A=\u0011\u0005i|X\"A>\u000b\u0005ql\u0018!C;oG\",7m[3e\u0015\tqh&\u0001\u0006b]:|G/\u0019;j_:L1!!\u0001|\u0005E)hn\u00195fG.,GMV1sS\u0006t7-Z\u0001\u0011[>$W\u000f\\3%I\u00164\u0017-\u001e7uIM*\"!a\u0002+\u0005ED\u0018a\u0003:fC\u00124VM]:j_:$B!!\u0004\u0002\u001cA!\u0011qBA\r\u001b\t\t\tB\u0003\u0003\u0002\u0014\u0005U\u0011\u0001\u00027b]\u001eT!!a\u0006\u0002\t)\fg/Y\u0005\u0004\u0011\u0006E\u0001\"\u00024\b\u0001\u0004y\u0015A\u00033fa\u0016tG-\u001a8dsR!\u0011\u0011EA\u0019!\u00159tHQA\u0012!\u0019i3*!\n\u0002,A\u0019\u0001-a\n\n\u0007\u0005%\u0012MA\u0007D_:4\u0017nZ;sCRLwN\u001c\t\u0004A\u00065\u0012bAA\u0018C\nQA)\u001a9f]\u0012,gnY=\t\u000b\u0019D\u0001\u0019A(\u0002#A\u0014xNZ5mK\u0006\u001bG/\u001b<bi&|g\u000e\u0006\u0003\u00028\u0005\u001d\u0003CB\u0017L\u0003s\t\t\u0005\u0005\u0003.U\u0006m\u0002cA\u0017\u0002>%\u0019\u0011q\b\u0018\u0003\u000f\t{w\u000e\\3b]B\u0019\u0001-a\u0011\n\u0007\u0005\u0015\u0013M\u0001\u0006BGRLg/\u0019;j_:DQAZ\u0005A\u0002=\u000bq\u0001\u001d:pM&dW\r\u0006\u0003\u0002N\u0005U\u0003#B\u001c@\u0005\u0006=\u0003c\u00011\u0002R%\u0019\u00111K1\u0003\u000fA\u0013xNZ5mK\")aM\u0003a\u0001\u001f\u0006a\u0001/Y2lC\u001eLgnZ(qiR!\u00111LA2!\u0011i#.!\u0018\u0011\u0007\u0001\fy&C\u0002\u0002b\u0005\u0014A\u0001V=qK\"1\u0011QM\u0006A\u0002=\u000b1\u0001]8n\u0003\u001d\u0001(o\u001c6fGR$B!a\u001b\u0002tA)qg\u0010\"\u0002nA\u0019\u0001-a\u001c\n\u0007\u0005E\u0014MA\u0004Qe>TWm\u0019;\t\r\u0005\u0015D\u00021\u0001P\u0003!1XM]:j_:\u001cH\u0003BA=\u0003\u0003\u0003RaN C\u0003w\u00022\u0001YA?\u0013\r\ty(\u0019\u0002\t-\u0016\u00148/[8og\")a-\u0004a\u0001\u001f\u0006y1O\\1qg\"|GOV3sg&|g\u000e\u0006\u0003\u0002\b\u0006=\u0005#B\u001c@\u0005\u0006%\u0005c\u00011\u0002\f&\u0019\u0011QR1\u0003\u001fMs\u0017\r]:i_R4VM]:j_:DQA\u001a\bA\u0002=\u000bacZ;fgN,Gm\u00158baNDw\u000e\u001e,feNLwN\u001c\u000b\t\u0003\u0013\u000b)*!\'\u0002\u001e\"1\u0011qS\bA\u0002\t\u000bqA^3sg&|g\u000e\u0003\u0004\u0002\u001c>\u0001\rAQ\u0001\ni&lWm\u001d;b[BDq!a(\u0010\u0001\u0004\t\t+A\u0006ck&dGMT;nE\u0016\u0014\bcA\u0017\u0002$&\u0019\u0011Q\u0015\u0018\u0003\u0007%sG/\u0001\nt]\u0006\u00048\u000f[8u-\u0016\u00148/[8oS:<G\u0003BAV\u0003g\u0003RaN C\u0003[\u00032\u0001YAX\u0013\r\t\t,\u0019\u0002\u0013\':\f\u0007o\u001d5piZ+\'o]5p]&tw\rC\u0003g!\u0001\u0007q*A\ffqR\u0014\u0018-\u0011;ue&\u0014W\u000f^3TKB\f\'/\u0019;peV\u0011\u0011QB\u0001\u0019Kb$(/Y!uiJL\'-\u001e;f\'\u0016\u0004\u0018M]1u_J\u0004\u0013\u0001F3yiJ\f\u0017\t\u001e;sS\n,H/\u001a)sK\u001aL\u00070A\u000bfqR\u0014\u0018-\u0011;ue&\u0014W\u000f^3Qe\u00164\u0017\u000e\u001f\u0011\u0002#\u0015DHO]1BiR\u0014\u0018NY;uK>\u0013x-\u0001\nfqR\u0014\u0018-\u0011;ue&\u0014W\u000f^3Pe\u001e\u0004\u0013AE3yiJ\f\u0017\t\u001e;sS\n,H/\u001a(b[\u0016\f1#\u001a=ue\u0006\fE\u000f\u001e:jEV$XMT1nK\u0002\nQ#\u001a=ue\u0006\fE\u000f\u001e:jEV$XMV3sg&|g.\u0001\ffqR\u0014\u0018-\u0011;ue&\u0014W\u000f^3WKJ\u001c\u0018n\u001c8!\u0003I)\u0007\u0010\u001e:b\u0003R$(/\u001b2vi\u0016\u0014\u0015m]3\u0016\u0005\u0005=\u0007CBAi\u00037\fi!\u0004\u0002\u0002T*!\u0011Q[Al\u0003%IW.\\;uC\ndWMC\u0002\u0002Z:\n!bY8mY\u0016\u001cG/[8o\u0013\u0011\ti.a5\u0003\u0007M+G/A\nfqR\u0014\u0018-\u0011;ue&\u0014W\u000f^3CCN,\u0007%\u0001\rfqR\u0014\u0018-\u0011;ue&\u0014W\u000f^3Ee>\u0004\bK]3gSb\f\u0011$\u001a=ue\u0006\fE\u000f\u001e:jEV$X\r\u0012:paB\u0013XMZ5yA\u0005qQ\r\u001f;sC\u0006#HO]5ckR,G\u0003BAu\u0003[\u0004RaN C\u0003W\u0004B!L&`\u0005\"1\u0011q^\u0010A\u0002\t\u000b\u0011a]\u0001\u0010Kb$(/Y!uiJL\'-\u001e;fgR!\u0011Q_A\u007f!\u00159tHQA|!\u00159\u0014\u0011`Av\u0013\r\tY0\u0011\u0002\u0004\'\u0016\f\bBBAxA\u0001\u0007!)A\u0010bI\u0012|\u0005\u000f^5p]\u0006dG)\u001a9f]\u0012,gnY5fg&s7i\u001c8gS\u001e$\u0002\"!\u001c\u0003\u0004\t\u001d!q\u0002\u0005\b\u0005\u000b\t\u0003\u0019AA7\u0003\u0011\u0001(o\u001c6\t\u000f\t%\u0011\u00051\u0001\u0003\f\u0005YaM]8n\u0007>tg-[4t!\u0015\u0019%QBA\u0013\u0013\r\ti.\u0013\u0005\b\u0005#\t\u0003\u0019AA\u0013\u00039y\u0007\u000f^5p]\u0006d7i\u001c8gS\u001e\u0004
    #9 = Utf8               coursier/util/Xml$Node
   #10 = Class              #9            // coursier/util/Xml$Node
   #11 = Utf8               coursier/util/Xml
   #12 = Class              #11           // coursier/util/Xml
   #13 = Utf8               Node
   #14 = Utf8               addOptionalDependenciesInConfig
   #15 = Utf8               (Lcoursier/core/Project;Lscala/collection/immutable/Set;Ljava/lang/String;)Lcoursier/core/Project;
   #16 = Utf8               (Lcoursier/core/Project;Lscala/collection/immutable/Set<Lcoursier/core/Configuration;>;Ljava/lang/String;)Lcoursier/core/Project;
   #17 = Utf8               proj
   #18 = Utf8               fromConfigs
   #19 = Utf8               optionalConfig
   #20 = Utf8               coursier/maven/Pom$
   #21 = Class              #20           // coursier/maven/Pom$
   #22 = Utf8               MODULE$
   #23 = Utf8               Lcoursier/maven/Pom$;
   #24 = NameAndType        #22:#23       // MODULE$:Lcoursier/maven/Pom$;
   #25 = Fieldref           #21.#24       // coursier/maven/Pom$.MODULE$:Lcoursier/maven/Pom$;
   #26 = NameAndType        #14:#15       // addOptionalDependenciesInConfig:(Lcoursier/core/Project;Lscala/collection/immutable/Set;Ljava/lang/String;)Lcoursier/core/Project;
   #27 = Methodref          #21.#26       // coursier/maven/Pom$.addOptionalDependenciesInConfig:(Lcoursier/core/Project;Lscala/collection/immutable/Set;Ljava/lang/String;)Lcoursier/core/Project;
   #28 = Utf8               extraAttributes
   #29 = Utf8               (Ljava/lang/String;)Lscala/util/Either;
   #30 = Utf8               (Ljava/lang/String;)Lscala/util/Either<Ljava/lang/String;Lscala/collection/immutable/Seq<Lscala/Tuple2<Lcoursier/core/Module;Ljava/lang/String;>;>;>;
   #31 = Utf8               s
   #32 = NameAndType        #28:#29       // extraAttributes:(Ljava/lang/String;)Lscala/util/Either;
   #33 = Methodref          #21.#32       // coursier/maven/Pom$.extraAttributes:(Ljava/lang/String;)Lscala/util/Either;
   #34 = Utf8               extraAttribute
   #35 = Utf8               (Ljava/lang/String;)Lscala/util/Either<Ljava/lang/String;Lscala/Tuple2<Lcoursier/core/Module;Ljava/lang/String;>;>;
   #36 = NameAndType        #34:#29       // extraAttribute:(Ljava/lang/String;)Lscala/util/Either;
   #37 = Methodref          #21.#36       // coursier/maven/Pom$.extraAttribute:(Ljava/lang/String;)Lscala/util/Either;
   #38 = Utf8               extraAttributeDropPrefix
   #39 = Utf8               ()Ljava/lang/String;
   #40 = NameAndType        #38:#39       // extraAttributeDropPrefix:()Ljava/lang/String;
   #41 = Methodref          #21.#40       // coursier/maven/Pom$.extraAttributeDropPrefix:()Ljava/lang/String;
   #42 = Utf8               extraAttributeBase
   #43 = Utf8               ()Lscala/collection/immutable/Set;
   #44 = Utf8               ()Lscala/collection/immutable/Set<Ljava/lang/String;>;
   #45 = NameAndType        #42:#43       // extraAttributeBase:()Lscala/collection/immutable/Set;
   #46 = Methodref          #21.#45       // coursier/maven/Pom$.extraAttributeBase:()Lscala/collection/immutable/Set;
   #47 = Utf8               extraAttributeVersion
   #48 = NameAndType        #47:#39       // extraAttributeVersion:()Ljava/lang/String;
   #49 = Methodref          #21.#48       // coursier/maven/Pom$.extraAttributeVersion:()Ljava/lang/String;
   #50 = Utf8               extraAttributeName
   #51 = NameAndType        #50:#39       // extraAttributeName:()Ljava/lang/String;
   #52 = Methodref          #21.#51       // coursier/maven/Pom$.extraAttributeName:()Ljava/lang/String;
   #53 = Utf8               extraAttributeOrg
   #54 = NameAndType        #53:#39       // extraAttributeOrg:()Ljava/lang/String;
   #55 = Methodref          #21.#54       // coursier/maven/Pom$.extraAttributeOrg:()Ljava/lang/String;
   #56 = Utf8               extraAttributePrefix
   #57 = NameAndType        #56:#39       // extraAttributePrefix:()Ljava/lang/String;
   #58 = Methodref          #21.#57       // coursier/maven/Pom$.extraAttributePrefix:()Ljava/lang/String;
   #59 = Utf8               extraAttributeSeparator
   #60 = NameAndType        #59:#39       // extraAttributeSeparator:()Ljava/lang/String;
   #61 = Methodref          #21.#60       // coursier/maven/Pom$.extraAttributeSeparator:()Ljava/lang/String;
   #62 = Utf8               snapshotVersioning
   #63 = Utf8               (Lcoursier/util/Xml$Node;)Lscala/util/Either;
   #64 = Utf8               (Lcoursier/util/Xml$Node;)Lscala/util/Either<Ljava/lang/String;Lcoursier/core/SnapshotVersioning;>;
   #65 = Utf8               node
   #66 = NameAndType        #62:#63       // snapshotVersioning:(Lcoursier/util/Xml$Node;)Lscala/util/Either;
   #67 = Methodref          #21.#66       // coursier/maven/Pom$.snapshotVersioning:(Lcoursier/util/Xml$Node;)Lscala/util/Either;
   #68 = Utf8               guessedSnapshotVersion
   #69 = Utf8               (Ljava/lang/String;Ljava/lang/String;I)Lcoursier/core/SnapshotVersion;
   #70 = Utf8               version
   #71 = Utf8               timestamp
   #72 = Utf8               buildNumber
   #73 = NameAndType        #68:#69       // guessedSnapshotVersion:(Ljava/lang/String;Ljava/lang/String;I)Lcoursier/core/SnapshotVersion;
   #74 = Methodref          #21.#73       // coursier/maven/Pom$.guessedSnapshotVersion:(Ljava/lang/String;Ljava/lang/String;I)Lcoursier/core/SnapshotVersion;
   #75 = Utf8               snapshotVersion
   #76 = Utf8               (Lcoursier/util/Xml$Node;)Lscala/util/Either<Ljava/lang/String;Lcoursier/core/SnapshotVersion;>;
   #77 = NameAndType        #75:#63       // snapshotVersion:(Lcoursier/util/Xml$Node;)Lscala/util/Either;
   #78 = Methodref          #21.#77       // coursier/maven/Pom$.snapshotVersion:(Lcoursier/util/Xml$Node;)Lscala/util/Either;
   #79 = Utf8               versions
   #80 = Utf8               (Lcoursier/util/Xml$Node;)Lscala/util/Either<Ljava/lang/String;Lcoursier/core/Versions;>;
   #81 = NameAndType        #79:#63       // versions:(Lcoursier/util/Xml$Node;)Lscala/util/Either;
   #82 = Methodref          #21.#81       // coursier/maven/Pom$.versions:(Lcoursier/util/Xml$Node;)Lscala/util/Either;
   #83 = Utf8               project
   #84 = Utf8               (Lcoursier/util/Xml$Node;)Lscala/util/Either<Ljava/lang/String;Lcoursier/core/Project;>;
   #85 = Utf8               pom
   #86 = NameAndType        #83:#63       // project:(Lcoursier/util/Xml$Node;)Lscala/util/Either;
   #87 = Methodref          #21.#86       // coursier/maven/Pom$.project:(Lcoursier/util/Xml$Node;)Lscala/util/Either;
   #88 = Utf8               packagingOpt
   #89 = Utf8               (Lcoursier/util/Xml$Node;)Lscala/Option;
   #90 = Utf8               (Lcoursier/util/Xml$Node;)Lscala/Option<Lcoursier/core/Type;>;
   #91 = NameAndType        #88:#89       // packagingOpt:(Lcoursier/util/Xml$Node;)Lscala/Option;
   #92 = Methodref          #21.#91       // coursier/maven/Pom$.packagingOpt:(Lcoursier/util/Xml$Node;)Lscala/Option;
   #93 = Utf8               profile
   #94 = Utf8               (Lcoursier/util/Xml$Node;)Lscala/util/Either<Ljava/lang/String;Lcoursier/core/Profile;>;
   #95 = NameAndType        #93:#63       // profile:(Lcoursier/util/Xml$Node;)Lscala/util/Either;
   #96 = Methodref          #21.#95       // coursier/maven/Pom$.profile:(Lcoursier/util/Xml$Node;)Lscala/util/Either;
   #97 = Utf8               dependency
   #98 = Utf8               (Lcoursier/util/Xml$Node;)Lscala/util/Either<Ljava/lang/String;Lscala/Tuple2<Lcoursier/core/Configuration;Lcoursier/core/Dependency;>;>;
   #99 = NameAndType        #97:#63       // dependency:(Lcoursier/util/Xml$Node;)Lscala/util/Either;
  #100 = Methodref          #21.#99       // coursier/maven/Pom$.dependency:(Lcoursier/util/Xml$Node;)Lscala/util/Either;
  #101 = Utf8               property
  #102 = Utf8               (Lcoursier/util/Xml$Node;)Lscala/util/Either<Ljava/lang/String;Lscala/Tuple2<Ljava/lang/String;Ljava/lang/String;>;>;
  #103 = Utf8               elem
  #104 = NameAndType        #101:#63      // property:(Lcoursier/util/Xml$Node;)Lscala/util/Either;
  #105 = Methodref          #21.#104      // coursier/maven/Pom$.property:(Lcoursier/util/Xml$Node;)Lscala/util/Either;
  #106 = Utf8               Code
  #107 = Utf8               Signature
  #108 = Utf8               MethodParameters
  #109 = Utf8               InnerClasses
  #110 = Utf8               SourceFile
  #111 = Utf8               RuntimeVisibleAnnotations
  #112 = Utf8               ScalaSig
{
  public static coursier.core.Project addOptionalDependenciesInConfig(coursier.core.Project, scala.collection.immutable.Set<coursier.core.Configuration>, java.lang.String);
    descriptor: (Lcoursier/core/Project;Lscala/collection/immutable/Set;Ljava/lang/String;)Lcoursier/core/Project;
    flags: (0x0009) ACC_PUBLIC, ACC_STATIC
    Code:
      stack=4, locals=3, args_size=3
         0: getstatic     #25                 // Field coursier/maven/Pom$.MODULE$:Lcoursier/maven/Pom$;
         3: aload_0
         4: aload_1
         5: aload_2
         6: invokevirtual #27                 // Method coursier/maven/Pom$.addOptionalDependenciesInConfig:(Lcoursier/core/Project;Lscala/collection/immutable/Set;Ljava/lang/String;)Lcoursier/core/Project;
         9: areturn
    Signature: #16                          // (Lcoursier/core/Project;Lscala/collection/immutable/Set<Lcoursier/core/Configuration;>;Ljava/lang/String;)Lcoursier/core/Project;
    MethodParameters:
      Name                           Flags
      proj                           final
      fromConfigs                    final
      optionalConfig                 final

  public static scala.util.Either<java.lang.String, scala.collection.immutable.Seq<scala.Tuple2<coursier.core.Module, java.lang.String>>> extraAttributes(java.lang.String);
    descriptor: (Ljava/lang/String;)Lscala/util/Either;
    flags: (0x0009) ACC_PUBLIC, ACC_STATIC
    Code:
      stack=2, locals=1, args_size=1
         0: getstatic     #25                 // Field coursier/maven/Pom$.MODULE$:Lcoursier/maven/Pom$;
         3: aload_0
         4: invokevirtual #33                 // Method coursier/maven/Pom$.extraAttributes:(Ljava/lang/String;)Lscala/util/Either;
         7: areturn
    Signature: #30                          // (Ljava/lang/String;)Lscala/util/Either<Ljava/lang/String;Lscala/collection/immutable/Seq<Lscala/Tuple2<Lcoursier/core/Module;Ljava/lang/String;>;>;>;
    MethodParameters:
      Name                           Flags
      s                              final

  public static scala.util.Either<java.lang.String, scala.Tuple2<coursier.core.Module, java.lang.String>> extraAttribute(java.lang.String);
    descriptor: (Ljava/lang/String;)Lscala/util/Either;
    flags: (0x0009) ACC_PUBLIC, ACC_STATIC
    Code:
      stack=2, locals=1, args_size=1
         0: getstatic     #25                 // Field coursier/maven/Pom$.MODULE$:Lcoursier/maven/Pom$;
         3: aload_0
         4: invokevirtual #37                 // Method coursier/maven/Pom$.extraAttribute:(Ljava/lang/String;)Lscala/util/Either;
         7: areturn
    Signature: #35                          // (Ljava/lang/String;)Lscala/util/Either<Ljava/lang/String;Lscala/Tuple2<Lcoursier/core/Module;Ljava/lang/String;>;>;
    MethodParameters:
      Name                           Flags
      s                              final

  public static java.lang.String extraAttributeDropPrefix();
    descriptor: ()Ljava/lang/String;
    flags: (0x0009) ACC_PUBLIC, ACC_STATIC
    Code:
      stack=1, locals=0, args_size=0
         0: getstatic     #25                 // Field coursier/maven/Pom$.MODULE$:Lcoursier/maven/Pom$;
         3: invokevirtual #41                 // Method coursier/maven/Pom$.extraAttributeDropPrefix:()Ljava/lang/String;
         6: areturn

  public static scala.collection.immutable.Set<java.lang.String> extraAttributeBase();
    descriptor: ()Lscala/collection/immutable/Set;
    flags: (0x0009) ACC_PUBLIC, ACC_STATIC
    Code:
      stack=1, locals=0, args_size=0
         0: getstatic     #25                 // Field coursier/maven/Pom$.MODULE$:Lcoursier/maven/Pom$;
         3: invokevirtual #46                 // Method coursier/maven/Pom$.extraAttributeBase:()Lscala/collection/immutable/Set;
         6: areturn
    Signature: #44                          // ()Lscala/collection/immutable/Set<Ljava/lang/String;>;

  public static java.lang.String extraAttributeVersion();
    descriptor: ()Ljava/lang/String;
    flags: (0x0009) ACC_PUBLIC, ACC_STATIC
    Code:
      stack=1, locals=0, args_size=0
         0: getstatic     #25                 // Field coursier/maven/Pom$.MODULE$:Lcoursier/maven/Pom$;
         3: invokevirtual #49                 // Method coursier/maven/Pom$.extraAttributeVersion:()Ljava/lang/String;
         6: areturn

  public static java.lang.String extraAttributeName();
    descriptor: ()Ljava/lang/String;
    flags: (0x0009) ACC_PUBLIC, ACC_STATIC
    Code:
      stack=1, locals=0, args_size=0
         0: getstatic     #25                 // Field coursier/maven/Pom$.MODULE$:Lcoursier/maven/Pom$;
         3: invokevirtual #52                 // Method coursier/maven/Pom$.extraAttributeName:()Ljava/lang/String;
         6: areturn

  public static java.lang.String extraAttributeOrg();
    descriptor: ()Ljava/lang/String;
    flags: (0x0009) ACC_PUBLIC, ACC_STATIC
    Code:
      stack=1, locals=0, args_size=0
         0: getstatic     #25                 // Field coursier/maven/Pom$.MODULE$:Lcoursier/maven/Pom$;
         3: invokevirtual #55                 // Method coursier/maven/Pom$.extraAttributeOrg:()Ljava/lang/String;
         6: areturn

  public static java.lang.String extraAttributePrefix();
    descriptor: ()Ljava/lang/String;
    flags: (0x0009) ACC_PUBLIC, ACC_STATIC
    Code:
      stack=1, locals=0, args_size=0
         0: getstatic     #25                 // Field coursier/maven/Pom$.MODULE$:Lcoursier/maven/Pom$;
         3: invokevirtual #58                 // Method coursier/maven/Pom$.extraAttributePrefix:()Ljava/lang/String;
         6: areturn

  public static java.lang.String extraAttributeSeparator();
    descriptor: ()Ljava/lang/String;
    flags: (0x0009) ACC_PUBLIC, ACC_STATIC
    Code:
      stack=1, locals=0, args_size=0
         0: getstatic     #25                 // Field coursier/maven/Pom$.MODULE$:Lcoursier/maven/Pom$;
         3: invokevirtual #61                 // Method coursier/maven/Pom$.extraAttributeSeparator:()Ljava/lang/String;
         6: areturn

  public static scala.util.Either<java.lang.String, coursier.core.SnapshotVersioning> snapshotVersioning(coursier.util.Xml$Node);
    descriptor: (Lcoursier/util/Xml$Node;)Lscala/util/Either;
    flags: (0x0009) ACC_PUBLIC, ACC_STATIC
    Code:
      stack=2, locals=1, args_size=1
         0: getstatic     #25                 // Field coursier/maven/Pom$.MODULE$:Lcoursier/maven/Pom$;
         3: aload_0
         4: invokevirtual #67                 // Method coursier/maven/Pom$.snapshotVersioning:(Lcoursier/util/Xml$Node;)Lscala/util/Either;
         7: areturn
    Signature: #64                          // (Lcoursier/util/Xml$Node;)Lscala/util/Either<Ljava/lang/String;Lcoursier/core/SnapshotVersioning;>;
    MethodParameters:
      Name                           Flags
      node                           final

  public static coursier.core.SnapshotVersion guessedSnapshotVersion(java.lang.String, java.lang.String, int);
    descriptor: (Ljava/lang/String;Ljava/lang/String;I)Lcoursier/core/SnapshotVersion;
    flags: (0x0009) ACC_PUBLIC, ACC_STATIC
    Code:
      stack=4, locals=3, args_size=3
         0: getstatic     #25                 // Field coursier/maven/Pom$.MODULE$:Lcoursier/maven/Pom$;
         3: aload_0
         4: aload_1
         5: iload_2
         6: invokevirtual #74                 // Method coursier/maven/Pom$.guessedSnapshotVersion:(Ljava/lang/String;Ljava/lang/String;I)Lcoursier/core/SnapshotVersion;
         9: areturn
    MethodParameters:
      Name                           Flags
      version                        final
      timestamp                      final
      buildNumber                    final

  public static scala.util.Either<java.lang.String, coursier.core.SnapshotVersion> snapshotVersion(coursier.util.Xml$Node);
    descriptor: (Lcoursier/util/Xml$Node;)Lscala/util/Either;
    flags: (0x0009) ACC_PUBLIC, ACC_STATIC
    Code:
      stack=2, locals=1, args_size=1
         0: getstatic     #25                 // Field coursier/maven/Pom$.MODULE$:Lcoursier/maven/Pom$;
         3: aload_0
         4: invokevirtual #78                 // Method coursier/maven/Pom$.snapshotVersion:(Lcoursier/util/Xml$Node;)Lscala/util/Either;
         7: areturn
    Signature: #76                          // (Lcoursier/util/Xml$Node;)Lscala/util/Either<Ljava/lang/String;Lcoursier/core/SnapshotVersion;>;
    MethodParameters:
      Name                           Flags
      node                           final

  public static scala.util.Either<java.lang.String, coursier.core.Versions> versions(coursier.util.Xml$Node);
    descriptor: (Lcoursier/util/Xml$Node;)Lscala/util/Either;
    flags: (0x0009) ACC_PUBLIC, ACC_STATIC
    Code:
      stack=2, locals=1, args_size=1
         0: getstatic     #25                 // Field coursier/maven/Pom$.MODULE$:Lcoursier/maven/Pom$;
         3: aload_0
         4: invokevirtual #82                 // Method coursier/maven/Pom$.versions:(Lcoursier/util/Xml$Node;)Lscala/util/Either;
         7: areturn
    Signature: #80                          // (Lcoursier/util/Xml$Node;)Lscala/util/Either<Ljava/lang/String;Lcoursier/core/Versions;>;
    MethodParameters:
      Name                           Flags
      node                           final

  public static scala.util.Either<java.lang.String, coursier.core.Project> project(coursier.util.Xml$Node);
    descriptor: (Lcoursier/util/Xml$Node;)Lscala/util/Either;
    flags: (0x0009) ACC_PUBLIC, ACC_STATIC
    Code:
      stack=2, locals=1, args_size=1
         0: getstatic     #25                 // Field coursier/maven/Pom$.MODULE$:Lcoursier/maven/Pom$;
         3: aload_0
         4: invokevirtual #87                 // Method coursier/maven/Pom$.project:(Lcoursier/util/Xml$Node;)Lscala/util/Either;
         7: areturn
    Signature: #84                          // (Lcoursier/util/Xml$Node;)Lscala/util/Either<Ljava/lang/String;Lcoursier/core/Project;>;
    MethodParameters:
      Name                           Flags
      pom                            final

  public static scala.Option<coursier.core.Type> packagingOpt(coursier.util.Xml$Node);
    descriptor: (Lcoursier/util/Xml$Node;)Lscala/Option;
    flags: (0x0009) ACC_PUBLIC, ACC_STATIC
    Code:
      stack=2, locals=1, args_size=1
         0: getstatic     #25                 // Field coursier/maven/Pom$.MODULE$:Lcoursier/maven/Pom$;
         3: aload_0
         4: invokevirtual #92                 // Method coursier/maven/Pom$.packagingOpt:(Lcoursier/util/Xml$Node;)Lscala/Option;
         7: areturn
    Signature: #90                          // (Lcoursier/util/Xml$Node;)Lscala/Option<Lcoursier/core/Type;>;
    MethodParameters:
      Name                           Flags
      pom                            final

  public static scala.util.Either<java.lang.String, coursier.core.Profile> profile(coursier.util.Xml$Node);
    descriptor: (Lcoursier/util/Xml$Node;)Lscala/util/Either;
    flags: (0x0009) ACC_PUBLIC, ACC_STATIC
    Code:
      stack=2, locals=1, args_size=1
         0: getstatic     #25                 // Field coursier/maven/Pom$.MODULE$:Lcoursier/maven/Pom$;
         3: aload_0
         4: invokevirtual #96                 // Method coursier/maven/Pom$.profile:(Lcoursier/util/Xml$Node;)Lscala/util/Either;
         7: areturn
    Signature: #94                          // (Lcoursier/util/Xml$Node;)Lscala/util/Either<Ljava/lang/String;Lcoursier/core/Profile;>;
    MethodParameters:
      Name                           Flags
      node                           final

  public static scala.util.Either<java.lang.String, scala.Tuple2<coursier.core.Configuration, coursier.core.Dependency>> dependency(coursier.util.Xml$Node);
    descriptor: (Lcoursier/util/Xml$Node;)Lscala/util/Either;
    flags: (0x0009) ACC_PUBLIC, ACC_STATIC
    Code:
      stack=2, locals=1, args_size=1
         0: getstatic     #25                 // Field coursier/maven/Pom$.MODULE$:Lcoursier/maven/Pom$;
         3: aload_0
         4: invokevirtual #100                // Method coursier/maven/Pom$.dependency:(Lcoursier/util/Xml$Node;)Lscala/util/Either;
         7: areturn
    Signature: #98                          // (Lcoursier/util/Xml$Node;)Lscala/util/Either<Ljava/lang/String;Lscala/Tuple2<Lcoursier/core/Configuration;Lcoursier/core/Dependency;>;>;
    MethodParameters:
      Name                           Flags
      node                           final

  public static scala.util.Either<java.lang.String, scala.Tuple2<java.lang.String, java.lang.String>> property(coursier.util.Xml$Node);
    descriptor: (Lcoursier/util/Xml$Node;)Lscala/util/Either;
    flags: (0x0009) ACC_PUBLIC, ACC_STATIC
    Code:
      stack=2, locals=1, args_size=1
         0: getstatic     #25                 // Field coursier/maven/Pom$.MODULE$:Lcoursier/maven/Pom$;
         3: aload_0
         4: invokevirtual #105                // Method coursier/maven/Pom$.property:(Lcoursier/util/Xml$Node;)Lscala/util/Either;
         7: areturn
    Signature: #102                         // (Lcoursier/util/Xml$Node;)Lscala/util/Either<Ljava/lang/String;Lscala/Tuple2<Ljava/lang/String;Ljava/lang/String;>;>;
    MethodParameters:
      Name                           Flags
      elem                           final
}
InnerClasses:
  public static #13= #10 of #12;          // Node=class coursier/util/Xml$Node of class coursier/util/Xml
SourceFile: "Pom.scala"
RuntimeVisibleAnnotations:
  0: #6(#7=s#8)
    scala.reflect.ScalaSignature(
      bytes="\u0006\u0005\tMq!\u0002\u0012$\u0011\u0003Ac!\u0002\u0016$\u0011\u0003Y\u0003\"\u0002\u001a\u0002\t\u0003\u0019\u0004\"\u0002\u001b\u0002\t\u0003)\u0004\"\u0002/\u0002\t\u0013i\u0006bB;\u0002#\u0003%IA\u001e\u0005\n\u0003\u0007\t\u0011\u0013!C\u0005\u0003\u000bAq!!\u0003\u0002\t\u0013\tY\u0001C\u0004\u0002\u001e\u0005!\t!a\b\t\u000f\u0005M\u0012\u0001\"\u0003\u00026!9\u0011\u0011J\u0001\u0005\u0002\u0005-\u0003bBA,\u0003\u0011\u0005\u0011\u0011\f\u0005\b\u0003O\nA\u0011AA5\u0011\u001d\t)(\u0001C\u0001\u0003oBq!a!\u0002\t\u0003\t)\tC\u0004\u0002\u0012\u0006!\t!a%\t\u000f\u0005\u001d\u0016\u0001\"\u0001\u0002*\"I\u0011QW\u0001C\u0002\u0013\u0005\u0011q\u0017\u0005\t\u0003s\u000b\u0001\u0015!\u0003\u0002\u000e!I\u00111X\u0001C\u0002\u0013\u0005\u0011q\u0017\u0005\t\u0003{\u000b\u0001\u0015!\u0003\u0002\u000e!I\u0011qX\u0001C\u0002\u0013\u0005\u0011q\u0017\u0005\t\u0003\u0003\f\u0001\u0015!\u0003\u0002\u000e!I\u00111Y\u0001C\u0002\u0013\u0005\u0011q\u0017\u0005\t\u0003\u000b\f\u0001\u0015!\u0003\u0002\u000e!I\u0011qY\u0001C\u0002\u0013\u0005\u0011q\u0017\u0005\t\u0003\u0013\f\u0001\u0015!\u0003\u0002\u000e!I\u00111Z\u0001C\u0002\u0013\u0005\u0011Q\u001a\u0005\t\u0003?\f\u0001\u0015!\u0003\u0002P\"I\u0011\u0011]\u0001C\u0002\u0013\u0005\u0011q\u0017\u0005\t\u0003G\f\u0001\u0015!\u0003\u0002\u000e!9\u0011Q]\u0001\u0005\u0002\u0005\u001d\bbBAy\u0003\u0011\u0005\u00111\u001f\u0005\b\u0003\u007f\fA\u0011\u0001B\u0001\u0003\r\u0001v.\u001c\u0006\u0003I\u0015\nQ!\\1wK:T\u0011AJ\u0001\tG>,(o]5fe\u000e\u0001\u0001CA\u0015\u0002\u001b\u0005\u0019#a\u0001)p[N\u0011\u0011\u0001\f\t\u0003[Aj\u0011A\f\u0006\u0002_\u0005)1oY1mC&\u0011\u0011G\f\u0002\u0007\u0003:L(+\u001a4\u0002\rqJg.\u001b;?)\u0005A\u0013\u0001\u00039s_B,\'\u000f^=\u0015\u0005Yj\u0005\u0003B\u001c@\u0005*s!\u0001O\u001f\u000f\u0005ebT\"\u0001\u001e\u000b\u0005m:\u0013A\u0002\u001fs_>$h(C\u00010\u0013\tqd&A\u0004qC\u000e\\\u0017mZ3\n\u0005\u0001\u000b%AB#ji\",\'O\u0003\u0002?]A\u00111i\u0012\b\u0003\t\u0016\u0003\"!\u000f\u0018\n\u0005\u0019s\u0013A\u0002)sK\u0012,g-\u0003\u0002I\u0013\n11\u000b\u001e:j]\u001eT!A\u0012\u0018\u0011\t5Z%IQ\u0005\u0003\u0019:\u0012a\u0001V;qY\u0016\u0014\u0004\"\u0002(\u0004\u0001\u0004y\u0015\u0001B3mK6\u0004\"\u0001U-\u000f\u0005E3fB\u0001*U\u001d\tI4+C\u0001\'\u0013\t)V%\u0001\u0003vi&d\u0017BA,Y\u0003\rAV\u000e\u001c\u0006\u0003+\u0016J!AW.\u0003\t9{G-\u001a\u0006\u0003/b\u000ba!\\8ek2,G\u0003\u00020fO>\u0004BaN C?B\u0011\u0001mY\u0007\u0002C*\u0011!-J\u0001\u0005G>\u0014X-\u0003\u0002eC\n1Qj\u001c3vY\u0016DQA\u001a\u0003A\u0002=\u000bAA\\8eK\"9\u0001\u000e\u0002I\u0001\u0002\u0004I\u0017A\u00043fM\u0006,H\u000e^$s_V\u0004\u0018\n\u001a\t\u0004[)d\u0017BA6/\u0005\u0019y\u0005\u000f^5p]B\u0011\u0001-\\\u0005\u0003]\u0006\u0014Ab\u0014:hC:L\'0\u0019;j_:Dq\u0001\u001d\u0003\u0011\u0002\u0003\u0007\u0011/A\teK\u001a\fW\u000f\u001c;BeRLg-Y2u\u0013\u0012\u00042!\f6s!\t\u00017/\u0003\u0002uC\nQQj\u001c3vY\u0016t\u0015-\\3\u0002!5|G-\u001e7fI\u0011,g-Y;mi\u0012\u0012T#A<+\u0005%D8&A=\u0011\u0005i|X\"A>\u000b\u0005ql\u0018!C;oG\",7m[3e\u0015\tqh&\u0001\u0006b]:|G/\u0019;j_:L1!!\u0001|\u0005E)hn\u00195fG.,GMV1sS\u0006t7-Z\u0001\u0011[>$W\u000f\\3%I\u00164\u0017-\u001e7uIM*\"!a\u0002+\u0005ED\u0018a\u0003:fC\u00124VM]:j_:$B!!\u0004\u0002\u001cA!\u0011qBA\r\u001b\t\t\tB\u0003\u0003\u0002\u0014\u0005U\u0011\u0001\u00027b]\u001eT!!a\u0006\u0002\t)\fg/Y\u0005\u0004\u0011\u0006E\u0001\"\u00024\b\u0001\u0004y\u0015A\u00033fa\u0016tG-\u001a8dsR!\u0011\u0011EA\u0019!\u00159tHQA\u0012!\u0019i3*!\n\u0002,A\u0019\u0001-a\n\n\u0007\u0005%\u0012MA\u0007D_:4\u0017nZ;sCRLwN\u001c\t\u0004A\u00065\u0012bAA\u0018C\nQA)\u001a9f]\u0012,gnY=\t\u000b\u0019D\u0001\u0019A(\u0002#A\u0014xNZ5mK\u0006\u001bG/\u001b<bi&|g\u000e\u0006\u0003\u00028\u0005\u001d\u0003CB\u0017L\u0003s\t\t\u0005\u0005\u0003.U\u0006m\u0002cA\u0017\u0002>%\u0019\u0011q\b\u0018\u0003\u000f\t{w\u000e\\3b]B\u0019\u0001-a\u0011\n\u0007\u0005\u0015\u0013M\u0001\u0006BGRLg/\u0019;j_:DQAZ\u0005A\u0002=\u000bq\u0001\u001d:pM&dW\r\u0006\u0003\u0002N\u0005U\u0003#B\u001c@\u0005\u0006=\u0003c\u00011\u0002R%\u0019\u00111K1\u0003\u000fA\u0013xNZ5mK\")aM\u0003a\u0001\u001f\u0006a\u0001/Y2lC\u001eLgnZ(qiR!\u00111LA2!\u0011i#.!\u0018\u0011\u0007\u0001\fy&C\u0002\u0002b\u0005\u0014A\u0001V=qK\"1\u0011QM\u0006A\u0002=\u000b1\u0001]8n\u0003\u001d\u0001(o\u001c6fGR$B!a\u001b\u0002tA)qg\u0010\"\u0002nA\u0019\u0001-a\u001c\n\u0007\u0005E\u0014MA\u0004Qe>TWm\u0019;\t\r\u0005\u0015D\u00021\u0001P\u0003!1XM]:j_:\u001cH\u0003BA=\u0003\u0003\u0003RaN C\u0003w\u00022\u0001YA?\u0013\r\ty(\u0019\u0002\t-\u0016\u00148/[8og\")a-\u0004a\u0001\u001f\u0006y1O\\1qg\"|GOV3sg&|g\u000e\u0006\u0003\u0002\b\u0006=\u0005#B\u001c@\u0005\u0006%\u0005c\u00011\u0002\f&\u0019\u0011QR1\u0003\u001fMs\u0017\r]:i_R4VM]:j_:DQA\u001a\bA\u0002=\u000bacZ;fgN,Gm\u00158baNDw\u000e\u001e,feNLwN\u001c\u000b\t\u0003\u0013\u000b)*!\'\u0002\u001e\"1\u0011qS\bA\u0002\t\u000bqA^3sg&|g\u000e\u0003\u0004\u0002\u001c>\u0001\rAQ\u0001\ni&lWm\u001d;b[BDq!a(\u0010\u0001\u0004\t\t+A\u0006ck&dGMT;nE\u0016\u0014\bcA\u0017\u0002$&\u0019\u0011Q\u0015\u0018\u0003\u0007%sG/\u0001\nt]\u0006\u00048\u000f[8u-\u0016\u00148/[8oS:<G\u0003BAV\u0003g\u0003RaN C\u0003[\u00032\u0001YAX\u0013\r\t\t,\u0019\u0002\u0013\':\f\u0007o\u001d5piZ+\'o]5p]&tw\rC\u0003g!\u0001\u0007q*A\ffqR\u0014\u0018-\u0011;ue&\u0014W\u000f^3TKB\f\'/\u0019;peV\u0011\u0011QB\u0001\u0019Kb$(/Y!uiJL\'-\u001e;f\'\u0016\u0004\u0018M]1u_J\u0004\u0013\u0001F3yiJ\f\u0017\t\u001e;sS\n,H/\u001a)sK\u001aL\u00070A\u000bfqR\u0014\u0018-\u0011;ue&\u0014W\u000f^3Qe\u00164\u0017\u000e\u001f\u0011\u0002#\u0015DHO]1BiR\u0014\u0018NY;uK>\u0013x-\u0001\nfqR\u0014\u0018-\u0011;ue&\u0014W\u000f^3Pe\u001e\u0004\u0013AE3yiJ\f\u0017\t\u001e;sS\n,H/\u001a(b[\u0016\f1#\u001a=ue\u0006\fE\u000f\u001e:jEV$XMT1nK\u0002\nQ#\u001a=ue\u0006\fE\u000f\u001e:jEV$XMV3sg&|g.\u0001\ffqR\u0014\u0018-\u0011;ue&\u0014W\u000f^3WKJ\u001c\u0018n\u001c8!\u0003I)\u0007\u0010\u001e:b\u0003R$(/\u001b2vi\u0016\u0014\u0015m]3\u0016\u0005\u0005=\u0007CBAi\u00037\fi!\u0004\u0002\u0002T*!\u0011Q[Al\u0003%IW.\\;uC\ndWMC\u0002\u0002Z:\n!bY8mY\u0016\u001cG/[8o\u0013\u0011\ti.a5\u0003\u0007M+G/A\nfqR\u0014\u0018-\u0011;ue&\u0014W\u000f^3CCN,\u0007%\u0001\rfqR\u0014\u0018-\u0011;ue&\u0014W\u000f^3Ee>\u0004\bK]3gSb\f\u0011$\u001a=ue\u0006\fE\u000f\u001e:jEV$X\r\u0012:paB\u0013XMZ5yA\u0005qQ\r\u001f;sC\u0006#HO]5ckR,G\u0003BAu\u0003[\u0004RaN C\u0003W\u0004B!L&`\u0005\"1\u0011q^\u0010A\u0002\t\u000b\u0011a]\u0001\u0010Kb$(/Y!uiJL\'-\u001e;fgR!\u0011Q_A\u007f!\u00159tHQA|!\u00159\u0014\u0011`Av\u0013\r\tY0\u0011\u0002\u0004\'\u0016\f\bBBAxA\u0001\u0007!)A\u0010bI\u0012|\u0005\u000f^5p]\u0006dG)\u001a9f]\u0012,gnY5fg&s7i\u001c8gS\u001e$\u0002\"!\u001c\u0003\u0004\t\u001d!q\u0002\u0005\b\u0005\u000b\t\u0003\u0019AA7\u0003\u0011\u0001(o\u001c6\t\u000f\t%\u0011\u00051\u0001\u0003\f\u0005YaM]8n\u0007>tg-[4t!\u0015\u0019%QBA\u0013\u0013\r\ti.\u0013\u0005\b\u0005#\t\u0003\u0019AA\u0013\u00039y\u0007\u000f^5p]\u0006d7i\u001c8gS\u001e\u0004"
    )
  ScalaSig: length = 0x3 (unknown attribute)
   05 02 00
