Classfile /Users/mw/Projects/slang-braindump/.jar/jar8/assemble/slang-braindump/assemble/content/coursier/maven/PomParser$CustomList$Nil$.class
  Last modified May 29, 2022; size 2784 bytes
  SHA-256 checksum 4c91c1693f69bff6353d58f1c89e5374b2a777dba56319b9d149234abfd95e73
  Compiled from "PomParser.scala"
public class coursier.maven.PomParser$CustomList$Nil$ extends coursier.maven.PomParser$CustomList<scala.runtime.Nothing$> implements scala.Product, java.io.Serializable
  minor version: 0
  major version: 52
  flags: (0x0021) ACC_PUBLIC, ACC_SUPER
  this_class: #2                          // coursier/maven/PomParser$CustomList$Nil$
  super_class: #5                         // coursier/maven/PomParser$CustomList
  interfaces: 2, fields: 1, methods: 13, attributes: 5
Constant pool:
    #1 = Utf8               coursier/maven/PomParser$CustomList$Nil$
    #2 = Class              #1            // coursier/maven/PomParser$CustomList$Nil$
    #3 = Utf8               Lcoursier/maven/PomParser$CustomList<Lscala/runtime/Nothing$;>;Lscala/Product;Ljava/io/Serializable;
    #4 = Utf8               coursier/maven/PomParser$CustomList
    #5 = Class              #4            // coursier/maven/PomParser$CustomList
    #6 = Utf8               scala/Product
    #7 = Class              #6            // scala/Product
    #8 = Utf8               java/io/Serializable
    #9 = Class              #8            // java/io/Serializable
   #10 = Utf8               PomParser.scala
   #11 = Utf8               coursier/maven/PomParser
   #12 = Class              #11           // coursier/maven/PomParser
   #13 = Utf8               CustomList
   #14 = Utf8               coursier/maven/PomParser$CustomList$
   #15 = Class              #14           // coursier/maven/PomParser$CustomList$
   #16 = Utf8
   #17 = Utf8               MODULE$
   #18 = Utf8               Lcoursier/maven/PomParser$CustomList$Nil$;
   #19 = Utf8               <clinit>
   #20 = Utf8               ()V
   #21 = Utf8               <init>
   #22 = NameAndType        #21:#20       // "<init>":()V
   #23 = Methodref          #2.#22        // coursier/maven/PomParser$CustomList$Nil$."<init>":()V
   #24 = NameAndType        #17:#18       // MODULE$:Lcoursier/maven/PomParser$CustomList$Nil$;
   #25 = Fieldref           #2.#24        // coursier/maven/PomParser$CustomList$Nil$.MODULE$:Lcoursier/maven/PomParser$CustomList$Nil$;
   #26 = Utf8               $init$
   #27 = Utf8               (Lscala/Product;)V
   #28 = NameAndType        #26:#27       // $init$:(Lscala/Product;)V
   #29 = InterfaceMethodref #7.#28        // scala/Product.$init$:(Lscala/Product;)V
   #30 = Utf8               productElementName
   #31 = Utf8               (I)Ljava/lang/String;
   #32 = Utf8               n
   #33 = Utf8               productElementName$
   #34 = Utf8               (Lscala/Product;I)Ljava/lang/String;
   #35 = NameAndType        #33:#34       // productElementName$:(Lscala/Product;I)Ljava/lang/String;
   #36 = InterfaceMethodref #7.#35        // scala/Product.productElementName$:(Lscala/Product;I)Ljava/lang/String;
   #37 = Utf8               this
   #38 = Utf8               I
   #39 = Utf8               productElementNames
   #40 = Utf8               ()Lscala/collection/Iterator;
   #41 = Utf8               ()Lscala/collection/Iterator<Ljava/lang/String;>;
   #42 = Utf8               productElementNames$
   #43 = Utf8               (Lscala/Product;)Lscala/collection/Iterator;
   #44 = NameAndType        #42:#43       // productElementNames$:(Lscala/Product;)Lscala/collection/Iterator;
   #45 = InterfaceMethodref #7.#44        // scala/Product.productElementNames$:(Lscala/Product;)Lscala/collection/Iterator;
   #46 = Utf8               tail
   #47 = Utf8               ()Lcoursier/maven/PomParser$CustomList;
   #48 = Utf8               ()Lcoursier/maven/PomParser$CustomList<Lscala/runtime/Nothing$;>;
   #49 = Utf8               java/util/NoSuchElementException
   #50 = Class              #49           // java/util/NoSuchElementException
   #51 = Utf8               tail of empty list
   #52 = String             #51           // tail of empty list
   #53 = Utf8               (Ljava/lang/String;)V
   #54 = NameAndType        #21:#53       // "<init>":(Ljava/lang/String;)V
   #55 = Methodref          #50.#54       // java/util/NoSuchElementException."<init>":(Ljava/lang/String;)V
   #56 = Utf8               productPrefix
   #57 = Utf8               ()Ljava/lang/String;
   #58 = Utf8               Nil
   #59 = String             #58           // Nil
   #60 = Utf8               productArity
   #61 = Utf8               ()I
   #62 = Utf8               productElement
   #63 = Utf8               (I)Ljava/lang/Object;
   #64 = Utf8               x$1
   #65 = Utf8               scala/runtime/Statics
   #66 = Class              #65           // scala/runtime/Statics
   #67 = Utf8               ioobe
   #68 = NameAndType        #67:#63       // ioobe:(I)Ljava/lang/Object;
   #69 = Methodref          #66.#68       // scala/runtime/Statics.ioobe:(I)Ljava/lang/Object;
   #70 = Utf8               java/lang/Object
   #71 = Class              #70           // java/lang/Object
   #72 = Utf8               productIterator
   #73 = Utf8               ()Lscala/collection/Iterator<Ljava/lang/Object;>;
   #74 = Utf8               scala/runtime/ScalaRunTime$
   #75 = Class              #74           // scala/runtime/ScalaRunTime$
   #76 = Utf8               Lscala/runtime/ScalaRunTime$;
   #77 = NameAndType        #17:#76       // MODULE$:Lscala/runtime/ScalaRunTime$;
   #78 = Fieldref           #75.#77       // scala/runtime/ScalaRunTime$.MODULE$:Lscala/runtime/ScalaRunTime$;
   #79 = Utf8               typedProductIterator
   #80 = NameAndType        #79:#43       // typedProductIterator:(Lscala/Product;)Lscala/collection/Iterator;
   #81 = Methodref          #75.#80       // scala/runtime/ScalaRunTime$.typedProductIterator:(Lscala/Product;)Lscala/collection/Iterator;
   #82 = Utf8               canEqual
   #83 = Utf8               (Ljava/lang/Object;)Z
   #84 = Utf8               Ljava/lang/Object;
   #85 = Utf8               hashCode
   #86 = Integer            78321
   #87 = Utf8               toString
   #88 = Utf8               writeReplace
   #89 = Utf8               ()Ljava/lang/Object;
   #90 = Utf8               scala/runtime/ModuleSerializationProxy
   #91 = Class              #90           // scala/runtime/ModuleSerializationProxy
   #92 = Utf8               (Ljava/lang/Class;)V
   #93 = NameAndType        #21:#92       // "<init>":(Ljava/lang/Class;)V
   #94 = Methodref          #91.#93       // scala/runtime/ModuleSerializationProxy."<init>":(Ljava/lang/Class;)V
   #95 = Methodref          #5.#22        // coursier/maven/PomParser$CustomList."<init>":()V
   #96 = Utf8               Code
   #97 = Utf8               LineNumberTable
   #98 = Utf8               LocalVariableTable
   #99 = Utf8               MethodParameters
  #100 = Utf8               Signature
  #101 = Utf8               StackMapTable
  #102 = Utf8               InnerClasses
  #103 = Utf8               SourceFile
  #104 = Utf8               ScalaInlineInfo
  #105 = Utf8               Scala
{
  public static final coursier.maven.PomParser$CustomList$Nil$ MODULE$;
    descriptor: Lcoursier/maven/PomParser$CustomList$Nil$;
    flags: (0x0019) ACC_PUBLIC, ACC_STATIC, ACC_FINAL

  public static {};
    descriptor: ()V
    flags: (0x0009) ACC_PUBLIC, ACC_STATIC
    Code:
      stack=2, locals=0, args_size=0
         0: new           #2                  // class coursier/maven/PomParser$CustomList$Nil$
         3: dup
         4: invokespecial #23                 // Method "<init>":()V
         7: putstatic     #25                 // Field MODULE$:Lcoursier/maven/PomParser$CustomList$Nil$;
        10: getstatic     #25                 // Field MODULE$:Lcoursier/maven/PomParser$CustomList$Nil$;
        13: invokestatic  #29                 // InterfaceMethod scala/Product.$init$:(Lscala/Product;)V
        16: return
      LineNumberTable:
        line 72: 0

  public java.lang.String productElementName(int);
    descriptor: (I)Ljava/lang/String;
    flags: (0x0001) ACC_PUBLIC
    Code:
      stack=2, locals=2, args_size=2
         0: aload_0
         1: iload_1
         2: invokestatic  #36                 // InterfaceMethod scala/Product.productElementName$:(Lscala/Product;I)Ljava/lang/String;
         5: areturn
      LineNumberTable:
        line 72: 0
      LocalVariableTable:
        Start  Length  Slot  Name   Signature
            0       6     0  this   Lcoursier/maven/PomParser$CustomList$Nil$;
            0       6     1     n   I
    MethodParameters:
      Name                           Flags
      n                              final

  public scala.collection.Iterator<java.lang.String> productElementNames();
    descriptor: ()Lscala/collection/Iterator;
    flags: (0x0001) ACC_PUBLIC
    Code:
      stack=1, locals=1, args_size=1
         0: aload_0
         1: invokestatic  #45                 // InterfaceMethod scala/Product.productElementNames$:(Lscala/Product;)Lscala/collection/Iterator;
         4: areturn
      LineNumberTable:
        line 72: 0
      LocalVariableTable:
        Start  Length  Slot  Name   Signature
            0       5     0  this   Lcoursier/maven/PomParser$CustomList$Nil$;
    Signature: #41                          // ()Lscala/collection/Iterator<Ljava/lang/String;>;

  public coursier.maven.PomParser$CustomList<scala.runtime.Nothing$> tail();
    descriptor: ()Lcoursier/maven/PomParser$CustomList;
    flags: (0x0001) ACC_PUBLIC
    Code:
      stack=3, locals=1, args_size=1
         0: new           #50                 // class java/util/NoSuchElementException
         3: dup
         4: ldc           #52                 // String tail of empty list
         6: invokespecial #55                 // Method java/util/NoSuchElementException."<init>":(Ljava/lang/String;)V
         9: athrow
      LineNumberTable:
        line 74: 0
      LocalVariableTable:
        Start  Length  Slot  Name   Signature
            0      10     0  this   Lcoursier/maven/PomParser$CustomList$Nil$;
    Signature: #48                          // ()Lcoursier/maven/PomParser$CustomList<Lscala/runtime/Nothing$;>;

  public java.lang.String productPrefix();
    descriptor: ()Ljava/lang/String;
    flags: (0x0001) ACC_PUBLIC
    Code:
      stack=1, locals=1, args_size=1
         0: ldc           #59                 // String Nil
         2: areturn
      LineNumberTable:
        line 72: 0
      LocalVariableTable:
        Start  Length  Slot  Name   Signature
            0       3     0  this   Lcoursier/maven/PomParser$CustomList$Nil$;

  public int productArity();
    descriptor: ()I
    flags: (0x0001) ACC_PUBLIC
    Code:
      stack=1, locals=1, args_size=1
         0: iconst_0
         1: ireturn
      LineNumberTable:
        line 72: 0
      LocalVariableTable:
        Start  Length  Slot  Name   Signature
            0       2     0  this   Lcoursier/maven/PomParser$CustomList$Nil$;

  public java.lang.Object productElement(int);
    descriptor: (I)Ljava/lang/Object;
    flags: (0x0001) ACC_PUBLIC
    Code:
      stack=1, locals=4, args_size=2
         0: iload_1
         1: istore_3
         2: iload_1
         3: invokestatic  #69                 // Method scala/runtime/Statics.ioobe:(I)Ljava/lang/Object;
         6: astore_2
         7: goto          10
        10: aload_2
        11: areturn
      StackMapTable: number_of_entries = 1
        frame_type = 253 /* append */
          offset_delta = 10
          locals = [ class java/lang/Object, int ]
      LineNumberTable:
        line 72: 0
      LocalVariableTable:
        Start  Length  Slot  Name   Signature
            0      12     0  this   Lcoursier/maven/PomParser$CustomList$Nil$;
            0      12     1   x$1   I
    MethodParameters:
      Name                           Flags
      x$1                            final

  public scala.collection.Iterator<java.lang.Object> productIterator();
    descriptor: ()Lscala/collection/Iterator;
    flags: (0x0001) ACC_PUBLIC
    Code:
      stack=2, locals=1, args_size=1
         0: getstatic     #78                 // Field scala/runtime/ScalaRunTime$.MODULE$:Lscala/runtime/ScalaRunTime$;
         3: aload_0
         4: invokevirtual #81                 // Method scala/runtime/ScalaRunTime$.typedProductIterator:(Lscala/Product;)Lscala/collection/Iterator;
         7: areturn
      LineNumberTable:
        line 72: 0
      LocalVariableTable:
        Start  Length  Slot  Name   Signature
            0       8     0  this   Lcoursier/maven/PomParser$CustomList$Nil$;
    Signature: #73                          // ()Lscala/collection/Iterator<Ljava/lang/Object;>;

  public boolean canEqual(java.lang.Object);
    descriptor: (Ljava/lang/Object;)Z
    flags: (0x0001) ACC_PUBLIC
    Code:
      stack=1, locals=2, args_size=2
         0: aload_1
         1: instanceof    #2                  // class coursier/maven/PomParser$CustomList$Nil$
         4: ireturn
      LineNumberTable:
        line 72: 0
      LocalVariableTable:
        Start  Length  Slot  Name   Signature
            0       5     0  this   Lcoursier/maven/PomParser$CustomList$Nil$;
            0       5     1   x$1   Ljava/lang/Object;
    MethodParameters:
      Name                           Flags
      x$1                            final

  public int hashCode();
    descriptor: ()I
    flags: (0x0001) ACC_PUBLIC
    Code:
      stack=1, locals=1, args_size=1
         0: ldc           #86                 // int 78321
         2: ireturn
      LineNumberTable:
        line 72: 0
      LocalVariableTable:
        Start  Length  Slot  Name   Signature
            0       3     0  this   Lcoursier/maven/PomParser$CustomList$Nil$;

  public java.lang.String toString();
    descriptor: ()Ljava/lang/String;
    flags: (0x0001) ACC_PUBLIC
    Code:
      stack=1, locals=1, args_size=1
         0: ldc           #59                 // String Nil
         2: areturn
      LineNumberTable:
        line 72: 0
      LocalVariableTable:
        Start  Length  Slot  Name   Signature
            0       3     0  this   Lcoursier/maven/PomParser$CustomList$Nil$;

  private java.lang.Object writeReplace();
    descriptor: ()Ljava/lang/Object;
    flags: (0x0002) ACC_PRIVATE
    Code:
      stack=3, locals=1, args_size=1
         0: new           #91                 // class scala/runtime/ModuleSerializationProxy
         3: dup
         4: ldc           #2                  // class coursier/maven/PomParser$CustomList$Nil$
         6: invokespecial #94                 // Method scala/runtime/ModuleSerializationProxy."<init>":(Ljava/lang/Class;)V
         9: areturn
      LineNumberTable:
        line 72: 0
      LocalVariableTable:
        Start  Length  Slot  Name   Signature
            0      10     0  this   Lcoursier/maven/PomParser$CustomList$Nil$;

  public coursier.maven.PomParser$CustomList$Nil$();
    descriptor: ()V
    flags: (0x0001) ACC_PUBLIC
    Code:
      stack=1, locals=1, args_size=1
         0: aload_0
         1: invokespecial #95                 // Method coursier/maven/PomParser$CustomList."<init>":()V
         4: return
      LineNumberTable:
        line 72: 0
      LocalVariableTable:
        Start  Length  Slot  Name   Signature
            0       5     0  this   Lcoursier/maven/PomParser$CustomList$Nil$;
}
InnerClasses:
  public static abstract #13= #5 of #12;  // CustomList=class coursier/maven/PomParser$CustomList of class coursier/maven/PomParser
  public static #16= #15 of #12;          // =class coursier/maven/PomParser$CustomList$ of class coursier/maven/PomParser
  public static #16= #2 of #15;           // =class coursier/maven/PomParser$CustomList$Nil$ of class coursier/maven/PomParser$CustomList$
Signature: #3                           // Lcoursier/maven/PomParser$CustomList<Lscala/runtime/Nothing$;>;Lscala/Product;Ljava/io/Serializable;
SourceFile: "PomParser.scala"
  ScalaInlineInfo: length = 0x40 (unknown attribute)
   01 01 00 0C 00 16 00 15 01 00 53 00 54 01 00 56
   00 3E 01 00 3D 00 3E 01 00 3F 00 40 01 00 1F 00
   20 01 00 28 00 29 01 00 49 00 29 01 00 39 00 3A
   01 00 2F 00 30 01 00 58 00 3A 01 00 59 00 5A 01

  Scala: length = 0x0 (unknown attribute)

