Classfile /Users/mw/Projects/slang-braindump/.jar/jar8/assemble/slang-braindump/assemble/content/coursier/maven/PomParser$Handler.class
  Last modified May 29, 2022; size 883 bytes
  SHA-256 checksum 46a123929e954c39d2b3e79afa6371e5bb249e9f61c4c8e4fe9259d5f2e91712
  Compiled from "PomParser.scala"
public abstract class coursier.maven.PomParser$Handler
  minor version: 0
  major version: 52
  flags: (0x0421) ACC_PUBLIC, ACC_SUPER, ACC_ABSTRACT
  this_class: #2                          // coursier/maven/PomParser$Handler
  super_class: #4                         // java/lang/Object
  interfaces: 0, fields: 1, methods: 2, attributes: 4
Constant pool:
   #1 = Utf8               coursier/maven/PomParser$Handler
   #2 = Class              #1             // coursier/maven/PomParser$Handler
   #3 = Utf8               java/lang/Object
   #4 = Class              #3             // java/lang/Object
   #5 = Utf8               PomParser.scala
   #6 = Utf8               coursier/maven/PomParser
   #7 = Class              #6             // coursier/maven/PomParser
   #8 = Utf8               Handler
   #9 = Utf8               path
  #10 = Utf8               Lscala/collection/immutable/List;
  #11 = Utf8               Lscala/collection/immutable/List<Ljava/lang/String;>;
  #12 = Utf8               ()Lscala/collection/immutable/List;
  #13 = Utf8               ()Lscala/collection/immutable/List<Ljava/lang/String;>;
  #14 = NameAndType        #9:#10         // path:Lscala/collection/immutable/List;
  #15 = Fieldref           #2.#14         // coursier/maven/PomParser$Handler.path:Lscala/collection/immutable/List;
  #16 = Utf8               this
  #17 = Utf8               Lcoursier/maven/PomParser$Handler;
  #18 = Utf8               <init>
  #19 = Utf8               (Lscala/collection/immutable/List;)V
  #20 = Utf8               (Lscala/collection/immutable/List<Ljava/lang/String;>;)V
  #21 = Utf8               ()V
  #22 = NameAndType        #18:#21        // "<init>":()V
  #23 = Methodref          #4.#22         // java/lang/Object."<init>":()V
  #24 = Utf8               Signature
  #25 = Utf8               Code
  #26 = Utf8               LineNumberTable
  #27 = Utf8               LocalVariableTable
  #28 = Utf8               MethodParameters
  #29 = Utf8               InnerClasses
  #30 = Utf8               SourceFile
  #31 = Utf8               ScalaInlineInfo
  #32 = Utf8               Scala
{
  private final scala.collection.immutable.List<java.lang.String> path;
    descriptor: Lscala/collection/immutable/List;
    flags: (0x0012) ACC_PRIVATE, ACC_FINAL
    Signature: #11                          // Lscala/collection/immutable/List<Ljava/lang/String;>;

  public scala.collection.immutable.List<java.lang.String> path();
    descriptor: ()Lscala/collection/immutable/List;
    flags: (0x0001) ACC_PUBLIC
    Code:
      stack=1, locals=1, args_size=1
         0: aload_0
         1: getfield      #15                 // Field path:Lscala/collection/immutable/List;
         4: areturn
      LineNumberTable:
        line 259: 0
      LocalVariableTable:
        Start  Length  Slot  Name   Signature
            0       5     0  this   Lcoursier/maven/PomParser$Handler;
    Signature: #13                          // ()Lscala/collection/immutable/List<Ljava/lang/String;>;

  public coursier.maven.PomParser$Handler(scala.collection.immutable.List<java.lang.String>);
    descriptor: (Lscala/collection/immutable/List;)V
    flags: (0x0001) ACC_PUBLIC
    Code:
      stack=2, locals=2, args_size=2
         0: aload_0
         1: aload_1
         2: putfield      #15                 // Field path:Lscala/collection/immutable/List;
         5: aload_0
         6: invokespecial #23                 // Method java/lang/Object."<init>":()V
         9: return
      LineNumberTable:
        line 259: 0
        line 261: 5
        line 259: 9
      LocalVariableTable:
        Start  Length  Slot  Name   Signature
            0      10     0  this   Lcoursier/maven/PomParser$Handler;
            0      10     1  path   Lscala/collection/immutable/List;
    Signature: #20                          // (Lscala/collection/immutable/List<Ljava/lang/String;>;)V
    MethodParameters:
      Name                           Flags
      path                           final
}
InnerClasses:
  public static abstract #8= #2 of #7;    // Handler=class coursier/maven/PomParser$Handler of class coursier/maven/PomParser
SourceFile: "PomParser.scala"
  ScalaInlineInfo: length = 0xE (unknown attribute)
   01 00 00 02 00 12 00 13 00 00 09 00 0C 00
  Scala: length = 0x0 (unknown attribute)

