Classfile /Users/mw/Projects/slang-braindump/.jar/jar8/assemble/slang-braindump/assemble/content/coursier/maven/WritePom$.class
  Last modified May 29, 2022; size 7279 bytes
  SHA-256 checksum 66bc1d90cede910126a1ef81c717fca64f0cdf9c53ed8701ca4668887958e6ed
  Compiled from "WritePom.scala"
public final class coursier.maven.WritePom$
  minor version: 0
  major version: 52
  flags: (0x0031) ACC_PUBLIC, ACC_FINAL, ACC_SUPER
  this_class: #2                          // coursier/maven/WritePom$
  super_class: #4                         // java/lang/Object
  interfaces: 0, fields: 1, methods: 8, attributes: 5
Constant pool:
    #1 = Utf8               coursier/maven/WritePom$
    #2 = Class              #1            // coursier/maven/WritePom$
    #3 = Utf8               java/lang/Object
    #4 = Class              #3            // java/lang/Object
    #5 = Utf8               WritePom.scala
    #6 = Utf8               java/lang/invoke/MethodHandles$Lookup
    #7 = Class              #6            // java/lang/invoke/MethodHandles$Lookup
    #8 = Utf8               java/lang/invoke/MethodHandles
    #9 = Class              #8            // java/lang/invoke/MethodHandles
   #10 = Utf8               Lookup
   #11 = Utf8               MODULE$
   #12 = Utf8               Lcoursier/maven/WritePom$;
   #13 = Utf8               <clinit>
   #14 = Utf8               ()V
   #15 = Utf8               <init>
   #16 = NameAndType        #15:#14       // "<init>":()V
   #17 = Methodref          #2.#16        // coursier/maven/WritePom$."<init>":()V
   #18 = NameAndType        #11:#12       // MODULE$:Lcoursier/maven/WritePom$;
   #19 = Fieldref           #2.#18        // coursier/maven/WritePom$.MODULE$:Lcoursier/maven/WritePom$;
   #20 = Utf8               project
   #21 = Utf8               (Lcoursier/core/Project;Lscala/Option;)Lscala/xml/Elem;
   #22 = Utf8               (Lcoursier/core/Project;Lscala/Option<Ljava/lang/String;>;)Lscala/xml/Elem;
   #23 = Utf8               proj
   #24 = Utf8               packaging
   #25 = Utf8               scala/xml/Elem
   #26 = Class              #25           // scala/xml/Elem
   #27 = String             #20           // project
   #28 = Utf8               scala/xml/Null$
   #29 = Class              #28           // scala/xml/Null$
   #30 = Utf8               Lscala/xml/Null$;
   #31 = NameAndType        #11:#30       // MODULE$:Lscala/xml/Null$;
   #32 = Fieldref           #29.#31       // scala/xml/Null$.MODULE$:Lscala/xml/Null$;
   #33 = Utf8               scala/xml/TopScope$
   #34 = Class              #33           // scala/xml/TopScope$
   #35 = Utf8               Lscala/xml/TopScope$;
   #36 = NameAndType        #11:#35       // MODULE$:Lscala/xml/TopScope$;
   #37 = Fieldref           #34.#36       // scala/xml/TopScope$.MODULE$:Lscala/xml/TopScope$;
   #38 = Utf8               scala/xml/NodeSeq$
   #39 = Class              #38           // scala/xml/NodeSeq$
   #40 = Utf8               Lscala/xml/NodeSeq$;
   #41 = NameAndType        #11:#40       // MODULE$:Lscala/xml/NodeSeq$;
   #42 = Fieldref           #39.#41       // scala/xml/NodeSeq$.MODULE$:Lscala/xml/NodeSeq$;
   #43 = Utf8               scala/xml/NodeBuffer
   #44 = Class              #43           // scala/xml/NodeBuffer
   #45 = Methodref          #44.#16       // scala/xml/NodeBuffer."<init>":()V
   #46 = Utf8               scala/xml/Text
   #47 = Class              #46           // scala/xml/Text
   #48 = Utf8               \n      // parent\n
   #49 = String             #48           // \n      // parent\n
   #50 = Utf8               (Ljava/lang/String;)V
   #51 = NameAndType        #15:#50       // "<init>":(Ljava/lang/String;)V
   #52 = Methodref          #47.#51       // scala/xml/Text."<init>":(Ljava/lang/String;)V
   #53 = Utf8               $amp$plus
   #54 = Utf8               (Ljava/lang/Object;)Lscala/xml/NodeBuffer;
   #55 = NameAndType        #53:#54       // $amp$plus:(Ljava/lang/Object;)Lscala/xml/NodeBuffer;
   #56 = Methodref          #44.#55       // scala/xml/NodeBuffer.$amp$plus:(Ljava/lang/Object;)Lscala/xml/NodeBuffer;
   #57 = Utf8               groupId
   #58 = String             #57           // groupId
   #59 = Utf8               coursier/core/Organization
   #60 = Class              #59           // coursier/core/Organization
   #61 = Utf8               coursier/core/Project
   #62 = Class              #61           // coursier/core/Project
   #63 = Utf8               module
   #64 = Utf8               ()Lcoursier/core/Module;
   #65 = NameAndType        #63:#64       // module:()Lcoursier/core/Module;
   #66 = Methodref          #62.#65       // coursier/core/Project.module:()Lcoursier/core/Module;
   #67 = Utf8               coursier/core/Module
   #68 = Class              #67           // coursier/core/Module
   #69 = Utf8               organization
   #70 = Utf8               ()Ljava/lang/String;
   #71 = NameAndType        #69:#70       // organization:()Ljava/lang/String;
   #72 = Methodref          #68.#71       // coursier/core/Module.organization:()Ljava/lang/String;
   #73 = Methodref          #60.#51       // coursier/core/Organization."<init>":(Ljava/lang/String;)V
   #74 = Utf8               seqToNodeSeq
   #75 = Utf8               (Lscala/collection/Seq;)Lscala/xml/NodeSeq;
   #76 = NameAndType        #74:#75       // seqToNodeSeq:(Lscala/collection/Seq;)Lscala/xml/NodeSeq;
   #77 = Methodref          #39.#76       // scala/xml/NodeSeq$.seqToNodeSeq:(Lscala/collection/Seq;)Lscala/xml/NodeSeq;
   #78 = Utf8               (Ljava/lang/String;Ljava/lang/String;Lscala/xml/MetaData;Lscala/xml/NamespaceBinding;ZLscala/collection/immutable/Seq;)V
   #79 = NameAndType        #15:#78       // "<init>":(Ljava/lang/String;Ljava/lang/String;Lscala/xml/MetaData;Lscala/xml/NamespaceBinding;ZLscala/collection/immutable/Seq;)V
   #80 = Methodref          #26.#79       // scala/xml/Elem."<init>":(Ljava/lang/String;Ljava/lang/String;Lscala/xml/MetaData;Lscala/xml/NamespaceBinding;ZLscala/collection/immutable/Seq;)V
   #81 = Utf8               \n
   #82 = String             #81           // \n
   #83 = Utf8               artifactId
   #84 = String             #83           // artifactId
   #85 = Utf8               coursier/core/ModuleName
   #86 = Class              #85           // coursier/core/ModuleName
   #87 = Utf8               name
   #88 = NameAndType        #87:#70       // name:()Ljava/lang/String;
   #89 = Methodref          #68.#88       // coursier/core/Module.name:()Ljava/lang/String;
   #90 = Methodref          #86.#51       // coursier/core/ModuleName."<init>":(Ljava/lang/String;)V
   #91 = Utf8               scala/Option$
   #92 = Class              #91           // scala/Option$
   #93 = Utf8               Lscala/Option$;
   #94 = NameAndType        #11:#93       // MODULE$:Lscala/Option$;
   #95 = Fieldref           #92.#94       // scala/Option$.MODULE$:Lscala/Option$;
   #96 = Utf8               (Ljava/lang/Object;)Ljava/lang/Object;
   #97 = MethodType         #96           //  (Ljava/lang/Object;)Ljava/lang/Object;
   #98 = Utf8               $anonfun$project$1
   #99 = Utf8               (Ljava/lang/String;)Lscala/xml/Elem;
  #100 = NameAndType        #98:#99       // $anonfun$project$1:(Ljava/lang/String;)Lscala/xml/Elem;
  #101 = Methodref          #2.#100       // coursier/maven/WritePom$.$anonfun$project$1:(Ljava/lang/String;)Lscala/xml/Elem;
  #102 = MethodHandle       6:#101        // REF_invokeStatic coursier/maven/WritePom$.$anonfun$project$1:(Ljava/lang/String;)Lscala/xml/Elem;
  #103 = MethodType         #99           //  (Ljava/lang/String;)Lscala/xml/Elem;
  #104 = Integer            5
  #105 = Integer            1
  #106 = Utf8               java/lang/invoke/LambdaMetafactory
  #107 = Class              #106          // java/lang/invoke/LambdaMetafactory
  #108 = Utf8               altMetafactory
  #109 = Utf8               (Ljava/lang/invoke/MethodHandles$Lookup;Ljava/lang/String;Ljava/lang/invoke/MethodType;[Ljava/lang/Object;)Ljava/lang/invoke/CallSite;
  #110 = NameAndType        #108:#109     // altMetafactory:(Ljava/lang/invoke/MethodHandles$Lookup;Ljava/lang/String;Ljava/lang/invoke/MethodType;[Ljava/lang/Object;)Ljava/lang/invoke/CallSite;
  #111 = Methodref          #107.#110     // java/lang/invoke/LambdaMetafactory.altMetafactory:(Ljava/lang/invoke/MethodHandles$Lookup;Ljava/lang/String;Ljava/lang/invoke/MethodType;[Ljava/lang/Object;)Ljava/lang/invoke/CallSite;
  #112 = MethodHandle       6:#111        // REF_invokeStatic java/lang/invoke/LambdaMetafactory.altMetafactory:(Ljava/lang/invoke/MethodHandles$Lookup;Ljava/lang/String;Ljava/lang/invoke/MethodType;[Ljava/lang/Object;)Ljava/lang/invoke/CallSite;
  #113 = Utf8               apply
  #114 = Utf8               ()Lscala/Function1;
  #115 = NameAndType        #113:#114     // apply:()Lscala/Function1;
  #116 = InvokeDynamic      #0:#115       // #0:apply:()Lscala/Function1;
  #117 = Utf8               scala/Option
  #118 = Class              #117          // scala/Option
  #119 = Utf8               map
  #120 = Utf8               (Lscala/Function1;)Lscala/Option;
  #121 = NameAndType        #119:#120     // map:(Lscala/Function1;)Lscala/Option;
  #122 = Methodref          #118.#121     // scala/Option.map:(Lscala/Function1;)Lscala/Option;
  #123 = Utf8               option2Iterable
  #124 = Utf8               (Lscala/Option;)Lscala/collection/Iterable;
  #125 = NameAndType        #123:#124     // option2Iterable:(Lscala/Option;)Lscala/collection/Iterable;
  #126 = Methodref          #92.#125      // scala/Option$.option2Iterable:(Lscala/Option;)Lscala/collection/Iterable;
  #127 = Utf8               scala/collection/Iterable
  #128 = Class              #127          // scala/collection/Iterable
  #129 = Utf8               toSeq
  #130 = Utf8               ()Lscala/collection/immutable/Seq;
  #131 = NameAndType        #129:#130     // toSeq:()Lscala/collection/immutable/Seq;
  #132 = InterfaceMethodref #128.#131     // scala/collection/Iterable.toSeq:()Lscala/collection/immutable/Seq;
  #133 = Utf8               description
  #134 = String             #133          // description
  #135 = Utf8               info
  #136 = Utf8               ()Lcoursier/core/Info;
  #137 = NameAndType        #135:#136     // info:()Lcoursier/core/Info;
  #138 = Methodref          #62.#137      // coursier/core/Project.info:()Lcoursier/core/Info;
  #139 = Utf8               coursier/core/Info
  #140 = Class              #139          // coursier/core/Info
  #141 = NameAndType        #133:#70      // description:()Ljava/lang/String;
  #142 = Methodref          #140.#141     // coursier/core/Info.description:()Ljava/lang/String;
  #143 = Utf8               url
  #144 = String             #143          // url
  #145 = Utf8               homePage
  #146 = NameAndType        #145:#70      // homePage:()Ljava/lang/String;
  #147 = Methodref          #140.#146     // coursier/core/Info.homePage:()Ljava/lang/String;
  #148 = Utf8               version
  #149 = String             #148          // version
  #150 = NameAndType        #148:#70      // version:()Ljava/lang/String;
  #151 = Methodref          #62.#150      // coursier/core/Project.version:()Ljava/lang/String;
  #152 = Utf8               \n      // licenses\n
  #153 = String             #152          // \n      // licenses\n
  #154 = String             #87           // name
  #155 = String             #69           // organization
  #156 = Utf8               \n
  #157 = String             #156          // \n
  #158 = Utf8               \n      // SCM\n      // developers\n
  #159 = String             #158          // \n      // SCM\n      // developers\n
  #160 = Utf8               dependencies
  #161 = NameAndType        #160:#130     // dependencies:()Lscala/collection/immutable/Seq;
  #162 = Methodref          #62.#161      // coursier/core/Project.dependencies:()Lscala/collection/immutable/Seq;
  #163 = Utf8               scala/collection/immutable/Seq
  #164 = Class              #163          // scala/collection/immutable/Seq
  #165 = Utf8               isEmpty
  #166 = Utf8               ()Z
  #167 = NameAndType        #165:#166     // isEmpty:()Z
  #168 = InterfaceMethodref #164.#167     // scala/collection/immutable/Seq.isEmpty:()Z
  #169 = Utf8               scala/collection/immutable/Nil$
  #170 = Class              #169          // scala/collection/immutable/Nil$
  #171 = Utf8               Lscala/collection/immutable/Nil$;
  #172 = NameAndType        #11:#171      // MODULE$:Lscala/collection/immutable/Nil$;
  #173 = Fieldref           #170.#172     // scala/collection/immutable/Nil$.MODULE$:Lscala/collection/immutable/Nil$;
  #174 = Utf8               java/lang/String
  #175 = Class              #174          // java/lang/String
  #176 = String             #160          // dependencies
  #177 = Utf8               $anonfun$project$2
  #178 = Utf8               (Lscala/Tuple2;)Lscala/xml/Elem;
  #179 = NameAndType        #177:#178     // $anonfun$project$2:(Lscala/Tuple2;)Lscala/xml/Elem;
  #180 = Methodref          #2.#179       // coursier/maven/WritePom$.$anonfun$project$2:(Lscala/Tuple2;)Lscala/xml/Elem;
  #181 = MethodHandle       6:#180        // REF_invokeStatic coursier/maven/WritePom$.$anonfun$project$2:(Lscala/Tuple2;)Lscala/xml/Elem;
  #182 = MethodType         #178          //  (Lscala/Tuple2;)Lscala/xml/Elem;
  #183 = InvokeDynamic      #1:#115       // #1:apply:()Lscala/Function1;
  #184 = Utf8               (Lscala/Function1;)Ljava/lang/Object;
  #185 = NameAndType        #119:#184     // map:(Lscala/Function1;)Ljava/lang/Object;
  #186 = InterfaceMethodref #164.#185     // scala/collection/immutable/Seq.map:(Lscala/Function1;)Ljava/lang/Object;
  #187 = Utf8               scala/collection/AbstractSeq
  #188 = Class              #187          // scala/collection/AbstractSeq
  #189 = Utf8               dependencyManagement
  #190 = NameAndType        #189:#130     // dependencyManagement:()Lscala/collection/immutable/Seq;
  #191 = Methodref          #62.#190      // coursier/core/Project.dependencyManagement:()Lscala/collection/immutable/Seq;
  #192 = String             #189          // dependencyManagement
  #193 = Utf8               \n
  #194 = String             #193          // \n
  #195 = Utf8               $anonfun$project$3
  #196 = NameAndType        #195:#178     // $anonfun$project$3:(Lscala/Tuple2;)Lscala/xml/Elem;
  #197 = Methodref          #2.#196       // coursier/maven/WritePom$.$anonfun$project$3:(Lscala/Tuple2;)Lscala/xml/Elem;
  #198 = MethodHandle       6:#197        // REF_invokeStatic coursier/maven/WritePom$.$anonfun$project$3:(Lscala/Tuple2;)Lscala/xml/Elem;
  #199 = InvokeDynamic      #2:#115       // #2:apply:()Lscala/Function1;
  #200 = Utf8               \n      // properties\n      // repositories\n
  #201 = String             #200          // \n      // properties\n      // repositories\n
  #202 = Utf8               $buf
  #203 = Utf8               Lscala/xml/NodeBuffer;
  #204 = Utf8               this
  #205 = Utf8               Lcoursier/core/Project;
  #206 = Utf8               Lscala/Option;
  #207 = Utf8               dependencyNode$1
  #208 = Utf8               (Ljava/lang/String;Lcoursier/core/Dependency;)Lscala/xml/Elem;
  #209 = Utf8               config
  #210 = Utf8               dep
  #211 = Utf8               dependency
  #212 = String             #211          // dependency
  #213 = Utf8               coursier/core/Dependency
  #214 = Class              #213          // coursier/core/Dependency
  #215 = Methodref          #214.#65      // coursier/core/Dependency.module:()Lcoursier/core/Module;
  #216 = Methodref          #214.#150     // coursier/core/Dependency.version:()Ljava/lang/String;
  #217 = Methodref          #175.#167     // java/lang/String.isEmpty:()Z
  #218 = Utf8               scala/collection/immutable/$colon$colon
  #219 = Class              #218          // scala/collection/immutable/$colon$colon
  #220 = Utf8               (Ljava/lang/Object;Lscala/collection/immutable/List;)V
  #221 = NameAndType        #15:#220      // "<init>":(Ljava/lang/Object;Lscala/collection/immutable/List;)V
  #222 = Methodref          #219.#221     // scala/collection/immutable/$colon$colon."<init>":(Ljava/lang/Object;Lscala/collection/immutable/List;)V
  #223 = Utf8               scala/collection/immutable/List
  #224 = Class              #223          // scala/collection/immutable/List
  #225 = Utf8               coursier/core/Configuration$
  #226 = Class              #225          // coursier/core/Configuration$
  #227 = Utf8               Lcoursier/core/Configuration$;
  #228 = NameAndType        #11:#227      // MODULE$:Lcoursier/core/Configuration$;
  #229 = Fieldref           #226.#228     // coursier/core/Configuration$.MODULE$:Lcoursier/core/Configuration$;
  #230 = Utf8               isEmpty$extension
  #231 = Utf8               (Ljava/lang/String;)Z
  #232 = NameAndType        #230:#231     // isEmpty$extension:(Ljava/lang/String;)Z
  #233 = Methodref          #226.#232     // coursier/core/Configuration$.isEmpty$extension:(Ljava/lang/String;)Z
  #234 = Utf8               scope
  #235 = String             #234          // scope
  #236 = Utf8               Ljava/lang/String;
  #237 = Utf8               Lcoursier/core/Dependency;
  #238 = Utf8               p
  #239 = String             #24           // packaging
  #240 = Utf8               x0$1
  #241 = Utf8               scala/Tuple2
  #242 = Class              #241          // scala/Tuple2
  #243 = Utf8               _1
  #244 = Utf8               ()Ljava/lang/Object;
  #245 = NameAndType        #243:#244     // _1:()Ljava/lang/Object;
  #246 = Methodref          #242.#245     // scala/Tuple2._1:()Ljava/lang/Object;
  #247 = Utf8               coursier/core/Configuration
  #248 = Class              #247          // coursier/core/Configuration
  #249 = Utf8               value
  #250 = NameAndType        #249:#70      // value:()Ljava/lang/String;
  #251 = Methodref          #248.#250     // coursier/core/Configuration.value:()Ljava/lang/String;
  #252 = Utf8               _2
  #253 = NameAndType        #252:#244     // _2:()Ljava/lang/Object;
  #254 = Methodref          #242.#253     // scala/Tuple2._2:()Ljava/lang/Object;
  #255 = NameAndType        #207:#208     // dependencyNode$1:(Ljava/lang/String;Lcoursier/core/Dependency;)Lscala/xml/Elem;
  #256 = Methodref          #2.#255       // coursier/maven/WritePom$.dependencyNode$1:(Ljava/lang/String;Lcoursier/core/Dependency;)Lscala/xml/Elem;
  #257 = Utf8               scala/MatchError
  #258 = Class              #257          // scala/MatchError
  #259 = Utf8               (Ljava/lang/Object;)V
  #260 = NameAndType        #15:#259      // "<init>":(Ljava/lang/Object;)V
  #261 = Methodref          #258.#260     // scala/MatchError."<init>":(Ljava/lang/Object;)V
  #262 = Utf8               Lscala/Tuple2;
  #263 = Utf8               x0$2
  #264 = Methodref          #4.#16        // java/lang/Object."<init>":()V
  #265 = Utf8               $deserializeLambda$
  #266 = Utf8               (Ljava/lang/invoke/SerializedLambda;)Ljava/lang/Object;
  #267 = Utf8               scala/runtime/LambdaDeserialize
  #268 = Class              #267          // scala/runtime/LambdaDeserialize
  #269 = Utf8               bootstrap
  #270 = Utf8               (Ljava/lang/invoke/MethodHandles$Lookup;Ljava/lang/String;Ljava/lang/invoke/MethodType;[Ljava/lang/invoke/MethodHandle;)Ljava/lang/invoke/CallSite;
  #271 = NameAndType        #269:#270     // bootstrap:(Ljava/lang/invoke/MethodHandles$Lookup;Ljava/lang/String;Ljava/lang/invoke/MethodType;[Ljava/lang/invoke/MethodHandle;)Ljava/lang/invoke/CallSite;
  #272 = Methodref          #268.#271     // scala/runtime/LambdaDeserialize.bootstrap:(Ljava/lang/invoke/MethodHandles$Lookup;Ljava/lang/String;Ljava/lang/invoke/MethodType;[Ljava/lang/invoke/MethodHandle;)Ljava/lang/invoke/CallSite;
  #273 = MethodHandle       6:#272        // REF_invokeStatic scala/runtime/LambdaDeserialize.bootstrap:(Ljava/lang/invoke/MethodHandles$Lookup;Ljava/lang/String;Ljava/lang/invoke/MethodType;[Ljava/lang/invoke/MethodHandle;)Ljava/lang/invoke/CallSite;
  #274 = Utf8               lambdaDeserialize
  #275 = NameAndType        #274:#266     // lambdaDeserialize:(Ljava/lang/invoke/SerializedLambda;)Ljava/lang/Object;
  #276 = InvokeDynamic      #3:#275       // #3:lambdaDeserialize:(Ljava/lang/invoke/SerializedLambda;)Ljava/lang/Object;
  #277 = Utf8               Code
  #278 = Utf8               LineNumberTable
  #279 = Utf8               StackMapTable
  #280 = Utf8               LocalVariableTable
  #281 = Utf8               Signature
  #282 = Utf8               MethodParameters
  #283 = Utf8               InnerClasses
  #284 = Utf8               SourceFile
  #285 = Utf8               BootstrapMethods
  #286 = Utf8               ScalaInlineInfo
  #287 = Utf8               Scala
{
  public static final coursier.maven.WritePom$ MODULE$;
    descriptor: Lcoursier/maven/WritePom$;
    flags: (0x0019) ACC_PUBLIC, ACC_STATIC, ACC_FINAL

  public static {};
    descriptor: ()V
    flags: (0x0009) ACC_PUBLIC, ACC_STATIC
    Code:
      stack=2, locals=0, args_size=0
         0: new           #2                  // class coursier/maven/WritePom$
         3: dup
         4: invokespecial #17                 // Method "<init>":()V
         7: putstatic     #19                 // Field MODULE$:Lcoursier/maven/WritePom$;
        10: return
      LineNumberTable:
        line 5: 0

  public scala.xml.Elem project(coursier.core.Project, scala.Option<java.lang.String>);
    descriptor: (Lcoursier/core/Project;Lscala/Option;)Lscala/xml/Elem;
    flags: (0x0001) ACC_PUBLIC
    Code:
      stack=30, locals=16, args_size=3
         0: new           #26                 // class scala/xml/Elem
         3: dup
         4: aconst_null
         5: ldc           #27                 // String project
         7: getstatic     #32                 // Field scala/xml/Null$.MODULE$:Lscala/xml/Null$;
        10: getstatic     #37                 // Field scala/xml/TopScope$.MODULE$:Lscala/xml/TopScope$;
        13: iconst_0
        14: getstatic     #42                 // Field scala/xml/NodeSeq$.MODULE$:Lscala/xml/NodeSeq$;
        17: new           #44                 // class scala/xml/NodeBuffer
        20: dup
        21: invokespecial #45                 // Method scala/xml/NodeBuffer."<init>":()V
        24: astore_3
        25: aload_3
        26: new           #47                 // class scala/xml/Text
        29: dup
        30: ldc           #49                 // String \n      // parent\n
        32: invokespecial #52                 // Method scala/xml/Text."<init>":(Ljava/lang/String;)V
        35: invokevirtual #56                 // Method scala/xml/NodeBuffer.$amp$plus:(Ljava/lang/Object;)Lscala/xml/NodeBuffer;
        38: pop
        39: aload_3
        40: new           #26                 // class scala/xml/Elem
        43: dup
        44: aconst_null
        45: ldc           #58                 // String groupId
        47: getstatic     #32                 // Field scala/xml/Null$.MODULE$:Lscala/xml/Null$;
        50: getstatic     #37                 // Field scala/xml/TopScope$.MODULE$:Lscala/xml/TopScope$;
        53: iconst_0
        54: getstatic     #42                 // Field scala/xml/NodeSeq$.MODULE$:Lscala/xml/NodeSeq$;
        57: new           #44                 // class scala/xml/NodeBuffer
        60: dup
        61: invokespecial #45                 // Method scala/xml/NodeBuffer."<init>":()V
        64: astore        4
        66: aload         4
        68: new           #60                 // class coursier/core/Organization
        71: dup
        72: aload_1
        73: invokevirtual #66                 // Method coursier/core/Project.module:()Lcoursier/core/Module;
        76: invokevirtual #72                 // Method coursier/core/Module.organization:()Ljava/lang/String;
        79: invokespecial #73                 // Method coursier/core/Organization."<init>":(Ljava/lang/String;)V
        82: invokevirtual #56                 // Method scala/xml/NodeBuffer.$amp$plus:(Ljava/lang/Object;)Lscala/xml/NodeBuffer;
        85: pop
        86: aload         4
        88: invokevirtual #77                 // Method scala/xml/NodeSeq$.seqToNodeSeq:(Lscala/collection/Seq;)Lscala/xml/NodeSeq;
        91: invokespecial #80                 // Method scala/xml/Elem."<init>":(Ljava/lang/String;Ljava/lang/String;Lscala/xml/MetaData;Lscala/xml/NamespaceBinding;ZLscala/collection/immutable/Seq;)V
        94: invokevirtual #56                 // Method scala/xml/NodeBuffer.$amp$plus:(Ljava/lang/Object;)Lscala/xml/NodeBuffer;
        97: pop
        98: aload_3
        99: new           #47                 // class scala/xml/Text
       102: dup
       103: ldc           #82                 // String \n
       105: invokespecial #52                 // Method scala/xml/Text."<init>":(Ljava/lang/String;)V
       108: invokevirtual #56                 // Method scala/xml/NodeBuffer.$amp$plus:(Ljava/lang/Object;)Lscala/xml/NodeBuffer;
       111: pop
       112: aload_3
       113: new           #26                 // class scala/xml/Elem
       116: dup
       117: aconst_null
       118: ldc           #84                 // String artifactId
       120: getstatic     #32                 // Field scala/xml/Null$.MODULE$:Lscala/xml/Null$;
       123: getstatic     #37                 // Field scala/xml/TopScope$.MODULE$:Lscala/xml/TopScope$;
       126: iconst_0
       127: getstatic     #42                 // Field scala/xml/NodeSeq$.MODULE$:Lscala/xml/NodeSeq$;
       130: new           #44                 // class scala/xml/NodeBuffer
       133: dup
       134: invokespecial #45                 // Method scala/xml/NodeBuffer."<init>":()V
       137: astore        5
       139: aload         5
       141: new           #86                 // class coursier/core/ModuleName
       144: dup
       145: aload_1
       146: invokevirtual #66                 // Method coursier/core/Project.module:()Lcoursier/core/Module;
       149: invokevirtual #89                 // Method coursier/core/Module.name:()Ljava/lang/String;
       152: invokespecial #90                 // Method coursier/core/ModuleName."<init>":(Ljava/lang/String;)V
       155: invokevirtual #56                 // Method scala/xml/NodeBuffer.$amp$plus:(Ljava/lang/Object;)Lscala/xml/NodeBuffer;
       158: pop
       159: aload         5
       161: invokevirtual #77                 // Method scala/xml/NodeSeq$.seqToNodeSeq:(Lscala/collection/Seq;)Lscala/xml/NodeSeq;
       164: invokespecial #80                 // Method scala/xml/Elem."<init>":(Ljava/lang/String;Ljava/lang/String;Lscala/xml/MetaData;Lscala/xml/NamespaceBinding;ZLscala/collection/immutable/Seq;)V
       167: invokevirtual #56                 // Method scala/xml/NodeBuffer.$amp$plus:(Ljava/lang/Object;)Lscala/xml/NodeBuffer;
       170: pop
       171: aload_3
       172: new           #47                 // class scala/xml/Text
       175: dup
       176: ldc           #82                 // String \n
       178: invokespecial #52                 // Method scala/xml/Text."<init>":(Ljava/lang/String;)V
       181: invokevirtual #56                 // Method scala/xml/NodeBuffer.$amp$plus:(Ljava/lang/Object;)Lscala/xml/NodeBuffer;
       184: pop
       185: aload_3
       186: getstatic     #95                 // Field scala/Option$.MODULE$:Lscala/Option$;
       189: aload_2
       190: invokedynamic #116,  0            // InvokeDynamic #0:apply:()Lscala/Function1;
       195: invokevirtual #122                // Method scala/Option.map:(Lscala/Function1;)Lscala/Option;
       198: invokevirtual #126                // Method scala/Option$.option2Iterable:(Lscala/Option;)Lscala/collection/Iterable;
       201: invokeinterface #132,  1          // InterfaceMethod scala/collection/Iterable.toSeq:()Lscala/collection/immutable/Seq;
       206: invokevirtual #56                 // Method scala/xml/NodeBuffer.$amp$plus:(Ljava/lang/Object;)Lscala/xml/NodeBuffer;
       209: pop
       210: aload_3
       211: new           #47                 // class scala/xml/Text
       214: dup
       215: ldc           #82                 // String \n
       217: invokespecial #52                 // Method scala/xml/Text."<init>":(Ljava/lang/String;)V
       220: invokevirtual #56                 // Method scala/xml/NodeBuffer.$amp$plus:(Ljava/lang/Object;)Lscala/xml/NodeBuffer;
       223: pop
       224: aload_3
       225: new           #26                 // class scala/xml/Elem
       228: dup
       229: aconst_null
       230: ldc           #134                // String description
       232: getstatic     #32                 // Field scala/xml/Null$.MODULE$:Lscala/xml/Null$;
       235: getstatic     #37                 // Field scala/xml/TopScope$.MODULE$:Lscala/xml/TopScope$;
       238: iconst_0
       239: getstatic     #42                 // Field scala/xml/NodeSeq$.MODULE$:Lscala/xml/NodeSeq$;
       242: new           #44                 // class scala/xml/NodeBuffer
       245: dup
       246: invokespecial #45                 // Method scala/xml/NodeBuffer."<init>":()V
       249: astore        6
       251: aload         6
       253: aload_1
       254: invokevirtual #138                // Method coursier/core/Project.info:()Lcoursier/core/Info;
       257: invokevirtual #142                // Method coursier/core/Info.description:()Ljava/lang/String;
       260: invokevirtual #56                 // Method scala/xml/NodeBuffer.$amp$plus:(Ljava/lang/Object;)Lscala/xml/NodeBuffer;
       263: pop
       264: aload         6
       266: invokevirtual #77                 // Method scala/xml/NodeSeq$.seqToNodeSeq:(Lscala/collection/Seq;)Lscala/xml/NodeSeq;
       269: invokespecial #80                 // Method scala/xml/Elem."<init>":(Ljava/lang/String;Ljava/lang/String;Lscala/xml/MetaData;Lscala/xml/NamespaceBinding;ZLscala/collection/immutable/Seq;)V
       272: invokevirtual #56                 // Method scala/xml/NodeBuffer.$amp$plus:(Ljava/lang/Object;)Lscala/xml/NodeBuffer;
       275: pop
       276: aload_3
       277: new           #47                 // class scala/xml/Text
       280: dup
       281: ldc           #82                 // String \n
       283: invokespecial #52                 // Method scala/xml/Text."<init>":(Ljava/lang/String;)V
       286: invokevirtual #56                 // Method scala/xml/NodeBuffer.$amp$plus:(Ljava/lang/Object;)Lscala/xml/NodeBuffer;
       289: pop
       290: aload_3
       291: new           #26                 // class scala/xml/Elem
       294: dup
       295: aconst_null
       296: ldc           #144                // String url
       298: getstatic     #32                 // Field scala/xml/Null$.MODULE$:Lscala/xml/Null$;
       301: getstatic     #37                 // Field scala/xml/TopScope$.MODULE$:Lscala/xml/TopScope$;
       304: iconst_0
       305: getstatic     #42                 // Field scala/xml/NodeSeq$.MODULE$:Lscala/xml/NodeSeq$;
       308: new           #44                 // class scala/xml/NodeBuffer
       311: dup
       312: invokespecial #45                 // Method scala/xml/NodeBuffer."<init>":()V
       315: astore        7
       317: aload         7
       319: aload_1
       320: invokevirtual #138                // Method coursier/core/Project.info:()Lcoursier/core/Info;
       323: invokevirtual #147                // Method coursier/core/Info.homePage:()Ljava/lang/String;
       326: invokevirtual #56                 // Method scala/xml/NodeBuffer.$amp$plus:(Ljava/lang/Object;)Lscala/xml/NodeBuffer;
       329: pop
       330: aload         7
       332: invokevirtual #77                 // Method scala/xml/NodeSeq$.seqToNodeSeq:(Lscala/collection/Seq;)Lscala/xml/NodeSeq;
       335: invokespecial #80                 // Method scala/xml/Elem."<init>":(Ljava/lang/String;Ljava/lang/String;Lscala/xml/MetaData;Lscala/xml/NamespaceBinding;ZLscala/collection/immutable/Seq;)V
       338: invokevirtual #56                 // Method scala/xml/NodeBuffer.$amp$plus:(Ljava/lang/Object;)Lscala/xml/NodeBuffer;
       341: pop
       342: aload_3
       343: new           #47                 // class scala/xml/Text
       346: dup
       347: ldc           #82                 // String \n
       349: invokespecial #52                 // Method scala/xml/Text."<init>":(Ljava/lang/String;)V
       352: invokevirtual #56                 // Method scala/xml/NodeBuffer.$amp$plus:(Ljava/lang/Object;)Lscala/xml/NodeBuffer;
       355: pop
       356: aload_3
       357: new           #26                 // class scala/xml/Elem
       360: dup
       361: aconst_null
       362: ldc           #149                // String version
       364: getstatic     #32                 // Field scala/xml/Null$.MODULE$:Lscala/xml/Null$;
       367: getstatic     #37                 // Field scala/xml/TopScope$.MODULE$:Lscala/xml/TopScope$;
       370: iconst_0
       371: getstatic     #42                 // Field scala/xml/NodeSeq$.MODULE$:Lscala/xml/NodeSeq$;
       374: new           #44                 // class scala/xml/NodeBuffer
       377: dup
       378: invokespecial #45                 // Method scala/xml/NodeBuffer."<init>":()V
       381: astore        8
       383: aload         8
       385: aload_1
       386: invokevirtual #151                // Method coursier/core/Project.version:()Ljava/lang/String;
       389: invokevirtual #56                 // Method scala/xml/NodeBuffer.$amp$plus:(Ljava/lang/Object;)Lscala/xml/NodeBuffer;
       392: pop
       393: aload         8
       395: invokevirtual #77                 // Method scala/xml/NodeSeq$.seqToNodeSeq:(Lscala/collection/Seq;)Lscala/xml/NodeSeq;
       398: invokespecial #80                 // Method scala/xml/Elem."<init>":(Ljava/lang/String;Ljava/lang/String;Lscala/xml/MetaData;Lscala/xml/NamespaceBinding;ZLscala/collection/immutable/Seq;)V
       401: invokevirtual #56                 // Method scala/xml/NodeBuffer.$amp$plus:(Ljava/lang/Object;)Lscala/xml/NodeBuffer;
       404: pop
       405: aload_3
       406: new           #47                 // class scala/xml/Text
       409: dup
       410: ldc           #153                // String \n      // licenses\n
       412: invokespecial #52                 // Method scala/xml/Text."<init>":(Ljava/lang/String;)V
       415: invokevirtual #56                 // Method scala/xml/NodeBuffer.$amp$plus:(Ljava/lang/Object;)Lscala/xml/NodeBuffer;
       418: pop
       419: aload_3
       420: new           #26                 // class scala/xml/Elem
       423: dup
       424: aconst_null
       425: ldc           #154                // String name
       427: getstatic     #32                 // Field scala/xml/Null$.MODULE$:Lscala/xml/Null$;
       430: getstatic     #37                 // Field scala/xml/TopScope$.MODULE$:Lscala/xml/TopScope$;
       433: iconst_0
       434: getstatic     #42                 // Field scala/xml/NodeSeq$.MODULE$:Lscala/xml/NodeSeq$;
       437: new           #44                 // class scala/xml/NodeBuffer
       440: dup
       441: invokespecial #45                 // Method scala/xml/NodeBuffer."<init>":()V
       444: astore        9
       446: aload         9
       448: new           #86                 // class coursier/core/ModuleName
       451: dup
       452: aload_1
       453: invokevirtual #66                 // Method coursier/core/Project.module:()Lcoursier/core/Module;
       456: invokevirtual #89                 // Method coursier/core/Module.name:()Ljava/lang/String;
       459: invokespecial #90                 // Method coursier/core/ModuleName."<init>":(Ljava/lang/String;)V
       462: invokevirtual #56                 // Method scala/xml/NodeBuffer.$amp$plus:(Ljava/lang/Object;)Lscala/xml/NodeBuffer;
       465: pop
       466: aload         9
       468: invokevirtual #77                 // Method scala/xml/NodeSeq$.seqToNodeSeq:(Lscala/collection/Seq;)Lscala/xml/NodeSeq;
       471: invokespecial #80                 // Method scala/xml/Elem."<init>":(Ljava/lang/String;Ljava/lang/String;Lscala/xml/MetaData;Lscala/xml/NamespaceBinding;ZLscala/collection/immutable/Seq;)V
       474: invokevirtual #56                 // Method scala/xml/NodeBuffer.$amp$plus:(Ljava/lang/Object;)Lscala/xml/NodeBuffer;
       477: pop
       478: aload_3
       479: new           #47                 // class scala/xml/Text
       482: dup
       483: ldc           #82                 // String \n
       485: invokespecial #52                 // Method scala/xml/Text."<init>":(Ljava/lang/String;)V
       488: invokevirtual #56                 // Method scala/xml/NodeBuffer.$amp$plus:(Ljava/lang/Object;)Lscala/xml/NodeBuffer;
       491: pop
       492: aload_3
       493: new           #26                 // class scala/xml/Elem
       496: dup
       497: aconst_null
       498: ldc           #155                // String organization
       500: getstatic     #32                 // Field scala/xml/Null$.MODULE$:Lscala/xml/Null$;
       503: getstatic     #37                 // Field scala/xml/TopScope$.MODULE$:Lscala/xml/TopScope$;
       506: iconst_0
       507: getstatic     #42                 // Field scala/xml/NodeSeq$.MODULE$:Lscala/xml/NodeSeq$;
       510: new           #44                 // class scala/xml/NodeBuffer
       513: dup
       514: invokespecial #45                 // Method scala/xml/NodeBuffer."<init>":()V
       517: astore        10
       519: aload         10
       521: new           #47                 // class scala/xml/Text
       524: dup
       525: ldc           #157                // String \n
       527: invokespecial #52                 // Method scala/xml/Text."<init>":(Ljava/lang/String;)V
       530: invokevirtual #56                 // Method scala/xml/NodeBuffer.$amp$plus:(Ljava/lang/Object;)Lscala/xml/NodeBuffer;
       533: pop
       534: aload         10
       536: new           #26                 // class scala/xml/Elem
       539: dup
       540: aconst_null
       541: ldc           #154                // String name
       543: getstatic     #32                 // Field scala/xml/Null$.MODULE$:Lscala/xml/Null$;
       546: getstatic     #37                 // Field scala/xml/TopScope$.MODULE$:Lscala/xml/TopScope$;
       549: iconst_0
       550: getstatic     #42                 // Field scala/xml/NodeSeq$.MODULE$:Lscala/xml/NodeSeq$;
       553: new           #44                 // class scala/xml/NodeBuffer
       556: dup
       557: invokespecial #45                 // Method scala/xml/NodeBuffer."<init>":()V
       560: astore        11
       562: aload         11
       564: new           #86                 // class coursier/core/ModuleName
       567: dup
       568: aload_1
       569: invokevirtual #66                 // Method coursier/core/Project.module:()Lcoursier/core/Module;
       572: invokevirtual #89                 // Method coursier/core/Module.name:()Ljava/lang/String;
       575: invokespecial #90                 // Method coursier/core/ModuleName."<init>":(Ljava/lang/String;)V
       578: invokevirtual #56                 // Method scala/xml/NodeBuffer.$amp$plus:(Ljava/lang/Object;)Lscala/xml/NodeBuffer;
       581: pop
       582: aload         11
       584: invokevirtual #77                 // Method scala/xml/NodeSeq$.seqToNodeSeq:(Lscala/collection/Seq;)Lscala/xml/NodeSeq;
       587: invokespecial #80                 // Method scala/xml/Elem."<init>":(Ljava/lang/String;Ljava/lang/String;Lscala/xml/MetaData;Lscala/xml/NamespaceBinding;ZLscala/collection/immutable/Seq;)V
       590: invokevirtual #56                 // Method scala/xml/NodeBuffer.$amp$plus:(Ljava/lang/Object;)Lscala/xml/NodeBuffer;
       593: pop
       594: aload         10
       596: new           #47                 // class scala/xml/Text
       599: dup
       600: ldc           #157                // String \n
       602: invokespecial #52                 // Method scala/xml/Text."<init>":(Ljava/lang/String;)V
       605: invokevirtual #56                 // Method scala/xml/NodeBuffer.$amp$plus:(Ljava/lang/Object;)Lscala/xml/NodeBuffer;
       608: pop
       609: aload         10
       611: new           #26                 // class scala/xml/Elem
       614: dup
       615: aconst_null
       616: ldc           #144                // String url
       618: getstatic     #32                 // Field scala/xml/Null$.MODULE$:Lscala/xml/Null$;
       621: getstatic     #37                 // Field scala/xml/TopScope$.MODULE$:Lscala/xml/TopScope$;
       624: iconst_0
       625: getstatic     #42                 // Field scala/xml/NodeSeq$.MODULE$:Lscala/xml/NodeSeq$;
       628: new           #44                 // class scala/xml/NodeBuffer
       631: dup
       632: invokespecial #45                 // Method scala/xml/NodeBuffer."<init>":()V
       635: astore        12
       637: aload         12
       639: aload_1
       640: invokevirtual #138                // Method coursier/core/Project.info:()Lcoursier/core/Info;
       643: invokevirtual #147                // Method coursier/core/Info.homePage:()Ljava/lang/String;
       646: invokevirtual #56                 // Method scala/xml/NodeBuffer.$amp$plus:(Ljava/lang/Object;)Lscala/xml/NodeBuffer;
       649: pop
       650: aload         12
       652: invokevirtual #77                 // Method scala/xml/NodeSeq$.seqToNodeSeq:(Lscala/collection/Seq;)Lscala/xml/NodeSeq;
       655: invokespecial #80                 // Method scala/xml/Elem."<init>":(Ljava/lang/String;Ljava/lang/String;Lscala/xml/MetaData;Lscala/xml/NamespaceBinding;ZLscala/collection/immutable/Seq;)V
       658: invokevirtual #56                 // Method scala/xml/NodeBuffer.$amp$plus:(Ljava/lang/Object;)Lscala/xml/NodeBuffer;
       661: pop
       662: aload         10
       664: new           #47                 // class scala/xml/Text
       667: dup
       668: ldc           #82                 // String \n
       670: invokespecial #52                 // Method scala/xml/Text."<init>":(Ljava/lang/String;)V
       673: invokevirtual #56                 // Method scala/xml/NodeBuffer.$amp$plus:(Ljava/lang/Object;)Lscala/xml/NodeBuffer;
       676: pop
       677: aload         10
       679: invokevirtual #77                 // Method scala/xml/NodeSeq$.seqToNodeSeq:(Lscala/collection/Seq;)Lscala/xml/NodeSeq;
       682: invokespecial #80                 // Method scala/xml/Elem."<init>":(Ljava/lang/String;Ljava/lang/String;Lscala/xml/MetaData;Lscala/xml/NamespaceBinding;ZLscala/collection/immutable/Seq;)V
       685: invokevirtual #56                 // Method scala/xml/NodeBuffer.$amp$plus:(Ljava/lang/Object;)Lscala/xml/NodeBuffer;
       688: pop
       689: aload_3
       690: new           #47                 // class scala/xml/Text
       693: dup
       694: ldc           #159                // String \n      // SCM\n      // developers\n
       696: invokespecial #52                 // Method scala/xml/Text."<init>":(Ljava/lang/String;)V
       699: invokevirtual #56                 // Method scala/xml/NodeBuffer.$amp$plus:(Ljava/lang/Object;)Lscala/xml/NodeBuffer;
       702: pop
       703: aload_3
       704: aload_1
       705: invokevirtual #162                // Method coursier/core/Project.dependencies:()Lscala/collection/immutable/Seq;
       708: invokeinterface #168,  1          // InterfaceMethod scala/collection/immutable/Seq.isEmpty:()Z
       713: ifeq          722
       716: getstatic     #173                // Field scala/collection/immutable/Nil$.MODULE$:Lscala/collection/immutable/Nil$;
       719: goto          776
       722: new           #26                 // class scala/xml/Elem
       725: dup
       726: aconst_null
       727: ldc           #176                // String dependencies
       729: getstatic     #32                 // Field scala/xml/Null$.MODULE$:Lscala/xml/Null$;
       732: getstatic     #37                 // Field scala/xml/TopScope$.MODULE$:Lscala/xml/TopScope$;
       735: iconst_0
       736: getstatic     #42                 // Field scala/xml/NodeSeq$.MODULE$:Lscala/xml/NodeSeq$;
       739: new           #44                 // class scala/xml/NodeBuffer
       742: dup
       743: invokespecial #45                 // Method scala/xml/NodeBuffer."<init>":()V
       746: astore        13
       748: aload         13
       750: aload_1
       751: invokevirtual #162                // Method coursier/core/Project.dependencies:()Lscala/collection/immutable/Seq;
       754: invokedynamic #183,  0            // InvokeDynamic #1:apply:()Lscala/Function1;
       759: invokeinterface #186,  2          // InterfaceMethod scala/collection/immutable/Seq.map:(Lscala/Function1;)Ljava/lang/Object;
       764: invokevirtual #56                 // Method scala/xml/NodeBuffer.$amp$plus:(Ljava/lang/Object;)Lscala/xml/NodeBuffer;
       767: pop
       768: aload         13
       770: invokevirtual #77                 // Method scala/xml/NodeSeq$.seqToNodeSeq:(Lscala/collection/Seq;)Lscala/xml/NodeSeq;
       773: invokespecial #80                 // Method scala/xml/Elem."<init>":(Ljava/lang/String;Ljava/lang/String;Lscala/xml/MetaData;Lscala/xml/NamespaceBinding;ZLscala/collection/immutable/Seq;)V
       776: invokevirtual #56                 // Method scala/xml/NodeBuffer.$amp$plus:(Ljava/lang/Object;)Lscala/xml/NodeBuffer;
       779: pop
       780: aload_3
       781: new           #47                 // class scala/xml/Text
       784: dup
       785: ldc           #82                 // String \n
       787: invokespecial #52                 // Method scala/xml/Text."<init>":(Ljava/lang/String;)V
       790: invokevirtual #56                 // Method scala/xml/NodeBuffer.$amp$plus:(Ljava/lang/Object;)Lscala/xml/NodeBuffer;
       793: pop
       794: aload_3
       795: aload_1
       796: invokevirtual #191                // Method coursier/core/Project.dependencyManagement:()Lscala/collection/immutable/Seq;
       799: invokeinterface #168,  1          // InterfaceMethod scala/collection/immutable/Seq.isEmpty:()Z
       804: ifeq          813
       807: getstatic     #173                // Field scala/collection/immutable/Nil$.MODULE$:Lscala/collection/immutable/Nil$;
       810: goto          937
       813: new           #26                 // class scala/xml/Elem
       816: dup
       817: aconst_null
       818: ldc           #192                // String dependencyManagement
       820: getstatic     #32                 // Field scala/xml/Null$.MODULE$:Lscala/xml/Null$;
       823: getstatic     #37                 // Field scala/xml/TopScope$.MODULE$:Lscala/xml/TopScope$;
       826: iconst_0
       827: getstatic     #42                 // Field scala/xml/NodeSeq$.MODULE$:Lscala/xml/NodeSeq$;
       830: new           #44                 // class scala/xml/NodeBuffer
       833: dup
       834: invokespecial #45                 // Method scala/xml/NodeBuffer."<init>":()V
       837: astore        14
       839: aload         14
       841: new           #47                 // class scala/xml/Text
       844: dup
       845: ldc           #194                // String \n
       847: invokespecial #52                 // Method scala/xml/Text."<init>":(Ljava/lang/String;)V
       850: invokevirtual #56                 // Method scala/xml/NodeBuffer.$amp$plus:(Ljava/lang/Object;)Lscala/xml/NodeBuffer;
       853: pop
       854: aload         14
       856: new           #26                 // class scala/xml/Elem
       859: dup
       860: aconst_null
       861: ldc           #176                // String dependencies
       863: getstatic     #32                 // Field scala/xml/Null$.MODULE$:Lscala/xml/Null$;
       866: getstatic     #37                 // Field scala/xml/TopScope$.MODULE$:Lscala/xml/TopScope$;
       869: iconst_0
       870: getstatic     #42                 // Field scala/xml/NodeSeq$.MODULE$:Lscala/xml/NodeSeq$;
       873: new           #44                 // class scala/xml/NodeBuffer
       876: dup
       877: invokespecial #45                 // Method scala/xml/NodeBuffer."<init>":()V
       880: astore        15
       882: aload         15
       884: aload_1
       885: invokevirtual #191                // Method coursier/core/Project.dependencyManagement:()Lscala/collection/immutable/Seq;
       888: invokedynamic #199,  0            // InvokeDynamic #2:apply:()Lscala/Function1;
       893: invokeinterface #186,  2          // InterfaceMethod scala/collection/immutable/Seq.map:(Lscala/Function1;)Ljava/lang/Object;
       898: invokevirtual #56                 // Method scala/xml/NodeBuffer.$amp$plus:(Ljava/lang/Object;)Lscala/xml/NodeBuffer;
       901: pop
       902: aload         15
       904: invokevirtual #77                 // Method scala/xml/NodeSeq$.seqToNodeSeq:(Lscala/collection/Seq;)Lscala/xml/NodeSeq;
       907: invokespecial #80                 // Method scala/xml/Elem."<init>":(Ljava/lang/String;Ljava/lang/String;Lscala/xml/MetaData;Lscala/xml/NamespaceBinding;ZLscala/collection/immutable/Seq;)V
       910: invokevirtual #56                 // Method scala/xml/NodeBuffer.$amp$plus:(Ljava/lang/Object;)Lscala/xml/NodeBuffer;
       913: pop
       914: aload         14
       916: new           #47                 // class scala/xml/Text
       919: dup
       920: ldc           #157                // String \n
       922: invokespecial #52                 // Method scala/xml/Text."<init>":(Ljava/lang/String;)V
       925: invokevirtual #56                 // Method scala/xml/NodeBuffer.$amp$plus:(Ljava/lang/Object;)Lscala/xml/NodeBuffer;
       928: pop
       929: aload         14
       931: invokevirtual #77                 // Method scala/xml/NodeSeq$.seqToNodeSeq:(Lscala/collection/Seq;)Lscala/xml/NodeSeq;
       934: invokespecial #80                 // Method scala/xml/Elem."<init>":(Ljava/lang/String;Ljava/lang/String;Lscala/xml/MetaData;Lscala/xml/NamespaceBinding;ZLscala/collection/immutable/Seq;)V
       937: invokevirtual #56                 // Method scala/xml/NodeBuffer.$amp$plus:(Ljava/lang/Object;)Lscala/xml/NodeBuffer;
       940: pop
       941: aload_3
       942: new           #47                 // class scala/xml/Text
       945: dup
       946: ldc           #201                // String \n      // properties\n      // repositories\n
       948: invokespecial #52                 // Method scala/xml/Text."<init>":(Ljava/lang/String;)V
       951: invokevirtual #56                 // Method scala/xml/NodeBuffer.$amp$plus:(Ljava/lang/Object;)Lscala/xml/NodeBuffer;
       954: pop
       955: aload_3
       956: invokevirtual #77                 // Method scala/xml/NodeSeq$.seqToNodeSeq:(Lscala/collection/Seq;)Lscala/xml/NodeSeq;
       959: invokespecial #80                 // Method scala/xml/Elem."<init>":(Ljava/lang/String;Ljava/lang/String;Lscala/xml/MetaData;Lscala/xml/NamespaceBinding;ZLscala/collection/immutable/Seq;)V
       962: areturn
      StackMapTable: number_of_entries = 4
        frame_type = 255 /* full_frame */
          offset_delta = 722
          locals = [ class coursier/maven/WritePom$, class coursier/core/Project, class scala/Option, class scala/xml/NodeBuffer, class scala/xml/NodeBuffer, class scala/xml/NodeBuffer, class scala/xml/NodeBuffer, class scala/xml/NodeBuffer, class scala/xml/NodeBuffer, class scala/xml/NodeBuffer, class scala/xml/NodeBuffer, class scala/xml/NodeBuffer, class scala/xml/NodeBuffer ]
          stack = [ uninitialized 0, uninitialized 0, null, class java/lang/String, class scala/xml/Null$, class scala/xml/TopScope$, int, class scala/xml/NodeSeq$, class scala/xml/NodeBuffer ]
        frame_type = 255 /* full_frame */
          offset_delta = 53
          locals = [ class coursier/maven/WritePom$, class coursier/core/Project, class scala/Option, class scala/xml/NodeBuffer, class scala/xml/NodeBuffer, class scala/xml/NodeBuffer, class scala/xml/NodeBuffer, class scala/xml/NodeBuffer, class scala/xml/NodeBuffer, class scala/xml/NodeBuffer, class scala/xml/NodeBuffer, class scala/xml/NodeBuffer, class scala/xml/NodeBuffer ]
          stack = [ uninitialized 0, uninitialized 0, null, class java/lang/String, class scala/xml/Null$, class scala/xml/TopScope$, int, class scala/xml/NodeSeq$, class scala/xml/NodeBuffer, class scala/collection/AbstractSeq ]
        frame_type = 255 /* full_frame */
          offset_delta = 36
          locals = [ class coursier/maven/WritePom$, class coursier/core/Project, class scala/Option, class scala/xml/NodeBuffer, class scala/xml/NodeBuffer, class scala/xml/NodeBuffer, class scala/xml/NodeBuffer, class scala/xml/NodeBuffer, class scala/xml/NodeBuffer, class scala/xml/NodeBuffer, class scala/xml/NodeBuffer, class scala/xml/NodeBuffer, class scala/xml/NodeBuffer ]
          stack = [ uninitialized 0, uninitialized 0, null, class java/lang/String, class scala/xml/Null$, class scala/xml/TopScope$, int, class scala/xml/NodeSeq$, class scala/xml/NodeBuffer ]
        frame_type = 255 /* full_frame */
          offset_delta = 123
          locals = [ class coursier/maven/WritePom$, class coursier/core/Project, class scala/Option, class scala/xml/NodeBuffer, class scala/xml/NodeBuffer, class scala/xml/NodeBuffer, class scala/xml/NodeBuffer, class scala/xml/NodeBuffer, class scala/xml/NodeBuffer, class scala/xml/NodeBuffer, class scala/xml/NodeBuffer, class scala/xml/NodeBuffer, class scala/xml/NodeBuffer ]
          stack = [ uninitialized 0, uninitialized 0, null, class java/lang/String, class scala/xml/Null$, class scala/xml/TopScope$, int, class scala/xml/NodeSeq$, class scala/xml/NodeBuffer, class scala/collection/AbstractSeq ]
      LineNumberTable:
        line 28: 0
        line 30: 40
        line 28: 98
        line 30: 99
        line 28: 112
        line 31: 113
        line 28: 171
        line 31: 172
        line 28: 185
        line 34: 186
        line 33: 189
        line 34: 190
        line 28: 210
        line 36: 211
        line 28: 224
        line 37: 225
        line 28: 276
        line 37: 277
        line 28: 290
        line 38: 291
        line 28: 342
        line 38: 343
        line 28: 356
        line 39: 357
        line 28: 405
        line 39: 406
        line 28: 419
        line 41: 420
        line 28: 478
        line 41: 479
        line 28: 492
        line 42: 493
        line 43: 536
        line 42: 594
        line 43: 596
        line 42: 609
        line 44: 611
        line 42: 662
        line 44: 664
        line 42: 677
        line 28: 689
        line 45: 690
        line 28: 703
        line 49: 704
        line 50: 716
        line 52: 722
        line 53: 750
        line 52: 768
        line 28: 780
        line 58: 781
        line 28: 794
        line 60: 795
        line 61: 807
        line 63: 813
        line 64: 856
        line 65: 884
        line 64: 902
        line 63: 914
        line 69: 916
        line 63: 929
        line 28: 941
        line 71: 942
        line 28: 955
      LocalVariableTable:
        Start  Length  Slot  Name   Signature
           66      22     4  $buf   Lscala/xml/NodeBuffer;
          139      22     5  $buf   Lscala/xml/NodeBuffer;
          251      15     6  $buf   Lscala/xml/NodeBuffer;
          317      15     7  $buf   Lscala/xml/NodeBuffer;
          383      12     8  $buf   Lscala/xml/NodeBuffer;
          446      22     9  $buf   Lscala/xml/NodeBuffer;
          562      22    11  $buf   Lscala/xml/NodeBuffer;
          637      15    12  $buf   Lscala/xml/NodeBuffer;
          519     160    10  $buf   Lscala/xml/NodeBuffer;
          748      22    13  $buf   Lscala/xml/NodeBuffer;
          882      22    15  $buf   Lscala/xml/NodeBuffer;
          839      92    14  $buf   Lscala/xml/NodeBuffer;
           25     931     3  $buf   Lscala/xml/NodeBuffer;
            0     963     0  this   Lcoursier/maven/WritePom$;
            0     963     1  proj   Lcoursier/core/Project;
            0     963     2 packaging   Lscala/Option;
    Signature: #22                          // (Lcoursier/core/Project;Lscala/Option<Ljava/lang/String;>;)Lscala/xml/Elem;
    MethodParameters:
      Name                           Flags
      proj                           final
      packaging                      final

  private static final scala.xml.Elem dependencyNode$1(java.lang.String, coursier.core.Dependency);
    descriptor: (Ljava/lang/String;Lcoursier/core/Dependency;)Lscala/xml/Elem;
    flags: (0x001a) ACC_PRIVATE, ACC_STATIC, ACC_FINAL
    Code:
      stack=21, locals=7, args_size=2
         0: new           #26                 // class scala/xml/Elem
         3: dup
         4: aconst_null
         5: ldc           #212                // String dependency
         7: getstatic     #32                 // Field scala/xml/Null$.MODULE$:Lscala/xml/Null$;
        10: getstatic     #37                 // Field scala/xml/TopScope$.MODULE$:Lscala/xml/TopScope$;
        13: iconst_0
        14: getstatic     #42                 // Field scala/xml/NodeSeq$.MODULE$:Lscala/xml/NodeSeq$;
        17: new           #44                 // class scala/xml/NodeBuffer
        20: dup
        21: invokespecial #45                 // Method scala/xml/NodeBuffer."<init>":()V
        24: astore_2
        25: aload_2
        26: new           #47                 // class scala/xml/Text
        29: dup
        30: ldc           #157                // String \n
        32: invokespecial #52                 // Method scala/xml/Text."<init>":(Ljava/lang/String;)V
        35: invokevirtual #56                 // Method scala/xml/NodeBuffer.$amp$plus:(Ljava/lang/Object;)Lscala/xml/NodeBuffer;
        38: pop
        39: aload_2
        40: new           #26                 // class scala/xml/Elem
        43: dup
        44: aconst_null
        45: ldc           #58                 // String groupId
        47: getstatic     #32                 // Field scala/xml/Null$.MODULE$:Lscala/xml/Null$;
        50: getstatic     #37                 // Field scala/xml/TopScope$.MODULE$:Lscala/xml/TopScope$;
        53: iconst_0
        54: getstatic     #42                 // Field scala/xml/NodeSeq$.MODULE$:Lscala/xml/NodeSeq$;
        57: new           #44                 // class scala/xml/NodeBuffer
        60: dup
        61: invokespecial #45                 // Method scala/xml/NodeBuffer."<init>":()V
        64: astore_3
        65: aload_3
        66: new           #60                 // class coursier/core/Organization
        69: dup
        70: aload_1
        71: invokevirtual #215                // Method coursier/core/Dependency.module:()Lcoursier/core/Module;
        74: invokevirtual #72                 // Method coursier/core/Module.organization:()Ljava/lang/String;
        77: invokespecial #73                 // Method coursier/core/Organization."<init>":(Ljava/lang/String;)V
        80: invokevirtual #56                 // Method scala/xml/NodeBuffer.$amp$plus:(Ljava/lang/Object;)Lscala/xml/NodeBuffer;
        83: pop
        84: aload_3
        85: invokevirtual #77                 // Method scala/xml/NodeSeq$.seqToNodeSeq:(Lscala/collection/Seq;)Lscala/xml/NodeSeq;
        88: invokespecial #80                 // Method scala/xml/Elem."<init>":(Ljava/lang/String;Ljava/lang/String;Lscala/xml/MetaData;Lscala/xml/NamespaceBinding;ZLscala/collection/immutable/Seq;)V
        91: invokevirtual #56                 // Method scala/xml/NodeBuffer.$amp$plus:(Ljava/lang/Object;)Lscala/xml/NodeBuffer;
        94: pop
        95: aload_2
        96: new           #47                 // class scala/xml/Text
        99: dup
       100: ldc           #157                // String \n
       102: invokespecial #52                 // Method scala/xml/Text."<init>":(Ljava/lang/String;)V
       105: invokevirtual #56                 // Method scala/xml/NodeBuffer.$amp$plus:(Ljava/lang/Object;)Lscala/xml/NodeBuffer;
       108: pop
       109: aload_2
       110: new           #26                 // class scala/xml/Elem
       113: dup
       114: aconst_null
       115: ldc           #84                 // String artifactId
       117: getstatic     #32                 // Field scala/xml/Null$.MODULE$:Lscala/xml/Null$;
       120: getstatic     #37                 // Field scala/xml/TopScope$.MODULE$:Lscala/xml/TopScope$;
       123: iconst_0
       124: getstatic     #42                 // Field scala/xml/NodeSeq$.MODULE$:Lscala/xml/NodeSeq$;
       127: new           #44                 // class scala/xml/NodeBuffer
       130: dup
       131: invokespecial #45                 // Method scala/xml/NodeBuffer."<init>":()V
       134: astore        4
       136: aload         4
       138: new           #86                 // class coursier/core/ModuleName
       141: dup
       142: aload_1
       143: invokevirtual #215                // Method coursier/core/Dependency.module:()Lcoursier/core/Module;
       146: invokevirtual #89                 // Method coursier/core/Module.name:()Ljava/lang/String;
       149: invokespecial #90                 // Method coursier/core/ModuleName."<init>":(Ljava/lang/String;)V
       152: invokevirtual #56                 // Method scala/xml/NodeBuffer.$amp$plus:(Ljava/lang/Object;)Lscala/xml/NodeBuffer;
       155: pop
       156: aload         4
       158: invokevirtual #77                 // Method scala/xml/NodeSeq$.seqToNodeSeq:(Lscala/collection/Seq;)Lscala/xml/NodeSeq;
       161: invokespecial #80                 // Method scala/xml/Elem."<init>":(Ljava/lang/String;Ljava/lang/String;Lscala/xml/MetaData;Lscala/xml/NamespaceBinding;ZLscala/collection/immutable/Seq;)V
       164: invokevirtual #56                 // Method scala/xml/NodeBuffer.$amp$plus:(Ljava/lang/Object;)Lscala/xml/NodeBuffer;
       167: pop
       168: aload_2
       169: new           #47                 // class scala/xml/Text
       172: dup
       173: ldc           #157                // String \n
       175: invokespecial #52                 // Method scala/xml/Text."<init>":(Ljava/lang/String;)V
       178: invokevirtual #56                 // Method scala/xml/NodeBuffer.$amp$plus:(Ljava/lang/Object;)Lscala/xml/NodeBuffer;
       181: pop
       182: aload_2
       183: aload_1
       184: invokevirtual #216                // Method coursier/core/Dependency.version:()Ljava/lang/String;
       187: invokevirtual #217                // Method java/lang/String.isEmpty:()Z
       190: ifeq          199
       193: getstatic     #173                // Field scala/collection/immutable/Nil$.MODULE$:Lscala/collection/immutable/Nil$;
       196: goto          253
       199: new           #219                // class scala/collection/immutable/$colon$colon
       202: dup
       203: new           #26                 // class scala/xml/Elem
       206: dup
       207: aconst_null
       208: ldc           #149                // String version
       210: getstatic     #32                 // Field scala/xml/Null$.MODULE$:Lscala/xml/Null$;
       213: getstatic     #37                 // Field scala/xml/TopScope$.MODULE$:Lscala/xml/TopScope$;
       216: iconst_0
       217: getstatic     #42                 // Field scala/xml/NodeSeq$.MODULE$:Lscala/xml/NodeSeq$;
       220: new           #44                 // class scala/xml/NodeBuffer
       223: dup
       224: invokespecial #45                 // Method scala/xml/NodeBuffer."<init>":()V
       227: astore        5
       229: aload         5
       231: aload_1
       232: invokevirtual #216                // Method coursier/core/Dependency.version:()Ljava/lang/String;
       235: invokevirtual #56                 // Method scala/xml/NodeBuffer.$amp$plus:(Ljava/lang/Object;)Lscala/xml/NodeBuffer;
       238: pop
       239: aload         5
       241: invokevirtual #77                 // Method scala/xml/NodeSeq$.seqToNodeSeq:(Lscala/collection/Seq;)Lscala/xml/NodeSeq;
       244: invokespecial #80                 // Method scala/xml/Elem."<init>":(Ljava/lang/String;Ljava/lang/String;Lscala/xml/MetaData;Lscala/xml/NamespaceBinding;ZLscala/collection/immutable/Seq;)V
       247: getstatic     #173                // Field scala/collection/immutable/Nil$.MODULE$:Lscala/collection/immutable/Nil$;
       250: invokespecial #222                // Method scala/collection/immutable/$colon$colon."<init>":(Ljava/lang/Object;Lscala/collection/immutable/List;)V
       253: invokevirtual #56                 // Method scala/xml/NodeBuffer.$amp$plus:(Ljava/lang/Object;)Lscala/xml/NodeBuffer;
       256: pop
       257: aload_2
       258: new           #47                 // class scala/xml/Text
       261: dup
       262: ldc           #157                // String \n
       264: invokespecial #52                 // Method scala/xml/Text."<init>":(Ljava/lang/String;)V
       267: invokevirtual #56                 // Method scala/xml/NodeBuffer.$amp$plus:(Ljava/lang/Object;)Lscala/xml/NodeBuffer;
       270: pop
       271: aload_2
       272: getstatic     #229                // Field coursier/core/Configuration$.MODULE$:Lcoursier/core/Configuration$;
       275: aload_0
       276: invokevirtual #233                // Method coursier/core/Configuration$.isEmpty$extension:(Ljava/lang/String;)Z
       279: ifeq          288
       282: getstatic     #173                // Field scala/collection/immutable/Nil$.MODULE$:Lscala/collection/immutable/Nil$;
       285: goto          339
       288: new           #219                // class scala/collection/immutable/$colon$colon
       291: dup
       292: new           #26                 // class scala/xml/Elem
       295: dup
       296: aconst_null
       297: ldc           #235                // String scope
       299: getstatic     #32                 // Field scala/xml/Null$.MODULE$:Lscala/xml/Null$;
       302: getstatic     #37                 // Field scala/xml/TopScope$.MODULE$:Lscala/xml/TopScope$;
       305: iconst_0
       306: getstatic     #42                 // Field scala/xml/NodeSeq$.MODULE$:Lscala/xml/NodeSeq$;
       309: new           #44                 // class scala/xml/NodeBuffer
       312: dup
       313: invokespecial #45                 // Method scala/xml/NodeBuffer."<init>":()V
       316: astore        6
       318: aload         6
       320: aload_0
       321: invokevirtual #56                 // Method scala/xml/NodeBuffer.$amp$plus:(Ljava/lang/Object;)Lscala/xml/NodeBuffer;
       324: pop
       325: aload         6
       327: invokevirtual #77                 // Method scala/xml/NodeSeq$.seqToNodeSeq:(Lscala/collection/Seq;)Lscala/xml/NodeSeq;
       330: invokespecial #80                 // Method scala/xml/Elem."<init>":(Ljava/lang/String;Ljava/lang/String;Lscala/xml/MetaData;Lscala/xml/NamespaceBinding;ZLscala/collection/immutable/Seq;)V
       333: getstatic     #173                // Field scala/collection/immutable/Nil$.MODULE$:Lscala/collection/immutable/Nil$;
       336: invokespecial #222                // Method scala/collection/immutable/$colon$colon."<init>":(Ljava/lang/Object;Lscala/collection/immutable/List;)V
       339: invokevirtual #56                 // Method scala/xml/NodeBuffer.$amp$plus:(Ljava/lang/Object;)Lscala/xml/NodeBuffer;
       342: pop
       343: aload_2
       344: new           #47                 // class scala/xml/Text
       347: dup
       348: ldc           #82                 // String \n
       350: invokespecial #52                 // Method scala/xml/Text."<init>":(Ljava/lang/String;)V
       353: invokevirtual #56                 // Method scala/xml/NodeBuffer.$amp$plus:(Ljava/lang/Object;)Lscala/xml/NodeBuffer;
       356: pop
       357: aload_2
       358: invokevirtual #77                 // Method scala/xml/NodeSeq$.seqToNodeSeq:(Lscala/collection/Seq;)Lscala/xml/NodeSeq;
       361: invokespecial #80                 // Method scala/xml/Elem."<init>":(Ljava/lang/String;Ljava/lang/String;Lscala/xml/MetaData;Lscala/xml/NamespaceBinding;ZLscala/collection/immutable/Seq;)V
       364: areturn
      StackMapTable: number_of_entries = 4
        frame_type = 255 /* full_frame */
          offset_delta = 199
          locals = [ class java/lang/String, class coursier/core/Dependency, class scala/xml/NodeBuffer, class scala/xml/NodeBuffer, class scala/xml/NodeBuffer ]
          stack = [ uninitialized 0, uninitialized 0, null, class java/lang/String, class scala/xml/Null$, class scala/xml/TopScope$, int, class scala/xml/NodeSeq$, class scala/xml/NodeBuffer ]
        frame_type = 255 /* full_frame */
          offset_delta = 53
          locals = [ class java/lang/String, class coursier/core/Dependency, class scala/xml/NodeBuffer, class scala/xml/NodeBuffer, class scala/xml/NodeBuffer ]
          stack = [ uninitialized 0, uninitialized 0, null, class java/lang/String, class scala/xml/Null$, class scala/xml/TopScope$, int, class scala/xml/NodeSeq$, class scala/xml/NodeBuffer, class scala/collection/immutable/List ]
        frame_type = 255 /* full_frame */
          offset_delta = 34
          locals = [ class java/lang/String, class coursier/core/Dependency, class scala/xml/NodeBuffer, class scala/xml/NodeBuffer, class scala/xml/NodeBuffer ]
          stack = [ uninitialized 0, uninitialized 0, null, class java/lang/String, class scala/xml/Null$, class scala/xml/TopScope$, int, class scala/xml/NodeSeq$, class scala/xml/NodeBuffer ]
        frame_type = 255 /* full_frame */
          offset_delta = 50
          locals = [ class java/lang/String, class coursier/core/Dependency, class scala/xml/NodeBuffer, class scala/xml/NodeBuffer, class scala/xml/NodeBuffer ]
          stack = [ uninitialized 0, uninitialized 0, null, class java/lang/String, class scala/xml/Null$, class scala/xml/TopScope$, int, class scala/xml/NodeSeq$, class scala/xml/NodeBuffer, class scala/collection/immutable/List ]
      LineNumberTable:
        line 10: 0
        line 11: 40
        line 10: 95
        line 11: 96
        line 10: 109
        line 12: 110
        line 10: 168
        line 12: 169
        line 10: 182
        line 14: 183
        line 15: 193
        line 17: 199
        line 10: 257
        line 18: 258
        line 10: 271
        line 20: 272
        line 21: 282
        line 23: 288
        line 10: 343
        line 24: 344
        line 10: 357
      LocalVariableTable:
        Start  Length  Slot  Name   Signature
           65      20     3  $buf   Lscala/xml/NodeBuffer;
          136      22     4  $buf   Lscala/xml/NodeBuffer;
          229      12     5  $buf   Lscala/xml/NodeBuffer;
          318       9     6  $buf   Lscala/xml/NodeBuffer;
           25     333     2  $buf   Lscala/xml/NodeBuffer;
            0     365     0 config   Ljava/lang/String;
            0     365     1   dep   Lcoursier/core/Dependency;
    MethodParameters:
      Name                           Flags
      config                         final
      dep                            final

  public static final scala.xml.Elem $anonfun$project$1(java.lang.String);
    descriptor: (Ljava/lang/String;)Lscala/xml/Elem;
    flags: (0x1019) ACC_PUBLIC, ACC_STATIC, ACC_FINAL, ACC_SYNTHETIC
    Code:
      stack=10, locals=2, args_size=1
         0: new           #26                 // class scala/xml/Elem
         3: dup
         4: aconst_null
         5: ldc           #239                // String packaging
         7: getstatic     #32                 // Field scala/xml/Null$.MODULE$:Lscala/xml/Null$;
        10: getstatic     #37                 // Field scala/xml/TopScope$.MODULE$:Lscala/xml/TopScope$;
        13: iconst_0
        14: getstatic     #42                 // Field scala/xml/NodeSeq$.MODULE$:Lscala/xml/NodeSeq$;
        17: new           #44                 // class scala/xml/NodeBuffer
        20: dup
        21: invokespecial #45                 // Method scala/xml/NodeBuffer."<init>":()V
        24: astore_1
        25: aload_1
        26: aload_0
        27: invokevirtual #56                 // Method scala/xml/NodeBuffer.$amp$plus:(Ljava/lang/Object;)Lscala/xml/NodeBuffer;
        30: pop
        31: aload_1
        32: invokevirtual #77                 // Method scala/xml/NodeSeq$.seqToNodeSeq:(Lscala/collection/Seq;)Lscala/xml/NodeSeq;
        35: invokespecial #80                 // Method scala/xml/Elem."<init>":(Ljava/lang/String;Ljava/lang/String;Lscala/xml/MetaData;Lscala/xml/NamespaceBinding;ZLscala/collection/immutable/Seq;)V
        38: areturn
      LineNumberTable:
        line 34: 0
      LocalVariableTable:
        Start  Length  Slot  Name   Signature
           25       7     1  $buf   Lscala/xml/NodeBuffer;
            0      39     0     p   Ljava/lang/String;
    MethodParameters:
      Name                           Flags
      p                              final

  public static final scala.xml.Elem $anonfun$project$2(scala.Tuple2);
    descriptor: (Lscala/Tuple2;)Lscala/xml/Elem;
    flags: (0x1019) ACC_PUBLIC, ACC_STATIC, ACC_FINAL, ACC_SYNTHETIC
    Code:
      stack=3, locals=5, args_size=1
         0: aload_0
         1: astore_2
         2: aload_2
         3: ifnull        36
         6: aload_2
         7: invokevirtual #246                // Method scala/Tuple2._1:()Ljava/lang/Object;
        10: checkcast     #248                // class coursier/core/Configuration
        13: invokevirtual #251                // Method coursier/core/Configuration.value:()Ljava/lang/String;
        16: astore_3
        17: aload_2
        18: invokevirtual #254                // Method scala/Tuple2._2:()Ljava/lang/Object;
        21: checkcast     #214                // class coursier/core/Dependency
        24: astore        4
        26: aload_3
        27: aload         4
        29: invokestatic  #256                // Method dependencyNode$1:(Ljava/lang/String;Lcoursier/core/Dependency;)Lscala/xml/Elem;
        32: astore_1
        33: goto          48
        36: goto          39
        39: new           #258                // class scala/MatchError
        42: dup
        43: aload_2
        44: invokespecial #261                // Method scala/MatchError."<init>":(Ljava/lang/Object;)V
        47: athrow
        48: aload_1
        49: areturn
      StackMapTable: number_of_entries = 3
        frame_type = 253 /* append */
          offset_delta = 36
          locals = [ top, class scala/Tuple2 ]
        frame_type = 2 /* same */
        frame_type = 255 /* full_frame */
          offset_delta = 8
          locals = [ class scala/Tuple2, class scala/xml/Elem, class scala/Tuple2, class java/lang/String, class coursier/core/Dependency ]
          stack = []
      LineNumberTable:
        line 53: 0
        line 54: 2
        line 55: 26
        line 54: 36
        line 53: 39
      LocalVariableTable:
        Start  Length  Slot  Name   Signature
           17      19     3 config   Ljava/lang/String;
           26      10     4   dep   Lcoursier/core/Dependency;
            0      50     0  x0$1   Lscala/Tuple2;
    MethodParameters:
      Name                           Flags
      x0$1                           final

  public static final scala.xml.Elem $anonfun$project$3(scala.Tuple2);
    descriptor: (Lscala/Tuple2;)Lscala/xml/Elem;
    flags: (0x1019) ACC_PUBLIC, ACC_STATIC, ACC_FINAL, ACC_SYNTHETIC
    Code:
      stack=3, locals=5, args_size=1
         0: aload_0
         1: astore_2
         2: aload_2
         3: ifnull        36
         6: aload_2
         7: invokevirtual #246                // Method scala/Tuple2._1:()Ljava/lang/Object;
        10: checkcast     #248                // class coursier/core/Configuration
        13: invokevirtual #251                // Method coursier/core/Configuration.value:()Ljava/lang/String;
        16: astore_3
        17: aload_2
        18: invokevirtual #254                // Method scala/Tuple2._2:()Ljava/lang/Object;
        21: checkcast     #214                // class coursier/core/Dependency
        24: astore        4
        26: aload_3
        27: aload         4
        29: invokestatic  #256                // Method dependencyNode$1:(Ljava/lang/String;Lcoursier/core/Dependency;)Lscala/xml/Elem;
        32: astore_1
        33: goto          48
        36: goto          39
        39: new           #258                // class scala/MatchError
        42: dup
        43: aload_2
        44: invokespecial #261                // Method scala/MatchError."<init>":(Ljava/lang/Object;)V
        47: athrow
        48: aload_1
        49: areturn
      StackMapTable: number_of_entries = 3
        frame_type = 253 /* append */
          offset_delta = 36
          locals = [ top, class scala/Tuple2 ]
        frame_type = 2 /* same */
        frame_type = 255 /* full_frame */
          offset_delta = 8
          locals = [ class scala/Tuple2, class scala/xml/Elem, class scala/Tuple2, class java/lang/String, class coursier/core/Dependency ]
          stack = []
      LineNumberTable:
        line 65: 0
        line 66: 2
        line 67: 26
        line 66: 36
        line 65: 39
      LocalVariableTable:
        Start  Length  Slot  Name   Signature
           17      19     3 config   Ljava/lang/String;
           26      10     4   dep   Lcoursier/core/Dependency;
            0      50     0  x0$2   Lscala/Tuple2;
    MethodParameters:
      Name                           Flags
      x0$2                           final

  private coursier.maven.WritePom$();
    descriptor: ()V
    flags: (0x0002) ACC_PRIVATE
    Code:
      stack=1, locals=1, args_size=1
         0: aload_0
         1: invokespecial #264                // Method java/lang/Object."<init>":()V
         4: return
      LineNumberTable:
        line 77: 0
        line 5: 4
      LocalVariableTable:
        Start  Length  Slot  Name   Signature
            0       5     0  this   Lcoursier/maven/WritePom$;

  private static java.lang.Object $deserializeLambda$(java.lang.invoke.SerializedLambda);
    descriptor: (Ljava/lang/invoke/SerializedLambda;)Ljava/lang/Object;
    flags: (0x100a) ACC_PRIVATE, ACC_STATIC, ACC_SYNTHETIC
    Code:
      stack=1, locals=1, args_size=1
         0: aload_0
         1: invokedynamic #276,  0            // InvokeDynamic #3:lambdaDeserialize:(Ljava/lang/invoke/SerializedLambda;)Ljava/lang/Object;
         6: areturn
}
InnerClasses:
  public static final #10= #7 of #9;      // Lookup=class java/lang/invoke/MethodHandles$Lookup of class java/lang/invoke/MethodHandles
SourceFile: "WritePom.scala"
BootstrapMethods:
  0: #112 REF_invokeStatic java/lang/invoke/LambdaMetafactory.altMetafactory:(Ljava/lang/invoke/MethodHandles$Lookup;Ljava/lang/String;Ljava/lang/invoke/MethodType;[Ljava/lang/Object;)Ljava/lang/invoke/CallSite;
    Method arguments:
      #97 (Ljava/lang/Object;)Ljava/lang/Object;
      #102 REF_invokeStatic coursier/maven/WritePom$.$anonfun$project$1:(Ljava/lang/String;)Lscala/xml/Elem;
      #103 (Ljava/lang/String;)Lscala/xml/Elem;
      #104 5
      #105 1
      #103 (Ljava/lang/String;)Lscala/xml/Elem;
  1: #112 REF_invokeStatic java/lang/invoke/LambdaMetafactory.altMetafactory:(Ljava/lang/invoke/MethodHandles$Lookup;Ljava/lang/String;Ljava/lang/invoke/MethodType;[Ljava/lang/Object;)Ljava/lang/invoke/CallSite;
    Method arguments:
      #97 (Ljava/lang/Object;)Ljava/lang/Object;
      #181 REF_invokeStatic coursier/maven/WritePom$.$anonfun$project$2:(Lscala/Tuple2;)Lscala/xml/Elem;
      #182 (Lscala/Tuple2;)Lscala/xml/Elem;
      #104 5
      #105 1
      #182 (Lscala/Tuple2;)Lscala/xml/Elem;
  2: #112 REF_invokeStatic java/lang/invoke/LambdaMetafactory.altMetafactory:(Ljava/lang/invoke/MethodHandles$Lookup;Ljava/lang/String;Ljava/lang/invoke/MethodType;[Ljava/lang/Object;)Ljava/lang/invoke/CallSite;
    Method arguments:
      #97 (Ljava/lang/Object;)Ljava/lang/Object;
      #198 REF_invokeStatic coursier/maven/WritePom$.$anonfun$project$3:(Lscala/Tuple2;)Lscala/xml/Elem;
      #182 (Lscala/Tuple2;)Lscala/xml/Elem;
      #104 5
      #105 1
      #182 (Lscala/Tuple2;)Lscala/xml/Elem;
  3: #273 REF_invokeStatic scala/runtime/LambdaDeserialize.bootstrap:(Ljava/lang/invoke/MethodHandles$Lookup;Ljava/lang/String;Ljava/lang/invoke/MethodType;[Ljava/lang/invoke/MethodHandle;)Ljava/lang/invoke/CallSite;
    Method arguments:
      #102 REF_invokeStatic coursier/maven/WritePom$.$anonfun$project$1:(Ljava/lang/String;)Lscala/xml/Elem;
      #181 REF_invokeStatic coursier/maven/WritePom$.$anonfun$project$2:(Lscala/Tuple2;)Lscala/xml/Elem;
      #198 REF_invokeStatic coursier/maven/WritePom$.$anonfun$project$3:(Lscala/Tuple2;)Lscala/xml/Elem;
  ScalaInlineInfo: length = 0x22 (unknown attribute)
   01 01 00 06 00 62 00 63 01 00 AF 00 B0 01 00 BF
   00 B0 01 00 0F 00 0E 01 00 CF 00 D0 01 00 14 00
   15 01
  Scala: length = 0x0 (unknown attribute)

