Classfile /Users/mw/Projects/slang-braindump/.jar/jar11/assemble/slang-braindump/assemble/content/coursier/util/shaded/org/jsoup/nodes/Attribute.class
  Last modified May 29, 2022; size 7392 bytes
  SHA-256 checksum 5d2299cc667dab34a2e3aa9b38c55415db1ef1335c4eb8337687f001ce368163
  Compiled from "Attribute.java"
public class coursier.util.shaded.org.jsoup.nodes.Attribute extends java.lang.Object implements java.util.Map$Entry<java.lang.String, java.lang.String>, java.lang.Cloneable
  minor version: 0
  major version: 51
  flags: (0x0021) ACC_PUBLIC, ACC_SUPER
  this_class: #2                          // coursier/util/shaded/org/jsoup/nodes/Attribute
  super_class: #5                         // java/lang/Object
  interfaces: 2, fields: 4, methods: 25, attributes: 3
Constant pool:
    #1 = Utf8               coursier/util/shaded/org/jsoup/nodes/Attribute
    #2 = Class              #1            // coursier/util/shaded/org/jsoup/nodes/Attribute
    #3 = Utf8               Ljava/lang/Object;Ljava/util/Map$Entry<Ljava/lang/String;Ljava/lang/String;>;Ljava/lang/Cloneable;
    #4 = Utf8               java/lang/Object
    #5 = Class              #4            // java/lang/Object
    #6 = Utf8               java/util/Map$Entry
    #7 = Class              #6            // java/util/Map$Entry
    #8 = Utf8               java/lang/Cloneable
    #9 = Class              #8            // java/lang/Cloneable
   #10 = Utf8               Attribute.java
   #11 = Utf8               coursier/util/shaded/org/jsoup/nodes/Document$OutputSettings
   #12 = Class              #11           // coursier/util/shaded/org/jsoup/nodes/Document$OutputSettings
   #13 = Utf8               coursier/util/shaded/org/jsoup/nodes/Document
   #14 = Class              #13           // coursier/util/shaded/org/jsoup/nodes/Document
   #15 = Utf8               OutputSettings
   #16 = Utf8               coursier/util/shaded/org/jsoup/nodes/Document$OutputSettings$Syntax
   #17 = Class              #16           // coursier/util/shaded/org/jsoup/nodes/Document$OutputSettings$Syntax
   #18 = Utf8               Syntax
   #19 = Utf8               java/util/Map
   #20 = Class              #19           // java/util/Map
   #21 = Utf8               Entry
   #22 = Utf8               booleanAttributes
   #23 = Utf8               [Ljava/lang/String;
   #24 = Utf8               key
   #25 = Utf8               Ljava/lang/String;
   #26 = Utf8               val
   #27 = Utf8               parent
   #28 = Utf8               Lcoursier/util/shaded/org/jsoup/nodes/Attributes;
   #29 = Utf8               <init>
   #30 = Utf8               (Ljava/lang/String;Ljava/lang/String;)V
   #31 = Utf8               (Ljava/lang/String;Ljava/lang/String;Lcoursier/util/shaded/org/jsoup/nodes/Attributes;)V
   #32 = NameAndType        #29:#31       // "<init>":(Ljava/lang/String;Ljava/lang/String;Lcoursier/util/shaded/org/jsoup/nodes/Attributes;)V
   #33 = Methodref          #2.#32        // coursier/util/shaded/org/jsoup/nodes/Attribute."<init>":(Ljava/lang/String;Ljava/lang/String;Lcoursier/util/shaded/org/jsoup/nodes/Attributes;)V
   #34 = Utf8               this
   #35 = Utf8               Lcoursier/util/shaded/org/jsoup/nodes/Attribute;
   #36 = Utf8               value
   #37 = Utf8               ()V
   #38 = NameAndType        #29:#37       // "<init>":()V
   #39 = Methodref          #5.#38        // java/lang/Object."<init>":()V
   #40 = Utf8               coursier/util/shaded/org/jsoup/helper/Validate
   #41 = Class              #40           // coursier/util/shaded/org/jsoup/helper/Validate
   #42 = Utf8               notNull
   #43 = Utf8               (Ljava/lang/Object;)V
   #44 = NameAndType        #42:#43       // notNull:(Ljava/lang/Object;)V
   #45 = Methodref          #41.#44       // coursier/util/shaded/org/jsoup/helper/Validate.notNull:(Ljava/lang/Object;)V
   #46 = Utf8               java/lang/String
   #47 = Class              #46           // java/lang/String
   #48 = Utf8               trim
   #49 = Utf8               ()Ljava/lang/String;
   #50 = NameAndType        #48:#49       // trim:()Ljava/lang/String;
   #51 = Methodref          #47.#50       // java/lang/String.trim:()Ljava/lang/String;
   #52 = Utf8               notEmpty
   #53 = Utf8               (Ljava/lang/String;)V
   #54 = NameAndType        #52:#53       // notEmpty:(Ljava/lang/String;)V
   #55 = Methodref          #41.#54       // coursier/util/shaded/org/jsoup/helper/Validate.notEmpty:(Ljava/lang/String;)V
   #56 = NameAndType        #24:#25       // key:Ljava/lang/String;
   #57 = Fieldref           #2.#56        // coursier/util/shaded/org/jsoup/nodes/Attribute.key:Ljava/lang/String;
   #58 = NameAndType        #26:#25       // val:Ljava/lang/String;
   #59 = Fieldref           #2.#58        // coursier/util/shaded/org/jsoup/nodes/Attribute.val:Ljava/lang/String;
   #60 = NameAndType        #27:#28       // parent:Lcoursier/util/shaded/org/jsoup/nodes/Attributes;
   #61 = Fieldref           #2.#60        // coursier/util/shaded/org/jsoup/nodes/Attribute.parent:Lcoursier/util/shaded/org/jsoup/nodes/Attributes;
   #62 = Utf8               getKey
   #63 = Utf8               setKey
   #64 = Utf8               coursier/util/shaded/org/jsoup/nodes/Attributes
   #65 = Class              #64           // coursier/util/shaded/org/jsoup/nodes/Attributes
   #66 = Utf8               indexOfKey
   #67 = Utf8               (Ljava/lang/String;)I
   #68 = NameAndType        #66:#67       // indexOfKey:(Ljava/lang/String;)I
   #69 = Methodref          #65.#68       // coursier/util/shaded/org/jsoup/nodes/Attributes.indexOfKey:(Ljava/lang/String;)I
   #70 = Utf8               keys
   #71 = NameAndType        #70:#23       // keys:[Ljava/lang/String;
   #72 = Fieldref           #65.#71       // coursier/util/shaded/org/jsoup/nodes/Attributes.keys:[Ljava/lang/String;
   #73 = Utf8               i
   #74 = Utf8               I
   #75 = Utf8               getValue
   #76 = Utf8               checkNotNull
   #77 = Utf8               (Ljava/lang/String;)Ljava/lang/String;
   #78 = NameAndType        #76:#77       // checkNotNull:(Ljava/lang/String;)Ljava/lang/String;
   #79 = Methodref          #65.#78       // coursier/util/shaded/org/jsoup/nodes/Attributes.checkNotNull:(Ljava/lang/String;)Ljava/lang/String;
   #80 = Utf8               hasDeclaredValue
   #81 = Utf8               ()Z
   #82 = Utf8               setValue
   #83 = Utf8               get
   #84 = NameAndType        #83:#77       // get:(Ljava/lang/String;)Ljava/lang/String;
   #85 = Methodref          #65.#84       // coursier/util/shaded/org/jsoup/nodes/Attributes.get:(Ljava/lang/String;)Ljava/lang/String;
   #86 = Utf8               vals
   #87 = NameAndType        #86:#23       // vals:[Ljava/lang/String;
   #88 = Fieldref           #65.#87       // coursier/util/shaded/org/jsoup/nodes/Attributes.vals:[Ljava/lang/String;
   #89 = Utf8               oldVal
   #90 = Utf8               html
   #91 = Utf8               java/io/IOException
   #92 = Class              #91           // java/io/IOException
   #93 = Utf8               coursier/util/shaded/org/jsoup/internal/StringUtil
   #94 = Class              #93           // coursier/util/shaded/org/jsoup/internal/StringUtil
   #95 = Utf8               borrowBuilder
   #96 = Utf8               ()Ljava/lang/StringBuilder;
   #97 = NameAndType        #95:#96       // borrowBuilder:()Ljava/lang/StringBuilder;
   #98 = Methodref          #94.#97       // coursier/util/shaded/org/jsoup/internal/StringUtil.borrowBuilder:()Ljava/lang/StringBuilder;
   #99 = Utf8
  #100 = String             #99           //
  #101 = NameAndType        #29:#53       // "<init>":(Ljava/lang/String;)V
  #102 = Methodref          #14.#101      // coursier/util/shaded/org/jsoup/nodes/Document."<init>":(Ljava/lang/String;)V
  #103 = Utf8               outputSettings
  #104 = Utf8               ()Lcoursier/util/shaded/org/jsoup/nodes/Document$OutputSettings;
  #105 = NameAndType        #103:#104     // outputSettings:()Lcoursier/util/shaded/org/jsoup/nodes/Document$OutputSettings;
  #106 = Methodref          #14.#105      // coursier/util/shaded/org/jsoup/nodes/Document.outputSettings:()Lcoursier/util/shaded/org/jsoup/nodes/Document$OutputSettings;
  #107 = Utf8               (Ljava/lang/Appendable;Lcoursier/util/shaded/org/jsoup/nodes/Document$OutputSettings;)V
  #108 = NameAndType        #90:#107      // html:(Ljava/lang/Appendable;Lcoursier/util/shaded/org/jsoup/nodes/Document$OutputSettings;)V
  #109 = Methodref          #2.#108       // coursier/util/shaded/org/jsoup/nodes/Attribute.html:(Ljava/lang/Appendable;Lcoursier/util/shaded/org/jsoup/nodes/Document$OutputSettings;)V
  #110 = Utf8               java/lang/StringBuilder
  #111 = Class              #110          // java/lang/StringBuilder
  #112 = Utf8               coursier/util/shaded/org/jsoup/SerializationException
  #113 = Class              #112          // coursier/util/shaded/org/jsoup/SerializationException
  #114 = Utf8               (Ljava/lang/Throwable;)V
  #115 = NameAndType        #29:#114      // "<init>":(Ljava/lang/Throwable;)V
  #116 = Methodref          #113.#115     // coursier/util/shaded/org/jsoup/SerializationException."<init>":(Ljava/lang/Throwable;)V
  #117 = Utf8               releaseBuilder
  #118 = Utf8               (Ljava/lang/StringBuilder;)Ljava/lang/String;
  #119 = NameAndType        #117:#118     // releaseBuilder:(Ljava/lang/StringBuilder;)Ljava/lang/String;
  #120 = Methodref          #94.#119      // coursier/util/shaded/org/jsoup/internal/StringUtil.releaseBuilder:(Ljava/lang/StringBuilder;)Ljava/lang/String;
  #121 = Utf8               exception
  #122 = Utf8               Ljava/io/IOException;
  #123 = Utf8               sb
  #124 = Utf8               Ljava/lang/StringBuilder;
  #125 = Utf8               (Ljava/lang/String;Ljava/lang/String;Ljava/lang/Appendable;Lcoursier/util/shaded/org/jsoup/nodes/Document$OutputSettings;)V
  #126 = Utf8               java/lang/Appendable
  #127 = Class              #126          // java/lang/Appendable
  #128 = Utf8               append
  #129 = Utf8               (Ljava/lang/CharSequence;)Ljava/lang/Appendable;
  #130 = NameAndType        #128:#129     // append:(Ljava/lang/CharSequence;)Ljava/lang/Appendable;
  #131 = InterfaceMethodref #127.#130     // java/lang/Appendable.append:(Ljava/lang/CharSequence;)Ljava/lang/Appendable;
  #132 = Utf8               shouldCollapseAttribute
  #133 = Utf8               (Ljava/lang/String;Ljava/lang/String;Lcoursier/util/shaded/org/jsoup/nodes/Document$OutputSettings;)Z
  #134 = NameAndType        #132:#133     // shouldCollapseAttribute:(Ljava/lang/String;Ljava/lang/String;Lcoursier/util/shaded/org/jsoup/nodes/Document$OutputSettings;)Z
  #135 = Methodref          #2.#134       // coursier/util/shaded/org/jsoup/nodes/Attribute.shouldCollapseAttribute:(Ljava/lang/String;Ljava/lang/String;Lcoursier/util/shaded/org/jsoup/nodes/Document$OutputSettings;)Z
  #136 = Utf8               =\"
  #137 = String             #136          // =\"
  #138 = Utf8               coursier/util/shaded/org/jsoup/nodes/Entities
  #139 = Class              #138          // coursier/util/shaded/org/jsoup/nodes/Entities
  #140 = Utf8               escape
  #141 = Utf8               (Ljava/lang/Appendable;Ljava/lang/String;Lcoursier/util/shaded/org/jsoup/nodes/Document$OutputSettings;ZZZ)V
  #142 = NameAndType        #140:#141     // escape:(Ljava/lang/Appendable;Ljava/lang/String;Lcoursier/util/shaded/org/jsoup/nodes/Document$OutputSettings;ZZZ)V
  #143 = Methodref          #139.#142     // coursier/util/shaded/org/jsoup/nodes/Entities.escape:(Ljava/lang/Appendable;Ljava/lang/String;Lcoursier/util/shaded/org/jsoup/nodes/Document$OutputSettings;ZZZ)V
  #144 = Utf8               (C)Ljava/lang/Appendable;
  #145 = NameAndType        #128:#144     // append:(C)Ljava/lang/Appendable;
  #146 = InterfaceMethodref #127.#145     // java/lang/Appendable.append:(C)Ljava/lang/Appendable;
  #147 = Utf8               accum
  #148 = Utf8               Ljava/lang/Appendable;
  #149 = Utf8               out
  #150 = Utf8               Lcoursier/util/shaded/org/jsoup/nodes/Document$OutputSettings;
  #151 = NameAndType        #90:#125      // html:(Ljava/lang/String;Ljava/lang/String;Ljava/lang/Appendable;Lcoursier/util/shaded/org/jsoup/nodes/Document$OutputSettings;)V
  #152 = Methodref          #2.#151       // coursier/util/shaded/org/jsoup/nodes/Attribute.html:(Ljava/lang/String;Ljava/lang/String;Ljava/lang/Appendable;Lcoursier/util/shaded/org/jsoup/nodes/Document$OutputSettings;)V
  #153 = Utf8               toString
  #154 = NameAndType        #90:#49       // html:()Ljava/lang/String;
  #155 = Methodref          #2.#154       // coursier/util/shaded/org/jsoup/nodes/Attribute.html:()Ljava/lang/String;
  #156 = Utf8               createFromEncoded
  #157 = Utf8               (Ljava/lang/String;Ljava/lang/String;)Lcoursier/util/shaded/org/jsoup/nodes/Attribute;
  #158 = Utf8               unescape
  #159 = Utf8               (Ljava/lang/String;Z)Ljava/lang/String;
  #160 = NameAndType        #158:#159     // unescape:(Ljava/lang/String;Z)Ljava/lang/String;
  #161 = Methodref          #139.#160     // coursier/util/shaded/org/jsoup/nodes/Entities.unescape:(Ljava/lang/String;Z)Ljava/lang/String;
  #162 = Utf8               unencodedKey
  #163 = Utf8               encodedValue
  #164 = Utf8               isDataAttribute
  #165 = Utf8               (Ljava/lang/String;)Z
  #166 = NameAndType        #164:#165     // isDataAttribute:(Ljava/lang/String;)Z
  #167 = Methodref          #2.#166       // coursier/util/shaded/org/jsoup/nodes/Attribute.isDataAttribute:(Ljava/lang/String;)Z
  #168 = Utf8               data-
  #169 = String             #168          // data-
  #170 = Utf8               startsWith
  #171 = NameAndType        #170:#165     // startsWith:(Ljava/lang/String;)Z
  #172 = Methodref          #47.#171      // java/lang/String.startsWith:(Ljava/lang/String;)Z
  #173 = Utf8               length
  #174 = Utf8               ()I
  #175 = NameAndType        #173:#174     // length:()I
  #176 = Methodref          #47.#175      // java/lang/String.length:()I
  #177 = Utf8               (Lcoursier/util/shaded/org/jsoup/nodes/Document$OutputSettings;)Z
  #178 = Utf8               syntax
  #179 = Utf8               ()Lcoursier/util/shaded/org/jsoup/nodes/Document$OutputSettings$Syntax;
  #180 = NameAndType        #178:#179     // syntax:()Lcoursier/util/shaded/org/jsoup/nodes/Document$OutputSettings$Syntax;
  #181 = Methodref          #12.#180      // coursier/util/shaded/org/jsoup/nodes/Document$OutputSettings.syntax:()Lcoursier/util/shaded/org/jsoup/nodes/Document$OutputSettings$Syntax;
  #182 = Utf8               Lcoursier/util/shaded/org/jsoup/nodes/Document$OutputSettings$Syntax;
  #183 = NameAndType        #90:#182      // html:Lcoursier/util/shaded/org/jsoup/nodes/Document$OutputSettings$Syntax;
  #184 = Fieldref           #17.#183      // coursier/util/shaded/org/jsoup/nodes/Document$OutputSettings$Syntax.html:Lcoursier/util/shaded/org/jsoup/nodes/Document$OutputSettings$Syntax;
  #185 = Utf8               equals
  #186 = Utf8               (Ljava/lang/Object;)Z
  #187 = NameAndType        #185:#186     // equals:(Ljava/lang/Object;)Z
  #188 = Methodref          #47.#187      // java/lang/String.equals:(Ljava/lang/Object;)Z
  #189 = Utf8               equalsIgnoreCase
  #190 = NameAndType        #189:#165     // equalsIgnoreCase:(Ljava/lang/String;)Z
  #191 = Methodref          #47.#190      // java/lang/String.equalsIgnoreCase:(Ljava/lang/String;)Z
  #192 = Utf8               isBooleanAttribute
  #193 = NameAndType        #192:#165     // isBooleanAttribute:(Ljava/lang/String;)Z
  #194 = Methodref          #2.#193       // coursier/util/shaded/org/jsoup/nodes/Attribute.isBooleanAttribute:(Ljava/lang/String;)Z
  #195 = NameAndType        #22:#23       // booleanAttributes:[Ljava/lang/String;
  #196 = Fieldref           #2.#195       // coursier/util/shaded/org/jsoup/nodes/Attribute.booleanAttributes:[Ljava/lang/String;
  #197 = Utf8               java/util/Arrays
  #198 = Class              #197          // java/util/Arrays
  #199 = Utf8               binarySearch
  #200 = Utf8               ([Ljava/lang/Object;Ljava/lang/Object;)I
  #201 = NameAndType        #199:#200     // binarySearch:([Ljava/lang/Object;Ljava/lang/Object;)I
  #202 = Methodref          #198.#201     // java/util/Arrays.binarySearch:([Ljava/lang/Object;Ljava/lang/Object;)I
  #203 = Utf8               getClass
  #204 = Utf8               ()Ljava/lang/Class;
  #205 = NameAndType        #203:#204     // getClass:()Ljava/lang/Class;
  #206 = Methodref          #5.#205       // java/lang/Object.getClass:()Ljava/lang/Class;
  #207 = Utf8               o
  #208 = Utf8               Ljava/lang/Object;
  #209 = Utf8               attribute
  #210 = Utf8               hashCode
  #211 = NameAndType        #210:#174     // hashCode:()I
  #212 = Methodref          #47.#211      // java/lang/String.hashCode:()I
  #213 = Utf8               result
  #214 = Utf8               clone
  #215 = Utf8               ()Lcoursier/util/shaded/org/jsoup/nodes/Attribute;
  #216 = Utf8               java/lang/CloneNotSupportedException
  #217 = Class              #216          // java/lang/CloneNotSupportedException
  #218 = Utf8               ()Ljava/lang/Object;
  #219 = NameAndType        #214:#218     // clone:()Ljava/lang/Object;
  #220 = Methodref          #5.#219       // java/lang/Object.clone:()Ljava/lang/Object;
  #221 = Utf8               java/lang/RuntimeException
  #222 = Class              #221          // java/lang/RuntimeException
  #223 = Methodref          #222.#115     // java/lang/RuntimeException."<init>":(Ljava/lang/Throwable;)V
  #224 = Utf8               e
  #225 = Utf8               Ljava/lang/CloneNotSupportedException;
  #226 = NameAndType        #214:#215     // clone:()Lcoursier/util/shaded/org/jsoup/nodes/Attribute;
  #227 = Methodref          #2.#226       // coursier/util/shaded/org/jsoup/nodes/Attribute.clone:()Lcoursier/util/shaded/org/jsoup/nodes/Attribute;
  #228 = Utf8               (Ljava/lang/Object;)Ljava/lang/Object;
  #229 = NameAndType        #82:#77       // setValue:(Ljava/lang/String;)Ljava/lang/String;
  #230 = Methodref          #2.#229       // coursier/util/shaded/org/jsoup/nodes/Attribute.setValue:(Ljava/lang/String;)Ljava/lang/String;
  #231 = NameAndType        #75:#49       // getValue:()Ljava/lang/String;
  #232 = Methodref          #2.#231       // coursier/util/shaded/org/jsoup/nodes/Attribute.getValue:()Ljava/lang/String;
  #233 = NameAndType        #62:#49       // getKey:()Ljava/lang/String;
  #234 = Methodref          #2.#233       // coursier/util/shaded/org/jsoup/nodes/Attribute.getKey:()Ljava/lang/String;
  #235 = Utf8               <clinit>
  #236 = Utf8               allowfullscreen
  #237 = String             #236          // allowfullscreen
  #238 = Utf8               async
  #239 = String             #238          // async
  #240 = Utf8               autofocus
  #241 = String             #240          // autofocus
  #242 = Utf8               checked
  #243 = String             #242          // checked
  #244 = Utf8               compact
  #245 = String             #244          // compact
  #246 = Utf8               declare
  #247 = String             #246          // declare
  #248 = Utf8               default
  #249 = String             #248          // default
  #250 = Utf8               defer
  #251 = String             #250          // defer
  #252 = Utf8               disabled
  #253 = String             #252          // disabled
  #254 = Utf8               formnovalidate
  #255 = String             #254          // formnovalidate
  #256 = Utf8               hidden
  #257 = String             #256          // hidden
  #258 = Utf8               inert
  #259 = String             #258          // inert
  #260 = Utf8               ismap
  #261 = String             #260          // ismap
  #262 = Utf8               itemscope
  #263 = String             #262          // itemscope
  #264 = Utf8               multiple
  #265 = String             #264          // multiple
  #266 = Utf8               muted
  #267 = String             #266          // muted
  #268 = Utf8               nohref
  #269 = String             #268          // nohref
  #270 = Utf8               noresize
  #271 = String             #270          // noresize
  #272 = Utf8               noshade
  #273 = String             #272          // noshade
  #274 = Utf8               novalidate
  #275 = String             #274          // novalidate
  #276 = Utf8               nowrap
  #277 = String             #276          // nowrap
  #278 = Utf8               open
  #279 = String             #278          // open
  #280 = Utf8               readonly
  #281 = String             #280          // readonly
  #282 = Utf8               required
  #283 = String             #282          // required
  #284 = Utf8               reversed
  #285 = String             #284          // reversed
  #286 = Utf8               seamless
  #287 = String             #286          // seamless
  #288 = Utf8               selected
  #289 = String             #288          // selected
  #290 = Utf8               sortable
  #291 = String             #290          // sortable
  #292 = Utf8               truespeed
  #293 = String             #292          // truespeed
  #294 = Utf8               typemustmatch
  #295 = String             #294          // typemustmatch
  #296 = Utf8               Code
  #297 = Utf8               LineNumberTable
  #298 = Utf8               LocalVariableTable
  #299 = Utf8               StackMapTable
  #300 = Utf8               Exceptions
  #301 = Utf8               InnerClasses
  #302 = Utf8               Signature
  #303 = Utf8               SourceFile
{
  private static final java.lang.String[] booleanAttributes;
    descriptor: [Ljava/lang/String;
    flags: (0x001a) ACC_PRIVATE, ACC_STATIC, ACC_FINAL

  private java.lang.String key;
    descriptor: Ljava/lang/String;
    flags: (0x0002) ACC_PRIVATE

  private java.lang.String val;
    descriptor: Ljava/lang/String;
    flags: (0x0002) ACC_PRIVATE

  coursier.util.shaded.org.jsoup.nodes.Attributes parent;
    descriptor: Lcoursier/util/shaded/org/jsoup/nodes/Attributes;
    flags: (0x0000)

  public coursier.util.shaded.org.jsoup.nodes.Attribute(java.lang.String, java.lang.String);
    descriptor: (Ljava/lang/String;Ljava/lang/String;)V
    flags: (0x0001) ACC_PUBLIC
    Code:
      stack=4, locals=3, args_size=3
         0: aload_0
         1: aload_1
         2: aload_2
         3: aconst_null
         4: invokespecial #33                 // Method "<init>":(Ljava/lang/String;Ljava/lang/String;Lcoursier/util/shaded/org/jsoup/nodes/Attributes;)V
         7: return
      LineNumberTable:
        line 33: 0
        line 34: 7
      LocalVariableTable:
        Start  Length  Slot  Name   Signature
            0       8     0  this   Lcoursier/util/shaded/org/jsoup/nodes/Attribute;
            0       8     1   key   Ljava/lang/String;
            0       8     2 value   Ljava/lang/String;

  public coursier.util.shaded.org.jsoup.nodes.Attribute(java.lang.String, java.lang.String, coursier.util.shaded.org.jsoup.nodes.Attributes);
    descriptor: (Ljava/lang/String;Ljava/lang/String;Lcoursier/util/shaded/org/jsoup/nodes/Attributes;)V
    flags: (0x0001) ACC_PUBLIC
    Code:
      stack=2, locals=4, args_size=4
         0: aload_0
         1: invokespecial #39                 // Method java/lang/Object."<init>":()V
         4: aload_1
         5: invokestatic  #45                 // Method coursier/util/shaded/org/jsoup/helper/Validate.notNull:(Ljava/lang/Object;)V
         8: aload_1
         9: invokevirtual #51                 // Method java/lang/String.trim:()Ljava/lang/String;
        12: astore_1
        13: aload_1
        14: invokestatic  #55                 // Method coursier/util/shaded/org/jsoup/helper/Validate.notEmpty:(Ljava/lang/String;)V
        17: aload_0
        18: aload_1
        19: putfield      #57                 // Field key:Ljava/lang/String;
        22: aload_0
        23: aload_2
        24: putfield      #59                 // Field val:Ljava/lang/String;
        27: aload_0
        28: aload_3
        29: putfield      #61                 // Field parent:Lcoursier/util/shaded/org/jsoup/nodes/Attributes;
        32: return
      LineNumberTable:
        line 42: 0
        line 43: 4
        line 44: 8
        line 45: 13
        line 46: 17
        line 47: 22
        line 48: 27
        line 49: 32
      LocalVariableTable:
        Start  Length  Slot  Name   Signature
            0      33     0  this   Lcoursier/util/shaded/org/jsoup/nodes/Attribute;
            0      33     1   key   Ljava/lang/String;
            0      33     2   val   Ljava/lang/String;
            0      33     3 parent   Lcoursier/util/shaded/org/jsoup/nodes/Attributes;

  public java.lang.String getKey();
    descriptor: ()Ljava/lang/String;
    flags: (0x0001) ACC_PUBLIC
    Code:
      stack=1, locals=1, args_size=1
         0: aload_0
         1: getfield      #57                 // Field key:Ljava/lang/String;
         4: areturn
      LineNumberTable:
        line 56: 0
      LocalVariableTable:
        Start  Length  Slot  Name   Signature
            0       5     0  this   Lcoursier/util/shaded/org/jsoup/nodes/Attribute;

  public void setKey(java.lang.String);
    descriptor: (Ljava/lang/String;)V
    flags: (0x0001) ACC_PUBLIC
    Code:
      stack=3, locals=3, args_size=2
         0: aload_1
         1: invokestatic  #45                 // Method coursier/util/shaded/org/jsoup/helper/Validate.notNull:(Ljava/lang/Object;)V
         4: aload_1
         5: invokevirtual #51                 // Method java/lang/String.trim:()Ljava/lang/String;
         8: astore_1
         9: aload_1
        10: invokestatic  #55                 // Method coursier/util/shaded/org/jsoup/helper/Validate.notEmpty:(Ljava/lang/String;)V
        13: aload_0
        14: getfield      #61                 // Field parent:Lcoursier/util/shaded/org/jsoup/nodes/Attributes;
        17: ifnull        47
        20: aload_0
        21: getfield      #61                 // Field parent:Lcoursier/util/shaded/org/jsoup/nodes/Attributes;
        24: aload_0
        25: getfield      #57                 // Field key:Ljava/lang/String;
        28: invokevirtual #69                 // Method coursier/util/shaded/org/jsoup/nodes/Attributes.indexOfKey:(Ljava/lang/String;)I
        31: istore_2
        32: iload_2
        33: iconst_m1
        34: if_icmpeq     47
        37: aload_0
        38: getfield      #61                 // Field parent:Lcoursier/util/shaded/org/jsoup/nodes/Attributes;
        41: getfield      #72                 // Field coursier/util/shaded/org/jsoup/nodes/Attributes.keys:[Ljava/lang/String;
        44: iload_2
        45: aload_1
        46: aastore
        47: aload_0
        48: aload_1
        49: putfield      #57                 // Field key:Ljava/lang/String;
        52: return
      StackMapTable: number_of_entries = 1
        frame_type = 47 /* same */
      LineNumberTable:
        line 64: 0
        line 65: 4
        line 66: 9
        line 67: 13
        line 68: 20
        line 69: 32
        line 70: 37
        line 72: 47
        line 73: 52
      LocalVariableTable:
        Start  Length  Slot  Name   Signature
           32      15     2     i   I
            0      53     0  this   Lcoursier/util/shaded/org/jsoup/nodes/Attribute;
            0      53     1   key   Ljava/lang/String;

  public java.lang.String getValue();
    descriptor: ()Ljava/lang/String;
    flags: (0x0001) ACC_PUBLIC
    Code:
      stack=1, locals=1, args_size=1
         0: aload_0
         1: getfield      #59                 // Field val:Ljava/lang/String;
         4: invokestatic  #79                 // Method coursier/util/shaded/org/jsoup/nodes/Attributes.checkNotNull:(Ljava/lang/String;)Ljava/lang/String;
         7: areturn
      LineNumberTable:
        line 80: 0
      LocalVariableTable:
        Start  Length  Slot  Name   Signature
            0       8     0  this   Lcoursier/util/shaded/org/jsoup/nodes/Attribute;

  public boolean hasDeclaredValue();
    descriptor: ()Z
    flags: (0x0001) ACC_PUBLIC
    Code:
      stack=1, locals=1, args_size=1
         0: aload_0
         1: getfield      #59                 // Field val:Ljava/lang/String;
         4: ifnull        11
         7: iconst_1
         8: goto          12
        11: iconst_0
        12: ireturn
      StackMapTable: number_of_entries = 2
        frame_type = 11 /* same */
        frame_type = 64 /* same_locals_1_stack_item */
          stack = [ int ]
      LineNumberTable:
        line 88: 0
      LocalVariableTable:
        Start  Length  Slot  Name   Signature
            0      13     0  this   Lcoursier/util/shaded/org/jsoup/nodes/Attribute;

  public java.lang.String setValue(java.lang.String);
    descriptor: (Ljava/lang/String;)Ljava/lang/String;
    flags: (0x0001) ACC_PUBLIC
    Code:
      stack=3, locals=4, args_size=2
         0: aload_0
         1: getfield      #59                 // Field val:Ljava/lang/String;
         4: astore_2
         5: aload_0
         6: getfield      #61                 // Field parent:Lcoursier/util/shaded/org/jsoup/nodes/Attributes;
         9: ifnull        51
        12: aload_0
        13: getfield      #61                 // Field parent:Lcoursier/util/shaded/org/jsoup/nodes/Attributes;
        16: aload_0
        17: getfield      #57                 // Field key:Ljava/lang/String;
        20: invokevirtual #85                 // Method coursier/util/shaded/org/jsoup/nodes/Attributes.get:(Ljava/lang/String;)Ljava/lang/String;
        23: astore_2
        24: aload_0
        25: getfield      #61                 // Field parent:Lcoursier/util/shaded/org/jsoup/nodes/Attributes;
        28: aload_0
        29: getfield      #57                 // Field key:Ljava/lang/String;
        32: invokevirtual #69                 // Method coursier/util/shaded/org/jsoup/nodes/Attributes.indexOfKey:(Ljava/lang/String;)I
        35: istore_3
        36: iload_3
        37: iconst_m1
        38: if_icmpeq     51
        41: aload_0
        42: getfield      #61                 // Field parent:Lcoursier/util/shaded/org/jsoup/nodes/Attributes;
        45: getfield      #88                 // Field coursier/util/shaded/org/jsoup/nodes/Attributes.vals:[Ljava/lang/String;
        48: iload_3
        49: aload_1
        50: aastore
        51: aload_0
        52: aload_1
        53: putfield      #59                 // Field val:Ljava/lang/String;
        56: aload_2
        57: invokestatic  #79                 // Method coursier/util/shaded/org/jsoup/nodes/Attributes.checkNotNull:(Ljava/lang/String;)Ljava/lang/String;
        60: areturn
      StackMapTable: number_of_entries = 1
        frame_type = 252 /* append */
          offset_delta = 51
          locals = [ class java/lang/String ]
      LineNumberTable:
        line 96: 0
        line 97: 5
        line 98: 12
        line 99: 24
        line 100: 36
        line 101: 41
        line 103: 51
        line 104: 56
      LocalVariableTable:
        Start  Length  Slot  Name   Signature
           36      15     3     i   I
            0      61     0  this   Lcoursier/util/shaded/org/jsoup/nodes/Attribute;
            0      61     1   val   Ljava/lang/String;
            5      56     2 oldVal   Ljava/lang/String;

  public java.lang.String html();
    descriptor: ()Ljava/lang/String;
    flags: (0x0001) ACC_PUBLIC
    Code:
      stack=5, locals=3, args_size=1
         0: invokestatic  #98                 // Method coursier/util/shaded/org/jsoup/internal/StringUtil.borrowBuilder:()Ljava/lang/StringBuilder;
         3: astore_1
         4: aload_0
         5: aload_1
         6: new           #14                 // class coursier/util/shaded/org/jsoup/nodes/Document
         9: dup
        10: ldc           #100                // String
        12: invokespecial #102                // Method coursier/util/shaded/org/jsoup/nodes/Document."<init>":(Ljava/lang/String;)V
        15: invokevirtual #106                // Method coursier/util/shaded/org/jsoup/nodes/Document.outputSettings:()Lcoursier/util/shaded/org/jsoup/nodes/Document$OutputSettings;
        18: invokevirtual #109                // Method html:(Ljava/lang/Appendable;Lcoursier/util/shaded/org/jsoup/nodes/Document$OutputSettings;)V
        21: goto          34
        24: astore_2
        25: new           #113                // class coursier/util/shaded/org/jsoup/SerializationException
        28: dup
        29: aload_2
        30: invokespecial #116                // Method coursier/util/shaded/org/jsoup/SerializationException."<init>":(Ljava/lang/Throwable;)V
        33: athrow
        34: aload_1
        35: invokestatic  #120                // Method coursier/util/shaded/org/jsoup/internal/StringUtil.releaseBuilder:(Ljava/lang/StringBuilder;)Ljava/lang/String;
        38: areturn
      Exception table:
         from    to  target type
             4    21    24   Class java/io/IOException
      StackMapTable: number_of_entries = 2
        frame_type = 255 /* full_frame */
          offset_delta = 24
          locals = [ class coursier/util/shaded/org/jsoup/nodes/Attribute, class java/lang/StringBuilder ]
          stack = [ class java/io/IOException ]
        frame_type = 9 /* same */
      LineNumberTable:
        line 112: 0
        line 115: 4
        line 118: 21
        line 116: 24
        line 117: 25
        line 119: 34
      LocalVariableTable:
        Start  Length  Slot  Name   Signature
           25       9     2 exception   Ljava/io/IOException;
            0      39     0  this   Lcoursier/util/shaded/org/jsoup/nodes/Attribute;
            4      35     1    sb   Ljava/lang/StringBuilder;

  protected static void html(java.lang.String, java.lang.String, java.lang.Appendable, coursier.util.shaded.org.jsoup.nodes.Document$OutputSettings) throws java.io.IOException;
    descriptor: (Ljava/lang/String;Ljava/lang/String;Ljava/lang/Appendable;Lcoursier/util/shaded/org/jsoup/nodes/Document$OutputSettings;)V
    flags: (0x000c) ACC_PROTECTED, ACC_STATIC
    Code:
      stack=6, locals=4, args_size=4
         0: aload_2
         1: aload_0
         2: invokeinterface #131,  2          // InterfaceMethod java/lang/Appendable.append:(Ljava/lang/CharSequence;)Ljava/lang/Appendable;
         7: pop
         8: aload_0
         9: aload_1
        10: aload_3
        11: invokestatic  #135                // Method shouldCollapseAttribute:(Ljava/lang/String;Ljava/lang/String;Lcoursier/util/shaded/org/jsoup/nodes/Document$OutputSettings;)Z
        14: ifne          47
        17: aload_2
        18: ldc           #137                // String =\"
        20: invokeinterface #131,  2          // InterfaceMethod java/lang/Appendable.append:(Ljava/lang/CharSequence;)Ljava/lang/Appendable;
        25: pop
        26: aload_2
        27: aload_1
        28: invokestatic  #79                 // Method coursier/util/shaded/org/jsoup/nodes/Attributes.checkNotNull:(Ljava/lang/String;)Ljava/lang/String;
        31: aload_3
        32: iconst_1
        33: iconst_0
        34: iconst_0
        35: invokestatic  #143                // Method coursier/util/shaded/org/jsoup/nodes/Entities.escape:(Ljava/lang/Appendable;Ljava/lang/String;Lcoursier/util/shaded/org/jsoup/nodes/Document$OutputSettings;ZZZ)V
        38: aload_2
        39: bipush        34
        41: invokeinterface #146,  2          // InterfaceMethod java/lang/Appendable.append:(C)Ljava/lang/Appendable;
        46: pop
        47: return
      StackMapTable: number_of_entries = 1
        frame_type = 47 /* same */
      LineNumberTable:
        line 123: 0
        line 124: 8
        line 125: 17
        line 126: 26
        line 127: 38
        line 129: 47
      LocalVariableTable:
        Start  Length  Slot  Name   Signature
            0      48     0   key   Ljava/lang/String;
            0      48     1   val   Ljava/lang/String;
            0      48     2 accum   Ljava/lang/Appendable;
            0      48     3   out   Lcoursier/util/shaded/org/jsoup/nodes/Document$OutputSettings;
    Exceptions:
      throws java.io.IOException

  protected void html(java.lang.Appendable, coursier.util.shaded.org.jsoup.nodes.Document$OutputSettings) throws java.io.IOException;
    descriptor: (Ljava/lang/Appendable;Lcoursier/util/shaded/org/jsoup/nodes/Document$OutputSettings;)V
    flags: (0x0004) ACC_PROTECTED
    Code:
      stack=4, locals=3, args_size=3
         0: aload_0
         1: getfield      #57                 // Field key:Ljava/lang/String;
         4: aload_0
         5: getfield      #59                 // Field val:Ljava/lang/String;
         8: aload_1
         9: aload_2
        10: invokestatic  #152                // Method html:(Ljava/lang/String;Ljava/lang/String;Ljava/lang/Appendable;Lcoursier/util/shaded/org/jsoup/nodes/Document$OutputSettings;)V
        13: return
      LineNumberTable:
        line 132: 0
        line 133: 13
      LocalVariableTable:
        Start  Length  Slot  Name   Signature
            0      14     0  this   Lcoursier/util/shaded/org/jsoup/nodes/Attribute;
            0      14     1 accum   Ljava/lang/Appendable;
            0      14     2   out   Lcoursier/util/shaded/org/jsoup/nodes/Document$OutputSettings;
    Exceptions:
      throws java.io.IOException

  public java.lang.String toString();
    descriptor: ()Ljava/lang/String;
    flags: (0x0001) ACC_PUBLIC
    Code:
      stack=1, locals=1, args_size=1
         0: aload_0
         1: invokevirtual #155                // Method html:()Ljava/lang/String;
         4: areturn
      LineNumberTable:
        line 141: 0
      LocalVariableTable:
        Start  Length  Slot  Name   Signature
            0       5     0  this   Lcoursier/util/shaded/org/jsoup/nodes/Attribute;

  public static coursier.util.shaded.org.jsoup.nodes.Attribute createFromEncoded(java.lang.String, java.lang.String);
    descriptor: (Ljava/lang/String;Ljava/lang/String;)Lcoursier/util/shaded/org/jsoup/nodes/Attribute;
    flags: (0x0009) ACC_PUBLIC, ACC_STATIC
    Code:
      stack=5, locals=3, args_size=2
         0: aload_1
         1: iconst_1
         2: invokestatic  #161                // Method coursier/util/shaded/org/jsoup/nodes/Entities.unescape:(Ljava/lang/String;Z)Ljava/lang/String;
         5: astore_2
         6: new           #2                  // class coursier/util/shaded/org/jsoup/nodes/Attribute
         9: dup
        10: aload_0
        11: aload_2
        12: aconst_null
        13: invokespecial #33                 // Method "<init>":(Ljava/lang/String;Ljava/lang/String;Lcoursier/util/shaded/org/jsoup/nodes/Attributes;)V
        16: areturn
      LineNumberTable:
        line 151: 0
        line 152: 6
      LocalVariableTable:
        Start  Length  Slot  Name   Signature
            0      17     0 unencodedKey   Ljava/lang/String;
            0      17     1 encodedValue   Ljava/lang/String;
            6      11     2 value   Ljava/lang/String;

  protected boolean isDataAttribute();
    descriptor: ()Z
    flags: (0x0004) ACC_PROTECTED
    Code:
      stack=1, locals=1, args_size=1
         0: aload_0
         1: getfield      #57                 // Field key:Ljava/lang/String;
         4: invokestatic  #167                // Method isDataAttribute:(Ljava/lang/String;)Z
         7: ireturn
      LineNumberTable:
        line 156: 0
      LocalVariableTable:
        Start  Length  Slot  Name   Signature
            0       8     0  this   Lcoursier/util/shaded/org/jsoup/nodes/Attribute;

  protected static boolean isDataAttribute(java.lang.String);
    descriptor: (Ljava/lang/String;)Z
    flags: (0x000c) ACC_PROTECTED, ACC_STATIC
    Code:
      stack=2, locals=1, args_size=1
         0: aload_0
         1: ldc           #169                // String data-
         3: invokevirtual #172                // Method java/lang/String.startsWith:(Ljava/lang/String;)Z
         6: ifeq          25
         9: aload_0
        10: invokevirtual #176                // Method java/lang/String.length:()I
        13: ldc           #169                // String data-
        15: invokevirtual #176                // Method java/lang/String.length:()I
        18: if_icmple     25
        21: iconst_1
        22: goto          26
        25: iconst_0
        26: ireturn
      StackMapTable: number_of_entries = 2
        frame_type = 25 /* same */
        frame_type = 64 /* same_locals_1_stack_item */
          stack = [ int ]
      LineNumberTable:
        line 160: 0
      LocalVariableTable:
        Start  Length  Slot  Name   Signature
            0      27     0   key   Ljava/lang/String;

  protected final boolean shouldCollapseAttribute(coursier.util.shaded.org.jsoup.nodes.Document$OutputSettings);
    descriptor: (Lcoursier/util/shaded/org/jsoup/nodes/Document$OutputSettings;)Z
    flags: (0x0014) ACC_PROTECTED, ACC_FINAL
    Code:
      stack=3, locals=2, args_size=2
         0: aload_0
         1: getfield      #57                 // Field key:Ljava/lang/String;
         4: aload_0
         5: getfield      #59                 // Field val:Ljava/lang/String;
         8: aload_1
         9: invokestatic  #135                // Method shouldCollapseAttribute:(Ljava/lang/String;Ljava/lang/String;Lcoursier/util/shaded/org/jsoup/nodes/Document$OutputSettings;)Z
        12: ireturn
      LineNumberTable:
        line 170: 0
      LocalVariableTable:
        Start  Length  Slot  Name   Signature
            0      13     0  this   Lcoursier/util/shaded/org/jsoup/nodes/Attribute;
            0      13     1   out   Lcoursier/util/shaded/org/jsoup/nodes/Document$OutputSettings;

  protected static boolean shouldCollapseAttribute(java.lang.String, java.lang.String, coursier.util.shaded.org.jsoup.nodes.Document$OutputSettings);
    descriptor: (Ljava/lang/String;Ljava/lang/String;Lcoursier/util/shaded/org/jsoup/nodes/Document$OutputSettings;)Z
    flags: (0x000c) ACC_PROTECTED, ACC_STATIC
    Code:
      stack=2, locals=3, args_size=3
         0: aload_2
         1: invokevirtual #181                // Method coursier/util/shaded/org/jsoup/nodes/Document$OutputSettings.syntax:()Lcoursier/util/shaded/org/jsoup/nodes/Document$OutputSettings$Syntax;
         4: getstatic     #184                // Field coursier/util/shaded/org/jsoup/nodes/Document$OutputSettings$Syntax.html:Lcoursier/util/shaded/org/jsoup/nodes/Document$OutputSettings$Syntax;
         7: if_acmpne     42
        10: aload_1
        11: ifnull        38
        14: ldc           #100                // String
        16: aload_1
        17: invokevirtual #188                // Method java/lang/String.equals:(Ljava/lang/Object;)Z
        20: ifne          31
        23: aload_1
        24: aload_0
        25: invokevirtual #191                // Method java/lang/String.equalsIgnoreCase:(Ljava/lang/String;)Z
        28: ifeq          42
        31: aload_0
        32: invokestatic  #194                // Method isBooleanAttribute:(Ljava/lang/String;)Z
        35: ifeq          42
        38: iconst_1
        39: goto          43
        42: iconst_0
        43: ireturn
      StackMapTable: number_of_entries = 4
        frame_type = 31 /* same */
        frame_type = 6 /* same */
        frame_type = 3 /* same */
        frame_type = 64 /* same_locals_1_stack_item */
          stack = [ int ]
      LineNumberTable:
        line 174: 0
        line 175: 1
        line 176: 17
        line 174: 43
      LocalVariableTable:
        Start  Length  Slot  Name   Signature
            0      44     0   key   Ljava/lang/String;
            0      44     1   val   Ljava/lang/String;
            0      44     2   out   Lcoursier/util/shaded/org/jsoup/nodes/Document$OutputSettings;

  protected static boolean isBooleanAttribute(java.lang.String);
    descriptor: (Ljava/lang/String;)Z
    flags: (0x000c) ACC_PROTECTED, ACC_STATIC
    Code:
      stack=2, locals=1, args_size=1
         0: getstatic     #196                // Field booleanAttributes:[Ljava/lang/String;
         3: aload_0
         4: invokestatic  #202                // Method java/util/Arrays.binarySearch:([Ljava/lang/Object;Ljava/lang/Object;)I
         7: iflt          14
        10: iconst_1
        11: goto          15
        14: iconst_0
        15: ireturn
      StackMapTable: number_of_entries = 2
        frame_type = 14 /* same */
        frame_type = 64 /* same_locals_1_stack_item */
          stack = [ int ]
      LineNumberTable:
        line 183: 0
      LocalVariableTable:
        Start  Length  Slot  Name   Signature
            0      16     0   key   Ljava/lang/String;

  public boolean equals(java.lang.Object);
    descriptor: (Ljava/lang/Object;)Z
    flags: (0x0001) ACC_PUBLIC
    Code:
      stack=2, locals=3, args_size=2
         0: aload_0
         1: aload_1
         2: if_acmpne     7
         5: iconst_1
         6: ireturn
         7: aload_1
         8: ifnull        22
        11: aload_0
        12: invokevirtual #206                // Method java/lang/Object.getClass:()Ljava/lang/Class;
        15: aload_1
        16: invokevirtual #206                // Method java/lang/Object.getClass:()Ljava/lang/Class;
        19: if_acmpeq     24
        22: iconst_0
        23: ireturn
        24: aload_1
        25: checkcast     #2                  // class coursier/util/shaded/org/jsoup/nodes/Attribute
        28: astore_2
        29: aload_0
        30: getfield      #57                 // Field key:Ljava/lang/String;
        33: ifnull        53
        36: aload_0
        37: getfield      #57                 // Field key:Ljava/lang/String;
        40: aload_2
        41: getfield      #57                 // Field key:Ljava/lang/String;
        44: invokevirtual #188                // Method java/lang/String.equals:(Ljava/lang/Object;)Z
        47: ifne          62
        50: goto          60
        53: aload_2
        54: getfield      #57                 // Field key:Ljava/lang/String;
        57: ifnull        62
        60: iconst_0
        61: ireturn
        62: aload_0
        63: getfield      #59                 // Field val:Ljava/lang/String;
        66: ifnull        83
        69: aload_0
        70: getfield      #59                 // Field val:Ljava/lang/String;
        73: aload_2
        74: getfield      #59                 // Field val:Ljava/lang/String;
        77: invokevirtual #188                // Method java/lang/String.equals:(Ljava/lang/Object;)Z
        80: goto          95
        83: aload_2
        84: getfield      #59                 // Field val:Ljava/lang/String;
        87: ifnonnull     94
        90: iconst_1
        91: goto          95
        94: iconst_0
        95: ireturn
      StackMapTable: number_of_entries = 9
        frame_type = 7 /* same */
        frame_type = 14 /* same */
        frame_type = 1 /* same */
        frame_type = 252 /* append */
          offset_delta = 28
          locals = [ class coursier/util/shaded/org/jsoup/nodes/Attribute ]
        frame_type = 6 /* same */
        frame_type = 1 /* same */
        frame_type = 20 /* same */
        frame_type = 10 /* same */
        frame_type = 64 /* same_locals_1_stack_item */
          stack = [ int ]
      LineNumberTable:
        line 188: 0
        line 189: 7
        line 190: 24
        line 191: 29
        line 192: 62
      LocalVariableTable:
        Start  Length  Slot  Name   Signature
            0      96     0  this   Lcoursier/util/shaded/org/jsoup/nodes/Attribute;
            0      96     1     o   Ljava/lang/Object;
           29      67     2 attribute   Lcoursier/util/shaded/org/jsoup/nodes/Attribute;

  public int hashCode();
    descriptor: ()I
    flags: (0x0001) ACC_PUBLIC
    Code:
      stack=2, locals=2, args_size=1
         0: aload_0
         1: getfield      #57                 // Field key:Ljava/lang/String;
         4: ifnull        17
         7: aload_0
         8: getfield      #57                 // Field key:Ljava/lang/String;
        11: invokevirtual #212                // Method java/lang/String.hashCode:()I
        14: goto          18
        17: iconst_0
        18: istore_1
        19: bipush        31
        21: iload_1
        22: imul
        23: aload_0
        24: getfield      #59                 // Field val:Ljava/lang/String;
        27: ifnull        40
        30: aload_0
        31: getfield      #59                 // Field val:Ljava/lang/String;
        34: invokevirtual #212                // Method java/lang/String.hashCode:()I
        37: goto          41
        40: iconst_0
        41: iadd
        42: istore_1
        43: iload_1
        44: ireturn
      StackMapTable: number_of_entries = 4
        frame_type = 17 /* same */
        frame_type = 64 /* same_locals_1_stack_item */
          stack = [ int ]
        frame_type = 255 /* full_frame */
          offset_delta = 21
          locals = [ class coursier/util/shaded/org/jsoup/nodes/Attribute, int ]
          stack = [ int ]
        frame_type = 255 /* full_frame */
          offset_delta = 0
          locals = [ class coursier/util/shaded/org/jsoup/nodes/Attribute, int ]
          stack = [ int, int ]
      LineNumberTable:
        line 197: 0
        line 198: 19
        line 199: 43
      LocalVariableTable:
        Start  Length  Slot  Name   Signature
            0      45     0  this   Lcoursier/util/shaded/org/jsoup/nodes/Attribute;
           19      26     1 result   I

  public coursier.util.shaded.org.jsoup.nodes.Attribute clone();
    descriptor: ()Lcoursier/util/shaded/org/jsoup/nodes/Attribute;
    flags: (0x0001) ACC_PUBLIC
    Code:
      stack=3, locals=2, args_size=1
         0: aload_0
         1: invokespecial #220                // Method java/lang/Object.clone:()Ljava/lang/Object;
         4: checkcast     #2                  // class coursier/util/shaded/org/jsoup/nodes/Attribute
         7: areturn
         8: astore_1
         9: new           #222                // class java/lang/RuntimeException
        12: dup
        13: aload_1
        14: invokespecial #223                // Method java/lang/RuntimeException."<init>":(Ljava/lang/Throwable;)V
        17: athrow
      Exception table:
         from    to  target type
             0     7     8   Class java/lang/CloneNotSupportedException
      StackMapTable: number_of_entries = 1
        frame_type = 72 /* same_locals_1_stack_item */
          stack = [ class java/lang/CloneNotSupportedException ]
      LineNumberTable:
        line 205: 0
        line 206: 8
        line 207: 9
      LocalVariableTable:
        Start  Length  Slot  Name   Signature
            9       9     1     e   Ljava/lang/CloneNotSupportedException;
            0      18     0  this   Lcoursier/util/shaded/org/jsoup/nodes/Attribute;

  public java.lang.Object clone() throws java.lang.CloneNotSupportedException;
    descriptor: ()Ljava/lang/Object;
    flags: (0x1041) ACC_PUBLIC, ACC_BRIDGE, ACC_SYNTHETIC
    Code:
      stack=1, locals=1, args_size=1
         0: aload_0
         1: invokevirtual #227                // Method clone:()Lcoursier/util/shaded/org/jsoup/nodes/Attribute;
         4: areturn
      LineNumberTable:
        line 14: 0
      LocalVariableTable:
        Start  Length  Slot  Name   Signature
            0       5     0  this   Lcoursier/util/shaded/org/jsoup/nodes/Attribute;
    Exceptions:
      throws java.lang.CloneNotSupportedException

  public java.lang.Object setValue(java.lang.Object);
    descriptor: (Ljava/lang/Object;)Ljava/lang/Object;
    flags: (0x1041) ACC_PUBLIC, ACC_BRIDGE, ACC_SYNTHETIC
    Code:
      stack=2, locals=2, args_size=2
         0: aload_0
         1: aload_1
         2: checkcast     #47                 // class java/lang/String
         5: invokevirtual #230                // Method setValue:(Ljava/lang/String;)Ljava/lang/String;
         8: areturn
      LineNumberTable:
        line 14: 0
      LocalVariableTable:
        Start  Length  Slot  Name   Signature
            0       9     0  this   Lcoursier/util/shaded/org/jsoup/nodes/Attribute;

  public java.lang.Object getValue();
    descriptor: ()Ljava/lang/Object;
    flags: (0x1041) ACC_PUBLIC, ACC_BRIDGE, ACC_SYNTHETIC
    Code:
      stack=1, locals=1, args_size=1
         0: aload_0
         1: invokevirtual #232                // Method getValue:()Ljava/lang/String;
         4: areturn
      LineNumberTable:
        line 14: 0
      LocalVariableTable:
        Start  Length  Slot  Name   Signature
            0       5     0  this   Lcoursier/util/shaded/org/jsoup/nodes/Attribute;

  public java.lang.Object getKey();
    descriptor: ()Ljava/lang/Object;
    flags: (0x1041) ACC_PUBLIC, ACC_BRIDGE, ACC_SYNTHETIC
    Code:
      stack=1, locals=1, args_size=1
         0: aload_0
         1: invokevirtual #234                // Method getKey:()Ljava/lang/String;
         4: areturn
      LineNumberTable:
        line 14: 0
      LocalVariableTable:
        Start  Length  Slot  Name   Signature
            0       5     0  this   Lcoursier/util/shaded/org/jsoup/nodes/Attribute;

  static {};
    descriptor: ()V
    flags: (0x0008) ACC_STATIC
    Code:
      stack=4, locals=0, args_size=0
         0: bipush        30
         2: anewarray     #47                 // class java/lang/String
         5: dup
         6: iconst_0
         7: ldc           #237                // String allowfullscreen
         9: aastore
        10: dup
        11: iconst_1
        12: ldc           #239                // String async
        14: aastore
        15: dup
        16: iconst_2
        17: ldc           #241                // String autofocus
        19: aastore
        20: dup
        21: iconst_3
        22: ldc           #243                // String checked
        24: aastore
        25: dup
        26: iconst_4
        27: ldc           #245                // String compact
        29: aastore
        30: dup
        31: iconst_5
        32: ldc           #247                // String declare
        34: aastore
        35: dup
        36: bipush        6
        38: ldc           #249                // String default
        40: aastore
        41: dup
        42: bipush        7
        44: ldc           #251                // String defer
        46: aastore
        47: dup
        48: bipush        8
        50: ldc           #253                // String disabled
        52: aastore
        53: dup
        54: bipush        9
        56: ldc           #255                // String formnovalidate
        58: aastore
        59: dup
        60: bipush        10
        62: ldc_w         #257                // String hidden
        65: aastore
        66: dup
        67: bipush        11
        69: ldc_w         #259                // String inert
        72: aastore
        73: dup
        74: bipush        12
        76: ldc_w         #261                // String ismap
        79: aastore
        80: dup
        81: bipush        13
        83: ldc_w         #263                // String itemscope
        86: aastore
        87: dup
        88: bipush        14
        90: ldc_w         #265                // String multiple
        93: aastore
        94: dup
        95: bipush        15
        97: ldc_w         #267                // String muted
       100: aastore
       101: dup
       102: bipush        16
       104: ldc_w         #269                // String nohref
       107: aastore
       108: dup
       109: bipush        17
       111: ldc_w         #271                // String noresize
       114: aastore
       115: dup
       116: bipush        18
       118: ldc_w         #273                // String noshade
       121: aastore
       122: dup
       123: bipush        19
       125: ldc_w         #275                // String novalidate
       128: aastore
       129: dup
       130: bipush        20
       132: ldc_w         #277                // String nowrap
       135: aastore
       136: dup
       137: bipush        21
       139: ldc_w         #279                // String open
       142: aastore
       143: dup
       144: bipush        22
       146: ldc_w         #281                // String readonly
       149: aastore
       150: dup
       151: bipush        23
       153: ldc_w         #283                // String required
       156: aastore
       157: dup
       158: bipush        24
       160: ldc_w         #285                // String reversed
       163: aastore
       164: dup
       165: bipush        25
       167: ldc_w         #287                // String seamless
       170: aastore
       171: dup
       172: bipush        26
       174: ldc_w         #289                // String selected
       177: aastore
       178: dup
       179: bipush        27
       181: ldc_w         #291                // String sortable
       184: aastore
       185: dup
       186: bipush        28
       188: ldc_w         #293                // String truespeed
       191: aastore
       192: dup
       193: bipush        29
       195: ldc_w         #295                // String typemustmatch
       198: aastore
       199: putstatic     #196                // Field booleanAttributes:[Ljava/lang/String;
       202: return
      LineNumberTable:
        line 15: 0
}
InnerClasses:
  public static #15= #12 of #14;          // OutputSettings=class coursier/util/shaded/org/jsoup/nodes/Document$OutputSettings of class coursier/util/shaded/org/jsoup/nodes/Document
  public static final #18= #17 of #12;    // Syntax=class coursier/util/shaded/org/jsoup/nodes/Document$OutputSettings$Syntax of class coursier/util/shaded/org/jsoup/nodes/Document$OutputSettings
  public static #21= #7 of #20;           // Entry=class java/util/Map$Entry of class java/util/Map
Signature: #3                           // Ljava/lang/Object;Ljava/util/Map$Entry<Ljava/lang/String;Ljava/lang/String;>;Ljava/lang/Cloneable;
SourceFile: "Attribute.java"
