Classfile /Users/mw/Projects/slang-braindump/.jar/jar11/assemble/slang-braindump/assemble/content/coursier/util/shaded/org/jsoup/nodes/Element$NodeList.class
  Last modified May 29, 2022; size 915 bytes
  SHA-256 checksum 92ba398a3d8d9bdd57c9e835a9e20aca55146b4280bf19181cbd3d4e8b88fa14
  Compiled from "Element.java"
final class coursier.util.shaded.org.jsoup.nodes.Element$NodeList extends coursier.util.shaded.org.jsoup.helper.ChangeNotifyingArrayList<coursier.util.shaded.org.jsoup.nodes.Node>
  minor version: 0
  major version: 51
  flags: (0x0030) ACC_FINAL, ACC_SUPER
  this_class: #2                          // coursier/util/shaded/org/jsoup/nodes/Element$NodeList
  super_class: #5                         // coursier/util/shaded/org/jsoup/helper/ChangeNotifyingArrayList
  interfaces: 0, fields: 1, methods: 2, attributes: 3
Constant pool:
   #1 = Utf8               coursier/util/shaded/org/jsoup/nodes/Element$NodeList
   #2 = Class              #1             // coursier/util/shaded/org/jsoup/nodes/Element$NodeList
   #3 = Utf8               Lcoursier/util/shaded/org/jsoup/helper/ChangeNotifyingArrayList<Lcoursier/util/shaded/org/jsoup/nodes/Node;>;
   #4 = Utf8               coursier/util/shaded/org/jsoup/helper/ChangeNotifyingArrayList
   #5 = Class              #4             // coursier/util/shaded/org/jsoup/helper/ChangeNotifyingArrayList
   #6 = Utf8               Element.java
   #7 = Utf8               coursier/util/shaded/org/jsoup/nodes/Element
   #8 = Class              #7             // coursier/util/shaded/org/jsoup/nodes/Element
   #9 = Utf8               NodeList
  #10 = Utf8               owner
  #11 = Utf8               Lcoursier/util/shaded/org/jsoup/nodes/Element;
  #12 = Utf8               <init>
  #13 = Utf8               (Lcoursier/util/shaded/org/jsoup/nodes/Element;I)V
  #14 = Utf8               (I)V
  #15 = NameAndType        #12:#14        // "<init>":(I)V
  #16 = Methodref          #5.#15         // coursier/util/shaded/org/jsoup/helper/ChangeNotifyingArrayList."<init>":(I)V
  #17 = NameAndType        #10:#11        // owner:Lcoursier/util/shaded/org/jsoup/nodes/Element;
  #18 = Fieldref           #2.#17         // coursier/util/shaded/org/jsoup/nodes/Element$NodeList.owner:Lcoursier/util/shaded/org/jsoup/nodes/Element;
  #19 = Utf8               this
  #20 = Utf8               Lcoursier/util/shaded/org/jsoup/nodes/Element$NodeList;
  #21 = Utf8               initialCapacity
  #22 = Utf8               I
  #23 = Utf8               onContentsChanged
  #24 = Utf8               ()V
  #25 = Utf8               nodelistChanged
  #26 = NameAndType        #25:#24        // nodelistChanged:()V
  #27 = Methodref          #8.#26         // coursier/util/shaded/org/jsoup/nodes/Element.nodelistChanged:()V
  #28 = Utf8               Code
  #29 = Utf8               LineNumberTable
  #30 = Utf8               LocalVariableTable
  #31 = Utf8               InnerClasses
  #32 = Utf8               Signature
  #33 = Utf8               SourceFile
{
  private final coursier.util.shaded.org.jsoup.nodes.Element owner;
    descriptor: Lcoursier/util/shaded/org/jsoup/nodes/Element;
    flags: (0x0012) ACC_PRIVATE, ACC_FINAL

  coursier.util.shaded.org.jsoup.nodes.Element$NodeList(coursier.util.shaded.org.jsoup.nodes.Element, int);
    descriptor: (Lcoursier/util/shaded/org/jsoup/nodes/Element;I)V
    flags: (0x0000)
    Code:
      stack=2, locals=3, args_size=3
         0: aload_0
         1: iload_2
         2: invokespecial #16                 // Method coursier/util/shaded/org/jsoup/helper/ChangeNotifyingArrayList."<init>":(I)V
         5: aload_0
         6: aload_1
         7: putfield      #18                 // Field owner:Lcoursier/util/shaded/org/jsoup/nodes/Element;
        10: return
      LineNumberTable:
        line 1603: 0
        line 1604: 5
        line 1605: 10
      LocalVariableTable:
        Start  Length  Slot  Name   Signature
            0      11     0  this   Lcoursier/util/shaded/org/jsoup/nodes/Element$NodeList;
            0      11     1 owner   Lcoursier/util/shaded/org/jsoup/nodes/Element;
            0      11     2 initialCapacity   I

  public void onContentsChanged();
    descriptor: ()V
    flags: (0x0001) ACC_PUBLIC
    Code:
      stack=1, locals=1, args_size=1
         0: aload_0
         1: getfield      #18                 // Field owner:Lcoursier/util/shaded/org/jsoup/nodes/Element;
         4: invokevirtual #27                 // Method coursier/util/shaded/org/jsoup/nodes/Element.nodelistChanged:()V
         7: return
      LineNumberTable:
        line 1608: 0
        line 1609: 7
      LocalVariableTable:
        Start  Length  Slot  Name   Signature
            0       8     0  this   Lcoursier/util/shaded/org/jsoup/nodes/Element$NodeList;
}
InnerClasses:
  private static final #9= #2 of #8;      // NodeList=class coursier/util/shaded/org/jsoup/nodes/Element$NodeList of class coursier/util/shaded/org/jsoup/nodes/Element
Signature: #3                           // Lcoursier/util/shaded/org/jsoup/helper/ChangeNotifyingArrayList<Lcoursier/util/shaded/org/jsoup/nodes/Node;>;
SourceFile: "Element.java"
