Classfile /Users/mw/Projects/slang-braindump/.jar/jar11/assemble/slang-braindump/assemble/content/coursier/util/shaded/org/jsoup/nodes/Entities$CoreCharset.class
  Last modified May 29, 2022; size 1569 bytes
  SHA-256 checksum f8fd77695af259b0198a756dd0306c62be17fdcef06eee78b73934bb6b0d811a
  Compiled from "Entities.java"
final class coursier.util.shaded.org.jsoup.nodes.Entities$CoreCharset extends java.lang.Enum<coursier.util.shaded.org.jsoup.nodes.Entities$CoreCharset>
  minor version: 0
  major version: 51
  flags: (0x4030) ACC_FINAL, ACC_SUPER, ACC_ENUM
  this_class: #2                          // coursier/util/shaded/org/jsoup/nodes/Entities$CoreCharset
  super_class: #5                         // java/lang/Enum
  interfaces: 0, fields: 4, methods: 5, attributes: 3
Constant pool:
   #1 = Utf8               coursier/util/shaded/org/jsoup/nodes/Entities$CoreCharset
   #2 = Class              #1             // coursier/util/shaded/org/jsoup/nodes/Entities$CoreCharset
   #3 = Utf8               Ljava/lang/Enum<Lcoursier/util/shaded/org/jsoup/nodes/Entities$CoreCharset;>;
   #4 = Utf8               java/lang/Enum
   #5 = Class              #4             // java/lang/Enum
   #6 = Utf8               Entities.java
   #7 = Utf8               coursier/util/shaded/org/jsoup/nodes/Entities
   #8 = Class              #7             // coursier/util/shaded/org/jsoup/nodes/Entities
   #9 = Utf8               CoreCharset
  #10 = Utf8               ascii
  #11 = Utf8               Lcoursier/util/shaded/org/jsoup/nodes/Entities$CoreCharset;
  #12 = Utf8               utf
  #13 = Utf8               fallback
  #14 = Utf8               $VALUES
  #15 = Utf8               [Lcoursier/util/shaded/org/jsoup/nodes/Entities$CoreCharset;
  #16 = Utf8               values
  #17 = Utf8               ()[Lcoursier/util/shaded/org/jsoup/nodes/Entities$CoreCharset;
  #18 = NameAndType        #14:#15        // $VALUES:[Lcoursier/util/shaded/org/jsoup/nodes/Entities$CoreCharset;
  #19 = Fieldref           #2.#18         // coursier/util/shaded/org/jsoup/nodes/Entities$CoreCharset.$VALUES:[Lcoursier/util/shaded/org/jsoup/nodes/Entities$CoreCharset;
  #20 = Class              #15            // "[Lcoursier/util/shaded/org/jsoup/nodes/Entities$CoreCharset;"
  #21 = Utf8               clone
  #22 = Utf8               ()Ljava/lang/Object;
  #23 = NameAndType        #21:#22        // clone:()Ljava/lang/Object;
  #24 = Methodref          #20.#23        // "[Lcoursier/util/shaded/org/jsoup/nodes/Entities$CoreCharset;".clone:()Ljava/lang/Object;
  #25 = Utf8               valueOf
  #26 = Utf8               (Ljava/lang/String;)Lcoursier/util/shaded/org/jsoup/nodes/Entities$CoreCharset;
  #27 = Utf8               (Ljava/lang/Class;Ljava/lang/String;)Ljava/lang/Enum;
  #28 = NameAndType        #25:#27        // valueOf:(Ljava/lang/Class;Ljava/lang/String;)Ljava/lang/Enum;
  #29 = Methodref          #5.#28         // java/lang/Enum.valueOf:(Ljava/lang/Class;Ljava/lang/String;)Ljava/lang/Enum;
  #30 = Utf8               name
  #31 = Utf8               Ljava/lang/String;
  #32 = Utf8               <init>
  #33 = Utf8               (Ljava/lang/String;I)V
  #34 = Utf8               ()V
  #35 = NameAndType        #32:#33        // "<init>":(Ljava/lang/String;I)V
  #36 = Methodref          #5.#35         // java/lang/Enum."<init>":(Ljava/lang/String;I)V
  #37 = Utf8               this
  #38 = Utf8               byName
  #39 = Utf8               US-ASCII
  #40 = String             #39            // US-ASCII
  #41 = Utf8               java/lang/String
  #42 = Class              #41            // java/lang/String
  #43 = Utf8               equals
  #44 = Utf8               (Ljava/lang/Object;)Z
  #45 = NameAndType        #43:#44        // equals:(Ljava/lang/Object;)Z
  #46 = Methodref          #42.#45        // java/lang/String.equals:(Ljava/lang/Object;)Z
  #47 = NameAndType        #10:#11        // ascii:Lcoursier/util/shaded/org/jsoup/nodes/Entities$CoreCharset;
  #48 = Fieldref           #2.#47         // coursier/util/shaded/org/jsoup/nodes/Entities$CoreCharset.ascii:Lcoursier/util/shaded/org/jsoup/nodes/Entities$CoreCharset;
  #49 = Utf8               UTF-
  #50 = String             #49            // UTF-
  #51 = Utf8               startsWith
  #52 = Utf8               (Ljava/lang/String;)Z
  #53 = NameAndType        #51:#52        // startsWith:(Ljava/lang/String;)Z
  #54 = Methodref          #42.#53        // java/lang/String.startsWith:(Ljava/lang/String;)Z
  #55 = NameAndType        #12:#11        // utf:Lcoursier/util/shaded/org/jsoup/nodes/Entities$CoreCharset;
  #56 = Fieldref           #2.#55         // coursier/util/shaded/org/jsoup/nodes/Entities$CoreCharset.utf:Lcoursier/util/shaded/org/jsoup/nodes/Entities$CoreCharset;
  #57 = NameAndType        #13:#11        // fallback:Lcoursier/util/shaded/org/jsoup/nodes/Entities$CoreCharset;
  #58 = Fieldref           #2.#57         // coursier/util/shaded/org/jsoup/nodes/Entities$CoreCharset.fallback:Lcoursier/util/shaded/org/jsoup/nodes/Entities$CoreCharset;
  #59 = Utf8               <clinit>
  #60 = String             #10            // ascii
  #61 = Methodref          #2.#35         // coursier/util/shaded/org/jsoup/nodes/Entities$CoreCharset."<init>":(Ljava/lang/String;I)V
  #62 = String             #12            // utf
  #63 = String             #13            // fallback
  #64 = Utf8               Code
  #65 = Utf8               LineNumberTable
  #66 = Utf8               LocalVariableTable
  #67 = Utf8               Signature
  #68 = Utf8               StackMapTable
  #69 = Utf8               InnerClasses
  #70 = Utf8               SourceFile
{
  public static final coursier.util.shaded.org.jsoup.nodes.Entities$CoreCharset ascii;
    descriptor: Lcoursier/util/shaded/org/jsoup/nodes/Entities$CoreCharset;
    flags: (0x4019) ACC_PUBLIC, ACC_STATIC, ACC_FINAL, ACC_ENUM

  public static final coursier.util.shaded.org.jsoup.nodes.Entities$CoreCharset utf;
    descriptor: Lcoursier/util/shaded/org/jsoup/nodes/Entities$CoreCharset;
    flags: (0x4019) ACC_PUBLIC, ACC_STATIC, ACC_FINAL, ACC_ENUM

  public static final coursier.util.shaded.org.jsoup.nodes.Entities$CoreCharset fallback;
    descriptor: Lcoursier/util/shaded/org/jsoup/nodes/Entities$CoreCharset;
    flags: (0x4019) ACC_PUBLIC, ACC_STATIC, ACC_FINAL, ACC_ENUM

  private static final coursier.util.shaded.org.jsoup.nodes.Entities$CoreCharset[] $VALUES;
    descriptor: [Lcoursier/util/shaded/org/jsoup/nodes/Entities$CoreCharset;
    flags: (0x101a) ACC_PRIVATE, ACC_STATIC, ACC_FINAL, ACC_SYNTHETIC

  public static coursier.util.shaded.org.jsoup.nodes.Entities$CoreCharset[] values();
    descriptor: ()[Lcoursier/util/shaded/org/jsoup/nodes/Entities$CoreCharset;
    flags: (0x0009) ACC_PUBLIC, ACC_STATIC
    Code:
      stack=1, locals=0, args_size=0
         0: getstatic     #19                 // Field $VALUES:[Lcoursier/util/shaded/org/jsoup/nodes/Entities$CoreCharset;
         3: invokevirtual #24                 // Method "[Lcoursier/util/shaded/org/jsoup/nodes/Entities$CoreCharset;".clone:()Ljava/lang/Object;
         6: checkcast     #20                 // class "[Lcoursier/util/shaded/org/jsoup/nodes/Entities$CoreCharset;"
         9: areturn
      LineNumberTable:
        line 291: 0

  public static coursier.util.shaded.org.jsoup.nodes.Entities$CoreCharset valueOf(java.lang.String);
    descriptor: (Ljava/lang/String;)Lcoursier/util/shaded/org/jsoup/nodes/Entities$CoreCharset;
    flags: (0x0009) ACC_PUBLIC, ACC_STATIC
    Code:
      stack=2, locals=1, args_size=1
         0: ldc           #2                  // class coursier/util/shaded/org/jsoup/nodes/Entities$CoreCharset
         2: aload_0
         3: invokestatic  #29                 // Method java/lang/Enum.valueOf:(Ljava/lang/Class;Ljava/lang/String;)Ljava/lang/Enum;
         6: checkcast     #2                  // class coursier/util/shaded/org/jsoup/nodes/Entities$CoreCharset
         9: areturn
      LineNumberTable:
        line 291: 0
      LocalVariableTable:
        Start  Length  Slot  Name   Signature
            0      10     0  name   Ljava/lang/String;

  private coursier.util.shaded.org.jsoup.nodes.Entities$CoreCharset();
    descriptor: (Ljava/lang/String;I)V
    flags: (0x0002) ACC_PRIVATE
    Code:
      stack=3, locals=3, args_size=3
         0: aload_0
         1: aload_1
         2: iload_2
         3: invokespecial #36                 // Method java/lang/Enum."<init>":(Ljava/lang/String;I)V
         6: return
      LineNumberTable:
        line 291: 0
      LocalVariableTable:
        Start  Length  Slot  Name   Signature
            0       7     0  this   Lcoursier/util/shaded/org/jsoup/nodes/Entities$CoreCharset;
    Signature: #34                          // ()V

  static coursier.util.shaded.org.jsoup.nodes.Entities$CoreCharset byName(java.lang.String);
    descriptor: (Ljava/lang/String;)Lcoursier/util/shaded/org/jsoup/nodes/Entities$CoreCharset;
    flags: (0x0008) ACC_STATIC
    Code:
      stack=2, locals=1, args_size=1
         0: aload_0
         1: ldc           #40                 // String US-ASCII
         3: invokevirtual #46                 // Method java/lang/String.equals:(Ljava/lang/Object;)Z
         6: ifeq          13
         9: getstatic     #48                 // Field ascii:Lcoursier/util/shaded/org/jsoup/nodes/Entities$CoreCharset;
        12: areturn
        13: aload_0
        14: ldc           #50                 // String UTF-
        16: invokevirtual #54                 // Method java/lang/String.startsWith:(Ljava/lang/String;)Z
        19: ifeq          26
        22: getstatic     #56                 // Field utf:Lcoursier/util/shaded/org/jsoup/nodes/Entities$CoreCharset;
        25: areturn
        26: getstatic     #58                 // Field fallback:Lcoursier/util/shaded/org/jsoup/nodes/Entities$CoreCharset;
        29: areturn
      StackMapTable: number_of_entries = 2
        frame_type = 13 /* same */
        frame_type = 12 /* same */
      LineNumberTable:
        line 295: 0
        line 296: 9
        line 297: 13
        line 298: 22
        line 299: 26
      LocalVariableTable:
        Start  Length  Slot  Name   Signature
            0      30     0  name   Ljava/lang/String;

  static {};
    descriptor: ()V
    flags: (0x0008) ACC_STATIC
    Code:
      stack=4, locals=0, args_size=0
         0: new           #2                  // class coursier/util/shaded/org/jsoup/nodes/Entities$CoreCharset
         3: dup
         4: ldc           #60                 // String ascii
         6: iconst_0
         7: invokespecial #61                 // Method "<init>":(Ljava/lang/String;I)V
        10: putstatic     #48                 // Field ascii:Lcoursier/util/shaded/org/jsoup/nodes/Entities$CoreCharset;
        13: new           #2                  // class coursier/util/shaded/org/jsoup/nodes/Entities$CoreCharset
        16: dup
        17: ldc           #62                 // String utf
        19: iconst_1
        20: invokespecial #61                 // Method "<init>":(Ljava/lang/String;I)V
        23: putstatic     #56                 // Field utf:Lcoursier/util/shaded/org/jsoup/nodes/Entities$CoreCharset;
        26: new           #2                  // class coursier/util/shaded/org/jsoup/nodes/Entities$CoreCharset
        29: dup
        30: ldc           #63                 // String fallback
        32: iconst_2
        33: invokespecial #61                 // Method "<init>":(Ljava/lang/String;I)V
        36: putstatic     #58                 // Field fallback:Lcoursier/util/shaded/org/jsoup/nodes/Entities$CoreCharset;
        39: iconst_3
        40: anewarray     #2                  // class coursier/util/shaded/org/jsoup/nodes/Entities$CoreCharset
        43: dup
        44: iconst_0
        45: getstatic     #48                 // Field ascii:Lcoursier/util/shaded/org/jsoup/nodes/Entities$CoreCharset;
        48: aastore
        49: dup
        50: iconst_1
        51: getstatic     #56                 // Field utf:Lcoursier/util/shaded/org/jsoup/nodes/Entities$CoreCharset;
        54: aastore
        55: dup
        56: iconst_2
        57: getstatic     #58                 // Field fallback:Lcoursier/util/shaded/org/jsoup/nodes/Entities$CoreCharset;
        60: aastore
        61: putstatic     #19                 // Field $VALUES:[Lcoursier/util/shaded/org/jsoup/nodes/Entities$CoreCharset;
        64: return
      LineNumberTable:
        line 292: 0
        line 291: 39
}
InnerClasses:
  static final #9= #2 of #8;              // CoreCharset=class coursier/util/shaded/org/jsoup/nodes/Entities$CoreCharset of class coursier/util/shaded/org/jsoup/nodes/Entities
Signature: #3                           // Ljava/lang/Enum<Lcoursier/util/shaded/org/jsoup/nodes/Entities$CoreCharset;>;
SourceFile: "Entities.java"
