Classfile /Users/mw/Projects/slang-braindump/.jar/jar11/assemble/slang-braindump/assemble/content/coursier/util/shaded/org/jsoup/nodes/Entities.class
  Last modified May 29, 2022; size 8057 bytes
  SHA-256 checksum 2d5054a6d81c3a602b2619717a020893f4dab06af2b685f4ce6f69ceeb751c98
  Compiled from "Entities.java"
public class coursier.util.shaded.org.jsoup.nodes.Entities
  minor version: 0
  major version: 51
  flags: (0x0021) ACC_PUBLIC, ACC_SUPER
  this_class: #2                          // coursier/util/shaded/org/jsoup/nodes/Entities
  super_class: #4                         // java/lang/Object
  interfaces: 0, fields: 6, methods: 15, attributes: 2
Constant pool:
    #1 = Utf8               coursier/util/shaded/org/jsoup/nodes/Entities
    #2 = Class              #1            // coursier/util/shaded/org/jsoup/nodes/Entities
    #3 = Utf8               java/lang/Object
    #4 = Class              #3            // java/lang/Object
    #5 = Utf8               Entities.java
    #6 = Utf8               coursier/util/shaded/org/jsoup/nodes/Entities$EscapeMode
    #7 = Class              #6            // coursier/util/shaded/org/jsoup/nodes/Entities$EscapeMode
    #8 = Utf8               EscapeMode
    #9 = Utf8               coursier/util/shaded/org/jsoup/nodes/Document$OutputSettings
   #10 = Class              #9            // coursier/util/shaded/org/jsoup/nodes/Document$OutputSettings
   #11 = Utf8               coursier/util/shaded/org/jsoup/nodes/Document
   #12 = Class              #11           // coursier/util/shaded/org/jsoup/nodes/Document
   #13 = Utf8               OutputSettings
   #14 = Utf8               coursier/util/shaded/org/jsoup/nodes/Entities$CoreCharset
   #15 = Class              #14           // coursier/util/shaded/org/jsoup/nodes/Entities$CoreCharset
   #16 = Utf8               CoreCharset
   #17 = Utf8               coursier/util/shaded/org/jsoup/nodes/Entities$1
   #18 = Class              #17           // coursier/util/shaded/org/jsoup/nodes/Entities$1
   #19 = Utf8               empty
   #20 = Utf8               I
   #21 = Integer            -1
   #22 = Utf8               emptyName
   #23 = Utf8               Ljava/lang/String;
   #24 = Utf8
   #25 = String             #24           //
   #26 = Utf8               codepointRadix
   #27 = Integer            36
   #28 = Utf8               codeDelims
   #29 = Utf8               [C
   #30 = Utf8               multipoints
   #31 = Utf8               Ljava/util/HashMap;
   #32 = Utf8               Ljava/util/HashMap<Ljava/lang/String;Ljava/lang/String;>;
   #33 = Utf8               DefaultOutput
   #34 = Utf8               Lcoursier/util/shaded/org/jsoup/nodes/Document$OutputSettings;
   #35 = Utf8               <init>
   #36 = Utf8               ()V
   #37 = NameAndType        #35:#36       // "<init>":()V
   #38 = Methodref          #4.#37        // java/lang/Object."<init>":()V
   #39 = Utf8               this
   #40 = Utf8               Lcoursier/util/shaded/org/jsoup/nodes/Entities;
   #41 = Utf8               isNamedEntity
   #42 = Utf8               (Ljava/lang/String;)Z
   #43 = Utf8               extended
   #44 = Utf8               Lcoursier/util/shaded/org/jsoup/nodes/Entities$EscapeMode;
   #45 = NameAndType        #43:#44       // extended:Lcoursier/util/shaded/org/jsoup/nodes/Entities$EscapeMode;
   #46 = Fieldref           #7.#45        // coursier/util/shaded/org/jsoup/nodes/Entities$EscapeMode.extended:Lcoursier/util/shaded/org/jsoup/nodes/Entities$EscapeMode;
   #47 = Utf8               codepointForName
   #48 = Utf8               (Ljava/lang/String;)I
   #49 = NameAndType        #47:#48       // codepointForName:(Ljava/lang/String;)I
   #50 = Methodref          #7.#49        // coursier/util/shaded/org/jsoup/nodes/Entities$EscapeMode.codepointForName:(Ljava/lang/String;)I
   #51 = Utf8               name
   #52 = Utf8               isBaseNamedEntity
   #53 = Utf8               base
   #54 = NameAndType        #53:#44       // base:Lcoursier/util/shaded/org/jsoup/nodes/Entities$EscapeMode;
   #55 = Fieldref           #7.#54        // coursier/util/shaded/org/jsoup/nodes/Entities$EscapeMode.base:Lcoursier/util/shaded/org/jsoup/nodes/Entities$EscapeMode;
   #56 = Utf8               getByName
   #57 = Utf8               (Ljava/lang/String;)Ljava/lang/String;
   #58 = NameAndType        #30:#31       // multipoints:Ljava/util/HashMap;
   #59 = Fieldref           #2.#58        // coursier/util/shaded/org/jsoup/nodes/Entities.multipoints:Ljava/util/HashMap;
   #60 = Utf8               java/util/HashMap
   #61 = Class              #60           // java/util/HashMap
   #62 = Utf8               get
   #63 = Utf8               (Ljava/lang/Object;)Ljava/lang/Object;
   #64 = NameAndType        #62:#63       // get:(Ljava/lang/Object;)Ljava/lang/Object;
   #65 = Methodref          #61.#64       // java/util/HashMap.get:(Ljava/lang/Object;)Ljava/lang/Object;
   #66 = Utf8               java/lang/String
   #67 = Class              #66           // java/lang/String
   #68 = Utf8               ([III)V
   #69 = NameAndType        #35:#68       // "<init>":([III)V
   #70 = Methodref          #67.#69       // java/lang/String."<init>":([III)V
   #71 = Utf8               val
   #72 = Utf8               codepoint
   #73 = Utf8               codepointsForName
   #74 = Utf8               (Ljava/lang/String;[I)I
   #75 = Utf8               codePointAt
   #76 = Utf8               (I)I
   #77 = NameAndType        #75:#76       // codePointAt:(I)I
   #78 = Methodref          #67.#77       // java/lang/String.codePointAt:(I)I
   #79 = Utf8               codepoints
   #80 = Utf8               [I
   #81 = Utf8               escape
   #82 = Utf8               (Ljava/lang/String;Lcoursier/util/shaded/org/jsoup/nodes/Document$OutputSettings;)Ljava/lang/String;
   #83 = Utf8               java/io/IOException
   #84 = Class              #83           // java/io/IOException
   #85 = Utf8               coursier/util/shaded/org/jsoup/internal/StringUtil
   #86 = Class              #85           // coursier/util/shaded/org/jsoup/internal/StringUtil
   #87 = Utf8               borrowBuilder
   #88 = Utf8               ()Ljava/lang/StringBuilder;
   #89 = NameAndType        #87:#88       // borrowBuilder:()Ljava/lang/StringBuilder;
   #90 = Methodref          #86.#89       // coursier/util/shaded/org/jsoup/internal/StringUtil.borrowBuilder:()Ljava/lang/StringBuilder;
   #91 = Utf8               (Ljava/lang/Appendable;Ljava/lang/String;Lcoursier/util/shaded/org/jsoup/nodes/Document$OutputSettings;ZZZ)V
   #92 = NameAndType        #81:#91       // escape:(Ljava/lang/Appendable;Ljava/lang/String;Lcoursier/util/shaded/org/jsoup/nodes/Document$OutputSettings;ZZZ)V
   #93 = Methodref          #2.#92        // coursier/util/shaded/org/jsoup/nodes/Entities.escape:(Ljava/lang/Appendable;Ljava/lang/String;Lcoursier/util/shaded/org/jsoup/nodes/Document$OutputSettings;ZZZ)V
   #94 = Utf8               java/lang/StringBuilder
   #95 = Class              #94           // java/lang/StringBuilder
   #96 = Utf8               coursier/util/shaded/org/jsoup/SerializationException
   #97 = Class              #96           // coursier/util/shaded/org/jsoup/SerializationException
   #98 = Utf8               (Ljava/lang/Throwable;)V
   #99 = NameAndType        #35:#98       // "<init>":(Ljava/lang/Throwable;)V
  #100 = Methodref          #97.#99       // coursier/util/shaded/org/jsoup/SerializationException."<init>":(Ljava/lang/Throwable;)V
  #101 = Utf8               releaseBuilder
  #102 = Utf8               (Ljava/lang/StringBuilder;)Ljava/lang/String;
  #103 = NameAndType        #101:#102     // releaseBuilder:(Ljava/lang/StringBuilder;)Ljava/lang/String;
  #104 = Methodref          #86.#103      // coursier/util/shaded/org/jsoup/internal/StringUtil.releaseBuilder:(Ljava/lang/StringBuilder;)Ljava/lang/String;
  #105 = Utf8               e
  #106 = Utf8               Ljava/io/IOException;
  #107 = Utf8               string
  #108 = Utf8               out
  #109 = Utf8               accum
  #110 = Utf8               Ljava/lang/StringBuilder;
  #111 = NameAndType        #33:#34       // DefaultOutput:Lcoursier/util/shaded/org/jsoup/nodes/Document$OutputSettings;
  #112 = Fieldref           #2.#111       // coursier/util/shaded/org/jsoup/nodes/Entities.DefaultOutput:Lcoursier/util/shaded/org/jsoup/nodes/Document$OutputSettings;
  #113 = NameAndType        #81:#82       // escape:(Ljava/lang/String;Lcoursier/util/shaded/org/jsoup/nodes/Document$OutputSettings;)Ljava/lang/String;
  #114 = Methodref          #2.#113       // coursier/util/shaded/org/jsoup/nodes/Entities.escape:(Ljava/lang/String;Lcoursier/util/shaded/org/jsoup/nodes/Document$OutputSettings;)Ljava/lang/String;
  #115 = Utf8               escapeMode
  #116 = Utf8               ()Lcoursier/util/shaded/org/jsoup/nodes/Entities$EscapeMode;
  #117 = NameAndType        #115:#116     // escapeMode:()Lcoursier/util/shaded/org/jsoup/nodes/Entities$EscapeMode;
  #118 = Methodref          #10.#117      // coursier/util/shaded/org/jsoup/nodes/Document$OutputSettings.escapeMode:()Lcoursier/util/shaded/org/jsoup/nodes/Entities$EscapeMode;
  #119 = Utf8               encoder
  #120 = Utf8               ()Ljava/nio/charset/CharsetEncoder;
  #121 = NameAndType        #119:#120     // encoder:()Ljava/nio/charset/CharsetEncoder;
  #122 = Methodref          #10.#121      // coursier/util/shaded/org/jsoup/nodes/Document$OutputSettings.encoder:()Ljava/nio/charset/CharsetEncoder;
  #123 = Utf8               coreCharset
  #124 = Utf8               Lcoursier/util/shaded/org/jsoup/nodes/Entities$CoreCharset;
  #125 = NameAndType        #123:#124     // coreCharset:Lcoursier/util/shaded/org/jsoup/nodes/Entities$CoreCharset;
  #126 = Fieldref           #10.#125      // coursier/util/shaded/org/jsoup/nodes/Document$OutputSettings.coreCharset:Lcoursier/util/shaded/org/jsoup/nodes/Entities$CoreCharset;
  #127 = Utf8               length
  #128 = Utf8               ()I
  #129 = NameAndType        #127:#128     // length:()I
  #130 = Methodref          #67.#129      // java/lang/String.length:()I
  #131 = Utf8               java/lang/Appendable
  #132 = Class              #131          // java/lang/Appendable
  #133 = Utf8               java/nio/charset/CharsetEncoder
  #134 = Class              #133          // java/nio/charset/CharsetEncoder
  #135 = Utf8               isWhitespace
  #136 = Utf8               (I)Z
  #137 = NameAndType        #135:#136     // isWhitespace:(I)Z
  #138 = Methodref          #86.#137      // coursier/util/shaded/org/jsoup/internal/StringUtil.isWhitespace:(I)Z
  #139 = Utf8               append
  #140 = Utf8               (C)Ljava/lang/Appendable;
  #141 = NameAndType        #139:#140     // append:(C)Ljava/lang/Appendable;
  #142 = InterfaceMethodref #132.#141     // java/lang/Appendable.append:(C)Ljava/lang/Appendable;
  #143 = Integer            65536
  #144 = Utf8               &amp;
  #145 = String             #144          // &amp;
  #146 = Utf8               (Ljava/lang/CharSequence;)Ljava/lang/Appendable;
  #147 = NameAndType        #139:#146     // append:(Ljava/lang/CharSequence;)Ljava/lang/Appendable;
  #148 = InterfaceMethodref #132.#147     // java/lang/Appendable.append:(Ljava/lang/CharSequence;)Ljava/lang/Appendable;
  #149 = Utf8               xhtml
  #150 = NameAndType        #149:#44      // xhtml:Lcoursier/util/shaded/org/jsoup/nodes/Entities$EscapeMode;
  #151 = Fieldref           #7.#150       // coursier/util/shaded/org/jsoup/nodes/Entities$EscapeMode.xhtml:Lcoursier/util/shaded/org/jsoup/nodes/Entities$EscapeMode;
  #152 = Utf8               &nbsp;
  #153 = String             #152          // &nbsp;
  #154 = Utf8               &#xa0;
  #155 = String             #154          // &#xa0;
  #156 = Utf8               &lt;
  #157 = String             #156          // &lt;
  #158 = Utf8               &gt;
  #159 = String             #158          // &gt;
  #160 = Utf8               &quot;
  #161 = String             #160          // &quot;
  #162 = Utf8               canEncode
  #163 = Utf8               (Lcoursier/util/shaded/org/jsoup/nodes/Entities$CoreCharset;CLjava/nio/charset/CharsetEncoder;)Z
  #164 = NameAndType        #162:#163     // canEncode:(Lcoursier/util/shaded/org/jsoup/nodes/Entities$CoreCharset;CLjava/nio/charset/CharsetEncoder;)Z
  #165 = Methodref          #2.#164       // coursier/util/shaded/org/jsoup/nodes/Entities.canEncode:(Lcoursier/util/shaded/org/jsoup/nodes/Entities$CoreCharset;CLjava/nio/charset/CharsetEncoder;)Z
  #166 = Utf8               appendEncoded
  #167 = Utf8               (Ljava/lang/Appendable;Lcoursier/util/shaded/org/jsoup/nodes/Entities$EscapeMode;I)V
  #168 = NameAndType        #166:#167     // appendEncoded:(Ljava/lang/Appendable;Lcoursier/util/shaded/org/jsoup/nodes/Entities$EscapeMode;I)V
  #169 = Methodref          #2.#168       // coursier/util/shaded/org/jsoup/nodes/Entities.appendEncoded:(Ljava/lang/Appendable;Lcoursier/util/shaded/org/jsoup/nodes/Entities$EscapeMode;I)V
  #170 = Utf8               java/lang/Character
  #171 = Class              #170          // java/lang/Character
  #172 = Utf8               toChars
  #173 = Utf8               (I)[C
  #174 = NameAndType        #172:#173     // toChars:(I)[C
  #175 = Methodref          #171.#174     // java/lang/Character.toChars:(I)[C
  #176 = Utf8               ([C)V
  #177 = NameAndType        #35:#176      // "<init>":([C)V
  #178 = Methodref          #67.#177      // java/lang/String."<init>":([C)V
  #179 = Utf8               (Ljava/lang/CharSequence;)Z
  #180 = NameAndType        #162:#179     // canEncode:(Ljava/lang/CharSequence;)Z
  #181 = Methodref          #134.#180     // java/nio/charset/CharsetEncoder.canEncode:(Ljava/lang/CharSequence;)Z
  #182 = Utf8               charCount
  #183 = NameAndType        #182:#76      // charCount:(I)I
  #184 = Methodref          #171.#183     // java/lang/Character.charCount:(I)I
  #185 = Utf8               c
  #186 = Utf8               C
  #187 = Utf8               codePoint
  #188 = Utf8               offset
  #189 = Utf8               Ljava/lang/Appendable;
  #190 = Utf8               inAttribute
  #191 = Utf8               Z
  #192 = Utf8               normaliseWhite
  #193 = Utf8               stripLeadingWhite
  #194 = Utf8               lastWasWhite
  #195 = Utf8               reachedNonWhite
  #196 = Utf8               Ljava/nio/charset/CharsetEncoder;
  #197 = Utf8               nameForCodepoint
  #198 = Utf8               (I)Ljava/lang/String;
  #199 = NameAndType        #197:#198     // nameForCodepoint:(I)Ljava/lang/String;
  #200 = Methodref          #7.#199       // coursier/util/shaded/org/jsoup/nodes/Entities$EscapeMode.nameForCodepoint:(I)Ljava/lang/String;
  #201 = Utf8               equals
  #202 = Utf8               (Ljava/lang/Object;)Z
  #203 = NameAndType        #201:#202     // equals:(Ljava/lang/Object;)Z
  #204 = Methodref          #67.#203      // java/lang/String.equals:(Ljava/lang/Object;)Z
  #205 = Utf8               &#x
  #206 = String             #205          // &#x
  #207 = Utf8               java/lang/Integer
  #208 = Class              #207          // java/lang/Integer
  #209 = Utf8               toHexString
  #210 = NameAndType        #209:#198     // toHexString:(I)Ljava/lang/String;
  #211 = Methodref          #208.#210     // java/lang/Integer.toHexString:(I)Ljava/lang/String;
  #212 = Utf8               unescape
  #213 = Utf8               (Ljava/lang/String;Z)Ljava/lang/String;
  #214 = NameAndType        #212:#213     // unescape:(Ljava/lang/String;Z)Ljava/lang/String;
  #215 = Methodref          #2.#214       // coursier/util/shaded/org/jsoup/nodes/Entities.unescape:(Ljava/lang/String;Z)Ljava/lang/String;
  #216 = Utf8               coursier/util/shaded/org/jsoup/parser/Parser
  #217 = Class              #216          // coursier/util/shaded/org/jsoup/parser/Parser
  #218 = Utf8               unescapeEntities
  #219 = NameAndType        #218:#213     // unescapeEntities:(Ljava/lang/String;Z)Ljava/lang/String;
  #220 = Methodref          #217.#219     // coursier/util/shaded/org/jsoup/parser/Parser.unescapeEntities:(Ljava/lang/String;Z)Ljava/lang/String;
  #221 = Utf8               strict
  #222 = Utf8               $SwitchMap$org$jsoup$nodes$Entities$CoreCharset
  #223 = NameAndType        #222:#80      // $SwitchMap$org$jsoup$nodes$Entities$CoreCharset:[I
  #224 = Fieldref           #18.#223      // coursier/util/shaded/org/jsoup/nodes/Entities$1.$SwitchMap$org$jsoup$nodes$Entities$CoreCharset:[I
  #225 = Utf8               ordinal
  #226 = NameAndType        #225:#128     // ordinal:()I
  #227 = Methodref          #15.#226      // coursier/util/shaded/org/jsoup/nodes/Entities$CoreCharset.ordinal:()I
  #228 = Utf8               (C)Z
  #229 = NameAndType        #162:#228     // canEncode:(C)Z
  #230 = Methodref          #134.#229     // java/nio/charset/CharsetEncoder.canEncode:(C)Z
  #231 = Utf8               charset
  #232 = Utf8               fallback
  #233 = Utf8               load
  #234 = Utf8               (Lcoursier/util/shaded/org/jsoup/nodes/Entities$EscapeMode;Ljava/lang/String;I)V
  #235 = Utf8               access$102
  #236 = Utf8               (Lcoursier/util/shaded/org/jsoup/nodes/Entities$EscapeMode;[Ljava/lang/String;)[Ljava/lang/String;
  #237 = NameAndType        #235:#236     // access$102:(Lcoursier/util/shaded/org/jsoup/nodes/Entities$EscapeMode;[Ljava/lang/String;)[Ljava/lang/String;
  #238 = Methodref          #7.#237       // coursier/util/shaded/org/jsoup/nodes/Entities$EscapeMode.access$102:(Lcoursier/util/shaded/org/jsoup/nodes/Entities$EscapeMode;[Ljava/lang/String;)[Ljava/lang/String;
  #239 = Utf8               access$202
  #240 = Utf8               (Lcoursier/util/shaded/org/jsoup/nodes/Entities$EscapeMode;[I)[I
  #241 = NameAndType        #239:#240     // access$202:(Lcoursier/util/shaded/org/jsoup/nodes/Entities$EscapeMode;[I)[I
  #242 = Methodref          #7.#241       // coursier/util/shaded/org/jsoup/nodes/Entities$EscapeMode.access$202:(Lcoursier/util/shaded/org/jsoup/nodes/Entities$EscapeMode;[I)[I
  #243 = Utf8               access$302
  #244 = NameAndType        #243:#240     // access$302:(Lcoursier/util/shaded/org/jsoup/nodes/Entities$EscapeMode;[I)[I
  #245 = Methodref          #7.#244       // coursier/util/shaded/org/jsoup/nodes/Entities$EscapeMode.access$302:(Lcoursier/util/shaded/org/jsoup/nodes/Entities$EscapeMode;[I)[I
  #246 = Utf8               access$402
  #247 = NameAndType        #246:#236     // access$402:(Lcoursier/util/shaded/org/jsoup/nodes/Entities$EscapeMode;[Ljava/lang/String;)[Ljava/lang/String;
  #248 = Methodref          #7.#247       // coursier/util/shaded/org/jsoup/nodes/Entities$EscapeMode.access$402:(Lcoursier/util/shaded/org/jsoup/nodes/Entities$EscapeMode;[Ljava/lang/String;)[Ljava/lang/String;
  #249 = Utf8               coursier/util/shaded/org/jsoup/parser/CharacterReader
  #250 = Class              #249          // coursier/util/shaded/org/jsoup/parser/CharacterReader
  #251 = Utf8               (Ljava/lang/String;)V
  #252 = NameAndType        #35:#251      // "<init>":(Ljava/lang/String;)V
  #253 = Methodref          #250.#252     // coursier/util/shaded/org/jsoup/parser/CharacterReader."<init>":(Ljava/lang/String;)V
  #254 = Utf8               isEmpty
  #255 = Utf8               ()Z
  #256 = NameAndType        #254:#255     // isEmpty:()Z
  #257 = Methodref          #250.#256     // coursier/util/shaded/org/jsoup/parser/CharacterReader.isEmpty:()Z
  #258 = Utf8               consumeTo
  #259 = Utf8               (C)Ljava/lang/String;
  #260 = NameAndType        #258:#259     // consumeTo:(C)Ljava/lang/String;
  #261 = Methodref          #250.#260     // coursier/util/shaded/org/jsoup/parser/CharacterReader.consumeTo:(C)Ljava/lang/String;
  #262 = Utf8               advance
  #263 = NameAndType        #262:#36      // advance:()V
  #264 = Methodref          #250.#263     // coursier/util/shaded/org/jsoup/parser/CharacterReader.advance:()V
  #265 = NameAndType        #28:#29       // codeDelims:[C
  #266 = Fieldref           #2.#265       // coursier/util/shaded/org/jsoup/nodes/Entities.codeDelims:[C
  #267 = Utf8               consumeToAny
  #268 = Utf8               ([C)Ljava/lang/String;
  #269 = NameAndType        #267:#268     // consumeToAny:([C)Ljava/lang/String;
  #270 = Methodref          #250.#269     // coursier/util/shaded/org/jsoup/parser/CharacterReader.consumeToAny:([C)Ljava/lang/String;
  #271 = Utf8               parseInt
  #272 = Utf8               (Ljava/lang/String;I)I
  #273 = NameAndType        #271:#272     // parseInt:(Ljava/lang/String;I)I
  #274 = Methodref          #208.#273     // java/lang/Integer.parseInt:(Ljava/lang/String;I)I
  #275 = Utf8               current
  #276 = Utf8               ()C
  #277 = NameAndType        #275:#276     // current:()C
  #278 = Methodref          #250.#277     // coursier/util/shaded/org/jsoup/parser/CharacterReader.current:()C
  #279 = Utf8               access$100
  #280 = Utf8               (Lcoursier/util/shaded/org/jsoup/nodes/Entities$EscapeMode;)[Ljava/lang/String;
  #281 = NameAndType        #279:#280     // access$100:(Lcoursier/util/shaded/org/jsoup/nodes/Entities$EscapeMode;)[Ljava/lang/String;
  #282 = Methodref          #7.#281       // coursier/util/shaded/org/jsoup/nodes/Entities$EscapeMode.access$100:(Lcoursier/util/shaded/org/jsoup/nodes/Entities$EscapeMode;)[Ljava/lang/String;
  #283 = Utf8               access$200
  #284 = Utf8               (Lcoursier/util/shaded/org/jsoup/nodes/Entities$EscapeMode;)[I
  #285 = NameAndType        #283:#284     // access$200:(Lcoursier/util/shaded/org/jsoup/nodes/Entities$EscapeMode;)[I
  #286 = Methodref          #7.#285       // coursier/util/shaded/org/jsoup/nodes/Entities$EscapeMode.access$200:(Lcoursier/util/shaded/org/jsoup/nodes/Entities$EscapeMode;)[I
  #287 = Utf8               access$300
  #288 = NameAndType        #287:#284     // access$300:(Lcoursier/util/shaded/org/jsoup/nodes/Entities$EscapeMode;)[I
  #289 = Methodref          #7.#288       // coursier/util/shaded/org/jsoup/nodes/Entities$EscapeMode.access$300:(Lcoursier/util/shaded/org/jsoup/nodes/Entities$EscapeMode;)[I
  #290 = Utf8               access$400
  #291 = NameAndType        #290:#280     // access$400:(Lcoursier/util/shaded/org/jsoup/nodes/Entities$EscapeMode;)[Ljava/lang/String;
  #292 = Methodref          #7.#291       // coursier/util/shaded/org/jsoup/nodes/Entities$EscapeMode.access$400:(Lcoursier/util/shaded/org/jsoup/nodes/Entities$EscapeMode;)[Ljava/lang/String;
  #293 = Utf8               put
  #294 = Utf8               (Ljava/lang/Object;Ljava/lang/Object;)Ljava/lang/Object;
  #295 = NameAndType        #293:#294     // put:(Ljava/lang/Object;Ljava/lang/Object;)Ljava/lang/Object;
  #296 = Methodref          #61.#295      // java/util/HashMap.put:(Ljava/lang/Object;Ljava/lang/Object;)Ljava/lang/Object;
  #297 = Utf8               Unexpected count of entities loaded
  #298 = String             #297          // Unexpected count of entities loaded
  #299 = Utf8               coursier/util/shaded/org/jsoup/helper/Validate
  #300 = Class              #299          // coursier/util/shaded/org/jsoup/helper/Validate
  #301 = Utf8               isTrue
  #302 = Utf8               (ZLjava/lang/String;)V
  #303 = NameAndType        #301:#302     // isTrue:(ZLjava/lang/String;)V
  #304 = Methodref          #300.#303     // coursier/util/shaded/org/jsoup/helper/Validate.isTrue:(ZLjava/lang/String;)V
  #305 = Utf8               cp2
  #306 = Utf8               cp1
  #307 = Utf8               codeDelim
  #308 = Utf8               indexS
  #309 = Utf8               index
  #310 = Utf8               pointsData
  #311 = Utf8               size
  #312 = Utf8               i
  #313 = Utf8               reader
  #314 = Utf8               Lcoursier/util/shaded/org/jsoup/parser/CharacterReader;
  #315 = Utf8               access$000
  #316 = NameAndType        #233:#234     // load:(Lcoursier/util/shaded/org/jsoup/nodes/Entities$EscapeMode;Ljava/lang/String;I)V
  #317 = Methodref          #2.#316       // coursier/util/shaded/org/jsoup/nodes/Entities.load:(Lcoursier/util/shaded/org/jsoup/nodes/Entities$EscapeMode;Ljava/lang/String;I)V
  #318 = Utf8               x0
  #319 = Utf8               x1
  #320 = Utf8               x2
  #321 = Utf8               <clinit>
  #322 = Methodref          #61.#37       // java/util/HashMap."<init>":()V
  #323 = Methodref          #10.#37       // coursier/util/shaded/org/jsoup/nodes/Document$OutputSettings."<init>":()V
  #324 = Utf8               ConstantValue
  #325 = Utf8               Signature
  #326 = Utf8               Code
  #327 = Utf8               LineNumberTable
  #328 = Utf8               LocalVariableTable
  #329 = Utf8               StackMapTable
  #330 = Utf8               Exceptions
  #331 = Utf8               InnerClasses
  #332 = Utf8               SourceFile
{
  private static final int empty;
    descriptor: I
    flags: (0x001a) ACC_PRIVATE, ACC_STATIC, ACC_FINAL
    ConstantValue: int -1

  private static final java.lang.String emptyName;
    descriptor: Ljava/lang/String;
    flags: (0x001a) ACC_PRIVATE, ACC_STATIC, ACC_FINAL
    ConstantValue: String

  static final int codepointRadix;
    descriptor: I
    flags: (0x0018) ACC_STATIC, ACC_FINAL
    ConstantValue: int 36

  private static final char[] codeDelims;
    descriptor: [C
    flags: (0x001a) ACC_PRIVATE, ACC_STATIC, ACC_FINAL

  private static final java.util.HashMap<java.lang.String, java.lang.String> multipoints;
    descriptor: Ljava/util/HashMap;
    flags: (0x001a) ACC_PRIVATE, ACC_STATIC, ACC_FINAL
    Signature: #32                          // Ljava/util/HashMap<Ljava/lang/String;Ljava/lang/String;>;

  private static final coursier.util.shaded.org.jsoup.nodes.Document$OutputSettings DefaultOutput;
    descriptor: Lcoursier/util/shaded/org/jsoup/nodes/Document$OutputSettings;
    flags: (0x001a) ACC_PRIVATE, ACC_STATIC, ACC_FINAL

  private coursier.util.shaded.org.jsoup.nodes.Entities();
    descriptor: ()V
    flags: (0x0002) ACC_PRIVATE
    Code:
      stack=1, locals=1, args_size=1
         0: aload_0
         1: invokespecial #38                 // Method java/lang/Object."<init>":()V
         4: return
      LineNumberTable:
        line 76: 0
        line 77: 4
      LocalVariableTable:
        Start  Length  Slot  Name   Signature
            0       5     0  this   Lcoursier/util/shaded/org/jsoup/nodes/Entities;

  public static boolean isNamedEntity(java.lang.String);
    descriptor: (Ljava/lang/String;)Z
    flags: (0x0009) ACC_PUBLIC, ACC_STATIC
    Code:
      stack=2, locals=1, args_size=1
         0: getstatic     #46                 // Field coursier/util/shaded/org/jsoup/nodes/Entities$EscapeMode.extended:Lcoursier/util/shaded/org/jsoup/nodes/Entities$EscapeMode;
         3: aload_0
         4: invokevirtual #50                 // Method coursier/util/shaded/org/jsoup/nodes/Entities$EscapeMode.codepointForName:(Ljava/lang/String;)I
         7: iconst_m1
         8: if_icmpeq     15
        11: iconst_1
        12: goto          16
        15: iconst_0
        16: ireturn
      StackMapTable: number_of_entries = 2
        frame_type = 15 /* same */
        frame_type = 64 /* same_locals_1_stack_item */
          stack = [ int ]
      LineNumberTable:
        line 86: 0
      LocalVariableTable:
        Start  Length  Slot  Name   Signature
            0      17     0  name   Ljava/lang/String;

  public static boolean isBaseNamedEntity(java.lang.String);
    descriptor: (Ljava/lang/String;)Z
    flags: (0x0009) ACC_PUBLIC, ACC_STATIC
    Code:
      stack=2, locals=1, args_size=1
         0: getstatic     #55                 // Field coursier/util/shaded/org/jsoup/nodes/Entities$EscapeMode.base:Lcoursier/util/shaded/org/jsoup/nodes/Entities$EscapeMode;
         3: aload_0
         4: invokevirtual #50                 // Method coursier/util/shaded/org/jsoup/nodes/Entities$EscapeMode.codepointForName:(Ljava/lang/String;)I
         7: iconst_m1
         8: if_icmpeq     15
        11: iconst_1
        12: goto          16
        15: iconst_0
        16: ireturn
      StackMapTable: number_of_entries = 2
        frame_type = 15 /* same */
        frame_type = 64 /* same_locals_1_stack_item */
          stack = [ int ]
      LineNumberTable:
        line 97: 0
      LocalVariableTable:
        Start  Length  Slot  Name   Signature
            0      17     0  name   Ljava/lang/String;

  public static java.lang.String getByName(java.lang.String);
    descriptor: (Ljava/lang/String;)Ljava/lang/String;
    flags: (0x0009) ACC_PUBLIC, ACC_STATIC
    Code:
      stack=6, locals=3, args_size=1
         0: getstatic     #59                 // Field multipoints:Ljava/util/HashMap;
         3: aload_0
         4: invokevirtual #65                 // Method java/util/HashMap.get:(Ljava/lang/Object;)Ljava/lang/Object;
         7: checkcast     #67                 // class java/lang/String
        10: astore_1
        11: aload_1
        12: ifnull        17
        15: aload_1
        16: areturn
        17: getstatic     #46                 // Field coursier/util/shaded/org/jsoup/nodes/Entities$EscapeMode.extended:Lcoursier/util/shaded/org/jsoup/nodes/Entities$EscapeMode;
        20: aload_0
        21: invokevirtual #50                 // Method coursier/util/shaded/org/jsoup/nodes/Entities$EscapeMode.codepointForName:(Ljava/lang/String;)I
        24: istore_2
        25: iload_2
        26: iconst_m1
        27: if_icmpeq     47
        30: new           #67                 // class java/lang/String
        33: dup
        34: iconst_1
        35: newarray       int
        37: dup
        38: iconst_0
        39: iload_2
        40: iastore
        41: iconst_0
        42: iconst_1
        43: invokespecial #70                 // Method java/lang/String."<init>":([III)V
        46: areturn
        47: ldc           #25                 // String
        49: areturn
      StackMapTable: number_of_entries = 2
        frame_type = 252 /* append */
          offset_delta = 17
          locals = [ class java/lang/String ]
        frame_type = 252 /* append */
          offset_delta = 29
          locals = [ int ]
      LineNumberTable:
        line 107: 0
        line 108: 11
        line 109: 15
        line 110: 17
        line 111: 25
        line 112: 30
        line 113: 47
      LocalVariableTable:
        Start  Length  Slot  Name   Signature
            0      50     0  name   Ljava/lang/String;
           11      39     1   val   Ljava/lang/String;
           25      25     2 codepoint   I

  public static int codepointsForName(java.lang.String, int[]);
    descriptor: (Ljava/lang/String;[I)I
    flags: (0x0009) ACC_PUBLIC, ACC_STATIC
    Code:
      stack=4, locals=4, args_size=2
         0: getstatic     #59                 // Field multipoints:Ljava/util/HashMap;
         3: aload_0
         4: invokevirtual #65                 // Method java/util/HashMap.get:(Ljava/lang/Object;)Ljava/lang/Object;
         7: checkcast     #67                 // class java/lang/String
        10: astore_2
        11: aload_2
        12: ifnull        33
        15: aload_1
        16: iconst_0
        17: aload_2
        18: iconst_0
        19: invokevirtual #78                 // Method java/lang/String.codePointAt:(I)I
        22: iastore
        23: aload_1
        24: iconst_1
        25: aload_2
        26: iconst_1
        27: invokevirtual #78                 // Method java/lang/String.codePointAt:(I)I
        30: iastore
        31: iconst_2
        32: ireturn
        33: getstatic     #46                 // Field coursier/util/shaded/org/jsoup/nodes/Entities$EscapeMode.extended:Lcoursier/util/shaded/org/jsoup/nodes/Entities$EscapeMode;
        36: aload_0
        37: invokevirtual #50                 // Method coursier/util/shaded/org/jsoup/nodes/Entities$EscapeMode.codepointForName:(Ljava/lang/String;)I
        40: istore_3
        41: iload_3
        42: iconst_m1
        43: if_icmpeq     52
        46: aload_1
        47: iconst_0
        48: iload_3
        49: iastore
        50: iconst_1
        51: ireturn
        52: iconst_0
        53: ireturn
      StackMapTable: number_of_entries = 2
        frame_type = 252 /* append */
          offset_delta = 33
          locals = [ class java/lang/String ]
        frame_type = 252 /* append */
          offset_delta = 18
          locals = [ int ]
      LineNumberTable:
        line 117: 0
        line 118: 11
        line 119: 15
        line 120: 23
        line 121: 31
        line 123: 33
        line 124: 41
        line 125: 46
        line 126: 50
        line 128: 52
      LocalVariableTable:
        Start  Length  Slot  Name   Signature
            0      54     0  name   Ljava/lang/String;
            0      54     1 codepoints   [I
           11      43     2   val   Ljava/lang/String;
           41      13     3 codepoint   I

  public static java.lang.String escape(java.lang.String, coursier.util.shaded.org.jsoup.nodes.Document$OutputSettings);
    descriptor: (Ljava/lang/String;Lcoursier/util/shaded/org/jsoup/nodes/Document$OutputSettings;)Ljava/lang/String;
    flags: (0x0009) ACC_PUBLIC, ACC_STATIC
    Code:
      stack=6, locals=4, args_size=2
         0: aload_0
         1: ifnonnull     7
         4: ldc           #25                 // String
         6: areturn
         7: invokestatic  #90                 // Method coursier/util/shaded/org/jsoup/internal/StringUtil.borrowBuilder:()Ljava/lang/StringBuilder;
        10: astore_2
        11: aload_2
        12: aload_0
        13: aload_1
        14: iconst_0
        15: iconst_0
        16: iconst_0
        17: invokestatic  #93                 // Method escape:(Ljava/lang/Appendable;Ljava/lang/String;Lcoursier/util/shaded/org/jsoup/nodes/Document$OutputSettings;ZZZ)V
        20: goto          33
        23: astore_3
        24: new           #97                 // class coursier/util/shaded/org/jsoup/SerializationException
        27: dup
        28: aload_3
        29: invokespecial #100                // Method coursier/util/shaded/org/jsoup/SerializationException."<init>":(Ljava/lang/Throwable;)V
        32: athrow
        33: aload_2
        34: invokestatic  #104                // Method coursier/util/shaded/org/jsoup/internal/StringUtil.releaseBuilder:(Ljava/lang/StringBuilder;)Ljava/lang/String;
        37: areturn
      Exception table:
         from    to  target type
            11    20    23   Class java/io/IOException
      StackMapTable: number_of_entries = 3
        frame_type = 7 /* same */
        frame_type = 255 /* full_frame */
          offset_delta = 15
          locals = [ class java/lang/String, class coursier/util/shaded/org/jsoup/nodes/Document$OutputSettings, class java/lang/StringBuilder ]
          stack = [ class java/io/IOException ]
        frame_type = 9 /* same */
      LineNumberTable:
        line 139: 0
        line 140: 4
        line 141: 7
        line 143: 11
        line 146: 20
        line 144: 23
        line 145: 24
        line 147: 33
      LocalVariableTable:
        Start  Length  Slot  Name   Signature
           24       9     3     e   Ljava/io/IOException;
            0      38     0 string   Ljava/lang/String;
            0      38     1   out   Lcoursier/util/shaded/org/jsoup/nodes/Document$OutputSettings;
           11      27     2 accum   Ljava/lang/StringBuilder;

  public static java.lang.String escape(java.lang.String);
    descriptor: (Ljava/lang/String;)Ljava/lang/String;
    flags: (0x0009) ACC_PUBLIC, ACC_STATIC
    Code:
      stack=2, locals=1, args_size=1
         0: aload_0
         1: getstatic     #112                // Field DefaultOutput:Lcoursier/util/shaded/org/jsoup/nodes/Document$OutputSettings;
         4: invokestatic  #114                // Method escape:(Ljava/lang/String;Lcoursier/util/shaded/org/jsoup/nodes/Document$OutputSettings;)Ljava/lang/String;
         7: areturn
      LineNumberTable:
        line 158: 0
      LocalVariableTable:
        Start  Length  Slot  Name   Signature
            0       8     0 string   Ljava/lang/String;

  static void escape(java.lang.Appendable, java.lang.String, coursier.util.shaded.org.jsoup.nodes.Document$OutputSettings, boolean, boolean, boolean) throws java.io.IOException;
    descriptor: (Ljava/lang/Appendable;Ljava/lang/String;Lcoursier/util/shaded/org/jsoup/nodes/Document$OutputSettings;ZZZ)V
    flags: (0x0008) ACC_STATIC
    Code:
      stack=3, locals=15, args_size=6
         0: iconst_0
         1: istore        6
         3: iconst_0
         4: istore        7
         6: aload_2
         7: invokevirtual #118                // Method coursier/util/shaded/org/jsoup/nodes/Document$OutputSettings.escapeMode:()Lcoursier/util/shaded/org/jsoup/nodes/Entities$EscapeMode;
        10: astore        8
        12: aload_2
        13: invokevirtual #122                // Method coursier/util/shaded/org/jsoup/nodes/Document$OutputSettings.encoder:()Ljava/nio/charset/CharsetEncoder;
        16: astore        9
        18: aload_2
        19: getfield      #126                // Field coursier/util/shaded/org/jsoup/nodes/Document$OutputSettings.coreCharset:Lcoursier/util/shaded/org/jsoup/nodes/Entities$CoreCharset;
        22: astore        10
        24: aload_1
        25: invokevirtual #130                // Method java/lang/String.length:()I
        28: istore        11
        30: iconst_0
        31: istore        13
        33: iload         13
        35: iload         11
        37: if_icmpge     392
        40: aload_1
        41: iload         13
        43: invokevirtual #78                 // Method java/lang/String.codePointAt:(I)I
        46: istore        12
        48: iload         4
        50: ifeq          100
        53: iload         12
        55: invokestatic  #138                // Method coursier/util/shaded/org/jsoup/internal/StringUtil.isWhitespace:(I)Z
        58: ifeq          94
        61: iload         5
        63: ifeq          71
        66: iload         7
        68: ifeq          379
        71: iload         6
        73: ifeq          79
        76: goto          379
        79: aload_0
        80: bipush        32
        82: invokeinterface #142,  2          // InterfaceMethod java/lang/Appendable.append:(C)Ljava/lang/Appendable;
        87: pop
        88: iconst_1
        89: istore        6
        91: goto          379
        94: iconst_0
        95: istore        6
        97: iconst_1
        98: istore        7
       100: iload         12
       102: ldc           #143                // int 65536
       104: if_icmpge     335
       107: iload         12
       109: i2c
       110: istore        14
       112: iload         14
       114: lookupswitch  { // 5
                      34: 272
                      38: 164
                      60: 208
                      62: 244
                     160: 176
                 default: 300
            }
       164: aload_0
       165: ldc           #145                // String &amp;
       167: invokeinterface #148,  2          // InterfaceMethod java/lang/Appendable.append:(Ljava/lang/CharSequence;)Ljava/lang/Appendable;
       172: pop
       173: goto          332
       176: aload         8
       178: getstatic     #151                // Field coursier/util/shaded/org/jsoup/nodes/Entities$EscapeMode.xhtml:Lcoursier/util/shaded/org/jsoup/nodes/Entities$EscapeMode;
       181: if_acmpeq     196
       184: aload_0
       185: ldc           #153                // String &nbsp;
       187: invokeinterface #148,  2          // InterfaceMethod java/lang/Appendable.append:(Ljava/lang/CharSequence;)Ljava/lang/Appendable;
       192: pop
       193: goto          332
       196: aload_0
       197: ldc           #155                // String &#xa0;
       199: invokeinterface #148,  2          // InterfaceMethod java/lang/Appendable.append:(Ljava/lang/CharSequence;)Ljava/lang/Appendable;
       204: pop
       205: goto          332
       208: iload_3
       209: ifeq          220
       212: aload         8
       214: getstatic     #151                // Field coursier/util/shaded/org/jsoup/nodes/Entities$EscapeMode.xhtml:Lcoursier/util/shaded/org/jsoup/nodes/Entities$EscapeMode;
       217: if_acmpne     232
       220: aload_0
       221: ldc           #157                // String &lt;
       223: invokeinterface #148,  2          // InterfaceMethod java/lang/Appendable.append:(Ljava/lang/CharSequence;)Ljava/lang/Appendable;
       228: pop
       229: goto          332
       232: aload_0
       233: iload         14
       235: invokeinterface #142,  2          // InterfaceMethod java/lang/Appendable.append:(C)Ljava/lang/Appendable;
       240: pop
       241: goto          332
       244: iload_3
       245: ifne          260
       248: aload_0
       249: ldc           #159                // String &gt;
       251: invokeinterface #148,  2          // InterfaceMethod java/lang/Appendable.append:(Ljava/lang/CharSequence;)Ljava/lang/Appendable;
       256: pop
       257: goto          332
       260: aload_0
       261: iload         14
       263: invokeinterface #142,  2          // InterfaceMethod java/lang/Appendable.append:(C)Ljava/lang/Appendable;
       268: pop
       269: goto          332
       272: iload_3
       273: ifeq          288
       276: aload_0
       277: ldc           #161                // String &quot;
       279: invokeinterface #148,  2          // InterfaceMethod java/lang/Appendable.append:(Ljava/lang/CharSequence;)Ljava/lang/Appendable;
       284: pop
       285: goto          332
       288: aload_0
       289: iload         14
       291: invokeinterface #142,  2          // InterfaceMethod java/lang/Appendable.append:(C)Ljava/lang/Appendable;
       296: pop
       297: goto          332
       300: aload         10
       302: iload         14
       304: aload         9
       306: invokestatic  #165                // Method canEncode:(Lcoursier/util/shaded/org/jsoup/nodes/Entities$CoreCharset;CLjava/nio/charset/CharsetEncoder;)Z
       309: ifeq          324
       312: aload_0
       313: iload         14
       315: invokeinterface #142,  2          // InterfaceMethod java/lang/Appendable.append:(C)Ljava/lang/Appendable;
       320: pop
       321: goto          332
       324: aload_0
       325: aload         8
       327: iload         12
       329: invokestatic  #169                // Method appendEncoded:(Ljava/lang/Appendable;Lcoursier/util/shaded/org/jsoup/nodes/Entities$EscapeMode;I)V
       332: goto          379
       335: new           #67                 // class java/lang/String
       338: dup
       339: iload         12
       341: invokestatic  #175                // Method java/lang/Character.toChars:(I)[C
       344: invokespecial #178                // Method java/lang/String."<init>":([C)V
       347: astore        14
       349: aload         9
       351: aload         14
       353: invokevirtual #181                // Method java/nio/charset/CharsetEncoder.canEncode:(Ljava/lang/CharSequence;)Z
       356: ifeq          371
       359: aload_0
       360: aload         14
       362: invokeinterface #148,  2          // InterfaceMethod java/lang/Appendable.append:(Ljava/lang/CharSequence;)Ljava/lang/Appendable;
       367: pop
       368: goto          379
       371: aload_0
       372: aload         8
       374: iload         12
       376: invokestatic  #169                // Method appendEncoded:(Ljava/lang/Appendable;Lcoursier/util/shaded/org/jsoup/nodes/Entities$EscapeMode;I)V
       379: iload         13
       381: iload         12
       383: invokestatic  #184                // Method java/lang/Character.charCount:(I)I
       386: iadd
       387: istore        13
       389: goto          33
       392: return
      StackMapTable: number_of_entries = 22
        frame_type = 255 /* full_frame */
          offset_delta = 33
          locals = [ class java/lang/Appendable, class java/lang/String, class coursier/util/shaded/org/jsoup/nodes/Document$OutputSettings, int, int, int, int, int, class coursier/util/shaded/org/jsoup/nodes/Entities$EscapeMode, class java/nio/charset/CharsetEncoder, class coursier/util/shaded/org/jsoup/nodes/Entities$CoreCharset, int, top, int ]
          stack = []
        frame_type = 255 /* full_frame */
          offset_delta = 37
          locals = [ class java/lang/Appendable, class java/lang/String, class coursier/util/shaded/org/jsoup/nodes/Document$OutputSettings, int, int, int, int, int, class coursier/util/shaded/org/jsoup/nodes/Entities$EscapeMode, class java/nio/charset/CharsetEncoder, class coursier/util/shaded/org/jsoup/nodes/Entities$CoreCharset, int, int, int ]
          stack = []
        frame_type = 7 /* same */
        frame_type = 14 /* same */
        frame_type = 5 /* same */
        frame_type = 252 /* append */
          offset_delta = 63
          locals = [ int ]
        frame_type = 11 /* same */
        frame_type = 19 /* same */
        frame_type = 11 /* same */
        frame_type = 11 /* same */
        frame_type = 11 /* same */
        frame_type = 11 /* same */
        frame_type = 15 /* same */
        frame_type = 11 /* same */
        frame_type = 15 /* same */
        frame_type = 11 /* same */
        frame_type = 23 /* same */
        frame_type = 250 /* chop */
          offset_delta = 7
        frame_type = 2 /* same */
        frame_type = 252 /* append */
          offset_delta = 35
          locals = [ class java/lang/String ]
        frame_type = 250 /* chop */
          offset_delta = 7
        frame_type = 249 /* chop */
          offset_delta = 12
      LineNumberTable:
        line 165: 0
        line 166: 3
        line 167: 6
        line 168: 12
        line 169: 18
        line 170: 24
        line 173: 30
        line 174: 40
        line 176: 48
        line 177: 53
        line 178: 61
        line 179: 76
        line 180: 79
        line 181: 88
        line 182: 91
        line 184: 94
        line 185: 97
        line 189: 100
        line 190: 107
        line 192: 112
        line 194: 164
        line 195: 173
        line 197: 176
        line 198: 184
        line 200: 196
        line 201: 205
        line 204: 208
        line 205: 220
        line 207: 232
        line 208: 241
        line 210: 244
        line 211: 248
        line 213: 260
        line 214: 269
        line 216: 272
        line 217: 276
        line 219: 288
        line 220: 297
        line 222: 300
        line 223: 312
        line 225: 324
        line 227: 332
        line 228: 335
        line 229: 349
        line 230: 359
        line 232: 371
        line 173: 379
        line 235: 392
      LocalVariableTable:
        Start  Length  Slot  Name   Signature
          112     220    14     c   C
          349      30    14     c   Ljava/lang/String;
           48     344    12 codePoint   I
           33     359    13 offset   I
            0     393     0 accum   Ljava/lang/Appendable;
            0     393     1 string   Ljava/lang/String;
            0     393     2   out   Lcoursier/util/shaded/org/jsoup/nodes/Document$OutputSettings;
            0     393     3 inAttribute   Z
            0     393     4 normaliseWhite   Z
            0     393     5 stripLeadingWhite   Z
            3     390     6 lastWasWhite   Z
            6     387     7 reachedNonWhite   Z
           12     381     8 escapeMode   Lcoursier/util/shaded/org/jsoup/nodes/Entities$EscapeMode;
           18     375     9 encoder   Ljava/nio/charset/CharsetEncoder;
           24     369    10 coreCharset   Lcoursier/util/shaded/org/jsoup/nodes/Entities$CoreCharset;
           30     363    11 length   I
    Exceptions:
      throws java.io.IOException

  private static void appendEncoded(java.lang.Appendable, coursier.util.shaded.org.jsoup.nodes.Entities$EscapeMode, int) throws java.io.IOException;
    descriptor: (Ljava/lang/Appendable;Lcoursier/util/shaded/org/jsoup/nodes/Entities$EscapeMode;I)V
    flags: (0x000a) ACC_PRIVATE, ACC_STATIC
    Code:
      stack=2, locals=4, args_size=3
         0: aload_1
         1: iload_2
         2: invokevirtual #200                // Method coursier/util/shaded/org/jsoup/nodes/Entities$EscapeMode.nameForCodepoint:(I)Ljava/lang/String;
         5: astore_3
         6: ldc           #25                 // String
         8: aload_3
         9: invokevirtual #204                // Method java/lang/String.equals:(Ljava/lang/Object;)Z
        12: ifne          40
        15: aload_0
        16: bipush        38
        18: invokeinterface #142,  2          // InterfaceMethod java/lang/Appendable.append:(C)Ljava/lang/Appendable;
        23: aload_3
        24: invokeinterface #148,  2          // InterfaceMethod java/lang/Appendable.append:(Ljava/lang/CharSequence;)Ljava/lang/Appendable;
        29: bipush        59
        31: invokeinterface #142,  2          // InterfaceMethod java/lang/Appendable.append:(C)Ljava/lang/Appendable;
        36: pop
        37: goto          65
        40: aload_0
        41: ldc           #206                // String &#x
        43: invokeinterface #148,  2          // InterfaceMethod java/lang/Appendable.append:(Ljava/lang/CharSequence;)Ljava/lang/Appendable;
        48: iload_2
        49: invokestatic  #211                // Method java/lang/Integer.toHexString:(I)Ljava/lang/String;
        52: invokeinterface #148,  2          // InterfaceMethod java/lang/Appendable.append:(Ljava/lang/CharSequence;)Ljava/lang/Appendable;
        57: bipush        59
        59: invokeinterface #142,  2          // InterfaceMethod java/lang/Appendable.append:(C)Ljava/lang/Appendable;
        64: pop
        65: return
      StackMapTable: number_of_entries = 2
        frame_type = 252 /* append */
          offset_delta = 40
          locals = [ class java/lang/String ]
        frame_type = 24 /* same */
      LineNumberTable:
        line 238: 0
        line 239: 6
        line 240: 15
        line 242: 40
        line 243: 65
      LocalVariableTable:
        Start  Length  Slot  Name   Signature
            0      66     0 accum   Ljava/lang/Appendable;
            0      66     1 escapeMode   Lcoursier/util/shaded/org/jsoup/nodes/Entities$EscapeMode;
            0      66     2 codePoint   I
            6      60     3  name   Ljava/lang/String;
    Exceptions:
      throws java.io.IOException

  public static java.lang.String unescape(java.lang.String);
    descriptor: (Ljava/lang/String;)Ljava/lang/String;
    flags: (0x0009) ACC_PUBLIC, ACC_STATIC
    Code:
      stack=2, locals=1, args_size=1
         0: aload_0
         1: iconst_0
         2: invokestatic  #215                // Method unescape:(Ljava/lang/String;Z)Ljava/lang/String;
         5: areturn
      LineNumberTable:
        line 252: 0
      LocalVariableTable:
        Start  Length  Slot  Name   Signature
            0       6     0 string   Ljava/lang/String;

  static java.lang.String unescape(java.lang.String, boolean);
    descriptor: (Ljava/lang/String;Z)Ljava/lang/String;
    flags: (0x0008) ACC_STATIC
    Code:
      stack=2, locals=2, args_size=2
         0: aload_0
         1: iload_1
         2: invokestatic  #220                // Method coursier/util/shaded/org/jsoup/parser/Parser.unescapeEntities:(Ljava/lang/String;Z)Ljava/lang/String;
         5: areturn
      LineNumberTable:
        line 263: 0
      LocalVariableTable:
        Start  Length  Slot  Name   Signature
            0       6     0 string   Ljava/lang/String;
            0       6     1 strict   Z

  private static boolean canEncode(coursier.util.shaded.org.jsoup.nodes.Entities$CoreCharset, char, java.nio.charset.CharsetEncoder);
    descriptor: (Lcoursier/util/shaded/org/jsoup/nodes/Entities$CoreCharset;CLjava/nio/charset/CharsetEncoder;)Z
    flags: (0x000a) ACC_PRIVATE, ACC_STATIC
    Code:
      stack=2, locals=3, args_size=3
         0: getstatic     #224                // Field coursier/util/shaded/org/jsoup/nodes/Entities$1.$SwitchMap$org$jsoup$nodes$Entities$CoreCharset:[I
         3: aload_0
         4: invokevirtual #227                // Method coursier/util/shaded/org/jsoup/nodes/Entities$CoreCharset.ordinal:()I
         7: iaload
         8: lookupswitch  { // 2
                       1: 36
                       2: 49
                 default: 51
            }
        36: iload_1
        37: sipush        128
        40: if_icmpge     47
        43: iconst_1
        44: goto          48
        47: iconst_0
        48: ireturn
        49: iconst_1
        50: ireturn
        51: aload_2
        52: iload_1
        53: invokevirtual #230                // Method java/nio/charset/CharsetEncoder.canEncode:(C)Z
        56: ireturn
      StackMapTable: number_of_entries = 5
        frame_type = 36 /* same */
        frame_type = 10 /* same */
        frame_type = 64 /* same_locals_1_stack_item */
          stack = [ int ]
        frame_type = 0 /* same */
        frame_type = 1 /* same */
      LineNumberTable:
        line 281: 0
        line 283: 36
        line 285: 49
        line 287: 51
      LocalVariableTable:
        Start  Length  Slot  Name   Signature
            0      57     0 charset   Lcoursier/util/shaded/org/jsoup/nodes/Entities$CoreCharset;
            0      57     1     c   C
            0      57     2 fallback   Ljava/nio/charset/CharsetEncoder;

  private static void load(coursier.util.shaded.org.jsoup.nodes.Entities$EscapeMode, java.lang.String, int);
    descriptor: (Lcoursier/util/shaded/org/jsoup/nodes/Entities$EscapeMode;Ljava/lang/String;I)V
    flags: (0x000a) ACC_PRIVATE, ACC_STATIC
    Code:
      stack=8, locals=11, args_size=3
         0: aload_0
         1: iload_2
         2: anewarray     #67                 // class java/lang/String
         5: invokestatic  #238                // Method coursier/util/shaded/org/jsoup/nodes/Entities$EscapeMode.access$102:(Lcoursier/util/shaded/org/jsoup/nodes/Entities$EscapeMode;[Ljava/lang/String;)[Ljava/lang/String;
         8: pop
         9: aload_0
        10: iload_2
        11: newarray       int
        13: invokestatic  #242                // Method coursier/util/shaded/org/jsoup/nodes/Entities$EscapeMode.access$202:(Lcoursier/util/shaded/org/jsoup/nodes/Entities$EscapeMode;[I)[I
        16: pop
        17: aload_0
        18: iload_2
        19: newarray       int
        21: invokestatic  #245                // Method coursier/util/shaded/org/jsoup/nodes/Entities$EscapeMode.access$302:(Lcoursier/util/shaded/org/jsoup/nodes/Entities$EscapeMode;[I)[I
        24: pop
        25: aload_0
        26: iload_2
        27: anewarray     #67                 // class java/lang/String
        30: invokestatic  #248                // Method coursier/util/shaded/org/jsoup/nodes/Entities$EscapeMode.access$402:(Lcoursier/util/shaded/org/jsoup/nodes/Entities$EscapeMode;[Ljava/lang/String;)[Ljava/lang/String;
        33: pop
        34: iconst_0
        35: istore_3
        36: new           #250                // class coursier/util/shaded/org/jsoup/parser/CharacterReader
        39: dup
        40: aload_1
        41: invokespecial #253                // Method coursier/util/shaded/org/jsoup/parser/CharacterReader."<init>":(Ljava/lang/String;)V
        44: astore        4
        46: aload         4
        48: invokevirtual #257                // Method coursier/util/shaded/org/jsoup/parser/CharacterReader.isEmpty:()Z
        51: ifne          227
        54: aload         4
        56: bipush        61
        58: invokevirtual #261                // Method coursier/util/shaded/org/jsoup/parser/CharacterReader.consumeTo:(C)Ljava/lang/String;
        61: astore        5
        63: aload         4
        65: invokevirtual #264                // Method coursier/util/shaded/org/jsoup/parser/CharacterReader.advance:()V
        68: aload         4
        70: getstatic     #266                // Field codeDelims:[C
        73: invokevirtual #270                // Method coursier/util/shaded/org/jsoup/parser/CharacterReader.consumeToAny:([C)Ljava/lang/String;
        76: bipush        36
        78: invokestatic  #274                // Method java/lang/Integer.parseInt:(Ljava/lang/String;I)I
        81: istore        6
        83: aload         4
        85: invokevirtual #278                // Method coursier/util/shaded/org/jsoup/parser/CharacterReader.current:()C
        88: istore        7
        90: aload         4
        92: invokevirtual #264                // Method coursier/util/shaded/org/jsoup/parser/CharacterReader.advance:()V
        95: iload         7
        97: bipush        44
        99: if_icmpne     124
       102: aload         4
       104: bipush        59
       106: invokevirtual #261                // Method coursier/util/shaded/org/jsoup/parser/CharacterReader.consumeTo:(C)Ljava/lang/String;
       109: bipush        36
       111: invokestatic  #274                // Method java/lang/Integer.parseInt:(Ljava/lang/String;I)I
       114: istore        8
       116: aload         4
       118: invokevirtual #264                // Method coursier/util/shaded/org/jsoup/parser/CharacterReader.advance:()V
       121: goto          127
       124: iconst_m1
       125: istore        8
       127: aload         4
       129: bipush        38
       131: invokevirtual #261                // Method coursier/util/shaded/org/jsoup/parser/CharacterReader.consumeTo:(C)Ljava/lang/String;
       134: astore        9
       136: aload         9
       138: bipush        36
       140: invokestatic  #274                // Method java/lang/Integer.parseInt:(Ljava/lang/String;I)I
       143: istore        10
       145: aload         4
       147: invokevirtual #264                // Method coursier/util/shaded/org/jsoup/parser/CharacterReader.advance:()V
       150: aload_0
       151: invokestatic  #282                // Method coursier/util/shaded/org/jsoup/nodes/Entities$EscapeMode.access$100:(Lcoursier/util/shaded/org/jsoup/nodes/Entities$EscapeMode;)[Ljava/lang/String;
       154: iload_3
       155: aload         5
       157: aastore
       158: aload_0
       159: invokestatic  #286                // Method coursier/util/shaded/org/jsoup/nodes/Entities$EscapeMode.access$200:(Lcoursier/util/shaded/org/jsoup/nodes/Entities$EscapeMode;)[I
       162: iload_3
       163: iload         6
       165: iastore
       166: aload_0
       167: invokestatic  #289                // Method coursier/util/shaded/org/jsoup/nodes/Entities$EscapeMode.access$300:(Lcoursier/util/shaded/org/jsoup/nodes/Entities$EscapeMode;)[I
       170: iload         10
       172: iload         6
       174: iastore
       175: aload_0
       176: invokestatic  #292                // Method coursier/util/shaded/org/jsoup/nodes/Entities$EscapeMode.access$400:(Lcoursier/util/shaded/org/jsoup/nodes/Entities$EscapeMode;)[Ljava/lang/String;
       179: iload         10
       181: aload         5
       183: aastore
       184: iload         8
       186: iconst_m1
       187: if_icmpeq     221
       190: getstatic     #59                 // Field multipoints:Ljava/util/HashMap;
       193: aload         5
       195: new           #67                 // class java/lang/String
       198: dup
       199: iconst_2
       200: newarray       int
       202: dup
       203: iconst_0
       204: iload         6
       206: iastore
       207: dup
       208: iconst_1
       209: iload         8
       211: iastore
       212: iconst_0
       213: iconst_2
       214: invokespecial #70                 // Method java/lang/String."<init>":([III)V
       217: invokevirtual #296                // Method java/util/HashMap.put:(Ljava/lang/Object;Ljava/lang/Object;)Ljava/lang/Object;
       220: pop
       221: iinc          3, 1
       224: goto          46
       227: iload_3
       228: iload_2
       229: if_icmpne     236
       232: iconst_1
       233: goto          237
       236: iconst_0
       237: ldc_w         #298                // String Unexpected count of entities loaded
       240: invokestatic  #304                // Method coursier/util/shaded/org/jsoup/helper/Validate.isTrue:(ZLjava/lang/String;)V
       243: return
      StackMapTable: number_of_entries = 7
        frame_type = 253 /* append */
          offset_delta = 46
          locals = [ int, class coursier/util/shaded/org/jsoup/parser/CharacterReader ]
        frame_type = 254 /* append */
          offset_delta = 77
          locals = [ class java/lang/String, int, int ]
        frame_type = 252 /* append */
          offset_delta = 2
          locals = [ int ]
        frame_type = 253 /* append */
          offset_delta = 93
          locals = [ class java/lang/String, int ]
        frame_type = 255 /* full_frame */
          offset_delta = 5
          locals = [ class coursier/util/shaded/org/jsoup/nodes/Entities$EscapeMode, class java/lang/String, int, int, class coursier/util/shaded/org/jsoup/parser/CharacterReader ]
          stack = []
        frame_type = 8 /* same */
        frame_type = 64 /* same_locals_1_stack_item */
          stack = [ int ]
      LineNumberTable:
        line 304: 0
        line 305: 9
        line 306: 17
        line 307: 25
        line 309: 34
        line 310: 36
        line 312: 46
        line 315: 54
        line 316: 63
        line 317: 68
        line 318: 83
        line 319: 90
        line 321: 95
        line 322: 102
        line 323: 116
        line 325: 124
        line 327: 127
        line 328: 136
        line 329: 145
        line 331: 150
        line 332: 158
        line 333: 166
        line 334: 175
        line 336: 184
        line 337: 190
        line 339: 221
        line 340: 224
        line 342: 227
        line 343: 243
      LocalVariableTable:
        Start  Length  Slot  Name   Signature
          116       8     8   cp2   I
           63     161     5  name   Ljava/lang/String;
           83     141     6   cp1   I
           90     134     7 codeDelim   C
          127      97     8   cp2   I
          136      88     9 indexS   Ljava/lang/String;
          145      79    10 index   I
            0     244     0     e   Lcoursier/util/shaded/org/jsoup/nodes/Entities$EscapeMode;
            0     244     1 pointsData   Ljava/lang/String;
            0     244     2  size   I
           36     208     3     i   I
           46     198     4 reader   Lcoursier/util/shaded/org/jsoup/parser/CharacterReader;

  static void access$000(coursier.util.shaded.org.jsoup.nodes.Entities$EscapeMode, java.lang.String, int);
    descriptor: (Lcoursier/util/shaded/org/jsoup/nodes/Entities$EscapeMode;Ljava/lang/String;I)V
    flags: (0x1008) ACC_STATIC, ACC_SYNTHETIC
    Code:
      stack=3, locals=3, args_size=3
         0: aload_0
         1: aload_1
         2: iload_2
         3: invokestatic  #317                // Method load:(Lcoursier/util/shaded/org/jsoup/nodes/Entities$EscapeMode;Ljava/lang/String;I)V
         6: return
      LineNumberTable:
        line 21: 0
      LocalVariableTable:
        Start  Length  Slot  Name   Signature
            0       7     0    x0   Lcoursier/util/shaded/org/jsoup/nodes/Entities$EscapeMode;
            0       7     1    x1   Ljava/lang/String;
            0       7     2    x2   I

  static {};
    descriptor: ()V
    flags: (0x0008) ACC_STATIC
    Code:
      stack=4, locals=0, args_size=0
         0: iconst_2
         1: newarray       char
         3: dup
         4: iconst_0
         5: bipush        44
         7: castore
         8: dup
         9: iconst_1
        10: bipush        59
        12: castore
        13: putstatic     #266                // Field codeDelims:[C
        16: new           #61                 // class java/util/HashMap
        19: dup
        20: invokespecial #322                // Method java/util/HashMap."<init>":()V
        23: putstatic     #59                 // Field multipoints:Ljava/util/HashMap;
        26: new           #10                 // class coursier/util/shaded/org/jsoup/nodes/Document$OutputSettings
        29: dup
        30: invokespecial #323                // Method coursier/util/shaded/org/jsoup/nodes/Document$OutputSettings."<init>":()V
        33: putstatic     #112                // Field DefaultOutput:Lcoursier/util/shaded/org/jsoup/nodes/Document$OutputSettings;
        36: return
      LineNumberTable:
        line 25: 0
        line 26: 16
        line 27: 26
}
InnerClasses:
  public static final #8= #7 of #2;       // EscapeMode=class coursier/util/shaded/org/jsoup/nodes/Entities$EscapeMode of class coursier/util/shaded/org/jsoup/nodes/Entities
  public static #13= #10 of #12;          // OutputSettings=class coursier/util/shaded/org/jsoup/nodes/Document$OutputSettings of class coursier/util/shaded/org/jsoup/nodes/Document
  static final #16= #15 of #2;            // CoreCharset=class coursier/util/shaded/org/jsoup/nodes/Entities$CoreCharset of class coursier/util/shaded/org/jsoup/nodes/Entities
  static #18;                             // class coursier/util/shaded/org/jsoup/nodes/Entities$1
SourceFile: "Entities.java"
