Classfile /Users/mw/Projects/slang-braindump/.jar/jar11/assemble/slang-braindump/assemble/content/coursier/util/shaded/org/jsoup/nodes/XmlDeclaration.class
  Last modified May 29, 2022; size 4525 bytes
  SHA-256 checksum 90e9d1f957011162c80446278f44f05e42760bcd02cd8e0c9d3a90096588db4c
  Compiled from "XmlDeclaration.java"
public class coursier.util.shaded.org.jsoup.nodes.XmlDeclaration extends coursier.util.shaded.org.jsoup.nodes.LeafNode
  minor version: 0
  major version: 51
  flags: (0x0021) ACC_PUBLIC, ACC_SUPER
  this_class: #2                          // coursier/util/shaded/org/jsoup/nodes/XmlDeclaration
  super_class: #4                         // coursier/util/shaded/org/jsoup/nodes/LeafNode
  interfaces: 0, fields: 1, methods: 19, attributes: 2
Constant pool:
    #1 = Utf8               coursier/util/shaded/org/jsoup/nodes/XmlDeclaration
    #2 = Class              #1            // coursier/util/shaded/org/jsoup/nodes/XmlDeclaration
    #3 = Utf8               coursier/util/shaded/org/jsoup/nodes/LeafNode
    #4 = Class              #3            // coursier/util/shaded/org/jsoup/nodes/LeafNode
    #5 = Utf8               XmlDeclaration.java
    #6 = Utf8               coursier/util/shaded/org/jsoup/nodes/Document$OutputSettings
    #7 = Class              #6            // coursier/util/shaded/org/jsoup/nodes/Document$OutputSettings
    #8 = Utf8               coursier/util/shaded/org/jsoup/nodes/Document
    #9 = Class              #8            // coursier/util/shaded/org/jsoup/nodes/Document
   #10 = Utf8               OutputSettings
   #11 = Utf8               isProcessingInstruction
   #12 = Utf8               Z
   #13 = Utf8               <init>
   #14 = Utf8               (Ljava/lang/String;Z)V
   #15 = Utf8               ()V
   #16 = NameAndType        #13:#15       // "<init>":()V
   #17 = Methodref          #4.#16        // coursier/util/shaded/org/jsoup/nodes/LeafNode."<init>":()V
   #18 = Utf8               coursier/util/shaded/org/jsoup/helper/Validate
   #19 = Class              #18           // coursier/util/shaded/org/jsoup/helper/Validate
   #20 = Utf8               notNull
   #21 = Utf8               (Ljava/lang/Object;)V
   #22 = NameAndType        #20:#21       // notNull:(Ljava/lang/Object;)V
   #23 = Methodref          #19.#22       // coursier/util/shaded/org/jsoup/helper/Validate.notNull:(Ljava/lang/Object;)V
   #24 = Utf8               value
   #25 = Utf8               Ljava/lang/Object;
   #26 = NameAndType        #24:#25       // value:Ljava/lang/Object;
   #27 = Fieldref           #2.#26        // coursier/util/shaded/org/jsoup/nodes/XmlDeclaration.value:Ljava/lang/Object;
   #28 = NameAndType        #11:#12       // isProcessingInstruction:Z
   #29 = Fieldref           #2.#28        // coursier/util/shaded/org/jsoup/nodes/XmlDeclaration.isProcessingInstruction:Z
   #30 = Utf8               this
   #31 = Utf8               Lcoursier/util/shaded/org/jsoup/nodes/XmlDeclaration;
   #32 = Utf8               name
   #33 = Utf8               Ljava/lang/String;
   #34 = Utf8               nodeName
   #35 = Utf8               ()Ljava/lang/String;
   #36 = Utf8               #declaration
   #37 = String             #36           // #declaration
   #38 = Utf8               coreValue
   #39 = NameAndType        #38:#35       // coreValue:()Ljava/lang/String;
   #40 = Methodref          #2.#39        // coursier/util/shaded/org/jsoup/nodes/XmlDeclaration.coreValue:()Ljava/lang/String;
   #41 = Utf8               getWholeDeclaration
   #42 = Utf8               java/io/IOException
   #43 = Class              #42           // java/io/IOException
   #44 = Utf8               coursier/util/shaded/org/jsoup/internal/StringUtil
   #45 = Class              #44           // coursier/util/shaded/org/jsoup/internal/StringUtil
   #46 = Utf8               borrowBuilder
   #47 = Utf8               ()Ljava/lang/StringBuilder;
   #48 = NameAndType        #46:#47       // borrowBuilder:()Ljava/lang/StringBuilder;
   #49 = Methodref          #45.#48       // coursier/util/shaded/org/jsoup/internal/StringUtil.borrowBuilder:()Ljava/lang/StringBuilder;
   #50 = Methodref          #7.#16        // coursier/util/shaded/org/jsoup/nodes/Document$OutputSettings."<init>":()V
   #51 = Utf8               (Ljava/lang/Appendable;Lcoursier/util/shaded/org/jsoup/nodes/Document$OutputSettings;)V
   #52 = NameAndType        #41:#51       // getWholeDeclaration:(Ljava/lang/Appendable;Lcoursier/util/shaded/org/jsoup/nodes/Document$OutputSettings;)V
   #53 = Methodref          #2.#52        // coursier/util/shaded/org/jsoup/nodes/XmlDeclaration.getWholeDeclaration:(Ljava/lang/Appendable;Lcoursier/util/shaded/org/jsoup/nodes/Document$OutputSettings;)V
   #54 = Utf8               java/lang/StringBuilder
   #55 = Class              #54           // java/lang/StringBuilder
   #56 = Utf8               coursier/util/shaded/org/jsoup/SerializationException
   #57 = Class              #56           // coursier/util/shaded/org/jsoup/SerializationException
   #58 = Utf8               (Ljava/lang/Throwable;)V
   #59 = NameAndType        #13:#58       // "<init>":(Ljava/lang/Throwable;)V
   #60 = Methodref          #57.#59       // coursier/util/shaded/org/jsoup/SerializationException."<init>":(Ljava/lang/Throwable;)V
   #61 = Utf8               releaseBuilder
   #62 = Utf8               (Ljava/lang/StringBuilder;)Ljava/lang/String;
   #63 = NameAndType        #61:#62       // releaseBuilder:(Ljava/lang/StringBuilder;)Ljava/lang/String;
   #64 = Methodref          #45.#63       // coursier/util/shaded/org/jsoup/internal/StringUtil.releaseBuilder:(Ljava/lang/StringBuilder;)Ljava/lang/String;
   #65 = Utf8               java/lang/String
   #66 = Class              #65           // java/lang/String
   #67 = Utf8               trim
   #68 = NameAndType        #67:#35       // trim:()Ljava/lang/String;
   #69 = Methodref          #66.#68       // java/lang/String.trim:()Ljava/lang/String;
   #70 = Utf8               e
   #71 = Utf8               Ljava/io/IOException;
   #72 = Utf8               sb
   #73 = Utf8               Ljava/lang/StringBuilder;
   #74 = Utf8               attributes
   #75 = Utf8               ()Lcoursier/util/shaded/org/jsoup/nodes/Attributes;
   #76 = NameAndType        #74:#75       // attributes:()Lcoursier/util/shaded/org/jsoup/nodes/Attributes;
   #77 = Methodref          #2.#76        // coursier/util/shaded/org/jsoup/nodes/XmlDeclaration.attributes:()Lcoursier/util/shaded/org/jsoup/nodes/Attributes;
   #78 = Utf8               coursier/util/shaded/org/jsoup/nodes/Attributes
   #79 = Class              #78           // coursier/util/shaded/org/jsoup/nodes/Attributes
   #80 = Utf8               iterator
   #81 = Utf8               ()Ljava/util/Iterator;
   #82 = NameAndType        #80:#81       // iterator:()Ljava/util/Iterator;
   #83 = Methodref          #79.#82       // coursier/util/shaded/org/jsoup/nodes/Attributes.iterator:()Ljava/util/Iterator;
   #84 = Utf8               java/util/Iterator
   #85 = Class              #84           // java/util/Iterator
   #86 = Utf8               hasNext
   #87 = Utf8               ()Z
   #88 = NameAndType        #86:#87       // hasNext:()Z
   #89 = InterfaceMethodref #85.#88       // java/util/Iterator.hasNext:()Z
   #90 = Utf8               next
   #91 = Utf8               ()Ljava/lang/Object;
   #92 = NameAndType        #90:#91       // next:()Ljava/lang/Object;
   #93 = InterfaceMethodref #85.#92       // java/util/Iterator.next:()Ljava/lang/Object;
   #94 = Utf8               coursier/util/shaded/org/jsoup/nodes/Attribute
   #95 = Class              #94           // coursier/util/shaded/org/jsoup/nodes/Attribute
   #96 = Utf8               getKey
   #97 = NameAndType        #96:#35       // getKey:()Ljava/lang/String;
   #98 = Methodref          #95.#97       // coursier/util/shaded/org/jsoup/nodes/Attribute.getKey:()Ljava/lang/String;
   #99 = NameAndType        #34:#35       // nodeName:()Ljava/lang/String;
  #100 = Methodref          #2.#99        // coursier/util/shaded/org/jsoup/nodes/XmlDeclaration.nodeName:()Ljava/lang/String;
  #101 = Utf8               equals
  #102 = Utf8               (Ljava/lang/Object;)Z
  #103 = NameAndType        #101:#102     // equals:(Ljava/lang/Object;)Z
  #104 = Methodref          #66.#103      // java/lang/String.equals:(Ljava/lang/Object;)Z
  #105 = Utf8               java/lang/Appendable
  #106 = Class              #105          // java/lang/Appendable
  #107 = Utf8               append
  #108 = Utf8               (C)Ljava/lang/Appendable;
  #109 = NameAndType        #107:#108     // append:(C)Ljava/lang/Appendable;
  #110 = InterfaceMethodref #106.#109     // java/lang/Appendable.append:(C)Ljava/lang/Appendable;
  #111 = Utf8               html
  #112 = NameAndType        #111:#51      // html:(Ljava/lang/Appendable;Lcoursier/util/shaded/org/jsoup/nodes/Document$OutputSettings;)V
  #113 = Methodref          #95.#112      // coursier/util/shaded/org/jsoup/nodes/Attribute.html:(Ljava/lang/Appendable;Lcoursier/util/shaded/org/jsoup/nodes/Document$OutputSettings;)V
  #114 = Utf8               attribute
  #115 = Utf8               Lcoursier/util/shaded/org/jsoup/nodes/Attribute;
  #116 = Utf8               accum
  #117 = Utf8               Ljava/lang/Appendable;
  #118 = Utf8               out
  #119 = Utf8               Lcoursier/util/shaded/org/jsoup/nodes/Document$OutputSettings;
  #120 = Utf8               outerHtmlHead
  #121 = Utf8               (Ljava/lang/Appendable;ILcoursier/util/shaded/org/jsoup/nodes/Document$OutputSettings;)V
  #122 = Utf8               <
  #123 = String             #122          // <
  #124 = Utf8               (Ljava/lang/CharSequence;)Ljava/lang/Appendable;
  #125 = NameAndType        #107:#124     // append:(Ljava/lang/CharSequence;)Ljava/lang/Appendable;
  #126 = InterfaceMethodref #106.#125     // java/lang/Appendable.append:(Ljava/lang/CharSequence;)Ljava/lang/Appendable;
  #127 = Utf8               !
  #128 = String             #127          // !
  #129 = Utf8               ?
  #130 = String             #129          // ?
  #131 = Utf8               >
  #132 = String             #131          // >
  #133 = Utf8               depth
  #134 = Utf8               I
  #135 = Utf8               outerHtmlTail
  #136 = Utf8               toString
  #137 = Utf8               outerHtml
  #138 = NameAndType        #137:#35      // outerHtml:()Ljava/lang/String;
  #139 = Methodref          #2.#138       // coursier/util/shaded/org/jsoup/nodes/XmlDeclaration.outerHtml:()Ljava/lang/String;
  #140 = Utf8               clone
  #141 = Utf8               ()Lcoursier/util/shaded/org/jsoup/nodes/XmlDeclaration;
  #142 = Utf8               ()Lcoursier/util/shaded/org/jsoup/nodes/Node;
  #143 = NameAndType        #140:#142     // clone:()Lcoursier/util/shaded/org/jsoup/nodes/Node;
  #144 = Methodref          #4.#143       // coursier/util/shaded/org/jsoup/nodes/LeafNode.clone:()Lcoursier/util/shaded/org/jsoup/nodes/Node;
  #145 = Utf8               empty
  #146 = NameAndType        #145:#142     // empty:()Lcoursier/util/shaded/org/jsoup/nodes/Node;
  #147 = Methodref          #4.#146       // coursier/util/shaded/org/jsoup/nodes/LeafNode.empty:()Lcoursier/util/shaded/org/jsoup/nodes/Node;
  #148 = Utf8               childNodeSize
  #149 = Utf8               ()I
  #150 = NameAndType        #148:#149     // childNodeSize:()I
  #151 = Methodref          #4.#150       // coursier/util/shaded/org/jsoup/nodes/LeafNode.childNodeSize:()I
  #152 = Utf8               baseUri
  #153 = NameAndType        #152:#35      // baseUri:()Ljava/lang/String;
  #154 = Methodref          #4.#153       // coursier/util/shaded/org/jsoup/nodes/LeafNode.baseUri:()Ljava/lang/String;
  #155 = Utf8               absUrl
  #156 = Utf8               (Ljava/lang/String;)Ljava/lang/String;
  #157 = NameAndType        #155:#156     // absUrl:(Ljava/lang/String;)Ljava/lang/String;
  #158 = Methodref          #4.#157       // coursier/util/shaded/org/jsoup/nodes/LeafNode.absUrl:(Ljava/lang/String;)Ljava/lang/String;
  #159 = Utf8               removeAttr
  #160 = Utf8               (Ljava/lang/String;)Lcoursier/util/shaded/org/jsoup/nodes/Node;
  #161 = NameAndType        #159:#160     // removeAttr:(Ljava/lang/String;)Lcoursier/util/shaded/org/jsoup/nodes/Node;
  #162 = Methodref          #4.#161       // coursier/util/shaded/org/jsoup/nodes/LeafNode.removeAttr:(Ljava/lang/String;)Lcoursier/util/shaded/org/jsoup/nodes/Node;
  #163 = Utf8               hasAttr
  #164 = Utf8               (Ljava/lang/String;)Z
  #165 = NameAndType        #163:#164     // hasAttr:(Ljava/lang/String;)Z
  #166 = Methodref          #4.#165       // coursier/util/shaded/org/jsoup/nodes/LeafNode.hasAttr:(Ljava/lang/String;)Z
  #167 = Utf8               attr
  #168 = Utf8               (Ljava/lang/String;Ljava/lang/String;)Lcoursier/util/shaded/org/jsoup/nodes/Node;
  #169 = NameAndType        #167:#168     // attr:(Ljava/lang/String;Ljava/lang/String;)Lcoursier/util/shaded/org/jsoup/nodes/Node;
  #170 = Methodref          #4.#169       // coursier/util/shaded/org/jsoup/nodes/LeafNode.attr:(Ljava/lang/String;Ljava/lang/String;)Lcoursier/util/shaded/org/jsoup/nodes/Node;
  #171 = NameAndType        #167:#156     // attr:(Ljava/lang/String;)Ljava/lang/String;
  #172 = Methodref          #4.#171       // coursier/util/shaded/org/jsoup/nodes/LeafNode.attr:(Ljava/lang/String;)Ljava/lang/String;
  #173 = NameAndType        #140:#141     // clone:()Lcoursier/util/shaded/org/jsoup/nodes/XmlDeclaration;
  #174 = Methodref          #2.#173       // coursier/util/shaded/org/jsoup/nodes/XmlDeclaration.clone:()Lcoursier/util/shaded/org/jsoup/nodes/XmlDeclaration;
  #175 = Utf8               java/lang/CloneNotSupportedException
  #176 = Class              #175          // java/lang/CloneNotSupportedException
  #177 = Utf8               Code
  #178 = Utf8               LineNumberTable
  #179 = Utf8               LocalVariableTable
  #180 = Utf8               StackMapTable
  #181 = Utf8               Exceptions
  #182 = Utf8               InnerClasses
  #183 = Utf8               SourceFile
{
  private final boolean isProcessingInstruction;
    descriptor: Z
    flags: (0x0012) ACC_PRIVATE, ACC_FINAL

  public coursier.util.shaded.org.jsoup.nodes.XmlDeclaration(java.lang.String, boolean);
    descriptor: (Ljava/lang/String;Z)V
    flags: (0x0001) ACC_PUBLIC
    Code:
      stack=2, locals=3, args_size=3
         0: aload_0
         1: invokespecial #17                 // Method coursier/util/shaded/org/jsoup/nodes/LeafNode."<init>":()V
         4: aload_1
         5: invokestatic  #23                 // Method coursier/util/shaded/org/jsoup/helper/Validate.notNull:(Ljava/lang/Object;)V
         8: aload_0
         9: aload_1
        10: putfield      #27                 // Field value:Ljava/lang/Object;
        13: aload_0
        14: iload_2
        15: putfield      #29                 // Field isProcessingInstruction:Z
        18: return
      LineNumberTable:
        line 21: 0
        line 22: 4
        line 23: 8
        line 24: 13
        line 25: 18
      LocalVariableTable:
        Start  Length  Slot  Name   Signature
            0      19     0  this   Lcoursier/util/shaded/org/jsoup/nodes/XmlDeclaration;
            0      19     1  name   Ljava/lang/String;
            0      19     2 isProcessingInstruction   Z

  public java.lang.String nodeName();
    descriptor: ()Ljava/lang/String;
    flags: (0x0001) ACC_PUBLIC
    Code:
      stack=1, locals=1, args_size=1
         0: ldc           #37                 // String #declaration
         2: areturn
      LineNumberTable:
        line 28: 0
      LocalVariableTable:
        Start  Length  Slot  Name   Signature
            0       3     0  this   Lcoursier/util/shaded/org/jsoup/nodes/XmlDeclaration;

  public java.lang.String name();
    descriptor: ()Ljava/lang/String;
    flags: (0x0001) ACC_PUBLIC
    Code:
      stack=1, locals=1, args_size=1
         0: aload_0
         1: invokevirtual #40                 // Method coreValue:()Ljava/lang/String;
         4: areturn
      LineNumberTable:
        line 36: 0
      LocalVariableTable:
        Start  Length  Slot  Name   Signature
            0       5     0  this   Lcoursier/util/shaded/org/jsoup/nodes/XmlDeclaration;

  public java.lang.String getWholeDeclaration();
    descriptor: ()Ljava/lang/String;
    flags: (0x0001) ACC_PUBLIC
    Code:
      stack=4, locals=3, args_size=1
         0: invokestatic  #49                 // Method coursier/util/shaded/org/jsoup/internal/StringUtil.borrowBuilder:()Ljava/lang/StringBuilder;
         3: astore_1
         4: aload_0
         5: aload_1
         6: new           #7                  // class coursier/util/shaded/org/jsoup/nodes/Document$OutputSettings
         9: dup
        10: invokespecial #50                 // Method coursier/util/shaded/org/jsoup/nodes/Document$OutputSettings."<init>":()V
        13: invokespecial #53                 // Method getWholeDeclaration:(Ljava/lang/Appendable;Lcoursier/util/shaded/org/jsoup/nodes/Document$OutputSettings;)V
        16: goto          29
        19: astore_2
        20: new           #57                 // class coursier/util/shaded/org/jsoup/SerializationException
        23: dup
        24: aload_2
        25: invokespecial #60                 // Method coursier/util/shaded/org/jsoup/SerializationException."<init>":(Ljava/lang/Throwable;)V
        28: athrow
        29: aload_1
        30: invokestatic  #64                 // Method coursier/util/shaded/org/jsoup/internal/StringUtil.releaseBuilder:(Ljava/lang/StringBuilder;)Ljava/lang/String;
        33: invokevirtual #69                 // Method java/lang/String.trim:()Ljava/lang/String;
        36: areturn
      Exception table:
         from    to  target type
             4    16    19   Class java/io/IOException
      StackMapTable: number_of_entries = 2
        frame_type = 255 /* full_frame */
          offset_delta = 19
          locals = [ class coursier/util/shaded/org/jsoup/nodes/XmlDeclaration, class java/lang/StringBuilder ]
          stack = [ class java/io/IOException ]
        frame_type = 9 /* same */
      LineNumberTable:
        line 44: 0
        line 46: 4
        line 49: 16
        line 47: 19
        line 48: 20
        line 50: 29
      LocalVariableTable:
        Start  Length  Slot  Name   Signature
           20       9     2     e   Ljava/io/IOException;
            0      37     0  this   Lcoursier/util/shaded/org/jsoup/nodes/XmlDeclaration;
            4      33     1    sb   Ljava/lang/StringBuilder;

  private void getWholeDeclaration(java.lang.Appendable, coursier.util.shaded.org.jsoup.nodes.Document$OutputSettings) throws java.io.IOException;
    descriptor: (Ljava/lang/Appendable;Lcoursier/util/shaded/org/jsoup/nodes/Document$OutputSettings;)V
    flags: (0x0002) ACC_PRIVATE
    Code:
      stack=3, locals=5, args_size=3
         0: aload_0
         1: invokevirtual #77                 // Method attributes:()Lcoursier/util/shaded/org/jsoup/nodes/Attributes;
         4: invokevirtual #83                 // Method coursier/util/shaded/org/jsoup/nodes/Attributes.iterator:()Ljava/util/Iterator;
         7: astore_3
         8: aload_3
         9: invokeinterface #89,  1           // InterfaceMethod java/util/Iterator.hasNext:()Z
        14: ifeq          62
        17: aload_3
        18: invokeinterface #93,  1           // InterfaceMethod java/util/Iterator.next:()Ljava/lang/Object;
        23: checkcast     #95                 // class coursier/util/shaded/org/jsoup/nodes/Attribute
        26: astore        4
        28: aload         4
        30: invokevirtual #98                 // Method coursier/util/shaded/org/jsoup/nodes/Attribute.getKey:()Ljava/lang/String;
        33: aload_0
        34: invokevirtual #100                // Method nodeName:()Ljava/lang/String;
        37: invokevirtual #104                // Method java/lang/String.equals:(Ljava/lang/Object;)Z
        40: ifne          59
        43: aload_1
        44: bipush        32
        46: invokeinterface #110,  2          // InterfaceMethod java/lang/Appendable.append:(C)Ljava/lang/Appendable;
        51: pop
        52: aload         4
        54: aload_1
        55: aload_2
        56: invokevirtual #113                // Method coursier/util/shaded/org/jsoup/nodes/Attribute.html:(Ljava/lang/Appendable;Lcoursier/util/shaded/org/jsoup/nodes/Document$OutputSettings;)V
        59: goto          8
        62: return
      StackMapTable: number_of_entries = 3
        frame_type = 252 /* append */
          offset_delta = 8
          locals = [ class java/util/Iterator ]
        frame_type = 50 /* same */
        frame_type = 250 /* chop */
          offset_delta = 2
      LineNumberTable:
        line 54: 0
        line 55: 28
        line 56: 43
        line 57: 52
        line 59: 59
        line 60: 62
      LocalVariableTable:
        Start  Length  Slot  Name   Signature
           28      31     4 attribute   Lcoursier/util/shaded/org/jsoup/nodes/Attribute;
            0      63     0  this   Lcoursier/util/shaded/org/jsoup/nodes/XmlDeclaration;
            0      63     1 accum   Ljava/lang/Appendable;
            0      63     2   out   Lcoursier/util/shaded/org/jsoup/nodes/Document$OutputSettings;
    Exceptions:
      throws java.io.IOException

  void outerHtmlHead(java.lang.Appendable, int, coursier.util.shaded.org.jsoup.nodes.Document$OutputSettings) throws java.io.IOException;
    descriptor: (Ljava/lang/Appendable;ILcoursier/util/shaded/org/jsoup/nodes/Document$OutputSettings;)V
    flags: (0x0000)
    Code:
      stack=3, locals=4, args_size=4
         0: aload_1
         1: ldc           #123                // String <
         3: invokeinterface #126,  2          // InterfaceMethod java/lang/Appendable.append:(Ljava/lang/CharSequence;)Ljava/lang/Appendable;
         8: aload_0
         9: getfield      #29                 // Field isProcessingInstruction:Z
        12: ifeq          20
        15: ldc           #128                // String !
        17: goto          22
        20: ldc           #130                // String ?
        22: invokeinterface #126,  2          // InterfaceMethod java/lang/Appendable.append:(Ljava/lang/CharSequence;)Ljava/lang/Appendable;
        27: aload_0
        28: invokevirtual #40                 // Method coreValue:()Ljava/lang/String;
        31: invokeinterface #126,  2          // InterfaceMethod java/lang/Appendable.append:(Ljava/lang/CharSequence;)Ljava/lang/Appendable;
        36: pop
        37: aload_0
        38: aload_1
        39: aload_3
        40: invokespecial #53                 // Method getWholeDeclaration:(Ljava/lang/Appendable;Lcoursier/util/shaded/org/jsoup/nodes/Document$OutputSettings;)V
        43: aload_1
        44: aload_0
        45: getfield      #29                 // Field isProcessingInstruction:Z
        48: ifeq          56
        51: ldc           #128                // String !
        53: goto          58
        56: ldc           #130                // String ?
        58: invokeinterface #126,  2          // InterfaceMethod java/lang/Appendable.append:(Ljava/lang/CharSequence;)Ljava/lang/Appendable;
        63: ldc           #132                // String >
        65: invokeinterface #126,  2          // InterfaceMethod java/lang/Appendable.append:(Ljava/lang/CharSequence;)Ljava/lang/Appendable;
        70: pop
        71: return
      StackMapTable: number_of_entries = 4
        frame_type = 84 /* same_locals_1_stack_item */
          stack = [ class java/lang/Appendable ]
        frame_type = 255 /* full_frame */
          offset_delta = 1
          locals = [ class coursier/util/shaded/org/jsoup/nodes/XmlDeclaration, class java/lang/Appendable, int, class coursier/util/shaded/org/jsoup/nodes/Document$OutputSettings ]
          stack = [ class java/lang/Appendable, class java/lang/String ]
        frame_type = 97 /* same_locals_1_stack_item */
          stack = [ class java/lang/Appendable ]
        frame_type = 255 /* full_frame */
          offset_delta = 1
          locals = [ class coursier/util/shaded/org/jsoup/nodes/XmlDeclaration, class java/lang/Appendable, int, class coursier/util/shaded/org/jsoup/nodes/Document$OutputSettings ]
          stack = [ class java/lang/Appendable, class java/lang/String ]
      LineNumberTable:
        line 63: 0
        line 64: 3
        line 65: 8
        line 66: 28
        line 67: 37
        line 68: 43
        line 69: 44
        line 70: 65
        line 71: 71
      LocalVariableTable:
        Start  Length  Slot  Name   Signature
            0      72     0  this   Lcoursier/util/shaded/org/jsoup/nodes/XmlDeclaration;
            0      72     1 accum   Ljava/lang/Appendable;
            0      72     2 depth   I
            0      72     3   out   Lcoursier/util/shaded/org/jsoup/nodes/Document$OutputSettings;
    Exceptions:
      throws java.io.IOException

  void outerHtmlTail(java.lang.Appendable, int, coursier.util.shaded.org.jsoup.nodes.Document$OutputSettings);
    descriptor: (Ljava/lang/Appendable;ILcoursier/util/shaded/org/jsoup/nodes/Document$OutputSettings;)V
    flags: (0x0000)
    Code:
      stack=0, locals=4, args_size=4
         0: return
      LineNumberTable:
        line 74: 0
      LocalVariableTable:
        Start  Length  Slot  Name   Signature
            0       1     0  this   Lcoursier/util/shaded/org/jsoup/nodes/XmlDeclaration;
            0       1     1 accum   Ljava/lang/Appendable;
            0       1     2 depth   I
            0       1     3   out   Lcoursier/util/shaded/org/jsoup/nodes/Document$OutputSettings;

  public java.lang.String toString();
    descriptor: ()Ljava/lang/String;
    flags: (0x0001) ACC_PUBLIC
    Code:
      stack=1, locals=1, args_size=1
         0: aload_0
         1: invokevirtual #139                // Method outerHtml:()Ljava/lang/String;
         4: areturn
      LineNumberTable:
        line 78: 0
      LocalVariableTable:
        Start  Length  Slot  Name   Signature
            0       5     0  this   Lcoursier/util/shaded/org/jsoup/nodes/XmlDeclaration;

  public coursier.util.shaded.org.jsoup.nodes.XmlDeclaration clone();
    descriptor: ()Lcoursier/util/shaded/org/jsoup/nodes/XmlDeclaration;
    flags: (0x0001) ACC_PUBLIC
    Code:
      stack=1, locals=1, args_size=1
         0: aload_0
         1: invokespecial #144                // Method coursier/util/shaded/org/jsoup/nodes/LeafNode.clone:()Lcoursier/util/shaded/org/jsoup/nodes/Node;
         4: checkcast     #2                  // class coursier/util/shaded/org/jsoup/nodes/XmlDeclaration
         7: areturn
      LineNumberTable:
        line 83: 0
      LocalVariableTable:
        Start  Length  Slot  Name   Signature
            0       8     0  this   Lcoursier/util/shaded/org/jsoup/nodes/XmlDeclaration;

  public coursier.util.shaded.org.jsoup.nodes.Node empty();
    descriptor: ()Lcoursier/util/shaded/org/jsoup/nodes/Node;
    flags: (0x1041) ACC_PUBLIC, ACC_BRIDGE, ACC_SYNTHETIC
    Code:
      stack=1, locals=1, args_size=1
         0: aload_0
         1: invokespecial #147                // Method coursier/util/shaded/org/jsoup/nodes/LeafNode.empty:()Lcoursier/util/shaded/org/jsoup/nodes/Node;
         4: areturn
      LineNumberTable:
        line 12: 0
      LocalVariableTable:
        Start  Length  Slot  Name   Signature
            0       5     0  this   Lcoursier/util/shaded/org/jsoup/nodes/XmlDeclaration;

  public int childNodeSize();
    descriptor: ()I
    flags: (0x1041) ACC_PUBLIC, ACC_BRIDGE, ACC_SYNTHETIC
    Code:
      stack=1, locals=1, args_size=1
         0: aload_0
         1: invokespecial #151                // Method coursier/util/shaded/org/jsoup/nodes/LeafNode.childNodeSize:()I
         4: ireturn
      LineNumberTable:
        line 12: 0
      LocalVariableTable:
        Start  Length  Slot  Name   Signature
            0       5     0  this   Lcoursier/util/shaded/org/jsoup/nodes/XmlDeclaration;

  public java.lang.String baseUri();
    descriptor: ()Ljava/lang/String;
    flags: (0x1041) ACC_PUBLIC, ACC_BRIDGE, ACC_SYNTHETIC
    Code:
      stack=1, locals=1, args_size=1
         0: aload_0
         1: invokespecial #154                // Method coursier/util/shaded/org/jsoup/nodes/LeafNode.baseUri:()Ljava/lang/String;
         4: areturn
      LineNumberTable:
        line 12: 0
      LocalVariableTable:
        Start  Length  Slot  Name   Signature
            0       5     0  this   Lcoursier/util/shaded/org/jsoup/nodes/XmlDeclaration;

  public java.lang.String absUrl(java.lang.String);
    descriptor: (Ljava/lang/String;)Ljava/lang/String;
    flags: (0x1041) ACC_PUBLIC, ACC_BRIDGE, ACC_SYNTHETIC
    Code:
      stack=2, locals=2, args_size=2
         0: aload_0
         1: aload_1
         2: invokespecial #158                // Method coursier/util/shaded/org/jsoup/nodes/LeafNode.absUrl:(Ljava/lang/String;)Ljava/lang/String;
         5: areturn
      LineNumberTable:
        line 12: 0
      LocalVariableTable:
        Start  Length  Slot  Name   Signature
            0       6     0  this   Lcoursier/util/shaded/org/jsoup/nodes/XmlDeclaration;

  public coursier.util.shaded.org.jsoup.nodes.Node removeAttr(java.lang.String);
    descriptor: (Ljava/lang/String;)Lcoursier/util/shaded/org/jsoup/nodes/Node;
    flags: (0x1041) ACC_PUBLIC, ACC_BRIDGE, ACC_SYNTHETIC
    Code:
      stack=2, locals=2, args_size=2
         0: aload_0
         1: aload_1
         2: invokespecial #162                // Method coursier/util/shaded/org/jsoup/nodes/LeafNode.removeAttr:(Ljava/lang/String;)Lcoursier/util/shaded/org/jsoup/nodes/Node;
         5: areturn
      LineNumberTable:
        line 12: 0
      LocalVariableTable:
        Start  Length  Slot  Name   Signature
            0       6     0  this   Lcoursier/util/shaded/org/jsoup/nodes/XmlDeclaration;

  public boolean hasAttr(java.lang.String);
    descriptor: (Ljava/lang/String;)Z
    flags: (0x1041) ACC_PUBLIC, ACC_BRIDGE, ACC_SYNTHETIC
    Code:
      stack=2, locals=2, args_size=2
         0: aload_0
         1: aload_1
         2: invokespecial #166                // Method coursier/util/shaded/org/jsoup/nodes/LeafNode.hasAttr:(Ljava/lang/String;)Z
         5: ireturn
      LineNumberTable:
        line 12: 0
      LocalVariableTable:
        Start  Length  Slot  Name   Signature
            0       6     0  this   Lcoursier/util/shaded/org/jsoup/nodes/XmlDeclaration;

  public coursier.util.shaded.org.jsoup.nodes.Node attr(java.lang.String, java.lang.String);
    descriptor: (Ljava/lang/String;Ljava/lang/String;)Lcoursier/util/shaded/org/jsoup/nodes/Node;
    flags: (0x1041) ACC_PUBLIC, ACC_BRIDGE, ACC_SYNTHETIC
    Code:
      stack=3, locals=3, args_size=3
         0: aload_0
         1: aload_1
         2: aload_2
         3: invokespecial #170                // Method coursier/util/shaded/org/jsoup/nodes/LeafNode.attr:(Ljava/lang/String;Ljava/lang/String;)Lcoursier/util/shaded/org/jsoup/nodes/Node;
         6: areturn
      LineNumberTable:
        line 12: 0
      LocalVariableTable:
        Start  Length  Slot  Name   Signature
            0       7     0  this   Lcoursier/util/shaded/org/jsoup/nodes/XmlDeclaration;

  public java.lang.String attr(java.lang.String);
    descriptor: (Ljava/lang/String;)Ljava/lang/String;
    flags: (0x1041) ACC_PUBLIC, ACC_BRIDGE, ACC_SYNTHETIC
    Code:
      stack=2, locals=2, args_size=2
         0: aload_0
         1: aload_1
         2: invokespecial #172                // Method coursier/util/shaded/org/jsoup/nodes/LeafNode.attr:(Ljava/lang/String;)Ljava/lang/String;
         5: areturn
      LineNumberTable:
        line 12: 0
      LocalVariableTable:
        Start  Length  Slot  Name   Signature
            0       6     0  this   Lcoursier/util/shaded/org/jsoup/nodes/XmlDeclaration;

  public coursier.util.shaded.org.jsoup.nodes.Node clone();
    descriptor: ()Lcoursier/util/shaded/org/jsoup/nodes/Node;
    flags: (0x1041) ACC_PUBLIC, ACC_BRIDGE, ACC_SYNTHETIC
    Code:
      stack=1, locals=1, args_size=1
         0: aload_0
         1: invokevirtual #174                // Method clone:()Lcoursier/util/shaded/org/jsoup/nodes/XmlDeclaration;
         4: areturn
      LineNumberTable:
        line 12: 0
      LocalVariableTable:
        Start  Length  Slot  Name   Signature
            0       5     0  this   Lcoursier/util/shaded/org/jsoup/nodes/XmlDeclaration;

  public java.lang.Object clone() throws java.lang.CloneNotSupportedException;
    descriptor: ()Ljava/lang/Object;
    flags: (0x1041) ACC_PUBLIC, ACC_BRIDGE, ACC_SYNTHETIC
    Code:
      stack=1, locals=1, args_size=1
         0: aload_0
         1: invokevirtual #174                // Method clone:()Lcoursier/util/shaded/org/jsoup/nodes/XmlDeclaration;
         4: areturn
      LineNumberTable:
        line 12: 0
      LocalVariableTable:
        Start  Length  Slot  Name   Signature
            0       5     0  this   Lcoursier/util/shaded/org/jsoup/nodes/XmlDeclaration;
    Exceptions:
      throws java.lang.CloneNotSupportedException
}
InnerClasses:
  public static #10= #7 of #9;            // OutputSettings=class coursier/util/shaded/org/jsoup/nodes/Document$OutputSettings of class coursier/util/shaded/org/jsoup/nodes/Document
SourceFile: "XmlDeclaration.java"
