Classfile /Users/mw/Projects/slang-braindump/.jar/jar11/assemble/slang-braindump/assemble/content/org/scalatest/events/Event.class
  Last modified May 29, 2022; size 10000 bytes
  SHA-256 checksum 818c6204892caec41ce79ddb906955efcc65c43a860c79baf8c55cd8ef9765cf
  Compiled from "Event.scala"
public abstract class org.scalatest.events.Event extends java.lang.Object implements scala.math.Ordered<org.scalatest.events.Event>, scala.Product, java.io.Serializable
  minor version: 0
  major version: 52
  flags: (0x0421) ACC_PUBLIC, ACC_SUPER, ACC_ABSTRACT
  this_class: #2                          // org/scalatest/events/Event
  super_class: #5                         // java/lang/Object
  interfaces: 3, fields: 2, methods: 30, attributes: 6
Constant pool:
    #1 = Utf8               org/scalatest/events/Event
    #2 = Class              #1            // org/scalatest/events/Event
    #3 = Utf8               Ljava/lang/Object;Lscala/math/Ordered<Lorg/scalatest/events/Event;>;Lscala/Product;Ljava/io/Serializable;
    #4 = Utf8               java/lang/Object
    #5 = Class              #4            // java/lang/Object
    #6 = Utf8               scala/math/Ordered
    #7 = Class              #6            // scala/math/Ordered
    #8 = Utf8               scala/Product
    #9 = Class              #8            // scala/Product
   #10 = Utf8               java/io/Serializable
   #11 = Class              #10           // java/io/Serializable
   #12 = Utf8               Event.scala
   #13 = Utf8               Lscala/reflect/ScalaSignature;
   #14 = Utf8               bytes
   #15 = Utf8               \u0006\u0005\t%e!B\u0016-\u0003C\u0019\u0004\"\u0002(\u0001\t\u0003y\u0005b\u0002)\u0001\u0005\u00045\t!\u0015\u0005\b+\u0002\u0011\rQ\"\u0001W\u0011\u001di\u0006A1A\u0007\u0002yCqa\u0019\u0001C\u0002\u001b\u0005A\rC\u0004j\u0001\t\u0007i\u0011\u00016\t\u000fM\u0004!\u0019!D\u0001i\")\u0001\u0010\u0001C\u0001s\"1q\u0010\u0001D\u0001])D\u0001\"!\u0001\u0001\r\u0003q\u00131A\u0004\t\u0003#\u0001\u0001\u0012\u0001\u0017\u0002\u0014\u0019A\u0011q\u0003\u0001\t\u00021\nI\u0002\u0003\u0004O\u0019\u0011\u0005\u00111\u0004\u0005\b\u0003;aA\u0011AA\u0010\u0011\u001d\t9\u0003\u0004C\u0001\u0003SAq!!\u0010\r\t\u0003\ty\u0004C\u0004\u0002L1!\t!!\u0014\t\u000f\u0005\u001dD\u0002\"\u0001\u0002j!9\u0011\u0011\u000f\u0007\u0005\u0002\u0005M\u0004bBA=\u0019\u0011\u0005\u00111\u0010\u0005\b\u0003\u000fcA\u0011AAE\u0011\u001d\t\u0019\n\u0004C\u0001\u0003+Cq!!*\r\t\u0003\t9k\u0002\u0005\u00028\u0002A\t\u0001LA]\r!\tY\f\u0001E\u0001Y\u0005u\u0006B\u0002(\u001a\t\u0003\ty\fC\u0004\u0002ze!\t!!1\t\u000f\u0005\u0015\u0017\u0004\"\u0001\u0002H\"9\u0011QD\r\u0005\u0002\u00055\u0007bBA&3\u0011\u0005\u00111\u001b\u0005\b\u0003OJB\u0011AAl\u0011\u001d\tY.\u0007C\u0001\u0003;Dq!a\"\u001a\t\u0003\tI\u000fC\u0004\u0002\u0014f!\t!!<\t\u000f\u0005E\u0018\u0004\"\u0001\u0002t\"9\u0011QU\r\u0005\u0002\u0005e\b\u0002CA\u007f\u0001\u0019\u0005A&a@\t\u0011\t\u0015\u0001\u0001\"\u0001-\u0005\u000fA\u0001B!\u0004\u0001\t\u0003a#q\u0002\u0005\b\u0005+\u0001A\u0011\u0001\u0018P\u0011!\u00119\u0002\u0001C\u0001]\te\u0001\u0002\u0003B\u000f\u0001\u0011\u0005aFa\b\u0003\u000b\u00153XM\u001c;\u000b\u00055r\u0013AB3wK:$8O\u0003\u00020a\u0005I1oY1mCR,7\u000f\u001e\u0006\u0002c\u0005\u0019qN]4\u0004\u0001M)\u0001\u0001\u000e\u001eI\u0017B\u0011Q\u0007O\u0007\u0002m)\tq\'A\u0003tG\u0006d\u0017-\u0003\u0002:m\t1\u0011I\\=SK\u001a\u00042aO\"G\u001d\ta\u0014I\u0004\u0002>\u00016\taH\u0003\u0002@e\u00051AH]8pizJ\u0011aN\u0005\u0003\u0005Z\nq\u0001]1dW\u0006<W-\u0003\u0002E\u000b\n9qJ\u001d3fe\u0016$\'B\u0001\"7!\t9\u0005!D\u0001-!\t)\u0014*\u0003\u0002Km\t9\u0001K]8ek\u000e$\bCA\u001eM\u0013\tiUI\u0001\u0007TKJL\u0017\r\\5{C\ndW-\u0001\u0004=S:LGO\u0010\u000b\u0002\r\u00069qN\u001d3j]\u0006dW#\u0001*\u0011\u0005\u001d\u001b\u0016B\u0001+-\u0005\u001dy%\u000fZ5oC2\f\u0011BZ8s[\u0006$H/\u001a:\u0016\u0003]\u00032!\u000e-[\u0013\tIfG\u0001\u0004PaRLwN\u001c\t\u0003\u000fnK!\u0001\u0018\u0017\u0003\u0013\u0019{\'/\\1ui\u0016\u0014\u0018\u0001\u00037pG\u0006$\u0018n\u001c8\u0016\u0003}\u00032!\u000e-a!\t9\u0015-\u0003\u0002cY\tAAj\\2bi&|g.A\u0004qCfdw.\u00193\u0016\u0003\u0015\u00042!\u000e-g!\t)t-\u0003\u0002im\t\u0019\u0011I\\=\u0002\u0015QD\'/Z1e\u001d\u0006lW-F\u0001l!\ta\u0007O\u0004\u0002n]B\u0011QHN\u0005\u0003_Z\na\u0001\u0015:fI\u00164\u0017BA9s\u0005\u0019\u0019FO]5oO*\u0011qNN\u0001\ni&lWm\u0015;b[B,\u0012!\u001e\t\u0003kYL!a\u001e\u001c\u0003\t1{gnZ\u0001\bG>l\u0007/\u0019:f)\tQX\u0010\u0005\u00026w&\u0011AP\u000e\u0002\u0004\u0013:$\b\"\u0002@\t\u0001\u00041\u0015\u0001\u0002;iCR\fa\u0001^8Kg>t\u0017!\u0002;p16dWCAA\u0003!\u0011\t9!!\u0004\u000e\u0005\u0005%!bAA\u0006m\u0005\u0019\u00010\u001c7\n\t\u0005=\u0011\u0011\u0002\u0002\u0005\u000b2,W.\u0001\bFm\u0016tG\u000fW7m\u0011\u0016d\u0007/\u001a:\u0011\u0007\u0005UA\"D\u0001\u0001\u00059)e/\u001a8u16d\u0007*\u001a7qKJ\u001c\"\u0001\u0004\u001b\u0015\u0005\u0005M\u0011\u0001D:ue&twm\u00149uS>tGcA6\u0002\"!9\u00111\u0005\bA\u0002\u0005\u0015\u0012!C:ue>\u0003H/[8o!\r)\u0004l[\u0001\u000bY>twm\u00149uS>tG\u0003BA\u0016\u0003s\u0001B!!\f\u000285\u0011\u0011q\u0006\u0006\u0005\u0003c\t\u0019$\u0001\u0003mC:<\'BAA\u001b\u0003\u0011Q\u0017M^1\n\u0007E\fy\u0003C\u0004\u0002(=\u0001\r!a\u000f\u0011\u0007UBV/A\u0007c_>dW-\u00198PaRLwN\u001c\u000b\u0005\u0003W\t\t\u0005C\u0004\u0002>A\u0001\r!a\u0011\u0011\tUB\u0016Q\t\t\u0004k\u0005\u001d\u0013bAA%m\t9!i\\8mK\u0006t\u0017a\u00044pe6\fG\u000f^3s\u001fB$\u0018n\u001c8\u0015\t\u0005=\u0013Q\r\n\u0007\u0003#\n)&a\u0017\u0007\r\u0005M\u0003\u0001AA(\u00051a$/\u001a4j]\u0016lWM\u001c;?!\u0011\ti#a\u0016\n\t\u0005e\u0013q\u0006\u0002\u0007\u001f\nTWm\u0019;\u0011\t\u0005u\u00131M\u0007\u0003\u0003?RA!!\u0019\u00024\u0005\u0011\u0011n\\\u0005\u0004\u001b\u0006}\u0003BBA&#\u0001\u0007q+\u0001\bm_\u000e\fG/[8o\u001fB$\u0018n\u001c8\u0015\t\u0005-\u0014q\u000e\n\u0007\u0003[\n)&a\u0017\u0007\r\u0005M\u0003\u0001AA6\u0011\u0019\t9G\u0005a\u0001?\u0006\u0011b-\u001b7f!\u0006$\bN\\1nK>\u0003H/[8o)\rY\u0017Q\u000f\u0005\b\u0003o\u001a\u0002\u0019AA\u0013\u0003=1\u0017\u000e\\3QCRDg.Y7f\u001fB$\u0018AF4fiRC\'o\\<bE2,7\u000b^1dW\u0012+\u0007\u000f\u001e5\u0015\u0007i\fi\bC\u0004\u0002\u0000Q\u0001\r!!!\u0002\u0013QD\'o\\<bE2,\u0007cA\u001e\u0002\u0004&\u0019\u0011QQ#\u0003\u0013QC\'o\\<bE2,\u0017a\u0004;ie><\u0018M\u00197f\u001fB$\u0018n\u001c8\u0015\t\u0005-\u0015q\u0012\n\u0007\u0003\u001b\u000b)&a\u0017\u0007\r\u0005M\u0003\u0001AAF\u0011\u001d\t9)\u0006a\u0001\u0003#\u0003B!\u000e-\u0002\u0002\u0006i1/^7nCJLx\n\u001d;j_:$B!a&\u0002\u001cJ1\u0011\u0011TA+\u000372a!a\u0015\u0001\u0001\u0005]\u0005bBAJ-\u0001\u0007\u0011Q\u0014\t\u0005ka\u000by\nE\u0002H\u0003CK1!a)-\u0005\u001d\u0019V/\\7bef\faB\\1nK&sgm\\(qi&|g\u000e\u0006\u0003\u0002*\u00065&CBAV\u0003+\nYF\u0002\u0004\u0002T\u0001\u0001\u0011\u0011\u0016\u0005\b\u0003K;\u0002\u0019AAX!\u0011)\u0004,!-\u0011\u0007\u001d\u000b\u0019,C\u0002\u000262\u0012\u0001BT1nK&sgm\\\u0001\u0010\u000bZ,g\u000e\u001e&t_:DU\r\u001c9feB\u0019\u0011QC\r\u0003\u001f\u00153XM\u001c;Kg>t\u0007*\u001a7qKJ\u001c\"!\u0007\u001b\u0015\u0005\u0005eFc\u0001>\u0002D\"9\u0011qP\u000eA\u0002\u0005\u0005\u0015AB:ue&tw\rF\u0002l\u0003\u0013Da!a3\u001d\u0001\u0004Y\u0017!\u0002<bYV,GcA6\u0002P\"9\u0011\u0011[\u000fA\u0002\u0005\u0015\u0012\u0001\u0003<bYV,w\n\u001d;\u0015\u0007-\f)\u000e\u0003\u0004\u0002Ly\u0001\ra\u0016\u000b\u0004W\u0006e\u0007BBA4?\u0001\u0007q,\u0001\u0006ti\u0006\u001c7\u000e\u0016:bG\u0016$2a[Ap\u0011\u001d\t\t\u000f\ta\u0001\u0003G\f!a\u001d;\u0011\t\u00055\u0012Q]\u0005\u0005\u0003O\fyCA\tTi\u0006\u001c7\u000e\u0016:bG\u0016,E.Z7f]R$2a[Av\u0011\u001d\t9)\ta\u0001\u0003##2a[Ax\u0011\u001d\t\u0019J\ta\u0001\u0003;\u000baA\\7J]\u001a|GcA6\u0002v\"9\u0011q_\u0012A\u0002\u0005E\u0016\u0001\u00038b[\u0016LeNZ8\u0015\u0007-\fY\u0010C\u0004\u0002&\u0012\u0002\r!a,\u0002\u0017]LG\u000f\u001b)bs2|\u0017\r\u001a\u000b\u0004\r\n\u0005\u0001B\u0002B\u0002K\u0001\u0007Q-\u0001\u0006oK^\u0004\u0016-\u001f7pC\u0012\fQb^5uQRC\'o\\<bE2,Gc\u0001$\u0003\n!9!1\u0002\u0014A\u0002\u0005E\u0015\u0001\u00048foRC\'o\\<bE2,\u0017AE:fe&\fG.\u001b>f%>,h\u000e\u001a;sSB$B!!\u0012\u0003\u0012!1!1C\u0014A\u0002\u0019\f\u0011!Y\u0001\u0013K:\u001cXO]3TKJL\u0017\r\\5{C\ndW-A\rf]N,(/\u001a)bs2|\u0017\rZ*fe&\fG.\u001b>bE2,Gc\u0001$\u0003\u001c!)1-\u000ba\u0001K\u0006YRM\\:ve\u0016$\u0006N]8xC\ndWmU3sS\u0006d\u0017N_1cY\u0016$2A\u0012B\u0011\u0011\u001d\tyH\u000ba\u0001\u0003#K3\u0007\u0001B\u0013\u0005S\u0011iC!\r\u00036\te\"Q\bB!\u0005\u000b\u0012IE!\u0014\u0003R\tU#\u0011\fB/\u0005C\u0012)G!\u001b\u0003n\tE$Q\u000fB=\u0005{\u0012\tI!\"\n\u0007\t\u001dBFA\u0007BY\u0016\u0014H\u000f\u0015:pm&$W\rZ\u0005\u0004\u0005Wa#A\u0005#jg\u000e|g/\u001a:z\u0007>l\u0007\u000f\\3uK\u0012L1Aa\f-\u0005E!\u0015n]2pm\u0016\u0014\u0018p\u0015;beRLgnZ\u0005\u0004\u0005ga#\u0001E#yG\u0016\u0004H/[8oC2,e/\u001a8u\u0013\r\u00119\u0004\f\u0002\r\u0013:4w\u000e\u0015:pm&$W\rZ\u0005\u0004\u0005wa#AD\'be.,\b\u000f\u0015:pm&$W\rZ\u0005\u0004\u0005\u007fa#\u0001\u0004(pi\u0016\u0004&o\u001c<jI\u0016$\u0017b\u0001B\"Y\t\tbj\u001c;jM&\u001c\u0017\r^5p]\u00163XM\u001c;\n\u0007\t\u001dCFA\bSK\u000e|\'\u000fZ1cY\u0016,e/\u001a8u\u0013\r\u0011Y\u0005\f\u0002\u000b%Vt\u0017IY8si\u0016$\u0017b\u0001B(Y\ta!+\u001e8D_6\u0004H.\u001a;fI&\u0019!1\u000b\u0017\u0003\u0017I+hn\u0015;beRLgnZ\u0005\u0004\u0005/b#A\u0003*v]N#x\u000e\u001d9fI&\u0019!1\f\u0017\u0003\u0017M\u001bw\u000e]3DY>\u001cX\rZ\u0005\u0004\u0005?b#aC*d_B,w\n]3oK\u0012L1Aa\u0019-\u00051\u00196m\u001c9f!\u0016tG-\u001b8h\u0013\r\u00119\u0007\f\u0002\r\'VLG/Z!c_J$X\rZ\u0005\u0004\u0005Wb#AD*vSR,7i\\7qY\u0016$X\rZ\u0005\u0004\u0005_b#!D*vSR,7\u000b^1si&tw-C\u0002\u0003t1\u0012A\u0002V3ti\u000e\u000bgnY3mK\u0012L1Aa\u001e-\u0005)!Vm\u001d;GC&dW\rZ\u0005\u0004\u0005wb#a\u0003+fgRLuM\\8sK\u0012L1Aa -\u0005-!Vm\u001d;QK:$\u0017N\\4\n\u0007\t\rEF\u0001\u0007UKN$8\u000b^1si&tw-C\u0002\u0003\b2\u0012Q\u0002V3tiN+8mY3fI\u0016$\u0007
   #16 = Utf8               org/scalatest/events/Event$EventJsonHelper$
   #17 = Class              #16           // org/scalatest/events/Event$EventJsonHelper$
   #18 = Utf8               EventJsonHelper$
   #19 = Utf8               org/scalatest/events/Event$EventXmlHelper$
   #20 = Class              #19           // org/scalatest/events/Event$EventXmlHelper$
   #21 = Utf8               EventXmlHelper$
   #22 = Utf8               EventXmlHelper$module
   #23 = Utf8               Lorg/scalatest/events/Event$EventXmlHelper$;
   #24 = Utf8               EventJsonHelper$module
   #25 = Utf8               Lorg/scalatest/events/Event$EventJsonHelper$;
   #26 = Utf8               productIterator
   #27 = Utf8               ()Lscala/collection/Iterator;
   #28 = Utf8               ()Lscala/collection/Iterator<Ljava/lang/Object;>;
   #29 = Utf8               productIterator$
   #30 = Utf8               (Lscala/Product;)Lscala/collection/Iterator;
   #31 = NameAndType        #29:#30       // productIterator$:(Lscala/Product;)Lscala/collection/Iterator;
   #32 = InterfaceMethodref #9.#31        // scala/Product.productIterator$:(Lscala/Product;)Lscala/collection/Iterator;
   #33 = Utf8               this
   #34 = Utf8               Lorg/scalatest/events/Event;
   #35 = Utf8               productPrefix
   #36 = Utf8               ()Ljava/lang/String;
   #37 = Utf8               productPrefix$
   #38 = Utf8               (Lscala/Product;)Ljava/lang/String;
   #39 = NameAndType        #37:#38       // productPrefix$:(Lscala/Product;)Ljava/lang/String;
   #40 = InterfaceMethodref #9.#39        // scala/Product.productPrefix$:(Lscala/Product;)Ljava/lang/String;
   #41 = Utf8               productElementName
   #42 = Utf8               (I)Ljava/lang/String;
   #43 = Utf8               n
   #44 = Utf8               productElementName$
   #45 = Utf8               (Lscala/Product;I)Ljava/lang/String;
   #46 = NameAndType        #44:#45       // productElementName$:(Lscala/Product;I)Ljava/lang/String;
   #47 = InterfaceMethodref #9.#46        // scala/Product.productElementName$:(Lscala/Product;I)Ljava/lang/String;
   #48 = Utf8               I
   #49 = Utf8               productElementNames
   #50 = Utf8               ()Lscala/collection/Iterator<Ljava/lang/String;>;
   #51 = Utf8               productElementNames$
   #52 = NameAndType        #51:#30       // productElementNames$:(Lscala/Product;)Lscala/collection/Iterator;
   #53 = InterfaceMethodref #9.#52        // scala/Product.productElementNames$:(Lscala/Product;)Lscala/collection/Iterator;
   #54 = Utf8               $less
   #55 = Utf8               (Ljava/lang/Object;)Z
   #56 = Utf8               that
   #57 = Utf8               $less$
   #58 = Utf8               (Lscala/math/Ordered;Ljava/lang/Object;)Z
   #59 = NameAndType        #57:#58       // $less$:(Lscala/math/Ordered;Ljava/lang/Object;)Z
   #60 = InterfaceMethodref #7.#59        // scala/math/Ordered.$less$:(Lscala/math/Ordered;Ljava/lang/Object;)Z
   #61 = Utf8               Ljava/lang/Object;
   #62 = Utf8               $greater
   #63 = Utf8               $greater$
   #64 = NameAndType        #63:#58       // $greater$:(Lscala/math/Ordered;Ljava/lang/Object;)Z
   #65 = InterfaceMethodref #7.#64        // scala/math/Ordered.$greater$:(Lscala/math/Ordered;Ljava/lang/Object;)Z
   #66 = Utf8               $less$eq
   #67 = Utf8               $less$eq$
   #68 = NameAndType        #67:#58       // $less$eq$:(Lscala/math/Ordered;Ljava/lang/Object;)Z
   #69 = InterfaceMethodref #7.#68        // scala/math/Ordered.$less$eq$:(Lscala/math/Ordered;Ljava/lang/Object;)Z
   #70 = Utf8               $greater$eq
   #71 = Utf8               $greater$eq$
   #72 = NameAndType        #71:#58       // $greater$eq$:(Lscala/math/Ordered;Ljava/lang/Object;)Z
   #73 = InterfaceMethodref #7.#72        // scala/math/Ordered.$greater$eq$:(Lscala/math/Ordered;Ljava/lang/Object;)Z
   #74 = Utf8               compareTo
   #75 = Utf8               (Ljava/lang/Object;)I
   #76 = Utf8               compareTo$
   #77 = Utf8               (Lscala/math/Ordered;Ljava/lang/Object;)I
   #78 = NameAndType        #76:#77       // compareTo$:(Lscala/math/Ordered;Ljava/lang/Object;)I
   #79 = InterfaceMethodref #7.#78        // scala/math/Ordered.compareTo$:(Lscala/math/Ordered;Ljava/lang/Object;)I
   #80 = Utf8               EventXmlHelper
   #81 = Utf8               ()Lorg/scalatest/events/Event$EventXmlHelper$;
   #82 = NameAndType        #22:#23       // EventXmlHelper$module:Lorg/scalatest/events/Event$EventXmlHelper$;
   #83 = Fieldref           #2.#82        // org/scalatest/events/Event.EventXmlHelper$module:Lorg/scalatest/events/Event$EventXmlHelper$;
   #84 = Utf8               EventXmlHelper$lzycompute$1
   #85 = Utf8               ()V
   #86 = NameAndType        #84:#85       // EventXmlHelper$lzycompute$1:()V
   #87 = Methodref          #2.#86        // org/scalatest/events/Event.EventXmlHelper$lzycompute$1:()V
   #88 = Utf8               EventJsonHelper
   #89 = Utf8               ()Lorg/scalatest/events/Event$EventJsonHelper$;
   #90 = NameAndType        #24:#25       // EventJsonHelper$module:Lorg/scalatest/events/Event$EventJsonHelper$;
   #91 = Fieldref           #2.#90        // org/scalatest/events/Event.EventJsonHelper$module:Lorg/scalatest/events/Event$EventJsonHelper$;
   #92 = Utf8               EventJsonHelper$lzycompute$1
   #93 = NameAndType        #92:#85       // EventJsonHelper$lzycompute$1:()V
   #94 = Methodref          #2.#93        // org/scalatest/events/Event.EventJsonHelper$lzycompute$1:()V
   #95 = Utf8               ordinal
   #96 = Utf8               ()Lorg/scalatest/events/Ordinal;
   #97 = Utf8               formatter
   #98 = Utf8               ()Lscala/Option;
   #99 = Utf8               ()Lscala/Option<Lorg/scalatest/events/Formatter;>;
  #100 = Utf8               location
  #101 = Utf8               ()Lscala/Option<Lorg/scalatest/events/Location;>;
  #102 = Utf8               payload
  #103 = Utf8               ()Lscala/Option<Ljava/lang/Object;>;
  #104 = Utf8               threadName
  #105 = Utf8               timeStamp
  #106 = Utf8               ()J
  #107 = Utf8               compare
  #108 = Utf8               (Lorg/scalatest/events/Event;)I
  #109 = NameAndType        #95:#96       // ordinal:()Lorg/scalatest/events/Ordinal;
  #110 = Methodref          #2.#109       // org/scalatest/events/Event.ordinal:()Lorg/scalatest/events/Ordinal;
  #111 = Utf8               org/scalatest/events/Ordinal
  #112 = Class              #111          // org/scalatest/events/Ordinal
  #113 = Utf8               (Lorg/scalatest/events/Ordinal;)I
  #114 = NameAndType        #107:#113     // compare:(Lorg/scalatest/events/Ordinal;)I
  #115 = Methodref          #112.#114     // org/scalatest/events/Ordinal.compare:(Lorg/scalatest/events/Ordinal;)I
  #116 = Utf8               toJson
  #117 = Utf8               toXml
  #118 = Utf8               ()Lscala/xml/Elem;
  #119 = Utf8               withPayload
  #120 = Utf8               (Lscala/Option;)Lorg/scalatest/events/Event;
  #121 = Utf8               (Lscala/Option<Ljava/lang/Object;>;)Lorg/scalatest/events/Event;
  #122 = Utf8               newPayload
  #123 = Utf8               withThrowable
  #124 = Utf8               (Lscala/Option<Ljava/lang/Throwable;>;)Lorg/scalatest/events/Event;
  #125 = Utf8               newThrowable
  #126 = Utf8               Lscala/Option;
  #127 = Utf8               serializeRoundtrip
  #128 = Utf8               a
  #129 = Utf8               java/io/NotSerializableException
  #130 = Class              #129          // java/io/NotSerializableException
  #131 = Utf8               java/io/ByteArrayOutputStream
  #132 = Class              #131          // java/io/ByteArrayOutputStream
  #133 = Utf8               <init>
  #134 = NameAndType        #133:#85      // "<init>":()V
  #135 = Methodref          #132.#134     // java/io/ByteArrayOutputStream."<init>":()V
  #136 = Utf8               java/io/ObjectOutputStream
  #137 = Class              #136          // java/io/ObjectOutputStream
  #138 = Utf8               (Ljava/io/OutputStream;)V
  #139 = NameAndType        #133:#138     // "<init>":(Ljava/io/OutputStream;)V
  #140 = Methodref          #137.#139     // java/io/ObjectOutputStream."<init>":(Ljava/io/OutputStream;)V
  #141 = Utf8               writeObject
  #142 = Utf8               (Ljava/lang/Object;)V
  #143 = NameAndType        #141:#142     // writeObject:(Ljava/lang/Object;)V
  #144 = Methodref          #137.#143     // java/io/ObjectOutputStream.writeObject:(Ljava/lang/Object;)V
  #145 = Utf8               flush
  #146 = NameAndType        #145:#85      // flush:()V
  #147 = Methodref          #137.#146     // java/io/ObjectOutputStream.flush:()V
  #148 = Utf8               java/io/ObjectInputStream
  #149 = Class              #148          // java/io/ObjectInputStream
  #150 = Utf8               java/io/ByteArrayInputStream
  #151 = Class              #150          // java/io/ByteArrayInputStream
  #152 = Utf8               toByteArray
  #153 = Utf8               ()[B
  #154 = NameAndType        #152:#153     // toByteArray:()[B
  #155 = Methodref          #132.#154     // java/io/ByteArrayOutputStream.toByteArray:()[B
  #156 = Utf8               ([B)V
  #157 = NameAndType        #133:#156     // "<init>":([B)V
  #158 = Methodref          #151.#157     // java/io/ByteArrayInputStream."<init>":([B)V
  #159 = Utf8               (Ljava/io/InputStream;)V
  #160 = NameAndType        #133:#159     // "<init>":(Ljava/io/InputStream;)V
  #161 = Methodref          #149.#160     // java/io/ObjectInputStream."<init>":(Ljava/io/InputStream;)V
  #162 = Utf8               readObject
  #163 = Utf8               ()Ljava/lang/Object;
  #164 = NameAndType        #162:#163     // readObject:()Ljava/lang/Object;
  #165 = Methodref          #149.#164     // java/io/ObjectInputStream.readObject:()Ljava/lang/Object;
  #166 = Utf8               baos
  #167 = Utf8               Ljava/io/ByteArrayOutputStream;
  #168 = Utf8               oos
  #169 = Utf8               Ljava/io/ObjectOutputStream;
  #170 = Utf8               ois
  #171 = Utf8               Ljava/io/ObjectInputStream;
  #172 = Utf8               ensureSerializable
  #173 = Utf8               ()Lorg/scalatest/events/Event;
  #174 = NameAndType        #102:#98      // payload:()Lscala/Option;
  #175 = Methodref          #2.#174       // org/scalatest/events/Event.payload:()Lscala/Option;
  #176 = Utf8               ensurePayloadSerializable
  #177 = NameAndType        #176:#120     // ensurePayloadSerializable:(Lscala/Option;)Lorg/scalatest/events/Event;
  #178 = Methodref          #2.#177       // org/scalatest/events/Event.ensurePayloadSerializable:(Lscala/Option;)Lorg/scalatest/events/Event;
  #179 = Utf8               scala/Some
  #180 = Class              #179          // scala/Some
  #181 = Utf8               value
  #182 = NameAndType        #181:#163     // value:()Ljava/lang/Object;
  #183 = Methodref          #180.#182     // scala/Some.value:()Ljava/lang/Object;
  #184 = NameAndType        #127:#55      // serializeRoundtrip:(Ljava/lang/Object;)Z
  #185 = Methodref          #2.#184       // org/scalatest/events/Event.serializeRoundtrip:(Ljava/lang/Object;)Z
  #186 = Utf8               scala/Predef$
  #187 = Class              #186          // scala/Predef$
  #188 = Utf8               MODULE$
  #189 = Utf8               Lscala/Predef$;
  #190 = NameAndType        #188:#189     // MODULE$:Lscala/Predef$;
  #191 = Fieldref           #187.#190     // scala/Predef$.MODULE$:Lscala/Predef$;
  #192 = Utf8               org/scalatest/Resources$
  #193 = Class              #192          // org/scalatest/Resources$
  #194 = Utf8               Lorg/scalatest/Resources$;
  #195 = NameAndType        #188:#194     // MODULE$:Lorg/scalatest/Resources$;
  #196 = Fieldref           #193.#195     // org/scalatest/Resources$.MODULE$:Lorg/scalatest/Resources$;
  #197 = Utf8               getClass
  #198 = Utf8               ()Ljava/lang/Class;
  #199 = NameAndType        #197:#198     // getClass:()Ljava/lang/Class;
  #200 = Methodref          #5.#199       // java/lang/Object.getClass:()Ljava/lang/Class;
  #201 = Utf8               java/lang/Class
  #202 = Class              #201          // java/lang/Class
  #203 = Utf8               getName
  #204 = NameAndType        #203:#36      // getName:()Ljava/lang/String;
  #205 = Methodref          #202.#204     // java/lang/Class.getName:()Ljava/lang/String;
  #206 = Utf8               toString
  #207 = NameAndType        #206:#36      // toString:()Ljava/lang/String;
  #208 = Methodref          #2.#207       // org/scalatest/events/Event.toString:()Ljava/lang/String;
  #209 = Utf8               unableToSerializePayload
  #210 = Utf8               (Ljava/lang/Object;Ljava/lang/Object;)Ljava/lang/String;
  #211 = NameAndType        #209:#210     // unableToSerializePayload:(Ljava/lang/Object;Ljava/lang/Object;)Ljava/lang/String;
  #212 = Methodref          #193.#211     // org/scalatest/Resources$.unableToSerializePayload:(Ljava/lang/Object;Ljava/lang/Object;)Ljava/lang/String;
  #213 = Utf8               println
  #214 = NameAndType        #213:#142     // println:(Ljava/lang/Object;)V
  #215 = Methodref          #187.#214     // scala/Predef$.println:(Ljava/lang/Object;)V
  #216 = Utf8               scala/None$
  #217 = Class              #216          // scala/None$
  #218 = Utf8               Lscala/None$;
  #219 = NameAndType        #188:#218     // MODULE$:Lscala/None$;
  #220 = Fieldref           #217.#219     // scala/None$.MODULE$:Lscala/None$;
  #221 = NameAndType        #119:#120     // withPayload:(Lscala/Option;)Lorg/scalatest/events/Event;
  #222 = Methodref          #2.#221       // org/scalatest/events/Event.withPayload:(Lscala/Option;)Lorg/scalatest/events/Event;
  #223 = Utf8               p
  #224 = Utf8               scala/Option
  #225 = Class              #224          // scala/Option
  #226 = Utf8               ensureThrowableSerializable
  #227 = Utf8               throwable
  #228 = Utf8               java/lang/Throwable
  #229 = Class              #228          // java/lang/Throwable
  #230 = Methodref          #229.#199     // java/lang/Throwable.getClass:()Ljava/lang/Class;
  #231 = Utf8               unableToSerializeThrowable
  #232 = NameAndType        #231:#210     // unableToSerializeThrowable:(Ljava/lang/Object;Ljava/lang/Object;)Ljava/lang/String;
  #233 = Methodref          #193.#232     // org/scalatest/Resources$.unableToSerializeThrowable:(Ljava/lang/Object;Ljava/lang/Object;)Ljava/lang/String;
  #234 = Utf8               org/scalatest/exceptions/NotSerializableWrapperException
  #235 = Class              #234          // org/scalatest/exceptions/NotSerializableWrapperException
  #236 = Utf8               getMessage
  #237 = NameAndType        #236:#36      // getMessage:()Ljava/lang/String;
  #238 = Methodref          #229.#237     // java/lang/Throwable.getMessage:()Ljava/lang/String;
  #239 = Utf8               getStackTrace
  #240 = Utf8               ()[Ljava/lang/StackTraceElement;
  #241 = NameAndType        #239:#240     // getStackTrace:()[Ljava/lang/StackTraceElement;
  #242 = Methodref          #229.#241     // java/lang/Throwable.getStackTrace:()[Ljava/lang/StackTraceElement;
  #243 = Utf8               (Ljava/lang/String;Ljava/lang/String;[Ljava/lang/StackTraceElement;)V
  #244 = NameAndType        #133:#243     // "<init>":(Ljava/lang/String;Ljava/lang/String;[Ljava/lang/StackTraceElement;)V
  #245 = Methodref          #235.#244     // org/scalatest/exceptions/NotSerializableWrapperException."<init>":(Ljava/lang/String;Ljava/lang/String;[Ljava/lang/StackTraceElement;)V
  #246 = NameAndType        #133:#142     // "<init>":(Ljava/lang/Object;)V
  #247 = Methodref          #180.#246     // scala/Some."<init>":(Ljava/lang/Object;)V
  #248 = NameAndType        #123:#120     // withThrowable:(Lscala/Option;)Lorg/scalatest/events/Event;
  #249 = Methodref          #2.#248       // org/scalatest/events/Event.withThrowable:(Lscala/Option;)Lorg/scalatest/events/Event;
  #250 = Utf8               className
  #251 = Utf8               Ljava/lang/String;
  #252 = Utf8               ex
  #253 = Utf8               Lorg/scalatest/exceptions/NotSerializableWrapperException;
  #254 = Utf8               t
  #255 = Utf8               Ljava/lang/Throwable;
  #256 = NameAndType        #107:#108     // compare:(Lorg/scalatest/events/Event;)I
  #257 = Methodref          #2.#256       // org/scalatest/events/Event.compare:(Lorg/scalatest/events/Event;)I
  #258 = Utf8               (Lorg/scalatest/events/Event;)V
  #259 = NameAndType        #133:#258     // "<init>":(Lorg/scalatest/events/Event;)V
  #260 = Methodref          #20.#259      // org/scalatest/events/Event$EventXmlHelper$."<init>":(Lorg/scalatest/events/Event;)V
  #261 = Methodref          #17.#259      // org/scalatest/events/Event$EventJsonHelper$."<init>":(Lorg/scalatest/events/Event;)V
  #262 = Methodref          #5.#134       // java/lang/Object."<init>":()V
  #263 = Utf8               $init$
  #264 = Utf8               (Lscala/math/Ordered;)V
  #265 = NameAndType        #263:#264     // $init$:(Lscala/math/Ordered;)V
  #266 = InterfaceMethodref #7.#265       // scala/math/Ordered.$init$:(Lscala/math/Ordered;)V
  #267 = Utf8               (Lscala/Product;)V
  #268 = NameAndType        #263:#267     // $init$:(Lscala/Product;)V
  #269 = InterfaceMethodref #9.#268       // scala/Product.$init$:(Lscala/Product;)V
  #270 = Utf8               Code
  #271 = Utf8               LineNumberTable
  #272 = Utf8               LocalVariableTable
  #273 = Utf8               Signature
  #274 = Utf8               MethodParameters
  #275 = Utf8               StackMapTable
  #276 = Utf8               InnerClasses
  #277 = Utf8               SourceFile
  #278 = Utf8               RuntimeVisibleAnnotations
  #279 = Utf8               ScalaInlineInfo
  #280 = Utf8               ScalaSig
{
  private volatile org.scalatest.events.Event$EventXmlHelper$ EventXmlHelper$module;
    descriptor: Lorg/scalatest/events/Event$EventXmlHelper$;
    flags: (0x0042) ACC_PRIVATE, ACC_VOLATILE

  private volatile org.scalatest.events.Event$EventJsonHelper$ EventJsonHelper$module;
    descriptor: Lorg/scalatest/events/Event$EventJsonHelper$;
    flags: (0x0042) ACC_PRIVATE, ACC_VOLATILE

  public scala.collection.Iterator<java.lang.Object> productIterator();
    descriptor: ()Lscala/collection/Iterator;
    flags: (0x0001) ACC_PUBLIC
    Code:
      stack=1, locals=1, args_size=1
         0: aload_0
         1: invokestatic  #32                 // InterfaceMethod scala/Product.productIterator$:(Lscala/Product;)Lscala/collection/Iterator;
         4: areturn
      LineNumberTable:
        line 37: 0
      LocalVariableTable:
        Start  Length  Slot  Name   Signature
            0       5     0  this   Lorg/scalatest/events/Event;
    Signature: #28                          // ()Lscala/collection/Iterator<Ljava/lang/Object;>;

  public java.lang.String productPrefix();
    descriptor: ()Ljava/lang/String;
    flags: (0x0001) ACC_PUBLIC
    Code:
      stack=1, locals=1, args_size=1
         0: aload_0
         1: invokestatic  #40                 // InterfaceMethod scala/Product.productPrefix$:(Lscala/Product;)Ljava/lang/String;
         4: areturn
      LineNumberTable:
        line 37: 0
      LocalVariableTable:
        Start  Length  Slot  Name   Signature
            0       5     0  this   Lorg/scalatest/events/Event;

  public java.lang.String productElementName(int);
    descriptor: (I)Ljava/lang/String;
    flags: (0x0001) ACC_PUBLIC
    Code:
      stack=2, locals=2, args_size=2
         0: aload_0
         1: iload_1
         2: invokestatic  #47                 // InterfaceMethod scala/Product.productElementName$:(Lscala/Product;I)Ljava/lang/String;
         5: areturn
      LineNumberTable:
        line 37: 0
      LocalVariableTable:
        Start  Length  Slot  Name   Signature
            0       6     0  this   Lorg/scalatest/events/Event;
            0       6     1     n   I
    MethodParameters:
      Name                           Flags
      n                              final

  public scala.collection.Iterator<java.lang.String> productElementNames();
    descriptor: ()Lscala/collection/Iterator;
    flags: (0x0001) ACC_PUBLIC
    Code:
      stack=1, locals=1, args_size=1
         0: aload_0
         1: invokestatic  #53                 // InterfaceMethod scala/Product.productElementNames$:(Lscala/Product;)Lscala/collection/Iterator;
         4: areturn
      LineNumberTable:
        line 37: 0
      LocalVariableTable:
        Start  Length  Slot  Name   Signature
            0       5     0  this   Lorg/scalatest/events/Event;
    Signature: #50                          // ()Lscala/collection/Iterator<Ljava/lang/String;>;

  public boolean $less(java.lang.Object);
    descriptor: (Ljava/lang/Object;)Z
    flags: (0x0001) ACC_PUBLIC
    Code:
      stack=2, locals=2, args_size=2
         0: aload_0
         1: aload_1
         2: invokestatic  #60                 // InterfaceMethod scala/math/Ordered.$less$:(Lscala/math/Ordered;Ljava/lang/Object;)Z
         5: ireturn
      LineNumberTable:
        line 37: 0
      LocalVariableTable:
        Start  Length  Slot  Name   Signature
            0       6     0  this   Lorg/scalatest/events/Event;
            0       6     1  that   Ljava/lang/Object;
    MethodParameters:
      Name                           Flags
      that                           final

  public boolean $greater(java.lang.Object);
    descriptor: (Ljava/lang/Object;)Z
    flags: (0x0001) ACC_PUBLIC
    Code:
      stack=2, locals=2, args_size=2
         0: aload_0
         1: aload_1
         2: invokestatic  #65                 // InterfaceMethod scala/math/Ordered.$greater$:(Lscala/math/Ordered;Ljava/lang/Object;)Z
         5: ireturn
      LineNumberTable:
        line 37: 0
      LocalVariableTable:
        Start  Length  Slot  Name   Signature
            0       6     0  this   Lorg/scalatest/events/Event;
            0       6     1  that   Ljava/lang/Object;
    MethodParameters:
      Name                           Flags
      that                           final

  public boolean $less$eq(java.lang.Object);
    descriptor: (Ljava/lang/Object;)Z
    flags: (0x0001) ACC_PUBLIC
    Code:
      stack=2, locals=2, args_size=2
         0: aload_0
         1: aload_1
         2: invokestatic  #69                 // InterfaceMethod scala/math/Ordered.$less$eq$:(Lscala/math/Ordered;Ljava/lang/Object;)Z
         5: ireturn
      LineNumberTable:
        line 37: 0
      LocalVariableTable:
        Start  Length  Slot  Name   Signature
            0       6     0  this   Lorg/scalatest/events/Event;
            0       6     1  that   Ljava/lang/Object;
    MethodParameters:
      Name                           Flags
      that                           final

  public boolean $greater$eq(java.lang.Object);
    descriptor: (Ljava/lang/Object;)Z
    flags: (0x0001) ACC_PUBLIC
    Code:
      stack=2, locals=2, args_size=2
         0: aload_0
         1: aload_1
         2: invokestatic  #73                 // InterfaceMethod scala/math/Ordered.$greater$eq$:(Lscala/math/Ordered;Ljava/lang/Object;)Z
         5: ireturn
      LineNumberTable:
        line 37: 0
      LocalVariableTable:
        Start  Length  Slot  Name   Signature
            0       6     0  this   Lorg/scalatest/events/Event;
            0       6     1  that   Ljava/lang/Object;
    MethodParameters:
      Name                           Flags
      that                           final

  public int compareTo(java.lang.Object);
    descriptor: (Ljava/lang/Object;)I
    flags: (0x0001) ACC_PUBLIC
    Code:
      stack=2, locals=2, args_size=2
         0: aload_0
         1: aload_1
         2: invokestatic  #79                 // InterfaceMethod scala/math/Ordered.compareTo$:(Lscala/math/Ordered;Ljava/lang/Object;)I
         5: ireturn
      LineNumberTable:
        line 37: 0
      LocalVariableTable:
        Start  Length  Slot  Name   Signature
            0       6     0  this   Lorg/scalatest/events/Event;
            0       6     1  that   Ljava/lang/Object;
    MethodParameters:
      Name                           Flags
      that                           final

  public org.scalatest.events.Event$EventXmlHelper$ EventXmlHelper();
    descriptor: ()Lorg/scalatest/events/Event$EventXmlHelper$;
    flags: (0x0001) ACC_PUBLIC
    Code:
      stack=1, locals=1, args_size=1
         0: aload_0
         1: getfield      #83                 // Field EventXmlHelper$module:Lorg/scalatest/events/Event$EventXmlHelper$;
         4: ifnonnull     11
         7: aload_0
         8: invokespecial #87                 // Method EventXmlHelper$lzycompute$1:()V
        11: aload_0
        12: getfield      #83                 // Field EventXmlHelper$module:Lorg/scalatest/events/Event$EventXmlHelper$;
        15: areturn
      StackMapTable: number_of_entries = 1
        frame_type = 11 /* same */
      LineNumberTable:
        line 90: 0
      LocalVariableTable:
        Start  Length  Slot  Name   Signature
            0      16     0  this   Lorg/scalatest/events/Event;

  public org.scalatest.events.Event$EventJsonHelper$ EventJsonHelper();
    descriptor: ()Lorg/scalatest/events/Event$EventJsonHelper$;
    flags: (0x0001) ACC_PUBLIC
    Code:
      stack=1, locals=1, args_size=1
         0: aload_0
         1: getfield      #91                 // Field EventJsonHelper$module:Lorg/scalatest/events/Event$EventJsonHelper$;
         4: ifnonnull     11
         7: aload_0
         8: invokespecial #94                 // Method EventJsonHelper$lzycompute$1:()V
        11: aload_0
        12: getfield      #91                 // Field EventJsonHelper$module:Lorg/scalatest/events/Event$EventJsonHelper$;
        15: areturn
      StackMapTable: number_of_entries = 1
        frame_type = 11 /* same */
      LineNumberTable:
        line 205: 0
      LocalVariableTable:
        Start  Length  Slot  Name   Signature
            0      16     0  this   Lorg/scalatest/events/Event;

  public abstract org.scalatest.events.Ordinal ordinal();
    descriptor: ()Lorg/scalatest/events/Ordinal;
    flags: (0x0401) ACC_PUBLIC, ACC_ABSTRACT

  public abstract scala.Option<org.scalatest.events.Formatter> formatter();
    descriptor: ()Lscala/Option;
    flags: (0x0401) ACC_PUBLIC, ACC_ABSTRACT
    Signature: #99                          // ()Lscala/Option<Lorg/scalatest/events/Formatter;>;

  public abstract scala.Option<org.scalatest.events.Location> location();
    descriptor: ()Lscala/Option;
    flags: (0x0401) ACC_PUBLIC, ACC_ABSTRACT
    Signature: #101                         // ()Lscala/Option<Lorg/scalatest/events/Location;>;

  public abstract scala.Option<java.lang.Object> payload();
    descriptor: ()Lscala/Option;
    flags: (0x0401) ACC_PUBLIC, ACC_ABSTRACT
    Signature: #103                         // ()Lscala/Option<Ljava/lang/Object;>;

  public abstract java.lang.String threadName();
    descriptor: ()Ljava/lang/String;
    flags: (0x0401) ACC_PUBLIC, ACC_ABSTRACT

  public abstract long timeStamp();
    descriptor: ()J
    flags: (0x0401) ACC_PUBLIC, ACC_ABSTRACT

  public int compare(org.scalatest.events.Event);
    descriptor: (Lorg/scalatest/events/Event;)I
    flags: (0x0001) ACC_PUBLIC
    Code:
      stack=2, locals=2, args_size=2
         0: aload_0
         1: invokevirtual #110                // Method ordinal:()Lorg/scalatest/events/Ordinal;
         4: aload_1
         5: invokevirtual #110                // Method ordinal:()Lorg/scalatest/events/Ordinal;
         8: invokevirtual #115                // Method org/scalatest/events/Ordinal.compare:(Lorg/scalatest/events/Ordinal;)I
        11: ireturn
      LineNumberTable:
        line 83: 0
      LocalVariableTable:
        Start  Length  Slot  Name   Signature
            0      12     0  this   Lorg/scalatest/events/Event;
            0      12     1  that   Lorg/scalatest/events/Event;
    MethodParameters:
      Name                           Flags
      that                           final

  public abstract java.lang.String toJson();
    descriptor: ()Ljava/lang/String;
    flags: (0x0401) ACC_PUBLIC, ACC_ABSTRACT

  public abstract scala.xml.Elem toXml();
    descriptor: ()Lscala/xml/Elem;
    flags: (0x0401) ACC_PUBLIC, ACC_ABSTRACT

  public abstract org.scalatest.events.Event withPayload(scala.Option<java.lang.Object>);
    descriptor: (Lscala/Option;)Lorg/scalatest/events/Event;
    flags: (0x0401) ACC_PUBLIC, ACC_ABSTRACT
    Signature: #121                         // (Lscala/Option<Ljava/lang/Object;>;)Lorg/scalatest/events/Event;
    MethodParameters:
      Name                           Flags
      newPayload                     final

  public org.scalatest.events.Event withThrowable(scala.Option<java.lang.Throwable>);
    descriptor: (Lscala/Option;)Lorg/scalatest/events/Event;
    flags: (0x0001) ACC_PUBLIC
    Code:
      stack=1, locals=2, args_size=2
         0: aload_0
         1: areturn
      LineNumberTable:
        line 289: 0
      LocalVariableTable:
        Start  Length  Slot  Name   Signature
            0       2     0  this   Lorg/scalatest/events/Event;
            0       2     1 newThrowable   Lscala/Option;
    Signature: #124                         // (Lscala/Option<Ljava/lang/Throwable;>;)Lorg/scalatest/events/Event;
    MethodParameters:
      Name                           Flags
      newThrowable                   final

  public boolean serializeRoundtrip(java.lang.Object);
    descriptor: (Ljava/lang/Object;)Z
    flags: (0x0001) ACC_PUBLIC
    Code:
      stack=5, locals=5, args_size=2
         0: new           #132                // class java/io/ByteArrayOutputStream
         3: dup
         4: invokespecial #135                // Method java/io/ByteArrayOutputStream."<init>":()V
         7: astore_2
         8: new           #137                // class java/io/ObjectOutputStream
        11: dup
        12: aload_2
        13: invokespecial #140                // Method java/io/ObjectOutputStream."<init>":(Ljava/io/OutputStream;)V
        16: astore_3
        17: aload_3
        18: aload_1
        19: invokevirtual #144                // Method java/io/ObjectOutputStream.writeObject:(Ljava/lang/Object;)V
        22: aload_3
        23: invokevirtual #147                // Method java/io/ObjectOutputStream.flush:()V
        26: new           #149                // class java/io/ObjectInputStream
        29: dup
        30: new           #151                // class java/io/ByteArrayInputStream
        33: dup
        34: aload_2
        35: invokevirtual #155                // Method java/io/ByteArrayOutputStream.toByteArray:()[B
        38: invokespecial #158                // Method java/io/ByteArrayInputStream."<init>":([B)V
        41: invokespecial #161                // Method java/io/ObjectInputStream."<init>":(Ljava/io/InputStream;)V
        44: astore        4
        46: aload         4
        48: invokevirtual #165                // Method java/io/ObjectInputStream.readObject:()Ljava/lang/Object;
        51: pop
        52: iconst_1
        53: goto          61
        56: pop
        57: iconst_0
        58: goto          61
        61: ireturn
      Exception table:
         from    to  target type
             0    53    56   Class java/io/NotSerializableException
      StackMapTable: number_of_entries = 2
        frame_type = 120 /* same_locals_1_stack_item */
          stack = [ class java/io/NotSerializableException ]
        frame_type = 68 /* same_locals_1_stack_item */
          stack = [ int ]
      LineNumberTable:
        line 293: 0
        line 294: 8
        line 295: 17
        line 296: 22
        line 297: 26
        line 298: 46
        line 299: 52
        line 302: 57
      LocalVariableTable:
        Start  Length  Slot  Name   Signature
            8      45     2  baos   Ljava/io/ByteArrayOutputStream;
           17      36     3   oos   Ljava/io/ObjectOutputStream;
           46       7     4   ois   Ljava/io/ObjectInputStream;
            0      62     0  this   Lorg/scalatest/events/Event;
            0      62     1     a   Ljava/lang/Object;
    MethodParameters:
      Name                           Flags
      a                              final

  public org.scalatest.events.Event ensureSerializable();
    descriptor: ()Lorg/scalatest/events/Event;
    flags: (0x0001) ACC_PUBLIC
    Code:
      stack=2, locals=1, args_size=1
         0: aload_0
         1: aload_0
         2: invokevirtual #175                // Method payload:()Lscala/Option;
         5: invokevirtual #178                // Method ensurePayloadSerializable:(Lscala/Option;)Lorg/scalatest/events/Event;
         8: areturn
      LineNumberTable:
        line 306: 0
      LocalVariableTable:
        Start  Length  Slot  Name   Signature
            0       9     0  this   Lorg/scalatest/events/Event;

  public org.scalatest.events.Event ensurePayloadSerializable(scala.Option<java.lang.Object>);
    descriptor: (Lscala/Option;)Lorg/scalatest/events/Event;
    flags: (0x0001) ACC_PUBLIC
    Code:
      stack=4, locals=6, args_size=2
         0: aload_1
         1: astore_3
         2: aload_3
         3: instanceof    #180                // class scala/Some
         6: ifeq          69
         9: aload_3
        10: checkcast     #180                // class scala/Some
        13: astore        4
        15: aload         4
        17: invokevirtual #183                // Method scala/Some.value:()Ljava/lang/Object;
        20: astore        5
        22: aload_0
        23: aload         5
        25: invokevirtual #185                // Method serializeRoundtrip:(Ljava/lang/Object;)Z
        28: ifne          66
        31: getstatic     #191                // Field scala/Predef$.MODULE$:Lscala/Predef$;
        34: getstatic     #196                // Field org/scalatest/Resources$.MODULE$:Lorg/scalatest/Resources$;
        37: aload         5
        39: invokevirtual #200                // Method java/lang/Object.getClass:()Ljava/lang/Class;
        42: invokevirtual #205                // Method java/lang/Class.getName:()Ljava/lang/String;
        45: aload_0
        46: invokevirtual #208                // Method toString:()Ljava/lang/String;
        49: invokevirtual #212                // Method org/scalatest/Resources$.unableToSerializePayload:(Ljava/lang/Object;Ljava/lang/Object;)Ljava/lang/String;
        52: invokevirtual #215                // Method scala/Predef$.println:(Ljava/lang/Object;)V
        55: aload_0
        56: getstatic     #220                // Field scala/None$.MODULE$:Lscala/None$;
        59: invokevirtual #222                // Method withPayload:(Lscala/Option;)Lorg/scalatest/events/Event;
        62: astore_2
        63: goto          77
        66: goto          72
        69: goto          72
        72: aload_0
        73: astore_2
        74: goto          77
        77: aload_2
        78: areturn
      StackMapTable: number_of_entries = 4
        frame_type = 255 /* full_frame */
          offset_delta = 66
          locals = [ class org/scalatest/events/Event, class scala/Option, top, class scala/Option, class scala/Some, class java/lang/Object ]
          stack = []
        frame_type = 249 /* chop */
          offset_delta = 2
        frame_type = 2 /* same */
        frame_type = 255 /* full_frame */
          offset_delta = 4
          locals = [ class org/scalatest/events/Event, class scala/Option, class org/scalatest/events/Event, class scala/Option ]
          stack = []
      LineNumberTable:
        line 309: 0
        line 310: 2
        line 311: 31
        line 312: 55
        line 310: 66
        line 314: 72
        line 309: 77
      LocalVariableTable:
        Start  Length  Slot  Name   Signature
           22      47     5     p   Ljava/lang/Object;
            0      79     0  this   Lorg/scalatest/events/Event;
            0      79     1 payload   Lscala/Option;
    Signature: #121                         // (Lscala/Option<Ljava/lang/Object;>;)Lorg/scalatest/events/Event;
    MethodParameters:
      Name                           Flags
      payload                        final

  public org.scalatest.events.Event ensureThrowableSerializable(scala.Option<java.lang.Throwable>);
    descriptor: (Lscala/Option;)Lorg/scalatest/events/Event;
    flags: (0x0001) ACC_PUBLIC
    Code:
      stack=5, locals=8, args_size=2
         0: aload_1
         1: astore_3
         2: aload_3
         3: instanceof    #180                // class scala/Some
         6: ifeq          103
         9: aload_3
        10: checkcast     #180                // class scala/Some
        13: astore        4
        15: aload         4
        17: invokevirtual #183                // Method scala/Some.value:()Ljava/lang/Object;
        20: checkcast     #229                // class java/lang/Throwable
        23: astore        5
        25: aload_0
        26: aload         5
        28: invokevirtual #185                // Method serializeRoundtrip:(Ljava/lang/Object;)Z
        31: ifne          100
        34: aload         5
        36: invokevirtual #230                // Method java/lang/Throwable.getClass:()Ljava/lang/Class;
        39: invokevirtual #205                // Method java/lang/Class.getName:()Ljava/lang/String;
        42: astore        6
        44: getstatic     #191                // Field scala/Predef$.MODULE$:Lscala/Predef$;
        47: getstatic     #196                // Field org/scalatest/Resources$.MODULE$:Lorg/scalatest/Resources$;
        50: aload         6
        52: aload_0
        53: invokevirtual #208                // Method toString:()Ljava/lang/String;
        56: invokevirtual #233                // Method org/scalatest/Resources$.unableToSerializeThrowable:(Ljava/lang/Object;Ljava/lang/Object;)Ljava/lang/String;
        59: invokevirtual #215                // Method scala/Predef$.println:(Ljava/lang/Object;)V
        62: new           #235                // class org/scalatest/exceptions/NotSerializableWrapperException
        65: dup
        66: aload         5
        68: invokevirtual #238                // Method java/lang/Throwable.getMessage:()Ljava/lang/String;
        71: aload         6
        73: aload         5
        75: invokevirtual #242                // Method java/lang/Throwable.getStackTrace:()[Ljava/lang/StackTraceElement;
        78: invokespecial #245                // Method org/scalatest/exceptions/NotSerializableWrapperException."<init>":(Ljava/lang/String;Ljava/lang/String;[Ljava/lang/StackTraceElement;)V
        81: astore        7
        83: aload_0
        84: new           #180                // class scala/Some
        87: dup
        88: aload         7
        90: invokespecial #247                // Method scala/Some."<init>":(Ljava/lang/Object;)V
        93: invokevirtual #249                // Method withThrowable:(Lscala/Option;)Lorg/scalatest/events/Event;
        96: astore_2
        97: goto          111
       100: goto          106
       103: goto          106
       106: aload_0
       107: astore_2
       108: goto          111
       111: aload_2
       112: areturn
      StackMapTable: number_of_entries = 4
        frame_type = 255 /* full_frame */
          offset_delta = 100
          locals = [ class org/scalatest/events/Event, class scala/Option, top, class scala/Option, class scala/Some, class java/lang/Throwable ]
          stack = []
        frame_type = 249 /* chop */
          offset_delta = 2
        frame_type = 2 /* same */
        frame_type = 255 /* full_frame */
          offset_delta = 4
          locals = [ class org/scalatest/events/Event, class scala/Option, class org/scalatest/events/Event, class scala/Option ]
          stack = []
      LineNumberTable:
        line 318: 0
        line 319: 2
        line 320: 34
        line 321: 44
        line 322: 62
        line 323: 83
        line 319: 100
        line 325: 106
        line 318: 111
      LocalVariableTable:
        Start  Length  Slot  Name   Signature
           44      52     6 className   Ljava/lang/String;
           83      13     7    ex   Lorg/scalatest/exceptions/NotSerializableWrapperException;
           25      78     5     t   Ljava/lang/Throwable;
            0     113     0  this   Lorg/scalatest/events/Event;
            0     113     1 throwable   Lscala/Option;
    Signature: #124                         // (Lscala/Option<Ljava/lang/Throwable;>;)Lorg/scalatest/events/Event;
    MethodParameters:
      Name                           Flags
      throwable                      final

  public int compare(java.lang.Object);
    descriptor: (Ljava/lang/Object;)I
    flags: (0x1041) ACC_PUBLIC, ACC_BRIDGE, ACC_SYNTHETIC
    Code:
      stack=2, locals=2, args_size=2
         0: aload_0
         1: aload_1
         2: checkcast     #2                  // class org/scalatest/events/Event
         5: invokevirtual #257                // Method compare:(Lorg/scalatest/events/Event;)I
         8: ireturn
      LineNumberTable:
        line 37: 0
      LocalVariableTable:
        Start  Length  Slot  Name   Signature
            0       9     0  this   Lorg/scalatest/events/Event;
            0       9     1  that   Ljava/lang/Object;
    MethodParameters:
      Name                           Flags
      that                           final

  private final void EventXmlHelper$lzycompute$1();
    descriptor: ()V
    flags: (0x0012) ACC_PRIVATE, ACC_FINAL
    Code:
      stack=4, locals=2, args_size=1
         0: aload_0
         1: dup
         2: astore_1
         3: monitorenter
         4: aload_0
         5: getfield      #83                 // Field EventXmlHelper$module:Lorg/scalatest/events/Event$EventXmlHelper$;
         8: ifnonnull     23
        11: aload_0
        12: new           #20                 // class org/scalatest/events/Event$EventXmlHelper$
        15: dup
        16: aload_0
        17: invokespecial #260                // Method org/scalatest/events/Event$EventXmlHelper$."<init>":(Lorg/scalatest/events/Event;)V
        20: putfield      #83                 // Field EventXmlHelper$module:Lorg/scalatest/events/Event$EventXmlHelper$;
        23: aload_1
        24: monitorexit
        25: goto          31
        28: aload_1
        29: monitorexit
        30: athrow
        31: return
      Exception table:
         from    to  target type
             4    23    28   any
      StackMapTable: number_of_entries = 3
        frame_type = 252 /* append */
          offset_delta = 23
          locals = [ class org/scalatest/events/Event ]
        frame_type = 68 /* same_locals_1_stack_item */
          stack = [ class java/lang/Throwable ]
        frame_type = 2 /* same */
      LineNumberTable:
        line 90: 0
      LocalVariableTable:
        Start  Length  Slot  Name   Signature
            0      32     0  this   Lorg/scalatest/events/Event;

  private final void EventJsonHelper$lzycompute$1();
    descriptor: ()V
    flags: (0x0012) ACC_PRIVATE, ACC_FINAL
    Code:
      stack=4, locals=2, args_size=1
         0: aload_0
         1: dup
         2: astore_1
         3: monitorenter
         4: aload_0
         5: getfield      #91                 // Field EventJsonHelper$module:Lorg/scalatest/events/Event$EventJsonHelper$;
         8: ifnonnull     23
        11: aload_0
        12: new           #17                 // class org/scalatest/events/Event$EventJsonHelper$
        15: dup
        16: aload_0
        17: invokespecial #261                // Method org/scalatest/events/Event$EventJsonHelper$."<init>":(Lorg/scalatest/events/Event;)V
        20: putfield      #91                 // Field EventJsonHelper$module:Lorg/scalatest/events/Event$EventJsonHelper$;
        23: aload_1
        24: monitorexit
        25: goto          31
        28: aload_1
        29: monitorexit
        30: athrow
        31: return
      Exception table:
         from    to  target type
             4    23    28   any
      StackMapTable: number_of_entries = 3
        frame_type = 252 /* append */
          offset_delta = 23
          locals = [ class org/scalatest/events/Event ]
        frame_type = 68 /* same_locals_1_stack_item */
          stack = [ class java/lang/Throwable ]
        frame_type = 2 /* same */
      LineNumberTable:
        line 205: 0
      LocalVariableTable:
        Start  Length  Slot  Name   Signature
            0      32     0  this   Lorg/scalatest/events/Event;

  public org.scalatest.events.Event();
    descriptor: ()V
    flags: (0x0001) ACC_PUBLIC
    Code:
      stack=1, locals=1, args_size=1
         0: aload_0
         1: invokespecial #262                // Method java/lang/Object."<init>":()V
         4: aload_0
         5: invokestatic  #266                // InterfaceMethod scala/math/Ordered.$init$:(Lscala/math/Ordered;)V
         8: aload_0
         9: invokestatic  #269                // InterfaceMethod scala/Product.$init$:(Lscala/Product;)V
        12: return
      LineNumberTable:
        line 37: 0
      LocalVariableTable:
        Start  Length  Slot  Name   Signature
            0      13     0  this   Lorg/scalatest/events/Event;
}
InnerClasses:
  public #18= #17 of #2;                  // EventJsonHelper$=class org/scalatest/events/Event$EventJsonHelper$ of class org/scalatest/events/Event
  public #21= #20 of #2;                  // EventXmlHelper$=class org/scalatest/events/Event$EventXmlHelper$ of class org/scalatest/events/Event
Signature: #3                           // Ljava/lang/Object;Lscala/math/Ordered<Lorg/scalatest/events/Event;>;Lscala/Product;Ljava/io/Serializable;
SourceFile: "Event.scala"
RuntimeVisibleAnnotations:
  0: #13(#14=s#15)
    scala.reflect.ScalaSignature(
      bytes="\u0006\u0005\t%e!B\u0016-\u0003C\u0019\u0004\"\u0002(\u0001\t\u0003y\u0005b\u0002)\u0001\u0005\u00045\t!\u0015\u0005\b+\u0002\u0011\rQ\"\u0001W\u0011\u001di\u0006A1A\u0007\u0002yCqa\u0019\u0001C\u0002\u001b\u0005A\rC\u0004j\u0001\t\u0007i\u0011\u00016\t\u000fM\u0004!\u0019!D\u0001i\")\u0001\u0010\u0001C\u0001s\"1q\u0010\u0001D\u0001])D\u0001\"!\u0001\u0001\r\u0003q\u00131A\u0004\t\u0003#\u0001\u0001\u0012\u0001\u0017\u0002\u0014\u0019A\u0011q\u0003\u0001\t\u00021\nI\u0002\u0003\u0004O\u0019\u0011\u0005\u00111\u0004\u0005\b\u0003;aA\u0011AA\u0010\u0011\u001d\t9\u0003\u0004C\u0001\u0003SAq!!\u0010\r\t\u0003\ty\u0004C\u0004\u0002L1!\t!!\u0014\t\u000f\u0005\u001dD\u0002\"\u0001\u0002j!9\u0011\u0011\u000f\u0007\u0005\u0002\u0005M\u0004bBA=\u0019\u0011\u0005\u00111\u0010\u0005\b\u0003\u000fcA\u0011AAE\u0011\u001d\t\u0019\n\u0004C\u0001\u0003+Cq!!*\r\t\u0003\t9k\u0002\u0005\u00028\u0002A\t\u0001LA]\r!\tY\f\u0001E\u0001Y\u0005u\u0006B\u0002(\u001a\t\u0003\ty\fC\u0004\u0002ze!\t!!1\t\u000f\u0005\u0015\u0017\u0004\"\u0001\u0002H\"9\u0011QD\r\u0005\u0002\u00055\u0007bBA&3\u0011\u0005\u00111\u001b\u0005\b\u0003OJB\u0011AAl\u0011\u001d\tY.\u0007C\u0001\u0003;Dq!a\"\u001a\t\u0003\tI\u000fC\u0004\u0002\u0014f!\t!!<\t\u000f\u0005E\u0018\u0004\"\u0001\u0002t\"9\u0011QU\r\u0005\u0002\u0005e\b\u0002CA\u007f\u0001\u0019\u0005A&a@\t\u0011\t\u0015\u0001\u0001\"\u0001-\u0005\u000fA\u0001B!\u0004\u0001\t\u0003a#q\u0002\u0005\b\u0005+\u0001A\u0011\u0001\u0018P\u0011!\u00119\u0002\u0001C\u0001]\te\u0001\u0002\u0003B\u000f\u0001\u0011\u0005aFa\b\u0003\u000b\u00153XM\u001c;\u000b\u00055r\u0013AB3wK:$8O\u0003\u00020a\u0005I1oY1mCR,7\u000f\u001e\u0006\u0002c\u0005\u0019qN]4\u0004\u0001M)\u0001\u0001\u000e\u001eI\u0017B\u0011Q\u0007O\u0007\u0002m)\tq\'A\u0003tG\u0006d\u0017-\u0003\u0002:m\t1\u0011I\\=SK\u001a\u00042aO\"G\u001d\ta\u0014I\u0004\u0002>\u00016\taH\u0003\u0002@e\u00051AH]8pizJ\u0011aN\u0005\u0003\u0005Z\nq\u0001]1dW\u0006<W-\u0003\u0002E\u000b\n9qJ\u001d3fe\u0016$\'B\u0001\"7!\t9\u0005!D\u0001-!\t)\u0014*\u0003\u0002Km\t9\u0001K]8ek\u000e$\bCA\u001eM\u0013\tiUI\u0001\u0007TKJL\u0017\r\\5{C\ndW-\u0001\u0004=S:LGO\u0010\u000b\u0002\r\u00069qN\u001d3j]\u0006dW#\u0001*\u0011\u0005\u001d\u001b\u0016B\u0001+-\u0005\u001dy%\u000fZ5oC2\f\u0011BZ8s[\u0006$H/\u001a:\u0016\u0003]\u00032!\u000e-[\u0013\tIfG\u0001\u0004PaRLwN\u001c\t\u0003\u000fnK!\u0001\u0018\u0017\u0003\u0013\u0019{\'/\\1ui\u0016\u0014\u0018\u0001\u00037pG\u0006$\u0018n\u001c8\u0016\u0003}\u00032!\u000e-a!\t9\u0015-\u0003\u0002cY\tAAj\\2bi&|g.A\u0004qCfdw.\u00193\u0016\u0003\u0015\u00042!\u000e-g!\t)t-\u0003\u0002im\t\u0019\u0011I\\=\u0002\u0015QD\'/Z1e\u001d\u0006lW-F\u0001l!\ta\u0007O\u0004\u0002n]B\u0011QHN\u0005\u0003_Z\na\u0001\u0015:fI\u00164\u0017BA9s\u0005\u0019\u0019FO]5oO*\u0011qNN\u0001\ni&lWm\u0015;b[B,\u0012!\u001e\t\u0003kYL!a\u001e\u001c\u0003\t1{gnZ\u0001\bG>l\u0007/\u0019:f)\tQX\u0010\u0005\u00026w&\u0011AP\u000e\u0002\u0004\u0013:$\b\"\u0002@\t\u0001\u00041\u0015\u0001\u0002;iCR\fa\u0001^8Kg>t\u0017!\u0002;p16dWCAA\u0003!\u0011\t9!!\u0004\u000e\u0005\u0005%!bAA\u0006m\u0005\u0019\u00010\u001c7\n\t\u0005=\u0011\u0011\u0002\u0002\u0005\u000b2,W.\u0001\bFm\u0016tG\u000fW7m\u0011\u0016d\u0007/\u001a:\u0011\u0007\u0005UA\"D\u0001\u0001\u00059)e/\u001a8u16d\u0007*\u001a7qKJ\u001c\"\u0001\u0004\u001b\u0015\u0005\u0005M\u0011\u0001D:ue&twm\u00149uS>tGcA6\u0002\"!9\u00111\u0005\bA\u0002\u0005\u0015\u0012!C:ue>\u0003H/[8o!\r)\u0004l[\u0001\u000bY>twm\u00149uS>tG\u0003BA\u0016\u0003s\u0001B!!\f\u000285\u0011\u0011q\u0006\u0006\u0005\u0003c\t\u0019$\u0001\u0003mC:<\'BAA\u001b\u0003\u0011Q\u0017M^1\n\u0007E\fy\u0003C\u0004\u0002(=\u0001\r!a\u000f\u0011\u0007UBV/A\u0007c_>dW-\u00198PaRLwN\u001c\u000b\u0005\u0003W\t\t\u0005C\u0004\u0002>A\u0001\r!a\u0011\u0011\tUB\u0016Q\t\t\u0004k\u0005\u001d\u0013bAA%m\t9!i\\8mK\u0006t\u0017a\u00044pe6\fG\u000f^3s\u001fB$\u0018n\u001c8\u0015\t\u0005=\u0013Q\r\n\u0007\u0003#\n)&a\u0017\u0007\r\u0005M\u0003\u0001AA(\u00051a$/\u001a4j]\u0016lWM\u001c;?!\u0011\ti#a\u0016\n\t\u0005e\u0013q\u0006\u0002\u0007\u001f\nTWm\u0019;\u0011\t\u0005u\u00131M\u0007\u0003\u0003?RA!!\u0019\u00024\u0005\u0011\u0011n\\\u0005\u0004\u001b\u0006}\u0003BBA&#\u0001\u0007q+\u0001\bm_\u000e\fG/[8o\u001fB$\u0018n\u001c8\u0015\t\u0005-\u0014q\u000e\n\u0007\u0003[\n)&a\u0017\u0007\r\u0005M\u0003\u0001AA6\u0011\u0019\t9G\u0005a\u0001?\u0006\u0011b-\u001b7f!\u0006$\bN\\1nK>\u0003H/[8o)\rY\u0017Q\u000f\u0005\b\u0003o\u001a\u0002\u0019AA\u0013\u0003=1\u0017\u000e\\3QCRDg.Y7f\u001fB$\u0018AF4fiRC\'o\\<bE2,7\u000b^1dW\u0012+\u0007\u000f\u001e5\u0015\u0007i\fi\bC\u0004\u0002\u0000Q\u0001\r!!!\u0002\u0013QD\'o\\<bE2,\u0007cA\u001e\u0002\u0004&\u0019\u0011QQ#\u0003\u0013QC\'o\\<bE2,\u0017a\u0004;ie><\u0018M\u00197f\u001fB$\u0018n\u001c8\u0015\t\u0005-\u0015q\u0012\n\u0007\u0003\u001b\u000b)&a\u0017\u0007\r\u0005M\u0003\u0001AAF\u0011\u001d\t9)\u0006a\u0001\u0003#\u0003B!\u000e-\u0002\u0002\u0006i1/^7nCJLx\n\u001d;j_:$B!a&\u0002\u001cJ1\u0011\u0011TA+\u000372a!a\u0015\u0001\u0001\u0005]\u0005bBAJ-\u0001\u0007\u0011Q\u0014\t\u0005ka\u000by\nE\u0002H\u0003CK1!a)-\u0005\u001d\u0019V/\\7bef\faB\\1nK&sgm\\(qi&|g\u000e\u0006\u0003\u0002*\u00065&CBAV\u0003+\nYF\u0002\u0004\u0002T\u0001\u0001\u0011\u0011\u0016\u0005\b\u0003K;\u0002\u0019AAX!\u0011)\u0004,!-\u0011\u0007\u001d\u000b\u0019,C\u0002\u000262\u0012\u0001BT1nK&sgm\\\u0001\u0010\u000bZ,g\u000e\u001e&t_:DU\r\u001c9feB\u0019\u0011QC\r\u0003\u001f\u00153XM\u001c;Kg>t\u0007*\u001a7qKJ\u001c\"!\u0007\u001b\u0015\u0005\u0005eFc\u0001>\u0002D\"9\u0011qP\u000eA\u0002\u0005\u0005\u0015AB:ue&tw\rF\u0002l\u0003\u0013Da!a3\u001d\u0001\u0004Y\u0017!\u0002<bYV,GcA6\u0002P\"9\u0011\u0011[\u000fA\u0002\u0005\u0015\u0012\u0001\u0003<bYV,w\n\u001d;\u0015\u0007-\f)\u000e\u0003\u0004\u0002Ly\u0001\ra\u0016\u000b\u0004W\u0006e\u0007BBA4?\u0001\u0007q,\u0001\u0006ti\u0006\u001c7\u000e\u0016:bG\u0016$2a[Ap\u0011\u001d\t\t\u000f\ta\u0001\u0003G\f!a\u001d;\u0011\t\u00055\u0012Q]\u0005\u0005\u0003O\fyCA\tTi\u0006\u001c7\u000e\u0016:bG\u0016,E.Z7f]R$2a[Av\u0011\u001d\t9)\ta\u0001\u0003##2a[Ax\u0011\u001d\t\u0019J\ta\u0001\u0003;\u000baA\\7J]\u001a|GcA6\u0002v\"9\u0011q_\u0012A\u0002\u0005E\u0016\u0001\u00038b[\u0016LeNZ8\u0015\u0007-\fY\u0010C\u0004\u0002&\u0012\u0002\r!a,\u0002\u0017]LG\u000f\u001b)bs2|\u0017\r\u001a\u000b\u0004\r\n\u0005\u0001B\u0002B\u0002K\u0001\u0007Q-\u0001\u0006oK^\u0004\u0016-\u001f7pC\u0012\fQb^5uQRC\'o\\<bE2,Gc\u0001$\u0003\n!9!1\u0002\u0014A\u0002\u0005E\u0015\u0001\u00048foRC\'o\\<bE2,\u0017AE:fe&\fG.\u001b>f%>,h\u000e\u001a;sSB$B!!\u0012\u0003\u0012!1!1C\u0014A\u0002\u0019\f\u0011!Y\u0001\u0013K:\u001cXO]3TKJL\u0017\r\\5{C\ndW-A\rf]N,(/\u001a)bs2|\u0017\rZ*fe&\fG.\u001b>bE2,Gc\u0001$\u0003\u001c!)1-\u000ba\u0001K\u0006YRM\\:ve\u0016$\u0006N]8xC\ndWmU3sS\u0006d\u0017N_1cY\u0016$2A\u0012B\u0011\u0011\u001d\tyH\u000ba\u0001\u0003#K3\u0007\u0001B\u0013\u0005S\u0011iC!\r\u00036\te\"Q\bB!\u0005\u000b\u0012IE!\u0014\u0003R\tU#\u0011\fB/\u0005C\u0012)G!\u001b\u0003n\tE$Q\u000fB=\u0005{\u0012\tI!\"\n\u0007\t\u001dBFA\u0007BY\u0016\u0014H\u000f\u0015:pm&$W\rZ\u0005\u0004\u0005Wa#A\u0005#jg\u000e|g/\u001a:z\u0007>l\u0007\u000f\\3uK\u0012L1Aa\f-\u0005E!\u0015n]2pm\u0016\u0014\u0018p\u0015;beRLgnZ\u0005\u0004\u0005ga#\u0001E#yG\u0016\u0004H/[8oC2,e/\u001a8u\u0013\r\u00119\u0004\f\u0002\r\u0013:4w\u000e\u0015:pm&$W\rZ\u0005\u0004\u0005wa#AD\'be.,\b\u000f\u0015:pm&$W\rZ\u0005\u0004\u0005\u007fa#\u0001\u0004(pi\u0016\u0004&o\u001c<jI\u0016$\u0017b\u0001B\"Y\t\tbj\u001c;jM&\u001c\u0017\r^5p]\u00163XM\u001c;\n\u0007\t\u001dCFA\bSK\u000e|\'\u000fZ1cY\u0016,e/\u001a8u\u0013\r\u0011Y\u0005\f\u0002\u000b%Vt\u0017IY8si\u0016$\u0017b\u0001B(Y\ta!+\u001e8D_6\u0004H.\u001a;fI&\u0019!1\u000b\u0017\u0003\u0017I+hn\u0015;beRLgnZ\u0005\u0004\u0005/b#A\u0003*v]N#x\u000e\u001d9fI&\u0019!1\f\u0017\u0003\u0017M\u001bw\u000e]3DY>\u001cX\rZ\u0005\u0004\u0005?b#aC*d_B,w\n]3oK\u0012L1Aa\u0019-\u00051\u00196m\u001c9f!\u0016tG-\u001b8h\u0013\r\u00119\u0007\f\u0002\r\'VLG/Z!c_J$X\rZ\u0005\u0004\u0005Wb#AD*vSR,7i\\7qY\u0016$X\rZ\u0005\u0004\u0005_b#!D*vSR,7\u000b^1si&tw-C\u0002\u0003t1\u0012A\u0002V3ti\u000e\u000bgnY3mK\u0012L1Aa\u001e-\u0005)!Vm\u001d;GC&dW\rZ\u0005\u0004\u0005wb#a\u0003+fgRLuM\\8sK\u0012L1Aa -\u0005-!Vm\u001d;QK:$\u0017N\\4\n\u0007\t\rEF\u0001\u0007UKN$8\u000b^1si&tw-C\u0002\u0003\b2\u0012Q\u0002V3tiN+8mY3fI\u0016$\u0007"
    )
  ScalaInlineInfo: length = 0x9A (unknown attribute)
   01 00 00 1E 00 3E 00 37 00 00 46 00 37 00 00 36
   00 37 00 00 42 00 37 00 00 85 00 55 00 00 58 00
   59 01 00 5C 00 55 01 00 50 00 51 01 00 54 00 55
   01 00 6B 00 4B 00 00 6B 00 6C 00 00 4A 00 4B 00
   00 B0 00 78 00 00 AC 00 AD 00 00 E2 00 78 00 00
   61 00 62 00 00 64 00 62 00 00 5F 00 60 00 00 66
   00 62 00 00 29 00 2A 00 00 31 00 1B 00 00 1A 00
   1B 00 00 23 00 24 00 00 7F 00 37 00 00 68 00 24
   00 00 69 00 6A 00 00 74 00 24 00 00 75 00 76 00
   00 77 00 78 00 00 7B 00 78 00
  ScalaSig: length = 0x3 (unknown attribute)
   05 02 00
