Classfile /Users/mw/Projects/slang-braindump/.jar/jar11/assemble/slang-braindump/assemble/content/org/scalatest/events/IndentedText.class
  Last modified May 29, 2022; size 7292 bytes
  SHA-256 checksum 97da03f765f9d796ce1c12beae06d76fe3f9a4e3c1686e95acaf5064dcc7cd7f
  Compiled from "Formatter.scala"
public final class org.scalatest.events.IndentedText extends org.scalatest.events.Formatter
  minor version: 0
  major version: 52
  flags: (0x0031) ACC_PUBLIC, ACC_FINAL, ACC_SUPER
  this_class: #2                          // org/scalatest/events/IndentedText
  super_class: #4                         // org/scalatest/events/Formatter
  interfaces: 0, fields: 3, methods: 23, attributes: 6
Constant pool:
    #1 = Utf8               org/scalatest/events/IndentedText
    #2 = Class              #1            // org/scalatest/events/IndentedText
    #3 = Utf8               org/scalatest/events/Formatter
    #4 = Class              #3            // org/scalatest/events/Formatter
    #5 = Utf8               Formatter.scala
    #6 = Utf8               Lscala/reflect/ScalaSignature;
    #7 = Utf8               bytes
    #8 = Utf8               \u0006\u0005\u0005-d\u0001\u0002\u000f\u001e\u0005\u0012B\u0001b\u000f\u0001\u0003\u0016\u0004%\t\u0001\u0010\u0005\t\u000b\u0002\u0011\t\u0012)A\u0005{!Aa\t\u0001BK\u0002\u0013\u0005A\b\u0003\u0005H\u0001\tE\t\u0015!\u0003>\u0011!A\u0005A!f\u0001\n\u0003I\u0005\u0002C\'\u0001\u0005#\u0005\u000b\u0011\u0002&\t\u000b9\u0003A\u0011A(\t\u000fQ\u0003\u0011\u0011!C\u0001+\"9\u0011\fAI\u0001\n\u0003Q\u0006bB3\u0001#\u0003%\tA\u0017\u0005\bM\u0002\t\n\u0011\"\u0001h\u0011\u001dI\u0007!!A\u0005B)DqA\u001d\u0001\u0002\u0002\u0013\u0005\u0011\nC\u0004t\u0001\u0005\u0005I\u0011\u0001;\t\u000fi\u0004\u0011\u0011!C!w\"I\u0011Q\u0001\u0001\u0002\u0002\u0013\u0005\u0011q\u0001\u0005\n\u0003#\u0001\u0011\u0011!C!\u0003\'A\u0011\"a\u0006\u0001\u0003\u0003%\t%!\u0007\t\u0013\u0005m\u0001!!A\u0005B\u0005u\u0001\"CA\u0010\u0001\u0005\u0005I\u0011IA\u0011\u000f%\t)#HA\u0001\u0012\u0003\t9C\u0002\u0005\u001d;\u0005\u0005\t\u0012AA\u0015\u0011\u0019qe\u0003\"\u0001\u0002B!I\u00111\u0004\f\u0002\u0002\u0013\u0015\u0013Q\u0004\u0005\n\u0003\u00072\u0012\u0011!CA\u0003\u000bB\u0011\"!\u0014\u0017\u0003\u0003%\t)a\u0014\t\u0013\u0005\u0005d#!A\u0005\n\u0005\r$\u0001D%oI\u0016tG/\u001a3UKb$(B\u0001\u0010 \u0003\u0019)g/\u001a8ug*\u0011\u0001%I\u0001\ng\u000e\fG.\u0019;fgRT\u0011AI\u0001\u0004_J<7\u0001A\n\u0005\u0001\u0015Js\u0006\u0005\u0002\'O5\tQ$\u0003\u0002);\tIai\u001c:nCR$XM\u001d\t\u0003U5j\u0011a\u000b\u0006\u0002Y\u0005)1oY1mC&\u0011af\u000b\u0002\b!J|G-^2u!\t\u0001\u0004H\u0004\u00022m9\u0011!\'N\u0007\u0002g)\u0011AgI\u0001\u0007yI|w\u000e\u001e \n\u00031J!aN\u0016\u0002\u000fA\f7m[1hK&\u0011\u0011H\u000f\u0002\r\'\u0016\u0014\u0018.\u00197ju\u0006\u0014G.\u001a\u0006\u0003o-\nQBZ8s[\u0006$H/\u001a3UKb$X#A\u001f\u0011\u0005y\u0012eBA A!\t\u00114&\u0003\u0002BW\u00051\u0001K]3eK\u001aL!a\u0011#\u0003\rM#(/\u001b8h\u0015\t\t5&\u0001\bg_Jl\u0017\r\u001e;fIR+\u0007\u0010\u001e\u0011\u0002\u000fI\fw\u000fV3yi\u0006A!/Y<UKb$\b%\u0001\tj]\u0012,g\u000e^1uS>tG*\u001a<fYV\t!\n\u0005\u0002+\u0017&\u0011Aj\u000b\u0002\u0004\u0013:$\u0018!E5oI\u0016tG/\u0019;j_:dUM^3mA\u00051A(\u001b8jiz\"B\u0001U)S\'B\u0011a\u0005\u0001\u0005\u0006w\u001d\u0001\r!\u0010\u0005\u0006\r\u001e\u0001\r!\u0010\u0005\u0006\u0011\u001e\u0001\rAS\u0001\u0005G>\u0004\u0018\u0010\u0006\u0003Q-^C\u0006bB\u001e\t!\u0003\u0005\r!\u0010\u0005\b\r\"\u0001\n\u00111\u0001>\u0011\u001dA\u0005\u0002%AA\u0002)\u000babY8qs\u0012\"WMZ1vYR$\u0013\'F\u0001\\U\tiDlK\u0001^!\tq6-D\u0001`\u0015\t\u0001\u0017-A\u0005v]\u000eDWmY6fI*\u0011!mK\u0001\u000bC:tw\u000e^1uS>t\u0017B\u00013`\u0005E)hn\u00195fG.,GMV1sS\u0006t7-Z\u0001\u000fG>\u0004\u0018\u0010\n3fM\u0006,H\u000e\u001e\u00133\u00039\u0019w\u000e]=%I\u00164\u0017-\u001e7uIM*\u0012\u0001\u001b\u0016\u0003\u0015r\u000bQ\u0002\u001d:pIV\u001cG\u000f\u0015:fM&DX#A6\u0011\u00051\fX\"A7\u000b\u00059|\u0017\u0001\u00027b]\u001eT\u0011\u0001]\u0001\u0005U\u00064\u0018-\u0003\u0002D[\u0006a\u0001O]8ek\u000e$\u0018I]5us\u0006q\u0001O]8ek\u000e$X\t\\3nK:$HCA;y!\tQc/\u0003\u0002xW\t\u0019\u0011I\\=\t\u000fet\u0011\u0011!a\u0001\u0015\u0006\u0019\u0001\u0010J\u0019\u0002\u001fA\u0014x\u000eZ;di&#XM]1u_J,\u0012\u0001 \t\u0005{\u0006\u0005Q/D\u0001\u007f\u0015\ty8&\u0001\u0006d_2dWm\u0019;j_:L1!a\u0001\u007f\u0005!IE/\u001a:bi>\u0014\u0018\u0001C2b]\u0016\u000bX/\u00197\u0015\t\u0005%\u0011q\u0002\t\u0004U\u0005-\u0011bAA\u0007W\t9!i\\8mK\u0006t\u0007bB=\u0011\u0003\u0003\u0005\r!^\u0001\u0013aJ|G-^2u\u000b2,W.\u001a8u\u001d\u0006lW\rF\u0002l\u0003+Aq!_\t\u0002\u0002\u0003\u0007!*\u0001\u0005iCND7i\u001c3f)\u0005Q\u0015\u0001\u0003;p\'R\u0014\u0018N\\4\u0015\u0003-\fa!Z9vC2\u001cH\u0003BA\u0005\u0003GAq!\u001f\u000b\u0002\u0002\u0003\u0007Q/\u0001\u0007J]\u0012,g\u000e^3e)\u0016DH\u000f\u0005\u0002\'-M)a#a\u000b\u00028AA\u0011QFA\u001a{uR\u0005+\u0004\u0002\u00020)\u0019\u0011\u0011G\u0016\u0002\u000fI,h\u000e^5nK&!\u0011QGA\u0018\u0005E\t%m\u001d;sC\u000e$h)\u001e8di&|gn\r\t\u0005\u0003s\ty$\u0004\u0002\u0002<)\u0019\u0011QH8\u0002\u0005%|\u0017bA\u001d\u0002<Q\u0011\u0011qE\u0001\u0006CB\u0004H.\u001f\u000b\b!\u0006\u001d\u0013\u0011JA&\u0011\u0015Y\u0014\u00041\u0001>\u0011\u00151\u0015\u00041\u0001>\u0011\u0015A\u0015\u00041\u0001K\u0003\u001d)h.\u00199qYf$B!!\u0015\u0002^A)!&a\u0015\u0002X%\u0019\u0011QK\u0016\u0003\r=\u0003H/[8o!\u0019Q\u0013\u0011L\u001f>\u0015&\u0019\u00111L\u0016\u0003\rQ+\b\u000f\\34\u0011!\tyFGA\u0001\u0002\u0004\u0001\u0016a\u0001=%a\u0005aqO]5uKJ+\u0007\u000f\\1dKR\u0011\u0011Q\r\t\u0004Y\u0006\u001d\u0014bAA5[\n1qJ\u00196fGR\u0004
    #9 = Utf8               java/lang/invoke/MethodHandles$Lookup
   #10 = Class              #9            // java/lang/invoke/MethodHandles$Lookup
   #11 = Utf8               java/lang/invoke/MethodHandles
   #12 = Class              #11           // java/lang/invoke/MethodHandles
   #13 = Utf8               Lookup
   #14 = Utf8               formattedText
   #15 = Utf8               Ljava/lang/String;
   #16 = Utf8               rawText
   #17 = Utf8               indentationLevel
   #18 = Utf8               I
   #19 = Utf8               unapply
   #20 = Utf8               (Lorg/scalatest/events/IndentedText;)Lscala/Option;
   #21 = Utf8               (Lorg/scalatest/events/IndentedText;)Lscala/Option<Lscala/Tuple3<Ljava/lang/String;Ljava/lang/String;Ljava/lang/Object;>;>;
   #22 = Utf8               x$0
   #23 = Utf8               org/scalatest/events/IndentedText$
   #24 = Class              #23           // org/scalatest/events/IndentedText$
   #25 = Utf8               MODULE$
   #26 = Utf8               Lorg/scalatest/events/IndentedText$;
   #27 = NameAndType        #25:#26       // MODULE$:Lorg/scalatest/events/IndentedText$;
   #28 = Fieldref           #24.#27       // org/scalatest/events/IndentedText$.MODULE$:Lorg/scalatest/events/IndentedText$;
   #29 = NameAndType        #19:#20       // unapply:(Lorg/scalatest/events/IndentedText;)Lscala/Option;
   #30 = Methodref          #24.#29       // org/scalatest/events/IndentedText$.unapply:(Lorg/scalatest/events/IndentedText;)Lscala/Option;
   #31 = Utf8               Lorg/scalatest/events/IndentedText;
   #32 = Utf8               apply
   #33 = Utf8               (Ljava/lang/String;Ljava/lang/String;I)Lorg/scalatest/events/IndentedText;
   #34 = NameAndType        #32:#33       // apply:(Ljava/lang/String;Ljava/lang/String;I)Lorg/scalatest/events/IndentedText;
   #35 = Methodref          #24.#34       // org/scalatest/events/IndentedText$.apply:(Ljava/lang/String;Ljava/lang/String;I)Lorg/scalatest/events/IndentedText;
   #36 = Utf8               tupled
   #37 = Utf8               ()Lscala/Function1;
   #38 = Utf8               ()Lscala/Function1<Lscala/Tuple3<Ljava/lang/String;Ljava/lang/String;Ljava/lang/Object;>;Lorg/scalatest/events/IndentedText;>;
   #39 = NameAndType        #36:#37       // tupled:()Lscala/Function1;
   #40 = Methodref          #24.#39       // org/scalatest/events/IndentedText$.tupled:()Lscala/Function1;
   #41 = Utf8               curried
   #42 = Utf8               ()Lscala/Function1<Ljava/lang/String;Lscala/Function1<Ljava/lang/String;Lscala/Function1<Ljava/lang/Object;Lorg/scalatest/events/IndentedText;>;>;>;
   #43 = NameAndType        #41:#37       // curried:()Lscala/Function1;
   #44 = Methodref          #24.#43       // org/scalatest/events/IndentedText$.curried:()Lscala/Function1;
   #45 = Utf8               ()Ljava/lang/String;
   #46 = NameAndType        #14:#15       // formattedText:Ljava/lang/String;
   #47 = Fieldref           #2.#46        // org/scalatest/events/IndentedText.formattedText:Ljava/lang/String;
   #48 = Utf8               this
   #49 = NameAndType        #16:#15       // rawText:Ljava/lang/String;
   #50 = Fieldref           #2.#49        // org/scalatest/events/IndentedText.rawText:Ljava/lang/String;
   #51 = Utf8               ()I
   #52 = NameAndType        #17:#18       // indentationLevel:I
   #53 = Fieldref           #2.#52        // org/scalatest/events/IndentedText.indentationLevel:I
   #54 = Utf8               copy
   #55 = Utf8               <init>
   #56 = Utf8               (Ljava/lang/String;Ljava/lang/String;I)V
   #57 = NameAndType        #55:#56       // "<init>":(Ljava/lang/String;Ljava/lang/String;I)V
   #58 = Methodref          #2.#57        // org/scalatest/events/IndentedText."<init>":(Ljava/lang/String;Ljava/lang/String;I)V
   #59 = Utf8               copy$default$1
   #60 = NameAndType        #14:#45       // formattedText:()Ljava/lang/String;
   #61 = Methodref          #2.#60        // org/scalatest/events/IndentedText.formattedText:()Ljava/lang/String;
   #62 = Utf8               copy$default$2
   #63 = NameAndType        #16:#45       // rawText:()Ljava/lang/String;
   #64 = Methodref          #2.#63        // org/scalatest/events/IndentedText.rawText:()Ljava/lang/String;
   #65 = Utf8               copy$default$3
   #66 = NameAndType        #17:#51       // indentationLevel:()I
   #67 = Methodref          #2.#66        // org/scalatest/events/IndentedText.indentationLevel:()I
   #68 = Utf8               productPrefix
   #69 = Utf8               IndentedText
   #70 = String             #69           // IndentedText
   #71 = Utf8               productArity
   #72 = Utf8               productElement
   #73 = Utf8               (I)Ljava/lang/Object;
   #74 = Utf8               x$1
   #75 = Utf8               scala/runtime/BoxesRunTime
   #76 = Class              #75           // scala/runtime/BoxesRunTime
   #77 = Utf8               boxToInteger
   #78 = Utf8               (I)Ljava/lang/Integer;
   #79 = NameAndType        #77:#78       // boxToInteger:(I)Ljava/lang/Integer;
   #80 = Methodref          #76.#79       // scala/runtime/BoxesRunTime.boxToInteger:(I)Ljava/lang/Integer;
   #81 = Utf8               scala/runtime/Statics
   #82 = Class              #81           // scala/runtime/Statics
   #83 = Utf8               ioobe
   #84 = NameAndType        #83:#73       // ioobe:(I)Ljava/lang/Object;
   #85 = Methodref          #82.#84       // scala/runtime/Statics.ioobe:(I)Ljava/lang/Object;
   #86 = Utf8               java/lang/Object
   #87 = Class              #86           // java/lang/Object
   #88 = Utf8               productIterator
   #89 = Utf8               ()Lscala/collection/Iterator;
   #90 = Utf8               ()Lscala/collection/Iterator<Ljava/lang/Object;>;
   #91 = Utf8               scala/runtime/ScalaRunTime$
   #92 = Class              #91           // scala/runtime/ScalaRunTime$
   #93 = Utf8               Lscala/runtime/ScalaRunTime$;
   #94 = NameAndType        #25:#93       // MODULE$:Lscala/runtime/ScalaRunTime$;
   #95 = Fieldref           #92.#94       // scala/runtime/ScalaRunTime$.MODULE$:Lscala/runtime/ScalaRunTime$;
   #96 = Utf8               typedProductIterator
   #97 = Utf8               (Lscala/Product;)Lscala/collection/Iterator;
   #98 = NameAndType        #96:#97       // typedProductIterator:(Lscala/Product;)Lscala/collection/Iterator;
   #99 = Methodref          #92.#98       // scala/runtime/ScalaRunTime$.typedProductIterator:(Lscala/Product;)Lscala/collection/Iterator;
  #100 = Utf8               canEqual
  #101 = Utf8               (Ljava/lang/Object;)Z
  #102 = Utf8               Ljava/lang/Object;
  #103 = Utf8               productElementName
  #104 = Utf8               (I)Ljava/lang/String;
  #105 = String             #14           // formattedText
  #106 = String             #16           // rawText
  #107 = String             #17           // indentationLevel
  #108 = Utf8               java/lang/String
  #109 = Class              #108          // java/lang/String
  #110 = Utf8               hashCode
  #111 = Integer            -889275714
  #112 = NameAndType        #68:#45       // productPrefix:()Ljava/lang/String;
  #113 = Methodref          #2.#112       // org/scalatest/events/IndentedText.productPrefix:()Ljava/lang/String;
  #114 = NameAndType        #110:#51      // hashCode:()I
  #115 = Methodref          #109.#114     // java/lang/String.hashCode:()I
  #116 = Utf8               mix
  #117 = Utf8               (II)I
  #118 = NameAndType        #116:#117     // mix:(II)I
  #119 = Methodref          #82.#118      // scala/runtime/Statics.mix:(II)I
  #120 = Utf8               anyHash
  #121 = Utf8               (Ljava/lang/Object;)I
  #122 = NameAndType        #120:#121     // anyHash:(Ljava/lang/Object;)I
  #123 = Methodref          #82.#122      // scala/runtime/Statics.anyHash:(Ljava/lang/Object;)I
  #124 = Utf8               finalizeHash
  #125 = NameAndType        #124:#117     // finalizeHash:(II)I
  #126 = Methodref          #82.#125      // scala/runtime/Statics.finalizeHash:(II)I
  #127 = Utf8               toString
  #128 = Utf8               _toString
  #129 = Utf8               (Lscala/Product;)Ljava/lang/String;
  #130 = NameAndType        #128:#129     // _toString:(Lscala/Product;)Ljava/lang/String;
  #131 = Methodref          #92.#130      // scala/runtime/ScalaRunTime$._toString:(Lscala/Product;)Ljava/lang/String;
  #132 = Utf8               equals
  #133 = NameAndType        #132:#101     // equals:(Ljava/lang/Object;)Z
  #134 = Methodref          #87.#133      // java/lang/Object.equals:(Ljava/lang/Object;)Z
  #135 = Utf8               $anonfun$new$1
  #136 = Utf8               (Lorg/scalatest/events/IndentedText;)Ljava/lang/String;
  #137 = Utf8               $this
  #138 = Utf8               java/lang/StringBuilder
  #139 = Class              #138          // java/lang/StringBuilder
  #140 = Integer            37
  #141 = Utf8               (I)V
  #142 = NameAndType        #55:#141      // "<init>":(I)V
  #143 = Methodref          #139.#142     // java/lang/StringBuilder."<init>":(I)V
  #144 = Utf8               indentationLevel was less than zero:
  #145 = String             #144          // indentationLevel was less than zero:
  #146 = Utf8               append
  #147 = Utf8               (Ljava/lang/String;)Ljava/lang/StringBuilder;
  #148 = NameAndType        #146:#147     // append:(Ljava/lang/String;)Ljava/lang/StringBuilder;
  #149 = Methodref          #139.#148     // java/lang/StringBuilder.append:(Ljava/lang/String;)Ljava/lang/StringBuilder;
  #150 = Utf8               (I)Ljava/lang/StringBuilder;
  #151 = NameAndType        #146:#150     // append:(I)Ljava/lang/StringBuilder;
  #152 = Methodref          #139.#151     // java/lang/StringBuilder.append:(I)Ljava/lang/StringBuilder;
  #153 = NameAndType        #127:#45      // toString:()Ljava/lang/String;
  #154 = Methodref          #139.#153     // java/lang/StringBuilder.toString:()Ljava/lang/String;
  #155 = Utf8               ()V
  #156 = NameAndType        #55:#155      // "<init>":()V
  #157 = Methodref          #4.#156       // org/scalatest/events/Formatter."<init>":()V
  #158 = Utf8               scala/Predef$
  #159 = Class              #158          // scala/Predef$
  #160 = Utf8               Lscala/Predef$;
  #161 = NameAndType        #25:#160      // MODULE$:Lscala/Predef$;
  #162 = Fieldref           #159.#161     // scala/Predef$.MODULE$:Lscala/Predef$;
  #163 = Utf8               ()Ljava/lang/Object;
  #164 = MethodType         #163          //  ()Ljava/lang/Object;
  #165 = NameAndType        #135:#136     // $anonfun$new$1:(Lorg/scalatest/events/IndentedText;)Ljava/lang/String;
  #166 = Methodref          #2.#165       // org/scalatest/events/IndentedText.$anonfun$new$1:(Lorg/scalatest/events/IndentedText;)Ljava/lang/String;
  #167 = MethodHandle       6:#166        // REF_invokeStatic org/scalatest/events/IndentedText.$anonfun$new$1:(Lorg/scalatest/events/IndentedText;)Ljava/lang/String;
  #168 = MethodType         #45           //  ()Ljava/lang/String;
  #169 = Integer            5
  #170 = Integer            1
  #171 = Utf8               java/lang/invoke/LambdaMetafactory
  #172 = Class              #171          // java/lang/invoke/LambdaMetafactory
  #173 = Utf8               altMetafactory
  #174 = Utf8               (Ljava/lang/invoke/MethodHandles$Lookup;Ljava/lang/String;Ljava/lang/invoke/MethodType;[Ljava/lang/Object;)Ljava/lang/invoke/CallSite;
  #175 = NameAndType        #173:#174     // altMetafactory:(Ljava/lang/invoke/MethodHandles$Lookup;Ljava/lang/String;Ljava/lang/invoke/MethodType;[Ljava/lang/Object;)Ljava/lang/invoke/CallSite;
  #176 = Methodref          #172.#175     // java/lang/invoke/LambdaMetafactory.altMetafactory:(Ljava/lang/invoke/MethodHandles$Lookup;Ljava/lang/String;Ljava/lang/invoke/MethodType;[Ljava/lang/Object;)Ljava/lang/invoke/CallSite;
  #177 = MethodHandle       6:#176        // REF_invokeStatic java/lang/invoke/LambdaMetafactory.altMetafactory:(Ljava/lang/invoke/MethodHandles$Lookup;Ljava/lang/String;Ljava/lang/invoke/MethodType;[Ljava/lang/Object;)Ljava/lang/invoke/CallSite;
  #178 = Utf8               (Lorg/scalatest/events/IndentedText;)Lscala/Function0;
  #179 = NameAndType        #32:#178      // apply:(Lorg/scalatest/events/IndentedText;)Lscala/Function0;
  #180 = InvokeDynamic      #0:#179       // #0:apply:(Lorg/scalatest/events/IndentedText;)Lscala/Function0;
  #181 = Utf8               require
  #182 = Utf8               (ZLscala/Function0;)V
  #183 = NameAndType        #181:#182     // require:(ZLscala/Function0;)V
  #184 = Methodref          #159.#183     // scala/Predef$.require:(ZLscala/Function0;)V
  #185 = Utf8               $deserializeLambda$
  #186 = Utf8               (Ljava/lang/invoke/SerializedLambda;)Ljava/lang/Object;
  #187 = Utf8               scala/runtime/LambdaDeserialize
  #188 = Class              #187          // scala/runtime/LambdaDeserialize
  #189 = Utf8               bootstrap
  #190 = Utf8               (Ljava/lang/invoke/MethodHandles$Lookup;Ljava/lang/String;Ljava/lang/invoke/MethodType;[Ljava/lang/invoke/MethodHandle;)Ljava/lang/invoke/CallSite;
  #191 = NameAndType        #189:#190     // bootstrap:(Ljava/lang/invoke/MethodHandles$Lookup;Ljava/lang/String;Ljava/lang/invoke/MethodType;[Ljava/lang/invoke/MethodHandle;)Ljava/lang/invoke/CallSite;
  #192 = Methodref          #188.#191     // scala/runtime/LambdaDeserialize.bootstrap:(Ljava/lang/invoke/MethodHandles$Lookup;Ljava/lang/String;Ljava/lang/invoke/MethodType;[Ljava/lang/invoke/MethodHandle;)Ljava/lang/invoke/CallSite;
  #193 = MethodHandle       6:#192        // REF_invokeStatic scala/runtime/LambdaDeserialize.bootstrap:(Ljava/lang/invoke/MethodHandles$Lookup;Ljava/lang/String;Ljava/lang/invoke/MethodType;[Ljava/lang/invoke/MethodHandle;)Ljava/lang/invoke/CallSite;
  #194 = Utf8               lambdaDeserialize
  #195 = NameAndType        #194:#186     // lambdaDeserialize:(Ljava/lang/invoke/SerializedLambda;)Ljava/lang/Object;
  #196 = InvokeDynamic      #1:#195       // #1:lambdaDeserialize:(Ljava/lang/invoke/SerializedLambda;)Ljava/lang/Object;
  #197 = Utf8               Code
  #198 = Utf8               LocalVariableTable
  #199 = Utf8               Signature
  #200 = Utf8               MethodParameters
  #201 = Utf8               LineNumberTable
  #202 = Utf8               StackMapTable
  #203 = Utf8               InnerClasses
  #204 = Utf8               SourceFile
  #205 = Utf8               RuntimeVisibleAnnotations
  #206 = Utf8               BootstrapMethods
  #207 = Utf8               ScalaInlineInfo
  #208 = Utf8               ScalaSig
{
  private final java.lang.String formattedText;
    descriptor: Ljava/lang/String;
    flags: (0x0012) ACC_PRIVATE, ACC_FINAL

  private final java.lang.String rawText;
    descriptor: Ljava/lang/String;
    flags: (0x0012) ACC_PRIVATE, ACC_FINAL

  private final int indentationLevel;
    descriptor: I
    flags: (0x0012) ACC_PRIVATE, ACC_FINAL

  public static scala.Option<scala.Tuple3<java.lang.String, java.lang.String, java.lang.Object>> unapply(org.scalatest.events.IndentedText);
    descriptor: (Lorg/scalatest/events/IndentedText;)Lscala/Option;
    flags: (0x0009) ACC_PUBLIC, ACC_STATIC
    Code:
      stack=2, locals=1, args_size=1
         0: getstatic     #28                 // Field org/scalatest/events/IndentedText$.MODULE$:Lorg/scalatest/events/IndentedText$;
         3: aload_0
         4: invokevirtual #30                 // Method org/scalatest/events/IndentedText$.unapply:(Lorg/scalatest/events/IndentedText;)Lscala/Option;
         7: areturn
      LocalVariableTable:
        Start  Length  Slot  Name   Signature
            0       8     0   x$0   Lorg/scalatest/events/IndentedText;
    Signature: #21                          // (Lorg/scalatest/events/IndentedText;)Lscala/Option<Lscala/Tuple3<Ljava/lang/String;Ljava/lang/String;Ljava/lang/Object;>;>;
    MethodParameters:
      Name                           Flags
      x$0                            final

  public static org.scalatest.events.IndentedText apply(java.lang.String, java.lang.String, int);
    descriptor: (Ljava/lang/String;Ljava/lang/String;I)Lorg/scalatest/events/IndentedText;
    flags: (0x0009) ACC_PUBLIC, ACC_STATIC
    Code:
      stack=4, locals=3, args_size=3
         0: getstatic     #28                 // Field org/scalatest/events/IndentedText$.MODULE$:Lorg/scalatest/events/IndentedText$;
         3: aload_0
         4: aload_1
         5: iload_2
         6: invokevirtual #35                 // Method org/scalatest/events/IndentedText$.apply:(Ljava/lang/String;Ljava/lang/String;I)Lorg/scalatest/events/IndentedText;
         9: areturn
      LocalVariableTable:
        Start  Length  Slot  Name   Signature
            0      10     0 formattedText   Ljava/lang/String;
            0      10     1 rawText   Ljava/lang/String;
            0      10     2 indentationLevel   I
    MethodParameters:
      Name                           Flags
      formattedText                  final
      rawText                        final
      indentationLevel               final

  public static scala.Function1<scala.Tuple3<java.lang.String, java.lang.String, java.lang.Object>, org.scalatest.events.IndentedText> tupled();
    descriptor: ()Lscala/Function1;
    flags: (0x0009) ACC_PUBLIC, ACC_STATIC
    Code:
      stack=1, locals=0, args_size=0
         0: getstatic     #28                 // Field org/scalatest/events/IndentedText$.MODULE$:Lorg/scalatest/events/IndentedText$;
         3: invokevirtual #40                 // Method org/scalatest/events/IndentedText$.tupled:()Lscala/Function1;
         6: areturn
    Signature: #38                          // ()Lscala/Function1<Lscala/Tuple3<Ljava/lang/String;Ljava/lang/String;Ljava/lang/Object;>;Lorg/scalatest/events/IndentedText;>;

  public static scala.Function1<java.lang.String, scala.Function1<java.lang.String, scala.Function1<java.lang.Object, org.scalatest.events.IndentedText>>> curried();
    descriptor: ()Lscala/Function1;
    flags: (0x0009) ACC_PUBLIC, ACC_STATIC
    Code:
      stack=1, locals=0, args_size=0
         0: getstatic     #28                 // Field org/scalatest/events/IndentedText$.MODULE$:Lorg/scalatest/events/IndentedText$;
         3: invokevirtual #44                 // Method org/scalatest/events/IndentedText$.curried:()Lscala/Function1;
         6: areturn
    Signature: #42                          // ()Lscala/Function1<Ljava/lang/String;Lscala/Function1<Ljava/lang/String;Lscala/Function1<Ljava/lang/Object;Lorg/scalatest/events/IndentedText;>;>;>;

  public java.lang.String formattedText();
    descriptor: ()Ljava/lang/String;
    flags: (0x0001) ACC_PUBLIC
    Code:
      stack=1, locals=1, args_size=1
         0: aload_0
         1: getfield      #47                 // Field formattedText:Ljava/lang/String;
         4: areturn
      LineNumberTable:
        line 132: 0
      LocalVariableTable:
        Start  Length  Slot  Name   Signature
            0       5     0  this   Lorg/scalatest/events/IndentedText;

  public java.lang.String rawText();
    descriptor: ()Ljava/lang/String;
    flags: (0x0001) ACC_PUBLIC
    Code:
      stack=1, locals=1, args_size=1
         0: aload_0
         1: getfield      #50                 // Field rawText:Ljava/lang/String;
         4: areturn
      LineNumberTable:
        line 132: 0
      LocalVariableTable:
        Start  Length  Slot  Name   Signature
            0       5     0  this   Lorg/scalatest/events/IndentedText;

  public int indentationLevel();
    descriptor: ()I
    flags: (0x0001) ACC_PUBLIC
    Code:
      stack=1, locals=1, args_size=1
         0: aload_0
         1: getfield      #53                 // Field indentationLevel:I
         4: ireturn
      LineNumberTable:
        line 132: 0
      LocalVariableTable:
        Start  Length  Slot  Name   Signature
            0       5     0  this   Lorg/scalatest/events/IndentedText;

  public org.scalatest.events.IndentedText copy(java.lang.String, java.lang.String, int);
    descriptor: (Ljava/lang/String;Ljava/lang/String;I)Lorg/scalatest/events/IndentedText;
    flags: (0x0001) ACC_PUBLIC
    Code:
      stack=5, locals=4, args_size=4
         0: new           #2                  // class org/scalatest/events/IndentedText
         3: dup
         4: aload_1
         5: aload_2
         6: iload_3
         7: invokespecial #58                 // Method "<init>":(Ljava/lang/String;Ljava/lang/String;I)V
        10: areturn
      LineNumberTable:
        line 132: 0
      LocalVariableTable:
        Start  Length  Slot  Name   Signature
            0      11     0  this   Lorg/scalatest/events/IndentedText;
            0      11     1 formattedText   Ljava/lang/String;
            0      11     2 rawText   Ljava/lang/String;
            0      11     3 indentationLevel   I
    MethodParameters:
      Name                           Flags
      formattedText                  final
      rawText                        final
      indentationLevel               final

  public java.lang.String copy$default$1();
    descriptor: ()Ljava/lang/String;
    flags: (0x0001) ACC_PUBLIC
    Code:
      stack=1, locals=1, args_size=1
         0: aload_0
         1: invokevirtual #61                 // Method formattedText:()Ljava/lang/String;
         4: areturn
      LineNumberTable:
        line 132: 0
      LocalVariableTable:
        Start  Length  Slot  Name   Signature
            0       5     0  this   Lorg/scalatest/events/IndentedText;

  public java.lang.String copy$default$2();
    descriptor: ()Ljava/lang/String;
    flags: (0x0001) ACC_PUBLIC
    Code:
      stack=1, locals=1, args_size=1
         0: aload_0
         1: invokevirtual #64                 // Method rawText:()Ljava/lang/String;
         4: areturn
      LineNumberTable:
        line 132: 0
      LocalVariableTable:
        Start  Length  Slot  Name   Signature
            0       5     0  this   Lorg/scalatest/events/IndentedText;

  public int copy$default$3();
    descriptor: ()I
    flags: (0x0001) ACC_PUBLIC
    Code:
      stack=1, locals=1, args_size=1
         0: aload_0
         1: invokevirtual #67                 // Method indentationLevel:()I
         4: ireturn
      LineNumberTable:
        line 132: 0
      LocalVariableTable:
        Start  Length  Slot  Name   Signature
            0       5     0  this   Lorg/scalatest/events/IndentedText;

  public java.lang.String productPrefix();
    descriptor: ()Ljava/lang/String;
    flags: (0x0001) ACC_PUBLIC
    Code:
      stack=1, locals=1, args_size=1
         0: ldc           #70                 // String IndentedText
         2: areturn
      LineNumberTable:
        line 132: 0
      LocalVariableTable:
        Start  Length  Slot  Name   Signature
            0       3     0  this   Lorg/scalatest/events/IndentedText;

  public int productArity();
    descriptor: ()I
    flags: (0x0001) ACC_PUBLIC
    Code:
      stack=1, locals=1, args_size=1
         0: iconst_3
         1: ireturn
      LineNumberTable:
        line 132: 0
      LocalVariableTable:
        Start  Length  Slot  Name   Signature
            0       2     0  this   Lorg/scalatest/events/IndentedText;

  public java.lang.Object productElement(int);
    descriptor: (I)Ljava/lang/Object;
    flags: (0x0001) ACC_PUBLIC
    Code:
      stack=1, locals=3, args_size=2
         0: iload_1
         1: istore_2
         2: iload_2
         3: tableswitch   { // 0 to 2
                       0: 28
                       1: 35
                       2: 42
                 default: 52
            }
        28: aload_0
        29: invokevirtual #61                 // Method formattedText:()Ljava/lang/String;
        32: goto          59
        35: aload_0
        36: invokevirtual #64                 // Method rawText:()Ljava/lang/String;
        39: goto          59
        42: aload_0
        43: invokevirtual #67                 // Method indentationLevel:()I
        46: invokestatic  #80                 // Method scala/runtime/BoxesRunTime.boxToInteger:(I)Ljava/lang/Integer;
        49: goto          59
        52: iload_1
        53: invokestatic  #85                 // Method scala/runtime/Statics.ioobe:(I)Ljava/lang/Object;
        56: goto          59
        59: areturn
      StackMapTable: number_of_entries = 5
        frame_type = 252 /* append */
          offset_delta = 28
          locals = [ int ]
        frame_type = 6 /* same */
        frame_type = 6 /* same */
        frame_type = 9 /* same */
        frame_type = 70 /* same_locals_1_stack_item */
          stack = [ class java/lang/Object ]
      LineNumberTable:
        line 132: 0
      LocalVariableTable:
        Start  Length  Slot  Name   Signature
            0      60     0  this   Lorg/scalatest/events/IndentedText;
            0      60     1   x$1   I
    MethodParameters:
      Name                           Flags
      x$1                            final

  public scala.collection.Iterator<java.lang.Object> productIterator();
    descriptor: ()Lscala/collection/Iterator;
    flags: (0x0001) ACC_PUBLIC
    Code:
      stack=2, locals=1, args_size=1
         0: getstatic     #95                 // Field scala/runtime/ScalaRunTime$.MODULE$:Lscala/runtime/ScalaRunTime$;
         3: aload_0
         4: invokevirtual #99                 // Method scala/runtime/ScalaRunTime$.typedProductIterator:(Lscala/Product;)Lscala/collection/Iterator;
         7: areturn
      LineNumberTable:
        line 132: 0
      LocalVariableTable:
        Start  Length  Slot  Name   Signature
            0       8     0  this   Lorg/scalatest/events/IndentedText;
    Signature: #90                          // ()Lscala/collection/Iterator<Ljava/lang/Object;>;

  public boolean canEqual(java.lang.Object);
    descriptor: (Ljava/lang/Object;)Z
    flags: (0x0001) ACC_PUBLIC
    Code:
      stack=1, locals=2, args_size=2
         0: aload_1
         1: instanceof    #2                  // class org/scalatest/events/IndentedText
         4: ireturn
      LineNumberTable:
        line 132: 0
      LocalVariableTable:
        Start  Length  Slot  Name   Signature
            0       5     0  this   Lorg/scalatest/events/IndentedText;
            0       5     1   x$1   Ljava/lang/Object;
    MethodParameters:
      Name                           Flags
      x$1                            final

  public java.lang.String productElementName(int);
    descriptor: (I)Ljava/lang/String;
    flags: (0x0001) ACC_PUBLIC
    Code:
      stack=1, locals=3, args_size=2
         0: iload_1
         1: istore_2
         2: iload_2
         3: tableswitch   { // 0 to 2
                       0: 28
                       1: 33
                       2: 38
                 default: 43
            }
        28: ldc           #105                // String formattedText
        30: goto          53
        33: ldc           #106                // String rawText
        35: goto          53
        38: ldc           #107                // String indentationLevel
        40: goto          53
        43: iload_1
        44: invokestatic  #85                 // Method scala/runtime/Statics.ioobe:(I)Ljava/lang/Object;
        47: checkcast     #109                // class java/lang/String
        50: goto          53
        53: areturn
      StackMapTable: number_of_entries = 5
        frame_type = 252 /* append */
          offset_delta = 28
          locals = [ int ]
        frame_type = 4 /* same */
        frame_type = 4 /* same */
        frame_type = 4 /* same */
        frame_type = 73 /* same_locals_1_stack_item */
          stack = [ class java/lang/String ]
      LineNumberTable:
        line 132: 0
      LocalVariableTable:
        Start  Length  Slot  Name   Signature
            0      54     0  this   Lorg/scalatest/events/IndentedText;
            0      54     1   x$1   I
    MethodParameters:
      Name                           Flags
      x$1                            final

  public int hashCode();
    descriptor: ()I
    flags: (0x0001) ACC_PUBLIC
    Code:
      stack=2, locals=2, args_size=1
         0: ldc           #111                // int -889275714
         2: istore_1
         3: iload_1
         4: aload_0
         5: invokevirtual #113                // Method productPrefix:()Ljava/lang/String;
         8: invokevirtual #115                // Method java/lang/String.hashCode:()I
        11: invokestatic  #119                // Method scala/runtime/Statics.mix:(II)I
        14: istore_1
        15: iload_1
        16: aload_0
        17: invokevirtual #61                 // Method formattedText:()Ljava/lang/String;
        20: invokestatic  #123                // Method scala/runtime/Statics.anyHash:(Ljava/lang/Object;)I
        23: invokestatic  #119                // Method scala/runtime/Statics.mix:(II)I
        26: istore_1
        27: iload_1
        28: aload_0
        29: invokevirtual #64                 // Method rawText:()Ljava/lang/String;
        32: invokestatic  #123                // Method scala/runtime/Statics.anyHash:(Ljava/lang/Object;)I
        35: invokestatic  #119                // Method scala/runtime/Statics.mix:(II)I
        38: istore_1
        39: iload_1
        40: aload_0
        41: invokevirtual #67                 // Method indentationLevel:()I
        44: invokestatic  #119                // Method scala/runtime/Statics.mix:(II)I
        47: istore_1
        48: iload_1
        49: iconst_3
        50: invokestatic  #126                // Method scala/runtime/Statics.finalizeHash:(II)I
        53: ireturn
      LineNumberTable:
        line 132: 0
      LocalVariableTable:
        Start  Length  Slot  Name   Signature
            0      54     0  this   Lorg/scalatest/events/IndentedText;

  public java.lang.String toString();
    descriptor: ()Ljava/lang/String;
    flags: (0x0001) ACC_PUBLIC
    Code:
      stack=2, locals=1, args_size=1
         0: getstatic     #95                 // Field scala/runtime/ScalaRunTime$.MODULE$:Lscala/runtime/ScalaRunTime$;
         3: aload_0
         4: invokevirtual #131                // Method scala/runtime/ScalaRunTime$._toString:(Lscala/Product;)Ljava/lang/String;
         7: areturn
      LineNumberTable:
        line 132: 0
      LocalVariableTable:
        Start  Length  Slot  Name   Signature
            0       8     0  this   Lorg/scalatest/events/IndentedText;

  public boolean equals(java.lang.Object);
    descriptor: (Ljava/lang/Object;)Z
    flags: (0x0001) ACC_PUBLIC
    Code:
      stack=2, locals=7, args_size=2
         0: aload_0
         1: aload_1
         2: if_acmpeq     121
         5: aload_1
         6: astore_3
         7: aload_3
         8: instanceof    #2                  // class org/scalatest/events/IndentedText
        11: ifeq          19
        14: iconst_1
        15: istore_2
        16: goto          27
        19: goto          22
        22: iconst_0
        23: istore_2
        24: goto          27
        27: iload_2
        28: ifeq          125
        31: aload_1
        32: checkcast     #2                  // class org/scalatest/events/IndentedText
        35: astore        4
        37: aload_0
        38: invokevirtual #67                 // Method indentationLevel:()I
        41: aload         4
        43: invokevirtual #67                 // Method indentationLevel:()I
        46: if_icmpne     117
        49: aload_0
        50: invokevirtual #61                 // Method formattedText:()Ljava/lang/String;
        53: aload         4
        55: invokevirtual #61                 // Method formattedText:()Ljava/lang/String;
        58: astore        5
        60: dup
        61: ifnonnull     73
        64: pop
        65: aload         5
        67: ifnull        81
        70: goto          117
        73: aload         5
        75: invokevirtual #134                // Method java/lang/Object.equals:(Ljava/lang/Object;)Z
        78: ifeq          117
        81: aload_0
        82: invokevirtual #64                 // Method rawText:()Ljava/lang/String;
        85: aload         4
        87: invokevirtual #64                 // Method rawText:()Ljava/lang/String;
        90: astore        6
        92: dup
        93: ifnonnull     105
        96: pop
        97: aload         6
        99: ifnull        113
       102: goto          117
       105: aload         6
       107: invokevirtual #134                // Method java/lang/Object.equals:(Ljava/lang/Object;)Z
       110: ifeq          117
       113: iconst_1
       114: goto          118
       117: iconst_0
       118: ifeq          125
       121: iconst_1
       122: goto          126
       125: iconst_0
       126: ireturn
      StackMapTable: number_of_entries = 12
        frame_type = 253 /* append */
          offset_delta = 19
          locals = [ top, class java/lang/Object ]
        frame_type = 2 /* same */
        frame_type = 255 /* full_frame */
          offset_delta = 4
          locals = [ class org/scalatest/events/IndentedText, class java/lang/Object, int, class java/lang/Object ]
          stack = []
        frame_type = 255 /* full_frame */
          offset_delta = 45
          locals = [ class org/scalatest/events/IndentedText, class java/lang/Object, int, class java/lang/Object, class org/scalatest/events/IndentedText, class java/lang/String ]
          stack = [ class java/lang/String ]
        frame_type = 7 /* same */
        frame_type = 255 /* full_frame */
          offset_delta = 23
          locals = [ class org/scalatest/events/IndentedText, class java/lang/Object, int, class java/lang/Object, class org/scalatest/events/IndentedText, class java/lang/String, class java/lang/String ]
          stack = [ class java/lang/String ]
        frame_type = 7 /* same */
        frame_type = 249 /* chop */
          offset_delta = 3
        frame_type = 64 /* same_locals_1_stack_item */
          stack = [ int ]
        frame_type = 248 /* chop */
          offset_delta = 2
        frame_type = 253 /* append */
          offset_delta = 3
          locals = [ int, class java/lang/Object ]
        frame_type = 255 /* full_frame */
          offset_delta = 0
          locals = [ class org/scalatest/events/IndentedText, class java/lang/Object ]
          stack = [ int ]
      LineNumberTable:
        line 132: 0
      LocalVariableTable:
        Start  Length  Slot  Name   Signature
            0     127     0  this   Lorg/scalatest/events/IndentedText;
            0     127     1   x$1   Ljava/lang/Object;
    MethodParameters:
      Name                           Flags
      x$1                            final

  public static final java.lang.String $anonfun$new$1(org.scalatest.events.IndentedText);
    descriptor: (Lorg/scalatest/events/IndentedText;)Ljava/lang/String;
    flags: (0x1019) ACC_PUBLIC, ACC_STATIC, ACC_FINAL, ACC_SYNTHETIC
    Code:
      stack=3, locals=1, args_size=1
         0: new           #139                // class java/lang/StringBuilder
         3: dup
         4: ldc           #140                // int 37
         6: invokespecial #143                // Method java/lang/StringBuilder."<init>":(I)V
         9: ldc           #145                // String indentationLevel was less than zero:
        11: invokevirtual #149                // Method java/lang/StringBuilder.append:(Ljava/lang/String;)Ljava/lang/StringBuilder;
        14: aload_0
        15: invokevirtual #67                 // Method indentationLevel:()I
        18: invokevirtual #152                // Method java/lang/StringBuilder.append:(I)Ljava/lang/StringBuilder;
        21: invokevirtual #154                // Method java/lang/StringBuilder.toString:()Ljava/lang/String;
        24: areturn
      LineNumberTable:
        line 133: 0
      LocalVariableTable:
        Start  Length  Slot  Name   Signature
            0      25     0 $this   Lorg/scalatest/events/IndentedText;
    MethodParameters:
      Name                           Flags
      $this                          final synthetic

  public org.scalatest.events.IndentedText(java.lang.String, java.lang.String, int);
    descriptor: (Ljava/lang/String;Ljava/lang/String;I)V
    flags: (0x0001) ACC_PUBLIC
    Code:
      stack=3, locals=4, args_size=4
         0: aload_0
         1: aload_1
         2: putfield      #47                 // Field formattedText:Ljava/lang/String;
         5: aload_0
         6: aload_2
         7: putfield      #50                 // Field rawText:Ljava/lang/String;
        10: aload_0
        11: iload_3
        12: putfield      #53                 // Field indentationLevel:I
        15: aload_0
        16: invokespecial #157                // Method org/scalatest/events/Formatter."<init>":()V
        19: getstatic     #162                // Field scala/Predef$.MODULE$:Lscala/Predef$;
        22: iload_3
        23: iconst_0
        24: if_icmplt     31
        27: iconst_1
        28: goto          32
        31: iconst_0
        32: aload_0
        33: invokedynamic #180,  0            // InvokeDynamic #0:apply:(Lorg/scalatest/events/IndentedText;)Lscala/Function0;
        38: invokevirtual #184                // Method scala/Predef$.require:(ZLscala/Function0;)V
        41: return
      StackMapTable: number_of_entries = 2
        frame_type = 255 /* full_frame */
          offset_delta = 31
          locals = [ class org/scalatest/events/IndentedText, class java/lang/String, class java/lang/String, int ]
          stack = [ class scala/Predef$ ]
        frame_type = 255 /* full_frame */
          offset_delta = 0
          locals = [ class org/scalatest/events/IndentedText, class java/lang/String, class java/lang/String, int ]
          stack = [ class scala/Predef$, int ]
      LineNumberTable:
        line 132: 0
        line 133: 19
        line 132: 41
      LocalVariableTable:
        Start  Length  Slot  Name   Signature
            0      42     0  this   Lorg/scalatest/events/IndentedText;
            0      42     1 formattedText   Ljava/lang/String;
            0      42     2 rawText   Ljava/lang/String;
            0      42     3 indentationLevel   I
    MethodParameters:
      Name                           Flags
      formattedText                  final
      rawText                        final
      indentationLevel               final

  private static java.lang.Object $deserializeLambda$(java.lang.invoke.SerializedLambda);
    descriptor: (Ljava/lang/invoke/SerializedLambda;)Ljava/lang/Object;
    flags: (0x100a) ACC_PRIVATE, ACC_STATIC, ACC_SYNTHETIC
    Code:
      stack=1, locals=1, args_size=1
         0: aload_0
         1: invokedynamic #196,  0            // InvokeDynamic #1:lambdaDeserialize:(Ljava/lang/invoke/SerializedLambda;)Ljava/lang/Object;
         6: areturn
}
InnerClasses:
  public static final #13= #10 of #12;    // Lookup=class java/lang/invoke/MethodHandles$Lookup of class java/lang/invoke/MethodHandles
SourceFile: "Formatter.scala"
RuntimeVisibleAnnotations:
  0: #6(#7=s#8)
    scala.reflect.ScalaSignature(
      bytes="\u0006\u0005\u0005-d\u0001\u0002\u000f\u001e\u0005\u0012B\u0001b\u000f\u0001\u0003\u0016\u0004%\t\u0001\u0010\u0005\t\u000b\u0002\u0011\t\u0012)A\u0005{!Aa\t\u0001BK\u0002\u0013\u0005A\b\u0003\u0005H\u0001\tE\t\u0015!\u0003>\u0011!A\u0005A!f\u0001\n\u0003I\u0005\u0002C\'\u0001\u0005#\u0005\u000b\u0011\u0002&\t\u000b9\u0003A\u0011A(\t\u000fQ\u0003\u0011\u0011!C\u0001+\"9\u0011\fAI\u0001\n\u0003Q\u0006bB3\u0001#\u0003%\tA\u0017\u0005\bM\u0002\t\n\u0011\"\u0001h\u0011\u001dI\u0007!!A\u0005B)DqA\u001d\u0001\u0002\u0002\u0013\u0005\u0011\nC\u0004t\u0001\u0005\u0005I\u0011\u0001;\t\u000fi\u0004\u0011\u0011!C!w\"I\u0011Q\u0001\u0001\u0002\u0002\u0013\u0005\u0011q\u0001\u0005\n\u0003#\u0001\u0011\u0011!C!\u0003\'A\u0011\"a\u0006\u0001\u0003\u0003%\t%!\u0007\t\u0013\u0005m\u0001!!A\u0005B\u0005u\u0001\"CA\u0010\u0001\u0005\u0005I\u0011IA\u0011\u000f%\t)#HA\u0001\u0012\u0003\t9C\u0002\u0005\u001d;\u0005\u0005\t\u0012AA\u0015\u0011\u0019qe\u0003\"\u0001\u0002B!I\u00111\u0004\f\u0002\u0002\u0013\u0015\u0013Q\u0004\u0005\n\u0003\u00072\u0012\u0011!CA\u0003\u000bB\u0011\"!\u0014\u0017\u0003\u0003%\t)a\u0014\t\u0013\u0005\u0005d#!A\u0005\n\u0005\r$\u0001D%oI\u0016tG/\u001a3UKb$(B\u0001\u0010 \u0003\u0019)g/\u001a8ug*\u0011\u0001%I\u0001\ng\u000e\fG.\u0019;fgRT\u0011AI\u0001\u0004_J<7\u0001A\n\u0005\u0001\u0015Js\u0006\u0005\u0002\'O5\tQ$\u0003\u0002);\tIai\u001c:nCR$XM\u001d\t\u0003U5j\u0011a\u000b\u0006\u0002Y\u0005)1oY1mC&\u0011af\u000b\u0002\b!J|G-^2u!\t\u0001\u0004H\u0004\u00022m9\u0011!\'N\u0007\u0002g)\u0011AgI\u0001\u0007yI|w\u000e\u001e \n\u00031J!aN\u0016\u0002\u000fA\f7m[1hK&\u0011\u0011H\u000f\u0002\r\'\u0016\u0014\u0018.\u00197ju\u0006\u0014G.\u001a\u0006\u0003o-\nQBZ8s[\u0006$H/\u001a3UKb$X#A\u001f\u0011\u0005y\u0012eBA A!\t\u00114&\u0003\u0002BW\u00051\u0001K]3eK\u001aL!a\u0011#\u0003\rM#(/\u001b8h\u0015\t\t5&\u0001\bg_Jl\u0017\r\u001e;fIR+\u0007\u0010\u001e\u0011\u0002\u000fI\fw\u000fV3yi\u0006A!/Y<UKb$\b%\u0001\tj]\u0012,g\u000e^1uS>tG*\u001a<fYV\t!\n\u0005\u0002+\u0017&\u0011Aj\u000b\u0002\u0004\u0013:$\u0018!E5oI\u0016tG/\u0019;j_:dUM^3mA\u00051A(\u001b8jiz\"B\u0001U)S\'B\u0011a\u0005\u0001\u0005\u0006w\u001d\u0001\r!\u0010\u0005\u0006\r\u001e\u0001\r!\u0010\u0005\u0006\u0011\u001e\u0001\rAS\u0001\u0005G>\u0004\u0018\u0010\u0006\u0003Q-^C\u0006bB\u001e\t!\u0003\u0005\r!\u0010\u0005\b\r\"\u0001\n\u00111\u0001>\u0011\u001dA\u0005\u0002%AA\u0002)\u000babY8qs\u0012\"WMZ1vYR$\u0013\'F\u0001\\U\tiDlK\u0001^!\tq6-D\u0001`\u0015\t\u0001\u0017-A\u0005v]\u000eDWmY6fI*\u0011!mK\u0001\u000bC:tw\u000e^1uS>t\u0017B\u00013`\u0005E)hn\u00195fG.,GMV1sS\u0006t7-Z\u0001\u000fG>\u0004\u0018\u0010\n3fM\u0006,H\u000e\u001e\u00133\u00039\u0019w\u000e]=%I\u00164\u0017-\u001e7uIM*\u0012\u0001\u001b\u0016\u0003\u0015r\u000bQ\u0002\u001d:pIV\u001cG\u000f\u0015:fM&DX#A6\u0011\u00051\fX\"A7\u000b\u00059|\u0017\u0001\u00027b]\u001eT\u0011\u0001]\u0001\u0005U\u00064\u0018-\u0003\u0002D[\u0006a\u0001O]8ek\u000e$\u0018I]5us\u0006q\u0001O]8ek\u000e$X\t\\3nK:$HCA;y!\tQc/\u0003\u0002xW\t\u0019\u0011I\\=\t\u000fet\u0011\u0011!a\u0001\u0015\u0006\u0019\u0001\u0010J\u0019\u0002\u001fA\u0014x\u000eZ;di&#XM]1u_J,\u0012\u0001 \t\u0005{\u0006\u0005Q/D\u0001\u007f\u0015\ty8&\u0001\u0006d_2dWm\u0019;j_:L1!a\u0001\u007f\u0005!IE/\u001a:bi>\u0014\u0018\u0001C2b]\u0016\u000bX/\u00197\u0015\t\u0005%\u0011q\u0002\t\u0004U\u0005-\u0011bAA\u0007W\t9!i\\8mK\u0006t\u0007bB=\u0011\u0003\u0003\u0005\r!^\u0001\u0013aJ|G-^2u\u000b2,W.\u001a8u\u001d\u0006lW\rF\u0002l\u0003+Aq!_\t\u0002\u0002\u0003\u0007!*\u0001\u0005iCND7i\u001c3f)\u0005Q\u0015\u0001\u0003;p\'R\u0014\u0018N\\4\u0015\u0003-\fa!Z9vC2\u001cH\u0003BA\u0005\u0003GAq!\u001f\u000b\u0002\u0002\u0003\u0007Q/\u0001\u0007J]\u0012,g\u000e^3e)\u0016DH\u000f\u0005\u0002\'-M)a#a\u000b\u00028AA\u0011QFA\u001a{uR\u0005+\u0004\u0002\u00020)\u0019\u0011\u0011G\u0016\u0002\u000fI,h\u000e^5nK&!\u0011QGA\u0018\u0005E\t%m\u001d;sC\u000e$h)\u001e8di&|gn\r\t\u0005\u0003s\ty$\u0004\u0002\u0002<)\u0019\u0011QH8\u0002\u0005%|\u0017bA\u001d\u0002<Q\u0011\u0011qE\u0001\u0006CB\u0004H.\u001f\u000b\b!\u0006\u001d\u0013\u0011JA&\u0011\u0015Y\u0014\u00041\u0001>\u0011\u00151\u0015\u00041\u0001>\u0011\u0015A\u0015\u00041\u0001K\u0003\u001d)h.\u00199qYf$B!!\u0015\u0002^A)!&a\u0015\u0002X%\u0019\u0011QK\u0016\u0003\r=\u0003H/[8o!\u0019Q\u0013\u0011L\u001f>\u0015&\u0019\u00111L\u0016\u0003\rQ+\b\u000f\\34\u0011!\tyFGA\u0001\u0002\u0004\u0001\u0016a\u0001=%a\u0005aqO]5uKJ+\u0007\u000f\\1dKR\u0011\u0011Q\r\t\u0004Y\u0006\u001d\u0014bAA5[\n1qJ\u00196fGR\u0004"
    )
BootstrapMethods:
  0: #177 REF_invokeStatic java/lang/invoke/LambdaMetafactory.altMetafactory:(Ljava/lang/invoke/MethodHandles$Lookup;Ljava/lang/String;Ljava/lang/invoke/MethodType;[Ljava/lang/Object;)Ljava/lang/invoke/CallSite;
    Method arguments:
      #164 ()Ljava/lang/Object;
      #167 REF_invokeStatic org/scalatest/events/IndentedText.$anonfun$new$1:(Lorg/scalatest/events/IndentedText;)Ljava/lang/String;
      #168 ()Ljava/lang/String;
      #169 5
      #170 1
      #168 ()Ljava/lang/String;
  1: #193 REF_invokeStatic scala/runtime/LambdaDeserialize.bootstrap:(Ljava/lang/invoke/MethodHandles$Lookup;Ljava/lang/String;Ljava/lang/invoke/MethodType;[Ljava/lang/invoke/MethodHandle;)Ljava/lang/invoke/CallSite;
    Method arguments:
      #167 REF_invokeStatic org/scalatest/events/IndentedText.$anonfun$new$1:(Lorg/scalatest/events/IndentedText;)Ljava/lang/String;
  ScalaInlineInfo: length = 0x5E (unknown attribute)
   01 01 00 12 00 87 00 88 01 00 37 00 38 01 00 64
   00 65 01 00 36 00 21 01 00 3B 00 2D 01 00 3E 00
   2D 01 00 41 00 33 01 00 84 00 65 01 00 0E 00 2D
   01 00 6E 00 33 01 00 11 00 33 01 00 47 00 33 01
   00 48 00 49 01 00 67 00 68 01 00 58 00 59 01 00
   44 00 2D 01 00 10 00 2D 01 00 7F 00 2D 01
  ScalaSig: length = 0x3 (unknown attribute)
   05 02 00
