Classfile /Users/mw/Projects/slang-braindump/.jar/jar11/assemble/slang-braindump/assemble/content/org/scalatest/events/MarkupProvided.class
  Last modified May 29, 2022; size 16799 bytes
  SHA-256 checksum 725f4b95729e1b487ae3fe945148928598c6aaa104cae6c7e91643d896b19f68
  Compiled from "Event.scala"
public final class org.scalatest.events.MarkupProvided extends org.scalatest.events.Event implements org.scalatest.events.RecordableEvent
  minor version: 0
  major version: 52
  flags: (0x0031) ACC_PUBLIC, ACC_FINAL, ACC_SUPER
  this_class: #2                          // org/scalatest/events/MarkupProvided
  super_class: #4                         // org/scalatest/events/Event
  interfaces: 1, fields: 8, methods: 45, attributes: 5
Constant pool:
    #1 = Utf8               org/scalatest/events/MarkupProvided
    #2 = Class              #1            // org/scalatest/events/MarkupProvided
    #3 = Utf8               org/scalatest/events/Event
    #4 = Class              #3            // org/scalatest/events/Event
    #5 = Utf8               org/scalatest/events/RecordableEvent
    #6 = Class              #5            // org/scalatest/events/RecordableEvent
    #7 = Utf8               Event.scala
    #8 = Utf8               Lscala/reflect/ScalaSignature;
    #9 = Utf8               bytes
   #10 = Utf8               \u0006\u0005\tec\u0001\u0002\u001d:\u0005\u0002C\u0001B\u0017\u0001\u0003\u0016\u0004%\ta\u0017\u0005\t?\u0002\u0011\t\u0012)A\u00059\"A\u0001\r\u0001BK\u0002\u0013\u0005\u0011\r\u0003\u0005k\u0001\tE\t\u0015!\u0003c\u0011!Y\u0007A!f\u0001\n\u0003a\u0007\u0002C:\u0001\u0005#\u0005\u000b\u0011B7\t\u0011Q\u0004!Q3A\u0005\u0002UD\u0001B\u001f\u0001\u0003\u0012\u0003\u0006IA\u001e\u0005\tw\u0002\u0011)\u001a!C\u0001y\"I\u00111\u0001\u0001\u0003\u0012\u0003\u0006I! \u0005\u000b\u0003\u000b\u0001!Q3A\u0005\u0002\u0005\u001d\u0001BCA\t\u0001\tE\t\u0015!\u0003\u0002\n!I\u00111\u0003\u0001\u0003\u0016\u0004%\t!\u0019\u0005\n\u0003+\u0001!\u0011#Q\u0001\n\tD!\"a\u0006\u0001\u0005+\u0007I\u0011AA\r\u0011)\t\t\u0003\u0001B\tB\u0003%\u00111\u0004\u0005\b\u0003G\u0001A\u0011AA\u0013\u0011!\tI\u0004\u0001C\u0001w\u0005m\u0002bBA%\u0001\u0011\u00051(\u0019\u0005\t\u0003\u0017\u0002A\u0011A\u001d\u0002N!I\u00111\u000b\u0001\u0002\u0002\u0013\u0005\u0011Q\u000b\u0005\n\u0003O\u0002\u0011\u0013!C\u0001\u0003SB\u0011\"a \u0001#\u0003%\t!!!\t\u0013\u0005\u0015\u0005!%A\u0005\u0002\u0005\u001d\u0005\"CAF\u0001E\u0005I\u0011AAG\u0011%\t\t\nAI\u0001\n\u0003\t\u0019\nC\u0005\u0002\u0018\u0002\t\n\u0011\"\u0001\u0002\u001a\"I\u0011Q\u0014\u0001\u0012\u0002\u0013\u0005\u0011\u0011\u0011\u0005\n\u0003?\u0003\u0011\u0013!C\u0001\u0003CC\u0011\"!*\u0001\u0003\u0003%\t%a*\t\u0013\u0005]\u0006!!A\u0005\u0002\u0005e\u0006\"CAa\u0001\u0005\u0005I\u0011AAb\u0011%\tI\rAA\u0001\n\u0003\nY\rC\u0005\u0002Z\u0002\t\t\u0011\"\u0001\u0002\\\"I\u0011Q\u001d\u0001\u0002\u0002\u0013\u0005\u0013q\u001d\u0005\n\u0003W\u0004\u0011\u0011!C!\u0003[D\u0011\"a<\u0001\u0003\u0003%\t%!=\t\u0013\u0005M\b!!A\u0005B\u0005Ux!CA}s\u0005\u0005\t\u0012AA~\r!A\u0014(!A\t\u0002\u0005u\bbBA\u0012Q\u0011\u0005!Q\u0003\u0005\n\u0003_D\u0013\u0011!C#\u0003cD\u0011Ba\u0006)\u0003\u0003%\tI!\u0007\t\u0013\t-\u0002&%A\u0005\u0002\u00055\u0005\"\u0003B\u0017QE\u0005I\u0011AAJ\u0011%\u0011y\u0003KI\u0001\n\u0003\tI\nC\u0005\u00032!\n\n\u0011\"\u0001\u0002\u0002\"I!1\u0007\u0015\u0012\u0002\u0013\u0005\u0011\u0011\u0015\u0005\n\u0005kA\u0013\u0011!CA\u0005oA\u0011B!\u0012)#\u0003%\t!!$\t\u0013\t\u001d\u0003&%A\u0005\u0002\u0005M\u0005\"\u0003B%QE\u0005I\u0011AAM\u0011%\u0011Y\u0005KI\u0001\n\u0003\t\t\tC\u0005\u0003N!\n\n\u0011\"\u0001\u0002\"\"I!q\n\u0015\u0002\u0002\u0013%!\u0011\u000b\u0002\u000f\u001b\u0006\u00148.\u001e9Qe>4\u0018\u000eZ3e\u0015\tQ4(\u0001\u0004fm\u0016tGo\u001d\u0006\u0003yu\n\u0011b]2bY\u0006$Xm\u001d;\u000b\u0003y\n1a\u001c:h\u0007\u0001\u0019R\u0001A!F\u0011:\u0003\"AQ\"\u000e\u0003eJ!\u0001R\u001d\u0003\u000b\u00153XM\u001c;\u0011\u0005\t3\u0015BA$:\u0005=\u0011VmY8sI\u0006\u0014G.Z#wK:$\bCA%M\u001b\u0005Q%\"A&\u0002\u000bM\u001c\u0017\r\\1\n\u00055S%a\u0002)s_\u0012,8\r\u001e\t\u0003\u001f^s!\u0001U+\u000f\u0005E#V\"\u0001*\u000b\u0005M{\u0014A\u0002\u001fs_>$h(C\u0001L\u0013\t1&*A\u0004qC\u000e\\\u0017mZ3\n\u0005aK&\u0001D*fe&\fG.\u001b>bE2,\'B\u0001,K\u0003\u001dy\'\u000fZ5oC2,\u0012\u0001\u0018\t\u0003\u0005vK!AX\u001d\u0003\u000f=\u0013H-\u001b8bY\u0006AqN\u001d3j]\u0006d\u0007%\u0001\u0003uKb$X#\u00012\u0011\u0005\r<gB\u00013f!\t\t&*\u0003\u0002g\u0015\u00061\u0001K]3eK\u001aL!\u0001[5\u0003\rM#(/\u001b8h\u0015\t1\'*A\u0003uKb$\b%\u0001\u0005oC6,\u0017J\u001c4p+\u0005i\u0007cA%oa&\u0011qN\u0013\u0002\u0007\u001fB$\u0018n\u001c8\u0011\u0005\t\u000b\u0018B\u0001::\u0005!q\u0015-\\3J]\u001a|\u0017!\u00038b[\u0016LeNZ8!\u0003%1wN]7biR,\'/F\u0001w!\rIen\u001e\t\u0003\u0005bL!!_\u001d\u0003\u0013\u0019{\'/\\1ui\u0016\u0014\u0018A\u00034pe6\fG\u000f^3sA\u0005AAn\\2bi&|g.F\u0001~!\rIeN \t\u0003\u0005~L1!!\u0001:\u0005!aunY1uS>t\u0017!\u00037pG\u0006$\u0018n\u001c8!\u0003\u001d\u0001\u0018-\u001f7pC\u0012,\"!!\u0003\u0011\t%s\u00171\u0002\t\u0004\u0013\u00065\u0011bAA\b\u0015\n\u0019\u0011I\\=\u0002\u0011A\f\u0017\u0010\\8bI\u0002\n!\u0002\u001e5sK\u0006$g*Y7f\u0003-!\bN]3bI:\u000bW.\u001a\u0011\u0002\u0013QLW.Z*uC6\u0004XCAA\u000e!\rI\u0015QD\u0005\u0004\u0003?Q%\u0001\u0002\'p]\u001e\f!\u0002^5nKN#\u0018-\u001c9!\u0003\u0019a\u0014N\\5u}Q\u0011\u0012qEA\u0015\u0003W\ti#a\f\u00022\u0005M\u0012QGA\u001c!\t\u0011\u0005\u0001C\u0003[#\u0001\u0007A\fC\u0003a#\u0001\u0007!\rC\u0003l#\u0001\u0007Q\u000eC\u0004u#A\u0005\t\u0019\u0001<\t\u000fm\f\u0002\u0013!a\u0001{\"I\u0011QA\t\u0011\u0002\u0003\u0007\u0011\u0011\u0002\u0005\t\u0003\'\t\u0002\u0013!a\u0001E\"I\u0011qC\t\u0011\u0002\u0003\u0007\u00111D\u0001\u0006i>DV\u000e\\\u000b\u0003\u0003{\u0001B!a\u0010\u0002F5\u0011\u0011\u0011\t\u0006\u0004\u0003\u0007R\u0015a\u0001=nY&!\u0011qIA!\u0005\u0011)E.Z7\u0002\rQ|\'j]8o\u0003-9\u0018\u000e\u001e5QCfdw.\u00193\u0015\t\u0005\u001d\u0012q\n\u0005\b\u0003#\"\u0002\u0019AA\u0005\u0003)qWm\u001e)bs2|\u0017\rZ\u0001\u0005G>\u0004\u0018\u0010\u0006\n\u0002(\u0005]\u0013\u0011LA.\u0003;\ny&!\u0019\u0002d\u0005\u0015\u0004b\u0002.\u0016!\u0003\u0005\r\u0001\u0018\u0005\bAV\u0001\n\u00111\u0001c\u0011\u001dYW\u0003%AA\u00025Dq\u0001^\u000b\u0011\u0002\u0003\u0007a\u000fC\u0004|+A\u0005\t\u0019A?\t\u0013\u0005\u0015Q\u0003%AA\u0002\u0005%\u0001\u0002CA\n+A\u0005\t\u0019\u00012\t\u0013\u0005]Q\u0003%AA\u0002\u0005m\u0011AD2paf$C-\u001a4bk2$H%M\u000b\u0003\u0003WR3\u0001XA7W\t\ty\u0007\u0005\u0003\u0002r\u0005mTBAA:\u0015\u0011\t)(a\u001e\u0002\u0013Ut7\r[3dW\u0016$\'bAA=\u0015\u0006Q\u0011M\u001c8pi\u0006$\u0018n\u001c8\n\t\u0005u\u00141\u000f\u0002\u0012k:\u001c\u0007.Z2lK\u00124\u0016M]5b]\u000e,\u0017AD2paf$C-\u001a4bk2$HEM\u000b\u0003\u0003\u0007S3AYA7\u00039\u0019w\u000e]=%I\u00164\u0017-\u001e7uIM*\"!!#+\u00075\fi\'\u0001\bd_BLH\u0005Z3gCVdG\u000f\n\u001b\u0016\u0005\u0005=%f\u0001<\u0002n\u0005q1m\u001c9zI\u0011,g-Y;mi\u0012*TCAAKU\ri\u0018QN\u0001\u000fG>\u0004\u0018\u0010\n3fM\u0006,H\u000e\u001e\u00137+\t\tYJ\u000b\u0003\u0002\n\u00055\u0014AD2paf$C-\u001a4bk2$HeN\u0001\u000fG>\u0004\u0018\u0010\n3fM\u0006,H\u000e\u001e\u00139+\t\t\u0019K\u000b\u0003\u0002\u001c\u00055\u0014!\u00049s_\u0012,8\r\u001e)sK\u001aL\u00070\u0006\u0002\u0002*B!\u00111VA[\u001b\t\tiK\u0003\u0003\u00020\u0006E\u0016\u0001\u00027b]\u001eT!!a-\u0002\t)\fg/Y\u0005\u0004Q\u00065\u0016\u0001\u00049s_\u0012,8\r^!sSRLXCAA^!\rI\u0015QX\u0005\u0004\u0003\u007fS%aA%oi\u0006q\u0001O]8ek\u000e$X\t\\3nK:$H\u0003BA\u0006\u0003\u000bD\u0011\"a2!\u0003\u0003\u0005\r!a/\u0002\u0007a$\u0013\'A\bqe>$Wo\u0019;Ji\u0016\u0014\u0018\r^8s+\t\ti\r\u0005\u0004\u0002P\u0006U\u00171B\u0007\u0003\u0003#T1!a5K\u0003)\u0019w\u000e\u001c7fGRLwN\\\u0005\u0005\u0003/\f\tN\u0001\u0005Ji\u0016\u0014\u0018\r^8s\u0003!\u0019\u0017M\\#rk\u0006dG\u0003BAo\u0003G\u00042!SAp\u0013\r\t\tO\u0013\u0002\b\u0005>|G.Z1o\u0011%\t9MIA\u0001\u0002\u0004\tY!\u0001\nqe>$Wo\u0019;FY\u0016lWM\u001c;OC6,G\u0003BAU\u0003SD\u0011\"a2$\u0003\u0003\u0005\r!a/\u0002\u0011!\f7\u000f[\"pI\u0016$\"!a/\u0002\u0011Q|7\u000b\u001e:j]\u001e$\"!!+\u0002\r\u0015\fX/\u00197t)\u0011\ti.a>\t\u0013\u0005\u001dg%!AA\u0002\u0005-\u0011AD\'be.,\b\u000f\u0015:pm&$W\r\u001a\t\u0003\u0005\"\u001aR\u0001KA\u0000\u0005\u0017\u0001\u0002C!\u0001\u0003\bq\u0013WN^?\u0002\n\t\fY\"a\n\u000e\u0005\t\r!b\u0001B\u0003\u0015\u00069!/\u001e8uS6,\u0017\u0002\u0002B\u0005\u0005\u0007\u0011\u0011#\u00112tiJ\f7\r\u001e$v]\u000e$\u0018n\u001c89!\u0011\u0011iAa\u0005\u000e\u0005\t=!\u0002\u0002B\t\u0003c\u000b!![8\n\u0007a\u0013y\u0001\u0006\u0002\u0002|\u0006)\u0011\r\u001d9msR\u0011\u0012q\u0005B\u000e\u0005;\u0011yB!\t\u0003$\t\u0015\"q\u0005B\u0015\u0011\u0015Q6\u00061\u0001]\u0011\u0015\u00017\u00061\u0001c\u0011\u0015Y7\u00061\u0001n\u0011\u001d!8\u0006%AA\u0002YDqa_\u0016\u0011\u0002\u0003\u0007Q\u0010C\u0005\u0002\u0006-\u0002\n\u00111\u0001\u0002\n!A\u00111C\u0016\u0011\u0002\u0003\u0007!\rC\u0005\u0002\u0018-\u0002\n\u00111\u0001\u0002\u001c\u0005y\u0011\r\u001d9ms\u0012\"WMZ1vYR$C\'A\bbaBd\u0017\u0010\n3fM\u0006,H\u000e\u001e\u00136\u0003=\t\u0007\u000f\u001d7zI\u0011,g-Y;mi\u00122\u0014aD1qa2LH\u0005Z3gCVdG\u000fJ\u001c\u0002\u001f\u0005\u0004\b\u000f\\=%I\u00164\u0017-\u001e7uIa\nq!\u001e8baBd\u0017\u0010\u0006\u0003\u0003:\t\u0005\u0003\u0003B%o\u0005w\u0001R\"\u0013B\u001f9\nlg/`A\u0005E\u0006m\u0011b\u0001B \u0015\n1A+\u001e9mKbB\u0011Ba\u00112\u0003\u0003\u0005\r!a\n\u0002\u0007a$\u0003\'A\u000e%Y\u0016\u001c8/\u001b8ji\u0012:\'/Z1uKJ$C-\u001a4bk2$H\u0005N\u0001\u001cI1,7o]5oSR$sM]3bi\u0016\u0014H\u0005Z3gCVdG\u000fJ\u001b\u00027\u0011bWm]:j]&$He\u001a:fCR,\'\u000f\n3fM\u0006,H\u000e\u001e\u00137\u0003m!C.Z:tS:LG\u000fJ4sK\u0006$XM\u001d\u0013eK\u001a\fW\u000f\u001c;%o\u0005YB\u0005\\3tg&t\u0017\u000e\u001e\u0013he\u0016\fG/\u001a:%I\u00164\u0017-\u001e7uIa\nAb\u001e:ji\u0016\u0014V\r\u001d7bG\u0016$\"Aa\u0015\u0011\t\u0005-&QK\u0005\u0005\u0005/\niK\u0001\u0004PE*,7\r\u001e
   #11 = Utf8               org/scalactic/Requirements$RequirementsHelper
   #12 = Class              #11           // org/scalactic/Requirements$RequirementsHelper
   #13 = Utf8               org/scalactic/Requirements
   #14 = Class              #13           // org/scalactic/Requirements
   #15 = Utf8               RequirementsHelper
   #16 = Utf8               org/scalatest/events/Event$EventJsonHelper$
   #17 = Class              #16           // org/scalatest/events/Event$EventJsonHelper$
   #18 = Utf8               EventJsonHelper$
   #19 = Utf8               org/scalatest/events/Event$EventXmlHelper$
   #20 = Class              #19           // org/scalatest/events/Event$EventXmlHelper$
   #21 = Utf8               EventXmlHelper$
   #22 = Utf8               ordinal
   #23 = Utf8               Lorg/scalatest/events/Ordinal;
   #24 = Utf8               text
   #25 = Utf8               Ljava/lang/String;
   #26 = Utf8               nameInfo
   #27 = Utf8               Lscala/Option;
   #28 = Utf8               Lscala/Option<Lorg/scalatest/events/NameInfo;>;
   #29 = Utf8               formatter
   #30 = Utf8               Lscala/Option<Lorg/scalatest/events/Formatter;>;
   #31 = Utf8               location
   #32 = Utf8               Lscala/Option<Lorg/scalatest/events/Location;>;
   #33 = Utf8               payload
   #34 = Utf8               Lscala/Option<Ljava/lang/Object;>;
   #35 = Utf8               threadName
   #36 = Utf8               timeStamp
   #37 = Utf8               J
   #38 = Utf8               $lessinit$greater$default$8
   #39 = Utf8               ()J
   #40 = Utf8               org/scalatest/events/MarkupProvided$
   #41 = Class              #40           // org/scalatest/events/MarkupProvided$
   #42 = Utf8               MODULE$
   #43 = Utf8               Lorg/scalatest/events/MarkupProvided$;
   #44 = NameAndType        #42:#43       // MODULE$:Lorg/scalatest/events/MarkupProvided$;
   #45 = Fieldref           #41.#44       // org/scalatest/events/MarkupProvided$.MODULE$:Lorg/scalatest/events/MarkupProvided$;
   #46 = NameAndType        #38:#39       // $lessinit$greater$default$8:()J
   #47 = Methodref          #41.#46       // org/scalatest/events/MarkupProvided$.$lessinit$greater$default$8:()J
   #48 = Utf8               $lessinit$greater$default$7
   #49 = Utf8               ()Ljava/lang/String;
   #50 = NameAndType        #48:#49       // $lessinit$greater$default$7:()Ljava/lang/String;
   #51 = Methodref          #41.#50       // org/scalatest/events/MarkupProvided$.$lessinit$greater$default$7:()Ljava/lang/String;
   #52 = Utf8               $lessinit$greater$default$6
   #53 = Utf8               ()Lscala/Option;
   #54 = Utf8               ()Lscala/Option<Ljava/lang/Object;>;
   #55 = NameAndType        #52:#53       // $lessinit$greater$default$6:()Lscala/Option;
   #56 = Methodref          #41.#55       // org/scalatest/events/MarkupProvided$.$lessinit$greater$default$6:()Lscala/Option;
   #57 = Utf8               $lessinit$greater$default$5
   #58 = Utf8               ()Lscala/Option<Lorg/scalatest/events/Location;>;
   #59 = NameAndType        #57:#53       // $lessinit$greater$default$5:()Lscala/Option;
   #60 = Methodref          #41.#59       // org/scalatest/events/MarkupProvided$.$lessinit$greater$default$5:()Lscala/Option;
   #61 = Utf8               $lessinit$greater$default$4
   #62 = Utf8               ()Lscala/Option<Lorg/scalatest/events/Formatter;>;
   #63 = NameAndType        #61:#53       // $lessinit$greater$default$4:()Lscala/Option;
   #64 = Methodref          #41.#63       // org/scalatest/events/MarkupProvided$.$lessinit$greater$default$4:()Lscala/Option;
   #65 = Utf8               unapply
   #66 = Utf8               (Lorg/scalatest/events/MarkupProvided;)Lscala/Option;
   #67 = Utf8               (Lorg/scalatest/events/MarkupProvided;)Lscala/Option<Lscala/Tuple8<Lorg/scalatest/events/Ordinal;Ljava/lang/String;Lscala/Option<Lorg/scalatest/events/NameInfo;>;Lscala/Option<Lorg/scalatest/events/Formatter;>;Lscala/Option<Lorg/scalatest/events/Location;>;Lscala/Option<Ljava/lang/Object;>;Ljava/lang/String;Ljava/lang/Object;>;>;
   #68 = Utf8               x$0
   #69 = NameAndType        #65:#66       // unapply:(Lorg/scalatest/events/MarkupProvided;)Lscala/Option;
   #70 = Methodref          #41.#69       // org/scalatest/events/MarkupProvided$.unapply:(Lorg/scalatest/events/MarkupProvided;)Lscala/Option;
   #71 = Utf8               Lorg/scalatest/events/MarkupProvided;
   #72 = Utf8               apply$default$8
   #73 = NameAndType        #72:#39       // apply$default$8:()J
   #74 = Methodref          #41.#73       // org/scalatest/events/MarkupProvided$.apply$default$8:()J
   #75 = Utf8               apply$default$7
   #76 = NameAndType        #75:#49       // apply$default$7:()Ljava/lang/String;
   #77 = Methodref          #41.#76       // org/scalatest/events/MarkupProvided$.apply$default$7:()Ljava/lang/String;
   #78 = Utf8               apply$default$6
   #79 = NameAndType        #78:#53       // apply$default$6:()Lscala/Option;
   #80 = Methodref          #41.#79       // org/scalatest/events/MarkupProvided$.apply$default$6:()Lscala/Option;
   #81 = Utf8               apply$default$5
   #82 = NameAndType        #81:#53       // apply$default$5:()Lscala/Option;
   #83 = Methodref          #41.#82       // org/scalatest/events/MarkupProvided$.apply$default$5:()Lscala/Option;
   #84 = Utf8               apply$default$4
   #85 = NameAndType        #84:#53       // apply$default$4:()Lscala/Option;
   #86 = Methodref          #41.#85       // org/scalatest/events/MarkupProvided$.apply$default$4:()Lscala/Option;
   #87 = Utf8               apply
   #88 = Utf8               (Lorg/scalatest/events/Ordinal;Ljava/lang/String;Lscala/Option;Lscala/Option;Lscala/Option;Lscala/Option;Ljava/lang/String;J)Lorg/scalatest/events/MarkupProvided;
   #89 = Utf8               (Lorg/scalatest/events/Ordinal;Ljava/lang/String;Lscala/Option<Lorg/scalatest/events/NameInfo;>;Lscala/Option<Lorg/scalatest/events/Formatter;>;Lscala/Option<Lorg/scalatest/events/Location;>;Lscala/Option<Ljava/lang/Object;>;Ljava/lang/String;J)Lorg/scalatest/events/MarkupProvided;
   #90 = NameAndType        #87:#88       // apply:(Lorg/scalatest/events/Ordinal;Ljava/lang/String;Lscala/Option;Lscala/Option;Lscala/Option;Lscala/Option;Ljava/lang/String;J)Lorg/scalatest/events/MarkupProvided;
   #91 = Methodref          #41.#90       // org/scalatest/events/MarkupProvided$.apply:(Lorg/scalatest/events/Ordinal;Ljava/lang/String;Lscala/Option;Lscala/Option;Lscala/Option;Lscala/Option;Ljava/lang/String;J)Lorg/scalatest/events/MarkupProvided;
   #92 = Utf8               tupled
   #93 = Utf8               ()Lscala/Function1;
   #94 = Utf8               ()Lscala/Function1<Lscala/Tuple8<Lorg/scalatest/events/Ordinal;Ljava/lang/String;Lscala/Option<Lorg/scalatest/events/NameInfo;>;Lscala/Option<Lorg/scalatest/events/Formatter;>;Lscala/Option<Lorg/scalatest/events/Location;>;Lscala/Option<Ljava/lang/Object;>;Ljava/lang/String;Ljava/lang/Object;>;Lorg/scalatest/events/MarkupProvided;>;
   #95 = NameAndType        #92:#93       // tupled:()Lscala/Function1;
   #96 = Methodref          #41.#95       // org/scalatest/events/MarkupProvided$.tupled:()Lscala/Function1;
   #97 = Utf8               curried
   #98 = Utf8               ()Lscala/Function1<Lorg/scalatest/events/Ordinal;Lscala/Function1<Ljava/lang/String;Lscala/Function1<Lscala/Option<Lorg/scalatest/events/NameInfo;>;Lscala/Function1<Lscala/Option<Lorg/scalatest/events/Formatter;>;Lscala/Function1<Lscala/Option<Lorg/scalatest/events/Location;>;Lscala/Function1<Lscala/Option<Ljava/lang/Object;>;Lscala/Function1<Ljava/lang/String;Lscala/Function1<Ljava/lang/Object;Lorg/scalatest/events/MarkupProvided;>;>;>;>;>;>;>;>;
   #99 = NameAndType        #97:#93       // curried:()Lscala/Function1;
  #100 = Methodref          #41.#99       // org/scalatest/events/MarkupProvided$.curried:()Lscala/Function1;
  #101 = Utf8               ()Lorg/scalatest/events/Ordinal;
  #102 = NameAndType        #22:#23       // ordinal:Lorg/scalatest/events/Ordinal;
  #103 = Fieldref           #2.#102       // org/scalatest/events/MarkupProvided.ordinal:Lorg/scalatest/events/Ordinal;
  #104 = Utf8               this
  #105 = NameAndType        #24:#25       // text:Ljava/lang/String;
  #106 = Fieldref           #2.#105       // org/scalatest/events/MarkupProvided.text:Ljava/lang/String;
  #107 = Utf8               ()Lscala/Option<Lorg/scalatest/events/NameInfo;>;
  #108 = NameAndType        #26:#27       // nameInfo:Lscala/Option;
  #109 = Fieldref           #2.#108       // org/scalatest/events/MarkupProvided.nameInfo:Lscala/Option;
  #110 = NameAndType        #29:#27       // formatter:Lscala/Option;
  #111 = Fieldref           #2.#110       // org/scalatest/events/MarkupProvided.formatter:Lscala/Option;
  #112 = NameAndType        #31:#27       // location:Lscala/Option;
  #113 = Fieldref           #2.#112       // org/scalatest/events/MarkupProvided.location:Lscala/Option;
  #114 = NameAndType        #33:#27       // payload:Lscala/Option;
  #115 = Fieldref           #2.#114       // org/scalatest/events/MarkupProvided.payload:Lscala/Option;
  #116 = NameAndType        #35:#25       // threadName:Ljava/lang/String;
  #117 = Fieldref           #2.#116       // org/scalatest/events/MarkupProvided.threadName:Ljava/lang/String;
  #118 = NameAndType        #36:#37       // timeStamp:J
  #119 = Fieldref           #2.#118       // org/scalatest/events/MarkupProvided.timeStamp:J
  #120 = Utf8               toXml
  #121 = Utf8               ()Lscala/xml/Elem;
  #122 = Utf8               scala/xml/Elem
  #123 = Class              #122          // scala/xml/Elem
  #124 = Utf8               MarkupProvided
  #125 = String             #124          // MarkupProvided
  #126 = Utf8               scala/xml/Null$
  #127 = Class              #126          // scala/xml/Null$
  #128 = Utf8               Lscala/xml/Null$;
  #129 = NameAndType        #42:#128      // MODULE$:Lscala/xml/Null$;
  #130 = Fieldref           #127.#129     // scala/xml/Null$.MODULE$:Lscala/xml/Null$;
  #131 = Utf8               scala/xml/TopScope$
  #132 = Class              #131          // scala/xml/TopScope$
  #133 = Utf8               Lscala/xml/TopScope$;
  #134 = NameAndType        #42:#133      // MODULE$:Lscala/xml/TopScope$;
  #135 = Fieldref           #132.#134     // scala/xml/TopScope$.MODULE$:Lscala/xml/TopScope$;
  #136 = Utf8               scala/xml/NodeSeq$
  #137 = Class              #136          // scala/xml/NodeSeq$
  #138 = Utf8               Lscala/xml/NodeSeq$;
  #139 = NameAndType        #42:#138      // MODULE$:Lscala/xml/NodeSeq$;
  #140 = Fieldref           #137.#139     // scala/xml/NodeSeq$.MODULE$:Lscala/xml/NodeSeq$;
  #141 = Utf8               scala/xml/NodeBuffer
  #142 = Class              #141          // scala/xml/NodeBuffer
  #143 = Utf8               <init>
  #144 = Utf8               ()V
  #145 = NameAndType        #143:#144     // "<init>":()V
  #146 = Methodref          #142.#145     // scala/xml/NodeBuffer."<init>":()V
  #147 = Utf8               scala/xml/Text
  #148 = Class              #147          // scala/xml/Text
  #149 = Utf8               \n
  #150 = String             #149          // \n
  #151 = Utf8               (Ljava/lang/String;)V
  #152 = NameAndType        #143:#151     // "<init>":(Ljava/lang/String;)V
  #153 = Methodref          #148.#152     // scala/xml/Text."<init>":(Ljava/lang/String;)V
  #154 = Utf8               $amp$plus
  #155 = Utf8               (Ljava/lang/Object;)Lscala/xml/NodeBuffer;
  #156 = NameAndType        #154:#155     // $amp$plus:(Ljava/lang/Object;)Lscala/xml/NodeBuffer;
  #157 = Methodref          #142.#156     // scala/xml/NodeBuffer.$amp$plus:(Ljava/lang/Object;)Lscala/xml/NodeBuffer;
  #158 = String             #22           // ordinal
  #159 = Utf8               \n
  #160 = String             #159          // \n
  #161 = Utf8               runStamp
  #162 = String             #161          // runStamp
  #163 = NameAndType        #22:#101      // ordinal:()Lorg/scalatest/events/Ordinal;
  #164 = Methodref          #2.#163       // org/scalatest/events/MarkupProvided.ordinal:()Lorg/scalatest/events/Ordinal;
  #165 = Utf8               org/scalatest/events/Ordinal
  #166 = Class              #165          // org/scalatest/events/Ordinal
  #167 = Utf8               ()I
  #168 = NameAndType        #161:#167     // runStamp:()I
  #169 = Methodref          #166.#168     // org/scalatest/events/Ordinal.runStamp:()I
  #170 = Utf8               scala/runtime/BoxesRunTime
  #171 = Class              #170          // scala/runtime/BoxesRunTime
  #172 = Utf8               boxToInteger
  #173 = Utf8               (I)Ljava/lang/Integer;
  #174 = NameAndType        #172:#173     // boxToInteger:(I)Ljava/lang/Integer;
  #175 = Methodref          #171.#174     // scala/runtime/BoxesRunTime.boxToInteger:(I)Ljava/lang/Integer;
  #176 = Utf8               seqToNodeSeq
  #177 = Utf8               (Lscala/collection/Seq;)Lscala/xml/NodeSeq;
  #178 = NameAndType        #176:#177     // seqToNodeSeq:(Lscala/collection/Seq;)Lscala/xml/NodeSeq;
  #179 = Methodref          #137.#178     // scala/xml/NodeSeq$.seqToNodeSeq:(Lscala/collection/Seq;)Lscala/xml/NodeSeq;
  #180 = Utf8               (Ljava/lang/String;Ljava/lang/String;Lscala/xml/MetaData;Lscala/xml/NamespaceBinding;ZLscala/collection/immutable/Seq;)V
  #181 = NameAndType        #143:#180     // "<init>":(Ljava/lang/String;Ljava/lang/String;Lscala/xml/MetaData;Lscala/xml/NamespaceBinding;ZLscala/collection/immutable/Seq;)V
  #182 = Methodref          #123.#181     // scala/xml/Elem."<init>":(Ljava/lang/String;Ljava/lang/String;Lscala/xml/MetaData;Lscala/xml/NamespaceBinding;ZLscala/collection/immutable/Seq;)V
  #183 = String             #24           // text
  #184 = NameAndType        #24:#49       // text:()Ljava/lang/String;
  #185 = Methodref          #2.#184       // org/scalatest/events/MarkupProvided.text:()Ljava/lang/String;
  #186 = String             #26           // nameInfo
  #187 = Utf8               EventXmlHelper
  #188 = Utf8               ()Lorg/scalatest/events/Event$EventXmlHelper$;
  #189 = NameAndType        #187:#188     // EventXmlHelper:()Lorg/scalatest/events/Event$EventXmlHelper$;
  #190 = Methodref          #2.#189       // org/scalatest/events/MarkupProvided.EventXmlHelper:()Lorg/scalatest/events/Event$EventXmlHelper$;
  #191 = NameAndType        #26:#53       // nameInfo:()Lscala/Option;
  #192 = Methodref          #2.#191       // org/scalatest/events/MarkupProvided.nameInfo:()Lscala/Option;
  #193 = Utf8               nameInfoOption
  #194 = Utf8               (Lscala/Option;)Ljava/lang/Object;
  #195 = NameAndType        #193:#194     // nameInfoOption:(Lscala/Option;)Ljava/lang/Object;
  #196 = Methodref          #20.#195      // org/scalatest/events/Event$EventXmlHelper$.nameInfoOption:(Lscala/Option;)Ljava/lang/Object;
  #197 = String             #29           // formatter
  #198 = NameAndType        #29:#53       // formatter:()Lscala/Option;
  #199 = Methodref          #2.#198       // org/scalatest/events/MarkupProvided.formatter:()Lscala/Option;
  #200 = Utf8               formatterOption
  #201 = NameAndType        #200:#194     // formatterOption:(Lscala/Option;)Ljava/lang/Object;
  #202 = Methodref          #20.#201      // org/scalatest/events/Event$EventXmlHelper$.formatterOption:(Lscala/Option;)Ljava/lang/Object;
  #203 = String             #31           // location
  #204 = NameAndType        #31:#53       // location:()Lscala/Option;
  #205 = Methodref          #2.#204       // org/scalatest/events/MarkupProvided.location:()Lscala/Option;
  #206 = Utf8               locationOption
  #207 = NameAndType        #206:#194     // locationOption:(Lscala/Option;)Ljava/lang/Object;
  #208 = Methodref          #20.#207      // org/scalatest/events/Event$EventXmlHelper$.locationOption:(Lscala/Option;)Ljava/lang/Object;
  #209 = String             #35           // threadName
  #210 = NameAndType        #35:#49       // threadName:()Ljava/lang/String;
  #211 = Methodref          #2.#210       // org/scalatest/events/MarkupProvided.threadName:()Ljava/lang/String;
  #212 = String             #36           // timeStamp
  #213 = NameAndType        #36:#39       // timeStamp:()J
  #214 = Methodref          #2.#213       // org/scalatest/events/MarkupProvided.timeStamp:()J
  #215 = Utf8               boxToLong
  #216 = Utf8               (J)Ljava/lang/Long;
  #217 = NameAndType        #215:#216     // boxToLong:(J)Ljava/lang/Long;
  #218 = Methodref          #171.#217     // scala/runtime/BoxesRunTime.boxToLong:(J)Ljava/lang/Long;
  #219 = Utf8               \n
  #220 = String             #219          // \n
  #221 = Utf8               $buf
  #222 = Utf8               Lscala/xml/NodeBuffer;
  #223 = Utf8               toJson
  #224 = Utf8               scala/collection/StringOps$
  #225 = Class              #224          // scala/collection/StringOps$
  #226 = Utf8               Lscala/collection/StringOps$;
  #227 = NameAndType        #42:#226      // MODULE$:Lscala/collection/StringOps$;
  #228 = Fieldref           #225.#227     // scala/collection/StringOps$.MODULE$:Lscala/collection/StringOps$;
  #229 = Utf8               scala/Predef$
  #230 = Class              #229          // scala/Predef$
  #231 = Utf8               Lscala/Predef$;
  #232 = NameAndType        #42:#231      // MODULE$:Lscala/Predef$;
  #233 = Fieldref           #230.#232     // scala/Predef$.MODULE$:Lscala/Predef$;
  #234 = Utf8               java/lang/StringBuilder
  #235 = Class              #234          // java/lang/StringBuilder
  #236 = Integer            130
  #237 = Utf8               (I)V
  #238 = NameAndType        #143:#237     // "<init>":(I)V
  #239 = Methodref          #235.#238     // java/lang/StringBuilder."<init>":(I)V
  #240 = Utf8               { \"eventType\": \"MarkupProvided\", \"ordinal\":
  #241 = String             #240          // { \"eventType\": \"MarkupProvided\", \"ordinal\":
  #242 = Utf8               append
  #243 = Utf8               (Ljava/lang/String;)Ljava/lang/StringBuilder;
  #244 = NameAndType        #242:#243     // append:(Ljava/lang/String;)Ljava/lang/StringBuilder;
  #245 = Methodref          #235.#244     // java/lang/StringBuilder.append:(Ljava/lang/String;)Ljava/lang/StringBuilder;
  #246 = Utf8               (I)Ljava/lang/StringBuilder;
  #247 = NameAndType        #242:#246     // append:(I)Ljava/lang/StringBuilder;
  #248 = Methodref          #235.#247     // java/lang/StringBuilder.append:(I)Ljava/lang/StringBuilder;
  #249 = Utf8               , \"text\":
  #250 = String             #249          // , \"text\":
  #251 = Utf8               EventJsonHelper
  #252 = Utf8               ()Lorg/scalatest/events/Event$EventJsonHelper$;
  #253 = NameAndType        #251:#252     // EventJsonHelper:()Lorg/scalatest/events/Event$EventJsonHelper$;
  #254 = Methodref          #2.#253       // org/scalatest/events/MarkupProvided.EventJsonHelper:()Lorg/scalatest/events/Event$EventJsonHelper$;
  #255 = Utf8               string
  #256 = Utf8               (Ljava/lang/String;)Ljava/lang/String;
  #257 = NameAndType        #255:#256     // string:(Ljava/lang/String;)Ljava/lang/String;
  #258 = Methodref          #17.#257      // org/scalatest/events/Event$EventJsonHelper$.string:(Ljava/lang/String;)Ljava/lang/String;
  #259 = Utf8               , \"nameInfo\":
  #260 = String             #259          // , \"nameInfo\":
  #261 = Utf8               (Lscala/Option;)Ljava/lang/String;
  #262 = NameAndType        #193:#261     // nameInfoOption:(Lscala/Option;)Ljava/lang/String;
  #263 = Methodref          #17.#262      // org/scalatest/events/Event$EventJsonHelper$.nameInfoOption:(Lscala/Option;)Ljava/lang/String;
  #264 = Utf8               , \"formatter\":
  #265 = String             #264          // , \"formatter\":
  #266 = NameAndType        #200:#261     // formatterOption:(Lscala/Option;)Ljava/lang/String;
  #267 = Methodref          #17.#266      // org/scalatest/events/Event$EventJsonHelper$.formatterOption:(Lscala/Option;)Ljava/lang/String;
  #268 = Utf8               , \"location\":
  #269 = String             #268          // , \"location\":
  #270 = NameAndType        #206:#261     // locationOption:(Lscala/Option;)Ljava/lang/String;
  #271 = Methodref          #17.#270      // org/scalatest/events/Event$EventJsonHelper$.locationOption:(Lscala/Option;)Ljava/lang/String;
  #272 = Utf8               , \"threadName\":
  #273 = String             #272          // , \"threadName\":
  #274 = Utf8               , \"timeStamp\":
  #275 = String             #274          // , \"timeStamp\":
  #276 = Utf8               (J)Ljava/lang/StringBuilder;
  #277 = NameAndType        #242:#276     // append:(J)Ljava/lang/StringBuilder;
  #278 = Methodref          #235.#277     // java/lang/StringBuilder.append:(J)Ljava/lang/StringBuilder;
  #279 = Utf8                }
  #280 = String             #279          //  }
  #281 = Utf8               toString
  #282 = NameAndType        #281:#49      // toString:()Ljava/lang/String;
  #283 = Methodref          #235.#282     // java/lang/StringBuilder.toString:()Ljava/lang/String;
  #284 = Utf8               augmentString
  #285 = NameAndType        #284:#256     // augmentString:(Ljava/lang/String;)Ljava/lang/String;
  #286 = Methodref          #230.#285     // scala/Predef$.augmentString:(Ljava/lang/String;)Ljava/lang/String;
  #287 = Utf8               stripMargin$extension
  #288 = NameAndType        #287:#256     // stripMargin$extension:(Ljava/lang/String;)Ljava/lang/String;
  #289 = Methodref          #225.#288     // scala/collection/StringOps$.stripMargin$extension:(Ljava/lang/String;)Ljava/lang/String;
  #290 = Utf8               withPayload
  #291 = Utf8               (Lscala/Option;)Lorg/scalatest/events/MarkupProvided;
  #292 = Utf8               (Lscala/Option<Ljava/lang/Object;>;)Lorg/scalatest/events/MarkupProvided;
  #293 = Utf8               newPayload
  #294 = Utf8               copy$default$1
  #295 = NameAndType        #294:#101     // copy$default$1:()Lorg/scalatest/events/Ordinal;
  #296 = Methodref          #2.#295       // org/scalatest/events/MarkupProvided.copy$default$1:()Lorg/scalatest/events/Ordinal;
  #297 = Utf8               copy$default$2
  #298 = NameAndType        #297:#49      // copy$default$2:()Ljava/lang/String;
  #299 = Methodref          #2.#298       // org/scalatest/events/MarkupProvided.copy$default$2:()Ljava/lang/String;
  #300 = Utf8               copy$default$3
  #301 = NameAndType        #300:#53      // copy$default$3:()Lscala/Option;
  #302 = Methodref          #2.#301       // org/scalatest/events/MarkupProvided.copy$default$3:()Lscala/Option;
  #303 = Utf8               copy$default$4
  #304 = NameAndType        #303:#53      // copy$default$4:()Lscala/Option;
  #305 = Methodref          #2.#304       // org/scalatest/events/MarkupProvided.copy$default$4:()Lscala/Option;
  #306 = Utf8               copy$default$5
  #307 = NameAndType        #306:#53      // copy$default$5:()Lscala/Option;
  #308 = Methodref          #2.#307       // org/scalatest/events/MarkupProvided.copy$default$5:()Lscala/Option;
  #309 = Utf8               copy$default$7
  #310 = NameAndType        #309:#49      // copy$default$7:()Ljava/lang/String;
  #311 = Methodref          #2.#310       // org/scalatest/events/MarkupProvided.copy$default$7:()Ljava/lang/String;
  #312 = Utf8               copy$default$8
  #313 = NameAndType        #312:#39      // copy$default$8:()J
  #314 = Methodref          #2.#313       // org/scalatest/events/MarkupProvided.copy$default$8:()J
  #315 = Utf8               copy
  #316 = NameAndType        #315:#88      // copy:(Lorg/scalatest/events/Ordinal;Ljava/lang/String;Lscala/Option;Lscala/Option;Lscala/Option;Lscala/Option;Ljava/lang/String;J)Lorg/scalatest/events/MarkupProvided;
  #317 = Methodref          #2.#316       // org/scalatest/events/MarkupProvided.copy:(Lorg/scalatest/events/Ordinal;Ljava/lang/String;Lscala/Option;Lscala/Option;Lscala/Option;Lscala/Option;Ljava/lang/String;J)Lorg/scalatest/events/MarkupProvided;
  #318 = Utf8               x$1
  #319 = Utf8               x$2
  #320 = Utf8               x$3
  #321 = Utf8               x$4
  #322 = Utf8               x$5
  #323 = Utf8               x$6
  #324 = Utf8               x$7
  #325 = Utf8               x$8
  #326 = Utf8               (Lorg/scalatest/events/Ordinal;Ljava/lang/String;Lscala/Option;Lscala/Option;Lscala/Option;Lscala/Option;Ljava/lang/String;J)V
  #327 = NameAndType        #143:#326     // "<init>":(Lorg/scalatest/events/Ordinal;Ljava/lang/String;Lscala/Option;Lscala/Option;Lscala/Option;Lscala/Option;Ljava/lang/String;J)V
  #328 = Methodref          #2.#327       // org/scalatest/events/MarkupProvided."<init>":(Lorg/scalatest/events/Ordinal;Ljava/lang/String;Lscala/Option;Lscala/Option;Lscala/Option;Lscala/Option;Ljava/lang/String;J)V
  #329 = Utf8               copy$default$6
  #330 = NameAndType        #33:#53       // payload:()Lscala/Option;
  #331 = Methodref          #2.#330       // org/scalatest/events/MarkupProvided.payload:()Lscala/Option;
  #332 = Utf8               productPrefix
  #333 = Utf8               productArity
  #334 = Utf8               productElement
  #335 = Utf8               (I)Ljava/lang/Object;
  #336 = Utf8               scala/runtime/Statics
  #337 = Class              #336          // scala/runtime/Statics
  #338 = Utf8               ioobe
  #339 = NameAndType        #338:#335     // ioobe:(I)Ljava/lang/Object;
  #340 = Methodref          #337.#339     // scala/runtime/Statics.ioobe:(I)Ljava/lang/Object;
  #341 = Utf8               I
  #342 = Utf8               java/lang/Object
  #343 = Class              #342          // java/lang/Object
  #344 = Utf8               productIterator
  #345 = Utf8               ()Lscala/collection/Iterator;
  #346 = Utf8               ()Lscala/collection/Iterator<Ljava/lang/Object;>;
  #347 = Utf8               scala/runtime/ScalaRunTime$
  #348 = Class              #347          // scala/runtime/ScalaRunTime$
  #349 = Utf8               Lscala/runtime/ScalaRunTime$;
  #350 = NameAndType        #42:#349      // MODULE$:Lscala/runtime/ScalaRunTime$;
  #351 = Fieldref           #348.#350     // scala/runtime/ScalaRunTime$.MODULE$:Lscala/runtime/ScalaRunTime$;
  #352 = Utf8               typedProductIterator
  #353 = Utf8               (Lscala/Product;)Lscala/collection/Iterator;
  #354 = NameAndType        #352:#353     // typedProductIterator:(Lscala/Product;)Lscala/collection/Iterator;
  #355 = Methodref          #348.#354     // scala/runtime/ScalaRunTime$.typedProductIterator:(Lscala/Product;)Lscala/collection/Iterator;
  #356 = Utf8               canEqual
  #357 = Utf8               (Ljava/lang/Object;)Z
  #358 = Utf8               Ljava/lang/Object;
  #359 = Utf8               productElementName
  #360 = Utf8               (I)Ljava/lang/String;
  #361 = String             #33           // payload
  #362 = Utf8               java/lang/String
  #363 = Class              #362          // java/lang/String
  #364 = Utf8               hashCode
  #365 = Integer            -889275714
  #366 = NameAndType        #332:#49      // productPrefix:()Ljava/lang/String;
  #367 = Methodref          #2.#366       // org/scalatest/events/MarkupProvided.productPrefix:()Ljava/lang/String;
  #368 = NameAndType        #364:#167     // hashCode:()I
  #369 = Methodref          #363.#368     // java/lang/String.hashCode:()I
  #370 = Utf8               mix
  #371 = Utf8               (II)I
  #372 = NameAndType        #370:#371     // mix:(II)I
  #373 = Methodref          #337.#372     // scala/runtime/Statics.mix:(II)I
  #374 = Utf8               anyHash
  #375 = Utf8               (Ljava/lang/Object;)I
  #376 = NameAndType        #374:#375     // anyHash:(Ljava/lang/Object;)I
  #377 = Methodref          #337.#376     // scala/runtime/Statics.anyHash:(Ljava/lang/Object;)I
  #378 = Utf8               longHash
  #379 = Utf8               (J)I
  #380 = NameAndType        #378:#379     // longHash:(J)I
  #381 = Methodref          #337.#380     // scala/runtime/Statics.longHash:(J)I
  #382 = Utf8               finalizeHash
  #383 = NameAndType        #382:#371     // finalizeHash:(II)I
  #384 = Methodref          #337.#383     // scala/runtime/Statics.finalizeHash:(II)I
  #385 = Utf8               _toString
  #386 = Utf8               (Lscala/Product;)Ljava/lang/String;
  #387 = NameAndType        #385:#386     // _toString:(Lscala/Product;)Ljava/lang/String;
  #388 = Methodref          #348.#387     // scala/runtime/ScalaRunTime$._toString:(Lscala/Product;)Ljava/lang/String;
  #389 = Utf8               equals
  #390 = NameAndType        #389:#357     // equals:(Ljava/lang/Object;)Z
  #391 = Methodref          #343.#390     // java/lang/Object.equals:(Ljava/lang/Object;)Z
  #392 = Utf8               scala/Option
  #393 = Class              #392          // scala/Option
  #394 = Utf8               (Lscala/Option;)Lorg/scalatest/events/Event;
  #395 = NameAndType        #290:#291     // withPayload:(Lscala/Option;)Lorg/scalatest/events/MarkupProvided;
  #396 = Methodref          #2.#395       // org/scalatest/events/MarkupProvided.withPayload:(Lscala/Option;)Lorg/scalatest/events/MarkupProvided;
  #397 = Utf8               (Lorg/scalatest/events/Ordinal;Ljava/lang/String;Lscala/Option<Lorg/scalatest/events/NameInfo;>;Lscala/Option<Lorg/scalatest/events/Formatter;>;Lscala/Option<Lorg/scalatest/events/Location;>;Lscala/Option<Ljava/lang/Object;>;Ljava/lang/String;J)V
  #398 = Methodref          #4.#145       // org/scalatest/events/Event."<init>":()V
  #399 = Utf8               org/scalactic/Requirements$
  #400 = Class              #399          // org/scalactic/Requirements$
  #401 = Utf8               Lorg/scalactic/Requirements$;
  #402 = NameAndType        #42:#401      // MODULE$:Lorg/scalactic/Requirements$;
  #403 = Fieldref           #400.#402     // org/scalactic/Requirements$.MODULE$:Lorg/scalactic/Requirements$;
  #404 = Utf8               requirementsHelper
  #405 = Utf8               ()Lorg/scalactic/Requirements$RequirementsHelper;
  #406 = NameAndType        #404:#405     // requirementsHelper:()Lorg/scalactic/Requirements$RequirementsHelper;
  #407 = Methodref          #400.#406     // org/scalactic/Requirements$.requirementsHelper:()Lorg/scalactic/Requirements$RequirementsHelper;
  #408 = Utf8               MarkupProvided.this.ordinal
  #409 = String             #408          // MarkupProvided.this.ordinal
  #410 = Utf8               MarkupProvided.this.text
  #411 = String             #410          // MarkupProvided.this.text
  #412 = Utf8               MarkupProvided.this.nameInfo
  #413 = String             #412          // MarkupProvided.this.nameInfo
  #414 = Utf8               MarkupProvided.this.formatter
  #415 = String             #414          // MarkupProvided.this.formatter
  #416 = Utf8               MarkupProvided.this.location
  #417 = String             #416          // MarkupProvided.this.location
  #418 = Utf8               MarkupProvided.this.payload
  #419 = String             #418          // MarkupProvided.this.payload
  #420 = Utf8               MarkupProvided.this.threadName
  #421 = String             #420          // MarkupProvided.this.threadName
  #422 = Utf8               [Ljava/lang/Object;
  #423 = Class              #422          // "[Ljava/lang/Object;"
  #424 = Utf8               [Ljava/lang/String;
  #425 = Class              #424          // "[Ljava/lang/String;"
  #426 = Utf8               org/scalactic/Prettifier$
  #427 = Class              #426          // org/scalactic/Prettifier$
  #428 = Utf8               Lorg/scalactic/Prettifier$;
  #429 = NameAndType        #42:#428      // MODULE$:Lorg/scalactic/Prettifier$;
  #430 = Fieldref           #427.#429     // org/scalactic/Prettifier$.MODULE$:Lorg/scalactic/Prettifier$;
  #431 = Utf8               default
  #432 = Utf8               ()Lorg/scalactic/Prettifier;
  #433 = NameAndType        #431:#432     // default:()Lorg/scalactic/Prettifier;
  #434 = Methodref          #427.#433     // org/scalactic/Prettifier$.default:()Lorg/scalactic/Prettifier;
  #435 = Utf8               org/scalactic/source/Position
  #436 = Class              #435          // org/scalactic/source/Position
  #437 = String             #7            // Event.scala
  #438 = Utf8               Please set the environment variable SCALACTIC_FILL_FILE_PATHNAMES to yes at compile time to enable this feature.
  #439 = String             #438          // Please set the environment variable SCALACTIC_FILL_FILE_PATHNAMES to yes at compile time to enable this feature.
  #440 = Utf8               (Ljava/lang/String;Ljava/lang/String;I)V
  #441 = NameAndType        #143:#440     // "<init>":(Ljava/lang/String;Ljava/lang/String;I)V
  #442 = Methodref          #436.#441     // org/scalactic/source/Position."<init>":(Ljava/lang/String;Ljava/lang/String;I)V
  #443 = Utf8               macroRequireNonNull
  #444 = Utf8               ([Ljava/lang/String;[Ljava/lang/Object;Lorg/scalactic/Prettifier;Lorg/scalactic/source/Position;)V
  #445 = NameAndType        #443:#444     // macroRequireNonNull:([Ljava/lang/String;[Ljava/lang/Object;Lorg/scalactic/Prettifier;Lorg/scalactic/source/Position;)V
  #446 = Methodref          #12.#445      // org/scalactic/Requirements$RequirementsHelper.macroRequireNonNull:([Ljava/lang/String;[Ljava/lang/Object;Lorg/scalactic/Prettifier;Lorg/scalactic/source/Position;)V
  #447 = Utf8               Signature
  #448 = Utf8               Code
  #449 = Utf8               LocalVariableTable
  #450 = Utf8               MethodParameters
  #451 = Utf8               LineNumberTable
  #452 = Utf8               StackMapTable
  #453 = Utf8               InnerClasses
  #454 = Utf8               SourceFile
  #455 = Utf8               RuntimeVisibleAnnotations
  #456 = Utf8               ScalaInlineInfo
  #457 = Utf8               ScalaSig
{
  private final org.scalatest.events.Ordinal ordinal;
    descriptor: Lorg/scalatest/events/Ordinal;
    flags: (0x0012) ACC_PRIVATE, ACC_FINAL

  private final java.lang.String text;
    descriptor: Ljava/lang/String;
    flags: (0x0012) ACC_PRIVATE, ACC_FINAL

  private final scala.Option<org.scalatest.events.NameInfo> nameInfo;
    descriptor: Lscala/Option;
    flags: (0x0012) ACC_PRIVATE, ACC_FINAL
    Signature: #28                          // Lscala/Option<Lorg/scalatest/events/NameInfo;>;

  private final scala.Option<org.scalatest.events.Formatter> formatter;
    descriptor: Lscala/Option;
    flags: (0x0012) ACC_PRIVATE, ACC_FINAL
    Signature: #30                          // Lscala/Option<Lorg/scalatest/events/Formatter;>;

  private final scala.Option<org.scalatest.events.Location> location;
    descriptor: Lscala/Option;
    flags: (0x0012) ACC_PRIVATE, ACC_FINAL
    Signature: #32                          // Lscala/Option<Lorg/scalatest/events/Location;>;

  private final scala.Option<java.lang.Object> payload;
    descriptor: Lscala/Option;
    flags: (0x0012) ACC_PRIVATE, ACC_FINAL
    Signature: #34                          // Lscala/Option<Ljava/lang/Object;>;

  private final java.lang.String threadName;
    descriptor: Ljava/lang/String;
    flags: (0x0012) ACC_PRIVATE, ACC_FINAL

  private final long timeStamp;
    descriptor: J
    flags: (0x0012) ACC_PRIVATE, ACC_FINAL

  public static long $lessinit$greater$default$8();
    descriptor: ()J
    flags: (0x0009) ACC_PUBLIC, ACC_STATIC
    Code:
      stack=2, locals=0, args_size=0
         0: getstatic     #45                 // Field org/scalatest/events/MarkupProvided$.MODULE$:Lorg/scalatest/events/MarkupProvided$;
         3: invokevirtual #47                 // Method org/scalatest/events/MarkupProvided$.$lessinit$greater$default$8:()J
         6: lreturn

  public static java.lang.String $lessinit$greater$default$7();
    descriptor: ()Ljava/lang/String;
    flags: (0x0009) ACC_PUBLIC, ACC_STATIC
    Code:
      stack=1, locals=0, args_size=0
         0: getstatic     #45                 // Field org/scalatest/events/MarkupProvided$.MODULE$:Lorg/scalatest/events/MarkupProvided$;
         3: invokevirtual #51                 // Method org/scalatest/events/MarkupProvided$.$lessinit$greater$default$7:()Ljava/lang/String;
         6: areturn

  public static scala.Option<java.lang.Object> $lessinit$greater$default$6();
    descriptor: ()Lscala/Option;
    flags: (0x0009) ACC_PUBLIC, ACC_STATIC
    Code:
      stack=1, locals=0, args_size=0
         0: getstatic     #45                 // Field org/scalatest/events/MarkupProvided$.MODULE$:Lorg/scalatest/events/MarkupProvided$;
         3: invokevirtual #56                 // Method org/scalatest/events/MarkupProvided$.$lessinit$greater$default$6:()Lscala/Option;
         6: areturn
    Signature: #54                          // ()Lscala/Option<Ljava/lang/Object;>;

  public static scala.Option<org.scalatest.events.Location> $lessinit$greater$default$5();
    descriptor: ()Lscala/Option;
    flags: (0x0009) ACC_PUBLIC, ACC_STATIC
    Code:
      stack=1, locals=0, args_size=0
         0: getstatic     #45                 // Field org/scalatest/events/MarkupProvided$.MODULE$:Lorg/scalatest/events/MarkupProvided$;
         3: invokevirtual #60                 // Method org/scalatest/events/MarkupProvided$.$lessinit$greater$default$5:()Lscala/Option;
         6: areturn
    Signature: #58                          // ()Lscala/Option<Lorg/scalatest/events/Location;>;

  public static scala.Option<org.scalatest.events.Formatter> $lessinit$greater$default$4();
    descriptor: ()Lscala/Option;
    flags: (0x0009) ACC_PUBLIC, ACC_STATIC
    Code:
      stack=1, locals=0, args_size=0
         0: getstatic     #45                 // Field org/scalatest/events/MarkupProvided$.MODULE$:Lorg/scalatest/events/MarkupProvided$;
         3: invokevirtual #64                 // Method org/scalatest/events/MarkupProvided$.$lessinit$greater$default$4:()Lscala/Option;
         6: areturn
    Signature: #62                          // ()Lscala/Option<Lorg/scalatest/events/Formatter;>;

  public static scala.Option<scala.Tuple8<org.scalatest.events.Ordinal, java.lang.String, scala.Option<org.scalatest.events.NameInfo>, scala.Option<org.scalatest.events.Formatter>, scala.Option<org.scalatest.events.Location>, scala.Option<java.lang.Object>, java.lang.String, java.lang.Object>> unapply(org.scalatest.events.MarkupProvided);
    descriptor: (Lorg/scalatest/events/MarkupProvided;)Lscala/Option;
    flags: (0x0009) ACC_PUBLIC, ACC_STATIC
    Code:
      stack=2, locals=1, args_size=1
         0: getstatic     #45                 // Field org/scalatest/events/MarkupProvided$.MODULE$:Lorg/scalatest/events/MarkupProvided$;
         3: aload_0
         4: invokevirtual #70                 // Method org/scalatest/events/MarkupProvided$.unapply:(Lorg/scalatest/events/MarkupProvided;)Lscala/Option;
         7: areturn
      LocalVariableTable:
        Start  Length  Slot  Name   Signature
            0       8     0   x$0   Lorg/scalatest/events/MarkupProvided;
    Signature: #67                          // (Lorg/scalatest/events/MarkupProvided;)Lscala/Option<Lscala/Tuple8<Lorg/scalatest/events/Ordinal;Ljava/lang/String;Lscala/Option<Lorg/scalatest/events/NameInfo;>;Lscala/Option<Lorg/scalatest/events/Formatter;>;Lscala/Option<Lorg/scalatest/events/Location;>;Lscala/Option<Ljava/lang/Object;>;Ljava/lang/String;Ljava/lang/Object;>;>;
    MethodParameters:
      Name                           Flags
      x$0                            final

  public static long apply$default$8();
    descriptor: ()J
    flags: (0x0009) ACC_PUBLIC, ACC_STATIC
    Code:
      stack=2, locals=0, args_size=0
         0: getstatic     #45                 // Field org/scalatest/events/MarkupProvided$.MODULE$:Lorg/scalatest/events/MarkupProvided$;
         3: invokevirtual #74                 // Method org/scalatest/events/MarkupProvided$.apply$default$8:()J
         6: lreturn

  public static java.lang.String apply$default$7();
    descriptor: ()Ljava/lang/String;
    flags: (0x0009) ACC_PUBLIC, ACC_STATIC
    Code:
      stack=1, locals=0, args_size=0
         0: getstatic     #45                 // Field org/scalatest/events/MarkupProvided$.MODULE$:Lorg/scalatest/events/MarkupProvided$;
         3: invokevirtual #77                 // Method org/scalatest/events/MarkupProvided$.apply$default$7:()Ljava/lang/String;
         6: areturn

  public static scala.Option<java.lang.Object> apply$default$6();
    descriptor: ()Lscala/Option;
    flags: (0x0009) ACC_PUBLIC, ACC_STATIC
    Code:
      stack=1, locals=0, args_size=0
         0: getstatic     #45                 // Field org/scalatest/events/MarkupProvided$.MODULE$:Lorg/scalatest/events/MarkupProvided$;
         3: invokevirtual #80                 // Method org/scalatest/events/MarkupProvided$.apply$default$6:()Lscala/Option;
         6: areturn
    Signature: #54                          // ()Lscala/Option<Ljava/lang/Object;>;

  public static scala.Option<org.scalatest.events.Location> apply$default$5();
    descriptor: ()Lscala/Option;
    flags: (0x0009) ACC_PUBLIC, ACC_STATIC
    Code:
      stack=1, locals=0, args_size=0
         0: getstatic     #45                 // Field org/scalatest/events/MarkupProvided$.MODULE$:Lorg/scalatest/events/MarkupProvided$;
         3: invokevirtual #83                 // Method org/scalatest/events/MarkupProvided$.apply$default$5:()Lscala/Option;
         6: areturn
    Signature: #58                          // ()Lscala/Option<Lorg/scalatest/events/Location;>;

  public static scala.Option<org.scalatest.events.Formatter> apply$default$4();
    descriptor: ()Lscala/Option;
    flags: (0x0009) ACC_PUBLIC, ACC_STATIC
    Code:
      stack=1, locals=0, args_size=0
         0: getstatic     #45                 // Field org/scalatest/events/MarkupProvided$.MODULE$:Lorg/scalatest/events/MarkupProvided$;
         3: invokevirtual #86                 // Method org/scalatest/events/MarkupProvided$.apply$default$4:()Lscala/Option;
         6: areturn
    Signature: #62                          // ()Lscala/Option<Lorg/scalatest/events/Formatter;>;

  public static org.scalatest.events.MarkupProvided apply(org.scalatest.events.Ordinal, java.lang.String, scala.Option<org.scalatest.events.NameInfo>, scala.Option<org.scalatest.events.Formatter>, scala.Option<org.scalatest.events.Location>, scala.Option<java.lang.Object>, java.lang.String, long);
    descriptor: (Lorg/scalatest/events/Ordinal;Ljava/lang/String;Lscala/Option;Lscala/Option;Lscala/Option;Lscala/Option;Ljava/lang/String;J)Lorg/scalatest/events/MarkupProvided;
    flags: (0x0009) ACC_PUBLIC, ACC_STATIC
    Code:
      stack=10, locals=9, args_size=8
         0: getstatic     #45                 // Field org/scalatest/events/MarkupProvided$.MODULE$:Lorg/scalatest/events/MarkupProvided$;
         3: aload_0
         4: aload_1
         5: aload_2
         6: aload_3
         7: aload         4
         9: aload         5
        11: aload         6
        13: lload         7
        15: invokevirtual #91                 // Method org/scalatest/events/MarkupProvided$.apply:(Lorg/scalatest/events/Ordinal;Ljava/lang/String;Lscala/Option;Lscala/Option;Lscala/Option;Lscala/Option;Ljava/lang/String;J)Lorg/scalatest/events/MarkupProvided;
        18: areturn
      LocalVariableTable:
        Start  Length  Slot  Name   Signature
            0      19     0 ordinal   Lorg/scalatest/events/Ordinal;
            0      19     1  text   Ljava/lang/String;
            0      19     2 nameInfo   Lscala/Option;
            0      19     3 formatter   Lscala/Option;
            0      19     4 location   Lscala/Option;
            0      19     5 payload   Lscala/Option;
            0      19     6 threadName   Ljava/lang/String;
            0      19     7 timeStamp   J
    Signature: #89                          // (Lorg/scalatest/events/Ordinal;Ljava/lang/String;Lscala/Option<Lorg/scalatest/events/NameInfo;>;Lscala/Option<Lorg/scalatest/events/Formatter;>;Lscala/Option<Lorg/scalatest/events/Location;>;Lscala/Option<Ljava/lang/Object;>;Ljava/lang/String;J)Lorg/scalatest/events/MarkupProvided;
    MethodParameters:
      Name                           Flags
      ordinal                        final
      text                           final
      nameInfo                       final
      formatter                      final
      location                       final
      payload                        final
      threadName                     final
      timeStamp                      final

  public static scala.Function1<scala.Tuple8<org.scalatest.events.Ordinal, java.lang.String, scala.Option<org.scalatest.events.NameInfo>, scala.Option<org.scalatest.events.Formatter>, scala.Option<org.scalatest.events.Location>, scala.Option<java.lang.Object>, java.lang.String, java.lang.Object>, org.scalatest.events.MarkupProvided> tupled();
    descriptor: ()Lscala/Function1;
    flags: (0x0009) ACC_PUBLIC, ACC_STATIC
    Code:
      stack=1, locals=0, args_size=0
         0: getstatic     #45                 // Field org/scalatest/events/MarkupProvided$.MODULE$:Lorg/scalatest/events/MarkupProvided$;
         3: invokevirtual #96                 // Method org/scalatest/events/MarkupProvided$.tupled:()Lscala/Function1;
         6: areturn
    Signature: #94                          // ()Lscala/Function1<Lscala/Tuple8<Lorg/scalatest/events/Ordinal;Ljava/lang/String;Lscala/Option<Lorg/scalatest/events/NameInfo;>;Lscala/Option<Lorg/scalatest/events/Formatter;>;Lscala/Option<Lorg/scalatest/events/Location;>;Lscala/Option<Ljava/lang/Object;>;Ljava/lang/String;Ljava/lang/Object;>;Lorg/scalatest/events/MarkupProvided;>;

  public static scala.Function1<org.scalatest.events.Ordinal, scala.Function1<java.lang.String, scala.Function1<scala.Option<org.scalatest.events.NameInfo>, scala.Function1<scala.Option<org.scalatest.events.Formatter>, scala.Function1<scala.Option<org.scalatest.events.Location>, scala.Function1<scala.Option<java.lang.Object>, scala.Function1<java.lang.String, scala.Function1<java.lang.Object, org.scalatest.events.MarkupProvided>>>>>>>> curried();
    descriptor: ()Lscala/Function1;
    flags: (0x0009) ACC_PUBLIC, ACC_STATIC
    Code:
      stack=1, locals=0, args_size=0
         0: getstatic     #45                 // Field org/scalatest/events/MarkupProvided$.MODULE$:Lorg/scalatest/events/MarkupProvided$;
         3: invokevirtual #100                // Method org/scalatest/events/MarkupProvided$.curried:()Lscala/Function1;
         6: areturn
    Signature: #98                          // ()Lscala/Function1<Lorg/scalatest/events/Ordinal;Lscala/Function1<Ljava/lang/String;Lscala/Function1<Lscala/Option<Lorg/scalatest/events/NameInfo;>;Lscala/Function1<Lscala/Option<Lorg/scalatest/events/Formatter;>;Lscala/Function1<Lscala/Option<Lorg/scalatest/events/Location;>;Lscala/Function1<Lscala/Option<Ljava/lang/Object;>;Lscala/Function1<Ljava/lang/String;Lscala/Function1<Ljava/lang/Object;Lorg/scalatest/events/MarkupProvided;>;>;>;>;>;>;>;>;

  public org.scalatest.events.Ordinal ordinal();
    descriptor: ()Lorg/scalatest/events/Ordinal;
    flags: (0x0001) ACC_PUBLIC
    Code:
      stack=1, locals=1, args_size=1
         0: aload_0
         1: getfield      #103                // Field ordinal:Lorg/scalatest/events/Ordinal;
         4: areturn
      LineNumberTable:
        line 1988: 0
      LocalVariableTable:
        Start  Length  Slot  Name   Signature
            0       5     0  this   Lorg/scalatest/events/MarkupProvided;

  public java.lang.String text();
    descriptor: ()Ljava/lang/String;
    flags: (0x0001) ACC_PUBLIC
    Code:
      stack=1, locals=1, args_size=1
         0: aload_0
         1: getfield      #106                // Field text:Ljava/lang/String;
         4: areturn
      LineNumberTable:
        line 1989: 0
      LocalVariableTable:
        Start  Length  Slot  Name   Signature
            0       5     0  this   Lorg/scalatest/events/MarkupProvided;

  public scala.Option<org.scalatest.events.NameInfo> nameInfo();
    descriptor: ()Lscala/Option;
    flags: (0x0001) ACC_PUBLIC
    Code:
      stack=1, locals=1, args_size=1
         0: aload_0
         1: getfield      #109                // Field nameInfo:Lscala/Option;
         4: areturn
      LineNumberTable:
        line 1990: 0
      LocalVariableTable:
        Start  Length  Slot  Name   Signature
            0       5     0  this   Lorg/scalatest/events/MarkupProvided;
    Signature: #107                         // ()Lscala/Option<Lorg/scalatest/events/NameInfo;>;

  public scala.Option<org.scalatest.events.Formatter> formatter();
    descriptor: ()Lscala/Option;
    flags: (0x0001) ACC_PUBLIC
    Code:
      stack=1, locals=1, args_size=1
         0: aload_0
         1: getfield      #111                // Field formatter:Lscala/Option;
         4: areturn
      LineNumberTable:
        line 1991: 0
      LocalVariableTable:
        Start  Length  Slot  Name   Signature
            0       5     0  this   Lorg/scalatest/events/MarkupProvided;
    Signature: #62                          // ()Lscala/Option<Lorg/scalatest/events/Formatter;>;

  public scala.Option<org.scalatest.events.Location> location();
    descriptor: ()Lscala/Option;
    flags: (0x0001) ACC_PUBLIC
    Code:
      stack=1, locals=1, args_size=1
         0: aload_0
         1: getfield      #113                // Field location:Lscala/Option;
         4: areturn
      LineNumberTable:
        line 1992: 0
      LocalVariableTable:
        Start  Length  Slot  Name   Signature
            0       5     0  this   Lorg/scalatest/events/MarkupProvided;
    Signature: #58                          // ()Lscala/Option<Lorg/scalatest/events/Location;>;

  public scala.Option<java.lang.Object> payload();
    descriptor: ()Lscala/Option;
    flags: (0x0001) ACC_PUBLIC
    Code:
      stack=1, locals=1, args_size=1
         0: aload_0
         1: getfield      #115                // Field payload:Lscala/Option;
         4: areturn
      LineNumberTable:
        line 1993: 0
      LocalVariableTable:
        Start  Length  Slot  Name   Signature
            0       5     0  this   Lorg/scalatest/events/MarkupProvided;
    Signature: #54                          // ()Lscala/Option<Ljava/lang/Object;>;

  public java.lang.String threadName();
    descriptor: ()Ljava/lang/String;
    flags: (0x0001) ACC_PUBLIC
    Code:
      stack=1, locals=1, args_size=1
         0: aload_0
         1: getfield      #117                // Field threadName:Ljava/lang/String;
         4: areturn
      LineNumberTable:
        line 1994: 0
      LocalVariableTable:
        Start  Length  Slot  Name   Signature
            0       5     0  this   Lorg/scalatest/events/MarkupProvided;

  public long timeStamp();
    descriptor: ()J
    flags: (0x0001) ACC_PUBLIC
    Code:
      stack=2, locals=1, args_size=1
         0: aload_0
         1: getfield      #119                // Field timeStamp:J
         4: lreturn
      LineNumberTable:
        line 1995: 0
      LocalVariableTable:
        Start  Length  Slot  Name   Signature
            0       5     0  this   Lorg/scalatest/events/MarkupProvided;

  public scala.xml.Elem toXml();
    descriptor: ()Lscala/xml/Elem;
    flags: (0x0001) ACC_PUBLIC
    Code:
      stack=28, locals=10, args_size=1
         0: new           #123                // class scala/xml/Elem
         3: dup
         4: aconst_null
         5: ldc           #125                // String MarkupProvided
         7: getstatic     #130                // Field scala/xml/Null$.MODULE$:Lscala/xml/Null$;
        10: getstatic     #135                // Field scala/xml/TopScope$.MODULE$:Lscala/xml/TopScope$;
        13: iconst_0
        14: getstatic     #140                // Field scala/xml/NodeSeq$.MODULE$:Lscala/xml/NodeSeq$;
        17: new           #142                // class scala/xml/NodeBuffer
        20: dup
        21: invokespecial #146                // Method scala/xml/NodeBuffer."<init>":()V
        24: astore_1
        25: aload_1
        26: new           #148                // class scala/xml/Text
        29: dup
        30: ldc           #150                // String \n
        32: invokespecial #153                // Method scala/xml/Text."<init>":(Ljava/lang/String;)V
        35: invokevirtual #157                // Method scala/xml/NodeBuffer.$amp$plus:(Ljava/lang/Object;)Lscala/xml/NodeBuffer;
        38: pop
        39: aload_1
        40: new           #123                // class scala/xml/Elem
        43: dup
        44: aconst_null
        45: ldc           #158                // String ordinal
        47: getstatic     #130                // Field scala/xml/Null$.MODULE$:Lscala/xml/Null$;
        50: getstatic     #135                // Field scala/xml/TopScope$.MODULE$:Lscala/xml/TopScope$;
        53: iconst_0
        54: getstatic     #140                // Field scala/xml/NodeSeq$.MODULE$:Lscala/xml/NodeSeq$;
        57: new           #142                // class scala/xml/NodeBuffer
        60: dup
        61: invokespecial #146                // Method scala/xml/NodeBuffer."<init>":()V
        64: astore_2
        65: aload_2
        66: new           #148                // class scala/xml/Text
        69: dup
        70: ldc           #160                // String \n
        72: invokespecial #153                // Method scala/xml/Text."<init>":(Ljava/lang/String;)V
        75: invokevirtual #157                // Method scala/xml/NodeBuffer.$amp$plus:(Ljava/lang/Object;)Lscala/xml/NodeBuffer;
        78: pop
        79: aload_2
        80: new           #123                // class scala/xml/Elem
        83: dup
        84: aconst_null
        85: ldc           #162                // String runStamp
        87: getstatic     #130                // Field scala/xml/Null$.MODULE$:Lscala/xml/Null$;
        90: getstatic     #135                // Field scala/xml/TopScope$.MODULE$:Lscala/xml/TopScope$;
        93: iconst_0
        94: getstatic     #140                // Field scala/xml/NodeSeq$.MODULE$:Lscala/xml/NodeSeq$;
        97: new           #142                // class scala/xml/NodeBuffer
       100: dup
       101: invokespecial #146                // Method scala/xml/NodeBuffer."<init>":()V
       104: astore_3
       105: aload_3
       106: aload_0
       107: invokevirtual #164                // Method ordinal:()Lorg/scalatest/events/Ordinal;
       110: invokevirtual #169                // Method org/scalatest/events/Ordinal.runStamp:()I
       113: invokestatic  #175                // Method scala/runtime/BoxesRunTime.boxToInteger:(I)Ljava/lang/Integer;
       116: invokevirtual #157                // Method scala/xml/NodeBuffer.$amp$plus:(Ljava/lang/Object;)Lscala/xml/NodeBuffer;
       119: pop
       120: aload_3
       121: invokevirtual #179                // Method scala/xml/NodeSeq$.seqToNodeSeq:(Lscala/collection/Seq;)Lscala/xml/NodeSeq;
       124: invokespecial #182                // Method scala/xml/Elem."<init>":(Ljava/lang/String;Ljava/lang/String;Lscala/xml/MetaData;Lscala/xml/NamespaceBinding;ZLscala/collection/immutable/Seq;)V
       127: invokevirtual #157                // Method scala/xml/NodeBuffer.$amp$plus:(Ljava/lang/Object;)Lscala/xml/NodeBuffer;
       130: pop
       131: aload_2
       132: new           #148                // class scala/xml/Text
       135: dup
       136: ldc           #150                // String \n
       138: invokespecial #153                // Method scala/xml/Text."<init>":(Ljava/lang/String;)V
       141: invokevirtual #157                // Method scala/xml/NodeBuffer.$amp$plus:(Ljava/lang/Object;)Lscala/xml/NodeBuffer;
       144: pop
       145: aload_2
       146: invokevirtual #179                // Method scala/xml/NodeSeq$.seqToNodeSeq:(Lscala/collection/Seq;)Lscala/xml/NodeSeq;
       149: invokespecial #182                // Method scala/xml/Elem."<init>":(Ljava/lang/String;Ljava/lang/String;Lscala/xml/MetaData;Lscala/xml/NamespaceBinding;ZLscala/collection/immutable/Seq;)V
       152: invokevirtual #157                // Method scala/xml/NodeBuffer.$amp$plus:(Ljava/lang/Object;)Lscala/xml/NodeBuffer;
       155: pop
       156: aload_1
       157: new           #148                // class scala/xml/Text
       160: dup
       161: ldc           #150                // String \n
       163: invokespecial #153                // Method scala/xml/Text."<init>":(Ljava/lang/String;)V
       166: invokevirtual #157                // Method scala/xml/NodeBuffer.$amp$plus:(Ljava/lang/Object;)Lscala/xml/NodeBuffer;
       169: pop
       170: aload_1
       171: new           #123                // class scala/xml/Elem
       174: dup
       175: aconst_null
       176: ldc           #183                // String text
       178: getstatic     #130                // Field scala/xml/Null$.MODULE$:Lscala/xml/Null$;
       181: getstatic     #135                // Field scala/xml/TopScope$.MODULE$:Lscala/xml/TopScope$;
       184: iconst_0
       185: getstatic     #140                // Field scala/xml/NodeSeq$.MODULE$:Lscala/xml/NodeSeq$;
       188: new           #142                // class scala/xml/NodeBuffer
       191: dup
       192: invokespecial #146                // Method scala/xml/NodeBuffer."<init>":()V
       195: astore        4
       197: aload         4
       199: aload_0
       200: invokevirtual #185                // Method text:()Ljava/lang/String;
       203: invokevirtual #157                // Method scala/xml/NodeBuffer.$amp$plus:(Ljava/lang/Object;)Lscala/xml/NodeBuffer;
       206: pop
       207: aload         4
       209: invokevirtual #179                // Method scala/xml/NodeSeq$.seqToNodeSeq:(Lscala/collection/Seq;)Lscala/xml/NodeSeq;
       212: invokespecial #182                // Method scala/xml/Elem."<init>":(Ljava/lang/String;Ljava/lang/String;Lscala/xml/MetaData;Lscala/xml/NamespaceBinding;ZLscala/collection/immutable/Seq;)V
       215: invokevirtual #157                // Method scala/xml/NodeBuffer.$amp$plus:(Ljava/lang/Object;)Lscala/xml/NodeBuffer;
       218: pop
       219: aload_1
       220: new           #148                // class scala/xml/Text
       223: dup
       224: ldc           #150                // String \n
       226: invokespecial #153                // Method scala/xml/Text."<init>":(Ljava/lang/String;)V
       229: invokevirtual #157                // Method scala/xml/NodeBuffer.$amp$plus:(Ljava/lang/Object;)Lscala/xml/NodeBuffer;
       232: pop
       233: aload_1
       234: new           #123                // class scala/xml/Elem
       237: dup
       238: aconst_null
       239: ldc           #186                // String nameInfo
       241: getstatic     #130                // Field scala/xml/Null$.MODULE$:Lscala/xml/Null$;
       244: getstatic     #135                // Field scala/xml/TopScope$.MODULE$:Lscala/xml/TopScope$;
       247: iconst_0
       248: getstatic     #140                // Field scala/xml/NodeSeq$.MODULE$:Lscala/xml/NodeSeq$;
       251: new           #142                // class scala/xml/NodeBuffer
       254: dup
       255: invokespecial #146                // Method scala/xml/NodeBuffer."<init>":()V
       258: astore        5
       260: aload         5
       262: aload_0
       263: invokevirtual #190                // Method EventXmlHelper:()Lorg/scalatest/events/Event$EventXmlHelper$;
       266: aload_0
       267: invokevirtual #192                // Method nameInfo:()Lscala/Option;
       270: invokevirtual #196                // Method org/scalatest/events/Event$EventXmlHelper$.nameInfoOption:(Lscala/Option;)Ljava/lang/Object;
       273: invokevirtual #157                // Method scala/xml/NodeBuffer.$amp$plus:(Ljava/lang/Object;)Lscala/xml/NodeBuffer;
       276: pop
       277: aload         5
       279: invokevirtual #179                // Method scala/xml/NodeSeq$.seqToNodeSeq:(Lscala/collection/Seq;)Lscala/xml/NodeSeq;
       282: invokespecial #182                // Method scala/xml/Elem."<init>":(Ljava/lang/String;Ljava/lang/String;Lscala/xml/MetaData;Lscala/xml/NamespaceBinding;ZLscala/collection/immutable/Seq;)V
       285: invokevirtual #157                // Method scala/xml/NodeBuffer.$amp$plus:(Ljava/lang/Object;)Lscala/xml/NodeBuffer;
       288: pop
       289: aload_1
       290: new           #148                // class scala/xml/Text
       293: dup
       294: ldc           #150                // String \n
       296: invokespecial #153                // Method scala/xml/Text."<init>":(Ljava/lang/String;)V
       299: invokevirtual #157                // Method scala/xml/NodeBuffer.$amp$plus:(Ljava/lang/Object;)Lscala/xml/NodeBuffer;
       302: pop
       303: aload_1
       304: new           #123                // class scala/xml/Elem
       307: dup
       308: aconst_null
       309: ldc           #197                // String formatter
       311: getstatic     #130                // Field scala/xml/Null$.MODULE$:Lscala/xml/Null$;
       314: getstatic     #135                // Field scala/xml/TopScope$.MODULE$:Lscala/xml/TopScope$;
       317: iconst_0
       318: getstatic     #140                // Field scala/xml/NodeSeq$.MODULE$:Lscala/xml/NodeSeq$;
       321: new           #142                // class scala/xml/NodeBuffer
       324: dup
       325: invokespecial #146                // Method scala/xml/NodeBuffer."<init>":()V
       328: astore        6
       330: aload         6
       332: aload_0
       333: invokevirtual #190                // Method EventXmlHelper:()Lorg/scalatest/events/Event$EventXmlHelper$;
       336: aload_0
       337: invokevirtual #199                // Method formatter:()Lscala/Option;
       340: invokevirtual #202                // Method org/scalatest/events/Event$EventXmlHelper$.formatterOption:(Lscala/Option;)Ljava/lang/Object;
       343: invokevirtual #157                // Method scala/xml/NodeBuffer.$amp$plus:(Ljava/lang/Object;)Lscala/xml/NodeBuffer;
       346: pop
       347: aload         6
       349: invokevirtual #179                // Method scala/xml/NodeSeq$.seqToNodeSeq:(Lscala/collection/Seq;)Lscala/xml/NodeSeq;
       352: invokespecial #182                // Method scala/xml/Elem."<init>":(Ljava/lang/String;Ljava/lang/String;Lscala/xml/MetaData;Lscala/xml/NamespaceBinding;ZLscala/collection/immutable/Seq;)V
       355: invokevirtual #157                // Method scala/xml/NodeBuffer.$amp$plus:(Ljava/lang/Object;)Lscala/xml/NodeBuffer;
       358: pop
       359: aload_1
       360: new           #148                // class scala/xml/Text
       363: dup
       364: ldc           #150                // String \n
       366: invokespecial #153                // Method scala/xml/Text."<init>":(Ljava/lang/String;)V
       369: invokevirtual #157                // Method scala/xml/NodeBuffer.$amp$plus:(Ljava/lang/Object;)Lscala/xml/NodeBuffer;
       372: pop
       373: aload_1
       374: new           #123                // class scala/xml/Elem
       377: dup
       378: aconst_null
       379: ldc           #203                // String location
       381: getstatic     #130                // Field scala/xml/Null$.MODULE$:Lscala/xml/Null$;
       384: getstatic     #135                // Field scala/xml/TopScope$.MODULE$:Lscala/xml/TopScope$;
       387: iconst_0
       388: getstatic     #140                // Field scala/xml/NodeSeq$.MODULE$:Lscala/xml/NodeSeq$;
       391: new           #142                // class scala/xml/NodeBuffer
       394: dup
       395: invokespecial #146                // Method scala/xml/NodeBuffer."<init>":()V
       398: astore        7
       400: aload         7
       402: aload_0
       403: invokevirtual #190                // Method EventXmlHelper:()Lorg/scalatest/events/Event$EventXmlHelper$;
       406: aload_0
       407: invokevirtual #205                // Method location:()Lscala/Option;
       410: invokevirtual #208                // Method org/scalatest/events/Event$EventXmlHelper$.locationOption:(Lscala/Option;)Ljava/lang/Object;
       413: invokevirtual #157                // Method scala/xml/NodeBuffer.$amp$plus:(Ljava/lang/Object;)Lscala/xml/NodeBuffer;
       416: pop
       417: aload         7
       419: invokevirtual #179                // Method scala/xml/NodeSeq$.seqToNodeSeq:(Lscala/collection/Seq;)Lscala/xml/NodeSeq;
       422: invokespecial #182                // Method scala/xml/Elem."<init>":(Ljava/lang/String;Ljava/lang/String;Lscala/xml/MetaData;Lscala/xml/NamespaceBinding;ZLscala/collection/immutable/Seq;)V
       425: invokevirtual #157                // Method scala/xml/NodeBuffer.$amp$plus:(Ljava/lang/Object;)Lscala/xml/NodeBuffer;
       428: pop
       429: aload_1
       430: new           #148                // class scala/xml/Text
       433: dup
       434: ldc           #150                // String \n
       436: invokespecial #153                // Method scala/xml/Text."<init>":(Ljava/lang/String;)V
       439: invokevirtual #157                // Method scala/xml/NodeBuffer.$amp$plus:(Ljava/lang/Object;)Lscala/xml/NodeBuffer;
       442: pop
       443: aload_1
       444: new           #123                // class scala/xml/Elem
       447: dup
       448: aconst_null
       449: ldc           #209                // String threadName
       451: getstatic     #130                // Field scala/xml/Null$.MODULE$:Lscala/xml/Null$;
       454: getstatic     #135                // Field scala/xml/TopScope$.MODULE$:Lscala/xml/TopScope$;
       457: iconst_0
       458: getstatic     #140                // Field scala/xml/NodeSeq$.MODULE$:Lscala/xml/NodeSeq$;
       461: new           #142                // class scala/xml/NodeBuffer
       464: dup
       465: invokespecial #146                // Method scala/xml/NodeBuffer."<init>":()V
       468: astore        8
       470: aload         8
       472: aload_0
       473: invokevirtual #211                // Method threadName:()Ljava/lang/String;
       476: invokevirtual #157                // Method scala/xml/NodeBuffer.$amp$plus:(Ljava/lang/Object;)Lscala/xml/NodeBuffer;
       479: pop
       480: aload         8
       482: invokevirtual #179                // Method scala/xml/NodeSeq$.seqToNodeSeq:(Lscala/collection/Seq;)Lscala/xml/NodeSeq;
       485: invokespecial #182                // Method scala/xml/Elem."<init>":(Ljava/lang/String;Ljava/lang/String;Lscala/xml/MetaData;Lscala/xml/NamespaceBinding;ZLscala/collection/immutable/Seq;)V
       488: invokevirtual #157                // Method scala/xml/NodeBuffer.$amp$plus:(Ljava/lang/Object;)Lscala/xml/NodeBuffer;
       491: pop
       492: aload_1
       493: new           #148                // class scala/xml/Text
       496: dup
       497: ldc           #150                // String \n
       499: invokespecial #153                // Method scala/xml/Text."<init>":(Ljava/lang/String;)V
       502: invokevirtual #157                // Method scala/xml/NodeBuffer.$amp$plus:(Ljava/lang/Object;)Lscala/xml/NodeBuffer;
       505: pop
       506: aload_1
       507: new           #123                // class scala/xml/Elem
       510: dup
       511: aconst_null
       512: ldc           #212                // String timeStamp
       514: getstatic     #130                // Field scala/xml/Null$.MODULE$:Lscala/xml/Null$;
       517: getstatic     #135                // Field scala/xml/TopScope$.MODULE$:Lscala/xml/TopScope$;
       520: iconst_0
       521: getstatic     #140                // Field scala/xml/NodeSeq$.MODULE$:Lscala/xml/NodeSeq$;
       524: new           #142                // class scala/xml/NodeBuffer
       527: dup
       528: invokespecial #146                // Method scala/xml/NodeBuffer."<init>":()V
       531: astore        9
       533: aload         9
       535: aload_0
       536: invokevirtual #214                // Method timeStamp:()J
       539: invokestatic  #218                // Method scala/runtime/BoxesRunTime.boxToLong:(J)Ljava/lang/Long;
       542: invokevirtual #157                // Method scala/xml/NodeBuffer.$amp$plus:(Ljava/lang/Object;)Lscala/xml/NodeBuffer;
       545: pop
       546: aload         9
       548: invokevirtual #179                // Method scala/xml/NodeSeq$.seqToNodeSeq:(Lscala/collection/Seq;)Lscala/xml/NodeSeq;
       551: invokespecial #182                // Method scala/xml/Elem."<init>":(Ljava/lang/String;Ljava/lang/String;Lscala/xml/MetaData;Lscala/xml/NamespaceBinding;ZLscala/collection/immutable/Seq;)V
       554: invokevirtual #157                // Method scala/xml/NodeBuffer.$amp$plus:(Ljava/lang/Object;)Lscala/xml/NodeBuffer;
       557: pop
       558: aload_1
       559: new           #148                // class scala/xml/Text
       562: dup
       563: ldc           #220                // String \n
       565: invokespecial #153                // Method scala/xml/Text."<init>":(Ljava/lang/String;)V
       568: invokevirtual #157                // Method scala/xml/NodeBuffer.$amp$plus:(Ljava/lang/Object;)Lscala/xml/NodeBuffer;
       571: pop
       572: aload_1
       573: invokevirtual #179                // Method scala/xml/NodeSeq$.seqToNodeSeq:(Lscala/collection/Seq;)Lscala/xml/NodeSeq;
       576: invokespecial #182                // Method scala/xml/Elem."<init>":(Ljava/lang/String;Ljava/lang/String;Lscala/xml/MetaData;Lscala/xml/NamespaceBinding;ZLscala/collection/immutable/Seq;)V
       579: areturn
      LineNumberTable:
        line 2009: 0
        line 2010: 40
        line 2011: 80
        line 2010: 131
        line 2011: 132
        line 2010: 145
        line 2009: 156
        line 2012: 157
        line 2009: 170
        line 2013: 171
        line 2009: 219
        line 2013: 220
        line 2009: 233
        line 2014: 234
        line 2009: 289
        line 2014: 290
        line 2009: 303
        line 2015: 304
        line 2009: 359
        line 2015: 360
        line 2009: 373
        line 2016: 374
        line 2009: 429
        line 2016: 430
        line 2009: 443
        line 2017: 444
        line 2009: 492
        line 2017: 493
        line 2009: 506
        line 2018: 507
        line 2009: 558
        line 2018: 559
        line 2009: 572
      LocalVariableTable:
        Start  Length  Slot  Name   Signature
          105      16     3  $buf   Lscala/xml/NodeBuffer;
           65      81     2  $buf   Lscala/xml/NodeBuffer;
          197      12     4  $buf   Lscala/xml/NodeBuffer;
          260      19     5  $buf   Lscala/xml/NodeBuffer;
          330      19     6  $buf   Lscala/xml/NodeBuffer;
          400      19     7  $buf   Lscala/xml/NodeBuffer;
          470      12     8  $buf   Lscala/xml/NodeBuffer;
          533      15     9  $buf   Lscala/xml/NodeBuffer;
           25     548     1  $buf   Lscala/xml/NodeBuffer;
            0     580     0  this   Lorg/scalatest/events/MarkupProvided;

  public java.lang.String toJson();
    descriptor: ()Ljava/lang/String;
    flags: (0x0001) ACC_PUBLIC
    Code:
      stack=5, locals=1, args_size=1
         0: getstatic     #228                // Field scala/collection/StringOps$.MODULE$:Lscala/collection/StringOps$;
         3: getstatic     #233                // Field scala/Predef$.MODULE$:Lscala/Predef$;
         6: new           #235                // class java/lang/StringBuilder
         9: dup
        10: ldc           #236                // int 130
        12: invokespecial #239                // Method java/lang/StringBuilder."<init>":(I)V
        15: ldc           #241                // String { \"eventType\": \"MarkupProvided\", \"ordinal\":
        17: invokevirtual #245                // Method java/lang/StringBuilder.append:(Ljava/lang/String;)Ljava/lang/StringBuilder;
        20: aload_0
        21: invokevirtual #164                // Method ordinal:()Lorg/scalatest/events/Ordinal;
        24: invokevirtual #169                // Method org/scalatest/events/Ordinal.runStamp:()I
        27: invokevirtual #248                // Method java/lang/StringBuilder.append:(I)Ljava/lang/StringBuilder;
        30: ldc           #250                // String , \"text\":
        32: invokevirtual #245                // Method java/lang/StringBuilder.append:(Ljava/lang/String;)Ljava/lang/StringBuilder;
        35: aload_0
        36: invokevirtual #254                // Method EventJsonHelper:()Lorg/scalatest/events/Event$EventJsonHelper$;
        39: aload_0
        40: invokevirtual #185                // Method text:()Ljava/lang/String;
        43: invokevirtual #258                // Method org/scalatest/events/Event$EventJsonHelper$.string:(Ljava/lang/String;)Ljava/lang/String;
        46: invokevirtual #245                // Method java/lang/StringBuilder.append:(Ljava/lang/String;)Ljava/lang/StringBuilder;
        49: ldc_w         #260                // String , \"nameInfo\":
        52: invokevirtual #245                // Method java/lang/StringBuilder.append:(Ljava/lang/String;)Ljava/lang/StringBuilder;
        55: aload_0
        56: invokevirtual #254                // Method EventJsonHelper:()Lorg/scalatest/events/Event$EventJsonHelper$;
        59: aload_0
        60: invokevirtual #192                // Method nameInfo:()Lscala/Option;
        63: invokevirtual #263                // Method org/scalatest/events/Event$EventJsonHelper$.nameInfoOption:(Lscala/Option;)Ljava/lang/String;
        66: invokevirtual #245                // Method java/lang/StringBuilder.append:(Ljava/lang/String;)Ljava/lang/StringBuilder;
        69: ldc_w         #265                // String , \"formatter\":
        72: invokevirtual #245                // Method java/lang/StringBuilder.append:(Ljava/lang/String;)Ljava/lang/StringBuilder;
        75: aload_0
        76: invokevirtual #254                // Method EventJsonHelper:()Lorg/scalatest/events/Event$EventJsonHelper$;
        79: aload_0
        80: invokevirtual #199                // Method formatter:()Lscala/Option;
        83: invokevirtual #267                // Method org/scalatest/events/Event$EventJsonHelper$.formatterOption:(Lscala/Option;)Ljava/lang/String;
        86: invokevirtual #245                // Method java/lang/StringBuilder.append:(Ljava/lang/String;)Ljava/lang/StringBuilder;
        89: ldc_w         #269                // String , \"location\":
        92: invokevirtual #245                // Method java/lang/StringBuilder.append:(Ljava/lang/String;)Ljava/lang/StringBuilder;
        95: aload_0
        96: invokevirtual #254                // Method EventJsonHelper:()Lorg/scalatest/events/Event$EventJsonHelper$;
        99: aload_0
       100: invokevirtual #205                // Method location:()Lscala/Option;
       103: invokevirtual #271                // Method org/scalatest/events/Event$EventJsonHelper$.locationOption:(Lscala/Option;)Ljava/lang/String;
       106: invokevirtual #245                // Method java/lang/StringBuilder.append:(Ljava/lang/String;)Ljava/lang/StringBuilder;
       109: ldc_w         #273                // String , \"threadName\":
       112: invokevirtual #245                // Method java/lang/StringBuilder.append:(Ljava/lang/String;)Ljava/lang/StringBuilder;
       115: aload_0
       116: invokevirtual #254                // Method EventJsonHelper:()Lorg/scalatest/events/Event$EventJsonHelper$;
       119: aload_0
       120: invokevirtual #211                // Method threadName:()Ljava/lang/String;
       123: invokevirtual #258                // Method org/scalatest/events/Event$EventJsonHelper$.string:(Ljava/lang/String;)Ljava/lang/String;
       126: invokevirtual #245                // Method java/lang/StringBuilder.append:(Ljava/lang/String;)Ljava/lang/StringBuilder;
       129: ldc_w         #275                // String , \"timeStamp\":
       132: invokevirtual #245                // Method java/lang/StringBuilder.append:(Ljava/lang/String;)Ljava/lang/StringBuilder;
       135: aload_0
       136: invokevirtual #214                // Method timeStamp:()J
       139: invokevirtual #278                // Method java/lang/StringBuilder.append:(J)Ljava/lang/StringBuilder;
       142: ldc_w         #280                // String  }
       145: invokevirtual #245                // Method java/lang/StringBuilder.append:(Ljava/lang/String;)Ljava/lang/StringBuilder;
       148: invokevirtual #283                // Method java/lang/StringBuilder.toString:()Ljava/lang/String;
       151: invokevirtual #286                // Method scala/Predef$.augmentString:(Ljava/lang/String;)Ljava/lang/String;
       154: invokevirtual #289                // Method scala/collection/StringOps$.stripMargin$extension:(Ljava/lang/String;)Ljava/lang/String;
       157: areturn
      LineNumberTable:
        line 2024: 3
      LocalVariableTable:
        Start  Length  Slot  Name   Signature
            0     158     0  this   Lorg/scalatest/events/MarkupProvided;

  public org.scalatest.events.MarkupProvided withPayload(scala.Option<java.lang.Object>);
    descriptor: (Lscala/Option;)Lorg/scalatest/events/MarkupProvided;
    flags: (0x0001) ACC_PUBLIC
    Code:
      stack=10, locals=11, args_size=2
         0: aload_1
         1: astore_2
         2: aload_0
         3: invokevirtual #296                // Method copy$default$1:()Lorg/scalatest/events/Ordinal;
         6: astore_3
         7: aload_0
         8: invokevirtual #299                // Method copy$default$2:()Ljava/lang/String;
        11: astore        4
        13: aload_0
        14: invokevirtual #302                // Method copy$default$3:()Lscala/Option;
        17: astore        5
        19: aload_0
        20: invokevirtual #305                // Method copy$default$4:()Lscala/Option;
        23: astore        6
        25: aload_0
        26: invokevirtual #308                // Method copy$default$5:()Lscala/Option;
        29: astore        7
        31: aload_0
        32: invokevirtual #311                // Method copy$default$7:()Ljava/lang/String;
        35: astore        8
        37: aload_0
        38: invokevirtual #314                // Method copy$default$8:()J
        41: lstore        9
        43: aload_0
        44: aload_3
        45: aload         4
        47: aload         5
        49: aload         6
        51: aload         7
        53: aload_2
        54: aload         8
        56: lload         9
        58: invokevirtual #317                // Method copy:(Lorg/scalatest/events/Ordinal;Ljava/lang/String;Lscala/Option;Lscala/Option;Lscala/Option;Lscala/Option;Ljava/lang/String;J)Lorg/scalatest/events/MarkupProvided;
        61: areturn
      LineNumberTable:
        line 2027: 0
      LocalVariableTable:
        Start  Length  Slot  Name   Signature
            2      59     2   x$1   Lscala/Option;
            7      54     3   x$2   Lorg/scalatest/events/Ordinal;
           13      48     4   x$3   Ljava/lang/String;
           19      42     5   x$4   Lscala/Option;
           25      36     6   x$5   Lscala/Option;
           31      30     7   x$6   Lscala/Option;
           37      24     8   x$7   Ljava/lang/String;
           43      18     9   x$8   J
            0      62     0  this   Lorg/scalatest/events/MarkupProvided;
            0      62     1 newPayload   Lscala/Option;
    Signature: #292                         // (Lscala/Option<Ljava/lang/Object;>;)Lorg/scalatest/events/MarkupProvided;
    MethodParameters:
      Name                           Flags
      newPayload                     final

  public org.scalatest.events.MarkupProvided copy(org.scalatest.events.Ordinal, java.lang.String, scala.Option<org.scalatest.events.NameInfo>, scala.Option<org.scalatest.events.Formatter>, scala.Option<org.scalatest.events.Location>, scala.Option<java.lang.Object>, java.lang.String, long);
    descriptor: (Lorg/scalatest/events/Ordinal;Ljava/lang/String;Lscala/Option;Lscala/Option;Lscala/Option;Lscala/Option;Ljava/lang/String;J)Lorg/scalatest/events/MarkupProvided;
    flags: (0x0001) ACC_PUBLIC
    Code:
      stack=11, locals=10, args_size=9
         0: new           #2                  // class org/scalatest/events/MarkupProvided
         3: dup
         4: aload_1
         5: aload_2
         6: aload_3
         7: aload         4
         9: aload         5
        11: aload         6
        13: aload         7
        15: lload         8
        17: invokespecial #328                // Method "<init>":(Lorg/scalatest/events/Ordinal;Ljava/lang/String;Lscala/Option;Lscala/Option;Lscala/Option;Lscala/Option;Ljava/lang/String;J)V
        20: areturn
      LineNumberTable:
        line 1987: 0
        line 1988: 4
        line 1989: 5
        line 1990: 6
        line 1991: 7
        line 1992: 9
        line 1993: 11
        line 1994: 13
        line 1995: 15
      LocalVariableTable:
        Start  Length  Slot  Name   Signature
            0      21     0  this   Lorg/scalatest/events/MarkupProvided;
            0      21     1 ordinal   Lorg/scalatest/events/Ordinal;
            0      21     2  text   Ljava/lang/String;
            0      21     3 nameInfo   Lscala/Option;
            0      21     4 formatter   Lscala/Option;
            0      21     5 location   Lscala/Option;
            0      21     6 payload   Lscala/Option;
            0      21     7 threadName   Ljava/lang/String;
            0      21     8 timeStamp   J
    Signature: #89                          // (Lorg/scalatest/events/Ordinal;Ljava/lang/String;Lscala/Option<Lorg/scalatest/events/NameInfo;>;Lscala/Option<Lorg/scalatest/events/Formatter;>;Lscala/Option<Lorg/scalatest/events/Location;>;Lscala/Option<Ljava/lang/Object;>;Ljava/lang/String;J)Lorg/scalatest/events/MarkupProvided;
    MethodParameters:
      Name                           Flags
      ordinal                        final
      text                           final
      nameInfo                       final
      formatter                      final
      location                       final
      payload                        final
      threadName                     final
      timeStamp                      final

  public org.scalatest.events.Ordinal copy$default$1();
    descriptor: ()Lorg/scalatest/events/Ordinal;
    flags: (0x0001) ACC_PUBLIC
    Code:
      stack=1, locals=1, args_size=1
         0: aload_0
         1: invokevirtual #164                // Method ordinal:()Lorg/scalatest/events/Ordinal;
         4: areturn
      LineNumberTable:
        line 1988: 0
      LocalVariableTable:
        Start  Length  Slot  Name   Signature
            0       5     0  this   Lorg/scalatest/events/MarkupProvided;

  public java.lang.String copy$default$2();
    descriptor: ()Ljava/lang/String;
    flags: (0x0001) ACC_PUBLIC
    Code:
      stack=1, locals=1, args_size=1
         0: aload_0
         1: invokevirtual #185                // Method text:()Ljava/lang/String;
         4: areturn
      LineNumberTable:
        line 1989: 0
      LocalVariableTable:
        Start  Length  Slot  Name   Signature
            0       5     0  this   Lorg/scalatest/events/MarkupProvided;

  public scala.Option<org.scalatest.events.NameInfo> copy$default$3();
    descriptor: ()Lscala/Option;
    flags: (0x0001) ACC_PUBLIC
    Code:
      stack=1, locals=1, args_size=1
         0: aload_0
         1: invokevirtual #192                // Method nameInfo:()Lscala/Option;
         4: areturn
      LineNumberTable:
        line 1990: 0
      LocalVariableTable:
        Start  Length  Slot  Name   Signature
            0       5     0  this   Lorg/scalatest/events/MarkupProvided;
    Signature: #107                         // ()Lscala/Option<Lorg/scalatest/events/NameInfo;>;

  public scala.Option<org.scalatest.events.Formatter> copy$default$4();
    descriptor: ()Lscala/Option;
    flags: (0x0001) ACC_PUBLIC
    Code:
      stack=1, locals=1, args_size=1
         0: aload_0
         1: invokevirtual #199                // Method formatter:()Lscala/Option;
         4: areturn
      LineNumberTable:
        line 1991: 0
      LocalVariableTable:
        Start  Length  Slot  Name   Signature
            0       5     0  this   Lorg/scalatest/events/MarkupProvided;
    Signature: #62                          // ()Lscala/Option<Lorg/scalatest/events/Formatter;>;

  public scala.Option<org.scalatest.events.Location> copy$default$5();
    descriptor: ()Lscala/Option;
    flags: (0x0001) ACC_PUBLIC
    Code:
      stack=1, locals=1, args_size=1
         0: aload_0
         1: invokevirtual #205                // Method location:()Lscala/Option;
         4: areturn
      LineNumberTable:
        line 1992: 0
      LocalVariableTable:
        Start  Length  Slot  Name   Signature
            0       5     0  this   Lorg/scalatest/events/MarkupProvided;
    Signature: #58                          // ()Lscala/Option<Lorg/scalatest/events/Location;>;

  public scala.Option<java.lang.Object> copy$default$6();
    descriptor: ()Lscala/Option;
    flags: (0x0001) ACC_PUBLIC
    Code:
      stack=1, locals=1, args_size=1
         0: aload_0
         1: invokevirtual #331                // Method payload:()Lscala/Option;
         4: areturn
      LineNumberTable:
        line 1993: 0
      LocalVariableTable:
        Start  Length  Slot  Name   Signature
            0       5     0  this   Lorg/scalatest/events/MarkupProvided;
    Signature: #54                          // ()Lscala/Option<Ljava/lang/Object;>;

  public java.lang.String copy$default$7();
    descriptor: ()Ljava/lang/String;
    flags: (0x0001) ACC_PUBLIC
    Code:
      stack=1, locals=1, args_size=1
         0: aload_0
         1: invokevirtual #211                // Method threadName:()Ljava/lang/String;
         4: areturn
      LineNumberTable:
        line 1994: 0
      LocalVariableTable:
        Start  Length  Slot  Name   Signature
            0       5     0  this   Lorg/scalatest/events/MarkupProvided;

  public long copy$default$8();
    descriptor: ()J
    flags: (0x0001) ACC_PUBLIC
    Code:
      stack=2, locals=1, args_size=1
         0: aload_0
         1: invokevirtual #214                // Method timeStamp:()J
         4: lreturn
      LineNumberTable:
        line 1995: 0
      LocalVariableTable:
        Start  Length  Slot  Name   Signature
            0       5     0  this   Lorg/scalatest/events/MarkupProvided;

  public java.lang.String productPrefix();
    descriptor: ()Ljava/lang/String;
    flags: (0x0001) ACC_PUBLIC
    Code:
      stack=1, locals=1, args_size=1
         0: ldc           #125                // String MarkupProvided
         2: areturn
      LineNumberTable:
        line 1987: 0
      LocalVariableTable:
        Start  Length  Slot  Name   Signature
            0       3     0  this   Lorg/scalatest/events/MarkupProvided;

  public int productArity();
    descriptor: ()I
    flags: (0x0001) ACC_PUBLIC
    Code:
      stack=1, locals=1, args_size=1
         0: bipush        8
         2: ireturn
      LineNumberTable:
        line 1987: 0
      LocalVariableTable:
        Start  Length  Slot  Name   Signature
            0       3     0  this   Lorg/scalatest/events/MarkupProvided;

  public java.lang.Object productElement(int);
    descriptor: (I)Ljava/lang/Object;
    flags: (0x0001) ACC_PUBLIC
    Code:
      stack=2, locals=3, args_size=2
         0: iload_1
         1: istore_2
         2: iload_2
         3: tableswitch   { // 0 to 7
                       0: 48
                       1: 55
                       2: 62
                       3: 69
                       4: 76
                       5: 83
                       6: 90
                       7: 97
                 default: 107
            }
        48: aload_0
        49: invokevirtual #164                // Method ordinal:()Lorg/scalatest/events/Ordinal;
        52: goto          114
        55: aload_0
        56: invokevirtual #185                // Method text:()Ljava/lang/String;
        59: goto          114
        62: aload_0
        63: invokevirtual #192                // Method nameInfo:()Lscala/Option;
        66: goto          114
        69: aload_0
        70: invokevirtual #199                // Method formatter:()Lscala/Option;
        73: goto          114
        76: aload_0
        77: invokevirtual #205                // Method location:()Lscala/Option;
        80: goto          114
        83: aload_0
        84: invokevirtual #331                // Method payload:()Lscala/Option;
        87: goto          114
        90: aload_0
        91: invokevirtual #211                // Method threadName:()Ljava/lang/String;
        94: goto          114
        97: aload_0
        98: invokevirtual #214                // Method timeStamp:()J
       101: invokestatic  #218                // Method scala/runtime/BoxesRunTime.boxToLong:(J)Ljava/lang/Long;
       104: goto          114
       107: iload_1
       108: invokestatic  #340                // Method scala/runtime/Statics.ioobe:(I)Ljava/lang/Object;
       111: goto          114
       114: areturn
      StackMapTable: number_of_entries = 10
        frame_type = 252 /* append */
          offset_delta = 48
          locals = [ int ]
        frame_type = 6 /* same */
        frame_type = 6 /* same */
        frame_type = 6 /* same */
        frame_type = 6 /* same */
        frame_type = 6 /* same */
        frame_type = 6 /* same */
        frame_type = 6 /* same */
        frame_type = 9 /* same */
        frame_type = 70 /* same_locals_1_stack_item */
          stack = [ class java/lang/Object ]
      LineNumberTable:
        line 1987: 0
      LocalVariableTable:
        Start  Length  Slot  Name   Signature
            0     115     0  this   Lorg/scalatest/events/MarkupProvided;
            0     115     1   x$1   I
    MethodParameters:
      Name                           Flags
      x$1                            final

  public scala.collection.Iterator<java.lang.Object> productIterator();
    descriptor: ()Lscala/collection/Iterator;
    flags: (0x0001) ACC_PUBLIC
    Code:
      stack=2, locals=1, args_size=1
         0: getstatic     #351                // Field scala/runtime/ScalaRunTime$.MODULE$:Lscala/runtime/ScalaRunTime$;
         3: aload_0
         4: invokevirtual #355                // Method scala/runtime/ScalaRunTime$.typedProductIterator:(Lscala/Product;)Lscala/collection/Iterator;
         7: areturn
      LineNumberTable:
        line 1987: 0
      LocalVariableTable:
        Start  Length  Slot  Name   Signature
            0       8     0  this   Lorg/scalatest/events/MarkupProvided;
    Signature: #346                         // ()Lscala/collection/Iterator<Ljava/lang/Object;>;

  public boolean canEqual(java.lang.Object);
    descriptor: (Ljava/lang/Object;)Z
    flags: (0x0001) ACC_PUBLIC
    Code:
      stack=1, locals=2, args_size=2
         0: aload_1
         1: instanceof    #2                  // class org/scalatest/events/MarkupProvided
         4: ireturn
      LineNumberTable:
        line 1987: 0
      LocalVariableTable:
        Start  Length  Slot  Name   Signature
            0       5     0  this   Lorg/scalatest/events/MarkupProvided;
            0       5     1   x$1   Ljava/lang/Object;
    MethodParameters:
      Name                           Flags
      x$1                            final

  public java.lang.String productElementName(int);
    descriptor: (I)Ljava/lang/String;
    flags: (0x0001) ACC_PUBLIC
    Code:
      stack=1, locals=3, args_size=2
         0: iload_1
         1: istore_2
         2: iload_2
         3: tableswitch   { // 0 to 7
                       0: 48
                       1: 53
                       2: 58
                       3: 63
                       4: 68
                       5: 73
                       6: 79
                       7: 84
                 default: 89
            }
        48: ldc           #158                // String ordinal
        50: goto          99
        53: ldc           #183                // String text
        55: goto          99
        58: ldc           #186                // String nameInfo
        60: goto          99
        63: ldc           #197                // String formatter
        65: goto          99
        68: ldc           #203                // String location
        70: goto          99
        73: ldc_w         #361                // String payload
        76: goto          99
        79: ldc           #209                // String threadName
        81: goto          99
        84: ldc           #212                // String timeStamp
        86: goto          99
        89: iload_1
        90: invokestatic  #340                // Method scala/runtime/Statics.ioobe:(I)Ljava/lang/Object;
        93: checkcast     #363                // class java/lang/String
        96: goto          99
        99: areturn
      StackMapTable: number_of_entries = 10
        frame_type = 252 /* append */
          offset_delta = 48
          locals = [ int ]
        frame_type = 4 /* same */
        frame_type = 4 /* same */
        frame_type = 4 /* same */
        frame_type = 4 /* same */
        frame_type = 4 /* same */
        frame_type = 5 /* same */
        frame_type = 4 /* same */
        frame_type = 4 /* same */
        frame_type = 73 /* same_locals_1_stack_item */
          stack = [ class java/lang/String ]
      LineNumberTable:
        line 1987: 0
      LocalVariableTable:
        Start  Length  Slot  Name   Signature
            0     100     0  this   Lorg/scalatest/events/MarkupProvided;
            0     100     1   x$1   I
    MethodParameters:
      Name                           Flags
      x$1                            final

  public int hashCode();
    descriptor: ()I
    flags: (0x0001) ACC_PUBLIC
    Code:
      stack=3, locals=2, args_size=1
         0: ldc_w         #365                // int -889275714
         3: istore_1
         4: iload_1
         5: aload_0
         6: invokevirtual #367                // Method productPrefix:()Ljava/lang/String;
         9: invokevirtual #369                // Method java/lang/String.hashCode:()I
        12: invokestatic  #373                // Method scala/runtime/Statics.mix:(II)I
        15: istore_1
        16: iload_1
        17: aload_0
        18: invokevirtual #164                // Method ordinal:()Lorg/scalatest/events/Ordinal;
        21: invokestatic  #377                // Method scala/runtime/Statics.anyHash:(Ljava/lang/Object;)I
        24: invokestatic  #373                // Method scala/runtime/Statics.mix:(II)I
        27: istore_1
        28: iload_1
        29: aload_0
        30: invokevirtual #185                // Method text:()Ljava/lang/String;
        33: invokestatic  #377                // Method scala/runtime/Statics.anyHash:(Ljava/lang/Object;)I
        36: invokestatic  #373                // Method scala/runtime/Statics.mix:(II)I
        39: istore_1
        40: iload_1
        41: aload_0
        42: invokevirtual #192                // Method nameInfo:()Lscala/Option;
        45: invokestatic  #377                // Method scala/runtime/Statics.anyHash:(Ljava/lang/Object;)I
        48: invokestatic  #373                // Method scala/runtime/Statics.mix:(II)I
        51: istore_1
        52: iload_1
        53: aload_0
        54: invokevirtual #199                // Method formatter:()Lscala/Option;
        57: invokestatic  #377                // Method scala/runtime/Statics.anyHash:(Ljava/lang/Object;)I
        60: invokestatic  #373                // Method scala/runtime/Statics.mix:(II)I
        63: istore_1
        64: iload_1
        65: aload_0
        66: invokevirtual #205                // Method location:()Lscala/Option;
        69: invokestatic  #377                // Method scala/runtime/Statics.anyHash:(Ljava/lang/Object;)I
        72: invokestatic  #373                // Method scala/runtime/Statics.mix:(II)I
        75: istore_1
        76: iload_1
        77: aload_0
        78: invokevirtual #331                // Method payload:()Lscala/Option;
        81: invokestatic  #377                // Method scala/runtime/Statics.anyHash:(Ljava/lang/Object;)I
        84: invokestatic  #373                // Method scala/runtime/Statics.mix:(II)I
        87: istore_1
        88: iload_1
        89: aload_0
        90: invokevirtual #211                // Method threadName:()Ljava/lang/String;
        93: invokestatic  #377                // Method scala/runtime/Statics.anyHash:(Ljava/lang/Object;)I
        96: invokestatic  #373                // Method scala/runtime/Statics.mix:(II)I
        99: istore_1
       100: iload_1
       101: aload_0
       102: invokevirtual #214                // Method timeStamp:()J
       105: invokestatic  #381                // Method scala/runtime/Statics.longHash:(J)I
       108: invokestatic  #373                // Method scala/runtime/Statics.mix:(II)I
       111: istore_1
       112: iload_1
       113: bipush        8
       115: invokestatic  #384                // Method scala/runtime/Statics.finalizeHash:(II)I
       118: ireturn
      LineNumberTable:
        line 1987: 0
      LocalVariableTable:
        Start  Length  Slot  Name   Signature
            0     119     0  this   Lorg/scalatest/events/MarkupProvided;

  public java.lang.String toString();
    descriptor: ()Ljava/lang/String;
    flags: (0x0001) ACC_PUBLIC
    Code:
      stack=2, locals=1, args_size=1
         0: getstatic     #351                // Field scala/runtime/ScalaRunTime$.MODULE$:Lscala/runtime/ScalaRunTime$;
         3: aload_0
         4: invokevirtual #388                // Method scala/runtime/ScalaRunTime$._toString:(Lscala/Product;)Ljava/lang/String;
         7: areturn
      LineNumberTable:
        line 1987: 0
      LocalVariableTable:
        Start  Length  Slot  Name   Signature
            0       8     0  this   Lorg/scalatest/events/MarkupProvided;

  public boolean equals(java.lang.Object);
    descriptor: (Ljava/lang/Object;)Z
    flags: (0x0001) ACC_PUBLIC
    Code:
      stack=4, locals=12, args_size=2
         0: aload_0
         1: aload_1
         2: if_acmpeq     282
         5: aload_1
         6: astore_3
         7: aload_3
         8: instanceof    #2                  // class org/scalatest/events/MarkupProvided
        11: ifeq          19
        14: iconst_1
        15: istore_2
        16: goto          27
        19: goto          22
        22: iconst_0
        23: istore_2
        24: goto          27
        27: iload_2
        28: ifeq          286
        31: aload_1
        32: checkcast     #2                  // class org/scalatest/events/MarkupProvided
        35: astore        4
        37: aload_0
        38: invokevirtual #214                // Method timeStamp:()J
        41: aload         4
        43: invokevirtual #214                // Method timeStamp:()J
        46: lcmp
        47: ifne          278
        50: aload_0
        51: invokevirtual #164                // Method ordinal:()Lorg/scalatest/events/Ordinal;
        54: aload         4
        56: invokevirtual #164                // Method ordinal:()Lorg/scalatest/events/Ordinal;
        59: astore        5
        61: dup
        62: ifnonnull     74
        65: pop
        66: aload         5
        68: ifnull        82
        71: goto          278
        74: aload         5
        76: invokevirtual #391                // Method java/lang/Object.equals:(Ljava/lang/Object;)Z
        79: ifeq          278
        82: aload_0
        83: invokevirtual #185                // Method text:()Ljava/lang/String;
        86: aload         4
        88: invokevirtual #185                // Method text:()Ljava/lang/String;
        91: astore        6
        93: dup
        94: ifnonnull     106
        97: pop
        98: aload         6
       100: ifnull        114
       103: goto          278
       106: aload         6
       108: invokevirtual #391                // Method java/lang/Object.equals:(Ljava/lang/Object;)Z
       111: ifeq          278
       114: aload_0
       115: invokevirtual #192                // Method nameInfo:()Lscala/Option;
       118: aload         4
       120: invokevirtual #192                // Method nameInfo:()Lscala/Option;
       123: astore        7
       125: dup
       126: ifnonnull     138
       129: pop
       130: aload         7
       132: ifnull        146
       135: goto          278
       138: aload         7
       140: invokevirtual #391                // Method java/lang/Object.equals:(Ljava/lang/Object;)Z
       143: ifeq          278
       146: aload_0
       147: invokevirtual #199                // Method formatter:()Lscala/Option;
       150: aload         4
       152: invokevirtual #199                // Method formatter:()Lscala/Option;
       155: astore        8
       157: dup
       158: ifnonnull     170
       161: pop
       162: aload         8
       164: ifnull        178
       167: goto          278
       170: aload         8
       172: invokevirtual #391                // Method java/lang/Object.equals:(Ljava/lang/Object;)Z
       175: ifeq          278
       178: aload_0
       179: invokevirtual #205                // Method location:()Lscala/Option;
       182: aload         4
       184: invokevirtual #205                // Method location:()Lscala/Option;
       187: astore        9
       189: dup
       190: ifnonnull     202
       193: pop
       194: aload         9
       196: ifnull        210
       199: goto          278
       202: aload         9
       204: invokevirtual #391                // Method java/lang/Object.equals:(Ljava/lang/Object;)Z
       207: ifeq          278
       210: aload_0
       211: invokevirtual #331                // Method payload:()Lscala/Option;
       214: aload         4
       216: invokevirtual #331                // Method payload:()Lscala/Option;
       219: astore        10
       221: dup
       222: ifnonnull     234
       225: pop
       226: aload         10
       228: ifnull        242
       231: goto          278
       234: aload         10
       236: invokevirtual #391                // Method java/lang/Object.equals:(Ljava/lang/Object;)Z
       239: ifeq          278
       242: aload_0
       243: invokevirtual #211                // Method threadName:()Ljava/lang/String;
       246: aload         4
       248: invokevirtual #211                // Method threadName:()Ljava/lang/String;
       251: astore        11
       253: dup
       254: ifnonnull     266
       257: pop
       258: aload         11
       260: ifnull        274
       263: goto          278
       266: aload         11
       268: invokevirtual #391                // Method java/lang/Object.equals:(Ljava/lang/Object;)Z
       271: ifeq          278
       274: iconst_1
       275: goto          279
       278: iconst_0
       279: ifeq          286
       282: iconst_1
       283: goto          287
       286: iconst_0
       287: ireturn
      StackMapTable: number_of_entries = 22
        frame_type = 253 /* append */
          offset_delta = 19
          locals = [ top, class java/lang/Object ]
        frame_type = 2 /* same */
        frame_type = 255 /* full_frame */
          offset_delta = 4
          locals = [ class org/scalatest/events/MarkupProvided, class java/lang/Object, int, class java/lang/Object ]
          stack = []
        frame_type = 255 /* full_frame */
          offset_delta = 46
          locals = [ class org/scalatest/events/MarkupProvided, class java/lang/Object, int, class java/lang/Object, class org/scalatest/events/MarkupProvided, class org/scalatest/events/Ordinal ]
          stack = [ class org/scalatest/events/Ordinal ]
        frame_type = 7 /* same */
        frame_type = 255 /* full_frame */
          offset_delta = 23
          locals = [ class org/scalatest/events/MarkupProvided, class java/lang/Object, int, class java/lang/Object, class org/scalatest/events/MarkupProvided, class org/scalatest/events/Ordinal, class java/lang/String ]
          stack = [ class java/lang/String ]
        frame_type = 7 /* same */
        frame_type = 255 /* full_frame */
          offset_delta = 23
          locals = [ class org/scalatest/events/MarkupProvided, class java/lang/Object, int, class java/lang/Object, class org/scalatest/events/MarkupProvided, class org/scalatest/events/Ordinal, class java/lang/String, class scala/Option ]
          stack = [ class scala/Option ]
        frame_type = 7 /* same */
        frame_type = 255 /* full_frame */
          offset_delta = 23
          locals = [ class org/scalatest/events/MarkupProvided, class java/lang/Object, int, class java/lang/Object, class org/scalatest/events/MarkupProvided, class org/scalatest/events/Ordinal, class java/lang/String, class scala/Option, class scala/Option ]
          stack = [ class scala/Option ]
        frame_type = 7 /* same */
        frame_type = 255 /* full_frame */
          offset_delta = 23
          locals = [ class org/scalatest/events/MarkupProvided, class java/lang/Object, int, class java/lang/Object, class org/scalatest/events/MarkupProvided, class org/scalatest/events/Ordinal, class java/lang/String, class scala/Option, class scala/Option, class scala/Option ]
          stack = [ class scala/Option ]
        frame_type = 7 /* same */
        frame_type = 255 /* full_frame */
          offset_delta = 23
          locals = [ class org/scalatest/events/MarkupProvided, class java/lang/Object, int, class java/lang/Object, class org/scalatest/events/MarkupProvided, class org/scalatest/events/Ordinal, class java/lang/String, class scala/Option, class scala/Option, class scala/Option, class scala/Option ]
          stack = [ class scala/Option ]
        frame_type = 7 /* same */
        frame_type = 255 /* full_frame */
          offset_delta = 23
          locals = [ class org/scalatest/events/MarkupProvided, class java/lang/Object, int, class java/lang/Object, class org/scalatest/events/MarkupProvided, class org/scalatest/events/Ordinal, class java/lang/String, class scala/Option, class scala/Option, class scala/Option, class scala/Option, class java/lang/String ]
          stack = [ class java/lang/String ]
        frame_type = 7 /* same */
        frame_type = 255 /* full_frame */
          offset_delta = 3
          locals = [ class org/scalatest/events/MarkupProvided, class java/lang/Object, int, class java/lang/Object, class org/scalatest/events/MarkupProvided ]
          stack = []
        frame_type = 64 /* same_locals_1_stack_item */
          stack = [ int ]
        frame_type = 248 /* chop */
          offset_delta = 2
        frame_type = 253 /* append */
          offset_delta = 3
          locals = [ int, class java/lang/Object ]
        frame_type = 255 /* full_frame */
          offset_delta = 0
          locals = [ class org/scalatest/events/MarkupProvided, class java/lang/Object ]
          stack = [ int ]
      LineNumberTable:
        line 1987: 0
      LocalVariableTable:
        Start  Length  Slot  Name   Signature
            0     288     0  this   Lorg/scalatest/events/MarkupProvided;
            0     288     1   x$1   Ljava/lang/Object;
    MethodParameters:
      Name                           Flags
      x$1                            final

  public org.scalatest.events.Event withPayload(scala.Option);
    descriptor: (Lscala/Option;)Lorg/scalatest/events/Event;
    flags: (0x1041) ACC_PUBLIC, ACC_BRIDGE, ACC_SYNTHETIC
    Code:
      stack=2, locals=2, args_size=2
         0: aload_0
         1: aload_1
         2: invokevirtual #396                // Method withPayload:(Lscala/Option;)Lorg/scalatest/events/MarkupProvided;
         5: areturn
      LineNumberTable:
        line 1987: 0
      LocalVariableTable:
        Start  Length  Slot  Name   Signature
            0       6     0  this   Lorg/scalatest/events/MarkupProvided;
            0       6     1 newPayload   Lscala/Option;
    MethodParameters:
      Name                           Flags
      newPayload                     final

  public org.scalatest.events.MarkupProvided(org.scalatest.events.Ordinal, java.lang.String, scala.Option<org.scalatest.events.NameInfo>, scala.Option<org.scalatest.events.Formatter>, scala.Option<org.scalatest.events.Location>, scala.Option<java.lang.Object>, java.lang.String, long);
    descriptor: (Lorg/scalatest/events/Ordinal;Ljava/lang/String;Lscala/Option;Lscala/Option;Lscala/Option;Lscala/Option;Ljava/lang/String;J)V
    flags: (0x0001) ACC_PUBLIC
    Code:
      stack=9, locals=10, args_size=9
         0: aload_0
         1: aload_1
         2: putfield      #103                // Field ordinal:Lorg/scalatest/events/Ordinal;
         5: aload_0
         6: aload_2
         7: putfield      #106                // Field text:Ljava/lang/String;
        10: aload_0
        11: aload_3
        12: putfield      #109                // Field nameInfo:Lscala/Option;
        15: aload_0
        16: aload         4
        18: putfield      #111                // Field formatter:Lscala/Option;
        21: aload_0
        22: aload         5
        24: putfield      #113                // Field location:Lscala/Option;
        27: aload_0
        28: aload         6
        30: putfield      #115                // Field payload:Lscala/Option;
        33: aload_0
        34: aload         7
        36: putfield      #117                // Field threadName:Ljava/lang/String;
        39: aload_0
        40: lload         8
        42: putfield      #119                // Field timeStamp:J
        45: aload_0
        46: invokespecial #398                // Method org/scalatest/events/Event."<init>":()V
        49: getstatic     #403                // Field org/scalactic/Requirements$.MODULE$:Lorg/scalactic/Requirements$;
        52: invokevirtual #407                // Method org/scalactic/Requirements$.requirementsHelper:()Lorg/scalactic/Requirements$RequirementsHelper;
        55: bipush        7
        57: anewarray     #363                // class java/lang/String
        60: dup
        61: iconst_0
        62: ldc_w         #409                // String MarkupProvided.this.ordinal
        65: aastore
        66: dup
        67: iconst_1
        68: ldc_w         #411                // String MarkupProvided.this.text
        71: aastore
        72: dup
        73: iconst_2
        74: ldc_w         #413                // String MarkupProvided.this.nameInfo
        77: aastore
        78: dup
        79: iconst_3
        80: ldc_w         #415                // String MarkupProvided.this.formatter
        83: aastore
        84: dup
        85: iconst_4
        86: ldc_w         #417                // String MarkupProvided.this.location
        89: aastore
        90: dup
        91: iconst_5
        92: ldc_w         #419                // String MarkupProvided.this.payload
        95: aastore
        96: dup
        97: bipush        6
        99: ldc_w         #421                // String MarkupProvided.this.threadName
       102: aastore
       103: checkcast     #423                // class "[Ljava/lang/Object;"
       106: checkcast     #425                // class "[Ljava/lang/String;"
       109: bipush        7
       111: anewarray     #343                // class java/lang/Object
       114: dup
       115: iconst_0
       116: aload_1
       117: aastore
       118: dup
       119: iconst_1
       120: aload_2
       121: aastore
       122: dup
       123: iconst_2
       124: aload_3
       125: aastore
       126: dup
       127: iconst_3
       128: aload         4
       130: aastore
       131: dup
       132: iconst_4
       133: aload         5
       135: aastore
       136: dup
       137: iconst_5
       138: aload         6
       140: aastore
       141: dup
       142: bipush        6
       144: aload         7
       146: aastore
       147: checkcast     #423                // class "[Ljava/lang/Object;"
       150: getstatic     #430                // Field org/scalactic/Prettifier$.MODULE$:Lorg/scalactic/Prettifier$;
       153: invokevirtual #434                // Method org/scalactic/Prettifier$.default:()Lorg/scalactic/Prettifier;
       156: new           #436                // class org/scalactic/source/Position
       159: dup
       160: ldc_w         #437                // String Event.scala
       163: ldc_w         #439                // String Please set the environment variable SCALACTIC_FILL_FILE_PATHNAMES to yes at compile time to enable this feature.
       166: sipush        1998
       169: invokespecial #442                // Method org/scalactic/source/Position."<init>":(Ljava/lang/String;Ljava/lang/String;I)V
       172: invokevirtual #446                // Method org/scalactic/Requirements$RequirementsHelper.macroRequireNonNull:([Ljava/lang/String;[Ljava/lang/Object;Lorg/scalactic/Prettifier;Lorg/scalactic/source/Position;)V
       175: return
      LineNumberTable:
        line 1988: 0
        line 1989: 5
        line 1990: 10
        line 1991: 15
        line 1992: 21
        line 1993: 27
        line 1994: 33
        line 1995: 39
        line 1996: 45
        line 1998: 49
        line 1999: 120
        line 2000: 124
        line 2001: 128
        line 2002: 133
        line 2003: 138
        line 2004: 144
        line 1998: 150
        line 1987: 175
      LocalVariableTable:
        Start  Length  Slot  Name   Signature
            0     176     0  this   Lorg/scalatest/events/MarkupProvided;
            0     176     1 ordinal   Lorg/scalatest/events/Ordinal;
            0     176     2  text   Ljava/lang/String;
            0     176     3 nameInfo   Lscala/Option;
            0     176     4 formatter   Lscala/Option;
            0     176     5 location   Lscala/Option;
            0     176     6 payload   Lscala/Option;
            0     176     7 threadName   Ljava/lang/String;
            0     176     8 timeStamp   J
    Signature: #397                         // (Lorg/scalatest/events/Ordinal;Ljava/lang/String;Lscala/Option<Lorg/scalatest/events/NameInfo;>;Lscala/Option<Lorg/scalatest/events/Formatter;>;Lscala/Option<Lorg/scalatest/events/Location;>;Lscala/Option<Ljava/lang/Object;>;Ljava/lang/String;J)V
    MethodParameters:
      Name                           Flags
      ordinal                        final
      text                           final
      nameInfo                       final
      formatter                      final
      location                       final
      payload                        final
      threadName                     final
      timeStamp                      final
}
InnerClasses:
  public static #15= #12 of #14;          // RequirementsHelper=class org/scalactic/Requirements$RequirementsHelper of class org/scalactic/Requirements
  public #18= #17 of #4;                  // EventJsonHelper$=class org/scalatest/events/Event$EventJsonHelper$ of class org/scalatest/events/Event
  public #21= #20 of #4;                  // EventXmlHelper$=class org/scalatest/events/Event$EventXmlHelper$ of class org/scalatest/events/Event
SourceFile: "Event.scala"
RuntimeVisibleAnnotations:
  0: #8(#9=s#10)
    scala.reflect.ScalaSignature(
      bytes="\u0006\u0005\tec\u0001\u0002\u001d:\u0005\u0002C\u0001B\u0017\u0001\u0003\u0016\u0004%\ta\u0017\u0005\t?\u0002\u0011\t\u0012)A\u00059\"A\u0001\r\u0001BK\u0002\u0013\u0005\u0011\r\u0003\u0005k\u0001\tE\t\u0015!\u0003c\u0011!Y\u0007A!f\u0001\n\u0003a\u0007\u0002C:\u0001\u0005#\u0005\u000b\u0011B7\t\u0011Q\u0004!Q3A\u0005\u0002UD\u0001B\u001f\u0001\u0003\u0012\u0003\u0006IA\u001e\u0005\tw\u0002\u0011)\u001a!C\u0001y\"I\u00111\u0001\u0001\u0003\u0012\u0003\u0006I! \u0005\u000b\u0003\u000b\u0001!Q3A\u0005\u0002\u0005\u001d\u0001BCA\t\u0001\tE\t\u0015!\u0003\u0002\n!I\u00111\u0003\u0001\u0003\u0016\u0004%\t!\u0019\u0005\n\u0003+\u0001!\u0011#Q\u0001\n\tD!\"a\u0006\u0001\u0005+\u0007I\u0011AA\r\u0011)\t\t\u0003\u0001B\tB\u0003%\u00111\u0004\u0005\b\u0003G\u0001A\u0011AA\u0013\u0011!\tI\u0004\u0001C\u0001w\u0005m\u0002bBA%\u0001\u0011\u00051(\u0019\u0005\t\u0003\u0017\u0002A\u0011A\u001d\u0002N!I\u00111\u000b\u0001\u0002\u0002\u0013\u0005\u0011Q\u000b\u0005\n\u0003O\u0002\u0011\u0013!C\u0001\u0003SB\u0011\"a \u0001#\u0003%\t!!!\t\u0013\u0005\u0015\u0005!%A\u0005\u0002\u0005\u001d\u0005\"CAF\u0001E\u0005I\u0011AAG\u0011%\t\t\nAI\u0001\n\u0003\t\u0019\nC\u0005\u0002\u0018\u0002\t\n\u0011\"\u0001\u0002\u001a\"I\u0011Q\u0014\u0001\u0012\u0002\u0013\u0005\u0011\u0011\u0011\u0005\n\u0003?\u0003\u0011\u0013!C\u0001\u0003CC\u0011\"!*\u0001\u0003\u0003%\t%a*\t\u0013\u0005]\u0006!!A\u0005\u0002\u0005e\u0006\"CAa\u0001\u0005\u0005I\u0011AAb\u0011%\tI\rAA\u0001\n\u0003\nY\rC\u0005\u0002Z\u0002\t\t\u0011\"\u0001\u0002\\\"I\u0011Q\u001d\u0001\u0002\u0002\u0013\u0005\u0013q\u001d\u0005\n\u0003W\u0004\u0011\u0011!C!\u0003[D\u0011\"a<\u0001\u0003\u0003%\t%!=\t\u0013\u0005M\b!!A\u0005B\u0005Ux!CA}s\u0005\u0005\t\u0012AA~\r!A\u0014(!A\t\u0002\u0005u\bbBA\u0012Q\u0011\u0005!Q\u0003\u0005\n\u0003_D\u0013\u0011!C#\u0003cD\u0011Ba\u0006)\u0003\u0003%\tI!\u0007\t\u0013\t-\u0002&%A\u0005\u0002\u00055\u0005\"\u0003B\u0017QE\u0005I\u0011AAJ\u0011%\u0011y\u0003KI\u0001\n\u0003\tI\nC\u0005\u00032!\n\n\u0011\"\u0001\u0002\u0002\"I!1\u0007\u0015\u0012\u0002\u0013\u0005\u0011\u0011\u0015\u0005\n\u0005kA\u0013\u0011!CA\u0005oA\u0011B!\u0012)#\u0003%\t!!$\t\u0013\t\u001d\u0003&%A\u0005\u0002\u0005M\u0005\"\u0003B%QE\u0005I\u0011AAM\u0011%\u0011Y\u0005KI\u0001\n\u0003\t\t\tC\u0005\u0003N!\n\n\u0011\"\u0001\u0002\"\"I!q\n\u0015\u0002\u0002\u0013%!\u0011\u000b\u0002\u000f\u001b\u0006\u00148.\u001e9Qe>4\u0018\u000eZ3e\u0015\tQ4(\u0001\u0004fm\u0016tGo\u001d\u0006\u0003yu\n\u0011b]2bY\u0006$Xm\u001d;\u000b\u0003y\n1a\u001c:h\u0007\u0001\u0019R\u0001A!F\u0011:\u0003\"AQ\"\u000e\u0003eJ!\u0001R\u001d\u0003\u000b\u00153XM\u001c;\u0011\u0005\t3\u0015BA$:\u0005=\u0011VmY8sI\u0006\u0014G.Z#wK:$\bCA%M\u001b\u0005Q%\"A&\u0002\u000bM\u001c\u0017\r\\1\n\u00055S%a\u0002)s_\u0012,8\r\u001e\t\u0003\u001f^s!\u0001U+\u000f\u0005E#V\"\u0001*\u000b\u0005M{\u0014A\u0002\u001fs_>$h(C\u0001L\u0013\t1&*A\u0004qC\u000e\\\u0017mZ3\n\u0005aK&\u0001D*fe&\fG.\u001b>bE2,\'B\u0001,K\u0003\u001dy\'\u000fZ5oC2,\u0012\u0001\u0018\t\u0003\u0005vK!AX\u001d\u0003\u000f=\u0013H-\u001b8bY\u0006AqN\u001d3j]\u0006d\u0007%\u0001\u0003uKb$X#\u00012\u0011\u0005\r<gB\u00013f!\t\t&*\u0003\u0002g\u0015\u00061\u0001K]3eK\u001aL!\u0001[5\u0003\rM#(/\u001b8h\u0015\t1\'*A\u0003uKb$\b%\u0001\u0005oC6,\u0017J\u001c4p+\u0005i\u0007cA%oa&\u0011qN\u0013\u0002\u0007\u001fB$\u0018n\u001c8\u0011\u0005\t\u000b\u0018B\u0001::\u0005!q\u0015-\\3J]\u001a|\u0017!\u00038b[\u0016LeNZ8!\u0003%1wN]7biR,\'/F\u0001w!\rIen\u001e\t\u0003\u0005bL!!_\u001d\u0003\u0013\u0019{\'/\\1ui\u0016\u0014\u0018A\u00034pe6\fG\u000f^3sA\u0005AAn\\2bi&|g.F\u0001~!\rIeN \t\u0003\u0005~L1!!\u0001:\u0005!aunY1uS>t\u0017!\u00037pG\u0006$\u0018n\u001c8!\u0003\u001d\u0001\u0018-\u001f7pC\u0012,\"!!\u0003\u0011\t%s\u00171\u0002\t\u0004\u0013\u00065\u0011bAA\b\u0015\n\u0019\u0011I\\=\u0002\u0011A\f\u0017\u0010\\8bI\u0002\n!\u0002\u001e5sK\u0006$g*Y7f\u0003-!\bN]3bI:\u000bW.\u001a\u0011\u0002\u0013QLW.Z*uC6\u0004XCAA\u000e!\rI\u0015QD\u0005\u0004\u0003?Q%\u0001\u0002\'p]\u001e\f!\u0002^5nKN#\u0018-\u001c9!\u0003\u0019a\u0014N\\5u}Q\u0011\u0012qEA\u0015\u0003W\ti#a\f\u00022\u0005M\u0012QGA\u001c!\t\u0011\u0005\u0001C\u0003[#\u0001\u0007A\fC\u0003a#\u0001\u0007!\rC\u0003l#\u0001\u0007Q\u000eC\u0004u#A\u0005\t\u0019\u0001<\t\u000fm\f\u0002\u0013!a\u0001{\"I\u0011QA\t\u0011\u0002\u0003\u0007\u0011\u0011\u0002\u0005\t\u0003\'\t\u0002\u0013!a\u0001E\"I\u0011qC\t\u0011\u0002\u0003\u0007\u00111D\u0001\u0006i>DV\u000e\\\u000b\u0003\u0003{\u0001B!a\u0010\u0002F5\u0011\u0011\u0011\t\u0006\u0004\u0003\u0007R\u0015a\u0001=nY&!\u0011qIA!\u0005\u0011)E.Z7\u0002\rQ|\'j]8o\u0003-9\u0018\u000e\u001e5QCfdw.\u00193\u0015\t\u0005\u001d\u0012q\n\u0005\b\u0003#\"\u0002\u0019AA\u0005\u0003)qWm\u001e)bs2|\u0017\rZ\u0001\u0005G>\u0004\u0018\u0010\u0006\n\u0002(\u0005]\u0013\u0011LA.\u0003;\ny&!\u0019\u0002d\u0005\u0015\u0004b\u0002.\u0016!\u0003\u0005\r\u0001\u0018\u0005\bAV\u0001\n\u00111\u0001c\u0011\u001dYW\u0003%AA\u00025Dq\u0001^\u000b\u0011\u0002\u0003\u0007a\u000fC\u0004|+A\u0005\t\u0019A?\t\u0013\u0005\u0015Q\u0003%AA\u0002\u0005%\u0001\u0002CA\n+A\u0005\t\u0019\u00012\t\u0013\u0005]Q\u0003%AA\u0002\u0005m\u0011AD2paf$C-\u001a4bk2$H%M\u000b\u0003\u0003WR3\u0001XA7W\t\ty\u0007\u0005\u0003\u0002r\u0005mTBAA:\u0015\u0011\t)(a\u001e\u0002\u0013Ut7\r[3dW\u0016$\'bAA=\u0015\u0006Q\u0011M\u001c8pi\u0006$\u0018n\u001c8\n\t\u0005u\u00141\u000f\u0002\u0012k:\u001c\u0007.Z2lK\u00124\u0016M]5b]\u000e,\u0017AD2paf$C-\u001a4bk2$HEM\u000b\u0003\u0003\u0007S3AYA7\u00039\u0019w\u000e]=%I\u00164\u0017-\u001e7uIM*\"!!#+\u00075\fi\'\u0001\bd_BLH\u0005Z3gCVdG\u000f\n\u001b\u0016\u0005\u0005=%f\u0001<\u0002n\u0005q1m\u001c9zI\u0011,g-Y;mi\u0012*TCAAKU\ri\u0018QN\u0001\u000fG>\u0004\u0018\u0010\n3fM\u0006,H\u000e\u001e\u00137+\t\tYJ\u000b\u0003\u0002\n\u00055\u0014AD2paf$C-\u001a4bk2$HeN\u0001\u000fG>\u0004\u0018\u0010\n3fM\u0006,H\u000e\u001e\u00139+\t\t\u0019K\u000b\u0003\u0002\u001c\u00055\u0014!\u00049s_\u0012,8\r\u001e)sK\u001aL\u00070\u0006\u0002\u0002*B!\u00111VA[\u001b\t\tiK\u0003\u0003\u00020\u0006E\u0016\u0001\u00027b]\u001eT!!a-\u0002\t)\fg/Y\u0005\u0004Q\u00065\u0016\u0001\u00049s_\u0012,8\r^!sSRLXCAA^!\rI\u0015QX\u0005\u0004\u0003\u007fS%aA%oi\u0006q\u0001O]8ek\u000e$X\t\\3nK:$H\u0003BA\u0006\u0003\u000bD\u0011\"a2!\u0003\u0003\u0005\r!a/\u0002\u0007a$\u0013\'A\bqe>$Wo\u0019;Ji\u0016\u0014\u0018\r^8s+\t\ti\r\u0005\u0004\u0002P\u0006U\u00171B\u0007\u0003\u0003#T1!a5K\u0003)\u0019w\u000e\u001c7fGRLwN\\\u0005\u0005\u0003/\f\tN\u0001\u0005Ji\u0016\u0014\u0018\r^8s\u0003!\u0019\u0017M\\#rk\u0006dG\u0003BAo\u0003G\u00042!SAp\u0013\r\t\tO\u0013\u0002\b\u0005>|G.Z1o\u0011%\t9MIA\u0001\u0002\u0004\tY!\u0001\nqe>$Wo\u0019;FY\u0016lWM\u001c;OC6,G\u0003BAU\u0003SD\u0011\"a2$\u0003\u0003\u0005\r!a/\u0002\u0011!\f7\u000f[\"pI\u0016$\"!a/\u0002\u0011Q|7\u000b\u001e:j]\u001e$\"!!+\u0002\r\u0015\fX/\u00197t)\u0011\ti.a>\t\u0013\u0005\u001dg%!AA\u0002\u0005-\u0011AD\'be.,\b\u000f\u0015:pm&$W\r\u001a\t\u0003\u0005\"\u001aR\u0001KA\u0000\u0005\u0017\u0001\u0002C!\u0001\u0003\bq\u0013WN^?\u0002\n\t\fY\"a\n\u000e\u0005\t\r!b\u0001B\u0003\u0015\u00069!/\u001e8uS6,\u0017\u0002\u0002B\u0005\u0005\u0007\u0011\u0011#\u00112tiJ\f7\r\u001e$v]\u000e$\u0018n\u001c89!\u0011\u0011iAa\u0005\u000e\u0005\t=!\u0002\u0002B\t\u0003c\u000b!![8\n\u0007a\u0013y\u0001\u0006\u0002\u0002|\u0006)\u0011\r\u001d9msR\u0011\u0012q\u0005B\u000e\u0005;\u0011yB!\t\u0003$\t\u0015\"q\u0005B\u0015\u0011\u0015Q6\u00061\u0001]\u0011\u0015\u00017\u00061\u0001c\u0011\u0015Y7\u00061\u0001n\u0011\u001d!8\u0006%AA\u0002YDqa_\u0016\u0011\u0002\u0003\u0007Q\u0010C\u0005\u0002\u0006-\u0002\n\u00111\u0001\u0002\n!A\u00111C\u0016\u0011\u0002\u0003\u0007!\rC\u0005\u0002\u0018-\u0002\n\u00111\u0001\u0002\u001c\u0005y\u0011\r\u001d9ms\u0012\"WMZ1vYR$C\'A\bbaBd\u0017\u0010\n3fM\u0006,H\u000e\u001e\u00136\u0003=\t\u0007\u000f\u001d7zI\u0011,g-Y;mi\u00122\u0014aD1qa2LH\u0005Z3gCVdG\u000fJ\u001c\u0002\u001f\u0005\u0004\b\u000f\\=%I\u00164\u0017-\u001e7uIa\nq!\u001e8baBd\u0017\u0010\u0006\u0003\u0003:\t\u0005\u0003\u0003B%o\u0005w\u0001R\"\u0013B\u001f9\nlg/`A\u0005E\u0006m\u0011b\u0001B \u0015\n1A+\u001e9mKbB\u0011Ba\u00112\u0003\u0003\u0005\r!a\n\u0002\u0007a$\u0003\'A\u000e%Y\u0016\u001c8/\u001b8ji\u0012:\'/Z1uKJ$C-\u001a4bk2$H\u0005N\u0001\u001cI1,7o]5oSR$sM]3bi\u0016\u0014H\u0005Z3gCVdG\u000fJ\u001b\u00027\u0011bWm]:j]&$He\u001a:fCR,\'\u000f\n3fM\u0006,H\u000e\u001e\u00137\u0003m!C.Z:tS:LG\u000fJ4sK\u0006$XM\u001d\u0013eK\u001a\fW\u000f\u001c;%o\u0005YB\u0005\\3tg&t\u0017\u000e\u001e\u0013he\u0016\fG/\u001a:%I\u00164\u0017-\u001e7uIa\nAb\u001e:ji\u0016\u0014V\r\u001d7bG\u0016$\"Aa\u0015\u0011\t\u0005-&QK\u0005\u0005\u0005/\niK\u0001\u0004PE*,7\r\u001e"
    )
  ScalaInlineInfo: length = 0x9F (unknown attribute)
   01 01 00 1F 00 8F 01 46 01 01 64 01 65 01 01 3B
   00 58 01 01 26 00 65 01 01 29 00 31 01 01 2C 00
   35 01 01 2F 00 35 01 01 32 00 35 01 01 49 00 35
   01 01 35 00 31 01 01 38 00 27 01 01 85 01 65 01
   00 1D 00 35 01 01 6C 00 A7 01 00 1F 00 35 01 00
   1A 00 35 01 00 16 00 65 01 00 21 00 35 01 01 4D
   00 A7 01 01 4E 01 4F 01 01 67 01 68 01 01 58 01
   59 01 01 4C 00 31 01 00 18 00 31 01 00 23 00 31
   01 00 24 00 27 01 00 DF 00 31 01 01 19 00 31 01
   00 78 00 79 01 01 22 01 8A 01 01 22 01 23 01
  ScalaSig: length = 0x3 (unknown attribute)
   05 02 00
