Classfile /Users/mw/Projects/slang-braindump/.jar/jar11/assemble/slang-braindump/assemble/content/org/scalatest/events/SuiteAborted.class
  Last modified May 29, 2022; size 24026 bytes
  SHA-256 checksum 208221b8a96d32d60b4dc3e376950f5d126edea74b63a5484480254b5db5568c
  Compiled from "Event.scala"
public final class org.scalatest.events.SuiteAborted extends org.scalatest.events.Event implements org.scalatest.events.ExceptionalEvent
  minor version: 0
  major version: 52
  flags: (0x0031) ACC_PUBLIC, ACC_FINAL, ACC_SUPER
  this_class: #2                          // org/scalatest/events/SuiteAborted
  super_class: #4                         // org/scalatest/events/Event
  interfaces: 1, fields: 13, methods: 65, attributes: 6
Constant pool:
    #1 = Utf8               org/scalatest/events/SuiteAborted
    #2 = Class              #1            // org/scalatest/events/SuiteAborted
    #3 = Utf8               org/scalatest/events/Event
    #4 = Class              #3            // org/scalatest/events/Event
    #5 = Utf8               org/scalatest/events/ExceptionalEvent
    #6 = Class              #5            // org/scalatest/events/ExceptionalEvent
    #7 = Utf8               Event.scala
    #8 = Utf8               Lscala/reflect/ScalaSignature;
    #9 = Utf8               bytes
   #10 = Utf8               \u0006\u0005\t-h\u0001B(Q\u0005^C\u0001\"\u001d\u0001\u0003\u0016\u0004%\tA\u001d\u0005\tm\u0002\u0011\t\u0012)A\u0005g\"Aq\u000f\u0001BK\u0002\u0013\u0005\u0001\u0010C\u0005\u0002\u0004\u0001\u0011\t\u0012)A\u0005s\"I\u0011Q\u0001\u0001\u0003\u0016\u0004%\t\u0001\u001f\u0005\n\u0003\u000f\u0001!\u0011#Q\u0001\neD\u0011\"!\u0003\u0001\u0005+\u0007I\u0011\u0001=\t\u0013\u0005-\u0001A!E!\u0002\u0013I\bBCA\u0007\u0001\tU\r\u0011\"\u0001\u0002\u0010!Q\u0011q\u0003\u0001\u0003\u0012\u0003\u0006I!!\u0005\t\u0015\u0005e\u0001A!f\u0001\n\u0003\tY\u0002\u0003\u0006\u0002&\u0001\u0011\t\u0012)A\u0005\u0003;A!\"a\n\u0001\u0005+\u0007I\u0011AA\u0015\u0011)\t\u0019\u0004\u0001B\tB\u0003%\u00111\u0006\u0005\u000b\u0003k\u0001!Q3A\u0005\u0002\u0005]\u0002BCA!\u0001\tE\t\u0015!\u0003\u0002:!Q\u00111\t\u0001\u0003\u0016\u0004%\t!!\u0012\t\u0015\u0005=\u0003A!E!\u0002\u0013\t9\u0005\u0003\u0006\u0002R\u0001\u0011)\u001a!C\u0001\u0003\u001fA!\"a\u0015\u0001\u0005#\u0005\u000b\u0011BA\t\u0011)\t)\u0006\u0001BK\u0002\u0013\u0005\u0011q\u000b\u0005\u000b\u0003C\u0002!\u0011#Q\u0001\n\u0005e\u0003\"CA2\u0001\tU\r\u0011\"\u0001y\u0011%\t)\u0007\u0001B\tB\u0003%\u0011\u0010\u0003\u0006\u0002h\u0001\u0011)\u001a!C\u0001\u0003SB!\"a\u001b\u0001\u0005#\u0005\u000b\u0011BA\u0017\u0011\u001d\ti\u0007\u0001C\u0001\u0003_B\u0001\"!$\u0001\t\u0003\u0011\u0016q\u0012\u0005\b\u0003;\u0003A\u0011\u0001*y\u0011!\ty\n\u0001C\u0001!\u0006\u0005\u0006\u0002CAT\u0001\u0011\u0005\u0003+!+\t\u0011\u0005=\u0006\u0001\"\u0011S\u0003cC\u0011\"a-\u0001\u0003\u0003%\t!!.\t\u0013\u0005E\u0007!%A\u0005\u0002\u0005M\u0007\"CAu\u0001E\u0005I\u0011AAv\u0011%\ty\u000fAI\u0001\n\u0003\tY\u000fC\u0005\u0002r\u0002\t\n\u0011\"\u0001\u0002l\"I\u00111\u001f\u0001\u0012\u0002\u0013\u0005\u0011Q\u001f\u0005\n\u0003s\u0004\u0011\u0013!C\u0001\u0003wD\u0011\"a@\u0001#\u0003%\tA!\u0001\t\u0013\t\u0015\u0001!%A\u0005\u0002\t\u001d\u0001\"\u0003B\u0006\u0001E\u0005I\u0011\u0001B\u0007\u0011%\u0011\t\u0002AI\u0001\n\u0003\t)\u0010C\u0005\u0003\u0014\u0001\t\n\u0011\"\u0001\u0003\u0016!I!\u0011\u0004\u0001\u0012\u0002\u0013\u0005\u00111\u001e\u0005\n\u00057\u0001\u0011\u0013!C\u0001\u0005;A\u0011B!\t\u0001\u0003\u0003%\tEa\t\t\u0013\tM\u0002!!A\u0005\u0002\tU\u0002\"\u0003B\u001f\u0001\u0005\u0005I\u0011\u0001B \u0011%\u0011)\u0005AA\u0001\n\u0003\u00129\u0005C\u0005\u0003V\u0001\t\t\u0011\"\u0001\u0003X!I!\u0011\r\u0001\u0002\u0002\u0013\u0005#1\r\u0005\n\u0005O\u0002\u0011\u0011!C!\u0005SB\u0011Ba\u001b\u0001\u0003\u0003%\tE!\u001c\t\u0013\t=\u0004!!A\u0005B\tEt!\u0003B;!\u0006\u0005\t\u0012\u0001B<\r!y\u0005+!A\t\u0002\te\u0004bBA7s\u0011\u0005!\u0011\u0013\u0005\n\u0005WJ\u0014\u0011!C#\u0005[B\u0011Ba%:\u0003\u0003%\tI!&\t\u0013\tE\u0016(%A\u0005\u0002\u0005m\b\"\u0003BZsE\u0005I\u0011\u0001B\u0001\u0011%\u0011),OI\u0001\n\u0003\u00119\u0001C\u0005\u00038f\n\n\u0011\"\u0001\u0003\u000e!I!\u0011X\u001d\u0012\u0002\u0013\u0005\u0011Q\u001f\u0005\n\u0005wK\u0014\u0013!C\u0001\u0005+A\u0011B!0:#\u0003%\t!a;\t\u0013\t}\u0016(%A\u0005\u0002\tu\u0001\"\u0003Bas\u0005\u0005I\u0011\u0011Bb\u0011%\u0011\t.OI\u0001\n\u0003\tY\u0010C\u0005\u0003Tf\n\n\u0011\"\u0001\u0003\u0002!I!Q[\u001d\u0012\u0002\u0013\u0005!q\u0001\u0005\n\u0005/L\u0014\u0013!C\u0001\u0005\u001bA\u0011B!7:#\u0003%\t!!>\t\u0013\tm\u0017(%A\u0005\u0002\tU\u0001\"\u0003BosE\u0005I\u0011AAv\u0011%\u0011y.OI\u0001\n\u0003\u0011i\u0002C\u0005\u0003bf\n\t\u0011\"\u0003\u0003d\na1+^5uK\u0006\u0013wN\u001d;fI*\u0011\u0011KU\u0001\u0007KZ,g\u000e^:\u000b\u0005M#\u0016!C:dC2\fG/Z:u\u0015\u0005)\u0016aA8sO\u000e\u00011#\u0002\u0001Y9~+\u0007CA-[\u001b\u0005\u0001\u0016BA.Q\u0005\u0015)e/\u001a8u!\tIV,\u0003\u0002_!\n\u0001R\t_2faRLwN\\1m\u000bZ,g\u000e\u001e\t\u0003A\u000el\u0011!\u0019\u0006\u0002E\u0006)1oY1mC&\u0011A-\u0019\u0002\b!J|G-^2u!\t1gN\u0004\u0002hY:\u0011\u0001n[\u0007\u0002S*\u0011!NV\u0001\u0007yI|w\u000e\u001e \n\u0003\tL!!\\1\u0002\u000fA\f7m[1hK&\u0011q\u000e\u001d\u0002\r\'\u0016\u0014\u0018.\u00197ju\u0006\u0014G.\u001a\u0006\u0003[\u0006\fqa\u001c:eS:\fG.F\u0001t!\tIF/\u0003\u0002v!\n9qJ\u001d3j]\u0006d\u0017\u0001C8sI&t\u0017\r\u001c\u0011\u0002\u000f5,7o]1hKV\t\u0011\u0010\u0005\u0002{}:\u00111\u0010 \t\u0003Q\u0006L!!`1\u0002\rA\u0013X\rZ3g\u0013\ry\u0018\u0011\u0001\u0002\u0007\'R\u0014\u0018N\\4\u000b\u0005u\f\u0017\u0001C7fgN\fw-\u001a\u0011\u0002\u0013M,\u0018\u000e^3OC6,\u0017AC:vSR,g*Y7fA\u000591/^5uK&#\u0017\u0001C:vSR,\u0017\n\u001a\u0011\u0002\u001dM,\u0018\u000e^3DY\u0006\u001c8OT1nKV\u0011\u0011\u0011\u0003\t\u0005A\u0006M\u00110C\u0002\u0002\u0016\u0005\u0014aa\u00149uS>t\u0017aD:vSR,7\t\\1tg:\u000bW.\u001a\u0011\u0002\u0013QD\'o\\<bE2,WCAA\u000f!\u0015\u0001\u00171CA\u0010!\r1\u0017\u0011E\u0005\u0004\u0003G\u0001(!\u0003+ie><\u0018M\u00197f\u0003)!\bN]8xC\ndW\rI\u0001\tIV\u0014\u0018\r^5p]V\u0011\u00111\u0006\t\u0006A\u0006M\u0011Q\u0006\t\u0004A\u0006=\u0012bAA\u0019C\n!Aj\u001c8h\u0003%!WO]1uS>t\u0007%A\u0005g_Jl\u0017\r\u001e;feV\u0011\u0011\u0011\b\t\u0006A\u0006M\u00111\b\t\u00043\u0006u\u0012bAA !\nIai\u001c:nCR$XM]\u0001\u000bM>\u0014X.\u0019;uKJ\u0004\u0013\u0001\u00037pG\u0006$\u0018n\u001c8\u0016\u0005\u0005\u001d\u0003#\u00021\u0002\u0014\u0005%\u0003cA-\u0002L%\u0019\u0011Q\n)\u0003\u00111{7-\u0019;j_:\f\u0011\u0002\\8dCRLwN\u001c\u0011\u0002\u0011I,\'/\u001e8oKJ\f\u0011B]3sk:tWM\u001d\u0011\u0002\u000fA\f\u0017\u0010\\8bIV\u0011\u0011\u0011\f\t\u0006A\u0006M\u00111\f\t\u0004A\u0006u\u0013bAA0C\n\u0019\u0011I\\=\u0002\u0011A\f\u0017\u0010\\8bI\u0002\n!\u0002\u001e5sK\u0006$g*Y7f\u0003-!\bN]3bI:\u000bW.\u001a\u0011\u0002\u0013QLW.Z*uC6\u0004XCAA\u0017\u0003)!\u0018.\\3Ti\u0006l\u0007\u000fI\u0001\u0007y%t\u0017\u000e\u001e \u00159\u0005E\u00141OA;\u0003o\nI(a\u001f\u0002~\u0005}\u0014\u0011QAB\u0003\u000b\u000b9)!#\u0002\fB\u0011\u0011\f\u0001\u0005\u0006cn\u0001\ra\u001d\u0005\u0006on\u0001\r!\u001f\u0005\u0007\u0003\u000bY\u0002\u0019A=\t\r\u0005%1\u00041\u0001z\u0011\u001d\tia\u0007a\u0001\u0003#A\u0011\"!\u0007\u001c!\u0003\u0005\r!!\b\t\u0013\u0005\u001d2\u0004%AA\u0002\u0005-\u0002\"CA\u001b7A\u0005\t\u0019AA\u001d\u0011%\t\u0019e\u0007I\u0001\u0002\u0004\t9\u0005C\u0005\u0002Rm\u0001\n\u00111\u0001\u0002\u0012!I\u0011QK\u000e\u0011\u0002\u0003\u0007\u0011\u0011\f\u0005\t\u0003GZ\u0002\u0013!a\u0001s\"I\u0011qM\u000e\u0011\u0002\u0003\u0007\u0011QF\u0001\u0006i>DV\u000e\\\u000b\u0003\u0003#\u0003B!a%\u0002\u001a6\u0011\u0011Q\u0013\u0006\u0004\u0003/\u000b\u0017a\u0001=nY&!\u00111TAK\u0005\u0011)E.Z7\u0002\rQ|\'j]8o\u0003-9\u0018\u000e\u001e5QCfdw.\u00193\u0015\t\u0005E\u00141\u0015\u0005\b\u0003Ks\u0002\u0019AA-\u0003)qWm\u001e)bs2|\u0017\rZ\u0001\u000eo&$\b\u000e\u00165s_^\f\'\r\\3\u0015\u0007a\u000bY\u000bC\u0004\u0002.~\u0001\r!!\b\u0002\u00199,w\u000f\u00165s_^\f\'\r\\3\u0002%\u0015t7/\u001e:f\'\u0016\u0014\u0018.\u00197ju\u0006\u0014G.\u001a\u000b\u00021\u0006!1m\u001c9z)q\t\t(a.\u0002:\u0006m\u0016QXA`\u0003\u0003\f\u0019-!2\u0002H\u0006%\u00171ZAg\u0003\u001fDq!]\u0011\u0011\u0002\u0003\u00071\u000fC\u0004xCA\u0005\t\u0019A=\t\u0011\u0005\u0015\u0011\u0005%AA\u0002eD\u0001\"!\u0003\"!\u0003\u0005\r!\u001f\u0005\n\u0003\u001b\t\u0003\u0013!a\u0001\u0003#A\u0011\"!\u0007\"!\u0003\u0005\r!!\b\t\u0013\u0005\u001d\u0012\u0005%AA\u0002\u0005-\u0002\"CA\u001bCA\u0005\t\u0019AA\u001d\u0011%\t\u0019%\tI\u0001\u0002\u0004\t9\u0005C\u0005\u0002R\u0005\u0002\n\u00111\u0001\u0002\u0012!I\u0011QK\u0011\u0011\u0002\u0003\u0007\u0011\u0011\f\u0005\t\u0003G\n\u0003\u0013!a\u0001s\"I\u0011qM\u0011\u0011\u0002\u0003\u0007\u0011QF\u0001\u000fG>\u0004\u0018\u0010\n3fM\u0006,H\u000e\u001e\u00132+\t\t)NK\u0002t\u0003/\\#!!7\u0011\t\u0005m\u0017Q]\u0007\u0003\u0003;TA!a8\u0002b\u0006IQO\\2iK\u000e\\W\r\u001a\u0006\u0004\u0003G\f\u0017AC1o]>$\u0018\r^5p]&!\u0011q]Ao\u0005E)hn\u00195fG.,GMV1sS\u0006t7-Z\u0001\u000fG>\u0004\u0018\u0010\n3fM\u0006,H\u000e\u001e\u00133+\t\tiOK\u0002z\u0003/\fabY8qs\u0012\"WMZ1vYR$3\'\u0001\bd_BLH\u0005Z3gCVdG\u000f\n\u001b\u0002\u001d\r|\u0007/\u001f\u0013eK\u001a\fW\u000f\u001c;%kU\u0011\u0011q\u001f\u0016\u0005\u0003#\t9.\u0001\bd_BLH\u0005Z3gCVdG\u000f\n\u001c\u0016\u0005\u0005u(\u0006BA\u000f\u0003/\fabY8qs\u0012\"WMZ1vYR$s\'\u0006\u0002\u0003\u0004)\"\u00111FAl\u00039\u0019w\u000e]=%I\u00164\u0017-\u001e7uIa*\"A!\u0003+\t\u0005e\u0012q[\u0001\u000fG>\u0004\u0018\u0010\n3fM\u0006,H\u000e\u001e\u0013:+\t\u0011yA\u000b\u0003\u0002H\u0005]\u0017aD2paf$C-\u001a4bk2$H%\r\u0019\u0002\u001f\r|\u0007/\u001f\u0013eK\u001a\fW\u000f\u001c;%cE*\"Aa\u0006+\t\u0005e\u0013q[\u0001\u0010G>\u0004\u0018\u0010\n3fM\u0006,H\u000e\u001e\u00132e\u0005y1m\u001c9zI\u0011,g-Y;mi\u0012\n4\'\u0006\u0002\u0003 )\"\u0011QFAl\u00035\u0001(o\u001c3vGR\u0004&/\u001a4jqV\u0011!Q\u0005\t\u0005\u0005O\u0011\t$\u0004\u0002\u0003*)!!1\u0006B\u0017\u0003\u0011a\u0017M\\4\u000b\u0005\t=\u0012\u0001\u00026bm\u0006L1a B\u0015\u00031\u0001(o\u001c3vGR\f%/\u001b;z+\t\u00119\u0004E\u0002a\u0005sI1Aa\u000fb\u0005\rIe\u000e^\u0001\u000faJ|G-^2u\u000b2,W.\u001a8u)\u0011\tYF!\u0011\t\u0013\t\r\u0013\'!AA\u0002\t]\u0012a\u0001=%c\u0005y\u0001O]8ek\u000e$\u0018\n^3sCR|\'/\u0006\u0002\u0003JA1!1\nB)\u00037j!A!\u0014\u000b\u0007\t=\u0013-\u0001\u0006d_2dWm\u0019;j_:LAAa\u0015\u0003N\tA\u0011\n^3sCR|\'/\u0001\u0005dC:,\u0015/^1m)\u0011\u0011IFa\u0018\u0011\u0007\u0001\u0014Y&C\u0002\u0003^\u0005\u0014qAQ8pY\u0016\fg\u000eC\u0005\u0003DM\n\t\u00111\u0001\u0002\\\u0005\u0011\u0002O]8ek\u000e$X\t\\3nK:$h*Y7f)\u0011\u0011)C!\u001a\t\u0013\t\rC\'!AA\u0002\t]\u0012\u0001\u00035bg\"\u001cu\u000eZ3\u0015\u0005\t]\u0012\u0001\u0003;p\'R\u0014\u0018N\\4\u0015\u0005\t\u0015\u0012AB3rk\u0006d7\u000f\u0006\u0003\u0003Z\tM\u0004\"\u0003B\"o\u0005\u0005\t\u0019AA.\u00031\u0019V/\u001b;f\u0003\n|\'\u000f^3e!\tI\u0016hE\u0003:\u0005w\u00129\tE\u000e\u0003~\t\r5/_=z\u0003#\ti\"a\u000b\u0002:\u0005\u001d\u0013\u0011CA-s\u00065\u0012\u0011O\u0007\u0003\u0005\u007fR1A!!b\u0003\u001d\u0011XO\u001c;j[\u0016LAA!\"\u0003\u0000\t\u0011\u0012IY:ue\u0006\u001cGOR;oGRLwN\\\u00194!\u0011\u0011IIa$\u000e\u0005\t-%\u0002\u0002BG\u0005[\t!![8\n\u0007=\u0014Y\t\u0006\u0002\u0003x\u0005)\u0011\r\u001d9msRa\u0012\u0011\u000fBL\u00053\u0013YJ!(\u0003 \n\u0005&1\u0015BS\u0005O\u0013IKa+\u0003.\n=\u0006\"B9=\u0001\u0004\u0019\b\"B<=\u0001\u0004I\bBBA\u0003y\u0001\u0007\u0011\u0010\u0003\u0004\u0002\nq\u0002\r!\u001f\u0005\b\u0003\u001ba\u0004\u0019AA\t\u0011%\tI\u0002\u0010I\u0001\u0002\u0004\ti\u0002C\u0005\u0002(q\u0002\n\u00111\u0001\u0002,!I\u0011Q\u0007\u001f\u0011\u0002\u0003\u0007\u0011\u0011\b\u0005\n\u0003\u0007b\u0004\u0013!a\u0001\u0003\u000fB\u0011\"!\u0015=!\u0003\u0005\r!!\u0005\t\u0013\u0005UC\b%AA\u0002\u0005e\u0003\u0002CA2yA\u0005\t\u0019A=\t\u0013\u0005\u001dD\b%AA\u0002\u00055\u0012aD1qa2LH\u0005Z3gCVdG\u000f\n\u001c\u0002\u001f\u0005\u0004\b\u000f\\=%I\u00164\u0017-\u001e7uI]\nq\"\u00199qYf$C-\u001a4bk2$H\u0005O\u0001\u0010CB\u0004H.\u001f\u0013eK\u001a\fW\u000f\u001c;%s\u0005\u0001\u0012\r\u001d9ms\u0012\"WMZ1vYR$\u0013\u0007M\u0001\u0011CB\u0004H.\u001f\u0013eK\u001a\fW\u000f\u001c;%cE\n\u0001#\u00199qYf$C-\u001a4bk2$H%\r\u001a\u0002!\u0005\u0004\b\u000f\\=%I\u00164\u0017-\u001e7uIE\u001a\u0014aB;oCB\u0004H.\u001f\u000b\u0005\u0005\u000b\u0014i\rE\u0003a\u0003\'\u00119\r\u0005\ra\u0005\u0013\u001c\u00180_=\u0002\u0012\u0005u\u00111FA\u001d\u0003\u000f\n\t\"!\u0017z\u0003[I1Aa3b\u0005\u001d!V\u000f\u001d7fcMB\u0011Ba4F\u0003\u0003\u0005\r!!\u001d\u0002\u0007a$\u0003\'A\u000e%Y\u0016\u001c8/\u001b8ji\u0012:\'/Z1uKJ$C-\u001a4bk2$HEN\u0001\u001cI1,7o]5oSR$sM]3bi\u0016\u0014H\u0005Z3gCVdG\u000fJ\u001c\u00027\u0011bWm]:j]&$He\u001a:fCR,\'\u000f\n3fM\u0006,H\u000e\u001e\u00139\u0003m!C.Z:tS:LG\u000fJ4sK\u0006$XM\u001d\u0013eK\u001a\fW\u000f\u001c;%s\u0005aB\u0005\\3tg&t\u0017\u000e\u001e\u0013he\u0016\fG/\u001a:%I\u00164\u0017-\u001e7uIE\u0002\u0014\u0001\b\u0013mKN\u001c\u0018N\\5uI\u001d\u0014X-\u0019;fe\u0012\"WMZ1vYR$\u0013\'M\u0001\u001dI1,7o]5oSR$sM]3bi\u0016\u0014H\u0005Z3gCVdG\u000fJ\u00193\u0003q!C.Z:tS:LG\u000fJ4sK\u0006$XM\u001d\u0013eK\u001a\fW\u000f\u001c;%cM\nAb\u001e:ji\u0016\u0014V\r\u001d7bG\u0016$\"A!:\u0011\t\t\u001d\"q]\u0005\u0005\u0005S\u0014IC\u0001\u0004PE*,7\r\u001e
   #11 = Utf8               java/lang/invoke/MethodHandles$Lookup
   #12 = Class              #11           // java/lang/invoke/MethodHandles$Lookup
   #13 = Utf8               java/lang/invoke/MethodHandles
   #14 = Class              #13           // java/lang/invoke/MethodHandles
   #15 = Utf8               Lookup
   #16 = Utf8               org/scalactic/Requirements$RequirementsHelper
   #17 = Class              #16           // org/scalactic/Requirements$RequirementsHelper
   #18 = Utf8               org/scalactic/Requirements
   #19 = Class              #18           // org/scalactic/Requirements
   #20 = Utf8               RequirementsHelper
   #21 = Utf8               org/scalatest/events/Event$EventJsonHelper$
   #22 = Class              #21           // org/scalatest/events/Event$EventJsonHelper$
   #23 = Utf8               EventJsonHelper$
   #24 = Utf8               org/scalatest/events/Event$EventXmlHelper$
   #25 = Class              #24           // org/scalatest/events/Event$EventXmlHelper$
   #26 = Utf8               EventXmlHelper$
   #27 = Utf8               ordinal
   #28 = Utf8               Lorg/scalatest/events/Ordinal;
   #29 = Utf8               message
   #30 = Utf8               Ljava/lang/String;
   #31 = Utf8               suiteName
   #32 = Utf8               suiteId
   #33 = Utf8               suiteClassName
   #34 = Utf8               Lscala/Option;
   #35 = Utf8               Lscala/Option<Ljava/lang/String;>;
   #36 = Utf8               throwable
   #37 = Utf8               Lscala/Option<Ljava/lang/Throwable;>;
   #38 = Utf8               duration
   #39 = Utf8               Lscala/Option<Ljava/lang/Object;>;
   #40 = Utf8               formatter
   #41 = Utf8               Lscala/Option<Lorg/scalatest/events/Formatter;>;
   #42 = Utf8               location
   #43 = Utf8               Lscala/Option<Lorg/scalatest/events/Location;>;
   #44 = Utf8               rerunner
   #45 = Utf8               payload
   #46 = Utf8               threadName
   #47 = Utf8               timeStamp
   #48 = Utf8               J
   #49 = Utf8               $lessinit$greater$default$13
   #50 = Utf8               ()J
   #51 = Utf8               org/scalatest/events/SuiteAborted$
   #52 = Class              #51           // org/scalatest/events/SuiteAborted$
   #53 = Utf8               MODULE$
   #54 = Utf8               Lorg/scalatest/events/SuiteAborted$;
   #55 = NameAndType        #53:#54       // MODULE$:Lorg/scalatest/events/SuiteAborted$;
   #56 = Fieldref           #52.#55       // org/scalatest/events/SuiteAborted$.MODULE$:Lorg/scalatest/events/SuiteAborted$;
   #57 = NameAndType        #49:#50       // $lessinit$greater$default$13:()J
   #58 = Methodref          #52.#57       // org/scalatest/events/SuiteAborted$.$lessinit$greater$default$13:()J
   #59 = Utf8               $lessinit$greater$default$12
   #60 = Utf8               ()Ljava/lang/String;
   #61 = NameAndType        #59:#60       // $lessinit$greater$default$12:()Ljava/lang/String;
   #62 = Methodref          #52.#61       // org/scalatest/events/SuiteAborted$.$lessinit$greater$default$12:()Ljava/lang/String;
   #63 = Utf8               $lessinit$greater$default$11
   #64 = Utf8               ()Lscala/Option;
   #65 = Utf8               ()Lscala/Option<Ljava/lang/Object;>;
   #66 = NameAndType        #63:#64       // $lessinit$greater$default$11:()Lscala/Option;
   #67 = Methodref          #52.#66       // org/scalatest/events/SuiteAborted$.$lessinit$greater$default$11:()Lscala/Option;
   #68 = Utf8               $lessinit$greater$default$10
   #69 = Utf8               ()Lscala/Option<Ljava/lang/String;>;
   #70 = NameAndType        #68:#64       // $lessinit$greater$default$10:()Lscala/Option;
   #71 = Methodref          #52.#70       // org/scalatest/events/SuiteAborted$.$lessinit$greater$default$10:()Lscala/Option;
   #72 = Utf8               $lessinit$greater$default$9
   #73 = Utf8               ()Lscala/Option<Lorg/scalatest/events/Location;>;
   #74 = NameAndType        #72:#64       // $lessinit$greater$default$9:()Lscala/Option;
   #75 = Methodref          #52.#74       // org/scalatest/events/SuiteAborted$.$lessinit$greater$default$9:()Lscala/Option;
   #76 = Utf8               $lessinit$greater$default$8
   #77 = Utf8               ()Lscala/Option<Lorg/scalatest/events/Formatter;>;
   #78 = NameAndType        #76:#64       // $lessinit$greater$default$8:()Lscala/Option;
   #79 = Methodref          #52.#78       // org/scalatest/events/SuiteAborted$.$lessinit$greater$default$8:()Lscala/Option;
   #80 = Utf8               $lessinit$greater$default$7
   #81 = NameAndType        #80:#64       // $lessinit$greater$default$7:()Lscala/Option;
   #82 = Methodref          #52.#81       // org/scalatest/events/SuiteAborted$.$lessinit$greater$default$7:()Lscala/Option;
   #83 = Utf8               $lessinit$greater$default$6
   #84 = Utf8               ()Lscala/Option<Ljava/lang/Throwable;>;
   #85 = NameAndType        #83:#64       // $lessinit$greater$default$6:()Lscala/Option;
   #86 = Methodref          #52.#85       // org/scalatest/events/SuiteAborted$.$lessinit$greater$default$6:()Lscala/Option;
   #87 = Utf8               unapply
   #88 = Utf8               (Lorg/scalatest/events/SuiteAborted;)Lscala/Option;
   #89 = Utf8               (Lorg/scalatest/events/SuiteAborted;)Lscala/Option<Lscala/Tuple13<Lorg/scalatest/events/Ordinal;Ljava/lang/String;Ljava/lang/String;Ljava/lang/String;Lscala/Option<Ljava/lang/String;>;Lscala/Option<Ljava/lang/Throwable;>;Lscala/Option<Ljava/lang/Object;>;Lscala/Option<Lorg/scalatest/events/Formatter;>;Lscala/Option<Lorg/scalatest/events/Location;>;Lscala/Option<Ljava/lang/String;>;Lscala/Option<Ljava/lang/Object;>;Ljava/lang/String;Ljava/lang/Object;>;>;
   #90 = Utf8               x$0
   #91 = NameAndType        #87:#88       // unapply:(Lorg/scalatest/events/SuiteAborted;)Lscala/Option;
   #92 = Methodref          #52.#91       // org/scalatest/events/SuiteAborted$.unapply:(Lorg/scalatest/events/SuiteAborted;)Lscala/Option;
   #93 = Utf8               Lorg/scalatest/events/SuiteAborted;
   #94 = Utf8               apply$default$13
   #95 = NameAndType        #94:#50       // apply$default$13:()J
   #96 = Methodref          #52.#95       // org/scalatest/events/SuiteAborted$.apply$default$13:()J
   #97 = Utf8               apply$default$12
   #98 = NameAndType        #97:#60       // apply$default$12:()Ljava/lang/String;
   #99 = Methodref          #52.#98       // org/scalatest/events/SuiteAborted$.apply$default$12:()Ljava/lang/String;
  #100 = Utf8               apply$default$11
  #101 = NameAndType        #100:#64      // apply$default$11:()Lscala/Option;
  #102 = Methodref          #52.#101      // org/scalatest/events/SuiteAborted$.apply$default$11:()Lscala/Option;
  #103 = Utf8               apply$default$10
  #104 = NameAndType        #103:#64      // apply$default$10:()Lscala/Option;
  #105 = Methodref          #52.#104      // org/scalatest/events/SuiteAborted$.apply$default$10:()Lscala/Option;
  #106 = Utf8               apply$default$9
  #107 = NameAndType        #106:#64      // apply$default$9:()Lscala/Option;
  #108 = Methodref          #52.#107      // org/scalatest/events/SuiteAborted$.apply$default$9:()Lscala/Option;
  #109 = Utf8               apply$default$8
  #110 = NameAndType        #109:#64      // apply$default$8:()Lscala/Option;
  #111 = Methodref          #52.#110      // org/scalatest/events/SuiteAborted$.apply$default$8:()Lscala/Option;
  #112 = Utf8               apply$default$7
  #113 = NameAndType        #112:#64      // apply$default$7:()Lscala/Option;
  #114 = Methodref          #52.#113      // org/scalatest/events/SuiteAborted$.apply$default$7:()Lscala/Option;
  #115 = Utf8               apply$default$6
  #116 = NameAndType        #115:#64      // apply$default$6:()Lscala/Option;
  #117 = Methodref          #52.#116      // org/scalatest/events/SuiteAborted$.apply$default$6:()Lscala/Option;
  #118 = Utf8               apply
  #119 = Utf8               (Lorg/scalatest/events/Ordinal;Ljava/lang/String;Ljava/lang/String;Ljava/lang/String;Lscala/Option;Lscala/Option;Lscala/Option;Lscala/Option;Lscala/Option;Lscala/Option;Lscala/Option;Ljava/lang/String;J)Lorg/scalatest/events/SuiteAborted;
  #120 = Utf8               (Lorg/scalatest/events/Ordinal;Ljava/lang/String;Ljava/lang/String;Ljava/lang/String;Lscala/Option<Ljava/lang/String;>;Lscala/Option<Ljava/lang/Throwable;>;Lscala/Option<Ljava/lang/Object;>;Lscala/Option<Lorg/scalatest/events/Formatter;>;Lscala/Option<Lorg/scalatest/events/Location;>;Lscala/Option<Ljava/lang/String;>;Lscala/Option<Ljava/lang/Object;>;Ljava/lang/String;J)Lorg/scalatest/events/SuiteAborted;
  #121 = NameAndType        #118:#119     // apply:(Lorg/scalatest/events/Ordinal;Ljava/lang/String;Ljava/lang/String;Ljava/lang/String;Lscala/Option;Lscala/Option;Lscala/Option;Lscala/Option;Lscala/Option;Lscala/Option;Lscala/Option;Ljava/lang/String;J)Lorg/scalatest/events/SuiteAborted;
  #122 = Methodref          #52.#121      // org/scalatest/events/SuiteAborted$.apply:(Lorg/scalatest/events/Ordinal;Ljava/lang/String;Ljava/lang/String;Ljava/lang/String;Lscala/Option;Lscala/Option;Lscala/Option;Lscala/Option;Lscala/Option;Lscala/Option;Lscala/Option;Ljava/lang/String;J)Lorg/scalatest/events/SuiteAborted;
  #123 = Utf8               tupled
  #124 = Utf8               ()Lscala/Function1;
  #125 = Utf8               ()Lscala/Function1<Lscala/Tuple13<Lorg/scalatest/events/Ordinal;Ljava/lang/String;Ljava/lang/String;Ljava/lang/String;Lscala/Option<Ljava/lang/String;>;Lscala/Option<Ljava/lang/Throwable;>;Lscala/Option<Ljava/lang/Object;>;Lscala/Option<Lorg/scalatest/events/Formatter;>;Lscala/Option<Lorg/scalatest/events/Location;>;Lscala/Option<Ljava/lang/String;>;Lscala/Option<Ljava/lang/Object;>;Ljava/lang/String;Ljava/lang/Object;>;Lorg/scalatest/events/SuiteAborted;>;
  #126 = NameAndType        #123:#124     // tupled:()Lscala/Function1;
  #127 = Methodref          #52.#126      // org/scalatest/events/SuiteAborted$.tupled:()Lscala/Function1;
  #128 = Utf8               curried
  #129 = Utf8               ()Lscala/Function1<Lorg/scalatest/events/Ordinal;Lscala/Function1<Ljava/lang/String;Lscala/Function1<Ljava/lang/String;Lscala/Function1<Ljava/lang/String;Lscala/Function1<Lscala/Option<Ljava/lang/String;>;Lscala/Function1<Lscala/Option<Ljava/lang/Throwable;>;Lscala/Function1<Lscala/Option<Ljava/lang/Object;>;Lscala/Function1<Lscala/Option<Lorg/scalatest/events/Formatter;>;Lscala/Function1<Lscala/Option<Lorg/scalatest/events/Location;>;Lscala/Function1<Lscala/Option<Ljava/lang/String;>;Lscala/Function1<Lscala/Option<Ljava/lang/Object;>;Lscala/Function1<Ljava/lang/String;Lscala/Function1<Ljava/lang/Object;Lorg/scalatest/events/SuiteAborted;>;>;>;>;>;>;>;>;>;>;>;>;>;
  #130 = NameAndType        #128:#124     // curried:()Lscala/Function1;
  #131 = Methodref          #52.#130      // org/scalatest/events/SuiteAborted$.curried:()Lscala/Function1;
  #132 = Utf8               ()Lorg/scalatest/events/Ordinal;
  #133 = NameAndType        #27:#28       // ordinal:Lorg/scalatest/events/Ordinal;
  #134 = Fieldref           #2.#133       // org/scalatest/events/SuiteAborted.ordinal:Lorg/scalatest/events/Ordinal;
  #135 = Utf8               this
  #136 = NameAndType        #29:#30       // message:Ljava/lang/String;
  #137 = Fieldref           #2.#136       // org/scalatest/events/SuiteAborted.message:Ljava/lang/String;
  #138 = NameAndType        #31:#30       // suiteName:Ljava/lang/String;
  #139 = Fieldref           #2.#138       // org/scalatest/events/SuiteAborted.suiteName:Ljava/lang/String;
  #140 = NameAndType        #32:#30       // suiteId:Ljava/lang/String;
  #141 = Fieldref           #2.#140       // org/scalatest/events/SuiteAborted.suiteId:Ljava/lang/String;
  #142 = NameAndType        #33:#34       // suiteClassName:Lscala/Option;
  #143 = Fieldref           #2.#142       // org/scalatest/events/SuiteAborted.suiteClassName:Lscala/Option;
  #144 = NameAndType        #36:#34       // throwable:Lscala/Option;
  #145 = Fieldref           #2.#144       // org/scalatest/events/SuiteAborted.throwable:Lscala/Option;
  #146 = NameAndType        #38:#34       // duration:Lscala/Option;
  #147 = Fieldref           #2.#146       // org/scalatest/events/SuiteAborted.duration:Lscala/Option;
  #148 = NameAndType        #40:#34       // formatter:Lscala/Option;
  #149 = Fieldref           #2.#148       // org/scalatest/events/SuiteAborted.formatter:Lscala/Option;
  #150 = NameAndType        #42:#34       // location:Lscala/Option;
  #151 = Fieldref           #2.#150       // org/scalatest/events/SuiteAborted.location:Lscala/Option;
  #152 = NameAndType        #44:#34       // rerunner:Lscala/Option;
  #153 = Fieldref           #2.#152       // org/scalatest/events/SuiteAborted.rerunner:Lscala/Option;
  #154 = NameAndType        #45:#34       // payload:Lscala/Option;
  #155 = Fieldref           #2.#154       // org/scalatest/events/SuiteAborted.payload:Lscala/Option;
  #156 = NameAndType        #46:#30       // threadName:Ljava/lang/String;
  #157 = Fieldref           #2.#156       // org/scalatest/events/SuiteAborted.threadName:Ljava/lang/String;
  #158 = NameAndType        #47:#48       // timeStamp:J
  #159 = Fieldref           #2.#158       // org/scalatest/events/SuiteAborted.timeStamp:J
  #160 = Utf8               toXml
  #161 = Utf8               ()Lscala/xml/Elem;
  #162 = Utf8               scala/xml/Elem
  #163 = Class              #162          // scala/xml/Elem
  #164 = Utf8               SuiteAborted
  #165 = String             #164          // SuiteAborted
  #166 = Utf8               scala/xml/Null$
  #167 = Class              #166          // scala/xml/Null$
  #168 = Utf8               Lscala/xml/Null$;
  #169 = NameAndType        #53:#168      // MODULE$:Lscala/xml/Null$;
  #170 = Fieldref           #167.#169     // scala/xml/Null$.MODULE$:Lscala/xml/Null$;
  #171 = Utf8               scala/xml/TopScope$
  #172 = Class              #171          // scala/xml/TopScope$
  #173 = Utf8               Lscala/xml/TopScope$;
  #174 = NameAndType        #53:#173      // MODULE$:Lscala/xml/TopScope$;
  #175 = Fieldref           #172.#174     // scala/xml/TopScope$.MODULE$:Lscala/xml/TopScope$;
  #176 = Utf8               scala/xml/NodeSeq$
  #177 = Class              #176          // scala/xml/NodeSeq$
  #178 = Utf8               Lscala/xml/NodeSeq$;
  #179 = NameAndType        #53:#178      // MODULE$:Lscala/xml/NodeSeq$;
  #180 = Fieldref           #177.#179     // scala/xml/NodeSeq$.MODULE$:Lscala/xml/NodeSeq$;
  #181 = Utf8               scala/xml/NodeBuffer
  #182 = Class              #181          // scala/xml/NodeBuffer
  #183 = Utf8               <init>
  #184 = Utf8               ()V
  #185 = NameAndType        #183:#184     // "<init>":()V
  #186 = Methodref          #182.#185     // scala/xml/NodeBuffer."<init>":()V
  #187 = Utf8               scala/xml/Text
  #188 = Class              #187          // scala/xml/Text
  #189 = Utf8               \n
  #190 = String             #189          // \n
  #191 = Utf8               (Ljava/lang/String;)V
  #192 = NameAndType        #183:#191     // "<init>":(Ljava/lang/String;)V
  #193 = Methodref          #188.#192     // scala/xml/Text."<init>":(Ljava/lang/String;)V
  #194 = Utf8               $amp$plus
  #195 = Utf8               (Ljava/lang/Object;)Lscala/xml/NodeBuffer;
  #196 = NameAndType        #194:#195     // $amp$plus:(Ljava/lang/Object;)Lscala/xml/NodeBuffer;
  #197 = Methodref          #182.#196     // scala/xml/NodeBuffer.$amp$plus:(Ljava/lang/Object;)Lscala/xml/NodeBuffer;
  #198 = String             #27           // ordinal
  #199 = Utf8               \n
  #200 = String             #199          // \n
  #201 = Utf8               runStamp
  #202 = String             #201          // runStamp
  #203 = NameAndType        #27:#132      // ordinal:()Lorg/scalatest/events/Ordinal;
  #204 = Methodref          #2.#203       // org/scalatest/events/SuiteAborted.ordinal:()Lorg/scalatest/events/Ordinal;
  #205 = Utf8               org/scalatest/events/Ordinal
  #206 = Class              #205          // org/scalatest/events/Ordinal
  #207 = Utf8               ()I
  #208 = NameAndType        #201:#207     // runStamp:()I
  #209 = Methodref          #206.#208     // org/scalatest/events/Ordinal.runStamp:()I
  #210 = Utf8               scala/runtime/BoxesRunTime
  #211 = Class              #210          // scala/runtime/BoxesRunTime
  #212 = Utf8               boxToInteger
  #213 = Utf8               (I)Ljava/lang/Integer;
  #214 = NameAndType        #212:#213     // boxToInteger:(I)Ljava/lang/Integer;
  #215 = Methodref          #211.#214     // scala/runtime/BoxesRunTime.boxToInteger:(I)Ljava/lang/Integer;
  #216 = Utf8               seqToNodeSeq
  #217 = Utf8               (Lscala/collection/Seq;)Lscala/xml/NodeSeq;
  #218 = NameAndType        #216:#217     // seqToNodeSeq:(Lscala/collection/Seq;)Lscala/xml/NodeSeq;
  #219 = Methodref          #177.#218     // scala/xml/NodeSeq$.seqToNodeSeq:(Lscala/collection/Seq;)Lscala/xml/NodeSeq;
  #220 = Utf8               (Ljava/lang/String;Ljava/lang/String;Lscala/xml/MetaData;Lscala/xml/NamespaceBinding;ZLscala/collection/immutable/Seq;)V
  #221 = NameAndType        #183:#220     // "<init>":(Ljava/lang/String;Ljava/lang/String;Lscala/xml/MetaData;Lscala/xml/NamespaceBinding;ZLscala/collection/immutable/Seq;)V
  #222 = Methodref          #163.#221     // scala/xml/Elem."<init>":(Ljava/lang/String;Ljava/lang/String;Lscala/xml/MetaData;Lscala/xml/NamespaceBinding;ZLscala/collection/immutable/Seq;)V
  #223 = String             #29           // message
  #224 = NameAndType        #29:#60       // message:()Ljava/lang/String;
  #225 = Methodref          #2.#224       // org/scalatest/events/SuiteAborted.message:()Ljava/lang/String;
  #226 = String             #31           // suiteName
  #227 = NameAndType        #31:#60       // suiteName:()Ljava/lang/String;
  #228 = Methodref          #2.#227       // org/scalatest/events/SuiteAborted.suiteName:()Ljava/lang/String;
  #229 = String             #32           // suiteId
  #230 = NameAndType        #32:#60       // suiteId:()Ljava/lang/String;
  #231 = Methodref          #2.#230       // org/scalatest/events/SuiteAborted.suiteId:()Ljava/lang/String;
  #232 = String             #33           // suiteClassName
  #233 = Utf8               EventXmlHelper
  #234 = Utf8               ()Lorg/scalatest/events/Event$EventXmlHelper$;
  #235 = NameAndType        #233:#234     // EventXmlHelper:()Lorg/scalatest/events/Event$EventXmlHelper$;
  #236 = Methodref          #2.#235       // org/scalatest/events/SuiteAborted.EventXmlHelper:()Lorg/scalatest/events/Event$EventXmlHelper$;
  #237 = NameAndType        #33:#64       // suiteClassName:()Lscala/Option;
  #238 = Methodref          #2.#237       // org/scalatest/events/SuiteAborted.suiteClassName:()Lscala/Option;
  #239 = Utf8               stringOption
  #240 = Utf8               (Lscala/Option;)Ljava/lang/String;
  #241 = NameAndType        #239:#240     // stringOption:(Lscala/Option;)Ljava/lang/String;
  #242 = Methodref          #25.#241      // org/scalatest/events/Event$EventXmlHelper$.stringOption:(Lscala/Option;)Ljava/lang/String;
  #243 = String             #38           // duration
  #244 = NameAndType        #38:#64       // duration:()Lscala/Option;
  #245 = Methodref          #2.#244       // org/scalatest/events/SuiteAborted.duration:()Lscala/Option;
  #246 = Utf8               longOption
  #247 = NameAndType        #246:#240     // longOption:(Lscala/Option;)Ljava/lang/String;
  #248 = Methodref          #25.#247      // org/scalatest/events/Event$EventXmlHelper$.longOption:(Lscala/Option;)Ljava/lang/String;
  #249 = String             #36           // throwable
  #250 = NameAndType        #36:#64       // throwable:()Lscala/Option;
  #251 = Methodref          #2.#250       // org/scalatest/events/SuiteAborted.throwable:()Lscala/Option;
  #252 = Utf8               throwableOption
  #253 = Utf8               (Lscala/Option;)Ljava/lang/Object;
  #254 = NameAndType        #252:#253     // throwableOption:(Lscala/Option;)Ljava/lang/Object;
  #255 = Methodref          #25.#254      // org/scalatest/events/Event$EventXmlHelper$.throwableOption:(Lscala/Option;)Ljava/lang/Object;
  #256 = String             #40           // formatter
  #257 = NameAndType        #40:#64       // formatter:()Lscala/Option;
  #258 = Methodref          #2.#257       // org/scalatest/events/SuiteAborted.formatter:()Lscala/Option;
  #259 = Utf8               formatterOption
  #260 = NameAndType        #259:#253     // formatterOption:(Lscala/Option;)Ljava/lang/Object;
  #261 = Methodref          #25.#260      // org/scalatest/events/Event$EventXmlHelper$.formatterOption:(Lscala/Option;)Ljava/lang/Object;
  #262 = String             #42           // location
  #263 = NameAndType        #42:#64       // location:()Lscala/Option;
  #264 = Methodref          #2.#263       // org/scalatest/events/SuiteAborted.location:()Lscala/Option;
  #265 = Utf8               locationOption
  #266 = NameAndType        #265:#253     // locationOption:(Lscala/Option;)Ljava/lang/Object;
  #267 = Methodref          #25.#266      // org/scalatest/events/Event$EventXmlHelper$.locationOption:(Lscala/Option;)Ljava/lang/Object;
  #268 = String             #44           // rerunner
  #269 = NameAndType        #44:#64       // rerunner:()Lscala/Option;
  #270 = Methodref          #2.#269       // org/scalatest/events/SuiteAborted.rerunner:()Lscala/Option;
  #271 = String             #46           // threadName
  #272 = NameAndType        #46:#60       // threadName:()Ljava/lang/String;
  #273 = Methodref          #2.#272       // org/scalatest/events/SuiteAborted.threadName:()Ljava/lang/String;
  #274 = String             #47           // timeStamp
  #275 = NameAndType        #47:#50       // timeStamp:()J
  #276 = Methodref          #2.#275       // org/scalatest/events/SuiteAborted.timeStamp:()J
  #277 = Utf8               boxToLong
  #278 = Utf8               (J)Ljava/lang/Long;
  #279 = NameAndType        #277:#278     // boxToLong:(J)Ljava/lang/Long;
  #280 = Methodref          #211.#279     // scala/runtime/BoxesRunTime.boxToLong:(J)Ljava/lang/Long;
  #281 = Utf8               \n
  #282 = String             #281          // \n
  #283 = Utf8               $buf
  #284 = Utf8               Lscala/xml/NodeBuffer;
  #285 = Utf8               toJson
  #286 = Utf8               scala/collection/StringOps$
  #287 = Class              #286          // scala/collection/StringOps$
  #288 = Utf8               Lscala/collection/StringOps$;
  #289 = NameAndType        #53:#288      // MODULE$:Lscala/collection/StringOps$;
  #290 = Fieldref           #287.#289     // scala/collection/StringOps$.MODULE$:Lscala/collection/StringOps$;
  #291 = Utf8               scala/Predef$
  #292 = Class              #291          // scala/Predef$
  #293 = Utf8               Lscala/Predef$;
  #294 = NameAndType        #53:#293      // MODULE$:Lscala/Predef$;
  #295 = Fieldref           #292.#294     // scala/Predef$.MODULE$:Lscala/Predef$;
  #296 = Utf8               java/lang/StringBuilder
  #297 = Class              #296          // java/lang/StringBuilder
  #298 = Integer            208
  #299 = Utf8               (I)V
  #300 = NameAndType        #183:#299     // "<init>":(I)V
  #301 = Methodref          #297.#300     // java/lang/StringBuilder."<init>":(I)V
  #302 = Utf8               { \"eventType\": \"SuiteAborted\", \"ordinal\":
  #303 = String             #302          // { \"eventType\": \"SuiteAborted\", \"ordinal\":
  #304 = Utf8               append
  #305 = Utf8               (Ljava/lang/String;)Ljava/lang/StringBuilder;
  #306 = NameAndType        #304:#305     // append:(Ljava/lang/String;)Ljava/lang/StringBuilder;
  #307 = Methodref          #297.#306     // java/lang/StringBuilder.append:(Ljava/lang/String;)Ljava/lang/StringBuilder;
  #308 = Utf8               (I)Ljava/lang/StringBuilder;
  #309 = NameAndType        #304:#308     // append:(I)Ljava/lang/StringBuilder;
  #310 = Methodref          #297.#309     // java/lang/StringBuilder.append:(I)Ljava/lang/StringBuilder;
  #311 = Utf8               , \"message\":
  #312 = String             #311          // , \"message\":
  #313 = Utf8               EventJsonHelper
  #314 = Utf8               ()Lorg/scalatest/events/Event$EventJsonHelper$;
  #315 = NameAndType        #313:#314     // EventJsonHelper:()Lorg/scalatest/events/Event$EventJsonHelper$;
  #316 = Methodref          #2.#315       // org/scalatest/events/SuiteAborted.EventJsonHelper:()Lorg/scalatest/events/Event$EventJsonHelper$;
  #317 = Utf8               string
  #318 = Utf8               (Ljava/lang/String;)Ljava/lang/String;
  #319 = NameAndType        #317:#318     // string:(Ljava/lang/String;)Ljava/lang/String;
  #320 = Methodref          #22.#319      // org/scalatest/events/Event$EventJsonHelper$.string:(Ljava/lang/String;)Ljava/lang/String;
  #321 = Utf8               , \"suiteName\":
  #322 = String             #321          // , \"suiteName\":
  #323 = Utf8               , \"suiteId\":
  #324 = String             #323          // , \"suiteId\":
  #325 = Utf8               , \"suiteClassName\":
  #326 = String             #325          // , \"suiteClassName\":
  #327 = Methodref          #22.#241      // org/scalatest/events/Event$EventJsonHelper$.stringOption:(Lscala/Option;)Ljava/lang/String;
  #328 = Utf8               , \"duration\":
  #329 = String             #328          // , \"duration\":
  #330 = Utf8               ()Ljava/lang/Object;
  #331 = MethodType         #330          //  ()Ljava/lang/Object;
  #332 = Utf8               $anonfun$toJson$10
  #333 = NameAndType        #332:#60      // $anonfun$toJson$10:()Ljava/lang/String;
  #334 = Methodref          #2.#333       // org/scalatest/events/SuiteAborted.$anonfun$toJson$10:()Ljava/lang/String;
  #335 = MethodHandle       6:#334        // REF_invokeStatic org/scalatest/events/SuiteAborted.$anonfun$toJson$10:()Ljava/lang/String;
  #336 = MethodType         #60           //  ()Ljava/lang/String;
  #337 = Integer            5
  #338 = Integer            1
  #339 = Utf8               java/lang/invoke/LambdaMetafactory
  #340 = Class              #339          // java/lang/invoke/LambdaMetafactory
  #341 = Utf8               altMetafactory
  #342 = Utf8               (Ljava/lang/invoke/MethodHandles$Lookup;Ljava/lang/String;Ljava/lang/invoke/MethodType;[Ljava/lang/Object;)Ljava/lang/invoke/CallSite;
  #343 = NameAndType        #341:#342     // altMetafactory:(Ljava/lang/invoke/MethodHandles$Lookup;Ljava/lang/String;Ljava/lang/invoke/MethodType;[Ljava/lang/Object;)Ljava/lang/invoke/CallSite;
  #344 = Methodref          #340.#343     // java/lang/invoke/LambdaMetafactory.altMetafactory:(Ljava/lang/invoke/MethodHandles$Lookup;Ljava/lang/String;Ljava/lang/invoke/MethodType;[Ljava/lang/Object;)Ljava/lang/invoke/CallSite;
  #345 = MethodHandle       6:#344        // REF_invokeStatic java/lang/invoke/LambdaMetafactory.altMetafactory:(Ljava/lang/invoke/MethodHandles$Lookup;Ljava/lang/String;Ljava/lang/invoke/MethodType;[Ljava/lang/Object;)Ljava/lang/invoke/CallSite;
  #346 = Utf8               ()Lscala/Function0;
  #347 = NameAndType        #118:#346     // apply:()Lscala/Function0;
  #348 = InvokeDynamic      #0:#347       // #0:apply:()Lscala/Function0;
  #349 = Utf8               scala/Option
  #350 = Class              #349          // scala/Option
  #351 = Utf8               getOrElse
  #352 = Utf8               (Lscala/Function0;)Ljava/lang/Object;
  #353 = NameAndType        #351:#352     // getOrElse:(Lscala/Function0;)Ljava/lang/Object;
  #354 = Methodref          #350.#353     // scala/Option.getOrElse:(Lscala/Function0;)Ljava/lang/Object;
  #355 = Utf8               (Ljava/lang/Object;)Ljava/lang/StringBuilder;
  #356 = NameAndType        #304:#355     // append:(Ljava/lang/Object;)Ljava/lang/StringBuilder;
  #357 = Methodref          #297.#356     // java/lang/StringBuilder.append:(Ljava/lang/Object;)Ljava/lang/StringBuilder;
  #358 = Utf8               , \"throwable\":
  #359 = String             #358          // , \"throwable\":
  #360 = NameAndType        #252:#240     // throwableOption:(Lscala/Option;)Ljava/lang/String;
  #361 = Methodref          #22.#360      // org/scalatest/events/Event$EventJsonHelper$.throwableOption:(Lscala/Option;)Ljava/lang/String;
  #362 = Utf8               , \"formatter\":
  #363 = String             #362          // , \"formatter\":
  #364 = NameAndType        #259:#240     // formatterOption:(Lscala/Option;)Ljava/lang/String;
  #365 = Methodref          #22.#364      // org/scalatest/events/Event$EventJsonHelper$.formatterOption:(Lscala/Option;)Ljava/lang/String;
  #366 = Utf8               , \"location\":
  #367 = String             #366          // , \"location\":
  #368 = NameAndType        #265:#240     // locationOption:(Lscala/Option;)Ljava/lang/String;
  #369 = Methodref          #22.#368      // org/scalatest/events/Event$EventJsonHelper$.locationOption:(Lscala/Option;)Ljava/lang/String;
  #370 = Utf8               , \"rerunner\":
  #371 = String             #370          // , \"rerunner\":
  #372 = Utf8               , \"threadName\":
  #373 = String             #372          // , \"threadName\":
  #374 = Utf8               , \"timeStamp\":
  #375 = String             #374          // , \"timeStamp\":
  #376 = Utf8               (J)Ljava/lang/StringBuilder;
  #377 = NameAndType        #304:#376     // append:(J)Ljava/lang/StringBuilder;
  #378 = Methodref          #297.#377     // java/lang/StringBuilder.append:(J)Ljava/lang/StringBuilder;
  #379 = Utf8                }
  #380 = String             #379          //  }
  #381 = Utf8               toString
  #382 = NameAndType        #381:#60      // toString:()Ljava/lang/String;
  #383 = Methodref          #297.#382     // java/lang/StringBuilder.toString:()Ljava/lang/String;
  #384 = Utf8               augmentString
  #385 = NameAndType        #384:#318     // augmentString:(Ljava/lang/String;)Ljava/lang/String;
  #386 = Methodref          #292.#385     // scala/Predef$.augmentString:(Ljava/lang/String;)Ljava/lang/String;
  #387 = Utf8               stripMargin$extension
  #388 = NameAndType        #387:#318     // stripMargin$extension:(Ljava/lang/String;)Ljava/lang/String;
  #389 = Methodref          #287.#388     // scala/collection/StringOps$.stripMargin$extension:(Ljava/lang/String;)Ljava/lang/String;
  #390 = Utf8               withPayload
  #391 = Utf8               (Lscala/Option;)Lorg/scalatest/events/SuiteAborted;
  #392 = Utf8               (Lscala/Option<Ljava/lang/Object;>;)Lorg/scalatest/events/SuiteAborted;
  #393 = Utf8               newPayload
  #394 = Utf8               copy$default$1
  #395 = NameAndType        #394:#132     // copy$default$1:()Lorg/scalatest/events/Ordinal;
  #396 = Methodref          #2.#395       // org/scalatest/events/SuiteAborted.copy$default$1:()Lorg/scalatest/events/Ordinal;
  #397 = Utf8               copy$default$2
  #398 = NameAndType        #397:#60      // copy$default$2:()Ljava/lang/String;
  #399 = Methodref          #2.#398       // org/scalatest/events/SuiteAborted.copy$default$2:()Ljava/lang/String;
  #400 = Utf8               copy$default$3
  #401 = NameAndType        #400:#60      // copy$default$3:()Ljava/lang/String;
  #402 = Methodref          #2.#401       // org/scalatest/events/SuiteAborted.copy$default$3:()Ljava/lang/String;
  #403 = Utf8               copy$default$4
  #404 = NameAndType        #403:#60      // copy$default$4:()Ljava/lang/String;
  #405 = Methodref          #2.#404       // org/scalatest/events/SuiteAborted.copy$default$4:()Ljava/lang/String;
  #406 = Utf8               copy$default$5
  #407 = NameAndType        #406:#64      // copy$default$5:()Lscala/Option;
  #408 = Methodref          #2.#407       // org/scalatest/events/SuiteAborted.copy$default$5:()Lscala/Option;
  #409 = Utf8               copy$default$6
  #410 = NameAndType        #409:#64      // copy$default$6:()Lscala/Option;
  #411 = Methodref          #2.#410       // org/scalatest/events/SuiteAborted.copy$default$6:()Lscala/Option;
  #412 = Utf8               copy$default$7
  #413 = NameAndType        #412:#64      // copy$default$7:()Lscala/Option;
  #414 = Methodref          #2.#413       // org/scalatest/events/SuiteAborted.copy$default$7:()Lscala/Option;
  #415 = Utf8               copy$default$8
  #416 = NameAndType        #415:#64      // copy$default$8:()Lscala/Option;
  #417 = Methodref          #2.#416       // org/scalatest/events/SuiteAborted.copy$default$8:()Lscala/Option;
  #418 = Utf8               copy$default$9
  #419 = NameAndType        #418:#64      // copy$default$9:()Lscala/Option;
  #420 = Methodref          #2.#419       // org/scalatest/events/SuiteAborted.copy$default$9:()Lscala/Option;
  #421 = Utf8               copy$default$10
  #422 = NameAndType        #421:#64      // copy$default$10:()Lscala/Option;
  #423 = Methodref          #2.#422       // org/scalatest/events/SuiteAborted.copy$default$10:()Lscala/Option;
  #424 = Utf8               copy$default$12
  #425 = NameAndType        #424:#60      // copy$default$12:()Ljava/lang/String;
  #426 = Methodref          #2.#425       // org/scalatest/events/SuiteAborted.copy$default$12:()Ljava/lang/String;
  #427 = Utf8               copy$default$13
  #428 = NameAndType        #427:#50      // copy$default$13:()J
  #429 = Methodref          #2.#428       // org/scalatest/events/SuiteAborted.copy$default$13:()J
  #430 = Utf8               copy
  #431 = NameAndType        #430:#119     // copy:(Lorg/scalatest/events/Ordinal;Ljava/lang/String;Ljava/lang/String;Ljava/lang/String;Lscala/Option;Lscala/Option;Lscala/Option;Lscala/Option;Lscala/Option;Lscala/Option;Lscala/Option;Ljava/lang/String;J)Lorg/scalatest/events/SuiteAborted;
  #432 = Methodref          #2.#431       // org/scalatest/events/SuiteAborted.copy:(Lorg/scalatest/events/Ordinal;Ljava/lang/String;Ljava/lang/String;Ljava/lang/String;Lscala/Option;Lscala/Option;Lscala/Option;Lscala/Option;Lscala/Option;Lscala/Option;Lscala/Option;Ljava/lang/String;J)Lorg/scalatest/events/SuiteAborted;
  #433 = Utf8               x$1
  #434 = Utf8               x$2
  #435 = Utf8               x$3
  #436 = Utf8               x$4
  #437 = Utf8               x$5
  #438 = Utf8               x$6
  #439 = Utf8               x$7
  #440 = Utf8               x$8
  #441 = Utf8               x$9
  #442 = Utf8               x$10
  #443 = Utf8               x$11
  #444 = Utf8               x$12
  #445 = Utf8               x$13
  #446 = Utf8               withThrowable
  #447 = Utf8               (Lscala/Option;)Lorg/scalatest/events/Event;
  #448 = Utf8               (Lscala/Option<Ljava/lang/Throwable;>;)Lorg/scalatest/events/Event;
  #449 = Utf8               newThrowable
  #450 = Utf8               copy$default$11
  #451 = NameAndType        #450:#64      // copy$default$11:()Lscala/Option;
  #452 = Methodref          #2.#451       // org/scalatest/events/SuiteAborted.copy$default$11:()Lscala/Option;
  #453 = Utf8               ensureSerializable
  #454 = Utf8               ()Lorg/scalatest/events/Event;
  #455 = NameAndType        #45:#64       // payload:()Lscala/Option;
  #456 = Methodref          #2.#455       // org/scalatest/events/SuiteAborted.payload:()Lscala/Option;
  #457 = Utf8               ensurePayloadSerializable
  #458 = NameAndType        #457:#447     // ensurePayloadSerializable:(Lscala/Option;)Lorg/scalatest/events/Event;
  #459 = Methodref          #2.#458       // org/scalatest/events/SuiteAborted.ensurePayloadSerializable:(Lscala/Option;)Lorg/scalatest/events/Event;
  #460 = Utf8               ensureThrowableSerializable
  #461 = NameAndType        #460:#447     // ensureThrowableSerializable:(Lscala/Option;)Lorg/scalatest/events/Event;
  #462 = Methodref          #4.#461       // org/scalatest/events/Event.ensureThrowableSerializable:(Lscala/Option;)Lorg/scalatest/events/Event;
  #463 = Utf8               (Lorg/scalatest/events/Ordinal;Ljava/lang/String;Ljava/lang/String;Ljava/lang/String;Lscala/Option;Lscala/Option;Lscala/Option;Lscala/Option;Lscala/Option;Lscala/Option;Lscala/Option;Ljava/lang/String;J)V
  #464 = NameAndType        #183:#463     // "<init>":(Lorg/scalatest/events/Ordinal;Ljava/lang/String;Ljava/lang/String;Ljava/lang/String;Lscala/Option;Lscala/Option;Lscala/Option;Lscala/Option;Lscala/Option;Lscala/Option;Lscala/Option;Ljava/lang/String;J)V
  #465 = Methodref          #2.#464       // org/scalatest/events/SuiteAborted."<init>":(Lorg/scalatest/events/Ordinal;Ljava/lang/String;Ljava/lang/String;Ljava/lang/String;Lscala/Option;Lscala/Option;Lscala/Option;Lscala/Option;Lscala/Option;Lscala/Option;Lscala/Option;Ljava/lang/String;J)V
  #466 = Utf8               productPrefix
  #467 = Utf8               productArity
  #468 = Utf8               productElement
  #469 = Utf8               (I)Ljava/lang/Object;
  #470 = Utf8               scala/runtime/Statics
  #471 = Class              #470          // scala/runtime/Statics
  #472 = Utf8               ioobe
  #473 = NameAndType        #472:#469     // ioobe:(I)Ljava/lang/Object;
  #474 = Methodref          #471.#473     // scala/runtime/Statics.ioobe:(I)Ljava/lang/Object;
  #475 = Utf8               I
  #476 = Utf8               java/lang/Object
  #477 = Class              #476          // java/lang/Object
  #478 = Utf8               productIterator
  #479 = Utf8               ()Lscala/collection/Iterator;
  #480 = Utf8               ()Lscala/collection/Iterator<Ljava/lang/Object;>;
  #481 = Utf8               scala/runtime/ScalaRunTime$
  #482 = Class              #481          // scala/runtime/ScalaRunTime$
  #483 = Utf8               Lscala/runtime/ScalaRunTime$;
  #484 = NameAndType        #53:#483      // MODULE$:Lscala/runtime/ScalaRunTime$;
  #485 = Fieldref           #482.#484     // scala/runtime/ScalaRunTime$.MODULE$:Lscala/runtime/ScalaRunTime$;
  #486 = Utf8               typedProductIterator
  #487 = Utf8               (Lscala/Product;)Lscala/collection/Iterator;
  #488 = NameAndType        #486:#487     // typedProductIterator:(Lscala/Product;)Lscala/collection/Iterator;
  #489 = Methodref          #482.#488     // scala/runtime/ScalaRunTime$.typedProductIterator:(Lscala/Product;)Lscala/collection/Iterator;
  #490 = Utf8               canEqual
  #491 = Utf8               (Ljava/lang/Object;)Z
  #492 = Utf8               Ljava/lang/Object;
  #493 = Utf8               productElementName
  #494 = Utf8               (I)Ljava/lang/String;
  #495 = String             #45           // payload
  #496 = Utf8               java/lang/String
  #497 = Class              #496          // java/lang/String
  #498 = Utf8               hashCode
  #499 = Integer            -889275714
  #500 = NameAndType        #466:#60      // productPrefix:()Ljava/lang/String;
  #501 = Methodref          #2.#500       // org/scalatest/events/SuiteAborted.productPrefix:()Ljava/lang/String;
  #502 = NameAndType        #498:#207     // hashCode:()I
  #503 = Methodref          #497.#502     // java/lang/String.hashCode:()I
  #504 = Utf8               mix
  #505 = Utf8               (II)I
  #506 = NameAndType        #504:#505     // mix:(II)I
  #507 = Methodref          #471.#506     // scala/runtime/Statics.mix:(II)I
  #508 = Utf8               anyHash
  #509 = Utf8               (Ljava/lang/Object;)I
  #510 = NameAndType        #508:#509     // anyHash:(Ljava/lang/Object;)I
  #511 = Methodref          #471.#510     // scala/runtime/Statics.anyHash:(Ljava/lang/Object;)I
  #512 = Utf8               longHash
  #513 = Utf8               (J)I
  #514 = NameAndType        #512:#513     // longHash:(J)I
  #515 = Methodref          #471.#514     // scala/runtime/Statics.longHash:(J)I
  #516 = Utf8               finalizeHash
  #517 = NameAndType        #516:#505     // finalizeHash:(II)I
  #518 = Methodref          #471.#517     // scala/runtime/Statics.finalizeHash:(II)I
  #519 = Utf8               _toString
  #520 = Utf8               (Lscala/Product;)Ljava/lang/String;
  #521 = NameAndType        #519:#520     // _toString:(Lscala/Product;)Ljava/lang/String;
  #522 = Methodref          #482.#521     // scala/runtime/ScalaRunTime$._toString:(Lscala/Product;)Ljava/lang/String;
  #523 = Utf8               equals
  #524 = NameAndType        #523:#491     // equals:(Ljava/lang/Object;)Z
  #525 = Methodref          #477.#524     // java/lang/Object.equals:(Ljava/lang/Object;)Z
  #526 = NameAndType        #390:#391     // withPayload:(Lscala/Option;)Lorg/scalatest/events/SuiteAborted;
  #527 = Methodref          #2.#526       // org/scalatest/events/SuiteAborted.withPayload:(Lscala/Option;)Lorg/scalatest/events/SuiteAborted;
  #528 = Utf8               null
  #529 = String             #528          // null
  #530 = Utf8               (Lorg/scalatest/events/Ordinal;Ljava/lang/String;Ljava/lang/String;Ljava/lang/String;Lscala/Option<Ljava/lang/String;>;Lscala/Option<Ljava/lang/Throwable;>;Lscala/Option<Ljava/lang/Object;>;Lscala/Option<Lorg/scalatest/events/Formatter;>;Lscala/Option<Lorg/scalatest/events/Location;>;Lscala/Option<Ljava/lang/String;>;Lscala/Option<Ljava/lang/Object;>;Ljava/lang/String;J)V
  #531 = Methodref          #4.#185       // org/scalatest/events/Event."<init>":()V
  #532 = Utf8               org/scalactic/Requirements$
  #533 = Class              #532          // org/scalactic/Requirements$
  #534 = Utf8               Lorg/scalactic/Requirements$;
  #535 = NameAndType        #53:#534      // MODULE$:Lorg/scalactic/Requirements$;
  #536 = Fieldref           #533.#535     // org/scalactic/Requirements$.MODULE$:Lorg/scalactic/Requirements$;
  #537 = Utf8               requirementsHelper
  #538 = Utf8               ()Lorg/scalactic/Requirements$RequirementsHelper;
  #539 = NameAndType        #537:#538     // requirementsHelper:()Lorg/scalactic/Requirements$RequirementsHelper;
  #540 = Methodref          #533.#539     // org/scalactic/Requirements$.requirementsHelper:()Lorg/scalactic/Requirements$RequirementsHelper;
  #541 = Utf8               SuiteAborted.this.ordinal
  #542 = String             #541          // SuiteAborted.this.ordinal
  #543 = Utf8               SuiteAborted.this.message
  #544 = String             #543          // SuiteAborted.this.message
  #545 = Utf8               SuiteAborted.this.suiteName
  #546 = String             #545          // SuiteAborted.this.suiteName
  #547 = Utf8               SuiteAborted.this.suiteId
  #548 = String             #547          // SuiteAborted.this.suiteId
  #549 = Utf8               SuiteAborted.this.suiteClassName
  #550 = String             #549          // SuiteAborted.this.suiteClassName
  #551 = Utf8               SuiteAborted.this.throwable
  #552 = String             #551          // SuiteAborted.this.throwable
  #553 = Utf8               SuiteAborted.this.duration
  #554 = String             #553          // SuiteAborted.this.duration
  #555 = Utf8               SuiteAborted.this.formatter
  #556 = String             #555          // SuiteAborted.this.formatter
  #557 = Utf8               SuiteAborted.this.location
  #558 = String             #557          // SuiteAborted.this.location
  #559 = Utf8               SuiteAborted.this.rerunner
  #560 = String             #559          // SuiteAborted.this.rerunner
  #561 = Utf8               SuiteAborted.this.payload
  #562 = String             #561          // SuiteAborted.this.payload
  #563 = Utf8               SuiteAborted.this.threadName
  #564 = String             #563          // SuiteAborted.this.threadName
  #565 = Utf8               [Ljava/lang/Object;
  #566 = Class              #565          // "[Ljava/lang/Object;"
  #567 = Utf8               [Ljava/lang/String;
  #568 = Class              #567          // "[Ljava/lang/String;"
  #569 = Utf8               org/scalactic/Prettifier$
  #570 = Class              #569          // org/scalactic/Prettifier$
  #571 = Utf8               Lorg/scalactic/Prettifier$;
  #572 = NameAndType        #53:#571      // MODULE$:Lorg/scalactic/Prettifier$;
  #573 = Fieldref           #570.#572     // org/scalactic/Prettifier$.MODULE$:Lorg/scalactic/Prettifier$;
  #574 = Utf8               default
  #575 = Utf8               ()Lorg/scalactic/Prettifier;
  #576 = NameAndType        #574:#575     // default:()Lorg/scalactic/Prettifier;
  #577 = Methodref          #570.#576     // org/scalactic/Prettifier$.default:()Lorg/scalactic/Prettifier;
  #578 = Utf8               org/scalactic/source/Position
  #579 = Class              #578          // org/scalactic/source/Position
  #580 = String             #7            // Event.scala
  #581 = Utf8               Please set the environment variable SCALACTIC_FILL_FILE_PATHNAMES to yes at compile time to enable this feature.
  #582 = String             #581          // Please set the environment variable SCALACTIC_FILL_FILE_PATHNAMES to yes at compile time to enable this feature.
  #583 = Utf8               (Ljava/lang/String;Ljava/lang/String;I)V
  #584 = NameAndType        #183:#583     // "<init>":(Ljava/lang/String;Ljava/lang/String;I)V
  #585 = Methodref          #579.#584     // org/scalactic/source/Position."<init>":(Ljava/lang/String;Ljava/lang/String;I)V
  #586 = Utf8               macroRequireNonNull
  #587 = Utf8               ([Ljava/lang/String;[Ljava/lang/Object;Lorg/scalactic/Prettifier;Lorg/scalactic/source/Position;)V
  #588 = NameAndType        #586:#587     // macroRequireNonNull:([Ljava/lang/String;[Ljava/lang/Object;Lorg/scalactic/Prettifier;Lorg/scalactic/source/Position;)V
  #589 = Methodref          #17.#588      // org/scalactic/Requirements$RequirementsHelper.macroRequireNonNull:([Ljava/lang/String;[Ljava/lang/Object;Lorg/scalactic/Prettifier;Lorg/scalactic/source/Position;)V
  #590 = Utf8               $deserializeLambda$
  #591 = Utf8               (Ljava/lang/invoke/SerializedLambda;)Ljava/lang/Object;
  #592 = Utf8               scala/runtime/LambdaDeserialize
  #593 = Class              #592          // scala/runtime/LambdaDeserialize
  #594 = Utf8               bootstrap
  #595 = Utf8               (Ljava/lang/invoke/MethodHandles$Lookup;Ljava/lang/String;Ljava/lang/invoke/MethodType;[Ljava/lang/invoke/MethodHandle;)Ljava/lang/invoke/CallSite;
  #596 = NameAndType        #594:#595     // bootstrap:(Ljava/lang/invoke/MethodHandles$Lookup;Ljava/lang/String;Ljava/lang/invoke/MethodType;[Ljava/lang/invoke/MethodHandle;)Ljava/lang/invoke/CallSite;
  #597 = Methodref          #593.#596     // scala/runtime/LambdaDeserialize.bootstrap:(Ljava/lang/invoke/MethodHandles$Lookup;Ljava/lang/String;Ljava/lang/invoke/MethodType;[Ljava/lang/invoke/MethodHandle;)Ljava/lang/invoke/CallSite;
  #598 = MethodHandle       6:#597        // REF_invokeStatic scala/runtime/LambdaDeserialize.bootstrap:(Ljava/lang/invoke/MethodHandles$Lookup;Ljava/lang/String;Ljava/lang/invoke/MethodType;[Ljava/lang/invoke/MethodHandle;)Ljava/lang/invoke/CallSite;
  #599 = Utf8               lambdaDeserialize
  #600 = NameAndType        #599:#591     // lambdaDeserialize:(Ljava/lang/invoke/SerializedLambda;)Ljava/lang/Object;
  #601 = InvokeDynamic      #1:#600       // #1:lambdaDeserialize:(Ljava/lang/invoke/SerializedLambda;)Ljava/lang/Object;
  #602 = Utf8               Signature
  #603 = Utf8               Code
  #604 = Utf8               LocalVariableTable
  #605 = Utf8               MethodParameters
  #606 = Utf8               LineNumberTable
  #607 = Utf8               StackMapTable
  #608 = Utf8               InnerClasses
  #609 = Utf8               SourceFile
  #610 = Utf8               RuntimeVisibleAnnotations
  #611 = Utf8               BootstrapMethods
  #612 = Utf8               ScalaInlineInfo
  #613 = Utf8               ScalaSig
{
  private final org.scalatest.events.Ordinal ordinal;
    descriptor: Lorg/scalatest/events/Ordinal;
    flags: (0x0012) ACC_PRIVATE, ACC_FINAL

  private final java.lang.String message;
    descriptor: Ljava/lang/String;
    flags: (0x0012) ACC_PRIVATE, ACC_FINAL

  private final java.lang.String suiteName;
    descriptor: Ljava/lang/String;
    flags: (0x0012) ACC_PRIVATE, ACC_FINAL

  private final java.lang.String suiteId;
    descriptor: Ljava/lang/String;
    flags: (0x0012) ACC_PRIVATE, ACC_FINAL

  private final scala.Option<java.lang.String> suiteClassName;
    descriptor: Lscala/Option;
    flags: (0x0012) ACC_PRIVATE, ACC_FINAL
    Signature: #35                          // Lscala/Option<Ljava/lang/String;>;

  private final scala.Option<java.lang.Throwable> throwable;
    descriptor: Lscala/Option;
    flags: (0x0012) ACC_PRIVATE, ACC_FINAL
    Signature: #37                          // Lscala/Option<Ljava/lang/Throwable;>;

  private final scala.Option<java.lang.Object> duration;
    descriptor: Lscala/Option;
    flags: (0x0012) ACC_PRIVATE, ACC_FINAL
    Signature: #39                          // Lscala/Option<Ljava/lang/Object;>;

  private final scala.Option<org.scalatest.events.Formatter> formatter;
    descriptor: Lscala/Option;
    flags: (0x0012) ACC_PRIVATE, ACC_FINAL
    Signature: #41                          // Lscala/Option<Lorg/scalatest/events/Formatter;>;

  private final scala.Option<org.scalatest.events.Location> location;
    descriptor: Lscala/Option;
    flags: (0x0012) ACC_PRIVATE, ACC_FINAL
    Signature: #43                          // Lscala/Option<Lorg/scalatest/events/Location;>;

  private final scala.Option<java.lang.String> rerunner;
    descriptor: Lscala/Option;
    flags: (0x0012) ACC_PRIVATE, ACC_FINAL
    Signature: #35                          // Lscala/Option<Ljava/lang/String;>;

  private final scala.Option<java.lang.Object> payload;
    descriptor: Lscala/Option;
    flags: (0x0012) ACC_PRIVATE, ACC_FINAL
    Signature: #39                          // Lscala/Option<Ljava/lang/Object;>;

  private final java.lang.String threadName;
    descriptor: Ljava/lang/String;
    flags: (0x0012) ACC_PRIVATE, ACC_FINAL

  private final long timeStamp;
    descriptor: J
    flags: (0x0012) ACC_PRIVATE, ACC_FINAL

  public static long $lessinit$greater$default$13();
    descriptor: ()J
    flags: (0x0009) ACC_PUBLIC, ACC_STATIC
    Code:
      stack=2, locals=0, args_size=0
         0: getstatic     #56                 // Field org/scalatest/events/SuiteAborted$.MODULE$:Lorg/scalatest/events/SuiteAborted$;
         3: invokevirtual #58                 // Method org/scalatest/events/SuiteAborted$.$lessinit$greater$default$13:()J
         6: lreturn

  public static java.lang.String $lessinit$greater$default$12();
    descriptor: ()Ljava/lang/String;
    flags: (0x0009) ACC_PUBLIC, ACC_STATIC
    Code:
      stack=1, locals=0, args_size=0
         0: getstatic     #56                 // Field org/scalatest/events/SuiteAborted$.MODULE$:Lorg/scalatest/events/SuiteAborted$;
         3: invokevirtual #62                 // Method org/scalatest/events/SuiteAborted$.$lessinit$greater$default$12:()Ljava/lang/String;
         6: areturn

  public static scala.Option<java.lang.Object> $lessinit$greater$default$11();
    descriptor: ()Lscala/Option;
    flags: (0x0009) ACC_PUBLIC, ACC_STATIC
    Code:
      stack=1, locals=0, args_size=0
         0: getstatic     #56                 // Field org/scalatest/events/SuiteAborted$.MODULE$:Lorg/scalatest/events/SuiteAborted$;
         3: invokevirtual #67                 // Method org/scalatest/events/SuiteAborted$.$lessinit$greater$default$11:()Lscala/Option;
         6: areturn
    Signature: #65                          // ()Lscala/Option<Ljava/lang/Object;>;

  public static scala.Option<java.lang.String> $lessinit$greater$default$10();
    descriptor: ()Lscala/Option;
    flags: (0x0009) ACC_PUBLIC, ACC_STATIC
    Code:
      stack=1, locals=0, args_size=0
         0: getstatic     #56                 // Field org/scalatest/events/SuiteAborted$.MODULE$:Lorg/scalatest/events/SuiteAborted$;
         3: invokevirtual #71                 // Method org/scalatest/events/SuiteAborted$.$lessinit$greater$default$10:()Lscala/Option;
         6: areturn
    Signature: #69                          // ()Lscala/Option<Ljava/lang/String;>;

  public static scala.Option<org.scalatest.events.Location> $lessinit$greater$default$9();
    descriptor: ()Lscala/Option;
    flags: (0x0009) ACC_PUBLIC, ACC_STATIC
    Code:
      stack=1, locals=0, args_size=0
         0: getstatic     #56                 // Field org/scalatest/events/SuiteAborted$.MODULE$:Lorg/scalatest/events/SuiteAborted$;
         3: invokevirtual #75                 // Method org/scalatest/events/SuiteAborted$.$lessinit$greater$default$9:()Lscala/Option;
         6: areturn
    Signature: #73                          // ()Lscala/Option<Lorg/scalatest/events/Location;>;

  public static scala.Option<org.scalatest.events.Formatter> $lessinit$greater$default$8();
    descriptor: ()Lscala/Option;
    flags: (0x0009) ACC_PUBLIC, ACC_STATIC
    Code:
      stack=1, locals=0, args_size=0
         0: getstatic     #56                 // Field org/scalatest/events/SuiteAborted$.MODULE$:Lorg/scalatest/events/SuiteAborted$;
         3: invokevirtual #79                 // Method org/scalatest/events/SuiteAborted$.$lessinit$greater$default$8:()Lscala/Option;
         6: areturn
    Signature: #77                          // ()Lscala/Option<Lorg/scalatest/events/Formatter;>;

  public static scala.Option<java.lang.Object> $lessinit$greater$default$7();
    descriptor: ()Lscala/Option;
    flags: (0x0009) ACC_PUBLIC, ACC_STATIC
    Code:
      stack=1, locals=0, args_size=0
         0: getstatic     #56                 // Field org/scalatest/events/SuiteAborted$.MODULE$:Lorg/scalatest/events/SuiteAborted$;
         3: invokevirtual #82                 // Method org/scalatest/events/SuiteAborted$.$lessinit$greater$default$7:()Lscala/Option;
         6: areturn
    Signature: #65                          // ()Lscala/Option<Ljava/lang/Object;>;

  public static scala.Option<java.lang.Throwable> $lessinit$greater$default$6();
    descriptor: ()Lscala/Option;
    flags: (0x0009) ACC_PUBLIC, ACC_STATIC
    Code:
      stack=1, locals=0, args_size=0
         0: getstatic     #56                 // Field org/scalatest/events/SuiteAborted$.MODULE$:Lorg/scalatest/events/SuiteAborted$;
         3: invokevirtual #86                 // Method org/scalatest/events/SuiteAborted$.$lessinit$greater$default$6:()Lscala/Option;
         6: areturn
    Signature: #84                          // ()Lscala/Option<Ljava/lang/Throwable;>;

  public static scala.Option<scala.Tuple13<org.scalatest.events.Ordinal, java.lang.String, java.lang.String, java.lang.String, scala.Option<java.lang.String>, scala.Option<java.lang.Throwable>, scala.Option<java.lang.Object>, scala.Option<org.scalatest.events.Formatter>, scala.Option<org.scalatest.events.Location>, scala.Option<java.lang.String>, scala.Option<java.lang.Object>, java.lang.String, java.lang.Object>> unapply(org.scalatest.events.SuiteAborted);
    descriptor: (Lorg/scalatest/events/SuiteAborted;)Lscala/Option;
    flags: (0x0009) ACC_PUBLIC, ACC_STATIC
    Code:
      stack=2, locals=1, args_size=1
         0: getstatic     #56                 // Field org/scalatest/events/SuiteAborted$.MODULE$:Lorg/scalatest/events/SuiteAborted$;
         3: aload_0
         4: invokevirtual #92                 // Method org/scalatest/events/SuiteAborted$.unapply:(Lorg/scalatest/events/SuiteAborted;)Lscala/Option;
         7: areturn
      LocalVariableTable:
        Start  Length  Slot  Name   Signature
            0       8     0   x$0   Lorg/scalatest/events/SuiteAborted;
    Signature: #89                          // (Lorg/scalatest/events/SuiteAborted;)Lscala/Option<Lscala/Tuple13<Lorg/scalatest/events/Ordinal;Ljava/lang/String;Ljava/lang/String;Ljava/lang/String;Lscala/Option<Ljava/lang/String;>;Lscala/Option<Ljava/lang/Throwable;>;Lscala/Option<Ljava/lang/Object;>;Lscala/Option<Lorg/scalatest/events/Formatter;>;Lscala/Option<Lorg/scalatest/events/Location;>;Lscala/Option<Ljava/lang/String;>;Lscala/Option<Ljava/lang/Object;>;Ljava/lang/String;Ljava/lang/Object;>;>;
    MethodParameters:
      Name                           Flags
      x$0                            final

  public static long apply$default$13();
    descriptor: ()J
    flags: (0x0009) ACC_PUBLIC, ACC_STATIC
    Code:
      stack=2, locals=0, args_size=0
         0: getstatic     #56                 // Field org/scalatest/events/SuiteAborted$.MODULE$:Lorg/scalatest/events/SuiteAborted$;
         3: invokevirtual #96                 // Method org/scalatest/events/SuiteAborted$.apply$default$13:()J
         6: lreturn

  public static java.lang.String apply$default$12();
    descriptor: ()Ljava/lang/String;
    flags: (0x0009) ACC_PUBLIC, ACC_STATIC
    Code:
      stack=1, locals=0, args_size=0
         0: getstatic     #56                 // Field org/scalatest/events/SuiteAborted$.MODULE$:Lorg/scalatest/events/SuiteAborted$;
         3: invokevirtual #99                 // Method org/scalatest/events/SuiteAborted$.apply$default$12:()Ljava/lang/String;
         6: areturn

  public static scala.Option<java.lang.Object> apply$default$11();
    descriptor: ()Lscala/Option;
    flags: (0x0009) ACC_PUBLIC, ACC_STATIC
    Code:
      stack=1, locals=0, args_size=0
         0: getstatic     #56                 // Field org/scalatest/events/SuiteAborted$.MODULE$:Lorg/scalatest/events/SuiteAborted$;
         3: invokevirtual #102                // Method org/scalatest/events/SuiteAborted$.apply$default$11:()Lscala/Option;
         6: areturn
    Signature: #65                          // ()Lscala/Option<Ljava/lang/Object;>;

  public static scala.Option<java.lang.String> apply$default$10();
    descriptor: ()Lscala/Option;
    flags: (0x0009) ACC_PUBLIC, ACC_STATIC
    Code:
      stack=1, locals=0, args_size=0
         0: getstatic     #56                 // Field org/scalatest/events/SuiteAborted$.MODULE$:Lorg/scalatest/events/SuiteAborted$;
         3: invokevirtual #105                // Method org/scalatest/events/SuiteAborted$.apply$default$10:()Lscala/Option;
         6: areturn
    Signature: #69                          // ()Lscala/Option<Ljava/lang/String;>;

  public static scala.Option<org.scalatest.events.Location> apply$default$9();
    descriptor: ()Lscala/Option;
    flags: (0x0009) ACC_PUBLIC, ACC_STATIC
    Code:
      stack=1, locals=0, args_size=0
         0: getstatic     #56                 // Field org/scalatest/events/SuiteAborted$.MODULE$:Lorg/scalatest/events/SuiteAborted$;
         3: invokevirtual #108                // Method org/scalatest/events/SuiteAborted$.apply$default$9:()Lscala/Option;
         6: areturn
    Signature: #73                          // ()Lscala/Option<Lorg/scalatest/events/Location;>;

  public static scala.Option<org.scalatest.events.Formatter> apply$default$8();
    descriptor: ()Lscala/Option;
    flags: (0x0009) ACC_PUBLIC, ACC_STATIC
    Code:
      stack=1, locals=0, args_size=0
         0: getstatic     #56                 // Field org/scalatest/events/SuiteAborted$.MODULE$:Lorg/scalatest/events/SuiteAborted$;
         3: invokevirtual #111                // Method org/scalatest/events/SuiteAborted$.apply$default$8:()Lscala/Option;
         6: areturn
    Signature: #77                          // ()Lscala/Option<Lorg/scalatest/events/Formatter;>;

  public static scala.Option<java.lang.Object> apply$default$7();
    descriptor: ()Lscala/Option;
    flags: (0x0009) ACC_PUBLIC, ACC_STATIC
    Code:
      stack=1, locals=0, args_size=0
         0: getstatic     #56                 // Field org/scalatest/events/SuiteAborted$.MODULE$:Lorg/scalatest/events/SuiteAborted$;
         3: invokevirtual #114                // Method org/scalatest/events/SuiteAborted$.apply$default$7:()Lscala/Option;
         6: areturn
    Signature: #65                          // ()Lscala/Option<Ljava/lang/Object;>;

  public static scala.Option<java.lang.Throwable> apply$default$6();
    descriptor: ()Lscala/Option;
    flags: (0x0009) ACC_PUBLIC, ACC_STATIC
    Code:
      stack=1, locals=0, args_size=0
         0: getstatic     #56                 // Field org/scalatest/events/SuiteAborted$.MODULE$:Lorg/scalatest/events/SuiteAborted$;
         3: invokevirtual #117                // Method org/scalatest/events/SuiteAborted$.apply$default$6:()Lscala/Option;
         6: areturn
    Signature: #84                          // ()Lscala/Option<Ljava/lang/Throwable;>;

  public static org.scalatest.events.SuiteAborted apply(org.scalatest.events.Ordinal, java.lang.String, java.lang.String, java.lang.String, scala.Option<java.lang.String>, scala.Option<java.lang.Throwable>, scala.Option<java.lang.Object>, scala.Option<org.scalatest.events.Formatter>, scala.Option<org.scalatest.events.Location>, scala.Option<java.lang.String>, scala.Option<java.lang.Object>, java.lang.String, long);
    descriptor: (Lorg/scalatest/events/Ordinal;Ljava/lang/String;Ljava/lang/String;Ljava/lang/String;Lscala/Option;Lscala/Option;Lscala/Option;Lscala/Option;Lscala/Option;Lscala/Option;Lscala/Option;Ljava/lang/String;J)Lorg/scalatest/events/SuiteAborted;
    flags: (0x0009) ACC_PUBLIC, ACC_STATIC
    Code:
      stack=15, locals=14, args_size=13
         0: getstatic     #56                 // Field org/scalatest/events/SuiteAborted$.MODULE$:Lorg/scalatest/events/SuiteAborted$;
         3: aload_0
         4: aload_1
         5: aload_2
         6: aload_3
         7: aload         4
         9: aload         5
        11: aload         6
        13: aload         7
        15: aload         8
        17: aload         9
        19: aload         10
        21: aload         11
        23: lload         12
        25: invokevirtual #122                // Method org/scalatest/events/SuiteAborted$.apply:(Lorg/scalatest/events/Ordinal;Ljava/lang/String;Ljava/lang/String;Ljava/lang/String;Lscala/Option;Lscala/Option;Lscala/Option;Lscala/Option;Lscala/Option;Lscala/Option;Lscala/Option;Ljava/lang/String;J)Lorg/scalatest/events/SuiteAborted;
        28: areturn
      LocalVariableTable:
        Start  Length  Slot  Name   Signature
            0      29     0 ordinal   Lorg/scalatest/events/Ordinal;
            0      29     1 message   Ljava/lang/String;
            0      29     2 suiteName   Ljava/lang/String;
            0      29     3 suiteId   Ljava/lang/String;
            0      29     4 suiteClassName   Lscala/Option;
            0      29     5 throwable   Lscala/Option;
            0      29     6 duration   Lscala/Option;
            0      29     7 formatter   Lscala/Option;
            0      29     8 location   Lscala/Option;
            0      29     9 rerunner   Lscala/Option;
            0      29    10 payload   Lscala/Option;
            0      29    11 threadName   Ljava/lang/String;
            0      29    12 timeStamp   J
    Signature: #120                         // (Lorg/scalatest/events/Ordinal;Ljava/lang/String;Ljava/lang/String;Ljava/lang/String;Lscala/Option<Ljava/lang/String;>;Lscala/Option<Ljava/lang/Throwable;>;Lscala/Option<Ljava/lang/Object;>;Lscala/Option<Lorg/scalatest/events/Formatter;>;Lscala/Option<Lorg/scalatest/events/Location;>;Lscala/Option<Ljava/lang/String;>;Lscala/Option<Ljava/lang/Object;>;Ljava/lang/String;J)Lorg/scalatest/events/SuiteAborted;
    MethodParameters:
      Name                           Flags
      ordinal                        final
      message                        final
      suiteName                      final
      suiteId                        final
      suiteClassName                 final
      throwable                      final
      duration                       final
      formatter                      final
      location                       final
      rerunner                       final
      payload                        final
      threadName                     final
      timeStamp                      final

  public static scala.Function1<scala.Tuple13<org.scalatest.events.Ordinal, java.lang.String, java.lang.String, java.lang.String, scala.Option<java.lang.String>, scala.Option<java.lang.Throwable>, scala.Option<java.lang.Object>, scala.Option<org.scalatest.events.Formatter>, scala.Option<org.scalatest.events.Location>, scala.Option<java.lang.String>, scala.Option<java.lang.Object>, java.lang.String, java.lang.Object>, org.scalatest.events.SuiteAborted> tupled();
    descriptor: ()Lscala/Function1;
    flags: (0x0009) ACC_PUBLIC, ACC_STATIC
    Code:
      stack=1, locals=0, args_size=0
         0: getstatic     #56                 // Field org/scalatest/events/SuiteAborted$.MODULE$:Lorg/scalatest/events/SuiteAborted$;
         3: invokevirtual #127                // Method org/scalatest/events/SuiteAborted$.tupled:()Lscala/Function1;
         6: areturn
    Signature: #125                         // ()Lscala/Function1<Lscala/Tuple13<Lorg/scalatest/events/Ordinal;Ljava/lang/String;Ljava/lang/String;Ljava/lang/String;Lscala/Option<Ljava/lang/String;>;Lscala/Option<Ljava/lang/Throwable;>;Lscala/Option<Ljava/lang/Object;>;Lscala/Option<Lorg/scalatest/events/Formatter;>;Lscala/Option<Lorg/scalatest/events/Location;>;Lscala/Option<Ljava/lang/String;>;Lscala/Option<Ljava/lang/Object;>;Ljava/lang/String;Ljava/lang/Object;>;Lorg/scalatest/events/SuiteAborted;>;

  public static scala.Function1<org.scalatest.events.Ordinal, scala.Function1<java.lang.String, scala.Function1<java.lang.String, scala.Function1<java.lang.String, scala.Function1<scala.Option<java.lang.String>, scala.Function1<scala.Option<java.lang.Throwable>, scala.Function1<scala.Option<java.lang.Object>, scala.Function1<scala.Option<org.scalatest.events.Formatter>, scala.Function1<scala.Option<org.scalatest.events.Location>, scala.Function1<scala.Option<java.lang.String>, scala.Function1<scala.Option<java.lang.Object>, scala.Function1<java.lang.String, scala.Function1<java.lang.Object, org.scalatest.events.SuiteAborted>>>>>>>>>>>>> curried();
    descriptor: ()Lscala/Function1;
    flags: (0x0009) ACC_PUBLIC, ACC_STATIC
    Code:
      stack=1, locals=0, args_size=0
         0: getstatic     #56                 // Field org/scalatest/events/SuiteAborted$.MODULE$:Lorg/scalatest/events/SuiteAborted$;
         3: invokevirtual #131                // Method org/scalatest/events/SuiteAborted$.curried:()Lscala/Function1;
         6: areturn
    Signature: #129                         // ()Lscala/Function1<Lorg/scalatest/events/Ordinal;Lscala/Function1<Ljava/lang/String;Lscala/Function1<Ljava/lang/String;Lscala/Function1<Ljava/lang/String;Lscala/Function1<Lscala/Option<Ljava/lang/String;>;Lscala/Function1<Lscala/Option<Ljava/lang/Throwable;>;Lscala/Function1<Lscala/Option<Ljava/lang/Object;>;Lscala/Function1<Lscala/Option<Lorg/scalatest/events/Formatter;>;Lscala/Function1<Lscala/Option<Lorg/scalatest/events/Location;>;Lscala/Function1<Lscala/Option<Ljava/lang/String;>;Lscala/Function1<Lscala/Option<Ljava/lang/Object;>;Lscala/Function1<Ljava/lang/String;Lscala/Function1<Ljava/lang/Object;Lorg/scalatest/events/SuiteAborted;>;>;>;>;>;>;>;>;>;>;>;>;>;

  public org.scalatest.events.Ordinal ordinal();
    descriptor: ()Lorg/scalatest/events/Ordinal;
    flags: (0x0001) ACC_PUBLIC
    Code:
      stack=1, locals=1, args_size=1
         0: aload_0
         1: getfield      #134                // Field ordinal:Lorg/scalatest/events/Ordinal;
         4: areturn
      LineNumberTable:
        line 1233: 0
      LocalVariableTable:
        Start  Length  Slot  Name   Signature
            0       5     0  this   Lorg/scalatest/events/SuiteAborted;

  public java.lang.String message();
    descriptor: ()Ljava/lang/String;
    flags: (0x0001) ACC_PUBLIC
    Code:
      stack=1, locals=1, args_size=1
         0: aload_0
         1: getfield      #137                // Field message:Ljava/lang/String;
         4: areturn
      LineNumberTable:
        line 1234: 0
      LocalVariableTable:
        Start  Length  Slot  Name   Signature
            0       5     0  this   Lorg/scalatest/events/SuiteAborted;

  public java.lang.String suiteName();
    descriptor: ()Ljava/lang/String;
    flags: (0x0001) ACC_PUBLIC
    Code:
      stack=1, locals=1, args_size=1
         0: aload_0
         1: getfield      #139                // Field suiteName:Ljava/lang/String;
         4: areturn
      LineNumberTable:
        line 1235: 0
      LocalVariableTable:
        Start  Length  Slot  Name   Signature
            0       5     0  this   Lorg/scalatest/events/SuiteAborted;

  public java.lang.String suiteId();
    descriptor: ()Ljava/lang/String;
    flags: (0x0001) ACC_PUBLIC
    Code:
      stack=1, locals=1, args_size=1
         0: aload_0
         1: getfield      #141                // Field suiteId:Ljava/lang/String;
         4: areturn
      LineNumberTable:
        line 1236: 0
      LocalVariableTable:
        Start  Length  Slot  Name   Signature
            0       5     0  this   Lorg/scalatest/events/SuiteAborted;

  public scala.Option<java.lang.String> suiteClassName();
    descriptor: ()Lscala/Option;
    flags: (0x0001) ACC_PUBLIC
    Code:
      stack=1, locals=1, args_size=1
         0: aload_0
         1: getfield      #143                // Field suiteClassName:Lscala/Option;
         4: areturn
      LineNumberTable:
        line 1237: 0
      LocalVariableTable:
        Start  Length  Slot  Name   Signature
            0       5     0  this   Lorg/scalatest/events/SuiteAborted;
    Signature: #69                          // ()Lscala/Option<Ljava/lang/String;>;

  public scala.Option<java.lang.Throwable> throwable();
    descriptor: ()Lscala/Option;
    flags: (0x0001) ACC_PUBLIC
    Code:
      stack=1, locals=1, args_size=1
         0: aload_0
         1: getfield      #145                // Field throwable:Lscala/Option;
         4: areturn
      LineNumberTable:
        line 1238: 0
      LocalVariableTable:
        Start  Length  Slot  Name   Signature
            0       5     0  this   Lorg/scalatest/events/SuiteAborted;
    Signature: #84                          // ()Lscala/Option<Ljava/lang/Throwable;>;

  public scala.Option<java.lang.Object> duration();
    descriptor: ()Lscala/Option;
    flags: (0x0001) ACC_PUBLIC
    Code:
      stack=1, locals=1, args_size=1
         0: aload_0
         1: getfield      #147                // Field duration:Lscala/Option;
         4: areturn
      LineNumberTable:
        line 1239: 0
      LocalVariableTable:
        Start  Length  Slot  Name   Signature
            0       5     0  this   Lorg/scalatest/events/SuiteAborted;
    Signature: #65                          // ()Lscala/Option<Ljava/lang/Object;>;

  public scala.Option<org.scalatest.events.Formatter> formatter();
    descriptor: ()Lscala/Option;
    flags: (0x0001) ACC_PUBLIC
    Code:
      stack=1, locals=1, args_size=1
         0: aload_0
         1: getfield      #149                // Field formatter:Lscala/Option;
         4: areturn
      LineNumberTable:
        line 1240: 0
      LocalVariableTable:
        Start  Length  Slot  Name   Signature
            0       5     0  this   Lorg/scalatest/events/SuiteAborted;
    Signature: #77                          // ()Lscala/Option<Lorg/scalatest/events/Formatter;>;

  public scala.Option<org.scalatest.events.Location> location();
    descriptor: ()Lscala/Option;
    flags: (0x0001) ACC_PUBLIC
    Code:
      stack=1, locals=1, args_size=1
         0: aload_0
         1: getfield      #151                // Field location:Lscala/Option;
         4: areturn
      LineNumberTable:
        line 1241: 0
      LocalVariableTable:
        Start  Length  Slot  Name   Signature
            0       5     0  this   Lorg/scalatest/events/SuiteAborted;
    Signature: #73                          // ()Lscala/Option<Lorg/scalatest/events/Location;>;

  public scala.Option<java.lang.String> rerunner();
    descriptor: ()Lscala/Option;
    flags: (0x0001) ACC_PUBLIC
    Code:
      stack=1, locals=1, args_size=1
         0: aload_0
         1: getfield      #153                // Field rerunner:Lscala/Option;
         4: areturn
      LineNumberTable:
        line 1242: 0
      LocalVariableTable:
        Start  Length  Slot  Name   Signature
            0       5     0  this   Lorg/scalatest/events/SuiteAborted;
    Signature: #69                          // ()Lscala/Option<Ljava/lang/String;>;

  public scala.Option<java.lang.Object> payload();
    descriptor: ()Lscala/Option;
    flags: (0x0001) ACC_PUBLIC
    Code:
      stack=1, locals=1, args_size=1
         0: aload_0
         1: getfield      #155                // Field payload:Lscala/Option;
         4: areturn
      LineNumberTable:
        line 1243: 0
      LocalVariableTable:
        Start  Length  Slot  Name   Signature
            0       5     0  this   Lorg/scalatest/events/SuiteAborted;
    Signature: #65                          // ()Lscala/Option<Ljava/lang/Object;>;

  public java.lang.String threadName();
    descriptor: ()Ljava/lang/String;
    flags: (0x0001) ACC_PUBLIC
    Code:
      stack=1, locals=1, args_size=1
         0: aload_0
         1: getfield      #157                // Field threadName:Ljava/lang/String;
         4: areturn
      LineNumberTable:
        line 1244: 0
      LocalVariableTable:
        Start  Length  Slot  Name   Signature
            0       5     0  this   Lorg/scalatest/events/SuiteAborted;

  public long timeStamp();
    descriptor: ()J
    flags: (0x0001) ACC_PUBLIC
    Code:
      stack=2, locals=1, args_size=1
         0: aload_0
         1: getfield      #159                // Field timeStamp:J
         4: lreturn
      LineNumberTable:
        line 1245: 0
      LocalVariableTable:
        Start  Length  Slot  Name   Signature
            0       5     0  this   Lorg/scalatest/events/SuiteAborted;

  public scala.xml.Elem toXml();
    descriptor: ()Lscala/xml/Elem;
    flags: (0x0001) ACC_PUBLIC
    Code:
      stack=28, locals=15, args_size=1
         0: new           #163                // class scala/xml/Elem
         3: dup
         4: aconst_null
         5: ldc           #165                // String SuiteAborted
         7: getstatic     #170                // Field scala/xml/Null$.MODULE$:Lscala/xml/Null$;
        10: getstatic     #175                // Field scala/xml/TopScope$.MODULE$:Lscala/xml/TopScope$;
        13: iconst_0
        14: getstatic     #180                // Field scala/xml/NodeSeq$.MODULE$:Lscala/xml/NodeSeq$;
        17: new           #182                // class scala/xml/NodeBuffer
        20: dup
        21: invokespecial #186                // Method scala/xml/NodeBuffer."<init>":()V
        24: astore_1
        25: aload_1
        26: new           #188                // class scala/xml/Text
        29: dup
        30: ldc           #190                // String \n
        32: invokespecial #193                // Method scala/xml/Text."<init>":(Ljava/lang/String;)V
        35: invokevirtual #197                // Method scala/xml/NodeBuffer.$amp$plus:(Ljava/lang/Object;)Lscala/xml/NodeBuffer;
        38: pop
        39: aload_1
        40: new           #163                // class scala/xml/Elem
        43: dup
        44: aconst_null
        45: ldc           #198                // String ordinal
        47: getstatic     #170                // Field scala/xml/Null$.MODULE$:Lscala/xml/Null$;
        50: getstatic     #175                // Field scala/xml/TopScope$.MODULE$:Lscala/xml/TopScope$;
        53: iconst_0
        54: getstatic     #180                // Field scala/xml/NodeSeq$.MODULE$:Lscala/xml/NodeSeq$;
        57: new           #182                // class scala/xml/NodeBuffer
        60: dup
        61: invokespecial #186                // Method scala/xml/NodeBuffer."<init>":()V
        64: astore_2
        65: aload_2
        66: new           #188                // class scala/xml/Text
        69: dup
        70: ldc           #200                // String \n
        72: invokespecial #193                // Method scala/xml/Text."<init>":(Ljava/lang/String;)V
        75: invokevirtual #197                // Method scala/xml/NodeBuffer.$amp$plus:(Ljava/lang/Object;)Lscala/xml/NodeBuffer;
        78: pop
        79: aload_2
        80: new           #163                // class scala/xml/Elem
        83: dup
        84: aconst_null
        85: ldc           #202                // String runStamp
        87: getstatic     #170                // Field scala/xml/Null$.MODULE$:Lscala/xml/Null$;
        90: getstatic     #175                // Field scala/xml/TopScope$.MODULE$:Lscala/xml/TopScope$;
        93: iconst_0
        94: getstatic     #180                // Field scala/xml/NodeSeq$.MODULE$:Lscala/xml/NodeSeq$;
        97: new           #182                // class scala/xml/NodeBuffer
       100: dup
       101: invokespecial #186                // Method scala/xml/NodeBuffer."<init>":()V
       104: astore_3
       105: aload_3
       106: aload_0
       107: invokevirtual #204                // Method ordinal:()Lorg/scalatest/events/Ordinal;
       110: invokevirtual #209                // Method org/scalatest/events/Ordinal.runStamp:()I
       113: invokestatic  #215                // Method scala/runtime/BoxesRunTime.boxToInteger:(I)Ljava/lang/Integer;
       116: invokevirtual #197                // Method scala/xml/NodeBuffer.$amp$plus:(Ljava/lang/Object;)Lscala/xml/NodeBuffer;
       119: pop
       120: aload_3
       121: invokevirtual #219                // Method scala/xml/NodeSeq$.seqToNodeSeq:(Lscala/collection/Seq;)Lscala/xml/NodeSeq;
       124: invokespecial #222                // Method scala/xml/Elem."<init>":(Ljava/lang/String;Ljava/lang/String;Lscala/xml/MetaData;Lscala/xml/NamespaceBinding;ZLscala/collection/immutable/Seq;)V
       127: invokevirtual #197                // Method scala/xml/NodeBuffer.$amp$plus:(Ljava/lang/Object;)Lscala/xml/NodeBuffer;
       130: pop
       131: aload_2
       132: new           #188                // class scala/xml/Text
       135: dup
       136: ldc           #190                // String \n
       138: invokespecial #193                // Method scala/xml/Text."<init>":(Ljava/lang/String;)V
       141: invokevirtual #197                // Method scala/xml/NodeBuffer.$amp$plus:(Ljava/lang/Object;)Lscala/xml/NodeBuffer;
       144: pop
       145: aload_2
       146: invokevirtual #219                // Method scala/xml/NodeSeq$.seqToNodeSeq:(Lscala/collection/Seq;)Lscala/xml/NodeSeq;
       149: invokespecial #222                // Method scala/xml/Elem."<init>":(Ljava/lang/String;Ljava/lang/String;Lscala/xml/MetaData;Lscala/xml/NamespaceBinding;ZLscala/collection/immutable/Seq;)V
       152: invokevirtual #197                // Method scala/xml/NodeBuffer.$amp$plus:(Ljava/lang/Object;)Lscala/xml/NodeBuffer;
       155: pop
       156: aload_1
       157: new           #188                // class scala/xml/Text
       160: dup
       161: ldc           #190                // String \n
       163: invokespecial #193                // Method scala/xml/Text."<init>":(Ljava/lang/String;)V
       166: invokevirtual #197                // Method scala/xml/NodeBuffer.$amp$plus:(Ljava/lang/Object;)Lscala/xml/NodeBuffer;
       169: pop
       170: aload_1
       171: new           #163                // class scala/xml/Elem
       174: dup
       175: aconst_null
       176: ldc           #223                // String message
       178: getstatic     #170                // Field scala/xml/Null$.MODULE$:Lscala/xml/Null$;
       181: getstatic     #175                // Field scala/xml/TopScope$.MODULE$:Lscala/xml/TopScope$;
       184: iconst_0
       185: getstatic     #180                // Field scala/xml/NodeSeq$.MODULE$:Lscala/xml/NodeSeq$;
       188: new           #182                // class scala/xml/NodeBuffer
       191: dup
       192: invokespecial #186                // Method scala/xml/NodeBuffer."<init>":()V
       195: astore        4
       197: aload         4
       199: aload_0
       200: invokevirtual #225                // Method message:()Ljava/lang/String;
       203: invokevirtual #197                // Method scala/xml/NodeBuffer.$amp$plus:(Ljava/lang/Object;)Lscala/xml/NodeBuffer;
       206: pop
       207: aload         4
       209: invokevirtual #219                // Method scala/xml/NodeSeq$.seqToNodeSeq:(Lscala/collection/Seq;)Lscala/xml/NodeSeq;
       212: invokespecial #222                // Method scala/xml/Elem."<init>":(Ljava/lang/String;Ljava/lang/String;Lscala/xml/MetaData;Lscala/xml/NamespaceBinding;ZLscala/collection/immutable/Seq;)V
       215: invokevirtual #197                // Method scala/xml/NodeBuffer.$amp$plus:(Ljava/lang/Object;)Lscala/xml/NodeBuffer;
       218: pop
       219: aload_1
       220: new           #188                // class scala/xml/Text
       223: dup
       224: ldc           #190                // String \n
       226: invokespecial #193                // Method scala/xml/Text."<init>":(Ljava/lang/String;)V
       229: invokevirtual #197                // Method scala/xml/NodeBuffer.$amp$plus:(Ljava/lang/Object;)Lscala/xml/NodeBuffer;
       232: pop
       233: aload_1
       234: new           #163                // class scala/xml/Elem
       237: dup
       238: aconst_null
       239: ldc           #226                // String suiteName
       241: getstatic     #170                // Field scala/xml/Null$.MODULE$:Lscala/xml/Null$;
       244: getstatic     #175                // Field scala/xml/TopScope$.MODULE$:Lscala/xml/TopScope$;
       247: iconst_0
       248: getstatic     #180                // Field scala/xml/NodeSeq$.MODULE$:Lscala/xml/NodeSeq$;
       251: new           #182                // class scala/xml/NodeBuffer
       254: dup
       255: invokespecial #186                // Method scala/xml/NodeBuffer."<init>":()V
       258: astore        5
       260: aload         5
       262: aload_0
       263: invokevirtual #228                // Method suiteName:()Ljava/lang/String;
       266: invokevirtual #197                // Method scala/xml/NodeBuffer.$amp$plus:(Ljava/lang/Object;)Lscala/xml/NodeBuffer;
       269: pop
       270: aload         5
       272: invokevirtual #219                // Method scala/xml/NodeSeq$.seqToNodeSeq:(Lscala/collection/Seq;)Lscala/xml/NodeSeq;
       275: invokespecial #222                // Method scala/xml/Elem."<init>":(Ljava/lang/String;Ljava/lang/String;Lscala/xml/MetaData;Lscala/xml/NamespaceBinding;ZLscala/collection/immutable/Seq;)V
       278: invokevirtual #197                // Method scala/xml/NodeBuffer.$amp$plus:(Ljava/lang/Object;)Lscala/xml/NodeBuffer;
       281: pop
       282: aload_1
       283: new           #188                // class scala/xml/Text
       286: dup
       287: ldc           #190                // String \n
       289: invokespecial #193                // Method scala/xml/Text."<init>":(Ljava/lang/String;)V
       292: invokevirtual #197                // Method scala/xml/NodeBuffer.$amp$plus:(Ljava/lang/Object;)Lscala/xml/NodeBuffer;
       295: pop
       296: aload_1
       297: new           #163                // class scala/xml/Elem
       300: dup
       301: aconst_null
       302: ldc           #229                // String suiteId
       304: getstatic     #170                // Field scala/xml/Null$.MODULE$:Lscala/xml/Null$;
       307: getstatic     #175                // Field scala/xml/TopScope$.MODULE$:Lscala/xml/TopScope$;
       310: iconst_0
       311: getstatic     #180                // Field scala/xml/NodeSeq$.MODULE$:Lscala/xml/NodeSeq$;
       314: new           #182                // class scala/xml/NodeBuffer
       317: dup
       318: invokespecial #186                // Method scala/xml/NodeBuffer."<init>":()V
       321: astore        6
       323: aload         6
       325: aload_0
       326: invokevirtual #231                // Method suiteId:()Ljava/lang/String;
       329: invokevirtual #197                // Method scala/xml/NodeBuffer.$amp$plus:(Ljava/lang/Object;)Lscala/xml/NodeBuffer;
       332: pop
       333: aload         6
       335: invokevirtual #219                // Method scala/xml/NodeSeq$.seqToNodeSeq:(Lscala/collection/Seq;)Lscala/xml/NodeSeq;
       338: invokespecial #222                // Method scala/xml/Elem."<init>":(Ljava/lang/String;Ljava/lang/String;Lscala/xml/MetaData;Lscala/xml/NamespaceBinding;ZLscala/collection/immutable/Seq;)V
       341: invokevirtual #197                // Method scala/xml/NodeBuffer.$amp$plus:(Ljava/lang/Object;)Lscala/xml/NodeBuffer;
       344: pop
       345: aload_1
       346: new           #188                // class scala/xml/Text
       349: dup
       350: ldc           #190                // String \n
       352: invokespecial #193                // Method scala/xml/Text."<init>":(Ljava/lang/String;)V
       355: invokevirtual #197                // Method scala/xml/NodeBuffer.$amp$plus:(Ljava/lang/Object;)Lscala/xml/NodeBuffer;
       358: pop
       359: aload_1
       360: new           #163                // class scala/xml/Elem
       363: dup
       364: aconst_null
       365: ldc           #232                // String suiteClassName
       367: getstatic     #170                // Field scala/xml/Null$.MODULE$:Lscala/xml/Null$;
       370: getstatic     #175                // Field scala/xml/TopScope$.MODULE$:Lscala/xml/TopScope$;
       373: iconst_0
       374: getstatic     #180                // Field scala/xml/NodeSeq$.MODULE$:Lscala/xml/NodeSeq$;
       377: new           #182                // class scala/xml/NodeBuffer
       380: dup
       381: invokespecial #186                // Method scala/xml/NodeBuffer."<init>":()V
       384: astore        7
       386: aload         7
       388: aload_0
       389: invokevirtual #236                // Method EventXmlHelper:()Lorg/scalatest/events/Event$EventXmlHelper$;
       392: aload_0
       393: invokevirtual #238                // Method suiteClassName:()Lscala/Option;
       396: invokevirtual #242                // Method org/scalatest/events/Event$EventXmlHelper$.stringOption:(Lscala/Option;)Ljava/lang/String;
       399: invokevirtual #197                // Method scala/xml/NodeBuffer.$amp$plus:(Ljava/lang/Object;)Lscala/xml/NodeBuffer;
       402: pop
       403: aload         7
       405: invokevirtual #219                // Method scala/xml/NodeSeq$.seqToNodeSeq:(Lscala/collection/Seq;)Lscala/xml/NodeSeq;
       408: invokespecial #222                // Method scala/xml/Elem."<init>":(Ljava/lang/String;Ljava/lang/String;Lscala/xml/MetaData;Lscala/xml/NamespaceBinding;ZLscala/collection/immutable/Seq;)V
       411: invokevirtual #197                // Method scala/xml/NodeBuffer.$amp$plus:(Ljava/lang/Object;)Lscala/xml/NodeBuffer;
       414: pop
       415: aload_1
       416: new           #188                // class scala/xml/Text
       419: dup
       420: ldc           #190                // String \n
       422: invokespecial #193                // Method scala/xml/Text."<init>":(Ljava/lang/String;)V
       425: invokevirtual #197                // Method scala/xml/NodeBuffer.$amp$plus:(Ljava/lang/Object;)Lscala/xml/NodeBuffer;
       428: pop
       429: aload_1
       430: new           #163                // class scala/xml/Elem
       433: dup
       434: aconst_null
       435: ldc           #243                // String duration
       437: getstatic     #170                // Field scala/xml/Null$.MODULE$:Lscala/xml/Null$;
       440: getstatic     #175                // Field scala/xml/TopScope$.MODULE$:Lscala/xml/TopScope$;
       443: iconst_0
       444: getstatic     #180                // Field scala/xml/NodeSeq$.MODULE$:Lscala/xml/NodeSeq$;
       447: new           #182                // class scala/xml/NodeBuffer
       450: dup
       451: invokespecial #186                // Method scala/xml/NodeBuffer."<init>":()V
       454: astore        8
       456: aload         8
       458: aload_0
       459: invokevirtual #236                // Method EventXmlHelper:()Lorg/scalatest/events/Event$EventXmlHelper$;
       462: aload_0
       463: invokevirtual #245                // Method duration:()Lscala/Option;
       466: invokevirtual #248                // Method org/scalatest/events/Event$EventXmlHelper$.longOption:(Lscala/Option;)Ljava/lang/String;
       469: invokevirtual #197                // Method scala/xml/NodeBuffer.$amp$plus:(Ljava/lang/Object;)Lscala/xml/NodeBuffer;
       472: pop
       473: aload         8
       475: invokevirtual #219                // Method scala/xml/NodeSeq$.seqToNodeSeq:(Lscala/collection/Seq;)Lscala/xml/NodeSeq;
       478: invokespecial #222                // Method scala/xml/Elem."<init>":(Ljava/lang/String;Ljava/lang/String;Lscala/xml/MetaData;Lscala/xml/NamespaceBinding;ZLscala/collection/immutable/Seq;)V
       481: invokevirtual #197                // Method scala/xml/NodeBuffer.$amp$plus:(Ljava/lang/Object;)Lscala/xml/NodeBuffer;
       484: pop
       485: aload_1
       486: new           #188                // class scala/xml/Text
       489: dup
       490: ldc           #190                // String \n
       492: invokespecial #193                // Method scala/xml/Text."<init>":(Ljava/lang/String;)V
       495: invokevirtual #197                // Method scala/xml/NodeBuffer.$amp$plus:(Ljava/lang/Object;)Lscala/xml/NodeBuffer;
       498: pop
       499: aload_1
       500: new           #163                // class scala/xml/Elem
       503: dup
       504: aconst_null
       505: ldc           #249                // String throwable
       507: getstatic     #170                // Field scala/xml/Null$.MODULE$:Lscala/xml/Null$;
       510: getstatic     #175                // Field scala/xml/TopScope$.MODULE$:Lscala/xml/TopScope$;
       513: iconst_0
       514: getstatic     #180                // Field scala/xml/NodeSeq$.MODULE$:Lscala/xml/NodeSeq$;
       517: new           #182                // class scala/xml/NodeBuffer
       520: dup
       521: invokespecial #186                // Method scala/xml/NodeBuffer."<init>":()V
       524: astore        9
       526: aload         9
       528: aload_0
       529: invokevirtual #236                // Method EventXmlHelper:()Lorg/scalatest/events/Event$EventXmlHelper$;
       532: aload_0
       533: invokevirtual #251                // Method throwable:()Lscala/Option;
       536: invokevirtual #255                // Method org/scalatest/events/Event$EventXmlHelper$.throwableOption:(Lscala/Option;)Ljava/lang/Object;
       539: invokevirtual #197                // Method scala/xml/NodeBuffer.$amp$plus:(Ljava/lang/Object;)Lscala/xml/NodeBuffer;
       542: pop
       543: aload         9
       545: invokevirtual #219                // Method scala/xml/NodeSeq$.seqToNodeSeq:(Lscala/collection/Seq;)Lscala/xml/NodeSeq;
       548: invokespecial #222                // Method scala/xml/Elem."<init>":(Ljava/lang/String;Ljava/lang/String;Lscala/xml/MetaData;Lscala/xml/NamespaceBinding;ZLscala/collection/immutable/Seq;)V
       551: invokevirtual #197                // Method scala/xml/NodeBuffer.$amp$plus:(Ljava/lang/Object;)Lscala/xml/NodeBuffer;
       554: pop
       555: aload_1
       556: new           #188                // class scala/xml/Text
       559: dup
       560: ldc           #190                // String \n
       562: invokespecial #193                // Method scala/xml/Text."<init>":(Ljava/lang/String;)V
       565: invokevirtual #197                // Method scala/xml/NodeBuffer.$amp$plus:(Ljava/lang/Object;)Lscala/xml/NodeBuffer;
       568: pop
       569: aload_1
       570: new           #163                // class scala/xml/Elem
       573: dup
       574: aconst_null
       575: ldc_w         #256                // String formatter
       578: getstatic     #170                // Field scala/xml/Null$.MODULE$:Lscala/xml/Null$;
       581: getstatic     #175                // Field scala/xml/TopScope$.MODULE$:Lscala/xml/TopScope$;
       584: iconst_0
       585: getstatic     #180                // Field scala/xml/NodeSeq$.MODULE$:Lscala/xml/NodeSeq$;
       588: new           #182                // class scala/xml/NodeBuffer
       591: dup
       592: invokespecial #186                // Method scala/xml/NodeBuffer."<init>":()V
       595: astore        10
       597: aload         10
       599: aload_0
       600: invokevirtual #236                // Method EventXmlHelper:()Lorg/scalatest/events/Event$EventXmlHelper$;
       603: aload_0
       604: invokevirtual #258                // Method formatter:()Lscala/Option;
       607: invokevirtual #261                // Method org/scalatest/events/Event$EventXmlHelper$.formatterOption:(Lscala/Option;)Ljava/lang/Object;
       610: invokevirtual #197                // Method scala/xml/NodeBuffer.$amp$plus:(Ljava/lang/Object;)Lscala/xml/NodeBuffer;
       613: pop
       614: aload         10
       616: invokevirtual #219                // Method scala/xml/NodeSeq$.seqToNodeSeq:(Lscala/collection/Seq;)Lscala/xml/NodeSeq;
       619: invokespecial #222                // Method scala/xml/Elem."<init>":(Ljava/lang/String;Ljava/lang/String;Lscala/xml/MetaData;Lscala/xml/NamespaceBinding;ZLscala/collection/immutable/Seq;)V
       622: invokevirtual #197                // Method scala/xml/NodeBuffer.$amp$plus:(Ljava/lang/Object;)Lscala/xml/NodeBuffer;
       625: pop
       626: aload_1
       627: new           #188                // class scala/xml/Text
       630: dup
       631: ldc           #190                // String \n
       633: invokespecial #193                // Method scala/xml/Text."<init>":(Ljava/lang/String;)V
       636: invokevirtual #197                // Method scala/xml/NodeBuffer.$amp$plus:(Ljava/lang/Object;)Lscala/xml/NodeBuffer;
       639: pop
       640: aload_1
       641: new           #163                // class scala/xml/Elem
       644: dup
       645: aconst_null
       646: ldc_w         #262                // String location
       649: getstatic     #170                // Field scala/xml/Null$.MODULE$:Lscala/xml/Null$;
       652: getstatic     #175                // Field scala/xml/TopScope$.MODULE$:Lscala/xml/TopScope$;
       655: iconst_0
       656: getstatic     #180                // Field scala/xml/NodeSeq$.MODULE$:Lscala/xml/NodeSeq$;
       659: new           #182                // class scala/xml/NodeBuffer
       662: dup
       663: invokespecial #186                // Method scala/xml/NodeBuffer."<init>":()V
       666: astore        11
       668: aload         11
       670: aload_0
       671: invokevirtual #236                // Method EventXmlHelper:()Lorg/scalatest/events/Event$EventXmlHelper$;
       674: aload_0
       675: invokevirtual #264                // Method location:()Lscala/Option;
       678: invokevirtual #267                // Method org/scalatest/events/Event$EventXmlHelper$.locationOption:(Lscala/Option;)Ljava/lang/Object;
       681: invokevirtual #197                // Method scala/xml/NodeBuffer.$amp$plus:(Ljava/lang/Object;)Lscala/xml/NodeBuffer;
       684: pop
       685: aload         11
       687: invokevirtual #219                // Method scala/xml/NodeSeq$.seqToNodeSeq:(Lscala/collection/Seq;)Lscala/xml/NodeSeq;
       690: invokespecial #222                // Method scala/xml/Elem."<init>":(Ljava/lang/String;Ljava/lang/String;Lscala/xml/MetaData;Lscala/xml/NamespaceBinding;ZLscala/collection/immutable/Seq;)V
       693: invokevirtual #197                // Method scala/xml/NodeBuffer.$amp$plus:(Ljava/lang/Object;)Lscala/xml/NodeBuffer;
       696: pop
       697: aload_1
       698: new           #188                // class scala/xml/Text
       701: dup
       702: ldc           #190                // String \n
       704: invokespecial #193                // Method scala/xml/Text."<init>":(Ljava/lang/String;)V
       707: invokevirtual #197                // Method scala/xml/NodeBuffer.$amp$plus:(Ljava/lang/Object;)Lscala/xml/NodeBuffer;
       710: pop
       711: aload_1
       712: new           #163                // class scala/xml/Elem
       715: dup
       716: aconst_null
       717: ldc_w         #268                // String rerunner
       720: getstatic     #170                // Field scala/xml/Null$.MODULE$:Lscala/xml/Null$;
       723: getstatic     #175                // Field scala/xml/TopScope$.MODULE$:Lscala/xml/TopScope$;
       726: iconst_0
       727: getstatic     #180                // Field scala/xml/NodeSeq$.MODULE$:Lscala/xml/NodeSeq$;
       730: new           #182                // class scala/xml/NodeBuffer
       733: dup
       734: invokespecial #186                // Method scala/xml/NodeBuffer."<init>":()V
       737: astore        12
       739: aload         12
       741: aload_0
       742: invokevirtual #236                // Method EventXmlHelper:()Lorg/scalatest/events/Event$EventXmlHelper$;
       745: aload_0
       746: invokevirtual #270                // Method rerunner:()Lscala/Option;
       749: invokevirtual #242                // Method org/scalatest/events/Event$EventXmlHelper$.stringOption:(Lscala/Option;)Ljava/lang/String;
       752: invokevirtual #197                // Method scala/xml/NodeBuffer.$amp$plus:(Ljava/lang/Object;)Lscala/xml/NodeBuffer;
       755: pop
       756: aload         12
       758: invokevirtual #219                // Method scala/xml/NodeSeq$.seqToNodeSeq:(Lscala/collection/Seq;)Lscala/xml/NodeSeq;
       761: invokespecial #222                // Method scala/xml/Elem."<init>":(Ljava/lang/String;Ljava/lang/String;Lscala/xml/MetaData;Lscala/xml/NamespaceBinding;ZLscala/collection/immutable/Seq;)V
       764: invokevirtual #197                // Method scala/xml/NodeBuffer.$amp$plus:(Ljava/lang/Object;)Lscala/xml/NodeBuffer;
       767: pop
       768: aload_1
       769: new           #188                // class scala/xml/Text
       772: dup
       773: ldc           #190                // String \n
       775: invokespecial #193                // Method scala/xml/Text."<init>":(Ljava/lang/String;)V
       778: invokevirtual #197                // Method scala/xml/NodeBuffer.$amp$plus:(Ljava/lang/Object;)Lscala/xml/NodeBuffer;
       781: pop
       782: aload_1
       783: new           #163                // class scala/xml/Elem
       786: dup
       787: aconst_null
       788: ldc_w         #271                // String threadName
       791: getstatic     #170                // Field scala/xml/Null$.MODULE$:Lscala/xml/Null$;
       794: getstatic     #175                // Field scala/xml/TopScope$.MODULE$:Lscala/xml/TopScope$;
       797: iconst_0
       798: getstatic     #180                // Field scala/xml/NodeSeq$.MODULE$:Lscala/xml/NodeSeq$;
       801: new           #182                // class scala/xml/NodeBuffer
       804: dup
       805: invokespecial #186                // Method scala/xml/NodeBuffer."<init>":()V
       808: astore        13
       810: aload         13
       812: aload_0
       813: invokevirtual #273                // Method threadName:()Ljava/lang/String;
       816: invokevirtual #197                // Method scala/xml/NodeBuffer.$amp$plus:(Ljava/lang/Object;)Lscala/xml/NodeBuffer;
       819: pop
       820: aload         13
       822: invokevirtual #219                // Method scala/xml/NodeSeq$.seqToNodeSeq:(Lscala/collection/Seq;)Lscala/xml/NodeSeq;
       825: invokespecial #222                // Method scala/xml/Elem."<init>":(Ljava/lang/String;Ljava/lang/String;Lscala/xml/MetaData;Lscala/xml/NamespaceBinding;ZLscala/collection/immutable/Seq;)V
       828: invokevirtual #197                // Method scala/xml/NodeBuffer.$amp$plus:(Ljava/lang/Object;)Lscala/xml/NodeBuffer;
       831: pop
       832: aload_1
       833: new           #188                // class scala/xml/Text
       836: dup
       837: ldc           #190                // String \n
       839: invokespecial #193                // Method scala/xml/Text."<init>":(Ljava/lang/String;)V
       842: invokevirtual #197                // Method scala/xml/NodeBuffer.$amp$plus:(Ljava/lang/Object;)Lscala/xml/NodeBuffer;
       845: pop
       846: aload_1
       847: new           #163                // class scala/xml/Elem
       850: dup
       851: aconst_null
       852: ldc_w         #274                // String timeStamp
       855: getstatic     #170                // Field scala/xml/Null$.MODULE$:Lscala/xml/Null$;
       858: getstatic     #175                // Field scala/xml/TopScope$.MODULE$:Lscala/xml/TopScope$;
       861: iconst_0
       862: getstatic     #180                // Field scala/xml/NodeSeq$.MODULE$:Lscala/xml/NodeSeq$;
       865: new           #182                // class scala/xml/NodeBuffer
       868: dup
       869: invokespecial #186                // Method scala/xml/NodeBuffer."<init>":()V
       872: astore        14
       874: aload         14
       876: aload_0
       877: invokevirtual #276                // Method timeStamp:()J
       880: invokestatic  #280                // Method scala/runtime/BoxesRunTime.boxToLong:(J)Ljava/lang/Long;
       883: invokevirtual #197                // Method scala/xml/NodeBuffer.$amp$plus:(Ljava/lang/Object;)Lscala/xml/NodeBuffer;
       886: pop
       887: aload         14
       889: invokevirtual #219                // Method scala/xml/NodeSeq$.seqToNodeSeq:(Lscala/collection/Seq;)Lscala/xml/NodeSeq;
       892: invokespecial #222                // Method scala/xml/Elem."<init>":(Ljava/lang/String;Ljava/lang/String;Lscala/xml/MetaData;Lscala/xml/NamespaceBinding;ZLscala/collection/immutable/Seq;)V
       895: invokevirtual #197                // Method scala/xml/NodeBuffer.$amp$plus:(Ljava/lang/Object;)Lscala/xml/NodeBuffer;
       898: pop
       899: aload_1
       900: new           #188                // class scala/xml/Text
       903: dup
       904: ldc_w         #282                // String \n
       907: invokespecial #193                // Method scala/xml/Text."<init>":(Ljava/lang/String;)V
       910: invokevirtual #197                // Method scala/xml/NodeBuffer.$amp$plus:(Ljava/lang/Object;)Lscala/xml/NodeBuffer;
       913: pop
       914: aload_1
       915: invokevirtual #219                // Method scala/xml/NodeSeq$.seqToNodeSeq:(Lscala/collection/Seq;)Lscala/xml/NodeSeq;
       918: invokespecial #222                // Method scala/xml/Elem."<init>":(Ljava/lang/String;Ljava/lang/String;Lscala/xml/MetaData;Lscala/xml/NamespaceBinding;ZLscala/collection/immutable/Seq;)V
       921: areturn
      LineNumberTable:
        line 1264: 0
        line 1265: 40
        line 1266: 80
        line 1265: 131
        line 1266: 132
        line 1265: 145
        line 1264: 156
        line 1267: 157
        line 1264: 170
        line 1268: 171
        line 1264: 219
        line 1268: 220
        line 1264: 233
        line 1269: 234
        line 1264: 282
        line 1269: 283
        line 1264: 296
        line 1270: 297
        line 1264: 345
        line 1270: 346
        line 1264: 359
        line 1271: 360
        line 1264: 415
        line 1271: 416
        line 1264: 429
        line 1272: 430
        line 1264: 485
        line 1272: 486
        line 1264: 499
        line 1273: 500
        line 1264: 555
        line 1273: 556
        line 1264: 569
        line 1274: 570
        line 1264: 626
        line 1274: 627
        line 1264: 640
        line 1275: 641
        line 1264: 697
        line 1275: 698
        line 1264: 711
        line 1276: 712
        line 1264: 768
        line 1276: 769
        line 1264: 782
        line 1277: 783
        line 1264: 832
        line 1277: 833
        line 1264: 846
        line 1278: 847
        line 1264: 899
        line 1278: 900
        line 1264: 914
      LocalVariableTable:
        Start  Length  Slot  Name   Signature
          105      16     3  $buf   Lscala/xml/NodeBuffer;
           65      81     2  $buf   Lscala/xml/NodeBuffer;
          197      12     4  $buf   Lscala/xml/NodeBuffer;
          260      12     5  $buf   Lscala/xml/NodeBuffer;
          323      12     6  $buf   Lscala/xml/NodeBuffer;
          386      19     7  $buf   Lscala/xml/NodeBuffer;
          456      19     8  $buf   Lscala/xml/NodeBuffer;
          526      19     9  $buf   Lscala/xml/NodeBuffer;
          597      19    10  $buf   Lscala/xml/NodeBuffer;
          668      19    11  $buf   Lscala/xml/NodeBuffer;
          739      19    12  $buf   Lscala/xml/NodeBuffer;
          810      12    13  $buf   Lscala/xml/NodeBuffer;
          874      15    14  $buf   Lscala/xml/NodeBuffer;
           25     890     1  $buf   Lscala/xml/NodeBuffer;
            0     922     0  this   Lorg/scalatest/events/SuiteAborted;

  public java.lang.String toJson();
    descriptor: ()Ljava/lang/String;
    flags: (0x0001) ACC_PUBLIC
    Code:
      stack=5, locals=1, args_size=1
         0: getstatic     #290                // Field scala/collection/StringOps$.MODULE$:Lscala/collection/StringOps$;
         3: getstatic     #295                // Field scala/Predef$.MODULE$:Lscala/Predef$;
         6: new           #297                // class java/lang/StringBuilder
         9: dup
        10: ldc_w         #298                // int 208
        13: invokespecial #301                // Method java/lang/StringBuilder."<init>":(I)V
        16: ldc_w         #303                // String { \"eventType\": \"SuiteAborted\", \"ordinal\":
        19: invokevirtual #307                // Method java/lang/StringBuilder.append:(Ljava/lang/String;)Ljava/lang/StringBuilder;
        22: aload_0
        23: invokevirtual #204                // Method ordinal:()Lorg/scalatest/events/Ordinal;
        26: invokevirtual #209                // Method org/scalatest/events/Ordinal.runStamp:()I
        29: invokevirtual #310                // Method java/lang/StringBuilder.append:(I)Ljava/lang/StringBuilder;
        32: ldc_w         #312                // String , \"message\":
        35: invokevirtual #307                // Method java/lang/StringBuilder.append:(Ljava/lang/String;)Ljava/lang/StringBuilder;
        38: aload_0
        39: invokevirtual #316                // Method EventJsonHelper:()Lorg/scalatest/events/Event$EventJsonHelper$;
        42: aload_0
        43: invokevirtual #225                // Method message:()Ljava/lang/String;
        46: invokevirtual #320                // Method org/scalatest/events/Event$EventJsonHelper$.string:(Ljava/lang/String;)Ljava/lang/String;
        49: invokevirtual #307                // Method java/lang/StringBuilder.append:(Ljava/lang/String;)Ljava/lang/StringBuilder;
        52: ldc_w         #322                // String , \"suiteName\":
        55: invokevirtual #307                // Method java/lang/StringBuilder.append:(Ljava/lang/String;)Ljava/lang/StringBuilder;
        58: aload_0
        59: invokevirtual #316                // Method EventJsonHelper:()Lorg/scalatest/events/Event$EventJsonHelper$;
        62: aload_0
        63: invokevirtual #228                // Method suiteName:()Ljava/lang/String;
        66: invokevirtual #320                // Method org/scalatest/events/Event$EventJsonHelper$.string:(Ljava/lang/String;)Ljava/lang/String;
        69: invokevirtual #307                // Method java/lang/StringBuilder.append:(Ljava/lang/String;)Ljava/lang/StringBuilder;
        72: ldc_w         #324                // String , \"suiteId\":
        75: invokevirtual #307                // Method java/lang/StringBuilder.append:(Ljava/lang/String;)Ljava/lang/StringBuilder;
        78: aload_0
        79: invokevirtual #316                // Method EventJsonHelper:()Lorg/scalatest/events/Event$EventJsonHelper$;
        82: aload_0
        83: invokevirtual #231                // Method suiteId:()Ljava/lang/String;
        86: invokevirtual #320                // Method org/scalatest/events/Event$EventJsonHelper$.string:(Ljava/lang/String;)Ljava/lang/String;
        89: invokevirtual #307                // Method java/lang/StringBuilder.append:(Ljava/lang/String;)Ljava/lang/StringBuilder;
        92: ldc_w         #326                // String , \"suiteClassName\":
        95: invokevirtual #307                // Method java/lang/StringBuilder.append:(Ljava/lang/String;)Ljava/lang/StringBuilder;
        98: aload_0
        99: invokevirtual #316                // Method EventJsonHelper:()Lorg/scalatest/events/Event$EventJsonHelper$;
       102: aload_0
       103: invokevirtual #238                // Method suiteClassName:()Lscala/Option;
       106: invokevirtual #327                // Method org/scalatest/events/Event$EventJsonHelper$.stringOption:(Lscala/Option;)Ljava/lang/String;
       109: invokevirtual #307                // Method java/lang/StringBuilder.append:(Ljava/lang/String;)Ljava/lang/StringBuilder;
       112: ldc_w         #329                // String , \"duration\":
       115: invokevirtual #307                // Method java/lang/StringBuilder.append:(Ljava/lang/String;)Ljava/lang/StringBuilder;
       118: aload_0
       119: invokevirtual #245                // Method duration:()Lscala/Option;
       122: invokedynamic #348,  0            // InvokeDynamic #0:apply:()Lscala/Function0;
       127: invokevirtual #354                // Method scala/Option.getOrElse:(Lscala/Function0;)Ljava/lang/Object;
       130: invokevirtual #357                // Method java/lang/StringBuilder.append:(Ljava/lang/Object;)Ljava/lang/StringBuilder;
       133: ldc_w         #359                // String , \"throwable\":
       136: invokevirtual #307                // Method java/lang/StringBuilder.append:(Ljava/lang/String;)Ljava/lang/StringBuilder;
       139: aload_0
       140: invokevirtual #316                // Method EventJsonHelper:()Lorg/scalatest/events/Event$EventJsonHelper$;
       143: aload_0
       144: invokevirtual #251                // Method throwable:()Lscala/Option;
       147: invokevirtual #361                // Method org/scalatest/events/Event$EventJsonHelper$.throwableOption:(Lscala/Option;)Ljava/lang/String;
       150: invokevirtual #307                // Method java/lang/StringBuilder.append:(Ljava/lang/String;)Ljava/lang/StringBuilder;
       153: ldc_w         #363                // String , \"formatter\":
       156: invokevirtual #307                // Method java/lang/StringBuilder.append:(Ljava/lang/String;)Ljava/lang/StringBuilder;
       159: aload_0
       160: invokevirtual #316                // Method EventJsonHelper:()Lorg/scalatest/events/Event$EventJsonHelper$;
       163: aload_0
       164: invokevirtual #258                // Method formatter:()Lscala/Option;
       167: invokevirtual #365                // Method org/scalatest/events/Event$EventJsonHelper$.formatterOption:(Lscala/Option;)Ljava/lang/String;
       170: invokevirtual #307                // Method java/lang/StringBuilder.append:(Ljava/lang/String;)Ljava/lang/StringBuilder;
       173: ldc_w         #367                // String , \"location\":
       176: invokevirtual #307                // Method java/lang/StringBuilder.append:(Ljava/lang/String;)Ljava/lang/StringBuilder;
       179: aload_0
       180: invokevirtual #316                // Method EventJsonHelper:()Lorg/scalatest/events/Event$EventJsonHelper$;
       183: aload_0
       184: invokevirtual #264                // Method location:()Lscala/Option;
       187: invokevirtual #369                // Method org/scalatest/events/Event$EventJsonHelper$.locationOption:(Lscala/Option;)Ljava/lang/String;
       190: invokevirtual #307                // Method java/lang/StringBuilder.append:(Ljava/lang/String;)Ljava/lang/StringBuilder;
       193: ldc_w         #371                // String , \"rerunner\":
       196: invokevirtual #307                // Method java/lang/StringBuilder.append:(Ljava/lang/String;)Ljava/lang/StringBuilder;
       199: aload_0
       200: invokevirtual #316                // Method EventJsonHelper:()Lorg/scalatest/events/Event$EventJsonHelper$;
       203: aload_0
       204: invokevirtual #270                // Method rerunner:()Lscala/Option;
       207: invokevirtual #327                // Method org/scalatest/events/Event$EventJsonHelper$.stringOption:(Lscala/Option;)Ljava/lang/String;
       210: invokevirtual #307                // Method java/lang/StringBuilder.append:(Ljava/lang/String;)Ljava/lang/StringBuilder;
       213: ldc_w         #373                // String , \"threadName\":
       216: invokevirtual #307                // Method java/lang/StringBuilder.append:(Ljava/lang/String;)Ljava/lang/StringBuilder;
       219: aload_0
       220: invokevirtual #316                // Method EventJsonHelper:()Lorg/scalatest/events/Event$EventJsonHelper$;
       223: aload_0
       224: invokevirtual #273                // Method threadName:()Ljava/lang/String;
       227: invokevirtual #320                // Method org/scalatest/events/Event$EventJsonHelper$.string:(Ljava/lang/String;)Ljava/lang/String;
       230: invokevirtual #307                // Method java/lang/StringBuilder.append:(Ljava/lang/String;)Ljava/lang/StringBuilder;
       233: ldc_w         #375                // String , \"timeStamp\":
       236: invokevirtual #307                // Method java/lang/StringBuilder.append:(Ljava/lang/String;)Ljava/lang/StringBuilder;
       239: aload_0
       240: invokevirtual #276                // Method timeStamp:()J
       243: invokevirtual #378                // Method java/lang/StringBuilder.append:(J)Ljava/lang/StringBuilder;
       246: ldc_w         #380                // String  }
       249: invokevirtual #307                // Method java/lang/StringBuilder.append:(Ljava/lang/String;)Ljava/lang/StringBuilder;
       252: invokevirtual #383                // Method java/lang/StringBuilder.toString:()Ljava/lang/String;
       255: invokevirtual #386                // Method scala/Predef$.augmentString:(Ljava/lang/String;)Ljava/lang/String;
       258: invokevirtual #389                // Method scala/collection/StringOps$.stripMargin$extension:(Ljava/lang/String;)Ljava/lang/String;
       261: areturn
      LineNumberTable:
        line 1285: 3
      LocalVariableTable:
        Start  Length  Slot  Name   Signature
            0     262     0  this   Lorg/scalatest/events/SuiteAborted;

  public org.scalatest.events.SuiteAborted withPayload(scala.Option<java.lang.Object>);
    descriptor: (Lscala/Option;)Lorg/scalatest/events/SuiteAborted;
    flags: (0x0001) ACC_PUBLIC
    Code:
      stack=15, locals=16, args_size=2
         0: aload_1
         1: astore_2
         2: aload_0
         3: invokevirtual #396                // Method copy$default$1:()Lorg/scalatest/events/Ordinal;
         6: astore_3
         7: aload_0
         8: invokevirtual #399                // Method copy$default$2:()Ljava/lang/String;
        11: astore        4
        13: aload_0
        14: invokevirtual #402                // Method copy$default$3:()Ljava/lang/String;
        17: astore        5
        19: aload_0
        20: invokevirtual #405                // Method copy$default$4:()Ljava/lang/String;
        23: astore        6
        25: aload_0
        26: invokevirtual #408                // Method copy$default$5:()Lscala/Option;
        29: astore        7
        31: aload_0
        32: invokevirtual #411                // Method copy$default$6:()Lscala/Option;
        35: astore        8
        37: aload_0
        38: invokevirtual #414                // Method copy$default$7:()Lscala/Option;
        41: astore        9
        43: aload_0
        44: invokevirtual #417                // Method copy$default$8:()Lscala/Option;
        47: astore        10
        49: aload_0
        50: invokevirtual #420                // Method copy$default$9:()Lscala/Option;
        53: astore        11
        55: aload_0
        56: invokevirtual #423                // Method copy$default$10:()Lscala/Option;
        59: astore        12
        61: aload_0
        62: invokevirtual #426                // Method copy$default$12:()Ljava/lang/String;
        65: astore        13
        67: aload_0
        68: invokevirtual #429                // Method copy$default$13:()J
        71: lstore        14
        73: aload_0
        74: aload_3
        75: aload         4
        77: aload         5
        79: aload         6
        81: aload         7
        83: aload         8
        85: aload         9
        87: aload         10
        89: aload         11
        91: aload         12
        93: aload_2
        94: aload         13
        96: lload         14
        98: invokevirtual #432                // Method copy:(Lorg/scalatest/events/Ordinal;Ljava/lang/String;Ljava/lang/String;Ljava/lang/String;Lscala/Option;Lscala/Option;Lscala/Option;Lscala/Option;Lscala/Option;Lscala/Option;Lscala/Option;Ljava/lang/String;J)Lorg/scalatest/events/SuiteAborted;
       101: areturn
      LineNumberTable:
        line 1288: 0
      LocalVariableTable:
        Start  Length  Slot  Name   Signature
            2      99     2   x$1   Lscala/Option;
            7      94     3   x$2   Lorg/scalatest/events/Ordinal;
           13      88     4   x$3   Ljava/lang/String;
           19      82     5   x$4   Ljava/lang/String;
           25      76     6   x$5   Ljava/lang/String;
           31      70     7   x$6   Lscala/Option;
           37      64     8   x$7   Lscala/Option;
           43      58     9   x$8   Lscala/Option;
           49      52    10   x$9   Lscala/Option;
           55      46    11  x$10   Lscala/Option;
           61      40    12  x$11   Lscala/Option;
           67      34    13  x$12   Ljava/lang/String;
           73      28    14  x$13   J
            0     102     0  this   Lorg/scalatest/events/SuiteAborted;
            0     102     1 newPayload   Lscala/Option;
    Signature: #392                         // (Lscala/Option<Ljava/lang/Object;>;)Lorg/scalatest/events/SuiteAborted;
    MethodParameters:
      Name                           Flags
      newPayload                     final

  public org.scalatest.events.Event withThrowable(scala.Option<java.lang.Throwable>);
    descriptor: (Lscala/Option;)Lorg/scalatest/events/Event;
    flags: (0x0001) ACC_PUBLIC
    Code:
      stack=15, locals=16, args_size=2
         0: aload_1
         1: astore_2
         2: aload_0
         3: invokevirtual #396                // Method copy$default$1:()Lorg/scalatest/events/Ordinal;
         6: astore_3
         7: aload_0
         8: invokevirtual #399                // Method copy$default$2:()Ljava/lang/String;
        11: astore        4
        13: aload_0
        14: invokevirtual #402                // Method copy$default$3:()Ljava/lang/String;
        17: astore        5
        19: aload_0
        20: invokevirtual #405                // Method copy$default$4:()Ljava/lang/String;
        23: astore        6
        25: aload_0
        26: invokevirtual #408                // Method copy$default$5:()Lscala/Option;
        29: astore        7
        31: aload_0
        32: invokevirtual #414                // Method copy$default$7:()Lscala/Option;
        35: astore        8
        37: aload_0
        38: invokevirtual #417                // Method copy$default$8:()Lscala/Option;
        41: astore        9
        43: aload_0
        44: invokevirtual #420                // Method copy$default$9:()Lscala/Option;
        47: astore        10
        49: aload_0
        50: invokevirtual #423                // Method copy$default$10:()Lscala/Option;
        53: astore        11
        55: aload_0
        56: invokevirtual #452                // Method copy$default$11:()Lscala/Option;
        59: astore        12
        61: aload_0
        62: invokevirtual #426                // Method copy$default$12:()Ljava/lang/String;
        65: astore        13
        67: aload_0
        68: invokevirtual #429                // Method copy$default$13:()J
        71: lstore        14
        73: aload_0
        74: aload_3
        75: aload         4
        77: aload         5
        79: aload         6
        81: aload         7
        83: aload_2
        84: aload         8
        86: aload         9
        88: aload         10
        90: aload         11
        92: aload         12
        94: aload         13
        96: lload         14
        98: invokevirtual #432                // Method copy:(Lorg/scalatest/events/Ordinal;Ljava/lang/String;Ljava/lang/String;Ljava/lang/String;Lscala/Option;Lscala/Option;Lscala/Option;Lscala/Option;Lscala/Option;Lscala/Option;Lscala/Option;Ljava/lang/String;J)Lorg/scalatest/events/SuiteAborted;
       101: areturn
      LineNumberTable:
        line 1290: 0
      LocalVariableTable:
        Start  Length  Slot  Name   Signature
            2      99     2   x$1   Lscala/Option;
            7      94     3   x$2   Lorg/scalatest/events/Ordinal;
           13      88     4   x$3   Ljava/lang/String;
           19      82     5   x$4   Ljava/lang/String;
           25      76     6   x$5   Ljava/lang/String;
           31      70     7   x$6   Lscala/Option;
           37      64     8   x$7   Lscala/Option;
           43      58     9   x$8   Lscala/Option;
           49      52    10   x$9   Lscala/Option;
           55      46    11  x$10   Lscala/Option;
           61      40    12  x$11   Lscala/Option;
           67      34    13  x$12   Ljava/lang/String;
           73      28    14  x$13   J
            0     102     0  this   Lorg/scalatest/events/SuiteAborted;
            0     102     1 newThrowable   Lscala/Option;
    Signature: #448                         // (Lscala/Option<Ljava/lang/Throwable;>;)Lorg/scalatest/events/Event;
    MethodParameters:
      Name                           Flags
      newThrowable                   final

  public org.scalatest.events.Event ensureSerializable();
    descriptor: ()Lorg/scalatest/events/Event;
    flags: (0x0001) ACC_PUBLIC
    Code:
      stack=2, locals=1, args_size=1
         0: aload_0
         1: aload_0
         2: invokevirtual #456                // Method payload:()Lscala/Option;
         5: invokevirtual #459                // Method ensurePayloadSerializable:(Lscala/Option;)Lorg/scalatest/events/Event;
         8: aload_0
         9: invokevirtual #251                // Method throwable:()Lscala/Option;
        12: invokevirtual #462                // Method org/scalatest/events/Event.ensureThrowableSerializable:(Lscala/Option;)Lorg/scalatest/events/Event;
        15: areturn
      LineNumberTable:
        line 1293: 0
      LocalVariableTable:
        Start  Length  Slot  Name   Signature
            0      16     0  this   Lorg/scalatest/events/SuiteAborted;

  public org.scalatest.events.SuiteAborted copy(org.scalatest.events.Ordinal, java.lang.String, java.lang.String, java.lang.String, scala.Option<java.lang.String>, scala.Option<java.lang.Throwable>, scala.Option<java.lang.Object>, scala.Option<org.scalatest.events.Formatter>, scala.Option<org.scalatest.events.Location>, scala.Option<java.lang.String>, scala.Option<java.lang.Object>, java.lang.String, long);
    descriptor: (Lorg/scalatest/events/Ordinal;Ljava/lang/String;Ljava/lang/String;Ljava/lang/String;Lscala/Option;Lscala/Option;Lscala/Option;Lscala/Option;Lscala/Option;Lscala/Option;Lscala/Option;Ljava/lang/String;J)Lorg/scalatest/events/SuiteAborted;
    flags: (0x0001) ACC_PUBLIC
    Code:
      stack=16, locals=15, args_size=14
         0: new           #2                  // class org/scalatest/events/SuiteAborted
         3: dup
         4: aload_1
         5: aload_2
         6: aload_3
         7: aload         4
         9: aload         5
        11: aload         6
        13: aload         7
        15: aload         8
        17: aload         9
        19: aload         10
        21: aload         11
        23: aload         12
        25: lload         13
        27: invokespecial #465                // Method "<init>":(Lorg/scalatest/events/Ordinal;Ljava/lang/String;Ljava/lang/String;Ljava/lang/String;Lscala/Option;Lscala/Option;Lscala/Option;Lscala/Option;Lscala/Option;Lscala/Option;Lscala/Option;Ljava/lang/String;J)V
        30: areturn
      LineNumberTable:
        line 1232: 0
        line 1233: 4
        line 1234: 5
        line 1235: 6
        line 1236: 7
        line 1237: 9
        line 1238: 11
        line 1239: 13
        line 1240: 15
        line 1241: 17
        line 1242: 19
        line 1243: 21
        line 1244: 23
        line 1245: 25
      LocalVariableTable:
        Start  Length  Slot  Name   Signature
            0      31     0  this   Lorg/scalatest/events/SuiteAborted;
            0      31     1 ordinal   Lorg/scalatest/events/Ordinal;
            0      31     2 message   Ljava/lang/String;
            0      31     3 suiteName   Ljava/lang/String;
            0      31     4 suiteId   Ljava/lang/String;
            0      31     5 suiteClassName   Lscala/Option;
            0      31     6 throwable   Lscala/Option;
            0      31     7 duration   Lscala/Option;
            0      31     8 formatter   Lscala/Option;
            0      31     9 location   Lscala/Option;
            0      31    10 rerunner   Lscala/Option;
            0      31    11 payload   Lscala/Option;
            0      31    12 threadName   Ljava/lang/String;
            0      31    13 timeStamp   J
    Signature: #120                         // (Lorg/scalatest/events/Ordinal;Ljava/lang/String;Ljava/lang/String;Ljava/lang/String;Lscala/Option<Ljava/lang/String;>;Lscala/Option<Ljava/lang/Throwable;>;Lscala/Option<Ljava/lang/Object;>;Lscala/Option<Lorg/scalatest/events/Formatter;>;Lscala/Option<Lorg/scalatest/events/Location;>;Lscala/Option<Ljava/lang/String;>;Lscala/Option<Ljava/lang/Object;>;Ljava/lang/String;J)Lorg/scalatest/events/SuiteAborted;
    MethodParameters:
      Name                           Flags
      ordinal                        final
      message                        final
      suiteName                      final
      suiteId                        final
      suiteClassName                 final
      throwable                      final
      duration                       final
      formatter                      final
      location                       final
      rerunner                       final
      payload                        final
      threadName                     final
      timeStamp                      final

  public org.scalatest.events.Ordinal copy$default$1();
    descriptor: ()Lorg/scalatest/events/Ordinal;
    flags: (0x0001) ACC_PUBLIC
    Code:
      stack=1, locals=1, args_size=1
         0: aload_0
         1: invokevirtual #204                // Method ordinal:()Lorg/scalatest/events/Ordinal;
         4: areturn
      LineNumberTable:
        line 1233: 0
      LocalVariableTable:
        Start  Length  Slot  Name   Signature
            0       5     0  this   Lorg/scalatest/events/SuiteAborted;

  public scala.Option<java.lang.String> copy$default$10();
    descriptor: ()Lscala/Option;
    flags: (0x0001) ACC_PUBLIC
    Code:
      stack=1, locals=1, args_size=1
         0: aload_0
         1: invokevirtual #270                // Method rerunner:()Lscala/Option;
         4: areturn
      LineNumberTable:
        line 1242: 0
      LocalVariableTable:
        Start  Length  Slot  Name   Signature
            0       5     0  this   Lorg/scalatest/events/SuiteAborted;
    Signature: #69                          // ()Lscala/Option<Ljava/lang/String;>;

  public scala.Option<java.lang.Object> copy$default$11();
    descriptor: ()Lscala/Option;
    flags: (0x0001) ACC_PUBLIC
    Code:
      stack=1, locals=1, args_size=1
         0: aload_0
         1: invokevirtual #456                // Method payload:()Lscala/Option;
         4: areturn
      LineNumberTable:
        line 1243: 0
      LocalVariableTable:
        Start  Length  Slot  Name   Signature
            0       5     0  this   Lorg/scalatest/events/SuiteAborted;
    Signature: #65                          // ()Lscala/Option<Ljava/lang/Object;>;

  public java.lang.String copy$default$12();
    descriptor: ()Ljava/lang/String;
    flags: (0x0001) ACC_PUBLIC
    Code:
      stack=1, locals=1, args_size=1
         0: aload_0
         1: invokevirtual #273                // Method threadName:()Ljava/lang/String;
         4: areturn
      LineNumberTable:
        line 1244: 0
      LocalVariableTable:
        Start  Length  Slot  Name   Signature
            0       5     0  this   Lorg/scalatest/events/SuiteAborted;

  public long copy$default$13();
    descriptor: ()J
    flags: (0x0001) ACC_PUBLIC
    Code:
      stack=2, locals=1, args_size=1
         0: aload_0
         1: invokevirtual #276                // Method timeStamp:()J
         4: lreturn
      LineNumberTable:
        line 1245: 0
      LocalVariableTable:
        Start  Length  Slot  Name   Signature
            0       5     0  this   Lorg/scalatest/events/SuiteAborted;

  public java.lang.String copy$default$2();
    descriptor: ()Ljava/lang/String;
    flags: (0x0001) ACC_PUBLIC
    Code:
      stack=1, locals=1, args_size=1
         0: aload_0
         1: invokevirtual #225                // Method message:()Ljava/lang/String;
         4: areturn
      LineNumberTable:
        line 1234: 0
      LocalVariableTable:
        Start  Length  Slot  Name   Signature
            0       5     0  this   Lorg/scalatest/events/SuiteAborted;

  public java.lang.String copy$default$3();
    descriptor: ()Ljava/lang/String;
    flags: (0x0001) ACC_PUBLIC
    Code:
      stack=1, locals=1, args_size=1
         0: aload_0
         1: invokevirtual #228                // Method suiteName:()Ljava/lang/String;
         4: areturn
      LineNumberTable:
        line 1235: 0
      LocalVariableTable:
        Start  Length  Slot  Name   Signature
            0       5     0  this   Lorg/scalatest/events/SuiteAborted;

  public java.lang.String copy$default$4();
    descriptor: ()Ljava/lang/String;
    flags: (0x0001) ACC_PUBLIC
    Code:
      stack=1, locals=1, args_size=1
         0: aload_0
         1: invokevirtual #231                // Method suiteId:()Ljava/lang/String;
         4: areturn
      LineNumberTable:
        line 1236: 0
      LocalVariableTable:
        Start  Length  Slot  Name   Signature
            0       5     0  this   Lorg/scalatest/events/SuiteAborted;

  public scala.Option<java.lang.String> copy$default$5();
    descriptor: ()Lscala/Option;
    flags: (0x0001) ACC_PUBLIC
    Code:
      stack=1, locals=1, args_size=1
         0: aload_0
         1: invokevirtual #238                // Method suiteClassName:()Lscala/Option;
         4: areturn
      LineNumberTable:
        line 1237: 0
      LocalVariableTable:
        Start  Length  Slot  Name   Signature
            0       5     0  this   Lorg/scalatest/events/SuiteAborted;
    Signature: #69                          // ()Lscala/Option<Ljava/lang/String;>;

  public scala.Option<java.lang.Throwable> copy$default$6();
    descriptor: ()Lscala/Option;
    flags: (0x0001) ACC_PUBLIC
    Code:
      stack=1, locals=1, args_size=1
         0: aload_0
         1: invokevirtual #251                // Method throwable:()Lscala/Option;
         4: areturn
      LineNumberTable:
        line 1238: 0
      LocalVariableTable:
        Start  Length  Slot  Name   Signature
            0       5     0  this   Lorg/scalatest/events/SuiteAborted;
    Signature: #84                          // ()Lscala/Option<Ljava/lang/Throwable;>;

  public scala.Option<java.lang.Object> copy$default$7();
    descriptor: ()Lscala/Option;
    flags: (0x0001) ACC_PUBLIC
    Code:
      stack=1, locals=1, args_size=1
         0: aload_0
         1: invokevirtual #245                // Method duration:()Lscala/Option;
         4: areturn
      LineNumberTable:
        line 1239: 0
      LocalVariableTable:
        Start  Length  Slot  Name   Signature
            0       5     0  this   Lorg/scalatest/events/SuiteAborted;
    Signature: #65                          // ()Lscala/Option<Ljava/lang/Object;>;

  public scala.Option<org.scalatest.events.Formatter> copy$default$8();
    descriptor: ()Lscala/Option;
    flags: (0x0001) ACC_PUBLIC
    Code:
      stack=1, locals=1, args_size=1
         0: aload_0
         1: invokevirtual #258                // Method formatter:()Lscala/Option;
         4: areturn
      LineNumberTable:
        line 1240: 0
      LocalVariableTable:
        Start  Length  Slot  Name   Signature
            0       5     0  this   Lorg/scalatest/events/SuiteAborted;
    Signature: #77                          // ()Lscala/Option<Lorg/scalatest/events/Formatter;>;

  public scala.Option<org.scalatest.events.Location> copy$default$9();
    descriptor: ()Lscala/Option;
    flags: (0x0001) ACC_PUBLIC
    Code:
      stack=1, locals=1, args_size=1
         0: aload_0
         1: invokevirtual #264                // Method location:()Lscala/Option;
         4: areturn
      LineNumberTable:
        line 1241: 0
      LocalVariableTable:
        Start  Length  Slot  Name   Signature
            0       5     0  this   Lorg/scalatest/events/SuiteAborted;
    Signature: #73                          // ()Lscala/Option<Lorg/scalatest/events/Location;>;

  public java.lang.String productPrefix();
    descriptor: ()Ljava/lang/String;
    flags: (0x0001) ACC_PUBLIC
    Code:
      stack=1, locals=1, args_size=1
         0: ldc           #165                // String SuiteAborted
         2: areturn
      LineNumberTable:
        line 1232: 0
      LocalVariableTable:
        Start  Length  Slot  Name   Signature
            0       3     0  this   Lorg/scalatest/events/SuiteAborted;

  public int productArity();
    descriptor: ()I
    flags: (0x0001) ACC_PUBLIC
    Code:
      stack=1, locals=1, args_size=1
         0: bipush        13
         2: ireturn
      LineNumberTable:
        line 1232: 0
      LocalVariableTable:
        Start  Length  Slot  Name   Signature
            0       3     0  this   Lorg/scalatest/events/SuiteAborted;

  public java.lang.Object productElement(int);
    descriptor: (I)Ljava/lang/Object;
    flags: (0x0001) ACC_PUBLIC
    Code:
      stack=2, locals=3, args_size=2
         0: iload_1
         1: istore_2
         2: iload_2
         3: tableswitch   { // 0 to 12
                       0: 68
                       1: 75
                       2: 82
                       3: 89
                       4: 96
                       5: 103
                       6: 110
                       7: 117
                       8: 124
                       9: 131
                      10: 138
                      11: 145
                      12: 152
                 default: 162
            }
        68: aload_0
        69: invokevirtual #204                // Method ordinal:()Lorg/scalatest/events/Ordinal;
        72: goto          169
        75: aload_0
        76: invokevirtual #225                // Method message:()Ljava/lang/String;
        79: goto          169
        82: aload_0
        83: invokevirtual #228                // Method suiteName:()Ljava/lang/String;
        86: goto          169
        89: aload_0
        90: invokevirtual #231                // Method suiteId:()Ljava/lang/String;
        93: goto          169
        96: aload_0
        97: invokevirtual #238                // Method suiteClassName:()Lscala/Option;
       100: goto          169
       103: aload_0
       104: invokevirtual #251                // Method throwable:()Lscala/Option;
       107: goto          169
       110: aload_0
       111: invokevirtual #245                // Method duration:()Lscala/Option;
       114: goto          169
       117: aload_0
       118: invokevirtual #258                // Method formatter:()Lscala/Option;
       121: goto          169
       124: aload_0
       125: invokevirtual #264                // Method location:()Lscala/Option;
       128: goto          169
       131: aload_0
       132: invokevirtual #270                // Method rerunner:()Lscala/Option;
       135: goto          169
       138: aload_0
       139: invokevirtual #456                // Method payload:()Lscala/Option;
       142: goto          169
       145: aload_0
       146: invokevirtual #273                // Method threadName:()Ljava/lang/String;
       149: goto          169
       152: aload_0
       153: invokevirtual #276                // Method timeStamp:()J
       156: invokestatic  #280                // Method scala/runtime/BoxesRunTime.boxToLong:(J)Ljava/lang/Long;
       159: goto          169
       162: iload_1
       163: invokestatic  #474                // Method scala/runtime/Statics.ioobe:(I)Ljava/lang/Object;
       166: goto          169
       169: areturn
      StackMapTable: number_of_entries = 15
        frame_type = 252 /* append */
          offset_delta = 68
          locals = [ int ]
        frame_type = 6 /* same */
        frame_type = 6 /* same */
        frame_type = 6 /* same */
        frame_type = 6 /* same */
        frame_type = 6 /* same */
        frame_type = 6 /* same */
        frame_type = 6 /* same */
        frame_type = 6 /* same */
        frame_type = 6 /* same */
        frame_type = 6 /* same */
        frame_type = 6 /* same */
        frame_type = 6 /* same */
        frame_type = 9 /* same */
        frame_type = 70 /* same_locals_1_stack_item */
          stack = [ class java/lang/Object ]
      LineNumberTable:
        line 1232: 0
      LocalVariableTable:
        Start  Length  Slot  Name   Signature
            0     170     0  this   Lorg/scalatest/events/SuiteAborted;
            0     170     1   x$1   I
    MethodParameters:
      Name                           Flags
      x$1                            final

  public scala.collection.Iterator<java.lang.Object> productIterator();
    descriptor: ()Lscala/collection/Iterator;
    flags: (0x0001) ACC_PUBLIC
    Code:
      stack=2, locals=1, args_size=1
         0: getstatic     #485                // Field scala/runtime/ScalaRunTime$.MODULE$:Lscala/runtime/ScalaRunTime$;
         3: aload_0
         4: invokevirtual #489                // Method scala/runtime/ScalaRunTime$.typedProductIterator:(Lscala/Product;)Lscala/collection/Iterator;
         7: areturn
      LineNumberTable:
        line 1232: 0
      LocalVariableTable:
        Start  Length  Slot  Name   Signature
            0       8     0  this   Lorg/scalatest/events/SuiteAborted;
    Signature: #480                         // ()Lscala/collection/Iterator<Ljava/lang/Object;>;

  public boolean canEqual(java.lang.Object);
    descriptor: (Ljava/lang/Object;)Z
    flags: (0x0001) ACC_PUBLIC
    Code:
      stack=1, locals=2, args_size=2
         0: aload_1
         1: instanceof    #2                  // class org/scalatest/events/SuiteAborted
         4: ireturn
      LineNumberTable:
        line 1232: 0
      LocalVariableTable:
        Start  Length  Slot  Name   Signature
            0       5     0  this   Lorg/scalatest/events/SuiteAborted;
            0       5     1   x$1   Ljava/lang/Object;
    MethodParameters:
      Name                           Flags
      x$1                            final

  public java.lang.String productElementName(int);
    descriptor: (I)Ljava/lang/String;
    flags: (0x0001) ACC_PUBLIC
    Code:
      stack=1, locals=3, args_size=2
         0: iload_1
         1: istore_2
         2: iload_2
         3: tableswitch   { // 0 to 12
                       0: 68
                       1: 73
                       2: 78
                       3: 83
                       4: 88
                       5: 93
                       6: 98
                       7: 103
                       8: 109
                       9: 115
                      10: 121
                      11: 127
                      12: 133
                 default: 139
            }
        68: ldc           #198                // String ordinal
        70: goto          149
        73: ldc           #223                // String message
        75: goto          149
        78: ldc           #226                // String suiteName
        80: goto          149
        83: ldc           #229                // String suiteId
        85: goto          149
        88: ldc           #232                // String suiteClassName
        90: goto          149
        93: ldc           #249                // String throwable
        95: goto          149
        98: ldc           #243                // String duration
       100: goto          149
       103: ldc_w         #256                // String formatter
       106: goto          149
       109: ldc_w         #262                // String location
       112: goto          149
       115: ldc_w         #268                // String rerunner
       118: goto          149
       121: ldc_w         #495                // String payload
       124: goto          149
       127: ldc_w         #271                // String threadName
       130: goto          149
       133: ldc_w         #274                // String timeStamp
       136: goto          149
       139: iload_1
       140: invokestatic  #474                // Method scala/runtime/Statics.ioobe:(I)Ljava/lang/Object;
       143: checkcast     #497                // class java/lang/String
       146: goto          149
       149: areturn
      StackMapTable: number_of_entries = 15
        frame_type = 252 /* append */
          offset_delta = 68
          locals = [ int ]
        frame_type = 4 /* same */
        frame_type = 4 /* same */
        frame_type = 4 /* same */
        frame_type = 4 /* same */
        frame_type = 4 /* same */
        frame_type = 4 /* same */
        frame_type = 4 /* same */
        frame_type = 5 /* same */
        frame_type = 5 /* same */
        frame_type = 5 /* same */
        frame_type = 5 /* same */
        frame_type = 5 /* same */
        frame_type = 5 /* same */
        frame_type = 73 /* same_locals_1_stack_item */
          stack = [ class java/lang/String ]
      LineNumberTable:
        line 1232: 0
      LocalVariableTable:
        Start  Length  Slot  Name   Signature
            0     150     0  this   Lorg/scalatest/events/SuiteAborted;
            0     150     1   x$1   I
    MethodParameters:
      Name                           Flags
      x$1                            final

  public int hashCode();
    descriptor: ()I
    flags: (0x0001) ACC_PUBLIC
    Code:
      stack=3, locals=2, args_size=1
         0: ldc_w         #499                // int -889275714
         3: istore_1
         4: iload_1
         5: aload_0
         6: invokevirtual #501                // Method productPrefix:()Ljava/lang/String;
         9: invokevirtual #503                // Method java/lang/String.hashCode:()I
        12: invokestatic  #507                // Method scala/runtime/Statics.mix:(II)I
        15: istore_1
        16: iload_1
        17: aload_0
        18: invokevirtual #204                // Method ordinal:()Lorg/scalatest/events/Ordinal;
        21: invokestatic  #511                // Method scala/runtime/Statics.anyHash:(Ljava/lang/Object;)I
        24: invokestatic  #507                // Method scala/runtime/Statics.mix:(II)I
        27: istore_1
        28: iload_1
        29: aload_0
        30: invokevirtual #225                // Method message:()Ljava/lang/String;
        33: invokestatic  #511                // Method scala/runtime/Statics.anyHash:(Ljava/lang/Object;)I
        36: invokestatic  #507                // Method scala/runtime/Statics.mix:(II)I
        39: istore_1
        40: iload_1
        41: aload_0
        42: invokevirtual #228                // Method suiteName:()Ljava/lang/String;
        45: invokestatic  #511                // Method scala/runtime/Statics.anyHash:(Ljava/lang/Object;)I
        48: invokestatic  #507                // Method scala/runtime/Statics.mix:(II)I
        51: istore_1
        52: iload_1
        53: aload_0
        54: invokevirtual #231                // Method suiteId:()Ljava/lang/String;
        57: invokestatic  #511                // Method scala/runtime/Statics.anyHash:(Ljava/lang/Object;)I
        60: invokestatic  #507                // Method scala/runtime/Statics.mix:(II)I
        63: istore_1
        64: iload_1
        65: aload_0
        66: invokevirtual #238                // Method suiteClassName:()Lscala/Option;
        69: invokestatic  #511                // Method scala/runtime/Statics.anyHash:(Ljava/lang/Object;)I
        72: invokestatic  #507                // Method scala/runtime/Statics.mix:(II)I
        75: istore_1
        76: iload_1
        77: aload_0
        78: invokevirtual #251                // Method throwable:()Lscala/Option;
        81: invokestatic  #511                // Method scala/runtime/Statics.anyHash:(Ljava/lang/Object;)I
        84: invokestatic  #507                // Method scala/runtime/Statics.mix:(II)I
        87: istore_1
        88: iload_1
        89: aload_0
        90: invokevirtual #245                // Method duration:()Lscala/Option;
        93: invokestatic  #511                // Method scala/runtime/Statics.anyHash:(Ljava/lang/Object;)I
        96: invokestatic  #507                // Method scala/runtime/Statics.mix:(II)I
        99: istore_1
       100: iload_1
       101: aload_0
       102: invokevirtual #258                // Method formatter:()Lscala/Option;
       105: invokestatic  #511                // Method scala/runtime/Statics.anyHash:(Ljava/lang/Object;)I
       108: invokestatic  #507                // Method scala/runtime/Statics.mix:(II)I
       111: istore_1
       112: iload_1
       113: aload_0
       114: invokevirtual #264                // Method location:()Lscala/Option;
       117: invokestatic  #511                // Method scala/runtime/Statics.anyHash:(Ljava/lang/Object;)I
       120: invokestatic  #507                // Method scala/runtime/Statics.mix:(II)I
       123: istore_1
       124: iload_1
       125: aload_0
       126: invokevirtual #270                // Method rerunner:()Lscala/Option;
       129: invokestatic  #511                // Method scala/runtime/Statics.anyHash:(Ljava/lang/Object;)I
       132: invokestatic  #507                // Method scala/runtime/Statics.mix:(II)I
       135: istore_1
       136: iload_1
       137: aload_0
       138: invokevirtual #456                // Method payload:()Lscala/Option;
       141: invokestatic  #511                // Method scala/runtime/Statics.anyHash:(Ljava/lang/Object;)I
       144: invokestatic  #507                // Method scala/runtime/Statics.mix:(II)I
       147: istore_1
       148: iload_1
       149: aload_0
       150: invokevirtual #273                // Method threadName:()Ljava/lang/String;
       153: invokestatic  #511                // Method scala/runtime/Statics.anyHash:(Ljava/lang/Object;)I
       156: invokestatic  #507                // Method scala/runtime/Statics.mix:(II)I
       159: istore_1
       160: iload_1
       161: aload_0
       162: invokevirtual #276                // Method timeStamp:()J
       165: invokestatic  #515                // Method scala/runtime/Statics.longHash:(J)I
       168: invokestatic  #507                // Method scala/runtime/Statics.mix:(II)I
       171: istore_1
       172: iload_1
       173: bipush        13
       175: invokestatic  #518                // Method scala/runtime/Statics.finalizeHash:(II)I
       178: ireturn
      LineNumberTable:
        line 1232: 0
      LocalVariableTable:
        Start  Length  Slot  Name   Signature
            0     179     0  this   Lorg/scalatest/events/SuiteAborted;

  public java.lang.String toString();
    descriptor: ()Ljava/lang/String;
    flags: (0x0001) ACC_PUBLIC
    Code:
      stack=2, locals=1, args_size=1
         0: getstatic     #485                // Field scala/runtime/ScalaRunTime$.MODULE$:Lscala/runtime/ScalaRunTime$;
         3: aload_0
         4: invokevirtual #522                // Method scala/runtime/ScalaRunTime$._toString:(Lscala/Product;)Ljava/lang/String;
         7: areturn
      LineNumberTable:
        line 1232: 0
      LocalVariableTable:
        Start  Length  Slot  Name   Signature
            0       8     0  this   Lorg/scalatest/events/SuiteAborted;

  public boolean equals(java.lang.Object);
    descriptor: (Ljava/lang/Object;)Z
    flags: (0x0001) ACC_PUBLIC
    Code:
      stack=4, locals=17, args_size=2
         0: aload_0
         1: aload_1
         2: if_acmpeq     442
         5: aload_1
         6: astore_3
         7: aload_3
         8: instanceof    #2                  // class org/scalatest/events/SuiteAborted
        11: ifeq          19
        14: iconst_1
        15: istore_2
        16: goto          27
        19: goto          22
        22: iconst_0
        23: istore_2
        24: goto          27
        27: iload_2
        28: ifeq          446
        31: aload_1
        32: checkcast     #2                  // class org/scalatest/events/SuiteAborted
        35: astore        4
        37: aload_0
        38: invokevirtual #276                // Method timeStamp:()J
        41: aload         4
        43: invokevirtual #276                // Method timeStamp:()J
        46: lcmp
        47: ifne          438
        50: aload_0
        51: invokevirtual #204                // Method ordinal:()Lorg/scalatest/events/Ordinal;
        54: aload         4
        56: invokevirtual #204                // Method ordinal:()Lorg/scalatest/events/Ordinal;
        59: astore        5
        61: dup
        62: ifnonnull     74
        65: pop
        66: aload         5
        68: ifnull        82
        71: goto          438
        74: aload         5
        76: invokevirtual #525                // Method java/lang/Object.equals:(Ljava/lang/Object;)Z
        79: ifeq          438
        82: aload_0
        83: invokevirtual #225                // Method message:()Ljava/lang/String;
        86: aload         4
        88: invokevirtual #225                // Method message:()Ljava/lang/String;
        91: astore        6
        93: dup
        94: ifnonnull     106
        97: pop
        98: aload         6
       100: ifnull        114
       103: goto          438
       106: aload         6
       108: invokevirtual #525                // Method java/lang/Object.equals:(Ljava/lang/Object;)Z
       111: ifeq          438
       114: aload_0
       115: invokevirtual #228                // Method suiteName:()Ljava/lang/String;
       118: aload         4
       120: invokevirtual #228                // Method suiteName:()Ljava/lang/String;
       123: astore        7
       125: dup
       126: ifnonnull     138
       129: pop
       130: aload         7
       132: ifnull        146
       135: goto          438
       138: aload         7
       140: invokevirtual #525                // Method java/lang/Object.equals:(Ljava/lang/Object;)Z
       143: ifeq          438
       146: aload_0
       147: invokevirtual #231                // Method suiteId:()Ljava/lang/String;
       150: aload         4
       152: invokevirtual #231                // Method suiteId:()Ljava/lang/String;
       155: astore        8
       157: dup
       158: ifnonnull     170
       161: pop
       162: aload         8
       164: ifnull        178
       167: goto          438
       170: aload         8
       172: invokevirtual #525                // Method java/lang/Object.equals:(Ljava/lang/Object;)Z
       175: ifeq          438
       178: aload_0
       179: invokevirtual #238                // Method suiteClassName:()Lscala/Option;
       182: aload         4
       184: invokevirtual #238                // Method suiteClassName:()Lscala/Option;
       187: astore        9
       189: dup
       190: ifnonnull     202
       193: pop
       194: aload         9
       196: ifnull        210
       199: goto          438
       202: aload         9
       204: invokevirtual #525                // Method java/lang/Object.equals:(Ljava/lang/Object;)Z
       207: ifeq          438
       210: aload_0
       211: invokevirtual #251                // Method throwable:()Lscala/Option;
       214: aload         4
       216: invokevirtual #251                // Method throwable:()Lscala/Option;
       219: astore        10
       221: dup
       222: ifnonnull     234
       225: pop
       226: aload         10
       228: ifnull        242
       231: goto          438
       234: aload         10
       236: invokevirtual #525                // Method java/lang/Object.equals:(Ljava/lang/Object;)Z
       239: ifeq          438
       242: aload_0
       243: invokevirtual #245                // Method duration:()Lscala/Option;
       246: aload         4
       248: invokevirtual #245                // Method duration:()Lscala/Option;
       251: astore        11
       253: dup
       254: ifnonnull     266
       257: pop
       258: aload         11
       260: ifnull        274
       263: goto          438
       266: aload         11
       268: invokevirtual #525                // Method java/lang/Object.equals:(Ljava/lang/Object;)Z
       271: ifeq          438
       274: aload_0
       275: invokevirtual #258                // Method formatter:()Lscala/Option;
       278: aload         4
       280: invokevirtual #258                // Method formatter:()Lscala/Option;
       283: astore        12
       285: dup
       286: ifnonnull     298
       289: pop
       290: aload         12
       292: ifnull        306
       295: goto          438
       298: aload         12
       300: invokevirtual #525                // Method java/lang/Object.equals:(Ljava/lang/Object;)Z
       303: ifeq          438
       306: aload_0
       307: invokevirtual #264                // Method location:()Lscala/Option;
       310: aload         4
       312: invokevirtual #264                // Method location:()Lscala/Option;
       315: astore        13
       317: dup
       318: ifnonnull     330
       321: pop
       322: aload         13
       324: ifnull        338
       327: goto          438
       330: aload         13
       332: invokevirtual #525                // Method java/lang/Object.equals:(Ljava/lang/Object;)Z
       335: ifeq          438
       338: aload_0
       339: invokevirtual #270                // Method rerunner:()Lscala/Option;
       342: aload         4
       344: invokevirtual #270                // Method rerunner:()Lscala/Option;
       347: astore        14
       349: dup
       350: ifnonnull     362
       353: pop
       354: aload         14
       356: ifnull        370
       359: goto          438
       362: aload         14
       364: invokevirtual #525                // Method java/lang/Object.equals:(Ljava/lang/Object;)Z
       367: ifeq          438
       370: aload_0
       371: invokevirtual #456                // Method payload:()Lscala/Option;
       374: aload         4
       376: invokevirtual #456                // Method payload:()Lscala/Option;
       379: astore        15
       381: dup
       382: ifnonnull     394
       385: pop
       386: aload         15
       388: ifnull        402
       391: goto          438
       394: aload         15
       396: invokevirtual #525                // Method java/lang/Object.equals:(Ljava/lang/Object;)Z
       399: ifeq          438
       402: aload_0
       403: invokevirtual #273                // Method threadName:()Ljava/lang/String;
       406: aload         4
       408: invokevirtual #273                // Method threadName:()Ljava/lang/String;
       411: astore        16
       413: dup
       414: ifnonnull     426
       417: pop
       418: aload         16
       420: ifnull        434
       423: goto          438
       426: aload         16
       428: invokevirtual #525                // Method java/lang/Object.equals:(Ljava/lang/Object;)Z
       431: ifeq          438
       434: iconst_1
       435: goto          439
       438: iconst_0
       439: ifeq          446
       442: iconst_1
       443: goto          447
       446: iconst_0
       447: ireturn
      StackMapTable: number_of_entries = 32
        frame_type = 253 /* append */
          offset_delta = 19
          locals = [ top, class java/lang/Object ]
        frame_type = 2 /* same */
        frame_type = 255 /* full_frame */
          offset_delta = 4
          locals = [ class org/scalatest/events/SuiteAborted, class java/lang/Object, int, class java/lang/Object ]
          stack = []
        frame_type = 255 /* full_frame */
          offset_delta = 46
          locals = [ class org/scalatest/events/SuiteAborted, class java/lang/Object, int, class java/lang/Object, class org/scalatest/events/SuiteAborted, class org/scalatest/events/Ordinal ]
          stack = [ class org/scalatest/events/Ordinal ]
        frame_type = 7 /* same */
        frame_type = 255 /* full_frame */
          offset_delta = 23
          locals = [ class org/scalatest/events/SuiteAborted, class java/lang/Object, int, class java/lang/Object, class org/scalatest/events/SuiteAborted, class org/scalatest/events/Ordinal, class java/lang/String ]
          stack = [ class java/lang/String ]
        frame_type = 7 /* same */
        frame_type = 255 /* full_frame */
          offset_delta = 23
          locals = [ class org/scalatest/events/SuiteAborted, class java/lang/Object, int, class java/lang/Object, class org/scalatest/events/SuiteAborted, class org/scalatest/events/Ordinal, class java/lang/String, class java/lang/String ]
          stack = [ class java/lang/String ]
        frame_type = 7 /* same */
        frame_type = 255 /* full_frame */
          offset_delta = 23
          locals = [ class org/scalatest/events/SuiteAborted, class java/lang/Object, int, class java/lang/Object, class org/scalatest/events/SuiteAborted, class org/scalatest/events/Ordinal, class java/lang/String, class java/lang/String, class java/lang/String ]
          stack = [ class java/lang/String ]
        frame_type = 7 /* same */
        frame_type = 255 /* full_frame */
          offset_delta = 23
          locals = [ class org/scalatest/events/SuiteAborted, class java/lang/Object, int, class java/lang/Object, class org/scalatest/events/SuiteAborted, class org/scalatest/events/Ordinal, class java/lang/String, class java/lang/String, class java/lang/String, class scala/Option ]
          stack = [ class scala/Option ]
        frame_type = 7 /* same */
        frame_type = 255 /* full_frame */
          offset_delta = 23
          locals = [ class org/scalatest/events/SuiteAborted, class java/lang/Object, int, class java/lang/Object, class org/scalatest/events/SuiteAborted, class org/scalatest/events/Ordinal, class java/lang/String, class java/lang/String, class java/lang/String, class scala/Option, class scala/Option ]
          stack = [ class scala/Option ]
        frame_type = 7 /* same */
        frame_type = 255 /* full_frame */
          offset_delta = 23
          locals = [ class org/scalatest/events/SuiteAborted, class java/lang/Object, int, class java/lang/Object, class org/scalatest/events/SuiteAborted, class org/scalatest/events/Ordinal, class java/lang/String, class java/lang/String, class java/lang/String, class scala/Option, class scala/Option, class scala/Option ]
          stack = [ class scala/Option ]
        frame_type = 7 /* same */
        frame_type = 255 /* full_frame */
          offset_delta = 23
          locals = [ class org/scalatest/events/SuiteAborted, class java/lang/Object, int, class java/lang/Object, class org/scalatest/events/SuiteAborted, class org/scalatest/events/Ordinal, class java/lang/String, class java/lang/String, class java/lang/String, class scala/Option, class scala/Option, class scala/Option, class scala/Option ]
          stack = [ class scala/Option ]
        frame_type = 7 /* same */
        frame_type = 255 /* full_frame */
          offset_delta = 23
          locals = [ class org/scalatest/events/SuiteAborted, class java/lang/Object, int, class java/lang/Object, class org/scalatest/events/SuiteAborted, class org/scalatest/events/Ordinal, class java/lang/String, class java/lang/String, class java/lang/String, class scala/Option, class scala/Option, class scala/Option, class scala/Option, class scala/Option ]
          stack = [ class scala/Option ]
        frame_type = 7 /* same */
        frame_type = 255 /* full_frame */
          offset_delta = 23
          locals = [ class org/scalatest/events/SuiteAborted, class java/lang/Object, int, class java/lang/Object, class org/scalatest/events/SuiteAborted, class org/scalatest/events/Ordinal, class java/lang/String, class java/lang/String, class java/lang/String, class scala/Option, class scala/Option, class scala/Option, class scala/Option, class scala/Option, class scala/Option ]
          stack = [ class scala/Option ]
        frame_type = 7 /* same */
        frame_type = 255 /* full_frame */
          offset_delta = 23
          locals = [ class org/scalatest/events/SuiteAborted, class java/lang/Object, int, class java/lang/Object, class org/scalatest/events/SuiteAborted, class org/scalatest/events/Ordinal, class java/lang/String, class java/lang/String, class java/lang/String, class scala/Option, class scala/Option, class scala/Option, class scala/Option, class scala/Option, class scala/Option, class scala/Option ]
          stack = [ class scala/Option ]
        frame_type = 7 /* same */
        frame_type = 255 /* full_frame */
          offset_delta = 23
          locals = [ class org/scalatest/events/SuiteAborted, class java/lang/Object, int, class java/lang/Object, class org/scalatest/events/SuiteAborted, class org/scalatest/events/Ordinal, class java/lang/String, class java/lang/String, class java/lang/String, class scala/Option, class scala/Option, class scala/Option, class scala/Option, class scala/Option, class scala/Option, class scala/Option, class java/lang/String ]
          stack = [ class java/lang/String ]
        frame_type = 7 /* same */
        frame_type = 255 /* full_frame */
          offset_delta = 3
          locals = [ class org/scalatest/events/SuiteAborted, class java/lang/Object, int, class java/lang/Object, class org/scalatest/events/SuiteAborted ]
          stack = []
        frame_type = 64 /* same_locals_1_stack_item */
          stack = [ int ]
        frame_type = 248 /* chop */
          offset_delta = 2
        frame_type = 253 /* append */
          offset_delta = 3
          locals = [ int, class java/lang/Object ]
        frame_type = 255 /* full_frame */
          offset_delta = 0
          locals = [ class org/scalatest/events/SuiteAborted, class java/lang/Object ]
          stack = [ int ]
      LineNumberTable:
        line 1232: 0
      LocalVariableTable:
        Start  Length  Slot  Name   Signature
            0     448     0  this   Lorg/scalatest/events/SuiteAborted;
            0     448     1   x$1   Ljava/lang/Object;
    MethodParameters:
      Name                           Flags
      x$1                            final

  public org.scalatest.events.Event withPayload(scala.Option);
    descriptor: (Lscala/Option;)Lorg/scalatest/events/Event;
    flags: (0x1041) ACC_PUBLIC, ACC_BRIDGE, ACC_SYNTHETIC
    Code:
      stack=2, locals=2, args_size=2
         0: aload_0
         1: aload_1
         2: invokevirtual #527                // Method withPayload:(Lscala/Option;)Lorg/scalatest/events/SuiteAborted;
         5: areturn
      LineNumberTable:
        line 1232: 0
      LocalVariableTable:
        Start  Length  Slot  Name   Signature
            0       6     0  this   Lorg/scalatest/events/SuiteAborted;
            0       6     1 newPayload   Lscala/Option;
    MethodParameters:
      Name                           Flags
      newPayload                     final

  public static final java.lang.String $anonfun$toJson$10();
    descriptor: ()Ljava/lang/String;
    flags: (0x1019) ACC_PUBLIC, ACC_STATIC, ACC_FINAL, ACC_SYNTHETIC
    Code:
      stack=1, locals=0, args_size=0
         0: ldc_w         #529                // String null
         3: areturn
      LineNumberTable:
        line 1285: 0

  public org.scalatest.events.SuiteAborted(org.scalatest.events.Ordinal, java.lang.String, java.lang.String, java.lang.String, scala.Option<java.lang.String>, scala.Option<java.lang.Throwable>, scala.Option<java.lang.Object>, scala.Option<org.scalatest.events.Formatter>, scala.Option<org.scalatest.events.Location>, scala.Option<java.lang.String>, scala.Option<java.lang.Object>, java.lang.String, long);
    descriptor: (Lorg/scalatest/events/Ordinal;Ljava/lang/String;Ljava/lang/String;Ljava/lang/String;Lscala/Option;Lscala/Option;Lscala/Option;Lscala/Option;Lscala/Option;Lscala/Option;Lscala/Option;Ljava/lang/String;J)V
    flags: (0x0001) ACC_PUBLIC
    Code:
      stack=9, locals=15, args_size=14
         0: aload_0
         1: aload_1
         2: putfield      #134                // Field ordinal:Lorg/scalatest/events/Ordinal;
         5: aload_0
         6: aload_2
         7: putfield      #137                // Field message:Ljava/lang/String;
        10: aload_0
        11: aload_3
        12: putfield      #139                // Field suiteName:Ljava/lang/String;
        15: aload_0
        16: aload         4
        18: putfield      #141                // Field suiteId:Ljava/lang/String;
        21: aload_0
        22: aload         5
        24: putfield      #143                // Field suiteClassName:Lscala/Option;
        27: aload_0
        28: aload         6
        30: putfield      #145                // Field throwable:Lscala/Option;
        33: aload_0
        34: aload         7
        36: putfield      #147                // Field duration:Lscala/Option;
        39: aload_0
        40: aload         8
        42: putfield      #149                // Field formatter:Lscala/Option;
        45: aload_0
        46: aload         9
        48: putfield      #151                // Field location:Lscala/Option;
        51: aload_0
        52: aload         10
        54: putfield      #153                // Field rerunner:Lscala/Option;
        57: aload_0
        58: aload         11
        60: putfield      #155                // Field payload:Lscala/Option;
        63: aload_0
        64: aload         12
        66: putfield      #157                // Field threadName:Ljava/lang/String;
        69: aload_0
        70: lload         13
        72: putfield      #159                // Field timeStamp:J
        75: aload_0
        76: invokespecial #531                // Method org/scalatest/events/Event."<init>":()V
        79: getstatic     #536                // Field org/scalactic/Requirements$.MODULE$:Lorg/scalactic/Requirements$;
        82: invokevirtual #540                // Method org/scalactic/Requirements$.requirementsHelper:()Lorg/scalactic/Requirements$RequirementsHelper;
        85: bipush        12
        87: anewarray     #497                // class java/lang/String
        90: dup
        91: iconst_0
        92: ldc_w         #542                // String SuiteAborted.this.ordinal
        95: aastore
        96: dup
        97: iconst_1
        98: ldc_w         #544                // String SuiteAborted.this.message
       101: aastore
       102: dup
       103: iconst_2
       104: ldc_w         #546                // String SuiteAborted.this.suiteName
       107: aastore
       108: dup
       109: iconst_3
       110: ldc_w         #548                // String SuiteAborted.this.suiteId
       113: aastore
       114: dup
       115: iconst_4
       116: ldc_w         #550                // String SuiteAborted.this.suiteClassName
       119: aastore
       120: dup
       121: iconst_5
       122: ldc_w         #552                // String SuiteAborted.this.throwable
       125: aastore
       126: dup
       127: bipush        6
       129: ldc_w         #554                // String SuiteAborted.this.duration
       132: aastore
       133: dup
       134: bipush        7
       136: ldc_w         #556                // String SuiteAborted.this.formatter
       139: aastore
       140: dup
       141: bipush        8
       143: ldc_w         #558                // String SuiteAborted.this.location
       146: aastore
       147: dup
       148: bipush        9
       150: ldc_w         #560                // String SuiteAborted.this.rerunner
       153: aastore
       154: dup
       155: bipush        10
       157: ldc_w         #562                // String SuiteAborted.this.payload
       160: aastore
       161: dup
       162: bipush        11
       164: ldc_w         #564                // String SuiteAborted.this.threadName
       167: aastore
       168: checkcast     #566                // class "[Ljava/lang/Object;"
       171: checkcast     #568                // class "[Ljava/lang/String;"
       174: bipush        12
       176: anewarray     #477                // class java/lang/Object
       179: dup
       180: iconst_0
       181: aload_1
       182: aastore
       183: dup
       184: iconst_1
       185: aload_2
       186: aastore
       187: dup
       188: iconst_2
       189: aload_3
       190: aastore
       191: dup
       192: iconst_3
       193: aload         4
       195: aastore
       196: dup
       197: iconst_4
       198: aload         5
       200: aastore
       201: dup
       202: iconst_5
       203: aload         6
       205: aastore
       206: dup
       207: bipush        6
       209: aload         7
       211: aastore
       212: dup
       213: bipush        7
       215: aload         8
       217: aastore
       218: dup
       219: bipush        8
       221: aload         9
       223: aastore
       224: dup
       225: bipush        9
       227: aload         10
       229: aastore
       230: dup
       231: bipush        10
       233: aload         11
       235: aastore
       236: dup
       237: bipush        11
       239: aload         12
       241: aastore
       242: checkcast     #566                // class "[Ljava/lang/Object;"
       245: getstatic     #573                // Field org/scalactic/Prettifier$.MODULE$:Lorg/scalactic/Prettifier$;
       248: invokevirtual #577                // Method org/scalactic/Prettifier$.default:()Lorg/scalactic/Prettifier;
       251: new           #579                // class org/scalactic/source/Position
       254: dup
       255: ldc_w         #580                // String Event.scala
       258: ldc_w         #582                // String Please set the environment variable SCALACTIC_FILL_FILE_PATHNAMES to yes at compile time to enable this feature.
       261: sipush        1248
       264: invokespecial #585                // Method org/scalactic/source/Position."<init>":(Ljava/lang/String;Ljava/lang/String;I)V
       267: invokevirtual #589                // Method org/scalactic/Requirements$RequirementsHelper.macroRequireNonNull:([Ljava/lang/String;[Ljava/lang/Object;Lorg/scalactic/Prettifier;Lorg/scalactic/source/Position;)V
       270: return
      LineNumberTable:
        line 1233: 0
        line 1234: 5
        line 1235: 10
        line 1236: 15
        line 1237: 21
        line 1238: 27
        line 1239: 33
        line 1240: 39
        line 1241: 45
        line 1242: 51
        line 1243: 57
        line 1244: 63
        line 1245: 69
        line 1246: 75
        line 1248: 79
        line 1249: 185
        line 1250: 189
        line 1251: 193
        line 1252: 198
        line 1253: 203
        line 1254: 209
        line 1255: 215
        line 1256: 221
        line 1257: 227
        line 1258: 233
        line 1259: 239
        line 1248: 245
        line 1232: 270
      LocalVariableTable:
        Start  Length  Slot  Name   Signature
            0     271     0  this   Lorg/scalatest/events/SuiteAborted;
            0     271     1 ordinal   Lorg/scalatest/events/Ordinal;
            0     271     2 message   Ljava/lang/String;
            0     271     3 suiteName   Ljava/lang/String;
            0     271     4 suiteId   Ljava/lang/String;
            0     271     5 suiteClassName   Lscala/Option;
            0     271     6 throwable   Lscala/Option;
            0     271     7 duration   Lscala/Option;
            0     271     8 formatter   Lscala/Option;
            0     271     9 location   Lscala/Option;
            0     271    10 rerunner   Lscala/Option;
            0     271    11 payload   Lscala/Option;
            0     271    12 threadName   Ljava/lang/String;
            0     271    13 timeStamp   J
    Signature: #530                         // (Lorg/scalatest/events/Ordinal;Ljava/lang/String;Ljava/lang/String;Ljava/lang/String;Lscala/Option<Ljava/lang/String;>;Lscala/Option<Ljava/lang/Throwable;>;Lscala/Option<Ljava/lang/Object;>;Lscala/Option<Lorg/scalatest/events/Formatter;>;Lscala/Option<Lorg/scalatest/events/Location;>;Lscala/Option<Ljava/lang/String;>;Lscala/Option<Ljava/lang/Object;>;Ljava/lang/String;J)V
    MethodParameters:
      Name                           Flags
      ordinal                        final
      message                        final
      suiteName                      final
      suiteId                        final
      suiteClassName                 final
      throwable                      final
      duration                       final
      formatter                      final
      location                       final
      rerunner                       final
      payload                        final
      threadName                     final
      timeStamp                      final

  private static java.lang.Object $deserializeLambda$(java.lang.invoke.SerializedLambda);
    descriptor: (Ljava/lang/invoke/SerializedLambda;)Ljava/lang/Object;
    flags: (0x100a) ACC_PRIVATE, ACC_STATIC, ACC_SYNTHETIC
    Code:
      stack=1, locals=1, args_size=1
         0: aload_0
         1: invokedynamic #601,  0            // InvokeDynamic #1:lambdaDeserialize:(Ljava/lang/invoke/SerializedLambda;)Ljava/lang/Object;
         6: areturn
}
InnerClasses:
  public static final #15= #12 of #14;    // Lookup=class java/lang/invoke/MethodHandles$Lookup of class java/lang/invoke/MethodHandles
  public static #20= #17 of #19;          // RequirementsHelper=class org/scalactic/Requirements$RequirementsHelper of class org/scalactic/Requirements
  public #23= #22 of #4;                  // EventJsonHelper$=class org/scalatest/events/Event$EventJsonHelper$ of class org/scalatest/events/Event
  public #26= #25 of #4;                  // EventXmlHelper$=class org/scalatest/events/Event$EventXmlHelper$ of class org/scalatest/events/Event
SourceFile: "Event.scala"
RuntimeVisibleAnnotations:
  0: #8(#9=s#10)
    scala.reflect.ScalaSignature(
      bytes="\u0006\u0005\t-h\u0001B(Q\u0005^C\u0001\"\u001d\u0001\u0003\u0016\u0004%\tA\u001d\u0005\tm\u0002\u0011\t\u0012)A\u0005g\"Aq\u000f\u0001BK\u0002\u0013\u0005\u0001\u0010C\u0005\u0002\u0004\u0001\u0011\t\u0012)A\u0005s\"I\u0011Q\u0001\u0001\u0003\u0016\u0004%\t\u0001\u001f\u0005\n\u0003\u000f\u0001!\u0011#Q\u0001\neD\u0011\"!\u0003\u0001\u0005+\u0007I\u0011\u0001=\t\u0013\u0005-\u0001A!E!\u0002\u0013I\bBCA\u0007\u0001\tU\r\u0011\"\u0001\u0002\u0010!Q\u0011q\u0003\u0001\u0003\u0012\u0003\u0006I!!\u0005\t\u0015\u0005e\u0001A!f\u0001\n\u0003\tY\u0002\u0003\u0006\u0002&\u0001\u0011\t\u0012)A\u0005\u0003;A!\"a\n\u0001\u0005+\u0007I\u0011AA\u0015\u0011)\t\u0019\u0004\u0001B\tB\u0003%\u00111\u0006\u0005\u000b\u0003k\u0001!Q3A\u0005\u0002\u0005]\u0002BCA!\u0001\tE\t\u0015!\u0003\u0002:!Q\u00111\t\u0001\u0003\u0016\u0004%\t!!\u0012\t\u0015\u0005=\u0003A!E!\u0002\u0013\t9\u0005\u0003\u0006\u0002R\u0001\u0011)\u001a!C\u0001\u0003\u001fA!\"a\u0015\u0001\u0005#\u0005\u000b\u0011BA\t\u0011)\t)\u0006\u0001BK\u0002\u0013\u0005\u0011q\u000b\u0005\u000b\u0003C\u0002!\u0011#Q\u0001\n\u0005e\u0003\"CA2\u0001\tU\r\u0011\"\u0001y\u0011%\t)\u0007\u0001B\tB\u0003%\u0011\u0010\u0003\u0006\u0002h\u0001\u0011)\u001a!C\u0001\u0003SB!\"a\u001b\u0001\u0005#\u0005\u000b\u0011BA\u0017\u0011\u001d\ti\u0007\u0001C\u0001\u0003_B\u0001\"!$\u0001\t\u0003\u0011\u0016q\u0012\u0005\b\u0003;\u0003A\u0011\u0001*y\u0011!\ty\n\u0001C\u0001!\u0006\u0005\u0006\u0002CAT\u0001\u0011\u0005\u0003+!+\t\u0011\u0005=\u0006\u0001\"\u0011S\u0003cC\u0011\"a-\u0001\u0003\u0003%\t!!.\t\u0013\u0005E\u0007!%A\u0005\u0002\u0005M\u0007\"CAu\u0001E\u0005I\u0011AAv\u0011%\ty\u000fAI\u0001\n\u0003\tY\u000fC\u0005\u0002r\u0002\t\n\u0011\"\u0001\u0002l\"I\u00111\u001f\u0001\u0012\u0002\u0013\u0005\u0011Q\u001f\u0005\n\u0003s\u0004\u0011\u0013!C\u0001\u0003wD\u0011\"a@\u0001#\u0003%\tA!\u0001\t\u0013\t\u0015\u0001!%A\u0005\u0002\t\u001d\u0001\"\u0003B\u0006\u0001E\u0005I\u0011\u0001B\u0007\u0011%\u0011\t\u0002AI\u0001\n\u0003\t)\u0010C\u0005\u0003\u0014\u0001\t\n\u0011\"\u0001\u0003\u0016!I!\u0011\u0004\u0001\u0012\u0002\u0013\u0005\u00111\u001e\u0005\n\u00057\u0001\u0011\u0013!C\u0001\u0005;A\u0011B!\t\u0001\u0003\u0003%\tEa\t\t\u0013\tM\u0002!!A\u0005\u0002\tU\u0002\"\u0003B\u001f\u0001\u0005\u0005I\u0011\u0001B \u0011%\u0011)\u0005AA\u0001\n\u0003\u00129\u0005C\u0005\u0003V\u0001\t\t\u0011\"\u0001\u0003X!I!\u0011\r\u0001\u0002\u0002\u0013\u0005#1\r\u0005\n\u0005O\u0002\u0011\u0011!C!\u0005SB\u0011Ba\u001b\u0001\u0003\u0003%\tE!\u001c\t\u0013\t=\u0004!!A\u0005B\tEt!\u0003B;!\u0006\u0005\t\u0012\u0001B<\r!y\u0005+!A\t\u0002\te\u0004bBA7s\u0011\u0005!\u0011\u0013\u0005\n\u0005WJ\u0014\u0011!C#\u0005[B\u0011Ba%:\u0003\u0003%\tI!&\t\u0013\tE\u0016(%A\u0005\u0002\u0005m\b\"\u0003BZsE\u0005I\u0011\u0001B\u0001\u0011%\u0011),OI\u0001\n\u0003\u00119\u0001C\u0005\u00038f\n\n\u0011\"\u0001\u0003\u000e!I!\u0011X\u001d\u0012\u0002\u0013\u0005\u0011Q\u001f\u0005\n\u0005wK\u0014\u0013!C\u0001\u0005+A\u0011B!0:#\u0003%\t!a;\t\u0013\t}\u0016(%A\u0005\u0002\tu\u0001\"\u0003Bas\u0005\u0005I\u0011\u0011Bb\u0011%\u0011\t.OI\u0001\n\u0003\tY\u0010C\u0005\u0003Tf\n\n\u0011\"\u0001\u0003\u0002!I!Q[\u001d\u0012\u0002\u0013\u0005!q\u0001\u0005\n\u0005/L\u0014\u0013!C\u0001\u0005\u001bA\u0011B!7:#\u0003%\t!!>\t\u0013\tm\u0017(%A\u0005\u0002\tU\u0001\"\u0003BosE\u0005I\u0011AAv\u0011%\u0011y.OI\u0001\n\u0003\u0011i\u0002C\u0005\u0003bf\n\t\u0011\"\u0003\u0003d\na1+^5uK\u0006\u0013wN\u001d;fI*\u0011\u0011KU\u0001\u0007KZ,g\u000e^:\u000b\u0005M#\u0016!C:dC2\fG/Z:u\u0015\u0005)\u0016aA8sO\u000e\u00011#\u0002\u0001Y9~+\u0007CA-[\u001b\u0005\u0001\u0016BA.Q\u0005\u0015)e/\u001a8u!\tIV,\u0003\u0002_!\n\u0001R\t_2faRLwN\\1m\u000bZ,g\u000e\u001e\t\u0003A\u000el\u0011!\u0019\u0006\u0002E\u0006)1oY1mC&\u0011A-\u0019\u0002\b!J|G-^2u!\t1gN\u0004\u0002hY:\u0011\u0001n[\u0007\u0002S*\u0011!NV\u0001\u0007yI|w\u000e\u001e \n\u0003\tL!!\\1\u0002\u000fA\f7m[1hK&\u0011q\u000e\u001d\u0002\r\'\u0016\u0014\u0018.\u00197ju\u0006\u0014G.\u001a\u0006\u0003[\u0006\fqa\u001c:eS:\fG.F\u0001t!\tIF/\u0003\u0002v!\n9qJ\u001d3j]\u0006d\u0017\u0001C8sI&t\u0017\r\u001c\u0011\u0002\u000f5,7o]1hKV\t\u0011\u0010\u0005\u0002{}:\u00111\u0010 \t\u0003Q\u0006L!!`1\u0002\rA\u0013X\rZ3g\u0013\ry\u0018\u0011\u0001\u0002\u0007\'R\u0014\u0018N\\4\u000b\u0005u\f\u0017\u0001C7fgN\fw-\u001a\u0011\u0002\u0013M,\u0018\u000e^3OC6,\u0017AC:vSR,g*Y7fA\u000591/^5uK&#\u0017\u0001C:vSR,\u0017\n\u001a\u0011\u0002\u001dM,\u0018\u000e^3DY\u0006\u001c8OT1nKV\u0011\u0011\u0011\u0003\t\u0005A\u0006M\u00110C\u0002\u0002\u0016\u0005\u0014aa\u00149uS>t\u0017aD:vSR,7\t\\1tg:\u000bW.\u001a\u0011\u0002\u0013QD\'o\\<bE2,WCAA\u000f!\u0015\u0001\u00171CA\u0010!\r1\u0017\u0011E\u0005\u0004\u0003G\u0001(!\u0003+ie><\u0018M\u00197f\u0003)!\bN]8xC\ndW\rI\u0001\tIV\u0014\u0018\r^5p]V\u0011\u00111\u0006\t\u0006A\u0006M\u0011Q\u0006\t\u0004A\u0006=\u0012bAA\u0019C\n!Aj\u001c8h\u0003%!WO]1uS>t\u0007%A\u0005g_Jl\u0017\r\u001e;feV\u0011\u0011\u0011\b\t\u0006A\u0006M\u00111\b\t\u00043\u0006u\u0012bAA !\nIai\u001c:nCR$XM]\u0001\u000bM>\u0014X.\u0019;uKJ\u0004\u0013\u0001\u00037pG\u0006$\u0018n\u001c8\u0016\u0005\u0005\u001d\u0003#\u00021\u0002\u0014\u0005%\u0003cA-\u0002L%\u0019\u0011Q\n)\u0003\u00111{7-\u0019;j_:\f\u0011\u0002\\8dCRLwN\u001c\u0011\u0002\u0011I,\'/\u001e8oKJ\f\u0011B]3sk:tWM\u001d\u0011\u0002\u000fA\f\u0017\u0010\\8bIV\u0011\u0011\u0011\f\t\u0006A\u0006M\u00111\f\t\u0004A\u0006u\u0013bAA0C\n\u0019\u0011I\\=\u0002\u0011A\f\u0017\u0010\\8bI\u0002\n!\u0002\u001e5sK\u0006$g*Y7f\u0003-!\bN]3bI:\u000bW.\u001a\u0011\u0002\u0013QLW.Z*uC6\u0004XCAA\u0017\u0003)!\u0018.\\3Ti\u0006l\u0007\u000fI\u0001\u0007y%t\u0017\u000e\u001e \u00159\u0005E\u00141OA;\u0003o\nI(a\u001f\u0002~\u0005}\u0014\u0011QAB\u0003\u000b\u000b9)!#\u0002\fB\u0011\u0011\f\u0001\u0005\u0006cn\u0001\ra\u001d\u0005\u0006on\u0001\r!\u001f\u0005\u0007\u0003\u000bY\u0002\u0019A=\t\r\u0005%1\u00041\u0001z\u0011\u001d\tia\u0007a\u0001\u0003#A\u0011\"!\u0007\u001c!\u0003\u0005\r!!\b\t\u0013\u0005\u001d2\u0004%AA\u0002\u0005-\u0002\"CA\u001b7A\u0005\t\u0019AA\u001d\u0011%\t\u0019e\u0007I\u0001\u0002\u0004\t9\u0005C\u0005\u0002Rm\u0001\n\u00111\u0001\u0002\u0012!I\u0011QK\u000e\u0011\u0002\u0003\u0007\u0011\u0011\f\u0005\t\u0003GZ\u0002\u0013!a\u0001s\"I\u0011qM\u000e\u0011\u0002\u0003\u0007\u0011QF\u0001\u0006i>DV\u000e\\\u000b\u0003\u0003#\u0003B!a%\u0002\u001a6\u0011\u0011Q\u0013\u0006\u0004\u0003/\u000b\u0017a\u0001=nY&!\u00111TAK\u0005\u0011)E.Z7\u0002\rQ|\'j]8o\u0003-9\u0018\u000e\u001e5QCfdw.\u00193\u0015\t\u0005E\u00141\u0015\u0005\b\u0003Ks\u0002\u0019AA-\u0003)qWm\u001e)bs2|\u0017\rZ\u0001\u000eo&$\b\u000e\u00165s_^\f\'\r\\3\u0015\u0007a\u000bY\u000bC\u0004\u0002.~\u0001\r!!\b\u0002\u00199,w\u000f\u00165s_^\f\'\r\\3\u0002%\u0015t7/\u001e:f\'\u0016\u0014\u0018.\u00197ju\u0006\u0014G.\u001a\u000b\u00021\u0006!1m\u001c9z)q\t\t(a.\u0002:\u0006m\u0016QXA`\u0003\u0003\f\u0019-!2\u0002H\u0006%\u00171ZAg\u0003\u001fDq!]\u0011\u0011\u0002\u0003\u00071\u000fC\u0004xCA\u0005\t\u0019A=\t\u0011\u0005\u0015\u0011\u0005%AA\u0002eD\u0001\"!\u0003\"!\u0003\u0005\r!\u001f\u0005\n\u0003\u001b\t\u0003\u0013!a\u0001\u0003#A\u0011\"!\u0007\"!\u0003\u0005\r!!\b\t\u0013\u0005\u001d\u0012\u0005%AA\u0002\u0005-\u0002\"CA\u001bCA\u0005\t\u0019AA\u001d\u0011%\t\u0019%\tI\u0001\u0002\u0004\t9\u0005C\u0005\u0002R\u0005\u0002\n\u00111\u0001\u0002\u0012!I\u0011QK\u0011\u0011\u0002\u0003\u0007\u0011\u0011\f\u0005\t\u0003G\n\u0003\u0013!a\u0001s\"I\u0011qM\u0011\u0011\u0002\u0003\u0007\u0011QF\u0001\u000fG>\u0004\u0018\u0010\n3fM\u0006,H\u000e\u001e\u00132+\t\t)NK\u0002t\u0003/\\#!!7\u0011\t\u0005m\u0017Q]\u0007\u0003\u0003;TA!a8\u0002b\u0006IQO\\2iK\u000e\\W\r\u001a\u0006\u0004\u0003G\f\u0017AC1o]>$\u0018\r^5p]&!\u0011q]Ao\u0005E)hn\u00195fG.,GMV1sS\u0006t7-Z\u0001\u000fG>\u0004\u0018\u0010\n3fM\u0006,H\u000e\u001e\u00133+\t\tiOK\u0002z\u0003/\fabY8qs\u0012\"WMZ1vYR$3\'\u0001\bd_BLH\u0005Z3gCVdG\u000f\n\u001b\u0002\u001d\r|\u0007/\u001f\u0013eK\u001a\fW\u000f\u001c;%kU\u0011\u0011q\u001f\u0016\u0005\u0003#\t9.\u0001\bd_BLH\u0005Z3gCVdG\u000f\n\u001c\u0016\u0005\u0005u(\u0006BA\u000f\u0003/\fabY8qs\u0012\"WMZ1vYR$s\'\u0006\u0002\u0003\u0004)\"\u00111FAl\u00039\u0019w\u000e]=%I\u00164\u0017-\u001e7uIa*\"A!\u0003+\t\u0005e\u0012q[\u0001\u000fG>\u0004\u0018\u0010\n3fM\u0006,H\u000e\u001e\u0013:+\t\u0011yA\u000b\u0003\u0002H\u0005]\u0017aD2paf$C-\u001a4bk2$H%\r\u0019\u0002\u001f\r|\u0007/\u001f\u0013eK\u001a\fW\u000f\u001c;%cE*\"Aa\u0006+\t\u0005e\u0013q[\u0001\u0010G>\u0004\u0018\u0010\n3fM\u0006,H\u000e\u001e\u00132e\u0005y1m\u001c9zI\u0011,g-Y;mi\u0012\n4\'\u0006\u0002\u0003 )\"\u0011QFAl\u00035\u0001(o\u001c3vGR\u0004&/\u001a4jqV\u0011!Q\u0005\t\u0005\u0005O\u0011\t$\u0004\u0002\u0003*)!!1\u0006B\u0017\u0003\u0011a\u0017M\\4\u000b\u0005\t=\u0012\u0001\u00026bm\u0006L1a B\u0015\u00031\u0001(o\u001c3vGR\f%/\u001b;z+\t\u00119\u0004E\u0002a\u0005sI1Aa\u000fb\u0005\rIe\u000e^\u0001\u000faJ|G-^2u\u000b2,W.\u001a8u)\u0011\tYF!\u0011\t\u0013\t\r\u0013\'!AA\u0002\t]\u0012a\u0001=%c\u0005y\u0001O]8ek\u000e$\u0018\n^3sCR|\'/\u0006\u0002\u0003JA1!1\nB)\u00037j!A!\u0014\u000b\u0007\t=\u0013-\u0001\u0006d_2dWm\u0019;j_:LAAa\u0015\u0003N\tA\u0011\n^3sCR|\'/\u0001\u0005dC:,\u0015/^1m)\u0011\u0011IFa\u0018\u0011\u0007\u0001\u0014Y&C\u0002\u0003^\u0005\u0014qAQ8pY\u0016\fg\u000eC\u0005\u0003DM\n\t\u00111\u0001\u0002\\\u0005\u0011\u0002O]8ek\u000e$X\t\\3nK:$h*Y7f)\u0011\u0011)C!\u001a\t\u0013\t\rC\'!AA\u0002\t]\u0012\u0001\u00035bg\"\u001cu\u000eZ3\u0015\u0005\t]\u0012\u0001\u0003;p\'R\u0014\u0018N\\4\u0015\u0005\t\u0015\u0012AB3rk\u0006d7\u000f\u0006\u0003\u0003Z\tM\u0004\"\u0003B\"o\u0005\u0005\t\u0019AA.\u00031\u0019V/\u001b;f\u0003\n|\'\u000f^3e!\tI\u0016hE\u0003:\u0005w\u00129\tE\u000e\u0003~\t\r5/_=z\u0003#\ti\"a\u000b\u0002:\u0005\u001d\u0013\u0011CA-s\u00065\u0012\u0011O\u0007\u0003\u0005\u007fR1A!!b\u0003\u001d\u0011XO\u001c;j[\u0016LAA!\"\u0003\u0000\t\u0011\u0012IY:ue\u0006\u001cGOR;oGRLwN\\\u00194!\u0011\u0011IIa$\u000e\u0005\t-%\u0002\u0002BG\u0005[\t!![8\n\u0007=\u0014Y\t\u0006\u0002\u0003x\u0005)\u0011\r\u001d9msRa\u0012\u0011\u000fBL\u00053\u0013YJ!(\u0003 \n\u0005&1\u0015BS\u0005O\u0013IKa+\u0003.\n=\u0006\"B9=\u0001\u0004\u0019\b\"B<=\u0001\u0004I\bBBA\u0003y\u0001\u0007\u0011\u0010\u0003\u0004\u0002\nq\u0002\r!\u001f\u0005\b\u0003\u001ba\u0004\u0019AA\t\u0011%\tI\u0002\u0010I\u0001\u0002\u0004\ti\u0002C\u0005\u0002(q\u0002\n\u00111\u0001\u0002,!I\u0011Q\u0007\u001f\u0011\u0002\u0003\u0007\u0011\u0011\b\u0005\n\u0003\u0007b\u0004\u0013!a\u0001\u0003\u000fB\u0011\"!\u0015=!\u0003\u0005\r!!\u0005\t\u0013\u0005UC\b%AA\u0002\u0005e\u0003\u0002CA2yA\u0005\t\u0019A=\t\u0013\u0005\u001dD\b%AA\u0002\u00055\u0012aD1qa2LH\u0005Z3gCVdG\u000f\n\u001c\u0002\u001f\u0005\u0004\b\u000f\\=%I\u00164\u0017-\u001e7uI]\nq\"\u00199qYf$C-\u001a4bk2$H\u0005O\u0001\u0010CB\u0004H.\u001f\u0013eK\u001a\fW\u000f\u001c;%s\u0005\u0001\u0012\r\u001d9ms\u0012\"WMZ1vYR$\u0013\u0007M\u0001\u0011CB\u0004H.\u001f\u0013eK\u001a\fW\u000f\u001c;%cE\n\u0001#\u00199qYf$C-\u001a4bk2$H%\r\u001a\u0002!\u0005\u0004\b\u000f\\=%I\u00164\u0017-\u001e7uIE\u001a\u0014aB;oCB\u0004H.\u001f\u000b\u0005\u0005\u000b\u0014i\rE\u0003a\u0003\'\u00119\r\u0005\ra\u0005\u0013\u001c\u00180_=\u0002\u0012\u0005u\u00111FA\u001d\u0003\u000f\n\t\"!\u0017z\u0003[I1Aa3b\u0005\u001d!V\u000f\u001d7fcMB\u0011Ba4F\u0003\u0003\u0005\r!!\u001d\u0002\u0007a$\u0003\'A\u000e%Y\u0016\u001c8/\u001b8ji\u0012:\'/Z1uKJ$C-\u001a4bk2$HEN\u0001\u001cI1,7o]5oSR$sM]3bi\u0016\u0014H\u0005Z3gCVdG\u000fJ\u001c\u00027\u0011bWm]:j]&$He\u001a:fCR,\'\u000f\n3fM\u0006,H\u000e\u001e\u00139\u0003m!C.Z:tS:LG\u000fJ4sK\u0006$XM\u001d\u0013eK\u001a\fW\u000f\u001c;%s\u0005aB\u0005\\3tg&t\u0017\u000e\u001e\u0013he\u0016\fG/\u001a:%I\u00164\u0017-\u001e7uIE\u0002\u0014\u0001\b\u0013mKN\u001c\u0018N\\5uI\u001d\u0014X-\u0019;fe\u0012\"WMZ1vYR$\u0013\'M\u0001\u001dI1,7o]5oSR$sM]3bi\u0016\u0014H\u0005Z3gCVdG\u000fJ\u00193\u0003q!C.Z:tS:LG\u000fJ4sK\u0006$XM\u001d\u0013eK\u001a\fW\u000f\u001c;%cM\nAb\u001e:ji\u0016\u0014V\r\u001d7bG\u0016$\"A!:\u0011\t\t\u001d\"q]\u0005\u0005\u0005S\u0014IC\u0001\u0004PE*,7\r\u001e"
    )
BootstrapMethods:
  0: #345 REF_invokeStatic java/lang/invoke/LambdaMetafactory.altMetafactory:(Ljava/lang/invoke/MethodHandles$Lookup;Ljava/lang/String;Ljava/lang/invoke/MethodType;[Ljava/lang/Object;)Ljava/lang/invoke/CallSite;
    Method arguments:
      #331 ()Ljava/lang/Object;
      #335 REF_invokeStatic org/scalatest/events/SuiteAborted.$anonfun$toJson$10:()Ljava/lang/String;
      #336 ()Ljava/lang/String;
      #337 5
      #338 1
      #336 ()Ljava/lang/String;
  1: #598 REF_invokeStatic scala/runtime/LambdaDeserialize.bootstrap:(Ljava/lang/invoke/MethodHandles$Lookup;Ljava/lang/String;Ljava/lang/invoke/MethodType;[Ljava/lang/invoke/MethodHandle;)Ljava/lang/invoke/CallSite;
    Method arguments:
      #335 REF_invokeStatic org/scalatest/events/SuiteAborted.$anonfun$toJson$10:()Ljava/lang/String;
  ScalaInlineInfo: length = 0xE0 (unknown attribute)
   01 01 00 2C 01 4C 00 3C 01 00 B7 01 CF 01 01 EA
   01 EB 01 01 AE 00 77 01 01 8A 00 84 01 01 A5 00
   40 01 01 C2 00 40 01 01 A8 00 3C 01 01 AB 00 32
   01 01 8D 00 3C 01 01 90 00 3C 01 01 93 00 3C 01
   01 96 00 40 01 01 99 00 40 01 01 9C 00 40 01 01
   9F 00 40 01 01 A2 00 40 01 00 26 00 40 01 01 C5
   01 C6 01 02 0B 01 EB 01 00 28 00 40 01 01 F2 00
   CF 01 00 2A 00 40 01 00 1D 00 3C 01 00 1B 00 84
   01 00 2D 00 40 01 01 D3 00 CF 01 01 D4 01 D5 01
   01 ED 01 EE 01 01 DE 01 DF 01 01 D2 00 3C 01 00
   2C 00 40 01 00 21 00 40 01 00 20 00 3C 01 00 1F
   00 3C 01 00 2E 00 3C 01 00 24 00 40 01 00 2F 00
   32 01 01 1D 00 3C 01 01 7D 00 3C 01 00 A0 00 A1
   01 01 86 01 BF 01 01 86 01 87 01 01 BE 01 BF 01

  ScalaSig: length = 0x3 (unknown attribute)
   05 02 00
