Classfile /Users/mw/Projects/slang-braindump/.jar/jar11/assemble/slang-braindump/assemble/content/com/fasterxml/jackson/databind/ext/DOMDeserializer$DocumentDeserializer.class
  Last modified May 29, 2022; size 1270 bytes
  SHA-256 checksum 36185b922ab0af9c4ec0ab53e32a8b019cb4440ff174a24ad3677eca90c5cd3b
  Compiled from "DOMDeserializer.java"
public class com.fasterxml.jackson.databind.ext.DOMDeserializer$DocumentDeserializer extends com.fasterxml.jackson.databind.ext.DOMDeserializer<org.w3c.dom.Document>
  minor version: 0
  major version: 52
  flags: (0x0021) ACC_PUBLIC, ACC_SUPER
  this_class: #5                          // com/fasterxml/jackson/databind/ext/DOMDeserializer$DocumentDeserializer
  super_class: #6                         // com/fasterxml/jackson/databind/ext/DOMDeserializer
  interfaces: 0, fields: 1, methods: 3, attributes: 3
Constant pool:
   #1 = Class              #34            // org/w3c/dom/Document
   #2 = Methodref          #6.#35         // com/fasterxml/jackson/databind/ext/DOMDeserializer."<init>":(Ljava/lang/Class;)V
   #3 = Methodref          #5.#36         // com/fasterxml/jackson/databind/ext/DOMDeserializer$DocumentDeserializer.parse:(Ljava/lang/String;)Lorg/w3c/dom/Document;
   #4 = Methodref          #5.#37         // com/fasterxml/jackson/databind/ext/DOMDeserializer$DocumentDeserializer._deserialize:(Ljava/lang/String;Lcom/fasterxml/jackson/databind/DeserializationContext;)Lorg/w3c/dom/Document;
   #5 = Class              #38            // com/fasterxml/jackson/databind/ext/DOMDeserializer$DocumentDeserializer
   #6 = Class              #39            // com/fasterxml/jackson/databind/ext/DOMDeserializer
   #7 = Utf8               serialVersionUID
   #8 = Utf8               J
   #9 = Utf8               ConstantValue
  #10 = Long               1l
  #12 = Utf8               <init>
  #13 = Utf8               ()V
  #14 = Utf8               Code
  #15 = Utf8               LineNumberTable
  #16 = Utf8               LocalVariableTable
  #17 = Utf8               this
  #18 = Utf8               DocumentDeserializer
  #19 = Utf8               InnerClasses
  #20 = Utf8               Lcom/fasterxml/jackson/databind/ext/DOMDeserializer$DocumentDeserializer;
  #21 = Utf8               _deserialize
  #22 = Utf8               (Ljava/lang/String;Lcom/fasterxml/jackson/databind/DeserializationContext;)Lorg/w3c/dom/Document;
  #23 = Utf8               value
  #24 = Utf8               Ljava/lang/String;
  #25 = Utf8               ctxt
  #26 = Utf8               Lcom/fasterxml/jackson/databind/DeserializationContext;
  #27 = Utf8               Exceptions
  #28 = Class              #40            // java/lang/IllegalArgumentException
  #29 = Utf8               (Ljava/lang/String;Lcom/fasterxml/jackson/databind/DeserializationContext;)Ljava/lang/Object;
  #30 = Utf8               Signature
  #31 = Utf8               Lcom/fasterxml/jackson/databind/ext/DOMDeserializer<Lorg/w3c/dom/Document;>;
  #32 = Utf8               SourceFile
  #33 = Utf8               DOMDeserializer.java
  #34 = Utf8               org/w3c/dom/Document
  #35 = NameAndType        #12:#41        // "<init>":(Ljava/lang/Class;)V
  #36 = NameAndType        #42:#43        // parse:(Ljava/lang/String;)Lorg/w3c/dom/Document;
  #37 = NameAndType        #21:#22        // _deserialize:(Ljava/lang/String;Lcom/fasterxml/jackson/databind/DeserializationContext;)Lorg/w3c/dom/Document;
  #38 = Utf8               com/fasterxml/jackson/databind/ext/DOMDeserializer$DocumentDeserializer
  #39 = Utf8               com/fasterxml/jackson/databind/ext/DOMDeserializer
  #40 = Utf8               java/lang/IllegalArgumentException
  #41 = Utf8               (Ljava/lang/Class;)V
  #42 = Utf8               parse
  #43 = Utf8               (Ljava/lang/String;)Lorg/w3c/dom/Document;
{
  private static final long serialVersionUID;
    descriptor: J
    flags: (0x001a) ACC_PRIVATE, ACC_STATIC, ACC_FINAL
    ConstantValue: long 1l

  public com.fasterxml.jackson.databind.ext.DOMDeserializer$DocumentDeserializer();
    descriptor: ()V
    flags: (0x0001) ACC_PUBLIC
    Code:
      stack=2, locals=1, args_size=1
         0: aload_0
         1: ldc           #1                  // class org/w3c/dom/Document
         3: invokespecial #2                  // Method com/fasterxml/jackson/databind/ext/DOMDeserializer."<init>":(Ljava/lang/Class;)V
         6: return
      LineNumberTable:
        line 93: 0
      LocalVariableTable:
        Start  Length  Slot  Name   Signature
            0       7     0  this   Lcom/fasterxml/jackson/databind/ext/DOMDeserializer$DocumentDeserializer;

  public org.w3c.dom.Document _deserialize(java.lang.String, com.fasterxml.jackson.databind.DeserializationContext) throws java.lang.IllegalArgumentException;
    descriptor: (Ljava/lang/String;Lcom/fasterxml/jackson/databind/DeserializationContext;)Lorg/w3c/dom/Document;
    flags: (0x0001) ACC_PUBLIC
    Code:
      stack=2, locals=3, args_size=3
         0: aload_0
         1: aload_1
         2: invokevirtual #3                  // Method parse:(Ljava/lang/String;)Lorg/w3c/dom/Document;
         5: areturn
      LineNumberTable:
        line 96: 0
      LocalVariableTable:
        Start  Length  Slot  Name   Signature
            0       6     0  this   Lcom/fasterxml/jackson/databind/ext/DOMDeserializer$DocumentDeserializer;
            0       6     1 value   Ljava/lang/String;
            0       6     2  ctxt   Lcom/fasterxml/jackson/databind/DeserializationContext;
    Exceptions:
      throws java.lang.IllegalArgumentException

  public java.lang.Object _deserialize(java.lang.String, com.fasterxml.jackson.databind.DeserializationContext);
    descriptor: (Ljava/lang/String;Lcom/fasterxml/jackson/databind/DeserializationContext;)Ljava/lang/Object;
    flags: (0x1041) ACC_PUBLIC, ACC_BRIDGE, ACC_SYNTHETIC
    Code:
      stack=3, locals=3, args_size=3
         0: aload_0
         1: aload_1
         2: aload_2
         3: invokevirtual #4                  // Method _deserialize:(Ljava/lang/String;Lcom/fasterxml/jackson/databind/DeserializationContext;)Lorg/w3c/dom/Document;
         6: areturn
      LineNumberTable:
        line 91: 0
      LocalVariableTable:
        Start  Length  Slot  Name   Signature
            0       7     0  this   Lcom/fasterxml/jackson/databind/ext/DOMDeserializer$DocumentDeserializer;
}
Signature: #31                          // Lcom/fasterxml/jackson/databind/ext/DOMDeserializer<Lorg/w3c/dom/Document;>;
SourceFile: "DOMDeserializer.java"
InnerClasses:
  public static #18= #5 of #6;            // DocumentDeserializer=class com/fasterxml/jackson/databind/ext/DOMDeserializer$DocumentDeserializer of class com/fasterxml/jackson/databind/ext/DOMDeserializer
