Classfile /Users/mw/Projects/slang-braindump/.jar/jar8/assemble/slang-braindump/assemble/content/scala/math/Equiv$ExtraImplicits.class
  Last modified May 29, 2022; size 1430 bytes
  SHA-256 checksum 677dd45cd5dff6e63d73c59bc72a9e5983461840ed1cc29a0f0bc9cf664d05a3
  Compiled from "Equiv.scala"
public interface scala.math.Equiv$ExtraImplicits
  minor version: 0
  major version: 52
  flags: (0x0601) ACC_PUBLIC, ACC_INTERFACE, ACC_ABSTRACT
  this_class: #2                          // scala/math/Equiv$ExtraImplicits
  super_class: #4                         // java/lang/Object
  interfaces: 0, fields: 0, methods: 5, attributes: 4
Constant pool:
   #1 = Utf8               scala/math/Equiv$ExtraImplicits
   #2 = Class              #1             // scala/math/Equiv$ExtraImplicits
   #3 = Utf8               java/lang/Object
   #4 = Class              #3             // java/lang/Object
   #5 = Utf8               Equiv.scala
   #6 = Utf8               scala/math/Equiv
   #7 = Class              #6             // scala/math/Equiv
   #8 = Utf8               ExtraImplicits
   #9 = Utf8               scala/math/Equiv$IterableEquiv
  #10 = Class              #9             // scala/math/Equiv$IterableEquiv
  #11 = Utf8               IterableEquiv
  #12 = Utf8               seqEquiv$
  #13 = Utf8               (Lscala/math/Equiv$ExtraImplicits;Lscala/math/Equiv;)Lscala/math/Equiv;
  #14 = Utf8               $this
  #15 = Utf8               eqv
  #16 = Utf8               seqEquiv
  #17 = Utf8               (Lscala/math/Equiv;)Lscala/math/Equiv;
  #18 = NameAndType        #16:#17        // seqEquiv:(Lscala/math/Equiv;)Lscala/math/Equiv;
  #19 = InterfaceMethodref #2.#18         // scala/math/Equiv$ExtraImplicits.seqEquiv:(Lscala/math/Equiv;)Lscala/math/Equiv;
  #20 = Utf8               Lscala/math/Equiv$ExtraImplicits;
  #21 = Utf8               Lscala/math/Equiv;
  #22 = Utf8               <CC::Lscala/collection/Seq<Ljava/lang/Object;>;T:Ljava/lang/Object;>(Lscala/math/Equiv<TT;>;)Lscala/math/Equiv<TCC;>;
  #23 = Utf8               <init>
  #24 = Utf8               (Lscala/math/Equiv;)V
  #25 = NameAndType        #23:#24        // "<init>":(Lscala/math/Equiv;)V
  #26 = Methodref          #10.#25        // scala/math/Equiv$IterableEquiv."<init>":(Lscala/math/Equiv;)V
  #27 = Utf8               this
  #28 = Utf8               sortedSetEquiv$
  #29 = Utf8               sortedSetEquiv
  #30 = NameAndType        #29:#17        // sortedSetEquiv:(Lscala/math/Equiv;)Lscala/math/Equiv;
  #31 = InterfaceMethodref #2.#30         // scala/math/Equiv$ExtraImplicits.sortedSetEquiv:(Lscala/math/Equiv;)Lscala/math/Equiv;
  #32 = Utf8               <CC::Lscala/collection/SortedSet<Ljava/lang/Object;>;T:Ljava/lang/Object;>(Lscala/math/Equiv<TT;>;)Lscala/math/Equiv<TCC;>;
  #33 = Utf8               $init$
  #34 = Utf8               (Lscala/math/Equiv$ExtraImplicits;)V
  #35 = Utf8               Code
  #36 = Utf8               LineNumberTable
  #37 = Utf8               LocalVariableTable
  #38 = Utf8               MethodParameters
  #39 = Utf8               Signature
  #40 = Utf8               InnerClasses
  #41 = Utf8               SourceFile
  #42 = Utf8               ScalaInlineInfo
  #43 = Utf8               Scala
{
  public static scala.math.Equiv seqEquiv$(scala.math.Equiv$ExtraImplicits, scala.math.Equiv);
    descriptor: (Lscala/math/Equiv$ExtraImplicits;Lscala/math/Equiv;)Lscala/math/Equiv;
    flags: (0x1009) ACC_PUBLIC, ACC_STATIC, ACC_SYNTHETIC
    Code:
      stack=2, locals=2, args_size=2
         0: aload_0
         1: aload_1
         2: invokespecial #19                 // InterfaceMethod seqEquiv:(Lscala/math/Equiv;)Lscala/math/Equiv;
         5: areturn
      LineNumberTable:
        line 100: 0
      LocalVariableTable:
        Start  Length  Slot  Name   Signature
            0       6     0 $this   Lscala/math/Equiv$ExtraImplicits;
            0       6     1   eqv   Lscala/math/Equiv;
    MethodParameters:
      Name                           Flags
      $this                          final synthetic
      eqv                            final

  public default <CC extends scala.collection.Seq<java.lang.Object>, T extends java.lang.Object> scala.math.Equiv<CC> seqEquiv(scala.math.Equiv<T>);
    descriptor: (Lscala/math/Equiv;)Lscala/math/Equiv;
    flags: (0x0001) ACC_PUBLIC
    Code:
      stack=3, locals=2, args_size=2
         0: new           #10                 // class scala/math/Equiv$IterableEquiv
         3: dup
         4: aload_1
         5: invokespecial #26                 // Method scala/math/Equiv$IterableEquiv."<init>":(Lscala/math/Equiv;)V
         8: areturn
      LineNumberTable:
        line 101: 0
      LocalVariableTable:
        Start  Length  Slot  Name   Signature
            0       9     0  this   Lscala/math/Equiv$ExtraImplicits;
            0       9     1   eqv   Lscala/math/Equiv;
    Signature: #22                          // <CC::Lscala/collection/Seq<Ljava/lang/Object;>;T:Ljava/lang/Object;>(Lscala/math/Equiv<TT;>;)Lscala/math/Equiv<TCC;>;
    MethodParameters:
      Name                           Flags
      eqv                            final

  public static scala.math.Equiv sortedSetEquiv$(scala.math.Equiv$ExtraImplicits, scala.math.Equiv);
    descriptor: (Lscala/math/Equiv$ExtraImplicits;Lscala/math/Equiv;)Lscala/math/Equiv;
    flags: (0x1009) ACC_PUBLIC, ACC_STATIC, ACC_SYNTHETIC
    Code:
      stack=2, locals=2, args_size=2
         0: aload_0
         1: aload_1
         2: invokespecial #31                 // InterfaceMethod sortedSetEquiv:(Lscala/math/Equiv;)Lscala/math/Equiv;
         5: areturn
      LineNumberTable:
        line 103: 0
      LocalVariableTable:
        Start  Length  Slot  Name   Signature
            0       6     0 $this   Lscala/math/Equiv$ExtraImplicits;
            0       6     1   eqv   Lscala/math/Equiv;
    MethodParameters:
      Name                           Flags
      $this                          final synthetic
      eqv                            final

  public default <CC extends scala.collection.SortedSet<java.lang.Object>, T extends java.lang.Object> scala.math.Equiv<CC> sortedSetEquiv(scala.math.Equiv<T>);
    descriptor: (Lscala/math/Equiv;)Lscala/math/Equiv;
    flags: (0x0001) ACC_PUBLIC
    Code:
      stack=3, locals=2, args_size=2
         0: new           #10                 // class scala/math/Equiv$IterableEquiv
         3: dup
         4: aload_1
         5: invokespecial #26                 // Method scala/math/Equiv$IterableEquiv."<init>":(Lscala/math/Equiv;)V
         8: areturn
      LineNumberTable:
        line 104: 0
      LocalVariableTable:
        Start  Length  Slot  Name   Signature
            0       9     0  this   Lscala/math/Equiv$ExtraImplicits;
            0       9     1   eqv   Lscala/math/Equiv;
    Signature: #32                          // <CC::Lscala/collection/SortedSet<Ljava/lang/Object;>;T:Ljava/lang/Object;>(Lscala/math/Equiv<TT;>;)Lscala/math/Equiv<TCC;>;
    MethodParameters:
      Name                           Flags
      eqv                            final

  public static void $init$(scala.math.Equiv$ExtraImplicits);
    descriptor: (Lscala/math/Equiv$ExtraImplicits;)V
    flags: (0x0009) ACC_PUBLIC, ACC_STATIC
    Code:
      stack=0, locals=1, args_size=1
         0: return
      LineNumberTable:
        line 96: 0
      LocalVariableTable:
        Start  Length  Slot  Name   Signature
            0       1     0 $this   Lscala/math/Equiv$ExtraImplicits;
    MethodParameters:
      Name                           Flags
      $this                          final synthetic
}
InnerClasses:
  public static #8= #2 of #7;             // ExtraImplicits=class scala/math/Equiv$ExtraImplicits of class scala/math/Equiv
  private static final #11= #10 of #7;    // IterableEquiv=class scala/math/Equiv$IterableEquiv of class scala/math/Equiv
SourceFile: "Equiv.scala"
  ScalaInlineInfo: length = 0x1D (unknown attribute)
   01 00 00 05 00 21 00 22 01 00 10 00 11 00 00 0C
   00 0D 01 00 1D 00 11 00 00 1C 00 0D 01
  Scala: length = 0x0 (unknown attribute)

