Classfile /Users/mw/Projects/slang-braindump/.jar/jar8/assemble/slang-braindump/assemble/content/scala/math/Equiv$Double$.class
  Last modified May 29, 2022; size 730 bytes
  SHA-256 checksum c9d9723744d03ea249f3630af47bbb04612f22dd32c24f5102c131e85a281ffe
  Compiled from "Equiv.scala"
public class scala.math.Equiv$Double$
  minor version: 0
  major version: 52
  flags: (0x0021) ACC_PUBLIC, ACC_SUPER
  this_class: #2                          // scala/math/Equiv$Double$
  super_class: #4                         // java/lang/Object
  interfaces: 0, fields: 1, methods: 2, attributes: 4
Constant pool:
   #1 = Utf8               scala/math/Equiv$Double$
   #2 = Class              #1             // scala/math/Equiv$Double$
   #3 = Utf8               java/lang/Object
   #4 = Class              #3             // java/lang/Object
   #5 = Utf8               Equiv.scala
   #6 = Utf8               scala/math/Equiv
   #7 = Class              #6             // scala/math/Equiv
   #8 = Utf8               Double$
   #9 = Utf8               scala/math/Equiv$Double$IeeeEquiv
  #10 = Class              #9             // scala/math/Equiv$Double$IeeeEquiv
  #11 = Utf8               IeeeEquiv
  #12 = Utf8               scala/math/Equiv$Double$IeeeEquiv$
  #13 = Class              #12            // scala/math/Equiv$Double$IeeeEquiv$
  #14 = Utf8               IeeeEquiv$
  #15 = Utf8               scala/math/Equiv$Double$StrictEquiv
  #16 = Class              #15            // scala/math/Equiv$Double$StrictEquiv
  #17 = Utf8               StrictEquiv
  #18 = Utf8               scala/math/Equiv$Double$StrictEquiv$
  #19 = Class              #18            // scala/math/Equiv$Double$StrictEquiv$
  #20 = Utf8               StrictEquiv$
  #21 = Utf8               MODULE$
  #22 = Utf8               Lscala/math/Equiv$Double$;
  #23 = Utf8               <clinit>
  #24 = Utf8               ()V
  #25 = Utf8               <init>
  #26 = NameAndType        #25:#24        // "<init>":()V
  #27 = Methodref          #2.#26         // scala/math/Equiv$Double$."<init>":()V
  #28 = NameAndType        #21:#22        // MODULE$:Lscala/math/Equiv$Double$;
  #29 = Fieldref           #2.#28         // scala/math/Equiv$Double$.MODULE$:Lscala/math/Equiv$Double$;
  #30 = Methodref          #4.#26         // java/lang/Object."<init>":()V
  #31 = Utf8               this
  #32 = Utf8               Code
  #33 = Utf8               LineNumberTable
  #34 = Utf8               LocalVariableTable
  #35 = Utf8               InnerClasses
  #36 = Utf8               SourceFile
  #37 = Utf8               ScalaInlineInfo
  #38 = Utf8               Scala
{
  public static final scala.math.Equiv$Double$ MODULE$;
    descriptor: Lscala/math/Equiv$Double$;
    flags: (0x0019) ACC_PUBLIC, ACC_STATIC, ACC_FINAL

  public static {};
    descriptor: ()V
    flags: (0x0009) ACC_PUBLIC, ACC_STATIC
    Code:
      stack=2, locals=0, args_size=0
         0: new           #2                  // class scala/math/Equiv$Double$
         3: dup
         4: invokespecial #27                 // Method "<init>":()V
         7: putstatic     #29                 // Field MODULE$:Lscala/math/Equiv$Double$;
        10: return
      LineNumberTable:
        line 195: 0

  public scala.math.Equiv$Double$();
    descriptor: ()V
    flags: (0x0001) ACC_PUBLIC
    Code:
      stack=1, locals=1, args_size=1
         0: aload_0
         1: invokespecial #30                 // Method java/lang/Object."<init>":()V
         4: return
      LineNumberTable:
        line 195: 0
      LocalVariableTable:
        Start  Length  Slot  Name   Signature
            0       5     0  this   Lscala/math/Equiv$Double$;
}
InnerClasses:
  public static #8= #2 of #7;             // Double$=class scala/math/Equiv$Double$ of class scala/math/Equiv
  public static #11= #10 of #2;           // IeeeEquiv=class scala/math/Equiv$Double$IeeeEquiv of class scala/math/Equiv$Double$
  public static #14= #13 of #2;           // IeeeEquiv$=class scala/math/Equiv$Double$IeeeEquiv$ of class scala/math/Equiv$Double$
  public static #17= #16 of #2;           // StrictEquiv=class scala/math/Equiv$Double$StrictEquiv of class scala/math/Equiv$Double$
  public static #20= #19 of #2;           // StrictEquiv$=class scala/math/Equiv$Double$StrictEquiv$ of class scala/math/Equiv$Double$
SourceFile: "Equiv.scala"
  ScalaInlineInfo: length = 0x9 (unknown attribute)
   01 01 00 01 00 19 00 18 01
  Scala: length = 0x0 (unknown attribute)

