Classfile /Users/mw/Projects/slang-braindump/.jar/jar8/assemble/slang-braindump/assemble/content/scala/math/Equiv$Implicits$.class
  Last modified May 29, 2022; size 1252 bytes
  SHA-256 checksum c39360e7d1f52b59b9e4ca6c5fc2b7f8e31169137c80bdabe0cf653d8b507df3
  Compiled from "Equiv.scala"
public class scala.math.Equiv$Implicits$ implements scala.math.Equiv$ExtraImplicits
  minor version: 0
  major version: 52
  flags: (0x0021) ACC_PUBLIC, ACC_SUPER
  this_class: #2                          // scala/math/Equiv$Implicits$
  super_class: #4                         // java/lang/Object
  interfaces: 1, fields: 1, methods: 4, attributes: 4
Constant pool:
   #1 = Utf8               scala/math/Equiv$Implicits$
   #2 = Class              #1             // scala/math/Equiv$Implicits$
   #3 = Utf8               java/lang/Object
   #4 = Class              #3             // java/lang/Object
   #5 = Utf8               scala/math/Equiv$ExtraImplicits
   #6 = Class              #5             // scala/math/Equiv$ExtraImplicits
   #7 = Utf8               Equiv.scala
   #8 = Utf8               scala/math/Equiv
   #9 = Class              #8             // scala/math/Equiv
  #10 = Utf8               ExtraImplicits
  #11 = Utf8               Implicits$
  #12 = Utf8               MODULE$
  #13 = Utf8               Lscala/math/Equiv$Implicits$;
  #14 = Utf8               <clinit>
  #15 = Utf8               ()V
  #16 = Utf8               <init>
  #17 = NameAndType        #16:#15        // "<init>":()V
  #18 = Methodref          #2.#17         // scala/math/Equiv$Implicits$."<init>":()V
  #19 = NameAndType        #12:#13        // MODULE$:Lscala/math/Equiv$Implicits$;
  #20 = Fieldref           #2.#19         // scala/math/Equiv$Implicits$.MODULE$:Lscala/math/Equiv$Implicits$;
  #21 = Utf8               seqEquiv
  #22 = Utf8               (Lscala/math/Equiv;)Lscala/math/Equiv;
  #23 = Utf8               <CC::Lscala/collection/Seq<Ljava/lang/Object;>;T:Ljava/lang/Object;>(Lscala/math/Equiv<TT;>;)Lscala/math/Equiv<TCC;>;
  #24 = Utf8               eqv
  #25 = Utf8               seqEquiv$
  #26 = Utf8               (Lscala/math/Equiv$ExtraImplicits;Lscala/math/Equiv;)Lscala/math/Equiv;
  #27 = NameAndType        #25:#26        // seqEquiv$:(Lscala/math/Equiv$ExtraImplicits;Lscala/math/Equiv;)Lscala/math/Equiv;
  #28 = InterfaceMethodref #6.#27         // scala/math/Equiv$ExtraImplicits.seqEquiv$:(Lscala/math/Equiv$ExtraImplicits;Lscala/math/Equiv;)Lscala/math/Equiv;
  #29 = Utf8               this
  #30 = Utf8               Lscala/math/Equiv;
  #31 = Utf8               sortedSetEquiv
  #32 = Utf8               <CC::Lscala/collection/SortedSet<Ljava/lang/Object;>;T:Ljava/lang/Object;>(Lscala/math/Equiv<TT;>;)Lscala/math/Equiv<TCC;>;
  #33 = Utf8               sortedSetEquiv$
  #34 = NameAndType        #33:#26        // sortedSetEquiv$:(Lscala/math/Equiv$ExtraImplicits;Lscala/math/Equiv;)Lscala/math/Equiv;
  #35 = InterfaceMethodref #6.#34         // scala/math/Equiv$ExtraImplicits.sortedSetEquiv$:(Lscala/math/Equiv$ExtraImplicits;Lscala/math/Equiv;)Lscala/math/Equiv;
  #36 = Methodref          #4.#17         // java/lang/Object."<init>":()V
  #37 = Utf8               Code
  #38 = Utf8               LineNumberTable
  #39 = Utf8               LocalVariableTable
  #40 = Utf8               Signature
  #41 = Utf8               MethodParameters
  #42 = Utf8               InnerClasses
  #43 = Utf8               SourceFile
  #44 = Utf8               ScalaInlineInfo
  #45 = Utf8               Scala
{
  public static final scala.math.Equiv$Implicits$ MODULE$;
    descriptor: Lscala/math/Equiv$Implicits$;
    flags: (0x0019) ACC_PUBLIC, ACC_STATIC, ACC_FINAL

  public static {};
    descriptor: ()V
    flags: (0x0009) ACC_PUBLIC, ACC_STATIC
    Code:
      stack=2, locals=0, args_size=0
         0: new           #2                  // class scala/math/Equiv$Implicits$
         3: dup
         4: invokespecial #18                 // Method "<init>":()V
         7: putstatic     #20                 // Field MODULE$:Lscala/math/Equiv$Implicits$;
        10: getstatic     #20                 // Field MODULE$:Lscala/math/Equiv$Implicits$;
        13: pop
        14: return
      LineNumberTable:
        line 108: 0
        line 108: 14

  public <CC extends scala.collection.Seq<java.lang.Object>, T extends java.lang.Object> scala.math.Equiv<CC> seqEquiv(scala.math.Equiv<T>);
    descriptor: (Lscala/math/Equiv;)Lscala/math/Equiv;
    flags: (0x0001) ACC_PUBLIC
    Code:
      stack=2, locals=2, args_size=2
         0: aload_0
         1: aload_1
         2: invokestatic  #28                 // InterfaceMethod scala/math/Equiv$ExtraImplicits.seqEquiv$:(Lscala/math/Equiv$ExtraImplicits;Lscala/math/Equiv;)Lscala/math/Equiv;
         5: areturn
      LineNumberTable:
        line 108: 0
      LocalVariableTable:
        Start  Length  Slot  Name   Signature
            0       6     0  this   Lscala/math/Equiv$Implicits$;
            0       6     1   eqv   Lscala/math/Equiv;
    Signature: #23                          // <CC::Lscala/collection/Seq<Ljava/lang/Object;>;T:Ljava/lang/Object;>(Lscala/math/Equiv<TT;>;)Lscala/math/Equiv<TCC;>;
    MethodParameters:
      Name                           Flags
      eqv                            final

  public <CC extends scala.collection.SortedSet<java.lang.Object>, T extends java.lang.Object> scala.math.Equiv<CC> sortedSetEquiv(scala.math.Equiv<T>);
    descriptor: (Lscala/math/Equiv;)Lscala/math/Equiv;
    flags: (0x0001) ACC_PUBLIC
    Code:
      stack=2, locals=2, args_size=2
         0: aload_0
         1: aload_1
         2: invokestatic  #35                 // InterfaceMethod scala/math/Equiv$ExtraImplicits.sortedSetEquiv$:(Lscala/math/Equiv$ExtraImplicits;Lscala/math/Equiv;)Lscala/math/Equiv;
         5: areturn
      LineNumberTable:
        line 108: 0
      LocalVariableTable:
        Start  Length  Slot  Name   Signature
            0       6     0  this   Lscala/math/Equiv$Implicits$;
            0       6     1   eqv   Lscala/math/Equiv;
    Signature: #32                          // <CC::Lscala/collection/SortedSet<Ljava/lang/Object;>;T:Ljava/lang/Object;>(Lscala/math/Equiv<TT;>;)Lscala/math/Equiv<TCC;>;
    MethodParameters:
      Name                           Flags
      eqv                            final

  public scala.math.Equiv$Implicits$();
    descriptor: ()V
    flags: (0x0001) ACC_PUBLIC
    Code:
      stack=1, locals=1, args_size=1
         0: aload_0
         1: invokespecial #36                 // Method java/lang/Object."<init>":()V
         4: return
      LineNumberTable:
        line 108: 0
      LocalVariableTable:
        Start  Length  Slot  Name   Signature
            0       5     0  this   Lscala/math/Equiv$Implicits$;
}
InnerClasses:
  public static #10= #6 of #9;            // ExtraImplicits=class scala/math/Equiv$ExtraImplicits of class scala/math/Equiv
  public static #11= #2 of #9;            // Implicits$=class scala/math/Equiv$Implicits$ of class scala/math/Equiv
SourceFile: "Equiv.scala"
  ScalaInlineInfo: length = 0x13 (unknown attribute)
   01 01 00 03 00 10 00 0F 01 00 15 00 16 01 00 1F
   00 16 01
  Scala: length = 0x0 (unknown attribute)

