Classfile /Users/mw/Projects/slang-braindump/.jar/jar8/assemble/slang-braindump/assemble/content/scala/math/Fractional.class
  Last modified May 29, 2022; size 2608 bytes
  SHA-256 checksum c6ad9e3e82db29bcd319407ae45e398bd1a9007fad1b1f6726cfd9adb934f0a4
  Compiled from "Fractional.scala"
public interface scala.math.Fractional<T extends java.lang.Object> extends scala.math.Numeric<T>
  minor version: 0
  major version: 52
  flags: (0x0601) ACC_PUBLIC, ACC_INTERFACE, ACC_ABSTRACT
  this_class: #2                          // scala/math/Fractional
  super_class: #5                         // java/lang/Object
  interfaces: 1, fields: 0, methods: 5, attributes: 6
Constant pool:
   #1 = Utf8               scala/math/Fractional
   #2 = Class              #1             // scala/math/Fractional
   #3 = Utf8               <T:Ljava/lang/Object;>Ljava/lang/Object;Lscala/math/Numeric<TT;>;
   #4 = Utf8               java/lang/Object
   #5 = Class              #4             // java/lang/Object
   #6 = Utf8               scala/math/Numeric
   #7 = Class              #6             // scala/math/Numeric
   #8 = Utf8               Fractional.scala
   #9 = Utf8               Lscala/reflect/ScalaSignature;
  #10 = Utf8               bytes
  #11 = Utf8               \u0006\u0005}4qa\u0005\u000b\u0011\u0002\u0007\u0005\u0011\u0004C\u00034\u0001\u0011\u0005A\u0007C\u00039\u0001\u0019\u0005\u0011H\u0002\u0003?\u0001\u0001y\u0004\u0002\u0003#\u0004\u0005\u0003\u0005\u000b\u0011B\u0014\t\u000b\u0015\u001bA\u0011\u0001$\t\u000b%\u001bA\u0011\u0001&\t\u000b5\u0003A1\t(\b\u000bA#\u0002\u0012A)\u0007\u000bM!\u0002\u0012\u0001*\t\u000b\u0015KA\u0011\u0001/\t\u000buKA\u0011\u00010\u0007\u000f%L\u0001\u0013aA\u0001U\")1\u0007\u0004C\u0001i!)1\u000e\u0004C\u0002Y\u001e)a/\u0003E\u0001o\u001a)\u00110\u0003E\u0001u\")Q\t\u0005C\u0001y\"9Q0CA\u0001\n\u0013q(A\u0003$sC\u000e$\u0018n\u001c8bY*\u0011QCF\u0001\u0005[\u0006$\bNC\u0001\u0018\u0003\u0015\u00198-\u00197b\u0007\u0001)\"AG\u0015\u0014\u0007\u0001Y2\u0005\u0005\u0002\u001dC5\tQD\u0003\u0002\u001f?\u0005!A.\u00198h\u0015\u0005\u0001\u0013\u0001\u00026bm\u0006L!AI\u000f\u0003\r=\u0013\'.Z2u!\r!SeJ\u0007\u0002)%\u0011a\u0005\u0006\u0002\b\u001dVlWM]5d!\tA\u0013\u0006\u0004\u0001\u0005\u000b)\u0002!\u0019A\u0016\u0003\u0003Q\u000b\"\u0001\f\u0019\u0011\u00055rS\"\u0001\f\n\u0005=2\"a\u0002(pi\"Lgn\u001a\t\u0003[EJ!A\r\f\u0003\u0007\u0005s\u00170\u0001\u0004%S:LG\u000f\n\u000b\u0002kA\u0011QFN\u0005\u0003oY\u0011A!\u00168ji\u0006\u0019A-\u001b<\u0015\u0007\u001dRD\bC\u0003<\u0005\u0001\u0007q%A\u0001y\u0011\u0015i$\u00011\u0001(\u0003\u0005I(!\u0004$sC\u000e$\u0018n\u001c8bY>\u00038o\u0005\u0002\u0004\u0001B\u0011\u0011IQ\u0007\u0002\u0001%\u00111)\n\u0002\u000b\u001dVlWM]5d\u001fB\u001c\u0018a\u00017ig\u00061A(\u001b8jiz\"\"a\u0012%\u0011\u0005\u0005\u001b\u0001\"\u0002#\u0006\u0001\u00049\u0013\u0001\u0002\u0013eSZ$\"aJ&\t\u000b13\u0001\u0019A\u0014\u0002\u0007ID7/\u0001\u0007nW:+X.\u001a:jG>\u00038\u000f\u0006\u0002H\u001f\")Ai\u0002a\u0001O\u0005QaI]1di&|g.\u00197\u0011\u0005\u0011J1cA\u0005T-B\u0011Q\u0006V\u0005\u0003+Z\u0011a!\u00118z%\u00164\u0007CA,[\u001b\u0005A&BA- \u0003\tIw.\u0003\u0002\\1\na1+\u001a:jC2L\'0\u00192mKR\t\u0011+A\u0003baBd\u00170\u0006\u0002`ER\u0011\u0001m\u0019\t\u0004I\u0001\t\u0007C\u0001\u0015c\t\u0015Q3B1\u0001,\u0011\u0015!7\u0002q\u0001a\u0003\u00111\'/Y2)\u0005-1\u0007CA\u0017h\u0013\tAgC\u0001\u0004j]2Lg.\u001a\u0002\u000f\u000bb$(/Y%na2L7-\u001b;t\'\ta1+\u0001\nj]\u001aL\u0007P\u0012:bGRLwN\\1m\u001fB\u001cXCA7s)\tqW\u000f\u0006\u0002pgB\u0011\u0001o\u0001\t\u0004I\u0001\t\bC\u0001\u0015s\t\u0015QcB1\u0001,\u0011\u0015!h\u0002q\u0001q\u0003\rqW/\u001c\u0005\u0006w9\u0001\r!]\u0001\n\u00136\u0004H.[2jiN\u0004\"\u0001\u001f\t\u000e\u0003%\u0011\u0011\"S7qY&\u001c\u0017\u000e^:\u0014\u0007A\u00196\u0010\u0005\u0002y\u0019Q\tq/\u0001\u0007xe&$XMU3qY\u0006\u001cW\rF\u0001\u001c\u0001
  #12 = Utf8               scala/math/Fractional$ExtraImplicits
  #13 = Class              #12            // scala/math/Fractional$ExtraImplicits
  #14 = Utf8               ExtraImplicits
  #15 = Utf8               scala/math/Fractional$FractionalOps
  #16 = Class              #15            // scala/math/Fractional$FractionalOps
  #17 = Utf8               FractionalOps
  #18 = Utf8               scala/math/Fractional$Implicits$
  #19 = Class              #18            // scala/math/Fractional$Implicits$
  #20 = Utf8               Implicits$
  #21 = Utf8               apply
  #22 = Utf8               (Lscala/math/Fractional;)Lscala/math/Fractional;
  #23 = Utf8               <T:Ljava/lang/Object;>(Lscala/math/Fractional<TT;>;)Lscala/math/Fractional<TT;>;
  #24 = Utf8               frac
  #25 = Utf8               scala/math/Fractional$
  #26 = Class              #25            // scala/math/Fractional$
  #27 = Utf8               MODULE$
  #28 = Utf8               Lscala/math/Fractional$;
  #29 = NameAndType        #27:#28        // MODULE$:Lscala/math/Fractional$;
  #30 = Fieldref           #26.#29        // scala/math/Fractional$.MODULE$:Lscala/math/Fractional$;
  #31 = Utf8               Lscala/math/Fractional;
  #32 = Utf8               div
  #33 = Utf8               (Ljava/lang/Object;Ljava/lang/Object;)Ljava/lang/Object;
  #34 = Utf8               (TT;TT;)TT;
  #35 = Utf8               x
  #36 = Utf8               y
  #37 = Utf8               mkNumericOps$
  #38 = Utf8               (Lscala/math/Fractional;Ljava/lang/Object;)Lscala/math/Fractional$FractionalOps;
  #39 = Utf8               $this
  #40 = Utf8               lhs
  #41 = Utf8               mkNumericOps
  #42 = Utf8               (Ljava/lang/Object;)Lscala/math/Fractional$FractionalOps;
  #43 = NameAndType        #41:#42        // mkNumericOps:(Ljava/lang/Object;)Lscala/math/Fractional$FractionalOps;
  #44 = InterfaceMethodref #2.#43         // scala/math/Fractional.mkNumericOps:(Ljava/lang/Object;)Lscala/math/Fractional$FractionalOps;
  #45 = Utf8               Ljava/lang/Object;
  #46 = Utf8               (TT;)Lscala/math/Fractional<TT;>.FractionalOps;
  #47 = Utf8               <init>
  #48 = Utf8               (Lscala/math/Fractional;Ljava/lang/Object;)V
  #49 = NameAndType        #47:#48        // "<init>":(Lscala/math/Fractional;Ljava/lang/Object;)V
  #50 = Methodref          #16.#49        // scala/math/Fractional$FractionalOps."<init>":(Lscala/math/Fractional;Ljava/lang/Object;)V
  #51 = Utf8               this
  #52 = Utf8               $init$
  #53 = Utf8               (Lscala/math/Fractional;)V
  #54 = Utf8               Code
  #55 = Utf8               LineNumberTable
  #56 = Utf8               LocalVariableTable
  #57 = Utf8               Signature
  #58 = Utf8               MethodParameters
  #59 = Utf8               InnerClasses
  #60 = Utf8               SourceFile
  #61 = Utf8               RuntimeVisibleAnnotations
  #62 = Utf8               ScalaInlineInfo
  #63 = Utf8               ScalaSig
{
  public static <T extends java.lang.Object> scala.math.Fractional<T> apply(scala.math.Fractional<T>);
    descriptor: (Lscala/math/Fractional;)Lscala/math/Fractional;
    flags: (0x0009) ACC_PUBLIC, ACC_STATIC
    Code:
      stack=1, locals=1, args_size=1
         0: getstatic     #30                 // Field scala/math/Fractional$.MODULE$:Lscala/math/Fractional$;
         3: pop
         4: aload_0
         5: areturn
      LineNumberTable:
        line 29: 4
      LocalVariableTable:
        Start  Length  Slot  Name   Signature
            0       6     0  frac   Lscala/math/Fractional;
    Signature: #23                          // <T:Ljava/lang/Object;>(Lscala/math/Fractional<TT;>;)Lscala/math/Fractional<TT;>;
    MethodParameters:
      Name                           Flags
      frac                           final

  public abstract T div(T, T);
    descriptor: (Ljava/lang/Object;Ljava/lang/Object;)Ljava/lang/Object;
    flags: (0x0401) ACC_PUBLIC, ACC_ABSTRACT
    Signature: #34                          // (TT;TT;)TT;
    MethodParameters:
      Name                           Flags
      x                              final
      y                              final

  public static scala.math.Fractional$FractionalOps mkNumericOps$(scala.math.Fractional, java.lang.Object);
    descriptor: (Lscala/math/Fractional;Ljava/lang/Object;)Lscala/math/Fractional$FractionalOps;
    flags: (0x1009) ACC_PUBLIC, ACC_STATIC, ACC_SYNTHETIC
    Code:
      stack=2, locals=2, args_size=2
         0: aload_0
         1: aload_1
         2: invokespecial #44                 // InterfaceMethod mkNumericOps:(Ljava/lang/Object;)Lscala/math/Fractional$FractionalOps;
         5: areturn
      LineNumberTable:
        line 24: 0
      LocalVariableTable:
        Start  Length  Slot  Name   Signature
            0       6     0 $this   Lscala/math/Fractional;
            0       6     1   lhs   Ljava/lang/Object;
    MethodParameters:
      Name                           Flags
      $this                          final synthetic
      lhs                            final

  public default scala.math.Fractional<T>.FractionalOps mkNumericOps(T);
    descriptor: (Ljava/lang/Object;)Lscala/math/Fractional$FractionalOps;
    flags: (0x0001) ACC_PUBLIC
    Code:
      stack=4, locals=2, args_size=2
         0: new           #16                 // class scala/math/Fractional$FractionalOps
         3: dup
         4: aload_0
         5: aload_1
         6: invokespecial #50                 // Method scala/math/Fractional$FractionalOps."<init>":(Lscala/math/Fractional;Ljava/lang/Object;)V
         9: areturn
      LineNumberTable:
        line 25: 0
      LocalVariableTable:
        Start  Length  Slot  Name   Signature
            0      10     0  this   Lscala/math/Fractional;
            0      10     1   lhs   Ljava/lang/Object;
    Signature: #46                          // (TT;)Lscala/math/Fractional<TT;>.FractionalOps;
    MethodParameters:
      Name                           Flags
      lhs                            final

  public static void $init$(scala.math.Fractional);
    descriptor: (Lscala/math/Fractional;)V
    flags: (0x0009) ACC_PUBLIC, ACC_STATIC
    Code:
      stack=0, locals=1, args_size=1
         0: return
      LineNumberTable:
        line 18: 0
      LocalVariableTable:
        Start  Length  Slot  Name   Signature
            0       1     0 $this   Lscala/math/Fractional;
    MethodParameters:
      Name                           Flags
      $this                          final synthetic
}
InnerClasses:
  public static #14= #13 of #2;           // ExtraImplicits=class scala/math/Fractional$ExtraImplicits of class scala/math/Fractional
  public #17= #16 of #2;                  // FractionalOps=class scala/math/Fractional$FractionalOps of class scala/math/Fractional
  public static #20= #19 of #2;           // Implicits$=class scala/math/Fractional$Implicits$ of class scala/math/Fractional
Signature: #3                           // <T:Ljava/lang/Object;>Ljava/lang/Object;Lscala/math/Numeric<TT;>;
SourceFile: "Fractional.scala"
RuntimeVisibleAnnotations:
  0: #9(#10=s#11)
    scala.reflect.ScalaSignature(
      bytes="\u0006\u0005}4qa\u0005\u000b\u0011\u0002\u0007\u0005\u0011\u0004C\u00034\u0001\u0011\u0005A\u0007C\u00039\u0001\u0019\u0005\u0011H\u0002\u0003?\u0001\u0001y\u0004\u0002\u0003#\u0004\u0005\u0003\u0005\u000b\u0011B\u0014\t\u000b\u0015\u001bA\u0011\u0001$\t\u000b%\u001bA\u0011\u0001&\t\u000b5\u0003A1\t(\b\u000bA#\u0002\u0012A)\u0007\u000bM!\u0002\u0012\u0001*\t\u000b\u0015KA\u0011\u0001/\t\u000buKA\u0011\u00010\u0007\u000f%L\u0001\u0013aA\u0001U\")1\u0007\u0004C\u0001i!)1\u000e\u0004C\u0002Y\u001e)a/\u0003E\u0001o\u001a)\u00110\u0003E\u0001u\")Q\t\u0005C\u0001y\"9Q0CA\u0001\n\u0013q(A\u0003$sC\u000e$\u0018n\u001c8bY*\u0011QCF\u0001\u0005[\u0006$\bNC\u0001\u0018\u0003\u0015\u00198-\u00197b\u0007\u0001)\"AG\u0015\u0014\u0007\u0001Y2\u0005\u0005\u0002\u001dC5\tQD\u0003\u0002\u001f?\u0005!A.\u00198h\u0015\u0005\u0001\u0013\u0001\u00026bm\u0006L!AI\u000f\u0003\r=\u0013\'.Z2u!\r!SeJ\u0007\u0002)%\u0011a\u0005\u0006\u0002\b\u001dVlWM]5d!\tA\u0013\u0006\u0004\u0001\u0005\u000b)\u0002!\u0019A\u0016\u0003\u0003Q\u000b\"\u0001\f\u0019\u0011\u00055rS\"\u0001\f\n\u0005=2\"a\u0002(pi\"Lgn\u001a\t\u0003[EJ!A\r\f\u0003\u0007\u0005s\u00170\u0001\u0004%S:LG\u000f\n\u000b\u0002kA\u0011QFN\u0005\u0003oY\u0011A!\u00168ji\u0006\u0019A-\u001b<\u0015\u0007\u001dRD\bC\u0003<\u0005\u0001\u0007q%A\u0001y\u0011\u0015i$\u00011\u0001(\u0003\u0005I(!\u0004$sC\u000e$\u0018n\u001c8bY>\u00038o\u0005\u0002\u0004\u0001B\u0011\u0011IQ\u0007\u0002\u0001%\u00111)\n\u0002\u000b\u001dVlWM]5d\u001fB\u001c\u0018a\u00017ig\u00061A(\u001b8jiz\"\"a\u0012%\u0011\u0005\u0005\u001b\u0001\"\u0002#\u0006\u0001\u00049\u0013\u0001\u0002\u0013eSZ$\"aJ&\t\u000b13\u0001\u0019A\u0014\u0002\u0007ID7/\u0001\u0007nW:+X.\u001a:jG>\u00038\u000f\u0006\u0002H\u001f\")Ai\u0002a\u0001O\u0005QaI]1di&|g.\u00197\u0011\u0005\u0011J1cA\u0005T-B\u0011Q\u0006V\u0005\u0003+Z\u0011a!\u00118z%\u00164\u0007CA,[\u001b\u0005A&BA- \u0003\tIw.\u0003\u0002\\1\na1+\u001a:jC2L\'0\u00192mKR\t\u0011+A\u0003baBd\u00170\u0006\u0002`ER\u0011\u0001m\u0019\t\u0004I\u0001\t\u0007C\u0001\u0015c\t\u0015Q3B1\u0001,\u0011\u0015!7\u0002q\u0001a\u0003\u00111\'/Y2)\u0005-1\u0007CA\u0017h\u0013\tAgC\u0001\u0004j]2Lg.\u001a\u0002\u000f\u000bb$(/Y%na2L7-\u001b;t\'\ta1+\u0001\nj]\u001aL\u0007P\u0012:bGRLwN\\1m\u001fB\u001cXCA7s)\tqW\u000f\u0006\u0002pgB\u0011\u0001o\u0001\t\u0004I\u0001\t\bC\u0001\u0015s\t\u0015QcB1\u0001,\u0011\u0015!h\u0002q\u0001q\u0003\rqW/\u001c\u0005\u0006w9\u0001\r!]\u0001\n\u00136\u0004H.[2jiN\u0004\"\u0001\u001f\t\u000e\u0003%\u0011\u0011\"S7qY&\u001c\u0017\u000e^:\u0014\u0007A\u00196\u0010\u0005\u0002y\u0019Q\tq/\u0001\u0007xe&$XMU3qY\u0006\u001cW\rF\u0001\u001c\u0001"
    )
  ScalaInlineInfo: length = 0x18 (unknown attribute)
   01 00 00 04 00 34 00 35 01 00 20 00 21 00 00 29
   00 2A 00 00 25 00 26 01
  ScalaSig: length = 0x3 (unknown attribute)
   05 02 00
