Classfile /Users/mw/Projects/slang-braindump/.jar/jar8/assemble/slang-braindump/assemble/content/scala/math/Integral$IntegralOps.class
  Last modified May 29, 2022; size 1619 bytes
  SHA-256 checksum d5350fa960612703a0f26366e46457edfcfc9226148e56ae7406f8adc02004b4
  Compiled from "Integral.scala"
public class scala.math.Integral$IntegralOps extends scala.math.Numeric<T>.NumericOps
  minor version: 0
  major version: 52
  flags: (0x0021) ACC_PUBLIC, ACC_SUPER
  this_class: #2                          // scala/math/Integral$IntegralOps
  super_class: #5                         // scala/math/Numeric$NumericOps
  interfaces: 0, fields: 1, methods: 5, attributes: 5
Constant pool:
   #1 = Utf8               scala/math/Integral$IntegralOps
   #2 = Class              #1             // scala/math/Integral$IntegralOps
   #3 = Utf8               Lscala/math/Numeric<TT;>.NumericOps;
   #4 = Utf8               scala/math/Numeric$NumericOps
   #5 = Class              #4             // scala/math/Numeric$NumericOps
   #6 = Utf8               Integral.scala
   #7 = Utf8               scala/math/Integral
   #8 = Class              #7             // scala/math/Integral
   #9 = Utf8               IntegralOps
  #10 = Utf8               scala/math/Numeric
  #11 = Class              #10            // scala/math/Numeric
  #12 = Utf8               NumericOps
  #13 = Utf8               lhs
  #14 = Utf8               Ljava/lang/Object;
  #15 = Utf8               TT;
  #16 = Utf8               $div
  #17 = Utf8               (Ljava/lang/Object;)Ljava/lang/Object;
  #18 = Utf8               (TT;)TT;
  #19 = Utf8               rhs
  #20 = Utf8               scala$math$Integral$IntegralOps$$$outer
  #21 = Utf8               ()Lscala/math/Integral;
  #22 = NameAndType        #20:#21        // scala$math$Integral$IntegralOps$$$outer:()Lscala/math/Integral;
  #23 = Methodref          #2.#22         // scala/math/Integral$IntegralOps.scala$math$Integral$IntegralOps$$$outer:()Lscala/math/Integral;
  #24 = NameAndType        #13:#14        // lhs:Ljava/lang/Object;
  #25 = Fieldref           #2.#24         // scala/math/Integral$IntegralOps.lhs:Ljava/lang/Object;
  #26 = Utf8               quot
  #27 = Utf8               (Ljava/lang/Object;Ljava/lang/Object;)Ljava/lang/Object;
  #28 = NameAndType        #26:#27        // quot:(Ljava/lang/Object;Ljava/lang/Object;)Ljava/lang/Object;
  #29 = InterfaceMethodref #8.#28         // scala/math/Integral.quot:(Ljava/lang/Object;Ljava/lang/Object;)Ljava/lang/Object;
  #30 = Utf8               this
  #31 = Utf8               Lscala/math/Integral$IntegralOps;
  #32 = Utf8               $percent
  #33 = Utf8               rem
  #34 = NameAndType        #33:#27        // rem:(Ljava/lang/Object;Ljava/lang/Object;)Ljava/lang/Object;
  #35 = InterfaceMethodref #8.#34         // scala/math/Integral.rem:(Ljava/lang/Object;Ljava/lang/Object;)Ljava/lang/Object;
  #36 = Utf8               $div$percent
  #37 = Utf8               (Ljava/lang/Object;)Lscala/Tuple2;
  #38 = Utf8               (TT;)Lscala/Tuple2<TT;TT;>;
  #39 = Utf8               scala/Tuple2
  #40 = Class              #39            // scala/Tuple2
  #41 = Utf8               <init>
  #42 = Utf8               (Ljava/lang/Object;Ljava/lang/Object;)V
  #43 = NameAndType        #41:#42        // "<init>":(Ljava/lang/Object;Ljava/lang/Object;)V
  #44 = Methodref          #40.#43        // scala/Tuple2."<init>":(Ljava/lang/Object;Ljava/lang/Object;)V
  #45 = Utf8               $outer
  #46 = Utf8               Lscala/math/Numeric;
  #47 = NameAndType        #45:#46        // $outer:Lscala/math/Numeric;
  #48 = Fieldref           #2.#47         // scala/math/Integral$IntegralOps.$outer:Lscala/math/Numeric;
  #49 = Utf8               (Lscala/math/Integral;Ljava/lang/Object;)V
  #50 = Utf8               (TT;)V
  #51 = Utf8               (Lscala/math/Numeric;Ljava/lang/Object;)V
  #52 = NameAndType        #41:#51        // "<init>":(Lscala/math/Numeric;Ljava/lang/Object;)V
  #53 = Methodref          #5.#52         // scala/math/Numeric$NumericOps."<init>":(Lscala/math/Numeric;Ljava/lang/Object;)V
  #54 = Utf8               Lscala/math/Integral;
  #55 = Utf8               Signature
  #56 = Utf8               Code
  #57 = Utf8               LineNumberTable
  #58 = Utf8               LocalVariableTable
  #59 = Utf8               MethodParameters
  #60 = Utf8               InnerClasses
  #61 = Utf8               SourceFile
  #62 = Utf8               ScalaInlineInfo
  #63 = Utf8               Scala
{
  private final T lhs;
    descriptor: Ljava/lang/Object;
    flags: (0x0012) ACC_PRIVATE, ACC_FINAL
    Signature: #15                          // TT;

  public T $div(T);
    descriptor: (Ljava/lang/Object;)Ljava/lang/Object;
    flags: (0x0001) ACC_PUBLIC
    Code:
      stack=3, locals=2, args_size=2
         0: aload_0
         1: invokevirtual #23                 // Method scala$math$Integral$IntegralOps$$$outer:()Lscala/math/Integral;
         4: aload_0
         5: getfield      #25                 // Field lhs:Ljava/lang/Object;
         8: aload_1
         9: invokeinterface #29,  3           // InterfaceMethod scala/math/Integral.quot:(Ljava/lang/Object;Ljava/lang/Object;)Ljava/lang/Object;
        14: areturn
      LineNumberTable:
        line 23: 0
      LocalVariableTable:
        Start  Length  Slot  Name   Signature
            0      15     0  this   Lscala/math/Integral$IntegralOps;
            0      15     1   rhs   Ljava/lang/Object;
    Signature: #18                          // (TT;)TT;
    MethodParameters:
      Name                           Flags
      rhs                            final

  public T $percent(T);
    descriptor: (Ljava/lang/Object;)Ljava/lang/Object;
    flags: (0x0001) ACC_PUBLIC
    Code:
      stack=3, locals=2, args_size=2
         0: aload_0
         1: invokevirtual #23                 // Method scala$math$Integral$IntegralOps$$$outer:()Lscala/math/Integral;
         4: aload_0
         5: getfield      #25                 // Field lhs:Ljava/lang/Object;
         8: aload_1
         9: invokeinterface #35,  3           // InterfaceMethod scala/math/Integral.rem:(Ljava/lang/Object;Ljava/lang/Object;)Ljava/lang/Object;
        14: areturn
      LineNumberTable:
        line 24: 0
      LocalVariableTable:
        Start  Length  Slot  Name   Signature
            0      15     0  this   Lscala/math/Integral$IntegralOps;
            0      15     1   rhs   Ljava/lang/Object;
    Signature: #18                          // (TT;)TT;
    MethodParameters:
      Name                           Flags
      rhs                            final

  public scala.Tuple2<T, T> $div$percent(T);
    descriptor: (Ljava/lang/Object;)Lscala/Tuple2;
    flags: (0x0001) ACC_PUBLIC
    Code:
      stack=6, locals=2, args_size=2
         0: new           #40                 // class scala/Tuple2
         3: dup
         4: aload_0
         5: invokevirtual #23                 // Method scala$math$Integral$IntegralOps$$$outer:()Lscala/math/Integral;
         8: aload_0
         9: getfield      #25                 // Field lhs:Ljava/lang/Object;
        12: aload_1
        13: invokeinterface #29,  3           // InterfaceMethod scala/math/Integral.quot:(Ljava/lang/Object;Ljava/lang/Object;)Ljava/lang/Object;
        18: aload_0
        19: invokevirtual #23                 // Method scala$math$Integral$IntegralOps$$$outer:()Lscala/math/Integral;
        22: aload_0
        23: getfield      #25                 // Field lhs:Ljava/lang/Object;
        26: aload_1
        27: invokeinterface #35,  3           // InterfaceMethod scala/math/Integral.rem:(Ljava/lang/Object;Ljava/lang/Object;)Ljava/lang/Object;
        32: invokespecial #44                 // Method scala/Tuple2."<init>":(Ljava/lang/Object;Ljava/lang/Object;)V
        35: areturn
      LineNumberTable:
        line 25: 0
      LocalVariableTable:
        Start  Length  Slot  Name   Signature
            0      36     0  this   Lscala/math/Integral$IntegralOps;
            0      36     1   rhs   Ljava/lang/Object;
    Signature: #38                          // (TT;)Lscala/Tuple2<TT;TT;>;
    MethodParameters:
      Name                           Flags
      rhs                            final

  public scala.math.Integral scala$math$Integral$IntegralOps$$$outer();
    descriptor: ()Lscala/math/Integral;
    flags: (0x1001) ACC_PUBLIC, ACC_SYNTHETIC
    Code:
      stack=1, locals=1, args_size=1
         0: aload_0
         1: getfield      #48                 // Field $outer:Lscala/math/Numeric;
         4: checkcast     #8                  // class scala/math/Integral
         7: areturn
      LineNumberTable:
        line 22: 0
      LocalVariableTable:
        Start  Length  Slot  Name   Signature
            0       8     0  this   Lscala/math/Integral$IntegralOps;

  public scala.math.Integral$IntegralOps(T);
    descriptor: (Lscala/math/Integral;Ljava/lang/Object;)V
    flags: (0x0001) ACC_PUBLIC
    Code:
      stack=3, locals=3, args_size=3
         0: aload_0
         1: aload_2
         2: putfield      #25                 // Field lhs:Ljava/lang/Object;
         5: aload_0
         6: aload_1
         7: aload_2
         8: invokespecial #53                 // Method scala/math/Numeric$NumericOps."<init>":(Lscala/math/Numeric;Ljava/lang/Object;)V
        11: return
      LineNumberTable:
        line 22: 0
      LocalVariableTable:
        Start  Length  Slot  Name   Signature
            0      12     0  this   Lscala/math/Integral$IntegralOps;
            0      12     1 $outer   Lscala/math/Integral;
            0      12     2   lhs   Ljava/lang/Object;
    Signature: #50                          // (TT;)V
    MethodParameters:
      Name                           Flags
      $outer                         final synthetic
      lhs                            final
}
InnerClasses:
  public #9= #2 of #8;                    // IntegralOps=class scala/math/Integral$IntegralOps of class scala/math/Integral
  public #12= #5 of #11;                  // NumericOps=class scala/math/Numeric$NumericOps of class scala/math/Numeric
Signature: #3                           // Lscala/math/Numeric<TT;>.NumericOps;
SourceFile: "Integral.scala"
  ScalaInlineInfo: length = 0x1D (unknown attribute)
   01 00 00 05 00 10 00 11 00 00 24 00 25 00 00 20
   00 11 00 00 29 00 31 00 00 14 00 15 00
  Scala: length = 0x0 (unknown attribute)

