Classfile /Users/mw/Projects/slang-braindump/.jar/jar8/assemble/slang-braindump/assemble/content/scala/math/Ordering$Double$IeeeOrdering$.class
  Last modified May 29, 2022; size 5822 bytes
  SHA-256 checksum ae2635fee8b3a1f86d8208db9a7a69ed579dc691e4756f0281ff68f88828dce8
  Compiled from "Ordering.scala"
public class scala.math.Ordering$Double$IeeeOrdering$ implements scala.math.Ordering$Double$IeeeOrdering
  minor version: 0
  major version: 52
  flags: (0x0021) ACC_PUBLIC, ACC_SUPER
  this_class: #2                          // scala/math/Ordering$Double$IeeeOrdering$
  super_class: #4                         // java/lang/Object
  interfaces: 1, fields: 1, methods: 28, attributes: 4
Constant pool:
    #1 = Utf8               scala/math/Ordering$Double$IeeeOrdering$
    #2 = Class              #1            // scala/math/Ordering$Double$IeeeOrdering$
    #3 = Utf8               java/lang/Object
    #4 = Class              #3            // java/lang/Object
    #5 = Utf8               scala/math/Ordering$Double$IeeeOrdering
    #6 = Class              #5            // scala/math/Ordering$Double$IeeeOrdering
    #7 = Utf8               Ordering.scala
    #8 = Utf8               scala/math/Ordering$Double$
    #9 = Class              #8            // scala/math/Ordering$Double$
   #10 = Utf8               scala/math/Ordering
   #11 = Class              #10           // scala/math/Ordering
   #12 = Utf8               Double$
   #13 = Utf8               IeeeOrdering
   #14 = Utf8               IeeeOrdering$
   #15 = Utf8               scala/math/Ordering$OrderingOps
   #16 = Class              #15           // scala/math/Ordering$OrderingOps
   #17 = Utf8               OrderingOps
   #18 = Utf8               MODULE$
   #19 = Utf8               Lscala/math/Ordering$Double$IeeeOrdering$;
   #20 = Utf8               <clinit>
   #21 = Utf8               ()V
   #22 = Utf8               <init>
   #23 = NameAndType        #22:#21       // "<init>":()V
   #24 = Methodref          #2.#23        // scala/math/Ordering$Double$IeeeOrdering$."<init>":()V
   #25 = NameAndType        #18:#19       // MODULE$:Lscala/math/Ordering$Double$IeeeOrdering$;
   #26 = Fieldref           #2.#25        // scala/math/Ordering$Double$IeeeOrdering$.MODULE$:Lscala/math/Ordering$Double$IeeeOrdering$;
   #27 = Utf8               compare
   #28 = Utf8               (DD)I
   #29 = Utf8               x
   #30 = Utf8               y
   #31 = Utf8               compare$
   #32 = Utf8               (Lscala/math/Ordering$Double$IeeeOrdering;DD)I
   #33 = NameAndType        #31:#32       // compare$:(Lscala/math/Ordering$Double$IeeeOrdering;DD)I
   #34 = InterfaceMethodref #6.#33        // scala/math/Ordering$Double$IeeeOrdering.compare$:(Lscala/math/Ordering$Double$IeeeOrdering;DD)I
   #35 = Utf8               this
   #36 = Utf8               D
   #37 = Utf8               lteq
   #38 = Utf8               (DD)Z
   #39 = Utf8               lteq$
   #40 = Utf8               (Lscala/math/Ordering$Double$IeeeOrdering;DD)Z
   #41 = NameAndType        #39:#40       // lteq$:(Lscala/math/Ordering$Double$IeeeOrdering;DD)Z
   #42 = InterfaceMethodref #6.#41        // scala/math/Ordering$Double$IeeeOrdering.lteq$:(Lscala/math/Ordering$Double$IeeeOrdering;DD)Z
   #43 = Utf8               gteq
   #44 = Utf8               gteq$
   #45 = NameAndType        #44:#40       // gteq$:(Lscala/math/Ordering$Double$IeeeOrdering;DD)Z
   #46 = InterfaceMethodref #6.#45        // scala/math/Ordering$Double$IeeeOrdering.gteq$:(Lscala/math/Ordering$Double$IeeeOrdering;DD)Z
   #47 = Utf8               lt
   #48 = Utf8               lt$
   #49 = NameAndType        #48:#40       // lt$:(Lscala/math/Ordering$Double$IeeeOrdering;DD)Z
   #50 = InterfaceMethodref #6.#49        // scala/math/Ordering$Double$IeeeOrdering.lt$:(Lscala/math/Ordering$Double$IeeeOrdering;DD)Z
   #51 = Utf8               gt
   #52 = Utf8               gt$
   #53 = NameAndType        #52:#40       // gt$:(Lscala/math/Ordering$Double$IeeeOrdering;DD)Z
   #54 = InterfaceMethodref #6.#53        // scala/math/Ordering$Double$IeeeOrdering.gt$:(Lscala/math/Ordering$Double$IeeeOrdering;DD)Z
   #55 = Utf8               equiv
   #56 = Utf8               equiv$
   #57 = NameAndType        #56:#40       // equiv$:(Lscala/math/Ordering$Double$IeeeOrdering;DD)Z
   #58 = InterfaceMethodref #6.#57        // scala/math/Ordering$Double$IeeeOrdering.equiv$:(Lscala/math/Ordering$Double$IeeeOrdering;DD)Z
   #59 = Utf8               max
   #60 = Utf8               (DD)D
   #61 = Utf8               <U:Ljava/lang/Object;>(TU;TU;)TU;
   #62 = Utf8               max$
   #63 = Utf8               (Lscala/math/Ordering$Double$IeeeOrdering;DD)D
   #64 = NameAndType        #62:#63       // max$:(Lscala/math/Ordering$Double$IeeeOrdering;DD)D
   #65 = InterfaceMethodref #6.#64        // scala/math/Ordering$Double$IeeeOrdering.max$:(Lscala/math/Ordering$Double$IeeeOrdering;DD)D
   #66 = Utf8               min
   #67 = Utf8               min$
   #68 = NameAndType        #67:#63       // min$:(Lscala/math/Ordering$Double$IeeeOrdering;DD)D
   #69 = InterfaceMethodref #6.#68        // scala/math/Ordering$Double$IeeeOrdering.min$:(Lscala/math/Ordering$Double$IeeeOrdering;DD)D
   #70 = Utf8               tryCompare
   #71 = Utf8               (Ljava/lang/Object;Ljava/lang/Object;)Lscala/Some;
   #72 = Utf8               tryCompare$
   #73 = Utf8               (Lscala/math/Ordering;Ljava/lang/Object;Ljava/lang/Object;)Lscala/Some;
   #74 = NameAndType        #72:#73       // tryCompare$:(Lscala/math/Ordering;Ljava/lang/Object;Ljava/lang/Object;)Lscala/Some;
   #75 = InterfaceMethodref #11.#74       // scala/math/Ordering.tryCompare$:(Lscala/math/Ordering;Ljava/lang/Object;Ljava/lang/Object;)Lscala/Some;
   #76 = Utf8               Ljava/lang/Object;
   #77 = Utf8               reverse
   #78 = Utf8               ()Lscala/math/Ordering;
   #79 = Utf8               ()Lscala/math/Ordering<Ljava/lang/Object;>;
   #80 = Utf8               reverse$
   #81 = Utf8               (Lscala/math/Ordering;)Lscala/math/Ordering;
   #82 = NameAndType        #80:#81       // reverse$:(Lscala/math/Ordering;)Lscala/math/Ordering;
   #83 = InterfaceMethodref #11.#82       // scala/math/Ordering.reverse$:(Lscala/math/Ordering;)Lscala/math/Ordering;
   #84 = Utf8               isReverseOf
   #85 = Utf8               (Lscala/math/Ordering;)Z
   #86 = Utf8               (Lscala/math/Ordering<*>;)Z
   #87 = Utf8               other
   #88 = Utf8               isReverseOf$
   #89 = Utf8               (Lscala/math/Ordering;Lscala/math/Ordering;)Z
   #90 = NameAndType        #88:#89       // isReverseOf$:(Lscala/math/Ordering;Lscala/math/Ordering;)Z
   #91 = InterfaceMethodref #11.#90       // scala/math/Ordering.isReverseOf$:(Lscala/math/Ordering;Lscala/math/Ordering;)Z
   #92 = Utf8               Lscala/math/Ordering;
   #93 = Utf8               on
   #94 = Utf8               (Lscala/Function1;)Lscala/math/Ordering;
   #95 = Utf8               <U:Ljava/lang/Object;>(Lscala/Function1<TU;Ljava/lang/Object;>;)Lscala/math/Ordering<TU;>;
   #96 = Utf8               f
   #97 = Utf8               on$
   #98 = Utf8               (Lscala/math/Ordering;Lscala/Function1;)Lscala/math/Ordering;
   #99 = NameAndType        #97:#98       // on$:(Lscala/math/Ordering;Lscala/Function1;)Lscala/math/Ordering;
  #100 = InterfaceMethodref #11.#99       // scala/math/Ordering.on$:(Lscala/math/Ordering;Lscala/Function1;)Lscala/math/Ordering;
  #101 = Utf8               Lscala/Function1;
  #102 = Utf8               orElse
  #103 = Utf8               (Lscala/math/Ordering<Ljava/lang/Object;>;)Lscala/math/Ordering<Ljava/lang/Object;>;
  #104 = Utf8               orElse$
  #105 = Utf8               (Lscala/math/Ordering;Lscala/math/Ordering;)Lscala/math/Ordering;
  #106 = NameAndType        #104:#105     // orElse$:(Lscala/math/Ordering;Lscala/math/Ordering;)Lscala/math/Ordering;
  #107 = InterfaceMethodref #11.#106      // scala/math/Ordering.orElse$:(Lscala/math/Ordering;Lscala/math/Ordering;)Lscala/math/Ordering;
  #108 = Utf8               orElseBy
  #109 = Utf8               (Lscala/Function1;Lscala/math/Ordering;)Lscala/math/Ordering;
  #110 = Utf8               <S:Ljava/lang/Object;>(Lscala/Function1<Ljava/lang/Object;TS;>;Lscala/math/Ordering<TS;>;)Lscala/math/Ordering<Ljava/lang/Object;>;
  #111 = Utf8               ord
  #112 = Utf8               orElseBy$
  #113 = Utf8               (Lscala/math/Ordering;Lscala/Function1;Lscala/math/Ordering;)Lscala/math/Ordering;
  #114 = NameAndType        #112:#113     // orElseBy$:(Lscala/math/Ordering;Lscala/Function1;Lscala/math/Ordering;)Lscala/math/Ordering;
  #115 = InterfaceMethodref #11.#114      // scala/math/Ordering.orElseBy$:(Lscala/math/Ordering;Lscala/Function1;Lscala/math/Ordering;)Lscala/math/Ordering;
  #116 = Utf8               mkOrderingOps
  #117 = Utf8               (Ljava/lang/Object;)Lscala/math/Ordering$OrderingOps;
  #118 = Utf8               lhs
  #119 = Utf8               mkOrderingOps$
  #120 = Utf8               (Lscala/math/Ordering;Ljava/lang/Object;)Lscala/math/Ordering$OrderingOps;
  #121 = NameAndType        #119:#120     // mkOrderingOps$:(Lscala/math/Ordering;Ljava/lang/Object;)Lscala/math/Ordering$OrderingOps;
  #122 = InterfaceMethodref #11.#121      // scala/math/Ordering.mkOrderingOps$:(Lscala/math/Ordering;Ljava/lang/Object;)Lscala/math/Ordering$OrderingOps;
  #123 = Utf8               writeReplace
  #124 = Utf8               ()Ljava/lang/Object;
  #125 = Utf8               scala/runtime/ModuleSerializationProxy
  #126 = Class              #125          // scala/runtime/ModuleSerializationProxy
  #127 = Utf8               (Ljava/lang/Class;)V
  #128 = NameAndType        #22:#127      // "<init>":(Ljava/lang/Class;)V
  #129 = Methodref          #126.#128     // scala/runtime/ModuleSerializationProxy."<init>":(Ljava/lang/Class;)V
  #130 = Utf8               ()Lscala/math/PartialOrdering;
  #131 = NameAndType        #77:#78       // reverse:()Lscala/math/Ordering;
  #132 = Methodref          #2.#131       // scala/math/Ordering$Double$IeeeOrdering$.reverse:()Lscala/math/Ordering;
  #133 = Utf8               (Ljava/lang/Object;Ljava/lang/Object;)Lscala/Option;
  #134 = NameAndType        #70:#71       // tryCompare:(Ljava/lang/Object;Ljava/lang/Object;)Lscala/Some;
  #135 = Methodref          #2.#134       // scala/math/Ordering$Double$IeeeOrdering$.tryCompare:(Ljava/lang/Object;Ljava/lang/Object;)Lscala/Some;
  #136 = Utf8               (Ljava/lang/Object;Ljava/lang/Object;)Ljava/lang/Object;
  #137 = Utf8               scala/runtime/BoxesRunTime
  #138 = Class              #137          // scala/runtime/BoxesRunTime
  #139 = Utf8               unboxToDouble
  #140 = Utf8               (Ljava/lang/Object;)D
  #141 = NameAndType        #139:#140     // unboxToDouble:(Ljava/lang/Object;)D
  #142 = Methodref          #138.#141     // scala/runtime/BoxesRunTime.unboxToDouble:(Ljava/lang/Object;)D
  #143 = NameAndType        #66:#60       // min:(DD)D
  #144 = Methodref          #2.#143       // scala/math/Ordering$Double$IeeeOrdering$.min:(DD)D
  #145 = Utf8               boxToDouble
  #146 = Utf8               (D)Ljava/lang/Double;
  #147 = NameAndType        #145:#146     // boxToDouble:(D)Ljava/lang/Double;
  #148 = Methodref          #138.#147     // scala/runtime/BoxesRunTime.boxToDouble:(D)Ljava/lang/Double;
  #149 = NameAndType        #59:#60       // max:(DD)D
  #150 = Methodref          #2.#149       // scala/math/Ordering$Double$IeeeOrdering$.max:(DD)D
  #151 = Utf8               (Ljava/lang/Object;Ljava/lang/Object;)Z
  #152 = NameAndType        #55:#38       // equiv:(DD)Z
  #153 = Methodref          #2.#152       // scala/math/Ordering$Double$IeeeOrdering$.equiv:(DD)Z
  #154 = NameAndType        #51:#38       // gt:(DD)Z
  #155 = Methodref          #2.#154       // scala/math/Ordering$Double$IeeeOrdering$.gt:(DD)Z
  #156 = NameAndType        #47:#38       // lt:(DD)Z
  #157 = Methodref          #2.#156       // scala/math/Ordering$Double$IeeeOrdering$.lt:(DD)Z
  #158 = NameAndType        #43:#38       // gteq:(DD)Z
  #159 = Methodref          #2.#158       // scala/math/Ordering$Double$IeeeOrdering$.gteq:(DD)Z
  #160 = NameAndType        #37:#38       // lteq:(DD)Z
  #161 = Methodref          #2.#160       // scala/math/Ordering$Double$IeeeOrdering$.lteq:(DD)Z
  #162 = Utf8               (Ljava/lang/Object;Ljava/lang/Object;)I
  #163 = NameAndType        #27:#28       // compare:(DD)I
  #164 = Methodref          #2.#163       // scala/math/Ordering$Double$IeeeOrdering$.compare:(DD)I
  #165 = Methodref          #4.#23        // java/lang/Object."<init>":()V
  #166 = Utf8               Code
  #167 = Utf8               LineNumberTable
  #168 = Utf8               LocalVariableTable
  #169 = Utf8               MethodParameters
  #170 = Utf8               Signature
  #171 = Utf8               InnerClasses
  #172 = Utf8               SourceFile
  #173 = Utf8               ScalaInlineInfo
  #174 = Utf8               Scala
{
  public static final scala.math.Ordering$Double$IeeeOrdering$ MODULE$;
    descriptor: Lscala/math/Ordering$Double$IeeeOrdering$;
    flags: (0x0019) ACC_PUBLIC, ACC_STATIC, ACC_FINAL

  public static {};
    descriptor: ()V
    flags: (0x0009) ACC_PUBLIC, ACC_STATIC
    Code:
      stack=2, locals=0, args_size=0
         0: new           #2                  // class scala/math/Ordering$Double$IeeeOrdering$
         3: dup
         4: invokespecial #24                 // Method "<init>":()V
         7: putstatic     #26                 // Field MODULE$:Lscala/math/Ordering$Double$IeeeOrdering$;
        10: getstatic     #26                 // Field MODULE$:Lscala/math/Ordering$Double$IeeeOrdering$;
        13: pop
        14: getstatic     #26                 // Field MODULE$:Lscala/math/Ordering$Double$IeeeOrdering$;
        17: pop
        18: getstatic     #26                 // Field MODULE$:Lscala/math/Ordering$Double$IeeeOrdering$;
        21: pop
        22: return
      LineNumberTable:
        line 553: 0
        line 553: 18
        line 553: 22

  public int compare(double, double);
    descriptor: (DD)I
    flags: (0x0001) ACC_PUBLIC
    Code:
      stack=5, locals=5, args_size=3
         0: aload_0
         1: dload_1
         2: dload_3
         3: invokestatic  #34                 // InterfaceMethod scala/math/Ordering$Double$IeeeOrdering.compare$:(Lscala/math/Ordering$Double$IeeeOrdering;DD)I
         6: ireturn
      LineNumberTable:
        line 553: 0
      LocalVariableTable:
        Start  Length  Slot  Name   Signature
            0       7     0  this   Lscala/math/Ordering$Double$IeeeOrdering$;
            0       7     1     x   D
            0       7     3     y   D
    MethodParameters:
      Name                           Flags
      x                              final
      y                              final

  public boolean lteq(double, double);
    descriptor: (DD)Z
    flags: (0x0001) ACC_PUBLIC
    Code:
      stack=5, locals=5, args_size=3
         0: aload_0
         1: dload_1
         2: dload_3
         3: invokestatic  #42                 // InterfaceMethod scala/math/Ordering$Double$IeeeOrdering.lteq$:(Lscala/math/Ordering$Double$IeeeOrdering;DD)Z
         6: ireturn
      LineNumberTable:
        line 553: 0
      LocalVariableTable:
        Start  Length  Slot  Name   Signature
            0       7     0  this   Lscala/math/Ordering$Double$IeeeOrdering$;
            0       7     1     x   D
            0       7     3     y   D
    MethodParameters:
      Name                           Flags
      x                              final
      y                              final

  public boolean gteq(double, double);
    descriptor: (DD)Z
    flags: (0x0001) ACC_PUBLIC
    Code:
      stack=5, locals=5, args_size=3
         0: aload_0
         1: dload_1
         2: dload_3
         3: invokestatic  #46                 // InterfaceMethod scala/math/Ordering$Double$IeeeOrdering.gteq$:(Lscala/math/Ordering$Double$IeeeOrdering;DD)Z
         6: ireturn
      LineNumberTable:
        line 553: 0
      LocalVariableTable:
        Start  Length  Slot  Name   Signature
            0       7     0  this   Lscala/math/Ordering$Double$IeeeOrdering$;
            0       7     1     x   D
            0       7     3     y   D
    MethodParameters:
      Name                           Flags
      x                              final
      y                              final

  public boolean lt(double, double);
    descriptor: (DD)Z
    flags: (0x0001) ACC_PUBLIC
    Code:
      stack=5, locals=5, args_size=3
         0: aload_0
         1: dload_1
         2: dload_3
         3: invokestatic  #50                 // InterfaceMethod scala/math/Ordering$Double$IeeeOrdering.lt$:(Lscala/math/Ordering$Double$IeeeOrdering;DD)Z
         6: ireturn
      LineNumberTable:
        line 553: 0
      LocalVariableTable:
        Start  Length  Slot  Name   Signature
            0       7     0  this   Lscala/math/Ordering$Double$IeeeOrdering$;
            0       7     1     x   D
            0       7     3     y   D
    MethodParameters:
      Name                           Flags
      x                              final
      y                              final

  public boolean gt(double, double);
    descriptor: (DD)Z
    flags: (0x0001) ACC_PUBLIC
    Code:
      stack=5, locals=5, args_size=3
         0: aload_0
         1: dload_1
         2: dload_3
         3: invokestatic  #54                 // InterfaceMethod scala/math/Ordering$Double$IeeeOrdering.gt$:(Lscala/math/Ordering$Double$IeeeOrdering;DD)Z
         6: ireturn
      LineNumberTable:
        line 553: 0
      LocalVariableTable:
        Start  Length  Slot  Name   Signature
            0       7     0  this   Lscala/math/Ordering$Double$IeeeOrdering$;
            0       7     1     x   D
            0       7     3     y   D
    MethodParameters:
      Name                           Flags
      x                              final
      y                              final

  public boolean equiv(double, double);
    descriptor: (DD)Z
    flags: (0x0001) ACC_PUBLIC
    Code:
      stack=5, locals=5, args_size=3
         0: aload_0
         1: dload_1
         2: dload_3
         3: invokestatic  #58                 // InterfaceMethod scala/math/Ordering$Double$IeeeOrdering.equiv$:(Lscala/math/Ordering$Double$IeeeOrdering;DD)Z
         6: ireturn
      LineNumberTable:
        line 553: 0
      LocalVariableTable:
        Start  Length  Slot  Name   Signature
            0       7     0  this   Lscala/math/Ordering$Double$IeeeOrdering$;
            0       7     1     x   D
            0       7     3     y   D
    MethodParameters:
      Name                           Flags
      x                              final
      y                              final

  public <U extends java.lang.Object> U max(U, U);
    descriptor: (DD)D
    flags: (0x0001) ACC_PUBLIC
    Code:
      stack=5, locals=5, args_size=3
         0: aload_0
         1: dload_1
         2: dload_3
         3: invokestatic  #65                 // InterfaceMethod scala/math/Ordering$Double$IeeeOrdering.max$:(Lscala/math/Ordering$Double$IeeeOrdering;DD)D
         6: dreturn
      LineNumberTable:
        line 553: 0
      LocalVariableTable:
        Start  Length  Slot  Name   Signature
            0       7     0  this   Lscala/math/Ordering$Double$IeeeOrdering$;
            0       7     1     x   D
            0       7     3     y   D
    Signature: #61                          // <U:Ljava/lang/Object;>(TU;TU;)TU;
    MethodParameters:
      Name                           Flags
      x                              final
      y                              final

  public <U extends java.lang.Object> U min(U, U);
    descriptor: (DD)D
    flags: (0x0001) ACC_PUBLIC
    Code:
      stack=5, locals=5, args_size=3
         0: aload_0
         1: dload_1
         2: dload_3
         3: invokestatic  #69                 // InterfaceMethod scala/math/Ordering$Double$IeeeOrdering.min$:(Lscala/math/Ordering$Double$IeeeOrdering;DD)D
         6: dreturn
      LineNumberTable:
        line 553: 0
      LocalVariableTable:
        Start  Length  Slot  Name   Signature
            0       7     0  this   Lscala/math/Ordering$Double$IeeeOrdering$;
            0       7     1     x   D
            0       7     3     y   D
    Signature: #61                          // <U:Ljava/lang/Object;>(TU;TU;)TU;
    MethodParameters:
      Name                           Flags
      x                              final
      y                              final

  public scala.Some tryCompare(java.lang.Object, java.lang.Object);
    descriptor: (Ljava/lang/Object;Ljava/lang/Object;)Lscala/Some;
    flags: (0x0001) ACC_PUBLIC
    Code:
      stack=3, locals=3, args_size=3
         0: aload_0
         1: aload_1
         2: aload_2
         3: invokestatic  #75                 // InterfaceMethod scala/math/Ordering.tryCompare$:(Lscala/math/Ordering;Ljava/lang/Object;Ljava/lang/Object;)Lscala/Some;
         6: areturn
      LineNumberTable:
        line 553: 0
      LocalVariableTable:
        Start  Length  Slot  Name   Signature
            0       7     0  this   Lscala/math/Ordering$Double$IeeeOrdering$;
            0       7     1     x   Ljava/lang/Object;
            0       7     2     y   Ljava/lang/Object;
    MethodParameters:
      Name                           Flags
      x                              final
      y                              final

  public scala.math.Ordering<java.lang.Object> reverse();
    descriptor: ()Lscala/math/Ordering;
    flags: (0x0001) ACC_PUBLIC
    Code:
      stack=1, locals=1, args_size=1
         0: aload_0
         1: invokestatic  #83                 // InterfaceMethod scala/math/Ordering.reverse$:(Lscala/math/Ordering;)Lscala/math/Ordering;
         4: areturn
      LineNumberTable:
        line 553: 0
      LocalVariableTable:
        Start  Length  Slot  Name   Signature
            0       5     0  this   Lscala/math/Ordering$Double$IeeeOrdering$;
    Signature: #79                          // ()Lscala/math/Ordering<Ljava/lang/Object;>;

  public boolean isReverseOf(scala.math.Ordering<?>);
    descriptor: (Lscala/math/Ordering;)Z
    flags: (0x0001) ACC_PUBLIC
    Code:
      stack=2, locals=2, args_size=2
         0: aload_0
         1: aload_1
         2: invokestatic  #91                 // InterfaceMethod scala/math/Ordering.isReverseOf$:(Lscala/math/Ordering;Lscala/math/Ordering;)Z
         5: ireturn
      LineNumberTable:
        line 553: 0
      LocalVariableTable:
        Start  Length  Slot  Name   Signature
            0       6     0  this   Lscala/math/Ordering$Double$IeeeOrdering$;
            0       6     1 other   Lscala/math/Ordering;
    Signature: #86                          // (Lscala/math/Ordering<*>;)Z
    MethodParameters:
      Name                           Flags
      other                          final

  public <U extends java.lang.Object> scala.math.Ordering<U> on(scala.Function1<U, java.lang.Object>);
    descriptor: (Lscala/Function1;)Lscala/math/Ordering;
    flags: (0x0001) ACC_PUBLIC
    Code:
      stack=2, locals=2, args_size=2
         0: aload_0
         1: aload_1
         2: invokestatic  #100                // InterfaceMethod scala/math/Ordering.on$:(Lscala/math/Ordering;Lscala/Function1;)Lscala/math/Ordering;
         5: areturn
      LineNumberTable:
        line 553: 0
      LocalVariableTable:
        Start  Length  Slot  Name   Signature
            0       6     0  this   Lscala/math/Ordering$Double$IeeeOrdering$;
            0       6     1     f   Lscala/Function1;
    Signature: #95                          // <U:Ljava/lang/Object;>(Lscala/Function1<TU;Ljava/lang/Object;>;)Lscala/math/Ordering<TU;>;
    MethodParameters:
      Name                           Flags
      f                              final

  public scala.math.Ordering<java.lang.Object> orElse(scala.math.Ordering<java.lang.Object>);
    descriptor: (Lscala/math/Ordering;)Lscala/math/Ordering;
    flags: (0x0001) ACC_PUBLIC
    Code:
      stack=2, locals=2, args_size=2
         0: aload_0
         1: aload_1
         2: invokestatic  #107                // InterfaceMethod scala/math/Ordering.orElse$:(Lscala/math/Ordering;Lscala/math/Ordering;)Lscala/math/Ordering;
         5: areturn
      LineNumberTable:
        line 553: 0
      LocalVariableTable:
        Start  Length  Slot  Name   Signature
            0       6     0  this   Lscala/math/Ordering$Double$IeeeOrdering$;
            0       6     1 other   Lscala/math/Ordering;
    Signature: #103                         // (Lscala/math/Ordering<Ljava/lang/Object;>;)Lscala/math/Ordering<Ljava/lang/Object;>;
    MethodParameters:
      Name                           Flags
      other                          final

  public <S extends java.lang.Object> scala.math.Ordering<java.lang.Object> orElseBy(scala.Function1<java.lang.Object, S>, scala.math.Ordering<S>);
    descriptor: (Lscala/Function1;Lscala/math/Ordering;)Lscala/math/Ordering;
    flags: (0x0001) ACC_PUBLIC
    Code:
      stack=3, locals=3, args_size=3
         0: aload_0
         1: aload_1
         2: aload_2
         3: invokestatic  #115                // InterfaceMethod scala/math/Ordering.orElseBy$:(Lscala/math/Ordering;Lscala/Function1;Lscala/math/Ordering;)Lscala/math/Ordering;
         6: areturn
      LineNumberTable:
        line 553: 0
      LocalVariableTable:
        Start  Length  Slot  Name   Signature
            0       7     0  this   Lscala/math/Ordering$Double$IeeeOrdering$;
            0       7     1     f   Lscala/Function1;
            0       7     2   ord   Lscala/math/Ordering;
    Signature: #110                         // <S:Ljava/lang/Object;>(Lscala/Function1<Ljava/lang/Object;TS;>;Lscala/math/Ordering<TS;>;)Lscala/math/Ordering<Ljava/lang/Object;>;
    MethodParameters:
      Name                           Flags
      f                              final
      ord                            final

  public scala.math.Ordering$OrderingOps mkOrderingOps(java.lang.Object);
    descriptor: (Ljava/lang/Object;)Lscala/math/Ordering$OrderingOps;
    flags: (0x0001) ACC_PUBLIC
    Code:
      stack=2, locals=2, args_size=2
         0: aload_0
         1: aload_1
         2: invokestatic  #122                // InterfaceMethod scala/math/Ordering.mkOrderingOps$:(Lscala/math/Ordering;Ljava/lang/Object;)Lscala/math/Ordering$OrderingOps;
         5: areturn
      LineNumberTable:
        line 553: 0
      LocalVariableTable:
        Start  Length  Slot  Name   Signature
            0       6     0  this   Lscala/math/Ordering$Double$IeeeOrdering$;
            0       6     1   lhs   Ljava/lang/Object;
    Signature: #117                         // (Ljava/lang/Object;)Lscala/math/Ordering$OrderingOps;
    MethodParameters:
      Name                           Flags
      lhs                            final

  private java.lang.Object writeReplace();
    descriptor: ()Ljava/lang/Object;
    flags: (0x0002) ACC_PRIVATE
    Code:
      stack=3, locals=1, args_size=1
         0: new           #126                // class scala/runtime/ModuleSerializationProxy
         3: dup
         4: ldc           #2                  // class scala/math/Ordering$Double$IeeeOrdering$
         6: invokespecial #129                // Method scala/runtime/ModuleSerializationProxy."<init>":(Ljava/lang/Class;)V
         9: areturn
      LineNumberTable:
        line 553: 0
      LocalVariableTable:
        Start  Length  Slot  Name   Signature
            0      10     0  this   Lscala/math/Ordering$Double$IeeeOrdering$;

  public scala.math.PartialOrdering reverse();
    descriptor: ()Lscala/math/PartialOrdering;
    flags: (0x1041) ACC_PUBLIC, ACC_BRIDGE, ACC_SYNTHETIC
    Code:
      stack=1, locals=1, args_size=1
         0: aload_0
         1: invokevirtual #132                // Method reverse:()Lscala/math/Ordering;
         4: areturn
      LineNumberTable:
        line 553: 0
      LocalVariableTable:
        Start  Length  Slot  Name   Signature
            0       5     0  this   Lscala/math/Ordering$Double$IeeeOrdering$;

  public scala.Option tryCompare(java.lang.Object, java.lang.Object);
    descriptor: (Ljava/lang/Object;Ljava/lang/Object;)Lscala/Option;
    flags: (0x1041) ACC_PUBLIC, ACC_BRIDGE, ACC_SYNTHETIC
    Code:
      stack=3, locals=3, args_size=3
         0: aload_0
         1: aload_1
         2: aload_2
         3: invokevirtual #135                // Method tryCompare:(Ljava/lang/Object;Ljava/lang/Object;)Lscala/Some;
         6: areturn
      LineNumberTable:
        line 553: 0
      LocalVariableTable:
        Start  Length  Slot  Name   Signature
            0       7     0  this   Lscala/math/Ordering$Double$IeeeOrdering$;
            0       7     1     x   Ljava/lang/Object;
            0       7     2     y   Ljava/lang/Object;
    MethodParameters:
      Name                           Flags
      x                              final
      y                              final

  public java.lang.Object min(java.lang.Object, java.lang.Object);
    descriptor: (Ljava/lang/Object;Ljava/lang/Object;)Ljava/lang/Object;
    flags: (0x1041) ACC_PUBLIC, ACC_BRIDGE, ACC_SYNTHETIC
    Code:
      stack=5, locals=3, args_size=3
         0: aload_0
         1: aload_1
         2: invokestatic  #142                // Method scala/runtime/BoxesRunTime.unboxToDouble:(Ljava/lang/Object;)D
         5: aload_2
         6: invokestatic  #142                // Method scala/runtime/BoxesRunTime.unboxToDouble:(Ljava/lang/Object;)D
         9: invokevirtual #144                // Method min:(DD)D
        12: invokestatic  #148                // Method scala/runtime/BoxesRunTime.boxToDouble:(D)Ljava/lang/Double;
        15: areturn
      LineNumberTable:
        line 553: 0
      LocalVariableTable:
        Start  Length  Slot  Name   Signature
            0      16     0  this   Lscala/math/Ordering$Double$IeeeOrdering$;
            0      16     1     x   Ljava/lang/Object;
            0      16     2     y   Ljava/lang/Object;
    MethodParameters:
      Name                           Flags
      x                              final
      y                              final

  public java.lang.Object max(java.lang.Object, java.lang.Object);
    descriptor: (Ljava/lang/Object;Ljava/lang/Object;)Ljava/lang/Object;
    flags: (0x1041) ACC_PUBLIC, ACC_BRIDGE, ACC_SYNTHETIC
    Code:
      stack=5, locals=3, args_size=3
         0: aload_0
         1: aload_1
         2: invokestatic  #142                // Method scala/runtime/BoxesRunTime.unboxToDouble:(Ljava/lang/Object;)D
         5: aload_2
         6: invokestatic  #142                // Method scala/runtime/BoxesRunTime.unboxToDouble:(Ljava/lang/Object;)D
         9: invokevirtual #150                // Method max:(DD)D
        12: invokestatic  #148                // Method scala/runtime/BoxesRunTime.boxToDouble:(D)Ljava/lang/Double;
        15: areturn
      LineNumberTable:
        line 553: 0
      LocalVariableTable:
        Start  Length  Slot  Name   Signature
            0      16     0  this   Lscala/math/Ordering$Double$IeeeOrdering$;
            0      16     1     x   Ljava/lang/Object;
            0      16     2     y   Ljava/lang/Object;
    MethodParameters:
      Name                           Flags
      x                              final
      y                              final

  public boolean equiv(java.lang.Object, java.lang.Object);
    descriptor: (Ljava/lang/Object;Ljava/lang/Object;)Z
    flags: (0x1041) ACC_PUBLIC, ACC_BRIDGE, ACC_SYNTHETIC
    Code:
      stack=5, locals=3, args_size=3
         0: aload_0
         1: aload_1
         2: invokestatic  #142                // Method scala/runtime/BoxesRunTime.unboxToDouble:(Ljava/lang/Object;)D
         5: aload_2
         6: invokestatic  #142                // Method scala/runtime/BoxesRunTime.unboxToDouble:(Ljava/lang/Object;)D
         9: invokevirtual #153                // Method equiv:(DD)Z
        12: ireturn
      LineNumberTable:
        line 553: 0
      LocalVariableTable:
        Start  Length  Slot  Name   Signature
            0      13     0  this   Lscala/math/Ordering$Double$IeeeOrdering$;
            0      13     1     x   Ljava/lang/Object;
            0      13     2     y   Ljava/lang/Object;
    MethodParameters:
      Name                           Flags
      x                              final
      y                              final

  public boolean gt(java.lang.Object, java.lang.Object);
    descriptor: (Ljava/lang/Object;Ljava/lang/Object;)Z
    flags: (0x1041) ACC_PUBLIC, ACC_BRIDGE, ACC_SYNTHETIC
    Code:
      stack=5, locals=3, args_size=3
         0: aload_0
         1: aload_1
         2: invokestatic  #142                // Method scala/runtime/BoxesRunTime.unboxToDouble:(Ljava/lang/Object;)D
         5: aload_2
         6: invokestatic  #142                // Method scala/runtime/BoxesRunTime.unboxToDouble:(Ljava/lang/Object;)D
         9: invokevirtual #155                // Method gt:(DD)Z
        12: ireturn
      LineNumberTable:
        line 553: 0
      LocalVariableTable:
        Start  Length  Slot  Name   Signature
            0      13     0  this   Lscala/math/Ordering$Double$IeeeOrdering$;
            0      13     1     x   Ljava/lang/Object;
            0      13     2     y   Ljava/lang/Object;
    MethodParameters:
      Name                           Flags
      x                              final
      y                              final

  public boolean lt(java.lang.Object, java.lang.Object);
    descriptor: (Ljava/lang/Object;Ljava/lang/Object;)Z
    flags: (0x1041) ACC_PUBLIC, ACC_BRIDGE, ACC_SYNTHETIC
    Code:
      stack=5, locals=3, args_size=3
         0: aload_0
         1: aload_1
         2: invokestatic  #142                // Method scala/runtime/BoxesRunTime.unboxToDouble:(Ljava/lang/Object;)D
         5: aload_2
         6: invokestatic  #142                // Method scala/runtime/BoxesRunTime.unboxToDouble:(Ljava/lang/Object;)D
         9: invokevirtual #157                // Method lt:(DD)Z
        12: ireturn
      LineNumberTable:
        line 553: 0
      LocalVariableTable:
        Start  Length  Slot  Name   Signature
            0      13     0  this   Lscala/math/Ordering$Double$IeeeOrdering$;
            0      13     1     x   Ljava/lang/Object;
            0      13     2     y   Ljava/lang/Object;
    MethodParameters:
      Name                           Flags
      x                              final
      y                              final

  public boolean gteq(java.lang.Object, java.lang.Object);
    descriptor: (Ljava/lang/Object;Ljava/lang/Object;)Z
    flags: (0x1041) ACC_PUBLIC, ACC_BRIDGE, ACC_SYNTHETIC
    Code:
      stack=5, locals=3, args_size=3
         0: aload_0
         1: aload_1
         2: invokestatic  #142                // Method scala/runtime/BoxesRunTime.unboxToDouble:(Ljava/lang/Object;)D
         5: aload_2
         6: invokestatic  #142                // Method scala/runtime/BoxesRunTime.unboxToDouble:(Ljava/lang/Object;)D
         9: invokevirtual #159                // Method gteq:(DD)Z
        12: ireturn
      LineNumberTable:
        line 553: 0
      LocalVariableTable:
        Start  Length  Slot  Name   Signature
            0      13     0  this   Lscala/math/Ordering$Double$IeeeOrdering$;
            0      13     1     x   Ljava/lang/Object;
            0      13     2     y   Ljava/lang/Object;
    MethodParameters:
      Name                           Flags
      x                              final
      y                              final

  public boolean lteq(java.lang.Object, java.lang.Object);
    descriptor: (Ljava/lang/Object;Ljava/lang/Object;)Z
    flags: (0x1041) ACC_PUBLIC, ACC_BRIDGE, ACC_SYNTHETIC
    Code:
      stack=5, locals=3, args_size=3
         0: aload_0
         1: aload_1
         2: invokestatic  #142                // Method scala/runtime/BoxesRunTime.unboxToDouble:(Ljava/lang/Object;)D
         5: aload_2
         6: invokestatic  #142                // Method scala/runtime/BoxesRunTime.unboxToDouble:(Ljava/lang/Object;)D
         9: invokevirtual #161                // Method lteq:(DD)Z
        12: ireturn
      LineNumberTable:
        line 553: 0
      LocalVariableTable:
        Start  Length  Slot  Name   Signature
            0      13     0  this   Lscala/math/Ordering$Double$IeeeOrdering$;
            0      13     1     x   Ljava/lang/Object;
            0      13     2     y   Ljava/lang/Object;
    MethodParameters:
      Name                           Flags
      x                              final
      y                              final

  public int compare(java.lang.Object, java.lang.Object);
    descriptor: (Ljava/lang/Object;Ljava/lang/Object;)I
    flags: (0x1041) ACC_PUBLIC, ACC_BRIDGE, ACC_SYNTHETIC
    Code:
      stack=5, locals=3, args_size=3
         0: aload_0
         1: aload_1
         2: invokestatic  #142                // Method scala/runtime/BoxesRunTime.unboxToDouble:(Ljava/lang/Object;)D
         5: aload_2
         6: invokestatic  #142                // Method scala/runtime/BoxesRunTime.unboxToDouble:(Ljava/lang/Object;)D
         9: invokevirtual #164                // Method compare:(DD)I
        12: ireturn
      LineNumberTable:
        line 553: 0
      LocalVariableTable:
        Start  Length  Slot  Name   Signature
            0      13     0  this   Lscala/math/Ordering$Double$IeeeOrdering$;
            0      13     1     x   Ljava/lang/Object;
            0      13     2     y   Ljava/lang/Object;
    MethodParameters:
      Name                           Flags
      x                              final
      y                              final

  public scala.math.Ordering$Double$IeeeOrdering$();
    descriptor: ()V
    flags: (0x0001) ACC_PUBLIC
    Code:
      stack=1, locals=1, args_size=1
         0: aload_0
         1: invokespecial #165                // Method java/lang/Object."<init>":()V
         4: return
      LineNumberTable:
        line 553: 0
      LocalVariableTable:
        Start  Length  Slot  Name   Signature
            0       5     0  this   Lscala/math/Ordering$Double$IeeeOrdering$;
}
InnerClasses:
  public static #12= #9 of #11;           // Double$=class scala/math/Ordering$Double$ of class scala/math/Ordering
  public static #13= #6 of #9;            // IeeeOrdering=class scala/math/Ordering$Double$IeeeOrdering of class scala/math/Ordering$Double$
  public static #14= #2 of #9;            // IeeeOrdering$=class scala/math/Ordering$Double$IeeeOrdering$ of class scala/math/Ordering$Double$
  public #17= #16 of #11;                 // OrderingOps=class scala/math/Ordering$OrderingOps of class scala/math/Ordering
SourceFile: "Ordering.scala"
  ScalaInlineInfo: length = 0x8B (unknown attribute)
   01 01 00 1B 00 16 00 15 01 00 1B 00 1C 01 00 1B
   00 A2 01 00 37 00 26 01 00 37 00 97 01 00 33 00
   26 01 00 33 00 97 01 00 2B 00 26 01 00 2B 00 97
   01 00 54 00 55 01 00 2F 00 26 01 00 2F 00 97 01
   00 25 00 26 01 00 25 00 97 01 00 3B 00 3C 01 00
   3B 00 88 01 00 42 00 3C 01 00 42 00 88 01 00 74
   00 75 01 00 5D 00 5E 01 00 66 00 51 01 00 6C 00
   6D 01 00 4D 00 4E 01 00 4D 00 82 01 00 46 00 85
   01 00 46 00 47 01 00 7B 00 7C 01
  Scala: length = 0x0 (unknown attribute)

