Classfile /Users/mw/Projects/slang-braindump/.jar/jar8/assemble/slang-braindump/assemble/content/scala/math/Ordering$ExtraImplicits.class
  Last modified May 29, 2022; size 2192 bytes
  SHA-256 checksum 2f5fac92650ed38d183168bdb4abebef802b53282723037136c43c406bae3d55
  Compiled from "Ordering.scala"
public interface scala.math.Ordering$ExtraImplicits
  minor version: 0
  major version: 52
  flags: (0x0601) ACC_PUBLIC, ACC_INTERFACE, ACC_ABSTRACT
  this_class: #2                          // scala/math/Ordering$ExtraImplicits
  super_class: #4                         // java/lang/Object
  interfaces: 0, fields: 0, methods: 7, attributes: 4
Constant pool:
   #1 = Utf8               scala/math/Ordering$ExtraImplicits
   #2 = Class              #1             // scala/math/Ordering$ExtraImplicits
   #3 = Utf8               java/lang/Object
   #4 = Class              #3             // java/lang/Object
   #5 = Utf8               Ordering.scala
   #6 = Utf8               scala/math/Ordering
   #7 = Class              #6             // scala/math/Ordering
   #8 = Utf8               ExtraImplicits
   #9 = Utf8               scala/math/Ordering$IterableOrdering
  #10 = Class              #9             // scala/math/Ordering$IterableOrdering
  #11 = Utf8               IterableOrdering
  #12 = Utf8               scala/math/Ordering$OrderingOps
  #13 = Class              #12            // scala/math/Ordering$OrderingOps
  #14 = Utf8               OrderingOps
  #15 = Utf8               seqOrdering$
  #16 = Utf8               (Lscala/math/Ordering$ExtraImplicits;Lscala/math/Ordering;)Lscala/math/Ordering;
  #17 = Utf8               $this
  #18 = Utf8               ord
  #19 = Utf8               seqOrdering
  #20 = Utf8               (Lscala/math/Ordering;)Lscala/math/Ordering;
  #21 = NameAndType        #19:#20        // seqOrdering:(Lscala/math/Ordering;)Lscala/math/Ordering;
  #22 = InterfaceMethodref #2.#21         // scala/math/Ordering$ExtraImplicits.seqOrdering:(Lscala/math/Ordering;)Lscala/math/Ordering;
  #23 = Utf8               Lscala/math/Ordering$ExtraImplicits;
  #24 = Utf8               Lscala/math/Ordering;
  #25 = Utf8               <CC::Lscala/collection/Seq<Ljava/lang/Object;>;T:Ljava/lang/Object;>(Lscala/math/Ordering<TT;>;)Lscala/math/Ordering<TCC;>;
  #26 = Utf8               <init>
  #27 = Utf8               (Lscala/math/Ordering;)V
  #28 = NameAndType        #26:#27        // "<init>":(Lscala/math/Ordering;)V
  #29 = Methodref          #10.#28        // scala/math/Ordering$IterableOrdering."<init>":(Lscala/math/Ordering;)V
  #30 = Utf8               this
  #31 = Utf8               sortedSetOrdering$
  #32 = Utf8               sortedSetOrdering
  #33 = NameAndType        #32:#20        // sortedSetOrdering:(Lscala/math/Ordering;)Lscala/math/Ordering;
  #34 = InterfaceMethodref #2.#33         // scala/math/Ordering$ExtraImplicits.sortedSetOrdering:(Lscala/math/Ordering;)Lscala/math/Ordering;
  #35 = Utf8               <CC::Lscala/collection/SortedSet<Ljava/lang/Object;>;T:Ljava/lang/Object;>(Lscala/math/Ordering<TT;>;)Lscala/math/Ordering<TCC;>;
  #36 = Utf8               infixOrderingOps$
  #37 = Utf8               (Lscala/math/Ordering$ExtraImplicits;Ljava/lang/Object;Lscala/math/Ordering;)Lscala/math/Ordering$OrderingOps;
  #38 = Utf8               x
  #39 = Utf8               infixOrderingOps
  #40 = Utf8               (Ljava/lang/Object;Lscala/math/Ordering;)Lscala/math/Ordering$OrderingOps;
  #41 = NameAndType        #39:#40        // infixOrderingOps:(Ljava/lang/Object;Lscala/math/Ordering;)Lscala/math/Ordering$OrderingOps;
  #42 = InterfaceMethodref #2.#41         // scala/math/Ordering$ExtraImplicits.infixOrderingOps:(Ljava/lang/Object;Lscala/math/Ordering;)Lscala/math/Ordering$OrderingOps;
  #43 = Utf8               Ljava/lang/Object;
  #44 = Utf8               <T:Ljava/lang/Object;>(TT;Lscala/math/Ordering<TT;>;)Lscala/math/Ordering<TT;>.OrderingOps;
  #45 = Utf8               (Lscala/math/Ordering;Ljava/lang/Object;)V
  #46 = NameAndType        #26:#45        // "<init>":(Lscala/math/Ordering;Ljava/lang/Object;)V
  #47 = Methodref          #13.#46        // scala/math/Ordering$OrderingOps."<init>":(Lscala/math/Ordering;Ljava/lang/Object;)V
  #48 = Utf8               $init$
  #49 = Utf8               (Lscala/math/Ordering$ExtraImplicits;)V
  #50 = Utf8               Code
  #51 = Utf8               LineNumberTable
  #52 = Utf8               LocalVariableTable
  #53 = Utf8               MethodParameters
  #54 = Utf8               Signature
  #55 = Utf8               InnerClasses
  #56 = Utf8               SourceFile
  #57 = Utf8               ScalaInlineInfo
  #58 = Utf8               Scala
{
  public static scala.math.Ordering seqOrdering$(scala.math.Ordering$ExtraImplicits, scala.math.Ordering);
    descriptor: (Lscala/math/Ordering$ExtraImplicits;Lscala/math/Ordering;)Lscala/math/Ordering;
    flags: (0x1009) ACC_PUBLIC, ACC_STATIC, ACC_SYNTHETIC
    Code:
      stack=2, locals=2, args_size=2
         0: aload_0
         1: aload_1
         2: invokespecial #22                 // InterfaceMethod seqOrdering:(Lscala/math/Ordering;)Lscala/math/Ordering;
         5: areturn
      LineNumberTable:
        line 293: 0
      LocalVariableTable:
        Start  Length  Slot  Name   Signature
            0       6     0 $this   Lscala/math/Ordering$ExtraImplicits;
            0       6     1   ord   Lscala/math/Ordering;
    MethodParameters:
      Name                           Flags
      $this                          final synthetic
      ord                            final

  public default <CC extends scala.collection.Seq<java.lang.Object>, T extends java.lang.Object> scala.math.Ordering<CC> seqOrdering(scala.math.Ordering<T>);
    descriptor: (Lscala/math/Ordering;)Lscala/math/Ordering;
    flags: (0x0001) ACC_PUBLIC
    Code:
      stack=3, locals=2, args_size=2
         0: new           #10                 // class scala/math/Ordering$IterableOrdering
         3: dup
         4: aload_1
         5: invokespecial #29                 // Method scala/math/Ordering$IterableOrdering."<init>":(Lscala/math/Ordering;)V
         8: areturn
      LineNumberTable:
        line 294: 0
      LocalVariableTable:
        Start  Length  Slot  Name   Signature
            0       9     0  this   Lscala/math/Ordering$ExtraImplicits;
            0       9     1   ord   Lscala/math/Ordering;
    Signature: #25                          // <CC::Lscala/collection/Seq<Ljava/lang/Object;>;T:Ljava/lang/Object;>(Lscala/math/Ordering<TT;>;)Lscala/math/Ordering<TCC;>;
    MethodParameters:
      Name                           Flags
      ord                            final

  public static scala.math.Ordering sortedSetOrdering$(scala.math.Ordering$ExtraImplicits, scala.math.Ordering);
    descriptor: (Lscala/math/Ordering$ExtraImplicits;Lscala/math/Ordering;)Lscala/math/Ordering;
    flags: (0x1009) ACC_PUBLIC, ACC_STATIC, ACC_SYNTHETIC
    Code:
      stack=2, locals=2, args_size=2
         0: aload_0
         1: aload_1
         2: invokespecial #34                 // InterfaceMethod sortedSetOrdering:(Lscala/math/Ordering;)Lscala/math/Ordering;
         5: areturn
      LineNumberTable:
        line 296: 0
      LocalVariableTable:
        Start  Length  Slot  Name   Signature
            0       6     0 $this   Lscala/math/Ordering$ExtraImplicits;
            0       6     1   ord   Lscala/math/Ordering;
    MethodParameters:
      Name                           Flags
      $this                          final synthetic
      ord                            final

  public default <CC extends scala.collection.SortedSet<java.lang.Object>, T extends java.lang.Object> scala.math.Ordering<CC> sortedSetOrdering(scala.math.Ordering<T>);
    descriptor: (Lscala/math/Ordering;)Lscala/math/Ordering;
    flags: (0x0001) ACC_PUBLIC
    Code:
      stack=3, locals=2, args_size=2
         0: new           #10                 // class scala/math/Ordering$IterableOrdering
         3: dup
         4: aload_1
         5: invokespecial #29                 // Method scala/math/Ordering$IterableOrdering."<init>":(Lscala/math/Ordering;)V
         8: areturn
      LineNumberTable:
        line 297: 0
      LocalVariableTable:
        Start  Length  Slot  Name   Signature
            0       9     0  this   Lscala/math/Ordering$ExtraImplicits;
            0       9     1   ord   Lscala/math/Ordering;
    Signature: #35                          // <CC::Lscala/collection/SortedSet<Ljava/lang/Object;>;T:Ljava/lang/Object;>(Lscala/math/Ordering<TT;>;)Lscala/math/Ordering<TCC;>;
    MethodParameters:
      Name                           Flags
      ord                            final

  public static scala.math.Ordering$OrderingOps infixOrderingOps$(scala.math.Ordering$ExtraImplicits, java.lang.Object, scala.math.Ordering);
    descriptor: (Lscala/math/Ordering$ExtraImplicits;Ljava/lang/Object;Lscala/math/Ordering;)Lscala/math/Ordering$OrderingOps;
    flags: (0x1009) ACC_PUBLIC, ACC_STATIC, ACC_SYNTHETIC
    Code:
      stack=3, locals=3, args_size=3
         0: aload_0
         1: aload_1
         2: aload_2
         3: invokespecial #42                 // InterfaceMethod infixOrderingOps:(Ljava/lang/Object;Lscala/math/Ordering;)Lscala/math/Ordering$OrderingOps;
         6: areturn
      LineNumberTable:
        line 307: 0
      LocalVariableTable:
        Start  Length  Slot  Name   Signature
            0       7     0 $this   Lscala/math/Ordering$ExtraImplicits;
            0       7     1     x   Ljava/lang/Object;
            0       7     2   ord   Lscala/math/Ordering;
    MethodParameters:
      Name                           Flags
      $this                          final synthetic
      x                              final
      ord                            final

  public default <T extends java.lang.Object> scala.math.Ordering<T>.OrderingOps infixOrderingOps(T, scala.math.Ordering<T>);
    descriptor: (Ljava/lang/Object;Lscala/math/Ordering;)Lscala/math/Ordering$OrderingOps;
    flags: (0x0001) ACC_PUBLIC
    Code:
      stack=4, locals=3, args_size=3
         0: new           #13                 // class scala/math/Ordering$OrderingOps
         3: dup
         4: aload_2
         5: aload_1
         6: invokespecial #47                 // Method scala/math/Ordering$OrderingOps."<init>":(Lscala/math/Ordering;Ljava/lang/Object;)V
         9: areturn
      LineNumberTable:
        line 307: 0
      LocalVariableTable:
        Start  Length  Slot  Name   Signature
            0      10     0  this   Lscala/math/Ordering$ExtraImplicits;
            0      10     1     x   Ljava/lang/Object;
            0      10     2   ord   Lscala/math/Ordering;
    Signature: #44                          // <T:Ljava/lang/Object;>(TT;Lscala/math/Ordering<TT;>;)Lscala/math/Ordering<TT;>.OrderingOps;
    MethodParameters:
      Name                           Flags
      x                              final
      ord                            final

  public static void $init$(scala.math.Ordering$ExtraImplicits);
    descriptor: (Lscala/math/Ordering$ExtraImplicits;)V
    flags: (0x0009) ACC_PUBLIC, ACC_STATIC
    Code:
      stack=0, locals=1, args_size=1
         0: return
      LineNumberTable:
        line 289: 0
      LocalVariableTable:
        Start  Length  Slot  Name   Signature
            0       1     0 $this   Lscala/math/Ordering$ExtraImplicits;
    MethodParameters:
      Name                           Flags
      $this                          final synthetic
}
InnerClasses:
  public static #8= #2 of #7;             // ExtraImplicits=class scala/math/Ordering$ExtraImplicits of class scala/math/Ordering
  private static final #11= #10 of #7;    // IterableOrdering=class scala/math/Ordering$IterableOrdering of class scala/math/Ordering
  public #14= #13 of #7;                  // OrderingOps=class scala/math/Ordering$OrderingOps of class scala/math/Ordering
SourceFile: "Ordering.scala"
  ScalaInlineInfo: length = 0x27 (unknown attribute)
   01 00 00 07 00 30 00 31 01 00 27 00 28 00 00 24
   00 25 01 00 13 00 14 00 00 0F 00 10 01 00 20 00
   14 00 00 1F 00 10 01
  Scala: length = 0x0 (unknown attribute)

