Classfile /Users/mw/Projects/slang-braindump/.jar/jar8/assemble/slang-braindump/assemble/content/scala/math/Ordering$Tuple9Ordering.class
  Last modified May 29, 2022; size 9314 bytes
  SHA-256 checksum db6935a0bbe01b92c0bd0726f040f12cc11b4d9936869340d5c918aad4ba2389
  Compiled from "Ordering.scala"
public final class scala.math.Ordering$Tuple9Ordering<T1 extends java.lang.Object, T2 extends java.lang.Object, T3 extends java.lang.Object, T4 extends java.lang.Object, T5 extends java.lang.Object, T6 extends java.lang.Object, T7 extends java.lang.Object, T8 extends java.lang.Object, T9 extends java.lang.Object> extends java.lang.Object implements scala.math.Ordering<scala.Tuple9<T1, T2, T3, T4, T5, T6, T7, T8, T9>>
  minor version: 0
  major version: 52
  flags: (0x0031) ACC_PUBLIC, ACC_FINAL, ACC_SUPER
  this_class: #2                          // scala/math/Ordering$Tuple9Ordering
  super_class: #5                         // java/lang/Object
  interfaces: 1, fields: 9, methods: 30, attributes: 5
Constant pool:
    #1 = Utf8               scala/math/Ordering$Tuple9Ordering
    #2 = Class              #1            // scala/math/Ordering$Tuple9Ordering
    #3 = Utf8               <T1:Ljava/lang/Object;T2:Ljava/lang/Object;T3:Ljava/lang/Object;T4:Ljava/lang/Object;T5:Ljava/lang/Object;T6:Ljava/lang/Object;T7:Ljava/lang/Object;T8:Ljava/lang/Object;T9:Ljava/lang/Object;>Ljava/lang/Object;Lscala/math/Ordering<Lscala/Tuple9<TT1;TT2;TT3;TT4;TT5;TT6;TT7;TT8;TT9;>;>;
    #4 = Utf8               java/lang/Object
    #5 = Class              #4            // java/lang/Object
    #6 = Utf8               scala/math/Ordering
    #7 = Class              #6            // scala/math/Ordering
    #8 = Utf8               Ordering.scala
    #9 = Utf8               scala/math/Ordering$OrderingOps
   #10 = Class              #9            // scala/math/Ordering$OrderingOps
   #11 = Utf8               OrderingOps
   #12 = Utf8               Tuple9Ordering
   #13 = Utf8               ord1
   #14 = Utf8               Lscala/math/Ordering;
   #15 = Utf8               Lscala/math/Ordering<TT1;>;
   #16 = Utf8               ord2
   #17 = Utf8               Lscala/math/Ordering<TT2;>;
   #18 = Utf8               ord3
   #19 = Utf8               Lscala/math/Ordering<TT3;>;
   #20 = Utf8               ord4
   #21 = Utf8               Lscala/math/Ordering<TT4;>;
   #22 = Utf8               ord5
   #23 = Utf8               Lscala/math/Ordering<TT5;>;
   #24 = Utf8               ord6
   #25 = Utf8               Lscala/math/Ordering<TT6;>;
   #26 = Utf8               ord7
   #27 = Utf8               Lscala/math/Ordering<TT7;>;
   #28 = Utf8               ord8
   #29 = Utf8               Lscala/math/Ordering<TT8;>;
   #30 = Utf8               ord9
   #31 = Utf8               Lscala/math/Ordering<TT9;>;
   #32 = Utf8               tryCompare
   #33 = Utf8               (Ljava/lang/Object;Ljava/lang/Object;)Lscala/Some;
   #34 = Utf8               x
   #35 = Utf8               y
   #36 = Utf8               tryCompare$
   #37 = Utf8               (Lscala/math/Ordering;Ljava/lang/Object;Ljava/lang/Object;)Lscala/Some;
   #38 = NameAndType        #36:#37       // tryCompare$:(Lscala/math/Ordering;Ljava/lang/Object;Ljava/lang/Object;)Lscala/Some;
   #39 = InterfaceMethodref #7.#38        // scala/math/Ordering.tryCompare$:(Lscala/math/Ordering;Ljava/lang/Object;Ljava/lang/Object;)Lscala/Some;
   #40 = Utf8               this
   #41 = Utf8               Lscala/math/Ordering$Tuple9Ordering;
   #42 = Utf8               Ljava/lang/Object;
   #43 = Utf8               lteq
   #44 = Utf8               (Ljava/lang/Object;Ljava/lang/Object;)Z
   #45 = Utf8               lteq$
   #46 = Utf8               (Lscala/math/Ordering;Ljava/lang/Object;Ljava/lang/Object;)Z
   #47 = NameAndType        #45:#46       // lteq$:(Lscala/math/Ordering;Ljava/lang/Object;Ljava/lang/Object;)Z
   #48 = InterfaceMethodref #7.#47        // scala/math/Ordering.lteq$:(Lscala/math/Ordering;Ljava/lang/Object;Ljava/lang/Object;)Z
   #49 = Utf8               gteq
   #50 = Utf8               gteq$
   #51 = NameAndType        #50:#46       // gteq$:(Lscala/math/Ordering;Ljava/lang/Object;Ljava/lang/Object;)Z
   #52 = InterfaceMethodref #7.#51        // scala/math/Ordering.gteq$:(Lscala/math/Ordering;Ljava/lang/Object;Ljava/lang/Object;)Z
   #53 = Utf8               lt
   #54 = Utf8               lt$
   #55 = NameAndType        #54:#46       // lt$:(Lscala/math/Ordering;Ljava/lang/Object;Ljava/lang/Object;)Z
   #56 = InterfaceMethodref #7.#55        // scala/math/Ordering.lt$:(Lscala/math/Ordering;Ljava/lang/Object;Ljava/lang/Object;)Z
   #57 = Utf8               gt
   #58 = Utf8               gt$
   #59 = NameAndType        #58:#46       // gt$:(Lscala/math/Ordering;Ljava/lang/Object;Ljava/lang/Object;)Z
   #60 = InterfaceMethodref #7.#59        // scala/math/Ordering.gt$:(Lscala/math/Ordering;Ljava/lang/Object;Ljava/lang/Object;)Z
   #61 = Utf8               equiv
   #62 = Utf8               equiv$
   #63 = NameAndType        #62:#46       // equiv$:(Lscala/math/Ordering;Ljava/lang/Object;Ljava/lang/Object;)Z
   #64 = InterfaceMethodref #7.#63        // scala/math/Ordering.equiv$:(Lscala/math/Ordering;Ljava/lang/Object;Ljava/lang/Object;)Z
   #65 = Utf8               max
   #66 = Utf8               (Ljava/lang/Object;Ljava/lang/Object;)Ljava/lang/Object;
   #67 = Utf8               max$
   #68 = Utf8               (Lscala/math/Ordering;Ljava/lang/Object;Ljava/lang/Object;)Ljava/lang/Object;
   #69 = NameAndType        #67:#68       // max$:(Lscala/math/Ordering;Ljava/lang/Object;Ljava/lang/Object;)Ljava/lang/Object;
   #70 = InterfaceMethodref #7.#69        // scala/math/Ordering.max$:(Lscala/math/Ordering;Ljava/lang/Object;Ljava/lang/Object;)Ljava/lang/Object;
   #71 = Utf8               min
   #72 = Utf8               min$
   #73 = NameAndType        #72:#68       // min$:(Lscala/math/Ordering;Ljava/lang/Object;Ljava/lang/Object;)Ljava/lang/Object;
   #74 = InterfaceMethodref #7.#73        // scala/math/Ordering.min$:(Lscala/math/Ordering;Ljava/lang/Object;Ljava/lang/Object;)Ljava/lang/Object;
   #75 = Utf8               reverse
   #76 = Utf8               ()Lscala/math/Ordering;
   #77 = Utf8               ()Lscala/math/Ordering<Lscala/Tuple9<TT1;TT2;TT3;TT4;TT5;TT6;TT7;TT8;TT9;>;>;
   #78 = Utf8               reverse$
   #79 = Utf8               (Lscala/math/Ordering;)Lscala/math/Ordering;
   #80 = NameAndType        #78:#79       // reverse$:(Lscala/math/Ordering;)Lscala/math/Ordering;
   #81 = InterfaceMethodref #7.#80        // scala/math/Ordering.reverse$:(Lscala/math/Ordering;)Lscala/math/Ordering;
   #82 = Utf8               isReverseOf
   #83 = Utf8               (Lscala/math/Ordering;)Z
   #84 = Utf8               (Lscala/math/Ordering<*>;)Z
   #85 = Utf8               other
   #86 = Utf8               isReverseOf$
   #87 = Utf8               (Lscala/math/Ordering;Lscala/math/Ordering;)Z
   #88 = NameAndType        #86:#87       // isReverseOf$:(Lscala/math/Ordering;Lscala/math/Ordering;)Z
   #89 = InterfaceMethodref #7.#88        // scala/math/Ordering.isReverseOf$:(Lscala/math/Ordering;Lscala/math/Ordering;)Z
   #90 = Utf8               on
   #91 = Utf8               (Lscala/Function1;)Lscala/math/Ordering;
   #92 = Utf8               <U:Ljava/lang/Object;>(Lscala/Function1<TU;Lscala/Tuple9<TT1;TT2;TT3;TT4;TT5;TT6;TT7;TT8;TT9;>;>;)Lscala/math/Ordering<TU;>;
   #93 = Utf8               f
   #94 = Utf8               on$
   #95 = Utf8               (Lscala/math/Ordering;Lscala/Function1;)Lscala/math/Ordering;
   #96 = NameAndType        #94:#95       // on$:(Lscala/math/Ordering;Lscala/Function1;)Lscala/math/Ordering;
   #97 = InterfaceMethodref #7.#96        // scala/math/Ordering.on$:(Lscala/math/Ordering;Lscala/Function1;)Lscala/math/Ordering;
   #98 = Utf8               Lscala/Function1;
   #99 = Utf8               orElse
  #100 = Utf8               (Lscala/math/Ordering<Lscala/Tuple9<TT1;TT2;TT3;TT4;TT5;TT6;TT7;TT8;TT9;>;>;)Lscala/math/Ordering<Lscala/Tuple9<TT1;TT2;TT3;TT4;TT5;TT6;TT7;TT8;TT9;>;>;
  #101 = Utf8               orElse$
  #102 = Utf8               (Lscala/math/Ordering;Lscala/math/Ordering;)Lscala/math/Ordering;
  #103 = NameAndType        #101:#102     // orElse$:(Lscala/math/Ordering;Lscala/math/Ordering;)Lscala/math/Ordering;
  #104 = InterfaceMethodref #7.#103       // scala/math/Ordering.orElse$:(Lscala/math/Ordering;Lscala/math/Ordering;)Lscala/math/Ordering;
  #105 = Utf8               orElseBy
  #106 = Utf8               (Lscala/Function1;Lscala/math/Ordering;)Lscala/math/Ordering;
  #107 = Utf8               <S:Ljava/lang/Object;>(Lscala/Function1<Lscala/Tuple9<TT1;TT2;TT3;TT4;TT5;TT6;TT7;TT8;TT9;>;TS;>;Lscala/math/Ordering<TS;>;)Lscala/math/Ordering<Lscala/Tuple9<TT1;TT2;TT3;TT4;TT5;TT6;TT7;TT8;TT9;>;>;
  #108 = Utf8               ord
  #109 = Utf8               orElseBy$
  #110 = Utf8               (Lscala/math/Ordering;Lscala/Function1;Lscala/math/Ordering;)Lscala/math/Ordering;
  #111 = NameAndType        #109:#110     // orElseBy$:(Lscala/math/Ordering;Lscala/Function1;Lscala/math/Ordering;)Lscala/math/Ordering;
  #112 = InterfaceMethodref #7.#111       // scala/math/Ordering.orElseBy$:(Lscala/math/Ordering;Lscala/Function1;Lscala/math/Ordering;)Lscala/math/Ordering;
  #113 = Utf8               mkOrderingOps
  #114 = Utf8               (Ljava/lang/Object;)Lscala/math/Ordering$OrderingOps;
  #115 = Utf8               lhs
  #116 = Utf8               mkOrderingOps$
  #117 = Utf8               (Lscala/math/Ordering;Ljava/lang/Object;)Lscala/math/Ordering$OrderingOps;
  #118 = NameAndType        #116:#117     // mkOrderingOps$:(Lscala/math/Ordering;Ljava/lang/Object;)Lscala/math/Ordering$OrderingOps;
  #119 = InterfaceMethodref #7.#118       // scala/math/Ordering.mkOrderingOps$:(Lscala/math/Ordering;Ljava/lang/Object;)Lscala/math/Ordering$OrderingOps;
  #120 = Utf8               ()Lscala/math/Ordering<TT1;>;
  #121 = NameAndType        #13:#14       // ord1:Lscala/math/Ordering;
  #122 = Fieldref           #2.#121       // scala/math/Ordering$Tuple9Ordering.ord1:Lscala/math/Ordering;
  #123 = Utf8               ()Lscala/math/Ordering<TT2;>;
  #124 = NameAndType        #16:#14       // ord2:Lscala/math/Ordering;
  #125 = Fieldref           #2.#124       // scala/math/Ordering$Tuple9Ordering.ord2:Lscala/math/Ordering;
  #126 = Utf8               ()Lscala/math/Ordering<TT3;>;
  #127 = NameAndType        #18:#14       // ord3:Lscala/math/Ordering;
  #128 = Fieldref           #2.#127       // scala/math/Ordering$Tuple9Ordering.ord3:Lscala/math/Ordering;
  #129 = Utf8               ()Lscala/math/Ordering<TT4;>;
  #130 = NameAndType        #20:#14       // ord4:Lscala/math/Ordering;
  #131 = Fieldref           #2.#130       // scala/math/Ordering$Tuple9Ordering.ord4:Lscala/math/Ordering;
  #132 = Utf8               ()Lscala/math/Ordering<TT5;>;
  #133 = NameAndType        #22:#14       // ord5:Lscala/math/Ordering;
  #134 = Fieldref           #2.#133       // scala/math/Ordering$Tuple9Ordering.ord5:Lscala/math/Ordering;
  #135 = Utf8               ()Lscala/math/Ordering<TT6;>;
  #136 = NameAndType        #24:#14       // ord6:Lscala/math/Ordering;
  #137 = Fieldref           #2.#136       // scala/math/Ordering$Tuple9Ordering.ord6:Lscala/math/Ordering;
  #138 = Utf8               ()Lscala/math/Ordering<TT7;>;
  #139 = NameAndType        #26:#14       // ord7:Lscala/math/Ordering;
  #140 = Fieldref           #2.#139       // scala/math/Ordering$Tuple9Ordering.ord7:Lscala/math/Ordering;
  #141 = Utf8               ()Lscala/math/Ordering<TT8;>;
  #142 = NameAndType        #28:#14       // ord8:Lscala/math/Ordering;
  #143 = Fieldref           #2.#142       // scala/math/Ordering$Tuple9Ordering.ord8:Lscala/math/Ordering;
  #144 = Utf8               ()Lscala/math/Ordering<TT9;>;
  #145 = NameAndType        #30:#14       // ord9:Lscala/math/Ordering;
  #146 = Fieldref           #2.#145       // scala/math/Ordering$Tuple9Ordering.ord9:Lscala/math/Ordering;
  #147 = Utf8               compare
  #148 = Utf8               (Lscala/Tuple9;Lscala/Tuple9;)I
  #149 = Utf8               (Lscala/Tuple9<TT1;TT2;TT3;TT4;TT5;TT6;TT7;TT8;TT9;>;Lscala/Tuple9<TT1;TT2;TT3;TT4;TT5;TT6;TT7;TT8;TT9;>;)I
  #150 = NameAndType        #13:#76       // ord1:()Lscala/math/Ordering;
  #151 = Methodref          #2.#150       // scala/math/Ordering$Tuple9Ordering.ord1:()Lscala/math/Ordering;
  #152 = Utf8               scala/Tuple9
  #153 = Class              #152          // scala/Tuple9
  #154 = Utf8               _1
  #155 = Utf8               ()Ljava/lang/Object;
  #156 = NameAndType        #154:#155     // _1:()Ljava/lang/Object;
  #157 = Methodref          #153.#156     // scala/Tuple9._1:()Ljava/lang/Object;
  #158 = Utf8               (Ljava/lang/Object;Ljava/lang/Object;)I
  #159 = NameAndType        #147:#158     // compare:(Ljava/lang/Object;Ljava/lang/Object;)I
  #160 = InterfaceMethodref #7.#159       // scala/math/Ordering.compare:(Ljava/lang/Object;Ljava/lang/Object;)I
  #161 = NameAndType        #16:#76       // ord2:()Lscala/math/Ordering;
  #162 = Methodref          #2.#161       // scala/math/Ordering$Tuple9Ordering.ord2:()Lscala/math/Ordering;
  #163 = Utf8               _2
  #164 = NameAndType        #163:#155     // _2:()Ljava/lang/Object;
  #165 = Methodref          #153.#164     // scala/Tuple9._2:()Ljava/lang/Object;
  #166 = NameAndType        #18:#76       // ord3:()Lscala/math/Ordering;
  #167 = Methodref          #2.#166       // scala/math/Ordering$Tuple9Ordering.ord3:()Lscala/math/Ordering;
  #168 = Utf8               _3
  #169 = NameAndType        #168:#155     // _3:()Ljava/lang/Object;
  #170 = Methodref          #153.#169     // scala/Tuple9._3:()Ljava/lang/Object;
  #171 = NameAndType        #20:#76       // ord4:()Lscala/math/Ordering;
  #172 = Methodref          #2.#171       // scala/math/Ordering$Tuple9Ordering.ord4:()Lscala/math/Ordering;
  #173 = Utf8               _4
  #174 = NameAndType        #173:#155     // _4:()Ljava/lang/Object;
  #175 = Methodref          #153.#174     // scala/Tuple9._4:()Ljava/lang/Object;
  #176 = NameAndType        #22:#76       // ord5:()Lscala/math/Ordering;
  #177 = Methodref          #2.#176       // scala/math/Ordering$Tuple9Ordering.ord5:()Lscala/math/Ordering;
  #178 = Utf8               _5
  #179 = NameAndType        #178:#155     // _5:()Ljava/lang/Object;
  #180 = Methodref          #153.#179     // scala/Tuple9._5:()Ljava/lang/Object;
  #181 = NameAndType        #24:#76       // ord6:()Lscala/math/Ordering;
  #182 = Methodref          #2.#181       // scala/math/Ordering$Tuple9Ordering.ord6:()Lscala/math/Ordering;
  #183 = Utf8               _6
  #184 = NameAndType        #183:#155     // _6:()Ljava/lang/Object;
  #185 = Methodref          #153.#184     // scala/Tuple9._6:()Ljava/lang/Object;
  #186 = NameAndType        #26:#76       // ord7:()Lscala/math/Ordering;
  #187 = Methodref          #2.#186       // scala/math/Ordering$Tuple9Ordering.ord7:()Lscala/math/Ordering;
  #188 = Utf8               _7
  #189 = NameAndType        #188:#155     // _7:()Ljava/lang/Object;
  #190 = Methodref          #153.#189     // scala/Tuple9._7:()Ljava/lang/Object;
  #191 = NameAndType        #28:#76       // ord8:()Lscala/math/Ordering;
  #192 = Methodref          #2.#191       // scala/math/Ordering$Tuple9Ordering.ord8:()Lscala/math/Ordering;
  #193 = Utf8               _8
  #194 = NameAndType        #193:#155     // _8:()Ljava/lang/Object;
  #195 = Methodref          #153.#194     // scala/Tuple9._8:()Ljava/lang/Object;
  #196 = NameAndType        #30:#76       // ord9:()Lscala/math/Ordering;
  #197 = Methodref          #2.#196       // scala/math/Ordering$Tuple9Ordering.ord9:()Lscala/math/Ordering;
  #198 = Utf8               _9
  #199 = NameAndType        #198:#155     // _9:()Ljava/lang/Object;
  #200 = Methodref          #153.#199     // scala/Tuple9._9:()Ljava/lang/Object;
  #201 = Utf8               compare1
  #202 = Utf8               I
  #203 = Utf8               compare2
  #204 = Utf8               compare3
  #205 = Utf8               compare4
  #206 = Utf8               compare5
  #207 = Utf8               compare6
  #208 = Utf8               compare7
  #209 = Utf8               compare8
  #210 = Utf8               Lscala/Tuple9;
  #211 = Utf8               equals
  #212 = Utf8               (Ljava/lang/Object;)Z
  #213 = Utf8               obj
  #214 = NameAndType        #211:#212     // equals:(Ljava/lang/Object;)Z
  #215 = Methodref          #5.#214       // java/lang/Object.equals:(Ljava/lang/Object;)Z
  #216 = Utf8               hashCode
  #217 = Utf8               ()I
  #218 = Utf8               <init>
  #219 = Utf8               (Ljava/lang/Object;Ljava/lang/Object;Ljava/lang/Object;Ljava/lang/Object;Ljava/lang/Object;Ljava/lang/Object;Ljava/lang/Object;Ljava/lang/Object;Ljava/lang/Object;)V
  #220 = NameAndType        #218:#219     // "<init>":(Ljava/lang/Object;Ljava/lang/Object;Ljava/lang/Object;Ljava/lang/Object;Ljava/lang/Object;Ljava/lang/Object;Ljava/lang/Object;Ljava/lang/Object;Ljava/lang/Object;)V
  #221 = Methodref          #153.#220     // scala/Tuple9."<init>":(Ljava/lang/Object;Ljava/lang/Object;Ljava/lang/Object;Ljava/lang/Object;Ljava/lang/Object;Ljava/lang/Object;Ljava/lang/Object;Ljava/lang/Object;Ljava/lang/Object;)V
  #222 = Utf8               scala/util/hashing/MurmurHash3$
  #223 = Class              #222          // scala/util/hashing/MurmurHash3$
  #224 = Utf8               MODULE$
  #225 = Utf8               Lscala/util/hashing/MurmurHash3$;
  #226 = NameAndType        #224:#225     // MODULE$:Lscala/util/hashing/MurmurHash3$;
  #227 = Fieldref           #223.#226     // scala/util/hashing/MurmurHash3$.MODULE$:Lscala/util/hashing/MurmurHash3$;
  #228 = Utf8               productHash
  #229 = Utf8               (Lscala/Product;)I
  #230 = NameAndType        #228:#229     // productHash:(Lscala/Product;)I
  #231 = Methodref          #223.#230     // scala/util/hashing/MurmurHash3$.productHash:(Lscala/Product;)I
  #232 = Utf8               hashCode_this
  #233 = Utf8               ()Lscala/math/PartialOrdering;
  #234 = NameAndType        #75:#76       // reverse:()Lscala/math/Ordering;
  #235 = Methodref          #2.#234       // scala/math/Ordering$Tuple9Ordering.reverse:()Lscala/math/Ordering;
  #236 = Utf8               (Ljava/lang/Object;Ljava/lang/Object;)Lscala/Option;
  #237 = NameAndType        #32:#33       // tryCompare:(Ljava/lang/Object;Ljava/lang/Object;)Lscala/Some;
  #238 = Methodref          #2.#237       // scala/math/Ordering$Tuple9Ordering.tryCompare:(Ljava/lang/Object;Ljava/lang/Object;)Lscala/Some;
  #239 = NameAndType        #147:#148     // compare:(Lscala/Tuple9;Lscala/Tuple9;)I
  #240 = Methodref          #2.#239       // scala/math/Ordering$Tuple9Ordering.compare:(Lscala/Tuple9;Lscala/Tuple9;)I
  #241 = Utf8               (Lscala/math/Ordering;Lscala/math/Ordering;Lscala/math/Ordering;Lscala/math/Ordering;Lscala/math/Ordering;Lscala/math/Ordering;Lscala/math/Ordering;Lscala/math/Ordering;Lscala/math/Ordering;)V
  #242 = Utf8               (Lscala/math/Ordering<TT1;>;Lscala/math/Ordering<TT2;>;Lscala/math/Ordering<TT3;>;Lscala/math/Ordering<TT4;>;Lscala/math/Ordering<TT5;>;Lscala/math/Ordering<TT6;>;Lscala/math/Ordering<TT7;>;Lscala/math/Ordering<TT8;>;Lscala/math/Ordering<TT9;>;)V
  #243 = Utf8               ()V
  #244 = NameAndType        #218:#243     // "<init>":()V
  #245 = Methodref          #5.#244       // java/lang/Object."<init>":()V
  #246 = Utf8               Signature
  #247 = Utf8               Code
  #248 = Utf8               LineNumberTable
  #249 = Utf8               LocalVariableTable
  #250 = Utf8               MethodParameters
  #251 = Utf8               StackMapTable
  #252 = Utf8               InnerClasses
  #253 = Utf8               SourceFile
  #254 = Utf8               ScalaInlineInfo
  #255 = Utf8               Scala
{
  private final scala.math.Ordering<T1> ord1;
    descriptor: Lscala/math/Ordering;
    flags: (0x0012) ACC_PRIVATE, ACC_FINAL
    Signature: #15                          // Lscala/math/Ordering<TT1;>;

  private final scala.math.Ordering<T2> ord2;
    descriptor: Lscala/math/Ordering;
    flags: (0x0012) ACC_PRIVATE, ACC_FINAL
    Signature: #17                          // Lscala/math/Ordering<TT2;>;

  private final scala.math.Ordering<T3> ord3;
    descriptor: Lscala/math/Ordering;
    flags: (0x0012) ACC_PRIVATE, ACC_FINAL
    Signature: #19                          // Lscala/math/Ordering<TT3;>;

  private final scala.math.Ordering<T4> ord4;
    descriptor: Lscala/math/Ordering;
    flags: (0x0012) ACC_PRIVATE, ACC_FINAL
    Signature: #21                          // Lscala/math/Ordering<TT4;>;

  private final scala.math.Ordering<T5> ord5;
    descriptor: Lscala/math/Ordering;
    flags: (0x0012) ACC_PRIVATE, ACC_FINAL
    Signature: #23                          // Lscala/math/Ordering<TT5;>;

  private final scala.math.Ordering<T6> ord6;
    descriptor: Lscala/math/Ordering;
    flags: (0x0012) ACC_PRIVATE, ACC_FINAL
    Signature: #25                          // Lscala/math/Ordering<TT6;>;

  private final scala.math.Ordering<T7> ord7;
    descriptor: Lscala/math/Ordering;
    flags: (0x0012) ACC_PRIVATE, ACC_FINAL
    Signature: #27                          // Lscala/math/Ordering<TT7;>;

  private final scala.math.Ordering<T8> ord8;
    descriptor: Lscala/math/Ordering;
    flags: (0x0012) ACC_PRIVATE, ACC_FINAL
    Signature: #29                          // Lscala/math/Ordering<TT8;>;

  private final scala.math.Ordering<T9> ord9;
    descriptor: Lscala/math/Ordering;
    flags: (0x0012) ACC_PRIVATE, ACC_FINAL
    Signature: #31                          // Lscala/math/Ordering<TT9;>;

  public scala.Some tryCompare(java.lang.Object, java.lang.Object);
    descriptor: (Ljava/lang/Object;Ljava/lang/Object;)Lscala/Some;
    flags: (0x0001) ACC_PUBLIC
    Code:
      stack=3, locals=3, args_size=3
         0: aload_0
         1: aload_1
         2: aload_2
         3: invokestatic  #39                 // InterfaceMethod scala/math/Ordering.tryCompare$:(Lscala/math/Ordering;Ljava/lang/Object;Ljava/lang/Object;)Lscala/Some;
         6: areturn
      LineNumberTable:
        line 852: 0
      LocalVariableTable:
        Start  Length  Slot  Name   Signature
            0       7     0  this   Lscala/math/Ordering$Tuple9Ordering;
            0       7     1     x   Ljava/lang/Object;
            0       7     2     y   Ljava/lang/Object;
    MethodParameters:
      Name                           Flags
      x                              final
      y                              final

  public boolean lteq(java.lang.Object, java.lang.Object);
    descriptor: (Ljava/lang/Object;Ljava/lang/Object;)Z
    flags: (0x0001) ACC_PUBLIC
    Code:
      stack=3, locals=3, args_size=3
         0: aload_0
         1: aload_1
         2: aload_2
         3: invokestatic  #48                 // InterfaceMethod scala/math/Ordering.lteq$:(Lscala/math/Ordering;Ljava/lang/Object;Ljava/lang/Object;)Z
         6: ireturn
      LineNumberTable:
        line 852: 0
      LocalVariableTable:
        Start  Length  Slot  Name   Signature
            0       7     0  this   Lscala/math/Ordering$Tuple9Ordering;
            0       7     1     x   Ljava/lang/Object;
            0       7     2     y   Ljava/lang/Object;
    MethodParameters:
      Name                           Flags
      x                              final
      y                              final

  public boolean gteq(java.lang.Object, java.lang.Object);
    descriptor: (Ljava/lang/Object;Ljava/lang/Object;)Z
    flags: (0x0001) ACC_PUBLIC
    Code:
      stack=3, locals=3, args_size=3
         0: aload_0
         1: aload_1
         2: aload_2
         3: invokestatic  #52                 // InterfaceMethod scala/math/Ordering.gteq$:(Lscala/math/Ordering;Ljava/lang/Object;Ljava/lang/Object;)Z
         6: ireturn
      LineNumberTable:
        line 852: 0
      LocalVariableTable:
        Start  Length  Slot  Name   Signature
            0       7     0  this   Lscala/math/Ordering$Tuple9Ordering;
            0       7     1     x   Ljava/lang/Object;
            0       7     2     y   Ljava/lang/Object;
    MethodParameters:
      Name                           Flags
      x                              final
      y                              final

  public boolean lt(java.lang.Object, java.lang.Object);
    descriptor: (Ljava/lang/Object;Ljava/lang/Object;)Z
    flags: (0x0001) ACC_PUBLIC
    Code:
      stack=3, locals=3, args_size=3
         0: aload_0
         1: aload_1
         2: aload_2
         3: invokestatic  #56                 // InterfaceMethod scala/math/Ordering.lt$:(Lscala/math/Ordering;Ljava/lang/Object;Ljava/lang/Object;)Z
         6: ireturn
      LineNumberTable:
        line 852: 0
      LocalVariableTable:
        Start  Length  Slot  Name   Signature
            0       7     0  this   Lscala/math/Ordering$Tuple9Ordering;
            0       7     1     x   Ljava/lang/Object;
            0       7     2     y   Ljava/lang/Object;
    MethodParameters:
      Name                           Flags
      x                              final
      y                              final

  public boolean gt(java.lang.Object, java.lang.Object);
    descriptor: (Ljava/lang/Object;Ljava/lang/Object;)Z
    flags: (0x0001) ACC_PUBLIC
    Code:
      stack=3, locals=3, args_size=3
         0: aload_0
         1: aload_1
         2: aload_2
         3: invokestatic  #60                 // InterfaceMethod scala/math/Ordering.gt$:(Lscala/math/Ordering;Ljava/lang/Object;Ljava/lang/Object;)Z
         6: ireturn
      LineNumberTable:
        line 852: 0
      LocalVariableTable:
        Start  Length  Slot  Name   Signature
            0       7     0  this   Lscala/math/Ordering$Tuple9Ordering;
            0       7     1     x   Ljava/lang/Object;
            0       7     2     y   Ljava/lang/Object;
    MethodParameters:
      Name                           Flags
      x                              final
      y                              final

  public boolean equiv(java.lang.Object, java.lang.Object);
    descriptor: (Ljava/lang/Object;Ljava/lang/Object;)Z
    flags: (0x0001) ACC_PUBLIC
    Code:
      stack=3, locals=3, args_size=3
         0: aload_0
         1: aload_1
         2: aload_2
         3: invokestatic  #64                 // InterfaceMethod scala/math/Ordering.equiv$:(Lscala/math/Ordering;Ljava/lang/Object;Ljava/lang/Object;)Z
         6: ireturn
      LineNumberTable:
        line 852: 0
      LocalVariableTable:
        Start  Length  Slot  Name   Signature
            0       7     0  this   Lscala/math/Ordering$Tuple9Ordering;
            0       7     1     x   Ljava/lang/Object;
            0       7     2     y   Ljava/lang/Object;
    MethodParameters:
      Name                           Flags
      x                              final
      y                              final

  public java.lang.Object max(java.lang.Object, java.lang.Object);
    descriptor: (Ljava/lang/Object;Ljava/lang/Object;)Ljava/lang/Object;
    flags: (0x0001) ACC_PUBLIC
    Code:
      stack=3, locals=3, args_size=3
         0: aload_0
         1: aload_1
         2: aload_2
         3: invokestatic  #70                 // InterfaceMethod scala/math/Ordering.max$:(Lscala/math/Ordering;Ljava/lang/Object;Ljava/lang/Object;)Ljava/lang/Object;
         6: areturn
      LineNumberTable:
        line 852: 0
      LocalVariableTable:
        Start  Length  Slot  Name   Signature
            0       7     0  this   Lscala/math/Ordering$Tuple9Ordering;
            0       7     1     x   Ljava/lang/Object;
            0       7     2     y   Ljava/lang/Object;
    MethodParameters:
      Name                           Flags
      x                              final
      y                              final

  public java.lang.Object min(java.lang.Object, java.lang.Object);
    descriptor: (Ljava/lang/Object;Ljava/lang/Object;)Ljava/lang/Object;
    flags: (0x0001) ACC_PUBLIC
    Code:
      stack=3, locals=3, args_size=3
         0: aload_0
         1: aload_1
         2: aload_2
         3: invokestatic  #74                 // InterfaceMethod scala/math/Ordering.min$:(Lscala/math/Ordering;Ljava/lang/Object;Ljava/lang/Object;)Ljava/lang/Object;
         6: areturn
      LineNumberTable:
        line 852: 0
      LocalVariableTable:
        Start  Length  Slot  Name   Signature
            0       7     0  this   Lscala/math/Ordering$Tuple9Ordering;
            0       7     1     x   Ljava/lang/Object;
            0       7     2     y   Ljava/lang/Object;
    MethodParameters:
      Name                           Flags
      x                              final
      y                              final

  public scala.math.Ordering<scala.Tuple9<T1, T2, T3, T4, T5, T6, T7, T8, T9>> reverse();
    descriptor: ()Lscala/math/Ordering;
    flags: (0x0001) ACC_PUBLIC
    Code:
      stack=1, locals=1, args_size=1
         0: aload_0
         1: invokestatic  #81                 // InterfaceMethod scala/math/Ordering.reverse$:(Lscala/math/Ordering;)Lscala/math/Ordering;
         4: areturn
      LineNumberTable:
        line 852: 0
      LocalVariableTable:
        Start  Length  Slot  Name   Signature
            0       5     0  this   Lscala/math/Ordering$Tuple9Ordering;
    Signature: #77                          // ()Lscala/math/Ordering<Lscala/Tuple9<TT1;TT2;TT3;TT4;TT5;TT6;TT7;TT8;TT9;>;>;

  public boolean isReverseOf(scala.math.Ordering<?>);
    descriptor: (Lscala/math/Ordering;)Z
    flags: (0x0001) ACC_PUBLIC
    Code:
      stack=2, locals=2, args_size=2
         0: aload_0
         1: aload_1
         2: invokestatic  #89                 // InterfaceMethod scala/math/Ordering.isReverseOf$:(Lscala/math/Ordering;Lscala/math/Ordering;)Z
         5: ireturn
      LineNumberTable:
        line 852: 0
      LocalVariableTable:
        Start  Length  Slot  Name   Signature
            0       6     0  this   Lscala/math/Ordering$Tuple9Ordering;
            0       6     1 other   Lscala/math/Ordering;
    Signature: #84                          // (Lscala/math/Ordering<*>;)Z
    MethodParameters:
      Name                           Flags
      other                          final

  public <U extends java.lang.Object> scala.math.Ordering<U> on(scala.Function1<U, scala.Tuple9<T1, T2, T3, T4, T5, T6, T7, T8, T9>>);
    descriptor: (Lscala/Function1;)Lscala/math/Ordering;
    flags: (0x0001) ACC_PUBLIC
    Code:
      stack=2, locals=2, args_size=2
         0: aload_0
         1: aload_1
         2: invokestatic  #97                 // InterfaceMethod scala/math/Ordering.on$:(Lscala/math/Ordering;Lscala/Function1;)Lscala/math/Ordering;
         5: areturn
      LineNumberTable:
        line 852: 0
      LocalVariableTable:
        Start  Length  Slot  Name   Signature
            0       6     0  this   Lscala/math/Ordering$Tuple9Ordering;
            0       6     1     f   Lscala/Function1;
    Signature: #92                          // <U:Ljava/lang/Object;>(Lscala/Function1<TU;Lscala/Tuple9<TT1;TT2;TT3;TT4;TT5;TT6;TT7;TT8;TT9;>;>;)Lscala/math/Ordering<TU;>;
    MethodParameters:
      Name                           Flags
      f                              final

  public scala.math.Ordering<scala.Tuple9<T1, T2, T3, T4, T5, T6, T7, T8, T9>> orElse(scala.math.Ordering<scala.Tuple9<T1, T2, T3, T4, T5, T6, T7, T8, T9>>);
    descriptor: (Lscala/math/Ordering;)Lscala/math/Ordering;
    flags: (0x0001) ACC_PUBLIC
    Code:
      stack=2, locals=2, args_size=2
         0: aload_0
         1: aload_1
         2: invokestatic  #104                // InterfaceMethod scala/math/Ordering.orElse$:(Lscala/math/Ordering;Lscala/math/Ordering;)Lscala/math/Ordering;
         5: areturn
      LineNumberTable:
        line 852: 0
      LocalVariableTable:
        Start  Length  Slot  Name   Signature
            0       6     0  this   Lscala/math/Ordering$Tuple9Ordering;
            0       6     1 other   Lscala/math/Ordering;
    Signature: #100                         // (Lscala/math/Ordering<Lscala/Tuple9<TT1;TT2;TT3;TT4;TT5;TT6;TT7;TT8;TT9;>;>;)Lscala/math/Ordering<Lscala/Tuple9<TT1;TT2;TT3;TT4;TT5;TT6;TT7;TT8;TT9;>;>;
    MethodParameters:
      Name                           Flags
      other                          final

  public <S extends java.lang.Object> scala.math.Ordering<scala.Tuple9<T1, T2, T3, T4, T5, T6, T7, T8, T9>> orElseBy(scala.Function1<scala.Tuple9<T1, T2, T3, T4, T5, T6, T7, T8, T9>, S>, scala.math.Ordering<S>);
    descriptor: (Lscala/Function1;Lscala/math/Ordering;)Lscala/math/Ordering;
    flags: (0x0001) ACC_PUBLIC
    Code:
      stack=3, locals=3, args_size=3
         0: aload_0
         1: aload_1
         2: aload_2
         3: invokestatic  #112                // InterfaceMethod scala/math/Ordering.orElseBy$:(Lscala/math/Ordering;Lscala/Function1;Lscala/math/Ordering;)Lscala/math/Ordering;
         6: areturn
      LineNumberTable:
        line 852: 0
      LocalVariableTable:
        Start  Length  Slot  Name   Signature
            0       7     0  this   Lscala/math/Ordering$Tuple9Ordering;
            0       7     1     f   Lscala/Function1;
            0       7     2   ord   Lscala/math/Ordering;
    Signature: #107                         // <S:Ljava/lang/Object;>(Lscala/Function1<Lscala/Tuple9<TT1;TT2;TT3;TT4;TT5;TT6;TT7;TT8;TT9;>;TS;>;Lscala/math/Ordering<TS;>;)Lscala/math/Ordering<Lscala/Tuple9<TT1;TT2;TT3;TT4;TT5;TT6;TT7;TT8;TT9;>;>;
    MethodParameters:
      Name                           Flags
      f                              final
      ord                            final

  public scala.math.Ordering$OrderingOps mkOrderingOps(java.lang.Object);
    descriptor: (Ljava/lang/Object;)Lscala/math/Ordering$OrderingOps;
    flags: (0x0001) ACC_PUBLIC
    Code:
      stack=2, locals=2, args_size=2
         0: aload_0
         1: aload_1
         2: invokestatic  #119                // InterfaceMethod scala/math/Ordering.mkOrderingOps$:(Lscala/math/Ordering;Ljava/lang/Object;)Lscala/math/Ordering$OrderingOps;
         5: areturn
      LineNumberTable:
        line 852: 0
      LocalVariableTable:
        Start  Length  Slot  Name   Signature
            0       6     0  this   Lscala/math/Ordering$Tuple9Ordering;
            0       6     1   lhs   Ljava/lang/Object;
    Signature: #114                         // (Ljava/lang/Object;)Lscala/math/Ordering$OrderingOps;
    MethodParameters:
      Name                           Flags
      lhs                            final

  private scala.math.Ordering<T1> ord1();
    descriptor: ()Lscala/math/Ordering;
    flags: (0x0002) ACC_PRIVATE
    Code:
      stack=1, locals=1, args_size=1
         0: aload_0
         1: getfield      #122                // Field ord1:Lscala/math/Ordering;
         4: areturn
      LineNumberTable:
        line 852: 0
      LocalVariableTable:
        Start  Length  Slot  Name   Signature
            0       5     0  this   Lscala/math/Ordering$Tuple9Ordering;
    Signature: #120                         // ()Lscala/math/Ordering<TT1;>;

  private scala.math.Ordering<T2> ord2();
    descriptor: ()Lscala/math/Ordering;
    flags: (0x0002) ACC_PRIVATE
    Code:
      stack=1, locals=1, args_size=1
         0: aload_0
         1: getfield      #125                // Field ord2:Lscala/math/Ordering;
         4: areturn
      LineNumberTable:
        line 853: 0
      LocalVariableTable:
        Start  Length  Slot  Name   Signature
            0       5     0  this   Lscala/math/Ordering$Tuple9Ordering;
    Signature: #123                         // ()Lscala/math/Ordering<TT2;>;

  private scala.math.Ordering<T3> ord3();
    descriptor: ()Lscala/math/Ordering;
    flags: (0x0002) ACC_PRIVATE
    Code:
      stack=1, locals=1, args_size=1
         0: aload_0
         1: getfield      #128                // Field ord3:Lscala/math/Ordering;
         4: areturn
      LineNumberTable:
        line 854: 0
      LocalVariableTable:
        Start  Length  Slot  Name   Signature
            0       5     0  this   Lscala/math/Ordering$Tuple9Ordering;
    Signature: #126                         // ()Lscala/math/Ordering<TT3;>;

  private scala.math.Ordering<T4> ord4();
    descriptor: ()Lscala/math/Ordering;
    flags: (0x0002) ACC_PRIVATE
    Code:
      stack=1, locals=1, args_size=1
         0: aload_0
         1: getfield      #131                // Field ord4:Lscala/math/Ordering;
         4: areturn
      LineNumberTable:
        line 855: 0
      LocalVariableTable:
        Start  Length  Slot  Name   Signature
            0       5     0  this   Lscala/math/Ordering$Tuple9Ordering;
    Signature: #129                         // ()Lscala/math/Ordering<TT4;>;

  private scala.math.Ordering<T5> ord5();
    descriptor: ()Lscala/math/Ordering;
    flags: (0x0002) ACC_PRIVATE
    Code:
      stack=1, locals=1, args_size=1
         0: aload_0
         1: getfield      #134                // Field ord5:Lscala/math/Ordering;
         4: areturn
      LineNumberTable:
        line 856: 0
      LocalVariableTable:
        Start  Length  Slot  Name   Signature
            0       5     0  this   Lscala/math/Ordering$Tuple9Ordering;
    Signature: #132                         // ()Lscala/math/Ordering<TT5;>;

  private scala.math.Ordering<T6> ord6();
    descriptor: ()Lscala/math/Ordering;
    flags: (0x0002) ACC_PRIVATE
    Code:
      stack=1, locals=1, args_size=1
         0: aload_0
         1: getfield      #137                // Field ord6:Lscala/math/Ordering;
         4: areturn
      LineNumberTable:
        line 857: 0
      LocalVariableTable:
        Start  Length  Slot  Name   Signature
            0       5     0  this   Lscala/math/Ordering$Tuple9Ordering;
    Signature: #135                         // ()Lscala/math/Ordering<TT6;>;

  private scala.math.Ordering<T7> ord7();
    descriptor: ()Lscala/math/Ordering;
    flags: (0x0002) ACC_PRIVATE
    Code:
      stack=1, locals=1, args_size=1
         0: aload_0
         1: getfield      #140                // Field ord7:Lscala/math/Ordering;
         4: areturn
      LineNumberTable:
        line 858: 0
      LocalVariableTable:
        Start  Length  Slot  Name   Signature
            0       5     0  this   Lscala/math/Ordering$Tuple9Ordering;
    Signature: #138                         // ()Lscala/math/Ordering<TT7;>;

  private scala.math.Ordering<T8> ord8();
    descriptor: ()Lscala/math/Ordering;
    flags: (0x0002) ACC_PRIVATE
    Code:
      stack=1, locals=1, args_size=1
         0: aload_0
         1: getfield      #143                // Field ord8:Lscala/math/Ordering;
         4: areturn
      LineNumberTable:
        line 859: 0
      LocalVariableTable:
        Start  Length  Slot  Name   Signature
            0       5     0  this   Lscala/math/Ordering$Tuple9Ordering;
    Signature: #141                         // ()Lscala/math/Ordering<TT8;>;

  private scala.math.Ordering<T9> ord9();
    descriptor: ()Lscala/math/Ordering;
    flags: (0x0002) ACC_PRIVATE
    Code:
      stack=1, locals=1, args_size=1
         0: aload_0
         1: getfield      #146                // Field ord9:Lscala/math/Ordering;
         4: areturn
      LineNumberTable:
        line 860: 0
      LocalVariableTable:
        Start  Length  Slot  Name   Signature
            0       5     0  this   Lscala/math/Ordering$Tuple9Ordering;
    Signature: #144                         // ()Lscala/math/Ordering<TT9;>;

  public int compare(scala.Tuple9<T1, T2, T3, T4, T5, T6, T7, T8, T9>, scala.Tuple9<T1, T2, T3, T4, T5, T6, T7, T8, T9>);
    descriptor: (Lscala/Tuple9;Lscala/Tuple9;)I
    flags: (0x0001) ACC_PUBLIC
    Code:
      stack=3, locals=11, args_size=3
         0: aload_0
         1: invokespecial #151                // Method ord1:()Lscala/math/Ordering;
         4: aload_1
         5: invokevirtual #157                // Method scala/Tuple9._1:()Ljava/lang/Object;
         8: aload_2
         9: invokevirtual #157                // Method scala/Tuple9._1:()Ljava/lang/Object;
        12: invokeinterface #160,  3          // InterfaceMethod scala/math/Ordering.compare:(Ljava/lang/Object;Ljava/lang/Object;)I
        17: istore_3
        18: iload_3
        19: iconst_0
        20: if_icmpeq     25
        23: iload_3
        24: ireturn
        25: aload_0
        26: invokespecial #162                // Method ord2:()Lscala/math/Ordering;
        29: aload_1
        30: invokevirtual #165                // Method scala/Tuple9._2:()Ljava/lang/Object;
        33: aload_2
        34: invokevirtual #165                // Method scala/Tuple9._2:()Ljava/lang/Object;
        37: invokeinterface #160,  3          // InterfaceMethod scala/math/Ordering.compare:(Ljava/lang/Object;Ljava/lang/Object;)I
        42: istore        4
        44: iload         4
        46: iconst_0
        47: if_icmpeq     53
        50: iload         4
        52: ireturn
        53: aload_0
        54: invokespecial #167                // Method ord3:()Lscala/math/Ordering;
        57: aload_1
        58: invokevirtual #170                // Method scala/Tuple9._3:()Ljava/lang/Object;
        61: aload_2
        62: invokevirtual #170                // Method scala/Tuple9._3:()Ljava/lang/Object;
        65: invokeinterface #160,  3          // InterfaceMethod scala/math/Ordering.compare:(Ljava/lang/Object;Ljava/lang/Object;)I
        70: istore        5
        72: iload         5
        74: iconst_0
        75: if_icmpeq     81
        78: iload         5
        80: ireturn
        81: aload_0
        82: invokespecial #172                // Method ord4:()Lscala/math/Ordering;
        85: aload_1
        86: invokevirtual #175                // Method scala/Tuple9._4:()Ljava/lang/Object;
        89: aload_2
        90: invokevirtual #175                // Method scala/Tuple9._4:()Ljava/lang/Object;
        93: invokeinterface #160,  3          // InterfaceMethod scala/math/Ordering.compare:(Ljava/lang/Object;Ljava/lang/Object;)I
        98: istore        6
       100: iload         6
       102: iconst_0
       103: if_icmpeq     109
       106: iload         6
       108: ireturn
       109: aload_0
       110: invokespecial #177                // Method ord5:()Lscala/math/Ordering;
       113: aload_1
       114: invokevirtual #180                // Method scala/Tuple9._5:()Ljava/lang/Object;
       117: aload_2
       118: invokevirtual #180                // Method scala/Tuple9._5:()Ljava/lang/Object;
       121: invokeinterface #160,  3          // InterfaceMethod scala/math/Ordering.compare:(Ljava/lang/Object;Ljava/lang/Object;)I
       126: istore        7
       128: iload         7
       130: iconst_0
       131: if_icmpeq     137
       134: iload         7
       136: ireturn
       137: aload_0
       138: invokespecial #182                // Method ord6:()Lscala/math/Ordering;
       141: aload_1
       142: invokevirtual #185                // Method scala/Tuple9._6:()Ljava/lang/Object;
       145: aload_2
       146: invokevirtual #185                // Method scala/Tuple9._6:()Ljava/lang/Object;
       149: invokeinterface #160,  3          // InterfaceMethod scala/math/Ordering.compare:(Ljava/lang/Object;Ljava/lang/Object;)I
       154: istore        8
       156: iload         8
       158: iconst_0
       159: if_icmpeq     165
       162: iload         8
       164: ireturn
       165: aload_0
       166: invokespecial #187                // Method ord7:()Lscala/math/Ordering;
       169: aload_1
       170: invokevirtual #190                // Method scala/Tuple9._7:()Ljava/lang/Object;
       173: aload_2
       174: invokevirtual #190                // Method scala/Tuple9._7:()Ljava/lang/Object;
       177: invokeinterface #160,  3          // InterfaceMethod scala/math/Ordering.compare:(Ljava/lang/Object;Ljava/lang/Object;)I
       182: istore        9
       184: iload         9
       186: iconst_0
       187: if_icmpeq     193
       190: iload         9
       192: ireturn
       193: aload_0
       194: invokespecial #192                // Method ord8:()Lscala/math/Ordering;
       197: aload_1
       198: invokevirtual #195                // Method scala/Tuple9._8:()Ljava/lang/Object;
       201: aload_2
       202: invokevirtual #195                // Method scala/Tuple9._8:()Ljava/lang/Object;
       205: invokeinterface #160,  3          // InterfaceMethod scala/math/Ordering.compare:(Ljava/lang/Object;Ljava/lang/Object;)I
       210: istore        10
       212: iload         10
       214: iconst_0
       215: if_icmpeq     221
       218: iload         10
       220: ireturn
       221: aload_0
       222: invokespecial #197                // Method ord9:()Lscala/math/Ordering;
       225: aload_1
       226: invokevirtual #200                // Method scala/Tuple9._9:()Ljava/lang/Object;
       229: aload_2
       230: invokevirtual #200                // Method scala/Tuple9._9:()Ljava/lang/Object;
       233: invokeinterface #160,  3          // InterfaceMethod scala/math/Ordering.compare:(Ljava/lang/Object;Ljava/lang/Object;)I
       238: ireturn
      StackMapTable: number_of_entries = 8
        frame_type = 252 /* append */
          offset_delta = 25
          locals = [ int ]
        frame_type = 252 /* append */
          offset_delta = 27
          locals = [ int ]
        frame_type = 252 /* append */
          offset_delta = 27
          locals = [ int ]
        frame_type = 252 /* append */
          offset_delta = 27
          locals = [ int ]
        frame_type = 252 /* append */
          offset_delta = 27
          locals = [ int ]
        frame_type = 252 /* append */
          offset_delta = 27
          locals = [ int ]
        frame_type = 252 /* append */
          offset_delta = 27
          locals = [ int ]
        frame_type = 252 /* append */
          offset_delta = 27
          locals = [ int ]
      LineNumberTable:
        line 863: 0
        line 864: 18
        line 865: 25
        line 866: 44
        line 867: 53
        line 868: 72
        line 869: 81
        line 870: 100
        line 871: 109
        line 872: 128
        line 873: 137
        line 874: 156
        line 875: 165
        line 876: 184
        line 877: 193
        line 878: 212
        line 879: 221
      LocalVariableTable:
        Start  Length  Slot  Name   Signature
           18     220     3 compare1   I
           44     194     4 compare2   I
           72     166     5 compare3   I
          100     138     6 compare4   I
          128     110     7 compare5   I
          156      82     8 compare6   I
          184      54     9 compare7   I
          212      26    10 compare8   I
            0     239     0  this   Lscala/math/Ordering$Tuple9Ordering;
            0     239     1     x   Lscala/Tuple9;
            0     239     2     y   Lscala/Tuple9;
    Signature: #149                         // (Lscala/Tuple9<TT1;TT2;TT3;TT4;TT5;TT6;TT7;TT8;TT9;>;Lscala/Tuple9<TT1;TT2;TT3;TT4;TT5;TT6;TT7;TT8;TT9;>;)I
    MethodParameters:
      Name                           Flags
      x                              final
      y                              final

  public boolean equals(java.lang.Object);
    descriptor: (Ljava/lang/Object;)Z
    flags: (0x0001) ACC_PUBLIC
    Code:
      stack=2, locals=13, args_size=2
         0: aload_1
         1: instanceof    #5                  // class java/lang/Object
         4: ifeq          17
         7: aload_0
         8: aload_1
         9: if_acmpne     17
        12: iconst_1
        13: istore_2
        14: goto          319
        17: aload_1
        18: instanceof    #2                  // class scala/math/Ordering$Tuple9Ordering
        21: ifeq          317
        24: aload_1
        25: checkcast     #2                  // class scala/math/Ordering$Tuple9Ordering
        28: astore_3
        29: aload_0
        30: invokespecial #151                // Method ord1:()Lscala/math/Ordering;
        33: aload_3
        34: invokespecial #151                // Method ord1:()Lscala/math/Ordering;
        37: astore        4
        39: dup
        40: ifnonnull     52
        43: pop
        44: aload         4
        46: ifnull        60
        49: goto          312
        52: aload         4
        54: invokevirtual #215                // Method java/lang/Object.equals:(Ljava/lang/Object;)Z
        57: ifeq          312
        60: aload_0
        61: invokespecial #162                // Method ord2:()Lscala/math/Ordering;
        64: aload_3
        65: invokespecial #162                // Method ord2:()Lscala/math/Ordering;
        68: astore        5
        70: dup
        71: ifnonnull     83
        74: pop
        75: aload         5
        77: ifnull        91
        80: goto          312
        83: aload         5
        85: invokevirtual #215                // Method java/lang/Object.equals:(Ljava/lang/Object;)Z
        88: ifeq          312
        91: aload_0
        92: invokespecial #167                // Method ord3:()Lscala/math/Ordering;
        95: aload_3
        96: invokespecial #167                // Method ord3:()Lscala/math/Ordering;
        99: astore        6
       101: dup
       102: ifnonnull     114
       105: pop
       106: aload         6
       108: ifnull        122
       111: goto          312
       114: aload         6
       116: invokevirtual #215                // Method java/lang/Object.equals:(Ljava/lang/Object;)Z
       119: ifeq          312
       122: aload_0
       123: invokespecial #172                // Method ord4:()Lscala/math/Ordering;
       126: aload_3
       127: invokespecial #172                // Method ord4:()Lscala/math/Ordering;
       130: astore        7
       132: dup
       133: ifnonnull     145
       136: pop
       137: aload         7
       139: ifnull        153
       142: goto          312
       145: aload         7
       147: invokevirtual #215                // Method java/lang/Object.equals:(Ljava/lang/Object;)Z
       150: ifeq          312
       153: aload_0
       154: invokespecial #177                // Method ord5:()Lscala/math/Ordering;
       157: aload_3
       158: invokespecial #177                // Method ord5:()Lscala/math/Ordering;
       161: astore        8
       163: dup
       164: ifnonnull     176
       167: pop
       168: aload         8
       170: ifnull        184
       173: goto          312
       176: aload         8
       178: invokevirtual #215                // Method java/lang/Object.equals:(Ljava/lang/Object;)Z
       181: ifeq          312
       184: aload_0
       185: invokespecial #182                // Method ord6:()Lscala/math/Ordering;
       188: aload_3
       189: invokespecial #182                // Method ord6:()Lscala/math/Ordering;
       192: astore        9
       194: dup
       195: ifnonnull     207
       198: pop
       199: aload         9
       201: ifnull        215
       204: goto          312
       207: aload         9
       209: invokevirtual #215                // Method java/lang/Object.equals:(Ljava/lang/Object;)Z
       212: ifeq          312
       215: aload_0
       216: invokespecial #187                // Method ord7:()Lscala/math/Ordering;
       219: aload_3
       220: invokespecial #187                // Method ord7:()Lscala/math/Ordering;
       223: astore        10
       225: dup
       226: ifnonnull     238
       229: pop
       230: aload         10
       232: ifnull        246
       235: goto          312
       238: aload         10
       240: invokevirtual #215                // Method java/lang/Object.equals:(Ljava/lang/Object;)Z
       243: ifeq          312
       246: aload_0
       247: invokespecial #192                // Method ord8:()Lscala/math/Ordering;
       250: aload_3
       251: invokespecial #192                // Method ord8:()Lscala/math/Ordering;
       254: astore        11
       256: dup
       257: ifnonnull     269
       260: pop
       261: aload         11
       263: ifnull        277
       266: goto          312
       269: aload         11
       271: invokevirtual #215                // Method java/lang/Object.equals:(Ljava/lang/Object;)Z
       274: ifeq          312
       277: aload_0
       278: invokespecial #197                // Method ord9:()Lscala/math/Ordering;
       281: aload_3
       282: invokespecial #197                // Method ord9:()Lscala/math/Ordering;
       285: astore        12
       287: dup
       288: ifnonnull     300
       291: pop
       292: aload         12
       294: ifnull        308
       297: goto          312
       300: aload         12
       302: invokevirtual #215                // Method java/lang/Object.equals:(Ljava/lang/Object;)Z
       305: ifeq          312
       308: iconst_1
       309: goto          313
       312: iconst_0
       313: istore_2
       314: goto          319
       317: iconst_0
       318: istore_2
       319: iload_2
       320: ireturn
      StackMapTable: number_of_entries = 23
        frame_type = 17 /* same */
        frame_type = 255 /* full_frame */
          offset_delta = 34
          locals = [ class scala/math/Ordering$Tuple9Ordering, class java/lang/Object, top, class scala/math/Ordering$Tuple9Ordering, class scala/math/Ordering ]
          stack = [ class scala/math/Ordering ]
        frame_type = 7 /* same */
        frame_type = 255 /* full_frame */
          offset_delta = 22
          locals = [ class scala/math/Ordering$Tuple9Ordering, class java/lang/Object, top, class scala/math/Ordering$Tuple9Ordering, class scala/math/Ordering, class scala/math/Ordering ]
          stack = [ class scala/math/Ordering ]
        frame_type = 7 /* same */
        frame_type = 255 /* full_frame */
          offset_delta = 22
          locals = [ class scala/math/Ordering$Tuple9Ordering, class java/lang/Object, top, class scala/math/Ordering$Tuple9Ordering, class scala/math/Ordering, class scala/math/Ordering, class scala/math/Ordering ]
          stack = [ class scala/math/Ordering ]
        frame_type = 7 /* same */
        frame_type = 255 /* full_frame */
          offset_delta = 22
          locals = [ class scala/math/Ordering$Tuple9Ordering, class java/lang/Object, top, class scala/math/Ordering$Tuple9Ordering, class scala/math/Ordering, class scala/math/Ordering, class scala/math/Ordering, class scala/math/Ordering ]
          stack = [ class scala/math/Ordering ]
        frame_type = 7 /* same */
        frame_type = 255 /* full_frame */
          offset_delta = 22
          locals = [ class scala/math/Ordering$Tuple9Ordering, class java/lang/Object, top, class scala/math/Ordering$Tuple9Ordering, class scala/math/Ordering, class scala/math/Ordering, class scala/math/Ordering, class scala/math/Ordering, class scala/math/Ordering ]
          stack = [ class scala/math/Ordering ]
        frame_type = 7 /* same */
        frame_type = 255 /* full_frame */
          offset_delta = 22
          locals = [ class scala/math/Ordering$Tuple9Ordering, class java/lang/Object, top, class scala/math/Ordering$Tuple9Ordering, class scala/math/Ordering, class scala/math/Ordering, class scala/math/Ordering, class scala/math/Ordering, class scala/math/Ordering, class scala/math/Ordering ]
          stack = [ class scala/math/Ordering ]
        frame_type = 7 /* same */
        frame_type = 255 /* full_frame */
          offset_delta = 22
          locals = [ class scala/math/Ordering$Tuple9Ordering, class java/lang/Object, top, class scala/math/Ordering$Tuple9Ordering, class scala/math/Ordering, class scala/math/Ordering, class scala/math/Ordering, class scala/math/Ordering, class scala/math/Ordering, class scala/math/Ordering, class scala/math/Ordering ]
          stack = [ class scala/math/Ordering ]
        frame_type = 7 /* same */
        frame_type = 255 /* full_frame */
          offset_delta = 22
          locals = [ class scala/math/Ordering$Tuple9Ordering, class java/lang/Object, top, class scala/math/Ordering$Tuple9Ordering, class scala/math/Ordering, class scala/math/Ordering, class scala/math/Ordering, class scala/math/Ordering, class scala/math/Ordering, class scala/math/Ordering, class scala/math/Ordering, class scala/math/Ordering ]
          stack = [ class scala/math/Ordering ]
        frame_type = 7 /* same */
        frame_type = 255 /* full_frame */
          offset_delta = 22
          locals = [ class scala/math/Ordering$Tuple9Ordering, class java/lang/Object, top, class scala/math/Ordering$Tuple9Ordering, class scala/math/Ordering, class scala/math/Ordering, class scala/math/Ordering, class scala/math/Ordering, class scala/math/Ordering, class scala/math/Ordering, class scala/math/Ordering, class scala/math/Ordering, class scala/math/Ordering ]
          stack = [ class scala/math/Ordering ]
        frame_type = 7 /* same */
        frame_type = 255 /* full_frame */
          offset_delta = 3
          locals = [ class scala/math/Ordering$Tuple9Ordering, class java/lang/Object, top, class scala/math/Ordering$Tuple9Ordering, class scala/math/Ordering ]
          stack = []
        frame_type = 64 /* same_locals_1_stack_item */
          stack = [ int ]
        frame_type = 248 /* chop */
          offset_delta = 3
        frame_type = 252 /* append */
          offset_delta = 1
          locals = [ int ]
      LineNumberTable:
        line 883: 0
        line 884: 17
        line 885: 29
        line 886: 60
        line 887: 91
        line 888: 122
        line 889: 153
        line 890: 184
        line 891: 215
        line 892: 246
        line 893: 277
        line 894: 317
        line 882: 319
      LocalVariableTable:
        Start  Length  Slot  Name   Signature
            0     321     0  this   Lscala/math/Ordering$Tuple9Ordering;
            0     321     1   obj   Ljava/lang/Object;
    MethodParameters:
      Name                           Flags
      obj                            final

  public int hashCode();
    descriptor: ()I
    flags: (0x0001) ACC_PUBLIC
    Code:
      stack=11, locals=2, args_size=1
         0: new           #153                // class scala/Tuple9
         3: dup
         4: aload_0
         5: invokespecial #151                // Method ord1:()Lscala/math/Ordering;
         8: aload_0
         9: invokespecial #162                // Method ord2:()Lscala/math/Ordering;
        12: aload_0
        13: invokespecial #167                // Method ord3:()Lscala/math/Ordering;
        16: aload_0
        17: invokespecial #172                // Method ord4:()Lscala/math/Ordering;
        20: aload_0
        21: invokespecial #177                // Method ord5:()Lscala/math/Ordering;
        24: aload_0
        25: invokespecial #182                // Method ord6:()Lscala/math/Ordering;
        28: aload_0
        29: invokespecial #187                // Method ord7:()Lscala/math/Ordering;
        32: aload_0
        33: invokespecial #192                // Method ord8:()Lscala/math/Ordering;
        36: aload_0
        37: invokespecial #197                // Method ord9:()Lscala/math/Ordering;
        40: invokespecial #221                // Method scala/Tuple9."<init>":(Ljava/lang/Object;Ljava/lang/Object;Ljava/lang/Object;Ljava/lang/Object;Ljava/lang/Object;Ljava/lang/Object;Ljava/lang/Object;Ljava/lang/Object;Ljava/lang/Object;)V
        43: astore_1
        44: getstatic     #227                // Field scala/util/hashing/MurmurHash3$.MODULE$:Lscala/util/hashing/MurmurHash3$;
        47: aload_1
        48: invokevirtual #231                // Method scala/util/hashing/MurmurHash3$.productHash:(Lscala/Product;)I
        51: ireturn
      LineNumberTable:
        line 896: 0
      LocalVariableTable:
        Start  Length  Slot  Name   Signature
            0      52     0  this   Lscala/math/Ordering$Tuple9Ordering;
           44       7     1 hashCode_this   Lscala/Tuple9;

  public scala.math.PartialOrdering reverse();
    descriptor: ()Lscala/math/PartialOrdering;
    flags: (0x1041) ACC_PUBLIC, ACC_BRIDGE, ACC_SYNTHETIC
    Code:
      stack=1, locals=1, args_size=1
         0: aload_0
         1: invokevirtual #235                // Method reverse:()Lscala/math/Ordering;
         4: areturn
      LineNumberTable:
        line 852: 0
      LocalVariableTable:
        Start  Length  Slot  Name   Signature
            0       5     0  this   Lscala/math/Ordering$Tuple9Ordering;

  public scala.Option tryCompare(java.lang.Object, java.lang.Object);
    descriptor: (Ljava/lang/Object;Ljava/lang/Object;)Lscala/Option;
    flags: (0x1041) ACC_PUBLIC, ACC_BRIDGE, ACC_SYNTHETIC
    Code:
      stack=3, locals=3, args_size=3
         0: aload_0
         1: aload_1
         2: aload_2
         3: invokevirtual #238                // Method tryCompare:(Ljava/lang/Object;Ljava/lang/Object;)Lscala/Some;
         6: areturn
      LineNumberTable:
        line 852: 0
      LocalVariableTable:
        Start  Length  Slot  Name   Signature
            0       7     0  this   Lscala/math/Ordering$Tuple9Ordering;
            0       7     1     x   Ljava/lang/Object;
            0       7     2     y   Ljava/lang/Object;
    MethodParameters:
      Name                           Flags
      x                              final
      y                              final

  public int compare(java.lang.Object, java.lang.Object);
    descriptor: (Ljava/lang/Object;Ljava/lang/Object;)I
    flags: (0x1041) ACC_PUBLIC, ACC_BRIDGE, ACC_SYNTHETIC
    Code:
      stack=3, locals=3, args_size=3
         0: aload_0
         1: aload_1
         2: checkcast     #153                // class scala/Tuple9
         5: aload_2
         6: checkcast     #153                // class scala/Tuple9
         9: invokevirtual #240                // Method compare:(Lscala/Tuple9;Lscala/Tuple9;)I
        12: ireturn
      LineNumberTable:
        line 852: 0
      LocalVariableTable:
        Start  Length  Slot  Name   Signature
            0      13     0  this   Lscala/math/Ordering$Tuple9Ordering;
            0      13     1     x   Ljava/lang/Object;
            0      13     2     y   Ljava/lang/Object;
    MethodParameters:
      Name                           Flags
      x                              final
      y                              final

  public scala.math.Ordering$Tuple9Ordering(scala.math.Ordering<T1>, scala.math.Ordering<T2>, scala.math.Ordering<T3>, scala.math.Ordering<T4>, scala.math.Ordering<T5>, scala.math.Ordering<T6>, scala.math.Ordering<T7>, scala.math.Ordering<T8>, scala.math.Ordering<T9>);
    descriptor: (Lscala/math/Ordering;Lscala/math/Ordering;Lscala/math/Ordering;Lscala/math/Ordering;Lscala/math/Ordering;Lscala/math/Ordering;Lscala/math/Ordering;Lscala/math/Ordering;Lscala/math/Ordering;)V
    flags: (0x0001) ACC_PUBLIC
    Code:
      stack=2, locals=10, args_size=10
         0: aload_0
         1: aload_1
         2: putfield      #122                // Field ord1:Lscala/math/Ordering;
         5: aload_0
         6: aload_2
         7: putfield      #125                // Field ord2:Lscala/math/Ordering;
        10: aload_0
        11: aload_3
        12: putfield      #128                // Field ord3:Lscala/math/Ordering;
        15: aload_0
        16: aload         4
        18: putfield      #131                // Field ord4:Lscala/math/Ordering;
        21: aload_0
        22: aload         5
        24: putfield      #134                // Field ord5:Lscala/math/Ordering;
        27: aload_0
        28: aload         6
        30: putfield      #137                // Field ord6:Lscala/math/Ordering;
        33: aload_0
        34: aload         7
        36: putfield      #140                // Field ord7:Lscala/math/Ordering;
        39: aload_0
        40: aload         8
        42: putfield      #143                // Field ord8:Lscala/math/Ordering;
        45: aload_0
        46: aload         9
        48: putfield      #146                // Field ord9:Lscala/math/Ordering;
        51: aload_0
        52: invokespecial #245                // Method java/lang/Object."<init>":()V
        55: return
      LineNumberTable:
        line 852: 0
        line 853: 5
        line 854: 10
        line 855: 15
        line 856: 21
        line 857: 27
        line 858: 33
        line 859: 39
        line 860: 45
        line 861: 51
      LocalVariableTable:
        Start  Length  Slot  Name   Signature
            0      56     0  this   Lscala/math/Ordering$Tuple9Ordering;
            0      56     1  ord1   Lscala/math/Ordering;
            0      56     2  ord2   Lscala/math/Ordering;
            0      56     3  ord3   Lscala/math/Ordering;
            0      56     4  ord4   Lscala/math/Ordering;
            0      56     5  ord5   Lscala/math/Ordering;
            0      56     6  ord6   Lscala/math/Ordering;
            0      56     7  ord7   Lscala/math/Ordering;
            0      56     8  ord8   Lscala/math/Ordering;
            0      56     9  ord9   Lscala/math/Ordering;
    Signature: #242                         // (Lscala/math/Ordering<TT1;>;Lscala/math/Ordering<TT2;>;Lscala/math/Ordering<TT3;>;Lscala/math/Ordering<TT4;>;Lscala/math/Ordering<TT5;>;Lscala/math/Ordering<TT6;>;Lscala/math/Ordering<TT7;>;Lscala/math/Ordering<TT8;>;Lscala/math/Ordering<TT9;>;)V
    MethodParameters:
      Name                           Flags
      ord1                           final
      ord2                           final
      ord3                           final
      ord4                           final
      ord5                           final
      ord6                           final
      ord7                           final
      ord8                           final
      ord9                           final
}
InnerClasses:
  public #11= #10 of #7;                  // OrderingOps=class scala/math/Ordering$OrderingOps of class scala/math/Ordering
  private static final #12= #2 of #7;     // Tuple9Ordering=class scala/math/Ordering$Tuple9Ordering of class scala/math/Ordering
Signature: #3                           // <T1:Ljava/lang/Object;T2:Ljava/lang/Object;T3:Ljava/lang/Object;T4:Ljava/lang/Object;T5:Ljava/lang/Object;T6:Ljava/lang/Object;T7:Ljava/lang/Object;T8:Ljava/lang/Object;T9:Ljava/lang/Object;>Ljava/lang/Object;Lscala/math/Ordering<Lscala/Tuple9<TT1;TT2;TT3;TT4;TT5;TT6;TT7;TT8;TT9;>;>;
SourceFile: "Ordering.scala"
  ScalaInlineInfo: length = 0x9A (unknown attribute)
   01 01 00 1E 00 DA 00 F1 01 00 93 00 9E 01 00 93
   00 94 01 00 D3 00 D4 01 00 3D 00 2C 01 00 39 00
   2C 01 00 31 00 2C 01 00 D8 00 D9 01 00 52 00 53
   01 00 35 00 2C 01 00 2B 00 2C 01 00 41 00 42 01
   00 47 00 42 01 00 71 00 72 01 00 5A 00 5B 01 00
   63 00 4F 01 00 69 00 6A 01 00 0D 00 4C 01 00 10
   00 4C 01 00 12 00 4C 01 00 14 00 4C 01 00 16 00
   4C 01 00 18 00 4C 01 00 1A 00 4C 01 00 1C 00 4C
   01 00 1E 00 4C 01 00 4B 00 4C 01 00 4B 00 E9 01
   00 20 00 EC 01 00 20 00 21 01
  Scala: length = 0x0 (unknown attribute)

