Classfile /Users/mw/Projects/slang-braindump/.jar/jar8/assemble/slang-braindump/assemble/content/scala/math/Ordering$StringOrdering.class
  Last modified May 29, 2022; size 1023 bytes
  SHA-256 checksum 08b22c925ac2ed5cbce26b9963be15da45f8f0c747e1185b08d5c5df374c5ee8
  Compiled from "Ordering.scala"
public interface scala.math.Ordering$StringOrdering extends scala.math.Ordering<java.lang.String>
  minor version: 0
  major version: 52
  flags: (0x0601) ACC_PUBLIC, ACC_INTERFACE, ACC_ABSTRACT
  this_class: #2                          // scala/math/Ordering$StringOrdering
  super_class: #5                         // java/lang/Object
  interfaces: 1, fields: 0, methods: 3, attributes: 5
Constant pool:
   #1 = Utf8               scala/math/Ordering$StringOrdering
   #2 = Class              #1             // scala/math/Ordering$StringOrdering
   #3 = Utf8               Ljava/lang/Object;Lscala/math/Ordering<Ljava/lang/String;>;
   #4 = Utf8               java/lang/Object
   #5 = Class              #4             // java/lang/Object
   #6 = Utf8               scala/math/Ordering
   #7 = Class              #6             // scala/math/Ordering
   #8 = Utf8               Ordering.scala
   #9 = Utf8               StringOrdering
  #10 = Utf8               compare$
  #11 = Utf8               (Lscala/math/Ordering$StringOrdering;Ljava/lang/String;Ljava/lang/String;)I
  #12 = Utf8               $this
  #13 = Utf8               x
  #14 = Utf8               y
  #15 = Utf8               compare
  #16 = Utf8               (Ljava/lang/String;Ljava/lang/String;)I
  #17 = NameAndType        #15:#16        // compare:(Ljava/lang/String;Ljava/lang/String;)I
  #18 = InterfaceMethodref #2.#17         // scala/math/Ordering$StringOrdering.compare:(Ljava/lang/String;Ljava/lang/String;)I
  #19 = Utf8               Lscala/math/Ordering$StringOrdering;
  #20 = Utf8               Ljava/lang/String;
  #21 = Utf8               java/lang/String
  #22 = Class              #21            // java/lang/String
  #23 = Utf8               compareTo
  #24 = Utf8               (Ljava/lang/String;)I
  #25 = NameAndType        #23:#24        // compareTo:(Ljava/lang/String;)I
  #26 = Methodref          #22.#25        // java/lang/String.compareTo:(Ljava/lang/String;)I
  #27 = Utf8               this
  #28 = Utf8               $init$
  #29 = Utf8               (Lscala/math/Ordering$StringOrdering;)V
  #30 = Utf8               Code
  #31 = Utf8               LineNumberTable
  #32 = Utf8               LocalVariableTable
  #33 = Utf8               MethodParameters
  #34 = Utf8               InnerClasses
  #35 = Utf8               Signature
  #36 = Utf8               SourceFile
  #37 = Utf8               ScalaInlineInfo
  #38 = Utf8               Scala
{
  public static int compare$(scala.math.Ordering$StringOrdering, java.lang.String, java.lang.String);
    descriptor: (Lscala/math/Ordering$StringOrdering;Ljava/lang/String;Ljava/lang/String;)I
    flags: (0x1009) ACC_PUBLIC, ACC_STATIC, ACC_SYNTHETIC
    Code:
      stack=3, locals=3, args_size=3
         0: aload_0
         1: aload_1
         2: aload_2
         3: invokespecial #18                 // InterfaceMethod compare:(Ljava/lang/String;Ljava/lang/String;)I
         6: ireturn
      LineNumberTable:
        line 575: 0
      LocalVariableTable:
        Start  Length  Slot  Name   Signature
            0       7     0 $this   Lscala/math/Ordering$StringOrdering;
            0       7     1     x   Ljava/lang/String;
            0       7     2     y   Ljava/lang/String;
    MethodParameters:
      Name                           Flags
      $this                          final synthetic
      x                              final
      y                              final

  public default int compare(java.lang.String, java.lang.String);
    descriptor: (Ljava/lang/String;Ljava/lang/String;)I
    flags: (0x0001) ACC_PUBLIC
    Code:
      stack=2, locals=3, args_size=3
         0: aload_1
         1: aload_2
         2: invokevirtual #26                 // Method java/lang/String.compareTo:(Ljava/lang/String;)I
         5: ireturn
      LineNumberTable:
        line 575: 0
      LocalVariableTable:
        Start  Length  Slot  Name   Signature
            0       6     0  this   Lscala/math/Ordering$StringOrdering;
            0       6     1     x   Ljava/lang/String;
            0       6     2     y   Ljava/lang/String;
    MethodParameters:
      Name                           Flags
      x                              final
      y                              final

  public static void $init$(scala.math.Ordering$StringOrdering);
    descriptor: (Lscala/math/Ordering$StringOrdering;)V
    flags: (0x0009) ACC_PUBLIC, ACC_STATIC
    Code:
      stack=0, locals=1, args_size=1
         0: return
      LineNumberTable:
        line 574: 0
      LocalVariableTable:
        Start  Length  Slot  Name   Signature
            0       1     0 $this   Lscala/math/Ordering$StringOrdering;
    MethodParameters:
      Name                           Flags
      $this                          final synthetic
}
InnerClasses:
  public static #9= #2 of #7;             // StringOrdering=class scala/math/Ordering$StringOrdering of class scala/math/Ordering
Signature: #3                           // Ljava/lang/Object;Lscala/math/Ordering<Ljava/lang/String;>;
SourceFile: "Ordering.scala"
  ScalaInlineInfo: length = 0x13 (unknown attribute)
   01 00 00 03 00 1C 00 1D 01 00 0F 00 10 00 00 0A
   00 0B 01
  Scala: length = 0x0 (unknown attribute)

