Classfile /Users/mw/Projects/slang-braindump/.jar/jar11/assemble/slang-braindump/assemble/content/org/sireum/test/package.class
  Last modified May 29, 2022; size 2076 bytes
  SHA-256 checksum 7b0af927211326bfc587ce7d6da4da92a4e1f8a45fa316a6aa0c57238450ee6b
  Compiled from "package.scala"
public final class org.sireum.test.package
  minor version: 0
  major version: 52
  flags: (0x0031) ACC_PUBLIC, ACC_FINAL, ACC_SUPER
  this_class: #2                          // org/sireum/test/package
  super_class: #4                         // java/lang/Object
  interfaces: 0, fields: 0, methods: 1, attributes: 4
Constant pool:
   #1 = Utf8               org/sireum/test/package
   #2 = Class              #1             // org/sireum/test/package
   #3 = Utf8               java/lang/Object
   #4 = Class              #3             // java/lang/Object
   #5 = Utf8               package.scala
   #6 = Utf8               Lscala/reflect/ScalaSignature;
   #7 = Utf8               bytes
   #8 = Utf8               \u0006\u0005\u0005\u0005t!\u0002\u000f\u001e\u0011\u0003!c!\u0002\u0014\u001e\u0011\u00039\u0003\"\u0002\u0018\u0002\t\u0003yca\u0002\u0019\u0002!\u0003\r\t!\r\u0005\u0006{\r!\tA\u0010\u0004\u0005\u0005\u000e\u00011\t\u0003\u0005E\u000b\t\u0005\t\u0015!\u0003F\u0011\u0015qS\u0001\"\u0001N\u0011\u0015\tV\u0001\"\u0001S\u0011\u0015A6\u0001\"\u0001Z\u0011\u0015Y6\u0001\"\u0001]\u0011\u0015q6\u0001\"\u0001`\r\u0011A\u0018aA=\t\u0011ud!Q1A\u0005\u0002yD\u0001b \u0007\u0003\u0002\u0003\u0006I\u0001\u001d\u0005\u0007]1!\t!!\u0001\t\u000f\u0005%A\u0002\"\u0001\u0002\f!9\u0011q\u0003\u0007\u0005\u0002\u0005e\u0001\"CA\u000f\u0019\u0005\u0005I\u0011IA\u0010\u0011%\t9\u0003DA\u0001\n\u0003\nIcB\u0005\u00020\u0005\t\t\u0011#\u0001\u00022\u0019A\u00010AA\u0001\u0012\u0003\t\u0019\u0004\u0003\u0004/+\u0011\u0005\u0011Q\u0007\u0005\b\u0003o)BQAA\u001d\u0011\u001d\t\u0019%\u0006C\u0003\u0003\u000bB\u0011\"!\u0014\u0016\u0003\u0003%)!a\u0014\t\u0013\u0005MS#!A\u0005\u0006\u0005U\u0003\"CA\u0018\u0003\u0005\u0005I1AA/\u0003\u001d\u0001\u0018mY6bO\u0016T!AH\u0010\u0002\tQ,7\u000f\u001e\u0006\u0003A\u0005\naa]5sKVl\'\"\u0001\u0012\u0002\u0007=\u0014xm\u0001\u0001\u0011\u0005\u0015\nQ\"A\u000f\u0003\u000fA\f7m[1hKN\u0011\u0011\u0001\u000b\t\u0003S1j\u0011A\u000b\u0006\u0002W\u0005)1oY1mC&\u0011QF\u000b\u0002\u0007\u0003:L(+\u001a4\u0002\rqJg.\u001b;?)\u0005!#!\u0003+fgR\u001cV/\u001b;f\'\r\u0019!G\u000f\t\u0003gaj\u0011\u0001\u000e\u0006\u0003kY\n\u0001B\u001a:fKN\u0004Xm\u0019\u0006\u0003o\u0005\n\u0011b]2bY\u0006$Xm\u001d;\n\u0005e\"$aC!os\u001a\u0013X-Z*qK\u000e\u0004\"!J\u001e\n\u0005qj\"AC*je\u0016,Xn\u00159fG\u00061A%\u001b8ji\u0012\"\u0012a\u0010\t\u0003S\u0001K!!\u0011\u0016\u0003\tUs\u0017\u000e\u001e\u0002\n\u0003:|g._7pkN\u001c\"!\u0002\u0015\u0002\u0011A|7/\u001b;j_:\u0004\"AR&\u000e\u0003\u001dS!\u0001S%\u0002\rM|WO]2f\u0015\tQ\u0015%A\u0005tG\u0006d\u0017m\u0019;jG&\u0011Aj\u0012\u0002\t!>\u001c\u0018\u000e^5p]R\u0011a\n\u0015\t\u0003\u001f\u0016i\u0011a\u0001\u0005\u0006\t\u001e\u0001\r!R\u0001\u0007I5Lg.^:\u0015\u0005}\u001a\u0006B\u0002+\t\t\u0003\u0007Q+A\u0001g!\rIckP\u0005\u0003/*\u0012\u0001\u0002\u00102z]\u0006lWMP\u0001\u0007IQLW.Z:\u0015\u00059S\u0006\"\u0002#\n\u0001\b)\u0015!\u0002+fgR\u001cHCA ^\u0011\u0019!&\u0002\"a\u0001+\u0006Y\u0011m]:feRl\u0015\r^2i+\t\u0001\'\u000e\u0006\u0002bmR\u0011qH\u0019\u0005\u0006G.\u0001\r\u0001Z\u0001\u0003a\u001a\u0004$!\u001a;\u0011\t%2\u0007n]\u0005\u0003O*\u0012q\u0002U1si&\fGNR;oGRLwN\u001c\t\u0003S*d\u0001\u0001B\u0003l\u0017\t\u0007ANA\u0001U#\ti\u0007\u000f\u0005\u0002*]&\u0011qN\u000b\u0002\b\u001d>$\b.\u001b8h!\tI\u0013/\u0003\u0002sU\t\u0019\u0011I\\=\u0011\u0005%$H!C;c\u0003\u0003\u0005\tQ!\u0001m\u0005\ryF%\r\u0005\u0006o.\u0001\r\u0001[\u0001\u0002_\n)Q)];jmN\u0011AB\u001f\t\u0003SmL!\u0001 \u0016\u0003\r\u0005s\u0017PV1m\u0003\u0019\u0011Xm];miV\t\u0001/A\u0004sKN,H\u000e\u001e\u0011\u0015\t\u0005\r\u0011q\u0001\t\u0004\u0003\u000baQ\"A\u0001\t\u000bu|\u0001\u0019\u00019\u0002\u0019\u0011*\u0017\u000f\n;jY\u0012,G%Z9\u0015\t\u00055\u00111\u0003\t\u0004S\u0005=\u0011bAA\tU\t9!i\\8mK\u0006t\u0007BBA\u000b!\u0001\u0007\u0001/\u0001\u0005fqB,7\r^3e\u00039!#-\u00198hIQLG\u000eZ3%KF$B!!\u0004\u0002\u001c!1\u0011QC\tA\u0002A\f\u0001\u0002[1tQ\u000e{G-\u001a\u000b\u0003\u0003C\u00012!KA\u0012\u0013\r\t)C\u000b\u0002\u0004\u0013:$\u0018AB3rk\u0006d7\u000f\u0006\u0003\u0002\u000e\u0005-\u0002\u0002CA\u0017\'\u0005\u0005\t\u0019\u00019\u0002\u0007a$\u0013\'A\u0003FcVLg\u000fE\u0002\u0002\u0006U\u0019\"!\u0006\u0015\u0015\u0005\u0005E\u0012A\u0006\u0013fc\u0012\"\u0018\u000e\u001c3fI\u0015\fH%\u001a=uK:\u001c\u0018n\u001c8\u0015\t\u0005m\u0012q\b\u000b\u0005\u0003\u001b\ti\u0004\u0003\u0004\u0002\u0016]\u0001\r\u0001\u001d\u0005\b\u0003\u0003:\u0002\u0019AA\u0002\u0003\u0015!C\u000f[5t\u0003a!#-\u00198hIQLG\u000eZ3%KF$S\r\u001f;f]NLwN\u001c\u000b\u0005\u0003\u000f\nY\u0005\u0006\u0003\u0002\u000e\u0005%\u0003BBA\u000b1\u0001\u0007\u0001\u000fC\u0004\u0002Ba\u0001\r!a\u0001\u0002%!\f7\u000f[\"pI\u0016$S\r\u001f;f]NLwN\u001c\u000b\u0005\u0003?\t\t\u0006C\u0004\u0002Be\u0001\r!a\u0001\u0002!\u0015\fX/\u00197tI\u0015DH/\u001a8tS>tG\u0003BA,\u00037\"B!!\u0004\u0002Z!A\u0011Q\u0006\u000e\u0002\u0002\u0003\u0007\u0001\u000fC\u0004\u0002Bi\u0001\r!a\u0001\u0015\t\u0005\r\u0011q\f\u0005\u0006{n\u0001\r\u0001\u001d
   #9 = Utf8               org/sireum/test/package$Equiv
  #10 = Class              #9             // org/sireum/test/package$Equiv
  #11 = Utf8               Equiv
  #12 = Utf8               org/sireum/test/package$Equiv$
  #13 = Class              #12            // org/sireum/test/package$Equiv$
  #14 = Utf8               Equiv$
  #15 = Utf8               org/sireum/test/package$TestSuite
  #16 = Class              #15            // org/sireum/test/package$TestSuite
  #17 = Utf8               TestSuite
  #18 = Utf8               (Ljava/lang/Object;)Ljava/lang/Object;
  #19 = Utf8               result
  #20 = Utf8               org/sireum/test/package$
  #21 = Class              #20            // org/sireum/test/package$
  #22 = Utf8               MODULE$
  #23 = Utf8               Lorg/sireum/test/package$;
  #24 = NameAndType        #22:#23        // MODULE$:Lorg/sireum/test/package$;
  #25 = Fieldref           #21.#24        // org/sireum/test/package$.MODULE$:Lorg/sireum/test/package$;
  #26 = NameAndType        #11:#18        // Equiv:(Ljava/lang/Object;)Ljava/lang/Object;
  #27 = Methodref          #21.#26        // org/sireum/test/package$.Equiv:(Ljava/lang/Object;)Ljava/lang/Object;
  #28 = Utf8               Ljava/lang/Object;
  #29 = Utf8               Code
  #30 = Utf8               LocalVariableTable
  #31 = Utf8               MethodParameters
  #32 = Utf8               InnerClasses
  #33 = Utf8               SourceFile
  #34 = Utf8               RuntimeVisibleAnnotations
  #35 = Utf8               ScalaSig
{
  public static java.lang.Object Equiv(java.lang.Object);
    descriptor: (Ljava/lang/Object;)Ljava/lang/Object;
    flags: (0x0009) ACC_PUBLIC, ACC_STATIC
    Code:
      stack=2, locals=1, args_size=1
         0: getstatic     #25                 // Field org/sireum/test/package$.MODULE$:Lorg/sireum/test/package$;
         3: aload_0
         4: invokevirtual #27                 // Method org/sireum/test/package$.Equiv:(Ljava/lang/Object;)Ljava/lang/Object;
         7: areturn
      LocalVariableTable:
        Start  Length  Slot  Name   Signature
            0       8     0 result   Ljava/lang/Object;
    MethodParameters:
      Name                           Flags
      result                         final
}
InnerClasses:
  public static final #11= #10 of #2;     // Equiv=class org/sireum/test/package$Equiv of class org/sireum/test/package
  public static #14= #13 of #2;           // Equiv$=class org/sireum/test/package$Equiv$ of class org/sireum/test/package
  public static #17= #16 of #2;           // TestSuite=class org/sireum/test/package$TestSuite of class org/sireum/test/package
SourceFile: "package.scala"
RuntimeVisibleAnnotations:
  0: #6(#7=s#8)
    scala.reflect.ScalaSignature(
      bytes="\u0006\u0005\u0005\u0005t!\u0002\u000f\u001e\u0011\u0003!c!\u0002\u0014\u001e\u0011\u00039\u0003\"\u0002\u0018\u0002\t\u0003yca\u0002\u0019\u0002!\u0003\r\t!\r\u0005\u0006{\r!\tA\u0010\u0004\u0005\u0005\u000e\u00011\t\u0003\u0005E\u000b\t\u0005\t\u0015!\u0003F\u0011\u0015qS\u0001\"\u0001N\u0011\u0015\tV\u0001\"\u0001S\u0011\u0015A6\u0001\"\u0001Z\u0011\u0015Y6\u0001\"\u0001]\u0011\u0015q6\u0001\"\u0001`\r\u0011A\u0018aA=\t\u0011ud!Q1A\u0005\u0002yD\u0001b \u0007\u0003\u0002\u0003\u0006I\u0001\u001d\u0005\u0007]1!\t!!\u0001\t\u000f\u0005%A\u0002\"\u0001\u0002\f!9\u0011q\u0003\u0007\u0005\u0002\u0005e\u0001\"CA\u000f\u0019\u0005\u0005I\u0011IA\u0010\u0011%\t9\u0003DA\u0001\n\u0003\nIcB\u0005\u00020\u0005\t\t\u0011#\u0001\u00022\u0019A\u00010AA\u0001\u0012\u0003\t\u0019\u0004\u0003\u0004/+\u0011\u0005\u0011Q\u0007\u0005\b\u0003o)BQAA\u001d\u0011\u001d\t\u0019%\u0006C\u0003\u0003\u000bB\u0011\"!\u0014\u0016\u0003\u0003%)!a\u0014\t\u0013\u0005MS#!A\u0005\u0006\u0005U\u0003\"CA\u0018\u0003\u0005\u0005I1AA/\u0003\u001d\u0001\u0018mY6bO\u0016T!AH\u0010\u0002\tQ,7\u000f\u001e\u0006\u0003A\u0005\naa]5sKVl\'\"\u0001\u0012\u0002\u0007=\u0014xm\u0001\u0001\u0011\u0005\u0015\nQ\"A\u000f\u0003\u000fA\f7m[1hKN\u0011\u0011\u0001\u000b\t\u0003S1j\u0011A\u000b\u0006\u0002W\u0005)1oY1mC&\u0011QF\u000b\u0002\u0007\u0003:L(+\u001a4\u0002\rqJg.\u001b;?)\u0005!#!\u0003+fgR\u001cV/\u001b;f\'\r\u0019!G\u000f\t\u0003gaj\u0011\u0001\u000e\u0006\u0003kY\n\u0001B\u001a:fKN\u0004Xm\u0019\u0006\u0003o\u0005\n\u0011b]2bY\u0006$Xm\u001d;\n\u0005e\"$aC!os\u001a\u0013X-Z*qK\u000e\u0004\"!J\u001e\n\u0005qj\"AC*je\u0016,Xn\u00159fG\u00061A%\u001b8ji\u0012\"\u0012a\u0010\t\u0003S\u0001K!!\u0011\u0016\u0003\tUs\u0017\u000e\u001e\u0002\n\u0003:|g._7pkN\u001c\"!\u0002\u0015\u0002\u0011A|7/\u001b;j_:\u0004\"AR&\u000e\u0003\u001dS!\u0001S%\u0002\rM|WO]2f\u0015\tQ\u0015%A\u0005tG\u0006d\u0017m\u0019;jG&\u0011Aj\u0012\u0002\t!>\u001c\u0018\u000e^5p]R\u0011a\n\u0015\t\u0003\u001f\u0016i\u0011a\u0001\u0005\u0006\t\u001e\u0001\r!R\u0001\u0007I5Lg.^:\u0015\u0005}\u001a\u0006B\u0002+\t\t\u0003\u0007Q+A\u0001g!\rIckP\u0005\u0003/*\u0012\u0001\u0002\u00102z]\u0006lWMP\u0001\u0007IQLW.Z:\u0015\u00059S\u0006\"\u0002#\n\u0001\b)\u0015!\u0002+fgR\u001cHCA ^\u0011\u0019!&\u0002\"a\u0001+\u0006Y\u0011m]:feRl\u0015\r^2i+\t\u0001\'\u000e\u0006\u0002bmR\u0011qH\u0019\u0005\u0006G.\u0001\r\u0001Z\u0001\u0003a\u001a\u0004$!\u001a;\u0011\t%2\u0007n]\u0005\u0003O*\u0012q\u0002U1si&\fGNR;oGRLwN\u001c\t\u0003S*d\u0001\u0001B\u0003l\u0017\t\u0007ANA\u0001U#\ti\u0007\u000f\u0005\u0002*]&\u0011qN\u000b\u0002\b\u001d>$\b.\u001b8h!\tI\u0013/\u0003\u0002sU\t\u0019\u0011I\\=\u0011\u0005%$H!C;c\u0003\u0003\u0005\tQ!\u0001m\u0005\ryF%\r\u0005\u0006o.\u0001\r\u0001[\u0001\u0002_\n)Q)];jmN\u0011AB\u001f\t\u0003SmL!\u0001 \u0016\u0003\r\u0005s\u0017PV1m\u0003\u0019\u0011Xm];miV\t\u0001/A\u0004sKN,H\u000e\u001e\u0011\u0015\t\u0005\r\u0011q\u0001\t\u0004\u0003\u000baQ\"A\u0001\t\u000bu|\u0001\u0019\u00019\u0002\u0019\u0011*\u0017\u000f\n;jY\u0012,G%Z9\u0015\t\u00055\u00111\u0003\t\u0004S\u0005=\u0011bAA\tU\t9!i\\8mK\u0006t\u0007BBA\u000b!\u0001\u0007\u0001/\u0001\u0005fqB,7\r^3e\u00039!#-\u00198hIQLG\u000eZ3%KF$B!!\u0004\u0002\u001c!1\u0011QC\tA\u0002A\f\u0001\u0002[1tQ\u000e{G-\u001a\u000b\u0003\u0003C\u00012!KA\u0012\u0013\r\t)C\u000b\u0002\u0004\u0013:$\u0018AB3rk\u0006d7\u000f\u0006\u0003\u0002\u000e\u0005-\u0002\u0002CA\u0017\'\u0005\u0005\t\u0019\u00019\u0002\u0007a$\u0013\'A\u0003FcVLg\u000fE\u0002\u0002\u0006U\u0019\"!\u0006\u0015\u0015\u0005\u0005E\u0012A\u0006\u0013fc\u0012\"\u0018\u000e\u001c3fI\u0015\fH%\u001a=uK:\u001c\u0018n\u001c8\u0015\t\u0005m\u0012q\b\u000b\u0005\u0003\u001b\ti\u0004\u0003\u0004\u0002\u0016]\u0001\r\u0001\u001d\u0005\b\u0003\u0003:\u0002\u0019AA\u0002\u0003\u0015!C\u000f[5t\u0003a!#-\u00198hIQLG\u000eZ3%KF$S\r\u001f;f]NLwN\u001c\u000b\u0005\u0003\u000f\nY\u0005\u0006\u0003\u0002\u000e\u0005%\u0003BBA\u000b1\u0001\u0007\u0001\u000fC\u0004\u0002Ba\u0001\r!a\u0001\u0002%!\f7\u000f[\"pI\u0016$S\r\u001f;f]NLwN\u001c\u000b\u0005\u0003?\t\t\u0006C\u0004\u0002Be\u0001\r!a\u0001\u0002!\u0015\fX/\u00197tI\u0015DH/\u001a8tS>tG\u0003BA,\u00037\"B!!\u0004\u0002Z!A\u0011Q\u0006\u000e\u0002\u0002\u0003\u0007\u0001\u000fC\u0004\u0002Bi\u0001\r!a\u0001\u0015\t\u0005\r\u0011q\f\u0005\u0006{n\u0001\r\u0001\u001d"
    )
  ScalaSig: length = 0x3 (unknown attribute)
   05 02 00
