Classfile /Users/mw/Projects/slang-braindump/.jar/jar11/assemble/slang-braindump/assemble/content/org/sireum/test/package$Equiv.class
  Last modified May 29, 2022; size 1381 bytes
  SHA-256 checksum 828cf8c9285ef0b0ca38059e638de02adf2405889f30f575f6ae9bf0d7641bfe
  Compiled from "package.scala"
public final class org.sireum.test.package$Equiv
  minor version: 0
  major version: 52
  flags: (0x0031) ACC_PUBLIC, ACC_FINAL, ACC_SUPER
  this_class: #2                          // org/sireum/test/package$Equiv
  super_class: #4                         // java/lang/Object
  interfaces: 0, fields: 1, methods: 6, attributes: 4
Constant pool:
   #1 = Utf8               org/sireum/test/package$Equiv
   #2 = Class              #1             // org/sireum/test/package$Equiv
   #3 = Utf8               java/lang/Object
   #4 = Class              #3             // java/lang/Object
   #5 = Utf8               package.scala
   #6 = Utf8               org/sireum/test/package
   #7 = Class              #6             // org/sireum/test/package
   #8 = Utf8               Equiv
   #9 = Utf8               org/sireum/test/package$Equiv$
  #10 = Class              #9             // org/sireum/test/package$Equiv$
  #11 = Utf8               Equiv$
  #12 = Utf8               result
  #13 = Utf8               Ljava/lang/Object;
  #14 = Utf8               ()Ljava/lang/Object;
  #15 = NameAndType        #12:#13        // result:Ljava/lang/Object;
  #16 = Fieldref           #2.#15         // org/sireum/test/package$Equiv.result:Ljava/lang/Object;
  #17 = Utf8               this
  #18 = Utf8               Lorg/sireum/test/package$Equiv;
  #19 = Utf8               $eq$tilde$eq
  #20 = Utf8               (Ljava/lang/Object;)Z
  #21 = Utf8               expected
  #22 = Utf8               MODULE$
  #23 = Utf8               Lorg/sireum/test/package$Equiv$;
  #24 = NameAndType        #22:#23        // MODULE$:Lorg/sireum/test/package$Equiv$;
  #25 = Fieldref           #10.#24        // org/sireum/test/package$Equiv$.MODULE$:Lorg/sireum/test/package$Equiv$;
  #26 = NameAndType        #12:#14        // result:()Ljava/lang/Object;
  #27 = Methodref          #2.#26         // org/sireum/test/package$Equiv.result:()Ljava/lang/Object;
  #28 = Utf8               $eq$tilde$eq$extension
  #29 = Utf8               (Ljava/lang/Object;Ljava/lang/Object;)Z
  #30 = NameAndType        #28:#29        // $eq$tilde$eq$extension:(Ljava/lang/Object;Ljava/lang/Object;)Z
  #31 = Methodref          #10.#30        // org/sireum/test/package$Equiv$.$eq$tilde$eq$extension:(Ljava/lang/Object;Ljava/lang/Object;)Z
  #32 = Utf8               $bang$tilde$eq
  #33 = Utf8               $bang$tilde$eq$extension
  #34 = NameAndType        #33:#29        // $bang$tilde$eq$extension:(Ljava/lang/Object;Ljava/lang/Object;)Z
  #35 = Methodref          #10.#34        // org/sireum/test/package$Equiv$.$bang$tilde$eq$extension:(Ljava/lang/Object;Ljava/lang/Object;)Z
  #36 = Utf8               hashCode
  #37 = Utf8               ()I
  #38 = Utf8               hashCode$extension
  #39 = Utf8               (Ljava/lang/Object;)I
  #40 = NameAndType        #38:#39        // hashCode$extension:(Ljava/lang/Object;)I
  #41 = Methodref          #10.#40        // org/sireum/test/package$Equiv$.hashCode$extension:(Ljava/lang/Object;)I
  #42 = Utf8               equals
  #43 = Utf8               x$1
  #44 = Utf8               equals$extension
  #45 = NameAndType        #44:#29        // equals$extension:(Ljava/lang/Object;Ljava/lang/Object;)Z
  #46 = Methodref          #10.#45        // org/sireum/test/package$Equiv$.equals$extension:(Ljava/lang/Object;Ljava/lang/Object;)Z
  #47 = Utf8               <init>
  #48 = Utf8               (Ljava/lang/Object;)V
  #49 = Utf8               ()V
  #50 = NameAndType        #47:#49        // "<init>":()V
  #51 = Methodref          #4.#50         // java/lang/Object."<init>":()V
  #52 = Utf8               Code
  #53 = Utf8               LineNumberTable
  #54 = Utf8               LocalVariableTable
  #55 = Utf8               MethodParameters
  #56 = Utf8               InnerClasses
  #57 = Utf8               SourceFile
  #58 = Utf8               ScalaInlineInfo
  #59 = Utf8               Scala
{
  private final java.lang.Object result;
    descriptor: Ljava/lang/Object;
    flags: (0x0012) ACC_PRIVATE, ACC_FINAL

  public java.lang.Object result();
    descriptor: ()Ljava/lang/Object;
    flags: (0x0001) ACC_PUBLIC
    Code:
      stack=1, locals=1, args_size=1
         0: aload_0
         1: getfield      #16                 // Field result:Ljava/lang/Object;
         4: areturn
      LineNumberTable:
        line 57: 0
      LocalVariableTable:
        Start  Length  Slot  Name   Signature
            0       5     0  this   Lorg/sireum/test/package$Equiv;

  public boolean $eq$tilde$eq(java.lang.Object);
    descriptor: (Ljava/lang/Object;)Z
    flags: (0x0001) ACC_PUBLIC
    Code:
      stack=3, locals=2, args_size=2
         0: getstatic     #25                 // Field org/sireum/test/package$Equiv$.MODULE$:Lorg/sireum/test/package$Equiv$;
         3: aload_0
         4: invokevirtual #27                 // Method result:()Ljava/lang/Object;
         7: aload_1
         8: invokevirtual #31                 // Method org/sireum/test/package$Equiv$.$eq$tilde$eq$extension:(Ljava/lang/Object;Ljava/lang/Object;)Z
        11: ireturn
      LineNumberTable:
        line 58: 0
      LocalVariableTable:
        Start  Length  Slot  Name   Signature
            0      12     0  this   Lorg/sireum/test/package$Equiv;
            0      12     1 expected   Ljava/lang/Object;
    MethodParameters:
      Name                           Flags
      expected                       final

  public boolean $bang$tilde$eq(java.lang.Object);
    descriptor: (Ljava/lang/Object;)Z
    flags: (0x0001) ACC_PUBLIC
    Code:
      stack=3, locals=2, args_size=2
         0: getstatic     #25                 // Field org/sireum/test/package$Equiv$.MODULE$:Lorg/sireum/test/package$Equiv$;
         3: aload_0
         4: invokevirtual #27                 // Method result:()Ljava/lang/Object;
         7: aload_1
         8: invokevirtual #35                 // Method org/sireum/test/package$Equiv$.$bang$tilde$eq$extension:(Ljava/lang/Object;Ljava/lang/Object;)Z
        11: ireturn
      LineNumberTable:
        line 82: 0
      LocalVariableTable:
        Start  Length  Slot  Name   Signature
            0      12     0  this   Lorg/sireum/test/package$Equiv;
            0      12     1 expected   Ljava/lang/Object;
    MethodParameters:
      Name                           Flags
      expected                       final

  public int hashCode();
    descriptor: ()I
    flags: (0x0001) ACC_PUBLIC
    Code:
      stack=2, locals=1, args_size=1
         0: getstatic     #25                 // Field org/sireum/test/package$Equiv$.MODULE$:Lorg/sireum/test/package$Equiv$;
         3: aload_0
         4: invokevirtual #27                 // Method result:()Ljava/lang/Object;
         7: invokevirtual #41                 // Method org/sireum/test/package$Equiv$.hashCode$extension:(Ljava/lang/Object;)I
        10: ireturn
      LineNumberTable:
        line 57: 0
      LocalVariableTable:
        Start  Length  Slot  Name   Signature
            0      11     0  this   Lorg/sireum/test/package$Equiv;

  public boolean equals(java.lang.Object);
    descriptor: (Ljava/lang/Object;)Z
    flags: (0x0001) ACC_PUBLIC
    Code:
      stack=3, locals=2, args_size=2
         0: getstatic     #25                 // Field org/sireum/test/package$Equiv$.MODULE$:Lorg/sireum/test/package$Equiv$;
         3: aload_0
         4: invokevirtual #27                 // Method result:()Ljava/lang/Object;
         7: aload_1
         8: invokevirtual #46                 // Method org/sireum/test/package$Equiv$.equals$extension:(Ljava/lang/Object;Ljava/lang/Object;)Z
        11: ireturn
      LineNumberTable:
        line 57: 0
      LocalVariableTable:
        Start  Length  Slot  Name   Signature
            0      12     0  this   Lorg/sireum/test/package$Equiv;
            0      12     1   x$1   Ljava/lang/Object;
    MethodParameters:
      Name                           Flags
      x$1                            final

  public org.sireum.test.package$Equiv(java.lang.Object);
    descriptor: (Ljava/lang/Object;)V
    flags: (0x0001) ACC_PUBLIC
    Code:
      stack=2, locals=2, args_size=2
         0: aload_0
         1: aload_1
         2: putfield      #16                 // Field result:Ljava/lang/Object;
         5: aload_0
         6: invokespecial #51                 // Method java/lang/Object."<init>":()V
         9: return
      LineNumberTable:
        line 57: 0
      LocalVariableTable:
        Start  Length  Slot  Name   Signature
            0      10     0  this   Lorg/sireum/test/package$Equiv;
            0      10     1 result   Ljava/lang/Object;
    MethodParameters:
      Name                           Flags
      result                         final
}
InnerClasses:
  public static final #8= #2 of #7;       // Equiv=class org/sireum/test/package$Equiv of class org/sireum/test/package
  public static #11= #10 of #7;           // Equiv$=class org/sireum/test/package$Equiv$ of class org/sireum/test/package
SourceFile: "package.scala"
  ScalaInlineInfo: length = 0x22 (unknown attribute)
   01 01 00 06 00 20 00 14 01 00 13 00 14 01 00 2F
   00 30 01 00 2A 00 14 01 00 24 00 25 01 00 0C 00
   0E 01
  Scala: length = 0x0 (unknown attribute)

