Classfile /Users/mw/Projects/slang-braindump/.jar/jar8/assemble/slang-braindump/assemble/content/coursier/credentials/DirectCredentials$.class
  Last modified May 29, 2022; size 4165 bytes
  SHA-256 checksum 1c080024418229dc5057725fc8248ceaaa2b8478c748f1adcdd53af06f8f1e93
  Compiled from "DirectCredentials.scala"
public final class coursier.credentials.DirectCredentials$ implements java.io.Serializable
  minor version: 0
  major version: 52
  flags: (0x0031) ACC_PUBLIC, ACC_FINAL, ACC_SUPER
  this_class: #2                          // coursier/credentials/DirectCredentials$
  super_class: #4                         // java/lang/Object
  interfaces: 1, fields: 1, methods: 12, attributes: 3
Constant pool:
   #1 = Utf8               coursier/credentials/DirectCredentials$
   #2 = Class              #1             // coursier/credentials/DirectCredentials$
   #3 = Utf8               java/lang/Object
   #4 = Class              #3             // java/lang/Object
   #5 = Utf8               java/io/Serializable
   #6 = Class              #5             // java/io/Serializable
   #7 = Utf8               DirectCredentials.scala
   #8 = Utf8               MODULE$
   #9 = Utf8               Lcoursier/credentials/DirectCredentials$;
  #10 = Utf8               <clinit>
  #11 = Utf8               ()V
  #12 = Utf8               <init>
  #13 = NameAndType        #12:#11        // "<init>":()V
  #14 = Methodref          #2.#13         // coursier/credentials/DirectCredentials$."<init>":()V
  #15 = NameAndType        #8:#9          // MODULE$:Lcoursier/credentials/DirectCredentials$;
  #16 = Fieldref           #2.#15         // coursier/credentials/DirectCredentials$.MODULE$:Lcoursier/credentials/DirectCredentials$;
  #17 = Utf8               apply
  #18 = Utf8               (Ljava/lang/String;Ljava/lang/String;Ljava/lang/String;)Lcoursier/credentials/DirectCredentials;
  #19 = Utf8               host
  #20 = Utf8               username
  #21 = Utf8               password
  #22 = Utf8               scala/Some
  #23 = Class              #22            // scala/Some
  #24 = Utf8               (Ljava/lang/Object;)V
  #25 = NameAndType        #12:#24        // "<init>":(Ljava/lang/Object;)V
  #26 = Methodref          #23.#25        // scala/Some."<init>":(Ljava/lang/Object;)V
  #27 = Utf8               coursier/credentials/Password$
  #28 = Class              #27            // coursier/credentials/Password$
  #29 = Utf8               Lcoursier/credentials/Password$;
  #30 = NameAndType        #8:#29         // MODULE$:Lcoursier/credentials/Password$;
  #31 = Fieldref           #28.#30        // coursier/credentials/Password$.MODULE$:Lcoursier/credentials/Password$;
  #32 = Utf8               (Ljava/lang/Object;)Lcoursier/credentials/Password;
  #33 = NameAndType        #17:#32        // apply:(Ljava/lang/Object;)Lcoursier/credentials/Password;
  #34 = Methodref          #28.#33        // coursier/credentials/Password$.apply:(Ljava/lang/Object;)Lcoursier/credentials/Password;
  #35 = Utf8               (Ljava/lang/String;Lscala/Option;Lscala/Option;)Lcoursier/credentials/DirectCredentials;
  #36 = NameAndType        #17:#35        // apply:(Ljava/lang/String;Lscala/Option;Lscala/Option;)Lcoursier/credentials/DirectCredentials;
  #37 = Methodref          #2.#36         // coursier/credentials/DirectCredentials$.apply:(Ljava/lang/String;Lscala/Option;Lscala/Option;)Lcoursier/credentials/DirectCredentials;
  #38 = Utf8               this
  #39 = Utf8               Ljava/lang/String;
  #40 = Utf8               (Ljava/lang/String;Ljava/lang/String;Ljava/lang/String;Lscala/Option;)Lcoursier/credentials/DirectCredentials;
  #41 = Utf8               (Ljava/lang/String;Ljava/lang/String;Ljava/lang/String;Lscala/Option<Ljava/lang/String;>;)Lcoursier/credentials/DirectCredentials;
  #42 = Utf8               realm
  #43 = Utf8               (Ljava/lang/String;Lscala/Option;Lscala/Option;Lscala/Option;)Lcoursier/credentials/DirectCredentials;
  #44 = NameAndType        #17:#43        // apply:(Ljava/lang/String;Lscala/Option;Lscala/Option;Lscala/Option;)Lcoursier/credentials/DirectCredentials;
  #45 = Methodref          #2.#44         // coursier/credentials/DirectCredentials$.apply:(Ljava/lang/String;Lscala/Option;Lscala/Option;Lscala/Option;)Lcoursier/credentials/DirectCredentials;
  #46 = Utf8               Lscala/Option;
  #47 = Utf8               defaultMatchHost
  #48 = Utf8               ()Z
  #49 = Utf8               defaultHttpsOnly
  #50 = Utf8               ()Lcoursier/credentials/DirectCredentials;
  #51 = Utf8               coursier/credentials/DirectCredentials
  #52 = Class              #51            // coursier/credentials/DirectCredentials
  #53 = Utf8
  #54 = String             #53            //
  #55 = Utf8               scala/None$
  #56 = Class              #55            // scala/None$
  #57 = Utf8               Lscala/None$;
  #58 = NameAndType        #8:#57         // MODULE$:Lscala/None$;
  #59 = Fieldref           #56.#58        // scala/None$.MODULE$:Lscala/None$;
  #60 = NameAndType        #47:#48        // defaultMatchHost:()Z
  #61 = Methodref          #2.#60         // coursier/credentials/DirectCredentials$.defaultMatchHost:()Z
  #62 = NameAndType        #49:#48        // defaultHttpsOnly:()Z
  #63 = Methodref          #2.#62         // coursier/credentials/DirectCredentials$.defaultHttpsOnly:()Z
  #64 = Utf8               (Ljava/lang/String;Lscala/Option;Lscala/Option;Lscala/Option;ZZZZ)V
  #65 = NameAndType        #12:#64        // "<init>":(Ljava/lang/String;Lscala/Option;Lscala/Option;Lscala/Option;ZZZZ)V
  #66 = Methodref          #52.#65        // coursier/credentials/DirectCredentials."<init>":(Ljava/lang/String;Lscala/Option;Lscala/Option;Lscala/Option;ZZZZ)V
  #67 = Utf8               (Ljava/lang/String;Lscala/Option<Ljava/lang/String;>;Lscala/Option<Lcoursier/credentials/Password<Ljava/lang/String;>;>;)Lcoursier/credentials/DirectCredentials;
  #68 = Utf8               usernameOpt
  #69 = Utf8               passwordOpt
  #70 = Utf8               (Ljava/lang/String;Lscala/Option<Ljava/lang/String;>;Lscala/Option<Lcoursier/credentials/Password<Ljava/lang/String;>;>;Lscala/Option<Ljava/lang/String;>;)Lcoursier/credentials/DirectCredentials;
  #71 = Utf8               (Ljava/lang/String;Lscala/Option;Lscala/Option;Lscala/Option;Z)Lcoursier/credentials/DirectCredentials;
  #72 = Utf8               (Ljava/lang/String;Lscala/Option<Ljava/lang/String;>;Lscala/Option<Lcoursier/credentials/Password<Ljava/lang/String;>;>;Lscala/Option<Ljava/lang/String;>;Z)Lcoursier/credentials/DirectCredentials;
  #73 = Utf8               optional
  #74 = Utf8               Z
  #75 = Utf8               (Ljava/lang/String;Lscala/Option;Lscala/Option;Lscala/Option;ZZZZ)Lcoursier/credentials/DirectCredentials;
  #76 = Utf8               (Ljava/lang/String;Lscala/Option<Ljava/lang/String;>;Lscala/Option<Lcoursier/credentials/Password<Ljava/lang/String;>;>;Lscala/Option<Ljava/lang/String;>;ZZZZ)Lcoursier/credentials/DirectCredentials;
  #77 = Utf8               matchHost
  #78 = Utf8               httpsOnly
  #79 = Utf8               passOnRedirect
  #80 = Utf8               writeReplace
  #81 = Utf8               ()Ljava/lang/Object;
  #82 = Utf8               scala/runtime/ModuleSerializationProxy
  #83 = Class              #82            // scala/runtime/ModuleSerializationProxy
  #84 = Utf8               (Ljava/lang/Class;)V
  #85 = NameAndType        #12:#84        // "<init>":(Ljava/lang/Class;)V
  #86 = Methodref          #83.#85        // scala/runtime/ModuleSerializationProxy."<init>":(Ljava/lang/Class;)V
  #87 = Methodref          #4.#13         // java/lang/Object."<init>":()V
  #88 = Utf8               Code
  #89 = Utf8               LineNumberTable
  #90 = Utf8               LocalVariableTable
  #91 = Utf8               MethodParameters
  #92 = Utf8               Signature
  #93 = Utf8               SourceFile
  #94 = Utf8               ScalaInlineInfo
  #95 = Utf8               Scala
{
  public static final coursier.credentials.DirectCredentials$ MODULE$;
    descriptor: Lcoursier/credentials/DirectCredentials$;
    flags: (0x0019) ACC_PUBLIC, ACC_STATIC, ACC_FINAL

  public static {};
    descriptor: ()V
    flags: (0x0009) ACC_PUBLIC, ACC_STATIC
    Code:
      stack=2, locals=0, args_size=0
         0: new           #2                  // class coursier/credentials/DirectCredentials$
         3: dup
         4: invokespecial #14                 // Method "<init>":()V
         7: putstatic     #16                 // Field MODULE$:Lcoursier/credentials/DirectCredentials$;
        10: return
      LineNumberTable:
        line 10: 0

  public coursier.credentials.DirectCredentials apply(java.lang.String, java.lang.String, java.lang.String);
    descriptor: (Ljava/lang/String;Ljava/lang/String;Ljava/lang/String;)Lcoursier/credentials/DirectCredentials;
    flags: (0x0001) ACC_PUBLIC
    Code:
      stack=7, locals=4, args_size=4
         0: aload_0
         1: aload_1
         2: new           #23                 // class scala/Some
         5: dup
         6: aload_2
         7: invokespecial #26                 // Method scala/Some."<init>":(Ljava/lang/Object;)V
        10: new           #23                 // class scala/Some
        13: dup
        14: getstatic     #31                 // Field coursier/credentials/Password$.MODULE$:Lcoursier/credentials/Password$;
        17: aload_3
        18: invokevirtual #34                 // Method coursier/credentials/Password$.apply:(Ljava/lang/Object;)Lcoursier/credentials/Password;
        21: invokespecial #26                 // Method scala/Some."<init>":(Ljava/lang/Object;)V
        24: invokevirtual #37                 // Method apply:(Ljava/lang/String;Lscala/Option;Lscala/Option;)Lcoursier/credentials/DirectCredentials;
        27: areturn
      LineNumberTable:
        line 75: 0
      LocalVariableTable:
        Start  Length  Slot  Name   Signature
            0      28     0  this   Lcoursier/credentials/DirectCredentials$;
            0      28     1  host   Ljava/lang/String;
            0      28     2 username   Ljava/lang/String;
            0      28     3 password   Ljava/lang/String;
    MethodParameters:
      Name                           Flags
      host                           final
      username                       final
      password                       final

  public coursier.credentials.DirectCredentials apply(java.lang.String, java.lang.String, java.lang.String, scala.Option<java.lang.String>);
    descriptor: (Ljava/lang/String;Ljava/lang/String;Ljava/lang/String;Lscala/Option;)Lcoursier/credentials/DirectCredentials;
    flags: (0x0001) ACC_PUBLIC
    Code:
      stack=7, locals=5, args_size=5
         0: aload_0
         1: aload_1
         2: new           #23                 // class scala/Some
         5: dup
         6: aload_2
         7: invokespecial #26                 // Method scala/Some."<init>":(Ljava/lang/Object;)V
        10: new           #23                 // class scala/Some
        13: dup
        14: getstatic     #31                 // Field coursier/credentials/Password$.MODULE$:Lcoursier/credentials/Password$;
        17: aload_3
        18: invokevirtual #34                 // Method coursier/credentials/Password$.apply:(Ljava/lang/Object;)Lcoursier/credentials/Password;
        21: invokespecial #26                 // Method scala/Some."<init>":(Ljava/lang/Object;)V
        24: aload         4
        26: invokevirtual #45                 // Method apply:(Ljava/lang/String;Lscala/Option;Lscala/Option;Lscala/Option;)Lcoursier/credentials/DirectCredentials;
        29: areturn
      LineNumberTable:
        line 76: 0
      LocalVariableTable:
        Start  Length  Slot  Name   Signature
            0      30     0  this   Lcoursier/credentials/DirectCredentials$;
            0      30     1  host   Ljava/lang/String;
            0      30     2 username   Ljava/lang/String;
            0      30     3 password   Ljava/lang/String;
            0      30     4 realm   Lscala/Option;
    Signature: #41                          // (Ljava/lang/String;Ljava/lang/String;Ljava/lang/String;Lscala/Option<Ljava/lang/String;>;)Lcoursier/credentials/DirectCredentials;
    MethodParameters:
      Name                           Flags
      host                           final
      username                       final
      password                       final
      realm                          final

  public boolean defaultMatchHost();
    descriptor: ()Z
    flags: (0x0001) ACC_PUBLIC
    Code:
      stack=1, locals=1, args_size=1
         0: iconst_1
         1: ireturn
      LineNumberTable:
        line 79: 0
      LocalVariableTable:
        Start  Length  Slot  Name   Signature
            0       2     0  this   Lcoursier/credentials/DirectCredentials$;

  public boolean defaultHttpsOnly();
    descriptor: ()Z
    flags: (0x0001) ACC_PUBLIC
    Code:
      stack=1, locals=1, args_size=1
         0: iconst_0
         1: ireturn
      LineNumberTable:
        line 81: 0
      LocalVariableTable:
        Start  Length  Slot  Name   Signature
            0       2     0  this   Lcoursier/credentials/DirectCredentials$;

  public coursier.credentials.DirectCredentials apply();
    descriptor: ()Lcoursier/credentials/DirectCredentials;
    flags: (0x0001) ACC_PUBLIC
    Code:
      stack=10, locals=1, args_size=1
         0: new           #52                 // class coursier/credentials/DirectCredentials
         3: dup
         4: ldc           #54                 // String
         6: getstatic     #59                 // Field scala/None$.MODULE$:Lscala/None$;
         9: getstatic     #59                 // Field scala/None$.MODULE$:Lscala/None$;
        12: getstatic     #59                 // Field scala/None$.MODULE$:Lscala/None$;
        15: iconst_1
        16: aload_0
        17: invokevirtual #61                 // Method defaultMatchHost:()Z
        20: aload_0
        21: invokevirtual #63                 // Method defaultHttpsOnly:()Z
        24: iconst_0
        25: invokespecial #66                 // Method coursier/credentials/DirectCredentials."<init>":(Ljava/lang/String;Lscala/Option;Lscala/Option;Lscala/Option;ZZZZ)V
        28: areturn
      LineNumberTable:
        line 10: 0
        line 11: 4
        line 12: 6
        line 13: 9
        line 15: 12
        line 17: 15
        line 19: 16
        line 20: 20
        line 21: 24
      LocalVariableTable:
        Start  Length  Slot  Name   Signature
            0      29     0  this   Lcoursier/credentials/DirectCredentials$;

  public coursier.credentials.DirectCredentials apply(java.lang.String, scala.Option<java.lang.String>, scala.Option<coursier.credentials.Password<java.lang.String>>);
    descriptor: (Ljava/lang/String;Lscala/Option;Lscala/Option;)Lcoursier/credentials/DirectCredentials;
    flags: (0x0001) ACC_PUBLIC
    Code:
      stack=10, locals=4, args_size=4
         0: new           #52                 // class coursier/credentials/DirectCredentials
         3: dup
         4: aload_1
         5: aload_2
         6: aload_3
         7: getstatic     #59                 // Field scala/None$.MODULE$:Lscala/None$;
        10: iconst_1
        11: aload_0
        12: invokevirtual #61                 // Method defaultMatchHost:()Z
        15: aload_0
        16: invokevirtual #63                 // Method defaultHttpsOnly:()Z
        19: iconst_0
        20: invokespecial #66                 // Method coursier/credentials/DirectCredentials."<init>":(Ljava/lang/String;Lscala/Option;Lscala/Option;Lscala/Option;ZZZZ)V
        23: areturn
      LineNumberTable:
        line 10: 0
        line 15: 7
        line 17: 10
        line 19: 11
        line 20: 15
        line 21: 19
      LocalVariableTable:
        Start  Length  Slot  Name   Signature
            0      24     0  this   Lcoursier/credentials/DirectCredentials$;
            0      24     1  host   Ljava/lang/String;
            0      24     2 usernameOpt   Lscala/Option;
            0      24     3 passwordOpt   Lscala/Option;
    Signature: #67                          // (Ljava/lang/String;Lscala/Option<Ljava/lang/String;>;Lscala/Option<Lcoursier/credentials/Password<Ljava/lang/String;>;>;)Lcoursier/credentials/DirectCredentials;
    MethodParameters:
      Name                           Flags
      host                           final
      usernameOpt                    final
      passwordOpt                    final

  public coursier.credentials.DirectCredentials apply(java.lang.String, scala.Option<java.lang.String>, scala.Option<coursier.credentials.Password<java.lang.String>>, scala.Option<java.lang.String>);
    descriptor: (Ljava/lang/String;Lscala/Option;Lscala/Option;Lscala/Option;)Lcoursier/credentials/DirectCredentials;
    flags: (0x0001) ACC_PUBLIC
    Code:
      stack=10, locals=5, args_size=5
         0: new           #52                 // class coursier/credentials/DirectCredentials
         3: dup
         4: aload_1
         5: aload_2
         6: aload_3
         7: aload         4
         9: iconst_1
        10: aload_0
        11: invokevirtual #61                 // Method defaultMatchHost:()Z
        14: aload_0
        15: invokevirtual #63                 // Method defaultHttpsOnly:()Z
        18: iconst_0
        19: invokespecial #66                 // Method coursier/credentials/DirectCredentials."<init>":(Ljava/lang/String;Lscala/Option;Lscala/Option;Lscala/Option;ZZZZ)V
        22: areturn
      LineNumberTable:
        line 10: 0
        line 17: 9
        line 19: 10
        line 20: 14
        line 21: 18
      LocalVariableTable:
        Start  Length  Slot  Name   Signature
            0      23     0  this   Lcoursier/credentials/DirectCredentials$;
            0      23     1  host   Ljava/lang/String;
            0      23     2 usernameOpt   Lscala/Option;
            0      23     3 passwordOpt   Lscala/Option;
            0      23     4 realm   Lscala/Option;
    Signature: #70                          // (Ljava/lang/String;Lscala/Option<Ljava/lang/String;>;Lscala/Option<Lcoursier/credentials/Password<Ljava/lang/String;>;>;Lscala/Option<Ljava/lang/String;>;)Lcoursier/credentials/DirectCredentials;
    MethodParameters:
      Name                           Flags
      host                           final
      usernameOpt                    final
      passwordOpt                    final
      realm                          final

  public coursier.credentials.DirectCredentials apply(java.lang.String, scala.Option<java.lang.String>, scala.Option<coursier.credentials.Password<java.lang.String>>, scala.Option<java.lang.String>, boolean);
    descriptor: (Ljava/lang/String;Lscala/Option;Lscala/Option;Lscala/Option;Z)Lcoursier/credentials/DirectCredentials;
    flags: (0x0001) ACC_PUBLIC
    Code:
      stack=10, locals=6, args_size=6
         0: new           #52                 // class coursier/credentials/DirectCredentials
         3: dup
         4: aload_1
         5: aload_2
         6: aload_3
         7: aload         4
         9: iload         5
        11: aload_0
        12: invokevirtual #61                 // Method defaultMatchHost:()Z
        15: aload_0
        16: invokevirtual #63                 // Method defaultHttpsOnly:()Z
        19: iconst_0
        20: invokespecial #66                 // Method coursier/credentials/DirectCredentials."<init>":(Ljava/lang/String;Lscala/Option;Lscala/Option;Lscala/Option;ZZZZ)V
        23: areturn
      LineNumberTable:
        line 10: 0
        line 19: 11
        line 20: 15
        line 21: 19
      LocalVariableTable:
        Start  Length  Slot  Name   Signature
            0      24     0  this   Lcoursier/credentials/DirectCredentials$;
            0      24     1  host   Ljava/lang/String;
            0      24     2 usernameOpt   Lscala/Option;
            0      24     3 passwordOpt   Lscala/Option;
            0      24     4 realm   Lscala/Option;
            0      24     5 optional   Z
    Signature: #72                          // (Ljava/lang/String;Lscala/Option<Ljava/lang/String;>;Lscala/Option<Lcoursier/credentials/Password<Ljava/lang/String;>;>;Lscala/Option<Ljava/lang/String;>;Z)Lcoursier/credentials/DirectCredentials;
    MethodParameters:
      Name                           Flags
      host                           final
      usernameOpt                    final
      passwordOpt                    final
      realm                          final
      optional                       final

  public coursier.credentials.DirectCredentials apply(java.lang.String, scala.Option<java.lang.String>, scala.Option<coursier.credentials.Password<java.lang.String>>, scala.Option<java.lang.String>, boolean, boolean, boolean, boolean);
    descriptor: (Ljava/lang/String;Lscala/Option;Lscala/Option;Lscala/Option;ZZZZ)Lcoursier/credentials/DirectCredentials;
    flags: (0x0001) ACC_PUBLIC
    Code:
      stack=10, locals=9, args_size=9
         0: new           #52                 // class coursier/credentials/DirectCredentials
         3: dup
         4: aload_1
         5: aload_2
         6: aload_3
         7: aload         4
         9: iload         5
        11: iload         6
        13: iload         7
        15: iload         8
        17: invokespecial #66                 // Method coursier/credentials/DirectCredentials."<init>":(Ljava/lang/String;Lscala/Option;Lscala/Option;Lscala/Option;ZZZZ)V
        20: areturn
      LineNumberTable:
        line 10: 0
      LocalVariableTable:
        Start  Length  Slot  Name   Signature
            0      21     0  this   Lcoursier/credentials/DirectCredentials$;
            0      21     1  host   Ljava/lang/String;
            0      21     2 usernameOpt   Lscala/Option;
            0      21     3 passwordOpt   Lscala/Option;
            0      21     4 realm   Lscala/Option;
            0      21     5 optional   Z
            0      21     6 matchHost   Z
            0      21     7 httpsOnly   Z
            0      21     8 passOnRedirect   Z
    Signature: #76                          // (Ljava/lang/String;Lscala/Option<Ljava/lang/String;>;Lscala/Option<Lcoursier/credentials/Password<Ljava/lang/String;>;>;Lscala/Option<Ljava/lang/String;>;ZZZZ)Lcoursier/credentials/DirectCredentials;
    MethodParameters:
      Name                           Flags
      host                           final
      usernameOpt                    final
      passwordOpt                    final
      realm                          final
      optional                       final
      matchHost                      final
      httpsOnly                      final
      passOnRedirect                 final

  private java.lang.Object writeReplace();
    descriptor: ()Ljava/lang/Object;
    flags: (0x0002) ACC_PRIVATE
    Code:
      stack=3, locals=1, args_size=1
         0: new           #83                 // class scala/runtime/ModuleSerializationProxy
         3: dup
         4: ldc           #2                  // class coursier/credentials/DirectCredentials$
         6: invokespecial #86                 // Method scala/runtime/ModuleSerializationProxy."<init>":(Ljava/lang/Class;)V
         9: areturn
      LineNumberTable:
        line 10: 0
      LocalVariableTable:
        Start  Length  Slot  Name   Signature
            0      10     0  this   Lcoursier/credentials/DirectCredentials$;

  private coursier.credentials.DirectCredentials$();
    descriptor: ()V
    flags: (0x0002) ACC_PRIVATE
    Code:
      stack=1, locals=1, args_size=1
         0: aload_0
         1: invokespecial #87                 // Method java/lang/Object."<init>":()V
         4: return
      LineNumberTable:
        line 82: 0
        line 10: 4
      LocalVariableTable:
        Start  Length  Slot  Name   Signature
            0       5     0  this   Lcoursier/credentials/DirectCredentials$;
}
SourceFile: "DirectCredentials.scala"
  ScalaInlineInfo: length = 0x3B (unknown attribute)
   01 01 00 0B 00 0C 00 0B 01 00 11 00 32 01 00 11
   00 12 01 00 11 00 28 01 00 11 00 23 01 00 11 00
   2B 01 00 11 00 47 01 00 11 00 4B 01 00 31 00 30
   01 00 2F 00 30 01 00 50 00 51 01
  Scala: length = 0x0 (unknown attribute)

