Classfile /Users/mw/Projects/slang-braindump/.jar/jar8/assemble/slang-braindump/assemble/content/coursier/credentials/FileCredentials$.class
  Last modified May 29, 2022; size 8255 bytes
  SHA-256 checksum 40ea6e5d1c2cc504304ee6a1bdb0ea579fbe14464de4638d1cdb19944e93a45f
  Compiled from "FileCredentials.scala"
public final class coursier.credentials.FileCredentials$ implements java.io.Serializable
  minor version: 0
  major version: 52
  flags: (0x0031) ACC_PUBLIC, ACC_FINAL, ACC_SUPER
  this_class: #2                          // coursier/credentials/FileCredentials$
  super_class: #4                         // java/lang/Object
  interfaces: 1, fields: 1, methods: 22, attributes: 5
Constant pool:
    #1 = Utf8               coursier/credentials/FileCredentials$
    #2 = Class              #1            // coursier/credentials/FileCredentials$
    #3 = Utf8               java/lang/Object
    #4 = Class              #3            // java/lang/Object
    #5 = Utf8               java/io/Serializable
    #6 = Class              #5            // java/io/Serializable
    #7 = Utf8               FileCredentials.scala
    #8 = Utf8               java/lang/invoke/MethodHandles$Lookup
    #9 = Class              #8            // java/lang/invoke/MethodHandles$Lookup
   #10 = Utf8               java/lang/invoke/MethodHandles
   #11 = Class              #10           // java/lang/invoke/MethodHandles
   #12 = Utf8               Lookup
   #13 = Utf8               scala/collection/convert/AsScalaExtensions$EnumerationHasAsScala
   #14 = Class              #13           // scala/collection/convert/AsScalaExtensions$EnumerationHasAsScala
   #15 = Utf8               scala/collection/convert/AsScalaExtensions
   #16 = Class              #15           // scala/collection/convert/AsScalaExtensions
   #17 = Utf8               EnumerationHasAsScala
   #18 = Utf8               MODULE$
   #19 = Utf8               Lcoursier/credentials/FileCredentials$;
   #20 = Utf8               <clinit>
   #21 = Utf8               ()V
   #22 = Utf8               <init>
   #23 = NameAndType        #22:#21       // "<init>":()V
   #24 = Methodref          #2.#23        // coursier/credentials/FileCredentials$."<init>":()V
   #25 = NameAndType        #18:#19       // MODULE$:Lcoursier/credentials/FileCredentials$;
   #26 = Fieldref           #2.#25        // coursier/credentials/FileCredentials$.MODULE$:Lcoursier/credentials/FileCredentials$;
   #27 = Utf8               parse
   #28 = Utf8               (Ljava/lang/String;Ljava/lang/String;)Lscala/collection/immutable/Seq;
   #29 = Utf8               (Ljava/lang/String;Ljava/lang/String;)Lscala/collection/immutable/Seq<Lcoursier/credentials/DirectCredentials;>;
   #30 = Utf8               content
   #31 = Utf8               origin
   #32 = Utf8               java/util/Properties
   #33 = Class              #32           // java/util/Properties
   #34 = Methodref          #33.#23       // java/util/Properties."<init>":()V
   #35 = Utf8               java/io/StringReader
   #36 = Class              #35           // java/io/StringReader
   #37 = Utf8               (Ljava/lang/String;)V
   #38 = NameAndType        #22:#37       // "<init>":(Ljava/lang/String;)V
   #39 = Methodref          #36.#38       // java/io/StringReader."<init>":(Ljava/lang/String;)V
   #40 = Utf8               load
   #41 = Utf8               (Ljava/io/Reader;)V
   #42 = NameAndType        #40:#41       // load:(Ljava/io/Reader;)V
   #43 = Methodref          #33.#42       // java/util/Properties.load:(Ljava/io/Reader;)V
   #44 = Utf8               scala/jdk/CollectionConverters$
   #45 = Class              #44           // scala/jdk/CollectionConverters$
   #46 = Utf8               Lscala/jdk/CollectionConverters$;
   #47 = NameAndType        #18:#46       // MODULE$:Lscala/jdk/CollectionConverters$;
   #48 = Fieldref           #45.#47       // scala/jdk/CollectionConverters$.MODULE$:Lscala/jdk/CollectionConverters$;
   #49 = Utf8               propertyNames
   #50 = Utf8               ()Ljava/util/Enumeration;
   #51 = NameAndType        #49:#50       // propertyNames:()Ljava/util/Enumeration;
   #52 = Methodref          #33.#51       // java/util/Properties.propertyNames:()Ljava/util/Enumeration;
   #53 = Utf8               (Ljava/util/Enumeration;)Lscala/collection/convert/AsScalaExtensions$EnumerationHasAsScala;
   #54 = NameAndType        #17:#53       // EnumerationHasAsScala:(Ljava/util/Enumeration;)Lscala/collection/convert/AsScalaExtensions$EnumerationHasAsScala;
   #55 = Methodref          #45.#54       // scala/jdk/CollectionConverters$.EnumerationHasAsScala:(Ljava/util/Enumeration;)Lscala/collection/convert/AsScalaExtensions$EnumerationHasAsScala;
   #56 = Utf8               asScala
   #57 = Utf8               ()Lscala/collection/Iterator;
   #58 = NameAndType        #56:#57       // asScala:()Lscala/collection/Iterator;
   #59 = Methodref          #14.#58       // scala/collection/convert/AsScalaExtensions$EnumerationHasAsScala.asScala:()Lscala/collection/Iterator;
   #60 = Utf8               (Ljava/lang/Object;)Ljava/lang/Object;
   #61 = MethodType         #60           //  (Ljava/lang/Object;)Ljava/lang/Object;
   #62 = Utf8               $anonfun$parse$1
   #63 = Utf8               (Ljava/lang/Object;)Ljava/lang/String;
   #64 = NameAndType        #62:#63       // $anonfun$parse$1:(Ljava/lang/Object;)Ljava/lang/String;
   #65 = Methodref          #2.#64        // coursier/credentials/FileCredentials$.$anonfun$parse$1:(Ljava/lang/Object;)Ljava/lang/String;
   #66 = MethodHandle       6:#65         // REF_invokeStatic coursier/credentials/FileCredentials$.$anonfun$parse$1:(Ljava/lang/Object;)Ljava/lang/String;
   #67 = MethodType         #63           //  (Ljava/lang/Object;)Ljava/lang/String;
   #68 = Integer            5
   #69 = Integer            1
   #70 = Utf8               java/lang/invoke/LambdaMetafactory
   #71 = Class              #70           // java/lang/invoke/LambdaMetafactory
   #72 = Utf8               altMetafactory
   #73 = Utf8               (Ljava/lang/invoke/MethodHandles$Lookup;Ljava/lang/String;Ljava/lang/invoke/MethodType;[Ljava/lang/Object;)Ljava/lang/invoke/CallSite;
   #74 = NameAndType        #72:#73       // altMetafactory:(Ljava/lang/invoke/MethodHandles$Lookup;Ljava/lang/String;Ljava/lang/invoke/MethodType;[Ljava/lang/Object;)Ljava/lang/invoke/CallSite;
   #75 = Methodref          #71.#74       // java/lang/invoke/LambdaMetafactory.altMetafactory:(Ljava/lang/invoke/MethodHandles$Lookup;Ljava/lang/String;Ljava/lang/invoke/MethodType;[Ljava/lang/Object;)Ljava/lang/invoke/CallSite;
   #76 = MethodHandle       6:#75         // REF_invokeStatic java/lang/invoke/LambdaMetafactory.altMetafactory:(Ljava/lang/invoke/MethodHandles$Lookup;Ljava/lang/String;Ljava/lang/invoke/MethodType;[Ljava/lang/Object;)Ljava/lang/invoke/CallSite;
   #77 = Utf8               apply
   #78 = Utf8               ()Lscala/Function1;
   #79 = NameAndType        #77:#78       // apply:()Lscala/Function1;
   #80 = InvokeDynamic      #0:#79        // #0:apply:()Lscala/Function1;
   #81 = Utf8               scala/collection/Iterator
   #82 = Class              #81           // scala/collection/Iterator
   #83 = Utf8               map
   #84 = Utf8               (Lscala/Function1;)Lscala/collection/Iterator;
   #85 = NameAndType        #83:#84       // map:(Lscala/Function1;)Lscala/collection/Iterator;
   #86 = InterfaceMethodref #82.#85       // scala/collection/Iterator.map:(Lscala/Function1;)Lscala/collection/Iterator;
   #87 = Utf8               $anonfun$parse$2$adapted
   #88 = Utf8               (Ljava/lang/String;)Ljava/lang/Object;
   #89 = NameAndType        #87:#88       // $anonfun$parse$2$adapted:(Ljava/lang/String;)Ljava/lang/Object;
   #90 = Methodref          #2.#89        // coursier/credentials/FileCredentials$.$anonfun$parse$2$adapted:(Ljava/lang/String;)Ljava/lang/Object;
   #91 = MethodHandle       6:#90         // REF_invokeStatic coursier/credentials/FileCredentials$.$anonfun$parse$2$adapted:(Ljava/lang/String;)Ljava/lang/Object;
   #92 = MethodType         #88           //  (Ljava/lang/String;)Ljava/lang/Object;
   #93 = InvokeDynamic      #1:#79        // #1:apply:()Lscala/Function1;
   #94 = Utf8               filter
   #95 = NameAndType        #94:#84       // filter:(Lscala/Function1;)Lscala/collection/Iterator;
   #96 = InterfaceMethodref #82.#95       // scala/collection/Iterator.filter:(Lscala/Function1;)Lscala/collection/Iterator;
   #97 = Utf8               toVector
   #98 = Utf8               ()Lscala/collection/immutable/Vector;
   #99 = NameAndType        #97:#98       // toVector:()Lscala/collection/immutable/Vector;
  #100 = InterfaceMethodref #82.#99       // scala/collection/Iterator.toVector:()Lscala/collection/immutable/Vector;
  #101 = Utf8               $anonfun$parse$3
  #102 = Utf8               (Ljava/util/Properties;Ljava/lang/String;Ljava/lang/String;)Lcoursier/credentials/DirectCredentials;
  #103 = NameAndType        #101:#102     // $anonfun$parse$3:(Ljava/util/Properties;Ljava/lang/String;Ljava/lang/String;)Lcoursier/credentials/DirectCredentials;
  #104 = Methodref          #2.#103       // coursier/credentials/FileCredentials$.$anonfun$parse$3:(Ljava/util/Properties;Ljava/lang/String;Ljava/lang/String;)Lcoursier/credentials/DirectCredentials;
  #105 = MethodHandle       6:#104        // REF_invokeStatic coursier/credentials/FileCredentials$.$anonfun$parse$3:(Ljava/util/Properties;Ljava/lang/String;Ljava/lang/String;)Lcoursier/credentials/DirectCredentials;
  #106 = Utf8               (Ljava/lang/String;)Lcoursier/credentials/DirectCredentials;
  #107 = MethodType         #106          //  (Ljava/lang/String;)Lcoursier/credentials/DirectCredentials;
  #108 = Utf8               (Ljava/util/Properties;Ljava/lang/String;)Lscala/Function1;
  #109 = NameAndType        #77:#108      // apply:(Ljava/util/Properties;Ljava/lang/String;)Lscala/Function1;
  #110 = InvokeDynamic      #2:#109       // #2:apply:(Ljava/util/Properties;Ljava/lang/String;)Lscala/Function1;
  #111 = Utf8               scala/collection/immutable/Vector
  #112 = Class              #111          // scala/collection/immutable/Vector
  #113 = Utf8               (Lscala/Function1;)Ljava/lang/Object;
  #114 = NameAndType        #83:#113      // map:(Lscala/Function1;)Ljava/lang/Object;
  #115 = Methodref          #112.#114     // scala/collection/immutable/Vector.map:(Lscala/Function1;)Ljava/lang/Object;
  #116 = Utf8               scala/collection/immutable/Seq
  #117 = Class              #116          // scala/collection/immutable/Seq
  #118 = Utf8               props
  #119 = Utf8               Ljava/util/Properties;
  #120 = Utf8               userProps
  #121 = Utf8               Lscala/collection/immutable/Vector;
  #122 = Utf8               this
  #123 = Utf8               Ljava/lang/String;
  #124 = Utf8               (Ljava/lang/String;)Lcoursier/credentials/FileCredentials;
  #125 = Utf8               path
  #126 = Utf8               coursier/credentials/FileCredentials
  #127 = Class              #126          // coursier/credentials/FileCredentials
  #128 = Utf8               (Ljava/lang/String;Z)V
  #129 = NameAndType        #22:#128      // "<init>":(Ljava/lang/String;Z)V
  #130 = Methodref          #127.#129     // coursier/credentials/FileCredentials."<init>":(Ljava/lang/String;Z)V
  #131 = Utf8               (Ljava/lang/String;Z)Lcoursier/credentials/FileCredentials;
  #132 = Utf8               optional
  #133 = Utf8               Z
  #134 = Utf8               writeReplace
  #135 = Utf8               ()Ljava/lang/Object;
  #136 = Utf8               scala/runtime/ModuleSerializationProxy
  #137 = Class              #136          // scala/runtime/ModuleSerializationProxy
  #138 = Utf8               (Ljava/lang/Class;)V
  #139 = NameAndType        #22:#138      // "<init>":(Ljava/lang/Class;)V
  #140 = Methodref          #137.#139     // scala/runtime/ModuleSerializationProxy."<init>":(Ljava/lang/Class;)V
  #141 = Utf8               x$1
  #142 = Utf8               java/lang/String
  #143 = Class              #142          // java/lang/String
  #144 = Utf8               Ljava/lang/Object;
  #145 = Utf8               $anonfun$parse$2
  #146 = Utf8               (Ljava/lang/String;)Z
  #147 = Utf8               x$2
  #148 = Utf8               .username
  #149 = String             #148          // .username
  #150 = Utf8               endsWith
  #151 = NameAndType        #150:#146     // endsWith:(Ljava/lang/String;)Z
  #152 = Methodref          #143.#151     // java/lang/String.endsWith:(Ljava/lang/String;)Z
  #153 = Utf8               $anonfun$parse$4
  #154 = Utf8               (Ljava/lang/String;Ljava/lang/String;)Lscala/runtime/Nothing$;
  #155 = Utf8               prefix$1
  #156 = Utf8               origin$1
  #157 = Utf8               java/lang/Exception
  #158 = Class              #157          // java/lang/Exception
  #159 = Utf8               java/lang/StringBuilder
  #160 = Class              #159          // java/lang/StringBuilder
  #161 = Integer            32
  #162 = Utf8               (I)V
  #163 = NameAndType        #22:#162      // "<init>":(I)V
  #164 = Methodref          #160.#163     // java/lang/StringBuilder."<init>":(I)V
  #165 = Utf8               Property
  #166 = String             #165          // Property
  #167 = Utf8               append
  #168 = Utf8               (Ljava/lang/String;)Ljava/lang/StringBuilder;
  #169 = NameAndType        #167:#168     // append:(Ljava/lang/String;)Ljava/lang/StringBuilder;
  #170 = Methodref          #160.#169     // java/lang/StringBuilder.append:(Ljava/lang/String;)Ljava/lang/StringBuilder;
  #171 = Utf8               .password not found in
  #172 = String             #171          // .password not found in
  #173 = Utf8               toString
  #174 = Utf8               ()Ljava/lang/String;
  #175 = NameAndType        #173:#174     // toString:()Ljava/lang/String;
  #176 = Methodref          #160.#175     // java/lang/StringBuilder.toString:()Ljava/lang/String;
  #177 = Methodref          #158.#38      // java/lang/Exception."<init>":(Ljava/lang/String;)V
  #178 = Utf8               $anonfun$parse$5
  #179 = Integer            28
  #180 = Utf8               .host not found in
  #181 = String             #180          // .host not found in
  #182 = Utf8               $anonfun$parse$6
  #183 = Utf8               ()Z
  #184 = Utf8               coursier/credentials/DirectCredentials$
  #185 = Class              #184          // coursier/credentials/DirectCredentials$
  #186 = Utf8               Lcoursier/credentials/DirectCredentials$;
  #187 = NameAndType        #18:#186      // MODULE$:Lcoursier/credentials/DirectCredentials$;
  #188 = Fieldref           #185.#187     // coursier/credentials/DirectCredentials$.MODULE$:Lcoursier/credentials/DirectCredentials$;
  #189 = Utf8               defaultMatchHost
  #190 = NameAndType        #189:#183     // defaultMatchHost:()Z
  #191 = Methodref          #185.#190     // coursier/credentials/DirectCredentials$.defaultMatchHost:()Z
  #192 = Utf8               $anonfun$parse$7
  #193 = Utf8               x$3
  #194 = Utf8               scala/collection/StringOps$
  #195 = Class              #194          // scala/collection/StringOps$
  #196 = Utf8               Lscala/collection/StringOps$;
  #197 = NameAndType        #18:#196      // MODULE$:Lscala/collection/StringOps$;
  #198 = Fieldref           #195.#197     // scala/collection/StringOps$.MODULE$:Lscala/collection/StringOps$;
  #199 = Utf8               scala/Predef$
  #200 = Class              #199          // scala/Predef$
  #201 = Utf8               Lscala/Predef$;
  #202 = NameAndType        #18:#201      // MODULE$:Lscala/Predef$;
  #203 = Fieldref           #200.#202     // scala/Predef$.MODULE$:Lscala/Predef$;
  #204 = Utf8               augmentString
  #205 = Utf8               (Ljava/lang/String;)Ljava/lang/String;
  #206 = NameAndType        #204:#205     // augmentString:(Ljava/lang/String;)Ljava/lang/String;
  #207 = Methodref          #200.#206     // scala/Predef$.augmentString:(Ljava/lang/String;)Ljava/lang/String;
  #208 = Utf8               toBoolean$extension
  #209 = NameAndType        #208:#146     // toBoolean$extension:(Ljava/lang/String;)Z
  #210 = Methodref          #195.#209     // scala/collection/StringOps$.toBoolean$extension:(Ljava/lang/String;)Z
  #211 = Utf8               $anonfun$parse$8
  #212 = Utf8               defaultHttpsOnly
  #213 = NameAndType        #212:#183     // defaultHttpsOnly:()Z
  #214 = Methodref          #185.#213     // coursier/credentials/DirectCredentials$.defaultHttpsOnly:()Z
  #215 = Utf8               $anonfun$parse$9
  #216 = Utf8               x$4
  #217 = Utf8               $anonfun$parse$10
  #218 = Utf8               $anonfun$parse$11
  #219 = Utf8               x$5
  #220 = Utf8               props$1
  #221 = Utf8               userProp
  #222 = Utf8               stripSuffix$extension
  #223 = Utf8               (Ljava/lang/String;Ljava/lang/String;)Ljava/lang/String;
  #224 = NameAndType        #222:#223     // stripSuffix$extension:(Ljava/lang/String;Ljava/lang/String;)Ljava/lang/String;
  #225 = Methodref          #195.#224     // scala/collection/StringOps$.stripSuffix$extension:(Ljava/lang/String;Ljava/lang/String;)Ljava/lang/String;
  #226 = Utf8               getProperty
  #227 = NameAndType        #226:#205     // getProperty:(Ljava/lang/String;)Ljava/lang/String;
  #228 = Methodref          #33.#227      // java/util/Properties.getProperty:(Ljava/lang/String;)Ljava/lang/String;
  #229 = Utf8               scala/Option$
  #230 = Class              #229          // scala/Option$
  #231 = Utf8               Lscala/Option$;
  #232 = NameAndType        #18:#231      // MODULE$:Lscala/Option$;
  #233 = Fieldref           #230.#232     // scala/Option$.MODULE$:Lscala/Option$;
  #234 = Integer            9
  #235 = Utf8               .password
  #236 = String             #235          // .password
  #237 = Utf8               (Ljava/lang/Object;)Lscala/Option;
  #238 = NameAndType        #77:#237      // apply:(Ljava/lang/Object;)Lscala/Option;
  #239 = Methodref          #230.#238     // scala/Option$.apply:(Ljava/lang/Object;)Lscala/Option;
  #240 = MethodType         #135          //  ()Ljava/lang/Object;
  #241 = NameAndType        #153:#154     // $anonfun$parse$4:(Ljava/lang/String;Ljava/lang/String;)Lscala/runtime/Nothing$;
  #242 = Methodref          #2.#241       // coursier/credentials/FileCredentials$.$anonfun$parse$4:(Ljava/lang/String;Ljava/lang/String;)Lscala/runtime/Nothing$;
  #243 = MethodHandle       6:#242        // REF_invokeStatic coursier/credentials/FileCredentials$.$anonfun$parse$4:(Ljava/lang/String;Ljava/lang/String;)Lscala/runtime/Nothing$;
  #244 = Utf8               ()Lscala/runtime/Nothing$;
  #245 = MethodType         #244          //  ()Lscala/runtime/Nothing$;
  #246 = Utf8               (Ljava/lang/String;Ljava/lang/String;)Lscala/Function0;
  #247 = NameAndType        #77:#246      // apply:(Ljava/lang/String;Ljava/lang/String;)Lscala/Function0;
  #248 = InvokeDynamic      #3:#247       // #3:apply:(Ljava/lang/String;Ljava/lang/String;)Lscala/Function0;
  #249 = Utf8               scala/Option
  #250 = Class              #249          // scala/Option
  #251 = Utf8               getOrElse
  #252 = Utf8               (Lscala/Function0;)Ljava/lang/Object;
  #253 = NameAndType        #251:#252     // getOrElse:(Lscala/Function0;)Ljava/lang/Object;
  #254 = Methodref          #250.#253     // scala/Option.getOrElse:(Lscala/Function0;)Ljava/lang/Object;
  #255 = Utf8               .host
  #256 = String             #255          // .host
  #257 = NameAndType        #178:#154     // $anonfun$parse$5:(Ljava/lang/String;Ljava/lang/String;)Lscala/runtime/Nothing$;
  #258 = Methodref          #2.#257       // coursier/credentials/FileCredentials$.$anonfun$parse$5:(Ljava/lang/String;Ljava/lang/String;)Lscala/runtime/Nothing$;
  #259 = MethodHandle       6:#258        // REF_invokeStatic coursier/credentials/FileCredentials$.$anonfun$parse$5:(Ljava/lang/String;Ljava/lang/String;)Lscala/runtime/Nothing$;
  #260 = InvokeDynamic      #4:#247       // #4:apply:(Ljava/lang/String;Ljava/lang/String;)Lscala/Function0;
  #261 = Integer            6
  #262 = Utf8               .realm
  #263 = String             #262          // .realm
  #264 = Utf8               .auto
  #265 = String             #264          // .auto
  #266 = MethodType         #183          //  ()Z
  #267 = NameAndType        #182:#183     // $anonfun$parse$6:()Z
  #268 = Methodref          #2.#267       // coursier/credentials/FileCredentials$.$anonfun$parse$6:()Z
  #269 = MethodHandle       6:#268        // REF_invokeStatic coursier/credentials/FileCredentials$.$anonfun$parse$6:()Z
  #270 = Utf8               apply$mcZ$sp
  #271 = Utf8               ()Lscala/runtime/java8/JFunction0$mcZ$sp;
  #272 = NameAndType        #270:#271     // apply$mcZ$sp:()Lscala/runtime/java8/JFunction0$mcZ$sp;
  #273 = InvokeDynamic      #5:#272       // #5:apply$mcZ$sp:()Lscala/runtime/java8/JFunction0$mcZ$sp;
  #274 = Utf8               $anonfun$parse$7$adapted
  #275 = NameAndType        #274:#88      // $anonfun$parse$7$adapted:(Ljava/lang/String;)Ljava/lang/Object;
  #276 = Methodref          #2.#275       // coursier/credentials/FileCredentials$.$anonfun$parse$7$adapted:(Ljava/lang/String;)Ljava/lang/Object;
  #277 = MethodHandle       6:#276        // REF_invokeStatic coursier/credentials/FileCredentials$.$anonfun$parse$7$adapted:(Ljava/lang/String;)Ljava/lang/Object;
  #278 = InvokeDynamic      #6:#79        // #6:apply:()Lscala/Function1;
  #279 = Utf8               fold
  #280 = Utf8               (Lscala/Function0;Lscala/Function1;)Ljava/lang/Object;
  #281 = NameAndType        #279:#280     // fold:(Lscala/Function0;Lscala/Function1;)Ljava/lang/Object;
  #282 = Methodref          #250.#281     // scala/Option.fold:(Lscala/Function0;Lscala/Function1;)Ljava/lang/Object;
  #283 = Utf8               scala/runtime/BoxesRunTime
  #284 = Class              #283          // scala/runtime/BoxesRunTime
  #285 = Utf8               unboxToBoolean
  #286 = Utf8               (Ljava/lang/Object;)Z
  #287 = NameAndType        #285:#286     // unboxToBoolean:(Ljava/lang/Object;)Z
  #288 = Methodref          #284.#287     // scala/runtime/BoxesRunTime.unboxToBoolean:(Ljava/lang/Object;)Z
  #289 = Integer            11
  #290 = Utf8               .https-only
  #291 = String             #290          // .https-only
  #292 = NameAndType        #211:#183     // $anonfun$parse$8:()Z
  #293 = Methodref          #2.#292       // coursier/credentials/FileCredentials$.$anonfun$parse$8:()Z
  #294 = MethodHandle       6:#293        // REF_invokeStatic coursier/credentials/FileCredentials$.$anonfun$parse$8:()Z
  #295 = InvokeDynamic      #7:#272       // #7:apply$mcZ$sp:()Lscala/runtime/java8/JFunction0$mcZ$sp;
  #296 = Utf8               $anonfun$parse$9$adapted
  #297 = NameAndType        #296:#88      // $anonfun$parse$9$adapted:(Ljava/lang/String;)Ljava/lang/Object;
  #298 = Methodref          #2.#297       // coursier/credentials/FileCredentials$.$anonfun$parse$9$adapted:(Ljava/lang/String;)Ljava/lang/Object;
  #299 = MethodHandle       6:#298        // REF_invokeStatic coursier/credentials/FileCredentials$.$anonfun$parse$9$adapted:(Ljava/lang/String;)Ljava/lang/Object;
  #300 = InvokeDynamic      #8:#79        // #8:apply:()Lscala/Function1;
  #301 = Integer            17
  #302 = Utf8               .pass-on-redirect
  #303 = String             #302          // .pass-on-redirect
  #304 = NameAndType        #217:#183     // $anonfun$parse$10:()Z
  #305 = Methodref          #2.#304       // coursier/credentials/FileCredentials$.$anonfun$parse$10:()Z
  #306 = MethodHandle       6:#305        // REF_invokeStatic coursier/credentials/FileCredentials$.$anonfun$parse$10:()Z
  #307 = InvokeDynamic      #9:#272       // #9:apply$mcZ$sp:()Lscala/runtime/java8/JFunction0$mcZ$sp;
  #308 = Utf8               $anonfun$parse$11$adapted
  #309 = NameAndType        #308:#88      // $anonfun$parse$11$adapted:(Ljava/lang/String;)Ljava/lang/Object;
  #310 = Methodref          #2.#309       // coursier/credentials/FileCredentials$.$anonfun$parse$11$adapted:(Ljava/lang/String;)Ljava/lang/Object;
  #311 = MethodHandle       6:#310        // REF_invokeStatic coursier/credentials/FileCredentials$.$anonfun$parse$11$adapted:(Ljava/lang/String;)Ljava/lang/Object;
  #312 = InvokeDynamic      #10:#79       // #10:apply:()Lscala/Function1;
  #313 = Utf8               (Ljava/lang/String;Ljava/lang/String;Ljava/lang/String;)Lcoursier/credentials/DirectCredentials;
  #314 = NameAndType        #77:#313      // apply:(Ljava/lang/String;Ljava/lang/String;Ljava/lang/String;)Lcoursier/credentials/DirectCredentials;
  #315 = Methodref          #185.#314     // coursier/credentials/DirectCredentials$.apply:(Ljava/lang/String;Ljava/lang/String;Ljava/lang/String;)Lcoursier/credentials/DirectCredentials;
  #316 = Utf8               coursier/credentials/DirectCredentials
  #317 = Class              #316          // coursier/credentials/DirectCredentials
  #318 = Utf8               withRealm
  #319 = Utf8               (Lscala/Option;)Lcoursier/credentials/DirectCredentials;
  #320 = NameAndType        #318:#319     // withRealm:(Lscala/Option;)Lcoursier/credentials/DirectCredentials;
  #321 = Methodref          #317.#320     // coursier/credentials/DirectCredentials.withRealm:(Lscala/Option;)Lcoursier/credentials/DirectCredentials;
  #322 = Utf8               withMatchHost
  #323 = Utf8               (Z)Lcoursier/credentials/DirectCredentials;
  #324 = NameAndType        #322:#323     // withMatchHost:(Z)Lcoursier/credentials/DirectCredentials;
  #325 = Methodref          #317.#324     // coursier/credentials/DirectCredentials.withMatchHost:(Z)Lcoursier/credentials/DirectCredentials;
  #326 = Utf8               withHttpsOnly
  #327 = NameAndType        #326:#323     // withHttpsOnly:(Z)Lcoursier/credentials/DirectCredentials;
  #328 = Methodref          #317.#327     // coursier/credentials/DirectCredentials.withHttpsOnly:(Z)Lcoursier/credentials/DirectCredentials;
  #329 = Utf8               withPassOnRedirect
  #330 = NameAndType        #329:#323     // withPassOnRedirect:(Z)Lcoursier/credentials/DirectCredentials;
  #331 = Methodref          #317.#330     // coursier/credentials/DirectCredentials.withPassOnRedirect:(Z)Lcoursier/credentials/DirectCredentials;
  #332 = Utf8               prefix
  #333 = Utf8               user
  #334 = Utf8               password
  #335 = Utf8               host
  #336 = Utf8               realmOpt
  #337 = Utf8               Lscala/Option;
  #338 = Utf8               matchHost
  #339 = Utf8               httpsOnly
  #340 = Utf8               passOnRedirect
  #341 = Methodref          #4.#23        // java/lang/Object."<init>":()V
  #342 = NameAndType        #145:#146     // $anonfun$parse$2:(Ljava/lang/String;)Z
  #343 = Methodref          #2.#342       // coursier/credentials/FileCredentials$.$anonfun$parse$2:(Ljava/lang/String;)Z
  #344 = Utf8               boxToBoolean
  #345 = Utf8               (Z)Ljava/lang/Boolean;
  #346 = NameAndType        #344:#345     // boxToBoolean:(Z)Ljava/lang/Boolean;
  #347 = Methodref          #284.#346     // scala/runtime/BoxesRunTime.boxToBoolean:(Z)Ljava/lang/Boolean;
  #348 = NameAndType        #192:#146     // $anonfun$parse$7:(Ljava/lang/String;)Z
  #349 = Methodref          #2.#348       // coursier/credentials/FileCredentials$.$anonfun$parse$7:(Ljava/lang/String;)Z
  #350 = NameAndType        #215:#146     // $anonfun$parse$9:(Ljava/lang/String;)Z
  #351 = Methodref          #2.#350       // coursier/credentials/FileCredentials$.$anonfun$parse$9:(Ljava/lang/String;)Z
  #352 = NameAndType        #218:#146     // $anonfun$parse$11:(Ljava/lang/String;)Z
  #353 = Methodref          #2.#352       // coursier/credentials/FileCredentials$.$anonfun$parse$11:(Ljava/lang/String;)Z
  #354 = Utf8               $deserializeLambda$
  #355 = Utf8               (Ljava/lang/invoke/SerializedLambda;)Ljava/lang/Object;
  #356 = Utf8               scala/runtime/LambdaDeserialize
  #357 = Class              #356          // scala/runtime/LambdaDeserialize
  #358 = Utf8               bootstrap
  #359 = Utf8               (Ljava/lang/invoke/MethodHandles$Lookup;Ljava/lang/String;Ljava/lang/invoke/MethodType;[Ljava/lang/invoke/MethodHandle;)Ljava/lang/invoke/CallSite;
  #360 = NameAndType        #358:#359     // bootstrap:(Ljava/lang/invoke/MethodHandles$Lookup;Ljava/lang/String;Ljava/lang/invoke/MethodType;[Ljava/lang/invoke/MethodHandle;)Ljava/lang/invoke/CallSite;
  #361 = Methodref          #357.#360     // scala/runtime/LambdaDeserialize.bootstrap:(Ljava/lang/invoke/MethodHandles$Lookup;Ljava/lang/String;Ljava/lang/invoke/MethodType;[Ljava/lang/invoke/MethodHandle;)Ljava/lang/invoke/CallSite;
  #362 = MethodHandle       6:#361        // REF_invokeStatic scala/runtime/LambdaDeserialize.bootstrap:(Ljava/lang/invoke/MethodHandles$Lookup;Ljava/lang/String;Ljava/lang/invoke/MethodType;[Ljava/lang/invoke/MethodHandle;)Ljava/lang/invoke/CallSite;
  #363 = Utf8               lambdaDeserialize
  #364 = NameAndType        #363:#355     // lambdaDeserialize:(Ljava/lang/invoke/SerializedLambda;)Ljava/lang/Object;
  #365 = InvokeDynamic      #11:#364      // #11:lambdaDeserialize:(Ljava/lang/invoke/SerializedLambda;)Ljava/lang/Object;
  #366 = Utf8               Code
  #367 = Utf8               LineNumberTable
  #368 = Utf8               LocalVariableTable
  #369 = Utf8               Signature
  #370 = Utf8               MethodParameters
  #371 = Utf8               InnerClasses
  #372 = Utf8               SourceFile
  #373 = Utf8               BootstrapMethods
  #374 = Utf8               ScalaInlineInfo
  #375 = Utf8               Scala
{
  public static final coursier.credentials.FileCredentials$ MODULE$;
    descriptor: Lcoursier/credentials/FileCredentials$;
    flags: (0x0019) ACC_PUBLIC, ACC_STATIC, ACC_FINAL

  public static {};
    descriptor: ()V
    flags: (0x0009) ACC_PUBLIC, ACC_STATIC
    Code:
      stack=2, locals=0, args_size=0
         0: new           #2                  // class coursier/credentials/FileCredentials$
         3: dup
         4: invokespecial #24                 // Method "<init>":()V
         7: putstatic     #26                 // Field MODULE$:Lcoursier/credentials/FileCredentials$;
        10: return
      LineNumberTable:
        line 12: 0

  public scala.collection.immutable.Seq<coursier.credentials.DirectCredentials> parse(java.lang.String, java.lang.String);
    descriptor: (Ljava/lang/String;Ljava/lang/String;)Lscala/collection/immutable/Seq;
    flags: (0x0001) ACC_PUBLIC
    Code:
      stack=4, locals=5, args_size=3
         0: new           #33                 // class java/util/Properties
         3: dup
         4: invokespecial #34                 // Method java/util/Properties."<init>":()V
         7: astore_3
         8: aload_3
         9: new           #36                 // class java/io/StringReader
        12: dup
        13: aload_1
        14: invokespecial #39                 // Method java/io/StringReader."<init>":(Ljava/lang/String;)V
        17: invokevirtual #43                 // Method java/util/Properties.load:(Ljava/io/Reader;)V
        20: getstatic     #48                 // Field scala/jdk/CollectionConverters$.MODULE$:Lscala/jdk/CollectionConverters$;
        23: aload_3
        24: invokevirtual #52                 // Method java/util/Properties.propertyNames:()Ljava/util/Enumeration;
        27: invokevirtual #55                 // Method scala/jdk/CollectionConverters$.EnumerationHasAsScala:(Ljava/util/Enumeration;)Lscala/collection/convert/AsScalaExtensions$EnumerationHasAsScala;
        30: invokevirtual #59                 // Method scala/collection/convert/AsScalaExtensions$EnumerationHasAsScala.asScala:()Lscala/collection/Iterator;
        33: invokedynamic #80,  0             // InvokeDynamic #0:apply:()Lscala/Function1;
        38: invokeinterface #86,  2           // InterfaceMethod scala/collection/Iterator.map:(Lscala/Function1;)Lscala/collection/Iterator;
        43: invokedynamic #93,  0             // InvokeDynamic #1:apply:()Lscala/Function1;
        48: invokeinterface #96,  2           // InterfaceMethod scala/collection/Iterator.filter:(Lscala/Function1;)Lscala/collection/Iterator;
        53: invokeinterface #100,  1          // InterfaceMethod scala/collection/Iterator.toVector:()Lscala/collection/immutable/Vector;
        58: astore        4
        60: aload         4
        62: aload_3
        63: aload_2
        64: invokedynamic #110,  0            // InvokeDynamic #2:apply:(Ljava/util/Properties;Ljava/lang/String;)Lscala/Function1;
        69: invokevirtual #115                // Method scala/collection/immutable/Vector.map:(Lscala/Function1;)Ljava/lang/Object;
        72: checkcast     #117                // class scala/collection/immutable/Seq
        75: areturn
      LineNumberTable:
        line 35: 0
        line 36: 8
        line 39: 20
        line 38: 23
        line 41: 33
        line 42: 43
        line 45: 60
      LocalVariableTable:
        Start  Length  Slot  Name   Signature
            8      67     3 props   Ljava/util/Properties;
           60      15     4 userProps   Lscala/collection/immutable/Vector;
            0      76     0  this   Lcoursier/credentials/FileCredentials$;
            0      76     1 content   Ljava/lang/String;
            0      76     2 origin   Ljava/lang/String;
    Signature: #29                          // (Ljava/lang/String;Ljava/lang/String;)Lscala/collection/immutable/Seq<Lcoursier/credentials/DirectCredentials;>;
    MethodParameters:
      Name                           Flags
      content                        final
      origin                         final

  public coursier.credentials.FileCredentials apply(java.lang.String);
    descriptor: (Ljava/lang/String;)Lcoursier/credentials/FileCredentials;
    flags: (0x0001) ACC_PUBLIC
    Code:
      stack=4, locals=2, args_size=2
         0: new           #127                // class coursier/credentials/FileCredentials
         3: dup
         4: aload_1
         5: iconst_1
         6: invokespecial #130                // Method coursier/credentials/FileCredentials."<init>":(Ljava/lang/String;Z)V
         9: areturn
      LineNumberTable:
        line 12: 0
        line 14: 5
      LocalVariableTable:
        Start  Length  Slot  Name   Signature
            0      10     0  this   Lcoursier/credentials/FileCredentials$;
            0      10     1  path   Ljava/lang/String;
    MethodParameters:
      Name                           Flags
      path                           final

  public coursier.credentials.FileCredentials apply(java.lang.String, boolean);
    descriptor: (Ljava/lang/String;Z)Lcoursier/credentials/FileCredentials;
    flags: (0x0001) ACC_PUBLIC
    Code:
      stack=4, locals=3, args_size=3
         0: new           #127                // class coursier/credentials/FileCredentials
         3: dup
         4: aload_1
         5: iload_2
         6: invokespecial #130                // Method coursier/credentials/FileCredentials."<init>":(Ljava/lang/String;Z)V
         9: areturn
      LineNumberTable:
        line 12: 0
      LocalVariableTable:
        Start  Length  Slot  Name   Signature
            0      10     0  this   Lcoursier/credentials/FileCredentials$;
            0      10     1  path   Ljava/lang/String;
            0      10     2 optional   Z
    MethodParameters:
      Name                           Flags
      path                           final
      optional                       final

  private java.lang.Object writeReplace();
    descriptor: ()Ljava/lang/Object;
    flags: (0x0002) ACC_PRIVATE
    Code:
      stack=3, locals=1, args_size=1
         0: new           #137                // class scala/runtime/ModuleSerializationProxy
         3: dup
         4: ldc           #2                  // class coursier/credentials/FileCredentials$
         6: invokespecial #140                // Method scala/runtime/ModuleSerializationProxy."<init>":(Ljava/lang/Class;)V
         9: areturn
      LineNumberTable:
        line 12: 0
      LocalVariableTable:
        Start  Length  Slot  Name   Signature
            0      10     0  this   Lcoursier/credentials/FileCredentials$;

  public static final java.lang.String $anonfun$parse$1(java.lang.Object);
    descriptor: (Ljava/lang/Object;)Ljava/lang/String;
    flags: (0x1019) ACC_PUBLIC, ACC_STATIC, ACC_FINAL, ACC_SYNTHETIC
    Code:
      stack=1, locals=1, args_size=1
         0: aload_0
         1: checkcast     #143                // class java/lang/String
         4: areturn
      LineNumberTable:
        line 41: 0
      LocalVariableTable:
        Start  Length  Slot  Name   Signature
            0       5     0   x$1   Ljava/lang/Object;
    MethodParameters:
      Name                           Flags
      x$1                            final

  public static final boolean $anonfun$parse$2(java.lang.String);
    descriptor: (Ljava/lang/String;)Z
    flags: (0x1019) ACC_PUBLIC, ACC_STATIC, ACC_FINAL, ACC_SYNTHETIC
    Code:
      stack=2, locals=1, args_size=1
         0: aload_0
         1: ldc           #149                // String .username
         3: invokevirtual #152                // Method java/lang/String.endsWith:(Ljava/lang/String;)Z
         6: ireturn
      LineNumberTable:
        line 42: 0
      LocalVariableTable:
        Start  Length  Slot  Name   Signature
            0       7     0   x$2   Ljava/lang/String;
    MethodParameters:
      Name                           Flags
      x$2                            final

  public static final scala.runtime.Nothing$ $anonfun$parse$4(java.lang.String, java.lang.String);
    descriptor: (Ljava/lang/String;Ljava/lang/String;)Lscala/runtime/Nothing$;
    flags: (0x1019) ACC_PUBLIC, ACC_STATIC, ACC_FINAL, ACC_SYNTHETIC
    Code:
      stack=5, locals=2, args_size=2
         0: new           #158                // class java/lang/Exception
         3: dup
         4: new           #160                // class java/lang/StringBuilder
         7: dup
         8: ldc           #161                // int 32
        10: invokespecial #164                // Method java/lang/StringBuilder."<init>":(I)V
        13: ldc           #166                // String Property
        15: invokevirtual #170                // Method java/lang/StringBuilder.append:(Ljava/lang/String;)Ljava/lang/StringBuilder;
        18: aload_0
        19: invokevirtual #170                // Method java/lang/StringBuilder.append:(Ljava/lang/String;)Ljava/lang/StringBuilder;
        22: ldc           #172                // String .password not found in
        24: invokevirtual #170                // Method java/lang/StringBuilder.append:(Ljava/lang/String;)Ljava/lang/StringBuilder;
        27: aload_1
        28: invokevirtual #170                // Method java/lang/StringBuilder.append:(Ljava/lang/String;)Ljava/lang/StringBuilder;
        31: invokevirtual #176                // Method java/lang/StringBuilder.toString:()Ljava/lang/String;
        34: invokespecial #177                // Method java/lang/Exception."<init>":(Ljava/lang/String;)V
        37: athrow
      LineNumberTable:
        line 50: 0
      LocalVariableTable:
        Start  Length  Slot  Name   Signature
            0      38     0 prefix$1   Ljava/lang/String;
            0      38     1 origin$1   Ljava/lang/String;
    MethodParameters:
      Name                           Flags
      prefix$1                       final
      origin$1                       final

  public static final scala.runtime.Nothing$ $anonfun$parse$5(java.lang.String, java.lang.String);
    descriptor: (Ljava/lang/String;Ljava/lang/String;)Lscala/runtime/Nothing$;
    flags: (0x1019) ACC_PUBLIC, ACC_STATIC, ACC_FINAL, ACC_SYNTHETIC
    Code:
      stack=5, locals=2, args_size=2
         0: new           #158                // class java/lang/Exception
         3: dup
         4: new           #160                // class java/lang/StringBuilder
         7: dup
         8: ldc           #179                // int 28
        10: invokespecial #164                // Method java/lang/StringBuilder."<init>":(I)V
        13: ldc           #166                // String Property
        15: invokevirtual #170                // Method java/lang/StringBuilder.append:(Ljava/lang/String;)Ljava/lang/StringBuilder;
        18: aload_0
        19: invokevirtual #170                // Method java/lang/StringBuilder.append:(Ljava/lang/String;)Ljava/lang/StringBuilder;
        22: ldc           #181                // String .host not found in
        24: invokevirtual #170                // Method java/lang/StringBuilder.append:(Ljava/lang/String;)Ljava/lang/StringBuilder;
        27: aload_1
        28: invokevirtual #170                // Method java/lang/StringBuilder.append:(Ljava/lang/String;)Ljava/lang/StringBuilder;
        31: invokevirtual #176                // Method java/lang/StringBuilder.toString:()Ljava/lang/String;
        34: invokespecial #177                // Method java/lang/Exception."<init>":(Ljava/lang/String;)V
        37: athrow
      LineNumberTable:
        line 54: 0
      LocalVariableTable:
        Start  Length  Slot  Name   Signature
            0      38     0 prefix$1   Ljava/lang/String;
            0      38     1 origin$1   Ljava/lang/String;
    MethodParameters:
      Name                           Flags
      prefix$1                       final
      origin$1                       final

  public static final boolean $anonfun$parse$6();
    descriptor: ()Z
    flags: (0x1019) ACC_PUBLIC, ACC_STATIC, ACC_FINAL, ACC_SYNTHETIC
    Code:
      stack=1, locals=0, args_size=0
         0: getstatic     #188                // Field coursier/credentials/DirectCredentials$.MODULE$:Lcoursier/credentials/DirectCredentials$;
         3: invokevirtual #191                // Method coursier/credentials/DirectCredentials$.defaultMatchHost:()Z
         6: ireturn
      LineNumberTable:
        line 59: 0

  public static final boolean $anonfun$parse$7(java.lang.String);
    descriptor: (Ljava/lang/String;)Z
    flags: (0x1019) ACC_PUBLIC, ACC_STATIC, ACC_FINAL, ACC_SYNTHETIC
    Code:
      stack=3, locals=1, args_size=1
         0: getstatic     #198                // Field scala/collection/StringOps$.MODULE$:Lscala/collection/StringOps$;
         3: getstatic     #203                // Field scala/Predef$.MODULE$:Lscala/Predef$;
         6: aload_0
         7: invokevirtual #207                // Method scala/Predef$.augmentString:(Ljava/lang/String;)Ljava/lang/String;
        10: invokevirtual #210                // Method scala/collection/StringOps$.toBoolean$extension:(Ljava/lang/String;)Z
        13: ireturn
      LineNumberTable:
        line 59: 3
      LocalVariableTable:
        Start  Length  Slot  Name   Signature
            0      14     0   x$3   Ljava/lang/String;
    MethodParameters:
      Name                           Flags
      x$3                            final

  public static final boolean $anonfun$parse$8();
    descriptor: ()Z
    flags: (0x1019) ACC_PUBLIC, ACC_STATIC, ACC_FINAL, ACC_SYNTHETIC
    Code:
      stack=1, locals=0, args_size=0
         0: getstatic     #188                // Field coursier/credentials/DirectCredentials$.MODULE$:Lcoursier/credentials/DirectCredentials$;
         3: invokevirtual #214                // Method coursier/credentials/DirectCredentials$.defaultHttpsOnly:()Z
         6: ireturn
      LineNumberTable:
        line 60: 0

  public static final boolean $anonfun$parse$9(java.lang.String);
    descriptor: (Ljava/lang/String;)Z
    flags: (0x1019) ACC_PUBLIC, ACC_STATIC, ACC_FINAL, ACC_SYNTHETIC
    Code:
      stack=3, locals=1, args_size=1
         0: getstatic     #198                // Field scala/collection/StringOps$.MODULE$:Lscala/collection/StringOps$;
         3: getstatic     #203                // Field scala/Predef$.MODULE$:Lscala/Predef$;
         6: aload_0
         7: invokevirtual #207                // Method scala/Predef$.augmentString:(Ljava/lang/String;)Ljava/lang/String;
        10: invokevirtual #210                // Method scala/collection/StringOps$.toBoolean$extension:(Ljava/lang/String;)Z
        13: ireturn
      LineNumberTable:
        line 60: 3
      LocalVariableTable:
        Start  Length  Slot  Name   Signature
            0      14     0   x$4   Ljava/lang/String;
    MethodParameters:
      Name                           Flags
      x$4                            final

  public static final boolean $anonfun$parse$10();
    descriptor: ()Z
    flags: (0x1019) ACC_PUBLIC, ACC_STATIC, ACC_FINAL, ACC_SYNTHETIC
    Code:
      stack=1, locals=0, args_size=0
         0: iconst_0
         1: ireturn
      LineNumberTable:
        line 61: 0

  public static final boolean $anonfun$parse$11(java.lang.String);
    descriptor: (Ljava/lang/String;)Z
    flags: (0x1019) ACC_PUBLIC, ACC_STATIC, ACC_FINAL, ACC_SYNTHETIC
    Code:
      stack=3, locals=1, args_size=1
         0: getstatic     #198                // Field scala/collection/StringOps$.MODULE$:Lscala/collection/StringOps$;
         3: getstatic     #203                // Field scala/Predef$.MODULE$:Lscala/Predef$;
         6: aload_0
         7: invokevirtual #207                // Method scala/Predef$.augmentString:(Ljava/lang/String;)Ljava/lang/String;
        10: invokevirtual #210                // Method scala/collection/StringOps$.toBoolean$extension:(Ljava/lang/String;)Z
        13: ireturn
      LineNumberTable:
        line 61: 3
      LocalVariableTable:
        Start  Length  Slot  Name   Signature
            0      14     0   x$5   Ljava/lang/String;
    MethodParameters:
      Name                           Flags
      x$5                            final

  public static final coursier.credentials.DirectCredentials $anonfun$parse$3(java.util.Properties, java.lang.String, java.lang.String);
    descriptor: (Ljava/util/Properties;Ljava/lang/String;Ljava/lang/String;)Lcoursier/credentials/DirectCredentials;
    flags: (0x1019) ACC_PUBLIC, ACC_STATIC, ACC_FINAL, ACC_SYNTHETIC
    Code:
      stack=5, locals=11, args_size=3
         0: getstatic     #198                // Field scala/collection/StringOps$.MODULE$:Lscala/collection/StringOps$;
         3: getstatic     #203                // Field scala/Predef$.MODULE$:Lscala/Predef$;
         6: aload_2
         7: invokevirtual #207                // Method scala/Predef$.augmentString:(Ljava/lang/String;)Ljava/lang/String;
        10: ldc           #149                // String .username
        12: invokevirtual #225                // Method scala/collection/StringOps$.stripSuffix$extension:(Ljava/lang/String;Ljava/lang/String;)Ljava/lang/String;
        15: astore_3
        16: aload_0
        17: aload_2
        18: invokevirtual #228                // Method java/util/Properties.getProperty:(Ljava/lang/String;)Ljava/lang/String;
        21: astore        4
        23: getstatic     #233                // Field scala/Option$.MODULE$:Lscala/Option$;
        26: aload_0
        27: new           #160                // class java/lang/StringBuilder
        30: dup
        31: ldc           #234                // int 9
        33: invokespecial #164                // Method java/lang/StringBuilder."<init>":(I)V
        36: aload_3
        37: invokevirtual #170                // Method java/lang/StringBuilder.append:(Ljava/lang/String;)Ljava/lang/StringBuilder;
        40: ldc           #236                // String .password
        42: invokevirtual #170                // Method java/lang/StringBuilder.append:(Ljava/lang/String;)Ljava/lang/StringBuilder;
        45: invokevirtual #176                // Method java/lang/StringBuilder.toString:()Ljava/lang/String;
        48: invokevirtual #228                // Method java/util/Properties.getProperty:(Ljava/lang/String;)Ljava/lang/String;
        51: invokevirtual #239                // Method scala/Option$.apply:(Ljava/lang/Object;)Lscala/Option;
        54: aload_3
        55: aload_1
        56: invokedynamic #248,  0            // InvokeDynamic #3:apply:(Ljava/lang/String;Ljava/lang/String;)Lscala/Function0;
        61: invokevirtual #254                // Method scala/Option.getOrElse:(Lscala/Function0;)Ljava/lang/Object;
        64: checkcast     #143                // class java/lang/String
        67: astore        5
        69: getstatic     #233                // Field scala/Option$.MODULE$:Lscala/Option$;
        72: aload_0
        73: new           #160                // class java/lang/StringBuilder
        76: dup
        77: ldc           #68                 // int 5
        79: invokespecial #164                // Method java/lang/StringBuilder."<init>":(I)V
        82: aload_3
        83: invokevirtual #170                // Method java/lang/StringBuilder.append:(Ljava/lang/String;)Ljava/lang/StringBuilder;
        86: ldc_w         #256                // String .host
        89: invokevirtual #170                // Method java/lang/StringBuilder.append:(Ljava/lang/String;)Ljava/lang/StringBuilder;
        92: invokevirtual #176                // Method java/lang/StringBuilder.toString:()Ljava/lang/String;
        95: invokevirtual #228                // Method java/util/Properties.getProperty:(Ljava/lang/String;)Ljava/lang/String;
        98: invokevirtual #239                // Method scala/Option$.apply:(Ljava/lang/Object;)Lscala/Option;
       101: aload_3
       102: aload_1
       103: invokedynamic #260,  0            // InvokeDynamic #4:apply:(Ljava/lang/String;Ljava/lang/String;)Lscala/Function0;
       108: invokevirtual #254                // Method scala/Option.getOrElse:(Lscala/Function0;)Ljava/lang/Object;
       111: checkcast     #143                // class java/lang/String
       114: astore        6
       116: getstatic     #233                // Field scala/Option$.MODULE$:Lscala/Option$;
       119: aload_0
       120: new           #160                // class java/lang/StringBuilder
       123: dup
       124: ldc_w         #261                // int 6
       127: invokespecial #164                // Method java/lang/StringBuilder."<init>":(I)V
       130: aload_3
       131: invokevirtual #170                // Method java/lang/StringBuilder.append:(Ljava/lang/String;)Ljava/lang/StringBuilder;
       134: ldc_w         #263                // String .realm
       137: invokevirtual #170                // Method java/lang/StringBuilder.append:(Ljava/lang/String;)Ljava/lang/StringBuilder;
       140: invokevirtual #176                // Method java/lang/StringBuilder.toString:()Ljava/lang/String;
       143: invokevirtual #228                // Method java/util/Properties.getProperty:(Ljava/lang/String;)Ljava/lang/String;
       146: invokevirtual #239                // Method scala/Option$.apply:(Ljava/lang/Object;)Lscala/Option;
       149: astore        7
       151: getstatic     #233                // Field scala/Option$.MODULE$:Lscala/Option$;
       154: aload_0
       155: new           #160                // class java/lang/StringBuilder
       158: dup
       159: ldc           #68                 // int 5
       161: invokespecial #164                // Method java/lang/StringBuilder."<init>":(I)V
       164: aload_3
       165: invokevirtual #170                // Method java/lang/StringBuilder.append:(Ljava/lang/String;)Ljava/lang/StringBuilder;
       168: ldc_w         #265                // String .auto
       171: invokevirtual #170                // Method java/lang/StringBuilder.append:(Ljava/lang/String;)Ljava/lang/StringBuilder;
       174: invokevirtual #176                // Method java/lang/StringBuilder.toString:()Ljava/lang/String;
       177: invokevirtual #228                // Method java/util/Properties.getProperty:(Ljava/lang/String;)Ljava/lang/String;
       180: invokevirtual #239                // Method scala/Option$.apply:(Ljava/lang/Object;)Lscala/Option;
       183: invokedynamic #273,  0            // InvokeDynamic #5:apply$mcZ$sp:()Lscala/runtime/java8/JFunction0$mcZ$sp;
       188: invokedynamic #278,  0            // InvokeDynamic #6:apply:()Lscala/Function1;
       193: invokevirtual #282                // Method scala/Option.fold:(Lscala/Function0;Lscala/Function1;)Ljava/lang/Object;
       196: invokestatic  #288                // Method scala/runtime/BoxesRunTime.unboxToBoolean:(Ljava/lang/Object;)Z
       199: istore        8
       201: getstatic     #233                // Field scala/Option$.MODULE$:Lscala/Option$;
       204: aload_0
       205: new           #160                // class java/lang/StringBuilder
       208: dup
       209: ldc_w         #289                // int 11
       212: invokespecial #164                // Method java/lang/StringBuilder."<init>":(I)V
       215: aload_3
       216: invokevirtual #170                // Method java/lang/StringBuilder.append:(Ljava/lang/String;)Ljava/lang/StringBuilder;
       219: ldc_w         #291                // String .https-only
       222: invokevirtual #170                // Method java/lang/StringBuilder.append:(Ljava/lang/String;)Ljava/lang/StringBuilder;
       225: invokevirtual #176                // Method java/lang/StringBuilder.toString:()Ljava/lang/String;
       228: invokevirtual #228                // Method java/util/Properties.getProperty:(Ljava/lang/String;)Ljava/lang/String;
       231: invokevirtual #239                // Method scala/Option$.apply:(Ljava/lang/Object;)Lscala/Option;
       234: invokedynamic #295,  0            // InvokeDynamic #7:apply$mcZ$sp:()Lscala/runtime/java8/JFunction0$mcZ$sp;
       239: invokedynamic #300,  0            // InvokeDynamic #8:apply:()Lscala/Function1;
       244: invokevirtual #282                // Method scala/Option.fold:(Lscala/Function0;Lscala/Function1;)Ljava/lang/Object;
       247: invokestatic  #288                // Method scala/runtime/BoxesRunTime.unboxToBoolean:(Ljava/lang/Object;)Z
       250: istore        9
       252: getstatic     #233                // Field scala/Option$.MODULE$:Lscala/Option$;
       255: aload_0
       256: new           #160                // class java/lang/StringBuilder
       259: dup
       260: ldc_w         #301                // int 17
       263: invokespecial #164                // Method java/lang/StringBuilder."<init>":(I)V
       266: aload_3
       267: invokevirtual #170                // Method java/lang/StringBuilder.append:(Ljava/lang/String;)Ljava/lang/StringBuilder;
       270: ldc_w         #303                // String .pass-on-redirect
       273: invokevirtual #170                // Method java/lang/StringBuilder.append:(Ljava/lang/String;)Ljava/lang/StringBuilder;
       276: invokevirtual #176                // Method java/lang/StringBuilder.toString:()Ljava/lang/String;
       279: invokevirtual #228                // Method java/util/Properties.getProperty:(Ljava/lang/String;)Ljava/lang/String;
       282: invokevirtual #239                // Method scala/Option$.apply:(Ljava/lang/Object;)Lscala/Option;
       285: invokedynamic #307,  0            // InvokeDynamic #9:apply$mcZ$sp:()Lscala/runtime/java8/JFunction0$mcZ$sp;
       290: invokedynamic #312,  0            // InvokeDynamic #10:apply:()Lscala/Function1;
       295: invokevirtual #282                // Method scala/Option.fold:(Lscala/Function0;Lscala/Function1;)Ljava/lang/Object;
       298: invokestatic  #288                // Method scala/runtime/BoxesRunTime.unboxToBoolean:(Ljava/lang/Object;)Z
       301: istore        10
       303: getstatic     #188                // Field coursier/credentials/DirectCredentials$.MODULE$:Lcoursier/credentials/DirectCredentials$;
       306: aload         6
       308: aload         4
       310: aload         5
       312: invokevirtual #315                // Method coursier/credentials/DirectCredentials$.apply:(Ljava/lang/String;Ljava/lang/String;Ljava/lang/String;)Lcoursier/credentials/DirectCredentials;
       315: aload         7
       317: invokevirtual #321                // Method coursier/credentials/DirectCredentials.withRealm:(Lscala/Option;)Lcoursier/credentials/DirectCredentials;
       320: iload         8
       322: invokevirtual #325                // Method coursier/credentials/DirectCredentials.withMatchHost:(Z)Lcoursier/credentials/DirectCredentials;
       325: iload         9
       327: invokevirtual #328                // Method coursier/credentials/DirectCredentials.withHttpsOnly:(Z)Lcoursier/credentials/DirectCredentials;
       330: iload         10
       332: invokevirtual #331                // Method coursier/credentials/DirectCredentials.withPassOnRedirect:(Z)Lcoursier/credentials/DirectCredentials;
       335: areturn
      LineNumberTable:
        line 46: 0
        line 48: 16
        line 49: 23
        line 50: 54
        line 53: 69
        line 54: 101
        line 57: 116
        line 59: 151
        line 60: 201
        line 61: 252
        line 63: 303
        line 64: 315
        line 65: 320
        line 66: 325
        line 67: 330
      LocalVariableTable:
        Start  Length  Slot  Name   Signature
           16     319     3 prefix   Ljava/lang/String;
           23     312     4  user   Ljava/lang/String;
           69     266     5 password   Ljava/lang/String;
          116     219     6  host   Ljava/lang/String;
          151     184     7 realmOpt   Lscala/Option;
          201     134     8 matchHost   Z
          252      83     9 httpsOnly   Z
          303      32    10 passOnRedirect   Z
            0     336     0 props$1   Ljava/util/Properties;
            0     336     1 origin$1   Ljava/lang/String;
            0     336     2 userProp   Ljava/lang/String;
    MethodParameters:
      Name                           Flags
      props$1                        final
      origin$1                       final
      userProp                       final

  private coursier.credentials.FileCredentials$();
    descriptor: ()V
    flags: (0x0002) ACC_PRIVATE
    Code:
      stack=1, locals=1, args_size=1
         0: aload_0
         1: invokespecial #341                // Method java/lang/Object."<init>":()V
         4: return
      LineNumberTable:
        line 71: 0
        line 12: 4
      LocalVariableTable:
        Start  Length  Slot  Name   Signature
            0       5     0  this   Lcoursier/credentials/FileCredentials$;

  public static final java.lang.Object $anonfun$parse$2$adapted(java.lang.String);
    descriptor: (Ljava/lang/String;)Ljava/lang/Object;
    flags: (0x1019) ACC_PUBLIC, ACC_STATIC, ACC_FINAL, ACC_SYNTHETIC
    Code:
      stack=1, locals=1, args_size=1
         0: aload_0
         1: invokestatic  #343                // Method $anonfun$parse$2:(Ljava/lang/String;)Z
         4: invokestatic  #347                // Method scala/runtime/BoxesRunTime.boxToBoolean:(Z)Ljava/lang/Boolean;
         7: areturn
      LineNumberTable:
        line 42: 0
      LocalVariableTable:
        Start  Length  Slot  Name   Signature
            0       8     0   x$2   Ljava/lang/String;
    MethodParameters:
      Name                           Flags
      x$2                            final

  public static final java.lang.Object $anonfun$parse$7$adapted(java.lang.String);
    descriptor: (Ljava/lang/String;)Ljava/lang/Object;
    flags: (0x1019) ACC_PUBLIC, ACC_STATIC, ACC_FINAL, ACC_SYNTHETIC
    Code:
      stack=1, locals=1, args_size=1
         0: aload_0
         1: invokestatic  #349                // Method $anonfun$parse$7:(Ljava/lang/String;)Z
         4: invokestatic  #347                // Method scala/runtime/BoxesRunTime.boxToBoolean:(Z)Ljava/lang/Boolean;
         7: areturn
      LineNumberTable:
        line 59: 0
      LocalVariableTable:
        Start  Length  Slot  Name   Signature
            0       8     0   x$3   Ljava/lang/String;
    MethodParameters:
      Name                           Flags
      x$3                            final

  public static final java.lang.Object $anonfun$parse$9$adapted(java.lang.String);
    descriptor: (Ljava/lang/String;)Ljava/lang/Object;
    flags: (0x1019) ACC_PUBLIC, ACC_STATIC, ACC_FINAL, ACC_SYNTHETIC
    Code:
      stack=1, locals=1, args_size=1
         0: aload_0
         1: invokestatic  #351                // Method $anonfun$parse$9:(Ljava/lang/String;)Z
         4: invokestatic  #347                // Method scala/runtime/BoxesRunTime.boxToBoolean:(Z)Ljava/lang/Boolean;
         7: areturn
      LineNumberTable:
        line 60: 0
      LocalVariableTable:
        Start  Length  Slot  Name   Signature
            0       8     0   x$4   Ljava/lang/String;
    MethodParameters:
      Name                           Flags
      x$4                            final

  public static final java.lang.Object $anonfun$parse$11$adapted(java.lang.String);
    descriptor: (Ljava/lang/String;)Ljava/lang/Object;
    flags: (0x1019) ACC_PUBLIC, ACC_STATIC, ACC_FINAL, ACC_SYNTHETIC
    Code:
      stack=1, locals=1, args_size=1
         0: aload_0
         1: invokestatic  #353                // Method $anonfun$parse$11:(Ljava/lang/String;)Z
         4: invokestatic  #347                // Method scala/runtime/BoxesRunTime.boxToBoolean:(Z)Ljava/lang/Boolean;
         7: areturn
      LineNumberTable:
        line 61: 0
      LocalVariableTable:
        Start  Length  Slot  Name   Signature
            0       8     0   x$5   Ljava/lang/String;
    MethodParameters:
      Name                           Flags
      x$5                            final

  private static java.lang.Object $deserializeLambda$(java.lang.invoke.SerializedLambda);
    descriptor: (Ljava/lang/invoke/SerializedLambda;)Ljava/lang/Object;
    flags: (0x100a) ACC_PRIVATE, ACC_STATIC, ACC_SYNTHETIC
    Code:
      stack=1, locals=1, args_size=1
         0: aload_0
         1: invokedynamic #365,  0            // InvokeDynamic #11:lambdaDeserialize:(Ljava/lang/invoke/SerializedLambda;)Ljava/lang/Object;
         6: areturn
}
InnerClasses:
  public static final #12= #9 of #11;     // Lookup=class java/lang/invoke/MethodHandles$Lookup of class java/lang/invoke/MethodHandles
  public #17= #14 of #16;                 // EnumerationHasAsScala=class scala/collection/convert/AsScalaExtensions$EnumerationHasAsScala of class scala/collection/convert/AsScalaExtensions
SourceFile: "FileCredentials.scala"
BootstrapMethods:
  0: #76 REF_invokeStatic java/lang/invoke/LambdaMetafactory.altMetafactory:(Ljava/lang/invoke/MethodHandles$Lookup;Ljava/lang/String;Ljava/lang/invoke/MethodType;[Ljava/lang/Object;)Ljava/lang/invoke/CallSite;
    Method arguments:
      #61 (Ljava/lang/Object;)Ljava/lang/Object;
      #66 REF_invokeStatic coursier/credentials/FileCredentials$.$anonfun$parse$1:(Ljava/lang/Object;)Ljava/lang/String;
      #67 (Ljava/lang/Object;)Ljava/lang/String;
      #68 5
      #69 1
      #67 (Ljava/lang/Object;)Ljava/lang/String;
  1: #76 REF_invokeStatic java/lang/invoke/LambdaMetafactory.altMetafactory:(Ljava/lang/invoke/MethodHandles$Lookup;Ljava/lang/String;Ljava/lang/invoke/MethodType;[Ljava/lang/Object;)Ljava/lang/invoke/CallSite;
    Method arguments:
      #61 (Ljava/lang/Object;)Ljava/lang/Object;
      #91 REF_invokeStatic coursier/credentials/FileCredentials$.$anonfun$parse$2$adapted:(Ljava/lang/String;)Ljava/lang/Object;
      #92 (Ljava/lang/String;)Ljava/lang/Object;
      #68 5
      #69 1
      #92 (Ljava/lang/String;)Ljava/lang/Object;
  2: #76 REF_invokeStatic java/lang/invoke/LambdaMetafactory.altMetafactory:(Ljava/lang/invoke/MethodHandles$Lookup;Ljava/lang/String;Ljava/lang/invoke/MethodType;[Ljava/lang/Object;)Ljava/lang/invoke/CallSite;
    Method arguments:
      #61 (Ljava/lang/Object;)Ljava/lang/Object;
      #105 REF_invokeStatic coursier/credentials/FileCredentials$.$anonfun$parse$3:(Ljava/util/Properties;Ljava/lang/String;Ljava/lang/String;)Lcoursier/credentials/DirectCredentials;
      #107 (Ljava/lang/String;)Lcoursier/credentials/DirectCredentials;
      #68 5
      #69 1
      #107 (Ljava/lang/String;)Lcoursier/credentials/DirectCredentials;
  3: #76 REF_invokeStatic java/lang/invoke/LambdaMetafactory.altMetafactory:(Ljava/lang/invoke/MethodHandles$Lookup;Ljava/lang/String;Ljava/lang/invoke/MethodType;[Ljava/lang/Object;)Ljava/lang/invoke/CallSite;
    Method arguments:
      #240 ()Ljava/lang/Object;
      #243 REF_invokeStatic coursier/credentials/FileCredentials$.$anonfun$parse$4:(Ljava/lang/String;Ljava/lang/String;)Lscala/runtime/Nothing$;
      #245 ()Lscala/runtime/Nothing$;
      #68 5
      #69 1
      #245 ()Lscala/runtime/Nothing$;
  4: #76 REF_invokeStatic java/lang/invoke/LambdaMetafactory.altMetafactory:(Ljava/lang/invoke/MethodHandles$Lookup;Ljava/lang/String;Ljava/lang/invoke/MethodType;[Ljava/lang/Object;)Ljava/lang/invoke/CallSite;
    Method arguments:
      #240 ()Ljava/lang/Object;
      #259 REF_invokeStatic coursier/credentials/FileCredentials$.$anonfun$parse$5:(Ljava/lang/String;Ljava/lang/String;)Lscala/runtime/Nothing$;
      #245 ()Lscala/runtime/Nothing$;
      #68 5
      #69 1
      #245 ()Lscala/runtime/Nothing$;
  5: #76 REF_invokeStatic java/lang/invoke/LambdaMetafactory.altMetafactory:(Ljava/lang/invoke/MethodHandles$Lookup;Ljava/lang/String;Ljava/lang/invoke/MethodType;[Ljava/lang/Object;)Ljava/lang/invoke/CallSite;
    Method arguments:
      #266 ()Z
      #269 REF_invokeStatic coursier/credentials/FileCredentials$.$anonfun$parse$6:()Z
      #266 ()Z
      #69 1
  6: #76 REF_invokeStatic java/lang/invoke/LambdaMetafactory.altMetafactory:(Ljava/lang/invoke/MethodHandles$Lookup;Ljava/lang/String;Ljava/lang/invoke/MethodType;[Ljava/lang/Object;)Ljava/lang/invoke/CallSite;
    Method arguments:
      #61 (Ljava/lang/Object;)Ljava/lang/Object;
      #277 REF_invokeStatic coursier/credentials/FileCredentials$.$anonfun$parse$7$adapted:(Ljava/lang/String;)Ljava/lang/Object;
      #92 (Ljava/lang/String;)Ljava/lang/Object;
      #68 5
      #69 1
      #92 (Ljava/lang/String;)Ljava/lang/Object;
  7: #76 REF_invokeStatic java/lang/invoke/LambdaMetafactory.altMetafactory:(Ljava/lang/invoke/MethodHandles$Lookup;Ljava/lang/String;Ljava/lang/invoke/MethodType;[Ljava/lang/Object;)Ljava/lang/invoke/CallSite;
    Method arguments:
      #266 ()Z
      #294 REF_invokeStatic coursier/credentials/FileCredentials$.$anonfun$parse$8:()Z
      #266 ()Z
      #69 1
  8: #76 REF_invokeStatic java/lang/invoke/LambdaMetafactory.altMetafactory:(Ljava/lang/invoke/MethodHandles$Lookup;Ljava/lang/String;Ljava/lang/invoke/MethodType;[Ljava/lang/Object;)Ljava/lang/invoke/CallSite;
    Method arguments:
      #61 (Ljava/lang/Object;)Ljava/lang/Object;
      #299 REF_invokeStatic coursier/credentials/FileCredentials$.$anonfun$parse$9$adapted:(Ljava/lang/String;)Ljava/lang/Object;
      #92 (Ljava/lang/String;)Ljava/lang/Object;
      #68 5
      #69 1
      #92 (Ljava/lang/String;)Ljava/lang/Object;
  9: #76 REF_invokeStatic java/lang/invoke/LambdaMetafactory.altMetafactory:(Ljava/lang/invoke/MethodHandles$Lookup;Ljava/lang/String;Ljava/lang/invoke/MethodType;[Ljava/lang/Object;)Ljava/lang/invoke/CallSite;
    Method arguments:
      #266 ()Z
      #306 REF_invokeStatic coursier/credentials/FileCredentials$.$anonfun$parse$10:()Z
      #266 ()Z
      #69 1
  10: #76 REF_invokeStatic java/lang/invoke/LambdaMetafactory.altMetafactory:(Ljava/lang/invoke/MethodHandles$Lookup;Ljava/lang/String;Ljava/lang/invoke/MethodType;[Ljava/lang/Object;)Ljava/lang/invoke/CallSite;
    Method arguments:
      #61 (Ljava/lang/Object;)Ljava/lang/Object;
      #311 REF_invokeStatic coursier/credentials/FileCredentials$.$anonfun$parse$11$adapted:(Ljava/lang/String;)Ljava/lang/Object;
      #92 (Ljava/lang/String;)Ljava/lang/Object;
      #68 5
      #69 1
      #92 (Ljava/lang/String;)Ljava/lang/Object;
  11: #362 REF_invokeStatic scala/runtime/LambdaDeserialize.bootstrap:(Ljava/lang/invoke/MethodHandles$Lookup;Ljava/lang/String;Ljava/lang/invoke/MethodType;[Ljava/lang/invoke/MethodHandle;)Ljava/lang/invoke/CallSite;
    Method arguments:
      #66 REF_invokeStatic coursier/credentials/FileCredentials$.$anonfun$parse$1:(Ljava/lang/Object;)Ljava/lang/String;
      #306 REF_invokeStatic coursier/credentials/FileCredentials$.$anonfun$parse$10:()Z
      #311 REF_invokeStatic coursier/credentials/FileCredentials$.$anonfun$parse$11$adapted:(Ljava/lang/String;)Ljava/lang/Object;
      #91 REF_invokeStatic coursier/credentials/FileCredentials$.$anonfun$parse$2$adapted:(Ljava/lang/String;)Ljava/lang/Object;
      #105 REF_invokeStatic coursier/credentials/FileCredentials$.$anonfun$parse$3:(Ljava/util/Properties;Ljava/lang/String;Ljava/lang/String;)Lcoursier/credentials/DirectCredentials;
      #243 REF_invokeStatic coursier/credentials/FileCredentials$.$anonfun$parse$4:(Ljava/lang/String;Ljava/lang/String;)Lscala/runtime/Nothing$;
      #259 REF_invokeStatic coursier/credentials/FileCredentials$.$anonfun$parse$5:(Ljava/lang/String;Ljava/lang/String;)Lscala/runtime/Nothing$;
      #269 REF_invokeStatic coursier/credentials/FileCredentials$.$anonfun$parse$6:()Z
      #277 REF_invokeStatic coursier/credentials/FileCredentials$.$anonfun$parse$7$adapted:(Ljava/lang/String;)Ljava/lang/Object;
      #294 REF_invokeStatic coursier/credentials/FileCredentials$.$anonfun$parse$8:()Z
      #299 REF_invokeStatic coursier/credentials/FileCredentials$.$anonfun$parse$9$adapted:(Ljava/lang/String;)Ljava/lang/Object;
  ScalaInlineInfo: length = 0x68 (unknown attribute)
   01 01 00 14 00 3E 00 3F 01 00 D9 00 B7 01 00 DA
   00 92 01 01 34 00 58 01 00 91 00 92 01 00 57 00
   58 01 00 65 00 66 01 00 99 00 9A 01 00 B2 00 9A
   01 00 B6 00 B7 01 00 C0 00 92 01 01 12 00 58 01
   00 D3 00 B7 01 00 D7 00 92 01 01 28 00 58 01 00
   16 00 15 01 00 4D 00 7C 01 00 4D 00 83 01 00 1B
   00 1C 01 00 86 00 87 01
  Scala: length = 0x0 (unknown attribute)

