Classfile /Users/mw/Projects/slang-braindump/.jar/jar8/assemble/slang-braindump/assemble/content/scala/compat/java8/wrappers/IteratorPrimitiveDoubleWrapper.class
  Last modified May 29, 2022; size 1021 bytes
  SHA-256 checksum 16fd4bc08b5c41a2503a13a46b92ccc4f627df4d1dbd43b10d233c81b342e82c
  Compiled from "IteratorPrimitiveDoubleWrapper.java"
public class scala.compat.java8.wrappers.IteratorPrimitiveDoubleWrapper implements java.util.PrimitiveIterator$OfDouble
  minor version: 0
  major version: 52
  flags: (0x0021) ACC_PUBLIC, ACC_SUPER
  this_class: #8                          // scala/compat/java8/wrappers/IteratorPrimitiveDoubleWrapper
  super_class: #9                         // java/lang/Object
  interfaces: 1, fields: 1, methods: 4, attributes: 2
Constant pool:
   #1 = Methodref          #9.#29         // java/lang/Object."<init>":()V
   #2 = Fieldref           #8.#30         // scala/compat/java8/wrappers/IteratorPrimitiveDoubleWrapper.it:Ljava/util/Iterator;
   #3 = InterfaceMethodref #31.#32        // java/util/Iterator.hasNext:()Z
   #4 = InterfaceMethodref #31.#33        // java/util/Iterator.next:()Ljava/lang/Object;
   #5 = Class              #34            // java/lang/Double
   #6 = Methodref          #5.#35         // java/lang/Double.doubleValue:()D
   #7 = InterfaceMethodref #31.#36        // java/util/Iterator.forEachRemaining:(Ljava/util/function/Consumer;)V
   #8 = Class              #37            // scala/compat/java8/wrappers/IteratorPrimitiveDoubleWrapper
   #9 = Class              #38            // java/lang/Object
  #10 = Class              #40            // java/util/PrimitiveIterator$OfDouble
  #11 = Utf8               it
  #12 = Utf8               Ljava/util/Iterator;
  #13 = Utf8               Signature
  #14 = Utf8               Ljava/util/Iterator<Ljava/lang/Double;>;
  #15 = Utf8               <init>
  #16 = Utf8               (Ljava/util/Iterator;)V
  #17 = Utf8               Code
  #18 = Utf8               LineNumberTable
  #19 = Utf8               (Ljava/util/Iterator<Ljava/lang/Double;>;)V
  #20 = Utf8               hasNext
  #21 = Utf8               ()Z
  #22 = Utf8               nextDouble
  #23 = Utf8               ()D
  #24 = Utf8               forEachRemaining
  #25 = Utf8               (Ljava/util/function/Consumer;)V
  #26 = Utf8               (Ljava/util/function/Consumer<-Ljava/lang/Double;>;)V
  #27 = Utf8               SourceFile
  #28 = Utf8               IteratorPrimitiveDoubleWrapper.java
  #29 = NameAndType        #15:#43        // "<init>":()V
  #30 = NameAndType        #11:#12        // it:Ljava/util/Iterator;
  #31 = Class              #44            // java/util/Iterator
  #32 = NameAndType        #20:#21        // hasNext:()Z
  #33 = NameAndType        #45:#46        // next:()Ljava/lang/Object;
  #34 = Utf8               java/lang/Double
  #35 = NameAndType        #47:#23        // doubleValue:()D
  #36 = NameAndType        #24:#25        // forEachRemaining:(Ljava/util/function/Consumer;)V
  #37 = Utf8               scala/compat/java8/wrappers/IteratorPrimitiveDoubleWrapper
  #38 = Utf8               java/lang/Object
  #39 = Class              #48            // java/util/PrimitiveIterator
  #40 = Utf8               java/util/PrimitiveIterator$OfDouble
  #41 = Utf8               OfDouble
  #42 = Utf8               InnerClasses
  #43 = Utf8               ()V
  #44 = Utf8               java/util/Iterator
  #45 = Utf8               next
  #46 = Utf8               ()Ljava/lang/Object;
  #47 = Utf8               doubleValue
  #48 = Utf8               java/util/PrimitiveIterator
{
  private java.util.Iterator<java.lang.Double> it;
    descriptor: Ljava/util/Iterator;
    flags: (0x0002) ACC_PRIVATE
    Signature: #14                          // Ljava/util/Iterator<Ljava/lang/Double;>;

  public scala.compat.java8.wrappers.IteratorPrimitiveDoubleWrapper(java.util.Iterator<java.lang.Double>);
    descriptor: (Ljava/util/Iterator;)V
    flags: (0x0001) ACC_PUBLIC
    Code:
      stack=2, locals=2, args_size=2
         0: aload_0
         1: invokespecial #1                  // Method java/lang/Object."<init>":()V
         4: aload_0
         5: aload_1
         6: putfield      #2                  // Field it:Ljava/util/Iterator;
         9: return
      LineNumberTable:
        line 17: 0
        line 18: 4
        line 19: 9
    Signature: #19                          // (Ljava/util/Iterator<Ljava/lang/Double;>;)V

  public boolean hasNext();
    descriptor: ()Z
    flags: (0x0001) ACC_PUBLIC
    Code:
      stack=1, locals=1, args_size=1
         0: aload_0
         1: getfield      #2                  // Field it:Ljava/util/Iterator;
         4: invokeinterface #3,  1            // InterfaceMethod java/util/Iterator.hasNext:()Z
         9: ireturn
      LineNumberTable:
        line 20: 0

  public double nextDouble();
    descriptor: ()D
    flags: (0x0001) ACC_PUBLIC
    Code:
      stack=2, locals=1, args_size=1
         0: aload_0
         1: getfield      #2                  // Field it:Ljava/util/Iterator;
         4: invokeinterface #4,  1            // InterfaceMethod java/util/Iterator.next:()Ljava/lang/Object;
         9: checkcast     #5                  // class java/lang/Double
        12: invokevirtual #6                  // Method java/lang/Double.doubleValue:()D
        15: dreturn
      LineNumberTable:
        line 21: 0

  public void forEachRemaining(java.util.function.Consumer<? super java.lang.Double>);
    descriptor: (Ljava/util/function/Consumer;)V
    flags: (0x0001) ACC_PUBLIC
    Code:
      stack=2, locals=2, args_size=2
         0: aload_0
         1: getfield      #2                  // Field it:Ljava/util/Iterator;
         4: aload_1
         5: invokeinterface #7,  2            // InterfaceMethod java/util/Iterator.forEachRemaining:(Ljava/util/function/Consumer;)V
        10: return
      LineNumberTable:
        line 23: 0
        line 24: 10
    Signature: #26                          // (Ljava/util/function/Consumer<-Ljava/lang/Double;>;)V
}
SourceFile: "IteratorPrimitiveDoubleWrapper.java"
InnerClasses:
  public static #41= #10 of #39;          // OfDouble=class java/util/PrimitiveIterator$OfDouble of class java/util/PrimitiveIterator
