Classfile /Users/mw/Projects/slang-braindump/.jar/jar8/assemble/slang-braindump/assemble/content/coursier/util/shaded/org/jsoup/safety/Cleaner$CleaningVisitor.class
  Last modified May 29, 2022; size 3618 bytes
  SHA-256 checksum 1a01af511d80f95b85b124b8ad49e0cf6ba9b32cd1ad1041f05ce21f9c78fc2d
  Compiled from "Cleaner.java"
final class coursier.util.shaded.org.jsoup.safety.Cleaner$CleaningVisitor implements coursier.util.shaded.org.jsoup.select.NodeVisitor
  minor version: 0
  major version: 51
  flags: (0x0030) ACC_FINAL, ACC_SUPER
  this_class: #2                          // coursier/util/shaded/org/jsoup/safety/Cleaner$CleaningVisitor
  super_class: #4                         // java/lang/Object
  interfaces: 1, fields: 4, methods: 5, attributes: 2
Constant pool:
    #1 = Utf8               coursier/util/shaded/org/jsoup/safety/Cleaner$CleaningVisitor
    #2 = Class              #1            // coursier/util/shaded/org/jsoup/safety/Cleaner$CleaningVisitor
    #3 = Utf8               java/lang/Object
    #4 = Class              #3            // java/lang/Object
    #5 = Utf8               coursier/util/shaded/org/jsoup/select/NodeVisitor
    #6 = Class              #5            // coursier/util/shaded/org/jsoup/select/NodeVisitor
    #7 = Utf8               Cleaner.java
    #8 = Utf8               coursier/util/shaded/org/jsoup/safety/Cleaner
    #9 = Class              #8            // coursier/util/shaded/org/jsoup/safety/Cleaner
   #10 = Utf8               CleaningVisitor
   #11 = Utf8               coursier/util/shaded/org/jsoup/safety/Cleaner$ElementMeta
   #12 = Class              #11           // coursier/util/shaded/org/jsoup/safety/Cleaner$ElementMeta
   #13 = Utf8               ElementMeta
   #14 = Utf8               coursier/util/shaded/org/jsoup/safety/Cleaner$1
   #15 = Class              #14           // coursier/util/shaded/org/jsoup/safety/Cleaner$1
   #16 = Utf8               numDiscarded
   #17 = Utf8               I
   #18 = Utf8               root
   #19 = Utf8               Lcoursier/util/shaded/org/jsoup/nodes/Element;
   #20 = Utf8               destination
   #21 = Utf8               this$0
   #22 = Utf8               Lcoursier/util/shaded/org/jsoup/safety/Cleaner;
   #23 = Utf8               <init>
   #24 = Utf8               (Lcoursier/util/shaded/org/jsoup/safety/Cleaner;Lcoursier/util/shaded/org/jsoup/nodes/Element;Lcoursier/util/shaded/org/jsoup/nodes/Element;)V
   #25 = NameAndType        #21:#22       // this$0:Lcoursier/util/shaded/org/jsoup/safety/Cleaner;
   #26 = Fieldref           #2.#25        // coursier/util/shaded/org/jsoup/safety/Cleaner$CleaningVisitor.this$0:Lcoursier/util/shaded/org/jsoup/safety/Cleaner;
   #27 = Utf8               ()V
   #28 = NameAndType        #23:#27       // "<init>":()V
   #29 = Methodref          #4.#28        // java/lang/Object."<init>":()V
   #30 = NameAndType        #16:#17       // numDiscarded:I
   #31 = Fieldref           #2.#30        // coursier/util/shaded/org/jsoup/safety/Cleaner$CleaningVisitor.numDiscarded:I
   #32 = NameAndType        #18:#19       // root:Lcoursier/util/shaded/org/jsoup/nodes/Element;
   #33 = Fieldref           #2.#32        // coursier/util/shaded/org/jsoup/safety/Cleaner$CleaningVisitor.root:Lcoursier/util/shaded/org/jsoup/nodes/Element;
   #34 = NameAndType        #20:#19       // destination:Lcoursier/util/shaded/org/jsoup/nodes/Element;
   #35 = Fieldref           #2.#34        // coursier/util/shaded/org/jsoup/safety/Cleaner$CleaningVisitor.destination:Lcoursier/util/shaded/org/jsoup/nodes/Element;
   #36 = Utf8               this
   #37 = Utf8               Lcoursier/util/shaded/org/jsoup/safety/Cleaner$CleaningVisitor;
   #38 = Utf8               head
   #39 = Utf8               (Lcoursier/util/shaded/org/jsoup/nodes/Node;I)V
   #40 = Utf8               coursier/util/shaded/org/jsoup/nodes/Element
   #41 = Class              #40           // coursier/util/shaded/org/jsoup/nodes/Element
   #42 = Utf8               access$000
   #43 = Utf8               (Lcoursier/util/shaded/org/jsoup/safety/Cleaner;)Lcoursier/util/shaded/org/jsoup/safety/Whitelist;
   #44 = NameAndType        #42:#43       // access$000:(Lcoursier/util/shaded/org/jsoup/safety/Cleaner;)Lcoursier/util/shaded/org/jsoup/safety/Whitelist;
   #45 = Methodref          #9.#44        // coursier/util/shaded/org/jsoup/safety/Cleaner.access$000:(Lcoursier/util/shaded/org/jsoup/safety/Cleaner;)Lcoursier/util/shaded/org/jsoup/safety/Whitelist;
   #46 = Utf8               normalName
   #47 = Utf8               ()Ljava/lang/String;
   #48 = NameAndType        #46:#47       // normalName:()Ljava/lang/String;
   #49 = Methodref          #41.#48       // coursier/util/shaded/org/jsoup/nodes/Element.normalName:()Ljava/lang/String;
   #50 = Utf8               coursier/util/shaded/org/jsoup/safety/Whitelist
   #51 = Class              #50           // coursier/util/shaded/org/jsoup/safety/Whitelist
   #52 = Utf8               isSafeTag
   #53 = Utf8               (Ljava/lang/String;)Z
   #54 = NameAndType        #52:#53       // isSafeTag:(Ljava/lang/String;)Z
   #55 = Methodref          #51.#54       // coursier/util/shaded/org/jsoup/safety/Whitelist.isSafeTag:(Ljava/lang/String;)Z
   #56 = Utf8               access$100
   #57 = Utf8               (Lcoursier/util/shaded/org/jsoup/safety/Cleaner;Lcoursier/util/shaded/org/jsoup/nodes/Element;)Lcoursier/util/shaded/org/jsoup/safety/Cleaner$ElementMeta;
   #58 = NameAndType        #56:#57       // access$100:(Lcoursier/util/shaded/org/jsoup/safety/Cleaner;Lcoursier/util/shaded/org/jsoup/nodes/Element;)Lcoursier/util/shaded/org/jsoup/safety/Cleaner$ElementMeta;
   #59 = Methodref          #9.#58        // coursier/util/shaded/org/jsoup/safety/Cleaner.access$100:(Lcoursier/util/shaded/org/jsoup/safety/Cleaner;Lcoursier/util/shaded/org/jsoup/nodes/Element;)Lcoursier/util/shaded/org/jsoup/safety/Cleaner$ElementMeta;
   #60 = Utf8               el
   #61 = NameAndType        #60:#19       // el:Lcoursier/util/shaded/org/jsoup/nodes/Element;
   #62 = Fieldref           #12.#61       // coursier/util/shaded/org/jsoup/safety/Cleaner$ElementMeta.el:Lcoursier/util/shaded/org/jsoup/nodes/Element;
   #63 = Utf8               appendChild
   #64 = Utf8               (Lcoursier/util/shaded/org/jsoup/nodes/Node;)Lcoursier/util/shaded/org/jsoup/nodes/Element;
   #65 = NameAndType        #63:#64       // appendChild:(Lcoursier/util/shaded/org/jsoup/nodes/Node;)Lcoursier/util/shaded/org/jsoup/nodes/Element;
   #66 = Methodref          #41.#65       // coursier/util/shaded/org/jsoup/nodes/Element.appendChild:(Lcoursier/util/shaded/org/jsoup/nodes/Node;)Lcoursier/util/shaded/org/jsoup/nodes/Element;
   #67 = Utf8               numAttribsDiscarded
   #68 = NameAndType        #67:#17       // numAttribsDiscarded:I
   #69 = Fieldref           #12.#68       // coursier/util/shaded/org/jsoup/safety/Cleaner$ElementMeta.numAttribsDiscarded:I
   #70 = Utf8               coursier/util/shaded/org/jsoup/nodes/TextNode
   #71 = Class              #70           // coursier/util/shaded/org/jsoup/nodes/TextNode
   #72 = Utf8               getWholeText
   #73 = NameAndType        #72:#47       // getWholeText:()Ljava/lang/String;
   #74 = Methodref          #71.#73       // coursier/util/shaded/org/jsoup/nodes/TextNode.getWholeText:()Ljava/lang/String;
   #75 = Utf8               (Ljava/lang/String;)V
   #76 = NameAndType        #23:#75       // "<init>":(Ljava/lang/String;)V
   #77 = Methodref          #71.#76       // coursier/util/shaded/org/jsoup/nodes/TextNode."<init>":(Ljava/lang/String;)V
   #78 = Utf8               coursier/util/shaded/org/jsoup/nodes/DataNode
   #79 = Class              #78           // coursier/util/shaded/org/jsoup/nodes/DataNode
   #80 = Utf8               coursier/util/shaded/org/jsoup/nodes/Node
   #81 = Class              #80           // coursier/util/shaded/org/jsoup/nodes/Node
   #82 = Utf8               parent
   #83 = Utf8               ()Lcoursier/util/shaded/org/jsoup/nodes/Node;
   #84 = NameAndType        #82:#83       // parent:()Lcoursier/util/shaded/org/jsoup/nodes/Node;
   #85 = Methodref          #81.#84       // coursier/util/shaded/org/jsoup/nodes/Node.parent:()Lcoursier/util/shaded/org/jsoup/nodes/Node;
   #86 = Utf8               nodeName
   #87 = NameAndType        #86:#47       // nodeName:()Ljava/lang/String;
   #88 = Methodref          #81.#87       // coursier/util/shaded/org/jsoup/nodes/Node.nodeName:()Ljava/lang/String;
   #89 = Utf8               getWholeData
   #90 = NameAndType        #89:#47       // getWholeData:()Ljava/lang/String;
   #91 = Methodref          #79.#90       // coursier/util/shaded/org/jsoup/nodes/DataNode.getWholeData:()Ljava/lang/String;
   #92 = Methodref          #79.#76       // coursier/util/shaded/org/jsoup/nodes/DataNode."<init>":(Ljava/lang/String;)V
   #93 = Utf8               meta
   #94 = Utf8               Lcoursier/util/shaded/org/jsoup/safety/Cleaner$ElementMeta;
   #95 = Utf8               destChild
   #96 = Utf8               sourceEl
   #97 = Utf8               sourceText
   #98 = Utf8               Lcoursier/util/shaded/org/jsoup/nodes/TextNode;
   #99 = Utf8               destText
  #100 = Utf8               sourceData
  #101 = Utf8               Lcoursier/util/shaded/org/jsoup/nodes/DataNode;
  #102 = Utf8               destData
  #103 = Utf8               source
  #104 = Utf8               Lcoursier/util/shaded/org/jsoup/nodes/Node;
  #105 = Utf8               depth
  #106 = Utf8               tail
  #107 = Utf8               ()Lcoursier/util/shaded/org/jsoup/nodes/Element;
  #108 = NameAndType        #82:#107      // parent:()Lcoursier/util/shaded/org/jsoup/nodes/Element;
  #109 = Methodref          #41.#108      // coursier/util/shaded/org/jsoup/nodes/Element.parent:()Lcoursier/util/shaded/org/jsoup/nodes/Element;
  #110 = Utf8               (Lcoursier/util/shaded/org/jsoup/safety/Cleaner;Lcoursier/util/shaded/org/jsoup/nodes/Element;Lcoursier/util/shaded/org/jsoup/nodes/Element;Lcoursier/util/shaded/org/jsoup/safety/Cleaner$1;)V
  #111 = NameAndType        #23:#24       // "<init>":(Lcoursier/util/shaded/org/jsoup/safety/Cleaner;Lcoursier/util/shaded/org/jsoup/nodes/Element;Lcoursier/util/shaded/org/jsoup/nodes/Element;)V
  #112 = Methodref          #2.#111       // coursier/util/shaded/org/jsoup/safety/Cleaner$CleaningVisitor."<init>":(Lcoursier/util/shaded/org/jsoup/safety/Cleaner;Lcoursier/util/shaded/org/jsoup/nodes/Element;Lcoursier/util/shaded/org/jsoup/nodes/Element;)V
  #113 = Utf8               x0
  #114 = Utf8               x1
  #115 = Utf8               x2
  #116 = Utf8               x3
  #117 = Utf8               Lcoursier/util/shaded/org/jsoup/safety/Cleaner$1;
  #118 = Utf8               access$300
  #119 = Utf8               (Lcoursier/util/shaded/org/jsoup/safety/Cleaner$CleaningVisitor;)I
  #120 = Utf8               Code
  #121 = Utf8               LineNumberTable
  #122 = Utf8               LocalVariableTable
  #123 = Utf8               StackMapTable
  #124 = Utf8               InnerClasses
  #125 = Utf8               SourceFile
{
  private int numDiscarded;
    descriptor: I
    flags: (0x0002) ACC_PRIVATE

  private final coursier.util.shaded.org.jsoup.nodes.Element root;
    descriptor: Lcoursier/util/shaded/org/jsoup/nodes/Element;
    flags: (0x0012) ACC_PRIVATE, ACC_FINAL

  private coursier.util.shaded.org.jsoup.nodes.Element destination;
    descriptor: Lcoursier/util/shaded/org/jsoup/nodes/Element;
    flags: (0x0002) ACC_PRIVATE

  final coursier.util.shaded.org.jsoup.safety.Cleaner this$0;
    descriptor: Lcoursier/util/shaded/org/jsoup/safety/Cleaner;
    flags: (0x1010) ACC_FINAL, ACC_SYNTHETIC

  private coursier.util.shaded.org.jsoup.safety.Cleaner$CleaningVisitor(coursier.util.shaded.org.jsoup.safety.Cleaner, coursier.util.shaded.org.jsoup.nodes.Element, coursier.util.shaded.org.jsoup.nodes.Element);
    descriptor: (Lcoursier/util/shaded/org/jsoup/safety/Cleaner;Lcoursier/util/shaded/org/jsoup/nodes/Element;Lcoursier/util/shaded/org/jsoup/nodes/Element;)V
    flags: (0x0002) ACC_PRIVATE
    Code:
      stack=2, locals=4, args_size=4
         0: aload_0
         1: aload_1
         2: putfield      #26                 // Field this$0:Lcoursier/util/shaded/org/jsoup/safety/Cleaner;
         5: aload_0
         6: invokespecial #29                 // Method java/lang/Object."<init>":()V
         9: aload_0
        10: iconst_0
        11: putfield      #31                 // Field numDiscarded:I
        14: aload_0
        15: aload_2
        16: putfield      #33                 // Field root:Lcoursier/util/shaded/org/jsoup/nodes/Element;
        19: aload_0
        20: aload_3
        21: putfield      #35                 // Field destination:Lcoursier/util/shaded/org/jsoup/nodes/Element;
        24: return
      LineNumberTable:
        line 101: 0
        line 97: 9
        line 102: 14
        line 103: 19
        line 104: 24
      LocalVariableTable:
        Start  Length  Slot  Name   Signature
            0      25     0  this   Lcoursier/util/shaded/org/jsoup/safety/Cleaner$CleaningVisitor;
            0      25     2  root   Lcoursier/util/shaded/org/jsoup/nodes/Element;
            0      25     3 destination   Lcoursier/util/shaded/org/jsoup/nodes/Element;

  public void head(coursier.util.shaded.org.jsoup.nodes.Node, int);
    descriptor: (Lcoursier/util/shaded/org/jsoup/nodes/Node;I)V
    flags: (0x0001) ACC_PUBLIC
    Code:
      stack=3, locals=6, args_size=3
         0: aload_1
         1: instanceof    #41                 // class coursier/util/shaded/org/jsoup/nodes/Element
         4: ifeq          100
         7: aload_1
         8: checkcast     #41                 // class coursier/util/shaded/org/jsoup/nodes/Element
        11: astore_3
        12: aload_0
        13: getfield      #26                 // Field this$0:Lcoursier/util/shaded/org/jsoup/safety/Cleaner;
        16: invokestatic  #45                 // Method coursier/util/shaded/org/jsoup/safety/Cleaner.access$000:(Lcoursier/util/shaded/org/jsoup/safety/Cleaner;)Lcoursier/util/shaded/org/jsoup/safety/Whitelist;
        19: aload_3
        20: invokevirtual #49                 // Method coursier/util/shaded/org/jsoup/nodes/Element.normalName:()Ljava/lang/String;
        23: invokevirtual #55                 // Method coursier/util/shaded/org/jsoup/safety/Whitelist.isSafeTag:(Ljava/lang/String;)Z
        26: ifeq          79
        29: aload_0
        30: getfield      #26                 // Field this$0:Lcoursier/util/shaded/org/jsoup/safety/Cleaner;
        33: aload_3
        34: invokestatic  #59                 // Method coursier/util/shaded/org/jsoup/safety/Cleaner.access$100:(Lcoursier/util/shaded/org/jsoup/safety/Cleaner;Lcoursier/util/shaded/org/jsoup/nodes/Element;)Lcoursier/util/shaded/org/jsoup/safety/Cleaner$ElementMeta;
        37: astore        4
        39: aload         4
        41: getfield      #62                 // Field coursier/util/shaded/org/jsoup/safety/Cleaner$ElementMeta.el:Lcoursier/util/shaded/org/jsoup/nodes/Element;
        44: astore        5
        46: aload_0
        47: getfield      #35                 // Field destination:Lcoursier/util/shaded/org/jsoup/nodes/Element;
        50: aload         5
        52: invokevirtual #66                 // Method coursier/util/shaded/org/jsoup/nodes/Element.appendChild:(Lcoursier/util/shaded/org/jsoup/nodes/Node;)Lcoursier/util/shaded/org/jsoup/nodes/Element;
        55: pop
        56: aload_0
        57: dup
        58: getfield      #31                 // Field numDiscarded:I
        61: aload         4
        63: getfield      #69                 // Field coursier/util/shaded/org/jsoup/safety/Cleaner$ElementMeta.numAttribsDiscarded:I
        66: iadd
        67: putfield      #31                 // Field numDiscarded:I
        70: aload_0
        71: aload         5
        73: putfield      #35                 // Field destination:Lcoursier/util/shaded/org/jsoup/nodes/Element;
        76: goto          97
        79: aload_1
        80: aload_0
        81: getfield      #33                 // Field root:Lcoursier/util/shaded/org/jsoup/nodes/Element;
        84: if_acmpeq     97
        87: aload_0
        88: dup
        89: getfield      #31                 // Field numDiscarded:I
        92: iconst_1
        93: iadd
        94: putfield      #31                 // Field numDiscarded:I
        97: goto          206
       100: aload_1
       101: instanceof    #71                 // class coursier/util/shaded/org/jsoup/nodes/TextNode
       104: ifeq          138
       107: aload_1
       108: checkcast     #71                 // class coursier/util/shaded/org/jsoup/nodes/TextNode
       111: astore_3
       112: new           #71                 // class coursier/util/shaded/org/jsoup/nodes/TextNode
       115: dup
       116: aload_3
       117: invokevirtual #74                 // Method coursier/util/shaded/org/jsoup/nodes/TextNode.getWholeText:()Ljava/lang/String;
       120: invokespecial #77                 // Method coursier/util/shaded/org/jsoup/nodes/TextNode."<init>":(Ljava/lang/String;)V
       123: astore        4
       125: aload_0
       126: getfield      #35                 // Field destination:Lcoursier/util/shaded/org/jsoup/nodes/Element;
       129: aload         4
       131: invokevirtual #66                 // Method coursier/util/shaded/org/jsoup/nodes/Element.appendChild:(Lcoursier/util/shaded/org/jsoup/nodes/Node;)Lcoursier/util/shaded/org/jsoup/nodes/Element;
       134: pop
       135: goto          206
       138: aload_1
       139: instanceof    #79                 // class coursier/util/shaded/org/jsoup/nodes/DataNode
       142: ifeq          196
       145: aload_0
       146: getfield      #26                 // Field this$0:Lcoursier/util/shaded/org/jsoup/safety/Cleaner;
       149: invokestatic  #45                 // Method coursier/util/shaded/org/jsoup/safety/Cleaner.access$000:(Lcoursier/util/shaded/org/jsoup/safety/Cleaner;)Lcoursier/util/shaded/org/jsoup/safety/Whitelist;
       152: aload_1
       153: invokevirtual #85                 // Method coursier/util/shaded/org/jsoup/nodes/Node.parent:()Lcoursier/util/shaded/org/jsoup/nodes/Node;
       156: invokevirtual #88                 // Method coursier/util/shaded/org/jsoup/nodes/Node.nodeName:()Ljava/lang/String;
       159: invokevirtual #55                 // Method coursier/util/shaded/org/jsoup/safety/Whitelist.isSafeTag:(Ljava/lang/String;)Z
       162: ifeq          196
       165: aload_1
       166: checkcast     #79                 // class coursier/util/shaded/org/jsoup/nodes/DataNode
       169: astore_3
       170: new           #79                 // class coursier/util/shaded/org/jsoup/nodes/DataNode
       173: dup
       174: aload_3
       175: invokevirtual #91                 // Method coursier/util/shaded/org/jsoup/nodes/DataNode.getWholeData:()Ljava/lang/String;
       178: invokespecial #92                 // Method coursier/util/shaded/org/jsoup/nodes/DataNode."<init>":(Ljava/lang/String;)V
       181: astore        4
       183: aload_0
       184: getfield      #35                 // Field destination:Lcoursier/util/shaded/org/jsoup/nodes/Element;
       187: aload         4
       189: invokevirtual #66                 // Method coursier/util/shaded/org/jsoup/nodes/Element.appendChild:(Lcoursier/util/shaded/org/jsoup/nodes/Node;)Lcoursier/util/shaded/org/jsoup/nodes/Element;
       192: pop
       193: goto          206
       196: aload_0
       197: dup
       198: getfield      #31                 // Field numDiscarded:I
       201: iconst_1
       202: iadd
       203: putfield      #31                 // Field numDiscarded:I
       206: return
      StackMapTable: number_of_entries = 6
        frame_type = 252 /* append */
          offset_delta = 79
          locals = [ class coursier/util/shaded/org/jsoup/nodes/Element ]
        frame_type = 250 /* chop */
          offset_delta = 17
        frame_type = 2 /* same */
        frame_type = 37 /* same */
        frame_type = 57 /* same */
        frame_type = 9 /* same */
      LineNumberTable:
        line 107: 0
        line 108: 7
        line 110: 12
        line 111: 29
        line 112: 39
        line 113: 46
        line 115: 56
        line 116: 70
        line 117: 76
        line 118: 87
        line 120: 97
        line 121: 107
        line 122: 112
        line 123: 125
        line 124: 135
        line 125: 165
        line 126: 170
        line 127: 183
        line 128: 193
        line 129: 196
        line 131: 206
      LocalVariableTable:
        Start  Length  Slot  Name   Signature
           39      37     4  meta   Lcoursier/util/shaded/org/jsoup/safety/Cleaner$ElementMeta;
           46      30     5 destChild   Lcoursier/util/shaded/org/jsoup/nodes/Element;
           12      85     3 sourceEl   Lcoursier/util/shaded/org/jsoup/nodes/Element;
          112      23     3 sourceText   Lcoursier/util/shaded/org/jsoup/nodes/TextNode;
          125      10     4 destText   Lcoursier/util/shaded/org/jsoup/nodes/TextNode;
          170      23     3 sourceData   Lcoursier/util/shaded/org/jsoup/nodes/DataNode;
          183      10     4 destData   Lcoursier/util/shaded/org/jsoup/nodes/DataNode;
            0     207     0  this   Lcoursier/util/shaded/org/jsoup/safety/Cleaner$CleaningVisitor;
            0     207     1 source   Lcoursier/util/shaded/org/jsoup/nodes/Node;
            0     207     2 depth   I

  public void tail(coursier.util.shaded.org.jsoup.nodes.Node, int);
    descriptor: (Lcoursier/util/shaded/org/jsoup/nodes/Node;I)V
    flags: (0x0001) ACC_PUBLIC
    Code:
      stack=2, locals=3, args_size=3
         0: aload_1
         1: instanceof    #41                 // class coursier/util/shaded/org/jsoup/nodes/Element
         4: ifeq          35
         7: aload_0
         8: getfield      #26                 // Field this$0:Lcoursier/util/shaded/org/jsoup/safety/Cleaner;
        11: invokestatic  #45                 // Method coursier/util/shaded/org/jsoup/safety/Cleaner.access$000:(Lcoursier/util/shaded/org/jsoup/safety/Cleaner;)Lcoursier/util/shaded/org/jsoup/safety/Whitelist;
        14: aload_1
        15: invokevirtual #88                 // Method coursier/util/shaded/org/jsoup/nodes/Node.nodeName:()Ljava/lang/String;
        18: invokevirtual #55                 // Method coursier/util/shaded/org/jsoup/safety/Whitelist.isSafeTag:(Ljava/lang/String;)Z
        21: ifeq          35
        24: aload_0
        25: aload_0
        26: getfield      #35                 // Field destination:Lcoursier/util/shaded/org/jsoup/nodes/Element;
        29: invokevirtual #109                // Method coursier/util/shaded/org/jsoup/nodes/Element.parent:()Lcoursier/util/shaded/org/jsoup/nodes/Element;
        32: putfield      #35                 // Field destination:Lcoursier/util/shaded/org/jsoup/nodes/Element;
        35: return
      StackMapTable: number_of_entries = 1
        frame_type = 35 /* same */
      LineNumberTable:
        line 134: 0
        line 135: 24
        line 137: 35
      LocalVariableTable:
        Start  Length  Slot  Name   Signature
            0      36     0  this   Lcoursier/util/shaded/org/jsoup/safety/Cleaner$CleaningVisitor;
            0      36     1 source   Lcoursier/util/shaded/org/jsoup/nodes/Node;
            0      36     2 depth   I

  coursier.util.shaded.org.jsoup.safety.Cleaner$CleaningVisitor(coursier.util.shaded.org.jsoup.safety.Cleaner, coursier.util.shaded.org.jsoup.nodes.Element, coursier.util.shaded.org.jsoup.nodes.Element, coursier.util.shaded.org.jsoup.safety.Cleaner$1);
    descriptor: (Lcoursier/util/shaded/org/jsoup/safety/Cleaner;Lcoursier/util/shaded/org/jsoup/nodes/Element;Lcoursier/util/shaded/org/jsoup/nodes/Element;Lcoursier/util/shaded/org/jsoup/safety/Cleaner$1;)V
    flags: (0x1000) ACC_SYNTHETIC
    Code:
      stack=4, locals=5, args_size=5
         0: aload_0
         1: aload_1
         2: aload_2
         3: aload_3
         4: invokespecial #112                // Method "<init>":(Lcoursier/util/shaded/org/jsoup/safety/Cleaner;Lcoursier/util/shaded/org/jsoup/nodes/Element;Lcoursier/util/shaded/org/jsoup/nodes/Element;)V
         7: return
      LineNumberTable:
        line 96: 0
      LocalVariableTable:
        Start  Length  Slot  Name   Signature
            0       8     0  this   Lcoursier/util/shaded/org/jsoup/safety/Cleaner$CleaningVisitor;
            0       8     1    x0   Lcoursier/util/shaded/org/jsoup/safety/Cleaner;
            0       8     2    x1   Lcoursier/util/shaded/org/jsoup/nodes/Element;
            0       8     3    x2   Lcoursier/util/shaded/org/jsoup/nodes/Element;
            0       8     4    x3   Lcoursier/util/shaded/org/jsoup/safety/Cleaner$1;

  static int access$300(coursier.util.shaded.org.jsoup.safety.Cleaner$CleaningVisitor);
    descriptor: (Lcoursier/util/shaded/org/jsoup/safety/Cleaner$CleaningVisitor;)I
    flags: (0x1008) ACC_STATIC, ACC_SYNTHETIC
    Code:
      stack=1, locals=1, args_size=1
         0: aload_0
         1: getfield      #31                 // Field numDiscarded:I
         4: ireturn
      LineNumberTable:
        line 96: 0
      LocalVariableTable:
        Start  Length  Slot  Name   Signature
            0       5     0    x0   Lcoursier/util/shaded/org/jsoup/safety/Cleaner$CleaningVisitor;
}
InnerClasses:
  private final #10= #2 of #9;            // CleaningVisitor=class coursier/util/shaded/org/jsoup/safety/Cleaner$CleaningVisitor of class coursier/util/shaded/org/jsoup/safety/Cleaner
  private static #13= #12 of #9;          // ElementMeta=class coursier/util/shaded/org/jsoup/safety/Cleaner$ElementMeta of class coursier/util/shaded/org/jsoup/safety/Cleaner
  static #15;                             // class coursier/util/shaded/org/jsoup/safety/Cleaner$1
SourceFile: "Cleaner.java"
