Classfile /Users/mw/Projects/slang-braindump/.jar/jar8/assemble/slang-braindump/assemble/content/scala/compat/java8/DurationConverters$.class
  Last modified May 29, 2022; size 3656 bytes
  SHA-256 checksum 3fdcef3b6240b4ead6bdfe885c55177047325d82239e9a2f3e825eda91c53742
  Compiled from "DurationConverters.scala"
public final class scala.compat.java8.DurationConverters$
  minor version: 0
  major version: 52
  flags: (0x0031) ACC_PUBLIC, ACC_FINAL, ACC_SUPER
  this_class: #2                          // scala/compat/java8/DurationConverters$
  super_class: #4                         // java/lang/Object
  interfaces: 0, fields: 1, methods: 6, attributes: 3
Constant pool:
    #1 = Utf8               scala/compat/java8/DurationConverters$
    #2 = Class              #1            // scala/compat/java8/DurationConverters$
    #3 = Utf8               java/lang/Object
    #4 = Class              #3            // java/lang/Object
    #5 = Utf8               DurationConverters.scala
    #6 = Utf8               MODULE$
    #7 = Utf8               Lscala/compat/java8/DurationConverters$;
    #8 = Utf8               <clinit>
    #9 = Utf8               ()V
   #10 = Utf8               <init>
   #11 = NameAndType        #10:#9        // "<init>":()V
   #12 = Methodref          #2.#11        // scala/compat/java8/DurationConverters$."<init>":()V
   #13 = NameAndType        #6:#7         // MODULE$:Lscala/compat/java8/DurationConverters$;
   #14 = Fieldref           #2.#13        // scala/compat/java8/DurationConverters$.MODULE$:Lscala/compat/java8/DurationConverters$;
   #15 = Utf8               toScala
   #16 = Utf8               (Ljava/time/Duration;)Lscala/concurrent/duration/FiniteDuration;
   #17 = Utf8               duration
   #18 = Utf8               java/lang/ArithmeticException
   #19 = Class              #18           // java/lang/ArithmeticException
   #20 = Utf8               java/time/Duration
   #21 = Class              #20           // java/time/Duration
   #22 = Utf8               getSeconds
   #23 = Utf8               ()J
   #24 = NameAndType        #22:#23       // getSeconds:()J
   #25 = Methodref          #21.#24       // java/time/Duration.getSeconds:()J
   #26 = Utf8               getNano
   #27 = Utf8               ()I
   #28 = NameAndType        #26:#27       // getNano:()I
   #29 = Methodref          #21.#28       // java/time/Duration.getNano:()I
   #30 = Utf8               scala/concurrent/duration/Duration$
   #31 = Class              #30           // scala/concurrent/duration/Duration$
   #32 = Utf8               Lscala/concurrent/duration/Duration$;
   #33 = NameAndType        #6:#32        // MODULE$:Lscala/concurrent/duration/Duration$;
   #34 = Fieldref           #31.#33       // scala/concurrent/duration/Duration$.MODULE$:Lscala/concurrent/duration/Duration$;
   #35 = Utf8               Zero
   #36 = Utf8               ()Lscala/concurrent/duration/FiniteDuration;
   #37 = NameAndType        #35:#36       // Zero:()Lscala/concurrent/duration/FiniteDuration;
   #38 = Methodref          #31.#37       // scala/concurrent/duration/Duration$.Zero:()Lscala/concurrent/duration/FiniteDuration;
   #39 = Utf8               scala/concurrent/duration/FiniteDuration$
   #40 = Class              #39           // scala/concurrent/duration/FiniteDuration$
   #41 = Utf8               Lscala/concurrent/duration/FiniteDuration$;
   #42 = NameAndType        #6:#41        // MODULE$:Lscala/concurrent/duration/FiniteDuration$;
   #43 = Fieldref           #40.#42       // scala/concurrent/duration/FiniteDuration$.MODULE$:Lscala/concurrent/duration/FiniteDuration$;
   #44 = Utf8               java/util/concurrent/TimeUnit
   #45 = Class              #44           // java/util/concurrent/TimeUnit
   #46 = Utf8               SECONDS
   #47 = Utf8               Ljava/util/concurrent/TimeUnit;
   #48 = NameAndType        #46:#47       // SECONDS:Ljava/util/concurrent/TimeUnit;
   #49 = Fieldref           #45.#48       // java/util/concurrent/TimeUnit.SECONDS:Ljava/util/concurrent/TimeUnit;
   #50 = Utf8               apply
   #51 = Utf8               (JLjava/util/concurrent/TimeUnit;)Lscala/concurrent/duration/FiniteDuration;
   #52 = NameAndType        #50:#51       // apply:(JLjava/util/concurrent/TimeUnit;)Lscala/concurrent/duration/FiniteDuration;
   #53 = Methodref          #40.#52       // scala/concurrent/duration/FiniteDuration$.apply:(JLjava/util/concurrent/TimeUnit;)Lscala/concurrent/duration/FiniteDuration;
   #54 = Utf8               scala/Int$
   #55 = Class              #54           // scala/Int$
   #56 = Utf8               Lscala/Int$;
   #57 = NameAndType        #6:#56        // MODULE$:Lscala/Int$;
   #58 = Fieldref           #55.#57       // scala/Int$.MODULE$:Lscala/Int$;
   #59 = Utf8               int2long
   #60 = Utf8               (I)J
   #61 = NameAndType        #59:#60       // int2long:(I)J
   #62 = Methodref          #55.#61       // scala/Int$.int2long:(I)J
   #63 = Utf8               NANOSECONDS
   #64 = NameAndType        #63:#47       // NANOSECONDS:Ljava/util/concurrent/TimeUnit;
   #65 = Fieldref           #45.#64       // java/util/concurrent/TimeUnit.NANOSECONDS:Ljava/util/concurrent/TimeUnit;
   #66 = Long               1000000000l
   #68 = Utf8               java/lang/Math
   #69 = Class              #68           // java/lang/Math
   #70 = Utf8               multiplyExact
   #71 = Utf8               (JJ)J
   #72 = NameAndType        #70:#71       // multiplyExact:(JJ)J
   #73 = Methodref          #69.#72       // java/lang/Math.multiplyExact:(JJ)J
   #74 = Methodref          #19.#11       // java/lang/ArithmeticException."<init>":()V
   #75 = Utf8               java/lang/IllegalArgumentException
   #76 = Class              #75           // java/lang/IllegalArgumentException
   #77 = Utf8               java/lang/StringBuilder
   #78 = Class              #77           // java/lang/StringBuilder
   #79 = Integer            54
   #80 = Utf8               (I)V
   #81 = NameAndType        #10:#80       // "<init>":(I)V
   #82 = Methodref          #78.#81       // java/lang/StringBuilder."<init>":(I)V
   #83 = Utf8               Java duration
   #84 = String             #83           // Java duration
   #85 = Utf8               append
   #86 = Utf8               (Ljava/lang/String;)Ljava/lang/StringBuilder;
   #87 = NameAndType        #85:#86       // append:(Ljava/lang/String;)Ljava/lang/StringBuilder;
   #88 = Methodref          #78.#87       // java/lang/StringBuilder.append:(Ljava/lang/String;)Ljava/lang/StringBuilder;
   #89 = Utf8               (Ljava/lang/Object;)Ljava/lang/StringBuilder;
   #90 = NameAndType        #85:#89       // append:(Ljava/lang/Object;)Ljava/lang/StringBuilder;
   #91 = Methodref          #78.#90       // java/lang/StringBuilder.append:(Ljava/lang/Object;)Ljava/lang/StringBuilder;
   #92 = Utf8                cannot be expressed as a Scala duration
   #93 = String             #92           //  cannot be expressed as a Scala duration
   #94 = Utf8               toString
   #95 = Utf8               ()Ljava/lang/String;
   #96 = NameAndType        #94:#95       // toString:()Ljava/lang/String;
   #97 = Methodref          #78.#96       // java/lang/StringBuilder.toString:()Ljava/lang/String;
   #98 = Utf8               (Ljava/lang/String;)V
   #99 = NameAndType        #10:#98       // "<init>":(Ljava/lang/String;)V
  #100 = Methodref          #76.#99       // java/lang/IllegalArgumentException."<init>":(Ljava/lang/String;)V
  #101 = Utf8               secondsAsNanos
  #102 = Utf8               J
  #103 = Utf8               totalNanos
  #104 = Utf8               originalSeconds
  #105 = Utf8               originalNanos
  #106 = Utf8               I
  #107 = Utf8               this
  #108 = Utf8               Ljava/time/Duration;
  #109 = Utf8               scala/concurrent/duration/FiniteDuration
  #110 = Class              #109          // scala/concurrent/duration/FiniteDuration
  #111 = Utf8               toJava
  #112 = Utf8               (Lscala/concurrent/duration/FiniteDuration;)Ljava/time/Duration;
  #113 = Utf8               length
  #114 = NameAndType        #113:#23      // length:()J
  #115 = Methodref          #110.#114     // scala/concurrent/duration/FiniteDuration.length:()J
  #116 = Utf8               ZERO
  #117 = NameAndType        #116:#108     // ZERO:Ljava/time/Duration;
  #118 = Fieldref           #21.#117      // java/time/Duration.ZERO:Ljava/time/Duration;
  #119 = Utf8               unit
  #120 = Utf8               ()Ljava/util/concurrent/TimeUnit;
  #121 = NameAndType        #119:#120     // unit:()Ljava/util/concurrent/TimeUnit;
  #122 = Methodref          #110.#121     // scala/concurrent/duration/FiniteDuration.unit:()Ljava/util/concurrent/TimeUnit;
  #123 = Utf8               equals
  #124 = Utf8               (Ljava/lang/Object;)Z
  #125 = NameAndType        #123:#124     // equals:(Ljava/lang/Object;)Z
  #126 = Methodref          #4.#125       // java/lang/Object.equals:(Ljava/lang/Object;)Z
  #127 = Utf8               ofNanos
  #128 = Utf8               (J)Ljava/time/Duration;
  #129 = NameAndType        #127:#128     // ofNanos:(J)Ljava/time/Duration;
  #130 = Methodref          #21.#129      // java/time/Duration.ofNanos:(J)Ljava/time/Duration;
  #131 = Utf8               MICROSECONDS
  #132 = NameAndType        #131:#47      // MICROSECONDS:Ljava/util/concurrent/TimeUnit;
  #133 = Fieldref           #45.#132      // java/util/concurrent/TimeUnit.MICROSECONDS:Ljava/util/concurrent/TimeUnit;
  #134 = Utf8               java/time/temporal/ChronoUnit
  #135 = Class              #134          // java/time/temporal/ChronoUnit
  #136 = Utf8               MICROS
  #137 = Utf8               Ljava/time/temporal/ChronoUnit;
  #138 = NameAndType        #136:#137     // MICROS:Ljava/time/temporal/ChronoUnit;
  #139 = Fieldref           #135.#138     // java/time/temporal/ChronoUnit.MICROS:Ljava/time/temporal/ChronoUnit;
  #140 = Utf8               of
  #141 = Utf8               (JLjava/time/temporal/TemporalUnit;)Ljava/time/Duration;
  #142 = NameAndType        #140:#141     // of:(JLjava/time/temporal/TemporalUnit;)Ljava/time/Duration;
  #143 = Methodref          #21.#142      // java/time/Duration.of:(JLjava/time/temporal/TemporalUnit;)Ljava/time/Duration;
  #144 = Utf8               MILLISECONDS
  #145 = NameAndType        #144:#47      // MILLISECONDS:Ljava/util/concurrent/TimeUnit;
  #146 = Fieldref           #45.#145      // java/util/concurrent/TimeUnit.MILLISECONDS:Ljava/util/concurrent/TimeUnit;
  #147 = Utf8               ofMillis
  #148 = NameAndType        #147:#128     // ofMillis:(J)Ljava/time/Duration;
  #149 = Methodref          #21.#148      // java/time/Duration.ofMillis:(J)Ljava/time/Duration;
  #150 = Utf8               ofSeconds
  #151 = NameAndType        #150:#128     // ofSeconds:(J)Ljava/time/Duration;
  #152 = Methodref          #21.#151      // java/time/Duration.ofSeconds:(J)Ljava/time/Duration;
  #153 = Utf8               MINUTES
  #154 = NameAndType        #153:#47      // MINUTES:Ljava/util/concurrent/TimeUnit;
  #155 = Fieldref           #45.#154      // java/util/concurrent/TimeUnit.MINUTES:Ljava/util/concurrent/TimeUnit;
  #156 = Utf8               ofMinutes
  #157 = NameAndType        #156:#128     // ofMinutes:(J)Ljava/time/Duration;
  #158 = Methodref          #21.#157      // java/time/Duration.ofMinutes:(J)Ljava/time/Duration;
  #159 = Utf8               HOURS
  #160 = NameAndType        #159:#47      // HOURS:Ljava/util/concurrent/TimeUnit;
  #161 = Fieldref           #45.#160      // java/util/concurrent/TimeUnit.HOURS:Ljava/util/concurrent/TimeUnit;
  #162 = Utf8               ofHours
  #163 = NameAndType        #162:#128     // ofHours:(J)Ljava/time/Duration;
  #164 = Methodref          #21.#163      // java/time/Duration.ofHours:(J)Ljava/time/Duration;
  #165 = Utf8               DAYS
  #166 = NameAndType        #165:#47      // DAYS:Ljava/util/concurrent/TimeUnit;
  #167 = Fieldref           #45.#166      // java/util/concurrent/TimeUnit.DAYS:Ljava/util/concurrent/TimeUnit;
  #168 = Utf8               ofDays
  #169 = NameAndType        #168:#128     // ofDays:(J)Ljava/time/Duration;
  #170 = Methodref          #21.#169      // java/time/Duration.ofDays:(J)Ljava/time/Duration;
  #171 = Utf8               scala/MatchError
  #172 = Class              #171          // scala/MatchError
  #173 = Utf8               (Ljava/lang/Object;)V
  #174 = NameAndType        #10:#173      // "<init>":(Ljava/lang/Object;)V
  #175 = Methodref          #172.#174     // scala/MatchError."<init>":(Ljava/lang/Object;)V
  #176 = Utf8               Lscala/concurrent/duration/FiniteDuration;
  #177 = Utf8               DurationOps
  #178 = Utf8               (Ljava/time/Duration;)Ljava/time/Duration;
  #179 = Utf8               FiniteDurationops
  #180 = Utf8               (Lscala/concurrent/duration/FiniteDuration;)Lscala/concurrent/duration/FiniteDuration;
  #181 = Methodref          #4.#11        // java/lang/Object."<init>":()V
  #182 = Utf8               Code
  #183 = Utf8               LineNumberTable
  #184 = Utf8               StackMapTable
  #185 = Utf8               LocalVariableTable
  #186 = Utf8               MethodParameters
  #187 = Utf8               SourceFile
  #188 = Utf8               ScalaInlineInfo
  #189 = Utf8               Scala
{
  public static final scala.compat.java8.DurationConverters$ MODULE$;
    descriptor: Lscala/compat/java8/DurationConverters$;
    flags: (0x0019) ACC_PUBLIC, ACC_STATIC, ACC_FINAL

  public static {};
    descriptor: ()V
    flags: (0x0009) ACC_PUBLIC, ACC_STATIC
    Code:
      stack=2, locals=0, args_size=0
         0: new           #2                  // class scala/compat/java8/DurationConverters$
         3: dup
         4: invokespecial #12                 // Method "<init>":()V
         7: putstatic     #14                 // Field MODULE$:Lscala/compat/java8/DurationConverters$;
        10: return
      LineNumberTable:
        line 27: 0

  public final scala.concurrent.duration.FiniteDuration toScala(java.time.Duration);
    descriptor: (Ljava/time/Duration;)Lscala/concurrent/duration/FiniteDuration;
    flags: (0x0011) ACC_PUBLIC, ACC_FINAL
    Code:
      stack=5, locals=9, args_size=2
         0: aload_1
         1: invokevirtual #25                 // Method java/time/Duration.getSeconds:()J
         4: lstore_2
         5: aload_1
         6: invokevirtual #29                 // Method java/time/Duration.getNano:()I
         9: istore        4
        11: iload         4
        13: iconst_0
        14: if_icmpne     45
        17: lload_2
        18: lconst_0
        19: lcmp
        20: ifne          32
        23: getstatic     #34                 // Field scala/concurrent/duration/Duration$.MODULE$:Lscala/concurrent/duration/Duration$;
        26: invokevirtual #38                 // Method scala/concurrent/duration/Duration$.Zero:()Lscala/concurrent/duration/FiniteDuration;
        29: goto          42
        32: getstatic     #43                 // Field scala/concurrent/duration/FiniteDuration$.MODULE$:Lscala/concurrent/duration/FiniteDuration$;
        35: lload_2
        36: getstatic     #49                 // Field java/util/concurrent/TimeUnit.SECONDS:Ljava/util/concurrent/TimeUnit;
        39: invokevirtual #53                 // Method scala/concurrent/duration/FiniteDuration$.apply:(JLjava/util/concurrent/TimeUnit;)Lscala/concurrent/duration/FiniteDuration;
        42: goto          176
        45: lload_2
        46: lconst_0
        47: lcmp
        48: ifne          71
        51: getstatic     #43                 // Field scala/concurrent/duration/FiniteDuration$.MODULE$:Lscala/concurrent/duration/FiniteDuration$;
        54: getstatic     #58                 // Field scala/Int$.MODULE$:Lscala/Int$;
        57: iload         4
        59: invokevirtual #62                 // Method scala/Int$.int2long:(I)J
        62: getstatic     #65                 // Field java/util/concurrent/TimeUnit.NANOSECONDS:Ljava/util/concurrent/TimeUnit;
        65: invokevirtual #53                 // Method scala/concurrent/duration/FiniteDuration$.apply:(JLjava/util/concurrent/TimeUnit;)Lscala/concurrent/duration/FiniteDuration;
        68: goto          176
        71: lload_2
        72: ldc2_w        #66                 // long 1000000000l
        75: invokestatic  #73                 // Method java/lang/Math.multiplyExact:(JJ)J
        78: lstore        5
        80: lload         5
        82: iload         4
        84: i2l
        85: ladd
        86: lstore        7
        88: lload         7
        90: lconst_0
        91: lcmp
        92: ifge          102
        95: lload         5
        97: lconst_0
        98: lcmp
        99: iflt          116
       102: lload         7
       104: lconst_0
       105: lcmp
       106: ifle          130
       109: lload         5
       111: lconst_0
       112: lcmp
       113: ifle          130
       116: getstatic     #43                 // Field scala/concurrent/duration/FiniteDuration$.MODULE$:Lscala/concurrent/duration/FiniteDuration$;
       119: lload         7
       121: getstatic     #65                 // Field java/util/concurrent/TimeUnit.NANOSECONDS:Ljava/util/concurrent/TimeUnit;
       124: invokevirtual #53                 // Method scala/concurrent/duration/FiniteDuration$.apply:(JLjava/util/concurrent/TimeUnit;)Lscala/concurrent/duration/FiniteDuration;
       127: goto          138
       130: new           #19                 // class java/lang/ArithmeticException
       133: dup
       134: invokespecial #74                 // Method java/lang/ArithmeticException."<init>":()V
       137: athrow
       138: goto          176
       141: pop
       142: new           #76                 // class java/lang/IllegalArgumentException
       145: dup
       146: new           #78                 // class java/lang/StringBuilder
       149: dup
       150: ldc           #79                 // int 54
       152: invokespecial #82                 // Method java/lang/StringBuilder."<init>":(I)V
       155: ldc           #84                 // String Java duration
       157: invokevirtual #88                 // Method java/lang/StringBuilder.append:(Ljava/lang/String;)Ljava/lang/StringBuilder;
       160: aload_1
       161: invokevirtual #91                 // Method java/lang/StringBuilder.append:(Ljava/lang/Object;)Ljava/lang/StringBuilder;
       164: ldc           #93                 // String  cannot be expressed as a Scala duration
       166: invokevirtual #88                 // Method java/lang/StringBuilder.append:(Ljava/lang/String;)Ljava/lang/StringBuilder;
       169: invokevirtual #97                 // Method java/lang/StringBuilder.toString:()Ljava/lang/String;
       172: invokespecial #100                // Method java/lang/IllegalArgumentException."<init>":(Ljava/lang/String;)V
       175: athrow
       176: areturn
      Exception table:
         from    to  target type
            71   138   141   Class java/lang/ArithmeticException
      StackMapTable: number_of_entries = 10
        frame_type = 253 /* append */
          offset_delta = 32
          locals = [ long, int ]
        frame_type = 73 /* same_locals_1_stack_item */
          stack = [ class scala/concurrent/duration/FiniteDuration ]
        frame_type = 2 /* same */
        frame_type = 25 /* same */
        frame_type = 253 /* append */
          offset_delta = 30
          locals = [ long, long ]
        frame_type = 13 /* same */
        frame_type = 13 /* same */
        frame_type = 71 /* same_locals_1_stack_item */
          stack = [ class scala/concurrent/duration/FiniteDuration ]
        frame_type = 255 /* full_frame */
          offset_delta = 2
          locals = [ class scala/compat/java8/DurationConverters$, class java/time/Duration, long, int ]
          stack = [ class java/lang/ArithmeticException ]
        frame_type = 98 /* same_locals_1_stack_item */
          stack = [ class scala/concurrent/duration/FiniteDuration ]
      LineNumberTable:
        line 38: 0
        line 39: 5
        line 40: 11
        line 41: 17
        line 42: 32
        line 43: 45
        line 44: 51
        line 47: 71
        line 48: 80
        line 49: 88
        line 50: 130
        line 52: 142
      LocalVariableTable:
        Start  Length  Slot  Name   Signature
           80      58     5 secondsAsNanos   J
           88      50     7 totalNanos   J
            5     171     2 originalSeconds   J
           11     165     4 originalNanos   I
            0     177     0  this   Lscala/compat/java8/DurationConverters$;
            0     177     1 duration   Ljava/time/Duration;
    MethodParameters:
      Name                           Flags
      duration                       final

  public final java.time.Duration toJava(scala.concurrent.duration.FiniteDuration);
    descriptor: (Lscala/concurrent/duration/FiniteDuration;)Ljava/time/Duration;
    flags: (0x0011) ACC_PUBLIC, ACC_FINAL
    Code:
      stack=4, locals=4, args_size=2
         0: aload_1
         1: invokevirtual #115                // Method scala/concurrent/duration/FiniteDuration.length:()J
         4: lconst_0
         5: lcmp
         6: ifne          15
         9: getstatic     #118                // Field java/time/Duration.ZERO:Ljava/time/Duration;
        12: goto          201
        15: aload_1
        16: invokevirtual #122                // Method scala/concurrent/duration/FiniteDuration.unit:()Ljava/util/concurrent/TimeUnit;
        19: astore_3
        20: getstatic     #65                 // Field java/util/concurrent/TimeUnit.NANOSECONDS:Ljava/util/concurrent/TimeUnit;
        23: aload_3
        24: invokevirtual #126                // Method java/lang/Object.equals:(Ljava/lang/Object;)Z
        27: ifeq          41
        30: aload_1
        31: invokevirtual #115                // Method scala/concurrent/duration/FiniteDuration.length:()J
        34: invokestatic  #130                // Method java/time/Duration.ofNanos:(J)Ljava/time/Duration;
        37: astore_2
        38: goto          200
        41: goto          44
        44: getstatic     #133                // Field java/util/concurrent/TimeUnit.MICROSECONDS:Ljava/util/concurrent/TimeUnit;
        47: aload_3
        48: invokevirtual #126                // Method java/lang/Object.equals:(Ljava/lang/Object;)Z
        51: ifeq          68
        54: aload_1
        55: invokevirtual #115                // Method scala/concurrent/duration/FiniteDuration.length:()J
        58: getstatic     #139                // Field java/time/temporal/ChronoUnit.MICROS:Ljava/time/temporal/ChronoUnit;
        61: invokestatic  #143                // Method java/time/Duration.of:(JLjava/time/temporal/TemporalUnit;)Ljava/time/Duration;
        64: astore_2
        65: goto          200
        68: goto          71
        71: getstatic     #146                // Field java/util/concurrent/TimeUnit.MILLISECONDS:Ljava/util/concurrent/TimeUnit;
        74: aload_3
        75: invokevirtual #126                // Method java/lang/Object.equals:(Ljava/lang/Object;)Z
        78: ifeq          92
        81: aload_1
        82: invokevirtual #115                // Method scala/concurrent/duration/FiniteDuration.length:()J
        85: invokestatic  #149                // Method java/time/Duration.ofMillis:(J)Ljava/time/Duration;
        88: astore_2
        89: goto          200
        92: goto          95
        95: getstatic     #49                 // Field java/util/concurrent/TimeUnit.SECONDS:Ljava/util/concurrent/TimeUnit;
        98: aload_3
        99: invokevirtual #126                // Method java/lang/Object.equals:(Ljava/lang/Object;)Z
       102: ifeq          116
       105: aload_1
       106: invokevirtual #115                // Method scala/concurrent/duration/FiniteDuration.length:()J
       109: invokestatic  #152                // Method java/time/Duration.ofSeconds:(J)Ljava/time/Duration;
       112: astore_2
       113: goto          200
       116: goto          119
       119: getstatic     #155                // Field java/util/concurrent/TimeUnit.MINUTES:Ljava/util/concurrent/TimeUnit;
       122: aload_3
       123: invokevirtual #126                // Method java/lang/Object.equals:(Ljava/lang/Object;)Z
       126: ifeq          140
       129: aload_1
       130: invokevirtual #115                // Method scala/concurrent/duration/FiniteDuration.length:()J
       133: invokestatic  #158                // Method java/time/Duration.ofMinutes:(J)Ljava/time/Duration;
       136: astore_2
       137: goto          200
       140: goto          143
       143: getstatic     #161                // Field java/util/concurrent/TimeUnit.HOURS:Ljava/util/concurrent/TimeUnit;
       146: aload_3
       147: invokevirtual #126                // Method java/lang/Object.equals:(Ljava/lang/Object;)Z
       150: ifeq          164
       153: aload_1
       154: invokevirtual #115                // Method scala/concurrent/duration/FiniteDuration.length:()J
       157: invokestatic  #164                // Method java/time/Duration.ofHours:(J)Ljava/time/Duration;
       160: astore_2
       161: goto          200
       164: goto          167
       167: getstatic     #167                // Field java/util/concurrent/TimeUnit.DAYS:Ljava/util/concurrent/TimeUnit;
       170: aload_3
       171: invokevirtual #126                // Method java/lang/Object.equals:(Ljava/lang/Object;)Z
       174: ifeq          188
       177: aload_1
       178: invokevirtual #115                // Method scala/concurrent/duration/FiniteDuration.length:()J
       181: invokestatic  #170                // Method java/time/Duration.ofDays:(J)Ljava/time/Duration;
       184: astore_2
       185: goto          200
       188: goto          191
       191: new           #172                // class scala/MatchError
       194: dup
       195: aload_3
       196: invokespecial #175                // Method scala/MatchError."<init>":(Ljava/lang/Object;)V
       199: athrow
       200: aload_2
       201: areturn
      StackMapTable: number_of_entries = 17
        frame_type = 15 /* same */
        frame_type = 253 /* append */
          offset_delta = 25
          locals = [ top, class java/util/concurrent/TimeUnit ]
        frame_type = 2 /* same */
        frame_type = 23 /* same */
        frame_type = 2 /* same */
        frame_type = 20 /* same */
        frame_type = 2 /* same */
        frame_type = 20 /* same */
        frame_type = 2 /* same */
        frame_type = 20 /* same */
        frame_type = 2 /* same */
        frame_type = 20 /* same */
        frame_type = 2 /* same */
        frame_type = 20 /* same */
        frame_type = 2 /* same */
        frame_type = 255 /* full_frame */
          offset_delta = 8
          locals = [ class scala/compat/java8/DurationConverters$, class scala/concurrent/duration/FiniteDuration, class java/time/Duration, class java/util/concurrent/TimeUnit ]
          stack = []
        frame_type = 255 /* full_frame */
          offset_delta = 0
          locals = [ class scala/compat/java8/DurationConverters$, class scala/concurrent/duration/FiniteDuration ]
          stack = [ class java/time/Duration ]
      LineNumberTable:
        line 62: 0
        line 63: 15
        line 64: 20
        line 65: 44
        line 66: 71
        line 67: 95
        line 68: 119
        line 69: 143
        line 70: 167
        line 63: 191
      LocalVariableTable:
        Start  Length  Slot  Name   Signature
            0     202     0  this   Lscala/compat/java8/DurationConverters$;
            0     202     1 duration   Lscala/concurrent/duration/FiniteDuration;
    MethodParameters:
      Name                           Flags
      duration                       final

  public final java.time.Duration DurationOps(java.time.Duration);
    descriptor: (Ljava/time/Duration;)Ljava/time/Duration;
    flags: (0x0011) ACC_PUBLIC, ACC_FINAL
    Code:
      stack=1, locals=2, args_size=2
         0: aload_1
         1: areturn
      LineNumberTable:
        line 74: 0
      LocalVariableTable:
        Start  Length  Slot  Name   Signature
            0       2     0  this   Lscala/compat/java8/DurationConverters$;
            0       2     1 duration   Ljava/time/Duration;
    MethodParameters:
      Name                           Flags
      duration                       final

  public final scala.concurrent.duration.FiniteDuration FiniteDurationops(scala.concurrent.duration.FiniteDuration);
    descriptor: (Lscala/concurrent/duration/FiniteDuration;)Lscala/concurrent/duration/FiniteDuration;
    flags: (0x0011) ACC_PUBLIC, ACC_FINAL
    Code:
      stack=1, locals=2, args_size=2
         0: aload_1
         1: areturn
      LineNumberTable:
        line 81: 0
      LocalVariableTable:
        Start  Length  Slot  Name   Signature
            0       2     0  this   Lscala/compat/java8/DurationConverters$;
            0       2     1 duration   Lscala/concurrent/duration/FiniteDuration;
    MethodParameters:
      Name                           Flags
      duration                       final

  private scala.compat.java8.DurationConverters$();
    descriptor: ()V
    flags: (0x0002) ACC_PRIVATE
    Code:
      stack=1, locals=1, args_size=1
         0: aload_0
         1: invokespecial #181                // Method java/lang/Object."<init>":()V
         4: return
      LineNumberTable:
        line 88: 0
        line 27: 4
      LocalVariableTable:
        Start  Length  Slot  Name   Signature
            0       5     0  this   Lscala/compat/java8/DurationConverters$;
}
SourceFile: "DurationConverters.scala"
  ScalaInlineInfo: length = 0x1D (unknown attribute)
   01 01 00 05 00 0A 00 09 01 00 B1 00 B2 01 00 B3
   00 B4 01 00 6F 00 70 01 00 0F 00 10 01
  Scala: length = 0x0 (unknown attribute)

