Classfile /Users/mw/Projects/slang-braindump/.jar/jar8/assemble/slang-braindump/assemble/content/scala/compat/java8/Priority3FunctionConverters.class
  Last modified May 29, 2022; size 1507 bytes
  SHA-256 checksum c027e33ce2f94ba4a2172d77298744bb63cb8fd46af340f79e5e236eafd596af
  Compiled from "FunctionConverters.scala"
public interface scala.compat.java8.Priority3FunctionConverters
  minor version: 0
  major version: 52
  flags: (0x0601) ACC_PUBLIC, ACC_INTERFACE, ACC_ABSTRACT
  this_class: #2                          // scala/compat/java8/Priority3FunctionConverters
  super_class: #4                         // java/lang/Object
  interfaces: 0, fields: 0, methods: 3, attributes: 4
Constant pool:
   #1 = Utf8               scala/compat/java8/Priority3FunctionConverters
   #2 = Class              #1             // scala/compat/java8/Priority3FunctionConverters
   #3 = Utf8               java/lang/Object
   #4 = Class              #3             // java/lang/Object
   #5 = Utf8               FunctionConverters.scala
   #6 = Utf8               Lscala/reflect/ScalaSignature;
   #7 = Utf8               bytes
   #8 = Utf8               \u0006\u0005a2qa\u0001\u0003\u0011\u0002\u0007\u00051\u0002C\u0003\u0011\u0001\u0011\u0005\u0011\u0003C\u0003\u0016\u0001\u0011\raCA\u000eQe&|\'/\u001b;zg\u0019+hn\u0019;j_:\u001cuN\u001c<feR,\'o\u001d\u0006\u0003\u000b\u0019\tQA[1wCbR!a\u0002\u0005\u0002\r\r|W\u000e]1u\u0015\u0005I\u0011!B:dC2\f7\u0001A\n\u0003\u00011\u0001\"!\u0004\b\u000e\u0003!I!a\u0004\u0005\u0003\r\u0005s\u0017PU3g\u0003\u0019!\u0013N\\5uIQ\t!\u0003\u0005\u0002\u000e\'%\u0011A\u0003\u0003\u0002\u0005+:LG/\u0001\ff]JL7\r[!t\u0015\u00064\u0018MQ5Gk:\u001cG/[8o+\u00119\u0002EK\u0017\u0015\u0005ay\u0003#B\r\u001d=%bS\"\u0001\u000e\u000b\u0005m!\u0011A\u00064v]\u000e$\u0018n\u001c8D_:4XM\u001d;fe&k\u0007\u000f\\:\n\u0005uQ\"!\u0007*jG\"4UO\\2uS>t\'\'Q:CS\u001a+hn\u0019;j_:\u0004\"a\b\u0011\r\u0001\u0011)\u0011E\u0001b\u0001E\t\tA+\u0005\u0002$MA\u0011Q\u0002J\u0005\u0003K!\u0011qAT8uQ&tw\r\u0005\u0002\u000eO%\u0011\u0001\u0006\u0003\u0002\u0004\u0003:L\bCA\u0010+\t\u0015Y#A1\u0001#\u0005\u0005)\u0006CA\u0010.\t\u0015q#A1\u0001#\u0005\u0005\u0011\u0006\"\u0002\u0019\u0003\u0001\u0004\t\u0014AA:g!\u0015i!GH\u0015-\u0013\t\u0019\u0004BA\u0005Gk:\u001cG/[8oe!\u0012!!\u000e\t\u0003\u001bYJ!a\u000e\u0005\u0003\r%tG.\u001b8f\u0001
   #9 = Utf8               enrichAsJavaBiFunction$
  #10 = Utf8               (Lscala/compat/java8/Priority3FunctionConverters;Lscala/Function2;)Lscala/Function2;
  #11 = Utf8               $this
  #12 = Utf8               sf
  #13 = Utf8               enrichAsJavaBiFunction
  #14 = Utf8               (Lscala/Function2;)Lscala/Function2;
  #15 = NameAndType        #13:#14        // enrichAsJavaBiFunction:(Lscala/Function2;)Lscala/Function2;
  #16 = InterfaceMethodref #2.#15         // scala/compat/java8/Priority3FunctionConverters.enrichAsJavaBiFunction:(Lscala/Function2;)Lscala/Function2;
  #17 = Utf8               Lscala/compat/java8/Priority3FunctionConverters;
  #18 = Utf8               Lscala/Function2;
  #19 = Utf8               <T:Ljava/lang/Object;U:Ljava/lang/Object;R:Ljava/lang/Object;>(Lscala/Function2<TT;TU;TR;>;)Lscala/Function2<TT;TU;TR;>;
  #20 = Utf8               this
  #21 = Utf8               $init$
  #22 = Utf8               (Lscala/compat/java8/Priority3FunctionConverters;)V
  #23 = Utf8               Code
  #24 = Utf8               LineNumberTable
  #25 = Utf8               LocalVariableTable
  #26 = Utf8               MethodParameters
  #27 = Utf8               Signature
  #28 = Utf8               SourceFile
  #29 = Utf8               RuntimeVisibleAnnotations
  #30 = Utf8               ScalaInlineInfo
  #31 = Utf8               ScalaSig
{
  public static scala.Function2 enrichAsJavaBiFunction$(scala.compat.java8.Priority3FunctionConverters, scala.Function2);
    descriptor: (Lscala/compat/java8/Priority3FunctionConverters;Lscala/Function2;)Lscala/Function2;
    flags: (0x1009) ACC_PUBLIC, ACC_STATIC, ACC_SYNTHETIC
    Code:
      stack=2, locals=2, args_size=2
         0: aload_0
         1: aload_1
         2: invokespecial #16                 // InterfaceMethod enrichAsJavaBiFunction:(Lscala/Function2;)Lscala/Function2;
         5: areturn
      LineNumberTable:
        line 748: 0
      LocalVariableTable:
        Start  Length  Slot  Name   Signature
            0       6     0 $this   Lscala/compat/java8/Priority3FunctionConverters;
            0       6     1    sf   Lscala/Function2;
    MethodParameters:
      Name                           Flags
      $this                          final synthetic
      sf                             final

  public default <T extends java.lang.Object, U extends java.lang.Object, R extends java.lang.Object> scala.Function2<T, U, R> enrichAsJavaBiFunction(scala.Function2<T, U, R>);
    descriptor: (Lscala/Function2;)Lscala/Function2;
    flags: (0x0001) ACC_PUBLIC
    Code:
      stack=1, locals=2, args_size=2
         0: aload_1
         1: areturn
      LineNumberTable:
        line 748: 0
      LocalVariableTable:
        Start  Length  Slot  Name   Signature
            0       2     0  this   Lscala/compat/java8/Priority3FunctionConverters;
            0       2     1    sf   Lscala/Function2;
    Signature: #19                          // <T:Ljava/lang/Object;U:Ljava/lang/Object;R:Ljava/lang/Object;>(Lscala/Function2<TT;TU;TR;>;)Lscala/Function2<TT;TU;TR;>;
    MethodParameters:
      Name                           Flags
      sf                             final

  public static void $init$(scala.compat.java8.Priority3FunctionConverters);
    descriptor: (Lscala/compat/java8/Priority3FunctionConverters;)V
    flags: (0x0009) ACC_PUBLIC, ACC_STATIC
    Code:
      stack=0, locals=1, args_size=1
         0: return
      LineNumberTable:
        line 745: 0
      LocalVariableTable:
        Start  Length  Slot  Name   Signature
            0       1     0 $this   Lscala/compat/java8/Priority3FunctionConverters;
    MethodParameters:
      Name                           Flags
      $this                          final synthetic
}
SourceFile: "FunctionConverters.scala"
RuntimeVisibleAnnotations:
  0: #6(#7=s#8)
    scala.reflect.ScalaSignature(
      bytes="\u0006\u0005a2qa\u0001\u0003\u0011\u0002\u0007\u00051\u0002C\u0003\u0011\u0001\u0011\u0005\u0011\u0003C\u0003\u0016\u0001\u0011\raCA\u000eQe&|\'/\u001b;zg\u0019+hn\u0019;j_:\u001cuN\u001c<feR,\'o\u001d\u0006\u0003\u000b\u0019\tQA[1wCbR!a\u0002\u0005\u0002\r\r|W\u000e]1u\u0015\u0005I\u0011!B:dC2\f7\u0001A\n\u0003\u00011\u0001\"!\u0004\b\u000e\u0003!I!a\u0004\u0005\u0003\r\u0005s\u0017PU3g\u0003\u0019!\u0013N\\5uIQ\t!\u0003\u0005\u0002\u000e\'%\u0011A\u0003\u0003\u0002\u0005+:LG/\u0001\ff]JL7\r[!t\u0015\u00064\u0018MQ5Gk:\u001cG/[8o+\u00119\u0002EK\u0017\u0015\u0005ay\u0003#B\r\u001d=%bS\"\u0001\u000e\u000b\u0005m!\u0011A\u00064v]\u000e$\u0018n\u001c8D_:4XM\u001d;fe&k\u0007\u000f\\:\n\u0005uQ\"!\u0007*jG\"4UO\\2uS>t\'\'Q:CS\u001a+hn\u0019;j_:\u0004\"a\b\u0011\r\u0001\u0011)\u0011E\u0001b\u0001E\t\tA+\u0005\u0002$MA\u0011Q\u0002J\u0005\u0003K!\u0011qAT8uQ&tw\r\u0005\u0002\u000eO%\u0011\u0001\u0006\u0003\u0002\u0004\u0003:L\bCA\u0010+\t\u0015Y#A1\u0001#\u0005\u0005)\u0006CA\u0010.\t\u0015q#A1\u0001#\u0005\u0005\u0011\u0006\"\u0002\u0019\u0003\u0001\u0004\t\u0014AA:g!\u0015i!GH\u0015-\u0013\t\u0019\u0004BA\u0005Gk:\u001cG/[8oe!\u0012!!\u000e\t\u0003\u001bYJ!a\u000e\u0005\u0003\r%tG.\u001b8f\u0001"
    )
  ScalaInlineInfo: length = 0x13 (unknown attribute)
   01 00 00 03 00 15 00 16 01 00 0D 00 0E 04 00 09
   00 0A 05
  ScalaSig: length = 0x3 (unknown attribute)
   05 02 00
