Classfile /Users/mw/Projects/slang-braindump/.jar/jar11/assemble/slang-braindump/assemble/content/org/scalatest/matchers/should/Matchers$ResultOfBeWordForCollectedArray.class
  Last modified May 29, 2022; size 3088 bytes
  SHA-256 checksum 22c7a778f6a423d24b7826d774cebb3a939024d3ee1f5072ff57d3e6bb7d33d3
  Compiled from "Matchers.scala"
public final class org.scalatest.matchers.should.Matchers$ResultOfBeWordForCollectedArray<T extends java.lang.Object> extends org.scalatest.matchers.should.Matchers$ResultOfBeWordForCollectedAny<java.lang.Object>
  minor version: 0
  major version: 52
  flags: (0x0031) ACC_PUBLIC, ACC_FINAL, ACC_SUPER
  this_class: #2                          // org/scalatest/matchers/should/Matchers$ResultOfBeWordForCollectedArray
  super_class: #5                         // org/scalatest/matchers/should/Matchers$ResultOfBeWordForCollectedAny
  interfaces: 0, fields: 5, methods: 3, attributes: 5
Constant pool:
    #1 = Utf8               org/scalatest/matchers/should/Matchers$ResultOfBeWordForCollectedArray
    #2 = Class              #1            // org/scalatest/matchers/should/Matchers$ResultOfBeWordForCollectedArray
    #3 = Utf8               <T:Ljava/lang/Object;>Lorg/scalatest/matchers/should/Matchers$ResultOfBeWordForCollectedAny<Ljava/lang/Object;>;
    #4 = Utf8               org/scalatest/matchers/should/Matchers$ResultOfBeWordForCollectedAny
    #5 = Class              #4            // org/scalatest/matchers/should/Matchers$ResultOfBeWordForCollectedAny
    #6 = Utf8               Matchers.scala
    #7 = Utf8               org/scalatest/matchers/should/Matchers$Collected
    #8 = Class              #7            // org/scalatest/matchers/should/Matchers$Collected
    #9 = Utf8               org/scalatest/matchers/should/Matchers
   #10 = Class              #9            // org/scalatest/matchers/should/Matchers
   #11 = Utf8               Collected
   #12 = Utf8               ResultOfBeWordForCollectedAny
   #13 = Utf8               ResultOfBeWordForCollectedArray
   #14 = Utf8               org/scalatest/matchers/should/Matchers$ResultOfBeWordForCollectedArray$$anon$4
   #15 = Class              #14           // org/scalatest/matchers/should/Matchers$ResultOfBeWordForCollectedArray$$anon$4
   #16 = Utf8               collected
   #17 = Utf8               Lorg/scalatest/matchers/should/Matchers$Collected;
   #18 = Utf8               xs
   #19 = Utf8               Lscala/collection/Iterable;
   #20 = Utf8               Lscala/collection/Iterable<Ljava/lang/Object;>;
   #21 = Utf8               shouldBeTrue
   #22 = Utf8               Z
   #23 = Utf8               org$scalatest$matchers$should$Matchers$ResultOfBeWordForCollectedArray$$prettifier
   #24 = Utf8               Lorg/scalactic/Prettifier;
   #25 = Utf8               org$scalatest$matchers$should$Matchers$ResultOfBeWordForCollectedArray$$pos
   #26 = Utf8               Lorg/scalactic/source/Position;
   #27 = Utf8               apply
   #28 = Utf8               (Lscala/Symbol;)Lorg/scalatest/matchers/Matcher;
   #29 = Utf8               (Lscala/Symbol;)Lorg/scalatest/matchers/Matcher<Ljava/lang/Object;>;
   #30 = Utf8               right
   #31 = Utf8               <init>
   #32 = Utf8               (Lorg/scalatest/matchers/should/Matchers$ResultOfBeWordForCollectedArray;Lscala/Symbol;)V
   #33 = NameAndType        #31:#32       // "<init>":(Lorg/scalatest/matchers/should/Matchers$ResultOfBeWordForCollectedArray;Lscala/Symbol;)V
   #34 = Methodref          #15.#33       // org/scalatest/matchers/should/Matchers$ResultOfBeWordForCollectedArray$$anon$4."<init>":(Lorg/scalatest/matchers/should/Matchers$ResultOfBeWordForCollectedArray;Lscala/Symbol;)V
   #35 = Utf8               this
   #36 = Utf8               Lorg/scalatest/matchers/should/Matchers$ResultOfBeWordForCollectedArray;
   #37 = Utf8               Lscala/Symbol;
   #38 = Utf8               toString
   #39 = Utf8               ()Ljava/lang/String;
   #40 = Utf8               java/lang/StringBuilder
   #41 = Class              #40           // java/lang/StringBuilder
   #42 = Integer            37
   #43 = Utf8               (I)V
   #44 = NameAndType        #31:#43       // "<init>":(I)V
   #45 = Methodref          #41.#44       // java/lang/StringBuilder."<init>":(I)V
   #46 = Utf8               ResultOfBeWordForCollectedArray(
   #47 = String             #46           // ResultOfBeWordForCollectedArray(
   #48 = Utf8               append
   #49 = Utf8               (Ljava/lang/String;)Ljava/lang/StringBuilder;
   #50 = NameAndType        #48:#49       // append:(Ljava/lang/String;)Ljava/lang/StringBuilder;
   #51 = Methodref          #41.#50       // java/lang/StringBuilder.append:(Ljava/lang/String;)Ljava/lang/StringBuilder;
   #52 = Utf8               org/scalactic/Prettifier$
   #53 = Class              #52           // org/scalactic/Prettifier$
   #54 = Utf8               MODULE$
   #55 = Utf8               Lorg/scalactic/Prettifier$;
   #56 = NameAndType        #54:#55       // MODULE$:Lorg/scalactic/Prettifier$;
   #57 = Fieldref           #53.#56       // org/scalactic/Prettifier$.MODULE$:Lorg/scalactic/Prettifier$;
   #58 = Utf8               default
   #59 = Utf8               ()Lorg/scalactic/Prettifier;
   #60 = NameAndType        #58:#59       // default:()Lorg/scalactic/Prettifier;
   #61 = Methodref          #53.#60       // org/scalactic/Prettifier$.default:()Lorg/scalactic/Prettifier;
   #62 = NameAndType        #16:#17       // collected:Lorg/scalatest/matchers/should/Matchers$Collected;
   #63 = Fieldref           #2.#62        // org/scalatest/matchers/should/Matchers$ResultOfBeWordForCollectedArray.collected:Lorg/scalatest/matchers/should/Matchers$Collected;
   #64 = Utf8               org/scalactic/Prettifier
   #65 = Class              #64           // org/scalactic/Prettifier
   #66 = Utf8               (Ljava/lang/Object;)Ljava/lang/String;
   #67 = NameAndType        #27:#66       // apply:(Ljava/lang/Object;)Ljava/lang/String;
   #68 = InterfaceMethodref #65.#67       // org/scalactic/Prettifier.apply:(Ljava/lang/Object;)Ljava/lang/String;
   #69 = Utf8               ,
   #70 = String             #69           // ,
   #71 = NameAndType        #18:#19       // xs:Lscala/collection/Iterable;
   #72 = Fieldref           #2.#71        // org/scalatest/matchers/should/Matchers$ResultOfBeWordForCollectedArray.xs:Lscala/collection/Iterable;
   #73 = NameAndType        #21:#22       // shouldBeTrue:Z
   #74 = Fieldref           #2.#73        // org/scalatest/matchers/should/Matchers$ResultOfBeWordForCollectedArray.shouldBeTrue:Z
   #75 = Utf8               scala/runtime/BoxesRunTime
   #76 = Class              #75           // scala/runtime/BoxesRunTime
   #77 = Utf8               boxToBoolean
   #78 = Utf8               (Z)Ljava/lang/Boolean;
   #79 = NameAndType        #77:#78       // boxToBoolean:(Z)Ljava/lang/Boolean;
   #80 = Methodref          #76.#79       // scala/runtime/BoxesRunTime.boxToBoolean:(Z)Ljava/lang/Boolean;
   #81 = Utf8               )
   #82 = String             #81           // )
   #83 = NameAndType        #38:#39       // toString:()Ljava/lang/String;
   #84 = Methodref          #41.#83       // java/lang/StringBuilder.toString:()Ljava/lang/String;
   #85 = Utf8               (Lorg/scalatest/matchers/should/Matchers;Lorg/scalatest/matchers/should/Matchers$Collected;Lscala/collection/Iterable;Ljava/lang/Object;ZLorg/scalactic/Prettifier;Lorg/scalactic/source/Position;)V
   #86 = Utf8               (Lorg/scalatest/matchers/should/Matchers$Collected;Lscala/collection/Iterable<Ljava/lang/Object;>;Ljava/lang/Object;ZLorg/scalactic/Prettifier;Lorg/scalactic/source/Position;)V
   #87 = Utf8               $outer
   #88 = Utf8               original
   #89 = Utf8               prettifier
   #90 = Utf8               pos
   #91 = NameAndType        #23:#24       // org$scalatest$matchers$should$Matchers$ResultOfBeWordForCollectedArray$$prettifier:Lorg/scalactic/Prettifier;
   #92 = Fieldref           #2.#91        // org/scalatest/matchers/should/Matchers$ResultOfBeWordForCollectedArray.org$scalatest$matchers$should$Matchers$ResultOfBeWordForCollectedArray$$prettifier:Lorg/scalactic/Prettifier;
   #93 = NameAndType        #25:#26       // org$scalatest$matchers$should$Matchers$ResultOfBeWordForCollectedArray$$pos:Lorg/scalactic/source/Position;
   #94 = Fieldref           #2.#93        // org/scalatest/matchers/should/Matchers$ResultOfBeWordForCollectedArray.org$scalatest$matchers$should$Matchers$ResultOfBeWordForCollectedArray$$pos:Lorg/scalactic/source/Position;
   #95 = NameAndType        #31:#85       // "<init>":(Lorg/scalatest/matchers/should/Matchers;Lorg/scalatest/matchers/should/Matchers$Collected;Lscala/collection/Iterable;Ljava/lang/Object;ZLorg/scalactic/Prettifier;Lorg/scalactic/source/Position;)V
   #96 = Methodref          #5.#95        // org/scalatest/matchers/should/Matchers$ResultOfBeWordForCollectedAny."<init>":(Lorg/scalatest/matchers/should/Matchers;Lorg/scalatest/matchers/should/Matchers$Collected;Lscala/collection/Iterable;Ljava/lang/Object;ZLorg/scalactic/Prettifier;Lorg/scalactic/source/Position;)V
   #97 = Utf8               Lorg/scalatest/matchers/should/Matchers;
   #98 = Utf8               Ljava/lang/Object;
   #99 = Utf8               Signature
  #100 = Utf8               Code
  #101 = Utf8               LineNumberTable
  #102 = Utf8               LocalVariableTable
  #103 = Utf8               MethodParameters
  #104 = Utf8               InnerClasses
  #105 = Utf8               SourceFile
  #106 = Utf8               ScalaInlineInfo
  #107 = Utf8               Scala
{
  private final org.scalatest.matchers.should.Matchers$Collected collected;
    descriptor: Lorg/scalatest/matchers/should/Matchers$Collected;
    flags: (0x0012) ACC_PRIVATE, ACC_FINAL

  private final scala.collection.Iterable<java.lang.Object> xs;
    descriptor: Lscala/collection/Iterable;
    flags: (0x0012) ACC_PRIVATE, ACC_FINAL
    Signature: #20                          // Lscala/collection/Iterable<Ljava/lang/Object;>;

  private final boolean shouldBeTrue;
    descriptor: Z
    flags: (0x0012) ACC_PRIVATE, ACC_FINAL

  public final org.scalactic.Prettifier org$scalatest$matchers$should$Matchers$ResultOfBeWordForCollectedArray$$prettifier;
    descriptor: Lorg/scalactic/Prettifier;
    flags: (0x0011) ACC_PUBLIC, ACC_FINAL

  public final org.scalactic.source.Position org$scalatest$matchers$should$Matchers$ResultOfBeWordForCollectedArray$$pos;
    descriptor: Lorg/scalactic/source/Position;
    flags: (0x0011) ACC_PUBLIC, ACC_FINAL

  public org.scalatest.matchers.Matcher<java.lang.Object> apply(scala.Symbol);
    descriptor: (Lscala/Symbol;)Lorg/scalatest/matchers/Matcher;
    flags: (0x0001) ACC_PUBLIC
    Code:
      stack=4, locals=2, args_size=2
         0: new           #15                 // class org/scalatest/matchers/should/Matchers$ResultOfBeWordForCollectedArray$$anon$4
         3: dup
         4: aload_0
         5: aload_1
         6: invokespecial #34                 // Method org/scalatest/matchers/should/Matchers$ResultOfBeWordForCollectedArray$$anon$4."<init>":(Lorg/scalatest/matchers/should/Matchers$ResultOfBeWordForCollectedArray;Lscala/Symbol;)V
         9: areturn
      LineNumberTable:
        line 5193: 0
      LocalVariableTable:
        Start  Length  Slot  Name   Signature
            0      10     0  this   Lorg/scalatest/matchers/should/Matchers$ResultOfBeWordForCollectedArray;
            0      10     1 right   Lscala/Symbol;
    Signature: #29                          // (Lscala/Symbol;)Lorg/scalatest/matchers/Matcher<Ljava/lang/Object;>;
    MethodParameters:
      Name                           Flags
      right                          final

  public java.lang.String toString();
    descriptor: ()Ljava/lang/String;
    flags: (0x0001) ACC_PUBLIC
    Code:
      stack=3, locals=1, args_size=1
         0: new           #41                 // class java/lang/StringBuilder
         3: dup
         4: ldc           #42                 // int 37
         6: invokespecial #45                 // Method java/lang/StringBuilder."<init>":(I)V
         9: ldc           #47                 // String ResultOfBeWordForCollectedArray(
        11: invokevirtual #51                 // Method java/lang/StringBuilder.append:(Ljava/lang/String;)Ljava/lang/StringBuilder;
        14: getstatic     #57                 // Field org/scalactic/Prettifier$.MODULE$:Lorg/scalactic/Prettifier$;
        17: invokevirtual #61                 // Method org/scalactic/Prettifier$.default:()Lorg/scalactic/Prettifier;
        20: aload_0
        21: getfield      #63                 // Field collected:Lorg/scalatest/matchers/should/Matchers$Collected;
        24: invokeinterface #68,  2           // InterfaceMethod org/scalactic/Prettifier.apply:(Ljava/lang/Object;)Ljava/lang/String;
        29: invokevirtual #51                 // Method java/lang/StringBuilder.append:(Ljava/lang/String;)Ljava/lang/StringBuilder;
        32: ldc           #70                 // String ,
        34: invokevirtual #51                 // Method java/lang/StringBuilder.append:(Ljava/lang/String;)Ljava/lang/StringBuilder;
        37: getstatic     #57                 // Field org/scalactic/Prettifier$.MODULE$:Lorg/scalactic/Prettifier$;
        40: invokevirtual #61                 // Method org/scalactic/Prettifier$.default:()Lorg/scalactic/Prettifier;
        43: aload_0
        44: getfield      #72                 // Field xs:Lscala/collection/Iterable;
        47: invokeinterface #68,  2           // InterfaceMethod org/scalactic/Prettifier.apply:(Ljava/lang/Object;)Ljava/lang/String;
        52: invokevirtual #51                 // Method java/lang/StringBuilder.append:(Ljava/lang/String;)Ljava/lang/StringBuilder;
        55: ldc           #70                 // String ,
        57: invokevirtual #51                 // Method java/lang/StringBuilder.append:(Ljava/lang/String;)Ljava/lang/StringBuilder;
        60: getstatic     #57                 // Field org/scalactic/Prettifier$.MODULE$:Lorg/scalactic/Prettifier$;
        63: invokevirtual #61                 // Method org/scalactic/Prettifier$.default:()Lorg/scalactic/Prettifier;
        66: aload_0
        67: getfield      #74                 // Field shouldBeTrue:Z
        70: invokestatic  #80                 // Method scala/runtime/BoxesRunTime.boxToBoolean:(Z)Ljava/lang/Boolean;
        73: invokeinterface #68,  2           // InterfaceMethod org/scalactic/Prettifier.apply:(Ljava/lang/Object;)Ljava/lang/String;
        78: invokevirtual #51                 // Method java/lang/StringBuilder.append:(Ljava/lang/String;)Ljava/lang/StringBuilder;
        81: ldc           #82                 // String )
        83: invokevirtual #51                 // Method java/lang/StringBuilder.append:(Ljava/lang/String;)Ljava/lang/StringBuilder;
        86: invokevirtual #84                 // Method java/lang/StringBuilder.toString:()Ljava/lang/String;
        89: areturn
      LineNumberTable:
        line 5202: 0
      LocalVariableTable:
        Start  Length  Slot  Name   Signature
            0      90     0  this   Lorg/scalatest/matchers/should/Matchers$ResultOfBeWordForCollectedArray;

  public org.scalatest.matchers.should.Matchers$ResultOfBeWordForCollectedArray(org.scalatest.matchers.should.Matchers$Collected, scala.collection.Iterable<java.lang.Object>, java.lang.Object, boolean, org.scalactic.Prettifier, org.scalactic.source.Position);
    descriptor: (Lorg/scalatest/matchers/should/Matchers;Lorg/scalatest/matchers/should/Matchers$Collected;Lscala/collection/Iterable;Ljava/lang/Object;ZLorg/scalactic/Prettifier;Lorg/scalactic/source/Position;)V
    flags: (0x0001) ACC_PUBLIC
    Code:
      stack=8, locals=8, args_size=8
         0: aload_0
         1: aload_2
         2: putfield      #63                 // Field collected:Lorg/scalatest/matchers/should/Matchers$Collected;
         5: aload_0
         6: aload_3
         7: putfield      #72                 // Field xs:Lscala/collection/Iterable;
        10: aload_0
        11: iload         5
        13: putfield      #74                 // Field shouldBeTrue:Z
        16: aload_0
        17: aload         6
        19: putfield      #92                 // Field org$scalatest$matchers$should$Matchers$ResultOfBeWordForCollectedArray$$prettifier:Lorg/scalactic/Prettifier;
        22: aload_0
        23: aload         7
        25: putfield      #94                 // Field org$scalatest$matchers$should$Matchers$ResultOfBeWordForCollectedArray$$pos:Lorg/scalactic/source/Position;
        28: aload_0
        29: aload_1
        30: aload_2
        31: aload_3
        32: aload         4
        34: iload         5
        36: aload         6
        38: aload         7
        40: invokespecial #96                 // Method org/scalatest/matchers/should/Matchers$ResultOfBeWordForCollectedAny."<init>":(Lorg/scalatest/matchers/should/Matchers;Lorg/scalatest/matchers/should/Matchers$Collected;Lscala/collection/Iterable;Ljava/lang/Object;ZLorg/scalactic/Prettifier;Lorg/scalactic/source/Position;)V
        43: return
      LineNumberTable:
        line 5181: 0
        line 5182: 28
        line 5181: 43
      LocalVariableTable:
        Start  Length  Slot  Name   Signature
            0      44     0  this   Lorg/scalatest/matchers/should/Matchers$ResultOfBeWordForCollectedArray;
            0      44     1 $outer   Lorg/scalatest/matchers/should/Matchers;
            0      44     2 collected   Lorg/scalatest/matchers/should/Matchers$Collected;
            0      44     3    xs   Lscala/collection/Iterable;
            0      44     4 original   Ljava/lang/Object;
            0      44     5 shouldBeTrue   Z
            0      44     6 prettifier   Lorg/scalactic/Prettifier;
            0      44     7   pos   Lorg/scalactic/source/Position;
    Signature: #86                          // (Lorg/scalatest/matchers/should/Matchers$Collected;Lscala/collection/Iterable<Ljava/lang/Object;>;Ljava/lang/Object;ZLorg/scalactic/Prettifier;Lorg/scalactic/source/Position;)V
    MethodParameters:
      Name                           Flags
      $outer                         final synthetic
      collected                      final
      xs                             final
      original                       final
      shouldBeTrue                   final
      prettifier                     final
      pos                            final
}
InnerClasses:
  public #11= #8 of #10;                  // Collected=class org/scalatest/matchers/should/Matchers$Collected of class org/scalatest/matchers/should/Matchers
  public #12= #5 of #10;                  // ResultOfBeWordForCollectedAny=class org/scalatest/matchers/should/Matchers$ResultOfBeWordForCollectedAny of class org/scalatest/matchers/should/Matchers
  public final #13= #2 of #10;            // ResultOfBeWordForCollectedArray=class org/scalatest/matchers/should/Matchers$ResultOfBeWordForCollectedArray of class org/scalatest/matchers/should/Matchers
  public final #15;                       // class org/scalatest/matchers/should/Matchers$ResultOfBeWordForCollectedArray$$anon$4
Signature: #3                           // <T:Ljava/lang/Object;>Lorg/scalatest/matchers/should/Matchers$ResultOfBeWordForCollectedAny<Ljava/lang/Object;>;
SourceFile: "Matchers.scala"
  ScalaInlineInfo: length = 0x13 (unknown attribute)
   01 01 00 03 00 1F 00 55 01 00 1B 00 1C 01 00 26
   00 27 01
  Scala: length = 0x0 (unknown attribute)

