Classfile /Users/mw/Projects/slang-braindump/.jar/jar11/assemble/slang-braindump/assemble/content/coursier/params/rule/AlwaysFail$NopityNope.class
  Last modified May 29, 2022; size 1047 bytes
  SHA-256 checksum 6d210a8962092ab313b81b73451467b8473f09a7fb34fb41832f58b12c008372
  Compiled from "AlwaysFail.scala"
public final class coursier.params.rule.AlwaysFail$NopityNope extends coursier.error.ResolutionError$UnsatisfiableRule
  minor version: 0
  major version: 52
  flags: (0x0031) ACC_PUBLIC, ACC_FINAL, ACC_SUPER
  this_class: #2                          // coursier/params/rule/AlwaysFail$NopityNope
  super_class: #4                         // coursier/error/ResolutionError$UnsatisfiableRule
  interfaces: 0, fields: 0, methods: 1, attributes: 4
Constant pool:
   #1 = Utf8               coursier/params/rule/AlwaysFail$NopityNope
   #2 = Class              #1             // coursier/params/rule/AlwaysFail$NopityNope
   #3 = Utf8               coursier/error/ResolutionError$UnsatisfiableRule
   #4 = Class              #3             // coursier/error/ResolutionError$UnsatisfiableRule
   #5 = Utf8               AlwaysFail.scala
   #6 = Utf8               coursier/error/ResolutionError
   #7 = Class              #6             // coursier/error/ResolutionError
   #8 = Utf8               UnsatisfiableRule
   #9 = Utf8               coursier/params/rule/AlwaysFail$Nope
  #10 = Class              #9             // coursier/params/rule/AlwaysFail$Nope
  #11 = Utf8               coursier/params/rule/AlwaysFail
  #12 = Class              #11            // coursier/params/rule/AlwaysFail
  #13 = Utf8               Nope
  #14 = Utf8               NopityNope
  #15 = Utf8               <init>
  #16 = Utf8               (Lcoursier/core/Resolution;Lcoursier/params/rule/AlwaysFail;Lcoursier/params/rule/AlwaysFail$Nope;)V
  #17 = Utf8               resolution
  #18 = Utf8               rule
  #19 = Utf8               conflict
  #20 = Utf8               Nopity nope
  #21 = String             #20            // Nopity nope
  #22 = Utf8               (Lcoursier/core/Resolution;Lcoursier/params/rule/Rule;Lcoursier/error/conflict/UnsatisfiedRule;Ljava/lang/String;)V
  #23 = NameAndType        #15:#22        // "<init>":(Lcoursier/core/Resolution;Lcoursier/params/rule/Rule;Lcoursier/error/conflict/UnsatisfiedRule;Ljava/lang/String;)V
  #24 = Methodref          #4.#23         // coursier/error/ResolutionError$UnsatisfiableRule."<init>":(Lcoursier/core/Resolution;Lcoursier/params/rule/Rule;Lcoursier/error/conflict/UnsatisfiedRule;Ljava/lang/String;)V
  #25 = Utf8               this
  #26 = Utf8               Lcoursier/params/rule/AlwaysFail$NopityNope;
  #27 = Utf8               Lcoursier/core/Resolution;
  #28 = Utf8               Lcoursier/params/rule/AlwaysFail;
  #29 = Utf8               Lcoursier/params/rule/AlwaysFail$Nope;
  #30 = Utf8               Code
  #31 = Utf8               LineNumberTable
  #32 = Utf8               LocalVariableTable
  #33 = Utf8               MethodParameters
  #34 = Utf8               InnerClasses
  #35 = Utf8               SourceFile
  #36 = Utf8               ScalaInlineInfo
  #37 = Utf8               Scala
{
  public coursier.params.rule.AlwaysFail$NopityNope(coursier.core.Resolution, coursier.params.rule.AlwaysFail, coursier.params.rule.AlwaysFail$Nope);
    descriptor: (Lcoursier/core/Resolution;Lcoursier/params/rule/AlwaysFail;Lcoursier/params/rule/AlwaysFail$Nope;)V
    flags: (0x0001) ACC_PUBLIC
    Code:
      stack=5, locals=4, args_size=4
         0: aload_0
         1: aload_1
         2: aload_2
         3: aload_3
         4: ldc           #21                 // String Nopity nope
         6: invokespecial #24                 // Method coursier/error/ResolutionError$UnsatisfiableRule."<init>":(Lcoursier/core/Resolution;Lcoursier/params/rule/Rule;Lcoursier/error/conflict/UnsatisfiedRule;Ljava/lang/String;)V
         9: return
      LineNumberTable:
        line 36: 0
        line 35: 9
      LocalVariableTable:
        Start  Length  Slot  Name   Signature
            0      10     0  this   Lcoursier/params/rule/AlwaysFail$NopityNope;
            0      10     1 resolution   Lcoursier/core/Resolution;
            0      10     2  rule   Lcoursier/params/rule/AlwaysFail;
            0      10     3 conflict   Lcoursier/params/rule/AlwaysFail$Nope;
    MethodParameters:
      Name                           Flags
      resolution                     final
      rule                           final
      conflict                       final
}
InnerClasses:
  public static abstract #8= #4 of #7;    // UnsatisfiableRule=class coursier/error/ResolutionError$UnsatisfiableRule of class coursier/error/ResolutionError
  public static final #13= #10 of #12;    // Nope=class coursier/params/rule/AlwaysFail$Nope of class coursier/params/rule/AlwaysFail
  public static final #14= #2 of #12;     // NopityNope=class coursier/params/rule/AlwaysFail$NopityNope of class coursier/params/rule/AlwaysFail
SourceFile: "AlwaysFail.scala"
  ScalaInlineInfo: length = 0x9 (unknown attribute)
   01 01 00 01 00 0F 00 10 01
  Scala: length = 0x0 (unknown attribute)

