Classfile /Users/mw/Projects/slang-braindump/.jar/jar11/assemble/slang-braindump/assemble/content/coursier/params/rule/DontBumpRootDependencies$.class
  Last modified May 29, 2022; size 1305 bytes
  SHA-256 checksum 6846d306f568549fc81736dfb6a2a2225d425a2b23d4a0d52381e5e70da32bf5
  Compiled from "DontBumpRootDependencies.scala"
public final class coursier.params.rule.DontBumpRootDependencies$ implements java.io.Serializable
  minor version: 0
  major version: 52
  flags: (0x0031) ACC_PUBLIC, ACC_FINAL, ACC_SUPER
  this_class: #2                          // coursier/params/rule/DontBumpRootDependencies$
  super_class: #4                         // java/lang/Object
  interfaces: 1, fields: 1, methods: 5, attributes: 3
Constant pool:
   #1 = Utf8               coursier/params/rule/DontBumpRootDependencies$
   #2 = Class              #1             // coursier/params/rule/DontBumpRootDependencies$
   #3 = Utf8               java/lang/Object
   #4 = Class              #3             // java/lang/Object
   #5 = Utf8               java/io/Serializable
   #6 = Class              #5             // java/io/Serializable
   #7 = Utf8               DontBumpRootDependencies.scala
   #8 = Utf8               MODULE$
   #9 = Utf8               Lcoursier/params/rule/DontBumpRootDependencies$;
  #10 = Utf8               <clinit>
  #11 = Utf8               ()V
  #12 = Utf8               <init>
  #13 = NameAndType        #12:#11        // "<init>":()V
  #14 = Methodref          #2.#13         // coursier/params/rule/DontBumpRootDependencies$."<init>":()V
  #15 = NameAndType        #8:#9          // MODULE$:Lcoursier/params/rule/DontBumpRootDependencies$;
  #16 = Fieldref           #2.#15         // coursier/params/rule/DontBumpRootDependencies$.MODULE$:Lcoursier/params/rule/DontBumpRootDependencies$;
  #17 = Utf8               apply
  #18 = Utf8               ()Lcoursier/params/rule/DontBumpRootDependencies;
  #19 = Utf8               coursier/util/ModuleMatchers$
  #20 = Class              #19            // coursier/util/ModuleMatchers$
  #21 = Utf8               Lcoursier/util/ModuleMatchers$;
  #22 = NameAndType        #8:#21         // MODULE$:Lcoursier/util/ModuleMatchers$;
  #23 = Fieldref           #20.#22        // coursier/util/ModuleMatchers$.MODULE$:Lcoursier/util/ModuleMatchers$;
  #24 = Utf8               all
  #25 = Utf8               ()Lcoursier/util/ModuleMatchers;
  #26 = NameAndType        #24:#25        // all:()Lcoursier/util/ModuleMatchers;
  #27 = Methodref          #20.#26        // coursier/util/ModuleMatchers$.all:()Lcoursier/util/ModuleMatchers;
  #28 = Utf8               (Lcoursier/util/ModuleMatchers;)Lcoursier/params/rule/DontBumpRootDependencies;
  #29 = NameAndType        #17:#28        // apply:(Lcoursier/util/ModuleMatchers;)Lcoursier/params/rule/DontBumpRootDependencies;
  #30 = Methodref          #2.#29         // coursier/params/rule/DontBumpRootDependencies$.apply:(Lcoursier/util/ModuleMatchers;)Lcoursier/params/rule/DontBumpRootDependencies;
  #31 = Utf8               this
  #32 = Utf8               matchers
  #33 = Utf8               coursier/params/rule/DontBumpRootDependencies
  #34 = Class              #33            // coursier/params/rule/DontBumpRootDependencies
  #35 = Utf8               (Lcoursier/util/ModuleMatchers;)V
  #36 = NameAndType        #12:#35        // "<init>":(Lcoursier/util/ModuleMatchers;)V
  #37 = Methodref          #34.#36        // coursier/params/rule/DontBumpRootDependencies."<init>":(Lcoursier/util/ModuleMatchers;)V
  #38 = Utf8               Lcoursier/util/ModuleMatchers;
  #39 = Utf8               writeReplace
  #40 = Utf8               ()Ljava/lang/Object;
  #41 = Utf8               scala/runtime/ModuleSerializationProxy
  #42 = Class              #41            // scala/runtime/ModuleSerializationProxy
  #43 = Utf8               (Ljava/lang/Class;)V
  #44 = NameAndType        #12:#43        // "<init>":(Ljava/lang/Class;)V
  #45 = Methodref          #42.#44        // scala/runtime/ModuleSerializationProxy."<init>":(Ljava/lang/Class;)V
  #46 = Methodref          #4.#13         // java/lang/Object."<init>":()V
  #47 = Utf8               Code
  #48 = Utf8               LineNumberTable
  #49 = Utf8               LocalVariableTable
  #50 = Utf8               MethodParameters
  #51 = Utf8               SourceFile
  #52 = Utf8               ScalaInlineInfo
  #53 = Utf8               Scala
{
  public static final coursier.params.rule.DontBumpRootDependencies$ MODULE$;
    descriptor: Lcoursier/params/rule/DontBumpRootDependencies$;
    flags: (0x0019) ACC_PUBLIC, ACC_STATIC, ACC_FINAL

  public static {};
    descriptor: ()V
    flags: (0x0009) ACC_PUBLIC, ACC_STATIC
    Code:
      stack=2, locals=0, args_size=0
         0: new           #2                  // class coursier/params/rule/DontBumpRootDependencies$
         3: dup
         4: invokespecial #14                 // Method "<init>":()V
         7: putstatic     #16                 // Field MODULE$:Lcoursier/params/rule/DontBumpRootDependencies$;
        10: return
      LineNumberTable:
        line 9: 0

  public coursier.params.rule.DontBumpRootDependencies apply();
    descriptor: ()Lcoursier/params/rule/DontBumpRootDependencies;
    flags: (0x0001) ACC_PUBLIC
    Code:
      stack=2, locals=1, args_size=1
         0: aload_0
         1: getstatic     #23                 // Field coursier/util/ModuleMatchers$.MODULE$:Lcoursier/util/ModuleMatchers$;
         4: invokevirtual #27                 // Method coursier/util/ModuleMatchers$.all:()Lcoursier/util/ModuleMatchers;
         7: invokevirtual #30                 // Method apply:(Lcoursier/util/ModuleMatchers;)Lcoursier/params/rule/DontBumpRootDependencies;
        10: areturn
      LineNumberTable:
        line 72: 0
      LocalVariableTable:
        Start  Length  Slot  Name   Signature
            0      11     0  this   Lcoursier/params/rule/DontBumpRootDependencies$;

  public coursier.params.rule.DontBumpRootDependencies apply(coursier.util.ModuleMatchers);
    descriptor: (Lcoursier/util/ModuleMatchers;)Lcoursier/params/rule/DontBumpRootDependencies;
    flags: (0x0001) ACC_PUBLIC
    Code:
      stack=3, locals=2, args_size=2
         0: new           #34                 // class coursier/params/rule/DontBumpRootDependencies
         3: dup
         4: aload_1
         5: invokespecial #37                 // Method coursier/params/rule/DontBumpRootDependencies."<init>":(Lcoursier/util/ModuleMatchers;)V
         8: areturn
      LineNumberTable:
        line 9: 0
      LocalVariableTable:
        Start  Length  Slot  Name   Signature
            0       9     0  this   Lcoursier/params/rule/DontBumpRootDependencies$;
            0       9     1 matchers   Lcoursier/util/ModuleMatchers;
    MethodParameters:
      Name                           Flags
      matchers                       final

  private java.lang.Object writeReplace();
    descriptor: ()Ljava/lang/Object;
    flags: (0x0002) ACC_PRIVATE
    Code:
      stack=3, locals=1, args_size=1
         0: new           #42                 // class scala/runtime/ModuleSerializationProxy
         3: dup
         4: ldc           #2                  // class coursier/params/rule/DontBumpRootDependencies$
         6: invokespecial #45                 // Method scala/runtime/ModuleSerializationProxy."<init>":(Ljava/lang/Class;)V
         9: areturn
      LineNumberTable:
        line 9: 0
      LocalVariableTable:
        Start  Length  Slot  Name   Signature
            0      10     0  this   Lcoursier/params/rule/DontBumpRootDependencies$;

  private coursier.params.rule.DontBumpRootDependencies$();
    descriptor: ()V
    flags: (0x0002) ACC_PRIVATE
    Code:
      stack=1, locals=1, args_size=1
         0: aload_0
         1: invokespecial #46                 // Method java/lang/Object."<init>":()V
         4: return
      LineNumberTable:
        line 100: 0
        line 9: 4
      LocalVariableTable:
        Start  Length  Slot  Name   Signature
            0       5     0  this   Lcoursier/params/rule/DontBumpRootDependencies$;
}
SourceFile: "DontBumpRootDependencies.scala"
  ScalaInlineInfo: length = 0x18 (unknown attribute)
   01 01 00 04 00 0C 00 0B 01 00 11 00 12 01 00 11
   00 1C 01 00 27 00 28 01
  Scala: length = 0x0 (unknown attribute)

