Classfile /Users/mw/Projects/slang-braindump/.jar/jar11/assemble/slang-braindump/assemble/content/coursier/params/rule/RuleResolution.class
  Last modified May 29, 2022; size 3071 bytes
  SHA-256 checksum 8d0393e9c73ef081f2306be3fda1a2f1fe35ab4fee9f102c56bfc2f3c023d0cf
  Compiled from "RuleResolution.scala"
public abstract class coursier.params.rule.RuleResolution implements scala.Product,java.io.Serializable
  minor version: 0
  major version: 52
  flags: (0x0421) ACC_PUBLIC, ACC_SUPER, ACC_ABSTRACT
  this_class: #2                          // coursier/params/rule/RuleResolution
  super_class: #4                         // java/lang/Object
  interfaces: 2, fields: 0, methods: 6, attributes: 5
Constant pool:
   #1 = Utf8               coursier/params/rule/RuleResolution
   #2 = Class              #1             // coursier/params/rule/RuleResolution
   #3 = Utf8               java/lang/Object
   #4 = Class              #3             // java/lang/Object
   #5 = Utf8               scala/Product
   #6 = Class              #5             // scala/Product
   #7 = Utf8               java/io/Serializable
   #8 = Class              #7             // java/io/Serializable
   #9 = Utf8               RuleResolution.scala
  #10 = Utf8               Lscala/reflect/ScalaSignature;
  #11 = Utf8               bytes
  #12 = Utf8               \u0006\u0005\u0005]b!\u0002\u0015*\u0003C\u0001\u0004\"\u0002$\u0001\t\u00039\u0005\"\u0002&\u0001\t\u0003YuABA\u001bS!\u0005!LB\u0003)S!\u0005\u0011\u000bC\u0003G\t\u0011\u0005\u0011lB\u0003\\\t!\u0005ELB\u0003_\t!\u0005u\fC\u0003G\u000f\u0011\u0005\u0001\rC\u0004b\u000f\u0005\u0005I\u0011\t2\t\u000f%<\u0011\u0011!C\u0001U\"9anBA\u0001\n\u0003y\u0007bB;\b\u0003\u0003%\tE\u001e\u0005\b{\u001e\t\t\u0011\"\u0001\u007f\u0011%\t\taBA\u0001\n\u0003\n\u0019\u0001C\u0005\u0002\u0006\u001d\t\t\u0011\"\u0011\u0002\b!I\u0011\u0011B\u0004\u0002\u0002\u0013%\u00111B\u0004\b\u0003\'!\u0001\u0012QA\u000b\r\u001d\t9\u0002\u0002EA\u00033AaA\u0012\n\u0005\u0002\u0005m\u0001bB1\u0013\u0003\u0003%\tE\u0019\u0005\bSJ\t\t\u0011\"\u0001k\u0011!q\'#!A\u0005\u0002\u0005u\u0001bB;\u0013\u0003\u0003%\tE\u001e\u0005\t{J\t\t\u0011\"\u0001\u0002\"!I\u0011\u0011\u0001\n\u0002\u0002\u0013\u0005\u00131\u0001\u0005\n\u0003\u000b\u0011\u0012\u0011!C!\u0003\u000fA\u0011\"!\u0003\u0013\u0003\u0003%I!a\u0003\b\u000f\u0005\u0015B\u0001#!\u0002(\u00191\u0001\u000b\u0002EA\u0003SAaAR\u000f\u0005\u0002\u0005-\u0002bB1\u001e\u0003\u0003%\tE\u0019\u0005\bSv\t\t\u0011\"\u0001k\u0011!qW$!A\u0005\u0002\u00055\u0002bB;\u001e\u0003\u0003%\tE\u001e\u0005\t{v\t\t\u0011\"\u0001\u00022!I\u0011\u0011A\u000f\u0002\u0002\u0013\u0005\u00131\u0001\u0005\n\u0003\u000bi\u0012\u0011!C!\u0003\u000fA\u0011\"!\u0003\u001e\u0003\u0003%I!a\u0003\t\u0013\u0005%A!!A\u0005\n\u0005-!A\u0004*vY\u0016\u0014Vm]8mkRLwN\u001c\u0006\u0003U-\nAA];mK*\u0011A&L\u0001\u0007a\u0006\u0014\u0018-\\:\u000b\u00039\n\u0001bY8veNLWM]\u0002\u0001\'\u0011\u0001\u0011g\u000e\u001e\u0011\u0005I*T\"A\u001a\u000b\u0003Q\nQa]2bY\u0006L!AN\u001a\u0003\r\u0005s\u0017PU3g!\t\u0011\u0004(\u0003\u0002:g\t9\u0001K]8ek\u000e$\bCA\u001eD\u001d\ta\u0014I\u0004\u0002>\u00016\taH\u0003\u0002@_\u00051AH]8pizJ\u0011\u0001N\u0005\u0003\u0005N\nq\u0001]1dW\u0006<W-\u0003\u0002E\u000b\na1+\u001a:jC2L\'0\u00192mK*\u0011!iM\u0001\u0007y%t\u0017\u000e\u001e \u0015\u0003!\u0003\"!\u0013\u0001\u000e\u0003%\na![:XCJtW#\u0001\'\u0011\u0005Ij\u0015B\u0001(4\u0005\u001d\u0011un\u001c7fC:LC\u0001A\u000f\b%\t!a)Y5m\'\r!\u0011G\u0015\t\u0003\'bk\u0011\u0001\u0016\u0006\u0003+Z\u000b!![8\u000b\u0003]\u000bAA[1wC&\u0011A\t\u0016\u000b\u00025B\u0011\u0011\nB\u0001\u000b)JL(+Z:pYZ,\u0007CA/\b\u001b\u0005!!A\u0003+ssJ+7o\u001c7wKN!q\u0001S\u001c;)\u0005a\u0016!\u00049s_\u0012,8\r\u001e)sK\u001aL\u00070F\u0001d!\t!w-D\u0001f\u0015\t1g+\u0001\u0003mC:<\u0017B\u00015f\u0005\u0019\u0019FO]5oO\u0006a\u0001O]8ek\u000e$\u0018I]5usV\t1\u000e\u0005\u00023Y&\u0011Qn\r\u0002\u0004\u0013:$\u0018A\u00049s_\u0012,8\r^#mK6,g\u000e\u001e\u000b\u0003aN\u0004\"AM9\n\u0005I\u001c$aA!os\"9AoCA\u0001\u0002\u0004Y\u0017a\u0001=%c\u0005y\u0001O]8ek\u000e$\u0018\n^3sCR|\'/F\u0001x!\rA8\u0010]\u0007\u0002s*\u0011!pM\u0001\u000bG>dG.Z2uS>t\u0017B\u0001?z\u0005!IE/\u001a:bi>\u0014\u0018\u0001C2b]\u0016\u000bX/\u00197\u0015\u00051{\bb\u0002;\u000e\u0003\u0003\u0005\r\u0001]\u0001\tQ\u0006\u001c\bnQ8eKR\t1.\u0001\u0005u_N#(/\u001b8h)\u0005\u0019\u0017\u0001D<sSR,\'+\u001a9mC\u000e,GCAA\u0007!\r!\u0017qB\u0005\u0004\u0003#)\'AB(cU\u0016\u001cG/\u0001\u0003XCJt\u0007CA/\u0013\u0005\u00119\u0016M\u001d8\u0014\tIAuG\u000f\u000b\u0003\u0003+!2\u0001]A\u0010\u0011\u001d!h#!AA\u0002-$2\u0001TA\u0012\u0011\u001d!\b$!AA\u0002A\fAAR1jYB\u0011Q,H\n\u0005;!;$\b\u0006\u0002\u0002(Q\u0019\u0001/a\f\t\u000fQ\f\u0013\u0011!a\u0001WR\u0019A*a\r\t\u000fQ\u001c\u0013\u0011!a\u0001a\u0006q!+\u001e7f%\u0016\u001cx\u000e\\;uS>t\u0007
  #13 = Utf8               coursier/params/rule/RuleResolution$Fail$
  #14 = Class              #13            // coursier/params/rule/RuleResolution$Fail$
  #15 = Utf8
  #16 = Utf8               coursier/params/rule/RuleResolution$TryResolve$
  #17 = Class              #16            // coursier/params/rule/RuleResolution$TryResolve$
  #18 = Utf8               coursier/params/rule/RuleResolution$Warn$
  #19 = Class              #18            // coursier/params/rule/RuleResolution$Warn$
  #20 = Utf8               productIterator
  #21 = Utf8               ()Lscala/collection/Iterator;
  #22 = Utf8               ()Lscala/collection/Iterator<Ljava/lang/Object;>;
  #23 = Utf8               productIterator$
  #24 = Utf8               (Lscala/Product;)Lscala/collection/Iterator;
  #25 = NameAndType        #23:#24        // productIterator$:(Lscala/Product;)Lscala/collection/Iterator;
  #26 = InterfaceMethodref #6.#25         // scala/Product.productIterator$:(Lscala/Product;)Lscala/collection/Iterator;
  #27 = Utf8               this
  #28 = Utf8               Lcoursier/params/rule/RuleResolution;
  #29 = Utf8               productPrefix
  #30 = Utf8               ()Ljava/lang/String;
  #31 = Utf8               productPrefix$
  #32 = Utf8               (Lscala/Product;)Ljava/lang/String;
  #33 = NameAndType        #31:#32        // productPrefix$:(Lscala/Product;)Ljava/lang/String;
  #34 = InterfaceMethodref #6.#33         // scala/Product.productPrefix$:(Lscala/Product;)Ljava/lang/String;
  #35 = Utf8               productElementName
  #36 = Utf8               (I)Ljava/lang/String;
  #37 = Utf8               n
  #38 = Utf8               productElementName$
  #39 = Utf8               (Lscala/Product;I)Ljava/lang/String;
  #40 = NameAndType        #38:#39        // productElementName$:(Lscala/Product;I)Ljava/lang/String;
  #41 = InterfaceMethodref #6.#40         // scala/Product.productElementName$:(Lscala/Product;I)Ljava/lang/String;
  #42 = Utf8               I
  #43 = Utf8               productElementNames
  #44 = Utf8               ()Lscala/collection/Iterator<Ljava/lang/String;>;
  #45 = Utf8               productElementNames$
  #46 = NameAndType        #45:#24        // productElementNames$:(Lscala/Product;)Lscala/collection/Iterator;
  #47 = InterfaceMethodref #6.#46         // scala/Product.productElementNames$:(Lscala/Product;)Lscala/collection/Iterator;
  #48 = Utf8               isWarn
  #49 = Utf8               ()Z
  #50 = Utf8               MODULE$
  #51 = Utf8               Lcoursier/params/rule/RuleResolution$Warn$;
  #52 = NameAndType        #50:#51        // MODULE$:Lcoursier/params/rule/RuleResolution$Warn$;
  #53 = Fieldref           #19.#52        // coursier/params/rule/RuleResolution$Warn$.MODULE$:Lcoursier/params/rule/RuleResolution$Warn$;
  #54 = Utf8               equals
  #55 = Utf8               (Ljava/lang/Object;)Z
  #56 = NameAndType        #54:#55        // equals:(Ljava/lang/Object;)Z
  #57 = Methodref          #4.#56         // java/lang/Object.equals:(Ljava/lang/Object;)Z
  #58 = Utf8               <init>
  #59 = Utf8               ()V
  #60 = NameAndType        #58:#59        // "<init>":()V
  #61 = Methodref          #4.#60         // java/lang/Object."<init>":()V
  #62 = Utf8               $init$
  #63 = Utf8               (Lscala/Product;)V
  #64 = NameAndType        #62:#63        // $init$:(Lscala/Product;)V
  #65 = InterfaceMethodref #6.#64         // scala/Product.$init$:(Lscala/Product;)V
  #66 = Utf8               Code
  #67 = Utf8               LineNumberTable
  #68 = Utf8               LocalVariableTable
  #69 = Utf8               Signature
  #70 = Utf8               MethodParameters
  #71 = Utf8               StackMapTable
  #72 = Utf8               InnerClasses
  #73 = Utf8               SourceFile
  #74 = Utf8               RuntimeVisibleAnnotations
  #75 = Utf8               ScalaInlineInfo
  #76 = Utf8               ScalaSig
{
  public scala.collection.Iterator<java.lang.Object> productIterator();
    descriptor: ()Lscala/collection/Iterator;
    flags: (0x0001) ACC_PUBLIC
    Code:
      stack=1, locals=1, args_size=1
         0: aload_0
         1: invokestatic  #26                 // InterfaceMethod scala/Product.productIterator$:(Lscala/Product;)Lscala/collection/Iterator;
         4: areturn
      LineNumberTable:
        line 3: 0
      LocalVariableTable:
        Start  Length  Slot  Name   Signature
            0       5     0  this   Lcoursier/params/rule/RuleResolution;
    Signature: #22                          // ()Lscala/collection/Iterator<Ljava/lang/Object;>;

  public java.lang.String productPrefix();
    descriptor: ()Ljava/lang/String;
    flags: (0x0001) ACC_PUBLIC
    Code:
      stack=1, locals=1, args_size=1
         0: aload_0
         1: invokestatic  #34                 // InterfaceMethod scala/Product.productPrefix$:(Lscala/Product;)Ljava/lang/String;
         4: areturn
      LineNumberTable:
        line 3: 0
      LocalVariableTable:
        Start  Length  Slot  Name   Signature
            0       5     0  this   Lcoursier/params/rule/RuleResolution;

  public java.lang.String productElementName(int);
    descriptor: (I)Ljava/lang/String;
    flags: (0x0001) ACC_PUBLIC
    Code:
      stack=2, locals=2, args_size=2
         0: aload_0
         1: iload_1
         2: invokestatic  #41                 // InterfaceMethod scala/Product.productElementName$:(Lscala/Product;I)Ljava/lang/String;
         5: areturn
      LineNumberTable:
        line 3: 0
      LocalVariableTable:
        Start  Length  Slot  Name   Signature
            0       6     0  this   Lcoursier/params/rule/RuleResolution;
            0       6     1     n   I
    MethodParameters:
      Name                           Flags
      n                              final

  public scala.collection.Iterator<java.lang.String> productElementNames();
    descriptor: ()Lscala/collection/Iterator;
    flags: (0x0001) ACC_PUBLIC
    Code:
      stack=1, locals=1, args_size=1
         0: aload_0
         1: invokestatic  #47                 // InterfaceMethod scala/Product.productElementNames$:(Lscala/Product;)Lscala/collection/Iterator;
         4: areturn
      LineNumberTable:
        line 3: 0
      LocalVariableTable:
        Start  Length  Slot  Name   Signature
            0       5     0  this   Lcoursier/params/rule/RuleResolution;
    Signature: #44                          // ()Lscala/collection/Iterator<Ljava/lang/String;>;

  public boolean isWarn();
    descriptor: ()Z
    flags: (0x0001) ACC_PUBLIC
    Code:
      stack=2, locals=3, args_size=1
         0: aload_0
         1: astore_2
         2: getstatic     #53                 // Field coursier/params/rule/RuleResolution$Warn$.MODULE$:Lcoursier/params/rule/RuleResolution$Warn$;
         5: aload_2
         6: invokevirtual #57                 // Method java/lang/Object.equals:(Ljava/lang/Object;)Z
         9: ifeq          17
        12: iconst_1
        13: istore_1
        14: goto          25
        17: goto          20
        20: iconst_0
        21: istore_1
        22: goto          25
        25: iload_1
        26: ireturn
      StackMapTable: number_of_entries = 3
        frame_type = 253 /* append */
          offset_delta = 17
          locals = [ top, class coursier/params/rule/RuleResolution ]
        frame_type = 2 /* same */
        frame_type = 255 /* full_frame */
          offset_delta = 4
          locals = [ class coursier/params/rule/RuleResolution, int, class coursier/params/rule/RuleResolution ]
          stack = []
      LineNumberTable:
        line 5: 0
        line 6: 2
        line 7: 20
        line 5: 25
      LocalVariableTable:
        Start  Length  Slot  Name   Signature
            0      27     0  this   Lcoursier/params/rule/RuleResolution;

  public coursier.params.rule.RuleResolution();
    descriptor: ()V
    flags: (0x0001) ACC_PUBLIC
    Code:
      stack=1, locals=1, args_size=1
         0: aload_0
         1: invokespecial #61                 // Method java/lang/Object."<init>":()V
         4: aload_0
         5: invokestatic  #65                 // InterfaceMethod scala/Product.$init$:(Lscala/Product;)V
         8: return
      LineNumberTable:
        line 3: 0
      LocalVariableTable:
        Start  Length  Slot  Name   Signature
            0       9     0  this   Lcoursier/params/rule/RuleResolution;
}
InnerClasses:
  public static #15= #14 of #2;           // =class coursier/params/rule/RuleResolution$Fail$ of class coursier/params/rule/RuleResolution
  public static #15= #17 of #2;           // =class coursier/params/rule/RuleResolution$TryResolve$ of class coursier/params/rule/RuleResolution
  public static #15= #19 of #2;           // =class coursier/params/rule/RuleResolution$Warn$ of class coursier/params/rule/RuleResolution
SourceFile: "RuleResolution.scala"
RuntimeVisibleAnnotations:
  0: #10(#11=s#12)
    scala.reflect.ScalaSignature(
      bytes="\u0006\u0005\u0005]b!\u0002\u0015*\u0003C\u0001\u0004\"\u0002$\u0001\t\u00039\u0005\"\u0002&\u0001\t\u0003YuABA\u001bS!\u0005!LB\u0003)S!\u0005\u0011\u000bC\u0003G\t\u0011\u0005\u0011lB\u0003\\\t!\u0005ELB\u0003_\t!\u0005u\fC\u0003G\u000f\u0011\u0005\u0001\rC\u0004b\u000f\u0005\u0005I\u0011\t2\t\u000f%<\u0011\u0011!C\u0001U\"9anBA\u0001\n\u0003y\u0007bB;\b\u0003\u0003%\tE\u001e\u0005\b{\u001e\t\t\u0011\"\u0001\u007f\u0011%\t\taBA\u0001\n\u0003\n\u0019\u0001C\u0005\u0002\u0006\u001d\t\t\u0011\"\u0011\u0002\b!I\u0011\u0011B\u0004\u0002\u0002\u0013%\u00111B\u0004\b\u0003\'!\u0001\u0012QA\u000b\r\u001d\t9\u0002\u0002EA\u00033AaA\u0012\n\u0005\u0002\u0005m\u0001bB1\u0013\u0003\u0003%\tE\u0019\u0005\bSJ\t\t\u0011\"\u0001k\u0011!q\'#!A\u0005\u0002\u0005u\u0001bB;\u0013\u0003\u0003%\tE\u001e\u0005\t{J\t\t\u0011\"\u0001\u0002\"!I\u0011\u0011\u0001\n\u0002\u0002\u0013\u0005\u00131\u0001\u0005\n\u0003\u000b\u0011\u0012\u0011!C!\u0003\u000fA\u0011\"!\u0003\u0013\u0003\u0003%I!a\u0003\b\u000f\u0005\u0015B\u0001#!\u0002(\u00191\u0001\u000b\u0002EA\u0003SAaAR\u000f\u0005\u0002\u0005-\u0002bB1\u001e\u0003\u0003%\tE\u0019\u0005\bSv\t\t\u0011\"\u0001k\u0011!qW$!A\u0005\u0002\u00055\u0002bB;\u001e\u0003\u0003%\tE\u001e\u0005\t{v\t\t\u0011\"\u0001\u00022!I\u0011\u0011A\u000f\u0002\u0002\u0013\u0005\u00131\u0001\u0005\n\u0003\u000bi\u0012\u0011!C!\u0003\u000fA\u0011\"!\u0003\u001e\u0003\u0003%I!a\u0003\t\u0013\u0005%A!!A\u0005\n\u0005-!A\u0004*vY\u0016\u0014Vm]8mkRLwN\u001c\u0006\u0003U-\nAA];mK*\u0011A&L\u0001\u0007a\u0006\u0014\u0018-\\:\u000b\u00039\n\u0001bY8veNLWM]\u0002\u0001\'\u0011\u0001\u0011g\u000e\u001e\u0011\u0005I*T\"A\u001a\u000b\u0003Q\nQa]2bY\u0006L!AN\u001a\u0003\r\u0005s\u0017PU3g!\t\u0011\u0004(\u0003\u0002:g\t9\u0001K]8ek\u000e$\bCA\u001eD\u001d\ta\u0014I\u0004\u0002>\u00016\taH\u0003\u0002@_\u00051AH]8pizJ\u0011\u0001N\u0005\u0003\u0005N\nq\u0001]1dW\u0006<W-\u0003\u0002E\u000b\na1+\u001a:jC2L\'0\u00192mK*\u0011!iM\u0001\u0007y%t\u0017\u000e\u001e \u0015\u0003!\u0003\"!\u0013\u0001\u000e\u0003%\na![:XCJtW#\u0001\'\u0011\u0005Ij\u0015B\u0001(4\u0005\u001d\u0011un\u001c7fC:LC\u0001A\u000f\b%\t!a)Y5m\'\r!\u0011G\u0015\t\u0003\'bk\u0011\u0001\u0016\u0006\u0003+Z\u000b!![8\u000b\u0003]\u000bAA[1wC&\u0011A\t\u0016\u000b\u00025B\u0011\u0011\nB\u0001\u000b)JL(+Z:pYZ,\u0007CA/\b\u001b\u0005!!A\u0003+ssJ+7o\u001c7wKN!q\u0001S\u001c;)\u0005a\u0016!\u00049s_\u0012,8\r\u001e)sK\u001aL\u00070F\u0001d!\t!w-D\u0001f\u0015\t1g+\u0001\u0003mC:<\u0017B\u00015f\u0005\u0019\u0019FO]5oO\u0006a\u0001O]8ek\u000e$\u0018I]5usV\t1\u000e\u0005\u00023Y&\u0011Qn\r\u0002\u0004\u0013:$\u0018A\u00049s_\u0012,8\r^#mK6,g\u000e\u001e\u000b\u0003aN\u0004\"AM9\n\u0005I\u001c$aA!os\"9AoCA\u0001\u0002\u0004Y\u0017a\u0001=%c\u0005y\u0001O]8ek\u000e$\u0018\n^3sCR|\'/F\u0001x!\rA8\u0010]\u0007\u0002s*\u0011!pM\u0001\u000bG>dG.Z2uS>t\u0017B\u0001?z\u0005!IE/\u001a:bi>\u0014\u0018\u0001C2b]\u0016\u000bX/\u00197\u0015\u00051{\bb\u0002;\u000e\u0003\u0003\u0005\r\u0001]\u0001\tQ\u0006\u001c\bnQ8eKR\t1.\u0001\u0005u_N#(/\u001b8h)\u0005\u0019\u0017\u0001D<sSR,\'+\u001a9mC\u000e,GCAA\u0007!\r!\u0017qB\u0005\u0004\u0003#)\'AB(cU\u0016\u001cG/\u0001\u0003XCJt\u0007CA/\u0013\u0005\u00119\u0016M\u001d8\u0014\tIAuG\u000f\u000b\u0003\u0003+!2\u0001]A\u0010\u0011\u001d!h#!AA\u0002-$2\u0001TA\u0012\u0011\u001d!\b$!AA\u0002A\fAAR1jYB\u0011Q,H\n\u0005;!;$\b\u0006\u0002\u0002(Q\u0019\u0001/a\f\t\u000fQ\f\u0013\u0011!a\u0001WR\u0019A*a\r\t\u000fQ\u001c\u0013\u0011!a\u0001a\u0006q!+\u001e7f%\u0016\u001cx\u000e\\;uS>t\u0007"
    )
  ScalaInlineInfo: length = 0x22 (unknown attribute)
   01 00 00 06 00 3C 00 3D 01 00 32 00 33 01 00 25
   00 26 01 00 2D 00 17 01 00 16 00 17 00 00 1F 00
   20 00
  ScalaSig: length = 0x3 (unknown attribute)
   05 02 00
