Classfile /Users/mw/Projects/slang-braindump/.jar/jar8/assemble/slang-braindump/assemble/content/org/scalactic/source/PositionMacro.class
  Last modified May 29, 2022; size 2338 bytes
  SHA-256 checksum f09c5976f1b11460270b2784baf01a1d64fda2d25fdb7d97026f13c68e69d72e
  Compiled from "PositionMacro.scala"
public final class org.scalactic.source.PositionMacro
  minor version: 0
  major version: 52
  flags: (0x0031) ACC_PUBLIC, ACC_FINAL, ACC_SUPER
  this_class: #2                          // org/scalactic/source/PositionMacro
  super_class: #4                         // java/lang/Object
  interfaces: 0, fields: 0, methods: 1, attributes: 4
Constant pool:
   #1 = Utf8               org/scalactic/source/PositionMacro
   #2 = Class              #1             // org/scalactic/source/PositionMacro
   #3 = Utf8               java/lang/Object
   #4 = Class              #3             // java/lang/Object
   #5 = Utf8               PositionMacro.scala
   #6 = Utf8               Lscala/reflect/ScalaSignature;
   #7 = Utf8               bytes
   #8 = Utf8               \u0006\u0005\u00055s!\u0002\u000f\u001e\u0011\u0003!c!\u0002\u0014\u001e\u0011\u00039\u0003\"\u0002\u0018\u0002\t\u0003ys!\u0002\u0019\u0002\u0011\u0013\td!B\u001a\u0002\u0011\u0013!\u0004\"\u0002\u0018\u0005\t\u0003)t!\u0002\u001c\u0005\u0011\u00039d!B\u001d\u0005\u0011\u0003Q\u0004\"\u0002\u0018\b\t\u0003Yt!\u0002\u001f\b\u0011\u0003id!B \b\u0011\u0003\u0001\u0005\"\u0002\u0018\u000b\t\u0003\t\u0005\"\u0003\"\u0002\u0011\u000b\u0007I\u0011A\u0010D\r\u00119\u0015\u0001\u0002%\t\u0011%k!Q1A\u0005\u0002)C\u0001bU\u0007\u0003\u0002\u0003\u0006Ia\u0013\u0005\u0006]5!\t\u0001\u0016\u0005\b/6\u0011\r\u0011\"\u0003Y\u0011\u0019\u0001W\u0002)A\u00053\"9\u0011-\u0004b\u0001\n\u0013\u0011\u0007B\u00024\u000eA\u0003%1\rC\u0004h\u001b\t\u0007I\u0011\u00025\t\r1l\u0001\u0015!\u0003j\u0011\u0015iW\u0002\"\u0001o\u0011%\t\t\"\u0001a\u0001\n\u0013\t\u0019\u0002C\u0005\u0002*\u0005\u0001\r\u0011\"\u0003\u0002,!A\u0011qG\u0001!B\u0013\t)\u0002C\u0004\u0002:\u0005!\t!a\u000f\u0002\u001bA{7/\u001b;j_:l\u0015m\u0019:p\u0015\tqr$\u0001\u0004t_V\u00148-\u001a\u0006\u0003A\u0005\n\u0011b]2bY\u0006\u001cG/[2\u000b\u0003\t\n1a\u001c:h\u0007\u0001\u0001\"!J\u0001\u000e\u0003u\u0011Q\u0002U8tSRLwN\\\'bGJ|7CA\u0001)!\tIC&D\u0001+\u0015\u0005Y\u0013!B:dC2\f\u0017BA\u0017+\u0005\u0019\te.\u001f*fM\u00061A(\u001b8jiz\"\u0012\u0001J\u0001\u0011g>,(oY3D_6\u0004\u0018\r\u001e%bG.\u0004\"A\r\u0003\u000e\u0003\u0005\u0011\u0001c]8ve\u000e,7i\\7qCRD\u0015mY6\u0014\u0005\u0011AC#A\u0019\u0002\u0011%tG/\u001a:oC2\u0004\"\u0001O\u0004\u000e\u0003\u0011\u0011\u0001\"\u001b8uKJt\u0017\r\\\n\u0003\u000f!\"\u0012aN\u0001\u000bI\u0016\u001cwN]1u_J\u001c\bC\u0001 \u000b\u001b\u00059!A\u00033fG>\u0014\u0018\r^8sgN\u0011!\u0002\u000b\u000b\u0002{\u0005q2\u000f[8x\'\u000e\fG.Y2uS\u000e4\u0015\u000e\u001c7GS2,\u0007+\u0019;i]\u0006lWm]\u000b\u0002\tB\u0011\u0011&R\u0005\u0003\r*\u0012qAQ8pY\u0016\fgNA\tQ_NLG/[8o\u001b\u0006\u001c\'o\\%na2\u001c\"!\u0004\u0015\u0002\u0011Ut\u0017N^3sg\u0016,\u0012a\u0013\t\u0003\u0019Fk\u0011!\u0014\u0006\u0003\u001d>\u000b1!\u00199j\u0015\t\u0001&&A\u0004sK\u001adWm\u0019;\n\u0005Ik%\u0001C+oSZ,\'o]3\u0002\u0013Ut\u0017N^3sg\u0016\u0004CCA+W!\t\u0011T\u0002C\u0003J!\u0001\u00071*\u0001\bQ_NLG/[8o\u001b>$W\u000f\\3\u0016\u0003e\u0003\"A\u0017/\u000f\u0005msQ\"A\u0007\n\u0005us&\u0001D\'pIVdWmU=nE>d\u0017BA0N\u0005\u001d\u0019\u00160\u001c2pYN\fq\u0002U8tSRLwN\\\'pIVdW\rI\u0001\u000e!>\u001c\u0018\u000e^5p]\u000ec\u0017m]:\u0016\u0003\r\u0004\"A\u00173\n\u0005\u0015t&aC\"mCN\u001c8+_7c_2\fa\u0002U8tSRLwN\\\"mCN\u001c\b%\u0001\bQ_NLG/[8o?\u0006\u0004\b\u000f\\=\u0016\u0003%\u0004\"A\u00176\n\u0005-t&AB*z[\n|G.A\bQ_NLG/[8o?\u0006\u0004\b\u000f\\=!\u0003\u0015\t\u0007\u000f\u001d7z)\ty\'\u000fE\u0002q\u0003\u000bq!!\u001d:\r\u0001!)1o\u0006a\u0001i\u000691m\u001c8uKb$\bCA;\u0000\u001d\t1XP\u0004\u0002xy:\u0011\u0001p_\u0007\u0002s*\u0011!pI\u0001\u0007yI|w\u000e\u001e \n\u0003\tJ!\u0001I\u0011\n\u0005y|\u0012\u0001D\'bGJ|7i\u001c8uKb$\u0018\u0002BA\u0001\u0003\u0007\u0011qaQ8oi\u0016DHO\u0003\u0002\u007f?%!\u0011qAA\u0005\u0005\u0011!&/Z3\n\t\u0005-\u0011Q\u0002\u0002\b\u00032L\u0017m]3t\u0015\r\tyaT\u0001\u0007[\u0006\u001c\'o\\:\u0002\u000b\r\f7\r[3\u0016\u0005\u0005U\u0001#BA\f\u0003K)VBAA\r\u0015\u0011\tY\"!\b\u0002\u0007I,gM\u0003\u0003\u0002 \u0005\u0005\u0012\u0001\u00027b]\u001eT!!a\t\u0002\t)\fg/Y\u0005\u0005\u0003O\tIBA\u0007XK\u0006\\\'+\u001a4fe\u0016t7-Z\u0001\nG\u0006\u001c\u0007.Z0%KF$B!!\f\u00024A\u0019\u0011&a\f\n\u0007\u0005E\"F\u0001\u0003V]&$\b\"CA\u001b3\u0005\u0005\t\u0019AA\u000b\u0003\rAH%M\u0001\u0007G\u0006\u001c\u0007.\u001a\u0011\u0002\u0017\u001d,g\u000eU8tSRLwN\u001c\u000b\u0005\u0003{\t\t\u0005\u0005\u0004\u0002@\u0005\r\u0013q\t\b\u0004c\u0006\u0005\u0003\"B:\u001c\u0001\u0004!\u0018\u0002BA#\u0003\u0013\u0011A!\u0012=qeB\u0019Q%!\u0013\n\u0007\u0005-SD\u0001\u0005Q_NLG/[8o\u0001
   #9 = Utf8               org/scalactic/source/PositionMacro$PositionMacroImpl
  #10 = Class              #9             // org/scalactic/source/PositionMacro$PositionMacroImpl
  #11 = Utf8               PositionMacroImpl
  #12 = Utf8               org/scalactic/source/PositionMacro$sourceCompatHack$
  #13 = Class              #12            // org/scalactic/source/PositionMacro$sourceCompatHack$
  #14 = Utf8               sourceCompatHack$
  #15 = Utf8               scala/reflect/api/Exprs$Expr
  #16 = Class              #15            // scala/reflect/api/Exprs$Expr
  #17 = Utf8               scala/reflect/api/Exprs
  #18 = Class              #17            // scala/reflect/api/Exprs
  #19 = Utf8               Expr
  #20 = Utf8               genPosition
  #21 = Utf8               (Lscala/reflect/macros/blackbox/Context;)Lscala/reflect/api/Exprs$Expr;
  #22 = Utf8               (Lscala/reflect/macros/blackbox/Context;)Lscala/reflect/api/Exprs$Expr<Lorg/scalactic/source/Position;>;
  #23 = Utf8               context
  #24 = Utf8               org/scalactic/source/PositionMacro$
  #25 = Class              #24            // org/scalactic/source/PositionMacro$
  #26 = Utf8               MODULE$
  #27 = Utf8               Lorg/scalactic/source/PositionMacro$;
  #28 = NameAndType        #26:#27        // MODULE$:Lorg/scalactic/source/PositionMacro$;
  #29 = Fieldref           #25.#28        // org/scalactic/source/PositionMacro$.MODULE$:Lorg/scalactic/source/PositionMacro$;
  #30 = NameAndType        #20:#21        // genPosition:(Lscala/reflect/macros/blackbox/Context;)Lscala/reflect/api/Exprs$Expr;
  #31 = Methodref          #25.#30        // org/scalactic/source/PositionMacro$.genPosition:(Lscala/reflect/macros/blackbox/Context;)Lscala/reflect/api/Exprs$Expr;
  #32 = Utf8               Lscala/reflect/macros/blackbox/Context;
  #33 = Utf8               Code
  #34 = Utf8               LocalVariableTable
  #35 = Utf8               Signature
  #36 = Utf8               MethodParameters
  #37 = Utf8               InnerClasses
  #38 = Utf8               SourceFile
  #39 = Utf8               RuntimeVisibleAnnotations
  #40 = Utf8               ScalaSig
{
  public static scala.reflect.api.Exprs$Expr<org.scalactic.source.Position> genPosition(scala.reflect.macros.blackbox.Context);
    descriptor: (Lscala/reflect/macros/blackbox/Context;)Lscala/reflect/api/Exprs$Expr;
    flags: (0x0009) ACC_PUBLIC, ACC_STATIC
    Code:
      stack=2, locals=1, args_size=1
         0: getstatic     #29                 // Field org/scalactic/source/PositionMacro$.MODULE$:Lorg/scalactic/source/PositionMacro$;
         3: aload_0
         4: invokevirtual #31                 // Method org/scalactic/source/PositionMacro$.genPosition:(Lscala/reflect/macros/blackbox/Context;)Lscala/reflect/api/Exprs$Expr;
         7: areturn
      LocalVariableTable:
        Start  Length  Slot  Name   Signature
            0       8     0 context   Lscala/reflect/macros/blackbox/Context;
    Signature: #22                          // (Lscala/reflect/macros/blackbox/Context;)Lscala/reflect/api/Exprs$Expr<Lorg/scalactic/source/Position;>;
    MethodParameters:
      Name                           Flags
      context                        final
}
InnerClasses:
  private static #11= #10 of #2;          // PositionMacroImpl=class org/scalactic/source/PositionMacro$PositionMacroImpl of class org/scalactic/source/PositionMacro
  private static #14= #13 of #2;          // sourceCompatHack$=class org/scalactic/source/PositionMacro$sourceCompatHack$ of class org/scalactic/source/PositionMacro
  public #19= #16 of #18;                 // Expr=class scala/reflect/api/Exprs$Expr of class scala/reflect/api/Exprs
SourceFile: "PositionMacro.scala"
RuntimeVisibleAnnotations:
  0: #6(#7=s#8)
    scala.reflect.ScalaSignature(
      bytes="\u0006\u0005\u00055s!\u0002\u000f\u001e\u0011\u0003!c!\u0002\u0014\u001e\u0011\u00039\u0003\"\u0002\u0018\u0002\t\u0003ys!\u0002\u0019\u0002\u0011\u0013\td!B\u001a\u0002\u0011\u0013!\u0004\"\u0002\u0018\u0005\t\u0003)t!\u0002\u001c\u0005\u0011\u00039d!B\u001d\u0005\u0011\u0003Q\u0004\"\u0002\u0018\b\t\u0003Yt!\u0002\u001f\b\u0011\u0003id!B \b\u0011\u0003\u0001\u0005\"\u0002\u0018\u000b\t\u0003\t\u0005\"\u0003\"\u0002\u0011\u000b\u0007I\u0011A\u0010D\r\u00119\u0015\u0001\u0002%\t\u0011%k!Q1A\u0005\u0002)C\u0001bU\u0007\u0003\u0002\u0003\u0006Ia\u0013\u0005\u0006]5!\t\u0001\u0016\u0005\b/6\u0011\r\u0011\"\u0003Y\u0011\u0019\u0001W\u0002)A\u00053\"9\u0011-\u0004b\u0001\n\u0013\u0011\u0007B\u00024\u000eA\u0003%1\rC\u0004h\u001b\t\u0007I\u0011\u00025\t\r1l\u0001\u0015!\u0003j\u0011\u0015iW\u0002\"\u0001o\u0011%\t\t\"\u0001a\u0001\n\u0013\t\u0019\u0002C\u0005\u0002*\u0005\u0001\r\u0011\"\u0003\u0002,!A\u0011qG\u0001!B\u0013\t)\u0002C\u0004\u0002:\u0005!\t!a\u000f\u0002\u001bA{7/\u001b;j_:l\u0015m\u0019:p\u0015\tqr$\u0001\u0004t_V\u00148-\u001a\u0006\u0003A\u0005\n\u0011b]2bY\u0006\u001cG/[2\u000b\u0003\t\n1a\u001c:h\u0007\u0001\u0001\"!J\u0001\u000e\u0003u\u0011Q\u0002U8tSRLwN\\\'bGJ|7CA\u0001)!\tIC&D\u0001+\u0015\u0005Y\u0013!B:dC2\f\u0017BA\u0017+\u0005\u0019\te.\u001f*fM\u00061A(\u001b8jiz\"\u0012\u0001J\u0001\u0011g>,(oY3D_6\u0004\u0018\r\u001e%bG.\u0004\"A\r\u0003\u000e\u0003\u0005\u0011\u0001c]8ve\u000e,7i\\7qCRD\u0015mY6\u0014\u0005\u0011AC#A\u0019\u0002\u0011%tG/\u001a:oC2\u0004\"\u0001O\u0004\u000e\u0003\u0011\u0011\u0001\"\u001b8uKJt\u0017\r\\\n\u0003\u000f!\"\u0012aN\u0001\u000bI\u0016\u001cwN]1u_J\u001c\bC\u0001 \u000b\u001b\u00059!A\u00033fG>\u0014\u0018\r^8sgN\u0011!\u0002\u000b\u000b\u0002{\u0005q2\u000f[8x\'\u000e\fG.Y2uS\u000e4\u0015\u000e\u001c7GS2,\u0007+\u0019;i]\u0006lWm]\u000b\u0002\tB\u0011\u0011&R\u0005\u0003\r*\u0012qAQ8pY\u0016\fgNA\tQ_NLG/[8o\u001b\u0006\u001c\'o\\%na2\u001c\"!\u0004\u0015\u0002\u0011Ut\u0017N^3sg\u0016,\u0012a\u0013\t\u0003\u0019Fk\u0011!\u0014\u0006\u0003\u001d>\u000b1!\u00199j\u0015\t\u0001&&A\u0004sK\u001adWm\u0019;\n\u0005Ik%\u0001C+oSZ,\'o]3\u0002\u0013Ut\u0017N^3sg\u0016\u0004CCA+W!\t\u0011T\u0002C\u0003J!\u0001\u00071*\u0001\bQ_NLG/[8o\u001b>$W\u000f\\3\u0016\u0003e\u0003\"A\u0017/\u000f\u0005msQ\"A\u0007\n\u0005us&\u0001D\'pIVdWmU=nE>d\u0017BA0N\u0005\u001d\u0019\u00160\u001c2pYN\fq\u0002U8tSRLwN\\\'pIVdW\rI\u0001\u000e!>\u001c\u0018\u000e^5p]\u000ec\u0017m]:\u0016\u0003\r\u0004\"A\u00173\n\u0005\u0015t&aC\"mCN\u001c8+_7c_2\fa\u0002U8tSRLwN\\\"mCN\u001c\b%\u0001\bQ_NLG/[8o?\u0006\u0004\b\u000f\\=\u0016\u0003%\u0004\"A\u00176\n\u0005-t&AB*z[\n|G.A\bQ_NLG/[8o?\u0006\u0004\b\u000f\\=!\u0003\u0015\t\u0007\u000f\u001d7z)\ty\'\u000fE\u0002q\u0003\u000bq!!\u001d:\r\u0001!)1o\u0006a\u0001i\u000691m\u001c8uKb$\bCA;\u0000\u001d\t1XP\u0004\u0002xy:\u0011\u0001p_\u0007\u0002s*\u0011!pI\u0001\u0007yI|w\u000e\u001e \n\u0003\tJ!\u0001I\u0011\n\u0005y|\u0012\u0001D\'bGJ|7i\u001c8uKb$\u0018\u0002BA\u0001\u0003\u0007\u0011qaQ8oi\u0016DHO\u0003\u0002\u007f?%!\u0011qAA\u0005\u0005\u0011!&/Z3\n\t\u0005-\u0011Q\u0002\u0002\b\u00032L\u0017m]3t\u0015\r\tyaT\u0001\u0007[\u0006\u001c\'o\\:\u0002\u000b\r\f7\r[3\u0016\u0005\u0005U\u0001#BA\f\u0003K)VBAA\r\u0015\u0011\tY\"!\b\u0002\u0007I,gM\u0003\u0003\u0002 \u0005\u0005\u0012\u0001\u00027b]\u001eT!!a\t\u0002\t)\fg/Y\u0005\u0005\u0003O\tIBA\u0007XK\u0006\\\'+\u001a4fe\u0016t7-Z\u0001\nG\u0006\u001c\u0007.Z0%KF$B!!\f\u00024A\u0019\u0011&a\f\n\u0007\u0005E\"F\u0001\u0003V]&$\b\"CA\u001b3\u0005\u0005\t\u0019AA\u000b\u0003\rAH%M\u0001\u0007G\u0006\u001c\u0007.\u001a\u0011\u0002\u0017\u001d,g\u000eU8tSRLwN\u001c\u000b\u0005\u0003{\t\t\u0005\u0005\u0004\u0002@\u0005\r\u0013q\t\b\u0004c\u0006\u0005\u0003\"B:\u001c\u0001\u0004!\u0018\u0002BA#\u0003\u0013\u0011A!\u0012=qeB\u0019Q%!\u0013\n\u0007\u0005-SD\u0001\u0005Q_NLG/[8o\u0001"
    )
  ScalaSig: length = 0x3 (unknown attribute)
   05 02 00
