Classfile /Users/mw/Projects/slang-braindump/.jar/jar11/assemble/slang-braindump/assemble/content/org/sireum/parser/Json$State$$String$.class
  Last modified May 29, 2022; size 2078 bytes
  SHA-256 checksum 5ed36e74ae347f96f1ecb216f333034cb796460bc246d63417e826a4d05e8616
  Compiled from "JsonParser.scala"
public class org.sireum.parser.Json$State$$String$ extends java.lang.Object implements org.sireum.$ZCompanionString<org.sireum.parser.Json$State>
  minor version: 0
  major version: 52
  flags: (0x0021) ACC_PUBLIC, ACC_SUPER
  this_class: #2                          // org/sireum/parser/Json$State$$String$
  super_class: #5                         // java/lang/Object
  interfaces: 1, fields: 1, methods: 6, attributes: 5
Constant pool:
    #1 = Utf8               org/sireum/parser/Json$State$$String$
    #2 = Class              #1            // org/sireum/parser/Json$State$$String$
    #3 = Utf8               Ljava/lang/Object;Lorg/sireum/$ZCompanionString<Lorg/sireum/parser/Json$State;>;
    #4 = Utf8               java/lang/Object
    #5 = Class              #4            // java/lang/Object
    #6 = Utf8               org/sireum/$ZCompanionString
    #7 = Class              #6            // org/sireum/$ZCompanionString
    #8 = Utf8               JsonParser.scala
    #9 = Utf8               org/sireum/Z$$String$
   #10 = Class              #9            // org/sireum/Z$$String$
   #11 = Utf8               org/sireum/Z
   #12 = Class              #11           // org/sireum/Z
   #13 = Utf8               $String$
   #14 = Utf8               org/sireum/parser/Json$State
   #15 = Class              #14           // org/sireum/parser/Json$State
   #16 = Utf8               org/sireum/parser/Json
   #17 = Class              #16           // org/sireum/parser/Json
   #18 = Utf8               State
   #19 = Utf8               org/sireum/parser/Json$State$
   #20 = Class              #19           // org/sireum/parser/Json$State$
   #21 = Utf8               State$
   #22 = Utf8               org/sireum/parser/Json$State$BigInt$
   #23 = Class              #22           // org/sireum/parser/Json$State$BigInt$
   #24 = Utf8               BigInt$
   #25 = Utf8               MODULE$
   #26 = Utf8               Lorg/sireum/parser/Json$State$$String$;
   #27 = Utf8               <clinit>
   #28 = Utf8               ()V
   #29 = Utf8               <init>
   #30 = NameAndType        #29:#28       // "<init>":()V
   #31 = Methodref          #2.#30        // org/sireum/parser/Json$State$$String$."<init>":()V
   #32 = NameAndType        #25:#26       // MODULE$:Lorg/sireum/parser/Json$State$$String$;
   #33 = Fieldref           #2.#32        // org/sireum/parser/Json$State$$String$.MODULE$:Lorg/sireum/parser/Json$State$$String$;
   #34 = Utf8               apply
   #35 = Utf8               (Ljava/lang/String;)Lorg/sireum/Z;
   #36 = Utf8               s
   #37 = Utf8               Lorg/sireum/parser/Json$State$BigInt$;
   #38 = NameAndType        #25:#37       // MODULE$:Lorg/sireum/parser/Json$State$BigInt$;
   #39 = Fieldref           #23.#38       // org/sireum/parser/Json$State$BigInt$.MODULE$:Lorg/sireum/parser/Json$State$BigInt$;
   #40 = Utf8               Lorg/sireum/Z$$String$;
   #41 = NameAndType        #25:#40       // MODULE$:Lorg/sireum/Z$$String$;
   #42 = Fieldref           #10.#41       // org/sireum/Z$$String$.MODULE$:Lorg/sireum/Z$$String$;
   #43 = NameAndType        #34:#35       // apply:(Ljava/lang/String;)Lorg/sireum/Z;
   #44 = Methodref          #10.#43       // org/sireum/Z$$String$.apply:(Ljava/lang/String;)Lorg/sireum/Z;
   #45 = Utf8               toBigInt
   #46 = Utf8               ()Lscala/math/BigInt;
   #47 = NameAndType        #45:#46       // toBigInt:()Lscala/math/BigInt;
   #48 = InterfaceMethodref #12.#47       // org/sireum/Z.toBigInt:()Lscala/math/BigInt;
   #49 = Utf8               (Lscala/math/BigInt;)Lorg/sireum/Z;
   #50 = NameAndType        #34:#49       // apply:(Lscala/math/BigInt;)Lorg/sireum/Z;
   #51 = Methodref          #23.#50       // org/sireum/parser/Json$State$BigInt$.apply:(Lscala/math/BigInt;)Lorg/sireum/Z;
   #52 = Utf8               this
   #53 = Utf8               Ljava/lang/String;
   #54 = Utf8               unapply
   #55 = Utf8               (Lorg/sireum/Z;)Lscala/Option;
   #56 = Utf8               (Lorg/sireum/Z;)Lscala/Option<Ljava/lang/String;>;
   #57 = Utf8               n
   #58 = Utf8               scala/Some
   #59 = Class              #58           // scala/Some
   #60 = Utf8               (Lorg/sireum/Z;)V
   #61 = NameAndType        #29:#60       // "<init>":(Lorg/sireum/Z;)V
   #62 = Methodref          #15.#61       // org/sireum/parser/Json$State."<init>":(Lorg/sireum/Z;)V
   #63 = Methodref          #15.#47       // org/sireum/parser/Json$State.toBigInt:()Lscala/math/BigInt;
   #64 = Utf8               scala/math/BigInt
   #65 = Class              #64           // scala/math/BigInt
   #66 = Utf8               toString
   #67 = Utf8               ()Ljava/lang/String;
   #68 = NameAndType        #66:#67       // toString:()Ljava/lang/String;
   #69 = Methodref          #65.#68       // scala/math/BigInt.toString:()Ljava/lang/String;
   #70 = Utf8               (Ljava/lang/Object;)V
   #71 = NameAndType        #29:#70       // "<init>":(Ljava/lang/Object;)V
   #72 = Methodref          #59.#71       // scala/Some."<init>":(Ljava/lang/Object;)V
   #73 = Utf8               Lorg/sireum/Z;
   #74 = Utf8               (Ljava/lang/Object;)Lscala/Option;
   #75 = Utf8               value
   #76 = Utf8               ()Lorg/sireum/Z;
   #77 = NameAndType        #75:#76       // value:()Lorg/sireum/Z;
   #78 = Methodref          #15.#77       // org/sireum/parser/Json$State.value:()Lorg/sireum/Z;
   #79 = NameAndType        #54:#55       // unapply:(Lorg/sireum/Z;)Lscala/Option;
   #80 = Methodref          #2.#79        // org/sireum/parser/Json$State$$String$.unapply:(Lorg/sireum/Z;)Lscala/Option;
   #81 = Utf8               scala/None$
   #82 = Class              #81           // scala/None$
   #83 = Utf8               Lscala/None$;
   #84 = NameAndType        #25:#83       // MODULE$:Lscala/None$;
   #85 = Fieldref           #82.#84       // scala/None$.MODULE$:Lscala/None$;
   #86 = Utf8               Ljava/lang/Object;
   #87 = Utf8               scala/Option
   #88 = Class              #87           // scala/Option
   #89 = Utf8               (Ljava/lang/String;)Ljava/lang/Object;
   #90 = Methodref          #2.#43        // org/sireum/parser/Json$State$$String$.apply:(Ljava/lang/String;)Lorg/sireum/Z;
   #91 = Methodref          #5.#30        // java/lang/Object."<init>":()V
   #92 = Utf8               Code
   #93 = Utf8               LineNumberTable
   #94 = Utf8               LocalVariableTable
   #95 = Utf8               MethodParameters
   #96 = Utf8               Signature
   #97 = Utf8               StackMapTable
   #98 = Utf8               InnerClasses
   #99 = Utf8               SourceFile
  #100 = Utf8               ScalaInlineInfo
  #101 = Utf8               Scala
{
  public static final org.sireum.parser.Json$State$$String$ MODULE$;
    descriptor: Lorg/sireum/parser/Json$State$$String$;
    flags: (0x0019) ACC_PUBLIC, ACC_STATIC, ACC_FINAL

  public static {};
    descriptor: ()V
    flags: (0x0009) ACC_PUBLIC, ACC_STATIC
    Code:
      stack=2, locals=0, args_size=0
         0: new           #2                  // class org/sireum/parser/Json$State$$String$
         3: dup
         4: invokespecial #31                 // Method "<init>":()V
         7: putstatic     #33                 // Field MODULE$:Lorg/sireum/parser/Json$State$$String$;
        10: return
      LineNumberTable:
        line 38: 0

  public org.sireum.Z apply(java.lang.String);
    descriptor: (Ljava/lang/String;)Lorg/sireum/Z;
    flags: (0x0001) ACC_PUBLIC
    Code:
      stack=3, locals=2, args_size=2
         0: getstatic     #39                 // Field org/sireum/parser/Json$State$BigInt$.MODULE$:Lorg/sireum/parser/Json$State$BigInt$;
         3: getstatic     #42                 // Field org/sireum/Z$$String$.MODULE$:Lorg/sireum/Z$$String$;
         6: aload_1
         7: invokevirtual #44                 // Method org/sireum/Z$$String$.apply:(Ljava/lang/String;)Lorg/sireum/Z;
        10: invokeinterface #48,  1           // InterfaceMethod org/sireum/Z.toBigInt:()Lscala/math/BigInt;
        15: invokevirtual #51                 // Method org/sireum/parser/Json$State$BigInt$.apply:(Lscala/math/BigInt;)Lorg/sireum/Z;
        18: areturn
      LineNumberTable:
        line 38: 0
      LocalVariableTable:
        Start  Length  Slot  Name   Signature
            0      19     0  this   Lorg/sireum/parser/Json$State$$String$;
            0      19     1     s   Ljava/lang/String;
    MethodParameters:
      Name                           Flags
      s                              final

  public scala.Option<java.lang.String> unapply(org.sireum.Z);
    descriptor: (Lorg/sireum/Z;)Lscala/Option;
    flags: (0x0001) ACC_PUBLIC
    Code:
      stack=5, locals=2, args_size=2
         0: new           #59                 // class scala/Some
         3: dup
         4: new           #15                 // class org/sireum/parser/Json$State
         7: dup
         8: aload_1
         9: invokespecial #62                 // Method org/sireum/parser/Json$State."<init>":(Lorg/sireum/Z;)V
        12: invokevirtual #63                 // Method org/sireum/parser/Json$State.toBigInt:()Lscala/math/BigInt;
        15: invokevirtual #69                 // Method scala/math/BigInt.toString:()Ljava/lang/String;
        18: invokespecial #72                 // Method scala/Some."<init>":(Ljava/lang/Object;)V
        21: areturn
      LineNumberTable:
        line 38: 0
      LocalVariableTable:
        Start  Length  Slot  Name   Signature
            0      22     0  this   Lorg/sireum/parser/Json$State$$String$;
            0      22     1     n   Lorg/sireum/Z;
    Signature: #56                          // (Lorg/sireum/Z;)Lscala/Option<Ljava/lang/String;>;
    MethodParameters:
      Name                           Flags
      n                              final

  public scala.Option unapply(java.lang.Object);
    descriptor: (Ljava/lang/Object;)Lscala/Option;
    flags: (0x1041) ACC_PUBLIC, ACC_BRIDGE, ACC_SYNTHETIC
    Code:
      stack=2, locals=2, args_size=2
         0: aload_1
         1: instanceof    #15                 // class org/sireum/parser/Json$State
         4: ifeq          21
         7: aload_0
         8: aload_1
         9: checkcast     #15                 // class org/sireum/parser/Json$State
        12: invokevirtual #78                 // Method org/sireum/parser/Json$State.value:()Lorg/sireum/Z;
        15: invokevirtual #80                 // Method unapply:(Lorg/sireum/Z;)Lscala/Option;
        18: goto          24
        21: getstatic     #85                 // Field scala/None$.MODULE$:Lscala/None$;
        24: areturn
      StackMapTable: number_of_entries = 2
        frame_type = 21 /* same */
        frame_type = 66 /* same_locals_1_stack_item */
          stack = [ class scala/Option ]
      LineNumberTable:
        line 38: 0
      LocalVariableTable:
        Start  Length  Slot  Name   Signature
            0      25     0  this   Lorg/sireum/parser/Json$State$$String$;
            0      25     1     n   Ljava/lang/Object;
    MethodParameters:
      Name                           Flags
      n                              final

  public java.lang.Object apply(java.lang.String);
    descriptor: (Ljava/lang/String;)Ljava/lang/Object;
    flags: (0x1041) ACC_PUBLIC, ACC_BRIDGE, ACC_SYNTHETIC
    Code:
      stack=4, locals=2, args_size=2
         0: new           #15                 // class org/sireum/parser/Json$State
         3: dup
         4: aload_0
         5: aload_1
         6: invokevirtual #90                 // Method apply:(Ljava/lang/String;)Lorg/sireum/Z;
         9: invokespecial #62                 // Method org/sireum/parser/Json$State."<init>":(Lorg/sireum/Z;)V
        12: areturn
      LineNumberTable:
        line 38: 0
      LocalVariableTable:
        Start  Length  Slot  Name   Signature
            0      13     0  this   Lorg/sireum/parser/Json$State$$String$;
            0      13     1     s   Ljava/lang/String;
    MethodParameters:
      Name                           Flags
      s                              final

  public org.sireum.parser.Json$State$$String$();
    descriptor: ()V
    flags: (0x0001) ACC_PUBLIC
    Code:
      stack=1, locals=1, args_size=1
         0: aload_0
         1: invokespecial #91                 // Method java/lang/Object."<init>":()V
         4: return
      LineNumberTable:
        line 38: 0
      LocalVariableTable:
        Start  Length  Slot  Name   Signature
            0       5     0  this   Lorg/sireum/parser/Json$State$$String$;
}
InnerClasses:
  public static #13= #10 of #12;          // $String$=class org/sireum/Z$$String$ of class org/sireum/Z
  public static final #18= #15 of #17;    // State=class org/sireum/parser/Json$State of class org/sireum/parser/Json
  public static #21= #20 of #17;          // State$=class org/sireum/parser/Json$State$ of class org/sireum/parser/Json
  public static #13= #2 of #20;           // $String$=class org/sireum/parser/Json$State$$String$ of class org/sireum/parser/Json$State$
  public static #24= #23 of #20;          // BigInt$=class org/sireum/parser/Json$State$BigInt$ of class org/sireum/parser/Json$State$
Signature: #3                           // Ljava/lang/Object;Lorg/sireum/$ZCompanionString<Lorg/sireum/parser/Json$State;>;
SourceFile: "JsonParser.scala"
  ScalaInlineInfo: length = 0x1D (unknown attribute)
   01 01 00 05 00 1D 00 1C 01 00 22 00 59 01 00 22
   00 23 01 00 36 00 4A 01 00 36 00 37 01
  Scala: length = 0x0 (unknown attribute)

