Classfile /Users/mw/Projects/slang-braindump/.jar/jar11/assemble/slang-braindump/assemble/content/org/scalatest/prop/Configuration$Parameter.class
  Last modified May 29, 2022; size 5592 bytes
  SHA-256 checksum 1339d7e745d9b272fbc453332eb13e20ba4dacb9e1031c4cdde62c33c3794672
  Compiled from "Configuration.scala"
public class org.scalatest.prop.Configuration$Parameter implements scala.Product,java.io.Serializable
  minor version: 0
  major version: 52
  flags: (0x0021) ACC_PUBLIC, ACC_SUPER
  this_class: #2                          // org/scalatest/prop/Configuration$Parameter
  super_class: #4                         // java/lang/Object
  interfaces: 2, fields: 7, methods: 24, attributes: 4
Constant pool:
    #1 = Utf8               org/scalatest/prop/Configuration$Parameter
    #2 = Class              #1            // org/scalatest/prop/Configuration$Parameter
    #3 = Utf8               java/lang/Object
    #4 = Class              #3            // java/lang/Object
    #5 = Utf8               scala/Product
    #6 = Class              #5            // scala/Product
    #7 = Utf8               java/io/Serializable
    #8 = Class              #7            // java/io/Serializable
    #9 = Utf8               Configuration.scala
   #10 = Utf8               org/scalactic/Requirements$RequirementsHelper
   #11 = Class              #10           // org/scalactic/Requirements$RequirementsHelper
   #12 = Utf8               org/scalactic/Requirements
   #13 = Class              #12           // org/scalactic/Requirements
   #14 = Utf8               RequirementsHelper
   #15 = Utf8               org/scalatest/prop/Configuration
   #16 = Class              #15           // org/scalatest/prop/Configuration
   #17 = Utf8               Parameter
   #18 = Utf8               maxSize
   #19 = Utf8               I
   #20 = Utf8               minSuccessful
   #21 = Utf8               maxDiscardedFactor
   #22 = Utf8               D
   #23 = Utf8               minSize
   #24 = Utf8               sizeRange
   #25 = Utf8               workers
   #26 = Utf8               bitmap$0
   #27 = Utf8               Z
   #28 = Utf8               productElementNames
   #29 = Utf8               ()Lscala/collection/Iterator;
   #30 = Utf8               ()Lscala/collection/Iterator<Ljava/lang/String;>;
   #31 = Utf8               productElementNames$
   #32 = Utf8               (Lscala/Product;)Lscala/collection/Iterator;
   #33 = NameAndType        #31:#32       // productElementNames$:(Lscala/Product;)Lscala/collection/Iterator;
   #34 = InterfaceMethodref #6.#33        // scala/Product.productElementNames$:(Lscala/Product;)Lscala/collection/Iterator;
   #35 = Utf8               this
   #36 = Utf8               Lorg/scalatest/prop/Configuration$Parameter;
   #37 = Utf8               ()I
   #38 = NameAndType        #20:#19       // minSuccessful:I
   #39 = Fieldref           #2.#38        // org/scalatest/prop/Configuration$Parameter.minSuccessful:I
   #40 = Utf8               ()D
   #41 = NameAndType        #21:#22       // maxDiscardedFactor:D
   #42 = Fieldref           #2.#41        // org/scalatest/prop/Configuration$Parameter.maxDiscardedFactor:D
   #43 = NameAndType        #23:#19       // minSize:I
   #44 = Fieldref           #2.#43        // org/scalatest/prop/Configuration$Parameter.minSize:I
   #45 = NameAndType        #24:#19       // sizeRange:I
   #46 = Fieldref           #2.#45        // org/scalatest/prop/Configuration$Parameter.sizeRange:I
   #47 = NameAndType        #25:#19       // workers:I
   #48 = Fieldref           #2.#47        // org/scalatest/prop/Configuration$Parameter.workers:I
   #49 = Utf8               maxSize$lzycompute
   #50 = NameAndType        #26:#27       // bitmap$0:Z
   #51 = Fieldref           #2.#50        // org/scalatest/prop/Configuration$Parameter.bitmap$0:Z
   #52 = Utf8               org/scalactic/anyvals/PosZInt$
   #53 = Class              #52           // org/scalactic/anyvals/PosZInt$
   #54 = Utf8               MODULE$
   #55 = Utf8               Lorg/scalactic/anyvals/PosZInt$;
   #56 = NameAndType        #54:#55       // MODULE$:Lorg/scalactic/anyvals/PosZInt$;
   #57 = Fieldref           #53.#56       // org/scalactic/anyvals/PosZInt$.MODULE$:Lorg/scalactic/anyvals/PosZInt$;
   #58 = NameAndType        #23:#37       // minSize:()I
   #59 = Methodref          #2.#58        // org/scalatest/prop/Configuration$Parameter.minSize:()I
   #60 = NameAndType        #24:#37       // sizeRange:()I
   #61 = Methodref          #2.#60        // org/scalatest/prop/Configuration$Parameter.sizeRange:()I
   #62 = Utf8               ensuringValid
   #63 = Utf8               (I)I
   #64 = NameAndType        #62:#63       // ensuringValid:(I)I
   #65 = Methodref          #53.#64       // org/scalactic/anyvals/PosZInt$.ensuringValid:(I)I
   #66 = NameAndType        #18:#19       // maxSize:I
   #67 = Fieldref           #2.#66        // org/scalatest/prop/Configuration$Parameter.maxSize:I
   #68 = Utf8               java/lang/Throwable
   #69 = Class              #68           // java/lang/Throwable
   #70 = NameAndType        #49:#37       // maxSize$lzycompute:()I
   #71 = Methodref          #2.#70        // org/scalatest/prop/Configuration$Parameter.maxSize$lzycompute:()I
   #72 = Utf8               copy
   #73 = Utf8               (IDIII)Lorg/scalatest/prop/Configuration$Parameter;
   #74 = Utf8               <init>
   #75 = Utf8               (IDIII)V
   #76 = NameAndType        #74:#75       // "<init>":(IDIII)V
   #77 = Methodref          #2.#76        // org/scalatest/prop/Configuration$Parameter."<init>":(IDIII)V
   #78 = Utf8               copy$default$1
   #79 = NameAndType        #20:#37       // minSuccessful:()I
   #80 = Methodref          #2.#79        // org/scalatest/prop/Configuration$Parameter.minSuccessful:()I
   #81 = Utf8               copy$default$2
   #82 = NameAndType        #21:#40       // maxDiscardedFactor:()D
   #83 = Methodref          #2.#82        // org/scalatest/prop/Configuration$Parameter.maxDiscardedFactor:()D
   #84 = Utf8               copy$default$3
   #85 = Utf8               copy$default$4
   #86 = Utf8               copy$default$5
   #87 = NameAndType        #25:#37       // workers:()I
   #88 = Methodref          #2.#87        // org/scalatest/prop/Configuration$Parameter.workers:()I
   #89 = Utf8               productPrefix
   #90 = Utf8               ()Ljava/lang/String;
   #91 = String             #17           // Parameter
   #92 = Utf8               productArity
   #93 = Utf8               productElement
   #94 = Utf8               (I)Ljava/lang/Object;
   #95 = Utf8               x$1
   #96 = Utf8               org/scalactic/anyvals/PosInt
   #97 = Class              #96           // org/scalactic/anyvals/PosInt
   #98 = Utf8               (I)V
   #99 = NameAndType        #74:#98       // "<init>":(I)V
  #100 = Methodref          #97.#99       // org/scalactic/anyvals/PosInt."<init>":(I)V
  #101 = Utf8               org/scalactic/anyvals/PosZDouble
  #102 = Class              #101          // org/scalactic/anyvals/PosZDouble
  #103 = Utf8               (D)V
  #104 = NameAndType        #74:#103      // "<init>":(D)V
  #105 = Methodref          #102.#104     // org/scalactic/anyvals/PosZDouble."<init>":(D)V
  #106 = Utf8               org/scalactic/anyvals/PosZInt
  #107 = Class              #106          // org/scalactic/anyvals/PosZInt
  #108 = Methodref          #107.#99      // org/scalactic/anyvals/PosZInt."<init>":(I)V
  #109 = Utf8               scala/runtime/Statics
  #110 = Class              #109          // scala/runtime/Statics
  #111 = Utf8               ioobe
  #112 = NameAndType        #111:#94      // ioobe:(I)Ljava/lang/Object;
  #113 = Methodref          #110.#112     // scala/runtime/Statics.ioobe:(I)Ljava/lang/Object;
  #114 = Utf8               productIterator
  #115 = Utf8               ()Lscala/collection/Iterator<Ljava/lang/Object;>;
  #116 = Utf8               scala/runtime/ScalaRunTime$
  #117 = Class              #116          // scala/runtime/ScalaRunTime$
  #118 = Utf8               Lscala/runtime/ScalaRunTime$;
  #119 = NameAndType        #54:#118      // MODULE$:Lscala/runtime/ScalaRunTime$;
  #120 = Fieldref           #117.#119     // scala/runtime/ScalaRunTime$.MODULE$:Lscala/runtime/ScalaRunTime$;
  #121 = Utf8               typedProductIterator
  #122 = NameAndType        #121:#32      // typedProductIterator:(Lscala/Product;)Lscala/collection/Iterator;
  #123 = Methodref          #117.#122     // scala/runtime/ScalaRunTime$.typedProductIterator:(Lscala/Product;)Lscala/collection/Iterator;
  #124 = Utf8               canEqual
  #125 = Utf8               (Ljava/lang/Object;)Z
  #126 = Utf8               Ljava/lang/Object;
  #127 = Utf8               productElementName
  #128 = Utf8               (I)Ljava/lang/String;
  #129 = String             #20           // minSuccessful
  #130 = String             #21           // maxDiscardedFactor
  #131 = String             #23           // minSize
  #132 = String             #24           // sizeRange
  #133 = String             #25           // workers
  #134 = Utf8               java/lang/String
  #135 = Class              #134          // java/lang/String
  #136 = Utf8               hashCode
  #137 = Utf8               _hashCode
  #138 = Utf8               (Lscala/Product;)I
  #139 = NameAndType        #137:#138     // _hashCode:(Lscala/Product;)I
  #140 = Methodref          #117.#139     // scala/runtime/ScalaRunTime$._hashCode:(Lscala/Product;)I
  #141 = Utf8               toString
  #142 = Utf8               _toString
  #143 = Utf8               (Lscala/Product;)Ljava/lang/String;
  #144 = NameAndType        #142:#143     // _toString:(Lscala/Product;)Ljava/lang/String;
  #145 = Methodref          #117.#144     // scala/runtime/ScalaRunTime$._toString:(Lscala/Product;)Ljava/lang/String;
  #146 = Utf8               equals
  #147 = NameAndType        #124:#125     // canEqual:(Ljava/lang/Object;)Z
  #148 = Methodref          #2.#147       // org/scalatest/prop/Configuration$Parameter.canEqual:(Ljava/lang/Object;)Z
  #149 = Utf8               ()V
  #150 = NameAndType        #74:#149      // "<init>":()V
  #151 = Methodref          #4.#150       // java/lang/Object."<init>":()V
  #152 = Utf8               $init$
  #153 = Utf8               (Lscala/Product;)V
  #154 = NameAndType        #152:#153     // $init$:(Lscala/Product;)V
  #155 = InterfaceMethodref #6.#154       // scala/Product.$init$:(Lscala/Product;)V
  #156 = Utf8               org/scalactic/Bool$
  #157 = Class              #156          // org/scalactic/Bool$
  #158 = Utf8               Lorg/scalactic/Bool$;
  #159 = NameAndType        #54:#158      // MODULE$:Lorg/scalactic/Bool$;
  #160 = Fieldref           #157.#159     // org/scalactic/Bool$.MODULE$:Lorg/scalactic/Bool$;
  #161 = Utf8               scala/runtime/BoxesRunTime
  #162 = Class              #161          // scala/runtime/BoxesRunTime
  #163 = Utf8               boxToInteger
  #164 = Utf8               (I)Ljava/lang/Integer;
  #165 = NameAndType        #163:#164     // boxToInteger:(I)Ljava/lang/Integer;
  #166 = Methodref          #162.#165     // scala/runtime/BoxesRunTime.boxToInteger:(I)Ljava/lang/Integer;
  #167 = Utf8               >=
  #168 = String             #167          // >=
  #169 = Utf8               org/scalactic/Prettifier$
  #170 = Class              #169          // org/scalactic/Prettifier$
  #171 = Utf8               Lorg/scalactic/Prettifier$;
  #172 = NameAndType        #54:#171      // MODULE$:Lorg/scalactic/Prettifier$;
  #173 = Fieldref           #170.#172     // org/scalactic/Prettifier$.MODULE$:Lorg/scalactic/Prettifier$;
  #174 = Utf8               default
  #175 = Utf8               ()Lorg/scalactic/Prettifier;
  #176 = NameAndType        #174:#175     // default:()Lorg/scalactic/Prettifier;
  #177 = Methodref          #170.#176     // org/scalactic/Prettifier$.default:()Lorg/scalactic/Prettifier;
  #178 = Utf8               binaryMacroBool
  #179 = Utf8               (Ljava/lang/Object;Ljava/lang/String;Ljava/lang/Object;ZLorg/scalactic/Prettifier;)Lorg/scalactic/Bool;
  #180 = NameAndType        #178:#179     // binaryMacroBool:(Ljava/lang/Object;Ljava/lang/String;Ljava/lang/Object;ZLorg/scalactic/Prettifier;)Lorg/scalactic/Bool;
  #181 = Methodref          #157.#180     // org/scalactic/Bool$.binaryMacroBool:(Ljava/lang/Object;Ljava/lang/String;Ljava/lang/Object;ZLorg/scalactic/Prettifier;)Lorg/scalactic/Bool;
  #182 = Utf8               org/scalactic/Requirements$
  #183 = Class              #182          // org/scalactic/Requirements$
  #184 = Utf8               Lorg/scalactic/Requirements$;
  #185 = NameAndType        #54:#184      // MODULE$:Lorg/scalactic/Requirements$;
  #186 = Fieldref           #183.#185     // org/scalactic/Requirements$.MODULE$:Lorg/scalactic/Requirements$;
  #187 = Utf8               requirementsHelper
  #188 = Utf8               ()Lorg/scalactic/Requirements$RequirementsHelper;
  #189 = NameAndType        #187:#188     // requirementsHelper:()Lorg/scalactic/Requirements$RequirementsHelper;
  #190 = Methodref          #183.#189     // org/scalactic/Requirements$.requirementsHelper:()Lorg/scalactic/Requirements$RequirementsHelper;
  #191 = Utf8
  #192 = String             #191          //
  #193 = Utf8               macroRequire
  #194 = Utf8               (Lorg/scalactic/Bool;Ljava/lang/Object;)V
  #195 = NameAndType        #193:#194     // macroRequire:(Lorg/scalactic/Bool;Ljava/lang/Object;)V
  #196 = Methodref          #11.#195      // org/scalactic/Requirements$RequirementsHelper.macroRequire:(Lorg/scalactic/Bool;Ljava/lang/Object;)V
  #197 = Utf8               $org_scalatest_assert_macro_left
  #198 = Utf8               $org_scalatest_assert_macro_right
  #199 = Utf8               $org_scalatest_assert_macro_expr
  #200 = Utf8               Lorg/scalactic/Bool;
  #201 = Utf8               java/lang/Integer
  #202 = Class              #201          // java/lang/Integer
  #203 = Utf8               Code
  #204 = Utf8               LineNumberTable
  #205 = Utf8               LocalVariableTable
  #206 = Utf8               Signature
  #207 = Utf8               StackMapTable
  #208 = Utf8               MethodParameters
  #209 = Utf8               InnerClasses
  #210 = Utf8               SourceFile
  #211 = Utf8               ScalaInlineInfo
  #212 = Utf8               Scala
{
  private int maxSize;
    descriptor: I
    flags: (0x0002) ACC_PRIVATE

  private final int minSuccessful;
    descriptor: I
    flags: (0x0012) ACC_PRIVATE, ACC_FINAL

  private final double maxDiscardedFactor;
    descriptor: D
    flags: (0x0012) ACC_PRIVATE, ACC_FINAL

  private final int minSize;
    descriptor: I
    flags: (0x0012) ACC_PRIVATE, ACC_FINAL

  private final int sizeRange;
    descriptor: I
    flags: (0x0012) ACC_PRIVATE, ACC_FINAL

  private final int workers;
    descriptor: I
    flags: (0x0012) ACC_PRIVATE, ACC_FINAL

  private volatile boolean bitmap$0;
    descriptor: Z
    flags: (0x0042) ACC_PRIVATE, ACC_VOLATILE

  public scala.collection.Iterator<java.lang.String> productElementNames();
    descriptor: ()Lscala/collection/Iterator;
    flags: (0x0001) ACC_PUBLIC
    Code:
      stack=1, locals=1, args_size=1
         0: aload_0
         1: invokestatic  #34                 // InterfaceMethod scala/Product.productElementNames$:(Lscala/Product;)Lscala/collection/Iterator;
         4: areturn
      LineNumberTable:
        line 362: 0
      LocalVariableTable:
        Start  Length  Slot  Name   Signature
            0       5     0  this   Lorg/scalatest/prop/Configuration$Parameter;
    Signature: #30                          // ()Lscala/collection/Iterator<Ljava/lang/String;>;

  public int minSuccessful();
    descriptor: ()I
    flags: (0x0001) ACC_PUBLIC
    Code:
      stack=1, locals=1, args_size=1
         0: aload_0
         1: getfield      #39                 // Field minSuccessful:I
         4: ireturn
      LineNumberTable:
        line 362: 0
      LocalVariableTable:
        Start  Length  Slot  Name   Signature
            0       5     0  this   Lorg/scalatest/prop/Configuration$Parameter;

  public double maxDiscardedFactor();
    descriptor: ()D
    flags: (0x0001) ACC_PUBLIC
    Code:
      stack=2, locals=1, args_size=1
         0: aload_0
         1: getfield      #42                 // Field maxDiscardedFactor:D
         4: dreturn
      LineNumberTable:
        line 363: 0
      LocalVariableTable:
        Start  Length  Slot  Name   Signature
            0       5     0  this   Lorg/scalatest/prop/Configuration$Parameter;

  public int minSize();
    descriptor: ()I
    flags: (0x0001) ACC_PUBLIC
    Code:
      stack=1, locals=1, args_size=1
         0: aload_0
         1: getfield      #44                 // Field minSize:I
         4: ireturn
      LineNumberTable:
        line 364: 0
      LocalVariableTable:
        Start  Length  Slot  Name   Signature
            0       5     0  this   Lorg/scalatest/prop/Configuration$Parameter;

  public int sizeRange();
    descriptor: ()I
    flags: (0x0001) ACC_PUBLIC
    Code:
      stack=1, locals=1, args_size=1
         0: aload_0
         1: getfield      #46                 // Field sizeRange:I
         4: ireturn
      LineNumberTable:
        line 365: 0
      LocalVariableTable:
        Start  Length  Slot  Name   Signature
            0       5     0  this   Lorg/scalatest/prop/Configuration$Parameter;

  public int workers();
    descriptor: ()I
    flags: (0x0001) ACC_PUBLIC
    Code:
      stack=1, locals=1, args_size=1
         0: aload_0
         1: getfield      #48                 // Field workers:I
         4: ireturn
      LineNumberTable:
        line 366: 0
      LocalVariableTable:
        Start  Length  Slot  Name   Signature
            0       5     0  this   Lorg/scalatest/prop/Configuration$Parameter;

  private int maxSize$lzycompute();
    descriptor: ()I
    flags: (0x0002) ACC_PRIVATE
    Code:
      stack=4, locals=2, args_size=1
         0: aload_0
         1: dup
         2: astore_1
         3: monitorenter
         4: aload_0
         5: getfield      #51                 // Field bitmap$0:Z
         8: ifne          35
        11: aload_0
        12: getstatic     #57                 // Field org/scalactic/anyvals/PosZInt$.MODULE$:Lorg/scalactic/anyvals/PosZInt$;
        15: aload_0
        16: invokevirtual #59                 // Method minSize:()I
        19: aload_0
        20: invokevirtual #61                 // Method sizeRange:()I
        23: iadd
        24: invokevirtual #65                 // Method org/scalactic/anyvals/PosZInt$.ensuringValid:(I)I
        27: putfield      #67                 // Field maxSize:I
        30: aload_0
        31: iconst_1
        32: putfield      #51                 // Field bitmap$0:Z
        35: aload_1
        36: monitorexit
        37: goto          43
        40: aload_1
        41: monitorexit
        42: athrow
        43: aload_0
        44: getfield      #67                 // Field maxSize:I
        47: ireturn
      Exception table:
         from    to  target type
             4    35    40   any
      StackMapTable: number_of_entries = 3
        frame_type = 252 /* append */
          offset_delta = 35
          locals = [ class org/scalatest/prop/Configuration$Parameter ]
        frame_type = 68 /* same_locals_1_stack_item */
          stack = [ class java/lang/Throwable ]
        frame_type = 2 /* same */
      LineNumberTable:
        line 372: 0
        line 373: 12
        line 372: 27
      LocalVariableTable:
        Start  Length  Slot  Name   Signature
            0      48     0  this   Lorg/scalatest/prop/Configuration$Parameter;

  public int maxSize();
    descriptor: ()I
    flags: (0x0001) ACC_PUBLIC
    Code:
      stack=1, locals=1, args_size=1
         0: aload_0
         1: getfield      #51                 // Field bitmap$0:Z
         4: ifne          14
         7: aload_0
         8: invokespecial #71                 // Method maxSize$lzycompute:()I
        11: goto          18
        14: aload_0
        15: getfield      #67                 // Field maxSize:I
        18: ireturn
      StackMapTable: number_of_entries = 2
        frame_type = 14 /* same */
        frame_type = 67 /* same_locals_1_stack_item */
          stack = [ int ]
      LineNumberTable:
        line 372: 0
      LocalVariableTable:
        Start  Length  Slot  Name   Signature
            0      19     0  this   Lorg/scalatest/prop/Configuration$Parameter;

  public org.scalatest.prop.Configuration$Parameter copy(int, double, int, int, int);
    descriptor: (IDIII)Lorg/scalatest/prop/Configuration$Parameter;
    flags: (0x0001) ACC_PUBLIC
    Code:
      stack=8, locals=7, args_size=6
         0: new           #2                  // class org/scalatest/prop/Configuration$Parameter
         3: dup
         4: iload_1
         5: dload_2
         6: iload         4
         8: iload         5
        10: iload         6
        12: invokespecial #77                 // Method "<init>":(IDIII)V
        15: areturn
      LineNumberTable:
        line 362: 0
        line 363: 5
        line 364: 6
        line 365: 8
        line 366: 10
      LocalVariableTable:
        Start  Length  Slot  Name   Signature
            0      16     0  this   Lorg/scalatest/prop/Configuration$Parameter;
            0      16     1 minSuccessful   I
            0      16     2 maxDiscardedFactor   D
            0      16     4 minSize   I
            0      16     5 sizeRange   I
            0      16     6 workers   I
    MethodParameters:
      Name                           Flags
      minSuccessful                  final
      maxDiscardedFactor             final
      minSize                        final
      sizeRange                      final
      workers                        final

  public int copy$default$1();
    descriptor: ()I
    flags: (0x0001) ACC_PUBLIC
    Code:
      stack=1, locals=1, args_size=1
         0: aload_0
         1: invokevirtual #80                 // Method minSuccessful:()I
         4: ireturn
      LineNumberTable:
        line 362: 0
      LocalVariableTable:
        Start  Length  Slot  Name   Signature
            0       5     0  this   Lorg/scalatest/prop/Configuration$Parameter;

  public double copy$default$2();
    descriptor: ()D
    flags: (0x0001) ACC_PUBLIC
    Code:
      stack=2, locals=1, args_size=1
         0: aload_0
         1: invokevirtual #83                 // Method maxDiscardedFactor:()D
         4: dreturn
      LineNumberTable:
        line 363: 0
      LocalVariableTable:
        Start  Length  Slot  Name   Signature
            0       5     0  this   Lorg/scalatest/prop/Configuration$Parameter;

  public int copy$default$3();
    descriptor: ()I
    flags: (0x0001) ACC_PUBLIC
    Code:
      stack=1, locals=1, args_size=1
         0: aload_0
         1: invokevirtual #59                 // Method minSize:()I
         4: ireturn
      LineNumberTable:
        line 364: 0
      LocalVariableTable:
        Start  Length  Slot  Name   Signature
            0       5     0  this   Lorg/scalatest/prop/Configuration$Parameter;

  public int copy$default$4();
    descriptor: ()I
    flags: (0x0001) ACC_PUBLIC
    Code:
      stack=1, locals=1, args_size=1
         0: aload_0
         1: invokevirtual #61                 // Method sizeRange:()I
         4: ireturn
      LineNumberTable:
        line 365: 0
      LocalVariableTable:
        Start  Length  Slot  Name   Signature
            0       5     0  this   Lorg/scalatest/prop/Configuration$Parameter;

  public int copy$default$5();
    descriptor: ()I
    flags: (0x0001) ACC_PUBLIC
    Code:
      stack=1, locals=1, args_size=1
         0: aload_0
         1: invokevirtual #88                 // Method workers:()I
         4: ireturn
      LineNumberTable:
        line 366: 0
      LocalVariableTable:
        Start  Length  Slot  Name   Signature
            0       5     0  this   Lorg/scalatest/prop/Configuration$Parameter;

  public java.lang.String productPrefix();
    descriptor: ()Ljava/lang/String;
    flags: (0x0001) ACC_PUBLIC
    Code:
      stack=1, locals=1, args_size=1
         0: ldc           #91                 // String Parameter
         2: areturn
      LineNumberTable:
        line 362: 0
      LocalVariableTable:
        Start  Length  Slot  Name   Signature
            0       3     0  this   Lorg/scalatest/prop/Configuration$Parameter;

  public int productArity();
    descriptor: ()I
    flags: (0x0001) ACC_PUBLIC
    Code:
      stack=1, locals=1, args_size=1
         0: iconst_5
         1: ireturn
      LineNumberTable:
        line 362: 0
      LocalVariableTable:
        Start  Length  Slot  Name   Signature
            0       2     0  this   Lorg/scalatest/prop/Configuration$Parameter;

  public java.lang.Object productElement(int);
    descriptor: (I)Ljava/lang/Object;
    flags: (0x0001) ACC_PUBLIC
    Code:
      stack=4, locals=3, args_size=2
         0: iload_1
         1: istore_2
         2: iload_2
         3: tableswitch   { // 0 to 4
                       0: 36
                       1: 50
                       2: 64
                       3: 78
                       4: 92
                 default: 106
            }
        36: new           #97                 // class org/scalactic/anyvals/PosInt
        39: dup
        40: aload_0
        41: invokevirtual #80                 // Method minSuccessful:()I
        44: invokespecial #100                // Method org/scalactic/anyvals/PosInt."<init>":(I)V
        47: goto          113
        50: new           #102                // class org/scalactic/anyvals/PosZDouble
        53: dup
        54: aload_0
        55: invokevirtual #83                 // Method maxDiscardedFactor:()D
        58: invokespecial #105                // Method org/scalactic/anyvals/PosZDouble."<init>":(D)V
        61: goto          113
        64: new           #107                // class org/scalactic/anyvals/PosZInt
        67: dup
        68: aload_0
        69: invokevirtual #59                 // Method minSize:()I
        72: invokespecial #108                // Method org/scalactic/anyvals/PosZInt."<init>":(I)V
        75: goto          113
        78: new           #107                // class org/scalactic/anyvals/PosZInt
        81: dup
        82: aload_0
        83: invokevirtual #61                 // Method sizeRange:()I
        86: invokespecial #108                // Method org/scalactic/anyvals/PosZInt."<init>":(I)V
        89: goto          113
        92: new           #97                 // class org/scalactic/anyvals/PosInt
        95: dup
        96: aload_0
        97: invokevirtual #88                 // Method workers:()I
       100: invokespecial #100                // Method org/scalactic/anyvals/PosInt."<init>":(I)V
       103: goto          113
       106: iload_1
       107: invokestatic  #113                // Method scala/runtime/Statics.ioobe:(I)Ljava/lang/Object;
       110: goto          113
       113: areturn
      StackMapTable: number_of_entries = 7
        frame_type = 252 /* append */
          offset_delta = 36
          locals = [ int ]
        frame_type = 13 /* same */
        frame_type = 13 /* same */
        frame_type = 13 /* same */
        frame_type = 13 /* same */
        frame_type = 13 /* same */
        frame_type = 70 /* same_locals_1_stack_item */
          stack = [ class java/lang/Object ]
      LineNumberTable:
        line 362: 0
      LocalVariableTable:
        Start  Length  Slot  Name   Signature
            0     114     0  this   Lorg/scalatest/prop/Configuration$Parameter;
            0     114     1   x$1   I
    MethodParameters:
      Name                           Flags
      x$1                            final

  public scala.collection.Iterator<java.lang.Object> productIterator();
    descriptor: ()Lscala/collection/Iterator;
    flags: (0x0001) ACC_PUBLIC
    Code:
      stack=2, locals=1, args_size=1
         0: getstatic     #120                // Field scala/runtime/ScalaRunTime$.MODULE$:Lscala/runtime/ScalaRunTime$;
         3: aload_0
         4: invokevirtual #123                // Method scala/runtime/ScalaRunTime$.typedProductIterator:(Lscala/Product;)Lscala/collection/Iterator;
         7: areturn
      LineNumberTable:
        line 362: 0
      LocalVariableTable:
        Start  Length  Slot  Name   Signature
            0       8     0  this   Lorg/scalatest/prop/Configuration$Parameter;
    Signature: #115                         // ()Lscala/collection/Iterator<Ljava/lang/Object;>;

  public boolean canEqual(java.lang.Object);
    descriptor: (Ljava/lang/Object;)Z
    flags: (0x0001) ACC_PUBLIC
    Code:
      stack=1, locals=2, args_size=2
         0: aload_1
         1: instanceof    #2                  // class org/scalatest/prop/Configuration$Parameter
         4: ireturn
      LineNumberTable:
        line 362: 0
      LocalVariableTable:
        Start  Length  Slot  Name   Signature
            0       5     0  this   Lorg/scalatest/prop/Configuration$Parameter;
            0       5     1   x$1   Ljava/lang/Object;
    MethodParameters:
      Name                           Flags
      x$1                            final

  public java.lang.String productElementName(int);
    descriptor: (I)Ljava/lang/String;
    flags: (0x0001) ACC_PUBLIC
    Code:
      stack=1, locals=3, args_size=2
         0: iload_1
         1: istore_2
         2: iload_2
         3: tableswitch   { // 0 to 4
                       0: 36
                       1: 41
                       2: 46
                       3: 51
                       4: 56
                 default: 61
            }
        36: ldc           #129                // String minSuccessful
        38: goto          71
        41: ldc           #130                // String maxDiscardedFactor
        43: goto          71
        46: ldc           #131                // String minSize
        48: goto          71
        51: ldc           #132                // String sizeRange
        53: goto          71
        56: ldc           #133                // String workers
        58: goto          71
        61: iload_1
        62: invokestatic  #113                // Method scala/runtime/Statics.ioobe:(I)Ljava/lang/Object;
        65: checkcast     #135                // class java/lang/String
        68: goto          71
        71: areturn
      StackMapTable: number_of_entries = 7
        frame_type = 252 /* append */
          offset_delta = 36
          locals = [ int ]
        frame_type = 4 /* same */
        frame_type = 4 /* same */
        frame_type = 4 /* same */
        frame_type = 4 /* same */
        frame_type = 4 /* same */
        frame_type = 73 /* same_locals_1_stack_item */
          stack = [ class java/lang/String ]
      LineNumberTable:
        line 362: 0
      LocalVariableTable:
        Start  Length  Slot  Name   Signature
            0      72     0  this   Lorg/scalatest/prop/Configuration$Parameter;
            0      72     1   x$1   I
    MethodParameters:
      Name                           Flags
      x$1                            final

  public int hashCode();
    descriptor: ()I
    flags: (0x0001) ACC_PUBLIC
    Code:
      stack=2, locals=1, args_size=1
         0: getstatic     #120                // Field scala/runtime/ScalaRunTime$.MODULE$:Lscala/runtime/ScalaRunTime$;
         3: aload_0
         4: invokevirtual #140                // Method scala/runtime/ScalaRunTime$._hashCode:(Lscala/Product;)I
         7: ireturn
      LineNumberTable:
        line 362: 0
      LocalVariableTable:
        Start  Length  Slot  Name   Signature
            0       8     0  this   Lorg/scalatest/prop/Configuration$Parameter;

  public java.lang.String toString();
    descriptor: ()Ljava/lang/String;
    flags: (0x0001) ACC_PUBLIC
    Code:
      stack=2, locals=1, args_size=1
         0: getstatic     #120                // Field scala/runtime/ScalaRunTime$.MODULE$:Lscala/runtime/ScalaRunTime$;
         3: aload_0
         4: invokevirtual #145                // Method scala/runtime/ScalaRunTime$._toString:(Lscala/Product;)Ljava/lang/String;
         7: areturn
      LineNumberTable:
        line 362: 0
      LocalVariableTable:
        Start  Length  Slot  Name   Signature
            0       8     0  this   Lorg/scalatest/prop/Configuration$Parameter;

  public boolean equals(java.lang.Object);
    descriptor: (Ljava/lang/Object;)Z
    flags: (0x0001) ACC_PUBLIC
    Code:
      stack=4, locals=5, args_size=2
         0: aload_0
         1: aload_1
         2: if_acmpeq     115
         5: aload_1
         6: astore_3
         7: aload_3
         8: instanceof    #2                  // class org/scalatest/prop/Configuration$Parameter
        11: ifeq          19
        14: iconst_1
        15: istore_2
        16: goto          27
        19: goto          22
        22: iconst_0
        23: istore_2
        24: goto          27
        27: iload_2
        28: ifeq          119
        31: aload_1
        32: checkcast     #2                  // class org/scalatest/prop/Configuration$Parameter
        35: astore        4
        37: aload_0
        38: invokevirtual #80                 // Method minSuccessful:()I
        41: aload         4
        43: invokevirtual #80                 // Method minSuccessful:()I
        46: if_icmpne     111
        49: aload_0
        50: invokevirtual #83                 // Method maxDiscardedFactor:()D
        53: aload         4
        55: invokevirtual #83                 // Method maxDiscardedFactor:()D
        58: dcmpl
        59: ifne          111
        62: aload_0
        63: invokevirtual #59                 // Method minSize:()I
        66: aload         4
        68: invokevirtual #59                 // Method minSize:()I
        71: if_icmpne     111
        74: aload_0
        75: invokevirtual #61                 // Method sizeRange:()I
        78: aload         4
        80: invokevirtual #61                 // Method sizeRange:()I
        83: if_icmpne     111
        86: aload_0
        87: invokevirtual #88                 // Method workers:()I
        90: aload         4
        92: invokevirtual #88                 // Method workers:()I
        95: if_icmpne     111
        98: aload         4
       100: aload_0
       101: invokevirtual #148                // Method canEqual:(Ljava/lang/Object;)Z
       104: ifeq          111
       107: iconst_1
       108: goto          112
       111: iconst_0
       112: ifeq          119
       115: iconst_1
       116: goto          120
       119: iconst_0
       120: ireturn
      StackMapTable: number_of_entries = 8
        frame_type = 253 /* append */
          offset_delta = 19
          locals = [ top, class java/lang/Object ]
        frame_type = 2 /* same */
        frame_type = 255 /* full_frame */
          offset_delta = 4
          locals = [ class org/scalatest/prop/Configuration$Parameter, class java/lang/Object, int, class java/lang/Object ]
          stack = []
        frame_type = 252 /* append */
          offset_delta = 83
          locals = [ class org/scalatest/prop/Configuration$Parameter ]
        frame_type = 64 /* same_locals_1_stack_item */
          stack = [ int ]
        frame_type = 248 /* chop */
          offset_delta = 2
        frame_type = 253 /* append */
          offset_delta = 3
          locals = [ int, class java/lang/Object ]
        frame_type = 255 /* full_frame */
          offset_delta = 0
          locals = [ class org/scalatest/prop/Configuration$Parameter, class java/lang/Object ]
          stack = [ int ]
      LineNumberTable:
        line 362: 0
      LocalVariableTable:
        Start  Length  Slot  Name   Signature
            0     121     0  this   Lorg/scalatest/prop/Configuration$Parameter;
            0     121     1   x$1   Ljava/lang/Object;
    MethodParameters:
      Name                           Flags
      x$1                            final

  public org.scalatest.prop.Configuration$Parameter(int, double, int, int, int);
    descriptor: (IDIII)V
    flags: (0x0001) ACC_PUBLIC
    Code:
      stack=6, locals=10, args_size=6
         0: aload_0
         1: iload_1
         2: putfield      #39                 // Field minSuccessful:I
         5: aload_0
         6: dload_2
         7: putfield      #42                 // Field maxDiscardedFactor:D
        10: aload_0
        11: iload         4
        13: putfield      #44                 // Field minSize:I
        16: aload_0
        17: iload         5
        19: putfield      #46                 // Field sizeRange:I
        22: aload_0
        23: iload         6
        25: putfield      #48                 // Field workers:I
        28: aload_0
        29: invokespecial #151                // Method java/lang/Object."<init>":()V
        32: aload_0
        33: invokestatic  #155                // InterfaceMethod scala/Product.$init$:(Lscala/Product;)V
        36: iload         4
        38: iload         5
        40: iadd
        41: istore        8
        43: iconst_0
        44: istore        9
        46: getstatic     #160                // Field org/scalactic/Bool$.MODULE$:Lorg/scalactic/Bool$;
        49: iload         8
        51: invokestatic  #166                // Method scala/runtime/BoxesRunTime.boxToInteger:(I)Ljava/lang/Integer;
        54: ldc           #168                // String >=
        56: iload         9
        58: invokestatic  #166                // Method scala/runtime/BoxesRunTime.boxToInteger:(I)Ljava/lang/Integer;
        61: iload         8
        63: iload         9
        65: if_icmplt     72
        68: iconst_1
        69: goto          73
        72: iconst_0
        73: getstatic     #173                // Field org/scalactic/Prettifier$.MODULE$:Lorg/scalactic/Prettifier$;
        76: invokevirtual #177                // Method org/scalactic/Prettifier$.default:()Lorg/scalactic/Prettifier;
        79: invokevirtual #181                // Method org/scalactic/Bool$.binaryMacroBool:(Ljava/lang/Object;Ljava/lang/String;Ljava/lang/Object;ZLorg/scalactic/Prettifier;)Lorg/scalactic/Bool;
        82: astore        7
        84: getstatic     #186                // Field org/scalactic/Requirements$.MODULE$:Lorg/scalactic/Requirements$;
        87: invokevirtual #190                // Method org/scalactic/Requirements$.requirementsHelper:()Lorg/scalactic/Requirements$RequirementsHelper;
        90: aload         7
        92: ldc           #192                // String
        94: invokevirtual #196                // Method org/scalactic/Requirements$RequirementsHelper.macroRequire:(Lorg/scalactic/Bool;Ljava/lang/Object;)V
        97: return
      StackMapTable: number_of_entries = 2
        frame_type = 255 /* full_frame */
          offset_delta = 72
          locals = [ class org/scalatest/prop/Configuration$Parameter, int, double, int, int, int, top, int, int ]
          stack = [ class org/scalactic/Bool$, class java/lang/Integer, class java/lang/String, class java/lang/Integer ]
        frame_type = 255 /* full_frame */
          offset_delta = 0
          locals = [ class org/scalatest/prop/Configuration$Parameter, int, double, int, int, int, top, int, int ]
          stack = [ class org/scalactic/Bool$, class java/lang/Integer, class java/lang/String, class java/lang/Integer, int ]
      LineNumberTable:
        line 362: 0
        line 363: 5
        line 364: 10
        line 365: 16
        line 366: 22
        line 362: 28
        line 370: 36
        line 362: 97
      LocalVariableTable:
        Start  Length  Slot  Name   Signature
           43      39     8 $org_scalatest_assert_macro_left   I
           46      36     9 $org_scalatest_assert_macro_right   I
           84      13     7 $org_scalatest_assert_macro_expr   Lorg/scalactic/Bool;
            0      98     0  this   Lorg/scalatest/prop/Configuration$Parameter;
            0      98     1 minSuccessful   I
            0      98     2 maxDiscardedFactor   D
            0      98     4 minSize   I
            0      98     5 sizeRange   I
            0      98     6 workers   I
    MethodParameters:
      Name                           Flags
      minSuccessful                  final
      maxDiscardedFactor             final
      minSize                        final
      sizeRange                      final
      workers                        final
}
InnerClasses:
  public static #14= #11 of #13;          // RequirementsHelper=class org/scalactic/Requirements$RequirementsHelper of class org/scalactic/Requirements
  public static #17= #2 of #16;           // Parameter=class org/scalatest/prop/Configuration$Parameter of class org/scalatest/prop/Configuration
SourceFile: "Configuration.scala"
  ScalaInlineInfo: length = 0x7C (unknown attribute)
   01 00 00 18 00 4A 00 4B 00 00 7C 00 7D 00 00 48
   00 49 00 00 4E 00 25 00 00 51 00 28 00 00 54 00
   25 00 00 55 00 25 00 00 56 00 25 00 00 92 00 7D
   00 00 88 00 25 00 00 15 00 28 00 00 12 00 25 00
   00 31 00 25 01 00 17 00 25 00 00 14 00 25 00 00
   5C 00 25 00 00 5D 00 5E 00 00 7F 00 80 00 00 1C
   00 1D 00 00 72 00 1D 00 00 59 00 5A 00 00 18 00
   25 00 00 8D 00 5A 00 00 19 00 25 00
  Scala: length = 0x0 (unknown attribute)

