Classfile /Users/mw/Projects/slang-braindump/.jar/jar11/assemble/slang-braindump/assemble/content/org/scalatest/prop/TableFor20$$anon$20.class
  Last modified May 29, 2022; size 5994 bytes
  SHA-256 checksum 569643e06532b814757ffc7fc73966186d317fc5d7c3a95ba2a66a3282c00dd7
  Compiled from "TableFor1.scala"
public final class org.scalatest.prop.TableFor20$$anon$20 extends java.lang.Object implements scala.collection.BuildFrom<org.scalatest.prop.TableFor20<A, B, C, D, E, F, G, H, I, J, K, L, M, N, O, P, Q, R, S, T>, scala.Tuple20<A, B, C, D, E, F, G, H, I, J, K, L, M, N, O, P, Q, R, S, T>, org.scalatest.prop.TableFor20<A, B, C, D, E, F, G, H, I, J, K, L, M, N, O, P, Q, R, S, T>>
  minor version: 0
  major version: 52
  flags: (0x0031) ACC_PUBLIC, ACC_FINAL, ACC_SUPER
  this_class: #2                          // org/scalatest/prop/TableFor20$$anon$20
  super_class: #5                         // java/lang/Object
  interfaces: 1, fields: 0, methods: 11, attributes: 7
Constant pool:
    #1 = Utf8               org/scalatest/prop/TableFor20$$anon$20
    #2 = Class              #1            // org/scalatest/prop/TableFor20$$anon$20
    #3 = Utf8               Ljava/lang/Object;Lscala/collection/BuildFrom<Lorg/scalatest/prop/TableFor20<TA;TB;TC;TD;TE;TF;TG;TH;TI;TJ;TK;TL;TM;TN;TO;TP;TQ;TR;TS;TT;>;Lscala/Tuple20<TA;TB;TC;TD;TE;TF;TG;TH;TI;TJ;TK;TL;TM;TN;TO;TP;TQ;TR;TS;TT;>;Lorg/scalatest/prop/TableFor20<TA;TB;TC;TD;TE;TF;TG;TH;TI;TJ;TK;TL;TM;TN;TO;TP;TQ;TR;TS;TT;>;>;
    #4 = Utf8               java/lang/Object
    #5 = Class              #4            // java/lang/Object
    #6 = Utf8               scala/collection/BuildFrom
    #7 = Class              #6            // scala/collection/BuildFrom
    #8 = Utf8               TableFor1.scala
    #9 = Utf8               org/scalatest/prop/TableFor20$
   #10 = Class              #9            // org/scalatest/prop/TableFor20$
   #11 = Utf8               canBuildFrom
   #12 = Utf8               ()Lscala/collection/BuildFrom;
   #13 = NameAndType        #11:#12       // canBuildFrom:()Lscala/collection/BuildFrom;
   #14 = Utf8               java/lang/invoke/MethodHandles$Lookup
   #15 = Class              #14           // java/lang/invoke/MethodHandles$Lookup
   #16 = Utf8               java/lang/invoke/MethodHandles
   #17 = Class              #16           // java/lang/invoke/MethodHandles
   #18 = Utf8               Lookup
   #19 = Utf8               apply
   #20 = Utf8               (Ljava/lang/Object;)Lscala/collection/mutable/Builder;
   #21 = Utf8               from
   #22 = Utf8               apply$
   #23 = Utf8               (Lscala/collection/BuildFrom;Ljava/lang/Object;)Lscala/collection/mutable/Builder;
   #24 = NameAndType        #22:#23       // apply$:(Lscala/collection/BuildFrom;Ljava/lang/Object;)Lscala/collection/mutable/Builder;
   #25 = InterfaceMethodref #7.#24        // scala/collection/BuildFrom.apply$:(Lscala/collection/BuildFrom;Ljava/lang/Object;)Lscala/collection/mutable/Builder;
   #26 = Utf8               this
   #27 = Utf8               Lorg/scalatest/prop/TableFor20$$anon$20;
   #28 = Utf8               Ljava/lang/Object;
   #29 = Utf8               toFactory
   #30 = Utf8               (Ljava/lang/Object;)Lscala/collection/Factory;
   #31 = Utf8               toFactory$
   #32 = Utf8               (Lscala/collection/BuildFrom;Ljava/lang/Object;)Lscala/collection/Factory;
   #33 = NameAndType        #31:#32       // toFactory$:(Lscala/collection/BuildFrom;Ljava/lang/Object;)Lscala/collection/Factory;
   #34 = InterfaceMethodref #7.#33        // scala/collection/BuildFrom.toFactory$:(Lscala/collection/BuildFrom;Ljava/lang/Object;)Lscala/collection/Factory;
   #35 = Utf8               ()Lscala/collection/mutable/Builder;
   #36 = Utf8               ()Lscala/collection/mutable/Builder<Lscala/Tuple20<TA;TB;TC;TD;TE;TF;TG;TH;TI;TJ;TK;TL;TM;TN;TO;TP;TQ;TR;TS;TT;>;Lorg/scalatest/prop/TableFor20<TA;TB;TC;TD;TE;TF;TG;TH;TI;TJ;TK;TL;TM;TN;TO;TP;TQ;TR;TS;TT;>;>;
   #37 = Utf8               scala/collection/mutable/ListBuffer
   #38 = Class              #37           // scala/collection/mutable/ListBuffer
   #39 = Utf8               <init>
   #40 = Utf8               ()V
   #41 = NameAndType        #39:#40       // "<init>":()V
   #42 = Methodref          #38.#41       // scala/collection/mutable/ListBuffer."<init>":()V
   #43 = Utf8               (Ljava/lang/Object;)Ljava/lang/Object;
   #44 = MethodType         #43           //  (Ljava/lang/Object;)Ljava/lang/Object;
   #45 = Utf8               $anonfun$apply$20
   #46 = Utf8               (Lscala/collection/immutable/Seq;)Lorg/scalatest/prop/TableFor20;
   #47 = NameAndType        #45:#46       // $anonfun$apply$20:(Lscala/collection/immutable/Seq;)Lorg/scalatest/prop/TableFor20;
   #48 = Methodref          #2.#47        // org/scalatest/prop/TableFor20$$anon$20.$anonfun$apply$20:(Lscala/collection/immutable/Seq;)Lorg/scalatest/prop/TableFor20;
   #49 = MethodHandle       6:#48         // REF_invokeStatic org/scalatest/prop/TableFor20$$anon$20.$anonfun$apply$20:(Lscala/collection/immutable/Seq;)Lorg/scalatest/prop/TableFor20;
   #50 = MethodType         #46           //  (Lscala/collection/immutable/Seq;)Lorg/scalatest/prop/TableFor20;
   #51 = Integer            5
   #52 = Integer            1
   #53 = Utf8               java/lang/invoke/LambdaMetafactory
   #54 = Class              #53           // java/lang/invoke/LambdaMetafactory
   #55 = Utf8               altMetafactory
   #56 = Utf8               (Ljava/lang/invoke/MethodHandles$Lookup;Ljava/lang/String;Ljava/lang/invoke/MethodType;[Ljava/lang/Object;)Ljava/lang/invoke/CallSite;
   #57 = NameAndType        #55:#56       // altMetafactory:(Ljava/lang/invoke/MethodHandles$Lookup;Ljava/lang/String;Ljava/lang/invoke/MethodType;[Ljava/lang/Object;)Ljava/lang/invoke/CallSite;
   #58 = Methodref          #54.#57       // java/lang/invoke/LambdaMetafactory.altMetafactory:(Ljava/lang/invoke/MethodHandles$Lookup;Ljava/lang/String;Ljava/lang/invoke/MethodType;[Ljava/lang/Object;)Ljava/lang/invoke/CallSite;
   #59 = MethodHandle       6:#58         // REF_invokeStatic java/lang/invoke/LambdaMetafactory.altMetafactory:(Ljava/lang/invoke/MethodHandles$Lookup;Ljava/lang/String;Ljava/lang/invoke/MethodType;[Ljava/lang/Object;)Ljava/lang/invoke/CallSite;
   #60 = Utf8               ()Lscala/Function1;
   #61 = NameAndType        #19:#60       // apply:()Lscala/Function1;
   #62 = InvokeDynamic      #0:#61        // #0:apply:()Lscala/Function1;
   #63 = Utf8               mapResult
   #64 = Utf8               (Lscala/Function1;)Lscala/collection/mutable/Builder;
   #65 = NameAndType        #63:#64       // mapResult:(Lscala/Function1;)Lscala/collection/mutable/Builder;
   #66 = Methodref          #38.#65       // scala/collection/mutable/ListBuffer.mapResult:(Lscala/Function1;)Lscala/collection/mutable/Builder;
   #67 = Utf8               newBuilder
   #68 = Utf8               (Lorg/scalatest/prop/TableFor20;)Lscala/collection/mutable/Builder;
   #69 = Utf8               (Lorg/scalatest/prop/TableFor20<TA;TB;TC;TD;TE;TF;TG;TH;TI;TJ;TK;TL;TM;TN;TO;TP;TQ;TR;TS;TT;>;)Lscala/collection/mutable/Builder<Lscala/Tuple20<TA;TB;TC;TD;TE;TF;TG;TH;TI;TJ;TK;TL;TM;TN;TO;TP;TQ;TR;TS;TT;>;Lorg/scalatest/prop/TableFor20<TA;TB;TC;TD;TE;TF;TG;TH;TI;TJ;TK;TL;TM;TN;TO;TP;TQ;TR;TS;TT;>;>;
   #70 = Utf8               $anonfun$newBuilder$20
   #71 = Utf8               (Lorg/scalatest/prop/TableFor20;Lscala/collection/immutable/Seq;)Lorg/scalatest/prop/TableFor20;
   #72 = NameAndType        #70:#71       // $anonfun$newBuilder$20:(Lorg/scalatest/prop/TableFor20;Lscala/collection/immutable/Seq;)Lorg/scalatest/prop/TableFor20;
   #73 = Methodref          #2.#72        // org/scalatest/prop/TableFor20$$anon$20.$anonfun$newBuilder$20:(Lorg/scalatest/prop/TableFor20;Lscala/collection/immutable/Seq;)Lorg/scalatest/prop/TableFor20;
   #74 = MethodHandle       6:#73         // REF_invokeStatic org/scalatest/prop/TableFor20$$anon$20.$anonfun$newBuilder$20:(Lorg/scalatest/prop/TableFor20;Lscala/collection/immutable/Seq;)Lorg/scalatest/prop/TableFor20;
   #75 = Utf8               (Lorg/scalatest/prop/TableFor20;)Lscala/Function1;
   #76 = NameAndType        #19:#75       // apply:(Lorg/scalatest/prop/TableFor20;)Lscala/Function1;
   #77 = InvokeDynamic      #1:#76        // #1:apply:(Lorg/scalatest/prop/TableFor20;)Lscala/Function1;
   #78 = Utf8               Lorg/scalatest/prop/TableFor20;
   #79 = Utf8               fromSpecific
   #80 = Utf8               (Lorg/scalatest/prop/TableFor20;Lscala/collection/IterableOnce;)Lorg/scalatest/prop/TableFor20;
   #81 = Utf8               (Lorg/scalatest/prop/TableFor20<TA;TB;TC;TD;TE;TF;TG;TH;TI;TJ;TK;TL;TM;TN;TO;TP;TQ;TR;TS;TT;>;Lscala/collection/IterableOnce<Lscala/Tuple20<TA;TB;TC;TD;TE;TF;TG;TH;TI;TJ;TK;TL;TM;TN;TO;TP;TQ;TR;TS;TT;>;>;)Lorg/scalatest/prop/TableFor20<TA;TB;TC;TD;TE;TF;TG;TH;TI;TJ;TK;TL;TM;TN;TO;TP;TQ;TR;TS;TT;>;
   #82 = Utf8               it
   #83 = Utf8               org/scalatest/prop/TableFor20
   #84 = Class              #83           // org/scalatest/prop/TableFor20
   #85 = Utf8               heading
   #86 = Utf8               ()Lscala/Tuple20;
   #87 = NameAndType        #85:#86       // heading:()Lscala/Tuple20;
   #88 = Methodref          #84.#87       // org/scalatest/prop/TableFor20.heading:()Lscala/Tuple20;
   #89 = Utf8               scala/collection/IterableOnceExtensionMethods$
   #90 = Class              #89           // scala/collection/IterableOnceExtensionMethods$
   #91 = Utf8               MODULE$
   #92 = Utf8               Lscala/collection/IterableOnceExtensionMethods$;
   #93 = NameAndType        #91:#92       // MODULE$:Lscala/collection/IterableOnceExtensionMethods$;
   #94 = Fieldref           #90.#93       // scala/collection/IterableOnceExtensionMethods$.MODULE$:Lscala/collection/IterableOnceExtensionMethods$;
   #95 = Utf8               scala/collection/IterableOnce$
   #96 = Class              #95           // scala/collection/IterableOnce$
   #97 = Utf8               Lscala/collection/IterableOnce$;
   #98 = NameAndType        #91:#97       // MODULE$:Lscala/collection/IterableOnce$;
   #99 = Fieldref           #96.#98       // scala/collection/IterableOnce$.MODULE$:Lscala/collection/IterableOnce$;
  #100 = Utf8               iterableOnceExtensionMethods
  #101 = Utf8               (Lscala/collection/IterableOnce;)Lscala/collection/IterableOnce;
  #102 = NameAndType        #100:#101     // iterableOnceExtensionMethods:(Lscala/collection/IterableOnce;)Lscala/collection/IterableOnce;
  #103 = Methodref          #96.#102      // scala/collection/IterableOnce$.iterableOnceExtensionMethods:(Lscala/collection/IterableOnce;)Lscala/collection/IterableOnce;
  #104 = Utf8               toSeq$extension
  #105 = Utf8               (Lscala/collection/IterableOnce;)Lscala/collection/immutable/Seq;
  #106 = NameAndType        #104:#105     // toSeq$extension:(Lscala/collection/IterableOnce;)Lscala/collection/immutable/Seq;
  #107 = Methodref          #90.#106      // scala/collection/IterableOnceExtensionMethods$.toSeq$extension:(Lscala/collection/IterableOnce;)Lscala/collection/immutable/Seq;
  #108 = Utf8               (Lscala/Tuple20;Lscala/collection/immutable/Seq;)V
  #109 = NameAndType        #39:#108      // "<init>":(Lscala/Tuple20;Lscala/collection/immutable/Seq;)V
  #110 = Methodref          #84.#109      // org/scalatest/prop/TableFor20."<init>":(Lscala/Tuple20;Lscala/collection/immutable/Seq;)V
  #111 = Utf8               Lscala/collection/IterableOnce;
  #112 = Utf8               (Ljava/lang/Object;Lscala/collection/IterableOnce;)Ljava/lang/Object;
  #113 = NameAndType        #79:#80       // fromSpecific:(Lorg/scalatest/prop/TableFor20;Lscala/collection/IterableOnce;)Lorg/scalatest/prop/TableFor20;
  #114 = Methodref          #2.#113       // org/scalatest/prop/TableFor20$$anon$20.fromSpecific:(Lorg/scalatest/prop/TableFor20;Lscala/collection/IterableOnce;)Lorg/scalatest/prop/TableFor20;
  #115 = NameAndType        #67:#68       // newBuilder:(Lorg/scalatest/prop/TableFor20;)Lscala/collection/mutable/Builder;
  #116 = Methodref          #2.#115       // org/scalatest/prop/TableFor20$$anon$20.newBuilder:(Lorg/scalatest/prop/TableFor20;)Lscala/collection/mutable/Builder;
  #117 = Utf8               buf
  #118 = Utf8               scala/Tuple20
  #119 = Class              #118          // scala/Tuple20
  #120 = Utf8               arg0
  #121 = String             #120          // arg0
  #122 = Utf8               arg1
  #123 = String             #122          // arg1
  #124 = Utf8               arg2
  #125 = String             #124          // arg2
  #126 = Utf8               arg3
  #127 = String             #126          // arg3
  #128 = Utf8               arg4
  #129 = String             #128          // arg4
  #130 = Utf8               arg5
  #131 = String             #130          // arg5
  #132 = Utf8               arg6
  #133 = String             #132          // arg6
  #134 = Utf8               arg7
  #135 = String             #134          // arg7
  #136 = Utf8               arg8
  #137 = String             #136          // arg8
  #138 = Utf8               arg9
  #139 = String             #138          // arg9
  #140 = Utf8               arg10
  #141 = String             #140          // arg10
  #142 = Utf8               arg11
  #143 = String             #142          // arg11
  #144 = Utf8               arg12
  #145 = String             #144          // arg12
  #146 = Utf8               arg13
  #147 = String             #146          // arg13
  #148 = Utf8               arg14
  #149 = String             #148          // arg14
  #150 = Utf8               arg15
  #151 = String             #150          // arg15
  #152 = Utf8               arg16
  #153 = String             #152          // arg16
  #154 = Utf8               arg17
  #155 = String             #154          // arg17
  #156 = Utf8               arg18
  #157 = String             #156          // arg18
  #158 = Utf8               arg19
  #159 = String             #158          // arg19
  #160 = Utf8               (Ljava/lang/Object;Ljava/lang/Object;Ljava/lang/Object;Ljava/lang/Object;Ljava/lang/Object;Ljava/lang/Object;Ljava/lang/Object;Ljava/lang/Object;Ljava/lang/Object;Ljava/lang/Object;Ljava/lang/Object;Ljava/lang/Object;Ljava/lang/Object;Ljava/lang/Object;Ljava/lang/Object;Ljava/lang/Object;Ljava/lang/Object;Ljava/lang/Object;Ljava/lang/Object;Ljava/lang/Object;)V
  #161 = NameAndType        #39:#160      // "<init>":(Ljava/lang/Object;Ljava/lang/Object;Ljava/lang/Object;Ljava/lang/Object;Ljava/lang/Object;Ljava/lang/Object;Ljava/lang/Object;Ljava/lang/Object;Ljava/lang/Object;Ljava/lang/Object;Ljava/lang/Object;Ljava/lang/Object;Ljava/lang/Object;Ljava/lang/Object;Ljava/lang/Object;Ljava/lang/Object;Ljava/lang/Object;Ljava/lang/Object;Ljava/lang/Object;Ljava/lang/Object;)V
  #162 = Methodref          #119.#161     // scala/Tuple20."<init>":(Ljava/lang/Object;Ljava/lang/Object;Ljava/lang/Object;Ljava/lang/Object;Ljava/lang/Object;Ljava/lang/Object;Ljava/lang/Object;Ljava/lang/Object;Ljava/lang/Object;Ljava/lang/Object;Ljava/lang/Object;Ljava/lang/Object;Ljava/lang/Object;Ljava/lang/Object;Ljava/lang/Object;Ljava/lang/Object;Ljava/lang/Object;Ljava/lang/Object;Ljava/lang/Object;Ljava/lang/Object;)V
  #163 = Utf8               scala/collection/immutable/Nil$
  #164 = Class              #163          // scala/collection/immutable/Nil$
  #165 = Utf8               Lscala/collection/immutable/Nil$;
  #166 = NameAndType        #91:#165      // MODULE$:Lscala/collection/immutable/Nil$;
  #167 = Fieldref           #164.#166     // scala/collection/immutable/Nil$.MODULE$:Lscala/collection/immutable/Nil$;
  #168 = Utf8               Lscala/collection/immutable/Seq;
  #169 = Utf8               from$20
  #170 = Methodref          #5.#41        // java/lang/Object."<init>":()V
  #171 = Utf8               $init$
  #172 = Utf8               (Lscala/collection/BuildFrom;)V
  #173 = NameAndType        #171:#172     // $init$:(Lscala/collection/BuildFrom;)V
  #174 = InterfaceMethodref #7.#173       // scala/collection/BuildFrom.$init$:(Lscala/collection/BuildFrom;)V
  #175 = Utf8               $deserializeLambda$
  #176 = Utf8               (Ljava/lang/invoke/SerializedLambda;)Ljava/lang/Object;
  #177 = Utf8               scala/runtime/LambdaDeserialize
  #178 = Class              #177          // scala/runtime/LambdaDeserialize
  #179 = Utf8               bootstrap
  #180 = Utf8               (Ljava/lang/invoke/MethodHandles$Lookup;Ljava/lang/String;Ljava/lang/invoke/MethodType;[Ljava/lang/invoke/MethodHandle;)Ljava/lang/invoke/CallSite;
  #181 = NameAndType        #179:#180     // bootstrap:(Ljava/lang/invoke/MethodHandles$Lookup;Ljava/lang/String;Ljava/lang/invoke/MethodType;[Ljava/lang/invoke/MethodHandle;)Ljava/lang/invoke/CallSite;
  #182 = Methodref          #178.#181     // scala/runtime/LambdaDeserialize.bootstrap:(Ljava/lang/invoke/MethodHandles$Lookup;Ljava/lang/String;Ljava/lang/invoke/MethodType;[Ljava/lang/invoke/MethodHandle;)Ljava/lang/invoke/CallSite;
  #183 = MethodHandle       6:#182        // REF_invokeStatic scala/runtime/LambdaDeserialize.bootstrap:(Ljava/lang/invoke/MethodHandles$Lookup;Ljava/lang/String;Ljava/lang/invoke/MethodType;[Ljava/lang/invoke/MethodHandle;)Ljava/lang/invoke/CallSite;
  #184 = Utf8               lambdaDeserialize
  #185 = NameAndType        #184:#176     // lambdaDeserialize:(Ljava/lang/invoke/SerializedLambda;)Ljava/lang/Object;
  #186 = InvokeDynamic      #2:#185       // #2:lambdaDeserialize:(Ljava/lang/invoke/SerializedLambda;)Ljava/lang/Object;
  #187 = Utf8               Code
  #188 = Utf8               LineNumberTable
  #189 = Utf8               LocalVariableTable
  #190 = Utf8               Deprecated
  #191 = Utf8               MethodParameters
  #192 = Utf8               Signature
  #193 = Utf8               InnerClasses
  #194 = Utf8               EnclosingMethod
  #195 = Utf8               SourceFile
  #196 = Utf8               BootstrapMethods
  #197 = Utf8               ScalaInlineInfo
  #198 = Utf8               Scala
{
  public scala.collection.mutable.Builder apply(java.lang.Object);
    descriptor: (Ljava/lang/Object;)Lscala/collection/mutable/Builder;
    flags: (0x0001) ACC_PUBLIC
    Code:
      stack=2, locals=2, args_size=2
         0: aload_0
         1: aload_1
         2: invokestatic  #25                 // InterfaceMethod scala/collection/BuildFrom.apply$:(Lscala/collection/BuildFrom;Ljava/lang/Object;)Lscala/collection/mutable/Builder;
         5: areturn
      LineNumberTable:
        line 3601: 0
      LocalVariableTable:
        Start  Length  Slot  Name   Signature
            0       6     0  this   Lorg/scalatest/prop/TableFor20$$anon$20;
            0       6     1  from   Ljava/lang/Object;
    Deprecated: true
    MethodParameters:
      Name                           Flags
      from                           final

  public scala.collection.Factory toFactory(java.lang.Object);
    descriptor: (Ljava/lang/Object;)Lscala/collection/Factory;
    flags: (0x0001) ACC_PUBLIC
    Code:
      stack=2, locals=2, args_size=2
         0: aload_0
         1: aload_1
         2: invokestatic  #34                 // InterfaceMethod scala/collection/BuildFrom.toFactory$:(Lscala/collection/BuildFrom;Ljava/lang/Object;)Lscala/collection/Factory;
         5: areturn
      LineNumberTable:
        line 3601: 0
      LocalVariableTable:
        Start  Length  Slot  Name   Signature
            0       6     0  this   Lorg/scalatest/prop/TableFor20$$anon$20;
            0       6     1  from   Ljava/lang/Object;
    MethodParameters:
      Name                           Flags
      from                           final

  private scala.collection.mutable.Builder<scala.Tuple20<A, B, C, D, E, F, G, H, I, J, K, L, M, N, O, P, Q, R, S, T>, org.scalatest.prop.TableFor20<A, B, C, D, E, F, G, H, I, J, K, L, M, N, O, P, Q, R, S, T>> apply();
    descriptor: ()Lscala/collection/mutable/Builder;
    flags: (0x0002) ACC_PRIVATE
    Code:
      stack=2, locals=1, args_size=1
         0: new           #38                 // class scala/collection/mutable/ListBuffer
         3: dup
         4: invokespecial #42                 // Method scala/collection/mutable/ListBuffer."<init>":()V
         7: invokedynamic #62,  0             // InvokeDynamic #0:apply:()Lscala/Function1;
        12: invokevirtual #66                 // Method scala/collection/mutable/ListBuffer.mapResult:(Lscala/Function1;)Lscala/collection/mutable/Builder;
        15: areturn
      LineNumberTable:
        line 3603: 0
      LocalVariableTable:
        Start  Length  Slot  Name   Signature
            0      16     0  this   Lorg/scalatest/prop/TableFor20$$anon$20;
    Signature: #36                          // ()Lscala/collection/mutable/Builder<Lscala/Tuple20<TA;TB;TC;TD;TE;TF;TG;TH;TI;TJ;TK;TL;TM;TN;TO;TP;TQ;TR;TS;TT;>;Lorg/scalatest/prop/TableFor20<TA;TB;TC;TD;TE;TF;TG;TH;TI;TJ;TK;TL;TM;TN;TO;TP;TQ;TR;TS;TT;>;>;

  public scala.collection.mutable.Builder<scala.Tuple20<A, B, C, D, E, F, G, H, I, J, K, L, M, N, O, P, Q, R, S, T>, org.scalatest.prop.TableFor20<A, B, C, D, E, F, G, H, I, J, K, L, M, N, O, P, Q, R, S, T>> newBuilder(org.scalatest.prop.TableFor20<A, B, C, D, E, F, G, H, I, J, K, L, M, N, O, P, Q, R, S, T>);
    descriptor: (Lorg/scalatest/prop/TableFor20;)Lscala/collection/mutable/Builder;
    flags: (0x0001) ACC_PUBLIC
    Code:
      stack=2, locals=2, args_size=2
         0: new           #38                 // class scala/collection/mutable/ListBuffer
         3: dup
         4: invokespecial #42                 // Method scala/collection/mutable/ListBuffer."<init>":()V
         7: aload_1
         8: invokedynamic #77,  0             // InvokeDynamic #1:apply:(Lorg/scalatest/prop/TableFor20;)Lscala/Function1;
        13: invokevirtual #66                 // Method scala/collection/mutable/ListBuffer.mapResult:(Lscala/Function1;)Lscala/collection/mutable/Builder;
        16: areturn
      LineNumberTable:
        line 3607: 0
      LocalVariableTable:
        Start  Length  Slot  Name   Signature
            0      17     0  this   Lorg/scalatest/prop/TableFor20$$anon$20;
            0      17     1  from   Lorg/scalatest/prop/TableFor20;
    Signature: #69                          // (Lorg/scalatest/prop/TableFor20<TA;TB;TC;TD;TE;TF;TG;TH;TI;TJ;TK;TL;TM;TN;TO;TP;TQ;TR;TS;TT;>;)Lscala/collection/mutable/Builder<Lscala/Tuple20<TA;TB;TC;TD;TE;TF;TG;TH;TI;TJ;TK;TL;TM;TN;TO;TP;TQ;TR;TS;TT;>;Lorg/scalatest/prop/TableFor20<TA;TB;TC;TD;TE;TF;TG;TH;TI;TJ;TK;TL;TM;TN;TO;TP;TQ;TR;TS;TT;>;>;
    MethodParameters:
      Name                           Flags
      from                           final

  public org.scalatest.prop.TableFor20<A, B, C, D, E, F, G, H, I, J, K, L, M, N, O, P, Q, R, S, T> fromSpecific(org.scalatest.prop.TableFor20<A, B, C, D, E, F, G, H, I, J, K, L, M, N, O, P, Q, R, S, T>, scala.collection.IterableOnce<scala.Tuple20<A, B, C, D, E, F, G, H, I, J, K, L, M, N, O, P, Q, R, S, T>>);
    descriptor: (Lorg/scalatest/prop/TableFor20;Lscala/collection/IterableOnce;)Lorg/scalatest/prop/TableFor20;
    flags: (0x0001) ACC_PUBLIC
    Code:
      stack=6, locals=3, args_size=3
         0: new           #84                 // class org/scalatest/prop/TableFor20
         3: dup
         4: aload_1
         5: invokevirtual #88                 // Method org/scalatest/prop/TableFor20.heading:()Lscala/Tuple20;
         8: getstatic     #94                 // Field scala/collection/IterableOnceExtensionMethods$.MODULE$:Lscala/collection/IterableOnceExtensionMethods$;
        11: getstatic     #99                 // Field scala/collection/IterableOnce$.MODULE$:Lscala/collection/IterableOnce$;
        14: aload_2
        15: invokevirtual #103                // Method scala/collection/IterableOnce$.iterableOnceExtensionMethods:(Lscala/collection/IterableOnce;)Lscala/collection/IterableOnce;
        18: invokevirtual #107                // Method scala/collection/IterableOnceExtensionMethods$.toSeq$extension:(Lscala/collection/IterableOnce;)Lscala/collection/immutable/Seq;
        21: invokespecial #110                // Method org/scalatest/prop/TableFor20."<init>":(Lscala/Tuple20;Lscala/collection/immutable/Seq;)V
        24: areturn
      LineNumberTable:
        line 3611: 0
      LocalVariableTable:
        Start  Length  Slot  Name   Signature
            0      25     0  this   Lorg/scalatest/prop/TableFor20$$anon$20;
            0      25     1  from   Lorg/scalatest/prop/TableFor20;
            0      25     2    it   Lscala/collection/IterableOnce;
    Signature: #81                          // (Lorg/scalatest/prop/TableFor20<TA;TB;TC;TD;TE;TF;TG;TH;TI;TJ;TK;TL;TM;TN;TO;TP;TQ;TR;TS;TT;>;Lscala/collection/IterableOnce<Lscala/Tuple20<TA;TB;TC;TD;TE;TF;TG;TH;TI;TJ;TK;TL;TM;TN;TO;TP;TQ;TR;TS;TT;>;>;)Lorg/scalatest/prop/TableFor20<TA;TB;TC;TD;TE;TF;TG;TH;TI;TJ;TK;TL;TM;TN;TO;TP;TQ;TR;TS;TT;>;
    MethodParameters:
      Name                           Flags
      from                           final
      it                             final

  public java.lang.Object fromSpecific(java.lang.Object, scala.collection.IterableOnce);
    descriptor: (Ljava/lang/Object;Lscala/collection/IterableOnce;)Ljava/lang/Object;
    flags: (0x1041) ACC_PUBLIC, ACC_BRIDGE, ACC_SYNTHETIC
    Code:
      stack=3, locals=3, args_size=3
         0: aload_0
         1: aload_1
         2: checkcast     #84                 // class org/scalatest/prop/TableFor20
         5: aload_2
         6: invokevirtual #114                // Method fromSpecific:(Lorg/scalatest/prop/TableFor20;Lscala/collection/IterableOnce;)Lorg/scalatest/prop/TableFor20;
         9: areturn
      LineNumberTable:
        line 3601: 0
      LocalVariableTable:
        Start  Length  Slot  Name   Signature
            0      10     0  this   Lorg/scalatest/prop/TableFor20$$anon$20;
            0      10     1  from   Ljava/lang/Object;
            0      10     2    it   Lscala/collection/IterableOnce;
    MethodParameters:
      Name                           Flags
      from                           final
      it                             final

  public scala.collection.mutable.Builder newBuilder(java.lang.Object);
    descriptor: (Ljava/lang/Object;)Lscala/collection/mutable/Builder;
    flags: (0x1041) ACC_PUBLIC, ACC_BRIDGE, ACC_SYNTHETIC
    Code:
      stack=2, locals=2, args_size=2
         0: aload_0
         1: aload_1
         2: checkcast     #84                 // class org/scalatest/prop/TableFor20
         5: invokevirtual #116                // Method newBuilder:(Lorg/scalatest/prop/TableFor20;)Lscala/collection/mutable/Builder;
         8: areturn
      LineNumberTable:
        line 3601: 0
      LocalVariableTable:
        Start  Length  Slot  Name   Signature
            0       9     0  this   Lorg/scalatest/prop/TableFor20$$anon$20;
            0       9     1  from   Ljava/lang/Object;
    MethodParameters:
      Name                           Flags
      from                           final

  public static final org.scalatest.prop.TableFor20 $anonfun$apply$20(scala.collection.immutable.Seq);
    descriptor: (Lscala/collection/immutable/Seq;)Lorg/scalatest/prop/TableFor20;
    flags: (0x1019) ACC_PUBLIC, ACC_STATIC, ACC_FINAL, ACC_SYNTHETIC
    Code:
      stack=24, locals=1, args_size=1
         0: new           #84                 // class org/scalatest/prop/TableFor20
         3: dup
         4: new           #119                // class scala/Tuple20
         7: dup
         8: ldc           #121                // String arg0
        10: ldc           #123                // String arg1
        12: ldc           #125                // String arg2
        14: ldc           #127                // String arg3
        16: ldc           #129                // String arg4
        18: ldc           #131                // String arg5
        20: ldc           #133                // String arg6
        22: ldc           #135                // String arg7
        24: ldc           #137                // String arg8
        26: ldc           #139                // String arg9
        28: ldc           #141                // String arg10
        30: ldc           #143                // String arg11
        32: ldc           #145                // String arg12
        34: ldc           #147                // String arg13
        36: ldc           #149                // String arg14
        38: ldc           #151                // String arg15
        40: ldc           #153                // String arg16
        42: ldc           #155                // String arg17
        44: ldc           #157                // String arg18
        46: ldc           #159                // String arg19
        48: invokespecial #162                // Method scala/Tuple20."<init>":(Ljava/lang/Object;Ljava/lang/Object;Ljava/lang/Object;Ljava/lang/Object;Ljava/lang/Object;Ljava/lang/Object;Ljava/lang/Object;Ljava/lang/Object;Ljava/lang/Object;Ljava/lang/Object;Ljava/lang/Object;Ljava/lang/Object;Ljava/lang/Object;Ljava/lang/Object;Ljava/lang/Object;Ljava/lang/Object;Ljava/lang/Object;Ljava/lang/Object;Ljava/lang/Object;Ljava/lang/Object;)V
        51: getstatic     #167                // Field scala/collection/immutable/Nil$.MODULE$:Lscala/collection/immutable/Nil$;
        54: invokespecial #110                // Method org/scalatest/prop/TableFor20."<init>":(Lscala/Tuple20;Lscala/collection/immutable/Seq;)V
        57: areturn
      LineNumberTable:
        line 3604: 0
      LocalVariableTable:
        Start  Length  Slot  Name   Signature
            0      58     0   buf   Lscala/collection/immutable/Seq;
    MethodParameters:
      Name                           Flags
      buf                            final

  public static final org.scalatest.prop.TableFor20 $anonfun$newBuilder$20(org.scalatest.prop.TableFor20, scala.collection.immutable.Seq);
    descriptor: (Lorg/scalatest/prop/TableFor20;Lscala/collection/immutable/Seq;)Lorg/scalatest/prop/TableFor20;
    flags: (0x1019) ACC_PUBLIC, ACC_STATIC, ACC_FINAL, ACC_SYNTHETIC
    Code:
      stack=4, locals=2, args_size=2
         0: new           #84                 // class org/scalatest/prop/TableFor20
         3: dup
         4: aload_0
         5: invokevirtual #88                 // Method org/scalatest/prop/TableFor20.heading:()Lscala/Tuple20;
         8: aload_1
         9: invokespecial #110                // Method org/scalatest/prop/TableFor20."<init>":(Lscala/Tuple20;Lscala/collection/immutable/Seq;)V
        12: areturn
      LineNumberTable:
        line 3608: 0
      LocalVariableTable:
        Start  Length  Slot  Name   Signature
            0      13     0 from$20   Lorg/scalatest/prop/TableFor20;
            0      13     1   buf   Lscala/collection/immutable/Seq;
    MethodParameters:
      Name                           Flags
      from$20                        final
      buf                            final

  public org.scalatest.prop.TableFor20$$anon$20();
    descriptor: ()V
    flags: (0x0001) ACC_PUBLIC
    Code:
      stack=1, locals=1, args_size=1
         0: aload_0
         1: invokespecial #170                // Method java/lang/Object."<init>":()V
         4: aload_0
         5: invokestatic  #174                // InterfaceMethod scala/collection/BuildFrom.$init$:(Lscala/collection/BuildFrom;)V
         8: return
      LineNumberTable:
        line 3601: 0
      LocalVariableTable:
        Start  Length  Slot  Name   Signature
            0       9     0  this   Lorg/scalatest/prop/TableFor20$$anon$20;

  private static java.lang.Object $deserializeLambda$(java.lang.invoke.SerializedLambda);
    descriptor: (Ljava/lang/invoke/SerializedLambda;)Ljava/lang/Object;
    flags: (0x100a) ACC_PRIVATE, ACC_STATIC, ACC_SYNTHETIC
    Code:
      stack=1, locals=1, args_size=1
         0: aload_0
         1: invokedynamic #186,  0            // InvokeDynamic #2:lambdaDeserialize:(Ljava/lang/invoke/SerializedLambda;)Ljava/lang/Object;
         6: areturn
}
InnerClasses:
  public static final #18= #15 of #17;    // Lookup=class java/lang/invoke/MethodHandles$Lookup of class java/lang/invoke/MethodHandles
  public final #2;                        // class org/scalatest/prop/TableFor20$$anon$20
EnclosingMethod: #10.#13                // org.scalatest.prop.TableFor20$.canBuildFrom
Signature: #3                           // Ljava/lang/Object;Lscala/collection/BuildFrom<Lorg/scalatest/prop/TableFor20<TA;TB;TC;TD;TE;TF;TG;TH;TI;TJ;TK;TL;TM;TN;TO;TP;TQ;TR;TS;TT;>;Lscala/Tuple20<TA;TB;TC;TD;TE;TF;TG;TH;TI;TJ;TK;TL;TM;TN;TO;TP;TQ;TR;TS;TT;>;Lorg/scalatest/prop/TableFor20<TA;TB;TC;TD;TE;TF;TG;TH;TI;TJ;TK;TL;TM;TN;TO;TP;TQ;TR;TS;TT;>;>;
SourceFile: "TableFor1.scala"
BootstrapMethods:
  0: #59 REF_invokeStatic java/lang/invoke/LambdaMetafactory.altMetafactory:(Ljava/lang/invoke/MethodHandles$Lookup;Ljava/lang/String;Ljava/lang/invoke/MethodType;[Ljava/lang/Object;)Ljava/lang/invoke/CallSite;
    Method arguments:
      #44 (Ljava/lang/Object;)Ljava/lang/Object;
      #49 REF_invokeStatic org/scalatest/prop/TableFor20$$anon$20.$anonfun$apply$20:(Lscala/collection/immutable/Seq;)Lorg/scalatest/prop/TableFor20;
      #50 (Lscala/collection/immutable/Seq;)Lorg/scalatest/prop/TableFor20;
      #51 5
      #52 1
      #50 (Lscala/collection/immutable/Seq;)Lorg/scalatest/prop/TableFor20;
  1: #59 REF_invokeStatic java/lang/invoke/LambdaMetafactory.altMetafactory:(Ljava/lang/invoke/MethodHandles$Lookup;Ljava/lang/String;Ljava/lang/invoke/MethodType;[Ljava/lang/Object;)Ljava/lang/invoke/CallSite;
    Method arguments:
      #44 (Ljava/lang/Object;)Ljava/lang/Object;
      #74 REF_invokeStatic org/scalatest/prop/TableFor20$$anon$20.$anonfun$newBuilder$20:(Lorg/scalatest/prop/TableFor20;Lscala/collection/immutable/Seq;)Lorg/scalatest/prop/TableFor20;
      #50 (Lscala/collection/immutable/Seq;)Lorg/scalatest/prop/TableFor20;
      #51 5
      #52 1
      #50 (Lscala/collection/immutable/Seq;)Lorg/scalatest/prop/TableFor20;
  2: #183 REF_invokeStatic scala/runtime/LambdaDeserialize.bootstrap:(Ljava/lang/invoke/MethodHandles$Lookup;Ljava/lang/String;Ljava/lang/invoke/MethodType;[Ljava/lang/invoke/MethodHandle;)Ljava/lang/invoke/CallSite;
    Method arguments:
      #49 REF_invokeStatic org/scalatest/prop/TableFor20$$anon$20.$anonfun$apply$20:(Lscala/collection/immutable/Seq;)Lorg/scalatest/prop/TableFor20;
      #74 REF_invokeStatic org/scalatest/prop/TableFor20$$anon$20.$anonfun$newBuilder$20:(Lorg/scalatest/prop/TableFor20;Lscala/collection/immutable/Seq;)Lorg/scalatest/prop/TableFor20;
  ScalaInlineInfo: length = 0x36 (unknown attribute)
   01 01 00 0A 00 2D 00 2E 01 00 46 00 47 01 00 27
   00 28 01 00 13 00 23 01 00 13 00 14 05 00 4F 00
   70 01 00 4F 00 50 01 00 43 00 14 01 00 43 00 44
   01 00 1D 00 1E 01
  Scala: length = 0x0 (unknown attribute)

