Classfile /Users/mw/Projects/slang-braindump/.jar/jar11/assemble/slang-braindump/assemble/content/shapeless/ops/record/AlignByKeys$$anon$44.class
  Last modified May 29, 2022; size 2302 bytes
  SHA-256 checksum 6cca7b7bfb6038e74849961cad6285d3e2bd5adc54af77e66fdecbd7b7257602
  Compiled from "records.scala"
public final class shapeless.ops.record.AlignByKeys$$anon$44 extends java.lang.Object implements shapeless.ops.record.AlignByKeys<T, shapeless.$colon$colon<KH, KT>>
  minor version: 0
  major version: 52
  flags: (0x0031) ACC_PUBLIC, ACC_FINAL, ACC_SUPER
  this_class: #2                          // shapeless/ops/record/AlignByKeys$$anon$44
  super_class: #5                         // java/lang/Object
  interfaces: 1, fields: 2, methods: 3, attributes: 6
Constant pool:
    #1 = Utf8               shapeless/ops/record/AlignByKeys$$anon$44
    #2 = Class              #1            // shapeless/ops/record/AlignByKeys$$anon$44
    #3 = Utf8               Ljava/lang/Object;Lshapeless/ops/record/AlignByKeys<TT;Lshapeless/$colon$colon<TKH;TKT;>;>;
    #4 = Utf8               java/lang/Object
    #5 = Class              #4            // java/lang/Object
    #6 = Utf8               shapeless/ops/record/AlignByKeys
    #7 = Class              #6            // shapeless/ops/record/AlignByKeys
    #8 = Utf8               records.scala
    #9 = Utf8               shapeless/ops/record/AlignByKeys$
   #10 = Class              #9            // shapeless/ops/record/AlignByKeys$
   #11 = Utf8               hlistAlign
   #12 = Utf8               (Lshapeless/ops/record/Remover;Lshapeless/ops/record/AlignByKeys;)Lshapeless/ops/record/AlignByKeys;
   #13 = NameAndType        #11:#12       // hlistAlign:(Lshapeless/ops/record/Remover;Lshapeless/ops/record/AlignByKeys;)Lshapeless/ops/record/AlignByKeys;
   #14 = Utf8               shapeless/labelled$FieldBuilder
   #15 = Class              #14           // shapeless/labelled$FieldBuilder
   #16 = Utf8               shapeless/labelled
   #17 = Class              #16           // shapeless/labelled
   #18 = Utf8               FieldBuilder
   #19 = Utf8               remover$1
   #20 = Utf8               Lshapeless/ops/record/Remover;
   #21 = Utf8               tailAlign$1
   #22 = Utf8               Lshapeless/ops/record/AlignByKeys;
   #23 = Utf8               apply
   #24 = Utf8               (Lshapeless/HList;)Lshapeless/$colon$colon;
   #25 = Utf8               (TT;)Lshapeless/$colon$colon<TV;TTA;>;
   #26 = Utf8               t
   #27 = NameAndType        #19:#20       // remover$1:Lshapeless/ops/record/Remover;
   #28 = Fieldref           #2.#27        // shapeless/ops/record/AlignByKeys$$anon$44.remover$1:Lshapeless/ops/record/Remover;
   #29 = Utf8               shapeless/ops/record/Remover
   #30 = Class              #29           // shapeless/ops/record/Remover
   #31 = Utf8               (Ljava/lang/Object;)Ljava/lang/Object;
   #32 = NameAndType        #23:#31       // apply:(Ljava/lang/Object;)Ljava/lang/Object;
   #33 = InterfaceMethodref #30.#32       // shapeless/ops/record/Remover.apply:(Ljava/lang/Object;)Ljava/lang/Object;
   #34 = Utf8               scala/Tuple2
   #35 = Class              #34           // scala/Tuple2
   #36 = Utf8               _1
   #37 = Utf8               ()Ljava/lang/Object;
   #38 = NameAndType        #36:#37       // _1:()Ljava/lang/Object;
   #39 = Methodref          #35.#38       // scala/Tuple2._1:()Ljava/lang/Object;
   #40 = Utf8               _2
   #41 = NameAndType        #40:#37       // _2:()Ljava/lang/Object;
   #42 = Methodref          #35.#41       // scala/Tuple2._2:()Ljava/lang/Object;
   #43 = Utf8               shapeless/HList
   #44 = Class              #43           // shapeless/HList
   #45 = Utf8               <init>
   #46 = Utf8               (Ljava/lang/Object;Ljava/lang/Object;)V
   #47 = NameAndType        #45:#46       // "<init>":(Ljava/lang/Object;Ljava/lang/Object;)V
   #48 = Methodref          #35.#47       // scala/Tuple2."<init>":(Ljava/lang/Object;Ljava/lang/Object;)V
   #49 = Utf8               scala/MatchError
   #50 = Class              #49           // scala/MatchError
   #51 = Utf8               (Ljava/lang/Object;)V
   #52 = NameAndType        #45:#51       // "<init>":(Ljava/lang/Object;)V
   #53 = Methodref          #50.#52       // scala/MatchError."<init>":(Ljava/lang/Object;)V
   #54 = Utf8               shapeless/labelled$
   #55 = Class              #54           // shapeless/labelled$
   #56 = Utf8               MODULE$
   #57 = Utf8               Lshapeless/labelled$;
   #58 = NameAndType        #56:#57       // MODULE$:Lshapeless/labelled$;
   #59 = Fieldref           #55.#58       // shapeless/labelled$.MODULE$:Lshapeless/labelled$;
   #60 = Utf8               field
   #61 = Utf8               ()Lshapeless/labelled$FieldBuilder;
   #62 = NameAndType        #60:#61       // field:()Lshapeless/labelled$FieldBuilder;
   #63 = Methodref          #55.#62       // shapeless/labelled$.field:()Lshapeless/labelled$FieldBuilder;
   #64 = Methodref          #15.#32       // shapeless/labelled$FieldBuilder.apply:(Ljava/lang/Object;)Ljava/lang/Object;
   #65 = Utf8               shapeless/HList$
   #66 = Class              #65           // shapeless/HList$
   #67 = Utf8               Lshapeless/HList$;
   #68 = NameAndType        #56:#67       // MODULE$:Lshapeless/HList$;
   #69 = Fieldref           #66.#68       // shapeless/HList$.MODULE$:Lshapeless/HList$;
   #70 = NameAndType        #21:#22       // tailAlign$1:Lshapeless/ops/record/AlignByKeys;
   #71 = Fieldref           #2.#70        // shapeless/ops/record/AlignByKeys$$anon$44.tailAlign$1:Lshapeless/ops/record/AlignByKeys;
   #72 = InterfaceMethodref #7.#32        // shapeless/ops/record/AlignByKeys.apply:(Ljava/lang/Object;)Ljava/lang/Object;
   #73 = Utf8               hlistOps
   #74 = Utf8               (Lshapeless/HList;)Lshapeless/syntax/HListOps;
   #75 = NameAndType        #73:#74       // hlistOps:(Lshapeless/HList;)Lshapeless/syntax/HListOps;
   #76 = Methodref          #66.#75       // shapeless/HList$.hlistOps:(Lshapeless/HList;)Lshapeless/syntax/HListOps;
   #77 = Utf8               shapeless/syntax/HListOps
   #78 = Class              #77           // shapeless/syntax/HListOps
   #79 = Utf8               $colon$colon
   #80 = Utf8               (Ljava/lang/Object;)Lshapeless/$colon$colon;
   #81 = NameAndType        #79:#80       // $colon$colon:(Ljava/lang/Object;)Lshapeless/$colon$colon;
   #82 = Methodref          #78.#81       // shapeless/syntax/HListOps.$colon$colon:(Ljava/lang/Object;)Lshapeless/$colon$colon;
   #83 = Utf8               v
   #84 = Utf8               Ljava/lang/Object;
   #85 = Utf8               r
   #86 = Utf8               Lshapeless/HList;
   #87 = Utf8               this
   #88 = Utf8               Lshapeless/ops/record/AlignByKeys$$anon$44;
   #89 = NameAndType        #23:#24       // apply:(Lshapeless/HList;)Lshapeless/$colon$colon;
   #90 = Methodref          #2.#89        // shapeless/ops/record/AlignByKeys$$anon$44.apply:(Lshapeless/HList;)Lshapeless/$colon$colon;
   #91 = Utf8               (Lshapeless/ops/record/Remover;Lshapeless/ops/record/AlignByKeys;)V
   #92 = Utf8               ()V
   #93 = NameAndType        #45:#92       // "<init>":()V
   #94 = Methodref          #5.#93        // java/lang/Object."<init>":()V
   #95 = Utf8               Code
   #96 = Utf8               StackMapTable
   #97 = Utf8               LineNumberTable
   #98 = Utf8               LocalVariableTable
   #99 = Utf8               Signature
  #100 = Utf8               MethodParameters
  #101 = Utf8               InnerClasses
  #102 = Utf8               EnclosingMethod
  #103 = Utf8               SourceFile
  #104 = Utf8               ScalaInlineInfo
  #105 = Utf8               Scala
{
  private final shapeless.ops.record.Remover remover$1;
    descriptor: Lshapeless/ops/record/Remover;
    flags: (0x0012) ACC_PRIVATE, ACC_FINAL

  private final shapeless.ops.record.AlignByKeys tailAlign$1;
    descriptor: Lshapeless/ops/record/AlignByKeys;
    flags: (0x0012) ACC_PRIVATE, ACC_FINAL

  public shapeless.$colon$colon<V, TA> apply(T);
    descriptor: (Lshapeless/HList;)Lshapeless/$colon$colon;
    flags: (0x0001) ACC_PUBLIC
    Code:
      stack=4, locals=10, args_size=2
         0: aload_0
         1: getfield      #28                 // Field remover$1:Lshapeless/ops/record/Remover;
         4: aload_1
         5: invokeinterface #33,  2           // InterfaceMethod shapeless/ops/record/Remover.apply:(Ljava/lang/Object;)Ljava/lang/Object;
        10: checkcast     #35                 // class scala/Tuple2
        13: astore        4
        15: aload         4
        17: ifnull        52
        20: aload         4
        22: invokevirtual #39                 // Method scala/Tuple2._1:()Ljava/lang/Object;
        25: astore        5
        27: aload         4
        29: invokevirtual #42                 // Method scala/Tuple2._2:()Ljava/lang/Object;
        32: checkcast     #44                 // class shapeless/HList
        35: astore        6
        37: new           #35                 // class scala/Tuple2
        40: dup
        41: aload         5
        43: aload         6
        45: invokespecial #48                 // Method scala/Tuple2."<init>":(Ljava/lang/Object;Ljava/lang/Object;)V
        48: astore_2
        49: goto          65
        52: goto          55
        55: new           #50                 // class scala/MatchError
        58: dup
        59: aload         4
        61: invokespecial #53                 // Method scala/MatchError."<init>":(Ljava/lang/Object;)V
        64: athrow
        65: aload_2
        66: astore_3
        67: aload_3
        68: invokevirtual #39                 // Method scala/Tuple2._1:()Ljava/lang/Object;
        71: astore        7
        73: aload_3
        74: invokevirtual #42                 // Method scala/Tuple2._2:()Ljava/lang/Object;
        77: checkcast     #44                 // class shapeless/HList
        80: astore        8
        82: getstatic     #59                 // Field shapeless/labelled$.MODULE$:Lshapeless/labelled$;
        85: invokevirtual #63                 // Method shapeless/labelled$.field:()Lshapeless/labelled$FieldBuilder;
        88: aload         7
        90: invokevirtual #64                 // Method shapeless/labelled$FieldBuilder.apply:(Ljava/lang/Object;)Ljava/lang/Object;
        93: astore        9
        95: getstatic     #69                 // Field shapeless/HList$.MODULE$:Lshapeless/HList$;
        98: aload_0
        99: getfield      #71                 // Field tailAlign$1:Lshapeless/ops/record/AlignByKeys;
       102: aload         8
       104: invokeinterface #72,  2           // InterfaceMethod shapeless/ops/record/AlignByKeys.apply:(Ljava/lang/Object;)Ljava/lang/Object;
       109: checkcast     #44                 // class shapeless/HList
       112: invokevirtual #76                 // Method shapeless/HList$.hlistOps:(Lshapeless/HList;)Lshapeless/syntax/HListOps;
       115: aload         9
       117: invokevirtual #82                 // Method shapeless/syntax/HListOps.$colon$colon:(Ljava/lang/Object;)Lshapeless/$colon$colon;
       120: areturn
      StackMapTable: number_of_entries = 3
        frame_type = 254 /* append */
          offset_delta = 52
          locals = [ top, top, class scala/Tuple2 ]
        frame_type = 2 /* same */
        frame_type = 255 /* full_frame */
          offset_delta = 9
          locals = [ class shapeless/ops/record/AlignByKeys$$anon$44, class shapeless/HList, class scala/Tuple2, top, class scala/Tuple2, class java/lang/Object, class shapeless/HList ]
          stack = []
      LineNumberTable:
        line 871: 0
        line 872: 82
      LocalVariableTable:
        Start  Length  Slot  Name   Signature
           25      27     5     v   Ljava/lang/Object;
           35      17     6     r   Lshapeless/HList;
           71      49     7     v   Ljava/lang/Object;
           80      40     8     r   Lshapeless/HList;
            0     121     0  this   Lshapeless/ops/record/AlignByKeys$$anon$44;
            0     121     1     t   Lshapeless/HList;
    Signature: #25                          // (TT;)Lshapeless/$colon$colon<TV;TTA;>;
    MethodParameters:
      Name                           Flags
      t                              final

  public java.lang.Object apply(java.lang.Object);
    descriptor: (Ljava/lang/Object;)Ljava/lang/Object;
    flags: (0x1041) ACC_PUBLIC, ACC_BRIDGE, ACC_SYNTHETIC
    Code:
      stack=2, locals=2, args_size=2
         0: aload_0
         1: aload_1
         2: checkcast     #44                 // class shapeless/HList
         5: invokevirtual #90                 // Method apply:(Lshapeless/HList;)Lshapeless/$colon$colon;
         8: areturn
      LineNumberTable:
        line 867: 0
      LocalVariableTable:
        Start  Length  Slot  Name   Signature
            0       9     0  this   Lshapeless/ops/record/AlignByKeys$$anon$44;
            0       9     1     t   Ljava/lang/Object;
    MethodParameters:
      Name                           Flags
      t                              final

  public shapeless.ops.record.AlignByKeys$$anon$44(shapeless.ops.record.Remover, shapeless.ops.record.AlignByKeys);
    descriptor: (Lshapeless/ops/record/Remover;Lshapeless/ops/record/AlignByKeys;)V
    flags: (0x0001) ACC_PUBLIC
    Code:
      stack=2, locals=3, args_size=3
         0: aload_0
         1: aload_1
         2: putfield      #28                 // Field remover$1:Lshapeless/ops/record/Remover;
         5: aload_0
         6: aload_2
         7: putfield      #71                 // Field tailAlign$1:Lshapeless/ops/record/AlignByKeys;
        10: aload_0
        11: invokespecial #94                 // Method java/lang/Object."<init>":()V
        14: return
      LineNumberTable:
        line 865: 0
        line 866: 5
        line 867: 10
      LocalVariableTable:
        Start  Length  Slot  Name   Signature
            0      15     0  this   Lshapeless/ops/record/AlignByKeys$$anon$44;
            0      15     1 remover$1   Lshapeless/ops/record/Remover;
            0      15     2 tailAlign$1   Lshapeless/ops/record/AlignByKeys;
    MethodParameters:
      Name                           Flags
      remover$1                      final
      tailAlign$1                    final
}
InnerClasses:
  public static #18= #15 of #17;          // FieldBuilder=class shapeless/labelled$FieldBuilder of class shapeless/labelled
  public final #2;                        // class shapeless/ops/record/AlignByKeys$$anon$44
EnclosingMethod: #10.#13                // shapeless.ops.record.AlignByKeys$.hlistAlign
Signature: #3                           // Ljava/lang/Object;Lshapeless/ops/record/AlignByKeys<TT;Lshapeless/$colon$colon<TKH;TKT;>;>;
SourceFile: "records.scala"
  ScalaInlineInfo: length = 0x13 (unknown attribute)
   01 01 00 03 00 2D 00 5B 01 00 17 00 1F 01 00 17
   00 18 01
  Scala: length = 0x0 (unknown attribute)

