Classfile /Users/mw/Projects/slang-braindump/.jar/jar11/assemble/slang-braindump/assemble/content/shapeless/ops/record/LowPriorityRemove$$anon$21.class
  Last modified May 29, 2022; size 2573 bytes
  SHA-256 checksum 26c9a2d19dee35eb94a3259e3eede2212a155272dc7d5e74c3cc24ba25a2e62d
  Compiled from "records.scala"
public final class shapeless.ops.record.LowPriorityRemove$$anon$21 extends java.lang.Object implements shapeless.ops.record.Remove<shapeless.$colon$colon<H, T>, E>
  minor version: 0
  major version: 52
  flags: (0x0031) ACC_PUBLIC, ACC_FINAL, ACC_SUPER
  this_class: #2                          // shapeless/ops/record/LowPriorityRemove$$anon$21
  super_class: #5                         // java/lang/Object
  interfaces: 1, fields: 1, methods: 5, attributes: 6
Constant pool:
    #1 = Utf8               shapeless/ops/record/LowPriorityRemove$$anon$21
    #2 = Class              #1            // shapeless/ops/record/LowPriorityRemove$$anon$21
    #3 = Utf8               Ljava/lang/Object;Lshapeless/ops/record/Remove<Lshapeless/$colon$colon<TH;TT;>;TE;>;
    #4 = Utf8               java/lang/Object
    #5 = Class              #4            // java/lang/Object
    #6 = Utf8               shapeless/ops/record/Remove
    #7 = Class              #6            // shapeless/ops/record/Remove
    #8 = Utf8               records.scala
    #9 = Utf8               shapeless/ops/record/LowPriorityRemove
   #10 = Class              #9            // shapeless/ops/record/LowPriorityRemove
   #11 = Utf8               hconsRemove
   #12 = Utf8               (Lshapeless/ops/record/Remove;)Lshapeless/ops/record/Remove;
   #13 = NameAndType        #11:#12       // hconsRemove:(Lshapeless/ops/record/Remove;)Lshapeless/ops/record/Remove;
   #14 = Utf8               rt$2
   #15 = Utf8               Lshapeless/ops/record/Remove;
   #16 = Utf8               apply
   #17 = Utf8               (Lshapeless/$colon$colon;)Lscala/Tuple2;
   #18 = Utf8               (Lshapeless/$colon$colon<TH;TT;>;)Lscala/Tuple2<TE;Lshapeless/$colon$colon<TH;TOutT;>;>;
   #19 = Utf8               l
   #20 = NameAndType        #14:#15       // rt$2:Lshapeless/ops/record/Remove;
   #21 = Fieldref           #2.#20        // shapeless/ops/record/LowPriorityRemove$$anon$21.rt$2:Lshapeless/ops/record/Remove;
   #22 = Utf8               shapeless/$colon$colon
   #23 = Class              #22           // shapeless/$colon$colon
   #24 = Utf8               tail
   #25 = Utf8               ()Lshapeless/HList;
   #26 = NameAndType        #24:#25       // tail:()Lshapeless/HList;
   #27 = Methodref          #23.#26       // shapeless/$colon$colon.tail:()Lshapeless/HList;
   #28 = Utf8               (Ljava/lang/Object;)Ljava/lang/Object;
   #29 = NameAndType        #16:#28       // apply:(Ljava/lang/Object;)Ljava/lang/Object;
   #30 = InterfaceMethodref #7.#29        // shapeless/ops/record/Remove.apply:(Ljava/lang/Object;)Ljava/lang/Object;
   #31 = Utf8               scala/Tuple2
   #32 = Class              #31           // scala/Tuple2
   #33 = Utf8               _1
   #34 = Utf8               ()Ljava/lang/Object;
   #35 = NameAndType        #33:#34       // _1:()Ljava/lang/Object;
   #36 = Methodref          #32.#35       // scala/Tuple2._1:()Ljava/lang/Object;
   #37 = Utf8               _2
   #38 = NameAndType        #37:#34       // _2:()Ljava/lang/Object;
   #39 = Methodref          #32.#38       // scala/Tuple2._2:()Ljava/lang/Object;
   #40 = Utf8               shapeless/HList
   #41 = Class              #40           // shapeless/HList
   #42 = Utf8               <init>
   #43 = Utf8               (Ljava/lang/Object;Ljava/lang/Object;)V
   #44 = NameAndType        #42:#43       // "<init>":(Ljava/lang/Object;Ljava/lang/Object;)V
   #45 = Methodref          #32.#44       // scala/Tuple2."<init>":(Ljava/lang/Object;Ljava/lang/Object;)V
   #46 = Utf8               scala/MatchError
   #47 = Class              #46           // scala/MatchError
   #48 = Utf8               (Ljava/lang/Object;)V
   #49 = NameAndType        #42:#48       // "<init>":(Ljava/lang/Object;)V
   #50 = Methodref          #47.#49       // scala/MatchError."<init>":(Ljava/lang/Object;)V
   #51 = Utf8               head
   #52 = NameAndType        #51:#34       // head:()Ljava/lang/Object;
   #53 = Methodref          #23.#52       // shapeless/$colon$colon.head:()Ljava/lang/Object;
   #54 = Utf8               shapeless/HList$
   #55 = Class              #54           // shapeless/HList$
   #56 = Utf8               MODULE$
   #57 = Utf8               Lshapeless/HList$;
   #58 = NameAndType        #56:#57       // MODULE$:Lshapeless/HList$;
   #59 = Fieldref           #55.#58       // shapeless/HList$.MODULE$:Lshapeless/HList$;
   #60 = Utf8               hlistOps
   #61 = Utf8               (Lshapeless/HList;)Lshapeless/syntax/HListOps;
   #62 = NameAndType        #60:#61       // hlistOps:(Lshapeless/HList;)Lshapeless/syntax/HListOps;
   #63 = Methodref          #55.#62       // shapeless/HList$.hlistOps:(Lshapeless/HList;)Lshapeless/syntax/HListOps;
   #64 = Utf8               shapeless/syntax/HListOps
   #65 = Class              #64           // shapeless/syntax/HListOps
   #66 = Utf8               $colon$colon
   #67 = Utf8               (Ljava/lang/Object;)Lshapeless/$colon$colon;
   #68 = NameAndType        #66:#67       // $colon$colon:(Ljava/lang/Object;)Lshapeless/$colon$colon;
   #69 = Methodref          #65.#68       // shapeless/syntax/HListOps.$colon$colon:(Ljava/lang/Object;)Lshapeless/$colon$colon;
   #70 = Utf8               e
   #71 = Utf8               Ljava/lang/Object;
   #72 = Utf8               Lshapeless/HList;
   #73 = Utf8               this
   #74 = Utf8               Lshapeless/ops/record/LowPriorityRemove$$anon$21;
   #75 = Utf8               Lshapeless/$colon$colon;
   #76 = Utf8               reinsert
   #77 = Utf8               (Lscala/Tuple2;)Lshapeless/$colon$colon;
   #78 = Utf8               (Lscala/Tuple2<TE;Lshapeless/$colon$colon<TH;TOutT;>;>;)Lshapeless/$colon$colon<TH;TT;>;
   #79 = Utf8               out
   #80 = NameAndType        #76:#28       // reinsert:(Ljava/lang/Object;)Ljava/lang/Object;
   #81 = InterfaceMethodref #7.#80        // shapeless/ops/record/Remove.reinsert:(Ljava/lang/Object;)Ljava/lang/Object;
   #82 = Utf8               Lscala/Tuple2;
   #83 = NameAndType        #76:#77       // reinsert:(Lscala/Tuple2;)Lshapeless/$colon$colon;
   #84 = Methodref          #2.#83        // shapeless/ops/record/LowPriorityRemove$$anon$21.reinsert:(Lscala/Tuple2;)Lshapeless/$colon$colon;
   #85 = Utf8               t
   #86 = NameAndType        #16:#17       // apply:(Lshapeless/$colon$colon;)Lscala/Tuple2;
   #87 = Methodref          #2.#86        // shapeless/ops/record/LowPriorityRemove$$anon$21.apply:(Lshapeless/$colon$colon;)Lscala/Tuple2;
   #88 = Utf8               (Lshapeless/ops/record/LowPriorityRemove;Lshapeless/ops/record/Remove;)V
   #89 = Utf8               $outer
   #90 = Utf8               ()V
   #91 = NameAndType        #42:#90       // "<init>":()V
   #92 = Methodref          #5.#91        // java/lang/Object."<init>":()V
   #93 = Utf8               Lshapeless/ops/record/LowPriorityRemove;
   #94 = Utf8               Code
   #95 = Utf8               StackMapTable
   #96 = Utf8               LineNumberTable
   #97 = Utf8               LocalVariableTable
   #98 = Utf8               Signature
   #99 = Utf8               MethodParameters
  #100 = Utf8               InnerClasses
  #101 = Utf8               EnclosingMethod
  #102 = Utf8               SourceFile
  #103 = Utf8               ScalaInlineInfo
  #104 = Utf8               Scala
{
  private final shapeless.ops.record.Remove rt$2;
    descriptor: Lshapeless/ops/record/Remove;
    flags: (0x0012) ACC_PRIVATE, ACC_FINAL

  public scala.Tuple2<E, shapeless.$colon$colon<H, OutT>> apply(shapeless.$colon$colon<H, T>);
    descriptor: (Lshapeless/$colon$colon;)Lscala/Tuple2;
    flags: (0x0001) ACC_PUBLIC
    Code:
      stack=5, locals=10, args_size=2
         0: aload_0
         1: getfield      #21                 // Field rt$2:Lshapeless/ops/record/Remove;
         4: aload_1
         5: invokevirtual #27                 // Method shapeless/$colon$colon.tail:()Lshapeless/HList;
         8: invokeinterface #30,  2           // InterfaceMethod shapeless/ops/record/Remove.apply:(Ljava/lang/Object;)Ljava/lang/Object;
        13: checkcast     #32                 // class scala/Tuple2
        16: astore        4
        18: aload         4
        20: ifnull        55
        23: aload         4
        25: invokevirtual #36                 // Method scala/Tuple2._1:()Ljava/lang/Object;
        28: astore        5
        30: aload         4
        32: invokevirtual #39                 // Method scala/Tuple2._2:()Ljava/lang/Object;
        35: checkcast     #41                 // class shapeless/HList
        38: astore        6
        40: new           #32                 // class scala/Tuple2
        43: dup
        44: aload         5
        46: aload         6
        48: invokespecial #45                 // Method scala/Tuple2."<init>":(Ljava/lang/Object;Ljava/lang/Object;)V
        51: astore_2
        52: goto          68
        55: goto          58
        58: new           #47                 // class scala/MatchError
        61: dup
        62: aload         4
        64: invokespecial #50                 // Method scala/MatchError."<init>":(Ljava/lang/Object;)V
        67: athrow
        68: aload_2
        69: astore_3
        70: aload_3
        71: invokevirtual #36                 // Method scala/Tuple2._1:()Ljava/lang/Object;
        74: astore        7
        76: aload_3
        77: invokevirtual #39                 // Method scala/Tuple2._2:()Ljava/lang/Object;
        80: checkcast     #41                 // class shapeless/HList
        83: astore        8
        85: new           #32                 // class scala/Tuple2
        88: dup
        89: aload         7
        91: aload_1
        92: invokevirtual #53                 // Method shapeless/$colon$colon.head:()Ljava/lang/Object;
        95: astore        9
        97: getstatic     #59                 // Field shapeless/HList$.MODULE$:Lshapeless/HList$;
       100: aload         8
       102: invokevirtual #63                 // Method shapeless/HList$.hlistOps:(Lshapeless/HList;)Lshapeless/syntax/HListOps;
       105: aload         9
       107: invokevirtual #69                 // Method shapeless/syntax/HListOps.$colon$colon:(Ljava/lang/Object;)Lshapeless/$colon$colon;
       110: invokespecial #45                 // Method scala/Tuple2."<init>":(Ljava/lang/Object;Ljava/lang/Object;)V
       113: areturn
      StackMapTable: number_of_entries = 3
        frame_type = 254 /* append */
          offset_delta = 55
          locals = [ top, top, class scala/Tuple2 ]
        frame_type = 2 /* same */
        frame_type = 255 /* full_frame */
          offset_delta = 9
          locals = [ class shapeless/ops/record/LowPriorityRemove$$anon$21, class shapeless/$colon$colon, class scala/Tuple2, top, class scala/Tuple2, class java/lang/Object, class shapeless/HList ]
          stack = []
      LineNumberTable:
        line 499: 0
        line 500: 85
      LocalVariableTable:
        Start  Length  Slot  Name   Signature
           28      27     5     e   Ljava/lang/Object;
           38      17     6  tail   Lshapeless/HList;
           74      39     7     e   Ljava/lang/Object;
           83      30     8  tail   Lshapeless/HList;
            0     114     0  this   Lshapeless/ops/record/LowPriorityRemove$$anon$21;
            0     114     1     l   Lshapeless/$colon$colon;
    Signature: #18                          // (Lshapeless/$colon$colon<TH;TT;>;)Lscala/Tuple2<TE;Lshapeless/$colon$colon<TH;TOutT;>;>;
    MethodParameters:
      Name                           Flags
      l                              final

  public shapeless.$colon$colon<H, T> reinsert(scala.Tuple2<E, shapeless.$colon$colon<H, OutT>>);
    descriptor: (Lscala/Tuple2;)Lshapeless/$colon$colon;
    flags: (0x0001) ACC_PUBLIC
    Code:
      stack=6, locals=3, args_size=2
         0: aload_1
         1: invokevirtual #39                 // Method scala/Tuple2._2:()Ljava/lang/Object;
         4: checkcast     #23                 // class shapeless/$colon$colon
         7: invokevirtual #53                 // Method shapeless/$colon$colon.head:()Ljava/lang/Object;
        10: astore_2
        11: getstatic     #59                 // Field shapeless/HList$.MODULE$:Lshapeless/HList$;
        14: aload_0
        15: getfield      #21                 // Field rt$2:Lshapeless/ops/record/Remove;
        18: new           #32                 // class scala/Tuple2
        21: dup
        22: aload_1
        23: invokevirtual #36                 // Method scala/Tuple2._1:()Ljava/lang/Object;
        26: aload_1
        27: invokevirtual #39                 // Method scala/Tuple2._2:()Ljava/lang/Object;
        30: checkcast     #23                 // class shapeless/$colon$colon
        33: invokevirtual #27                 // Method shapeless/$colon$colon.tail:()Lshapeless/HList;
        36: invokespecial #45                 // Method scala/Tuple2."<init>":(Ljava/lang/Object;Ljava/lang/Object;)V
        39: invokeinterface #81,  2           // InterfaceMethod shapeless/ops/record/Remove.reinsert:(Ljava/lang/Object;)Ljava/lang/Object;
        44: checkcast     #41                 // class shapeless/HList
        47: invokevirtual #63                 // Method shapeless/HList$.hlistOps:(Lshapeless/HList;)Lshapeless/syntax/HListOps;
        50: aload_2
        51: invokevirtual #69                 // Method shapeless/syntax/HListOps.$colon$colon:(Ljava/lang/Object;)Lshapeless/$colon$colon;
        54: areturn
      LineNumberTable:
        line 503: 0
      LocalVariableTable:
        Start  Length  Slot  Name   Signature
            0      55     0  this   Lshapeless/ops/record/LowPriorityRemove$$anon$21;
            0      55     1   out   Lscala/Tuple2;
    Signature: #78                          // (Lscala/Tuple2<TE;Lshapeless/$colon$colon<TH;TOutT;>;>;)Lshapeless/$colon$colon<TH;TT;>;
    MethodParameters:
      Name                           Flags
      out                            final

  public java.lang.Object reinsert(java.lang.Object);
    descriptor: (Ljava/lang/Object;)Ljava/lang/Object;
    flags: (0x1041) ACC_PUBLIC, ACC_BRIDGE, ACC_SYNTHETIC
    Code:
      stack=2, locals=2, args_size=2
         0: aload_0
         1: aload_1
         2: checkcast     #32                 // class scala/Tuple2
         5: invokevirtual #84                 // Method reinsert:(Lscala/Tuple2;)Lshapeless/$colon$colon;
         8: areturn
      LineNumberTable:
        line 495: 0
      LocalVariableTable:
        Start  Length  Slot  Name   Signature
            0       9     0  this   Lshapeless/ops/record/LowPriorityRemove$$anon$21;
            0       9     1   out   Ljava/lang/Object;
    MethodParameters:
      Name                           Flags
      out                            final

  public java.lang.Object apply(java.lang.Object);
    descriptor: (Ljava/lang/Object;)Ljava/lang/Object;
    flags: (0x1041) ACC_PUBLIC, ACC_BRIDGE, ACC_SYNTHETIC
    Code:
      stack=2, locals=2, args_size=2
         0: aload_0
         1: aload_1
         2: checkcast     #23                 // class shapeless/$colon$colon
         5: invokevirtual #87                 // Method apply:(Lshapeless/$colon$colon;)Lscala/Tuple2;
         8: areturn
      LineNumberTable:
        line 495: 0
      LocalVariableTable:
        Start  Length  Slot  Name   Signature
            0       9     0  this   Lshapeless/ops/record/LowPriorityRemove$$anon$21;
            0       9     1     t   Ljava/lang/Object;
    MethodParameters:
      Name                           Flags
      t                              final

  public shapeless.ops.record.LowPriorityRemove$$anon$21(shapeless.ops.record.LowPriorityRemove, shapeless.ops.record.Remove);
    descriptor: (Lshapeless/ops/record/LowPriorityRemove;Lshapeless/ops/record/Remove;)V
    flags: (0x0001) ACC_PUBLIC
    Code:
      stack=2, locals=3, args_size=3
         0: aload_0
         1: aload_2
         2: putfield      #21                 // Field rt$2:Lshapeless/ops/record/Remove;
         5: aload_0
         6: invokespecial #92                 // Method java/lang/Object."<init>":()V
         9: return
      LineNumberTable:
        line 494: 0
        line 495: 5
      LocalVariableTable:
        Start  Length  Slot  Name   Signature
            0      10     0  this   Lshapeless/ops/record/LowPriorityRemove$$anon$21;
            0      10     1 $outer   Lshapeless/ops/record/LowPriorityRemove;
            0      10     2  rt$2   Lshapeless/ops/record/Remove;
    MethodParameters:
      Name                           Flags
      $outer                         final synthetic
      rt$2                           final
}
InnerClasses:
  public final #2;                        // class shapeless/ops/record/LowPriorityRemove$$anon$21
EnclosingMethod: #10.#13                // shapeless.ops.record.LowPriorityRemove.hconsRemove
Signature: #3                           // Ljava/lang/Object;Lshapeless/ops/record/Remove<Lshapeless/$colon$colon<TH;TT;>;TE;>;
SourceFile: "records.scala"
  ScalaInlineInfo: length = 0x1D (unknown attribute)
   01 01 00 05 00 2A 00 58 01 00 10 00 1C 01 00 10
   00 11 01 00 4C 00 1C 01 00 4C 00 4D 01
  Scala: length = 0x0 (unknown attribute)

