Classfile /Users/mw/Projects/slang-braindump/.jar/jar11/assemble/slang-braindump/assemble/content/shapeless/ops/record/LowPriorityMerger.class
  Last modified May 29, 2022; size 1822 bytes
  SHA-256 checksum 5057a1ef0da1f2609025de416f4cb7f4768e08616682845a96e57754c7c4bdbf
  Compiled from "records.scala"
public interface shapeless.ops.record.LowPriorityMerger
  minor version: 0
  major version: 52
  flags: (0x0601) ACC_PUBLIC, ACC_INTERFACE, ACC_ABSTRACT
  this_class: #2                          // shapeless/ops/record/LowPriorityMerger
  super_class: #4                         // java/lang/Object
  interfaces: 0, fields: 0, methods: 3, attributes: 5
Constant pool:
   #1 = Utf8               shapeless/ops/record/LowPriorityMerger
   #2 = Class              #1             // shapeless/ops/record/LowPriorityMerger
   #3 = Utf8               java/lang/Object
   #4 = Class              #3             // java/lang/Object
   #5 = Utf8               records.scala
   #6 = Utf8               Lscala/reflect/ScalaSignature;
   #7 = Utf8               bytes
   #8 = Utf8               \u0006\u0005A3q\u0001B\u0003\u0011\u0002\u0007\u0005A\u0002C\u0003\u0014\u0001\u0011\u0005A#\u0002\u0003\u0019\u0001\u0001I\u0002\"B\u001b\u0001\t\u00071$!\u0005\'poB\u0013\u0018n\u001c:jiflUM]4fe*\u0011aaB\u0001\u0007e\u0016\u001cwN\u001d3\u000b\u0005!I\u0011aA8qg*\t!\"A\u0005tQ\u0006\u0004X\r\\3tg\u000e\u00011C\u0001\u0001\u000e!\tq\u0011#D\u0001\u0010\u0015\u0005\u0001\u0012!B:dC2\f\u0017B\u0001\n\u0010\u0005\u0019\te.\u001f*fM\u00061A%\u001b8ji\u0012\"\u0012!\u0006\t\u0003\u001dYI!aF\b\u0003\tUs\u0017\u000e\u001e\u0002\u0004\u0003VDX\u0003\u0002\u000e$]M\u0012\"aG\u000f\u0007\tq\u0001\u0001A\u0007\u0002\ryI,g-\u001b8f[\u0016tGO\u0010\t\u0005=}\tS&D\u0001\u0006\u0013\t\u0001SA\u0001\u0004NKJ<WM\u001d\t\u0003E\rb\u0001\u0001B\u0003%\u0005\t\u0007QEA\u0001M#\t1\u0013\u0006\u0005\u0002\u000fO%\u0011\u0001f\u0004\u0002\b\u001d>$\b.\u001b8h!\tQ3&D\u0001\n\u0013\ta\u0013BA\u0003I\u0019&\u001cH\u000f\u0005\u0002#]\u0011)qF\u0001b\u0001K\t\tQ*\u0002\u000327\u0001\u0012$aA(viB\u0011!e\r\u0003\u0006i\t\u0011\r!\n\u0002\u0005\u001fV$\b\'\u0001\u0007iY&\u001cH/T3sO\u0016\u0014\u0018\'\u0006\u00038}\u0015CEC\u0001\u001dM!\u0015I$AO$J\u001b\u0005\u0001\u0001\u0003\u0002\u0016<{\u0011K!\u0001P\u0005\u0003\u0019\u0011\u001aw\u000e\\8oI\r|Gn\u001c8\u0011\u0005\trD!B \u0004\u0005\u0004\u0001%!\u0001%\u0012\u0005\u0019\n\u0005C\u0001\bC\u0013\t\u0019uBA\u0002B]f\u0004\"AI#\u0005\u000b\u0019\u001b!\u0019A\u0013\u0003\u0003Q\u0003\"A\t%\u0005\u000b=\u001a!\u0019A\u0013\u0011\t)ZTH\u0013\t\u0003\u0017>s!A\t\'\t\u000b5\u001b\u00019\u0001(\u0002\u00055$\b\u0003\u0002\u0010 \t\u001eK!!M\u0010
   #9 = Utf8               shapeless/ops/record/LowPriorityMerger$$anon$3
  #10 = Class              #9             // shapeless/ops/record/LowPriorityMerger$$anon$3
  #11 = Utf8               hlistMerger1$
  #12 = Utf8               (Lshapeless/ops/record/LowPriorityMerger;Lshapeless/ops/record/Merger;)Lshapeless/ops/record/Merger;
  #13 = Utf8               $this
  #14 = Utf8               mt
  #15 = Utf8               hlistMerger1
  #16 = Utf8               (Lshapeless/ops/record/Merger;)Lshapeless/ops/record/Merger;
  #17 = NameAndType        #15:#16        // hlistMerger1:(Lshapeless/ops/record/Merger;)Lshapeless/ops/record/Merger;
  #18 = InterfaceMethodref #2.#17         // shapeless/ops/record/LowPriorityMerger.hlistMerger1:(Lshapeless/ops/record/Merger;)Lshapeless/ops/record/Merger;
  #19 = Utf8               Lshapeless/ops/record/LowPriorityMerger;
  #20 = Utf8               Lshapeless/ops/record/Merger;
  #21 = Utf8               <H:Ljava/lang/Object;T::Lshapeless/HList;M::Lshapeless/HList;>(Lshapeless/ops/record/Merger<TT;TM;>;)Lshapeless/ops/record/Merger<Lshapeless/$colon$colon<TH;TT;>;TM;>;
  #22 = Utf8               <init>
  #23 = Utf8               (Lshapeless/ops/record/LowPriorityMerger;Lshapeless/ops/record/Merger;)V
  #24 = NameAndType        #22:#23        // "<init>":(Lshapeless/ops/record/LowPriorityMerger;Lshapeless/ops/record/Merger;)V
  #25 = Methodref          #10.#24        // shapeless/ops/record/LowPriorityMerger$$anon$3."<init>":(Lshapeless/ops/record/LowPriorityMerger;Lshapeless/ops/record/Merger;)V
  #26 = Utf8               this
  #27 = Utf8               $init$
  #28 = Utf8               (Lshapeless/ops/record/LowPriorityMerger;)V
  #29 = Utf8               Code
  #30 = Utf8               LineNumberTable
  #31 = Utf8               LocalVariableTable
  #32 = Utf8               MethodParameters
  #33 = Utf8               Signature
  #34 = Utf8               InnerClasses
  #35 = Utf8               SourceFile
  #36 = Utf8               RuntimeVisibleAnnotations
  #37 = Utf8               ScalaInlineInfo
  #38 = Utf8               ScalaSig
{
  public static shapeless.ops.record.Merger hlistMerger1$(shapeless.ops.record.LowPriorityMerger, shapeless.ops.record.Merger);
    descriptor: (Lshapeless/ops/record/LowPriorityMerger;Lshapeless/ops/record/Merger;)Lshapeless/ops/record/Merger;
    flags: (0x1009) ACC_PUBLIC, ACC_STATIC, ACC_SYNTHETIC
    Code:
      stack=2, locals=2, args_size=2
         0: aload_0
         1: aload_1
         2: invokespecial #18                 // InterfaceMethod hlistMerger1:(Lshapeless/ops/record/Merger;)Lshapeless/ops/record/Merger;
         5: areturn
      LineNumberTable:
        line 162: 0
      LocalVariableTable:
        Start  Length  Slot  Name   Signature
            0       6     0 $this   Lshapeless/ops/record/LowPriorityMerger;
            0       6     1    mt   Lshapeless/ops/record/Merger;
    MethodParameters:
      Name                           Flags
      $this                          final synthetic
      mt                             final

  public default <H extends java.lang.Object, T extends shapeless.HList, M extends shapeless.HList> shapeless.ops.record.Merger<shapeless.$colon$colon<H, T>, M> hlistMerger1(shapeless.ops.record.Merger<T, M>);
    descriptor: (Lshapeless/ops/record/Merger;)Lshapeless/ops/record/Merger;
    flags: (0x0001) ACC_PUBLIC
    Code:
      stack=4, locals=2, args_size=2
         0: new           #10                 // class shapeless/ops/record/LowPriorityMerger$$anon$3
         3: dup
         4: aconst_null
         5: aload_1
         6: invokespecial #25                 // Method shapeless/ops/record/LowPriorityMerger$$anon$3."<init>":(Lshapeless/ops/record/LowPriorityMerger;Lshapeless/ops/record/Merger;)V
         9: areturn
      LineNumberTable:
        line 164: 0
      LocalVariableTable:
        Start  Length  Slot  Name   Signature
            0      10     0  this   Lshapeless/ops/record/LowPriorityMerger;
            0      10     1    mt   Lshapeless/ops/record/Merger;
    Signature: #21                          // <H:Ljava/lang/Object;T::Lshapeless/HList;M::Lshapeless/HList;>(Lshapeless/ops/record/Merger<TT;TM;>;)Lshapeless/ops/record/Merger<Lshapeless/$colon$colon<TH;TT;>;TM;>;
    MethodParameters:
      Name                           Flags
      mt                             final

  public static void $init$(shapeless.ops.record.LowPriorityMerger);
    descriptor: (Lshapeless/ops/record/LowPriorityMerger;)V
    flags: (0x0009) ACC_PUBLIC, ACC_STATIC
    Code:
      stack=0, locals=1, args_size=1
         0: return
      LineNumberTable:
        line 159: 0
      LocalVariableTable:
        Start  Length  Slot  Name   Signature
            0       1     0 $this   Lshapeless/ops/record/LowPriorityMerger;
    MethodParameters:
      Name                           Flags
      $this                          final synthetic
}
InnerClasses:
  public final #10;                       // class shapeless/ops/record/LowPriorityMerger$$anon$3
SourceFile: "records.scala"
RuntimeVisibleAnnotations:
  0: #6(#7=s#8)
    scala.reflect.ScalaSignature(
      bytes="\u0006\u0005A3q\u0001B\u0003\u0011\u0002\u0007\u0005A\u0002C\u0003\u0014\u0001\u0011\u0005A#\u0002\u0003\u0019\u0001\u0001I\u0002\"B\u001b\u0001\t\u00071$!\u0005\'poB\u0013\u0018n\u001c:jiflUM]4fe*\u0011aaB\u0001\u0007e\u0016\u001cwN\u001d3\u000b\u0005!I\u0011aA8qg*\t!\"A\u0005tQ\u0006\u0004X\r\\3tg\u000e\u00011C\u0001\u0001\u000e!\tq\u0011#D\u0001\u0010\u0015\u0005\u0001\u0012!B:dC2\f\u0017B\u0001\n\u0010\u0005\u0019\te.\u001f*fM\u00061A%\u001b8ji\u0012\"\u0012!\u0006\t\u0003\u001dYI!aF\b\u0003\tUs\u0017\u000e\u001e\u0002\u0004\u0003VDX\u0003\u0002\u000e$]M\u0012\"aG\u000f\u0007\tq\u0001\u0001A\u0007\u0002\ryI,g-\u001b8f[\u0016tGO\u0010\t\u0005=}\tS&D\u0001\u0006\u0013\t\u0001SA\u0001\u0004NKJ<WM\u001d\t\u0003E\rb\u0001\u0001B\u0003%\u0005\t\u0007QEA\u0001M#\t1\u0013\u0006\u0005\u0002\u000fO%\u0011\u0001f\u0004\u0002\b\u001d>$\b.\u001b8h!\tQ3&D\u0001\n\u0013\ta\u0013BA\u0003I\u0019&\u001cH\u000f\u0005\u0002#]\u0011)qF\u0001b\u0001K\t\tQ*\u0002\u000327\u0001\u0012$aA(viB\u0011!e\r\u0003\u0006i\t\u0011\r!\n\u0002\u0005\u001fV$\b\'\u0001\u0007iY&\u001cH/T3sO\u0016\u0014\u0018\'\u0006\u00038}\u0015CEC\u0001\u001dM!\u0015I$AO$J\u001b\u0005\u0001\u0001\u0003\u0002\u0016<{\u0011K!\u0001P\u0005\u0003\u0019\u0011\u001aw\u000e\\8oI\r|Gn\u001c8\u0011\u0005\trD!B \u0004\u0005\u0004\u0001%!\u0001%\u0012\u0005\u0019\n\u0005C\u0001\bC\u0013\t\u0019uBA\u0002B]f\u0004\"AI#\u0005\u000b\u0019\u001b!\u0019A\u0013\u0003\u0003Q\u0003\"A\t%\u0005\u000b=\u001a!\u0019A\u0013\u0011\t)ZTH\u0013\t\u0003\u0017>s!A\t\'\t\u000b5\u001b\u00019\u0001(\u0002\u00055$\b\u0003\u0002\u0010 \t\u001eK!!M\u0010"
    )
  ScalaInlineInfo: length = 0x13 (unknown attribute)
   01 00 00 03 00 1B 00 1C 01 00 0B 00 0C 01 00 0F
   00 10 00
  ScalaSig: length = 0x3 (unknown attribute)
   05 02 00
