Classfile /Users/mw/Projects/slang-braindump/.jar/jar11/assemble/slang-braindump/assemble/content/shapeless/ops/record/LowPriorityRemover.class
  Last modified May 29, 2022; size 2036 bytes
  SHA-256 checksum e05a829c4ab4d3220712d762e95b2fd07e2bf262a7b0f96cd25075b76aebb1dd
  Compiled from "records.scala"
public interface shapeless.ops.record.LowPriorityRemover
  minor version: 0
  major version: 52
  flags: (0x0601) ACC_PUBLIC, ACC_INTERFACE, ACC_ABSTRACT
  this_class: #2                          // shapeless/ops/record/LowPriorityRemover
  super_class: #4                         // java/lang/Object
  interfaces: 0, fields: 0, methods: 3, attributes: 5
Constant pool:
   #1 = Utf8               shapeless/ops/record/LowPriorityRemover
   #2 = Class              #1             // shapeless/ops/record/LowPriorityRemover
   #3 = Utf8               java/lang/Object
   #4 = Class              #3             // java/lang/Object
   #5 = Utf8               records.scala
   #6 = Utf8               Lscala/reflect/ScalaSignature;
   #7 = Utf8               bytes
   #8 = Utf8               \u0006\u0005}3q\u0001B\u0003\u0011\u0002\u0007\u0005A\u0002C\u0003\u0014\u0001\u0011\u0005A#\u0002\u0003\u0019\u0001\u0001I\u0002\"B\u001d\u0001\t\u0003Q$A\u0005\'poB\u0013\u0018n\u001c:jif\u0014V-\\8wKJT!AB\u0004\u0002\rI,7m\u001c:e\u0015\tA\u0011\"A\u0002paNT\u0011AC\u0001\ng\"\f\u0007/\u001a7fgN\u001c\u0001a\u0005\u0002\u0001\u001bA\u0011a\"E\u0007\u0002\u001f)\t\u0001#A\u0003tG\u0006d\u0017-\u0003\u0002\u0013\u001f\t1\u0011I\\=SK\u001a\fa\u0001J5oSR$C#A\u000b\u0011\u000591\u0012BA\f\u0010\u0005\u0011)f.\u001b;\u0003\u0007\u0005+\b0\u0006\u0003\u001bG9:$CA\u000e\u001e\r\u0011a\u0002\u0001\u0001\u000e\u0003\u0019q\u0012XMZ5oK6,g\u000e\u001e \u0011\tyy\u0012%L\u0007\u0002\u000b%\u0011\u0001%\u0002\u0002\b%\u0016lwN^3s!\t\u00113\u0005\u0004\u0001\u0005\u000b\u0011\u0012!\u0019A\u0013\u0003\u00031\u000b\"AJ\u0015\u0011\u000599\u0013B\u0001\u0015\u0010\u0005\u001dqu\u000e\u001e5j]\u001e\u0004\"AK\u0016\u000e\u0003%I!\u0001L\u0005\u0003\u000b!c\u0015n\u001d;\u0011\u0005\trC!B\u0018\u0003\u0005\u0004\u0001$!A&\u0012\u0005\u0019\n\u0004C\u0001\b3\u0013\t\u0019tBA\u0002B]f,A!N\u000e!m\t\u0019q*\u001e;\u0011\u0005\t:D!\u0002\u001d\u0003\u0005\u0004\u0001$\u0001B(viB\n1\u0002\u001b7jgR\u0014V-\\8wKV11HQ#I\u001bF#\"\u0001P*\u0011\u000bu\u0012ahR%\u000e\u0003\u0001\u0001BAK B\t&\u0011\u0001)\u0003\u0002\rI\r|Gn\u001c8%G>dwN\u001c\t\u0003E\t#QaQ\u0002C\u0002A\u0012\u0011\u0001\u0013\t\u0003E\u0015#QAR\u0002C\u0002\u0015\u0012\u0011\u0001\u0016\t\u0003E!#QaL\u0002C\u0002A\u0002BA\u0004&M\u001f&\u00111j\u0004\u0002\u0007)V\u0004H.\u001a\u001a\u0011\u0005\tjE!\u0002(\u0004\u0005\u0004\u0001$!\u0001,\u0011\t)z\u0014\t\u0015\t\u0003EE#QAU\u0002C\u0002\u0015\u0012AaT;u)\")Ak\u0001a\u0002+\u0006\u0011!\u000f\u001e\t\u0006{\t!uI\u0016\t\u0005\u001d)c\u0005\u000b\u000b\u0003\u00041nk\u0006C\u0001\bZ\u0013\tQvB\u0001\u0006eKB\u0014XmY1uK\u0012\f\u0013\u0001X\u0001\"%\u0016$\u0018-\u001b8fI\u00022wN\u001d\u0011cS:\f\'/\u001f\u0011d_6\u0004\u0018\r^1cS2LG/_\u0011\u0002=\u0006)!GL\u001a/c\u0001
   #9 = Utf8               shapeless/ops/record/LowPriorityRemover$$anon$19
  #10 = Class              #9             // shapeless/ops/record/LowPriorityRemover$$anon$19
  #11 = Utf8               hlistRemove$
  #12 = Utf8               (Lshapeless/ops/record/LowPriorityRemover;Lshapeless/ops/record/Remover;)Lshapeless/ops/record/Remover;
  #13 = Utf8               $this
  #14 = Utf8               rt
  #15 = Utf8               hlistRemove
  #16 = Utf8               (Lshapeless/ops/record/Remover;)Lshapeless/ops/record/Remover;
  #17 = NameAndType        #15:#16        // hlistRemove:(Lshapeless/ops/record/Remover;)Lshapeless/ops/record/Remover;
  #18 = InterfaceMethodref #2.#17         // shapeless/ops/record/LowPriorityRemover.hlistRemove:(Lshapeless/ops/record/Remover;)Lshapeless/ops/record/Remover;
  #19 = Utf8               Lshapeless/ops/record/LowPriorityRemover;
  #20 = Utf8               Lshapeless/ops/record/Remover;
  #21 = Utf8               <H:Ljava/lang/Object;T::Lshapeless/HList;K:Ljava/lang/Object;V:Ljava/lang/Object;OutT::Lshapeless/HList;>(Lshapeless/ops/record/Remover<TT;TK;>;)Lshapeless/ops/record/Remover<Lshapeless/$colon$colon<TH;TT;>;TK;>;
  #22 = Utf8               <init>
  #23 = Utf8               (Lshapeless/ops/record/LowPriorityRemover;Lshapeless/ops/record/Remover;)V
  #24 = NameAndType        #22:#23        // "<init>":(Lshapeless/ops/record/LowPriorityRemover;Lshapeless/ops/record/Remover;)V
  #25 = Methodref          #10.#24        // shapeless/ops/record/LowPriorityRemover$$anon$19."<init>":(Lshapeless/ops/record/LowPriorityRemover;Lshapeless/ops/record/Remover;)V
  #26 = Utf8               this
  #27 = Utf8               $init$
  #28 = Utf8               (Lshapeless/ops/record/LowPriorityRemover;)V
  #29 = Utf8               Code
  #30 = Utf8               LineNumberTable
  #31 = Utf8               LocalVariableTable
  #32 = Utf8               MethodParameters
  #33 = Utf8               Signature
  #34 = Utf8               Deprecated
  #35 = Utf8               InnerClasses
  #36 = Utf8               SourceFile
  #37 = Utf8               RuntimeVisibleAnnotations
  #38 = Utf8               ScalaInlineInfo
  #39 = Utf8               ScalaSig
{
  public static shapeless.ops.record.Remover hlistRemove$(shapeless.ops.record.LowPriorityRemover, shapeless.ops.record.Remover);
    descriptor: (Lshapeless/ops/record/LowPriorityRemover;Lshapeless/ops/record/Remover;)Lshapeless/ops/record/Remover;
    flags: (0x1009) ACC_PUBLIC, ACC_STATIC, ACC_SYNTHETIC
    Code:
      stack=2, locals=2, args_size=2
         0: aload_0
         1: aload_1
         2: invokespecial #18                 // InterfaceMethod hlistRemove:(Lshapeless/ops/record/Remover;)Lshapeless/ops/record/Remover;
         5: areturn
      LineNumberTable:
        line 427: 0
      LocalVariableTable:
        Start  Length  Slot  Name   Signature
            0       6     0 $this   Lshapeless/ops/record/LowPriorityRemover;
            0       6     1    rt   Lshapeless/ops/record/Remover;
    MethodParameters:
      Name                           Flags
      $this                          final synthetic
      rt                             final

  public default <H extends java.lang.Object, T extends shapeless.HList, K extends java.lang.Object, V extends java.lang.Object, OutT extends shapeless.HList> shapeless.ops.record.Remover<shapeless.$colon$colon<H, T>, K> hlistRemove(shapeless.ops.record.Remover<T, K>);
    descriptor: (Lshapeless/ops/record/Remover;)Lshapeless/ops/record/Remover;
    flags: (0x0001) ACC_PUBLIC
    Code:
      stack=4, locals=2, args_size=2
         0: new           #10                 // class shapeless/ops/record/LowPriorityRemover$$anon$19
         3: dup
         4: aconst_null
         5: aload_1
         6: invokespecial #25                 // Method shapeless/ops/record/LowPriorityRemover$$anon$19."<init>":(Lshapeless/ops/record/LowPriorityRemover;Lshapeless/ops/record/Remover;)V
         9: areturn
      LineNumberTable:
        line 429: 0
      LocalVariableTable:
        Start  Length  Slot  Name   Signature
            0      10     0  this   Lshapeless/ops/record/LowPriorityRemover;
            0      10     1    rt   Lshapeless/ops/record/Remover;
    Signature: #21                          // <H:Ljava/lang/Object;T::Lshapeless/HList;K:Ljava/lang/Object;V:Ljava/lang/Object;OutT::Lshapeless/HList;>(Lshapeless/ops/record/Remover<TT;TK;>;)Lshapeless/ops/record/Remover<Lshapeless/$colon$colon<TH;TT;>;TK;>;
    Deprecated: true
    MethodParameters:
      Name                           Flags
      rt                             final

  public static void $init$(shapeless.ops.record.LowPriorityRemover);
    descriptor: (Lshapeless/ops/record/LowPriorityRemover;)V
    flags: (0x0009) ACC_PUBLIC, ACC_STATIC
    Code:
      stack=0, locals=1, args_size=1
         0: return
      LineNumberTable:
        line 423: 0
      LocalVariableTable:
        Start  Length  Slot  Name   Signature
            0       1     0 $this   Lshapeless/ops/record/LowPriorityRemover;
    MethodParameters:
      Name                           Flags
      $this                          final synthetic
}
InnerClasses:
  public final #10;                       // class shapeless/ops/record/LowPriorityRemover$$anon$19
SourceFile: "records.scala"
RuntimeVisibleAnnotations:
  0: #6(#7=s#8)
    scala.reflect.ScalaSignature(
      bytes="\u0006\u0005}3q\u0001B\u0003\u0011\u0002\u0007\u0005A\u0002C\u0003\u0014\u0001\u0011\u0005A#\u0002\u0003\u0019\u0001\u0001I\u0002\"B\u001d\u0001\t\u0003Q$A\u0005\'poB\u0013\u0018n\u001c:jif\u0014V-\\8wKJT!AB\u0004\u0002\rI,7m\u001c:e\u0015\tA\u0011\"A\u0002paNT\u0011AC\u0001\ng\"\f\u0007/\u001a7fgN\u001c\u0001a\u0005\u0002\u0001\u001bA\u0011a\"E\u0007\u0002\u001f)\t\u0001#A\u0003tG\u0006d\u0017-\u0003\u0002\u0013\u001f\t1\u0011I\\=SK\u001a\fa\u0001J5oSR$C#A\u000b\u0011\u000591\u0012BA\f\u0010\u0005\u0011)f.\u001b;\u0003\u0007\u0005+\b0\u0006\u0003\u001bG9:$CA\u000e\u001e\r\u0011a\u0002\u0001\u0001\u000e\u0003\u0019q\u0012XMZ5oK6,g\u000e\u001e \u0011\tyy\u0012%L\u0007\u0002\u000b%\u0011\u0001%\u0002\u0002\b%\u0016lwN^3s!\t\u00113\u0005\u0004\u0001\u0005\u000b\u0011\u0012!\u0019A\u0013\u0003\u00031\u000b\"AJ\u0015\u0011\u000599\u0013B\u0001\u0015\u0010\u0005\u001dqu\u000e\u001e5j]\u001e\u0004\"AK\u0016\u000e\u0003%I!\u0001L\u0005\u0003\u000b!c\u0015n\u001d;\u0011\u0005\trC!B\u0018\u0003\u0005\u0004\u0001$!A&\u0012\u0005\u0019\n\u0004C\u0001\b3\u0013\t\u0019tBA\u0002B]f,A!N\u000e!m\t\u0019q*\u001e;\u0011\u0005\t:D!\u0002\u001d\u0003\u0005\u0004\u0001$\u0001B(viB\n1\u0002\u001b7jgR\u0014V-\\8wKV11HQ#I\u001bF#\"\u0001P*\u0011\u000bu\u0012ahR%\u000e\u0003\u0001\u0001BAK B\t&\u0011\u0001)\u0003\u0002\rI\r|Gn\u001c8%G>dwN\u001c\t\u0003E\t#QaQ\u0002C\u0002A\u0012\u0011\u0001\u0013\t\u0003E\u0015#QAR\u0002C\u0002\u0015\u0012\u0011\u0001\u0016\t\u0003E!#QaL\u0002C\u0002A\u0002BA\u0004&M\u001f&\u00111j\u0004\u0002\u0007)V\u0004H.\u001a\u001a\u0011\u0005\tjE!\u0002(\u0004\u0005\u0004\u0001$!\u0001,\u0011\t)z\u0014\t\u0015\t\u0003EE#QAU\u0002C\u0002\u0015\u0012AaT;u)\")Ak\u0001a\u0002+\u0006\u0011!\u000f\u001e\t\u0006{\t!uI\u0016\t\u0005\u001d)c\u0005\u000b\u000b\u0003\u00041nk\u0006C\u0001\bZ\u0013\tQvB\u0001\u0006eKB\u0014XmY1uK\u0012\f\u0013\u0001X\u0001\"%\u0016$\u0018-\u001b8fI\u00022wN\u001d\u0011cS:\f\'/\u001f\u0011d_6\u0004\u0018\r^1cS2LG/_\u0011\u0002=\u0006)!GL\u001a/c\u0001"
    )
  ScalaInlineInfo: length = 0x13 (unknown attribute)
   01 00 00 03 00 1B 00 1C 01 00 0B 00 0C 01 00 0F
   00 10 00
  ScalaSig: length = 0x3 (unknown attribute)
   05 02 00
