Classfile /Users/mw/Projects/slang-braindump/.jar/jar11/assemble/slang-braindump/assemble/content/shapeless/ops/record/MapValues$.class
  Last modified May 29, 2022; size 2078 bytes
  SHA-256 checksum 46a3856f66d7387f4c4bb0c29bc7e3c98ed41e382a471bbac54a70b35086317b
  Compiled from "records.scala"
public final class shapeless.ops.record.MapValues$ implements java.io.Serializable
  minor version: 0
  major version: 52
  flags: (0x0031) ACC_PUBLIC, ACC_FINAL, ACC_SUPER
  this_class: #2                          // shapeless/ops/record/MapValues$
  super_class: #4                         // java/lang/Object
  interfaces: 1, fields: 1, methods: 6, attributes: 4
Constant pool:
   #1 = Utf8               shapeless/ops/record/MapValues$
   #2 = Class              #1             // shapeless/ops/record/MapValues$
   #3 = Utf8               java/lang/Object
   #4 = Class              #3             // java/lang/Object
   #5 = Utf8               java/io/Serializable
   #6 = Class              #5             // java/io/Serializable
   #7 = Utf8               records.scala
   #8 = Utf8               shapeless/PolyDefns$Case
   #9 = Class              #8             // shapeless/PolyDefns$Case
  #10 = Utf8               shapeless/PolyDefns
  #11 = Class              #10            // shapeless/PolyDefns
  #12 = Utf8               Case
  #13 = Utf8               shapeless/ops/record/MapValues$$anon$41
  #14 = Class              #13            // shapeless/ops/record/MapValues$$anon$41
  #15 = Utf8               shapeless/ops/record/MapValues$$anon$42
  #16 = Class              #15            // shapeless/ops/record/MapValues$$anon$42
  #17 = Utf8               MODULE$
  #18 = Utf8               Lshapeless/ops/record/MapValues$;
  #19 = Utf8               <clinit>
  #20 = Utf8               ()V
  #21 = Utf8               <init>
  #22 = NameAndType        #21:#20        // "<init>":()V
  #23 = Methodref          #2.#22         // shapeless/ops/record/MapValues$."<init>":()V
  #24 = NameAndType        #17:#18        // MODULE$:Lshapeless/ops/record/MapValues$;
  #25 = Fieldref           #2.#24         // shapeless/ops/record/MapValues$.MODULE$:Lshapeless/ops/record/MapValues$;
  #26 = Utf8               apply
  #27 = Utf8               (Lshapeless/ops/record/MapValues;)Lshapeless/ops/record/MapValues;
  #28 = Utf8               <HF:Ljava/lang/Object;L::Lshapeless/HList;>(Lshapeless/ops/record/MapValues<THF;TL;>;)Lshapeless/ops/record/MapValues<THF;TL;>;
  #29 = Utf8               mapValues
  #30 = Utf8               this
  #31 = Utf8               Lshapeless/ops/record/MapValues;
  #32 = Utf8               hnilMapValues
  #33 = Utf8               ()Lshapeless/ops/record/MapValues;
  #34 = Utf8               <HF:Ljava/lang/Object;L::Lshapeless/HNil;>()Lshapeless/ops/record/MapValues<THF;TL;>;
  #35 = Methodref          #14.#22        // shapeless/ops/record/MapValues$$anon$41."<init>":()V
  #36 = Utf8               hconsMapValues
  #37 = Utf8               (Lshapeless/PolyDefns$Case;Lshapeless/ops/record/MapValues;)Lshapeless/ops/record/MapValues;
  #38 = Utf8               <HF:Ljava/lang/Object;K:Ljava/lang/Object;V:Ljava/lang/Object;T::Lshapeless/HList;>(Lshapeless/PolyDefns$Case<THF;Lshapeless/$colon$colon<TV;Lshapeless/HNil;>;>;Lshapeless/ops/record/MapValues<THF;TT;>;)Lshapeless/ops/record/MapValues<THF;Lshapeless/$colon$colon<TV;TT;>;>;
  #39 = Utf8               hc
  #40 = Utf8               mapValuesTail
  #41 = Utf8               (Lshapeless/PolyDefns$Case;Lshapeless/ops/record/MapValues;)V
  #42 = NameAndType        #21:#41        // "<init>":(Lshapeless/PolyDefns$Case;Lshapeless/ops/record/MapValues;)V
  #43 = Methodref          #16.#42        // shapeless/ops/record/MapValues$$anon$42."<init>":(Lshapeless/PolyDefns$Case;Lshapeless/ops/record/MapValues;)V
  #44 = Utf8               Lshapeless/PolyDefns$Case;
  #45 = Utf8               writeReplace
  #46 = Utf8               ()Ljava/lang/Object;
  #47 = Utf8               scala/runtime/ModuleSerializationProxy
  #48 = Class              #47            // scala/runtime/ModuleSerializationProxy
  #49 = Utf8               (Ljava/lang/Class;)V
  #50 = NameAndType        #21:#49        // "<init>":(Ljava/lang/Class;)V
  #51 = Methodref          #48.#50        // scala/runtime/ModuleSerializationProxy."<init>":(Ljava/lang/Class;)V
  #52 = Methodref          #4.#22         // java/lang/Object."<init>":()V
  #53 = Utf8               Code
  #54 = Utf8               LineNumberTable
  #55 = Utf8               LocalVariableTable
  #56 = Utf8               Signature
  #57 = Utf8               MethodParameters
  #58 = Utf8               InnerClasses
  #59 = Utf8               SourceFile
  #60 = Utf8               ScalaInlineInfo
  #61 = Utf8               Scala
{
  public static final shapeless.ops.record.MapValues$ MODULE$;
    descriptor: Lshapeless/ops/record/MapValues$;
    flags: (0x0019) ACC_PUBLIC, ACC_STATIC, ACC_FINAL

  public static {};
    descriptor: ()V
    flags: (0x0009) ACC_PUBLIC, ACC_STATIC
    Code:
      stack=2, locals=0, args_size=0
         0: new           #2                  // class shapeless/ops/record/MapValues$
         3: dup
         4: invokespecial #23                 // Method "<init>":()V
         7: putstatic     #25                 // Field MODULE$:Lshapeless/ops/record/MapValues$;
        10: return
      LineNumberTable:
        line 824: 0

  public <HF extends java.lang.Object, L extends shapeless.HList> shapeless.ops.record.MapValues<HF, L> apply(shapeless.ops.record.MapValues<HF, L>);
    descriptor: (Lshapeless/ops/record/MapValues;)Lshapeless/ops/record/MapValues;
    flags: (0x0001) ACC_PUBLIC
    Code:
      stack=1, locals=2, args_size=2
         0: aload_1
         1: areturn
      LineNumberTable:
        line 825: 0
      LocalVariableTable:
        Start  Length  Slot  Name   Signature
            0       2     0  this   Lshapeless/ops/record/MapValues$;
            0       2     1 mapValues   Lshapeless/ops/record/MapValues;
    Signature: #28                          // <HF:Ljava/lang/Object;L::Lshapeless/HList;>(Lshapeless/ops/record/MapValues<THF;TL;>;)Lshapeless/ops/record/MapValues<THF;TL;>;
    MethodParameters:
      Name                           Flags
      mapValues                      final

  public <HF extends java.lang.Object, L extends shapeless.HNil> shapeless.ops.record.MapValues<HF, L> hnilMapValues();
    descriptor: ()Lshapeless/ops/record/MapValues;
    flags: (0x0001) ACC_PUBLIC
    Code:
      stack=2, locals=1, args_size=1
         0: new           #14                 // class shapeless/ops/record/MapValues$$anon$41
         3: dup
         4: invokespecial #35                 // Method shapeless/ops/record/MapValues$$anon$41."<init>":()V
         7: areturn
      LineNumberTable:
        line 830: 0
      LocalVariableTable:
        Start  Length  Slot  Name   Signature
            0       8     0  this   Lshapeless/ops/record/MapValues$;
    Signature: #34                          // <HF:Ljava/lang/Object;L::Lshapeless/HNil;>()Lshapeless/ops/record/MapValues<THF;TL;>;

  public <HF extends java.lang.Object, K extends java.lang.Object, V extends java.lang.Object, T extends shapeless.HList> shapeless.ops.record.MapValues<HF, shapeless.$colon$colon<V, T>> hconsMapValues(shapeless.PolyDefns$Case<HF, shapeless.$colon$colon<V, shapeless.HNil>>, shapeless.ops.record.MapValues<HF, T>);
    descriptor: (Lshapeless/PolyDefns$Case;Lshapeless/ops/record/MapValues;)Lshapeless/ops/record/MapValues;
    flags: (0x0001) ACC_PUBLIC
    Code:
      stack=4, locals=3, args_size=3
         0: new           #16                 // class shapeless/ops/record/MapValues$$anon$42
         3: dup
         4: aload_1
         5: aload_2
         6: invokespecial #43                 // Method shapeless/ops/record/MapValues$$anon$42."<init>":(Lshapeless/PolyDefns$Case;Lshapeless/ops/record/MapValues;)V
         9: areturn
      LineNumberTable:
        line 839: 0
      LocalVariableTable:
        Start  Length  Slot  Name   Signature
            0      10     0  this   Lshapeless/ops/record/MapValues$;
            0      10     1    hc   Lshapeless/PolyDefns$Case;
            0      10     2 mapValuesTail   Lshapeless/ops/record/MapValues;
    Signature: #38                          // <HF:Ljava/lang/Object;K:Ljava/lang/Object;V:Ljava/lang/Object;T::Lshapeless/HList;>(Lshapeless/PolyDefns$Case<THF;Lshapeless/$colon$colon<TV;Lshapeless/HNil;>;>;Lshapeless/ops/record/MapValues<THF;TT;>;)Lshapeless/ops/record/MapValues<THF;Lshapeless/$colon$colon<TV;TT;>;>;
    MethodParameters:
      Name                           Flags
      hc                             final
      mapValuesTail                  final

  private java.lang.Object writeReplace();
    descriptor: ()Ljava/lang/Object;
    flags: (0x0002) ACC_PRIVATE
    Code:
      stack=3, locals=1, args_size=1
         0: new           #48                 // class scala/runtime/ModuleSerializationProxy
         3: dup
         4: ldc           #2                  // class shapeless/ops/record/MapValues$
         6: invokespecial #51                 // Method scala/runtime/ModuleSerializationProxy."<init>":(Ljava/lang/Class;)V
         9: areturn
      LineNumberTable:
        line 824: 0
      LocalVariableTable:
        Start  Length  Slot  Name   Signature
            0      10     0  this   Lshapeless/ops/record/MapValues$;

  private shapeless.ops.record.MapValues$();
    descriptor: ()V
    flags: (0x0002) ACC_PRIVATE
    Code:
      stack=1, locals=1, args_size=1
         0: aload_0
         1: invokespecial #52                 // Method java/lang/Object."<init>":()V
         4: return
      LineNumberTable:
        line 850: 0
        line 824: 4
      LocalVariableTable:
        Start  Length  Slot  Name   Signature
            0       5     0  this   Lshapeless/ops/record/MapValues$;
}
InnerClasses:
  public static abstract #12= #9 of #11;  // Case=class shapeless/PolyDefns$Case of class shapeless/PolyDefns
  public final #14;                       // class shapeless/ops/record/MapValues$$anon$41
  public final #16;                       // class shapeless/ops/record/MapValues$$anon$42
SourceFile: "records.scala"
  ScalaInlineInfo: length = 0x1D (unknown attribute)
   01 01 00 05 00 15 00 14 01 00 1A 00 1B 01 00 24
   00 25 01 00 20 00 21 01 00 2D 00 2E 01
  Scala: length = 0x0 (unknown attribute)

