Classfile /Users/mw/Projects/slang-braindump/.jar/jar11/assemble/slang-braindump/assemble/content/shapeless/ops/record/MergeWith.class
  Last modified May 29, 2022; size 3438 bytes
  SHA-256 checksum 872c1095ad481baaef69cec54192981a20606529c1370a7e9853d87c1ddbb1ec
  Compiled from "records.scala"
public interface shapeless.ops.record.MergeWith<L extends shapeless.HList, M extends shapeless.HList, F extends java.lang.Object> extends shapeless.package$DepFn2<L, M>, java.io.Serializable
  minor version: 0
  major version: 52
  flags: (0x0601) ACC_PUBLIC, ACC_INTERFACE, ACC_ABSTRACT
  this_class: #2                          // shapeless/ops/record/MergeWith
  super_class: #5                         // java/lang/Object
  interfaces: 2, fields: 0, methods: 3, attributes: 6
Constant pool:
   #1 = Utf8               shapeless/ops/record/MergeWith
   #2 = Class              #1             // shapeless/ops/record/MergeWith
   #3 = Utf8               <L::Lshapeless/HList;M::Lshapeless/HList;F:Ljava/lang/Object;>Ljava/lang/Object;Lshapeless/package$DepFn2<TL;TM;>;Ljava/io/Serializable;
   #4 = Utf8               java/lang/Object
   #5 = Class              #4             // java/lang/Object
   #6 = Utf8               shapeless/package$DepFn2
   #7 = Class              #6             // shapeless/package$DepFn2
   #8 = Utf8               java/io/Serializable
   #9 = Class              #8             // java/io/Serializable
  #10 = Utf8               records.scala
  #11 = Utf8               Lscala/reflect/ScalaSignature;
  #12 = Utf8               bytes
  #13 = Utf8               \u0006\u0005\u0005udaB\u0005\u000b!\u0003\r\n!\u0005\u0003\u0006u\u0001\u0011\t!J\u0004\u0006\u0003*A\tA\u0011\u0004\u0006\u0013)A\t\u0001\u0012\u0005\u0006\u001f\u000e!\t\u0001\u0015\u0005\u0006#\u000e!\tA\u0015\u0005\u0006G\u000e!\u0019\u0001\u001a\u0005\u0006]\u000e!\u0019a\u001c\u0005\n\u0003[\u001a\u0011\u0011!C\u0005\u0003_\u0012\u0011\"T3sO\u0016<\u0016\u000e\u001e5\u000b\u0005-a\u0011A\u0002:fG>\u0014HM\u0003\u0002\u000e\u001d\u0005\u0019q\u000e]:\u000b\u0003=\t\u0011b\u001d5ba\u0016dWm]:\u0004\u0001U!!cI\u0017<\'\u0011\u00011#G\u0018\u0011\u0005Q9R\"A\u000b\u000b\u0003Y\tQa]2bY\u0006L!\u0001G\u000b\u0003\r\u0005s\u0017PU3g!\u0011Qb$\t\u0017\u000f\u0005maR\"\u0001\b\n\u0005uq\u0011a\u00029bG.\fw-Z\u0005\u0003?\u0001\u0012a\u0001R3q\r:\u0014$BA\u000f\u000f!\t\u00113\u0005\u0004\u0001\u0005\u000b\u0011\u0002!\u0019A\u0013\u0003\u00031\u000b\"AJ\u0015\u0011\u0005Q9\u0013B\u0001\u0015\u0016\u0005\u001dqu\u000e\u001e5j]\u001e\u0004\"a\u0007\u0016\n\u0005-r!!\u0002%MSN$\bC\u0001\u0012.\t\u0015q\u0003A1\u0001&\u0005\u0005i\u0005C\u0001\u00198\u001d\t\tdG\u0004\u00023k5\t1G\u0003\u00025!\u00051AH]8pizJ\u0011AF\u0005\u0003;UI!\u0001O\u001d\u0003\u0019M+\'/[1mSj\f\'\r\\3\u000b\u0005u)\"aA(vi\u0012)A\b\u0001b\u0001{\t\ta)\u0005\u0002\'}A\u0011AcP\u0005\u0003\u0001V\u00111!\u00118z\u0003%iUM]4f/&$\b\u000e\u0005\u0002D\u00075\t!b\u0005\u0003\u0004\'\u0015C\u0005CA\"G\u0013\t9%B\u0001\u000bM_^\u0004&/[8sSRLX*\u001a:hK^KG\u000f\u001b\t\u0003\u0013:k\u0011A\u0013\u0006\u0003\u00172\u000b!![8\u000b\u00035\u000bAA[1wC&\u0011\u0001HS\u0001\u0007y%t\u0017\u000e\u001e \u0015\u0003\t\u000bQ!\u00199qYf,BaU-\\;R\u0011A\u000b\u0019\t\u0007+ZC&\f\u00180\u000e\u0003\rI!a\u0016$\u0003\u0007\u0005+\b\u0010\u0005\u0002#3\u0012)A%\u0002b\u0001KA\u0011!e\u0017\u0003\u0006]\u0015\u0011\r!\n\t\u0003Eu#Q\u0001P\u0003C\u0002u\u0002\"aX\u0001\u000f\u0005\t\u0002\u0007\"B1\u0006\u0001\b\u0011\u0017!C7fe\u001e,w+\u001b;i!\u0015\u0019\u0005\u0001\u0017.]\u00035Ag.\u001b7NKJ<WmV5uQV\u0019Qm[7\u0016\u0003\u0019\u0004b!\u0016,hU2T\u0007CA\u000ei\u0013\tIgB\u0001\u0003I\u001d&d\u0007C\u0001\u0012l\t\u0015qcA1\u0001&!\t\u0011S\u000eB\u0003=\r\t\u0007Q(A\biY&\u001cH/T3sO\u0016<\u0016\u000e\u001e53+I\u0001x0!\u0002\u0002B\u0005u\u00111BA\t\u0003\u000f\n)\"a\t\u0015\u000fE\f9#a\u0013\u0002TAIQK\u0016:\u0002\u0010\u0005M\u0011q\u0003\t\u00067M,\u0018\u0011B\u0005\u0003i:\u0011A\u0002J2pY>tGeY8m_:\u0004RA^>\u007f\u0003\u0007q!a^=\u000f\u0005IB\u0018\"A\b\n\u0005it\u0011\u0001\u00037bE\u0016dG.\u001a3\n\u0005ql(!\u0003$jK2$G+\u001f9f\u0015\tQh\u0002\u0005\u0002#\u007f\u00121\u0011\u0011A\u0004C\u0002u\u0012\u0011a\u0013\t\u0004E\u0005\u0015AABA\u0004\u000f\t\u0007QH\u0001\u0002WaA\u0019!%a\u0003\u0005\r\u00055qA1\u0001&\u0005\u0005!\u0006c\u0001\u0012\u0002\u0012\u0011)af\u0002b\u0001KA\u0019!%!\u0006\u0005\u000bq:!\u0019A\u001f\u0011\rm\u0019\u0018\u0011DA\u0011!\u001518P`A\u000e!\r\u0011\u0013Q\u0004\u0003\u0007\u0003?9!\u0019A\u001f\u0003\u0003Y\u00032AIA\u0012\t\u0019\t)c\u0002b\u0001K\t!q*\u001e;1\u0011\u001d\tIc\u0002a\u0002\u0003W\t!A]7\u0011\u0013\u00055\u00121GA\b}\u0006ebbA\"\u00020%\u0019\u0011\u0011\u0007\u0006\u0002\u000fI+Wn\u001c<fe&\u0019q+!\u000e\n\u0007\u0005]\"B\u0001\nM_^\u0004&/[8sSRL(+Z7pm\u0016\u0014\bc\u0002\u000b\u0002<\u0005}\u0012QI\u0005\u0004\u0003{)\"A\u0002+va2,\'\u0007E\u0002#\u0003\u0003\"a!a\u0011\b\u0005\u0004i$A\u0001,2!\r\u0011\u0013q\t\u0003\u0007\u0003\u0013:!\u0019A\u0013\u0003\u00055#\u0006bBA\'\u000f\u0001\u000f\u0011qJ\u0001\u0003[R\u00042\"!\u0015W\u0003\u0013\t)%a\u0005\u0002\"9\u00111I\u0001\u0005\b\u0003+:\u00019AA,\u0003!\u0019\u0017\r\u001c7cC\u000e\\\u0007\u0003DA-\u0003S\n\u0019\"a\u0001\u0002@\u0005ma\u0002BA.\u0003Cr1aGA/\u0013\r\tyFD\u0001\n!>d\u0017\u0010R3g]NLA!a\u0019\u0002f\u0005)1)Y:fe%\u0019\u0011q\r\b\u0003\u000b\r\u000b7/Z:\n\u0007]\u000bYG\u0003\u0003\u0002d\u0005\u0015\u0014\u0001D<sSR,\'+\u001a9mC\u000e,GCAA9!\u0011\t\u0019(!\u001f\u000e\u0005\u0005U$bAA<\u0019\u0006!A.\u00198h\u0013\u0011\tY(!\u001e\u0003\r=\u0013\'.Z2u\u0001
  #14 = Utf8               shapeless/PolyDefns$Case
  #15 = Class              #14            // shapeless/PolyDefns$Case
  #16 = Utf8               shapeless/PolyDefns
  #17 = Class              #16            // shapeless/PolyDefns
  #18 = Utf8               Case
  #19 = Utf8               shapeless/package
  #20 = Class              #19            // shapeless/package
  #21 = Utf8               DepFn2
  #22 = Utf8               hlistMergeWith2
  #23 = Utf8               (Lshapeless/ops/record/Remover;Lshapeless/ops/record/MergeWith;Lshapeless/PolyDefns$Case;)Lshapeless/ops/record/MergeWith;
  #24 = Utf8               <K:Ljava/lang/Object;V0:Ljava/lang/Object;V1:Ljava/lang/Object;V:Ljava/lang/Object;T::Lshapeless/HList;M::Lshapeless/HList;MT::Lshapeless/HList;F:Ljava/lang/Object;Out0::Lshapeless/HList;>(Lshapeless/ops/record/Remover<TM;TK;>;Lshapeless/ops/record/MergeWith<TT;TMT;TF;>;Lshapeless/PolyDefns$Case<TF;Lshapeless/$colon$colon<TV0;Lshapeless/$colon$colon<TV1;Lshapeless/HNil;>;>;>;)Lshapeless/ops/record/MergeWith<Lshapeless/$colon$colon<TV0;TT;>;TM;TF;>;
  #25 = Utf8               rm
  #26 = Utf8               mt
  #27 = Utf8               callback
  #28 = Utf8               shapeless/ops/record/MergeWith$
  #29 = Class              #28            // shapeless/ops/record/MergeWith$
  #30 = Utf8               MODULE$
  #31 = Utf8               Lshapeless/ops/record/MergeWith$;
  #32 = NameAndType        #30:#31        // MODULE$:Lshapeless/ops/record/MergeWith$;
  #33 = Fieldref           #29.#32        // shapeless/ops/record/MergeWith$.MODULE$:Lshapeless/ops/record/MergeWith$;
  #34 = NameAndType        #22:#23        // hlistMergeWith2:(Lshapeless/ops/record/Remover;Lshapeless/ops/record/MergeWith;Lshapeless/PolyDefns$Case;)Lshapeless/ops/record/MergeWith;
  #35 = Methodref          #29.#34        // shapeless/ops/record/MergeWith$.hlistMergeWith2:(Lshapeless/ops/record/Remover;Lshapeless/ops/record/MergeWith;Lshapeless/PolyDefns$Case;)Lshapeless/ops/record/MergeWith;
  #36 = Utf8               hnilMergeWith
  #37 = Utf8               ()Lshapeless/ops/record/MergeWith;
  #38 = Utf8               <M::Lshapeless/HList;F:Ljava/lang/Object;>()Lshapeless/ops/record/MergeWith<Lshapeless/HNil;TM;TF;>;
  #39 = NameAndType        #36:#37        // hnilMergeWith:()Lshapeless/ops/record/MergeWith;
  #40 = Methodref          #29.#39        // shapeless/ops/record/MergeWith$.hnilMergeWith:()Lshapeless/ops/record/MergeWith;
  #41 = Utf8               hlistMergeWith1
  #42 = Utf8               (Lshapeless/ops/record/MergeWith;Lshapeless/ops/record/LacksKey;)Lshapeless/ops/record/MergeWith;
  #43 = Utf8               <K:Ljava/lang/Object;V:Ljava/lang/Object;T::Lshapeless/HList;M::Lshapeless/HList;F:Ljava/lang/Object;>(Lshapeless/ops/record/MergeWith<TT;TM;TF;>;Lshapeless/ops/record/LacksKey<TM;TK;>;)Lshapeless/ops/record/MergeWith<Lshapeless/$colon$colon<TV;TT;>;TM;TF;>;
  #44 = Utf8               lacksKey
  #45 = NameAndType        #41:#42        // hlistMergeWith1:(Lshapeless/ops/record/MergeWith;Lshapeless/ops/record/LacksKey;)Lshapeless/ops/record/MergeWith;
  #46 = Methodref          #29.#45        // shapeless/ops/record/MergeWith$.hlistMergeWith1:(Lshapeless/ops/record/MergeWith;Lshapeless/ops/record/LacksKey;)Lshapeless/ops/record/MergeWith;
  #47 = Utf8               Code
  #48 = Utf8               Signature
  #49 = Utf8               MethodParameters
  #50 = Utf8               InnerClasses
  #51 = Utf8               SourceFile
  #52 = Utf8               RuntimeVisibleAnnotations
  #53 = Utf8               ScalaInlineInfo
  #54 = Utf8               ScalaSig
{
  public static <K extends java.lang.Object, V0 extends java.lang.Object, V1 extends java.lang.Object, V extends java.lang.Object, T extends shapeless.HList, M extends shapeless.HList, MT extends shapeless.HList, F extends java.lang.Object, Out0 extends shapeless.HList> shapeless.ops.record.MergeWith<shapeless.$colon$colon<V0, T>, M, F> hlistMergeWith2(shapeless.ops.record.Remover<M, K>, shapeless.ops.record.MergeWith<T, MT, F>, shapeless.PolyDefns$Case<F, shapeless.$colon$colon<V0, shapeless.$colon$colon<V1, shapeless.HNil>>>);
    descriptor: (Lshapeless/ops/record/Remover;Lshapeless/ops/record/MergeWith;Lshapeless/PolyDefns$Case;)Lshapeless/ops/record/MergeWith;
    flags: (0x0009) ACC_PUBLIC, ACC_STATIC
    Code:
      stack=4, locals=3, args_size=3
         0: getstatic     #33                 // Field shapeless/ops/record/MergeWith$.MODULE$:Lshapeless/ops/record/MergeWith$;
         3: aload_0
         4: aload_1
         5: aload_2
         6: invokevirtual #35                 // Method shapeless/ops/record/MergeWith$.hlistMergeWith2:(Lshapeless/ops/record/Remover;Lshapeless/ops/record/MergeWith;Lshapeless/PolyDefns$Case;)Lshapeless/ops/record/MergeWith;
         9: areturn
    Signature: #24                          // <K:Ljava/lang/Object;V0:Ljava/lang/Object;V1:Ljava/lang/Object;V:Ljava/lang/Object;T::Lshapeless/HList;M::Lshapeless/HList;MT::Lshapeless/HList;F:Ljava/lang/Object;Out0::Lshapeless/HList;>(Lshapeless/ops/record/Remover<TM;TK;>;Lshapeless/ops/record/MergeWith<TT;TMT;TF;>;Lshapeless/PolyDefns$Case<TF;Lshapeless/$colon$colon<TV0;Lshapeless/$colon$colon<TV1;Lshapeless/HNil;>;>;>;)Lshapeless/ops/record/MergeWith<Lshapeless/$colon$colon<TV0;TT;>;TM;TF;>;
    MethodParameters:
      Name                           Flags
      rm                             final
      mt                             final
      callback                       final

  public static <M extends shapeless.HList, F extends java.lang.Object> shapeless.ops.record.MergeWith<shapeless.HNil, M, F> hnilMergeWith();
    descriptor: ()Lshapeless/ops/record/MergeWith;
    flags: (0x0009) ACC_PUBLIC, ACC_STATIC
    Code:
      stack=1, locals=0, args_size=0
         0: getstatic     #33                 // Field shapeless/ops/record/MergeWith$.MODULE$:Lshapeless/ops/record/MergeWith$;
         3: invokevirtual #40                 // Method shapeless/ops/record/MergeWith$.hnilMergeWith:()Lshapeless/ops/record/MergeWith;
         6: areturn
    Signature: #38                          // <M::Lshapeless/HList;F:Ljava/lang/Object;>()Lshapeless/ops/record/MergeWith<Lshapeless/HNil;TM;TF;>;

  public static <K extends java.lang.Object, V extends java.lang.Object, T extends shapeless.HList, M extends shapeless.HList, F extends java.lang.Object> shapeless.ops.record.MergeWith<shapeless.$colon$colon<V, T>, M, F> hlistMergeWith1(shapeless.ops.record.MergeWith<T, M, F>, shapeless.ops.record.LacksKey<M, K>);
    descriptor: (Lshapeless/ops/record/MergeWith;Lshapeless/ops/record/LacksKey;)Lshapeless/ops/record/MergeWith;
    flags: (0x0009) ACC_PUBLIC, ACC_STATIC
    Code:
      stack=3, locals=2, args_size=2
         0: getstatic     #33                 // Field shapeless/ops/record/MergeWith$.MODULE$:Lshapeless/ops/record/MergeWith$;
         3: aload_0
         4: aload_1
         5: invokevirtual #46                 // Method shapeless/ops/record/MergeWith$.hlistMergeWith1:(Lshapeless/ops/record/MergeWith;Lshapeless/ops/record/LacksKey;)Lshapeless/ops/record/MergeWith;
         8: areturn
    Signature: #43                          // <K:Ljava/lang/Object;V:Ljava/lang/Object;T::Lshapeless/HList;M::Lshapeless/HList;F:Ljava/lang/Object;>(Lshapeless/ops/record/MergeWith<TT;TM;TF;>;Lshapeless/ops/record/LacksKey<TM;TK;>;)Lshapeless/ops/record/MergeWith<Lshapeless/$colon$colon<TV;TT;>;TM;TF;>;
    MethodParameters:
      Name                           Flags
      mt                             final
      lacksKey                       final
}
InnerClasses:
  public static abstract #18= #15 of #17; // Case=class shapeless/PolyDefns$Case of class shapeless/PolyDefns
  public static #21= #7 of #20;           // DepFn2=class shapeless/package$DepFn2 of class shapeless/package
Signature: #3                           // <L::Lshapeless/HList;M::Lshapeless/HList;F:Ljava/lang/Object;>Ljava/lang/Object;Lshapeless/package$DepFn2<TL;TM;>;Ljava/io/Serializable;
SourceFile: "records.scala"
RuntimeVisibleAnnotations:
  0: #11(#12=s#13)
    scala.reflect.ScalaSignature(
      bytes="\u0006\u0005\u0005udaB\u0005\u000b!\u0003\r\n!\u0005\u0003\u0006u\u0001\u0011\t!J\u0004\u0006\u0003*A\tA\u0011\u0004\u0006\u0013)A\t\u0001\u0012\u0005\u0006\u001f\u000e!\t\u0001\u0015\u0005\u0006#\u000e!\tA\u0015\u0005\u0006G\u000e!\u0019\u0001\u001a\u0005\u0006]\u000e!\u0019a\u001c\u0005\n\u0003[\u001a\u0011\u0011!C\u0005\u0003_\u0012\u0011\"T3sO\u0016<\u0016\u000e\u001e5\u000b\u0005-a\u0011A\u0002:fG>\u0014HM\u0003\u0002\u000e\u001d\u0005\u0019q\u000e]:\u000b\u0003=\t\u0011b\u001d5ba\u0016dWm]:\u0004\u0001U!!cI\u0017<\'\u0011\u00011#G\u0018\u0011\u0005Q9R\"A\u000b\u000b\u0003Y\tQa]2bY\u0006L!\u0001G\u000b\u0003\r\u0005s\u0017PU3g!\u0011Qb$\t\u0017\u000f\u0005maR\"\u0001\b\n\u0005uq\u0011a\u00029bG.\fw-Z\u0005\u0003?\u0001\u0012a\u0001R3q\r:\u0014$BA\u000f\u000f!\t\u00113\u0005\u0004\u0001\u0005\u000b\u0011\u0002!\u0019A\u0013\u0003\u00031\u000b\"AJ\u0015\u0011\u0005Q9\u0013B\u0001\u0015\u0016\u0005\u001dqu\u000e\u001e5j]\u001e\u0004\"a\u0007\u0016\n\u0005-r!!\u0002%MSN$\bC\u0001\u0012.\t\u0015q\u0003A1\u0001&\u0005\u0005i\u0005C\u0001\u00198\u001d\t\tdG\u0004\u00023k5\t1G\u0003\u00025!\u00051AH]8pizJ\u0011AF\u0005\u0003;UI!\u0001O\u001d\u0003\u0019M+\'/[1mSj\f\'\r\\3\u000b\u0005u)\"aA(vi\u0012)A\b\u0001b\u0001{\t\ta)\u0005\u0002\'}A\u0011AcP\u0005\u0003\u0001V\u00111!\u00118z\u0003%iUM]4f/&$\b\u000e\u0005\u0002D\u00075\t!b\u0005\u0003\u0004\'\u0015C\u0005CA\"G\u0013\t9%B\u0001\u000bM_^\u0004&/[8sSRLX*\u001a:hK^KG\u000f\u001b\t\u0003\u0013:k\u0011A\u0013\u0006\u0003\u00172\u000b!![8\u000b\u00035\u000bAA[1wC&\u0011\u0001HS\u0001\u0007y%t\u0017\u000e\u001e \u0015\u0003\t\u000bQ!\u00199qYf,BaU-\\;R\u0011A\u000b\u0019\t\u0007+ZC&\f\u00180\u000e\u0003\rI!a\u0016$\u0003\u0007\u0005+\b\u0010\u0005\u0002#3\u0012)A%\u0002b\u0001KA\u0011!e\u0017\u0003\u0006]\u0015\u0011\r!\n\t\u0003Eu#Q\u0001P\u0003C\u0002u\u0002\"aX\u0001\u000f\u0005\t\u0002\u0007\"B1\u0006\u0001\b\u0011\u0017!C7fe\u001e,w+\u001b;i!\u0015\u0019\u0005\u0001\u0017.]\u00035Ag.\u001b7NKJ<WmV5uQV\u0019Qm[7\u0016\u0003\u0019\u0004b!\u0016,hU2T\u0007CA\u000ei\u0013\tIgB\u0001\u0003I\u001d&d\u0007C\u0001\u0012l\t\u0015qcA1\u0001&!\t\u0011S\u000eB\u0003=\r\t\u0007Q(A\biY&\u001cH/T3sO\u0016<\u0016\u000e\u001e53+I\u0001x0!\u0002\u0002B\u0005u\u00111BA\t\u0003\u000f\n)\"a\t\u0015\u000fE\f9#a\u0013\u0002TAIQK\u0016:\u0002\u0010\u0005M\u0011q\u0003\t\u00067M,\u0018\u0011B\u0005\u0003i:\u0011A\u0002J2pY>tGeY8m_:\u0004RA^>\u007f\u0003\u0007q!a^=\u000f\u0005IB\u0018\"A\b\n\u0005it\u0011\u0001\u00037bE\u0016dG.\u001a3\n\u0005ql(!\u0003$jK2$G+\u001f9f\u0015\tQh\u0002\u0005\u0002#\u007f\u00121\u0011\u0011A\u0004C\u0002u\u0012\u0011a\u0013\t\u0004E\u0005\u0015AABA\u0004\u000f\t\u0007QH\u0001\u0002WaA\u0019!%a\u0003\u0005\r\u00055qA1\u0001&\u0005\u0005!\u0006c\u0001\u0012\u0002\u0012\u0011)af\u0002b\u0001KA\u0019!%!\u0006\u0005\u000bq:!\u0019A\u001f\u0011\rm\u0019\u0018\u0011DA\u0011!\u001518P`A\u000e!\r\u0011\u0013Q\u0004\u0003\u0007\u0003?9!\u0019A\u001f\u0003\u0003Y\u00032AIA\u0012\t\u0019\t)c\u0002b\u0001K\t!q*\u001e;1\u0011\u001d\tIc\u0002a\u0002\u0003W\t!A]7\u0011\u0013\u00055\u00121GA\b}\u0006ebbA\"\u00020%\u0019\u0011\u0011\u0007\u0006\u0002\u000fI+Wn\u001c<fe&\u0019q+!\u000e\n\u0007\u0005]\"B\u0001\nM_^\u0004&/[8sSRL(+Z7pm\u0016\u0014\bc\u0002\u000b\u0002<\u0005}\u0012QI\u0005\u0004\u0003{)\"A\u0002+va2,\'\u0007E\u0002#\u0003\u0003\"a!a\u0011\b\u0005\u0004i$A\u0001,2!\r\u0011\u0013q\t\u0003\u0007\u0003\u0013:!\u0019A\u0013\u0003\u00055#\u0006bBA\'\u000f\u0001\u000f\u0011qJ\u0001\u0003[R\u00042\"!\u0015W\u0003\u0013\t)%a\u0005\u0002\"9\u00111I\u0001\u0005\b\u0003+:\u00019AA,\u0003!\u0019\u0017\r\u001c7cC\u000e\\\u0007\u0003DA-\u0003S\n\u0019\"a\u0001\u0002@\u0005ma\u0002BA.\u0003Cr1aGA/\u0013\r\tyFD\u0001\n!>d\u0017\u0010R3g]NLA!a\u0019\u0002f\u0005)1)Y:fe%\u0019\u0011q\r\b\u0003\u000b\r\u000b7/Z:\n\u0007]\u000bYG\u0003\u0003\u0002d\u0005\u0015\u0014\u0001D<sSR,\'+\u001a9mC\u000e,GCAA9!\u0011\t\u0019(!\u001f\u000e\u0005\u0005U$bAA<\u0019\u0006!A.\u00198h\u0013\u0011\tY(!\u001e\u0003\r=\u0013\'.Z2u\u0001"
    )
  ScalaInlineInfo: length = 0x4 (unknown attribute)
   01 00 00 00
  ScalaSig: length = 0x3 (unknown attribute)
   05 02 00
