Classfile /Users/mw/Projects/slang-braindump/.jar/jar11/assemble/slang-braindump/assemble/content/shapeless/ops/record/Remove$.class
  Last modified May 29, 2022; size 2042 bytes
  SHA-256 checksum efef177ccddbb6da6fc45bb44e9a79d2db92bfa1c5e9e64802ffb26199516627
  Compiled from "records.scala"
public final class shapeless.ops.record.Remove$ implements shapeless.ops.record.LowPriorityRemove,java.io.Serializable
  minor version: 0
  major version: 52
  flags: (0x0031) ACC_PUBLIC, ACC_FINAL, ACC_SUPER
  this_class: #2                          // shapeless/ops/record/Remove$
  super_class: #4                         // java/lang/Object
  interfaces: 2, fields: 1, methods: 7, attributes: 4
Constant pool:
   #1 = Utf8               shapeless/ops/record/Remove$
   #2 = Class              #1             // shapeless/ops/record/Remove$
   #3 = Utf8               java/lang/Object
   #4 = Class              #3             // java/lang/Object
   #5 = Utf8               shapeless/ops/record/LowPriorityRemove
   #6 = Class              #5             // shapeless/ops/record/LowPriorityRemove
   #7 = Utf8               java/io/Serializable
   #8 = Class              #7             // java/io/Serializable
   #9 = Utf8               records.scala
  #10 = Utf8               shapeless/ops/record/Remove$$anon$22
  #11 = Class              #10            // shapeless/ops/record/Remove$$anon$22
  #12 = Utf8               shapeless/ops/record/Remove$$anon$23
  #13 = Class              #12            // shapeless/ops/record/Remove$$anon$23
  #14 = Utf8               MODULE$
  #15 = Utf8               Lshapeless/ops/record/Remove$;
  #16 = Utf8               <clinit>
  #17 = Utf8               ()V
  #18 = Utf8               <init>
  #19 = NameAndType        #18:#17        // "<init>":()V
  #20 = Methodref          #2.#19         // shapeless/ops/record/Remove$."<init>":()V
  #21 = NameAndType        #14:#15        // MODULE$:Lshapeless/ops/record/Remove$;
  #22 = Fieldref           #2.#21         // shapeless/ops/record/Remove$.MODULE$:Lshapeless/ops/record/Remove$;
  #23 = Utf8               $init$
  #24 = Utf8               (Lshapeless/ops/record/LowPriorityRemove;)V
  #25 = NameAndType        #23:#24        // $init$:(Lshapeless/ops/record/LowPriorityRemove;)V
  #26 = InterfaceMethodref #6.#25         // shapeless/ops/record/LowPriorityRemove.$init$:(Lshapeless/ops/record/LowPriorityRemove;)V
  #27 = Utf8               hconsRemove
  #28 = Utf8               (Lshapeless/ops/record/Remove;)Lshapeless/ops/record/Remove;
  #29 = Utf8               <H:Ljava/lang/Object;T::Lshapeless/HList;E:Ljava/lang/Object;OutT::Lshapeless/HList;>(Lshapeless/ops/record/Remove<TT;TE;>;)Lshapeless/ops/record/Remove<Lshapeless/$colon$colon<TH;TT;>;TE;>;
  #30 = Utf8               rt
  #31 = Utf8               hconsRemove$
  #32 = Utf8               (Lshapeless/ops/record/LowPriorityRemove;Lshapeless/ops/record/Remove;)Lshapeless/ops/record/Remove;
  #33 = NameAndType        #31:#32        // hconsRemove$:(Lshapeless/ops/record/LowPriorityRemove;Lshapeless/ops/record/Remove;)Lshapeless/ops/record/Remove;
  #34 = InterfaceMethodref #6.#33         // shapeless/ops/record/LowPriorityRemove.hconsRemove$:(Lshapeless/ops/record/LowPriorityRemove;Lshapeless/ops/record/Remove;)Lshapeless/ops/record/Remove;
  #35 = Utf8               this
  #36 = Utf8               Lshapeless/ops/record/Remove;
  #37 = Utf8               apply
  #38 = Utf8               <L::Lshapeless/HList;E:Ljava/lang/Object;>(Lshapeless/ops/record/Remove<TL;TE;>;)Lshapeless/ops/record/Remove<TL;TE;>;
  #39 = Utf8               remove
  #40 = Utf8               removeHead
  #41 = Utf8               ()Lshapeless/ops/record/Remove;
  #42 = Utf8               <K:Ljava/lang/Object;V:Ljava/lang/Object;T::Lshapeless/HList;>()Lshapeless/ops/record/Remove<Lshapeless/$colon$colon<TV;TT;>;TV;>;
  #43 = Methodref          #11.#19        // shapeless/ops/record/Remove$$anon$22."<init>":()V
  #44 = Utf8               removeUnlabelledHead
  #45 = Methodref          #13.#19        // shapeless/ops/record/Remove$$anon$23."<init>":()V
  #46 = Utf8               writeReplace
  #47 = Utf8               ()Ljava/lang/Object;
  #48 = Utf8               scala/runtime/ModuleSerializationProxy
  #49 = Class              #48            // scala/runtime/ModuleSerializationProxy
  #50 = Utf8               (Ljava/lang/Class;)V
  #51 = NameAndType        #18:#50        // "<init>":(Ljava/lang/Class;)V
  #52 = Methodref          #49.#51        // scala/runtime/ModuleSerializationProxy."<init>":(Ljava/lang/Class;)V
  #53 = Methodref          #4.#19         // java/lang/Object."<init>":()V
  #54 = Utf8               Code
  #55 = Utf8               LineNumberTable
  #56 = Utf8               LocalVariableTable
  #57 = Utf8               Signature
  #58 = Utf8               MethodParameters
  #59 = Utf8               InnerClasses
  #60 = Utf8               SourceFile
  #61 = Utf8               ScalaInlineInfo
  #62 = Utf8               Scala
{
  public static final shapeless.ops.record.Remove$ MODULE$;
    descriptor: Lshapeless/ops/record/Remove$;
    flags: (0x0019) ACC_PUBLIC, ACC_STATIC, ACC_FINAL

  public static {};
    descriptor: ()V
    flags: (0x0009) ACC_PUBLIC, ACC_STATIC
    Code:
      stack=2, locals=0, args_size=0
         0: new           #2                  // class shapeless/ops/record/Remove$
         3: dup
         4: invokespecial #20                 // Method "<init>":()V
         7: putstatic     #22                 // Field MODULE$:Lshapeless/ops/record/Remove$;
        10: getstatic     #22                 // Field MODULE$:Lshapeless/ops/record/Remove$;
        13: invokestatic  #26                 // InterfaceMethod shapeless/ops/record/LowPriorityRemove.$init$:(Lshapeless/ops/record/LowPriorityRemove;)V
        16: return
      LineNumberTable:
        line 507: 0

  public <H extends java.lang.Object, T extends shapeless.HList, E extends java.lang.Object, OutT extends shapeless.HList> shapeless.ops.record.Remove<shapeless.$colon$colon<H, T>, E> hconsRemove(shapeless.ops.record.Remove<T, E>);
    descriptor: (Lshapeless/ops/record/Remove;)Lshapeless/ops/record/Remove;
    flags: (0x0001) ACC_PUBLIC
    Code:
      stack=2, locals=2, args_size=2
         0: aload_0
         1: aload_1
         2: invokestatic  #34                 // InterfaceMethod shapeless/ops/record/LowPriorityRemove.hconsRemove$:(Lshapeless/ops/record/LowPriorityRemove;Lshapeless/ops/record/Remove;)Lshapeless/ops/record/Remove;
         5: areturn
      LineNumberTable:
        line 507: 0
      LocalVariableTable:
        Start  Length  Slot  Name   Signature
            0       6     0  this   Lshapeless/ops/record/Remove$;
            0       6     1    rt   Lshapeless/ops/record/Remove;
    Signature: #29                          // <H:Ljava/lang/Object;T::Lshapeless/HList;E:Ljava/lang/Object;OutT::Lshapeless/HList;>(Lshapeless/ops/record/Remove<TT;TE;>;)Lshapeless/ops/record/Remove<Lshapeless/$colon$colon<TH;TT;>;TE;>;
    MethodParameters:
      Name                           Flags
      rt                             final

  public <L extends shapeless.HList, E extends java.lang.Object> shapeless.ops.record.Remove<L, E> apply(shapeless.ops.record.Remove<L, E>);
    descriptor: (Lshapeless/ops/record/Remove;)Lshapeless/ops/record/Remove;
    flags: (0x0001) ACC_PUBLIC
    Code:
      stack=1, locals=2, args_size=2
         0: aload_1
         1: areturn
      LineNumberTable:
        line 508: 0
      LocalVariableTable:
        Start  Length  Slot  Name   Signature
            0       2     0  this   Lshapeless/ops/record/Remove$;
            0       2     1 remove   Lshapeless/ops/record/Remove;
    Signature: #38                          // <L::Lshapeless/HList;E:Ljava/lang/Object;>(Lshapeless/ops/record/Remove<TL;TE;>;)Lshapeless/ops/record/Remove<TL;TE;>;
    MethodParameters:
      Name                           Flags
      remove                         final

  public <K extends java.lang.Object, V extends java.lang.Object, T extends shapeless.HList> shapeless.ops.record.Remove<shapeless.$colon$colon<V, T>, V> removeHead();
    descriptor: ()Lshapeless/ops/record/Remove;
    flags: (0x0001) ACC_PUBLIC
    Code:
      stack=2, locals=1, args_size=1
         0: new           #11                 // class shapeless/ops/record/Remove$$anon$22
         3: dup
         4: invokespecial #43                 // Method shapeless/ops/record/Remove$$anon$22."<init>":()V
         7: areturn
      LineNumberTable:
        line 511: 0
      LocalVariableTable:
        Start  Length  Slot  Name   Signature
            0       8     0  this   Lshapeless/ops/record/Remove$;
    Signature: #42                          // <K:Ljava/lang/Object;V:Ljava/lang/Object;T::Lshapeless/HList;>()Lshapeless/ops/record/Remove<Lshapeless/$colon$colon<TV;TT;>;TV;>;

  public <K extends java.lang.Object, V extends java.lang.Object, T extends shapeless.HList> shapeless.ops.record.Remove<shapeless.$colon$colon<V, T>, V> removeUnlabelledHead();
    descriptor: ()Lshapeless/ops/record/Remove;
    flags: (0x0001) ACC_PUBLIC
    Code:
      stack=2, locals=1, args_size=1
         0: new           #13                 // class shapeless/ops/record/Remove$$anon$23
         3: dup
         4: invokespecial #45                 // Method shapeless/ops/record/Remove$$anon$23."<init>":()V
         7: areturn
      LineNumberTable:
        line 519: 0
      LocalVariableTable:
        Start  Length  Slot  Name   Signature
            0       8     0  this   Lshapeless/ops/record/Remove$;
    Signature: #42                          // <K:Ljava/lang/Object;V:Ljava/lang/Object;T::Lshapeless/HList;>()Lshapeless/ops/record/Remove<Lshapeless/$colon$colon<TV;TT;>;TV;>;

  private java.lang.Object writeReplace();
    descriptor: ()Ljava/lang/Object;
    flags: (0x0002) ACC_PRIVATE
    Code:
      stack=3, locals=1, args_size=1
         0: new           #49                 // class scala/runtime/ModuleSerializationProxy
         3: dup
         4: ldc           #2                  // class shapeless/ops/record/Remove$
         6: invokespecial #52                 // Method scala/runtime/ModuleSerializationProxy."<init>":(Ljava/lang/Class;)V
         9: areturn
      LineNumberTable:
        line 507: 0
      LocalVariableTable:
        Start  Length  Slot  Name   Signature
            0      10     0  this   Lshapeless/ops/record/Remove$;

  private shapeless.ops.record.Remove$();
    descriptor: ()V
    flags: (0x0002) ACC_PRIVATE
    Code:
      stack=1, locals=1, args_size=1
         0: aload_0
         1: invokespecial #53                 // Method java/lang/Object."<init>":()V
         4: return
      LineNumberTable:
        line 507: 0
      LocalVariableTable:
        Start  Length  Slot  Name   Signature
            0       5     0  this   Lshapeless/ops/record/Remove$;
}
InnerClasses:
  public final #11;                       // class shapeless/ops/record/Remove$$anon$22
  public final #13;                       // class shapeless/ops/record/Remove$$anon$23
SourceFile: "records.scala"
  ScalaInlineInfo: length = 0x22 (unknown attribute)
   01 01 00 06 00 12 00 11 01 00 25 00 1C 01 00 1B
   00 1C 01 00 28 00 29 01 00 2C 00 29 01 00 2E 00
   2F 01
  Scala: length = 0x0 (unknown attribute)

