Classfile /Users/mw/Projects/slang-braindump/.jar/jar11/assemble/slang-braindump/assemble/content/shapeless/ops/record/Remove$$anon$23.class
  Last modified May 29, 2022; size 2114 bytes
  SHA-256 checksum e053606cccdbd75d8b19a6e017d3f0d8d0f49249730ca7312ece32920a563963
  Compiled from "records.scala"
public final class shapeless.ops.record.Remove$$anon$23 extends java.lang.Object implements shapeless.ops.record.Remove<shapeless.$colon$colon<V, T>, V>
  minor version: 0
  major version: 52
  flags: (0x0031) ACC_PUBLIC, ACC_FINAL, ACC_SUPER
  this_class: #2                          // shapeless/ops/record/Remove$$anon$23
  super_class: #5                         // java/lang/Object
  interfaces: 1, fields: 0, methods: 5, attributes: 6
Constant pool:
    #1 = Utf8               shapeless/ops/record/Remove$$anon$23
    #2 = Class              #1            // shapeless/ops/record/Remove$$anon$23
    #3 = Utf8               Ljava/lang/Object;Lshapeless/ops/record/Remove<Lshapeless/$colon$colon<TV;TT;>;TV;>;
    #4 = Utf8               java/lang/Object
    #5 = Class              #4            // java/lang/Object
    #6 = Utf8               shapeless/ops/record/Remove
    #7 = Class              #6            // shapeless/ops/record/Remove
    #8 = Utf8               records.scala
    #9 = Utf8               shapeless/ops/record/Remove$
   #10 = Class              #9            // shapeless/ops/record/Remove$
   #11 = Utf8               removeUnlabelledHead
   #12 = Utf8               ()Lshapeless/ops/record/Remove;
   #13 = NameAndType        #11:#12       // removeUnlabelledHead:()Lshapeless/ops/record/Remove;
   #14 = Utf8               shapeless/labelled$FieldBuilder
   #15 = Class              #14           // shapeless/labelled$FieldBuilder
   #16 = Utf8               shapeless/labelled
   #17 = Class              #16           // shapeless/labelled
   #18 = Utf8               FieldBuilder
   #19 = Utf8               apply
   #20 = Utf8               (Lshapeless/$colon$colon;)Lscala/Tuple2;
   #21 = Utf8               (Lshapeless/$colon$colon<TV;TT;>;)Lscala/Tuple2<TV;TT;>;
   #22 = Utf8               l
   #23 = Utf8               scala/Tuple2
   #24 = Class              #23           // scala/Tuple2
   #25 = Utf8               shapeless/$colon$colon
   #26 = Class              #25           // shapeless/$colon$colon
   #27 = Utf8               head
   #28 = Utf8               ()Ljava/lang/Object;
   #29 = NameAndType        #27:#28       // head:()Ljava/lang/Object;
   #30 = Methodref          #26.#29       // shapeless/$colon$colon.head:()Ljava/lang/Object;
   #31 = Utf8               tail
   #32 = Utf8               ()Lshapeless/HList;
   #33 = NameAndType        #31:#32       // tail:()Lshapeless/HList;
   #34 = Methodref          #26.#33       // shapeless/$colon$colon.tail:()Lshapeless/HList;
   #35 = Utf8               <init>
   #36 = Utf8               (Ljava/lang/Object;Ljava/lang/Object;)V
   #37 = NameAndType        #35:#36       // "<init>":(Ljava/lang/Object;Ljava/lang/Object;)V
   #38 = Methodref          #24.#37       // scala/Tuple2."<init>":(Ljava/lang/Object;Ljava/lang/Object;)V
   #39 = Utf8               this
   #40 = Utf8               Lshapeless/ops/record/Remove$$anon$23;
   #41 = Utf8               Lshapeless/$colon$colon;
   #42 = Utf8               reinsert
   #43 = Utf8               (Lscala/Tuple2;)Lshapeless/$colon$colon;
   #44 = Utf8               (Lscala/Tuple2<TV;TT;>;)Lshapeless/$colon$colon<TV;TT;>;
   #45 = Utf8               out
   #46 = Utf8               shapeless/labelled$
   #47 = Class              #46           // shapeless/labelled$
   #48 = Utf8               MODULE$
   #49 = Utf8               Lshapeless/labelled$;
   #50 = NameAndType        #48:#49       // MODULE$:Lshapeless/labelled$;
   #51 = Fieldref           #47.#50       // shapeless/labelled$.MODULE$:Lshapeless/labelled$;
   #52 = Utf8               field
   #53 = Utf8               ()Lshapeless/labelled$FieldBuilder;
   #54 = NameAndType        #52:#53       // field:()Lshapeless/labelled$FieldBuilder;
   #55 = Methodref          #47.#54       // shapeless/labelled$.field:()Lshapeless/labelled$FieldBuilder;
   #56 = Utf8               _1
   #57 = NameAndType        #56:#28       // _1:()Ljava/lang/Object;
   #58 = Methodref          #24.#57       // scala/Tuple2._1:()Ljava/lang/Object;
   #59 = Utf8               (Ljava/lang/Object;)Ljava/lang/Object;
   #60 = NameAndType        #19:#59       // apply:(Ljava/lang/Object;)Ljava/lang/Object;
   #61 = Methodref          #15.#60       // shapeless/labelled$FieldBuilder.apply:(Ljava/lang/Object;)Ljava/lang/Object;
   #62 = Utf8               shapeless/HList$
   #63 = Class              #62           // shapeless/HList$
   #64 = Utf8               Lshapeless/HList$;
   #65 = NameAndType        #48:#64       // MODULE$:Lshapeless/HList$;
   #66 = Fieldref           #63.#65       // shapeless/HList$.MODULE$:Lshapeless/HList$;
   #67 = Utf8               _2
   #68 = NameAndType        #67:#28       // _2:()Ljava/lang/Object;
   #69 = Methodref          #24.#68       // scala/Tuple2._2:()Ljava/lang/Object;
   #70 = Utf8               shapeless/HList
   #71 = Class              #70           // shapeless/HList
   #72 = Utf8               hlistOps
   #73 = Utf8               (Lshapeless/HList;)Lshapeless/syntax/HListOps;
   #74 = NameAndType        #72:#73       // hlistOps:(Lshapeless/HList;)Lshapeless/syntax/HListOps;
   #75 = Methodref          #63.#74       // shapeless/HList$.hlistOps:(Lshapeless/HList;)Lshapeless/syntax/HListOps;
   #76 = Utf8               shapeless/syntax/HListOps
   #77 = Class              #76           // shapeless/syntax/HListOps
   #78 = Utf8               $colon$colon
   #79 = Utf8               (Ljava/lang/Object;)Lshapeless/$colon$colon;
   #80 = NameAndType        #78:#79       // $colon$colon:(Ljava/lang/Object;)Lshapeless/$colon$colon;
   #81 = Methodref          #77.#80       // shapeless/syntax/HListOps.$colon$colon:(Ljava/lang/Object;)Lshapeless/$colon$colon;
   #82 = Utf8               Lscala/Tuple2;
   #83 = NameAndType        #42:#43       // reinsert:(Lscala/Tuple2;)Lshapeless/$colon$colon;
   #84 = Methodref          #2.#83        // shapeless/ops/record/Remove$$anon$23.reinsert:(Lscala/Tuple2;)Lshapeless/$colon$colon;
   #85 = Utf8               Ljava/lang/Object;
   #86 = Utf8               t
   #87 = NameAndType        #19:#20       // apply:(Lshapeless/$colon$colon;)Lscala/Tuple2;
   #88 = Methodref          #2.#87        // shapeless/ops/record/Remove$$anon$23.apply:(Lshapeless/$colon$colon;)Lscala/Tuple2;
   #89 = Utf8               ()V
   #90 = NameAndType        #35:#89       // "<init>":()V
   #91 = Methodref          #5.#90        // java/lang/Object."<init>":()V
   #92 = Utf8               Code
   #93 = Utf8               LineNumberTable
   #94 = Utf8               LocalVariableTable
   #95 = Utf8               Signature
   #96 = Utf8               MethodParameters
   #97 = Utf8               InnerClasses
   #98 = Utf8               EnclosingMethod
   #99 = Utf8               SourceFile
  #100 = Utf8               ScalaInlineInfo
  #101 = Utf8               Scala
{
  public scala.Tuple2<V, T> apply(shapeless.$colon$colon<V, T>);
    descriptor: (Lshapeless/$colon$colon;)Lscala/Tuple2;
    flags: (0x0001) ACC_PUBLIC
    Code:
      stack=4, locals=2, args_size=2
         0: new           #24                 // class scala/Tuple2
         3: dup
         4: aload_1
         5: invokevirtual #30                 // Method shapeless/$colon$colon.head:()Ljava/lang/Object;
         8: aload_1
         9: invokevirtual #34                 // Method shapeless/$colon$colon.tail:()Lshapeless/HList;
        12: invokespecial #38                 // Method scala/Tuple2."<init>":(Ljava/lang/Object;Ljava/lang/Object;)V
        15: areturn
      LineNumberTable:
        line 522: 0
      LocalVariableTable:
        Start  Length  Slot  Name   Signature
            0      16     0  this   Lshapeless/ops/record/Remove$$anon$23;
            0      16     1     l   Lshapeless/$colon$colon;
    Signature: #21                          // (Lshapeless/$colon$colon<TV;TT;>;)Lscala/Tuple2<TV;TT;>;
    MethodParameters:
      Name                           Flags
      l                              final

  public shapeless.$colon$colon<V, T> reinsert(scala.Tuple2<V, T>);
    descriptor: (Lscala/Tuple2;)Lshapeless/$colon$colon;
    flags: (0x0001) ACC_PUBLIC
    Code:
      stack=2, locals=3, args_size=2
         0: getstatic     #51                 // Field shapeless/labelled$.MODULE$:Lshapeless/labelled$;
         3: invokevirtual #55                 // Method shapeless/labelled$.field:()Lshapeless/labelled$FieldBuilder;
         6: aload_1
         7: invokevirtual #58                 // Method scala/Tuple2._1:()Ljava/lang/Object;
        10: invokevirtual #61                 // Method shapeless/labelled$FieldBuilder.apply:(Ljava/lang/Object;)Ljava/lang/Object;
        13: astore_2
        14: getstatic     #66                 // Field shapeless/HList$.MODULE$:Lshapeless/HList$;
        17: aload_1
        18: invokevirtual #69                 // Method scala/Tuple2._2:()Ljava/lang/Object;
        21: checkcast     #71                 // class shapeless/HList
        24: invokevirtual #75                 // Method shapeless/HList$.hlistOps:(Lshapeless/HList;)Lshapeless/syntax/HListOps;
        27: aload_2
        28: invokevirtual #81                 // Method shapeless/syntax/HListOps.$colon$colon:(Ljava/lang/Object;)Lshapeless/$colon$colon;
        31: areturn
      LineNumberTable:
        line 523: 0
      LocalVariableTable:
        Start  Length  Slot  Name   Signature
            0      32     0  this   Lshapeless/ops/record/Remove$$anon$23;
            0      32     1   out   Lscala/Tuple2;
    Signature: #44                          // (Lscala/Tuple2<TV;TT;>;)Lshapeless/$colon$colon<TV;TT;>;
    MethodParameters:
      Name                           Flags
      out                            final

  public java.lang.Object reinsert(java.lang.Object);
    descriptor: (Ljava/lang/Object;)Ljava/lang/Object;
    flags: (0x1041) ACC_PUBLIC, ACC_BRIDGE, ACC_SYNTHETIC
    Code:
      stack=2, locals=2, args_size=2
         0: aload_0
         1: aload_1
         2: checkcast     #24                 // class scala/Tuple2
         5: invokevirtual #84                 // Method reinsert:(Lscala/Tuple2;)Lshapeless/$colon$colon;
         8: areturn
      LineNumberTable:
        line 519: 0
      LocalVariableTable:
        Start  Length  Slot  Name   Signature
            0       9     0  this   Lshapeless/ops/record/Remove$$anon$23;
            0       9     1   out   Ljava/lang/Object;
    MethodParameters:
      Name                           Flags
      out                            final

  public java.lang.Object apply(java.lang.Object);
    descriptor: (Ljava/lang/Object;)Ljava/lang/Object;
    flags: (0x1041) ACC_PUBLIC, ACC_BRIDGE, ACC_SYNTHETIC
    Code:
      stack=2, locals=2, args_size=2
         0: aload_0
         1: aload_1
         2: checkcast     #26                 // class shapeless/$colon$colon
         5: invokevirtual #88                 // Method apply:(Lshapeless/$colon$colon;)Lscala/Tuple2;
         8: areturn
      LineNumberTable:
        line 519: 0
      LocalVariableTable:
        Start  Length  Slot  Name   Signature
            0       9     0  this   Lshapeless/ops/record/Remove$$anon$23;
            0       9     1     t   Ljava/lang/Object;
    MethodParameters:
      Name                           Flags
      t                              final

  public shapeless.ops.record.Remove$$anon$23();
    descriptor: ()V
    flags: (0x0001) ACC_PUBLIC
    Code:
      stack=1, locals=1, args_size=1
         0: aload_0
         1: invokespecial #91                 // Method java/lang/Object."<init>":()V
         4: return
      LineNumberTable:
        line 519: 0
      LocalVariableTable:
        Start  Length  Slot  Name   Signature
            0       5     0  this   Lshapeless/ops/record/Remove$$anon$23;
}
InnerClasses:
  public static #18= #15 of #17;          // FieldBuilder=class shapeless/labelled$FieldBuilder of class shapeless/labelled
  public final #2;                        // class shapeless/ops/record/Remove$$anon$23
EnclosingMethod: #10.#13                // shapeless.ops.record.Remove$.removeUnlabelledHead
Signature: #3                           // Ljava/lang/Object;Lshapeless/ops/record/Remove<Lshapeless/$colon$colon<TV;TT;>;TV;>;
SourceFile: "records.scala"
  ScalaInlineInfo: length = 0x1D (unknown attribute)
   01 01 00 05 00 23 00 59 01 00 13 00 3B 01 00 13
   00 14 01 00 2A 00 3B 01 00 2A 00 2B 01
  Scala: length = 0x0 (unknown attribute)

