Classfile /Users/mw/Projects/slang-braindump/.jar/jar11/assemble/slang-braindump/assemble/content/shapeless/ops/record/UnsafeUpdater.class
  Last modified May 29, 2022; size 1535 bytes
  SHA-256 checksum 576cc6b052e81f6bb12cf38a333e433ed26963f5ef599f2c9f68c1163bc6bddf
  Compiled from "records.scala"
public class shapeless.ops.record.UnsafeUpdater extends java.lang.Object implements shapeless.ops.record.Updater<shapeless.HList, java.lang.Object>
  minor version: 0
  major version: 52
  flags: (0x0021) ACC_PUBLIC, ACC_SUPER
  this_class: #2                          // shapeless/ops/record/UnsafeUpdater
  super_class: #5                         // java/lang/Object
  interfaces: 1, fields: 1, methods: 3, attributes: 5
Constant pool:
   #1 = Utf8               shapeless/ops/record/UnsafeUpdater
   #2 = Class              #1             // shapeless/ops/record/UnsafeUpdater
   #3 = Utf8               Ljava/lang/Object;Lshapeless/ops/record/Updater<Lshapeless/HList;Ljava/lang/Object;>;
   #4 = Utf8               java/lang/Object
   #5 = Class              #4             // java/lang/Object
   #6 = Utf8               shapeless/ops/record/Updater
   #7 = Class              #6             // shapeless/ops/record/Updater
   #8 = Utf8               records.scala
   #9 = Utf8               Lscala/reflect/ScalaSignature;
  #10 = Utf8               bytes
  #11 = Utf8               \u0006\u000592A!\u0002\u0004\u0001\u001b!Aq\u0004\u0001B\u0001B\u0003%\u0001\u0005C\u0003$\u0001\u0011\u0005A%\u0002\u0003(\u0001\u0001A\u0002\"\u0002\u0015\u0001\t\u0003I#!D+og\u00064W-\u00169eCR,\'O\u0003\u0002\b\u0011\u00051!/Z2pe\u0012T!!\u0003\u0006\u0002\u0007=\u00048OC\u0001\f\u0003%\u0019\b.\u00199fY\u0016\u001c8o\u0001\u0001\u0014\u0007\u0001qA\u0003\u0005\u0002\u0010%5\t\u0001CC\u0001\u0012\u0003\u0015\u00198-\u00197b\u0013\t\u0019\u0002C\u0001\u0004B]f\u0014VM\u001a\t\u0005+YAB$D\u0001\u0007\u0013\t9bAA\u0004Va\u0012\fG/\u001a:\u0011\u0005eQR\"\u0001\u0006\n\u0005mQ!!\u0002%MSN$\bCA\b\u001e\u0013\tq\u0002CA\u0002B]f\f\u0011!\u001b\t\u0003\u001f\u0005J!A\t\t\u0003\u0007%sG/\u0001\u0004=S:LGO\u0010\u000b\u0003K\u0019\u0002\"!\u0006\u0001\t\u000b}\u0011\u0001\u0019\u0001\u0011\u0003\u0007=+H/A\u0003baBd\u0017\u0010F\u0002\u0019U1BQa\u000b\u0003A\u0002a\t\u0011\u0001\u001c\u0005\u0006[\u0011\u0001\r\u0001H\u0001\u0002M\u0002
  #12 = Utf8               i
  #13 = Utf8               I
  #14 = Utf8               apply
  #15 = Utf8               (Lshapeless/HList;Ljava/lang/Object;)Lshapeless/HList;
  #16 = Utf8               l
  #17 = Utf8               f
  #18 = Utf8               shapeless/HList$
  #19 = Class              #18            // shapeless/HList$
  #20 = Utf8               MODULE$
  #21 = Utf8               Lshapeless/HList$;
  #22 = NameAndType        #20:#21        // MODULE$:Lshapeless/HList$;
  #23 = Fieldref           #19.#22        // shapeless/HList$.MODULE$:Lshapeless/HList$;
  #24 = NameAndType        #12:#13        // i:I
  #25 = Fieldref           #2.#24         // shapeless/ops/record/UnsafeUpdater.i:I
  #26 = Utf8               unsafeUpdateAppend
  #27 = Utf8               (Lshapeless/HList;ILjava/lang/Object;)Lshapeless/HList;
  #28 = NameAndType        #26:#27        // unsafeUpdateAppend:(Lshapeless/HList;ILjava/lang/Object;)Lshapeless/HList;
  #29 = Methodref          #19.#28        // shapeless/HList$.unsafeUpdateAppend:(Lshapeless/HList;ILjava/lang/Object;)Lshapeless/HList;
  #30 = Utf8               this
  #31 = Utf8               Lshapeless/ops/record/UnsafeUpdater;
  #32 = Utf8               Lshapeless/HList;
  #33 = Utf8               Ljava/lang/Object;
  #34 = Utf8               (Ljava/lang/Object;Ljava/lang/Object;)Ljava/lang/Object;
  #35 = Utf8               t
  #36 = Utf8               u
  #37 = Utf8               shapeless/HList
  #38 = Class              #37            // shapeless/HList
  #39 = NameAndType        #14:#15        // apply:(Lshapeless/HList;Ljava/lang/Object;)Lshapeless/HList;
  #40 = Methodref          #2.#39         // shapeless/ops/record/UnsafeUpdater.apply:(Lshapeless/HList;Ljava/lang/Object;)Lshapeless/HList;
  #41 = Utf8               <init>
  #42 = Utf8               (I)V
  #43 = Utf8               ()V
  #44 = NameAndType        #41:#43        // "<init>":()V
  #45 = Methodref          #5.#44         // java/lang/Object."<init>":()V
  #46 = Utf8               Code
  #47 = Utf8               LineNumberTable
  #48 = Utf8               LocalVariableTable
  #49 = Utf8               MethodParameters
  #50 = Utf8               Signature
  #51 = Utf8               SourceFile
  #52 = Utf8               RuntimeVisibleAnnotations
  #53 = Utf8               ScalaInlineInfo
  #54 = Utf8               ScalaSig
{
  private final int i;
    descriptor: I
    flags: (0x0012) ACC_PRIVATE, ACC_FINAL

  public shapeless.HList apply(shapeless.HList, java.lang.Object);
    descriptor: (Lshapeless/HList;Ljava/lang/Object;)Lshapeless/HList;
    flags: (0x0001) ACC_PUBLIC
    Code:
      stack=4, locals=3, args_size=3
         0: getstatic     #23                 // Field shapeless/HList$.MODULE$:Lshapeless/HList$;
         3: aload_1
         4: aload_0
         5: getfield      #25                 // Field i:I
         8: aload_2
         9: invokevirtual #29                 // Method shapeless/HList$.unsafeUpdateAppend:(Lshapeless/HList;ILjava/lang/Object;)Lshapeless/HList;
        12: areturn
      LineNumberTable:
        line 125: 0
      LocalVariableTable:
        Start  Length  Slot  Name   Signature
            0      13     0  this   Lshapeless/ops/record/UnsafeUpdater;
            0      13     1     l   Lshapeless/HList;
            0      13     2     f   Ljava/lang/Object;
    MethodParameters:
      Name                           Flags
      l                              final
      f                              final

  public java.lang.Object apply(java.lang.Object, java.lang.Object);
    descriptor: (Ljava/lang/Object;Ljava/lang/Object;)Ljava/lang/Object;
    flags: (0x1041) ACC_PUBLIC, ACC_BRIDGE, ACC_SYNTHETIC
    Code:
      stack=3, locals=3, args_size=3
         0: aload_0
         1: aload_1
         2: checkcast     #38                 // class shapeless/HList
         5: aload_2
         6: invokevirtual #40                 // Method apply:(Lshapeless/HList;Ljava/lang/Object;)Lshapeless/HList;
         9: areturn
      LineNumberTable:
        line 123: 0
      LocalVariableTable:
        Start  Length  Slot  Name   Signature
            0      10     0  this   Lshapeless/ops/record/UnsafeUpdater;
            0      10     1     t   Ljava/lang/Object;
            0      10     2     u   Ljava/lang/Object;
    MethodParameters:
      Name                           Flags
      t                              final
      u                              final

  public shapeless.ops.record.UnsafeUpdater(int);
    descriptor: (I)V
    flags: (0x0001) ACC_PUBLIC
    Code:
      stack=2, locals=2, args_size=2
         0: aload_0
         1: iload_1
         2: putfield      #25                 // Field i:I
         5: aload_0
         6: invokespecial #45                 // Method java/lang/Object."<init>":()V
         9: return
      LineNumberTable:
        line 123: 0
      LocalVariableTable:
        Start  Length  Slot  Name   Signature
            0      10     0  this   Lshapeless/ops/record/UnsafeUpdater;
            0      10     1     i   I
    MethodParameters:
      Name                           Flags
      i                              final
}
Signature: #3                           // Ljava/lang/Object;Lshapeless/ops/record/Updater<Lshapeless/HList;Ljava/lang/Object;>;
SourceFile: "records.scala"
RuntimeVisibleAnnotations:
  0: #9(#10=s#11)
    scala.reflect.ScalaSignature(
      bytes="\u0006\u000592A!\u0002\u0004\u0001\u001b!Aq\u0004\u0001B\u0001B\u0003%\u0001\u0005C\u0003$\u0001\u0011\u0005A%\u0002\u0003(\u0001\u0001A\u0002\"\u0002\u0015\u0001\t\u0003I#!D+og\u00064W-\u00169eCR,\'O\u0003\u0002\b\u0011\u00051!/Z2pe\u0012T!!\u0003\u0006\u0002\u0007=\u00048OC\u0001\f\u0003%\u0019\b.\u00199fY\u0016\u001c8o\u0001\u0001\u0014\u0007\u0001qA\u0003\u0005\u0002\u0010%5\t\u0001CC\u0001\u0012\u0003\u0015\u00198-\u00197b\u0013\t\u0019\u0002C\u0001\u0004B]f\u0014VM\u001a\t\u0005+YAB$D\u0001\u0007\u0013\t9bAA\u0004Va\u0012\fG/\u001a:\u0011\u0005eQR\"\u0001\u0006\n\u0005mQ!!\u0002%MSN$\bCA\b\u001e\u0013\tq\u0002CA\u0002B]f\f\u0011!\u001b\t\u0003\u001f\u0005J!A\t\t\u0003\u0007%sG/\u0001\u0004=S:LGO\u0010\u000b\u0003K\u0019\u0002\"!\u0006\u0001\t\u000b}\u0011\u0001\u0019\u0001\u0011\u0003\u0007=+H/A\u0003baBd\u0017\u0010F\u0002\u0019U1BQa\u000b\u0003A\u0002a\t\u0011\u0001\u001c\u0005\u0006[\u0011\u0001\r\u0001H\u0001\u0002M\u0002"
    )
  ScalaInlineInfo: length = 0x13 (unknown attribute)
   01 00 00 03 00 29 00 2A 00 00 0E 00 22 00 00 0E
   00 0F 00
  ScalaSig: length = 0x3 (unknown attribute)
   05 02 00
