Classfile /Users/mw/Projects/slang-braindump/.jar/jar11/assemble/slang-braindump/assemble/content/shapeless/ops/record/UnzipFields$$anon$37.class
  Last modified May 29, 2022; size 2091 bytes
  SHA-256 checksum e583cbc2c8aedc3b0e58a36235f100acf7eb6c19c01c52f57f1d2d7978f381b2
  Compiled from "records.scala"
public final class shapeless.ops.record.UnzipFields$$anon$37 extends java.lang.Object implements shapeless.ops.record.UnzipFields<shapeless.$colon$colon<V, T>>
  minor version: 0
  major version: 52
  flags: (0x0031) ACC_PUBLIC, ACC_FINAL, ACC_SUPER
  this_class: #2                          // shapeless/ops/record/UnzipFields$$anon$37
  super_class: #5                         // java/lang/Object
  interfaces: 1, fields: 2, methods: 5, attributes: 6
Constant pool:
   #1 = Utf8               shapeless/ops/record/UnzipFields$$anon$37
   #2 = Class              #1             // shapeless/ops/record/UnzipFields$$anon$37
   #3 = Utf8               Ljava/lang/Object;Lshapeless/ops/record/UnzipFields<Lshapeless/$colon$colon<TV;TT;>;>;
   #4 = Utf8               java/lang/Object
   #5 = Class              #4             // java/lang/Object
   #6 = Utf8               shapeless/ops/record/UnzipFields
   #7 = Class              #6             // shapeless/ops/record/UnzipFields
   #8 = Utf8               records.scala
   #9 = Utf8               shapeless/ops/record/UnzipFields$
  #10 = Class              #9             // shapeless/ops/record/UnzipFields$
  #11 = Utf8               hconsUnzipFields
  #12 = Utf8               (Lshapeless/Witness;Lshapeless/ops/record/UnzipFields;)Lshapeless/ops/record/UnzipFields;
  #13 = NameAndType        #11:#12        // hconsUnzipFields:(Lshapeless/Witness;Lshapeless/ops/record/UnzipFields;)Lshapeless/ops/record/UnzipFields;
  #14 = Utf8               key$2
  #15 = Utf8               Lshapeless/Witness;
  #16 = Utf8               tailUF$1
  #17 = Utf8               Lshapeless/ops/record/UnzipFields;
  #18 = Utf8               keys
  #19 = Utf8               ()Lshapeless/$colon$colon;
  #20 = Utf8               ()Lshapeless/$colon$colon<TK;Lshapeless/HList;>;
  #21 = NameAndType        #14:#15        // key$2:Lshapeless/Witness;
  #22 = Fieldref           #2.#21         // shapeless/ops/record/UnzipFields$$anon$37.key$2:Lshapeless/Witness;
  #23 = Utf8               shapeless/Witness
  #24 = Class              #23            // shapeless/Witness
  #25 = Utf8               value
  #26 = Utf8               ()Ljava/lang/Object;
  #27 = NameAndType        #25:#26        // value:()Ljava/lang/Object;
  #28 = InterfaceMethodref #24.#27        // shapeless/Witness.value:()Ljava/lang/Object;
  #29 = Utf8               shapeless/HList$
  #30 = Class              #29            // shapeless/HList$
  #31 = Utf8               MODULE$
  #32 = Utf8               Lshapeless/HList$;
  #33 = NameAndType        #31:#32        // MODULE$:Lshapeless/HList$;
  #34 = Fieldref           #30.#33        // shapeless/HList$.MODULE$:Lshapeless/HList$;
  #35 = NameAndType        #16:#17        // tailUF$1:Lshapeless/ops/record/UnzipFields;
  #36 = Fieldref           #2.#35         // shapeless/ops/record/UnzipFields$$anon$37.tailUF$1:Lshapeless/ops/record/UnzipFields;
  #37 = Utf8               ()Lshapeless/HList;
  #38 = NameAndType        #18:#37        // keys:()Lshapeless/HList;
  #39 = InterfaceMethodref #7.#38         // shapeless/ops/record/UnzipFields.keys:()Lshapeless/HList;
  #40 = Utf8               hlistOps
  #41 = Utf8               (Lshapeless/HList;)Lshapeless/syntax/HListOps;
  #42 = NameAndType        #40:#41        // hlistOps:(Lshapeless/HList;)Lshapeless/syntax/HListOps;
  #43 = Methodref          #30.#42        // shapeless/HList$.hlistOps:(Lshapeless/HList;)Lshapeless/syntax/HListOps;
  #44 = Utf8               shapeless/syntax/HListOps
  #45 = Class              #44            // shapeless/syntax/HListOps
  #46 = Utf8               $colon$colon
  #47 = Utf8               (Ljava/lang/Object;)Lshapeless/$colon$colon;
  #48 = NameAndType        #46:#47        // $colon$colon:(Ljava/lang/Object;)Lshapeless/$colon$colon;
  #49 = Methodref          #45.#48        // shapeless/syntax/HListOps.$colon$colon:(Ljava/lang/Object;)Lshapeless/$colon$colon;
  #50 = Utf8               this
  #51 = Utf8               Lshapeless/ops/record/UnzipFields$$anon$37;
  #52 = Utf8               values
  #53 = Utf8               (Lshapeless/$colon$colon;)Lshapeless/$colon$colon;
  #54 = Utf8               (Lshapeless/$colon$colon<TV;TT;>;)Lshapeless/$colon$colon<TV;Lshapeless/HList;>;
  #55 = Utf8               l
  #56 = Utf8               shapeless/$colon$colon
  #57 = Class              #56            // shapeless/$colon$colon
  #58 = Utf8               head
  #59 = NameAndType        #58:#26        // head:()Ljava/lang/Object;
  #60 = Methodref          #57.#59        // shapeless/$colon$colon.head:()Ljava/lang/Object;
  #61 = Utf8               tail
  #62 = NameAndType        #61:#37        // tail:()Lshapeless/HList;
  #63 = Methodref          #57.#62        // shapeless/$colon$colon.tail:()Lshapeless/HList;
  #64 = Utf8               (Lshapeless/HList;)Lshapeless/HList;
  #65 = NameAndType        #52:#64        // values:(Lshapeless/HList;)Lshapeless/HList;
  #66 = InterfaceMethodref #7.#65         // shapeless/ops/record/UnzipFields.values:(Lshapeless/HList;)Lshapeless/HList;
  #67 = Utf8               Lshapeless/$colon$colon;
  #68 = NameAndType        #52:#53        // values:(Lshapeless/$colon$colon;)Lshapeless/$colon$colon;
  #69 = Methodref          #2.#68         // shapeless/ops/record/UnzipFields$$anon$37.values:(Lshapeless/$colon$colon;)Lshapeless/$colon$colon;
  #70 = Utf8               Lshapeless/HList;
  #71 = NameAndType        #18:#19        // keys:()Lshapeless/$colon$colon;
  #72 = Methodref          #2.#71         // shapeless/ops/record/UnzipFields$$anon$37.keys:()Lshapeless/$colon$colon;
  #73 = Utf8               <init>
  #74 = Utf8               (Lshapeless/Witness;Lshapeless/ops/record/UnzipFields;)V
  #75 = Utf8               ()V
  #76 = NameAndType        #73:#75        // "<init>":()V
  #77 = Methodref          #5.#76         // java/lang/Object."<init>":()V
  #78 = Utf8               Code
  #79 = Utf8               LineNumberTable
  #80 = Utf8               LocalVariableTable
  #81 = Utf8               Signature
  #82 = Utf8               MethodParameters
  #83 = Utf8               InnerClasses
  #84 = Utf8               EnclosingMethod
  #85 = Utf8               SourceFile
  #86 = Utf8               ScalaInlineInfo
  #87 = Utf8               Scala
{
  private final shapeless.Witness key$2;
    descriptor: Lshapeless/Witness;
    flags: (0x0012) ACC_PRIVATE, ACC_FINAL

  private final shapeless.ops.record.UnzipFields tailUF$1;
    descriptor: Lshapeless/ops/record/UnzipFields;
    flags: (0x0012) ACC_PRIVATE, ACC_FINAL

  public shapeless.$colon$colon<K, shapeless.HList> keys();
    descriptor: ()Lshapeless/$colon$colon;
    flags: (0x0001) ACC_PUBLIC
    Code:
      stack=2, locals=2, args_size=1
         0: aload_0
         1: getfield      #22                 // Field key$2:Lshapeless/Witness;
         4: invokeinterface #28,  1           // InterfaceMethod shapeless/Witness.value:()Ljava/lang/Object;
         9: astore_1
        10: getstatic     #34                 // Field shapeless/HList$.MODULE$:Lshapeless/HList$;
        13: aload_0
        14: getfield      #36                 // Field tailUF$1:Lshapeless/ops/record/UnzipFields;
        17: invokeinterface #39,  1           // InterfaceMethod shapeless/ops/record/UnzipFields.keys:()Lshapeless/HList;
        22: invokevirtual #43                 // Method shapeless/HList$.hlistOps:(Lshapeless/HList;)Lshapeless/syntax/HListOps;
        25: aload_1
        26: invokevirtual #49                 // Method shapeless/syntax/HListOps.$colon$colon:(Ljava/lang/Object;)Lshapeless/$colon$colon;
        29: areturn
      LineNumberTable:
        line 762: 0
      LocalVariableTable:
        Start  Length  Slot  Name   Signature
            0      30     0  this   Lshapeless/ops/record/UnzipFields$$anon$37;
    Signature: #20                          // ()Lshapeless/$colon$colon<TK;Lshapeless/HList;>;

  public shapeless.$colon$colon<V, shapeless.HList> values(shapeless.$colon$colon<V, T>);
    descriptor: (Lshapeless/$colon$colon;)Lshapeless/$colon$colon;
    flags: (0x0001) ACC_PUBLIC
    Code:
      stack=3, locals=3, args_size=2
         0: aload_1
         1: invokevirtual #60                 // Method shapeless/$colon$colon.head:()Ljava/lang/Object;
         4: astore_2
         5: getstatic     #34                 // Field shapeless/HList$.MODULE$:Lshapeless/HList$;
         8: aload_0
         9: getfield      #36                 // Field tailUF$1:Lshapeless/ops/record/UnzipFields;
        12: aload_1
        13: invokevirtual #63                 // Method shapeless/$colon$colon.tail:()Lshapeless/HList;
        16: invokeinterface #66,  2           // InterfaceMethod shapeless/ops/record/UnzipFields.values:(Lshapeless/HList;)Lshapeless/HList;
        21: invokevirtual #43                 // Method shapeless/HList$.hlistOps:(Lshapeless/HList;)Lshapeless/syntax/HListOps;
        24: aload_2
        25: invokevirtual #49                 // Method shapeless/syntax/HListOps.$colon$colon:(Ljava/lang/Object;)Lshapeless/$colon$colon;
        28: areturn
      LineNumberTable:
        line 763: 0
      LocalVariableTable:
        Start  Length  Slot  Name   Signature
            0      29     0  this   Lshapeless/ops/record/UnzipFields$$anon$37;
            0      29     1     l   Lshapeless/$colon$colon;
    Signature: #54                          // (Lshapeless/$colon$colon<TV;TT;>;)Lshapeless/$colon$colon<TV;Lshapeless/HList;>;
    MethodParameters:
      Name                           Flags
      l                              final

  public shapeless.HList values(shapeless.HList);
    descriptor: (Lshapeless/HList;)Lshapeless/HList;
    flags: (0x1041) ACC_PUBLIC, ACC_BRIDGE, ACC_SYNTHETIC
    Code:
      stack=2, locals=2, args_size=2
         0: aload_0
         1: aload_1
         2: checkcast     #57                 // class shapeless/$colon$colon
         5: invokevirtual #69                 // Method values:(Lshapeless/$colon$colon;)Lshapeless/$colon$colon;
         8: areturn
      LineNumberTable:
        line 758: 0
      LocalVariableTable:
        Start  Length  Slot  Name   Signature
            0       9     0  this   Lshapeless/ops/record/UnzipFields$$anon$37;
            0       9     1     l   Lshapeless/HList;
    MethodParameters:
      Name                           Flags
      l                              final

  public shapeless.HList keys();
    descriptor: ()Lshapeless/HList;
    flags: (0x1041) ACC_PUBLIC, ACC_BRIDGE, ACC_SYNTHETIC
    Code:
      stack=1, locals=1, args_size=1
         0: aload_0
         1: invokevirtual #72                 // Method keys:()Lshapeless/$colon$colon;
         4: areturn
      LineNumberTable:
        line 758: 0
      LocalVariableTable:
        Start  Length  Slot  Name   Signature
            0       5     0  this   Lshapeless/ops/record/UnzipFields$$anon$37;

  public shapeless.ops.record.UnzipFields$$anon$37(shapeless.Witness, shapeless.ops.record.UnzipFields);
    descriptor: (Lshapeless/Witness;Lshapeless/ops/record/UnzipFields;)V
    flags: (0x0001) ACC_PUBLIC
    Code:
      stack=2, locals=3, args_size=3
         0: aload_0
         1: aload_1
         2: putfield      #22                 // Field key$2:Lshapeless/Witness;
         5: aload_0
         6: aload_2
         7: putfield      #36                 // Field tailUF$1:Lshapeless/ops/record/UnzipFields;
        10: aload_0
        11: invokespecial #77                 // Method java/lang/Object."<init>":()V
        14: return
      LineNumberTable:
        line 755: 0
        line 756: 5
        line 758: 10
      LocalVariableTable:
        Start  Length  Slot  Name   Signature
            0      15     0  this   Lshapeless/ops/record/UnzipFields$$anon$37;
            0      15     1 key$2   Lshapeless/Witness;
            0      15     2 tailUF$1   Lshapeless/ops/record/UnzipFields;
    MethodParameters:
      Name                           Flags
      key$2                          final
      tailUF$1                       final
}
InnerClasses:
  public final #2;                        // class shapeless/ops/record/UnzipFields$$anon$37
EnclosingMethod: #10.#13                // shapeless.ops.record.UnzipFields$.hconsUnzipFields
Signature: #3                           // Ljava/lang/Object;Lshapeless/ops/record/UnzipFields<Lshapeless/$colon$colon<TV;TT;>;>;
SourceFile: "records.scala"
  ScalaInlineInfo: length = 0x1D (unknown attribute)
   01 01 00 05 00 49 00 4A 01 00 12 00 13 01 00 12
   00 25 01 00 34 00 35 01 00 34 00 40 01
  Scala: length = 0x0 (unknown attribute)

