Classfile /Users/mw/Projects/slang-braindump/.jar/jar11/assemble/slang-braindump/assemble/content/shapeless/ops/record/UnzipFields.class
  Last modified May 29, 2022; size 2597 bytes
  SHA-256 checksum 387969c2713b4690146dfd148bcd3ca436de79621fe6d6f31033cbdfd60f8b86
  Compiled from "records.scala"
public interface shapeless.ops.record.UnzipFields<L extends shapeless.HList> extends java.io.Serializable
  minor version: 0
  major version: 52
  flags: (0x0601) ACC_PUBLIC, ACC_INTERFACE, ACC_ABSTRACT
  this_class: #2                          // shapeless/ops/record/UnzipFields
  super_class: #5                         // java/lang/Object
  interfaces: 1, fields: 0, methods: 5, attributes: 5
Constant pool:
   #1 = Utf8               shapeless/ops/record/UnzipFields
   #2 = Class              #1             // shapeless/ops/record/UnzipFields
   #3 = Utf8               <L::Lshapeless/HList;>Ljava/lang/Object;Ljava/io/Serializable;
   #4 = Utf8               java/lang/Object
   #5 = Class              #4             // java/lang/Object
   #6 = Utf8               java/io/Serializable
   #7 = Class              #6             // java/io/Serializable
   #8 = Utf8               records.scala
   #9 = Utf8               Lscala/reflect/ScalaSignature;
  #10 = Utf8               bytes
  #11 = Utf8               \u0006\u0005\u0005=caB\u0007\u000f!\u0003\r\n!\u0006\u0003\u0006S\u0001\u0011\tA\u000b\u0003\u0006e\u0001\u0011\tA\u000b\u0005\u0006g\u00011\t\u0001\u000e\u0005\u0006o\u00011\t\u0001O\u0004\u0006\u0001:A\t!\u0011\u0004\u0006\u001b9A\ta\u0011\u0005\u0006\u0017\u001a!\t\u0001\u0014\u0005\u0006\u001b\u001a!\tAT\u0003\u0005%\u001a\u00011\u000bC\u0003k\r\u0011\r1\u000eC\u0003u\r\u0011\rQ\u000fC\u0005\u0002@\u0019\t\t\u0011\"\u0003\u0002B\tYQK\u001c>ja\u001aKW\r\u001c3t\u0015\ty\u0001#\u0001\u0004sK\u000e|\'\u000f\u001a\u0006\u0003#I\t1a\u001c9t\u0015\u0005\u0019\u0012!C:iCB,G.Z:t\u0007\u0001)\"A\u0006 \u0014\u0007\u00019R\u0004\u0005\u0002\u001975\t\u0011DC\u0001\u001b\u0003\u0015\u00198-\u00197b\u0013\ta\u0012D\u0001\u0004B]f\u0014VM\u001a\t\u0003=\u0019r!a\b\u0013\u000f\u0005\u0001\u001aS\"A\u0011\u000b\u0005\t\"\u0012A\u0002\u001fs_>$h(C\u0001\u001b\u0013\t)\u0013$A\u0004qC\u000e\\\u0017mZ3\n\u0005\u001dB#\u0001D*fe&\fG.\u001b>bE2,\'BA\u0013\u001a\u0005\u0011YU-_:\u0012\u0005-r\u0003C\u0001\r-\u0013\ti\u0013DA\u0004O_RD\u0017N\\4\u0011\u0005=\u0002T\"\u0001\n\n\u0005E\u0012\"!\u0002%MSN$(A\u0002,bYV,7/\u0001\u0003lKf\u001cH#A\u001b\u0011\u0005Y\nQ\"\u0001\u0001\u0002\rY\fG.^3t)\tI$\b\u0005\u00027\u0005!)1\b\u0002a\u0001y\u0005\tA\u000e\u0005\u0002>}1\u0001A!B \u0001\u0005\u0004Q#!\u0001\'\u0002\u0017Us\'0\u001b9GS\u0016dGm\u001d\t\u0003\u0005\u001ai\u0011AD\n\u0004\r]!\u0005CA#K\u001b\u00051%BA$I\u0003\tIwNC\u0001J\u0003\u0011Q\u0017M^1\n\u0005\u001d2\u0015A\u0002\u001fj]&$h\bF\u0001B\u0003\u0015\t\u0007\u000f\u001d7z+\ty5\r\u0006\u0002QMB)\u0011+\u00032eS6\taAA\u0002Bkb,B\u0001V-]AJ\u0011Qk\u0016\u0004\u0005-\u001a\u0001AK\u0001\u0007=e\u00164\u0017N\\3nK:$h\bE\u0002C\u0001a\u0003\"!P-\u0005\u000b}J!\u0019\u0001\u0016\u0006\t%*\u0006e\u0017\t\u0003{q#Q!X\u0005C\u0002)\u0012\u0011aS\u0003\u0005eU\u0003s\f\u0005\u0002>A\u0012)\u0011-\u0003b\u0001U\t\ta\u000b\u0005\u0002>G\u0012)q\b\u0003b\u0001UA\u0011Q-\u0001\b\u0003{\u0019DQa\u001a\u0005A\u0004!\f!!\u001e4\u0011\u0007\t\u0003!\r\u0005\u0002f\u0005\u0005y\u0001N\\5m+:T\u0018\u000e\u001d$jK2$7/\u0006\u0002m_V\tQ\u000eE\u0003R\u00139\fh\u000e\u0005\u0002>_\u0012)qH\u0003b\u0001aF\u00111&\u001d\t\u0003_IL!a\u001d\n\u0003\t!s\u0015\u000e\\\u0001\u0011Q\u000e|gn]+ou&\u0004h)[3mIN,rA^A\u0006\u0003/\tY\u0002F\u0003x\u0003_\t)\u0003E\u0004R\u0013a\fy\"a\u000b\u0011\u000b=J80!\u0007\n\u0005i\u0014\"\u0001\u0004\u0013d_2|g\u000eJ2pY>t\u0007c\u0002?\u0002\u0004\u0005%\u0011Q\u0003\b\u0003{~t!\u0001\t@\n\u0003MI1!!\u0001\u0013\u0003!a\u0017MY3mY\u0016$\u0017\u0002BA\u0003\u0003\u000f\u0011\u0011BR5fY\u0012$\u0016\u0010]3\u000b\u0007\u0005\u0005!\u0003E\u0002>\u0003\u0017!a!X\u0006C\u0002\u00055\u0011cA\u0016\u0002\u0010A\u0019\u0001$!\u0005\n\u0007\u0005M\u0011DA\u0002B]f\u00042!PA\f\t\u0019\t7B1\u0001\u0002\u000eA\u0019Q(a\u0007\u0005\r\u0005u1B1\u0001+\u0005\u0005!\u0006CB\u0018z\u0003\u0013\t\t\u0003E\u0002\u0002$\u0005q1!PA\u0013\u0011\u001d\t9c\u0003a\u0002\u0003S\ta\u0001^1jYV3\u0005\u0003\u0002\"\u0001\u00033\u0001baL=\u0002\u0016\u00055\u0002cAA\u0012\u0005!9\u0011\u0011G\u0006A\u0004\u0005M\u0012aA6fsB1\u0011QGA\u001e\u0003\u0013q1aLA\u001c\u0013\r\tIDE\u0001\b/&$h.Z:t\u0013\r\u0011\u0016Q\b\u0006\u0004\u0003s\u0011\u0012\u0001D<sSR,\'+\u001a9mC\u000e,GCAA\"!\u0011\t)%a\u0013\u000e\u0005\u0005\u001d#bAA%\u0011\u0006!A.\u00198h\u0013\u0011\ti%a\u0012\u0003\r=\u0013\'.Z2u\u0001
  #12 = Utf8               hconsUnzipFields
  #13 = Utf8               (Lshapeless/Witness;Lshapeless/ops/record/UnzipFields;)Lshapeless/ops/record/UnzipFields;
  #14 = Utf8               <K:Ljava/lang/Object;V:Ljava/lang/Object;T::Lshapeless/HList;>(Lshapeless/Witness;Lshapeless/ops/record/UnzipFields<TT;>;)Lshapeless/ops/record/UnzipFields<Lshapeless/$colon$colon<TV;TT;>;>;
  #15 = Utf8               key
  #16 = Utf8               tailUF
  #17 = Utf8               shapeless/ops/record/UnzipFields$
  #18 = Class              #17            // shapeless/ops/record/UnzipFields$
  #19 = Utf8               MODULE$
  #20 = Utf8               Lshapeless/ops/record/UnzipFields$;
  #21 = NameAndType        #19:#20        // MODULE$:Lshapeless/ops/record/UnzipFields$;
  #22 = Fieldref           #18.#21        // shapeless/ops/record/UnzipFields$.MODULE$:Lshapeless/ops/record/UnzipFields$;
  #23 = NameAndType        #12:#13        // hconsUnzipFields:(Lshapeless/Witness;Lshapeless/ops/record/UnzipFields;)Lshapeless/ops/record/UnzipFields;
  #24 = Methodref          #18.#23        // shapeless/ops/record/UnzipFields$.hconsUnzipFields:(Lshapeless/Witness;Lshapeless/ops/record/UnzipFields;)Lshapeless/ops/record/UnzipFields;
  #25 = Utf8               hnilUnzipFields
  #26 = Utf8               ()Lshapeless/ops/record/UnzipFields;
  #27 = Utf8               <L::Lshapeless/HNil;>()Lshapeless/ops/record/UnzipFields<TL;>;
  #28 = NameAndType        #25:#26        // hnilUnzipFields:()Lshapeless/ops/record/UnzipFields;
  #29 = Methodref          #18.#28        // shapeless/ops/record/UnzipFields$.hnilUnzipFields:()Lshapeless/ops/record/UnzipFields;
  #30 = Utf8               apply
  #31 = Utf8               (Lshapeless/ops/record/UnzipFields;)Lshapeless/ops/record/UnzipFields;
  #32 = Utf8               <L::Lshapeless/HList;>(Lshapeless/ops/record/UnzipFields<TL;>;)Lshapeless/ops/record/UnzipFields<TL;>;
  #33 = Utf8               uf
  #34 = NameAndType        #30:#31        // apply:(Lshapeless/ops/record/UnzipFields;)Lshapeless/ops/record/UnzipFields;
  #35 = Methodref          #18.#34        // shapeless/ops/record/UnzipFields$.apply:(Lshapeless/ops/record/UnzipFields;)Lshapeless/ops/record/UnzipFields;
  #36 = Utf8               keys
  #37 = Utf8               ()Lshapeless/HList;
  #38 = Utf8               values
  #39 = Utf8               (Lshapeless/HList;)Lshapeless/HList;
  #40 = Utf8               (TL;)Lshapeless/HList;
  #41 = Utf8               l
  #42 = Utf8               Code
  #43 = Utf8               Signature
  #44 = Utf8               MethodParameters
  #45 = Utf8               SourceFile
  #46 = Utf8               RuntimeVisibleAnnotations
  #47 = Utf8               ScalaInlineInfo
  #48 = Utf8               ScalaSig
{
  public static <K extends java.lang.Object, V extends java.lang.Object, T extends shapeless.HList> shapeless.ops.record.UnzipFields<shapeless.$colon$colon<V, T>> hconsUnzipFields(shapeless.Witness, shapeless.ops.record.UnzipFields<T>);
    descriptor: (Lshapeless/Witness;Lshapeless/ops/record/UnzipFields;)Lshapeless/ops/record/UnzipFields;
    flags: (0x0009) ACC_PUBLIC, ACC_STATIC
    Code:
      stack=3, locals=2, args_size=2
         0: getstatic     #22                 // Field shapeless/ops/record/UnzipFields$.MODULE$:Lshapeless/ops/record/UnzipFields$;
         3: aload_0
         4: aload_1
         5: invokevirtual #24                 // Method shapeless/ops/record/UnzipFields$.hconsUnzipFields:(Lshapeless/Witness;Lshapeless/ops/record/UnzipFields;)Lshapeless/ops/record/UnzipFields;
         8: areturn
    Signature: #14                          // <K:Ljava/lang/Object;V:Ljava/lang/Object;T::Lshapeless/HList;>(Lshapeless/Witness;Lshapeless/ops/record/UnzipFields<TT;>;)Lshapeless/ops/record/UnzipFields<Lshapeless/$colon$colon<TV;TT;>;>;
    MethodParameters:
      Name                           Flags
      key                            final
      tailUF                         final

  public static <L extends shapeless.HNil> shapeless.ops.record.UnzipFields<L> hnilUnzipFields();
    descriptor: ()Lshapeless/ops/record/UnzipFields;
    flags: (0x0009) ACC_PUBLIC, ACC_STATIC
    Code:
      stack=1, locals=0, args_size=0
         0: getstatic     #22                 // Field shapeless/ops/record/UnzipFields$.MODULE$:Lshapeless/ops/record/UnzipFields$;
         3: invokevirtual #29                 // Method shapeless/ops/record/UnzipFields$.hnilUnzipFields:()Lshapeless/ops/record/UnzipFields;
         6: areturn
    Signature: #27                          // <L::Lshapeless/HNil;>()Lshapeless/ops/record/UnzipFields<TL;>;

  public static <L extends shapeless.HList> shapeless.ops.record.UnzipFields<L> apply(shapeless.ops.record.UnzipFields<L>);
    descriptor: (Lshapeless/ops/record/UnzipFields;)Lshapeless/ops/record/UnzipFields;
    flags: (0x0009) ACC_PUBLIC, ACC_STATIC
    Code:
      stack=2, locals=1, args_size=1
         0: getstatic     #22                 // Field shapeless/ops/record/UnzipFields$.MODULE$:Lshapeless/ops/record/UnzipFields$;
         3: aload_0
         4: invokevirtual #35                 // Method shapeless/ops/record/UnzipFields$.apply:(Lshapeless/ops/record/UnzipFields;)Lshapeless/ops/record/UnzipFields;
         7: areturn
    Signature: #32                          // <L::Lshapeless/HList;>(Lshapeless/ops/record/UnzipFields<TL;>;)Lshapeless/ops/record/UnzipFields<TL;>;
    MethodParameters:
      Name                           Flags
      uf                             final

  public abstract shapeless.HList keys();
    descriptor: ()Lshapeless/HList;
    flags: (0x0401) ACC_PUBLIC, ACC_ABSTRACT
    Signature: #37                          // ()Lshapeless/HList;

  public abstract shapeless.HList values(L);
    descriptor: (Lshapeless/HList;)Lshapeless/HList;
    flags: (0x0401) ACC_PUBLIC, ACC_ABSTRACT
    Signature: #40                          // (TL;)Lshapeless/HList;
    MethodParameters:
      Name                           Flags
      l                              final
}
Signature: #3                           // <L::Lshapeless/HList;>Ljava/lang/Object;Ljava/io/Serializable;
SourceFile: "records.scala"
RuntimeVisibleAnnotations:
  0: #9(#10=s#11)
    scala.reflect.ScalaSignature(
      bytes="\u0006\u0005\u0005=caB\u0007\u000f!\u0003\r\n!\u0006\u0003\u0006S\u0001\u0011\tA\u000b\u0003\u0006e\u0001\u0011\tA\u000b\u0005\u0006g\u00011\t\u0001\u000e\u0005\u0006o\u00011\t\u0001O\u0004\u0006\u0001:A\t!\u0011\u0004\u0006\u001b9A\ta\u0011\u0005\u0006\u0017\u001a!\t\u0001\u0014\u0005\u0006\u001b\u001a!\tAT\u0003\u0005%\u001a\u00011\u000bC\u0003k\r\u0011\r1\u000eC\u0003u\r\u0011\rQ\u000fC\u0005\u0002@\u0019\t\t\u0011\"\u0003\u0002B\tYQK\u001c>ja\u001aKW\r\u001c3t\u0015\ty\u0001#\u0001\u0004sK\u000e|\'\u000f\u001a\u0006\u0003#I\t1a\u001c9t\u0015\u0005\u0019\u0012!C:iCB,G.Z:t\u0007\u0001)\"A\u0006 \u0014\u0007\u00019R\u0004\u0005\u0002\u001975\t\u0011DC\u0001\u001b\u0003\u0015\u00198-\u00197b\u0013\ta\u0012D\u0001\u0004B]f\u0014VM\u001a\t\u0003=\u0019r!a\b\u0013\u000f\u0005\u0001\u001aS\"A\u0011\u000b\u0005\t\"\u0012A\u0002\u001fs_>$h(C\u0001\u001b\u0013\t)\u0013$A\u0004qC\u000e\\\u0017mZ3\n\u0005\u001dB#\u0001D*fe&\fG.\u001b>bE2,\'BA\u0013\u001a\u0005\u0011YU-_:\u0012\u0005-r\u0003C\u0001\r-\u0013\ti\u0013DA\u0004O_RD\u0017N\\4\u0011\u0005=\u0002T\"\u0001\n\n\u0005E\u0012\"!\u0002%MSN$(A\u0002,bYV,7/\u0001\u0003lKf\u001cH#A\u001b\u0011\u0005Y\nQ\"\u0001\u0001\u0002\rY\fG.^3t)\tI$\b\u0005\u00027\u0005!)1\b\u0002a\u0001y\u0005\tA\u000e\u0005\u0002>}1\u0001A!B \u0001\u0005\u0004Q#!\u0001\'\u0002\u0017Us\'0\u001b9GS\u0016dGm\u001d\t\u0003\u0005\u001ai\u0011AD\n\u0004\r]!\u0005CA#K\u001b\u00051%BA$I\u0003\tIwNC\u0001J\u0003\u0011Q\u0017M^1\n\u0005\u001d2\u0015A\u0002\u001fj]&$h\bF\u0001B\u0003\u0015\t\u0007\u000f\u001d7z+\ty5\r\u0006\u0002QMB)\u0011+\u00032eS6\taAA\u0002Bkb,B\u0001V-]AJ\u0011Qk\u0016\u0004\u0005-\u001a\u0001AK\u0001\u0007=e\u00164\u0017N\\3nK:$h\bE\u0002C\u0001a\u0003\"!P-\u0005\u000b}J!\u0019\u0001\u0016\u0006\t%*\u0006e\u0017\t\u0003{q#Q!X\u0005C\u0002)\u0012\u0011aS\u0003\u0005eU\u0003s\f\u0005\u0002>A\u0012)\u0011-\u0003b\u0001U\t\ta\u000b\u0005\u0002>G\u0012)q\b\u0003b\u0001UA\u0011Q-\u0001\b\u0003{\u0019DQa\u001a\u0005A\u0004!\f!!\u001e4\u0011\u0007\t\u0003!\r\u0005\u0002f\u0005\u0005y\u0001N\\5m+:T\u0018\u000e\u001d$jK2$7/\u0006\u0002m_V\tQ\u000eE\u0003R\u00139\fh\u000e\u0005\u0002>_\u0012)qH\u0003b\u0001aF\u00111&\u001d\t\u0003_IL!a\u001d\n\u0003\t!s\u0015\u000e\\\u0001\u0011Q\u000e|gn]+ou&\u0004h)[3mIN,rA^A\u0006\u0003/\tY\u0002F\u0003x\u0003_\t)\u0003E\u0004R\u0013a\fy\"a\u000b\u0011\u000b=J80!\u0007\n\u0005i\u0014\"\u0001\u0004\u0013d_2|g\u000eJ2pY>t\u0007c\u0002?\u0002\u0004\u0005%\u0011Q\u0003\b\u0003{~t!\u0001\t@\n\u0003MI1!!\u0001\u0013\u0003!a\u0017MY3mY\u0016$\u0017\u0002BA\u0003\u0003\u000f\u0011\u0011BR5fY\u0012$\u0016\u0010]3\u000b\u0007\u0005\u0005!\u0003E\u0002>\u0003\u0017!a!X\u0006C\u0002\u00055\u0011cA\u0016\u0002\u0010A\u0019\u0001$!\u0005\n\u0007\u0005M\u0011DA\u0002B]f\u00042!PA\f\t\u0019\t7B1\u0001\u0002\u000eA\u0019Q(a\u0007\u0005\r\u0005u1B1\u0001+\u0005\u0005!\u0006CB\u0018z\u0003\u0013\t\t\u0003E\u0002\u0002$\u0005q1!PA\u0013\u0011\u001d\t9c\u0003a\u0002\u0003S\ta\u0001^1jYV3\u0005\u0003\u0002\"\u0001\u00033\u0001baL=\u0002\u0016\u00055\u0002cAA\u0012\u0005!9\u0011\u0011G\u0006A\u0004\u0005M\u0012aA6fsB1\u0011QGA\u001e\u0003\u0013q1aLA\u001c\u0013\r\tIDE\u0001\b/&$h.Z:t\u0013\r\u0011\u0016Q\b\u0006\u0004\u0003s\u0011\u0012\u0001D<sSR,\'+\u001a9mC\u000e,GCAA\"!\u0011\t)%a\u0013\u000e\u0005\u0005\u001d#bAA%\u0011\u0006!A.\u00198h\u0013\u0011\ti%a\u0012\u0003\r=\u0013\'.Z2u\u0001"
    )
  ScalaInlineInfo: length = 0xE (unknown attribute)
   01 00 00 02 00 24 00 25 00 00 26 00 27 00
  ScalaSig: length = 0x3 (unknown attribute)
   05 02 00
