Classfile /Users/mw/Projects/slang-braindump/.jar/jar11/assemble/slang-braindump/assemble/content/coursier/core/shaded/sourcecode/Line$$anonfun$$lessinit$greater$7.class
  Last modified May 29, 2022; size 1239 bytes
  SHA-256 checksum e1b34abb10b328b501978d40a2bba1e2a3028b99f9bc51c339a1c94486d4ed2c
  Compiled from "SourceContext.scala"
public final class coursier.core.shaded.sourcecode.Line$$anonfun$$lessinit$greater$7 extends scala.runtime.AbstractFunction1<java.lang.Object, coursier.core.shaded.sourcecode.Line> implements java.io.Serializable
  minor version: 0
  major version: 52
  flags: (0x0031) ACC_PUBLIC, ACC_FINAL, ACC_SUPER
  this_class: #2                          // coursier/core/shaded/sourcecode/Line$$anonfun$$lessinit$greater$7
  super_class: #5                         // scala/runtime/AbstractFunction1
  interfaces: 1, fields: 1, methods: 3, attributes: 6
Constant pool:
   #1 = Utf8               coursier/core/shaded/sourcecode/Line$$anonfun$$lessinit$greater$7
   #2 = Class              #1             // coursier/core/shaded/sourcecode/Line$$anonfun$$lessinit$greater$7
   #3 = Utf8               Lscala/runtime/AbstractFunction1<Ljava/lang/Object;Lcoursier/core/shaded/sourcecode/Line;>;Ljava/io/Serializable;
   #4 = Utf8               scala/runtime/AbstractFunction1
   #5 = Class              #4             // scala/runtime/AbstractFunction1
   #6 = Utf8               java/io/Serializable
   #7 = Class              #6             // java/io/Serializable
   #8 = Utf8               SourceContext.scala
   #9 = Utf8               coursier/core/shaded/sourcecode/Line$
  #10 = Class              #9             // coursier/core/shaded/sourcecode/Line$
  #11 = Utf8               <init>
  #12 = Utf8               ()V
  #13 = NameAndType        #11:#12        // "<init>":()V
  #14 = Utf8               serialVersionUID
  #15 = Utf8               J
  #16 = Long               0l
  #18 = Utf8               apply
  #19 = Utf8               (I)Lcoursier/core/shaded/sourcecode/Line;
  #20 = Utf8               x$7
  #21 = Utf8               coursier/core/shaded/sourcecode/Line
  #22 = Class              #21            // coursier/core/shaded/sourcecode/Line
  #23 = Utf8               (I)V
  #24 = NameAndType        #11:#23        // "<init>":(I)V
  #25 = Methodref          #22.#24        // coursier/core/shaded/sourcecode/Line."<init>":(I)V
  #26 = Utf8               this
  #27 = Utf8               Lcoursier/core/shaded/sourcecode/Line$$anonfun$$lessinit$greater$7;
  #28 = Utf8               I
  #29 = Utf8               (Ljava/lang/Object;)Ljava/lang/Object;
  #30 = Utf8               v1
  #31 = Utf8               scala/runtime/BoxesRunTime
  #32 = Class              #31            // scala/runtime/BoxesRunTime
  #33 = Utf8               unboxToInt
  #34 = Utf8               (Ljava/lang/Object;)I
  #35 = NameAndType        #33:#34        // unboxToInt:(Ljava/lang/Object;)I
  #36 = Methodref          #32.#35        // scala/runtime/BoxesRunTime.unboxToInt:(Ljava/lang/Object;)I
  #37 = NameAndType        #18:#19        // apply:(I)Lcoursier/core/shaded/sourcecode/Line;
  #38 = Methodref          #2.#37         // coursier/core/shaded/sourcecode/Line$$anonfun$$lessinit$greater$7.apply:(I)Lcoursier/core/shaded/sourcecode/Line;
  #39 = Utf8               Ljava/lang/Object;
  #40 = Methodref          #5.#13         // scala/runtime/AbstractFunction1."<init>":()V
  #41 = Utf8               ConstantValue
  #42 = Utf8               Code
  #43 = Utf8               LineNumberTable
  #44 = Utf8               LocalVariableTable
  #45 = Utf8               MethodParameters
  #46 = Utf8               InnerClasses
  #47 = Utf8               EnclosingMethod
  #48 = Utf8               Signature
  #49 = Utf8               SourceFile
  #50 = Utf8               ScalaInlineInfo
  #51 = Utf8               Scala
{
  private static final long serialVersionUID;
    descriptor: J
    flags: (0x001a) ACC_PRIVATE, ACC_STATIC, ACC_FINAL
    ConstantValue: long 0l

  public final coursier.core.shaded.sourcecode.Line apply(int);
    descriptor: (I)Lcoursier/core/shaded/sourcecode/Line;
    flags: (0x0011) ACC_PUBLIC, ACC_FINAL
    Code:
      stack=3, locals=2, args_size=2
         0: new           #22                 // class coursier/core/shaded/sourcecode/Line
         3: dup
         4: iload_1
         5: invokespecial #25                 // Method coursier/core/shaded/sourcecode/Line."<init>":(I)V
         8: areturn
      LineNumberTable:
        line 29: 0
      LocalVariableTable:
        Start  Length  Slot  Name   Signature
            0       9     0  this   Lcoursier/core/shaded/sourcecode/Line$$anonfun$$lessinit$greater$7;
            0       9     1   x$7   I
    MethodParameters:
      Name                           Flags
      x$7                            final

  public final java.lang.Object apply(java.lang.Object);
    descriptor: (Ljava/lang/Object;)Ljava/lang/Object;
    flags: (0x1051) ACC_PUBLIC, ACC_FINAL, ACC_BRIDGE, ACC_SYNTHETIC
    Code:
      stack=2, locals=2, args_size=2
         0: aload_0
         1: aload_1
         2: invokestatic  #36                 // Method scala/runtime/BoxesRunTime.unboxToInt:(Ljava/lang/Object;)I
         5: invokevirtual #38                 // Method apply:(I)Lcoursier/core/shaded/sourcecode/Line;
         8: areturn
      LineNumberTable:
        line 29: 0
      LocalVariableTable:
        Start  Length  Slot  Name   Signature
            0       9     0  this   Lcoursier/core/shaded/sourcecode/Line$$anonfun$$lessinit$greater$7;
            0       9     1    v1   Ljava/lang/Object;
    MethodParameters:
      Name                           Flags
      v1                             final

  public coursier.core.shaded.sourcecode.Line$$anonfun$$lessinit$greater$7();
    descriptor: ()V
    flags: (0x0001) ACC_PUBLIC
    Code:
      stack=1, locals=1, args_size=1
         0: aload_0
         1: invokespecial #40                 // Method scala/runtime/AbstractFunction1."<init>":()V
         4: return
      LineNumberTable:
        line 29: 0
      LocalVariableTable:
        Start  Length  Slot  Name   Signature
            0       5     0  this   Lcoursier/core/shaded/sourcecode/Line$$anonfun$$lessinit$greater$7;
}
InnerClasses:
  public final #2;                        // class coursier/core/shaded/sourcecode/Line$$anonfun$$lessinit$greater$7
EnclosingMethod: #10.#13                // coursier.core.shaded.sourcecode.Line$.<init>
Signature: #3                           // Lscala/runtime/AbstractFunction1<Ljava/lang/Object;Lcoursier/core/shaded/sourcecode/Line;>;Ljava/io/Serializable;
SourceFile: "SourceContext.scala"
  ScalaInlineInfo: length = 0x13 (unknown attribute)
   01 01 00 03 00 0B 00 0C 01 00 12 00 13 01 00 12
   00 1D 01
  Scala: length = 0x0 (unknown attribute)

