Classfile /Users/mw/Projects/slang-braindump/.jar/jar11/assemble/slang-braindump/assemble/content/coursier/core/shaded/sourcecode/Macros$$anonfun$1.class
  Last modified May 29, 2022; size 2640 bytes
  SHA-256 checksum 16f832147be30914117ce7bcb6908051f47cfc1bc737dbf38fab41d700fd4e9c
  Compiled from "Macros.scala"
public final class coursier.core.shaded.sourcecode.Macros$$anonfun$1 extends scala.runtime.AbstractPartialFunction<scala.reflect.api.Trees$TreeApi, java.lang.Object> implements java.io.Serializable
  minor version: 0
  major version: 52
  flags: (0x0031) ACC_PUBLIC, ACC_FINAL, ACC_SUPER
  this_class: #2                          // coursier/core/shaded/sourcecode/Macros$$anonfun$1
  super_class: #5                         // scala/runtime/AbstractPartialFunction
  interfaces: 1, fields: 2, methods: 5, attributes: 6
Constant pool:
    #1 = Utf8               coursier/core/shaded/sourcecode/Macros$$anonfun$1
    #2 = Class              #1            // coursier/core/shaded/sourcecode/Macros$$anonfun$1
    #3 = Utf8               Lscala/runtime/AbstractPartialFunction<Lscala/reflect/api/Trees$TreeApi;Ljava/lang/Object;>;Ljava/io/Serializable;
    #4 = Utf8               scala/runtime/AbstractPartialFunction
    #5 = Class              #4            // scala/runtime/AbstractPartialFunction
    #6 = Utf8               java/io/Serializable
    #7 = Class              #6            // java/io/Serializable
    #8 = Utf8               Macros.scala
    #9 = Utf8               coursier/core/shaded/sourcecode/Macros$
   #10 = Class              #9            // coursier/core/shaded/sourcecode/Macros$
   #11 = Utf8               text
   #12 = Utf8               (Lscala/reflect/macros/blackbox/Context;Lscala/reflect/api/Exprs$Expr;Lscala/reflect/api/TypeTags$WeakTypeTag;)Lscala/reflect/api/Exprs$Expr;
   #13 = NameAndType        #11:#12       // text:(Lscala/reflect/macros/blackbox/Context;Lscala/reflect/api/Exprs$Expr;Lscala/reflect/api/TypeTags$WeakTypeTag;)Lscala/reflect/api/Exprs$Expr;
   #14 = Utf8               scala/reflect/api/Trees$TreeApi
   #15 = Class              #14           // scala/reflect/api/Trees$TreeApi
   #16 = Utf8               scala/reflect/api/Trees
   #17 = Class              #16           // scala/reflect/api/Trees
   #18 = Utf8               TreeApi
   #19 = Utf8               serialVersionUID
   #20 = Utf8               J
   #21 = Long               0l
   #23 = Utf8               c$3
   #24 = Utf8               Lscala/reflect/macros/blackbox/Context;
   #25 = Utf8               applyOrElse
   #26 = Utf8               (Lscala/reflect/api/Trees$TreeApi;Lscala/Function1;)Ljava/lang/Object;
   #27 = Utf8               <A1:Lscala/reflect/api/Trees$TreeApi;B1:Ljava/lang/Object;>(TA1;Lscala/Function1<TA1;TB1;>;)TB1;
   #28 = Utf8               x1
   #29 = Utf8               default
   #30 = Utf8               pos
   #31 = Utf8               ()Lscala/reflect/api/Position;
   #32 = NameAndType        #30:#31       // pos:()Lscala/reflect/api/Position;
   #33 = InterfaceMethodref #15.#32       // scala/reflect/api/Trees$TreeApi.pos:()Lscala/reflect/api/Position;
   #34 = NameAndType        #23:#24       // c$3:Lscala/reflect/macros/blackbox/Context;
   #35 = Fieldref           #2.#34        // coursier/core/shaded/sourcecode/Macros$$anonfun$1.c$3:Lscala/reflect/macros/blackbox/Context;
   #36 = Utf8               scala/reflect/macros/blackbox/Context
   #37 = Class              #36           // scala/reflect/macros/blackbox/Context
   #38 = Utf8               universe
   #39 = Utf8               ()Lscala/reflect/macros/Universe;
   #40 = NameAndType        #38:#39       // universe:()Lscala/reflect/macros/Universe;
   #41 = InterfaceMethodref #37.#40       // scala/reflect/macros/blackbox/Context.universe:()Lscala/reflect/macros/Universe;
   #42 = Utf8               scala/reflect/macros/Universe
   #43 = Class              #42           // scala/reflect/macros/Universe
   #44 = Utf8               NoPosition
   #45 = NameAndType        #44:#31       // NoPosition:()Lscala/reflect/api/Position;
   #46 = Methodref          #43.#45       // scala/reflect/macros/Universe.NoPosition:()Lscala/reflect/api/Position;
   #47 = Utf8               scala/Function1
   #48 = Class              #47           // scala/Function1
   #49 = Utf8               scala/reflect/api/Position
   #50 = Class              #49           // scala/reflect/api/Position
   #51 = Utf8               java/lang/Object
   #52 = Class              #51           // java/lang/Object
   #53 = Utf8               equals
   #54 = Utf8               (Ljava/lang/Object;)Z
   #55 = NameAndType        #53:#54       // equals:(Ljava/lang/Object;)Z
   #56 = Methodref          #52.#55       // java/lang/Object.equals:(Ljava/lang/Object;)Z
   #57 = Integer            2147483647
   #58 = Utf8               startOrPoint
   #59 = Utf8               ()I
   #60 = NameAndType        #58:#59       // startOrPoint:()I
   #61 = InterfaceMethodref #50.#60       // scala/reflect/api/Position.startOrPoint:()I
   #62 = Utf8               scala/runtime/BoxesRunTime
   #63 = Class              #62           // scala/runtime/BoxesRunTime
   #64 = Utf8               boxToInteger
   #65 = Utf8               (I)Ljava/lang/Integer;
   #66 = NameAndType        #64:#65       // boxToInteger:(I)Ljava/lang/Integer;
   #67 = Methodref          #63.#66       // scala/runtime/BoxesRunTime.boxToInteger:(I)Ljava/lang/Integer;
   #68 = Utf8               java/lang/Integer
   #69 = Class              #68           // java/lang/Integer
   #70 = Utf8               this
   #71 = Utf8               Lcoursier/core/shaded/sourcecode/Macros$$anonfun$1;
   #72 = Utf8               Lscala/reflect/api/Trees$TreeApi;
   #73 = Utf8               Lscala/Function1;
   #74 = Utf8               isDefinedAt
   #75 = Utf8               (Lscala/reflect/api/Trees$TreeApi;)Z
   #76 = Utf8               x
   #77 = NameAndType        #74:#75       // isDefinedAt:(Lscala/reflect/api/Trees$TreeApi;)Z
   #78 = Methodref          #2.#77        // coursier/core/shaded/sourcecode/Macros$$anonfun$1.isDefinedAt:(Lscala/reflect/api/Trees$TreeApi;)Z
   #79 = Utf8               Ljava/lang/Object;
   #80 = Utf8               (Ljava/lang/Object;Lscala/Function1;)Ljava/lang/Object;
   #81 = NameAndType        #25:#26       // applyOrElse:(Lscala/reflect/api/Trees$TreeApi;Lscala/Function1;)Ljava/lang/Object;
   #82 = Methodref          #2.#81        // coursier/core/shaded/sourcecode/Macros$$anonfun$1.applyOrElse:(Lscala/reflect/api/Trees$TreeApi;Lscala/Function1;)Ljava/lang/Object;
   #83 = Utf8               <init>
   #84 = Utf8               (Lscala/reflect/macros/blackbox/Context;)V
   #85 = Utf8               ()V
   #86 = NameAndType        #83:#85       // "<init>":()V
   #87 = Methodref          #5.#86        // scala/runtime/AbstractPartialFunction."<init>":()V
   #88 = Utf8               ConstantValue
   #89 = Utf8               Code
   #90 = Utf8               StackMapTable
   #91 = Utf8               LineNumberTable
   #92 = Utf8               LocalVariableTable
   #93 = Utf8               Signature
   #94 = Utf8               MethodParameters
   #95 = Utf8               InnerClasses
   #96 = Utf8               EnclosingMethod
   #97 = Utf8               SourceFile
   #98 = Utf8               ScalaInlineInfo
   #99 = Utf8               Scala
{
  private static final long serialVersionUID;
    descriptor: J
    flags: (0x001a) ACC_PRIVATE, ACC_STATIC, ACC_FINAL
    ConstantValue: long 0l

  private final scala.reflect.macros.blackbox.Context c$3;
    descriptor: Lscala/reflect/macros/blackbox/Context;
    flags: (0x0012) ACC_PRIVATE, ACC_FINAL

  public final <A1 extends scala.reflect.api.Trees$TreeApi, B1 extends java.lang.Object> B1 applyOrElse(A1, scala.Function1<A1, B1>);
    descriptor: (Lscala/reflect/api/Trees$TreeApi;Lscala/Function1;)Ljava/lang/Object;
    flags: (0x0011) ACC_PUBLIC, ACC_FINAL
    Code:
      stack=2, locals=8, args_size=3
         0: aload_1
         1: astore        5
         3: aload         5
         5: invokeinterface #33,  1           // InterfaceMethod scala/reflect/api/Trees$TreeApi.pos:()Lscala/reflect/api/Position;
        10: astore        6
        12: aload_0
        13: getfield      #35                 // Field c$3:Lscala/reflect/macros/blackbox/Context;
        16: invokeinterface #41,  1           // InterfaceMethod scala/reflect/macros/blackbox/Context.universe:()Lscala/reflect/macros/Universe;
        21: invokevirtual #46                 // Method scala/reflect/macros/Universe.NoPosition:()Lscala/reflect/api/Position;
        24: aload         6
        26: astore        7
        28: dup
        29: ifnonnull     41
        32: pop
        33: aload         7
        35: ifnull        49
        38: goto          56
        41: aload         7
        43: invokevirtual #56                 // Method java/lang/Object.equals:(Ljava/lang/Object;)Z
        46: ifeq          56
        49: ldc           #57                 // int 2147483647
        51: istore        4
        53: goto          71
        56: goto          59
        59: aload         6
        61: invokeinterface #61,  1           // InterfaceMethod scala/reflect/api/Position.startOrPoint:()I
        66: istore        4
        68: goto          71
        71: iload         4
        73: invokestatic  #67                 // Method scala/runtime/BoxesRunTime.boxToInteger:(I)Ljava/lang/Integer;
        76: astore_3
        77: goto          80
        80: aload_3
        81: areturn
      StackMapTable: number_of_entries = 6
        frame_type = 255 /* full_frame */
          offset_delta = 41
          locals = [ class coursier/core/shaded/sourcecode/Macros$$anonfun$1, class scala/reflect/api/Trees$TreeApi, class scala/Function1, top, top, class scala/reflect/api/Trees$TreeApi, class scala/reflect/api/Position, class scala/reflect/api/Position ]
          stack = [ class scala/reflect/api/Position ]
        frame_type = 7 /* same */
        frame_type = 6 /* same */
        frame_type = 2 /* same */
        frame_type = 255 /* full_frame */
          offset_delta = 11
          locals = [ class coursier/core/shaded/sourcecode/Macros$$anonfun$1, class scala/reflect/api/Trees$TreeApi, class scala/Function1, top, int, class scala/reflect/api/Trees$TreeApi, class scala/reflect/api/Position, class scala/reflect/api/Position ]
          stack = []
        frame_type = 255 /* full_frame */
          offset_delta = 8
          locals = [ class coursier/core/shaded/sourcecode/Macros$$anonfun$1, class scala/reflect/api/Trees$TreeApi, class scala/Function1, class java/lang/Integer, int, class scala/reflect/api/Trees$TreeApi, class scala/reflect/api/Position, class scala/reflect/api/Position ]
          stack = []
      LineNumberTable:
        line 136: 0
        line 137: 3
        line 138: 12
        line 139: 59
        line 137: 71
        line 136: 80
      LocalVariableTable:
        Start  Length  Slot  Name   Signature
            0      82     0  this   Lcoursier/core/shaded/sourcecode/Macros$$anonfun$1;
            0      82     1    x1   Lscala/reflect/api/Trees$TreeApi;
            0      82     2 default   Lscala/Function1;
    Signature: #27                          // <A1:Lscala/reflect/api/Trees$TreeApi;B1:Ljava/lang/Object;>(TA1;Lscala/Function1<TA1;TB1;>;)TB1;
    MethodParameters:
      Name                           Flags
      x1                             final
      default                        final

  public final boolean isDefinedAt(scala.reflect.api.Trees$TreeApi);
    descriptor: (Lscala/reflect/api/Trees$TreeApi;)Z
    flags: (0x0011) ACC_PUBLIC, ACC_FINAL
    Code:
      stack=1, locals=4, args_size=2
         0: aload_1
         1: astore_3
         2: iconst_1
         3: istore_2
         4: goto          7
         7: iload_2
         8: ireturn
      StackMapTable: number_of_entries = 1
        frame_type = 253 /* append */
          offset_delta = 7
          locals = [ int, class scala/reflect/api/Trees$TreeApi ]
      LineNumberTable:
        line 136: 0
        line 137: 2
        line 136: 7
      LocalVariableTable:
        Start  Length  Slot  Name   Signature
            0       9     0  this   Lcoursier/core/shaded/sourcecode/Macros$$anonfun$1;
            0       9     1    x1   Lscala/reflect/api/Trees$TreeApi;
    MethodParameters:
      Name                           Flags
      x1                             final

  public final boolean isDefinedAt(java.lang.Object);
    descriptor: (Ljava/lang/Object;)Z
    flags: (0x1051) ACC_PUBLIC, ACC_FINAL, ACC_BRIDGE, ACC_SYNTHETIC
    Code:
      stack=2, locals=2, args_size=2
         0: aload_0
         1: aload_1
         2: checkcast     #15                 // class scala/reflect/api/Trees$TreeApi
         5: invokevirtual #78                 // Method isDefinedAt:(Lscala/reflect/api/Trees$TreeApi;)Z
         8: ireturn
      LineNumberTable:
        line 136: 0
      LocalVariableTable:
        Start  Length  Slot  Name   Signature
            0       9     0  this   Lcoursier/core/shaded/sourcecode/Macros$$anonfun$1;
            0       9     1     x   Ljava/lang/Object;
    MethodParameters:
      Name                           Flags
      x                              final

  public final java.lang.Object applyOrElse(java.lang.Object, scala.Function1);
    descriptor: (Ljava/lang/Object;Lscala/Function1;)Ljava/lang/Object;
    flags: (0x1051) ACC_PUBLIC, ACC_FINAL, ACC_BRIDGE, ACC_SYNTHETIC
    Code:
      stack=3, locals=3, args_size=3
         0: aload_0
         1: aload_1
         2: checkcast     #15                 // class scala/reflect/api/Trees$TreeApi
         5: aload_2
         6: invokevirtual #82                 // Method applyOrElse:(Lscala/reflect/api/Trees$TreeApi;Lscala/Function1;)Ljava/lang/Object;
         9: areturn
      LineNumberTable:
        line 136: 0
      LocalVariableTable:
        Start  Length  Slot  Name   Signature
            0      10     0  this   Lcoursier/core/shaded/sourcecode/Macros$$anonfun$1;
            0      10     1     x   Ljava/lang/Object;
            0      10     2 default   Lscala/Function1;
    MethodParameters:
      Name                           Flags
      x                              final
      default                        final

  public coursier.core.shaded.sourcecode.Macros$$anonfun$1(scala.reflect.macros.blackbox.Context);
    descriptor: (Lscala/reflect/macros/blackbox/Context;)V
    flags: (0x0001) ACC_PUBLIC
    Code:
      stack=2, locals=2, args_size=2
         0: aload_0
         1: aload_1
         2: putfield      #35                 // Field c$3:Lscala/reflect/macros/blackbox/Context;
         5: aload_0
         6: invokespecial #87                 // Method scala/runtime/AbstractPartialFunction."<init>":()V
         9: return
      LineNumberTable:
        line 133: 0
        line 136: 5
      LocalVariableTable:
        Start  Length  Slot  Name   Signature
            0      10     0  this   Lcoursier/core/shaded/sourcecode/Macros$$anonfun$1;
            0      10     1   c$3   Lscala/reflect/macros/blackbox/Context;
    MethodParameters:
      Name                           Flags
      c$3                            final
}
InnerClasses:
  public #18= #15 of #17;                 // TreeApi=class scala/reflect/api/Trees$TreeApi of class scala/reflect/api/Trees
  public final #2;                        // class coursier/core/shaded/sourcecode/Macros$$anonfun$1
EnclosingMethod: #10.#13                // coursier.core.shaded.sourcecode.Macros$.text
Signature: #3                           // Lscala/runtime/AbstractPartialFunction<Lscala/reflect/api/Trees$TreeApi;Ljava/lang/Object;>;Ljava/io/Serializable;
SourceFile: "Macros.scala"
  ScalaInlineInfo: length = 0x1D (unknown attribute)
   01 01 00 05 00 53 00 54 01 00 19 00 50 01 00 19
   00 1A 01 00 4A 00 32 01 00 4A 00 4B 01
  Scala: length = 0x0 (unknown attribute)

