Classfile /Users/mw/Projects/slang-braindump/.jar/jar11/assemble/slang-braindump/assemble/content/coursier/core/shaded/sourcecode/TestUtil.class
  Last modified May 29, 2022; size 591 bytes
  SHA-256 checksum f32cd129a732d4b6c9f3f374a7a01c256837b8c94c431db5789ecd94a4919223
  Compiled from "TestUtil.scala"
public final class coursier.core.shaded.sourcecode.TestUtil
  minor version: 0
  major version: 52
  flags: (0x0031) ACC_PUBLIC, ACC_FINAL, ACC_SUPER
  this_class: #2                          // coursier/core/shaded/sourcecode/TestUtil
  super_class: #4                         // java/lang/Object
  interfaces: 0, fields: 0, methods: 1, attributes: 3
Constant pool:
   #1 = Utf8               coursier/core/shaded/sourcecode/TestUtil
   #2 = Class              #1             // coursier/core/shaded/sourcecode/TestUtil
   #3 = Utf8               java/lang/Object
   #4 = Class              #3             // java/lang/Object
   #5 = Utf8               TestUtil.scala
   #6 = Utf8               Lscala/reflect/ScalaSignature;
   #7 = Utf8               bytes
   #8 = Utf8               \u0006\u0005e9Q\u0001B\u0003\t\u0002!1QAC\u0003\t\u0002-AQAE\u0001\u0005\u0002MA\u0001\u0002F\u0001\t\u0006\u0004%\t!F\u0001\t)\u0016\u001cH/\u0016;jY*\ta!\u0001\u0006t_V\u00148-Z2pI\u0016\u001c\u0001\u0001\u0005\u0002\n\u00035\tQA\u0001\u0005UKN$X\u000b^5m\'\t\tA\u0002\u0005\u0002\u000e!5\taBC\u0001\u0010\u0003\u0015\u00198-\u00197b\u0013\t\tbB\u0001\u0004B]f\u0014VMZ\u0001\u0007y%t\u0017\u000e\u001e \u0015\u0003!\tq![:E_R$\u00180F\u0001\u0017!\tiq#\u0003\u0002\u0019\u001d\t9!i\\8mK\u0006t\u0007
   #9 = Utf8               isDotty
  #10 = Utf8               ()Z
  #11 = Utf8               coursier/core/shaded/sourcecode/TestUtil$
  #12 = Class              #11            // coursier/core/shaded/sourcecode/TestUtil$
  #13 = Utf8               MODULE$
  #14 = Utf8               Lcoursier/core/shaded/sourcecode/TestUtil$;
  #15 = NameAndType        #13:#14        // MODULE$:Lcoursier/core/shaded/sourcecode/TestUtil$;
  #16 = Fieldref           #12.#15        // coursier/core/shaded/sourcecode/TestUtil$.MODULE$:Lcoursier/core/shaded/sourcecode/TestUtil$;
  #17 = NameAndType        #9:#10         // isDotty:()Z
  #18 = Methodref          #12.#17        // coursier/core/shaded/sourcecode/TestUtil$.isDotty:()Z
  #19 = Utf8               Code
  #20 = Utf8               SourceFile
  #21 = Utf8               RuntimeVisibleAnnotations
  #22 = Utf8               ScalaSig
{
  public static boolean isDotty();
    descriptor: ()Z
    flags: (0x0009) ACC_PUBLIC, ACC_STATIC
    Code:
      stack=1, locals=0, args_size=0
         0: getstatic     #16                 // Field coursier/core/shaded/sourcecode/TestUtil$.MODULE$:Lcoursier/core/shaded/sourcecode/TestUtil$;
         3: invokevirtual #18                 // Method coursier/core/shaded/sourcecode/TestUtil$.isDotty:()Z
         6: ireturn
}
SourceFile: "TestUtil.scala"
RuntimeVisibleAnnotations:
  0: #6(#7=s#8)
    scala.reflect.ScalaSignature(
      bytes="\u0006\u0005e9Q\u0001B\u0003\t\u0002!1QAC\u0003\t\u0002-AQAE\u0001\u0005\u0002MA\u0001\u0002F\u0001\t\u0006\u0004%\t!F\u0001\t)\u0016\u001cH/\u0016;jY*\ta!\u0001\u0006t_V\u00148-Z2pI\u0016\u001c\u0001\u0001\u0005\u0002\n\u00035\tQA\u0001\u0005UKN$X\u000b^5m\'\t\tA\u0002\u0005\u0002\u000e!5\taBC\u0001\u0010\u0003\u0015\u00198-\u00197b\u0013\t\tbB\u0001\u0004B]f\u0014VMZ\u0001\u0007y%t\u0017\u000e\u001e \u0015\u0003!\tq![:E_R$\u00180F\u0001\u0017!\tiq#\u0003\u0002\u0019\u001d\t9!i\\8mK\u0006t\u0007"
    )
  ScalaSig: length = 0x3 (unknown attribute)
   05 02 00
