Classfile /Users/mw/Projects/slang-braindump/.jar/jar11/assemble/slang-braindump/assemble/content/coursier/core/shaded/sourcecode/TestUtil$.class
  Last modified May 29, 2022; size 1352 bytes
  SHA-256 checksum a8df5cc6c0faea2995ef7a75c24139acd648a7940c8a4d66b038cdba95e39311
  Compiled from "TestUtil.scala"
public final class coursier.core.shaded.sourcecode.TestUtil$
  minor version: 0
  major version: 52
  flags: (0x0031) ACC_PUBLIC, ACC_FINAL, ACC_SUPER
  this_class: #2                          // coursier/core/shaded/sourcecode/TestUtil$
  super_class: #4                         // java/lang/Object
  interfaces: 0, fields: 3, methods: 5, attributes: 3
Constant pool:
   #1 = Utf8               coursier/core/shaded/sourcecode/TestUtil$
   #2 = Class              #1             // coursier/core/shaded/sourcecode/TestUtil$
   #3 = Utf8               java/lang/Object
   #4 = Class              #3             // java/lang/Object
   #5 = Utf8               TestUtil.scala
   #6 = Utf8               MODULE$
   #7 = Utf8               Lcoursier/core/shaded/sourcecode/TestUtil$;
   #8 = Utf8               isDotty
   #9 = Utf8               Z
  #10 = Utf8               bitmap$0
  #11 = Utf8               <clinit>
  #12 = Utf8               ()V
  #13 = Utf8               <init>
  #14 = NameAndType        #13:#12        // "<init>":()V
  #15 = Methodref          #2.#14         // coursier/core/shaded/sourcecode/TestUtil$."<init>":()V
  #16 = NameAndType        #6:#7          // MODULE$:Lcoursier/core/shaded/sourcecode/TestUtil$;
  #17 = Fieldref           #2.#16         // coursier/core/shaded/sourcecode/TestUtil$.MODULE$:Lcoursier/core/shaded/sourcecode/TestUtil$;
  #18 = Utf8               isDotty$lzycompute
  #19 = Utf8               ()Z
  #20 = NameAndType        #10:#9         // bitmap$0:Z
  #21 = Fieldref           #2.#20         // coursier/core/shaded/sourcecode/TestUtil$.bitmap$0:Z
  #22 = Utf8               java/lang/Thread
  #23 = Class              #22            // java/lang/Thread
  #24 = Utf8               currentThread
  #25 = Utf8               ()Ljava/lang/Thread;
  #26 = NameAndType        #24:#25        // currentThread:()Ljava/lang/Thread;
  #27 = Methodref          #23.#26        // java/lang/Thread.currentThread:()Ljava/lang/Thread;
  #28 = Utf8               getContextClassLoader
  #29 = Utf8               ()Ljava/lang/ClassLoader;
  #30 = NameAndType        #28:#29        // getContextClassLoader:()Ljava/lang/ClassLoader;
  #31 = Methodref          #23.#30        // java/lang/Thread.getContextClassLoader:()Ljava/lang/ClassLoader;
  #32 = Utf8               liftedTree1$1
  #33 = Utf8               (Ljava/lang/ClassLoader;)Z
  #34 = NameAndType        #32:#33        // liftedTree1$1:(Ljava/lang/ClassLoader;)Z
  #35 = Methodref          #2.#34         // coursier/core/shaded/sourcecode/TestUtil$.liftedTree1$1:(Ljava/lang/ClassLoader;)Z
  #36 = NameAndType        #8:#9          // isDotty:Z
  #37 = Fieldref           #2.#36         // coursier/core/shaded/sourcecode/TestUtil$.isDotty:Z
  #38 = Utf8               java/lang/Throwable
  #39 = Class              #38            // java/lang/Throwable
  #40 = Utf8               cl
  #41 = Utf8               Ljava/lang/ClassLoader;
  #42 = Utf8               this
  #43 = NameAndType        #18:#19        // isDotty$lzycompute:()Z
  #44 = Methodref          #2.#43         // coursier/core/shaded/sourcecode/TestUtil$.isDotty$lzycompute:()Z
  #45 = Utf8               cl$1
  #46 = Utf8               java/lang/ClassNotFoundException
  #47 = Class              #46            // java/lang/ClassNotFoundException
  #48 = Utf8               dotty.DottyPredef
  #49 = String             #48            // dotty.DottyPredef
  #50 = Utf8               java/lang/ClassLoader
  #51 = Class              #50            // java/lang/ClassLoader
  #52 = Utf8               loadClass
  #53 = Utf8               (Ljava/lang/String;)Ljava/lang/Class;
  #54 = NameAndType        #52:#53        // loadClass:(Ljava/lang/String;)Ljava/lang/Class;
  #55 = Methodref          #51.#54        // java/lang/ClassLoader.loadClass:(Ljava/lang/String;)Ljava/lang/Class;
  #56 = Methodref          #4.#14         // java/lang/Object."<init>":()V
  #57 = Utf8               Code
  #58 = Utf8               LineNumberTable
  #59 = Utf8               StackMapTable
  #60 = Utf8               LocalVariableTable
  #61 = Utf8               MethodParameters
  #62 = Utf8               SourceFile
  #63 = Utf8               ScalaInlineInfo
  #64 = Utf8               Scala
{
  public static final coursier.core.shaded.sourcecode.TestUtil$ MODULE$;
    descriptor: Lcoursier/core/shaded/sourcecode/TestUtil$;
    flags: (0x0019) ACC_PUBLIC, ACC_STATIC, ACC_FINAL

  private static boolean isDotty;
    descriptor: Z
    flags: (0x000a) ACC_PRIVATE, ACC_STATIC

  private static volatile boolean bitmap$0;
    descriptor: Z
    flags: (0x004a) ACC_PRIVATE, ACC_STATIC, ACC_VOLATILE

  public static {};
    descriptor: ()V
    flags: (0x0009) ACC_PUBLIC, ACC_STATIC
    Code:
      stack=2, locals=0, args_size=0
         0: new           #2                  // class coursier/core/shaded/sourcecode/TestUtil$
         3: dup
         4: invokespecial #15                 // Method "<init>":()V
         7: putstatic     #17                 // Field MODULE$:Lcoursier/core/shaded/sourcecode/TestUtil$;
        10: return
      LineNumberTable:
        line 3: 0

  private boolean isDotty$lzycompute();
    descriptor: ()Z
    flags: (0x0002) ACC_PRIVATE
    Code:
      stack=2, locals=3, args_size=1
         0: aload_0
         1: dup
         2: astore_1
         3: monitorenter
         4: getstatic     #21                 // Field bitmap$0:Z
         7: ifne          28
        10: invokestatic  #27                 // Method java/lang/Thread.currentThread:()Ljava/lang/Thread;
        13: invokevirtual #31                 // Method java/lang/Thread.getContextClassLoader:()Ljava/lang/ClassLoader;
        16: astore_2
        17: aload_2
        18: invokestatic  #35                 // Method liftedTree1$1:(Ljava/lang/ClassLoader;)Z
        21: putstatic     #37                 // Field isDotty:Z
        24: iconst_1
        25: putstatic     #21                 // Field bitmap$0:Z
        28: aload_1
        29: monitorexit
        30: goto          36
        33: aload_1
        34: monitorexit
        35: athrow
        36: getstatic     #37                 // Field isDotty:Z
        39: ireturn
      Exception table:
         from    to  target type
             4    28    33   any
      StackMapTable: number_of_entries = 3
        frame_type = 252 /* append */
          offset_delta = 28
          locals = [ class coursier/core/shaded/sourcecode/TestUtil$ ]
        frame_type = 68 /* same_locals_1_stack_item */
          stack = [ class java/lang/Throwable ]
        frame_type = 2 /* same */
      LineNumberTable:
        line 6: 0
        line 7: 10
        line 8: 17
        line 6: 21
      LocalVariableTable:
        Start  Length  Slot  Name   Signature
           16       5     2    cl   Ljava/lang/ClassLoader;
            0      40     0  this   Lcoursier/core/shaded/sourcecode/TestUtil$;

  public boolean isDotty();
    descriptor: ()Z
    flags: (0x0001) ACC_PUBLIC
    Code:
      stack=1, locals=1, args_size=1
         0: getstatic     #21                 // Field bitmap$0:Z
         3: ifne          13
         6: aload_0
         7: invokespecial #44                 // Method isDotty$lzycompute:()Z
        10: goto          16
        13: getstatic     #37                 // Field isDotty:Z
        16: ireturn
      StackMapTable: number_of_entries = 2
        frame_type = 13 /* same */
        frame_type = 66 /* same_locals_1_stack_item */
          stack = [ int ]
      LineNumberTable:
        line 6: 0
      LocalVariableTable:
        Start  Length  Slot  Name   Signature
            0      17     0  this   Lcoursier/core/shaded/sourcecode/TestUtil$;

  private static final boolean liftedTree1$1(java.lang.ClassLoader);
    descriptor: (Ljava/lang/ClassLoader;)Z
    flags: (0x001a) ACC_PRIVATE, ACC_STATIC, ACC_FINAL
    Code:
      stack=2, locals=1, args_size=1
         0: aload_0
         1: ldc           #49                 // String dotty.DottyPredef
         3: invokevirtual #55                 // Method java/lang/ClassLoader.loadClass:(Ljava/lang/String;)Ljava/lang/Class;
         6: pop
         7: iconst_1
         8: goto          16
        11: pop
        12: iconst_0
        13: goto          16
        16: ireturn
      Exception table:
         from    to  target type
             0     8    11   Class java/lang/ClassNotFoundException
      StackMapTable: number_of_entries = 2
        frame_type = 75 /* same_locals_1_stack_item */
          stack = [ class java/lang/ClassNotFoundException ]
        frame_type = 68 /* same_locals_1_stack_item */
          stack = [ int ]
      LineNumberTable:
        line 9: 0
        line 10: 7
        line 13: 12
      LocalVariableTable:
        Start  Length  Slot  Name   Signature
            0      17     0  cl$1   Ljava/lang/ClassLoader;
    MethodParameters:
      Name                           Flags
      cl$1                           final

  private coursier.core.shaded.sourcecode.TestUtil$();
    descriptor: ()V
    flags: (0x0002) ACC_PRIVATE
    Code:
      stack=1, locals=1, args_size=1
         0: aload_0
         1: invokespecial #56                 // Method java/lang/Object."<init>":()V
         4: return
      LineNumberTable:
        line 17: 0
        line 3: 4
      LocalVariableTable:
        Start  Length  Slot  Name   Signature
            0       5     0  this   Lcoursier/core/shaded/sourcecode/TestUtil$;
}
SourceFile: "TestUtil.scala"
  ScalaInlineInfo: length = 0x18 (unknown attribute)
   01 01 00 04 00 0D 00 0C 01 00 08 00 13 01 00 12
   00 13 01 00 20 00 21 01
  Scala: length = 0x0 (unknown attribute)

