Classfile /Users/mw/Projects/slang-braindump/.jar/jar11/assemble/slang-braindump/assemble/content/coursier/core/shaded/sourcecode/Text.class
  Last modified May 29, 2022; size 5512 bytes
  SHA-256 checksum 5082bb7e90477370fe37e96dd67494ce19de1ec998b181310751e05cc30ab50e
  Compiled from "SourceContext.scala"
public class coursier.core.shaded.sourcecode.Text<T extends java.lang.Object> extends java.lang.Object implements scala.Product, java.io.Serializable
  minor version: 0
  major version: 52
  flags: (0x0021) ACC_PUBLIC, ACC_SUPER
  this_class: #2                          // coursier/core/shaded/sourcecode/Text
  super_class: #5                         // java/lang/Object
  interfaces: 2, fields: 2, methods: 18, attributes: 5
Constant pool:
    #1 = Utf8               coursier/core/shaded/sourcecode/Text
    #2 = Class              #1            // coursier/core/shaded/sourcecode/Text
    #3 = Utf8               <T:Ljava/lang/Object;>Ljava/lang/Object;Lscala/Product;Ljava/io/Serializable;
    #4 = Utf8               java/lang/Object
    #5 = Class              #4            // java/lang/Object
    #6 = Utf8               scala/Product
    #7 = Class              #6            // scala/Product
    #8 = Utf8               java/io/Serializable
    #9 = Class              #8            // java/io/Serializable
   #10 = Utf8               SourceContext.scala
   #11 = Utf8               Lscala/reflect/ScalaSignature;
   #12 = Utf8               bytes
   #13 = Utf8               \u0006\u0005\u0005ud\u0001\u0002\r\u001a\u0001rA\u0001b\r\u0001\u0003\u0016\u0004%\t\u0001\u000e\u0005\t\u0001\u0002\u0011\t\u0012)A\u0005k!A\u0011\t\u0001BK\u0002\u0013\u0005!\t\u0003\u0005L\u0001\tE\t\u0015!\u0003D\u0011\u0015a\u0005\u0001\"\u0001N\u0011\u001d\u0011\u0006!!A\u0005\u0002MCqA\u0017\u0001\u0012\u0002\u0013\u00051\fC\u0004i\u0001E\u0005I\u0011A5\t\u000f5\u0004\u0011\u0011!C!]\"9a\u000fAA\u0001\n\u00039\bbB>\u0001\u0003\u0003%\t\u0001 \u0005\t\u007f\u0002\t\t\u0011\"\u0011\u0002\u0002!I\u0011q\u0002\u0001\u0002\u0002\u0013\u0005\u0011\u0011\u0003\u0005\n\u00037\u0001\u0011\u0011!C!\u0003;A\u0011\"!\t\u0001\u0003\u0003%\t%a\t\t\u0013\u0005\u0015\u0002!!A\u0005B\u0005\u001d\u0002\"CA\u0015\u0001\u0005\u0005I\u0011IA\u0016\u000f\u001d\ty#\u0007E\u0001\u0003c1a\u0001G\r\t\u0002\u0005M\u0002B\u0002\'\u0014\t\u0003\t)\u0005C\u0005\u0002HM\t\t\u0011\"!\u0002J!I\u0011qK\n\u0002\u0002\u0013\u0005\u0015\u0011\f\u0005\n\u0003g\u001a\u0012\u0011!C\u0005\u0003k\u0012A\u0001V3yi*\t!$\u0001\u0006t_V\u00148-Z2pI\u0016\u001c\u0001!\u0006\u0002\u001eoM!\u0001A\b\u0013(!\ty\"%D\u0001!\u0015\u0005\t\u0013!B:dC2\f\u0017BA\u0012!\u0005\u0019\te.\u001f*fMB\u0011q$J\u0005\u0003M\u0001\u0012q\u0001\u0015:pIV\u001cG\u000f\u0005\u0002)a9\u0011\u0011F\f\b\u0003U5j\u0011a\u000b\u0006\u0003Ym\ta\u0001\u0010:p_Rt\u0014\"A\u0011\n\u0005=\u0002\u0013a\u00029bG.\fw-Z\u0005\u0003cI\u0012AbU3sS\u0006d\u0017N_1cY\u0016T!a\f\u0011\u0002\u000bY\fG.^3\u0016\u0003U\u0002\"AN\u001c\r\u0001\u0011)\u0001\b\u0001b\u0001s\t\tA+\u0005\u0002;{A\u0011qdO\u0005\u0003y\u0001\u0012qAT8uQ&tw\r\u0005\u0002 }%\u0011q\b\t\u0002\u0004\u0003:L\u0018A\u0002<bYV,\u0007%\u0001\u0004t_V\u00148-Z\u000b\u0002\u0007B\u0011A\t\u0013\b\u0003\u000b\u001a\u0003\"A\u000b\u0011\n\u0005\u001d\u0003\u0013A\u0002)sK\u0012,g-\u0003\u0002J\u0015\n11\u000b\u001e:j]\u001eT!a\u0012\u0011\u0002\u000fM|WO]2fA\u00051A(\u001b8jiz\"2A\u0014)R!\ry\u0005!N\u0007\u00023!)1\'\u0002a\u0001k!)\u0011)\u0002a\u0001\u0007\u0006!1m\u001c9z+\t!v\u000bF\u0002V1f\u00032a\u0014\u0001W!\t1t\u000bB\u00039\r\t\u0007\u0011\bC\u00044\rA\u0005\t\u0019\u0001,\t\u000f\u00053\u0001\u0013!a\u0001\u0007\u0006q1m\u001c9zI\u0011,g-Y;mi\u0012\nTC\u0001/h+\u0005i&FA\u001b_W\u0005y\u0006C\u00011f\u001b\u0005\t\'B\u00012d\u0003%)hn\u00195fG.,GM\u0003\u0002eA\u0005Q\u0011M\u001c8pi\u0006$\u0018n\u001c8\n\u0005\u0019\f\'!E;oG\",7m[3e-\u0006\u0014\u0018.\u00198dK\u0012)\u0001h\u0002b\u0001s\u0005q1m\u001c9zI\u0011,g-Y;mi\u0012\u0012TC\u00016m+\u0005Y\'FA\"_\t\u0015A\u0004B1\u0001:\u00035\u0001(o\u001c3vGR\u0004&/\u001a4jqV\tq\u000e\u0005\u0002qk6\t\u0011O\u0003\u0002sg\u0006!A.\u00198h\u0015\u0005!\u0018\u0001\u00026bm\u0006L!!S9\u0002\u0019A\u0014x\u000eZ;di\u0006\u0013\u0018\u000e^=\u0016\u0003a\u0004\"aH=\n\u0005i\u0004#aA%oi\u0006q\u0001O]8ek\u000e$X\t\\3nK:$HCA\u001f~\u0011\u001dq8\"!AA\u0002a\f1\u0001\u001f\u00132\u0003=\u0001(o\u001c3vGRLE/\u001a:bi>\u0014XCAA\u0002!\u0015\t)!a\u0003>\u001b\t\t9AC\u0002\u0002\n\u0001\n!bY8mY\u0016\u001cG/[8o\u0013\u0011\ti!a\u0002\u0003\u0011%#XM]1u_J\f\u0001bY1o\u000bF,\u0018\r\u001c\u000b\u0005\u0003\'\tI\u0002E\u0002 \u0003+I1!a\u0006!\u0005\u001d\u0011un\u001c7fC:DqA`\u0007\u0002\u0002\u0003\u0007Q(\u0001\nqe>$Wo\u0019;FY\u0016lWM\u001c;OC6,GcA8\u0002 !9aPDA\u0001\u0002\u0004A\u0018\u0001\u00035bg\"\u001cu\u000eZ3\u0015\u0003a\f\u0001\u0002^8TiJLgn\u001a\u000b\u0002_\u00061Q-];bYN$B!a\u0005\u0002.!9a0EA\u0001\u0002\u0004i\u0014\u0001\u0002+fqR\u0004\"aT\n\u0014\rMq\u0012QGA\u001e!\ry\u0015qG\u0005\u0004\u0003sI\"A\u0003+fqRl\u0015m\u0019:pgB!\u0011QHA\"\u001b\t\tyDC\u0002\u0002BM\f!![8\n\u0007E\ny\u0004\u0006\u0002\u00022\u0005)\u0011\r\u001d9msV!\u00111JA))\u0019\ti%a\u0015\u0002VA!q\nAA(!\r1\u0014\u0011\u000b\u0003\u0006qU\u0011\r!\u000f\u0005\u0007gU\u0001\r!a\u0014\t\u000b\u0005+\u0002\u0019A\"\u0002\u000fUt\u0017\r\u001d9msV!\u00111LA6)\u0011\ti&!\u001c\u0011\u000b}\ty&a\u0019\n\u0007\u0005\u0005\u0004E\u0001\u0004PaRLwN\u001c\t\u0007?\u0005\u0015\u0014\u0011N\"\n\u0007\u0005\u001d\u0004E\u0001\u0004UkBdWM\r\t\u0004m\u0005-D!\u0002\u001d\u0017\u0005\u0004I\u0004\"CA8-\u0005\u0005\t\u0019AA9\u0003\rAH\u0005\r\t\u0005\u001f\u0002\tI\'\u0001\u0007xe&$XMU3qY\u0006\u001cW\r\u0006\u0002\u0002xA\u0019\u0001/!\u001f\n\u0007\u0005m\u0014O\u0001\u0004PE*,7\r\u001e
   #14 = Utf8               value
   #15 = Utf8               Ljava/lang/Object;
   #16 = Utf8               TT;
   #17 = Utf8               source
   #18 = Utf8               Ljava/lang/String;
   #19 = Utf8               unapply
   #20 = Utf8               (Lcoursier/core/shaded/sourcecode/Text;)Lscala/Option;
   #21 = Utf8               <T:Ljava/lang/Object;>(Lcoursier/core/shaded/sourcecode/Text<TT;>;)Lscala/Option<Lscala/Tuple2<TT;Ljava/lang/String;>;>;
   #22 = Utf8               x$0
   #23 = Utf8               coursier/core/shaded/sourcecode/Text$
   #24 = Class              #23           // coursier/core/shaded/sourcecode/Text$
   #25 = Utf8               MODULE$
   #26 = Utf8               Lcoursier/core/shaded/sourcecode/Text$;
   #27 = NameAndType        #25:#26       // MODULE$:Lcoursier/core/shaded/sourcecode/Text$;
   #28 = Fieldref           #24.#27       // coursier/core/shaded/sourcecode/Text$.MODULE$:Lcoursier/core/shaded/sourcecode/Text$;
   #29 = NameAndType        #19:#20       // unapply:(Lcoursier/core/shaded/sourcecode/Text;)Lscala/Option;
   #30 = Methodref          #24.#29       // coursier/core/shaded/sourcecode/Text$.unapply:(Lcoursier/core/shaded/sourcecode/Text;)Lscala/Option;
   #31 = Utf8               apply
   #32 = Utf8               (Ljava/lang/Object;Ljava/lang/String;)Lcoursier/core/shaded/sourcecode/Text;
   #33 = Utf8               <T:Ljava/lang/Object;>(TT;Ljava/lang/String;)Lcoursier/core/shaded/sourcecode/Text<TT;>;
   #34 = NameAndType        #31:#32       // apply:(Ljava/lang/Object;Ljava/lang/String;)Lcoursier/core/shaded/sourcecode/Text;
   #35 = Methodref          #24.#34       // coursier/core/shaded/sourcecode/Text$.apply:(Ljava/lang/Object;Ljava/lang/String;)Lcoursier/core/shaded/sourcecode/Text;
   #36 = Utf8               productElementNames
   #37 = Utf8               ()Lscala/collection/Iterator;
   #38 = Utf8               ()Lscala/collection/Iterator<Ljava/lang/String;>;
   #39 = Utf8               productElementNames$
   #40 = Utf8               (Lscala/Product;)Lscala/collection/Iterator;
   #41 = NameAndType        #39:#40       // productElementNames$:(Lscala/Product;)Lscala/collection/Iterator;
   #42 = InterfaceMethodref #7.#41        // scala/Product.productElementNames$:(Lscala/Product;)Lscala/collection/Iterator;
   #43 = Utf8               this
   #44 = Utf8               Lcoursier/core/shaded/sourcecode/Text;
   #45 = Utf8               ()Ljava/lang/Object;
   #46 = Utf8               ()TT;
   #47 = NameAndType        #14:#15       // value:Ljava/lang/Object;
   #48 = Fieldref           #2.#47        // coursier/core/shaded/sourcecode/Text.value:Ljava/lang/Object;
   #49 = Utf8               ()Ljava/lang/String;
   #50 = NameAndType        #17:#18       // source:Ljava/lang/String;
   #51 = Fieldref           #2.#50        // coursier/core/shaded/sourcecode/Text.source:Ljava/lang/String;
   #52 = Utf8               copy
   #53 = Utf8               <init>
   #54 = Utf8               (Ljava/lang/Object;Ljava/lang/String;)V
   #55 = NameAndType        #53:#54       // "<init>":(Ljava/lang/Object;Ljava/lang/String;)V
   #56 = Methodref          #2.#55        // coursier/core/shaded/sourcecode/Text."<init>":(Ljava/lang/Object;Ljava/lang/String;)V
   #57 = Utf8               copy$default$1
   #58 = Utf8               <T:Ljava/lang/Object;>()TT;
   #59 = NameAndType        #14:#45       // value:()Ljava/lang/Object;
   #60 = Methodref          #2.#59        // coursier/core/shaded/sourcecode/Text.value:()Ljava/lang/Object;
   #61 = Utf8               copy$default$2
   #62 = Utf8               <T:Ljava/lang/Object;>()Ljava/lang/String;
   #63 = NameAndType        #17:#49       // source:()Ljava/lang/String;
   #64 = Methodref          #2.#63        // coursier/core/shaded/sourcecode/Text.source:()Ljava/lang/String;
   #65 = Utf8               productPrefix
   #66 = Utf8               Text
   #67 = String             #66           // Text
   #68 = Utf8               productArity
   #69 = Utf8               ()I
   #70 = Utf8               productElement
   #71 = Utf8               (I)Ljava/lang/Object;
   #72 = Utf8               x$1
   #73 = Utf8               scala/runtime/Statics
   #74 = Class              #73           // scala/runtime/Statics
   #75 = Utf8               ioobe
   #76 = NameAndType        #75:#71       // ioobe:(I)Ljava/lang/Object;
   #77 = Methodref          #74.#76       // scala/runtime/Statics.ioobe:(I)Ljava/lang/Object;
   #78 = Utf8               I
   #79 = Utf8               productIterator
   #80 = Utf8               ()Lscala/collection/Iterator<Ljava/lang/Object;>;
   #81 = Utf8               scala/runtime/ScalaRunTime$
   #82 = Class              #81           // scala/runtime/ScalaRunTime$
   #83 = Utf8               Lscala/runtime/ScalaRunTime$;
   #84 = NameAndType        #25:#83       // MODULE$:Lscala/runtime/ScalaRunTime$;
   #85 = Fieldref           #82.#84       // scala/runtime/ScalaRunTime$.MODULE$:Lscala/runtime/ScalaRunTime$;
   #86 = Utf8               typedProductIterator
   #87 = NameAndType        #86:#40       // typedProductIterator:(Lscala/Product;)Lscala/collection/Iterator;
   #88 = Methodref          #82.#87       // scala/runtime/ScalaRunTime$.typedProductIterator:(Lscala/Product;)Lscala/collection/Iterator;
   #89 = Utf8               canEqual
   #90 = Utf8               (Ljava/lang/Object;)Z
   #91 = Utf8               productElementName
   #92 = Utf8               (I)Ljava/lang/String;
   #93 = String             #14           // value
   #94 = String             #17           // source
   #95 = Utf8               java/lang/String
   #96 = Class              #95           // java/lang/String
   #97 = Utf8               hashCode
   #98 = Utf8               _hashCode
   #99 = Utf8               (Lscala/Product;)I
  #100 = NameAndType        #98:#99       // _hashCode:(Lscala/Product;)I
  #101 = Methodref          #82.#100      // scala/runtime/ScalaRunTime$._hashCode:(Lscala/Product;)I
  #102 = Utf8               toString
  #103 = Utf8               _toString
  #104 = Utf8               (Lscala/Product;)Ljava/lang/String;
  #105 = NameAndType        #103:#104     // _toString:(Lscala/Product;)Ljava/lang/String;
  #106 = Methodref          #82.#105      // scala/runtime/ScalaRunTime$._toString:(Lscala/Product;)Ljava/lang/String;
  #107 = Utf8               equals
  #108 = Utf8               scala/runtime/BoxesRunTime
  #109 = Class              #108          // scala/runtime/BoxesRunTime
  #110 = Utf8               (Ljava/lang/Object;Ljava/lang/Object;)Z
  #111 = NameAndType        #107:#110     // equals:(Ljava/lang/Object;Ljava/lang/Object;)Z
  #112 = Methodref          #109.#111     // scala/runtime/BoxesRunTime.equals:(Ljava/lang/Object;Ljava/lang/Object;)Z
  #113 = NameAndType        #107:#90      // equals:(Ljava/lang/Object;)Z
  #114 = Methodref          #5.#113       // java/lang/Object.equals:(Ljava/lang/Object;)Z
  #115 = NameAndType        #89:#90       // canEqual:(Ljava/lang/Object;)Z
  #116 = Methodref          #2.#115       // coursier/core/shaded/sourcecode/Text.canEqual:(Ljava/lang/Object;)Z
  #117 = Utf8               (TT;Ljava/lang/String;)V
  #118 = Utf8               ()V
  #119 = NameAndType        #53:#118      // "<init>":()V
  #120 = Methodref          #5.#119       // java/lang/Object."<init>":()V
  #121 = Utf8               $init$
  #122 = Utf8               (Lscala/Product;)V
  #123 = NameAndType        #121:#122     // $init$:(Lscala/Product;)V
  #124 = InterfaceMethodref #7.#123       // scala/Product.$init$:(Lscala/Product;)V
  #125 = Utf8               Signature
  #126 = Utf8               Code
  #127 = Utf8               MethodParameters
  #128 = Utf8               LineNumberTable
  #129 = Utf8               LocalVariableTable
  #130 = Utf8               StackMapTable
  #131 = Utf8               SourceFile
  #132 = Utf8               RuntimeVisibleAnnotations
  #133 = Utf8               ScalaInlineInfo
  #134 = Utf8               ScalaSig
{
  private final T value;
    descriptor: Ljava/lang/Object;
    flags: (0x0012) ACC_PRIVATE, ACC_FINAL
    Signature: #16                          // TT;

  private final java.lang.String source;
    descriptor: Ljava/lang/String;
    flags: (0x0012) ACC_PRIVATE, ACC_FINAL

  public static <T extends java.lang.Object> scala.Option<scala.Tuple2<T, java.lang.String>> unapply(coursier.core.shaded.sourcecode.Text<T>);
    descriptor: (Lcoursier/core/shaded/sourcecode/Text;)Lscala/Option;
    flags: (0x0009) ACC_PUBLIC, ACC_STATIC
    Code:
      stack=2, locals=1, args_size=1
         0: getstatic     #28                 // Field coursier/core/shaded/sourcecode/Text$.MODULE$:Lcoursier/core/shaded/sourcecode/Text$;
         3: aload_0
         4: invokevirtual #30                 // Method coursier/core/shaded/sourcecode/Text$.unapply:(Lcoursier/core/shaded/sourcecode/Text;)Lscala/Option;
         7: areturn
    Signature: #21                          // <T:Ljava/lang/Object;>(Lcoursier/core/shaded/sourcecode/Text<TT;>;)Lscala/Option<Lscala/Tuple2<TT;Ljava/lang/String;>;>;
    MethodParameters:
      Name                           Flags
      x$0                            final

  public static <T extends java.lang.Object> coursier.core.shaded.sourcecode.Text<T> apply(T, java.lang.String);
    descriptor: (Ljava/lang/Object;Ljava/lang/String;)Lcoursier/core/shaded/sourcecode/Text;
    flags: (0x0009) ACC_PUBLIC, ACC_STATIC
    Code:
      stack=3, locals=2, args_size=2
         0: getstatic     #28                 // Field coursier/core/shaded/sourcecode/Text$.MODULE$:Lcoursier/core/shaded/sourcecode/Text$;
         3: aload_0
         4: aload_1
         5: invokevirtual #35                 // Method coursier/core/shaded/sourcecode/Text$.apply:(Ljava/lang/Object;Ljava/lang/String;)Lcoursier/core/shaded/sourcecode/Text;
         8: areturn
    Signature: #33                          // <T:Ljava/lang/Object;>(TT;Ljava/lang/String;)Lcoursier/core/shaded/sourcecode/Text<TT;>;
    MethodParameters:
      Name                           Flags
      value                          final
      source                         final

  public scala.collection.Iterator<java.lang.String> productElementNames();
    descriptor: ()Lscala/collection/Iterator;
    flags: (0x0001) ACC_PUBLIC
    Code:
      stack=1, locals=1, args_size=1
         0: aload_0
         1: invokestatic  #42                 // InterfaceMethod scala/Product.productElementNames$:(Lscala/Product;)Lscala/collection/Iterator;
         4: areturn
      LineNumberTable:
        line 41: 0
      LocalVariableTable:
        Start  Length  Slot  Name   Signature
            0       5     0  this   Lcoursier/core/shaded/sourcecode/Text;
    Signature: #38                          // ()Lscala/collection/Iterator<Ljava/lang/String;>;

  public T value();
    descriptor: ()Ljava/lang/Object;
    flags: (0x0001) ACC_PUBLIC
    Code:
      stack=1, locals=1, args_size=1
         0: aload_0
         1: getfield      #48                 // Field value:Ljava/lang/Object;
         4: areturn
      LineNumberTable:
        line 41: 0
      LocalVariableTable:
        Start  Length  Slot  Name   Signature
            0       5     0  this   Lcoursier/core/shaded/sourcecode/Text;
    Signature: #46                          // ()TT;

  public java.lang.String source();
    descriptor: ()Ljava/lang/String;
    flags: (0x0001) ACC_PUBLIC
    Code:
      stack=1, locals=1, args_size=1
         0: aload_0
         1: getfield      #51                 // Field source:Ljava/lang/String;
         4: areturn
      LineNumberTable:
        line 41: 0
      LocalVariableTable:
        Start  Length  Slot  Name   Signature
            0       5     0  this   Lcoursier/core/shaded/sourcecode/Text;

  public <T extends java.lang.Object> coursier.core.shaded.sourcecode.Text<T> copy(T, java.lang.String);
    descriptor: (Ljava/lang/Object;Ljava/lang/String;)Lcoursier/core/shaded/sourcecode/Text;
    flags: (0x0001) ACC_PUBLIC
    Code:
      stack=4, locals=3, args_size=3
         0: new           #2                  // class coursier/core/shaded/sourcecode/Text
         3: dup
         4: aload_1
         5: aload_2
         6: invokespecial #56                 // Method "<init>":(Ljava/lang/Object;Ljava/lang/String;)V
         9: areturn
      LineNumberTable:
        line 41: 0
      LocalVariableTable:
        Start  Length  Slot  Name   Signature
            0      10     0  this   Lcoursier/core/shaded/sourcecode/Text;
            0      10     1 value   Ljava/lang/Object;
            0      10     2 source   Ljava/lang/String;
    Signature: #33                          // <T:Ljava/lang/Object;>(TT;Ljava/lang/String;)Lcoursier/core/shaded/sourcecode/Text<TT;>;
    MethodParameters:
      Name                           Flags
      value                          final
      source                         final

  public <T extends java.lang.Object> T copy$default$1();
    descriptor: ()Ljava/lang/Object;
    flags: (0x0001) ACC_PUBLIC
    Code:
      stack=1, locals=1, args_size=1
         0: aload_0
         1: invokevirtual #60                 // Method value:()Ljava/lang/Object;
         4: areturn
      LineNumberTable:
        line 41: 0
      LocalVariableTable:
        Start  Length  Slot  Name   Signature
            0       5     0  this   Lcoursier/core/shaded/sourcecode/Text;
    Signature: #58                          // <T:Ljava/lang/Object;>()TT;

  public <T extends java.lang.Object> java.lang.String copy$default$2();
    descriptor: ()Ljava/lang/String;
    flags: (0x0001) ACC_PUBLIC
    Code:
      stack=1, locals=1, args_size=1
         0: aload_0
         1: invokevirtual #64                 // Method source:()Ljava/lang/String;
         4: areturn
      LineNumberTable:
        line 41: 0
      LocalVariableTable:
        Start  Length  Slot  Name   Signature
            0       5     0  this   Lcoursier/core/shaded/sourcecode/Text;
    Signature: #62                          // <T:Ljava/lang/Object;>()Ljava/lang/String;

  public java.lang.String productPrefix();
    descriptor: ()Ljava/lang/String;
    flags: (0x0001) ACC_PUBLIC
    Code:
      stack=1, locals=1, args_size=1
         0: ldc           #67                 // String Text
         2: areturn
      LineNumberTable:
        line 41: 0
      LocalVariableTable:
        Start  Length  Slot  Name   Signature
            0       3     0  this   Lcoursier/core/shaded/sourcecode/Text;

  public int productArity();
    descriptor: ()I
    flags: (0x0001) ACC_PUBLIC
    Code:
      stack=1, locals=1, args_size=1
         0: iconst_2
         1: ireturn
      LineNumberTable:
        line 41: 0
      LocalVariableTable:
        Start  Length  Slot  Name   Signature
            0       2     0  this   Lcoursier/core/shaded/sourcecode/Text;

  public java.lang.Object productElement(int);
    descriptor: (I)Ljava/lang/Object;
    flags: (0x0001) ACC_PUBLIC
    Code:
      stack=1, locals=3, args_size=2
         0: iload_1
         1: istore_2
         2: iload_2
         3: tableswitch   { // 0 to 1
                       0: 24
                       1: 31
                 default: 38
            }
        24: aload_0
        25: invokevirtual #60                 // Method value:()Ljava/lang/Object;
        28: goto          45
        31: aload_0
        32: invokevirtual #64                 // Method source:()Ljava/lang/String;
        35: goto          45
        38: iload_1
        39: invokestatic  #77                 // Method scala/runtime/Statics.ioobe:(I)Ljava/lang/Object;
        42: goto          45
        45: areturn
      StackMapTable: number_of_entries = 4
        frame_type = 252 /* append */
          offset_delta = 24
          locals = [ int ]
        frame_type = 6 /* same */
        frame_type = 6 /* same */
        frame_type = 70 /* same_locals_1_stack_item */
          stack = [ class java/lang/Object ]
      LineNumberTable:
        line 41: 0
      LocalVariableTable:
        Start  Length  Slot  Name   Signature
            0      46     0  this   Lcoursier/core/shaded/sourcecode/Text;
            0      46     1   x$1   I
    MethodParameters:
      Name                           Flags
      x$1                            final

  public scala.collection.Iterator<java.lang.Object> productIterator();
    descriptor: ()Lscala/collection/Iterator;
    flags: (0x0001) ACC_PUBLIC
    Code:
      stack=2, locals=1, args_size=1
         0: getstatic     #85                 // Field scala/runtime/ScalaRunTime$.MODULE$:Lscala/runtime/ScalaRunTime$;
         3: aload_0
         4: invokevirtual #88                 // Method scala/runtime/ScalaRunTime$.typedProductIterator:(Lscala/Product;)Lscala/collection/Iterator;
         7: areturn
      LineNumberTable:
        line 41: 0
      LocalVariableTable:
        Start  Length  Slot  Name   Signature
            0       8     0  this   Lcoursier/core/shaded/sourcecode/Text;
    Signature: #80                          // ()Lscala/collection/Iterator<Ljava/lang/Object;>;

  public boolean canEqual(java.lang.Object);
    descriptor: (Ljava/lang/Object;)Z
    flags: (0x0001) ACC_PUBLIC
    Code:
      stack=1, locals=2, args_size=2
         0: aload_1
         1: instanceof    #2                  // class coursier/core/shaded/sourcecode/Text
         4: ireturn
      LineNumberTable:
        line 41: 0
      LocalVariableTable:
        Start  Length  Slot  Name   Signature
            0       5     0  this   Lcoursier/core/shaded/sourcecode/Text;
            0       5     1   x$1   Ljava/lang/Object;
    MethodParameters:
      Name                           Flags
      x$1                            final

  public java.lang.String productElementName(int);
    descriptor: (I)Ljava/lang/String;
    flags: (0x0001) ACC_PUBLIC
    Code:
      stack=1, locals=3, args_size=2
         0: iload_1
         1: istore_2
         2: iload_2
         3: tableswitch   { // 0 to 1
                       0: 24
                       1: 29
                 default: 34
            }
        24: ldc           #93                 // String value
        26: goto          44
        29: ldc           #94                 // String source
        31: goto          44
        34: iload_1
        35: invokestatic  #77                 // Method scala/runtime/Statics.ioobe:(I)Ljava/lang/Object;
        38: checkcast     #96                 // class java/lang/String
        41: goto          44
        44: areturn
      StackMapTable: number_of_entries = 4
        frame_type = 252 /* append */
          offset_delta = 24
          locals = [ int ]
        frame_type = 4 /* same */
        frame_type = 4 /* same */
        frame_type = 73 /* same_locals_1_stack_item */
          stack = [ class java/lang/String ]
      LineNumberTable:
        line 41: 0
      LocalVariableTable:
        Start  Length  Slot  Name   Signature
            0      45     0  this   Lcoursier/core/shaded/sourcecode/Text;
            0      45     1   x$1   I
    MethodParameters:
      Name                           Flags
      x$1                            final

  public int hashCode();
    descriptor: ()I
    flags: (0x0001) ACC_PUBLIC
    Code:
      stack=2, locals=1, args_size=1
         0: getstatic     #85                 // Field scala/runtime/ScalaRunTime$.MODULE$:Lscala/runtime/ScalaRunTime$;
         3: aload_0
         4: invokevirtual #101                // Method scala/runtime/ScalaRunTime$._hashCode:(Lscala/Product;)I
         7: ireturn
      LineNumberTable:
        line 41: 0
      LocalVariableTable:
        Start  Length  Slot  Name   Signature
            0       8     0  this   Lcoursier/core/shaded/sourcecode/Text;

  public java.lang.String toString();
    descriptor: ()Ljava/lang/String;
    flags: (0x0001) ACC_PUBLIC
    Code:
      stack=2, locals=1, args_size=1
         0: getstatic     #85                 // Field scala/runtime/ScalaRunTime$.MODULE$:Lscala/runtime/ScalaRunTime$;
         3: aload_0
         4: invokevirtual #106                // Method scala/runtime/ScalaRunTime$._toString:(Lscala/Product;)Ljava/lang/String;
         7: areturn
      LineNumberTable:
        line 41: 0
      LocalVariableTable:
        Start  Length  Slot  Name   Signature
            0       8     0  this   Lcoursier/core/shaded/sourcecode/Text;

  public boolean equals(java.lang.Object);
    descriptor: (Ljava/lang/Object;)Z
    flags: (0x0001) ACC_PUBLIC
    Code:
      stack=2, locals=6, args_size=2
         0: aload_0
         1: aload_1
         2: if_acmpeq     101
         5: aload_1
         6: astore_3
         7: aload_3
         8: instanceof    #2                  // class coursier/core/shaded/sourcecode/Text
        11: ifeq          19
        14: iconst_1
        15: istore_2
        16: goto          27
        19: goto          22
        22: iconst_0
        23: istore_2
        24: goto          27
        27: iload_2
        28: ifeq          105
        31: aload_1
        32: checkcast     #2                  // class coursier/core/shaded/sourcecode/Text
        35: astore        4
        37: aload_0
        38: invokevirtual #60                 // Method value:()Ljava/lang/Object;
        41: aload         4
        43: invokevirtual #60                 // Method value:()Ljava/lang/Object;
        46: invokestatic  #112                // Method scala/runtime/BoxesRunTime.equals:(Ljava/lang/Object;Ljava/lang/Object;)Z
        49: ifeq          97
        52: aload_0
        53: invokevirtual #64                 // Method source:()Ljava/lang/String;
        56: aload         4
        58: invokevirtual #64                 // Method source:()Ljava/lang/String;
        61: astore        5
        63: dup
        64: ifnonnull     76
        67: pop
        68: aload         5
        70: ifnull        84
        73: goto          97
        76: aload         5
        78: invokevirtual #114                // Method java/lang/Object.equals:(Ljava/lang/Object;)Z
        81: ifeq          97
        84: aload         4
        86: aload_0
        87: invokevirtual #116                // Method canEqual:(Ljava/lang/Object;)Z
        90: ifeq          97
        93: iconst_1
        94: goto          98
        97: iconst_0
        98: ifeq          105
       101: iconst_1
       102: goto          106
       105: iconst_0
       106: ireturn
      StackMapTable: number_of_entries = 10
        frame_type = 253 /* append */
          offset_delta = 19
          locals = [ top, class java/lang/Object ]
        frame_type = 2 /* same */
        frame_type = 255 /* full_frame */
          offset_delta = 4
          locals = [ class coursier/core/shaded/sourcecode/Text, class java/lang/Object, int, class java/lang/Object ]
          stack = []
        frame_type = 255 /* full_frame */
          offset_delta = 48
          locals = [ class coursier/core/shaded/sourcecode/Text, class java/lang/Object, int, class java/lang/Object, class coursier/core/shaded/sourcecode/Text, class java/lang/String ]
          stack = [ class java/lang/String ]
        frame_type = 7 /* same */
        frame_type = 250 /* chop */
          offset_delta = 12
        frame_type = 64 /* same_locals_1_stack_item */
          stack = [ int ]
        frame_type = 248 /* chop */
          offset_delta = 2
        frame_type = 253 /* append */
          offset_delta = 3
          locals = [ int, class java/lang/Object ]
        frame_type = 255 /* full_frame */
          offset_delta = 0
          locals = [ class coursier/core/shaded/sourcecode/Text, class java/lang/Object ]
          stack = [ int ]
      LineNumberTable:
        line 41: 0
      LocalVariableTable:
        Start  Length  Slot  Name   Signature
            0     107     0  this   Lcoursier/core/shaded/sourcecode/Text;
            0     107     1   x$1   Ljava/lang/Object;
    MethodParameters:
      Name                           Flags
      x$1                            final

  public coursier.core.shaded.sourcecode.Text(T, java.lang.String);
    descriptor: (Ljava/lang/Object;Ljava/lang/String;)V
    flags: (0x0001) ACC_PUBLIC
    Code:
      stack=2, locals=3, args_size=3
         0: aload_0
         1: aload_1
         2: putfield      #48                 // Field value:Ljava/lang/Object;
         5: aload_0
         6: aload_2
         7: putfield      #51                 // Field source:Ljava/lang/String;
        10: aload_0
        11: invokespecial #120                // Method java/lang/Object."<init>":()V
        14: aload_0
        15: invokestatic  #124                // InterfaceMethod scala/Product.$init$:(Lscala/Product;)V
        18: return
      LineNumberTable:
        line 41: 0
      LocalVariableTable:
        Start  Length  Slot  Name   Signature
            0      19     0  this   Lcoursier/core/shaded/sourcecode/Text;
            0      19     1 value   Ljava/lang/Object;
            0      19     2 source   Ljava/lang/String;
    Signature: #117                         // (TT;Ljava/lang/String;)V
    MethodParameters:
      Name                           Flags
      value                          final
      source                         final
}
Signature: #3                           // <T:Ljava/lang/Object;>Ljava/lang/Object;Lscala/Product;Ljava/io/Serializable;
SourceFile: "SourceContext.scala"
RuntimeVisibleAnnotations:
  0: #11(#12=s#13)
    scala.reflect.ScalaSignature(
      bytes="\u0006\u0005\u0005ud\u0001\u0002\r\u001a\u0001rA\u0001b\r\u0001\u0003\u0016\u0004%\t\u0001\u000e\u0005\t\u0001\u0002\u0011\t\u0012)A\u0005k!A\u0011\t\u0001BK\u0002\u0013\u0005!\t\u0003\u0005L\u0001\tE\t\u0015!\u0003D\u0011\u0015a\u0005\u0001\"\u0001N\u0011\u001d\u0011\u0006!!A\u0005\u0002MCqA\u0017\u0001\u0012\u0002\u0013\u00051\fC\u0004i\u0001E\u0005I\u0011A5\t\u000f5\u0004\u0011\u0011!C!]\"9a\u000fAA\u0001\n\u00039\bbB>\u0001\u0003\u0003%\t\u0001 \u0005\t\u007f\u0002\t\t\u0011\"\u0011\u0002\u0002!I\u0011q\u0002\u0001\u0002\u0002\u0013\u0005\u0011\u0011\u0003\u0005\n\u00037\u0001\u0011\u0011!C!\u0003;A\u0011\"!\t\u0001\u0003\u0003%\t%a\t\t\u0013\u0005\u0015\u0002!!A\u0005B\u0005\u001d\u0002\"CA\u0015\u0001\u0005\u0005I\u0011IA\u0016\u000f\u001d\ty#\u0007E\u0001\u0003c1a\u0001G\r\t\u0002\u0005M\u0002B\u0002\'\u0014\t\u0003\t)\u0005C\u0005\u0002HM\t\t\u0011\"!\u0002J!I\u0011qK\n\u0002\u0002\u0013\u0005\u0015\u0011\f\u0005\n\u0003g\u001a\u0012\u0011!C\u0005\u0003k\u0012A\u0001V3yi*\t!$\u0001\u0006t_V\u00148-Z2pI\u0016\u001c\u0001!\u0006\u0002\u001eoM!\u0001A\b\u0013(!\ty\"%D\u0001!\u0015\u0005\t\u0013!B:dC2\f\u0017BA\u0012!\u0005\u0019\te.\u001f*fMB\u0011q$J\u0005\u0003M\u0001\u0012q\u0001\u0015:pIV\u001cG\u000f\u0005\u0002)a9\u0011\u0011F\f\b\u0003U5j\u0011a\u000b\u0006\u0003Ym\ta\u0001\u0010:p_Rt\u0014\"A\u0011\n\u0005=\u0002\u0013a\u00029bG.\fw-Z\u0005\u0003cI\u0012AbU3sS\u0006d\u0017N_1cY\u0016T!a\f\u0011\u0002\u000bY\fG.^3\u0016\u0003U\u0002\"AN\u001c\r\u0001\u0011)\u0001\b\u0001b\u0001s\t\tA+\u0005\u0002;{A\u0011qdO\u0005\u0003y\u0001\u0012qAT8uQ&tw\r\u0005\u0002 }%\u0011q\b\t\u0002\u0004\u0003:L\u0018A\u0002<bYV,\u0007%\u0001\u0004t_V\u00148-Z\u000b\u0002\u0007B\u0011A\t\u0013\b\u0003\u000b\u001a\u0003\"A\u000b\u0011\n\u0005\u001d\u0003\u0013A\u0002)sK\u0012,g-\u0003\u0002J\u0015\n11\u000b\u001e:j]\u001eT!a\u0012\u0011\u0002\u000fM|WO]2fA\u00051A(\u001b8jiz\"2A\u0014)R!\ry\u0005!N\u0007\u00023!)1\'\u0002a\u0001k!)\u0011)\u0002a\u0001\u0007\u0006!1m\u001c9z+\t!v\u000bF\u0002V1f\u00032a\u0014\u0001W!\t1t\u000bB\u00039\r\t\u0007\u0011\bC\u00044\rA\u0005\t\u0019\u0001,\t\u000f\u00053\u0001\u0013!a\u0001\u0007\u0006q1m\u001c9zI\u0011,g-Y;mi\u0012\nTC\u0001/h+\u0005i&FA\u001b_W\u0005y\u0006C\u00011f\u001b\u0005\t\'B\u00012d\u0003%)hn\u00195fG.,GM\u0003\u0002eA\u0005Q\u0011M\u001c8pi\u0006$\u0018n\u001c8\n\u0005\u0019\f\'!E;oG\",7m[3e-\u0006\u0014\u0018.\u00198dK\u0012)\u0001h\u0002b\u0001s\u0005q1m\u001c9zI\u0011,g-Y;mi\u0012\u0012TC\u00016m+\u0005Y\'FA\"_\t\u0015A\u0004B1\u0001:\u00035\u0001(o\u001c3vGR\u0004&/\u001a4jqV\tq\u000e\u0005\u0002qk6\t\u0011O\u0003\u0002sg\u0006!A.\u00198h\u0015\u0005!\u0018\u0001\u00026bm\u0006L!!S9\u0002\u0019A\u0014x\u000eZ;di\u0006\u0013\u0018\u000e^=\u0016\u0003a\u0004\"aH=\n\u0005i\u0004#aA%oi\u0006q\u0001O]8ek\u000e$X\t\\3nK:$HCA\u001f~\u0011\u001dq8\"!AA\u0002a\f1\u0001\u001f\u00132\u0003=\u0001(o\u001c3vGRLE/\u001a:bi>\u0014XCAA\u0002!\u0015\t)!a\u0003>\u001b\t\t9AC\u0002\u0002\n\u0001\n!bY8mY\u0016\u001cG/[8o\u0013\u0011\ti!a\u0002\u0003\u0011%#XM]1u_J\f\u0001bY1o\u000bF,\u0018\r\u001c\u000b\u0005\u0003\'\tI\u0002E\u0002 \u0003+I1!a\u0006!\u0005\u001d\u0011un\u001c7fC:DqA`\u0007\u0002\u0002\u0003\u0007Q(\u0001\nqe>$Wo\u0019;FY\u0016lWM\u001c;OC6,GcA8\u0002 !9aPDA\u0001\u0002\u0004A\u0018\u0001\u00035bg\"\u001cu\u000eZ3\u0015\u0003a\f\u0001\u0002^8TiJLgn\u001a\u000b\u0002_\u00061Q-];bYN$B!a\u0005\u0002.!9a0EA\u0001\u0002\u0004i\u0014\u0001\u0002+fqR\u0004\"aT\n\u0014\rMq\u0012QGA\u001e!\ry\u0015qG\u0005\u0004\u0003sI\"A\u0003+fqRl\u0015m\u0019:pgB!\u0011QHA\"\u001b\t\tyDC\u0002\u0002BM\f!![8\n\u0007E\ny\u0004\u0006\u0002\u00022\u0005)\u0011\r\u001d9msV!\u00111JA))\u0019\ti%a\u0015\u0002VA!q\nAA(!\r1\u0014\u0011\u000b\u0003\u0006qU\u0011\r!\u000f\u0005\u0007gU\u0001\r!a\u0014\t\u000b\u0005+\u0002\u0019A\"\u0002\u000fUt\u0017\r\u001d9msV!\u00111LA6)\u0011\ti&!\u001c\u0011\u000b}\ty&a\u0019\n\u0007\u0005\u0005\u0004E\u0001\u0004PaRLwN\u001c\t\u0007?\u0005\u0015\u0014\u0011N\"\n\u0007\u0005\u001d\u0004E\u0001\u0004UkBdWM\r\t\u0004m\u0005-D!\u0002\u001d\u0017\u0005\u0004I\u0004\"CA8-\u0005\u0005\t\u0019AA9\u0003\rAH\u0005\r\t\u0005\u001f\u0002\tI\'\u0001\u0007xe&$XMU3qY\u0006\u001cW\r\u0006\u0002\u0002xA\u0019\u0001/!\u001f\n\u0007\u0005m\u0014O\u0001\u0004PE*,7\r\u001e"
    )
  ScalaInlineInfo: length = 0x54 (unknown attribute)
   01 00 00 10 00 35 00 36 00 00 59 00 5A 00 00 34
   00 20 00 00 39 00 2D 00 00 3D 00 31 00 00 6B 00
   5A 00 00 61 00 45 00 00 44 00 45 00 00 46 00 47
   00 00 5B 00 5C 00 00 24 00 25 00 00 4F 00 25 00
   00 41 00 31 00 00 11 00 31 00 00 66 00 31 00 00
   0E 00 2D 00
  ScalaSig: length = 0x3 (unknown attribute)
   05 02 00
