Classfile /Users/mw/Projects/slang-braindump/.jar/jar11/assemble/slang-braindump/assemble/content/scala/concurrent/duration/Duration$$anon$2.class
  Last modified May 29, 2022; size 1671 bytes
  SHA-256 checksum c48079b795c9c859e854fdb8a702a9a1c929ed07b9904983f4594c3f22d3ecde
  Compiled from "Duration.scala"
public final class scala.concurrent.duration.Duration$$anon$2 extends scala.concurrent.duration.Duration$Infinite
  minor version: 0
  major version: 52
  flags: (0x0031) ACC_PUBLIC, ACC_FINAL, ACC_SUPER
  this_class: #2                          // scala/concurrent/duration/Duration$$anon$2
  super_class: #4                         // scala/concurrent/duration/Duration$Infinite
  interfaces: 0, fields: 0, methods: 7, attributes: 5
Constant pool:
   #1 = Utf8               scala/concurrent/duration/Duration$$anon$2
   #2 = Class              #1             // scala/concurrent/duration/Duration$$anon$2
   #3 = Utf8               scala/concurrent/duration/Duration$Infinite
   #4 = Class              #3             // scala/concurrent/duration/Duration$Infinite
   #5 = Utf8               Duration.scala
   #6 = Utf8               scala/concurrent/duration/Duration$
   #7 = Class              #6             // scala/concurrent/duration/Duration$
   #8 = Utf8               scala/concurrent/duration/Duration
   #9 = Class              #8             // scala/concurrent/duration/Duration
  #10 = Utf8               Infinite
  #11 = Utf8               toString
  #12 = Utf8               ()Ljava/lang/String;
  #13 = Utf8               Duration.Inf
  #14 = String             #13            // Duration.Inf
  #15 = Utf8               this
  #16 = Utf8               Lscala/concurrent/duration/Duration$$anon$2;
  #17 = Utf8               compare
  #18 = Utf8               (Lscala/concurrent/duration/Duration;)I
  #19 = Utf8               other
  #20 = Utf8               MODULE$
  #21 = Utf8               Lscala/concurrent/duration/Duration$;
  #22 = NameAndType        #20:#21        // MODULE$:Lscala/concurrent/duration/Duration$;
  #23 = Fieldref           #7.#22         // scala/concurrent/duration/Duration$.MODULE$:Lscala/concurrent/duration/Duration$;
  #24 = Utf8               Undefined
  #25 = Utf8               ()Lscala/concurrent/duration/Duration$Infinite;
  #26 = NameAndType        #24:#25        // Undefined:()Lscala/concurrent/duration/Duration$Infinite;
  #27 = Methodref          #7.#26         // scala/concurrent/duration/Duration$.Undefined:()Lscala/concurrent/duration/Duration$Infinite;
  #28 = Utf8               Lscala/concurrent/duration/Duration;
  #29 = Utf8               unary_$minus
  #30 = Utf8               ()Lscala/concurrent/duration/Duration;
  #31 = Utf8               MinusInf
  #32 = NameAndType        #31:#25        // MinusInf:()Lscala/concurrent/duration/Duration$Infinite;
  #33 = Methodref          #7.#32         // scala/concurrent/duration/Duration$.MinusInf:()Lscala/concurrent/duration/Duration$Infinite;
  #34 = Utf8               toUnit
  #35 = Utf8               (Ljava/util/concurrent/TimeUnit;)D
  #36 = Utf8               unit
  #37 = Double             Infinityd
  #39 = Utf8               Ljava/util/concurrent/TimeUnit;
  #40 = Utf8               readResolve
  #41 = Utf8               ()Ljava/lang/Object;
  #42 = Utf8               Inf
  #43 = NameAndType        #42:#25        // Inf:()Lscala/concurrent/duration/Duration$Infinite;
  #44 = Methodref          #7.#43         // scala/concurrent/duration/Duration$.Inf:()Lscala/concurrent/duration/Duration$Infinite;
  #45 = Utf8               (Ljava/lang/Object;)I
  #46 = Utf8               that
  #47 = NameAndType        #17:#18        // compare:(Lscala/concurrent/duration/Duration;)I
  #48 = Methodref          #2.#47         // scala/concurrent/duration/Duration$$anon$2.compare:(Lscala/concurrent/duration/Duration;)I
  #49 = Utf8               Ljava/lang/Object;
  #50 = Utf8               <init>
  #51 = Utf8               ()V
  #52 = NameAndType        #50:#51        // "<init>":()V
  #53 = Methodref          #4.#52         // scala/concurrent/duration/Duration$Infinite."<init>":()V
  #54 = Utf8               Code
  #55 = Utf8               LineNumberTable
  #56 = Utf8               LocalVariableTable
  #57 = Utf8               StackMapTable
  #58 = Utf8               MethodParameters
  #59 = Utf8               InnerClasses
  #60 = Utf8               EnclosingMethod
  #61 = Utf8               SourceFile
  #62 = Utf8               ScalaInlineInfo
  #63 = Utf8               Scala
{
  public java.lang.String toString();
    descriptor: ()Ljava/lang/String;
    flags: (0x0001) ACC_PUBLIC
    Code:
      stack=1, locals=1, args_size=1
         0: ldc           #14                 // String Duration.Inf
         2: areturn
      LineNumberTable:
        line 239: 0
      LocalVariableTable:
        Start  Length  Slot  Name   Signature
            0       3     0  this   Lscala/concurrent/duration/Duration$$anon$2;

  public int compare(scala.concurrent.duration.Duration);
    descriptor: (Lscala/concurrent/duration/Duration;)I
    flags: (0x0001) ACC_PUBLIC
    Code:
      stack=2, locals=3, args_size=2
         0: aload_1
         1: getstatic     #23                 // Field scala/concurrent/duration/Duration$.MODULE$:Lscala/concurrent/duration/Duration$;
         4: invokevirtual #27                 // Method scala/concurrent/duration/Duration$.Undefined:()Lscala/concurrent/duration/Duration$Infinite;
         7: if_acmpne     15
        10: iconst_m1
        11: istore_2
        12: goto          27
        15: aload_1
        16: aload_0
        17: if_acmpne     25
        20: iconst_0
        21: istore_2
        22: goto          27
        25: iconst_1
        26: istore_2
        27: iload_2
        28: ireturn
      StackMapTable: number_of_entries = 3
        frame_type = 15 /* same */
        frame_type = 9 /* same */
        frame_type = 252 /* append */
          offset_delta = 1
          locals = [ int ]
      LineNumberTable:
        line 241: 0
        line 242: 15
        line 243: 25
        line 240: 27
      LocalVariableTable:
        Start  Length  Slot  Name   Signature
            0      29     0  this   Lscala/concurrent/duration/Duration$$anon$2;
            0      29     1 other   Lscala/concurrent/duration/Duration;
    MethodParameters:
      Name                           Flags
      other                          final

  public scala.concurrent.duration.Duration unary_$minus();
    descriptor: ()Lscala/concurrent/duration/Duration;
    flags: (0x0001) ACC_PUBLIC
    Code:
      stack=1, locals=1, args_size=1
         0: getstatic     #23                 // Field scala/concurrent/duration/Duration$.MODULE$:Lscala/concurrent/duration/Duration$;
         3: invokevirtual #33                 // Method scala/concurrent/duration/Duration$.MinusInf:()Lscala/concurrent/duration/Duration$Infinite;
         6: areturn
      LineNumberTable:
        line 245: 0
      LocalVariableTable:
        Start  Length  Slot  Name   Signature
            0       7     0  this   Lscala/concurrent/duration/Duration$$anon$2;

  public double toUnit(java.util.concurrent.TimeUnit);
    descriptor: (Ljava/util/concurrent/TimeUnit;)D
    flags: (0x0001) ACC_PUBLIC
    Code:
      stack=2, locals=2, args_size=2
         0: ldc2_w        #37                 // double Infinityd
         3: dreturn
      LineNumberTable:
        line 246: 0
      LocalVariableTable:
        Start  Length  Slot  Name   Signature
            0       4     0  this   Lscala/concurrent/duration/Duration$$anon$2;
            0       4     1  unit   Ljava/util/concurrent/TimeUnit;
    MethodParameters:
      Name                           Flags
      unit                           final

  private java.lang.Object readResolve();
    descriptor: ()Ljava/lang/Object;
    flags: (0x0002) ACC_PRIVATE
    Code:
      stack=1, locals=1, args_size=1
         0: getstatic     #23                 // Field scala/concurrent/duration/Duration$.MODULE$:Lscala/concurrent/duration/Duration$;
         3: invokevirtual #44                 // Method scala/concurrent/duration/Duration$.Inf:()Lscala/concurrent/duration/Duration$Infinite;
         6: areturn
      LineNumberTable:
        line 247: 0
      LocalVariableTable:
        Start  Length  Slot  Name   Signature
            0       7     0  this   Lscala/concurrent/duration/Duration$$anon$2;

  public int compare(java.lang.Object);
    descriptor: (Ljava/lang/Object;)I
    flags: (0x1041) ACC_PUBLIC, ACC_BRIDGE, ACC_SYNTHETIC
    Code:
      stack=2, locals=2, args_size=2
         0: aload_0
         1: aload_1
         2: checkcast     #9                  // class scala/concurrent/duration/Duration
         5: invokevirtual #48                 // Method compare:(Lscala/concurrent/duration/Duration;)I
         8: ireturn
      LineNumberTable:
        line 238: 0
      LocalVariableTable:
        Start  Length  Slot  Name   Signature
            0       9     0  this   Lscala/concurrent/duration/Duration$$anon$2;
            0       9     1  that   Ljava/lang/Object;
    MethodParameters:
      Name                           Flags
      that                           final

  public scala.concurrent.duration.Duration$$anon$2();
    descriptor: ()V
    flags: (0x0001) ACC_PUBLIC
    Code:
      stack=1, locals=1, args_size=1
         0: aload_0
         1: invokespecial #53                 // Method scala/concurrent/duration/Duration$Infinite."<init>":()V
         4: return
      LineNumberTable:
        line 238: 0
      LocalVariableTable:
        Start  Length  Slot  Name   Signature
            0       5     0  this   Lscala/concurrent/duration/Duration$$anon$2;
}
InnerClasses:
  public final #2;                        // class scala/concurrent/duration/Duration$$anon$2
  public static abstract #10= #4 of #9;   // Infinite=class scala/concurrent/duration/Duration$Infinite of class scala/concurrent/duration/Duration
EnclosingMethod: #7.#0                  // scala.concurrent.duration.Duration$
SourceFile: "Duration.scala"
  ScalaInlineInfo: length = 0x27 (unknown attribute)
   01 01 00 07 00 32 00 33 01 00 11 00 2D 01 00 11
   00 12 01 00 28 00 29 01 00 0B 00 0C 01 00 22 00
   23 01 00 1D 00 1E 01
  Scala: length = 0x0 (unknown attribute)

