Classfile /Users/mw/Projects/slang-braindump/.jar/jar11/assemble/slang-braindump/assemble/content/scala/concurrent/duration/package$DurationInt.class
  Last modified May 29, 2022; size 6740 bytes
  SHA-256 checksum b9b15a2923b3e8a6339066557f170cd9edd30a69b2a73cef4f7d80eceb549e85
  Compiled from "package.scala"
public final class scala.concurrent.duration.package$DurationInt implements scala.concurrent.duration.DurationConversions
  minor version: 0
  major version: 52
  flags: (0x0031) ACC_PUBLIC, ACC_FINAL, ACC_SUPER
  this_class: #2                          // scala/concurrent/duration/package$DurationInt
  super_class: #4                         // java/lang/Object
  interfaces: 1, fields: 1, methods: 45, attributes: 4
Constant pool:
    #1 = Utf8               scala/concurrent/duration/package$DurationInt
    #2 = Class              #1            // scala/concurrent/duration/package$DurationInt
    #3 = Utf8               java/lang/Object
    #4 = Class              #3            // java/lang/Object
    #5 = Utf8               scala/concurrent/duration/DurationConversions
    #6 = Class              #5            // scala/concurrent/duration/DurationConversions
    #7 = Utf8               package.scala
    #8 = Utf8               scala/concurrent/duration/DurationConversions$Classifier
    #9 = Class              #8            // scala/concurrent/duration/DurationConversions$Classifier
   #10 = Utf8               Classifier
   #11 = Utf8               scala/concurrent/duration/package
   #12 = Class              #11           // scala/concurrent/duration/package
   #13 = Utf8               DurationInt
   #14 = Utf8               scala/concurrent/duration/package$DurationInt$
   #15 = Class              #14           // scala/concurrent/duration/package$DurationInt$
   #16 = Utf8               DurationInt$
   #17 = Utf8               scala$concurrent$duration$DurationInt$$n
   #18 = Utf8               I
   #19 = Utf8               nanoseconds
   #20 = Utf8               ()Lscala/concurrent/duration/FiniteDuration;
   #21 = Utf8               nanoseconds$
   #22 = Utf8               (Lscala/concurrent/duration/DurationConversions;)Lscala/concurrent/duration/FiniteDuration;
   #23 = NameAndType        #21:#22       // nanoseconds$:(Lscala/concurrent/duration/DurationConversions;)Lscala/concurrent/duration/FiniteDuration;
   #24 = InterfaceMethodref #6.#23        // scala/concurrent/duration/DurationConversions.nanoseconds$:(Lscala/concurrent/duration/DurationConversions;)Lscala/concurrent/duration/FiniteDuration;
   #25 = Utf8               this
   #26 = Utf8               Lscala/concurrent/duration/package$DurationInt;
   #27 = Utf8               nanos
   #28 = Utf8               nanos$
   #29 = NameAndType        #28:#22       // nanos$:(Lscala/concurrent/duration/DurationConversions;)Lscala/concurrent/duration/FiniteDuration;
   #30 = InterfaceMethodref #6.#29        // scala/concurrent/duration/DurationConversions.nanos$:(Lscala/concurrent/duration/DurationConversions;)Lscala/concurrent/duration/FiniteDuration;
   #31 = Utf8               nanosecond
   #32 = Utf8               nanosecond$
   #33 = NameAndType        #32:#22       // nanosecond$:(Lscala/concurrent/duration/DurationConversions;)Lscala/concurrent/duration/FiniteDuration;
   #34 = InterfaceMethodref #6.#33        // scala/concurrent/duration/DurationConversions.nanosecond$:(Lscala/concurrent/duration/DurationConversions;)Lscala/concurrent/duration/FiniteDuration;
   #35 = Utf8               nano
   #36 = Utf8               nano$
   #37 = NameAndType        #36:#22       // nano$:(Lscala/concurrent/duration/DurationConversions;)Lscala/concurrent/duration/FiniteDuration;
   #38 = InterfaceMethodref #6.#37        // scala/concurrent/duration/DurationConversions.nano$:(Lscala/concurrent/duration/DurationConversions;)Lscala/concurrent/duration/FiniteDuration;
   #39 = Utf8               microseconds
   #40 = Utf8               microseconds$
   #41 = NameAndType        #40:#22       // microseconds$:(Lscala/concurrent/duration/DurationConversions;)Lscala/concurrent/duration/FiniteDuration;
   #42 = InterfaceMethodref #6.#41        // scala/concurrent/duration/DurationConversions.microseconds$:(Lscala/concurrent/duration/DurationConversions;)Lscala/concurrent/duration/FiniteDuration;
   #43 = Utf8               micros
   #44 = Utf8               micros$
   #45 = NameAndType        #44:#22       // micros$:(Lscala/concurrent/duration/DurationConversions;)Lscala/concurrent/duration/FiniteDuration;
   #46 = InterfaceMethodref #6.#45        // scala/concurrent/duration/DurationConversions.micros$:(Lscala/concurrent/duration/DurationConversions;)Lscala/concurrent/duration/FiniteDuration;
   #47 = Utf8               microsecond
   #48 = Utf8               microsecond$
   #49 = NameAndType        #48:#22       // microsecond$:(Lscala/concurrent/duration/DurationConversions;)Lscala/concurrent/duration/FiniteDuration;
   #50 = InterfaceMethodref #6.#49        // scala/concurrent/duration/DurationConversions.microsecond$:(Lscala/concurrent/duration/DurationConversions;)Lscala/concurrent/duration/FiniteDuration;
   #51 = Utf8               micro
   #52 = Utf8               micro$
   #53 = NameAndType        #52:#22       // micro$:(Lscala/concurrent/duration/DurationConversions;)Lscala/concurrent/duration/FiniteDuration;
   #54 = InterfaceMethodref #6.#53        // scala/concurrent/duration/DurationConversions.micro$:(Lscala/concurrent/duration/DurationConversions;)Lscala/concurrent/duration/FiniteDuration;
   #55 = Utf8               milliseconds
   #56 = Utf8               milliseconds$
   #57 = NameAndType        #56:#22       // milliseconds$:(Lscala/concurrent/duration/DurationConversions;)Lscala/concurrent/duration/FiniteDuration;
   #58 = InterfaceMethodref #6.#57        // scala/concurrent/duration/DurationConversions.milliseconds$:(Lscala/concurrent/duration/DurationConversions;)Lscala/concurrent/duration/FiniteDuration;
   #59 = Utf8               millis
   #60 = Utf8               millis$
   #61 = NameAndType        #60:#22       // millis$:(Lscala/concurrent/duration/DurationConversions;)Lscala/concurrent/duration/FiniteDuration;
   #62 = InterfaceMethodref #6.#61        // scala/concurrent/duration/DurationConversions.millis$:(Lscala/concurrent/duration/DurationConversions;)Lscala/concurrent/duration/FiniteDuration;
   #63 = Utf8               millisecond
   #64 = Utf8               millisecond$
   #65 = NameAndType        #64:#22       // millisecond$:(Lscala/concurrent/duration/DurationConversions;)Lscala/concurrent/duration/FiniteDuration;
   #66 = InterfaceMethodref #6.#65        // scala/concurrent/duration/DurationConversions.millisecond$:(Lscala/concurrent/duration/DurationConversions;)Lscala/concurrent/duration/FiniteDuration;
   #67 = Utf8               milli
   #68 = Utf8               milli$
   #69 = NameAndType        #68:#22       // milli$:(Lscala/concurrent/duration/DurationConversions;)Lscala/concurrent/duration/FiniteDuration;
   #70 = InterfaceMethodref #6.#69        // scala/concurrent/duration/DurationConversions.milli$:(Lscala/concurrent/duration/DurationConversions;)Lscala/concurrent/duration/FiniteDuration;
   #71 = Utf8               seconds
   #72 = Utf8               seconds$
   #73 = NameAndType        #72:#22       // seconds$:(Lscala/concurrent/duration/DurationConversions;)Lscala/concurrent/duration/FiniteDuration;
   #74 = InterfaceMethodref #6.#73        // scala/concurrent/duration/DurationConversions.seconds$:(Lscala/concurrent/duration/DurationConversions;)Lscala/concurrent/duration/FiniteDuration;
   #75 = Utf8               second
   #76 = Utf8               second$
   #77 = NameAndType        #76:#22       // second$:(Lscala/concurrent/duration/DurationConversions;)Lscala/concurrent/duration/FiniteDuration;
   #78 = InterfaceMethodref #6.#77        // scala/concurrent/duration/DurationConversions.second$:(Lscala/concurrent/duration/DurationConversions;)Lscala/concurrent/duration/FiniteDuration;
   #79 = Utf8               minutes
   #80 = Utf8               minutes$
   #81 = NameAndType        #80:#22       // minutes$:(Lscala/concurrent/duration/DurationConversions;)Lscala/concurrent/duration/FiniteDuration;
   #82 = InterfaceMethodref #6.#81        // scala/concurrent/duration/DurationConversions.minutes$:(Lscala/concurrent/duration/DurationConversions;)Lscala/concurrent/duration/FiniteDuration;
   #83 = Utf8               minute
   #84 = Utf8               minute$
   #85 = NameAndType        #84:#22       // minute$:(Lscala/concurrent/duration/DurationConversions;)Lscala/concurrent/duration/FiniteDuration;
   #86 = InterfaceMethodref #6.#85        // scala/concurrent/duration/DurationConversions.minute$:(Lscala/concurrent/duration/DurationConversions;)Lscala/concurrent/duration/FiniteDuration;
   #87 = Utf8               hours
   #88 = Utf8               hours$
   #89 = NameAndType        #88:#22       // hours$:(Lscala/concurrent/duration/DurationConversions;)Lscala/concurrent/duration/FiniteDuration;
   #90 = InterfaceMethodref #6.#89        // scala/concurrent/duration/DurationConversions.hours$:(Lscala/concurrent/duration/DurationConversions;)Lscala/concurrent/duration/FiniteDuration;
   #91 = Utf8               hour
   #92 = Utf8               hour$
   #93 = NameAndType        #92:#22       // hour$:(Lscala/concurrent/duration/DurationConversions;)Lscala/concurrent/duration/FiniteDuration;
   #94 = InterfaceMethodref #6.#93        // scala/concurrent/duration/DurationConversions.hour$:(Lscala/concurrent/duration/DurationConversions;)Lscala/concurrent/duration/FiniteDuration;
   #95 = Utf8               days
   #96 = Utf8               days$
   #97 = NameAndType        #96:#22       // days$:(Lscala/concurrent/duration/DurationConversions;)Lscala/concurrent/duration/FiniteDuration;
   #98 = InterfaceMethodref #6.#97        // scala/concurrent/duration/DurationConversions.days$:(Lscala/concurrent/duration/DurationConversions;)Lscala/concurrent/duration/FiniteDuration;
   #99 = Utf8               day
  #100 = Utf8               day$
  #101 = NameAndType        #100:#22      // day$:(Lscala/concurrent/duration/DurationConversions;)Lscala/concurrent/duration/FiniteDuration;
  #102 = InterfaceMethodref #6.#101       // scala/concurrent/duration/DurationConversions.day$:(Lscala/concurrent/duration/DurationConversions;)Lscala/concurrent/duration/FiniteDuration;
  #103 = Utf8               (Ljava/lang/Object;Lscala/concurrent/duration/DurationConversions$Classifier;)Ljava/lang/Object;
  #104 = Utf8               <C:Ljava/lang/Object;>(TC;Lscala/concurrent/duration/DurationConversions$Classifier<TC;>;)Ljava/lang/Object;
  #105 = Utf8               c
  #106 = Utf8               ev
  #107 = Utf8               (Lscala/concurrent/duration/DurationConversions;Ljava/lang/Object;Lscala/concurrent/duration/DurationConversions$Classifier;)Ljava/lang/Object;
  #108 = NameAndType        #21:#107      // nanoseconds$:(Lscala/concurrent/duration/DurationConversions;Ljava/lang/Object;Lscala/concurrent/duration/DurationConversions$Classifier;)Ljava/lang/Object;
  #109 = InterfaceMethodref #6.#108       // scala/concurrent/duration/DurationConversions.nanoseconds$:(Lscala/concurrent/duration/DurationConversions;Ljava/lang/Object;Lscala/concurrent/duration/DurationConversions$Classifier;)Ljava/lang/Object;
  #110 = Utf8               Ljava/lang/Object;
  #111 = Utf8               Lscala/concurrent/duration/DurationConversions$Classifier;
  #112 = NameAndType        #28:#107      // nanos$:(Lscala/concurrent/duration/DurationConversions;Ljava/lang/Object;Lscala/concurrent/duration/DurationConversions$Classifier;)Ljava/lang/Object;
  #113 = InterfaceMethodref #6.#112       // scala/concurrent/duration/DurationConversions.nanos$:(Lscala/concurrent/duration/DurationConversions;Ljava/lang/Object;Lscala/concurrent/duration/DurationConversions$Classifier;)Ljava/lang/Object;
  #114 = NameAndType        #32:#107      // nanosecond$:(Lscala/concurrent/duration/DurationConversions;Ljava/lang/Object;Lscala/concurrent/duration/DurationConversions$Classifier;)Ljava/lang/Object;
  #115 = InterfaceMethodref #6.#114       // scala/concurrent/duration/DurationConversions.nanosecond$:(Lscala/concurrent/duration/DurationConversions;Ljava/lang/Object;Lscala/concurrent/duration/DurationConversions$Classifier;)Ljava/lang/Object;
  #116 = NameAndType        #36:#107      // nano$:(Lscala/concurrent/duration/DurationConversions;Ljava/lang/Object;Lscala/concurrent/duration/DurationConversions$Classifier;)Ljava/lang/Object;
  #117 = InterfaceMethodref #6.#116       // scala/concurrent/duration/DurationConversions.nano$:(Lscala/concurrent/duration/DurationConversions;Ljava/lang/Object;Lscala/concurrent/duration/DurationConversions$Classifier;)Ljava/lang/Object;
  #118 = NameAndType        #40:#107      // microseconds$:(Lscala/concurrent/duration/DurationConversions;Ljava/lang/Object;Lscala/concurrent/duration/DurationConversions$Classifier;)Ljava/lang/Object;
  #119 = InterfaceMethodref #6.#118       // scala/concurrent/duration/DurationConversions.microseconds$:(Lscala/concurrent/duration/DurationConversions;Ljava/lang/Object;Lscala/concurrent/duration/DurationConversions$Classifier;)Ljava/lang/Object;
  #120 = NameAndType        #44:#107      // micros$:(Lscala/concurrent/duration/DurationConversions;Ljava/lang/Object;Lscala/concurrent/duration/DurationConversions$Classifier;)Ljava/lang/Object;
  #121 = InterfaceMethodref #6.#120       // scala/concurrent/duration/DurationConversions.micros$:(Lscala/concurrent/duration/DurationConversions;Ljava/lang/Object;Lscala/concurrent/duration/DurationConversions$Classifier;)Ljava/lang/Object;
  #122 = NameAndType        #48:#107      // microsecond$:(Lscala/concurrent/duration/DurationConversions;Ljava/lang/Object;Lscala/concurrent/duration/DurationConversions$Classifier;)Ljava/lang/Object;
  #123 = InterfaceMethodref #6.#122       // scala/concurrent/duration/DurationConversions.microsecond$:(Lscala/concurrent/duration/DurationConversions;Ljava/lang/Object;Lscala/concurrent/duration/DurationConversions$Classifier;)Ljava/lang/Object;
  #124 = NameAndType        #52:#107      // micro$:(Lscala/concurrent/duration/DurationConversions;Ljava/lang/Object;Lscala/concurrent/duration/DurationConversions$Classifier;)Ljava/lang/Object;
  #125 = InterfaceMethodref #6.#124       // scala/concurrent/duration/DurationConversions.micro$:(Lscala/concurrent/duration/DurationConversions;Ljava/lang/Object;Lscala/concurrent/duration/DurationConversions$Classifier;)Ljava/lang/Object;
  #126 = NameAndType        #56:#107      // milliseconds$:(Lscala/concurrent/duration/DurationConversions;Ljava/lang/Object;Lscala/concurrent/duration/DurationConversions$Classifier;)Ljava/lang/Object;
  #127 = InterfaceMethodref #6.#126       // scala/concurrent/duration/DurationConversions.milliseconds$:(Lscala/concurrent/duration/DurationConversions;Ljava/lang/Object;Lscala/concurrent/duration/DurationConversions$Classifier;)Ljava/lang/Object;
  #128 = NameAndType        #60:#107      // millis$:(Lscala/concurrent/duration/DurationConversions;Ljava/lang/Object;Lscala/concurrent/duration/DurationConversions$Classifier;)Ljava/lang/Object;
  #129 = InterfaceMethodref #6.#128       // scala/concurrent/duration/DurationConversions.millis$:(Lscala/concurrent/duration/DurationConversions;Ljava/lang/Object;Lscala/concurrent/duration/DurationConversions$Classifier;)Ljava/lang/Object;
  #130 = NameAndType        #64:#107      // millisecond$:(Lscala/concurrent/duration/DurationConversions;Ljava/lang/Object;Lscala/concurrent/duration/DurationConversions$Classifier;)Ljava/lang/Object;
  #131 = InterfaceMethodref #6.#130       // scala/concurrent/duration/DurationConversions.millisecond$:(Lscala/concurrent/duration/DurationConversions;Ljava/lang/Object;Lscala/concurrent/duration/DurationConversions$Classifier;)Ljava/lang/Object;
  #132 = NameAndType        #68:#107      // milli$:(Lscala/concurrent/duration/DurationConversions;Ljava/lang/Object;Lscala/concurrent/duration/DurationConversions$Classifier;)Ljava/lang/Object;
  #133 = InterfaceMethodref #6.#132       // scala/concurrent/duration/DurationConversions.milli$:(Lscala/concurrent/duration/DurationConversions;Ljava/lang/Object;Lscala/concurrent/duration/DurationConversions$Classifier;)Ljava/lang/Object;
  #134 = NameAndType        #72:#107      // seconds$:(Lscala/concurrent/duration/DurationConversions;Ljava/lang/Object;Lscala/concurrent/duration/DurationConversions$Classifier;)Ljava/lang/Object;
  #135 = InterfaceMethodref #6.#134       // scala/concurrent/duration/DurationConversions.seconds$:(Lscala/concurrent/duration/DurationConversions;Ljava/lang/Object;Lscala/concurrent/duration/DurationConversions$Classifier;)Ljava/lang/Object;
  #136 = NameAndType        #76:#107      // second$:(Lscala/concurrent/duration/DurationConversions;Ljava/lang/Object;Lscala/concurrent/duration/DurationConversions$Classifier;)Ljava/lang/Object;
  #137 = InterfaceMethodref #6.#136       // scala/concurrent/duration/DurationConversions.second$:(Lscala/concurrent/duration/DurationConversions;Ljava/lang/Object;Lscala/concurrent/duration/DurationConversions$Classifier;)Ljava/lang/Object;
  #138 = NameAndType        #80:#107      // minutes$:(Lscala/concurrent/duration/DurationConversions;Ljava/lang/Object;Lscala/concurrent/duration/DurationConversions$Classifier;)Ljava/lang/Object;
  #139 = InterfaceMethodref #6.#138       // scala/concurrent/duration/DurationConversions.minutes$:(Lscala/concurrent/duration/DurationConversions;Ljava/lang/Object;Lscala/concurrent/duration/DurationConversions$Classifier;)Ljava/lang/Object;
  #140 = NameAndType        #84:#107      // minute$:(Lscala/concurrent/duration/DurationConversions;Ljava/lang/Object;Lscala/concurrent/duration/DurationConversions$Classifier;)Ljava/lang/Object;
  #141 = InterfaceMethodref #6.#140       // scala/concurrent/duration/DurationConversions.minute$:(Lscala/concurrent/duration/DurationConversions;Ljava/lang/Object;Lscala/concurrent/duration/DurationConversions$Classifier;)Ljava/lang/Object;
  #142 = NameAndType        #88:#107      // hours$:(Lscala/concurrent/duration/DurationConversions;Ljava/lang/Object;Lscala/concurrent/duration/DurationConversions$Classifier;)Ljava/lang/Object;
  #143 = InterfaceMethodref #6.#142       // scala/concurrent/duration/DurationConversions.hours$:(Lscala/concurrent/duration/DurationConversions;Ljava/lang/Object;Lscala/concurrent/duration/DurationConversions$Classifier;)Ljava/lang/Object;
  #144 = NameAndType        #92:#107      // hour$:(Lscala/concurrent/duration/DurationConversions;Ljava/lang/Object;Lscala/concurrent/duration/DurationConversions$Classifier;)Ljava/lang/Object;
  #145 = InterfaceMethodref #6.#144       // scala/concurrent/duration/DurationConversions.hour$:(Lscala/concurrent/duration/DurationConversions;Ljava/lang/Object;Lscala/concurrent/duration/DurationConversions$Classifier;)Ljava/lang/Object;
  #146 = NameAndType        #96:#107      // days$:(Lscala/concurrent/duration/DurationConversions;Ljava/lang/Object;Lscala/concurrent/duration/DurationConversions$Classifier;)Ljava/lang/Object;
  #147 = InterfaceMethodref #6.#146       // scala/concurrent/duration/DurationConversions.days$:(Lscala/concurrent/duration/DurationConversions;Ljava/lang/Object;Lscala/concurrent/duration/DurationConversions$Classifier;)Ljava/lang/Object;
  #148 = NameAndType        #100:#107     // day$:(Lscala/concurrent/duration/DurationConversions;Ljava/lang/Object;Lscala/concurrent/duration/DurationConversions$Classifier;)Ljava/lang/Object;
  #149 = InterfaceMethodref #6.#148       // scala/concurrent/duration/DurationConversions.day$:(Lscala/concurrent/duration/DurationConversions;Ljava/lang/Object;Lscala/concurrent/duration/DurationConversions$Classifier;)Ljava/lang/Object;
  #150 = Utf8               ()I
  #151 = NameAndType        #17:#18       // scala$concurrent$duration$DurationInt$$n:I
  #152 = Fieldref           #2.#151       // scala/concurrent/duration/package$DurationInt.scala$concurrent$duration$DurationInt$$n:I
  #153 = Utf8               durationIn
  #154 = Utf8               (Ljava/util/concurrent/TimeUnit;)Lscala/concurrent/duration/FiniteDuration;
  #155 = Utf8               unit
  #156 = Utf8               MODULE$
  #157 = Utf8               Lscala/concurrent/duration/package$DurationInt$;
  #158 = NameAndType        #156:#157     // MODULE$:Lscala/concurrent/duration/package$DurationInt$;
  #159 = Fieldref           #15.#158      // scala/concurrent/duration/package$DurationInt$.MODULE$:Lscala/concurrent/duration/package$DurationInt$;
  #160 = NameAndType        #17:#150      // scala$concurrent$duration$DurationInt$$n:()I
  #161 = Methodref          #2.#160       // scala/concurrent/duration/package$DurationInt.scala$concurrent$duration$DurationInt$$n:()I
  #162 = Utf8               scala/concurrent/duration/Duration$
  #163 = Class              #162          // scala/concurrent/duration/Duration$
  #164 = Utf8               Lscala/concurrent/duration/Duration$;
  #165 = NameAndType        #156:#164     // MODULE$:Lscala/concurrent/duration/Duration$;
  #166 = Fieldref           #163.#165     // scala/concurrent/duration/Duration$.MODULE$:Lscala/concurrent/duration/Duration$;
  #167 = Utf8               scala/concurrent/duration/FiniteDuration
  #168 = Class              #167          // scala/concurrent/duration/FiniteDuration
  #169 = Utf8               <init>
  #170 = Utf8               (JLjava/util/concurrent/TimeUnit;)V
  #171 = NameAndType        #169:#170     // "<init>":(JLjava/util/concurrent/TimeUnit;)V
  #172 = Methodref          #168.#171     // scala/concurrent/duration/FiniteDuration."<init>":(JLjava/util/concurrent/TimeUnit;)V
  #173 = Utf8               Ljava/util/concurrent/TimeUnit;
  #174 = Utf8               durationIn$extension_$this
  #175 = Utf8               durationIn$extension_apply_length
  #176 = Utf8               J
  #177 = Utf8               hashCode
  #178 = Utf8               java/lang/Integer
  #179 = Class              #178          // java/lang/Integer
  #180 = Utf8               (I)I
  #181 = NameAndType        #177:#180     // hashCode:(I)I
  #182 = Methodref          #179.#181     // java/lang/Integer.hashCode:(I)I
  #183 = Utf8               equals
  #184 = Utf8               (Ljava/lang/Object;)Z
  #185 = Utf8               x$1
  #186 = Utf8               equals$extension
  #187 = Utf8               (ILjava/lang/Object;)Z
  #188 = NameAndType        #186:#187     // equals$extension:(ILjava/lang/Object;)Z
  #189 = Methodref          #15.#188      // scala/concurrent/duration/package$DurationInt$.equals$extension:(ILjava/lang/Object;)Z
  #190 = Utf8               (I)V
  #191 = Utf8               n
  #192 = Utf8               ()V
  #193 = NameAndType        #169:#192     // "<init>":()V
  #194 = Methodref          #4.#193       // java/lang/Object."<init>":()V
  #195 = Utf8               Code
  #196 = Utf8               LineNumberTable
  #197 = Utf8               LocalVariableTable
  #198 = Utf8               Signature
  #199 = Utf8               MethodParameters
  #200 = Utf8               InnerClasses
  #201 = Utf8               SourceFile
  #202 = Utf8               ScalaInlineInfo
  #203 = Utf8               Scala
{
  private final int scala$concurrent$duration$DurationInt$$n;
    descriptor: I
    flags: (0x0012) ACC_PRIVATE, ACC_FINAL

  public scala.concurrent.duration.FiniteDuration nanoseconds();
    descriptor: ()Lscala/concurrent/duration/FiniteDuration;
    flags: (0x0001) ACC_PUBLIC
    Code:
      stack=1, locals=1, args_size=1
         0: aload_0
         1: invokestatic  #24                 // InterfaceMethod scala/concurrent/duration/DurationConversions.nanoseconds$:(Lscala/concurrent/duration/DurationConversions;)Lscala/concurrent/duration/FiniteDuration;
         4: areturn
      LineNumberTable:
        line 55: 0
      LocalVariableTable:
        Start  Length  Slot  Name   Signature
            0       5     0  this   Lscala/concurrent/duration/package$DurationInt;

  public scala.concurrent.duration.FiniteDuration nanos();
    descriptor: ()Lscala/concurrent/duration/FiniteDuration;
    flags: (0x0001) ACC_PUBLIC
    Code:
      stack=1, locals=1, args_size=1
         0: aload_0
         1: invokestatic  #30                 // InterfaceMethod scala/concurrent/duration/DurationConversions.nanos$:(Lscala/concurrent/duration/DurationConversions;)Lscala/concurrent/duration/FiniteDuration;
         4: areturn
      LineNumberTable:
        line 55: 0
      LocalVariableTable:
        Start  Length  Slot  Name   Signature
            0       5     0  this   Lscala/concurrent/duration/package$DurationInt;

  public scala.concurrent.duration.FiniteDuration nanosecond();
    descriptor: ()Lscala/concurrent/duration/FiniteDuration;
    flags: (0x0001) ACC_PUBLIC
    Code:
      stack=1, locals=1, args_size=1
         0: aload_0
         1: invokestatic  #34                 // InterfaceMethod scala/concurrent/duration/DurationConversions.nanosecond$:(Lscala/concurrent/duration/DurationConversions;)Lscala/concurrent/duration/FiniteDuration;
         4: areturn
      LineNumberTable:
        line 55: 0
      LocalVariableTable:
        Start  Length  Slot  Name   Signature
            0       5     0  this   Lscala/concurrent/duration/package$DurationInt;

  public scala.concurrent.duration.FiniteDuration nano();
    descriptor: ()Lscala/concurrent/duration/FiniteDuration;
    flags: (0x0001) ACC_PUBLIC
    Code:
      stack=1, locals=1, args_size=1
         0: aload_0
         1: invokestatic  #38                 // InterfaceMethod scala/concurrent/duration/DurationConversions.nano$:(Lscala/concurrent/duration/DurationConversions;)Lscala/concurrent/duration/FiniteDuration;
         4: areturn
      LineNumberTable:
        line 55: 0
      LocalVariableTable:
        Start  Length  Slot  Name   Signature
            0       5     0  this   Lscala/concurrent/duration/package$DurationInt;

  public scala.concurrent.duration.FiniteDuration microseconds();
    descriptor: ()Lscala/concurrent/duration/FiniteDuration;
    flags: (0x0001) ACC_PUBLIC
    Code:
      stack=1, locals=1, args_size=1
         0: aload_0
         1: invokestatic  #42                 // InterfaceMethod scala/concurrent/duration/DurationConversions.microseconds$:(Lscala/concurrent/duration/DurationConversions;)Lscala/concurrent/duration/FiniteDuration;
         4: areturn
      LineNumberTable:
        line 55: 0
      LocalVariableTable:
        Start  Length  Slot  Name   Signature
            0       5     0  this   Lscala/concurrent/duration/package$DurationInt;

  public scala.concurrent.duration.FiniteDuration micros();
    descriptor: ()Lscala/concurrent/duration/FiniteDuration;
    flags: (0x0001) ACC_PUBLIC
    Code:
      stack=1, locals=1, args_size=1
         0: aload_0
         1: invokestatic  #46                 // InterfaceMethod scala/concurrent/duration/DurationConversions.micros$:(Lscala/concurrent/duration/DurationConversions;)Lscala/concurrent/duration/FiniteDuration;
         4: areturn
      LineNumberTable:
        line 55: 0
      LocalVariableTable:
        Start  Length  Slot  Name   Signature
            0       5     0  this   Lscala/concurrent/duration/package$DurationInt;

  public scala.concurrent.duration.FiniteDuration microsecond();
    descriptor: ()Lscala/concurrent/duration/FiniteDuration;
    flags: (0x0001) ACC_PUBLIC
    Code:
      stack=1, locals=1, args_size=1
         0: aload_0
         1: invokestatic  #50                 // InterfaceMethod scala/concurrent/duration/DurationConversions.microsecond$:(Lscala/concurrent/duration/DurationConversions;)Lscala/concurrent/duration/FiniteDuration;
         4: areturn
      LineNumberTable:
        line 55: 0
      LocalVariableTable:
        Start  Length  Slot  Name   Signature
            0       5     0  this   Lscala/concurrent/duration/package$DurationInt;

  public scala.concurrent.duration.FiniteDuration micro();
    descriptor: ()Lscala/concurrent/duration/FiniteDuration;
    flags: (0x0001) ACC_PUBLIC
    Code:
      stack=1, locals=1, args_size=1
         0: aload_0
         1: invokestatic  #54                 // InterfaceMethod scala/concurrent/duration/DurationConversions.micro$:(Lscala/concurrent/duration/DurationConversions;)Lscala/concurrent/duration/FiniteDuration;
         4: areturn
      LineNumberTable:
        line 55: 0
      LocalVariableTable:
        Start  Length  Slot  Name   Signature
            0       5     0  this   Lscala/concurrent/duration/package$DurationInt;

  public scala.concurrent.duration.FiniteDuration milliseconds();
    descriptor: ()Lscala/concurrent/duration/FiniteDuration;
    flags: (0x0001) ACC_PUBLIC
    Code:
      stack=1, locals=1, args_size=1
         0: aload_0
         1: invokestatic  #58                 // InterfaceMethod scala/concurrent/duration/DurationConversions.milliseconds$:(Lscala/concurrent/duration/DurationConversions;)Lscala/concurrent/duration/FiniteDuration;
         4: areturn
      LineNumberTable:
        line 55: 0
      LocalVariableTable:
        Start  Length  Slot  Name   Signature
            0       5     0  this   Lscala/concurrent/duration/package$DurationInt;

  public scala.concurrent.duration.FiniteDuration millis();
    descriptor: ()Lscala/concurrent/duration/FiniteDuration;
    flags: (0x0001) ACC_PUBLIC
    Code:
      stack=1, locals=1, args_size=1
         0: aload_0
         1: invokestatic  #62                 // InterfaceMethod scala/concurrent/duration/DurationConversions.millis$:(Lscala/concurrent/duration/DurationConversions;)Lscala/concurrent/duration/FiniteDuration;
         4: areturn
      LineNumberTable:
        line 55: 0
      LocalVariableTable:
        Start  Length  Slot  Name   Signature
            0       5     0  this   Lscala/concurrent/duration/package$DurationInt;

  public scala.concurrent.duration.FiniteDuration millisecond();
    descriptor: ()Lscala/concurrent/duration/FiniteDuration;
    flags: (0x0001) ACC_PUBLIC
    Code:
      stack=1, locals=1, args_size=1
         0: aload_0
         1: invokestatic  #66                 // InterfaceMethod scala/concurrent/duration/DurationConversions.millisecond$:(Lscala/concurrent/duration/DurationConversions;)Lscala/concurrent/duration/FiniteDuration;
         4: areturn
      LineNumberTable:
        line 55: 0
      LocalVariableTable:
        Start  Length  Slot  Name   Signature
            0       5     0  this   Lscala/concurrent/duration/package$DurationInt;

  public scala.concurrent.duration.FiniteDuration milli();
    descriptor: ()Lscala/concurrent/duration/FiniteDuration;
    flags: (0x0001) ACC_PUBLIC
    Code:
      stack=1, locals=1, args_size=1
         0: aload_0
         1: invokestatic  #70                 // InterfaceMethod scala/concurrent/duration/DurationConversions.milli$:(Lscala/concurrent/duration/DurationConversions;)Lscala/concurrent/duration/FiniteDuration;
         4: areturn
      LineNumberTable:
        line 55: 0
      LocalVariableTable:
        Start  Length  Slot  Name   Signature
            0       5     0  this   Lscala/concurrent/duration/package$DurationInt;

  public scala.concurrent.duration.FiniteDuration seconds();
    descriptor: ()Lscala/concurrent/duration/FiniteDuration;
    flags: (0x0001) ACC_PUBLIC
    Code:
      stack=1, locals=1, args_size=1
         0: aload_0
         1: invokestatic  #74                 // InterfaceMethod scala/concurrent/duration/DurationConversions.seconds$:(Lscala/concurrent/duration/DurationConversions;)Lscala/concurrent/duration/FiniteDuration;
         4: areturn
      LineNumberTable:
        line 55: 0
      LocalVariableTable:
        Start  Length  Slot  Name   Signature
            0       5     0  this   Lscala/concurrent/duration/package$DurationInt;

  public scala.concurrent.duration.FiniteDuration second();
    descriptor: ()Lscala/concurrent/duration/FiniteDuration;
    flags: (0x0001) ACC_PUBLIC
    Code:
      stack=1, locals=1, args_size=1
         0: aload_0
         1: invokestatic  #78                 // InterfaceMethod scala/concurrent/duration/DurationConversions.second$:(Lscala/concurrent/duration/DurationConversions;)Lscala/concurrent/duration/FiniteDuration;
         4: areturn
      LineNumberTable:
        line 55: 0
      LocalVariableTable:
        Start  Length  Slot  Name   Signature
            0       5     0  this   Lscala/concurrent/duration/package$DurationInt;

  public scala.concurrent.duration.FiniteDuration minutes();
    descriptor: ()Lscala/concurrent/duration/FiniteDuration;
    flags: (0x0001) ACC_PUBLIC
    Code:
      stack=1, locals=1, args_size=1
         0: aload_0
         1: invokestatic  #82                 // InterfaceMethod scala/concurrent/duration/DurationConversions.minutes$:(Lscala/concurrent/duration/DurationConversions;)Lscala/concurrent/duration/FiniteDuration;
         4: areturn
      LineNumberTable:
        line 55: 0
      LocalVariableTable:
        Start  Length  Slot  Name   Signature
            0       5     0  this   Lscala/concurrent/duration/package$DurationInt;

  public scala.concurrent.duration.FiniteDuration minute();
    descriptor: ()Lscala/concurrent/duration/FiniteDuration;
    flags: (0x0001) ACC_PUBLIC
    Code:
      stack=1, locals=1, args_size=1
         0: aload_0
         1: invokestatic  #86                 // InterfaceMethod scala/concurrent/duration/DurationConversions.minute$:(Lscala/concurrent/duration/DurationConversions;)Lscala/concurrent/duration/FiniteDuration;
         4: areturn
      LineNumberTable:
        line 55: 0
      LocalVariableTable:
        Start  Length  Slot  Name   Signature
            0       5     0  this   Lscala/concurrent/duration/package$DurationInt;

  public scala.concurrent.duration.FiniteDuration hours();
    descriptor: ()Lscala/concurrent/duration/FiniteDuration;
    flags: (0x0001) ACC_PUBLIC
    Code:
      stack=1, locals=1, args_size=1
         0: aload_0
         1: invokestatic  #90                 // InterfaceMethod scala/concurrent/duration/DurationConversions.hours$:(Lscala/concurrent/duration/DurationConversions;)Lscala/concurrent/duration/FiniteDuration;
         4: areturn
      LineNumberTable:
        line 55: 0
      LocalVariableTable:
        Start  Length  Slot  Name   Signature
            0       5     0  this   Lscala/concurrent/duration/package$DurationInt;

  public scala.concurrent.duration.FiniteDuration hour();
    descriptor: ()Lscala/concurrent/duration/FiniteDuration;
    flags: (0x0001) ACC_PUBLIC
    Code:
      stack=1, locals=1, args_size=1
         0: aload_0
         1: invokestatic  #94                 // InterfaceMethod scala/concurrent/duration/DurationConversions.hour$:(Lscala/concurrent/duration/DurationConversions;)Lscala/concurrent/duration/FiniteDuration;
         4: areturn
      LineNumberTable:
        line 55: 0
      LocalVariableTable:
        Start  Length  Slot  Name   Signature
            0       5     0  this   Lscala/concurrent/duration/package$DurationInt;

  public scala.concurrent.duration.FiniteDuration days();
    descriptor: ()Lscala/concurrent/duration/FiniteDuration;
    flags: (0x0001) ACC_PUBLIC
    Code:
      stack=1, locals=1, args_size=1
         0: aload_0
         1: invokestatic  #98                 // InterfaceMethod scala/concurrent/duration/DurationConversions.days$:(Lscala/concurrent/duration/DurationConversions;)Lscala/concurrent/duration/FiniteDuration;
         4: areturn
      LineNumberTable:
        line 55: 0
      LocalVariableTable:
        Start  Length  Slot  Name   Signature
            0       5     0  this   Lscala/concurrent/duration/package$DurationInt;

  public scala.concurrent.duration.FiniteDuration day();
    descriptor: ()Lscala/concurrent/duration/FiniteDuration;
    flags: (0x0001) ACC_PUBLIC
    Code:
      stack=1, locals=1, args_size=1
         0: aload_0
         1: invokestatic  #102                // InterfaceMethod scala/concurrent/duration/DurationConversions.day$:(Lscala/concurrent/duration/DurationConversions;)Lscala/concurrent/duration/FiniteDuration;
         4: areturn
      LineNumberTable:
        line 55: 0
      LocalVariableTable:
        Start  Length  Slot  Name   Signature
            0       5     0  this   Lscala/concurrent/duration/package$DurationInt;

  public <C extends java.lang.Object> java.lang.Object nanoseconds(C, scala.concurrent.duration.DurationConversions$Classifier<C>);
    descriptor: (Ljava/lang/Object;Lscala/concurrent/duration/DurationConversions$Classifier;)Ljava/lang/Object;
    flags: (0x0001) ACC_PUBLIC
    Code:
      stack=3, locals=3, args_size=3
         0: aload_0
         1: aload_1
         2: aload_2
         3: invokestatic  #109                // InterfaceMethod scala/concurrent/duration/DurationConversions.nanoseconds$:(Lscala/concurrent/duration/DurationConversions;Ljava/lang/Object;Lscala/concurrent/duration/DurationConversions$Classifier;)Ljava/lang/Object;
         6: areturn
      LineNumberTable:
        line 55: 0
      LocalVariableTable:
        Start  Length  Slot  Name   Signature
            0       7     0  this   Lscala/concurrent/duration/package$DurationInt;
            0       7     1     c   Ljava/lang/Object;
            0       7     2    ev   Lscala/concurrent/duration/DurationConversions$Classifier;
    Signature: #104                         // <C:Ljava/lang/Object;>(TC;Lscala/concurrent/duration/DurationConversions$Classifier<TC;>;)Ljava/lang/Object;
    MethodParameters:
      Name                           Flags
      c                              final
      ev                             final

  public <C extends java.lang.Object> java.lang.Object nanos(C, scala.concurrent.duration.DurationConversions$Classifier<C>);
    descriptor: (Ljava/lang/Object;Lscala/concurrent/duration/DurationConversions$Classifier;)Ljava/lang/Object;
    flags: (0x0001) ACC_PUBLIC
    Code:
      stack=3, locals=3, args_size=3
         0: aload_0
         1: aload_1
         2: aload_2
         3: invokestatic  #113                // InterfaceMethod scala/concurrent/duration/DurationConversions.nanos$:(Lscala/concurrent/duration/DurationConversions;Ljava/lang/Object;Lscala/concurrent/duration/DurationConversions$Classifier;)Ljava/lang/Object;
         6: areturn
      LineNumberTable:
        line 55: 0
      LocalVariableTable:
        Start  Length  Slot  Name   Signature
            0       7     0  this   Lscala/concurrent/duration/package$DurationInt;
            0       7     1     c   Ljava/lang/Object;
            0       7     2    ev   Lscala/concurrent/duration/DurationConversions$Classifier;
    Signature: #104                         // <C:Ljava/lang/Object;>(TC;Lscala/concurrent/duration/DurationConversions$Classifier<TC;>;)Ljava/lang/Object;
    MethodParameters:
      Name                           Flags
      c                              final
      ev                             final

  public <C extends java.lang.Object> java.lang.Object nanosecond(C, scala.concurrent.duration.DurationConversions$Classifier<C>);
    descriptor: (Ljava/lang/Object;Lscala/concurrent/duration/DurationConversions$Classifier;)Ljava/lang/Object;
    flags: (0x0001) ACC_PUBLIC
    Code:
      stack=3, locals=3, args_size=3
         0: aload_0
         1: aload_1
         2: aload_2
         3: invokestatic  #115                // InterfaceMethod scala/concurrent/duration/DurationConversions.nanosecond$:(Lscala/concurrent/duration/DurationConversions;Ljava/lang/Object;Lscala/concurrent/duration/DurationConversions$Classifier;)Ljava/lang/Object;
         6: areturn
      LineNumberTable:
        line 55: 0
      LocalVariableTable:
        Start  Length  Slot  Name   Signature
            0       7     0  this   Lscala/concurrent/duration/package$DurationInt;
            0       7     1     c   Ljava/lang/Object;
            0       7     2    ev   Lscala/concurrent/duration/DurationConversions$Classifier;
    Signature: #104                         // <C:Ljava/lang/Object;>(TC;Lscala/concurrent/duration/DurationConversions$Classifier<TC;>;)Ljava/lang/Object;
    MethodParameters:
      Name                           Flags
      c                              final
      ev                             final

  public <C extends java.lang.Object> java.lang.Object nano(C, scala.concurrent.duration.DurationConversions$Classifier<C>);
    descriptor: (Ljava/lang/Object;Lscala/concurrent/duration/DurationConversions$Classifier;)Ljava/lang/Object;
    flags: (0x0001) ACC_PUBLIC
    Code:
      stack=3, locals=3, args_size=3
         0: aload_0
         1: aload_1
         2: aload_2
         3: invokestatic  #117                // InterfaceMethod scala/concurrent/duration/DurationConversions.nano$:(Lscala/concurrent/duration/DurationConversions;Ljava/lang/Object;Lscala/concurrent/duration/DurationConversions$Classifier;)Ljava/lang/Object;
         6: areturn
      LineNumberTable:
        line 55: 0
      LocalVariableTable:
        Start  Length  Slot  Name   Signature
            0       7     0  this   Lscala/concurrent/duration/package$DurationInt;
            0       7     1     c   Ljava/lang/Object;
            0       7     2    ev   Lscala/concurrent/duration/DurationConversions$Classifier;
    Signature: #104                         // <C:Ljava/lang/Object;>(TC;Lscala/concurrent/duration/DurationConversions$Classifier<TC;>;)Ljava/lang/Object;
    MethodParameters:
      Name                           Flags
      c                              final
      ev                             final

  public <C extends java.lang.Object> java.lang.Object microseconds(C, scala.concurrent.duration.DurationConversions$Classifier<C>);
    descriptor: (Ljava/lang/Object;Lscala/concurrent/duration/DurationConversions$Classifier;)Ljava/lang/Object;
    flags: (0x0001) ACC_PUBLIC
    Code:
      stack=3, locals=3, args_size=3
         0: aload_0
         1: aload_1
         2: aload_2
         3: invokestatic  #119                // InterfaceMethod scala/concurrent/duration/DurationConversions.microseconds$:(Lscala/concurrent/duration/DurationConversions;Ljava/lang/Object;Lscala/concurrent/duration/DurationConversions$Classifier;)Ljava/lang/Object;
         6: areturn
      LineNumberTable:
        line 55: 0
      LocalVariableTable:
        Start  Length  Slot  Name   Signature
            0       7     0  this   Lscala/concurrent/duration/package$DurationInt;
            0       7     1     c   Ljava/lang/Object;
            0       7     2    ev   Lscala/concurrent/duration/DurationConversions$Classifier;
    Signature: #104                         // <C:Ljava/lang/Object;>(TC;Lscala/concurrent/duration/DurationConversions$Classifier<TC;>;)Ljava/lang/Object;
    MethodParameters:
      Name                           Flags
      c                              final
      ev                             final

  public <C extends java.lang.Object> java.lang.Object micros(C, scala.concurrent.duration.DurationConversions$Classifier<C>);
    descriptor: (Ljava/lang/Object;Lscala/concurrent/duration/DurationConversions$Classifier;)Ljava/lang/Object;
    flags: (0x0001) ACC_PUBLIC
    Code:
      stack=3, locals=3, args_size=3
         0: aload_0
         1: aload_1
         2: aload_2
         3: invokestatic  #121                // InterfaceMethod scala/concurrent/duration/DurationConversions.micros$:(Lscala/concurrent/duration/DurationConversions;Ljava/lang/Object;Lscala/concurrent/duration/DurationConversions$Classifier;)Ljava/lang/Object;
         6: areturn
      LineNumberTable:
        line 55: 0
      LocalVariableTable:
        Start  Length  Slot  Name   Signature
            0       7     0  this   Lscala/concurrent/duration/package$DurationInt;
            0       7     1     c   Ljava/lang/Object;
            0       7     2    ev   Lscala/concurrent/duration/DurationConversions$Classifier;
    Signature: #104                         // <C:Ljava/lang/Object;>(TC;Lscala/concurrent/duration/DurationConversions$Classifier<TC;>;)Ljava/lang/Object;
    MethodParameters:
      Name                           Flags
      c                              final
      ev                             final

  public <C extends java.lang.Object> java.lang.Object microsecond(C, scala.concurrent.duration.DurationConversions$Classifier<C>);
    descriptor: (Ljava/lang/Object;Lscala/concurrent/duration/DurationConversions$Classifier;)Ljava/lang/Object;
    flags: (0x0001) ACC_PUBLIC
    Code:
      stack=3, locals=3, args_size=3
         0: aload_0
         1: aload_1
         2: aload_2
         3: invokestatic  #123                // InterfaceMethod scala/concurrent/duration/DurationConversions.microsecond$:(Lscala/concurrent/duration/DurationConversions;Ljava/lang/Object;Lscala/concurrent/duration/DurationConversions$Classifier;)Ljava/lang/Object;
         6: areturn
      LineNumberTable:
        line 55: 0
      LocalVariableTable:
        Start  Length  Slot  Name   Signature
            0       7     0  this   Lscala/concurrent/duration/package$DurationInt;
            0       7     1     c   Ljava/lang/Object;
            0       7     2    ev   Lscala/concurrent/duration/DurationConversions$Classifier;
    Signature: #104                         // <C:Ljava/lang/Object;>(TC;Lscala/concurrent/duration/DurationConversions$Classifier<TC;>;)Ljava/lang/Object;
    MethodParameters:
      Name                           Flags
      c                              final
      ev                             final

  public <C extends java.lang.Object> java.lang.Object micro(C, scala.concurrent.duration.DurationConversions$Classifier<C>);
    descriptor: (Ljava/lang/Object;Lscala/concurrent/duration/DurationConversions$Classifier;)Ljava/lang/Object;
    flags: (0x0001) ACC_PUBLIC
    Code:
      stack=3, locals=3, args_size=3
         0: aload_0
         1: aload_1
         2: aload_2
         3: invokestatic  #125                // InterfaceMethod scala/concurrent/duration/DurationConversions.micro$:(Lscala/concurrent/duration/DurationConversions;Ljava/lang/Object;Lscala/concurrent/duration/DurationConversions$Classifier;)Ljava/lang/Object;
         6: areturn
      LineNumberTable:
        line 55: 0
      LocalVariableTable:
        Start  Length  Slot  Name   Signature
            0       7     0  this   Lscala/concurrent/duration/package$DurationInt;
            0       7     1     c   Ljava/lang/Object;
            0       7     2    ev   Lscala/concurrent/duration/DurationConversions$Classifier;
    Signature: #104                         // <C:Ljava/lang/Object;>(TC;Lscala/concurrent/duration/DurationConversions$Classifier<TC;>;)Ljava/lang/Object;
    MethodParameters:
      Name                           Flags
      c                              final
      ev                             final

  public <C extends java.lang.Object> java.lang.Object milliseconds(C, scala.concurrent.duration.DurationConversions$Classifier<C>);
    descriptor: (Ljava/lang/Object;Lscala/concurrent/duration/DurationConversions$Classifier;)Ljava/lang/Object;
    flags: (0x0001) ACC_PUBLIC
    Code:
      stack=3, locals=3, args_size=3
         0: aload_0
         1: aload_1
         2: aload_2
         3: invokestatic  #127                // InterfaceMethod scala/concurrent/duration/DurationConversions.milliseconds$:(Lscala/concurrent/duration/DurationConversions;Ljava/lang/Object;Lscala/concurrent/duration/DurationConversions$Classifier;)Ljava/lang/Object;
         6: areturn
      LineNumberTable:
        line 55: 0
      LocalVariableTable:
        Start  Length  Slot  Name   Signature
            0       7     0  this   Lscala/concurrent/duration/package$DurationInt;
            0       7     1     c   Ljava/lang/Object;
            0       7     2    ev   Lscala/concurrent/duration/DurationConversions$Classifier;
    Signature: #104                         // <C:Ljava/lang/Object;>(TC;Lscala/concurrent/duration/DurationConversions$Classifier<TC;>;)Ljava/lang/Object;
    MethodParameters:
      Name                           Flags
      c                              final
      ev                             final

  public <C extends java.lang.Object> java.lang.Object millis(C, scala.concurrent.duration.DurationConversions$Classifier<C>);
    descriptor: (Ljava/lang/Object;Lscala/concurrent/duration/DurationConversions$Classifier;)Ljava/lang/Object;
    flags: (0x0001) ACC_PUBLIC
    Code:
      stack=3, locals=3, args_size=3
         0: aload_0
         1: aload_1
         2: aload_2
         3: invokestatic  #129                // InterfaceMethod scala/concurrent/duration/DurationConversions.millis$:(Lscala/concurrent/duration/DurationConversions;Ljava/lang/Object;Lscala/concurrent/duration/DurationConversions$Classifier;)Ljava/lang/Object;
         6: areturn
      LineNumberTable:
        line 55: 0
      LocalVariableTable:
        Start  Length  Slot  Name   Signature
            0       7     0  this   Lscala/concurrent/duration/package$DurationInt;
            0       7     1     c   Ljava/lang/Object;
            0       7     2    ev   Lscala/concurrent/duration/DurationConversions$Classifier;
    Signature: #104                         // <C:Ljava/lang/Object;>(TC;Lscala/concurrent/duration/DurationConversions$Classifier<TC;>;)Ljava/lang/Object;
    MethodParameters:
      Name                           Flags
      c                              final
      ev                             final

  public <C extends java.lang.Object> java.lang.Object millisecond(C, scala.concurrent.duration.DurationConversions$Classifier<C>);
    descriptor: (Ljava/lang/Object;Lscala/concurrent/duration/DurationConversions$Classifier;)Ljava/lang/Object;
    flags: (0x0001) ACC_PUBLIC
    Code:
      stack=3, locals=3, args_size=3
         0: aload_0
         1: aload_1
         2: aload_2
         3: invokestatic  #131                // InterfaceMethod scala/concurrent/duration/DurationConversions.millisecond$:(Lscala/concurrent/duration/DurationConversions;Ljava/lang/Object;Lscala/concurrent/duration/DurationConversions$Classifier;)Ljava/lang/Object;
         6: areturn
      LineNumberTable:
        line 55: 0
      LocalVariableTable:
        Start  Length  Slot  Name   Signature
            0       7     0  this   Lscala/concurrent/duration/package$DurationInt;
            0       7     1     c   Ljava/lang/Object;
            0       7     2    ev   Lscala/concurrent/duration/DurationConversions$Classifier;
    Signature: #104                         // <C:Ljava/lang/Object;>(TC;Lscala/concurrent/duration/DurationConversions$Classifier<TC;>;)Ljava/lang/Object;
    MethodParameters:
      Name                           Flags
      c                              final
      ev                             final

  public <C extends java.lang.Object> java.lang.Object milli(C, scala.concurrent.duration.DurationConversions$Classifier<C>);
    descriptor: (Ljava/lang/Object;Lscala/concurrent/duration/DurationConversions$Classifier;)Ljava/lang/Object;
    flags: (0x0001) ACC_PUBLIC
    Code:
      stack=3, locals=3, args_size=3
         0: aload_0
         1: aload_1
         2: aload_2
         3: invokestatic  #133                // InterfaceMethod scala/concurrent/duration/DurationConversions.milli$:(Lscala/concurrent/duration/DurationConversions;Ljava/lang/Object;Lscala/concurrent/duration/DurationConversions$Classifier;)Ljava/lang/Object;
         6: areturn
      LineNumberTable:
        line 55: 0
      LocalVariableTable:
        Start  Length  Slot  Name   Signature
            0       7     0  this   Lscala/concurrent/duration/package$DurationInt;
            0       7     1     c   Ljava/lang/Object;
            0       7     2    ev   Lscala/concurrent/duration/DurationConversions$Classifier;
    Signature: #104                         // <C:Ljava/lang/Object;>(TC;Lscala/concurrent/duration/DurationConversions$Classifier<TC;>;)Ljava/lang/Object;
    MethodParameters:
      Name                           Flags
      c                              final
      ev                             final

  public <C extends java.lang.Object> java.lang.Object seconds(C, scala.concurrent.duration.DurationConversions$Classifier<C>);
    descriptor: (Ljava/lang/Object;Lscala/concurrent/duration/DurationConversions$Classifier;)Ljava/lang/Object;
    flags: (0x0001) ACC_PUBLIC
    Code:
      stack=3, locals=3, args_size=3
         0: aload_0
         1: aload_1
         2: aload_2
         3: invokestatic  #135                // InterfaceMethod scala/concurrent/duration/DurationConversions.seconds$:(Lscala/concurrent/duration/DurationConversions;Ljava/lang/Object;Lscala/concurrent/duration/DurationConversions$Classifier;)Ljava/lang/Object;
         6: areturn
      LineNumberTable:
        line 55: 0
      LocalVariableTable:
        Start  Length  Slot  Name   Signature
            0       7     0  this   Lscala/concurrent/duration/package$DurationInt;
            0       7     1     c   Ljava/lang/Object;
            0       7     2    ev   Lscala/concurrent/duration/DurationConversions$Classifier;
    Signature: #104                         // <C:Ljava/lang/Object;>(TC;Lscala/concurrent/duration/DurationConversions$Classifier<TC;>;)Ljava/lang/Object;
    MethodParameters:
      Name                           Flags
      c                              final
      ev                             final

  public <C extends java.lang.Object> java.lang.Object second(C, scala.concurrent.duration.DurationConversions$Classifier<C>);
    descriptor: (Ljava/lang/Object;Lscala/concurrent/duration/DurationConversions$Classifier;)Ljava/lang/Object;
    flags: (0x0001) ACC_PUBLIC
    Code:
      stack=3, locals=3, args_size=3
         0: aload_0
         1: aload_1
         2: aload_2
         3: invokestatic  #137                // InterfaceMethod scala/concurrent/duration/DurationConversions.second$:(Lscala/concurrent/duration/DurationConversions;Ljava/lang/Object;Lscala/concurrent/duration/DurationConversions$Classifier;)Ljava/lang/Object;
         6: areturn
      LineNumberTable:
        line 55: 0
      LocalVariableTable:
        Start  Length  Slot  Name   Signature
            0       7     0  this   Lscala/concurrent/duration/package$DurationInt;
            0       7     1     c   Ljava/lang/Object;
            0       7     2    ev   Lscala/concurrent/duration/DurationConversions$Classifier;
    Signature: #104                         // <C:Ljava/lang/Object;>(TC;Lscala/concurrent/duration/DurationConversions$Classifier<TC;>;)Ljava/lang/Object;
    MethodParameters:
      Name                           Flags
      c                              final
      ev                             final

  public <C extends java.lang.Object> java.lang.Object minutes(C, scala.concurrent.duration.DurationConversions$Classifier<C>);
    descriptor: (Ljava/lang/Object;Lscala/concurrent/duration/DurationConversions$Classifier;)Ljava/lang/Object;
    flags: (0x0001) ACC_PUBLIC
    Code:
      stack=3, locals=3, args_size=3
         0: aload_0
         1: aload_1
         2: aload_2
         3: invokestatic  #139                // InterfaceMethod scala/concurrent/duration/DurationConversions.minutes$:(Lscala/concurrent/duration/DurationConversions;Ljava/lang/Object;Lscala/concurrent/duration/DurationConversions$Classifier;)Ljava/lang/Object;
         6: areturn
      LineNumberTable:
        line 55: 0
      LocalVariableTable:
        Start  Length  Slot  Name   Signature
            0       7     0  this   Lscala/concurrent/duration/package$DurationInt;
            0       7     1     c   Ljava/lang/Object;
            0       7     2    ev   Lscala/concurrent/duration/DurationConversions$Classifier;
    Signature: #104                         // <C:Ljava/lang/Object;>(TC;Lscala/concurrent/duration/DurationConversions$Classifier<TC;>;)Ljava/lang/Object;
    MethodParameters:
      Name                           Flags
      c                              final
      ev                             final

  public <C extends java.lang.Object> java.lang.Object minute(C, scala.concurrent.duration.DurationConversions$Classifier<C>);
    descriptor: (Ljava/lang/Object;Lscala/concurrent/duration/DurationConversions$Classifier;)Ljava/lang/Object;
    flags: (0x0001) ACC_PUBLIC
    Code:
      stack=3, locals=3, args_size=3
         0: aload_0
         1: aload_1
         2: aload_2
         3: invokestatic  #141                // InterfaceMethod scala/concurrent/duration/DurationConversions.minute$:(Lscala/concurrent/duration/DurationConversions;Ljava/lang/Object;Lscala/concurrent/duration/DurationConversions$Classifier;)Ljava/lang/Object;
         6: areturn
      LineNumberTable:
        line 55: 0
      LocalVariableTable:
        Start  Length  Slot  Name   Signature
            0       7     0  this   Lscala/concurrent/duration/package$DurationInt;
            0       7     1     c   Ljava/lang/Object;
            0       7     2    ev   Lscala/concurrent/duration/DurationConversions$Classifier;
    Signature: #104                         // <C:Ljava/lang/Object;>(TC;Lscala/concurrent/duration/DurationConversions$Classifier<TC;>;)Ljava/lang/Object;
    MethodParameters:
      Name                           Flags
      c                              final
      ev                             final

  public <C extends java.lang.Object> java.lang.Object hours(C, scala.concurrent.duration.DurationConversions$Classifier<C>);
    descriptor: (Ljava/lang/Object;Lscala/concurrent/duration/DurationConversions$Classifier;)Ljava/lang/Object;
    flags: (0x0001) ACC_PUBLIC
    Code:
      stack=3, locals=3, args_size=3
         0: aload_0
         1: aload_1
         2: aload_2
         3: invokestatic  #143                // InterfaceMethod scala/concurrent/duration/DurationConversions.hours$:(Lscala/concurrent/duration/DurationConversions;Ljava/lang/Object;Lscala/concurrent/duration/DurationConversions$Classifier;)Ljava/lang/Object;
         6: areturn
      LineNumberTable:
        line 55: 0
      LocalVariableTable:
        Start  Length  Slot  Name   Signature
            0       7     0  this   Lscala/concurrent/duration/package$DurationInt;
            0       7     1     c   Ljava/lang/Object;
            0       7     2    ev   Lscala/concurrent/duration/DurationConversions$Classifier;
    Signature: #104                         // <C:Ljava/lang/Object;>(TC;Lscala/concurrent/duration/DurationConversions$Classifier<TC;>;)Ljava/lang/Object;
    MethodParameters:
      Name                           Flags
      c                              final
      ev                             final

  public <C extends java.lang.Object> java.lang.Object hour(C, scala.concurrent.duration.DurationConversions$Classifier<C>);
    descriptor: (Ljava/lang/Object;Lscala/concurrent/duration/DurationConversions$Classifier;)Ljava/lang/Object;
    flags: (0x0001) ACC_PUBLIC
    Code:
      stack=3, locals=3, args_size=3
         0: aload_0
         1: aload_1
         2: aload_2
         3: invokestatic  #145                // InterfaceMethod scala/concurrent/duration/DurationConversions.hour$:(Lscala/concurrent/duration/DurationConversions;Ljava/lang/Object;Lscala/concurrent/duration/DurationConversions$Classifier;)Ljava/lang/Object;
         6: areturn
      LineNumberTable:
        line 55: 0
      LocalVariableTable:
        Start  Length  Slot  Name   Signature
            0       7     0  this   Lscala/concurrent/duration/package$DurationInt;
            0       7     1     c   Ljava/lang/Object;
            0       7     2    ev   Lscala/concurrent/duration/DurationConversions$Classifier;
    Signature: #104                         // <C:Ljava/lang/Object;>(TC;Lscala/concurrent/duration/DurationConversions$Classifier<TC;>;)Ljava/lang/Object;
    MethodParameters:
      Name                           Flags
      c                              final
      ev                             final

  public <C extends java.lang.Object> java.lang.Object days(C, scala.concurrent.duration.DurationConversions$Classifier<C>);
    descriptor: (Ljava/lang/Object;Lscala/concurrent/duration/DurationConversions$Classifier;)Ljava/lang/Object;
    flags: (0x0001) ACC_PUBLIC
    Code:
      stack=3, locals=3, args_size=3
         0: aload_0
         1: aload_1
         2: aload_2
         3: invokestatic  #147                // InterfaceMethod scala/concurrent/duration/DurationConversions.days$:(Lscala/concurrent/duration/DurationConversions;Ljava/lang/Object;Lscala/concurrent/duration/DurationConversions$Classifier;)Ljava/lang/Object;
         6: areturn
      LineNumberTable:
        line 55: 0
      LocalVariableTable:
        Start  Length  Slot  Name   Signature
            0       7     0  this   Lscala/concurrent/duration/package$DurationInt;
            0       7     1     c   Ljava/lang/Object;
            0       7     2    ev   Lscala/concurrent/duration/DurationConversions$Classifier;
    Signature: #104                         // <C:Ljava/lang/Object;>(TC;Lscala/concurrent/duration/DurationConversions$Classifier<TC;>;)Ljava/lang/Object;
    MethodParameters:
      Name                           Flags
      c                              final
      ev                             final

  public <C extends java.lang.Object> java.lang.Object day(C, scala.concurrent.duration.DurationConversions$Classifier<C>);
    descriptor: (Ljava/lang/Object;Lscala/concurrent/duration/DurationConversions$Classifier;)Ljava/lang/Object;
    flags: (0x0001) ACC_PUBLIC
    Code:
      stack=3, locals=3, args_size=3
         0: aload_0
         1: aload_1
         2: aload_2
         3: invokestatic  #149                // InterfaceMethod scala/concurrent/duration/DurationConversions.day$:(Lscala/concurrent/duration/DurationConversions;Ljava/lang/Object;Lscala/concurrent/duration/DurationConversions$Classifier;)Ljava/lang/Object;
         6: areturn
      LineNumberTable:
        line 55: 0
      LocalVariableTable:
        Start  Length  Slot  Name   Signature
            0       7     0  this   Lscala/concurrent/duration/package$DurationInt;
            0       7     1     c   Ljava/lang/Object;
            0       7     2    ev   Lscala/concurrent/duration/DurationConversions$Classifier;
    Signature: #104                         // <C:Ljava/lang/Object;>(TC;Lscala/concurrent/duration/DurationConversions$Classifier<TC;>;)Ljava/lang/Object;
    MethodParameters:
      Name                           Flags
      c                              final
      ev                             final

  public int scala$concurrent$duration$DurationInt$$n();
    descriptor: ()I
    flags: (0x0001) ACC_PUBLIC
    Code:
      stack=1, locals=1, args_size=1
         0: aload_0
         1: getfield      #152                // Field scala$concurrent$duration$DurationInt$$n:I
         4: ireturn
      LineNumberTable:
        line 55: 0
      LocalVariableTable:
        Start  Length  Slot  Name   Signature
            0       5     0  this   Lscala/concurrent/duration/package$DurationInt;

  public scala.concurrent.duration.FiniteDuration durationIn(java.util.concurrent.TimeUnit);
    descriptor: (Ljava/util/concurrent/TimeUnit;)Lscala/concurrent/duration/FiniteDuration;
    flags: (0x0001) ACC_PUBLIC
    Code:
      stack=5, locals=5, args_size=2
         0: getstatic     #159                // Field scala/concurrent/duration/package$DurationInt$.MODULE$:Lscala/concurrent/duration/package$DurationInt$;
         3: pop
         4: aload_0
         5: invokevirtual #161                // Method scala$concurrent$duration$DurationInt$$n:()I
         8: istore_2
         9: getstatic     #166                // Field scala/concurrent/duration/Duration$.MODULE$:Lscala/concurrent/duration/Duration$;
        12: pop
        13: iload_2
        14: i2l
        15: lstore_3
        16: new           #168                // class scala/concurrent/duration/FiniteDuration
        19: dup
        20: lload_3
        21: aload_1
        22: invokespecial #172                // Method scala/concurrent/duration/FiniteDuration."<init>":(JLjava/util/concurrent/TimeUnit;)V
        25: areturn
      LineNumberTable:
        line 56: 0
        line 56: 9
        line 56: 25
      LocalVariableTable:
        Start  Length  Slot  Name   Signature
            0      26     0  this   Lscala/concurrent/duration/package$DurationInt;
            0      26     1  unit   Ljava/util/concurrent/TimeUnit;
            9      16     2 durationIn$extension_$this   I
           16       9     3 durationIn$extension_apply_length   J
    MethodParameters:
      Name                           Flags
      unit                           final

  public int hashCode();
    descriptor: ()I
    flags: (0x0001) ACC_PUBLIC
    Code:
      stack=1, locals=1, args_size=1
         0: getstatic     #159                // Field scala/concurrent/duration/package$DurationInt$.MODULE$:Lscala/concurrent/duration/package$DurationInt$;
         3: pop
         4: aload_0
         5: invokevirtual #161                // Method scala$concurrent$duration$DurationInt$$n:()I
         8: invokestatic  #182                // Method java/lang/Integer.hashCode:(I)I
        11: ireturn
      LineNumberTable:
        line 55: 0
        line 55: 8
        line 55: 11
      LocalVariableTable:
        Start  Length  Slot  Name   Signature
            0      12     0  this   Lscala/concurrent/duration/package$DurationInt;

  public boolean equals(java.lang.Object);
    descriptor: (Ljava/lang/Object;)Z
    flags: (0x0001) ACC_PUBLIC
    Code:
      stack=3, locals=2, args_size=2
         0: getstatic     #159                // Field scala/concurrent/duration/package$DurationInt$.MODULE$:Lscala/concurrent/duration/package$DurationInt$;
         3: aload_0
         4: invokevirtual #161                // Method scala$concurrent$duration$DurationInt$$n:()I
         7: aload_1
         8: invokevirtual #189                // Method scala/concurrent/duration/package$DurationInt$.equals$extension:(ILjava/lang/Object;)Z
        11: ireturn
      LineNumberTable:
        line 55: 0
      LocalVariableTable:
        Start  Length  Slot  Name   Signature
            0      12     0  this   Lscala/concurrent/duration/package$DurationInt;
            0      12     1   x$1   Ljava/lang/Object;
    MethodParameters:
      Name                           Flags
      x$1                            final

  public scala.concurrent.duration.package$DurationInt(int);
    descriptor: (I)V
    flags: (0x0001) ACC_PUBLIC
    Code:
      stack=2, locals=2, args_size=2
         0: aload_0
         1: iload_1
         2: putfield      #152                // Field scala$concurrent$duration$DurationInt$$n:I
         5: aload_0
         6: invokespecial #194                // Method java/lang/Object."<init>":()V
         9: return
      LineNumberTable:
        line 55: 0
      LocalVariableTable:
        Start  Length  Slot  Name   Signature
            0      10     0  this   Lscala/concurrent/duration/package$DurationInt;
            0      10     1     n   I
    MethodParameters:
      Name                           Flags
      n                              final
}
InnerClasses:
  public static #10= #9 of #6;            // Classifier=class scala/concurrent/duration/DurationConversions$Classifier of class scala/concurrent/duration/DurationConversions
  public static final #13= #2 of #12;     // DurationInt=class scala/concurrent/duration/package$DurationInt of class scala/concurrent/duration/package
  public static #16= #15 of #12;          // DurationInt$=class scala/concurrent/duration/package$DurationInt$ of class scala/concurrent/duration/package
SourceFile: "package.scala"
  ScalaInlineInfo: length = 0xE5 (unknown attribute)
   01 01 00 2D 00 A9 00 BE 01 00 63 00 14 01 00 63
   00 67 01 00 5F 00 14 01 00 5F 00 67 01 00 99 00
   9A 01 00 B7 00 B8 01 00 B1 00 96 01 00 5B 00 14
   01 00 5B 00 67 01 00 57 00 14 01 00 57 00 67 01
   00 33 00 14 01 00 33 00 67 01 00 2B 00 14 01 00
   2B 00 67 01 00 2F 00 14 01 00 2F 00 67 01 00 27
   00 14 01 00 27 00 67 01 00 43 00 14 01 00 43 00
   67 01 00 3B 00 14 01 00 3B 00 67 01 00 3F 00 14
   01 00 3F 00 67 01 00 37 00 14 01 00 37 00 67 01
   00 53 00 14 01 00 53 00 67 01 00 4F 00 14 01 00
   4F 00 67 01 00 23 00 14 01 00 23 00 67 01 00 1B
   00 14 01 00 1B 00 67 01 00 1F 00 14 01 00 1F 00
   67 01 00 13 00 14 01 00 13 00 67 01 00 11 00 96
   01 00 4B 00 14 01 00 4B 00 67 01 00 47 00 14 01
   00 47 00 67 01
  Scala: length = 0x0 (unknown attribute)

