Classfile /Users/mw/Projects/slang-braindump/.jar/jar11/assemble/slang-braindump/assemble/content/shapeless/ops/coproduct$Remove.class
  Last modified May 29, 2022; size 1849 bytes
  SHA-256 checksum 5525177d4a0976ef39127d6ce189dcc16b33d62823fb4800f73a072a8dfeb1a7
  Compiled from "coproduct.scala"
public interface shapeless.ops.coproduct$Remove<C extends shapeless.Coproduct, U extends java.lang.Object> extends shapeless.package$DepFn1<C>, java.io.Serializable
  minor version: 0
  major version: 52
  flags: (0x0601) ACC_PUBLIC, ACC_INTERFACE, ACC_ABSTRACT
  this_class: #2                          // shapeless/ops/coproduct$Remove
  super_class: #5                         // java/lang/Object
  interfaces: 2, fields: 0, methods: 4, attributes: 5
Constant pool:
   #1 = Utf8               shapeless/ops/coproduct$Remove
   #2 = Class              #1             // shapeless/ops/coproduct$Remove
   #3 = Utf8               <C::Lshapeless/Coproduct;U:Ljava/lang/Object;>Ljava/lang/Object;Lshapeless/package$DepFn1<TC;>;Ljava/io/Serializable;
   #4 = Utf8               java/lang/Object
   #5 = Class              #4             // java/lang/Object
   #6 = Utf8               shapeless/package$DepFn1
   #7 = Class              #6             // shapeless/package$DepFn1
   #8 = Utf8               java/io/Serializable
   #9 = Class              #8             // java/io/Serializable
  #10 = Utf8               coproduct.scala
  #11 = Utf8               shapeless/ops/coproduct
  #12 = Class              #11            // shapeless/ops/coproduct
  #13 = Utf8               Remove
  #14 = Utf8               shapeless/package
  #15 = Class              #14            // shapeless/package
  #16 = Utf8               DepFn1
  #17 = Utf8               inverse
  #18 = Utf8               (Lscala/util/Either;)Lshapeless/Coproduct;
  #19 = Utf8               (Lscala/util/Either<TU;Lshapeless/Coproduct;>;)TC;
  #20 = Utf8               r
  #21 = Utf8               coproduct$
  #22 = Utf8               (Lshapeless/ops/coproduct$Remove;Lshapeless/Coproduct;)Lshapeless/$colon$plus$colon;
  #23 = Utf8               $this
  #24 = Utf8               c
  #25 = Utf8               coproduct
  #26 = Utf8               (Lshapeless/Coproduct;)Lshapeless/$colon$plus$colon;
  #27 = NameAndType        #25:#26        // coproduct:(Lshapeless/Coproduct;)Lshapeless/$colon$plus$colon;
  #28 = InterfaceMethodref #2.#27         // shapeless/ops/coproduct$Remove.coproduct:(Lshapeless/Coproduct;)Lshapeless/$colon$plus$colon;
  #29 = Utf8               Lshapeless/ops/coproduct$Remove;
  #30 = Utf8               Lshapeless/Coproduct;
  #31 = Utf8               (TC;)Lshapeless/$colon$plus$colon<TU;Lshapeless/Coproduct;>;
  #32 = Utf8               apply
  #33 = Utf8               (Ljava/lang/Object;)Ljava/lang/Object;
  #34 = NameAndType        #32:#33        // apply:(Ljava/lang/Object;)Ljava/lang/Object;
  #35 = InterfaceMethodref #2.#34         // shapeless/ops/coproduct$Remove.apply:(Ljava/lang/Object;)Ljava/lang/Object;
  #36 = Utf8               scala/util/Either
  #37 = Class              #36            // scala/util/Either
  #38 = Utf8               scala/util/Left
  #39 = Class              #38            // scala/util/Left
  #40 = Utf8               value
  #41 = Utf8               ()Ljava/lang/Object;
  #42 = NameAndType        #40:#41        // value:()Ljava/lang/Object;
  #43 = Methodref          #39.#42        // scala/util/Left.value:()Ljava/lang/Object;
  #44 = Utf8               shapeless/Inl
  #45 = Class              #44            // shapeless/Inl
  #46 = Utf8               <init>
  #47 = Utf8               (Ljava/lang/Object;)V
  #48 = NameAndType        #46:#47        // "<init>":(Ljava/lang/Object;)V
  #49 = Methodref          #45.#48        // shapeless/Inl."<init>":(Ljava/lang/Object;)V
  #50 = Utf8               scala/util/Right
  #51 = Class              #50            // scala/util/Right
  #52 = Methodref          #51.#42        // scala/util/Right.value:()Ljava/lang/Object;
  #53 = Utf8               shapeless/Coproduct
  #54 = Class              #53            // shapeless/Coproduct
  #55 = Utf8               shapeless/Inr
  #56 = Class              #55            // shapeless/Inr
  #57 = Utf8               (Lshapeless/Coproduct;)V
  #58 = NameAndType        #46:#57        // "<init>":(Lshapeless/Coproduct;)V
  #59 = Methodref          #56.#58        // shapeless/Inr."<init>":(Lshapeless/Coproduct;)V
  #60 = Utf8               scala/MatchError
  #61 = Class              #60            // scala/MatchError
  #62 = Methodref          #61.#48        // scala/MatchError."<init>":(Ljava/lang/Object;)V
  #63 = Utf8               u
  #64 = Utf8               Ljava/lang/Object;
  #65 = Utf8               this
  #66 = Utf8               $init$
  #67 = Utf8               (Lshapeless/ops/coproduct$Remove;)V
  #68 = Utf8               Signature
  #69 = Utf8               MethodParameters
  #70 = Utf8               Code
  #71 = Utf8               LineNumberTable
  #72 = Utf8               LocalVariableTable
  #73 = Utf8               StackMapTable
  #74 = Utf8               InnerClasses
  #75 = Utf8               SourceFile
  #76 = Utf8               ScalaInlineInfo
  #77 = Utf8               Scala
{
  public abstract C inverse(scala.util.Either<U, shapeless.Coproduct>);
    descriptor: (Lscala/util/Either;)Lshapeless/Coproduct;
    flags: (0x0401) ACC_PUBLIC, ACC_ABSTRACT
    Signature: #19                          // (Lscala/util/Either<TU;Lshapeless/Coproduct;>;)TC;
    MethodParameters:
      Name                           Flags
      r                              final

  public static shapeless.$colon$plus$colon coproduct$(shapeless.ops.coproduct$Remove, shapeless.Coproduct);
    descriptor: (Lshapeless/ops/coproduct$Remove;Lshapeless/Coproduct;)Lshapeless/$colon$plus$colon;
    flags: (0x1009) ACC_PUBLIC, ACC_STATIC, ACC_SYNTHETIC
    Code:
      stack=2, locals=2, args_size=2
         0: aload_0
         1: aload_1
         2: invokespecial #28                 // InterfaceMethod coproduct:(Lshapeless/Coproduct;)Lshapeless/$colon$plus$colon;
         5: areturn
      LineNumberTable:
        line 195: 0
      LocalVariableTable:
        Start  Length  Slot  Name   Signature
            0       6     0 $this   Lshapeless/ops/coproduct$Remove;
            0       6     1     c   Lshapeless/Coproduct;
    MethodParameters:
      Name                           Flags
      $this                          final synthetic
      c                              final

  public default shapeless.$colon$plus$colon<U, shapeless.Coproduct> coproduct(C);
    descriptor: (Lshapeless/Coproduct;)Lshapeless/$colon$plus$colon;
    flags: (0x0001) ACC_PUBLIC
    Code:
      stack=3, locals=8, args_size=2
         0: aload_0
         1: aload_1
         2: invokeinterface #35,  2           // InterfaceMethod apply:(Ljava/lang/Object;)Ljava/lang/Object;
         7: checkcast     #37                 // class scala/util/Either
        10: astore_3
        11: aload_3
        12: instanceof    #39                 // class scala/util/Left
        15: ifeq          44
        18: aload_3
        19: checkcast     #39                 // class scala/util/Left
        22: astore        4
        24: aload         4
        26: invokevirtual #43                 // Method scala/util/Left.value:()Ljava/lang/Object;
        29: astore        5
        31: new           #45                 // class shapeless/Inl
        34: dup
        35: aload         5
        37: invokespecial #49                 // Method shapeless/Inl."<init>":(Ljava/lang/Object;)V
        40: astore_2
        41: goto          95
        44: goto          47
        47: aload_3
        48: instanceof    #51                 // class scala/util/Right
        51: ifeq          83
        54: aload_3
        55: checkcast     #51                 // class scala/util/Right
        58: astore        6
        60: aload         6
        62: invokevirtual #52                 // Method scala/util/Right.value:()Ljava/lang/Object;
        65: checkcast     #54                 // class shapeless/Coproduct
        68: astore        7
        70: new           #56                 // class shapeless/Inr
        73: dup
        74: aload         7
        76: invokespecial #59                 // Method shapeless/Inr."<init>":(Lshapeless/Coproduct;)V
        79: astore_2
        80: goto          95
        83: goto          86
        86: new           #61                 // class scala/MatchError
        89: dup
        90: aload_3
        91: invokespecial #62                 // Method scala/MatchError."<init>":(Ljava/lang/Object;)V
        94: athrow
        95: aload_2
        96: areturn
      StackMapTable: number_of_entries = 5
        frame_type = 253 /* append */
          offset_delta = 44
          locals = [ top, class scala/util/Either ]
        frame_type = 2 /* same */
        frame_type = 35 /* same */
        frame_type = 2 /* same */
        frame_type = 255 /* full_frame */
          offset_delta = 8
          locals = [ class shapeless/ops/coproduct$Remove, class shapeless/Coproduct, class java/lang/Object, class scala/util/Either ]
          stack = []
      LineNumberTable:
        line 195: 0
        line 196: 11
        line 197: 47
        line 195: 86
      LocalVariableTable:
        Start  Length  Slot  Name   Signature
           29      15     5     u   Ljava/lang/Object;
           68      15     7     r   Lshapeless/Coproduct;
            0      97     0  this   Lshapeless/ops/coproduct$Remove;
            0      97     1     c   Lshapeless/Coproduct;
    Signature: #31                          // (TC;)Lshapeless/$colon$plus$colon<TU;Lshapeless/Coproduct;>;
    MethodParameters:
      Name                           Flags
      c                              final

  public static void $init$(shapeless.ops.coproduct$Remove);
    descriptor: (Lshapeless/ops/coproduct$Remove;)V
    flags: (0x0009) ACC_PUBLIC, ACC_STATIC
    Code:
      stack=0, locals=1, args_size=1
         0: return
      LineNumberTable:
        line 190: 0
      LocalVariableTable:
        Start  Length  Slot  Name   Signature
            0       1     0 $this   Lshapeless/ops/coproduct$Remove;
    MethodParameters:
      Name                           Flags
      $this                          final synthetic
}
InnerClasses:
  public static #13= #2 of #12;           // Remove=class shapeless/ops/coproduct$Remove of class shapeless/ops/coproduct
  public static #16= #7 of #15;           // DepFn1=class shapeless/package$DepFn1 of class shapeless/package
Signature: #3                           // <C::Lshapeless/Coproduct;U:Ljava/lang/Object;>Ljava/lang/Object;Lshapeless/package$DepFn1<TC;>;Ljava/io/Serializable;
SourceFile: "coproduct.scala"
  ScalaInlineInfo: length = 0x18 (unknown attribute)
   01 00 00 04 00 42 00 43 01 00 15 00 16 01 00 19
   00 1A 00 00 11 00 12 00
  Scala: length = 0x0 (unknown attribute)

