Classfile /Users/mw/Projects/slang-braindump/.jar/jar11/assemble/slang-braindump/assemble/content/shapeless/ops/coproduct$Drop$.class
  Last modified May 29, 2022; size 1799 bytes
  SHA-256 checksum cd1cbf5f658c62a7f6d753d977bdca2b2d29b5a55cfe5d2856455e29c7daf830
  Compiled from "coproduct.scala"
public class shapeless.ops.coproduct$Drop$ implements java.io.Serializable
  minor version: 0
  major version: 52
  flags: (0x0021) ACC_PUBLIC, ACC_SUPER
  this_class: #2                          // shapeless/ops/coproduct$Drop$
  super_class: #4                         // java/lang/Object
  interfaces: 1, fields: 1, methods: 6, attributes: 4
Constant pool:
   #1 = Utf8               shapeless/ops/coproduct$Drop$
   #2 = Class              #1             // shapeless/ops/coproduct$Drop$
   #3 = Utf8               java/lang/Object
   #4 = Class              #3             // java/lang/Object
   #5 = Utf8               java/io/Serializable
   #6 = Class              #5             // java/io/Serializable
   #7 = Utf8               coproduct.scala
   #8 = Utf8               shapeless/ops/coproduct$Drop
   #9 = Class              #8             // shapeless/ops/coproduct$Drop
  #10 = Utf8               shapeless/ops/coproduct
  #11 = Class              #10            // shapeless/ops/coproduct
  #12 = Utf8               Drop
  #13 = Utf8               Drop$
  #14 = Utf8               shapeless/ops/coproduct$Drop$$anon$59
  #15 = Class              #14            // shapeless/ops/coproduct$Drop$$anon$59
  #16 = Utf8               shapeless/ops/coproduct$Drop$$anon$60
  #17 = Class              #16            // shapeless/ops/coproduct$Drop$$anon$60
  #18 = Utf8               MODULE$
  #19 = Utf8               Lshapeless/ops/coproduct$Drop$;
  #20 = Utf8               <clinit>
  #21 = Utf8               ()V
  #22 = Utf8               <init>
  #23 = NameAndType        #22:#21        // "<init>":()V
  #24 = Methodref          #2.#23         // shapeless/ops/coproduct$Drop$."<init>":()V
  #25 = NameAndType        #18:#19        // MODULE$:Lshapeless/ops/coproduct$Drop$;
  #26 = Fieldref           #2.#25         // shapeless/ops/coproduct$Drop$.MODULE$:Lshapeless/ops/coproduct$Drop$;
  #27 = Utf8               apply
  #28 = Utf8               (Lshapeless/ops/coproduct$Drop;)Lshapeless/ops/coproduct$Drop;
  #29 = Utf8               <C::Lshapeless/Coproduct;N::Lshapeless/Nat;>(Lshapeless/ops/coproduct$Drop<TC;TN;>;)Lshapeless/ops/coproduct$Drop<TC;TN;>;
  #30 = Utf8               drop
  #31 = Utf8               this
  #32 = Utf8               Lshapeless/ops/coproduct$Drop;
  #33 = Utf8               dropZero
  #34 = Utf8               ()Lshapeless/ops/coproduct$Drop;
  #35 = Utf8               <C::Lshapeless/Coproduct;>()Lshapeless/ops/coproduct$Drop<TC;Lshapeless/_0;>;
  #36 = Methodref          #15.#23        // shapeless/ops/coproduct$Drop$$anon$59."<init>":()V
  #37 = Utf8               dropSucc
  #38 = Utf8               <H:Ljava/lang/Object;T::Lshapeless/Coproduct;N::Lshapeless/Nat;>(Lshapeless/ops/coproduct$Drop<TT;TN;>;)Lshapeless/ops/coproduct$Drop<Lshapeless/$colon$plus$colon<TH;TT;>;Lshapeless/Succ<TN;>;>;
  #39 = Utf8               tail
  #40 = Utf8               (Lshapeless/ops/coproduct$Drop;)V
  #41 = NameAndType        #22:#40        // "<init>":(Lshapeless/ops/coproduct$Drop;)V
  #42 = Methodref          #17.#41        // shapeless/ops/coproduct$Drop$$anon$60."<init>":(Lshapeless/ops/coproduct$Drop;)V
  #43 = Utf8               writeReplace
  #44 = Utf8               ()Ljava/lang/Object;
  #45 = Utf8               scala/runtime/ModuleSerializationProxy
  #46 = Class              #45            // scala/runtime/ModuleSerializationProxy
  #47 = Utf8               (Ljava/lang/Class;)V
  #48 = NameAndType        #22:#47        // "<init>":(Ljava/lang/Class;)V
  #49 = Methodref          #46.#48        // scala/runtime/ModuleSerializationProxy."<init>":(Ljava/lang/Class;)V
  #50 = Methodref          #4.#23         // java/lang/Object."<init>":()V
  #51 = Utf8               Code
  #52 = Utf8               LineNumberTable
  #53 = Utf8               LocalVariableTable
  #54 = Utf8               Signature
  #55 = Utf8               MethodParameters
  #56 = Utf8               InnerClasses
  #57 = Utf8               SourceFile
  #58 = Utf8               ScalaInlineInfo
  #59 = Utf8               Scala
{
  public static final shapeless.ops.coproduct$Drop$ MODULE$;
    descriptor: Lshapeless/ops/coproduct$Drop$;
    flags: (0x0019) ACC_PUBLIC, ACC_STATIC, ACC_FINAL

  public static {};
    descriptor: ()V
    flags: (0x0009) ACC_PUBLIC, ACC_STATIC
    Code:
      stack=2, locals=0, args_size=0
         0: new           #2                  // class shapeless/ops/coproduct$Drop$
         3: dup
         4: invokespecial #24                 // Method "<init>":()V
         7: putstatic     #26                 // Field MODULE$:Lshapeless/ops/coproduct$Drop$;
        10: return
      LineNumberTable:
        line 949: 0

  public <C extends shapeless.Coproduct, N extends shapeless.Nat> shapeless.ops.coproduct$Drop<C, N> apply(shapeless.ops.coproduct$Drop<C, N>);
    descriptor: (Lshapeless/ops/coproduct$Drop;)Lshapeless/ops/coproduct$Drop;
    flags: (0x0001) ACC_PUBLIC
    Code:
      stack=1, locals=2, args_size=2
         0: aload_1
         1: areturn
      LineNumberTable:
        line 950: 0
      LocalVariableTable:
        Start  Length  Slot  Name   Signature
            0       2     0  this   Lshapeless/ops/coproduct$Drop$;
            0       2     1  drop   Lshapeless/ops/coproduct$Drop;
    Signature: #29                          // <C::Lshapeless/Coproduct;N::Lshapeless/Nat;>(Lshapeless/ops/coproduct$Drop<TC;TN;>;)Lshapeless/ops/coproduct$Drop<TC;TN;>;
    MethodParameters:
      Name                           Flags
      drop                           final

  public <C extends shapeless.Coproduct> shapeless.ops.coproduct$Drop<C, shapeless._0> dropZero();
    descriptor: ()Lshapeless/ops/coproduct$Drop;
    flags: (0x0001) ACC_PUBLIC
    Code:
      stack=2, locals=1, args_size=1
         0: new           #15                 // class shapeless/ops/coproduct$Drop$$anon$59
         3: dup
         4: invokespecial #36                 // Method shapeless/ops/coproduct$Drop$$anon$59."<init>":()V
         7: areturn
      LineNumberTable:
        line 955: 0
      LocalVariableTable:
        Start  Length  Slot  Name   Signature
            0       8     0  this   Lshapeless/ops/coproduct$Drop$;
    Signature: #35                          // <C::Lshapeless/Coproduct;>()Lshapeless/ops/coproduct$Drop<TC;Lshapeless/_0;>;

  public <H extends java.lang.Object, T extends shapeless.Coproduct, N extends shapeless.Nat> shapeless.ops.coproduct$Drop<shapeless.$colon$plus$colon<H, T>, shapeless.Succ<N>> dropSucc(shapeless.ops.coproduct$Drop<T, N>);
    descriptor: (Lshapeless/ops/coproduct$Drop;)Lshapeless/ops/coproduct$Drop;
    flags: (0x0001) ACC_PUBLIC
    Code:
      stack=3, locals=2, args_size=2
         0: new           #17                 // class shapeless/ops/coproduct$Drop$$anon$60
         3: dup
         4: aload_1
         5: invokespecial #42                 // Method shapeless/ops/coproduct$Drop$$anon$60."<init>":(Lshapeless/ops/coproduct$Drop;)V
         8: areturn
      LineNumberTable:
        line 962: 0
      LocalVariableTable:
        Start  Length  Slot  Name   Signature
            0       9     0  this   Lshapeless/ops/coproduct$Drop$;
            0       9     1  tail   Lshapeless/ops/coproduct$Drop;
    Signature: #38                          // <H:Ljava/lang/Object;T::Lshapeless/Coproduct;N::Lshapeless/Nat;>(Lshapeless/ops/coproduct$Drop<TT;TN;>;)Lshapeless/ops/coproduct$Drop<Lshapeless/$colon$plus$colon<TH;TT;>;Lshapeless/Succ<TN;>;>;
    MethodParameters:
      Name                           Flags
      tail                           final

  private java.lang.Object writeReplace();
    descriptor: ()Ljava/lang/Object;
    flags: (0x0002) ACC_PRIVATE
    Code:
      stack=3, locals=1, args_size=1
         0: new           #46                 // class scala/runtime/ModuleSerializationProxy
         3: dup
         4: ldc           #2                  // class shapeless/ops/coproduct$Drop$
         6: invokespecial #49                 // Method scala/runtime/ModuleSerializationProxy."<init>":(Ljava/lang/Class;)V
         9: areturn
      LineNumberTable:
        line 949: 0
      LocalVariableTable:
        Start  Length  Slot  Name   Signature
            0      10     0  this   Lshapeless/ops/coproduct$Drop$;

  public shapeless.ops.coproduct$Drop$();
    descriptor: ()V
    flags: (0x0001) ACC_PUBLIC
    Code:
      stack=1, locals=1, args_size=1
         0: aload_0
         1: invokespecial #50                 // Method java/lang/Object."<init>":()V
         4: return
      LineNumberTable:
        line 977: 0
        line 949: 4
      LocalVariableTable:
        Start  Length  Slot  Name   Signature
            0       5     0  this   Lshapeless/ops/coproduct$Drop$;
}
InnerClasses:
  public static #12= #9 of #11;           // Drop=class shapeless/ops/coproduct$Drop of class shapeless/ops/coproduct
  public static #13= #2 of #11;           // Drop$=class shapeless/ops/coproduct$Drop$ of class shapeless/ops/coproduct
  public final #15;                       // class shapeless/ops/coproduct$Drop$$anon$59
  public final #17;                       // class shapeless/ops/coproduct$Drop$$anon$60
SourceFile: "coproduct.scala"
  ScalaInlineInfo: length = 0x1D (unknown attribute)
   01 01 00 05 00 16 00 15 01 00 1B 00 1C 01 00 25
   00 1C 01 00 21 00 22 01 00 2B 00 2C 01
  Scala: length = 0x0 (unknown attribute)

