Classfile /Users/mw/Projects/slang-braindump/.jar/jar11/assemble/slang-braindump/assemble/content/shapeless/ops/coproduct$Reverse$Reverse0$$anon$63.class
  Last modified May 29, 2022; size 2509 bytes
  SHA-256 checksum 704c75eebe7af098bddbd1862c7f8588338f975a7f4be9a7ed5abb7f69c1f866
  Compiled from "coproduct.scala"
public final class shapeless.ops.coproduct$Reverse$Reverse0$$anon$63 extends java.lang.Object implements shapeless.ops.coproduct$Reverse$Reverse0<Acc, shapeless.$colon$plus$colon<InH, InT>, Out>
  minor version: 0
  major version: 52
  flags: (0x0031) ACC_PUBLIC, ACC_FINAL, ACC_SUPER
  this_class: #2                          // shapeless/ops/coproduct$Reverse$Reverse0$$anon$63
  super_class: #5                         // java/lang/Object
  interfaces: 1, fields: 1, methods: 2, attributes: 6
Constant pool:
    #1 = Utf8               shapeless/ops/coproduct$Reverse$Reverse0$$anon$63
    #2 = Class              #1            // shapeless/ops/coproduct$Reverse$Reverse0$$anon$63
    #3 = Utf8               Ljava/lang/Object;Lshapeless/ops/coproduct$Reverse$Reverse0<TAcc;Lshapeless/$colon$plus$colon<TInH;TInT;>;TOut;>;
    #4 = Utf8               java/lang/Object
    #5 = Class              #4            // java/lang/Object
    #6 = Utf8               shapeless/ops/coproduct$Reverse$Reverse0
    #7 = Class              #6            // shapeless/ops/coproduct$Reverse$Reverse0
    #8 = Utf8               coproduct.scala
    #9 = Utf8               shapeless/ops/coproduct$Reverse$Reverse0$
   #10 = Class              #9            // shapeless/ops/coproduct$Reverse$Reverse0$
   #11 = Utf8               cconsReverse
   #12 = Utf8               (Lshapeless/ops/coproduct$Reverse$Reverse0;)Lshapeless/ops/coproduct$Reverse$Reverse0;
   #13 = NameAndType        #11:#12       // cconsReverse:(Lshapeless/ops/coproduct$Reverse$Reverse0;)Lshapeless/ops/coproduct$Reverse$Reverse0;
   #14 = Utf8               shapeless/ops/coproduct$Reverse$
   #15 = Class              #14           // shapeless/ops/coproduct$Reverse$
   #16 = Utf8               shapeless/ops/coproduct
   #17 = Class              #16           // shapeless/ops/coproduct
   #18 = Utf8               Reverse$
   #19 = Utf8               Reverse0
   #20 = Utf8               Reverse0$
   #21 = Utf8               rt$1
   #22 = Utf8               Lshapeless/ops/coproduct$Reverse$Reverse0;
   #23 = Utf8               apply
   #24 = Utf8               (Lscala/util/Either;)Lshapeless/Coproduct;
   #25 = Utf8               (Lscala/util/Either<TAcc;Lshapeless/$colon$plus$colon<TInH;TInT;>;>;)TOut;
   #26 = Utf8               e
   #27 = NameAndType        #21:#22       // rt$1:Lshapeless/ops/coproduct$Reverse$Reverse0;
   #28 = Fieldref           #2.#27        // shapeless/ops/coproduct$Reverse$Reverse0$$anon$63.rt$1:Lshapeless/ops/coproduct$Reverse$Reverse0;
   #29 = Utf8               scala/util/Left
   #30 = Class              #29           // scala/util/Left
   #31 = Utf8               value
   #32 = Utf8               ()Ljava/lang/Object;
   #33 = NameAndType        #31:#32       // value:()Ljava/lang/Object;
   #34 = Methodref          #30.#33       // scala/util/Left.value:()Ljava/lang/Object;
   #35 = Utf8               shapeless/Coproduct
   #36 = Class              #35           // shapeless/Coproduct
   #37 = Utf8               scala/package$
   #38 = Class              #37           // scala/package$
   #39 = Utf8               MODULE$
   #40 = Utf8               Lscala/package$;
   #41 = NameAndType        #39:#40       // MODULE$:Lscala/package$;
   #42 = Fieldref           #38.#41       // scala/package$.MODULE$:Lscala/package$;
   #43 = Utf8               Left
   #44 = Utf8               ()Lscala/util/Left$;
   #45 = NameAndType        #43:#44       // Left:()Lscala/util/Left$;
   #46 = Methodref          #38.#45       // scala/package$.Left:()Lscala/util/Left$;
   #47 = Utf8               shapeless/Inr
   #48 = Class              #47           // shapeless/Inr
   #49 = Utf8               <init>
   #50 = Utf8               (Lshapeless/Coproduct;)V
   #51 = NameAndType        #49:#50       // "<init>":(Lshapeless/Coproduct;)V
   #52 = Methodref          #48.#51       // shapeless/Inr."<init>":(Lshapeless/Coproduct;)V
   #53 = Utf8               scala/util/Left$
   #54 = Class              #53           // scala/util/Left$
   #55 = Utf8               (Ljava/lang/Object;)Lscala/util/Left;
   #56 = NameAndType        #23:#55       // apply:(Ljava/lang/Object;)Lscala/util/Left;
   #57 = Methodref          #54.#56       // scala/util/Left$.apply:(Ljava/lang/Object;)Lscala/util/Left;
   #58 = Utf8               scala/util/Right
   #59 = Class              #58           // scala/util/Right
   #60 = Methodref          #59.#33       // scala/util/Right.value:()Ljava/lang/Object;
   #61 = Utf8               shapeless/$colon$plus$colon
   #62 = Class              #61           // shapeless/$colon$plus$colon
   #63 = Utf8               shapeless/Inl
   #64 = Class              #63           // shapeless/Inl
   #65 = Utf8               head
   #66 = NameAndType        #65:#32       // head:()Ljava/lang/Object;
   #67 = Methodref          #64.#66       // shapeless/Inl.head:()Ljava/lang/Object;
   #68 = Utf8               (Ljava/lang/Object;)V
   #69 = NameAndType        #49:#68       // "<init>":(Ljava/lang/Object;)V
   #70 = Methodref          #64.#69       // shapeless/Inl."<init>":(Ljava/lang/Object;)V
   #71 = Utf8               tail
   #72 = Utf8               ()Lshapeless/Coproduct;
   #73 = NameAndType        #71:#72       // tail:()Lshapeless/Coproduct;
   #74 = Methodref          #48.#73       // shapeless/Inr.tail:()Lshapeless/Coproduct;
   #75 = Utf8               Right
   #76 = Utf8               ()Lscala/util/Right$;
   #77 = NameAndType        #75:#76       // Right:()Lscala/util/Right$;
   #78 = Methodref          #38.#77       // scala/package$.Right:()Lscala/util/Right$;
   #79 = Utf8               scala/util/Right$
   #80 = Class              #79           // scala/util/Right$
   #81 = Utf8               (Ljava/lang/Object;)Lscala/util/Right;
   #82 = NameAndType        #23:#81       // apply:(Ljava/lang/Object;)Lscala/util/Right;
   #83 = Methodref          #80.#82       // scala/util/Right$.apply:(Ljava/lang/Object;)Lscala/util/Right;
   #84 = Utf8               scala/MatchError
   #85 = Class              #84           // scala/MatchError
   #86 = Methodref          #85.#69       // scala/MatchError."<init>":(Ljava/lang/Object;)V
   #87 = NameAndType        #23:#24       // apply:(Lscala/util/Either;)Lshapeless/Coproduct;
   #88 = InterfaceMethodref #7.#87        // shapeless/ops/coproduct$Reverse$Reverse0.apply:(Lscala/util/Either;)Lshapeless/Coproduct;
   #89 = Utf8               acc
   #90 = Utf8               Lshapeless/Coproduct;
   #91 = Utf8               h
   #92 = Utf8               Ljava/lang/Object;
   #93 = Utf8               t
   #94 = Utf8               this
   #95 = Utf8               Lshapeless/ops/coproduct$Reverse$Reverse0$$anon$63;
   #96 = Utf8               Lscala/util/Either;
   #97 = Utf8               scala/util/Either
   #98 = Class              #97           // scala/util/Either
   #99 = Utf8               (Lshapeless/ops/coproduct$Reverse$Reverse0;)V
  #100 = Utf8               ()V
  #101 = NameAndType        #49:#100      // "<init>":()V
  #102 = Methodref          #5.#101       // java/lang/Object."<init>":()V
  #103 = Utf8               Code
  #104 = Utf8               StackMapTable
  #105 = Utf8               LineNumberTable
  #106 = Utf8               LocalVariableTable
  #107 = Utf8               Signature
  #108 = Utf8               MethodParameters
  #109 = Utf8               InnerClasses
  #110 = Utf8               EnclosingMethod
  #111 = Utf8               SourceFile
  #112 = Utf8               ScalaInlineInfo
  #113 = Utf8               Scala
{
  private final shapeless.ops.coproduct$Reverse$Reverse0 rt$1;
    descriptor: Lshapeless/ops/coproduct$Reverse$Reverse0;
    flags: (0x0012) ACC_PRIVATE, ACC_FINAL

  public Out apply(scala.util.Either<Acc, shapeless.$colon$plus$colon<InH, InT>>);
    descriptor: (Lscala/util/Either;)Lshapeless/Coproduct;
    flags: (0x0001) ACC_PUBLIC
    Code:
      stack=5, locals=14, args_size=2
         0: aload_0
         1: getfield      #28                 // Field rt$1:Lshapeless/ops/coproduct$Reverse$Reverse0;
         4: iconst_0
         5: istore_3
         6: aconst_null
         7: astore        4
         9: aload_1
        10: astore        5
        12: aload         5
        14: instanceof    #30                 // class scala/util/Left
        17: ifeq          59
        20: aload         5
        22: checkcast     #30                 // class scala/util/Left
        25: astore        6
        27: aload         6
        29: invokevirtual #34                 // Method scala/util/Left.value:()Ljava/lang/Object;
        32: checkcast     #36                 // class shapeless/Coproduct
        35: astore        7
        37: getstatic     #42                 // Field scala/package$.MODULE$:Lscala/package$;
        40: invokevirtual #46                 // Method scala/package$.Left:()Lscala/util/Left$;
        43: new           #48                 // class shapeless/Inr
        46: dup
        47: aload         7
        49: invokespecial #52                 // Method shapeless/Inr."<init>":(Lshapeless/Coproduct;)V
        52: invokevirtual #57                 // Method scala/util/Left$.apply:(Ljava/lang/Object;)Lscala/util/Left;
        55: astore_2
        56: goto          206
        59: goto          62
        62: aload         5
        64: instanceof    #59                 // class scala/util/Right
        67: ifeq          136
        70: iconst_1
        71: istore_3
        72: aload         5
        74: checkcast     #59                 // class scala/util/Right
        77: astore        4
        79: aload         4
        81: invokevirtual #60                 // Method scala/util/Right.value:()Ljava/lang/Object;
        84: checkcast     #62                 // class shapeless/$colon$plus$colon
        87: astore        8
        89: aload         8
        91: instanceof    #64                 // class shapeless/Inl
        94: ifeq          133
        97: aload         8
        99: checkcast     #64                 // class shapeless/Inl
       102: astore        9
       104: aload         9
       106: invokevirtual #67                 // Method shapeless/Inl.head:()Ljava/lang/Object;
       109: astore        10
       111: getstatic     #42                 // Field scala/package$.MODULE$:Lscala/package$;
       114: invokevirtual #46                 // Method scala/package$.Left:()Lscala/util/Left$;
       117: new           #64                 // class shapeless/Inl
       120: dup
       121: aload         10
       123: invokespecial #70                 // Method shapeless/Inl."<init>":(Ljava/lang/Object;)V
       126: invokevirtual #57                 // Method scala/util/Left$.apply:(Ljava/lang/Object;)Lscala/util/Left;
       129: astore_2
       130: goto          206
       133: goto          139
       136: goto          139
       139: iload_3
       140: ifeq          193
       143: aload         4
       145: invokevirtual #60                 // Method scala/util/Right.value:()Ljava/lang/Object;
       148: checkcast     #62                 // class shapeless/$colon$plus$colon
       151: astore        11
       153: aload         11
       155: instanceof    #48                 // class shapeless/Inr
       158: ifeq          190
       161: aload         11
       163: checkcast     #48                 // class shapeless/Inr
       166: astore        12
       168: aload         12
       170: invokevirtual #74                 // Method shapeless/Inr.tail:()Lshapeless/Coproduct;
       173: astore        13
       175: getstatic     #42                 // Field scala/package$.MODULE$:Lscala/package$;
       178: invokevirtual #78                 // Method scala/package$.Right:()Lscala/util/Right$;
       181: aload         13
       183: invokevirtual #83                 // Method scala/util/Right$.apply:(Ljava/lang/Object;)Lscala/util/Right;
       186: astore_2
       187: goto          206
       190: goto          196
       193: goto          196
       196: new           #85                 // class scala/MatchError
       199: dup
       200: aload         5
       202: invokespecial #86                 // Method scala/MatchError."<init>":(Ljava/lang/Object;)V
       205: athrow
       206: aload_2
       207: invokeinterface #88,  2           // InterfaceMethod shapeless/ops/coproduct$Reverse$Reverse0.apply:(Lscala/util/Either;)Lshapeless/Coproduct;
       212: areturn
      StackMapTable: number_of_entries = 9
        frame_type = 255 /* full_frame */
          offset_delta = 59
          locals = [ class shapeless/ops/coproduct$Reverse$Reverse0$$anon$63, class scala/util/Either, top, int, null, class scala/util/Either ]
          stack = [ class shapeless/ops/coproduct$Reverse$Reverse0 ]
        frame_type = 66 /* same_locals_1_stack_item */
          stack = [ class shapeless/ops/coproduct$Reverse$Reverse0 ]
        frame_type = 255 /* full_frame */
          offset_delta = 70
          locals = [ class shapeless/ops/coproduct$Reverse$Reverse0$$anon$63, class scala/util/Either, top, int, class scala/util/Right, class scala/util/Either, top, top, class shapeless/$colon$plus$colon ]
          stack = [ class shapeless/ops/coproduct$Reverse$Reverse0 ]
        frame_type = 255 /* full_frame */
          offset_delta = 2
          locals = [ class shapeless/ops/coproduct$Reverse$Reverse0$$anon$63, class scala/util/Either, top, int, null, class scala/util/Either ]
          stack = [ class shapeless/ops/coproduct$Reverse$Reverse0 ]
        frame_type = 255 /* full_frame */
          offset_delta = 2
          locals = [ class shapeless/ops/coproduct$Reverse$Reverse0$$anon$63, class scala/util/Either, top, int, class scala/util/Right, class scala/util/Either ]
          stack = [ class shapeless/ops/coproduct$Reverse$Reverse0 ]
        frame_type = 255 /* full_frame */
          offset_delta = 50
          locals = [ class shapeless/ops/coproduct$Reverse$Reverse0$$anon$63, class scala/util/Either, top, int, class scala/util/Right, class scala/util/Either, top, top, top, top, top, class shapeless/$colon$plus$colon ]
          stack = [ class shapeless/ops/coproduct$Reverse$Reverse0 ]
        frame_type = 255 /* full_frame */
          offset_delta = 2
          locals = [ class shapeless/ops/coproduct$Reverse$Reverse0$$anon$63, class scala/util/Either, top, int, class scala/util/Right, class scala/util/Either ]
          stack = [ class shapeless/ops/coproduct$Reverse$Reverse0 ]
        frame_type = 66 /* same_locals_1_stack_item */
          stack = [ class shapeless/ops/coproduct$Reverse$Reverse0 ]
        frame_type = 255 /* full_frame */
          offset_delta = 9
          locals = [ class shapeless/ops/coproduct$Reverse$Reverse0$$anon$63, class scala/util/Either, class scala/util/Either, int, class scala/util/Right, class scala/util/Either ]
          stack = [ class shapeless/ops/coproduct$Reverse$Reverse0 ]
      LineNumberTable:
        line 1005: 0
        line 1006: 12
        line 1007: 62
        line 1008: 139
        line 1005: 196
      LocalVariableTable:
        Start  Length  Slot  Name   Signature
           35      24     7   acc   Lshapeless/Coproduct;
          109      24    10     h   Ljava/lang/Object;
          173      17    13     t   Lshapeless/Coproduct;
            0     213     0  this   Lshapeless/ops/coproduct$Reverse$Reverse0$$anon$63;
            0     213     1     e   Lscala/util/Either;
    Signature: #25                          // (Lscala/util/Either<TAcc;Lshapeless/$colon$plus$colon<TInH;TInT;>;>;)TOut;
    MethodParameters:
      Name                           Flags
      e                              final

  public shapeless.ops.coproduct$Reverse$Reverse0$$anon$63(shapeless.ops.coproduct$Reverse$Reverse0);
    descriptor: (Lshapeless/ops/coproduct$Reverse$Reverse0;)V
    flags: (0x0001) ACC_PUBLIC
    Code:
      stack=2, locals=2, args_size=2
         0: aload_0
         1: aload_1
         2: putfield      #28                 // Field rt$1:Lshapeless/ops/coproduct$Reverse$Reverse0;
         5: aload_0
         6: invokespecial #102                // Method java/lang/Object."<init>":()V
         9: return
      LineNumberTable:
        line 1003: 0
        line 1004: 5
      LocalVariableTable:
        Start  Length  Slot  Name   Signature
            0      10     0  this   Lshapeless/ops/coproduct$Reverse$Reverse0$$anon$63;
            0      10     1  rt$1   Lshapeless/ops/coproduct$Reverse$Reverse0;
    MethodParameters:
      Name                           Flags
      rt$1                           final
}
InnerClasses:
  public static #18= #15 of #17;          // Reverse$=class shapeless/ops/coproduct$Reverse$ of class shapeless/ops/coproduct
  public static #19= #7 of #15;           // Reverse0=class shapeless/ops/coproduct$Reverse$Reverse0 of class shapeless/ops/coproduct$Reverse$
  public static #20= #10 of #15;          // Reverse0$=class shapeless/ops/coproduct$Reverse$Reverse0$ of class shapeless/ops/coproduct$Reverse$
  public final #2;                        // class shapeless/ops/coproduct$Reverse$Reverse0$$anon$63
EnclosingMethod: #10.#13                // shapeless.ops.coproduct$Reverse$Reverse0$.cconsReverse
Signature: #3                           // Ljava/lang/Object;Lshapeless/ops/coproduct$Reverse$Reverse0<TAcc;Lshapeless/$colon$plus$colon<TInH;TInT;>;TOut;>;
SourceFile: "coproduct.scala"
  ScalaInlineInfo: length = 0xE (unknown attribute)
   01 01 00 02 00 31 00 63 01 00 17 00 18 01
  Scala: length = 0x0 (unknown attribute)

