Classfile /Users/mw/Projects/slang-braindump/.jar/jar11/assemble/slang-braindump/assemble/content/shapeless/ops/coproduct$Partition$.class
  Last modified May 29, 2022; size 2672 bytes
  SHA-256 checksum 4b863ff45dbd33076445c07248d908d71ae4e872845d6513740f333fc2c9a383
  Compiled from "coproduct.scala"
public class shapeless.ops.coproduct$Partition$ implements java.io.Serializable
  minor version: 0
  major version: 52
  flags: (0x0021) ACC_PUBLIC, ACC_SUPER
  this_class: #2                          // shapeless/ops/coproduct$Partition$
  super_class: #4                         // java/lang/Object
  interfaces: 1, fields: 1, methods: 7, attributes: 4
Constant pool:
   #1 = Utf8               shapeless/ops/coproduct$Partition$
   #2 = Class              #1             // shapeless/ops/coproduct$Partition$
   #3 = Utf8               java/lang/Object
   #4 = Class              #3             // java/lang/Object
   #5 = Utf8               java/io/Serializable
   #6 = Class              #5             // java/io/Serializable
   #7 = Utf8               coproduct.scala
   #8 = Utf8               shapeless/ops/coproduct$Partition
   #9 = Class              #8             // shapeless/ops/coproduct$Partition
  #10 = Utf8               shapeless/ops/coproduct
  #11 = Class              #10            // shapeless/ops/coproduct
  #12 = Utf8               Partition
  #13 = Utf8               Partition$
  #14 = Utf8               shapeless/ops/coproduct$Partition$$anon$7
  #15 = Class              #14            // shapeless/ops/coproduct$Partition$$anon$7
  #16 = Utf8               shapeless/ops/coproduct$Partition$$anon$8
  #17 = Class              #16            // shapeless/ops/coproduct$Partition$$anon$8
  #18 = Utf8               shapeless/ops/coproduct$Partition$$anon$9
  #19 = Class              #18            // shapeless/ops/coproduct$Partition$$anon$9
  #20 = Utf8               shapeless/package$$eq$colon$bang$eq
  #21 = Class              #20            // shapeless/package$$eq$colon$bang$eq
  #22 = Utf8               shapeless/package
  #23 = Class              #22            // shapeless/package
  #24 = Utf8               $eq$colon$bang$eq
  #25 = Utf8               MODULE$
  #26 = Utf8               Lshapeless/ops/coproduct$Partition$;
  #27 = Utf8               <clinit>
  #28 = Utf8               ()V
  #29 = Utf8               <init>
  #30 = NameAndType        #29:#28        // "<init>":()V
  #31 = Methodref          #2.#30         // shapeless/ops/coproduct$Partition$."<init>":()V
  #32 = NameAndType        #25:#26        // MODULE$:Lshapeless/ops/coproduct$Partition$;
  #33 = Fieldref           #2.#32         // shapeless/ops/coproduct$Partition$.MODULE$:Lshapeless/ops/coproduct$Partition$;
  #34 = Utf8               apply
  #35 = Utf8               (Lshapeless/ops/coproduct$Partition;)Lshapeless/ops/coproduct$Partition;
  #36 = Utf8               <C::Lshapeless/Coproduct;U:Ljava/lang/Object;>(Lshapeless/ops/coproduct$Partition<TC;TU;>;)Lshapeless/ops/coproduct$Partition<TC;TU;>;
  #37 = Utf8               partition
  #38 = Utf8               this
  #39 = Utf8               Lshapeless/ops/coproduct$Partition;
  #40 = Utf8               cnilPartition
  #41 = Utf8               ()Lshapeless/ops/coproduct$Partition;
  #42 = Utf8               <U:Ljava/lang/Object;>()Lshapeless/ops/coproduct$Partition<Lshapeless/CNil;TU;>;
  #43 = Methodref          #15.#30        // shapeless/ops/coproduct$Partition$$anon$7."<init>":()V
  #44 = Utf8               coproductPartition_Match
  #45 = Utf8               <H:Ljava/lang/Object;T::Lshapeless/Coproduct;TPrefix::Lshapeless/Coproduct;TSuffix::Lshapeless/Coproduct;>(Lshapeless/ops/coproduct$Partition<TT;TH;>;)Lshapeless/ops/coproduct$Partition<Lshapeless/$colon$plus$colon<TH;TT;>;TH;>;
  #46 = Utf8               (Lshapeless/ops/coproduct$Partition;)V
  #47 = NameAndType        #29:#46        // "<init>":(Lshapeless/ops/coproduct$Partition;)V
  #48 = Methodref          #17.#47        // shapeless/ops/coproduct$Partition$$anon$8."<init>":(Lshapeless/ops/coproduct$Partition;)V
  #49 = Utf8               coproductPartition_NonMatch
  #50 = Utf8               (Lshapeless/ops/coproduct$Partition;Lshapeless/package$$eq$colon$bang$eq;)Lshapeless/ops/coproduct$Partition;
  #51 = Utf8               <H:Ljava/lang/Object;T::Lshapeless/Coproduct;TPrefix::Lshapeless/Coproduct;TSuffix::Lshapeless/Coproduct;U:Ljava/lang/Object;>(Lshapeless/ops/coproduct$Partition<TT;TU;>;Lshapeless/package$$eq$colon$bang$eq<TU;TH;>;)Lshapeless/ops/coproduct$Partition<Lshapeless/$colon$plus$colon<TH;TT;>;TU;>;
  #52 = Utf8               e
  #53 = Methodref          #19.#47        // shapeless/ops/coproduct$Partition$$anon$9."<init>":(Lshapeless/ops/coproduct$Partition;)V
  #54 = Utf8               Lshapeless/package$$eq$colon$bang$eq;
  #55 = Utf8               writeReplace
  #56 = Utf8               ()Ljava/lang/Object;
  #57 = Utf8               scala/runtime/ModuleSerializationProxy
  #58 = Class              #57            // scala/runtime/ModuleSerializationProxy
  #59 = Utf8               (Ljava/lang/Class;)V
  #60 = NameAndType        #29:#59        // "<init>":(Ljava/lang/Class;)V
  #61 = Methodref          #58.#60        // scala/runtime/ModuleSerializationProxy."<init>":(Ljava/lang/Class;)V
  #62 = Methodref          #4.#30         // java/lang/Object."<init>":()V
  #63 = Utf8               Code
  #64 = Utf8               LineNumberTable
  #65 = Utf8               LocalVariableTable
  #66 = Utf8               Signature
  #67 = Utf8               MethodParameters
  #68 = Utf8               InnerClasses
  #69 = Utf8               SourceFile
  #70 = Utf8               ScalaInlineInfo
  #71 = Utf8               Scala
{
  public static final shapeless.ops.coproduct$Partition$ MODULE$;
    descriptor: Lshapeless/ops/coproduct$Partition$;
    flags: (0x0019) ACC_PUBLIC, ACC_STATIC, ACC_FINAL

  public static {};
    descriptor: ()V
    flags: (0x0009) ACC_PUBLIC, ACC_STATIC
    Code:
      stack=2, locals=0, args_size=0
         0: new           #2                  // class shapeless/ops/coproduct$Partition$
         3: dup
         4: invokespecial #31                 // Method "<init>":()V
         7: putstatic     #33                 // Field MODULE$:Lshapeless/ops/coproduct$Partition$;
        10: return
      LineNumberTable:
        line 104: 0

  public <C extends shapeless.Coproduct, U extends java.lang.Object> shapeless.ops.coproduct$Partition<C, U> apply(shapeless.ops.coproduct$Partition<C, U>);
    descriptor: (Lshapeless/ops/coproduct$Partition;)Lshapeless/ops/coproduct$Partition;
    flags: (0x0001) ACC_PUBLIC
    Code:
      stack=1, locals=2, args_size=2
         0: aload_1
         1: areturn
      LineNumberTable:
        line 106: 0
      LocalVariableTable:
        Start  Length  Slot  Name   Signature
            0       2     0  this   Lshapeless/ops/coproduct$Partition$;
            0       2     1 partition   Lshapeless/ops/coproduct$Partition;
    Signature: #36                          // <C::Lshapeless/Coproduct;U:Ljava/lang/Object;>(Lshapeless/ops/coproduct$Partition<TC;TU;>;)Lshapeless/ops/coproduct$Partition<TC;TU;>;
    MethodParameters:
      Name                           Flags
      partition                      final

  public <U extends java.lang.Object> shapeless.ops.coproduct$Partition<shapeless.CNil, U> cnilPartition();
    descriptor: ()Lshapeless/ops/coproduct$Partition;
    flags: (0x0001) ACC_PUBLIC
    Code:
      stack=2, locals=1, args_size=1
         0: new           #15                 // class shapeless/ops/coproduct$Partition$$anon$7
         3: dup
         4: invokespecial #43                 // Method shapeless/ops/coproduct$Partition$$anon$7."<init>":()V
         7: areturn
      LineNumberTable:
        line 113: 0
      LocalVariableTable:
        Start  Length  Slot  Name   Signature
            0       8     0  this   Lshapeless/ops/coproduct$Partition$;
    Signature: #42                          // <U:Ljava/lang/Object;>()Lshapeless/ops/coproduct$Partition<Lshapeless/CNil;TU;>;

  public <H extends java.lang.Object, T extends shapeless.Coproduct, TPrefix extends shapeless.Coproduct, TSuffix extends shapeless.Coproduct> shapeless.ops.coproduct$Partition<shapeless.$colon$plus$colon<H, T>, H> coproductPartition_Match(shapeless.ops.coproduct$Partition<T, H>);
    descriptor: (Lshapeless/ops/coproduct$Partition;)Lshapeless/ops/coproduct$Partition;
    flags: (0x0001) ACC_PUBLIC
    Code:
      stack=3, locals=2, args_size=2
         0: new           #17                 // class shapeless/ops/coproduct$Partition$$anon$8
         3: dup
         4: aload_1
         5: invokespecial #48                 // Method shapeless/ops/coproduct$Partition$$anon$8."<init>":(Lshapeless/ops/coproduct$Partition;)V
         8: areturn
      LineNumberTable:
        line 122: 0
      LocalVariableTable:
        Start  Length  Slot  Name   Signature
            0       9     0  this   Lshapeless/ops/coproduct$Partition$;
            0       9     1 partition   Lshapeless/ops/coproduct$Partition;
    Signature: #45                          // <H:Ljava/lang/Object;T::Lshapeless/Coproduct;TPrefix::Lshapeless/Coproduct;TSuffix::Lshapeless/Coproduct;>(Lshapeless/ops/coproduct$Partition<TT;TH;>;)Lshapeless/ops/coproduct$Partition<Lshapeless/$colon$plus$colon<TH;TT;>;TH;>;
    MethodParameters:
      Name                           Flags
      partition                      final

  public <H extends java.lang.Object, T extends shapeless.Coproduct, TPrefix extends shapeless.Coproduct, TSuffix extends shapeless.Coproduct, U extends java.lang.Object> shapeless.ops.coproduct$Partition<shapeless.$colon$plus$colon<H, T>, U> coproductPartition_NonMatch(shapeless.ops.coproduct$Partition<T, U>, shapeless.package$$eq$colon$bang$eq<U, H>);
    descriptor: (Lshapeless/ops/coproduct$Partition;Lshapeless/package$$eq$colon$bang$eq;)Lshapeless/ops/coproduct$Partition;
    flags: (0x0001) ACC_PUBLIC
    Code:
      stack=3, locals=3, args_size=3
         0: new           #19                 // class shapeless/ops/coproduct$Partition$$anon$9
         3: dup
         4: aload_1
         5: invokespecial #53                 // Method shapeless/ops/coproduct$Partition$$anon$9."<init>":(Lshapeless/ops/coproduct$Partition;)V
         8: areturn
      LineNumberTable:
        line 137: 0
      LocalVariableTable:
        Start  Length  Slot  Name   Signature
            0       9     0  this   Lshapeless/ops/coproduct$Partition$;
            0       9     1 partition   Lshapeless/ops/coproduct$Partition;
            0       9     2     e   Lshapeless/package$$eq$colon$bang$eq;
    Signature: #51                          // <H:Ljava/lang/Object;T::Lshapeless/Coproduct;TPrefix::Lshapeless/Coproduct;TSuffix::Lshapeless/Coproduct;U:Ljava/lang/Object;>(Lshapeless/ops/coproduct$Partition<TT;TU;>;Lshapeless/package$$eq$colon$bang$eq<TU;TH;>;)Lshapeless/ops/coproduct$Partition<Lshapeless/$colon$plus$colon<TH;TT;>;TU;>;
    MethodParameters:
      Name                           Flags
      partition                      final
      e                              final

  private java.lang.Object writeReplace();
    descriptor: ()Ljava/lang/Object;
    flags: (0x0002) ACC_PRIVATE
    Code:
      stack=3, locals=1, args_size=1
         0: new           #58                 // class scala/runtime/ModuleSerializationProxy
         3: dup
         4: ldc           #2                  // class shapeless/ops/coproduct$Partition$
         6: invokespecial #61                 // Method scala/runtime/ModuleSerializationProxy."<init>":(Ljava/lang/Class;)V
         9: areturn
      LineNumberTable:
        line 104: 0
      LocalVariableTable:
        Start  Length  Slot  Name   Signature
            0      10     0  this   Lshapeless/ops/coproduct$Partition$;

  public shapeless.ops.coproduct$Partition$();
    descriptor: ()V
    flags: (0x0001) ACC_PUBLIC
    Code:
      stack=1, locals=1, args_size=1
         0: aload_0
         1: invokespecial #62                 // Method java/lang/Object."<init>":()V
         4: return
      LineNumberTable:
        line 152: 0
        line 104: 4
      LocalVariableTable:
        Start  Length  Slot  Name   Signature
            0       5     0  this   Lshapeless/ops/coproduct$Partition$;
}
InnerClasses:
  public static #12= #9 of #11;           // Partition=class shapeless/ops/coproduct$Partition of class shapeless/ops/coproduct
  public static #13= #2 of #11;           // Partition$=class shapeless/ops/coproduct$Partition$ of class shapeless/ops/coproduct
  public final #15;                       // class shapeless/ops/coproduct$Partition$$anon$7
  public final #17;                       // class shapeless/ops/coproduct$Partition$$anon$8
  public final #19;                       // class shapeless/ops/coproduct$Partition$$anon$9
  public static #24= #21 of #23;          // $eq$colon$bang$eq=class shapeless/package$$eq$colon$bang$eq of class shapeless/package
SourceFile: "coproduct.scala"
  ScalaInlineInfo: length = 0x22 (unknown attribute)
   01 01 00 06 00 1D 00 1C 01 00 22 00 23 01 00 28
   00 29 01 00 2C 00 23 01 00 31 00 32 01 00 37 00
   38 01
  Scala: length = 0x0 (unknown attribute)

