Classfile /Users/mw/Projects/slang-braindump/.jar/jar11/assemble/slang-braindump/assemble/content/shapeless/ops/coproduct$Length$.class
  Last modified May 29, 2022; size 1902 bytes
  SHA-256 checksum 60436a32f6cba7e6aa1d5ff268cedece914c2bffcdb9e0a5a8201d165ab85736
  Compiled from "coproduct.scala"
public class shapeless.ops.coproduct$Length$ implements java.io.Serializable
  minor version: 0
  major version: 52
  flags: (0x0021) ACC_PUBLIC, ACC_SUPER
  this_class: #2                          // shapeless/ops/coproduct$Length$
  super_class: #4                         // java/lang/Object
  interfaces: 1, fields: 1, methods: 6, attributes: 4
Constant pool:
   #1 = Utf8               shapeless/ops/coproduct$Length$
   #2 = Class              #1             // shapeless/ops/coproduct$Length$
   #3 = Utf8               java/lang/Object
   #4 = Class              #3             // java/lang/Object
   #5 = Utf8               java/io/Serializable
   #6 = Class              #5             // java/io/Serializable
   #7 = Utf8               coproduct.scala
   #8 = Utf8               shapeless/ops/coproduct$Length
   #9 = Class              #8             // shapeless/ops/coproduct$Length
  #10 = Utf8               shapeless/ops/coproduct
  #11 = Class              #10            // shapeless/ops/coproduct
  #12 = Utf8               Length
  #13 = Utf8               Length$
  #14 = Utf8               shapeless/ops/coproduct$Length$$anon$34
  #15 = Class              #14            // shapeless/ops/coproduct$Length$$anon$34
  #16 = Utf8               shapeless/ops/coproduct$Length$$anon$35
  #17 = Class              #16            // shapeless/ops/coproduct$Length$$anon$35
  #18 = Utf8               MODULE$
  #19 = Utf8               Lshapeless/ops/coproduct$Length$;
  #20 = Utf8               <clinit>
  #21 = Utf8               ()V
  #22 = Utf8               <init>
  #23 = NameAndType        #22:#21        // "<init>":()V
  #24 = Methodref          #2.#23         // shapeless/ops/coproduct$Length$."<init>":()V
  #25 = NameAndType        #18:#19        // MODULE$:Lshapeless/ops/coproduct$Length$;
  #26 = Fieldref           #2.#25         // shapeless/ops/coproduct$Length$.MODULE$:Lshapeless/ops/coproduct$Length$;
  #27 = Utf8               apply
  #28 = Utf8               (Lshapeless/ops/coproduct$Length;)Lshapeless/ops/coproduct$Length;
  #29 = Utf8               <C::Lshapeless/Coproduct;>(Lshapeless/ops/coproduct$Length<TC;>;)Lshapeless/ops/coproduct$Length<TC;>;
  #30 = Utf8               length
  #31 = Utf8               this
  #32 = Utf8               Lshapeless/ops/coproduct$Length;
  #33 = Utf8               cnilLength
  #34 = Utf8               ()Lshapeless/ops/coproduct$Length;
  #35 = Utf8               ()Lshapeless/ops/coproduct$Length<Lshapeless/CNil;>;
  #36 = Methodref          #15.#23        // shapeless/ops/coproduct$Length$$anon$34."<init>":()V
  #37 = Utf8               coproductLength
  #38 = Utf8               (Lshapeless/ops/coproduct$Length;Lshapeless/Witness;)Lshapeless/ops/coproduct$Length;
  #39 = Utf8               <H:Ljava/lang/Object;T::Lshapeless/Coproduct;N::Lshapeless/Nat;>(Lshapeless/ops/coproduct$Length<TT;>;Lshapeless/Witness;)Lshapeless/ops/coproduct$Length<Lshapeless/$colon$plus$colon<TH;TT;>;>;
  #40 = Utf8               lt
  #41 = Utf8               sn
  #42 = Utf8               (Lshapeless/Witness;)V
  #43 = NameAndType        #22:#42        // "<init>":(Lshapeless/Witness;)V
  #44 = Methodref          #17.#43        // shapeless/ops/coproduct$Length$$anon$35."<init>":(Lshapeless/Witness;)V
  #45 = Utf8               Lshapeless/Witness;
  #46 = Utf8               writeReplace
  #47 = Utf8               ()Ljava/lang/Object;
  #48 = Utf8               scala/runtime/ModuleSerializationProxy
  #49 = Class              #48            // scala/runtime/ModuleSerializationProxy
  #50 = Utf8               (Ljava/lang/Class;)V
  #51 = NameAndType        #22:#50        // "<init>":(Ljava/lang/Class;)V
  #52 = Methodref          #49.#51        // scala/runtime/ModuleSerializationProxy."<init>":(Ljava/lang/Class;)V
  #53 = Methodref          #4.#23         // java/lang/Object."<init>":()V
  #54 = Utf8               Code
  #55 = Utf8               LineNumberTable
  #56 = Utf8               LocalVariableTable
  #57 = Utf8               Signature
  #58 = Utf8               MethodParameters
  #59 = Utf8               InnerClasses
  #60 = Utf8               SourceFile
  #61 = Utf8               ScalaInlineInfo
  #62 = Utf8               Scala
{
  public static final shapeless.ops.coproduct$Length$ MODULE$;
    descriptor: Lshapeless/ops/coproduct$Length$;
    flags: (0x0019) ACC_PUBLIC, ACC_STATIC, ACC_FINAL

  public static {};
    descriptor: ()V
    flags: (0x0009) ACC_PUBLIC, ACC_STATIC
    Code:
      stack=2, locals=0, args_size=0
         0: new           #2                  // class shapeless/ops/coproduct$Length$
         3: dup
         4: invokespecial #24                 // Method "<init>":()V
         7: putstatic     #26                 // Field MODULE$:Lshapeless/ops/coproduct$Length$;
        10: return
      LineNumberTable:
        line 547: 0

  public <C extends shapeless.Coproduct> shapeless.ops.coproduct$Length<C> apply(shapeless.ops.coproduct$Length<C>);
    descriptor: (Lshapeless/ops/coproduct$Length;)Lshapeless/ops/coproduct$Length;
    flags: (0x0001) ACC_PUBLIC
    Code:
      stack=1, locals=2, args_size=2
         0: aload_1
         1: areturn
      LineNumberTable:
        line 548: 0
      LocalVariableTable:
        Start  Length  Slot  Name   Signature
            0       2     0  this   Lshapeless/ops/coproduct$Length$;
            0       2     1 length   Lshapeless/ops/coproduct$Length;
    Signature: #29                          // <C::Lshapeless/Coproduct;>(Lshapeless/ops/coproduct$Length<TC;>;)Lshapeless/ops/coproduct$Length<TC;>;
    MethodParameters:
      Name                           Flags
      length                         final

  public shapeless.ops.coproduct$Length<shapeless.CNil> cnilLength();
    descriptor: ()Lshapeless/ops/coproduct$Length;
    flags: (0x0001) ACC_PUBLIC
    Code:
      stack=2, locals=1, args_size=1
         0: new           #15                 // class shapeless/ops/coproduct$Length$$anon$34
         3: dup
         4: invokespecial #36                 // Method shapeless/ops/coproduct$Length$$anon$34."<init>":()V
         7: areturn
      LineNumberTable:
        line 552: 0
      LocalVariableTable:
        Start  Length  Slot  Name   Signature
            0       8     0  this   Lshapeless/ops/coproduct$Length$;
    Signature: #35                          // ()Lshapeless/ops/coproduct$Length<Lshapeless/CNil;>;

  public <H extends java.lang.Object, T extends shapeless.Coproduct, N extends shapeless.Nat> shapeless.ops.coproduct$Length<shapeless.$colon$plus$colon<H, T>> coproductLength(shapeless.ops.coproduct$Length<T>, shapeless.Witness);
    descriptor: (Lshapeless/ops/coproduct$Length;Lshapeless/Witness;)Lshapeless/ops/coproduct$Length;
    flags: (0x0001) ACC_PUBLIC
    Code:
      stack=3, locals=3, args_size=3
         0: new           #17                 // class shapeless/ops/coproduct$Length$$anon$35
         3: dup
         4: aload_2
         5: invokespecial #44                 // Method shapeless/ops/coproduct$Length$$anon$35."<init>":(Lshapeless/Witness;)V
         8: areturn
      LineNumberTable:
        line 559: 0
      LocalVariableTable:
        Start  Length  Slot  Name   Signature
            0       9     0  this   Lshapeless/ops/coproduct$Length$;
            0       9     1    lt   Lshapeless/ops/coproduct$Length;
            0       9     2    sn   Lshapeless/Witness;
    Signature: #39                          // <H:Ljava/lang/Object;T::Lshapeless/Coproduct;N::Lshapeless/Nat;>(Lshapeless/ops/coproduct$Length<TT;>;Lshapeless/Witness;)Lshapeless/ops/coproduct$Length<Lshapeless/$colon$plus$colon<TH;TT;>;>;
    MethodParameters:
      Name                           Flags
      lt                             final
      sn                             final

  private java.lang.Object writeReplace();
    descriptor: ()Ljava/lang/Object;
    flags: (0x0002) ACC_PRIVATE
    Code:
      stack=3, locals=1, args_size=1
         0: new           #49                 // class scala/runtime/ModuleSerializationProxy
         3: dup
         4: ldc           #2                  // class shapeless/ops/coproduct$Length$
         6: invokespecial #52                 // Method scala/runtime/ModuleSerializationProxy."<init>":(Ljava/lang/Class;)V
         9: areturn
      LineNumberTable:
        line 547: 0
      LocalVariableTable:
        Start  Length  Slot  Name   Signature
            0      10     0  this   Lshapeless/ops/coproduct$Length$;

  public shapeless.ops.coproduct$Length$();
    descriptor: ()V
    flags: (0x0001) ACC_PUBLIC
    Code:
      stack=1, locals=1, args_size=1
         0: aload_0
         1: invokespecial #53                 // Method java/lang/Object."<init>":()V
         4: return
      LineNumberTable:
        line 572: 0
        line 547: 4
      LocalVariableTable:
        Start  Length  Slot  Name   Signature
            0       5     0  this   Lshapeless/ops/coproduct$Length$;
}
InnerClasses:
  public static #12= #9 of #11;           // Length=class shapeless/ops/coproduct$Length of class shapeless/ops/coproduct
  public static #13= #2 of #11;           // Length$=class shapeless/ops/coproduct$Length$ of class shapeless/ops/coproduct
  public final #15;                       // class shapeless/ops/coproduct$Length$$anon$34
  public final #17;                       // class shapeless/ops/coproduct$Length$$anon$35
SourceFile: "coproduct.scala"
  ScalaInlineInfo: length = 0x1D (unknown attribute)
   01 01 00 05 00 16 00 15 01 00 1B 00 1C 01 00 21
   00 22 01 00 25 00 26 01 00 2E 00 2F 01
  Scala: length = 0x0 (unknown attribute)

