Classfile /Users/mw/Projects/slang-braindump/.jar/jar11/assemble/slang-braindump/assemble/content/shapeless/ops/coproduct$IsCCons$$anon$54.class
  Last modified May 29, 2022; size 2676 bytes
  SHA-256 checksum 9a1aeb52d3acafa88fac465477801a1bac2c9bf48cccf3ace9c444cbf27dbdde
  Compiled from "coproduct.scala"
public final class shapeless.ops.coproduct$IsCCons$$anon$54 extends java.lang.Object implements shapeless.ops.coproduct$IsCCons<shapeless.$colon$plus$colon<H0, T0>>
  minor version: 0
  major version: 52
  flags: (0x0031) ACC_PUBLIC, ACC_FINAL, ACC_SUPER
  this_class: #2                          // shapeless/ops/coproduct$IsCCons$$anon$54
  super_class: #5                         // java/lang/Object
  interfaces: 1, fields: 0, methods: 7, attributes: 6
Constant pool:
    #1 = Utf8               shapeless/ops/coproduct$IsCCons$$anon$54
    #2 = Class              #1            // shapeless/ops/coproduct$IsCCons$$anon$54
    #3 = Utf8               Ljava/lang/Object;Lshapeless/ops/coproduct$IsCCons<Lshapeless/$colon$plus$colon<TH0;TT0;>;>;
    #4 = Utf8               java/lang/Object
    #5 = Class              #4            // java/lang/Object
    #6 = Utf8               shapeless/ops/coproduct$IsCCons
    #7 = Class              #6            // shapeless/ops/coproduct$IsCCons
    #8 = Utf8               coproduct.scala
    #9 = Utf8               shapeless/ops/coproduct$IsCCons$
   #10 = Class              #9            // shapeless/ops/coproduct$IsCCons$
   #11 = Utf8               coproductCCons
   #12 = Utf8               ()Lshapeless/ops/coproduct$IsCCons;
   #13 = NameAndType        #11:#12       // coproductCCons:()Lshapeless/ops/coproduct$IsCCons;
   #14 = Utf8               shapeless/ops/coproduct
   #15 = Class              #14           // shapeless/ops/coproduct
   #16 = Utf8               IsCCons
   #17 = Utf8               IsCCons$
   #18 = Utf8               head
   #19 = Utf8               (Lshapeless/$colon$plus$colon;)Lscala/Option;
   #20 = Utf8               (Lshapeless/$colon$plus$colon<TH0;TT0;>;)Lscala/Option<TH0;>;
   #21 = Utf8               c
   #22 = Utf8               shapeless/Inl
   #23 = Class              #22           // shapeless/Inl
   #24 = Utf8               ()Ljava/lang/Object;
   #25 = NameAndType        #18:#24       // head:()Ljava/lang/Object;
   #26 = Methodref          #23.#25       // shapeless/Inl.head:()Ljava/lang/Object;
   #27 = Utf8               scala/Some
   #28 = Class              #27           // scala/Some
   #29 = Utf8               <init>
   #30 = Utf8               (Ljava/lang/Object;)V
   #31 = NameAndType        #29:#30       // "<init>":(Ljava/lang/Object;)V
   #32 = Methodref          #28.#31       // scala/Some."<init>":(Ljava/lang/Object;)V
   #33 = Utf8               scala/None$
   #34 = Class              #33           // scala/None$
   #35 = Utf8               MODULE$
   #36 = Utf8               Lscala/None$;
   #37 = NameAndType        #35:#36       // MODULE$:Lscala/None$;
   #38 = Fieldref           #34.#37       // scala/None$.MODULE$:Lscala/None$;
   #39 = Utf8               h
   #40 = Utf8               Ljava/lang/Object;
   #41 = Utf8               this
   #42 = Utf8               Lshapeless/ops/coproduct$IsCCons$$anon$54;
   #43 = Utf8               Lshapeless/$colon$plus$colon;
   #44 = Utf8               shapeless/$colon$plus$colon
   #45 = Class              #44           // shapeless/$colon$plus$colon
   #46 = Utf8               scala/Option
   #47 = Class              #46           // scala/Option
   #48 = Utf8               tail
   #49 = Utf8               (Lshapeless/$colon$plus$colon<TH0;TT0;>;)Lscala/Option<TT0;>;
   #50 = Utf8               shapeless/Inr
   #51 = Class              #50           // shapeless/Inr
   #52 = Utf8               ()Lshapeless/Coproduct;
   #53 = NameAndType        #48:#52       // tail:()Lshapeless/Coproduct;
   #54 = Methodref          #51.#53       // shapeless/Inr.tail:()Lshapeless/Coproduct;
   #55 = Utf8               t
   #56 = Utf8               Lshapeless/Coproduct;
   #57 = Utf8               cons
   #58 = Utf8               (Lscala/util/Either;)Lshapeless/$colon$plus$colon;
   #59 = Utf8               (Lscala/util/Either<TH0;TT0;>;)Lshapeless/$colon$plus$colon<TH0;TT0;>;
   #60 = Utf8               e
   #61 = Utf8               scala/util/Left
   #62 = Class              #61           // scala/util/Left
   #63 = Utf8               value
   #64 = NameAndType        #63:#24       // value:()Ljava/lang/Object;
   #65 = Methodref          #62.#64       // scala/util/Left.value:()Ljava/lang/Object;
   #66 = Methodref          #23.#31       // shapeless/Inl."<init>":(Ljava/lang/Object;)V
   #67 = Utf8               scala/util/Right
   #68 = Class              #67           // scala/util/Right
   #69 = Methodref          #68.#64       // scala/util/Right.value:()Ljava/lang/Object;
   #70 = Utf8               shapeless/Coproduct
   #71 = Class              #70           // shapeless/Coproduct
   #72 = Utf8               (Lshapeless/Coproduct;)V
   #73 = NameAndType        #29:#72       // "<init>":(Lshapeless/Coproduct;)V
   #74 = Methodref          #51.#73       // shapeless/Inr."<init>":(Lshapeless/Coproduct;)V
   #75 = Utf8               scala/MatchError
   #76 = Class              #75           // scala/MatchError
   #77 = Methodref          #76.#31       // scala/MatchError."<init>":(Ljava/lang/Object;)V
   #78 = Utf8               Lscala/util/Either;
   #79 = Utf8               scala/util/Either
   #80 = Class              #79           // scala/util/Either
   #81 = Utf8               (Lscala/util/Either;)Lshapeless/Coproduct;
   #82 = NameAndType        #57:#58       // cons:(Lscala/util/Either;)Lshapeless/$colon$plus$colon;
   #83 = Methodref          #2.#82        // shapeless/ops/coproduct$IsCCons$$anon$54.cons:(Lscala/util/Either;)Lshapeless/$colon$plus$colon;
   #84 = Utf8               (Lshapeless/Coproduct;)Lscala/Option;
   #85 = NameAndType        #48:#19       // tail:(Lshapeless/$colon$plus$colon;)Lscala/Option;
   #86 = Methodref          #2.#85        // shapeless/ops/coproduct$IsCCons$$anon$54.tail:(Lshapeless/$colon$plus$colon;)Lscala/Option;
   #87 = NameAndType        #18:#19       // head:(Lshapeless/$colon$plus$colon;)Lscala/Option;
   #88 = Methodref          #2.#87        // shapeless/ops/coproduct$IsCCons$$anon$54.head:(Lshapeless/$colon$plus$colon;)Lscala/Option;
   #89 = Utf8               ()V
   #90 = NameAndType        #29:#89       // "<init>":()V
   #91 = Methodref          #5.#90        // java/lang/Object."<init>":()V
   #92 = Utf8               Code
   #93 = Utf8               StackMapTable
   #94 = Utf8               LineNumberTable
   #95 = Utf8               LocalVariableTable
   #96 = Utf8               Signature
   #97 = Utf8               MethodParameters
   #98 = Utf8               InnerClasses
   #99 = Utf8               EnclosingMethod
  #100 = Utf8               SourceFile
  #101 = Utf8               ScalaInlineInfo
  #102 = Utf8               Scala
{
  public scala.Option<H0> head(shapeless.$colon$plus$colon<H0, T0>);
    descriptor: (Lshapeless/$colon$plus$colon;)Lscala/Option;
    flags: (0x0001) ACC_PUBLIC
    Code:
      stack=3, locals=6, args_size=2
         0: aload_1
         1: astore_3
         2: aload_3
         3: instanceof    #23                 // class shapeless/Inl
         6: ifeq          35
         9: aload_3
        10: checkcast     #23                 // class shapeless/Inl
        13: astore        4
        15: aload         4
        17: invokevirtual #26                 // Method shapeless/Inl.head:()Ljava/lang/Object;
        20: astore        5
        22: new           #28                 // class scala/Some
        25: dup
        26: aload         5
        28: invokespecial #32                 // Method scala/Some."<init>":(Ljava/lang/Object;)V
        31: astore_2
        32: goto          45
        35: goto          38
        38: getstatic     #38                 // Field scala/None$.MODULE$:Lscala/None$;
        41: astore_2
        42: goto          45
        45: aload_2
        46: areturn
      StackMapTable: number_of_entries = 3
        frame_type = 253 /* append */
          offset_delta = 35
          locals = [ top, class shapeless/$colon$plus$colon ]
        frame_type = 2 /* same */
        frame_type = 255 /* full_frame */
          offset_delta = 6
          locals = [ class shapeless/ops/coproduct$IsCCons$$anon$54, class shapeless/$colon$plus$colon, class scala/Option, class shapeless/$colon$plus$colon ]
          stack = []
      LineNumberTable:
        line 845: 0
        line 846: 2
        line 847: 38
        line 845: 45
      LocalVariableTable:
        Start  Length  Slot  Name   Signature
           20      15     5     h   Ljava/lang/Object;
            0      47     0  this   Lshapeless/ops/coproduct$IsCCons$$anon$54;
            0      47     1     c   Lshapeless/$colon$plus$colon;
    Signature: #20                          // (Lshapeless/$colon$plus$colon<TH0;TT0;>;)Lscala/Option<TH0;>;
    MethodParameters:
      Name                           Flags
      c                              final

  public scala.Option<T0> tail(shapeless.$colon$plus$colon<H0, T0>);
    descriptor: (Lshapeless/$colon$plus$colon;)Lscala/Option;
    flags: (0x0001) ACC_PUBLIC
    Code:
      stack=3, locals=6, args_size=2
         0: aload_1
         1: astore_3
         2: aload_3
         3: instanceof    #51                 // class shapeless/Inr
         6: ifeq          35
         9: aload_3
        10: checkcast     #51                 // class shapeless/Inr
        13: astore        4
        15: aload         4
        17: invokevirtual #54                 // Method shapeless/Inr.tail:()Lshapeless/Coproduct;
        20: astore        5
        22: new           #28                 // class scala/Some
        25: dup
        26: aload         5
        28: invokespecial #32                 // Method scala/Some."<init>":(Ljava/lang/Object;)V
        31: astore_2
        32: goto          45
        35: goto          38
        38: getstatic     #38                 // Field scala/None$.MODULE$:Lscala/None$;
        41: astore_2
        42: goto          45
        45: aload_2
        46: areturn
      StackMapTable: number_of_entries = 3
        frame_type = 253 /* append */
          offset_delta = 35
          locals = [ top, class shapeless/$colon$plus$colon ]
        frame_type = 2 /* same */
        frame_type = 255 /* full_frame */
          offset_delta = 6
          locals = [ class shapeless/ops/coproduct$IsCCons$$anon$54, class shapeless/$colon$plus$colon, class scala/Option, class shapeless/$colon$plus$colon ]
          stack = []
      LineNumberTable:
        line 850: 0
        line 851: 2
        line 852: 38
        line 850: 45
      LocalVariableTable:
        Start  Length  Slot  Name   Signature
           20      15     5     t   Lshapeless/Coproduct;
            0      47     0  this   Lshapeless/ops/coproduct$IsCCons$$anon$54;
            0      47     1     c   Lshapeless/$colon$plus$colon;
    Signature: #49                          // (Lshapeless/$colon$plus$colon<TH0;TT0;>;)Lscala/Option<TT0;>;
    MethodParameters:
      Name                           Flags
      c                              final

  public shapeless.$colon$plus$colon<H0, T0> cons(scala.util.Either<H0, T0>);
    descriptor: (Lscala/util/Either;)Lshapeless/$colon$plus$colon;
    flags: (0x0001) ACC_PUBLIC
    Code:
      stack=3, locals=8, args_size=2
         0: aload_1
         1: astore_3
         2: aload_3
         3: instanceof    #62                 // class scala/util/Left
         6: ifeq          35
         9: aload_3
        10: checkcast     #62                 // class scala/util/Left
        13: astore        4
        15: aload         4
        17: invokevirtual #65                 // Method scala/util/Left.value:()Ljava/lang/Object;
        20: astore        5
        22: new           #23                 // class shapeless/Inl
        25: dup
        26: aload         5
        28: invokespecial #66                 // Method shapeless/Inl."<init>":(Ljava/lang/Object;)V
        31: astore_2
        32: goto          86
        35: goto          38
        38: aload_3
        39: instanceof    #68                 // class scala/util/Right
        42: ifeq          74
        45: aload_3
        46: checkcast     #68                 // class scala/util/Right
        49: astore        6
        51: aload         6
        53: invokevirtual #69                 // Method scala/util/Right.value:()Ljava/lang/Object;
        56: checkcast     #71                 // class shapeless/Coproduct
        59: astore        7
        61: new           #51                 // class shapeless/Inr
        64: dup
        65: aload         7
        67: invokespecial #74                 // Method shapeless/Inr."<init>":(Lshapeless/Coproduct;)V
        70: astore_2
        71: goto          86
        74: goto          77
        77: new           #76                 // class scala/MatchError
        80: dup
        81: aload_3
        82: invokespecial #77                 // Method scala/MatchError."<init>":(Ljava/lang/Object;)V
        85: athrow
        86: aload_2
        87: areturn
      StackMapTable: number_of_entries = 5
        frame_type = 253 /* append */
          offset_delta = 35
          locals = [ top, class scala/util/Either ]
        frame_type = 2 /* same */
        frame_type = 35 /* same */
        frame_type = 2 /* same */
        frame_type = 255 /* full_frame */
          offset_delta = 8
          locals = [ class shapeless/ops/coproduct$IsCCons$$anon$54, class scala/util/Either, class java/lang/Object, class scala/util/Either ]
          stack = []
      LineNumberTable:
        line 855: 0
        line 856: 2
        line 857: 38
        line 855: 77
      LocalVariableTable:
        Start  Length  Slot  Name   Signature
           20      15     5     h   Ljava/lang/Object;
           59      15     7     t   Lshapeless/Coproduct;
            0      88     0  this   Lshapeless/ops/coproduct$IsCCons$$anon$54;
            0      88     1     e   Lscala/util/Either;
    Signature: #59                          // (Lscala/util/Either<TH0;TT0;>;)Lshapeless/$colon$plus$colon<TH0;TT0;>;
    MethodParameters:
      Name                           Flags
      e                              final

  public shapeless.Coproduct cons(scala.util.Either);
    descriptor: (Lscala/util/Either;)Lshapeless/Coproduct;
    flags: (0x1041) ACC_PUBLIC, ACC_BRIDGE, ACC_SYNTHETIC
    Code:
      stack=2, locals=2, args_size=2
         0: aload_0
         1: aload_1
         2: invokevirtual #83                 // Method cons:(Lscala/util/Either;)Lshapeless/$colon$plus$colon;
         5: areturn
      LineNumberTable:
        line 841: 0
      LocalVariableTable:
        Start  Length  Slot  Name   Signature
            0       6     0  this   Lshapeless/ops/coproduct$IsCCons$$anon$54;
            0       6     1     e   Lscala/util/Either;
    MethodParameters:
      Name                           Flags
      e                              final

  public scala.Option tail(shapeless.Coproduct);
    descriptor: (Lshapeless/Coproduct;)Lscala/Option;
    flags: (0x1041) ACC_PUBLIC, ACC_BRIDGE, ACC_SYNTHETIC
    Code:
      stack=2, locals=2, args_size=2
         0: aload_0
         1: aload_1
         2: checkcast     #45                 // class shapeless/$colon$plus$colon
         5: invokevirtual #86                 // Method tail:(Lshapeless/$colon$plus$colon;)Lscala/Option;
         8: areturn
      LineNumberTable:
        line 841: 0
      LocalVariableTable:
        Start  Length  Slot  Name   Signature
            0       9     0  this   Lshapeless/ops/coproduct$IsCCons$$anon$54;
            0       9     1     c   Lshapeless/Coproduct;
    MethodParameters:
      Name                           Flags
      c                              final

  public scala.Option head(shapeless.Coproduct);
    descriptor: (Lshapeless/Coproduct;)Lscala/Option;
    flags: (0x1041) ACC_PUBLIC, ACC_BRIDGE, ACC_SYNTHETIC
    Code:
      stack=2, locals=2, args_size=2
         0: aload_0
         1: aload_1
         2: checkcast     #45                 // class shapeless/$colon$plus$colon
         5: invokevirtual #88                 // Method head:(Lshapeless/$colon$plus$colon;)Lscala/Option;
         8: areturn
      LineNumberTable:
        line 841: 0
      LocalVariableTable:
        Start  Length  Slot  Name   Signature
            0       9     0  this   Lshapeless/ops/coproduct$IsCCons$$anon$54;
            0       9     1     c   Lshapeless/Coproduct;
    MethodParameters:
      Name                           Flags
      c                              final

  public shapeless.ops.coproduct$IsCCons$$anon$54();
    descriptor: ()V
    flags: (0x0001) ACC_PUBLIC
    Code:
      stack=1, locals=1, args_size=1
         0: aload_0
         1: invokespecial #91                 // Method java/lang/Object."<init>":()V
         4: return
      LineNumberTable:
        line 841: 0
      LocalVariableTable:
        Start  Length  Slot  Name   Signature
            0       5     0  this   Lshapeless/ops/coproduct$IsCCons$$anon$54;
}
InnerClasses:
  public static #16= #7 of #15;           // IsCCons=class shapeless/ops/coproduct$IsCCons of class shapeless/ops/coproduct
  public static #17= #10 of #15;          // IsCCons$=class shapeless/ops/coproduct$IsCCons$ of class shapeless/ops/coproduct
  public final #2;                        // class shapeless/ops/coproduct$IsCCons$$anon$54
EnclosingMethod: #10.#13                // shapeless.ops.coproduct$IsCCons$.coproductCCons
Signature: #3                           // Ljava/lang/Object;Lshapeless/ops/coproduct$IsCCons<Lshapeless/$colon$plus$colon<TH0;TT0;>;>;
SourceFile: "coproduct.scala"
  ScalaInlineInfo: length = 0x27 (unknown attribute)
   01 01 00 07 00 1D 00 59 01 00 39 00 3A 01 00 39
   00 51 01 00 12 00 13 01 00 12 00 54 01 00 30 00
   13 01 00 30 00 54 01
  Scala: length = 0x0 (unknown attribute)

