Classfile /Users/mw/Projects/slang-braindump/.jar/jar11/assemble/slang-braindump/assemble/content/shapeless/ops/coproduct$Reverse$$anon$61.class
  Last modified May 29, 2022; size 1604 bytes
  SHA-256 checksum 7026b12c065df635745951a37363ceeab5a4d4e9d76fff2b916b04393b78cb52
  Compiled from "coproduct.scala"
public final class shapeless.ops.coproduct$Reverse$$anon$61 extends java.lang.Object implements shapeless.ops.coproduct$Reverse<C>
  minor version: 0
  major version: 52
  flags: (0x0031) ACC_PUBLIC, ACC_FINAL, ACC_SUPER
  this_class: #2                          // shapeless/ops/coproduct$Reverse$$anon$61
  super_class: #5                         // java/lang/Object
  interfaces: 1, fields: 1, methods: 3, attributes: 6
Constant pool:
   #1 = Utf8               shapeless/ops/coproduct$Reverse$$anon$61
   #2 = Class              #1             // shapeless/ops/coproduct$Reverse$$anon$61
   #3 = Utf8               Ljava/lang/Object;Lshapeless/ops/coproduct$Reverse<TC;>;
   #4 = Utf8               java/lang/Object
   #5 = Class              #4             // java/lang/Object
   #6 = Utf8               shapeless/ops/coproduct$Reverse
   #7 = Class              #6             // shapeless/ops/coproduct$Reverse
   #8 = Utf8               coproduct.scala
   #9 = Utf8               shapeless/ops/coproduct$Reverse$
  #10 = Class              #9             // shapeless/ops/coproduct$Reverse$
  #11 = Utf8               reverse
  #12 = Utf8               (Lshapeless/ops/coproduct$Reverse$Reverse0;)Lshapeless/ops/coproduct$Reverse;
  #13 = NameAndType        #11:#12        // reverse:(Lshapeless/ops/coproduct$Reverse$Reverse0;)Lshapeless/ops/coproduct$Reverse;
  #14 = Utf8               shapeless/ops/coproduct
  #15 = Class              #14            // shapeless/ops/coproduct
  #16 = Utf8               Reverse
  #17 = Utf8               Reverse$
  #18 = Utf8               shapeless/ops/coproduct$Reverse$Reverse0
  #19 = Class              #18            // shapeless/ops/coproduct$Reverse$Reverse0
  #20 = Utf8               Reverse0
  #21 = Utf8               reverse$1
  #22 = Utf8               Lshapeless/ops/coproduct$Reverse$Reverse0;
  #23 = Utf8               apply
  #24 = Utf8               (Lshapeless/Coproduct;)Lshapeless/Coproduct;
  #25 = Utf8               (TC;)TOut0;
  #26 = Utf8               c
  #27 = NameAndType        #21:#22        // reverse$1:Lshapeless/ops/coproduct$Reverse$Reverse0;
  #28 = Fieldref           #2.#27         // shapeless/ops/coproduct$Reverse$$anon$61.reverse$1:Lshapeless/ops/coproduct$Reverse$Reverse0;
  #29 = Utf8               scala/package$
  #30 = Class              #29            // scala/package$
  #31 = Utf8               MODULE$
  #32 = Utf8               Lscala/package$;
  #33 = NameAndType        #31:#32        // MODULE$:Lscala/package$;
  #34 = Fieldref           #30.#33        // scala/package$.MODULE$:Lscala/package$;
  #35 = Utf8               Right
  #36 = Utf8               ()Lscala/util/Right$;
  #37 = NameAndType        #35:#36        // Right:()Lscala/util/Right$;
  #38 = Methodref          #30.#37        // scala/package$.Right:()Lscala/util/Right$;
  #39 = Utf8               scala/util/Right$
  #40 = Class              #39            // scala/util/Right$
  #41 = Utf8               (Ljava/lang/Object;)Lscala/util/Right;
  #42 = NameAndType        #23:#41        // apply:(Ljava/lang/Object;)Lscala/util/Right;
  #43 = Methodref          #40.#42        // scala/util/Right$.apply:(Ljava/lang/Object;)Lscala/util/Right;
  #44 = Utf8               (Lscala/util/Either;)Lshapeless/Coproduct;
  #45 = NameAndType        #23:#44        // apply:(Lscala/util/Either;)Lshapeless/Coproduct;
  #46 = InterfaceMethodref #19.#45        // shapeless/ops/coproduct$Reverse$Reverse0.apply:(Lscala/util/Either;)Lshapeless/Coproduct;
  #47 = Utf8               this
  #48 = Utf8               Lshapeless/ops/coproduct$Reverse$$anon$61;
  #49 = Utf8               Lshapeless/Coproduct;
  #50 = Utf8               (Ljava/lang/Object;)Ljava/lang/Object;
  #51 = Utf8               t
  #52 = Utf8               shapeless/Coproduct
  #53 = Class              #52            // shapeless/Coproduct
  #54 = NameAndType        #23:#24        // apply:(Lshapeless/Coproduct;)Lshapeless/Coproduct;
  #55 = Methodref          #2.#54         // shapeless/ops/coproduct$Reverse$$anon$61.apply:(Lshapeless/Coproduct;)Lshapeless/Coproduct;
  #56 = Utf8               Ljava/lang/Object;
  #57 = Utf8               <init>
  #58 = Utf8               (Lshapeless/ops/coproduct$Reverse$Reverse0;)V
  #59 = Utf8               ()V
  #60 = NameAndType        #57:#59        // "<init>":()V
  #61 = Methodref          #5.#60         // java/lang/Object."<init>":()V
  #62 = Utf8               Code
  #63 = Utf8               LineNumberTable
  #64 = Utf8               LocalVariableTable
  #65 = Utf8               Signature
  #66 = Utf8               MethodParameters
  #67 = Utf8               InnerClasses
  #68 = Utf8               EnclosingMethod
  #69 = Utf8               SourceFile
  #70 = Utf8               ScalaInlineInfo
  #71 = Utf8               Scala
{
  private final shapeless.ops.coproduct$Reverse$Reverse0 reverse$1;
    descriptor: Lshapeless/ops/coproduct$Reverse$Reverse0;
    flags: (0x0012) ACC_PRIVATE, ACC_FINAL

  public Out0 apply(C);
    descriptor: (Lshapeless/Coproduct;)Lshapeless/Coproduct;
    flags: (0x0001) ACC_PUBLIC
    Code:
      stack=3, locals=2, args_size=2
         0: aload_0
         1: getfield      #28                 // Field reverse$1:Lshapeless/ops/coproduct$Reverse$Reverse0;
         4: getstatic     #34                 // Field scala/package$.MODULE$:Lscala/package$;
         7: invokevirtual #38                 // Method scala/package$.Right:()Lscala/util/Right$;
        10: aload_1
        11: invokevirtual #43                 // Method scala/util/Right$.apply:(Ljava/lang/Object;)Lscala/util/Right;
        14: invokeinterface #46,  2           // InterfaceMethod shapeless/ops/coproduct$Reverse$Reverse0.apply:(Lscala/util/Either;)Lshapeless/Coproduct;
        19: areturn
      LineNumberTable:
        line 987: 0
      LocalVariableTable:
        Start  Length  Slot  Name   Signature
            0      20     0  this   Lshapeless/ops/coproduct$Reverse$$anon$61;
            0      20     1     c   Lshapeless/Coproduct;
    Signature: #25                          // (TC;)TOut0;
    MethodParameters:
      Name                           Flags
      c                              final

  public java.lang.Object apply(java.lang.Object);
    descriptor: (Ljava/lang/Object;)Ljava/lang/Object;
    flags: (0x1041) ACC_PUBLIC, ACC_BRIDGE, ACC_SYNTHETIC
    Code:
      stack=2, locals=2, args_size=2
         0: aload_0
         1: aload_1
         2: checkcast     #53                 // class shapeless/Coproduct
         5: invokevirtual #55                 // Method apply:(Lshapeless/Coproduct;)Lshapeless/Coproduct;
         8: areturn
      LineNumberTable:
        line 985: 0
      LocalVariableTable:
        Start  Length  Slot  Name   Signature
            0       9     0  this   Lshapeless/ops/coproduct$Reverse$$anon$61;
            0       9     1     t   Ljava/lang/Object;
    MethodParameters:
      Name                           Flags
      t                              final

  public shapeless.ops.coproduct$Reverse$$anon$61(shapeless.ops.coproduct$Reverse$Reverse0);
    descriptor: (Lshapeless/ops/coproduct$Reverse$Reverse0;)V
    flags: (0x0001) ACC_PUBLIC
    Code:
      stack=2, locals=2, args_size=2
         0: aload_0
         1: aload_1
         2: putfield      #28                 // Field reverse$1:Lshapeless/ops/coproduct$Reverse$Reverse0;
         5: aload_0
         6: invokespecial #61                 // Method java/lang/Object."<init>":()V
         9: return
      LineNumberTable:
        line 984: 0
        line 985: 5
      LocalVariableTable:
        Start  Length  Slot  Name   Signature
            0      10     0  this   Lshapeless/ops/coproduct$Reverse$$anon$61;
            0      10     1 reverse$1   Lshapeless/ops/coproduct$Reverse$Reverse0;
    MethodParameters:
      Name                           Flags
      reverse$1                      final
}
InnerClasses:
  public static #16= #7 of #15;           // Reverse=class shapeless/ops/coproduct$Reverse of class shapeless/ops/coproduct
  public static #17= #10 of #15;          // Reverse$=class shapeless/ops/coproduct$Reverse$ of class shapeless/ops/coproduct
  public final #2;                        // class shapeless/ops/coproduct$Reverse$$anon$61
  public static #20= #19 of #10;          // Reverse0=class shapeless/ops/coproduct$Reverse$Reverse0 of class shapeless/ops/coproduct$Reverse$
EnclosingMethod: #10.#13                // shapeless.ops.coproduct$Reverse$.reverse
Signature: #3                           // Ljava/lang/Object;Lshapeless/ops/coproduct$Reverse<TC;>;
SourceFile: "coproduct.scala"
  ScalaInlineInfo: length = 0x13 (unknown attribute)
   01 01 00 03 00 39 00 3A 01 00 17 00 32 01 00 17
   00 18 01
  Scala: length = 0x0 (unknown attribute)

