Classfile /Users/mw/Projects/slang-braindump/.jar/jar11/assemble/slang-braindump/assemble/content/shapeless/ops/coproduct$ZipWith$$anon$32.class
  Last modified May 29, 2022; size 1200 bytes
  SHA-256 checksum 4c27301a82de826590a2c4e095da93cac49a853359923204c6b7f7d6daff4871
  Compiled from "coproduct.scala"
public final class shapeless.ops.coproduct$ZipWith$$anon$32 extends java.lang.Object implements shapeless.ops.coproduct$ZipWith<shapeless.HNil, shapeless.CNil>
  minor version: 0
  major version: 52
  flags: (0x0031) ACC_PUBLIC, ACC_FINAL, ACC_SUPER
  this_class: #2                          // shapeless/ops/coproduct$ZipWith$$anon$32
  super_class: #5                         // java/lang/Object
  interfaces: 1, fields: 0, methods: 3, attributes: 6
Constant pool:
   #1 = Utf8               shapeless/ops/coproduct$ZipWith$$anon$32
   #2 = Class              #1             // shapeless/ops/coproduct$ZipWith$$anon$32
   #3 = Utf8               Ljava/lang/Object;Lshapeless/ops/coproduct$ZipWith<Lshapeless/HNil;Lshapeless/CNil;>;
   #4 = Utf8               java/lang/Object
   #5 = Class              #4             // java/lang/Object
   #6 = Utf8               shapeless/ops/coproduct$ZipWith
   #7 = Class              #6             // shapeless/ops/coproduct$ZipWith
   #8 = Utf8               coproduct.scala
   #9 = Utf8               shapeless/ops/coproduct$ZipWith$
  #10 = Class              #9             // shapeless/ops/coproduct$ZipWith$
  #11 = Utf8               cnilZipWith
  #12 = Utf8               ()Lshapeless/ops/coproduct$ZipWith;
  #13 = NameAndType        #11:#12        // cnilZipWith:()Lshapeless/ops/coproduct$ZipWith;
  #14 = Utf8               shapeless/ops/coproduct
  #15 = Class              #14            // shapeless/ops/coproduct
  #16 = Utf8               ZipWith
  #17 = Utf8               ZipWith$
  #18 = Utf8               apply
  #19 = Utf8               (Lshapeless/HNil;Lshapeless/CNil;)Lshapeless/CNil;
  #20 = Utf8               h
  #21 = Utf8               v
  #22 = Utf8               this
  #23 = Utf8               Lshapeless/ops/coproduct$ZipWith$$anon$32;
  #24 = Utf8               Lshapeless/HNil;
  #25 = Utf8               Lshapeless/CNil;
  #26 = Utf8               (Ljava/lang/Object;Ljava/lang/Object;)Ljava/lang/Object;
  #27 = Utf8               t
  #28 = Utf8               u
  #29 = Utf8               shapeless/HNil
  #30 = Class              #29            // shapeless/HNil
  #31 = Utf8               shapeless/CNil
  #32 = Class              #31            // shapeless/CNil
  #33 = NameAndType        #18:#19        // apply:(Lshapeless/HNil;Lshapeless/CNil;)Lshapeless/CNil;
  #34 = Methodref          #2.#33         // shapeless/ops/coproduct$ZipWith$$anon$32.apply:(Lshapeless/HNil;Lshapeless/CNil;)Lshapeless/CNil;
  #35 = Utf8               Ljava/lang/Object;
  #36 = Utf8               <init>
  #37 = Utf8               ()V
  #38 = NameAndType        #36:#37        // "<init>":()V
  #39 = Methodref          #5.#38         // java/lang/Object."<init>":()V
  #40 = Utf8               Code
  #41 = Utf8               LineNumberTable
  #42 = Utf8               LocalVariableTable
  #43 = Utf8               MethodParameters
  #44 = Utf8               InnerClasses
  #45 = Utf8               EnclosingMethod
  #46 = Utf8               Signature
  #47 = Utf8               SourceFile
  #48 = Utf8               ScalaInlineInfo
  #49 = Utf8               Scala
{
  public shapeless.CNil apply(shapeless.HNil, shapeless.CNil);
    descriptor: (Lshapeless/HNil;Lshapeless/CNil;)Lshapeless/CNil;
    flags: (0x0001) ACC_PUBLIC
    Code:
      stack=1, locals=3, args_size=3
         0: aload_2
         1: areturn
      LineNumberTable:
        line 527: 0
      LocalVariableTable:
        Start  Length  Slot  Name   Signature
            0       2     0  this   Lshapeless/ops/coproduct$ZipWith$$anon$32;
            0       2     1     h   Lshapeless/HNil;
            0       2     2     v   Lshapeless/CNil;
    MethodParameters:
      Name                           Flags
      h                              final
      v                              final

  public java.lang.Object apply(java.lang.Object, java.lang.Object);
    descriptor: (Ljava/lang/Object;Ljava/lang/Object;)Ljava/lang/Object;
    flags: (0x1041) ACC_PUBLIC, ACC_BRIDGE, ACC_SYNTHETIC
    Code:
      stack=3, locals=3, args_size=3
         0: aload_0
         1: aload_1
         2: checkcast     #30                 // class shapeless/HNil
         5: aload_2
         6: checkcast     #32                 // class shapeless/CNil
         9: invokevirtual #34                 // Method apply:(Lshapeless/HNil;Lshapeless/CNil;)Lshapeless/CNil;
        12: areturn
      LineNumberTable:
        line 525: 0
      LocalVariableTable:
        Start  Length  Slot  Name   Signature
            0      13     0  this   Lshapeless/ops/coproduct$ZipWith$$anon$32;
            0      13     1     t   Ljava/lang/Object;
            0      13     2     u   Ljava/lang/Object;
    MethodParameters:
      Name                           Flags
      t                              final
      u                              final

  public shapeless.ops.coproduct$ZipWith$$anon$32();
    descriptor: ()V
    flags: (0x0001) ACC_PUBLIC
    Code:
      stack=1, locals=1, args_size=1
         0: aload_0
         1: invokespecial #39                 // Method java/lang/Object."<init>":()V
         4: return
      LineNumberTable:
        line 525: 0
      LocalVariableTable:
        Start  Length  Slot  Name   Signature
            0       5     0  this   Lshapeless/ops/coproduct$ZipWith$$anon$32;
}
InnerClasses:
  public static #16= #7 of #15;           // ZipWith=class shapeless/ops/coproduct$ZipWith of class shapeless/ops/coproduct
  public static #17= #10 of #15;          // ZipWith$=class shapeless/ops/coproduct$ZipWith$ of class shapeless/ops/coproduct
  public final #2;                        // class shapeless/ops/coproduct$ZipWith$$anon$32
EnclosingMethod: #10.#13                // shapeless.ops.coproduct$ZipWith$.cnilZipWith
Signature: #3                           // Ljava/lang/Object;Lshapeless/ops/coproduct$ZipWith<Lshapeless/HNil;Lshapeless/CNil;>;
SourceFile: "coproduct.scala"
  ScalaInlineInfo: length = 0x13 (unknown attribute)
   01 01 00 03 00 24 00 25 01 00 12 00 1A 01 00 12
   00 13 01
  Scala: length = 0x0 (unknown attribute)

