Classfile /Users/mw/Projects/slang-braindump/.jar/jar11/assemble/slang-braindump/assemble/content/shapeless/ops/coproduct$LeftFolder$.class
  Last modified May 29, 2022; size 2601 bytes
  SHA-256 checksum 9bfc63fc893d82b0c0ac5f432d72ff4f8c2d34672435826062ca900f3f5ee948
  Compiled from "coproduct.scala"
public class shapeless.ops.coproduct$LeftFolder$ implements java.io.Serializable
  minor version: 0
  major version: 52
  flags: (0x0021) ACC_PUBLIC, ACC_SUPER
  this_class: #2                          // shapeless/ops/coproduct$LeftFolder$
  super_class: #4                         // java/lang/Object
  interfaces: 1, fields: 1, methods: 6, attributes: 4
Constant pool:
   #1 = Utf8               shapeless/ops/coproduct$LeftFolder$
   #2 = Class              #1             // shapeless/ops/coproduct$LeftFolder$
   #3 = Utf8               java/lang/Object
   #4 = Class              #3             // java/lang/Object
   #5 = Utf8               java/io/Serializable
   #6 = Class              #5             // java/io/Serializable
   #7 = Utf8               coproduct.scala
   #8 = Utf8               shapeless/PolyDefns$Case
   #9 = Class              #8             // shapeless/PolyDefns$Case
  #10 = Utf8               shapeless/PolyDefns
  #11 = Class              #10            // shapeless/PolyDefns
  #12 = Utf8               Case
  #13 = Utf8               shapeless/ops/coproduct$LeftFolder
  #14 = Class              #13            // shapeless/ops/coproduct$LeftFolder
  #15 = Utf8               shapeless/ops/coproduct
  #16 = Class              #15            // shapeless/ops/coproduct
  #17 = Utf8               LeftFolder
  #18 = Utf8               LeftFolder$
  #19 = Utf8               shapeless/ops/coproduct$LeftFolder$$anon$23
  #20 = Class              #19            // shapeless/ops/coproduct$LeftFolder$$anon$23
  #21 = Utf8               shapeless/ops/coproduct$LeftFolder$$anon$24
  #22 = Class              #21            // shapeless/ops/coproduct$LeftFolder$$anon$24
  #23 = Utf8               MODULE$
  #24 = Utf8               Lshapeless/ops/coproduct$LeftFolder$;
  #25 = Utf8               <clinit>
  #26 = Utf8               ()V
  #27 = Utf8               <init>
  #28 = NameAndType        #27:#26        // "<init>":()V
  #29 = Methodref          #2.#28         // shapeless/ops/coproduct$LeftFolder$."<init>":()V
  #30 = NameAndType        #23:#24        // MODULE$:Lshapeless/ops/coproduct$LeftFolder$;
  #31 = Fieldref           #2.#30         // shapeless/ops/coproduct$LeftFolder$.MODULE$:Lshapeless/ops/coproduct$LeftFolder$;
  #32 = Utf8               apply
  #33 = Utf8               (Lshapeless/ops/coproduct$LeftFolder;)Lshapeless/ops/coproduct$LeftFolder;
  #34 = Utf8               <C::Lshapeless/Coproduct;In:Ljava/lang/Object;F:Ljava/lang/Object;>(Lshapeless/ops/coproduct$LeftFolder<TC;TIn;TF;>;)Lshapeless/ops/coproduct$LeftFolder<TC;TIn;TF;>;
  #35 = Utf8               folder
  #36 = Utf8               this
  #37 = Utf8               Lshapeless/ops/coproduct$LeftFolder;
  #38 = Utf8               hdLeftFolder
  #39 = Utf8               (Lshapeless/PolyDefns$Case;)Lshapeless/ops/coproduct$LeftFolder;
  #40 = Utf8               <H:Ljava/lang/Object;In:Ljava/lang/Object;F:Ljava/lang/Object;>(Lshapeless/PolyDefns$Case<TF;Lshapeless/$colon$colon<TIn;Lshapeless/$colon$colon<TH;Lshapeless/HNil;>;>;>;)Lshapeless/ops/coproduct$LeftFolder<Lshapeless/$colon$plus$colon<TH;Lshapeless/CNil;>;TIn;TF;>;
  #41 = Utf8               f
  #42 = Utf8               (Lshapeless/PolyDefns$Case;)V
  #43 = NameAndType        #27:#42        // "<init>":(Lshapeless/PolyDefns$Case;)V
  #44 = Methodref          #20.#43        // shapeless/ops/coproduct$LeftFolder$$anon$23."<init>":(Lshapeless/PolyDefns$Case;)V
  #45 = Utf8               Lshapeless/PolyDefns$Case;
  #46 = Utf8               tlLeftFolder
  #47 = Utf8               (Lshapeless/PolyDefns$Case;Lshapeless/ops/coproduct$LeftFolder;)Lshapeless/ops/coproduct$LeftFolder;
  #48 = Utf8               <H:Ljava/lang/Object;T::Lshapeless/Coproduct;In:Ljava/lang/Object;HF:Ljava/lang/Object;OutH:Ljava/lang/Object;>(Lshapeless/PolyDefns$Case<THF;Lshapeless/$colon$colon<TIn;Lshapeless/$colon$colon<TH;Lshapeless/HNil;>;>;>;Lshapeless/ops/coproduct$LeftFolder<TT;TIn;THF;>;)Lshapeless/ops/coproduct$LeftFolder<Lshapeless/$colon$plus$colon<TH;TT;>;TIn;THF;>;
  #49 = Utf8               ft
  #50 = Utf8               (Lshapeless/PolyDefns$Case;Lshapeless/ops/coproduct$LeftFolder;)V
  #51 = NameAndType        #27:#50        // "<init>":(Lshapeless/PolyDefns$Case;Lshapeless/ops/coproduct$LeftFolder;)V
  #52 = Methodref          #22.#51        // shapeless/ops/coproduct$LeftFolder$$anon$24."<init>":(Lshapeless/PolyDefns$Case;Lshapeless/ops/coproduct$LeftFolder;)V
  #53 = Utf8               writeReplace
  #54 = Utf8               ()Ljava/lang/Object;
  #55 = Utf8               scala/runtime/ModuleSerializationProxy
  #56 = Class              #55            // scala/runtime/ModuleSerializationProxy
  #57 = Utf8               (Ljava/lang/Class;)V
  #58 = NameAndType        #27:#57        // "<init>":(Ljava/lang/Class;)V
  #59 = Methodref          #56.#58        // scala/runtime/ModuleSerializationProxy."<init>":(Ljava/lang/Class;)V
  #60 = Methodref          #4.#28         // java/lang/Object."<init>":()V
  #61 = Utf8               Code
  #62 = Utf8               LineNumberTable
  #63 = Utf8               LocalVariableTable
  #64 = Utf8               Signature
  #65 = Utf8               MethodParameters
  #66 = Utf8               InnerClasses
  #67 = Utf8               SourceFile
  #68 = Utf8               ScalaInlineInfo
  #69 = Utf8               Scala
{
  public static final shapeless.ops.coproduct$LeftFolder$ MODULE$;
    descriptor: Lshapeless/ops/coproduct$LeftFolder$;
    flags: (0x0019) ACC_PUBLIC, ACC_STATIC, ACC_FINAL

  public static {};
    descriptor: ()V
    flags: (0x0009) ACC_PUBLIC, ACC_STATIC
    Code:
      stack=2, locals=0, args_size=0
         0: new           #2                  // class shapeless/ops/coproduct$LeftFolder$
         3: dup
         4: invokespecial #29                 // Method "<init>":()V
         7: putstatic     #31                 // Field MODULE$:Lshapeless/ops/coproduct$LeftFolder$;
        10: return
      LineNumberTable:
        line 380: 0

  public <C extends shapeless.Coproduct, In extends java.lang.Object, F extends java.lang.Object> shapeless.ops.coproduct$LeftFolder<C, In, F> apply(shapeless.ops.coproduct$LeftFolder<C, In, F>);
    descriptor: (Lshapeless/ops/coproduct$LeftFolder;)Lshapeless/ops/coproduct$LeftFolder;
    flags: (0x0001) ACC_PUBLIC
    Code:
      stack=1, locals=2, args_size=2
         0: aload_1
         1: areturn
      LineNumberTable:
        line 381: 0
      LocalVariableTable:
        Start  Length  Slot  Name   Signature
            0       2     0  this   Lshapeless/ops/coproduct$LeftFolder$;
            0       2     1 folder   Lshapeless/ops/coproduct$LeftFolder;
    Signature: #34                          // <C::Lshapeless/Coproduct;In:Ljava/lang/Object;F:Ljava/lang/Object;>(Lshapeless/ops/coproduct$LeftFolder<TC;TIn;TF;>;)Lshapeless/ops/coproduct$LeftFolder<TC;TIn;TF;>;
    MethodParameters:
      Name                           Flags
      folder                         final

  public <H extends java.lang.Object, In extends java.lang.Object, F extends java.lang.Object> shapeless.ops.coproduct$LeftFolder<shapeless.$colon$plus$colon<H, shapeless.CNil>, In, F> hdLeftFolder(shapeless.PolyDefns$Case<F, shapeless.$colon$colon<In, shapeless.$colon$colon<H, shapeless.HNil>>>);
    descriptor: (Lshapeless/PolyDefns$Case;)Lshapeless/ops/coproduct$LeftFolder;
    flags: (0x0001) ACC_PUBLIC
    Code:
      stack=3, locals=2, args_size=2
         0: new           #20                 // class shapeless/ops/coproduct$LeftFolder$$anon$23
         3: dup
         4: aload_1
         5: invokespecial #44                 // Method shapeless/ops/coproduct$LeftFolder$$anon$23."<init>":(Lshapeless/PolyDefns$Case;)V
         8: areturn
      LineNumberTable:
        line 386: 0
      LocalVariableTable:
        Start  Length  Slot  Name   Signature
            0       9     0  this   Lshapeless/ops/coproduct$LeftFolder$;
            0       9     1     f   Lshapeless/PolyDefns$Case;
    Signature: #40                          // <H:Ljava/lang/Object;In:Ljava/lang/Object;F:Ljava/lang/Object;>(Lshapeless/PolyDefns$Case<TF;Lshapeless/$colon$colon<TIn;Lshapeless/$colon$colon<TH;Lshapeless/HNil;>;>;>;)Lshapeless/ops/coproduct$LeftFolder<Lshapeless/$colon$plus$colon<TH;Lshapeless/CNil;>;TIn;TF;>;
    MethodParameters:
      Name                           Flags
      f                              final

  public <H extends java.lang.Object, T extends shapeless.Coproduct, In extends java.lang.Object, HF extends java.lang.Object, OutH extends java.lang.Object> shapeless.ops.coproduct$LeftFolder<shapeless.$colon$plus$colon<H, T>, In, HF> tlLeftFolder(shapeless.PolyDefns$Case<HF, shapeless.$colon$colon<In, shapeless.$colon$colon<H, shapeless.HNil>>>, shapeless.ops.coproduct$LeftFolder<T, In, HF>);
    descriptor: (Lshapeless/PolyDefns$Case;Lshapeless/ops/coproduct$LeftFolder;)Lshapeless/ops/coproduct$LeftFolder;
    flags: (0x0001) ACC_PUBLIC
    Code:
      stack=4, locals=3, args_size=3
         0: new           #22                 // class shapeless/ops/coproduct$LeftFolder$$anon$24
         3: dup
         4: aload_1
         5: aload_2
         6: invokespecial #52                 // Method shapeless/ops/coproduct$LeftFolder$$anon$24."<init>":(Lshapeless/PolyDefns$Case;Lshapeless/ops/coproduct$LeftFolder;)V
         9: areturn
      LineNumberTable:
        line 392: 0
      LocalVariableTable:
        Start  Length  Slot  Name   Signature
            0      10     0  this   Lshapeless/ops/coproduct$LeftFolder$;
            0      10     1     f   Lshapeless/PolyDefns$Case;
            0      10     2    ft   Lshapeless/ops/coproduct$LeftFolder;
    Signature: #48                          // <H:Ljava/lang/Object;T::Lshapeless/Coproduct;In:Ljava/lang/Object;HF:Ljava/lang/Object;OutH:Ljava/lang/Object;>(Lshapeless/PolyDefns$Case<THF;Lshapeless/$colon$colon<TIn;Lshapeless/$colon$colon<TH;Lshapeless/HNil;>;>;>;Lshapeless/ops/coproduct$LeftFolder<TT;TIn;THF;>;)Lshapeless/ops/coproduct$LeftFolder<Lshapeless/$colon$plus$colon<TH;TT;>;TIn;THF;>;
    MethodParameters:
      Name                           Flags
      f                              final
      ft                             final

  private java.lang.Object writeReplace();
    descriptor: ()Ljava/lang/Object;
    flags: (0x0002) ACC_PRIVATE
    Code:
      stack=3, locals=1, args_size=1
         0: new           #56                 // class scala/runtime/ModuleSerializationProxy
         3: dup
         4: ldc           #2                  // class shapeless/ops/coproduct$LeftFolder$
         6: invokespecial #59                 // Method scala/runtime/ModuleSerializationProxy."<init>":(Ljava/lang/Class;)V
         9: areturn
      LineNumberTable:
        line 380: 0
      LocalVariableTable:
        Start  Length  Slot  Name   Signature
            0      10     0  this   Lshapeless/ops/coproduct$LeftFolder$;

  public shapeless.ops.coproduct$LeftFolder$();
    descriptor: ()V
    flags: (0x0001) ACC_PUBLIC
    Code:
      stack=1, locals=1, args_size=1
         0: aload_0
         1: invokespecial #60                 // Method java/lang/Object."<init>":()V
         4: return
      LineNumberTable:
        line 408: 0
        line 380: 4
      LocalVariableTable:
        Start  Length  Slot  Name   Signature
            0       5     0  this   Lshapeless/ops/coproduct$LeftFolder$;
}
InnerClasses:
  public static abstract #12= #9 of #11;  // Case=class shapeless/PolyDefns$Case of class shapeless/PolyDefns
  public static #17= #14 of #16;          // LeftFolder=class shapeless/ops/coproduct$LeftFolder of class shapeless/ops/coproduct
  public static #18= #2 of #16;           // LeftFolder$=class shapeless/ops/coproduct$LeftFolder$ of class shapeless/ops/coproduct
  public final #20;                       // class shapeless/ops/coproduct$LeftFolder$$anon$23
  public final #22;                       // class shapeless/ops/coproduct$LeftFolder$$anon$24
SourceFile: "coproduct.scala"
  ScalaInlineInfo: length = 0x1D (unknown attribute)
   01 01 00 05 00 1B 00 1A 01 00 20 00 21 01 00 26
   00 27 01 00 2E 00 2F 01 00 35 00 36 01
  Scala: length = 0x0 (unknown attribute)

