Classfile /Users/mw/Projects/slang-braindump/.jar/jar11/assemble/slang-braindump/assemble/content/shapeless/ops/coproduct$Reverse$$anon$64.class
  Last modified May 29, 2022; size 2340 bytes
  SHA-256 checksum 19b7120eac82f77565d7f1f45418eb23ec49764579b8440b708dd056a13045fa
  Compiled from "coproduct.scala"
public final class shapeless.ops.coproduct$Reverse$$anon$64 extends java.lang.Object implements shapeless.ops.coproduct$Reverse<shapeless.$colon$plus$colon<H, T>>
  minor version: 0
  major version: 52
  flags: (0x0031) ACC_PUBLIC, ACC_FINAL, ACC_SUPER
  this_class: #2                          // shapeless/ops/coproduct$Reverse$$anon$64
  super_class: #5                         // java/lang/Object
  interfaces: 1, fields: 3, methods: 3, attributes: 6
Constant pool:
   #1 = Utf8               shapeless/ops/coproduct$Reverse$$anon$64
   #2 = Class              #1             // shapeless/ops/coproduct$Reverse$$anon$64
   #3 = Utf8               Ljava/lang/Object;Lshapeless/ops/coproduct$Reverse<Lshapeless/$colon$plus$colon<TH;TT;>;>;
   #4 = Utf8               java/lang/Object
   #5 = Class              #4             // java/lang/Object
   #6 = Utf8               shapeless/ops/coproduct$Reverse
   #7 = Class              #6             // shapeless/ops/coproduct$Reverse
   #8 = Utf8               coproduct.scala
   #9 = Utf8               shapeless/ops/coproduct$Reverse$
  #10 = Class              #9             // shapeless/ops/coproduct$Reverse$
  #11 = Utf8               reverseCoproduct
  #12 = Utf8               (Lshapeless/ops/coproduct$Reverse;Lshapeless/ops/coproduct$RotateLeft;Lshapeless/ops/coproduct$Inject;)Lshapeless/ops/coproduct$Reverse;
  #13 = NameAndType        #11:#12        // reverseCoproduct:(Lshapeless/ops/coproduct$Reverse;Lshapeless/ops/coproduct$RotateLeft;Lshapeless/ops/coproduct$Inject;)Lshapeless/ops/coproduct$Reverse;
  #14 = Utf8               shapeless/ops/coproduct$Inject
  #15 = Class              #14            // shapeless/ops/coproduct$Inject
  #16 = Utf8               shapeless/ops/coproduct
  #17 = Class              #16            // shapeless/ops/coproduct
  #18 = Utf8               Inject
  #19 = Utf8               Reverse
  #20 = Utf8               Reverse$
  #21 = Utf8               shapeless/ops/coproduct$RotateLeft
  #22 = Class              #21            // shapeless/ops/coproduct$RotateLeft
  #23 = Utf8               RotateLeft
  #24 = Utf8               inject$2
  #25 = Utf8               Lshapeless/ops/coproduct$Inject;
  #26 = Utf8               rotateLeft$3
  #27 = Utf8               Lshapeless/ops/coproduct$RotateLeft;
  #28 = Utf8               reverse$2
  #29 = Utf8               Lshapeless/ops/coproduct$Reverse;
  #30 = Utf8               apply
  #31 = Utf8               (Lshapeless/$colon$plus$colon;)Lshapeless/Coproduct;
  #32 = Utf8               (Lshapeless/$colon$plus$colon<TH;TT;>;)TRotateL_HReverseT;
  #33 = Utf8               c
  #34 = Utf8               shapeless/Inl
  #35 = Class              #34            // shapeless/Inl
  #36 = Utf8               head
  #37 = Utf8               ()Ljava/lang/Object;
  #38 = NameAndType        #36:#37        // head:()Ljava/lang/Object;
  #39 = Methodref          #35.#38        // shapeless/Inl.head:()Ljava/lang/Object;
  #40 = NameAndType        #24:#25        // inject$2:Lshapeless/ops/coproduct$Inject;
  #41 = Fieldref           #2.#40         // shapeless/ops/coproduct$Reverse$$anon$64.inject$2:Lshapeless/ops/coproduct$Inject;
  #42 = Utf8               (Ljava/lang/Object;)Lshapeless/Coproduct;
  #43 = NameAndType        #30:#42        // apply:(Ljava/lang/Object;)Lshapeless/Coproduct;
  #44 = InterfaceMethodref #15.#43        // shapeless/ops/coproduct$Inject.apply:(Ljava/lang/Object;)Lshapeless/Coproduct;
  #45 = Utf8               shapeless/Inr
  #46 = Class              #45            // shapeless/Inr
  #47 = Utf8               tail
  #48 = Utf8               ()Lshapeless/Coproduct;
  #49 = NameAndType        #47:#48        // tail:()Lshapeless/Coproduct;
  #50 = Methodref          #46.#49        // shapeless/Inr.tail:()Lshapeless/Coproduct;
  #51 = NameAndType        #26:#27        // rotateLeft$3:Lshapeless/ops/coproduct$RotateLeft;
  #52 = Fieldref           #2.#51         // shapeless/ops/coproduct$Reverse$$anon$64.rotateLeft$3:Lshapeless/ops/coproduct$RotateLeft;
  #53 = NameAndType        #28:#29        // reverse$2:Lshapeless/ops/coproduct$Reverse;
  #54 = Fieldref           #2.#53         // shapeless/ops/coproduct$Reverse$$anon$64.reverse$2:Lshapeless/ops/coproduct$Reverse;
  #55 = Utf8               (Ljava/lang/Object;)Ljava/lang/Object;
  #56 = NameAndType        #30:#55        // apply:(Ljava/lang/Object;)Ljava/lang/Object;
  #57 = InterfaceMethodref #7.#56         // shapeless/ops/coproduct$Reverse.apply:(Ljava/lang/Object;)Ljava/lang/Object;
  #58 = Utf8               shapeless/Coproduct
  #59 = Class              #58            // shapeless/Coproduct
  #60 = Utf8               <init>
  #61 = Utf8               (Lshapeless/Coproduct;)V
  #62 = NameAndType        #60:#61        // "<init>":(Lshapeless/Coproduct;)V
  #63 = Methodref          #46.#62        // shapeless/Inr."<init>":(Lshapeless/Coproduct;)V
  #64 = InterfaceMethodref #22.#56        // shapeless/ops/coproduct$RotateLeft.apply:(Ljava/lang/Object;)Ljava/lang/Object;
  #65 = Utf8               scala/MatchError
  #66 = Class              #65            // scala/MatchError
  #67 = Utf8               (Ljava/lang/Object;)V
  #68 = NameAndType        #60:#67        // "<init>":(Ljava/lang/Object;)V
  #69 = Methodref          #66.#68        // scala/MatchError."<init>":(Ljava/lang/Object;)V
  #70 = Utf8               h
  #71 = Utf8               Ljava/lang/Object;
  #72 = Utf8               t
  #73 = Utf8               Lshapeless/Coproduct;
  #74 = Utf8               this
  #75 = Utf8               Lshapeless/ops/coproduct$Reverse$$anon$64;
  #76 = Utf8               Lshapeless/$colon$plus$colon;
  #77 = Utf8               shapeless/$colon$plus$colon
  #78 = Class              #77            // shapeless/$colon$plus$colon
  #79 = NameAndType        #30:#31        // apply:(Lshapeless/$colon$plus$colon;)Lshapeless/Coproduct;
  #80 = Methodref          #2.#79         // shapeless/ops/coproduct$Reverse$$anon$64.apply:(Lshapeless/$colon$plus$colon;)Lshapeless/Coproduct;
  #81 = Utf8               (Lshapeless/ops/coproduct$Inject;Lshapeless/ops/coproduct$RotateLeft;Lshapeless/ops/coproduct$Reverse;)V
  #82 = Utf8               ()V
  #83 = NameAndType        #60:#82        // "<init>":()V
  #84 = Methodref          #5.#83         // java/lang/Object."<init>":()V
  #85 = Utf8               Code
  #86 = Utf8               StackMapTable
  #87 = Utf8               LineNumberTable
  #88 = Utf8               LocalVariableTable
  #89 = Utf8               Signature
  #90 = Utf8               MethodParameters
  #91 = Utf8               InnerClasses
  #92 = Utf8               EnclosingMethod
  #93 = Utf8               SourceFile
  #94 = Utf8               ScalaInlineInfo
  #95 = Utf8               Scala
{
  private final shapeless.ops.coproduct$Inject inject$2;
    descriptor: Lshapeless/ops/coproduct$Inject;
    flags: (0x0012) ACC_PRIVATE, ACC_FINAL

  private final shapeless.ops.coproduct$RotateLeft rotateLeft$3;
    descriptor: Lshapeless/ops/coproduct$RotateLeft;
    flags: (0x0012) ACC_PRIVATE, ACC_FINAL

  private final shapeless.ops.coproduct$Reverse reverse$2;
    descriptor: Lshapeless/ops/coproduct$Reverse;
    flags: (0x0012) ACC_PRIVATE, ACC_FINAL

  public RotateL_HReverseT apply(shapeless.$colon$plus$colon<H, T>);
    descriptor: (Lshapeless/$colon$plus$colon;)Lshapeless/Coproduct;
    flags: (0x0001) ACC_PUBLIC
    Code:
      stack=5, locals=8, args_size=2
         0: aload_1
         1: astore_3
         2: aload_3
         3: instanceof    #35                 // class shapeless/Inl
         6: ifeq          37
         9: aload_3
        10: checkcast     #35                 // class shapeless/Inl
        13: astore        4
        15: aload         4
        17: invokevirtual #39                 // Method shapeless/Inl.head:()Ljava/lang/Object;
        20: astore        5
        22: aload_0
        23: getfield      #41                 // Field inject$2:Lshapeless/ops/coproduct$Inject;
        26: aload         5
        28: invokeinterface #44,  2           // InterfaceMethod shapeless/ops/coproduct$Inject.apply:(Ljava/lang/Object;)Lshapeless/Coproduct;
        33: astore_2
        34: goto          109
        37: goto          40
        40: aload_3
        41: instanceof    #46                 // class shapeless/Inr
        44: ifeq          97
        47: aload_3
        48: checkcast     #46                 // class shapeless/Inr
        51: astore        6
        53: aload         6
        55: invokevirtual #50                 // Method shapeless/Inr.tail:()Lshapeless/Coproduct;
        58: astore        7
        60: aload_0
        61: getfield      #52                 // Field rotateLeft$3:Lshapeless/ops/coproduct$RotateLeft;
        64: new           #46                 // class shapeless/Inr
        67: dup
        68: aload_0
        69: getfield      #54                 // Field reverse$2:Lshapeless/ops/coproduct$Reverse;
        72: aload         7
        74: invokeinterface #57,  2           // InterfaceMethod shapeless/ops/coproduct$Reverse.apply:(Ljava/lang/Object;)Ljava/lang/Object;
        79: checkcast     #59                 // class shapeless/Coproduct
        82: invokespecial #63                 // Method shapeless/Inr."<init>":(Lshapeless/Coproduct;)V
        85: invokeinterface #64,  2           // InterfaceMethod shapeless/ops/coproduct$RotateLeft.apply:(Ljava/lang/Object;)Ljava/lang/Object;
        90: checkcast     #59                 // class shapeless/Coproduct
        93: astore_2
        94: goto          109
        97: goto          100
       100: new           #66                 // class scala/MatchError
       103: dup
       104: aload_3
       105: invokespecial #69                 // Method scala/MatchError."<init>":(Ljava/lang/Object;)V
       108: athrow
       109: aload_2
       110: areturn
      StackMapTable: number_of_entries = 5
        frame_type = 253 /* append */
          offset_delta = 37
          locals = [ top, class shapeless/$colon$plus$colon ]
        frame_type = 2 /* same */
        frame_type = 56 /* same */
        frame_type = 2 /* same */
        frame_type = 255 /* full_frame */
          offset_delta = 8
          locals = [ class shapeless/ops/coproduct$Reverse$$anon$64, class shapeless/$colon$plus$colon, class shapeless/Coproduct, class shapeless/$colon$plus$colon ]
          stack = []
      LineNumberTable:
        line 1023: 0
        line 1024: 2
        line 1025: 40
        line 1023: 100
      LocalVariableTable:
        Start  Length  Slot  Name   Signature
           20      17     5     h   Ljava/lang/Object;
           58      39     7     t   Lshapeless/Coproduct;
            0     111     0  this   Lshapeless/ops/coproduct$Reverse$$anon$64;
            0     111     1     c   Lshapeless/$colon$plus$colon;
    Signature: #32                          // (Lshapeless/$colon$plus$colon<TH;TT;>;)TRotateL_HReverseT;
    MethodParameters:
      Name                           Flags
      c                              final

  public java.lang.Object apply(java.lang.Object);
    descriptor: (Ljava/lang/Object;)Ljava/lang/Object;
    flags: (0x1041) ACC_PUBLIC, ACC_BRIDGE, ACC_SYNTHETIC
    Code:
      stack=2, locals=2, args_size=2
         0: aload_0
         1: aload_1
         2: checkcast     #78                 // class shapeless/$colon$plus$colon
         5: invokevirtual #80                 // Method apply:(Lshapeless/$colon$plus$colon;)Lshapeless/Coproduct;
         8: areturn
      LineNumberTable:
        line 1021: 0
      LocalVariableTable:
        Start  Length  Slot  Name   Signature
            0       9     0  this   Lshapeless/ops/coproduct$Reverse$$anon$64;
            0       9     1     t   Ljava/lang/Object;
    MethodParameters:
      Name                           Flags
      t                              final

  public shapeless.ops.coproduct$Reverse$$anon$64(shapeless.ops.coproduct$Inject, shapeless.ops.coproduct$RotateLeft, shapeless.ops.coproduct$Reverse);
    descriptor: (Lshapeless/ops/coproduct$Inject;Lshapeless/ops/coproduct$RotateLeft;Lshapeless/ops/coproduct$Reverse;)V
    flags: (0x0001) ACC_PUBLIC
    Code:
      stack=2, locals=4, args_size=4
         0: aload_0
         1: aload_1
         2: putfield      #41                 // Field inject$2:Lshapeless/ops/coproduct$Inject;
         5: aload_0
         6: aload_2
         7: putfield      #52                 // Field rotateLeft$3:Lshapeless/ops/coproduct$RotateLeft;
        10: aload_0
        11: aload_3
        12: putfield      #54                 // Field reverse$2:Lshapeless/ops/coproduct$Reverse;
        15: aload_0
        16: invokespecial #84                 // Method java/lang/Object."<init>":()V
        19: return
      LineNumberTable:
        line 1020: 0
        line 1019: 5
        line 1018: 10
        line 1021: 15
      LocalVariableTable:
        Start  Length  Slot  Name   Signature
            0      20     0  this   Lshapeless/ops/coproduct$Reverse$$anon$64;
            0      20     1 inject$2   Lshapeless/ops/coproduct$Inject;
            0      20     2 rotateLeft$3   Lshapeless/ops/coproduct$RotateLeft;
            0      20     3 reverse$2   Lshapeless/ops/coproduct$Reverse;
    MethodParameters:
      Name                           Flags
      inject$2                       final
      rotateLeft$3                   final
      reverse$2                      final
}
InnerClasses:
  public static #18= #15 of #17;          // Inject=class shapeless/ops/coproduct$Inject of class shapeless/ops/coproduct
  public static #19= #7 of #17;           // Reverse=class shapeless/ops/coproduct$Reverse of class shapeless/ops/coproduct
  public static #20= #10 of #17;          // Reverse$=class shapeless/ops/coproduct$Reverse$ of class shapeless/ops/coproduct
  public final #2;                        // class shapeless/ops/coproduct$Reverse$$anon$64
  public static #23= #22 of #17;          // RotateLeft=class shapeless/ops/coproduct$RotateLeft of class shapeless/ops/coproduct
EnclosingMethod: #10.#13                // shapeless.ops.coproduct$Reverse$.reverseCoproduct
Signature: #3                           // Ljava/lang/Object;Lshapeless/ops/coproduct$Reverse<Lshapeless/$colon$plus$colon<TH;TT;>;>;
SourceFile: "coproduct.scala"
  ScalaInlineInfo: length = 0x13 (unknown attribute)
   01 01 00 03 00 3C 00 51 01 00 1E 00 37 01 00 1E
   00 1F 01
  Scala: length = 0x0 (unknown attribute)

