Classfile /Users/mw/Projects/slang-braindump/.jar/jar11/assemble/slang-braindump/assemble/content/shapeless/ops/coproduct$Drop$$anon$59.class
  Last modified May 29, 2022; size 1146 bytes
  SHA-256 checksum 14c7f51055ccf6e480188d57b1f21a351fa4c00630020a94fbd489e87e9da9fe
  Compiled from "coproduct.scala"
public final class shapeless.ops.coproduct$Drop$$anon$59 extends java.lang.Object implements shapeless.ops.coproduct$Drop<C, shapeless._0>
  minor version: 0
  major version: 52
  flags: (0x0031) ACC_PUBLIC, ACC_FINAL, ACC_SUPER
  this_class: #2                          // shapeless/ops/coproduct$Drop$$anon$59
  super_class: #5                         // java/lang/Object
  interfaces: 1, fields: 0, methods: 3, attributes: 6
Constant pool:
   #1 = Utf8               shapeless/ops/coproduct$Drop$$anon$59
   #2 = Class              #1             // shapeless/ops/coproduct$Drop$$anon$59
   #3 = Utf8               Ljava/lang/Object;Lshapeless/ops/coproduct$Drop<TC;Lshapeless/_0;>;
   #4 = Utf8               java/lang/Object
   #5 = Class              #4             // java/lang/Object
   #6 = Utf8               shapeless/ops/coproduct$Drop
   #7 = Class              #6             // shapeless/ops/coproduct$Drop
   #8 = Utf8               coproduct.scala
   #9 = Utf8               shapeless/ops/coproduct$Drop$
  #10 = Class              #9             // shapeless/ops/coproduct$Drop$
  #11 = Utf8               dropZero
  #12 = Utf8               ()Lshapeless/ops/coproduct$Drop;
  #13 = NameAndType        #11:#12        // dropZero:()Lshapeless/ops/coproduct$Drop;
  #14 = Utf8               shapeless/ops/coproduct
  #15 = Class              #14            // shapeless/ops/coproduct
  #16 = Utf8               Drop
  #17 = Utf8               Drop$
  #18 = Utf8               apply
  #19 = Utf8               (Lshapeless/Coproduct;)Lscala/Some;
  #20 = Utf8               (TC;)Lscala/Some<TC;>;
  #21 = Utf8               c
  #22 = Utf8               scala/Some
  #23 = Class              #22            // scala/Some
  #24 = Utf8               <init>
  #25 = Utf8               (Ljava/lang/Object;)V
  #26 = NameAndType        #24:#25        // "<init>":(Ljava/lang/Object;)V
  #27 = Methodref          #23.#26        // scala/Some."<init>":(Ljava/lang/Object;)V
  #28 = Utf8               this
  #29 = Utf8               Lshapeless/ops/coproduct$Drop$$anon$59;
  #30 = Utf8               Lshapeless/Coproduct;
  #31 = Utf8               (Ljava/lang/Object;)Ljava/lang/Object;
  #32 = Utf8               t
  #33 = Utf8               shapeless/Coproduct
  #34 = Class              #33            // shapeless/Coproduct
  #35 = NameAndType        #18:#19        // apply:(Lshapeless/Coproduct;)Lscala/Some;
  #36 = Methodref          #2.#35         // shapeless/ops/coproduct$Drop$$anon$59.apply:(Lshapeless/Coproduct;)Lscala/Some;
  #37 = Utf8               Ljava/lang/Object;
  #38 = Utf8               ()V
  #39 = NameAndType        #24:#38        // "<init>":()V
  #40 = Methodref          #5.#39         // java/lang/Object."<init>":()V
  #41 = Utf8               Code
  #42 = Utf8               LineNumberTable
  #43 = Utf8               LocalVariableTable
  #44 = Utf8               Signature
  #45 = Utf8               MethodParameters
  #46 = Utf8               InnerClasses
  #47 = Utf8               EnclosingMethod
  #48 = Utf8               SourceFile
  #49 = Utf8               ScalaInlineInfo
  #50 = Utf8               Scala
{
  public scala.Some<C> apply(C);
    descriptor: (Lshapeless/Coproduct;)Lscala/Some;
    flags: (0x0001) ACC_PUBLIC
    Code:
      stack=3, locals=2, args_size=2
         0: new           #23                 // class scala/Some
         3: dup
         4: aload_1
         5: invokespecial #27                 // Method scala/Some."<init>":(Ljava/lang/Object;)V
         8: areturn
      LineNumberTable:
        line 957: 0
      LocalVariableTable:
        Start  Length  Slot  Name   Signature
            0       9     0  this   Lshapeless/ops/coproduct$Drop$$anon$59;
            0       9     1     c   Lshapeless/Coproduct;
    Signature: #20                          // (TC;)Lscala/Some<TC;>;
    MethodParameters:
      Name                           Flags
      c                              final

  public java.lang.Object apply(java.lang.Object);
    descriptor: (Ljava/lang/Object;)Ljava/lang/Object;
    flags: (0x1041) ACC_PUBLIC, ACC_BRIDGE, ACC_SYNTHETIC
    Code:
      stack=2, locals=2, args_size=2
         0: aload_0
         1: aload_1
         2: checkcast     #34                 // class shapeless/Coproduct
         5: invokevirtual #36                 // Method apply:(Lshapeless/Coproduct;)Lscala/Some;
         8: areturn
      LineNumberTable:
        line 955: 0
      LocalVariableTable:
        Start  Length  Slot  Name   Signature
            0       9     0  this   Lshapeless/ops/coproduct$Drop$$anon$59;
            0       9     1     t   Ljava/lang/Object;
    MethodParameters:
      Name                           Flags
      t                              final

  public shapeless.ops.coproduct$Drop$$anon$59();
    descriptor: ()V
    flags: (0x0001) ACC_PUBLIC
    Code:
      stack=1, locals=1, args_size=1
         0: aload_0
         1: invokespecial #40                 // Method java/lang/Object."<init>":()V
         4: return
      LineNumberTable:
        line 955: 0
      LocalVariableTable:
        Start  Length  Slot  Name   Signature
            0       5     0  this   Lshapeless/ops/coproduct$Drop$$anon$59;
}
InnerClasses:
  public static #16= #7 of #15;           // Drop=class shapeless/ops/coproduct$Drop of class shapeless/ops/coproduct
  public static #17= #10 of #15;          // Drop$=class shapeless/ops/coproduct$Drop$ of class shapeless/ops/coproduct
  public final #2;                        // class shapeless/ops/coproduct$Drop$$anon$59
EnclosingMethod: #10.#13                // shapeless.ops.coproduct$Drop$.dropZero
Signature: #3                           // Ljava/lang/Object;Lshapeless/ops/coproduct$Drop<TC;Lshapeless/_0;>;
SourceFile: "coproduct.scala"
  ScalaInlineInfo: length = 0x13 (unknown attribute)
   01 01 00 03 00 18 00 26 01 00 12 00 1F 01 00 12
   00 13 01
  Scala: length = 0x0 (unknown attribute)

