Classfile /Users/mw/Projects/slang-braindump/.jar/jar11/assemble/slang-braindump/assemble/content/shapeless/ops/coproduct$RuntimeInject$$anon$84.class
  Last modified May 29, 2022; size 2337 bytes
  SHA-256 checksum 8d140303b3c185af2fe78eeb3c48fdc27f42b032b29c0c03325ba217b8949ecf
  Compiled from "coproduct.scala"
public final class shapeless.ops.coproduct$RuntimeInject$$anon$84 extends java.lang.Object implements shapeless.ops.coproduct$RuntimeInject<shapeless.$colon$plus$colon<H, shapeless.CNil>>
  minor version: 0
  major version: 52
  flags: (0x0031) ACC_PUBLIC, ACC_FINAL, ACC_SUPER
  this_class: #2                          // shapeless/ops/coproduct$RuntimeInject$$anon$84
  super_class: #5                         // java/lang/Object
  interfaces: 1, fields: 1, methods: 4, attributes: 7
Constant pool:
   #1 = Utf8               shapeless/ops/coproduct$RuntimeInject$$anon$84
   #2 = Class              #1             // shapeless/ops/coproduct$RuntimeInject$$anon$84
   #3 = Utf8               Ljava/lang/Object;Lshapeless/ops/coproduct$RuntimeInject<Lshapeless/$colon$plus$colon<TH;Lshapeless/CNil;>;>;
   #4 = Utf8               java/lang/Object
   #5 = Class              #4             // java/lang/Object
   #6 = Utf8               shapeless/ops/coproduct$RuntimeInject
   #7 = Class              #6             // shapeless/ops/coproduct$RuntimeInject
   #8 = Utf8               coproduct.scala
   #9 = Utf8               shapeless/ops/coproduct$RuntimeInject$
  #10 = Class              #9             // shapeless/ops/coproduct$RuntimeInject$
  #11 = Utf8               baseCaseRuntimeInject
  #12 = Utf8               (Lshapeless/Typeable;)Lshapeless/ops/coproduct$RuntimeInject;
  #13 = NameAndType        #11:#12        // baseCaseRuntimeInject:(Lshapeless/Typeable;)Lshapeless/ops/coproduct$RuntimeInject;
  #14 = Utf8               java/lang/invoke/MethodHandles$Lookup
  #15 = Class              #14            // java/lang/invoke/MethodHandles$Lookup
  #16 = Utf8               java/lang/invoke/MethodHandles
  #17 = Class              #16            // java/lang/invoke/MethodHandles
  #18 = Utf8               Lookup
  #19 = Utf8               shapeless/ops/coproduct
  #20 = Class              #19            // shapeless/ops/coproduct
  #21 = Utf8               RuntimeInject
  #22 = Utf8               RuntimeInject$
  #23 = Utf8               castH$1
  #24 = Utf8               Lshapeless/Typeable;
  #25 = Utf8               apply
  #26 = Utf8               (Ljava/lang/Object;)Lscala/Option;
  #27 = Utf8               (Ljava/lang/Object;)Lscala/Option<Lshapeless/$colon$plus$colon<TH;Lshapeless/CNil;>;>;
  #28 = Utf8               x
  #29 = NameAndType        #23:#24        // castH$1:Lshapeless/Typeable;
  #30 = Fieldref           #2.#29         // shapeless/ops/coproduct$RuntimeInject$$anon$84.castH$1:Lshapeless/Typeable;
  #31 = Utf8               shapeless/Typeable
  #32 = Class              #31            // shapeless/Typeable
  #33 = Utf8               cast
  #34 = NameAndType        #33:#26        // cast:(Ljava/lang/Object;)Lscala/Option;
  #35 = InterfaceMethodref #32.#34        // shapeless/Typeable.cast:(Ljava/lang/Object;)Lscala/Option;
  #36 = Utf8               (Ljava/lang/Object;)Ljava/lang/Object;
  #37 = MethodType         #36            //  (Ljava/lang/Object;)Ljava/lang/Object;
  #38 = Utf8               $anonfun$apply$2
  #39 = Utf8               (Ljava/lang/Object;)Lshapeless/Inl;
  #40 = NameAndType        #38:#39        // $anonfun$apply$2:(Ljava/lang/Object;)Lshapeless/Inl;
  #41 = Methodref          #2.#40         // shapeless/ops/coproduct$RuntimeInject$$anon$84.$anonfun$apply$2:(Ljava/lang/Object;)Lshapeless/Inl;
  #42 = MethodHandle       6:#41          // REF_invokeStatic shapeless/ops/coproduct$RuntimeInject$$anon$84.$anonfun$apply$2:(Ljava/lang/Object;)Lshapeless/Inl;
  #43 = MethodType         #39            //  (Ljava/lang/Object;)Lshapeless/Inl;
  #44 = Integer            5
  #45 = Integer            1
  #46 = Utf8               java/lang/invoke/LambdaMetafactory
  #47 = Class              #46            // java/lang/invoke/LambdaMetafactory
  #48 = Utf8               altMetafactory
  #49 = Utf8               (Ljava/lang/invoke/MethodHandles$Lookup;Ljava/lang/String;Ljava/lang/invoke/MethodType;[Ljava/lang/Object;)Ljava/lang/invoke/CallSite;
  #50 = NameAndType        #48:#49        // altMetafactory:(Ljava/lang/invoke/MethodHandles$Lookup;Ljava/lang/String;Ljava/lang/invoke/MethodType;[Ljava/lang/Object;)Ljava/lang/invoke/CallSite;
  #51 = Methodref          #47.#50        // java/lang/invoke/LambdaMetafactory.altMetafactory:(Ljava/lang/invoke/MethodHandles$Lookup;Ljava/lang/String;Ljava/lang/invoke/MethodType;[Ljava/lang/Object;)Ljava/lang/invoke/CallSite;
  #52 = MethodHandle       6:#51          // REF_invokeStatic java/lang/invoke/LambdaMetafactory.altMetafactory:(Ljava/lang/invoke/MethodHandles$Lookup;Ljava/lang/String;Ljava/lang/invoke/MethodType;[Ljava/lang/Object;)Ljava/lang/invoke/CallSite;
  #53 = Utf8               ()Lscala/Function1;
  #54 = NameAndType        #25:#53        // apply:()Lscala/Function1;
  #55 = InvokeDynamic      #0:#54         // #0:apply:()Lscala/Function1;
  #56 = Utf8               scala/Option
  #57 = Class              #56            // scala/Option
  #58 = Utf8               map
  #59 = Utf8               (Lscala/Function1;)Lscala/Option;
  #60 = NameAndType        #58:#59        // map:(Lscala/Function1;)Lscala/Option;
  #61 = Methodref          #57.#60        // scala/Option.map:(Lscala/Function1;)Lscala/Option;
  #62 = Utf8               this
  #63 = Utf8               Lshapeless/ops/coproduct$RuntimeInject$$anon$84;
  #64 = Utf8               Ljava/lang/Object;
  #65 = Utf8               v
  #66 = Utf8               shapeless/Inl
  #67 = Class              #66            // shapeless/Inl
  #68 = Utf8               <init>
  #69 = Utf8               (Ljava/lang/Object;)V
  #70 = NameAndType        #68:#69        // "<init>":(Ljava/lang/Object;)V
  #71 = Methodref          #67.#70        // shapeless/Inl."<init>":(Ljava/lang/Object;)V
  #72 = Utf8               (Lshapeless/Typeable;)V
  #73 = Utf8               ()V
  #74 = NameAndType        #68:#73        // "<init>":()V
  #75 = Methodref          #5.#74         // java/lang/Object."<init>":()V
  #76 = Utf8               $deserializeLambda$
  #77 = Utf8               (Ljava/lang/invoke/SerializedLambda;)Ljava/lang/Object;
  #78 = Utf8               scala/runtime/LambdaDeserialize
  #79 = Class              #78            // scala/runtime/LambdaDeserialize
  #80 = Utf8               bootstrap
  #81 = Utf8               (Ljava/lang/invoke/MethodHandles$Lookup;Ljava/lang/String;Ljava/lang/invoke/MethodType;[Ljava/lang/invoke/MethodHandle;)Ljava/lang/invoke/CallSite;
  #82 = NameAndType        #80:#81        // bootstrap:(Ljava/lang/invoke/MethodHandles$Lookup;Ljava/lang/String;Ljava/lang/invoke/MethodType;[Ljava/lang/invoke/MethodHandle;)Ljava/lang/invoke/CallSite;
  #83 = Methodref          #79.#82        // scala/runtime/LambdaDeserialize.bootstrap:(Ljava/lang/invoke/MethodHandles$Lookup;Ljava/lang/String;Ljava/lang/invoke/MethodType;[Ljava/lang/invoke/MethodHandle;)Ljava/lang/invoke/CallSite;
  #84 = MethodHandle       6:#83          // REF_invokeStatic scala/runtime/LambdaDeserialize.bootstrap:(Ljava/lang/invoke/MethodHandles$Lookup;Ljava/lang/String;Ljava/lang/invoke/MethodType;[Ljava/lang/invoke/MethodHandle;)Ljava/lang/invoke/CallSite;
  #85 = Utf8               lambdaDeserialize
  #86 = NameAndType        #85:#77        // lambdaDeserialize:(Ljava/lang/invoke/SerializedLambda;)Ljava/lang/Object;
  #87 = InvokeDynamic      #1:#86         // #1:lambdaDeserialize:(Ljava/lang/invoke/SerializedLambda;)Ljava/lang/Object;
  #88 = Utf8               Code
  #89 = Utf8               LineNumberTable
  #90 = Utf8               LocalVariableTable
  #91 = Utf8               Signature
  #92 = Utf8               MethodParameters
  #93 = Utf8               InnerClasses
  #94 = Utf8               EnclosingMethod
  #95 = Utf8               SourceFile
  #96 = Utf8               BootstrapMethods
  #97 = Utf8               ScalaInlineInfo
  #98 = Utf8               Scala
{
  private final shapeless.Typeable castH$1;
    descriptor: Lshapeless/Typeable;
    flags: (0x0012) ACC_PRIVATE, ACC_FINAL

  public scala.Option<shapeless.$colon$plus$colon<H, shapeless.CNil>> apply(java.lang.Object);
    descriptor: (Ljava/lang/Object;)Lscala/Option;
    flags: (0x0001) ACC_PUBLIC
    Code:
      stack=2, locals=2, args_size=2
         0: aload_0
         1: getfield      #30                 // Field castH$1:Lshapeless/Typeable;
         4: aload_1
         5: invokeinterface #35,  2           // InterfaceMethod shapeless/Typeable.cast:(Ljava/lang/Object;)Lscala/Option;
        10: invokedynamic #55,  0             // InvokeDynamic #0:apply:()Lscala/Function1;
        15: invokevirtual #61                 // Method scala/Option.map:(Lscala/Function1;)Lscala/Option;
        18: areturn
      LineNumberTable:
        line 1361: 0
      LocalVariableTable:
        Start  Length  Slot  Name   Signature
            0      19     0  this   Lshapeless/ops/coproduct$RuntimeInject$$anon$84;
            0      19     1     x   Ljava/lang/Object;
    Signature: #27                          // (Ljava/lang/Object;)Lscala/Option<Lshapeless/$colon$plus$colon<TH;Lshapeless/CNil;>;>;
    MethodParameters:
      Name                           Flags
      x                              final

  public static final shapeless.Inl $anonfun$apply$2(java.lang.Object);
    descriptor: (Ljava/lang/Object;)Lshapeless/Inl;
    flags: (0x1019) ACC_PUBLIC, ACC_STATIC, ACC_FINAL, ACC_SYNTHETIC
    Code:
      stack=3, locals=1, args_size=1
         0: new           #67                 // class shapeless/Inl
         3: dup
         4: aload_0
         5: invokespecial #71                 // Method shapeless/Inl."<init>":(Ljava/lang/Object;)V
         8: areturn
      LineNumberTable:
        line 1361: 0
      LocalVariableTable:
        Start  Length  Slot  Name   Signature
            0       9     0     v   Ljava/lang/Object;
    MethodParameters:
      Name                           Flags
      v                              final

  public shapeless.ops.coproduct$RuntimeInject$$anon$84(shapeless.Typeable);
    descriptor: (Lshapeless/Typeable;)V
    flags: (0x0001) ACC_PUBLIC
    Code:
      stack=2, locals=2, args_size=2
         0: aload_0
         1: aload_1
         2: putfield      #30                 // Field castH$1:Lshapeless/Typeable;
         5: aload_0
         6: invokespecial #75                 // Method java/lang/Object."<init>":()V
         9: return
      LineNumberTable:
        line 1358: 0
        line 1359: 5
      LocalVariableTable:
        Start  Length  Slot  Name   Signature
            0      10     0  this   Lshapeless/ops/coproduct$RuntimeInject$$anon$84;
            0      10     1 castH$1   Lshapeless/Typeable;
    MethodParameters:
      Name                           Flags
      castH$1                        final

  private static java.lang.Object $deserializeLambda$(java.lang.invoke.SerializedLambda);
    descriptor: (Ljava/lang/invoke/SerializedLambda;)Ljava/lang/Object;
    flags: (0x100a) ACC_PRIVATE, ACC_STATIC, ACC_SYNTHETIC
    Code:
      stack=1, locals=1, args_size=1
         0: aload_0
         1: invokedynamic #87,  0             // InvokeDynamic #1:lambdaDeserialize:(Ljava/lang/invoke/SerializedLambda;)Ljava/lang/Object;
         6: areturn
}
InnerClasses:
  public static final #18= #15 of #17;    // Lookup=class java/lang/invoke/MethodHandles$Lookup of class java/lang/invoke/MethodHandles
  public static #21= #7 of #20;           // RuntimeInject=class shapeless/ops/coproduct$RuntimeInject of class shapeless/ops/coproduct
  public static #22= #10 of #20;          // RuntimeInject$=class shapeless/ops/coproduct$RuntimeInject$ of class shapeless/ops/coproduct
  public final #2;                        // class shapeless/ops/coproduct$RuntimeInject$$anon$84
EnclosingMethod: #10.#13                // shapeless.ops.coproduct$RuntimeInject$.baseCaseRuntimeInject
Signature: #3                           // Ljava/lang/Object;Lshapeless/ops/coproduct$RuntimeInject<Lshapeless/$colon$plus$colon<TH;Lshapeless/CNil;>;>;
SourceFile: "coproduct.scala"
BootstrapMethods:
  0: #52 REF_invokeStatic java/lang/invoke/LambdaMetafactory.altMetafactory:(Ljava/lang/invoke/MethodHandles$Lookup;Ljava/lang/String;Ljava/lang/invoke/MethodType;[Ljava/lang/Object;)Ljava/lang/invoke/CallSite;
    Method arguments:
      #37 (Ljava/lang/Object;)Ljava/lang/Object;
      #42 REF_invokeStatic shapeless/ops/coproduct$RuntimeInject$$anon$84.$anonfun$apply$2:(Ljava/lang/Object;)Lshapeless/Inl;
      #43 (Ljava/lang/Object;)Lshapeless/Inl;
      #44 5
      #45 1
      #43 (Ljava/lang/Object;)Lshapeless/Inl;
  1: #84 REF_invokeStatic scala/runtime/LambdaDeserialize.bootstrap:(Ljava/lang/invoke/MethodHandles$Lookup;Ljava/lang/String;Ljava/lang/invoke/MethodType;[Ljava/lang/invoke/MethodHandle;)Ljava/lang/invoke/CallSite;
    Method arguments:
      #42 REF_invokeStatic shapeless/ops/coproduct$RuntimeInject$$anon$84.$anonfun$apply$2:(Ljava/lang/Object;)Lshapeless/Inl;
  ScalaInlineInfo: length = 0x13 (unknown attribute)
   01 01 00 03 00 26 00 27 01 00 44 00 48 01 00 19
   00 1A 01
  Scala: length = 0x0 (unknown attribute)

