Classfile /Users/mw/Projects/slang-braindump/.jar/jar11/assemble/slang-braindump/assemble/content/shapeless/ops/coproduct$ExtendRightBy$.class
  Last modified May 29, 2022; size 2333 bytes
  SHA-256 checksum d1c7758bac5d07fbcebe9d98e4ae8852ef9452f27ac52d3c057af3c9501fd0c9
  Compiled from "coproduct.scala"
public class shapeless.ops.coproduct$ExtendRightBy$ implements java.io.Serializable
  minor version: 0
  major version: 52
  flags: (0x0021) ACC_PUBLIC, ACC_SUPER
  this_class: #2                          // shapeless/ops/coproduct$ExtendRightBy$
  super_class: #4                         // java/lang/Object
  interfaces: 1, fields: 1, methods: 6, attributes: 4
Constant pool:
   #1 = Utf8               shapeless/ops/coproduct$ExtendRightBy$
   #2 = Class              #1             // shapeless/ops/coproduct$ExtendRightBy$
   #3 = Utf8               java/lang/Object
   #4 = Class              #3             // java/lang/Object
   #5 = Utf8               java/io/Serializable
   #6 = Class              #5             // java/io/Serializable
   #7 = Utf8               coproduct.scala
   #8 = Utf8               shapeless/ops/coproduct$ExtendRight
   #9 = Class              #8             // shapeless/ops/coproduct$ExtendRight
  #10 = Utf8               shapeless/ops/coproduct
  #11 = Class              #10            // shapeless/ops/coproduct
  #12 = Utf8               ExtendRight
  #13 = Utf8               shapeless/ops/coproduct$ExtendRightBy
  #14 = Class              #13            // shapeless/ops/coproduct$ExtendRightBy
  #15 = Utf8               ExtendRightBy
  #16 = Utf8               ExtendRightBy$
  #17 = Utf8               shapeless/ops/coproduct$ExtendRightBy$$anon$42
  #18 = Class              #17            // shapeless/ops/coproduct$ExtendRightBy$$anon$42
  #19 = Utf8               shapeless/ops/coproduct$ExtendRightBy$$anon$43
  #20 = Class              #19            // shapeless/ops/coproduct$ExtendRightBy$$anon$43
  #21 = Utf8               MODULE$
  #22 = Utf8               Lshapeless/ops/coproduct$ExtendRightBy$;
  #23 = Utf8               <clinit>
  #24 = Utf8               ()V
  #25 = Utf8               <init>
  #26 = NameAndType        #25:#24        // "<init>":()V
  #27 = Methodref          #2.#26         // shapeless/ops/coproduct$ExtendRightBy$."<init>":()V
  #28 = NameAndType        #21:#22        // MODULE$:Lshapeless/ops/coproduct$ExtendRightBy$;
  #29 = Fieldref           #2.#28         // shapeless/ops/coproduct$ExtendRightBy$.MODULE$:Lshapeless/ops/coproduct$ExtendRightBy$;
  #30 = Utf8               apply
  #31 = Utf8               (Lshapeless/ops/coproduct$ExtendRightBy;)Lshapeless/ops/coproduct$ExtendRightBy;
  #32 = Utf8               <L::Lshapeless/Coproduct;R::Lshapeless/Coproduct;>(Lshapeless/ops/coproduct$ExtendRightBy<TL;TR;>;)Lshapeless/ops/coproduct$ExtendRightBy<TL;TR;>;
  #33 = Utf8               extendRightBy
  #34 = Utf8               this
  #35 = Utf8               Lshapeless/ops/coproduct$ExtendRightBy;
  #36 = Utf8               extendRightByCNil
  #37 = Utf8               ()Lshapeless/ops/coproduct$ExtendRightBy;
  #38 = Utf8               <L::Lshapeless/Coproduct;>()Lshapeless/ops/coproduct$ExtendRightBy<TL;Lshapeless/CNil;>;
  #39 = Methodref          #18.#26        // shapeless/ops/coproduct$ExtendRightBy$$anon$42."<init>":()V
  #40 = Utf8               extendRightByCoproduct
  #41 = Utf8               (Lshapeless/ops/coproduct$ExtendRight;Lshapeless/ops/coproduct$ExtendRightBy;)Lshapeless/ops/coproduct$ExtendRightBy;
  #42 = Utf8               <L::Lshapeless/Coproduct;H:Ljava/lang/Object;LH::Lshapeless/Coproduct;T::Lshapeless/Coproduct;>(Lshapeless/ops/coproduct$ExtendRight<TL;TH;>;Lshapeless/ops/coproduct$ExtendRightBy<TLH;TT;>;)Lshapeless/ops/coproduct$ExtendRightBy<TL;Lshapeless/$colon$plus$colon<TH;TT;>;>;
  #43 = Utf8               extendRight
  #44 = Utf8               (Lshapeless/ops/coproduct$ExtendRightBy;Lshapeless/ops/coproduct$ExtendRight;)V
  #45 = NameAndType        #25:#44        // "<init>":(Lshapeless/ops/coproduct$ExtendRightBy;Lshapeless/ops/coproduct$ExtendRight;)V
  #46 = Methodref          #20.#45        // shapeless/ops/coproduct$ExtendRightBy$$anon$43."<init>":(Lshapeless/ops/coproduct$ExtendRightBy;Lshapeless/ops/coproduct$ExtendRight;)V
  #47 = Utf8               Lshapeless/ops/coproduct$ExtendRight;
  #48 = Utf8               writeReplace
  #49 = Utf8               ()Ljava/lang/Object;
  #50 = Utf8               scala/runtime/ModuleSerializationProxy
  #51 = Class              #50            // scala/runtime/ModuleSerializationProxy
  #52 = Utf8               (Ljava/lang/Class;)V
  #53 = NameAndType        #25:#52        // "<init>":(Ljava/lang/Class;)V
  #54 = Methodref          #51.#53        // scala/runtime/ModuleSerializationProxy."<init>":(Ljava/lang/Class;)V
  #55 = Methodref          #4.#26         // java/lang/Object."<init>":()V
  #56 = Utf8               Code
  #57 = Utf8               LineNumberTable
  #58 = Utf8               LocalVariableTable
  #59 = Utf8               Signature
  #60 = Utf8               MethodParameters
  #61 = Utf8               InnerClasses
  #62 = Utf8               SourceFile
  #63 = Utf8               ScalaInlineInfo
  #64 = Utf8               Scala
{
  public static final shapeless.ops.coproduct$ExtendRightBy$ MODULE$;
    descriptor: Lshapeless/ops/coproduct$ExtendRightBy$;
    flags: (0x0019) ACC_PUBLIC, ACC_STATIC, ACC_FINAL

  public static {};
    descriptor: ()V
    flags: (0x0009) ACC_PUBLIC, ACC_STATIC
    Code:
      stack=2, locals=0, args_size=0
         0: new           #2                  // class shapeless/ops/coproduct$ExtendRightBy$
         3: dup
         4: invokespecial #27                 // Method "<init>":()V
         7: putstatic     #29                 // Field MODULE$:Lshapeless/ops/coproduct$ExtendRightBy$;
        10: return
      LineNumberTable:
        line 664: 0

  public <L extends shapeless.Coproduct, R extends shapeless.Coproduct> shapeless.ops.coproduct$ExtendRightBy<L, R> apply(shapeless.ops.coproduct$ExtendRightBy<L, R>);
    descriptor: (Lshapeless/ops/coproduct$ExtendRightBy;)Lshapeless/ops/coproduct$ExtendRightBy;
    flags: (0x0001) ACC_PUBLIC
    Code:
      stack=1, locals=2, args_size=2
         0: aload_1
         1: areturn
      LineNumberTable:
        line 666: 0
      LocalVariableTable:
        Start  Length  Slot  Name   Signature
            0       2     0  this   Lshapeless/ops/coproduct$ExtendRightBy$;
            0       2     1 extendRightBy   Lshapeless/ops/coproduct$ExtendRightBy;
    Signature: #32                          // <L::Lshapeless/Coproduct;R::Lshapeless/Coproduct;>(Lshapeless/ops/coproduct$ExtendRightBy<TL;TR;>;)Lshapeless/ops/coproduct$ExtendRightBy<TL;TR;>;
    MethodParameters:
      Name                           Flags
      extendRightBy                  final

  public <L extends shapeless.Coproduct> shapeless.ops.coproduct$ExtendRightBy<L, shapeless.CNil> extendRightByCNil();
    descriptor: ()Lshapeless/ops/coproduct$ExtendRightBy;
    flags: (0x0001) ACC_PUBLIC
    Code:
      stack=2, locals=1, args_size=1
         0: new           #18                 // class shapeless/ops/coproduct$ExtendRightBy$$anon$42
         3: dup
         4: invokespecial #39                 // Method shapeless/ops/coproduct$ExtendRightBy$$anon$42."<init>":()V
         7: areturn
      LineNumberTable:
        line 670: 0
      LocalVariableTable:
        Start  Length  Slot  Name   Signature
            0       8     0  this   Lshapeless/ops/coproduct$ExtendRightBy$;
    Signature: #38                          // <L::Lshapeless/Coproduct;>()Lshapeless/ops/coproduct$ExtendRightBy<TL;Lshapeless/CNil;>;

  public <L extends shapeless.Coproduct, H extends java.lang.Object, LH extends shapeless.Coproduct, T extends shapeless.Coproduct> shapeless.ops.coproduct$ExtendRightBy<L, shapeless.$colon$plus$colon<H, T>> extendRightByCoproduct(shapeless.ops.coproduct$ExtendRight<L, H>, shapeless.ops.coproduct$ExtendRightBy<LH, T>);
    descriptor: (Lshapeless/ops/coproduct$ExtendRight;Lshapeless/ops/coproduct$ExtendRightBy;)Lshapeless/ops/coproduct$ExtendRightBy;
    flags: (0x0001) ACC_PUBLIC
    Code:
      stack=4, locals=3, args_size=3
         0: new           #20                 // class shapeless/ops/coproduct$ExtendRightBy$$anon$43
         3: dup
         4: aload_2
         5: aload_1
         6: invokespecial #46                 // Method shapeless/ops/coproduct$ExtendRightBy$$anon$43."<init>":(Lshapeless/ops/coproduct$ExtendRightBy;Lshapeless/ops/coproduct$ExtendRight;)V
         9: areturn
      LineNumberTable:
        line 678: 0
      LocalVariableTable:
        Start  Length  Slot  Name   Signature
            0      10     0  this   Lshapeless/ops/coproduct$ExtendRightBy$;
            0      10     1 extendRight   Lshapeless/ops/coproduct$ExtendRight;
            0      10     2 extendRightBy   Lshapeless/ops/coproduct$ExtendRightBy;
    Signature: #42                          // <L::Lshapeless/Coproduct;H:Ljava/lang/Object;LH::Lshapeless/Coproduct;T::Lshapeless/Coproduct;>(Lshapeless/ops/coproduct$ExtendRight<TL;TH;>;Lshapeless/ops/coproduct$ExtendRightBy<TLH;TT;>;)Lshapeless/ops/coproduct$ExtendRightBy<TL;Lshapeless/$colon$plus$colon<TH;TT;>;>;
    MethodParameters:
      Name                           Flags
      extendRight                    final
      extendRightBy                  final

  private java.lang.Object writeReplace();
    descriptor: ()Ljava/lang/Object;
    flags: (0x0002) ACC_PRIVATE
    Code:
      stack=3, locals=1, args_size=1
         0: new           #51                 // class scala/runtime/ModuleSerializationProxy
         3: dup
         4: ldc           #2                  // class shapeless/ops/coproduct$ExtendRightBy$
         6: invokespecial #54                 // Method scala/runtime/ModuleSerializationProxy."<init>":(Ljava/lang/Class;)V
         9: areturn
      LineNumberTable:
        line 664: 0
      LocalVariableTable:
        Start  Length  Slot  Name   Signature
            0      10     0  this   Lshapeless/ops/coproduct$ExtendRightBy$;

  public shapeless.ops.coproduct$ExtendRightBy$();
    descriptor: ()V
    flags: (0x0001) ACC_PUBLIC
    Code:
      stack=1, locals=1, args_size=1
         0: aload_0
         1: invokespecial #55                 // Method java/lang/Object."<init>":()V
         4: return
      LineNumberTable:
        line 691: 0
        line 664: 4
      LocalVariableTable:
        Start  Length  Slot  Name   Signature
            0       5     0  this   Lshapeless/ops/coproduct$ExtendRightBy$;
}
InnerClasses:
  public static #12= #9 of #11;           // ExtendRight=class shapeless/ops/coproduct$ExtendRight of class shapeless/ops/coproduct
  public static #15= #14 of #11;          // ExtendRightBy=class shapeless/ops/coproduct$ExtendRightBy of class shapeless/ops/coproduct
  public static #16= #2 of #11;           // ExtendRightBy$=class shapeless/ops/coproduct$ExtendRightBy$ of class shapeless/ops/coproduct
  public final #18;                       // class shapeless/ops/coproduct$ExtendRightBy$$anon$42
  public final #20;                       // class shapeless/ops/coproduct$ExtendRightBy$$anon$43
SourceFile: "coproduct.scala"
  ScalaInlineInfo: length = 0x1D (unknown attribute)
   01 01 00 05 00 19 00 18 01 00 1E 00 1F 01 00 24
   00 25 01 00 28 00 29 01 00 30 00 31 01
  Scala: length = 0x0 (unknown attribute)

