Classfile /Users/mw/Projects/slang-braindump/.jar/jar11/assemble/slang-braindump/assemble/content/shapeless/ops/fin$FromNat$$anon$2.class
  Last modified May 29, 2022; size 999 bytes
  SHA-256 checksum 779bed208951e996b9a0a5cd24e0c3382de837c50fcaf1a7a5e2ef4993db5367
  Compiled from "fin.scala"
public final class shapeless.ops.fin$FromNat$$anon$2 extends java.lang.Object implements shapeless.ops.fin$FromNat<shapeless.Succ<M>, shapeless.Succ<N>>
  minor version: 0
  major version: 52
  flags: (0x0031) ACC_PUBLIC, ACC_FINAL, ACC_SUPER
  this_class: #2                          // shapeless/ops/fin$FromNat$$anon$2
  super_class: #5                         // java/lang/Object
  interfaces: 1, fields: 0, methods: 3, attributes: 6
Constant pool:
   #1 = Utf8               shapeless/ops/fin$FromNat$$anon$2
   #2 = Class              #1             // shapeless/ops/fin$FromNat$$anon$2
   #3 = Utf8               Ljava/lang/Object;Lshapeless/ops/fin$FromNat<Lshapeless/Succ<TM;>;Lshapeless/Succ<TN;>;>;
   #4 = Utf8               java/lang/Object
   #5 = Class              #4             // java/lang/Object
   #6 = Utf8               shapeless/ops/fin$FromNat
   #7 = Class              #6             // shapeless/ops/fin$FromNat
   #8 = Utf8               fin.scala
   #9 = Utf8               shapeless/ops/fin$FromNat$
  #10 = Class              #9             // shapeless/ops/fin$FromNat$
  #11 = Utf8               finSuccFromNat
  #12 = Utf8               (Lshapeless/ops/fin$FromNat;)Lshapeless/ops/fin$FromNat;
  #13 = NameAndType        #11:#12        // finSuccFromNat:(Lshapeless/ops/fin$FromNat;)Lshapeless/ops/fin$FromNat;
  #14 = Utf8               shapeless/ops/fin
  #15 = Class              #14            // shapeless/ops/fin
  #16 = Utf8               FromNat
  #17 = Utf8               FromNat$
  #18 = Utf8               apply
  #19 = Utf8               ()Lshapeless/FinSucc;
  #20 = Utf8               ()Lshapeless/FinSucc<TN;Lshapeless/Fin;>;
  #21 = Utf8               shapeless/FinSucc
  #22 = Class              #21            // shapeless/FinSucc
  #23 = Utf8               <init>
  #24 = Utf8               ()V
  #25 = NameAndType        #23:#24        // "<init>":()V
  #26 = Methodref          #22.#25        // shapeless/FinSucc."<init>":()V
  #27 = Utf8               this
  #28 = Utf8               Lshapeless/ops/fin$FromNat$$anon$2;
  #29 = Utf8               ()Ljava/lang/Object;
  #30 = NameAndType        #18:#19        // apply:()Lshapeless/FinSucc;
  #31 = Methodref          #2.#30         // shapeless/ops/fin$FromNat$$anon$2.apply:()Lshapeless/FinSucc;
  #32 = Methodref          #5.#25         // java/lang/Object."<init>":()V
  #33 = Utf8               Code
  #34 = Utf8               LineNumberTable
  #35 = Utf8               LocalVariableTable
  #36 = Utf8               Signature
  #37 = Utf8               InnerClasses
  #38 = Utf8               EnclosingMethod
  #39 = Utf8               SourceFile
  #40 = Utf8               ScalaInlineInfo
  #41 = Utf8               Scala
{
  public shapeless.FinSucc<N, shapeless.Fin> apply();
    descriptor: ()Lshapeless/FinSucc;
    flags: (0x0001) ACC_PUBLIC
    Code:
      stack=2, locals=1, args_size=1
         0: new           #22                 // class shapeless/FinSucc
         3: dup
         4: invokespecial #26                 // Method shapeless/FinSucc."<init>":()V
         7: areturn
      LineNumberTable:
        line 44: 0
      LocalVariableTable:
        Start  Length  Slot  Name   Signature
            0       8     0  this   Lshapeless/ops/fin$FromNat$$anon$2;
    Signature: #20                          // ()Lshapeless/FinSucc<TN;Lshapeless/Fin;>;

  public java.lang.Object apply();
    descriptor: ()Ljava/lang/Object;
    flags: (0x1041) ACC_PUBLIC, ACC_BRIDGE, ACC_SYNTHETIC
    Code:
      stack=1, locals=1, args_size=1
         0: aload_0
         1: invokevirtual #31                 // Method apply:()Lshapeless/FinSucc;
         4: areturn
      LineNumberTable:
        line 41: 0
      LocalVariableTable:
        Start  Length  Slot  Name   Signature
            0       5     0  this   Lshapeless/ops/fin$FromNat$$anon$2;

  public shapeless.ops.fin$FromNat$$anon$2();
    descriptor: ()V
    flags: (0x0001) ACC_PUBLIC
    Code:
      stack=1, locals=1, args_size=1
         0: aload_0
         1: invokespecial #32                 // Method java/lang/Object."<init>":()V
         4: return
      LineNumberTable:
        line 41: 0
      LocalVariableTable:
        Start  Length  Slot  Name   Signature
            0       5     0  this   Lshapeless/ops/fin$FromNat$$anon$2;
}
InnerClasses:
  public static #16= #7 of #15;           // FromNat=class shapeless/ops/fin$FromNat of class shapeless/ops/fin
  public static #17= #10 of #15;          // FromNat$=class shapeless/ops/fin$FromNat$ of class shapeless/ops/fin
  public final #2;                        // class shapeless/ops/fin$FromNat$$anon$2
EnclosingMethod: #10.#13                // shapeless.ops.fin$FromNat$.finSuccFromNat
Signature: #3                           // Ljava/lang/Object;Lshapeless/ops/fin$FromNat<Lshapeless/Succ<TM;>;Lshapeless/Succ<TN;>;>;
SourceFile: "fin.scala"
  ScalaInlineInfo: length = 0x13 (unknown attribute)
   01 01 00 03 00 17 00 18 01 00 12 00 1D 01 00 12
   00 13 01
  Scala: length = 0x0 (unknown attribute)

