Classfile /Users/mw/Projects/slang-braindump/.jar/jar11/assemble/slang-braindump/assemble/content/shapeless/ops/hlist$LowPriorityComapped$$anon$7.class
  Last modified May 29, 2022; size 879 bytes
  SHA-256 checksum 84d2596e2bcda25ee325fdd8354b4ab9bdfdaa1987931b00225c3a1a4f8daef0
  Compiled from "hlists.scala"
public final class shapeless.ops.hlist$LowPriorityComapped$$anon$7 extends java.lang.Object implements shapeless.ops.hlist$Comapped<L, java.lang.Object>
  minor version: 0
  major version: 52
  flags: (0x0031) ACC_PUBLIC, ACC_FINAL, ACC_SUPER
  this_class: #2                          // shapeless/ops/hlist$LowPriorityComapped$$anon$7
  super_class: #5                         // java/lang/Object
  interfaces: 1, fields: 0, methods: 1, attributes: 6
Constant pool:
   #1 = Utf8               shapeless/ops/hlist$LowPriorityComapped$$anon$7
   #2 = Class              #1             // shapeless/ops/hlist$LowPriorityComapped$$anon$7
   #3 = Utf8               Ljava/lang/Object;Lshapeless/ops/hlist$Comapped<TL;Ljava/lang/Object;>;
   #4 = Utf8               java/lang/Object
   #5 = Class              #4             // java/lang/Object
   #6 = Utf8               shapeless/ops/hlist$Comapped
   #7 = Class              #6             // shapeless/ops/hlist$Comapped
   #8 = Utf8               hlists.scala
   #9 = Utf8               shapeless/ops/hlist$LowPriorityComapped
  #10 = Class              #9             // shapeless/ops/hlist$LowPriorityComapped
  #11 = Utf8               hlistIdComapped
  #12 = Utf8               ()Lshapeless/ops/hlist$Comapped;
  #13 = NameAndType        #11:#12        // hlistIdComapped:()Lshapeless/ops/hlist$Comapped;
  #14 = Utf8               shapeless/ops/hlist
  #15 = Class              #14            // shapeless/ops/hlist
  #16 = Utf8               Comapped
  #17 = Utf8               LowPriorityComapped
  #18 = Utf8               <init>
  #19 = Utf8               (Lshapeless/ops/hlist$LowPriorityComapped;)V
  #20 = Utf8               $outer
  #21 = Utf8               ()V
  #22 = NameAndType        #18:#21        // "<init>":()V
  #23 = Methodref          #5.#22         // java/lang/Object."<init>":()V
  #24 = Utf8               this
  #25 = Utf8               Lshapeless/ops/hlist$LowPriorityComapped$$anon$7;
  #26 = Utf8               Lshapeless/ops/hlist$LowPriorityComapped;
  #27 = Utf8               Code
  #28 = Utf8               LineNumberTable
  #29 = Utf8               LocalVariableTable
  #30 = Utf8               MethodParameters
  #31 = Utf8               InnerClasses
  #32 = Utf8               EnclosingMethod
  #33 = Utf8               Signature
  #34 = Utf8               SourceFile
  #35 = Utf8               ScalaInlineInfo
  #36 = Utf8               Scala
{
  public shapeless.ops.hlist$LowPriorityComapped$$anon$7(shapeless.ops.hlist$LowPriorityComapped);
    descriptor: (Lshapeless/ops/hlist$LowPriorityComapped;)V
    flags: (0x0001) ACC_PUBLIC
    Code:
      stack=1, locals=2, args_size=2
         0: aload_0
         1: invokespecial #23                 // Method java/lang/Object."<init>":()V
         4: return
      LineNumberTable:
        line 97: 0
      LocalVariableTable:
        Start  Length  Slot  Name   Signature
            0       5     0  this   Lshapeless/ops/hlist$LowPriorityComapped$$anon$7;
            0       5     1 $outer   Lshapeless/ops/hlist$LowPriorityComapped;
    MethodParameters:
      Name                           Flags
      $outer                         final synthetic
}
InnerClasses:
  public static #16= #7 of #15;           // Comapped=class shapeless/ops/hlist$Comapped of class shapeless/ops/hlist
  public static #17= #10 of #15;          // LowPriorityComapped=class shapeless/ops/hlist$LowPriorityComapped of class shapeless/ops/hlist
  public final #2;                        // class shapeless/ops/hlist$LowPriorityComapped$$anon$7
EnclosingMethod: #10.#13                // shapeless.ops.hlist$LowPriorityComapped.hlistIdComapped
Signature: #3                           // Ljava/lang/Object;Lshapeless/ops/hlist$Comapped<TL;Ljava/lang/Object;>;
SourceFile: "hlists.scala"
  ScalaInlineInfo: length = 0x9 (unknown attribute)
   01 01 00 01 00 12 00 13 01
  Scala: length = 0x0 (unknown attribute)

