Classfile /Users/mw/Projects/slang-braindump/.jar/jar11/assemble/slang-braindump/assemble/content/shapeless/ops/hlist$LowPriorityGrouper$$anon$73.class
  Last modified May 29, 2022; size 2305 bytes
  SHA-256 checksum 643628ce143f277cf950f61bd395a2aae5e8cb8724fb05a86f45aa2538861855
  Compiled from "hlists.scala"
public final class shapeless.ops.hlist$LowPriorityGrouper$$anon$73 extends java.lang.Object implements shapeless.ops.hlist$Grouper<L, N, Step>
  minor version: 0
  major version: 52
  flags: (0x0031) ACC_PUBLIC, ACC_FINAL, ACC_SUPER
  this_class: #2                          // shapeless/ops/hlist$LowPriorityGrouper$$anon$73
  super_class: #5                         // java/lang/Object
  interfaces: 1, fields: 4, methods: 3, attributes: 6
Constant pool:
   #1 = Utf8               shapeless/ops/hlist$LowPriorityGrouper$$anon$73
   #2 = Class              #1             // shapeless/ops/hlist$LowPriorityGrouper$$anon$73
   #3 = Utf8               Ljava/lang/Object;Lshapeless/ops/hlist$Grouper<TL;TN;TStep;>;
   #4 = Utf8               java/lang/Object
   #5 = Class              #4             // java/lang/Object
   #6 = Utf8               shapeless/ops/hlist$Grouper
   #7 = Class              #6             // shapeless/ops/hlist$Grouper
   #8 = Utf8               hlists.scala
   #9 = Utf8               shapeless/ops/hlist$LowPriorityGrouper
  #10 = Class              #9             // shapeless/ops/hlist$LowPriorityGrouper
  #11 = Utf8               hlistGrouper
  #12 = Utf8               (Lshapeless/ops/hlist$Length;Lshapeless/ops/nat$Min;Lshapeless/ops/hlist$Take;Lshapeless/ops/hlist$Drop;Lshapeless/ops/hlist$Tupler;Lshapeless/ops/hlist$Grouper;)Lshapeless/ops/hlist$Grouper;
  #13 = NameAndType        #11:#12        // hlistGrouper:(Lshapeless/ops/hlist$Length;Lshapeless/ops/nat$Min;Lshapeless/ops/hlist$Take;Lshapeless/ops/hlist$Drop;Lshapeless/ops/hlist$Tupler;Lshapeless/ops/hlist$Grouper;)Lshapeless/ops/hlist$Grouper;
  #14 = Utf8               shapeless/ops/hlist$Drop
  #15 = Class              #14            // shapeless/ops/hlist$Drop
  #16 = Utf8               shapeless/ops/hlist
  #17 = Class              #16            // shapeless/ops/hlist
  #18 = Utf8               Drop
  #19 = Utf8               Grouper
  #20 = Utf8               LowPriorityGrouper
  #21 = Utf8               shapeless/ops/hlist$Take
  #22 = Class              #21            // shapeless/ops/hlist$Take
  #23 = Utf8               Take
  #24 = Utf8               shapeless/ops/hlist$Tupler
  #25 = Class              #24            // shapeless/ops/hlist$Tupler
  #26 = Utf8               Tupler
  #27 = Utf8               tup$1
  #28 = Utf8               Lshapeless/ops/hlist$Tupler;
  #29 = Utf8               take$1
  #30 = Utf8               Lshapeless/ops/hlist$Take;
  #31 = Utf8               grouper$1
  #32 = Utf8               Lshapeless/ops/hlist$Grouper;
  #33 = Utf8               drop$1
  #34 = Utf8               Lshapeless/ops/hlist$Drop;
  #35 = Utf8               apply
  #36 = Utf8               (Lshapeless/HList;)Lshapeless/$colon$colon;
  #37 = Utf8               (TL;)Lshapeless/$colon$colon<TT;TOutG;>;
  #38 = Utf8               l
  #39 = NameAndType        #27:#28        // tup$1:Lshapeless/ops/hlist$Tupler;
  #40 = Fieldref           #2.#39         // shapeless/ops/hlist$LowPriorityGrouper$$anon$73.tup$1:Lshapeless/ops/hlist$Tupler;
  #41 = NameAndType        #29:#30        // take$1:Lshapeless/ops/hlist$Take;
  #42 = Fieldref           #2.#41         // shapeless/ops/hlist$LowPriorityGrouper$$anon$73.take$1:Lshapeless/ops/hlist$Take;
  #43 = Utf8               (Ljava/lang/Object;)Ljava/lang/Object;
  #44 = NameAndType        #35:#43        // apply:(Ljava/lang/Object;)Ljava/lang/Object;
  #45 = InterfaceMethodref #22.#44        // shapeless/ops/hlist$Take.apply:(Ljava/lang/Object;)Ljava/lang/Object;
  #46 = InterfaceMethodref #25.#44        // shapeless/ops/hlist$Tupler.apply:(Ljava/lang/Object;)Ljava/lang/Object;
  #47 = Utf8               shapeless/HList$
  #48 = Class              #47            // shapeless/HList$
  #49 = Utf8               MODULE$
  #50 = Utf8               Lshapeless/HList$;
  #51 = NameAndType        #49:#50        // MODULE$:Lshapeless/HList$;
  #52 = Fieldref           #48.#51        // shapeless/HList$.MODULE$:Lshapeless/HList$;
  #53 = NameAndType        #31:#32        // grouper$1:Lshapeless/ops/hlist$Grouper;
  #54 = Fieldref           #2.#53         // shapeless/ops/hlist$LowPriorityGrouper$$anon$73.grouper$1:Lshapeless/ops/hlist$Grouper;
  #55 = NameAndType        #33:#34        // drop$1:Lshapeless/ops/hlist$Drop;
  #56 = Fieldref           #2.#55         // shapeless/ops/hlist$LowPriorityGrouper$$anon$73.drop$1:Lshapeless/ops/hlist$Drop;
  #57 = InterfaceMethodref #15.#44        // shapeless/ops/hlist$Drop.apply:(Ljava/lang/Object;)Ljava/lang/Object;
  #58 = InterfaceMethodref #7.#44         // shapeless/ops/hlist$Grouper.apply:(Ljava/lang/Object;)Ljava/lang/Object;
  #59 = Utf8               shapeless/HList
  #60 = Class              #59            // shapeless/HList
  #61 = Utf8               hlistOps
  #62 = Utf8               (Lshapeless/HList;)Lshapeless/syntax/HListOps;
  #63 = NameAndType        #61:#62        // hlistOps:(Lshapeless/HList;)Lshapeless/syntax/HListOps;
  #64 = Methodref          #48.#63        // shapeless/HList$.hlistOps:(Lshapeless/HList;)Lshapeless/syntax/HListOps;
  #65 = Utf8               shapeless/syntax/HListOps
  #66 = Class              #65            // shapeless/syntax/HListOps
  #67 = Utf8               $colon$colon
  #68 = Utf8               (Ljava/lang/Object;)Lshapeless/$colon$colon;
  #69 = NameAndType        #67:#68        // $colon$colon:(Ljava/lang/Object;)Lshapeless/$colon$colon;
  #70 = Methodref          #66.#69        // shapeless/syntax/HListOps.$colon$colon:(Ljava/lang/Object;)Lshapeless/$colon$colon;
  #71 = Utf8               this
  #72 = Utf8               Lshapeless/ops/hlist$LowPriorityGrouper$$anon$73;
  #73 = Utf8               Lshapeless/HList;
  #74 = Utf8               t
  #75 = NameAndType        #35:#36        // apply:(Lshapeless/HList;)Lshapeless/$colon$colon;
  #76 = Methodref          #2.#75         // shapeless/ops/hlist$LowPriorityGrouper$$anon$73.apply:(Lshapeless/HList;)Lshapeless/$colon$colon;
  #77 = Utf8               Ljava/lang/Object;
  #78 = Utf8               <init>
  #79 = Utf8               (Lshapeless/ops/hlist$LowPriorityGrouper;Lshapeless/ops/hlist$Tupler;Lshapeless/ops/hlist$Take;Lshapeless/ops/hlist$Grouper;Lshapeless/ops/hlist$Drop;)V
  #80 = Utf8               $outer
  #81 = Utf8               ()V
  #82 = NameAndType        #78:#81        // "<init>":()V
  #83 = Methodref          #5.#82         // java/lang/Object."<init>":()V
  #84 = Utf8               Lshapeless/ops/hlist$LowPriorityGrouper;
  #85 = Utf8               Code
  #86 = Utf8               LineNumberTable
  #87 = Utf8               LocalVariableTable
  #88 = Utf8               Signature
  #89 = Utf8               MethodParameters
  #90 = Utf8               InnerClasses
  #91 = Utf8               EnclosingMethod
  #92 = Utf8               SourceFile
  #93 = Utf8               ScalaInlineInfo
  #94 = Utf8               Scala
{
  private final shapeless.ops.hlist$Tupler tup$1;
    descriptor: Lshapeless/ops/hlist$Tupler;
    flags: (0x0012) ACC_PRIVATE, ACC_FINAL

  private final shapeless.ops.hlist$Take take$1;
    descriptor: Lshapeless/ops/hlist$Take;
    flags: (0x0012) ACC_PRIVATE, ACC_FINAL

  private final shapeless.ops.hlist$Grouper grouper$1;
    descriptor: Lshapeless/ops/hlist$Grouper;
    flags: (0x0012) ACC_PRIVATE, ACC_FINAL

  private final shapeless.ops.hlist$Drop drop$1;
    descriptor: Lshapeless/ops/hlist$Drop;
    flags: (0x0012) ACC_PRIVATE, ACC_FINAL

  public shapeless.$colon$colon<T, OutG> apply(L);
    descriptor: (Lshapeless/HList;)Lshapeless/$colon$colon;
    flags: (0x0001) ACC_PUBLIC
    Code:
      stack=4, locals=3, args_size=2
         0: aload_0
         1: getfield      #40                 // Field tup$1:Lshapeless/ops/hlist$Tupler;
         4: aload_0
         5: getfield      #42                 // Field take$1:Lshapeless/ops/hlist$Take;
         8: aload_1
         9: invokeinterface #45,  2           // InterfaceMethod shapeless/ops/hlist$Take.apply:(Ljava/lang/Object;)Ljava/lang/Object;
        14: invokeinterface #46,  2           // InterfaceMethod shapeless/ops/hlist$Tupler.apply:(Ljava/lang/Object;)Ljava/lang/Object;
        19: astore_2
        20: getstatic     #52                 // Field shapeless/HList$.MODULE$:Lshapeless/HList$;
        23: aload_0
        24: getfield      #54                 // Field grouper$1:Lshapeless/ops/hlist$Grouper;
        27: aload_0
        28: getfield      #56                 // Field drop$1:Lshapeless/ops/hlist$Drop;
        31: aload_1
        32: invokeinterface #57,  2           // InterfaceMethod shapeless/ops/hlist$Drop.apply:(Ljava/lang/Object;)Ljava/lang/Object;
        37: invokeinterface #58,  2           // InterfaceMethod shapeless/ops/hlist$Grouper.apply:(Ljava/lang/Object;)Ljava/lang/Object;
        42: checkcast     #60                 // class shapeless/HList
        45: invokevirtual #64                 // Method shapeless/HList$.hlistOps:(Lshapeless/HList;)Lshapeless/syntax/HListOps;
        48: aload_2
        49: invokevirtual #70                 // Method shapeless/syntax/HListOps.$colon$colon:(Ljava/lang/Object;)Lshapeless/$colon$colon;
        52: areturn
      LineNumberTable:
        line 1039: 0
      LocalVariableTable:
        Start  Length  Slot  Name   Signature
            0      53     0  this   Lshapeless/ops/hlist$LowPriorityGrouper$$anon$73;
            0      53     1     l   Lshapeless/HList;
    Signature: #37                          // (TL;)Lshapeless/$colon$colon<TT;TOutG;>;
    MethodParameters:
      Name                           Flags
      l                              final

  public java.lang.Object apply(java.lang.Object);
    descriptor: (Ljava/lang/Object;)Ljava/lang/Object;
    flags: (0x1041) ACC_PUBLIC, ACC_BRIDGE, ACC_SYNTHETIC
    Code:
      stack=2, locals=2, args_size=2
         0: aload_0
         1: aload_1
         2: checkcast     #60                 // class shapeless/HList
         5: invokevirtual #76                 // Method apply:(Lshapeless/HList;)Lshapeless/$colon$colon;
         8: areturn
      LineNumberTable:
        line 1036: 0
      LocalVariableTable:
        Start  Length  Slot  Name   Signature
            0       9     0  this   Lshapeless/ops/hlist$LowPriorityGrouper$$anon$73;
            0       9     1     t   Ljava/lang/Object;
    MethodParameters:
      Name                           Flags
      t                              final

  public shapeless.ops.hlist$LowPriorityGrouper$$anon$73(shapeless.ops.hlist$LowPriorityGrouper, shapeless.ops.hlist$Tupler, shapeless.ops.hlist$Take, shapeless.ops.hlist$Grouper, shapeless.ops.hlist$Drop);
    descriptor: (Lshapeless/ops/hlist$LowPriorityGrouper;Lshapeless/ops/hlist$Tupler;Lshapeless/ops/hlist$Take;Lshapeless/ops/hlist$Grouper;Lshapeless/ops/hlist$Drop;)V
    flags: (0x0001) ACC_PUBLIC
    Code:
      stack=2, locals=6, args_size=6
         0: aload_0
         1: aload_2
         2: putfield      #40                 // Field tup$1:Lshapeless/ops/hlist$Tupler;
         5: aload_0
         6: aload_3
         7: putfield      #42                 // Field take$1:Lshapeless/ops/hlist$Take;
        10: aload_0
        11: aload         4
        13: putfield      #54                 // Field grouper$1:Lshapeless/ops/hlist$Grouper;
        16: aload_0
        17: aload         5
        19: putfield      #56                 // Field drop$1:Lshapeless/ops/hlist$Drop;
        22: aload_0
        23: invokespecial #83                 // Method java/lang/Object."<init>":()V
        26: return
      LineNumberTable:
        line 1034: 0
        line 1032: 5
        line 1035: 10
        line 1033: 16
        line 1036: 22
      LocalVariableTable:
        Start  Length  Slot  Name   Signature
            0      27     0  this   Lshapeless/ops/hlist$LowPriorityGrouper$$anon$73;
            0      27     1 $outer   Lshapeless/ops/hlist$LowPriorityGrouper;
            0      27     2 tup$1   Lshapeless/ops/hlist$Tupler;
            0      27     3 take$1   Lshapeless/ops/hlist$Take;
            0      27     4 grouper$1   Lshapeless/ops/hlist$Grouper;
            0      27     5 drop$1   Lshapeless/ops/hlist$Drop;
    MethodParameters:
      Name                           Flags
      $outer                         final synthetic
      tup$1                          final
      take$1                         final
      grouper$1                      final
      drop$1                         final
}
InnerClasses:
  public static #18= #15 of #17;          // Drop=class shapeless/ops/hlist$Drop of class shapeless/ops/hlist
  public static #19= #7 of #17;           // Grouper=class shapeless/ops/hlist$Grouper of class shapeless/ops/hlist
  public static #20= #10 of #17;          // LowPriorityGrouper=class shapeless/ops/hlist$LowPriorityGrouper of class shapeless/ops/hlist
  public final #2;                        // class shapeless/ops/hlist$LowPriorityGrouper$$anon$73
  public static #23= #22 of #17;          // Take=class shapeless/ops/hlist$Take of class shapeless/ops/hlist
  public static #26= #25 of #17;          // Tupler=class shapeless/ops/hlist$Tupler of class shapeless/ops/hlist
EnclosingMethod: #10.#13                // shapeless.ops.hlist$LowPriorityGrouper.hlistGrouper
Signature: #3                           // Ljava/lang/Object;Lshapeless/ops/hlist$Grouper<TL;TN;TStep;>;
SourceFile: "hlists.scala"
  ScalaInlineInfo: length = 0x13 (unknown attribute)
   01 01 00 03 00 4E 00 4F 01 00 23 00 2B 01 00 23
   00 24 01
  Scala: length = 0x0 (unknown attribute)

