Classfile /Users/mw/Projects/slang-braindump/.jar/jar11/assemble/slang-braindump/assemble/content/shapeless/ops/hlist$PaddedGrouper$$anon$77.class
  Last modified May 29, 2022; size 1547 bytes
  SHA-256 checksum af14b1fdeea1bf8eccab0f73fe5da2e09fd69cb36ff23019f98f1190a969b680
  Compiled from "hlists.scala"
public final class shapeless.ops.hlist$PaddedGrouper$$anon$77 extends java.lang.Object implements shapeless.ops.hlist$PaddedGrouper<L, N, Step, Pad>
  minor version: 0
  major version: 52
  flags: (0x0031) ACC_PUBLIC, ACC_FINAL, ACC_SUPER
  this_class: #2                          // shapeless/ops/hlist$PaddedGrouper$$anon$77
  super_class: #5                         // java/lang/Object
  interfaces: 1, fields: 1, methods: 3, attributes: 6
Constant pool:
   #1 = Utf8               shapeless/ops/hlist$PaddedGrouper$$anon$77
   #2 = Class              #1             // shapeless/ops/hlist$PaddedGrouper$$anon$77
   #3 = Utf8               Ljava/lang/Object;Lshapeless/ops/hlist$PaddedGrouper<TL;TN;TStep;TPad;>;
   #4 = Utf8               java/lang/Object
   #5 = Class              #4             // java/lang/Object
   #6 = Utf8               shapeless/ops/hlist$PaddedGrouper
   #7 = Class              #6             // shapeless/ops/hlist$PaddedGrouper
   #8 = Utf8               hlists.scala
   #9 = Utf8               shapeless/ops/hlist$PaddedGrouper$
  #10 = Class              #9             // shapeless/ops/hlist$PaddedGrouper$
  #11 = Utf8               defaultPaddedGrouper
  #12 = Utf8               (Lshapeless/ops/hlist$Length;Lshapeless/ops/nat$Mod;Lscala/$eq$colon$eq;Lshapeless/ops/hlist$Grouper;)Lshapeless/ops/hlist$PaddedGrouper;
  #13 = NameAndType        #11:#12        // defaultPaddedGrouper:(Lshapeless/ops/hlist$Length;Lshapeless/ops/nat$Mod;Lscala/$eq$colon$eq;Lshapeless/ops/hlist$Grouper;)Lshapeless/ops/hlist$PaddedGrouper;
  #14 = Utf8               shapeless/ops/hlist$Grouper
  #15 = Class              #14            // shapeless/ops/hlist$Grouper
  #16 = Utf8               shapeless/ops/hlist
  #17 = Class              #16            // shapeless/ops/hlist
  #18 = Utf8               Grouper
  #19 = Utf8               PaddedGrouper
  #20 = Utf8               PaddedGrouper$
  #21 = Utf8               grouper$3
  #22 = Utf8               Lshapeless/ops/hlist$Grouper;
  #23 = Utf8               apply
  #24 = Utf8               (Lshapeless/HList;Lshapeless/HList;)Lshapeless/HList;
  #25 = Utf8               (TL;TPad;)TOut0;
  #26 = Utf8               l
  #27 = Utf8               pad
  #28 = NameAndType        #21:#22        // grouper$3:Lshapeless/ops/hlist$Grouper;
  #29 = Fieldref           #2.#28         // shapeless/ops/hlist$PaddedGrouper$$anon$77.grouper$3:Lshapeless/ops/hlist$Grouper;
  #30 = Utf8               (Ljava/lang/Object;)Ljava/lang/Object;
  #31 = NameAndType        #23:#30        // apply:(Ljava/lang/Object;)Ljava/lang/Object;
  #32 = InterfaceMethodref #15.#31        // shapeless/ops/hlist$Grouper.apply:(Ljava/lang/Object;)Ljava/lang/Object;
  #33 = Utf8               shapeless/HList
  #34 = Class              #33            // shapeless/HList
  #35 = Utf8               this
  #36 = Utf8               Lshapeless/ops/hlist$PaddedGrouper$$anon$77;
  #37 = Utf8               Lshapeless/HList;
  #38 = Utf8               (Ljava/lang/Object;Ljava/lang/Object;)Ljava/lang/Object;
  #39 = Utf8               t
  #40 = Utf8               u
  #41 = NameAndType        #23:#24        // apply:(Lshapeless/HList;Lshapeless/HList;)Lshapeless/HList;
  #42 = Methodref          #2.#41         // shapeless/ops/hlist$PaddedGrouper$$anon$77.apply:(Lshapeless/HList;Lshapeless/HList;)Lshapeless/HList;
  #43 = Utf8               Ljava/lang/Object;
  #44 = Utf8               <init>
  #45 = Utf8               (Lshapeless/ops/hlist$Grouper;)V
  #46 = Utf8               ()V
  #47 = NameAndType        #44:#46        // "<init>":()V
  #48 = Methodref          #5.#47         // java/lang/Object."<init>":()V
  #49 = Utf8               Code
  #50 = Utf8               LineNumberTable
  #51 = Utf8               LocalVariableTable
  #52 = Utf8               Signature
  #53 = Utf8               MethodParameters
  #54 = Utf8               InnerClasses
  #55 = Utf8               EnclosingMethod
  #56 = Utf8               SourceFile
  #57 = Utf8               ScalaInlineInfo
  #58 = Utf8               Scala
{
  private final shapeless.ops.hlist$Grouper grouper$3;
    descriptor: Lshapeless/ops/hlist$Grouper;
    flags: (0x0012) ACC_PRIVATE, ACC_FINAL

  public Out0 apply(L, Pad);
    descriptor: (Lshapeless/HList;Lshapeless/HList;)Lshapeless/HList;
    flags: (0x0001) ACC_PUBLIC
    Code:
      stack=2, locals=3, args_size=3
         0: aload_0
         1: getfield      #29                 // Field grouper$3:Lshapeless/ops/hlist$Grouper;
         4: aload_1
         5: invokeinterface #32,  2           // InterfaceMethod shapeless/ops/hlist$Grouper.apply:(Ljava/lang/Object;)Ljava/lang/Object;
        10: checkcast     #34                 // class shapeless/HList
        13: areturn
      LineNumberTable:
        line 1132: 0
      LocalVariableTable:
        Start  Length  Slot  Name   Signature
            0      14     0  this   Lshapeless/ops/hlist$PaddedGrouper$$anon$77;
            0      14     1     l   Lshapeless/HList;
            0      14     2   pad   Lshapeless/HList;
    Signature: #25                          // (TL;TPad;)TOut0;
    MethodParameters:
      Name                           Flags
      l                              final
      pad                            final

  public java.lang.Object apply(java.lang.Object, java.lang.Object);
    descriptor: (Ljava/lang/Object;Ljava/lang/Object;)Ljava/lang/Object;
    flags: (0x1041) ACC_PUBLIC, ACC_BRIDGE, ACC_SYNTHETIC
    Code:
      stack=3, locals=3, args_size=3
         0: aload_0
         1: aload_1
         2: checkcast     #34                 // class shapeless/HList
         5: aload_2
         6: checkcast     #34                 // class shapeless/HList
         9: invokevirtual #42                 // Method apply:(Lshapeless/HList;Lshapeless/HList;)Lshapeless/HList;
        12: areturn
      LineNumberTable:
        line 1128: 0
      LocalVariableTable:
        Start  Length  Slot  Name   Signature
            0      13     0  this   Lshapeless/ops/hlist$PaddedGrouper$$anon$77;
            0      13     1     t   Ljava/lang/Object;
            0      13     2     u   Ljava/lang/Object;
    MethodParameters:
      Name                           Flags
      t                              final
      u                              final

  public shapeless.ops.hlist$PaddedGrouper$$anon$77(shapeless.ops.hlist$Grouper);
    descriptor: (Lshapeless/ops/hlist$Grouper;)V
    flags: (0x0001) ACC_PUBLIC
    Code:
      stack=2, locals=2, args_size=2
         0: aload_0
         1: aload_1
         2: putfield      #29                 // Field grouper$3:Lshapeless/ops/hlist$Grouper;
         5: aload_0
         6: invokespecial #48                 // Method java/lang/Object."<init>":()V
         9: return
      LineNumberTable:
        line 1127: 0
        line 1128: 5
      LocalVariableTable:
        Start  Length  Slot  Name   Signature
            0      10     0  this   Lshapeless/ops/hlist$PaddedGrouper$$anon$77;
            0      10     1 grouper$3   Lshapeless/ops/hlist$Grouper;
    MethodParameters:
      Name                           Flags
      grouper$3                      final
}
InnerClasses:
  public static #18= #15 of #17;          // Grouper=class shapeless/ops/hlist$Grouper of class shapeless/ops/hlist
  public static #19= #7 of #17;           // PaddedGrouper=class shapeless/ops/hlist$PaddedGrouper of class shapeless/ops/hlist
  public static #20= #10 of #17;          // PaddedGrouper$=class shapeless/ops/hlist$PaddedGrouper$ of class shapeless/ops/hlist
  public final #2;                        // class shapeless/ops/hlist$PaddedGrouper$$anon$77
EnclosingMethod: #10.#13                // shapeless.ops.hlist$PaddedGrouper$.defaultPaddedGrouper
Signature: #3                           // Ljava/lang/Object;Lshapeless/ops/hlist$PaddedGrouper<TL;TN;TStep;TPad;>;
SourceFile: "hlists.scala"
  ScalaInlineInfo: length = 0x13 (unknown attribute)
   01 01 00 03 00 2C 00 2D 01 00 17 00 26 01 00 17
   00 18 01
  Scala: length = 0x0 (unknown attribute)

