Classfile /Users/mw/Projects/slang-braindump/.jar/jar11/assemble/slang-braindump/assemble/content/shapeless/ops/hlist$Transposer$$anon$147.class
  Last modified May 29, 2022; size 1818 bytes
  SHA-256 checksum 5df7b40d2455232bec612f45a87fc197bde47fc26c94a669fe56253603008660
  Compiled from "hlists.scala"
public final class shapeless.ops.hlist$Transposer$$anon$147 extends java.lang.Object implements shapeless.ops.hlist$Transposer<shapeless.$colon$colon<H, shapeless.HNil>>
  minor version: 0
  major version: 52
  flags: (0x0031) ACC_PUBLIC, ACC_FINAL, ACC_SUPER
  this_class: #2                          // shapeless/ops/hlist$Transposer$$anon$147
  super_class: #5                         // java/lang/Object
  interfaces: 1, fields: 2, methods: 3, attributes: 6
Constant pool:
   #1 = Utf8               shapeless/ops/hlist$Transposer$$anon$147
   #2 = Class              #1             // shapeless/ops/hlist$Transposer$$anon$147
   #3 = Utf8               Ljava/lang/Object;Lshapeless/ops/hlist$Transposer<Lshapeless/$colon$colon<TH;Lshapeless/HNil;>;>;
   #4 = Utf8               java/lang/Object
   #5 = Class              #4             // java/lang/Object
   #6 = Utf8               shapeless/ops/hlist$Transposer
   #7 = Class              #6             // shapeless/ops/hlist$Transposer
   #8 = Utf8               hlists.scala
   #9 = Utf8               shapeless/ops/hlist$Transposer$
  #10 = Class              #9             // shapeless/ops/hlist$Transposer$
  #11 = Utf8               hlistTransposer1
  #12 = Utf8               (Lshapeless/ops/hlist$ConstMapper;Lshapeless/ops/hlist$ZipOne;)Lshapeless/ops/hlist$Transposer;
  #13 = NameAndType        #11:#12        // hlistTransposer1:(Lshapeless/ops/hlist$ConstMapper;Lshapeless/ops/hlist$ZipOne;)Lshapeless/ops/hlist$Transposer;
  #14 = Utf8               shapeless/ops/hlist$ConstMapper
  #15 = Class              #14            // shapeless/ops/hlist$ConstMapper
  #16 = Utf8               shapeless/ops/hlist
  #17 = Class              #16            // shapeless/ops/hlist
  #18 = Utf8               ConstMapper
  #19 = Utf8               Transposer
  #20 = Utf8               Transposer$
  #21 = Utf8               shapeless/ops/hlist$ZipOne
  #22 = Class              #21            // shapeless/ops/hlist$ZipOne
  #23 = Utf8               ZipOne
  #24 = Utf8               zo$1
  #25 = Utf8               Lshapeless/ops/hlist$ZipOne;
  #26 = Utf8               mc$1
  #27 = Utf8               Lshapeless/ops/hlist$ConstMapper;
  #28 = Utf8               apply
  #29 = Utf8               (Lshapeless/$colon$colon;)Lshapeless/HList;
  #30 = Utf8               (Lshapeless/$colon$colon<TH;Lshapeless/HNil;>;)TOut0;
  #31 = Utf8               l
  #32 = NameAndType        #24:#25        // zo$1:Lshapeless/ops/hlist$ZipOne;
  #33 = Fieldref           #2.#32         // shapeless/ops/hlist$Transposer$$anon$147.zo$1:Lshapeless/ops/hlist$ZipOne;
  #34 = Utf8               shapeless/$colon$colon
  #35 = Class              #34            // shapeless/$colon$colon
  #36 = Utf8               head
  #37 = Utf8               ()Ljava/lang/Object;
  #38 = NameAndType        #36:#37        // head:()Ljava/lang/Object;
  #39 = Methodref          #35.#38        // shapeless/$colon$colon.head:()Ljava/lang/Object;
  #40 = NameAndType        #26:#27        // mc$1:Lshapeless/ops/hlist$ConstMapper;
  #41 = Fieldref           #2.#40         // shapeless/ops/hlist$Transposer$$anon$147.mc$1:Lshapeless/ops/hlist$ConstMapper;
  #42 = Utf8               shapeless/HNil$
  #43 = Class              #42            // shapeless/HNil$
  #44 = Utf8               MODULE$
  #45 = Utf8               Lshapeless/HNil$;
  #46 = NameAndType        #44:#45        // MODULE$:Lshapeless/HNil$;
  #47 = Fieldref           #43.#46        // shapeless/HNil$.MODULE$:Lshapeless/HNil$;
  #48 = Utf8               (Ljava/lang/Object;Ljava/lang/Object;)Ljava/lang/Object;
  #49 = NameAndType        #28:#48        // apply:(Ljava/lang/Object;Ljava/lang/Object;)Ljava/lang/Object;
  #50 = InterfaceMethodref #15.#49        // shapeless/ops/hlist$ConstMapper.apply:(Ljava/lang/Object;Ljava/lang/Object;)Ljava/lang/Object;
  #51 = InterfaceMethodref #22.#49        // shapeless/ops/hlist$ZipOne.apply:(Ljava/lang/Object;Ljava/lang/Object;)Ljava/lang/Object;
  #52 = Utf8               shapeless/HList
  #53 = Class              #52            // shapeless/HList
  #54 = Utf8               this
  #55 = Utf8               Lshapeless/ops/hlist$Transposer$$anon$147;
  #56 = Utf8               Lshapeless/$colon$colon;
  #57 = Utf8               (Ljava/lang/Object;)Ljava/lang/Object;
  #58 = Utf8               t
  #59 = NameAndType        #28:#29        // apply:(Lshapeless/$colon$colon;)Lshapeless/HList;
  #60 = Methodref          #2.#59         // shapeless/ops/hlist$Transposer$$anon$147.apply:(Lshapeless/$colon$colon;)Lshapeless/HList;
  #61 = Utf8               Ljava/lang/Object;
  #62 = Utf8               <init>
  #63 = Utf8               (Lshapeless/ops/hlist$ZipOne;Lshapeless/ops/hlist$ConstMapper;)V
  #64 = Utf8               ()V
  #65 = NameAndType        #62:#64        // "<init>":()V
  #66 = Methodref          #5.#65         // java/lang/Object."<init>":()V
  #67 = Utf8               Code
  #68 = Utf8               LineNumberTable
  #69 = Utf8               LocalVariableTable
  #70 = Utf8               Signature
  #71 = Utf8               MethodParameters
  #72 = Utf8               InnerClasses
  #73 = Utf8               EnclosingMethod
  #74 = Utf8               SourceFile
  #75 = Utf8               ScalaInlineInfo
  #76 = Utf8               Scala
{
  private final shapeless.ops.hlist$ZipOne zo$1;
    descriptor: Lshapeless/ops/hlist$ZipOne;
    flags: (0x0012) ACC_PRIVATE, ACC_FINAL

  private final shapeless.ops.hlist$ConstMapper mc$1;
    descriptor: Lshapeless/ops/hlist$ConstMapper;
    flags: (0x0012) ACC_PRIVATE, ACC_FINAL

  public Out0 apply(shapeless.$colon$colon<H, shapeless.HNil>);
    descriptor: (Lshapeless/$colon$colon;)Lshapeless/HList;
    flags: (0x0001) ACC_PUBLIC
    Code:
      stack=5, locals=2, args_size=2
         0: aload_0
         1: getfield      #33                 // Field zo$1:Lshapeless/ops/hlist$ZipOne;
         4: aload_1
         5: invokevirtual #39                 // Method shapeless/$colon$colon.head:()Ljava/lang/Object;
         8: aload_0
         9: getfield      #41                 // Field mc$1:Lshapeless/ops/hlist$ConstMapper;
        12: getstatic     #47                 // Field shapeless/HNil$.MODULE$:Lshapeless/HNil$;
        15: aload_1
        16: invokevirtual #39                 // Method shapeless/$colon$colon.head:()Ljava/lang/Object;
        19: invokeinterface #50,  3           // InterfaceMethod shapeless/ops/hlist$ConstMapper.apply:(Ljava/lang/Object;Ljava/lang/Object;)Ljava/lang/Object;
        24: invokeinterface #51,  3           // InterfaceMethod shapeless/ops/hlist$ZipOne.apply:(Ljava/lang/Object;Ljava/lang/Object;)Ljava/lang/Object;
        29: checkcast     #53                 // class shapeless/HList
        32: areturn
      LineNumberTable:
        line 2192: 0
      LocalVariableTable:
        Start  Length  Slot  Name   Signature
            0      33     0  this   Lshapeless/ops/hlist$Transposer$$anon$147;
            0      33     1     l   Lshapeless/$colon$colon;
    Signature: #30                          // (Lshapeless/$colon$colon<TH;Lshapeless/HNil;>;)TOut0;
    MethodParameters:
      Name                           Flags
      l                              final

  public java.lang.Object apply(java.lang.Object);
    descriptor: (Ljava/lang/Object;)Ljava/lang/Object;
    flags: (0x1041) ACC_PUBLIC, ACC_BRIDGE, ACC_SYNTHETIC
    Code:
      stack=2, locals=2, args_size=2
         0: aload_0
         1: aload_1
         2: checkcast     #35                 // class shapeless/$colon$colon
         5: invokevirtual #60                 // Method apply:(Lshapeless/$colon$colon;)Lshapeless/HList;
         8: areturn
      LineNumberTable:
        line 2190: 0
      LocalVariableTable:
        Start  Length  Slot  Name   Signature
            0       9     0  this   Lshapeless/ops/hlist$Transposer$$anon$147;
            0       9     1     t   Ljava/lang/Object;
    MethodParameters:
      Name                           Flags
      t                              final

  public shapeless.ops.hlist$Transposer$$anon$147(shapeless.ops.hlist$ZipOne, shapeless.ops.hlist$ConstMapper);
    descriptor: (Lshapeless/ops/hlist$ZipOne;Lshapeless/ops/hlist$ConstMapper;)V
    flags: (0x0001) ACC_PUBLIC
    Code:
      stack=2, locals=3, args_size=3
         0: aload_0
         1: aload_1
         2: putfield      #33                 // Field zo$1:Lshapeless/ops/hlist$ZipOne;
         5: aload_0
         6: aload_2
         7: putfield      #41                 // Field mc$1:Lshapeless/ops/hlist$ConstMapper;
        10: aload_0
        11: invokespecial #66                 // Method java/lang/Object."<init>":()V
        14: return
      LineNumberTable:
        line 2189: 0
        line 2190: 10
      LocalVariableTable:
        Start  Length  Slot  Name   Signature
            0      15     0  this   Lshapeless/ops/hlist$Transposer$$anon$147;
            0      15     1  zo$1   Lshapeless/ops/hlist$ZipOne;
            0      15     2  mc$1   Lshapeless/ops/hlist$ConstMapper;
    MethodParameters:
      Name                           Flags
      zo$1                           final
      mc$1                           final
}
InnerClasses:
  public static #18= #15 of #17;          // ConstMapper=class shapeless/ops/hlist$ConstMapper of class shapeless/ops/hlist
  public static #19= #7 of #17;           // Transposer=class shapeless/ops/hlist$Transposer of class shapeless/ops/hlist
  public static #20= #10 of #17;          // Transposer$=class shapeless/ops/hlist$Transposer$ of class shapeless/ops/hlist
  public final #2;                        // class shapeless/ops/hlist$Transposer$$anon$147
  public static #23= #22 of #17;          // ZipOne=class shapeless/ops/hlist$ZipOne of class shapeless/ops/hlist
EnclosingMethod: #10.#13                // shapeless.ops.hlist$Transposer$.hlistTransposer1
Signature: #3                           // Ljava/lang/Object;Lshapeless/ops/hlist$Transposer<Lshapeless/$colon$colon<TH;Lshapeless/HNil;>;>;
SourceFile: "hlists.scala"
  ScalaInlineInfo: length = 0x13 (unknown attribute)
   01 01 00 03 00 3E 00 3F 01 00 1C 00 39 01 00 1C
   00 1D 01
  Scala: length = 0x0 (unknown attribute)

