Classfile /Users/mw/Projects/slang-braindump/.jar/jar11/assemble/slang-braindump/assemble/content/shapeless/ops/hlist$Collect$.class
  Last modified May 29, 2022; size 2721 bytes
  SHA-256 checksum 5af8393cd437eb350cff05294f0d31854b64c994f87625723e782dfe104f8dc0
  Compiled from "hlists.scala"
public class shapeless.ops.hlist$Collect$ implements shapeless.ops.hlist$LowPriorityCollect,java.io.Serializable
  minor version: 0
  major version: 52
  flags: (0x0021) ACC_PUBLIC, ACC_SUPER
  this_class: #2                          // shapeless/ops/hlist$Collect$
  super_class: #4                         // java/lang/Object
  interfaces: 2, fields: 1, methods: 7, attributes: 4
Constant pool:
   #1 = Utf8               shapeless/ops/hlist$Collect$
   #2 = Class              #1             // shapeless/ops/hlist$Collect$
   #3 = Utf8               java/lang/Object
   #4 = Class              #3             // java/lang/Object
   #5 = Utf8               shapeless/ops/hlist$LowPriorityCollect
   #6 = Class              #5             // shapeless/ops/hlist$LowPriorityCollect
   #7 = Utf8               java/io/Serializable
   #8 = Class              #7             // java/io/Serializable
   #9 = Utf8               hlists.scala
  #10 = Utf8               shapeless/PolyDefns$Case
  #11 = Class              #10            // shapeless/PolyDefns$Case
  #12 = Utf8               shapeless/PolyDefns
  #13 = Class              #12            // shapeless/PolyDefns
  #14 = Utf8               Case
  #15 = Utf8               shapeless/ops/hlist$Collect
  #16 = Class              #15            // shapeless/ops/hlist$Collect
  #17 = Utf8               shapeless/ops/hlist
  #18 = Class              #17            // shapeless/ops/hlist
  #19 = Utf8               Collect
  #20 = Utf8               Collect$
  #21 = Utf8               shapeless/ops/hlist$Collect$$anon$162
  #22 = Class              #21            // shapeless/ops/hlist$Collect$$anon$162
  #23 = Utf8               shapeless/ops/hlist$Collect$$anon$163
  #24 = Class              #23            // shapeless/ops/hlist$Collect$$anon$163
  #25 = Utf8               LowPriorityCollect
  #26 = Utf8               MODULE$
  #27 = Utf8               Lshapeless/ops/hlist$Collect$;
  #28 = Utf8               <clinit>
  #29 = Utf8               ()V
  #30 = Utf8               <init>
  #31 = NameAndType        #30:#29        // "<init>":()V
  #32 = Methodref          #2.#31         // shapeless/ops/hlist$Collect$."<init>":()V
  #33 = NameAndType        #26:#27        // MODULE$:Lshapeless/ops/hlist$Collect$;
  #34 = Fieldref           #2.#33         // shapeless/ops/hlist$Collect$.MODULE$:Lshapeless/ops/hlist$Collect$;
  #35 = Utf8               $init$
  #36 = Utf8               (Lshapeless/ops/hlist$LowPriorityCollect;)V
  #37 = NameAndType        #35:#36        // $init$:(Lshapeless/ops/hlist$LowPriorityCollect;)V
  #38 = InterfaceMethodref #6.#37         // shapeless/ops/hlist$LowPriorityCollect.$init$:(Lshapeless/ops/hlist$LowPriorityCollect;)V
  #39 = Utf8               hlistNoPolyCase
  #40 = Utf8               (Lshapeless/ops/hlist$Collect;)Lshapeless/ops/hlist$Collect;
  #41 = Utf8               <LH:Ljava/lang/Object;LT::Lshapeless/HList;P::Lshapeless/Poly;CollectOut::Lshapeless/HList;>(Lshapeless/ops/hlist$Collect<TLT;TP;>;)Lshapeless/ops/hlist$Collect<Lshapeless/$colon$colon<TLH;TLT;>;TP;>;
  #42 = Utf8               collect
  #43 = Utf8               hlistNoPolyCase$
  #44 = Utf8               (Lshapeless/ops/hlist$LowPriorityCollect;Lshapeless/ops/hlist$Collect;)Lshapeless/ops/hlist$Collect;
  #45 = NameAndType        #43:#44        // hlistNoPolyCase$:(Lshapeless/ops/hlist$LowPriorityCollect;Lshapeless/ops/hlist$Collect;)Lshapeless/ops/hlist$Collect;
  #46 = InterfaceMethodref #6.#45         // shapeless/ops/hlist$LowPriorityCollect.hlistNoPolyCase$:(Lshapeless/ops/hlist$LowPriorityCollect;Lshapeless/ops/hlist$Collect;)Lshapeless/ops/hlist$Collect;
  #47 = Utf8               this
  #48 = Utf8               Lshapeless/ops/hlist$Collect;
  #49 = Utf8               apply
  #50 = Utf8               <L::Lshapeless/HList;P::Lshapeless/Poly;>(Lshapeless/ops/hlist$Collect<TL;TP;>;)Lshapeless/ops/hlist$Collect<TL;TP;>;
  #51 = Utf8               hnilCollect
  #52 = Utf8               ()Lshapeless/ops/hlist$Collect;
  #53 = Utf8               <P::Lshapeless/Poly;>()Lshapeless/ops/hlist$Collect<Lshapeless/HNil;TP;>;
  #54 = Methodref          #22.#31        // shapeless/ops/hlist$Collect$$anon$162."<init>":()V
  #55 = Utf8               hlistCollect
  #56 = Utf8               (Lshapeless/ops/hlist$Collect;Lshapeless/PolyDefns$Case;)Lshapeless/ops/hlist$Collect;
  #57 = Utf8               <LH:Ljava/lang/Object;LT::Lshapeless/HList;P::Lshapeless/Poly;CollectOut::Lshapeless/HList;ClrResult:Ljava/lang/Object;>(Lshapeless/ops/hlist$Collect<TLT;TP;>;Lshapeless/PolyDefns$Case<TP;Lshapeless/$colon$colon<TLH;Lshapeless/HNil;>;>;)Lshapeless/ops/hlist$Collect<Lshapeless/$colon$colon<TLH;TLT;>;TP;>;
  #58 = Utf8               clr
  #59 = Utf8               (Lshapeless/PolyDefns$Case;Lshapeless/ops/hlist$Collect;)V
  #60 = NameAndType        #30:#59        // "<init>":(Lshapeless/PolyDefns$Case;Lshapeless/ops/hlist$Collect;)V
  #61 = Methodref          #24.#60        // shapeless/ops/hlist$Collect$$anon$163."<init>":(Lshapeless/PolyDefns$Case;Lshapeless/ops/hlist$Collect;)V
  #62 = Utf8               Lshapeless/PolyDefns$Case;
  #63 = Utf8               writeReplace
  #64 = Utf8               ()Ljava/lang/Object;
  #65 = Utf8               scala/runtime/ModuleSerializationProxy
  #66 = Class              #65            // scala/runtime/ModuleSerializationProxy
  #67 = Utf8               (Ljava/lang/Class;)V
  #68 = NameAndType        #30:#67        // "<init>":(Ljava/lang/Class;)V
  #69 = Methodref          #66.#68        // scala/runtime/ModuleSerializationProxy."<init>":(Ljava/lang/Class;)V
  #70 = Methodref          #4.#31         // java/lang/Object."<init>":()V
  #71 = Utf8               Code
  #72 = Utf8               LineNumberTable
  #73 = Utf8               LocalVariableTable
  #74 = Utf8               Signature
  #75 = Utf8               MethodParameters
  #76 = Utf8               InnerClasses
  #77 = Utf8               SourceFile
  #78 = Utf8               ScalaInlineInfo
  #79 = Utf8               Scala
{
  public static final shapeless.ops.hlist$Collect$ MODULE$;
    descriptor: Lshapeless/ops/hlist$Collect$;
    flags: (0x0019) ACC_PUBLIC, ACC_STATIC, ACC_FINAL

  public static {};
    descriptor: ()V
    flags: (0x0009) ACC_PUBLIC, ACC_STATIC
    Code:
      stack=2, locals=0, args_size=0
         0: new           #2                  // class shapeless/ops/hlist$Collect$
         3: dup
         4: invokespecial #32                 // Method "<init>":()V
         7: putstatic     #34                 // Field MODULE$:Lshapeless/ops/hlist$Collect$;
        10: getstatic     #34                 // Field MODULE$:Lshapeless/ops/hlist$Collect$;
        13: invokestatic  #38                 // InterfaceMethod shapeless/ops/hlist$LowPriorityCollect.$init$:(Lshapeless/ops/hlist$LowPriorityCollect;)V
        16: return
      LineNumberTable:
        line 2426: 0

  public <LH extends java.lang.Object, LT extends shapeless.HList, P extends shapeless.Poly, CollectOut extends shapeless.HList> shapeless.ops.hlist$Collect<shapeless.$colon$colon<LH, LT>, P> hlistNoPolyCase(shapeless.ops.hlist$Collect<LT, P>);
    descriptor: (Lshapeless/ops/hlist$Collect;)Lshapeless/ops/hlist$Collect;
    flags: (0x0001) ACC_PUBLIC
    Code:
      stack=2, locals=2, args_size=2
         0: aload_0
         1: aload_1
         2: invokestatic  #46                 // InterfaceMethod shapeless/ops/hlist$LowPriorityCollect.hlistNoPolyCase$:(Lshapeless/ops/hlist$LowPriorityCollect;Lshapeless/ops/hlist$Collect;)Lshapeless/ops/hlist$Collect;
         5: areturn
      LineNumberTable:
        line 2426: 0
      LocalVariableTable:
        Start  Length  Slot  Name   Signature
            0       6     0  this   Lshapeless/ops/hlist$Collect$;
            0       6     1 collect   Lshapeless/ops/hlist$Collect;
    Signature: #41                          // <LH:Ljava/lang/Object;LT::Lshapeless/HList;P::Lshapeless/Poly;CollectOut::Lshapeless/HList;>(Lshapeless/ops/hlist$Collect<TLT;TP;>;)Lshapeless/ops/hlist$Collect<Lshapeless/$colon$colon<TLH;TLT;>;TP;>;
    MethodParameters:
      Name                           Flags
      collect                        final

  public <L extends shapeless.HList, P extends shapeless.Poly> shapeless.ops.hlist$Collect<L, P> apply(shapeless.ops.hlist$Collect<L, P>);
    descriptor: (Lshapeless/ops/hlist$Collect;)Lshapeless/ops/hlist$Collect;
    flags: (0x0001) ACC_PUBLIC
    Code:
      stack=1, locals=2, args_size=2
         0: aload_1
         1: areturn
      LineNumberTable:
        line 2428: 0
      LocalVariableTable:
        Start  Length  Slot  Name   Signature
            0       2     0  this   Lshapeless/ops/hlist$Collect$;
            0       2     1 collect   Lshapeless/ops/hlist$Collect;
    Signature: #50                          // <L::Lshapeless/HList;P::Lshapeless/Poly;>(Lshapeless/ops/hlist$Collect<TL;TP;>;)Lshapeless/ops/hlist$Collect<TL;TP;>;
    MethodParameters:
      Name                           Flags
      collect                        final

  public <P extends shapeless.Poly> shapeless.ops.hlist$Collect<shapeless.HNil, P> hnilCollect();
    descriptor: ()Lshapeless/ops/hlist$Collect;
    flags: (0x0001) ACC_PUBLIC
    Code:
      stack=2, locals=1, args_size=1
         0: new           #22                 // class shapeless/ops/hlist$Collect$$anon$162
         3: dup
         4: invokespecial #54                 // Method shapeless/ops/hlist$Collect$$anon$162."<init>":()V
         7: areturn
      LineNumberTable:
        line 2432: 0
      LocalVariableTable:
        Start  Length  Slot  Name   Signature
            0       8     0  this   Lshapeless/ops/hlist$Collect$;
    Signature: #53                          // <P::Lshapeless/Poly;>()Lshapeless/ops/hlist$Collect<Lshapeless/HNil;TP;>;

  public <LH extends java.lang.Object, LT extends shapeless.HList, P extends shapeless.Poly, CollectOut extends shapeless.HList, ClrResult extends java.lang.Object> shapeless.ops.hlist$Collect<shapeless.$colon$colon<LH, LT>, P> hlistCollect(shapeless.ops.hlist$Collect<LT, P>, shapeless.PolyDefns$Case<P, shapeless.$colon$colon<LH, shapeless.HNil>>);
    descriptor: (Lshapeless/ops/hlist$Collect;Lshapeless/PolyDefns$Case;)Lshapeless/ops/hlist$Collect;
    flags: (0x0001) ACC_PUBLIC
    Code:
      stack=4, locals=3, args_size=3
         0: new           #24                 // class shapeless/ops/hlist$Collect$$anon$163
         3: dup
         4: aload_2
         5: aload_1
         6: invokespecial #61                 // Method shapeless/ops/hlist$Collect$$anon$163."<init>":(Lshapeless/PolyDefns$Case;Lshapeless/ops/hlist$Collect;)V
         9: areturn
      LineNumberTable:
        line 2441: 0
      LocalVariableTable:
        Start  Length  Slot  Name   Signature
            0      10     0  this   Lshapeless/ops/hlist$Collect$;
            0      10     1 collect   Lshapeless/ops/hlist$Collect;
            0      10     2   clr   Lshapeless/PolyDefns$Case;
    Signature: #57                          // <LH:Ljava/lang/Object;LT::Lshapeless/HList;P::Lshapeless/Poly;CollectOut::Lshapeless/HList;ClrResult:Ljava/lang/Object;>(Lshapeless/ops/hlist$Collect<TLT;TP;>;Lshapeless/PolyDefns$Case<TP;Lshapeless/$colon$colon<TLH;Lshapeless/HNil;>;>;)Lshapeless/ops/hlist$Collect<Lshapeless/$colon$colon<TLH;TLT;>;TP;>;
    MethodParameters:
      Name                           Flags
      collect                        final
      clr                            final

  private java.lang.Object writeReplace();
    descriptor: ()Ljava/lang/Object;
    flags: (0x0002) ACC_PRIVATE
    Code:
      stack=3, locals=1, args_size=1
         0: new           #66                 // class scala/runtime/ModuleSerializationProxy
         3: dup
         4: ldc           #2                  // class shapeless/ops/hlist$Collect$
         6: invokespecial #69                 // Method scala/runtime/ModuleSerializationProxy."<init>":(Ljava/lang/Class;)V
         9: areturn
      LineNumberTable:
        line 2426: 0
      LocalVariableTable:
        Start  Length  Slot  Name   Signature
            0      10     0  this   Lshapeless/ops/hlist$Collect$;

  public shapeless.ops.hlist$Collect$();
    descriptor: ()V
    flags: (0x0001) ACC_PUBLIC
    Code:
      stack=1, locals=1, args_size=1
         0: aload_0
         1: invokespecial #70                 // Method java/lang/Object."<init>":()V
         4: return
      LineNumberTable:
        line 2426: 0
      LocalVariableTable:
        Start  Length  Slot  Name   Signature
            0       5     0  this   Lshapeless/ops/hlist$Collect$;
}
InnerClasses:
  public static abstract #14= #11 of #13; // Case=class shapeless/PolyDefns$Case of class shapeless/PolyDefns
  public static #19= #16 of #18;          // Collect=class shapeless/ops/hlist$Collect of class shapeless/ops/hlist
  public static #20= #2 of #18;           // Collect$=class shapeless/ops/hlist$Collect$ of class shapeless/ops/hlist
  public final #22;                       // class shapeless/ops/hlist$Collect$$anon$162
  public final #24;                       // class shapeless/ops/hlist$Collect$$anon$163
  public static #25= #6 of #18;           // LowPriorityCollect=class shapeless/ops/hlist$LowPriorityCollect of class shapeless/ops/hlist
SourceFile: "hlists.scala"
  ScalaInlineInfo: length = 0x22 (unknown attribute)
   01 01 00 06 00 1E 00 1D 01 00 31 00 28 01 00 37
   00 38 01 00 27 00 28 01 00 33 00 34 01 00 3F 00
   40 01
  Scala: length = 0x0 (unknown attribute)

