Classfile /Users/mw/Projects/slang-braindump/.jar/jar11/assemble/slang-braindump/assemble/content/shapeless/ops/hlist$HKernelAux$.class
  Last modified May 29, 2022; size 1402 bytes
  SHA-256 checksum 483e50c53c92aae3af311543a6beca79a72e5ed55592831dbc1978dcdbafa16e
  Compiled from "hlists.scala"
public class shapeless.ops.hlist$HKernelAux$
  minor version: 0
  major version: 52
  flags: (0x0021) ACC_PUBLIC, ACC_SUPER
  this_class: #2                          // shapeless/ops/hlist$HKernelAux$
  super_class: #4                         // java/lang/Object
  interfaces: 0, fields: 1, methods: 4, attributes: 4
Constant pool:
   #1 = Utf8               shapeless/ops/hlist$HKernelAux$
   #2 = Class              #1             // shapeless/ops/hlist$HKernelAux$
   #3 = Utf8               java/lang/Object
   #4 = Class              #3             // java/lang/Object
   #5 = Utf8               hlists.scala
   #6 = Utf8               shapeless/ops/hlist$HKernel
   #7 = Class              #6             // shapeless/ops/hlist$HKernel
   #8 = Utf8               shapeless/ops/hlist
   #9 = Class              #8             // shapeless/ops/hlist
  #10 = Utf8               HKernel
  #11 = Utf8               shapeless/ops/hlist$HKernelAux
  #12 = Class              #11            // shapeless/ops/hlist$HKernelAux
  #13 = Utf8               HKernelAux
  #14 = Utf8               HKernelAux$
  #15 = Utf8               shapeless/ops/hlist$HKernelAux$$anon$17
  #16 = Class              #15            // shapeless/ops/hlist$HKernelAux$$anon$17
  #17 = Utf8               shapeless/ops/hlist$HKernelAux$$anon$18
  #18 = Class              #17            // shapeless/ops/hlist$HKernelAux$$anon$18
  #19 = Utf8               MODULE$
  #20 = Utf8               Lshapeless/ops/hlist$HKernelAux$;
  #21 = Utf8               <clinit>
  #22 = Utf8               ()V
  #23 = Utf8               <init>
  #24 = NameAndType        #23:#22        // "<init>":()V
  #25 = Methodref          #2.#24         // shapeless/ops/hlist$HKernelAux$."<init>":()V
  #26 = NameAndType        #19:#20        // MODULE$:Lshapeless/ops/hlist$HKernelAux$;
  #27 = Fieldref           #2.#26         // shapeless/ops/hlist$HKernelAux$.MODULE$:Lshapeless/ops/hlist$HKernelAux$;
  #28 = Utf8               mkHNilHKernel
  #29 = Utf8               ()Lshapeless/ops/hlist$HKernelAux;
  #30 = Utf8               ()Lshapeless/ops/hlist$HKernelAux<Lshapeless/HNil;>;
  #31 = Methodref          #16.#24        // shapeless/ops/hlist$HKernelAux$$anon$17."<init>":()V
  #32 = Utf8               this
  #33 = Utf8               mkHListHKernel
  #34 = Utf8               (Lshapeless/ops/hlist$HKernelAux;)Lshapeless/ops/hlist$HKernelAux;
  #35 = Utf8               <H:Ljava/lang/Object;T::Lshapeless/HList;CtOut::Lshapeless/ops/hlist$HKernel;>(Lshapeless/ops/hlist$HKernelAux<TT;>;)Lshapeless/ops/hlist$HKernelAux<Lshapeless/$colon$colon<TH;TT;>;>;
  #36 = Utf8               ct
  #37 = Utf8               (Lshapeless/ops/hlist$HKernelAux;)V
  #38 = NameAndType        #23:#37        // "<init>":(Lshapeless/ops/hlist$HKernelAux;)V
  #39 = Methodref          #18.#38        // shapeless/ops/hlist$HKernelAux$$anon$18."<init>":(Lshapeless/ops/hlist$HKernelAux;)V
  #40 = Utf8               Lshapeless/ops/hlist$HKernelAux;
  #41 = Methodref          #4.#24         // java/lang/Object."<init>":()V
  #42 = Utf8               Code
  #43 = Utf8               LineNumberTable
  #44 = Utf8               LocalVariableTable
  #45 = Utf8               Signature
  #46 = Utf8               MethodParameters
  #47 = Utf8               InnerClasses
  #48 = Utf8               SourceFile
  #49 = Utf8               ScalaInlineInfo
  #50 = Utf8               Scala
{
  public static final shapeless.ops.hlist$HKernelAux$ MODULE$;
    descriptor: Lshapeless/ops/hlist$HKernelAux$;
    flags: (0x0019) ACC_PUBLIC, ACC_STATIC, ACC_FINAL

  public static {};
    descriptor: ()V
    flags: (0x0009) ACC_PUBLIC, ACC_STATIC
    Code:
      stack=2, locals=0, args_size=0
         0: new           #2                  // class shapeless/ops/hlist$HKernelAux$
         3: dup
         4: invokespecial #25                 // Method "<init>":()V
         7: putstatic     #27                 // Field MODULE$:Lshapeless/ops/hlist$HKernelAux$;
        10: return
      LineNumberTable:
        line 213: 0

  public shapeless.ops.hlist$HKernelAux<shapeless.HNil> mkHNilHKernel();
    descriptor: ()Lshapeless/ops/hlist$HKernelAux;
    flags: (0x0001) ACC_PUBLIC
    Code:
      stack=2, locals=1, args_size=1
         0: new           #16                 // class shapeless/ops/hlist$HKernelAux$$anon$17
         3: dup
         4: invokespecial #31                 // Method shapeless/ops/hlist$HKernelAux$$anon$17."<init>":()V
         7: areturn
      LineNumberTable:
        line 217: 0
      LocalVariableTable:
        Start  Length  Slot  Name   Signature
            0       8     0  this   Lshapeless/ops/hlist$HKernelAux$;
    Signature: #30                          // ()Lshapeless/ops/hlist$HKernelAux<Lshapeless/HNil;>;

  public <H extends java.lang.Object, T extends shapeless.HList, CtOut extends shapeless.ops.hlist$HKernel> shapeless.ops.hlist$HKernelAux<shapeless.$colon$colon<H, T>> mkHListHKernel(shapeless.ops.hlist$HKernelAux<T>);
    descriptor: (Lshapeless/ops/hlist$HKernelAux;)Lshapeless/ops/hlist$HKernelAux;
    flags: (0x0001) ACC_PUBLIC
    Code:
      stack=3, locals=2, args_size=2
         0: new           #18                 // class shapeless/ops/hlist$HKernelAux$$anon$18
         3: dup
         4: aload_1
         5: invokespecial #39                 // Method shapeless/ops/hlist$HKernelAux$$anon$18."<init>":(Lshapeless/ops/hlist$HKernelAux;)V
         8: areturn
      LineNumberTable:
        line 222: 0
      LocalVariableTable:
        Start  Length  Slot  Name   Signature
            0       9     0  this   Lshapeless/ops/hlist$HKernelAux$;
            0       9     1    ct   Lshapeless/ops/hlist$HKernelAux;
    Signature: #35                          // <H:Ljava/lang/Object;T::Lshapeless/HList;CtOut::Lshapeless/ops/hlist$HKernel;>(Lshapeless/ops/hlist$HKernelAux<TT;>;)Lshapeless/ops/hlist$HKernelAux<Lshapeless/$colon$colon<TH;TT;>;>;
    MethodParameters:
      Name                           Flags
      ct                             final

  public shapeless.ops.hlist$HKernelAux$();
    descriptor: ()V
    flags: (0x0001) ACC_PUBLIC
    Code:
      stack=1, locals=1, args_size=1
         0: aload_0
         1: invokespecial #41                 // Method java/lang/Object."<init>":()V
         4: return
      LineNumberTable:
        line 233: 0
        line 213: 4
      LocalVariableTable:
        Start  Length  Slot  Name   Signature
            0       5     0  this   Lshapeless/ops/hlist$HKernelAux$;
}
InnerClasses:
  public static #10= #7 of #9;            // HKernel=class shapeless/ops/hlist$HKernel of class shapeless/ops/hlist
  public static #13= #12 of #9;           // HKernelAux=class shapeless/ops/hlist$HKernelAux of class shapeless/ops/hlist
  public static #14= #2 of #9;            // HKernelAux$=class shapeless/ops/hlist$HKernelAux$ of class shapeless/ops/hlist
  public final #16;                       // class shapeless/ops/hlist$HKernelAux$$anon$17
  public final #18;                       // class shapeless/ops/hlist$HKernelAux$$anon$18
SourceFile: "hlists.scala"
  ScalaInlineInfo: length = 0x13 (unknown attribute)
   01 01 00 03 00 17 00 16 01 00 21 00 22 01 00 1C
   00 1D 01
  Scala: length = 0x0 (unknown attribute)

