Classfile /Users/mw/Projects/slang-braindump/.jar/jar11/assemble/slang-braindump/assemble/content/shapeless/ops/hlist$Fill$.class
  Last modified May 29, 2022; size 2269 bytes
  SHA-256 checksum 7565ff0c41cbfe510a19a296e25e668e280139535c74d0c947b1ffe5d684811c
  Compiled from "hlists.scala"
public class shapeless.ops.hlist$Fill$ implements java.io.Serializable
  minor version: 0
  major version: 52
  flags: (0x0021) ACC_PUBLIC, ACC_SUPER
  this_class: #2                          // shapeless/ops/hlist$Fill$
  super_class: #4                         // java/lang/Object
  interfaces: 1, fields: 1, methods: 7, attributes: 4
Constant pool:
   #1 = Utf8               shapeless/ops/hlist$Fill$
   #2 = Class              #1             // shapeless/ops/hlist$Fill$
   #3 = Utf8               java/lang/Object
   #4 = Class              #3             // java/lang/Object
   #5 = Utf8               java/io/Serializable
   #6 = Class              #5             // java/io/Serializable
   #7 = Utf8               hlists.scala
   #8 = Utf8               shapeless/ops/hlist$Fill
   #9 = Class              #8             // shapeless/ops/hlist$Fill
  #10 = Utf8               shapeless/ops/hlist
  #11 = Class              #10            // shapeless/ops/hlist
  #12 = Utf8               Fill
  #13 = Utf8               Fill$
  #14 = Utf8               shapeless/ops/hlist$Fill$$anon$185
  #15 = Class              #14            // shapeless/ops/hlist$Fill$$anon$185
  #16 = Utf8               shapeless/ops/hlist$Fill$$anon$186
  #17 = Class              #16            // shapeless/ops/hlist$Fill$$anon$186
  #18 = Utf8               shapeless/ops/hlist$Fill$$anon$187
  #19 = Class              #18            // shapeless/ops/hlist$Fill$$anon$187
  #20 = Utf8               MODULE$
  #21 = Utf8               Lshapeless/ops/hlist$Fill$;
  #22 = Utf8               <clinit>
  #23 = Utf8               ()V
  #24 = Utf8               <init>
  #25 = NameAndType        #24:#23        // "<init>":()V
  #26 = Methodref          #2.#25         // shapeless/ops/hlist$Fill$."<init>":()V
  #27 = NameAndType        #20:#21        // MODULE$:Lshapeless/ops/hlist$Fill$;
  #28 = Fieldref           #2.#27         // shapeless/ops/hlist$Fill$.MODULE$:Lshapeless/ops/hlist$Fill$;
  #29 = Utf8               apply
  #30 = Utf8               (Lshapeless/ops/hlist$Fill;)Lshapeless/ops/hlist$Fill;
  #31 = Utf8               <N:Ljava/lang/Object;A:Ljava/lang/Object;>(Lshapeless/ops/hlist$Fill<TN;TA;>;)Lshapeless/ops/hlist$Fill<TN;TA;>;
  #32 = Utf8               fill
  #33 = Utf8               this
  #34 = Utf8               Lshapeless/ops/hlist$Fill;
  #35 = Utf8               fill1Zero
  #36 = Utf8               ()Lshapeless/ops/hlist$Fill;
  #37 = Utf8               <A:Ljava/lang/Object;>()Lshapeless/ops/hlist$Fill<Lshapeless/_0;TA;>;
  #38 = Methodref          #15.#25        // shapeless/ops/hlist$Fill$$anon$185."<init>":()V
  #39 = Utf8               fill1Succ
  #40 = Utf8               <N::Lshapeless/Nat;A:Ljava/lang/Object;OutT::Lshapeless/HList;>(Lshapeless/ops/hlist$Fill<TN;TA;>;)Lshapeless/ops/hlist$Fill<Lshapeless/Succ<TN;>;TA;>;
  #41 = Utf8               prev
  #42 = Utf8               (Lshapeless/ops/hlist$Fill;)V
  #43 = NameAndType        #24:#42        // "<init>":(Lshapeless/ops/hlist$Fill;)V
  #44 = Methodref          #17.#43        // shapeless/ops/hlist$Fill$$anon$186."<init>":(Lshapeless/ops/hlist$Fill;)V
  #45 = Utf8               fill2
  #46 = Utf8               (Lshapeless/ops/hlist$Fill;Lshapeless/ops/hlist$Fill;)Lshapeless/ops/hlist$Fill;
  #47 = Utf8               <A:Ljava/lang/Object;N1::Lshapeless/Nat;N2::Lshapeless/Nat;SubOut:Ljava/lang/Object;OutT::Lshapeless/HList;>(Lshapeless/ops/hlist$Fill<TN2;TA;>;Lshapeless/ops/hlist$Fill<TN1;TSubOut;>;)Lshapeless/ops/hlist$Fill<Lscala/Tuple2<TN1;TN2;>;TA;>;
  #48 = Utf8               subFill
  #49 = Utf8               (Lshapeless/ops/hlist$Fill;Lshapeless/ops/hlist$Fill;)V
  #50 = NameAndType        #24:#49        // "<init>":(Lshapeless/ops/hlist$Fill;Lshapeless/ops/hlist$Fill;)V
  #51 = Methodref          #19.#50        // shapeless/ops/hlist$Fill$$anon$187."<init>":(Lshapeless/ops/hlist$Fill;Lshapeless/ops/hlist$Fill;)V
  #52 = Utf8               writeReplace
  #53 = Utf8               ()Ljava/lang/Object;
  #54 = Utf8               scala/runtime/ModuleSerializationProxy
  #55 = Class              #54            // scala/runtime/ModuleSerializationProxy
  #56 = Utf8               (Ljava/lang/Class;)V
  #57 = NameAndType        #24:#56        // "<init>":(Ljava/lang/Class;)V
  #58 = Methodref          #55.#57        // scala/runtime/ModuleSerializationProxy."<init>":(Ljava/lang/Class;)V
  #59 = Methodref          #4.#25         // java/lang/Object."<init>":()V
  #60 = Utf8               Code
  #61 = Utf8               LineNumberTable
  #62 = Utf8               LocalVariableTable
  #63 = Utf8               Signature
  #64 = Utf8               MethodParameters
  #65 = Utf8               InnerClasses
  #66 = Utf8               SourceFile
  #67 = Utf8               ScalaInlineInfo
  #68 = Utf8               Scala
{
  public static final shapeless.ops.hlist$Fill$ MODULE$;
    descriptor: Lshapeless/ops/hlist$Fill$;
    flags: (0x0019) ACC_PUBLIC, ACC_STATIC, ACC_FINAL

  public static {};
    descriptor: ()V
    flags: (0x0009) ACC_PUBLIC, ACC_STATIC
    Code:
      stack=2, locals=0, args_size=0
         0: new           #2                  // class shapeless/ops/hlist$Fill$
         3: dup
         4: invokespecial #26                 // Method "<init>":()V
         7: putstatic     #28                 // Field MODULE$:Lshapeless/ops/hlist$Fill$;
        10: return
      LineNumberTable:
        line 2755: 0

  public <N extends java.lang.Object, A extends java.lang.Object> shapeless.ops.hlist$Fill<N, A> apply(shapeless.ops.hlist$Fill<N, A>);
    descriptor: (Lshapeless/ops/hlist$Fill;)Lshapeless/ops/hlist$Fill;
    flags: (0x0001) ACC_PUBLIC
    Code:
      stack=1, locals=2, args_size=2
         0: aload_1
         1: areturn
      LineNumberTable:
        line 2756: 0
      LocalVariableTable:
        Start  Length  Slot  Name   Signature
            0       2     0  this   Lshapeless/ops/hlist$Fill$;
            0       2     1  fill   Lshapeless/ops/hlist$Fill;
    Signature: #31                          // <N:Ljava/lang/Object;A:Ljava/lang/Object;>(Lshapeless/ops/hlist$Fill<TN;TA;>;)Lshapeless/ops/hlist$Fill<TN;TA;>;
    MethodParameters:
      Name                           Flags
      fill                           final

  public <A extends java.lang.Object> shapeless.ops.hlist$Fill<shapeless._0, A> fill1Zero();
    descriptor: ()Lshapeless/ops/hlist$Fill;
    flags: (0x0001) ACC_PUBLIC
    Code:
      stack=2, locals=1, args_size=1
         0: new           #15                 // class shapeless/ops/hlist$Fill$$anon$185
         3: dup
         4: invokespecial #38                 // Method shapeless/ops/hlist$Fill$$anon$185."<init>":()V
         7: areturn
      LineNumberTable:
        line 2761: 0
      LocalVariableTable:
        Start  Length  Slot  Name   Signature
            0       8     0  this   Lshapeless/ops/hlist$Fill$;
    Signature: #37                          // <A:Ljava/lang/Object;>()Lshapeless/ops/hlist$Fill<Lshapeless/_0;TA;>;

  public <N extends shapeless.Nat, A extends java.lang.Object, OutT extends shapeless.HList> shapeless.ops.hlist$Fill<shapeless.Succ<N>, A> fill1Succ(shapeless.ops.hlist$Fill<N, A>);
    descriptor: (Lshapeless/ops/hlist$Fill;)Lshapeless/ops/hlist$Fill;
    flags: (0x0001) ACC_PUBLIC
    Code:
      stack=3, locals=2, args_size=2
         0: new           #17                 // class shapeless/ops/hlist$Fill$$anon$186
         3: dup
         4: aload_1
         5: invokespecial #44                 // Method shapeless/ops/hlist$Fill$$anon$186."<init>":(Lshapeless/ops/hlist$Fill;)V
         8: areturn
      LineNumberTable:
        line 2768: 0
      LocalVariableTable:
        Start  Length  Slot  Name   Signature
            0       9     0  this   Lshapeless/ops/hlist$Fill$;
            0       9     1  prev   Lshapeless/ops/hlist$Fill;
    Signature: #40                          // <N::Lshapeless/Nat;A:Ljava/lang/Object;OutT::Lshapeless/HList;>(Lshapeless/ops/hlist$Fill<TN;TA;>;)Lshapeless/ops/hlist$Fill<Lshapeless/Succ<TN;>;TA;>;
    MethodParameters:
      Name                           Flags
      prev                           final

  public <A extends java.lang.Object, N1 extends shapeless.Nat, N2 extends shapeless.Nat, SubOut extends java.lang.Object, OutT extends shapeless.HList> shapeless.ops.hlist$Fill<scala.Tuple2<N1, N2>, A> fill2(shapeless.ops.hlist$Fill<N2, A>, shapeless.ops.hlist$Fill<N1, SubOut>);
    descriptor: (Lshapeless/ops/hlist$Fill;Lshapeless/ops/hlist$Fill;)Lshapeless/ops/hlist$Fill;
    flags: (0x0001) ACC_PUBLIC
    Code:
      stack=4, locals=3, args_size=3
         0: new           #19                 // class shapeless/ops/hlist$Fill$$anon$187
         3: dup
         4: aload_2
         5: aload_1
         6: invokespecial #51                 // Method shapeless/ops/hlist$Fill$$anon$187."<init>":(Lshapeless/ops/hlist$Fill;Lshapeless/ops/hlist$Fill;)V
         9: areturn
      LineNumberTable:
        line 2775: 0
      LocalVariableTable:
        Start  Length  Slot  Name   Signature
            0      10     0  this   Lshapeless/ops/hlist$Fill$;
            0      10     1 subFill   Lshapeless/ops/hlist$Fill;
            0      10     2  fill   Lshapeless/ops/hlist$Fill;
    Signature: #47                          // <A:Ljava/lang/Object;N1::Lshapeless/Nat;N2::Lshapeless/Nat;SubOut:Ljava/lang/Object;OutT::Lshapeless/HList;>(Lshapeless/ops/hlist$Fill<TN2;TA;>;Lshapeless/ops/hlist$Fill<TN1;TSubOut;>;)Lshapeless/ops/hlist$Fill<Lscala/Tuple2<TN1;TN2;>;TA;>;
    MethodParameters:
      Name                           Flags
      subFill                        final
      fill                           final

  private java.lang.Object writeReplace();
    descriptor: ()Ljava/lang/Object;
    flags: (0x0002) ACC_PRIVATE
    Code:
      stack=3, locals=1, args_size=1
         0: new           #55                 // class scala/runtime/ModuleSerializationProxy
         3: dup
         4: ldc           #2                  // class shapeless/ops/hlist$Fill$
         6: invokespecial #58                 // Method scala/runtime/ModuleSerializationProxy."<init>":(Ljava/lang/Class;)V
         9: areturn
      LineNumberTable:
        line 2755: 0
      LocalVariableTable:
        Start  Length  Slot  Name   Signature
            0      10     0  this   Lshapeless/ops/hlist$Fill$;

  public shapeless.ops.hlist$Fill$();
    descriptor: ()V
    flags: (0x0001) ACC_PUBLIC
    Code:
      stack=1, locals=1, args_size=1
         0: aload_0
         1: invokespecial #59                 // Method java/lang/Object."<init>":()V
         4: return
      LineNumberTable:
        line 2786: 0
        line 2755: 4
      LocalVariableTable:
        Start  Length  Slot  Name   Signature
            0       5     0  this   Lshapeless/ops/hlist$Fill$;
}
InnerClasses:
  public static #12= #9 of #11;           // Fill=class shapeless/ops/hlist$Fill of class shapeless/ops/hlist
  public static #13= #2 of #11;           // Fill$=class shapeless/ops/hlist$Fill$ of class shapeless/ops/hlist
  public final #15;                       // class shapeless/ops/hlist$Fill$$anon$185
  public final #17;                       // class shapeless/ops/hlist$Fill$$anon$186
  public final #19;                       // class shapeless/ops/hlist$Fill$$anon$187
SourceFile: "hlists.scala"
  ScalaInlineInfo: length = 0x22 (unknown attribute)
   01 01 00 06 00 18 00 17 01 00 1D 00 1E 01 00 27
   00 1E 01 00 23 00 24 01 00 2D 00 2E 01 00 34 00
   35 01
  Scala: length = 0x0 (unknown attribute)

