Classfile /Users/mw/Projects/slang-braindump/.jar/jar11/assemble/slang-braindump/assemble/content/shapeless/ops/hlist$ReverseSplitLeft$LowPriorityReverseSplitLeft0.class
  Last modified May 29, 2022; size 1978 bytes
  SHA-256 checksum d9ba7670a512a50084f74906675d8f3c1b9867b47d88e16b1152caeebe3f5651
  Compiled from "hlists.scala"
public interface shapeless.ops.hlist$ReverseSplitLeft$LowPriorityReverseSplitLeft0
  minor version: 0
  major version: 52
  flags: (0x0601) ACC_PUBLIC, ACC_INTERFACE, ACC_ABSTRACT
  this_class: #2                          // shapeless/ops/hlist$ReverseSplitLeft$LowPriorityReverseSplitLeft0
  super_class: #4                         // java/lang/Object
  interfaces: 0, fields: 0, methods: 3, attributes: 4
Constant pool:
   #1 = Utf8               shapeless/ops/hlist$ReverseSplitLeft$LowPriorityReverseSplitLeft0
   #2 = Class              #1             // shapeless/ops/hlist$ReverseSplitLeft$LowPriorityReverseSplitLeft0
   #3 = Utf8               java/lang/Object
   #4 = Class              #3             // java/lang/Object
   #5 = Utf8               hlists.scala
   #6 = Utf8               shapeless/ops/hlist$ReverseSplitLeft$
   #7 = Class              #6             // shapeless/ops/hlist$ReverseSplitLeft$
   #8 = Utf8               shapeless/ops/hlist
   #9 = Class              #8             // shapeless/ops/hlist
  #10 = Utf8               ReverseSplitLeft$
  #11 = Utf8               LowPriorityReverseSplitLeft0
  #12 = Utf8               shapeless/ops/hlist$ReverseSplitLeft$LowPriorityReverseSplitLeft0$$anon$118
  #13 = Class              #12            // shapeless/ops/hlist$ReverseSplitLeft$LowPriorityReverseSplitLeft0$$anon$118
  #14 = Utf8               shapeless/ops/hlist$ReverseSplitLeft$ReverseSplitLeft0
  #15 = Class              #14            // shapeless/ops/hlist$ReverseSplitLeft$ReverseSplitLeft0
  #16 = Utf8               ReverseSplitLeft0
  #17 = Utf8               hlistReverseSplitLeft1$
  #18 = Utf8               (Lshapeless/ops/hlist$ReverseSplitLeft$LowPriorityReverseSplitLeft0;Lshapeless/ops/hlist$ReverseSplitLeft$ReverseSplitLeft0;)Lshapeless/ops/hlist$ReverseSplitLeft$ReverseSplitLeft0;
  #19 = Utf8               $this
  #20 = Utf8               slt
  #21 = Utf8               hlistReverseSplitLeft1
  #22 = Utf8               (Lshapeless/ops/hlist$ReverseSplitLeft$ReverseSplitLeft0;)Lshapeless/ops/hlist$ReverseSplitLeft$ReverseSplitLeft0;
  #23 = NameAndType        #21:#22        // hlistReverseSplitLeft1:(Lshapeless/ops/hlist$ReverseSplitLeft$ReverseSplitLeft0;)Lshapeless/ops/hlist$ReverseSplitLeft$ReverseSplitLeft0;
  #24 = InterfaceMethodref #2.#23         // shapeless/ops/hlist$ReverseSplitLeft$LowPriorityReverseSplitLeft0.hlistReverseSplitLeft1:(Lshapeless/ops/hlist$ReverseSplitLeft$ReverseSplitLeft0;)Lshapeless/ops/hlist$ReverseSplitLeft$ReverseSplitLeft0;
  #25 = Utf8               Lshapeless/ops/hlist$ReverseSplitLeft$LowPriorityReverseSplitLeft0;
  #26 = Utf8               Lshapeless/ops/hlist$ReverseSplitLeft$ReverseSplitLeft0;
  #27 = Utf8               <AccP::Lshapeless/HList;AccSH:Ljava/lang/Object;AccST::Lshapeless/HList;U:Ljava/lang/Object;P:Ljava/lang/Object;S:Ljava/lang/Object;>(Lshapeless/ops/hlist$ReverseSplitLeft$ReverseSplitLeft0<Lshapeless/$colon$colon<TAccSH;TAccP;>;TAccST;TU;TP;TS;>;)Lshapeless/ops/hlist$ReverseSplitLeft$ReverseSplitLeft0<TAccP;Lshapeless/$colon$colon<TAccSH;TAccST;>;TU;TP;TS;>;
  #28 = Utf8               <init>
  #29 = Utf8               (Lshapeless/ops/hlist$ReverseSplitLeft$LowPriorityReverseSplitLeft0;Lshapeless/ops/hlist$ReverseSplitLeft$ReverseSplitLeft0;)V
  #30 = NameAndType        #28:#29        // "<init>":(Lshapeless/ops/hlist$ReverseSplitLeft$LowPriorityReverseSplitLeft0;Lshapeless/ops/hlist$ReverseSplitLeft$ReverseSplitLeft0;)V
  #31 = Methodref          #13.#30        // shapeless/ops/hlist$ReverseSplitLeft$LowPriorityReverseSplitLeft0$$anon$118."<init>":(Lshapeless/ops/hlist$ReverseSplitLeft$LowPriorityReverseSplitLeft0;Lshapeless/ops/hlist$ReverseSplitLeft$ReverseSplitLeft0;)V
  #32 = Utf8               this
  #33 = Utf8               $init$
  #34 = Utf8               (Lshapeless/ops/hlist$ReverseSplitLeft$LowPriorityReverseSplitLeft0;)V
  #35 = Utf8               Code
  #36 = Utf8               LineNumberTable
  #37 = Utf8               LocalVariableTable
  #38 = Utf8               MethodParameters
  #39 = Utf8               Signature
  #40 = Utf8               InnerClasses
  #41 = Utf8               SourceFile
  #42 = Utf8               ScalaInlineInfo
  #43 = Utf8               Scala
{
  public static shapeless.ops.hlist$ReverseSplitLeft$ReverseSplitLeft0 hlistReverseSplitLeft1$(shapeless.ops.hlist$ReverseSplitLeft$LowPriorityReverseSplitLeft0, shapeless.ops.hlist$ReverseSplitLeft$ReverseSplitLeft0);
    descriptor: (Lshapeless/ops/hlist$ReverseSplitLeft$LowPriorityReverseSplitLeft0;Lshapeless/ops/hlist$ReverseSplitLeft$ReverseSplitLeft0;)Lshapeless/ops/hlist$ReverseSplitLeft$ReverseSplitLeft0;
    flags: (0x1009) ACC_PUBLIC, ACC_STATIC, ACC_SYNTHETIC
    Code:
      stack=2, locals=2, args_size=2
         0: aload_0
         1: aload_1
         2: invokespecial #24                 // InterfaceMethod hlistReverseSplitLeft1:(Lshapeless/ops/hlist$ReverseSplitLeft$ReverseSplitLeft0;)Lshapeless/ops/hlist$ReverseSplitLeft$ReverseSplitLeft0;
         5: areturn
      LineNumberTable:
        line 1820: 0
      LocalVariableTable:
        Start  Length  Slot  Name   Signature
            0       6     0 $this   Lshapeless/ops/hlist$ReverseSplitLeft$LowPriorityReverseSplitLeft0;
            0       6     1   slt   Lshapeless/ops/hlist$ReverseSplitLeft$ReverseSplitLeft0;
    MethodParameters:
      Name                           Flags
      $this                          final synthetic
      slt                            final

  public default <AccP extends shapeless.HList, AccSH extends java.lang.Object, AccST extends shapeless.HList, U extends java.lang.Object, P extends java.lang.Object, S extends java.lang.Object> shapeless.ops.hlist$ReverseSplitLeft$ReverseSplitLeft0<AccP, shapeless.$colon$colon<AccSH, AccST>, U, P, S> hlistReverseSplitLeft1(shapeless.ops.hlist$ReverseSplitLeft$ReverseSplitLeft0<shapeless.$colon$colon<AccSH, AccP>, AccST, U, P, S>);
    descriptor: (Lshapeless/ops/hlist$ReverseSplitLeft$ReverseSplitLeft0;)Lshapeless/ops/hlist$ReverseSplitLeft$ReverseSplitLeft0;
    flags: (0x0001) ACC_PUBLIC
    Code:
      stack=4, locals=2, args_size=2
         0: new           #13                 // class shapeless/ops/hlist$ReverseSplitLeft$LowPriorityReverseSplitLeft0$$anon$118
         3: dup
         4: aconst_null
         5: aload_1
         6: invokespecial #31                 // Method shapeless/ops/hlist$ReverseSplitLeft$LowPriorityReverseSplitLeft0$$anon$118."<init>":(Lshapeless/ops/hlist$ReverseSplitLeft$LowPriorityReverseSplitLeft0;Lshapeless/ops/hlist$ReverseSplitLeft$ReverseSplitLeft0;)V
         9: areturn
      LineNumberTable:
        line 1822: 0
      LocalVariableTable:
        Start  Length  Slot  Name   Signature
            0      10     0  this   Lshapeless/ops/hlist$ReverseSplitLeft$LowPriorityReverseSplitLeft0;
            0      10     1   slt   Lshapeless/ops/hlist$ReverseSplitLeft$ReverseSplitLeft0;
    Signature: #27                          // <AccP::Lshapeless/HList;AccSH:Ljava/lang/Object;AccST::Lshapeless/HList;U:Ljava/lang/Object;P:Ljava/lang/Object;S:Ljava/lang/Object;>(Lshapeless/ops/hlist$ReverseSplitLeft$ReverseSplitLeft0<Lshapeless/$colon$colon<TAccSH;TAccP;>;TAccST;TU;TP;TS;>;)Lshapeless/ops/hlist$ReverseSplitLeft$ReverseSplitLeft0<TAccP;Lshapeless/$colon$colon<TAccSH;TAccST;>;TU;TP;TS;>;
    MethodParameters:
      Name                           Flags
      slt                            final

  public static void $init$(shapeless.ops.hlist$ReverseSplitLeft$LowPriorityReverseSplitLeft0);
    descriptor: (Lshapeless/ops/hlist$ReverseSplitLeft$LowPriorityReverseSplitLeft0;)V
    flags: (0x0009) ACC_PUBLIC, ACC_STATIC
    Code:
      stack=0, locals=1, args_size=1
         0: return
      LineNumberTable:
        line 1819: 0
      LocalVariableTable:
        Start  Length  Slot  Name   Signature
            0       1     0 $this   Lshapeless/ops/hlist$ReverseSplitLeft$LowPriorityReverseSplitLeft0;
    MethodParameters:
      Name                           Flags
      $this                          final synthetic
}
InnerClasses:
  public static #10= #7 of #9;            // ReverseSplitLeft$=class shapeless/ops/hlist$ReverseSplitLeft$ of class shapeless/ops/hlist
  public static #11= #2 of #7;            // LowPriorityReverseSplitLeft0=class shapeless/ops/hlist$ReverseSplitLeft$LowPriorityReverseSplitLeft0 of class shapeless/ops/hlist$ReverseSplitLeft$
  public final #13;                       // class shapeless/ops/hlist$ReverseSplitLeft$LowPriorityReverseSplitLeft0$$anon$118
  public static #16= #15 of #7;           // ReverseSplitLeft0=class shapeless/ops/hlist$ReverseSplitLeft$ReverseSplitLeft0 of class shapeless/ops/hlist$ReverseSplitLeft$
SourceFile: "hlists.scala"
  ScalaInlineInfo: length = 0x13 (unknown attribute)
   01 00 00 03 00 21 00 22 01 00 11 00 12 01 00 15
   00 16 00
  Scala: length = 0x0 (unknown attribute)

