Classfile /Users/mw/Projects/slang-braindump/.jar/jar11/assemble/slang-braindump/assemble/content/shapeless/ops/hlist$LowPriorityRotateRight$$anon$178.class
  Last modified May 29, 2022; size 1582 bytes
  SHA-256 checksum c549b2f09a7997185e3f76c8e2c380f34c6827dc536faf4f2f5262f718e0fff6
  Compiled from "hlists.scala"
public final class shapeless.ops.hlist$LowPriorityRotateRight$$anon$178 extends java.lang.Object implements shapeless.ops.hlist$RotateRight<L, N>
  minor version: 0
  major version: 52
  flags: (0x0031) ACC_PUBLIC, ACC_FINAL, ACC_SUPER
  this_class: #2                          // shapeless/ops/hlist$LowPriorityRotateRight$$anon$178
  super_class: #5                         // java/lang/Object
  interfaces: 1, fields: 1, methods: 3, attributes: 6
Constant pool:
   #1 = Utf8               shapeless/ops/hlist$LowPriorityRotateRight$$anon$178
   #2 = Class              #1             // shapeless/ops/hlist$LowPriorityRotateRight$$anon$178
   #3 = Utf8               Ljava/lang/Object;Lshapeless/ops/hlist$RotateRight<TL;TN;>;
   #4 = Utf8               java/lang/Object
   #5 = Class              #4             // java/lang/Object
   #6 = Utf8               shapeless/ops/hlist$RotateRight
   #7 = Class              #6             // shapeless/ops/hlist$RotateRight
   #8 = Utf8               hlists.scala
   #9 = Utf8               shapeless/ops/hlist$LowPriorityRotateRight
  #10 = Class              #9             // shapeless/ops/hlist$LowPriorityRotateRight
  #11 = Utf8               hlistRotateRight
  #12 = Utf8               (Lshapeless/ops/hlist$Length;Lshapeless/ops/nat$Mod;Lshapeless/ops/nat$Diff;Lshapeless/ops/hlist$RotateLeft;)Lshapeless/ops/hlist$RotateRight;
  #13 = NameAndType        #11:#12        // hlistRotateRight:(Lshapeless/ops/hlist$Length;Lshapeless/ops/nat$Mod;Lshapeless/ops/nat$Diff;Lshapeless/ops/hlist$RotateLeft;)Lshapeless/ops/hlist$RotateRight;
  #14 = Utf8               shapeless/ops/hlist
  #15 = Class              #14            // shapeless/ops/hlist
  #16 = Utf8               LowPriorityRotateRight
  #17 = Utf8               shapeless/ops/hlist$RotateLeft
  #18 = Class              #17            // shapeless/ops/hlist$RotateLeft
  #19 = Utf8               RotateLeft
  #20 = Utf8               RotateRight
  #21 = Utf8               rotateLeft$1
  #22 = Utf8               Lshapeless/ops/hlist$RotateLeft;
  #23 = Utf8               apply
  #24 = Utf8               (Lshapeless/HList;)Lshapeless/HList;
  #25 = Utf8               (TL;)TRotateLeftOut;
  #26 = Utf8               l
  #27 = NameAndType        #21:#22        // rotateLeft$1:Lshapeless/ops/hlist$RotateLeft;
  #28 = Fieldref           #2.#27         // shapeless/ops/hlist$LowPriorityRotateRight$$anon$178.rotateLeft$1:Lshapeless/ops/hlist$RotateLeft;
  #29 = Utf8               (Ljava/lang/Object;)Ljava/lang/Object;
  #30 = NameAndType        #23:#29        // apply:(Ljava/lang/Object;)Ljava/lang/Object;
  #31 = InterfaceMethodref #18.#30        // shapeless/ops/hlist$RotateLeft.apply:(Ljava/lang/Object;)Ljava/lang/Object;
  #32 = Utf8               shapeless/HList
  #33 = Class              #32            // shapeless/HList
  #34 = Utf8               this
  #35 = Utf8               Lshapeless/ops/hlist$LowPriorityRotateRight$$anon$178;
  #36 = Utf8               Lshapeless/HList;
  #37 = Utf8               t
  #38 = NameAndType        #23:#24        // apply:(Lshapeless/HList;)Lshapeless/HList;
  #39 = Methodref          #2.#38         // shapeless/ops/hlist$LowPriorityRotateRight$$anon$178.apply:(Lshapeless/HList;)Lshapeless/HList;
  #40 = Utf8               Ljava/lang/Object;
  #41 = Utf8               <init>
  #42 = Utf8               (Lshapeless/ops/hlist$LowPriorityRotateRight;Lshapeless/ops/hlist$RotateLeft;)V
  #43 = Utf8               $outer
  #44 = Utf8               ()V
  #45 = NameAndType        #41:#44        // "<init>":()V
  #46 = Methodref          #5.#45         // java/lang/Object."<init>":()V
  #47 = Utf8               Lshapeless/ops/hlist$LowPriorityRotateRight;
  #48 = Utf8               Code
  #49 = Utf8               LineNumberTable
  #50 = Utf8               LocalVariableTable
  #51 = Utf8               Signature
  #52 = Utf8               MethodParameters
  #53 = Utf8               InnerClasses
  #54 = Utf8               EnclosingMethod
  #55 = Utf8               SourceFile
  #56 = Utf8               ScalaInlineInfo
  #57 = Utf8               Scala
{
  private final shapeless.ops.hlist$RotateLeft rotateLeft$1;
    descriptor: Lshapeless/ops/hlist$RotateLeft;
    flags: (0x0012) ACC_PRIVATE, ACC_FINAL

  public RotateLeftOut apply(L);
    descriptor: (Lshapeless/HList;)Lshapeless/HList;
    flags: (0x0001) ACC_PUBLIC
    Code:
      stack=2, locals=2, args_size=2
         0: aload_0
         1: getfield      #28                 // Field rotateLeft$1:Lshapeless/ops/hlist$RotateLeft;
         4: aload_1
         5: invokeinterface #31,  2           // InterfaceMethod shapeless/ops/hlist$RotateLeft.apply:(Ljava/lang/Object;)Ljava/lang/Object;
        10: checkcast     #33                 // class shapeless/HList
        13: areturn
      LineNumberTable:
        line 2663: 0
      LocalVariableTable:
        Start  Length  Slot  Name   Signature
            0      14     0  this   Lshapeless/ops/hlist$LowPriorityRotateRight$$anon$178;
            0      14     1     l   Lshapeless/HList;
    Signature: #25                          // (TL;)TRotateLeftOut;
    MethodParameters:
      Name                           Flags
      l                              final

  public java.lang.Object apply(java.lang.Object);
    descriptor: (Ljava/lang/Object;)Ljava/lang/Object;
    flags: (0x1041) ACC_PUBLIC, ACC_BRIDGE, ACC_SYNTHETIC
    Code:
      stack=2, locals=2, args_size=2
         0: aload_0
         1: aload_1
         2: checkcast     #33                 // class shapeless/HList
         5: invokevirtual #39                 // Method apply:(Lshapeless/HList;)Lshapeless/HList;
         8: areturn
      LineNumberTable:
        line 2660: 0
      LocalVariableTable:
        Start  Length  Slot  Name   Signature
            0       9     0  this   Lshapeless/ops/hlist$LowPriorityRotateRight$$anon$178;
            0       9     1     t   Ljava/lang/Object;
    MethodParameters:
      Name                           Flags
      t                              final

  public shapeless.ops.hlist$LowPriorityRotateRight$$anon$178(shapeless.ops.hlist$LowPriorityRotateRight, shapeless.ops.hlist$RotateLeft);
    descriptor: (Lshapeless/ops/hlist$LowPriorityRotateRight;Lshapeless/ops/hlist$RotateLeft;)V
    flags: (0x0001) ACC_PUBLIC
    Code:
      stack=2, locals=3, args_size=3
         0: aload_0
         1: aload_2
         2: putfield      #28                 // Field rotateLeft$1:Lshapeless/ops/hlist$RotateLeft;
         5: aload_0
         6: invokespecial #46                 // Method java/lang/Object."<init>":()V
         9: return
      LineNumberTable:
        line 2659: 0
        line 2660: 5
      LocalVariableTable:
        Start  Length  Slot  Name   Signature
            0      10     0  this   Lshapeless/ops/hlist$LowPriorityRotateRight$$anon$178;
            0      10     1 $outer   Lshapeless/ops/hlist$LowPriorityRotateRight;
            0      10     2 rotateLeft$1   Lshapeless/ops/hlist$RotateLeft;
    MethodParameters:
      Name                           Flags
      $outer                         final synthetic
      rotateLeft$1                   final
}
InnerClasses:
  public static #16= #10 of #15;          // LowPriorityRotateRight=class shapeless/ops/hlist$LowPriorityRotateRight of class shapeless/ops/hlist
  public final #2;                        // class shapeless/ops/hlist$LowPriorityRotateRight$$anon$178
  public static #19= #18 of #15;          // RotateLeft=class shapeless/ops/hlist$RotateLeft of class shapeless/ops/hlist
  public static #20= #7 of #15;           // RotateRight=class shapeless/ops/hlist$RotateRight of class shapeless/ops/hlist
EnclosingMethod: #10.#13                // shapeless.ops.hlist$LowPriorityRotateRight.hlistRotateRight
Signature: #3                           // Ljava/lang/Object;Lshapeless/ops/hlist$RotateRight<TL;TN;>;
SourceFile: "hlists.scala"
  ScalaInlineInfo: length = 0x13 (unknown attribute)
   01 01 00 03 00 29 00 2A 01 00 17 00 1D 01 00 17
   00 18 01
  Scala: length = 0x0 (unknown attribute)

