Classfile /Users/mw/Projects/slang-braindump/.jar/jar11/assemble/slang-braindump/assemble/content/shapeless/ops/hlist$ToTraversable$$anon$49.class
  Last modified May 29, 2022; size 4059 bytes
  SHA-256 checksum 45b1b55b81c6bf40f0fe7d8d304876de6126b61d7df7dd32261239a8bb5d28a8
  Compiled from "hlists.scala"
public final class shapeless.ops.hlist$ToTraversable$$anon$49 extends java.lang.Object implements shapeless.ops.hlist$ToTraversable<shapeless.$colon$colon<H1, shapeless.$colon$colon<H2, T>>, M>
  minor version: 0
  major version: 52
  flags: (0x0031) ACC_PUBLIC, ACC_FINAL, ACC_SUPER
  this_class: #2                          // shapeless/ops/hlist$ToTraversable$$anon$49
  super_class: #5                         // java/lang/Object
  interfaces: 1, fields: 3, methods: 8, attributes: 7
Constant pool:
    #1 = Utf8               shapeless/ops/hlist$ToTraversable$$anon$49
    #2 = Class              #1            // shapeless/ops/hlist$ToTraversable$$anon$49
    #3 = Utf8               Ljava/lang/Object;Lshapeless/ops/hlist$ToTraversable<Lshapeless/$colon$colon<TH1;Lshapeless/$colon$colon<TH2;TT;>;>;TM;>;
    #4 = Utf8               java/lang/Object
    #5 = Class              #4            // java/lang/Object
    #6 = Utf8               shapeless/ops/hlist$ToTraversable
    #7 = Class              #6            // shapeless/ops/hlist$ToTraversable
    #8 = Utf8               hlists.scala
    #9 = Utf8               shapeless/ops/hlist$ToTraversable$
   #10 = Class              #9            // shapeless/ops/hlist$ToTraversable$
   #11 = Utf8               hlistToTraversable
   #12 = Utf8               (Lshapeless/ops/hlist$ToTraversable;Lshapeless/Lub;Lscala/collection/Factory;)Lshapeless/ops/hlist$ToTraversable;
   #13 = NameAndType        #11:#12       // hlistToTraversable:(Lshapeless/ops/hlist$ToTraversable;Lshapeless/Lub;Lscala/collection/Factory;)Lshapeless/ops/hlist$ToTraversable;
   #14 = Utf8               java/lang/invoke/MethodHandles$Lookup
   #15 = Class              #14           // java/lang/invoke/MethodHandles$Lookup
   #16 = Utf8               java/lang/invoke/MethodHandles
   #17 = Class              #16           // java/lang/invoke/MethodHandles
   #18 = Utf8               Lookup
   #19 = Utf8               shapeless/ops/hlist
   #20 = Class              #19           // shapeless/ops/hlist
   #21 = Utf8               ToTraversable
   #22 = Utf8               ToTraversable$
   #23 = Utf8               cbf$3
   #24 = Utf8               Lscala/collection/Factory;
   #25 = Utf8               u$2
   #26 = Utf8               Lshapeless/Lub;
   #27 = Utf8               tttvs$1
   #28 = Utf8               Lshapeless/ops/hlist$ToTraversable;
   #29 = Utf8               apply
   #30 = Utf8               (Lshapeless/HList;)Ljava/lang/Object;
   #31 = Utf8               l
   #32 = Utf8               apply$
   #33 = Utf8               (Lshapeless/ops/hlist$ToTraversable;Lshapeless/HList;)Ljava/lang/Object;
   #34 = NameAndType        #32:#33       // apply$:(Lshapeless/ops/hlist$ToTraversable;Lshapeless/HList;)Ljava/lang/Object;
   #35 = InterfaceMethodref #7.#34        // shapeless/ops/hlist$ToTraversable.apply$:(Lshapeless/ops/hlist$ToTraversable;Lshapeless/HList;)Ljava/lang/Object;
   #36 = Utf8               this
   #37 = Utf8               Lshapeless/ops/hlist$ToTraversable$$anon$49;
   #38 = Utf8               Lshapeless/HList;
   #39 = Utf8               builder
   #40 = Utf8               ()Lscala/collection/mutable/Builder;
   #41 = Utf8               ()Lscala/collection/mutable/Builder<TLub0;TM;>;
   #42 = NameAndType        #23:#24       // cbf$3:Lscala/collection/Factory;
   #43 = Fieldref           #2.#42        // shapeless/ops/hlist$ToTraversable$$anon$49.cbf$3:Lscala/collection/Factory;
   #44 = Utf8               scala/collection/Factory
   #45 = Class              #44           // scala/collection/Factory
   #46 = Utf8               newBuilder
   #47 = NameAndType        #46:#40       // newBuilder:()Lscala/collection/mutable/Builder;
   #48 = InterfaceMethodref #45.#47       // scala/collection/Factory.newBuilder:()Lscala/collection/mutable/Builder;
   #49 = Utf8               append
   #50 = Utf8               (Lshapeless/$colon$colon;Lscala/collection/mutable/Builder;Lscala/Function1;)V
   #51 = Utf8               <LLub:Ljava/lang/Object;>(Lshapeless/$colon$colon<TH1;Lshapeless/$colon$colon<TH2;TT;>;>;Lscala/collection/mutable/Builder<TLLub;TM;>;Lscala/Function1<TLub0;TLLub;>;)V
   #52 = Utf8               b
   #53 = Utf8               f
   #54 = NameAndType        #25:#26       // u$2:Lshapeless/Lub;
   #55 = Fieldref           #2.#54        // shapeless/ops/hlist$ToTraversable$$anon$49.u$2:Lshapeless/Lub;
   #56 = Utf8               shapeless/$colon$colon
   #57 = Class              #56           // shapeless/$colon$colon
   #58 = Utf8               head
   #59 = Utf8               ()Ljava/lang/Object;
   #60 = NameAndType        #58:#59       // head:()Ljava/lang/Object;
   #61 = Methodref          #57.#60       // shapeless/$colon$colon.head:()Ljava/lang/Object;
   #62 = Utf8               shapeless/Lub
   #63 = Class              #62           // shapeless/Lub
   #64 = Utf8               left
   #65 = Utf8               (Ljava/lang/Object;)Ljava/lang/Object;
   #66 = NameAndType        #64:#65       // left:(Ljava/lang/Object;)Ljava/lang/Object;
   #67 = InterfaceMethodref #63.#66       // shapeless/Lub.left:(Ljava/lang/Object;)Ljava/lang/Object;
   #68 = Utf8               scala/Function1
   #69 = Class              #68           // scala/Function1
   #70 = NameAndType        #29:#65       // apply:(Ljava/lang/Object;)Ljava/lang/Object;
   #71 = InterfaceMethodref #69.#70       // scala/Function1.apply:(Ljava/lang/Object;)Ljava/lang/Object;
   #72 = Utf8               scala/collection/mutable/Builder
   #73 = Class              #72           // scala/collection/mutable/Builder
   #74 = Utf8               $plus$eq
   #75 = Utf8               (Ljava/lang/Object;)Lscala/collection/mutable/Growable;
   #76 = NameAndType        #74:#75       // $plus$eq:(Ljava/lang/Object;)Lscala/collection/mutable/Growable;
   #77 = InterfaceMethodref #73.#76       // scala/collection/mutable/Builder.$plus$eq:(Ljava/lang/Object;)Lscala/collection/mutable/Growable;
   #78 = NameAndType        #27:#28       // tttvs$1:Lshapeless/ops/hlist$ToTraversable;
   #79 = Fieldref           #2.#78        // shapeless/ops/hlist$ToTraversable$$anon$49.tttvs$1:Lshapeless/ops/hlist$ToTraversable;
   #80 = Utf8               tail
   #81 = Utf8               ()Lshapeless/HList;
   #82 = NameAndType        #80:#81       // tail:()Lshapeless/HList;
   #83 = Methodref          #57.#82       // shapeless/$colon$colon.tail:()Lshapeless/HList;
   #84 = MethodType         #65           //  (Ljava/lang/Object;)Ljava/lang/Object;
   #85 = Utf8               $anonfun$append$1
   #86 = Utf8               (Lshapeless/ops/hlist$ToTraversable$$anon$49;Ljava/lang/Object;)Ljava/lang/Object;
   #87 = NameAndType        #85:#86       // $anonfun$append$1:(Lshapeless/ops/hlist$ToTraversable$$anon$49;Ljava/lang/Object;)Ljava/lang/Object;
   #88 = Methodref          #2.#87        // shapeless/ops/hlist$ToTraversable$$anon$49.$anonfun$append$1:(Lshapeless/ops/hlist$ToTraversable$$anon$49;Ljava/lang/Object;)Ljava/lang/Object;
   #89 = MethodHandle       6:#88         // REF_invokeStatic shapeless/ops/hlist$ToTraversable$$anon$49.$anonfun$append$1:(Lshapeless/ops/hlist$ToTraversable$$anon$49;Ljava/lang/Object;)Ljava/lang/Object;
   #90 = Integer            1
   #91 = Utf8               java/lang/invoke/LambdaMetafactory
   #92 = Class              #91           // java/lang/invoke/LambdaMetafactory
   #93 = Utf8               altMetafactory
   #94 = Utf8               (Ljava/lang/invoke/MethodHandles$Lookup;Ljava/lang/String;Ljava/lang/invoke/MethodType;[Ljava/lang/Object;)Ljava/lang/invoke/CallSite;
   #95 = NameAndType        #93:#94       // altMetafactory:(Ljava/lang/invoke/MethodHandles$Lookup;Ljava/lang/String;Ljava/lang/invoke/MethodType;[Ljava/lang/Object;)Ljava/lang/invoke/CallSite;
   #96 = Methodref          #92.#95       // java/lang/invoke/LambdaMetafactory.altMetafactory:(Ljava/lang/invoke/MethodHandles$Lookup;Ljava/lang/String;Ljava/lang/invoke/MethodType;[Ljava/lang/Object;)Ljava/lang/invoke/CallSite;
   #97 = MethodHandle       6:#96         // REF_invokeStatic java/lang/invoke/LambdaMetafactory.altMetafactory:(Ljava/lang/invoke/MethodHandles$Lookup;Ljava/lang/String;Ljava/lang/invoke/MethodType;[Ljava/lang/Object;)Ljava/lang/invoke/CallSite;
   #98 = Utf8               (Lshapeless/ops/hlist$ToTraversable$$anon$49;)Lscala/Function1;
   #99 = NameAndType        #29:#98       // apply:(Lshapeless/ops/hlist$ToTraversable$$anon$49;)Lscala/Function1;
  #100 = InvokeDynamic      #0:#99        // #0:apply:(Lshapeless/ops/hlist$ToTraversable$$anon$49;)Lscala/Function1;
  #101 = Utf8               compose
  #102 = Utf8               (Lscala/Function1;)Lscala/Function1;
  #103 = NameAndType        #101:#102     // compose:(Lscala/Function1;)Lscala/Function1;
  #104 = InterfaceMethodref #69.#103      // scala/Function1.compose:(Lscala/Function1;)Lscala/Function1;
  #105 = Utf8               (Lshapeless/HList;Lscala/collection/mutable/Builder;Lscala/Function1;)V
  #106 = NameAndType        #49:#105      // append:(Lshapeless/HList;Lscala/collection/mutable/Builder;Lscala/Function1;)V
  #107 = InterfaceMethodref #7.#106       // shapeless/ops/hlist$ToTraversable.append:(Lshapeless/HList;Lscala/collection/mutable/Builder;Lscala/Function1;)V
  #108 = Utf8               Lshapeless/$colon$colon;
  #109 = Utf8               Lscala/collection/mutable/Builder;
  #110 = Utf8               Lscala/Function1;
  #111 = Utf8               t
  #112 = Utf8               shapeless/HList
  #113 = Class              #112          // shapeless/HList
  #114 = NameAndType        #29:#30       // apply:(Lshapeless/HList;)Ljava/lang/Object;
  #115 = Methodref          #2.#114       // shapeless/ops/hlist$ToTraversable$$anon$49.apply:(Lshapeless/HList;)Ljava/lang/Object;
  #116 = Utf8               Ljava/lang/Object;
  #117 = NameAndType        #49:#50       // append:(Lshapeless/$colon$colon;Lscala/collection/mutable/Builder;Lscala/Function1;)V
  #118 = Methodref          #2.#117       // shapeless/ops/hlist$ToTraversable$$anon$49.append:(Lshapeless/$colon$colon;Lscala/collection/mutable/Builder;Lscala/Function1;)V
  #119 = Utf8               $this
  #120 = Utf8               right
  #121 = NameAndType        #120:#65      // right:(Ljava/lang/Object;)Ljava/lang/Object;
  #122 = InterfaceMethodref #63.#121      // shapeless/Lub.right:(Ljava/lang/Object;)Ljava/lang/Object;
  #123 = Utf8               <init>
  #124 = Utf8               (Lscala/collection/Factory;Lshapeless/Lub;Lshapeless/ops/hlist$ToTraversable;)V
  #125 = Utf8               ()V
  #126 = NameAndType        #123:#125     // "<init>":()V
  #127 = Methodref          #5.#126       // java/lang/Object."<init>":()V
  #128 = Utf8               $init$
  #129 = Utf8               (Lshapeless/ops/hlist$ToTraversable;)V
  #130 = NameAndType        #128:#129     // $init$:(Lshapeless/ops/hlist$ToTraversable;)V
  #131 = InterfaceMethodref #7.#130       // shapeless/ops/hlist$ToTraversable.$init$:(Lshapeless/ops/hlist$ToTraversable;)V
  #132 = Utf8               $deserializeLambda$
  #133 = Utf8               (Ljava/lang/invoke/SerializedLambda;)Ljava/lang/Object;
  #134 = Utf8               scala/runtime/LambdaDeserialize
  #135 = Class              #134          // scala/runtime/LambdaDeserialize
  #136 = Utf8               bootstrap
  #137 = Utf8               (Ljava/lang/invoke/MethodHandles$Lookup;Ljava/lang/String;Ljava/lang/invoke/MethodType;[Ljava/lang/invoke/MethodHandle;)Ljava/lang/invoke/CallSite;
  #138 = NameAndType        #136:#137     // bootstrap:(Ljava/lang/invoke/MethodHandles$Lookup;Ljava/lang/String;Ljava/lang/invoke/MethodType;[Ljava/lang/invoke/MethodHandle;)Ljava/lang/invoke/CallSite;
  #139 = Methodref          #135.#138     // scala/runtime/LambdaDeserialize.bootstrap:(Ljava/lang/invoke/MethodHandles$Lookup;Ljava/lang/String;Ljava/lang/invoke/MethodType;[Ljava/lang/invoke/MethodHandle;)Ljava/lang/invoke/CallSite;
  #140 = MethodHandle       6:#139        // REF_invokeStatic scala/runtime/LambdaDeserialize.bootstrap:(Ljava/lang/invoke/MethodHandles$Lookup;Ljava/lang/String;Ljava/lang/invoke/MethodType;[Ljava/lang/invoke/MethodHandle;)Ljava/lang/invoke/CallSite;
  #141 = Utf8               lambdaDeserialize
  #142 = NameAndType        #141:#133     // lambdaDeserialize:(Ljava/lang/invoke/SerializedLambda;)Ljava/lang/Object;
  #143 = InvokeDynamic      #1:#142       // #1:lambdaDeserialize:(Ljava/lang/invoke/SerializedLambda;)Ljava/lang/Object;
  #144 = Utf8               Code
  #145 = Utf8               LineNumberTable
  #146 = Utf8               LocalVariableTable
  #147 = Utf8               MethodParameters
  #148 = Utf8               Signature
  #149 = Utf8               InnerClasses
  #150 = Utf8               EnclosingMethod
  #151 = Utf8               SourceFile
  #152 = Utf8               BootstrapMethods
  #153 = Utf8               ScalaInlineInfo
  #154 = Utf8               Scala
{
  private final scala.collection.Factory cbf$3;
    descriptor: Lscala/collection/Factory;
    flags: (0x0012) ACC_PRIVATE, ACC_FINAL

  private final shapeless.Lub u$2;
    descriptor: Lshapeless/Lub;
    flags: (0x0012) ACC_PRIVATE, ACC_FINAL

  private final shapeless.ops.hlist$ToTraversable tttvs$1;
    descriptor: Lshapeless/ops/hlist$ToTraversable;
    flags: (0x0012) ACC_PRIVATE, ACC_FINAL

  public java.lang.Object apply(shapeless.HList);
    descriptor: (Lshapeless/HList;)Ljava/lang/Object;
    flags: (0x0001) ACC_PUBLIC
    Code:
      stack=2, locals=2, args_size=2
         0: aload_0
         1: aload_1
         2: invokestatic  #35                 // InterfaceMethod shapeless/ops/hlist$ToTraversable.apply$:(Lshapeless/ops/hlist$ToTraversable;Lshapeless/HList;)Ljava/lang/Object;
         5: areturn
      LineNumberTable:
        line 631: 0
      LocalVariableTable:
        Start  Length  Slot  Name   Signature
            0       6     0  this   Lshapeless/ops/hlist$ToTraversable$$anon$49;
            0       6     1     l   Lshapeless/HList;
    MethodParameters:
      Name                           Flags
      l                              final

  public scala.collection.mutable.Builder<Lub0, M> builder();
    descriptor: ()Lscala/collection/mutable/Builder;
    flags: (0x0001) ACC_PUBLIC
    Code:
      stack=1, locals=1, args_size=1
         0: aload_0
         1: getfield      #43                 // Field cbf$3:Lscala/collection/Factory;
         4: invokeinterface #48,  1           // InterfaceMethod scala/collection/Factory.newBuilder:()Lscala/collection/mutable/Builder;
         9: areturn
      LineNumberTable:
        line 633: 0
      LocalVariableTable:
        Start  Length  Slot  Name   Signature
            0      10     0  this   Lshapeless/ops/hlist$ToTraversable$$anon$49;
    Signature: #41                          // ()Lscala/collection/mutable/Builder<TLub0;TM;>;

  public <LLub extends java.lang.Object> void append(shapeless.$colon$colon<H1, shapeless.$colon$colon<H2, T>>, scala.collection.mutable.Builder<LLub, M>, scala.Function1<Lub0, LLub>);
    descriptor: (Lshapeless/$colon$colon;Lscala/collection/mutable/Builder;Lscala/Function1;)V
    flags: (0x0001) ACC_PUBLIC
    Code:
      stack=5, locals=4, args_size=4
         0: aload_2
         1: aload_3
         2: aload_0
         3: getfield      #55                 // Field u$2:Lshapeless/Lub;
         6: aload_1
         7: invokevirtual #61                 // Method shapeless/$colon$colon.head:()Ljava/lang/Object;
        10: invokeinterface #67,  2           // InterfaceMethod shapeless/Lub.left:(Ljava/lang/Object;)Ljava/lang/Object;
        15: invokeinterface #71,  2           // InterfaceMethod scala/Function1.apply:(Ljava/lang/Object;)Ljava/lang/Object;
        20: invokeinterface #77,  2           // InterfaceMethod scala/collection/mutable/Builder.$plus$eq:(Ljava/lang/Object;)Lscala/collection/mutable/Growable;
        25: pop
        26: aload_0
        27: getfield      #79                 // Field tttvs$1:Lshapeless/ops/hlist$ToTraversable;
        30: aload_1
        31: invokevirtual #83                 // Method shapeless/$colon$colon.tail:()Lshapeless/HList;
        34: aload_2
        35: aload_3
        36: aload_0
        37: invokedynamic #100,  0            // InvokeDynamic #0:apply:(Lshapeless/ops/hlist$ToTraversable$$anon$49;)Lscala/Function1;
        42: invokeinterface #104,  2          // InterfaceMethod scala/Function1.compose:(Lscala/Function1;)Lscala/Function1;
        47: invokeinterface #107,  4          // InterfaceMethod shapeless/ops/hlist$ToTraversable.append:(Lshapeless/HList;Lscala/collection/mutable/Builder;Lscala/Function1;)V
        52: return
      LineNumberTable:
        line 635: 0
      LocalVariableTable:
        Start  Length  Slot  Name   Signature
            0      53     0  this   Lshapeless/ops/hlist$ToTraversable$$anon$49;
            0      53     1     l   Lshapeless/$colon$colon;
            0      53     2     b   Lscala/collection/mutable/Builder;
            0      53     3     f   Lscala/Function1;
    Signature: #51                          // <LLub:Ljava/lang/Object;>(Lshapeless/$colon$colon<TH1;Lshapeless/$colon$colon<TH2;TT;>;>;Lscala/collection/mutable/Builder<TLLub;TM;>;Lscala/Function1<TLub0;TLLub;>;)V
    MethodParameters:
      Name                           Flags
      l                              final
      b                              final
      f                              final

  public java.lang.Object apply(java.lang.Object);
    descriptor: (Ljava/lang/Object;)Ljava/lang/Object;
    flags: (0x1041) ACC_PUBLIC, ACC_BRIDGE, ACC_SYNTHETIC
    Code:
      stack=2, locals=2, args_size=2
         0: aload_0
         1: aload_1
         2: checkcast     #113                // class shapeless/HList
         5: invokevirtual #115                // Method apply:(Lshapeless/HList;)Ljava/lang/Object;
         8: areturn
      LineNumberTable:
        line 631: 0
      LocalVariableTable:
        Start  Length  Slot  Name   Signature
            0       9     0  this   Lshapeless/ops/hlist$ToTraversable$$anon$49;
            0       9     1     t   Ljava/lang/Object;
    MethodParameters:
      Name                           Flags
      t                              final

  public void append(shapeless.HList, scala.collection.mutable.Builder, scala.Function1);
    descriptor: (Lshapeless/HList;Lscala/collection/mutable/Builder;Lscala/Function1;)V
    flags: (0x1041) ACC_PUBLIC, ACC_BRIDGE, ACC_SYNTHETIC
    Code:
      stack=4, locals=4, args_size=4
         0: aload_0
         1: aload_1
         2: checkcast     #57                 // class shapeless/$colon$colon
         5: aload_2
         6: aload_3
         7: invokevirtual #118                // Method append:(Lshapeless/$colon$colon;Lscala/collection/mutable/Builder;Lscala/Function1;)V
        10: return
      LineNumberTable:
        line 631: 0
      LocalVariableTable:
        Start  Length  Slot  Name   Signature
            0      11     0  this   Lshapeless/ops/hlist$ToTraversable$$anon$49;
            0      11     1     l   Lshapeless/HList;
            0      11     2     b   Lscala/collection/mutable/Builder;
            0      11     3     f   Lscala/Function1;
    MethodParameters:
      Name                           Flags
      l                              final
      b                              final
      f                              final

  public static final java.lang.Object $anonfun$append$1(shapeless.ops.hlist$ToTraversable$$anon$49, java.lang.Object);
    descriptor: (Lshapeless/ops/hlist$ToTraversable$$anon$49;Ljava/lang/Object;)Ljava/lang/Object;
    flags: (0x1019) ACC_PUBLIC, ACC_STATIC, ACC_FINAL, ACC_SYNTHETIC
    Code:
      stack=2, locals=2, args_size=2
         0: aload_0
         1: getfield      #55                 // Field u$2:Lshapeless/Lub;
         4: aload_1
         5: invokeinterface #122,  2          // InterfaceMethod shapeless/Lub.right:(Ljava/lang/Object;)Ljava/lang/Object;
        10: areturn
      LineNumberTable:
        line 635: 0
      LocalVariableTable:
        Start  Length  Slot  Name   Signature
            0      11     0 $this   Lshapeless/ops/hlist$ToTraversable$$anon$49;
            0      11     1     b   Ljava/lang/Object;
    MethodParameters:
      Name                           Flags
      $this                          final synthetic
      b                              final

  public shapeless.ops.hlist$ToTraversable$$anon$49(scala.collection.Factory, shapeless.Lub, shapeless.ops.hlist$ToTraversable);
    descriptor: (Lscala/collection/Factory;Lshapeless/Lub;Lshapeless/ops/hlist$ToTraversable;)V
    flags: (0x0001) ACC_PUBLIC
    Code:
      stack=2, locals=4, args_size=4
         0: aload_0
         1: aload_1
         2: putfield      #43                 // Field cbf$3:Lscala/collection/Factory;
         5: aload_0
         6: aload_2
         7: putfield      #55                 // Field u$2:Lshapeless/Lub;
        10: aload_0
        11: aload_3
        12: putfield      #79                 // Field tttvs$1:Lshapeless/ops/hlist$ToTraversable;
        15: aload_0
        16: invokespecial #127                // Method java/lang/Object."<init>":()V
        19: aload_0
        20: invokestatic  #131                // InterfaceMethod shapeless/ops/hlist$ToTraversable.$init$:(Lshapeless/ops/hlist$ToTraversable;)V
        23: return
      LineNumberTable:
        line 630: 0
        line 629: 5
        line 628: 10
        line 631: 15
      LocalVariableTable:
        Start  Length  Slot  Name   Signature
            0      24     0  this   Lshapeless/ops/hlist$ToTraversable$$anon$49;
            0      24     1 cbf$3   Lscala/collection/Factory;
            0      24     2   u$2   Lshapeless/Lub;
            0      24     3 tttvs$1   Lshapeless/ops/hlist$ToTraversable;
    MethodParameters:
      Name                           Flags
      cbf$3                          final
      u$2                            final
      tttvs$1                        final

  private static java.lang.Object $deserializeLambda$(java.lang.invoke.SerializedLambda);
    descriptor: (Ljava/lang/invoke/SerializedLambda;)Ljava/lang/Object;
    flags: (0x100a) ACC_PRIVATE, ACC_STATIC, ACC_SYNTHETIC
    Code:
      stack=1, locals=1, args_size=1
         0: aload_0
         1: invokedynamic #143,  0            // InvokeDynamic #1:lambdaDeserialize:(Ljava/lang/invoke/SerializedLambda;)Ljava/lang/Object;
         6: areturn
}
InnerClasses:
  public static final #18= #15 of #17;    // Lookup=class java/lang/invoke/MethodHandles$Lookup of class java/lang/invoke/MethodHandles
  public static #21= #7 of #20;           // ToTraversable=class shapeless/ops/hlist$ToTraversable of class shapeless/ops/hlist
  public static #22= #10 of #20;          // ToTraversable$=class shapeless/ops/hlist$ToTraversable$ of class shapeless/ops/hlist
  public final #2;                        // class shapeless/ops/hlist$ToTraversable$$anon$49
EnclosingMethod: #10.#13                // shapeless.ops.hlist$ToTraversable$.hlistToTraversable
Signature: #3                           // Ljava/lang/Object;Lshapeless/ops/hlist$ToTraversable<Lshapeless/$colon$colon<TH1;Lshapeless/$colon$colon<TH2;TT;>;>;TM;>;
SourceFile: "hlists.scala"
BootstrapMethods:
  0: #97 REF_invokeStatic java/lang/invoke/LambdaMetafactory.altMetafactory:(Ljava/lang/invoke/MethodHandles$Lookup;Ljava/lang/String;Ljava/lang/invoke/MethodType;[Ljava/lang/Object;)Ljava/lang/invoke/CallSite;
    Method arguments:
      #84 (Ljava/lang/Object;)Ljava/lang/Object;
      #89 REF_invokeStatic shapeless/ops/hlist$ToTraversable$$anon$49.$anonfun$append$1:(Lshapeless/ops/hlist$ToTraversable$$anon$49;Ljava/lang/Object;)Ljava/lang/Object;
      #84 (Ljava/lang/Object;)Ljava/lang/Object;
      #90 1
  1: #140 REF_invokeStatic scala/runtime/LambdaDeserialize.bootstrap:(Ljava/lang/invoke/MethodHandles$Lookup;Ljava/lang/String;Ljava/lang/invoke/MethodType;[Ljava/lang/invoke/MethodHandle;)Ljava/lang/invoke/CallSite;
    Method arguments:
      #89 REF_invokeStatic shapeless/ops/hlist$ToTraversable$$anon$49.$anonfun$append$1:(Lshapeless/ops/hlist$ToTraversable$$anon$49;Ljava/lang/Object;)Ljava/lang/Object;
  ScalaInlineInfo: length = 0x27 (unknown attribute)
   01 01 00 07 00 55 00 56 01 00 7B 00 7C 01 00 31
   00 32 01 00 31 00 69 01 00 1D 00 41 01 00 1D 00
   1E 01 00 27 00 28 01
  Scala: length = 0x0 (unknown attribute)

