Classfile /Users/mw/Projects/slang-braindump/.jar/jar11/assemble/slang-braindump/assemble/content/shapeless/ops/hlist$Replacer$.class
  Last modified May 29, 2022; size 1919 bytes
  SHA-256 checksum dc24b768869cebacc67a8483d75f662cf9d8a24ff32280b3fdf6dff14f726cea
  Compiled from "hlists.scala"
public class shapeless.ops.hlist$Replacer$ implements java.io.Serializable
  minor version: 0
  major version: 52
  flags: (0x0021) ACC_PUBLIC, ACC_SUPER
  this_class: #2                          // shapeless/ops/hlist$Replacer$
  super_class: #4                         // java/lang/Object
  interfaces: 1, fields: 1, methods: 6, attributes: 4
Constant pool:
   #1 = Utf8               shapeless/ops/hlist$Replacer$
   #2 = Class              #1             // shapeless/ops/hlist$Replacer$
   #3 = Utf8               java/lang/Object
   #4 = Class              #3             // java/lang/Object
   #5 = Utf8               java/io/Serializable
   #6 = Class              #5             // java/io/Serializable
   #7 = Utf8               hlists.scala
   #8 = Utf8               shapeless/ops/hlist$Replacer
   #9 = Class              #8             // shapeless/ops/hlist$Replacer
  #10 = Utf8               shapeless/ops/hlist
  #11 = Class              #10            // shapeless/ops/hlist
  #12 = Utf8               Replacer
  #13 = Utf8               Replacer$
  #14 = Utf8               shapeless/ops/hlist$Replacer$$anon$95
  #15 = Class              #14            // shapeless/ops/hlist$Replacer$$anon$95
  #16 = Utf8               shapeless/ops/hlist$Replacer$$anon$96
  #17 = Class              #16            // shapeless/ops/hlist$Replacer$$anon$96
  #18 = Utf8               MODULE$
  #19 = Utf8               Lshapeless/ops/hlist$Replacer$;
  #20 = Utf8               <clinit>
  #21 = Utf8               ()V
  #22 = Utf8               <init>
  #23 = NameAndType        #22:#21        // "<init>":()V
  #24 = Methodref          #2.#23         // shapeless/ops/hlist$Replacer$."<init>":()V
  #25 = NameAndType        #18:#19        // MODULE$:Lshapeless/ops/hlist$Replacer$;
  #26 = Fieldref           #2.#25         // shapeless/ops/hlist$Replacer$.MODULE$:Lshapeless/ops/hlist$Replacer$;
  #27 = Utf8               apply
  #28 = Utf8               (Lshapeless/ops/hlist$Replacer;)Lshapeless/ops/hlist$Replacer;
  #29 = Utf8               <L::Lshapeless/HList;U:Ljava/lang/Object;V:Ljava/lang/Object;>(Lshapeless/ops/hlist$Replacer<TL;TU;TV;>;)Lshapeless/ops/hlist$Replacer<TL;TU;TV;>;
  #30 = Utf8               replacer
  #31 = Utf8               this
  #32 = Utf8               Lshapeless/ops/hlist$Replacer;
  #33 = Utf8               hlistReplacer1
  #34 = Utf8               ()Lshapeless/ops/hlist$Replacer;
  #35 = Utf8               <T::Lshapeless/HList;U:Ljava/lang/Object;V:Ljava/lang/Object;>()Lshapeless/ops/hlist$Replacer<Lshapeless/$colon$colon<TU;TT;>;TU;TV;>;
  #36 = Methodref          #15.#23        // shapeless/ops/hlist$Replacer$$anon$95."<init>":()V
  #37 = Utf8               hlistReplacer2
  #38 = Utf8               <H:Ljava/lang/Object;T::Lshapeless/HList;U:Ljava/lang/Object;V:Ljava/lang/Object;OutT::Lshapeless/HList;>(Lshapeless/ops/hlist$Replacer<TT;TU;TV;>;)Lshapeless/ops/hlist$Replacer<Lshapeless/$colon$colon<TH;TT;>;TU;TV;>;
  #39 = Utf8               ut
  #40 = Utf8               (Lshapeless/ops/hlist$Replacer;)V
  #41 = NameAndType        #22:#40        // "<init>":(Lshapeless/ops/hlist$Replacer;)V
  #42 = Methodref          #17.#41        // shapeless/ops/hlist$Replacer$$anon$96."<init>":(Lshapeless/ops/hlist$Replacer;)V
  #43 = Utf8               writeReplace
  #44 = Utf8               ()Ljava/lang/Object;
  #45 = Utf8               scala/runtime/ModuleSerializationProxy
  #46 = Class              #45            // scala/runtime/ModuleSerializationProxy
  #47 = Utf8               (Ljava/lang/Class;)V
  #48 = NameAndType        #22:#47        // "<init>":(Ljava/lang/Class;)V
  #49 = Methodref          #46.#48        // scala/runtime/ModuleSerializationProxy."<init>":(Ljava/lang/Class;)V
  #50 = Methodref          #4.#23         // java/lang/Object."<init>":()V
  #51 = Utf8               Code
  #52 = Utf8               LineNumberTable
  #53 = Utf8               LocalVariableTable
  #54 = Utf8               Signature
  #55 = Utf8               MethodParameters
  #56 = Utf8               InnerClasses
  #57 = Utf8               SourceFile
  #58 = Utf8               ScalaInlineInfo
  #59 = Utf8               Scala
{
  public static final shapeless.ops.hlist$Replacer$ MODULE$;
    descriptor: Lshapeless/ops/hlist$Replacer$;
    flags: (0x0019) ACC_PUBLIC, ACC_STATIC, ACC_FINAL

  public static {};
    descriptor: ()V
    flags: (0x0009) ACC_PUBLIC, ACC_STATIC
    Code:
      stack=2, locals=0, args_size=0
         0: new           #2                  // class shapeless/ops/hlist$Replacer$
         3: dup
         4: invokespecial #24                 // Method "<init>":()V
         7: putstatic     #26                 // Field MODULE$:Lshapeless/ops/hlist$Replacer$;
        10: return
      LineNumberTable:
        line 1422: 0

  public <L extends shapeless.HList, U extends java.lang.Object, V extends java.lang.Object> shapeless.ops.hlist$Replacer<L, U, V> apply(shapeless.ops.hlist$Replacer<L, U, V>);
    descriptor: (Lshapeless/ops/hlist$Replacer;)Lshapeless/ops/hlist$Replacer;
    flags: (0x0001) ACC_PUBLIC
    Code:
      stack=1, locals=2, args_size=2
         0: aload_1
         1: areturn
      LineNumberTable:
        line 1423: 0
      LocalVariableTable:
        Start  Length  Slot  Name   Signature
            0       2     0  this   Lshapeless/ops/hlist$Replacer$;
            0       2     1 replacer   Lshapeless/ops/hlist$Replacer;
    Signature: #29                          // <L::Lshapeless/HList;U:Ljava/lang/Object;V:Ljava/lang/Object;>(Lshapeless/ops/hlist$Replacer<TL;TU;TV;>;)Lshapeless/ops/hlist$Replacer<TL;TU;TV;>;
    MethodParameters:
      Name                           Flags
      replacer                       final

  public <T extends shapeless.HList, U extends java.lang.Object, V extends java.lang.Object> shapeless.ops.hlist$Replacer<shapeless.$colon$colon<U, T>, U, V> hlistReplacer1();
    descriptor: ()Lshapeless/ops/hlist$Replacer;
    flags: (0x0001) ACC_PUBLIC
    Code:
      stack=2, locals=1, args_size=1
         0: new           #15                 // class shapeless/ops/hlist$Replacer$$anon$95
         3: dup
         4: invokespecial #36                 // Method shapeless/ops/hlist$Replacer$$anon$95."<init>":()V
         7: areturn
      LineNumberTable:
        line 1428: 0
      LocalVariableTable:
        Start  Length  Slot  Name   Signature
            0       8     0  this   Lshapeless/ops/hlist$Replacer$;
    Signature: #35                          // <T::Lshapeless/HList;U:Ljava/lang/Object;V:Ljava/lang/Object;>()Lshapeless/ops/hlist$Replacer<Lshapeless/$colon$colon<TU;TT;>;TU;TV;>;

  public <H extends java.lang.Object, T extends shapeless.HList, U extends java.lang.Object, V extends java.lang.Object, OutT extends shapeless.HList> shapeless.ops.hlist$Replacer<shapeless.$colon$colon<H, T>, U, V> hlistReplacer2(shapeless.ops.hlist$Replacer<T, U, V>);
    descriptor: (Lshapeless/ops/hlist$Replacer;)Lshapeless/ops/hlist$Replacer;
    flags: (0x0001) ACC_PUBLIC
    Code:
      stack=3, locals=2, args_size=2
         0: new           #17                 // class shapeless/ops/hlist$Replacer$$anon$96
         3: dup
         4: aload_1
         5: invokespecial #42                 // Method shapeless/ops/hlist$Replacer$$anon$96."<init>":(Lshapeless/ops/hlist$Replacer;)V
         8: areturn
      LineNumberTable:
        line 1435: 0
      LocalVariableTable:
        Start  Length  Slot  Name   Signature
            0       9     0  this   Lshapeless/ops/hlist$Replacer$;
            0       9     1    ut   Lshapeless/ops/hlist$Replacer;
    Signature: #38                          // <H:Ljava/lang/Object;T::Lshapeless/HList;U:Ljava/lang/Object;V:Ljava/lang/Object;OutT::Lshapeless/HList;>(Lshapeless/ops/hlist$Replacer<TT;TU;TV;>;)Lshapeless/ops/hlist$Replacer<Lshapeless/$colon$colon<TH;TT;>;TU;TV;>;
    MethodParameters:
      Name                           Flags
      ut                             final

  private java.lang.Object writeReplace();
    descriptor: ()Ljava/lang/Object;
    flags: (0x0002) ACC_PRIVATE
    Code:
      stack=3, locals=1, args_size=1
         0: new           #46                 // class scala/runtime/ModuleSerializationProxy
         3: dup
         4: ldc           #2                  // class shapeless/ops/hlist$Replacer$
         6: invokespecial #49                 // Method scala/runtime/ModuleSerializationProxy."<init>":(Ljava/lang/Class;)V
         9: areturn
      LineNumberTable:
        line 1422: 0
      LocalVariableTable:
        Start  Length  Slot  Name   Signature
            0      10     0  this   Lshapeless/ops/hlist$Replacer$;

  public shapeless.ops.hlist$Replacer$();
    descriptor: ()V
    flags: (0x0001) ACC_PUBLIC
    Code:
      stack=1, locals=1, args_size=1
         0: aload_0
         1: invokespecial #50                 // Method java/lang/Object."<init>":()V
         4: return
      LineNumberTable:
        line 1451: 0
        line 1422: 4
      LocalVariableTable:
        Start  Length  Slot  Name   Signature
            0       5     0  this   Lshapeless/ops/hlist$Replacer$;
}
InnerClasses:
  public static #12= #9 of #11;           // Replacer=class shapeless/ops/hlist$Replacer of class shapeless/ops/hlist
  public static #13= #2 of #11;           // Replacer$=class shapeless/ops/hlist$Replacer$ of class shapeless/ops/hlist
  public final #15;                       // class shapeless/ops/hlist$Replacer$$anon$95
  public final #17;                       // class shapeless/ops/hlist$Replacer$$anon$96
SourceFile: "hlists.scala"
  ScalaInlineInfo: length = 0x1D (unknown attribute)
   01 01 00 05 00 16 00 15 01 00 1B 00 1C 01 00 21
   00 22 01 00 25 00 1C 01 00 2B 00 2C 01
  Scala: length = 0x0 (unknown attribute)

