Classfile /Users/mw/Projects/slang-braindump/.jar/jar11/assemble/slang-braindump/assemble/content/shapeless/ops/hlist$FlatMapper$$anon$29.class
  Last modified May 29, 2022; size 2136 bytes
  SHA-256 checksum 0305b1fa7d990506e439f1822a8633d97c9f20c0308bcc6a615052312e48ff94
  Compiled from "hlists.scala"
public final class shapeless.ops.hlist$FlatMapper$$anon$29 extends java.lang.Object implements shapeless.ops.hlist$FlatMapper<HF, shapeless.$colon$colon<InH, InT>>
  minor version: 0
  major version: 52
  flags: (0x0031) ACC_PUBLIC, ACC_FINAL, ACC_SUPER
  this_class: #2                          // shapeless/ops/hlist$FlatMapper$$anon$29
  super_class: #5                         // java/lang/Object
  interfaces: 1, fields: 3, methods: 3, attributes: 6
Constant pool:
   #1 = Utf8               shapeless/ops/hlist$FlatMapper$$anon$29
   #2 = Class              #1             // shapeless/ops/hlist$FlatMapper$$anon$29
   #3 = Utf8               Ljava/lang/Object;Lshapeless/ops/hlist$FlatMapper<THF;Lshapeless/$colon$colon<TInH;TInT;>;>;
   #4 = Utf8               java/lang/Object
   #5 = Class              #4             // java/lang/Object
   #6 = Utf8               shapeless/ops/hlist$FlatMapper
   #7 = Class              #6             // shapeless/ops/hlist$FlatMapper
   #8 = Utf8               hlists.scala
   #9 = Utf8               shapeless/ops/hlist$FlatMapper$
  #10 = Class              #9             // shapeless/ops/hlist$FlatMapper$
  #11 = Utf8               hlistFlatMapper1
  #12 = Utf8               (Lshapeless/PolyDefns$Case;Lshapeless/ops/hlist$FlatMapper;Lshapeless/ops/hlist$Prepend;)Lshapeless/ops/hlist$FlatMapper;
  #13 = NameAndType        #11:#12        // hlistFlatMapper1:(Lshapeless/PolyDefns$Case;Lshapeless/ops/hlist$FlatMapper;Lshapeless/ops/hlist$Prepend;)Lshapeless/ops/hlist$FlatMapper;
  #14 = Utf8               shapeless/PolyDefns$Case
  #15 = Class              #14            // shapeless/PolyDefns$Case
  #16 = Utf8               shapeless/PolyDefns
  #17 = Class              #16            // shapeless/PolyDefns
  #18 = Utf8               Case
  #19 = Utf8               shapeless/ops/hlist
  #20 = Class              #19            // shapeless/ops/hlist
  #21 = Utf8               FlatMapper
  #22 = Utf8               FlatMapper$
  #23 = Utf8               shapeless/ops/hlist$Prepend
  #24 = Class              #23            // shapeless/ops/hlist$Prepend
  #25 = Utf8               Prepend
  #26 = Utf8               prepend$1
  #27 = Utf8               Lshapeless/ops/hlist$Prepend;
  #28 = Utf8               hc$2
  #29 = Utf8               Lshapeless/PolyDefns$Case;
  #30 = Utf8               mt$2
  #31 = Utf8               Lshapeless/ops/hlist$FlatMapper;
  #32 = Utf8               apply
  #33 = Utf8               (Lshapeless/$colon$colon;)Lshapeless/HList;
  #34 = Utf8               (Lshapeless/$colon$colon<TInH;TInT;>;)TOut0;
  #35 = Utf8               l
  #36 = NameAndType        #26:#27        // prepend$1:Lshapeless/ops/hlist$Prepend;
  #37 = Fieldref           #2.#36         // shapeless/ops/hlist$FlatMapper$$anon$29.prepend$1:Lshapeless/ops/hlist$Prepend;
  #38 = NameAndType        #28:#29        // hc$2:Lshapeless/PolyDefns$Case;
  #39 = Fieldref           #2.#38         // shapeless/ops/hlist$FlatMapper$$anon$29.hc$2:Lshapeless/PolyDefns$Case;
  #40 = Utf8               shapeless/$colon$colon
  #41 = Class              #40            // shapeless/$colon$colon
  #42 = Utf8               head
  #43 = Utf8               ()Ljava/lang/Object;
  #44 = NameAndType        #42:#43        // head:()Ljava/lang/Object;
  #45 = Methodref          #41.#44        // shapeless/$colon$colon.head:()Ljava/lang/Object;
  #46 = Utf8               scala/$less$colon$less$
  #47 = Class              #46            // scala/$less$colon$less$
  #48 = Utf8               MODULE$
  #49 = Utf8               Lscala/$less$colon$less$;
  #50 = NameAndType        #48:#49        // MODULE$:Lscala/$less$colon$less$;
  #51 = Fieldref           #47.#50        // scala/$less$colon$less$.MODULE$:Lscala/$less$colon$less$;
  #52 = Utf8               refl
  #53 = Utf8               ()Lscala/$eq$colon$eq;
  #54 = NameAndType        #52:#53        // refl:()Lscala/$eq$colon$eq;
  #55 = Methodref          #47.#54        // scala/$less$colon$less$.refl:()Lscala/$eq$colon$eq;
  #56 = Utf8               (Ljava/lang/Object;Lscala/$eq$colon$eq;)Ljava/lang/Object;
  #57 = NameAndType        #32:#56        // apply:(Ljava/lang/Object;Lscala/$eq$colon$eq;)Ljava/lang/Object;
  #58 = Methodref          #15.#57        // shapeless/PolyDefns$Case.apply:(Ljava/lang/Object;Lscala/$eq$colon$eq;)Ljava/lang/Object;
  #59 = NameAndType        #30:#31        // mt$2:Lshapeless/ops/hlist$FlatMapper;
  #60 = Fieldref           #2.#59         // shapeless/ops/hlist$FlatMapper$$anon$29.mt$2:Lshapeless/ops/hlist$FlatMapper;
  #61 = Utf8               tail
  #62 = Utf8               ()Lshapeless/HList;
  #63 = NameAndType        #61:#62        // tail:()Lshapeless/HList;
  #64 = Methodref          #41.#63        // shapeless/$colon$colon.tail:()Lshapeless/HList;
  #65 = Utf8               (Ljava/lang/Object;)Ljava/lang/Object;
  #66 = NameAndType        #32:#65        // apply:(Ljava/lang/Object;)Ljava/lang/Object;
  #67 = InterfaceMethodref #7.#66         // shapeless/ops/hlist$FlatMapper.apply:(Ljava/lang/Object;)Ljava/lang/Object;
  #68 = Utf8               (Ljava/lang/Object;Ljava/lang/Object;)Ljava/lang/Object;
  #69 = NameAndType        #32:#68        // apply:(Ljava/lang/Object;Ljava/lang/Object;)Ljava/lang/Object;
  #70 = InterfaceMethodref #24.#69        // shapeless/ops/hlist$Prepend.apply:(Ljava/lang/Object;Ljava/lang/Object;)Ljava/lang/Object;
  #71 = Utf8               shapeless/HList
  #72 = Class              #71            // shapeless/HList
  #73 = Utf8               this
  #74 = Utf8               Lshapeless/ops/hlist$FlatMapper$$anon$29;
  #75 = Utf8               Lshapeless/$colon$colon;
  #76 = Utf8               t
  #77 = NameAndType        #32:#33        // apply:(Lshapeless/$colon$colon;)Lshapeless/HList;
  #78 = Methodref          #2.#77         // shapeless/ops/hlist$FlatMapper$$anon$29.apply:(Lshapeless/$colon$colon;)Lshapeless/HList;
  #79 = Utf8               Ljava/lang/Object;
  #80 = Utf8               <init>
  #81 = Utf8               (Lshapeless/ops/hlist$Prepend;Lshapeless/PolyDefns$Case;Lshapeless/ops/hlist$FlatMapper;)V
  #82 = Utf8               ()V
  #83 = NameAndType        #80:#82        // "<init>":()V
  #84 = Methodref          #5.#83         // java/lang/Object."<init>":()V
  #85 = Utf8               Code
  #86 = Utf8               LineNumberTable
  #87 = Utf8               LocalVariableTable
  #88 = Utf8               Signature
  #89 = Utf8               MethodParameters
  #90 = Utf8               InnerClasses
  #91 = Utf8               EnclosingMethod
  #92 = Utf8               SourceFile
  #93 = Utf8               ScalaInlineInfo
  #94 = Utf8               Scala
{
  private final shapeless.ops.hlist$Prepend prepend$1;
    descriptor: Lshapeless/ops/hlist$Prepend;
    flags: (0x0012) ACC_PRIVATE, ACC_FINAL

  private final shapeless.PolyDefns$Case hc$2;
    descriptor: Lshapeless/PolyDefns$Case;
    flags: (0x0012) ACC_PRIVATE, ACC_FINAL

  private final shapeless.ops.hlist$FlatMapper mt$2;
    descriptor: Lshapeless/ops/hlist$FlatMapper;
    flags: (0x0012) ACC_PRIVATE, ACC_FINAL

  public Out0 apply(shapeless.$colon$colon<InH, InT>);
    descriptor: (Lshapeless/$colon$colon;)Lshapeless/HList;
    flags: (0x0001) ACC_PUBLIC
    Code:
      stack=4, locals=2, args_size=2
         0: aload_0
         1: getfield      #37                 // Field prepend$1:Lshapeless/ops/hlist$Prepend;
         4: aload_0
         5: getfield      #39                 // Field hc$2:Lshapeless/PolyDefns$Case;
         8: aload_1
         9: invokevirtual #45                 // Method shapeless/$colon$colon.head:()Ljava/lang/Object;
        12: getstatic     #51                 // Field scala/$less$colon$less$.MODULE$:Lscala/$less$colon$less$;
        15: invokevirtual #55                 // Method scala/$less$colon$less$.refl:()Lscala/$eq$colon$eq;
        18: invokevirtual #58                 // Method shapeless/PolyDefns$Case.apply:(Ljava/lang/Object;Lscala/$eq$colon$eq;)Ljava/lang/Object;
        21: aload_0
        22: getfield      #60                 // Field mt$2:Lshapeless/ops/hlist$FlatMapper;
        25: aload_1
        26: invokevirtual #64                 // Method shapeless/$colon$colon.tail:()Lshapeless/HList;
        29: invokeinterface #67,  2           // InterfaceMethod shapeless/ops/hlist$FlatMapper.apply:(Ljava/lang/Object;)Ljava/lang/Object;
        34: invokeinterface #70,  3           // InterfaceMethod shapeless/ops/hlist$Prepend.apply:(Ljava/lang/Object;Ljava/lang/Object;)Ljava/lang/Object;
        39: checkcast     #72                 // class shapeless/HList
        42: areturn
      LineNumberTable:
        line 359: 0
      LocalVariableTable:
        Start  Length  Slot  Name   Signature
            0      43     0  this   Lshapeless/ops/hlist$FlatMapper$$anon$29;
            0      43     1     l   Lshapeless/$colon$colon;
    Signature: #34                          // (Lshapeless/$colon$colon<TInH;TInT;>;)TOut0;
    MethodParameters:
      Name                           Flags
      l                              final

  public java.lang.Object apply(java.lang.Object);
    descriptor: (Ljava/lang/Object;)Ljava/lang/Object;
    flags: (0x1041) ACC_PUBLIC, ACC_BRIDGE, ACC_SYNTHETIC
    Code:
      stack=2, locals=2, args_size=2
         0: aload_0
         1: aload_1
         2: checkcast     #41                 // class shapeless/$colon$colon
         5: invokevirtual #78                 // Method apply:(Lshapeless/$colon$colon;)Lshapeless/HList;
         8: areturn
      LineNumberTable:
        line 357: 0
      LocalVariableTable:
        Start  Length  Slot  Name   Signature
            0       9     0  this   Lshapeless/ops/hlist$FlatMapper$$anon$29;
            0       9     1     t   Ljava/lang/Object;
    MethodParameters:
      Name                           Flags
      t                              final

  public shapeless.ops.hlist$FlatMapper$$anon$29(shapeless.ops.hlist$Prepend, shapeless.PolyDefns$Case, shapeless.ops.hlist$FlatMapper);
    descriptor: (Lshapeless/ops/hlist$Prepend;Lshapeless/PolyDefns$Case;Lshapeless/ops/hlist$FlatMapper;)V
    flags: (0x0001) ACC_PUBLIC
    Code:
      stack=2, locals=4, args_size=4
         0: aload_0
         1: aload_1
         2: putfield      #37                 // Field prepend$1:Lshapeless/ops/hlist$Prepend;
         5: aload_0
         6: aload_2
         7: putfield      #39                 // Field hc$2:Lshapeless/PolyDefns$Case;
        10: aload_0
        11: aload_3
        12: putfield      #60                 // Field mt$2:Lshapeless/ops/hlist$FlatMapper;
        15: aload_0
        16: invokespecial #84                 // Method java/lang/Object."<init>":()V
        19: return
      LineNumberTable:
        line 355: 0
        line 353: 5
        line 354: 10
        line 357: 15
      LocalVariableTable:
        Start  Length  Slot  Name   Signature
            0      20     0  this   Lshapeless/ops/hlist$FlatMapper$$anon$29;
            0      20     1 prepend$1   Lshapeless/ops/hlist$Prepend;
            0      20     2  hc$2   Lshapeless/PolyDefns$Case;
            0      20     3  mt$2   Lshapeless/ops/hlist$FlatMapper;
    MethodParameters:
      Name                           Flags
      prepend$1                      final
      hc$2                           final
      mt$2                           final
}
InnerClasses:
  public static abstract #18= #15 of #17; // Case=class shapeless/PolyDefns$Case of class shapeless/PolyDefns
  public static #21= #7 of #20;           // FlatMapper=class shapeless/ops/hlist$FlatMapper of class shapeless/ops/hlist
  public static #22= #10 of #20;          // FlatMapper$=class shapeless/ops/hlist$FlatMapper$ of class shapeless/ops/hlist
  public final #2;                        // class shapeless/ops/hlist$FlatMapper$$anon$29
  public static #25= #24 of #20;          // Prepend=class shapeless/ops/hlist$Prepend of class shapeless/ops/hlist
EnclosingMethod: #10.#13                // shapeless.ops.hlist$FlatMapper$.hlistFlatMapper1
Signature: #3                           // Ljava/lang/Object;Lshapeless/ops/hlist$FlatMapper<THF;Lshapeless/$colon$colon<TInH;TInT;>;>;
SourceFile: "hlists.scala"
  ScalaInlineInfo: length = 0x13 (unknown attribute)
   01 01 00 03 00 50 00 51 01 00 20 00 41 01 00 20
   00 21 01
  Scala: length = 0x0 (unknown attribute)

