Classfile /Users/mw/Projects/slang-braindump/.jar/jar11/assemble/slang-braindump/assemble/content/shapeless/ops/hlist$HKernelAux$$anon$17.class
  Last modified May 29, 2022; size 1037 bytes
  SHA-256 checksum bd5d8197741522c93b455c29dad9b3fe1ead24c700ba7c71adc772cd1a22aeab
  Compiled from "hlists.scala"
public final class shapeless.ops.hlist$HKernelAux$$anon$17 extends java.lang.Object implements shapeless.ops.hlist$HKernelAux<shapeless.HNil>
  minor version: 0
  major version: 52
  flags: (0x0031) ACC_PUBLIC, ACC_FINAL, ACC_SUPER
  this_class: #2                          // shapeless/ops/hlist$HKernelAux$$anon$17
  super_class: #5                         // java/lang/Object
  interfaces: 1, fields: 0, methods: 3, attributes: 6
Constant pool:
   #1 = Utf8               shapeless/ops/hlist$HKernelAux$$anon$17
   #2 = Class              #1             // shapeless/ops/hlist$HKernelAux$$anon$17
   #3 = Utf8               Ljava/lang/Object;Lshapeless/ops/hlist$HKernelAux<Lshapeless/HNil;>;
   #4 = Utf8               java/lang/Object
   #5 = Class              #4             // java/lang/Object
   #6 = Utf8               shapeless/ops/hlist$HKernelAux
   #7 = Class              #6             // shapeless/ops/hlist$HKernelAux
   #8 = Utf8               hlists.scala
   #9 = Utf8               shapeless/ops/hlist$HKernelAux$
  #10 = Class              #9             // shapeless/ops/hlist$HKernelAux$
  #11 = Utf8               mkHNilHKernel
  #12 = Utf8               ()Lshapeless/ops/hlist$HKernelAux;
  #13 = NameAndType        #11:#12        // mkHNilHKernel:()Lshapeless/ops/hlist$HKernelAux;
  #14 = Utf8               shapeless/ops/hlist
  #15 = Class              #14            // shapeless/ops/hlist
  #16 = Utf8               HKernelAux
  #17 = Utf8               HKernelAux$
  #18 = Utf8               shapeless/ops/hlist$HNilHKernel$
  #19 = Class              #18            // shapeless/ops/hlist$HNilHKernel$
  #20 = Utf8               HNilHKernel$
  #21 = Utf8               apply
  #22 = Utf8               ()Lshapeless/ops/hlist$HNilHKernel$;
  #23 = Utf8               MODULE$
  #24 = Utf8               Lshapeless/ops/hlist$HNilHKernel$;
  #25 = NameAndType        #23:#24        // MODULE$:Lshapeless/ops/hlist$HNilHKernel$;
  #26 = Fieldref           #19.#25        // shapeless/ops/hlist$HNilHKernel$.MODULE$:Lshapeless/ops/hlist$HNilHKernel$;
  #27 = Utf8               this
  #28 = Utf8               Lshapeless/ops/hlist$HKernelAux$$anon$17;
  #29 = Utf8               ()Ljava/lang/Object;
  #30 = NameAndType        #21:#22        // apply:()Lshapeless/ops/hlist$HNilHKernel$;
  #31 = Methodref          #2.#30         // shapeless/ops/hlist$HKernelAux$$anon$17.apply:()Lshapeless/ops/hlist$HNilHKernel$;
  #32 = Utf8               <init>
  #33 = Utf8               ()V
  #34 = NameAndType        #32:#33        // "<init>":()V
  #35 = Methodref          #5.#34         // java/lang/Object."<init>":()V
  #36 = Utf8               Code
  #37 = Utf8               LineNumberTable
  #38 = Utf8               LocalVariableTable
  #39 = Utf8               InnerClasses
  #40 = Utf8               EnclosingMethod
  #41 = Utf8               Signature
  #42 = Utf8               SourceFile
  #43 = Utf8               ScalaInlineInfo
  #44 = Utf8               Scala
{
  public shapeless.ops.hlist$HNilHKernel$ apply();
    descriptor: ()Lshapeless/ops/hlist$HNilHKernel$;
    flags: (0x0001) ACC_PUBLIC
    Code:
      stack=1, locals=1, args_size=1
         0: getstatic     #26                 // Field shapeless/ops/hlist$HNilHKernel$.MODULE$:Lshapeless/ops/hlist$HNilHKernel$;
         3: areturn
      LineNumberTable:
        line 219: 0
      LocalVariableTable:
        Start  Length  Slot  Name   Signature
            0       4     0  this   Lshapeless/ops/hlist$HKernelAux$$anon$17;

  public java.lang.Object apply();
    descriptor: ()Ljava/lang/Object;
    flags: (0x1041) ACC_PUBLIC, ACC_BRIDGE, ACC_SYNTHETIC
    Code:
      stack=1, locals=1, args_size=1
         0: aload_0
         1: invokevirtual #31                 // Method apply:()Lshapeless/ops/hlist$HNilHKernel$;
         4: areturn
      LineNumberTable:
        line 217: 0
      LocalVariableTable:
        Start  Length  Slot  Name   Signature
            0       5     0  this   Lshapeless/ops/hlist$HKernelAux$$anon$17;

  public shapeless.ops.hlist$HKernelAux$$anon$17();
    descriptor: ()V
    flags: (0x0001) ACC_PUBLIC
    Code:
      stack=1, locals=1, args_size=1
         0: aload_0
         1: invokespecial #35                 // Method java/lang/Object."<init>":()V
         4: return
      LineNumberTable:
        line 217: 0
      LocalVariableTable:
        Start  Length  Slot  Name   Signature
            0       5     0  this   Lshapeless/ops/hlist$HKernelAux$$anon$17;
}
InnerClasses:
  public static #16= #7 of #15;           // HKernelAux=class shapeless/ops/hlist$HKernelAux of class shapeless/ops/hlist
  public static #17= #10 of #15;          // HKernelAux$=class shapeless/ops/hlist$HKernelAux$ of class shapeless/ops/hlist
  public final #2;                        // class shapeless/ops/hlist$HKernelAux$$anon$17
  public static #20= #19 of #15;          // HNilHKernel$=class shapeless/ops/hlist$HNilHKernel$ of class shapeless/ops/hlist
EnclosingMethod: #10.#13                // shapeless.ops.hlist$HKernelAux$.mkHNilHKernel
Signature: #3                           // Ljava/lang/Object;Lshapeless/ops/hlist$HKernelAux<Lshapeless/HNil;>;
SourceFile: "hlists.scala"
  ScalaInlineInfo: length = 0x13 (unknown attribute)
   01 01 00 03 00 20 00 21 01 00 15 00 1D 01 00 15
   00 16 01
  Scala: length = 0x0 (unknown attribute)

