Classfile /Users/mw/Projects/slang-braindump/.jar/jar11/assemble/slang-braindump/assemble/content/shapeless/ops/hlist$LiftAll$.class
  Last modified May 29, 2022; size 1973 bytes
  SHA-256 checksum 376b1abb2b6b3d530f9d459e2ef767c85a0f06d713d24a492fa9d0339bc58a60
  Compiled from "hlists.scala"
public class shapeless.ops.hlist$LiftAll$
  minor version: 0
  major version: 52
  flags: (0x0021) ACC_PUBLIC, ACC_SUPER
  this_class: #2                          // shapeless/ops/hlist$LiftAll$
  super_class: #4                         // java/lang/Object
  interfaces: 0, fields: 1, methods: 6, attributes: 4
Constant pool:
   #1 = Utf8               shapeless/ops/hlist$LiftAll$
   #2 = Class              #1             // shapeless/ops/hlist$LiftAll$
   #3 = Utf8               java/lang/Object
   #4 = Class              #3             // java/lang/Object
   #5 = Utf8               hlists.scala
   #6 = Utf8               shapeless/ops/hlist$LiftAll
   #7 = Class              #6             // shapeless/ops/hlist$LiftAll
   #8 = Utf8               shapeless/ops/hlist
   #9 = Class              #8             // shapeless/ops/hlist
  #10 = Utf8               LiftAll
  #11 = Utf8               LiftAll$
  #12 = Utf8               shapeless/ops/hlist$LiftAll$$anon$194
  #13 = Class              #12            // shapeless/ops/hlist$LiftAll$$anon$194
  #14 = Utf8               shapeless/ops/hlist$LiftAll$$anon$195
  #15 = Class              #14            // shapeless/ops/hlist$LiftAll$$anon$195
  #16 = Utf8               shapeless/ops/hlist$LiftAll$Curried
  #17 = Class              #16            // shapeless/ops/hlist$LiftAll$Curried
  #18 = Utf8               Curried
  #19 = Utf8               MODULE$
  #20 = Utf8               Lshapeless/ops/hlist$LiftAll$;
  #21 = Utf8               <clinit>
  #22 = Utf8               ()V
  #23 = Utf8               <init>
  #24 = NameAndType        #23:#22        // "<init>":()V
  #25 = Methodref          #2.#24         // shapeless/ops/hlist$LiftAll$."<init>":()V
  #26 = NameAndType        #19:#20        // MODULE$:Lshapeless/ops/hlist$LiftAll$;
  #27 = Fieldref           #2.#26         // shapeless/ops/hlist$LiftAll$.MODULE$:Lshapeless/ops/hlist$LiftAll$;
  #28 = Utf8               apply
  #29 = Utf8               ()Lshapeless/ops/hlist$LiftAll$Curried;
  #30 = Utf8               <F:Ljava/lang/Object;>()Lshapeless/ops/hlist$LiftAll$Curried<TF;>;
  #31 = Methodref          #17.#24        // shapeless/ops/hlist$LiftAll$Curried."<init>":()V
  #32 = Utf8               this
  #33 = Utf8               (Lshapeless/ops/hlist$LiftAll;)Lshapeless/ops/hlist$LiftAll;
  #34 = Utf8               <F:Ljava/lang/Object;In::Lshapeless/HList;>(Lshapeless/ops/hlist$LiftAll<TF;TIn;>;)Lshapeless/ops/hlist$LiftAll<TF;TIn;>;
  #35 = Utf8               lift
  #36 = Utf8               Lshapeless/ops/hlist$LiftAll;
  #37 = Utf8               hnil
  #38 = Utf8               ()Lshapeless/ops/hlist$LiftAll;
  #39 = Utf8               <F:Ljava/lang/Object;>()Lshapeless/ops/hlist$LiftAll<TF;Lshapeless/HNil;>;
  #40 = Methodref          #13.#24        // shapeless/ops/hlist$LiftAll$$anon$194."<init>":()V
  #41 = Utf8               hcons
  #42 = Utf8               (Ljava/lang/Object;Lshapeless/ops/hlist$LiftAll;)Lshapeless/ops/hlist$LiftAll;
  #43 = Utf8               <F:Ljava/lang/Object;H:Ljava/lang/Object;T::Lshapeless/HList;TI::Lshapeless/HList;>(TF;Lshapeless/ops/hlist$LiftAll<TF;TT;>;)Lshapeless/ops/hlist$LiftAll<TF;Lshapeless/$colon$colon<TH;TT;>;>;
  #44 = Utf8               headInstance
  #45 = Utf8               tailInstances
  #46 = Utf8               (Ljava/lang/Object;Lshapeless/ops/hlist$LiftAll;)V
  #47 = NameAndType        #23:#46        // "<init>":(Ljava/lang/Object;Lshapeless/ops/hlist$LiftAll;)V
  #48 = Methodref          #15.#47        // shapeless/ops/hlist$LiftAll$$anon$195."<init>":(Ljava/lang/Object;Lshapeless/ops/hlist$LiftAll;)V
  #49 = Utf8               Ljava/lang/Object;
  #50 = Methodref          #4.#24         // java/lang/Object."<init>":()V
  #51 = Utf8               Code
  #52 = Utf8               LineNumberTable
  #53 = Utf8               LocalVariableTable
  #54 = Utf8               Signature
  #55 = Utf8               MethodParameters
  #56 = Utf8               InnerClasses
  #57 = Utf8               SourceFile
  #58 = Utf8               ScalaInlineInfo
  #59 = Utf8               Scala
{
  public static final shapeless.ops.hlist$LiftAll$ MODULE$;
    descriptor: Lshapeless/ops/hlist$LiftAll$;
    flags: (0x0019) ACC_PUBLIC, ACC_STATIC, ACC_FINAL

  public static {};
    descriptor: ()V
    flags: (0x0009) ACC_PUBLIC, ACC_STATIC
    Code:
      stack=2, locals=0, args_size=0
         0: new           #2                  // class shapeless/ops/hlist$LiftAll$
         3: dup
         4: invokespecial #25                 // Method "<init>":()V
         7: putstatic     #27                 // Field MODULE$:Lshapeless/ops/hlist$LiftAll$;
        10: return
      LineNumberTable:
        line 2882: 0

  public <F extends java.lang.Object> shapeless.ops.hlist$LiftAll$Curried<F> apply();
    descriptor: ()Lshapeless/ops/hlist$LiftAll$Curried;
    flags: (0x0001) ACC_PUBLIC
    Code:
      stack=2, locals=1, args_size=1
         0: new           #17                 // class shapeless/ops/hlist$LiftAll$Curried
         3: dup
         4: invokespecial #31                 // Method shapeless/ops/hlist$LiftAll$Curried."<init>":()V
         7: areturn
      LineNumberTable:
        line 2890: 0
      LocalVariableTable:
        Start  Length  Slot  Name   Signature
            0       8     0  this   Lshapeless/ops/hlist$LiftAll$;
    Signature: #30                          // <F:Ljava/lang/Object;>()Lshapeless/ops/hlist$LiftAll$Curried<TF;>;

  public <F extends java.lang.Object, In extends shapeless.HList> shapeless.ops.hlist$LiftAll<F, In> apply(shapeless.ops.hlist$LiftAll<F, In>);
    descriptor: (Lshapeless/ops/hlist$LiftAll;)Lshapeless/ops/hlist$LiftAll;
    flags: (0x0001) ACC_PUBLIC
    Code:
      stack=1, locals=2, args_size=2
         0: aload_1
         1: areturn
      LineNumberTable:
        line 2891: 0
      LocalVariableTable:
        Start  Length  Slot  Name   Signature
            0       2     0  this   Lshapeless/ops/hlist$LiftAll$;
            0       2     1  lift   Lshapeless/ops/hlist$LiftAll;
    Signature: #34                          // <F:Ljava/lang/Object;In::Lshapeless/HList;>(Lshapeless/ops/hlist$LiftAll<TF;TIn;>;)Lshapeless/ops/hlist$LiftAll<TF;TIn;>;
    MethodParameters:
      Name                           Flags
      lift                           final

  public <F extends java.lang.Object> shapeless.ops.hlist$LiftAll<F, shapeless.HNil> hnil();
    descriptor: ()Lshapeless/ops/hlist$LiftAll;
    flags: (0x0001) ACC_PUBLIC
    Code:
      stack=2, locals=1, args_size=1
         0: new           #13                 // class shapeless/ops/hlist$LiftAll$$anon$194
         3: dup
         4: invokespecial #40                 // Method shapeless/ops/hlist$LiftAll$$anon$194."<init>":()V
         7: areturn
      LineNumberTable:
        line 2893: 0
      LocalVariableTable:
        Start  Length  Slot  Name   Signature
            0       8     0  this   Lshapeless/ops/hlist$LiftAll$;
    Signature: #39                          // <F:Ljava/lang/Object;>()Lshapeless/ops/hlist$LiftAll<TF;Lshapeless/HNil;>;

  public <F extends java.lang.Object, H extends java.lang.Object, T extends shapeless.HList, TI extends shapeless.HList> shapeless.ops.hlist$LiftAll<F, shapeless.$colon$colon<H, T>> hcons(F, shapeless.ops.hlist$LiftAll<F, T>);
    descriptor: (Ljava/lang/Object;Lshapeless/ops/hlist$LiftAll;)Lshapeless/ops/hlist$LiftAll;
    flags: (0x0001) ACC_PUBLIC
    Code:
      stack=4, locals=3, args_size=3
         0: new           #15                 // class shapeless/ops/hlist$LiftAll$$anon$195
         3: dup
         4: aload_1
         5: aload_2
         6: invokespecial #48                 // Method shapeless/ops/hlist$LiftAll$$anon$195."<init>":(Ljava/lang/Object;Lshapeless/ops/hlist$LiftAll;)V
         9: areturn
      LineNumberTable:
        line 2900: 0
      LocalVariableTable:
        Start  Length  Slot  Name   Signature
            0      10     0  this   Lshapeless/ops/hlist$LiftAll$;
            0      10     1 headInstance   Ljava/lang/Object;
            0      10     2 tailInstances   Lshapeless/ops/hlist$LiftAll;
    Signature: #43                          // <F:Ljava/lang/Object;H:Ljava/lang/Object;T::Lshapeless/HList;TI::Lshapeless/HList;>(TF;Lshapeless/ops/hlist$LiftAll<TF;TT;>;)Lshapeless/ops/hlist$LiftAll<TF;Lshapeless/$colon$colon<TH;TT;>;>;
    MethodParameters:
      Name                           Flags
      headInstance                   final
      tailInstances                  final

  public shapeless.ops.hlist$LiftAll$();
    descriptor: ()V
    flags: (0x0001) ACC_PUBLIC
    Code:
      stack=1, locals=1, args_size=1
         0: aload_0
         1: invokespecial #50                 // Method java/lang/Object."<init>":()V
         4: return
      LineNumberTable:
        line 2911: 0
        line 2882: 4
      LocalVariableTable:
        Start  Length  Slot  Name   Signature
            0       5     0  this   Lshapeless/ops/hlist$LiftAll$;
}
InnerClasses:
  public static #10= #7 of #9;            // LiftAll=class shapeless/ops/hlist$LiftAll of class shapeless/ops/hlist
  public static #11= #2 of #9;            // LiftAll$=class shapeless/ops/hlist$LiftAll$ of class shapeless/ops/hlist
  public final #13;                       // class shapeless/ops/hlist$LiftAll$$anon$194
  public final #15;                       // class shapeless/ops/hlist$LiftAll$$anon$195
  public static #18= #17 of #2;           // Curried=class shapeless/ops/hlist$LiftAll$Curried of class shapeless/ops/hlist$LiftAll$
SourceFile: "hlists.scala"
  ScalaInlineInfo: length = 0x1D (unknown attribute)
   01 01 00 05 00 17 00 16 01 00 1C 00 1D 01 00 1C
   00 21 01 00 29 00 2A 01 00 25 00 26 01
  Scala: length = 0x0 (unknown attribute)

