Classfile /Users/mw/Projects/slang-braindump/.jar/jar11/assemble/slang-braindump/assemble/content/shapeless/ops/hlist$ToTraversable.class
  Last modified May 29, 2022; size 2034 bytes
  SHA-256 checksum 68ead318d1306651b25714be189e0159461a1f5f7af537aba23bf045f4b1e09f
  Compiled from "hlists.scala"
public interface shapeless.ops.hlist$ToTraversable<L extends shapeless.HList, M extends java.lang.Object> extends shapeless.package$DepFn1<L>, java.io.Serializable
  minor version: 0
  major version: 52
  flags: (0x0601) ACC_PUBLIC, ACC_INTERFACE, ACC_ABSTRACT
  this_class: #2                          // shapeless/ops/hlist$ToTraversable
  super_class: #5                         // java/lang/Object
  interfaces: 2, fields: 0, methods: 5, attributes: 5
Constant pool:
   #1 = Utf8               shapeless/ops/hlist$ToTraversable
   #2 = Class              #1             // shapeless/ops/hlist$ToTraversable
   #3 = Utf8               <L::Lshapeless/HList;M:Ljava/lang/Object;>Ljava/lang/Object;Lshapeless/package$DepFn1<TL;>;Ljava/io/Serializable;
   #4 = Utf8               java/lang/Object
   #5 = Class              #4             // java/lang/Object
   #6 = Utf8               shapeless/package$DepFn1
   #7 = Class              #6             // shapeless/package$DepFn1
   #8 = Utf8               java/io/Serializable
   #9 = Class              #8             // java/io/Serializable
  #10 = Utf8               hlists.scala
  #11 = Utf8               shapeless/PolyDefns$$tilde$greater
  #12 = Class              #11            // shapeless/PolyDefns$$tilde$greater
  #13 = Utf8               shapeless/PolyDefns
  #14 = Class              #13            // shapeless/PolyDefns
  #15 = Utf8               $tilde$greater
  #16 = Utf8               shapeless/PolyDefns$$tilde$greater$
  #17 = Class              #16            // shapeless/PolyDefns$$tilde$greater$
  #18 = Utf8               $tilde$greater$
  #19 = Utf8               shapeless/PolyDefns$identity$
  #20 = Class              #19            // shapeless/PolyDefns$identity$
  #21 = Utf8               identity$
  #22 = Utf8               shapeless/ops/hlist
  #23 = Class              #22            // shapeless/ops/hlist
  #24 = Utf8               ToTraversable
  #25 = Utf8               shapeless/package
  #26 = Class              #25            // shapeless/package
  #27 = Utf8               DepFn1
  #28 = Utf8               builder
  #29 = Utf8               ()Lscala/collection/mutable/Builder;
  #30 = Utf8               ()Lscala/collection/mutable/Builder<Ljava/lang/Object;TM;>;
  #31 = Utf8               append
  #32 = Utf8               (Lshapeless/HList;Lscala/collection/mutable/Builder;Lscala/Function1;)V
  #33 = Utf8               <LLub:Ljava/lang/Object;>(TL;Lscala/collection/mutable/Builder<TLLub;TM;>;Lscala/Function1<Ljava/lang/Object;TLLub;>;)V
  #34 = Utf8               l
  #35 = Utf8               b
  #36 = Utf8               f
  #37 = Utf8               apply$
  #38 = Utf8               (Lshapeless/ops/hlist$ToTraversable;Lshapeless/HList;)Ljava/lang/Object;
  #39 = Utf8               $this
  #40 = Utf8               apply
  #41 = Utf8               (Lshapeless/HList;)Ljava/lang/Object;
  #42 = NameAndType        #40:#41        // apply:(Lshapeless/HList;)Ljava/lang/Object;
  #43 = InterfaceMethodref #2.#42         // shapeless/ops/hlist$ToTraversable.apply:(Lshapeless/HList;)Ljava/lang/Object;
  #44 = Utf8               Lshapeless/ops/hlist$ToTraversable;
  #45 = Utf8               Lshapeless/HList;
  #46 = Utf8               (TL;)TM;
  #47 = NameAndType        #28:#29        // builder:()Lscala/collection/mutable/Builder;
  #48 = InterfaceMethodref #2.#47         // shapeless/ops/hlist$ToTraversable.builder:()Lscala/collection/mutable/Builder;
  #49 = Utf8               MODULE$
  #50 = Utf8               Lshapeless/PolyDefns$$tilde$greater$;
  #51 = NameAndType        #49:#50        // MODULE$:Lshapeless/PolyDefns$$tilde$greater$;
  #52 = Fieldref           #17.#51        // shapeless/PolyDefns$$tilde$greater$.MODULE$:Lshapeless/PolyDefns$$tilde$greater$;
  #53 = Utf8               Lshapeless/PolyDefns$identity$;
  #54 = NameAndType        #49:#53        // MODULE$:Lshapeless/PolyDefns$identity$;
  #55 = Fieldref           #20.#54        // shapeless/PolyDefns$identity$.MODULE$:Lshapeless/PolyDefns$identity$;
  #56 = Utf8               inst4
  #57 = Utf8               (Lshapeless/PolyDefns$$tilde$greater;)Lscala/Function1;
  #58 = NameAndType        #56:#57        // inst4:(Lshapeless/PolyDefns$$tilde$greater;)Lscala/Function1;
  #59 = Methodref          #17.#58        // shapeless/PolyDefns$$tilde$greater$.inst4:(Lshapeless/PolyDefns$$tilde$greater;)Lscala/Function1;
  #60 = NameAndType        #31:#32        // append:(Lshapeless/HList;Lscala/collection/mutable/Builder;Lscala/Function1;)V
  #61 = InterfaceMethodref #2.#60         // shapeless/ops/hlist$ToTraversable.append:(Lshapeless/HList;Lscala/collection/mutable/Builder;Lscala/Function1;)V
  #62 = Utf8               scala/collection/mutable/Builder
  #63 = Class              #62            // scala/collection/mutable/Builder
  #64 = Utf8               result
  #65 = Utf8               ()Ljava/lang/Object;
  #66 = NameAndType        #64:#65        // result:()Ljava/lang/Object;
  #67 = InterfaceMethodref #63.#66        // scala/collection/mutable/Builder.result:()Ljava/lang/Object;
  #68 = Utf8               Lscala/collection/mutable/Builder;
  #69 = Utf8               this
  #70 = Utf8               $init$
  #71 = Utf8               (Lshapeless/ops/hlist$ToTraversable;)V
  #72 = Utf8               Signature
  #73 = Utf8               MethodParameters
  #74 = Utf8               Code
  #75 = Utf8               LineNumberTable
  #76 = Utf8               LocalVariableTable
  #77 = Utf8               InnerClasses
  #78 = Utf8               SourceFile
  #79 = Utf8               ScalaInlineInfo
  #80 = Utf8               Scala
{
  public abstract scala.collection.mutable.Builder<java.lang.Object, M> builder();
    descriptor: ()Lscala/collection/mutable/Builder;
    flags: (0x0401) ACC_PUBLIC, ACC_ABSTRACT
    Signature: #30                          // ()Lscala/collection/mutable/Builder<Ljava/lang/Object;TM;>;

  public abstract <LLub extends java.lang.Object> void append(L, scala.collection.mutable.Builder<LLub, M>, scala.Function1<java.lang.Object, LLub>);
    descriptor: (Lshapeless/HList;Lscala/collection/mutable/Builder;Lscala/Function1;)V
    flags: (0x0401) ACC_PUBLIC, ACC_ABSTRACT
    Signature: #33                          // <LLub:Ljava/lang/Object;>(TL;Lscala/collection/mutable/Builder<TLLub;TM;>;Lscala/Function1<Ljava/lang/Object;TLLub;>;)V
    MethodParameters:
      Name                           Flags
      l                              final
      b                              final
      f                              final

  public static java.lang.Object apply$(shapeless.ops.hlist$ToTraversable, shapeless.HList);
    descriptor: (Lshapeless/ops/hlist$ToTraversable;Lshapeless/HList;)Ljava/lang/Object;
    flags: (0x1009) ACC_PUBLIC, ACC_STATIC, ACC_SYNTHETIC
    Code:
      stack=2, locals=2, args_size=2
         0: aload_0
         1: aload_1
         2: invokespecial #43                 // InterfaceMethod apply:(Lshapeless/HList;)Ljava/lang/Object;
         5: areturn
      LineNumberTable:
        line 591: 0
      LocalVariableTable:
        Start  Length  Slot  Name   Signature
            0       6     0 $this   Lshapeless/ops/hlist$ToTraversable;
            0       6     1     l   Lshapeless/HList;
    MethodParameters:
      Name                           Flags
      $this                          final synthetic
      l                              final

  public default M apply(L);
    descriptor: (Lshapeless/HList;)Ljava/lang/Object;
    flags: (0x0001) ACC_PUBLIC
    Code:
      stack=5, locals=3, args_size=2
         0: aload_0
         1: invokeinterface #48,  1           // InterfaceMethod builder:()Lscala/collection/mutable/Builder;
         6: astore_2
         7: aload_0
         8: aload_1
         9: aload_2
        10: getstatic     #52                 // Field shapeless/PolyDefns$$tilde$greater$.MODULE$:Lshapeless/PolyDefns$$tilde$greater$;
        13: getstatic     #55                 // Field shapeless/PolyDefns$identity$.MODULE$:Lshapeless/PolyDefns$identity$;
        16: invokevirtual #59                 // Method shapeless/PolyDefns$$tilde$greater$.inst4:(Lshapeless/PolyDefns$$tilde$greater;)Lscala/Function1;
        19: invokeinterface #61,  4           // InterfaceMethod append:(Lshapeless/HList;Lscala/collection/mutable/Builder;Lscala/Function1;)V
        24: aload_2
        25: invokeinterface #67,  1           // InterfaceMethod scala/collection/mutable/Builder.result:()Ljava/lang/Object;
        30: areturn
      LineNumberTable:
        line 592: 0
        line 593: 7
        line 594: 24
      LocalVariableTable:
        Start  Length  Slot  Name   Signature
            6      24     2     b   Lscala/collection/mutable/Builder;
            0      31     0  this   Lshapeless/ops/hlist$ToTraversable;
            0      31     1     l   Lshapeless/HList;
    Signature: #46                          // (TL;)TM;
    MethodParameters:
      Name                           Flags
      l                              final

  public static void $init$(shapeless.ops.hlist$ToTraversable);
    descriptor: (Lshapeless/ops/hlist$ToTraversable;)V
    flags: (0x0009) ACC_PUBLIC, ACC_STATIC
    Code:
      stack=0, locals=1, args_size=1
         0: return
      LineNumberTable:
        line 585: 0
      LocalVariableTable:
        Start  Length  Slot  Name   Signature
            0       1     0 $this   Lshapeless/ops/hlist$ToTraversable;
    MethodParameters:
      Name                           Flags
      $this                          final synthetic
}
InnerClasses:
  public static #15= #12 of #14;          // $tilde$greater=class shapeless/PolyDefns$$tilde$greater of class shapeless/PolyDefns
  public static #18= #17 of #14;          // $tilde$greater$=class shapeless/PolyDefns$$tilde$greater$ of class shapeless/PolyDefns
  public static #21= #20 of #14;          // identity$=class shapeless/PolyDefns$identity$ of class shapeless/PolyDefns
  public static #24= #2 of #23;           // ToTraversable=class shapeless/ops/hlist$ToTraversable of class shapeless/ops/hlist
  public static #27= #7 of #26;           // DepFn1=class shapeless/package$DepFn1 of class shapeless/package
Signature: #3                           // <L::Lshapeless/HList;M:Ljava/lang/Object;>Ljava/lang/Object;Lshapeless/package$DepFn1<TL;>;Ljava/io/Serializable;
SourceFile: "hlists.scala"
  ScalaInlineInfo: length = 0x1D (unknown attribute)
   01 00 00 05 00 46 00 47 01 00 1F 00 20 00 00 25
   00 26 01 00 28 00 29 00 00 1C 00 1D 00
  Scala: length = 0x0 (unknown attribute)

