Classfile /Users/mw/Projects/slang-braindump/.jar/jar11/assemble/slang-braindump/assemble/content/shapeless/ops/hlist$Length$$anon$24.class
  Last modified May 29, 2022; size 996 bytes
  SHA-256 checksum 4ef70970f124e65f2f5ce5fd2f448b0fd0a0bf4d29bcbb65fb4b815e934de8a4
  Compiled from "hlists.scala"
public final class shapeless.ops.hlist$Length$$anon$24 extends java.lang.Object implements shapeless.ops.hlist$Length<L>
  minor version: 0
  major version: 52
  flags: (0x0031) ACC_PUBLIC, ACC_FINAL, ACC_SUPER
  this_class: #2                          // shapeless/ops/hlist$Length$$anon$24
  super_class: #5                         // java/lang/Object
  interfaces: 1, fields: 0, methods: 3, attributes: 6
Constant pool:
   #1 = Utf8               shapeless/ops/hlist$Length$$anon$24
   #2 = Class              #1             // shapeless/ops/hlist$Length$$anon$24
   #3 = Utf8               Ljava/lang/Object;Lshapeless/ops/hlist$Length<TL;>;
   #4 = Utf8               java/lang/Object
   #5 = Class              #4             // java/lang/Object
   #6 = Utf8               shapeless/ops/hlist$Length
   #7 = Class              #6             // shapeless/ops/hlist$Length
   #8 = Utf8               hlists.scala
   #9 = Utf8               shapeless/ops/hlist$Length$
  #10 = Class              #9             // shapeless/ops/hlist$Length$
  #11 = Utf8               hnilLength
  #12 = Utf8               ()Lshapeless/ops/hlist$Length;
  #13 = NameAndType        #11:#12        // hnilLength:()Lshapeless/ops/hlist$Length;
  #14 = Utf8               shapeless/ops/hlist
  #15 = Class              #14            // shapeless/ops/hlist
  #16 = Utf8               Length
  #17 = Utf8               Length$
  #18 = Utf8               apply
  #19 = Utf8               ()Lshapeless/_0;
  #20 = Utf8               shapeless/package$
  #21 = Class              #20            // shapeless/package$
  #22 = Utf8               MODULE$
  #23 = Utf8               Lshapeless/package$;
  #24 = NameAndType        #22:#23        // MODULE$:Lshapeless/package$;
  #25 = Fieldref           #21.#24        // shapeless/package$.MODULE$:Lshapeless/package$;
  #26 = Utf8               nat
  #27 = Utf8               ()Lshapeless/Nat$;
  #28 = NameAndType        #26:#27        // nat:()Lshapeless/Nat$;
  #29 = Methodref          #21.#28        // shapeless/package$.nat:()Lshapeless/Nat$;
  #30 = Utf8               shapeless/Nat$
  #31 = Class              #30            // shapeless/Nat$
  #32 = Utf8               _0
  #33 = NameAndType        #32:#19        // _0:()Lshapeless/_0;
  #34 = Methodref          #31.#33        // shapeless/Nat$._0:()Lshapeless/_0;
  #35 = Utf8               this
  #36 = Utf8               Lshapeless/ops/hlist$Length$$anon$24;
  #37 = Utf8               ()Ljava/lang/Object;
  #38 = NameAndType        #18:#19        // apply:()Lshapeless/_0;
  #39 = Methodref          #2.#38         // shapeless/ops/hlist$Length$$anon$24.apply:()Lshapeless/_0;
  #40 = Utf8               <init>
  #41 = Utf8               ()V
  #42 = NameAndType        #40:#41        // "<init>":()V
  #43 = Methodref          #5.#42         // java/lang/Object."<init>":()V
  #44 = Utf8               Code
  #45 = Utf8               LineNumberTable
  #46 = Utf8               LocalVariableTable
  #47 = Utf8               InnerClasses
  #48 = Utf8               EnclosingMethod
  #49 = Utf8               Signature
  #50 = Utf8               SourceFile
  #51 = Utf8               ScalaInlineInfo
  #52 = Utf8               Scala
{
  public shapeless._0 apply();
    descriptor: ()Lshapeless/_0;
    flags: (0x0001) ACC_PUBLIC
    Code:
      stack=1, locals=1, args_size=1
         0: getstatic     #25                 // Field shapeless/package$.MODULE$:Lshapeless/package$;
         3: invokevirtual #29                 // Method shapeless/package$.nat:()Lshapeless/Nat$;
         6: invokevirtual #34                 // Method shapeless/Nat$._0:()Lshapeless/_0;
         9: areturn
      LineNumberTable:
        line 298: 0
      LocalVariableTable:
        Start  Length  Slot  Name   Signature
            0      10     0  this   Lshapeless/ops/hlist$Length$$anon$24;

  public java.lang.Object apply();
    descriptor: ()Ljava/lang/Object;
    flags: (0x1041) ACC_PUBLIC, ACC_BRIDGE, ACC_SYNTHETIC
    Code:
      stack=1, locals=1, args_size=1
         0: aload_0
         1: invokevirtual #39                 // Method apply:()Lshapeless/_0;
         4: areturn
      LineNumberTable:
        line 296: 0
      LocalVariableTable:
        Start  Length  Slot  Name   Signature
            0       5     0  this   Lshapeless/ops/hlist$Length$$anon$24;

  public shapeless.ops.hlist$Length$$anon$24();
    descriptor: ()V
    flags: (0x0001) ACC_PUBLIC
    Code:
      stack=1, locals=1, args_size=1
         0: aload_0
         1: invokespecial #43                 // Method java/lang/Object."<init>":()V
         4: return
      LineNumberTable:
        line 296: 0
      LocalVariableTable:
        Start  Length  Slot  Name   Signature
            0       5     0  this   Lshapeless/ops/hlist$Length$$anon$24;
}
InnerClasses:
  public static #16= #7 of #15;           // Length=class shapeless/ops/hlist$Length of class shapeless/ops/hlist
  public static #17= #10 of #15;          // Length$=class shapeless/ops/hlist$Length$ of class shapeless/ops/hlist
  public final #2;                        // class shapeless/ops/hlist$Length$$anon$24
EnclosingMethod: #10.#13                // shapeless.ops.hlist$Length$.hnilLength
Signature: #3                           // Ljava/lang/Object;Lshapeless/ops/hlist$Length<TL;>;
SourceFile: "hlists.scala"
  ScalaInlineInfo: length = 0x13 (unknown attribute)
   01 01 00 03 00 28 00 29 01 00 12 00 25 01 00 12
   00 13 01
  Scala: length = 0x0 (unknown attribute)

