Classfile /Users/mw/Projects/slang-braindump/.jar/jar11/assemble/slang-braindump/assemble/content/shapeless/ops/hlist$ZipConst$$anon$154.class
  Last modified May 29, 2022; size 1946 bytes
  SHA-256 checksum 68189da6d5d5eb2db25aed60123dabddaf5b6a6b7d3a17e1ea48968b9b647f61
  Compiled from "hlists.scala"
public final class shapeless.ops.hlist$ZipConst$$anon$154 extends java.lang.Object implements shapeless.ops.hlist$ZipConst<C, L>
  minor version: 0
  major version: 52
  flags: (0x0031) ACC_PUBLIC, ACC_FINAL, ACC_SUPER
  this_class: #2                          // shapeless/ops/hlist$ZipConst$$anon$154
  super_class: #5                         // java/lang/Object
  interfaces: 1, fields: 2, methods: 3, attributes: 6
Constant pool:
   #1 = Utf8               shapeless/ops/hlist$ZipConst$$anon$154
   #2 = Class              #1             // shapeless/ops/hlist$ZipConst$$anon$154
   #3 = Utf8               Ljava/lang/Object;Lshapeless/ops/hlist$ZipConst<TC;TL;>;
   #4 = Utf8               java/lang/Object
   #5 = Class              #4             // java/lang/Object
   #6 = Utf8               shapeless/ops/hlist$ZipConst
   #7 = Class              #6             // shapeless/ops/hlist$ZipConst
   #8 = Utf8               hlists.scala
   #9 = Utf8               shapeless/ops/hlist$ZipConst$
  #10 = Class              #9             // shapeless/ops/hlist$ZipConst$
  #11 = Utf8               constZipper
  #12 = Utf8               (Lshapeless/ops/hlist$ConstMapper;Lshapeless/ops/hlist$Zip;)Lshapeless/ops/hlist$ZipConst;
  #13 = NameAndType        #11:#12        // constZipper:(Lshapeless/ops/hlist$ConstMapper;Lshapeless/ops/hlist$Zip;)Lshapeless/ops/hlist$ZipConst;
  #14 = Utf8               shapeless/ops/hlist$ConstMapper
  #15 = Class              #14            // shapeless/ops/hlist$ConstMapper
  #16 = Utf8               shapeless/ops/hlist
  #17 = Class              #16            // shapeless/ops/hlist
  #18 = Utf8               ConstMapper
  #19 = Utf8               shapeless/ops/hlist$Zip
  #20 = Class              #19            // shapeless/ops/hlist$Zip
  #21 = Utf8               Zip
  #22 = Utf8               ZipConst
  #23 = Utf8               ZipConst$
  #24 = Utf8               zipper$1
  #25 = Utf8               Lshapeless/ops/hlist$Zip;
  #26 = Utf8               mapper$3
  #27 = Utf8               Lshapeless/ops/hlist$ConstMapper;
  #28 = Utf8               apply
  #29 = Utf8               (Ljava/lang/Object;Lshapeless/HList;)Lshapeless/HList;
  #30 = Utf8               (TC;TL;)TZipperOut;
  #31 = Utf8               c
  #32 = Utf8               l
  #33 = NameAndType        #24:#25        // zipper$1:Lshapeless/ops/hlist$Zip;
  #34 = Fieldref           #2.#33         // shapeless/ops/hlist$ZipConst$$anon$154.zipper$1:Lshapeless/ops/hlist$Zip;
  #35 = Utf8               shapeless/HList$
  #36 = Class              #35            // shapeless/HList$
  #37 = Utf8               MODULE$
  #38 = Utf8               Lshapeless/HList$;
  #39 = NameAndType        #37:#38        // MODULE$:Lshapeless/HList$;
  #40 = Fieldref           #36.#39        // shapeless/HList$.MODULE$:Lshapeless/HList$;
  #41 = NameAndType        #26:#27        // mapper$3:Lshapeless/ops/hlist$ConstMapper;
  #42 = Fieldref           #2.#41         // shapeless/ops/hlist$ZipConst$$anon$154.mapper$3:Lshapeless/ops/hlist$ConstMapper;
  #43 = Utf8               (Ljava/lang/Object;Ljava/lang/Object;)Ljava/lang/Object;
  #44 = NameAndType        #28:#43        // apply:(Ljava/lang/Object;Ljava/lang/Object;)Ljava/lang/Object;
  #45 = InterfaceMethodref #15.#44        // shapeless/ops/hlist$ConstMapper.apply:(Ljava/lang/Object;Ljava/lang/Object;)Ljava/lang/Object;
  #46 = Utf8               shapeless/HList
  #47 = Class              #46            // shapeless/HList
  #48 = Utf8               shapeless/HNil$
  #49 = Class              #48            // shapeless/HNil$
  #50 = Utf8               Lshapeless/HNil$;
  #51 = NameAndType        #37:#50        // MODULE$:Lshapeless/HNil$;
  #52 = Fieldref           #49.#51        // shapeless/HNil$.MODULE$:Lshapeless/HNil$;
  #53 = Utf8               $colon$colon
  #54 = Utf8               (Ljava/lang/Object;)Lshapeless/$colon$colon;
  #55 = NameAndType        #53:#54        // $colon$colon:(Ljava/lang/Object;)Lshapeless/$colon$colon;
  #56 = Methodref          #49.#55        // shapeless/HNil$.$colon$colon:(Ljava/lang/Object;)Lshapeless/$colon$colon;
  #57 = Utf8               hlistOps
  #58 = Utf8               (Lshapeless/HList;)Lshapeless/syntax/HListOps;
  #59 = NameAndType        #57:#58        // hlistOps:(Lshapeless/HList;)Lshapeless/syntax/HListOps;
  #60 = Methodref          #36.#59        // shapeless/HList$.hlistOps:(Lshapeless/HList;)Lshapeless/syntax/HListOps;
  #61 = Utf8               shapeless/syntax/HListOps
  #62 = Class              #61            // shapeless/syntax/HListOps
  #63 = Methodref          #62.#55        // shapeless/syntax/HListOps.$colon$colon:(Ljava/lang/Object;)Lshapeless/$colon$colon;
  #64 = Utf8               (Ljava/lang/Object;)Ljava/lang/Object;
  #65 = NameAndType        #28:#64        // apply:(Ljava/lang/Object;)Ljava/lang/Object;
  #66 = InterfaceMethodref #20.#65        // shapeless/ops/hlist$Zip.apply:(Ljava/lang/Object;)Ljava/lang/Object;
  #67 = Utf8               this
  #68 = Utf8               Lshapeless/ops/hlist$ZipConst$$anon$154;
  #69 = Utf8               Ljava/lang/Object;
  #70 = Utf8               Lshapeless/HList;
  #71 = Utf8               t
  #72 = Utf8               u
  #73 = NameAndType        #28:#29        // apply:(Ljava/lang/Object;Lshapeless/HList;)Lshapeless/HList;
  #74 = Methodref          #2.#73         // shapeless/ops/hlist$ZipConst$$anon$154.apply:(Ljava/lang/Object;Lshapeless/HList;)Lshapeless/HList;
  #75 = Utf8               <init>
  #76 = Utf8               (Lshapeless/ops/hlist$Zip;Lshapeless/ops/hlist$ConstMapper;)V
  #77 = Utf8               ()V
  #78 = NameAndType        #75:#77        // "<init>":()V
  #79 = Methodref          #5.#78         // java/lang/Object."<init>":()V
  #80 = Utf8               Code
  #81 = Utf8               LineNumberTable
  #82 = Utf8               LocalVariableTable
  #83 = Utf8               Signature
  #84 = Utf8               MethodParameters
  #85 = Utf8               InnerClasses
  #86 = Utf8               EnclosingMethod
  #87 = Utf8               SourceFile
  #88 = Utf8               ScalaInlineInfo
  #89 = Utf8               Scala
{
  private final shapeless.ops.hlist$Zip zipper$1;
    descriptor: Lshapeless/ops/hlist$Zip;
    flags: (0x0012) ACC_PRIVATE, ACC_FINAL

  private final shapeless.ops.hlist$ConstMapper mapper$3;
    descriptor: Lshapeless/ops/hlist$ConstMapper;
    flags: (0x0012) ACC_PRIVATE, ACC_FINAL

  public ZipperOut apply(C, L);
    descriptor: (Ljava/lang/Object;Lshapeless/HList;)Lshapeless/HList;
    flags: (0x0001) ACC_PUBLIC
    Code:
      stack=5, locals=5, args_size=3
         0: aload_0
         1: getfield      #34                 // Field zipper$1:Lshapeless/ops/hlist$Zip;
         4: aload_2
         5: astore_3
         6: getstatic     #40                 // Field shapeless/HList$.MODULE$:Lshapeless/HList$;
         9: aload_0
        10: getfield      #42                 // Field mapper$3:Lshapeless/ops/hlist$ConstMapper;
        13: aload_1
        14: aload_2
        15: invokeinterface #45,  3           // InterfaceMethod shapeless/ops/hlist$ConstMapper.apply:(Ljava/lang/Object;Ljava/lang/Object;)Ljava/lang/Object;
        20: checkcast     #47                 // class shapeless/HList
        23: astore        4
        25: getstatic     #52                 // Field shapeless/HNil$.MODULE$:Lshapeless/HNil$;
        28: aload         4
        30: invokevirtual #56                 // Method shapeless/HNil$.$colon$colon:(Ljava/lang/Object;)Lshapeless/$colon$colon;
        33: invokevirtual #60                 // Method shapeless/HList$.hlistOps:(Lshapeless/HList;)Lshapeless/syntax/HListOps;
        36: aload_3
        37: invokevirtual #63                 // Method shapeless/syntax/HListOps.$colon$colon:(Ljava/lang/Object;)Lshapeless/$colon$colon;
        40: invokeinterface #66,  2           // InterfaceMethod shapeless/ops/hlist$Zip.apply:(Ljava/lang/Object;)Ljava/lang/Object;
        45: checkcast     #47                 // class shapeless/HList
        48: areturn
      LineNumberTable:
        line 2301: 0
      LocalVariableTable:
        Start  Length  Slot  Name   Signature
            0      49     0  this   Lshapeless/ops/hlist$ZipConst$$anon$154;
            0      49     1     c   Ljava/lang/Object;
            0      49     2     l   Lshapeless/HList;
    Signature: #30                          // (TC;TL;)TZipperOut;
    MethodParameters:
      Name                           Flags
      c                              final
      l                              final

  public java.lang.Object apply(java.lang.Object, java.lang.Object);
    descriptor: (Ljava/lang/Object;Ljava/lang/Object;)Ljava/lang/Object;
    flags: (0x1041) ACC_PUBLIC, ACC_BRIDGE, ACC_SYNTHETIC
    Code:
      stack=3, locals=3, args_size=3
         0: aload_0
         1: aload_1
         2: aload_2
         3: checkcast     #47                 // class shapeless/HList
         6: invokevirtual #74                 // Method apply:(Ljava/lang/Object;Lshapeless/HList;)Lshapeless/HList;
         9: areturn
      LineNumberTable:
        line 2299: 0
      LocalVariableTable:
        Start  Length  Slot  Name   Signature
            0      10     0  this   Lshapeless/ops/hlist$ZipConst$$anon$154;
            0      10     1     t   Ljava/lang/Object;
            0      10     2     u   Ljava/lang/Object;
    MethodParameters:
      Name                           Flags
      t                              final
      u                              final

  public shapeless.ops.hlist$ZipConst$$anon$154(shapeless.ops.hlist$Zip, shapeless.ops.hlist$ConstMapper);
    descriptor: (Lshapeless/ops/hlist$Zip;Lshapeless/ops/hlist$ConstMapper;)V
    flags: (0x0001) ACC_PUBLIC
    Code:
      stack=2, locals=3, args_size=3
         0: aload_0
         1: aload_1
         2: putfield      #34                 // Field zipper$1:Lshapeless/ops/hlist$Zip;
         5: aload_0
         6: aload_2
         7: putfield      #42                 // Field mapper$3:Lshapeless/ops/hlist$ConstMapper;
        10: aload_0
        11: invokespecial #79                 // Method java/lang/Object."<init>":()V
        14: return
      LineNumberTable:
        line 2298: 0
        line 2297: 5
        line 2299: 10
      LocalVariableTable:
        Start  Length  Slot  Name   Signature
            0      15     0  this   Lshapeless/ops/hlist$ZipConst$$anon$154;
            0      15     1 zipper$1   Lshapeless/ops/hlist$Zip;
            0      15     2 mapper$3   Lshapeless/ops/hlist$ConstMapper;
    MethodParameters:
      Name                           Flags
      zipper$1                       final
      mapper$3                       final
}
InnerClasses:
  public static #18= #15 of #17;          // ConstMapper=class shapeless/ops/hlist$ConstMapper of class shapeless/ops/hlist
  public static #21= #20 of #17;          // Zip=class shapeless/ops/hlist$Zip of class shapeless/ops/hlist
  public static #22= #7 of #17;           // ZipConst=class shapeless/ops/hlist$ZipConst of class shapeless/ops/hlist
  public static #23= #10 of #17;          // ZipConst$=class shapeless/ops/hlist$ZipConst$ of class shapeless/ops/hlist
  public final #2;                        // class shapeless/ops/hlist$ZipConst$$anon$154
EnclosingMethod: #10.#13                // shapeless.ops.hlist$ZipConst$.constZipper
Signature: #3                           // Ljava/lang/Object;Lshapeless/ops/hlist$ZipConst<TC;TL;>;
SourceFile: "hlists.scala"
  ScalaInlineInfo: length = 0x13 (unknown attribute)
   01 01 00 03 00 4B 00 4C 01 00 1C 00 2B 01 00 1C
   00 1D 01
  Scala: length = 0x0 (unknown attribute)

