Classfile /Users/mw/Projects/slang-braindump/.jar/jar11/assemble/slang-braindump/assemble/content/shapeless/ops/hlist$ZipWithIndex$Helper$.class
  Last modified May 29, 2022; size 2027 bytes
  SHA-256 checksum 2dd685355618778f153027c4890d061fec344d9c6c5ab298eb5d95e6b6f40097
  Compiled from "hlists.scala"
public class shapeless.ops.hlist$ZipWithIndex$Helper$ implements java.io.Serializable
  minor version: 0
  major version: 52
  flags: (0x0021) ACC_PUBLIC, ACC_SUPER
  this_class: #2                          // shapeless/ops/hlist$ZipWithIndex$Helper$
  super_class: #4                         // java/lang/Object
  interfaces: 1, fields: 1, methods: 6, attributes: 4
Constant pool:
   #1 = Utf8               shapeless/ops/hlist$ZipWithIndex$Helper$
   #2 = Class              #1             // shapeless/ops/hlist$ZipWithIndex$Helper$
   #3 = Utf8               java/lang/Object
   #4 = Class              #3             // java/lang/Object
   #5 = Utf8               java/io/Serializable
   #6 = Class              #5             // java/io/Serializable
   #7 = Utf8               hlists.scala
   #8 = Utf8               shapeless/ops/hlist$ZipWithIndex$
   #9 = Class              #8             // shapeless/ops/hlist$ZipWithIndex$
  #10 = Utf8               shapeless/ops/hlist
  #11 = Class              #10            // shapeless/ops/hlist
  #12 = Utf8               ZipWithIndex$
  #13 = Utf8               shapeless/ops/hlist$ZipWithIndex$Helper
  #14 = Class              #13            // shapeless/ops/hlist$ZipWithIndex$Helper
  #15 = Utf8               Helper
  #16 = Utf8               Helper$
  #17 = Utf8               shapeless/ops/hlist$ZipWithIndex$Helper$$anon$159
  #18 = Class              #17            // shapeless/ops/hlist$ZipWithIndex$Helper$$anon$159
  #19 = Utf8               shapeless/ops/hlist$ZipWithIndex$Helper$$anon$160
  #20 = Class              #19            // shapeless/ops/hlist$ZipWithIndex$Helper$$anon$160
  #21 = Utf8               MODULE$
  #22 = Utf8               Lshapeless/ops/hlist$ZipWithIndex$Helper$;
  #23 = Utf8               <clinit>
  #24 = Utf8               ()V
  #25 = Utf8               <init>
  #26 = NameAndType        #25:#24        // "<init>":()V
  #27 = Methodref          #2.#26         // shapeless/ops/hlist$ZipWithIndex$Helper$."<init>":()V
  #28 = NameAndType        #21:#22        // MODULE$:Lshapeless/ops/hlist$ZipWithIndex$Helper$;
  #29 = Fieldref           #2.#28         // shapeless/ops/hlist$ZipWithIndex$Helper$.MODULE$:Lshapeless/ops/hlist$ZipWithIndex$Helper$;
  #30 = Utf8               apply
  #31 = Utf8               (Lshapeless/ops/hlist$ZipWithIndex$Helper;)Lshapeless/ops/hlist$ZipWithIndex$Helper;
  #32 = Utf8               <L::Lshapeless/HList;N::Lshapeless/Nat;>(Lshapeless/ops/hlist$ZipWithIndex$Helper<TL;TN;>;)Lshapeless/ops/hlist$ZipWithIndex$Helper<TL;TN;>;
  #33 = Utf8               helper
  #34 = Utf8               this
  #35 = Utf8               Lshapeless/ops/hlist$ZipWithIndex$Helper;
  #36 = Utf8               hnil
  #37 = Utf8               ()Lshapeless/ops/hlist$ZipWithIndex$Helper;
  #38 = Utf8               <N::Lshapeless/Nat;>()Lshapeless/ops/hlist$ZipWithIndex$Helper<Lshapeless/HNil;TN;>;
  #39 = Methodref          #18.#26        // shapeless/ops/hlist$ZipWithIndex$Helper$$anon$159."<init>":()V
  #40 = Utf8               hcons
  #41 = Utf8               <H:Ljava/lang/Object;T::Lshapeless/HList;OutT::Lshapeless/HList;N::Lshapeless/Nat;>(Lshapeless/ops/hlist$ZipWithIndex$Helper<TT;Lshapeless/Succ<TN;>;>;)Lshapeless/ops/hlist$ZipWithIndex$Helper<Lshapeless/$colon$colon<TH;TT;>;TN;>;
  #42 = Utf8               tail
  #43 = Utf8               (Lshapeless/ops/hlist$ZipWithIndex$Helper;)V
  #44 = NameAndType        #25:#43        // "<init>":(Lshapeless/ops/hlist$ZipWithIndex$Helper;)V
  #45 = Methodref          #20.#44        // shapeless/ops/hlist$ZipWithIndex$Helper$$anon$160."<init>":(Lshapeless/ops/hlist$ZipWithIndex$Helper;)V
  #46 = Utf8               writeReplace
  #47 = Utf8               ()Ljava/lang/Object;
  #48 = Utf8               scala/runtime/ModuleSerializationProxy
  #49 = Class              #48            // scala/runtime/ModuleSerializationProxy
  #50 = Utf8               (Ljava/lang/Class;)V
  #51 = NameAndType        #25:#50        // "<init>":(Ljava/lang/Class;)V
  #52 = Methodref          #49.#51        // scala/runtime/ModuleSerializationProxy."<init>":(Ljava/lang/Class;)V
  #53 = Methodref          #4.#26         // java/lang/Object."<init>":()V
  #54 = Utf8               Code
  #55 = Utf8               LineNumberTable
  #56 = Utf8               LocalVariableTable
  #57 = Utf8               Signature
  #58 = Utf8               MethodParameters
  #59 = Utf8               InnerClasses
  #60 = Utf8               SourceFile
  #61 = Utf8               ScalaInlineInfo
  #62 = Utf8               Scala
{
  public static final shapeless.ops.hlist$ZipWithIndex$Helper$ MODULE$;
    descriptor: Lshapeless/ops/hlist$ZipWithIndex$Helper$;
    flags: (0x0019) ACC_PUBLIC, ACC_STATIC, ACC_FINAL

  public static {};
    descriptor: ()V
    flags: (0x0009) ACC_PUBLIC, ACC_STATIC
    Code:
      stack=2, locals=0, args_size=0
         0: new           #2                  // class shapeless/ops/hlist$ZipWithIndex$Helper$
         3: dup
         4: invokespecial #27                 // Method "<init>":()V
         7: putstatic     #29                 // Field MODULE$:Lshapeless/ops/hlist$ZipWithIndex$Helper$;
        10: return
      LineNumberTable:
        line 2389: 0

  public <L extends shapeless.HList, N extends shapeless.Nat> shapeless.ops.hlist$ZipWithIndex$Helper<L, N> apply(shapeless.ops.hlist$ZipWithIndex$Helper<L, N>);
    descriptor: (Lshapeless/ops/hlist$ZipWithIndex$Helper;)Lshapeless/ops/hlist$ZipWithIndex$Helper;
    flags: (0x0001) ACC_PUBLIC
    Code:
      stack=1, locals=2, args_size=2
         0: aload_1
         1: areturn
      LineNumberTable:
        line 2390: 0
      LocalVariableTable:
        Start  Length  Slot  Name   Signature
            0       2     0  this   Lshapeless/ops/hlist$ZipWithIndex$Helper$;
            0       2     1 helper   Lshapeless/ops/hlist$ZipWithIndex$Helper;
    Signature: #32                          // <L::Lshapeless/HList;N::Lshapeless/Nat;>(Lshapeless/ops/hlist$ZipWithIndex$Helper<TL;TN;>;)Lshapeless/ops/hlist$ZipWithIndex$Helper<TL;TN;>;
    MethodParameters:
      Name                           Flags
      helper                         final

  public <N extends shapeless.Nat> shapeless.ops.hlist$ZipWithIndex$Helper<shapeless.HNil, N> hnil();
    descriptor: ()Lshapeless/ops/hlist$ZipWithIndex$Helper;
    flags: (0x0001) ACC_PUBLIC
    Code:
      stack=2, locals=1, args_size=1
         0: new           #18                 // class shapeless/ops/hlist$ZipWithIndex$Helper$$anon$159
         3: dup
         4: invokespecial #39                 // Method shapeless/ops/hlist$ZipWithIndex$Helper$$anon$159."<init>":()V
         7: areturn
      LineNumberTable:
        line 2395: 0
      LocalVariableTable:
        Start  Length  Slot  Name   Signature
            0       8     0  this   Lshapeless/ops/hlist$ZipWithIndex$Helper$;
    Signature: #38                          // <N::Lshapeless/Nat;>()Lshapeless/ops/hlist$ZipWithIndex$Helper<Lshapeless/HNil;TN;>;

  public <H extends java.lang.Object, T extends shapeless.HList, OutT extends shapeless.HList, N extends shapeless.Nat> shapeless.ops.hlist$ZipWithIndex$Helper<shapeless.$colon$colon<H, T>, N> hcons(shapeless.ops.hlist$ZipWithIndex$Helper<T, shapeless.Succ<N>>);
    descriptor: (Lshapeless/ops/hlist$ZipWithIndex$Helper;)Lshapeless/ops/hlist$ZipWithIndex$Helper;
    flags: (0x0001) ACC_PUBLIC
    Code:
      stack=3, locals=2, args_size=2
         0: new           #20                 // class shapeless/ops/hlist$ZipWithIndex$Helper$$anon$160
         3: dup
         4: aload_1
         5: invokespecial #45                 // Method shapeless/ops/hlist$ZipWithIndex$Helper$$anon$160."<init>":(Lshapeless/ops/hlist$ZipWithIndex$Helper;)V
         8: areturn
      LineNumberTable:
        line 2404: 0
      LocalVariableTable:
        Start  Length  Slot  Name   Signature
            0       9     0  this   Lshapeless/ops/hlist$ZipWithIndex$Helper$;
            0       9     1  tail   Lshapeless/ops/hlist$ZipWithIndex$Helper;
    Signature: #41                          // <H:Ljava/lang/Object;T::Lshapeless/HList;OutT::Lshapeless/HList;N::Lshapeless/Nat;>(Lshapeless/ops/hlist$ZipWithIndex$Helper<TT;Lshapeless/Succ<TN;>;>;)Lshapeless/ops/hlist$ZipWithIndex$Helper<Lshapeless/$colon$colon<TH;TT;>;TN;>;
    MethodParameters:
      Name                           Flags
      tail                           final

  private java.lang.Object writeReplace();
    descriptor: ()Ljava/lang/Object;
    flags: (0x0002) ACC_PRIVATE
    Code:
      stack=3, locals=1, args_size=1
         0: new           #49                 // class scala/runtime/ModuleSerializationProxy
         3: dup
         4: ldc           #2                  // class shapeless/ops/hlist$ZipWithIndex$Helper$
         6: invokespecial #52                 // Method scala/runtime/ModuleSerializationProxy."<init>":(Ljava/lang/Class;)V
         9: areturn
      LineNumberTable:
        line 2389: 0
      LocalVariableTable:
        Start  Length  Slot  Name   Signature
            0      10     0  this   Lshapeless/ops/hlist$ZipWithIndex$Helper$;

  public shapeless.ops.hlist$ZipWithIndex$Helper$();
    descriptor: ()V
    flags: (0x0001) ACC_PUBLIC
    Code:
      stack=1, locals=1, args_size=1
         0: aload_0
         1: invokespecial #53                 // Method java/lang/Object."<init>":()V
         4: return
      LineNumberTable:
        line 2411: 0
        line 2389: 4
      LocalVariableTable:
        Start  Length  Slot  Name   Signature
            0       5     0  this   Lshapeless/ops/hlist$ZipWithIndex$Helper$;
}
InnerClasses:
  public static #12= #9 of #11;           // ZipWithIndex$=class shapeless/ops/hlist$ZipWithIndex$ of class shapeless/ops/hlist
  public static #15= #14 of #9;           // Helper=class shapeless/ops/hlist$ZipWithIndex$Helper of class shapeless/ops/hlist$ZipWithIndex$
  public static #16= #2 of #9;            // Helper$=class shapeless/ops/hlist$ZipWithIndex$Helper$ of class shapeless/ops/hlist$ZipWithIndex$
  public final #18;                       // class shapeless/ops/hlist$ZipWithIndex$Helper$$anon$159
  public final #20;                       // class shapeless/ops/hlist$ZipWithIndex$Helper$$anon$160
SourceFile: "hlists.scala"
  ScalaInlineInfo: length = 0x1D (unknown attribute)
   01 01 00 05 00 19 00 18 01 00 1E 00 1F 01 00 28
   00 1F 01 00 24 00 25 01 00 2E 00 2F 01
  Scala: length = 0x0 (unknown attribute)

