Classfile /Users/mw/Projects/slang-braindump/.jar/jar11/assemble/slang-braindump/assemble/content/shapeless/ops/nat$LT0.class
  Last modified May 29, 2022; size 867 bytes
  SHA-256 checksum 39a21a8b7b5c1352cde3ded7af7a1c419c819c13fe731a098d8009682a907800
  Compiled from "nat.scala"
public interface shapeless.ops.nat$LT0
  minor version: 0
  major version: 52
  flags: (0x0601) ACC_PUBLIC, ACC_INTERFACE, ACC_ABSTRACT
  this_class: #2                          // shapeless/ops/nat$LT0
  super_class: #4                         // java/lang/Object
  interfaces: 0, fields: 0, methods: 3, attributes: 4
Constant pool:
   #1 = Utf8               shapeless/ops/nat$LT0
   #2 = Class              #1             // shapeless/ops/nat$LT0
   #3 = Utf8               java/lang/Object
   #4 = Class              #3             // java/lang/Object
   #5 = Utf8               nat.scala
   #6 = Utf8               shapeless/ops/nat$LT
   #7 = Class              #6             // shapeless/ops/nat$LT
   #8 = Utf8               shapeless/ops/nat
   #9 = Class              #8             // shapeless/ops/nat
  #10 = Utf8               LT
  #11 = Utf8               LT0
  #12 = Utf8               shapeless/ops/nat$LT0$$anon$14
  #13 = Class              #12            // shapeless/ops/nat$LT0$$anon$14
  #14 = Utf8               lt3$
  #15 = Utf8               (Lshapeless/ops/nat$LT0;)Lshapeless/ops/nat$LT;
  #16 = Utf8               $this
  #17 = Utf8               lt3
  #18 = Utf8               ()Lshapeless/ops/nat$LT;
  #19 = NameAndType        #17:#18        // lt3:()Lshapeless/ops/nat$LT;
  #20 = InterfaceMethodref #2.#19         // shapeless/ops/nat$LT0.lt3:()Lshapeless/ops/nat$LT;
  #21 = Utf8               Lshapeless/ops/nat$LT0;
  #22 = Utf8               <A::Lshapeless/Nat;>()Lshapeless/ops/nat$LT<TA;Lshapeless/Succ<TA;>;>;
  #23 = Utf8               <init>
  #24 = Utf8               (Lshapeless/ops/nat$LT0;)V
  #25 = NameAndType        #23:#24        // "<init>":(Lshapeless/ops/nat$LT0;)V
  #26 = Methodref          #13.#25        // shapeless/ops/nat$LT0$$anon$14."<init>":(Lshapeless/ops/nat$LT0;)V
  #27 = Utf8               this
  #28 = Utf8               $init$
  #29 = Utf8               Code
  #30 = Utf8               LineNumberTable
  #31 = Utf8               LocalVariableTable
  #32 = Utf8               MethodParameters
  #33 = Utf8               Signature
  #34 = Utf8               InnerClasses
  #35 = Utf8               SourceFile
  #36 = Utf8               ScalaInlineInfo
  #37 = Utf8               Scala
{
  public static shapeless.ops.nat$LT lt3$(shapeless.ops.nat$LT0);
    descriptor: (Lshapeless/ops/nat$LT0;)Lshapeless/ops/nat$LT;
    flags: (0x1009) ACC_PUBLIC, ACC_STATIC, ACC_SYNTHETIC
    Code:
      stack=1, locals=1, args_size=1
         0: aload_0
         1: invokespecial #20                 // InterfaceMethod lt3:()Lshapeless/ops/nat$LT;
         4: areturn
      LineNumberTable:
        line 150: 0
      LocalVariableTable:
        Start  Length  Slot  Name   Signature
            0       5     0 $this   Lshapeless/ops/nat$LT0;
    MethodParameters:
      Name                           Flags
      $this                          final synthetic

  public default <A extends shapeless.Nat> shapeless.ops.nat$LT<A, shapeless.Succ<A>> lt3();
    descriptor: ()Lshapeless/ops/nat$LT;
    flags: (0x0001) ACC_PUBLIC
    Code:
      stack=3, locals=1, args_size=1
         0: new           #13                 // class shapeless/ops/nat$LT0$$anon$14
         3: dup
         4: aconst_null
         5: invokespecial #26                 // Method shapeless/ops/nat$LT0$$anon$14."<init>":(Lshapeless/ops/nat$LT0;)V
         8: areturn
      LineNumberTable:
        line 150: 0
      LocalVariableTable:
        Start  Length  Slot  Name   Signature
            0       9     0  this   Lshapeless/ops/nat$LT0;
    Signature: #22                          // <A::Lshapeless/Nat;>()Lshapeless/ops/nat$LT<TA;Lshapeless/Succ<TA;>;>;

  public static void $init$(shapeless.ops.nat$LT0);
    descriptor: (Lshapeless/ops/nat$LT0;)V
    flags: (0x0009) ACC_PUBLIC, ACC_STATIC
    Code:
      stack=0, locals=1, args_size=1
         0: return
      LineNumberTable:
        line 147: 0
      LocalVariableTable:
        Start  Length  Slot  Name   Signature
            0       1     0 $this   Lshapeless/ops/nat$LT0;
    MethodParameters:
      Name                           Flags
      $this                          final synthetic
}
InnerClasses:
  public static #10= #7 of #9;            // LT=class shapeless/ops/nat$LT of class shapeless/ops/nat
  public static #11= #2 of #9;            // LT0=class shapeless/ops/nat$LT0 of class shapeless/ops/nat
  public final #13;                       // class shapeless/ops/nat$LT0$$anon$14
SourceFile: "nat.scala"
  ScalaInlineInfo: length = 0x13 (unknown attribute)
   01 00 00 03 00 1C 00 18 01 00 0E 00 0F 01 00 11
   00 12 00
  Scala: length = 0x0 (unknown attribute)

