Classfile /Users/mw/Projects/slang-braindump/.jar/jar11/assemble/slang-braindump/assemble/content/shapeless/ops/tuple$Length$$anon$40.class
  Last modified May 29, 2022; size 1299 bytes
  SHA-256 checksum ee58a28f9c836c85060da69e51ad61c4db7bc14fbaa688a3e8a3f623f7c769f0
  Compiled from "tuples.scala"
public final class shapeless.ops.tuple$Length$$anon$40 extends java.lang.Object implements shapeless.ops.tuple$Length<T>
  minor version: 0
  major version: 52
  flags: (0x0031) ACC_PUBLIC, ACC_FINAL, ACC_SUPER
  this_class: #2                          // shapeless/ops/tuple$Length$$anon$40
  super_class: #5                         // java/lang/Object
  interfaces: 1, fields: 1, methods: 3, attributes: 6
Constant pool:
   #1 = Utf8               shapeless/ops/tuple$Length$$anon$40
   #2 = Class              #1             // shapeless/ops/tuple$Length$$anon$40
   #3 = Utf8               Ljava/lang/Object;Lshapeless/ops/tuple$Length<TT;>;
   #4 = Utf8               java/lang/Object
   #5 = Class              #4             // java/lang/Object
   #6 = Utf8               shapeless/ops/tuple$Length
   #7 = Class              #6             // shapeless/ops/tuple$Length
   #8 = Utf8               tuples.scala
   #9 = Utf8               shapeless/ops/tuple$Length$
  #10 = Class              #9             // shapeless/ops/tuple$Length$
  #11 = Utf8               length
  #12 = Utf8               (Lshapeless/Generic;Lshapeless/ops/hlist$Length;)Lshapeless/ops/tuple$Length;
  #13 = NameAndType        #11:#12        // length:(Lshapeless/Generic;Lshapeless/ops/hlist$Length;)Lshapeless/ops/tuple$Length;
  #14 = Utf8               shapeless/ops/hlist$Length
  #15 = Class              #14            // shapeless/ops/hlist$Length
  #16 = Utf8               shapeless/ops/hlist
  #17 = Class              #16            // shapeless/ops/hlist
  #18 = Utf8               Length
  #19 = Utf8               shapeless/ops/tuple
  #20 = Class              #19            // shapeless/ops/tuple
  #21 = Utf8               Length$
  #22 = Utf8               length$1
  #23 = Utf8               Lshapeless/ops/hlist$Length;
  #24 = Utf8               apply
  #25 = Utf8               (Ljava/lang/Object;)Lshapeless/Nat;
  #26 = Utf8               (TT;)Lshapeless/Nat;
  #27 = Utf8               t
  #28 = NameAndType        #22:#23        // length$1:Lshapeless/ops/hlist$Length;
  #29 = Fieldref           #2.#28         // shapeless/ops/tuple$Length$$anon$40.length$1:Lshapeless/ops/hlist$Length;
  #30 = Utf8               ()Ljava/lang/Object;
  #31 = NameAndType        #24:#30        // apply:()Ljava/lang/Object;
  #32 = InterfaceMethodref #15.#31        // shapeless/ops/hlist$Length.apply:()Ljava/lang/Object;
  #33 = Utf8               shapeless/Nat
  #34 = Class              #33            // shapeless/Nat
  #35 = Utf8               this
  #36 = Utf8               Lshapeless/ops/tuple$Length$$anon$40;
  #37 = Utf8               Ljava/lang/Object;
  #38 = Utf8               (Ljava/lang/Object;)Ljava/lang/Object;
  #39 = NameAndType        #24:#25        // apply:(Ljava/lang/Object;)Lshapeless/Nat;
  #40 = Methodref          #2.#39         // shapeless/ops/tuple$Length$$anon$40.apply:(Ljava/lang/Object;)Lshapeless/Nat;
  #41 = Utf8               <init>
  #42 = Utf8               (Lshapeless/ops/hlist$Length;)V
  #43 = Utf8               ()V
  #44 = NameAndType        #41:#43        // "<init>":()V
  #45 = Methodref          #5.#44         // java/lang/Object."<init>":()V
  #46 = Utf8               Code
  #47 = Utf8               LineNumberTable
  #48 = Utf8               LocalVariableTable
  #49 = Utf8               Signature
  #50 = Utf8               MethodParameters
  #51 = Utf8               InnerClasses
  #52 = Utf8               EnclosingMethod
  #53 = Utf8               SourceFile
  #54 = Utf8               ScalaInlineInfo
  #55 = Utf8               Scala
{
  private final shapeless.ops.hlist$Length length$1;
    descriptor: Lshapeless/ops/hlist$Length;
    flags: (0x0012) ACC_PRIVATE, ACC_FINAL

  public shapeless.Nat apply(T);
    descriptor: (Ljava/lang/Object;)Lshapeless/Nat;
    flags: (0x0001) ACC_PUBLIC
    Code:
      stack=1, locals=2, args_size=2
         0: aload_0
         1: getfield      #29                 // Field length$1:Lshapeless/ops/hlist$Length;
         4: invokeinterface #32,  1           // InterfaceMethod shapeless/ops/hlist$Length.apply:()Ljava/lang/Object;
         9: checkcast     #34                 // class shapeless/Nat
        12: areturn
      LineNumberTable:
        line 908: 0
      LocalVariableTable:
        Start  Length  Slot  Name   Signature
            0      13     0  this   Lshapeless/ops/tuple$Length$$anon$40;
            0      13     1     t   Ljava/lang/Object;
    Signature: #26                          // (TT;)Lshapeless/Nat;
    MethodParameters:
      Name                           Flags
      t                              final

  public java.lang.Object apply(java.lang.Object);
    descriptor: (Ljava/lang/Object;)Ljava/lang/Object;
    flags: (0x1041) ACC_PUBLIC, ACC_BRIDGE, ACC_SYNTHETIC
    Code:
      stack=2, locals=2, args_size=2
         0: aload_0
         1: aload_1
         2: invokevirtual #40                 // Method apply:(Ljava/lang/Object;)Lshapeless/Nat;
         5: areturn
      LineNumberTable:
        line 906: 0
      LocalVariableTable:
        Start  Length  Slot  Name   Signature
            0       6     0  this   Lshapeless/ops/tuple$Length$$anon$40;
            0       6     1     t   Ljava/lang/Object;
    MethodParameters:
      Name                           Flags
      t                              final

  public shapeless.ops.tuple$Length$$anon$40(shapeless.ops.hlist$Length);
    descriptor: (Lshapeless/ops/hlist$Length;)V
    flags: (0x0001) ACC_PUBLIC
    Code:
      stack=2, locals=2, args_size=2
         0: aload_0
         1: aload_1
         2: putfield      #29                 // Field length$1:Lshapeless/ops/hlist$Length;
         5: aload_0
         6: invokespecial #45                 // Method java/lang/Object."<init>":()V
         9: return
      LineNumberTable:
        line 905: 0
        line 906: 5
      LocalVariableTable:
        Start  Length  Slot  Name   Signature
            0      10     0  this   Lshapeless/ops/tuple$Length$$anon$40;
            0      10     1 length$1   Lshapeless/ops/hlist$Length;
    MethodParameters:
      Name                           Flags
      length$1                       final
}
InnerClasses:
  public static #18= #15 of #17;          // Length=class shapeless/ops/hlist$Length of class shapeless/ops/hlist
  public static #18= #7 of #20;           // Length=class shapeless/ops/tuple$Length of class shapeless/ops/tuple
  public static #21= #10 of #20;          // Length$=class shapeless/ops/tuple$Length$ of class shapeless/ops/tuple
  public final #2;                        // class shapeless/ops/tuple$Length$$anon$40
EnclosingMethod: #10.#13                // shapeless.ops.tuple$Length$.length
Signature: #3                           // Ljava/lang/Object;Lshapeless/ops/tuple$Length<TT;>;
SourceFile: "tuples.scala"
  ScalaInlineInfo: length = 0x13 (unknown attribute)
   01 01 00 03 00 29 00 2A 01 00 18 00 26 01 00 18
   00 19 01
  Scala: length = 0x0 (unknown attribute)

