Classfile /Users/mw/Projects/slang-braindump/.jar/jar11/assemble/slang-braindump/assemble/content/shapeless/ops/zipper$Reify$.class
  Last modified May 29, 2022; size 2296 bytes
  SHA-256 checksum cc525adeb60816242c3d1964845c3106946a5177003029d445b8d5ade6e319c6
  Compiled from "zipper.scala"
public class shapeless.ops.zipper$Reify$ implements java.io.Serializable
  minor version: 0
  major version: 52
  flags: (0x0021) ACC_PUBLIC, ACC_SUPER
  this_class: #2                          // shapeless/ops/zipper$Reify$
  super_class: #4                         // java/lang/Object
  interfaces: 1, fields: 1, methods: 6, attributes: 4
Constant pool:
   #1 = Utf8               shapeless/ops/zipper$Reify$
   #2 = Class              #1             // shapeless/ops/zipper$Reify$
   #3 = Utf8               java/lang/Object
   #4 = Class              #3             // java/lang/Object
   #5 = Utf8               java/io/Serializable
   #6 = Class              #5             // java/io/Serializable
   #7 = Utf8               zipper.scala
   #8 = Utf8               shapeless/ops/hlist$ReversePrepend
   #9 = Class              #8             // shapeless/ops/hlist$ReversePrepend
  #10 = Utf8               shapeless/ops/hlist
  #11 = Class              #10            // shapeless/ops/hlist
  #12 = Utf8               ReversePrepend
  #13 = Utf8               shapeless/ops/zipper$Reify
  #14 = Class              #13            // shapeless/ops/zipper$Reify
  #15 = Utf8               shapeless/ops/zipper
  #16 = Class              #15            // shapeless/ops/zipper
  #17 = Utf8               Reify
  #18 = Utf8               Reify$
  #19 = Utf8               shapeless/ops/zipper$Reify$$anon$20
  #20 = Class              #19            // shapeless/ops/zipper$Reify$$anon$20
  #21 = Utf8               shapeless/ops/zipper$Reify$$anon$21
  #22 = Class              #21            // shapeless/ops/zipper$Reify$$anon$21
  #23 = Utf8               MODULE$
  #24 = Utf8               Lshapeless/ops/zipper$Reify$;
  #25 = Utf8               <clinit>
  #26 = Utf8               ()V
  #27 = Utf8               <init>
  #28 = NameAndType        #27:#26        // "<init>":()V
  #29 = Methodref          #2.#28         // shapeless/ops/zipper$Reify$."<init>":()V
  #30 = NameAndType        #23:#24        // MODULE$:Lshapeless/ops/zipper$Reify$;
  #31 = Fieldref           #2.#30         // shapeless/ops/zipper$Reify$.MODULE$:Lshapeless/ops/zipper$Reify$;
  #32 = Utf8               apply
  #33 = Utf8               (Lshapeless/ops/zipper$Reify;)Lshapeless/ops/zipper$Reify;
  #34 = Utf8               <Z:Ljava/lang/Object;>(Lshapeless/ops/zipper$Reify<TZ;>;)Lshapeless/ops/zipper$Reify<TZ;>;
  #35 = Utf8               reify
  #36 = Utf8               this
  #37 = Utf8               Lshapeless/ops/zipper$Reify;
  #38 = Utf8               hlistReify
  #39 = Utf8               (Lshapeless/ops/hlist$ReversePrepend;)Lshapeless/ops/zipper$Reify;
  #40 = Utf8               <LR::Lshapeless/HList;L::Lshapeless/HList;R::Lshapeless/HList;P:Ljava/lang/Object;>(Lshapeless/ops/hlist$ReversePrepend<TL;TR;>;)Lshapeless/ops/zipper$Reify<Lshapeless/Zipper<TLR;TL;TR;TP;>;>;
  #41 = Utf8               rp
  #42 = Utf8               (Lshapeless/ops/hlist$ReversePrepend;)V
  #43 = NameAndType        #27:#42        // "<init>":(Lshapeless/ops/hlist$ReversePrepend;)V
  #44 = Methodref          #20.#43        // shapeless/ops/zipper$Reify$$anon$20."<init>":(Lshapeless/ops/hlist$ReversePrepend;)V
  #45 = Utf8               Lshapeless/ops/hlist$ReversePrepend;
  #46 = Utf8               genericReify
  #47 = Utf8               (Lshapeless/Generic;Lshapeless/ops/hlist$ReversePrepend;)Lshapeless/ops/zipper$Reify;
  #48 = Utf8               <C:Ljava/lang/Object;L::Lshapeless/HList;R::Lshapeless/HList;P:Ljava/lang/Object;CL::Lshapeless/HList;>(Lshapeless/Generic<TC;>;Lshapeless/ops/hlist$ReversePrepend<TL;TR;>;)Lshapeless/ops/zipper$Reify<Lshapeless/Zipper<TC;TL;TR;TP;>;>;
  #49 = Utf8               gen
  #50 = Utf8               (Lshapeless/Generic;Lshapeless/ops/hlist$ReversePrepend;)V
  #51 = NameAndType        #27:#50        // "<init>":(Lshapeless/Generic;Lshapeless/ops/hlist$ReversePrepend;)V
  #52 = Methodref          #22.#51        // shapeless/ops/zipper$Reify$$anon$21."<init>":(Lshapeless/Generic;Lshapeless/ops/hlist$ReversePrepend;)V
  #53 = Utf8               Lshapeless/Generic;
  #54 = Utf8               writeReplace
  #55 = Utf8               ()Ljava/lang/Object;
  #56 = Utf8               scala/runtime/ModuleSerializationProxy
  #57 = Class              #56            // scala/runtime/ModuleSerializationProxy
  #58 = Utf8               (Ljava/lang/Class;)V
  #59 = NameAndType        #27:#58        // "<init>":(Ljava/lang/Class;)V
  #60 = Methodref          #57.#59        // scala/runtime/ModuleSerializationProxy."<init>":(Ljava/lang/Class;)V
  #61 = Methodref          #4.#28         // java/lang/Object."<init>":()V
  #62 = Utf8               Code
  #63 = Utf8               LineNumberTable
  #64 = Utf8               LocalVariableTable
  #65 = Utf8               Signature
  #66 = Utf8               MethodParameters
  #67 = Utf8               InnerClasses
  #68 = Utf8               SourceFile
  #69 = Utf8               ScalaInlineInfo
  #70 = Utf8               Scala
{
  public static final shapeless.ops.zipper$Reify$ MODULE$;
    descriptor: Lshapeless/ops/zipper$Reify$;
    flags: (0x0019) ACC_PUBLIC, ACC_STATIC, ACC_FINAL

  public static {};
    descriptor: ()V
    flags: (0x0009) ACC_PUBLIC, ACC_STATIC
    Code:
      stack=2, locals=0, args_size=0
         0: new           #2                  // class shapeless/ops/zipper$Reify$
         3: dup
         4: invokespecial #29                 // Method "<init>":()V
         7: putstatic     #31                 // Field MODULE$:Lshapeless/ops/zipper$Reify$;
        10: return
      LineNumberTable:
        line 312: 0

  public <Z extends java.lang.Object> shapeless.ops.zipper$Reify<Z> apply(shapeless.ops.zipper$Reify<Z>);
    descriptor: (Lshapeless/ops/zipper$Reify;)Lshapeless/ops/zipper$Reify;
    flags: (0x0001) ACC_PUBLIC
    Code:
      stack=1, locals=2, args_size=2
         0: aload_1
         1: areturn
      LineNumberTable:
        line 313: 0
      LocalVariableTable:
        Start  Length  Slot  Name   Signature
            0       2     0  this   Lshapeless/ops/zipper$Reify$;
            0       2     1 reify   Lshapeless/ops/zipper$Reify;
    Signature: #34                          // <Z:Ljava/lang/Object;>(Lshapeless/ops/zipper$Reify<TZ;>;)Lshapeless/ops/zipper$Reify<TZ;>;
    MethodParameters:
      Name                           Flags
      reify                          final

  public <LR extends shapeless.HList, L extends shapeless.HList, R extends shapeless.HList, P extends java.lang.Object> shapeless.ops.zipper$Reify<shapeless.Zipper<LR, L, R, P>> hlistReify(shapeless.ops.hlist$ReversePrepend<L, R>);
    descriptor: (Lshapeless/ops/hlist$ReversePrepend;)Lshapeless/ops/zipper$Reify;
    flags: (0x0001) ACC_PUBLIC
    Code:
      stack=3, locals=2, args_size=2
         0: new           #20                 // class shapeless/ops/zipper$Reify$$anon$20
         3: dup
         4: aload_1
         5: invokespecial #44                 // Method shapeless/ops/zipper$Reify$$anon$20."<init>":(Lshapeless/ops/hlist$ReversePrepend;)V
         8: areturn
      LineNumberTable:
        line 319: 0
      LocalVariableTable:
        Start  Length  Slot  Name   Signature
            0       9     0  this   Lshapeless/ops/zipper$Reify$;
            0       9     1    rp   Lshapeless/ops/hlist$ReversePrepend;
    Signature: #40                          // <LR::Lshapeless/HList;L::Lshapeless/HList;R::Lshapeless/HList;P:Ljava/lang/Object;>(Lshapeless/ops/hlist$ReversePrepend<TL;TR;>;)Lshapeless/ops/zipper$Reify<Lshapeless/Zipper<TLR;TL;TR;TP;>;>;
    MethodParameters:
      Name                           Flags
      rp                             final

  public <C extends java.lang.Object, L extends shapeless.HList, R extends shapeless.HList, P extends java.lang.Object, CL extends shapeless.HList> shapeless.ops.zipper$Reify<shapeless.Zipper<C, L, R, P>> genericReify(shapeless.Generic<C>, shapeless.ops.hlist$ReversePrepend<L, R>);
    descriptor: (Lshapeless/Generic;Lshapeless/ops/hlist$ReversePrepend;)Lshapeless/ops/zipper$Reify;
    flags: (0x0001) ACC_PUBLIC
    Code:
      stack=4, locals=3, args_size=3
         0: new           #22                 // class shapeless/ops/zipper$Reify$$anon$21
         3: dup
         4: aload_1
         5: aload_2
         6: invokespecial #52                 // Method shapeless/ops/zipper$Reify$$anon$21."<init>":(Lshapeless/Generic;Lshapeless/ops/hlist$ReversePrepend;)V
         9: areturn
      LineNumberTable:
        line 328: 0
      LocalVariableTable:
        Start  Length  Slot  Name   Signature
            0      10     0  this   Lshapeless/ops/zipper$Reify$;
            0      10     1   gen   Lshapeless/Generic;
            0      10     2    rp   Lshapeless/ops/hlist$ReversePrepend;
    Signature: #48                          // <C:Ljava/lang/Object;L::Lshapeless/HList;R::Lshapeless/HList;P:Ljava/lang/Object;CL::Lshapeless/HList;>(Lshapeless/Generic<TC;>;Lshapeless/ops/hlist$ReversePrepend<TL;TR;>;)Lshapeless/ops/zipper$Reify<Lshapeless/Zipper<TC;TL;TR;TP;>;>;
    MethodParameters:
      Name                           Flags
      gen                            final
      rp                             final

  private java.lang.Object writeReplace();
    descriptor: ()Ljava/lang/Object;
    flags: (0x0002) ACC_PRIVATE
    Code:
      stack=3, locals=1, args_size=1
         0: new           #57                 // class scala/runtime/ModuleSerializationProxy
         3: dup
         4: ldc           #2                  // class shapeless/ops/zipper$Reify$
         6: invokespecial #60                 // Method scala/runtime/ModuleSerializationProxy."<init>":(Ljava/lang/Class;)V
         9: areturn
      LineNumberTable:
        line 312: 0
      LocalVariableTable:
        Start  Length  Slot  Name   Signature
            0      10     0  this   Lshapeless/ops/zipper$Reify$;

  public shapeless.ops.zipper$Reify$();
    descriptor: ()V
    flags: (0x0001) ACC_PUBLIC
    Code:
      stack=1, locals=1, args_size=1
         0: aload_0
         1: invokespecial #61                 // Method java/lang/Object."<init>":()V
         4: return
      LineNumberTable:
        line 333: 0
        line 312: 4
      LocalVariableTable:
        Start  Length  Slot  Name   Signature
            0       5     0  this   Lshapeless/ops/zipper$Reify$;
}
InnerClasses:
  public static #12= #9 of #11;           // ReversePrepend=class shapeless/ops/hlist$ReversePrepend of class shapeless/ops/hlist
  public static #17= #14 of #16;          // Reify=class shapeless/ops/zipper$Reify of class shapeless/ops/zipper
  public static #18= #2 of #16;           // Reify$=class shapeless/ops/zipper$Reify$ of class shapeless/ops/zipper
  public final #20;                       // class shapeless/ops/zipper$Reify$$anon$20
  public final #22;                       // class shapeless/ops/zipper$Reify$$anon$21
SourceFile: "zipper.scala"
  ScalaInlineInfo: length = 0x1D (unknown attribute)
   01 01 00 05 00 1B 00 1A 01 00 20 00 21 01 00 2E
   00 2F 01 00 26 00 27 01 00 36 00 37 01
  Scala: length = 0x0 (unknown attribute)

