Classfile /Users/mw/Projects/slang-braindump/.jar/jar8/assemble/slang-braindump/assemble/content/coursier/core/compatibility/Entities$.class
  Last modified May 29, 2022; size 6250 bytes
  SHA-256 checksum 971450775c69ea8767c4c7941cad2721c4279b64398a0eb74f1c2f8a629c5371
  Compiled from "Entities.scala"
public final class coursier.core.compatibility.Entities$
  minor version: 0
  major version: 52
  flags: (0x0031) ACC_PUBLIC, ACC_FINAL, ACC_SUPER
  this_class: #2                          // coursier/core/compatibility/Entities$
  super_class: #4                         // java/lang/Object
  interfaces: 0, fields: 4, methods: 5, attributes: 3
Constant pool:
    #1 = Utf8               coursier/core/compatibility/Entities$
    #2 = Class              #1            // coursier/core/compatibility/Entities$
    #3 = Utf8               java/lang/Object
    #4 = Class              #3            // java/lang/Object
    #5 = Utf8               Entities.scala
    #6 = Utf8               MODULE$
    #7 = Utf8               Lcoursier/core/compatibility/Entities$;
    #8 = Utf8               map
    #9 = Utf8               Lscala/collection/immutable/Map;
   #10 = Utf8               Lscala/collection/immutable/Map<Ljava/lang/String;Ljava/lang/String;>;
   #11 = Utf8               entities
   #12 = Utf8               Lscala/collection/immutable/Vector;
   #13 = Utf8               Lscala/collection/immutable/Vector<Lscala/Tuple2<Ljava/lang/String;Ljava/lang/String;>;>;
   #14 = Utf8               bitmap$0
   #15 = Utf8               Z
   #16 = Utf8               <clinit>
   #17 = Utf8               ()V
   #18 = Utf8               <init>
   #19 = NameAndType        #18:#17       // "<init>":()V
   #20 = Methodref          #2.#19        // coursier/core/compatibility/Entities$."<init>":()V
   #21 = NameAndType        #6:#7         // MODULE$:Lcoursier/core/compatibility/Entities$;
   #22 = Fieldref           #2.#21        // coursier/core/compatibility/Entities$.MODULE$:Lcoursier/core/compatibility/Entities$;
   #23 = Utf8               scala/package$
   #24 = Class              #23           // scala/package$
   #25 = Utf8               Lscala/package$;
   #26 = NameAndType        #6:#25        // MODULE$:Lscala/package$;
   #27 = Fieldref           #24.#26       // scala/package$.MODULE$:Lscala/package$;
   #28 = Utf8               Vector
   #29 = Utf8               ()Lscala/collection/immutable/Vector$;
   #30 = NameAndType        #28:#29       // Vector:()Lscala/collection/immutable/Vector$;
   #31 = Methodref          #24.#30       // scala/package$.Vector:()Lscala/collection/immutable/Vector$;
   #32 = Utf8               scala/runtime/ScalaRunTime$
   #33 = Class              #32           // scala/runtime/ScalaRunTime$
   #34 = Utf8               Lscala/runtime/ScalaRunTime$;
   #35 = NameAndType        #6:#34        // MODULE$:Lscala/runtime/ScalaRunTime$;
   #36 = Fieldref           #33.#35       // scala/runtime/ScalaRunTime$.MODULE$:Lscala/runtime/ScalaRunTime$;
   #37 = Utf8               scala/Tuple2
   #38 = Class              #37           // scala/Tuple2
   #39 = Utf8               &nbsp;
   #40 = String             #39           // &nbsp;
   #41 = Utf8               &#160;
   #42 = String             #41           // &#160;
   #43 = Utf8               (Ljava/lang/Object;Ljava/lang/Object;)V
   #44 = NameAndType        #18:#43       // "<init>":(Ljava/lang/Object;Ljava/lang/Object;)V
   #45 = Methodref          #38.#44       // scala/Tuple2."<init>":(Ljava/lang/Object;Ljava/lang/Object;)V
   #46 = Utf8               &iexcl;
   #47 = String             #46           // &iexcl;
   #48 = Utf8               &#161;
   #49 = String             #48           // &#161;
   #50 = Utf8               &cent;
   #51 = String             #50           // &cent;
   #52 = Utf8               &#162;
   #53 = String             #52           // &#162;
   #54 = Utf8               &pound;
   #55 = String             #54           // &pound;
   #56 = Utf8               &#163;
   #57 = String             #56           // &#163;
   #58 = Utf8               &curren;
   #59 = String             #58           // &curren;
   #60 = Utf8               &#164;
   #61 = String             #60           // &#164;
   #62 = Utf8               &yen;
   #63 = String             #62           // &yen;
   #64 = Utf8               &#165;
   #65 = String             #64           // &#165;
   #66 = Utf8               &brvbar;
   #67 = String             #66           // &brvbar;
   #68 = Utf8               &#166;
   #69 = String             #68           // &#166;
   #70 = Utf8               &sect;
   #71 = String             #70           // &sect;
   #72 = Utf8               &#167;
   #73 = String             #72           // &#167;
   #74 = Utf8               &uml;
   #75 = String             #74           // &uml;
   #76 = Utf8               &#168;
   #77 = String             #76           // &#168;
   #78 = Utf8               &copy;
   #79 = String             #78           // &copy;
   #80 = Utf8               &#169;
   #81 = String             #80           // &#169;
   #82 = Utf8               &ordf;
   #83 = String             #82           // &ordf;
   #84 = Utf8               &#170;
   #85 = String             #84           // &#170;
   #86 = Utf8               &laquo;
   #87 = String             #86           // &laquo;
   #88 = Utf8               &#171;
   #89 = String             #88           // &#171;
   #90 = Utf8               &not;
   #91 = String             #90           // &not;
   #92 = Utf8               &#172;
   #93 = String             #92           // &#172;
   #94 = Utf8               &shy;
   #95 = String             #94           // &shy;
   #96 = Utf8               &#173;
   #97 = String             #96           // &#173;
   #98 = Utf8               &reg;
   #99 = String             #98           // &reg;
  #100 = Utf8               &#174;
  #101 = String             #100          // &#174;
  #102 = Utf8               &macr;
  #103 = String             #102          // &macr;
  #104 = Utf8               &#175;
  #105 = String             #104          // &#175;
  #106 = Utf8               &deg;
  #107 = String             #106          // &deg;
  #108 = Utf8               &#176;
  #109 = String             #108          // &#176;
  #110 = Utf8               &plusmn;
  #111 = String             #110          // &plusmn;
  #112 = Utf8               &#177;
  #113 = String             #112          // &#177;
  #114 = Utf8               &acute;
  #115 = String             #114          // &acute;
  #116 = Utf8               &#180;
  #117 = String             #116          // &#180;
  #118 = Utf8               &micro;
  #119 = String             #118          // &micro;
  #120 = Utf8               &#181;
  #121 = String             #120          // &#181;
  #122 = Utf8               &para;
  #123 = String             #122          // &para;
  #124 = Utf8               &#182;
  #125 = String             #124          // &#182;
  #126 = Utf8               &middot;
  #127 = String             #126          // &middot;
  #128 = Utf8               &#183;
  #129 = String             #128          // &#183;
  #130 = Utf8               &cedil;
  #131 = String             #130          // &cedil;
  #132 = Utf8               &#184;
  #133 = String             #132          // &#184;
  #134 = Utf8               &ordm;
  #135 = String             #134          // &ordm;
  #136 = Utf8               &#186;
  #137 = String             #136          // &#186;
  #138 = Utf8               &raquo;
  #139 = String             #138          // &raquo;
  #140 = Utf8               &#187;
  #141 = String             #140          // &#187;
  #142 = Utf8               &iquest;
  #143 = String             #142          // &iquest;
  #144 = Utf8               &#191;
  #145 = String             #144          // &#191;
  #146 = Utf8               &Agrave;
  #147 = String             #146          // &Agrave;
  #148 = Utf8               &#192;
  #149 = String             #148          // &#192;
  #150 = Utf8               &Aacute;
  #151 = String             #150          // &Aacute;
  #152 = Utf8               &#193;
  #153 = String             #152          // &#193;
  #154 = Utf8               &Acirc;
  #155 = String             #154          // &Acirc;
  #156 = Utf8               &#194;
  #157 = String             #156          // &#194;
  #158 = Utf8               &Atilde;
  #159 = String             #158          // &Atilde;
  #160 = Utf8               &#195;
  #161 = String             #160          // &#195;
  #162 = Utf8               &Auml;
  #163 = String             #162          // &Auml;
  #164 = Utf8               &#196;
  #165 = String             #164          // &#196;
  #166 = Utf8               &Aring;
  #167 = String             #166          // &Aring;
  #168 = Utf8               &#197;
  #169 = String             #168          // &#197;
  #170 = Utf8               &AElig;
  #171 = String             #170          // &AElig;
  #172 = Utf8               &#198;
  #173 = String             #172          // &#198;
  #174 = Utf8               &Ccedil;
  #175 = String             #174          // &Ccedil;
  #176 = Utf8               &#199;
  #177 = String             #176          // &#199;
  #178 = Utf8               &Egrave;
  #179 = String             #178          // &Egrave;
  #180 = Utf8               &#200;
  #181 = String             #180          // &#200;
  #182 = Utf8               &Eacute;
  #183 = String             #182          // &Eacute;
  #184 = Utf8               &#201;
  #185 = String             #184          // &#201;
  #186 = Utf8               &Ecirc;
  #187 = String             #186          // &Ecirc;
  #188 = Utf8               &#202;
  #189 = String             #188          // &#202;
  #190 = Utf8               &Euml;
  #191 = String             #190          // &Euml;
  #192 = Utf8               &#203;
  #193 = String             #192          // &#203;
  #194 = Utf8               &Igrave;
  #195 = String             #194          // &Igrave;
  #196 = Utf8               &#204;
  #197 = String             #196          // &#204;
  #198 = Utf8               &Iacute;
  #199 = String             #198          // &Iacute;
  #200 = Utf8               &#205;
  #201 = String             #200          // &#205;
  #202 = Utf8               &Icirc;
  #203 = String             #202          // &Icirc;
  #204 = Utf8               &#206;
  #205 = String             #204          // &#206;
  #206 = Utf8               &Iuml;
  #207 = String             #206          // &Iuml;
  #208 = Utf8               &#207;
  #209 = String             #208          // &#207;
  #210 = Utf8               &ETH;
  #211 = String             #210          // &ETH;
  #212 = Utf8               &#208;
  #213 = String             #212          // &#208;
  #214 = Utf8               &Ntilde;
  #215 = String             #214          // &Ntilde;
  #216 = Utf8               &#209;
  #217 = String             #216          // &#209;
  #218 = Utf8               &Ograve;
  #219 = String             #218          // &Ograve;
  #220 = Utf8               &#210;
  #221 = String             #220          // &#210;
  #222 = Utf8               &Oacute;
  #223 = String             #222          // &Oacute;
  #224 = Utf8               &#211;
  #225 = String             #224          // &#211;
  #226 = Utf8               &Ocirc;
  #227 = String             #226          // &Ocirc;
  #228 = Utf8               &#212;
  #229 = String             #228          // &#212;
  #230 = Utf8               &Otilde;
  #231 = String             #230          // &Otilde;
  #232 = Utf8               &#213;
  #233 = String             #232          // &#213;
  #234 = Utf8               &Ouml;
  #235 = String             #234          // &Ouml;
  #236 = Utf8               &#214;
  #237 = String             #236          // &#214;
  #238 = Utf8               &times;
  #239 = String             #238          // &times;
  #240 = Utf8               &#215;
  #241 = String             #240          // &#215;
  #242 = Utf8               &Oslash;
  #243 = String             #242          // &Oslash;
  #244 = Utf8               &#216;
  #245 = String             #244          // &#216;
  #246 = Utf8               &Ugrave;
  #247 = String             #246          // &Ugrave;
  #248 = Utf8               &#217;
  #249 = String             #248          // &#217;
  #250 = Utf8               &Uacute;
  #251 = String             #250          // &Uacute;
  #252 = Utf8               &#218;
  #253 = String             #252          // &#218;
  #254 = Utf8               &Ucirc;
  #255 = String             #254          // &Ucirc;
  #256 = Utf8               &#219;
  #257 = String             #256          // &#219;
  #258 = Utf8               &Uuml;
  #259 = String             #258          // &Uuml;
  #260 = Utf8               &#220;
  #261 = String             #260          // &#220;
  #262 = Utf8               &Yacute;
  #263 = String             #262          // &Yacute;
  #264 = Utf8               &#221;
  #265 = String             #264          // &#221;
  #266 = Utf8               &THORN;
  #267 = String             #266          // &THORN;
  #268 = Utf8               &#222;
  #269 = String             #268          // &#222;
  #270 = Utf8               &szlig;
  #271 = String             #270          // &szlig;
  #272 = Utf8               &#223;
  #273 = String             #272          // &#223;
  #274 = Utf8               &agrave;
  #275 = String             #274          // &agrave;
  #276 = Utf8               &#224;
  #277 = String             #276          // &#224;
  #278 = Utf8               &aacute;
  #279 = String             #278          // &aacute;
  #280 = Utf8               &#225;
  #281 = String             #280          // &#225;
  #282 = Utf8               &acirc;
  #283 = String             #282          // &acirc;
  #284 = Utf8               &#226;
  #285 = String             #284          // &#226;
  #286 = Utf8               &atilde;
  #287 = String             #286          // &atilde;
  #288 = Utf8               &#227;
  #289 = String             #288          // &#227;
  #290 = Utf8               &auml;
  #291 = String             #290          // &auml;
  #292 = Utf8               &#228;
  #293 = String             #292          // &#228;
  #294 = Utf8               &aring;
  #295 = String             #294          // &aring;
  #296 = Utf8               &#229;
  #297 = String             #296          // &#229;
  #298 = Utf8               &aelig;
  #299 = String             #298          // &aelig;
  #300 = Utf8               &#230;
  #301 = String             #300          // &#230;
  #302 = Utf8               &ccedil;
  #303 = String             #302          // &ccedil;
  #304 = Utf8               &#231;
  #305 = String             #304          // &#231;
  #306 = Utf8               &egrave;
  #307 = String             #306          // &egrave;
  #308 = Utf8               &#232;
  #309 = String             #308          // &#232;
  #310 = Utf8               &eacute;
  #311 = String             #310          // &eacute;
  #312 = Utf8               &#233;
  #313 = String             #312          // &#233;
  #314 = Utf8               &ecirc;
  #315 = String             #314          // &ecirc;
  #316 = Utf8               &#234;
  #317 = String             #316          // &#234;
  #318 = Utf8               &euml;
  #319 = String             #318          // &euml;
  #320 = Utf8               &#235;
  #321 = String             #320          // &#235;
  #322 = Utf8               &igrave;
  #323 = String             #322          // &igrave;
  #324 = Utf8               &#236;
  #325 = String             #324          // &#236;
  #326 = Utf8               &iacute;
  #327 = String             #326          // &iacute;
  #328 = Utf8               &#237;
  #329 = String             #328          // &#237;
  #330 = Utf8               &icirc;
  #331 = String             #330          // &icirc;
  #332 = Utf8               &#238;
  #333 = String             #332          // &#238;
  #334 = Utf8               &iuml;
  #335 = String             #334          // &iuml;
  #336 = Utf8               &#239;
  #337 = String             #336          // &#239;
  #338 = Utf8               &eth;
  #339 = String             #338          // &eth;
  #340 = Utf8               &#240;
  #341 = String             #340          // &#240;
  #342 = Utf8               &ntilde;
  #343 = String             #342          // &ntilde;
  #344 = Utf8               &#241;
  #345 = String             #344          // &#241;
  #346 = Utf8               &ograve;
  #347 = String             #346          // &ograve;
  #348 = Utf8               &#242;
  #349 = String             #348          // &#242;
  #350 = Utf8               &oacute;
  #351 = String             #350          // &oacute;
  #352 = Utf8               &#243;
  #353 = String             #352          // &#243;
  #354 = Utf8               &ocirc;
  #355 = String             #354          // &ocirc;
  #356 = Utf8               &#244;
  #357 = String             #356          // &#244;
  #358 = Utf8               &otilde;
  #359 = String             #358          // &otilde;
  #360 = Utf8               &#245;
  #361 = String             #360          // &#245;
  #362 = Utf8               &ouml;
  #363 = String             #362          // &ouml;
  #364 = Utf8               &#246;
  #365 = String             #364          // &#246;
  #366 = Utf8               &divide;
  #367 = String             #366          // &divide;
  #368 = Utf8               &#247;
  #369 = String             #368          // &#247;
  #370 = Utf8               &oslash;
  #371 = String             #370          // &oslash;
  #372 = Utf8               &#248;
  #373 = String             #372          // &#248;
  #374 = Utf8               &ugrave;
  #375 = String             #374          // &ugrave;
  #376 = Utf8               &#249;
  #377 = String             #376          // &#249;
  #378 = Utf8               &uacute;
  #379 = String             #378          // &uacute;
  #380 = Utf8               &#250;
  #381 = String             #380          // &#250;
  #382 = Utf8               &ucirc;
  #383 = String             #382          // &ucirc;
  #384 = Utf8               &#251;
  #385 = String             #384          // &#251;
  #386 = Utf8               &uuml;
  #387 = String             #386          // &uuml;
  #388 = Utf8               &#252;
  #389 = String             #388          // &#252;
  #390 = Utf8               &yacute;
  #391 = String             #390          // &yacute;
  #392 = Utf8               &#253;
  #393 = String             #392          // &#253;
  #394 = Utf8               &thorn;
  #395 = String             #394          // &thorn;
  #396 = Utf8               &#254;
  #397 = String             #396          // &#254;
  #398 = Utf8               &yuml;
  #399 = String             #398          // &yuml;
  #400 = Utf8               &#255;
  #401 = String             #400          // &#255;
  #402 = Utf8               [Ljava/lang/Object;
  #403 = Class              #402          // "[Ljava/lang/Object;"
  #404 = Utf8               wrapRefArray
  #405 = Utf8               ([Ljava/lang/Object;)Lscala/collection/immutable/ArraySeq;
  #406 = NameAndType        #404:#405     // wrapRefArray:([Ljava/lang/Object;)Lscala/collection/immutable/ArraySeq;
  #407 = Methodref          #33.#406      // scala/runtime/ScalaRunTime$.wrapRefArray:([Ljava/lang/Object;)Lscala/collection/immutable/ArraySeq;
  #408 = Utf8               scala/collection/immutable/Vector$
  #409 = Class              #408          // scala/collection/immutable/Vector$
  #410 = Utf8               apply
  #411 = Utf8               (Lscala/collection/immutable/Seq;)Ljava/lang/Object;
  #412 = NameAndType        #410:#411     // apply:(Lscala/collection/immutable/Seq;)Ljava/lang/Object;
  #413 = Methodref          #409.#412     // scala/collection/immutable/Vector$.apply:(Lscala/collection/immutable/Seq;)Ljava/lang/Object;
  #414 = Utf8               scala/collection/immutable/Vector
  #415 = Class              #414          // scala/collection/immutable/Vector
  #416 = NameAndType        #11:#12       // entities:Lscala/collection/immutable/Vector;
  #417 = Fieldref           #2.#416       // coursier/core/compatibility/Entities$.entities:Lscala/collection/immutable/Vector;
  #418 = Utf8               ()Lscala/collection/immutable/Vector;
  #419 = Utf8               ()Lscala/collection/immutable/Vector<Lscala/Tuple2<Ljava/lang/String;Ljava/lang/String;>;>;
  #420 = Utf8               this
  #421 = Utf8               map$lzycompute
  #422 = Utf8               ()Lscala/collection/immutable/Map;
  #423 = Utf8               ()Lscala/collection/immutable/Map<Ljava/lang/String;Ljava/lang/String;>;
  #424 = NameAndType        #14:#15       // bitmap$0:Z
  #425 = Fieldref           #2.#424       // coursier/core/compatibility/Entities$.bitmap$0:Z
  #426 = NameAndType        #11:#418      // entities:()Lscala/collection/immutable/Vector;
  #427 = Methodref          #2.#426       // coursier/core/compatibility/Entities$.entities:()Lscala/collection/immutable/Vector;
  #428 = Utf8               scala/$less$colon$less$
  #429 = Class              #428          // scala/$less$colon$less$
  #430 = Utf8               Lscala/$less$colon$less$;
  #431 = NameAndType        #6:#430       // MODULE$:Lscala/$less$colon$less$;
  #432 = Fieldref           #429.#431     // scala/$less$colon$less$.MODULE$:Lscala/$less$colon$less$;
  #433 = Utf8               refl
  #434 = Utf8               ()Lscala/$eq$colon$eq;
  #435 = NameAndType        #433:#434     // refl:()Lscala/$eq$colon$eq;
  #436 = Methodref          #429.#435     // scala/$less$colon$less$.refl:()Lscala/$eq$colon$eq;
  #437 = Utf8               toMap
  #438 = Utf8               (Lscala/$less$colon$less;)Lscala/collection/immutable/Map;
  #439 = NameAndType        #437:#438     // toMap:(Lscala/$less$colon$less;)Lscala/collection/immutable/Map;
  #440 = Methodref          #415.#439     // scala/collection/immutable/Vector.toMap:(Lscala/$less$colon$less;)Lscala/collection/immutable/Map;
  #441 = NameAndType        #8:#9         // map:Lscala/collection/immutable/Map;
  #442 = Fieldref           #2.#441       // coursier/core/compatibility/Entities$.map:Lscala/collection/immutable/Map;
  #443 = Utf8               java/lang/Throwable
  #444 = Class              #443          // java/lang/Throwable
  #445 = NameAndType        #421:#422     // map$lzycompute:()Lscala/collection/immutable/Map;
  #446 = Methodref          #2.#445       // coursier/core/compatibility/Entities$.map$lzycompute:()Lscala/collection/immutable/Map;
  #447 = Utf8               scala/collection/immutable/Map
  #448 = Class              #447          // scala/collection/immutable/Map
  #449 = Methodref          #4.#19        // java/lang/Object."<init>":()V
  #450 = Utf8               Signature
  #451 = Utf8               Code
  #452 = Utf8               LineNumberTable
  #453 = Utf8               LocalVariableTable
  #454 = Utf8               StackMapTable
  #455 = Utf8               SourceFile
  #456 = Utf8               ScalaInlineInfo
  #457 = Utf8               Scala
{
  public static final coursier.core.compatibility.Entities$ MODULE$;
    descriptor: Lcoursier/core/compatibility/Entities$;
    flags: (0x0019) ACC_PUBLIC, ACC_STATIC, ACC_FINAL

  private static scala.collection.immutable.Map<java.lang.String, java.lang.String> map;
    descriptor: Lscala/collection/immutable/Map;
    flags: (0x000a) ACC_PRIVATE, ACC_STATIC
    Signature: #10                          // Lscala/collection/immutable/Map<Ljava/lang/String;Ljava/lang/String;>;

  private static final scala.collection.immutable.Vector<scala.Tuple2<java.lang.String, java.lang.String>> entities;
    descriptor: Lscala/collection/immutable/Vector;
    flags: (0x001a) ACC_PRIVATE, ACC_STATIC, ACC_FINAL
    Signature: #13                          // Lscala/collection/immutable/Vector<Lscala/Tuple2<Ljava/lang/String;Ljava/lang/String;>;>;

  private static volatile boolean bitmap$0;
    descriptor: Z
    flags: (0x004a) ACC_PRIVATE, ACC_STATIC, ACC_VOLATILE

  public static {};
    descriptor: ()V
    flags: (0x0009) ACC_PUBLIC, ACC_STATIC
    Code:
      stack=9, locals=0, args_size=0
         0: new           #2                  // class coursier/core/compatibility/Entities$
         3: dup
         4: invokespecial #20                 // Method "<init>":()V
         7: putstatic     #22                 // Field MODULE$:Lcoursier/core/compatibility/Entities$;
        10: getstatic     #27                 // Field scala/package$.MODULE$:Lscala/package$;
        13: invokevirtual #31                 // Method scala/package$.Vector:()Lscala/collection/immutable/Vector$;
        16: getstatic     #36                 // Field scala/runtime/ScalaRunTime$.MODULE$:Lscala/runtime/ScalaRunTime$;
        19: bipush        90
        21: anewarray     #38                 // class scala/Tuple2
        24: dup
        25: iconst_0
        26: new           #38                 // class scala/Tuple2
        29: dup
        30: ldc           #40                 // String &nbsp;
        32: ldc           #42                 // String &#160;
        34: invokespecial #45                 // Method scala/Tuple2."<init>":(Ljava/lang/Object;Ljava/lang/Object;)V
        37: aastore
        38: dup
        39: iconst_1
        40: new           #38                 // class scala/Tuple2
        43: dup
        44: ldc           #47                 // String &iexcl;
        46: ldc           #49                 // String &#161;
        48: invokespecial #45                 // Method scala/Tuple2."<init>":(Ljava/lang/Object;Ljava/lang/Object;)V
        51: aastore
        52: dup
        53: iconst_2
        54: new           #38                 // class scala/Tuple2
        57: dup
        58: ldc           #51                 // String &cent;
        60: ldc           #53                 // String &#162;
        62: invokespecial #45                 // Method scala/Tuple2."<init>":(Ljava/lang/Object;Ljava/lang/Object;)V
        65: aastore
        66: dup
        67: iconst_3
        68: new           #38                 // class scala/Tuple2
        71: dup
        72: ldc           #55                 // String &pound;
        74: ldc           #57                 // String &#163;
        76: invokespecial #45                 // Method scala/Tuple2."<init>":(Ljava/lang/Object;Ljava/lang/Object;)V
        79: aastore
        80: dup
        81: iconst_4
        82: new           #38                 // class scala/Tuple2
        85: dup
        86: ldc           #59                 // String &curren;
        88: ldc           #61                 // String &#164;
        90: invokespecial #45                 // Method scala/Tuple2."<init>":(Ljava/lang/Object;Ljava/lang/Object;)V
        93: aastore
        94: dup
        95: iconst_5
        96: new           #38                 // class scala/Tuple2
        99: dup
       100: ldc           #63                 // String &yen;
       102: ldc           #65                 // String &#165;
       104: invokespecial #45                 // Method scala/Tuple2."<init>":(Ljava/lang/Object;Ljava/lang/Object;)V
       107: aastore
       108: dup
       109: bipush        6
       111: new           #38                 // class scala/Tuple2
       114: dup
       115: ldc           #67                 // String &brvbar;
       117: ldc           #69                 // String &#166;
       119: invokespecial #45                 // Method scala/Tuple2."<init>":(Ljava/lang/Object;Ljava/lang/Object;)V
       122: aastore
       123: dup
       124: bipush        7
       126: new           #38                 // class scala/Tuple2
       129: dup
       130: ldc           #71                 // String &sect;
       132: ldc           #73                 // String &#167;
       134: invokespecial #45                 // Method scala/Tuple2."<init>":(Ljava/lang/Object;Ljava/lang/Object;)V
       137: aastore
       138: dup
       139: bipush        8
       141: new           #38                 // class scala/Tuple2
       144: dup
       145: ldc           #75                 // String &uml;
       147: ldc           #77                 // String &#168;
       149: invokespecial #45                 // Method scala/Tuple2."<init>":(Ljava/lang/Object;Ljava/lang/Object;)V
       152: aastore
       153: dup
       154: bipush        9
       156: new           #38                 // class scala/Tuple2
       159: dup
       160: ldc           #79                 // String &copy;
       162: ldc           #81                 // String &#169;
       164: invokespecial #45                 // Method scala/Tuple2."<init>":(Ljava/lang/Object;Ljava/lang/Object;)V
       167: aastore
       168: dup
       169: bipush        10
       171: new           #38                 // class scala/Tuple2
       174: dup
       175: ldc           #83                 // String &ordf;
       177: ldc           #85                 // String &#170;
       179: invokespecial #45                 // Method scala/Tuple2."<init>":(Ljava/lang/Object;Ljava/lang/Object;)V
       182: aastore
       183: dup
       184: bipush        11
       186: new           #38                 // class scala/Tuple2
       189: dup
       190: ldc           #87                 // String &laquo;
       192: ldc           #89                 // String &#171;
       194: invokespecial #45                 // Method scala/Tuple2."<init>":(Ljava/lang/Object;Ljava/lang/Object;)V
       197: aastore
       198: dup
       199: bipush        12
       201: new           #38                 // class scala/Tuple2
       204: dup
       205: ldc           #91                 // String &not;
       207: ldc           #93                 // String &#172;
       209: invokespecial #45                 // Method scala/Tuple2."<init>":(Ljava/lang/Object;Ljava/lang/Object;)V
       212: aastore
       213: dup
       214: bipush        13
       216: new           #38                 // class scala/Tuple2
       219: dup
       220: ldc           #95                 // String &shy;
       222: ldc           #97                 // String &#173;
       224: invokespecial #45                 // Method scala/Tuple2."<init>":(Ljava/lang/Object;Ljava/lang/Object;)V
       227: aastore
       228: dup
       229: bipush        14
       231: new           #38                 // class scala/Tuple2
       234: dup
       235: ldc           #99                 // String &reg;
       237: ldc           #101                // String &#174;
       239: invokespecial #45                 // Method scala/Tuple2."<init>":(Ljava/lang/Object;Ljava/lang/Object;)V
       242: aastore
       243: dup
       244: bipush        15
       246: new           #38                 // class scala/Tuple2
       249: dup
       250: ldc           #103                // String &macr;
       252: ldc           #105                // String &#175;
       254: invokespecial #45                 // Method scala/Tuple2."<init>":(Ljava/lang/Object;Ljava/lang/Object;)V
       257: aastore
       258: dup
       259: bipush        16
       261: new           #38                 // class scala/Tuple2
       264: dup
       265: ldc           #107                // String &deg;
       267: ldc           #109                // String &#176;
       269: invokespecial #45                 // Method scala/Tuple2."<init>":(Ljava/lang/Object;Ljava/lang/Object;)V
       272: aastore
       273: dup
       274: bipush        17
       276: new           #38                 // class scala/Tuple2
       279: dup
       280: ldc           #111                // String &plusmn;
       282: ldc           #113                // String &#177;
       284: invokespecial #45                 // Method scala/Tuple2."<init>":(Ljava/lang/Object;Ljava/lang/Object;)V
       287: aastore
       288: dup
       289: bipush        18
       291: new           #38                 // class scala/Tuple2
       294: dup
       295: ldc           #115                // String &acute;
       297: ldc           #117                // String &#180;
       299: invokespecial #45                 // Method scala/Tuple2."<init>":(Ljava/lang/Object;Ljava/lang/Object;)V
       302: aastore
       303: dup
       304: bipush        19
       306: new           #38                 // class scala/Tuple2
       309: dup
       310: ldc           #119                // String &micro;
       312: ldc           #121                // String &#181;
       314: invokespecial #45                 // Method scala/Tuple2."<init>":(Ljava/lang/Object;Ljava/lang/Object;)V
       317: aastore
       318: dup
       319: bipush        20
       321: new           #38                 // class scala/Tuple2
       324: dup
       325: ldc           #123                // String &para;
       327: ldc           #125                // String &#182;
       329: invokespecial #45                 // Method scala/Tuple2."<init>":(Ljava/lang/Object;Ljava/lang/Object;)V
       332: aastore
       333: dup
       334: bipush        21
       336: new           #38                 // class scala/Tuple2
       339: dup
       340: ldc           #127                // String &middot;
       342: ldc           #129                // String &#183;
       344: invokespecial #45                 // Method scala/Tuple2."<init>":(Ljava/lang/Object;Ljava/lang/Object;)V
       347: aastore
       348: dup
       349: bipush        22
       351: new           #38                 // class scala/Tuple2
       354: dup
       355: ldc           #131                // String &cedil;
       357: ldc           #133                // String &#184;
       359: invokespecial #45                 // Method scala/Tuple2."<init>":(Ljava/lang/Object;Ljava/lang/Object;)V
       362: aastore
       363: dup
       364: bipush        23
       366: new           #38                 // class scala/Tuple2
       369: dup
       370: ldc           #135                // String &ordm;
       372: ldc           #137                // String &#186;
       374: invokespecial #45                 // Method scala/Tuple2."<init>":(Ljava/lang/Object;Ljava/lang/Object;)V
       377: aastore
       378: dup
       379: bipush        24
       381: new           #38                 // class scala/Tuple2
       384: dup
       385: ldc           #139                // String &raquo;
       387: ldc           #141                // String &#187;
       389: invokespecial #45                 // Method scala/Tuple2."<init>":(Ljava/lang/Object;Ljava/lang/Object;)V
       392: aastore
       393: dup
       394: bipush        25
       396: new           #38                 // class scala/Tuple2
       399: dup
       400: ldc           #143                // String &iquest;
       402: ldc           #145                // String &#191;
       404: invokespecial #45                 // Method scala/Tuple2."<init>":(Ljava/lang/Object;Ljava/lang/Object;)V
       407: aastore
       408: dup
       409: bipush        26
       411: new           #38                 // class scala/Tuple2
       414: dup
       415: ldc           #147                // String &Agrave;
       417: ldc           #149                // String &#192;
       419: invokespecial #45                 // Method scala/Tuple2."<init>":(Ljava/lang/Object;Ljava/lang/Object;)V
       422: aastore
       423: dup
       424: bipush        27
       426: new           #38                 // class scala/Tuple2
       429: dup
       430: ldc           #151                // String &Aacute;
       432: ldc           #153                // String &#193;
       434: invokespecial #45                 // Method scala/Tuple2."<init>":(Ljava/lang/Object;Ljava/lang/Object;)V
       437: aastore
       438: dup
       439: bipush        28
       441: new           #38                 // class scala/Tuple2
       444: dup
       445: ldc           #155                // String &Acirc;
       447: ldc           #157                // String &#194;
       449: invokespecial #45                 // Method scala/Tuple2."<init>":(Ljava/lang/Object;Ljava/lang/Object;)V
       452: aastore
       453: dup
       454: bipush        29
       456: new           #38                 // class scala/Tuple2
       459: dup
       460: ldc           #159                // String &Atilde;
       462: ldc           #161                // String &#195;
       464: invokespecial #45                 // Method scala/Tuple2."<init>":(Ljava/lang/Object;Ljava/lang/Object;)V
       467: aastore
       468: dup
       469: bipush        30
       471: new           #38                 // class scala/Tuple2
       474: dup
       475: ldc           #163                // String &Auml;
       477: ldc           #165                // String &#196;
       479: invokespecial #45                 // Method scala/Tuple2."<init>":(Ljava/lang/Object;Ljava/lang/Object;)V
       482: aastore
       483: dup
       484: bipush        31
       486: new           #38                 // class scala/Tuple2
       489: dup
       490: ldc           #167                // String &Aring;
       492: ldc           #169                // String &#197;
       494: invokespecial #45                 // Method scala/Tuple2."<init>":(Ljava/lang/Object;Ljava/lang/Object;)V
       497: aastore
       498: dup
       499: bipush        32
       501: new           #38                 // class scala/Tuple2
       504: dup
       505: ldc           #171                // String &AElig;
       507: ldc           #173                // String &#198;
       509: invokespecial #45                 // Method scala/Tuple2."<init>":(Ljava/lang/Object;Ljava/lang/Object;)V
       512: aastore
       513: dup
       514: bipush        33
       516: new           #38                 // class scala/Tuple2
       519: dup
       520: ldc           #175                // String &Ccedil;
       522: ldc           #177                // String &#199;
       524: invokespecial #45                 // Method scala/Tuple2."<init>":(Ljava/lang/Object;Ljava/lang/Object;)V
       527: aastore
       528: dup
       529: bipush        34
       531: new           #38                 // class scala/Tuple2
       534: dup
       535: ldc           #179                // String &Egrave;
       537: ldc           #181                // String &#200;
       539: invokespecial #45                 // Method scala/Tuple2."<init>":(Ljava/lang/Object;Ljava/lang/Object;)V
       542: aastore
       543: dup
       544: bipush        35
       546: new           #38                 // class scala/Tuple2
       549: dup
       550: ldc           #183                // String &Eacute;
       552: ldc           #185                // String &#201;
       554: invokespecial #45                 // Method scala/Tuple2."<init>":(Ljava/lang/Object;Ljava/lang/Object;)V
       557: aastore
       558: dup
       559: bipush        36
       561: new           #38                 // class scala/Tuple2
       564: dup
       565: ldc           #187                // String &Ecirc;
       567: ldc           #189                // String &#202;
       569: invokespecial #45                 // Method scala/Tuple2."<init>":(Ljava/lang/Object;Ljava/lang/Object;)V
       572: aastore
       573: dup
       574: bipush        37
       576: new           #38                 // class scala/Tuple2
       579: dup
       580: ldc           #191                // String &Euml;
       582: ldc           #193                // String &#203;
       584: invokespecial #45                 // Method scala/Tuple2."<init>":(Ljava/lang/Object;Ljava/lang/Object;)V
       587: aastore
       588: dup
       589: bipush        38
       591: new           #38                 // class scala/Tuple2
       594: dup
       595: ldc           #195                // String &Igrave;
       597: ldc           #197                // String &#204;
       599: invokespecial #45                 // Method scala/Tuple2."<init>":(Ljava/lang/Object;Ljava/lang/Object;)V
       602: aastore
       603: dup
       604: bipush        39
       606: new           #38                 // class scala/Tuple2
       609: dup
       610: ldc           #199                // String &Iacute;
       612: ldc           #201                // String &#205;
       614: invokespecial #45                 // Method scala/Tuple2."<init>":(Ljava/lang/Object;Ljava/lang/Object;)V
       617: aastore
       618: dup
       619: bipush        40
       621: new           #38                 // class scala/Tuple2
       624: dup
       625: ldc           #203                // String &Icirc;
       627: ldc           #205                // String &#206;
       629: invokespecial #45                 // Method scala/Tuple2."<init>":(Ljava/lang/Object;Ljava/lang/Object;)V
       632: aastore
       633: dup
       634: bipush        41
       636: new           #38                 // class scala/Tuple2
       639: dup
       640: ldc           #207                // String &Iuml;
       642: ldc           #209                // String &#207;
       644: invokespecial #45                 // Method scala/Tuple2."<init>":(Ljava/lang/Object;Ljava/lang/Object;)V
       647: aastore
       648: dup
       649: bipush        42
       651: new           #38                 // class scala/Tuple2
       654: dup
       655: ldc           #211                // String &ETH;
       657: ldc           #213                // String &#208;
       659: invokespecial #45                 // Method scala/Tuple2."<init>":(Ljava/lang/Object;Ljava/lang/Object;)V
       662: aastore
       663: dup
       664: bipush        43
       666: new           #38                 // class scala/Tuple2
       669: dup
       670: ldc           #215                // String &Ntilde;
       672: ldc           #217                // String &#209;
       674: invokespecial #45                 // Method scala/Tuple2."<init>":(Ljava/lang/Object;Ljava/lang/Object;)V
       677: aastore
       678: dup
       679: bipush        44
       681: new           #38                 // class scala/Tuple2
       684: dup
       685: ldc           #219                // String &Ograve;
       687: ldc           #221                // String &#210;
       689: invokespecial #45                 // Method scala/Tuple2."<init>":(Ljava/lang/Object;Ljava/lang/Object;)V
       692: aastore
       693: dup
       694: bipush        45
       696: new           #38                 // class scala/Tuple2
       699: dup
       700: ldc           #223                // String &Oacute;
       702: ldc           #225                // String &#211;
       704: invokespecial #45                 // Method scala/Tuple2."<init>":(Ljava/lang/Object;Ljava/lang/Object;)V
       707: aastore
       708: dup
       709: bipush        46
       711: new           #38                 // class scala/Tuple2
       714: dup
       715: ldc           #227                // String &Ocirc;
       717: ldc           #229                // String &#212;
       719: invokespecial #45                 // Method scala/Tuple2."<init>":(Ljava/lang/Object;Ljava/lang/Object;)V
       722: aastore
       723: dup
       724: bipush        47
       726: new           #38                 // class scala/Tuple2
       729: dup
       730: ldc           #231                // String &Otilde;
       732: ldc           #233                // String &#213;
       734: invokespecial #45                 // Method scala/Tuple2."<init>":(Ljava/lang/Object;Ljava/lang/Object;)V
       737: aastore
       738: dup
       739: bipush        48
       741: new           #38                 // class scala/Tuple2
       744: dup
       745: ldc           #235                // String &Ouml;
       747: ldc           #237                // String &#214;
       749: invokespecial #45                 // Method scala/Tuple2."<init>":(Ljava/lang/Object;Ljava/lang/Object;)V
       752: aastore
       753: dup
       754: bipush        49
       756: new           #38                 // class scala/Tuple2
       759: dup
       760: ldc           #239                // String &times;
       762: ldc           #241                // String &#215;
       764: invokespecial #45                 // Method scala/Tuple2."<init>":(Ljava/lang/Object;Ljava/lang/Object;)V
       767: aastore
       768: dup
       769: bipush        50
       771: new           #38                 // class scala/Tuple2
       774: dup
       775: ldc           #243                // String &Oslash;
       777: ldc           #245                // String &#216;
       779: invokespecial #45                 // Method scala/Tuple2."<init>":(Ljava/lang/Object;Ljava/lang/Object;)V
       782: aastore
       783: dup
       784: bipush        51
       786: new           #38                 // class scala/Tuple2
       789: dup
       790: ldc           #247                // String &Ugrave;
       792: ldc           #249                // String &#217;
       794: invokespecial #45                 // Method scala/Tuple2."<init>":(Ljava/lang/Object;Ljava/lang/Object;)V
       797: aastore
       798: dup
       799: bipush        52
       801: new           #38                 // class scala/Tuple2
       804: dup
       805: ldc           #251                // String &Uacute;
       807: ldc           #253                // String &#218;
       809: invokespecial #45                 // Method scala/Tuple2."<init>":(Ljava/lang/Object;Ljava/lang/Object;)V
       812: aastore
       813: dup
       814: bipush        53
       816: new           #38                 // class scala/Tuple2
       819: dup
       820: ldc           #255                // String &Ucirc;
       822: ldc_w         #257                // String &#219;
       825: invokespecial #45                 // Method scala/Tuple2."<init>":(Ljava/lang/Object;Ljava/lang/Object;)V
       828: aastore
       829: dup
       830: bipush        54
       832: new           #38                 // class scala/Tuple2
       835: dup
       836: ldc_w         #259                // String &Uuml;
       839: ldc_w         #261                // String &#220;
       842: invokespecial #45                 // Method scala/Tuple2."<init>":(Ljava/lang/Object;Ljava/lang/Object;)V
       845: aastore
       846: dup
       847: bipush        55
       849: new           #38                 // class scala/Tuple2
       852: dup
       853: ldc_w         #263                // String &Yacute;
       856: ldc_w         #265                // String &#221;
       859: invokespecial #45                 // Method scala/Tuple2."<init>":(Ljava/lang/Object;Ljava/lang/Object;)V
       862: aastore
       863: dup
       864: bipush        56
       866: new           #38                 // class scala/Tuple2
       869: dup
       870: ldc_w         #267                // String &THORN;
       873: ldc_w         #269                // String &#222;
       876: invokespecial #45                 // Method scala/Tuple2."<init>":(Ljava/lang/Object;Ljava/lang/Object;)V
       879: aastore
       880: dup
       881: bipush        57
       883: new           #38                 // class scala/Tuple2
       886: dup
       887: ldc_w         #271                // String &szlig;
       890: ldc_w         #273                // String &#223;
       893: invokespecial #45                 // Method scala/Tuple2."<init>":(Ljava/lang/Object;Ljava/lang/Object;)V
       896: aastore
       897: dup
       898: bipush        58
       900: new           #38                 // class scala/Tuple2
       903: dup
       904: ldc_w         #275                // String &agrave;
       907: ldc_w         #277                // String &#224;
       910: invokespecial #45                 // Method scala/Tuple2."<init>":(Ljava/lang/Object;Ljava/lang/Object;)V
       913: aastore
       914: dup
       915: bipush        59
       917: new           #38                 // class scala/Tuple2
       920: dup
       921: ldc_w         #279                // String &aacute;
       924: ldc_w         #281                // String &#225;
       927: invokespecial #45                 // Method scala/Tuple2."<init>":(Ljava/lang/Object;Ljava/lang/Object;)V
       930: aastore
       931: dup
       932: bipush        60
       934: new           #38                 // class scala/Tuple2
       937: dup
       938: ldc_w         #283                // String &acirc;
       941: ldc_w         #285                // String &#226;
       944: invokespecial #45                 // Method scala/Tuple2."<init>":(Ljava/lang/Object;Ljava/lang/Object;)V
       947: aastore
       948: dup
       949: bipush        61
       951: new           #38                 // class scala/Tuple2
       954: dup
       955: ldc_w         #287                // String &atilde;
       958: ldc_w         #289                // String &#227;
       961: invokespecial #45                 // Method scala/Tuple2."<init>":(Ljava/lang/Object;Ljava/lang/Object;)V
       964: aastore
       965: dup
       966: bipush        62
       968: new           #38                 // class scala/Tuple2
       971: dup
       972: ldc_w         #291                // String &auml;
       975: ldc_w         #293                // String &#228;
       978: invokespecial #45                 // Method scala/Tuple2."<init>":(Ljava/lang/Object;Ljava/lang/Object;)V
       981: aastore
       982: dup
       983: bipush        63
       985: new           #38                 // class scala/Tuple2
       988: dup
       989: ldc_w         #295                // String &aring;
       992: ldc_w         #297                // String &#229;
       995: invokespecial #45                 // Method scala/Tuple2."<init>":(Ljava/lang/Object;Ljava/lang/Object;)V
       998: aastore
       999: dup
      1000: bipush        64
      1002: new           #38                 // class scala/Tuple2
      1005: dup
      1006: ldc_w         #299                // String &aelig;
      1009: ldc_w         #301                // String &#230;
      1012: invokespecial #45                 // Method scala/Tuple2."<init>":(Ljava/lang/Object;Ljava/lang/Object;)V
      1015: aastore
      1016: dup
      1017: bipush        65
      1019: new           #38                 // class scala/Tuple2
      1022: dup
      1023: ldc_w         #303                // String &ccedil;
      1026: ldc_w         #305                // String &#231;
      1029: invokespecial #45                 // Method scala/Tuple2."<init>":(Ljava/lang/Object;Ljava/lang/Object;)V
      1032: aastore
      1033: dup
      1034: bipush        66
      1036: new           #38                 // class scala/Tuple2
      1039: dup
      1040: ldc_w         #307                // String &egrave;
      1043: ldc_w         #309                // String &#232;
      1046: invokespecial #45                 // Method scala/Tuple2."<init>":(Ljava/lang/Object;Ljava/lang/Object;)V
      1049: aastore
      1050: dup
      1051: bipush        67
      1053: new           #38                 // class scala/Tuple2
      1056: dup
      1057: ldc_w         #311                // String &eacute;
      1060: ldc_w         #313                // String &#233;
      1063: invokespecial #45                 // Method scala/Tuple2."<init>":(Ljava/lang/Object;Ljava/lang/Object;)V
      1066: aastore
      1067: dup
      1068: bipush        68
      1070: new           #38                 // class scala/Tuple2
      1073: dup
      1074: ldc_w         #315                // String &ecirc;
      1077: ldc_w         #317                // String &#234;
      1080: invokespecial #45                 // Method scala/Tuple2."<init>":(Ljava/lang/Object;Ljava/lang/Object;)V
      1083: aastore
      1084: dup
      1085: bipush        69
      1087: new           #38                 // class scala/Tuple2
      1090: dup
      1091: ldc_w         #319                // String &euml;
      1094: ldc_w         #321                // String &#235;
      1097: invokespecial #45                 // Method scala/Tuple2."<init>":(Ljava/lang/Object;Ljava/lang/Object;)V
      1100: aastore
      1101: dup
      1102: bipush        70
      1104: new           #38                 // class scala/Tuple2
      1107: dup
      1108: ldc_w         #323                // String &igrave;
      1111: ldc_w         #325                // String &#236;
      1114: invokespecial #45                 // Method scala/Tuple2."<init>":(Ljava/lang/Object;Ljava/lang/Object;)V
      1117: aastore
      1118: dup
      1119: bipush        71
      1121: new           #38                 // class scala/Tuple2
      1124: dup
      1125: ldc_w         #327                // String &iacute;
      1128: ldc_w         #329                // String &#237;
      1131: invokespecial #45                 // Method scala/Tuple2."<init>":(Ljava/lang/Object;Ljava/lang/Object;)V
      1134: aastore
      1135: dup
      1136: bipush        72
      1138: new           #38                 // class scala/Tuple2
      1141: dup
      1142: ldc_w         #331                // String &icirc;
      1145: ldc_w         #333                // String &#238;
      1148: invokespecial #45                 // Method scala/Tuple2."<init>":(Ljava/lang/Object;Ljava/lang/Object;)V
      1151: aastore
      1152: dup
      1153: bipush        73
      1155: new           #38                 // class scala/Tuple2
      1158: dup
      1159: ldc_w         #335                // String &iuml;
      1162: ldc_w         #337                // String &#239;
      1165: invokespecial #45                 // Method scala/Tuple2."<init>":(Ljava/lang/Object;Ljava/lang/Object;)V
      1168: aastore
      1169: dup
      1170: bipush        74
      1172: new           #38                 // class scala/Tuple2
      1175: dup
      1176: ldc_w         #339                // String &eth;
      1179: ldc_w         #341                // String &#240;
      1182: invokespecial #45                 // Method scala/Tuple2."<init>":(Ljava/lang/Object;Ljava/lang/Object;)V
      1185: aastore
      1186: dup
      1187: bipush        75
      1189: new           #38                 // class scala/Tuple2
      1192: dup
      1193: ldc_w         #343                // String &ntilde;
      1196: ldc_w         #345                // String &#241;
      1199: invokespecial #45                 // Method scala/Tuple2."<init>":(Ljava/lang/Object;Ljava/lang/Object;)V
      1202: aastore
      1203: dup
      1204: bipush        76
      1206: new           #38                 // class scala/Tuple2
      1209: dup
      1210: ldc_w         #347                // String &ograve;
      1213: ldc_w         #349                // String &#242;
      1216: invokespecial #45                 // Method scala/Tuple2."<init>":(Ljava/lang/Object;Ljava/lang/Object;)V
      1219: aastore
      1220: dup
      1221: bipush        77
      1223: new           #38                 // class scala/Tuple2
      1226: dup
      1227: ldc_w         #351                // String &oacute;
      1230: ldc_w         #353                // String &#243;
      1233: invokespecial #45                 // Method scala/Tuple2."<init>":(Ljava/lang/Object;Ljava/lang/Object;)V
      1236: aastore
      1237: dup
      1238: bipush        78
      1240: new           #38                 // class scala/Tuple2
      1243: dup
      1244: ldc_w         #355                // String &ocirc;
      1247: ldc_w         #357                // String &#244;
      1250: invokespecial #45                 // Method scala/Tuple2."<init>":(Ljava/lang/Object;Ljava/lang/Object;)V
      1253: aastore
      1254: dup
      1255: bipush        79
      1257: new           #38                 // class scala/Tuple2
      1260: dup
      1261: ldc_w         #359                // String &otilde;
      1264: ldc_w         #361                // String &#245;
      1267: invokespecial #45                 // Method scala/Tuple2."<init>":(Ljava/lang/Object;Ljava/lang/Object;)V
      1270: aastore
      1271: dup
      1272: bipush        80
      1274: new           #38                 // class scala/Tuple2
      1277: dup
      1278: ldc_w         #363                // String &ouml;
      1281: ldc_w         #365                // String &#246;
      1284: invokespecial #45                 // Method scala/Tuple2."<init>":(Ljava/lang/Object;Ljava/lang/Object;)V
      1287: aastore
      1288: dup
      1289: bipush        81
      1291: new           #38                 // class scala/Tuple2
      1294: dup
      1295: ldc_w         #367                // String &divide;
      1298: ldc_w         #369                // String &#247;
      1301: invokespecial #45                 // Method scala/Tuple2."<init>":(Ljava/lang/Object;Ljava/lang/Object;)V
      1304: aastore
      1305: dup
      1306: bipush        82
      1308: new           #38                 // class scala/Tuple2
      1311: dup
      1312: ldc_w         #371                // String &oslash;
      1315: ldc_w         #373                // String &#248;
      1318: invokespecial #45                 // Method scala/Tuple2."<init>":(Ljava/lang/Object;Ljava/lang/Object;)V
      1321: aastore
      1322: dup
      1323: bipush        83
      1325: new           #38                 // class scala/Tuple2
      1328: dup
      1329: ldc_w         #375                // String &ugrave;
      1332: ldc_w         #377                // String &#249;
      1335: invokespecial #45                 // Method scala/Tuple2."<init>":(Ljava/lang/Object;Ljava/lang/Object;)V
      1338: aastore
      1339: dup
      1340: bipush        84
      1342: new           #38                 // class scala/Tuple2
      1345: dup
      1346: ldc_w         #379                // String &uacute;
      1349: ldc_w         #381                // String &#250;
      1352: invokespecial #45                 // Method scala/Tuple2."<init>":(Ljava/lang/Object;Ljava/lang/Object;)V
      1355: aastore
      1356: dup
      1357: bipush        85
      1359: new           #38                 // class scala/Tuple2
      1362: dup
      1363: ldc_w         #383                // String &ucirc;
      1366: ldc_w         #385                // String &#251;
      1369: invokespecial #45                 // Method scala/Tuple2."<init>":(Ljava/lang/Object;Ljava/lang/Object;)V
      1372: aastore
      1373: dup
      1374: bipush        86
      1376: new           #38                 // class scala/Tuple2
      1379: dup
      1380: ldc_w         #387                // String &uuml;
      1383: ldc_w         #389                // String &#252;
      1386: invokespecial #45                 // Method scala/Tuple2."<init>":(Ljava/lang/Object;Ljava/lang/Object;)V
      1389: aastore
      1390: dup
      1391: bipush        87
      1393: new           #38                 // class scala/Tuple2
      1396: dup
      1397: ldc_w         #391                // String &yacute;
      1400: ldc_w         #393                // String &#253;
      1403: invokespecial #45                 // Method scala/Tuple2."<init>":(Ljava/lang/Object;Ljava/lang/Object;)V
      1406: aastore
      1407: dup
      1408: bipush        88
      1410: new           #38                 // class scala/Tuple2
      1413: dup
      1414: ldc_w         #395                // String &thorn;
      1417: ldc_w         #397                // String &#254;
      1420: invokespecial #45                 // Method scala/Tuple2."<init>":(Ljava/lang/Object;Ljava/lang/Object;)V
      1423: aastore
      1424: dup
      1425: bipush        89
      1427: new           #38                 // class scala/Tuple2
      1430: dup
      1431: ldc_w         #399                // String &yuml;
      1434: ldc_w         #401                // String &#255;
      1437: invokespecial #45                 // Method scala/Tuple2."<init>":(Ljava/lang/Object;Ljava/lang/Object;)V
      1440: aastore
      1441: checkcast     #403                // class "[Ljava/lang/Object;"
      1444: invokevirtual #407                // Method scala/runtime/ScalaRunTime$.wrapRefArray:([Ljava/lang/Object;)Lscala/collection/immutable/ArraySeq;
      1447: invokevirtual #413                // Method scala/collection/immutable/Vector$.apply:(Lscala/collection/immutable/Seq;)Ljava/lang/Object;
      1450: checkcast     #415                // class scala/collection/immutable/Vector
      1453: putstatic     #417                // Field entities:Lscala/collection/immutable/Vector;
      1456: return
      LineNumberTable:
        line 3: 0
        line 7: 10
        line 8: 26
        line 9: 40
        line 10: 54
        line 11: 68
        line 12: 82
        line 13: 96
        line 14: 111
        line 15: 126
        line 16: 141
        line 17: 156
        line 18: 171
        line 19: 186
        line 20: 201
        line 21: 216
        line 22: 231
        line 23: 246
        line 24: 261
        line 25: 276
        line 26: 291
        line 27: 306
        line 28: 321
        line 29: 336
        line 30: 351
        line 31: 366
        line 32: 381
        line 33: 396
        line 34: 411
        line 35: 426
        line 36: 441
        line 37: 456
        line 38: 471
        line 39: 486
        line 40: 501
        line 41: 516
        line 42: 531
        line 43: 546
        line 44: 561
        line 45: 576
        line 46: 591
        line 47: 606
        line 48: 621
        line 49: 636
        line 50: 651
        line 51: 666
        line 52: 681
        line 53: 696
        line 54: 711
        line 55: 726
        line 56: 741
        line 57: 756
        line 58: 771
        line 59: 786
        line 60: 801
        line 61: 816
        line 62: 832
        line 63: 849
        line 64: 866
        line 65: 883
        line 66: 900
        line 67: 917
        line 68: 934
        line 69: 951
        line 70: 968
        line 71: 985
        line 72: 1002
        line 73: 1019
        line 74: 1036
        line 75: 1053
        line 76: 1070
        line 77: 1087
        line 78: 1104
        line 79: 1121
        line 80: 1138
        line 81: 1155
        line 82: 1172
        line 83: 1189
        line 84: 1206
        line 85: 1223
        line 86: 1240
        line 87: 1257
        line 88: 1274
        line 89: 1291
        line 90: 1308
        line 91: 1325
        line 92: 1342
        line 93: 1359
        line 94: 1376
        line 95: 1393
        line 96: 1410
        line 97: 1427
        line 7: 1453
        line 3: 1456

  public scala.collection.immutable.Vector<scala.Tuple2<java.lang.String, java.lang.String>> entities();
    descriptor: ()Lscala/collection/immutable/Vector;
    flags: (0x0001) ACC_PUBLIC
    Code:
      stack=1, locals=1, args_size=1
         0: getstatic     #417                // Field entities:Lscala/collection/immutable/Vector;
         3: areturn
      LineNumberTable:
        line 7: 0
      LocalVariableTable:
        Start  Length  Slot  Name   Signature
            0       4     0  this   Lcoursier/core/compatibility/Entities$;
    Signature: #419                         // ()Lscala/collection/immutable/Vector<Lscala/Tuple2<Ljava/lang/String;Ljava/lang/String;>;>;

  private scala.collection.immutable.Map<java.lang.String, java.lang.String> map$lzycompute();
    descriptor: ()Lscala/collection/immutable/Map;
    flags: (0x0002) ACC_PRIVATE
    Code:
      stack=2, locals=2, args_size=1
         0: aload_0
         1: dup
         2: astore_1
         3: monitorenter
         4: getstatic     #425                // Field bitmap$0:Z
         7: ifne          30
        10: aload_0
        11: invokevirtual #427                // Method entities:()Lscala/collection/immutable/Vector;
        14: getstatic     #432                // Field scala/$less$colon$less$.MODULE$:Lscala/$less$colon$less$;
        17: invokevirtual #436                // Method scala/$less$colon$less$.refl:()Lscala/$eq$colon$eq;
        20: invokevirtual #440                // Method scala/collection/immutable/Vector.toMap:(Lscala/$less$colon$less;)Lscala/collection/immutable/Map;
        23: putstatic     #442                // Field map:Lscala/collection/immutable/Map;
        26: iconst_1
        27: putstatic     #425                // Field bitmap$0:Z
        30: aload_1
        31: monitorexit
        32: goto          38
        35: aload_1
        36: monitorexit
        37: athrow
        38: getstatic     #442                // Field map:Lscala/collection/immutable/Map;
        41: areturn
      Exception table:
         from    to  target type
             4    30    35   any
      StackMapTable: number_of_entries = 3
        frame_type = 252 /* append */
          offset_delta = 30
          locals = [ class coursier/core/compatibility/Entities$ ]
        frame_type = 68 /* same_locals_1_stack_item */
          stack = [ class java/lang/Throwable ]
        frame_type = 2 /* same */
      LineNumberTable:
        line 100: 0
      LocalVariableTable:
        Start  Length  Slot  Name   Signature
            0      42     0  this   Lcoursier/core/compatibility/Entities$;
    Signature: #423                         // ()Lscala/collection/immutable/Map<Ljava/lang/String;Ljava/lang/String;>;

  public scala.collection.immutable.Map<java.lang.String, java.lang.String> map();
    descriptor: ()Lscala/collection/immutable/Map;
    flags: (0x0001) ACC_PUBLIC
    Code:
      stack=1, locals=1, args_size=1
         0: getstatic     #425                // Field bitmap$0:Z
         3: ifne          13
         6: aload_0
         7: invokespecial #446                // Method map$lzycompute:()Lscala/collection/immutable/Map;
        10: goto          16
        13: getstatic     #442                // Field map:Lscala/collection/immutable/Map;
        16: areturn
      StackMapTable: number_of_entries = 2
        frame_type = 13 /* same */
        frame_type = 66 /* same_locals_1_stack_item */
          stack = [ class scala/collection/immutable/Map ]
      LineNumberTable:
        line 100: 0
      LocalVariableTable:
        Start  Length  Slot  Name   Signature
            0      17     0  this   Lcoursier/core/compatibility/Entities$;
    Signature: #423                         // ()Lscala/collection/immutable/Map<Ljava/lang/String;Ljava/lang/String;>;

  private coursier.core.compatibility.Entities$();
    descriptor: ()V
    flags: (0x0002) ACC_PRIVATE
    Code:
      stack=1, locals=1, args_size=1
         0: aload_0
         1: invokespecial #449                // Method java/lang/Object."<init>":()V
         4: return
      LineNumberTable:
        line 101: 0
        line 3: 4
      LocalVariableTable:
        Start  Length  Slot  Name   Signature
            0       5     0  this   Lcoursier/core/compatibility/Entities$;
}
SourceFile: "Entities.scala"
  ScalaInlineInfo: length = 0x18 (unknown attribute)
   01 01 00 04 00 12 00 11 01 00 0B 01 A2 01 00 08
   01 A6 01 01 A5 01 A6 01
  Scala: length = 0x0 (unknown attribute)

