Classfile /Users/mw/Projects/slang-braindump/.jar/jar11/assemble/slang-braindump/assemble/content/org/sireum/cli/CliOpt$Opt$.class
  Last modified May 29, 2022; size 2079 bytes
  SHA-256 checksum a3d0eb5d4825b13aeedcbbdaa09c50905fff65d1527777e8aed6169aa3698ce6
  Compiled from "CliOpt.scala"
public class org.sireum.cli.CliOpt$Opt$
  minor version: 0
  major version: 52
  flags: (0x0021) ACC_PUBLIC, ACC_SUPER
  this_class: #2                          // org/sireum/cli/CliOpt$Opt$
  super_class: #4                         // java/lang/Object
  interfaces: 0, fields: 1, methods: 4, attributes: 4
Constant pool:
   #1 = Utf8               org/sireum/cli/CliOpt$Opt$
   #2 = Class              #1             // org/sireum/cli/CliOpt$Opt$
   #3 = Utf8               java/lang/Object
   #4 = Class              #3             // java/lang/Object
   #5 = Utf8               CliOpt.scala
   #6 = Utf8               org/sireum/cli/CliOpt$Opt
   #7 = Class              #6             // org/sireum/cli/CliOpt$Opt
   #8 = Utf8               org/sireum/cli/CliOpt
   #9 = Class              #8             // org/sireum/cli/CliOpt
  #10 = Utf8               Opt
  #11 = Utf8               Opt$
  #12 = Utf8               org/sireum/cli/CliOpt$Type
  #13 = Class              #12            // org/sireum/cli/CliOpt$Type
  #14 = Utf8               Type
  #15 = Utf8               MODULE$
  #16 = Utf8               Lorg/sireum/cli/CliOpt$Opt$;
  #17 = Utf8               <clinit>
  #18 = Utf8               ()V
  #19 = Utf8               <init>
  #20 = NameAndType        #19:#18        // "<init>":()V
  #21 = Methodref          #2.#20         // org/sireum/cli/CliOpt$Opt$."<init>":()V
  #22 = NameAndType        #15:#16        // MODULE$:Lorg/sireum/cli/CliOpt$Opt$;
  #23 = Fieldref           #2.#22         // org/sireum/cli/CliOpt$Opt$.MODULE$:Lorg/sireum/cli/CliOpt$Opt$;
  #24 = Utf8               apply
  #25 = Utf8               (Ljava/lang/String;Ljava/lang/String;Lorg/sireum/Option;Lorg/sireum/cli/CliOpt$Type;Ljava/lang/String;)Lorg/sireum/cli/CliOpt$Opt;
  #26 = Utf8               (Ljava/lang/String;Ljava/lang/String;Lorg/sireum/Option<Lorg/sireum/C;>;Lorg/sireum/cli/CliOpt$Type;Ljava/lang/String;)Lorg/sireum/cli/CliOpt$Opt;
  #27 = Utf8               name
  #28 = Utf8               longKey
  #29 = Utf8               shortKey
  #30 = Utf8               tpe
  #31 = Utf8               description
  #32 = Utf8               (Ljava/lang/String;Ljava/lang/String;Lorg/sireum/Option;Lorg/sireum/cli/CliOpt$Type;Ljava/lang/String;)V
  #33 = NameAndType        #19:#32        // "<init>":(Ljava/lang/String;Ljava/lang/String;Lorg/sireum/Option;Lorg/sireum/cli/CliOpt$Type;Ljava/lang/String;)V
  #34 = Methodref          #7.#33         // org/sireum/cli/CliOpt$Opt."<init>":(Ljava/lang/String;Ljava/lang/String;Lorg/sireum/Option;Lorg/sireum/cli/CliOpt$Type;Ljava/lang/String;)V
  #35 = Utf8               this
  #36 = Utf8               Ljava/lang/String;
  #37 = Utf8               Lorg/sireum/Option;
  #38 = Utf8               Lorg/sireum/cli/CliOpt$Type;
  #39 = Utf8               unapply
  #40 = Utf8               (Lorg/sireum/cli/CliOpt$Opt;)Lscala/Some;
  #41 = Utf8               (Lorg/sireum/cli/CliOpt$Opt;)Lscala/Some<Lscala/Tuple5<Lorg/sireum/String;Lorg/sireum/String;Lorg/sireum/Option<Lorg/sireum/C;>;Lorg/sireum/cli/CliOpt$Type;Lorg/sireum/String;>;>;
  #42 = Utf8               o
  #43 = Utf8               scala/Some
  #44 = Class              #43            // scala/Some
  #45 = Utf8               scala/Tuple5
  #46 = Class              #45            // scala/Tuple5
  #47 = Utf8               org/sireum/String
  #48 = Class              #47            // org/sireum/String
  #49 = Utf8               ()Ljava/lang/String;
  #50 = NameAndType        #27:#49        // name:()Ljava/lang/String;
  #51 = Methodref          #7.#50         // org/sireum/cli/CliOpt$Opt.name:()Ljava/lang/String;
  #52 = Utf8               (Ljava/lang/String;)V
  #53 = NameAndType        #19:#52        // "<init>":(Ljava/lang/String;)V
  #54 = Methodref          #48.#53        // org/sireum/String."<init>":(Ljava/lang/String;)V
  #55 = NameAndType        #28:#49        // longKey:()Ljava/lang/String;
  #56 = Methodref          #7.#55         // org/sireum/cli/CliOpt$Opt.longKey:()Ljava/lang/String;
  #57 = Utf8               ()Lorg/sireum/Option;
  #58 = NameAndType        #29:#57        // shortKey:()Lorg/sireum/Option;
  #59 = Methodref          #7.#58         // org/sireum/cli/CliOpt$Opt.shortKey:()Lorg/sireum/Option;
  #60 = Utf8               ()Lorg/sireum/cli/CliOpt$Type;
  #61 = NameAndType        #30:#60        // tpe:()Lorg/sireum/cli/CliOpt$Type;
  #62 = Methodref          #7.#61         // org/sireum/cli/CliOpt$Opt.tpe:()Lorg/sireum/cli/CliOpt$Type;
  #63 = NameAndType        #31:#49        // description:()Ljava/lang/String;
  #64 = Methodref          #7.#63         // org/sireum/cli/CliOpt$Opt.description:()Ljava/lang/String;
  #65 = Utf8               (Ljava/lang/Object;Ljava/lang/Object;Ljava/lang/Object;Ljava/lang/Object;Ljava/lang/Object;)V
  #66 = NameAndType        #19:#65        // "<init>":(Ljava/lang/Object;Ljava/lang/Object;Ljava/lang/Object;Ljava/lang/Object;Ljava/lang/Object;)V
  #67 = Methodref          #46.#66        // scala/Tuple5."<init>":(Ljava/lang/Object;Ljava/lang/Object;Ljava/lang/Object;Ljava/lang/Object;Ljava/lang/Object;)V
  #68 = Utf8               (Ljava/lang/Object;)V
  #69 = NameAndType        #19:#68        // "<init>":(Ljava/lang/Object;)V
  #70 = Methodref          #44.#69        // scala/Some."<init>":(Ljava/lang/Object;)V
  #71 = Utf8               Lorg/sireum/cli/CliOpt$Opt;
  #72 = Methodref          #4.#20         // java/lang/Object."<init>":()V
  #73 = Utf8               Code
  #74 = Utf8               LineNumberTable
  #75 = Utf8               LocalVariableTable
  #76 = Utf8               Signature
  #77 = Utf8               MethodParameters
  #78 = Utf8               InnerClasses
  #79 = Utf8               SourceFile
  #80 = Utf8               ScalaInlineInfo
  #81 = Utf8               Scala
{
  public static final org.sireum.cli.CliOpt$Opt$ MODULE$;
    descriptor: Lorg/sireum/cli/CliOpt$Opt$;
    flags: (0x0019) ACC_PUBLIC, ACC_STATIC, ACC_FINAL

  public static {};
    descriptor: ()V
    flags: (0x0009) ACC_PUBLIC, ACC_STATIC
    Code:
      stack=2, locals=0, args_size=0
         0: new           #2                  // class org/sireum/cli/CliOpt$Opt$
         3: dup
         4: invokespecial #21                 // Method "<init>":()V
         7: putstatic     #23                 // Field MODULE$:Lorg/sireum/cli/CliOpt$Opt$;
        10: return
      LineNumberTable:
        line 77: 0

  public org.sireum.cli.CliOpt$Opt apply(java.lang.String, java.lang.String, org.sireum.Option<org.sireum.C>, org.sireum.cli.CliOpt$Type, java.lang.String);
    descriptor: (Ljava/lang/String;Ljava/lang/String;Lorg/sireum/Option;Lorg/sireum/cli/CliOpt$Type;Ljava/lang/String;)Lorg/sireum/cli/CliOpt$Opt;
    flags: (0x0001) ACC_PUBLIC
    Code:
      stack=7, locals=6, args_size=6
         0: new           #7                  // class org/sireum/cli/CliOpt$Opt
         3: dup
         4: aload_1
         5: aload_2
         6: aload_3
         7: aload         4
         9: aload         5
        11: invokespecial #34                 // Method org/sireum/cli/CliOpt$Opt."<init>":(Ljava/lang/String;Ljava/lang/String;Lorg/sireum/Option;Lorg/sireum/cli/CliOpt$Type;Ljava/lang/String;)V
        14: areturn
      LineNumberTable:
        line 77: 0
      LocalVariableTable:
        Start  Length  Slot  Name   Signature
            0      15     0  this   Lorg/sireum/cli/CliOpt$Opt$;
            0      15     1  name   Ljava/lang/String;
            0      15     2 longKey   Ljava/lang/String;
            0      15     3 shortKey   Lorg/sireum/Option;
            0      15     4   tpe   Lorg/sireum/cli/CliOpt$Type;
            0      15     5 description   Ljava/lang/String;
    Signature: #26                          // (Ljava/lang/String;Ljava/lang/String;Lorg/sireum/Option<Lorg/sireum/C;>;Lorg/sireum/cli/CliOpt$Type;Ljava/lang/String;)Lorg/sireum/cli/CliOpt$Opt;
    MethodParameters:
      Name                           Flags
      name                           final
      longKey                        final
      shortKey                       final
      tpe                            final
      description                    final

  public scala.Some<scala.Tuple5<org.sireum.String, org.sireum.String, org.sireum.Option<org.sireum.C>, org.sireum.cli.CliOpt$Type, org.sireum.String>> unapply(org.sireum.cli.CliOpt$Opt);
    descriptor: (Lorg/sireum/cli/CliOpt$Opt;)Lscala/Some;
    flags: (0x0001) ACC_PUBLIC
    Code:
      stack=11, locals=2, args_size=2
         0: new           #44                 // class scala/Some
         3: dup
         4: new           #46                 // class scala/Tuple5
         7: dup
         8: new           #48                 // class org/sireum/String
        11: dup
        12: aload_1
        13: invokevirtual #51                 // Method org/sireum/cli/CliOpt$Opt.name:()Ljava/lang/String;
        16: invokespecial #54                 // Method org/sireum/String."<init>":(Ljava/lang/String;)V
        19: new           #48                 // class org/sireum/String
        22: dup
        23: aload_1
        24: invokevirtual #56                 // Method org/sireum/cli/CliOpt$Opt.longKey:()Ljava/lang/String;
        27: invokespecial #54                 // Method org/sireum/String."<init>":(Ljava/lang/String;)V
        30: aload_1
        31: invokevirtual #59                 // Method org/sireum/cli/CliOpt$Opt.shortKey:()Lorg/sireum/Option;
        34: aload_1
        35: invokevirtual #62                 // Method org/sireum/cli/CliOpt$Opt.tpe:()Lorg/sireum/cli/CliOpt$Type;
        38: new           #48                 // class org/sireum/String
        41: dup
        42: aload_1
        43: invokevirtual #64                 // Method org/sireum/cli/CliOpt$Opt.description:()Ljava/lang/String;
        46: invokespecial #54                 // Method org/sireum/String."<init>":(Ljava/lang/String;)V
        49: invokespecial #67                 // Method scala/Tuple5."<init>":(Ljava/lang/Object;Ljava/lang/Object;Ljava/lang/Object;Ljava/lang/Object;Ljava/lang/Object;)V
        52: invokespecial #70                 // Method scala/Some."<init>":(Ljava/lang/Object;)V
        55: areturn
      LineNumberTable:
        line 77: 0
      LocalVariableTable:
        Start  Length  Slot  Name   Signature
            0      56     0  this   Lorg/sireum/cli/CliOpt$Opt$;
            0      56     1     o   Lorg/sireum/cli/CliOpt$Opt;
    Signature: #41                          // (Lorg/sireum/cli/CliOpt$Opt;)Lscala/Some<Lscala/Tuple5<Lorg/sireum/String;Lorg/sireum/String;Lorg/sireum/Option<Lorg/sireum/C;>;Lorg/sireum/cli/CliOpt$Type;Lorg/sireum/String;>;>;
    MethodParameters:
      Name                           Flags
      o                              final

  public org.sireum.cli.CliOpt$Opt$();
    descriptor: ()V
    flags: (0x0001) ACC_PUBLIC
    Code:
      stack=1, locals=1, args_size=1
         0: aload_0
         1: invokespecial #72                 // Method java/lang/Object."<init>":()V
         4: return
      LineNumberTable:
        line 77: 0
      LocalVariableTable:
        Start  Length  Slot  Name   Signature
            0       5     0  this   Lorg/sireum/cli/CliOpt$Opt$;
}
InnerClasses:
  public static final #10= #7 of #9;      // Opt=class org/sireum/cli/CliOpt$Opt of class org/sireum/cli/CliOpt
  public static #11= #2 of #9;            // Opt$=class org/sireum/cli/CliOpt$Opt$ of class org/sireum/cli/CliOpt
  public static #14= #13 of #9;           // Type=class org/sireum/cli/CliOpt$Type of class org/sireum/cli/CliOpt
SourceFile: "CliOpt.scala"
  ScalaInlineInfo: length = 0x13 (unknown attribute)
   01 01 00 03 00 13 00 12 01 00 18 00 19 01 00 27
   00 28 01
  Scala: length = 0x0 (unknown attribute)

