Classfile /Users/mw/Projects/slang-braindump/.jar/jar11/assemble/slang-braindump/assemble/content/org/sireum/cli/CliOpt$Type$Choice$.class
  Last modified May 29, 2022; size 1863 bytes
  SHA-256 checksum 798ece5f5ba64992193a02dbcbff320f4c172db23d989bfcf6acca7db836fea1
  Compiled from "CliOpt.scala"
public class org.sireum.cli.CliOpt$Type$Choice$
  minor version: 0
  major version: 52
  flags: (0x0021) ACC_PUBLIC, ACC_SUPER
  this_class: #2                          // org/sireum/cli/CliOpt$Type$Choice$
  super_class: #4                         // java/lang/Object
  interfaces: 0, fields: 1, methods: 4, attributes: 4
Constant pool:
   #1 = Utf8               org/sireum/cli/CliOpt$Type$Choice$
   #2 = Class              #1             // org/sireum/cli/CliOpt$Type$Choice$
   #3 = Utf8               java/lang/Object
   #4 = Class              #3             // java/lang/Object
   #5 = Utf8               CliOpt.scala
   #6 = Utf8               org/sireum/cli/CliOpt$Type$
   #7 = Class              #6             // org/sireum/cli/CliOpt$Type$
   #8 = Utf8               org/sireum/cli/CliOpt
   #9 = Class              #8             // org/sireum/cli/CliOpt
  #10 = Utf8               Type$
  #11 = Utf8               org/sireum/cli/CliOpt$Type$Choice
  #12 = Class              #11            // org/sireum/cli/CliOpt$Type$Choice
  #13 = Utf8               Choice
  #14 = Utf8               Choice$
  #15 = Utf8               MODULE$
  #16 = Utf8               Lorg/sireum/cli/CliOpt$Type$Choice$;
  #17 = Utf8               <clinit>
  #18 = Utf8               ()V
  #19 = Utf8               <init>
  #20 = NameAndType        #19:#18        // "<init>":()V
  #21 = Methodref          #2.#20         // org/sireum/cli/CliOpt$Type$Choice$."<init>":()V
  #22 = NameAndType        #15:#16        // MODULE$:Lorg/sireum/cli/CliOpt$Type$Choice$;
  #23 = Fieldref           #2.#22         // org/sireum/cli/CliOpt$Type$Choice$.MODULE$:Lorg/sireum/cli/CliOpt$Type$Choice$;
  #24 = Utf8               apply
  #25 = Utf8               (Ljava/lang/String;Lorg/sireum/Option;Lorg/sireum/IS;)Lorg/sireum/cli/CliOpt$Type$Choice;
  #26 = Utf8               (Ljava/lang/String;Lorg/sireum/Option<Lorg/sireum/C;>;Lorg/sireum/IS<Lorg/sireum/Z;Lorg/sireum/String;>;)Lorg/sireum/cli/CliOpt$Type$Choice;
  #27 = Utf8               name
  #28 = Utf8               sep
  #29 = Utf8               elements
  #30 = Utf8               (Ljava/lang/String;Lorg/sireum/Option;Lorg/sireum/IS;)V
  #31 = NameAndType        #19:#30        // "<init>":(Ljava/lang/String;Lorg/sireum/Option;Lorg/sireum/IS;)V
  #32 = Methodref          #12.#31        // org/sireum/cli/CliOpt$Type$Choice."<init>":(Ljava/lang/String;Lorg/sireum/Option;Lorg/sireum/IS;)V
  #33 = Utf8               this
  #34 = Utf8               Ljava/lang/String;
  #35 = Utf8               Lorg/sireum/Option;
  #36 = Utf8               Lorg/sireum/IS;
  #37 = Utf8               unapply
  #38 = Utf8               (Lorg/sireum/cli/CliOpt$Type$Choice;)Lscala/Some;
  #39 = Utf8               (Lorg/sireum/cli/CliOpt$Type$Choice;)Lscala/Some<Lscala/Tuple3<Lorg/sireum/String;Lorg/sireum/Option<Lorg/sireum/C;>;Lorg/sireum/IS<Lorg/sireum/Z;Lorg/sireum/String;>;>;>;
  #40 = Utf8               o
  #41 = Utf8               scala/Some
  #42 = Class              #41            // scala/Some
  #43 = Utf8               scala/Tuple3
  #44 = Class              #43            // scala/Tuple3
  #45 = Utf8               org/sireum/String
  #46 = Class              #45            // org/sireum/String
  #47 = Utf8               ()Ljava/lang/String;
  #48 = NameAndType        #27:#47        // name:()Ljava/lang/String;
  #49 = Methodref          #12.#48        // org/sireum/cli/CliOpt$Type$Choice.name:()Ljava/lang/String;
  #50 = Utf8               (Ljava/lang/String;)V
  #51 = NameAndType        #19:#50        // "<init>":(Ljava/lang/String;)V
  #52 = Methodref          #46.#51        // org/sireum/String."<init>":(Ljava/lang/String;)V
  #53 = Utf8               ()Lorg/sireum/Option;
  #54 = NameAndType        #28:#53        // sep:()Lorg/sireum/Option;
  #55 = Methodref          #12.#54        // org/sireum/cli/CliOpt$Type$Choice.sep:()Lorg/sireum/Option;
  #56 = Utf8               ()Lorg/sireum/IS;
  #57 = NameAndType        #29:#56        // elements:()Lorg/sireum/IS;
  #58 = Methodref          #12.#57        // org/sireum/cli/CliOpt$Type$Choice.elements:()Lorg/sireum/IS;
  #59 = Utf8               (Ljava/lang/Object;Ljava/lang/Object;Ljava/lang/Object;)V
  #60 = NameAndType        #19:#59        // "<init>":(Ljava/lang/Object;Ljava/lang/Object;Ljava/lang/Object;)V
  #61 = Methodref          #44.#60        // scala/Tuple3."<init>":(Ljava/lang/Object;Ljava/lang/Object;Ljava/lang/Object;)V
  #62 = Utf8               (Ljava/lang/Object;)V
  #63 = NameAndType        #19:#62        // "<init>":(Ljava/lang/Object;)V
  #64 = Methodref          #42.#63        // scala/Some."<init>":(Ljava/lang/Object;)V
  #65 = Utf8               Lorg/sireum/cli/CliOpt$Type$Choice;
  #66 = Methodref          #4.#20         // java/lang/Object."<init>":()V
  #67 = Utf8               Code
  #68 = Utf8               LineNumberTable
  #69 = Utf8               LocalVariableTable
  #70 = Utf8               Signature
  #71 = Utf8               MethodParameters
  #72 = Utf8               InnerClasses
  #73 = Utf8               SourceFile
  #74 = Utf8               ScalaInlineInfo
  #75 = Utf8               Scala
{
  public static final org.sireum.cli.CliOpt$Type$Choice$ MODULE$;
    descriptor: Lorg/sireum/cli/CliOpt$Type$Choice$;
    flags: (0x0019) ACC_PUBLIC, ACC_STATIC, ACC_FINAL

  public static {};
    descriptor: ()V
    flags: (0x0009) ACC_PUBLIC, ACC_STATIC
    Code:
      stack=2, locals=0, args_size=0
         0: new           #2                  // class org/sireum/cli/CliOpt$Type$Choice$
         3: dup
         4: invokespecial #21                 // Method "<init>":()V
         7: putstatic     #23                 // Field MODULE$:Lorg/sireum/cli/CliOpt$Type$Choice$;
        10: return
      LineNumberTable:
        line 93: 0

  public org.sireum.cli.CliOpt$Type$Choice apply(java.lang.String, org.sireum.Option<org.sireum.C>, org.sireum.IS<org.sireum.Z, org.sireum.String>);
    descriptor: (Ljava/lang/String;Lorg/sireum/Option;Lorg/sireum/IS;)Lorg/sireum/cli/CliOpt$Type$Choice;
    flags: (0x0001) ACC_PUBLIC
    Code:
      stack=5, locals=4, args_size=4
         0: new           #12                 // class org/sireum/cli/CliOpt$Type$Choice
         3: dup
         4: aload_1
         5: aload_2
         6: aload_3
         7: invokespecial #32                 // Method org/sireum/cli/CliOpt$Type$Choice."<init>":(Ljava/lang/String;Lorg/sireum/Option;Lorg/sireum/IS;)V
        10: areturn
      LineNumberTable:
        line 93: 0
      LocalVariableTable:
        Start  Length  Slot  Name   Signature
            0      11     0  this   Lorg/sireum/cli/CliOpt$Type$Choice$;
            0      11     1  name   Ljava/lang/String;
            0      11     2   sep   Lorg/sireum/Option;
            0      11     3 elements   Lorg/sireum/IS;
    Signature: #26                          // (Ljava/lang/String;Lorg/sireum/Option<Lorg/sireum/C;>;Lorg/sireum/IS<Lorg/sireum/Z;Lorg/sireum/String;>;)Lorg/sireum/cli/CliOpt$Type$Choice;
    MethodParameters:
      Name                           Flags
      name                           final
      sep                            final
      elements                       final

  public scala.Some<scala.Tuple3<org.sireum.String, org.sireum.Option<org.sireum.C>, org.sireum.IS<org.sireum.Z, org.sireum.String>>> unapply(org.sireum.cli.CliOpt$Type$Choice);
    descriptor: (Lorg/sireum/cli/CliOpt$Type$Choice;)Lscala/Some;
    flags: (0x0001) ACC_PUBLIC
    Code:
      stack=7, locals=2, args_size=2
         0: new           #42                 // class scala/Some
         3: dup
         4: new           #44                 // class scala/Tuple3
         7: dup
         8: new           #46                 // class org/sireum/String
        11: dup
        12: aload_1
        13: invokevirtual #49                 // Method org/sireum/cli/CliOpt$Type$Choice.name:()Ljava/lang/String;
        16: invokespecial #52                 // Method org/sireum/String."<init>":(Ljava/lang/String;)V
        19: aload_1
        20: invokevirtual #55                 // Method org/sireum/cli/CliOpt$Type$Choice.sep:()Lorg/sireum/Option;
        23: aload_1
        24: invokevirtual #58                 // Method org/sireum/cli/CliOpt$Type$Choice.elements:()Lorg/sireum/IS;
        27: invokespecial #61                 // Method scala/Tuple3."<init>":(Ljava/lang/Object;Ljava/lang/Object;Ljava/lang/Object;)V
        30: invokespecial #64                 // Method scala/Some."<init>":(Ljava/lang/Object;)V
        33: areturn
      LineNumberTable:
        line 93: 0
      LocalVariableTable:
        Start  Length  Slot  Name   Signature
            0      34     0  this   Lorg/sireum/cli/CliOpt$Type$Choice$;
            0      34     1     o   Lorg/sireum/cli/CliOpt$Type$Choice;
    Signature: #39                          // (Lorg/sireum/cli/CliOpt$Type$Choice;)Lscala/Some<Lscala/Tuple3<Lorg/sireum/String;Lorg/sireum/Option<Lorg/sireum/C;>;Lorg/sireum/IS<Lorg/sireum/Z;Lorg/sireum/String;>;>;>;
    MethodParameters:
      Name                           Flags
      o                              final

  public org.sireum.cli.CliOpt$Type$Choice$();
    descriptor: ()V
    flags: (0x0001) ACC_PUBLIC
    Code:
      stack=1, locals=1, args_size=1
         0: aload_0
         1: invokespecial #66                 // Method java/lang/Object."<init>":()V
         4: return
      LineNumberTable:
        line 93: 0
      LocalVariableTable:
        Start  Length  Slot  Name   Signature
            0       5     0  this   Lorg/sireum/cli/CliOpt$Type$Choice$;
}
InnerClasses:
  public static #10= #7 of #9;            // Type$=class org/sireum/cli/CliOpt$Type$ of class org/sireum/cli/CliOpt
  public static final #13= #12 of #7;     // Choice=class org/sireum/cli/CliOpt$Type$Choice of class org/sireum/cli/CliOpt$Type$
  public static #14= #2 of #7;            // Choice$=class org/sireum/cli/CliOpt$Type$Choice$ of class org/sireum/cli/CliOpt$Type$
SourceFile: "CliOpt.scala"
  ScalaInlineInfo: length = 0x13 (unknown attribute)
   01 01 00 03 00 13 00 12 01 00 18 00 19 01 00 25
   00 26 01
  Scala: length = 0x0 (unknown attribute)

