Classfile /Users/mw/Projects/slang-braindump/.jar/jar11/assemble/slang-braindump/assemble/content/org/sireum/cli/CliOpt$Type$.class
  Last modified May 29, 2022; size 1266 bytes
  SHA-256 checksum 0aa99e4dbab12414df6ff05812052e06ab88c4ea62ccf308b0f618d81eaa1705
  Compiled from "CliOpt.scala"
public class org.sireum.cli.CliOpt$Type$
  minor version: 0
  major version: 52
  flags: (0x0021) ACC_PUBLIC, ACC_SUPER
  this_class: #2                          // org/sireum/cli/CliOpt$Type$
  super_class: #4                         // java/lang/Object
  interfaces: 0, fields: 1, methods: 2, attributes: 4
Constant pool:
   #1 = Utf8               org/sireum/cli/CliOpt$Type$
   #2 = Class              #1             // org/sireum/cli/CliOpt$Type$
   #3 = Utf8               java/lang/Object
   #4 = Class              #3             // java/lang/Object
   #5 = Utf8               CliOpt.scala
   #6 = Utf8               org/sireum/cli/CliOpt
   #7 = Class              #6             // org/sireum/cli/CliOpt
   #8 = Utf8               Type$
   #9 = Utf8               org/sireum/cli/CliOpt$Type$Choice
  #10 = Class              #9             // org/sireum/cli/CliOpt$Type$Choice
  #11 = Utf8               Choice
  #12 = Utf8               org/sireum/cli/CliOpt$Type$Choice$
  #13 = Class              #12            // org/sireum/cli/CliOpt$Type$Choice$
  #14 = Utf8               Choice$
  #15 = Utf8               org/sireum/cli/CliOpt$Type$Flag
  #16 = Class              #15            // org/sireum/cli/CliOpt$Type$Flag
  #17 = Utf8               Flag
  #18 = Utf8               org/sireum/cli/CliOpt$Type$Flag$
  #19 = Class              #18            // org/sireum/cli/CliOpt$Type$Flag$
  #20 = Utf8               Flag$
  #21 = Utf8               org/sireum/cli/CliOpt$Type$Num
  #22 = Class              #21            // org/sireum/cli/CliOpt$Type$Num
  #23 = Utf8               Num
  #24 = Utf8               org/sireum/cli/CliOpt$Type$Num$
  #25 = Class              #24            // org/sireum/cli/CliOpt$Type$Num$
  #26 = Utf8               Num$
  #27 = Utf8               org/sireum/cli/CliOpt$Type$NumChoice
  #28 = Class              #27            // org/sireum/cli/CliOpt$Type$NumChoice
  #29 = Utf8               NumChoice
  #30 = Utf8               org/sireum/cli/CliOpt$Type$NumChoice$
  #31 = Class              #30            // org/sireum/cli/CliOpt$Type$NumChoice$
  #32 = Utf8               NumChoice$
  #33 = Utf8               org/sireum/cli/CliOpt$Type$NumFlag
  #34 = Class              #33            // org/sireum/cli/CliOpt$Type$NumFlag
  #35 = Utf8               NumFlag
  #36 = Utf8               org/sireum/cli/CliOpt$Type$NumFlag$
  #37 = Class              #36            // org/sireum/cli/CliOpt$Type$NumFlag$
  #38 = Utf8               NumFlag$
  #39 = Utf8               org/sireum/cli/CliOpt$Type$Path
  #40 = Class              #39            // org/sireum/cli/CliOpt$Type$Path
  #41 = Utf8               Path
  #42 = Utf8               org/sireum/cli/CliOpt$Type$Path$
  #43 = Class              #42            // org/sireum/cli/CliOpt$Type$Path$
  #44 = Utf8               Path$
  #45 = Utf8               org/sireum/cli/CliOpt$Type$Str
  #46 = Class              #45            // org/sireum/cli/CliOpt$Type$Str
  #47 = Utf8               Str
  #48 = Utf8               org/sireum/cli/CliOpt$Type$Str$
  #49 = Class              #48            // org/sireum/cli/CliOpt$Type$Str$
  #50 = Utf8               Str$
  #51 = Utf8               MODULE$
  #52 = Utf8               Lorg/sireum/cli/CliOpt$Type$;
  #53 = Utf8               <clinit>
  #54 = Utf8               ()V
  #55 = Utf8               <init>
  #56 = NameAndType        #55:#54        // "<init>":()V
  #57 = Methodref          #2.#56         // org/sireum/cli/CliOpt$Type$."<init>":()V
  #58 = NameAndType        #51:#52        // MODULE$:Lorg/sireum/cli/CliOpt$Type$;
  #59 = Fieldref           #2.#58         // org/sireum/cli/CliOpt$Type$.MODULE$:Lorg/sireum/cli/CliOpt$Type$;
  #60 = Methodref          #4.#56         // java/lang/Object."<init>":()V
  #61 = Utf8               this
  #62 = Utf8               Code
  #63 = Utf8               LineNumberTable
  #64 = Utf8               LocalVariableTable
  #65 = Utf8               InnerClasses
  #66 = Utf8               SourceFile
  #67 = Utf8               ScalaInlineInfo
  #68 = Utf8               Scala
{
  public static final org.sireum.cli.CliOpt$Type$ MODULE$;
    descriptor: Lorg/sireum/cli/CliOpt$Type$;
    flags: (0x0019) ACC_PUBLIC, ACC_STATIC, ACC_FINAL

  public static {};
    descriptor: ()V
    flags: (0x0009) ACC_PUBLIC, ACC_STATIC
    Code:
      stack=2, locals=0, args_size=0
         0: new           #2                  // class org/sireum/cli/CliOpt$Type$
         3: dup
         4: invokespecial #57                 // Method "<init>":()V
         7: putstatic     #59                 // Field MODULE$:Lorg/sireum/cli/CliOpt$Type$;
        10: return
      LineNumberTable:
        line 81: 0

  public org.sireum.cli.CliOpt$Type$();
    descriptor: ()V
    flags: (0x0001) ACC_PUBLIC
    Code:
      stack=1, locals=1, args_size=1
         0: aload_0
         1: invokespecial #60                 // Method java/lang/Object."<init>":()V
         4: return
      LineNumberTable:
        line 81: 0
      LocalVariableTable:
        Start  Length  Slot  Name   Signature
            0       5     0  this   Lorg/sireum/cli/CliOpt$Type$;
}
InnerClasses:
  public static #8= #2 of #7;             // Type$=class org/sireum/cli/CliOpt$Type$ of class org/sireum/cli/CliOpt
  public static final #11= #10 of #2;     // Choice=class org/sireum/cli/CliOpt$Type$Choice of class org/sireum/cli/CliOpt$Type$
  public static #14= #13 of #2;           // Choice$=class org/sireum/cli/CliOpt$Type$Choice$ of class org/sireum/cli/CliOpt$Type$
  public static final #17= #16 of #2;     // Flag=class org/sireum/cli/CliOpt$Type$Flag of class org/sireum/cli/CliOpt$Type$
  public static #20= #19 of #2;           // Flag$=class org/sireum/cli/CliOpt$Type$Flag$ of class org/sireum/cli/CliOpt$Type$
  public static final #23= #22 of #2;     // Num=class org/sireum/cli/CliOpt$Type$Num of class org/sireum/cli/CliOpt$Type$
  public static #26= #25 of #2;           // Num$=class org/sireum/cli/CliOpt$Type$Num$ of class org/sireum/cli/CliOpt$Type$
  public static final #29= #28 of #2;     // NumChoice=class org/sireum/cli/CliOpt$Type$NumChoice of class org/sireum/cli/CliOpt$Type$
  public static #32= #31 of #2;           // NumChoice$=class org/sireum/cli/CliOpt$Type$NumChoice$ of class org/sireum/cli/CliOpt$Type$
  public static final #35= #34 of #2;     // NumFlag=class org/sireum/cli/CliOpt$Type$NumFlag of class org/sireum/cli/CliOpt$Type$
  public static #38= #37 of #2;           // NumFlag$=class org/sireum/cli/CliOpt$Type$NumFlag$ of class org/sireum/cli/CliOpt$Type$
  public static final #41= #40 of #2;     // Path=class org/sireum/cli/CliOpt$Type$Path of class org/sireum/cli/CliOpt$Type$
  public static #44= #43 of #2;           // Path$=class org/sireum/cli/CliOpt$Type$Path$ of class org/sireum/cli/CliOpt$Type$
  public static final #47= #46 of #2;     // Str=class org/sireum/cli/CliOpt$Type$Str of class org/sireum/cli/CliOpt$Type$
  public static #50= #49 of #2;           // Str$=class org/sireum/cli/CliOpt$Type$Str$ of class org/sireum/cli/CliOpt$Type$
SourceFile: "CliOpt.scala"
  ScalaInlineInfo: length = 0x9 (unknown attribute)
   01 01 00 01 00 37 00 36 01
  Scala: length = 0x0 (unknown attribute)

