Classfile /Users/mw/Projects/slang-braindump/.jar/jar11/assemble/slang-braindump/assemble/content/org/sireum/cli/JSON.class
  Last modified May 29, 2022; size 11979 bytes
  SHA-256 checksum e735ee7731680d9ed7ff8a67a2ad65d09a9fd928eba7dea04c9763505dedb480
  Compiled from "JSON.scala"
public final class org.sireum.cli.JSON
  minor version: 0
  major version: 52
  flags: (0x0031) ACC_PUBLIC, ACC_FINAL, ACC_SUPER
  this_class: #2                          // org/sireum/cli/JSON
  super_class: #4                         // java/lang/Object
  interfaces: 0, fields: 0, methods: 27, attributes: 4
Constant pool:
    #1 = Utf8               org/sireum/cli/JSON
    #2 = Class              #1            // org/sireum/cli/JSON
    #3 = Utf8               java/lang/Object
    #4 = Class              #3            // java/lang/Object
    #5 = Utf8               JSON.scala
    #6 = Utf8               Lscala/reflect/ScalaSignature;
    #7 = Utf8               bytes
    #8 = Utf8               \u0006\u0005\u0011eq!B/_\u0011\u0003)g!B4_\u0011\u0003A\u0007\"B8\u0002\t\u0003\u0001x!B9\u0002\u0011\u0003\u0011h!\u0002;\u0002\u0011\u0003)\b\"B8\u0005\t\u00031\b\"B<\u0005\t\u0003A\bbBA\u0007\t\u0011\u0005\u0011q\u0002\u0005\b\u0003G!A\u0011AA\u0013\u0011\u001d\t\t\u0004\u0002C\u0001\u0003gAq!a\u0010\u0005\t\u0003\t\t\u0005C\u0004\u0002N\u0011!\t!a\u0014\t\u000f\u0005mC\u0001\"\u0001\u0002^!9\u0011\u0011\u000f\u0003\u0005\u0002\u0005M\u0004bBA@\t\u0011\u0005\u0011\u0011\u0011\u0005\b\u0003\u001b#A\u0011AAH\u0011\u001d\tY\n\u0002C\u0001\u0003;Cq!!+\u0005\t\u0003\tY\u000bC\u0004\u00028\u0012!\t!!/\b\u000f\u0005\u0015\u0017\u0001#\u0001\u0002H\u001a9\u0011\u0011Z\u0001\t\u0002\u0005-\u0007BB8\u0015\t\u0003\ti\rC\u0004\u0002PR!\t!!5\t\u000f\rEA\u0003\"\u0001\u0004\u0014\u00191\u0011\u0011Z\u0001\u0003\u0003+D!\"!8\u0019\u0005\u0003\u0005\u000b\u0011BAp\u0011\u0019y\u0007\u0004\"\u0001\u0002f\"A\u0011\u0011\u001e\r!B\u0013\ty\u000eC\u0004\u0002lb!\t!!<\t\u000f\u0005=\b\u0004\"\u0001\u0002n\"9\u0011\u0011\u001f\r\u0005B\u0005M\bb\u0002B\u00021\u0011\u0005\u0013Q\u001e\u0005\b\u0005\u000bAB\u0011\tB\u0004\u0011\u001d\u0011y\u0001\u0007C!\u0005#Aq!a4\u0019\t\u0003\u0011\t\u0003C\u0005\u0003&a\t\n\u0011\"\u0001\u0003(!9!Q\b\r\u0005B\t}\u0002b\u0002B01\u0011\u0005#\u0011\r\u0005\n\u0005GB\"\u0019!C\u0001\u0005KB\u0001Ba\u001d\u0019A\u0003%!q\r\u0005\b\u0005kBB\u0011\u0001B<\u0011\u001d\u0011)\t\u0007C\u0001\u0005\u000fCqA!#\u0019\t\u0003\u0011Y\tC\u0004\u0003\u000eb!\tAa$\t\u000f\tm\u0005\u0004\"\u0001\u0003\u001e\"9!q\u0014\r\u0005\u0002\t\u0005\u0006b\u0002BS1\u0011\u0005!q\u0015\u0005\b\u0005SCB\u0011\u0001BV\u0011\u001d\u0011y\u000b\u0007C\u0001\u0005cCqAa-\u0019\t\u0003\u0011)\fC\u0004\u0003:b!\tAa/\t\u000f\tu\u0006\u0004\"\u0001\u0003@\"9!\u0011\u0019\r\u0005\u0002\t\r\u0007b\u0002Bd1\u0011\u0005!\u0011\u001a\u0005\b\u0005\u0017DB\u0011\u0001Bg\u0011\u001d\u0011\t\u000e\u0007C\u0001\u0005\'DqA!6\u0019\t\u0003\u00119\u000eC\u0004\u0003\\b!\tA!8\t\u000f\t}\u0007\u0004\"\u0001\u0003b\"9!Q\u001d\r\u0005\u0002\t\u001d\bb\u0002Bu1\u0011\u0005!1\u001e\u0005\b\u0005_DB\u0011\u0001By\u0011\u001d\u0011\u0019\u0010\u0007C\u0001\u0005kDqA!?\u0019\t\u0003\u0011Y\u0010C\u0004\u0003~b!\tAa@\t\u000f\r\r\u0001\u0004\"\u0001\u0004\u0006!91QD\u0001\u0005\u0002\r}\u0001bBB$\u0003\u0011\u00051\u0011\n\u0005\b\u0007#\nA\u0011AB*\u0011\u001d\u0019I&\u0001C\u0001\u00077Bqa!\u0019\u0002\t\u0003\u0019\u0019\u0007C\u0004\u0004j\u0005!\taa\u001b\t\u000f\rE\u0014\u0001\"\u0001\u0004t!91\u0011P\u0001\u0005\u0002\rm\u0004bBBA\u0003\u0011\u000511\u0011\u0005\b\u0007\u0013\u000bA\u0011ABF\u0011\u001d\u0019\t*\u0001C\u0001\u0007\'Cqa!\'\u0002\t\u0003\u0019Y\nC\u0004\u0004\"\u0006!\taa)\t\u000f\r%\u0016\u0001\"\u0001\u0004,\"91\u0011W\u0001\u0005\u0002\rM\u0006bBB]\u0003\u0011\u000511\u0018\u0005\b\u0007\u0003\fA\u0011ABb\u0011\u001d\u0019I-\u0001C\u0001\u0007\u0017Dqa!5\u0002\t\u0003\u0019\u0019\u000eC\u0004\u0004Z\u0006!\taa7\t\u000f\r\u0005\u0018\u0001\"\u0001\u0004d\"91\u0011^\u0001\u0005\u0002\r-\bbBBy\u0003\u0011\u000511\u001f\u0005\b\u0007s\fA\u0011AB~\u0011\u001d!\t!\u0001C\u0001\t\u0007Aq\u0001\"\u0003\u0002\t\u0003!Y\u0001C\u0004\u0005\u0012\u0005!\t\u0001b\u0005\u0002\t)\u001bvJ\u0014\u0006\u0003?\u0002\f1a\u00197j\u0015\t\t\'-\u0001\u0004tSJ,W/\u001c\u0006\u0002G\u0006\u0019qN]4\u0004\u0001A\u0011a-A\u0007\u0002=\n!!jU(O\'\t\t\u0011\u000e\u0005\u0002k[6\t1NC\u0001m\u0003\u0015\u00198-\u00197b\u0013\tq7N\u0001\u0004B]f\u0014VMZ\u0001\u0007y%t\u0017\u000e\u001e \u0015\u0003\u0015\fq\u0001\u0015:j]R,\'\u000f\u0005\u0002t\t5\t\u0011AA\u0004Qe&tG/\u001a:\u0014\u0005\u0011IG#\u0001:\u0002\u0017A\u0014\u0018N\u001c;DY&|\u0005\u000f\u001e\u000b\u0003sv\u0004\"A_>\u000e\u0003\u0001L!\u0001 1\u0003\u0005M#\u0006\"\u0002@\u0007\u0001\u0004y\u0018!A8\u0011\u0007\u0019\f\t!C\u0002\u0002\u0004y\u0013aa\u00117j\u001fB$\bf\u0001\u0004\u0002\bA\u0019!0!\u0003\n\u0007\u0005-\u0001M\u0001\u0003qkJ,\u0017\u0001\u00059sS:$8\t\\5PaR<%o\\;q)\rI\u0018\u0011\u0003\u0005\u0007}\u001e\u0001\r!a\u0005\u0011\t\u0005U\u00111\u0004\b\u0004M\u0006]\u0011bAA\r=\u000611\t\\5PaRLA!!\b\u0002 \t)qI]8va*\u0019\u0011\u0011\u00040)\u0007\u001d\t9!A\bqe&tGo\u00117j\u001fB$Hk\\8m)\rI\u0018q\u0005\u0005\u0007}\"\u0001\r!!\u000b\u0011\t\u0005U\u00111F\u0005\u0005\u0003[\tyB\u0001\u0003U_>d\u0007f\u0001\u0005\u0002\b\u0005\u0019\u0002O]5oi\u000ec\u0017n\u00149u\u001fB$xI]8vaR\u0019\u00110!\u000e\t\ryL\u0001\u0019AA\u001c!\u0011\t)\"!\u000f\n\t\u0005m\u0012q\u0004\u0002\t\u001fB$xI]8va\"\u001a\u0011\"a\u0002\u0002\u001dA\u0014\u0018N\u001c;DY&|\u0005\u000f^(qiR\u0019\u00110a\u0011\t\ryT\u0001\u0019AA#!\u0011\t)\"a\u0012\n\t\u0005%\u0013q\u0004\u0002\u0004\u001fB$\bf\u0001\u0006\u0002\b\u0005y\u0001O]5oi\u000ec\u0017n\u00149u)f\u0004X\rF\u0002z\u0003#BaA`\u0006A\u0002\u0005M\u0003\u0003BA\u000b\u0003+JA!a\u0016\u0002 \t!A+\u001f9fQ\rY\u0011qA\u0001\u0014aJLg\u000e^\"mS>\u0003H\u000fV=qK\u001ac\u0017m\u001a\u000b\u0004s\u0006}\u0003B\u0002@\r\u0001\u0004\t\t\u0007\u0005\u0003\u0002d\u0005%d\u0002BA\u000b\u0003KJA!a\u001a\u0002 \u0005!A+\u001f9f\u0013\u0011\tY\'!\u001c\u0003\t\u0019c\u0017m\u001a\u0006\u0005\u0003O\ny\u0002K\u0002\r\u0003\u000f\t!\u0003\u001d:j]R\u001cE.[(qiRK\b/\u001a(v[R\u0019\u00110!\u001e\t\ryl\u0001\u0019AA<!\u0011\t\u0019\'!\u001f\n\t\u0005m\u0014Q\u000e\u0002\u0004\u001dVl\u0007fA\u0007\u0002\b\u00051\u0002O]5oi\u000ec\u0017n\u00149u)f\u0004XMT;n\r2\fw\rF\u0002z\u0003\u0007CaA \bA\u0002\u0005\u0015\u0005\u0003BA2\u0003\u000fKA!!#\u0002n\t9a*^7GY\u0006<\u0007f\u0001\b\u0002\b\u0005A\u0002O]5oi\u000ec\u0017n\u00149u)f\u0004XMT;n\u0007\"|\u0017nY3\u0015\u0007e\f\t\n\u0003\u0004\u007f\u001f\u0001\u0007\u00111\u0013\t\u0005\u0003G\n)*\u0003\u0003\u0002\u0018\u00065$!\u0003(v[\u000eCw.[2fQ\ry\u0011qA\u0001\u0013aJLg\u000e^\"mS>\u0003H\u000fV=qKN#(\u000fF\u0002z\u0003?CaA \tA\u0002\u0005\u0005\u0006\u0003BA2\u0003GKA!!*\u0002n\t\u00191\u000b\u001e:)\u0007A\t9!A\u000bqe&tGo\u00117j\u001fB$H+\u001f9f\u0007\"|\u0017nY3\u0015\u0007e\fi\u000b\u0003\u0004\u007f#\u0001\u0007\u0011q\u0016\t\u0005\u0003G\n\t,\u0003\u0003\u00024\u00065$AB\"i_&\u001cW\rK\u0002\u0012\u0003\u000f\t1\u0003\u001d:j]R\u001cE.[(qiRK\b/\u001a)bi\"$2!_A^\u0011\u0019q(\u00031\u0001\u0002>B!\u00111MA`\u0013\u0011\t\t-!\u001c\u0003\tA\u000bG\u000f\u001b\u0015\u0004%\u0005\u001d\u0011A\u0002)beN,\'\u000f\u0005\u0002t)\t1\u0001+\u0019:tKJ\u001c\"\u0001F5\u0015\u0005\u0005\u001d\u0017!B1qa2LH\u0003BAj\u0007\u001f\u0001\"a\u001d\r\u0014\taI\u0017q\u001b\t\u0004u\u0006e\u0017bAAnA\nI!+Z2pe\u0012\u001c\u0016nZ\u0001\b?~Kg\u000e];u!\rQ\u0018\u0011]\u0005\u0004\u0003G\u0004\'AB*ue&tw\r\u0006\u0003\u0002T\u0006\u001d\bbBAo5\u0001\u0007\u0011q\\\u0001\u0007?&t\u0007/\u001e;\u0002\u000b%t\u0007/\u001e;\u0016\u0005\u0005}\u0017\u0001C4fi&s\u0007/\u001e;\u0002\u0011Q|7\u000b\u001e:j]\u001e$\"!!>\u0011\t\u0005](\u0011A\u0007\u0003\u0003sTA!a?\u0002~\u0006!A.\u00198h\u0015\t\ty0\u0001\u0003kCZ\f\u0017\u0002BAr\u0003s\faa\u001d;sS:<\u0017\u0001\u00035bg\"\u001cu\u000eZ3\u0015\u0005\t%\u0001c\u00016\u0003\f%\u0019!QB6\u0003\u0007%sG/\u0001\u0004fcV\fGn\u001d\u000b\u0005\u0005\'\u0011I\u0002E\u0002k\u0005+I1Aa\u0006l\u0005\u001d\u0011un\u001c7fC:DaA`\u0011A\u0002\tm\u0001c\u00016\u0003\u001e%\u0019!qD6\u0003\u0007\u0005s\u0017\u0010\u0006\u0003\u0002T\n\r\u0002\"CAvEA\u0005\t\u0019AAp\u0003=\t\u0007\u000f\u001d7zI\u0011,g-Y;mi\u0012\nTC\u0001B\u0015U\u0011\tyNa\u000b,\u0005\t5\u0002\u0003\u0002B\u0018\u0005si!A!\r\u000b\t\tM\"QG\u0001\nk:\u001c\u0007.Z2lK\u0012T1Aa\u000el\u0003)\tgN\\8uCRLwN\\\u0005\u0005\u0005w\u0011\tDA\tv]\u000eDWmY6fIZ\u000b\'/[1oG\u0016\f\u0001\u0002J2p]R,g\u000e^\u000b\u0003\u0005\u0003\u0002bAa\u0011\u0003T\tec\u0002\u0002B#\u0005\u001frAAa\u0012\u0003N5\u0011!\u0011\n\u0006\u0004\u0005\u0017\"\u0017A\u0002\u001fs_>$h(C\u0001m\u0013\r\u0011\tf[\u0001\ba\u0006\u001c7.Y4f\u0013\u0011\u0011)Fa\u0016\u0003\u0007M+\u0017OC\u0002\u0003R-\u0004rA\u001bB.\u0003k\u0014Y\"C\u0002\u0003^-\u0014a\u0001V;qY\u0016\u0014\u0014A\u0002\u0013dY>tW-\u0006\u0002\u0002T\u00061\u0001/\u0019:tKJ,\"Aa\u001a\u0011\t\t%$q\u000e\b\u0004u\n-\u0014b\u0001B7A\u0006!!j]8o\u0013\u0011\tIM!\u001d\u000b\u0007\t5\u0004-A\u0004qCJ\u001cXM\u001d\u0011\u0002\u0011\u0015\u0014(o\u001c:PaR,\"A!\u001f\u0011\u000bi\u0014YHa \n\u0007\tu\u0004M\u0001\u0004PaRLwN\u001c\t\u0005\u0005S\u0012\t)\u0003\u0003\u0003\u0004\nE$\u0001C#se>\u0014Xj]4\u0002\u0017A\f\'o]3DY&|\u0005\u000f\u001e\u000b\u0002\u007f\u0006\u0001\u0002/\u0019:tK\u000ec\u0017n\u00149u\u000fJ|W\u000f\u001d\u000b\u0003\u0003\'\t\u0011\u0003]1sg\u0016\u001cE.[(qi\u001e\u0013x.\u001e9U)\u0011\t\u0019B!%\t\u000f\tM5\u00061\u0001\u0003\u0016\u0006QA/\u001f9f!\u0006\u00148/\u001a3\u0011\u0007i\u00149*C\u0002\u0003\u001a\u0002\u0014\u0011AQ\u0001\u0010a\u0006\u00148/Z\"mS>\u0003H\u000fV8pYR\u0011\u0011\u0011F\u0001\u0011a\u0006\u00148/Z\"mS>\u0003H\u000fV8pYR#B!!\u000b\u0003$\"9!1S\u0017A\u0002\tU\u0015a\u00059beN,7\t\\5PaR|\u0005\u000f^$s_V\u0004HCAA\u001c\u0003Q\u0001\u0018M]:f\u00072Lw\n\u001d;PaR<%o\\;q)R!\u0011q\u0007BW\u0011\u001d\u0011\u0019j\fa\u0001\u0005+\u000ba\u0002]1sg\u0016\u001cE.[(qi>\u0003H\u000f\u0006\u0002\u0002F\u0005y\u0001/\u0019:tK\u000ec\u0017n\u00149u\u001fB$H\u000b\u0006\u0003\u0002F\t]\u0006b\u0002BJc\u0001\u0007!QS\u0001\u0010a\u0006\u00148/Z\"mS>\u0003H\u000fV=qKR\u0011\u00111K\u0001\u0014a\u0006\u00148/Z\"mS>\u0003H\u000fV=qK\u001ac\u0017m\u001a\u000b\u0003\u0003C\nA\u0003]1sg\u0016\u001cE.[(qiRK\b/\u001a$mC\u001e$F\u0003BA1\u0005\u000bDqAa%5\u0001\u0004\u0011)*\u0001\nqCJ\u001cXm\u00117j\u001fB$H+\u001f9f\u001dVlGCAA<\u0003M\u0001\u0018M]:f\u00072Lw\n\u001d;UsB,g*^7U)\u0011\t9Ha4\t\u000f\tMe\u00071\u0001\u0003\u0016\u00061\u0002/\u0019:tK\u000ec\u0017n\u00149u)f\u0004XMT;n\r2\fw\r\u0006\u0002\u0002\u0006\u00069\u0002/\u0019:tK\u000ec\u0017n\u00149u)f\u0004XMT;n\r2\fw\r\u0016\u000b\u0005\u0003\u000b\u0013I\u000eC\u0004\u0003\u0014b\u0002\rA!&\u00021A\f\'o]3DY&|\u0005\u000f\u001e+za\u0016tU/\\\"i_&\u001cW\r\u0006\u0002\u0002\u0014\u0006I\u0002/\u0019:tK\u000ec\u0017n\u00149u)f\u0004XMT;n\u0007\"|\u0017nY3U)\u0011\t\u0019Ja9\t\u000f\tM%\b1\u0001\u0003\u0016\u0006\u0011\u0002/\u0019:tK\u000ec\u0017n\u00149u)f\u0004Xm\u0015;s)\t\t\t+A\nqCJ\u001cXm\u00117j\u001fB$H+\u001f9f\'R\u0014H\u000b\u0006\u0003\u0002\"\n5\bb\u0002BJy\u0001\u0007!QS\u0001\u0016a\u0006\u00148/Z\"mS>\u0003H\u000fV=qK\u000eCw.[2f)\t\ty+\u0001\fqCJ\u001cXm\u00117j\u001fB$H+\u001f9f\u0007\"|\u0017nY3U)\u0011\tyKa>\t\u000f\tMe\b1\u0001\u0003\u0016\u0006\u0019\u0002/\u0019:tK\u000ec\u0017n\u00149u)f\u0004X\rU1uQR\u0011\u0011QX\u0001\u0015a\u0006\u00148/Z\"mS>\u0003H\u000fV=qKB\u000bG\u000f\u001b+\u0015\t\u0005u6\u0011\u0001\u0005\b\u0005\'\u0003\u0005\u0019\u0001BK\u0003\r)wN\u001a\u000b\u0003\u0005+C3\u0001GB\u0005!\rQ81B\u0005\u0004\u0007\u001b\u0001\'A\u0002:fG>\u0014H\rC\u0004\u0002lZ\u0001\r!a8\u0002\u000fUt\u0017\r\u001d9msR!1QCB\u000e!\u0015Q7qCAp\u0013\r\u0019Ib\u001b\u0002\u0005\'>lW\r\u0003\u0004\u007f/\u0001\u0007\u00111[\u0001\u0003i>,Ba!\t\u0004.Q111EB\u001d\u0007{\u0001rA_B\u0013\u0007S\u0011y(C\u0002\u0004(\u0001\u0014a!R5uQ\u0016\u0014\b\u0003BB\u0016\u0007[a\u0001\u0001B\u0004\u00040\t\u0013\ra!\r\u0003\u0003Q\u000bBaa\r\u0003\u001cA\u0019!n!\u000e\n\u0007\r]2NA\u0004O_RD\u0017N\\4\t\u000f\rm\"\t1\u0001\u0002`\u0006\t1\u000fC\u0004\u0004@\t\u0003\ra!\u0011\u0002\u0003\u0019\u0004rA[B\"\u0003\'\u001cI#C\u0002\u0004F-\u0014\u0011BR;oGRLwN\\\u0019\u0002\u0015\u0019\u0014x.\\\"mS>\u0003H\u000f\u0006\u0004\u0002`\u000e-3Q\n\u0005\u0006}\u000e\u0003\ra \u0005\b\u0007\u001f\u001a\u0005\u0019\u0001BK\u0003%I7oQ8na\u0006\u001cG/\u0001\u0005u_\u000ec\u0017n\u00149u)\u0011\u0019)fa\u0016\u0011\ri\u001c)c B@\u0011\u001d\u0019Y\u0004\u0012a\u0001\u0003?\fqB\u001a:p[\u000ec\u0017n\u00149u\u000fJ|W\u000f\u001d\u000b\u0007\u0003?\u001cifa\u0018\t\ry,\u0005\u0019AA\n\u0011\u001d\u0019y%\u0012a\u0001\u0005+\u000bQ\u0002^8DY&|\u0005\u000f^$s_V\u0004H\u0003BB3\u0007O\u0002rA_B\u0013\u0003\'\u0011y\bC\u0004\u0004<\u0019\u0003\r!a8\u0002\u001d\u0019\u0014x.\\\"mS>\u0003H\u000fV8pYR1\u0011q\\B7\u0007_BaA`$A\u0002\u0005%\u0002bBB(\u000f\u0002\u0007!QS\u0001\ri>\u001cE.[(qiR{w\u000e\u001c\u000b\u0005\u0007k\u001a9\bE\u0004{\u0007K\tICa \t\u000f\rm\u0002\n1\u0001\u0002`\u0006\u0011bM]8n\u00072Lw\n\u001d;PaR<%o\\;q)\u0019\tyn! \u0004\u0000!1a0\u0013a\u0001\u0003oAqaa\u0014J\u0001\u0004\u0011)*\u0001\tu_\u000ec\u0017n\u00149u\u001fB$xI]8vaR!1QQBD!\u001dQ8QEA\u001c\u0005\u007fBqaa\u000fK\u0001\u0004\ty.A\u0007ge>l7\t\\5PaR|\u0005\u000f\u001e\u000b\u0007\u0003?\u001ciia$\t\ry\\\u0005\u0019AA#\u0011\u001d\u0019ye\u0013a\u0001\u0005+\u000b1\u0002^8DY&|\u0005\u000f^(qiR!1QSBL!\u001dQ8QEA#\u0005\u007fBqaa\u000fM\u0001\u0004\ty.\u0001\bge>l7\t\\5PaR$\u0016\u0010]3\u0015\r\u0005}7QTBP\u0011\u0019qX\n1\u0001\u0002T!91qJ\'A\u0002\tU\u0015\u0001\u0004;p\u00072Lw\n\u001d;UsB,G\u0003BBS\u0007O\u0003rA_B\u0013\u0003\'\u0012y\bC\u0004\u0004<9\u0003\r!a8\u0002%\u0019\u0014x.\\\"mS>\u0003H\u000fV=qK\u001ac\u0017m\u001a\u000b\u0007\u0003?\u001cika,\t\ry|\u0005\u0019AA1\u0011\u001d\u0019ye\u0014a\u0001\u0005+\u000b\u0001\u0003^8DY&|\u0005\u000f\u001e+za\u00164E.Y4\u0015\t\rU6q\u0017\t\bu\u000e\u0015\u0012\u0011\rB@\u0011\u001d\u0019Y\u0004\u0015a\u0001\u0003?\f\u0011C\u001a:p[\u000ec\u0017n\u00149u)f\u0004XMT;n)\u0019\tyn!0\u0004@\"1a0\u0015a\u0001\u0003oBqaa\u0014R\u0001\u0004\u0011)*A\bu_\u000ec\u0017n\u00149u)f\u0004XMT;n)\u0011\u0019)ma2\u0011\u000fi\u001c)#a\u001e\u0003\u0000!911\b*A\u0002\u0005}\u0017!\u00064s_6\u001cE.[(qiRK\b/\u001a(v[\u001ac\u0017m\u001a\u000b\u0007\u0003?\u001cima4\t\ry\u001c\u0006\u0019AAC\u0011\u001d\u0019ye\u0015a\u0001\u0005+\u000b1\u0003^8DY&|\u0005\u000f\u001e+za\u0016tU/\u001c$mC\u001e$Ba!6\u0004XB9!p!\n\u0002\u0006\n}\u0004bBB\u001e)\u0002\u0007\u0011q\\\u0001\u0018MJ|Wn\u00117j\u001fB$H+\u001f9f\u001dVl7\t[8jG\u0016$b!a8\u0004^\u000e}\u0007B\u0002@V\u0001\u0004\t\u0019\nC\u0004\u0004PU\u0003\rA!&\u0002+Q|7\t\\5PaR$\u0016\u0010]3Ok6\u001c\u0005n\\5dKR!1Q]Bt!\u001dQ8QEAJ\u0005\u007fBqaa\u000fW\u0001\u0004\ty.A\tge>l7\t\\5PaR$\u0016\u0010]3TiJ$b!a8\u0004n\u000e=\bB\u0002@X\u0001\u0004\t\t\u000bC\u0004\u0004P]\u0003\rA!&\u0002\u001fQ|7\t\\5PaR$\u0016\u0010]3TiJ$Ba!>\u0004xB9!p!\n\u0002\"\n}\u0004bBB\u001e1\u0002\u0007\u0011q\\\u0001\u0015MJ|Wn\u00117j\u001fB$H+\u001f9f\u0007\"|\u0017nY3\u0015\r\u0005}7Q`B\u0000\u0011\u0019q\u0018\f1\u0001\u00020\"91qJ-A\u0002\tU\u0015A\u0005;p\u00072Lw\n\u001d;UsB,7\t[8jG\u0016$B\u0001\"\u0002\u0005\bA9!p!\n\u00020\n}\u0004bBB\u001e5\u0002\u0007\u0011q\\\u0001\u0013MJ|Wn\u00117j\u001fB$H+\u001f9f!\u0006$\b\u000e\u0006\u0004\u0002`\u00125Aq\u0002\u0005\u0007}n\u0003\r!!0\t\u000f\r=3\f1\u0001\u0003\u0016\u0006\u0001Bo\\\"mS>\u0003H\u000fV=qKB\u000bG\u000f\u001b\u000b\u0005\t+!9\u0002E\u0004{\u0007K\tiLa \t\u000f\rmB\f1\u0001\u0002`\u0002
    #9 = Utf8               org/sireum/Json$ErrorMsg
   #10 = Class              #9            // org/sireum/Json$ErrorMsg
   #11 = Utf8               org/sireum/Json
   #12 = Class              #11           // org/sireum/Json
   #13 = Utf8               ErrorMsg
   #14 = Utf8               org/sireum/cli/CliOpt$Group
   #15 = Class              #14           // org/sireum/cli/CliOpt$Group
   #16 = Utf8               org/sireum/cli/CliOpt
   #17 = Class              #16           // org/sireum/cli/CliOpt
   #18 = Utf8               Group
   #19 = Utf8               org/sireum/cli/CliOpt$Opt
   #20 = Class              #19           // org/sireum/cli/CliOpt$Opt
   #21 = Utf8               Opt
   #22 = Utf8               org/sireum/cli/CliOpt$OptGroup
   #23 = Class              #22           // org/sireum/cli/CliOpt$OptGroup
   #24 = Utf8               OptGroup
   #25 = Utf8               org/sireum/cli/CliOpt$Tool
   #26 = Class              #25           // org/sireum/cli/CliOpt$Tool
   #27 = Utf8               Tool
   #28 = Utf8               org/sireum/cli/CliOpt$Type
   #29 = Class              #28           // org/sireum/cli/CliOpt$Type
   #30 = Utf8               Type
   #31 = Utf8               org/sireum/cli/CliOpt$Type$
   #32 = Class              #31           // org/sireum/cli/CliOpt$Type$
   #33 = Utf8               Type$
   #34 = Utf8               org/sireum/cli/CliOpt$Type$Choice
   #35 = Class              #34           // org/sireum/cli/CliOpt$Type$Choice
   #36 = Utf8               Choice
   #37 = Utf8               org/sireum/cli/CliOpt$Type$Flag
   #38 = Class              #37           // org/sireum/cli/CliOpt$Type$Flag
   #39 = Utf8               Flag
   #40 = Utf8               org/sireum/cli/CliOpt$Type$Num
   #41 = Class              #40           // org/sireum/cli/CliOpt$Type$Num
   #42 = Utf8               Num
   #43 = Utf8               org/sireum/cli/CliOpt$Type$NumChoice
   #44 = Class              #43           // org/sireum/cli/CliOpt$Type$NumChoice
   #45 = Utf8               NumChoice
   #46 = Utf8               org/sireum/cli/CliOpt$Type$NumFlag
   #47 = Class              #46           // org/sireum/cli/CliOpt$Type$NumFlag
   #48 = Utf8               NumFlag
   #49 = Utf8               org/sireum/cli/CliOpt$Type$Path
   #50 = Class              #49           // org/sireum/cli/CliOpt$Type$Path
   #51 = Utf8               Path
   #52 = Utf8               org/sireum/cli/CliOpt$Type$Str
   #53 = Class              #52           // org/sireum/cli/CliOpt$Type$Str
   #54 = Utf8               Str
   #55 = Utf8               org/sireum/cli/JSON$Parser
   #56 = Class              #55           // org/sireum/cli/JSON$Parser
   #57 = Utf8               Parser
   #58 = Utf8               org/sireum/cli/JSON$Parser$
   #59 = Class              #58           // org/sireum/cli/JSON$Parser$
   #60 = Utf8               Parser$
   #61 = Utf8               org/sireum/cli/JSON$Printer$
   #62 = Class              #61           // org/sireum/cli/JSON$Printer$
   #63 = Utf8               Printer$
   #64 = Utf8               toCliOptTypePath
   #65 = Utf8               (Ljava/lang/String;)Lorg/sireum/Either;
   #66 = Utf8               (Ljava/lang/String;)Lorg/sireum/Either<Lorg/sireum/cli/CliOpt$Type$Path;Lorg/sireum/Json$ErrorMsg;>;
   #67 = Utf8               s
   #68 = Utf8               org/sireum/cli/JSON$
   #69 = Class              #68           // org/sireum/cli/JSON$
   #70 = Utf8               MODULE$
   #71 = Utf8               Lorg/sireum/cli/JSON$;
   #72 = NameAndType        #70:#71       // MODULE$:Lorg/sireum/cli/JSON$;
   #73 = Fieldref           #69.#72       // org/sireum/cli/JSON$.MODULE$:Lorg/sireum/cli/JSON$;
   #74 = NameAndType        #64:#65       // toCliOptTypePath:(Ljava/lang/String;)Lorg/sireum/Either;
   #75 = Methodref          #69.#74       // org/sireum/cli/JSON$.toCliOptTypePath:(Ljava/lang/String;)Lorg/sireum/Either;
   #76 = Utf8               Ljava/lang/String;
   #77 = Utf8               fromCliOptTypePath
   #78 = Utf8               (Lorg/sireum/cli/CliOpt$Type$Path;Z)Ljava/lang/String;
   #79 = Utf8               o
   #80 = Utf8               isCompact
   #81 = NameAndType        #77:#78       // fromCliOptTypePath:(Lorg/sireum/cli/CliOpt$Type$Path;Z)Ljava/lang/String;
   #82 = Methodref          #69.#81       // org/sireum/cli/JSON$.fromCliOptTypePath:(Lorg/sireum/cli/CliOpt$Type$Path;Z)Ljava/lang/String;
   #83 = Utf8               Lorg/sireum/cli/CliOpt$Type$Path;
   #84 = Utf8               Z
   #85 = Utf8               toCliOptTypeChoice
   #86 = Utf8               (Ljava/lang/String;)Lorg/sireum/Either<Lorg/sireum/cli/CliOpt$Type$Choice;Lorg/sireum/Json$ErrorMsg;>;
   #87 = NameAndType        #85:#65       // toCliOptTypeChoice:(Ljava/lang/String;)Lorg/sireum/Either;
   #88 = Methodref          #69.#87       // org/sireum/cli/JSON$.toCliOptTypeChoice:(Ljava/lang/String;)Lorg/sireum/Either;
   #89 = Utf8               fromCliOptTypeChoice
   #90 = Utf8               (Lorg/sireum/cli/CliOpt$Type$Choice;Z)Ljava/lang/String;
   #91 = NameAndType        #89:#90       // fromCliOptTypeChoice:(Lorg/sireum/cli/CliOpt$Type$Choice;Z)Ljava/lang/String;
   #92 = Methodref          #69.#91       // org/sireum/cli/JSON$.fromCliOptTypeChoice:(Lorg/sireum/cli/CliOpt$Type$Choice;Z)Ljava/lang/String;
   #93 = Utf8               Lorg/sireum/cli/CliOpt$Type$Choice;
   #94 = Utf8               toCliOptTypeStr
   #95 = Utf8               (Ljava/lang/String;)Lorg/sireum/Either<Lorg/sireum/cli/CliOpt$Type$Str;Lorg/sireum/Json$ErrorMsg;>;
   #96 = NameAndType        #94:#65       // toCliOptTypeStr:(Ljava/lang/String;)Lorg/sireum/Either;
   #97 = Methodref          #69.#96       // org/sireum/cli/JSON$.toCliOptTypeStr:(Ljava/lang/String;)Lorg/sireum/Either;
   #98 = Utf8               fromCliOptTypeStr
   #99 = Utf8               (Lorg/sireum/cli/CliOpt$Type$Str;Z)Ljava/lang/String;
  #100 = NameAndType        #98:#99       // fromCliOptTypeStr:(Lorg/sireum/cli/CliOpt$Type$Str;Z)Ljava/lang/String;
  #101 = Methodref          #69.#100      // org/sireum/cli/JSON$.fromCliOptTypeStr:(Lorg/sireum/cli/CliOpt$Type$Str;Z)Ljava/lang/String;
  #102 = Utf8               Lorg/sireum/cli/CliOpt$Type$Str;
  #103 = Utf8               toCliOptTypeNumChoice
  #104 = Utf8               (Ljava/lang/String;)Lorg/sireum/Either<Lorg/sireum/cli/CliOpt$Type$NumChoice;Lorg/sireum/Json$ErrorMsg;>;
  #105 = NameAndType        #103:#65      // toCliOptTypeNumChoice:(Ljava/lang/String;)Lorg/sireum/Either;
  #106 = Methodref          #69.#105      // org/sireum/cli/JSON$.toCliOptTypeNumChoice:(Ljava/lang/String;)Lorg/sireum/Either;
  #107 = Utf8               fromCliOptTypeNumChoice
  #108 = Utf8               (Lorg/sireum/cli/CliOpt$Type$NumChoice;Z)Ljava/lang/String;
  #109 = NameAndType        #107:#108     // fromCliOptTypeNumChoice:(Lorg/sireum/cli/CliOpt$Type$NumChoice;Z)Ljava/lang/String;
  #110 = Methodref          #69.#109      // org/sireum/cli/JSON$.fromCliOptTypeNumChoice:(Lorg/sireum/cli/CliOpt$Type$NumChoice;Z)Ljava/lang/String;
  #111 = Utf8               Lorg/sireum/cli/CliOpt$Type$NumChoice;
  #112 = Utf8               toCliOptTypeNumFlag
  #113 = Utf8               (Ljava/lang/String;)Lorg/sireum/Either<Lorg/sireum/cli/CliOpt$Type$NumFlag;Lorg/sireum/Json$ErrorMsg;>;
  #114 = NameAndType        #112:#65      // toCliOptTypeNumFlag:(Ljava/lang/String;)Lorg/sireum/Either;
  #115 = Methodref          #69.#114      // org/sireum/cli/JSON$.toCliOptTypeNumFlag:(Ljava/lang/String;)Lorg/sireum/Either;
  #116 = Utf8               fromCliOptTypeNumFlag
  #117 = Utf8               (Lorg/sireum/cli/CliOpt$Type$NumFlag;Z)Ljava/lang/String;
  #118 = NameAndType        #116:#117     // fromCliOptTypeNumFlag:(Lorg/sireum/cli/CliOpt$Type$NumFlag;Z)Ljava/lang/String;
  #119 = Methodref          #69.#118      // org/sireum/cli/JSON$.fromCliOptTypeNumFlag:(Lorg/sireum/cli/CliOpt$Type$NumFlag;Z)Ljava/lang/String;
  #120 = Utf8               Lorg/sireum/cli/CliOpt$Type$NumFlag;
  #121 = Utf8               toCliOptTypeNum
  #122 = Utf8               (Ljava/lang/String;)Lorg/sireum/Either<Lorg/sireum/cli/CliOpt$Type$Num;Lorg/sireum/Json$ErrorMsg;>;
  #123 = NameAndType        #121:#65      // toCliOptTypeNum:(Ljava/lang/String;)Lorg/sireum/Either;
  #124 = Methodref          #69.#123      // org/sireum/cli/JSON$.toCliOptTypeNum:(Ljava/lang/String;)Lorg/sireum/Either;
  #125 = Utf8               fromCliOptTypeNum
  #126 = Utf8               (Lorg/sireum/cli/CliOpt$Type$Num;Z)Ljava/lang/String;
  #127 = NameAndType        #125:#126     // fromCliOptTypeNum:(Lorg/sireum/cli/CliOpt$Type$Num;Z)Ljava/lang/String;
  #128 = Methodref          #69.#127      // org/sireum/cli/JSON$.fromCliOptTypeNum:(Lorg/sireum/cli/CliOpt$Type$Num;Z)Ljava/lang/String;
  #129 = Utf8               Lorg/sireum/cli/CliOpt$Type$Num;
  #130 = Utf8               toCliOptTypeFlag
  #131 = Utf8               (Ljava/lang/String;)Lorg/sireum/Either<Lorg/sireum/cli/CliOpt$Type$Flag;Lorg/sireum/Json$ErrorMsg;>;
  #132 = NameAndType        #130:#65      // toCliOptTypeFlag:(Ljava/lang/String;)Lorg/sireum/Either;
  #133 = Methodref          #69.#132      // org/sireum/cli/JSON$.toCliOptTypeFlag:(Ljava/lang/String;)Lorg/sireum/Either;
  #134 = Utf8               fromCliOptTypeFlag
  #135 = Utf8               (Lorg/sireum/cli/CliOpt$Type$Flag;Z)Ljava/lang/String;
  #136 = NameAndType        #134:#135     // fromCliOptTypeFlag:(Lorg/sireum/cli/CliOpt$Type$Flag;Z)Ljava/lang/String;
  #137 = Methodref          #69.#136      // org/sireum/cli/JSON$.fromCliOptTypeFlag:(Lorg/sireum/cli/CliOpt$Type$Flag;Z)Ljava/lang/String;
  #138 = Utf8               Lorg/sireum/cli/CliOpt$Type$Flag;
  #139 = Utf8               toCliOptType
  #140 = Utf8               (Ljava/lang/String;)Lorg/sireum/Either<Lorg/sireum/cli/CliOpt$Type;Lorg/sireum/Json$ErrorMsg;>;
  #141 = NameAndType        #139:#65      // toCliOptType:(Ljava/lang/String;)Lorg/sireum/Either;
  #142 = Methodref          #69.#141      // org/sireum/cli/JSON$.toCliOptType:(Ljava/lang/String;)Lorg/sireum/Either;
  #143 = Utf8               fromCliOptType
  #144 = Utf8               (Lorg/sireum/cli/CliOpt$Type;Z)Ljava/lang/String;
  #145 = NameAndType        #143:#144     // fromCliOptType:(Lorg/sireum/cli/CliOpt$Type;Z)Ljava/lang/String;
  #146 = Methodref          #69.#145      // org/sireum/cli/JSON$.fromCliOptType:(Lorg/sireum/cli/CliOpt$Type;Z)Ljava/lang/String;
  #147 = Utf8               Lorg/sireum/cli/CliOpt$Type;
  #148 = Utf8               toCliOptOpt
  #149 = Utf8               (Ljava/lang/String;)Lorg/sireum/Either<Lorg/sireum/cli/CliOpt$Opt;Lorg/sireum/Json$ErrorMsg;>;
  #150 = NameAndType        #148:#65      // toCliOptOpt:(Ljava/lang/String;)Lorg/sireum/Either;
  #151 = Methodref          #69.#150      // org/sireum/cli/JSON$.toCliOptOpt:(Ljava/lang/String;)Lorg/sireum/Either;
  #152 = Utf8               fromCliOptOpt
  #153 = Utf8               (Lorg/sireum/cli/CliOpt$Opt;Z)Ljava/lang/String;
  #154 = NameAndType        #152:#153     // fromCliOptOpt:(Lorg/sireum/cli/CliOpt$Opt;Z)Ljava/lang/String;
  #155 = Methodref          #69.#154      // org/sireum/cli/JSON$.fromCliOptOpt:(Lorg/sireum/cli/CliOpt$Opt;Z)Ljava/lang/String;
  #156 = Utf8               Lorg/sireum/cli/CliOpt$Opt;
  #157 = Utf8               toCliOptOptGroup
  #158 = Utf8               (Ljava/lang/String;)Lorg/sireum/Either<Lorg/sireum/cli/CliOpt$OptGroup;Lorg/sireum/Json$ErrorMsg;>;
  #159 = NameAndType        #157:#65      // toCliOptOptGroup:(Ljava/lang/String;)Lorg/sireum/Either;
  #160 = Methodref          #69.#159      // org/sireum/cli/JSON$.toCliOptOptGroup:(Ljava/lang/String;)Lorg/sireum/Either;
  #161 = Utf8               fromCliOptOptGroup
  #162 = Utf8               (Lorg/sireum/cli/CliOpt$OptGroup;Z)Ljava/lang/String;
  #163 = NameAndType        #161:#162     // fromCliOptOptGroup:(Lorg/sireum/cli/CliOpt$OptGroup;Z)Ljava/lang/String;
  #164 = Methodref          #69.#163      // org/sireum/cli/JSON$.fromCliOptOptGroup:(Lorg/sireum/cli/CliOpt$OptGroup;Z)Ljava/lang/String;
  #165 = Utf8               Lorg/sireum/cli/CliOpt$OptGroup;
  #166 = Utf8               toCliOptTool
  #167 = Utf8               (Ljava/lang/String;)Lorg/sireum/Either<Lorg/sireum/cli/CliOpt$Tool;Lorg/sireum/Json$ErrorMsg;>;
  #168 = NameAndType        #166:#65      // toCliOptTool:(Ljava/lang/String;)Lorg/sireum/Either;
  #169 = Methodref          #69.#168      // org/sireum/cli/JSON$.toCliOptTool:(Ljava/lang/String;)Lorg/sireum/Either;
  #170 = Utf8               fromCliOptTool
  #171 = Utf8               (Lorg/sireum/cli/CliOpt$Tool;Z)Ljava/lang/String;
  #172 = NameAndType        #170:#171     // fromCliOptTool:(Lorg/sireum/cli/CliOpt$Tool;Z)Ljava/lang/String;
  #173 = Methodref          #69.#172      // org/sireum/cli/JSON$.fromCliOptTool:(Lorg/sireum/cli/CliOpt$Tool;Z)Ljava/lang/String;
  #174 = Utf8               Lorg/sireum/cli/CliOpt$Tool;
  #175 = Utf8               toCliOptGroup
  #176 = Utf8               (Ljava/lang/String;)Lorg/sireum/Either<Lorg/sireum/cli/CliOpt$Group;Lorg/sireum/Json$ErrorMsg;>;
  #177 = NameAndType        #175:#65      // toCliOptGroup:(Ljava/lang/String;)Lorg/sireum/Either;
  #178 = Methodref          #69.#177      // org/sireum/cli/JSON$.toCliOptGroup:(Ljava/lang/String;)Lorg/sireum/Either;
  #179 = Utf8               fromCliOptGroup
  #180 = Utf8               (Lorg/sireum/cli/CliOpt$Group;Z)Ljava/lang/String;
  #181 = NameAndType        #179:#180     // fromCliOptGroup:(Lorg/sireum/cli/CliOpt$Group;Z)Ljava/lang/String;
  #182 = Methodref          #69.#181      // org/sireum/cli/JSON$.fromCliOptGroup:(Lorg/sireum/cli/CliOpt$Group;Z)Ljava/lang/String;
  #183 = Utf8               Lorg/sireum/cli/CliOpt$Group;
  #184 = Utf8               toCliOpt
  #185 = Utf8               (Ljava/lang/String;)Lorg/sireum/Either<Lorg/sireum/cli/CliOpt;Lorg/sireum/Json$ErrorMsg;>;
  #186 = NameAndType        #184:#65      // toCliOpt:(Ljava/lang/String;)Lorg/sireum/Either;
  #187 = Methodref          #69.#186      // org/sireum/cli/JSON$.toCliOpt:(Ljava/lang/String;)Lorg/sireum/Either;
  #188 = Utf8               fromCliOpt
  #189 = Utf8               (Lorg/sireum/cli/CliOpt;Z)Ljava/lang/String;
  #190 = NameAndType        #188:#189     // fromCliOpt:(Lorg/sireum/cli/CliOpt;Z)Ljava/lang/String;
  #191 = Methodref          #69.#190      // org/sireum/cli/JSON$.fromCliOpt:(Lorg/sireum/cli/CliOpt;Z)Ljava/lang/String;
  #192 = Utf8               Lorg/sireum/cli/CliOpt;
  #193 = Utf8               to
  #194 = Utf8               (Ljava/lang/String;Lscala/Function1;)Lorg/sireum/Either;
  #195 = Utf8               <T:Ljava/lang/Object;>(Ljava/lang/String;Lscala/Function1<Lorg/sireum/cli/JSON$Parser;TT;>;)Lorg/sireum/Either<TT;Lorg/sireum/Json$ErrorMsg;>;
  #196 = Utf8               f
  #197 = NameAndType        #193:#194     // to:(Ljava/lang/String;Lscala/Function1;)Lorg/sireum/Either;
  #198 = Methodref          #69.#197      // org/sireum/cli/JSON$.to:(Ljava/lang/String;Lscala/Function1;)Lorg/sireum/Either;
  #199 = Utf8               Lscala/Function1;
  #200 = Utf8               Code
  #201 = Utf8               LocalVariableTable
  #202 = Utf8               Signature
  #203 = Utf8               MethodParameters
  #204 = Utf8               InnerClasses
  #205 = Utf8               SourceFile
  #206 = Utf8               RuntimeVisibleAnnotations
  #207 = Utf8               ScalaSig
{
  public static org.sireum.Either<org.sireum.cli.CliOpt$Type$Path, org.sireum.Json$ErrorMsg> toCliOptTypePath(java.lang.String);
    descriptor: (Ljava/lang/String;)Lorg/sireum/Either;
    flags: (0x0009) ACC_PUBLIC, ACC_STATIC
    Code:
      stack=2, locals=1, args_size=1
         0: getstatic     #73                 // Field org/sireum/cli/JSON$.MODULE$:Lorg/sireum/cli/JSON$;
         3: aload_0
         4: invokevirtual #75                 // Method org/sireum/cli/JSON$.toCliOptTypePath:(Ljava/lang/String;)Lorg/sireum/Either;
         7: areturn
      LocalVariableTable:
        Start  Length  Slot  Name   Signature
            0       8     0     s   Ljava/lang/String;
    Signature: #66                          // (Ljava/lang/String;)Lorg/sireum/Either<Lorg/sireum/cli/CliOpt$Type$Path;Lorg/sireum/Json$ErrorMsg;>;
    MethodParameters:
      Name                           Flags
      s                              final

  public static java.lang.String fromCliOptTypePath(org.sireum.cli.CliOpt$Type$Path, boolean);
    descriptor: (Lorg/sireum/cli/CliOpt$Type$Path;Z)Ljava/lang/String;
    flags: (0x0009) ACC_PUBLIC, ACC_STATIC
    Code:
      stack=3, locals=2, args_size=2
         0: getstatic     #73                 // Field org/sireum/cli/JSON$.MODULE$:Lorg/sireum/cli/JSON$;
         3: aload_0
         4: iload_1
         5: invokevirtual #82                 // Method org/sireum/cli/JSON$.fromCliOptTypePath:(Lorg/sireum/cli/CliOpt$Type$Path;Z)Ljava/lang/String;
         8: areturn
      LocalVariableTable:
        Start  Length  Slot  Name   Signature
            0       9     0     o   Lorg/sireum/cli/CliOpt$Type$Path;
            0       9     1 isCompact   Z
    MethodParameters:
      Name                           Flags
      o                              final
      isCompact                      final

  public static org.sireum.Either<org.sireum.cli.CliOpt$Type$Choice, org.sireum.Json$ErrorMsg> toCliOptTypeChoice(java.lang.String);
    descriptor: (Ljava/lang/String;)Lorg/sireum/Either;
    flags: (0x0009) ACC_PUBLIC, ACC_STATIC
    Code:
      stack=2, locals=1, args_size=1
         0: getstatic     #73                 // Field org/sireum/cli/JSON$.MODULE$:Lorg/sireum/cli/JSON$;
         3: aload_0
         4: invokevirtual #88                 // Method org/sireum/cli/JSON$.toCliOptTypeChoice:(Ljava/lang/String;)Lorg/sireum/Either;
         7: areturn
      LocalVariableTable:
        Start  Length  Slot  Name   Signature
            0       8     0     s   Ljava/lang/String;
    Signature: #86                          // (Ljava/lang/String;)Lorg/sireum/Either<Lorg/sireum/cli/CliOpt$Type$Choice;Lorg/sireum/Json$ErrorMsg;>;
    MethodParameters:
      Name                           Flags
      s                              final

  public static java.lang.String fromCliOptTypeChoice(org.sireum.cli.CliOpt$Type$Choice, boolean);
    descriptor: (Lorg/sireum/cli/CliOpt$Type$Choice;Z)Ljava/lang/String;
    flags: (0x0009) ACC_PUBLIC, ACC_STATIC
    Code:
      stack=3, locals=2, args_size=2
         0: getstatic     #73                 // Field org/sireum/cli/JSON$.MODULE$:Lorg/sireum/cli/JSON$;
         3: aload_0
         4: iload_1
         5: invokevirtual #92                 // Method org/sireum/cli/JSON$.fromCliOptTypeChoice:(Lorg/sireum/cli/CliOpt$Type$Choice;Z)Ljava/lang/String;
         8: areturn
      LocalVariableTable:
        Start  Length  Slot  Name   Signature
            0       9     0     o   Lorg/sireum/cli/CliOpt$Type$Choice;
            0       9     1 isCompact   Z
    MethodParameters:
      Name                           Flags
      o                              final
      isCompact                      final

  public static org.sireum.Either<org.sireum.cli.CliOpt$Type$Str, org.sireum.Json$ErrorMsg> toCliOptTypeStr(java.lang.String);
    descriptor: (Ljava/lang/String;)Lorg/sireum/Either;
    flags: (0x0009) ACC_PUBLIC, ACC_STATIC
    Code:
      stack=2, locals=1, args_size=1
         0: getstatic     #73                 // Field org/sireum/cli/JSON$.MODULE$:Lorg/sireum/cli/JSON$;
         3: aload_0
         4: invokevirtual #97                 // Method org/sireum/cli/JSON$.toCliOptTypeStr:(Ljava/lang/String;)Lorg/sireum/Either;
         7: areturn
      LocalVariableTable:
        Start  Length  Slot  Name   Signature
            0       8     0     s   Ljava/lang/String;
    Signature: #95                          // (Ljava/lang/String;)Lorg/sireum/Either<Lorg/sireum/cli/CliOpt$Type$Str;Lorg/sireum/Json$ErrorMsg;>;
    MethodParameters:
      Name                           Flags
      s                              final

  public static java.lang.String fromCliOptTypeStr(org.sireum.cli.CliOpt$Type$Str, boolean);
    descriptor: (Lorg/sireum/cli/CliOpt$Type$Str;Z)Ljava/lang/String;
    flags: (0x0009) ACC_PUBLIC, ACC_STATIC
    Code:
      stack=3, locals=2, args_size=2
         0: getstatic     #73                 // Field org/sireum/cli/JSON$.MODULE$:Lorg/sireum/cli/JSON$;
         3: aload_0
         4: iload_1
         5: invokevirtual #101                // Method org/sireum/cli/JSON$.fromCliOptTypeStr:(Lorg/sireum/cli/CliOpt$Type$Str;Z)Ljava/lang/String;
         8: areturn
      LocalVariableTable:
        Start  Length  Slot  Name   Signature
            0       9     0     o   Lorg/sireum/cli/CliOpt$Type$Str;
            0       9     1 isCompact   Z
    MethodParameters:
      Name                           Flags
      o                              final
      isCompact                      final

  public static org.sireum.Either<org.sireum.cli.CliOpt$Type$NumChoice, org.sireum.Json$ErrorMsg> toCliOptTypeNumChoice(java.lang.String);
    descriptor: (Ljava/lang/String;)Lorg/sireum/Either;
    flags: (0x0009) ACC_PUBLIC, ACC_STATIC
    Code:
      stack=2, locals=1, args_size=1
         0: getstatic     #73                 // Field org/sireum/cli/JSON$.MODULE$:Lorg/sireum/cli/JSON$;
         3: aload_0
         4: invokevirtual #106                // Method org/sireum/cli/JSON$.toCliOptTypeNumChoice:(Ljava/lang/String;)Lorg/sireum/Either;
         7: areturn
      LocalVariableTable:
        Start  Length  Slot  Name   Signature
            0       8     0     s   Ljava/lang/String;
    Signature: #104                         // (Ljava/lang/String;)Lorg/sireum/Either<Lorg/sireum/cli/CliOpt$Type$NumChoice;Lorg/sireum/Json$ErrorMsg;>;
    MethodParameters:
      Name                           Flags
      s                              final

  public static java.lang.String fromCliOptTypeNumChoice(org.sireum.cli.CliOpt$Type$NumChoice, boolean);
    descriptor: (Lorg/sireum/cli/CliOpt$Type$NumChoice;Z)Ljava/lang/String;
    flags: (0x0009) ACC_PUBLIC, ACC_STATIC
    Code:
      stack=3, locals=2, args_size=2
         0: getstatic     #73                 // Field org/sireum/cli/JSON$.MODULE$:Lorg/sireum/cli/JSON$;
         3: aload_0
         4: iload_1
         5: invokevirtual #110                // Method org/sireum/cli/JSON$.fromCliOptTypeNumChoice:(Lorg/sireum/cli/CliOpt$Type$NumChoice;Z)Ljava/lang/String;
         8: areturn
      LocalVariableTable:
        Start  Length  Slot  Name   Signature
            0       9     0     o   Lorg/sireum/cli/CliOpt$Type$NumChoice;
            0       9     1 isCompact   Z
    MethodParameters:
      Name                           Flags
      o                              final
      isCompact                      final

  public static org.sireum.Either<org.sireum.cli.CliOpt$Type$NumFlag, org.sireum.Json$ErrorMsg> toCliOptTypeNumFlag(java.lang.String);
    descriptor: (Ljava/lang/String;)Lorg/sireum/Either;
    flags: (0x0009) ACC_PUBLIC, ACC_STATIC
    Code:
      stack=2, locals=1, args_size=1
         0: getstatic     #73                 // Field org/sireum/cli/JSON$.MODULE$:Lorg/sireum/cli/JSON$;
         3: aload_0
         4: invokevirtual #115                // Method org/sireum/cli/JSON$.toCliOptTypeNumFlag:(Ljava/lang/String;)Lorg/sireum/Either;
         7: areturn
      LocalVariableTable:
        Start  Length  Slot  Name   Signature
            0       8     0     s   Ljava/lang/String;
    Signature: #113                         // (Ljava/lang/String;)Lorg/sireum/Either<Lorg/sireum/cli/CliOpt$Type$NumFlag;Lorg/sireum/Json$ErrorMsg;>;
    MethodParameters:
      Name                           Flags
      s                              final

  public static java.lang.String fromCliOptTypeNumFlag(org.sireum.cli.CliOpt$Type$NumFlag, boolean);
    descriptor: (Lorg/sireum/cli/CliOpt$Type$NumFlag;Z)Ljava/lang/String;
    flags: (0x0009) ACC_PUBLIC, ACC_STATIC
    Code:
      stack=3, locals=2, args_size=2
         0: getstatic     #73                 // Field org/sireum/cli/JSON$.MODULE$:Lorg/sireum/cli/JSON$;
         3: aload_0
         4: iload_1
         5: invokevirtual #119                // Method org/sireum/cli/JSON$.fromCliOptTypeNumFlag:(Lorg/sireum/cli/CliOpt$Type$NumFlag;Z)Ljava/lang/String;
         8: areturn
      LocalVariableTable:
        Start  Length  Slot  Name   Signature
            0       9     0     o   Lorg/sireum/cli/CliOpt$Type$NumFlag;
            0       9     1 isCompact   Z
    MethodParameters:
      Name                           Flags
      o                              final
      isCompact                      final

  public static org.sireum.Either<org.sireum.cli.CliOpt$Type$Num, org.sireum.Json$ErrorMsg> toCliOptTypeNum(java.lang.String);
    descriptor: (Ljava/lang/String;)Lorg/sireum/Either;
    flags: (0x0009) ACC_PUBLIC, ACC_STATIC
    Code:
      stack=2, locals=1, args_size=1
         0: getstatic     #73                 // Field org/sireum/cli/JSON$.MODULE$:Lorg/sireum/cli/JSON$;
         3: aload_0
         4: invokevirtual #124                // Method org/sireum/cli/JSON$.toCliOptTypeNum:(Ljava/lang/String;)Lorg/sireum/Either;
         7: areturn
      LocalVariableTable:
        Start  Length  Slot  Name   Signature
            0       8     0     s   Ljava/lang/String;
    Signature: #122                         // (Ljava/lang/String;)Lorg/sireum/Either<Lorg/sireum/cli/CliOpt$Type$Num;Lorg/sireum/Json$ErrorMsg;>;
    MethodParameters:
      Name                           Flags
      s                              final

  public static java.lang.String fromCliOptTypeNum(org.sireum.cli.CliOpt$Type$Num, boolean);
    descriptor: (Lorg/sireum/cli/CliOpt$Type$Num;Z)Ljava/lang/String;
    flags: (0x0009) ACC_PUBLIC, ACC_STATIC
    Code:
      stack=3, locals=2, args_size=2
         0: getstatic     #73                 // Field org/sireum/cli/JSON$.MODULE$:Lorg/sireum/cli/JSON$;
         3: aload_0
         4: iload_1
         5: invokevirtual #128                // Method org/sireum/cli/JSON$.fromCliOptTypeNum:(Lorg/sireum/cli/CliOpt$Type$Num;Z)Ljava/lang/String;
         8: areturn
      LocalVariableTable:
        Start  Length  Slot  Name   Signature
            0       9     0     o   Lorg/sireum/cli/CliOpt$Type$Num;
            0       9     1 isCompact   Z
    MethodParameters:
      Name                           Flags
      o                              final
      isCompact                      final

  public static org.sireum.Either<org.sireum.cli.CliOpt$Type$Flag, org.sireum.Json$ErrorMsg> toCliOptTypeFlag(java.lang.String);
    descriptor: (Ljava/lang/String;)Lorg/sireum/Either;
    flags: (0x0009) ACC_PUBLIC, ACC_STATIC
    Code:
      stack=2, locals=1, args_size=1
         0: getstatic     #73                 // Field org/sireum/cli/JSON$.MODULE$:Lorg/sireum/cli/JSON$;
         3: aload_0
         4: invokevirtual #133                // Method org/sireum/cli/JSON$.toCliOptTypeFlag:(Ljava/lang/String;)Lorg/sireum/Either;
         7: areturn
      LocalVariableTable:
        Start  Length  Slot  Name   Signature
            0       8     0     s   Ljava/lang/String;
    Signature: #131                         // (Ljava/lang/String;)Lorg/sireum/Either<Lorg/sireum/cli/CliOpt$Type$Flag;Lorg/sireum/Json$ErrorMsg;>;
    MethodParameters:
      Name                           Flags
      s                              final

  public static java.lang.String fromCliOptTypeFlag(org.sireum.cli.CliOpt$Type$Flag, boolean);
    descriptor: (Lorg/sireum/cli/CliOpt$Type$Flag;Z)Ljava/lang/String;
    flags: (0x0009) ACC_PUBLIC, ACC_STATIC
    Code:
      stack=3, locals=2, args_size=2
         0: getstatic     #73                 // Field org/sireum/cli/JSON$.MODULE$:Lorg/sireum/cli/JSON$;
         3: aload_0
         4: iload_1
         5: invokevirtual #137                // Method org/sireum/cli/JSON$.fromCliOptTypeFlag:(Lorg/sireum/cli/CliOpt$Type$Flag;Z)Ljava/lang/String;
         8: areturn
      LocalVariableTable:
        Start  Length  Slot  Name   Signature
            0       9     0     o   Lorg/sireum/cli/CliOpt$Type$Flag;
            0       9     1 isCompact   Z
    MethodParameters:
      Name                           Flags
      o                              final
      isCompact                      final

  public static org.sireum.Either<org.sireum.cli.CliOpt$Type, org.sireum.Json$ErrorMsg> toCliOptType(java.lang.String);
    descriptor: (Ljava/lang/String;)Lorg/sireum/Either;
    flags: (0x0009) ACC_PUBLIC, ACC_STATIC
    Code:
      stack=2, locals=1, args_size=1
         0: getstatic     #73                 // Field org/sireum/cli/JSON$.MODULE$:Lorg/sireum/cli/JSON$;
         3: aload_0
         4: invokevirtual #142                // Method org/sireum/cli/JSON$.toCliOptType:(Ljava/lang/String;)Lorg/sireum/Either;
         7: areturn
      LocalVariableTable:
        Start  Length  Slot  Name   Signature
            0       8     0     s   Ljava/lang/String;
    Signature: #140                         // (Ljava/lang/String;)Lorg/sireum/Either<Lorg/sireum/cli/CliOpt$Type;Lorg/sireum/Json$ErrorMsg;>;
    MethodParameters:
      Name                           Flags
      s                              final

  public static java.lang.String fromCliOptType(org.sireum.cli.CliOpt$Type, boolean);
    descriptor: (Lorg/sireum/cli/CliOpt$Type;Z)Ljava/lang/String;
    flags: (0x0009) ACC_PUBLIC, ACC_STATIC
    Code:
      stack=3, locals=2, args_size=2
         0: getstatic     #73                 // Field org/sireum/cli/JSON$.MODULE$:Lorg/sireum/cli/JSON$;
         3: aload_0
         4: iload_1
         5: invokevirtual #146                // Method org/sireum/cli/JSON$.fromCliOptType:(Lorg/sireum/cli/CliOpt$Type;Z)Ljava/lang/String;
         8: areturn
      LocalVariableTable:
        Start  Length  Slot  Name   Signature
            0       9     0     o   Lorg/sireum/cli/CliOpt$Type;
            0       9     1 isCompact   Z
    MethodParameters:
      Name                           Flags
      o                              final
      isCompact                      final

  public static org.sireum.Either<org.sireum.cli.CliOpt$Opt, org.sireum.Json$ErrorMsg> toCliOptOpt(java.lang.String);
    descriptor: (Ljava/lang/String;)Lorg/sireum/Either;
    flags: (0x0009) ACC_PUBLIC, ACC_STATIC
    Code:
      stack=2, locals=1, args_size=1
         0: getstatic     #73                 // Field org/sireum/cli/JSON$.MODULE$:Lorg/sireum/cli/JSON$;
         3: aload_0
         4: invokevirtual #151                // Method org/sireum/cli/JSON$.toCliOptOpt:(Ljava/lang/String;)Lorg/sireum/Either;
         7: areturn
      LocalVariableTable:
        Start  Length  Slot  Name   Signature
            0       8     0     s   Ljava/lang/String;
    Signature: #149                         // (Ljava/lang/String;)Lorg/sireum/Either<Lorg/sireum/cli/CliOpt$Opt;Lorg/sireum/Json$ErrorMsg;>;
    MethodParameters:
      Name                           Flags
      s                              final

  public static java.lang.String fromCliOptOpt(org.sireum.cli.CliOpt$Opt, boolean);
    descriptor: (Lorg/sireum/cli/CliOpt$Opt;Z)Ljava/lang/String;
    flags: (0x0009) ACC_PUBLIC, ACC_STATIC
    Code:
      stack=3, locals=2, args_size=2
         0: getstatic     #73                 // Field org/sireum/cli/JSON$.MODULE$:Lorg/sireum/cli/JSON$;
         3: aload_0
         4: iload_1
         5: invokevirtual #155                // Method org/sireum/cli/JSON$.fromCliOptOpt:(Lorg/sireum/cli/CliOpt$Opt;Z)Ljava/lang/String;
         8: areturn
      LocalVariableTable:
        Start  Length  Slot  Name   Signature
            0       9     0     o   Lorg/sireum/cli/CliOpt$Opt;
            0       9     1 isCompact   Z
    MethodParameters:
      Name                           Flags
      o                              final
      isCompact                      final

  public static org.sireum.Either<org.sireum.cli.CliOpt$OptGroup, org.sireum.Json$ErrorMsg> toCliOptOptGroup(java.lang.String);
    descriptor: (Ljava/lang/String;)Lorg/sireum/Either;
    flags: (0x0009) ACC_PUBLIC, ACC_STATIC
    Code:
      stack=2, locals=1, args_size=1
         0: getstatic     #73                 // Field org/sireum/cli/JSON$.MODULE$:Lorg/sireum/cli/JSON$;
         3: aload_0
         4: invokevirtual #160                // Method org/sireum/cli/JSON$.toCliOptOptGroup:(Ljava/lang/String;)Lorg/sireum/Either;
         7: areturn
      LocalVariableTable:
        Start  Length  Slot  Name   Signature
            0       8     0     s   Ljava/lang/String;
    Signature: #158                         // (Ljava/lang/String;)Lorg/sireum/Either<Lorg/sireum/cli/CliOpt$OptGroup;Lorg/sireum/Json$ErrorMsg;>;
    MethodParameters:
      Name                           Flags
      s                              final

  public static java.lang.String fromCliOptOptGroup(org.sireum.cli.CliOpt$OptGroup, boolean);
    descriptor: (Lorg/sireum/cli/CliOpt$OptGroup;Z)Ljava/lang/String;
    flags: (0x0009) ACC_PUBLIC, ACC_STATIC
    Code:
      stack=3, locals=2, args_size=2
         0: getstatic     #73                 // Field org/sireum/cli/JSON$.MODULE$:Lorg/sireum/cli/JSON$;
         3: aload_0
         4: iload_1
         5: invokevirtual #164                // Method org/sireum/cli/JSON$.fromCliOptOptGroup:(Lorg/sireum/cli/CliOpt$OptGroup;Z)Ljava/lang/String;
         8: areturn
      LocalVariableTable:
        Start  Length  Slot  Name   Signature
            0       9     0     o   Lorg/sireum/cli/CliOpt$OptGroup;
            0       9     1 isCompact   Z
    MethodParameters:
      Name                           Flags
      o                              final
      isCompact                      final

  public static org.sireum.Either<org.sireum.cli.CliOpt$Tool, org.sireum.Json$ErrorMsg> toCliOptTool(java.lang.String);
    descriptor: (Ljava/lang/String;)Lorg/sireum/Either;
    flags: (0x0009) ACC_PUBLIC, ACC_STATIC
    Code:
      stack=2, locals=1, args_size=1
         0: getstatic     #73                 // Field org/sireum/cli/JSON$.MODULE$:Lorg/sireum/cli/JSON$;
         3: aload_0
         4: invokevirtual #169                // Method org/sireum/cli/JSON$.toCliOptTool:(Ljava/lang/String;)Lorg/sireum/Either;
         7: areturn
      LocalVariableTable:
        Start  Length  Slot  Name   Signature
            0       8     0     s   Ljava/lang/String;
    Signature: #167                         // (Ljava/lang/String;)Lorg/sireum/Either<Lorg/sireum/cli/CliOpt$Tool;Lorg/sireum/Json$ErrorMsg;>;
    MethodParameters:
      Name                           Flags
      s                              final

  public static java.lang.String fromCliOptTool(org.sireum.cli.CliOpt$Tool, boolean);
    descriptor: (Lorg/sireum/cli/CliOpt$Tool;Z)Ljava/lang/String;
    flags: (0x0009) ACC_PUBLIC, ACC_STATIC
    Code:
      stack=3, locals=2, args_size=2
         0: getstatic     #73                 // Field org/sireum/cli/JSON$.MODULE$:Lorg/sireum/cli/JSON$;
         3: aload_0
         4: iload_1
         5: invokevirtual #173                // Method org/sireum/cli/JSON$.fromCliOptTool:(Lorg/sireum/cli/CliOpt$Tool;Z)Ljava/lang/String;
         8: areturn
      LocalVariableTable:
        Start  Length  Slot  Name   Signature
            0       9     0     o   Lorg/sireum/cli/CliOpt$Tool;
            0       9     1 isCompact   Z
    MethodParameters:
      Name                           Flags
      o                              final
      isCompact                      final

  public static org.sireum.Either<org.sireum.cli.CliOpt$Group, org.sireum.Json$ErrorMsg> toCliOptGroup(java.lang.String);
    descriptor: (Ljava/lang/String;)Lorg/sireum/Either;
    flags: (0x0009) ACC_PUBLIC, ACC_STATIC
    Code:
      stack=2, locals=1, args_size=1
         0: getstatic     #73                 // Field org/sireum/cli/JSON$.MODULE$:Lorg/sireum/cli/JSON$;
         3: aload_0
         4: invokevirtual #178                // Method org/sireum/cli/JSON$.toCliOptGroup:(Ljava/lang/String;)Lorg/sireum/Either;
         7: areturn
      LocalVariableTable:
        Start  Length  Slot  Name   Signature
            0       8     0     s   Ljava/lang/String;
    Signature: #176                         // (Ljava/lang/String;)Lorg/sireum/Either<Lorg/sireum/cli/CliOpt$Group;Lorg/sireum/Json$ErrorMsg;>;
    MethodParameters:
      Name                           Flags
      s                              final

  public static java.lang.String fromCliOptGroup(org.sireum.cli.CliOpt$Group, boolean);
    descriptor: (Lorg/sireum/cli/CliOpt$Group;Z)Ljava/lang/String;
    flags: (0x0009) ACC_PUBLIC, ACC_STATIC
    Code:
      stack=3, locals=2, args_size=2
         0: getstatic     #73                 // Field org/sireum/cli/JSON$.MODULE$:Lorg/sireum/cli/JSON$;
         3: aload_0
         4: iload_1
         5: invokevirtual #182                // Method org/sireum/cli/JSON$.fromCliOptGroup:(Lorg/sireum/cli/CliOpt$Group;Z)Ljava/lang/String;
         8: areturn
      LocalVariableTable:
        Start  Length  Slot  Name   Signature
            0       9     0     o   Lorg/sireum/cli/CliOpt$Group;
            0       9     1 isCompact   Z
    MethodParameters:
      Name                           Flags
      o                              final
      isCompact                      final

  public static org.sireum.Either<org.sireum.cli.CliOpt, org.sireum.Json$ErrorMsg> toCliOpt(java.lang.String);
    descriptor: (Ljava/lang/String;)Lorg/sireum/Either;
    flags: (0x0009) ACC_PUBLIC, ACC_STATIC
    Code:
      stack=2, locals=1, args_size=1
         0: getstatic     #73                 // Field org/sireum/cli/JSON$.MODULE$:Lorg/sireum/cli/JSON$;
         3: aload_0
         4: invokevirtual #187                // Method org/sireum/cli/JSON$.toCliOpt:(Ljava/lang/String;)Lorg/sireum/Either;
         7: areturn
      LocalVariableTable:
        Start  Length  Slot  Name   Signature
            0       8     0     s   Ljava/lang/String;
    Signature: #185                         // (Ljava/lang/String;)Lorg/sireum/Either<Lorg/sireum/cli/CliOpt;Lorg/sireum/Json$ErrorMsg;>;
    MethodParameters:
      Name                           Flags
      s                              final

  public static java.lang.String fromCliOpt(org.sireum.cli.CliOpt, boolean);
    descriptor: (Lorg/sireum/cli/CliOpt;Z)Ljava/lang/String;
    flags: (0x0009) ACC_PUBLIC, ACC_STATIC
    Code:
      stack=3, locals=2, args_size=2
         0: getstatic     #73                 // Field org/sireum/cli/JSON$.MODULE$:Lorg/sireum/cli/JSON$;
         3: aload_0
         4: iload_1
         5: invokevirtual #191                // Method org/sireum/cli/JSON$.fromCliOpt:(Lorg/sireum/cli/CliOpt;Z)Ljava/lang/String;
         8: areturn
      LocalVariableTable:
        Start  Length  Slot  Name   Signature
            0       9     0     o   Lorg/sireum/cli/CliOpt;
            0       9     1 isCompact   Z
    MethodParameters:
      Name                           Flags
      o                              final
      isCompact                      final

  public static <T extends java.lang.Object> org.sireum.Either<T, org.sireum.Json$ErrorMsg> to(java.lang.String, scala.Function1<org.sireum.cli.JSON$Parser, T>);
    descriptor: (Ljava/lang/String;Lscala/Function1;)Lorg/sireum/Either;
    flags: (0x0009) ACC_PUBLIC, ACC_STATIC
    Code:
      stack=3, locals=2, args_size=2
         0: getstatic     #73                 // Field org/sireum/cli/JSON$.MODULE$:Lorg/sireum/cli/JSON$;
         3: aload_0
         4: aload_1
         5: invokevirtual #198                // Method org/sireum/cli/JSON$.to:(Ljava/lang/String;Lscala/Function1;)Lorg/sireum/Either;
         8: areturn
      LocalVariableTable:
        Start  Length  Slot  Name   Signature
            0       9     0     s   Ljava/lang/String;
            0       9     1     f   Lscala/Function1;
    Signature: #195                         // <T:Ljava/lang/Object;>(Ljava/lang/String;Lscala/Function1<Lorg/sireum/cli/JSON$Parser;TT;>;)Lorg/sireum/Either<TT;Lorg/sireum/Json$ErrorMsg;>;
    MethodParameters:
      Name                           Flags
      s                              final
      f                              final
}
InnerClasses:
  public static final #13= #10 of #12;    // ErrorMsg=class org/sireum/Json$ErrorMsg of class org/sireum/Json
  public static final #18= #15 of #17;    // Group=class org/sireum/cli/CliOpt$Group of class org/sireum/cli/CliOpt
  public static final #21= #20 of #17;    // Opt=class org/sireum/cli/CliOpt$Opt of class org/sireum/cli/CliOpt
  public static final #24= #23 of #17;    // OptGroup=class org/sireum/cli/CliOpt$OptGroup of class org/sireum/cli/CliOpt
  public static final #27= #26 of #17;    // Tool=class org/sireum/cli/CliOpt$Tool of class org/sireum/cli/CliOpt
  public static #30= #29 of #17;          // Type=class org/sireum/cli/CliOpt$Type of class org/sireum/cli/CliOpt
  public static #33= #32 of #17;          // Type$=class org/sireum/cli/CliOpt$Type$ of class org/sireum/cli/CliOpt
  public static final #36= #35 of #32;    // Choice=class org/sireum/cli/CliOpt$Type$Choice of class org/sireum/cli/CliOpt$Type$
  public static final #39= #38 of #32;    // Flag=class org/sireum/cli/CliOpt$Type$Flag of class org/sireum/cli/CliOpt$Type$
  public static final #42= #41 of #32;    // Num=class org/sireum/cli/CliOpt$Type$Num of class org/sireum/cli/CliOpt$Type$
  public static final #45= #44 of #32;    // NumChoice=class org/sireum/cli/CliOpt$Type$NumChoice of class org/sireum/cli/CliOpt$Type$
  public static final #48= #47 of #32;    // NumFlag=class org/sireum/cli/CliOpt$Type$NumFlag of class org/sireum/cli/CliOpt$Type$
  public static final #51= #50 of #32;    // Path=class org/sireum/cli/CliOpt$Type$Path of class org/sireum/cli/CliOpt$Type$
  public static final #54= #53 of #32;    // Str=class org/sireum/cli/CliOpt$Type$Str of class org/sireum/cli/CliOpt$Type$
  public static final #57= #56 of #2;     // Parser=class org/sireum/cli/JSON$Parser of class org/sireum/cli/JSON
  public static #60= #59 of #2;           // Parser$=class org/sireum/cli/JSON$Parser$ of class org/sireum/cli/JSON
  public static #63= #62 of #2;           // Printer$=class org/sireum/cli/JSON$Printer$ of class org/sireum/cli/JSON
SourceFile: "JSON.scala"
RuntimeVisibleAnnotations:
  0: #6(#7=s#8)
    scala.reflect.ScalaSignature(
      bytes="\u0006\u0005\u0011eq!B/_\u0011\u0003)g!B4_\u0011\u0003A\u0007\"B8\u0002\t\u0003\u0001x!B9\u0002\u0011\u0003\u0011h!\u0002;\u0002\u0011\u0003)\b\"B8\u0005\t\u00031\b\"B<\u0005\t\u0003A\bbBA\u0007\t\u0011\u0005\u0011q\u0002\u0005\b\u0003G!A\u0011AA\u0013\u0011\u001d\t\t\u0004\u0002C\u0001\u0003gAq!a\u0010\u0005\t\u0003\t\t\u0005C\u0004\u0002N\u0011!\t!a\u0014\t\u000f\u0005mC\u0001\"\u0001\u0002^!9\u0011\u0011\u000f\u0003\u0005\u0002\u0005M\u0004bBA@\t\u0011\u0005\u0011\u0011\u0011\u0005\b\u0003\u001b#A\u0011AAH\u0011\u001d\tY\n\u0002C\u0001\u0003;Cq!!+\u0005\t\u0003\tY\u000bC\u0004\u00028\u0012!\t!!/\b\u000f\u0005\u0015\u0017\u0001#\u0001\u0002H\u001a9\u0011\u0011Z\u0001\t\u0002\u0005-\u0007BB8\u0015\t\u0003\ti\rC\u0004\u0002PR!\t!!5\t\u000f\rEA\u0003\"\u0001\u0004\u0014\u00191\u0011\u0011Z\u0001\u0003\u0003+D!\"!8\u0019\u0005\u0003\u0005\u000b\u0011BAp\u0011\u0019y\u0007\u0004\"\u0001\u0002f\"A\u0011\u0011\u001e\r!B\u0013\ty\u000eC\u0004\u0002lb!\t!!<\t\u000f\u0005=\b\u0004\"\u0001\u0002n\"9\u0011\u0011\u001f\r\u0005B\u0005M\bb\u0002B\u00021\u0011\u0005\u0013Q\u001e\u0005\b\u0005\u000bAB\u0011\tB\u0004\u0011\u001d\u0011y\u0001\u0007C!\u0005#Aq!a4\u0019\t\u0003\u0011\t\u0003C\u0005\u0003&a\t\n\u0011\"\u0001\u0003(!9!Q\b\r\u0005B\t}\u0002b\u0002B01\u0011\u0005#\u0011\r\u0005\n\u0005GB\"\u0019!C\u0001\u0005KB\u0001Ba\u001d\u0019A\u0003%!q\r\u0005\b\u0005kBB\u0011\u0001B<\u0011\u001d\u0011)\t\u0007C\u0001\u0005\u000fCqA!#\u0019\t\u0003\u0011Y\tC\u0004\u0003\u000eb!\tAa$\t\u000f\tm\u0005\u0004\"\u0001\u0003\u001e\"9!q\u0014\r\u0005\u0002\t\u0005\u0006b\u0002BS1\u0011\u0005!q\u0015\u0005\b\u0005SCB\u0011\u0001BV\u0011\u001d\u0011y\u000b\u0007C\u0001\u0005cCqAa-\u0019\t\u0003\u0011)\fC\u0004\u0003:b!\tAa/\t\u000f\tu\u0006\u0004\"\u0001\u0003@\"9!\u0011\u0019\r\u0005\u0002\t\r\u0007b\u0002Bd1\u0011\u0005!\u0011\u001a\u0005\b\u0005\u0017DB\u0011\u0001Bg\u0011\u001d\u0011\t\u000e\u0007C\u0001\u0005\'DqA!6\u0019\t\u0003\u00119\u000eC\u0004\u0003\\b!\tA!8\t\u000f\t}\u0007\u0004\"\u0001\u0003b\"9!Q\u001d\r\u0005\u0002\t\u001d\bb\u0002Bu1\u0011\u0005!1\u001e\u0005\b\u0005_DB\u0011\u0001By\u0011\u001d\u0011\u0019\u0010\u0007C\u0001\u0005kDqA!?\u0019\t\u0003\u0011Y\u0010C\u0004\u0003~b!\tAa@\t\u000f\r\r\u0001\u0004\"\u0001\u0004\u0006!91QD\u0001\u0005\u0002\r}\u0001bBB$\u0003\u0011\u00051\u0011\n\u0005\b\u0007#\nA\u0011AB*\u0011\u001d\u0019I&\u0001C\u0001\u00077Bqa!\u0019\u0002\t\u0003\u0019\u0019\u0007C\u0004\u0004j\u0005!\taa\u001b\t\u000f\rE\u0014\u0001\"\u0001\u0004t!91\u0011P\u0001\u0005\u0002\rm\u0004bBBA\u0003\u0011\u000511\u0011\u0005\b\u0007\u0013\u000bA\u0011ABF\u0011\u001d\u0019\t*\u0001C\u0001\u0007\'Cqa!\'\u0002\t\u0003\u0019Y\nC\u0004\u0004\"\u0006!\taa)\t\u000f\r%\u0016\u0001\"\u0001\u0004,\"91\u0011W\u0001\u0005\u0002\rM\u0006bBB]\u0003\u0011\u000511\u0018\u0005\b\u0007\u0003\fA\u0011ABb\u0011\u001d\u0019I-\u0001C\u0001\u0007\u0017Dqa!5\u0002\t\u0003\u0019\u0019\u000eC\u0004\u0004Z\u0006!\taa7\t\u000f\r\u0005\u0018\u0001\"\u0001\u0004d\"91\u0011^\u0001\u0005\u0002\r-\bbBBy\u0003\u0011\u000511\u001f\u0005\b\u0007s\fA\u0011AB~\u0011\u001d!\t!\u0001C\u0001\t\u0007Aq\u0001\"\u0003\u0002\t\u0003!Y\u0001C\u0004\u0005\u0012\u0005!\t\u0001b\u0005\u0002\t)\u001bvJ\u0014\u0006\u0003?\u0002\f1a\u00197j\u0015\t\t\'-\u0001\u0004tSJ,W/\u001c\u0006\u0002G\u0006\u0019qN]4\u0004\u0001A\u0011a-A\u0007\u0002=\n!!jU(O\'\t\t\u0011\u000e\u0005\u0002k[6\t1NC\u0001m\u0003\u0015\u00198-\u00197b\u0013\tq7N\u0001\u0004B]f\u0014VMZ\u0001\u0007y%t\u0017\u000e\u001e \u0015\u0003\u0015\fq\u0001\u0015:j]R,\'\u000f\u0005\u0002t\t5\t\u0011AA\u0004Qe&tG/\u001a:\u0014\u0005\u0011IG#\u0001:\u0002\u0017A\u0014\u0018N\u001c;DY&|\u0005\u000f\u001e\u000b\u0003sv\u0004\"A_>\u000e\u0003\u0001L!\u0001 1\u0003\u0005M#\u0006\"\u0002@\u0007\u0001\u0004y\u0018!A8\u0011\u0007\u0019\f\t!C\u0002\u0002\u0004y\u0013aa\u00117j\u001fB$\bf\u0001\u0004\u0002\bA\u0019!0!\u0003\n\u0007\u0005-\u0001M\u0001\u0003qkJ,\u0017\u0001\u00059sS:$8\t\\5PaR<%o\\;q)\rI\u0018\u0011\u0003\u0005\u0007}\u001e\u0001\r!a\u0005\u0011\t\u0005U\u00111\u0004\b\u0004M\u0006]\u0011bAA\r=\u000611\t\\5PaRLA!!\b\u0002 \t)qI]8va*\u0019\u0011\u0011\u00040)\u0007\u001d\t9!A\bqe&tGo\u00117j\u001fB$Hk\\8m)\rI\u0018q\u0005\u0005\u0007}\"\u0001\r!!\u000b\u0011\t\u0005U\u00111F\u0005\u0005\u0003[\tyB\u0001\u0003U_>d\u0007f\u0001\u0005\u0002\b\u0005\u0019\u0002O]5oi\u000ec\u0017n\u00149u\u001fB$xI]8vaR\u0019\u00110!\u000e\t\ryL\u0001\u0019AA\u001c!\u0011\t)\"!\u000f\n\t\u0005m\u0012q\u0004\u0002\t\u001fB$xI]8va\"\u001a\u0011\"a\u0002\u0002\u001dA\u0014\u0018N\u001c;DY&|\u0005\u000f^(qiR\u0019\u00110a\u0011\t\ryT\u0001\u0019AA#!\u0011\t)\"a\u0012\n\t\u0005%\u0013q\u0004\u0002\u0004\u001fB$\bf\u0001\u0006\u0002\b\u0005y\u0001O]5oi\u000ec\u0017n\u00149u)f\u0004X\rF\u0002z\u0003#BaA`\u0006A\u0002\u0005M\u0003\u0003BA\u000b\u0003+JA!a\u0016\u0002 \t!A+\u001f9fQ\rY\u0011qA\u0001\u0014aJLg\u000e^\"mS>\u0003H\u000fV=qK\u001ac\u0017m\u001a\u000b\u0004s\u0006}\u0003B\u0002@\r\u0001\u0004\t\t\u0007\u0005\u0003\u0002d\u0005%d\u0002BA\u000b\u0003KJA!a\u001a\u0002 \u0005!A+\u001f9f\u0013\u0011\tY\'!\u001c\u0003\t\u0019c\u0017m\u001a\u0006\u0005\u0003O\ny\u0002K\u0002\r\u0003\u000f\t!\u0003\u001d:j]R\u001cE.[(qiRK\b/\u001a(v[R\u0019\u00110!\u001e\t\ryl\u0001\u0019AA<!\u0011\t\u0019\'!\u001f\n\t\u0005m\u0014Q\u000e\u0002\u0004\u001dVl\u0007fA\u0007\u0002\b\u00051\u0002O]5oi\u000ec\u0017n\u00149u)f\u0004XMT;n\r2\fw\rF\u0002z\u0003\u0007CaA \bA\u0002\u0005\u0015\u0005\u0003BA2\u0003\u000fKA!!#\u0002n\t9a*^7GY\u0006<\u0007f\u0001\b\u0002\b\u0005A\u0002O]5oi\u000ec\u0017n\u00149u)f\u0004XMT;n\u0007\"|\u0017nY3\u0015\u0007e\f\t\n\u0003\u0004\u007f\u001f\u0001\u0007\u00111\u0013\t\u0005\u0003G\n)*\u0003\u0003\u0002\u0018\u00065$!\u0003(v[\u000eCw.[2fQ\ry\u0011qA\u0001\u0013aJLg\u000e^\"mS>\u0003H\u000fV=qKN#(\u000fF\u0002z\u0003?CaA \tA\u0002\u0005\u0005\u0006\u0003BA2\u0003GKA!!*\u0002n\t\u00191\u000b\u001e:)\u0007A\t9!A\u000bqe&tGo\u00117j\u001fB$H+\u001f9f\u0007\"|\u0017nY3\u0015\u0007e\fi\u000b\u0003\u0004\u007f#\u0001\u0007\u0011q\u0016\t\u0005\u0003G\n\t,\u0003\u0003\u00024\u00065$AB\"i_&\u001cW\rK\u0002\u0012\u0003\u000f\t1\u0003\u001d:j]R\u001cE.[(qiRK\b/\u001a)bi\"$2!_A^\u0011\u0019q(\u00031\u0001\u0002>B!\u00111MA`\u0013\u0011\t\t-!\u001c\u0003\tA\u000bG\u000f\u001b\u0015\u0004%\u0005\u001d\u0011A\u0002)beN,\'\u000f\u0005\u0002t)\t1\u0001+\u0019:tKJ\u001c\"\u0001F5\u0015\u0005\u0005\u001d\u0017!B1qa2LH\u0003BAj\u0007\u001f\u0001\"a\u001d\r\u0014\taI\u0017q\u001b\t\u0004u\u0006e\u0017bAAnA\nI!+Z2pe\u0012\u001c\u0016nZ\u0001\b?~Kg\u000e];u!\rQ\u0018\u0011]\u0005\u0004\u0003G\u0004\'AB*ue&tw\r\u0006\u0003\u0002T\u0006\u001d\bbBAo5\u0001\u0007\u0011q\\\u0001\u0007?&t\u0007/\u001e;\u0002\u000b%t\u0007/\u001e;\u0016\u0005\u0005}\u0017\u0001C4fi&s\u0007/\u001e;\u0002\u0011Q|7\u000b\u001e:j]\u001e$\"!!>\u0011\t\u0005](\u0011A\u0007\u0003\u0003sTA!a?\u0002~\u0006!A.\u00198h\u0015\t\ty0\u0001\u0003kCZ\f\u0017\u0002BAr\u0003s\faa\u001d;sS:<\u0017\u0001\u00035bg\"\u001cu\u000eZ3\u0015\u0005\t%\u0001c\u00016\u0003\f%\u0019!QB6\u0003\u0007%sG/\u0001\u0004fcV\fGn\u001d\u000b\u0005\u0005\'\u0011I\u0002E\u0002k\u0005+I1Aa\u0006l\u0005\u001d\u0011un\u001c7fC:DaA`\u0011A\u0002\tm\u0001c\u00016\u0003\u001e%\u0019!qD6\u0003\u0007\u0005s\u0017\u0010\u0006\u0003\u0002T\n\r\u0002\"CAvEA\u0005\t\u0019AAp\u0003=\t\u0007\u000f\u001d7zI\u0011,g-Y;mi\u0012\nTC\u0001B\u0015U\u0011\tyNa\u000b,\u0005\t5\u0002\u0003\u0002B\u0018\u0005si!A!\r\u000b\t\tM\"QG\u0001\nk:\u001c\u0007.Z2lK\u0012T1Aa\u000el\u0003)\tgN\\8uCRLwN\\\u0005\u0005\u0005w\u0011\tDA\tv]\u000eDWmY6fIZ\u000b\'/[1oG\u0016\f\u0001\u0002J2p]R,g\u000e^\u000b\u0003\u0005\u0003\u0002bAa\u0011\u0003T\tec\u0002\u0002B#\u0005\u001frAAa\u0012\u0003N5\u0011!\u0011\n\u0006\u0004\u0005\u0017\"\u0017A\u0002\u001fs_>$h(C\u0001m\u0013\r\u0011\tf[\u0001\ba\u0006\u001c7.Y4f\u0013\u0011\u0011)Fa\u0016\u0003\u0007M+\u0017OC\u0002\u0003R-\u0004rA\u001bB.\u0003k\u0014Y\"C\u0002\u0003^-\u0014a\u0001V;qY\u0016\u0014\u0014A\u0002\u0013dY>tW-\u0006\u0002\u0002T\u00061\u0001/\u0019:tKJ,\"Aa\u001a\u0011\t\t%$q\u000e\b\u0004u\n-\u0014b\u0001B7A\u0006!!j]8o\u0013\u0011\tIM!\u001d\u000b\u0007\t5\u0004-A\u0004qCJ\u001cXM\u001d\u0011\u0002\u0011\u0015\u0014(o\u001c:PaR,\"A!\u001f\u0011\u000bi\u0014YHa \n\u0007\tu\u0004M\u0001\u0004PaRLwN\u001c\t\u0005\u0005S\u0012\t)\u0003\u0003\u0003\u0004\nE$\u0001C#se>\u0014Xj]4\u0002\u0017A\f\'o]3DY&|\u0005\u000f\u001e\u000b\u0002\u007f\u0006\u0001\u0002/\u0019:tK\u000ec\u0017n\u00149u\u000fJ|W\u000f\u001d\u000b\u0003\u0003\'\t\u0011\u0003]1sg\u0016\u001cE.[(qi\u001e\u0013x.\u001e9U)\u0011\t\u0019B!%\t\u000f\tM5\u00061\u0001\u0003\u0016\u0006QA/\u001f9f!\u0006\u00148/\u001a3\u0011\u0007i\u00149*C\u0002\u0003\u001a\u0002\u0014\u0011AQ\u0001\u0010a\u0006\u00148/Z\"mS>\u0003H\u000fV8pYR\u0011\u0011\u0011F\u0001\u0011a\u0006\u00148/Z\"mS>\u0003H\u000fV8pYR#B!!\u000b\u0003$\"9!1S\u0017A\u0002\tU\u0015a\u00059beN,7\t\\5PaR|\u0005\u000f^$s_V\u0004HCAA\u001c\u0003Q\u0001\u0018M]:f\u00072Lw\n\u001d;PaR<%o\\;q)R!\u0011q\u0007BW\u0011\u001d\u0011\u0019j\fa\u0001\u0005+\u000ba\u0002]1sg\u0016\u001cE.[(qi>\u0003H\u000f\u0006\u0002\u0002F\u0005y\u0001/\u0019:tK\u000ec\u0017n\u00149u\u001fB$H\u000b\u0006\u0003\u0002F\t]\u0006b\u0002BJc\u0001\u0007!QS\u0001\u0010a\u0006\u00148/Z\"mS>\u0003H\u000fV=qKR\u0011\u00111K\u0001\u0014a\u0006\u00148/Z\"mS>\u0003H\u000fV=qK\u001ac\u0017m\u001a\u000b\u0003\u0003C\nA\u0003]1sg\u0016\u001cE.[(qiRK\b/\u001a$mC\u001e$F\u0003BA1\u0005\u000bDqAa%5\u0001\u0004\u0011)*\u0001\nqCJ\u001cXm\u00117j\u001fB$H+\u001f9f\u001dVlGCAA<\u0003M\u0001\u0018M]:f\u00072Lw\n\u001d;UsB,g*^7U)\u0011\t9Ha4\t\u000f\tMe\u00071\u0001\u0003\u0016\u00061\u0002/\u0019:tK\u000ec\u0017n\u00149u)f\u0004XMT;n\r2\fw\r\u0006\u0002\u0002\u0006\u00069\u0002/\u0019:tK\u000ec\u0017n\u00149u)f\u0004XMT;n\r2\fw\r\u0016\u000b\u0005\u0003\u000b\u0013I\u000eC\u0004\u0003\u0014b\u0002\rA!&\u00021A\f\'o]3DY&|\u0005\u000f\u001e+za\u0016tU/\\\"i_&\u001cW\r\u0006\u0002\u0002\u0014\u0006I\u0002/\u0019:tK\u000ec\u0017n\u00149u)f\u0004XMT;n\u0007\"|\u0017nY3U)\u0011\t\u0019Ja9\t\u000f\tM%\b1\u0001\u0003\u0016\u0006\u0011\u0002/\u0019:tK\u000ec\u0017n\u00149u)f\u0004Xm\u0015;s)\t\t\t+A\nqCJ\u001cXm\u00117j\u001fB$H+\u001f9f\'R\u0014H\u000b\u0006\u0003\u0002\"\n5\bb\u0002BJy\u0001\u0007!QS\u0001\u0016a\u0006\u00148/Z\"mS>\u0003H\u000fV=qK\u000eCw.[2f)\t\ty+\u0001\fqCJ\u001cXm\u00117j\u001fB$H+\u001f9f\u0007\"|\u0017nY3U)\u0011\tyKa>\t\u000f\tMe\b1\u0001\u0003\u0016\u0006\u0019\u0002/\u0019:tK\u000ec\u0017n\u00149u)f\u0004X\rU1uQR\u0011\u0011QX\u0001\u0015a\u0006\u00148/Z\"mS>\u0003H\u000fV=qKB\u000bG\u000f\u001b+\u0015\t\u0005u6\u0011\u0001\u0005\b\u0005\'\u0003\u0005\u0019\u0001BK\u0003\r)wN\u001a\u000b\u0003\u0005+C3\u0001GB\u0005!\rQ81B\u0005\u0004\u0007\u001b\u0001\'A\u0002:fG>\u0014H\rC\u0004\u0002lZ\u0001\r!a8\u0002\u000fUt\u0017\r\u001d9msR!1QCB\u000e!\u0015Q7qCAp\u0013\r\u0019Ib\u001b\u0002\u0005\'>lW\r\u0003\u0004\u007f/\u0001\u0007\u00111[\u0001\u0003i>,Ba!\t\u0004.Q111EB\u001d\u0007{\u0001rA_B\u0013\u0007S\u0011y(C\u0002\u0004(\u0001\u0014a!R5uQ\u0016\u0014\b\u0003BB\u0016\u0007[a\u0001\u0001B\u0004\u00040\t\u0013\ra!\r\u0003\u0003Q\u000bBaa\r\u0003\u001cA\u0019!n!\u000e\n\u0007\r]2NA\u0004O_RD\u0017N\\4\t\u000f\rm\"\t1\u0001\u0002`\u0006\t1\u000fC\u0004\u0004@\t\u0003\ra!\u0011\u0002\u0003\u0019\u0004rA[B\"\u0003\'\u001cI#C\u0002\u0004F-\u0014\u0011BR;oGRLwN\\\u0019\u0002\u0015\u0019\u0014x.\\\"mS>\u0003H\u000f\u0006\u0004\u0002`\u000e-3Q\n\u0005\u0006}\u000e\u0003\ra \u0005\b\u0007\u001f\u001a\u0005\u0019\u0001BK\u0003%I7oQ8na\u0006\u001cG/\u0001\u0005u_\u000ec\u0017n\u00149u)\u0011\u0019)fa\u0016\u0011\ri\u001c)c B@\u0011\u001d\u0019Y\u0004\u0012a\u0001\u0003?\fqB\u001a:p[\u000ec\u0017n\u00149u\u000fJ|W\u000f\u001d\u000b\u0007\u0003?\u001cifa\u0018\t\ry,\u0005\u0019AA\n\u0011\u001d\u0019y%\u0012a\u0001\u0005+\u000bQ\u0002^8DY&|\u0005\u000f^$s_V\u0004H\u0003BB3\u0007O\u0002rA_B\u0013\u0003\'\u0011y\bC\u0004\u0004<\u0019\u0003\r!a8\u0002\u001d\u0019\u0014x.\\\"mS>\u0003H\u000fV8pYR1\u0011q\\B7\u0007_BaA`$A\u0002\u0005%\u0002bBB(\u000f\u0002\u0007!QS\u0001\ri>\u001cE.[(qiR{w\u000e\u001c\u000b\u0005\u0007k\u001a9\bE\u0004{\u0007K\tICa \t\u000f\rm\u0002\n1\u0001\u0002`\u0006\u0011bM]8n\u00072Lw\n\u001d;PaR<%o\\;q)\u0019\tyn! \u0004\u0000!1a0\u0013a\u0001\u0003oAqaa\u0014J\u0001\u0004\u0011)*\u0001\tu_\u000ec\u0017n\u00149u\u001fB$xI]8vaR!1QQBD!\u001dQ8QEA\u001c\u0005\u007fBqaa\u000fK\u0001\u0004\ty.A\u0007ge>l7\t\\5PaR|\u0005\u000f\u001e\u000b\u0007\u0003?\u001ciia$\t\ry\\\u0005\u0019AA#\u0011\u001d\u0019ye\u0013a\u0001\u0005+\u000b1\u0002^8DY&|\u0005\u000f^(qiR!1QSBL!\u001dQ8QEA#\u0005\u007fBqaa\u000fM\u0001\u0004\ty.\u0001\bge>l7\t\\5PaR$\u0016\u0010]3\u0015\r\u0005}7QTBP\u0011\u0019qX\n1\u0001\u0002T!91qJ\'A\u0002\tU\u0015\u0001\u0004;p\u00072Lw\n\u001d;UsB,G\u0003BBS\u0007O\u0003rA_B\u0013\u0003\'\u0012y\bC\u0004\u0004<9\u0003\r!a8\u0002%\u0019\u0014x.\\\"mS>\u0003H\u000fV=qK\u001ac\u0017m\u001a\u000b\u0007\u0003?\u001cika,\t\ry|\u0005\u0019AA1\u0011\u001d\u0019ye\u0014a\u0001\u0005+\u000b\u0001\u0003^8DY&|\u0005\u000f\u001e+za\u00164E.Y4\u0015\t\rU6q\u0017\t\bu\u000e\u0015\u0012\u0011\rB@\u0011\u001d\u0019Y\u0004\u0015a\u0001\u0003?\f\u0011C\u001a:p[\u000ec\u0017n\u00149u)f\u0004XMT;n)\u0019\tyn!0\u0004@\"1a0\u0015a\u0001\u0003oBqaa\u0014R\u0001\u0004\u0011)*A\bu_\u000ec\u0017n\u00149u)f\u0004XMT;n)\u0011\u0019)ma2\u0011\u000fi\u001c)#a\u001e\u0003\u0000!911\b*A\u0002\u0005}\u0017!\u00064s_6\u001cE.[(qiRK\b/\u001a(v[\u001ac\u0017m\u001a\u000b\u0007\u0003?\u001cima4\t\ry\u001c\u0006\u0019AAC\u0011\u001d\u0019ye\u0015a\u0001\u0005+\u000b1\u0003^8DY&|\u0005\u000f\u001e+za\u0016tU/\u001c$mC\u001e$Ba!6\u0004XB9!p!\n\u0002\u0006\n}\u0004bBB\u001e)\u0002\u0007\u0011q\\\u0001\u0018MJ|Wn\u00117j\u001fB$H+\u001f9f\u001dVl7\t[8jG\u0016$b!a8\u0004^\u000e}\u0007B\u0002@V\u0001\u0004\t\u0019\nC\u0004\u0004PU\u0003\rA!&\u0002+Q|7\t\\5PaR$\u0016\u0010]3Ok6\u001c\u0005n\\5dKR!1Q]Bt!\u001dQ8QEAJ\u0005\u007fBqaa\u000fW\u0001\u0004\ty.A\tge>l7\t\\5PaR$\u0016\u0010]3TiJ$b!a8\u0004n\u000e=\bB\u0002@X\u0001\u0004\t\t\u000bC\u0004\u0004P]\u0003\rA!&\u0002\u001fQ|7\t\\5PaR$\u0016\u0010]3TiJ$Ba!>\u0004xB9!p!\n\u0002\"\n}\u0004bBB\u001e1\u0002\u0007\u0011q\\\u0001\u0015MJ|Wn\u00117j\u001fB$H+\u001f9f\u0007\"|\u0017nY3\u0015\r\u0005}7Q`B\u0000\u0011\u0019q\u0018\f1\u0001\u00020\"91qJ-A\u0002\tU\u0015A\u0005;p\u00072Lw\n\u001d;UsB,7\t[8jG\u0016$B\u0001\"\u0002\u0005\bA9!p!\n\u00020\n}\u0004bBB\u001e5\u0002\u0007\u0011q\\\u0001\u0013MJ|Wn\u00117j\u001fB$H+\u001f9f!\u0006$\b\u000e\u0006\u0004\u0002`\u00125Aq\u0002\u0005\u0007}n\u0003\r!!0\t\u000f\r=3\f1\u0001\u0003\u0016\u0006\u0001Bo\\\"mS>\u0003H\u000fV=qKB\u000bG\u000f\u001b\u000b\u0005\t+!9\u0002E\u0004{\u0007K\tiLa \t\u000f\rmB\f1\u0001\u0002`\u0002"
    )
  ScalaSig: length = 0x3 (unknown attribute)
   05 02 00
