Classfile /Users/mw/Projects/slang-braindump/.jar/jar8/assemble/slang-braindump/assemble/content/org/scalatest/time/Day.class
  Last modified May 29, 2022; size 2047 bytes
  SHA-256 checksum 3d3bdd8b39a25099488d04d4c0fa78835cc0176b660c89abe9cbc82d6dc054bd
  Compiled from "Units.scala"
public final class org.scalatest.time.Day
  minor version: 0
  major version: 52
  flags: (0x0031) ACC_PUBLIC, ACC_FINAL, ACC_SUPER
  this_class: #2                          // org/scalatest/time/Day
  super_class: #4                         // java/lang/Object
  interfaces: 0, fields: 0, methods: 9, attributes: 3
Constant pool:
   #1 = Utf8               org/scalatest/time/Day
   #2 = Class              #1             // org/scalatest/time/Day
   #3 = Utf8               java/lang/Object
   #4 = Class              #3             // java/lang/Object
   #5 = Utf8               Units.scala
   #6 = Utf8               Lscala/reflect/ScalaSignature;
   #7 = Utf8               bytes
   #8 = Utf8               \u0006\u0005-<Q!\u0004\b\t\u0002V1Qa\u0006\b\t\u0002bAQAL\u0001\u0005\u0002=Ba\u0001M\u0001\u0005\u0002A\t\u0004B\u0002\u001f\u0002\t\u0003\u0001R\bC\u0004@\u0003\u0005\u0005I\u0011\t!\t\u000f!\u000b\u0011\u0011!C\u0001\u0013\"9Q*AA\u0001\n\u0003q\u0005b\u0002+\u0002\u0003\u0003%\t%\u0016\u0005\b9\u0006\t\t\u0011\"\u0001^\u0011\u001d\u0011\u0017!!A\u0005B\rDq\u0001Z\u0001\u0002\u0002\u0013\u0005S\rC\u0004g\u0003\u0005\u0005I\u0011B4\u0002\u0007\u0011\u000b\u0017P\u0003\u0002\u0010!\u0005!A/[7f\u0015\t\t\"#A\u0005tG\u0006d\u0017\r^3ti*\t1#A\u0002pe\u001e\u001c\u0001\u0001\u0005\u0002\u0017\u00035\taBA\u0002ECf\u001cB!A\r\u001dEA\u0011aCG\u0005\u000379\u0011Q!\u00168jiN\u0004\"!\b\u0011\u000e\u0003yQ\u0011aH\u0001\u0006g\u000e\fG.Y\u0005\u0003Cy\u0011q\u0001\u0015:pIV\u001cG\u000f\u0005\u0002$W9\u0011A%\u000b\b\u0003K!j\u0011A\n\u0006\u0003OQ\ta\u0001\u0010:p_Rt\u0014\"A\u0010\n\u0005)r\u0012a\u00029bG.\fw-Z\u0005\u0003Y5\u0012AbU3sS\u0006d\u0017N_1cY\u0016T!A\u000b\u0010\u0002\rqJg.\u001b;?)\u0005)\u0012AE:j]\u001e,H.\u0019:NKN\u001c\u0018mZ3Gk:$\"A\r\u001e\u0011\u0005M:dB\u0001\u001b6!\t)c$\u0003\u00027=\u00051\u0001K]3eK\u001aL!\u0001O\u001d\u0003\rM#(/\u001b8h\u0015\t1d\u0004C\u0003<\u0007\u0001\u0007!\'\u0001\u0007mK:<G\u000f[*ue&tw-\u0001\tqYV\u0014\u0018\r\\\'fgN\fw-\u001a$v]R\u0011!G\u0010\u0005\u0006w\u0011\u0001\rAM\u0001\u000eaJ|G-^2u!J,g-\u001b=\u0016\u0003\u0005\u0003\"AQ$\u000e\u0003\rS!\u0001R#\u0002\t1\fgn\u001a\u0006\u0002\r\u0006!!.\u0019<b\u0013\tA4)\u0001\u0007qe>$Wo\u0019;Be&$\u00180F\u0001K!\ti2*\u0003\u0002M=\t\u0019\u0011J\u001c;\u0002\u001dA\u0014x\u000eZ;di\u0016cW-\\3oiR\u0011qJ\u0015\t\u0003;AK!!\u0015\u0010\u0003\u0007\u0005s\u0017\u0010C\u0004T\u000f\u0005\u0005\t\u0019\u0001&\u0002\u0007a$\u0013\'A\bqe>$Wo\u0019;Ji\u0016\u0014\u0018\r^8s+\u00051\u0006cA,[\u001f6\t\u0001L\u0003\u0002Z=\u0005Q1m\u001c7mK\u000e$\u0018n\u001c8\n\u0005mC&\u0001C%uKJ\fGo\u001c:\u0002\u0011\r\fg.R9vC2$\"AX1\u0011\u0005uy\u0016B\u00011\u001f\u0005\u001d\u0011un\u001c7fC:DqaU\u0005\u0002\u0002\u0003\u0007q*\u0001\u0005iCND7i\u001c3f)\u0005Q\u0015\u0001\u0003;p\'R\u0014\u0018N\\4\u0015\u0003\u0005\u000bAb\u001e:ji\u0016\u0014V\r\u001d7bG\u0016$\u0012\u0001\u001b\t\u0003\u0005&L!A[\"\u0003\r=\u0013\'.Z2u\u0001
   #9 = Utf8               toString
  #10 = Utf8               ()Ljava/lang/String;
  #11 = Utf8               org/scalatest/time/Day$
  #12 = Class              #11            // org/scalatest/time/Day$
  #13 = Utf8               MODULE$
  #14 = Utf8               Lorg/scalatest/time/Day$;
  #15 = NameAndType        #13:#14        // MODULE$:Lorg/scalatest/time/Day$;
  #16 = Fieldref           #12.#15        // org/scalatest/time/Day$.MODULE$:Lorg/scalatest/time/Day$;
  #17 = NameAndType        #9:#10         // toString:()Ljava/lang/String;
  #18 = Methodref          #12.#17        // org/scalatest/time/Day$.toString:()Ljava/lang/String;
  #19 = Utf8               hashCode
  #20 = Utf8               ()I
  #21 = NameAndType        #19:#20        // hashCode:()I
  #22 = Methodref          #12.#21        // org/scalatest/time/Day$.hashCode:()I
  #23 = Utf8               canEqual
  #24 = Utf8               (Ljava/lang/Object;)Z
  #25 = Utf8               x$1
  #26 = NameAndType        #23:#24        // canEqual:(Ljava/lang/Object;)Z
  #27 = Methodref          #12.#26        // org/scalatest/time/Day$.canEqual:(Ljava/lang/Object;)Z
  #28 = Utf8               Ljava/lang/Object;
  #29 = Utf8               productIterator
  #30 = Utf8               ()Lscala/collection/Iterator;
  #31 = Utf8               ()Lscala/collection/Iterator<Ljava/lang/Object;>;
  #32 = NameAndType        #29:#30        // productIterator:()Lscala/collection/Iterator;
  #33 = Methodref          #12.#32        // org/scalatest/time/Day$.productIterator:()Lscala/collection/Iterator;
  #34 = Utf8               productElement
  #35 = Utf8               (I)Ljava/lang/Object;
  #36 = NameAndType        #34:#35        // productElement:(I)Ljava/lang/Object;
  #37 = Methodref          #12.#36        // org/scalatest/time/Day$.productElement:(I)Ljava/lang/Object;
  #38 = Utf8               I
  #39 = Utf8               productArity
  #40 = NameAndType        #39:#20        // productArity:()I
  #41 = Methodref          #12.#40        // org/scalatest/time/Day$.productArity:()I
  #42 = Utf8               productPrefix
  #43 = NameAndType        #42:#10        // productPrefix:()Ljava/lang/String;
  #44 = Methodref          #12.#43        // org/scalatest/time/Day$.productPrefix:()Ljava/lang/String;
  #45 = Utf8               productElementNames
  #46 = Utf8               ()Lscala/collection/Iterator<Ljava/lang/String;>;
  #47 = NameAndType        #45:#30        // productElementNames:()Lscala/collection/Iterator;
  #48 = Methodref          #12.#47        // org/scalatest/time/Day$.productElementNames:()Lscala/collection/Iterator;
  #49 = Utf8               productElementName
  #50 = Utf8               (I)Ljava/lang/String;
  #51 = Utf8               n
  #52 = NameAndType        #49:#50        // productElementName:(I)Ljava/lang/String;
  #53 = Methodref          #12.#52        // org/scalatest/time/Day$.productElementName:(I)Ljava/lang/String;
  #54 = Utf8               Code
  #55 = Utf8               LocalVariableTable
  #56 = Utf8               MethodParameters
  #57 = Utf8               Signature
  #58 = Utf8               SourceFile
  #59 = Utf8               RuntimeVisibleAnnotations
  #60 = Utf8               ScalaSig
{
  public static java.lang.String toString();
    descriptor: ()Ljava/lang/String;
    flags: (0x0009) ACC_PUBLIC, ACC_STATIC
    Code:
      stack=1, locals=0, args_size=0
         0: getstatic     #16                 // Field org/scalatest/time/Day$.MODULE$:Lorg/scalatest/time/Day$;
         3: invokevirtual #18                 // Method org/scalatest/time/Day$.toString:()Ljava/lang/String;
         6: areturn

  public static int hashCode();
    descriptor: ()I
    flags: (0x0009) ACC_PUBLIC, ACC_STATIC
    Code:
      stack=1, locals=0, args_size=0
         0: getstatic     #16                 // Field org/scalatest/time/Day$.MODULE$:Lorg/scalatest/time/Day$;
         3: invokevirtual #22                 // Method org/scalatest/time/Day$.hashCode:()I
         6: ireturn

  public static boolean canEqual(java.lang.Object);
    descriptor: (Ljava/lang/Object;)Z
    flags: (0x0009) ACC_PUBLIC, ACC_STATIC
    Code:
      stack=2, locals=1, args_size=1
         0: getstatic     #16                 // Field org/scalatest/time/Day$.MODULE$:Lorg/scalatest/time/Day$;
         3: aload_0
         4: invokevirtual #27                 // Method org/scalatest/time/Day$.canEqual:(Ljava/lang/Object;)Z
         7: ireturn
      LocalVariableTable:
        Start  Length  Slot  Name   Signature
            0       8     0   x$1   Ljava/lang/Object;
    MethodParameters:
      Name                           Flags
      x$1                            final

  public static scala.collection.Iterator<java.lang.Object> productIterator();
    descriptor: ()Lscala/collection/Iterator;
    flags: (0x0009) ACC_PUBLIC, ACC_STATIC
    Code:
      stack=1, locals=0, args_size=0
         0: getstatic     #16                 // Field org/scalatest/time/Day$.MODULE$:Lorg/scalatest/time/Day$;
         3: invokevirtual #33                 // Method org/scalatest/time/Day$.productIterator:()Lscala/collection/Iterator;
         6: areturn
    Signature: #31                          // ()Lscala/collection/Iterator<Ljava/lang/Object;>;

  public static java.lang.Object productElement(int);
    descriptor: (I)Ljava/lang/Object;
    flags: (0x0009) ACC_PUBLIC, ACC_STATIC
    Code:
      stack=2, locals=1, args_size=1
         0: getstatic     #16                 // Field org/scalatest/time/Day$.MODULE$:Lorg/scalatest/time/Day$;
         3: iload_0
         4: invokevirtual #37                 // Method org/scalatest/time/Day$.productElement:(I)Ljava/lang/Object;
         7: areturn
      LocalVariableTable:
        Start  Length  Slot  Name   Signature
            0       8     0   x$1   I
    MethodParameters:
      Name                           Flags
      x$1                            final

  public static int productArity();
    descriptor: ()I
    flags: (0x0009) ACC_PUBLIC, ACC_STATIC
    Code:
      stack=1, locals=0, args_size=0
         0: getstatic     #16                 // Field org/scalatest/time/Day$.MODULE$:Lorg/scalatest/time/Day$;
         3: invokevirtual #41                 // Method org/scalatest/time/Day$.productArity:()I
         6: ireturn

  public static java.lang.String productPrefix();
    descriptor: ()Ljava/lang/String;
    flags: (0x0009) ACC_PUBLIC, ACC_STATIC
    Code:
      stack=1, locals=0, args_size=0
         0: getstatic     #16                 // Field org/scalatest/time/Day$.MODULE$:Lorg/scalatest/time/Day$;
         3: invokevirtual #44                 // Method org/scalatest/time/Day$.productPrefix:()Ljava/lang/String;
         6: areturn

  public static scala.collection.Iterator<java.lang.String> productElementNames();
    descriptor: ()Lscala/collection/Iterator;
    flags: (0x0009) ACC_PUBLIC, ACC_STATIC
    Code:
      stack=1, locals=0, args_size=0
         0: getstatic     #16                 // Field org/scalatest/time/Day$.MODULE$:Lorg/scalatest/time/Day$;
         3: invokevirtual #48                 // Method org/scalatest/time/Day$.productElementNames:()Lscala/collection/Iterator;
         6: areturn
    Signature: #46                          // ()Lscala/collection/Iterator<Ljava/lang/String;>;

  public static java.lang.String productElementName(int);
    descriptor: (I)Ljava/lang/String;
    flags: (0x0009) ACC_PUBLIC, ACC_STATIC
    Code:
      stack=2, locals=1, args_size=1
         0: getstatic     #16                 // Field org/scalatest/time/Day$.MODULE$:Lorg/scalatest/time/Day$;
         3: iload_0
         4: invokevirtual #53                 // Method org/scalatest/time/Day$.productElementName:(I)Ljava/lang/String;
         7: areturn
      LocalVariableTable:
        Start  Length  Slot  Name   Signature
            0       8     0     n   I
    MethodParameters:
      Name                           Flags
      n                              final
}
SourceFile: "Units.scala"
RuntimeVisibleAnnotations:
  0: #6(#7=s#8)
    scala.reflect.ScalaSignature(
      bytes="\u0006\u0005-<Q!\u0004\b\t\u0002V1Qa\u0006\b\t\u0002bAQAL\u0001\u0005\u0002=Ba\u0001M\u0001\u0005\u0002A\t\u0004B\u0002\u001f\u0002\t\u0003\u0001R\bC\u0004@\u0003\u0005\u0005I\u0011\t!\t\u000f!\u000b\u0011\u0011!C\u0001\u0013\"9Q*AA\u0001\n\u0003q\u0005b\u0002+\u0002\u0003\u0003%\t%\u0016\u0005\b9\u0006\t\t\u0011\"\u0001^\u0011\u001d\u0011\u0017!!A\u0005B\rDq\u0001Z\u0001\u0002\u0002\u0013\u0005S\rC\u0004g\u0003\u0005\u0005I\u0011B4\u0002\u0007\u0011\u000b\u0017P\u0003\u0002\u0010!\u0005!A/[7f\u0015\t\t\"#A\u0005tG\u0006d\u0017\r^3ti*\t1#A\u0002pe\u001e\u001c\u0001\u0001\u0005\u0002\u0017\u00035\taBA\u0002ECf\u001cB!A\r\u001dEA\u0011aCG\u0005\u000379\u0011Q!\u00168jiN\u0004\"!\b\u0011\u000e\u0003yQ\u0011aH\u0001\u0006g\u000e\fG.Y\u0005\u0003Cy\u0011q\u0001\u0015:pIV\u001cG\u000f\u0005\u0002$W9\u0011A%\u000b\b\u0003K!j\u0011A\n\u0006\u0003OQ\ta\u0001\u0010:p_Rt\u0014\"A\u0010\n\u0005)r\u0012a\u00029bG.\fw-Z\u0005\u0003Y5\u0012AbU3sS\u0006d\u0017N_1cY\u0016T!A\u000b\u0010\u0002\rqJg.\u001b;?)\u0005)\u0012AE:j]\u001e,H.\u0019:NKN\u001c\u0018mZ3Gk:$\"A\r\u001e\u0011\u0005M:dB\u0001\u001b6!\t)c$\u0003\u00027=\u00051\u0001K]3eK\u001aL!\u0001O\u001d\u0003\rM#(/\u001b8h\u0015\t1d\u0004C\u0003<\u0007\u0001\u0007!\'\u0001\u0007mK:<G\u000f[*ue&tw-\u0001\tqYV\u0014\u0018\r\\\'fgN\fw-\u001a$v]R\u0011!G\u0010\u0005\u0006w\u0011\u0001\rAM\u0001\u000eaJ|G-^2u!J,g-\u001b=\u0016\u0003\u0005\u0003\"AQ$\u000e\u0003\rS!\u0001R#\u0002\t1\fgn\u001a\u0006\u0002\r\u0006!!.\u0019<b\u0013\tA4)\u0001\u0007qe>$Wo\u0019;Be&$\u00180F\u0001K!\ti2*\u0003\u0002M=\t\u0019\u0011J\u001c;\u0002\u001dA\u0014x\u000eZ;di\u0016cW-\\3oiR\u0011qJ\u0015\t\u0003;AK!!\u0015\u0010\u0003\u0007\u0005s\u0017\u0010C\u0004T\u000f\u0005\u0005\t\u0019\u0001&\u0002\u0007a$\u0013\'A\bqe>$Wo\u0019;Ji\u0016\u0014\u0018\r^8s+\u00051\u0006cA,[\u001f6\t\u0001L\u0003\u0002Z=\u0005Q1m\u001c7mK\u000e$\u0018n\u001c8\n\u0005mC&\u0001C%uKJ\fGo\u001c:\u0002\u0011\r\fg.R9vC2$\"AX1\u0011\u0005uy\u0016B\u00011\u001f\u0005\u001d\u0011un\u001c7fC:DqaU\u0005\u0002\u0002\u0003\u0007q*\u0001\u0005iCND7i\u001c3f)\u0005Q\u0015\u0001\u0003;p\'R\u0014\u0018N\\4\u0015\u0003\u0005\u000bAb\u001e:ji\u0016\u0014V\r\u001d7bG\u0016$\u0012\u0001\u001b\t\u0003\u0005&L!A[\"\u0003\r=\u0013\'.Z2u\u0001"
    )
  ScalaSig: length = 0x3 (unknown attribute)
   05 02 00
