Classfile /Users/mw/Projects/slang-braindump/.jar/jar8/assemble/slang-braindump/assemble/content/org/scalatest/time/Minutes.class
  Last modified May 29, 2022; size 2068 bytes
  SHA-256 checksum 9737e111c84bca9ebb84be0df68b2da0d0b1c6eb4624764a3ca670109cc7a16d
  Compiled from "Units.scala"
public final class org.scalatest.time.Minutes
  minor version: 0
  major version: 52
  flags: (0x0031) ACC_PUBLIC, ACC_FINAL, ACC_SUPER
  this_class: #2                          // org/scalatest/time/Minutes
  super_class: #4                         // java/lang/Object
  interfaces: 0, fields: 0, methods: 9, attributes: 3
Constant pool:
   #1 = Utf8               org/scalatest/time/Minutes
   #2 = Class              #1             // org/scalatest/time/Minutes
   #3 = Utf8               java/lang/Object
   #4 = Class              #3             // java/lang/Object
   #5 = Utf8               Units.scala
   #6 = Utf8               Lscala/reflect/ScalaSignature;
   #7 = Utf8               bytes
   #8 = Utf8               \u0006\u0005-<Q!\u0004\b\t\u0002V1Qa\u0006\b\t\u0002bAQAL\u0001\u0005\u0002=Ba\u0001M\u0001\u0005\u0002A\t\u0004B\u0002\u001f\u0002\t\u0003\u0001R\bC\u0004@\u0003\u0005\u0005I\u0011\t!\t\u000f!\u000b\u0011\u0011!C\u0001\u0013\"9Q*AA\u0001\n\u0003q\u0005b\u0002+\u0002\u0003\u0003%\t%\u0016\u0005\b9\u0006\t\t\u0011\"\u0001^\u0011\u001d\u0011\u0017!!A\u0005B\rDq\u0001Z\u0001\u0002\u0002\u0013\u0005S\rC\u0004g\u0003\u0005\u0005I\u0011B4\u0002\u000f5Kg.\u001e;fg*\u0011q\u0002E\u0001\u0005i&lWM\u0003\u0002\u0012%\u0005I1oY1mCR,7\u000f\u001e\u0006\u0002\'\u0005\u0019qN]4\u0004\u0001A\u0011a#A\u0007\u0002\u001d\t9Q*\u001b8vi\u0016\u001c8\u0003B\u0001\u001a9\t\u0002\"A\u0006\u000e\n\u0005mq!!B+oSR\u001c\bCA\u000f!\u001b\u0005q\"\"A\u0010\u0002\u000bM\u001c\u0017\r\\1\n\u0005\u0005r\"a\u0002)s_\u0012,8\r\u001e\t\u0003G-r!\u0001J\u0015\u000f\u0005\u0015BS\"\u0001\u0014\u000b\u0005\u001d\"\u0012A\u0002\u001fs_>$h(C\u0001 \u0013\tQc$A\u0004qC\u000e\\\u0017mZ3\n\u00051j#\u0001D*fe&\fG.\u001b>bE2,\'B\u0001\u0016\u001f\u0003\u0019a\u0014N\\5u}Q\tQ#\u0001\ntS:<W\u000f\\1s\u001b\u0016\u001c8/Y4f\rVtGC\u0001\u001a;!\t\u0019tG\u0004\u00025kA\u0011QEH\u0005\u0003my\ta\u0001\u0015:fI\u00164\u0017B\u0001\u001d:\u0005\u0019\u0019FO]5oO*\u0011aG\b\u0005\u0006w\r\u0001\rAM\u0001\rY\u0016tw\r\u001e5TiJLgnZ\u0001\u0011a2,(/\u00197NKN\u001c\u0018mZ3Gk:$\"A\r \t\u000bm\"\u0001\u0019\u0001\u001a\u0002\u001bA\u0014x\u000eZ;diB\u0013XMZ5y+\u0005\t\u0005C\u0001\"H\u001b\u0005\u0019%B\u0001#F\u0003\u0011a\u0017M\\4\u000b\u0003\u0019\u000bAA[1wC&\u0011\u0001hQ\u0001\raJ|G-^2u\u0003JLG/_\u000b\u0002\u0015B\u0011QdS\u0005\u0003\u0019z\u00111!\u00138u\u00039\u0001(o\u001c3vGR,E.Z7f]R$\"a\u0014*\u0011\u0005u\u0001\u0016BA)\u001f\u0005\r\te.\u001f\u0005\b\'\u001e\t\t\u00111\u0001K\u0003\rAH%M\u0001\u0010aJ|G-^2u\u0013R,\'/\u0019;peV\ta\u000bE\u0002X5>k\u0011\u0001\u0017\u0006\u00033z\t!bY8mY\u0016\u001cG/[8o\u0013\tY\u0006L\u0001\u0005Ji\u0016\u0014\u0018\r^8s\u0003!\u0019\u0017M\\#rk\u0006dGC\u00010b!\tir,\u0003\u0002a=\t9!i\\8mK\u0006t\u0007bB*\n\u0003\u0003\u0005\raT\u0001\tQ\u0006\u001c\bnQ8eKR\t!*\u0001\u0005u_N#(/\u001b8h)\u0005\t\u0015\u0001D<sSR,\'+\u001a9mC\u000e,G#\u00015\u0011\u0005\tK\u0017B\u00016D\u0005\u0019y%M[3di\u0002
   #9 = Utf8               toString
  #10 = Utf8               ()Ljava/lang/String;
  #11 = Utf8               org/scalatest/time/Minutes$
  #12 = Class              #11            // org/scalatest/time/Minutes$
  #13 = Utf8               MODULE$
  #14 = Utf8               Lorg/scalatest/time/Minutes$;
  #15 = NameAndType        #13:#14        // MODULE$:Lorg/scalatest/time/Minutes$;
  #16 = Fieldref           #12.#15        // org/scalatest/time/Minutes$.MODULE$:Lorg/scalatest/time/Minutes$;
  #17 = NameAndType        #9:#10         // toString:()Ljava/lang/String;
  #18 = Methodref          #12.#17        // org/scalatest/time/Minutes$.toString:()Ljava/lang/String;
  #19 = Utf8               hashCode
  #20 = Utf8               ()I
  #21 = NameAndType        #19:#20        // hashCode:()I
  #22 = Methodref          #12.#21        // org/scalatest/time/Minutes$.hashCode:()I
  #23 = Utf8               canEqual
  #24 = Utf8               (Ljava/lang/Object;)Z
  #25 = Utf8               x$1
  #26 = NameAndType        #23:#24        // canEqual:(Ljava/lang/Object;)Z
  #27 = Methodref          #12.#26        // org/scalatest/time/Minutes$.canEqual:(Ljava/lang/Object;)Z
  #28 = Utf8               Ljava/lang/Object;
  #29 = Utf8               productIterator
  #30 = Utf8               ()Lscala/collection/Iterator;
  #31 = Utf8               ()Lscala/collection/Iterator<Ljava/lang/Object;>;
  #32 = NameAndType        #29:#30        // productIterator:()Lscala/collection/Iterator;
  #33 = Methodref          #12.#32        // org/scalatest/time/Minutes$.productIterator:()Lscala/collection/Iterator;
  #34 = Utf8               productElement
  #35 = Utf8               (I)Ljava/lang/Object;
  #36 = NameAndType        #34:#35        // productElement:(I)Ljava/lang/Object;
  #37 = Methodref          #12.#36        // org/scalatest/time/Minutes$.productElement:(I)Ljava/lang/Object;
  #38 = Utf8               I
  #39 = Utf8               productArity
  #40 = NameAndType        #39:#20        // productArity:()I
  #41 = Methodref          #12.#40        // org/scalatest/time/Minutes$.productArity:()I
  #42 = Utf8               productPrefix
  #43 = NameAndType        #42:#10        // productPrefix:()Ljava/lang/String;
  #44 = Methodref          #12.#43        // org/scalatest/time/Minutes$.productPrefix:()Ljava/lang/String;
  #45 = Utf8               productElementNames
  #46 = Utf8               ()Lscala/collection/Iterator<Ljava/lang/String;>;
  #47 = NameAndType        #45:#30        // productElementNames:()Lscala/collection/Iterator;
  #48 = Methodref          #12.#47        // org/scalatest/time/Minutes$.productElementNames:()Lscala/collection/Iterator;
  #49 = Utf8               productElementName
  #50 = Utf8               (I)Ljava/lang/String;
  #51 = Utf8               n
  #52 = NameAndType        #49:#50        // productElementName:(I)Ljava/lang/String;
  #53 = Methodref          #12.#52        // org/scalatest/time/Minutes$.productElementName:(I)Ljava/lang/String;
  #54 = Utf8               Code
  #55 = Utf8               LocalVariableTable
  #56 = Utf8               MethodParameters
  #57 = Utf8               Signature
  #58 = Utf8               SourceFile
  #59 = Utf8               RuntimeVisibleAnnotations
  #60 = Utf8               ScalaSig
{
  public static java.lang.String toString();
    descriptor: ()Ljava/lang/String;
    flags: (0x0009) ACC_PUBLIC, ACC_STATIC
    Code:
      stack=1, locals=0, args_size=0
         0: getstatic     #16                 // Field org/scalatest/time/Minutes$.MODULE$:Lorg/scalatest/time/Minutes$;
         3: invokevirtual #18                 // Method org/scalatest/time/Minutes$.toString:()Ljava/lang/String;
         6: areturn

  public static int hashCode();
    descriptor: ()I
    flags: (0x0009) ACC_PUBLIC, ACC_STATIC
    Code:
      stack=1, locals=0, args_size=0
         0: getstatic     #16                 // Field org/scalatest/time/Minutes$.MODULE$:Lorg/scalatest/time/Minutes$;
         3: invokevirtual #22                 // Method org/scalatest/time/Minutes$.hashCode:()I
         6: ireturn

  public static boolean canEqual(java.lang.Object);
    descriptor: (Ljava/lang/Object;)Z
    flags: (0x0009) ACC_PUBLIC, ACC_STATIC
    Code:
      stack=2, locals=1, args_size=1
         0: getstatic     #16                 // Field org/scalatest/time/Minutes$.MODULE$:Lorg/scalatest/time/Minutes$;
         3: aload_0
         4: invokevirtual #27                 // Method org/scalatest/time/Minutes$.canEqual:(Ljava/lang/Object;)Z
         7: ireturn
      LocalVariableTable:
        Start  Length  Slot  Name   Signature
            0       8     0   x$1   Ljava/lang/Object;
    MethodParameters:
      Name                           Flags
      x$1                            final

  public static scala.collection.Iterator<java.lang.Object> productIterator();
    descriptor: ()Lscala/collection/Iterator;
    flags: (0x0009) ACC_PUBLIC, ACC_STATIC
    Code:
      stack=1, locals=0, args_size=0
         0: getstatic     #16                 // Field org/scalatest/time/Minutes$.MODULE$:Lorg/scalatest/time/Minutes$;
         3: invokevirtual #33                 // Method org/scalatest/time/Minutes$.productIterator:()Lscala/collection/Iterator;
         6: areturn
    Signature: #31                          // ()Lscala/collection/Iterator<Ljava/lang/Object;>;

  public static java.lang.Object productElement(int);
    descriptor: (I)Ljava/lang/Object;
    flags: (0x0009) ACC_PUBLIC, ACC_STATIC
    Code:
      stack=2, locals=1, args_size=1
         0: getstatic     #16                 // Field org/scalatest/time/Minutes$.MODULE$:Lorg/scalatest/time/Minutes$;
         3: iload_0
         4: invokevirtual #37                 // Method org/scalatest/time/Minutes$.productElement:(I)Ljava/lang/Object;
         7: areturn
      LocalVariableTable:
        Start  Length  Slot  Name   Signature
            0       8     0   x$1   I
    MethodParameters:
      Name                           Flags
      x$1                            final

  public static int productArity();
    descriptor: ()I
    flags: (0x0009) ACC_PUBLIC, ACC_STATIC
    Code:
      stack=1, locals=0, args_size=0
         0: getstatic     #16                 // Field org/scalatest/time/Minutes$.MODULE$:Lorg/scalatest/time/Minutes$;
         3: invokevirtual #41                 // Method org/scalatest/time/Minutes$.productArity:()I
         6: ireturn

  public static java.lang.String productPrefix();
    descriptor: ()Ljava/lang/String;
    flags: (0x0009) ACC_PUBLIC, ACC_STATIC
    Code:
      stack=1, locals=0, args_size=0
         0: getstatic     #16                 // Field org/scalatest/time/Minutes$.MODULE$:Lorg/scalatest/time/Minutes$;
         3: invokevirtual #44                 // Method org/scalatest/time/Minutes$.productPrefix:()Ljava/lang/String;
         6: areturn

  public static scala.collection.Iterator<java.lang.String> productElementNames();
    descriptor: ()Lscala/collection/Iterator;
    flags: (0x0009) ACC_PUBLIC, ACC_STATIC
    Code:
      stack=1, locals=0, args_size=0
         0: getstatic     #16                 // Field org/scalatest/time/Minutes$.MODULE$:Lorg/scalatest/time/Minutes$;
         3: invokevirtual #48                 // Method org/scalatest/time/Minutes$.productElementNames:()Lscala/collection/Iterator;
         6: areturn
    Signature: #46                          // ()Lscala/collection/Iterator<Ljava/lang/String;>;

  public static java.lang.String productElementName(int);
    descriptor: (I)Ljava/lang/String;
    flags: (0x0009) ACC_PUBLIC, ACC_STATIC
    Code:
      stack=2, locals=1, args_size=1
         0: getstatic     #16                 // Field org/scalatest/time/Minutes$.MODULE$:Lorg/scalatest/time/Minutes$;
         3: iload_0
         4: invokevirtual #53                 // Method org/scalatest/time/Minutes$.productElementName:(I)Ljava/lang/String;
         7: areturn
      LocalVariableTable:
        Start  Length  Slot  Name   Signature
            0       8     0     n   I
    MethodParameters:
      Name                           Flags
      n                              final
}
SourceFile: "Units.scala"
RuntimeVisibleAnnotations:
  0: #6(#7=s#8)
    scala.reflect.ScalaSignature(
      bytes="\u0006\u0005-<Q!\u0004\b\t\u0002V1Qa\u0006\b\t\u0002bAQAL\u0001\u0005\u0002=Ba\u0001M\u0001\u0005\u0002A\t\u0004B\u0002\u001f\u0002\t\u0003\u0001R\bC\u0004@\u0003\u0005\u0005I\u0011\t!\t\u000f!\u000b\u0011\u0011!C\u0001\u0013\"9Q*AA\u0001\n\u0003q\u0005b\u0002+\u0002\u0003\u0003%\t%\u0016\u0005\b9\u0006\t\t\u0011\"\u0001^\u0011\u001d\u0011\u0017!!A\u0005B\rDq\u0001Z\u0001\u0002\u0002\u0013\u0005S\rC\u0004g\u0003\u0005\u0005I\u0011B4\u0002\u000f5Kg.\u001e;fg*\u0011q\u0002E\u0001\u0005i&lWM\u0003\u0002\u0012%\u0005I1oY1mCR,7\u000f\u001e\u0006\u0002\'\u0005\u0019qN]4\u0004\u0001A\u0011a#A\u0007\u0002\u001d\t9Q*\u001b8vi\u0016\u001c8\u0003B\u0001\u001a9\t\u0002\"A\u0006\u000e\n\u0005mq!!B+oSR\u001c\bCA\u000f!\u001b\u0005q\"\"A\u0010\u0002\u000bM\u001c\u0017\r\\1\n\u0005\u0005r\"a\u0002)s_\u0012,8\r\u001e\t\u0003G-r!\u0001J\u0015\u000f\u0005\u0015BS\"\u0001\u0014\u000b\u0005\u001d\"\u0012A\u0002\u001fs_>$h(C\u0001 \u0013\tQc$A\u0004qC\u000e\\\u0017mZ3\n\u00051j#\u0001D*fe&\fG.\u001b>bE2,\'B\u0001\u0016\u001f\u0003\u0019a\u0014N\\5u}Q\tQ#\u0001\ntS:<W\u000f\\1s\u001b\u0016\u001c8/Y4f\rVtGC\u0001\u001a;!\t\u0019tG\u0004\u00025kA\u0011QEH\u0005\u0003my\ta\u0001\u0015:fI\u00164\u0017B\u0001\u001d:\u0005\u0019\u0019FO]5oO*\u0011aG\b\u0005\u0006w\r\u0001\rAM\u0001\rY\u0016tw\r\u001e5TiJLgnZ\u0001\u0011a2,(/\u00197NKN\u001c\u0018mZ3Gk:$\"A\r \t\u000bm\"\u0001\u0019\u0001\u001a\u0002\u001bA\u0014x\u000eZ;diB\u0013XMZ5y+\u0005\t\u0005C\u0001\"H\u001b\u0005\u0019%B\u0001#F\u0003\u0011a\u0017M\\4\u000b\u0003\u0019\u000bAA[1wC&\u0011\u0001hQ\u0001\raJ|G-^2u\u0003JLG/_\u000b\u0002\u0015B\u0011QdS\u0005\u0003\u0019z\u00111!\u00138u\u00039\u0001(o\u001c3vGR,E.Z7f]R$\"a\u0014*\u0011\u0005u\u0001\u0016BA)\u001f\u0005\r\te.\u001f\u0005\b\'\u001e\t\t\u00111\u0001K\u0003\rAH%M\u0001\u0010aJ|G-^2u\u0013R,\'/\u0019;peV\ta\u000bE\u0002X5>k\u0011\u0001\u0017\u0006\u00033z\t!bY8mY\u0016\u001cG/[8o\u0013\tY\u0006L\u0001\u0005Ji\u0016\u0014\u0018\r^8s\u0003!\u0019\u0017M\\#rk\u0006dGC\u00010b!\tir,\u0003\u0002a=\t9!i\\8mK\u0006t\u0007bB*\n\u0003\u0003\u0005\raT\u0001\tQ\u0006\u001c\bnQ8eKR\t!*\u0001\u0005u_N#(/\u001b8h)\u0005\t\u0015\u0001D<sSR,\'+\u001a9mC\u000e,G#\u00015\u0011\u0005\tK\u0017B\u00016D\u0005\u0019y%M[3di\u0002"
    )
  ScalaSig: length = 0x3 (unknown attribute)
   05 02 00
