Classfile /Users/mw/Projects/slang-braindump/.jar/jar8/assemble/slang-braindump/assemble/content/org/scalatest/time/SpanSugar$FloatingGrainOfTime.class
  Last modified May 29, 2022; size 3469 bytes
  SHA-256 checksum 1d5658a04ca3bccb2ba12a7971f88122fb5975290c5a23aad466556205b61da0
  Compiled from "SpanSugar.scala"
public class org.scalatest.time.SpanSugar$FloatingGrainOfTime
  minor version: 0
  major version: 52
  flags: (0x0021) ACC_PUBLIC, ACC_SUPER
  this_class: #2                          // org/scalatest/time/SpanSugar$FloatingGrainOfTime
  super_class: #4                         // java/lang/Object
  interfaces: 0, fields: 2, methods: 17, attributes: 4
Constant pool:
    #1 = Utf8               org/scalatest/time/SpanSugar$FloatingGrainOfTime
    #2 = Class              #1            // org/scalatest/time/SpanSugar$FloatingGrainOfTime
    #3 = Utf8               java/lang/Object
    #4 = Class              #3            // java/lang/Object
    #5 = Utf8               SpanSugar.scala
    #6 = Utf8               org/scalatest/time/SpanSugar
    #7 = Class              #6            // org/scalatest/time/SpanSugar
    #8 = Utf8               FloatingGrainOfTime
    #9 = Utf8               value
   #10 = Utf8               D
   #11 = Utf8               $outer
   #12 = Utf8               Lorg/scalatest/time/SpanSugar;
   #13 = Utf8               nanosecond
   #14 = Utf8               ()Lorg/scalatest/time/Span;
   #15 = Utf8               org/scalatest/time/Span$
   #16 = Class              #15           // org/scalatest/time/Span$
   #17 = Utf8               MODULE$
   #18 = Utf8               Lorg/scalatest/time/Span$;
   #19 = NameAndType        #17:#18       // MODULE$:Lorg/scalatest/time/Span$;
   #20 = Fieldref           #16.#19       // org/scalatest/time/Span$.MODULE$:Lorg/scalatest/time/Span$;
   #21 = NameAndType        #9:#10        // value:D
   #22 = Fieldref           #2.#21        // org/scalatest/time/SpanSugar$FloatingGrainOfTime.value:D
   #23 = Utf8               org/scalatest/time/Nanosecond$
   #24 = Class              #23           // org/scalatest/time/Nanosecond$
   #25 = Utf8               Lorg/scalatest/time/Nanosecond$;
   #26 = NameAndType        #17:#25       // MODULE$:Lorg/scalatest/time/Nanosecond$;
   #27 = Fieldref           #24.#26       // org/scalatest/time/Nanosecond$.MODULE$:Lorg/scalatest/time/Nanosecond$;
   #28 = Utf8               apply
   #29 = Utf8               (DLorg/scalatest/time/Units;)Lorg/scalatest/time/Span;
   #30 = NameAndType        #28:#29       // apply:(DLorg/scalatest/time/Units;)Lorg/scalatest/time/Span;
   #31 = Methodref          #16.#30       // org/scalatest/time/Span$.apply:(DLorg/scalatest/time/Units;)Lorg/scalatest/time/Span;
   #32 = Utf8               this
   #33 = Utf8               Lorg/scalatest/time/SpanSugar$FloatingGrainOfTime;
   #34 = Utf8               nanoseconds
   #35 = Utf8               org/scalatest/time/Nanoseconds$
   #36 = Class              #35           // org/scalatest/time/Nanoseconds$
   #37 = Utf8               Lorg/scalatest/time/Nanoseconds$;
   #38 = NameAndType        #17:#37       // MODULE$:Lorg/scalatest/time/Nanoseconds$;
   #39 = Fieldref           #36.#38       // org/scalatest/time/Nanoseconds$.MODULE$:Lorg/scalatest/time/Nanoseconds$;
   #40 = Utf8               microsecond
   #41 = Utf8               org/scalatest/time/Microsecond$
   #42 = Class              #41           // org/scalatest/time/Microsecond$
   #43 = Utf8               Lorg/scalatest/time/Microsecond$;
   #44 = NameAndType        #17:#43       // MODULE$:Lorg/scalatest/time/Microsecond$;
   #45 = Fieldref           #42.#44       // org/scalatest/time/Microsecond$.MODULE$:Lorg/scalatest/time/Microsecond$;
   #46 = Utf8               microseconds
   #47 = Utf8               org/scalatest/time/Microseconds$
   #48 = Class              #47           // org/scalatest/time/Microseconds$
   #49 = Utf8               Lorg/scalatest/time/Microseconds$;
   #50 = NameAndType        #17:#49       // MODULE$:Lorg/scalatest/time/Microseconds$;
   #51 = Fieldref           #48.#50       // org/scalatest/time/Microseconds$.MODULE$:Lorg/scalatest/time/Microseconds$;
   #52 = Utf8               millisecond
   #53 = Utf8               org/scalatest/time/Millisecond$
   #54 = Class              #53           // org/scalatest/time/Millisecond$
   #55 = Utf8               Lorg/scalatest/time/Millisecond$;
   #56 = NameAndType        #17:#55       // MODULE$:Lorg/scalatest/time/Millisecond$;
   #57 = Fieldref           #54.#56       // org/scalatest/time/Millisecond$.MODULE$:Lorg/scalatest/time/Millisecond$;
   #58 = Utf8               milliseconds
   #59 = Utf8               org/scalatest/time/Milliseconds$
   #60 = Class              #59           // org/scalatest/time/Milliseconds$
   #61 = Utf8               Lorg/scalatest/time/Milliseconds$;
   #62 = NameAndType        #17:#61       // MODULE$:Lorg/scalatest/time/Milliseconds$;
   #63 = Fieldref           #60.#62       // org/scalatest/time/Milliseconds$.MODULE$:Lorg/scalatest/time/Milliseconds$;
   #64 = Utf8               millis
   #65 = Utf8               org/scalatest/time/Millis$
   #66 = Class              #65           // org/scalatest/time/Millis$
   #67 = Utf8               Lorg/scalatest/time/Millis$;
   #68 = NameAndType        #17:#67       // MODULE$:Lorg/scalatest/time/Millis$;
   #69 = Fieldref           #66.#68       // org/scalatest/time/Millis$.MODULE$:Lorg/scalatest/time/Millis$;
   #70 = Utf8               second
   #71 = Utf8               org/scalatest/time/Second$
   #72 = Class              #71           // org/scalatest/time/Second$
   #73 = Utf8               Lorg/scalatest/time/Second$;
   #74 = NameAndType        #17:#73       // MODULE$:Lorg/scalatest/time/Second$;
   #75 = Fieldref           #72.#74       // org/scalatest/time/Second$.MODULE$:Lorg/scalatest/time/Second$;
   #76 = Utf8               seconds
   #77 = Utf8               org/scalatest/time/Seconds$
   #78 = Class              #77           // org/scalatest/time/Seconds$
   #79 = Utf8               Lorg/scalatest/time/Seconds$;
   #80 = NameAndType        #17:#79       // MODULE$:Lorg/scalatest/time/Seconds$;
   #81 = Fieldref           #78.#80       // org/scalatest/time/Seconds$.MODULE$:Lorg/scalatest/time/Seconds$;
   #82 = Utf8               minute
   #83 = Utf8               org/scalatest/time/Minute$
   #84 = Class              #83           // org/scalatest/time/Minute$
   #85 = Utf8               Lorg/scalatest/time/Minute$;
   #86 = NameAndType        #17:#85       // MODULE$:Lorg/scalatest/time/Minute$;
   #87 = Fieldref           #84.#86       // org/scalatest/time/Minute$.MODULE$:Lorg/scalatest/time/Minute$;
   #88 = Utf8               minutes
   #89 = Utf8               org/scalatest/time/Minutes$
   #90 = Class              #89           // org/scalatest/time/Minutes$
   #91 = Utf8               Lorg/scalatest/time/Minutes$;
   #92 = NameAndType        #17:#91       // MODULE$:Lorg/scalatest/time/Minutes$;
   #93 = Fieldref           #90.#92       // org/scalatest/time/Minutes$.MODULE$:Lorg/scalatest/time/Minutes$;
   #94 = Utf8               hour
   #95 = Utf8               org/scalatest/time/Hour$
   #96 = Class              #95           // org/scalatest/time/Hour$
   #97 = Utf8               Lorg/scalatest/time/Hour$;
   #98 = NameAndType        #17:#97       // MODULE$:Lorg/scalatest/time/Hour$;
   #99 = Fieldref           #96.#98       // org/scalatest/time/Hour$.MODULE$:Lorg/scalatest/time/Hour$;
  #100 = Utf8               hours
  #101 = Utf8               org/scalatest/time/Hours$
  #102 = Class              #101          // org/scalatest/time/Hours$
  #103 = Utf8               Lorg/scalatest/time/Hours$;
  #104 = NameAndType        #17:#103      // MODULE$:Lorg/scalatest/time/Hours$;
  #105 = Fieldref           #102.#104     // org/scalatest/time/Hours$.MODULE$:Lorg/scalatest/time/Hours$;
  #106 = Utf8               day
  #107 = Utf8               org/scalatest/time/Day$
  #108 = Class              #107          // org/scalatest/time/Day$
  #109 = Utf8               Lorg/scalatest/time/Day$;
  #110 = NameAndType        #17:#109      // MODULE$:Lorg/scalatest/time/Day$;
  #111 = Fieldref           #108.#110     // org/scalatest/time/Day$.MODULE$:Lorg/scalatest/time/Day$;
  #112 = Utf8               days
  #113 = Utf8               org/scalatest/time/Days$
  #114 = Class              #113          // org/scalatest/time/Days$
  #115 = Utf8               Lorg/scalatest/time/Days$;
  #116 = NameAndType        #17:#115      // MODULE$:Lorg/scalatest/time/Days$;
  #117 = Fieldref           #114.#116     // org/scalatest/time/Days$.MODULE$:Lorg/scalatest/time/Days$;
  #118 = Utf8               org$scalatest$time$SpanSugar$FloatingGrainOfTime$$$outer
  #119 = Utf8               ()Lorg/scalatest/time/SpanSugar;
  #120 = NameAndType        #11:#12       // $outer:Lorg/scalatest/time/SpanSugar;
  #121 = Fieldref           #2.#120       // org/scalatest/time/SpanSugar$FloatingGrainOfTime.$outer:Lorg/scalatest/time/SpanSugar;
  #122 = Utf8               <init>
  #123 = Utf8               (Lorg/scalatest/time/SpanSugar;D)V
  #124 = Utf8               ()V
  #125 = NameAndType        #122:#124     // "<init>":()V
  #126 = Methodref          #4.#125       // java/lang/Object."<init>":()V
  #127 = Utf8               Code
  #128 = Utf8               LineNumberTable
  #129 = Utf8               LocalVariableTable
  #130 = Utf8               StackMapTable
  #131 = Utf8               MethodParameters
  #132 = Utf8               InnerClasses
  #133 = Utf8               SourceFile
  #134 = Utf8               ScalaInlineInfo
  #135 = Utf8               Scala
{
  private final double value;
    descriptor: D
    flags: (0x0012) ACC_PRIVATE, ACC_FINAL

  public final org.scalatest.time.SpanSugar $outer;
    descriptor: Lorg/scalatest/time/SpanSugar;
    flags: (0x1011) ACC_PUBLIC, ACC_FINAL, ACC_SYNTHETIC

  public org.scalatest.time.Span nanosecond();
    descriptor: ()Lorg/scalatest/time/Span;
    flags: (0x0001) ACC_PUBLIC
    Code:
      stack=4, locals=1, args_size=1
         0: getstatic     #20                 // Field org/scalatest/time/Span$.MODULE$:Lorg/scalatest/time/Span$;
         3: aload_0
         4: getfield      #22                 // Field value:D
         7: getstatic     #27                 // Field org/scalatest/time/Nanosecond$.MODULE$:Lorg/scalatest/time/Nanosecond$;
        10: invokevirtual #31                 // Method org/scalatest/time/Span$.apply:(DLorg/scalatest/time/Units;)Lorg/scalatest/time/Span;
        13: areturn
      LineNumberTable:
        line 411: 0
      LocalVariableTable:
        Start  Length  Slot  Name   Signature
            0      14     0  this   Lorg/scalatest/time/SpanSugar$FloatingGrainOfTime;

  public org.scalatest.time.Span nanoseconds();
    descriptor: ()Lorg/scalatest/time/Span;
    flags: (0x0001) ACC_PUBLIC
    Code:
      stack=4, locals=1, args_size=1
         0: getstatic     #20                 // Field org/scalatest/time/Span$.MODULE$:Lorg/scalatest/time/Span$;
         3: aload_0
         4: getfield      #22                 // Field value:D
         7: getstatic     #39                 // Field org/scalatest/time/Nanoseconds$.MODULE$:Lorg/scalatest/time/Nanoseconds$;
        10: invokevirtual #31                 // Method org/scalatest/time/Span$.apply:(DLorg/scalatest/time/Units;)Lorg/scalatest/time/Span;
        13: areturn
      LineNumberTable:
        line 418: 0
      LocalVariableTable:
        Start  Length  Slot  Name   Signature
            0      14     0  this   Lorg/scalatest/time/SpanSugar$FloatingGrainOfTime;

  public org.scalatest.time.Span microsecond();
    descriptor: ()Lorg/scalatest/time/Span;
    flags: (0x0001) ACC_PUBLIC
    Code:
      stack=4, locals=1, args_size=1
         0: getstatic     #20                 // Field org/scalatest/time/Span$.MODULE$:Lorg/scalatest/time/Span$;
         3: aload_0
         4: getfield      #22                 // Field value:D
         7: getstatic     #45                 // Field org/scalatest/time/Microsecond$.MODULE$:Lorg/scalatest/time/Microsecond$;
        10: invokevirtual #31                 // Method org/scalatest/time/Span$.apply:(DLorg/scalatest/time/Units;)Lorg/scalatest/time/Span;
        13: areturn
      LineNumberTable:
        line 425: 0
      LocalVariableTable:
        Start  Length  Slot  Name   Signature
            0      14     0  this   Lorg/scalatest/time/SpanSugar$FloatingGrainOfTime;

  public org.scalatest.time.Span microseconds();
    descriptor: ()Lorg/scalatest/time/Span;
    flags: (0x0001) ACC_PUBLIC
    Code:
      stack=4, locals=1, args_size=1
         0: getstatic     #20                 // Field org/scalatest/time/Span$.MODULE$:Lorg/scalatest/time/Span$;
         3: aload_0
         4: getfield      #22                 // Field value:D
         7: getstatic     #51                 // Field org/scalatest/time/Microseconds$.MODULE$:Lorg/scalatest/time/Microseconds$;
        10: invokevirtual #31                 // Method org/scalatest/time/Span$.apply:(DLorg/scalatest/time/Units;)Lorg/scalatest/time/Span;
        13: areturn
      LineNumberTable:
        line 432: 0
      LocalVariableTable:
        Start  Length  Slot  Name   Signature
            0      14     0  this   Lorg/scalatest/time/SpanSugar$FloatingGrainOfTime;

  public org.scalatest.time.Span millisecond();
    descriptor: ()Lorg/scalatest/time/Span;
    flags: (0x0001) ACC_PUBLIC
    Code:
      stack=4, locals=1, args_size=1
         0: getstatic     #20                 // Field org/scalatest/time/Span$.MODULE$:Lorg/scalatest/time/Span$;
         3: aload_0
         4: getfield      #22                 // Field value:D
         7: getstatic     #57                 // Field org/scalatest/time/Millisecond$.MODULE$:Lorg/scalatest/time/Millisecond$;
        10: invokevirtual #31                 // Method org/scalatest/time/Span$.apply:(DLorg/scalatest/time/Units;)Lorg/scalatest/time/Span;
        13: areturn
      LineNumberTable:
        line 439: 0
      LocalVariableTable:
        Start  Length  Slot  Name   Signature
            0      14     0  this   Lorg/scalatest/time/SpanSugar$FloatingGrainOfTime;

  public org.scalatest.time.Span milliseconds();
    descriptor: ()Lorg/scalatest/time/Span;
    flags: (0x0001) ACC_PUBLIC
    Code:
      stack=4, locals=1, args_size=1
         0: getstatic     #20                 // Field org/scalatest/time/Span$.MODULE$:Lorg/scalatest/time/Span$;
         3: aload_0
         4: getfield      #22                 // Field value:D
         7: getstatic     #63                 // Field org/scalatest/time/Milliseconds$.MODULE$:Lorg/scalatest/time/Milliseconds$;
        10: invokevirtual #31                 // Method org/scalatest/time/Span$.apply:(DLorg/scalatest/time/Units;)Lorg/scalatest/time/Span;
        13: areturn
      LineNumberTable:
        line 446: 0
      LocalVariableTable:
        Start  Length  Slot  Name   Signature
            0      14     0  this   Lorg/scalatest/time/SpanSugar$FloatingGrainOfTime;

  public org.scalatest.time.Span millis();
    descriptor: ()Lorg/scalatest/time/Span;
    flags: (0x0001) ACC_PUBLIC
    Code:
      stack=4, locals=1, args_size=1
         0: getstatic     #20                 // Field org/scalatest/time/Span$.MODULE$:Lorg/scalatest/time/Span$;
         3: aload_0
         4: getfield      #22                 // Field value:D
         7: getstatic     #69                 // Field org/scalatest/time/Millis$.MODULE$:Lorg/scalatest/time/Millis$;
        10: invokevirtual #31                 // Method org/scalatest/time/Span$.apply:(DLorg/scalatest/time/Units;)Lorg/scalatest/time/Span;
        13: areturn
      LineNumberTable:
        line 453: 0
      LocalVariableTable:
        Start  Length  Slot  Name   Signature
            0      14     0  this   Lorg/scalatest/time/SpanSugar$FloatingGrainOfTime;

  public org.scalatest.time.Span second();
    descriptor: ()Lorg/scalatest/time/Span;
    flags: (0x0001) ACC_PUBLIC
    Code:
      stack=4, locals=1, args_size=1
         0: getstatic     #20                 // Field org/scalatest/time/Span$.MODULE$:Lorg/scalatest/time/Span$;
         3: aload_0
         4: getfield      #22                 // Field value:D
         7: getstatic     #75                 // Field org/scalatest/time/Second$.MODULE$:Lorg/scalatest/time/Second$;
        10: invokevirtual #31                 // Method org/scalatest/time/Span$.apply:(DLorg/scalatest/time/Units;)Lorg/scalatest/time/Span;
        13: areturn
      LineNumberTable:
        line 460: 0
      LocalVariableTable:
        Start  Length  Slot  Name   Signature
            0      14     0  this   Lorg/scalatest/time/SpanSugar$FloatingGrainOfTime;

  public org.scalatest.time.Span seconds();
    descriptor: ()Lorg/scalatest/time/Span;
    flags: (0x0001) ACC_PUBLIC
    Code:
      stack=4, locals=1, args_size=1
         0: getstatic     #20                 // Field org/scalatest/time/Span$.MODULE$:Lorg/scalatest/time/Span$;
         3: aload_0
         4: getfield      #22                 // Field value:D
         7: getstatic     #81                 // Field org/scalatest/time/Seconds$.MODULE$:Lorg/scalatest/time/Seconds$;
        10: invokevirtual #31                 // Method org/scalatest/time/Span$.apply:(DLorg/scalatest/time/Units;)Lorg/scalatest/time/Span;
        13: areturn
      LineNumberTable:
        line 467: 0
      LocalVariableTable:
        Start  Length  Slot  Name   Signature
            0      14     0  this   Lorg/scalatest/time/SpanSugar$FloatingGrainOfTime;

  public org.scalatest.time.Span minute();
    descriptor: ()Lorg/scalatest/time/Span;
    flags: (0x0001) ACC_PUBLIC
    Code:
      stack=4, locals=1, args_size=1
         0: getstatic     #20                 // Field org/scalatest/time/Span$.MODULE$:Lorg/scalatest/time/Span$;
         3: aload_0
         4: getfield      #22                 // Field value:D
         7: getstatic     #87                 // Field org/scalatest/time/Minute$.MODULE$:Lorg/scalatest/time/Minute$;
        10: invokevirtual #31                 // Method org/scalatest/time/Span$.apply:(DLorg/scalatest/time/Units;)Lorg/scalatest/time/Span;
        13: areturn
      LineNumberTable:
        line 474: 0
      LocalVariableTable:
        Start  Length  Slot  Name   Signature
            0      14     0  this   Lorg/scalatest/time/SpanSugar$FloatingGrainOfTime;

  public org.scalatest.time.Span minutes();
    descriptor: ()Lorg/scalatest/time/Span;
    flags: (0x0001) ACC_PUBLIC
    Code:
      stack=4, locals=1, args_size=1
         0: getstatic     #20                 // Field org/scalatest/time/Span$.MODULE$:Lorg/scalatest/time/Span$;
         3: aload_0
         4: getfield      #22                 // Field value:D
         7: getstatic     #93                 // Field org/scalatest/time/Minutes$.MODULE$:Lorg/scalatest/time/Minutes$;
        10: invokevirtual #31                 // Method org/scalatest/time/Span$.apply:(DLorg/scalatest/time/Units;)Lorg/scalatest/time/Span;
        13: areturn
      LineNumberTable:
        line 481: 0
      LocalVariableTable:
        Start  Length  Slot  Name   Signature
            0      14     0  this   Lorg/scalatest/time/SpanSugar$FloatingGrainOfTime;

  public org.scalatest.time.Span hour();
    descriptor: ()Lorg/scalatest/time/Span;
    flags: (0x0001) ACC_PUBLIC
    Code:
      stack=4, locals=1, args_size=1
         0: getstatic     #20                 // Field org/scalatest/time/Span$.MODULE$:Lorg/scalatest/time/Span$;
         3: aload_0
         4: getfield      #22                 // Field value:D
         7: getstatic     #99                 // Field org/scalatest/time/Hour$.MODULE$:Lorg/scalatest/time/Hour$;
        10: invokevirtual #31                 // Method org/scalatest/time/Span$.apply:(DLorg/scalatest/time/Units;)Lorg/scalatest/time/Span;
        13: areturn
      LineNumberTable:
        line 488: 0
      LocalVariableTable:
        Start  Length  Slot  Name   Signature
            0      14     0  this   Lorg/scalatest/time/SpanSugar$FloatingGrainOfTime;

  public org.scalatest.time.Span hours();
    descriptor: ()Lorg/scalatest/time/Span;
    flags: (0x0001) ACC_PUBLIC
    Code:
      stack=4, locals=1, args_size=1
         0: getstatic     #20                 // Field org/scalatest/time/Span$.MODULE$:Lorg/scalatest/time/Span$;
         3: aload_0
         4: getfield      #22                 // Field value:D
         7: getstatic     #105                // Field org/scalatest/time/Hours$.MODULE$:Lorg/scalatest/time/Hours$;
        10: invokevirtual #31                 // Method org/scalatest/time/Span$.apply:(DLorg/scalatest/time/Units;)Lorg/scalatest/time/Span;
        13: areturn
      LineNumberTable:
        line 495: 0
      LocalVariableTable:
        Start  Length  Slot  Name   Signature
            0      14     0  this   Lorg/scalatest/time/SpanSugar$FloatingGrainOfTime;

  public org.scalatest.time.Span day();
    descriptor: ()Lorg/scalatest/time/Span;
    flags: (0x0001) ACC_PUBLIC
    Code:
      stack=4, locals=1, args_size=1
         0: getstatic     #20                 // Field org/scalatest/time/Span$.MODULE$:Lorg/scalatest/time/Span$;
         3: aload_0
         4: getfield      #22                 // Field value:D
         7: getstatic     #111                // Field org/scalatest/time/Day$.MODULE$:Lorg/scalatest/time/Day$;
        10: invokevirtual #31                 // Method org/scalatest/time/Span$.apply:(DLorg/scalatest/time/Units;)Lorg/scalatest/time/Span;
        13: areturn
      LineNumberTable:
        line 502: 0
      LocalVariableTable:
        Start  Length  Slot  Name   Signature
            0      14     0  this   Lorg/scalatest/time/SpanSugar$FloatingGrainOfTime;

  public org.scalatest.time.Span days();
    descriptor: ()Lorg/scalatest/time/Span;
    flags: (0x0001) ACC_PUBLIC
    Code:
      stack=4, locals=1, args_size=1
         0: getstatic     #20                 // Field org/scalatest/time/Span$.MODULE$:Lorg/scalatest/time/Span$;
         3: aload_0
         4: getfield      #22                 // Field value:D
         7: getstatic     #117                // Field org/scalatest/time/Days$.MODULE$:Lorg/scalatest/time/Days$;
        10: invokevirtual #31                 // Method org/scalatest/time/Span$.apply:(DLorg/scalatest/time/Units;)Lorg/scalatest/time/Span;
        13: areturn
      LineNumberTable:
        line 509: 0
      LocalVariableTable:
        Start  Length  Slot  Name   Signature
            0      14     0  this   Lorg/scalatest/time/SpanSugar$FloatingGrainOfTime;

  public org.scalatest.time.SpanSugar org$scalatest$time$SpanSugar$FloatingGrainOfTime$$$outer();
    descriptor: ()Lorg/scalatest/time/SpanSugar;
    flags: (0x1001) ACC_PUBLIC, ACC_SYNTHETIC
    Code:
      stack=1, locals=1, args_size=1
         0: aload_0
         1: getfield      #121                // Field $outer:Lorg/scalatest/time/SpanSugar;
         4: areturn
      LineNumberTable:
        line 404: 0
      LocalVariableTable:
        Start  Length  Slot  Name   Signature
            0       5     0  this   Lorg/scalatest/time/SpanSugar$FloatingGrainOfTime;

  public org.scalatest.time.SpanSugar$FloatingGrainOfTime(org.scalatest.time.SpanSugar, double);
    descriptor: (Lorg/scalatest/time/SpanSugar;D)V
    flags: (0x0001) ACC_PUBLIC
    Code:
      stack=3, locals=4, args_size=3
         0: aload_0
         1: dload_2
         2: putfield      #22                 // Field value:D
         5: aload_1
         6: ifnonnull     11
         9: aconst_null
        10: athrow
        11: aload_0
        12: aload_1
        13: putfield      #121                // Field $outer:Lorg/scalatest/time/SpanSugar;
        16: aload_0
        17: invokespecial #126                // Method java/lang/Object."<init>":()V
        20: return
      StackMapTable: number_of_entries = 1
        frame_type = 11 /* same */
      LineNumberTable:
        line 404: 0
        line 512: 16
        line 404: 20
      LocalVariableTable:
        Start  Length  Slot  Name   Signature
            0      21     0  this   Lorg/scalatest/time/SpanSugar$FloatingGrainOfTime;
            0      21     1 $outer   Lorg/scalatest/time/SpanSugar;
            0      21     2 value   D
    MethodParameters:
      Name                           Flags
      $outer                         final synthetic
      value                          final
}
InnerClasses:
  public #8= #2 of #7;                    // FloatingGrainOfTime=class org/scalatest/time/SpanSugar$FloatingGrainOfTime of class org/scalatest/time/SpanSugar
SourceFile: "SpanSugar.scala"
  ScalaInlineInfo: length = 0x59 (unknown attribute)
   01 00 00 11 00 7A 00 7B 00 00 6A 00 0E 00 00 70
   00 0E 00 00 5E 00 0E 00 00 64 00 0E 00 00 28 00
   0E 00 00 2E 00 0E 00 00 40 00 0E 00 00 34 00 0E
   00 00 3A 00 0E 00 00 52 00 0E 00 00 58 00 0E 00
   00 0D 00 0E 00 00 22 00 0E 00 00 76 00 77 00 00
   46 00 0E 00 00 4C 00 0E 00
  Scala: length = 0x0 (unknown attribute)

