Classfile /Users/mw/Projects/slang-braindump/.jar/jar8/assemble/slang-braindump/assemble/content/org/scalatest/time/SpanSugar$.class
  Last modified May 29, 2022; size 2337 bytes
  SHA-256 checksum 5642fd4525d1736c35e91958c128c2a5d047d3340b0b5d82617c45772f54191c
  Compiled from "SpanSugar.scala"
public final class org.scalatest.time.SpanSugar$ implements org.scalatest.time.SpanSugar
  minor version: 0
  major version: 52
  flags: (0x0031) ACC_PUBLIC, ACC_FINAL, ACC_SUPER
  this_class: #2                          // org/scalatest/time/SpanSugar$
  super_class: #4                         // java/lang/Object
  interfaces: 1, fields: 2, methods: 8, attributes: 4
Constant pool:
   #1 = Utf8               org/scalatest/time/SpanSugar$
   #2 = Class              #1             // org/scalatest/time/SpanSugar$
   #3 = Utf8               java/lang/Object
   #4 = Class              #3             // java/lang/Object
   #5 = Utf8               org/scalatest/time/SpanSugar
   #6 = Class              #5             // org/scalatest/time/SpanSugar
   #7 = Utf8               SpanSugar.scala
   #8 = Utf8               org/scalatest/time/SpanSugar$FloatingGrainOfTime
   #9 = Class              #8             // org/scalatest/time/SpanSugar$FloatingGrainOfTime
  #10 = Utf8               FloatingGrainOfTime
  #11 = Utf8               org/scalatest/time/SpanSugar$GrainOfTime
  #12 = Class              #11            // org/scalatest/time/SpanSugar$GrainOfTime
  #13 = Utf8               GrainOfTime
  #14 = Utf8               scala/languageFeature$postfixOps
  #15 = Class              #14            // scala/languageFeature$postfixOps
  #16 = Utf8               scala/languageFeature
  #17 = Class              #16            // scala/languageFeature
  #18 = Utf8               postfixOps
  #19 = Utf8               MODULE$
  #20 = Utf8               Lorg/scalatest/time/SpanSugar$;
  #21 = Utf8               Lscala/languageFeature$postfixOps;
  #22 = Utf8               <clinit>
  #23 = Utf8               ()V
  #24 = Utf8               <init>
  #25 = NameAndType        #24:#23        // "<init>":()V
  #26 = Methodref          #2.#25         // org/scalatest/time/SpanSugar$."<init>":()V
  #27 = NameAndType        #19:#20        // MODULE$:Lorg/scalatest/time/SpanSugar$;
  #28 = Fieldref           #2.#27         // org/scalatest/time/SpanSugar$.MODULE$:Lorg/scalatest/time/SpanSugar$;
  #29 = Utf8               $init$
  #30 = Utf8               (Lorg/scalatest/time/SpanSugar;)V
  #31 = NameAndType        #29:#30        // $init$:(Lorg/scalatest/time/SpanSugar;)V
  #32 = InterfaceMethodref #6.#31         // org/scalatest/time/SpanSugar.$init$:(Lorg/scalatest/time/SpanSugar;)V
  #33 = Utf8               convertIntToGrainOfTime
  #34 = Utf8               (I)Lorg/scalatest/time/SpanSugar$GrainOfTime;
  #35 = Utf8               i
  #36 = Utf8               convertIntToGrainOfTime$
  #37 = Utf8               (Lorg/scalatest/time/SpanSugar;I)Lorg/scalatest/time/SpanSugar$GrainOfTime;
  #38 = NameAndType        #36:#37        // convertIntToGrainOfTime$:(Lorg/scalatest/time/SpanSugar;I)Lorg/scalatest/time/SpanSugar$GrainOfTime;
  #39 = InterfaceMethodref #6.#38         // org/scalatest/time/SpanSugar.convertIntToGrainOfTime$:(Lorg/scalatest/time/SpanSugar;I)Lorg/scalatest/time/SpanSugar$GrainOfTime;
  #40 = Utf8               this
  #41 = Utf8               I
  #42 = Utf8               convertLongToGrainOfTime
  #43 = Utf8               (J)Lorg/scalatest/time/SpanSugar$GrainOfTime;
  #44 = Utf8               convertLongToGrainOfTime$
  #45 = Utf8               (Lorg/scalatest/time/SpanSugar;J)Lorg/scalatest/time/SpanSugar$GrainOfTime;
  #46 = NameAndType        #44:#45        // convertLongToGrainOfTime$:(Lorg/scalatest/time/SpanSugar;J)Lorg/scalatest/time/SpanSugar$GrainOfTime;
  #47 = InterfaceMethodref #6.#46         // org/scalatest/time/SpanSugar.convertLongToGrainOfTime$:(Lorg/scalatest/time/SpanSugar;J)Lorg/scalatest/time/SpanSugar$GrainOfTime;
  #48 = Utf8               J
  #49 = Utf8               convertFloatToGrainOfTime
  #50 = Utf8               (F)Lorg/scalatest/time/SpanSugar$FloatingGrainOfTime;
  #51 = Utf8               f
  #52 = Utf8               convertFloatToGrainOfTime$
  #53 = Utf8               (Lorg/scalatest/time/SpanSugar;F)Lorg/scalatest/time/SpanSugar$FloatingGrainOfTime;
  #54 = NameAndType        #52:#53        // convertFloatToGrainOfTime$:(Lorg/scalatest/time/SpanSugar;F)Lorg/scalatest/time/SpanSugar$FloatingGrainOfTime;
  #55 = InterfaceMethodref #6.#54         // org/scalatest/time/SpanSugar.convertFloatToGrainOfTime$:(Lorg/scalatest/time/SpanSugar;F)Lorg/scalatest/time/SpanSugar$FloatingGrainOfTime;
  #56 = Utf8               F
  #57 = Utf8               convertDoubleToGrainOfTime
  #58 = Utf8               (D)Lorg/scalatest/time/SpanSugar$FloatingGrainOfTime;
  #59 = Utf8               d
  #60 = Utf8               convertDoubleToGrainOfTime$
  #61 = Utf8               (Lorg/scalatest/time/SpanSugar;D)Lorg/scalatest/time/SpanSugar$FloatingGrainOfTime;
  #62 = NameAndType        #60:#61        // convertDoubleToGrainOfTime$:(Lorg/scalatest/time/SpanSugar;D)Lorg/scalatest/time/SpanSugar$FloatingGrainOfTime;
  #63 = InterfaceMethodref #6.#62         // org/scalatest/time/SpanSugar.convertDoubleToGrainOfTime$:(Lorg/scalatest/time/SpanSugar;D)Lorg/scalatest/time/SpanSugar$FloatingGrainOfTime;
  #64 = Utf8               D
  #65 = Utf8               ()Lscala/languageFeature$postfixOps;
  #66 = NameAndType        #18:#21        // postfixOps:Lscala/languageFeature$postfixOps;
  #67 = Fieldref           #2.#66         // org/scalatest/time/SpanSugar$.postfixOps:Lscala/languageFeature$postfixOps;
  #68 = Utf8               org$scalatest$time$SpanSugar$_setter_$postfixOps_$eq
  #69 = Utf8               (Lscala/languageFeature$postfixOps;)V
  #70 = Utf8               x$1
  #71 = Methodref          #4.#25         // java/lang/Object."<init>":()V
  #72 = Utf8               Code
  #73 = Utf8               LineNumberTable
  #74 = Utf8               LocalVariableTable
  #75 = Utf8               MethodParameters
  #76 = Utf8               InnerClasses
  #77 = Utf8               SourceFile
  #78 = Utf8               ScalaInlineInfo
  #79 = Utf8               Scala
{
  public static final org.scalatest.time.SpanSugar$ MODULE$;
    descriptor: Lorg/scalatest/time/SpanSugar$;
    flags: (0x0019) ACC_PUBLIC, ACC_STATIC, ACC_FINAL

  private static scala.languageFeature$postfixOps postfixOps;
    descriptor: Lscala/languageFeature$postfixOps;
    flags: (0x000a) ACC_PRIVATE, ACC_STATIC

  public static {};
    descriptor: ()V
    flags: (0x0009) ACC_PUBLIC, ACC_STATIC
    Code:
      stack=2, locals=0, args_size=0
         0: new           #2                  // class org/scalatest/time/SpanSugar$
         3: dup
         4: invokespecial #26                 // Method "<init>":()V
         7: putstatic     #28                 // Field MODULE$:Lorg/scalatest/time/SpanSugar$;
        10: getstatic     #28                 // Field MODULE$:Lorg/scalatest/time/SpanSugar$;
        13: invokestatic  #32                 // InterfaceMethod org/scalatest/time/SpanSugar.$init$:(Lorg/scalatest/time/SpanSugar;)V
        16: return
      LineNumberTable:
        line 571: 0

  public org.scalatest.time.SpanSugar$GrainOfTime convertIntToGrainOfTime(int);
    descriptor: (I)Lorg/scalatest/time/SpanSugar$GrainOfTime;
    flags: (0x0001) ACC_PUBLIC
    Code:
      stack=2, locals=2, args_size=2
         0: aload_0
         1: iload_1
         2: invokestatic  #39                 // InterfaceMethod org/scalatest/time/SpanSugar.convertIntToGrainOfTime$:(Lorg/scalatest/time/SpanSugar;I)Lorg/scalatest/time/SpanSugar$GrainOfTime;
         5: areturn
      LineNumberTable:
        line 571: 0
      LocalVariableTable:
        Start  Length  Slot  Name   Signature
            0       6     0  this   Lorg/scalatest/time/SpanSugar$;
            0       6     1     i   I
    MethodParameters:
      Name                           Flags
      i                              final

  public org.scalatest.time.SpanSugar$GrainOfTime convertLongToGrainOfTime(long);
    descriptor: (J)Lorg/scalatest/time/SpanSugar$GrainOfTime;
    flags: (0x0001) ACC_PUBLIC
    Code:
      stack=3, locals=3, args_size=2
         0: aload_0
         1: lload_1
         2: invokestatic  #47                 // InterfaceMethod org/scalatest/time/SpanSugar.convertLongToGrainOfTime$:(Lorg/scalatest/time/SpanSugar;J)Lorg/scalatest/time/SpanSugar$GrainOfTime;
         5: areturn
      LineNumberTable:
        line 571: 0
      LocalVariableTable:
        Start  Length  Slot  Name   Signature
            0       6     0  this   Lorg/scalatest/time/SpanSugar$;
            0       6     1     i   J
    MethodParameters:
      Name                           Flags
      i                              final

  public org.scalatest.time.SpanSugar$FloatingGrainOfTime convertFloatToGrainOfTime(float);
    descriptor: (F)Lorg/scalatest/time/SpanSugar$FloatingGrainOfTime;
    flags: (0x0001) ACC_PUBLIC
    Code:
      stack=2, locals=2, args_size=2
         0: aload_0
         1: fload_1
         2: invokestatic  #55                 // InterfaceMethod org/scalatest/time/SpanSugar.convertFloatToGrainOfTime$:(Lorg/scalatest/time/SpanSugar;F)Lorg/scalatest/time/SpanSugar$FloatingGrainOfTime;
         5: areturn
      LineNumberTable:
        line 571: 0
      LocalVariableTable:
        Start  Length  Slot  Name   Signature
            0       6     0  this   Lorg/scalatest/time/SpanSugar$;
            0       6     1     f   F
    MethodParameters:
      Name                           Flags
      f                              final

  public org.scalatest.time.SpanSugar$FloatingGrainOfTime convertDoubleToGrainOfTime(double);
    descriptor: (D)Lorg/scalatest/time/SpanSugar$FloatingGrainOfTime;
    flags: (0x0001) ACC_PUBLIC
    Code:
      stack=3, locals=3, args_size=2
         0: aload_0
         1: dload_1
         2: invokestatic  #63                 // InterfaceMethod org/scalatest/time/SpanSugar.convertDoubleToGrainOfTime$:(Lorg/scalatest/time/SpanSugar;D)Lorg/scalatest/time/SpanSugar$FloatingGrainOfTime;
         5: areturn
      LineNumberTable:
        line 571: 0
      LocalVariableTable:
        Start  Length  Slot  Name   Signature
            0       6     0  this   Lorg/scalatest/time/SpanSugar$;
            0       6     1     d   D
    MethodParameters:
      Name                           Flags
      d                              final

  public scala.languageFeature$postfixOps postfixOps();
    descriptor: ()Lscala/languageFeature$postfixOps;
    flags: (0x0001) ACC_PUBLIC
    Code:
      stack=1, locals=1, args_size=1
         0: getstatic     #67                 // Field postfixOps:Lscala/languageFeature$postfixOps;
         3: areturn
      LineNumberTable:
        line 571: 0
      LocalVariableTable:
        Start  Length  Slot  Name   Signature
            0       4     0  this   Lorg/scalatest/time/SpanSugar$;

  public void org$scalatest$time$SpanSugar$_setter_$postfixOps_$eq(scala.languageFeature$postfixOps);
    descriptor: (Lscala/languageFeature$postfixOps;)V
    flags: (0x0001) ACC_PUBLIC
    Code:
      stack=1, locals=2, args_size=2
         0: aload_1
         1: putstatic     #67                 // Field postfixOps:Lscala/languageFeature$postfixOps;
         4: return
      LineNumberTable:
        line 571: 0
      LocalVariableTable:
        Start  Length  Slot  Name   Signature
            0       5     0  this   Lorg/scalatest/time/SpanSugar$;
            0       5     1   x$1   Lscala/languageFeature$postfixOps;
    MethodParameters:
      Name                           Flags
      x$1                            final

  private org.scalatest.time.SpanSugar$();
    descriptor: ()V
    flags: (0x0002) ACC_PRIVATE
    Code:
      stack=1, locals=1, args_size=1
         0: aload_0
         1: invokespecial #71                 // Method java/lang/Object."<init>":()V
         4: return
      LineNumberTable:
        line 571: 0
      LocalVariableTable:
        Start  Length  Slot  Name   Signature
            0       5     0  this   Lorg/scalatest/time/SpanSugar$;
}
InnerClasses:
  public #10= #9 of #6;                   // FloatingGrainOfTime=class org/scalatest/time/SpanSugar$FloatingGrainOfTime of class org/scalatest/time/SpanSugar
  public #13= #12 of #6;                  // GrainOfTime=class org/scalatest/time/SpanSugar$GrainOfTime of class org/scalatest/time/SpanSugar
  public static #18= #15 of #17;          // postfixOps=class scala/languageFeature$postfixOps of class scala/languageFeature
SourceFile: "SpanSugar.scala"
  ScalaInlineInfo: length = 0x27 (unknown attribute)
   01 01 00 07 00 18 00 17 01 00 39 00 3A 01 00 31
   00 32 01 00 21 00 22 01 00 2A 00 2B 01 00 44 00
   45 01 00 12 00 41 01
  Scala: length = 0x0 (unknown attribute)

