Classfile /Users/mw/Projects/slang-braindump/.jar/jar8/assemble/slang-braindump/assemble/content/org/scalatest/time/SpanSugar.class
  Last modified May 29, 2022; size 3850 bytes
  SHA-256 checksum 54b077b1b957a45647b352b5116cb0bc738826fd64de797acb7237cbac2fc8af
  Compiled from "SpanSugar.scala"
public interface org.scalatest.time.SpanSugar
  minor version: 0
  major version: 52
  flags: (0x0601) ACC_PUBLIC, ACC_INTERFACE, ACC_ABSTRACT
  this_class: #2                          // org/scalatest/time/SpanSugar
  super_class: #4                         // java/lang/Object
  interfaces: 0, fields: 0, methods: 11, attributes: 5
Constant pool:
   #1 = Utf8               org/scalatest/time/SpanSugar
   #2 = Class              #1             // org/scalatest/time/SpanSugar
   #3 = Utf8               java/lang/Object
   #4 = Class              #3             // java/lang/Object
   #5 = Utf8               SpanSugar.scala
   #6 = Utf8               Lscala/reflect/ScalaSignature;
   #7 = Utf8               bytes
   #8 = Utf8               \u0006\u0005\u0005eaa\u0002\u00180!\u0003\r\tA\u000e\u0005\u0006{\u0001!\tA\u0010\u0005\b\u0005\u0002\u0011\r\u0011b\u0001D\r\u0011Y\u0005\u0001\u0001\'\t\u00115\u001b!\u0011!Q\u0001\n9CQ!U\u0002\u0005\u0002ICQAV\u0002\u0005\u0002]CQ\u0001X\u0002\u0005\u0002]CQ!X\u0002\u0005\u0002]CQAX\u0002\u0005\u0002]CQaX\u0002\u0005\u0002]CQ\u0001Y\u0002\u0005\u0002]CQ!Y\u0002\u0005\u0002]CQAY\u0002\u0005\u0002]CQaY\u0002\u0005\u0002]CQ\u0001Z\u0002\u0005\u0002]CQ!Z\u0002\u0005\u0002]CQAZ\u0002\u0005\u0002]CQaZ\u0002\u0005\u0002]CQ\u0001[\u0002\u0005\u0002]CQ![\u0002\u0005\u0002]3AA\u001b\u0001\u0001W\"AQ*\u0006B\u0001B\u0003%A\u000eC\u0003R+\u0011\u0005q\u000eC\u0003W+\u0011\u0005q\u000bC\u0003]+\u0011\u0005q\u000bC\u0003^+\u0011\u0005q\u000bC\u0003_+\u0011\u0005q\u000bC\u0003`+\u0011\u0005q\u000bC\u0003a+\u0011\u0005q\u000bC\u0003b+\u0011\u0005q\u000bC\u0003c+\u0011\u0005q\u000bC\u0003d+\u0011\u0005q\u000bC\u0003e+\u0011\u0005q\u000bC\u0003f+\u0011\u0005q\u000bC\u0003g+\u0011\u0005q\u000bC\u0003h+\u0011\u0005q\u000bC\u0003i+\u0011\u0005q\u000bC\u0003j+\u0011\u0005q\u000bC\u0003s\u0001\u0011\r1\u000fC\u0003z\u0001\u0011\r!\u0010C\u0003}\u0001\u0011\rQ\u0010C\u0004\u0002\b\u0001!\u0019!!\u0003\b\u000f\u0005=q\u0006#\u0001\u0002\u0012\u00191af\fE\u0001\u0003\'Aa!\u0015\u0017\u0005\u0002\u0005]!!C*qC:\u001cVoZ1s\u0015\t\u0001\u0014\'\u0001\u0003uS6,\'B\u0001\u001a4\u0003%\u00198-\u00197bi\u0016\u001cHOC\u00015\u0003\ry\'oZ\u0002\u0001\'\t\u0001q\u0007\u0005\u00029w5\t\u0011HC\u0001;\u0003\u0015\u00198-\u00197b\u0013\ta\u0014H\u0001\u0004B]f\u0014VMZ\u0001\u0007I%t\u0017\u000e\u001e\u0013\u0015\u0003}\u0002\"\u0001\u000f!\n\u0005\u0005K$\u0001B+oSR\f!\u0002]8ti\u001aL\u0007p\u00149t+\u0005!\u0005CA#I\u001d\tAd)\u0003\u0002Hs\u0005yA.\u00198hk\u0006<WMR3biV\u0014X-\u0003\u0002J\u0015\nQ\u0001o\\:uM&Dx\n]:\u000b\u0005\u001dK$aC$sC&twJ\u001a+j[\u0016\u001c\"aA\u001c\u0002\u000bY\fG.^3\u0011\u0005az\u0015B\u0001):\u0005\u0011auN\\4\u0002\rqJg.\u001b;?)\t\u0019V\u000b\u0005\u0002U\u00075\t\u0001\u0001C\u0003N\u000b\u0001\u0007a*\u0001\u0006oC:|7/Z2p]\u0012,\u0012\u0001\u0017\t\u00033jk\u0011aL\u0005\u00037>\u0012Aa\u00159b]\u0006Ya.\u00198pg\u0016\u001cwN\u001c3t\u0003-i\u0017n\u0019:pg\u0016\u001cwN\u001c3\u0002\u00195L7M]8tK\u000e|g\u000eZ:\u0002\u00175LG\u000e\\5tK\u000e|g\u000eZ\u0001\r[&dG.[:fG>tGm]\u0001\u0007[&dG.[:\u0002\rM,7m\u001c8e\u0003\u001d\u0019XmY8oIN\fa!\\5okR,\u0017aB7j]V$Xm]\u0001\u0005Q>,(/A\u0003i_V\u00148/A\u0002eCf\fA\u0001Z1zg\n\u0019b\t\\8bi&twm\u0012:bS:|e\rV5nKN\u0011Qc\u000e\t\u0003q5L!A\\\u001d\u0003\r\u0011{WO\u00197f)\t\u0001\u0018\u000f\u0005\u0002U+!)Qj\u0006a\u0001Y\u000692m\u001c8wKJ$\u0018J\u001c;U_\u001e\u0013\u0018-\u001b8PMRKW.\u001a\u000b\u0003\'RDQ!^\u0014A\u0002Y\f\u0011!\u001b\t\u0003q]L!\u0001_\u001d\u0003\u0007%sG/\u0001\rd_:4XM\u001d;M_:<Gk\\$sC&twJ\u001a+j[\u0016$\"aU>\t\u000bUD\u0003\u0019\u0001(\u00023\r|gN^3si\u001acw.\u0019;U_\u001e\u0013\u0018-\u001b8PMRKW.\u001a\u000b\u0003azDaa`\u0015A\u0002\u0005\u0005\u0011!\u00014\u0011\u0007a\n\u0019!C\u0002\u0002\u0006e\u0012QA\u00127pCR\f!dY8om\u0016\u0014H\u000fR8vE2,Gk\\$sC&twJ\u001a+j[\u0016$2\u0001]A\u0006\u0011\u0019\tiA\u000ba\u0001Y\u0006\tA-A\u0005Ta\u0006t7+^4beB\u0011\u0011\fL\n\u0005Y]\n)\u0002\u0005\u0002Z\u0001Q\u0011\u0011\u0011\u0003
   #9 = Utf8               org/scalatest/time/SpanSugar$FloatingGrainOfTime
  #10 = Class              #9             // org/scalatest/time/SpanSugar$FloatingGrainOfTime
  #11 = Utf8               FloatingGrainOfTime
  #12 = Utf8               org/scalatest/time/SpanSugar$GrainOfTime
  #13 = Class              #12            // org/scalatest/time/SpanSugar$GrainOfTime
  #14 = Utf8               GrainOfTime
  #15 = Utf8               scala/languageFeature$postfixOps
  #16 = Class              #15            // scala/languageFeature$postfixOps
  #17 = Utf8               scala/languageFeature
  #18 = Class              #17            // scala/languageFeature
  #19 = Utf8               postfixOps
  #20 = Utf8               org$scalatest$time$SpanSugar$_setter_$postfixOps_$eq
  #21 = Utf8               (Lscala/languageFeature$postfixOps;)V
  #22 = Utf8               x$1
  #23 = Utf8               ()Lscala/languageFeature$postfixOps;
  #24 = Utf8               convertIntToGrainOfTime$
  #25 = Utf8               (Lorg/scalatest/time/SpanSugar;I)Lorg/scalatest/time/SpanSugar$GrainOfTime;
  #26 = Utf8               $this
  #27 = Utf8               i
  #28 = Utf8               convertIntToGrainOfTime
  #29 = Utf8               (I)Lorg/scalatest/time/SpanSugar$GrainOfTime;
  #30 = NameAndType        #28:#29        // convertIntToGrainOfTime:(I)Lorg/scalatest/time/SpanSugar$GrainOfTime;
  #31 = InterfaceMethodref #2.#30         // org/scalatest/time/SpanSugar.convertIntToGrainOfTime:(I)Lorg/scalatest/time/SpanSugar$GrainOfTime;
  #32 = Utf8               Lorg/scalatest/time/SpanSugar;
  #33 = Utf8               I
  #34 = Utf8               <init>
  #35 = Utf8               (Lorg/scalatest/time/SpanSugar;J)V
  #36 = NameAndType        #34:#35        // "<init>":(Lorg/scalatest/time/SpanSugar;J)V
  #37 = Methodref          #13.#36        // org/scalatest/time/SpanSugar$GrainOfTime."<init>":(Lorg/scalatest/time/SpanSugar;J)V
  #38 = Utf8               this
  #39 = Utf8               convertLongToGrainOfTime$
  #40 = Utf8               (Lorg/scalatest/time/SpanSugar;J)Lorg/scalatest/time/SpanSugar$GrainOfTime;
  #41 = Utf8               convertLongToGrainOfTime
  #42 = Utf8               (J)Lorg/scalatest/time/SpanSugar$GrainOfTime;
  #43 = NameAndType        #41:#42        // convertLongToGrainOfTime:(J)Lorg/scalatest/time/SpanSugar$GrainOfTime;
  #44 = InterfaceMethodref #2.#43         // org/scalatest/time/SpanSugar.convertLongToGrainOfTime:(J)Lorg/scalatest/time/SpanSugar$GrainOfTime;
  #45 = Utf8               J
  #46 = Utf8               convertFloatToGrainOfTime$
  #47 = Utf8               (Lorg/scalatest/time/SpanSugar;F)Lorg/scalatest/time/SpanSugar$FloatingGrainOfTime;
  #48 = Utf8               f
  #49 = Utf8               convertFloatToGrainOfTime
  #50 = Utf8               (F)Lorg/scalatest/time/SpanSugar$FloatingGrainOfTime;
  #51 = NameAndType        #49:#50        // convertFloatToGrainOfTime:(F)Lorg/scalatest/time/SpanSugar$FloatingGrainOfTime;
  #52 = InterfaceMethodref #2.#51         // org/scalatest/time/SpanSugar.convertFloatToGrainOfTime:(F)Lorg/scalatest/time/SpanSugar$FloatingGrainOfTime;
  #53 = Utf8               F
  #54 = Utf8               (Lorg/scalatest/time/SpanSugar;D)V
  #55 = NameAndType        #34:#54        // "<init>":(Lorg/scalatest/time/SpanSugar;D)V
  #56 = Methodref          #10.#55        // org/scalatest/time/SpanSugar$FloatingGrainOfTime."<init>":(Lorg/scalatest/time/SpanSugar;D)V
  #57 = Utf8               convertDoubleToGrainOfTime$
  #58 = Utf8               (Lorg/scalatest/time/SpanSugar;D)Lorg/scalatest/time/SpanSugar$FloatingGrainOfTime;
  #59 = Utf8               d
  #60 = Utf8               convertDoubleToGrainOfTime
  #61 = Utf8               (D)Lorg/scalatest/time/SpanSugar$FloatingGrainOfTime;
  #62 = NameAndType        #60:#61        // convertDoubleToGrainOfTime:(D)Lorg/scalatest/time/SpanSugar$FloatingGrainOfTime;
  #63 = InterfaceMethodref #2.#62         // org/scalatest/time/SpanSugar.convertDoubleToGrainOfTime:(D)Lorg/scalatest/time/SpanSugar$FloatingGrainOfTime;
  #64 = Utf8               D
  #65 = Utf8               $init$
  #66 = Utf8               (Lorg/scalatest/time/SpanSugar;)V
  #67 = Utf8               scala/language$
  #68 = Class              #67            // scala/language$
  #69 = Utf8               MODULE$
  #70 = Utf8               Lscala/language$;
  #71 = NameAndType        #69:#70        // MODULE$:Lscala/language$;
  #72 = Fieldref           #68.#71        // scala/language$.MODULE$:Lscala/language$;
  #73 = NameAndType        #19:#23        // postfixOps:()Lscala/languageFeature$postfixOps;
  #74 = Methodref          #68.#73        // scala/language$.postfixOps:()Lscala/languageFeature$postfixOps;
  #75 = NameAndType        #20:#21        // org$scalatest$time$SpanSugar$_setter_$postfixOps_$eq:(Lscala/languageFeature$postfixOps;)V
  #76 = InterfaceMethodref #2.#75         // org/scalatest/time/SpanSugar.org$scalatest$time$SpanSugar$_setter_$postfixOps_$eq:(Lscala/languageFeature$postfixOps;)V
  #77 = Utf8               MethodParameters
  #78 = Utf8               Code
  #79 = Utf8               LineNumberTable
  #80 = Utf8               LocalVariableTable
  #81 = Utf8               InnerClasses
  #82 = Utf8               SourceFile
  #83 = Utf8               RuntimeVisibleAnnotations
  #84 = Utf8               ScalaInlineInfo
  #85 = Utf8               ScalaSig
{
  public abstract void org$scalatest$time$SpanSugar$_setter_$postfixOps_$eq(scala.languageFeature$postfixOps);
    descriptor: (Lscala/languageFeature$postfixOps;)V
    flags: (0x0401) ACC_PUBLIC, ACC_ABSTRACT
    MethodParameters:
      Name                           Flags
      x$1                            final

  public abstract scala.languageFeature$postfixOps postfixOps();
    descriptor: ()Lscala/languageFeature$postfixOps;
    flags: (0x0401) ACC_PUBLIC, ACC_ABSTRACT

  public static org.scalatest.time.SpanSugar$GrainOfTime convertIntToGrainOfTime$(org.scalatest.time.SpanSugar, int);
    descriptor: (Lorg/scalatest/time/SpanSugar;I)Lorg/scalatest/time/SpanSugar$GrainOfTime;
    flags: (0x1009) ACC_PUBLIC, ACC_STATIC, ACC_SYNTHETIC
    Code:
      stack=2, locals=2, args_size=2
         0: aload_0
         1: iload_1
         2: invokespecial #31                 // InterfaceMethod convertIntToGrainOfTime:(I)Lorg/scalatest/time/SpanSugar$GrainOfTime;
         5: areturn
      LineNumberTable:
        line 520: 0
      LocalVariableTable:
        Start  Length  Slot  Name   Signature
            0       6     0 $this   Lorg/scalatest/time/SpanSugar;
            0       6     1     i   I
    MethodParameters:
      Name                           Flags
      $this                          final synthetic
      i                              final

  public default org.scalatest.time.SpanSugar$GrainOfTime convertIntToGrainOfTime(int);
    descriptor: (I)Lorg/scalatest/time/SpanSugar$GrainOfTime;
    flags: (0x0001) ACC_PUBLIC
    Code:
      stack=5, locals=2, args_size=2
         0: new           #13                 // class org/scalatest/time/SpanSugar$GrainOfTime
         3: dup
         4: aload_0
         5: iload_1
         6: i2l
         7: invokespecial #37                 // Method org/scalatest/time/SpanSugar$GrainOfTime."<init>":(Lorg/scalatest/time/SpanSugar;J)V
        10: areturn
      LineNumberTable:
        line 520: 0
      LocalVariableTable:
        Start  Length  Slot  Name   Signature
            0      11     0  this   Lorg/scalatest/time/SpanSugar;
            0      11     1     i   I
    MethodParameters:
      Name                           Flags
      i                              final

  public static org.scalatest.time.SpanSugar$GrainOfTime convertLongToGrainOfTime$(org.scalatest.time.SpanSugar, long);
    descriptor: (Lorg/scalatest/time/SpanSugar;J)Lorg/scalatest/time/SpanSugar$GrainOfTime;
    flags: (0x1009) ACC_PUBLIC, ACC_STATIC, ACC_SYNTHETIC
    Code:
      stack=3, locals=3, args_size=2
         0: aload_0
         1: lload_1
         2: invokespecial #44                 // InterfaceMethod convertLongToGrainOfTime:(J)Lorg/scalatest/time/SpanSugar$GrainOfTime;
         5: areturn
      LineNumberTable:
        line 528: 0
      LocalVariableTable:
        Start  Length  Slot  Name   Signature
            0       6     0 $this   Lorg/scalatest/time/SpanSugar;
            0       6     1     i   J
    MethodParameters:
      Name                           Flags
      $this                          final synthetic
      i                              final

  public default org.scalatest.time.SpanSugar$GrainOfTime convertLongToGrainOfTime(long);
    descriptor: (J)Lorg/scalatest/time/SpanSugar$GrainOfTime;
    flags: (0x0001) ACC_PUBLIC
    Code:
      stack=5, locals=3, args_size=2
         0: new           #13                 // class org/scalatest/time/SpanSugar$GrainOfTime
         3: dup
         4: aload_0
         5: lload_1
         6: invokespecial #37                 // Method org/scalatest/time/SpanSugar$GrainOfTime."<init>":(Lorg/scalatest/time/SpanSugar;J)V
         9: areturn
      LineNumberTable:
        line 528: 0
      LocalVariableTable:
        Start  Length  Slot  Name   Signature
            0      10     0  this   Lorg/scalatest/time/SpanSugar;
            0      10     1     i   J
    MethodParameters:
      Name                           Flags
      i                              final

  public static org.scalatest.time.SpanSugar$FloatingGrainOfTime convertFloatToGrainOfTime$(org.scalatest.time.SpanSugar, float);
    descriptor: (Lorg/scalatest/time/SpanSugar;F)Lorg/scalatest/time/SpanSugar$FloatingGrainOfTime;
    flags: (0x1009) ACC_PUBLIC, ACC_STATIC, ACC_SYNTHETIC
    Code:
      stack=2, locals=2, args_size=2
         0: aload_0
         1: fload_1
         2: invokespecial #52                 // InterfaceMethod convertFloatToGrainOfTime:(F)Lorg/scalatest/time/SpanSugar$FloatingGrainOfTime;
         5: areturn
      LineNumberTable:
        line 537: 0
      LocalVariableTable:
        Start  Length  Slot  Name   Signature
            0       6     0 $this   Lorg/scalatest/time/SpanSugar;
            0       6     1     f   F
    MethodParameters:
      Name                           Flags
      $this                          final synthetic
      f                              final

  public default org.scalatest.time.SpanSugar$FloatingGrainOfTime convertFloatToGrainOfTime(float);
    descriptor: (F)Lorg/scalatest/time/SpanSugar$FloatingGrainOfTime;
    flags: (0x0001) ACC_PUBLIC
    Code:
      stack=5, locals=2, args_size=2
         0: new           #10                 // class org/scalatest/time/SpanSugar$FloatingGrainOfTime
         3: dup
         4: aload_0
         5: fload_1
         6: f2d
         7: invokespecial #56                 // Method org/scalatest/time/SpanSugar$FloatingGrainOfTime."<init>":(Lorg/scalatest/time/SpanSugar;D)V
        10: areturn
      LineNumberTable:
        line 537: 0
      LocalVariableTable:
        Start  Length  Slot  Name   Signature
            0      11     0  this   Lorg/scalatest/time/SpanSugar;
            0      11     1     f   F
    MethodParameters:
      Name                           Flags
      f                              final

  public static org.scalatest.time.SpanSugar$FloatingGrainOfTime convertDoubleToGrainOfTime$(org.scalatest.time.SpanSugar, double);
    descriptor: (Lorg/scalatest/time/SpanSugar;D)Lorg/scalatest/time/SpanSugar$FloatingGrainOfTime;
    flags: (0x1009) ACC_PUBLIC, ACC_STATIC, ACC_SYNTHETIC
    Code:
      stack=3, locals=3, args_size=2
         0: aload_0
         1: dload_1
         2: invokespecial #63                 // InterfaceMethod convertDoubleToGrainOfTime:(D)Lorg/scalatest/time/SpanSugar$FloatingGrainOfTime;
         5: areturn
      LineNumberTable:
        line 545: 0
      LocalVariableTable:
        Start  Length  Slot  Name   Signature
            0       6     0 $this   Lorg/scalatest/time/SpanSugar;
            0       6     1     d   D
    MethodParameters:
      Name                           Flags
      $this                          final synthetic
      d                              final

  public default org.scalatest.time.SpanSugar$FloatingGrainOfTime convertDoubleToGrainOfTime(double);
    descriptor: (D)Lorg/scalatest/time/SpanSugar$FloatingGrainOfTime;
    flags: (0x0001) ACC_PUBLIC
    Code:
      stack=5, locals=3, args_size=2
         0: new           #10                 // class org/scalatest/time/SpanSugar$FloatingGrainOfTime
         3: dup
         4: aload_0
         5: dload_1
         6: invokespecial #56                 // Method org/scalatest/time/SpanSugar$FloatingGrainOfTime."<init>":(Lorg/scalatest/time/SpanSugar;D)V
         9: areturn
      LineNumberTable:
        line 545: 0
      LocalVariableTable:
        Start  Length  Slot  Name   Signature
            0      10     0  this   Lorg/scalatest/time/SpanSugar;
            0      10     1     d   D
    MethodParameters:
      Name                           Flags
      d                              final

  public static void $init$(org.scalatest.time.SpanSugar);
    descriptor: (Lorg/scalatest/time/SpanSugar;)V
    flags: (0x0009) ACC_PUBLIC, ACC_STATIC
    Code:
      stack=2, locals=1, args_size=1
         0: aload_0
         1: getstatic     #72                 // Field scala/language$.MODULE$:Lscala/language$;
         4: invokevirtual #74                 // Method scala/language$.postfixOps:()Lscala/languageFeature$postfixOps;
         7: invokeinterface #76,  2           // InterfaceMethod org$scalatest$time$SpanSugar$_setter_$postfixOps_$eq:(Lscala/languageFeature$postfixOps;)V
        12: return
      LineNumberTable:
        line 282: 0
        line 280: 12
      LocalVariableTable:
        Start  Length  Slot  Name   Signature
            0      13     0 $this   Lorg/scalatest/time/SpanSugar;
    MethodParameters:
      Name                           Flags
      $this                          final synthetic
}
InnerClasses:
  public #11= #10 of #2;                  // FloatingGrainOfTime=class org/scalatest/time/SpanSugar$FloatingGrainOfTime of class org/scalatest/time/SpanSugar
  public #14= #13 of #2;                  // GrainOfTime=class org/scalatest/time/SpanSugar$GrainOfTime of class org/scalatest/time/SpanSugar
  public static #19= #16 of #18;          // postfixOps=class scala/languageFeature$postfixOps of class scala/languageFeature
SourceFile: "SpanSugar.scala"
RuntimeVisibleAnnotations:
  0: #6(#7=s#8)
    scala.reflect.ScalaSignature(
      bytes="\u0006\u0005\u0005eaa\u0002\u00180!\u0003\r\tA\u000e\u0005\u0006{\u0001!\tA\u0010\u0005\b\u0005\u0002\u0011\r\u0011b\u0001D\r\u0011Y\u0005\u0001\u0001\'\t\u00115\u001b!\u0011!Q\u0001\n9CQ!U\u0002\u0005\u0002ICQAV\u0002\u0005\u0002]CQ\u0001X\u0002\u0005\u0002]CQ!X\u0002\u0005\u0002]CQAX\u0002\u0005\u0002]CQaX\u0002\u0005\u0002]CQ\u0001Y\u0002\u0005\u0002]CQ!Y\u0002\u0005\u0002]CQAY\u0002\u0005\u0002]CQaY\u0002\u0005\u0002]CQ\u0001Z\u0002\u0005\u0002]CQ!Z\u0002\u0005\u0002]CQAZ\u0002\u0005\u0002]CQaZ\u0002\u0005\u0002]CQ\u0001[\u0002\u0005\u0002]CQ![\u0002\u0005\u0002]3AA\u001b\u0001\u0001W\"AQ*\u0006B\u0001B\u0003%A\u000eC\u0003R+\u0011\u0005q\u000eC\u0003W+\u0011\u0005q\u000bC\u0003]+\u0011\u0005q\u000bC\u0003^+\u0011\u0005q\u000bC\u0003_+\u0011\u0005q\u000bC\u0003`+\u0011\u0005q\u000bC\u0003a+\u0011\u0005q\u000bC\u0003b+\u0011\u0005q\u000bC\u0003c+\u0011\u0005q\u000bC\u0003d+\u0011\u0005q\u000bC\u0003e+\u0011\u0005q\u000bC\u0003f+\u0011\u0005q\u000bC\u0003g+\u0011\u0005q\u000bC\u0003h+\u0011\u0005q\u000bC\u0003i+\u0011\u0005q\u000bC\u0003j+\u0011\u0005q\u000bC\u0003s\u0001\u0011\r1\u000fC\u0003z\u0001\u0011\r!\u0010C\u0003}\u0001\u0011\rQ\u0010C\u0004\u0002\b\u0001!\u0019!!\u0003\b\u000f\u0005=q\u0006#\u0001\u0002\u0012\u00191af\fE\u0001\u0003\'Aa!\u0015\u0017\u0005\u0002\u0005]!!C*qC:\u001cVoZ1s\u0015\t\u0001\u0014\'\u0001\u0003uS6,\'B\u0001\u001a4\u0003%\u00198-\u00197bi\u0016\u001cHOC\u00015\u0003\ry\'oZ\u0002\u0001\'\t\u0001q\u0007\u0005\u00029w5\t\u0011HC\u0001;\u0003\u0015\u00198-\u00197b\u0013\ta\u0014H\u0001\u0004B]f\u0014VMZ\u0001\u0007I%t\u0017\u000e\u001e\u0013\u0015\u0003}\u0002\"\u0001\u000f!\n\u0005\u0005K$\u0001B+oSR\f!\u0002]8ti\u001aL\u0007p\u00149t+\u0005!\u0005CA#I\u001d\tAd)\u0003\u0002Hs\u0005yA.\u00198hk\u0006<WMR3biV\u0014X-\u0003\u0002J\u0015\nQ\u0001o\\:uM&Dx\n]:\u000b\u0005\u001dK$aC$sC&twJ\u001a+j[\u0016\u001c\"aA\u001c\u0002\u000bY\fG.^3\u0011\u0005az\u0015B\u0001):\u0005\u0011auN\\4\u0002\rqJg.\u001b;?)\t\u0019V\u000b\u0005\u0002U\u00075\t\u0001\u0001C\u0003N\u000b\u0001\u0007a*\u0001\u0006oC:|7/Z2p]\u0012,\u0012\u0001\u0017\t\u00033jk\u0011aL\u0005\u00037>\u0012Aa\u00159b]\u0006Ya.\u00198pg\u0016\u001cwN\u001c3t\u0003-i\u0017n\u0019:pg\u0016\u001cwN\u001c3\u0002\u00195L7M]8tK\u000e|g\u000eZ:\u0002\u00175LG\u000e\\5tK\u000e|g\u000eZ\u0001\r[&dG.[:fG>tGm]\u0001\u0007[&dG.[:\u0002\rM,7m\u001c8e\u0003\u001d\u0019XmY8oIN\fa!\\5okR,\u0017aB7j]V$Xm]\u0001\u0005Q>,(/A\u0003i_V\u00148/A\u0002eCf\fA\u0001Z1zg\n\u0019b\t\\8bi&twm\u0012:bS:|e\rV5nKN\u0011Qc\u000e\t\u0003q5L!A\\\u001d\u0003\r\u0011{WO\u00197f)\t\u0001\u0018\u000f\u0005\u0002U+!)Qj\u0006a\u0001Y\u000692m\u001c8wKJ$\u0018J\u001c;U_\u001e\u0013\u0018-\u001b8PMRKW.\u001a\u000b\u0003\'RDQ!^\u0014A\u0002Y\f\u0011!\u001b\t\u0003q]L!\u0001_\u001d\u0003\u0007%sG/\u0001\rd_:4XM\u001d;M_:<Gk\\$sC&twJ\u001a+j[\u0016$\"aU>\t\u000bUD\u0003\u0019\u0001(\u00023\r|gN^3si\u001acw.\u0019;U_\u001e\u0013\u0018-\u001b8PMRKW.\u001a\u000b\u0003azDaa`\u0015A\u0002\u0005\u0005\u0011!\u00014\u0011\u0007a\n\u0019!C\u0002\u0002\u0006e\u0012QA\u00127pCR\f!dY8om\u0016\u0014H\u000fR8vE2,Gk\\$sC&twJ\u001a+j[\u0016$2\u0001]A\u0006\u0011\u0019\tiA\u000ba\u0001Y\u0006\tA-A\u0005Ta\u0006t7+^4beB\u0011\u0011\fL\n\u0005Y]\n)\u0002\u0005\u0002Z\u0001Q\u0011\u0011\u0011\u0003"
    )
  ScalaInlineInfo: length = 0x3B (unknown attribute)
   01 00 00 0B 00 41 00 42 01 00 3C 00 3D 00 00 39
   00 3A 01 00 31 00 32 00 00 2E 00 2F 01 00 1C 00
   1D 00 00 18 00 19 01 00 29 00 2A 00 00 27 00 28
   01 00 14 00 15 00 00 13 00 17 00
  ScalaSig: length = 0x3 (unknown attribute)
   05 02 00
