Classfile /Users/mw/Projects/slang-braindump/.jar/jar8/assemble/slang-braindump/modules/jar/classes/jar/JarApp$.class
  Last modified May 29, 2022; size 4777 bytes
  SHA-256 checksum 5c91bb5f052b223282a3e27628bee3037a9959e803e292ad8254e86db23f3bf9
  Compiled from "JarApp.scala"
public final class jar.JarApp$ implements org.sireum.App
  minor version: 0
  major version: 52
  flags: (0x0031) ACC_PUBLIC, ACC_FINAL, ACC_SUPER
  this_class: #2                          // jar/JarApp$
  super_class: #4                         // java/lang/Object
  interfaces: 1, fields: 1, methods: 9, attributes: 5
Constant pool:
    #1 = Utf8               jar/JarApp$
    #2 = Class              #1            // jar/JarApp$
    #3 = Utf8               java/lang/Object
    #4 = Class              #3            // java/lang/Object
    #5 = Utf8               org/sireum/App
    #6 = Class              #5            // org/sireum/App
    #7 = Utf8               JarApp.scala
    #8 = Utf8               java/lang/invoke/MethodHandles$Lookup
    #9 = Class              #8            // java/lang/invoke/MethodHandles$Lookup
   #10 = Utf8               java/lang/invoke/MethodHandles
   #11 = Class              #10           // java/lang/invoke/MethodHandles
   #12 = Utf8               Lookup
   #13 = Utf8               org/sireum/$internal/PackageTrait$ISZ$
   #14 = Class              #13           // org/sireum/$internal/PackageTrait$ISZ$
   #15 = Utf8               org/sireum/$internal/PackageTrait
   #16 = Class              #15           // org/sireum/$internal/PackageTrait
   #17 = Utf8               ISZ$
   #18 = Utf8               org/sireum/ST$Any
   #19 = Class              #18           // org/sireum/ST$Any
   #20 = Utf8               org/sireum/ST
   #21 = Class              #20           // org/sireum/ST
   #22 = Utf8               Any
   #23 = Utf8               org/sireum/ST$Any$
   #24 = Class              #23           // org/sireum/ST$Any$
   #25 = Utf8               Any$
   #26 = Utf8               org/sireum/ST$Arg
   #27 = Class              #26           // org/sireum/ST$Arg
   #28 = Utf8               Arg
   #29 = Utf8               org/sireum/Z$$String$
   #30 = Class              #29           // org/sireum/Z$$String$
   #31 = Utf8               org/sireum/Z
   #32 = Class              #31           // org/sireum/Z
   #33 = Utf8               $String$
   #34 = Utf8               MODULE$
   #35 = Utf8               Ljar/JarApp$;
   #36 = Utf8               <clinit>
   #37 = Utf8               ()V
   #38 = Utf8               <init>
   #39 = NameAndType        #38:#37       // "<init>":()V
   #40 = Methodref          #2.#39        // jar/JarApp$."<init>":()V
   #41 = NameAndType        #34:#35       // MODULE$:Ljar/JarApp$;
   #42 = Fieldref           #2.#41        // jar/JarApp$.MODULE$:Ljar/JarApp$;
   #43 = Utf8               $init$
   #44 = Utf8               (Lorg/sireum/App;)V
   #45 = NameAndType        #43:#44       // $init$:(Lorg/sireum/App;)V
   #46 = InterfaceMethodref #6.#45        // org/sireum/App.$init$:(Lorg/sireum/App;)V
   #47 = Utf8               main
   #48 = Utf8               ([Ljava/lang/String;)V
   #49 = Utf8               args
   #50 = Utf8               main$
   #51 = Utf8               (Lorg/sireum/App;[Ljava/lang/String;)V
   #52 = NameAndType        #50:#51       // main$:(Lorg/sireum/App;[Ljava/lang/String;)V
   #53 = InterfaceMethodref #6.#52        // org/sireum/App.main$:(Lorg/sireum/App;[Ljava/lang/String;)V
   #54 = Utf8               this
   #55 = Utf8               [Ljava/lang/String;
   #56 = Utf8               atExit
   #57 = Utf8               atExit$
   #58 = NameAndType        #57:#44       // atExit$:(Lorg/sireum/App;)V
   #59 = InterfaceMethodref #6.#58        // org/sireum/App.atExit$:(Lorg/sireum/App;)V
   #60 = Utf8               (Lorg/sireum/IS;)Lorg/sireum/Z;
   #61 = Utf8               (Lorg/sireum/IS<Lorg/sireum/Z;Lorg/sireum/String;>;)Lorg/sireum/Z;
   #62 = Utf8               org/sireum/ops/ISZOps$
   #63 = Class              #62           // org/sireum/ops/ISZOps$
   #64 = Utf8               Lorg/sireum/ops/ISZOps$;
   #65 = NameAndType        #34:#64       // MODULE$:Lorg/sireum/ops/ISZOps$;
   #66 = Fieldref           #63.#65       // org/sireum/ops/ISZOps$.MODULE$:Lorg/sireum/ops/ISZOps$;
   #67 = Utf8               org/sireum/package$
   #68 = Class              #67           // org/sireum/package$
   #69 = Utf8               Lorg/sireum/package$;
   #70 = NameAndType        #34:#69       // MODULE$:Lorg/sireum/package$;
   #71 = Fieldref           #68.#70       // org/sireum/package$.MODULE$:Lorg/sireum/package$;
   #72 = Utf8               ISZ
   #73 = Utf8               ()Lorg/sireum/$internal/PackageTrait$ISZ$;
   #74 = NameAndType        #72:#73       // ISZ:()Lorg/sireum/$internal/PackageTrait$ISZ$;
   #75 = Methodref          #68.#74       // org/sireum/package$.ISZ:()Lorg/sireum/$internal/PackageTrait$ISZ$;
   #76 = Utf8               scala/runtime/ScalaRunTime$
   #77 = Class              #76           // scala/runtime/ScalaRunTime$
   #78 = Utf8               Lscala/runtime/ScalaRunTime$;
   #79 = NameAndType        #34:#78       // MODULE$:Lscala/runtime/ScalaRunTime$;
   #80 = Fieldref           #77.#79       // scala/runtime/ScalaRunTime$.MODULE$:Lscala/runtime/ScalaRunTime$;
   #81 = Utf8               Lorg/sireum/Z$$String$;
   #82 = NameAndType        #34:#81       // MODULE$:Lorg/sireum/Z$$String$;
   #83 = Fieldref           #30.#82       // org/sireum/Z$$String$.MODULE$:Lorg/sireum/Z$$String$;
   #84 = Utf8               1
   #85 = String             #84           // 1
   #86 = Utf8               apply
   #87 = Utf8               (Ljava/lang/String;)Lorg/sireum/Z;
   #88 = NameAndType        #86:#87       // apply:(Ljava/lang/String;)Lorg/sireum/Z;
   #89 = Methodref          #30.#88       // org/sireum/Z$$String$.apply:(Ljava/lang/String;)Lorg/sireum/Z;
   #90 = Utf8               2
   #91 = String             #90           // 2
   #92 = Utf8               3
   #93 = String             #92           // 3
   #94 = Utf8               [Ljava/lang/Object;
   #95 = Class              #94           // "[Ljava/lang/Object;"
   #96 = Utf8               wrapRefArray
   #97 = Utf8               ([Ljava/lang/Object;)Lscala/collection/immutable/ArraySeq;
   #98 = NameAndType        #96:#97       // wrapRefArray:([Ljava/lang/Object;)Lscala/collection/immutable/ArraySeq;
   #99 = Methodref          #77.#98       // scala/runtime/ScalaRunTime$.wrapRefArray:([Ljava/lang/Object;)Lscala/collection/immutable/ArraySeq;
  #100 = Utf8               (Lscala/collection/immutable/Seq;)Lorg/sireum/IS;
  #101 = NameAndType        #86:#100      // apply:(Lscala/collection/immutable/Seq;)Lorg/sireum/IS;
  #102 = Methodref          #14.#101      // org/sireum/$internal/PackageTrait$ISZ$.apply:(Lscala/collection/immutable/Seq;)Lorg/sireum/IS;
  #103 = Utf8               (Lorg/sireum/IS;)Lorg/sireum/ops/ISZOps;
  #104 = NameAndType        #86:#103      // apply:(Lorg/sireum/IS;)Lorg/sireum/ops/ISZOps;
  #105 = Methodref          #63.#104      // org/sireum/ops/ISZOps$.apply:(Lorg/sireum/IS;)Lorg/sireum/ops/ISZOps;
  #106 = Utf8               (Ljava/lang/Object;)Ljava/lang/Object;
  #107 = MethodType         #106          //  (Ljava/lang/Object;)Ljava/lang/Object;
  #108 = Utf8               $anonfun$main$1
  #109 = Utf8               (Lorg/sireum/Z;)Lorg/sireum/ST;
  #110 = NameAndType        #108:#109     // $anonfun$main$1:(Lorg/sireum/Z;)Lorg/sireum/ST;
  #111 = Methodref          #2.#110       // jar/JarApp$.$anonfun$main$1:(Lorg/sireum/Z;)Lorg/sireum/ST;
  #112 = MethodHandle       6:#111        // REF_invokeStatic jar/JarApp$.$anonfun$main$1:(Lorg/sireum/Z;)Lorg/sireum/ST;
  #113 = MethodType         #109          //  (Lorg/sireum/Z;)Lorg/sireum/ST;
  #114 = Integer            5
  #115 = Integer            1
  #116 = Utf8               java/lang/invoke/LambdaMetafactory
  #117 = Class              #116          // java/lang/invoke/LambdaMetafactory
  #118 = Utf8               altMetafactory
  #119 = Utf8               (Ljava/lang/invoke/MethodHandles$Lookup;Ljava/lang/String;Ljava/lang/invoke/MethodType;[Ljava/lang/Object;)Ljava/lang/invoke/CallSite;
  #120 = NameAndType        #118:#119     // altMetafactory:(Ljava/lang/invoke/MethodHandles$Lookup;Ljava/lang/String;Ljava/lang/invoke/MethodType;[Ljava/lang/Object;)Ljava/lang/invoke/CallSite;
  #121 = Methodref          #117.#120     // java/lang/invoke/LambdaMetafactory.altMetafactory:(Ljava/lang/invoke/MethodHandles$Lookup;Ljava/lang/String;Ljava/lang/invoke/MethodType;[Ljava/lang/Object;)Ljava/lang/invoke/CallSite;
  #122 = MethodHandle       6:#121        // REF_invokeStatic java/lang/invoke/LambdaMetafactory.altMetafactory:(Ljava/lang/invoke/MethodHandles$Lookup;Ljava/lang/String;Ljava/lang/invoke/MethodType;[Ljava/lang/Object;)Ljava/lang/invoke/CallSite;
  #123 = Utf8               ()Lscala/Function1;
  #124 = NameAndType        #86:#123      // apply:()Lscala/Function1;
  #125 = InvokeDynamic      #0:#124       // #0:apply:()Lscala/Function1;
  #126 = Utf8               org/sireum/ops/ISZOps
  #127 = Class              #126          // org/sireum/ops/ISZOps
  #128 = Utf8               mParMapCores
  #129 = Utf8               (Lscala/Function1;Lorg/sireum/Z;)Lorg/sireum/IS;
  #130 = NameAndType        #128:#129     // mParMapCores:(Lscala/Function1;Lorg/sireum/Z;)Lorg/sireum/IS;
  #131 = Methodref          #127.#130     // org/sireum/ops/ISZOps.mParMapCores:(Lscala/Function1;Lorg/sireum/Z;)Lorg/sireum/IS;
  #132 = Utf8               $anonfun$main$2$adapted
  #133 = Utf8               (Lorg/sireum/ST;)Ljava/lang/Object;
  #134 = NameAndType        #132:#133     // $anonfun$main$2$adapted:(Lorg/sireum/ST;)Ljava/lang/Object;
  #135 = Methodref          #2.#134       // jar/JarApp$.$anonfun$main$2$adapted:(Lorg/sireum/ST;)Ljava/lang/Object;
  #136 = MethodHandle       6:#135        // REF_invokeStatic jar/JarApp$.$anonfun$main$2$adapted:(Lorg/sireum/ST;)Ljava/lang/Object;
  #137 = MethodType         #133          //  (Lorg/sireum/ST;)Ljava/lang/Object;
  #138 = InvokeDynamic      #1:#124       // #1:apply:()Lscala/Function1;
  #139 = Utf8               org/sireum/IS
  #140 = Class              #139          // org/sireum/IS
  #141 = Utf8               foreach
  #142 = Utf8               (Lscala/Function1;)V
  #143 = NameAndType        #141:#142     // foreach:(Lscala/Function1;)V
  #144 = Methodref          #140.#143     // org/sireum/IS.foreach:(Lscala/Function1;)V
  #145 = Utf8               0
  #146 = String             #145          // 0
  #147 = Utf8               Lorg/sireum/IS;
  #148 = Utf8               z
  #149 = Utf8               org/sireum/ST$
  #150 = Class              #149          // org/sireum/ST$
  #151 = Utf8               Lorg/sireum/ST$;
  #152 = NameAndType        #34:#151      // MODULE$:Lorg/sireum/ST$;
  #153 = Fieldref           #150.#152     // org/sireum/ST$.MODULE$:Lorg/sireum/ST$;
  #154 = Utf8               scala/package$
  #155 = Class              #154          // scala/package$
  #156 = Utf8               Lscala/package$;
  #157 = NameAndType        #34:#156      // MODULE$:Lscala/package$;
  #158 = Fieldref           #155.#157     // scala/package$.MODULE$:Lscala/package$;
  #159 = Utf8               Seq
  #160 = Utf8               ()Lscala/collection/immutable/Seq$;
  #161 = NameAndType        #159:#160     // Seq:()Lscala/collection/immutable/Seq$;
  #162 = Methodref          #155.#161     // scala/package$.Seq:()Lscala/collection/immutable/Seq$;
  #163 = Utf8               java/lang/String
  #164 = Class              #163          // java/lang/String
  #165 = Utf8               scala/StringContext$
  #166 = Class              #165          // scala/StringContext$
  #167 = Utf8               Lscala/StringContext$;
  #168 = NameAndType        #34:#167      // MODULE$:Lscala/StringContext$;
  #169 = Fieldref           #166.#168     // scala/StringContext$.MODULE$:Lscala/StringContext$;
  #170 = Utf8
  #171 = String             #170          //
  #172 = Utf8               processEscapes
  #173 = Utf8               (Ljava/lang/String;)Ljava/lang/String;
  #174 = NameAndType        #172:#173     // processEscapes:(Ljava/lang/String;)Ljava/lang/String;
  #175 = Methodref          #166.#174     // scala/StringContext$.processEscapes:(Ljava/lang/String;)Ljava/lang/String;
  #176 = Utf8               scala/collection/immutable/Seq$
  #177 = Class              #176          // scala/collection/immutable/Seq$
  #178 = Utf8               (Lscala/collection/immutable/Seq;)Lscala/collection/SeqOps;
  #179 = NameAndType        #86:#178      // apply:(Lscala/collection/immutable/Seq;)Lscala/collection/SeqOps;
  #180 = Methodref          #177.#179     // scala/collection/immutable/Seq$.apply:(Lscala/collection/immutable/Seq;)Lscala/collection/SeqOps;
  #181 = Utf8               scala/collection/immutable/Seq
  #182 = Class              #181          // scala/collection/immutable/Seq
  #183 = Utf8               Lorg/sireum/ST$Any$;
  #184 = NameAndType        #34:#183      // MODULE$:Lorg/sireum/ST$Any$;
  #185 = Fieldref           #24.#184      // org/sireum/ST$Any$.MODULE$:Lorg/sireum/ST$Any$;
  #186 = Utf8               org/sireum/$internal/Option$
  #187 = Class              #186          // org/sireum/$internal/Option$
  #188 = Utf8               Lorg/sireum/$internal/Option$;
  #189 = NameAndType        #34:#188      // MODULE$:Lorg/sireum/$internal/Option$;
  #190 = Fieldref           #187.#189     // org/sireum/$internal/Option$.MODULE$:Lorg/sireum/$internal/Option$;
  #191 = NameAndType        #86:#106      // apply:(Ljava/lang/Object;)Ljava/lang/Object;
  #192 = Methodref          #187.#191     // org/sireum/$internal/Option$.apply:(Ljava/lang/Object;)Ljava/lang/Object;
  #193 = Utf8               genericWrapArray
  #194 = Utf8               (Ljava/lang/Object;)Lscala/collection/immutable/ArraySeq;
  #195 = NameAndType        #193:#194     // genericWrapArray:(Ljava/lang/Object;)Lscala/collection/immutable/ArraySeq;
  #196 = Methodref          #77.#195      // scala/runtime/ScalaRunTime$.genericWrapArray:(Ljava/lang/Object;)Lscala/collection/immutable/ArraySeq;
  #197 = Utf8               (Lscala/collection/immutable/Seq;Ljava/lang/String;)Lorg/sireum/ST$Any;
  #198 = NameAndType        #86:#197      // apply:(Lscala/collection/immutable/Seq;Ljava/lang/String;)Lorg/sireum/ST$Any;
  #199 = Methodref          #24.#198      // org/sireum/ST$Any$.apply:(Lscala/collection/immutable/Seq;Ljava/lang/String;)Lorg/sireum/ST$Any;
  #200 = Utf8                                             st\"$z\"
  #201 = String             #200          //                               st\"$z\"
  #202 = Utf8               (Lscala/collection/immutable/Seq;Lscala/collection/immutable/Seq;Ljava/lang/String;)Lorg/sireum/ST;
  #203 = NameAndType        #86:#202      // apply:(Lscala/collection/immutable/Seq;Lscala/collection/immutable/Seq;Ljava/lang/String;)Lorg/sireum/ST;
  #204 = Methodref          #150.#203     // org/sireum/ST$.apply:(Lscala/collection/immutable/Seq;Lscala/collection/immutable/Seq;Ljava/lang/String;)Lorg/sireum/ST;
  #205 = Utf8               Lorg/sireum/Z;
  #206 = Utf8               $anonfun$main$2
  #207 = Utf8               (Lorg/sireum/ST;)V
  #208 = Utf8               st
  #209 = Utf8               org/sireum/String
  #210 = Class              #209          // org/sireum/String
  #211 = Utf8               render
  #212 = Utf8               ()Ljava/lang/String;
  #213 = NameAndType        #211:#212     // render:()Ljava/lang/String;
  #214 = Methodref          #21.#213      // org/sireum/ST.render:()Ljava/lang/String;
  #215 = Utf8               (Ljava/lang/String;)V
  #216 = NameAndType        #38:#215      // "<init>":(Ljava/lang/String;)V
  #217 = Methodref          #210.#216     // org/sireum/String."<init>":(Ljava/lang/String;)V
  #218 = Utf8               println
  #219 = Utf8               (Lscala/collection/immutable/Seq;)V
  #220 = NameAndType        #218:#219     // println:(Lscala/collection/immutable/Seq;)V
  #221 = Methodref          #68.#220      // org/sireum/package$.println:(Lscala/collection/immutable/Seq;)V
  #222 = Utf8               scala/runtime/BoxedUnit
  #223 = Class              #222          // scala/runtime/BoxedUnit
  #224 = Utf8               UNIT
  #225 = Utf8               Lscala/runtime/BoxedUnit;
  #226 = NameAndType        #224:#225     // UNIT:Lscala/runtime/BoxedUnit;
  #227 = Fieldref           #223.#226     // scala/runtime/BoxedUnit.UNIT:Lscala/runtime/BoxedUnit;
  #228 = Utf8               Lorg/sireum/ST;
  #229 = Methodref          #4.#39        // java/lang/Object."<init>":()V
  #230 = NameAndType        #206:#207     // $anonfun$main$2:(Lorg/sireum/ST;)V
  #231 = Methodref          #2.#230       // jar/JarApp$.$anonfun$main$2:(Lorg/sireum/ST;)V
  #232 = Utf8               $deserializeLambda$
  #233 = Utf8               (Ljava/lang/invoke/SerializedLambda;)Ljava/lang/Object;
  #234 = Utf8               scala/runtime/LambdaDeserialize
  #235 = Class              #234          // scala/runtime/LambdaDeserialize
  #236 = Utf8               bootstrap
  #237 = Utf8               (Ljava/lang/invoke/MethodHandles$Lookup;Ljava/lang/String;Ljava/lang/invoke/MethodType;[Ljava/lang/invoke/MethodHandle;)Ljava/lang/invoke/CallSite;
  #238 = NameAndType        #236:#237     // bootstrap:(Ljava/lang/invoke/MethodHandles$Lookup;Ljava/lang/String;Ljava/lang/invoke/MethodType;[Ljava/lang/invoke/MethodHandle;)Ljava/lang/invoke/CallSite;
  #239 = Methodref          #235.#238     // scala/runtime/LambdaDeserialize.bootstrap:(Ljava/lang/invoke/MethodHandles$Lookup;Ljava/lang/String;Ljava/lang/invoke/MethodType;[Ljava/lang/invoke/MethodHandle;)Ljava/lang/invoke/CallSite;
  #240 = MethodHandle       6:#239        // REF_invokeStatic scala/runtime/LambdaDeserialize.bootstrap:(Ljava/lang/invoke/MethodHandles$Lookup;Ljava/lang/String;Ljava/lang/invoke/MethodType;[Ljava/lang/invoke/MethodHandle;)Ljava/lang/invoke/CallSite;
  #241 = Utf8               lambdaDeserialize
  #242 = NameAndType        #241:#233     // lambdaDeserialize:(Ljava/lang/invoke/SerializedLambda;)Ljava/lang/Object;
  #243 = InvokeDynamic      #2:#242       // #2:lambdaDeserialize:(Ljava/lang/invoke/SerializedLambda;)Ljava/lang/Object;
  #244 = Utf8               Code
  #245 = Utf8               LineNumberTable
  #246 = Utf8               LocalVariableTable
  #247 = Utf8               MethodParameters
  #248 = Utf8               Signature
  #249 = Utf8               InnerClasses
  #250 = Utf8               SourceFile
  #251 = Utf8               BootstrapMethods
  #252 = Utf8               ScalaInlineInfo
  #253 = Utf8               Scala
{
  public static final jar.JarApp$ MODULE$;
    descriptor: Ljar/JarApp$;
    flags: (0x0019) ACC_PUBLIC, ACC_STATIC, ACC_FINAL

  public static {};
    descriptor: ()V
    flags: (0x0009) ACC_PUBLIC, ACC_STATIC
    Code:
      stack=2, locals=0, args_size=0
         0: new           #2                  // class jar/JarApp$
         3: dup
         4: invokespecial #40                 // Method "<init>":()V
         7: putstatic     #42                 // Field MODULE$:Ljar/JarApp$;
        10: getstatic     #42                 // Field MODULE$:Ljar/JarApp$;
        13: invokestatic  #46                 // InterfaceMethod org/sireum/App.$init$:(Lorg/sireum/App;)V
        16: return
      LineNumberTable:
        line 7: 0

  public final void main(java.lang.String[]);
    descriptor: ([Ljava/lang/String;)V
    flags: (0x0011) ACC_PUBLIC, ACC_FINAL
    Code:
      stack=2, locals=2, args_size=2
         0: aload_0
         1: aload_1
         2: invokestatic  #53                 // InterfaceMethod org/sireum/App.main$:(Lorg/sireum/App;[Ljava/lang/String;)V
         5: return
      LineNumberTable:
        line 7: 0
      LocalVariableTable:
        Start  Length  Slot  Name   Signature
            0       6     0  this   Ljar/JarApp$;
            0       6     1  args   [Ljava/lang/String;
    MethodParameters:
      Name                           Flags
      args                           final

  public void atExit();
    descriptor: ()V
    flags: (0x0001) ACC_PUBLIC
    Code:
      stack=1, locals=1, args_size=1
         0: aload_0
         1: invokestatic  #59                 // InterfaceMethod org/sireum/App.atExit$:(Lorg/sireum/App;)V
         4: return
      LineNumberTable:
        line 7: 0
      LocalVariableTable:
        Start  Length  Slot  Name   Signature
            0       5     0  this   Ljar/JarApp$;

  public org.sireum.Z main(org.sireum.IS<org.sireum.Z, org.sireum.String>);
    descriptor: (Lorg/sireum/IS;)Lorg/sireum/Z;
    flags: (0x0001) ACC_PUBLIC
    Code:
      stack=8, locals=2, args_size=2
         0: getstatic     #66                 // Field org/sireum/ops/ISZOps$.MODULE$:Lorg/sireum/ops/ISZOps$;
         3: getstatic     #71                 // Field org/sireum/package$.MODULE$:Lorg/sireum/package$;
         6: invokevirtual #75                 // Method org/sireum/package$.ISZ:()Lorg/sireum/$internal/PackageTrait$ISZ$;
         9: getstatic     #80                 // Field scala/runtime/ScalaRunTime$.MODULE$:Lscala/runtime/ScalaRunTime$;
        12: iconst_3
        13: anewarray     #32                 // class org/sireum/Z
        16: dup
        17: iconst_0
        18: getstatic     #83                 // Field org/sireum/Z$$String$.MODULE$:Lorg/sireum/Z$$String$;
        21: ldc           #85                 // String 1
        23: invokevirtual #89                 // Method org/sireum/Z$$String$.apply:(Ljava/lang/String;)Lorg/sireum/Z;
        26: aastore
        27: dup
        28: iconst_1
        29: getstatic     #83                 // Field org/sireum/Z$$String$.MODULE$:Lorg/sireum/Z$$String$;
        32: ldc           #91                 // String 2
        34: invokevirtual #89                 // Method org/sireum/Z$$String$.apply:(Ljava/lang/String;)Lorg/sireum/Z;
        37: aastore
        38: dup
        39: iconst_2
        40: getstatic     #83                 // Field org/sireum/Z$$String$.MODULE$:Lorg/sireum/Z$$String$;
        43: ldc           #93                 // String 3
        45: invokevirtual #89                 // Method org/sireum/Z$$String$.apply:(Ljava/lang/String;)Lorg/sireum/Z;
        48: aastore
        49: checkcast     #95                 // class "[Ljava/lang/Object;"
        52: invokevirtual #99                 // Method scala/runtime/ScalaRunTime$.wrapRefArray:([Ljava/lang/Object;)Lscala/collection/immutable/ArraySeq;
        55: invokevirtual #102                // Method org/sireum/$internal/PackageTrait$ISZ$.apply:(Lscala/collection/immutable/Seq;)Lorg/sireum/IS;
        58: invokevirtual #105                // Method org/sireum/ops/ISZOps$.apply:(Lorg/sireum/IS;)Lorg/sireum/ops/ISZOps;
        61: invokedynamic #125,  0            // InvokeDynamic #0:apply:()Lscala/Function1;
        66: getstatic     #83                 // Field org/sireum/Z$$String$.MODULE$:Lorg/sireum/Z$$String$;
        69: ldc           #91                 // String 2
        71: invokevirtual #89                 // Method org/sireum/Z$$String$.apply:(Ljava/lang/String;)Lorg/sireum/Z;
        74: invokevirtual #131                // Method org/sireum/ops/ISZOps.mParMapCores:(Lscala/Function1;Lorg/sireum/Z;)Lorg/sireum/IS;
        77: invokedynamic #138,  0            // InvokeDynamic #1:apply:()Lscala/Function1;
        82: invokevirtual #144                // Method org/sireum/IS.foreach:(Lscala/Function1;)V
        85: getstatic     #83                 // Field org/sireum/Z$$String$.MODULE$:Lorg/sireum/Z$$String$;
        88: ldc           #146                // String 0
        90: invokevirtual #89                 // Method org/sireum/Z$$String$.apply:(Ljava/lang/String;)Lorg/sireum/Z;
        93: areturn
      LineNumberTable:
        line 9: 0
        line 10: 61
        line 11: 77
        line 12: 85
      LocalVariableTable:
        Start  Length  Slot  Name   Signature
            0      94     0  this   Ljar/JarApp$;
            0      94     1  args   Lorg/sireum/IS;
    Signature: #61                          // (Lorg/sireum/IS<Lorg/sireum/Z;Lorg/sireum/String;>;)Lorg/sireum/Z;
    MethodParameters:
      Name                           Flags
      args                           final

  public static final org.sireum.ST $anonfun$main$1(org.sireum.Z);
    descriptor: (Lorg/sireum/Z;)Lorg/sireum/ST;
    flags: (0x1019) ACC_PUBLIC, ACC_STATIC, ACC_FINAL, ACC_SYNTHETIC
    Code:
      stack=15, locals=1, args_size=1
         0: getstatic     #153                // Field org/sireum/ST$.MODULE$:Lorg/sireum/ST$;
         3: getstatic     #158                // Field scala/package$.MODULE$:Lscala/package$;
         6: invokevirtual #162                // Method scala/package$.Seq:()Lscala/collection/immutable/Seq$;
         9: getstatic     #80                 // Field scala/runtime/ScalaRunTime$.MODULE$:Lscala/runtime/ScalaRunTime$;
        12: iconst_2
        13: anewarray     #164                // class java/lang/String
        16: dup
        17: iconst_0
        18: getstatic     #169                // Field scala/StringContext$.MODULE$:Lscala/StringContext$;
        21: ldc           #171                // String
        23: invokevirtual #175                // Method scala/StringContext$.processEscapes:(Ljava/lang/String;)Ljava/lang/String;
        26: aastore
        27: dup
        28: iconst_1
        29: getstatic     #169                // Field scala/StringContext$.MODULE$:Lscala/StringContext$;
        32: ldc           #171                // String
        34: invokevirtual #175                // Method scala/StringContext$.processEscapes:(Ljava/lang/String;)Ljava/lang/String;
        37: aastore
        38: checkcast     #95                 // class "[Ljava/lang/Object;"
        41: invokevirtual #99                 // Method scala/runtime/ScalaRunTime$.wrapRefArray:([Ljava/lang/Object;)Lscala/collection/immutable/ArraySeq;
        44: invokevirtual #180                // Method scala/collection/immutable/Seq$.apply:(Lscala/collection/immutable/Seq;)Lscala/collection/SeqOps;
        47: checkcast     #182                // class scala/collection/immutable/Seq
        50: getstatic     #158                // Field scala/package$.MODULE$:Lscala/package$;
        53: invokevirtual #162                // Method scala/package$.Seq:()Lscala/collection/immutable/Seq$;
        56: getstatic     #80                 // Field scala/runtime/ScalaRunTime$.MODULE$:Lscala/runtime/ScalaRunTime$;
        59: iconst_1
        60: anewarray     #27                 // class org/sireum/ST$Arg
        63: dup
        64: iconst_0
        65: getstatic     #185                // Field org/sireum/ST$Any$.MODULE$:Lorg/sireum/ST$Any$;
        68: getstatic     #158                // Field scala/package$.MODULE$:Lscala/package$;
        71: invokevirtual #162                // Method scala/package$.Seq:()Lscala/collection/immutable/Seq$;
        74: getstatic     #80                 // Field scala/runtime/ScalaRunTime$.MODULE$:Lscala/runtime/ScalaRunTime$;
        77: iconst_1
        78: anewarray     #4                  // class java/lang/Object
        81: dup
        82: iconst_0
        83: getstatic     #190                // Field org/sireum/$internal/Option$.MODULE$:Lorg/sireum/$internal/Option$;
        86: aload_0
        87: invokevirtual #192                // Method org/sireum/$internal/Option$.apply:(Ljava/lang/Object;)Ljava/lang/Object;
        90: aastore
        91: invokevirtual #196                // Method scala/runtime/ScalaRunTime$.genericWrapArray:(Ljava/lang/Object;)Lscala/collection/immutable/ArraySeq;
        94: invokevirtual #180                // Method scala/collection/immutable/Seq$.apply:(Lscala/collection/immutable/Seq;)Lscala/collection/SeqOps;
        97: checkcast     #182                // class scala/collection/immutable/Seq
       100: ldc           #171                // String
       102: invokevirtual #199                // Method org/sireum/ST$Any$.apply:(Lscala/collection/immutable/Seq;Ljava/lang/String;)Lorg/sireum/ST$Any;
       105: aastore
       106: checkcast     #95                 // class "[Ljava/lang/Object;"
       109: invokevirtual #99                 // Method scala/runtime/ScalaRunTime$.wrapRefArray:([Ljava/lang/Object;)Lscala/collection/immutable/ArraySeq;
       112: invokevirtual #180                // Method scala/collection/immutable/Seq$.apply:(Lscala/collection/immutable/Seq;)Lscala/collection/SeqOps;
       115: checkcast     #182                // class scala/collection/immutable/Seq
       118: ldc           #201                // String                               st\"$z\"
       120: invokevirtual #204                // Method org/sireum/ST$.apply:(Lscala/collection/immutable/Seq;Lscala/collection/immutable/Seq;Ljava/lang/String;)Lorg/sireum/ST;
       123: areturn
      LineNumberTable:
        line 10: 0
      LocalVariableTable:
        Start  Length  Slot  Name   Signature
            0     124     0     z   Lorg/sireum/Z;
    MethodParameters:
      Name                           Flags
      z                              final

  public static final void $anonfun$main$2(org.sireum.ST);
    descriptor: (Lorg/sireum/ST;)V
    flags: (0x1019) ACC_PUBLIC, ACC_STATIC, ACC_FINAL, ACC_SYNTHETIC
    Code:
      stack=8, locals=1, args_size=1
         0: getstatic     #71                 // Field org/sireum/package$.MODULE$:Lorg/sireum/package$;
         3: getstatic     #80                 // Field scala/runtime/ScalaRunTime$.MODULE$:Lscala/runtime/ScalaRunTime$;
         6: iconst_1
         7: anewarray     #4                  // class java/lang/Object
        10: dup
        11: iconst_0
        12: new           #210                // class org/sireum/String
        15: dup
        16: aload_0
        17: invokevirtual #214                // Method org/sireum/ST.render:()Ljava/lang/String;
        20: invokespecial #217                // Method org/sireum/String."<init>":(Ljava/lang/String;)V
        23: aastore
        24: invokevirtual #196                // Method scala/runtime/ScalaRunTime$.genericWrapArray:(Ljava/lang/Object;)Lscala/collection/immutable/ArraySeq;
        27: invokevirtual #221                // Method org/sireum/package$.println:(Lscala/collection/immutable/Seq;)V
        30: getstatic     #227                // Field scala/runtime/BoxedUnit.UNIT:Lscala/runtime/BoxedUnit;
        33: pop
        34: return
      LineNumberTable:
        line 11: 0
      LocalVariableTable:
        Start  Length  Slot  Name   Signature
            0      35     0    st   Lorg/sireum/ST;
    MethodParameters:
      Name                           Flags
      st                             final

  private jar.JarApp$();
    descriptor: ()V
    flags: (0x0002) ACC_PRIVATE
    Code:
      stack=1, locals=1, args_size=1
         0: aload_0
         1: invokespecial #229                // Method java/lang/Object."<init>":()V
         4: return
      LineNumberTable:
        line 7: 0
      LocalVariableTable:
        Start  Length  Slot  Name   Signature
            0       5     0  this   Ljar/JarApp$;

  public static final java.lang.Object $anonfun$main$2$adapted(org.sireum.ST);
    descriptor: (Lorg/sireum/ST;)Ljava/lang/Object;
    flags: (0x1019) ACC_PUBLIC, ACC_STATIC, ACC_FINAL, ACC_SYNTHETIC
    Code:
      stack=1, locals=1, args_size=1
         0: aload_0
         1: invokestatic  #231                // Method $anonfun$main$2:(Lorg/sireum/ST;)V
         4: getstatic     #227                // Field scala/runtime/BoxedUnit.UNIT:Lscala/runtime/BoxedUnit;
         7: areturn
      LineNumberTable:
        line 11: 0
      LocalVariableTable:
        Start  Length  Slot  Name   Signature
            0       8     0    st   Lorg/sireum/ST;
    MethodParameters:
      Name                           Flags
      st                             final

  private static java.lang.Object $deserializeLambda$(java.lang.invoke.SerializedLambda);
    descriptor: (Ljava/lang/invoke/SerializedLambda;)Ljava/lang/Object;
    flags: (0x100a) ACC_PRIVATE, ACC_STATIC, ACC_SYNTHETIC
    Code:
      stack=1, locals=1, args_size=1
         0: aload_0
         1: invokedynamic #243,  0            // InvokeDynamic #2:lambdaDeserialize:(Ljava/lang/invoke/SerializedLambda;)Ljava/lang/Object;
         6: areturn
}
InnerClasses:
  public static final #12= #9 of #11;     // Lookup=class java/lang/invoke/MethodHandles$Lookup of class java/lang/invoke/MethodHandles
  public #17= #14 of #16;                 // ISZ$=class org/sireum/$internal/PackageTrait$ISZ$ of class org/sireum/$internal/PackageTrait
  public static final #22= #19 of #21;    // Any=class org/sireum/ST$Any of class org/sireum/ST
  public static #25= #24 of #21;          // Any$=class org/sireum/ST$Any$ of class org/sireum/ST
  public static #28= #27 of #21;          // Arg=class org/sireum/ST$Arg of class org/sireum/ST
  public static #33= #30 of #32;          // $String$=class org/sireum/Z$$String$ of class org/sireum/Z
SourceFile: "JarApp.scala"
BootstrapMethods:
  0: #122 REF_invokeStatic java/lang/invoke/LambdaMetafactory.altMetafactory:(Ljava/lang/invoke/MethodHandles$Lookup;Ljava/lang/String;Ljava/lang/invoke/MethodType;[Ljava/lang/Object;)Ljava/lang/invoke/CallSite;
    Method arguments:
      #107 (Ljava/lang/Object;)Ljava/lang/Object;
      #112 REF_invokeStatic jar/JarApp$.$anonfun$main$1:(Lorg/sireum/Z;)Lorg/sireum/ST;
      #113 (Lorg/sireum/Z;)Lorg/sireum/ST;
      #114 5
      #115 1
      #113 (Lorg/sireum/Z;)Lorg/sireum/ST;
  1: #122 REF_invokeStatic java/lang/invoke/LambdaMetafactory.altMetafactory:(Ljava/lang/invoke/MethodHandles$Lookup;Ljava/lang/String;Ljava/lang/invoke/MethodType;[Ljava/lang/Object;)Ljava/lang/invoke/CallSite;
    Method arguments:
      #107 (Ljava/lang/Object;)Ljava/lang/Object;
      #136 REF_invokeStatic jar/JarApp$.$anonfun$main$2$adapted:(Lorg/sireum/ST;)Ljava/lang/Object;
      #137 (Lorg/sireum/ST;)Ljava/lang/Object;
      #114 5
      #115 1
      #137 (Lorg/sireum/ST;)Ljava/lang/Object;
  2: #240 REF_invokeStatic scala/runtime/LambdaDeserialize.bootstrap:(Ljava/lang/invoke/MethodHandles$Lookup;Ljava/lang/String;Ljava/lang/invoke/MethodType;[Ljava/lang/invoke/MethodHandle;)Ljava/lang/invoke/CallSite;
    Method arguments:
      #112 REF_invokeStatic jar/JarApp$.$anonfun$main$1:(Lorg/sireum/Z;)Lorg/sireum/ST;
      #136 REF_invokeStatic jar/JarApp$.$anonfun$main$2$adapted:(Lorg/sireum/ST;)Ljava/lang/Object;
  ScalaInlineInfo: length = 0x27 (unknown attribute)
   01 01 00 07 00 6C 00 6D 01 00 CE 00 CF 01 00 84
   00 85 01 00 26 00 25 01 00 38 00 25 01 00 2F 00
   3C 01 00 2F 00 30 01
  Scala: length = 0x0 (unknown attribute)

