Classfile /Users/mw/Projects/slang-braindump/.jar/jar11/assemble/slang-braindump/assemble/content/scala/collection/parallel/mutable/ResizableParArrayCombiner$ResizableParArrayCombinerC$1.class
  Last modified May 29, 2022; size 10346 bytes
  SHA-256 checksum b6c18455779524e8bd3ac3d61380714d8f6e2892dfc4b7583ed1577c17c09c4a
  Compiled from "ResizableParArrayCombiner.scala"
public class scala.collection.parallel.mutable.ResizableParArrayCombiner$ResizableParArrayCombinerC$1<A extends java.lang.Object> extends java.lang.Object implements scala.collection.parallel.mutable.ResizableParArrayCombiner<A>
  minor version: 0
  major version: 52
  flags: (0x0021) ACC_PUBLIC, ACC_SUPER
  this_class: #2                          // scala/collection/parallel/mutable/ResizableParArrayCombiner$ResizableParArrayCombinerC$1
  super_class: #5                         // java/lang/Object
  interfaces: 1, fields: 3, methods: 34, attributes: 6
Constant pool:
    #1 = Utf8               scala/collection/parallel/mutable/ResizableParArrayCombiner$ResizableParArrayCombinerC$1
    #2 = Class              #1            // scala/collection/parallel/mutable/ResizableParArrayCombiner$ResizableParArrayCombinerC$1
    #3 = Utf8               <A:Ljava/lang/Object;>Ljava/lang/Object;Lscala/collection/parallel/mutable/ResizableParArrayCombiner<TA;>;
    #4 = Utf8               java/lang/Object
    #5 = Class              #4            // java/lang/Object
    #6 = Utf8               scala/collection/parallel/mutable/ResizableParArrayCombiner
    #7 = Class              #6            // scala/collection/parallel/mutable/ResizableParArrayCombiner
    #8 = Utf8               ResizableParArrayCombiner.scala
    #9 = Utf8               scala/collection/parallel/mutable/ResizableParArrayCombiner$
   #10 = Class              #9            // scala/collection/parallel/mutable/ResizableParArrayCombiner$
   #11 = Utf8               apply
   #12 = Utf8               (Lscala/collection/mutable/ArrayBuffer;)Lscala/collection/parallel/mutable/ResizableParArrayCombiner;
   #13 = NameAndType        #11:#12       // apply:(Lscala/collection/mutable/ArrayBuffer;)Lscala/collection/parallel/mutable/ResizableParArrayCombiner;
   #14 = Utf8               ResizableParArrayCombinerC$1
   #15 = Utf8               chain
   #16 = Utf8               Lscala/collection/mutable/ArrayBuffer;
   #17 = Utf8               Lscala/collection/mutable/ArrayBuffer<Lscala/collection/parallel/mutable/ExposedArrayBuffer<TA;>;>;
   #18 = Utf8               lastbuff
   #19 = Utf8               Lscala/collection/parallel/mutable/ExposedArrayBuffer;
   #20 = Utf8               Lscala/collection/parallel/mutable/ExposedArrayBuffer<TA;>;
   #21 = Utf8               _combinerTaskSupport
   #22 = Utf8               Lscala/collection/parallel/TaskSupport;
   #23 = Utf8               sizeHint
   #24 = Utf8               (I)V
   #25 = Utf8               sz
   #26 = Utf8               sizeHint$
   #27 = Utf8               (Lscala/collection/parallel/mutable/ResizableParArrayCombiner;I)V
   #28 = NameAndType        #26:#27       // sizeHint$:(Lscala/collection/parallel/mutable/ResizableParArrayCombiner;I)V
   #29 = InterfaceMethodref #7.#28        // scala/collection/parallel/mutable/ResizableParArrayCombiner.sizeHint$:(Lscala/collection/parallel/mutable/ResizableParArrayCombiner;I)V
   #30 = Utf8               this
   #31 = Utf8               Lscala/collection/parallel/mutable/ResizableParArrayCombiner$ResizableParArrayCombinerC$1;
   #32 = Utf8               I
   #33 = Utf8               newLazyCombiner
   #34 = Utf8               (Lscala/collection/mutable/ArrayBuffer<Lscala/collection/parallel/mutable/ExposedArrayBuffer<TA;>;>;)Lscala/collection/parallel/mutable/ResizableParArrayCombiner<TA;>;
   #35 = Utf8               c
   #36 = Utf8               newLazyCombiner$
   #37 = Utf8               (Lscala/collection/parallel/mutable/ResizableParArrayCombiner;Lscala/collection/mutable/ArrayBuffer;)Lscala/collection/parallel/mutable/ResizableParArrayCombiner;
   #38 = NameAndType        #36:#37       // newLazyCombiner$:(Lscala/collection/parallel/mutable/ResizableParArrayCombiner;Lscala/collection/mutable/ArrayBuffer;)Lscala/collection/parallel/mutable/ResizableParArrayCombiner;
   #39 = InterfaceMethodref #7.#38        // scala/collection/parallel/mutable/ResizableParArrayCombiner.newLazyCombiner$:(Lscala/collection/parallel/mutable/ResizableParArrayCombiner;Lscala/collection/mutable/ArrayBuffer;)Lscala/collection/parallel/mutable/ResizableParArrayCombiner;
   #40 = Utf8               allocateAndCopy
   #41 = Utf8               ()Lscala/collection/parallel/mutable/ParArray;
   #42 = Utf8               ()Lscala/collection/parallel/mutable/ParArray<TA;>;
   #43 = Utf8               allocateAndCopy$
   #44 = Utf8               (Lscala/collection/parallel/mutable/ResizableParArrayCombiner;)Lscala/collection/parallel/mutable/ParArray;
   #45 = NameAndType        #43:#44       // allocateAndCopy$:(Lscala/collection/parallel/mutable/ResizableParArrayCombiner;)Lscala/collection/parallel/mutable/ParArray;
   #46 = InterfaceMethodref #7.#45        // scala/collection/parallel/mutable/ResizableParArrayCombiner.allocateAndCopy$:(Lscala/collection/parallel/mutable/ResizableParArrayCombiner;)Lscala/collection/parallel/mutable/ParArray;
   #47 = Utf8               toString
   #48 = Utf8               ()Ljava/lang/String;
   #49 = Utf8               toString$
   #50 = Utf8               (Lscala/collection/parallel/mutable/ResizableParArrayCombiner;)Ljava/lang/String;
   #51 = NameAndType        #49:#50       // toString$:(Lscala/collection/parallel/mutable/ResizableParArrayCombiner;)Ljava/lang/String;
   #52 = InterfaceMethodref #7.#51        // scala/collection/parallel/mutable/ResizableParArrayCombiner.toString$:(Lscala/collection/parallel/mutable/ResizableParArrayCombiner;)Ljava/lang/String;
   #53 = Utf8               addOne
   #54 = Utf8               (Ljava/lang/Object;)Lscala/collection/parallel/mutable/LazyCombiner;
   #55 = Utf8               (TA;)Lscala/collection/parallel/mutable/LazyCombiner<TA;Lscala/collection/parallel/mutable/ParArray<TA;>;Lscala/collection/parallel/mutable/ExposedArrayBuffer<TA;>;>;
   #56 = Utf8               elem
   #57 = Utf8               scala/collection/parallel/mutable/LazyCombiner
   #58 = Class              #57           // scala/collection/parallel/mutable/LazyCombiner
   #59 = Utf8               addOne$
   #60 = Utf8               (Lscala/collection/parallel/mutable/LazyCombiner;Ljava/lang/Object;)Lscala/collection/parallel/mutable/LazyCombiner;
   #61 = NameAndType        #59:#60       // addOne$:(Lscala/collection/parallel/mutable/LazyCombiner;Ljava/lang/Object;)Lscala/collection/parallel/mutable/LazyCombiner;
   #62 = InterfaceMethodref #58.#61       // scala/collection/parallel/mutable/LazyCombiner.addOne$:(Lscala/collection/parallel/mutable/LazyCombiner;Ljava/lang/Object;)Lscala/collection/parallel/mutable/LazyCombiner;
   #63 = Utf8               Ljava/lang/Object;
   #64 = Utf8               result
   #65 = Utf8               ()Ljava/lang/Object;
   #66 = Utf8               result$
   #67 = Utf8               (Lscala/collection/parallel/mutable/LazyCombiner;)Ljava/lang/Object;
   #68 = NameAndType        #66:#67       // result$:(Lscala/collection/parallel/mutable/LazyCombiner;)Ljava/lang/Object;
   #69 = InterfaceMethodref #58.#68       // scala/collection/parallel/mutable/LazyCombiner.result$:(Lscala/collection/parallel/mutable/LazyCombiner;)Ljava/lang/Object;
   #70 = Utf8               clear
   #71 = Utf8               ()V
   #72 = Utf8               clear$
   #73 = Utf8               (Lscala/collection/parallel/mutable/LazyCombiner;)V
   #74 = NameAndType        #72:#73       // clear$:(Lscala/collection/parallel/mutable/LazyCombiner;)V
   #75 = InterfaceMethodref #58.#74       // scala/collection/parallel/mutable/LazyCombiner.clear$:(Lscala/collection/parallel/mutable/LazyCombiner;)V
   #76 = Utf8               combine
   #77 = Utf8               (Lscala/collection/parallel/Combiner;)Lscala/collection/parallel/Combiner;
   #78 = Utf8               <N:TA;NewTo:Ljava/lang/Object;>(Lscala/collection/parallel/Combiner<TN;TNewTo;>;)Lscala/collection/parallel/Combiner<TN;TNewTo;>;
   #79 = Utf8               other
   #80 = Utf8               combine$
   #81 = Utf8               (Lscala/collection/parallel/mutable/LazyCombiner;Lscala/collection/parallel/Combiner;)Lscala/collection/parallel/Combiner;
   #82 = NameAndType        #80:#81       // combine$:(Lscala/collection/parallel/mutable/LazyCombiner;Lscala/collection/parallel/Combiner;)Lscala/collection/parallel/Combiner;
   #83 = InterfaceMethodref #58.#82       // scala/collection/parallel/mutable/LazyCombiner.combine$:(Lscala/collection/parallel/mutable/LazyCombiner;Lscala/collection/parallel/Combiner;)Lscala/collection/parallel/Combiner;
   #84 = Utf8               Lscala/collection/parallel/Combiner;
   #85 = Utf8               size
   #86 = Utf8               ()I
   #87 = Utf8               size$
   #88 = Utf8               (Lscala/collection/parallel/mutable/LazyCombiner;)I
   #89 = NameAndType        #87:#88       // size$:(Lscala/collection/parallel/mutable/LazyCombiner;)I
   #90 = InterfaceMethodref #58.#89       // scala/collection/parallel/mutable/LazyCombiner.size$:(Lscala/collection/parallel/mutable/LazyCombiner;)I
   #91 = Utf8               combinerTaskSupport
   #92 = Utf8               ()Lscala/collection/parallel/TaskSupport;
   #93 = Utf8               scala/collection/parallel/Combiner
   #94 = Class              #93           // scala/collection/parallel/Combiner
   #95 = Utf8               combinerTaskSupport$
   #96 = Utf8               (Lscala/collection/parallel/Combiner;)Lscala/collection/parallel/TaskSupport;
   #97 = NameAndType        #95:#96       // combinerTaskSupport$:(Lscala/collection/parallel/Combiner;)Lscala/collection/parallel/TaskSupport;
   #98 = InterfaceMethodref #94.#97       // scala/collection/parallel/Combiner.combinerTaskSupport$:(Lscala/collection/parallel/Combiner;)Lscala/collection/parallel/TaskSupport;
   #99 = Utf8               combinerTaskSupport_$eq
  #100 = Utf8               (Lscala/collection/parallel/TaskSupport;)V
  #101 = Utf8               cts
  #102 = Utf8               combinerTaskSupport_$eq$
  #103 = Utf8               (Lscala/collection/parallel/Combiner;Lscala/collection/parallel/TaskSupport;)V
  #104 = NameAndType        #102:#103     // combinerTaskSupport_$eq$:(Lscala/collection/parallel/Combiner;Lscala/collection/parallel/TaskSupport;)V
  #105 = InterfaceMethodref #94.#104      // scala/collection/parallel/Combiner.combinerTaskSupport_$eq$:(Lscala/collection/parallel/Combiner;Lscala/collection/parallel/TaskSupport;)V
  #106 = Utf8               canBeShared
  #107 = Utf8               ()Z
  #108 = Utf8               canBeShared$
  #109 = Utf8               (Lscala/collection/parallel/Combiner;)Z
  #110 = NameAndType        #108:#109     // canBeShared$:(Lscala/collection/parallel/Combiner;)Z
  #111 = InterfaceMethodref #94.#110      // scala/collection/parallel/Combiner.canBeShared$:(Lscala/collection/parallel/Combiner;)Z
  #112 = Utf8               resultWithTaskSupport
  #113 = Utf8               resultWithTaskSupport$
  #114 = Utf8               (Lscala/collection/parallel/Combiner;)Ljava/lang/Object;
  #115 = NameAndType        #113:#114     // resultWithTaskSupport$:(Lscala/collection/parallel/Combiner;)Ljava/lang/Object;
  #116 = InterfaceMethodref #94.#115      // scala/collection/parallel/Combiner.resultWithTaskSupport$:(Lscala/collection/parallel/Combiner;)Ljava/lang/Object;
  #117 = Utf8               fromSequential
  #118 = Utf8               (Lscala/collection/IterableOnce;)Ljava/lang/Object;
  #119 = Utf8               seq
  #120 = Utf8               fromSequential$
  #121 = Utf8               (Lscala/collection/parallel/Combiner;Lscala/collection/IterableOnce;)Ljava/lang/Object;
  #122 = NameAndType        #120:#121     // fromSequential$:(Lscala/collection/parallel/Combiner;Lscala/collection/IterableOnce;)Ljava/lang/Object;
  #123 = InterfaceMethodref #94.#122      // scala/collection/parallel/Combiner.fromSequential$:(Lscala/collection/parallel/Combiner;Lscala/collection/IterableOnce;)Ljava/lang/Object;
  #124 = Utf8               Lscala/collection/IterableOnce;
  #125 = Utf8               (Lscala/collection/IterableOnce;I)V
  #126 = Utf8               (Lscala/collection/IterableOnce<*>;I)V
  #127 = Utf8               coll
  #128 = Utf8               delta
  #129 = Utf8               scala/collection/mutable/Builder
  #130 = Class              #129          // scala/collection/mutable/Builder
  #131 = Utf8               (Lscala/collection/mutable/Builder;Lscala/collection/IterableOnce;I)V
  #132 = NameAndType        #26:#131      // sizeHint$:(Lscala/collection/mutable/Builder;Lscala/collection/IterableOnce;I)V
  #133 = InterfaceMethodref #130.#132     // scala/collection/mutable/Builder.sizeHint$:(Lscala/collection/mutable/Builder;Lscala/collection/IterableOnce;I)V
  #134 = Utf8               sizeHint$default$2
  #135 = Utf8               sizeHint$default$2$
  #136 = Utf8               (Lscala/collection/mutable/Builder;)I
  #137 = NameAndType        #135:#136     // sizeHint$default$2$:(Lscala/collection/mutable/Builder;)I
  #138 = InterfaceMethodref #130.#137     // scala/collection/mutable/Builder.sizeHint$default$2$:(Lscala/collection/mutable/Builder;)I
  #139 = Utf8               sizeHintBounded
  #140 = Utf8               (ILscala/collection/Iterable;)V
  #141 = Utf8               (ILscala/collection/Iterable<*>;)V
  #142 = Utf8               boundingColl
  #143 = Utf8               sizeHintBounded$
  #144 = Utf8               (Lscala/collection/mutable/Builder;ILscala/collection/Iterable;)V
  #145 = NameAndType        #143:#144     // sizeHintBounded$:(Lscala/collection/mutable/Builder;ILscala/collection/Iterable;)V
  #146 = InterfaceMethodref #130.#145     // scala/collection/mutable/Builder.sizeHintBounded$:(Lscala/collection/mutable/Builder;ILscala/collection/Iterable;)V
  #147 = Utf8               Lscala/collection/Iterable;
  #148 = Utf8               mapResult
  #149 = Utf8               (Lscala/Function1;)Lscala/collection/mutable/Builder;
  #150 = Utf8               <NewTo:Ljava/lang/Object;>(Lscala/Function1<Lscala/collection/parallel/mutable/ParArray<TA;>;TNewTo;>;)Lscala/collection/mutable/Builder<TA;TNewTo;>;
  #151 = Utf8               f
  #152 = Utf8               mapResult$
  #153 = Utf8               (Lscala/collection/mutable/Builder;Lscala/Function1;)Lscala/collection/mutable/Builder;
  #154 = NameAndType        #152:#153     // mapResult$:(Lscala/collection/mutable/Builder;Lscala/Function1;)Lscala/collection/mutable/Builder;
  #155 = InterfaceMethodref #130.#154     // scala/collection/mutable/Builder.mapResult$:(Lscala/collection/mutable/Builder;Lscala/Function1;)Lscala/collection/mutable/Builder;
  #156 = Utf8               Lscala/Function1;
  #157 = Utf8               $plus$eq
  #158 = Utf8               (Ljava/lang/Object;)Lscala/collection/mutable/Growable;
  #159 = Utf8               (TA;)Lscala/collection/mutable/Growable<TA;>;
  #160 = Utf8               scala/collection/mutable/Growable
  #161 = Class              #160          // scala/collection/mutable/Growable
  #162 = Utf8               $plus$eq$
  #163 = Utf8               (Lscala/collection/mutable/Growable;Ljava/lang/Object;)Lscala/collection/mutable/Growable;
  #164 = NameAndType        #162:#163     // $plus$eq$:(Lscala/collection/mutable/Growable;Ljava/lang/Object;)Lscala/collection/mutable/Growable;
  #165 = InterfaceMethodref #161.#164     // scala/collection/mutable/Growable.$plus$eq$:(Lscala/collection/mutable/Growable;Ljava/lang/Object;)Lscala/collection/mutable/Growable;
  #166 = Utf8               (Ljava/lang/Object;Ljava/lang/Object;Lscala/collection/immutable/Seq;)Lscala/collection/mutable/Growable;
  #167 = Utf8               (TA;TA;Lscala/collection/immutable/Seq<TA;>;)Lscala/collection/mutable/Growable<TA;>;
  #168 = Utf8               elem1
  #169 = Utf8               elem2
  #170 = Utf8               elems
  #171 = Utf8               (Lscala/collection/mutable/Growable;Ljava/lang/Object;Ljava/lang/Object;Lscala/collection/immutable/Seq;)Lscala/collection/mutable/Growable;
  #172 = NameAndType        #162:#171     // $plus$eq$:(Lscala/collection/mutable/Growable;Ljava/lang/Object;Ljava/lang/Object;Lscala/collection/immutable/Seq;)Lscala/collection/mutable/Growable;
  #173 = InterfaceMethodref #161.#172     // scala/collection/mutable/Growable.$plus$eq$:(Lscala/collection/mutable/Growable;Ljava/lang/Object;Ljava/lang/Object;Lscala/collection/immutable/Seq;)Lscala/collection/mutable/Growable;
  #174 = Utf8               Lscala/collection/immutable/Seq;
  #175 = Utf8               addAll
  #176 = Utf8               (Lscala/collection/IterableOnce;)Lscala/collection/mutable/Growable;
  #177 = Utf8               (Lscala/collection/IterableOnce<TA;>;)Lscala/collection/mutable/Growable<TA;>;
  #178 = Utf8               xs
  #179 = Utf8               addAll$
  #180 = Utf8               (Lscala/collection/mutable/Growable;Lscala/collection/IterableOnce;)Lscala/collection/mutable/Growable;
  #181 = NameAndType        #179:#180     // addAll$:(Lscala/collection/mutable/Growable;Lscala/collection/IterableOnce;)Lscala/collection/mutable/Growable;
  #182 = InterfaceMethodref #161.#181     // scala/collection/mutable/Growable.addAll$:(Lscala/collection/mutable/Growable;Lscala/collection/IterableOnce;)Lscala/collection/mutable/Growable;
  #183 = Utf8               $plus$plus$eq
  #184 = Utf8               $plus$plus$eq$
  #185 = NameAndType        #184:#180     // $plus$plus$eq$:(Lscala/collection/mutable/Growable;Lscala/collection/IterableOnce;)Lscala/collection/mutable/Growable;
  #186 = InterfaceMethodref #161.#185     // scala/collection/mutable/Growable.$plus$plus$eq$:(Lscala/collection/mutable/Growable;Lscala/collection/IterableOnce;)Lscala/collection/mutable/Growable;
  #187 = Utf8               knownSize
  #188 = Utf8               knownSize$
  #189 = Utf8               (Lscala/collection/mutable/Growable;)I
  #190 = NameAndType        #188:#189     // knownSize$:(Lscala/collection/mutable/Growable;)I
  #191 = InterfaceMethodref #161.#190     // scala/collection/mutable/Growable.knownSize$:(Lscala/collection/mutable/Growable;)I
  #192 = Utf8               ()Lscala/collection/parallel/mutable/ExposedArrayBuffer;
  #193 = Utf8               ()Lscala/collection/parallel/mutable/ExposedArrayBuffer<TA;>;
  #194 = NameAndType        #18:#19       // lastbuff:Lscala/collection/parallel/mutable/ExposedArrayBuffer;
  #195 = Fieldref           #2.#194       // scala/collection/parallel/mutable/ResizableParArrayCombiner$ResizableParArrayCombinerC$1.lastbuff:Lscala/collection/parallel/mutable/ExposedArrayBuffer;
  #196 = Utf8               scala$collection$parallel$mutable$LazyCombiner$_setter_$lastbuff_$eq
  #197 = Utf8               (Lscala/collection/parallel/mutable/ExposedArrayBuffer;)V
  #198 = Utf8               (Lscala/collection/parallel/mutable/ExposedArrayBuffer<TA;>;)V
  #199 = Utf8               x$1
  #200 = NameAndType        #21:#22       // _combinerTaskSupport:Lscala/collection/parallel/TaskSupport;
  #201 = Fieldref           #2.#200       // scala/collection/parallel/mutable/ResizableParArrayCombiner$ResizableParArrayCombinerC$1._combinerTaskSupport:Lscala/collection/parallel/TaskSupport;
  #202 = Utf8               _combinerTaskSupport_$eq
  #203 = Utf8               ()Lscala/collection/mutable/ArrayBuffer;
  #204 = Utf8               ()Lscala/collection/mutable/ArrayBuffer<Lscala/collection/parallel/mutable/ExposedArrayBuffer<TA;>;>;
  #205 = NameAndType        #15:#16       // chain:Lscala/collection/mutable/ArrayBuffer;
  #206 = Fieldref           #2.#205       // scala/collection/parallel/mutable/ResizableParArrayCombiner$ResizableParArrayCombinerC$1.chain:Lscala/collection/mutable/ArrayBuffer;
  #207 = NameAndType        #53:#54       // addOne:(Ljava/lang/Object;)Lscala/collection/parallel/mutable/LazyCombiner;
  #208 = Methodref          #2.#207       // scala/collection/parallel/mutable/ResizableParArrayCombiner$ResizableParArrayCombinerC$1.addOne:(Ljava/lang/Object;)Lscala/collection/parallel/mutable/LazyCombiner;
  #209 = NameAndType        #40:#41       // allocateAndCopy:()Lscala/collection/parallel/mutable/ParArray;
  #210 = Methodref          #2.#209       // scala/collection/parallel/mutable/ResizableParArrayCombiner$ResizableParArrayCombinerC$1.allocateAndCopy:()Lscala/collection/parallel/mutable/ParArray;
  #211 = Utf8               (Lscala/collection/mutable/ArrayBuffer;)Lscala/collection/parallel/mutable/LazyCombiner;
  #212 = Utf8               buffchain
  #213 = NameAndType        #33:#12       // newLazyCombiner:(Lscala/collection/mutable/ArrayBuffer;)Lscala/collection/parallel/mutable/ResizableParArrayCombiner;
  #214 = Methodref          #2.#213       // scala/collection/parallel/mutable/ResizableParArrayCombiner$ResizableParArrayCombinerC$1.newLazyCombiner:(Lscala/collection/mutable/ArrayBuffer;)Lscala/collection/parallel/mutable/ResizableParArrayCombiner;
  #215 = Utf8               (Lscala/collection/mutable/Growable;)V
  #216 = Utf8               scala/collection/parallel/mutable/ExposedArrayBuffer
  #217 = Class              #216          // scala/collection/parallel/mutable/ExposedArrayBuffer
  #218 = NameAndType        #196:#197     // scala$collection$parallel$mutable$LazyCombiner$_setter_$lastbuff_$eq:(Lscala/collection/parallel/mutable/ExposedArrayBuffer;)V
  #219 = Methodref          #2.#218       // scala/collection/parallel/mutable/ResizableParArrayCombiner$ResizableParArrayCombinerC$1.scala$collection$parallel$mutable$LazyCombiner$_setter_$lastbuff_$eq:(Lscala/collection/parallel/mutable/ExposedArrayBuffer;)V
  #220 = Utf8               Lscala/collection/mutable/Growable;
  #221 = Utf8               ()Lscala/collection/mutable/Growable;
  #222 = NameAndType        #18:#192      // lastbuff:()Lscala/collection/parallel/mutable/ExposedArrayBuffer;
  #223 = Methodref          #2.#222       // scala/collection/parallel/mutable/ResizableParArrayCombiner$ResizableParArrayCombinerC$1.lastbuff:()Lscala/collection/parallel/mutable/ExposedArrayBuffer;
  #224 = Utf8               <init>
  #225 = Utf8               (Lscala/collection/mutable/ArrayBuffer;)V
  #226 = Utf8               (Lscala/collection/mutable/ArrayBuffer<Lscala/collection/parallel/mutable/ExposedArrayBuffer<TA;>;>;)V
  #227 = NameAndType        #224:#71      // "<init>":()V
  #228 = Methodref          #5.#227       // java/lang/Object."<init>":()V
  #229 = Utf8               $init$
  #230 = NameAndType        #229:#215     // $init$:(Lscala/collection/mutable/Growable;)V
  #231 = InterfaceMethodref #161.#230     // scala/collection/mutable/Growable.$init$:(Lscala/collection/mutable/Growable;)V
  #232 = Utf8               (Lscala/collection/mutable/Builder;)V
  #233 = NameAndType        #229:#232     // $init$:(Lscala/collection/mutable/Builder;)V
  #234 = InterfaceMethodref #130.#233     // scala/collection/mutable/Builder.$init$:(Lscala/collection/mutable/Builder;)V
  #235 = Utf8               (Lscala/collection/parallel/Combiner;)V
  #236 = NameAndType        #229:#235     // $init$:(Lscala/collection/parallel/Combiner;)V
  #237 = InterfaceMethodref #94.#236      // scala/collection/parallel/Combiner.$init$:(Lscala/collection/parallel/Combiner;)V
  #238 = NameAndType        #229:#73      // $init$:(Lscala/collection/parallel/mutable/LazyCombiner;)V
  #239 = InterfaceMethodref #58.#238      // scala/collection/parallel/mutable/LazyCombiner.$init$:(Lscala/collection/parallel/mutable/LazyCombiner;)V
  #240 = Utf8               (Lscala/collection/parallel/mutable/ResizableParArrayCombiner;)V
  #241 = NameAndType        #229:#240     // $init$:(Lscala/collection/parallel/mutable/ResizableParArrayCombiner;)V
  #242 = InterfaceMethodref #7.#241       // scala/collection/parallel/mutable/ResizableParArrayCombiner.$init$:(Lscala/collection/parallel/mutable/ResizableParArrayCombiner;)V
  #243 = Utf8               scala/runtime/Statics
  #244 = Class              #243          // scala/runtime/Statics
  #245 = Utf8               releaseFence
  #246 = NameAndType        #245:#71      // releaseFence:()V
  #247 = Methodref          #244.#246     // scala/runtime/Statics.releaseFence:()V
  #248 = Utf8               Signature
  #249 = Utf8               Code
  #250 = Utf8               LineNumberTable
  #251 = Utf8               LocalVariableTable
  #252 = Utf8               MethodParameters
  #253 = Utf8               Deprecated
  #254 = Utf8               InnerClasses
  #255 = Utf8               EnclosingMethod
  #256 = Utf8               SourceFile
  #257 = Utf8               ScalaInlineInfo
  #258 = Utf8               Scala
{
  private final scala.collection.mutable.ArrayBuffer<scala.collection.parallel.mutable.ExposedArrayBuffer<A>> chain;
    descriptor: Lscala/collection/mutable/ArrayBuffer;
    flags: (0x0012) ACC_PRIVATE, ACC_FINAL
    Signature: #17                          // Lscala/collection/mutable/ArrayBuffer<Lscala/collection/parallel/mutable/ExposedArrayBuffer<TA;>;>;

  private scala.collection.parallel.mutable.ExposedArrayBuffer<A> lastbuff;
    descriptor: Lscala/collection/parallel/mutable/ExposedArrayBuffer;
    flags: (0x0002) ACC_PRIVATE
    Signature: #20                          // Lscala/collection/parallel/mutable/ExposedArrayBuffer<TA;>;

  private volatile transient scala.collection.parallel.TaskSupport _combinerTaskSupport;
    descriptor: Lscala/collection/parallel/TaskSupport;
    flags: (0x00c2) ACC_PRIVATE, ACC_VOLATILE, ACC_TRANSIENT

  public void sizeHint(int);
    descriptor: (I)V
    flags: (0x0001) ACC_PUBLIC
    Code:
      stack=2, locals=2, args_size=2
         0: aload_0
         1: iload_1
         2: invokestatic  #29                 // InterfaceMethod scala/collection/parallel/mutable/ResizableParArrayCombiner.sizeHint$:(Lscala/collection/parallel/mutable/ResizableParArrayCombiner;I)V
         5: return
      LineNumberTable:
        line 87: 0
      LocalVariableTable:
        Start  Length  Slot  Name   Signature
            0       6     0  this   Lscala/collection/parallel/mutable/ResizableParArrayCombiner$ResizableParArrayCombinerC$1;
            0       6     1    sz   I
    MethodParameters:
      Name                           Flags
      sz                             final

  public final scala.collection.parallel.mutable.ResizableParArrayCombiner<A> newLazyCombiner(scala.collection.mutable.ArrayBuffer<scala.collection.parallel.mutable.ExposedArrayBuffer<A>>);
    descriptor: (Lscala/collection/mutable/ArrayBuffer;)Lscala/collection/parallel/mutable/ResizableParArrayCombiner;
    flags: (0x0011) ACC_PUBLIC, ACC_FINAL
    Code:
      stack=2, locals=2, args_size=2
         0: aload_0
         1: aload_1
         2: invokestatic  #39                 // InterfaceMethod scala/collection/parallel/mutable/ResizableParArrayCombiner.newLazyCombiner$:(Lscala/collection/parallel/mutable/ResizableParArrayCombiner;Lscala/collection/mutable/ArrayBuffer;)Lscala/collection/parallel/mutable/ResizableParArrayCombiner;
         5: areturn
      LineNumberTable:
        line 87: 0
      LocalVariableTable:
        Start  Length  Slot  Name   Signature
            0       6     0  this   Lscala/collection/parallel/mutable/ResizableParArrayCombiner$ResizableParArrayCombinerC$1;
            0       6     1     c   Lscala/collection/mutable/ArrayBuffer;
    Signature: #34                          // (Lscala/collection/mutable/ArrayBuffer<Lscala/collection/parallel/mutable/ExposedArrayBuffer<TA;>;>;)Lscala/collection/parallel/mutable/ResizableParArrayCombiner<TA;>;
    MethodParameters:
      Name                           Flags
      c                              final

  public scala.collection.parallel.mutable.ParArray<A> allocateAndCopy();
    descriptor: ()Lscala/collection/parallel/mutable/ParArray;
    flags: (0x0001) ACC_PUBLIC
    Code:
      stack=1, locals=1, args_size=1
         0: aload_0
         1: invokestatic  #46                 // InterfaceMethod scala/collection/parallel/mutable/ResizableParArrayCombiner.allocateAndCopy$:(Lscala/collection/parallel/mutable/ResizableParArrayCombiner;)Lscala/collection/parallel/mutable/ParArray;
         4: areturn
      LineNumberTable:
        line 87: 0
      LocalVariableTable:
        Start  Length  Slot  Name   Signature
            0       5     0  this   Lscala/collection/parallel/mutable/ResizableParArrayCombiner$ResizableParArrayCombinerC$1;
    Signature: #42                          // ()Lscala/collection/parallel/mutable/ParArray<TA;>;

  public java.lang.String toString();
    descriptor: ()Ljava/lang/String;
    flags: (0x0001) ACC_PUBLIC
    Code:
      stack=1, locals=1, args_size=1
         0: aload_0
         1: invokestatic  #52                 // InterfaceMethod scala/collection/parallel/mutable/ResizableParArrayCombiner.toString$:(Lscala/collection/parallel/mutable/ResizableParArrayCombiner;)Ljava/lang/String;
         4: areturn
      LineNumberTable:
        line 87: 0
      LocalVariableTable:
        Start  Length  Slot  Name   Signature
            0       5     0  this   Lscala/collection/parallel/mutable/ResizableParArrayCombiner$ResizableParArrayCombinerC$1;

  public scala.collection.parallel.mutable.LazyCombiner<A, scala.collection.parallel.mutable.ParArray<A>, scala.collection.parallel.mutable.ExposedArrayBuffer<A>> addOne(A);
    descriptor: (Ljava/lang/Object;)Lscala/collection/parallel/mutable/LazyCombiner;
    flags: (0x0001) ACC_PUBLIC
    Code:
      stack=2, locals=2, args_size=2
         0: aload_0
         1: aload_1
         2: invokestatic  #62                 // InterfaceMethod scala/collection/parallel/mutable/LazyCombiner.addOne$:(Lscala/collection/parallel/mutable/LazyCombiner;Ljava/lang/Object;)Lscala/collection/parallel/mutable/LazyCombiner;
         5: areturn
      LineNumberTable:
        line 87: 0
      LocalVariableTable:
        Start  Length  Slot  Name   Signature
            0       6     0  this   Lscala/collection/parallel/mutable/ResizableParArrayCombiner$ResizableParArrayCombinerC$1;
            0       6     1  elem   Ljava/lang/Object;
    Signature: #55                          // (TA;)Lscala/collection/parallel/mutable/LazyCombiner<TA;Lscala/collection/parallel/mutable/ParArray<TA;>;Lscala/collection/parallel/mutable/ExposedArrayBuffer<TA;>;>;
    MethodParameters:
      Name                           Flags
      elem                           final

  public java.lang.Object result();
    descriptor: ()Ljava/lang/Object;
    flags: (0x0001) ACC_PUBLIC
    Code:
      stack=1, locals=1, args_size=1
         0: aload_0
         1: invokestatic  #69                 // InterfaceMethod scala/collection/parallel/mutable/LazyCombiner.result$:(Lscala/collection/parallel/mutable/LazyCombiner;)Ljava/lang/Object;
         4: areturn
      LineNumberTable:
        line 87: 0
      LocalVariableTable:
        Start  Length  Slot  Name   Signature
            0       5     0  this   Lscala/collection/parallel/mutable/ResizableParArrayCombiner$ResizableParArrayCombinerC$1;

  public void clear();
    descriptor: ()V
    flags: (0x0001) ACC_PUBLIC
    Code:
      stack=1, locals=1, args_size=1
         0: aload_0
         1: invokestatic  #75                 // InterfaceMethod scala/collection/parallel/mutable/LazyCombiner.clear$:(Lscala/collection/parallel/mutable/LazyCombiner;)V
         4: return
      LineNumberTable:
        line 87: 0
      LocalVariableTable:
        Start  Length  Slot  Name   Signature
            0       5     0  this   Lscala/collection/parallel/mutable/ResizableParArrayCombiner$ResizableParArrayCombinerC$1;

  public <N extends A, NewTo extends java.lang.Object> scala.collection.parallel.Combiner<N, NewTo> combine(scala.collection.parallel.Combiner<N, NewTo>);
    descriptor: (Lscala/collection/parallel/Combiner;)Lscala/collection/parallel/Combiner;
    flags: (0x0001) ACC_PUBLIC
    Code:
      stack=2, locals=2, args_size=2
         0: aload_0
         1: aload_1
         2: invokestatic  #83                 // InterfaceMethod scala/collection/parallel/mutable/LazyCombiner.combine$:(Lscala/collection/parallel/mutable/LazyCombiner;Lscala/collection/parallel/Combiner;)Lscala/collection/parallel/Combiner;
         5: areturn
      LineNumberTable:
        line 87: 0
      LocalVariableTable:
        Start  Length  Slot  Name   Signature
            0       6     0  this   Lscala/collection/parallel/mutable/ResizableParArrayCombiner$ResizableParArrayCombinerC$1;
            0       6     1 other   Lscala/collection/parallel/Combiner;
    Signature: #78                          // <N:TA;NewTo:Ljava/lang/Object;>(Lscala/collection/parallel/Combiner<TN;TNewTo;>;)Lscala/collection/parallel/Combiner<TN;TNewTo;>;
    MethodParameters:
      Name                           Flags
      other                          final

  public int size();
    descriptor: ()I
    flags: (0x0001) ACC_PUBLIC
    Code:
      stack=1, locals=1, args_size=1
         0: aload_0
         1: invokestatic  #90                 // InterfaceMethod scala/collection/parallel/mutable/LazyCombiner.size$:(Lscala/collection/parallel/mutable/LazyCombiner;)I
         4: ireturn
      LineNumberTable:
        line 87: 0
      LocalVariableTable:
        Start  Length  Slot  Name   Signature
            0       5     0  this   Lscala/collection/parallel/mutable/ResizableParArrayCombiner$ResizableParArrayCombinerC$1;

  public scala.collection.parallel.TaskSupport combinerTaskSupport();
    descriptor: ()Lscala/collection/parallel/TaskSupport;
    flags: (0x0001) ACC_PUBLIC
    Code:
      stack=1, locals=1, args_size=1
         0: aload_0
         1: invokestatic  #98                 // InterfaceMethod scala/collection/parallel/Combiner.combinerTaskSupport$:(Lscala/collection/parallel/Combiner;)Lscala/collection/parallel/TaskSupport;
         4: areturn
      LineNumberTable:
        line 87: 0
      LocalVariableTable:
        Start  Length  Slot  Name   Signature
            0       5     0  this   Lscala/collection/parallel/mutable/ResizableParArrayCombiner$ResizableParArrayCombinerC$1;

  public void combinerTaskSupport_$eq(scala.collection.parallel.TaskSupport);
    descriptor: (Lscala/collection/parallel/TaskSupport;)V
    flags: (0x0001) ACC_PUBLIC
    Code:
      stack=2, locals=2, args_size=2
         0: aload_0
         1: aload_1
         2: invokestatic  #105                // InterfaceMethod scala/collection/parallel/Combiner.combinerTaskSupport_$eq$:(Lscala/collection/parallel/Combiner;Lscala/collection/parallel/TaskSupport;)V
         5: return
      LineNumberTable:
        line 87: 0
      LocalVariableTable:
        Start  Length  Slot  Name   Signature
            0       6     0  this   Lscala/collection/parallel/mutable/ResizableParArrayCombiner$ResizableParArrayCombinerC$1;
            0       6     1   cts   Lscala/collection/parallel/TaskSupport;
    MethodParameters:
      Name                           Flags
      cts                            final

  public boolean canBeShared();
    descriptor: ()Z
    flags: (0x0001) ACC_PUBLIC
    Code:
      stack=1, locals=1, args_size=1
         0: aload_0
         1: invokestatic  #111                // InterfaceMethod scala/collection/parallel/Combiner.canBeShared$:(Lscala/collection/parallel/Combiner;)Z
         4: ireturn
      LineNumberTable:
        line 87: 0
      LocalVariableTable:
        Start  Length  Slot  Name   Signature
            0       5     0  this   Lscala/collection/parallel/mutable/ResizableParArrayCombiner$ResizableParArrayCombinerC$1;

  public java.lang.Object resultWithTaskSupport();
    descriptor: ()Ljava/lang/Object;
    flags: (0x0001) ACC_PUBLIC
    Code:
      stack=1, locals=1, args_size=1
         0: aload_0
         1: invokestatic  #116                // InterfaceMethod scala/collection/parallel/Combiner.resultWithTaskSupport$:(Lscala/collection/parallel/Combiner;)Ljava/lang/Object;
         4: areturn
      LineNumberTable:
        line 87: 0
      LocalVariableTable:
        Start  Length  Slot  Name   Signature
            0       5     0  this   Lscala/collection/parallel/mutable/ResizableParArrayCombiner$ResizableParArrayCombinerC$1;

  public java.lang.Object fromSequential(scala.collection.IterableOnce);
    descriptor: (Lscala/collection/IterableOnce;)Ljava/lang/Object;
    flags: (0x0001) ACC_PUBLIC
    Code:
      stack=2, locals=2, args_size=2
         0: aload_0
         1: aload_1
         2: invokestatic  #123                // InterfaceMethod scala/collection/parallel/Combiner.fromSequential$:(Lscala/collection/parallel/Combiner;Lscala/collection/IterableOnce;)Ljava/lang/Object;
         5: areturn
      LineNumberTable:
        line 87: 0
      LocalVariableTable:
        Start  Length  Slot  Name   Signature
            0       6     0  this   Lscala/collection/parallel/mutable/ResizableParArrayCombiner$ResizableParArrayCombinerC$1;
            0       6     1   seq   Lscala/collection/IterableOnce;
    MethodParameters:
      Name                           Flags
      seq                            final

  public final void sizeHint(scala.collection.IterableOnce<?>, int);
    descriptor: (Lscala/collection/IterableOnce;I)V
    flags: (0x0011) ACC_PUBLIC, ACC_FINAL
    Code:
      stack=3, locals=3, args_size=3
         0: aload_0
         1: aload_1
         2: iload_2
         3: invokestatic  #133                // InterfaceMethod scala/collection/mutable/Builder.sizeHint$:(Lscala/collection/mutable/Builder;Lscala/collection/IterableOnce;I)V
         6: return
      LineNumberTable:
        line 87: 0
      LocalVariableTable:
        Start  Length  Slot  Name   Signature
            0       7     0  this   Lscala/collection/parallel/mutable/ResizableParArrayCombiner$ResizableParArrayCombinerC$1;
            0       7     1  coll   Lscala/collection/IterableOnce;
            0       7     2 delta   I
    Signature: #126                         // (Lscala/collection/IterableOnce<*>;I)V
    MethodParameters:
      Name                           Flags
      coll                           final
      delta                          final

  public final int sizeHint$default$2();
    descriptor: ()I
    flags: (0x0011) ACC_PUBLIC, ACC_FINAL
    Code:
      stack=1, locals=1, args_size=1
         0: aload_0
         1: invokestatic  #138                // InterfaceMethod scala/collection/mutable/Builder.sizeHint$default$2$:(Lscala/collection/mutable/Builder;)I
         4: ireturn
      LineNumberTable:
        line 87: 0
      LocalVariableTable:
        Start  Length  Slot  Name   Signature
            0       5     0  this   Lscala/collection/parallel/mutable/ResizableParArrayCombiner$ResizableParArrayCombinerC$1;

  public final void sizeHintBounded(int, scala.collection.Iterable<?>);
    descriptor: (ILscala/collection/Iterable;)V
    flags: (0x0011) ACC_PUBLIC, ACC_FINAL
    Code:
      stack=3, locals=3, args_size=3
         0: aload_0
         1: iload_1
         2: aload_2
         3: invokestatic  #146                // InterfaceMethod scala/collection/mutable/Builder.sizeHintBounded$:(Lscala/collection/mutable/Builder;ILscala/collection/Iterable;)V
         6: return
      LineNumberTable:
        line 87: 0
      LocalVariableTable:
        Start  Length  Slot  Name   Signature
            0       7     0  this   Lscala/collection/parallel/mutable/ResizableParArrayCombiner$ResizableParArrayCombinerC$1;
            0       7     1  size   I
            0       7     2 boundingColl   Lscala/collection/Iterable;
    Signature: #141                         // (ILscala/collection/Iterable<*>;)V
    MethodParameters:
      Name                           Flags
      size                           final
      boundingColl                   final

  public <NewTo extends java.lang.Object> scala.collection.mutable.Builder<A, NewTo> mapResult(scala.Function1<scala.collection.parallel.mutable.ParArray<A>, NewTo>);
    descriptor: (Lscala/Function1;)Lscala/collection/mutable/Builder;
    flags: (0x0001) ACC_PUBLIC
    Code:
      stack=2, locals=2, args_size=2
         0: aload_0
         1: aload_1
         2: invokestatic  #155                // InterfaceMethod scala/collection/mutable/Builder.mapResult$:(Lscala/collection/mutable/Builder;Lscala/Function1;)Lscala/collection/mutable/Builder;
         5: areturn
      LineNumberTable:
        line 87: 0
      LocalVariableTable:
        Start  Length  Slot  Name   Signature
            0       6     0  this   Lscala/collection/parallel/mutable/ResizableParArrayCombiner$ResizableParArrayCombinerC$1;
            0       6     1     f   Lscala/Function1;
    Signature: #150                         // <NewTo:Ljava/lang/Object;>(Lscala/Function1<Lscala/collection/parallel/mutable/ParArray<TA;>;TNewTo;>;)Lscala/collection/mutable/Builder<TA;TNewTo;>;
    MethodParameters:
      Name                           Flags
      f                              final

  public final scala.collection.mutable.Growable<A> $plus$eq(A);
    descriptor: (Ljava/lang/Object;)Lscala/collection/mutable/Growable;
    flags: (0x0011) ACC_PUBLIC, ACC_FINAL
    Code:
      stack=2, locals=2, args_size=2
         0: aload_0
         1: aload_1
         2: invokestatic  #165                // InterfaceMethod scala/collection/mutable/Growable.$plus$eq$:(Lscala/collection/mutable/Growable;Ljava/lang/Object;)Lscala/collection/mutable/Growable;
         5: areturn
      LineNumberTable:
        line 87: 0
      LocalVariableTable:
        Start  Length  Slot  Name   Signature
            0       6     0  this   Lscala/collection/parallel/mutable/ResizableParArrayCombiner$ResizableParArrayCombinerC$1;
            0       6     1  elem   Ljava/lang/Object;
    Signature: #159                         // (TA;)Lscala/collection/mutable/Growable<TA;>;
    MethodParameters:
      Name                           Flags
      elem                           final

  public final scala.collection.mutable.Growable<A> $plus$eq(A, A, scala.collection.immutable.Seq<A>);
    descriptor: (Ljava/lang/Object;Ljava/lang/Object;Lscala/collection/immutable/Seq;)Lscala/collection/mutable/Growable;
    flags: (0x0011) ACC_PUBLIC, ACC_FINAL
    Code:
      stack=4, locals=4, args_size=4
         0: aload_0
         1: aload_1
         2: aload_2
         3: aload_3
         4: invokestatic  #173                // InterfaceMethod scala/collection/mutable/Growable.$plus$eq$:(Lscala/collection/mutable/Growable;Ljava/lang/Object;Ljava/lang/Object;Lscala/collection/immutable/Seq;)Lscala/collection/mutable/Growable;
         7: areturn
      LineNumberTable:
        line 87: 0
      LocalVariableTable:
        Start  Length  Slot  Name   Signature
            0       8     0  this   Lscala/collection/parallel/mutable/ResizableParArrayCombiner$ResizableParArrayCombinerC$1;
            0       8     1 elem1   Ljava/lang/Object;
            0       8     2 elem2   Ljava/lang/Object;
            0       8     3 elems   Lscala/collection/immutable/Seq;
    Signature: #167                         // (TA;TA;Lscala/collection/immutable/Seq<TA;>;)Lscala/collection/mutable/Growable<TA;>;
    Deprecated: true
    MethodParameters:
      Name                           Flags
      elem1                          final
      elem2                          final
      elems                          final

  public scala.collection.mutable.Growable<A> addAll(scala.collection.IterableOnce<A>);
    descriptor: (Lscala/collection/IterableOnce;)Lscala/collection/mutable/Growable;
    flags: (0x0001) ACC_PUBLIC
    Code:
      stack=2, locals=2, args_size=2
         0: aload_0
         1: aload_1
         2: invokestatic  #182                // InterfaceMethod scala/collection/mutable/Growable.addAll$:(Lscala/collection/mutable/Growable;Lscala/collection/IterableOnce;)Lscala/collection/mutable/Growable;
         5: areturn
      LineNumberTable:
        line 87: 0
      LocalVariableTable:
        Start  Length  Slot  Name   Signature
            0       6     0  this   Lscala/collection/parallel/mutable/ResizableParArrayCombiner$ResizableParArrayCombinerC$1;
            0       6     1    xs   Lscala/collection/IterableOnce;
    Signature: #177                         // (Lscala/collection/IterableOnce<TA;>;)Lscala/collection/mutable/Growable<TA;>;
    MethodParameters:
      Name                           Flags
      xs                             final

  public final scala.collection.mutable.Growable<A> $plus$plus$eq(scala.collection.IterableOnce<A>);
    descriptor: (Lscala/collection/IterableOnce;)Lscala/collection/mutable/Growable;
    flags: (0x0011) ACC_PUBLIC, ACC_FINAL
    Code:
      stack=2, locals=2, args_size=2
         0: aload_0
         1: aload_1
         2: invokestatic  #186                // InterfaceMethod scala/collection/mutable/Growable.$plus$plus$eq$:(Lscala/collection/mutable/Growable;Lscala/collection/IterableOnce;)Lscala/collection/mutable/Growable;
         5: areturn
      LineNumberTable:
        line 87: 0
      LocalVariableTable:
        Start  Length  Slot  Name   Signature
            0       6     0  this   Lscala/collection/parallel/mutable/ResizableParArrayCombiner$ResizableParArrayCombinerC$1;
            0       6     1    xs   Lscala/collection/IterableOnce;
    Signature: #177                         // (Lscala/collection/IterableOnce<TA;>;)Lscala/collection/mutable/Growable<TA;>;
    MethodParameters:
      Name                           Flags
      xs                             final

  public int knownSize();
    descriptor: ()I
    flags: (0x0001) ACC_PUBLIC
    Code:
      stack=1, locals=1, args_size=1
         0: aload_0
         1: invokestatic  #191                // InterfaceMethod scala/collection/mutable/Growable.knownSize$:(Lscala/collection/mutable/Growable;)I
         4: ireturn
      LineNumberTable:
        line 87: 0
      LocalVariableTable:
        Start  Length  Slot  Name   Signature
            0       5     0  this   Lscala/collection/parallel/mutable/ResizableParArrayCombiner$ResizableParArrayCombinerC$1;

  public scala.collection.parallel.mutable.ExposedArrayBuffer<A> lastbuff();
    descriptor: ()Lscala/collection/parallel/mutable/ExposedArrayBuffer;
    flags: (0x0001) ACC_PUBLIC
    Code:
      stack=1, locals=1, args_size=1
         0: aload_0
         1: getfield      #195                // Field lastbuff:Lscala/collection/parallel/mutable/ExposedArrayBuffer;
         4: areturn
      LineNumberTable:
        line 87: 0
      LocalVariableTable:
        Start  Length  Slot  Name   Signature
            0       5     0  this   Lscala/collection/parallel/mutable/ResizableParArrayCombiner$ResizableParArrayCombinerC$1;
    Signature: #193                         // ()Lscala/collection/parallel/mutable/ExposedArrayBuffer<TA;>;

  public void scala$collection$parallel$mutable$LazyCombiner$_setter_$lastbuff_$eq(scala.collection.parallel.mutable.ExposedArrayBuffer<A>);
    descriptor: (Lscala/collection/parallel/mutable/ExposedArrayBuffer;)V
    flags: (0x0001) ACC_PUBLIC
    Code:
      stack=2, locals=2, args_size=2
         0: aload_0
         1: aload_1
         2: putfield      #195                // Field lastbuff:Lscala/collection/parallel/mutable/ExposedArrayBuffer;
         5: return
      LineNumberTable:
        line 87: 0
      LocalVariableTable:
        Start  Length  Slot  Name   Signature
            0       6     0  this   Lscala/collection/parallel/mutable/ResizableParArrayCombiner$ResizableParArrayCombinerC$1;
            0       6     1   x$1   Lscala/collection/parallel/mutable/ExposedArrayBuffer;
    Signature: #198                         // (Lscala/collection/parallel/mutable/ExposedArrayBuffer<TA;>;)V
    MethodParameters:
      Name                           Flags
      x$1                            final

  public scala.collection.parallel.TaskSupport _combinerTaskSupport();
    descriptor: ()Lscala/collection/parallel/TaskSupport;
    flags: (0x0001) ACC_PUBLIC
    Code:
      stack=1, locals=1, args_size=1
         0: aload_0
         1: getfield      #201                // Field _combinerTaskSupport:Lscala/collection/parallel/TaskSupport;
         4: areturn
      LineNumberTable:
        line 87: 0
      LocalVariableTable:
        Start  Length  Slot  Name   Signature
            0       5     0  this   Lscala/collection/parallel/mutable/ResizableParArrayCombiner$ResizableParArrayCombinerC$1;

  public void _combinerTaskSupport_$eq(scala.collection.parallel.TaskSupport);
    descriptor: (Lscala/collection/parallel/TaskSupport;)V
    flags: (0x0001) ACC_PUBLIC
    Code:
      stack=2, locals=2, args_size=2
         0: aload_0
         1: aload_1
         2: putfield      #201                // Field _combinerTaskSupport:Lscala/collection/parallel/TaskSupport;
         5: return
      LineNumberTable:
        line 87: 0
      LocalVariableTable:
        Start  Length  Slot  Name   Signature
            0       6     0  this   Lscala/collection/parallel/mutable/ResizableParArrayCombiner$ResizableParArrayCombinerC$1;
            0       6     1   x$1   Lscala/collection/parallel/TaskSupport;
    MethodParameters:
      Name                           Flags
      x$1                            final

  public scala.collection.mutable.ArrayBuffer<scala.collection.parallel.mutable.ExposedArrayBuffer<A>> chain();
    descriptor: ()Lscala/collection/mutable/ArrayBuffer;
    flags: (0x0001) ACC_PUBLIC
    Code:
      stack=1, locals=1, args_size=1
         0: aload_0
         1: getfield      #206                // Field chain:Lscala/collection/mutable/ArrayBuffer;
         4: areturn
      LineNumberTable:
        line 87: 0
      LocalVariableTable:
        Start  Length  Slot  Name   Signature
            0       5     0  this   Lscala/collection/parallel/mutable/ResizableParArrayCombiner$ResizableParArrayCombinerC$1;
    Signature: #204                         // ()Lscala/collection/mutable/ArrayBuffer<Lscala/collection/parallel/mutable/ExposedArrayBuffer<TA;>;>;

  public scala.collection.mutable.Growable addOne(java.lang.Object);
    descriptor: (Ljava/lang/Object;)Lscala/collection/mutable/Growable;
    flags: (0x1041) ACC_PUBLIC, ACC_BRIDGE, ACC_SYNTHETIC
    Code:
      stack=2, locals=2, args_size=2
         0: aload_0
         1: aload_1
         2: invokevirtual #208                // Method addOne:(Ljava/lang/Object;)Lscala/collection/parallel/mutable/LazyCombiner;
         5: areturn
      LineNumberTable:
        line 87: 0
      LocalVariableTable:
        Start  Length  Slot  Name   Signature
            0       6     0  this   Lscala/collection/parallel/mutable/ResizableParArrayCombiner$ResizableParArrayCombinerC$1;
            0       6     1  elem   Ljava/lang/Object;
    MethodParameters:
      Name                           Flags
      elem                           final

  public java.lang.Object allocateAndCopy();
    descriptor: ()Ljava/lang/Object;
    flags: (0x1041) ACC_PUBLIC, ACC_BRIDGE, ACC_SYNTHETIC
    Code:
      stack=1, locals=1, args_size=1
         0: aload_0
         1: invokevirtual #210                // Method allocateAndCopy:()Lscala/collection/parallel/mutable/ParArray;
         4: areturn
      LineNumberTable:
        line 87: 0
      LocalVariableTable:
        Start  Length  Slot  Name   Signature
            0       5     0  this   Lscala/collection/parallel/mutable/ResizableParArrayCombiner$ResizableParArrayCombinerC$1;

  public final scala.collection.parallel.mutable.LazyCombiner newLazyCombiner(scala.collection.mutable.ArrayBuffer);
    descriptor: (Lscala/collection/mutable/ArrayBuffer;)Lscala/collection/parallel/mutable/LazyCombiner;
    flags: (0x1051) ACC_PUBLIC, ACC_FINAL, ACC_BRIDGE, ACC_SYNTHETIC
    Code:
      stack=2, locals=2, args_size=2
         0: aload_0
         1: aload_1
         2: invokevirtual #214                // Method newLazyCombiner:(Lscala/collection/mutable/ArrayBuffer;)Lscala/collection/parallel/mutable/ResizableParArrayCombiner;
         5: areturn
      LineNumberTable:
        line 87: 0
      LocalVariableTable:
        Start  Length  Slot  Name   Signature
            0       6     0  this   Lscala/collection/parallel/mutable/ResizableParArrayCombiner$ResizableParArrayCombinerC$1;
            0       6     1 buffchain   Lscala/collection/mutable/ArrayBuffer;
    MethodParameters:
      Name                           Flags
      buffchain                      final

  public void scala$collection$parallel$mutable$LazyCombiner$_setter_$lastbuff_$eq(scala.collection.mutable.Growable);
    descriptor: (Lscala/collection/mutable/Growable;)V
    flags: (0x1041) ACC_PUBLIC, ACC_BRIDGE, ACC_SYNTHETIC
    Code:
      stack=2, locals=2, args_size=2
         0: aload_0
         1: aload_1
         2: checkcast     #217                // class scala/collection/parallel/mutable/ExposedArrayBuffer
         5: invokevirtual #219                // Method scala$collection$parallel$mutable$LazyCombiner$_setter_$lastbuff_$eq:(Lscala/collection/parallel/mutable/ExposedArrayBuffer;)V
         8: return
      LineNumberTable:
        line 87: 0
      LocalVariableTable:
        Start  Length  Slot  Name   Signature
            0       9     0  this   Lscala/collection/parallel/mutable/ResizableParArrayCombiner$ResizableParArrayCombinerC$1;
            0       9     1   x$1   Lscala/collection/mutable/Growable;
    MethodParameters:
      Name                           Flags
      x$1                            final

  public scala.collection.mutable.Growable lastbuff();
    descriptor: ()Lscala/collection/mutable/Growable;
    flags: (0x1041) ACC_PUBLIC, ACC_BRIDGE, ACC_SYNTHETIC
    Code:
      stack=1, locals=1, args_size=1
         0: aload_0
         1: invokevirtual #223                // Method lastbuff:()Lscala/collection/parallel/mutable/ExposedArrayBuffer;
         4: areturn
      LineNumberTable:
        line 87: 0
      LocalVariableTable:
        Start  Length  Slot  Name   Signature
            0       5     0  this   Lscala/collection/parallel/mutable/ResizableParArrayCombiner$ResizableParArrayCombinerC$1;

  public scala.collection.parallel.mutable.ResizableParArrayCombiner$ResizableParArrayCombinerC$1(scala.collection.mutable.ArrayBuffer<scala.collection.parallel.mutable.ExposedArrayBuffer<A>>);
    descriptor: (Lscala/collection/mutable/ArrayBuffer;)V
    flags: (0x0001) ACC_PUBLIC
    Code:
      stack=2, locals=2, args_size=2
         0: aload_0
         1: aload_1
         2: putfield      #206                // Field chain:Lscala/collection/mutable/ArrayBuffer;
         5: aload_0
         6: invokespecial #228                // Method java/lang/Object."<init>":()V
         9: aload_0
        10: invokestatic  #231                // InterfaceMethod scala/collection/mutable/Growable.$init$:(Lscala/collection/mutable/Growable;)V
        13: aload_0
        14: invokestatic  #234                // InterfaceMethod scala/collection/mutable/Builder.$init$:(Lscala/collection/mutable/Builder;)V
        17: aload_0
        18: invokestatic  #237                // InterfaceMethod scala/collection/parallel/Combiner.$init$:(Lscala/collection/parallel/Combiner;)V
        21: aload_0
        22: invokestatic  #239                // InterfaceMethod scala/collection/parallel/mutable/LazyCombiner.$init$:(Lscala/collection/parallel/mutable/LazyCombiner;)V
        25: aload_0
        26: invokestatic  #242                // InterfaceMethod scala/collection/parallel/mutable/ResizableParArrayCombiner.$init$:(Lscala/collection/parallel/mutable/ResizableParArrayCombiner;)V
        29: invokestatic  #247                // Method scala/runtime/Statics.releaseFence:()V
        32: return
      LineNumberTable:
        line 87: 0
      LocalVariableTable:
        Start  Length  Slot  Name   Signature
            0      33     0  this   Lscala/collection/parallel/mutable/ResizableParArrayCombiner$ResizableParArrayCombinerC$1;
            0      33     1 chain   Lscala/collection/mutable/ArrayBuffer;
    Signature: #226                         // (Lscala/collection/mutable/ArrayBuffer<Lscala/collection/parallel/mutable/ExposedArrayBuffer<TA;>;>;)V
    MethodParameters:
      Name                           Flags
      chain                          final
}
InnerClasses:
  public #14= #2;                         // ResizableParArrayCombinerC$1=class scala/collection/parallel/mutable/ResizableParArrayCombiner$ResizableParArrayCombinerC$1
EnclosingMethod: #10.#13                // scala.collection.parallel.mutable.ResizableParArrayCombiner$.apply
Signature: #3                           // <A:Ljava/lang/Object;>Ljava/lang/Object;Lscala/collection/parallel/mutable/ResizableParArrayCombiner<TA;>;
SourceFile: "ResizableParArrayCombiner.scala"
  ScalaInlineInfo: length = 0xAE (unknown attribute)
   01 01 00 22 00 9D 00 9E 05 00 9D 00 A6 05 00 B7
   00 B0 05 00 E0 00 E1 01 00 15 00 5C 01 00 CA 00
   64 01 00 AF 00 B0 01 00 35 00 9E 01 00 35 00 36
   01 00 28 00 41 01 00 28 00 29 01 00 6A 00 6B 01
   00 0F 00 CB 01 00 46 00 47 01 00 4C 00 4D 01 00
   5B 00 5C 01 00 63 00 64 01 00 75 00 76 01 00 BB
   00 56 01 00 12 00 DD 01 00 12 00 C0 01 00 94 00
   95 01 00 21 00 D3 01 00 21 00 0C 01 00 40 00 41
   01 00 70 00 41 01 00 C4 00 D7 01 00 C4 00 C5 01
   00 55 00 56 01 00 17 00 18 01 00 17 00 7D 01 00
   86 00 56 01 00 8B 00 8C 01 00 2F 00 30 01
  Scala: length = 0x0 (unknown attribute)

