Classfile /Users/mw/Projects/slang-braindump/.jar/jar11/assemble/slang-braindump/assemble/content/scala/collection/parallel/mutable/UnrolledParArrayCombiner$.class
  Last modified May 29, 2022; size 874 bytes
  SHA-256 checksum d058632d776e7e1f6293f9bddba533fcc559d50be26e9ac221b677dbc696639e
  Compiled from "UnrolledParArrayCombiner.scala"
public final class scala.collection.parallel.mutable.UnrolledParArrayCombiner$
  minor version: 0
  major version: 52
  flags: (0x0031) ACC_PUBLIC, ACC_FINAL, ACC_SUPER
  this_class: #2                          // scala/collection/parallel/mutable/UnrolledParArrayCombiner$
  super_class: #4                         // java/lang/Object
  interfaces: 0, fields: 1, methods: 3, attributes: 4
Constant pool:
   #1 = Utf8               scala/collection/parallel/mutable/UnrolledParArrayCombiner$
   #2 = Class              #1             // scala/collection/parallel/mutable/UnrolledParArrayCombiner$
   #3 = Utf8               java/lang/Object
   #4 = Class              #3             // java/lang/Object
   #5 = Utf8               UnrolledParArrayCombiner.scala
   #6 = Utf8               scala/collection/parallel/mutable/UnrolledParArrayCombiner$$anon$1
   #7 = Class              #6             // scala/collection/parallel/mutable/UnrolledParArrayCombiner$$anon$1
   #8 = Utf8               MODULE$
   #9 = Utf8               Lscala/collection/parallel/mutable/UnrolledParArrayCombiner$;
  #10 = Utf8               <clinit>
  #11 = Utf8               ()V
  #12 = Utf8               <init>
  #13 = NameAndType        #12:#11        // "<init>":()V
  #14 = Methodref          #2.#13         // scala/collection/parallel/mutable/UnrolledParArrayCombiner$."<init>":()V
  #15 = NameAndType        #8:#9          // MODULE$:Lscala/collection/parallel/mutable/UnrolledParArrayCombiner$;
  #16 = Fieldref           #2.#15         // scala/collection/parallel/mutable/UnrolledParArrayCombiner$.MODULE$:Lscala/collection/parallel/mutable/UnrolledParArrayCombiner$;
  #17 = Utf8               apply
  #18 = Utf8               ()Lscala/collection/parallel/mutable/UnrolledParArrayCombiner;
  #19 = Utf8               <T:Ljava/lang/Object;>()Lscala/collection/parallel/mutable/UnrolledParArrayCombiner<TT;>;
  #20 = Methodref          #7.#13         // scala/collection/parallel/mutable/UnrolledParArrayCombiner$$anon$1."<init>":()V
  #21 = Utf8               this
  #22 = Methodref          #4.#13         // java/lang/Object."<init>":()V
  #23 = Utf8               Code
  #24 = Utf8               LineNumberTable
  #25 = Utf8               LocalVariableTable
  #26 = Utf8               Signature
  #27 = Utf8               InnerClasses
  #28 = Utf8               SourceFile
  #29 = Utf8               ScalaInlineInfo
  #30 = Utf8               Scala
{
  public static final scala.collection.parallel.mutable.UnrolledParArrayCombiner$ MODULE$;
    descriptor: Lscala/collection/parallel/mutable/UnrolledParArrayCombiner$;
    flags: (0x0019) ACC_PUBLIC, ACC_STATIC, ACC_FINAL

  public static {};
    descriptor: ()V
    flags: (0x0009) ACC_PUBLIC, ACC_STATIC
    Code:
      stack=2, locals=0, args_size=0
         0: new           #2                  // class scala/collection/parallel/mutable/UnrolledParArrayCombiner$
         3: dup
         4: invokespecial #14                 // Method "<init>":()V
         7: putstatic     #16                 // Field MODULE$:Lscala/collection/parallel/mutable/UnrolledParArrayCombiner$;
        10: return
      LineNumberTable:
        line 102: 0

  public <T extends java.lang.Object> scala.collection.parallel.mutable.UnrolledParArrayCombiner<T> apply();
    descriptor: ()Lscala/collection/parallel/mutable/UnrolledParArrayCombiner;
    flags: (0x0001) ACC_PUBLIC
    Code:
      stack=2, locals=1, args_size=1
         0: new           #7                  // class scala/collection/parallel/mutable/UnrolledParArrayCombiner$$anon$1
         3: dup
         4: invokespecial #20                 // Method scala/collection/parallel/mutable/UnrolledParArrayCombiner$$anon$1."<init>":()V
         7: areturn
      LineNumberTable:
        line 103: 0
      LocalVariableTable:
        Start  Length  Slot  Name   Signature
            0       8     0  this   Lscala/collection/parallel/mutable/UnrolledParArrayCombiner$;
    Signature: #19                          // <T:Ljava/lang/Object;>()Lscala/collection/parallel/mutable/UnrolledParArrayCombiner<TT;>;

  private scala.collection.parallel.mutable.UnrolledParArrayCombiner$();
    descriptor: ()V
    flags: (0x0002) ACC_PRIVATE
    Code:
      stack=1, locals=1, args_size=1
         0: aload_0
         1: invokespecial #22                 // Method java/lang/Object."<init>":()V
         4: return
      LineNumberTable:
        line 105: 0
        line 102: 4
      LocalVariableTable:
        Start  Length  Slot  Name   Signature
            0       5     0  this   Lscala/collection/parallel/mutable/UnrolledParArrayCombiner$;
}
InnerClasses:
  public final #7;                        // class scala/collection/parallel/mutable/UnrolledParArrayCombiner$$anon$1
SourceFile: "UnrolledParArrayCombiner.scala"
  ScalaInlineInfo: length = 0xE (unknown attribute)
   01 01 00 02 00 0C 00 0B 01 00 11 00 12 01
  Scala: length = 0x0 (unknown attribute)

