Classfile /Users/mw/Projects/slang-braindump/.jar/jar11/assemble/slang-braindump/assemble/content/coursier/parse/DependencyParser$$anonfun$javaOrScalaDependencyParams$3.class
  Last modified May 29, 2022; size 2551 bytes
  SHA-256 checksum 82b3b5fc73ea8202d39adb4689bdcc46889534ff2fa4134bdf2e363a6956d257
  Compiled from "DependencyParser.scala"
public final class coursier.parse.DependencyParser$$anonfun$javaOrScalaDependencyParams$3 extends scala.runtime.AbstractPartialFunction<scala.util.Either<java.lang.String, scala.Tuple2<java.lang.String, java.lang.String>>, scala.util.Left<java.lang.String, scala.runtime.Nothing$>> implements java.io.Serializable
  minor version: 0
  major version: 52
  flags: (0x0031) ACC_PUBLIC, ACC_FINAL, ACC_SUPER
  this_class: #2                          // coursier/parse/DependencyParser$$anonfun$javaOrScalaDependencyParams$3
  super_class: #5                         // scala/runtime/AbstractPartialFunction
  interfaces: 1, fields: 1, methods: 5, attributes: 6
Constant pool:
   #1 = Utf8               coursier/parse/DependencyParser$$anonfun$javaOrScalaDependencyParams$3
   #2 = Class              #1             // coursier/parse/DependencyParser$$anonfun$javaOrScalaDependencyParams$3
   #3 = Utf8               Lscala/runtime/AbstractPartialFunction<Lscala/util/Either<Ljava/lang/String;Lscala/Tuple2<Ljava/lang/String;Ljava/lang/String;>;>;Lscala/util/Left<Ljava/lang/String;Lscala/runtime/Nothing$;>;>;Ljava/io/Serializable;
   #4 = Utf8               scala/runtime/AbstractPartialFunction
   #5 = Class              #4             // scala/runtime/AbstractPartialFunction
   #6 = Utf8               java/io/Serializable
   #7 = Class              #6             // java/io/Serializable
   #8 = Utf8               DependencyParser.scala
   #9 = Utf8               coursier/parse/DependencyParser$
  #10 = Class              #9             // coursier/parse/DependencyParser$
  #11 = Utf8               javaOrScalaDependencyParams
  #12 = Utf8               (Ljava/lang/String;Ljava/lang/String;)Lscala/util/Either;
  #13 = NameAndType        #11:#12        // javaOrScalaDependencyParams:(Ljava/lang/String;Ljava/lang/String;)Lscala/util/Either;
  #14 = Utf8               serialVersionUID
  #15 = Utf8               J
  #16 = Long               0l
  #18 = Utf8               applyOrElse
  #19 = Utf8               (Lscala/util/Either;Lscala/Function1;)Ljava/lang/Object;
  #20 = Utf8               <A1:Lscala/util/Either<Ljava/lang/String;Lscala/Tuple2<Ljava/lang/String;Ljava/lang/String;>;>;B1:Ljava/lang/Object;>(TA1;Lscala/Function1<TA1;TB1;>;)TB1;
  #21 = Utf8               x1
  #22 = Utf8               default
  #23 = Utf8               scala/util/Left
  #24 = Class              #23            // scala/util/Left
  #25 = Utf8               value
  #26 = Utf8               ()Ljava/lang/Object;
  #27 = NameAndType        #25:#26        // value:()Ljava/lang/Object;
  #28 = Methodref          #24.#27        // scala/util/Left.value:()Ljava/lang/Object;
  #29 = Utf8               java/lang/String
  #30 = Class              #29            // java/lang/String
  #31 = Utf8               scala/package$
  #32 = Class              #31            // scala/package$
  #33 = Utf8               MODULE$
  #34 = Utf8               Lscala/package$;
  #35 = NameAndType        #33:#34        // MODULE$:Lscala/package$;
  #36 = Fieldref           #32.#35        // scala/package$.MODULE$:Lscala/package$;
  #37 = Utf8               Left
  #38 = Utf8               ()Lscala/util/Left$;
  #39 = NameAndType        #37:#38        // Left:()Lscala/util/Left$;
  #40 = Methodref          #32.#39        // scala/package$.Left:()Lscala/util/Left$;
  #41 = Utf8               scala/util/Left$
  #42 = Class              #41            // scala/util/Left$
  #43 = Utf8               apply
  #44 = Utf8               (Ljava/lang/Object;)Lscala/util/Left;
  #45 = NameAndType        #43:#44        // apply:(Ljava/lang/Object;)Lscala/util/Left;
  #46 = Methodref          #42.#45        // scala/util/Left$.apply:(Ljava/lang/Object;)Lscala/util/Left;
  #47 = Utf8               scala/util/Either
  #48 = Class              #47            // scala/util/Either
  #49 = Utf8               scala/Function1
  #50 = Class              #49            // scala/Function1
  #51 = Utf8               (Ljava/lang/Object;)Ljava/lang/Object;
  #52 = NameAndType        #43:#51        // apply:(Ljava/lang/Object;)Ljava/lang/Object;
  #53 = InterfaceMethodref #50.#52        // scala/Function1.apply:(Ljava/lang/Object;)Ljava/lang/Object;
  #54 = Utf8               java/lang/Object
  #55 = Class              #54            // java/lang/Object
  #56 = Utf8               err
  #57 = Utf8               Ljava/lang/String;
  #58 = Utf8               this
  #59 = Utf8               Lcoursier/parse/DependencyParser$$anonfun$javaOrScalaDependencyParams$3;
  #60 = Utf8               Lscala/util/Either;
  #61 = Utf8               Lscala/Function1;
  #62 = Utf8               isDefinedAt
  #63 = Utf8               (Lscala/util/Either;)Z
  #64 = Utf8               (Lscala/util/Either<Ljava/lang/String;Lscala/Tuple2<Ljava/lang/String;Ljava/lang/String;>;>;)Z
  #65 = Utf8               (Ljava/lang/Object;)Z
  #66 = Utf8               x
  #67 = NameAndType        #62:#63        // isDefinedAt:(Lscala/util/Either;)Z
  #68 = Methodref          #2.#67         // coursier/parse/DependencyParser$$anonfun$javaOrScalaDependencyParams$3.isDefinedAt:(Lscala/util/Either;)Z
  #69 = Utf8               Ljava/lang/Object;
  #70 = Utf8               (Ljava/lang/Object;Lscala/Function1;)Ljava/lang/Object;
  #71 = NameAndType        #18:#19        // applyOrElse:(Lscala/util/Either;Lscala/Function1;)Ljava/lang/Object;
  #72 = Methodref          #2.#71         // coursier/parse/DependencyParser$$anonfun$javaOrScalaDependencyParams$3.applyOrElse:(Lscala/util/Either;Lscala/Function1;)Ljava/lang/Object;
  #73 = Utf8               <init>
  #74 = Utf8               ()V
  #75 = NameAndType        #73:#74        // "<init>":()V
  #76 = Methodref          #5.#75         // scala/runtime/AbstractPartialFunction."<init>":()V
  #77 = Utf8               ConstantValue
  #78 = Utf8               Code
  #79 = Utf8               StackMapTable
  #80 = Utf8               LineNumberTable
  #81 = Utf8               LocalVariableTable
  #82 = Utf8               Signature
  #83 = Utf8               MethodParameters
  #84 = Utf8               InnerClasses
  #85 = Utf8               EnclosingMethod
  #86 = Utf8               SourceFile
  #87 = Utf8               ScalaInlineInfo
  #88 = Utf8               Scala
{
  private static final long serialVersionUID;
    descriptor: J
    flags: (0x001a) ACC_PRIVATE, ACC_STATIC, ACC_FINAL
    ConstantValue: long 0l

  public final <A1 extends scala.util.Either<java.lang.String, scala.Tuple2<java.lang.String, java.lang.String>>, B1 extends java.lang.Object> B1 applyOrElse(A1, scala.Function1<A1, B1>);
    descriptor: (Lscala/util/Either;Lscala/Function1;)Ljava/lang/Object;
    flags: (0x0011) ACC_PUBLIC, ACC_FINAL
    Code:
      stack=2, locals=7, args_size=3
         0: aload_1
         1: astore        4
         3: aload         4
         5: instanceof    #24                 // class scala/util/Left
         8: ifeq          43
        11: aload         4
        13: checkcast     #24                 // class scala/util/Left
        16: astore        5
        18: aload         5
        20: invokevirtual #28                 // Method scala/util/Left.value:()Ljava/lang/Object;
        23: checkcast     #30                 // class java/lang/String
        26: astore        6
        28: getstatic     #36                 // Field scala/package$.MODULE$:Lscala/package$;
        31: invokevirtual #40                 // Method scala/package$.Left:()Lscala/util/Left$;
        34: aload         6
        36: invokevirtual #46                 // Method scala/util/Left$.apply:(Ljava/lang/Object;)Lscala/util/Left;
        39: astore_3
        40: goto          57
        43: goto          46
        46: aload_2
        47: aload_1
        48: invokeinterface #53,  2           // InterfaceMethod scala/Function1.apply:(Ljava/lang/Object;)Ljava/lang/Object;
        53: astore_3
        54: goto          57
        57: aload_3
        58: areturn
      StackMapTable: number_of_entries = 3
        frame_type = 253 /* append */
          offset_delta = 43
          locals = [ top, class scala/util/Either ]
        frame_type = 2 /* same */
        frame_type = 255 /* full_frame */
          offset_delta = 10
          locals = [ class coursier/parse/DependencyParser$$anonfun$javaOrScalaDependencyParams$3, class scala/util/Either, class scala/Function1, class java/lang/Object, class scala/util/Either ]
          stack = []
      LineNumberTable:
        line 205: 0
        line 206: 3
        line 208: 28
        line 206: 43
        line 205: 46
      LocalVariableTable:
        Start  Length  Slot  Name   Signature
           28      15     6   err   Ljava/lang/String;
            0      59     0  this   Lcoursier/parse/DependencyParser$$anonfun$javaOrScalaDependencyParams$3;
            0      59     1    x1   Lscala/util/Either;
            0      59     2 default   Lscala/Function1;
    Signature: #20                          // <A1:Lscala/util/Either<Ljava/lang/String;Lscala/Tuple2<Ljava/lang/String;Ljava/lang/String;>;>;B1:Ljava/lang/Object;>(TA1;Lscala/Function1<TA1;TB1;>;)TB1;
    MethodParameters:
      Name                           Flags
      x1                             final
      default                        final

  public final boolean isDefinedAt(scala.util.Either<java.lang.String, scala.Tuple2<java.lang.String, java.lang.String>>);
    descriptor: (Lscala/util/Either;)Z
    flags: (0x0011) ACC_PUBLIC, ACC_FINAL
    Code:
      stack=1, locals=4, args_size=2
         0: aload_1
         1: astore_3
         2: aload_3
         3: instanceof    #24                 // class scala/util/Left
         6: ifeq          14
         9: iconst_1
        10: istore_2
        11: goto          22
        14: goto          17
        17: iconst_0
        18: istore_2
        19: goto          22
        22: iload_2
        23: ireturn
      StackMapTable: number_of_entries = 3
        frame_type = 253 /* append */
          offset_delta = 14
          locals = [ top, class scala/util/Either ]
        frame_type = 2 /* same */
        frame_type = 255 /* full_frame */
          offset_delta = 4
          locals = [ class coursier/parse/DependencyParser$$anonfun$javaOrScalaDependencyParams$3, class scala/util/Either, int, class scala/util/Either ]
          stack = []
      LineNumberTable:
        line 205: 0
        line 206: 2
        line 208: 9
        line 206: 14
        line 205: 17
      LocalVariableTable:
        Start  Length  Slot  Name   Signature
            0      24     0  this   Lcoursier/parse/DependencyParser$$anonfun$javaOrScalaDependencyParams$3;
            0      24     1    x1   Lscala/util/Either;
    Signature: #64                          // (Lscala/util/Either<Ljava/lang/String;Lscala/Tuple2<Ljava/lang/String;Ljava/lang/String;>;>;)Z
    MethodParameters:
      Name                           Flags
      x1                             final

  public final boolean isDefinedAt(java.lang.Object);
    descriptor: (Ljava/lang/Object;)Z
    flags: (0x1051) ACC_PUBLIC, ACC_FINAL, ACC_BRIDGE, ACC_SYNTHETIC
    Code:
      stack=2, locals=2, args_size=2
         0: aload_0
         1: aload_1
         2: checkcast     #48                 // class scala/util/Either
         5: invokevirtual #68                 // Method isDefinedAt:(Lscala/util/Either;)Z
         8: ireturn
      LineNumberTable:
        line 205: 0
      LocalVariableTable:
        Start  Length  Slot  Name   Signature
            0       9     0  this   Lcoursier/parse/DependencyParser$$anonfun$javaOrScalaDependencyParams$3;
            0       9     1     x   Ljava/lang/Object;
    MethodParameters:
      Name                           Flags
      x                              final

  public final java.lang.Object applyOrElse(java.lang.Object, scala.Function1);
    descriptor: (Ljava/lang/Object;Lscala/Function1;)Ljava/lang/Object;
    flags: (0x1051) ACC_PUBLIC, ACC_FINAL, ACC_BRIDGE, ACC_SYNTHETIC
    Code:
      stack=3, locals=3, args_size=3
         0: aload_0
         1: aload_1
         2: checkcast     #48                 // class scala/util/Either
         5: aload_2
         6: invokevirtual #72                 // Method applyOrElse:(Lscala/util/Either;Lscala/Function1;)Ljava/lang/Object;
         9: areturn
      LineNumberTable:
        line 205: 0
      LocalVariableTable:
        Start  Length  Slot  Name   Signature
            0      10     0  this   Lcoursier/parse/DependencyParser$$anonfun$javaOrScalaDependencyParams$3;
            0      10     1     x   Ljava/lang/Object;
            0      10     2 default   Lscala/Function1;
    MethodParameters:
      Name                           Flags
      x                              final
      default                        final

  public coursier.parse.DependencyParser$$anonfun$javaOrScalaDependencyParams$3();
    descriptor: ()V
    flags: (0x0001) ACC_PUBLIC
    Code:
      stack=1, locals=1, args_size=1
         0: aload_0
         1: invokespecial #76                 // Method scala/runtime/AbstractPartialFunction."<init>":()V
         4: return
      LineNumberTable:
        line 205: 0
      LocalVariableTable:
        Start  Length  Slot  Name   Signature
            0       5     0  this   Lcoursier/parse/DependencyParser$$anonfun$javaOrScalaDependencyParams$3;
}
InnerClasses:
  public final #2;                        // class coursier/parse/DependencyParser$$anonfun$javaOrScalaDependencyParams$3
EnclosingMethod: #10.#13                // coursier.parse.DependencyParser$.javaOrScalaDependencyParams
Signature: #3                           // Lscala/runtime/AbstractPartialFunction<Lscala/util/Either<Ljava/lang/String;Lscala/Tuple2<Ljava/lang/String;Ljava/lang/String;>;>;Lscala/util/Left<Ljava/lang/String;Lscala/runtime/Nothing$;>;>;Ljava/io/Serializable;
SourceFile: "DependencyParser.scala"
  ScalaInlineInfo: length = 0x1D (unknown attribute)
   01 01 00 05 00 49 00 4A 01 00 12 00 46 01 00 12
   00 13 01 00 3E 00 41 01 00 3E 00 3F 01
  Scala: length = 0x0 (unknown attribute)

