Classfile /Users/mw/Projects/slang-braindump/.jar/jar11/assemble/slang-braindump/assemble/content/coursier/parse/JsonRuleParser$anon$derivedDecodeJson$macro$23$1$anon$macro$16$1.class
  Last modified May 29, 2022; size 3517 bytes
  SHA-256 checksum dfb464155216171f5c179434b18360973220de248e9a5c237133cc0ab0898a55
  Compiled from "JsonRuleParser.scala"
public final class coursier.parse.JsonRuleParser$anon$derivedDecodeJson$macro$23$1$anon$macro$16$1 extends java.lang.Object implements shapeless.Generic<coursier.parse.JsonRuleParser$Helper$1>
  minor version: 0
  major version: 52
  flags: (0x0031) ACC_PUBLIC, ACC_FINAL, ACC_SUPER
  this_class: #2                          // coursier/parse/JsonRuleParser$anon$derivedDecodeJson$macro$23$1$anon$macro$16$1
  super_class: #5                         // java/lang/Object
  interfaces: 1, fields: 1, methods: 5, attributes: 6
Constant pool:
    #1 = Utf8               coursier/parse/JsonRuleParser$anon$derivedDecodeJson$macro$23$1$anon$macro$16$1
    #2 = Class              #1            // coursier/parse/JsonRuleParser$anon$derivedDecodeJson$macro$23$1$anon$macro$16$1
    #3 = Utf8               Ljava/lang/Object;Lshapeless/Generic<Lcoursier/parse/JsonRuleParser$Helper$1;>;
    #4 = Utf8               java/lang/Object
    #5 = Class              #4            // java/lang/Object
    #6 = Utf8               shapeless/Generic
    #7 = Class              #6            // shapeless/Generic
    #8 = Utf8               JsonRuleParser.scala
    #9 = Utf8               coursier/parse/JsonRuleParser$anon$derivedDecodeJson$macro$23$1
   #10 = Class              #9            // coursier/parse/JsonRuleParser$anon$derivedDecodeJson$macro$23$1
   #11 = Utf8               coursier/parse/JsonRuleParser$Helper$1
   #12 = Class              #11           // coursier/parse/JsonRuleParser$Helper$1
   #13 = Utf8               1
   #14 = Utf8               coursier/parse/JsonRuleParser$Helper$2$
   #15 = Class              #14           // coursier/parse/JsonRuleParser$Helper$2$
   #16 = Utf8
   #17 = Utf8               $outer
   #18 = Utf8               Lcoursier/parse/JsonRuleParser$anon$derivedDecodeJson$macro$23$1;
   #19 = Utf8               to
   #20 = Utf8               (Lcoursier/parse/JsonRuleParser$Helper$1;)Lshapeless/$colon$colon;
   #21 = Utf8               (Lcoursier/parse/JsonRuleParser$Helper$1;)Lshapeless/$colon$colon<Lscala/collection/immutable/List<Lcoursier/util/ModuleMatcher;>;Lshapeless/$colon$colon<Lscala/collection/immutable/List<Lcoursier/util/ModuleMatcher;>;Lshapeless/HNil;>;>;
   #22 = Utf8               p
   #23 = Utf8               exclude
   #24 = Utf8               ()Lscala/collection/immutable/List;
   #25 = NameAndType        #23:#24       // exclude:()Lscala/collection/immutable/List;
   #26 = Methodref          #12.#25       // coursier/parse/JsonRuleParser$Helper$1.exclude:()Lscala/collection/immutable/List;
   #27 = Utf8               include
   #28 = NameAndType        #27:#24       // include:()Lscala/collection/immutable/List;
   #29 = Methodref          #12.#28       // coursier/parse/JsonRuleParser$Helper$1.include:()Lscala/collection/immutable/List;
   #30 = Utf8               shapeless/$colon$colon
   #31 = Class              #30           // shapeless/$colon$colon
   #32 = Utf8               shapeless/HNil$
   #33 = Class              #32           // shapeless/HNil$
   #34 = Utf8               MODULE$
   #35 = Utf8               Lshapeless/HNil$;
   #36 = NameAndType        #34:#35       // MODULE$:Lshapeless/HNil$;
   #37 = Fieldref           #33.#36       // shapeless/HNil$.MODULE$:Lshapeless/HNil$;
   #38 = Utf8               <init>
   #39 = Utf8               (Ljava/lang/Object;Lshapeless/HList;)V
   #40 = NameAndType        #38:#39       // "<init>":(Ljava/lang/Object;Lshapeless/HList;)V
   #41 = Methodref          #31.#40       // shapeless/$colon$colon."<init>":(Ljava/lang/Object;Lshapeless/HList;)V
   #42 = Utf8               scala/MatchError
   #43 = Class              #42           // scala/MatchError
   #44 = Utf8               (Ljava/lang/Object;)V
   #45 = NameAndType        #38:#44       // "<init>":(Ljava/lang/Object;)V
   #46 = Methodref          #43.#45       // scala/MatchError."<init>":(Ljava/lang/Object;)V
   #47 = Utf8               scala/collection/immutable/List
   #48 = Class              #47           // scala/collection/immutable/List
   #49 = Utf8               pat$macro$14
   #50 = Utf8               Lscala/collection/immutable/List;
   #51 = Utf8               pat$macro$15
   #52 = Utf8               this
   #53 = Utf8               Lcoursier/parse/JsonRuleParser$anon$derivedDecodeJson$macro$23$1$anon$macro$16$1;
   #54 = Utf8               Lcoursier/parse/JsonRuleParser$Helper$1;
   #55 = Utf8               from
   #56 = Utf8               (Lshapeless/$colon$colon;)Lcoursier/parse/JsonRuleParser$Helper$1;
   #57 = Utf8               (Lshapeless/$colon$colon<Lscala/collection/immutable/List<Lcoursier/util/ModuleMatcher;>;Lshapeless/$colon$colon<Lscala/collection/immutable/List<Lcoursier/util/ModuleMatcher;>;Lshapeless/HNil;>;>;)Lcoursier/parse/JsonRuleParser$Helper$1;
   #58 = Utf8               head
   #59 = Utf8               ()Ljava/lang/Object;
   #60 = NameAndType        #58:#59       // head:()Ljava/lang/Object;
   #61 = Methodref          #31.#60       // shapeless/$colon$colon.head:()Ljava/lang/Object;
   #62 = Utf8               tail
   #63 = Utf8               ()Lshapeless/HList;
   #64 = NameAndType        #62:#63       // tail:()Lshapeless/HList;
   #65 = Methodref          #31.#64       // shapeless/$colon$colon.tail:()Lshapeless/HList;
   #66 = Utf8               shapeless/HNil
   #67 = Class              #66           // shapeless/HNil
   #68 = Utf8               equals
   #69 = Utf8               (Ljava/lang/Object;)Z
   #70 = NameAndType        #68:#69       // equals:(Ljava/lang/Object;)Z
   #71 = Methodref          #5.#70        // java/lang/Object.equals:(Ljava/lang/Object;)Z
   #72 = NameAndType        #17:#18       // $outer:Lcoursier/parse/JsonRuleParser$anon$derivedDecodeJson$macro$23$1;
   #73 = Fieldref           #2.#72        // coursier/parse/JsonRuleParser$anon$derivedDecodeJson$macro$23$1$anon$macro$16$1.$outer:Lcoursier/parse/JsonRuleParser$anon$derivedDecodeJson$macro$23$1;
   #74 = Utf8               coursier$parse$JsonRuleParser$anon$derivedDecodeJson$macro$23$$$outer
   #75 = Utf8               ()Lcoursier/parse/JsonRuleParser;
   #76 = NameAndType        #74:#75       // coursier$parse$JsonRuleParser$anon$derivedDecodeJson$macro$23$$$outer:()Lcoursier/parse/JsonRuleParser;
   #77 = Methodref          #10.#76       // coursier/parse/JsonRuleParser$anon$derivedDecodeJson$macro$23$1.coursier$parse$JsonRuleParser$anon$derivedDecodeJson$macro$23$$$outer:()Lcoursier/parse/JsonRuleParser;
   #78 = Utf8               Helper$module$1
   #79 = Utf8               Lscala/runtime/LazyRef;
   #80 = NameAndType        #78:#79       // Helper$module$1:Lscala/runtime/LazyRef;
   #81 = Fieldref           #10.#80       // coursier/parse/JsonRuleParser$anon$derivedDecodeJson$macro$23$1.Helper$module$1:Lscala/runtime/LazyRef;
   #82 = Utf8               coursier/parse/JsonRuleParser
   #83 = Class              #82           // coursier/parse/JsonRuleParser
   #84 = Utf8               coursier$parse$JsonRuleParser$$Helper$3
   #85 = Utf8               (Lscala/runtime/LazyRef;)Lcoursier/parse/JsonRuleParser$Helper$2$;
   #86 = NameAndType        #84:#85       // coursier$parse$JsonRuleParser$$Helper$3:(Lscala/runtime/LazyRef;)Lcoursier/parse/JsonRuleParser$Helper$2$;
   #87 = Methodref          #83.#86       // coursier/parse/JsonRuleParser.coursier$parse$JsonRuleParser$$Helper$3:(Lscala/runtime/LazyRef;)Lcoursier/parse/JsonRuleParser$Helper$2$;
   #88 = Utf8               apply
   #89 = Utf8               (Lscala/collection/immutable/List;Lscala/collection/immutable/List;)Lcoursier/parse/JsonRuleParser$Helper$1;
   #90 = NameAndType        #88:#89       // apply:(Lscala/collection/immutable/List;Lscala/collection/immutable/List;)Lcoursier/parse/JsonRuleParser$Helper$1;
   #91 = Methodref          #15.#90       // coursier/parse/JsonRuleParser$Helper$2$.apply:(Lscala/collection/immutable/List;Lscala/collection/immutable/List;)Lcoursier/parse/JsonRuleParser$Helper$1;
   #92 = Utf8               Lshapeless/$colon$colon;
   #93 = Utf8               (Ljava/lang/Object;)Ljava/lang/Object;
   #94 = Utf8               r
   #95 = NameAndType        #55:#56       // from:(Lshapeless/$colon$colon;)Lcoursier/parse/JsonRuleParser$Helper$1;
   #96 = Methodref          #2.#95        // coursier/parse/JsonRuleParser$anon$derivedDecodeJson$macro$23$1$anon$macro$16$1.from:(Lshapeless/$colon$colon;)Lcoursier/parse/JsonRuleParser$Helper$1;
   #97 = Utf8               Ljava/lang/Object;
   #98 = Utf8               t
   #99 = NameAndType        #19:#20       // to:(Lcoursier/parse/JsonRuleParser$Helper$1;)Lshapeless/$colon$colon;
  #100 = Methodref          #2.#99        // coursier/parse/JsonRuleParser$anon$derivedDecodeJson$macro$23$1$anon$macro$16$1.to:(Lcoursier/parse/JsonRuleParser$Helper$1;)Lshapeless/$colon$colon;
  #101 = Utf8               (Lcoursier/parse/JsonRuleParser$anon$derivedDecodeJson$macro$23$1;)V
  #102 = Utf8               ()V
  #103 = NameAndType        #38:#102      // "<init>":()V
  #104 = Methodref          #5.#103       // java/lang/Object."<init>":()V
  #105 = Utf8               Code
  #106 = Utf8               StackMapTable
  #107 = Utf8               LineNumberTable
  #108 = Utf8               LocalVariableTable
  #109 = Utf8               Signature
  #110 = Utf8               MethodParameters
  #111 = Utf8               InnerClasses
  #112 = Utf8               EnclosingMethod
  #113 = Utf8               SourceFile
  #114 = Utf8               ScalaInlineInfo
  #115 = Utf8               Scala
{
  private final coursier.parse.JsonRuleParser$anon$derivedDecodeJson$macro$23$1 $outer;
    descriptor: Lcoursier/parse/JsonRuleParser$anon$derivedDecodeJson$macro$23$1;
    flags: (0x1012) ACC_PRIVATE, ACC_FINAL, ACC_SYNTHETIC

  public shapeless.$colon$colon<scala.collection.immutable.List<coursier.util.ModuleMatcher>, shapeless.$colon$colon<scala.collection.immutable.List<coursier.util.ModuleMatcher>, shapeless.HNil>> to(coursier.parse.JsonRuleParser$Helper$1);
    descriptor: (Lcoursier/parse/JsonRuleParser$Helper$1;)Lshapeless/$colon$colon;
    flags: (0x0001) ACC_PUBLIC
    Code:
      stack=7, locals=6, args_size=2
         0: aload_1
         1: astore_3
         2: aload_3
         3: ifnull        43
         6: aload_3
         7: invokevirtual #26                 // Method coursier/parse/JsonRuleParser$Helper$1.exclude:()Lscala/collection/immutable/List;
        10: astore        4
        12: aload_3
        13: invokevirtual #29                 // Method coursier/parse/JsonRuleParser$Helper$1.include:()Lscala/collection/immutable/List;
        16: astore        5
        18: new           #31                 // class shapeless/$colon$colon
        21: dup
        22: aload         4
        24: new           #31                 // class shapeless/$colon$colon
        27: dup
        28: aload         5
        30: getstatic     #37                 // Field shapeless/HNil$.MODULE$:Lshapeless/HNil$;
        33: invokespecial #41                 // Method shapeless/$colon$colon."<init>":(Ljava/lang/Object;Lshapeless/HList;)V
        36: invokespecial #41                 // Method shapeless/$colon$colon."<init>":(Ljava/lang/Object;Lshapeless/HList;)V
        39: astore_2
        40: goto          55
        43: goto          46
        46: new           #43                 // class scala/MatchError
        49: dup
        50: aload_3
        51: invokespecial #46                 // Method scala/MatchError."<init>":(Ljava/lang/Object;)V
        54: athrow
        55: aload_2
        56: areturn
      StackMapTable: number_of_entries = 3
        frame_type = 253 /* append */
          offset_delta = 43
          locals = [ top, class coursier/parse/JsonRuleParser$Helper$1 ]
        frame_type = 2 /* same */
        frame_type = 255 /* full_frame */
          offset_delta = 8
          locals = [ class coursier/parse/JsonRuleParser$anon$derivedDecodeJson$macro$23$1$anon$macro$16$1, class coursier/parse/JsonRuleParser$Helper$1, class shapeless/$colon$colon, class coursier/parse/JsonRuleParser$Helper$1, class scala/collection/immutable/List, class scala/collection/immutable/List ]
          stack = []
      LineNumberTable:
        line 37: 0
      LocalVariableTable:
        Start  Length  Slot  Name   Signature
           12      31     4 pat$macro$14   Lscala/collection/immutable/List;
           18      25     5 pat$macro$15   Lscala/collection/immutable/List;
            0      57     0  this   Lcoursier/parse/JsonRuleParser$anon$derivedDecodeJson$macro$23$1$anon$macro$16$1;
            0      57     1     p   Lcoursier/parse/JsonRuleParser$Helper$1;
    Signature: #21                          // (Lcoursier/parse/JsonRuleParser$Helper$1;)Lshapeless/$colon$colon<Lscala/collection/immutable/List<Lcoursier/util/ModuleMatcher;>;Lshapeless/$colon$colon<Lscala/collection/immutable/List<Lcoursier/util/ModuleMatcher;>;Lshapeless/HNil;>;>;
    MethodParameters:
      Name                           Flags
      p                              final

  public coursier.parse.JsonRuleParser$Helper$1 from(shapeless.$colon$colon<scala.collection.immutable.List<coursier.util.ModuleMatcher>, shapeless.$colon$colon<scala.collection.immutable.List<coursier.util.ModuleMatcher>, shapeless.HNil>>);
    descriptor: (Lshapeless/$colon$colon;)Lcoursier/parse/JsonRuleParser$Helper$1;
    flags: (0x0001) ACC_PUBLIC
    Code:
      stack=3, locals=8, args_size=2
         0: aload_1
         1: astore_3
         2: aload_3
         3: ifnull        94
         6: aload_3
         7: invokevirtual #61                 // Method shapeless/$colon$colon.head:()Ljava/lang/Object;
        10: checkcast     #48                 // class scala/collection/immutable/List
        13: astore        4
        15: aload_3
        16: invokevirtual #65                 // Method shapeless/$colon$colon.tail:()Lshapeless/HList;
        19: checkcast     #31                 // class shapeless/$colon$colon
        22: astore        5
        24: aload         5
        26: ifnull        91
        29: aload         5
        31: invokevirtual #61                 // Method shapeless/$colon$colon.head:()Ljava/lang/Object;
        34: checkcast     #48                 // class scala/collection/immutable/List
        37: astore        6
        39: aload         5
        41: invokevirtual #65                 // Method shapeless/$colon$colon.tail:()Lshapeless/HList;
        44: checkcast     #67                 // class shapeless/HNil
        47: astore        7
        49: getstatic     #37                 // Field shapeless/HNil$.MODULE$:Lshapeless/HNil$;
        52: aload         7
        54: invokevirtual #71                 // Method java/lang/Object.equals:(Ljava/lang/Object;)Z
        57: ifeq          88
        60: aload_0
        61: getfield      #73                 // Field $outer:Lcoursier/parse/JsonRuleParser$anon$derivedDecodeJson$macro$23$1;
        64: invokevirtual #77                 // Method coursier/parse/JsonRuleParser$anon$derivedDecodeJson$macro$23$1.coursier$parse$JsonRuleParser$anon$derivedDecodeJson$macro$23$$$outer:()Lcoursier/parse/JsonRuleParser;
        67: aload_0
        68: getfield      #73                 // Field $outer:Lcoursier/parse/JsonRuleParser$anon$derivedDecodeJson$macro$23$1;
        71: getfield      #81                 // Field coursier/parse/JsonRuleParser$anon$derivedDecodeJson$macro$23$1.Helper$module$1:Lscala/runtime/LazyRef;
        74: invokevirtual #87                 // Method coursier/parse/JsonRuleParser.coursier$parse$JsonRuleParser$$Helper$3:(Lscala/runtime/LazyRef;)Lcoursier/parse/JsonRuleParser$Helper$2$;
        77: aload         4
        79: aload         6
        81: invokevirtual #91                 // Method coursier/parse/JsonRuleParser$Helper$2$.apply:(Lscala/collection/immutable/List;Lscala/collection/immutable/List;)Lcoursier/parse/JsonRuleParser$Helper$1;
        84: astore_2
        85: goto          106
        88: goto          97
        91: goto          97
        94: goto          97
        97: new           #43                 // class scala/MatchError
       100: dup
       101: aload_3
       102: invokespecial #46                 // Method scala/MatchError."<init>":(Ljava/lang/Object;)V
       105: athrow
       106: aload_2
       107: areturn
      StackMapTable: number_of_entries = 5
        frame_type = 255 /* full_frame */
          offset_delta = 88
          locals = [ class coursier/parse/JsonRuleParser$anon$derivedDecodeJson$macro$23$1$anon$macro$16$1, class shapeless/$colon$colon, top, class shapeless/$colon$colon, class scala/collection/immutable/List, class shapeless/$colon$colon, class scala/collection/immutable/List, class shapeless/HNil ]
          stack = []
        frame_type = 249 /* chop */
          offset_delta = 2
        frame_type = 249 /* chop */
          offset_delta = 2
        frame_type = 2 /* same */
        frame_type = 255 /* full_frame */
          offset_delta = 8
          locals = [ class coursier/parse/JsonRuleParser$anon$derivedDecodeJson$macro$23$1$anon$macro$16$1, class shapeless/$colon$colon, class coursier/parse/JsonRuleParser$Helper$1, class shapeless/$colon$colon, class scala/collection/immutable/List, class shapeless/$colon$colon, class scala/collection/immutable/List, class shapeless/HNil ]
          stack = []
      LineNumberTable:
        line 37: 0
      LocalVariableTable:
        Start  Length  Slot  Name   Signature
           39      52     6 pat$macro$15   Lscala/collection/immutable/List;
           15      79     4 pat$macro$14   Lscala/collection/immutable/List;
            0     108     0  this   Lcoursier/parse/JsonRuleParser$anon$derivedDecodeJson$macro$23$1$anon$macro$16$1;
            0     108     1     p   Lshapeless/$colon$colon;
    Signature: #57                          // (Lshapeless/$colon$colon<Lscala/collection/immutable/List<Lcoursier/util/ModuleMatcher;>;Lshapeless/$colon$colon<Lscala/collection/immutable/List<Lcoursier/util/ModuleMatcher;>;Lshapeless/HNil;>;>;)Lcoursier/parse/JsonRuleParser$Helper$1;
    MethodParameters:
      Name                           Flags
      p                              final

  public java.lang.Object from(java.lang.Object);
    descriptor: (Ljava/lang/Object;)Ljava/lang/Object;
    flags: (0x1041) ACC_PUBLIC, ACC_BRIDGE, ACC_SYNTHETIC
    Code:
      stack=2, locals=2, args_size=2
         0: aload_0
         1: aload_1
         2: checkcast     #31                 // class shapeless/$colon$colon
         5: invokevirtual #96                 // Method from:(Lshapeless/$colon$colon;)Lcoursier/parse/JsonRuleParser$Helper$1;
         8: areturn
      LineNumberTable:
        line 37: 0
      LocalVariableTable:
        Start  Length  Slot  Name   Signature
            0       9     0  this   Lcoursier/parse/JsonRuleParser$anon$derivedDecodeJson$macro$23$1$anon$macro$16$1;
            0       9     1     r   Ljava/lang/Object;
    MethodParameters:
      Name                           Flags
      r                              final

  public java.lang.Object to(java.lang.Object);
    descriptor: (Ljava/lang/Object;)Ljava/lang/Object;
    flags: (0x1041) ACC_PUBLIC, ACC_BRIDGE, ACC_SYNTHETIC
    Code:
      stack=2, locals=2, args_size=2
         0: aload_0
         1: aload_1
         2: checkcast     #12                 // class coursier/parse/JsonRuleParser$Helper$1
         5: invokevirtual #100                // Method to:(Lcoursier/parse/JsonRuleParser$Helper$1;)Lshapeless/$colon$colon;
         8: areturn
      LineNumberTable:
        line 37: 0
      LocalVariableTable:
        Start  Length  Slot  Name   Signature
            0       9     0  this   Lcoursier/parse/JsonRuleParser$anon$derivedDecodeJson$macro$23$1$anon$macro$16$1;
            0       9     1     t   Ljava/lang/Object;
    MethodParameters:
      Name                           Flags
      t                              final

  public coursier.parse.JsonRuleParser$anon$derivedDecodeJson$macro$23$1$anon$macro$16$1(coursier.parse.JsonRuleParser$anon$derivedDecodeJson$macro$23$1);
    descriptor: (Lcoursier/parse/JsonRuleParser$anon$derivedDecodeJson$macro$23$1;)V
    flags: (0x0001) ACC_PUBLIC
    Code:
      stack=2, locals=2, args_size=2
         0: aload_1
         1: ifnonnull     6
         4: aconst_null
         5: athrow
         6: aload_0
         7: aload_1
         8: putfield      #73                 // Field $outer:Lcoursier/parse/JsonRuleParser$anon$derivedDecodeJson$macro$23$1;
        11: aload_0
        12: invokespecial #104                // Method java/lang/Object."<init>":()V
        15: return
      StackMapTable: number_of_entries = 1
        frame_type = 6 /* same */
      LineNumberTable:
        line 37: 0
      LocalVariableTable:
        Start  Length  Slot  Name   Signature
            0      16     0  this   Lcoursier/parse/JsonRuleParser$anon$derivedDecodeJson$macro$23$1$anon$macro$16$1;
            0      16     1 $outer   Lcoursier/parse/JsonRuleParser$anon$derivedDecodeJson$macro$23$1;
    MethodParameters:
      Name                           Flags
      $outer                         final synthetic
}
InnerClasses:
  public final #13= #12;                  // 1=class coursier/parse/JsonRuleParser$Helper$1
  public #16= #15;                        // =class coursier/parse/JsonRuleParser$Helper$2$
  public final #13= #10;                  // 1=class coursier/parse/JsonRuleParser$anon$derivedDecodeJson$macro$23$1
  public final #13= #2;                   // 1=class coursier/parse/JsonRuleParser$anon$derivedDecodeJson$macro$23$1$anon$macro$16$1
EnclosingMethod: #10.#0                 // coursier.parse.JsonRuleParser$anon$derivedDecodeJson$macro$23$1
Signature: #3                           // Ljava/lang/Object;Lshapeless/Generic<Lcoursier/parse/JsonRuleParser$Helper$1;>;
SourceFile: "JsonRuleParser.scala"
  ScalaInlineInfo: length = 0x1D (unknown attribute)
   01 01 00 05 00 28 00 67 01 00 39 00 5F 01 00 39
   00 3A 01 00 15 00 16 01 00 15 00 5F 01
  Scala: length = 0x0 (unknown attribute)

