Classfile /Users/mw/Projects/slang-braindump/.jar/jar11/assemble/slang-braindump/assemble/content/coursier/parse/ModuleParser.class
  Last modified May 29, 2022; size 2129 bytes
  SHA-256 checksum bf33fb0deb92cbb16d2232e0675642bdf24bf8dd402a10108ee296cc9a729a65
  Compiled from "ModuleParser.scala"
public final class coursier.parse.ModuleParser
  minor version: 0
  major version: 52
  flags: (0x0031) ACC_PUBLIC, ACC_FINAL, ACC_SUPER
  this_class: #2                          // coursier/parse/ModuleParser
  super_class: #4                         // java/lang/Object
  interfaces: 0, fields: 0, methods: 4, attributes: 3
Constant pool:
   #1 = Utf8               coursier/parse/ModuleParser
   #2 = Class              #1             // coursier/parse/ModuleParser
   #3 = Utf8               java/lang/Object
   #4 = Class              #3             // java/lang/Object
   #5 = Utf8               ModuleParser.scala
   #6 = Utf8               Lscala/reflect/ScalaSignature;
   #7 = Utf8               bytes
   #8 = Utf8               \u0006\u0005Q;Qa\u0002\u0005\t\u000251Qa\u0004\u0005\t\u0002AAQaF\u0001\u0005\u0002aAQ!G\u0001\u0005\u0002iAQ\u0001N\u0001\u0005\u0002UBQ\u0001Q\u0001\u0005\u0002\u0005CQAT\u0001\u0005\u0002=\u000bA\"T8ek2,\u0007+\u0019:tKJT!!\u0003\u0006\u0002\u000bA\f\'o]3\u000b\u0003-\t\u0001bY8veNLWM]\u0002\u0001!\tq\u0011!D\u0001\t\u00051iu\u000eZ;mKB\u000b\'o]3s\'\t\t\u0011\u0003\u0005\u0002\u0013+5\t1CC\u0001\u0015\u0003\u0015\u00198-\u00197b\u0013\t12C\u0001\u0004B]f\u0014VMZ\u0001\u0007y%t\u0017\u000e\u001e \u0015\u00035\t\u0011C[1wC>\u00138kY1mC6{G-\u001e7f)\tY\"\u0007\u0005\u0003\u001dI\u001dzcBA\u000f#\u001d\tq\u0012%D\u0001 \u0015\t\u0001C\"\u0001\u0004=e>|GOP\u0005\u0002)%\u00111eE\u0001\ba\u0006\u001c7.Y4f\u0013\t)cE\u0001\u0004FSRDWM\u001d\u0006\u0003GM\u0001\"\u0001\u000b\u0017\u000f\u0005%R\u0003C\u0001\u0010\u0014\u0013\tY3#\u0001\u0004Qe\u0016$WMZ\u0005\u0003[9\u0012aa\u0015;sS:<\'BA\u0016\u0014!\tq\u0001\'\u0003\u00022\u0011\t\t\"*\u0019<b\u001fJ\u001c6-\u00197b\u001b>$W\u000f\\3\t\u000bM\u001a\u0001\u0019A\u0014\u0002\u0003M\fa!\\8ek2,Gc\u0001\u001c>}A!A\u0004J\u00148!\tA4(D\u0001:\u0015\tQ$\"\u0001\u0003d_J,\u0017B\u0001\u001f:\u0005\u0019iu\u000eZ;mK\")1\u0007\u0002a\u0001O!)q\b\u0002a\u0001O\u0005\u0019B-\u001a4bk2$8kY1mCZ+\'o]5p]\u0006\u0011\".\u0019<b\u001fJ\u001c6-\u00197b\u001b>$W\u000f\\3t)\t\u00115\n\u0005\u0003D\r\u001eBU\"\u0001#\u000b\u0005\u0015S\u0011\u0001B;uS2L!a\u0012#\u0003\u001bY\u000bG.\u001b3bi&|gNT3m!\ra\u0012jL\u0005\u0003\u0015\u001a\u00121aU3r\u0011\u0015aU\u00011\u0001N\u0003\u0019Ig\u000e];ugB\u0019A$S\u0014\u0002\u000f5|G-\u001e7fgR\u0019\u0001KU*\u0011\t\r3u%\u0015\t\u00049%;\u0004\"\u0002\'\u0007\u0001\u0004i\u0005\"B \u0007\u0001\u00049\u0003
   #9 = Utf8               modules
  #10 = Utf8               (Lscala/collection/immutable/Seq;Ljava/lang/String;)Lcoursier/util/ValidationNel;
  #11 = Utf8               (Lscala/collection/immutable/Seq<Ljava/lang/String;>;Ljava/lang/String;)Lcoursier/util/ValidationNel<Ljava/lang/String;Lscala/collection/immutable/Seq<Lcoursier/core/Module;>;>;
  #12 = Utf8               inputs
  #13 = Utf8               defaultScalaVersion
  #14 = Utf8               coursier/parse/ModuleParser$
  #15 = Class              #14            // coursier/parse/ModuleParser$
  #16 = Utf8               MODULE$
  #17 = Utf8               Lcoursier/parse/ModuleParser$;
  #18 = NameAndType        #16:#17        // MODULE$:Lcoursier/parse/ModuleParser$;
  #19 = Fieldref           #15.#18        // coursier/parse/ModuleParser$.MODULE$:Lcoursier/parse/ModuleParser$;
  #20 = NameAndType        #9:#10         // modules:(Lscala/collection/immutable/Seq;Ljava/lang/String;)Lcoursier/util/ValidationNel;
  #21 = Methodref          #15.#20        // coursier/parse/ModuleParser$.modules:(Lscala/collection/immutable/Seq;Ljava/lang/String;)Lcoursier/util/ValidationNel;
  #22 = Utf8               javaOrScalaModules
  #23 = Utf8               (Lscala/collection/immutable/Seq;)Lcoursier/util/ValidationNel;
  #24 = Utf8               (Lscala/collection/immutable/Seq<Ljava/lang/String;>;)Lcoursier/util/ValidationNel<Ljava/lang/String;Lscala/collection/immutable/Seq<Lcoursier/parse/JavaOrScalaModule;>;>;
  #25 = NameAndType        #22:#23        // javaOrScalaModules:(Lscala/collection/immutable/Seq;)Lcoursier/util/ValidationNel;
  #26 = Methodref          #15.#25        // coursier/parse/ModuleParser$.javaOrScalaModules:(Lscala/collection/immutable/Seq;)Lcoursier/util/ValidationNel;
  #27 = Utf8               module
  #28 = Utf8               (Ljava/lang/String;Ljava/lang/String;)Lscala/util/Either;
  #29 = Utf8               (Ljava/lang/String;Ljava/lang/String;)Lscala/util/Either<Ljava/lang/String;Lcoursier/core/Module;>;
  #30 = Utf8               s
  #31 = NameAndType        #27:#28        // module:(Ljava/lang/String;Ljava/lang/String;)Lscala/util/Either;
  #32 = Methodref          #15.#31        // coursier/parse/ModuleParser$.module:(Ljava/lang/String;Ljava/lang/String;)Lscala/util/Either;
  #33 = Utf8               javaOrScalaModule
  #34 = Utf8               (Ljava/lang/String;)Lscala/util/Either;
  #35 = Utf8               (Ljava/lang/String;)Lscala/util/Either<Ljava/lang/String;Lcoursier/parse/JavaOrScalaModule;>;
  #36 = NameAndType        #33:#34        // javaOrScalaModule:(Ljava/lang/String;)Lscala/util/Either;
  #37 = Methodref          #15.#36        // coursier/parse/ModuleParser$.javaOrScalaModule:(Ljava/lang/String;)Lscala/util/Either;
  #38 = Utf8               Code
  #39 = Utf8               Signature
  #40 = Utf8               MethodParameters
  #41 = Utf8               SourceFile
  #42 = Utf8               RuntimeVisibleAnnotations
  #43 = Utf8               ScalaSig
{
  public static coursier.util.ValidationNel<java.lang.String, scala.collection.immutable.Seq<coursier.core.Module>> modules(scala.collection.immutable.Seq<java.lang.String>, java.lang.String);
    descriptor: (Lscala/collection/immutable/Seq;Ljava/lang/String;)Lcoursier/util/ValidationNel;
    flags: (0x0009) ACC_PUBLIC, ACC_STATIC
    Code:
      stack=3, locals=2, args_size=2
         0: getstatic     #19                 // Field coursier/parse/ModuleParser$.MODULE$:Lcoursier/parse/ModuleParser$;
         3: aload_0
         4: aload_1
         5: invokevirtual #21                 // Method coursier/parse/ModuleParser$.modules:(Lscala/collection/immutable/Seq;Ljava/lang/String;)Lcoursier/util/ValidationNel;
         8: areturn
    Signature: #11                          // (Lscala/collection/immutable/Seq<Ljava/lang/String;>;Ljava/lang/String;)Lcoursier/util/ValidationNel<Ljava/lang/String;Lscala/collection/immutable/Seq<Lcoursier/core/Module;>;>;
    MethodParameters:
      Name                           Flags
      inputs                         final
      defaultScalaVersion            final

  public static coursier.util.ValidationNel<java.lang.String, scala.collection.immutable.Seq<coursier.parse.JavaOrScalaModule>> javaOrScalaModules(scala.collection.immutable.Seq<java.lang.String>);
    descriptor: (Lscala/collection/immutable/Seq;)Lcoursier/util/ValidationNel;
    flags: (0x0009) ACC_PUBLIC, ACC_STATIC
    Code:
      stack=2, locals=1, args_size=1
         0: getstatic     #19                 // Field coursier/parse/ModuleParser$.MODULE$:Lcoursier/parse/ModuleParser$;
         3: aload_0
         4: invokevirtual #26                 // Method coursier/parse/ModuleParser$.javaOrScalaModules:(Lscala/collection/immutable/Seq;)Lcoursier/util/ValidationNel;
         7: areturn
    Signature: #24                          // (Lscala/collection/immutable/Seq<Ljava/lang/String;>;)Lcoursier/util/ValidationNel<Ljava/lang/String;Lscala/collection/immutable/Seq<Lcoursier/parse/JavaOrScalaModule;>;>;
    MethodParameters:
      Name                           Flags
      inputs                         final

  public static scala.util.Either<java.lang.String, coursier.core.Module> module(java.lang.String, java.lang.String);
    descriptor: (Ljava/lang/String;Ljava/lang/String;)Lscala/util/Either;
    flags: (0x0009) ACC_PUBLIC, ACC_STATIC
    Code:
      stack=3, locals=2, args_size=2
         0: getstatic     #19                 // Field coursier/parse/ModuleParser$.MODULE$:Lcoursier/parse/ModuleParser$;
         3: aload_0
         4: aload_1
         5: invokevirtual #32                 // Method coursier/parse/ModuleParser$.module:(Ljava/lang/String;Ljava/lang/String;)Lscala/util/Either;
         8: areturn
    Signature: #29                          // (Ljava/lang/String;Ljava/lang/String;)Lscala/util/Either<Ljava/lang/String;Lcoursier/core/Module;>;
    MethodParameters:
      Name                           Flags
      s                              final
      defaultScalaVersion            final

  public static scala.util.Either<java.lang.String, coursier.parse.JavaOrScalaModule> javaOrScalaModule(java.lang.String);
    descriptor: (Ljava/lang/String;)Lscala/util/Either;
    flags: (0x0009) ACC_PUBLIC, ACC_STATIC
    Code:
      stack=2, locals=1, args_size=1
         0: getstatic     #19                 // Field coursier/parse/ModuleParser$.MODULE$:Lcoursier/parse/ModuleParser$;
         3: aload_0
         4: invokevirtual #37                 // Method coursier/parse/ModuleParser$.javaOrScalaModule:(Ljava/lang/String;)Lscala/util/Either;
         7: areturn
    Signature: #35                          // (Ljava/lang/String;)Lscala/util/Either<Ljava/lang/String;Lcoursier/parse/JavaOrScalaModule;>;
    MethodParameters:
      Name                           Flags
      s                              final
}
SourceFile: "ModuleParser.scala"
RuntimeVisibleAnnotations:
  0: #6(#7=s#8)
    scala.reflect.ScalaSignature(
      bytes="\u0006\u0005Q;Qa\u0002\u0005\t\u000251Qa\u0004\u0005\t\u0002AAQaF\u0001\u0005\u0002aAQ!G\u0001\u0005\u0002iAQ\u0001N\u0001\u0005\u0002UBQ\u0001Q\u0001\u0005\u0002\u0005CQAT\u0001\u0005\u0002=\u000bA\"T8ek2,\u0007+\u0019:tKJT!!\u0003\u0006\u0002\u000bA\f\'o]3\u000b\u0003-\t\u0001bY8veNLWM]\u0002\u0001!\tq\u0011!D\u0001\t\u00051iu\u000eZ;mKB\u000b\'o]3s\'\t\t\u0011\u0003\u0005\u0002\u0013+5\t1CC\u0001\u0015\u0003\u0015\u00198-\u00197b\u0013\t12C\u0001\u0004B]f\u0014VMZ\u0001\u0007y%t\u0017\u000e\u001e \u0015\u00035\t\u0011C[1wC>\u00138kY1mC6{G-\u001e7f)\tY\"\u0007\u0005\u0003\u001dI\u001dzcBA\u000f#\u001d\tq\u0012%D\u0001 \u0015\t\u0001C\"\u0001\u0004=e>|GOP\u0005\u0002)%\u00111eE\u0001\ba\u0006\u001c7.Y4f\u0013\t)cE\u0001\u0004FSRDWM\u001d\u0006\u0003GM\u0001\"\u0001\u000b\u0017\u000f\u0005%R\u0003C\u0001\u0010\u0014\u0013\tY3#\u0001\u0004Qe\u0016$WMZ\u0005\u0003[9\u0012aa\u0015;sS:<\'BA\u0016\u0014!\tq\u0001\'\u0003\u00022\u0011\t\t\"*\u0019<b\u001fJ\u001c6-\u00197b\u001b>$W\u000f\\3\t\u000bM\u001a\u0001\u0019A\u0014\u0002\u0003M\fa!\\8ek2,Gc\u0001\u001c>}A!A\u0004J\u00148!\tA4(D\u0001:\u0015\tQ$\"\u0001\u0003d_J,\u0017B\u0001\u001f:\u0005\u0019iu\u000eZ;mK\")1\u0007\u0002a\u0001O!)q\b\u0002a\u0001O\u0005\u0019B-\u001a4bk2$8kY1mCZ+\'o]5p]\u0006\u0011\".\u0019<b\u001fJ\u001c6-\u00197b\u001b>$W\u000f\\3t)\t\u00115\n\u0005\u0003D\r\u001eBU\"\u0001#\u000b\u0005\u0015S\u0011\u0001B;uS2L!a\u0012#\u0003\u001bY\u000bG.\u001b3bi&|gNT3m!\ra\u0012jL\u0005\u0003\u0015\u001a\u00121aU3r\u0011\u0015aU\u00011\u0001N\u0003\u0019Ig\u000e];ugB\u0019A$S\u0014\u0002\u000f5|G-\u001e7fgR\u0019\u0001KU*\u0011\t\r3u%\u0015\t\u00049%;\u0004\"\u0002\'\u0007\u0001\u0004i\u0005\"B \u0007\u0001\u00049\u0003"
    )
  ScalaSig: length = 0x3 (unknown attribute)
   05 02 00
