Classfile /Users/mw/Projects/slang-braindump/.jar/jar11/assemble/slang-braindump/assemble/content/coursier/parse/ReconciliationParser.class
  Last modified May 29, 2022; size 1402 bytes
  SHA-256 checksum 5217a526a29c31e9c88805ebfc32cb03e247f2053e2b8eacd9db9145608dc864
  Compiled from "ReconciliationParser.scala"
public final class coursier.parse.ReconciliationParser
  minor version: 0
  major version: 52
  flags: (0x0031) ACC_PUBLIC, ACC_FINAL, ACC_SUPER
  this_class: #2                          // coursier/parse/ReconciliationParser
  super_class: #4                         // java/lang/Object
  interfaces: 0, fields: 0, methods: 1, attributes: 3
Constant pool:
   #1 = Utf8               coursier/parse/ReconciliationParser
   #2 = Class              #1             // coursier/parse/ReconciliationParser
   #3 = Utf8               java/lang/Object
   #4 = Class              #3             // java/lang/Object
   #5 = Utf8               ReconciliationParser.scala
   #6 = Utf8               Lscala/reflect/ScalaSignature;
   #7 = Utf8               bytes
   #8 = Utf8               \u0006\u0005=;Q!\u0002\u0004\t\u0002-1Q!\u0004\u0004\t\u00029AQ!F\u0001\u0005\u0002YAQaF\u0001\u0005\u0002aAQaF\u0001\u0005\n\u0011\u000bACU3d_:\u001c\u0017\u000e\\5bi&|g\u000eU1sg\u0016\u0014(BA\u0004\t\u0003\u0015\u0001\u0018M]:f\u0015\u0005I\u0011\u0001C2pkJ\u001c\u0018.\u001a:\u0004\u0001A\u0011A\"A\u0007\u0002\r\t!\"+Z2p]\u000eLG.[1uS>t\u0007+\u0019:tKJ\u001c\"!A\b\u0011\u0005A\u0019R\"A\t\u000b\u0003I\tQa]2bY\u0006L!\u0001F\t\u0003\r\u0005s\u0017PU3g\u0003\u0019a\u0014N\\5u}Q\t1\"\u0001\bsK\u000e|gnY5mS\u0006$\u0018n\u001c8\u0015\u0007ey$\t\u0005\u0003\u001b;}QS\"A\u000e\u000b\u0005qA\u0011\u0001B;uS2L!AH\u000e\u0003\u001bY\u000bG.\u001b3bi&|gNT3m!\t\u0001sE\u0004\u0002\"KA\u0011!%E\u0007\u0002G)\u0011AEC\u0001\u0007yI|w\u000e\u001e \n\u0005\u0019\n\u0012A\u0002)sK\u0012,g-\u0003\u0002)S\t11\u000b\u001e:j]\u001eT!AJ\t\u0011\u0007-\u00024G\u0004\u0002-]9\u0011!%L\u0005\u0002%%\u0011q&E\u0001\ba\u0006\u001c7.Y4f\u0013\t\t$GA\u0002TKFT!aL\t\u0011\tA!d\'O\u0005\u0003kE\u0011a\u0001V;qY\u0016\u0014\u0004C\u0001\u000e8\u0013\tA4D\u0001\bN_\u0012,H.Z\'bi\u000eDWM]:\u0011\u0005ijT\"A\u001e\u000b\u0005qB\u0011\u0001B2pe\u0016L!AP\u001e\u0003\u001dI+7m\u001c8dS2L\u0017\r^5p]\")\u0001i\u0001a\u0001\u0003\u0006)\u0011N\u001c9viB\u00191\u0006M\u0010\t\u000b\r\u001b\u0001\u0019A\u0010\u0002+M\u001c\u0017\r\\1WKJ\u001c\u0018n\u001c8Pe\u0012+g-Y;miR\u0019Q\tS\'\u0011\t-2udM\u0005\u0003\u000fJ\u0012a!R5uQ\u0016\u0014\b\"B%\u0005\u0001\u0004Q\u0015AB7pIVdW\r\u0005\u0002;\u0017&\u0011Aj\u000f\u0002\u0007\u001b>$W\u000f\\3\t\u000b9#\u0001\u0019A\u0010\u0002\u0003Y\u0004
   #9 = Utf8               reconciliation
  #10 = Utf8               (Lscala/collection/immutable/Seq;Ljava/lang/String;)Lcoursier/util/ValidationNel;
  #11 = Utf8               (Lscala/collection/immutable/Seq<Ljava/lang/String;>;Ljava/lang/String;)Lcoursier/util/ValidationNel<Ljava/lang/String;Lscala/collection/immutable/Seq<Lscala/Tuple2<Lcoursier/util/ModuleMatchers;Lcoursier/core/Reconciliation;>;>;>;
  #12 = Utf8               input
  #13 = Utf8               scalaVersionOrDefault
  #14 = Utf8               coursier/parse/ReconciliationParser$
  #15 = Class              #14            // coursier/parse/ReconciliationParser$
  #16 = Utf8               MODULE$
  #17 = Utf8               Lcoursier/parse/ReconciliationParser$;
  #18 = NameAndType        #16:#17        // MODULE$:Lcoursier/parse/ReconciliationParser$;
  #19 = Fieldref           #15.#18        // coursier/parse/ReconciliationParser$.MODULE$:Lcoursier/parse/ReconciliationParser$;
  #20 = NameAndType        #9:#10         // reconciliation:(Lscala/collection/immutable/Seq;Ljava/lang/String;)Lcoursier/util/ValidationNel;
  #21 = Methodref          #15.#20        // coursier/parse/ReconciliationParser$.reconciliation:(Lscala/collection/immutable/Seq;Ljava/lang/String;)Lcoursier/util/ValidationNel;
  #22 = Utf8               Code
  #23 = Utf8               Signature
  #24 = Utf8               MethodParameters
  #25 = Utf8               SourceFile
  #26 = Utf8               RuntimeVisibleAnnotations
  #27 = Utf8               ScalaSig
{
  public static coursier.util.ValidationNel<java.lang.String, scala.collection.immutable.Seq<scala.Tuple2<coursier.util.ModuleMatchers, coursier.core.Reconciliation>>> reconciliation(scala.collection.immutable.Seq<java.lang.String>, java.lang.String);
    descriptor: (Lscala/collection/immutable/Seq;Ljava/lang/String;)Lcoursier/util/ValidationNel;
    flags: (0x0009) ACC_PUBLIC, ACC_STATIC
    Code:
      stack=3, locals=2, args_size=2
         0: getstatic     #19                 // Field coursier/parse/ReconciliationParser$.MODULE$:Lcoursier/parse/ReconciliationParser$;
         3: aload_0
         4: aload_1
         5: invokevirtual #21                 // Method coursier/parse/ReconciliationParser$.reconciliation:(Lscala/collection/immutable/Seq;Ljava/lang/String;)Lcoursier/util/ValidationNel;
         8: areturn
    Signature: #11                          // (Lscala/collection/immutable/Seq<Ljava/lang/String;>;Ljava/lang/String;)Lcoursier/util/ValidationNel<Ljava/lang/String;Lscala/collection/immutable/Seq<Lscala/Tuple2<Lcoursier/util/ModuleMatchers;Lcoursier/core/Reconciliation;>;>;>;
    MethodParameters:
      Name                           Flags
      input                          final
      scalaVersionOrDefault          final
}
SourceFile: "ReconciliationParser.scala"
RuntimeVisibleAnnotations:
  0: #6(#7=s#8)
    scala.reflect.ScalaSignature(
      bytes="\u0006\u0005=;Q!\u0002\u0004\t\u0002-1Q!\u0004\u0004\t\u00029AQ!F\u0001\u0005\u0002YAQaF\u0001\u0005\u0002aAQaF\u0001\u0005\n\u0011\u000bACU3d_:\u001c\u0017\u000e\\5bi&|g\u000eU1sg\u0016\u0014(BA\u0004\t\u0003\u0015\u0001\u0018M]:f\u0015\u0005I\u0011\u0001C2pkJ\u001c\u0018.\u001a:\u0004\u0001A\u0011A\"A\u0007\u0002\r\t!\"+Z2p]\u000eLG.[1uS>t\u0007+\u0019:tKJ\u001c\"!A\b\u0011\u0005A\u0019R\"A\t\u000b\u0003I\tQa]2bY\u0006L!\u0001F\t\u0003\r\u0005s\u0017PU3g\u0003\u0019a\u0014N\\5u}Q\t1\"\u0001\bsK\u000e|gnY5mS\u0006$\u0018n\u001c8\u0015\u0007ey$\t\u0005\u0003\u001b;}QS\"A\u000e\u000b\u0005qA\u0011\u0001B;uS2L!AH\u000e\u0003\u001bY\u000bG.\u001b3bi&|gNT3m!\t\u0001sE\u0004\u0002\"KA\u0011!%E\u0007\u0002G)\u0011AEC\u0001\u0007yI|w\u000e\u001e \n\u0005\u0019\n\u0012A\u0002)sK\u0012,g-\u0003\u0002)S\t11\u000b\u001e:j]\u001eT!AJ\t\u0011\u0007-\u00024G\u0004\u0002-]9\u0011!%L\u0005\u0002%%\u0011q&E\u0001\ba\u0006\u001c7.Y4f\u0013\t\t$GA\u0002TKFT!aL\t\u0011\tA!d\'O\u0005\u0003kE\u0011a\u0001V;qY\u0016\u0014\u0004C\u0001\u000e8\u0013\tA4D\u0001\bN_\u0012,H.Z\'bi\u000eDWM]:\u0011\u0005ijT\"A\u001e\u000b\u0005qB\u0011\u0001B2pe\u0016L!AP\u001e\u0003\u001dI+7m\u001c8dS2L\u0017\r^5p]\")\u0001i\u0001a\u0001\u0003\u0006)\u0011N\u001c9viB\u00191\u0006M\u0010\t\u000b\r\u001b\u0001\u0019A\u0010\u0002+M\u001c\u0017\r\\1WKJ\u001c\u0018n\u001c8Pe\u0012+g-Y;miR\u0019Q\tS\'\u0011\t-2udM\u0005\u0003\u000fJ\u0012a!R5uQ\u0016\u0014\b\"B%\u0005\u0001\u0004Q\u0015AB7pIVdW\r\u0005\u0002;\u0017&\u0011Aj\u000f\u0002\u0007\u001b>$W\u000f\\3\t\u000b9#\u0001\u0019A\u0010\u0002\u0003Y\u0004"
    )
  ScalaSig: length = 0x3 (unknown attribute)
   05 02 00
