Classfile /Users/mw/Projects/slang-braindump/.jar/jar11/assemble/slang-braindump/assemble/content/coursier/graph/ModuleTree$Node.class
  Last modified May 29, 2022; size 6059 bytes
  SHA-256 checksum d24c7416c397dffc8478368ed7a6023359fc122478f6f8a7e6d9d97fb001c831
  Compiled from "ModuleTree.scala"
public final class coursier.graph.ModuleTree$Node extends coursier.graph.ModuleTree implements scala.Product,java.io.Serializable
  minor version: 0
  major version: 52
  flags: (0x0031) ACC_PUBLIC, ACC_FINAL, ACC_SUPER
  this_class: #2                          // coursier/graph/ModuleTree$Node
  super_class: #4                         // coursier/graph/ModuleTree
  interfaces: 2, fields: 4, methods: 23, attributes: 5
Constant pool:
    #1 = Utf8               coursier/graph/ModuleTree$Node
    #2 = Class              #1            // coursier/graph/ModuleTree$Node
    #3 = Utf8               coursier/graph/ModuleTree
    #4 = Class              #3            // coursier/graph/ModuleTree
    #5 = Utf8               scala/Product
    #6 = Class              #5            // scala/Product
    #7 = Utf8               java/io/Serializable
    #8 = Class              #7            // java/io/Serializable
    #9 = Utf8               ModuleTree.scala
   #10 = Utf8               Node
   #11 = Utf8               java/lang/invoke/MethodHandles$Lookup
   #12 = Class              #11           // java/lang/invoke/MethodHandles$Lookup
   #13 = Utf8               java/lang/invoke/MethodHandles
   #14 = Class              #13           // java/lang/invoke/MethodHandles
   #15 = Utf8               Lookup
   #16 = Utf8               module
   #17 = Utf8               Lcoursier/core/Module;
   #18 = Utf8               reconciledVersion
   #19 = Utf8               Ljava/lang/String;
   #20 = Utf8               retainedVersion
   #21 = Utf8               dependencyTrees
   #22 = Utf8               Lscala/collection/immutable/Seq;
   #23 = Utf8               Lscala/collection/immutable/Seq<Lcoursier/graph/DependencyTree;>;
   #24 = Utf8               productElementNames
   #25 = Utf8               ()Lscala/collection/Iterator;
   #26 = Utf8               ()Lscala/collection/Iterator<Ljava/lang/String;>;
   #27 = Utf8               productElementNames$
   #28 = Utf8               (Lscala/Product;)Lscala/collection/Iterator;
   #29 = NameAndType        #27:#28       // productElementNames$:(Lscala/Product;)Lscala/collection/Iterator;
   #30 = InterfaceMethodref #6.#29        // scala/Product.productElementNames$:(Lscala/Product;)Lscala/collection/Iterator;
   #31 = Utf8               this
   #32 = Utf8               Lcoursier/graph/ModuleTree$Node;
   #33 = Utf8               ()Lcoursier/core/Module;
   #34 = NameAndType        #16:#17       // module:Lcoursier/core/Module;
   #35 = Fieldref           #2.#34        // coursier/graph/ModuleTree$Node.module:Lcoursier/core/Module;
   #36 = Utf8               ()Ljava/lang/String;
   #37 = NameAndType        #18:#19       // reconciledVersion:Ljava/lang/String;
   #38 = Fieldref           #2.#37        // coursier/graph/ModuleTree$Node.reconciledVersion:Ljava/lang/String;
   #39 = NameAndType        #20:#19       // retainedVersion:Ljava/lang/String;
   #40 = Fieldref           #2.#39        // coursier/graph/ModuleTree$Node.retainedVersion:Ljava/lang/String;
   #41 = Utf8               ()Lscala/collection/immutable/Seq;
   #42 = Utf8               ()Lscala/collection/immutable/Seq<Lcoursier/graph/DependencyTree;>;
   #43 = NameAndType        #21:#22       // dependencyTrees:Lscala/collection/immutable/Seq;
   #44 = Fieldref           #2.#43        // coursier/graph/ModuleTree$Node.dependencyTrees:Lscala/collection/immutable/Seq;
   #45 = Utf8               children
   #46 = Utf8               ()Lscala/collection/immutable/Seq<Lcoursier/graph/ModuleTree;>;
   #47 = Utf8               coursier/graph/ModuleTree$
   #48 = Class              #47           // coursier/graph/ModuleTree$
   #49 = Utf8               MODULE$
   #50 = Utf8               Lcoursier/graph/ModuleTree$;
   #51 = NameAndType        #49:#50       // MODULE$:Lcoursier/graph/ModuleTree$;
   #52 = Fieldref           #48.#51       // coursier/graph/ModuleTree$.MODULE$:Lcoursier/graph/ModuleTree$;
   #53 = NameAndType        #21:#41       // dependencyTrees:()Lscala/collection/immutable/Seq;
   #54 = Methodref          #2.#53        // coursier/graph/ModuleTree$Node.dependencyTrees:()Lscala/collection/immutable/Seq;
   #55 = Utf8               (Ljava/lang/Object;)Ljava/lang/Object;
   #56 = MethodType         #55           //  (Ljava/lang/Object;)Ljava/lang/Object;
   #57 = Utf8               $anonfun$children$1
   #58 = Utf8               (Lcoursier/graph/DependencyTree;)Lscala/collection/immutable/Seq;
   #59 = NameAndType        #57:#58       // $anonfun$children$1:(Lcoursier/graph/DependencyTree;)Lscala/collection/immutable/Seq;
   #60 = Methodref          #2.#59        // coursier/graph/ModuleTree$Node.$anonfun$children$1:(Lcoursier/graph/DependencyTree;)Lscala/collection/immutable/Seq;
   #61 = MethodHandle       6:#60         // REF_invokeStatic coursier/graph/ModuleTree$Node.$anonfun$children$1:(Lcoursier/graph/DependencyTree;)Lscala/collection/immutable/Seq;
   #62 = MethodType         #58           //  (Lcoursier/graph/DependencyTree;)Lscala/collection/immutable/Seq;
   #63 = Integer            5
   #64 = Integer            1
   #65 = Utf8               java/lang/invoke/LambdaMetafactory
   #66 = Class              #65           // java/lang/invoke/LambdaMetafactory
   #67 = Utf8               altMetafactory
   #68 = Utf8               (Ljava/lang/invoke/MethodHandles$Lookup;Ljava/lang/String;Ljava/lang/invoke/MethodType;[Ljava/lang/Object;)Ljava/lang/invoke/CallSite;
   #69 = NameAndType        #67:#68       // altMetafactory:(Ljava/lang/invoke/MethodHandles$Lookup;Ljava/lang/String;Ljava/lang/invoke/MethodType;[Ljava/lang/Object;)Ljava/lang/invoke/CallSite;
   #70 = Methodref          #66.#69       // java/lang/invoke/LambdaMetafactory.altMetafactory:(Ljava/lang/invoke/MethodHandles$Lookup;Ljava/lang/String;Ljava/lang/invoke/MethodType;[Ljava/lang/Object;)Ljava/lang/invoke/CallSite;
   #71 = MethodHandle       6:#70         // REF_invokeStatic java/lang/invoke/LambdaMetafactory.altMetafactory:(Ljava/lang/invoke/MethodHandles$Lookup;Ljava/lang/String;Ljava/lang/invoke/MethodType;[Ljava/lang/Object;)Ljava/lang/invoke/CallSite;
   #72 = Utf8               apply
   #73 = Utf8               ()Lscala/Function1;
   #74 = NameAndType        #72:#73       // apply:()Lscala/Function1;
   #75 = InvokeDynamic      #0:#74        // #0:apply:()Lscala/Function1;
   #76 = Utf8               scala/collection/immutable/Seq
   #77 = Class              #76           // scala/collection/immutable/Seq
   #78 = Utf8               flatMap
   #79 = Utf8               (Lscala/Function1;)Ljava/lang/Object;
   #80 = NameAndType        #78:#79       // flatMap:(Lscala/Function1;)Ljava/lang/Object;
   #81 = InterfaceMethodref #77.#80       // scala/collection/immutable/Seq.flatMap:(Lscala/Function1;)Ljava/lang/Object;
   #82 = Utf8               (Lscala/collection/immutable/Seq;)Lscala/collection/immutable/Seq;
   #83 = NameAndType        #72:#82       // apply:(Lscala/collection/immutable/Seq;)Lscala/collection/immutable/Seq;
   #84 = Methodref          #48.#83       // coursier/graph/ModuleTree$.apply:(Lscala/collection/immutable/Seq;)Lscala/collection/immutable/Seq;
   #85 = Utf8               copy
   #86 = Utf8               (Lcoursier/core/Module;Ljava/lang/String;Ljava/lang/String;Lscala/collection/immutable/Seq;)Lcoursier/graph/ModuleTree$Node;
   #87 = Utf8               (Lcoursier/core/Module;Ljava/lang/String;Ljava/lang/String;Lscala/collection/immutable/Seq<Lcoursier/graph/DependencyTree;>;)Lcoursier/graph/ModuleTree$Node;
   #88 = Utf8               <init>
   #89 = Utf8               (Lcoursier/core/Module;Ljava/lang/String;Ljava/lang/String;Lscala/collection/immutable/Seq;)V
   #90 = NameAndType        #88:#89       // "<init>":(Lcoursier/core/Module;Ljava/lang/String;Ljava/lang/String;Lscala/collection/immutable/Seq;)V
   #91 = Methodref          #2.#90        // coursier/graph/ModuleTree$Node."<init>":(Lcoursier/core/Module;Ljava/lang/String;Ljava/lang/String;Lscala/collection/immutable/Seq;)V
   #92 = Utf8               copy$default$1
   #93 = NameAndType        #16:#33       // module:()Lcoursier/core/Module;
   #94 = Methodref          #2.#93        // coursier/graph/ModuleTree$Node.module:()Lcoursier/core/Module;
   #95 = Utf8               copy$default$2
   #96 = NameAndType        #18:#36       // reconciledVersion:()Ljava/lang/String;
   #97 = Methodref          #2.#96        // coursier/graph/ModuleTree$Node.reconciledVersion:()Ljava/lang/String;
   #98 = Utf8               copy$default$3
   #99 = NameAndType        #20:#36       // retainedVersion:()Ljava/lang/String;
  #100 = Methodref          #2.#99        // coursier/graph/ModuleTree$Node.retainedVersion:()Ljava/lang/String;
  #101 = Utf8               copy$default$4
  #102 = Utf8               productPrefix
  #103 = String             #10           // Node
  #104 = Utf8               productArity
  #105 = Utf8               ()I
  #106 = Utf8               productElement
  #107 = Utf8               (I)Ljava/lang/Object;
  #108 = Utf8               x$1
  #109 = Utf8               scala/runtime/Statics
  #110 = Class              #109          // scala/runtime/Statics
  #111 = Utf8               ioobe
  #112 = NameAndType        #111:#107     // ioobe:(I)Ljava/lang/Object;
  #113 = Methodref          #110.#112     // scala/runtime/Statics.ioobe:(I)Ljava/lang/Object;
  #114 = Utf8               java/lang/Object
  #115 = Class              #114          // java/lang/Object
  #116 = Utf8               I
  #117 = Utf8               productIterator
  #118 = Utf8               ()Lscala/collection/Iterator<Ljava/lang/Object;>;
  #119 = Utf8               scala/runtime/ScalaRunTime$
  #120 = Class              #119          // scala/runtime/ScalaRunTime$
  #121 = Utf8               Lscala/runtime/ScalaRunTime$;
  #122 = NameAndType        #49:#121      // MODULE$:Lscala/runtime/ScalaRunTime$;
  #123 = Fieldref           #120.#122     // scala/runtime/ScalaRunTime$.MODULE$:Lscala/runtime/ScalaRunTime$;
  #124 = Utf8               typedProductIterator
  #125 = NameAndType        #124:#28      // typedProductIterator:(Lscala/Product;)Lscala/collection/Iterator;
  #126 = Methodref          #120.#125     // scala/runtime/ScalaRunTime$.typedProductIterator:(Lscala/Product;)Lscala/collection/Iterator;
  #127 = Utf8               canEqual
  #128 = Utf8               (Ljava/lang/Object;)Z
  #129 = Utf8               Ljava/lang/Object;
  #130 = Utf8               productElementName
  #131 = Utf8               (I)Ljava/lang/String;
  #132 = String             #16           // module
  #133 = String             #18           // reconciledVersion
  #134 = String             #20           // retainedVersion
  #135 = String             #21           // dependencyTrees
  #136 = Utf8               java/lang/String
  #137 = Class              #136          // java/lang/String
  #138 = Utf8               hashCode
  #139 = Utf8               _hashCode
  #140 = Utf8               (Lscala/Product;)I
  #141 = NameAndType        #139:#140     // _hashCode:(Lscala/Product;)I
  #142 = Methodref          #120.#141     // scala/runtime/ScalaRunTime$._hashCode:(Lscala/Product;)I
  #143 = Utf8               toString
  #144 = Utf8               _toString
  #145 = Utf8               (Lscala/Product;)Ljava/lang/String;
  #146 = NameAndType        #144:#145     // _toString:(Lscala/Product;)Ljava/lang/String;
  #147 = Methodref          #120.#146     // scala/runtime/ScalaRunTime$._toString:(Lscala/Product;)Ljava/lang/String;
  #148 = Utf8               equals
  #149 = Utf8               coursier/core/Module
  #150 = Class              #149          // coursier/core/Module
  #151 = NameAndType        #148:#128     // equals:(Ljava/lang/Object;)Z
  #152 = Methodref          #115.#151     // java/lang/Object.equals:(Ljava/lang/Object;)Z
  #153 = Utf8               x$4
  #154 = Utf8               coursier/graph/DependencyTree
  #155 = Class              #154          // coursier/graph/DependencyTree
  #156 = NameAndType        #45:#41       // children:()Lscala/collection/immutable/Seq;
  #157 = Methodref          #155.#156     // coursier/graph/DependencyTree.children:()Lscala/collection/immutable/Seq;
  #158 = Utf8               Lcoursier/graph/DependencyTree;
  #159 = Utf8               (Lcoursier/core/Module;Ljava/lang/String;Ljava/lang/String;Lscala/collection/immutable/Seq<Lcoursier/graph/DependencyTree;>;)V
  #160 = Utf8               ()V
  #161 = NameAndType        #88:#160      // "<init>":()V
  #162 = Methodref          #4.#161       // coursier/graph/ModuleTree."<init>":()V
  #163 = Utf8               $init$
  #164 = Utf8               (Lscala/Product;)V
  #165 = NameAndType        #163:#164     // $init$:(Lscala/Product;)V
  #166 = InterfaceMethodref #6.#165       // scala/Product.$init$:(Lscala/Product;)V
  #167 = Utf8               $deserializeLambda$
  #168 = Utf8               (Ljava/lang/invoke/SerializedLambda;)Ljava/lang/Object;
  #169 = Utf8               scala/runtime/LambdaDeserialize
  #170 = Class              #169          // scala/runtime/LambdaDeserialize
  #171 = Utf8               bootstrap
  #172 = Utf8               (Ljava/lang/invoke/MethodHandles$Lookup;Ljava/lang/String;Ljava/lang/invoke/MethodType;[Ljava/lang/invoke/MethodHandle;)Ljava/lang/invoke/CallSite;
  #173 = NameAndType        #171:#172     // bootstrap:(Ljava/lang/invoke/MethodHandles$Lookup;Ljava/lang/String;Ljava/lang/invoke/MethodType;[Ljava/lang/invoke/MethodHandle;)Ljava/lang/invoke/CallSite;
  #174 = Methodref          #170.#173     // scala/runtime/LambdaDeserialize.bootstrap:(Ljava/lang/invoke/MethodHandles$Lookup;Ljava/lang/String;Ljava/lang/invoke/MethodType;[Ljava/lang/invoke/MethodHandle;)Ljava/lang/invoke/CallSite;
  #175 = MethodHandle       6:#174        // REF_invokeStatic scala/runtime/LambdaDeserialize.bootstrap:(Ljava/lang/invoke/MethodHandles$Lookup;Ljava/lang/String;Ljava/lang/invoke/MethodType;[Ljava/lang/invoke/MethodHandle;)Ljava/lang/invoke/CallSite;
  #176 = Utf8               lambdaDeserialize
  #177 = NameAndType        #176:#168     // lambdaDeserialize:(Ljava/lang/invoke/SerializedLambda;)Ljava/lang/Object;
  #178 = InvokeDynamic      #1:#177       // #1:lambdaDeserialize:(Ljava/lang/invoke/SerializedLambda;)Ljava/lang/Object;
  #179 = Utf8               Signature
  #180 = Utf8               Code
  #181 = Utf8               LineNumberTable
  #182 = Utf8               LocalVariableTable
  #183 = Utf8               MethodParameters
  #184 = Utf8               StackMapTable
  #185 = Utf8               InnerClasses
  #186 = Utf8               SourceFile
  #187 = Utf8               BootstrapMethods
  #188 = Utf8               ScalaInlineInfo
  #189 = Utf8               Scala
{
  private final coursier.core.Module module;
    descriptor: Lcoursier/core/Module;
    flags: (0x0012) ACC_PRIVATE, ACC_FINAL

  private final java.lang.String reconciledVersion;
    descriptor: Ljava/lang/String;
    flags: (0x0012) ACC_PRIVATE, ACC_FINAL

  private final java.lang.String retainedVersion;
    descriptor: Ljava/lang/String;
    flags: (0x0012) ACC_PRIVATE, ACC_FINAL

  private final scala.collection.immutable.Seq<coursier.graph.DependencyTree> dependencyTrees;
    descriptor: Lscala/collection/immutable/Seq;
    flags: (0x0012) ACC_PRIVATE, ACC_FINAL
    Signature: #23                          // Lscala/collection/immutable/Seq<Lcoursier/graph/DependencyTree;>;

  public scala.collection.Iterator<java.lang.String> productElementNames();
    descriptor: ()Lscala/collection/Iterator;
    flags: (0x0001) ACC_PUBLIC
    Code:
      stack=1, locals=1, args_size=1
         0: aload_0
         1: invokestatic  #30                 // InterfaceMethod scala/Product.productElementNames$:(Lscala/Product;)Lscala/collection/Iterator;
         4: areturn
      LineNumberTable:
        line 56: 0
      LocalVariableTable:
        Start  Length  Slot  Name   Signature
            0       5     0  this   Lcoursier/graph/ModuleTree$Node;
    Signature: #26                          // ()Lscala/collection/Iterator<Ljava/lang/String;>;

  public coursier.core.Module module();
    descriptor: ()Lcoursier/core/Module;
    flags: (0x0001) ACC_PUBLIC
    Code:
      stack=1, locals=1, args_size=1
         0: aload_0
         1: getfield      #35                 // Field module:Lcoursier/core/Module;
         4: areturn
      LineNumberTable:
        line 57: 0
      LocalVariableTable:
        Start  Length  Slot  Name   Signature
            0       5     0  this   Lcoursier/graph/ModuleTree$Node;

  public java.lang.String reconciledVersion();
    descriptor: ()Ljava/lang/String;
    flags: (0x0001) ACC_PUBLIC
    Code:
      stack=1, locals=1, args_size=1
         0: aload_0
         1: getfield      #38                 // Field reconciledVersion:Ljava/lang/String;
         4: areturn
      LineNumberTable:
        line 58: 0
      LocalVariableTable:
        Start  Length  Slot  Name   Signature
            0       5     0  this   Lcoursier/graph/ModuleTree$Node;

  public java.lang.String retainedVersion();
    descriptor: ()Ljava/lang/String;
    flags: (0x0001) ACC_PUBLIC
    Code:
      stack=1, locals=1, args_size=1
         0: aload_0
         1: getfield      #40                 // Field retainedVersion:Ljava/lang/String;
         4: areturn
      LineNumberTable:
        line 59: 0
      LocalVariableTable:
        Start  Length  Slot  Name   Signature
            0       5     0  this   Lcoursier/graph/ModuleTree$Node;

  public scala.collection.immutable.Seq<coursier.graph.DependencyTree> dependencyTrees();
    descriptor: ()Lscala/collection/immutable/Seq;
    flags: (0x0001) ACC_PUBLIC
    Code:
      stack=1, locals=1, args_size=1
         0: aload_0
         1: getfield      #44                 // Field dependencyTrees:Lscala/collection/immutable/Seq;
         4: areturn
      LineNumberTable:
        line 60: 0
      LocalVariableTable:
        Start  Length  Slot  Name   Signature
            0       5     0  this   Lcoursier/graph/ModuleTree$Node;
    Signature: #42                          // ()Lscala/collection/immutable/Seq<Lcoursier/graph/DependencyTree;>;

  public scala.collection.immutable.Seq<coursier.graph.ModuleTree> children();
    descriptor: ()Lscala/collection/immutable/Seq;
    flags: (0x0001) ACC_PUBLIC
    Code:
      stack=3, locals=1, args_size=1
         0: getstatic     #52                 // Field coursier/graph/ModuleTree$.MODULE$:Lcoursier/graph/ModuleTree$;
         3: aload_0
         4: invokevirtual #54                 // Method dependencyTrees:()Lscala/collection/immutable/Seq;
         7: invokedynamic #75,  0             // InvokeDynamic #0:apply:()Lscala/Function1;
        12: invokeinterface #81,  2           // InterfaceMethod scala/collection/immutable/Seq.flatMap:(Lscala/Function1;)Ljava/lang/Object;
        17: checkcast     #77                 // class scala/collection/immutable/Seq
        20: invokevirtual #84                 // Method coursier/graph/ModuleTree$.apply:(Lscala/collection/immutable/Seq;)Lscala/collection/immutable/Seq;
        23: areturn
      LineNumberTable:
        line 63: 0
      LocalVariableTable:
        Start  Length  Slot  Name   Signature
            0      24     0  this   Lcoursier/graph/ModuleTree$Node;
    Signature: #46                          // ()Lscala/collection/immutable/Seq<Lcoursier/graph/ModuleTree;>;

  public coursier.graph.ModuleTree$Node copy(coursier.core.Module, java.lang.String, java.lang.String, scala.collection.immutable.Seq<coursier.graph.DependencyTree>);
    descriptor: (Lcoursier/core/Module;Ljava/lang/String;Ljava/lang/String;Lscala/collection/immutable/Seq;)Lcoursier/graph/ModuleTree$Node;
    flags: (0x0001) ACC_PUBLIC
    Code:
      stack=6, locals=5, args_size=5
         0: new           #2                  // class coursier/graph/ModuleTree$Node
         3: dup
         4: aload_1
         5: aload_2
         6: aload_3
         7: aload         4
         9: invokespecial #91                 // Method "<init>":(Lcoursier/core/Module;Ljava/lang/String;Ljava/lang/String;Lscala/collection/immutable/Seq;)V
        12: areturn
      LineNumberTable:
        line 56: 0
        line 57: 4
        line 58: 5
        line 59: 6
        line 60: 7
      LocalVariableTable:
        Start  Length  Slot  Name   Signature
            0      13     0  this   Lcoursier/graph/ModuleTree$Node;
            0      13     1 module   Lcoursier/core/Module;
            0      13     2 reconciledVersion   Ljava/lang/String;
            0      13     3 retainedVersion   Ljava/lang/String;
            0      13     4 dependencyTrees   Lscala/collection/immutable/Seq;
    Signature: #87                          // (Lcoursier/core/Module;Ljava/lang/String;Ljava/lang/String;Lscala/collection/immutable/Seq<Lcoursier/graph/DependencyTree;>;)Lcoursier/graph/ModuleTree$Node;
    MethodParameters:
      Name                           Flags
      module                         final
      reconciledVersion              final
      retainedVersion                final
      dependencyTrees                final

  public coursier.core.Module copy$default$1();
    descriptor: ()Lcoursier/core/Module;
    flags: (0x0001) ACC_PUBLIC
    Code:
      stack=1, locals=1, args_size=1
         0: aload_0
         1: invokevirtual #94                 // Method module:()Lcoursier/core/Module;
         4: areturn
      LineNumberTable:
        line 57: 0
      LocalVariableTable:
        Start  Length  Slot  Name   Signature
            0       5     0  this   Lcoursier/graph/ModuleTree$Node;

  public java.lang.String copy$default$2();
    descriptor: ()Ljava/lang/String;
    flags: (0x0001) ACC_PUBLIC
    Code:
      stack=1, locals=1, args_size=1
         0: aload_0
         1: invokevirtual #97                 // Method reconciledVersion:()Ljava/lang/String;
         4: areturn
      LineNumberTable:
        line 58: 0
      LocalVariableTable:
        Start  Length  Slot  Name   Signature
            0       5     0  this   Lcoursier/graph/ModuleTree$Node;

  public java.lang.String copy$default$3();
    descriptor: ()Ljava/lang/String;
    flags: (0x0001) ACC_PUBLIC
    Code:
      stack=1, locals=1, args_size=1
         0: aload_0
         1: invokevirtual #100                // Method retainedVersion:()Ljava/lang/String;
         4: areturn
      LineNumberTable:
        line 59: 0
      LocalVariableTable:
        Start  Length  Slot  Name   Signature
            0       5     0  this   Lcoursier/graph/ModuleTree$Node;

  public scala.collection.immutable.Seq<coursier.graph.DependencyTree> copy$default$4();
    descriptor: ()Lscala/collection/immutable/Seq;
    flags: (0x0001) ACC_PUBLIC
    Code:
      stack=1, locals=1, args_size=1
         0: aload_0
         1: invokevirtual #54                 // Method dependencyTrees:()Lscala/collection/immutable/Seq;
         4: areturn
      LineNumberTable:
        line 60: 0
      LocalVariableTable:
        Start  Length  Slot  Name   Signature
            0       5     0  this   Lcoursier/graph/ModuleTree$Node;
    Signature: #42                          // ()Lscala/collection/immutable/Seq<Lcoursier/graph/DependencyTree;>;

  public java.lang.String productPrefix();
    descriptor: ()Ljava/lang/String;
    flags: (0x0001) ACC_PUBLIC
    Code:
      stack=1, locals=1, args_size=1
         0: ldc           #103                // String Node
         2: areturn
      LineNumberTable:
        line 56: 0
      LocalVariableTable:
        Start  Length  Slot  Name   Signature
            0       3     0  this   Lcoursier/graph/ModuleTree$Node;

  public int productArity();
    descriptor: ()I
    flags: (0x0001) ACC_PUBLIC
    Code:
      stack=1, locals=1, args_size=1
         0: iconst_4
         1: ireturn
      LineNumberTable:
        line 56: 0
      LocalVariableTable:
        Start  Length  Slot  Name   Signature
            0       2     0  this   Lcoursier/graph/ModuleTree$Node;

  public java.lang.Object productElement(int);
    descriptor: (I)Ljava/lang/Object;
    flags: (0x0001) ACC_PUBLIC
    Code:
      stack=1, locals=3, args_size=2
         0: iload_1
         1: istore_2
         2: iload_2
         3: tableswitch   { // 0 to 3
                       0: 32
                       1: 39
                       2: 46
                       3: 53
                 default: 60
            }
        32: aload_0
        33: invokevirtual #94                 // Method module:()Lcoursier/core/Module;
        36: goto          67
        39: aload_0
        40: invokevirtual #97                 // Method reconciledVersion:()Ljava/lang/String;
        43: goto          67
        46: aload_0
        47: invokevirtual #100                // Method retainedVersion:()Ljava/lang/String;
        50: goto          67
        53: aload_0
        54: invokevirtual #54                 // Method dependencyTrees:()Lscala/collection/immutable/Seq;
        57: goto          67
        60: iload_1
        61: invokestatic  #113                // Method scala/runtime/Statics.ioobe:(I)Ljava/lang/Object;
        64: goto          67
        67: areturn
      StackMapTable: number_of_entries = 6
        frame_type = 252 /* append */
          offset_delta = 32
          locals = [ int ]
        frame_type = 6 /* same */
        frame_type = 6 /* same */
        frame_type = 6 /* same */
        frame_type = 6 /* same */
        frame_type = 70 /* same_locals_1_stack_item */
          stack = [ class java/lang/Object ]
      LineNumberTable:
        line 56: 0
      LocalVariableTable:
        Start  Length  Slot  Name   Signature
            0      68     0  this   Lcoursier/graph/ModuleTree$Node;
            0      68     1   x$1   I
    MethodParameters:
      Name                           Flags
      x$1                            final

  public scala.collection.Iterator<java.lang.Object> productIterator();
    descriptor: ()Lscala/collection/Iterator;
    flags: (0x0001) ACC_PUBLIC
    Code:
      stack=2, locals=1, args_size=1
         0: getstatic     #123                // Field scala/runtime/ScalaRunTime$.MODULE$:Lscala/runtime/ScalaRunTime$;
         3: aload_0
         4: invokevirtual #126                // Method scala/runtime/ScalaRunTime$.typedProductIterator:(Lscala/Product;)Lscala/collection/Iterator;
         7: areturn
      LineNumberTable:
        line 56: 0
      LocalVariableTable:
        Start  Length  Slot  Name   Signature
            0       8     0  this   Lcoursier/graph/ModuleTree$Node;
    Signature: #118                         // ()Lscala/collection/Iterator<Ljava/lang/Object;>;

  public boolean canEqual(java.lang.Object);
    descriptor: (Ljava/lang/Object;)Z
    flags: (0x0001) ACC_PUBLIC
    Code:
      stack=1, locals=2, args_size=2
         0: aload_1
         1: instanceof    #2                  // class coursier/graph/ModuleTree$Node
         4: ireturn
      LineNumberTable:
        line 56: 0
      LocalVariableTable:
        Start  Length  Slot  Name   Signature
            0       5     0  this   Lcoursier/graph/ModuleTree$Node;
            0       5     1   x$1   Ljava/lang/Object;
    MethodParameters:
      Name                           Flags
      x$1                            final

  public java.lang.String productElementName(int);
    descriptor: (I)Ljava/lang/String;
    flags: (0x0001) ACC_PUBLIC
    Code:
      stack=1, locals=3, args_size=2
         0: iload_1
         1: istore_2
         2: iload_2
         3: tableswitch   { // 0 to 3
                       0: 32
                       1: 37
                       2: 42
                       3: 47
                 default: 52
            }
        32: ldc           #132                // String module
        34: goto          62
        37: ldc           #133                // String reconciledVersion
        39: goto          62
        42: ldc           #134                // String retainedVersion
        44: goto          62
        47: ldc           #135                // String dependencyTrees
        49: goto          62
        52: iload_1
        53: invokestatic  #113                // Method scala/runtime/Statics.ioobe:(I)Ljava/lang/Object;
        56: checkcast     #137                // class java/lang/String
        59: goto          62
        62: areturn
      StackMapTable: number_of_entries = 6
        frame_type = 252 /* append */
          offset_delta = 32
          locals = [ int ]
        frame_type = 4 /* same */
        frame_type = 4 /* same */
        frame_type = 4 /* same */
        frame_type = 4 /* same */
        frame_type = 73 /* same_locals_1_stack_item */
          stack = [ class java/lang/String ]
      LineNumberTable:
        line 56: 0
      LocalVariableTable:
        Start  Length  Slot  Name   Signature
            0      63     0  this   Lcoursier/graph/ModuleTree$Node;
            0      63     1   x$1   I
    MethodParameters:
      Name                           Flags
      x$1                            final

  public int hashCode();
    descriptor: ()I
    flags: (0x0001) ACC_PUBLIC
    Code:
      stack=2, locals=1, args_size=1
         0: getstatic     #123                // Field scala/runtime/ScalaRunTime$.MODULE$:Lscala/runtime/ScalaRunTime$;
         3: aload_0
         4: invokevirtual #142                // Method scala/runtime/ScalaRunTime$._hashCode:(Lscala/Product;)I
         7: ireturn
      LineNumberTable:
        line 56: 0
      LocalVariableTable:
        Start  Length  Slot  Name   Signature
            0       8     0  this   Lcoursier/graph/ModuleTree$Node;

  public java.lang.String toString();
    descriptor: ()Ljava/lang/String;
    flags: (0x0001) ACC_PUBLIC
    Code:
      stack=2, locals=1, args_size=1
         0: getstatic     #123                // Field scala/runtime/ScalaRunTime$.MODULE$:Lscala/runtime/ScalaRunTime$;
         3: aload_0
         4: invokevirtual #147                // Method scala/runtime/ScalaRunTime$._toString:(Lscala/Product;)Ljava/lang/String;
         7: areturn
      LineNumberTable:
        line 56: 0
      LocalVariableTable:
        Start  Length  Slot  Name   Signature
            0       8     0  this   Lcoursier/graph/ModuleTree$Node;

  public boolean equals(java.lang.Object);
    descriptor: (Ljava/lang/Object;)Z
    flags: (0x0001) ACC_PUBLIC
    Code:
      stack=2, locals=9, args_size=2
         0: aload_0
         1: aload_1
         2: if_acmpeq     173
         5: aload_1
         6: astore_3
         7: aload_3
         8: instanceof    #2                  // class coursier/graph/ModuleTree$Node
        11: ifeq          19
        14: iconst_1
        15: istore_2
        16: goto          27
        19: goto          22
        22: iconst_0
        23: istore_2
        24: goto          27
        27: iload_2
        28: ifeq          177
        31: aload_1
        32: checkcast     #2                  // class coursier/graph/ModuleTree$Node
        35: astore        4
        37: aload_0
        38: invokevirtual #94                 // Method module:()Lcoursier/core/Module;
        41: aload         4
        43: invokevirtual #94                 // Method module:()Lcoursier/core/Module;
        46: astore        5
        48: dup
        49: ifnonnull     61
        52: pop
        53: aload         5
        55: ifnull        69
        58: goto          169
        61: aload         5
        63: invokevirtual #152                // Method java/lang/Object.equals:(Ljava/lang/Object;)Z
        66: ifeq          169
        69: aload_0
        70: invokevirtual #97                 // Method reconciledVersion:()Ljava/lang/String;
        73: aload         4
        75: invokevirtual #97                 // Method reconciledVersion:()Ljava/lang/String;
        78: astore        6
        80: dup
        81: ifnonnull     93
        84: pop
        85: aload         6
        87: ifnull        101
        90: goto          169
        93: aload         6
        95: invokevirtual #152                // Method java/lang/Object.equals:(Ljava/lang/Object;)Z
        98: ifeq          169
       101: aload_0
       102: invokevirtual #100                // Method retainedVersion:()Ljava/lang/String;
       105: aload         4
       107: invokevirtual #100                // Method retainedVersion:()Ljava/lang/String;
       110: astore        7
       112: dup
       113: ifnonnull     125
       116: pop
       117: aload         7
       119: ifnull        133
       122: goto          169
       125: aload         7
       127: invokevirtual #152                // Method java/lang/Object.equals:(Ljava/lang/Object;)Z
       130: ifeq          169
       133: aload_0
       134: invokevirtual #54                 // Method dependencyTrees:()Lscala/collection/immutable/Seq;
       137: aload         4
       139: invokevirtual #54                 // Method dependencyTrees:()Lscala/collection/immutable/Seq;
       142: astore        8
       144: dup
       145: ifnonnull     157
       148: pop
       149: aload         8
       151: ifnull        165
       154: goto          169
       157: aload         8
       159: invokevirtual #152                // Method java/lang/Object.equals:(Ljava/lang/Object;)Z
       162: ifeq          169
       165: iconst_1
       166: goto          170
       169: iconst_0
       170: ifeq          177
       173: iconst_1
       174: goto          178
       177: iconst_0
       178: ireturn
      StackMapTable: number_of_entries = 16
        frame_type = 253 /* append */
          offset_delta = 19
          locals = [ top, class java/lang/Object ]
        frame_type = 2 /* same */
        frame_type = 255 /* full_frame */
          offset_delta = 4
          locals = [ class coursier/graph/ModuleTree$Node, class java/lang/Object, int, class java/lang/Object ]
          stack = []
        frame_type = 255 /* full_frame */
          offset_delta = 33
          locals = [ class coursier/graph/ModuleTree$Node, class java/lang/Object, int, class java/lang/Object, class coursier/graph/ModuleTree$Node, class coursier/core/Module ]
          stack = [ class coursier/core/Module ]
        frame_type = 7 /* same */
        frame_type = 255 /* full_frame */
          offset_delta = 23
          locals = [ class coursier/graph/ModuleTree$Node, class java/lang/Object, int, class java/lang/Object, class coursier/graph/ModuleTree$Node, class coursier/core/Module, class java/lang/String ]
          stack = [ class java/lang/String ]
        frame_type = 7 /* same */
        frame_type = 255 /* full_frame */
          offset_delta = 23
          locals = [ class coursier/graph/ModuleTree$Node, class java/lang/Object, int, class java/lang/Object, class coursier/graph/ModuleTree$Node, class coursier/core/Module, class java/lang/String, class java/lang/String ]
          stack = [ class java/lang/String ]
        frame_type = 7 /* same */
        frame_type = 255 /* full_frame */
          offset_delta = 23
          locals = [ class coursier/graph/ModuleTree$Node, class java/lang/Object, int, class java/lang/Object, class coursier/graph/ModuleTree$Node, class coursier/core/Module, class java/lang/String, class java/lang/String, class scala/collection/immutable/Seq ]
          stack = [ class scala/collection/immutable/Seq ]
        frame_type = 7 /* same */
        frame_type = 248 /* chop */
          offset_delta = 3
        frame_type = 64 /* same_locals_1_stack_item */
          stack = [ int ]
        frame_type = 255 /* full_frame */
          offset_delta = 2
          locals = [ class coursier/graph/ModuleTree$Node, class java/lang/Object ]
          stack = []
        frame_type = 253 /* append */
          offset_delta = 3
          locals = [ int, class java/lang/Object ]
        frame_type = 255 /* full_frame */
          offset_delta = 0
          locals = [ class coursier/graph/ModuleTree$Node, class java/lang/Object ]
          stack = [ int ]
      LineNumberTable:
        line 56: 0
      LocalVariableTable:
        Start  Length  Slot  Name   Signature
            0     179     0  this   Lcoursier/graph/ModuleTree$Node;
            0     179     1   x$1   Ljava/lang/Object;
    MethodParameters:
      Name                           Flags
      x$1                            final

  public static final scala.collection.immutable.Seq $anonfun$children$1(coursier.graph.DependencyTree);
    descriptor: (Lcoursier/graph/DependencyTree;)Lscala/collection/immutable/Seq;
    flags: (0x1019) ACC_PUBLIC, ACC_STATIC, ACC_FINAL, ACC_SYNTHETIC
    Code:
      stack=1, locals=1, args_size=1
         0: aload_0
         1: invokevirtual #157                // Method coursier/graph/DependencyTree.children:()Lscala/collection/immutable/Seq;
         4: areturn
      LineNumberTable:
        line 63: 0
      LocalVariableTable:
        Start  Length  Slot  Name   Signature
            0       5     0   x$4   Lcoursier/graph/DependencyTree;
    MethodParameters:
      Name                           Flags
      x$4                            final

  public coursier.graph.ModuleTree$Node(coursier.core.Module, java.lang.String, java.lang.String, scala.collection.immutable.Seq<coursier.graph.DependencyTree>);
    descriptor: (Lcoursier/core/Module;Ljava/lang/String;Ljava/lang/String;Lscala/collection/immutable/Seq;)V
    flags: (0x0001) ACC_PUBLIC
    Code:
      stack=2, locals=5, args_size=5
         0: aload_0
         1: aload_1
         2: putfield      #35                 // Field module:Lcoursier/core/Module;
         5: aload_0
         6: aload_2
         7: putfield      #38                 // Field reconciledVersion:Ljava/lang/String;
        10: aload_0
        11: aload_3
        12: putfield      #40                 // Field retainedVersion:Ljava/lang/String;
        15: aload_0
        16: aload         4
        18: putfield      #44                 // Field dependencyTrees:Lscala/collection/immutable/Seq;
        21: aload_0
        22: invokespecial #162                // Method coursier/graph/ModuleTree."<init>":()V
        25: aload_0
        26: invokestatic  #166                // InterfaceMethod scala/Product.$init$:(Lscala/Product;)V
        29: return
      LineNumberTable:
        line 57: 0
        line 58: 5
        line 59: 10
        line 60: 15
        line 61: 21
        line 56: 29
      LocalVariableTable:
        Start  Length  Slot  Name   Signature
            0      30     0  this   Lcoursier/graph/ModuleTree$Node;
            0      30     1 module   Lcoursier/core/Module;
            0      30     2 reconciledVersion   Ljava/lang/String;
            0      30     3 retainedVersion   Ljava/lang/String;
            0      30     4 dependencyTrees   Lscala/collection/immutable/Seq;
    Signature: #159                         // (Lcoursier/core/Module;Ljava/lang/String;Ljava/lang/String;Lscala/collection/immutable/Seq<Lcoursier/graph/DependencyTree;>;)V
    MethodParameters:
      Name                           Flags
      module                         final
      reconciledVersion              final
      retainedVersion                final
      dependencyTrees                final

  private static java.lang.Object $deserializeLambda$(java.lang.invoke.SerializedLambda);
    descriptor: (Ljava/lang/invoke/SerializedLambda;)Ljava/lang/Object;
    flags: (0x100a) ACC_PRIVATE, ACC_STATIC, ACC_SYNTHETIC
    Code:
      stack=1, locals=1, args_size=1
         0: aload_0
         1: invokedynamic #178,  0            // InvokeDynamic #1:lambdaDeserialize:(Ljava/lang/invoke/SerializedLambda;)Ljava/lang/Object;
         6: areturn
}
InnerClasses:
  public static final #10= #2 of #4;      // Node=class coursier/graph/ModuleTree$Node of class coursier/graph/ModuleTree
  public static final #15= #12 of #14;    // Lookup=class java/lang/invoke/MethodHandles$Lookup of class java/lang/invoke/MethodHandles
SourceFile: "ModuleTree.scala"
BootstrapMethods:
  0: #71 REF_invokeStatic java/lang/invoke/LambdaMetafactory.altMetafactory:(Ljava/lang/invoke/MethodHandles$Lookup;Ljava/lang/String;Ljava/lang/invoke/MethodType;[Ljava/lang/Object;)Ljava/lang/invoke/CallSite;
    Method arguments:
      #56 (Ljava/lang/Object;)Ljava/lang/Object;
      #61 REF_invokeStatic coursier/graph/ModuleTree$Node.$anonfun$children$1:(Lcoursier/graph/DependencyTree;)Lscala/collection/immutable/Seq;
      #62 (Lcoursier/graph/DependencyTree;)Lscala/collection/immutable/Seq;
      #63 5
      #64 1
      #62 (Lcoursier/graph/DependencyTree;)Lscala/collection/immutable/Seq;
  1: #175 REF_invokeStatic scala/runtime/LambdaDeserialize.bootstrap:(Ljava/lang/invoke/MethodHandles$Lookup;Ljava/lang/String;Ljava/lang/invoke/MethodType;[Ljava/lang/invoke/MethodHandle;)Ljava/lang/invoke/CallSite;
    Method arguments:
      #61 REF_invokeStatic coursier/graph/ModuleTree$Node.$anonfun$children$1:(Lcoursier/graph/DependencyTree;)Lscala/collection/immutable/Seq;
  ScalaInlineInfo: length = 0x72 (unknown attribute)
   01 01 00 16 00 39 00 3A 01 00 58 00 59 01 00 7F
   00 80 01 00 2D 00 29 01 00 55 00 56 01 00 5C 00
   21 01 00 5F 00 24 01 00 62 00 24 01 00 65 00 29
   01 00 15 00 29 01 00 94 00 80 01 00 8A 00 69 01
   00 10 00 21 01 00 68 00 69 01 00 6A 00 6B 01 00
   82 00 83 01 00 18 00 19 01 00 75 00 19 01 00 66
   00 24 01 00 12 00 24 01 00 14 00 24 01 00 8F 00
   24 01
  Scala: length = 0x0 (unknown attribute)

