Classfile /Users/mw/Projects/slang-braindump/.jar/jar8/assemble/slang-braindump/assemble/content/org/scalatest/AppendedClues$Clueful.class
  Last modified May 29, 2022; size 5421 bytes
  SHA-256 checksum 47e5abba54ffa4422abbf7e8bb499ecdb2d9e33ddaf3270ceec8fce5ed87cbda
  Compiled from "AppendedClues.scala"
public class org.scalatest.AppendedClues$Clueful<T extends java.lang.Object> extends java.lang.Object
  minor version: 0
  major version: 52
  flags: (0x0021) ACC_PUBLIC, ACC_SUPER
  this_class: #2                          // org/scalatest/AppendedClues$Clueful
  super_class: #5                         // java/lang/Object
  interfaces: 0, fields: 2, methods: 8, attributes: 6
Constant pool:
    #1 = Utf8               org/scalatest/AppendedClues$Clueful
    #2 = Class              #1            // org/scalatest/AppendedClues$Clueful
    #3 = Utf8               <T:Ljava/lang/Object;>Ljava/lang/Object;
    #4 = Utf8               java/lang/Object
    #5 = Class              #4            // java/lang/Object
    #6 = Utf8               AppendedClues.scala
    #7 = Utf8               java/lang/invoke/MethodHandles$Lookup
    #8 = Class              #7            // java/lang/invoke/MethodHandles$Lookup
    #9 = Utf8               java/lang/invoke/MethodHandles
   #10 = Class              #9            // java/lang/invoke/MethodHandles
   #11 = Utf8               Lookup
   #12 = Utf8               org/scalactic/Requirements$RequirementsHelper
   #13 = Class              #12           // org/scalactic/Requirements$RequirementsHelper
   #14 = Utf8               org/scalactic/Requirements
   #15 = Class              #14           // org/scalactic/Requirements
   #16 = Utf8               RequirementsHelper
   #17 = Utf8               org/scalatest/AppendedClues
   #18 = Class              #17           // org/scalatest/AppendedClues
   #19 = Utf8               Clueful
   #20 = Utf8               fun
   #21 = Utf8               Lscala/Function0;
   #22 = Utf8               Lscala/Function0<TT;>;
   #23 = Utf8               $outer
   #24 = Utf8               Lorg/scalatest/AppendedClues;
   #25 = Utf8               withClue
   #26 = Utf8               (Ljava/lang/Object;)Ljava/lang/Object;
   #27 = Utf8               (Ljava/lang/Object;)TT;
   #28 = Utf8               clue
   #29 = Utf8               java/lang/Throwable
   #30 = Class              #29           // java/lang/Throwable
   #31 = Utf8               org/scalactic/Requirements$
   #32 = Class              #31           // org/scalactic/Requirements$
   #33 = Utf8               MODULE$
   #34 = Utf8               Lorg/scalactic/Requirements$;
   #35 = NameAndType        #33:#34       // MODULE$:Lorg/scalactic/Requirements$;
   #36 = Fieldref           #32.#35       // org/scalactic/Requirements$.MODULE$:Lorg/scalactic/Requirements$;
   #37 = Utf8               requirementsHelper
   #38 = Utf8               ()Lorg/scalactic/Requirements$RequirementsHelper;
   #39 = NameAndType        #37:#38       // requirementsHelper:()Lorg/scalactic/Requirements$RequirementsHelper;
   #40 = Methodref          #32.#39       // org/scalactic/Requirements$.requirementsHelper:()Lorg/scalactic/Requirements$RequirementsHelper;
   #41 = Utf8               java/lang/String
   #42 = Class              #41           // java/lang/String
   #43 = String             #28           // clue
   #44 = Utf8               [Ljava/lang/Object;
   #45 = Class              #44           // "[Ljava/lang/Object;"
   #46 = Utf8               [Ljava/lang/String;
   #47 = Class              #46           // "[Ljava/lang/String;"
   #48 = Utf8               org/scalactic/Prettifier$
   #49 = Class              #48           // org/scalactic/Prettifier$
   #50 = Utf8               Lorg/scalactic/Prettifier$;
   #51 = NameAndType        #33:#50       // MODULE$:Lorg/scalactic/Prettifier$;
   #52 = Fieldref           #49.#51       // org/scalactic/Prettifier$.MODULE$:Lorg/scalactic/Prettifier$;
   #53 = Utf8               default
   #54 = Utf8               ()Lorg/scalactic/Prettifier;
   #55 = NameAndType        #53:#54       // default:()Lorg/scalactic/Prettifier;
   #56 = Methodref          #49.#55       // org/scalactic/Prettifier$.default:()Lorg/scalactic/Prettifier;
   #57 = Utf8               org/scalactic/source/Position
   #58 = Class              #57           // org/scalactic/source/Position
   #59 = String             #6            // AppendedClues.scala
   #60 = Utf8               Please set the environment variable SCALACTIC_FILL_FILE_PATHNAMES to yes at compile time to enable this feature.
   #61 = String             #60           // Please set the environment variable SCALACTIC_FILL_FILE_PATHNAMES to yes at compile time to enable this feature.
   #62 = Utf8               <init>
   #63 = Utf8               (Ljava/lang/String;Ljava/lang/String;I)V
   #64 = NameAndType        #62:#63       // "<init>":(Ljava/lang/String;Ljava/lang/String;I)V
   #65 = Methodref          #58.#64       // org/scalactic/source/Position."<init>":(Ljava/lang/String;Ljava/lang/String;I)V
   #66 = Utf8               macroRequireNonNull
   #67 = Utf8               ([Ljava/lang/String;[Ljava/lang/Object;Lorg/scalactic/Prettifier;Lorg/scalactic/source/Position;)V
   #68 = NameAndType        #66:#67       // macroRequireNonNull:([Ljava/lang/String;[Ljava/lang/Object;Lorg/scalactic/Prettifier;Lorg/scalactic/source/Position;)V
   #69 = Methodref          #13.#68       // org/scalactic/Requirements$RequirementsHelper.macroRequireNonNull:([Ljava/lang/String;[Ljava/lang/Object;Lorg/scalactic/Prettifier;Lorg/scalactic/source/Position;)V
   #70 = NameAndType        #20:#21       // fun:Lscala/Function0;
   #71 = Fieldref           #2.#70        // org/scalatest/AppendedClues$Clueful.fun:Lscala/Function0;
   #72 = Utf8               scala/Function0
   #73 = Class              #72           // scala/Function0
   #74 = Utf8               apply
   #75 = Utf8               ()Ljava/lang/Object;
   #76 = NameAndType        #74:#75       // apply:()Ljava/lang/Object;
   #77 = InterfaceMethodref #73.#76       // scala/Function0.apply:()Ljava/lang/Object;
   #78 = Utf8               org/scalatest/Failed
   #79 = Class              #78           // org/scalatest/Failed
   #80 = Utf8               exception
   #81 = Utf8               ()Ljava/lang/Throwable;
   #82 = NameAndType        #80:#81       // exception:()Ljava/lang/Throwable;
   #83 = Methodref          #79.#82       // org/scalatest/Failed.exception:()Ljava/lang/Throwable;
   #84 = Utf8               org/scalatest/exceptions/ModifiableMessage
   #85 = Class              #84           // org/scalatest/exceptions/ModifiableMessage
   #86 = Utf8               toString
   #87 = Utf8               ()Ljava/lang/String;
   #88 = NameAndType        #86:#87       // toString:()Ljava/lang/String;
   #89 = Methodref          #5.#88        // java/lang/Object.toString:()Ljava/lang/String;
   #90 = Utf8
   #91 = String             #90           //
   #92 = Utf8               equals
   #93 = Utf8               (Ljava/lang/Object;)Z
   #94 = NameAndType        #92:#93       // equals:(Ljava/lang/Object;)Z
   #95 = Methodref          #5.#94        // java/lang/Object.equals:(Ljava/lang/Object;)Z
   #96 = MethodType         #26           //  (Ljava/lang/Object;)Ljava/lang/Object;
   #97 = Utf8               $anonfun$withClue$1
   #98 = Utf8               (Ljava/lang/Object;Lscala/Option;)Lscala/Some;
   #99 = NameAndType        #97:#98       // $anonfun$withClue$1:(Ljava/lang/Object;Lscala/Option;)Lscala/Some;
  #100 = Methodref          #2.#99        // org/scalatest/AppendedClues$Clueful.$anonfun$withClue$1:(Ljava/lang/Object;Lscala/Option;)Lscala/Some;
  #101 = MethodHandle       6:#100        // REF_invokeStatic org/scalatest/AppendedClues$Clueful.$anonfun$withClue$1:(Ljava/lang/Object;Lscala/Option;)Lscala/Some;
  #102 = Utf8               (Lscala/Option;)Lscala/Some;
  #103 = MethodType         #102          //  (Lscala/Option;)Lscala/Some;
  #104 = Integer            5
  #105 = Integer            1
  #106 = Utf8               java/lang/invoke/LambdaMetafactory
  #107 = Class              #106          // java/lang/invoke/LambdaMetafactory
  #108 = Utf8               altMetafactory
  #109 = Utf8               (Ljava/lang/invoke/MethodHandles$Lookup;Ljava/lang/String;Ljava/lang/invoke/MethodType;[Ljava/lang/Object;)Ljava/lang/invoke/CallSite;
  #110 = NameAndType        #108:#109     // altMetafactory:(Ljava/lang/invoke/MethodHandles$Lookup;Ljava/lang/String;Ljava/lang/invoke/MethodType;[Ljava/lang/Object;)Ljava/lang/invoke/CallSite;
  #111 = Methodref          #107.#110     // java/lang/invoke/LambdaMetafactory.altMetafactory:(Ljava/lang/invoke/MethodHandles$Lookup;Ljava/lang/String;Ljava/lang/invoke/MethodType;[Ljava/lang/Object;)Ljava/lang/invoke/CallSite;
  #112 = MethodHandle       6:#111        // REF_invokeStatic java/lang/invoke/LambdaMetafactory.altMetafactory:(Ljava/lang/invoke/MethodHandles$Lookup;Ljava/lang/String;Ljava/lang/invoke/MethodType;[Ljava/lang/Object;)Ljava/lang/invoke/CallSite;
  #113 = Utf8               (Ljava/lang/Object;)Lscala/Function1;
  #114 = NameAndType        #74:#113      // apply:(Ljava/lang/Object;)Lscala/Function1;
  #115 = InvokeDynamic      #0:#114       // #0:apply:(Ljava/lang/Object;)Lscala/Function1;
  #116 = Utf8               modifyMessage
  #117 = Utf8               (Lscala/Function1;)Ljava/lang/Throwable;
  #118 = NameAndType        #116:#117     // modifyMessage:(Lscala/Function1;)Ljava/lang/Throwable;
  #119 = InterfaceMethodref #85.#118      // org/scalatest/exceptions/ModifiableMessage.modifyMessage:(Lscala/Function1;)Ljava/lang/Throwable;
  #120 = Utf8               (Ljava/lang/Throwable;)V
  #121 = NameAndType        #62:#120      // "<init>":(Ljava/lang/Throwable;)V
  #122 = Methodref          #79.#121      // org/scalatest/Failed."<init>":(Ljava/lang/Throwable;)V
  #123 = Utf8               org/scalatest/Canceled
  #124 = Class              #123          // org/scalatest/Canceled
  #125 = Utf8               ()Lorg/scalatest/exceptions/TestCanceledException;
  #126 = NameAndType        #80:#125      // exception:()Lorg/scalatest/exceptions/TestCanceledException;
  #127 = Methodref          #124.#126     // org/scalatest/Canceled.exception:()Lorg/scalatest/exceptions/TestCanceledException;
  #128 = Utf8               $anonfun$withClue$2
  #129 = NameAndType        #128:#98      // $anonfun$withClue$2:(Ljava/lang/Object;Lscala/Option;)Lscala/Some;
  #130 = Methodref          #2.#129       // org/scalatest/AppendedClues$Clueful.$anonfun$withClue$2:(Ljava/lang/Object;Lscala/Option;)Lscala/Some;
  #131 = MethodHandle       6:#130        // REF_invokeStatic org/scalatest/AppendedClues$Clueful.$anonfun$withClue$2:(Ljava/lang/Object;Lscala/Option;)Lscala/Some;
  #132 = InvokeDynamic      #1:#114       // #1:apply:(Ljava/lang/Object;)Lscala/Function1;
  #133 = Utf8               org/scalatest/exceptions/TestCanceledException
  #134 = Class              #133          // org/scalatest/exceptions/TestCanceledException
  #135 = Utf8               (Lscala/Function1;)Lorg/scalatest/exceptions/TestCanceledException;
  #136 = NameAndType        #116:#135     // modifyMessage:(Lscala/Function1;)Lorg/scalatest/exceptions/TestCanceledException;
  #137 = Methodref          #134.#136     // org/scalatest/exceptions/TestCanceledException.modifyMessage:(Lscala/Function1;)Lorg/scalatest/exceptions/TestCanceledException;
  #138 = Utf8               (Lorg/scalatest/exceptions/TestCanceledException;)V
  #139 = NameAndType        #62:#138      // "<init>":(Lorg/scalatest/exceptions/TestCanceledException;)V
  #140 = Methodref          #124.#139     // org/scalatest/Canceled."<init>":(Lorg/scalatest/exceptions/TestCanceledException;)V
  #141 = Utf8               $anonfun$withClue$3
  #142 = NameAndType        #141:#98      // $anonfun$withClue$3:(Ljava/lang/Object;Lscala/Option;)Lscala/Some;
  #143 = Methodref          #2.#142       // org/scalatest/AppendedClues$Clueful.$anonfun$withClue$3:(Ljava/lang/Object;Lscala/Option;)Lscala/Some;
  #144 = MethodHandle       6:#143        // REF_invokeStatic org/scalatest/AppendedClues$Clueful.$anonfun$withClue$3:(Ljava/lang/Object;Lscala/Option;)Lscala/Some;
  #145 = InvokeDynamic      #2:#114       // #2:apply:(Ljava/lang/Object;)Lscala/Function1;
  #146 = Utf8               e
  #147 = Utf8               Ljava/lang/Throwable;
  #148 = Utf8               Lorg/scalatest/exceptions/TestCanceledException;
  #149 = Utf8               outcome
  #150 = Utf8               Ljava/lang/Object;
  #151 = Utf8               this
  #152 = Utf8               Lorg/scalatest/AppendedClues$Clueful;
  #153 = Utf8               org$scalatest$AppendedClues$Clueful$$$outer
  #154 = Utf8               ()Lorg/scalatest/AppendedClues;
  #155 = NameAndType        #23:#24       // $outer:Lorg/scalatest/AppendedClues;
  #156 = Fieldref           #2.#155       // org/scalatest/AppendedClues$Clueful.$outer:Lorg/scalatest/AppendedClues;
  #157 = Utf8               append$1
  #158 = Utf8               (Lscala/Option;Ljava/lang/Object;)Lscala/Some;
  #159 = Utf8               currentMessage
  #160 = Utf8               clue$1
  #161 = Utf8               scala/Some
  #162 = Class              #161          // scala/Some
  #163 = Utf8               value
  #164 = NameAndType        #163:#75      // value:()Ljava/lang/Object;
  #165 = Methodref          #162.#164     // scala/Some.value:()Ljava/lang/Object;
  #166 = Utf8               org/scalatest/AppendedClues$
  #167 = Class              #166          // org/scalatest/AppendedClues$
  #168 = Utf8               Lorg/scalatest/AppendedClues$;
  #169 = NameAndType        #33:#168      // MODULE$:Lorg/scalatest/AppendedClues$;
  #170 = Fieldref           #167.#169     // org/scalatest/AppendedClues$.MODULE$:Lorg/scalatest/AppendedClues$;
  #171 = Utf8               appendClue
  #172 = Utf8               (Ljava/lang/String;Ljava/lang/String;)Ljava/lang/String;
  #173 = NameAndType        #171:#172     // appendClue:(Ljava/lang/String;Ljava/lang/String;)Ljava/lang/String;
  #174 = Methodref          #167.#173     // org/scalatest/AppendedClues$.appendClue:(Ljava/lang/String;Ljava/lang/String;)Ljava/lang/String;
  #175 = Utf8               (Ljava/lang/Object;)V
  #176 = NameAndType        #62:#175      // "<init>":(Ljava/lang/Object;)V
  #177 = Methodref          #162.#176     // scala/Some."<init>":(Ljava/lang/Object;)V
  #178 = Utf8               scala/None$
  #179 = Class              #178          // scala/None$
  #180 = Utf8               Lscala/None$;
  #181 = NameAndType        #33:#180      // MODULE$:Lscala/None$;
  #182 = Fieldref           #179.#181     // scala/None$.MODULE$:Lscala/None$;
  #183 = Utf8               scala/MatchError
  #184 = Class              #183          // scala/MatchError
  #185 = Methodref          #184.#176     // scala/MatchError."<init>":(Ljava/lang/Object;)V
  #186 = Utf8               msg
  #187 = Utf8               Ljava/lang/String;
  #188 = Utf8               Lscala/Option;
  #189 = Utf8               scala/Option
  #190 = Class              #189          // scala/Option
  #191 = NameAndType        #157:#158     // append$1:(Lscala/Option;Ljava/lang/Object;)Lscala/Some;
  #192 = Methodref          #2.#191       // org/scalatest/AppendedClues$Clueful.append$1:(Lscala/Option;Ljava/lang/Object;)Lscala/Some;
  #193 = Utf8               (Lorg/scalatest/AppendedClues;Lscala/Function0;)V
  #194 = Utf8               (Lscala/Function0<TT;>;)V
  #195 = Utf8               ()V
  #196 = NameAndType        #62:#195      // "<init>":()V
  #197 = Methodref          #5.#196       // java/lang/Object."<init>":()V
  #198 = Utf8               $deserializeLambda$
  #199 = Utf8               (Ljava/lang/invoke/SerializedLambda;)Ljava/lang/Object;
  #200 = Utf8               scala/runtime/LambdaDeserialize
  #201 = Class              #200          // scala/runtime/LambdaDeserialize
  #202 = Utf8               bootstrap
  #203 = Utf8               (Ljava/lang/invoke/MethodHandles$Lookup;Ljava/lang/String;Ljava/lang/invoke/MethodType;[Ljava/lang/invoke/MethodHandle;)Ljava/lang/invoke/CallSite;
  #204 = NameAndType        #202:#203     // bootstrap:(Ljava/lang/invoke/MethodHandles$Lookup;Ljava/lang/String;Ljava/lang/invoke/MethodType;[Ljava/lang/invoke/MethodHandle;)Ljava/lang/invoke/CallSite;
  #205 = Methodref          #201.#204     // scala/runtime/LambdaDeserialize.bootstrap:(Ljava/lang/invoke/MethodHandles$Lookup;Ljava/lang/String;Ljava/lang/invoke/MethodType;[Ljava/lang/invoke/MethodHandle;)Ljava/lang/invoke/CallSite;
  #206 = MethodHandle       6:#205        // REF_invokeStatic scala/runtime/LambdaDeserialize.bootstrap:(Ljava/lang/invoke/MethodHandles$Lookup;Ljava/lang/String;Ljava/lang/invoke/MethodType;[Ljava/lang/invoke/MethodHandle;)Ljava/lang/invoke/CallSite;
  #207 = Utf8               lambdaDeserialize
  #208 = NameAndType        #207:#199     // lambdaDeserialize:(Ljava/lang/invoke/SerializedLambda;)Ljava/lang/Object;
  #209 = InvokeDynamic      #3:#208       // #3:lambdaDeserialize:(Ljava/lang/invoke/SerializedLambda;)Ljava/lang/Object;
  #210 = Utf8               Signature
  #211 = Utf8               Code
  #212 = Utf8               StackMapTable
  #213 = Utf8               LineNumberTable
  #214 = Utf8               LocalVariableTable
  #215 = Utf8               MethodParameters
  #216 = Utf8               InnerClasses
  #217 = Utf8               SourceFile
  #218 = Utf8               BootstrapMethods
  #219 = Utf8               ScalaInlineInfo
  #220 = Utf8               Scala
{
  private final scala.Function0<T> fun;
    descriptor: Lscala/Function0;
    flags: (0x0012) ACC_PRIVATE, ACC_FINAL
    Signature: #22                          // Lscala/Function0<TT;>;

  public final org.scalatest.AppendedClues $outer;
    descriptor: Lorg/scalatest/AppendedClues;
    flags: (0x1011) ACC_PUBLIC, ACC_FINAL, ACC_SYNTHETIC

  public T withClue(java.lang.Object);
    descriptor: (Ljava/lang/Object;)Ljava/lang/Object;
    flags: (0x0001) ACC_PUBLIC
    Code:
      stack=9, locals=18, args_size=2
         0: getstatic     #36                 // Field org/scalactic/Requirements$.MODULE$:Lorg/scalactic/Requirements$;
         3: invokevirtual #40                 // Method org/scalactic/Requirements$.requirementsHelper:()Lorg/scalactic/Requirements$RequirementsHelper;
         6: iconst_1
         7: anewarray     #42                 // class java/lang/String
        10: dup
        11: iconst_0
        12: ldc           #43                 // String clue
        14: aastore
        15: checkcast     #45                 // class "[Ljava/lang/Object;"
        18: checkcast     #47                 // class "[Ljava/lang/String;"
        21: iconst_1
        22: anewarray     #5                  // class java/lang/Object
        25: dup
        26: iconst_0
        27: aload_1
        28: aastore
        29: checkcast     #45                 // class "[Ljava/lang/Object;"
        32: getstatic     #52                 // Field org/scalactic/Prettifier$.MODULE$:Lorg/scalactic/Prettifier$;
        35: invokevirtual #56                 // Method org/scalactic/Prettifier$.default:()Lorg/scalactic/Prettifier;
        38: new           #58                 // class org/scalactic/source/Position
        41: dup
        42: ldc           #59                 // String AppendedClues.scala
        44: ldc           #61                 // String Please set the environment variable SCALACTIC_FILL_FILE_PATHNAMES to yes at compile time to enable this feature.
        46: sipush        144
        49: invokespecial #65                 // Method org/scalactic/source/Position."<init>":(Ljava/lang/String;Ljava/lang/String;I)V
        52: invokevirtual #69                 // Method org/scalactic/Requirements$RequirementsHelper.macroRequireNonNull:([Ljava/lang/String;[Ljava/lang/Object;Lorg/scalactic/Prettifier;Lorg/scalactic/source/Position;)V
        55: aload_0
        56: getfield      #71                 // Field fun:Lscala/Function0;
        59: invokeinterface #77,  1           // InterfaceMethod scala/Function0.apply:()Ljava/lang/Object;
        64: astore        4
        66: aload         4
        68: astore        5
        70: aload         5
        72: instanceof    #79                 // class org/scalatest/Failed
        75: ifeq          166
        78: aload         5
        80: checkcast     #79                 // class org/scalatest/Failed
        83: astore        6
        85: aload         6
        87: invokevirtual #83                 // Method org/scalatest/Failed.exception:()Ljava/lang/Throwable;
        90: astore        7
        92: aload         7
        94: instanceof    #85                 // class org/scalatest/exceptions/ModifiableMessage
        97: ifeq          163
       100: aload         7
       102: astore        8
       104: aload_1
       105: invokevirtual #89                 // Method java/lang/Object.toString:()Ljava/lang/String;
       108: ldc           #91                 // String
       110: astore        9
       112: dup
       113: ifnonnull     125
       116: pop
       117: aload         9
       119: ifnull        160
       122: goto          133
       125: aload         9
       127: invokevirtual #95                 // Method java/lang/Object.equals:(Ljava/lang/Object;)Z
       130: ifne          160
       133: new           #79                 // class org/scalatest/Failed
       136: dup
       137: aload         8
       139: checkcast     #85                 // class org/scalatest/exceptions/ModifiableMessage
       142: aload_1
       143: invokedynamic #115,  0            // InvokeDynamic #0:apply:(Ljava/lang/Object;)Lscala/Function1;
       148: invokeinterface #119,  2          // InterfaceMethod org/scalatest/exceptions/ModifiableMessage.modifyMessage:(Lscala/Function1;)Ljava/lang/Throwable;
       153: invokespecial #122                // Method org/scalatest/Failed."<init>":(Ljava/lang/Throwable;)V
       156: astore_3
       157: goto          266
       160: goto          169
       163: goto          169
       166: goto          169
       169: aload         5
       171: instanceof    #124                // class org/scalatest/Canceled
       174: ifeq          257
       177: aload         5
       179: checkcast     #124                // class org/scalatest/Canceled
       182: astore        10
       184: aload         10
       186: invokevirtual #127                // Method org/scalatest/Canceled.exception:()Lorg/scalatest/exceptions/TestCanceledException;
       189: astore        11
       191: aload         11
       193: ifnull        254
       196: aload         11
       198: astore        12
       200: aload_1
       201: invokevirtual #89                 // Method java/lang/Object.toString:()Ljava/lang/String;
       204: ldc           #91                 // String
       206: astore        13
       208: dup
       209: ifnonnull     221
       212: pop
       213: aload         13
       215: ifnull        251
       218: goto          229
       221: aload         13
       223: invokevirtual #95                 // Method java/lang/Object.equals:(Ljava/lang/Object;)Z
       226: ifne          251
       229: new           #124                // class org/scalatest/Canceled
       232: dup
       233: aload         12
       235: aload_1
       236: invokedynamic #132,  0            // InvokeDynamic #1:apply:(Ljava/lang/Object;)Lscala/Function1;
       241: invokevirtual #137                // Method org/scalatest/exceptions/TestCanceledException.modifyMessage:(Lscala/Function1;)Lorg/scalatest/exceptions/TestCanceledException;
       244: invokespecial #140                // Method org/scalatest/Canceled."<init>":(Lorg/scalatest/exceptions/TestCanceledException;)V
       247: astore_3
       248: goto          266
       251: goto          260
       254: goto          260
       257: goto          260
       260: aload         4
       262: astore_3
       263: goto          266
       266: aload_3
       267: goto          343
       270: astore        14
       272: aload         14
       274: astore        15
       276: aload         15
       278: instanceof    #85                 // class org/scalatest/exceptions/ModifiableMessage
       281: ifeq          337
       284: aload         15
       286: astore        16
       288: aload_1
       289: invokevirtual #89                 // Method java/lang/Object.toString:()Ljava/lang/String;
       292: ldc           #91                 // String
       294: astore        17
       296: dup
       297: ifnonnull     309
       300: pop
       301: aload         17
       303: ifnull        334
       306: goto          317
       309: aload         17
       311: invokevirtual #95                 // Method java/lang/Object.equals:(Ljava/lang/Object;)Z
       314: ifne          334
       317: aload         16
       319: checkcast     #85                 // class org/scalatest/exceptions/ModifiableMessage
       322: aload_1
       323: invokedynamic #145,  0            // InvokeDynamic #2:apply:(Ljava/lang/Object;)Lscala/Function1;
       328: invokeinterface #119,  2          // InterfaceMethod org/scalatest/exceptions/ModifiableMessage.modifyMessage:(Lscala/Function1;)Ljava/lang/Throwable;
       333: athrow
       334: aload         16
       336: athrow
       337: goto          340
       340: aload         14
       342: athrow
       343: areturn
      Exception table:
         from    to  target type
            55   267   270   Class java/lang/Throwable
      StackMapTable: number_of_entries = 20
        frame_type = 255 /* full_frame */
          offset_delta = 125
          locals = [ class org/scalatest/AppendedClues$Clueful, class java/lang/Object, top, top, class java/lang/Object, class java/lang/Object, class org/scalatest/Failed, class java/lang/Throwable, class java/lang/Throwable, class java/lang/String ]
          stack = [ class java/lang/String ]
        frame_type = 7 /* same */
        frame_type = 26 /* same */
        frame_type = 249 /* chop */
          offset_delta = 2
        frame_type = 249 /* chop */
          offset_delta = 2
        frame_type = 2 /* same */
        frame_type = 255 /* full_frame */
          offset_delta = 51
          locals = [ class org/scalatest/AppendedClues$Clueful, class java/lang/Object, top, top, class java/lang/Object, class java/lang/Object, top, top, top, top, class org/scalatest/Canceled, class org/scalatest/exceptions/TestCanceledException, class org/scalatest/exceptions/TestCanceledException, class java/lang/String ]
          stack = [ class java/lang/String ]
        frame_type = 7 /* same */
        frame_type = 21 /* same */
        frame_type = 249 /* chop */
          offset_delta = 2
        frame_type = 255 /* full_frame */
          offset_delta = 2
          locals = [ class org/scalatest/AppendedClues$Clueful, class java/lang/Object, top, top, class java/lang/Object, class java/lang/Object ]
          stack = []
        frame_type = 2 /* same */
        frame_type = 255 /* full_frame */
          offset_delta = 5
          locals = [ class org/scalatest/AppendedClues$Clueful, class java/lang/Object, top, class java/lang/Object, class java/lang/Object, class java/lang/Object ]
          stack = []
        frame_type = 255 /* full_frame */
          offset_delta = 3
          locals = [ class org/scalatest/AppendedClues$Clueful, class java/lang/Object ]
          stack = [ class java/lang/Throwable ]
        frame_type = 255 /* full_frame */
          offset_delta = 38
          locals = [ class org/scalatest/AppendedClues$Clueful, class java/lang/Object, top, top, top, top, top, top, top, top, top, top, top, top, class java/lang/Throwable, class java/lang/Throwable, class java/lang/Throwable, class java/lang/String ]
          stack = [ class java/lang/String ]
        frame_type = 7 /* same */
        frame_type = 16 /* same */
        frame_type = 249 /* chop */
          offset_delta = 2
        frame_type = 2 /* same */
        frame_type = 255 /* full_frame */
          offset_delta = 2
          locals = [ class org/scalatest/AppendedClues$Clueful, class java/lang/Object, top, class java/lang/Object, class java/lang/Object, class java/lang/Object ]
          stack = [ class java/lang/Object ]
      LineNumberTable:
        line 144: 0
        line 151: 55
        line 152: 66
        line 153: 70
        line 154: 133
        line 153: 160
        line 155: 169
        line 156: 229
        line 155: 251
        line 157: 260
        line 152: 266
        line 161: 272
        line 161: 276
        line 162: 288
        line 163: 317
        line 165: 334
        line 161: 337
        line 150: 340
      LocalVariableTable:
        Start  Length  Slot  Name   Signature
           92      74     7     e   Ljava/lang/Throwable;
          191      66    11     e   Lorg/scalatest/exceptions/TestCanceledException;
           66     201     4 outcome   Ljava/lang/Object;
            0     344     0  this   Lorg/scalatest/AppendedClues$Clueful;
            0     344     1  clue   Ljava/lang/Object;
    Signature: #27                          // (Ljava/lang/Object;)TT;
    MethodParameters:
      Name                           Flags
      clue                           final

  public org.scalatest.AppendedClues org$scalatest$AppendedClues$Clueful$$$outer();
    descriptor: ()Lorg/scalatest/AppendedClues;
    flags: (0x1001) ACC_PUBLIC, ACC_SYNTHETIC
    Code:
      stack=1, locals=1, args_size=1
         0: aload_0
         1: getfield      #156                // Field $outer:Lorg/scalatest/AppendedClues;
         4: areturn
      LineNumberTable:
        line 112: 0
      LocalVariableTable:
        Start  Length  Slot  Name   Signature
            0       5     0  this   Lorg/scalatest/AppendedClues$Clueful;

  private static final scala.Some append$1(scala.Option, java.lang.Object);
    descriptor: (Lscala/Option;Ljava/lang/Object;)Lscala/Some;
    flags: (0x001a) ACC_PRIVATE, ACC_STATIC, ACC_FINAL
    Code:
      stack=5, locals=6, args_size=2
         0: aload_0
         1: astore_3
         2: aload_3
         3: instanceof    #162                // class scala/Some
         6: ifeq          48
         9: aload_3
        10: checkcast     #162                // class scala/Some
        13: astore        4
        15: aload         4
        17: invokevirtual #165                // Method scala/Some.value:()Ljava/lang/Object;
        20: checkcast     #42                 // class java/lang/String
        23: astore        5
        25: new           #162                // class scala/Some
        28: dup
        29: getstatic     #170                // Field org/scalatest/AppendedClues$.MODULE$:Lorg/scalatest/AppendedClues$;
        32: aload         5
        34: aload_1
        35: invokevirtual #89                 // Method java/lang/Object.toString:()Ljava/lang/String;
        38: invokevirtual #174                // Method org/scalatest/AppendedClues$.appendClue:(Ljava/lang/String;Ljava/lang/String;)Ljava/lang/String;
        41: invokespecial #177                // Method scala/Some."<init>":(Ljava/lang/Object;)V
        44: astore_2
        45: goto          88
        48: goto          51
        51: getstatic     #182                // Field scala/None$.MODULE$:Lscala/None$;
        54: aload_3
        55: invokevirtual #95                 // Method java/lang/Object.equals:(Ljava/lang/Object;)Z
        58: ifeq          76
        61: new           #162                // class scala/Some
        64: dup
        65: aload_1
        66: invokevirtual #89                 // Method java/lang/Object.toString:()Ljava/lang/String;
        69: invokespecial #177                // Method scala/Some."<init>":(Ljava/lang/Object;)V
        72: astore_2
        73: goto          88
        76: goto          79
        79: new           #184                // class scala/MatchError
        82: dup
        83: aload_3
        84: invokespecial #185                // Method scala/MatchError."<init>":(Ljava/lang/Object;)V
        87: athrow
        88: aload_2
        89: areturn
      StackMapTable: number_of_entries = 5
        frame_type = 253 /* append */
          offset_delta = 48
          locals = [ top, class scala/Option ]
        frame_type = 2 /* same */
        frame_type = 24 /* same */
        frame_type = 2 /* same */
        frame_type = 255 /* full_frame */
          offset_delta = 8
          locals = [ class scala/Option, class java/lang/Object, class scala/Some, class scala/Option ]
          stack = []
      LineNumberTable:
        line 146: 0
        line 147: 2
        line 148: 51
        line 146: 79
      LocalVariableTable:
        Start  Length  Slot  Name   Signature
           25      23     5   msg   Ljava/lang/String;
            0      90     0 currentMessage   Lscala/Option;
            0      90     1 clue$1   Ljava/lang/Object;
    MethodParameters:
      Name                           Flags
      currentMessage                 final
      clue$1                         final

  public static final scala.Some $anonfun$withClue$1(java.lang.Object, scala.Option);
    descriptor: (Ljava/lang/Object;Lscala/Option;)Lscala/Some;
    flags: (0x1019) ACC_PUBLIC, ACC_STATIC, ACC_FINAL, ACC_SYNTHETIC
    Code:
      stack=2, locals=2, args_size=2
         0: aload_1
         1: aload_0
         2: invokestatic  #192                // Method append$1:(Lscala/Option;Ljava/lang/Object;)Lscala/Some;
         5: areturn
      LineNumberTable:
        line 154: 0
      LocalVariableTable:
        Start  Length  Slot  Name   Signature
            0       6     0 clue$1   Ljava/lang/Object;
            0       6     1 currentMessage   Lscala/Option;
    MethodParameters:
      Name                           Flags
      clue$1                         final
      currentMessage                 final

  public static final scala.Some $anonfun$withClue$2(java.lang.Object, scala.Option);
    descriptor: (Ljava/lang/Object;Lscala/Option;)Lscala/Some;
    flags: (0x1019) ACC_PUBLIC, ACC_STATIC, ACC_FINAL, ACC_SYNTHETIC
    Code:
      stack=2, locals=2, args_size=2
         0: aload_1
         1: aload_0
         2: invokestatic  #192                // Method append$1:(Lscala/Option;Ljava/lang/Object;)Lscala/Some;
         5: areturn
      LineNumberTable:
        line 156: 0
      LocalVariableTable:
        Start  Length  Slot  Name   Signature
            0       6     0 clue$1   Ljava/lang/Object;
            0       6     1 currentMessage   Lscala/Option;
    MethodParameters:
      Name                           Flags
      clue$1                         final
      currentMessage                 final

  public static final scala.Some $anonfun$withClue$3(java.lang.Object, scala.Option);
    descriptor: (Ljava/lang/Object;Lscala/Option;)Lscala/Some;
    flags: (0x1019) ACC_PUBLIC, ACC_STATIC, ACC_FINAL, ACC_SYNTHETIC
    Code:
      stack=2, locals=2, args_size=2
         0: aload_1
         1: aload_0
         2: invokestatic  #192                // Method append$1:(Lscala/Option;Ljava/lang/Object;)Lscala/Some;
         5: areturn
      LineNumberTable:
        line 163: 0
      LocalVariableTable:
        Start  Length  Slot  Name   Signature
            0       6     0 clue$1   Ljava/lang/Object;
            0       6     1 currentMessage   Lscala/Option;
    MethodParameters:
      Name                           Flags
      clue$1                         final
      currentMessage                 final

  public org.scalatest.AppendedClues$Clueful(scala.Function0<T>);
    descriptor: (Lorg/scalatest/AppendedClues;Lscala/Function0;)V
    flags: (0x0001) ACC_PUBLIC
    Code:
      stack=2, locals=3, args_size=3
         0: aload_0
         1: aload_2
         2: putfield      #71                 // Field fun:Lscala/Function0;
         5: aload_1
         6: ifnonnull     11
         9: aconst_null
        10: athrow
        11: aload_0
        12: aload_1
        13: putfield      #156                // Field $outer:Lorg/scalatest/AppendedClues;
        16: aload_0
        17: invokespecial #197                // Method java/lang/Object."<init>":()V
        20: return
      StackMapTable: number_of_entries = 1
        frame_type = 11 /* same */
      LineNumberTable:
        line 112: 0
        line 170: 16
        line 112: 20
      LocalVariableTable:
        Start  Length  Slot  Name   Signature
            0      21     0  this   Lorg/scalatest/AppendedClues$Clueful;
            0      21     1 $outer   Lorg/scalatest/AppendedClues;
            0      21     2   fun   Lscala/Function0;
    Signature: #194                         // (Lscala/Function0<TT;>;)V
    MethodParameters:
      Name                           Flags
      $outer                         final synthetic
      fun                            final

  private static java.lang.Object $deserializeLambda$(java.lang.invoke.SerializedLambda);
    descriptor: (Ljava/lang/invoke/SerializedLambda;)Ljava/lang/Object;
    flags: (0x100a) ACC_PRIVATE, ACC_STATIC, ACC_SYNTHETIC
    Code:
      stack=1, locals=1, args_size=1
         0: aload_0
         1: invokedynamic #209,  0            // InvokeDynamic #3:lambdaDeserialize:(Ljava/lang/invoke/SerializedLambda;)Ljava/lang/Object;
         6: areturn
}
InnerClasses:
  public static final #11= #8 of #10;     // Lookup=class java/lang/invoke/MethodHandles$Lookup of class java/lang/invoke/MethodHandles
  public static #16= #13 of #15;          // RequirementsHelper=class org/scalactic/Requirements$RequirementsHelper of class org/scalactic/Requirements
  public #19= #2 of #18;                  // Clueful=class org/scalatest/AppendedClues$Clueful of class org/scalatest/AppendedClues
Signature: #3                           // <T:Ljava/lang/Object;>Ljava/lang/Object;
SourceFile: "AppendedClues.scala"
BootstrapMethods:
  0: #112 REF_invokeStatic java/lang/invoke/LambdaMetafactory.altMetafactory:(Ljava/lang/invoke/MethodHandles$Lookup;Ljava/lang/String;Ljava/lang/invoke/MethodType;[Ljava/lang/Object;)Ljava/lang/invoke/CallSite;
    Method arguments:
      #96 (Ljava/lang/Object;)Ljava/lang/Object;
      #101 REF_invokeStatic org/scalatest/AppendedClues$Clueful.$anonfun$withClue$1:(Ljava/lang/Object;Lscala/Option;)Lscala/Some;
      #103 (Lscala/Option;)Lscala/Some;
      #104 5
      #105 1
      #103 (Lscala/Option;)Lscala/Some;
  1: #112 REF_invokeStatic java/lang/invoke/LambdaMetafactory.altMetafactory:(Ljava/lang/invoke/MethodHandles$Lookup;Ljava/lang/String;Ljava/lang/invoke/MethodType;[Ljava/lang/Object;)Ljava/lang/invoke/CallSite;
    Method arguments:
      #96 (Ljava/lang/Object;)Ljava/lang/Object;
      #131 REF_invokeStatic org/scalatest/AppendedClues$Clueful.$anonfun$withClue$2:(Ljava/lang/Object;Lscala/Option;)Lscala/Some;
      #103 (Lscala/Option;)Lscala/Some;
      #104 5
      #105 1
      #103 (Lscala/Option;)Lscala/Some;
  2: #112 REF_invokeStatic java/lang/invoke/LambdaMetafactory.altMetafactory:(Ljava/lang/invoke/MethodHandles$Lookup;Ljava/lang/String;Ljava/lang/invoke/MethodType;[Ljava/lang/Object;)Ljava/lang/invoke/CallSite;
    Method arguments:
      #96 (Ljava/lang/Object;)Ljava/lang/Object;
      #144 REF_invokeStatic org/scalatest/AppendedClues$Clueful.$anonfun$withClue$3:(Ljava/lang/Object;Lscala/Option;)Lscala/Some;
      #103 (Lscala/Option;)Lscala/Some;
      #104 5
      #105 1
      #103 (Lscala/Option;)Lscala/Some;
  3: #206 REF_invokeStatic scala/runtime/LambdaDeserialize.bootstrap:(Ljava/lang/invoke/MethodHandles$Lookup;Ljava/lang/String;Ljava/lang/invoke/MethodType;[Ljava/lang/invoke/MethodHandle;)Ljava/lang/invoke/CallSite;
    Method arguments:
      #101 REF_invokeStatic org/scalatest/AppendedClues$Clueful.$anonfun$withClue$1:(Ljava/lang/Object;Lscala/Option;)Lscala/Some;
      #131 REF_invokeStatic org/scalatest/AppendedClues$Clueful.$anonfun$withClue$2:(Ljava/lang/Object;Lscala/Option;)Lscala/Some;
      #144 REF_invokeStatic org/scalatest/AppendedClues$Clueful.$anonfun$withClue$3:(Ljava/lang/Object;Lscala/Option;)Lscala/Some;
  ScalaInlineInfo: length = 0x27 (unknown attribute)
   01 00 00 07 00 61 00 62 01 00 80 00 62 01 00 8D
   00 62 01 00 3E 00 C1 00 00 9D 00 9E 01 00 99 00
   9A 00 00 19 00 1A 00
  Scala: length = 0x0 (unknown attribute)

