Classfile /Users/mw/Projects/slang-braindump/.jar/jar8/assemble/slang-braindump/assemble/content/org/scalatest/BeforeAndAfterAllConfigMap.class
  Last modified May 29, 2022; size 6213 bytes
  SHA-256 checksum 82b417e7f9e2cbb6e44af268143d53b4383d9b2f6e9b83df83881da76e57091f
  Compiled from "BeforeAndAfterAllConfigMap.scala"
public interface org.scalatest.BeforeAndAfterAllConfigMap extends org.scalatest.SuiteMixin
  minor version: 0
  major version: 52
  flags: (0x0601) ACC_PUBLIC, ACC_INTERFACE, ACC_ABSTRACT
  this_class: #2                          // org/scalatest/BeforeAndAfterAllConfigMap
  super_class: #4                         // java/lang/Object
  interfaces: 1, fields: 0, methods: 13, attributes: 6
Constant pool:
    #1 = Utf8               org/scalatest/BeforeAndAfterAllConfigMap
    #2 = Class              #1            // org/scalatest/BeforeAndAfterAllConfigMap
    #3 = Utf8               java/lang/Object
    #4 = Class              #3            // java/lang/Object
    #5 = Utf8               org/scalatest/SuiteMixin
    #6 = Class              #5            // org/scalatest/SuiteMixin
    #7 = Utf8               BeforeAndAfterAllConfigMap.scala
    #8 = Utf8               Lscala/reflect/ScalaSignature;
    #9 = Utf8               bytes
   #10 = Utf8               \u0006\u0005I3\u0001b\u0002\u0005\u0011\u0002\u0007\u0005Qb\u0013\u0005\u00061\u0001!\t!\u0007\u0005\b;\u0001\u0011\r\u0011\"\u0001\u001f\u0011\u0015\u0011\u0003\u0001\"\u0005$\u0011\u0015I\u0003\u0001\"\u0005+\u0011\u0019a\u0003\u0001%C\u0001[!Ya\t\u0001I\u0001\u0004\u0003\u0005I\u0011B$K\u0005i\u0011UMZ8sK\u0006sG-\u00114uKJ\fE\u000e\\\"p]\u001aLw-T1q\u0015\tI!\"A\u0005tG\u0006d\u0017\r^3ti*\t1\"A\u0002pe\u001e\u001c\u0001aE\u0002\u0001\u001dQ\u0001\"a\u0004\n\u000e\u0003AQ\u0011!E\u0001\u0006g\u000e\fG.Y\u0005\u0003\'A\u0011a!\u00118z%\u00164\u0007CA\u000b\u0017\u001b\u0005A\u0011BA\f\t\u0005)\u0019V/\u001b;f\u001b&D\u0018N\\\u0001\u0007I%t\u0017\u000e\u001e\u0013\u0015\u0003i\u0001\"aD\u000e\n\u0005q\u0001\"\u0001B+oSR\f!\'\u001b8w_.,\')\u001a4pe\u0016\fE\u000e\\!oI\u00063G/\u001a:BY2,e/\u001a8JM:{G+Z:ug\u0006\u0013X-\u0012=qK\u000e$X\rZ\u000b\u0002?A\u0011q\u0002I\u0005\u0003CA\u0011qAQ8pY\u0016\fg.A\u0005cK\u001a|\'/Z!mYR\u0011!\u0004\n\u0005\u0006K\r\u0001\rAJ\u0001\nG>tg-[4NCB\u0004\"!F\u0014\n\u0005!B!!C\"p]\u001aLw-T1q\u0003!\tg\r^3s\u00032dGC\u0001\u000e,\u0011\u0015)C\u00011\u0001\'\u0003\r\u0011XO\u001c\u000b\u0004]E\n\u0005CA\u000b0\u0013\t\u0001\u0004B\u0001\u0004Ti\u0006$Xo\u001d\u0005\u0006e\u0015\u0001\raM\u0001\ti\u0016\u001cHOT1nKB\u0019q\u0002\u000e\u001c\n\u0005U\u0002\"AB(qi&|g\u000e\u0005\u00028}9\u0011\u0001\b\u0010\t\u0003sAi\u0011A\u000f\u0006\u0003w1\ta\u0001\u0010:p_Rt\u0014BA\u001f\u0011\u0003\u0019\u0001&/\u001a3fM&\u0011q\b\u0011\u0002\u0007\'R\u0014\u0018N\\4\u000b\u0005u\u0002\u0002\"\u0002\"\u0006\u0001\u0004\u0019\u0015\u0001B1sON\u0004\"!\u0006#\n\u0005\u0015C!\u0001B!sON\f\u0011b];qKJ$#/\u001e8\u0015\u00079B\u0015\nC\u00033\r\u0001\u00071\u0007C\u0003C\r\u0001\u00071)\u0003\u0002--I\u0019AJT(\u0007\t5\u0003\u0001a\u0013\u0002\ryI,g-\u001b8f[\u0016tGO\u0010\t\u0003+\u0001\u0001\"!\u0006)\n\u0005EC!!B*vSR,\u0007
   #11 = Utf8               java/lang/invoke/MethodHandles$Lookup
   #12 = Class              #11           // java/lang/invoke/MethodHandles$Lookup
   #13 = Utf8               java/lang/invoke/MethodHandles
   #14 = Class              #13           // java/lang/invoke/MethodHandles
   #15 = Utf8               Lookup
   #16 = Utf8               org$scalatest$BeforeAndAfterAllConfigMap$_setter_$invokeBeforeAllAndAfterAllEvenIfNoTestsAreExpected_$eq
   #17 = Utf8               (Z)V
   #18 = Utf8               x$1
   #19 = Utf8               org$scalatest$BeforeAndAfterAllConfigMap$$super$run
   #20 = Utf8               (Lscala/Option;Lorg/scalatest/Args;)Lorg/scalatest/Status;
   #21 = Utf8               testName
   #22 = Utf8               args
   #23 = Utf8               invokeBeforeAllAndAfterAllEvenIfNoTestsAreExpected
   #24 = Utf8               ()Z
   #25 = Utf8               beforeAll$
   #26 = Utf8               (Lorg/scalatest/BeforeAndAfterAllConfigMap;Lorg/scalatest/ConfigMap;)V
   #27 = Utf8               $this
   #28 = Utf8               configMap
   #29 = Utf8               beforeAll
   #30 = Utf8               (Lorg/scalatest/ConfigMap;)V
   #31 = NameAndType        #29:#30       // beforeAll:(Lorg/scalatest/ConfigMap;)V
   #32 = InterfaceMethodref #2.#31        // org/scalatest/BeforeAndAfterAllConfigMap.beforeAll:(Lorg/scalatest/ConfigMap;)V
   #33 = Utf8               Lorg/scalatest/BeforeAndAfterAllConfigMap;
   #34 = Utf8               Lorg/scalatest/ConfigMap;
   #35 = Utf8               this
   #36 = Utf8               afterAll$
   #37 = Utf8               afterAll
   #38 = NameAndType        #37:#30       // afterAll:(Lorg/scalatest/ConfigMap;)V
   #39 = InterfaceMethodref #2.#38        // org/scalatest/BeforeAndAfterAllConfigMap.afterAll:(Lorg/scalatest/ConfigMap;)V
   #40 = Utf8               run$
   #41 = Utf8               (Lorg/scalatest/BeforeAndAfterAllConfigMap;Lscala/Option;Lorg/scalatest/Args;)Lorg/scalatest/Status;
   #42 = Utf8               run
   #43 = NameAndType        #42:#20       // run:(Lscala/Option;Lorg/scalatest/Args;)Lorg/scalatest/Status;
   #44 = InterfaceMethodref #2.#43        // org/scalatest/BeforeAndAfterAllConfigMap.run:(Lscala/Option;Lorg/scalatest/Args;)Lorg/scalatest/Status;
   #45 = Utf8               Lscala/Option;
   #46 = Utf8               Lorg/scalatest/Args;
   #47 = Utf8               (Lscala/Option<Ljava/lang/String;>;Lorg/scalatest/Args;)Lorg/scalatest/Status;
   #48 = Utf8               java/lang/Exception
   #49 = Class              #48           // java/lang/Exception
   #50 = Utf8               liftedTree1$1
   #51 = Utf8               (Lorg/scalatest/Args;Lscala/Option;)Lscala/Tuple2;
   #52 = NameAndType        #50:#51       // liftedTree1$1:(Lorg/scalatest/Args;Lscala/Option;)Lscala/Tuple2;
   #53 = InterfaceMethodref #2.#52        // org/scalatest/BeforeAndAfterAllConfigMap.liftedTree1$1:(Lorg/scalatest/Args;Lscala/Option;)Lscala/Tuple2;
   #54 = Utf8               scala/Tuple2
   #55 = Class              #54           // scala/Tuple2
   #56 = Utf8               _1
   #57 = Utf8               ()Ljava/lang/Object;
   #58 = NameAndType        #56:#57       // _1:()Ljava/lang/Object;
   #59 = Methodref          #55.#58       // scala/Tuple2._1:()Ljava/lang/Object;
   #60 = Utf8               org/scalatest/Status
   #61 = Class              #60           // org/scalatest/Status
   #62 = Utf8               _2
   #63 = NameAndType        #62:#57       // _2:()Ljava/lang/Object;
   #64 = Methodref          #55.#63       // scala/Tuple2._2:()Ljava/lang/Object;
   #65 = Utf8               scala/Option
   #66 = Class              #65           // scala/Option
   #67 = Utf8               <init>
   #68 = Utf8               (Ljava/lang/Object;Ljava/lang/Object;)V
   #69 = NameAndType        #67:#68       // "<init>":(Ljava/lang/Object;Ljava/lang/Object;)V
   #70 = Methodref          #55.#69       // scala/Tuple2."<init>":(Ljava/lang/Object;Ljava/lang/Object;)V
   #71 = Utf8               scala/MatchError
   #72 = Class              #71           // scala/MatchError
   #73 = Utf8               (Ljava/lang/Object;)V
   #74 = NameAndType        #67:#73       // "<init>":(Ljava/lang/Object;)V
   #75 = Methodref          #72.#74       // scala/MatchError."<init>":(Ljava/lang/Object;)V
   #76 = Utf8               org/scalatest/Args
   #77 = Class              #76           // org/scalatest/Args
   #78 = Utf8               runTestInNewInstance
   #79 = NameAndType        #78:#24       // runTestInNewInstance:()Z
   #80 = Methodref          #77.#79       // org/scalatest/Args.runTestInNewInstance:()Z
   #81 = Utf8               org/scalatest/Suite
   #82 = Class              #81           // org/scalatest/Suite
   #83 = Utf8               filter
   #84 = Utf8               ()Lorg/scalatest/Filter;
   #85 = NameAndType        #83:#84       // filter:()Lorg/scalatest/Filter;
   #86 = Methodref          #77.#85       // org/scalatest/Args.filter:()Lorg/scalatest/Filter;
   #87 = Utf8               expectedTestCount
   #88 = Utf8               (Lorg/scalatest/Filter;)I
   #89 = NameAndType        #87:#88       // expectedTestCount:(Lorg/scalatest/Filter;)I
   #90 = InterfaceMethodref #82.#89       // org/scalatest/Suite.expectedTestCount:(Lorg/scalatest/Filter;)I
   #91 = NameAndType        #23:#24       // invokeBeforeAllAndAfterAllEvenIfNoTestsAreExpected:()Z
   #92 = InterfaceMethodref #2.#91        // org/scalatest/BeforeAndAfterAllConfigMap.invokeBeforeAllAndAfterAllEvenIfNoTestsAreExpected:()Z
   #93 = Utf8               ()V
   #94 = MethodType         #93           //  ()V
   #95 = Utf8               $anonfun$run$1
   #96 = Utf8               (Lorg/scalatest/BeforeAndAfterAllConfigMap;Lorg/scalatest/Args;Lscala/Option;)V
   #97 = NameAndType        #95:#96       // $anonfun$run$1:(Lorg/scalatest/BeforeAndAfterAllConfigMap;Lorg/scalatest/Args;Lscala/Option;)V
   #98 = InterfaceMethodref #2.#97        // org/scalatest/BeforeAndAfterAllConfigMap.$anonfun$run$1:(Lorg/scalatest/BeforeAndAfterAllConfigMap;Lorg/scalatest/Args;Lscala/Option;)V
   #99 = MethodHandle       6:#98         // REF_invokeStatic org/scalatest/BeforeAndAfterAllConfigMap.$anonfun$run$1:(Lorg/scalatest/BeforeAndAfterAllConfigMap;Lorg/scalatest/Args;Lscala/Option;)V
  #100 = Integer            1
  #101 = Utf8               java/lang/invoke/LambdaMetafactory
  #102 = Class              #101          // java/lang/invoke/LambdaMetafactory
  #103 = Utf8               altMetafactory
  #104 = Utf8               (Ljava/lang/invoke/MethodHandles$Lookup;Ljava/lang/String;Ljava/lang/invoke/MethodType;[Ljava/lang/Object;)Ljava/lang/invoke/CallSite;
  #105 = NameAndType        #103:#104     // altMetafactory:(Ljava/lang/invoke/MethodHandles$Lookup;Ljava/lang/String;Ljava/lang/invoke/MethodType;[Ljava/lang/Object;)Ljava/lang/invoke/CallSite;
  #106 = Methodref          #102.#105     // java/lang/invoke/LambdaMetafactory.altMetafactory:(Ljava/lang/invoke/MethodHandles$Lookup;Ljava/lang/String;Ljava/lang/invoke/MethodType;[Ljava/lang/Object;)Ljava/lang/invoke/CallSite;
  #107 = MethodHandle       6:#106        // REF_invokeStatic java/lang/invoke/LambdaMetafactory.altMetafactory:(Ljava/lang/invoke/MethodHandles$Lookup;Ljava/lang/String;Ljava/lang/invoke/MethodType;[Ljava/lang/Object;)Ljava/lang/invoke/CallSite;
  #108 = Utf8               apply$mcV$sp
  #109 = Utf8               (Lorg/scalatest/BeforeAndAfterAllConfigMap;Lorg/scalatest/Args;Lscala/Option;)Lscala/runtime/java8/JFunction0$mcV$sp;
  #110 = NameAndType        #108:#109     // apply$mcV$sp:(Lorg/scalatest/BeforeAndAfterAllConfigMap;Lorg/scalatest/Args;Lscala/Option;)Lscala/runtime/java8/JFunction0$mcV$sp;
  #111 = InvokeDynamic      #0:#110       // #0:apply$mcV$sp:(Lorg/scalatest/BeforeAndAfterAllConfigMap;Lorg/scalatest/Args;Lscala/Option;)Lscala/runtime/java8/JFunction0$mcV$sp;
  #112 = Utf8               withAfterEffect
  #113 = Utf8               (Lscala/Function0;)Lorg/scalatest/Status;
  #114 = NameAndType        #112:#113     // withAfterEffect:(Lscala/Function0;)Lorg/scalatest/Status;
  #115 = InterfaceMethodref #61.#114      // org/scalatest/Status.withAfterEffect:(Lscala/Function0;)Lorg/scalatest/Status;
  #116 = Utf8               scala/Some
  #117 = Class              #116          // scala/Some
  #118 = Utf8               value
  #119 = NameAndType        #118:#57      // value:()Ljava/lang/Object;
  #120 = Methodref          #117.#119     // scala/Some.value:()Ljava/lang/Object;
  #121 = Utf8               scala/None$
  #122 = Class              #121          // scala/None$
  #123 = Utf8               MODULE$
  #124 = Utf8               Lscala/None$;
  #125 = NameAndType        #123:#124     // MODULE$:Lscala/None$;
  #126 = Fieldref           #122.#125     // scala/None$.MODULE$:Lscala/None$;
  #127 = Utf8               equals
  #128 = Utf8               (Ljava/lang/Object;)Z
  #129 = NameAndType        #127:#128     // equals:(Ljava/lang/Object;)Z
  #130 = Methodref          #4.#129       // java/lang/Object.equals:(Ljava/lang/Object;)Z
  #131 = Utf8               scala/runtime/BoxedUnit
  #132 = Class              #131          // scala/runtime/BoxedUnit
  #133 = Utf8               UNIT
  #134 = Utf8               Lscala/runtime/BoxedUnit;
  #135 = NameAndType        #133:#134     // UNIT:Lscala/runtime/BoxedUnit;
  #136 = Fieldref           #132.#135     // scala/runtime/BoxedUnit.UNIT:Lscala/runtime/BoxedUnit;
  #137 = Utf8               runStatus
  #138 = Utf8               Lorg/scalatest/Status;
  #139 = Utf8               thrownException
  #140 = Utf8               e
  #141 = Utf8               Ljava/lang/Exception;
  #142 = Utf8               statusToReturn
  #143 = Utf8               earlierException
  #144 = Utf8               laterException
  #145 = Utf8               args$1
  #146 = Utf8               testName$1
  #147 = Utf8               ()Lorg/scalatest/ConfigMap;
  #148 = NameAndType        #28:#147      // configMap:()Lorg/scalatest/ConfigMap;
  #149 = Methodref          #77.#148      // org/scalatest/Args.configMap:()Lorg/scalatest/ConfigMap;
  #150 = NameAndType        #19:#20       // org$scalatest$BeforeAndAfterAllConfigMap$$super$run:(Lscala/Option;Lorg/scalatest/Args;)Lorg/scalatest/Status;
  #151 = InterfaceMethodref #2.#150       // org/scalatest/BeforeAndAfterAllConfigMap.org$scalatest$BeforeAndAfterAllConfigMap$$super$run:(Lscala/Option;Lorg/scalatest/Args;)Lorg/scalatest/Status;
  #152 = Utf8               org/scalatest/FailedStatus$
  #153 = Class              #152          // org/scalatest/FailedStatus$
  #154 = Utf8               Lorg/scalatest/FailedStatus$;
  #155 = NameAndType        #123:#154     // MODULE$:Lorg/scalatest/FailedStatus$;
  #156 = Fieldref           #153.#155     // org/scalatest/FailedStatus$.MODULE$:Lorg/scalatest/FailedStatus$;
  #157 = Methodref          #117.#74      // scala/Some."<init>":(Ljava/lang/Object;)V
  #158 = Utf8               thrownException$1
  #159 = Utf8               java/lang/Throwable
  #160 = Class              #159          // java/lang/Throwable
  #161 = Utf8               org/scalatest/Suite$
  #162 = Class              #161          // org/scalatest/Suite$
  #163 = Utf8               Lorg/scalatest/Suite$;
  #164 = NameAndType        #123:#163     // MODULE$:Lorg/scalatest/Suite$;
  #165 = Fieldref           #162.#164     // org/scalatest/Suite$.MODULE$:Lorg/scalatest/Suite$;
  #166 = Utf8               anExceptionThatShouldCauseAnAbort
  #167 = Utf8               (Ljava/lang/Throwable;)Z
  #168 = NameAndType        #166:#167     // anExceptionThatShouldCauseAnAbort:(Ljava/lang/Throwable;)Z
  #169 = Methodref          #162.#168     // org/scalatest/Suite$.anExceptionThatShouldCauseAnAbort:(Ljava/lang/Throwable;)Z
  #170 = Utf8               isDefined
  #171 = NameAndType        #170:#24      // isDefined:()Z
  #172 = Methodref          #66.#171      // scala/Option.isDefined:()Z
  #173 = Utf8               $init$
  #174 = Utf8               (Lorg/scalatest/BeforeAndAfterAllConfigMap;)V
  #175 = NameAndType        #16:#17       // org$scalatest$BeforeAndAfterAllConfigMap$_setter_$invokeBeforeAllAndAfterAllEvenIfNoTestsAreExpected_$eq:(Z)V
  #176 = InterfaceMethodref #2.#175       // org/scalatest/BeforeAndAfterAllConfigMap.org$scalatest$BeforeAndAfterAllConfigMap$_setter_$invokeBeforeAllAndAfterAllEvenIfNoTestsAreExpected_$eq:(Z)V
  #177 = Utf8               $deserializeLambda$
  #178 = Utf8               (Ljava/lang/invoke/SerializedLambda;)Ljava/lang/Object;
  #179 = Utf8               scala/runtime/LambdaDeserialize
  #180 = Class              #179          // scala/runtime/LambdaDeserialize
  #181 = Utf8               bootstrap
  #182 = Utf8               (Ljava/lang/invoke/MethodHandles$Lookup;Ljava/lang/String;Ljava/lang/invoke/MethodType;[Ljava/lang/invoke/MethodHandle;)Ljava/lang/invoke/CallSite;
  #183 = NameAndType        #181:#182     // bootstrap:(Ljava/lang/invoke/MethodHandles$Lookup;Ljava/lang/String;Ljava/lang/invoke/MethodType;[Ljava/lang/invoke/MethodHandle;)Ljava/lang/invoke/CallSite;
  #184 = Methodref          #180.#183     // scala/runtime/LambdaDeserialize.bootstrap:(Ljava/lang/invoke/MethodHandles$Lookup;Ljava/lang/String;Ljava/lang/invoke/MethodType;[Ljava/lang/invoke/MethodHandle;)Ljava/lang/invoke/CallSite;
  #185 = MethodHandle       6:#184        // REF_invokeStatic scala/runtime/LambdaDeserialize.bootstrap:(Ljava/lang/invoke/MethodHandles$Lookup;Ljava/lang/String;Ljava/lang/invoke/MethodType;[Ljava/lang/invoke/MethodHandle;)Ljava/lang/invoke/CallSite;
  #186 = Utf8               lambdaDeserialize
  #187 = NameAndType        #186:#178     // lambdaDeserialize:(Ljava/lang/invoke/SerializedLambda;)Ljava/lang/Object;
  #188 = InvokeDynamic      #1:#187       // #1:lambdaDeserialize:(Ljava/lang/invoke/SerializedLambda;)Ljava/lang/Object;
  #189 = Utf8               MethodParameters
  #190 = Utf8               Code
  #191 = Utf8               LineNumberTable
  #192 = Utf8               LocalVariableTable
  #193 = Utf8               StackMapTable
  #194 = Utf8               Signature
  #195 = Utf8               InnerClasses
  #196 = Utf8               SourceFile
  #197 = Utf8               RuntimeVisibleAnnotations
  #198 = Utf8               BootstrapMethods
  #199 = Utf8               ScalaInlineInfo
  #200 = Utf8               ScalaSig
{
  public abstract void org$scalatest$BeforeAndAfterAllConfigMap$_setter_$invokeBeforeAllAndAfterAllEvenIfNoTestsAreExpected_$eq(boolean);
    descriptor: (Z)V
    flags: (0x0401) ACC_PUBLIC, ACC_ABSTRACT
    MethodParameters:
      Name                           Flags
      x$1                            final

  public abstract org.scalatest.Status org$scalatest$BeforeAndAfterAllConfigMap$$super$run(scala.Option, org.scalatest.Args);
    descriptor: (Lscala/Option;Lorg/scalatest/Args;)Lorg/scalatest/Status;
    flags: (0x1401) ACC_PUBLIC, ACC_ABSTRACT, ACC_SYNTHETIC
    MethodParameters:
      Name                           Flags
      testName                       final
      args                           final

  public abstract boolean invokeBeforeAllAndAfterAllEvenIfNoTestsAreExpected();
    descriptor: ()Z
    flags: (0x0401) ACC_PUBLIC, ACC_ABSTRACT

  public static void beforeAll$(org.scalatest.BeforeAndAfterAllConfigMap, org.scalatest.ConfigMap);
    descriptor: (Lorg/scalatest/BeforeAndAfterAllConfigMap;Lorg/scalatest/ConfigMap;)V
    flags: (0x1009) ACC_PUBLIC, ACC_STATIC, ACC_SYNTHETIC
    Code:
      stack=2, locals=2, args_size=2
         0: aload_0
         1: aload_1
         2: invokespecial #32                 // InterfaceMethod beforeAll:(Lorg/scalatest/ConfigMap;)V
         5: return
      LineNumberTable:
        line 189: 0
      LocalVariableTable:
        Start  Length  Slot  Name   Signature
            0       6     0 $this   Lorg/scalatest/BeforeAndAfterAllConfigMap;
            0       6     1 configMap   Lorg/scalatest/ConfigMap;
    MethodParameters:
      Name                           Flags
      $this                          final synthetic
      configMap                      final

  public default void beforeAll(org.scalatest.ConfigMap);
    descriptor: (Lorg/scalatest/ConfigMap;)V
    flags: (0x0001) ACC_PUBLIC
    Code:
      stack=0, locals=2, args_size=2
         0: return
      LineNumberTable:
        line 189: 0
      LocalVariableTable:
        Start  Length  Slot  Name   Signature
            0       1     0  this   Lorg/scalatest/BeforeAndAfterAllConfigMap;
            0       1     1 configMap   Lorg/scalatest/ConfigMap;
    MethodParameters:
      Name                           Flags
      configMap                      final

  public static void afterAll$(org.scalatest.BeforeAndAfterAllConfigMap, org.scalatest.ConfigMap);
    descriptor: (Lorg/scalatest/BeforeAndAfterAllConfigMap;Lorg/scalatest/ConfigMap;)V
    flags: (0x1009) ACC_PUBLIC, ACC_STATIC, ACC_SYNTHETIC
    Code:
      stack=2, locals=2, args_size=2
         0: aload_0
         1: aload_1
         2: invokespecial #39                 // InterfaceMethod afterAll:(Lorg/scalatest/ConfigMap;)V
         5: return
      LineNumberTable:
        line 204: 0
      LocalVariableTable:
        Start  Length  Slot  Name   Signature
            0       6     0 $this   Lorg/scalatest/BeforeAndAfterAllConfigMap;
            0       6     1 configMap   Lorg/scalatest/ConfigMap;
    MethodParameters:
      Name                           Flags
      $this                          final synthetic
      configMap                      final

  public default void afterAll(org.scalatest.ConfigMap);
    descriptor: (Lorg/scalatest/ConfigMap;)V
    flags: (0x0001) ACC_PUBLIC
    Code:
      stack=0, locals=2, args_size=2
         0: return
      LineNumberTable:
        line 204: 0
      LocalVariableTable:
        Start  Length  Slot  Name   Signature
            0       1     0  this   Lorg/scalatest/BeforeAndAfterAllConfigMap;
            0       1     1 configMap   Lorg/scalatest/ConfigMap;
    MethodParameters:
      Name                           Flags
      configMap                      final

  public static org.scalatest.Status run$(org.scalatest.BeforeAndAfterAllConfigMap, scala.Option, org.scalatest.Args);
    descriptor: (Lorg/scalatest/BeforeAndAfterAllConfigMap;Lscala/Option;Lorg/scalatest/Args;)Lorg/scalatest/Status;
    flags: (0x1009) ACC_PUBLIC, ACC_STATIC, ACC_SYNTHETIC
    Code:
      stack=3, locals=3, args_size=3
         0: aload_0
         1: aload_1
         2: aload_2
         3: invokespecial #44                 // InterfaceMethod run:(Lscala/Option;Lorg/scalatest/Args;)Lorg/scalatest/Status;
         6: areturn
      LineNumberTable:
        line 242: 0
      LocalVariableTable:
        Start  Length  Slot  Name   Signature
            0       7     0 $this   Lorg/scalatest/BeforeAndAfterAllConfigMap;
            0       7     1 testName   Lscala/Option;
            0       7     2  args   Lorg/scalatest/Args;
    MethodParameters:
      Name                           Flags
      $this                          final synthetic
      testName                       final
      args                           final

  public default org.scalatest.Status run(scala.Option<java.lang.String>, org.scalatest.Args);
    descriptor: (Lscala/Option;Lorg/scalatest/Args;)Lorg/scalatest/Status;
    flags: (0x0001) ACC_PUBLIC
    Code:
      stack=4, locals=20, args_size=3
         0: aload_0
         1: aload_2
         2: aload_1
         3: invokespecial #53                 // InterfaceMethod liftedTree1$1:(Lorg/scalatest/Args;Lscala/Option;)Lscala/Tuple2;
         6: astore        7
         8: aload         7
        10: ifnull        49
        13: aload         7
        15: invokevirtual #59                 // Method scala/Tuple2._1:()Ljava/lang/Object;
        18: checkcast     #61                 // class org/scalatest/Status
        21: astore        8
        23: aload         7
        25: invokevirtual #64                 // Method scala/Tuple2._2:()Ljava/lang/Object;
        28: checkcast     #66                 // class scala/Option
        31: astore        9
        33: new           #55                 // class scala/Tuple2
        36: dup
        37: aload         8
        39: aload         9
        41: invokespecial #70                 // Method scala/Tuple2."<init>":(Ljava/lang/Object;Ljava/lang/Object;)V
        44: astore        5
        46: goto          62
        49: goto          52
        52: new           #72                 // class scala/MatchError
        55: dup
        56: aload         7
        58: invokespecial #75                 // Method scala/MatchError."<init>":(Ljava/lang/Object;)V
        61: athrow
        62: aload         5
        64: astore        6
        66: aload         6
        68: invokevirtual #59                 // Method scala/Tuple2._1:()Ljava/lang/Object;
        71: checkcast     #61                 // class org/scalatest/Status
        74: astore        10
        76: aload         6
        78: invokevirtual #64                 // Method scala/Tuple2._2:()Ljava/lang/Object;
        81: checkcast     #66                 // class scala/Option
        84: astore        11
        86: aload_2
        87: invokevirtual #80                 // Method org/scalatest/Args.runTestInNewInstance:()Z
        90: ifne          138
        93: aload_0
        94: checkcast     #82                 // class org/scalatest/Suite
        97: aload_2
        98: invokevirtual #86                 // Method org/scalatest/Args.filter:()Lorg/scalatest/Filter;
       101: invokeinterface #90,  2           // InterfaceMethod org/scalatest/Suite.expectedTestCount:(Lorg/scalatest/Filter;)I
       106: iconst_0
       107: if_icmpgt     119
       110: aload_0
       111: invokeinterface #92,  1           // InterfaceMethod invokeBeforeAllAndAfterAllEvenIfNoTestsAreExpected:()Z
       116: ifeq          138
       119: aload         10
       121: aload_0
       122: aload_2
       123: aload         11
       125: invokedynamic #111,  0            // InvokeDynamic #0:apply$mcV$sp:(Lorg/scalatest/BeforeAndAfterAllConfigMap;Lorg/scalatest/Args;Lscala/Option;)Lscala/runtime/java8/JFunction0$mcV$sp;
       130: invokeinterface #115,  2          // InterfaceMethod org/scalatest/Status.withAfterEffect:(Lscala/Function0;)Lorg/scalatest/Status;
       135: goto          140
       138: aload         10
       140: astore        12
       142: aload         11
       144: astore        13
       146: aload         13
       148: instanceof    #117                // class scala/Some
       151: ifeq          174
       154: aload         13
       156: checkcast     #117                // class scala/Some
       159: astore        14
       161: aload         14
       163: invokevirtual #120                // Method scala/Some.value:()Ljava/lang/Object;
       166: checkcast     #49                 // class java/lang/Exception
       169: astore        15
       171: aload         15
       173: athrow
       174: goto          177
       177: getstatic     #126                // Field scala/None$.MODULE$:Lscala/None$;
       180: aload         13
       182: invokevirtual #130                // Method java/lang/Object.equals:(Ljava/lang/Object;)Z
       185: ifeq          196
       188: getstatic     #136                // Field scala/runtime/BoxedUnit.UNIT:Lscala/runtime/BoxedUnit;
       191: astore        4
       193: goto          209
       196: goto          199
       199: new           #72                 // class scala/MatchError
       202: dup
       203: aload         13
       205: invokespecial #75                 // Method scala/MatchError."<init>":(Ljava/lang/Object;)V
       208: athrow
       209: aload         12
       211: goto          278
       214: astore        16
       216: aload         11
       218: astore        17
       220: aload         17
       222: instanceof    #117                // class scala/Some
       225: ifeq          248
       228: aload         17
       230: checkcast     #117                // class scala/Some
       233: astore        18
       235: aload         18
       237: invokevirtual #120                // Method scala/Some.value:()Ljava/lang/Object;
       240: checkcast     #49                 // class java/lang/Exception
       243: astore        19
       245: aload         19
       247: athrow
       248: goto          251
       251: getstatic     #126                // Field scala/None$.MODULE$:Lscala/None$;
       254: aload         17
       256: invokevirtual #130                // Method java/lang/Object.equals:(Ljava/lang/Object;)Z
       259: ifeq          265
       262: aload         16
       264: athrow
       265: goto          268
       268: new           #72                 // class scala/MatchError
       271: dup
       272: aload         17
       274: invokespecial #75                 // Method scala/MatchError."<init>":(Ljava/lang/Object;)V
       277: athrow
       278: areturn
      Exception table:
         from    to  target type
            86   211   214   Class java/lang/Exception
      StackMapTable: number_of_entries = 17
        frame_type = 255 /* full_frame */
          offset_delta = 49
          locals = [ class org/scalatest/BeforeAndAfterAllConfigMap, class scala/Option, class org/scalatest/Args, top, top, top, top, class scala/Tuple2 ]
          stack = []
        frame_type = 2 /* same */
        frame_type = 255 /* full_frame */
          offset_delta = 9
          locals = [ class org/scalatest/BeforeAndAfterAllConfigMap, class scala/Option, class org/scalatest/Args, top, top, class scala/Tuple2, top, class scala/Tuple2, class org/scalatest/Status, class scala/Option ]
          stack = []
        frame_type = 255 /* full_frame */
          offset_delta = 56
          locals = [ class org/scalatest/BeforeAndAfterAllConfigMap, class scala/Option, class org/scalatest/Args, top, top, class scala/Tuple2, class scala/Tuple2, class scala/Tuple2, class org/scalatest/Status, class scala/Option, class org/scalatest/Status, class scala/Option ]
          stack = []
        frame_type = 18 /* same */
        frame_type = 65 /* same_locals_1_stack_item */
          stack = [ class org/scalatest/Status ]
        frame_type = 253 /* append */
          offset_delta = 33
          locals = [ class org/scalatest/Status, class scala/Option ]
        frame_type = 2 /* same */
        frame_type = 18 /* same */
        frame_type = 2 /* same */
        frame_type = 255 /* full_frame */
          offset_delta = 9
          locals = [ class org/scalatest/BeforeAndAfterAllConfigMap, class scala/Option, class org/scalatest/Args, top, class scala/runtime/BoxedUnit, class scala/Tuple2, class scala/Tuple2, class scala/Tuple2, class org/scalatest/Status, class scala/Option, class org/scalatest/Status, class scala/Option, class org/scalatest/Status, class scala/Option ]
          stack = []
        frame_type = 255 /* full_frame */
          offset_delta = 4
          locals = [ class org/scalatest/BeforeAndAfterAllConfigMap, class scala/Option, class org/scalatest/Args, top, top, class scala/Tuple2, class scala/Tuple2, class scala/Tuple2, class org/scalatest/Status, class scala/Option, class org/scalatest/Status, class scala/Option ]
          stack = [ class java/lang/Exception ]
        frame_type = 255 /* full_frame */
          offset_delta = 33
          locals = [ class org/scalatest/BeforeAndAfterAllConfigMap, class scala/Option, class org/scalatest/Args, top, top, class scala/Tuple2, class scala/Tuple2, class scala/Tuple2, class org/scalatest/Status, class scala/Option, class org/scalatest/Status, class scala/Option, top, top, top, top, class java/lang/Exception, class scala/Option ]
          stack = []
        frame_type = 2 /* same */
        frame_type = 13 /* same */
        frame_type = 2 /* same */
        frame_type = 255 /* full_frame */
          offset_delta = 9
          locals = [ class org/scalatest/BeforeAndAfterAllConfigMap, class scala/Option, class org/scalatest/Args, top, class scala/runtime/BoxedUnit, class scala/Tuple2, class scala/Tuple2, class scala/Tuple2, class org/scalatest/Status, class scala/Option, class org/scalatest/Status, class scala/Option, class org/scalatest/Status, class scala/Option ]
          stack = [ class org/scalatest/Status ]
      LineNumberTable:
        line 245: 0
        line 244: 8
        line 245: 52
        line 244: 66
        line 256: 86
        line 258: 119
        line 259: 121
        line 268: 138
        line 269: 142
        line 270: 146
        line 271: 177
        line 269: 199
        line 273: 209
        line 277: 216
        line 278: 220
        line 279: 251
        line 277: 268
      LocalVariableTable:
        Start  Length  Slot  Name   Signature
           23      26     8 runStatus   Lorg/scalatest/Status;
           33      16     9 thrownException   Lscala/Option;
          171       3    15     e   Ljava/lang/Exception;
          142      69    12 statusToReturn   Lorg/scalatest/Status;
          245       3    19 earlierException   Ljava/lang/Exception;
          214      64    16 laterException   Ljava/lang/Exception;
           76     202    10 runStatus   Lorg/scalatest/Status;
           86     192    11 thrownException   Lscala/Option;
            0     279     0  this   Lorg/scalatest/BeforeAndAfterAllConfigMap;
            0     279     1 testName   Lscala/Option;
            0     279     2  args   Lorg/scalatest/Args;
    Signature: #47                          // (Lscala/Option<Ljava/lang/String;>;Lorg/scalatest/Args;)Lorg/scalatest/Status;
    MethodParameters:
      Name                           Flags
      testName                       final
      args                           final

  private scala.Tuple2 liftedTree1$1(org.scalatest.Args, scala.Option);
    descriptor: (Lorg/scalatest/Args;Lscala/Option;)Lscala/Tuple2;
    flags: (0x1002) ACC_PRIVATE, ACC_SYNTHETIC
    Code:
      stack=6, locals=4, args_size=3
         0: aload_1
         1: invokevirtual #80                 // Method org/scalatest/Args.runTestInNewInstance:()Z
         4: ifne          46
         7: aload_0
         8: checkcast     #82                 // class org/scalatest/Suite
        11: aload_1
        12: invokevirtual #86                 // Method org/scalatest/Args.filter:()Lorg/scalatest/Filter;
        15: invokeinterface #90,  2           // InterfaceMethod org/scalatest/Suite.expectedTestCount:(Lorg/scalatest/Filter;)I
        20: iconst_0
        21: if_icmpgt     33
        24: aload_0
        25: invokeinterface #92,  1           // InterfaceMethod invokeBeforeAllAndAfterAllEvenIfNoTestsAreExpected:()Z
        30: ifeq          46
        33: aload_0
        34: aload_1
        35: invokevirtual #149                // Method org/scalatest/Args.configMap:()Lorg/scalatest/ConfigMap;
        38: invokeinterface #32,  2           // InterfaceMethod beforeAll:(Lorg/scalatest/ConfigMap;)V
        43: goto          46
        46: new           #55                 // class scala/Tuple2
        49: dup
        50: aload_0
        51: aload_2
        52: aload_1
        53: invokeinterface #151,  3          // InterfaceMethod org$scalatest$BeforeAndAfterAllConfigMap$$super$run:(Lscala/Option;Lorg/scalatest/Args;)Lorg/scalatest/Status;
        58: getstatic     #126                // Field scala/None$.MODULE$:Lscala/None$;
        61: invokespecial #70                 // Method scala/Tuple2."<init>":(Ljava/lang/Object;Ljava/lang/Object;)V
        64: goto          89
        67: astore_3
        68: new           #55                 // class scala/Tuple2
        71: dup
        72: getstatic     #156                // Field org/scalatest/FailedStatus$.MODULE$:Lorg/scalatest/FailedStatus$;
        75: new           #117                // class scala/Some
        78: dup
        79: aload_3
        80: invokespecial #157                // Method scala/Some."<init>":(Ljava/lang/Object;)V
        83: invokespecial #70                 // Method scala/Tuple2."<init>":(Ljava/lang/Object;Ljava/lang/Object;)V
        86: goto          89
        89: areturn
      Exception table:
         from    to  target type
             0    64    67   Class java/lang/Exception
      StackMapTable: number_of_entries = 4
        frame_type = 33 /* same */
        frame_type = 12 /* same */
        frame_type = 84 /* same_locals_1_stack_item */
          stack = [ class java/lang/Exception ]
        frame_type = 85 /* same_locals_1_stack_item */
          stack = [ class scala/Tuple2 ]
      LineNumberTable:
        line 246: 0
        line 247: 33
        line 248: 46
        line 251: 68
      LocalVariableTable:
        Start  Length  Slot  Name   Signature
           67      19     3     e   Ljava/lang/Exception;
            0      90     0  this   Lorg/scalatest/BeforeAndAfterAllConfigMap;
            0      90     1 args$1   Lorg/scalatest/Args;
            0      90     2 testName$1   Lscala/Option;
    MethodParameters:
      Name                           Flags
      args$1                         final
      testName$1                     final

  public static void $anonfun$run$1(org.scalatest.BeforeAndAfterAllConfigMap, org.scalatest.Args, scala.Option);
    descriptor: (Lorg/scalatest/BeforeAndAfterAllConfigMap;Lorg/scalatest/Args;Lscala/Option;)V
    flags: (0x1009) ACC_PUBLIC, ACC_STATIC, ACC_SYNTHETIC
    Code:
      stack=2, locals=7, args_size=3
         0: aload_0
         1: aload_1
         2: invokevirtual #149                // Method org/scalatest/Args.configMap:()Lorg/scalatest/ConfigMap;
         5: invokeinterface #39,  2           // InterfaceMethod afterAll:(Lorg/scalatest/ConfigMap;)V
        10: goto          71
        13: astore        4
        15: aload         4
        17: astore        5
        19: aload         5
        21: instanceof    #49                 // class java/lang/Exception
        24: ifeq          62
        27: aload         5
        29: checkcast     #49                 // class java/lang/Exception
        32: astore        6
        34: getstatic     #165                // Field org/scalatest/Suite$.MODULE$:Lorg/scalatest/Suite$;
        37: aload         6
        39: invokevirtual #169                // Method org/scalatest/Suite$.anExceptionThatShouldCauseAnAbort:(Ljava/lang/Throwable;)Z
        42: ifne          59
        45: aload_2
        46: invokevirtual #172                // Method scala/Option.isDefined:()Z
        49: ifeq          59
        52: getstatic     #136                // Field scala/runtime/BoxedUnit.UNIT:Lscala/runtime/BoxedUnit;
        55: astore_3
        56: goto          68
        59: goto          65
        62: goto          65
        65: aload         4
        67: athrow
        68: goto          71
        71: return
      Exception table:
         from    to  target type
             0    10    13   Class java/lang/Throwable
      StackMapTable: number_of_entries = 6
        frame_type = 77 /* same_locals_1_stack_item */
          stack = [ class java/lang/Throwable ]
        frame_type = 255 /* full_frame */
          offset_delta = 45
          locals = [ class org/scalatest/BeforeAndAfterAllConfigMap, class org/scalatest/Args, class scala/Option, top, class java/lang/Throwable, class java/lang/Throwable, class java/lang/Exception ]
          stack = []
        frame_type = 250 /* chop */
          offset_delta = 2
        frame_type = 2 /* same */
        frame_type = 255 /* full_frame */
          offset_delta = 2
          locals = [ class org/scalatest/BeforeAndAfterAllConfigMap, class org/scalatest/Args, class scala/Option, class scala/runtime/BoxedUnit, class java/lang/Throwable, class java/lang/Throwable, class java/lang/Exception ]
          stack = []
        frame_type = 255 /* full_frame */
          offset_delta = 2
          locals = [ class org/scalatest/BeforeAndAfterAllConfigMap, class org/scalatest/Args, class scala/Option ]
          stack = []
      LineNumberTable:
        line 260: 0
        line 263: 15
        line 263: 19
        line 259: 65
      LocalVariableTable:
        Start  Length  Slot  Name   Signature
            0      72     0 $this   Lorg/scalatest/BeforeAndAfterAllConfigMap;
            0      72     1 args$1   Lorg/scalatest/Args;
            0      72     2 thrownException$1   Lscala/Option;
    MethodParameters:
      Name                           Flags
      $this                          final synthetic
      args$1                         final
      thrownException$1              final

  public static void $init$(org.scalatest.BeforeAndAfterAllConfigMap);
    descriptor: (Lorg/scalatest/BeforeAndAfterAllConfigMap;)V
    flags: (0x0009) ACC_PUBLIC, ACC_STATIC
    Code:
      stack=2, locals=1, args_size=1
         0: aload_0
         1: iconst_0
         2: invokeinterface #176,  2          // InterfaceMethod org$scalatest$BeforeAndAfterAllConfigMap$_setter_$invokeBeforeAllAndAfterAllEvenIfNoTestsAreExpected_$eq:(Z)V
         7: return
      LineNumberTable:
        line 175: 0
        line 162: 7
      LocalVariableTable:
        Start  Length  Slot  Name   Signature
            0       8     0 $this   Lorg/scalatest/BeforeAndAfterAllConfigMap;
    MethodParameters:
      Name                           Flags
      $this                          final synthetic

  private static java.lang.Object $deserializeLambda$(java.lang.invoke.SerializedLambda);
    descriptor: (Ljava/lang/invoke/SerializedLambda;)Ljava/lang/Object;
    flags: (0x100a) ACC_PRIVATE, ACC_STATIC, ACC_SYNTHETIC
    Code:
      stack=1, locals=1, args_size=1
         0: aload_0
         1: invokedynamic #188,  0            // InvokeDynamic #1:lambdaDeserialize:(Ljava/lang/invoke/SerializedLambda;)Ljava/lang/Object;
         6: areturn
}
InnerClasses:
  public static final #15= #12 of #14;    // Lookup=class java/lang/invoke/MethodHandles$Lookup of class java/lang/invoke/MethodHandles
SourceFile: "BeforeAndAfterAllConfigMap.scala"
RuntimeVisibleAnnotations:
  0: #8(#9=s#10)
    scala.reflect.ScalaSignature(
      bytes="\u0006\u0005I3\u0001b\u0002\u0005\u0011\u0002\u0007\u0005Qb\u0013\u0005\u00061\u0001!\t!\u0007\u0005\b;\u0001\u0011\r\u0011\"\u0001\u001f\u0011\u0015\u0011\u0003\u0001\"\u0005$\u0011\u0015I\u0003\u0001\"\u0005+\u0011\u0019a\u0003\u0001%C\u0001[!Ya\t\u0001I\u0001\u0004\u0003\u0005I\u0011B$K\u0005i\u0011UMZ8sK\u0006sG-\u00114uKJ\fE\u000e\\\"p]\u001aLw-T1q\u0015\tI!\"A\u0005tG\u0006d\u0017\r^3ti*\t1\"A\u0002pe\u001e\u001c\u0001aE\u0002\u0001\u001dQ\u0001\"a\u0004\n\u000e\u0003AQ\u0011!E\u0001\u0006g\u000e\fG.Y\u0005\u0003\'A\u0011a!\u00118z%\u00164\u0007CA\u000b\u0017\u001b\u0005A\u0011BA\f\t\u0005)\u0019V/\u001b;f\u001b&D\u0018N\\\u0001\u0007I%t\u0017\u000e\u001e\u0013\u0015\u0003i\u0001\"aD\u000e\n\u0005q\u0001\"\u0001B+oSR\f!\'\u001b8w_.,\')\u001a4pe\u0016\fE\u000e\\!oI\u00063G/\u001a:BY2,e/\u001a8JM:{G+Z:ug\u0006\u0013X-\u0012=qK\u000e$X\rZ\u000b\u0002?A\u0011q\u0002I\u0005\u0003CA\u0011qAQ8pY\u0016\fg.A\u0005cK\u001a|\'/Z!mYR\u0011!\u0004\n\u0005\u0006K\r\u0001\rAJ\u0001\nG>tg-[4NCB\u0004\"!F\u0014\n\u0005!B!!C\"p]\u001aLw-T1q\u0003!\tg\r^3s\u00032dGC\u0001\u000e,\u0011\u0015)C\u00011\u0001\'\u0003\r\u0011XO\u001c\u000b\u0004]E\n\u0005CA\u000b0\u0013\t\u0001\u0004B\u0001\u0004Ti\u0006$Xo\u001d\u0005\u0006e\u0015\u0001\raM\u0001\ti\u0016\u001cHOT1nKB\u0019q\u0002\u000e\u001c\n\u0005U\u0002\"AB(qi&|g\u000e\u0005\u00028}9\u0011\u0001\b\u0010\t\u0003sAi\u0011A\u000f\u0006\u0003w1\ta\u0001\u0010:p_Rt\u0014BA\u001f\u0011\u0003\u0019\u0001&/\u001a3fM&\u0011q\b\u0011\u0002\u0007\'R\u0014\u0018N\\4\u000b\u0005u\u0002\u0002\"\u0002\"\u0006\u0001\u0004\u0019\u0015\u0001B1sON\u0004\"!\u0006#\n\u0005\u0015C!\u0001B!sON\f\u0011b];qKJ$#/\u001e8\u0015\u00079B\u0015\nC\u00033\r\u0001\u00071\u0007C\u0003C\r\u0001\u00071)\u0003\u0002--I\u0019AJT(\u0007\t5\u0003\u0001a\u0013\u0002\ryI,g-\u001b8f[\u0016tGO\u0010\t\u0003+\u0001\u0001\"!\u0006)\n\u0005EC!!B*vSR,\u0007"
    )
BootstrapMethods:
  0: #107 REF_invokeStatic java/lang/invoke/LambdaMetafactory.altMetafactory:(Ljava/lang/invoke/MethodHandles$Lookup;Ljava/lang/String;Ljava/lang/invoke/MethodType;[Ljava/lang/Object;)Ljava/lang/invoke/CallSite;
    Method arguments:
      #94 ()V
      #99 REF_invokeStatic org/scalatest/BeforeAndAfterAllConfigMap.$anonfun$run$1:(Lorg/scalatest/BeforeAndAfterAllConfigMap;Lorg/scalatest/Args;Lscala/Option;)V
      #94 ()V
      #100 1
  1: #185 REF_invokeStatic scala/runtime/LambdaDeserialize.bootstrap:(Ljava/lang/invoke/MethodHandles$Lookup;Ljava/lang/String;Ljava/lang/invoke/MethodType;[Ljava/lang/invoke/MethodHandle;)Ljava/lang/invoke/CallSite;
    Method arguments:
      #99 REF_invokeStatic org/scalatest/BeforeAndAfterAllConfigMap.$anonfun$run$1:(Lorg/scalatest/BeforeAndAfterAllConfigMap;Lorg/scalatest/Args;Lscala/Option;)V
  ScalaInlineInfo: length = 0x40 (unknown attribute)
   01 00 00 0C 00 5F 00 60 01 00 AD 00 AE 01 00 25
   00 1E 00 00 24 00 1A 01 00 1D 00 1E 00 00 19 00
   1A 01 00 17 00 18 00 00 32 00 33 01 00 13 00 14
   01 00 10 00 11 00 00 2A 00 14 00 00 28 00 29 01

  ScalaSig: length = 0x3 (unknown attribute)
   05 02 00
