Classfile /Users/mw/Projects/slang-braindump/.jar/jar8/assemble/slang-braindump/assemble/content/org/scalatest/Checkpoints$Checkpoint.class
  Last modified May 29, 2022; size 5267 bytes
  SHA-256 checksum dfb7145507e943f94ced028e049de638e571a533861c6c04a14c26d91a5ebe49
  Compiled from "Checkpoints.scala"
public class org.scalatest.Checkpoints$Checkpoint
  minor version: 0
  major version: 52
  flags: (0x0021) ACC_PUBLIC, ACC_SUPER
  this_class: #2                          // org/scalatest/Checkpoints$Checkpoint
  super_class: #4                         // java/lang/Object
  interfaces: 0, fields: 2, methods: 9, attributes: 5
Constant pool:
    #1 = Utf8               org/scalatest/Checkpoints$Checkpoint
    #2 = Class              #1            // org/scalatest/Checkpoints$Checkpoint
    #3 = Utf8               java/lang/Object
    #4 = Class              #3            // java/lang/Object
    #5 = Utf8               Checkpoints.scala
    #6 = Utf8               java/lang/invoke/MethodHandles$Lookup
    #7 = Class              #6            // java/lang/invoke/MethodHandles$Lookup
    #8 = Utf8               java/lang/invoke/MethodHandles
    #9 = Class              #8            // java/lang/invoke/MethodHandles
   #10 = Utf8               Lookup
   #11 = Utf8               org/scalatest/Checkpoints
   #12 = Class              #11           // org/scalatest/Checkpoints
   #13 = Utf8               Checkpoint
   #14 = Utf8               failures
   #15 = Utf8               Lorg/scalatest/ConcurrentLinkedQueue;
   #16 = Utf8               Lorg/scalatest/ConcurrentLinkedQueue<Ljava/lang/Throwable;>;
   #17 = Utf8               $outer
   #18 = Utf8               Lorg/scalatest/Checkpoints;
   #19 = Utf8               ()Lorg/scalatest/ConcurrentLinkedQueue;
   #20 = Utf8               ()Lorg/scalatest/ConcurrentLinkedQueue<Ljava/lang/Throwable;>;
   #21 = NameAndType        #14:#15       // failures:Lorg/scalatest/ConcurrentLinkedQueue;
   #22 = Fieldref           #2.#21        // org/scalatest/Checkpoints$Checkpoint.failures:Lorg/scalatest/ConcurrentLinkedQueue;
   #23 = Utf8               this
   #24 = Utf8               Lorg/scalatest/Checkpoints$Checkpoint;
   #25 = Utf8               getFailLine
   #26 = Utf8               (Ljava/lang/Throwable;)Ljava/lang/String;
   #27 = Utf8               t
   #28 = Utf8               org/scalatest/exceptions/StackDepth
   #29 = Class              #28           // org/scalatest/exceptions/StackDepth
   #30 = Utf8               failedCodeFileNameAndLineNumberString
   #31 = Utf8               ()Lscala/Option;
   #32 = NameAndType        #30:#31       // failedCodeFileNameAndLineNumberString:()Lscala/Option;
   #33 = InterfaceMethodref #29.#32       // org/scalatest/exceptions/StackDepth.failedCodeFileNameAndLineNumberString:()Lscala/Option;
   #34 = Utf8               scala/Some
   #35 = Class              #34           // scala/Some
   #36 = Utf8               value
   #37 = Utf8               ()Ljava/lang/Object;
   #38 = NameAndType        #36:#37       // value:()Ljava/lang/Object;
   #39 = Methodref          #35.#38       // scala/Some.value:()Ljava/lang/Object;
   #40 = Utf8               java/lang/String
   #41 = Class              #40           // java/lang/String
   #42 = Utf8               scala/None$
   #43 = Class              #42           // scala/None$
   #44 = Utf8               MODULE$
   #45 = Utf8               Lscala/None$;
   #46 = NameAndType        #44:#45       // MODULE$:Lscala/None$;
   #47 = Fieldref           #43.#46       // scala/None$.MODULE$:Lscala/None$;
   #48 = Utf8               equals
   #49 = Utf8               (Ljava/lang/Object;)Z
   #50 = NameAndType        #48:#49       // equals:(Ljava/lang/Object;)Z
   #51 = Methodref          #4.#50        // java/lang/Object.equals:(Ljava/lang/Object;)Z
   #52 = Utf8               unknown line number
   #53 = String             #52           // unknown line number
   #54 = Utf8               scala/MatchError
   #55 = Class              #54           // scala/MatchError
   #56 = Utf8               <init>
   #57 = Utf8               (Ljava/lang/Object;)V
   #58 = NameAndType        #56:#57       // "<init>":(Ljava/lang/Object;)V
   #59 = Methodref          #55.#58       // scala/MatchError."<init>":(Ljava/lang/Object;)V
   #60 = Utf8               failLine
   #61 = Utf8               Ljava/lang/String;
   #62 = Utf8               Ljava/lang/Throwable;
   #63 = Utf8               scala/Option
   #64 = Class              #63           // scala/Option
   #65 = Utf8               java/lang/Throwable
   #66 = Class              #65           // java/lang/Throwable
   #67 = Utf8               apply
   #68 = Utf8               (Lscala/Function0;)V
   #69 = Utf8               (Lscala/Function0<Lscala/runtime/BoxedUnit;>;)V
   #70 = Utf8               f
   #71 = Utf8               scala/Function0
   #72 = Class              #71           // scala/Function0
   #73 = Utf8               apply$mcV$sp
   #74 = Utf8               ()V
   #75 = NameAndType        #73:#74       // apply$mcV$sp:()V
   #76 = InterfaceMethodref #72.#75       // scala/Function0.apply$mcV$sp:()V
   #77 = Utf8               org/scalatest/exceptions/TestCanceledException
   #78 = Class              #77           // org/scalatest/exceptions/TestCanceledException
   #79 = Utf8               org/scalatest/exceptions/TestRegistrationClosedException
   #80 = Class              #79           // org/scalatest/exceptions/TestRegistrationClosedException
   #81 = Utf8               org/scalatest/exceptions/NotAllowedException
   #82 = Class              #81           // org/scalatest/exceptions/NotAllowedException
   #83 = Utf8               org/scalatest/exceptions/DuplicateTestNameException
   #84 = Class              #83           // org/scalatest/exceptions/DuplicateTestNameException
   #85 = NameAndType        #14:#19       // failures:()Lorg/scalatest/ConcurrentLinkedQueue;
   #86 = Methodref          #2.#85        // org/scalatest/Checkpoints$Checkpoint.failures:()Lorg/scalatest/ConcurrentLinkedQueue;
   #87 = Utf8               org/scalatest/ConcurrentLinkedQueue
   #88 = Class              #87           // org/scalatest/ConcurrentLinkedQueue
   #89 = Utf8               add
   #90 = NameAndType        #89:#57       // add:(Ljava/lang/Object;)V
   #91 = Methodref          #88.#90       // org/scalatest/ConcurrentLinkedQueue.add:(Ljava/lang/Object;)V
   #92 = Utf8               scala/runtime/BoxedUnit
   #93 = Class              #92           // scala/runtime/BoxedUnit
   #94 = Utf8               UNIT
   #95 = Utf8               Lscala/runtime/BoxedUnit;
   #96 = NameAndType        #94:#95       // UNIT:Lscala/runtime/BoxedUnit;
   #97 = Fieldref           #93.#96       // scala/runtime/BoxedUnit.UNIT:Lscala/runtime/BoxedUnit;
   #98 = Utf8               Lscala/Function0;
   #99 = Utf8               reportAll
  #100 = Utf8               (Lorg/scalactic/source/Position;)V
  #101 = Utf8               pos
  #102 = Utf8               isEmpty
  #103 = Utf8               ()Z
  #104 = NameAndType        #102:#103     // isEmpty:()Z
  #105 = Methodref          #88.#104      // org/scalatest/ConcurrentLinkedQueue.isEmpty:()Z
  #106 = Utf8               asScala
  #107 = Utf8               ()Lscala/collection/Iterable;
  #108 = NameAndType        #106:#107     // asScala:()Lscala/collection/Iterable;
  #109 = Methodref          #88.#108      // org/scalatest/ConcurrentLinkedQueue.asScala:()Lscala/collection/Iterable;
  #110 = Utf8               (Ljava/lang/Object;)Ljava/lang/Object;
  #111 = MethodType         #110          //  (Ljava/lang/Object;)Ljava/lang/Object;
  #112 = Utf8               $anonfun$reportAll$1
  #113 = Utf8               (Lorg/scalatest/Checkpoints$Checkpoint;Ljava/lang/Throwable;)Ljava/lang/String;
  #114 = NameAndType        #112:#113     // $anonfun$reportAll$1:(Lorg/scalatest/Checkpoints$Checkpoint;Ljava/lang/Throwable;)Ljava/lang/String;
  #115 = Methodref          #2.#114       // org/scalatest/Checkpoints$Checkpoint.$anonfun$reportAll$1:(Lorg/scalatest/Checkpoints$Checkpoint;Ljava/lang/Throwable;)Ljava/lang/String;
  #116 = MethodHandle       6:#115        // REF_invokeStatic org/scalatest/Checkpoints$Checkpoint.$anonfun$reportAll$1:(Lorg/scalatest/Checkpoints$Checkpoint;Ljava/lang/Throwable;)Ljava/lang/String;
  #117 = MethodType         #26           //  (Ljava/lang/Throwable;)Ljava/lang/String;
  #118 = Integer            5
  #119 = Integer            1
  #120 = Utf8               java/lang/invoke/LambdaMetafactory
  #121 = Class              #120          // java/lang/invoke/LambdaMetafactory
  #122 = Utf8               altMetafactory
  #123 = Utf8               (Ljava/lang/invoke/MethodHandles$Lookup;Ljava/lang/String;Ljava/lang/invoke/MethodType;[Ljava/lang/Object;)Ljava/lang/invoke/CallSite;
  #124 = NameAndType        #122:#123     // altMetafactory:(Ljava/lang/invoke/MethodHandles$Lookup;Ljava/lang/String;Ljava/lang/invoke/MethodType;[Ljava/lang/Object;)Ljava/lang/invoke/CallSite;
  #125 = Methodref          #121.#124     // java/lang/invoke/LambdaMetafactory.altMetafactory:(Ljava/lang/invoke/MethodHandles$Lookup;Ljava/lang/String;Ljava/lang/invoke/MethodType;[Ljava/lang/Object;)Ljava/lang/invoke/CallSite;
  #126 = MethodHandle       6:#125        // REF_invokeStatic java/lang/invoke/LambdaMetafactory.altMetafactory:(Ljava/lang/invoke/MethodHandles$Lookup;Ljava/lang/String;Ljava/lang/invoke/MethodType;[Ljava/lang/Object;)Ljava/lang/invoke/CallSite;
  #127 = Utf8               (Lorg/scalatest/Checkpoints$Checkpoint;)Lscala/Function1;
  #128 = NameAndType        #67:#127      // apply:(Lorg/scalatest/Checkpoints$Checkpoint;)Lscala/Function1;
  #129 = InvokeDynamic      #0:#128       // #0:apply:(Lorg/scalatest/Checkpoints$Checkpoint;)Lscala/Function1;
  #130 = Utf8               scala/collection/Iterable
  #131 = Class              #130          // scala/collection/Iterable
  #132 = Utf8               map
  #133 = Utf8               (Lscala/Function1;)Ljava/lang/Object;
  #134 = NameAndType        #132:#133     // map:(Lscala/Function1;)Ljava/lang/Object;
  #135 = InterfaceMethodref #131.#134     // scala/collection/Iterable.map:(Lscala/Function1;)Ljava/lang/Object;
  #136 = Utf8               org/scalatest/exceptions/TestFailedException
  #137 = Class              #136          // org/scalatest/exceptions/TestFailedException
  #138 = Utf8               $anonfun$reportAll$2
  #139 = Utf8               (Lscala/collection/Iterable;Lorg/scalatest/exceptions/StackDepthException;)Lscala/Some;
  #140 = NameAndType        #138:#139     // $anonfun$reportAll$2:(Lscala/collection/Iterable;Lorg/scalatest/exceptions/StackDepthException;)Lscala/Some;
  #141 = Methodref          #2.#140       // org/scalatest/Checkpoints$Checkpoint.$anonfun$reportAll$2:(Lscala/collection/Iterable;Lorg/scalatest/exceptions/StackDepthException;)Lscala/Some;
  #142 = MethodHandle       6:#141        // REF_invokeStatic org/scalatest/Checkpoints$Checkpoint.$anonfun$reportAll$2:(Lscala/collection/Iterable;Lorg/scalatest/exceptions/StackDepthException;)Lscala/Some;
  #143 = Utf8               (Lorg/scalatest/exceptions/StackDepthException;)Lscala/Some;
  #144 = MethodType         #143          //  (Lorg/scalatest/exceptions/StackDepthException;)Lscala/Some;
  #145 = Utf8               (Lscala/collection/Iterable;)Lscala/Function1;
  #146 = NameAndType        #67:#145      // apply:(Lscala/collection/Iterable;)Lscala/Function1;
  #147 = InvokeDynamic      #1:#146       // #1:apply:(Lscala/collection/Iterable;)Lscala/Function1;
  #148 = Utf8               (Lscala/Function1;Lscala/Option;Lorg/scalactic/source/Position;)V
  #149 = NameAndType        #56:#148      // "<init>":(Lscala/Function1;Lscala/Option;Lorg/scalactic/source/Position;)V
  #150 = Methodref          #137.#149     // org/scalatest/exceptions/TestFailedException."<init>":(Lscala/Function1;Lscala/Option;Lorg/scalactic/source/Position;)V
  #151 = Utf8               failMessages
  #152 = Utf8               Lscala/collection/Iterable;
  #153 = Utf8               stackDepth
  #154 = Utf8               I
  #155 = Utf8               Lorg/scalactic/source/Position;
  #156 = Utf8               org$scalatest$Checkpoints$Checkpoint$$$outer
  #157 = Utf8               ()Lorg/scalatest/Checkpoints;
  #158 = NameAndType        #17:#18       // $outer:Lorg/scalatest/Checkpoints;
  #159 = Fieldref           #2.#158       // org/scalatest/Checkpoints$Checkpoint.$outer:Lorg/scalatest/Checkpoints;
  #160 = Utf8               $this
  #161 = Utf8               failure
  #162 = Utf8               java/lang/StringBuilder
  #163 = Class              #162          // java/lang/StringBuilder
  #164 = Integer            2
  #165 = Utf8               (I)V
  #166 = NameAndType        #56:#165      // "<init>":(I)V
  #167 = Methodref          #163.#166     // java/lang/StringBuilder."<init>":(I)V
  #168 = Utf8               getMessage
  #169 = Utf8               ()Ljava/lang/String;
  #170 = NameAndType        #168:#169     // getMessage:()Ljava/lang/String;
  #171 = Methodref          #66.#170      // java/lang/Throwable.getMessage:()Ljava/lang/String;
  #172 = Utf8               append
  #173 = Utf8               (Ljava/lang/String;)Ljava/lang/StringBuilder;
  #174 = NameAndType        #172:#173     // append:(Ljava/lang/String;)Ljava/lang/StringBuilder;
  #175 = Methodref          #163.#174     // java/lang/StringBuilder.append:(Ljava/lang/String;)Ljava/lang/StringBuilder;
  #176 = Utf8
  #177 = String             #176          //
  #178 = Utf8               org/scalatest/Resources$
  #179 = Class              #178          // org/scalatest/Resources$
  #180 = Utf8               Lorg/scalatest/Resources$;
  #181 = NameAndType        #44:#180      // MODULE$:Lorg/scalatest/Resources$;
  #182 = Fieldref           #179.#181     // org/scalatest/Resources$.MODULE$:Lorg/scalatest/Resources$;
  #183 = Utf8               atCheckpointAt
  #184 = NameAndType        #183:#169     // atCheckpointAt:()Ljava/lang/String;
  #185 = Methodref          #179.#184     // org/scalatest/Resources$.atCheckpointAt:()Ljava/lang/String;
  #186 = NameAndType        #25:#26       // getFailLine:(Ljava/lang/Throwable;)Ljava/lang/String;
  #187 = Methodref          #2.#186       // org/scalatest/Checkpoints$Checkpoint.getFailLine:(Ljava/lang/Throwable;)Ljava/lang/String;
  #188 = Utf8               toString
  #189 = NameAndType        #188:#169     // toString:()Ljava/lang/String;
  #190 = Methodref          #163.#189     // java/lang/StringBuilder.toString:()Ljava/lang/String;
  #191 = Utf8               failMessages$1
  #192 = Utf8               sde
  #193 = Utf8               \n
  #194 = String             #193          // \n
  #195 = Utf8               mkString
  #196 = Utf8               (Ljava/lang/String;)Ljava/lang/String;
  #197 = NameAndType        #195:#196     // mkString:(Ljava/lang/String;)Ljava/lang/String;
  #198 = InterfaceMethodref #131.#197     // scala/collection/Iterable.mkString:(Ljava/lang/String;)Ljava/lang/String;
  #199 = Methodref          #35.#58       // scala/Some."<init>":(Ljava/lang/Object;)V
  #200 = Utf8               Lorg/scalatest/exceptions/StackDepthException;
  #201 = Utf8               (Lorg/scalatest/Checkpoints;)V
  #202 = NameAndType        #56:#74       // "<init>":()V
  #203 = Methodref          #4.#202       // java/lang/Object."<init>":()V
  #204 = Methodref          #88.#202      // org/scalatest/ConcurrentLinkedQueue."<init>":()V
  #205 = Utf8               $deserializeLambda$
  #206 = Utf8               (Ljava/lang/invoke/SerializedLambda;)Ljava/lang/Object;
  #207 = Utf8               scala/runtime/LambdaDeserialize
  #208 = Class              #207          // scala/runtime/LambdaDeserialize
  #209 = Utf8               bootstrap
  #210 = Utf8               (Ljava/lang/invoke/MethodHandles$Lookup;Ljava/lang/String;Ljava/lang/invoke/MethodType;[Ljava/lang/invoke/MethodHandle;)Ljava/lang/invoke/CallSite;
  #211 = NameAndType        #209:#210     // bootstrap:(Ljava/lang/invoke/MethodHandles$Lookup;Ljava/lang/String;Ljava/lang/invoke/MethodType;[Ljava/lang/invoke/MethodHandle;)Ljava/lang/invoke/CallSite;
  #212 = Methodref          #208.#211     // scala/runtime/LambdaDeserialize.bootstrap:(Ljava/lang/invoke/MethodHandles$Lookup;Ljava/lang/String;Ljava/lang/invoke/MethodType;[Ljava/lang/invoke/MethodHandle;)Ljava/lang/invoke/CallSite;
  #213 = MethodHandle       6:#212        // REF_invokeStatic scala/runtime/LambdaDeserialize.bootstrap:(Ljava/lang/invoke/MethodHandles$Lookup;Ljava/lang/String;Ljava/lang/invoke/MethodType;[Ljava/lang/invoke/MethodHandle;)Ljava/lang/invoke/CallSite;
  #214 = Utf8               lambdaDeserialize
  #215 = NameAndType        #214:#206     // lambdaDeserialize:(Ljava/lang/invoke/SerializedLambda;)Ljava/lang/Object;
  #216 = InvokeDynamic      #2:#215       // #2:lambdaDeserialize:(Ljava/lang/invoke/SerializedLambda;)Ljava/lang/Object;
  #217 = Utf8               Signature
  #218 = Utf8               Code
  #219 = Utf8               LineNumberTable
  #220 = Utf8               LocalVariableTable
  #221 = Utf8               StackMapTable
  #222 = Utf8               MethodParameters
  #223 = Utf8               InnerClasses
  #224 = Utf8               SourceFile
  #225 = Utf8               BootstrapMethods
  #226 = Utf8               ScalaInlineInfo
  #227 = Utf8               Scala
{
  private final org.scalatest.ConcurrentLinkedQueue<java.lang.Throwable> failures;
    descriptor: Lorg/scalatest/ConcurrentLinkedQueue;
    flags: (0x0012) ACC_PRIVATE, ACC_FINAL
    Signature: #16                          // Lorg/scalatest/ConcurrentLinkedQueue<Ljava/lang/Throwable;>;

  public final org.scalatest.Checkpoints $outer;
    descriptor: Lorg/scalatest/Checkpoints;
    flags: (0x1011) ACC_PUBLIC, ACC_FINAL, ACC_SYNTHETIC

  private final org.scalatest.ConcurrentLinkedQueue<java.lang.Throwable> failures();
    descriptor: ()Lorg/scalatest/ConcurrentLinkedQueue;
    flags: (0x0012) ACC_PRIVATE, ACC_FINAL
    Code:
      stack=1, locals=1, args_size=1
         0: aload_0
         1: getfield      #22                 // Field failures:Lorg/scalatest/ConcurrentLinkedQueue;
         4: areturn
      LineNumberTable:
        line 104: 0
      LocalVariableTable:
        Start  Length  Slot  Name   Signature
            0       5     0  this   Lorg/scalatest/Checkpoints$Checkpoint;
    Signature: #20                          // ()Lorg/scalatest/ConcurrentLinkedQueue<Ljava/lang/Throwable;>;

  private java.lang.String getFailLine(java.lang.Throwable);
    descriptor: (Ljava/lang/Throwable;)Ljava/lang/String;
    flags: (0x0002) ACC_PRIVATE
    Code:
      stack=3, locals=6, args_size=2
         0: aload_1
         1: checkcast     #29                 // class org/scalatest/exceptions/StackDepth
         4: invokeinterface #33,  1           // InterfaceMethod org/scalatest/exceptions/StackDepth.failedCodeFileNameAndLineNumberString:()Lscala/Option;
         9: astore_3
        10: aload_3
        11: instanceof    #35                 // class scala/Some
        14: ifeq          39
        17: aload_3
        18: checkcast     #35                 // class scala/Some
        21: astore        4
        23: aload         4
        25: invokevirtual #39                 // Method scala/Some.value:()Ljava/lang/Object;
        28: checkcast     #41                 // class java/lang/String
        31: astore        5
        33: aload         5
        35: astore_2
        36: goto          70
        39: goto          42
        42: getstatic     #47                 // Field scala/None$.MODULE$:Lscala/None$;
        45: aload_3
        46: invokevirtual #51                 // Method java/lang/Object.equals:(Ljava/lang/Object;)Z
        49: ifeq          58
        52: ldc           #53                 // String unknown line number
        54: astore_2
        55: goto          70
        58: goto          61
        61: new           #55                 // class scala/MatchError
        64: dup
        65: aload_3
        66: invokespecial #59                 // Method scala/MatchError."<init>":(Ljava/lang/Object;)V
        69: athrow
        70: aload_2
        71: areturn
      StackMapTable: number_of_entries = 5
        frame_type = 253 /* append */
          offset_delta = 39
          locals = [ top, class scala/Option ]
        frame_type = 2 /* same */
        frame_type = 15 /* same */
        frame_type = 2 /* same */
        frame_type = 255 /* full_frame */
          offset_delta = 8
          locals = [ class org/scalatest/Checkpoints$Checkpoint, class java/lang/Throwable, class java/lang/String, class scala/Option ]
          stack = []
      LineNumberTable:
        line 112: 0
        line 113: 10
        line 114: 42
        line 112: 61
      LocalVariableTable:
        Start  Length  Slot  Name   Signature
           33       6     5 failLine   Ljava/lang/String;
            0      72     0  this   Lorg/scalatest/Checkpoints$Checkpoint;
            0      72     1     t   Ljava/lang/Throwable;
    MethodParameters:
      Name                           Flags
      t                              final

  public void apply(scala.Function0<scala.runtime.BoxedUnit>);
    descriptor: (Lscala/Function0;)V
    flags: (0x0001) ACC_PUBLIC
    Code:
      stack=2, locals=11, args_size=2
         0: aload_1
         1: invokeinterface #76,  1           // InterfaceMethod scala/Function0.apply$mcV$sp:()V
         6: goto          148
         9: astore_3
        10: aload_3
        11: astore        4
        13: aload         4
        15: instanceof    #78                 // class org/scalatest/exceptions/TestCanceledException
        18: ifeq          31
        21: aload         4
        23: checkcast     #78                 // class org/scalatest/exceptions/TestCanceledException
        26: astore        5
        28: aload         5
        30: athrow
        31: goto          34
        34: aload         4
        36: instanceof    #80                 // class org/scalatest/exceptions/TestRegistrationClosedException
        39: ifeq          52
        42: aload         4
        44: checkcast     #80                 // class org/scalatest/exceptions/TestRegistrationClosedException
        47: astore        6
        49: aload         6
        51: athrow
        52: goto          55
        55: aload         4
        57: instanceof    #82                 // class org/scalatest/exceptions/NotAllowedException
        60: ifeq          73
        63: aload         4
        65: checkcast     #82                 // class org/scalatest/exceptions/NotAllowedException
        68: astore        7
        70: aload         7
        72: athrow
        73: goto          76
        76: aload         4
        78: instanceof    #84                 // class org/scalatest/exceptions/DuplicateTestNameException
        81: ifeq          94
        84: aload         4
        86: checkcast     #84                 // class org/scalatest/exceptions/DuplicateTestNameException
        89: astore        8
        91: aload         8
        93: athrow
        94: goto          97
        97: aload         4
        99: instanceof    #29                 // class org/scalatest/exceptions/StackDepth
       102: ifeq          125
       105: aload         4
       107: astore        9
       109: aload_0
       110: invokespecial #86                 // Method failures:()Lorg/scalatest/ConcurrentLinkedQueue;
       113: aload         9
       115: invokevirtual #91                 // Method org/scalatest/ConcurrentLinkedQueue.add:(Ljava/lang/Object;)V
       118: getstatic     #97                 // Field scala/runtime/BoxedUnit.UNIT:Lscala/runtime/BoxedUnit;
       121: astore_2
       122: goto          145
       125: goto          128
       128: aload         4
       130: ifnull        140
       133: aload         4
       135: astore        10
       137: aload         10
       139: athrow
       140: goto          143
       143: aload_3
       144: athrow
       145: goto          148
       148: return
      Exception table:
         from    to  target type
             0     6     9   Class java/lang/Throwable
      StackMapTable: number_of_entries = 15
        frame_type = 73 /* same_locals_1_stack_item */
          stack = [ class java/lang/Throwable ]
        frame_type = 254 /* append */
          offset_delta = 21
          locals = [ top, class java/lang/Throwable, class java/lang/Throwable ]
        frame_type = 2 /* same */
        frame_type = 17 /* same */
        frame_type = 2 /* same */
        frame_type = 17 /* same */
        frame_type = 2 /* same */
        frame_type = 17 /* same */
        frame_type = 2 /* same */
        frame_type = 27 /* same */
        frame_type = 2 /* same */
        frame_type = 11 /* same */
        frame_type = 2 /* same */
        frame_type = 255 /* full_frame */
          offset_delta = 1
          locals = [ class org/scalatest/Checkpoints$Checkpoint, class scala/Function0, class scala/runtime/BoxedUnit, class java/lang/Throwable, class java/lang/Throwable, top, top, top, top, class java/lang/Throwable ]
          stack = []
        frame_type = 255 /* full_frame */
          offset_delta = 2
          locals = [ class org/scalatest/Checkpoints$Checkpoint, class scala/Function0 ]
          stack = []
      LineNumberTable:
        line 132: 0
        line 135: 10
        line 135: 13
        line 136: 34
        line 137: 55
        line 138: 76
        line 139: 97
        line 140: 128
        line 131: 143
      LocalVariableTable:
        Start  Length  Slot  Name   Signature
            0     149     0  this   Lorg/scalatest/Checkpoints$Checkpoint;
            0     149     1     f   Lscala/Function0;
    Signature: #69                          // (Lscala/Function0<Lscala/runtime/BoxedUnit;>;)V
    MethodParameters:
      Name                           Flags
      f                              final

  public void reportAll(org.scalactic.source.Position);
    descriptor: (Lorg/scalactic/source/Position;)V
    flags: (0x0001) ACC_PUBLIC
    Code:
      stack=5, locals=4, args_size=2
         0: iconst_1
         1: istore_2
         2: aload_0
         3: invokespecial #86                 // Method failures:()Lorg/scalatest/ConcurrentLinkedQueue;
         6: invokevirtual #105                // Method org/scalatest/ConcurrentLinkedQueue.isEmpty:()Z
         9: ifne          52
        12: aload_0
        13: invokespecial #86                 // Method failures:()Lorg/scalatest/ConcurrentLinkedQueue;
        16: invokevirtual #109                // Method org/scalatest/ConcurrentLinkedQueue.asScala:()Lscala/collection/Iterable;
        19: aload_0
        20: invokedynamic #129,  0            // InvokeDynamic #0:apply:(Lorg/scalatest/Checkpoints$Checkpoint;)Lscala/Function1;
        25: invokeinterface #135,  2          // InterfaceMethod scala/collection/Iterable.map:(Lscala/Function1;)Ljava/lang/Object;
        30: checkcast     #131                // class scala/collection/Iterable
        33: astore_3
        34: new           #137                // class org/scalatest/exceptions/TestFailedException
        37: dup
        38: aload_3
        39: invokedynamic #147,  0            // InvokeDynamic #1:apply:(Lscala/collection/Iterable;)Lscala/Function1;
        44: getstatic     #47                 // Field scala/None$.MODULE$:Lscala/None$;
        47: aload_1
        48: invokespecial #150                // Method org/scalatest/exceptions/TestFailedException."<init>":(Lscala/Function1;Lscala/Option;Lorg/scalactic/source/Position;)V
        51: athrow
        52: return
      StackMapTable: number_of_entries = 1
        frame_type = 252 /* append */
          offset_delta = 52
          locals = [ int ]
      LineNumberTable:
        line 151: 0
        line 154: 2
        line 156: 12
        line 158: 34
        line 154: 52
      LocalVariableTable:
        Start  Length  Slot  Name   Signature
           34      18     3 failMessages   Lscala/collection/Iterable;
            2      50     2 stackDepth   I
            0      53     0  this   Lorg/scalatest/Checkpoints$Checkpoint;
            0      53     1   pos   Lorg/scalactic/source/Position;
    MethodParameters:
      Name                           Flags
      pos                            final

  public org.scalatest.Checkpoints org$scalatest$Checkpoints$Checkpoint$$$outer();
    descriptor: ()Lorg/scalatest/Checkpoints;
    flags: (0x1001) ACC_PUBLIC, ACC_SYNTHETIC
    Code:
      stack=1, locals=1, args_size=1
         0: aload_0
         1: getfield      #159                // Field $outer:Lorg/scalatest/Checkpoints;
         4: areturn
      LineNumberTable:
        line 103: 0
      LocalVariableTable:
        Start  Length  Slot  Name   Signature
            0       5     0  this   Lorg/scalatest/Checkpoints$Checkpoint;

  public static final java.lang.String $anonfun$reportAll$1(org.scalatest.Checkpoints$Checkpoint, java.lang.Throwable);
    descriptor: (Lorg/scalatest/Checkpoints$Checkpoint;Ljava/lang/Throwable;)Ljava/lang/String;
    flags: (0x1019) ACC_PUBLIC, ACC_STATIC, ACC_FINAL, ACC_SYNTHETIC
    Code:
      stack=3, locals=2, args_size=2
         0: new           #163                // class java/lang/StringBuilder
         3: dup
         4: ldc           #164                // int 2
         6: invokespecial #167                // Method java/lang/StringBuilder."<init>":(I)V
         9: aload_1
        10: invokevirtual #171                // Method java/lang/Throwable.getMessage:()Ljava/lang/String;
        13: invokevirtual #175                // Method java/lang/StringBuilder.append:(Ljava/lang/String;)Ljava/lang/StringBuilder;
        16: ldc           #177                // String
        18: invokevirtual #175                // Method java/lang/StringBuilder.append:(Ljava/lang/String;)Ljava/lang/StringBuilder;
        21: getstatic     #182                // Field org/scalatest/Resources$.MODULE$:Lorg/scalatest/Resources$;
        24: invokevirtual #185                // Method org/scalatest/Resources$.atCheckpointAt:()Ljava/lang/String;
        27: invokevirtual #175                // Method java/lang/StringBuilder.append:(Ljava/lang/String;)Ljava/lang/StringBuilder;
        30: ldc           #177                // String
        32: invokevirtual #175                // Method java/lang/StringBuilder.append:(Ljava/lang/String;)Ljava/lang/StringBuilder;
        35: aload_0
        36: aload_1
        37: invokespecial #187                // Method getFailLine:(Ljava/lang/Throwable;)Ljava/lang/String;
        40: invokevirtual #175                // Method java/lang/StringBuilder.append:(Ljava/lang/String;)Ljava/lang/StringBuilder;
        43: invokevirtual #190                // Method java/lang/StringBuilder.toString:()Ljava/lang/String;
        46: areturn
      LineNumberTable:
        line 157: 0
      LocalVariableTable:
        Start  Length  Slot  Name   Signature
            0      47     0 $this   Lorg/scalatest/Checkpoints$Checkpoint;
            0      47     1 failure   Ljava/lang/Throwable;
    MethodParameters:
      Name                           Flags
      $this                          final synthetic
      failure                        final

  public static final scala.Some $anonfun$reportAll$2(scala.collection.Iterable, org.scalatest.exceptions.StackDepthException);
    descriptor: (Lscala/collection/Iterable;Lorg/scalatest/exceptions/StackDepthException;)Lscala/Some;
    flags: (0x1019) ACC_PUBLIC, ACC_STATIC, ACC_FINAL, ACC_SYNTHETIC
    Code:
      stack=4, locals=2, args_size=2
         0: new           #35                 // class scala/Some
         3: dup
         4: aload_0
         5: ldc           #194                // String \n
         7: invokeinterface #198,  2          // InterfaceMethod scala/collection/Iterable.mkString:(Ljava/lang/String;)Ljava/lang/String;
        12: invokespecial #199                // Method scala/Some."<init>":(Ljava/lang/Object;)V
        15: areturn
      LineNumberTable:
        line 158: 0
      LocalVariableTable:
        Start  Length  Slot  Name   Signature
            0      16     0 failMessages$1   Lscala/collection/Iterable;
            0      16     1   sde   Lorg/scalatest/exceptions/StackDepthException;
    MethodParameters:
      Name                           Flags
      failMessages$1                 final
      sde                            final

  public org.scalatest.Checkpoints$Checkpoint(org.scalatest.Checkpoints);
    descriptor: (Lorg/scalatest/Checkpoints;)V
    flags: (0x0001) ACC_PUBLIC
    Code:
      stack=3, locals=2, args_size=2
         0: aload_1
         1: ifnonnull     6
         4: aconst_null
         5: athrow
         6: aload_0
         7: aload_1
         8: putfield      #159                // Field $outer:Lorg/scalatest/Checkpoints;
        11: aload_0
        12: invokespecial #203                // Method java/lang/Object."<init>":()V
        15: aload_0
        16: new           #88                 // class org/scalatest/ConcurrentLinkedQueue
        19: dup
        20: invokespecial #204                // Method org/scalatest/ConcurrentLinkedQueue."<init>":()V
        23: putfield      #22                 // Field failures:Lorg/scalatest/ConcurrentLinkedQueue;
        26: return
      StackMapTable: number_of_entries = 1
        frame_type = 6 /* same */
      LineNumberTable:
        line 103: 0
        line 162: 11
        line 104: 15
        line 105: 16
        line 104: 23
        line 103: 26
      LocalVariableTable:
        Start  Length  Slot  Name   Signature
            0      27     0  this   Lorg/scalatest/Checkpoints$Checkpoint;
            0      27     1 $outer   Lorg/scalatest/Checkpoints;
    MethodParameters:
      Name                           Flags
      $outer                         final synthetic

  private static java.lang.Object $deserializeLambda$(java.lang.invoke.SerializedLambda);
    descriptor: (Ljava/lang/invoke/SerializedLambda;)Ljava/lang/Object;
    flags: (0x100a) ACC_PRIVATE, ACC_STATIC, ACC_SYNTHETIC
    Code:
      stack=1, locals=1, args_size=1
         0: aload_0
         1: invokedynamic #216,  0            // InvokeDynamic #2:lambdaDeserialize:(Ljava/lang/invoke/SerializedLambda;)Ljava/lang/Object;
         6: areturn
}
InnerClasses:
  public static final #10= #7 of #9;      // Lookup=class java/lang/invoke/MethodHandles$Lookup of class java/lang/invoke/MethodHandles
  public #13= #2 of #12;                  // Checkpoint=class org/scalatest/Checkpoints$Checkpoint of class org/scalatest/Checkpoints
SourceFile: "Checkpoints.scala"
BootstrapMethods:
  0: #126 REF_invokeStatic java/lang/invoke/LambdaMetafactory.altMetafactory:(Ljava/lang/invoke/MethodHandles$Lookup;Ljava/lang/String;Ljava/lang/invoke/MethodType;[Ljava/lang/Object;)Ljava/lang/invoke/CallSite;
    Method arguments:
      #111 (Ljava/lang/Object;)Ljava/lang/Object;
      #116 REF_invokeStatic org/scalatest/Checkpoints$Checkpoint.$anonfun$reportAll$1:(Lorg/scalatest/Checkpoints$Checkpoint;Ljava/lang/Throwable;)Ljava/lang/String;
      #117 (Ljava/lang/Throwable;)Ljava/lang/String;
      #118 5
      #119 1
      #117 (Ljava/lang/Throwable;)Ljava/lang/String;
  1: #126 REF_invokeStatic java/lang/invoke/LambdaMetafactory.altMetafactory:(Ljava/lang/invoke/MethodHandles$Lookup;Ljava/lang/String;Ljava/lang/invoke/MethodType;[Ljava/lang/Object;)Ljava/lang/invoke/CallSite;
    Method arguments:
      #111 (Ljava/lang/Object;)Ljava/lang/Object;
      #142 REF_invokeStatic org/scalatest/Checkpoints$Checkpoint.$anonfun$reportAll$2:(Lscala/collection/Iterable;Lorg/scalatest/exceptions/StackDepthException;)Lscala/Some;
      #144 (Lorg/scalatest/exceptions/StackDepthException;)Lscala/Some;
      #118 5
      #119 1
      #144 (Lorg/scalatest/exceptions/StackDepthException;)Lscala/Some;
  2: #213 REF_invokeStatic scala/runtime/LambdaDeserialize.bootstrap:(Ljava/lang/invoke/MethodHandles$Lookup;Ljava/lang/String;Ljava/lang/invoke/MethodType;[Ljava/lang/invoke/MethodHandle;)Ljava/lang/invoke/CallSite;
    Method arguments:
      #116 REF_invokeStatic org/scalatest/Checkpoints$Checkpoint.$anonfun$reportAll$1:(Lorg/scalatest/Checkpoints$Checkpoint;Ljava/lang/Throwable;)Ljava/lang/String;
      #142 REF_invokeStatic org/scalatest/Checkpoints$Checkpoint.$anonfun$reportAll$2:(Lscala/collection/Iterable;Lorg/scalatest/exceptions/StackDepthException;)Lscala/Some;
  ScalaInlineInfo: length = 0x2C (unknown attribute)
   01 00 00 08 00 70 00 71 01 00 8A 00 8B 01 00 38
   00 C9 00 00 43 00 44 00 00 0E 00 13 01 00 19 00
   1A 01 00 9C 00 9D 00 00 63 00 64 00
  Scala: length = 0x0 (unknown attribute)

