Classfile /Users/mw/Projects/slang-braindump/.jar/jar8/assemble/slang-braindump/assemble/content/org/scalatest/ConfigMap$.class
  Last modified May 29, 2022; size 1491 bytes
  SHA-256 checksum 92ef39b97c1178a4883735f84b262ab404ca412cdfb6b1005685d9564320a3ae
  Compiled from "ConfigMap.scala"
public final class org.scalatest.ConfigMap$ implements java.io.Serializable
  minor version: 0
  major version: 52
  flags: (0x0031) ACC_PUBLIC, ACC_FINAL, ACC_SUPER
  this_class: #2                          // org/scalatest/ConfigMap$
  super_class: #4                         // java/lang/Object
  interfaces: 1, fields: 1, methods: 5, attributes: 3
Constant pool:
   #1 = Utf8               org/scalatest/ConfigMap$
   #2 = Class              #1             // org/scalatest/ConfigMap$
   #3 = Utf8               java/lang/Object
   #4 = Class              #3             // java/lang/Object
   #5 = Utf8               java/io/Serializable
   #6 = Class              #5             // java/io/Serializable
   #7 = Utf8               ConfigMap.scala
   #8 = Utf8               MODULE$
   #9 = Utf8               Lorg/scalatest/ConfigMap$;
  #10 = Utf8               <clinit>
  #11 = Utf8               ()V
  #12 = Utf8               <init>
  #13 = NameAndType        #12:#11        // "<init>":()V
  #14 = Methodref          #2.#13         // org/scalatest/ConfigMap$."<init>":()V
  #15 = NameAndType        #8:#9          // MODULE$:Lorg/scalatest/ConfigMap$;
  #16 = Fieldref           #2.#15         // org/scalatest/ConfigMap$.MODULE$:Lorg/scalatest/ConfigMap$;
  #17 = Utf8               apply
  #18 = Utf8               (Lscala/collection/immutable/Seq;)Lorg/scalatest/ConfigMap;
  #19 = Utf8               (Lscala/collection/immutable/Seq<Lscala/Tuple2<Ljava/lang/String;Ljava/lang/Object;>;>;)Lorg/scalatest/ConfigMap;
  #20 = Utf8               pairs
  #21 = Utf8               org/scalatest/ConfigMap
  #22 = Class              #21            // org/scalatest/ConfigMap
  #23 = Utf8               scala/Predef$
  #24 = Class              #23            // scala/Predef$
  #25 = Utf8               Lscala/Predef$;
  #26 = NameAndType        #8:#25         // MODULE$:Lscala/Predef$;
  #27 = Fieldref           #24.#26        // scala/Predef$.MODULE$:Lscala/Predef$;
  #28 = Utf8               Map
  #29 = Utf8               ()Lscala/collection/immutable/Map$;
  #30 = NameAndType        #28:#29        // Map:()Lscala/collection/immutable/Map$;
  #31 = Methodref          #24.#30        // scala/Predef$.Map:()Lscala/collection/immutable/Map$;
  #32 = Utf8               scala/collection/immutable/Map$
  #33 = Class              #32            // scala/collection/immutable/Map$
  #34 = Utf8               (Lscala/collection/immutable/Seq;)Ljava/lang/Object;
  #35 = NameAndType        #17:#34        // apply:(Lscala/collection/immutable/Seq;)Ljava/lang/Object;
  #36 = Methodref          #33.#35        // scala/collection/immutable/Map$.apply:(Lscala/collection/immutable/Seq;)Ljava/lang/Object;
  #37 = Utf8               scala/collection/immutable/Map
  #38 = Class              #37            // scala/collection/immutable/Map
  #39 = Utf8               (Lscala/collection/immutable/Map;)V
  #40 = NameAndType        #12:#39        // "<init>":(Lscala/collection/immutable/Map;)V
  #41 = Methodref          #22.#40        // org/scalatest/ConfigMap."<init>":(Lscala/collection/immutable/Map;)V
  #42 = Utf8               this
  #43 = Utf8               Lscala/collection/immutable/Seq;
  #44 = Utf8               empty
  #45 = Utf8               ()Lorg/scalatest/ConfigMap;
  #46 = Utf8               ()Lscala/collection/immutable/Map;
  #47 = NameAndType        #44:#46        // empty:()Lscala/collection/immutable/Map;
  #48 = Methodref          #33.#47        // scala/collection/immutable/Map$.empty:()Lscala/collection/immutable/Map;
  #49 = Utf8               writeReplace
  #50 = Utf8               ()Ljava/lang/Object;
  #51 = Utf8               scala/runtime/ModuleSerializationProxy
  #52 = Class              #51            // scala/runtime/ModuleSerializationProxy
  #53 = Utf8               (Ljava/lang/Class;)V
  #54 = NameAndType        #12:#53        // "<init>":(Ljava/lang/Class;)V
  #55 = Methodref          #52.#54        // scala/runtime/ModuleSerializationProxy."<init>":(Ljava/lang/Class;)V
  #56 = Methodref          #4.#13         // java/lang/Object."<init>":()V
  #57 = Utf8               Code
  #58 = Utf8               LineNumberTable
  #59 = Utf8               LocalVariableTable
  #60 = Utf8               Signature
  #61 = Utf8               MethodParameters
  #62 = Utf8               SourceFile
  #63 = Utf8               ScalaInlineInfo
  #64 = Utf8               Scala
{
  public static final org.scalatest.ConfigMap$ MODULE$;
    descriptor: Lorg/scalatest/ConfigMap$;
    flags: (0x0019) ACC_PUBLIC, ACC_STATIC, ACC_FINAL

  public static {};
    descriptor: ()V
    flags: (0x0009) ACC_PUBLIC, ACC_STATIC
    Code:
      stack=2, locals=0, args_size=0
         0: new           #2                  // class org/scalatest/ConfigMap$
         3: dup
         4: invokespecial #14                 // Method "<init>":()V
         7: putstatic     #16                 // Field MODULE$:Lorg/scalatest/ConfigMap$;
        10: return
      LineNumberTable:
        line 200: 0

  public org.scalatest.ConfigMap apply(scala.collection.immutable.Seq<scala.Tuple2<java.lang.String, java.lang.Object>>);
    descriptor: (Lscala/collection/immutable/Seq;)Lorg/scalatest/ConfigMap;
    flags: (0x0001) ACC_PUBLIC
    Code:
      stack=4, locals=2, args_size=2
         0: new           #22                 // class org/scalatest/ConfigMap
         3: dup
         4: getstatic     #27                 // Field scala/Predef$.MODULE$:Lscala/Predef$;
         7: invokevirtual #31                 // Method scala/Predef$.Map:()Lscala/collection/immutable/Map$;
        10: aload_1
        11: invokevirtual #36                 // Method scala/collection/immutable/Map$.apply:(Lscala/collection/immutable/Seq;)Ljava/lang/Object;
        14: checkcast     #38                 // class scala/collection/immutable/Map
        17: invokespecial #41                 // Method org/scalatest/ConfigMap."<init>":(Lscala/collection/immutable/Map;)V
        20: areturn
      LineNumberTable:
        line 207: 0
      LocalVariableTable:
        Start  Length  Slot  Name   Signature
            0      21     0  this   Lorg/scalatest/ConfigMap$;
            0      21     1 pairs   Lscala/collection/immutable/Seq;
    Signature: #19                          // (Lscala/collection/immutable/Seq<Lscala/Tuple2<Ljava/lang/String;Ljava/lang/Object;>;>;)Lorg/scalatest/ConfigMap;
    MethodParameters:
      Name                           Flags
      pairs                          final

  public org.scalatest.ConfigMap empty();
    descriptor: ()Lorg/scalatest/ConfigMap;
    flags: (0x0001) ACC_PUBLIC
    Code:
      stack=3, locals=1, args_size=1
         0: new           #22                 // class org/scalatest/ConfigMap
         3: dup
         4: getstatic     #27                 // Field scala/Predef$.MODULE$:Lscala/Predef$;
         7: invokevirtual #31                 // Method scala/Predef$.Map:()Lscala/collection/immutable/Map$;
        10: invokevirtual #48                 // Method scala/collection/immutable/Map$.empty:()Lscala/collection/immutable/Map;
        13: invokespecial #41                 // Method org/scalatest/ConfigMap."<init>":(Lscala/collection/immutable/Map;)V
        16: areturn
      LineNumberTable:
        line 212: 0
      LocalVariableTable:
        Start  Length  Slot  Name   Signature
            0      17     0  this   Lorg/scalatest/ConfigMap$;

  private java.lang.Object writeReplace();
    descriptor: ()Ljava/lang/Object;
    flags: (0x0002) ACC_PRIVATE
    Code:
      stack=3, locals=1, args_size=1
         0: new           #52                 // class scala/runtime/ModuleSerializationProxy
         3: dup
         4: ldc           #2                  // class org/scalatest/ConfigMap$
         6: invokespecial #55                 // Method scala/runtime/ModuleSerializationProxy."<init>":(Ljava/lang/Class;)V
         9: areturn
      LineNumberTable:
        line 200: 0
      LocalVariableTable:
        Start  Length  Slot  Name   Signature
            0      10     0  this   Lorg/scalatest/ConfigMap$;

  private org.scalatest.ConfigMap$();
    descriptor: ()V
    flags: (0x0002) ACC_PRIVATE
    Code:
      stack=1, locals=1, args_size=1
         0: aload_0
         1: invokespecial #56                 // Method java/lang/Object."<init>":()V
         4: return
      LineNumberTable:
        line 215: 0
        line 200: 4
      LocalVariableTable:
        Start  Length  Slot  Name   Signature
            0       5     0  this   Lorg/scalatest/ConfigMap$;
}
SourceFile: "ConfigMap.scala"
  ScalaInlineInfo: length = 0x18 (unknown attribute)
   01 01 00 04 00 0C 00 0B 01 00 11 00 12 01 00 2C
   00 2D 01 00 31 00 32 01
  Scala: length = 0x0 (unknown attribute)

