Classfile /Users/mw/Projects/slang-braindump/.jar/jar8/assemble/slang-braindump/assemble/content/org/scalatest/CountDownLatch.class
  Last modified May 29, 2022; size 1413 bytes
  SHA-256 checksum d374eaa56eb269a445dbe2e2a1b0d7a0bc70929bf66e4fb9fd8cdd291974d4b1
  Compiled from "JavaClassesWrappers.scala"
public class org.scalatest.CountDownLatch
  minor version: 0
  major version: 52
  flags: (0x0021) ACC_PUBLIC, ACC_SUPER
  this_class: #2                          // org/scalatest/CountDownLatch
  super_class: #4                         // java/lang/Object
  interfaces: 0, fields: 1, methods: 5, attributes: 4
Constant pool:
   #1 = Utf8               org/scalatest/CountDownLatch
   #2 = Class              #1             // org/scalatest/CountDownLatch
   #3 = Utf8               java/lang/Object
   #4 = Class              #3             // java/lang/Object
   #5 = Utf8               JavaClassesWrappers.scala
   #6 = Utf8               Lscala/reflect/ScalaSignature;
   #7 = Utf8               bytes
   #8 = Utf8               \u0006\u0005e2Q\u0001C\u0005\u0001\u00135A\u0001\u0002\u0006\u0001\u0003\u0002\u0003\u0006IA\u0006\u0005\u00063\u0001!\tA\u0007\u0005\b=\u0001\u0011\r\u0011\"\u0004 \u0011\u0019I\u0003\u0001)A\u0007A!)a\u0006\u0001C\u0001_!)1\u0007\u0001C\u0001i!)\u0001\b\u0001C\u0001_\tq1i\\;oi\u0012{wO\u001c\'bi\u000eD\'B\u0001\u0006\f\u0003%\u00198-\u00197bi\u0016\u001cHOC\u0001\r\u0003\ry\'oZ\n\u0003\u00019\u0001\"a\u0004\n\u000e\u0003AQ\u0011!E\u0001\u0006g\u000e\fG.Y\u0005\u0003\'A\u0011a!\u00118z%\u00164\u0017!B2pk:$8\u0001\u0001\t\u0003\u001f]I!\u0001\u0007\t\u0003\u0007%sG/\u0001\u0004=S:LGO\u0010\u000b\u00037u\u0001\"\u0001\b\u0001\u000e\u0003%AQ\u0001\u0006\u0002A\u0002Y\tQ\u0001\\1uG\",\u0012\u0001\t\t\u0003C!j\u0011A\t\u0006\u0003G\u0011\n!bY8oGV\u0014(/\u001a8u\u0015\t)c%\u0001\u0003vi&d\'\"A\u0014\u0002\t)\fg/Y\u0005\u0003\u0011\t\na\u0001\\1uG\"\u0004\u0003F\u0001\u0003,!\tyA&\u0003\u0002.!\tIAO]1og&,g\u000e^\u0001\nG>,h\u000e\u001e#po:$\u0012\u0001\r\t\u0003\u001fEJ!A\r\t\u0003\tUs\u0017\u000e^\u0001\tO\u0016$8i\\;oiV\tQ\u0007\u0005\u0002\u0010m%\u0011q\u0007\u0005\u0002\u0005\u0019>tw-A\u0003bo\u0006LG\u000f
   #9 = Utf8               latch
  #10 = Utf8               Ljava/util/concurrent/CountDownLatch;
  #11 = Utf8               ()Ljava/util/concurrent/CountDownLatch;
  #12 = NameAndType        #9:#10         // latch:Ljava/util/concurrent/CountDownLatch;
  #13 = Fieldref           #2.#12         // org/scalatest/CountDownLatch.latch:Ljava/util/concurrent/CountDownLatch;
  #14 = Utf8               this
  #15 = Utf8               Lorg/scalatest/CountDownLatch;
  #16 = Utf8               countDown
  #17 = Utf8               ()V
  #18 = NameAndType        #9:#11         // latch:()Ljava/util/concurrent/CountDownLatch;
  #19 = Methodref          #2.#18         // org/scalatest/CountDownLatch.latch:()Ljava/util/concurrent/CountDownLatch;
  #20 = Utf8               java/util/concurrent/CountDownLatch
  #21 = Class              #20            // java/util/concurrent/CountDownLatch
  #22 = NameAndType        #16:#17        // countDown:()V
  #23 = Methodref          #21.#22        // java/util/concurrent/CountDownLatch.countDown:()V
  #24 = Utf8               getCount
  #25 = Utf8               ()J
  #26 = NameAndType        #24:#25        // getCount:()J
  #27 = Methodref          #21.#26        // java/util/concurrent/CountDownLatch.getCount:()J
  #28 = Utf8               await
  #29 = NameAndType        #28:#17        // await:()V
  #30 = Methodref          #21.#29        // java/util/concurrent/CountDownLatch.await:()V
  #31 = Utf8               <init>
  #32 = Utf8               (I)V
  #33 = Utf8               count
  #34 = NameAndType        #31:#17        // "<init>":()V
  #35 = Methodref          #4.#34         // java/lang/Object."<init>":()V
  #36 = NameAndType        #31:#32        // "<init>":(I)V
  #37 = Methodref          #21.#36        // java/util/concurrent/CountDownLatch."<init>":(I)V
  #38 = Utf8               I
  #39 = Utf8               Code
  #40 = Utf8               LineNumberTable
  #41 = Utf8               LocalVariableTable
  #42 = Utf8               MethodParameters
  #43 = Utf8               SourceFile
  #44 = Utf8               RuntimeVisibleAnnotations
  #45 = Utf8               ScalaInlineInfo
  #46 = Utf8               ScalaSig
{
  private final transient java.util.concurrent.CountDownLatch latch;
    descriptor: Ljava/util/concurrent/CountDownLatch;
    flags: (0x0092) ACC_PRIVATE, ACC_FINAL, ACC_TRANSIENT

  private final java.util.concurrent.CountDownLatch latch();
    descriptor: ()Ljava/util/concurrent/CountDownLatch;
    flags: (0x0012) ACC_PRIVATE, ACC_FINAL
    Code:
      stack=1, locals=1, args_size=1
         0: aload_0
         1: getfield      #13                 // Field latch:Ljava/util/concurrent/CountDownLatch;
         4: areturn
      LineNumberTable:
        line 52: 0
      LocalVariableTable:
        Start  Length  Slot  Name   Signature
            0       5     0  this   Lorg/scalatest/CountDownLatch;

  public void countDown();
    descriptor: ()V
    flags: (0x0001) ACC_PUBLIC
    Code:
      stack=1, locals=1, args_size=1
         0: aload_0
         1: invokespecial #19                 // Method latch:()Ljava/util/concurrent/CountDownLatch;
         4: invokevirtual #23                 // Method java/util/concurrent/CountDownLatch.countDown:()V
         7: return
      LineNumberTable:
        line 54: 0
      LocalVariableTable:
        Start  Length  Slot  Name   Signature
            0       8     0  this   Lorg/scalatest/CountDownLatch;

  public long getCount();
    descriptor: ()J
    flags: (0x0001) ACC_PUBLIC
    Code:
      stack=2, locals=1, args_size=1
         0: aload_0
         1: invokespecial #19                 // Method latch:()Ljava/util/concurrent/CountDownLatch;
         4: invokevirtual #27                 // Method java/util/concurrent/CountDownLatch.getCount:()J
         7: lreturn
      LineNumberTable:
        line 56: 0
      LocalVariableTable:
        Start  Length  Slot  Name   Signature
            0       8     0  this   Lorg/scalatest/CountDownLatch;

  public void await();
    descriptor: ()V
    flags: (0x0001) ACC_PUBLIC
    Code:
      stack=1, locals=1, args_size=1
         0: aload_0
         1: invokespecial #19                 // Method latch:()Ljava/util/concurrent/CountDownLatch;
         4: invokevirtual #30                 // Method java/util/concurrent/CountDownLatch.await:()V
         7: return
      LineNumberTable:
        line 58: 0
      LocalVariableTable:
        Start  Length  Slot  Name   Signature
            0       8     0  this   Lorg/scalatest/CountDownLatch;

  public org.scalatest.CountDownLatch(int);
    descriptor: (I)V
    flags: (0x0001) ACC_PUBLIC
    Code:
      stack=4, locals=2, args_size=2
         0: aload_0
         1: invokespecial #35                 // Method java/lang/Object."<init>":()V
         4: aload_0
         5: new           #21                 // class java/util/concurrent/CountDownLatch
         8: dup
         9: iload_1
        10: invokespecial #37                 // Method java/util/concurrent/CountDownLatch."<init>":(I)V
        13: putfield      #13                 // Field latch:Ljava/util/concurrent/CountDownLatch;
        16: return
      LineNumberTable:
        line 61: 0
        line 52: 4
        line 50: 16
      LocalVariableTable:
        Start  Length  Slot  Name   Signature
            0      17     0  this   Lorg/scalatest/CountDownLatch;
            0      17     1 count   I
    MethodParameters:
      Name                           Flags
      count                          final
}
SourceFile: "JavaClassesWrappers.scala"
RuntimeVisibleAnnotations:
  0: #6(#7=s#8)
    scala.reflect.ScalaSignature(
      bytes="\u0006\u0005e2Q\u0001C\u0005\u0001\u00135A\u0001\u0002\u0006\u0001\u0003\u0002\u0003\u0006IA\u0006\u0005\u00063\u0001!\tA\u0007\u0005\b=\u0001\u0011\r\u0011\"\u0004 \u0011\u0019I\u0003\u0001)A\u0007A!)a\u0006\u0001C\u0001_!)1\u0007\u0001C\u0001i!)\u0001\b\u0001C\u0001_\tq1i\\;oi\u0012{wO\u001c\'bi\u000eD\'B\u0001\u0006\f\u0003%\u00198-\u00197bi\u0016\u001cHOC\u0001\r\u0003\ry\'oZ\n\u0003\u00019\u0001\"a\u0004\n\u000e\u0003AQ\u0011!E\u0001\u0006g\u000e\fG.Y\u0005\u0003\'A\u0011a!\u00118z%\u00164\u0017!B2pk:$8\u0001\u0001\t\u0003\u001f]I!\u0001\u0007\t\u0003\u0007%sG/\u0001\u0004=S:LGO\u0010\u000b\u00037u\u0001\"\u0001\b\u0001\u000e\u0003%AQ\u0001\u0006\u0002A\u0002Y\tQ\u0001\\1uG\",\u0012\u0001\t\t\u0003C!j\u0011A\t\u0006\u0003G\u0011\n!bY8oGV\u0014(/\u001a8u\u0015\t)c%\u0001\u0003vi&d\'\"A\u0014\u0002\t)\fg/Y\u0005\u0003\u0011\t\na\u0001\\1uG\"\u0004\u0003F\u0001\u0003,!\tyA&\u0003\u0002.!\tIAO]1og&,g\u000e^\u0001\nG>,h\u000e\u001e#po:$\u0012\u0001\r\t\u0003\u001fEJ!A\r\t\u0003\tUs\u0017\u000e^\u0001\tO\u0016$8i\\;oiV\tQ\u0007\u0005\u0002\u0010m%\u0011q\u0007\u0005\u0002\u0005\u0019>tw-A\u0003bo\u0006LG\u000f"
    )
  ScalaInlineInfo: length = 0x1D (unknown attribute)
   01 00 00 05 00 1F 00 20 00 00 1C 00 11 00 00 10
   00 11 00 00 18 00 19 00 00 09 00 0B 01
  ScalaSig: length = 0x3 (unknown attribute)
   05 02 00
