Classfile /Users/mw/Projects/slang-braindump/.jar/jar8/assemble/slang-braindump/assemble/content/org/scalatest/DocSpecLike$MarkupContext.class
  Last modified May 29, 2022; size 2966 bytes
  SHA-256 checksum f677d48893815603cc3c80a48ced9fcbb96853cf230d097a2c6b81786dfb0545
  Compiled from "DocSpecLike.scala"
public class org.scalatest.DocSpecLike$MarkupContext
  minor version: 0
  major version: 52
  flags: (0x0021) ACC_PUBLIC, ACC_SUPER
  this_class: #2                          // org/scalatest/DocSpecLike$MarkupContext
  super_class: #4                         // java/lang/Object
  interfaces: 0, fields: 2, methods: 4, attributes: 4
Constant pool:
    #1 = Utf8               org/scalatest/DocSpecLike$MarkupContext
    #2 = Class              #1            // org/scalatest/DocSpecLike$MarkupContext
    #3 = Utf8               java/lang/Object
    #4 = Class              #3            // java/lang/Object
    #5 = Utf8               DocSpecLike.scala
    #6 = Utf8               org/scalatest/DocSpecLike
    #7 = Class              #6            // org/scalatest/DocSpecLike
    #8 = Utf8               MarkupContext
    #9 = Utf8               org/scalatest/DocSpecLike$MarkupSnippet
   #10 = Class              #9            // org/scalatest/DocSpecLike$MarkupSnippet
   #11 = Utf8               MarkupSnippet
   #12 = Utf8               org/scalatest/DocSpecLike$Snippet
   #13 = Class              #12           // org/scalatest/DocSpecLike$Snippet
   #14 = Utf8               Snippet
   #15 = Utf8               org/scalatest/DocSpecLike$SuiteSnippet
   #16 = Class              #15           // org/scalatest/DocSpecLike$SuiteSnippet
   #17 = Utf8               SuiteSnippet
   #18 = Utf8               sc
   #19 = Utf8               Lscala/StringContext;
   #20 = Utf8               $outer
   #21 = Utf8               Lorg/scalatest/DocSpecLike;
   #22 = Utf8               ()Lscala/StringContext;
   #23 = NameAndType        #18:#19       // sc:Lscala/StringContext;
   #24 = Fieldref           #2.#23        // org/scalatest/DocSpecLike$MarkupContext.sc:Lscala/StringContext;
   #25 = Utf8               this
   #26 = Utf8               Lorg/scalatest/DocSpecLike$MarkupContext;
   #27 = Utf8               markup
   #28 = Utf8               (Lscala/collection/immutable/Seq;)Lscala/collection/immutable/IndexedSeq;
   #29 = Utf8               (Lscala/collection/immutable/Seq<Lorg/scalatest/Suite;>;)Lscala/collection/immutable/IndexedSeq<Lorg/scalatest/DocSpecLike$Snippet;>;
   #30 = Utf8               suites
   #31 = NameAndType        #18:#22       // sc:()Lscala/StringContext;
   #32 = Methodref          #2.#31        // org/scalatest/DocSpecLike$MarkupContext.sc:()Lscala/StringContext;
   #33 = Utf8               scala/StringContext
   #34 = Class              #33           // scala/StringContext
   #35 = Utf8               parts
   #36 = Utf8               ()Lscala/collection/immutable/Seq;
   #37 = NameAndType        #35:#36       // parts:()Lscala/collection/immutable/Seq;
   #38 = Methodref          #34.#37       // scala/StringContext.parts:()Lscala/collection/immutable/Seq;
   #39 = Utf8               scala/collection/immutable/Seq
   #40 = Class              #39           // scala/collection/immutable/Seq
   #41 = Utf8               iterator
   #42 = Utf8               ()Lscala/collection/Iterator;
   #43 = NameAndType        #41:#42       // iterator:()Lscala/collection/Iterator;
   #44 = InterfaceMethodref #40.#43       // scala/collection/immutable/Seq.iterator:()Lscala/collection/Iterator;
   #45 = Utf8               scala/collection/mutable/ListBuffer
   #46 = Class              #45           // scala/collection/mutable/ListBuffer
   #47 = Utf8               <init>
   #48 = Utf8               ()V
   #49 = NameAndType        #47:#48       // "<init>":()V
   #50 = Methodref          #46.#49       // scala/collection/mutable/ListBuffer."<init>":()V
   #51 = Utf8               scala/collection/Iterator
   #52 = Class              #51           // scala/collection/Iterator
   #53 = Utf8               next
   #54 = Utf8               ()Ljava/lang/Object;
   #55 = NameAndType        #53:#54       // next:()Ljava/lang/Object;
   #56 = InterfaceMethodref #52.#55       // scala/collection/Iterator.next:()Ljava/lang/Object;
   #57 = Utf8               java/lang/String
   #58 = Class              #57           // java/lang/String
   #59 = Utf8               isEmpty
   #60 = Utf8               ()Z
   #61 = NameAndType        #59:#60       // isEmpty:()Z
   #62 = Methodref          #58.#61       // java/lang/String.isEmpty:()Z
   #63 = Utf8               org$scalatest$DocSpecLike$MarkupContext$$$outer
   #64 = Utf8               ()Lorg/scalatest/DocSpecLike;
   #65 = NameAndType        #63:#64       // org$scalatest$DocSpecLike$MarkupContext$$$outer:()Lorg/scalatest/DocSpecLike;
   #66 = Methodref          #2.#65        // org/scalatest/DocSpecLike$MarkupContext.org$scalatest$DocSpecLike$MarkupContext$$$outer:()Lorg/scalatest/DocSpecLike;
   #67 = Utf8               (Lorg/scalatest/DocSpecLike;Ljava/lang/String;)V
   #68 = NameAndType        #47:#67       // "<init>":(Lorg/scalatest/DocSpecLike;Ljava/lang/String;)V
   #69 = Methodref          #10.#68       // org/scalatest/DocSpecLike$MarkupSnippet."<init>":(Lorg/scalatest/DocSpecLike;Ljava/lang/String;)V
   #70 = Utf8               $plus$eq
   #71 = Utf8               (Ljava/lang/Object;)Lscala/collection/mutable/Growable;
   #72 = NameAndType        #70:#71       // $plus$eq:(Ljava/lang/Object;)Lscala/collection/mutable/Growable;
   #73 = Methodref          #46.#72       // scala/collection/mutable/ListBuffer.$plus$eq:(Ljava/lang/Object;)Lscala/collection/mutable/Growable;
   #74 = Utf8               scala/runtime/BoxedUnit
   #75 = Class              #74           // scala/runtime/BoxedUnit
   #76 = Utf8               UNIT
   #77 = Utf8               Lscala/runtime/BoxedUnit;
   #78 = NameAndType        #76:#77       // UNIT:Lscala/runtime/BoxedUnit;
   #79 = Fieldref           #75.#78       // scala/runtime/BoxedUnit.UNIT:Lscala/runtime/BoxedUnit;
   #80 = Utf8               hasNext
   #81 = NameAndType        #80:#60       // hasNext:()Z
   #82 = InterfaceMethodref #52.#81       // scala/collection/Iterator.hasNext:()Z
   #83 = Utf8               org/scalatest/Suite
   #84 = Class              #83           // org/scalatest/Suite
   #85 = Utf8               (Lorg/scalatest/DocSpecLike;Lorg/scalatest/Suite;)V
   #86 = NameAndType        #47:#85       // "<init>":(Lorg/scalatest/DocSpecLike;Lorg/scalatest/Suite;)V
   #87 = Methodref          #16.#86       // org/scalatest/DocSpecLike$SuiteSnippet."<init>":(Lorg/scalatest/DocSpecLike;Lorg/scalatest/Suite;)V
   #88 = Utf8               scala/package$
   #89 = Class              #88           // scala/package$
   #90 = Utf8               MODULE$
   #91 = Utf8               Lscala/package$;
   #92 = NameAndType        #90:#91       // MODULE$:Lscala/package$;
   #93 = Fieldref           #89.#92       // scala/package$.MODULE$:Lscala/package$;
   #94 = Utf8               Vector
   #95 = Utf8               ()Lscala/collection/immutable/Vector$;
   #96 = NameAndType        #94:#95       // Vector:()Lscala/collection/immutable/Vector$;
   #97 = Methodref          #89.#96       // scala/package$.Vector:()Lscala/collection/immutable/Vector$;
   #98 = Utf8               scala/collection/immutable/Vector$
   #99 = Class              #98           // scala/collection/immutable/Vector$
  #100 = Utf8               empty
  #101 = Utf8               ()Lscala/collection/immutable/Vector;
  #102 = NameAndType        #100:#101     // empty:()Lscala/collection/immutable/Vector;
  #103 = Methodref          #99.#102      // scala/collection/immutable/Vector$.empty:()Lscala/collection/immutable/Vector;
  #104 = Utf8               scala/collection/immutable/Vector
  #105 = Class              #104          // scala/collection/immutable/Vector
  #106 = Utf8               $plus$plus
  #107 = Utf8               (Lscala/collection/IterableOnce;)Ljava/lang/Object;
  #108 = NameAndType        #106:#107     // $plus$plus:(Lscala/collection/IterableOnce;)Ljava/lang/Object;
  #109 = Methodref          #105.#108     // scala/collection/immutable/Vector.$plus$plus:(Lscala/collection/IterableOnce;)Ljava/lang/Object;
  #110 = Utf8               scala/collection/immutable/IndexedSeq
  #111 = Class              #110          // scala/collection/immutable/IndexedSeq
  #112 = Utf8               stringIt
  #113 = Utf8               Lscala/collection/Iterator;
  #114 = Utf8               suiteIt
  #115 = Utf8               buf
  #116 = Utf8               Lscala/collection/mutable/ListBuffer;
  #117 = Utf8               initialString
  #118 = Utf8               Ljava/lang/String;
  #119 = Utf8               Lscala/collection/immutable/Seq;
  #120 = NameAndType        #20:#21       // $outer:Lorg/scalatest/DocSpecLike;
  #121 = Fieldref           #2.#120       // org/scalatest/DocSpecLike$MarkupContext.$outer:Lorg/scalatest/DocSpecLike;
  #122 = Utf8               (Lorg/scalatest/DocSpecLike;Lscala/StringContext;)V
  #123 = Methodref          #4.#49        // java/lang/Object."<init>":()V
  #124 = Utf8               Code
  #125 = Utf8               LineNumberTable
  #126 = Utf8               LocalVariableTable
  #127 = Utf8               StackMapTable
  #128 = Utf8               Signature
  #129 = Utf8               MethodParameters
  #130 = Utf8               InnerClasses
  #131 = Utf8               SourceFile
  #132 = Utf8               ScalaInlineInfo
  #133 = Utf8               Scala
{
  private final scala.StringContext sc;
    descriptor: Lscala/StringContext;
    flags: (0x0012) ACC_PRIVATE, ACC_FINAL

  public final org.scalatest.DocSpecLike $outer;
    descriptor: Lorg/scalatest/DocSpecLike;
    flags: (0x1011) ACC_PUBLIC, ACC_FINAL, ACC_SYNTHETIC

  public scala.StringContext sc();
    descriptor: ()Lscala/StringContext;
    flags: (0x0001) ACC_PUBLIC
    Code:
      stack=1, locals=1, args_size=1
         0: aload_0
         1: getfield      #24                 // Field sc:Lscala/StringContext;
         4: areturn
      LineNumberTable:
        line 50: 0
      LocalVariableTable:
        Start  Length  Slot  Name   Signature
            0       5     0  this   Lorg/scalatest/DocSpecLike$MarkupContext;

  public scala.collection.immutable.IndexedSeq<org.scalatest.DocSpecLike$Snippet> markup(scala.collection.immutable.Seq<org.scalatest.Suite>);
    descriptor: (Lscala/collection/immutable/Seq;)Lscala/collection/immutable/IndexedSeq;
    flags: (0x0001) ACC_PUBLIC
    Code:
      stack=5, locals=6, args_size=2
         0: aload_0
         1: invokevirtual #32                 // Method sc:()Lscala/StringContext;
         4: invokevirtual #38                 // Method scala/StringContext.parts:()Lscala/collection/immutable/Seq;
         7: invokeinterface #44,  1           // InterfaceMethod scala/collection/immutable/Seq.iterator:()Lscala/collection/Iterator;
        12: astore_2
        13: aload_1
        14: invokeinterface #44,  1           // InterfaceMethod scala/collection/immutable/Seq.iterator:()Lscala/collection/Iterator;
        19: astore_3
        20: new           #46                 // class scala/collection/mutable/ListBuffer
        23: dup
        24: invokespecial #50                 // Method scala/collection/mutable/ListBuffer."<init>":()V
        27: astore        4
        29: aload_2
        30: invokeinterface #56,  1           // InterfaceMethod scala/collection/Iterator.next:()Ljava/lang/Object;
        35: checkcast     #58                 // class java/lang/String
        38: astore        5
        40: aload         5
        42: invokevirtual #62                 // Method java/lang/String.isEmpty:()Z
        45: ifne          69
        48: aload         4
        50: new           #10                 // class org/scalatest/DocSpecLike$MarkupSnippet
        53: dup
        54: aload_0
        55: invokevirtual #66                 // Method org$scalatest$DocSpecLike$MarkupContext$$$outer:()Lorg/scalatest/DocSpecLike;
        58: aload         5
        60: invokespecial #69                 // Method org/scalatest/DocSpecLike$MarkupSnippet."<init>":(Lorg/scalatest/DocSpecLike;Ljava/lang/String;)V
        63: invokevirtual #73                 // Method scala/collection/mutable/ListBuffer.$plus$eq:(Ljava/lang/Object;)Lscala/collection/mutable/Growable;
        66: goto          72
        69: getstatic     #79                 // Field scala/runtime/BoxedUnit.UNIT:Lscala/runtime/BoxedUnit;
        72: pop
        73: aload_2
        74: invokeinterface #82,  1           // InterfaceMethod scala/collection/Iterator.hasNext:()Z
        79: ifeq          137
        82: aload         4
        84: new           #16                 // class org/scalatest/DocSpecLike$SuiteSnippet
        87: dup
        88: aload_0
        89: invokevirtual #66                 // Method org$scalatest$DocSpecLike$MarkupContext$$$outer:()Lorg/scalatest/DocSpecLike;
        92: aload_3
        93: invokeinterface #56,  1           // InterfaceMethod scala/collection/Iterator.next:()Ljava/lang/Object;
        98: checkcast     #84                 // class org/scalatest/Suite
       101: invokespecial #87                 // Method org/scalatest/DocSpecLike$SuiteSnippet."<init>":(Lorg/scalatest/DocSpecLike;Lorg/scalatest/Suite;)V
       104: invokevirtual #73                 // Method scala/collection/mutable/ListBuffer.$plus$eq:(Ljava/lang/Object;)Lscala/collection/mutable/Growable;
       107: pop
       108: aload         4
       110: new           #10                 // class org/scalatest/DocSpecLike$MarkupSnippet
       113: dup
       114: aload_0
       115: invokevirtual #66                 // Method org$scalatest$DocSpecLike$MarkupContext$$$outer:()Lorg/scalatest/DocSpecLike;
       118: aload_2
       119: invokeinterface #56,  1           // InterfaceMethod scala/collection/Iterator.next:()Ljava/lang/Object;
       124: checkcast     #58                 // class java/lang/String
       127: invokespecial #69                 // Method org/scalatest/DocSpecLike$MarkupSnippet."<init>":(Lorg/scalatest/DocSpecLike;Ljava/lang/String;)V
       130: invokevirtual #73                 // Method scala/collection/mutable/ListBuffer.$plus$eq:(Ljava/lang/Object;)Lscala/collection/mutable/Growable;
       133: pop
       134: goto          73
       137: getstatic     #93                 // Field scala/package$.MODULE$:Lscala/package$;
       140: invokevirtual #97                 // Method scala/package$.Vector:()Lscala/collection/immutable/Vector$;
       143: invokevirtual #103                // Method scala/collection/immutable/Vector$.empty:()Lscala/collection/immutable/Vector;
       146: aload         4
       148: invokevirtual #109                // Method scala/collection/immutable/Vector.$plus$plus:(Lscala/collection/IterableOnce;)Ljava/lang/Object;
       151: checkcast     #111                // class scala/collection/immutable/IndexedSeq
       154: areturn
      StackMapTable: number_of_entries = 4
        frame_type = 255 /* full_frame */
          offset_delta = 69
          locals = [ class org/scalatest/DocSpecLike$MarkupContext, class scala/collection/immutable/Seq, class scala/collection/Iterator, class scala/collection/Iterator, class scala/collection/mutable/ListBuffer, class java/lang/String ]
          stack = []
        frame_type = 66 /* same_locals_1_stack_item */
          stack = [ class java/lang/Object ]
        frame_type = 0 /* same */
        frame_type = 63 /* same */
      LineNumberTable:
        line 52: 0
        line 53: 13
        line 56: 20
        line 57: 29
        line 58: 40
        line 59: 48
        line 58: 69
        line 62: 73
        line 63: 82
        line 64: 108
        line 62: 134
        line 67: 137
      LocalVariableTable:
        Start  Length  Slot  Name   Signature
           13     141     2 stringIt   Lscala/collection/Iterator;
           20     134     3 suiteIt   Lscala/collection/Iterator;
           29     125     4   buf   Lscala/collection/mutable/ListBuffer;
           40     114     5 initialString   Ljava/lang/String;
            0     155     0  this   Lorg/scalatest/DocSpecLike$MarkupContext;
            0     155     1 suites   Lscala/collection/immutable/Seq;
    Signature: #29                          // (Lscala/collection/immutable/Seq<Lorg/scalatest/Suite;>;)Lscala/collection/immutable/IndexedSeq<Lorg/scalatest/DocSpecLike$Snippet;>;
    MethodParameters:
      Name                           Flags
      suites                         final

  public org.scalatest.DocSpecLike org$scalatest$DocSpecLike$MarkupContext$$$outer();
    descriptor: ()Lorg/scalatest/DocSpecLike;
    flags: (0x1001) ACC_PUBLIC, ACC_SYNTHETIC
    Code:
      stack=1, locals=1, args_size=1
         0: aload_0
         1: getfield      #121                // Field $outer:Lorg/scalatest/DocSpecLike;
         4: areturn
      LineNumberTable:
        line 50: 0
      LocalVariableTable:
        Start  Length  Slot  Name   Signature
            0       5     0  this   Lorg/scalatest/DocSpecLike$MarkupContext;

  public org.scalatest.DocSpecLike$MarkupContext(org.scalatest.DocSpecLike, scala.StringContext);
    descriptor: (Lorg/scalatest/DocSpecLike;Lscala/StringContext;)V
    flags: (0x0001) ACC_PUBLIC
    Code:
      stack=2, locals=3, args_size=3
         0: aload_0
         1: aload_2
         2: putfield      #24                 // Field sc:Lscala/StringContext;
         5: aload_1
         6: ifnonnull     11
         9: aconst_null
        10: athrow
        11: aload_0
        12: aload_1
        13: putfield      #121                // Field $outer:Lorg/scalatest/DocSpecLike;
        16: aload_0
        17: invokespecial #123                // Method java/lang/Object."<init>":()V
        20: return
      StackMapTable: number_of_entries = 1
        frame_type = 11 /* same */
      LineNumberTable:
        line 50: 0
        line 71: 16
        line 50: 20
      LocalVariableTable:
        Start  Length  Slot  Name   Signature
            0      21     0  this   Lorg/scalatest/DocSpecLike$MarkupContext;
            0      21     1 $outer   Lorg/scalatest/DocSpecLike;
            0      21     2    sc   Lscala/StringContext;
    MethodParameters:
      Name                           Flags
      $outer                         final synthetic
      sc                             final
}
InnerClasses:
  public #8= #2 of #7;                    // MarkupContext=class org/scalatest/DocSpecLike$MarkupContext of class org/scalatest/DocSpecLike
  public #11= #10 of #7;                  // MarkupSnippet=class org/scalatest/DocSpecLike$MarkupSnippet of class org/scalatest/DocSpecLike
  public abstract #14= #13 of #7;         // Snippet=class org/scalatest/DocSpecLike$Snippet of class org/scalatest/DocSpecLike
  public #17= #16 of #7;                  // SuiteSnippet=class org/scalatest/DocSpecLike$SuiteSnippet of class org/scalatest/DocSpecLike
SourceFile: "DocSpecLike.scala"
  ScalaInlineInfo: length = 0x18 (unknown attribute)
   01 00 00 04 00 2F 00 7A 00 00 1B 00 1C 00 00 3F
   00 40 00 00 12 00 16 00
  Scala: length = 0x0 (unknown attribute)

