Classfile /Users/mw/Projects/slang-braindump/.jar/jar8/assemble/slang-braindump/assemble/content/org/scalatest/DocSpecLike$Snippet.class
  Last modified May 29, 2022; size 1650 bytes
  SHA-256 checksum 243b632ea64030471399326bf714f9a64ba23e18b475249fc38469cf4e825c90
  Compiled from "DocSpecLike.scala"
public abstract class org.scalatest.DocSpecLike$Snippet implements scala.Product,java.io.Serializable
  minor version: 0
  major version: 52
  flags: (0x0421) ACC_PUBLIC, ACC_SUPER, ACC_ABSTRACT
  this_class: #2                          // org/scalatest/DocSpecLike$Snippet
  super_class: #4                         // java/lang/Object
  interfaces: 2, fields: 1, methods: 6, attributes: 4
Constant pool:
   #1 = Utf8               org/scalatest/DocSpecLike$Snippet
   #2 = Class              #1             // org/scalatest/DocSpecLike$Snippet
   #3 = Utf8               java/lang/Object
   #4 = Class              #3             // java/lang/Object
   #5 = Utf8               scala/Product
   #6 = Class              #5             // scala/Product
   #7 = Utf8               java/io/Serializable
   #8 = Class              #7             // java/io/Serializable
   #9 = Utf8               DocSpecLike.scala
  #10 = Utf8               org/scalatest/DocSpecLike
  #11 = Class              #10            // org/scalatest/DocSpecLike
  #12 = Utf8               Snippet
  #13 = Utf8               $outer
  #14 = Utf8               Lorg/scalatest/DocSpecLike;
  #15 = Utf8               productIterator
  #16 = Utf8               ()Lscala/collection/Iterator;
  #17 = Utf8               ()Lscala/collection/Iterator<Ljava/lang/Object;>;
  #18 = Utf8               productIterator$
  #19 = Utf8               (Lscala/Product;)Lscala/collection/Iterator;
  #20 = NameAndType        #18:#19        // productIterator$:(Lscala/Product;)Lscala/collection/Iterator;
  #21 = InterfaceMethodref #6.#20         // scala/Product.productIterator$:(Lscala/Product;)Lscala/collection/Iterator;
  #22 = Utf8               this
  #23 = Utf8               Lorg/scalatest/DocSpecLike$Snippet;
  #24 = Utf8               productPrefix
  #25 = Utf8               ()Ljava/lang/String;
  #26 = Utf8               productPrefix$
  #27 = Utf8               (Lscala/Product;)Ljava/lang/String;
  #28 = NameAndType        #26:#27        // productPrefix$:(Lscala/Product;)Ljava/lang/String;
  #29 = InterfaceMethodref #6.#28         // scala/Product.productPrefix$:(Lscala/Product;)Ljava/lang/String;
  #30 = Utf8               productElementName
  #31 = Utf8               (I)Ljava/lang/String;
  #32 = Utf8               n
  #33 = Utf8               productElementName$
  #34 = Utf8               (Lscala/Product;I)Ljava/lang/String;
  #35 = NameAndType        #33:#34        // productElementName$:(Lscala/Product;I)Ljava/lang/String;
  #36 = InterfaceMethodref #6.#35         // scala/Product.productElementName$:(Lscala/Product;I)Ljava/lang/String;
  #37 = Utf8               I
  #38 = Utf8               productElementNames
  #39 = Utf8               ()Lscala/collection/Iterator<Ljava/lang/String;>;
  #40 = Utf8               productElementNames$
  #41 = NameAndType        #40:#19        // productElementNames$:(Lscala/Product;)Lscala/collection/Iterator;
  #42 = InterfaceMethodref #6.#41         // scala/Product.productElementNames$:(Lscala/Product;)Lscala/collection/Iterator;
  #43 = Utf8               org$scalatest$DocSpecLike$Snippet$$$outer
  #44 = Utf8               ()Lorg/scalatest/DocSpecLike;
  #45 = NameAndType        #13:#14        // $outer:Lorg/scalatest/DocSpecLike;
  #46 = Fieldref           #2.#45         // org/scalatest/DocSpecLike$Snippet.$outer:Lorg/scalatest/DocSpecLike;
  #47 = Utf8               <init>
  #48 = Utf8               (Lorg/scalatest/DocSpecLike;)V
  #49 = Utf8               ()V
  #50 = NameAndType        #47:#49        // "<init>":()V
  #51 = Methodref          #4.#50         // java/lang/Object."<init>":()V
  #52 = Utf8               $init$
  #53 = Utf8               (Lscala/Product;)V
  #54 = NameAndType        #52:#53        // $init$:(Lscala/Product;)V
  #55 = InterfaceMethodref #6.#54         // scala/Product.$init$:(Lscala/Product;)V
  #56 = Utf8               Code
  #57 = Utf8               LineNumberTable
  #58 = Utf8               LocalVariableTable
  #59 = Utf8               Signature
  #60 = Utf8               MethodParameters
  #61 = Utf8               StackMapTable
  #62 = Utf8               InnerClasses
  #63 = Utf8               SourceFile
  #64 = Utf8               ScalaInlineInfo
  #65 = Utf8               Scala
{
  public final org.scalatest.DocSpecLike $outer;
    descriptor: Lorg/scalatest/DocSpecLike;
    flags: (0x1011) ACC_PUBLIC, ACC_FINAL, ACC_SYNTHETIC

  public scala.collection.Iterator<java.lang.Object> productIterator();
    descriptor: ()Lscala/collection/Iterator;
    flags: (0x0001) ACC_PUBLIC
    Code:
      stack=1, locals=1, args_size=1
         0: aload_0
         1: invokestatic  #21                 // InterfaceMethod scala/Product.productIterator$:(Lscala/Product;)Lscala/collection/Iterator;
         4: areturn
      LineNumberTable:
        line 46: 0
      LocalVariableTable:
        Start  Length  Slot  Name   Signature
            0       5     0  this   Lorg/scalatest/DocSpecLike$Snippet;
    Signature: #17                          // ()Lscala/collection/Iterator<Ljava/lang/Object;>;

  public java.lang.String productPrefix();
    descriptor: ()Ljava/lang/String;
    flags: (0x0001) ACC_PUBLIC
    Code:
      stack=1, locals=1, args_size=1
         0: aload_0
         1: invokestatic  #29                 // InterfaceMethod scala/Product.productPrefix$:(Lscala/Product;)Ljava/lang/String;
         4: areturn
      LineNumberTable:
        line 46: 0
      LocalVariableTable:
        Start  Length  Slot  Name   Signature
            0       5     0  this   Lorg/scalatest/DocSpecLike$Snippet;

  public java.lang.String productElementName(int);
    descriptor: (I)Ljava/lang/String;
    flags: (0x0001) ACC_PUBLIC
    Code:
      stack=2, locals=2, args_size=2
         0: aload_0
         1: iload_1
         2: invokestatic  #36                 // InterfaceMethod scala/Product.productElementName$:(Lscala/Product;I)Ljava/lang/String;
         5: areturn
      LineNumberTable:
        line 46: 0
      LocalVariableTable:
        Start  Length  Slot  Name   Signature
            0       6     0  this   Lorg/scalatest/DocSpecLike$Snippet;
            0       6     1     n   I
    MethodParameters:
      Name                           Flags
      n                              final

  public scala.collection.Iterator<java.lang.String> productElementNames();
    descriptor: ()Lscala/collection/Iterator;
    flags: (0x0001) ACC_PUBLIC
    Code:
      stack=1, locals=1, args_size=1
         0: aload_0
         1: invokestatic  #42                 // InterfaceMethod scala/Product.productElementNames$:(Lscala/Product;)Lscala/collection/Iterator;
         4: areturn
      LineNumberTable:
        line 46: 0
      LocalVariableTable:
        Start  Length  Slot  Name   Signature
            0       5     0  this   Lorg/scalatest/DocSpecLike$Snippet;
    Signature: #39                          // ()Lscala/collection/Iterator<Ljava/lang/String;>;

  public org.scalatest.DocSpecLike org$scalatest$DocSpecLike$Snippet$$$outer();
    descriptor: ()Lorg/scalatest/DocSpecLike;
    flags: (0x1001) ACC_PUBLIC, ACC_SYNTHETIC
    Code:
      stack=1, locals=1, args_size=1
         0: aload_0
         1: getfield      #46                 // Field $outer:Lorg/scalatest/DocSpecLike;
         4: areturn
      LineNumberTable:
        line 46: 0
      LocalVariableTable:
        Start  Length  Slot  Name   Signature
            0       5     0  this   Lorg/scalatest/DocSpecLike$Snippet;

  public org.scalatest.DocSpecLike$Snippet(org.scalatest.DocSpecLike);
    descriptor: (Lorg/scalatest/DocSpecLike;)V
    flags: (0x0001) ACC_PUBLIC
    Code:
      stack=2, locals=2, args_size=2
         0: aload_1
         1: ifnonnull     6
         4: aconst_null
         5: athrow
         6: aload_0
         7: aload_1
         8: putfield      #46                 // Field $outer:Lorg/scalatest/DocSpecLike;
        11: aload_0
        12: invokespecial #51                 // Method java/lang/Object."<init>":()V
        15: aload_0
        16: invokestatic  #55                 // InterfaceMethod scala/Product.$init$:(Lscala/Product;)V
        19: return
      StackMapTable: number_of_entries = 1
        frame_type = 6 /* same */
      LineNumberTable:
        line 46: 0
      LocalVariableTable:
        Start  Length  Slot  Name   Signature
            0      20     0  this   Lorg/scalatest/DocSpecLike$Snippet;
            0      20     1 $outer   Lorg/scalatest/DocSpecLike;
    MethodParameters:
      Name                           Flags
      $outer                         final synthetic
}
InnerClasses:
  public abstract #12= #2 of #11;         // Snippet=class org/scalatest/DocSpecLike$Snippet of class org/scalatest/DocSpecLike
SourceFile: "DocSpecLike.scala"
  ScalaInlineInfo: length = 0x22 (unknown attribute)
   01 00 00 06 00 2F 00 30 00 00 2B 00 2C 00 00 1E
   00 1F 00 00 26 00 10 00 00 0F 00 10 00 00 18 00
   19 00
  Scala: length = 0x0 (unknown attribute)

