Classfile /Users/mw/Projects/slang-braindump/.jar/jar8/assemble/slang-braindump/assemble/content/org/scalatest/Fact$MidSentenceSimplifiedFactMessage$.class
  Last modified May 29, 2022; size 2103 bytes
  SHA-256 checksum eb0eb6630add6de0c1c840bb56d69f38d39f37563ff1e1a01d8f240b138c1c96
  Compiled from "Fact.scala"
public class org.scalatest.Fact$MidSentenceSimplifiedFactMessage$ extends scala.runtime.AbstractFunction1<org.scalatest.Fact, org.scalatest.Fact$MidSentenceSimplifiedFactMessage> implements java.io.Serializable
  minor version: 0
  major version: 52
  flags: (0x0021) ACC_PUBLIC, ACC_SUPER
  this_class: #2                          // org/scalatest/Fact$MidSentenceSimplifiedFactMessage$
  super_class: #5                         // scala/runtime/AbstractFunction1
  interfaces: 1, fields: 1, methods: 7, attributes: 5
Constant pool:
   #1 = Utf8               org/scalatest/Fact$MidSentenceSimplifiedFactMessage$
   #2 = Class              #1             // org/scalatest/Fact$MidSentenceSimplifiedFactMessage$
   #3 = Utf8               Lscala/runtime/AbstractFunction1<Lorg/scalatest/Fact;Lorg/scalatest/Fact$MidSentenceSimplifiedFactMessage;>;Ljava/io/Serializable;
   #4 = Utf8               scala/runtime/AbstractFunction1
   #5 = Class              #4             // scala/runtime/AbstractFunction1
   #6 = Utf8               java/io/Serializable
   #7 = Class              #6             // java/io/Serializable
   #8 = Utf8               Fact.scala
   #9 = Utf8               org/scalatest/Fact$MidSentenceSimplifiedFactMessage
  #10 = Class              #9             // org/scalatest/Fact$MidSentenceSimplifiedFactMessage
  #11 = Utf8               org/scalatest/Fact
  #12 = Class              #11            // org/scalatest/Fact
  #13 = Utf8               MidSentenceSimplifiedFactMessage
  #14 = Utf8               MidSentenceSimplifiedFactMessage$
  #15 = Utf8               MODULE$
  #16 = Utf8               Lorg/scalatest/Fact$MidSentenceSimplifiedFactMessage$;
  #17 = Utf8               <clinit>
  #18 = Utf8               ()V
  #19 = Utf8               <init>
  #20 = NameAndType        #19:#18        // "<init>":()V
  #21 = Methodref          #2.#20         // org/scalatest/Fact$MidSentenceSimplifiedFactMessage$."<init>":()V
  #22 = NameAndType        #15:#16        // MODULE$:Lorg/scalatest/Fact$MidSentenceSimplifiedFactMessage$;
  #23 = Fieldref           #2.#22         // org/scalatest/Fact$MidSentenceSimplifiedFactMessage$.MODULE$:Lorg/scalatest/Fact$MidSentenceSimplifiedFactMessage$;
  #24 = Utf8               toString
  #25 = Utf8               ()Ljava/lang/String;
  #26 = String             #13            // MidSentenceSimplifiedFactMessage
  #27 = Utf8               this
  #28 = Utf8               apply
  #29 = Utf8               (Lorg/scalatest/Fact;)Lorg/scalatest/Fact$MidSentenceSimplifiedFactMessage;
  #30 = Utf8               fact
  #31 = Utf8               (Lorg/scalatest/Fact;)V
  #32 = NameAndType        #19:#31        // "<init>":(Lorg/scalatest/Fact;)V
  #33 = Methodref          #10.#32        // org/scalatest/Fact$MidSentenceSimplifiedFactMessage."<init>":(Lorg/scalatest/Fact;)V
  #34 = Utf8               Lorg/scalatest/Fact;
  #35 = Utf8               unapply
  #36 = Utf8               (Lorg/scalatest/Fact$MidSentenceSimplifiedFactMessage;)Lscala/Option;
  #37 = Utf8               (Lorg/scalatest/Fact$MidSentenceSimplifiedFactMessage;)Lscala/Option<Lorg/scalatest/Fact;>;
  #38 = Utf8               x$0
  #39 = Utf8               scala/None$
  #40 = Class              #39            // scala/None$
  #41 = Utf8               Lscala/None$;
  #42 = NameAndType        #15:#41        // MODULE$:Lscala/None$;
  #43 = Fieldref           #40.#42        // scala/None$.MODULE$:Lscala/None$;
  #44 = Utf8               scala/Some
  #45 = Class              #44            // scala/Some
  #46 = Utf8               ()Lorg/scalatest/Fact;
  #47 = NameAndType        #30:#46        // fact:()Lorg/scalatest/Fact;
  #48 = Methodref          #10.#47        // org/scalatest/Fact$MidSentenceSimplifiedFactMessage.fact:()Lorg/scalatest/Fact;
  #49 = Utf8               (Ljava/lang/Object;)V
  #50 = NameAndType        #19:#49        // "<init>":(Ljava/lang/Object;)V
  #51 = Methodref          #45.#50        // scala/Some."<init>":(Ljava/lang/Object;)V
  #52 = Utf8               Lorg/scalatest/Fact$MidSentenceSimplifiedFactMessage;
  #53 = Utf8               scala/Option
  #54 = Class              #53            // scala/Option
  #55 = Utf8               writeReplace
  #56 = Utf8               ()Ljava/lang/Object;
  #57 = Utf8               scala/runtime/ModuleSerializationProxy
  #58 = Class              #57            // scala/runtime/ModuleSerializationProxy
  #59 = Utf8               (Ljava/lang/Class;)V
  #60 = NameAndType        #19:#59        // "<init>":(Ljava/lang/Class;)V
  #61 = Methodref          #58.#60        // scala/runtime/ModuleSerializationProxy."<init>":(Ljava/lang/Class;)V
  #62 = Utf8               (Ljava/lang/Object;)Ljava/lang/Object;
  #63 = Utf8               v1
  #64 = NameAndType        #28:#29        // apply:(Lorg/scalatest/Fact;)Lorg/scalatest/Fact$MidSentenceSimplifiedFactMessage;
  #65 = Methodref          #2.#64         // org/scalatest/Fact$MidSentenceSimplifiedFactMessage$.apply:(Lorg/scalatest/Fact;)Lorg/scalatest/Fact$MidSentenceSimplifiedFactMessage;
  #66 = Utf8               Ljava/lang/Object;
  #67 = Methodref          #5.#20         // scala/runtime/AbstractFunction1."<init>":()V
  #68 = Utf8               Code
  #69 = Utf8               LineNumberTable
  #70 = Utf8               LocalVariableTable
  #71 = Utf8               MethodParameters
  #72 = Utf8               StackMapTable
  #73 = Utf8               Signature
  #74 = Utf8               InnerClasses
  #75 = Utf8               SourceFile
  #76 = Utf8               ScalaInlineInfo
  #77 = Utf8               Scala
{
  public static final org.scalatest.Fact$MidSentenceSimplifiedFactMessage$ MODULE$;
    descriptor: Lorg/scalatest/Fact$MidSentenceSimplifiedFactMessage$;
    flags: (0x0019) ACC_PUBLIC, ACC_STATIC, ACC_FINAL

  public static {};
    descriptor: ()V
    flags: (0x0009) ACC_PUBLIC, ACC_STATIC
    Code:
      stack=2, locals=0, args_size=0
         0: new           #2                  // class org/scalatest/Fact$MidSentenceSimplifiedFactMessage$
         3: dup
         4: invokespecial #21                 // Method "<init>":()V
         7: putstatic     #23                 // Field MODULE$:Lorg/scalatest/Fact$MidSentenceSimplifiedFactMessage$;
        10: return
      LineNumberTable:
        line 1126: 0

  public final java.lang.String toString();
    descriptor: ()Ljava/lang/String;
    flags: (0x0011) ACC_PUBLIC, ACC_FINAL
    Code:
      stack=1, locals=1, args_size=1
         0: ldc           #26                 // String MidSentenceSimplifiedFactMessage
         2: areturn
      LineNumberTable:
        line 1126: 0
      LocalVariableTable:
        Start  Length  Slot  Name   Signature
            0       3     0  this   Lorg/scalatest/Fact$MidSentenceSimplifiedFactMessage$;

  public org.scalatest.Fact$MidSentenceSimplifiedFactMessage apply(org.scalatest.Fact);
    descriptor: (Lorg/scalatest/Fact;)Lorg/scalatest/Fact$MidSentenceSimplifiedFactMessage;
    flags: (0x0001) ACC_PUBLIC
    Code:
      stack=3, locals=2, args_size=2
         0: new           #10                 // class org/scalatest/Fact$MidSentenceSimplifiedFactMessage
         3: dup
         4: aload_1
         5: invokespecial #33                 // Method org/scalatest/Fact$MidSentenceSimplifiedFactMessage."<init>":(Lorg/scalatest/Fact;)V
         8: areturn
      LineNumberTable:
        line 1126: 0
      LocalVariableTable:
        Start  Length  Slot  Name   Signature
            0       9     0  this   Lorg/scalatest/Fact$MidSentenceSimplifiedFactMessage$;
            0       9     1  fact   Lorg/scalatest/Fact;
    MethodParameters:
      Name                           Flags
      fact                           final

  public scala.Option<org.scalatest.Fact> unapply(org.scalatest.Fact$MidSentenceSimplifiedFactMessage);
    descriptor: (Lorg/scalatest/Fact$MidSentenceSimplifiedFactMessage;)Lscala/Option;
    flags: (0x0001) ACC_PUBLIC
    Code:
      stack=3, locals=2, args_size=2
         0: aload_1
         1: ifnonnull     10
         4: getstatic     #43                 // Field scala/None$.MODULE$:Lscala/None$;
         7: goto          21
        10: new           #45                 // class scala/Some
        13: dup
        14: aload_1
        15: invokevirtual #48                 // Method org/scalatest/Fact$MidSentenceSimplifiedFactMessage.fact:()Lorg/scalatest/Fact;
        18: invokespecial #51                 // Method scala/Some."<init>":(Ljava/lang/Object;)V
        21: areturn
      StackMapTable: number_of_entries = 2
        frame_type = 10 /* same */
        frame_type = 74 /* same_locals_1_stack_item */
          stack = [ class scala/Option ]
      LineNumberTable:
        line 1126: 0
      LocalVariableTable:
        Start  Length  Slot  Name   Signature
            0      22     0  this   Lorg/scalatest/Fact$MidSentenceSimplifiedFactMessage$;
            0      22     1   x$0   Lorg/scalatest/Fact$MidSentenceSimplifiedFactMessage;
    Signature: #37                          // (Lorg/scalatest/Fact$MidSentenceSimplifiedFactMessage;)Lscala/Option<Lorg/scalatest/Fact;>;
    MethodParameters:
      Name                           Flags
      x$0                            final

  private java.lang.Object writeReplace();
    descriptor: ()Ljava/lang/Object;
    flags: (0x0002) ACC_PRIVATE
    Code:
      stack=3, locals=1, args_size=1
         0: new           #58                 // class scala/runtime/ModuleSerializationProxy
         3: dup
         4: ldc           #2                  // class org/scalatest/Fact$MidSentenceSimplifiedFactMessage$
         6: invokespecial #61                 // Method scala/runtime/ModuleSerializationProxy."<init>":(Ljava/lang/Class;)V
         9: areturn
      LineNumberTable:
        line 1126: 0
      LocalVariableTable:
        Start  Length  Slot  Name   Signature
            0      10     0  this   Lorg/scalatest/Fact$MidSentenceSimplifiedFactMessage$;

  public java.lang.Object apply(java.lang.Object);
    descriptor: (Ljava/lang/Object;)Ljava/lang/Object;
    flags: (0x1041) ACC_PUBLIC, ACC_BRIDGE, ACC_SYNTHETIC
    Code:
      stack=2, locals=2, args_size=2
         0: aload_0
         1: aload_1
         2: checkcast     #12                 // class org/scalatest/Fact
         5: invokevirtual #65                 // Method apply:(Lorg/scalatest/Fact;)Lorg/scalatest/Fact$MidSentenceSimplifiedFactMessage;
         8: areturn
      LineNumberTable:
        line 1126: 0
      LocalVariableTable:
        Start  Length  Slot  Name   Signature
            0       9     0  this   Lorg/scalatest/Fact$MidSentenceSimplifiedFactMessage$;
            0       9     1    v1   Ljava/lang/Object;
    MethodParameters:
      Name                           Flags
      v1                             final

  public org.scalatest.Fact$MidSentenceSimplifiedFactMessage$();
    descriptor: ()V
    flags: (0x0001) ACC_PUBLIC
    Code:
      stack=1, locals=1, args_size=1
         0: aload_0
         1: invokespecial #67                 // Method scala/runtime/AbstractFunction1."<init>":()V
         4: return
      LineNumberTable:
        line 1126: 0
      LocalVariableTable:
        Start  Length  Slot  Name   Signature
            0       5     0  this   Lorg/scalatest/Fact$MidSentenceSimplifiedFactMessage$;
}
InnerClasses:
  public static #13= #10 of #12;          // MidSentenceSimplifiedFactMessage=class org/scalatest/Fact$MidSentenceSimplifiedFactMessage of class org/scalatest/Fact
  public static #14= #2 of #12;           // MidSentenceSimplifiedFactMessage$=class org/scalatest/Fact$MidSentenceSimplifiedFactMessage$ of class org/scalatest/Fact
Signature: #3                           // Lscala/runtime/AbstractFunction1<Lorg/scalatest/Fact;Lorg/scalatest/Fact$MidSentenceSimplifiedFactMessage;>;Ljava/io/Serializable;
SourceFile: "Fact.scala"
  ScalaInlineInfo: length = 0x22 (unknown attribute)
   01 01 00 06 00 13 00 12 01 00 1C 00 3E 01 00 1C
   00 1D 01 00 18 00 19 01 00 23 00 24 01 00 37 00
   38 01
  Scala: length = 0x0 (unknown attribute)

