Classfile /Users/mw/Projects/slang-braindump/.jar/jar8/assemble/slang-braindump/assemble/content/org/scalatest/Fact.class
  Last modified May 29, 2022; size 24977 bytes
  SHA-256 checksum f1410b4f261da2d5ec40d429f134628dc4b8ea029e0220226935c8b169a09337
  Compiled from "Fact.scala"
public abstract class org.scalatest.Fact
  minor version: 0
  major version: 52
  flags: (0x0421) ACC_PUBLIC, ACC_SUPER, ACC_ABSTRACT
  this_class: #2                          // org/scalatest/Fact
  super_class: #4                         // java/lang/Object
  interfaces: 0, fields: 2, methods: 41, attributes: 6
Constant pool:
    #1 = Utf8               org/scalatest/Fact
    #2 = Class              #1            // org/scalatest/Fact
    #3 = Utf8               java/lang/Object
    #4 = Class              #3            // java/lang/Object
    #5 = Utf8               Fact.scala
    #6 = Utf8               Lscala/reflect/ScalaSignature;
    #7 = Utf8               bytes
    #8 = Utf8               \u0006\u0005!uhACBJ\u0007+\u000b\tc!&\u0004\u001e\"911\u0016\u0001\u0005\u0002\r=\u0006\"CB[\u0001\t\u0007i\u0011AB\\\u0011%\u0019y\r\u0001b\u0001\u000e\u0003\u00199\fC\u0005\u0004R\u0002\u0011\rQ\"\u0001\u00048\"I11\u001b\u0001C\u0002\u001b\u00051q\u0017\u0005\n\u0007+\u0004!\u0019!D\u0001\u0007/D\u0011b!=\u0001\u0005\u00045\taa6\t\u0013\rM\bA1A\u0007\u0002\r]\u0007\"CB{\u0001\t\u0007i\u0011ABl\u0011%\u00199\u0010\u0001b\u0001\u000e\u0003\u0019I\u0010C\u0005\u0005\u0002\u0001\u0011\rQ\"\u0001\u0004z\"IA1\u0001\u0001C\u0002\u001b\u0005AQ\u0001\u0005\n\t\'\u0001!\u0019!C\u0001\t+A\u0001\u0002b\t\u0001A\u0003%Aq\u0003\u0005\n\tK\u0001!\u0019!D\u0001\u0007sDq\u0001b\n\u0001\t\u000b\u0019I\u0010C\u0004\u0005*\u0001!)a!?\t\u000f\u0011-\u0002\u0001\"\u0002\u0005.!IA1\n\u0001\u0005\u0006\rUEQ\n\u0005\b\t#\u0002A\u0011\u0001C*\u0011\u001d!)\u0006\u0001C\u0003\t/Bq\u0001b\u0019\u0001\t\u000b!)\u0007C\u0004\u0005j\u0001!)\u0001b\u001b\t\u000f\u0011=\u0004\u0001\"\u0002\u0005r!9AQ\u000f\u0001\u0005\u0006\r]\u0006b\u0002C<\u0001\u0011\u0015A\u0011\u0010\u0005\b\t{\u0002AQ\u0001C@\u0011\u001d!\u0019\t\u0001C\u0001\u0007oCq\u0001\"\"\u0001\t\u0003\u00199\fC\u0004\u0005\b\u0002!\taa.\t\u000f\u0011%\u0005\u0001\"\u0001\u00048\"9A1\u0012\u0001\u0005\n\u00115\u0005b\u0003CL\u0001\t\u0007I\u0011ABK\u0007oC\u0001\u0002\"\'\u0001A\u0003%1\u0011\u0018\u0005\b\t7\u0003A\u0011\u0001CO\u0011\u001d!I\u000b\u0001C!\tW;!\u0002c?\u0004\u0016\"\u00051Q\u0013C[\r)\u0019\u0019j!&\t\u0002\rUE\u0011\u0017\u0005\b\u0007W3C\u0011\u0001CZ\r\u0019!9L\n!\u0005:\"Q1Q\u0017\u0015\u0003\u0016\u0004%\taa.\t\u0015\u0011\u001d\u0007F!E!\u0002\u0013\u0019I\f\u0003\u0006\u0004P\"\u0012)\u001a!C\u0001\u0007oC!\u0002\"3)\u0005#\u0005\u000b\u0011BB]\u0011)\u0019\t\u000e\u000bBK\u0002\u0013\u00051q\u0017\u0005\u000b\t\u0017D#\u0011#Q\u0001\n\re\u0006BCBjQ\tU\r\u0011\"\u0001\u00048\"QAQ\u001a\u0015\u0003\u0012\u0003\u0006Ia!/\t\u0015\rU\u0007F!f\u0001\n\u0003\u00199\u000e\u0003\u0006\u0005P\"\u0012\t\u0012)A\u0005\u00073D!b!=)\u0005+\u0007I\u0011ABl\u0011)!\t\u000e\u000bB\tB\u0003%1\u0011\u001c\u0005\u000b\u0007gD#Q3A\u0005\u0002\r]\u0007B\u0003CjQ\tE\t\u0015!\u0003\u0004Z\"Q1Q\u001f\u0015\u0003\u0016\u0004%\taa6\t\u0015\u0011U\u0007F!E!\u0002\u0013\u0019I\u000e\u0003\u0006\u0005&!\u0012)\u001a!C\u0001\u0007sD!\u0002b6)\u0005#\u0005\u000b\u0011BB~\u0011)!\t\u0001\u000bBK\u0002\u0013\u00051\u0011 \u0005\u000b\t3D#\u0011#Q\u0001\n\rm\bB\u0003C\u0002Q\tU\r\u0011\"\u0001\u0005\u0006!QA1\u001c\u0015\u0003\u0012\u0003\u0006I\u0001b\u0002\t\u0015\u0011M\u0001F!f\u0001\n\u0003\")\u0002\u0003\u0006\u0005$!\u0012\t\u0012)A\u0005\t/Aqaa+)\t\u0003!i\u000eC\u0005\u0004x\"\u0012\r\u0011\"\u0001\u0004z\"AA1 \u0015!\u0002\u0013\u0019Y\u0010C\u0005\u0005~\"\n\t\u0011\"\u0001\u0005\u0000\"IQ\u0011\u0004\u0015\u0012\u0002\u0013\u0005Q1\u0004\u0005\n\u000bcA\u0013\u0013!C\u0001\u000b7A\u0011\"b\r)#\u0003%\t!b\u0007\t\u0013\u0015U\u0002&%A\u0005\u0002\u0015m\u0001\"CC\u001cQE\u0005I\u0011AC\u001d\u0011%)i\u0004KI\u0001\n\u0003)I\u0004C\u0005\u0006@!\n\n\u0011\"\u0001\u0006:!IQ\u0011\t\u0015\u0012\u0002\u0013\u0005Q\u0011\b\u0005\n\u000b\u0007B\u0013\u0013!C\u0001\u000b\u000bB\u0011\"\"\u0013)#\u0003%\t!\"\u0012\t\u0013\u0015-\u0003&%A\u0005\u0002\u00155\u0003\"CC)QE\u0005I\u0011AC*\u0011%)9\u0006KA\u0001\n\u0003*I\u0006C\u0005\u0006j!\n\t\u0011\"\u0001\u0006l!IQQ\u000e\u0015\u0002\u0002\u0013\u0005Qq\u000e\u0005\n\u000bkB\u0013\u0011!C!\u000boB\u0011\"\"\")\u0003\u0003%\t!b\"\t\u0013\u0015-\u0005&!A\u0005B\u00155\u0005\"CCIQ\u0005\u0005I\u0011ICJ\u0011%))\nKA\u0001\n\u0003*9jB\u0005\u0006\u001c\u001a\n\t\u0011#\u0001\u0006\u001e\u001aIAq\u0017\u0014\u0002\u0002#\u0005Qq\u0014\u0005\b\u0007WSF\u0011AC\\\u0011%!IKWA\u0001\n\u000b*I\fC\u0005\u0006<j\u000b\t\u0011\"!\u0006>\"IQq\u001b.\u0012\u0002\u0013\u0005Q1\u000b\u0005\n\u000b3T\u0016\u0011!CA\u000b7D\u0011\"\";[#\u0003%\t!b\u0015\t\u0013\u0015-(,!A\u0005\n\u00155hABC{M\u0001)9\u0010\u0003\u0006\u0006z\n\u0014\t\u0011)A\u0005\u0007cCqaa+c\t\u0003)Y\u0010C\u0005\u00046\n\u0014\r\u0011\"\u0001\u00048\"AAq\u00192!\u0002\u0013\u0019I\fC\u0005\u0004P\n\u0014\r\u0011\"\u0001\u00048\"AA\u0011\u001a2!\u0002\u0013\u0019I\fC\u0005\u0004R\n\u0014\r\u0011\"\u0001\u00048\"AA1\u001a2!\u0002\u0013\u0019I\fC\u0005\u0004T\n\u0014\r\u0011\"\u0001\u00048\"AAQ\u001a2!\u0002\u0013\u0019I\fC\u0005\u0004V\n\u0014\r\u0011\"\u0001\u0004X\"AAq\u001a2!\u0002\u0013\u0019I\u000eC\u0005\u0004r\n\u0014\r\u0011\"\u0001\u0004X\"AA\u0011\u001b2!\u0002\u0013\u0019I\u000eC\u0005\u0004t\n\u0014\r\u0011\"\u0001\u0004X\"AA1\u001b2!\u0002\u0013\u0019I\u000eC\u0005\u0004v\n\u0014\r\u0011\"\u0001\u0004X\"AAQ\u001b2!\u0002\u0013\u0019I\u000eC\u0005\u0004x\n\u0014\r\u0011\"\u0001\u0004z\"AA1 2!\u0002\u0013\u0019Y\u0010C\u0005\u0005\u0004\t\u0014\r\u0011\"\u0001\u0005\u0006!AA1\u001c2!\u0002\u0013!9\u0001C\u0005\u0005\u0014\t\u0014\r\u0011\"\u0011\u0005\u0016!AA1\u00052!\u0002\u0013!9\u0002C\u0005\u0005&\t\u0014\r\u0011\"\u0001\u0004z\"AAq\u001b2!\u0002\u0013\u0019Y\u0010C\u0005\u0005\u0002\t\u0014\r\u0011\"\u0001\u0004z\"AA\u0011\u001c2!\u0002\u0013\u0019YpB\u0004\u0007\u0002\u0019B\tAb\u0001\u0007\u000f\u0015Uh\u0005#\u0001\u0007\u0006!A11VA\u0001\t\u000319\u0001\u0003\u0005\u0006<\u0006\u0005A\u0011\u0001D\u0005\u000f\u001d1iA\nE\u0001\r\u001f1qA\"\u0005\'\u0011\u00031\u0019\u0002\u0003\u0005\u0004,\u0006%A\u0011\u0001D\u000b\u0011!)Y,!\u0003\u0005\u0002\u0019]\u0001B\u0003D\u0018\u0003\u0013\t\n\u0011\"\u0001\u0006T!AQ1XA\u0005\t\u00031\t\u0004\u0003\u0005\u0006<\u0006%A\u0011\u0001D\u001f\u0011!)Y,!\u0003\u0005\u0002\u0019-\u0003\u0002CC^\u0003\u0013!\tA\"\u0016\t\u0011\u0015m\u0016\u0011\u0002C\u0001\rGB\u0001\"b/\u0002\n\u0011\u0005aQ\u000f\u0005\t\u000bw\u000bI\u0001\"\u0001\u0007\f\"AQ1XA\u0005\t\u00031\u0019\n\u0003\u0005\u0006<\u0006%A\u0011\u0001DO\u000f\u001d19K\nE\u0001\rS3qAb+\'\u0011\u00031i\u000b\u0003\u0005\u0004,\u0006\u0015B\u0011\u0001DX\u0011!)Y,!\n\u0005\u0002\u0019E\u0006B\u0003D\u0018\u0003K\t\n\u0011\"\u0001\u0006F!Qa1ZA\u0013#\u0003%\t!b\u0015\t\u0011\u0015m\u0016Q\u0005C\u0001\r\u001bD\u0001\"b/\u0002&\u0011\u0005a\u0011\u001c\u0005\t\u000bw\u000b)\u0003\"\u0001\u0007h\"AQ1XA\u0013\t\u00031\t\u0010\u0003\u0005\u0006<\u0006\u0015B\u0011\u0001D\u0000\u0011!)Y,!\n\u0005\u0002\u001dE\u0001\u0002CC^\u0003K!\tab\n\t\u0011\u0015m\u0016Q\u0005C\u0001\u000f_1aa\"\u000f\'\u0001\u001em\u0002bCC}\u0003\u007f\u0011)\u001a!C\u0001\t\'B1b\"\u0010\u0002@\tE\t\u0015!\u0003\u00042\"A11VA \t\u00039y\u0004\u0003\u0006\u00046\u0006}\"\u0019!C\u0001\u0007oC\u0011\u0002b2\u0002@\u0001\u0006Ia!/\t\u0015\r=\u0017q\bb\u0001\n\u0003\u00199\fC\u0005\u0005J\u0006}\u0002\u0015!\u0003\u0004:\"Q1\u0011[A \u0005\u0004%\taa.\t\u0013\u0011-\u0017q\bQ\u0001\n\re\u0006BCBj\u0003\u007f\u0011\r\u0011\"\u0001\u00048\"IAQZA A\u0003%1\u0011\u0018\u0005\u000b\u0007+\fyD1A\u0005\u0002\r]\u0007\"\u0003Ch\u0003\u007f\u0001\u000b\u0011BBm\u0011)\u0019\t0a\u0010C\u0002\u0013\u00051q\u001b\u0005\n\t#\fy\u0004)A\u0005\u00073D!ba=\u0002@\t\u0007I\u0011ABl\u0011%!\u0019.a\u0010!\u0002\u0013\u0019I\u000e\u0003\u0006\u0004v\u0006}\"\u0019!C\u0001\u0007/D\u0011\u0002\"6\u0002@\u0001\u0006Ia!7\t\u0015\r]\u0018q\bb\u0001\n\u0003\u0019I\u0010C\u0005\u0005|\u0006}\u0002\u0015!\u0003\u0004|\"QA1AA \u0005\u0004%\t\u0001\"\u0002\t\u0013\u0011m\u0017q\bQ\u0001\n\u0011\u001d\u0001B\u0003C\u0013\u0003\u007f\u0011\r\u0011\"\u0001\u0004z\"IAq[A A\u0003%11 \u0005\u000b\t\u0003\tyD1A\u0005\u0002\re\b\"\u0003Cm\u0003\u007f\u0001\u000b\u0011BB~\u0011!!\t&a\u0010\u0005B\u0011M\u0003\u0002\u0003CN\u0003\u007f!\te\"\u0012\t\u0015\u0011u\u0018qHA\u0001\n\u00039I\u0005\u0003\u0006\u0006\u001a\u0005}\u0012\u0013!C\u0001\u000f\u001bB!\"b\u0016\u0002@\u0005\u0005I\u0011IC-\u0011))I\'a\u0010\u0002\u0002\u0013\u0005Q1\u000e\u0005\u000b\u000b[\ny$!A\u0005\u0002\u001dE\u0003BCC;\u0003\u007f\t\t\u0011\"\u0011\u0006x!QQQQA \u0003\u0003%\ta\"\u0016\t\u0015\u0015-\u0015qHA\u0001\n\u0003:I\u0006\u0003\u0006\u0006\u0012\u0006}\u0012\u0011!C!\u000b\'C!\"\"&\u0002@\u0005\u0005I\u0011ID/\u000f%9\tGJA\u0001\u0012\u00039\u0019GB\u0005\b:\u0019\n\t\u0011#\u0001\bf!A11VAI\t\u00039i\u0007\u0003\u0006\u0005*\u0006E\u0015\u0011!C#\u000bsC!\"b/\u0002\u0012\u0006\u0005I\u0011QD8\u0011))I.!%\u0002\u0002\u0013\u0005u1\u000f\u0005\u000b\u000bW\f\t*!A\u0005\n\u00155hA\u0002CXM\u0001Ay\u000fC\u0006\b\u0006\u0006u%\u0011!Q\u0001\n\rE\u0006bCDE\u0003;\u0013\t\u0011)A\u0005\u0007cC\u0001ba+\u0002\u001e\u0012\u0005\u0001\u0012\u001f\u0005\u000b\u000f3\u000bi\n\"\u0001\u0004\u0016\u000e]\u0006BCB[\u0003;\u0013\r\u0011\"\u0001\u00048\"IAqYAOA\u0003%1\u0011\u0018\u0005\u000b\u0007\u001f\fiJ1A\u0005\u0002\r]\u0006\"\u0003Ce\u0003;\u0003\u000b\u0011BB]\u0011)\u0019\t.!(C\u0002\u0013\u00051q\u0017\u0005\n\t\u0017\fi\n)A\u0005\u0007sC!ba5\u0002\u001e\n\u0007I\u0011AB\\\u0011%!i-!(!\u0002\u0013\u0019I\f\u0003\u0006\u0004V\u0006u%\u0019!C\u0001\u0007/D\u0011\u0002b4\u0002\u001e\u0002\u0006Ia!7\t\u0015\rE\u0018Q\u0014b\u0001\n\u0003\u00199\u000eC\u0005\u0005R\u0006u\u0005\u0015!\u0003\u0004Z\"Q11_AO\u0005\u0004%\taa6\t\u0013\u0011M\u0017Q\u0014Q\u0001\n\re\u0007BCB{\u0003;\u0013\r\u0011\"\u0001\u0004X\"IAQ[AOA\u0003%1\u0011\u001c\u0005\u000b\u0007o\fiJ1A\u0005\u0002\re\b\"\u0003C~\u0003;\u0003\u000b\u0011BB~\u0011)!)#!(C\u0002\u0013\u00051\u0011 \u0005\n\t/\fi\n)A\u0005\u0007wD!\u0002\"\u0001\u0002\u001e\n\u0007I\u0011AB}\u0011%!I.!(!\u0002\u0013\u0019Y\u0010\u0003\u0006\u0005\u0004\u0005u%\u0019!C\u0001\t\u000bA\u0011\u0002b7\u0002\u001e\u0002\u0006I\u0001b\u0002\t\u0011\u0011m\u0015Q\u0014C!\u0011o<qa\"\u001f\'\u0011\u00039YHB\u0004\u00050\u001aB\ta\" \t\u0011\r-\u00161\u001cC\u0001\u000f\u007fB\u0001\"b/\u0002\\\u0012\u0005q\u0011\u0011\u0004\u0007\u000f\u00173\u0003a\"$\t\u0017\u001d\u0015\u0015\u0011\u001dB\u0001B\u0003%1\u0011\u0017\u0005\f\u000f\u0013\u000b\tO!A!\u0002\u0013\u0019\t\f\u0003\u0005\u0004,\u0006\u0005H\u0011ADI\u0011)9I*!9\u0005B\rU5qW\u0004\b\u000f73\u0003\u0012ADO\r\u001d9YI\nE\u0001\u000f?C\u0001ba+\u0002n\u0012\u0005q\u0011\u0015\u0005\t\u000bw\u000bi\u000f\"\u0001\b$\u001a1q\u0011\u0016\u0014\u0001\u000fWC1b\"\"\u0002t\n\u0005\t\u0015!\u0003\u00042\"Yq\u0011RAz\u0005\u0003\u0005\u000b\u0011BBY\u0011!\u0019Y+a=\u0005\u0002\u001d5\u0006BCDM\u0003g$\ta!&\u00048\"Q1QWAz\u0005\u0004%\taa.\t\u0013\u0011\u001d\u00171\u001fQ\u0001\n\re\u0006BCBh\u0003g\u0014\r\u0011\"\u0001\u00048\"IA\u0011ZAzA\u0003%1\u0011\u0018\u0005\u000b\u0007#\f\u0019P1A\u0005\u0002\r]\u0006\"\u0003Cf\u0003g\u0004\u000b\u0011BB]\u0011)\u0019\u0019.a=C\u0002\u0013\u00051q\u0017\u0005\n\t\u001b\f\u0019\u0010)A\u0005\u0007sC!b!6\u0002t\n\u0007I\u0011ABl\u0011%!y-a=!\u0002\u0013\u0019I\u000e\u0003\u0006\u0004r\u0006M(\u0019!C\u0001\u0007/D\u0011\u0002\"5\u0002t\u0002\u0006Ia!7\t\u0015\rM\u00181\u001fb\u0001\n\u0003\u00199\u000eC\u0005\u0005T\u0006M\b\u0015!\u0003\u0004Z\"Q1Q_Az\u0005\u0004%\taa6\t\u0013\u0011U\u00171\u001fQ\u0001\n\re\u0007BCB|\u0003g\u0014\r\u0011\"\u0001\u0004z\"IA1`AzA\u0003%11 \u0005\u000b\tK\t\u0019P1A\u0005\u0002\re\b\"\u0003Cl\u0003g\u0004\u000b\u0011BB~\u0011)!\t!a=C\u0002\u0013\u00051\u0011 \u0005\n\t3\f\u0019\u0010)A\u0005\u0007wD!\u0002b\u0001\u0002t\n\u0007I\u0011\u0001C\u0003\u0011%!Y.a=!\u0002\u0013!9\u0001\u0003\u0005\u0005\u001c\u0006MH\u0011ID[\u000f\u001d9IL\nE\u0001\u000fw3qa\"+\'\u0011\u00039i\f\u0003\u0005\u0004,\nEB\u0011AD`\u0011!)YL!\r\u0005\u0002\u001d\u0005gABDdM\u00019I\rC\u0006\b\u0006\n]\"\u0011!Q\u0001\n\rE\u0006bCDE\u0005o\u0011\t\u0011)A\u0005\u0007cC\u0001ba+\u00038\u0011\u0005q1\u001a\u0005\u000b\u000f3\u00139\u0004\"\u0011\u0004\u0016\u000e]vaBDjM!\u0005qQ\u001b\u0004\b\u000f\u000f4\u0003\u0012ADl\u0011!\u0019YKa\u0011\u0005\u0002\u001de\u0007\u0002CC^\u0005\u0007\"\tab7\u0007\r\u001d\u0005h\u0005ADr\u0011-9)I!\u0013\u0003\u0002\u0003\u0006Ia!-\t\u0017\u001d%%\u0011\nB\u0001B\u0003%1\u0011\u0017\u0005\t\u0007W\u0013I\u0005\"\u0001\bf\"Q1Q\u0017B%\u0005\u0004%\taa.\t\u0013\u0011\u001d\'\u0011\nQ\u0001\n\re\u0006BCBh\u0005\u0013\u0012\r\u0011\"\u0001\u00048\"IA\u0011\u001aB%A\u0003%1\u0011\u0018\u0005\u000b\u0007#\u0014IE1A\u0005\u0002\r]\u0006\"\u0003Cf\u0005\u0013\u0002\u000b\u0011BB]\u0011)\u0019\u0019N!\u0013C\u0002\u0013\u00051q\u0017\u0005\n\t\u001b\u0014I\u0005)A\u0005\u0007sC!b!6\u0003J\t\u0007I\u0011ABl\u0011%!yM!\u0013!\u0002\u0013\u0019I\u000e\u0003\u0006\u0004r\n%#\u0019!C\u0001\u0007/D\u0011\u0002\"5\u0003J\u0001\u0006Ia!7\t\u0015\rM(\u0011\nb\u0001\n\u0003\u00199\u000eC\u0005\u0005T\n%\u0003\u0015!\u0003\u0004Z\"Q1Q\u001fB%\u0005\u0004%\taa6\t\u0013\u0011U\'\u0011\nQ\u0001\n\re\u0007BCB|\u0005\u0013\u0012\r\u0011\"\u0001\u0004z\"IA1 B%A\u0003%11 \u0005\u000b\t\u0003\u0011IE1A\u0005\u0002\re\b\"\u0003Cm\u0005\u0013\u0002\u000b\u0011BB~\u0011)!\u0019A!\u0013C\u0002\u0013\u0005AQ\u0001\u0005\n\t7\u0014I\u0005)A\u0005\t\u000fA!\u0002\"\n\u0003J\t\u0007I\u0011AB}\u0011%!9N!\u0013!\u0002\u0013\u0019Y\u0010\u0003\u0005\u0005\u001c\n%C\u0011IDw\u000f\u001d9\tP\nE\u0001\u000fg4qa\"9\'\u0011\u00039)\u0010\u0003\u0005\u0004,\n\u0015E\u0011AD|\u0011!)YL!\"\u0005\u0002\u001dehABD\u0000M\u0001A\t\u0001C\u0006\b\u0006\n-%\u0011!Q\u0001\n\rE\u0006bCDE\u0005\u0017\u0013\t\u0011)A\u0005\u0007cC\u0001ba+\u0003\f\u0012\u0005\u00012\u0001\u0005\u000b\u0007k\u0013YI1A\u0005\u0002\r]\u0006\"\u0003Cd\u0005\u0017\u0003\u000b\u0011BB]\u0011)\u0019yMa#C\u0002\u0013\u00051q\u0017\u0005\n\t\u0013\u0014Y\t)A\u0005\u0007sC!b!5\u0003\f\n\u0007I\u0011AB\\\u0011%!YMa#!\u0002\u0013\u0019I\f\u0003\u0006\u0004T\n-%\u0019!C\u0001\u0007oC\u0011\u0002\"4\u0003\f\u0002\u0006Ia!/\t\u0015\rU\'1\u0012b\u0001\n\u0003\u00199\u000eC\u0005\u0005P\n-\u0005\u0015!\u0003\u0004Z\"Q1\u0011\u001fBF\u0005\u0004%\taa6\t\u0013\u0011E\'1\u0012Q\u0001\n\re\u0007BCBz\u0005\u0017\u0013\r\u0011\"\u0001\u0004X\"IA1\u001bBFA\u0003%1\u0011\u001c\u0005\u000b\u0007k\u0014YI1A\u0005\u0002\r]\u0007\"\u0003Ck\u0005\u0017\u0003\u000b\u0011BBm\u0011)\u00199Pa#C\u0002\u0013\u00051\u0011 \u0005\n\tw\u0014Y\t)A\u0005\u0007wD!\u0002\"\n\u0003\f\n\u0007I\u0011AB}\u0011%!9Na#!\u0002\u0013\u0019Y\u0010\u0003\u0006\u0005\u0002\t-%\u0019!C\u0001\u0007sD\u0011\u0002\"7\u0003\f\u0002\u0006Iaa?\t\u0015\u0011\r!1\u0012b\u0001\n\u0003!)\u0001C\u0005\u0005\\\n-\u0005\u0015!\u0003\u0005\b!AA1\u0014BF\t\u0003BYaB\u0004\t\u0010\u0019B\t\u0001#\u0005\u0007\u000f\u001d}h\u0005#\u0001\t\u0014!A11\u0016Bd\t\u0003A)\u0002\u0003\u0005\u0006<\n\u001dG\u0011\u0001E\f\r%AiBJA\u0011\u0007+Cy\u0002\u0003\u0005\u0004,\n5G\u0011\u0001E\u0011\u0011)A)C!4C\u0002\u001b\u00051q\u001b\u0004\t\u0011S1\u0003i!&\t,!Y\u0001R\u0006Bj\u0005+\u0007I\u0011\u0001C*\u0011-AyCa5\u0003\u0012\u0003\u0006Ia!-\t\u0011\r-&1\u001bC\u0001\u0011cA!\u0002#\n\u0003T\n\u0007I\u0011ABl\u0011%A9Da5!\u0002\u0013\u0019I\u000e\u0003\u0005\u0005*\nMG\u0011\tCV\u0011)!iPa5\u0002\u0002\u0013\u0005\u0001\u0012\b\u0005\u000b\u000b3\u0011\u0019.%A\u0005\u0002\u001d5\u0003BCC,\u0005\'\f\t\u0011\"\u0011\u0006Z!QQ\u0011\u000eBj\u0003\u0003%\t!b\u001b\t\u0015\u00155$1[A\u0001\n\u0003Ai\u0004\u0003\u0006\u0006v\tM\u0017\u0011!C!\u000boB!\"\"\"\u0003T\u0006\u0005I\u0011\u0001E!\u0011))YIa5\u0002\u0002\u0013\u0005\u0003R\t\u0005\u000b\u000b#\u0013\u0019.!A\u0005B\u0015M\u0005BCCK\u0005\'\f\t\u0011\"\u0011\tJ\u001dY\u0001r\u0015\u0014\u0002\u0002#\u00051Q\u0013EU\r-AICJA\u0001\u0012\u0003\u0019)\nc+\t\u0011\r-&q\u001fC\u0001\u0011_C!\u0002\"+\u0003x\u0006\u0005IQIC]\u0011))YLa>\u0002\u0002\u0013\u0005\u0005\u0012\u0017\u0005\u000b\u000b3\u001490!A\u0005\u0002\"U\u0006BCCv\u0005o\f\t\u0011\"\u0003\u0006n\u001aA\u0001R\n\u0014A\u0007+Cy\u0005C\u0006\t.\r\r!Q3A\u0005\u0002\u0011M\u0003b\u0003E\u0018\u0007\u0007\u0011\t\u0012)A\u0005\u0007cC\u0001ba+\u0004\u0004\u0011\u0005\u0001\u0012\u000b\u0005\u000b\u0011K\u0019\u0019A1A\u0005\u0002\r]\u0007\"\u0003E\u001c\u0007\u0007\u0001\u000b\u0011BBm\u0011!!Ika\u0001\u0005B\u0011-\u0006B\u0003C\u007f\u0007\u0007\t\t\u0011\"\u0001\tX!QQ\u0011DB\u0002#\u0003%\ta\"\u0014\t\u0015\u0015]31AA\u0001\n\u0003*I\u0006\u0003\u0006\u0006j\r\r\u0011\u0011!C\u0001\u000bWB!\"\"\u001c\u0004\u0004\u0005\u0005I\u0011\u0001E.\u0011)))ha\u0001\u0002\u0002\u0013\u0005Sq\u000f\u0005\u000b\u000b\u000b\u001b\u0019!!A\u0005\u0002!}\u0003BCCF\u0007\u0007\t\t\u0011\"\u0011\td!QQ\u0011SB\u0002\u0003\u0003%\t%b%\t\u0015\u0015U51AA\u0001\n\u0003B9gB\u0006\t:\u001a\n\t\u0011#\u0001\u0004\u0016\"mfa\u0003E\'M\u0005\u0005\t\u0012ABK\u0011{C\u0001ba+\u0004(\u0011\u0005\u0001\u0012\u0019\u0005\u000b\tS\u001b9#!A\u0005F\u0015e\u0006BCC^\u0007O\t\t\u0011\"!\tD\"QQ\u0011\\B\u0014\u0003\u0003%\t\tc2\t\u0015\u0015-8qEA\u0001\n\u0013)iO\u0002\u0005\t\n\u001a\u00025Q\u0013EF\u0011-Aica\r\u0003\u0016\u0004%\t\u0001b\u0015\t\u0017!=21\u0007B\tB\u0003%1\u0011\u0017\u0005\t\u0007W\u001b\u0019\u0004\"\u0001\t\u000e\"Q\u0001REB\u001a\u0005\u0004%\taa6\t\u0013!]21\u0007Q\u0001\n\re\u0007\u0002\u0003CU\u0007g!\t\u0005b+\t\u0015\u0011u81GA\u0001\n\u0003A\u0019\n\u0003\u0006\u0006\u001a\rM\u0012\u0013!C\u0001\u000f\u001bB!\"b\u0016\u00044\u0005\u0005I\u0011IC-\u0011))Iga\r\u0002\u0002\u0013\u0005Q1\u000e\u0005\u000b\u000b[\u001a\u0019$!A\u0005\u0002!]\u0005BCC;\u0007g\t\t\u0011\"\u0011\u0006x!QQQQB\u001a\u0003\u0003%\t\u0001c\'\t\u0015\u0015-51GA\u0001\n\u0003By\n\u0003\u0006\u0006\u0012\u000eM\u0012\u0011!C!\u000b\'C!\"\"&\u00044\u0005\u0005I\u0011\tER\u000f-AYMJA\u0001\u0012\u0003\u0019)\n#4\u0007\u0017!%e%!A\t\u0002\rU\u0005r\u001a\u0005\t\u0007W\u001b9\u0006\"\u0001\tT\"QA\u0011VB,\u0003\u0003%)%\"/\t\u0015\u0015m6qKA\u0001\n\u0003C)\u000e\u0003\u0006\u0006Z\u000e]\u0013\u0011!CA\u00113D!\"b;\u0004X\u0005\u0005I\u0011BCw\r!AYG\n!\u0004\u0016\"5\u0004b\u0003E\u0017\u0007G\u0012)\u001a!C\u0001\t\'B1\u0002c\f\u0004d\tE\t\u0015!\u0003\u00042\"A11VB2\t\u0003Ay\u0007\u0003\u0006\t&\r\r$\u0019!C\u0001\u0007/D\u0011\u0002c\u000e\u0004d\u0001\u0006Ia!7\t\u0011\u0011%61\rC!\tWC!\u0002\"@\u0004d\u0005\u0005I\u0011\u0001E;\u0011))Iba\u0019\u0012\u0002\u0013\u0005qQ\n\u0005\u000b\u000b/\u001a\u0019\'!A\u0005B\u0015e\u0003BCC5\u0007G\n\t\u0011\"\u0001\u0006l!QQQNB2\u0003\u0003%\t\u0001#\u001f\t\u0015\u0015U41MA\u0001\n\u0003*9\b\u0003\u0006\u0006\u0006\u000e\r\u0014\u0011!C\u0001\u0011{B!\"b#\u0004d\u0005\u0005I\u0011\tEA\u0011))\tja\u0019\u0002\u0002\u0013\u0005S1\u0013\u0005\u000b\u000b+\u001b\u0019\'!A\u0005B!\u0015ua\u0003EoM\u0005\u0005\t\u0012ABK\u0011?41\u0002c\u001b\'\u0003\u0003E\ta!&\tb\"A11VBD\t\u0003A)\u000f\u0003\u0006\u0005*\u000e\u001d\u0015\u0011!C#\u000bsC!\"b/\u0004\b\u0006\u0005I\u0011\u0011Et\u0011))Ina\"\u0002\u0002\u0013\u0005\u00052\u001e\u0005\u000b\u000bW\u001c9)!A\u0005\n\u00155(\u0001\u0002$bGRTAaa&\u0004\u001a\u0006I1oY1mCR,7\u000f\u001e\u0006\u0003\u00077\u000b1a\u001c:h\'\r\u00011q\u0014\t\u0005\u0007C\u001b9+\u0004\u0002\u0004$*\u00111QU\u0001\u0006g\u000e\fG.Y\u0005\u0005\u0007S\u001b\u0019K\u0001\u0004B]f\u0014VMZ\u0001\u0007y%t\u0017\u000e\u001e \u0004\u0001Q\u00111\u0011\u0017\t\u0004\u0007g\u0003QBABK\u00039\u0011\u0018m\u001e$bGRlUm]:bO\u0016,\"a!/\u0011\t\rm6\u0011\u001a\b\u0005\u0007{\u001b)\r\u0005\u0003\u0004@\u000e\rVBABa\u0015\u0011\u0019\u0019m!,\u0002\rq\u0012xn\u001c;?\u0013\u0011\u00199ma)\u0002\rA\u0013X\rZ3g\u0013\u0011\u0019Ym!4\u0003\rM#(/\u001b8h\u0015\u0011\u00199ma)\u00021I\fwoU5na2Lg-[3e\r\u0006\u001cG/T3tg\u0006<W-A\rsC^l\u0015\u000eZ*f]R,gnY3GC\u000e$X*Z:tC\u001e,\u0017a\t:bo6KGmU3oi\u0016t7-Z*j[Bd\u0017NZ5fI\u001a\u000b7\r^\'fgN\fw-Z\u0001\u0010M\u0006\u001cG/T3tg\u0006<W-\u0011:hgV\u00111\u0011\u001c\t\u0007\u00077\u001c)oa;\u000f\t\ru7\u0011\u001d\b\u0005\u0007\u007f\u001by.\u0003\u0002\u0004&&!11]BR\u0003\u001d\u0001\u0018mY6bO\u0016LAaa:\u0004j\nQ\u0011J\u001c3fq\u0016$7+Z9\u000b\t\r\r81\u0015\t\u0005\u0007C\u001bi/\u0003\u0003\u0004p\u000e\r&aA!os\u0006I2/[7qY&4\u0017.\u001a3GC\u000e$X*Z:tC\u001e,\u0017I]4t\u0003ii\u0017\u000eZ*f]R,gnY3GC\u000e$X*Z:tC\u001e,\u0017I]4t\u0003\u0011j\u0017\u000eZ*f]R,gnY3TS6\u0004H.\u001b4jK\u00124\u0015m\u0019;NKN\u001c\u0018mZ3Be\u001e\u001c\u0018AB5t\u0019\u0016\fg-\u0006\u0002\u0004|B!1\u0011UB\u007f\u0013\u0011\u0019ypa)\u0003\u000f\t{w\u000e\\3b]\u0006a\u0011n\u001d,bGV|Wo]-fg\u0006Q\u0001O]3ui&4\u0017.\u001a:\u0016\u0005\u0011\u001d\u0001\u0003\u0002C\u0005\t\u001fi!\u0001b\u0003\u000b\t\u001151\u0011T\u0001\ng\u000e\fG.Y2uS\u000eLA\u0001\"\u0005\u0005\f\tQ\u0001K]3ui&4\u0017.\u001a:\u0002\u000b\r\fWo]3\u0016\u0005\u0011]\u0001CBBQ\t3!i\"\u0003\u0003\u0005\u001c\r\r&AB(qi&|g\u000e\u0005\u0003\u0004\\\u0012}\u0011\u0002\u0002C\u0011\u0007S\u0014\u0011\u0002\u00165s_^\f\'\r\\3\u0002\r\r\fWo]3!\u0003\u0015I7/W3t\u0003\u0011I7OT8\u0002\u0013Q|\'i\\8mK\u0006t\u0017a\u0003;p\u0003N\u001cXM\u001d;j_:$B\u0001b\f\u0005<A!A\u0011\u0007C\u001b\u001d\u0011\u0019\u0019\fb\r\n\t\r\r8QS\u0005\u0005\to!IDA\u0005BgN,\'\u000f^5p]*!11]BK\u0011\u001d!iD\u0005a\u0002\t\u007f\t1\u0001]8t!\u0011!\t\u0005b\u0012\u000e\u0005\u0011\r#\u0002\u0002C#\t\u0017\taa]8ve\u000e,\u0017\u0002\u0002C%\t\u0007\u0012\u0001\u0002U8tSRLwN\\\u0001\u0014S:$XM\u001d8bYR{\u0017i]:feRLwN\u001c\u000b\u0005\t_!y\u0005C\u0004\u0005>M\u0001\r\u0001b\u0010\u0002\u0017Ut\u0017M]=`I\t\fgnZ\u000b\u0003\u0007c\u000b\u0001\u0002\n2be\u0012\u0012\u0017M\u001d\u000b\u0005\u0007c#I\u0006\u0003\u0005\u0005\\U!\t\u0019\u0001C/\u0003\r\u0011\bn\u001d\t\u0007\u0007C#yf!-\n\t\u0011\u000541\u0015\u0002\ty\tLh.Y7f}\u0005AA%Y7qI\u0005l\u0007\u000f\u0006\u0003\u00042\u0012\u001d\u0004\u0002\u0003C.-\u0011\u0005\r\u0001\"\u0018\u0002\t\u0011\u0012\u0017M\u001d\u000b\u0005\u0007c#i\u0007C\u0004\u0005\\]\u0001\ra!-\u0002\t\u0011\nW\u000e\u001d\u000b\u0005\u0007c#\u0019\bC\u0004\u0005\\a\u0001\ra!-\u0002\u0019M$(/\u001b8h!J,g-\u001b=\u0002\u000f%l\u0007\u000f\\5fgR!1\u0011\u0017C>\u0011!!YF\u0007CA\u0002\u0011u\u0013aB5t\u000bF4Hk\u001c\u000b\u0005\u0007c#\t\tC\u0004\u0005\\m\u0001\ra!-\u0002\u0017\u0019\f7\r^\'fgN\fw-Z\u0001\u0016g&l\u0007\u000f\\5gS\u0016$g)Y2u\u001b\u0016\u001c8/Y4f\u0003Yi\u0017\u000eZ*f]R,gnY3GC\u000e$X*Z:tC\u001e,\u0017\u0001I7jIN+g\u000e^3oG\u0016\u001c\u0016.\u001c9mS\u001aLW\r\u001a$bGRlUm]:bO\u0016\f!\"\\1lKN#(/\u001b8h)\u0019\u0019I\fb$\u0005\u0014\"9A\u0011\u0013\u0011A\u0002\re\u0016a\u0001:bo\"9AQ\u0013\u0011A\u0002\re\u0017\u0001B1sON\fqAT#X\u0019&sU)\u0001\u0005O\u000b^c\u0015JT#!\u0003-1\u0017m\u0019;ES\u0006<\'/Y7\u0015\t\reFq\u0014\u0005\b\tC\u001b\u0003\u0019\u0001CR\u0003\u0015aWM^3m!\u0011\u0019\t\u000b\"*\n\t\u0011\u001d61\u0015\u0002\u0004\u0013:$\u0018\u0001\u0003;p\'R\u0014\u0018N\\4\u0015\u0005\re\u0016&\u0004\u0001\u0002\u001e\u0006M(\u0011\nBFQ\u0005}\"MA\u0006CS:\f\'/_0%C6\u00048c\u0001\u0014\u0004 R\u0011AQ\u0017\t\u0004\u0007g3#\u0001\u0002\'fC\u001a\u001cr\u0001KBY\tw#\t\r\u0005\u0003\u0004\"\u0012u\u0016\u0002\u0002C`\u0007G\u0013q\u0001\u0015:pIV\u001cG\u000f\u0005\u0003\u0004\\\u0012\r\u0017\u0002\u0002Cc\u0007S\u0014AbU3sS\u0006d\u0017N_1cY\u0016\fqB]1x\r\u0006\u001cG/T3tg\u0006<W\rI\u0001\u001ae\u0006<8+[7qY&4\u0017.\u001a3GC\u000e$X*Z:tC\u001e,\u0007%\u0001\u000esC^l\u0015\u000eZ*f]R,gnY3GC\u000e$X*Z:tC\u001e,\u0007%\u0001\u0013sC^l\u0015\u000eZ*f]R,gnY3TS6\u0004H.\u001b4jK\u00124\u0015m\u0019;NKN\u001c\u0018mZ3!\u0003A1\u0017m\u0019;NKN\u001c\u0018mZ3Be\u001e\u001c\b%\u0001\u000etS6\u0004H.\u001b4jK\u00124\u0015m\u0019;NKN\u001c\u0018mZ3Be\u001e\u001c\b%A\u000enS\u0012\u001cVM\u001c;f]\u000e,g)Y2u\u001b\u0016\u001c8/Y4f\u0003J<7\u000fI\u0001&[&$7+\u001a8uK:\u001cWmU5na2Lg-[3e\r\u0006\u001cG/T3tg\u0006<W-\u0011:hg\u0002\na![:ZKN\u0004\u0013!D5t-\u0006\u001cWo\\;t3\u0016\u001c\b%A\u0006qe\u0016$H/\u001b4jKJ\u0004CC\u0007Cp\tG$)\u000fb:\u0005j\u0012-HQ\u001eCx\tc$\u0019\u0010\">\u0005x\u0012e\bc\u0001CqQ5\ta\u0005C\u0004\u00046\u0006\u0003\ra!/\t\u000f\r=\u0017\t1\u0001\u0004:\"91\u0011[!A\u0002\re\u0006bBBj\u0003\u0002\u00071\u0011\u0018\u0005\b\u0007+\f\u0005\u0019ABm\u0011\u001d\u0019\t0\u0011a\u0001\u00073Dqaa=B\u0001\u0004\u0019I\u000eC\u0004\u0004v\u0006\u0003\ra!7\t\u000f\u0011\u0015\u0012\t1\u0001\u0004|\"9A\u0011A!A\u0002\rm\bb\u0002C\u0002\u0003\u0002\u0007Aq\u0001\u0005\n\t\'\t\u0005\u0013!a\u0001\t/\tq![:MK\u00064\u0007%\u0001\u0003d_BLHC\u0007Cp\u000b\u0003)\u0019!\"\u0002\u0006\b\u0015%Q1BC\u0007\u000b\u001f)\t\"b\u0005\u0006\u0016\u0015]\u0001\"CB[\tB\u0005\t\u0019AB]\u0011%\u0019y\r\u0012I\u0001\u0002\u0004\u0019I\fC\u0005\u0004R\u0012\u0003\n\u00111\u0001\u0004:\"I11\u001b#\u0011\u0002\u0003\u00071\u0011\u0018\u0005\n\u0007+$\u0005\u0013!a\u0001\u00073D\u0011b!=E!\u0003\u0005\ra!7\t\u0013\rMH\t%AA\u0002\re\u0007\"CB{\tB\u0005\t\u0019ABm\u0011%!)\u0003\u0012I\u0001\u0002\u0004\u0019Y\u0010C\u0005\u0005\u0002\u0011\u0003\n\u00111\u0001\u0004|\"IA1\u0001#\u0011\u0002\u0003\u0007Aq\u0001\u0005\n\t\'!\u0005\u0013!a\u0001\t/\tabY8qs\u0012\"WMZ1vYR$\u0013\'\u0006\u0002\u0006\u001e)\"1\u0011XC\u0010W\t)\t\u0003\u0005\u0003\u0006$\u00155RBAC\u0013\u0015\u0011)9#\"\u000b\u0002\u0013Ut7\r[3dW\u0016$\'\u0002BC\u0016\u0007G\u000b!\"\u00198o_R\fG/[8o\u0013\u0011)y#\"\n\u0003#Ut7\r[3dW\u0016$g+\u0019:jC:\u001cW-\u0001\bd_BLH\u0005Z3gCVdG\u000f\n\u001a\u0002\u001d\r|\u0007/\u001f\u0013eK\u001a\fW\u000f\u001c;%g\u0005q1m\u001c9zI\u0011,g-Y;mi\u0012\"\u0014AD2paf$C-\u001a4bk2$H%N\u000b\u0003\u000bwQCa!7\u0006 \u0005q1m\u001c9zI\u0011,g-Y;mi\u00122\u0014AD2paf$C-\u001a4bk2$HeN\u0001\u000fG>\u0004\u0018\u0010\n3fM\u0006,H\u000e\u001e\u00139\u00039\u0019w\u000e]=%I\u00164\u0017-\u001e7uIe*\"!b\u0012+\t\rmXqD\u0001\u0010G>\u0004\u0018\u0010\n3fM\u0006,H\u000e\u001e\u00132a\u0005y1m\u001c9zI\u0011,g-Y;mi\u0012\n\u0014\'\u0006\u0002\u0006P)\"AqAC\u0010\u0003=\u0019w\u000e]=%I\u00164\u0017-\u001e7uIE\u0012TCAC+U\u0011!9\"b\b\u0002\u001bA\u0014x\u000eZ;diB\u0013XMZ5y+\t)Y\u0006\u0005\u0003\u0006^\u0015\u001dTBAC0\u0015\u0011)\t\'b\u0019\u0002\t1\fgn\u001a\u0006\u0003\u000bK\nAA[1wC&!11ZC0\u00031\u0001(o\u001c3vGR\f%/\u001b;z+\t!\u0019+\u0001\bqe>$Wo\u0019;FY\u0016lWM\u001c;\u0015\t\r-X\u0011\u000f\u0005\n\u000bg\u001a\u0016\u0011!a\u0001\tG\u000b1\u0001\u001f\u00132\u0003=\u0001(o\u001c3vGRLE/\u001a:bi>\u0014XCAC=!\u0019)Y(\"!\u0004l6\u0011QQ\u0010\u0006\u0005\u000b\u007f\u001a\u0019+\u0001\u0006d_2dWm\u0019;j_:LA!b!\u0006~\tA\u0011\n^3sCR|\'/\u0001\u0005dC:,\u0015/^1m)\u0011\u0019Y0\"#\t\u0013\u0015MT+!AA\u0002\r-\u0018A\u00059s_\u0012,8\r^#mK6,g\u000e\u001e(b[\u0016$B!b\u0017\u0006\u0010\"IQ1\u000f,\u0002\u0002\u0003\u0007A1U\u0001\tQ\u0006\u001c\bnQ8eKR\u0011A1U\u0001\u0007KF,\u0018\r\\:\u0015\t\rmX\u0011\u0014\u0005\n\u000bgB\u0016\u0011!a\u0001\u0007W\fA\u0001T3bMB\u0019A\u0011\u001d.\u0014\u000bi+\t+\",\u0011=\u0015\rV\u0011VB]\u0007s\u001bIl!/\u0004Z\u000ee7\u0011\\Bm\u0007w\u001cY\u0010b\u0002\u0005\u0018\u0011}WBACS\u0015\u0011)9ka)\u0002\u000fI,h\u000e^5nK&!Q1VCS\u0005I\t%m\u001d;sC\u000e$h)\u001e8di&|g.\r\u001a\u0011\t\u0015=VQW\u0007\u0003\u000bcSA!b-\u0006d\u0005\u0011\u0011n\\\u0005\u0005\t\u000b,\t\f\u0006\u0002\u0006\u001eR\u0011Q1L\u0001\u0006CB\u0004H.\u001f\u000b\u001b\t?,y,\"1\u0006D\u0016\u0015WqYCe\u000b\u0017,i-b4\u0006R\u0016MWQ\u001b\u0005\b\u0007kk\u0006\u0019AB]\u0011\u001d\u0019y-\u0018a\u0001\u0007sCqa!5^\u0001\u0004\u0019I\fC\u0004\u0004Tv\u0003\ra!/\t\u000f\rUW\f1\u0001\u0004Z\"91\u0011_/A\u0002\re\u0007bBBz;\u0002\u00071\u0011\u001c\u0005\b\u0007kl\u0006\u0019ABm\u0011\u001d!)#\u0018a\u0001\u0007wDq\u0001\"\u0001^\u0001\u0004\u0019Y\u0010C\u0004\u0005\u0004u\u0003\r\u0001b\u0002\t\u0013\u0011MQ\f%AA\u0002\u0011]\u0011\u0001E1qa2LH\u0005Z3gCVdG\u000fJ\u00193\u0003\u001d)h.\u00199qYf$B!\"8\u0006fB11\u0011\u0015C\r\u000b?\u0004Bd!)\u0006b\u000ee6\u0011XB]\u0007s\u001bIn!7\u0004Z\u000ee71`B~\t\u000f!9\"\u0003\u0003\u0006d\u000e\r&a\u0002+va2,\u0017G\r\u0005\n\u000bO|\u0016\u0011!a\u0001\t?\f1\u0001\u001f\u00131\u0003q!C.Z:tS:LG\u000fJ4sK\u0006$XM\u001d\u0013eK\u001a\fW\u000f\u001c;%cI\nAb\u001e:ji\u0016\u0014V\r\u001d7bG\u0016$\"!b<\u0011\t\u0015uS\u0011_\u0005\u0005\u000bg,yF\u0001\u0004PE*,7\r\u001e\u0002\u000b-\u0006\u001cWo\\;t3\u0016\u001c8c\u00012\u00042\u0006QQO\u001c3fe2L\u0018N\\4\u0015\t\u0015uXq \t\u0004\tC\u0014\u0007bBC}I\u0002\u00071\u0011W\u0001\u000b-\u0006\u001cWo\\;t3\u0016\u001c\b\u0003\u0002Cq\u0003\u0003\u0019B!!\u0001\u0004 R\u0011a1\u0001\u000b\u0005\u000b{4Y\u0001\u0003\u0005\u0006z\u0006\u0015\u0001\u0019ABY\u0003\tqu\u000e\u0005\u0003\u0005b\u0006%!A\u0001(p\'\u0011\tIaa(\u0015\u0005\u0019=A\u0003\u0006D\r\r;1yB\"\t\u0007$\u0019\u0015bq\u0005D\u0015\rW1i\u0003\u0006\u0003\u0005`\u001am\u0001\u0002\u0003C\u0002\u0003\u001b\u0001\u001d\u0001b\u0002\t\u0011\rU\u0016Q\u0002a\u0001\u0007sC\u0001ba4\u0002\u000e\u0001\u00071\u0011\u0018\u0005\t\u0007#\fi\u00011\u0001\u0004:\"A11[A\u0007\u0001\u0004\u0019I\f\u0003\u0005\u0004V\u00065\u0001\u0019ABm\u0011!\u0019\t0!\u0004A\u0002\re\u0007\u0002CBz\u0003\u001b\u0001\ra!7\t\u0011\rU\u0018Q\u0002a\u0001\u00073D!\u0002b\u0005\u0002\u000eA\u0005\t\u0019\u0001C\f\u0003=\t\u0007\u000f\u001d7zI\u0011,g-Y;mi\u0012JD\u0003\u0003D\u001a\ro1IDb\u000f\u0015\t\u0011}gQ\u0007\u0005\t\t\u0007\t\t\u0002q\u0001\u0005\b!A1QWA\t\u0001\u0004\u0019I\f\u0003\u0005\u0004R\u0006E\u0001\u0019AB]\u0011!\u0019).!\u0005A\u0002\reGC\u0003D \r\u00072)Eb\u0012\u0007JQ!Aq\u001cD!\u0011!!\u0019!a\u0005A\u0004\u0011\u001d\u0001\u0002CB[\u0003\'\u0001\ra!/\t\u0011\rE\u00171\u0003a\u0001\u0007sC\u0001b!6\u0002\u0014\u0001\u00071\u0011\u001c\u0005\t\u0007g\f\u0019\u00021\u0001\u0004ZR1aQ\nD)\r\'\"B\u0001b8\u0007P!AA1AA\u000b\u0001\b!9\u0001\u0003\u0005\u00046\u0006U\u0001\u0019AB]\u0011!\u0019\t.!\u0006A\u0002\reFC\u0003D,\r72iFb\u0018\u0007bQ!Aq\u001cD-\u0011!!\u0019!a\u0006A\u0004\u0011\u001d\u0001\u0002CB[\u0003/\u0001\ra!/\t\u0011\r=\u0017q\u0003a\u0001\u0007sC\u0001b!5\u0002\u0018\u0001\u00071\u0011\u0018\u0005\t\u0007\'\f9\u00021\u0001\u0004:RqaQ\rD5\rW2iGb\u001c\u0007r\u0019MD\u0003\u0002Cp\rOB\u0001\u0002b\u0001\u0002\u001a\u0001\u000fAq\u0001\u0005\t\u0007k\u000bI\u00021\u0001\u0004:\"A1qZA\r\u0001\u0004\u0019I\f\u0003\u0005\u0004R\u0006e\u0001\u0019AB]\u0011!\u0019\u0019.!\u0007A\u0002\re\u0006\u0002CBk\u00033\u0001\ra!7\t\u0011\rE\u0018\u0011\u0004a\u0001\u00073$\"Cb\u001e\u0007|\u0019udq\u0010DA\r\u00073)Ib\"\u0007\nR!Aq\u001cD=\u0011!!\u0019!a\u0007A\u0004\u0011\u001d\u0001\u0002CB[\u00037\u0001\ra!/\t\u0011\r=\u00171\u0004a\u0001\u0007sC\u0001b!5\u0002\u001c\u0001\u00071\u0011\u0018\u0005\t\u0007\'\fY\u00021\u0001\u0004:\"A1Q[A\u000e\u0001\u0004\u0019I\u000e\u0003\u0005\u0004r\u0006m\u0001\u0019ABm\u0011!\u0019\u00190a\u0007A\u0002\re\u0007\u0002CB{\u00037\u0001\ra!7\u0015\t\u00195e\u0011\u0013\u000b\u0005\t?4y\t\u0003\u0005\u0005\u0004\u0005u\u00019\u0001C\u0004\u0011!\u0019),!\bA\u0002\reFC\u0002DK\r33Y\n\u0006\u0003\u0005`\u001a]\u0005\u0002\u0003C\u0002\u0003?\u0001\u001d\u0001b\u0002\t\u0011\rU\u0016q\u0004a\u0001\u0007sC\u0001b!6\u0002 \u0001\u00071\u0011\u001c\u000b\u0007\r?3\u0019K\"*\u0015\t\u0011}g\u0011\u0015\u0005\t\t\u0007\t\t\u0003q\u0001\u0005\b!A1QWA\u0011\u0001\u0004\u0019I\f\u0003\u0005\u0005\u0014\u0005\u0005\u0002\u0019\u0001C\u000f\u0003\rIVm\u001d\t\u0005\tC\f)CA\u0002ZKN\u001cB!!\n\u0004 R\u0011a\u0011\u0016\u000b\u0017\rg39L\"/\u0007<\u001aufq\u0018Da\r\u00074)Mb2\u0007JR!Aq\u001cD[\u0011!!\u0019!!\u000bA\u0004\u0011\u001d\u0001\u0002CB[\u0003S\u0001\ra!/\t\u0011\r=\u0017\u0011\u0006a\u0001\u0007sC\u0001b!5\u0002*\u0001\u00071\u0011\u0018\u0005\t\u0007\'\fI\u00031\u0001\u0004:\"A1Q[A\u0015\u0001\u0004\u0019I\u000e\u0003\u0005\u0004r\u0006%\u0002\u0019ABm\u0011!\u0019\u00190!\u000bA\u0002\re\u0007\u0002CB{\u0003S\u0001\ra!7\t\u0015\u0011\u0005\u0011\u0011\u0006I\u0001\u0002\u0004\u0019Y\u0010\u0003\u0006\u0005\u0014\u0005%\u0002\u0013!a\u0001\t/\t\u0001#\u00199qYf$C-\u001a4bk2$H%\r\u0019\u0015\u0011\u0019=g1\u001bDk\r/$B\u0001b8\u0007R\"AA1AA\u0018\u0001\b!9\u0001\u0003\u0005\u00046\u0006=\u0002\u0019AB]\u0011!\u0019\t.a\fA\u0002\re\u0006\u0002CBk\u0003_\u0001\ra!7\u0015\u0015\u0019mgq\u001cDq\rG4)\u000f\u0006\u0003\u0005`\u001au\u0007\u0002\u0003C\u0002\u0003c\u0001\u001d\u0001b\u0002\t\u0011\rU\u0016\u0011\u0007a\u0001\u0007sC\u0001b!5\u00022\u0001\u00071\u0011\u0018\u0005\t\u0007+\f\t\u00041\u0001\u0004Z\"A11_A\u0019\u0001\u0004\u0019I\u000e\u0006\u0004\u0007j\u001a5hq\u001e\u000b\u0005\t?4Y\u000f\u0003\u0005\u0005\u0004\u0005M\u00029\u0001C\u0004\u0011!\u0019),a\rA\u0002\re\u0006\u0002CBi\u0003g\u0001\ra!/\u0015\u0015\u0019Mhq\u001fD}\rw4i\u0010\u0006\u0003\u0005`\u001aU\b\u0002\u0003C\u0002\u0003k\u0001\u001d\u0001b\u0002\t\u0011\rU\u0016Q\u0007a\u0001\u0007sC\u0001ba4\u00026\u0001\u00071\u0011\u0018\u0005\t\u0007#\f)\u00041\u0001\u0004:\"A11[A\u001b\u0001\u0004\u0019I\f\u0006\b\b\u0002\u001d\u0015qqAD\u0005\u000f\u00179iab\u0004\u0015\t\u0011}w1\u0001\u0005\t\t\u0007\t9\u0004q\u0001\u0005\b!A1QWA\u001c\u0001\u0004\u0019I\f\u0003\u0005\u0004P\u0006]\u0002\u0019AB]\u0011!\u0019\t.a\u000eA\u0002\re\u0006\u0002CBj\u0003o\u0001\ra!/\t\u0011\rU\u0017q\u0007a\u0001\u00073D\u0001b!=\u00028\u0001\u00071\u0011\u001c\u000b\u0013\u000f\'99b\"\u0007\b\u001c\u001duqqDD\u0011\u000fG9)\u0003\u0006\u0003\u0005`\u001eU\u0001\u0002\u0003C\u0002\u0003s\u0001\u001d\u0001b\u0002\t\u0011\rU\u0016\u0011\ba\u0001\u0007sC\u0001ba4\u0002:\u0001\u00071\u0011\u0018\u0005\t\u0007#\fI\u00041\u0001\u0004:\"A11[A\u001d\u0001\u0004\u0019I\f\u0003\u0005\u0004V\u0006e\u0002\u0019ABm\u0011!\u0019\t0!\u000fA\u0002\re\u0007\u0002CBz\u0003s\u0001\ra!7\t\u0011\rU\u0018\u0011\ba\u0001\u00073$Ba\"\u000b\b.Q!Aq\\D\u0016\u0011!!\u0019!a\u000fA\u0004\u0011\u001d\u0001\u0002CB[\u0003w\u0001\ra!/\u0015\r\u001dErQGD\u001c)\u0011!ynb\r\t\u0011\u0011\r\u0011Q\ba\u0002\t\u000fA\u0001b!.\u0002>\u0001\u00071\u0011\u0018\u0005\t\u0007+\fi\u00041\u0001\u0004Z\nYQK\\1ss~##-\u00198h\'!\tyd!-\u0005<\u0012\u0005\u0017aC;oI\u0016\u0014H._5oO\u0002\"Ba\"\u0011\bDA!A\u0011]A \u0011!)I0!\u0012A\u0002\rEF\u0003BB]\u000f\u000fB\u0001\u0002\")\u0002z\u0001\u0007A1\u0015\u000b\u0005\u000f\u0003:Y\u0005\u0003\u0006\u0006z\u0006m\u0004\u0013!a\u0001\u0007c+\"ab\u0014+\t\rEVq\u0004\u000b\u0005\u0007W<\u0019\u0006\u0003\u0006\u0006t\u0005\r\u0015\u0011!a\u0001\tG#Baa?\bX!QQ1OAD\u0003\u0003\u0005\raa;\u0015\t\u0015ms1\f\u0005\u000b\u000bg\nI)!AA\u0002\u0011\rF\u0003BB~\u000f?B!\"b\u001d\u0002\u000e\u0006\u0005\t\u0019ABv\u0003-)f.\u0019:z?\u0012\u0012\u0017M\\4\u0011\t\u0011\u0005\u0018\u0011S\n\u0007\u0003#;9\'\",\u0011\u0011\u0015\rv\u0011NBY\u000f\u0003JAab\u001b\u0006&\n\t\u0012IY:ue\u0006\u001cGOR;oGRLwN\\\u0019\u0015\u0005\u001d\rD\u0003BD!\u000fcB\u0001\"\"?\u0002\u0018\u0002\u00071\u0011\u0017\u000b\u0005\u000fk:9\b\u0005\u0004\u0004\"\u0012e1\u0011\u0017\u0005\u000b\u000bO\fI*!AA\u0002\u001d\u0005\u0013a\u0003\"j]\u0006\u0014\u0018p\u0018\u0013b[B\u0004B\u0001\"9\u0002\\N!\u00111\\BP)\t9Y\b\u0006\u0004\u00042\u001e\ruq\u0011\u0005\t\u000f\u000b\u000by\u000e1\u0001\u00042\u0006!A.\u001a4u\u0011!9I)a8A\u0002\rE\u0016!\u0002:jO\"$(a\u0004\"j]\u0006\u0014\u0018p\u0018\u0013b[B$\u0013-\u001c9\u0014\t\u0005\u0005xq\u0012\t\u0005\tC\fi\n\u0006\u0004\b\u0014\u001eUuq\u0013\t\u0005\tC\f\t\u000f\u0003\u0005\b\u0006\u0006\u001d\b\u0019ABY\u0011!9I)a:A\u0002\rE\u0016\u0001D8qKJ\fGo\u001c:OC6,\u0017a\u0004\"j]\u0006\u0014\u0018p\u0018\u0013b[B$\u0013-\u001c9\u0011\t\u0011\u0005\u0018Q^\n\u0005\u0003[\u001cy\n\u0006\u0002\b\u001eR11\u0011WDS\u000fOC\u0001b\"\"\u0002r\u0002\u00071\u0011\u0017\u0005\t\u000f\u0013\u000b\t\u00101\u0001\u00042\nY!)\u001b8bef|FEY1s\'\u0011\t\u0019p!-\u0015\r\u001d=v\u0011WDZ!\u0011!\t/a=\t\u0011\u001d\u0015\u0015\u0011 a\u0001\u0007cC\u0001b\"#\u0002z\u0002\u00071\u0011\u0017\u000b\u0005\u0007s;9\f\u0003\u0005\u0005\"\n5\u0002\u0019\u0001CR\u0003-\u0011\u0015N\\1ss~##-\u0019:\u0011\t\u0011\u0005(\u0011G\n\u0005\u0005c\u0019y\n\u0006\u0002\b<R11\u0011WDb\u000f\u000bD\u0001b\"\"\u00036\u0001\u00071\u0011\u0017\u0005\t\u000f\u0013\u0013)\u00041\u0001\u00042\ny!)\u001b8bef|FEY1sI\t\f\'o\u0005\u0003\u00038\u001d=FCBDg\u000f\u001f<\t\u000e\u0005\u0003\u0005b\n]\u0002\u0002CDC\u0005{\u0001\ra!-\t\u0011\u001d%%Q\ba\u0001\u0007c\u000bqBQ5oCJLx\f\n2be\u0012\u0012\u0017M\u001d\t\u0005\tC\u0014\u0019e\u0005\u0003\u0003D\r}ECADk)\u0019\u0019\tl\"8\b`\"AqQ\u0011B$\u0001\u0004\u0019\t\f\u0003\u0005\b\n\n\u001d\u0003\u0019ABY\u0005\u001dIU\u000e\u001d7jKN\u001cBA!\u0013\u00042R1qq]Du\u000fW\u0004B\u0001\"9\u0003J!AqQ\u0011B(\u0001\u0004\u0019\t\f\u0003\u0005\b\n\n=\u0003\u0019ABY)\u0011\u0019Ilb<\t\u0011\u0011\u0005&\u0011\u0011a\u0001\tG\u000bq!S7qY&,7\u000f\u0005\u0003\u0005b\n\u00155\u0003\u0002BC\u0007?#\"ab=\u0015\r\rEv1`D\u007f\u0011!9)I!#A\u0002\rE\u0006\u0002CDE\u0005\u0013\u0003\ra!-\u0003\u000f%\u001bX)\u001d<U_N!!1RBY)\u0019A)\u0001c\u0002\t\nA!A\u0011\u001dBF\u0011!9)I!%A\u0002\rE\u0006\u0002CDE\u0005#\u0003\ra!-\u0015\t\re\u0006R\u0002\u0005\t\tC\u0013\u0019\r1\u0001\u0005$\u00069\u0011j]#rmR{\u0007\u0003\u0002Cq\u0005\u000f\u001cBAa2\u0004 R\u0011\u0001\u0012\u0003\u000b\u0007\u0007cCI\u0002c\u0007\t\u0011\u001d\u0015%1\u001aa\u0001\u0007cC\u0001b\"#\u0003L\u0002\u00071\u0011\u0017\u0002\f\u0019\u0006T\u00180T3tg\u0006<Wm\u0005\u0003\u0003N\u000e}EC\u0001E\u0012!\u0011!\tO!4\u0002\u00159,7\u000f^3e\u0003J<7/\u000b\u0006\u0003N\nM71AB2\u0007g\u00111BR1di6+7o]1hKNA!1\u001bE\u0012\tw#\t-\u0001\u0003gC\u000e$\u0018!\u00024bGR\u0004C\u0003\u0002E\u001a\u0011k\u0001B\u0001\"9\u0003T\"A\u0001R\u0006Bm\u0001\u0004\u0019\t,A\u0006oKN$X\rZ!sON\u0004C\u0003\u0002E\u001a\u0011wA!\u0002#\f\u0003bB\u0005\t\u0019ABY)\u0011\u0019Y\u000fc\u0010\t\u0015\u0015M$\u0011^A\u0001\u0002\u0004!\u0019\u000b\u0006\u0003\u0004|\"\r\u0003BCC:\u0005[\f\t\u00111\u0001\u0004lR!Q1\fE$\u0011))\u0019Ha<\u0002\u0002\u0003\u0007A1\u0015\u000b\u0005\u0007wDY\u0005\u0003\u0006\u0006t\tM\u0018\u0011!a\u0001\u0007W\u0014a#T5e\'\u0016tG/\u001a8dK\u001a\u000b7\r^\'fgN\fw-Z\n\t\u0007\u0007A\u0019\u0003b/\u0005BR!\u00012\u000bE+!\u0011!\toa\u0001\t\u0011!52\u0011\u0002a\u0001\u0007c#B\u0001c\u0015\tZ!Q\u0001RFB\t!\u0003\u0005\ra!-\u0015\t\r-\bR\f\u0005\u000b\u000bg\u001aI\"!AA\u0002\u0011\rF\u0003BB~\u0011CB!\"b\u001d\u0004\u001e\u0005\u0005\t\u0019ABv)\u0011)Y\u0006#\u001a\t\u0015\u0015M4qDA\u0001\u0002\u0004!\u0019\u000b\u0006\u0003\u0004|\"%\u0004BCC:\u0007G\t\t\u00111\u0001\u0004l\n\u0001S*\u001b3TK:$XM\\2f\'&l\u0007\u000f\\5gS\u0016$g)Y2u\u001b\u0016\u001c8/Y4f\'!\u0019\u0019\u0007c\t\u0005<\u0012\u0005G\u0003\u0002E9\u0011g\u0002B\u0001\"9\u0004d!A\u0001RFB5\u0001\u0004\u0019\t\f\u0006\u0003\tr!]\u0004B\u0003E\u0017\u0007c\u0002\n\u00111\u0001\u00042R!11\u001eE>\u0011))\u0019h!\u001f\u0002\u0002\u0003\u0007A1\u0015\u000b\u0005\u0007wDy\b\u0003\u0006\u0006t\ru\u0014\u0011!a\u0001\u0007W$B!b\u0017\t\u0004\"QQ1OB@\u0003\u0003\u0005\r\u0001b)\u0015\t\rm\br\u0011\u0005\u000b\u000bg\u001a\u0019)!AA\u0002\r-(!F*j[Bd\u0017NZ5fI\u001a\u000b7\r^\'fgN\fw-Z\n\t\u0007gA\u0019\u0003b/\u0005BR!\u0001r\u0012EI!\u0011!\toa\r\t\u0011!52\u0011\ba\u0001\u0007c#B\u0001c$\t\u0016\"Q\u0001RFB!!\u0003\u0005\ra!-\u0015\t\r-\b\u0012\u0014\u0005\u000b\u000bg\u001aI%!AA\u0002\u0011\rF\u0003BB~\u0011;C!\"b\u001d\u0004N\u0005\u0005\t\u0019ABv)\u0011)Y\u0006#)\t\u0015\u0015M4qJA\u0001\u0002\u0004!\u0019\u000b\u0006\u0003\u0004|\"\u0015\u0006BCC:\u0007\'\n\t\u00111\u0001\u0004l\u0006Ya)Y2u\u001b\u0016\u001c8/Y4f!\u0011!\tOa>\u0014\r\t]\bRVCW!!)\u0019k\"\u001b\u00042\"MBC\u0001EU)\u0011A\u0019\u0004c-\t\u0011!5\"Q a\u0001\u0007c#Ba\"\u001e\t8\"QQq\u001dB\u0000\u0003\u0003\u0005\r\u0001c\r\u0002-5KGmU3oi\u0016t7-\u001a$bGRlUm]:bO\u0016\u0004B\u0001\"9\u0004(M11q\u0005E`\u000b[\u0003\u0002\"b)\bj\rE\u00062\u000b\u000b\u0003\u0011w#B\u0001c\u0015\tF\"A\u0001RFB\u0017\u0001\u0004\u0019\t\f\u0006\u0003\bv!%\u0007BCCt\u0007_\t\t\u00111\u0001\tT\u0005)2+[7qY&4\u0017.\u001a3GC\u000e$X*Z:tC\u001e,\u0007\u0003\u0002Cq\u0007/\u001abaa\u0016\tR\u00165\u0006\u0003CCR\u000fS\u001a\t\fc$\u0015\u0005!5G\u0003\u0002EH\u0011/D\u0001\u0002#\f\u0004^\u0001\u00071\u0011\u0017\u000b\u0005\u000fkBY\u000e\u0003\u0006\u0006h\u000e}\u0013\u0011!a\u0001\u0011\u001f\u000b\u0001%T5e\'\u0016tG/\u001a8dKNKW\u000e\u001d7jM&,GMR1di6+7o]1hKB!A\u0011]BD\'\u0019\u00199\tc9\u0006.BAQ1UD5\u0007cC\t\b\u0006\u0002\t`R!\u0001\u0012\u000fEu\u0011!Aic!$A\u0002\rEF\u0003BD;\u0011[D!\"b:\u0004\u0010\u0006\u0005\t\u0019\u0001E9\'\u0011\tij!-\u0015\r\u001d=\u00052\u001fE{\u0011!9))a)A\u0002\rE\u0006\u0002CDE\u0003G\u0003\ra!-\u0015\t\re\u0006\u0012 \u0005\t\tC\u000b9\u000e1\u0001\u0005$\u0006!a)Y2u\u0001
    #9 = Utf8               java/lang/invoke/MethodHandles$Lookup
   #10 = Class              #9            // java/lang/invoke/MethodHandles$Lookup
   #11 = Utf8               java/lang/invoke/MethodHandles
   #12 = Class              #11           // java/lang/invoke/MethodHandles
   #13 = Utf8               Lookup
   #14 = Utf8               org/scalatest/Fact$Binary_$amp
   #15 = Class              #14           // org/scalatest/Fact$Binary_$amp
   #16 = Utf8               Binary_$amp
   #17 = Utf8               org/scalatest/Fact$Binary_$amp$
   #18 = Class              #17           // org/scalatest/Fact$Binary_$amp$
   #19 = Utf8               Binary_$amp$
   #20 = Utf8               org/scalatest/Fact$Binary_$amp$amp
   #21 = Class              #20           // org/scalatest/Fact$Binary_$amp$amp
   #22 = Utf8               Binary_$amp$amp
   #23 = Utf8               org/scalatest/Fact$Binary_$amp$amp$
   #24 = Class              #23           // org/scalatest/Fact$Binary_$amp$amp$
   #25 = Utf8               Binary_$amp$amp$
   #26 = Utf8               org/scalatest/Fact$Binary_$bar
   #27 = Class              #26           // org/scalatest/Fact$Binary_$bar
   #28 = Utf8               Binary_$bar
   #29 = Utf8               org/scalatest/Fact$Binary_$bar$
   #30 = Class              #29           // org/scalatest/Fact$Binary_$bar$
   #31 = Utf8               Binary_$bar$
   #32 = Utf8               org/scalatest/Fact$Binary_$bar$bar
   #33 = Class              #32           // org/scalatest/Fact$Binary_$bar$bar
   #34 = Utf8               Binary_$bar$bar
   #35 = Utf8               org/scalatest/Fact$Binary_$bar$bar$
   #36 = Class              #35           // org/scalatest/Fact$Binary_$bar$bar$
   #37 = Utf8               Binary_$bar$bar$
   #38 = Utf8               org/scalatest/Fact$FactMessage
   #39 = Class              #38           // org/scalatest/Fact$FactMessage
   #40 = Utf8               FactMessage
   #41 = Utf8               org/scalatest/Fact$FactMessage$
   #42 = Class              #41           // org/scalatest/Fact$FactMessage$
   #43 = Utf8               FactMessage$
   #44 = Utf8               org/scalatest/Fact$Implies
   #45 = Class              #44           // org/scalatest/Fact$Implies
   #46 = Utf8               Implies
   #47 = Utf8               org/scalatest/Fact$Implies$
   #48 = Class              #47           // org/scalatest/Fact$Implies$
   #49 = Utf8               Implies$
   #50 = Utf8               org/scalatest/Fact$IsEqvTo
   #51 = Class              #50           // org/scalatest/Fact$IsEqvTo
   #52 = Utf8               IsEqvTo
   #53 = Utf8               org/scalatest/Fact$IsEqvTo$
   #54 = Class              #53           // org/scalatest/Fact$IsEqvTo$
   #55 = Utf8               IsEqvTo$
   #56 = Utf8               org/scalatest/Fact$LazyMessage
   #57 = Class              #56           // org/scalatest/Fact$LazyMessage
   #58 = Utf8               LazyMessage
   #59 = Utf8               org/scalatest/Fact$Leaf
   #60 = Class              #59           // org/scalatest/Fact$Leaf
   #61 = Utf8               Leaf
   #62 = Utf8               org/scalatest/Fact$Leaf$
   #63 = Class              #62           // org/scalatest/Fact$Leaf$
   #64 = Utf8               Leaf$
   #65 = Utf8               org/scalatest/Fact$MidSentenceFactMessage
   #66 = Class              #65           // org/scalatest/Fact$MidSentenceFactMessage
   #67 = Utf8               MidSentenceFactMessage
   #68 = Utf8               org/scalatest/Fact$MidSentenceFactMessage$
   #69 = Class              #68           // org/scalatest/Fact$MidSentenceFactMessage$
   #70 = Utf8               MidSentenceFactMessage$
   #71 = Utf8               org/scalatest/Fact$MidSentenceSimplifiedFactMessage
   #72 = Class              #71           // org/scalatest/Fact$MidSentenceSimplifiedFactMessage
   #73 = Utf8               MidSentenceSimplifiedFactMessage
   #74 = Utf8               org/scalatest/Fact$MidSentenceSimplifiedFactMessage$
   #75 = Class              #74           // org/scalatest/Fact$MidSentenceSimplifiedFactMessage$
   #76 = Utf8               MidSentenceSimplifiedFactMessage$
   #77 = Utf8               org/scalatest/Fact$No$
   #78 = Class              #77           // org/scalatest/Fact$No$
   #79 = Utf8               No$
   #80 = Utf8               org/scalatest/Fact$SimplifiedFactMessage
   #81 = Class              #80           // org/scalatest/Fact$SimplifiedFactMessage
   #82 = Utf8               SimplifiedFactMessage
   #83 = Utf8               org/scalatest/Fact$SimplifiedFactMessage$
   #84 = Class              #83           // org/scalatest/Fact$SimplifiedFactMessage$
   #85 = Utf8               SimplifiedFactMessage$
   #86 = Utf8               org/scalatest/Fact$Unary_$bang
   #87 = Class              #86           // org/scalatest/Fact$Unary_$bang
   #88 = Utf8               Unary_$bang
   #89 = Utf8               org/scalatest/Fact$Unary_$bang$
   #90 = Class              #89           // org/scalatest/Fact$Unary_$bang$
   #91 = Utf8               Unary_$bang$
   #92 = Utf8               org/scalatest/Fact$VacuousYes
   #93 = Class              #92           // org/scalatest/Fact$VacuousYes
   #94 = Utf8               VacuousYes
   #95 = Utf8               org/scalatest/Fact$VacuousYes$
   #96 = Class              #95           // org/scalatest/Fact$VacuousYes$
   #97 = Utf8               VacuousYes$
   #98 = Utf8               org/scalatest/Fact$Yes$
   #99 = Class              #98           // org/scalatest/Fact$Yes$
  #100 = Utf8               Yes$
  #101 = Utf8               scala/collection/mutable/ArraySeq$ofRef
  #102 = Class              #101          // scala/collection/mutable/ArraySeq$ofRef
  #103 = Utf8               scala/collection/mutable/ArraySeq
  #104 = Class              #103          // scala/collection/mutable/ArraySeq
  #105 = Utf8               ofRef
  #106 = Utf8               cause
  #107 = Utf8               Lscala/Option;
  #108 = Utf8               Lscala/Option<Ljava/lang/Throwable;>;
  #109 = Utf8               NEWLINE
  #110 = Utf8               Ljava/lang/String;
  #111 = Utf8               rawFactMessage
  #112 = Utf8               ()Ljava/lang/String;
  #113 = Utf8               rawSimplifiedFactMessage
  #114 = Utf8               rawMidSentenceFactMessage
  #115 = Utf8               rawMidSentenceSimplifiedFactMessage
  #116 = Utf8               factMessageArgs
  #117 = Utf8               ()Lscala/collection/immutable/IndexedSeq;
  #118 = Utf8               ()Lscala/collection/immutable/IndexedSeq<Ljava/lang/Object;>;
  #119 = Utf8               simplifiedFactMessageArgs
  #120 = Utf8               midSentenceFactMessageArgs
  #121 = Utf8               midSentenceSimplifiedFactMessageArgs
  #122 = Utf8               isLeaf
  #123 = Utf8               ()Z
  #124 = Utf8               isVacuousYes
  #125 = Utf8               prettifier
  #126 = Utf8               ()Lorg/scalactic/Prettifier;
  #127 = Utf8               ()Lscala/Option;
  #128 = Utf8               ()Lscala/Option<Ljava/lang/Throwable;>;
  #129 = NameAndType        #106:#107     // cause:Lscala/Option;
  #130 = Fieldref           #2.#129       // org/scalatest/Fact.cause:Lscala/Option;
  #131 = Utf8               this
  #132 = Utf8               Lorg/scalatest/Fact;
  #133 = Utf8               isYes
  #134 = Utf8               isNo
  #135 = NameAndType        #133:#123     // isYes:()Z
  #136 = Methodref          #2.#135       // org/scalatest/Fact.isYes:()Z
  #137 = Utf8               toBoolean
  #138 = Utf8               toAssertion
  #139 = Utf8               (Lorg/scalactic/source/Position;)Lorg/scalatest/compatible/Assertion;
  #140 = Utf8               pos
  #141 = NameAndType        #124:#123     // isVacuousYes:()Z
  #142 = Methodref          #2.#141       // org/scalatest/Fact.isVacuousYes:()Z
  #143 = Utf8               org/scalatest/Succeeded$
  #144 = Class              #143          // org/scalatest/Succeeded$
  #145 = Utf8               MODULE$
  #146 = Utf8               Lorg/scalatest/Succeeded$;
  #147 = NameAndType        #145:#146     // MODULE$:Lorg/scalatest/Succeeded$;
  #148 = Fieldref           #144.#147     // org/scalatest/Succeeded$.MODULE$:Lorg/scalatest/Succeeded$;
  #149 = Utf8               org/scalatest/exceptions/TestCanceledException
  #150 = Class              #149          // org/scalatest/exceptions/TestCanceledException
  #151 = Utf8               (Ljava/lang/Object;)Ljava/lang/Object;
  #152 = MethodType         #151          //  (Ljava/lang/Object;)Ljava/lang/Object;
  #153 = Utf8               $anonfun$toAssertion$1
  #154 = Utf8               (Lorg/scalatest/Fact;Lorg/scalatest/exceptions/StackDepthException;)Lscala/Some;
  #155 = NameAndType        #153:#154     // $anonfun$toAssertion$1:(Lorg/scalatest/Fact;Lorg/scalatest/exceptions/StackDepthException;)Lscala/Some;
  #156 = Methodref          #2.#155       // org/scalatest/Fact.$anonfun$toAssertion$1:(Lorg/scalatest/Fact;Lorg/scalatest/exceptions/StackDepthException;)Lscala/Some;
  #157 = MethodHandle       6:#156        // REF_invokeStatic org/scalatest/Fact.$anonfun$toAssertion$1:(Lorg/scalatest/Fact;Lorg/scalatest/exceptions/StackDepthException;)Lscala/Some;
  #158 = Utf8               (Lorg/scalatest/exceptions/StackDepthException;)Lscala/Some;
  #159 = MethodType         #158          //  (Lorg/scalatest/exceptions/StackDepthException;)Lscala/Some;
  #160 = Integer            5
  #161 = Integer            1
  #162 = Utf8               java/lang/invoke/LambdaMetafactory
  #163 = Class              #162          // java/lang/invoke/LambdaMetafactory
  #164 = Utf8               altMetafactory
  #165 = Utf8               (Ljava/lang/invoke/MethodHandles$Lookup;Ljava/lang/String;Ljava/lang/invoke/MethodType;[Ljava/lang/Object;)Ljava/lang/invoke/CallSite;
  #166 = NameAndType        #164:#165     // altMetafactory:(Ljava/lang/invoke/MethodHandles$Lookup;Ljava/lang/String;Ljava/lang/invoke/MethodType;[Ljava/lang/Object;)Ljava/lang/invoke/CallSite;
  #167 = Methodref          #163.#166     // java/lang/invoke/LambdaMetafactory.altMetafactory:(Ljava/lang/invoke/MethodHandles$Lookup;Ljava/lang/String;Ljava/lang/invoke/MethodType;[Ljava/lang/Object;)Ljava/lang/invoke/CallSite;
  #168 = MethodHandle       6:#167        // REF_invokeStatic java/lang/invoke/LambdaMetafactory.altMetafactory:(Ljava/lang/invoke/MethodHandles$Lookup;Ljava/lang/String;Ljava/lang/invoke/MethodType;[Ljava/lang/Object;)Ljava/lang/invoke/CallSite;
  #169 = Utf8               apply
  #170 = Utf8               (Lorg/scalatest/Fact;)Lscala/Function1;
  #171 = NameAndType        #169:#170     // apply:(Lorg/scalatest/Fact;)Lscala/Function1;
  #172 = InvokeDynamic      #0:#171       // #0:apply:(Lorg/scalatest/Fact;)Lscala/Function1;
  #173 = Utf8               scala/None$
  #174 = Class              #173          // scala/None$
  #175 = Utf8               Lscala/None$;
  #176 = NameAndType        #145:#175     // MODULE$:Lscala/None$;
  #177 = Fieldref           #174.#176     // scala/None$.MODULE$:Lscala/None$;
  #178 = Utf8               <init>
  #179 = Utf8               (Lscala/Function1;Lscala/Option;Lorg/scalactic/source/Position;Lscala/Option;)V
  #180 = NameAndType        #178:#179     // "<init>":(Lscala/Function1;Lscala/Option;Lorg/scalactic/source/Position;Lscala/Option;)V
  #181 = Methodref          #150.#180     // org/scalatest/exceptions/TestCanceledException."<init>":(Lscala/Function1;Lscala/Option;Lorg/scalactic/source/Position;Lscala/Option;)V
  #182 = Utf8               org/scalatest/exceptions/TestFailedException
  #183 = Class              #182          // org/scalatest/exceptions/TestFailedException
  #184 = Utf8               $anonfun$toAssertion$2
  #185 = NameAndType        #184:#154     // $anonfun$toAssertion$2:(Lorg/scalatest/Fact;Lorg/scalatest/exceptions/StackDepthException;)Lscala/Some;
  #186 = Methodref          #2.#185       // org/scalatest/Fact.$anonfun$toAssertion$2:(Lorg/scalatest/Fact;Lorg/scalatest/exceptions/StackDepthException;)Lscala/Some;
  #187 = MethodHandle       6:#186        // REF_invokeStatic org/scalatest/Fact.$anonfun$toAssertion$2:(Lorg/scalatest/Fact;Lorg/scalatest/exceptions/StackDepthException;)Lscala/Some;
  #188 = InvokeDynamic      #1:#171       // #1:apply:(Lorg/scalatest/Fact;)Lscala/Function1;
  #189 = Utf8               (Lscala/Function1;Lscala/Option;Lorg/scalactic/source/Position;)V
  #190 = NameAndType        #178:#189     // "<init>":(Lscala/Function1;Lscala/Option;Lorg/scalactic/source/Position;)V
  #191 = Methodref          #183.#190     // org/scalatest/exceptions/TestFailedException."<init>":(Lscala/Function1;Lscala/Option;Lorg/scalactic/source/Position;)V
  #192 = Utf8               Lorg/scalactic/source/Position;
  #193 = Utf8               internalToAssertion
  #194 = Utf8               $anonfun$internalToAssertion$1
  #195 = NameAndType        #194:#154     // $anonfun$internalToAssertion$1:(Lorg/scalatest/Fact;Lorg/scalatest/exceptions/StackDepthException;)Lscala/Some;
  #196 = Methodref          #2.#195       // org/scalatest/Fact.$anonfun$internalToAssertion$1:(Lorg/scalatest/Fact;Lorg/scalatest/exceptions/StackDepthException;)Lscala/Some;
  #197 = MethodHandle       6:#196        // REF_invokeStatic org/scalatest/Fact.$anonfun$internalToAssertion$1:(Lorg/scalatest/Fact;Lorg/scalatest/exceptions/StackDepthException;)Lscala/Some;
  #198 = InvokeDynamic      #2:#171       // #2:apply:(Lorg/scalatest/Fact;)Lscala/Function1;
  #199 = Utf8               $anonfun$internalToAssertion$2
  #200 = NameAndType        #199:#154     // $anonfun$internalToAssertion$2:(Lorg/scalatest/Fact;Lorg/scalatest/exceptions/StackDepthException;)Lscala/Some;
  #201 = Methodref          #2.#200       // org/scalatest/Fact.$anonfun$internalToAssertion$2:(Lorg/scalatest/Fact;Lorg/scalatest/exceptions/StackDepthException;)Lscala/Some;
  #202 = MethodHandle       6:#201        // REF_invokeStatic org/scalatest/Fact.$anonfun$internalToAssertion$2:(Lorg/scalatest/Fact;Lorg/scalatest/exceptions/StackDepthException;)Lscala/Some;
  #203 = InvokeDynamic      #3:#171       // #3:apply:(Lorg/scalatest/Fact;)Lscala/Function1;
  #204 = Utf8               unary_$bang
  #205 = Utf8               ()Lorg/scalatest/Fact;
  #206 = Utf8               (Lorg/scalatest/Fact;)V
  #207 = NameAndType        #178:#206     // "<init>":(Lorg/scalatest/Fact;)V
  #208 = Methodref          #87.#207      // org/scalatest/Fact$Unary_$bang."<init>":(Lorg/scalatest/Fact;)V
  #209 = Utf8               $bar$bar
  #210 = Utf8               (Lscala/Function0;)Lorg/scalatest/Fact;
  #211 = Utf8               (Lscala/Function0<Lorg/scalatest/Fact;>;)Lorg/scalatest/Fact;
  #212 = Utf8               rhs
  #213 = Utf8               Lorg/scalatest/Fact$Binary_$bar$bar$;
  #214 = NameAndType        #145:#213     // MODULE$:Lorg/scalatest/Fact$Binary_$bar$bar$;
  #215 = Fieldref           #36.#214      // org/scalatest/Fact$Binary_$bar$bar$.MODULE$:Lorg/scalatest/Fact$Binary_$bar$bar$;
  #216 = Utf8               scala/Function0
  #217 = Class              #216          // scala/Function0
  #218 = Utf8               ()Ljava/lang/Object;
  #219 = NameAndType        #169:#218     // apply:()Ljava/lang/Object;
  #220 = InterfaceMethodref #217.#219     // scala/Function0.apply:()Ljava/lang/Object;
  #221 = Utf8               (Lorg/scalatest/Fact;Lorg/scalatest/Fact;)Lorg/scalatest/Fact;
  #222 = NameAndType        #169:#221     // apply:(Lorg/scalatest/Fact;Lorg/scalatest/Fact;)Lorg/scalatest/Fact;
  #223 = Methodref          #36.#222      // org/scalatest/Fact$Binary_$bar$bar$.apply:(Lorg/scalatest/Fact;Lorg/scalatest/Fact;)Lorg/scalatest/Fact;
  #224 = Utf8               Lscala/Function0;
  #225 = Utf8               $amp$amp
  #226 = NameAndType        #134:#123     // isNo:()Z
  #227 = Methodref          #2.#226       // org/scalatest/Fact.isNo:()Z
  #228 = Utf8               Lorg/scalatest/Fact$Binary_$amp$amp$;
  #229 = NameAndType        #145:#228     // MODULE$:Lorg/scalatest/Fact$Binary_$amp$amp$;
  #230 = Fieldref           #24.#229      // org/scalatest/Fact$Binary_$amp$amp$.MODULE$:Lorg/scalatest/Fact$Binary_$amp$amp$;
  #231 = Methodref          #24.#222      // org/scalatest/Fact$Binary_$amp$amp$.apply:(Lorg/scalatest/Fact;Lorg/scalatest/Fact;)Lorg/scalatest/Fact;
  #232 = Utf8               $bar
  #233 = Utf8               (Lorg/scalatest/Fact;)Lorg/scalatest/Fact;
  #234 = Utf8               Lorg/scalatest/Fact$Binary_$bar$;
  #235 = NameAndType        #145:#234     // MODULE$:Lorg/scalatest/Fact$Binary_$bar$;
  #236 = Fieldref           #30.#235      // org/scalatest/Fact$Binary_$bar$.MODULE$:Lorg/scalatest/Fact$Binary_$bar$;
  #237 = Methodref          #30.#222      // org/scalatest/Fact$Binary_$bar$.apply:(Lorg/scalatest/Fact;Lorg/scalatest/Fact;)Lorg/scalatest/Fact;
  #238 = Utf8               $amp
  #239 = Utf8               Lorg/scalatest/Fact$Binary_$amp$;
  #240 = NameAndType        #145:#239     // MODULE$:Lorg/scalatest/Fact$Binary_$amp$;
  #241 = Fieldref           #18.#240      // org/scalatest/Fact$Binary_$amp$.MODULE$:Lorg/scalatest/Fact$Binary_$amp$;
  #242 = Methodref          #18.#222      // org/scalatest/Fact$Binary_$amp$.apply:(Lorg/scalatest/Fact;Lorg/scalatest/Fact;)Lorg/scalatest/Fact;
  #243 = Utf8               stringPrefix
  #244 = String             #94           // VacuousYes
  #245 = Utf8               Yes
  #246 = String             #245          // Yes
  #247 = Utf8               No
  #248 = String             #247          // No
  #249 = Utf8               java/lang/String
  #250 = Class              #249          // java/lang/String
  #251 = Utf8               implies
  #252 = Utf8               Lorg/scalatest/Fact$VacuousYes$;
  #253 = NameAndType        #145:#252     // MODULE$:Lorg/scalatest/Fact$VacuousYes$;
  #254 = Fieldref           #96.#253      // org/scalatest/Fact$VacuousYes$.MODULE$:Lorg/scalatest/Fact$VacuousYes$;
  #255 = Utf8               (Lorg/scalatest/Fact;)Lorg/scalatest/Fact$VacuousYes;
  #256 = NameAndType        #169:#255     // apply:(Lorg/scalatest/Fact;)Lorg/scalatest/Fact$VacuousYes;
  #257 = Methodref          #96.#256      // org/scalatest/Fact$VacuousYes$.apply:(Lorg/scalatest/Fact;)Lorg/scalatest/Fact$VacuousYes;
  #258 = Utf8               Lorg/scalatest/Fact$Implies$;
  #259 = NameAndType        #145:#258     // MODULE$:Lorg/scalatest/Fact$Implies$;
  #260 = Fieldref           #48.#259      // org/scalatest/Fact$Implies$.MODULE$:Lorg/scalatest/Fact$Implies$;
  #261 = Methodref          #48.#222      // org/scalatest/Fact$Implies$.apply:(Lorg/scalatest/Fact;Lorg/scalatest/Fact;)Lorg/scalatest/Fact;
  #262 = Utf8               isEqvTo
  #263 = Utf8               Lorg/scalatest/Fact$IsEqvTo$;
  #264 = NameAndType        #145:#263     // MODULE$:Lorg/scalatest/Fact$IsEqvTo$;
  #265 = Fieldref           #54.#264      // org/scalatest/Fact$IsEqvTo$.MODULE$:Lorg/scalatest/Fact$IsEqvTo$;
  #266 = Methodref          #54.#222      // org/scalatest/Fact$IsEqvTo$.apply:(Lorg/scalatest/Fact;Lorg/scalatest/Fact;)Lorg/scalatest/Fact;
  #267 = Utf8               factMessage
  #268 = NameAndType        #116:#117     // factMessageArgs:()Lscala/collection/immutable/IndexedSeq;
  #269 = Methodref          #2.#268       // org/scalatest/Fact.factMessageArgs:()Lscala/collection/immutable/IndexedSeq;
  #270 = Utf8               scala/collection/immutable/IndexedSeq
  #271 = Class              #270          // scala/collection/immutable/IndexedSeq
  #272 = Utf8               isEmpty
  #273 = NameAndType        #272:#123     // isEmpty:()Z
  #274 = InterfaceMethodref #271.#273     // scala/collection/immutable/IndexedSeq.isEmpty:()Z
  #275 = NameAndType        #111:#112     // rawFactMessage:()Ljava/lang/String;
  #276 = Methodref          #2.#275       // org/scalatest/Fact.rawFactMessage:()Ljava/lang/String;
  #277 = Utf8               makeString
  #278 = Utf8               (Ljava/lang/String;Lscala/collection/immutable/IndexedSeq;)Ljava/lang/String;
  #279 = NameAndType        #277:#278     // makeString:(Ljava/lang/String;Lscala/collection/immutable/IndexedSeq;)Ljava/lang/String;
  #280 = Methodref          #2.#279       // org/scalatest/Fact.makeString:(Ljava/lang/String;Lscala/collection/immutable/IndexedSeq;)Ljava/lang/String;
  #281 = Utf8               simplifiedFactMessage
  #282 = NameAndType        #119:#117     // simplifiedFactMessageArgs:()Lscala/collection/immutable/IndexedSeq;
  #283 = Methodref          #2.#282       // org/scalatest/Fact.simplifiedFactMessageArgs:()Lscala/collection/immutable/IndexedSeq;
  #284 = NameAndType        #113:#112     // rawSimplifiedFactMessage:()Ljava/lang/String;
  #285 = Methodref          #2.#284       // org/scalatest/Fact.rawSimplifiedFactMessage:()Ljava/lang/String;
  #286 = Utf8               midSentenceFactMessage
  #287 = NameAndType        #120:#117     // midSentenceFactMessageArgs:()Lscala/collection/immutable/IndexedSeq;
  #288 = Methodref          #2.#287       // org/scalatest/Fact.midSentenceFactMessageArgs:()Lscala/collection/immutable/IndexedSeq;
  #289 = NameAndType        #114:#112     // rawMidSentenceFactMessage:()Ljava/lang/String;
  #290 = Methodref          #2.#289       // org/scalatest/Fact.rawMidSentenceFactMessage:()Ljava/lang/String;
  #291 = Utf8               midSentenceSimplifiedFactMessage
  #292 = NameAndType        #121:#117     // midSentenceSimplifiedFactMessageArgs:()Lscala/collection/immutable/IndexedSeq;
  #293 = Methodref          #2.#292       // org/scalatest/Fact.midSentenceSimplifiedFactMessageArgs:()Lscala/collection/immutable/IndexedSeq;
  #294 = NameAndType        #115:#112     // rawMidSentenceSimplifiedFactMessage:()Ljava/lang/String;
  #295 = Methodref          #2.#294       // org/scalatest/Fact.rawMidSentenceSimplifiedFactMessage:()Ljava/lang/String;
  #296 = Utf8               (Ljava/lang/String;Lscala/collection/immutable/IndexedSeq<Ljava/lang/Object;>;)Ljava/lang/String;
  #297 = Utf8               raw
  #298 = Utf8               args
  #299 = Utf8               org/scalatest/Resources$
  #300 = Class              #299          // org/scalatest/Resources$
  #301 = Utf8               Lorg/scalatest/Resources$;
  #302 = NameAndType        #145:#301     // MODULE$:Lorg/scalatest/Resources$;
  #303 = Fieldref           #300.#302     // org/scalatest/Resources$.MODULE$:Lorg/scalatest/Resources$;
  #304 = Utf8               $anonfun$makeString$1
  #305 = Utf8               (Lorg/scalatest/Fact;Ljava/lang/Object;)Ljava/lang/String;
  #306 = NameAndType        #304:#305     // $anonfun$makeString$1:(Lorg/scalatest/Fact;Ljava/lang/Object;)Ljava/lang/String;
  #307 = Methodref          #2.#306       // org/scalatest/Fact.$anonfun$makeString$1:(Lorg/scalatest/Fact;Ljava/lang/Object;)Ljava/lang/String;
  #308 = MethodHandle       6:#307        // REF_invokeStatic org/scalatest/Fact.$anonfun$makeString$1:(Lorg/scalatest/Fact;Ljava/lang/Object;)Ljava/lang/String;
  #309 = Utf8               (Ljava/lang/Object;)Ljava/lang/String;
  #310 = MethodType         #309          //  (Ljava/lang/Object;)Ljava/lang/String;
  #311 = InvokeDynamic      #4:#171       // #4:apply:(Lorg/scalatest/Fact;)Lscala/Function1;
  #312 = Utf8               map
  #313 = Utf8               (Lscala/Function1;)Ljava/lang/Object;
  #314 = NameAndType        #312:#313     // map:(Lscala/Function1;)Ljava/lang/Object;
  #315 = InterfaceMethodref #271.#314     // scala/collection/immutable/IndexedSeq.map:(Lscala/Function1;)Ljava/lang/Object;
  #316 = Utf8               scala/collection/IterableOnceOps
  #317 = Class              #316          // scala/collection/IterableOnceOps
  #318 = Utf8               scala/reflect/ClassTag$
  #319 = Class              #318          // scala/reflect/ClassTag$
  #320 = Utf8               Lscala/reflect/ClassTag$;
  #321 = NameAndType        #145:#320     // MODULE$:Lscala/reflect/ClassTag$;
  #322 = Fieldref           #319.#321     // scala/reflect/ClassTag$.MODULE$:Lscala/reflect/ClassTag$;
  #323 = Utf8               Any
  #324 = Utf8               ()Lscala/reflect/ClassTag;
  #325 = NameAndType        #323:#324     // Any:()Lscala/reflect/ClassTag;
  #326 = Methodref          #319.#325     // scala/reflect/ClassTag$.Any:()Lscala/reflect/ClassTag;
  #327 = Utf8               toArray
  #328 = Utf8               (Lscala/reflect/ClassTag;)Ljava/lang/Object;
  #329 = NameAndType        #327:#328     // toArray:(Lscala/reflect/ClassTag;)Ljava/lang/Object;
  #330 = InterfaceMethodref #317.#329     // scala/collection/IterableOnceOps.toArray:(Lscala/reflect/ClassTag;)Ljava/lang/Object;
  #331 = Utf8               [Ljava/lang/Object;
  #332 = Class              #331          // "[Ljava/lang/Object;"
  #333 = Utf8               formatString
  #334 = Utf8               (Ljava/lang/String;[Ljava/lang/Object;)Ljava/lang/String;
  #335 = NameAndType        #333:#334     // formatString:(Ljava/lang/String;[Ljava/lang/Object;)Ljava/lang/String;
  #336 = Methodref          #300.#335     // org/scalatest/Resources$.formatString:(Ljava/lang/String;[Ljava/lang/Object;)Ljava/lang/String;
  #337 = Utf8               Lscala/collection/immutable/IndexedSeq;
  #338 = NameAndType        #109:#110     // NEWLINE:Ljava/lang/String;
  #339 = Fieldref           #2.#338       // org/scalatest/Fact.NEWLINE:Ljava/lang/String;
  #340 = Utf8               factDiagram
  #341 = Utf8               (I)Ljava/lang/String;
  #342 = Utf8               level
  #343 = NameAndType        #286:#112     // midSentenceFactMessage:()Ljava/lang/String;
  #344 = Methodref          #2.#343       // org/scalatest/Fact.midSentenceFactMessage:()Ljava/lang/String;
  #345 = Utf8               scala/collection/StringOps$
  #346 = Class              #345          // scala/collection/StringOps$
  #347 = Utf8               Lscala/collection/StringOps$;
  #348 = NameAndType        #145:#347     // MODULE$:Lscala/collection/StringOps$;
  #349 = Fieldref           #346.#348     // scala/collection/StringOps$.MODULE$:Lscala/collection/StringOps$;
  #350 = Utf8               scala/Predef$
  #351 = Class              #350          // scala/Predef$
  #352 = Utf8               Lscala/Predef$;
  #353 = NameAndType        #145:#352     // MODULE$:Lscala/Predef$;
  #354 = Fieldref           #351.#353     // scala/Predef$.MODULE$:Lscala/Predef$;
  #355 = Utf8
  #356 = String             #355          //
  #357 = Utf8               augmentString
  #358 = Utf8               (Ljava/lang/String;)Ljava/lang/String;
  #359 = NameAndType        #357:#358     // augmentString:(Ljava/lang/String;)Ljava/lang/String;
  #360 = Methodref          #351.#359     // scala/Predef$.augmentString:(Ljava/lang/String;)Ljava/lang/String;
  #361 = Utf8               $times$extension
  #362 = Utf8               (Ljava/lang/String;I)Ljava/lang/String;
  #363 = NameAndType        #361:#362     // $times$extension:(Ljava/lang/String;I)Ljava/lang/String;
  #364 = Methodref          #346.#363     // scala/collection/StringOps$.$times$extension:(Ljava/lang/String;I)Ljava/lang/String;
  #365 = Utf8               \n
  #366 = String             #365          // \n
  #367 = Utf8               contains
  #368 = Utf8               (Ljava/lang/CharSequence;)Z
  #369 = NameAndType        #367:#368     // contains:(Ljava/lang/CharSequence;)Z
  #370 = Methodref          #250.#369     // java/lang/String.contains:(Ljava/lang/CharSequence;)Z
  #371 = Utf8               java/lang/StringBuilder
  #372 = Class              #371          // java/lang/StringBuilder
  #373 = Integer            2
  #374 = Utf8               (I)V
  #375 = NameAndType        #178:#374     // "<init>":(I)V
  #376 = Methodref          #372.#375     // java/lang/StringBuilder."<init>":(I)V
  #377 = Utf8               append
  #378 = Utf8               (Ljava/lang/String;)Ljava/lang/StringBuilder;
  #379 = NameAndType        #377:#378     // append:(Ljava/lang/String;)Ljava/lang/StringBuilder;
  #380 = Methodref          #372.#379     // java/lang/StringBuilder.append:(Ljava/lang/String;)Ljava/lang/StringBuilder;
  #381 = NameAndType        #243:#112     // stringPrefix:()Ljava/lang/String;
  #382 = Methodref          #2.#381       // org/scalatest/Fact.stringPrefix:()Ljava/lang/String;
  #383 = Utf8               (
  #384 = String             #383          // (
  #385 = NameAndType        #109:#112     // NEWLINE:()Ljava/lang/String;
  #386 = Methodref          #2.#385       // org/scalatest/Fact.NEWLINE:()Ljava/lang/String;
  #387 = Utf8               scala/collection/ArrayOps$
  #388 = Class              #387          // scala/collection/ArrayOps$
  #389 = Utf8               Lscala/collection/ArrayOps$;
  #390 = NameAndType        #145:#389     // MODULE$:Lscala/collection/ArrayOps$;
  #391 = Fieldref           #388.#390     // scala/collection/ArrayOps$.MODULE$:Lscala/collection/ArrayOps$;
  #392 = Utf8               split
  #393 = Utf8               (Ljava/lang/String;)[Ljava/lang/String;
  #394 = NameAndType        #392:#393     // split:(Ljava/lang/String;)[Ljava/lang/String;
  #395 = Methodref          #250.#394     // java/lang/String.split:(Ljava/lang/String;)[Ljava/lang/String;
  #396 = Utf8               refArrayOps
  #397 = Utf8               ([Ljava/lang/Object;)Ljava/lang/Object;
  #398 = NameAndType        #396:#397     // refArrayOps:([Ljava/lang/Object;)Ljava/lang/Object;
  #399 = Methodref          #351.#398     // scala/Predef$.refArrayOps:([Ljava/lang/Object;)Ljava/lang/Object;
  #400 = Utf8               $anonfun$factDiagram$1
  #401 = Utf8               (Ljava/lang/String;Ljava/lang/String;)Ljava/lang/String;
  #402 = NameAndType        #400:#401     // $anonfun$factDiagram$1:(Ljava/lang/String;Ljava/lang/String;)Ljava/lang/String;
  #403 = Methodref          #2.#402       // org/scalatest/Fact.$anonfun$factDiagram$1:(Ljava/lang/String;Ljava/lang/String;)Ljava/lang/String;
  #404 = MethodHandle       6:#403        // REF_invokeStatic org/scalatest/Fact.$anonfun$factDiagram$1:(Ljava/lang/String;Ljava/lang/String;)Ljava/lang/String;
  #405 = MethodType         #358          //  (Ljava/lang/String;)Ljava/lang/String;
  #406 = Utf8               (Ljava/lang/String;)Lscala/Function1;
  #407 = NameAndType        #169:#406     // apply:(Ljava/lang/String;)Lscala/Function1;
  #408 = InvokeDynamic      #5:#407       // #5:apply:(Ljava/lang/String;)Lscala/Function1;
  #409 = Utf8               (Ljava/lang/Class;)Lscala/reflect/ClassTag;
  #410 = NameAndType        #169:#409     // apply:(Ljava/lang/Class;)Lscala/reflect/ClassTag;
  #411 = Methodref          #319.#410     // scala/reflect/ClassTag$.apply:(Ljava/lang/Class;)Lscala/reflect/ClassTag;
  #412 = Utf8               map$extension
  #413 = Utf8               (Ljava/lang/Object;Lscala/Function1;Lscala/reflect/ClassTag;)Ljava/lang/Object;
  #414 = NameAndType        #412:#413     // map$extension:(Ljava/lang/Object;Lscala/Function1;Lscala/reflect/ClassTag;)Ljava/lang/Object;
  #415 = Methodref          #388.#414     // scala/collection/ArrayOps$.map$extension:(Ljava/lang/Object;Lscala/Function1;Lscala/reflect/ClassTag;)Ljava/lang/Object;
  #416 = Utf8               wrapRefArray
  #417 = Utf8               ([Ljava/lang/Object;)Lscala/collection/mutable/ArraySeq$ofRef;
  #418 = NameAndType        #416:#417     // wrapRefArray:([Ljava/lang/Object;)Lscala/collection/mutable/ArraySeq$ofRef;
  #419 = Methodref          #351.#418     // scala/Predef$.wrapRefArray:([Ljava/lang/Object;)Lscala/collection/mutable/ArraySeq$ofRef;
  #420 = Utf8               mkString
  #421 = NameAndType        #420:#358     // mkString:(Ljava/lang/String;)Ljava/lang/String;
  #422 = Methodref          #102.#421     // scala/collection/mutable/ArraySeq$ofRef.mkString:(Ljava/lang/String;)Ljava/lang/String;
  #423 = Utf8               )
  #424 = String             #423          // )
  #425 = Utf8               toString
  #426 = NameAndType        #425:#112     // toString:()Ljava/lang/String;
  #427 = Methodref          #372.#426     // java/lang/StringBuilder.toString:()Ljava/lang/String;
  #428 = Utf8               padding
  #429 = Utf8               msg
  #430 = Utf8               I
  #431 = NameAndType        #340:#341     // factDiagram:(I)Ljava/lang/String;
  #432 = Methodref          #2.#431       // org/scalatest/Fact.factDiagram:(I)Ljava/lang/String;
  #433 = Utf8               $this
  #434 = Utf8               e
  #435 = Utf8               scala/Some
  #436 = Class              #435          // scala/Some
  #437 = NameAndType        #267:#112     // factMessage:()Ljava/lang/String;
  #438 = Methodref          #2.#437       // org/scalatest/Fact.factMessage:()Ljava/lang/String;
  #439 = Utf8               (Ljava/lang/Object;)V
  #440 = NameAndType        #178:#439     // "<init>":(Ljava/lang/Object;)V
  #441 = Methodref          #436.#440     // scala/Some."<init>":(Ljava/lang/Object;)V
  #442 = Utf8               Lorg/scalatest/exceptions/StackDepthException;
  #443 = Utf8               o
  #444 = NameAndType        #125:#126     // prettifier:()Lorg/scalactic/Prettifier;
  #445 = Methodref          #2.#444       // org/scalatest/Fact.prettifier:()Lorg/scalactic/Prettifier;
  #446 = Utf8               org/scalactic/Prettifier
  #447 = Class              #446          // org/scalactic/Prettifier
  #448 = NameAndType        #169:#309     // apply:(Ljava/lang/Object;)Ljava/lang/String;
  #449 = InterfaceMethodref #447.#448     // org/scalactic/Prettifier.apply:(Ljava/lang/Object;)Ljava/lang/String;
  #450 = Utf8               Ljava/lang/Object;
  #451 = Utf8               padding$1
  #452 = Utf8               line
  #453 = Utf8               ()V
  #454 = NameAndType        #178:#453     // "<init>":()V
  #455 = Methodref          #4.#454       // java/lang/Object."<init>":()V
  #456 = Utf8               scala/compat/Platform$
  #457 = Class              #456          // scala/compat/Platform$
  #458 = Utf8               Lscala/compat/Platform$;
  #459 = NameAndType        #145:#458     // MODULE$:Lscala/compat/Platform$;
  #460 = Fieldref           #457.#459     // scala/compat/Platform$.MODULE$:Lscala/compat/Platform$;
  #461 = Utf8               EOL
  #462 = NameAndType        #461:#112     // EOL:()Ljava/lang/String;
  #463 = Methodref          #457.#462     // scala/compat/Platform$.EOL:()Ljava/lang/String;
  #464 = Utf8               $deserializeLambda$
  #465 = Utf8               (Ljava/lang/invoke/SerializedLambda;)Ljava/lang/Object;
  #466 = Utf8               scala/runtime/LambdaDeserialize
  #467 = Class              #466          // scala/runtime/LambdaDeserialize
  #468 = Utf8               bootstrap
  #469 = Utf8               (Ljava/lang/invoke/MethodHandles$Lookup;Ljava/lang/String;Ljava/lang/invoke/MethodType;[Ljava/lang/invoke/MethodHandle;)Ljava/lang/invoke/CallSite;
  #470 = NameAndType        #468:#469     // bootstrap:(Ljava/lang/invoke/MethodHandles$Lookup;Ljava/lang/String;Ljava/lang/invoke/MethodType;[Ljava/lang/invoke/MethodHandle;)Ljava/lang/invoke/CallSite;
  #471 = Methodref          #467.#470     // scala/runtime/LambdaDeserialize.bootstrap:(Ljava/lang/invoke/MethodHandles$Lookup;Ljava/lang/String;Ljava/lang/invoke/MethodType;[Ljava/lang/invoke/MethodHandle;)Ljava/lang/invoke/CallSite;
  #472 = MethodHandle       6:#471        // REF_invokeStatic scala/runtime/LambdaDeserialize.bootstrap:(Ljava/lang/invoke/MethodHandles$Lookup;Ljava/lang/String;Ljava/lang/invoke/MethodType;[Ljava/lang/invoke/MethodHandle;)Ljava/lang/invoke/CallSite;
  #473 = Utf8               lambdaDeserialize
  #474 = NameAndType        #473:#465     // lambdaDeserialize:(Ljava/lang/invoke/SerializedLambda;)Ljava/lang/Object;
  #475 = InvokeDynamic      #6:#474       // #6:lambdaDeserialize:(Ljava/lang/invoke/SerializedLambda;)Ljava/lang/Object;
  #476 = Utf8               Signature
  #477 = Utf8               Code
  #478 = Utf8               LineNumberTable
  #479 = Utf8               LocalVariableTable
  #480 = Utf8               StackMapTable
  #481 = Utf8               MethodParameters
  #482 = Utf8               InnerClasses
  #483 = Utf8               SourceFile
  #484 = Utf8               RuntimeVisibleAnnotations
  #485 = Utf8               BootstrapMethods
  #486 = Utf8               ScalaInlineInfo
  #487 = Utf8               ScalaSig
{
  private final scala.Option<java.lang.Throwable> cause;
    descriptor: Lscala/Option;
    flags: (0x0012) ACC_PRIVATE, ACC_FINAL
    Signature: #108                         // Lscala/Option<Ljava/lang/Throwable;>;

  private final java.lang.String NEWLINE;
    descriptor: Ljava/lang/String;
    flags: (0x0012) ACC_PRIVATE, ACC_FINAL

  public abstract java.lang.String rawFactMessage();
    descriptor: ()Ljava/lang/String;
    flags: (0x0401) ACC_PUBLIC, ACC_ABSTRACT

  public abstract java.lang.String rawSimplifiedFactMessage();
    descriptor: ()Ljava/lang/String;
    flags: (0x0401) ACC_PUBLIC, ACC_ABSTRACT

  public abstract java.lang.String rawMidSentenceFactMessage();
    descriptor: ()Ljava/lang/String;
    flags: (0x0401) ACC_PUBLIC, ACC_ABSTRACT

  public abstract java.lang.String rawMidSentenceSimplifiedFactMessage();
    descriptor: ()Ljava/lang/String;
    flags: (0x0401) ACC_PUBLIC, ACC_ABSTRACT

  public abstract scala.collection.immutable.IndexedSeq<java.lang.Object> factMessageArgs();
    descriptor: ()Lscala/collection/immutable/IndexedSeq;
    flags: (0x0401) ACC_PUBLIC, ACC_ABSTRACT
    Signature: #118                         // ()Lscala/collection/immutable/IndexedSeq<Ljava/lang/Object;>;

  public abstract scala.collection.immutable.IndexedSeq<java.lang.Object> simplifiedFactMessageArgs();
    descriptor: ()Lscala/collection/immutable/IndexedSeq;
    flags: (0x0401) ACC_PUBLIC, ACC_ABSTRACT
    Signature: #118                         // ()Lscala/collection/immutable/IndexedSeq<Ljava/lang/Object;>;

  public abstract scala.collection.immutable.IndexedSeq<java.lang.Object> midSentenceFactMessageArgs();
    descriptor: ()Lscala/collection/immutable/IndexedSeq;
    flags: (0x0401) ACC_PUBLIC, ACC_ABSTRACT
    Signature: #118                         // ()Lscala/collection/immutable/IndexedSeq<Ljava/lang/Object;>;

  public abstract scala.collection.immutable.IndexedSeq<java.lang.Object> midSentenceSimplifiedFactMessageArgs();
    descriptor: ()Lscala/collection/immutable/IndexedSeq;
    flags: (0x0401) ACC_PUBLIC, ACC_ABSTRACT
    Signature: #118                         // ()Lscala/collection/immutable/IndexedSeq<Ljava/lang/Object;>;

  public abstract boolean isLeaf();
    descriptor: ()Z
    flags: (0x0401) ACC_PUBLIC, ACC_ABSTRACT

  public abstract boolean isVacuousYes();
    descriptor: ()Z
    flags: (0x0401) ACC_PUBLIC, ACC_ABSTRACT

  public abstract org.scalactic.Prettifier prettifier();
    descriptor: ()Lorg/scalactic/Prettifier;
    flags: (0x0401) ACC_PUBLIC, ACC_ABSTRACT

  public scala.Option<java.lang.Throwable> cause();
    descriptor: ()Lscala/Option;
    flags: (0x0001) ACC_PUBLIC
    Code:
      stack=1, locals=1, args_size=1
         0: aload_0
         1: getfield      #130                // Field cause:Lscala/Option;
         4: areturn
      LineNumberTable:
        line 39: 0
      LocalVariableTable:
        Start  Length  Slot  Name   Signature
            0       5     0  this   Lorg/scalatest/Fact;
    Signature: #128                         // ()Lscala/Option<Ljava/lang/Throwable;>;

  public abstract boolean isYes();
    descriptor: ()Z
    flags: (0x0401) ACC_PUBLIC, ACC_ABSTRACT

  public final boolean isNo();
    descriptor: ()Z
    flags: (0x0011) ACC_PUBLIC, ACC_FINAL
    Code:
      stack=1, locals=1, args_size=1
         0: aload_0
         1: invokevirtual #136                // Method isYes:()Z
         4: ifne          11
         7: iconst_1
         8: goto          12
        11: iconst_0
        12: ireturn
      StackMapTable: number_of_entries = 2
        frame_type = 11 /* same */
        frame_type = 64 /* same_locals_1_stack_item */
          stack = [ int ]
      LineNumberTable:
        line 43: 0
      LocalVariableTable:
        Start  Length  Slot  Name   Signature
            0      13     0  this   Lorg/scalatest/Fact;

  public final boolean toBoolean();
    descriptor: ()Z
    flags: (0x0011) ACC_PUBLIC, ACC_FINAL
    Code:
      stack=1, locals=1, args_size=1
         0: aload_0
         1: invokevirtual #136                // Method isYes:()Z
         4: ireturn
      LineNumberTable:
        line 45: 0
      LocalVariableTable:
        Start  Length  Slot  Name   Signature
            0       5     0  this   Lorg/scalatest/Fact;

  public final org.scalatest.compatible.Assertion toAssertion(org.scalactic.source.Position);
    descriptor: (Lorg/scalactic/source/Position;)Lorg/scalatest/compatible/Assertion;
    flags: (0x0011) ACC_PUBLIC, ACC_FINAL
    Code:
      stack=6, locals=2, args_size=2
         0: aload_0
         1: invokevirtual #136                // Method isYes:()Z
         4: ifeq          44
         7: aload_0
         8: invokevirtual #142                // Method isVacuousYes:()Z
        11: ifne          20
        14: getstatic     #148                // Field org/scalatest/Succeeded$.MODULE$:Lorg/scalatest/Succeeded$;
        17: goto          41
        20: new           #150                // class org/scalatest/exceptions/TestCanceledException
        23: dup
        24: aload_0
        25: invokedynamic #172,  0            // InvokeDynamic #0:apply:(Lorg/scalatest/Fact;)Lscala/Function1;
        30: getstatic     #177                // Field scala/None$.MODULE$:Lscala/None$;
        33: aload_1
        34: getstatic     #177                // Field scala/None$.MODULE$:Lscala/None$;
        37: invokespecial #181                // Method org/scalatest/exceptions/TestCanceledException."<init>":(Lscala/Function1;Lscala/Option;Lorg/scalactic/source/Position;Lscala/Option;)V
        40: athrow
        41: goto          62
        44: new           #183                // class org/scalatest/exceptions/TestFailedException
        47: dup
        48: aload_0
        49: invokedynamic #188,  0            // InvokeDynamic #1:apply:(Lorg/scalatest/Fact;)Lscala/Function1;
        54: getstatic     #177                // Field scala/None$.MODULE$:Lscala/None$;
        57: aload_1
        58: invokespecial #191                // Method org/scalatest/exceptions/TestFailedException."<init>":(Lscala/Function1;Lscala/Option;Lorg/scalactic/source/Position;)V
        61: athrow
        62: areturn
      StackMapTable: number_of_entries = 4
        frame_type = 20 /* same */
        frame_type = 84 /* same_locals_1_stack_item */
          stack = [ class org/scalatest/Succeeded$ ]
        frame_type = 2 /* same */
        frame_type = 81 /* same_locals_1_stack_item */
          stack = [ class org/scalatest/Succeeded$ ]
      LineNumberTable:
        line 48: 0
        line 49: 7
        line 50: 20
        line 52: 44
      LocalVariableTable:
        Start  Length  Slot  Name   Signature
            0      63     0  this   Lorg/scalatest/Fact;
            0      63     1   pos   Lorg/scalactic/source/Position;
    MethodParameters:
      Name                           Flags
      pos                            final

  public final org.scalatest.compatible.Assertion internalToAssertion(org.scalactic.source.Position);
    descriptor: (Lorg/scalactic/source/Position;)Lorg/scalatest/compatible/Assertion;
    flags: (0x0011) ACC_PUBLIC, ACC_FINAL
    Code:
      stack=6, locals=2, args_size=2
         0: aload_0
         1: invokevirtual #136                // Method isYes:()Z
         4: ifeq          44
         7: aload_0
         8: invokevirtual #142                // Method isVacuousYes:()Z
        11: ifne          20
        14: getstatic     #148                // Field org/scalatest/Succeeded$.MODULE$:Lorg/scalatest/Succeeded$;
        17: goto          41
        20: new           #150                // class org/scalatest/exceptions/TestCanceledException
        23: dup
        24: aload_0
        25: invokedynamic #198,  0            // InvokeDynamic #2:apply:(Lorg/scalatest/Fact;)Lscala/Function1;
        30: getstatic     #177                // Field scala/None$.MODULE$:Lscala/None$;
        33: aload_1
        34: getstatic     #177                // Field scala/None$.MODULE$:Lscala/None$;
        37: invokespecial #181                // Method org/scalatest/exceptions/TestCanceledException."<init>":(Lscala/Function1;Lscala/Option;Lorg/scalactic/source/Position;Lscala/Option;)V
        40: athrow
        41: goto          62
        44: new           #183                // class org/scalatest/exceptions/TestFailedException
        47: dup
        48: aload_0
        49: invokedynamic #203,  0            // InvokeDynamic #3:apply:(Lorg/scalatest/Fact;)Lscala/Function1;
        54: getstatic     #177                // Field scala/None$.MODULE$:Lscala/None$;
        57: aload_1
        58: invokespecial #191                // Method org/scalatest/exceptions/TestFailedException."<init>":(Lscala/Function1;Lscala/Option;Lorg/scalactic/source/Position;)V
        61: athrow
        62: areturn
      StackMapTable: number_of_entries = 4
        frame_type = 20 /* same */
        frame_type = 84 /* same_locals_1_stack_item */
          stack = [ class org/scalatest/Succeeded$ ]
        frame_type = 2 /* same */
        frame_type = 81 /* same_locals_1_stack_item */
          stack = [ class org/scalatest/Succeeded$ ]
      LineNumberTable:
        line 57: 0
        line 58: 7
        line 59: 20
        line 61: 44
      LocalVariableTable:
        Start  Length  Slot  Name   Signature
            0      63     0  this   Lorg/scalatest/Fact;
            0      63     1   pos   Lorg/scalactic/source/Position;
    MethodParameters:
      Name                           Flags
      pos                            final

  public org.scalatest.Fact unary_$bang();
    descriptor: ()Lorg/scalatest/Fact;
    flags: (0x0001) ACC_PUBLIC
    Code:
      stack=3, locals=1, args_size=1
         0: new           #87                 // class org/scalatest/Fact$Unary_$bang
         3: dup
         4: aload_0
         5: invokespecial #208                // Method org/scalatest/Fact$Unary_$bang."<init>":(Lorg/scalatest/Fact;)V
         8: areturn
      LineNumberTable:
        line 69: 0
      LocalVariableTable:
        Start  Length  Slot  Name   Signature
            0       9     0  this   Lorg/scalatest/Fact;

  public final org.scalatest.Fact $bar$bar(scala.Function0<org.scalatest.Fact>);
    descriptor: (Lscala/Function0;)Lorg/scalatest/Fact;
    flags: (0x0011) ACC_PUBLIC, ACC_FINAL
    Code:
      stack=3, locals=2, args_size=2
         0: aload_0
         1: invokevirtual #136                // Method isYes:()Z
         4: ifeq          11
         7: aload_0
         8: goto          27
        11: getstatic     #215                // Field org/scalatest/Fact$Binary_$bar$bar$.MODULE$:Lorg/scalatest/Fact$Binary_$bar$bar$;
        14: aload_0
        15: aload_1
        16: invokeinterface #220,  1          // InterfaceMethod scala/Function0.apply:()Ljava/lang/Object;
        21: checkcast     #2                  // class org/scalatest/Fact
        24: invokevirtual #223                // Method org/scalatest/Fact$Binary_$bar$bar$.apply:(Lorg/scalatest/Fact;Lorg/scalatest/Fact;)Lorg/scalatest/Fact;
        27: areturn
      StackMapTable: number_of_entries = 2
        frame_type = 11 /* same */
        frame_type = 79 /* same_locals_1_stack_item */
          stack = [ class org/scalatest/Fact ]
      LineNumberTable:
        line 71: 0
      LocalVariableTable:
        Start  Length  Slot  Name   Signature
            0      28     0  this   Lorg/scalatest/Fact;
            0      28     1   rhs   Lscala/Function0;
    Signature: #211                         // (Lscala/Function0<Lorg/scalatest/Fact;>;)Lorg/scalatest/Fact;
    MethodParameters:
      Name                           Flags
      rhs                            final

  public final org.scalatest.Fact $amp$amp(scala.Function0<org.scalatest.Fact>);
    descriptor: (Lscala/Function0;)Lorg/scalatest/Fact;
    flags: (0x0011) ACC_PUBLIC, ACC_FINAL
    Code:
      stack=3, locals=2, args_size=2
         0: aload_0
         1: invokevirtual #227                // Method isNo:()Z
         4: ifeq          11
         7: aload_0
         8: goto          27
        11: getstatic     #230                // Field org/scalatest/Fact$Binary_$amp$amp$.MODULE$:Lorg/scalatest/Fact$Binary_$amp$amp$;
        14: aload_0
        15: aload_1
        16: invokeinterface #220,  1          // InterfaceMethod scala/Function0.apply:()Ljava/lang/Object;
        21: checkcast     #2                  // class org/scalatest/Fact
        24: invokevirtual #231                // Method org/scalatest/Fact$Binary_$amp$amp$.apply:(Lorg/scalatest/Fact;Lorg/scalatest/Fact;)Lorg/scalatest/Fact;
        27: areturn
      StackMapTable: number_of_entries = 2
        frame_type = 11 /* same */
        frame_type = 79 /* same_locals_1_stack_item */
          stack = [ class org/scalatest/Fact ]
      LineNumberTable:
        line 73: 0
      LocalVariableTable:
        Start  Length  Slot  Name   Signature
            0      28     0  this   Lorg/scalatest/Fact;
            0      28     1   rhs   Lscala/Function0;
    Signature: #211                         // (Lscala/Function0<Lorg/scalatest/Fact;>;)Lorg/scalatest/Fact;
    MethodParameters:
      Name                           Flags
      rhs                            final

  public final org.scalatest.Fact $bar(org.scalatest.Fact);
    descriptor: (Lorg/scalatest/Fact;)Lorg/scalatest/Fact;
    flags: (0x0011) ACC_PUBLIC, ACC_FINAL
    Code:
      stack=3, locals=2, args_size=2
         0: getstatic     #236                // Field org/scalatest/Fact$Binary_$bar$.MODULE$:Lorg/scalatest/Fact$Binary_$bar$;
         3: aload_0
         4: aload_1
         5: invokevirtual #237                // Method org/scalatest/Fact$Binary_$bar$.apply:(Lorg/scalatest/Fact;Lorg/scalatest/Fact;)Lorg/scalatest/Fact;
         8: areturn
      LineNumberTable:
        line 75: 0
      LocalVariableTable:
        Start  Length  Slot  Name   Signature
            0       9     0  this   Lorg/scalatest/Fact;
            0       9     1   rhs   Lorg/scalatest/Fact;
    MethodParameters:
      Name                           Flags
      rhs                            final

  public final org.scalatest.Fact $amp(org.scalatest.Fact);
    descriptor: (Lorg/scalatest/Fact;)Lorg/scalatest/Fact;
    flags: (0x0011) ACC_PUBLIC, ACC_FINAL
    Code:
      stack=3, locals=2, args_size=2
         0: getstatic     #241                // Field org/scalatest/Fact$Binary_$amp$.MODULE$:Lorg/scalatest/Fact$Binary_$amp$;
         3: aload_0
         4: aload_1
         5: invokevirtual #242                // Method org/scalatest/Fact$Binary_$amp$.apply:(Lorg/scalatest/Fact;Lorg/scalatest/Fact;)Lorg/scalatest/Fact;
         8: areturn
      LineNumberTable:
        line 77: 0
      LocalVariableTable:
        Start  Length  Slot  Name   Signature
            0       9     0  this   Lorg/scalatest/Fact;
            0       9     1   rhs   Lorg/scalatest/Fact;
    MethodParameters:
      Name                           Flags
      rhs                            final

  public final java.lang.String stringPrefix();
    descriptor: ()Ljava/lang/String;
    flags: (0x0011) ACC_PUBLIC, ACC_FINAL
    Code:
      stack=1, locals=1, args_size=1
         0: aload_0
         1: invokevirtual #136                // Method isYes:()Z
         4: ifeq          24
         7: aload_0
         8: invokevirtual #142                // Method isVacuousYes:()Z
        11: ifeq          19
        14: ldc           #244                // String VacuousYes
        16: goto          21
        19: ldc           #246                // String Yes
        21: goto          26
        24: ldc           #248                // String No
        26: areturn
      StackMapTable: number_of_entries = 4
        frame_type = 19 /* same */
        frame_type = 65 /* same_locals_1_stack_item */
          stack = [ class java/lang/String ]
        frame_type = 2 /* same */
        frame_type = 65 /* same_locals_1_stack_item */
          stack = [ class java/lang/String ]
      LineNumberTable:
        line 80: 0
        line 81: 7
        line 83: 24
      LocalVariableTable:
        Start  Length  Slot  Name   Signature
            0      27     0  this   Lorg/scalatest/Fact;

  public final org.scalatest.Fact implies(scala.Function0<org.scalatest.Fact>);
    descriptor: (Lscala/Function0;)Lorg/scalatest/Fact;
    flags: (0x0011) ACC_PUBLIC, ACC_FINAL
    Code:
      stack=3, locals=2, args_size=2
         0: aload_0
         1: invokevirtual #227                // Method isNo:()Z
         4: ifeq          17
         7: getstatic     #254                // Field org/scalatest/Fact$VacuousYes$.MODULE$:Lorg/scalatest/Fact$VacuousYes$;
        10: aload_0
        11: invokevirtual #257                // Method org/scalatest/Fact$VacuousYes$.apply:(Lorg/scalatest/Fact;)Lorg/scalatest/Fact$VacuousYes;
        14: goto          33
        17: getstatic     #260                // Field org/scalatest/Fact$Implies$.MODULE$:Lorg/scalatest/Fact$Implies$;
        20: aload_0
        21: aload_1
        22: invokeinterface #220,  1          // InterfaceMethod scala/Function0.apply:()Ljava/lang/Object;
        27: checkcast     #2                  // class org/scalatest/Fact
        30: invokevirtual #261                // Method org/scalatest/Fact$Implies$.apply:(Lorg/scalatest/Fact;Lorg/scalatest/Fact;)Lorg/scalatest/Fact;
        33: areturn
      StackMapTable: number_of_entries = 2
        frame_type = 17 /* same */
        frame_type = 79 /* same_locals_1_stack_item */
          stack = [ class org/scalatest/Fact ]
      LineNumberTable:
        line 85: 0
      LocalVariableTable:
        Start  Length  Slot  Name   Signature
            0      34     0  this   Lorg/scalatest/Fact;
            0      34     1   rhs   Lscala/Function0;
    Signature: #211                         // (Lscala/Function0<Lorg/scalatest/Fact;>;)Lorg/scalatest/Fact;
    MethodParameters:
      Name                           Flags
      rhs                            final

  public final org.scalatest.Fact isEqvTo(org.scalatest.Fact);
    descriptor: (Lorg/scalatest/Fact;)Lorg/scalatest/Fact;
    flags: (0x0011) ACC_PUBLIC, ACC_FINAL
    Code:
      stack=3, locals=2, args_size=2
         0: getstatic     #265                // Field org/scalatest/Fact$IsEqvTo$.MODULE$:Lorg/scalatest/Fact$IsEqvTo$;
         3: aload_0
         4: aload_1
         5: invokevirtual #266                // Method org/scalatest/Fact$IsEqvTo$.apply:(Lorg/scalatest/Fact;Lorg/scalatest/Fact;)Lorg/scalatest/Fact;
         8: areturn
      LineNumberTable:
        line 87: 0
      LocalVariableTable:
        Start  Length  Slot  Name   Signature
            0       9     0  this   Lorg/scalatest/Fact;
            0       9     1   rhs   Lorg/scalatest/Fact;
    MethodParameters:
      Name                           Flags
      rhs                            final

  public java.lang.String factMessage();
    descriptor: ()Ljava/lang/String;
    flags: (0x0001) ACC_PUBLIC
    Code:
      stack=3, locals=1, args_size=1
         0: aload_0
         1: invokevirtual #269                // Method factMessageArgs:()Lscala/collection/immutable/IndexedSeq;
         4: invokeinterface #274,  1          // InterfaceMethod scala/collection/immutable/IndexedSeq.isEmpty:()Z
         9: ifeq          19
        12: aload_0
        13: invokevirtual #276                // Method rawFactMessage:()Ljava/lang/String;
        16: goto          31
        19: aload_0
        20: aload_0
        21: invokevirtual #276                // Method rawFactMessage:()Ljava/lang/String;
        24: aload_0
        25: invokevirtual #269                // Method factMessageArgs:()Lscala/collection/immutable/IndexedSeq;
        28: invokespecial #280                // Method makeString:(Ljava/lang/String;Lscala/collection/immutable/IndexedSeq;)Ljava/lang/String;
        31: areturn
      StackMapTable: number_of_entries = 2
        frame_type = 19 /* same */
        frame_type = 75 /* same_locals_1_stack_item */
          stack = [ class java/lang/String ]
      LineNumberTable:
        line 95: 0
        line 96: 19
      LocalVariableTable:
        Start  Length  Slot  Name   Signature
            0      32     0  this   Lorg/scalatest/Fact;

  public java.lang.String simplifiedFactMessage();
    descriptor: ()Ljava/lang/String;
    flags: (0x0001) ACC_PUBLIC
    Code:
      stack=3, locals=1, args_size=1
         0: aload_0
         1: invokevirtual #283                // Method simplifiedFactMessageArgs:()Lscala/collection/immutable/IndexedSeq;
         4: invokeinterface #274,  1          // InterfaceMethod scala/collection/immutable/IndexedSeq.isEmpty:()Z
         9: ifeq          19
        12: aload_0
        13: invokevirtual #285                // Method rawSimplifiedFactMessage:()Ljava/lang/String;
        16: goto          31
        19: aload_0
        20: aload_0
        21: invokevirtual #285                // Method rawSimplifiedFactMessage:()Ljava/lang/String;
        24: aload_0
        25: invokevirtual #283                // Method simplifiedFactMessageArgs:()Lscala/collection/immutable/IndexedSeq;
        28: invokespecial #280                // Method makeString:(Ljava/lang/String;Lscala/collection/immutable/IndexedSeq;)Ljava/lang/String;
        31: areturn
      StackMapTable: number_of_entries = 2
        frame_type = 19 /* same */
        frame_type = 75 /* same_locals_1_stack_item */
          stack = [ class java/lang/String ]
      LineNumberTable:
        line 99: 0
        line 100: 19
      LocalVariableTable:
        Start  Length  Slot  Name   Signature
            0      32     0  this   Lorg/scalatest/Fact;

  public java.lang.String midSentenceFactMessage();
    descriptor: ()Ljava/lang/String;
    flags: (0x0001) ACC_PUBLIC
    Code:
      stack=3, locals=1, args_size=1
         0: aload_0
         1: invokevirtual #288                // Method midSentenceFactMessageArgs:()Lscala/collection/immutable/IndexedSeq;
         4: invokeinterface #274,  1          // InterfaceMethod scala/collection/immutable/IndexedSeq.isEmpty:()Z
         9: ifeq          19
        12: aload_0
        13: invokevirtual #290                // Method rawMidSentenceFactMessage:()Ljava/lang/String;
        16: goto          31
        19: aload_0
        20: aload_0
        21: invokevirtual #290                // Method rawMidSentenceFactMessage:()Ljava/lang/String;
        24: aload_0
        25: invokevirtual #288                // Method midSentenceFactMessageArgs:()Lscala/collection/immutable/IndexedSeq;
        28: invokespecial #280                // Method makeString:(Ljava/lang/String;Lscala/collection/immutable/IndexedSeq;)Ljava/lang/String;
        31: areturn
      StackMapTable: number_of_entries = 2
        frame_type = 19 /* same */
        frame_type = 75 /* same_locals_1_stack_item */
          stack = [ class java/lang/String ]
      LineNumberTable:
        line 108: 0
        line 109: 19
      LocalVariableTable:
        Start  Length  Slot  Name   Signature
            0      32     0  this   Lorg/scalatest/Fact;

  public java.lang.String midSentenceSimplifiedFactMessage();
    descriptor: ()Ljava/lang/String;
    flags: (0x0001) ACC_PUBLIC
    Code:
      stack=3, locals=1, args_size=1
         0: aload_0
         1: invokevirtual #293                // Method midSentenceSimplifiedFactMessageArgs:()Lscala/collection/immutable/IndexedSeq;
         4: invokeinterface #274,  1          // InterfaceMethod scala/collection/immutable/IndexedSeq.isEmpty:()Z
         9: ifeq          19
        12: aload_0
        13: invokevirtual #295                // Method rawMidSentenceSimplifiedFactMessage:()Ljava/lang/String;
        16: goto          31
        19: aload_0
        20: aload_0
        21: invokevirtual #295                // Method rawMidSentenceSimplifiedFactMessage:()Ljava/lang/String;
        24: aload_0
        25: invokevirtual #293                // Method midSentenceSimplifiedFactMessageArgs:()Lscala/collection/immutable/IndexedSeq;
        28: invokespecial #280                // Method makeString:(Ljava/lang/String;Lscala/collection/immutable/IndexedSeq;)Ljava/lang/String;
        31: areturn
      StackMapTable: number_of_entries = 2
        frame_type = 19 /* same */
        frame_type = 75 /* same_locals_1_stack_item */
          stack = [ class java/lang/String ]
      LineNumberTable:
        line 112: 0
        line 113: 19
      LocalVariableTable:
        Start  Length  Slot  Name   Signature
            0      32     0  this   Lorg/scalatest/Fact;

  private java.lang.String makeString(java.lang.String, scala.collection.immutable.IndexedSeq<java.lang.Object>);
    descriptor: (Ljava/lang/String;Lscala/collection/immutable/IndexedSeq;)Ljava/lang/String;
    flags: (0x0002) ACC_PRIVATE
    Code:
      stack=4, locals=3, args_size=3
         0: getstatic     #303                // Field org/scalatest/Resources$.MODULE$:Lorg/scalatest/Resources$;
         3: aload_1
         4: aload_2
         5: aload_0
         6: invokedynamic #311,  0            // InvokeDynamic #4:apply:(Lorg/scalatest/Fact;)Lscala/Function1;
        11: invokeinterface #315,  2          // InterfaceMethod scala/collection/immutable/IndexedSeq.map:(Lscala/Function1;)Ljava/lang/Object;
        16: checkcast     #317                // class scala/collection/IterableOnceOps
        19: getstatic     #322                // Field scala/reflect/ClassTag$.MODULE$:Lscala/reflect/ClassTag$;
        22: invokevirtual #326                // Method scala/reflect/ClassTag$.Any:()Lscala/reflect/ClassTag;
        25: invokeinterface #330,  2          // InterfaceMethod scala/collection/IterableOnceOps.toArray:(Lscala/reflect/ClassTag;)Ljava/lang/Object;
        30: checkcast     #332                // class "[Ljava/lang/Object;"
        33: invokevirtual #336                // Method org/scalatest/Resources$.formatString:(Ljava/lang/String;[Ljava/lang/Object;)Ljava/lang/String;
        36: areturn
      LineNumberTable:
        line 116: 0
      LocalVariableTable:
        Start  Length  Slot  Name   Signature
            0      37     0  this   Lorg/scalatest/Fact;
            0      37     1   raw   Ljava/lang/String;
            0      37     2  args   Lscala/collection/immutable/IndexedSeq;
    Signature: #296                         // (Ljava/lang/String;Lscala/collection/immutable/IndexedSeq<Ljava/lang/Object;>;)Ljava/lang/String;
    MethodParameters:
      Name                           Flags
      raw                            final
      args                           final

  public java.lang.String NEWLINE();
    descriptor: ()Ljava/lang/String;
    flags: (0x0001) ACC_PUBLIC
    Code:
      stack=1, locals=1, args_size=1
         0: aload_0
         1: getfield      #339                // Field NEWLINE:Ljava/lang/String;
         4: areturn
      LineNumberTable:
        line 118: 0
      LocalVariableTable:
        Start  Length  Slot  Name   Signature
            0       5     0  this   Lorg/scalatest/Fact;

  public java.lang.String factDiagram(int);
    descriptor: (I)Ljava/lang/String;
    flags: (0x0001) ACC_PUBLIC
    Code:
      stack=7, locals=5, args_size=2
         0: aload_0
         1: invokevirtual #344                // Method midSentenceFactMessage:()Ljava/lang/String;
         4: astore_2
         5: getstatic     #349                // Field scala/collection/StringOps$.MODULE$:Lscala/collection/StringOps$;
         8: getstatic     #354                // Field scala/Predef$.MODULE$:Lscala/Predef$;
        11: ldc_w         #356                // String
        14: invokevirtual #360                // Method scala/Predef$.augmentString:(Ljava/lang/String;)Ljava/lang/String;
        17: iload_1
        18: invokevirtual #364                // Method scala/collection/StringOps$.$times$extension:(Ljava/lang/String;I)Ljava/lang/String;
        21: astore_3
        22: aload_2
        23: ldc_w         #366                // String \n
        26: invokevirtual #370                // Method java/lang/String.contains:(Ljava/lang/CharSequence;)Z
        29: ifeq          159
        32: getstatic     #349                // Field scala/collection/StringOps$.MODULE$:Lscala/collection/StringOps$;
        35: getstatic     #354                // Field scala/Predef$.MODULE$:Lscala/Predef$;
        38: ldc_w         #356                // String
        41: invokevirtual #360                // Method scala/Predef$.augmentString:(Ljava/lang/String;)Ljava/lang/String;
        44: iload_1
        45: invokevirtual #364                // Method scala/collection/StringOps$.$times$extension:(Ljava/lang/String;I)Ljava/lang/String;
        48: astore        4
        50: new           #372                // class java/lang/StringBuilder
        53: dup
        54: ldc_w         #373                // int 2
        57: invokespecial #376                // Method java/lang/StringBuilder."<init>":(I)V
        60: aload         4
        62: invokevirtual #380                // Method java/lang/StringBuilder.append:(Ljava/lang/String;)Ljava/lang/StringBuilder;
        65: aload_0
        66: invokevirtual #382                // Method stringPrefix:()Ljava/lang/String;
        69: invokevirtual #380                // Method java/lang/StringBuilder.append:(Ljava/lang/String;)Ljava/lang/StringBuilder;
        72: ldc_w         #384                // String (
        75: invokevirtual #380                // Method java/lang/StringBuilder.append:(Ljava/lang/String;)Ljava/lang/StringBuilder;
        78: aload_0
        79: invokevirtual #386                // Method NEWLINE:()Ljava/lang/String;
        82: invokevirtual #380                // Method java/lang/StringBuilder.append:(Ljava/lang/String;)Ljava/lang/StringBuilder;
        85: getstatic     #354                // Field scala/Predef$.MODULE$:Lscala/Predef$;
        88: getstatic     #391                // Field scala/collection/ArrayOps$.MODULE$:Lscala/collection/ArrayOps$;
        91: getstatic     #354                // Field scala/Predef$.MODULE$:Lscala/Predef$;
        94: aload_2
        95: ldc_w         #366                // String \n
        98: invokevirtual #395                // Method java/lang/String.split:(Ljava/lang/String;)[Ljava/lang/String;
       101: checkcast     #332                // class "[Ljava/lang/Object;"
       104: invokevirtual #399                // Method scala/Predef$.refArrayOps:([Ljava/lang/Object;)Ljava/lang/Object;
       107: aload         4
       109: invokedynamic #408,  0            // InvokeDynamic #5:apply:(Ljava/lang/String;)Lscala/Function1;
       114: getstatic     #322                // Field scala/reflect/ClassTag$.MODULE$:Lscala/reflect/ClassTag$;
       117: ldc           #250                // class java/lang/String
       119: invokevirtual #411                // Method scala/reflect/ClassTag$.apply:(Ljava/lang/Class;)Lscala/reflect/ClassTag;
       122: invokevirtual #415                // Method scala/collection/ArrayOps$.map$extension:(Ljava/lang/Object;Lscala/Function1;Lscala/reflect/ClassTag;)Ljava/lang/Object;
       125: checkcast     #332                // class "[Ljava/lang/Object;"
       128: invokevirtual #419                // Method scala/Predef$.wrapRefArray:([Ljava/lang/Object;)Lscala/collection/mutable/ArraySeq$ofRef;
       131: ldc_w         #366                // String \n
       134: invokevirtual #422                // Method scala/collection/mutable/ArraySeq$ofRef.mkString:(Ljava/lang/String;)Ljava/lang/String;
       137: invokevirtual #380                // Method java/lang/StringBuilder.append:(Ljava/lang/String;)Ljava/lang/StringBuilder;
       140: aload_0
       141: invokevirtual #386                // Method NEWLINE:()Ljava/lang/String;
       144: invokevirtual #380                // Method java/lang/StringBuilder.append:(Ljava/lang/String;)Ljava/lang/StringBuilder;
       147: ldc_w         #424                // String )
       150: invokevirtual #380                // Method java/lang/StringBuilder.append:(Ljava/lang/String;)Ljava/lang/StringBuilder;
       153: invokevirtual #427                // Method java/lang/StringBuilder.toString:()Ljava/lang/String;
       156: goto          199
       159: new           #372                // class java/lang/StringBuilder
       162: dup
       163: ldc_w         #373                // int 2
       166: invokespecial #376                // Method java/lang/StringBuilder."<init>":(I)V
       169: aload_3
       170: invokevirtual #380                // Method java/lang/StringBuilder.append:(Ljava/lang/String;)Ljava/lang/StringBuilder;
       173: aload_0
       174: invokevirtual #382                // Method stringPrefix:()Ljava/lang/String;
       177: invokevirtual #380                // Method java/lang/StringBuilder.append:(Ljava/lang/String;)Ljava/lang/StringBuilder;
       180: ldc_w         #384                // String (
       183: invokevirtual #380                // Method java/lang/StringBuilder.append:(Ljava/lang/String;)Ljava/lang/StringBuilder;
       186: aload_2
       187: invokevirtual #380                // Method java/lang/StringBuilder.append:(Ljava/lang/String;)Ljava/lang/StringBuilder;
       190: ldc_w         #424                // String )
       193: invokevirtual #380                // Method java/lang/StringBuilder.append:(Ljava/lang/String;)Ljava/lang/StringBuilder;
       196: invokevirtual #427                // Method java/lang/StringBuilder.toString:()Ljava/lang/String;
       199: areturn
      StackMapTable: number_of_entries = 2
        frame_type = 253 /* append */
          offset_delta = 159
          locals = [ class java/lang/String, class java/lang/String ]
        frame_type = 103 /* same_locals_1_stack_item */
          stack = [ class java/lang/String ]
      LineNumberTable:
        line 122: 0
        line 123: 5
        line 124: 22
        line 125: 32
        line 126: 50
        line 129: 159
      LocalVariableTable:
        Start  Length  Slot  Name   Signature
           50     106     4 padding   Ljava/lang/String;
            5     194     2   msg   Ljava/lang/String;
           22     177     3 padding   Ljava/lang/String;
            0     200     0  this   Lorg/scalatest/Fact;
            0     200     1 level   I
    MethodParameters:
      Name                           Flags
      level                          final

  public java.lang.String toString();
    descriptor: ()Ljava/lang/String;
    flags: (0x0001) ACC_PUBLIC
    Code:
      stack=2, locals=1, args_size=1
         0: aload_0
         1: iconst_0
         2: invokevirtual #432                // Method factDiagram:(I)Ljava/lang/String;
         5: areturn
      LineNumberTable:
        line 132: 0
      LocalVariableTable:
        Start  Length  Slot  Name   Signature
            0       6     0  this   Lorg/scalatest/Fact;

  public static final scala.Some $anonfun$toAssertion$1(org.scalatest.Fact, org.scalatest.exceptions.StackDepthException);
    descriptor: (Lorg/scalatest/Fact;Lorg/scalatest/exceptions/StackDepthException;)Lscala/Some;
    flags: (0x1019) ACC_PUBLIC, ACC_STATIC, ACC_FINAL, ACC_SYNTHETIC
    Code:
      stack=3, locals=2, args_size=2
         0: new           #436                // class scala/Some
         3: dup
         4: aload_0
         5: invokevirtual #438                // Method factMessage:()Ljava/lang/String;
         8: invokespecial #441                // Method scala/Some."<init>":(Ljava/lang/Object;)V
        11: areturn
      LineNumberTable:
        line 50: 0
      LocalVariableTable:
        Start  Length  Slot  Name   Signature
            0      12     0 $this   Lorg/scalatest/Fact;
            0      12     1     e   Lorg/scalatest/exceptions/StackDepthException;
    MethodParameters:
      Name                           Flags
      $this                          final synthetic
      e                              final

  public static final scala.Some $anonfun$toAssertion$2(org.scalatest.Fact, org.scalatest.exceptions.StackDepthException);
    descriptor: (Lorg/scalatest/Fact;Lorg/scalatest/exceptions/StackDepthException;)Lscala/Some;
    flags: (0x1019) ACC_PUBLIC, ACC_STATIC, ACC_FINAL, ACC_SYNTHETIC
    Code:
      stack=3, locals=2, args_size=2
         0: new           #436                // class scala/Some
         3: dup
         4: aload_0
         5: invokevirtual #438                // Method factMessage:()Ljava/lang/String;
         8: invokespecial #441                // Method scala/Some."<init>":(Ljava/lang/Object;)V
        11: areturn
      LineNumberTable:
        line 52: 0
      LocalVariableTable:
        Start  Length  Slot  Name   Signature
            0      12     0 $this   Lorg/scalatest/Fact;
            0      12     1     e   Lorg/scalatest/exceptions/StackDepthException;
    MethodParameters:
      Name                           Flags
      $this                          final synthetic
      e                              final

  public static final scala.Some $anonfun$internalToAssertion$1(org.scalatest.Fact, org.scalatest.exceptions.StackDepthException);
    descriptor: (Lorg/scalatest/Fact;Lorg/scalatest/exceptions/StackDepthException;)Lscala/Some;
    flags: (0x1019) ACC_PUBLIC, ACC_STATIC, ACC_FINAL, ACC_SYNTHETIC
    Code:
      stack=3, locals=2, args_size=2
         0: new           #436                // class scala/Some
         3: dup
         4: aload_0
         5: invokevirtual #438                // Method factMessage:()Ljava/lang/String;
         8: invokespecial #441                // Method scala/Some."<init>":(Ljava/lang/Object;)V
        11: areturn
      LineNumberTable:
        line 59: 0
      LocalVariableTable:
        Start  Length  Slot  Name   Signature
            0      12     0 $this   Lorg/scalatest/Fact;
            0      12     1     e   Lorg/scalatest/exceptions/StackDepthException;
    MethodParameters:
      Name                           Flags
      $this                          final synthetic
      e                              final

  public static final scala.Some $anonfun$internalToAssertion$2(org.scalatest.Fact, org.scalatest.exceptions.StackDepthException);
    descriptor: (Lorg/scalatest/Fact;Lorg/scalatest/exceptions/StackDepthException;)Lscala/Some;
    flags: (0x1019) ACC_PUBLIC, ACC_STATIC, ACC_FINAL, ACC_SYNTHETIC
    Code:
      stack=3, locals=2, args_size=2
         0: new           #436                // class scala/Some
         3: dup
         4: aload_0
         5: invokevirtual #438                // Method factMessage:()Ljava/lang/String;
         8: invokespecial #441                // Method scala/Some."<init>":(Ljava/lang/Object;)V
        11: areturn
      LineNumberTable:
        line 61: 0
      LocalVariableTable:
        Start  Length  Slot  Name   Signature
            0      12     0 $this   Lorg/scalatest/Fact;
            0      12     1     e   Lorg/scalatest/exceptions/StackDepthException;
    MethodParameters:
      Name                           Flags
      $this                          final synthetic
      e                              final

  public static final java.lang.String $anonfun$makeString$1(org.scalatest.Fact, java.lang.Object);
    descriptor: (Lorg/scalatest/Fact;Ljava/lang/Object;)Ljava/lang/String;
    flags: (0x1019) ACC_PUBLIC, ACC_STATIC, ACC_FINAL, ACC_SYNTHETIC
    Code:
      stack=2, locals=2, args_size=2
         0: aload_0
         1: invokevirtual #445                // Method prettifier:()Lorg/scalactic/Prettifier;
         4: aload_1
         5: invokeinterface #449,  2          // InterfaceMethod org/scalactic/Prettifier.apply:(Ljava/lang/Object;)Ljava/lang/String;
        10: areturn
      LineNumberTable:
        line 116: 0
      LocalVariableTable:
        Start  Length  Slot  Name   Signature
            0      11     0 $this   Lorg/scalatest/Fact;
            0      11     1     o   Ljava/lang/Object;
    MethodParameters:
      Name                           Flags
      $this                          final synthetic
      o                              final

  public static final java.lang.String $anonfun$factDiagram$1(java.lang.String, java.lang.String);
    descriptor: (Ljava/lang/String;Ljava/lang/String;)Ljava/lang/String;
    flags: (0x1019) ACC_PUBLIC, ACC_STATIC, ACC_FINAL, ACC_SYNTHETIC
    Code:
      stack=3, locals=2, args_size=2
         0: new           #372                // class java/lang/StringBuilder
         3: dup
         4: ldc_w         #373                // int 2
         7: invokespecial #376                // Method java/lang/StringBuilder."<init>":(I)V
        10: aload_0
        11: invokevirtual #380                // Method java/lang/StringBuilder.append:(Ljava/lang/String;)Ljava/lang/StringBuilder;
        14: ldc_w         #356                // String
        17: invokevirtual #380                // Method java/lang/StringBuilder.append:(Ljava/lang/String;)Ljava/lang/StringBuilder;
        20: aload_1
        21: invokevirtual #380                // Method java/lang/StringBuilder.append:(Ljava/lang/String;)Ljava/lang/StringBuilder;
        24: invokevirtual #427                // Method java/lang/StringBuilder.toString:()Ljava/lang/String;
        27: areturn
      LineNumberTable:
        line 126: 0
      LocalVariableTable:
        Start  Length  Slot  Name   Signature
            0      28     0 padding$1   Ljava/lang/String;
            0      28     1  line   Ljava/lang/String;
    MethodParameters:
      Name                           Flags
      padding$1                      final
      line                           final

  public org.scalatest.Fact();
    descriptor: ()V
    flags: (0x0001) ACC_PUBLIC
    Code:
      stack=2, locals=1, args_size=1
         0: aload_0
         1: invokespecial #455                // Method java/lang/Object."<init>":()V
         4: aload_0
         5: getstatic     #177                // Field scala/None$.MODULE$:Lscala/None$;
         8: putfield      #130                // Field cause:Lscala/Option;
        11: aload_0
        12: getstatic     #460                // Field scala/compat/Platform$.MODULE$:Lscala/compat/Platform$;
        15: invokevirtual #463                // Method scala/compat/Platform$.EOL:()Ljava/lang/String;
        18: putfield      #339                // Field NEWLINE:Ljava/lang/String;
        21: return
      LineNumberTable:
        line 135: 0
        line 39: 4
        line 118: 11
        line 23: 21
      LocalVariableTable:
        Start  Length  Slot  Name   Signature
            0      22     0  this   Lorg/scalatest/Fact;

  private static java.lang.Object $deserializeLambda$(java.lang.invoke.SerializedLambda);
    descriptor: (Ljava/lang/invoke/SerializedLambda;)Ljava/lang/Object;
    flags: (0x100a) ACC_PRIVATE, ACC_STATIC, ACC_SYNTHETIC
    Code:
      stack=1, locals=1, args_size=1
         0: aload_0
         1: invokedynamic #475,  0            // InvokeDynamic #6:lambdaDeserialize:(Ljava/lang/invoke/SerializedLambda;)Ljava/lang/Object;
         6: areturn
}
InnerClasses:
  public static final #13= #10 of #12;    // Lookup=class java/lang/invoke/MethodHandles$Lookup of class java/lang/invoke/MethodHandles
  public static #16= #15 of #2;           // Binary_$amp=class org/scalatest/Fact$Binary_$amp of class org/scalatest/Fact
  public static #19= #18 of #2;           // Binary_$amp$=class org/scalatest/Fact$Binary_$amp$ of class org/scalatest/Fact
  public static #22= #21 of #2;           // Binary_$amp$amp=class org/scalatest/Fact$Binary_$amp$amp of class org/scalatest/Fact
  public static #25= #24 of #2;           // Binary_$amp$amp$=class org/scalatest/Fact$Binary_$amp$amp$ of class org/scalatest/Fact
  public static #28= #27 of #2;           // Binary_$bar=class org/scalatest/Fact$Binary_$bar of class org/scalatest/Fact
  public static #31= #30 of #2;           // Binary_$bar$=class org/scalatest/Fact$Binary_$bar$ of class org/scalatest/Fact
  public static #34= #33 of #2;           // Binary_$bar$bar=class org/scalatest/Fact$Binary_$bar$bar of class org/scalatest/Fact
  public static #37= #36 of #2;           // Binary_$bar$bar$=class org/scalatest/Fact$Binary_$bar$bar$ of class org/scalatest/Fact
  public static #40= #39 of #2;           // FactMessage=class org/scalatest/Fact$FactMessage of class org/scalatest/Fact
  public static #43= #42 of #2;           // FactMessage$=class org/scalatest/Fact$FactMessage$ of class org/scalatest/Fact
  public static #46= #45 of #2;           // Implies=class org/scalatest/Fact$Implies of class org/scalatest/Fact
  public static #49= #48 of #2;           // Implies$=class org/scalatest/Fact$Implies$ of class org/scalatest/Fact
  public static #52= #51 of #2;           // IsEqvTo=class org/scalatest/Fact$IsEqvTo of class org/scalatest/Fact
  public static #55= #54 of #2;           // IsEqvTo$=class org/scalatest/Fact$IsEqvTo$ of class org/scalatest/Fact
  public static abstract #58= #57 of #2;  // LazyMessage=class org/scalatest/Fact$LazyMessage of class org/scalatest/Fact
  public static #61= #60 of #2;           // Leaf=class org/scalatest/Fact$Leaf of class org/scalatest/Fact
  public static #64= #63 of #2;           // Leaf$=class org/scalatest/Fact$Leaf$ of class org/scalatest/Fact
  public static #67= #66 of #2;           // MidSentenceFactMessage=class org/scalatest/Fact$MidSentenceFactMessage of class org/scalatest/Fact
  public static #70= #69 of #2;           // MidSentenceFactMessage$=class org/scalatest/Fact$MidSentenceFactMessage$ of class org/scalatest/Fact
  public static #73= #72 of #2;           // MidSentenceSimplifiedFactMessage=class org/scalatest/Fact$MidSentenceSimplifiedFactMessage of class org/scalatest/Fact
  public static #76= #75 of #2;           // MidSentenceSimplifiedFactMessage$=class org/scalatest/Fact$MidSentenceSimplifiedFactMessage$ of class org/scalatest/Fact
  public static #79= #78 of #2;           // No$=class org/scalatest/Fact$No$ of class org/scalatest/Fact
  public static #82= #81 of #2;           // SimplifiedFactMessage=class org/scalatest/Fact$SimplifiedFactMessage of class org/scalatest/Fact
  public static #85= #84 of #2;           // SimplifiedFactMessage$=class org/scalatest/Fact$SimplifiedFactMessage$ of class org/scalatest/Fact
  public static #88= #87 of #2;           // Unary_$bang=class org/scalatest/Fact$Unary_$bang of class org/scalatest/Fact
  public static #91= #90 of #2;           // Unary_$bang$=class org/scalatest/Fact$Unary_$bang$ of class org/scalatest/Fact
  public static #94= #93 of #2;           // VacuousYes=class org/scalatest/Fact$VacuousYes of class org/scalatest/Fact
  public static #97= #96 of #2;           // VacuousYes$=class org/scalatest/Fact$VacuousYes$ of class org/scalatest/Fact
  public static #100= #99 of #2;          // Yes$=class org/scalatest/Fact$Yes$ of class org/scalatest/Fact
  public static final #105= #102 of #104; // ofRef=class scala/collection/mutable/ArraySeq$ofRef of class scala/collection/mutable/ArraySeq
SourceFile: "Fact.scala"
RuntimeVisibleAnnotations:
  0: #6(#7=s#8)
    scala.reflect.ScalaSignature(
      bytes="\u0006\u0005!uhACBJ\u0007+\u000b\tc!&\u0004\u001e\"911\u0016\u0001\u0005\u0002\r=\u0006\"CB[\u0001\t\u0007i\u0011AB\\\u0011%\u0019y\r\u0001b\u0001\u000e\u0003\u00199\fC\u0005\u0004R\u0002\u0011\rQ\"\u0001\u00048\"I11\u001b\u0001C\u0002\u001b\u00051q\u0017\u0005\n\u0007+\u0004!\u0019!D\u0001\u0007/D\u0011b!=\u0001\u0005\u00045\taa6\t\u0013\rM\bA1A\u0007\u0002\r]\u0007\"CB{\u0001\t\u0007i\u0011ABl\u0011%\u00199\u0010\u0001b\u0001\u000e\u0003\u0019I\u0010C\u0005\u0005\u0002\u0001\u0011\rQ\"\u0001\u0004z\"IA1\u0001\u0001C\u0002\u001b\u0005AQ\u0001\u0005\n\t\'\u0001!\u0019!C\u0001\t+A\u0001\u0002b\t\u0001A\u0003%Aq\u0003\u0005\n\tK\u0001!\u0019!D\u0001\u0007sDq\u0001b\n\u0001\t\u000b\u0019I\u0010C\u0004\u0005*\u0001!)a!?\t\u000f\u0011-\u0002\u0001\"\u0002\u0005.!IA1\n\u0001\u0005\u0006\rUEQ\n\u0005\b\t#\u0002A\u0011\u0001C*\u0011\u001d!)\u0006\u0001C\u0003\t/Bq\u0001b\u0019\u0001\t\u000b!)\u0007C\u0004\u0005j\u0001!)\u0001b\u001b\t\u000f\u0011=\u0004\u0001\"\u0002\u0005r!9AQ\u000f\u0001\u0005\u0006\r]\u0006b\u0002C<\u0001\u0011\u0015A\u0011\u0010\u0005\b\t{\u0002AQ\u0001C@\u0011\u001d!\u0019\t\u0001C\u0001\u0007oCq\u0001\"\"\u0001\t\u0003\u00199\fC\u0004\u0005\b\u0002!\taa.\t\u000f\u0011%\u0005\u0001\"\u0001\u00048\"9A1\u0012\u0001\u0005\n\u00115\u0005b\u0003CL\u0001\t\u0007I\u0011ABK\u0007oC\u0001\u0002\"\'\u0001A\u0003%1\u0011\u0018\u0005\b\t7\u0003A\u0011\u0001CO\u0011\u001d!I\u000b\u0001C!\tW;!\u0002c?\u0004\u0016\"\u00051Q\u0013C[\r)\u0019\u0019j!&\t\u0002\rUE\u0011\u0017\u0005\b\u0007W3C\u0011\u0001CZ\r\u0019!9L\n!\u0005:\"Q1Q\u0017\u0015\u0003\u0016\u0004%\taa.\t\u0015\u0011\u001d\u0007F!E!\u0002\u0013\u0019I\f\u0003\u0006\u0004P\"\u0012)\u001a!C\u0001\u0007oC!\u0002\"3)\u0005#\u0005\u000b\u0011BB]\u0011)\u0019\t\u000e\u000bBK\u0002\u0013\u00051q\u0017\u0005\u000b\t\u0017D#\u0011#Q\u0001\n\re\u0006BCBjQ\tU\r\u0011\"\u0001\u00048\"QAQ\u001a\u0015\u0003\u0012\u0003\u0006Ia!/\t\u0015\rU\u0007F!f\u0001\n\u0003\u00199\u000e\u0003\u0006\u0005P\"\u0012\t\u0012)A\u0005\u00073D!b!=)\u0005+\u0007I\u0011ABl\u0011)!\t\u000e\u000bB\tB\u0003%1\u0011\u001c\u0005\u000b\u0007gD#Q3A\u0005\u0002\r]\u0007B\u0003CjQ\tE\t\u0015!\u0003\u0004Z\"Q1Q\u001f\u0015\u0003\u0016\u0004%\taa6\t\u0015\u0011U\u0007F!E!\u0002\u0013\u0019I\u000e\u0003\u0006\u0005&!\u0012)\u001a!C\u0001\u0007sD!\u0002b6)\u0005#\u0005\u000b\u0011BB~\u0011)!\t\u0001\u000bBK\u0002\u0013\u00051\u0011 \u0005\u000b\t3D#\u0011#Q\u0001\n\rm\bB\u0003C\u0002Q\tU\r\u0011\"\u0001\u0005\u0006!QA1\u001c\u0015\u0003\u0012\u0003\u0006I\u0001b\u0002\t\u0015\u0011M\u0001F!f\u0001\n\u0003\")\u0002\u0003\u0006\u0005$!\u0012\t\u0012)A\u0005\t/Aqaa+)\t\u0003!i\u000eC\u0005\u0004x\"\u0012\r\u0011\"\u0001\u0004z\"AA1 \u0015!\u0002\u0013\u0019Y\u0010C\u0005\u0005~\"\n\t\u0011\"\u0001\u0005\u0000\"IQ\u0011\u0004\u0015\u0012\u0002\u0013\u0005Q1\u0004\u0005\n\u000bcA\u0013\u0013!C\u0001\u000b7A\u0011\"b\r)#\u0003%\t!b\u0007\t\u0013\u0015U\u0002&%A\u0005\u0002\u0015m\u0001\"CC\u001cQE\u0005I\u0011AC\u001d\u0011%)i\u0004KI\u0001\n\u0003)I\u0004C\u0005\u0006@!\n\n\u0011\"\u0001\u0006:!IQ\u0011\t\u0015\u0012\u0002\u0013\u0005Q\u0011\b\u0005\n\u000b\u0007B\u0013\u0013!C\u0001\u000b\u000bB\u0011\"\"\u0013)#\u0003%\t!\"\u0012\t\u0013\u0015-\u0003&%A\u0005\u0002\u00155\u0003\"CC)QE\u0005I\u0011AC*\u0011%)9\u0006KA\u0001\n\u0003*I\u0006C\u0005\u0006j!\n\t\u0011\"\u0001\u0006l!IQQ\u000e\u0015\u0002\u0002\u0013\u0005Qq\u000e\u0005\n\u000bkB\u0013\u0011!C!\u000boB\u0011\"\"\")\u0003\u0003%\t!b\"\t\u0013\u0015-\u0005&!A\u0005B\u00155\u0005\"CCIQ\u0005\u0005I\u0011ICJ\u0011%))\nKA\u0001\n\u0003*9jB\u0005\u0006\u001c\u001a\n\t\u0011#\u0001\u0006\u001e\u001aIAq\u0017\u0014\u0002\u0002#\u0005Qq\u0014\u0005\b\u0007WSF\u0011AC\\\u0011%!IKWA\u0001\n\u000b*I\fC\u0005\u0006<j\u000b\t\u0011\"!\u0006>\"IQq\u001b.\u0012\u0002\u0013\u0005Q1\u000b\u0005\n\u000b3T\u0016\u0011!CA\u000b7D\u0011\"\";[#\u0003%\t!b\u0015\t\u0013\u0015-(,!A\u0005\n\u00155hABC{M\u0001)9\u0010\u0003\u0006\u0006z\n\u0014\t\u0011)A\u0005\u0007cCqaa+c\t\u0003)Y\u0010C\u0005\u00046\n\u0014\r\u0011\"\u0001\u00048\"AAq\u00192!\u0002\u0013\u0019I\fC\u0005\u0004P\n\u0014\r\u0011\"\u0001\u00048\"AA\u0011\u001a2!\u0002\u0013\u0019I\fC\u0005\u0004R\n\u0014\r\u0011\"\u0001\u00048\"AA1\u001a2!\u0002\u0013\u0019I\fC\u0005\u0004T\n\u0014\r\u0011\"\u0001\u00048\"AAQ\u001a2!\u0002\u0013\u0019I\fC\u0005\u0004V\n\u0014\r\u0011\"\u0001\u0004X\"AAq\u001a2!\u0002\u0013\u0019I\u000eC\u0005\u0004r\n\u0014\r\u0011\"\u0001\u0004X\"AA\u0011\u001b2!\u0002\u0013\u0019I\u000eC\u0005\u0004t\n\u0014\r\u0011\"\u0001\u0004X\"AA1\u001b2!\u0002\u0013\u0019I\u000eC\u0005\u0004v\n\u0014\r\u0011\"\u0001\u0004X\"AAQ\u001b2!\u0002\u0013\u0019I\u000eC\u0005\u0004x\n\u0014\r\u0011\"\u0001\u0004z\"AA1 2!\u0002\u0013\u0019Y\u0010C\u0005\u0005\u0004\t\u0014\r\u0011\"\u0001\u0005\u0006!AA1\u001c2!\u0002\u0013!9\u0001C\u0005\u0005\u0014\t\u0014\r\u0011\"\u0011\u0005\u0016!AA1\u00052!\u0002\u0013!9\u0002C\u0005\u0005&\t\u0014\r\u0011\"\u0001\u0004z\"AAq\u001b2!\u0002\u0013\u0019Y\u0010C\u0005\u0005\u0002\t\u0014\r\u0011\"\u0001\u0004z\"AA\u0011\u001c2!\u0002\u0013\u0019YpB\u0004\u0007\u0002\u0019B\tAb\u0001\u0007\u000f\u0015Uh\u0005#\u0001\u0007\u0006!A11VA\u0001\t\u000319\u0001\u0003\u0005\u0006<\u0006\u0005A\u0011\u0001D\u0005\u000f\u001d1iA\nE\u0001\r\u001f1qA\"\u0005\'\u0011\u00031\u0019\u0002\u0003\u0005\u0004,\u0006%A\u0011\u0001D\u000b\u0011!)Y,!\u0003\u0005\u0002\u0019]\u0001B\u0003D\u0018\u0003\u0013\t\n\u0011\"\u0001\u0006T!AQ1XA\u0005\t\u00031\t\u0004\u0003\u0005\u0006<\u0006%A\u0011\u0001D\u001f\u0011!)Y,!\u0003\u0005\u0002\u0019-\u0003\u0002CC^\u0003\u0013!\tA\"\u0016\t\u0011\u0015m\u0016\u0011\u0002C\u0001\rGB\u0001\"b/\u0002\n\u0011\u0005aQ\u000f\u0005\t\u000bw\u000bI\u0001\"\u0001\u0007\f\"AQ1XA\u0005\t\u00031\u0019\n\u0003\u0005\u0006<\u0006%A\u0011\u0001DO\u000f\u001d19K\nE\u0001\rS3qAb+\'\u0011\u00031i\u000b\u0003\u0005\u0004,\u0006\u0015B\u0011\u0001DX\u0011!)Y,!\n\u0005\u0002\u0019E\u0006B\u0003D\u0018\u0003K\t\n\u0011\"\u0001\u0006F!Qa1ZA\u0013#\u0003%\t!b\u0015\t\u0011\u0015m\u0016Q\u0005C\u0001\r\u001bD\u0001\"b/\u0002&\u0011\u0005a\u0011\u001c\u0005\t\u000bw\u000b)\u0003\"\u0001\u0007h\"AQ1XA\u0013\t\u00031\t\u0010\u0003\u0005\u0006<\u0006\u0015B\u0011\u0001D\u0000\u0011!)Y,!\n\u0005\u0002\u001dE\u0001\u0002CC^\u0003K!\tab\n\t\u0011\u0015m\u0016Q\u0005C\u0001\u000f_1aa\"\u000f\'\u0001\u001em\u0002bCC}\u0003\u007f\u0011)\u001a!C\u0001\t\'B1b\"\u0010\u0002@\tE\t\u0015!\u0003\u00042\"A11VA \t\u00039y\u0004\u0003\u0006\u00046\u0006}\"\u0019!C\u0001\u0007oC\u0011\u0002b2\u0002@\u0001\u0006Ia!/\t\u0015\r=\u0017q\bb\u0001\n\u0003\u00199\fC\u0005\u0005J\u0006}\u0002\u0015!\u0003\u0004:\"Q1\u0011[A \u0005\u0004%\taa.\t\u0013\u0011-\u0017q\bQ\u0001\n\re\u0006BCBj\u0003\u007f\u0011\r\u0011\"\u0001\u00048\"IAQZA A\u0003%1\u0011\u0018\u0005\u000b\u0007+\fyD1A\u0005\u0002\r]\u0007\"\u0003Ch\u0003\u007f\u0001\u000b\u0011BBm\u0011)\u0019\t0a\u0010C\u0002\u0013\u00051q\u001b\u0005\n\t#\fy\u0004)A\u0005\u00073D!ba=\u0002@\t\u0007I\u0011ABl\u0011%!\u0019.a\u0010!\u0002\u0013\u0019I\u000e\u0003\u0006\u0004v\u0006}\"\u0019!C\u0001\u0007/D\u0011\u0002\"6\u0002@\u0001\u0006Ia!7\t\u0015\r]\u0018q\bb\u0001\n\u0003\u0019I\u0010C\u0005\u0005|\u0006}\u0002\u0015!\u0003\u0004|\"QA1AA \u0005\u0004%\t\u0001\"\u0002\t\u0013\u0011m\u0017q\bQ\u0001\n\u0011\u001d\u0001B\u0003C\u0013\u0003\u007f\u0011\r\u0011\"\u0001\u0004z\"IAq[A A\u0003%11 \u0005\u000b\t\u0003\tyD1A\u0005\u0002\re\b\"\u0003Cm\u0003\u007f\u0001\u000b\u0011BB~\u0011!!\t&a\u0010\u0005B\u0011M\u0003\u0002\u0003CN\u0003\u007f!\te\"\u0012\t\u0015\u0011u\u0018qHA\u0001\n\u00039I\u0005\u0003\u0006\u0006\u001a\u0005}\u0012\u0013!C\u0001\u000f\u001bB!\"b\u0016\u0002@\u0005\u0005I\u0011IC-\u0011))I\'a\u0010\u0002\u0002\u0013\u0005Q1\u000e\u0005\u000b\u000b[\ny$!A\u0005\u0002\u001dE\u0003BCC;\u0003\u007f\t\t\u0011\"\u0011\u0006x!QQQQA \u0003\u0003%\ta\"\u0016\t\u0015\u0015-\u0015qHA\u0001\n\u0003:I\u0006\u0003\u0006\u0006\u0012\u0006}\u0012\u0011!C!\u000b\'C!\"\"&\u0002@\u0005\u0005I\u0011ID/\u000f%9\tGJA\u0001\u0012\u00039\u0019GB\u0005\b:\u0019\n\t\u0011#\u0001\bf!A11VAI\t\u00039i\u0007\u0003\u0006\u0005*\u0006E\u0015\u0011!C#\u000bsC!\"b/\u0002\u0012\u0006\u0005I\u0011QD8\u0011))I.!%\u0002\u0002\u0013\u0005u1\u000f\u0005\u000b\u000bW\f\t*!A\u0005\n\u00155hA\u0002CXM\u0001Ay\u000fC\u0006\b\u0006\u0006u%\u0011!Q\u0001\n\rE\u0006bCDE\u0003;\u0013\t\u0011)A\u0005\u0007cC\u0001ba+\u0002\u001e\u0012\u0005\u0001\u0012\u001f\u0005\u000b\u000f3\u000bi\n\"\u0001\u0004\u0016\u000e]\u0006BCB[\u0003;\u0013\r\u0011\"\u0001\u00048\"IAqYAOA\u0003%1\u0011\u0018\u0005\u000b\u0007\u001f\fiJ1A\u0005\u0002\r]\u0006\"\u0003Ce\u0003;\u0003\u000b\u0011BB]\u0011)\u0019\t.!(C\u0002\u0013\u00051q\u0017\u0005\n\t\u0017\fi\n)A\u0005\u0007sC!ba5\u0002\u001e\n\u0007I\u0011AB\\\u0011%!i-!(!\u0002\u0013\u0019I\f\u0003\u0006\u0004V\u0006u%\u0019!C\u0001\u0007/D\u0011\u0002b4\u0002\u001e\u0002\u0006Ia!7\t\u0015\rE\u0018Q\u0014b\u0001\n\u0003\u00199\u000eC\u0005\u0005R\u0006u\u0005\u0015!\u0003\u0004Z\"Q11_AO\u0005\u0004%\taa6\t\u0013\u0011M\u0017Q\u0014Q\u0001\n\re\u0007BCB{\u0003;\u0013\r\u0011\"\u0001\u0004X\"IAQ[AOA\u0003%1\u0011\u001c\u0005\u000b\u0007o\fiJ1A\u0005\u0002\re\b\"\u0003C~\u0003;\u0003\u000b\u0011BB~\u0011)!)#!(C\u0002\u0013\u00051\u0011 \u0005\n\t/\fi\n)A\u0005\u0007wD!\u0002\"\u0001\u0002\u001e\n\u0007I\u0011AB}\u0011%!I.!(!\u0002\u0013\u0019Y\u0010\u0003\u0006\u0005\u0004\u0005u%\u0019!C\u0001\t\u000bA\u0011\u0002b7\u0002\u001e\u0002\u0006I\u0001b\u0002\t\u0011\u0011m\u0015Q\u0014C!\u0011o<qa\"\u001f\'\u0011\u00039YHB\u0004\u00050\u001aB\ta\" \t\u0011\r-\u00161\u001cC\u0001\u000f\u007fB\u0001\"b/\u0002\\\u0012\u0005q\u0011\u0011\u0004\u0007\u000f\u00173\u0003a\"$\t\u0017\u001d\u0015\u0015\u0011\u001dB\u0001B\u0003%1\u0011\u0017\u0005\f\u000f\u0013\u000b\tO!A!\u0002\u0013\u0019\t\f\u0003\u0005\u0004,\u0006\u0005H\u0011ADI\u0011)9I*!9\u0005B\rU5qW\u0004\b\u000f73\u0003\u0012ADO\r\u001d9YI\nE\u0001\u000f?C\u0001ba+\u0002n\u0012\u0005q\u0011\u0015\u0005\t\u000bw\u000bi\u000f\"\u0001\b$\u001a1q\u0011\u0016\u0014\u0001\u000fWC1b\"\"\u0002t\n\u0005\t\u0015!\u0003\u00042\"Yq\u0011RAz\u0005\u0003\u0005\u000b\u0011BBY\u0011!\u0019Y+a=\u0005\u0002\u001d5\u0006BCDM\u0003g$\ta!&\u00048\"Q1QWAz\u0005\u0004%\taa.\t\u0013\u0011\u001d\u00171\u001fQ\u0001\n\re\u0006BCBh\u0003g\u0014\r\u0011\"\u0001\u00048\"IA\u0011ZAzA\u0003%1\u0011\u0018\u0005\u000b\u0007#\f\u0019P1A\u0005\u0002\r]\u0006\"\u0003Cf\u0003g\u0004\u000b\u0011BB]\u0011)\u0019\u0019.a=C\u0002\u0013\u00051q\u0017\u0005\n\t\u001b\f\u0019\u0010)A\u0005\u0007sC!b!6\u0002t\n\u0007I\u0011ABl\u0011%!y-a=!\u0002\u0013\u0019I\u000e\u0003\u0006\u0004r\u0006M(\u0019!C\u0001\u0007/D\u0011\u0002\"5\u0002t\u0002\u0006Ia!7\t\u0015\rM\u00181\u001fb\u0001\n\u0003\u00199\u000eC\u0005\u0005T\u0006M\b\u0015!\u0003\u0004Z\"Q1Q_Az\u0005\u0004%\taa6\t\u0013\u0011U\u00171\u001fQ\u0001\n\re\u0007BCB|\u0003g\u0014\r\u0011\"\u0001\u0004z\"IA1`AzA\u0003%11 \u0005\u000b\tK\t\u0019P1A\u0005\u0002\re\b\"\u0003Cl\u0003g\u0004\u000b\u0011BB~\u0011)!\t!a=C\u0002\u0013\u00051\u0011 \u0005\n\t3\f\u0019\u0010)A\u0005\u0007wD!\u0002b\u0001\u0002t\n\u0007I\u0011\u0001C\u0003\u0011%!Y.a=!\u0002\u0013!9\u0001\u0003\u0005\u0005\u001c\u0006MH\u0011ID[\u000f\u001d9IL\nE\u0001\u000fw3qa\"+\'\u0011\u00039i\f\u0003\u0005\u0004,\nEB\u0011AD`\u0011!)YL!\r\u0005\u0002\u001d\u0005gABDdM\u00019I\rC\u0006\b\u0006\n]\"\u0011!Q\u0001\n\rE\u0006bCDE\u0005o\u0011\t\u0011)A\u0005\u0007cC\u0001ba+\u00038\u0011\u0005q1\u001a\u0005\u000b\u000f3\u00139\u0004\"\u0011\u0004\u0016\u000e]vaBDjM!\u0005qQ\u001b\u0004\b\u000f\u000f4\u0003\u0012ADl\u0011!\u0019YKa\u0011\u0005\u0002\u001de\u0007\u0002CC^\u0005\u0007\"\tab7\u0007\r\u001d\u0005h\u0005ADr\u0011-9)I!\u0013\u0003\u0002\u0003\u0006Ia!-\t\u0017\u001d%%\u0011\nB\u0001B\u0003%1\u0011\u0017\u0005\t\u0007W\u0013I\u0005\"\u0001\bf\"Q1Q\u0017B%\u0005\u0004%\taa.\t\u0013\u0011\u001d\'\u0011\nQ\u0001\n\re\u0006BCBh\u0005\u0013\u0012\r\u0011\"\u0001\u00048\"IA\u0011\u001aB%A\u0003%1\u0011\u0018\u0005\u000b\u0007#\u0014IE1A\u0005\u0002\r]\u0006\"\u0003Cf\u0005\u0013\u0002\u000b\u0011BB]\u0011)\u0019\u0019N!\u0013C\u0002\u0013\u00051q\u0017\u0005\n\t\u001b\u0014I\u0005)A\u0005\u0007sC!b!6\u0003J\t\u0007I\u0011ABl\u0011%!yM!\u0013!\u0002\u0013\u0019I\u000e\u0003\u0006\u0004r\n%#\u0019!C\u0001\u0007/D\u0011\u0002\"5\u0003J\u0001\u0006Ia!7\t\u0015\rM(\u0011\nb\u0001\n\u0003\u00199\u000eC\u0005\u0005T\n%\u0003\u0015!\u0003\u0004Z\"Q1Q\u001fB%\u0005\u0004%\taa6\t\u0013\u0011U\'\u0011\nQ\u0001\n\re\u0007BCB|\u0005\u0013\u0012\r\u0011\"\u0001\u0004z\"IA1 B%A\u0003%11 \u0005\u000b\t\u0003\u0011IE1A\u0005\u0002\re\b\"\u0003Cm\u0005\u0013\u0002\u000b\u0011BB~\u0011)!\u0019A!\u0013C\u0002\u0013\u0005AQ\u0001\u0005\n\t7\u0014I\u0005)A\u0005\t\u000fA!\u0002\"\n\u0003J\t\u0007I\u0011AB}\u0011%!9N!\u0013!\u0002\u0013\u0019Y\u0010\u0003\u0005\u0005\u001c\n%C\u0011IDw\u000f\u001d9\tP\nE\u0001\u000fg4qa\"9\'\u0011\u00039)\u0010\u0003\u0005\u0004,\n\u0015E\u0011AD|\u0011!)YL!\"\u0005\u0002\u001dehABD\u0000M\u0001A\t\u0001C\u0006\b\u0006\n-%\u0011!Q\u0001\n\rE\u0006bCDE\u0005\u0017\u0013\t\u0011)A\u0005\u0007cC\u0001ba+\u0003\f\u0012\u0005\u00012\u0001\u0005\u000b\u0007k\u0013YI1A\u0005\u0002\r]\u0006\"\u0003Cd\u0005\u0017\u0003\u000b\u0011BB]\u0011)\u0019yMa#C\u0002\u0013\u00051q\u0017\u0005\n\t\u0013\u0014Y\t)A\u0005\u0007sC!b!5\u0003\f\n\u0007I\u0011AB\\\u0011%!YMa#!\u0002\u0013\u0019I\f\u0003\u0006\u0004T\n-%\u0019!C\u0001\u0007oC\u0011\u0002\"4\u0003\f\u0002\u0006Ia!/\t\u0015\rU\'1\u0012b\u0001\n\u0003\u00199\u000eC\u0005\u0005P\n-\u0005\u0015!\u0003\u0004Z\"Q1\u0011\u001fBF\u0005\u0004%\taa6\t\u0013\u0011E\'1\u0012Q\u0001\n\re\u0007BCBz\u0005\u0017\u0013\r\u0011\"\u0001\u0004X\"IA1\u001bBFA\u0003%1\u0011\u001c\u0005\u000b\u0007k\u0014YI1A\u0005\u0002\r]\u0007\"\u0003Ck\u0005\u0017\u0003\u000b\u0011BBm\u0011)\u00199Pa#C\u0002\u0013\u00051\u0011 \u0005\n\tw\u0014Y\t)A\u0005\u0007wD!\u0002\"\n\u0003\f\n\u0007I\u0011AB}\u0011%!9Na#!\u0002\u0013\u0019Y\u0010\u0003\u0006\u0005\u0002\t-%\u0019!C\u0001\u0007sD\u0011\u0002\"7\u0003\f\u0002\u0006Iaa?\t\u0015\u0011\r!1\u0012b\u0001\n\u0003!)\u0001C\u0005\u0005\\\n-\u0005\u0015!\u0003\u0005\b!AA1\u0014BF\t\u0003BYaB\u0004\t\u0010\u0019B\t\u0001#\u0005\u0007\u000f\u001d}h\u0005#\u0001\t\u0014!A11\u0016Bd\t\u0003A)\u0002\u0003\u0005\u0006<\n\u001dG\u0011\u0001E\f\r%AiBJA\u0011\u0007+Cy\u0002\u0003\u0005\u0004,\n5G\u0011\u0001E\u0011\u0011)A)C!4C\u0002\u001b\u00051q\u001b\u0004\t\u0011S1\u0003i!&\t,!Y\u0001R\u0006Bj\u0005+\u0007I\u0011\u0001C*\u0011-AyCa5\u0003\u0012\u0003\u0006Ia!-\t\u0011\r-&1\u001bC\u0001\u0011cA!\u0002#\n\u0003T\n\u0007I\u0011ABl\u0011%A9Da5!\u0002\u0013\u0019I\u000e\u0003\u0005\u0005*\nMG\u0011\tCV\u0011)!iPa5\u0002\u0002\u0013\u0005\u0001\u0012\b\u0005\u000b\u000b3\u0011\u0019.%A\u0005\u0002\u001d5\u0003BCC,\u0005\'\f\t\u0011\"\u0011\u0006Z!QQ\u0011\u000eBj\u0003\u0003%\t!b\u001b\t\u0015\u00155$1[A\u0001\n\u0003Ai\u0004\u0003\u0006\u0006v\tM\u0017\u0011!C!\u000boB!\"\"\"\u0003T\u0006\u0005I\u0011\u0001E!\u0011))YIa5\u0002\u0002\u0013\u0005\u0003R\t\u0005\u000b\u000b#\u0013\u0019.!A\u0005B\u0015M\u0005BCCK\u0005\'\f\t\u0011\"\u0011\tJ\u001dY\u0001r\u0015\u0014\u0002\u0002#\u00051Q\u0013EU\r-AICJA\u0001\u0012\u0003\u0019)\nc+\t\u0011\r-&q\u001fC\u0001\u0011_C!\u0002\"+\u0003x\u0006\u0005IQIC]\u0011))YLa>\u0002\u0002\u0013\u0005\u0005\u0012\u0017\u0005\u000b\u000b3\u001490!A\u0005\u0002\"U\u0006BCCv\u0005o\f\t\u0011\"\u0003\u0006n\u001aA\u0001R\n\u0014A\u0007+Cy\u0005C\u0006\t.\r\r!Q3A\u0005\u0002\u0011M\u0003b\u0003E\u0018\u0007\u0007\u0011\t\u0012)A\u0005\u0007cC\u0001ba+\u0004\u0004\u0011\u0005\u0001\u0012\u000b\u0005\u000b\u0011K\u0019\u0019A1A\u0005\u0002\r]\u0007\"\u0003E\u001c\u0007\u0007\u0001\u000b\u0011BBm\u0011!!Ika\u0001\u0005B\u0011-\u0006B\u0003C\u007f\u0007\u0007\t\t\u0011\"\u0001\tX!QQ\u0011DB\u0002#\u0003%\ta\"\u0014\t\u0015\u0015]31AA\u0001\n\u0003*I\u0006\u0003\u0006\u0006j\r\r\u0011\u0011!C\u0001\u000bWB!\"\"\u001c\u0004\u0004\u0005\u0005I\u0011\u0001E.\u0011)))ha\u0001\u0002\u0002\u0013\u0005Sq\u000f\u0005\u000b\u000b\u000b\u001b\u0019!!A\u0005\u0002!}\u0003BCCF\u0007\u0007\t\t\u0011\"\u0011\td!QQ\u0011SB\u0002\u0003\u0003%\t%b%\t\u0015\u0015U51AA\u0001\n\u0003B9gB\u0006\t:\u001a\n\t\u0011#\u0001\u0004\u0016\"mfa\u0003E\'M\u0005\u0005\t\u0012ABK\u0011{C\u0001ba+\u0004(\u0011\u0005\u0001\u0012\u0019\u0005\u000b\tS\u001b9#!A\u0005F\u0015e\u0006BCC^\u0007O\t\t\u0011\"!\tD\"QQ\u0011\\B\u0014\u0003\u0003%\t\tc2\t\u0015\u0015-8qEA\u0001\n\u0013)iO\u0002\u0005\t\n\u001a\u00025Q\u0013EF\u0011-Aica\r\u0003\u0016\u0004%\t\u0001b\u0015\t\u0017!=21\u0007B\tB\u0003%1\u0011\u0017\u0005\t\u0007W\u001b\u0019\u0004\"\u0001\t\u000e\"Q\u0001REB\u001a\u0005\u0004%\taa6\t\u0013!]21\u0007Q\u0001\n\re\u0007\u0002\u0003CU\u0007g!\t\u0005b+\t\u0015\u0011u81GA\u0001\n\u0003A\u0019\n\u0003\u0006\u0006\u001a\rM\u0012\u0013!C\u0001\u000f\u001bB!\"b\u0016\u00044\u0005\u0005I\u0011IC-\u0011))Iga\r\u0002\u0002\u0013\u0005Q1\u000e\u0005\u000b\u000b[\u001a\u0019$!A\u0005\u0002!]\u0005BCC;\u0007g\t\t\u0011\"\u0011\u0006x!QQQQB\u001a\u0003\u0003%\t\u0001c\'\t\u0015\u0015-51GA\u0001\n\u0003By\n\u0003\u0006\u0006\u0012\u000eM\u0012\u0011!C!\u000b\'C!\"\"&\u00044\u0005\u0005I\u0011\tER\u000f-AYMJA\u0001\u0012\u0003\u0019)\n#4\u0007\u0017!%e%!A\t\u0002\rU\u0005r\u001a\u0005\t\u0007W\u001b9\u0006\"\u0001\tT\"QA\u0011VB,\u0003\u0003%)%\"/\t\u0015\u0015m6qKA\u0001\n\u0003C)\u000e\u0003\u0006\u0006Z\u000e]\u0013\u0011!CA\u00113D!\"b;\u0004X\u0005\u0005I\u0011BCw\r!AYG\n!\u0004\u0016\"5\u0004b\u0003E\u0017\u0007G\u0012)\u001a!C\u0001\t\'B1\u0002c\f\u0004d\tE\t\u0015!\u0003\u00042\"A11VB2\t\u0003Ay\u0007\u0003\u0006\t&\r\r$\u0019!C\u0001\u0007/D\u0011\u0002c\u000e\u0004d\u0001\u0006Ia!7\t\u0011\u0011%61\rC!\tWC!\u0002\"@\u0004d\u0005\u0005I\u0011\u0001E;\u0011))Iba\u0019\u0012\u0002\u0013\u0005qQ\n\u0005\u000b\u000b/\u001a\u0019\'!A\u0005B\u0015e\u0003BCC5\u0007G\n\t\u0011\"\u0001\u0006l!QQQNB2\u0003\u0003%\t\u0001#\u001f\t\u0015\u0015U41MA\u0001\n\u0003*9\b\u0003\u0006\u0006\u0006\u000e\r\u0014\u0011!C\u0001\u0011{B!\"b#\u0004d\u0005\u0005I\u0011\tEA\u0011))\tja\u0019\u0002\u0002\u0013\u0005S1\u0013\u0005\u000b\u000b+\u001b\u0019\'!A\u0005B!\u0015ua\u0003EoM\u0005\u0005\t\u0012ABK\u0011?41\u0002c\u001b\'\u0003\u0003E\ta!&\tb\"A11VBD\t\u0003A)\u000f\u0003\u0006\u0005*\u000e\u001d\u0015\u0011!C#\u000bsC!\"b/\u0004\b\u0006\u0005I\u0011\u0011Et\u0011))Ina\"\u0002\u0002\u0013\u0005\u00052\u001e\u0005\u000b\u000bW\u001c9)!A\u0005\n\u00155(\u0001\u0002$bGRTAaa&\u0004\u001a\u0006I1oY1mCR,7\u000f\u001e\u0006\u0003\u00077\u000b1a\u001c:h\'\r\u00011q\u0014\t\u0005\u0007C\u001b9+\u0004\u0002\u0004$*\u00111QU\u0001\u0006g\u000e\fG.Y\u0005\u0005\u0007S\u001b\u0019K\u0001\u0004B]f\u0014VMZ\u0001\u0007y%t\u0017\u000e\u001e \u0004\u0001Q\u00111\u0011\u0017\t\u0004\u0007g\u0003QBABK\u00039\u0011\u0018m\u001e$bGRlUm]:bO\u0016,\"a!/\u0011\t\rm6\u0011\u001a\b\u0005\u0007{\u001b)\r\u0005\u0003\u0004@\u000e\rVBABa\u0015\u0011\u0019\u0019m!,\u0002\rq\u0012xn\u001c;?\u0013\u0011\u00199ma)\u0002\rA\u0013X\rZ3g\u0013\u0011\u0019Ym!4\u0003\rM#(/\u001b8h\u0015\u0011\u00199ma)\u00021I\fwoU5na2Lg-[3e\r\u0006\u001cG/T3tg\u0006<W-A\rsC^l\u0015\u000eZ*f]R,gnY3GC\u000e$X*Z:tC\u001e,\u0017a\t:bo6KGmU3oi\u0016t7-Z*j[Bd\u0017NZ5fI\u001a\u000b7\r^\'fgN\fw-Z\u0001\u0010M\u0006\u001cG/T3tg\u0006<W-\u0011:hgV\u00111\u0011\u001c\t\u0007\u00077\u001c)oa;\u000f\t\ru7\u0011\u001d\b\u0005\u0007\u007f\u001by.\u0003\u0002\u0004&&!11]BR\u0003\u001d\u0001\u0018mY6bO\u0016LAaa:\u0004j\nQ\u0011J\u001c3fq\u0016$7+Z9\u000b\t\r\r81\u0015\t\u0005\u0007C\u001bi/\u0003\u0003\u0004p\u000e\r&aA!os\u0006I2/[7qY&4\u0017.\u001a3GC\u000e$X*Z:tC\u001e,\u0017I]4t\u0003ii\u0017\u000eZ*f]R,gnY3GC\u000e$X*Z:tC\u001e,\u0017I]4t\u0003\u0011j\u0017\u000eZ*f]R,gnY3TS6\u0004H.\u001b4jK\u00124\u0015m\u0019;NKN\u001c\u0018mZ3Be\u001e\u001c\u0018AB5t\u0019\u0016\fg-\u0006\u0002\u0004|B!1\u0011UB\u007f\u0013\u0011\u0019ypa)\u0003\u000f\t{w\u000e\\3b]\u0006a\u0011n\u001d,bGV|Wo]-fg\u0006Q\u0001O]3ui&4\u0017.\u001a:\u0016\u0005\u0011\u001d\u0001\u0003\u0002C\u0005\t\u001fi!\u0001b\u0003\u000b\t\u001151\u0011T\u0001\ng\u000e\fG.Y2uS\u000eLA\u0001\"\u0005\u0005\f\tQ\u0001K]3ui&4\u0017.\u001a:\u0002\u000b\r\fWo]3\u0016\u0005\u0011]\u0001CBBQ\t3!i\"\u0003\u0003\u0005\u001c\r\r&AB(qi&|g\u000e\u0005\u0003\u0004\\\u0012}\u0011\u0002\u0002C\u0011\u0007S\u0014\u0011\u0002\u00165s_^\f\'\r\\3\u0002\r\r\fWo]3!\u0003\u0015I7/W3t\u0003\u0011I7OT8\u0002\u0013Q|\'i\\8mK\u0006t\u0017a\u0003;p\u0003N\u001cXM\u001d;j_:$B\u0001b\f\u0005<A!A\u0011\u0007C\u001b\u001d\u0011\u0019\u0019\fb\r\n\t\r\r8QS\u0005\u0005\to!IDA\u0005BgN,\'\u000f^5p]*!11]BK\u0011\u001d!iD\u0005a\u0002\t\u007f\t1\u0001]8t!\u0011!\t\u0005b\u0012\u000e\u0005\u0011\r#\u0002\u0002C#\t\u0017\taa]8ve\u000e,\u0017\u0002\u0002C%\t\u0007\u0012\u0001\u0002U8tSRLwN\\\u0001\u0014S:$XM\u001d8bYR{\u0017i]:feRLwN\u001c\u000b\u0005\t_!y\u0005C\u0004\u0005>M\u0001\r\u0001b\u0010\u0002\u0017Ut\u0017M]=`I\t\fgnZ\u000b\u0003\u0007c\u000b\u0001\u0002\n2be\u0012\u0012\u0017M\u001d\u000b\u0005\u0007c#I\u0006\u0003\u0005\u0005\\U!\t\u0019\u0001C/\u0003\r\u0011\bn\u001d\t\u0007\u0007C#yf!-\n\t\u0011\u000541\u0015\u0002\ty\tLh.Y7f}\u0005AA%Y7qI\u0005l\u0007\u000f\u0006\u0003\u00042\u0012\u001d\u0004\u0002\u0003C.-\u0011\u0005\r\u0001\"\u0018\u0002\t\u0011\u0012\u0017M\u001d\u000b\u0005\u0007c#i\u0007C\u0004\u0005\\]\u0001\ra!-\u0002\t\u0011\nW\u000e\u001d\u000b\u0005\u0007c#\u0019\bC\u0004\u0005\\a\u0001\ra!-\u0002\u0019M$(/\u001b8h!J,g-\u001b=\u0002\u000f%l\u0007\u000f\\5fgR!1\u0011\u0017C>\u0011!!YF\u0007CA\u0002\u0011u\u0013aB5t\u000bF4Hk\u001c\u000b\u0005\u0007c#\t\tC\u0004\u0005\\m\u0001\ra!-\u0002\u0017\u0019\f7\r^\'fgN\fw-Z\u0001\u0016g&l\u0007\u000f\\5gS\u0016$g)Y2u\u001b\u0016\u001c8/Y4f\u0003Yi\u0017\u000eZ*f]R,gnY3GC\u000e$X*Z:tC\u001e,\u0017\u0001I7jIN+g\u000e^3oG\u0016\u001c\u0016.\u001c9mS\u001aLW\r\u001a$bGRlUm]:bO\u0016\f!\"\\1lKN#(/\u001b8h)\u0019\u0019I\fb$\u0005\u0014\"9A\u0011\u0013\u0011A\u0002\re\u0016a\u0001:bo\"9AQ\u0013\u0011A\u0002\re\u0017\u0001B1sON\fqAT#X\u0019&sU)\u0001\u0005O\u000b^c\u0015JT#!\u0003-1\u0017m\u0019;ES\u0006<\'/Y7\u0015\t\reFq\u0014\u0005\b\tC\u001b\u0003\u0019\u0001CR\u0003\u0015aWM^3m!\u0011\u0019\t\u000b\"*\n\t\u0011\u001d61\u0015\u0002\u0004\u0013:$\u0018\u0001\u0003;p\'R\u0014\u0018N\\4\u0015\u0005\re\u0016&\u0004\u0001\u0002\u001e\u0006M(\u0011\nBFQ\u0005}\"MA\u0006CS:\f\'/_0%C6\u00048c\u0001\u0014\u0004 R\u0011AQ\u0017\t\u0004\u0007g3#\u0001\u0002\'fC\u001a\u001cr\u0001KBY\tw#\t\r\u0005\u0003\u0004\"\u0012u\u0016\u0002\u0002C`\u0007G\u0013q\u0001\u0015:pIV\u001cG\u000f\u0005\u0003\u0004\\\u0012\r\u0017\u0002\u0002Cc\u0007S\u0014AbU3sS\u0006d\u0017N_1cY\u0016\fqB]1x\r\u0006\u001cG/T3tg\u0006<W\rI\u0001\u001ae\u0006<8+[7qY&4\u0017.\u001a3GC\u000e$X*Z:tC\u001e,\u0007%\u0001\u000esC^l\u0015\u000eZ*f]R,gnY3GC\u000e$X*Z:tC\u001e,\u0007%\u0001\u0013sC^l\u0015\u000eZ*f]R,gnY3TS6\u0004H.\u001b4jK\u00124\u0015m\u0019;NKN\u001c\u0018mZ3!\u0003A1\u0017m\u0019;NKN\u001c\u0018mZ3Be\u001e\u001c\b%\u0001\u000etS6\u0004H.\u001b4jK\u00124\u0015m\u0019;NKN\u001c\u0018mZ3Be\u001e\u001c\b%A\u000enS\u0012\u001cVM\u001c;f]\u000e,g)Y2u\u001b\u0016\u001c8/Y4f\u0003J<7\u000fI\u0001&[&$7+\u001a8uK:\u001cWmU5na2Lg-[3e\r\u0006\u001cG/T3tg\u0006<W-\u0011:hg\u0002\na![:ZKN\u0004\u0013!D5t-\u0006\u001cWo\\;t3\u0016\u001c\b%A\u0006qe\u0016$H/\u001b4jKJ\u0004CC\u0007Cp\tG$)\u000fb:\u0005j\u0012-HQ\u001eCx\tc$\u0019\u0010\">\u0005x\u0012e\bc\u0001CqQ5\ta\u0005C\u0004\u00046\u0006\u0003\ra!/\t\u000f\r=\u0017\t1\u0001\u0004:\"91\u0011[!A\u0002\re\u0006bBBj\u0003\u0002\u00071\u0011\u0018\u0005\b\u0007+\f\u0005\u0019ABm\u0011\u001d\u0019\t0\u0011a\u0001\u00073Dqaa=B\u0001\u0004\u0019I\u000eC\u0004\u0004v\u0006\u0003\ra!7\t\u000f\u0011\u0015\u0012\t1\u0001\u0004|\"9A\u0011A!A\u0002\rm\bb\u0002C\u0002\u0003\u0002\u0007Aq\u0001\u0005\n\t\'\t\u0005\u0013!a\u0001\t/\tq![:MK\u00064\u0007%\u0001\u0003d_BLHC\u0007Cp\u000b\u0003)\u0019!\"\u0002\u0006\b\u0015%Q1BC\u0007\u000b\u001f)\t\"b\u0005\u0006\u0016\u0015]\u0001\"CB[\tB\u0005\t\u0019AB]\u0011%\u0019y\r\u0012I\u0001\u0002\u0004\u0019I\fC\u0005\u0004R\u0012\u0003\n\u00111\u0001\u0004:\"I11\u001b#\u0011\u0002\u0003\u00071\u0011\u0018\u0005\n\u0007+$\u0005\u0013!a\u0001\u00073D\u0011b!=E!\u0003\u0005\ra!7\t\u0013\rMH\t%AA\u0002\re\u0007\"CB{\tB\u0005\t\u0019ABm\u0011%!)\u0003\u0012I\u0001\u0002\u0004\u0019Y\u0010C\u0005\u0005\u0002\u0011\u0003\n\u00111\u0001\u0004|\"IA1\u0001#\u0011\u0002\u0003\u0007Aq\u0001\u0005\n\t\'!\u0005\u0013!a\u0001\t/\tabY8qs\u0012\"WMZ1vYR$\u0013\'\u0006\u0002\u0006\u001e)\"1\u0011XC\u0010W\t)\t\u0003\u0005\u0003\u0006$\u00155RBAC\u0013\u0015\u0011)9#\"\u000b\u0002\u0013Ut7\r[3dW\u0016$\'\u0002BC\u0016\u0007G\u000b!\"\u00198o_R\fG/[8o\u0013\u0011)y#\"\n\u0003#Ut7\r[3dW\u0016$g+\u0019:jC:\u001cW-\u0001\bd_BLH\u0005Z3gCVdG\u000f\n\u001a\u0002\u001d\r|\u0007/\u001f\u0013eK\u001a\fW\u000f\u001c;%g\u0005q1m\u001c9zI\u0011,g-Y;mi\u0012\"\u0014AD2paf$C-\u001a4bk2$H%N\u000b\u0003\u000bwQCa!7\u0006 \u0005q1m\u001c9zI\u0011,g-Y;mi\u00122\u0014AD2paf$C-\u001a4bk2$HeN\u0001\u000fG>\u0004\u0018\u0010\n3fM\u0006,H\u000e\u001e\u00139\u00039\u0019w\u000e]=%I\u00164\u0017-\u001e7uIe*\"!b\u0012+\t\rmXqD\u0001\u0010G>\u0004\u0018\u0010\n3fM\u0006,H\u000e\u001e\u00132a\u0005y1m\u001c9zI\u0011,g-Y;mi\u0012\n\u0014\'\u0006\u0002\u0006P)\"AqAC\u0010\u0003=\u0019w\u000e]=%I\u00164\u0017-\u001e7uIE\u0012TCAC+U\u0011!9\"b\b\u0002\u001bA\u0014x\u000eZ;diB\u0013XMZ5y+\t)Y\u0006\u0005\u0003\u0006^\u0015\u001dTBAC0\u0015\u0011)\t\'b\u0019\u0002\t1\fgn\u001a\u0006\u0003\u000bK\nAA[1wC&!11ZC0\u00031\u0001(o\u001c3vGR\f%/\u001b;z+\t!\u0019+\u0001\bqe>$Wo\u0019;FY\u0016lWM\u001c;\u0015\t\r-X\u0011\u000f\u0005\n\u000bg\u001a\u0016\u0011!a\u0001\tG\u000b1\u0001\u001f\u00132\u0003=\u0001(o\u001c3vGRLE/\u001a:bi>\u0014XCAC=!\u0019)Y(\"!\u0004l6\u0011QQ\u0010\u0006\u0005\u000b\u007f\u001a\u0019+\u0001\u0006d_2dWm\u0019;j_:LA!b!\u0006~\tA\u0011\n^3sCR|\'/\u0001\u0005dC:,\u0015/^1m)\u0011\u0019Y0\"#\t\u0013\u0015MT+!AA\u0002\r-\u0018A\u00059s_\u0012,8\r^#mK6,g\u000e\u001e(b[\u0016$B!b\u0017\u0006\u0010\"IQ1\u000f,\u0002\u0002\u0003\u0007A1U\u0001\tQ\u0006\u001c\bnQ8eKR\u0011A1U\u0001\u0007KF,\u0018\r\\:\u0015\t\rmX\u0011\u0014\u0005\n\u000bgB\u0016\u0011!a\u0001\u0007W\fA\u0001T3bMB\u0019A\u0011\u001d.\u0014\u000bi+\t+\",\u0011=\u0015\rV\u0011VB]\u0007s\u001bIl!/\u0004Z\u000ee7\u0011\\Bm\u0007w\u001cY\u0010b\u0002\u0005\u0018\u0011}WBACS\u0015\u0011)9ka)\u0002\u000fI,h\u000e^5nK&!Q1VCS\u0005I\t%m\u001d;sC\u000e$h)\u001e8di&|g.\r\u001a\u0011\t\u0015=VQW\u0007\u0003\u000bcSA!b-\u0006d\u0005\u0011\u0011n\\\u0005\u0005\t\u000b,\t\f\u0006\u0002\u0006\u001eR\u0011Q1L\u0001\u0006CB\u0004H.\u001f\u000b\u001b\t?,y,\"1\u0006D\u0016\u0015WqYCe\u000b\u0017,i-b4\u0006R\u0016MWQ\u001b\u0005\b\u0007kk\u0006\u0019AB]\u0011\u001d\u0019y-\u0018a\u0001\u0007sCqa!5^\u0001\u0004\u0019I\fC\u0004\u0004Tv\u0003\ra!/\t\u000f\rUW\f1\u0001\u0004Z\"91\u0011_/A\u0002\re\u0007bBBz;\u0002\u00071\u0011\u001c\u0005\b\u0007kl\u0006\u0019ABm\u0011\u001d!)#\u0018a\u0001\u0007wDq\u0001\"\u0001^\u0001\u0004\u0019Y\u0010C\u0004\u0005\u0004u\u0003\r\u0001b\u0002\t\u0013\u0011MQ\f%AA\u0002\u0011]\u0011\u0001E1qa2LH\u0005Z3gCVdG\u000fJ\u00193\u0003\u001d)h.\u00199qYf$B!\"8\u0006fB11\u0011\u0015C\r\u000b?\u0004Bd!)\u0006b\u000ee6\u0011XB]\u0007s\u001bIn!7\u0004Z\u000ee71`B~\t\u000f!9\"\u0003\u0003\u0006d\u000e\r&a\u0002+va2,\u0017G\r\u0005\n\u000bO|\u0016\u0011!a\u0001\t?\f1\u0001\u001f\u00131\u0003q!C.Z:tS:LG\u000fJ4sK\u0006$XM\u001d\u0013eK\u001a\fW\u000f\u001c;%cI\nAb\u001e:ji\u0016\u0014V\r\u001d7bG\u0016$\"!b<\u0011\t\u0015uS\u0011_\u0005\u0005\u000bg,yF\u0001\u0004PE*,7\r\u001e\u0002\u000b-\u0006\u001cWo\\;t3\u0016\u001c8c\u00012\u00042\u0006QQO\u001c3fe2L\u0018N\\4\u0015\t\u0015uXq \t\u0004\tC\u0014\u0007bBC}I\u0002\u00071\u0011W\u0001\u000b-\u0006\u001cWo\\;t3\u0016\u001c\b\u0003\u0002Cq\u0003\u0003\u0019B!!\u0001\u0004 R\u0011a1\u0001\u000b\u0005\u000b{4Y\u0001\u0003\u0005\u0006z\u0006\u0015\u0001\u0019ABY\u0003\tqu\u000e\u0005\u0003\u0005b\u0006%!A\u0001(p\'\u0011\tIaa(\u0015\u0005\u0019=A\u0003\u0006D\r\r;1yB\"\t\u0007$\u0019\u0015bq\u0005D\u0015\rW1i\u0003\u0006\u0003\u0005`\u001am\u0001\u0002\u0003C\u0002\u0003\u001b\u0001\u001d\u0001b\u0002\t\u0011\rU\u0016Q\u0002a\u0001\u0007sC\u0001ba4\u0002\u000e\u0001\u00071\u0011\u0018\u0005\t\u0007#\fi\u00011\u0001\u0004:\"A11[A\u0007\u0001\u0004\u0019I\f\u0003\u0005\u0004V\u00065\u0001\u0019ABm\u0011!\u0019\t0!\u0004A\u0002\re\u0007\u0002CBz\u0003\u001b\u0001\ra!7\t\u0011\rU\u0018Q\u0002a\u0001\u00073D!\u0002b\u0005\u0002\u000eA\u0005\t\u0019\u0001C\f\u0003=\t\u0007\u000f\u001d7zI\u0011,g-Y;mi\u0012JD\u0003\u0003D\u001a\ro1IDb\u000f\u0015\t\u0011}gQ\u0007\u0005\t\t\u0007\t\t\u0002q\u0001\u0005\b!A1QWA\t\u0001\u0004\u0019I\f\u0003\u0005\u0004R\u0006E\u0001\u0019AB]\u0011!\u0019).!\u0005A\u0002\reGC\u0003D \r\u00072)Eb\u0012\u0007JQ!Aq\u001cD!\u0011!!\u0019!a\u0005A\u0004\u0011\u001d\u0001\u0002CB[\u0003\'\u0001\ra!/\t\u0011\rE\u00171\u0003a\u0001\u0007sC\u0001b!6\u0002\u0014\u0001\u00071\u0011\u001c\u0005\t\u0007g\f\u0019\u00021\u0001\u0004ZR1aQ\nD)\r\'\"B\u0001b8\u0007P!AA1AA\u000b\u0001\b!9\u0001\u0003\u0005\u00046\u0006U\u0001\u0019AB]\u0011!\u0019\t.!\u0006A\u0002\reFC\u0003D,\r72iFb\u0018\u0007bQ!Aq\u001cD-\u0011!!\u0019!a\u0006A\u0004\u0011\u001d\u0001\u0002CB[\u0003/\u0001\ra!/\t\u0011\r=\u0017q\u0003a\u0001\u0007sC\u0001b!5\u0002\u0018\u0001\u00071\u0011\u0018\u0005\t\u0007\'\f9\u00021\u0001\u0004:RqaQ\rD5\rW2iGb\u001c\u0007r\u0019MD\u0003\u0002Cp\rOB\u0001\u0002b\u0001\u0002\u001a\u0001\u000fAq\u0001\u0005\t\u0007k\u000bI\u00021\u0001\u0004:\"A1qZA\r\u0001\u0004\u0019I\f\u0003\u0005\u0004R\u0006e\u0001\u0019AB]\u0011!\u0019\u0019.!\u0007A\u0002\re\u0006\u0002CBk\u00033\u0001\ra!7\t\u0011\rE\u0018\u0011\u0004a\u0001\u00073$\"Cb\u001e\u0007|\u0019udq\u0010DA\r\u00073)Ib\"\u0007\nR!Aq\u001cD=\u0011!!\u0019!a\u0007A\u0004\u0011\u001d\u0001\u0002CB[\u00037\u0001\ra!/\t\u0011\r=\u00171\u0004a\u0001\u0007sC\u0001b!5\u0002\u001c\u0001\u00071\u0011\u0018\u0005\t\u0007\'\fY\u00021\u0001\u0004:\"A1Q[A\u000e\u0001\u0004\u0019I\u000e\u0003\u0005\u0004r\u0006m\u0001\u0019ABm\u0011!\u0019\u00190a\u0007A\u0002\re\u0007\u0002CB{\u00037\u0001\ra!7\u0015\t\u00195e\u0011\u0013\u000b\u0005\t?4y\t\u0003\u0005\u0005\u0004\u0005u\u00019\u0001C\u0004\u0011!\u0019),!\bA\u0002\reFC\u0002DK\r33Y\n\u0006\u0003\u0005`\u001a]\u0005\u0002\u0003C\u0002\u0003?\u0001\u001d\u0001b\u0002\t\u0011\rU\u0016q\u0004a\u0001\u0007sC\u0001b!6\u0002 \u0001\u00071\u0011\u001c\u000b\u0007\r?3\u0019K\"*\u0015\t\u0011}g\u0011\u0015\u0005\t\t\u0007\t\t\u0003q\u0001\u0005\b!A1QWA\u0011\u0001\u0004\u0019I\f\u0003\u0005\u0005\u0014\u0005\u0005\u0002\u0019\u0001C\u000f\u0003\rIVm\u001d\t\u0005\tC\f)CA\u0002ZKN\u001cB!!\n\u0004 R\u0011a\u0011\u0016\u000b\u0017\rg39L\"/\u0007<\u001aufq\u0018Da\r\u00074)Mb2\u0007JR!Aq\u001cD[\u0011!!\u0019!!\u000bA\u0004\u0011\u001d\u0001\u0002CB[\u0003S\u0001\ra!/\t\u0011\r=\u0017\u0011\u0006a\u0001\u0007sC\u0001b!5\u0002*\u0001\u00071\u0011\u0018\u0005\t\u0007\'\fI\u00031\u0001\u0004:\"A1Q[A\u0015\u0001\u0004\u0019I\u000e\u0003\u0005\u0004r\u0006%\u0002\u0019ABm\u0011!\u0019\u00190!\u000bA\u0002\re\u0007\u0002CB{\u0003S\u0001\ra!7\t\u0015\u0011\u0005\u0011\u0011\u0006I\u0001\u0002\u0004\u0019Y\u0010\u0003\u0006\u0005\u0014\u0005%\u0002\u0013!a\u0001\t/\t\u0001#\u00199qYf$C-\u001a4bk2$H%\r\u0019\u0015\u0011\u0019=g1\u001bDk\r/$B\u0001b8\u0007R\"AA1AA\u0018\u0001\b!9\u0001\u0003\u0005\u00046\u0006=\u0002\u0019AB]\u0011!\u0019\t.a\fA\u0002\re\u0006\u0002CBk\u0003_\u0001\ra!7\u0015\u0015\u0019mgq\u001cDq\rG4)\u000f\u0006\u0003\u0005`\u001au\u0007\u0002\u0003C\u0002\u0003c\u0001\u001d\u0001b\u0002\t\u0011\rU\u0016\u0011\u0007a\u0001\u0007sC\u0001b!5\u00022\u0001\u00071\u0011\u0018\u0005\t\u0007+\f\t\u00041\u0001\u0004Z\"A11_A\u0019\u0001\u0004\u0019I\u000e\u0006\u0004\u0007j\u001a5hq\u001e\u000b\u0005\t?4Y\u000f\u0003\u0005\u0005\u0004\u0005M\u00029\u0001C\u0004\u0011!\u0019),a\rA\u0002\re\u0006\u0002CBi\u0003g\u0001\ra!/\u0015\u0015\u0019Mhq\u001fD}\rw4i\u0010\u0006\u0003\u0005`\u001aU\b\u0002\u0003C\u0002\u0003k\u0001\u001d\u0001b\u0002\t\u0011\rU\u0016Q\u0007a\u0001\u0007sC\u0001ba4\u00026\u0001\u00071\u0011\u0018\u0005\t\u0007#\f)\u00041\u0001\u0004:\"A11[A\u001b\u0001\u0004\u0019I\f\u0006\b\b\u0002\u001d\u0015qqAD\u0005\u000f\u00179iab\u0004\u0015\t\u0011}w1\u0001\u0005\t\t\u0007\t9\u0004q\u0001\u0005\b!A1QWA\u001c\u0001\u0004\u0019I\f\u0003\u0005\u0004P\u0006]\u0002\u0019AB]\u0011!\u0019\t.a\u000eA\u0002\re\u0006\u0002CBj\u0003o\u0001\ra!/\t\u0011\rU\u0017q\u0007a\u0001\u00073D\u0001b!=\u00028\u0001\u00071\u0011\u001c\u000b\u0013\u000f\'99b\"\u0007\b\u001c\u001duqqDD\u0011\u000fG9)\u0003\u0006\u0003\u0005`\u001eU\u0001\u0002\u0003C\u0002\u0003s\u0001\u001d\u0001b\u0002\t\u0011\rU\u0016\u0011\ba\u0001\u0007sC\u0001ba4\u0002:\u0001\u00071\u0011\u0018\u0005\t\u0007#\fI\u00041\u0001\u0004:\"A11[A\u001d\u0001\u0004\u0019I\f\u0003\u0005\u0004V\u0006e\u0002\u0019ABm\u0011!\u0019\t0!\u000fA\u0002\re\u0007\u0002CBz\u0003s\u0001\ra!7\t\u0011\rU\u0018\u0011\ba\u0001\u00073$Ba\"\u000b\b.Q!Aq\\D\u0016\u0011!!\u0019!a\u000fA\u0004\u0011\u001d\u0001\u0002CB[\u0003w\u0001\ra!/\u0015\r\u001dErQGD\u001c)\u0011!ynb\r\t\u0011\u0011\r\u0011Q\ba\u0002\t\u000fA\u0001b!.\u0002>\u0001\u00071\u0011\u0018\u0005\t\u0007+\fi\u00041\u0001\u0004Z\nYQK\\1ss~##-\u00198h\'!\tyd!-\u0005<\u0012\u0005\u0017aC;oI\u0016\u0014H._5oO\u0002\"Ba\"\u0011\bDA!A\u0011]A \u0011!)I0!\u0012A\u0002\rEF\u0003BB]\u000f\u000fB\u0001\u0002\")\u0002z\u0001\u0007A1\u0015\u000b\u0005\u000f\u0003:Y\u0005\u0003\u0006\u0006z\u0006m\u0004\u0013!a\u0001\u0007c+\"ab\u0014+\t\rEVq\u0004\u000b\u0005\u0007W<\u0019\u0006\u0003\u0006\u0006t\u0005\r\u0015\u0011!a\u0001\tG#Baa?\bX!QQ1OAD\u0003\u0003\u0005\raa;\u0015\t\u0015ms1\f\u0005\u000b\u000bg\nI)!AA\u0002\u0011\rF\u0003BB~\u000f?B!\"b\u001d\u0002\u000e\u0006\u0005\t\u0019ABv\u0003-)f.\u0019:z?\u0012\u0012\u0017M\\4\u0011\t\u0011\u0005\u0018\u0011S\n\u0007\u0003#;9\'\",\u0011\u0011\u0015\rv\u0011NBY\u000f\u0003JAab\u001b\u0006&\n\t\u0012IY:ue\u0006\u001cGOR;oGRLwN\\\u0019\u0015\u0005\u001d\rD\u0003BD!\u000fcB\u0001\"\"?\u0002\u0018\u0002\u00071\u0011\u0017\u000b\u0005\u000fk:9\b\u0005\u0004\u0004\"\u0012e1\u0011\u0017\u0005\u000b\u000bO\fI*!AA\u0002\u001d\u0005\u0013a\u0003\"j]\u0006\u0014\u0018p\u0018\u0013b[B\u0004B\u0001\"9\u0002\\N!\u00111\\BP)\t9Y\b\u0006\u0004\u00042\u001e\ruq\u0011\u0005\t\u000f\u000b\u000by\u000e1\u0001\u00042\u0006!A.\u001a4u\u0011!9I)a8A\u0002\rE\u0016!\u0002:jO\"$(a\u0004\"j]\u0006\u0014\u0018p\u0018\u0013b[B$\u0013-\u001c9\u0014\t\u0005\u0005xq\u0012\t\u0005\tC\fi\n\u0006\u0004\b\u0014\u001eUuq\u0013\t\u0005\tC\f\t\u000f\u0003\u0005\b\u0006\u0006\u001d\b\u0019ABY\u0011!9I)a:A\u0002\rE\u0016\u0001D8qKJ\fGo\u001c:OC6,\u0017a\u0004\"j]\u0006\u0014\u0018p\u0018\u0013b[B$\u0013-\u001c9\u0011\t\u0011\u0005\u0018Q^\n\u0005\u0003[\u001cy\n\u0006\u0002\b\u001eR11\u0011WDS\u000fOC\u0001b\"\"\u0002r\u0002\u00071\u0011\u0017\u0005\t\u000f\u0013\u000b\t\u00101\u0001\u00042\nY!)\u001b8bef|FEY1s\'\u0011\t\u0019p!-\u0015\r\u001d=v\u0011WDZ!\u0011!\t/a=\t\u0011\u001d\u0015\u0015\u0011 a\u0001\u0007cC\u0001b\"#\u0002z\u0002\u00071\u0011\u0017\u000b\u0005\u0007s;9\f\u0003\u0005\u0005\"\n5\u0002\u0019\u0001CR\u0003-\u0011\u0015N\\1ss~##-\u0019:\u0011\t\u0011\u0005(\u0011G\n\u0005\u0005c\u0019y\n\u0006\u0002\b<R11\u0011WDb\u000f\u000bD\u0001b\"\"\u00036\u0001\u00071\u0011\u0017\u0005\t\u000f\u0013\u0013)\u00041\u0001\u00042\ny!)\u001b8bef|FEY1sI\t\f\'o\u0005\u0003\u00038\u001d=FCBDg\u000f\u001f<\t\u000e\u0005\u0003\u0005b\n]\u0002\u0002CDC\u0005{\u0001\ra!-\t\u0011\u001d%%Q\ba\u0001\u0007c\u000bqBQ5oCJLx\f\n2be\u0012\u0012\u0017M\u001d\t\u0005\tC\u0014\u0019e\u0005\u0003\u0003D\r}ECADk)\u0019\u0019\tl\"8\b`\"AqQ\u0011B$\u0001\u0004\u0019\t\f\u0003\u0005\b\n\n\u001d\u0003\u0019ABY\u0005\u001dIU\u000e\u001d7jKN\u001cBA!\u0013\u00042R1qq]Du\u000fW\u0004B\u0001\"9\u0003J!AqQ\u0011B(\u0001\u0004\u0019\t\f\u0003\u0005\b\n\n=\u0003\u0019ABY)\u0011\u0019Ilb<\t\u0011\u0011\u0005&\u0011\u0011a\u0001\tG\u000bq!S7qY&,7\u000f\u0005\u0003\u0005b\n\u00155\u0003\u0002BC\u0007?#\"ab=\u0015\r\rEv1`D\u007f\u0011!9)I!#A\u0002\rE\u0006\u0002CDE\u0005\u0013\u0003\ra!-\u0003\u000f%\u001bX)\u001d<U_N!!1RBY)\u0019A)\u0001c\u0002\t\nA!A\u0011\u001dBF\u0011!9)I!%A\u0002\rE\u0006\u0002CDE\u0005#\u0003\ra!-\u0015\t\re\u0006R\u0002\u0005\t\tC\u0013\u0019\r1\u0001\u0005$\u00069\u0011j]#rmR{\u0007\u0003\u0002Cq\u0005\u000f\u001cBAa2\u0004 R\u0011\u0001\u0012\u0003\u000b\u0007\u0007cCI\u0002c\u0007\t\u0011\u001d\u0015%1\u001aa\u0001\u0007cC\u0001b\"#\u0003L\u0002\u00071\u0011\u0017\u0002\f\u0019\u0006T\u00180T3tg\u0006<Wm\u0005\u0003\u0003N\u000e}EC\u0001E\u0012!\u0011!\tO!4\u0002\u00159,7\u000f^3e\u0003J<7/\u000b\u0006\u0003N\nM71AB2\u0007g\u00111BR1di6+7o]1hKNA!1\u001bE\u0012\tw#\t-\u0001\u0003gC\u000e$\u0018!\u00024bGR\u0004C\u0003\u0002E\u001a\u0011k\u0001B\u0001\"9\u0003T\"A\u0001R\u0006Bm\u0001\u0004\u0019\t,A\u0006oKN$X\rZ!sON\u0004C\u0003\u0002E\u001a\u0011wA!\u0002#\f\u0003bB\u0005\t\u0019ABY)\u0011\u0019Y\u000fc\u0010\t\u0015\u0015M$\u0011^A\u0001\u0002\u0004!\u0019\u000b\u0006\u0003\u0004|\"\r\u0003BCC:\u0005[\f\t\u00111\u0001\u0004lR!Q1\fE$\u0011))\u0019Ha<\u0002\u0002\u0003\u0007A1\u0015\u000b\u0005\u0007wDY\u0005\u0003\u0006\u0006t\tM\u0018\u0011!a\u0001\u0007W\u0014a#T5e\'\u0016tG/\u001a8dK\u001a\u000b7\r^\'fgN\fw-Z\n\t\u0007\u0007A\u0019\u0003b/\u0005BR!\u00012\u000bE+!\u0011!\toa\u0001\t\u0011!52\u0011\u0002a\u0001\u0007c#B\u0001c\u0015\tZ!Q\u0001RFB\t!\u0003\u0005\ra!-\u0015\t\r-\bR\f\u0005\u000b\u000bg\u001aI\"!AA\u0002\u0011\rF\u0003BB~\u0011CB!\"b\u001d\u0004\u001e\u0005\u0005\t\u0019ABv)\u0011)Y\u0006#\u001a\t\u0015\u0015M4qDA\u0001\u0002\u0004!\u0019\u000b\u0006\u0003\u0004|\"%\u0004BCC:\u0007G\t\t\u00111\u0001\u0004l\n\u0001S*\u001b3TK:$XM\\2f\'&l\u0007\u000f\\5gS\u0016$g)Y2u\u001b\u0016\u001c8/Y4f\'!\u0019\u0019\u0007c\t\u0005<\u0012\u0005G\u0003\u0002E9\u0011g\u0002B\u0001\"9\u0004d!A\u0001RFB5\u0001\u0004\u0019\t\f\u0006\u0003\tr!]\u0004B\u0003E\u0017\u0007c\u0002\n\u00111\u0001\u00042R!11\u001eE>\u0011))\u0019h!\u001f\u0002\u0002\u0003\u0007A1\u0015\u000b\u0005\u0007wDy\b\u0003\u0006\u0006t\ru\u0014\u0011!a\u0001\u0007W$B!b\u0017\t\u0004\"QQ1OB@\u0003\u0003\u0005\r\u0001b)\u0015\t\rm\br\u0011\u0005\u000b\u000bg\u001a\u0019)!AA\u0002\r-(!F*j[Bd\u0017NZ5fI\u001a\u000b7\r^\'fgN\fw-Z\n\t\u0007gA\u0019\u0003b/\u0005BR!\u0001r\u0012EI!\u0011!\toa\r\t\u0011!52\u0011\ba\u0001\u0007c#B\u0001c$\t\u0016\"Q\u0001RFB!!\u0003\u0005\ra!-\u0015\t\r-\b\u0012\u0014\u0005\u000b\u000bg\u001aI%!AA\u0002\u0011\rF\u0003BB~\u0011;C!\"b\u001d\u0004N\u0005\u0005\t\u0019ABv)\u0011)Y\u0006#)\t\u0015\u0015M4qJA\u0001\u0002\u0004!\u0019\u000b\u0006\u0003\u0004|\"\u0015\u0006BCC:\u0007\'\n\t\u00111\u0001\u0004l\u0006Ya)Y2u\u001b\u0016\u001c8/Y4f!\u0011!\tOa>\u0014\r\t]\bRVCW!!)\u0019k\"\u001b\u00042\"MBC\u0001EU)\u0011A\u0019\u0004c-\t\u0011!5\"Q a\u0001\u0007c#Ba\"\u001e\t8\"QQq\u001dB\u0000\u0003\u0003\u0005\r\u0001c\r\u0002-5KGmU3oi\u0016t7-\u001a$bGRlUm]:bO\u0016\u0004B\u0001\"9\u0004(M11q\u0005E`\u000b[\u0003\u0002\"b)\bj\rE\u00062\u000b\u000b\u0003\u0011w#B\u0001c\u0015\tF\"A\u0001RFB\u0017\u0001\u0004\u0019\t\f\u0006\u0003\bv!%\u0007BCCt\u0007_\t\t\u00111\u0001\tT\u0005)2+[7qY&4\u0017.\u001a3GC\u000e$X*Z:tC\u001e,\u0007\u0003\u0002Cq\u0007/\u001abaa\u0016\tR\u00165\u0006\u0003CCR\u000fS\u001a\t\fc$\u0015\u0005!5G\u0003\u0002EH\u0011/D\u0001\u0002#\f\u0004^\u0001\u00071\u0011\u0017\u000b\u0005\u000fkBY\u000e\u0003\u0006\u0006h\u000e}\u0013\u0011!a\u0001\u0011\u001f\u000b\u0001%T5e\'\u0016tG/\u001a8dKNKW\u000e\u001d7jM&,GMR1di6+7o]1hKB!A\u0011]BD\'\u0019\u00199\tc9\u0006.BAQ1UD5\u0007cC\t\b\u0006\u0002\t`R!\u0001\u0012\u000fEu\u0011!Aic!$A\u0002\rEF\u0003BD;\u0011[D!\"b:\u0004\u0010\u0006\u0005\t\u0019\u0001E9\'\u0011\tij!-\u0015\r\u001d=\u00052\u001fE{\u0011!9))a)A\u0002\rE\u0006\u0002CDE\u0003G\u0003\ra!-\u0015\t\re\u0006\u0012 \u0005\t\tC\u000b9\u000e1\u0001\u0005$\u0006!a)Y2u\u0001"
    )
BootstrapMethods:
  0: #168 REF_invokeStatic java/lang/invoke/LambdaMetafactory.altMetafactory:(Ljava/lang/invoke/MethodHandles$Lookup;Ljava/lang/String;Ljava/lang/invoke/MethodType;[Ljava/lang/Object;)Ljava/lang/invoke/CallSite;
    Method arguments:
      #152 (Ljava/lang/Object;)Ljava/lang/Object;
      #157 REF_invokeStatic org/scalatest/Fact.$anonfun$toAssertion$1:(Lorg/scalatest/Fact;Lorg/scalatest/exceptions/StackDepthException;)Lscala/Some;
      #159 (Lorg/scalatest/exceptions/StackDepthException;)Lscala/Some;
      #160 5
      #161 1
      #159 (Lorg/scalatest/exceptions/StackDepthException;)Lscala/Some;
  1: #168 REF_invokeStatic java/lang/invoke/LambdaMetafactory.altMetafactory:(Ljava/lang/invoke/MethodHandles$Lookup;Ljava/lang/String;Ljava/lang/invoke/MethodType;[Ljava/lang/Object;)Ljava/lang/invoke/CallSite;
    Method arguments:
      #152 (Ljava/lang/Object;)Ljava/lang/Object;
      #187 REF_invokeStatic org/scalatest/Fact.$anonfun$toAssertion$2:(Lorg/scalatest/Fact;Lorg/scalatest/exceptions/StackDepthException;)Lscala/Some;
      #159 (Lorg/scalatest/exceptions/StackDepthException;)Lscala/Some;
      #160 5
      #161 1
      #159 (Lorg/scalatest/exceptions/StackDepthException;)Lscala/Some;
  2: #168 REF_invokeStatic java/lang/invoke/LambdaMetafactory.altMetafactory:(Ljava/lang/invoke/MethodHandles$Lookup;Ljava/lang/String;Ljava/lang/invoke/MethodType;[Ljava/lang/Object;)Ljava/lang/invoke/CallSite;
    Method arguments:
      #152 (Ljava/lang/Object;)Ljava/lang/Object;
      #197 REF_invokeStatic org/scalatest/Fact.$anonfun$internalToAssertion$1:(Lorg/scalatest/Fact;Lorg/scalatest/exceptions/StackDepthException;)Lscala/Some;
      #159 (Lorg/scalatest/exceptions/StackDepthException;)Lscala/Some;
      #160 5
      #161 1
      #159 (Lorg/scalatest/exceptions/StackDepthException;)Lscala/Some;
  3: #168 REF_invokeStatic java/lang/invoke/LambdaMetafactory.altMetafactory:(Ljava/lang/invoke/MethodHandles$Lookup;Ljava/lang/String;Ljava/lang/invoke/MethodType;[Ljava/lang/Object;)Ljava/lang/invoke/CallSite;
    Method arguments:
      #152 (Ljava/lang/Object;)Ljava/lang/Object;
      #202 REF_invokeStatic org/scalatest/Fact.$anonfun$internalToAssertion$2:(Lorg/scalatest/Fact;Lorg/scalatest/exceptions/StackDepthException;)Lscala/Some;
      #159 (Lorg/scalatest/exceptions/StackDepthException;)Lscala/Some;
      #160 5
      #161 1
      #159 (Lorg/scalatest/exceptions/StackDepthException;)Lscala/Some;
  4: #168 REF_invokeStatic java/lang/invoke/LambdaMetafactory.altMetafactory:(Ljava/lang/invoke/MethodHandles$Lookup;Ljava/lang/String;Ljava/lang/invoke/MethodType;[Ljava/lang/Object;)Ljava/lang/invoke/CallSite;
    Method arguments:
      #152 (Ljava/lang/Object;)Ljava/lang/Object;
      #308 REF_invokeStatic org/scalatest/Fact.$anonfun$makeString$1:(Lorg/scalatest/Fact;Ljava/lang/Object;)Ljava/lang/String;
      #310 (Ljava/lang/Object;)Ljava/lang/String;
      #160 5
      #161 1
      #310 (Ljava/lang/Object;)Ljava/lang/String;
  5: #168 REF_invokeStatic java/lang/invoke/LambdaMetafactory.altMetafactory:(Ljava/lang/invoke/MethodHandles$Lookup;Ljava/lang/String;Ljava/lang/invoke/MethodType;[Ljava/lang/Object;)Ljava/lang/invoke/CallSite;
    Method arguments:
      #152 (Ljava/lang/Object;)Ljava/lang/Object;
      #404 REF_invokeStatic org/scalatest/Fact.$anonfun$factDiagram$1:(Ljava/lang/String;Ljava/lang/String;)Ljava/lang/String;
      #405 (Ljava/lang/String;)Ljava/lang/String;
      #160 5
      #161 1
      #405 (Ljava/lang/String;)Ljava/lang/String;
  6: #472 REF_invokeStatic scala/runtime/LambdaDeserialize.bootstrap:(Ljava/lang/invoke/MethodHandles$Lookup;Ljava/lang/String;Ljava/lang/invoke/MethodType;[Ljava/lang/invoke/MethodHandle;)Ljava/lang/invoke/CallSite;
    Method arguments:
      #404 REF_invokeStatic org/scalatest/Fact.$anonfun$factDiagram$1:(Ljava/lang/String;Ljava/lang/String;)Ljava/lang/String;
      #197 REF_invokeStatic org/scalatest/Fact.$anonfun$internalToAssertion$1:(Lorg/scalatest/Fact;Lorg/scalatest/exceptions/StackDepthException;)Lscala/Some;
      #202 REF_invokeStatic org/scalatest/Fact.$anonfun$internalToAssertion$2:(Lorg/scalatest/Fact;Lorg/scalatest/exceptions/StackDepthException;)Lscala/Some;
      #308 REF_invokeStatic org/scalatest/Fact.$anonfun$makeString$1:(Lorg/scalatest/Fact;Ljava/lang/Object;)Ljava/lang/String;
      #157 REF_invokeStatic org/scalatest/Fact.$anonfun$toAssertion$1:(Lorg/scalatest/Fact;Lorg/scalatest/exceptions/StackDepthException;)Lscala/Some;
      #187 REF_invokeStatic org/scalatest/Fact.$anonfun$toAssertion$2:(Lorg/scalatest/Fact;Lorg/scalatest/exceptions/StackDepthException;)Lscala/Some;
  ScalaInlineInfo: length = 0xCC (unknown attribute)
   01 00 00 28 00 EE 00 E9 01 00 E1 00 D2 01 01 90
   01 91 01 00 C2 00 9A 01 00 C7 00 9A 01 01 30 01
   31 01 00 99 00 9A 01 00 B8 00 9A 01 00 E8 00 E9
   01 00 D1 00 D2 01 00 B2 01 C5 00 00 6D 00 70 00
   00 6A 00 7F 00 01 54 01 55 00 01 0B 00 70 00 00
   74 00 75 00 00 FB 00 D2 01 00 C1 00 8B 01 01 06
   00 E9 01 00 7A 00 7B 00 00 86 00 7B 01 00 7C 00
   7B 00 00 85 00 7B 00 01 15 01 16 01 01 1E 00 70
   00 00 78 00 75 00 01 23 00 70 00 00 79 00 75 00
   00 7D 00 7E 00 00 6F 00 70 00 00 72 00 70 00 00
   73 00 70 00 00 71 00 70 00 01 19 00 70 00 00 77
   00 75 00 00 F3 00 70 01 00 8A 00 8B 01 00 89 00
   7B 01 01 A9 00 70 00 00 CC 00 CD 00
  ScalaSig: length = 0x3 (unknown attribute)
   05 02 00
