Classfile /Users/mw/Projects/slang-braindump/.jar/jar8/assemble/slang-braindump/assemble/content/org/scalatest/Fact$Binary_$bar$.class
  Last modified May 29, 2022; size 856 bytes
  SHA-256 checksum 1bdc2350f11753ba6831e4376e662dbf7d8e486ad6a975cd9862f2a7211a279a
  Compiled from "Fact.scala"
public class org.scalatest.Fact$Binary_$bar$
  minor version: 0
  major version: 52
  flags: (0x0021) ACC_PUBLIC, ACC_SUPER
  this_class: #2                          // org/scalatest/Fact$Binary_$bar$
  super_class: #4                         // java/lang/Object
  interfaces: 0, fields: 1, methods: 3, attributes: 4
Constant pool:
   #1 = Utf8               org/scalatest/Fact$Binary_$bar$
   #2 = Class              #1             // org/scalatest/Fact$Binary_$bar$
   #3 = Utf8               java/lang/Object
   #4 = Class              #3             // java/lang/Object
   #5 = Utf8               Fact.scala
   #6 = Utf8               org/scalatest/Fact$Binary_$bar
   #7 = Class              #6             // org/scalatest/Fact$Binary_$bar
   #8 = Utf8               org/scalatest/Fact
   #9 = Class              #8             // org/scalatest/Fact
  #10 = Utf8               Binary_$bar
  #11 = Utf8               Binary_$bar$
  #12 = Utf8               MODULE$
  #13 = Utf8               Lorg/scalatest/Fact$Binary_$bar$;
  #14 = Utf8               <clinit>
  #15 = Utf8               ()V
  #16 = Utf8               <init>
  #17 = NameAndType        #16:#15        // "<init>":()V
  #18 = Methodref          #2.#17         // org/scalatest/Fact$Binary_$bar$."<init>":()V
  #19 = NameAndType        #12:#13        // MODULE$:Lorg/scalatest/Fact$Binary_$bar$;
  #20 = Fieldref           #2.#19         // org/scalatest/Fact$Binary_$bar$.MODULE$:Lorg/scalatest/Fact$Binary_$bar$;
  #21 = Utf8               apply
  #22 = Utf8               (Lorg/scalatest/Fact;Lorg/scalatest/Fact;)Lorg/scalatest/Fact;
  #23 = Utf8               left
  #24 = Utf8               right
  #25 = Utf8               (Lorg/scalatest/Fact;Lorg/scalatest/Fact;)V
  #26 = NameAndType        #16:#25        // "<init>":(Lorg/scalatest/Fact;Lorg/scalatest/Fact;)V
  #27 = Methodref          #7.#26         // org/scalatest/Fact$Binary_$bar."<init>":(Lorg/scalatest/Fact;Lorg/scalatest/Fact;)V
  #28 = Utf8               this
  #29 = Utf8               Lorg/scalatest/Fact;
  #30 = Methodref          #4.#17         // java/lang/Object."<init>":()V
  #31 = Utf8               Code
  #32 = Utf8               LineNumberTable
  #33 = Utf8               LocalVariableTable
  #34 = Utf8               MethodParameters
  #35 = Utf8               InnerClasses
  #36 = Utf8               SourceFile
  #37 = Utf8               ScalaInlineInfo
  #38 = Utf8               Scala
{
  public static final org.scalatest.Fact$Binary_$bar$ MODULE$;
    descriptor: Lorg/scalatest/Fact$Binary_$bar$;
    flags: (0x0019) ACC_PUBLIC, ACC_STATIC, ACC_FINAL

  public static {};
    descriptor: ()V
    flags: (0x0009) ACC_PUBLIC, ACC_STATIC
    Code:
      stack=2, locals=0, args_size=0
         0: new           #2                  // class org/scalatest/Fact$Binary_$bar$
         3: dup
         4: invokespecial #18                 // Method "<init>":()V
         7: putstatic     #20                 // Field MODULE$:Lorg/scalatest/Fact$Binary_$bar$;
        10: return
      LineNumberTable:
        line 980: 0

  public org.scalatest.Fact apply(org.scalatest.Fact, org.scalatest.Fact);
    descriptor: (Lorg/scalatest/Fact;Lorg/scalatest/Fact;)Lorg/scalatest/Fact;
    flags: (0x0001) ACC_PUBLIC
    Code:
      stack=4, locals=3, args_size=3
         0: new           #7                  // class org/scalatest/Fact$Binary_$bar
         3: dup
         4: aload_1
         5: aload_2
         6: invokespecial #27                 // Method org/scalatest/Fact$Binary_$bar."<init>":(Lorg/scalatest/Fact;Lorg/scalatest/Fact;)V
         9: areturn
      LineNumberTable:
        line 981: 0
      LocalVariableTable:
        Start  Length  Slot  Name   Signature
            0      10     0  this   Lorg/scalatest/Fact$Binary_$bar$;
            0      10     1  left   Lorg/scalatest/Fact;
            0      10     2 right   Lorg/scalatest/Fact;
    MethodParameters:
      Name                           Flags
      left                           final
      right                          final

  public org.scalatest.Fact$Binary_$bar$();
    descriptor: ()V
    flags: (0x0001) ACC_PUBLIC
    Code:
      stack=1, locals=1, args_size=1
         0: aload_0
         1: invokespecial #30                 // Method java/lang/Object."<init>":()V
         4: return
      LineNumberTable:
        line 984: 0
        line 980: 4
      LocalVariableTable:
        Start  Length  Slot  Name   Signature
            0       5     0  this   Lorg/scalatest/Fact$Binary_$bar$;
}
InnerClasses:
  public static #10= #7 of #9;            // Binary_$bar=class org/scalatest/Fact$Binary_$bar of class org/scalatest/Fact
  public static #11= #2 of #9;            // Binary_$bar$=class org/scalatest/Fact$Binary_$bar$ of class org/scalatest/Fact
SourceFile: "Fact.scala"
  ScalaInlineInfo: length = 0xE (unknown attribute)
   01 01 00 02 00 10 00 0F 01 00 15 00 16 01
  Scala: length = 0x0 (unknown attribute)

