Classfile /Users/mw/Projects/slang-braindump/.jar/jar8/assemble/slang-braindump/assemble/content/org/scalatest/Fact$Binary_$amp.class
  Last modified May 29, 2022; size 4987 bytes
  SHA-256 checksum 04e19bbc3b0bf4e0ed220869c5123e436f6d69b83d19b21443152a2c970aca45
  Compiled from "Fact.scala"
public class org.scalatest.Fact$Binary_$amp extends org.scalatest.Fact
  minor version: 0
  major version: 52
  flags: (0x0021) ACC_PUBLIC, ACC_SUPER
  this_class: #2                          // org/scalatest/Fact$Binary_$amp
  super_class: #4                         // org/scalatest/Fact
  interfaces: 0, fields: 14, methods: 15, attributes: 4
Constant pool:
    #1 = Utf8               org/scalatest/Fact$Binary_$amp
    #2 = Class              #1            // org/scalatest/Fact$Binary_$amp
    #3 = Utf8               org/scalatest/Fact
    #4 = Class              #3            // org/scalatest/Fact
    #5 = Utf8               Fact.scala
    #6 = Utf8               Binary_$amp
    #7 = Utf8               org/scalatest/Fact$LazyMessage
    #8 = Class              #7            // org/scalatest/Fact$LazyMessage
    #9 = Utf8               LazyMessage
   #10 = Utf8               org/scalatest/Fact$MidSentenceSimplifiedFactMessage
   #11 = Class              #10           // org/scalatest/Fact$MidSentenceSimplifiedFactMessage
   #12 = Utf8               MidSentenceSimplifiedFactMessage
   #13 = Utf8               org/scalatest/Fact$SimplifiedFactMessage
   #14 = Class              #13           // org/scalatest/Fact$SimplifiedFactMessage
   #15 = Utf8               SimplifiedFactMessage
   #16 = Utf8               left
   #17 = Utf8               Lorg/scalatest/Fact;
   #18 = Utf8               right
   #19 = Utf8               rawFactMessage
   #20 = Utf8               Ljava/lang/String;
   #21 = Utf8               rawSimplifiedFactMessage
   #22 = Utf8               rawMidSentenceFactMessage
   #23 = Utf8               rawMidSentenceSimplifiedFactMessage
   #24 = Utf8               factMessageArgs
   #25 = Utf8               Lscala/collection/immutable/IndexedSeq;
   #26 = Utf8               Lscala/collection/immutable/IndexedSeq<Ljava/lang/Object;>;
   #27 = Utf8               simplifiedFactMessageArgs
   #28 = Utf8               midSentenceFactMessageArgs
   #29 = Utf8               midSentenceSimplifiedFactMessageArgs
   #30 = Utf8               isLeaf
   #31 = Utf8               Z
   #32 = Utf8               isYes
   #33 = Utf8               isVacuousYes
   #34 = Utf8               prettifier
   #35 = Utf8               Lorg/scalactic/Prettifier;
   #36 = Utf8               operatorName
   #37 = Utf8               ()Ljava/lang/String;
   #38 = Utf8               &
   #39 = String             #38           // &
   #40 = Utf8               this
   #41 = Utf8               Lorg/scalatest/Fact$Binary_$amp;
   #42 = NameAndType        #19:#20       // rawFactMessage:Ljava/lang/String;
   #43 = Fieldref           #2.#42        // org/scalatest/Fact$Binary_$amp.rawFactMessage:Ljava/lang/String;
   #44 = NameAndType        #21:#20       // rawSimplifiedFactMessage:Ljava/lang/String;
   #45 = Fieldref           #2.#44        // org/scalatest/Fact$Binary_$amp.rawSimplifiedFactMessage:Ljava/lang/String;
   #46 = NameAndType        #22:#20       // rawMidSentenceFactMessage:Ljava/lang/String;
   #47 = Fieldref           #2.#46        // org/scalatest/Fact$Binary_$amp.rawMidSentenceFactMessage:Ljava/lang/String;
   #48 = NameAndType        #23:#20       // rawMidSentenceSimplifiedFactMessage:Ljava/lang/String;
   #49 = Fieldref           #2.#48        // org/scalatest/Fact$Binary_$amp.rawMidSentenceSimplifiedFactMessage:Ljava/lang/String;
   #50 = Utf8               ()Lscala/collection/immutable/IndexedSeq;
   #51 = Utf8               ()Lscala/collection/immutable/IndexedSeq<Ljava/lang/Object;>;
   #52 = NameAndType        #24:#25       // factMessageArgs:Lscala/collection/immutable/IndexedSeq;
   #53 = Fieldref           #2.#52        // org/scalatest/Fact$Binary_$amp.factMessageArgs:Lscala/collection/immutable/IndexedSeq;
   #54 = NameAndType        #27:#25       // simplifiedFactMessageArgs:Lscala/collection/immutable/IndexedSeq;
   #55 = Fieldref           #2.#54        // org/scalatest/Fact$Binary_$amp.simplifiedFactMessageArgs:Lscala/collection/immutable/IndexedSeq;
   #56 = NameAndType        #28:#25       // midSentenceFactMessageArgs:Lscala/collection/immutable/IndexedSeq;
   #57 = Fieldref           #2.#56        // org/scalatest/Fact$Binary_$amp.midSentenceFactMessageArgs:Lscala/collection/immutable/IndexedSeq;
   #58 = NameAndType        #29:#25       // midSentenceSimplifiedFactMessageArgs:Lscala/collection/immutable/IndexedSeq;
   #59 = Fieldref           #2.#58        // org/scalatest/Fact$Binary_$amp.midSentenceSimplifiedFactMessageArgs:Lscala/collection/immutable/IndexedSeq;
   #60 = Utf8               ()Z
   #61 = NameAndType        #30:#31       // isLeaf:Z
   #62 = Fieldref           #2.#61        // org/scalatest/Fact$Binary_$amp.isLeaf:Z
   #63 = NameAndType        #32:#31       // isYes:Z
   #64 = Fieldref           #2.#63        // org/scalatest/Fact$Binary_$amp.isYes:Z
   #65 = NameAndType        #33:#31       // isVacuousYes:Z
   #66 = Fieldref           #2.#65        // org/scalatest/Fact$Binary_$amp.isVacuousYes:Z
   #67 = Utf8               ()Lorg/scalactic/Prettifier;
   #68 = NameAndType        #34:#35       // prettifier:Lorg/scalactic/Prettifier;
   #69 = Fieldref           #2.#68        // org/scalatest/Fact$Binary_$amp.prettifier:Lorg/scalactic/Prettifier;
   #70 = Utf8               factDiagram
   #71 = Utf8               (I)Ljava/lang/String;
   #72 = Utf8               level
   #73 = Utf8               scala/collection/StringOps$
   #74 = Class              #73           // scala/collection/StringOps$
   #75 = Utf8               MODULE$
   #76 = Utf8               Lscala/collection/StringOps$;
   #77 = NameAndType        #75:#76       // MODULE$:Lscala/collection/StringOps$;
   #78 = Fieldref           #74.#77       // scala/collection/StringOps$.MODULE$:Lscala/collection/StringOps$;
   #79 = Utf8               scala/Predef$
   #80 = Class              #79           // scala/Predef$
   #81 = Utf8               Lscala/Predef$;
   #82 = NameAndType        #75:#81       // MODULE$:Lscala/Predef$;
   #83 = Fieldref           #80.#82       // scala/Predef$.MODULE$:Lscala/Predef$;
   #84 = Utf8
   #85 = String             #84           //
   #86 = Utf8               augmentString
   #87 = Utf8               (Ljava/lang/String;)Ljava/lang/String;
   #88 = NameAndType        #86:#87       // augmentString:(Ljava/lang/String;)Ljava/lang/String;
   #89 = Methodref          #80.#88       // scala/Predef$.augmentString:(Ljava/lang/String;)Ljava/lang/String;
   #90 = Utf8               $times$extension
   #91 = Utf8               (Ljava/lang/String;I)Ljava/lang/String;
   #92 = NameAndType        #90:#91       // $times$extension:(Ljava/lang/String;I)Ljava/lang/String;
   #93 = Methodref          #74.#92       // scala/collection/StringOps$.$times$extension:(Ljava/lang/String;I)Ljava/lang/String;
   #94 = Utf8               java/lang/StringBuilder
   #95 = Class              #94           // java/lang/StringBuilder
   #96 = Integer            3
   #97 = Utf8               <init>
   #98 = Utf8               (I)V
   #99 = NameAndType        #97:#98       // "<init>":(I)V
  #100 = Methodref          #95.#99       // java/lang/StringBuilder."<init>":(I)V
  #101 = Utf8               append
  #102 = Utf8               (Ljava/lang/String;)Ljava/lang/StringBuilder;
  #103 = NameAndType        #101:#102     // append:(Ljava/lang/String;)Ljava/lang/StringBuilder;
  #104 = Methodref          #95.#103      // java/lang/StringBuilder.append:(Ljava/lang/String;)Ljava/lang/StringBuilder;
  #105 = Utf8               stringPrefix
  #106 = NameAndType        #105:#37      // stringPrefix:()Ljava/lang/String;
  #107 = Methodref          #2.#106       // org/scalatest/Fact$Binary_$amp.stringPrefix:()Ljava/lang/String;
  #108 = Utf8               (
  #109 = String             #108          // (
  #110 = Utf8               NEWLINE
  #111 = NameAndType        #110:#37      // NEWLINE:()Ljava/lang/String;
  #112 = Methodref          #2.#111       // org/scalatest/Fact$Binary_$amp.NEWLINE:()Ljava/lang/String;
  #113 = NameAndType        #16:#17       // left:Lorg/scalatest/Fact;
  #114 = Fieldref           #2.#113       // org/scalatest/Fact$Binary_$amp.left:Lorg/scalatest/Fact;
  #115 = NameAndType        #70:#71       // factDiagram:(I)Ljava/lang/String;
  #116 = Methodref          #4.#115       // org/scalatest/Fact.factDiagram:(I)Ljava/lang/String;
  #117 = Utf8
  #118 = String             #117          //
  #119 = NameAndType        #36:#37       // operatorName:()Ljava/lang/String;
  #120 = Methodref          #2.#119       // org/scalatest/Fact$Binary_$amp.operatorName:()Ljava/lang/String;
  #121 = NameAndType        #18:#17       // right:Lorg/scalatest/Fact;
  #122 = Fieldref           #2.#121       // org/scalatest/Fact$Binary_$amp.right:Lorg/scalatest/Fact;
  #123 = Utf8               )
  #124 = String             #123          // )
  #125 = Utf8               toString
  #126 = NameAndType        #125:#37      // toString:()Ljava/lang/String;
  #127 = Methodref          #95.#126      // java/lang/StringBuilder.toString:()Ljava/lang/String;
  #128 = Utf8               padding
  #129 = Utf8               I
  #130 = Utf8               (Lorg/scalatest/Fact;Lorg/scalatest/Fact;)V
  #131 = Utf8               ()V
  #132 = NameAndType        #97:#131      // "<init>":()V
  #133 = Methodref          #4.#132       // org/scalatest/Fact."<init>":()V
  #134 = NameAndType        #30:#60       // isLeaf:()Z
  #135 = Methodref          #4.#134       // org/scalatest/Fact.isLeaf:()Z
  #136 = NameAndType        #32:#60       // isYes:()Z
  #137 = Methodref          #4.#136       // org/scalatest/Fact.isYes:()Z
  #138 = Utf8               isNo
  #139 = NameAndType        #138:#60      // isNo:()Z
  #140 = Methodref          #4.#139       // org/scalatest/Fact.isNo:()Z
  #141 = Utf8               org/scalatest/Resources$
  #142 = Class              #141          // org/scalatest/Resources$
  #143 = Utf8               Lorg/scalatest/Resources$;
  #144 = NameAndType        #75:#143      // MODULE$:Lorg/scalatest/Resources$;
  #145 = Fieldref           #142.#144     // org/scalatest/Resources$.MODULE$:Lorg/scalatest/Resources$;
  #146 = Utf8               rawCommaBut
  #147 = NameAndType        #146:#37      // rawCommaBut:()Ljava/lang/String;
  #148 = Methodref          #142.#147     // org/scalatest/Resources$.rawCommaBut:()Ljava/lang/String;
  #149 = Utf8               rawCommaAnd
  #150 = NameAndType        #149:#37      // rawCommaAnd:()Ljava/lang/String;
  #151 = Methodref          #142.#150     // org/scalatest/Resources$.rawCommaAnd:()Ljava/lang/String;
  #152 = Methodref          #2.#115       // org/scalatest/Fact$Binary_$amp.factDiagram:(I)Ljava/lang/String;
  #153 = NameAndType        #19:#37       // rawFactMessage:()Ljava/lang/String;
  #154 = Methodref          #2.#153       // org/scalatest/Fact$Binary_$amp.rawFactMessage:()Ljava/lang/String;
  #155 = Utf8               scala/package$
  #156 = Class              #155          // scala/package$
  #157 = Utf8               Lscala/package$;
  #158 = NameAndType        #75:#157      // MODULE$:Lscala/package$;
  #159 = Fieldref           #156.#158     // scala/package$.MODULE$:Lscala/package$;
  #160 = Utf8               Vector
  #161 = Utf8               ()Lscala/collection/immutable/Vector$;
  #162 = NameAndType        #160:#161     // Vector:()Lscala/collection/immutable/Vector$;
  #163 = Methodref          #156.#162     // scala/package$.Vector:()Lscala/collection/immutable/Vector$;
  #164 = Utf8               scala/runtime/ScalaRunTime$
  #165 = Class              #164          // scala/runtime/ScalaRunTime$
  #166 = Utf8               Lscala/runtime/ScalaRunTime$;
  #167 = NameAndType        #75:#166      // MODULE$:Lscala/runtime/ScalaRunTime$;
  #168 = Fieldref           #165.#167     // scala/runtime/ScalaRunTime$.MODULE$:Lscala/runtime/ScalaRunTime$;
  #169 = Utf8               (Lorg/scalatest/Fact;)V
  #170 = NameAndType        #97:#169      // "<init>":(Lorg/scalatest/Fact;)V
  #171 = Methodref          #14.#170      // org/scalatest/Fact$SimplifiedFactMessage."<init>":(Lorg/scalatest/Fact;)V
  #172 = Methodref          #11.#170      // org/scalatest/Fact$MidSentenceSimplifiedFactMessage."<init>":(Lorg/scalatest/Fact;)V
  #173 = Utf8               [Ljava/lang/Object;
  #174 = Class              #173          // "[Ljava/lang/Object;"
  #175 = Utf8               wrapRefArray
  #176 = Utf8               ([Ljava/lang/Object;)Lscala/collection/immutable/ArraySeq;
  #177 = NameAndType        #175:#176     // wrapRefArray:([Ljava/lang/Object;)Lscala/collection/immutable/ArraySeq;
  #178 = Methodref          #165.#177     // scala/runtime/ScalaRunTime$.wrapRefArray:([Ljava/lang/Object;)Lscala/collection/immutable/ArraySeq;
  #179 = Utf8               scala/collection/immutable/Vector$
  #180 = Class              #179          // scala/collection/immutable/Vector$
  #181 = Utf8               apply
  #182 = Utf8               (Lscala/collection/immutable/Seq;)Ljava/lang/Object;
  #183 = NameAndType        #181:#182     // apply:(Lscala/collection/immutable/Seq;)Ljava/lang/Object;
  #184 = Methodref          #180.#183     // scala/collection/immutable/Vector$.apply:(Lscala/collection/immutable/Seq;)Ljava/lang/Object;
  #185 = Utf8               scala/collection/immutable/IndexedSeq
  #186 = Class              #185          // scala/collection/immutable/IndexedSeq
  #187 = Utf8               org/scalatest/UnquotedString
  #188 = Class              #187          // org/scalatest/UnquotedString
  #189 = Utf8               org/scalatest/UnquotedString$
  #190 = Class              #189          // org/scalatest/UnquotedString$
  #191 = Utf8               Lorg/scalatest/UnquotedString$;
  #192 = NameAndType        #75:#191      // MODULE$:Lorg/scalatest/UnquotedString$;
  #193 = Fieldref           #190.#192     // org/scalatest/UnquotedString$.MODULE$:Lorg/scalatest/UnquotedString$;
  #194 = Utf8               (Ljava/lang/String;)Lorg/scalatest/UnquotedString;
  #195 = NameAndType        #181:#194     // apply:(Ljava/lang/String;)Lorg/scalatest/UnquotedString;
  #196 = Methodref          #190.#195     // org/scalatest/UnquotedString$.apply:(Ljava/lang/String;)Lorg/scalatest/UnquotedString;
  #197 = NameAndType        #24:#50       // factMessageArgs:()Lscala/collection/immutable/IndexedSeq;
  #198 = Methodref          #2.#197       // org/scalatest/Fact$Binary_$amp.factMessageArgs:()Lscala/collection/immutable/IndexedSeq;
  #199 = NameAndType        #28:#50       // midSentenceFactMessageArgs:()Lscala/collection/immutable/IndexedSeq;
  #200 = Methodref          #2.#199       // org/scalatest/Fact$Binary_$amp.midSentenceFactMessageArgs:()Lscala/collection/immutable/IndexedSeq;
  #201 = Methodref          #2.#136       // org/scalatest/Fact$Binary_$amp.isYes:()Z
  #202 = NameAndType        #33:#60       // isVacuousYes:()Z
  #203 = Methodref          #4.#202       // org/scalatest/Fact.isVacuousYes:()Z
  #204 = NameAndType        #34:#67       // prettifier:()Lorg/scalactic/Prettifier;
  #205 = Methodref          #4.#204       // org/scalatest/Fact.prettifier:()Lorg/scalactic/Prettifier;
  #206 = Utf8               java/lang/String
  #207 = Class              #206          // java/lang/String
  #208 = Utf8               Signature
  #209 = Utf8               Code
  #210 = Utf8               LineNumberTable
  #211 = Utf8               LocalVariableTable
  #212 = Utf8               MethodParameters
  #213 = Utf8               StackMapTable
  #214 = Utf8               InnerClasses
  #215 = Utf8               SourceFile
  #216 = Utf8               ScalaInlineInfo
  #217 = Utf8               Scala
{
  private final org.scalatest.Fact left;
    descriptor: Lorg/scalatest/Fact;
    flags: (0x0012) ACC_PRIVATE, ACC_FINAL

  private final org.scalatest.Fact right;
    descriptor: Lorg/scalatest/Fact;
    flags: (0x0012) ACC_PRIVATE, ACC_FINAL

  private final java.lang.String rawFactMessage;
    descriptor: Ljava/lang/String;
    flags: (0x0012) ACC_PRIVATE, ACC_FINAL

  private final java.lang.String rawSimplifiedFactMessage;
    descriptor: Ljava/lang/String;
    flags: (0x0012) ACC_PRIVATE, ACC_FINAL

  private final java.lang.String rawMidSentenceFactMessage;
    descriptor: Ljava/lang/String;
    flags: (0x0012) ACC_PRIVATE, ACC_FINAL

  private final java.lang.String rawMidSentenceSimplifiedFactMessage;
    descriptor: Ljava/lang/String;
    flags: (0x0012) ACC_PRIVATE, ACC_FINAL

  private final scala.collection.immutable.IndexedSeq<java.lang.Object> factMessageArgs;
    descriptor: Lscala/collection/immutable/IndexedSeq;
    flags: (0x0012) ACC_PRIVATE, ACC_FINAL
    Signature: #26                          // Lscala/collection/immutable/IndexedSeq<Ljava/lang/Object;>;

  private final scala.collection.immutable.IndexedSeq<java.lang.Object> simplifiedFactMessageArgs;
    descriptor: Lscala/collection/immutable/IndexedSeq;
    flags: (0x0012) ACC_PRIVATE, ACC_FINAL
    Signature: #26                          // Lscala/collection/immutable/IndexedSeq<Ljava/lang/Object;>;

  private final scala.collection.immutable.IndexedSeq<java.lang.Object> midSentenceFactMessageArgs;
    descriptor: Lscala/collection/immutable/IndexedSeq;
    flags: (0x0012) ACC_PRIVATE, ACC_FINAL
    Signature: #26                          // Lscala/collection/immutable/IndexedSeq<Ljava/lang/Object;>;

  private final scala.collection.immutable.IndexedSeq<java.lang.Object> midSentenceSimplifiedFactMessageArgs;
    descriptor: Lscala/collection/immutable/IndexedSeq;
    flags: (0x0012) ACC_PRIVATE, ACC_FINAL
    Signature: #26                          // Lscala/collection/immutable/IndexedSeq<Ljava/lang/Object;>;

  private final boolean isLeaf;
    descriptor: Z
    flags: (0x0012) ACC_PRIVATE, ACC_FINAL

  private final boolean isYes;
    descriptor: Z
    flags: (0x0012) ACC_PRIVATE, ACC_FINAL

  private final boolean isVacuousYes;
    descriptor: Z
    flags: (0x0012) ACC_PRIVATE, ACC_FINAL

  private final org.scalactic.Prettifier prettifier;
    descriptor: Lorg/scalactic/Prettifier;
    flags: (0x0012) ACC_PRIVATE, ACC_FINAL

  public java.lang.String operatorName();
    descriptor: ()Ljava/lang/String;
    flags: (0x0001) ACC_PUBLIC
    Code:
      stack=1, locals=1, args_size=1
         0: ldc           #39                 // String &
         2: areturn
      LineNumberTable:
        line 866: 0
      LocalVariableTable:
        Start  Length  Slot  Name   Signature
            0       3     0  this   Lorg/scalatest/Fact$Binary_$amp;

  public java.lang.String rawFactMessage();
    descriptor: ()Ljava/lang/String;
    flags: (0x0001) ACC_PUBLIC
    Code:
      stack=1, locals=1, args_size=1
         0: aload_0
         1: getfield      #43                 // Field rawFactMessage:Ljava/lang/String;
         4: areturn
      LineNumberTable:
        line 868: 0
      LocalVariableTable:
        Start  Length  Slot  Name   Signature
            0       5     0  this   Lorg/scalatest/Fact$Binary_$amp;

  public java.lang.String rawSimplifiedFactMessage();
    descriptor: ()Ljava/lang/String;
    flags: (0x0001) ACC_PUBLIC
    Code:
      stack=1, locals=1, args_size=1
         0: aload_0
         1: getfield      #45                 // Field rawSimplifiedFactMessage:Ljava/lang/String;
         4: areturn
      LineNumberTable:
        line 877: 0
      LocalVariableTable:
        Start  Length  Slot  Name   Signature
            0       5     0  this   Lorg/scalatest/Fact$Binary_$amp;

  public java.lang.String rawMidSentenceFactMessage();
    descriptor: ()Ljava/lang/String;
    flags: (0x0001) ACC_PUBLIC
    Code:
      stack=1, locals=1, args_size=1
         0: aload_0
         1: getfield      #47                 // Field rawMidSentenceFactMessage:Ljava/lang/String;
         4: areturn
      LineNumberTable:
        line 878: 0
      LocalVariableTable:
        Start  Length  Slot  Name   Signature
            0       5     0  this   Lorg/scalatest/Fact$Binary_$amp;

  public java.lang.String rawMidSentenceSimplifiedFactMessage();
    descriptor: ()Ljava/lang/String;
    flags: (0x0001) ACC_PUBLIC
    Code:
      stack=1, locals=1, args_size=1
         0: aload_0
         1: getfield      #49                 // Field rawMidSentenceSimplifiedFactMessage:Ljava/lang/String;
         4: areturn
      LineNumberTable:
        line 879: 0
      LocalVariableTable:
        Start  Length  Slot  Name   Signature
            0       5     0  this   Lorg/scalatest/Fact$Binary_$amp;

  public scala.collection.immutable.IndexedSeq<java.lang.Object> factMessageArgs();
    descriptor: ()Lscala/collection/immutable/IndexedSeq;
    flags: (0x0001) ACC_PUBLIC
    Code:
      stack=1, locals=1, args_size=1
         0: aload_0
         1: getfield      #53                 // Field factMessageArgs:Lscala/collection/immutable/IndexedSeq;
         4: areturn
      LineNumberTable:
        line 880: 0
      LocalVariableTable:
        Start  Length  Slot  Name   Signature
            0       5     0  this   Lorg/scalatest/Fact$Binary_$amp;
    Signature: #51                          // ()Lscala/collection/immutable/IndexedSeq<Ljava/lang/Object;>;

  public scala.collection.immutable.IndexedSeq<java.lang.Object> simplifiedFactMessageArgs();
    descriptor: ()Lscala/collection/immutable/IndexedSeq;
    flags: (0x0001) ACC_PUBLIC
    Code:
      stack=1, locals=1, args_size=1
         0: aload_0
         1: getfield      #55                 // Field simplifiedFactMessageArgs:Lscala/collection/immutable/IndexedSeq;
         4: areturn
      LineNumberTable:
        line 891: 0
      LocalVariableTable:
        Start  Length  Slot  Name   Signature
            0       5     0  this   Lorg/scalatest/Fact$Binary_$amp;
    Signature: #51                          // ()Lscala/collection/immutable/IndexedSeq<Ljava/lang/Object;>;

  public scala.collection.immutable.IndexedSeq<java.lang.Object> midSentenceFactMessageArgs();
    descriptor: ()Lscala/collection/immutable/IndexedSeq;
    flags: (0x0001) ACC_PUBLIC
    Code:
      stack=1, locals=1, args_size=1
         0: aload_0
         1: getfield      #57                 // Field midSentenceFactMessageArgs:Lscala/collection/immutable/IndexedSeq;
         4: areturn
      LineNumberTable:
        line 892: 0
      LocalVariableTable:
        Start  Length  Slot  Name   Signature
            0       5     0  this   Lorg/scalatest/Fact$Binary_$amp;
    Signature: #51                          // ()Lscala/collection/immutable/IndexedSeq<Ljava/lang/Object;>;

  public scala.collection.immutable.IndexedSeq<java.lang.Object> midSentenceSimplifiedFactMessageArgs();
    descriptor: ()Lscala/collection/immutable/IndexedSeq;
    flags: (0x0001) ACC_PUBLIC
    Code:
      stack=1, locals=1, args_size=1
         0: aload_0
         1: getfield      #59                 // Field midSentenceSimplifiedFactMessageArgs:Lscala/collection/immutable/IndexedSeq;
         4: areturn
      LineNumberTable:
        line 904: 0
      LocalVariableTable:
        Start  Length  Slot  Name   Signature
            0       5     0  this   Lorg/scalatest/Fact$Binary_$amp;
    Signature: #51                          // ()Lscala/collection/immutable/IndexedSeq<Ljava/lang/Object;>;

  public boolean isLeaf();
    descriptor: ()Z
    flags: (0x0001) ACC_PUBLIC
    Code:
      stack=1, locals=1, args_size=1
         0: aload_0
         1: getfield      #62                 // Field isLeaf:Z
         4: ireturn
      LineNumberTable:
        line 906: 0
      LocalVariableTable:
        Start  Length  Slot  Name   Signature
            0       5     0  this   Lorg/scalatest/Fact$Binary_$amp;

  public boolean isYes();
    descriptor: ()Z
    flags: (0x0001) ACC_PUBLIC
    Code:
      stack=1, locals=1, args_size=1
         0: aload_0
         1: getfield      #64                 // Field isYes:Z
         4: ireturn
      LineNumberTable:
        line 907: 0
      LocalVariableTable:
        Start  Length  Slot  Name   Signature
            0       5     0  this   Lorg/scalatest/Fact$Binary_$amp;

  public boolean isVacuousYes();
    descriptor: ()Z
    flags: (0x0001) ACC_PUBLIC
    Code:
      stack=1, locals=1, args_size=1
         0: aload_0
         1: getfield      #66                 // Field isVacuousYes:Z
         4: ireturn
      LineNumberTable:
        line 908: 0
      LocalVariableTable:
        Start  Length  Slot  Name   Signature
            0       5     0  this   Lorg/scalatest/Fact$Binary_$amp;

  public org.scalactic.Prettifier prettifier();
    descriptor: ()Lorg/scalactic/Prettifier;
    flags: (0x0001) ACC_PUBLIC
    Code:
      stack=1, locals=1, args_size=1
         0: aload_0
         1: getfield      #69                 // Field prettifier:Lorg/scalactic/Prettifier;
         4: areturn
      LineNumberTable:
        line 909: 0
      LocalVariableTable:
        Start  Length  Slot  Name   Signature
            0       5     0  this   Lorg/scalatest/Fact$Binary_$amp;

  public java.lang.String factDiagram(int);
    descriptor: (I)Ljava/lang/String;
    flags: (0x0001) ACC_PUBLIC
    Code:
      stack=4, locals=3, args_size=2
         0: getstatic     #78                 // Field scala/collection/StringOps$.MODULE$:Lscala/collection/StringOps$;
         3: getstatic     #83                 // Field scala/Predef$.MODULE$:Lscala/Predef$;
         6: ldc           #85                 // String
         8: invokevirtual #89                 // Method scala/Predef$.augmentString:(Ljava/lang/String;)Ljava/lang/String;
        11: iload_1
        12: invokevirtual #93                 // Method scala/collection/StringOps$.$times$extension:(Ljava/lang/String;I)Ljava/lang/String;
        15: astore_2
        16: new           #95                 // class java/lang/StringBuilder
        19: dup
        20: ldc           #96                 // int 3
        22: invokespecial #100                // Method java/lang/StringBuilder."<init>":(I)V
        25: aload_2
        26: invokevirtual #104                // Method java/lang/StringBuilder.append:(Ljava/lang/String;)Ljava/lang/StringBuilder;
        29: aload_0
        30: invokevirtual #107                // Method stringPrefix:()Ljava/lang/String;
        33: invokevirtual #104                // Method java/lang/StringBuilder.append:(Ljava/lang/String;)Ljava/lang/StringBuilder;
        36: ldc           #109                // String (
        38: invokevirtual #104                // Method java/lang/StringBuilder.append:(Ljava/lang/String;)Ljava/lang/StringBuilder;
        41: aload_0
        42: invokevirtual #112                // Method NEWLINE:()Ljava/lang/String;
        45: invokevirtual #104                // Method java/lang/StringBuilder.append:(Ljava/lang/String;)Ljava/lang/StringBuilder;
        48: aload_0
        49: getfield      #114                // Field left:Lorg/scalatest/Fact;
        52: iload_1
        53: iconst_1
        54: iadd
        55: invokevirtual #116                // Method org/scalatest/Fact.factDiagram:(I)Ljava/lang/String;
        58: invokevirtual #104                // Method java/lang/StringBuilder.append:(Ljava/lang/String;)Ljava/lang/StringBuilder;
        61: ldc           #118                // String
        63: invokevirtual #104                // Method java/lang/StringBuilder.append:(Ljava/lang/String;)Ljava/lang/StringBuilder;
        66: aload_0
        67: invokevirtual #120                // Method operatorName:()Ljava/lang/String;
        70: invokevirtual #104                // Method java/lang/StringBuilder.append:(Ljava/lang/String;)Ljava/lang/StringBuilder;
        73: aload_0
        74: invokevirtual #112                // Method NEWLINE:()Ljava/lang/String;
        77: invokevirtual #104                // Method java/lang/StringBuilder.append:(Ljava/lang/String;)Ljava/lang/StringBuilder;
        80: aload_0
        81: getfield      #122                // Field right:Lorg/scalatest/Fact;
        84: iload_1
        85: iconst_1
        86: iadd
        87: invokevirtual #116                // Method org/scalatest/Fact.factDiagram:(I)Ljava/lang/String;
        90: invokevirtual #104                // Method java/lang/StringBuilder.append:(Ljava/lang/String;)Ljava/lang/StringBuilder;
        93: aload_0
        94: invokevirtual #112                // Method NEWLINE:()Ljava/lang/String;
        97: invokevirtual #104                // Method java/lang/StringBuilder.append:(Ljava/lang/String;)Ljava/lang/StringBuilder;
       100: aload_2
       101: invokevirtual #104                // Method java/lang/StringBuilder.append:(Ljava/lang/String;)Ljava/lang/StringBuilder;
       104: ldc           #124                // String )
       106: invokevirtual #104                // Method java/lang/StringBuilder.append:(Ljava/lang/String;)Ljava/lang/StringBuilder;
       109: invokevirtual #127                // Method java/lang/StringBuilder.toString:()Ljava/lang/String;
       112: areturn
      LineNumberTable:
        line 913: 0
        line 917: 16
        line 914: 25
        line 915: 48
        line 916: 80
        line 917: 100
      LocalVariableTable:
        Start  Length  Slot  Name   Signature
           16      96     2 padding   Ljava/lang/String;
            0     113     0  this   Lorg/scalatest/Fact$Binary_$amp;
            0     113     1 level   I
    MethodParameters:
      Name                           Flags
      level                          final

  public org.scalatest.Fact$Binary_$amp(org.scalatest.Fact, org.scalatest.Fact);
    descriptor: (Lorg/scalatest/Fact;Lorg/scalatest/Fact;)V
    flags: (0x0001) ACC_PUBLIC
    Code:
      stack=9, locals=3, args_size=3
         0: aload_0
         1: aload_1
         2: putfield      #114                // Field left:Lorg/scalatest/Fact;
         5: aload_0
         6: aload_2
         7: putfield      #122                // Field right:Lorg/scalatest/Fact;
        10: aload_0
        11: invokespecial #133                // Method org/scalatest/Fact."<init>":()V
        14: aload_0
        15: aload_1
        16: invokevirtual #135                // Method org/scalatest/Fact.isLeaf:()Z
        19: ifeq          61
        22: aload_2
        23: invokevirtual #135                // Method org/scalatest/Fact.isLeaf:()Z
        26: ifeq          61
        29: aload_1
        30: invokevirtual #137                // Method org/scalatest/Fact.isYes:()Z
        33: ifeq          52
        36: aload_2
        37: invokevirtual #140                // Method org/scalatest/Fact.isNo:()Z
        40: ifeq          52
        43: getstatic     #145                // Field org/scalatest/Resources$.MODULE$:Lorg/scalatest/Resources$;
        46: invokevirtual #148                // Method org/scalatest/Resources$.rawCommaBut:()Ljava/lang/String;
        49: goto          58
        52: getstatic     #145                // Field org/scalatest/Resources$.MODULE$:Lorg/scalatest/Resources$;
        55: invokevirtual #151                // Method org/scalatest/Resources$.rawCommaAnd:()Ljava/lang/String;
        58: goto          66
        61: aload_0
        62: iconst_0
        63: invokevirtual #152                // Method factDiagram:(I)Ljava/lang/String;
        66: putfield      #43                 // Field rawFactMessage:Ljava/lang/String;
        69: aload_0
        70: aload_0
        71: invokevirtual #154                // Method rawFactMessage:()Ljava/lang/String;
        74: putfield      #45                 // Field rawSimplifiedFactMessage:Ljava/lang/String;
        77: aload_0
        78: aload_0
        79: invokevirtual #154                // Method rawFactMessage:()Ljava/lang/String;
        82: putfield      #47                 // Field rawMidSentenceFactMessage:Ljava/lang/String;
        85: aload_0
        86: aload_0
        87: invokevirtual #154                // Method rawFactMessage:()Ljava/lang/String;
        90: putfield      #49                 // Field rawMidSentenceSimplifiedFactMessage:Ljava/lang/String;
        93: aload_0
        94: aload_1
        95: invokevirtual #135                // Method org/scalatest/Fact.isLeaf:()Z
        98: ifeq          158
       101: aload_2
       102: invokevirtual #135                // Method org/scalatest/Fact.isLeaf:()Z
       105: ifeq          158
       108: getstatic     #159                // Field scala/package$.MODULE$:Lscala/package$;
       111: invokevirtual #163                // Method scala/package$.Vector:()Lscala/collection/immutable/Vector$;
       114: getstatic     #168                // Field scala/runtime/ScalaRunTime$.MODULE$:Lscala/runtime/ScalaRunTime$;
       117: iconst_2
       118: anewarray     #8                  // class org/scalatest/Fact$LazyMessage
       121: dup
       122: iconst_0
       123: new           #14                 // class org/scalatest/Fact$SimplifiedFactMessage
       126: dup
       127: aload_1
       128: invokespecial #171                // Method org/scalatest/Fact$SimplifiedFactMessage."<init>":(Lorg/scalatest/Fact;)V
       131: aastore
       132: dup
       133: iconst_1
       134: new           #11                 // class org/scalatest/Fact$MidSentenceSimplifiedFactMessage
       137: dup
       138: aload_2
       139: invokespecial #172                // Method org/scalatest/Fact$MidSentenceSimplifiedFactMessage."<init>":(Lorg/scalatest/Fact;)V
       142: aastore
       143: checkcast     #174                // class "[Ljava/lang/Object;"
       146: invokevirtual #178                // Method scala/runtime/ScalaRunTime$.wrapRefArray:([Ljava/lang/Object;)Lscala/collection/immutable/ArraySeq;
       149: invokevirtual #184                // Method scala/collection/immutable/Vector$.apply:(Lscala/collection/immutable/Seq;)Ljava/lang/Object;
       152: checkcast     #186                // class scala/collection/immutable/IndexedSeq
       155: goto          211
       158: getstatic     #159                // Field scala/package$.MODULE$:Lscala/package$;
       161: invokevirtual #163                // Method scala/package$.Vector:()Lscala/collection/immutable/Vector$;
       164: getstatic     #168                // Field scala/runtime/ScalaRunTime$.MODULE$:Lscala/runtime/ScalaRunTime$;
       167: iconst_2
       168: anewarray     #188                // class org/scalatest/UnquotedString
       171: dup
       172: iconst_0
       173: getstatic     #193                // Field org/scalatest/UnquotedString$.MODULE$:Lorg/scalatest/UnquotedString$;
       176: aload_1
       177: iconst_0
       178: invokevirtual #116                // Method org/scalatest/Fact.factDiagram:(I)Ljava/lang/String;
       181: invokevirtual #196                // Method org/scalatest/UnquotedString$.apply:(Ljava/lang/String;)Lorg/scalatest/UnquotedString;
       184: aastore
       185: dup
       186: iconst_1
       187: getstatic     #193                // Field org/scalatest/UnquotedString$.MODULE$:Lorg/scalatest/UnquotedString$;
       190: aload_2
       191: iconst_0
       192: invokevirtual #116                // Method org/scalatest/Fact.factDiagram:(I)Ljava/lang/String;
       195: invokevirtual #196                // Method org/scalatest/UnquotedString$.apply:(Ljava/lang/String;)Lorg/scalatest/UnquotedString;
       198: aastore
       199: checkcast     #174                // class "[Ljava/lang/Object;"
       202: invokevirtual #178                // Method scala/runtime/ScalaRunTime$.wrapRefArray:([Ljava/lang/Object;)Lscala/collection/immutable/ArraySeq;
       205: invokevirtual #184                // Method scala/collection/immutable/Vector$.apply:(Lscala/collection/immutable/Seq;)Ljava/lang/Object;
       208: checkcast     #186                // class scala/collection/immutable/IndexedSeq
       211: putfield      #53                 // Field factMessageArgs:Lscala/collection/immutable/IndexedSeq;
       214: aload_0
       215: aload_0
       216: invokevirtual #198                // Method factMessageArgs:()Lscala/collection/immutable/IndexedSeq;
       219: putfield      #55                 // Field simplifiedFactMessageArgs:Lscala/collection/immutable/IndexedSeq;
       222: aload_0
       223: aload_1
       224: invokevirtual #135                // Method org/scalatest/Fact.isLeaf:()Z
       227: ifeq          287
       230: aload_2
       231: invokevirtual #135                // Method org/scalatest/Fact.isLeaf:()Z
       234: ifeq          287
       237: getstatic     #159                // Field scala/package$.MODULE$:Lscala/package$;
       240: invokevirtual #163                // Method scala/package$.Vector:()Lscala/collection/immutable/Vector$;
       243: getstatic     #168                // Field scala/runtime/ScalaRunTime$.MODULE$:Lscala/runtime/ScalaRunTime$;
       246: iconst_2
       247: anewarray     #11                 // class org/scalatest/Fact$MidSentenceSimplifiedFactMessage
       250: dup
       251: iconst_0
       252: new           #11                 // class org/scalatest/Fact$MidSentenceSimplifiedFactMessage
       255: dup
       256: aload_1
       257: invokespecial #172                // Method org/scalatest/Fact$MidSentenceSimplifiedFactMessage."<init>":(Lorg/scalatest/Fact;)V
       260: aastore
       261: dup
       262: iconst_1
       263: new           #11                 // class org/scalatest/Fact$MidSentenceSimplifiedFactMessage
       266: dup
       267: aload_2
       268: invokespecial #172                // Method org/scalatest/Fact$MidSentenceSimplifiedFactMessage."<init>":(Lorg/scalatest/Fact;)V
       271: aastore
       272: checkcast     #174                // class "[Ljava/lang/Object;"
       275: invokevirtual #178                // Method scala/runtime/ScalaRunTime$.wrapRefArray:([Ljava/lang/Object;)Lscala/collection/immutable/ArraySeq;
       278: invokevirtual #184                // Method scala/collection/immutable/Vector$.apply:(Lscala/collection/immutable/Seq;)Ljava/lang/Object;
       281: checkcast     #186                // class scala/collection/immutable/IndexedSeq
       284: goto          340
       287: getstatic     #159                // Field scala/package$.MODULE$:Lscala/package$;
       290: invokevirtual #163                // Method scala/package$.Vector:()Lscala/collection/immutable/Vector$;
       293: getstatic     #168                // Field scala/runtime/ScalaRunTime$.MODULE$:Lscala/runtime/ScalaRunTime$;
       296: iconst_2
       297: anewarray     #188                // class org/scalatest/UnquotedString
       300: dup
       301: iconst_0
       302: getstatic     #193                // Field org/scalatest/UnquotedString$.MODULE$:Lorg/scalatest/UnquotedString$;
       305: aload_1
       306: iconst_0
       307: invokevirtual #116                // Method org/scalatest/Fact.factDiagram:(I)Ljava/lang/String;
       310: invokevirtual #196                // Method org/scalatest/UnquotedString$.apply:(Ljava/lang/String;)Lorg/scalatest/UnquotedString;
       313: aastore
       314: dup
       315: iconst_1
       316: getstatic     #193                // Field org/scalatest/UnquotedString$.MODULE$:Lorg/scalatest/UnquotedString$;
       319: aload_2
       320: iconst_0
       321: invokevirtual #116                // Method org/scalatest/Fact.factDiagram:(I)Ljava/lang/String;
       324: invokevirtual #196                // Method org/scalatest/UnquotedString$.apply:(Ljava/lang/String;)Lorg/scalatest/UnquotedString;
       327: aastore
       328: checkcast     #174                // class "[Ljava/lang/Object;"
       331: invokevirtual #178                // Method scala/runtime/ScalaRunTime$.wrapRefArray:([Ljava/lang/Object;)Lscala/collection/immutable/ArraySeq;
       334: invokevirtual #184                // Method scala/collection/immutable/Vector$.apply:(Lscala/collection/immutable/Seq;)Ljava/lang/Object;
       337: checkcast     #186                // class scala/collection/immutable/IndexedSeq
       340: putfield      #57                 // Field midSentenceFactMessageArgs:Lscala/collection/immutable/IndexedSeq;
       343: aload_0
       344: aload_0
       345: invokevirtual #200                // Method midSentenceFactMessageArgs:()Lscala/collection/immutable/IndexedSeq;
       348: putfield      #59                 // Field midSentenceSimplifiedFactMessageArgs:Lscala/collection/immutable/IndexedSeq;
       351: aload_0
       352: iconst_0
       353: putfield      #62                 // Field isLeaf:Z
       356: aload_0
       357: aload_1
       358: invokevirtual #137                // Method org/scalatest/Fact.isYes:()Z
       361: ifeq          375
       364: aload_2
       365: invokevirtual #137                // Method org/scalatest/Fact.isYes:()Z
       368: ifeq          375
       371: iconst_1
       372: goto          376
       375: iconst_0
       376: putfield      #64                 // Field isYes:Z
       379: aload_0
       380: aload_0
       381: invokevirtual #201                // Method isYes:()Z
       384: ifeq          405
       387: aload_1
       388: invokevirtual #203                // Method org/scalatest/Fact.isVacuousYes:()Z
       391: ifne          401
       394: aload_2
       395: invokevirtual #203                // Method org/scalatest/Fact.isVacuousYes:()Z
       398: ifeq          405
       401: iconst_1
       402: goto          406
       405: iconst_0
       406: putfield      #66                 // Field isVacuousYes:Z
       409: aload_0
       410: aload_1
       411: invokevirtual #205                // Method org/scalatest/Fact.prettifier:()Lorg/scalactic/Prettifier;
       414: putfield      #69                 // Field prettifier:Lorg/scalactic/Prettifier;
       417: return
      StackMapTable: number_of_entries = 13
        frame_type = 255 /* full_frame */
          offset_delta = 52
          locals = [ class org/scalatest/Fact$Binary_$amp, class org/scalatest/Fact, class org/scalatest/Fact ]
          stack = [ class org/scalatest/Fact$Binary_$amp ]
        frame_type = 255 /* full_frame */
          offset_delta = 5
          locals = [ class org/scalatest/Fact$Binary_$amp, class org/scalatest/Fact, class org/scalatest/Fact ]
          stack = [ class org/scalatest/Fact$Binary_$amp, class java/lang/String ]
        frame_type = 66 /* same_locals_1_stack_item */
          stack = [ class org/scalatest/Fact$Binary_$amp ]
        frame_type = 255 /* full_frame */
          offset_delta = 4
          locals = [ class org/scalatest/Fact$Binary_$amp, class org/scalatest/Fact, class org/scalatest/Fact ]
          stack = [ class org/scalatest/Fact$Binary_$amp, class java/lang/String ]
        frame_type = 247 /* same_locals_1_stack_item_frame_extended */
          offset_delta = 91
          stack = [ class org/scalatest/Fact$Binary_$amp ]
        frame_type = 255 /* full_frame */
          offset_delta = 52
          locals = [ class org/scalatest/Fact$Binary_$amp, class org/scalatest/Fact, class org/scalatest/Fact ]
          stack = [ class org/scalatest/Fact$Binary_$amp, class scala/collection/immutable/IndexedSeq ]
        frame_type = 247 /* same_locals_1_stack_item_frame_extended */
          offset_delta = 75
          stack = [ class org/scalatest/Fact$Binary_$amp ]
        frame_type = 255 /* full_frame */
          offset_delta = 52
          locals = [ class org/scalatest/Fact$Binary_$amp, class org/scalatest/Fact, class org/scalatest/Fact ]
          stack = [ class org/scalatest/Fact$Binary_$amp, class scala/collection/immutable/IndexedSeq ]
        frame_type = 98 /* same_locals_1_stack_item */
          stack = [ class org/scalatest/Fact$Binary_$amp ]
        frame_type = 255 /* full_frame */
          offset_delta = 0
          locals = [ class org/scalatest/Fact$Binary_$amp, class org/scalatest/Fact, class org/scalatest/Fact ]
          stack = [ class org/scalatest/Fact$Binary_$amp, int ]
        frame_type = 88 /* same_locals_1_stack_item */
          stack = [ class org/scalatest/Fact$Binary_$amp ]
        frame_type = 67 /* same_locals_1_stack_item */
          stack = [ class org/scalatest/Fact$Binary_$amp ]
        frame_type = 255 /* full_frame */
          offset_delta = 0
          locals = [ class org/scalatest/Fact$Binary_$amp, class org/scalatest/Fact, class org/scalatest/Fact ]
          stack = [ class org/scalatest/Fact$Binary_$amp, int ]
      LineNumberTable:
        line 864: 0
        line 868: 14
        line 869: 15
        line 870: 29
        line 871: 43
        line 873: 52
        line 875: 61
        line 868: 66
        line 877: 69
        line 878: 77
        line 879: 85
        line 880: 93
        line 881: 94
        line 882: 108
        line 883: 123
        line 884: 134
        line 888: 158
        line 880: 211
        line 891: 214
        line 892: 222
        line 893: 223
        line 894: 237
        line 895: 252
        line 896: 263
        line 900: 287
        line 892: 340
        line 904: 343
        line 906: 351
        line 907: 356
        line 908: 379
        line 909: 409
        line 864: 417
      LocalVariableTable:
        Start  Length  Slot  Name   Signature
            0     418     0  this   Lorg/scalatest/Fact$Binary_$amp;
            0     418     1  left   Lorg/scalatest/Fact;
            0     418     2 right   Lorg/scalatest/Fact;
    MethodParameters:
      Name                           Flags
      left                           final
      right                          final
}
InnerClasses:
  public static #6= #2 of #4;             // Binary_$amp=class org/scalatest/Fact$Binary_$amp of class org/scalatest/Fact
  public static abstract #9= #8 of #4;    // LazyMessage=class org/scalatest/Fact$LazyMessage of class org/scalatest/Fact
  public static #12= #11 of #4;           // MidSentenceSimplifiedFactMessage=class org/scalatest/Fact$MidSentenceSimplifiedFactMessage of class org/scalatest/Fact
  public static #15= #14 of #4;           // SimplifiedFactMessage=class org/scalatest/Fact$SimplifiedFactMessage of class org/scalatest/Fact
SourceFile: "Fact.scala"
  ScalaInlineInfo: length = 0x4F (unknown attribute)
   01 00 00 0F 00 61 00 82 00 00 46 00 47 00 00 18
   00 32 00 00 1E 00 3C 00 00 21 00 3C 00 00 20 00
   3C 00 00 1C 00 32 00 00 1D 00 32 00 00 24 00 25
   00 00 22 00 43 00 00 13 00 25 00 00 16 00 25 00
   00 17 00 25 00 00 15 00 25 00 00 1B 00 32 00
  Scala: length = 0x0 (unknown attribute)

