Classfile /Users/mw/Projects/slang-braindump/.jar/jar8/assemble/slang-braindump/assemble/content/org/scalatest/Fact$VacuousYes.class
  Last modified May 29, 2022; size 2767 bytes
  SHA-256 checksum 82cf89d434ce708238ef73d19bf646625e1455c3fb4e0d3108cf63a83ded0849
  Compiled from "Fact.scala"
public class org.scalatest.Fact$VacuousYes extends org.scalatest.Fact
  minor version: 0
  major version: 52
  flags: (0x0021) ACC_PUBLIC, ACC_SUPER
  this_class: #2                          // org/scalatest/Fact$VacuousYes
  super_class: #4                         // org/scalatest/Fact
  interfaces: 0, fields: 13, methods: 14, attributes: 4
Constant pool:
    #1 = Utf8               org/scalatest/Fact$VacuousYes
    #2 = Class              #1            // org/scalatest/Fact$VacuousYes
    #3 = Utf8               org/scalatest/Fact
    #4 = Class              #3            // org/scalatest/Fact
    #5 = Utf8               Fact.scala
    #6 = Utf8               VacuousYes
    #7 = Utf8               rawFactMessage
    #8 = Utf8               Ljava/lang/String;
    #9 = Utf8               rawSimplifiedFactMessage
   #10 = Utf8               rawMidSentenceFactMessage
   #11 = Utf8               rawMidSentenceSimplifiedFactMessage
   #12 = Utf8               factMessageArgs
   #13 = Utf8               Lscala/collection/immutable/IndexedSeq;
   #14 = Utf8               Lscala/collection/immutable/IndexedSeq<Ljava/lang/Object;>;
   #15 = Utf8               simplifiedFactMessageArgs
   #16 = Utf8               midSentenceFactMessageArgs
   #17 = Utf8               midSentenceSimplifiedFactMessageArgs
   #18 = Utf8               isLeaf
   #19 = Utf8               Z
   #20 = Utf8               prettifier
   #21 = Utf8               Lorg/scalactic/Prettifier;
   #22 = Utf8               cause
   #23 = Utf8               Lscala/Option;
   #24 = Utf8               Lscala/Option<Ljava/lang/Throwable;>;
   #25 = Utf8               isYes
   #26 = Utf8               isVacuousYes
   #27 = Utf8               ()Ljava/lang/String;
   #28 = NameAndType        #7:#8         // rawFactMessage:Ljava/lang/String;
   #29 = Fieldref           #2.#28        // org/scalatest/Fact$VacuousYes.rawFactMessage:Ljava/lang/String;
   #30 = Utf8               this
   #31 = Utf8               Lorg/scalatest/Fact$VacuousYes;
   #32 = NameAndType        #9:#8         // rawSimplifiedFactMessage:Ljava/lang/String;
   #33 = Fieldref           #2.#32        // org/scalatest/Fact$VacuousYes.rawSimplifiedFactMessage:Ljava/lang/String;
   #34 = NameAndType        #10:#8        // rawMidSentenceFactMessage:Ljava/lang/String;
   #35 = Fieldref           #2.#34        // org/scalatest/Fact$VacuousYes.rawMidSentenceFactMessage:Ljava/lang/String;
   #36 = NameAndType        #11:#8        // rawMidSentenceSimplifiedFactMessage:Ljava/lang/String;
   #37 = Fieldref           #2.#36        // org/scalatest/Fact$VacuousYes.rawMidSentenceSimplifiedFactMessage:Ljava/lang/String;
   #38 = Utf8               ()Lscala/collection/immutable/IndexedSeq;
   #39 = Utf8               ()Lscala/collection/immutable/IndexedSeq<Ljava/lang/Object;>;
   #40 = NameAndType        #12:#13       // factMessageArgs:Lscala/collection/immutable/IndexedSeq;
   #41 = Fieldref           #2.#40        // org/scalatest/Fact$VacuousYes.factMessageArgs:Lscala/collection/immutable/IndexedSeq;
   #42 = NameAndType        #15:#13       // simplifiedFactMessageArgs:Lscala/collection/immutable/IndexedSeq;
   #43 = Fieldref           #2.#42        // org/scalatest/Fact$VacuousYes.simplifiedFactMessageArgs:Lscala/collection/immutable/IndexedSeq;
   #44 = NameAndType        #16:#13       // midSentenceFactMessageArgs:Lscala/collection/immutable/IndexedSeq;
   #45 = Fieldref           #2.#44        // org/scalatest/Fact$VacuousYes.midSentenceFactMessageArgs:Lscala/collection/immutable/IndexedSeq;
   #46 = NameAndType        #17:#13       // midSentenceSimplifiedFactMessageArgs:Lscala/collection/immutable/IndexedSeq;
   #47 = Fieldref           #2.#46        // org/scalatest/Fact$VacuousYes.midSentenceSimplifiedFactMessageArgs:Lscala/collection/immutable/IndexedSeq;
   #48 = Utf8               ()Z
   #49 = NameAndType        #18:#19       // isLeaf:Z
   #50 = Fieldref           #2.#49        // org/scalatest/Fact$VacuousYes.isLeaf:Z
   #51 = Utf8               ()Lorg/scalactic/Prettifier;
   #52 = NameAndType        #20:#21       // prettifier:Lorg/scalactic/Prettifier;
   #53 = Fieldref           #2.#52        // org/scalatest/Fact$VacuousYes.prettifier:Lorg/scalactic/Prettifier;
   #54 = Utf8               ()Lscala/Option;
   #55 = Utf8               ()Lscala/Option<Ljava/lang/Throwable;>;
   #56 = NameAndType        #22:#23       // cause:Lscala/Option;
   #57 = Fieldref           #2.#56        // org/scalatest/Fact$VacuousYes.cause:Lscala/Option;
   #58 = NameAndType        #25:#19       // isYes:Z
   #59 = Fieldref           #2.#58        // org/scalatest/Fact$VacuousYes.isYes:Z
   #60 = NameAndType        #26:#19       // isVacuousYes:Z
   #61 = Fieldref           #2.#60        // org/scalatest/Fact$VacuousYes.isVacuousYes:Z
   #62 = Utf8               <init>
   #63 = Utf8               (Lorg/scalatest/Fact;)V
   #64 = Utf8               underlying
   #65 = Utf8               ()V
   #66 = NameAndType        #62:#65       // "<init>":()V
   #67 = Methodref          #4.#66        // org/scalatest/Fact."<init>":()V
   #68 = Utf8               scala/Predef$
   #69 = Class              #68           // scala/Predef$
   #70 = Utf8               MODULE$
   #71 = Utf8               Lscala/Predef$;
   #72 = NameAndType        #70:#71       // MODULE$:Lscala/Predef$;
   #73 = Fieldref           #69.#72       // scala/Predef$.MODULE$:Lscala/Predef$;
   #74 = Utf8               isNo
   #75 = NameAndType        #74:#48       // isNo:()Z
   #76 = Methodref          #4.#75        // org/scalatest/Fact.isNo:()Z
   #77 = Utf8               require
   #78 = Utf8               (Z)V
   #79 = NameAndType        #77:#78       // require:(Z)V
   #80 = Methodref          #69.#79       // scala/Predef$.require:(Z)V
   #81 = NameAndType        #7:#27        // rawFactMessage:()Ljava/lang/String;
   #82 = Methodref          #4.#81        // org/scalatest/Fact.rawFactMessage:()Ljava/lang/String;
   #83 = NameAndType        #9:#27        // rawSimplifiedFactMessage:()Ljava/lang/String;
   #84 = Methodref          #4.#83        // org/scalatest/Fact.rawSimplifiedFactMessage:()Ljava/lang/String;
   #85 = NameAndType        #10:#27       // rawMidSentenceFactMessage:()Ljava/lang/String;
   #86 = Methodref          #4.#85        // org/scalatest/Fact.rawMidSentenceFactMessage:()Ljava/lang/String;
   #87 = NameAndType        #11:#27       // rawMidSentenceSimplifiedFactMessage:()Ljava/lang/String;
   #88 = Methodref          #4.#87        // org/scalatest/Fact.rawMidSentenceSimplifiedFactMessage:()Ljava/lang/String;
   #89 = NameAndType        #12:#38       // factMessageArgs:()Lscala/collection/immutable/IndexedSeq;
   #90 = Methodref          #4.#89        // org/scalatest/Fact.factMessageArgs:()Lscala/collection/immutable/IndexedSeq;
   #91 = NameAndType        #15:#38       // simplifiedFactMessageArgs:()Lscala/collection/immutable/IndexedSeq;
   #92 = Methodref          #4.#91        // org/scalatest/Fact.simplifiedFactMessageArgs:()Lscala/collection/immutable/IndexedSeq;
   #93 = NameAndType        #16:#38       // midSentenceFactMessageArgs:()Lscala/collection/immutable/IndexedSeq;
   #94 = Methodref          #4.#93        // org/scalatest/Fact.midSentenceFactMessageArgs:()Lscala/collection/immutable/IndexedSeq;
   #95 = NameAndType        #17:#38       // midSentenceSimplifiedFactMessageArgs:()Lscala/collection/immutable/IndexedSeq;
   #96 = Methodref          #4.#95        // org/scalatest/Fact.midSentenceSimplifiedFactMessageArgs:()Lscala/collection/immutable/IndexedSeq;
   #97 = NameAndType        #18:#48       // isLeaf:()Z
   #98 = Methodref          #4.#97        // org/scalatest/Fact.isLeaf:()Z
   #99 = NameAndType        #20:#51       // prettifier:()Lorg/scalactic/Prettifier;
  #100 = Methodref          #4.#99        // org/scalatest/Fact.prettifier:()Lorg/scalactic/Prettifier;
  #101 = NameAndType        #22:#54       // cause:()Lscala/Option;
  #102 = Methodref          #4.#101       // org/scalatest/Fact.cause:()Lscala/Option;
  #103 = Utf8               Lorg/scalatest/Fact;
  #104 = Utf8               Signature
  #105 = Utf8               Code
  #106 = Utf8               LineNumberTable
  #107 = Utf8               LocalVariableTable
  #108 = Utf8               MethodParameters
  #109 = Utf8               InnerClasses
  #110 = Utf8               SourceFile
  #111 = Utf8               ScalaInlineInfo
  #112 = Utf8               Scala
{
  private final java.lang.String rawFactMessage;
    descriptor: Ljava/lang/String;
    flags: (0x0012) ACC_PRIVATE, ACC_FINAL

  private final java.lang.String rawSimplifiedFactMessage;
    descriptor: Ljava/lang/String;
    flags: (0x0012) ACC_PRIVATE, ACC_FINAL

  private final java.lang.String rawMidSentenceFactMessage;
    descriptor: Ljava/lang/String;
    flags: (0x0012) ACC_PRIVATE, ACC_FINAL

  private final java.lang.String rawMidSentenceSimplifiedFactMessage;
    descriptor: Ljava/lang/String;
    flags: (0x0012) ACC_PRIVATE, ACC_FINAL

  private final scala.collection.immutable.IndexedSeq<java.lang.Object> factMessageArgs;
    descriptor: Lscala/collection/immutable/IndexedSeq;
    flags: (0x0012) ACC_PRIVATE, ACC_FINAL
    Signature: #14                          // Lscala/collection/immutable/IndexedSeq<Ljava/lang/Object;>;

  private final scala.collection.immutable.IndexedSeq<java.lang.Object> simplifiedFactMessageArgs;
    descriptor: Lscala/collection/immutable/IndexedSeq;
    flags: (0x0012) ACC_PRIVATE, ACC_FINAL
    Signature: #14                          // Lscala/collection/immutable/IndexedSeq<Ljava/lang/Object;>;

  private final scala.collection.immutable.IndexedSeq<java.lang.Object> midSentenceFactMessageArgs;
    descriptor: Lscala/collection/immutable/IndexedSeq;
    flags: (0x0012) ACC_PRIVATE, ACC_FINAL
    Signature: #14                          // Lscala/collection/immutable/IndexedSeq<Ljava/lang/Object;>;

  private final scala.collection.immutable.IndexedSeq<java.lang.Object> midSentenceSimplifiedFactMessageArgs;
    descriptor: Lscala/collection/immutable/IndexedSeq;
    flags: (0x0012) ACC_PRIVATE, ACC_FINAL
    Signature: #14                          // Lscala/collection/immutable/IndexedSeq<Ljava/lang/Object;>;

  private final boolean isLeaf;
    descriptor: Z
    flags: (0x0012) ACC_PRIVATE, ACC_FINAL

  private final org.scalactic.Prettifier prettifier;
    descriptor: Lorg/scalactic/Prettifier;
    flags: (0x0012) ACC_PRIVATE, ACC_FINAL

  private final scala.Option<java.lang.Throwable> cause;
    descriptor: Lscala/Option;
    flags: (0x0012) ACC_PRIVATE, ACC_FINAL
    Signature: #24                          // Lscala/Option<Ljava/lang/Throwable;>;

  private final boolean isYes;
    descriptor: Z
    flags: (0x0012) ACC_PRIVATE, ACC_FINAL

  private final boolean isVacuousYes;
    descriptor: Z
    flags: (0x0012) ACC_PRIVATE, ACC_FINAL

  public java.lang.String rawFactMessage();
    descriptor: ()Ljava/lang/String;
    flags: (0x0001) ACC_PUBLIC
    Code:
      stack=1, locals=1, args_size=1
         0: aload_0
         1: getfield      #29                 // Field rawFactMessage:Ljava/lang/String;
         4: areturn
      LineNumberTable:
        line 159: 0
      LocalVariableTable:
        Start  Length  Slot  Name   Signature
            0       5     0  this   Lorg/scalatest/Fact$VacuousYes;

  public java.lang.String rawSimplifiedFactMessage();
    descriptor: ()Ljava/lang/String;
    flags: (0x0001) ACC_PUBLIC
    Code:
      stack=1, locals=1, args_size=1
         0: aload_0
         1: getfield      #33                 // Field rawSimplifiedFactMessage:Ljava/lang/String;
         4: areturn
      LineNumberTable:
        line 160: 0
      LocalVariableTable:
        Start  Length  Slot  Name   Signature
            0       5     0  this   Lorg/scalatest/Fact$VacuousYes;

  public java.lang.String rawMidSentenceFactMessage();
    descriptor: ()Ljava/lang/String;
    flags: (0x0001) ACC_PUBLIC
    Code:
      stack=1, locals=1, args_size=1
         0: aload_0
         1: getfield      #35                 // Field rawMidSentenceFactMessage:Ljava/lang/String;
         4: areturn
      LineNumberTable:
        line 161: 0
      LocalVariableTable:
        Start  Length  Slot  Name   Signature
            0       5     0  this   Lorg/scalatest/Fact$VacuousYes;

  public java.lang.String rawMidSentenceSimplifiedFactMessage();
    descriptor: ()Ljava/lang/String;
    flags: (0x0001) ACC_PUBLIC
    Code:
      stack=1, locals=1, args_size=1
         0: aload_0
         1: getfield      #37                 // Field rawMidSentenceSimplifiedFactMessage:Ljava/lang/String;
         4: areturn
      LineNumberTable:
        line 162: 0
      LocalVariableTable:
        Start  Length  Slot  Name   Signature
            0       5     0  this   Lorg/scalatest/Fact$VacuousYes;

  public scala.collection.immutable.IndexedSeq<java.lang.Object> factMessageArgs();
    descriptor: ()Lscala/collection/immutable/IndexedSeq;
    flags: (0x0001) ACC_PUBLIC
    Code:
      stack=1, locals=1, args_size=1
         0: aload_0
         1: getfield      #41                 // Field factMessageArgs:Lscala/collection/immutable/IndexedSeq;
         4: areturn
      LineNumberTable:
        line 164: 0
      LocalVariableTable:
        Start  Length  Slot  Name   Signature
            0       5     0  this   Lorg/scalatest/Fact$VacuousYes;
    Signature: #39                          // ()Lscala/collection/immutable/IndexedSeq<Ljava/lang/Object;>;

  public scala.collection.immutable.IndexedSeq<java.lang.Object> simplifiedFactMessageArgs();
    descriptor: ()Lscala/collection/immutable/IndexedSeq;
    flags: (0x0001) ACC_PUBLIC
    Code:
      stack=1, locals=1, args_size=1
         0: aload_0
         1: getfield      #43                 // Field simplifiedFactMessageArgs:Lscala/collection/immutable/IndexedSeq;
         4: areturn
      LineNumberTable:
        line 165: 0
      LocalVariableTable:
        Start  Length  Slot  Name   Signature
            0       5     0  this   Lorg/scalatest/Fact$VacuousYes;
    Signature: #39                          // ()Lscala/collection/immutable/IndexedSeq<Ljava/lang/Object;>;

  public scala.collection.immutable.IndexedSeq<java.lang.Object> midSentenceFactMessageArgs();
    descriptor: ()Lscala/collection/immutable/IndexedSeq;
    flags: (0x0001) ACC_PUBLIC
    Code:
      stack=1, locals=1, args_size=1
         0: aload_0
         1: getfield      #45                 // Field midSentenceFactMessageArgs:Lscala/collection/immutable/IndexedSeq;
         4: areturn
      LineNumberTable:
        line 166: 0
      LocalVariableTable:
        Start  Length  Slot  Name   Signature
            0       5     0  this   Lorg/scalatest/Fact$VacuousYes;
    Signature: #39                          // ()Lscala/collection/immutable/IndexedSeq<Ljava/lang/Object;>;

  public scala.collection.immutable.IndexedSeq<java.lang.Object> midSentenceSimplifiedFactMessageArgs();
    descriptor: ()Lscala/collection/immutable/IndexedSeq;
    flags: (0x0001) ACC_PUBLIC
    Code:
      stack=1, locals=1, args_size=1
         0: aload_0
         1: getfield      #47                 // Field midSentenceSimplifiedFactMessageArgs:Lscala/collection/immutable/IndexedSeq;
         4: areturn
      LineNumberTable:
        line 167: 0
      LocalVariableTable:
        Start  Length  Slot  Name   Signature
            0       5     0  this   Lorg/scalatest/Fact$VacuousYes;
    Signature: #39                          // ()Lscala/collection/immutable/IndexedSeq<Ljava/lang/Object;>;

  public boolean isLeaf();
    descriptor: ()Z
    flags: (0x0001) ACC_PUBLIC
    Code:
      stack=1, locals=1, args_size=1
         0: aload_0
         1: getfield      #50                 // Field isLeaf:Z
         4: ireturn
      LineNumberTable:
        line 169: 0
      LocalVariableTable:
        Start  Length  Slot  Name   Signature
            0       5     0  this   Lorg/scalatest/Fact$VacuousYes;

  public org.scalactic.Prettifier prettifier();
    descriptor: ()Lorg/scalactic/Prettifier;
    flags: (0x0001) ACC_PUBLIC
    Code:
      stack=1, locals=1, args_size=1
         0: aload_0
         1: getfield      #53                 // Field prettifier:Lorg/scalactic/Prettifier;
         4: areturn
      LineNumberTable:
        line 170: 0
      LocalVariableTable:
        Start  Length  Slot  Name   Signature
            0       5     0  this   Lorg/scalatest/Fact$VacuousYes;

  public scala.Option<java.lang.Throwable> cause();
    descriptor: ()Lscala/Option;
    flags: (0x0001) ACC_PUBLIC
    Code:
      stack=1, locals=1, args_size=1
         0: aload_0
         1: getfield      #57                 // Field cause:Lscala/Option;
         4: areturn
      LineNumberTable:
        line 172: 0
      LocalVariableTable:
        Start  Length  Slot  Name   Signature
            0       5     0  this   Lorg/scalatest/Fact$VacuousYes;
    Signature: #55                          // ()Lscala/Option<Ljava/lang/Throwable;>;

  public boolean isYes();
    descriptor: ()Z
    flags: (0x0001) ACC_PUBLIC
    Code:
      stack=1, locals=1, args_size=1
         0: aload_0
         1: getfield      #59                 // Field isYes:Z
         4: ireturn
      LineNumberTable:
        line 174: 0
      LocalVariableTable:
        Start  Length  Slot  Name   Signature
            0       5     0  this   Lorg/scalatest/Fact$VacuousYes;

  public boolean isVacuousYes();
    descriptor: ()Z
    flags: (0x0001) ACC_PUBLIC
    Code:
      stack=1, locals=1, args_size=1
         0: aload_0
         1: getfield      #61                 // Field isVacuousYes:Z
         4: ireturn
      LineNumberTable:
        line 175: 0
      LocalVariableTable:
        Start  Length  Slot  Name   Signature
            0       5     0  this   Lorg/scalatest/Fact$VacuousYes;

  public org.scalatest.Fact$VacuousYes(org.scalatest.Fact);
    descriptor: (Lorg/scalatest/Fact;)V
    flags: (0x0001) ACC_PUBLIC
    Code:
      stack=2, locals=2, args_size=2
         0: aload_0
         1: invokespecial #67                 // Method org/scalatest/Fact."<init>":()V
         4: getstatic     #73                 // Field scala/Predef$.MODULE$:Lscala/Predef$;
         7: aload_1
         8: invokevirtual #76                 // Method org/scalatest/Fact.isNo:()Z
        11: invokevirtual #80                 // Method scala/Predef$.require:(Z)V
        14: aload_0
        15: aload_1
        16: invokevirtual #82                 // Method org/scalatest/Fact.rawFactMessage:()Ljava/lang/String;
        19: putfield      #29                 // Field rawFactMessage:Ljava/lang/String;
        22: aload_0
        23: aload_1
        24: invokevirtual #84                 // Method org/scalatest/Fact.rawSimplifiedFactMessage:()Ljava/lang/String;
        27: putfield      #33                 // Field rawSimplifiedFactMessage:Ljava/lang/String;
        30: aload_0
        31: aload_1
        32: invokevirtual #86                 // Method org/scalatest/Fact.rawMidSentenceFactMessage:()Ljava/lang/String;
        35: putfield      #35                 // Field rawMidSentenceFactMessage:Ljava/lang/String;
        38: aload_0
        39: aload_1
        40: invokevirtual #88                 // Method org/scalatest/Fact.rawMidSentenceSimplifiedFactMessage:()Ljava/lang/String;
        43: putfield      #37                 // Field rawMidSentenceSimplifiedFactMessage:Ljava/lang/String;
        46: aload_0
        47: aload_1
        48: invokevirtual #90                 // Method org/scalatest/Fact.factMessageArgs:()Lscala/collection/immutable/IndexedSeq;
        51: putfield      #41                 // Field factMessageArgs:Lscala/collection/immutable/IndexedSeq;
        54: aload_0
        55: aload_1
        56: invokevirtual #92                 // Method org/scalatest/Fact.simplifiedFactMessageArgs:()Lscala/collection/immutable/IndexedSeq;
        59: putfield      #43                 // Field simplifiedFactMessageArgs:Lscala/collection/immutable/IndexedSeq;
        62: aload_0
        63: aload_1
        64: invokevirtual #94                 // Method org/scalatest/Fact.midSentenceFactMessageArgs:()Lscala/collection/immutable/IndexedSeq;
        67: putfield      #45                 // Field midSentenceFactMessageArgs:Lscala/collection/immutable/IndexedSeq;
        70: aload_0
        71: aload_1
        72: invokevirtual #96                 // Method org/scalatest/Fact.midSentenceSimplifiedFactMessageArgs:()Lscala/collection/immutable/IndexedSeq;
        75: putfield      #47                 // Field midSentenceSimplifiedFactMessageArgs:Lscala/collection/immutable/IndexedSeq;
        78: aload_0
        79: aload_1
        80: invokevirtual #98                 // Method org/scalatest/Fact.isLeaf:()Z
        83: putfield      #50                 // Field isLeaf:Z
        86: aload_0
        87: aload_1
        88: invokevirtual #100                // Method org/scalatest/Fact.prettifier:()Lorg/scalactic/Prettifier;
        91: putfield      #53                 // Field prettifier:Lorg/scalactic/Prettifier;
        94: aload_0
        95: aload_1
        96: invokevirtual #102                // Method org/scalatest/Fact.cause:()Lscala/Option;
        99: putfield      #57                 // Field cause:Lscala/Option;
       102: aload_0
       103: iconst_1
       104: putfield      #59                 // Field isYes:Z
       107: aload_0
       108: iconst_1
       109: putfield      #61                 // Field isVacuousYes:Z
       112: return
      LineNumberTable:
        line 155: 0
        line 157: 4
        line 159: 14
        line 160: 22
        line 161: 30
        line 162: 38
        line 164: 46
        line 165: 54
        line 166: 62
        line 167: 70
        line 169: 78
        line 170: 86
        line 172: 94
        line 174: 102
        line 175: 107
        line 155: 112
      LocalVariableTable:
        Start  Length  Slot  Name   Signature
            0     113     0  this   Lorg/scalatest/Fact$VacuousYes;
            0     113     1 underlying   Lorg/scalatest/Fact;
    MethodParameters:
      Name                           Flags
      underlying                     final
}
InnerClasses:
  public static #6= #2 of #4;             // VacuousYes=class org/scalatest/Fact$VacuousYes of class org/scalatest/Fact
SourceFile: "Fact.scala"
  ScalaInlineInfo: length = 0x4A (unknown attribute)
   01 00 00 0E 00 3E 00 3F 00 00 16 00 36 00 00 0C
   00 26 00 00 12 00 30 00 00 1A 00 30 00 00 19 00
   30 00 00 10 00 26 00 00 11 00 26 00 00 14 00 33
   00 00 07 00 1B 00 00 0A 00 1B 00 00 0B 00 1B 00
   00 09 00 1B 00 00 0F 00 26 00
  Scala: length = 0x0 (unknown attribute)

