Classfile /Users/mw/Projects/slang-braindump/.jar/jar8/assemble/slang-braindump/assemble/content/org/scalatest/FailedStatus$.class
  Last modified May 29, 2022; size 2479 bytes
  SHA-256 checksum e4906c3a7dfbff354b90b2410b4a33b0a44733dcfdea1fdf8bfaa3e694a4f460
  Compiled from "Status.scala"
public final class org.scalatest.FailedStatus$ implements org.scalatest.Status,java.io.Serializable
  minor version: 0
  major version: 52
  flags: (0x0031) ACC_PUBLIC, ACC_FINAL, ACC_SUPER
  this_class: #2                          // org/scalatest/FailedStatus$
  super_class: #4                         // java/lang/Object
  interfaces: 2, fields: 1, methods: 11, attributes: 3
Constant pool:
   #1 = Utf8               org/scalatest/FailedStatus$
   #2 = Class              #1             // org/scalatest/FailedStatus$
   #3 = Utf8               java/lang/Object
   #4 = Class              #3             // java/lang/Object
   #5 = Utf8               org/scalatest/Status
   #6 = Class              #5             // org/scalatest/Status
   #7 = Utf8               java/io/Serializable
   #8 = Class              #7             // java/io/Serializable
   #9 = Utf8               Status.scala
  #10 = Utf8               MODULE$
  #11 = Utf8               Lorg/scalatest/FailedStatus$;
  #12 = Utf8               <clinit>
  #13 = Utf8               ()V
  #14 = Utf8               <init>
  #15 = NameAndType        #14:#13        // "<init>":()V
  #16 = Methodref          #2.#15         // org/scalatest/FailedStatus$."<init>":()V
  #17 = NameAndType        #10:#11        // MODULE$:Lorg/scalatest/FailedStatus$;
  #18 = Fieldref           #2.#17         // org/scalatest/FailedStatus$.MODULE$:Lorg/scalatest/FailedStatus$;
  #19 = Utf8               $init$
  #20 = Utf8               (Lorg/scalatest/Status;)V
  #21 = NameAndType        #19:#20        // $init$:(Lorg/scalatest/Status;)V
  #22 = InterfaceMethodref #6.#21         // org/scalatest/Status.$init$:(Lorg/scalatest/Status;)V
  #23 = Utf8               thenRun
  #24 = Utf8               (Lscala/Function0;)Lorg/scalatest/Status;
  #25 = Utf8               (Lscala/Function0<Lorg/scalatest/Status;>;)Lorg/scalatest/Status;
  #26 = Utf8               f
  #27 = Utf8               thenRun$
  #28 = Utf8               (Lorg/scalatest/Status;Lscala/Function0;)Lorg/scalatest/Status;
  #29 = NameAndType        #27:#28        // thenRun$:(Lorg/scalatest/Status;Lscala/Function0;)Lorg/scalatest/Status;
  #30 = InterfaceMethodref #6.#29         // org/scalatest/Status.thenRun$:(Lorg/scalatest/Status;Lscala/Function0;)Lorg/scalatest/Status;
  #31 = Utf8               this
  #32 = Utf8               Lscala/Function0;
  #33 = Utf8               toFuture
  #34 = Utf8               ()Lscala/concurrent/Future;
  #35 = Utf8               ()Lscala/concurrent/Future<Ljava/lang/Object;>;
  #36 = Utf8               toFuture$
  #37 = Utf8               (Lorg/scalatest/Status;)Lscala/concurrent/Future;
  #38 = NameAndType        #36:#37        // toFuture$:(Lorg/scalatest/Status;)Lscala/concurrent/Future;
  #39 = InterfaceMethodref #6.#38         // org/scalatest/Status.toFuture$:(Lorg/scalatest/Status;)Lscala/concurrent/Future;
  #40 = Utf8               unreportedException
  #41 = Utf8               ()Lscala/Option;
  #42 = Utf8               ()Lscala/Option<Ljava/lang/Throwable;>;
  #43 = Utf8               unreportedException$
  #44 = Utf8               (Lorg/scalatest/Status;)Lscala/Option;
  #45 = NameAndType        #43:#44        // unreportedException$:(Lorg/scalatest/Status;)Lscala/Option;
  #46 = InterfaceMethodref #6.#45         // org/scalatest/Status.unreportedException$:(Lorg/scalatest/Status;)Lscala/Option;
  #47 = Utf8               withAfterEffect
  #48 = Utf8               (Lscala/Function0<Lscala/runtime/BoxedUnit;>;)Lorg/scalatest/Status;
  #49 = Utf8               withAfterEffect$
  #50 = NameAndType        #49:#28        // withAfterEffect$:(Lorg/scalatest/Status;Lscala/Function0;)Lorg/scalatest/Status;
  #51 = InterfaceMethodref #6.#50         // org/scalatest/Status.withAfterEffect$:(Lorg/scalatest/Status;Lscala/Function0;)Lorg/scalatest/Status;
  #52 = Utf8               succeeds
  #53 = Utf8               ()Z
  #54 = Utf8               isCompleted
  #55 = Utf8               waitUntilCompleted
  #56 = Utf8               whenCompleted
  #57 = Utf8               (Lscala/Function1;)V
  #58 = Utf8               (Lscala/Function1<Lscala/util/Try<Ljava/lang/Object;>;Lscala/runtime/BoxedUnit;>;)V
  #59 = Utf8               scala/util/Success
  #60 = Class              #59            // scala/util/Success
  #61 = Utf8               scala/runtime/BoxesRunTime
  #62 = Class              #61            // scala/runtime/BoxesRunTime
  #63 = Utf8               boxToBoolean
  #64 = Utf8               (Z)Ljava/lang/Boolean;
  #65 = NameAndType        #63:#64        // boxToBoolean:(Z)Ljava/lang/Boolean;
  #66 = Methodref          #62.#65        // scala/runtime/BoxesRunTime.boxToBoolean:(Z)Ljava/lang/Boolean;
  #67 = Utf8               (Ljava/lang/Object;)V
  #68 = NameAndType        #14:#67        // "<init>":(Ljava/lang/Object;)V
  #69 = Methodref          #60.#68        // scala/util/Success."<init>":(Ljava/lang/Object;)V
  #70 = Utf8               scala/Function1
  #71 = Class              #70            // scala/Function1
  #72 = Utf8               apply
  #73 = Utf8               (Ljava/lang/Object;)Ljava/lang/Object;
  #74 = NameAndType        #72:#73        // apply:(Ljava/lang/Object;)Ljava/lang/Object;
  #75 = InterfaceMethodref #71.#74        // scala/Function1.apply:(Ljava/lang/Object;)Ljava/lang/Object;
  #76 = Utf8               Lscala/Function1;
  #77 = Utf8               writeReplace
  #78 = Utf8               ()Ljava/lang/Object;
  #79 = Utf8               scala/runtime/ModuleSerializationProxy
  #80 = Class              #79            // scala/runtime/ModuleSerializationProxy
  #81 = Utf8               (Ljava/lang/Class;)V
  #82 = NameAndType        #14:#81        // "<init>":(Ljava/lang/Class;)V
  #83 = Methodref          #80.#82        // scala/runtime/ModuleSerializationProxy."<init>":(Ljava/lang/Class;)V
  #84 = Methodref          #4.#15         // java/lang/Object."<init>":()V
  #85 = Utf8               Code
  #86 = Utf8               LineNumberTable
  #87 = Utf8               LocalVariableTable
  #88 = Utf8               Signature
  #89 = Utf8               MethodParameters
  #90 = Utf8               SourceFile
  #91 = Utf8               ScalaInlineInfo
  #92 = Utf8               Scala
{
  public static final org.scalatest.FailedStatus$ MODULE$;
    descriptor: Lorg/scalatest/FailedStatus$;
    flags: (0x0019) ACC_PUBLIC, ACC_STATIC, ACC_FINAL

  public static {};
    descriptor: ()V
    flags: (0x0009) ACC_PUBLIC, ACC_STATIC
    Code:
      stack=2, locals=0, args_size=0
         0: new           #2                  // class org/scalatest/FailedStatus$
         3: dup
         4: invokespecial #16                 // Method "<init>":()V
         7: putstatic     #18                 // Field MODULE$:Lorg/scalatest/FailedStatus$;
        10: getstatic     #18                 // Field MODULE$:Lorg/scalatest/FailedStatus$;
        13: invokestatic  #22                 // InterfaceMethod org/scalatest/Status.$init$:(Lorg/scalatest/Status;)V
        16: return
      LineNumberTable:
        line 477: 0

  public final org.scalatest.Status thenRun(scala.Function0<org.scalatest.Status>);
    descriptor: (Lscala/Function0;)Lorg/scalatest/Status;
    flags: (0x0011) ACC_PUBLIC, ACC_FINAL
    Code:
      stack=2, locals=2, args_size=2
         0: aload_0
         1: aload_1
         2: invokestatic  #30                 // InterfaceMethod org/scalatest/Status.thenRun$:(Lorg/scalatest/Status;Lscala/Function0;)Lorg/scalatest/Status;
         5: areturn
      LineNumberTable:
        line 477: 0
      LocalVariableTable:
        Start  Length  Slot  Name   Signature
            0       6     0  this   Lorg/scalatest/FailedStatus$;
            0       6     1     f   Lscala/Function0;
    Signature: #25                          // (Lscala/Function0<Lorg/scalatest/Status;>;)Lorg/scalatest/Status;
    MethodParameters:
      Name                           Flags
      f                              final

  public final scala.concurrent.Future<java.lang.Object> toFuture();
    descriptor: ()Lscala/concurrent/Future;
    flags: (0x0011) ACC_PUBLIC, ACC_FINAL
    Code:
      stack=1, locals=1, args_size=1
         0: aload_0
         1: invokestatic  #39                 // InterfaceMethod org/scalatest/Status.toFuture$:(Lorg/scalatest/Status;)Lscala/concurrent/Future;
         4: areturn
      LineNumberTable:
        line 477: 0
      LocalVariableTable:
        Start  Length  Slot  Name   Signature
            0       5     0  this   Lorg/scalatest/FailedStatus$;
    Signature: #35                          // ()Lscala/concurrent/Future<Ljava/lang/Object;>;

  public scala.Option<java.lang.Throwable> unreportedException();
    descriptor: ()Lscala/Option;
    flags: (0x0001) ACC_PUBLIC
    Code:
      stack=1, locals=1, args_size=1
         0: aload_0
         1: invokestatic  #46                 // InterfaceMethod org/scalatest/Status.unreportedException$:(Lorg/scalatest/Status;)Lscala/Option;
         4: areturn
      LineNumberTable:
        line 477: 0
      LocalVariableTable:
        Start  Length  Slot  Name   Signature
            0       5     0  this   Lorg/scalatest/FailedStatus$;
    Signature: #42                          // ()Lscala/Option<Ljava/lang/Throwable;>;

  public final org.scalatest.Status withAfterEffect(scala.Function0<scala.runtime.BoxedUnit>);
    descriptor: (Lscala/Function0;)Lorg/scalatest/Status;
    flags: (0x0011) ACC_PUBLIC, ACC_FINAL
    Code:
      stack=2, locals=2, args_size=2
         0: aload_0
         1: aload_1
         2: invokestatic  #51                 // InterfaceMethod org/scalatest/Status.withAfterEffect$:(Lorg/scalatest/Status;Lscala/Function0;)Lorg/scalatest/Status;
         5: areturn
      LineNumberTable:
        line 477: 0
      LocalVariableTable:
        Start  Length  Slot  Name   Signature
            0       6     0  this   Lorg/scalatest/FailedStatus$;
            0       6     1     f   Lscala/Function0;
    Signature: #48                          // (Lscala/Function0<Lscala/runtime/BoxedUnit;>;)Lorg/scalatest/Status;
    MethodParameters:
      Name                           Flags
      f                              final

  public boolean succeeds();
    descriptor: ()Z
    flags: (0x0001) ACC_PUBLIC
    Code:
      stack=1, locals=1, args_size=1
         0: iconst_0
         1: ireturn
      LineNumberTable:
        line 485: 0
      LocalVariableTable:
        Start  Length  Slot  Name   Signature
            0       2     0  this   Lorg/scalatest/FailedStatus$;

  public boolean isCompleted();
    descriptor: ()Z
    flags: (0x0001) ACC_PUBLIC
    Code:
      stack=1, locals=1, args_size=1
         0: iconst_1
         1: ireturn
      LineNumberTable:
        line 493: 0
      LocalVariableTable:
        Start  Length  Slot  Name   Signature
            0       2     0  this   Lorg/scalatest/FailedStatus$;

  public void waitUntilCompleted();
    descriptor: ()V
    flags: (0x0001) ACC_PUBLIC
    Code:
      stack=0, locals=1, args_size=1
         0: return
      LineNumberTable:
        line 499: 0
      LocalVariableTable:
        Start  Length  Slot  Name   Signature
            0       1     0  this   Lorg/scalatest/FailedStatus$;

  public void whenCompleted(scala.Function1<scala.util.Try<java.lang.Object>, scala.runtime.BoxedUnit>);
    descriptor: (Lscala/Function1;)V
    flags: (0x0001) ACC_PUBLIC
    Code:
      stack=4, locals=2, args_size=2
         0: aload_1
         1: new           #60                 // class scala/util/Success
         4: dup
         5: iconst_0
         6: invokestatic  #66                 // Method scala/runtime/BoxesRunTime.boxToBoolean:(Z)Ljava/lang/Boolean;
         9: invokespecial #69                 // Method scala/util/Success."<init>":(Ljava/lang/Object;)V
        12: invokeinterface #75,  2           // InterfaceMethod scala/Function1.apply:(Ljava/lang/Object;)Ljava/lang/Object;
        17: pop
        18: return
      LineNumberTable:
        line 505: 0
      LocalVariableTable:
        Start  Length  Slot  Name   Signature
            0      19     0  this   Lorg/scalatest/FailedStatus$;
            0      19     1     f   Lscala/Function1;
    Signature: #58                          // (Lscala/Function1<Lscala/util/Try<Ljava/lang/Object;>;Lscala/runtime/BoxedUnit;>;)V
    MethodParameters:
      Name                           Flags
      f                              final

  private java.lang.Object writeReplace();
    descriptor: ()Ljava/lang/Object;
    flags: (0x0002) ACC_PRIVATE
    Code:
      stack=3, locals=1, args_size=1
         0: new           #80                 // class scala/runtime/ModuleSerializationProxy
         3: dup
         4: ldc           #2                  // class org/scalatest/FailedStatus$
         6: invokespecial #83                 // Method scala/runtime/ModuleSerializationProxy."<init>":(Ljava/lang/Class;)V
         9: areturn
      LineNumberTable:
        line 477: 0
      LocalVariableTable:
        Start  Length  Slot  Name   Signature
            0      10     0  this   Lorg/scalatest/FailedStatus$;

  private org.scalatest.FailedStatus$();
    descriptor: ()V
    flags: (0x0002) ACC_PRIVATE
    Code:
      stack=1, locals=1, args_size=1
         0: aload_0
         1: invokespecial #84                 // Method java/lang/Object."<init>":()V
         4: return
      LineNumberTable:
        line 477: 0
      LocalVariableTable:
        Start  Length  Slot  Name   Signature
            0       5     0  this   Lorg/scalatest/FailedStatus$;
}
SourceFile: "Status.scala"
  ScalaInlineInfo: length = 0x36 (unknown attribute)
   01 01 00 0A 00 0E 00 0D 01 00 36 00 35 01 00 34
   00 35 01 00 17 00 18 01 00 21 00 22 01 00 28 00
   29 01 00 37 00 0D 01 00 38 00 39 01 00 2F 00 18
   01 00 4D 00 4E 01
  Scala: length = 0x0 (unknown attribute)

