Classfile /Users/mw/Projects/slang-braindump/.jar/jar8/assemble/slang-braindump/assemble/content/org/scalatest/Filter.class
  Last modified May 29, 2022; size 20410 bytes
  SHA-256 checksum 07867f41d8ef51f98ce93f084f059af276714272cc1de17a3634575a98e150e3
  Compiled from "Filter.scala"
public final class org.scalatest.Filter implements java.io.Serializable
  minor version: 0
  major version: 52
  flags: (0x0031) ACC_PUBLIC, ACC_FINAL, ACC_SUPER
  this_class: #2                          // org/scalatest/Filter
  super_class: #4                         // java/lang/Object
  interfaces: 1, fields: 4, methods: 42, attributes: 6
Constant pool:
    #1 = Utf8               org/scalatest/Filter
    #2 = Class              #1            // org/scalatest/Filter
    #3 = Utf8               java/lang/Object
    #4 = Class              #3            // java/lang/Object
    #5 = Utf8               java/io/Serializable
    #6 = Class              #5            // java/io/Serializable
    #7 = Utf8               Filter.scala
    #8 = Utf8               Lscala/reflect/ScalaSignature;
    #9 = Utf8               bytes
   #10 = Utf8               \u0006\u0005\u0005Ue\u0001B\u000f\u001f\u0005\rB\u0001B\u000e\u0001\u0003\u0006\u0004%\ta\u000e\u0005\t\r\u0002\u0011\t\u0011)A\u0005q!Aq\t\u0001BC\u0002\u0013\u0005\u0001\n\u0003\u0005J\u0001\t\u0005\t\u0015!\u0003<\u0011!Q\u0005A!b\u0001\n\u0003Y\u0005\u0002C(\u0001\u0005\u0003\u0005\u000b\u0011\u0002\'\t\u0011A\u0003!Q1A\u0005\u0002EC\u0001B\u0016\u0001\u0003\u0002\u0003\u0006IA\u0015\u0005\u0006/\u0002!I\u0001\u0017\u0005\u0006=\u0002!Ia\u0018\u0005\u0006U\u0002!Ia\u001b\u0005\u0006e\u0002!Ia\u001d\u0005\u0007o\u0002!\tA\b=\t\u000bu\u0004A\u0011\u0001@\t\ru\u0004A\u0011AA\u0007\u0011\u001d\tI\u0002\u0001C\u0001\u000379q!a\u000b\u001f\u0011\u0003\tiC\u0002\u0004\u001e=!\u0005\u0011q\u0006\u0005\u0007/J!\t!a\u0010\t\u0013\u0005\u0005#C1A\u0005\u000e\u0005\r\u0003\u0002CA&%\u0001\u0006i!!\u0012\t\ru\u0014B\u0011AA\'\u0011%\t9FEI\u0001\n\u0003\tI\u0006C\u0005\u0002pI\t\n\u0011\"\u0001\u0002r!I\u0011Q\u000f\n\u0012\u0002\u0013\u0005\u0011q\u000f\u0005\n\u0003w\u0012\u0012\u0013!C\u0001\u0003{Bq!!!\u0013\t\u0003\t\u0019\tC\u0005\u0002\u0006J\t\t\u0011\"\u0003\u0002\b\n1a)\u001b7uKJT!a\b\u0011\u0002\u0013M\u001c\u0017\r\\1uKN$(\"A\u0011\u0002\u0007=\u0014xm\u0001\u0001\u0014\u0007\u0001!#\u0006\u0005\u0002&Q5\taEC\u0001(\u0003\u0015\u00198-\u00197b\u0013\tIcE\u0001\u0004B]f\u0014VM\u001a\t\u0003WMr!\u0001L\u0019\u000f\u00055\u0002T\"\u0001\u0018\u000b\u0005=\u0012\u0013A\u0002\u001fs_>$h(C\u0001(\u0013\t\u0011d%A\u0004qC\u000e\\\u0017mZ3\n\u0005Q*$\u0001D*fe&\fG.\u001b>bE2,\'B\u0001\u001a\'\u00035!\u0018mZ:U_&s7\r\\;eKV\t\u0001\bE\u0002&smJ!A\u000f\u0014\u0003\r=\u0003H/[8o!\ra\u0004i\u0011\b\u0003{y\u0002\"!\f\u0014\n\u0005}2\u0013A\u0002)sK\u0012,g-\u0003\u0002B\u0005\n\u00191+\u001a;\u000b\u0005}2\u0003C\u0001\u001fE\u0013\t)%I\u0001\u0004TiJLgnZ\u0001\u000fi\u0006<7\u000fV8J]\u000edW\u000fZ3!\u00035!\u0018mZ:U_\u0016C8\r\\;eKV\t1(\u0001\buC\u001e\u001cHk\\#yG2,H-\u001a\u0011\u0002\'\u0015D8\r\\;eK:+7\u000f^3e\'VLG/Z:\u0016\u00031\u0003\"!J\'\n\u000593#a\u0002\"p_2,\u0017M\\\u0001\u0015Kb\u001cG.\u001e3f\u001d\u0016\u001cH/\u001a3Tk&$Xm\u001d\u0011\u0002\u0011\u0011Lh.\u0019+bON,\u0012A\u0015\t\u0003\'Rk\u0011AH\u0005\u0003+z\u0011\u0001\u0002R=oCR\u000bwm]\u0001\nIft\u0017\rV1hg\u0002\na\u0001P5oSRtD#B-[7rk\u0006CA*\u0001\u0011\u00151\u0014\u00021\u00019\u0011\u00159\u0015\u00021\u0001<\u0011\u0015Q\u0015\u00021\u0001M\u0011\u0015\u0001\u0016\u00021\u0001S\u0003EIgn\u00197vI\u0016$G+Z:u\u001d\u0006lWm\u001d\u000b\u0004A\u000e,\u0007cA\u0016b\u0007&\u0011!-\u000e\u0002\u0005\u0019&\u001cH\u000fC\u0003e\u0015\u0001\u0007\u0001-A\buKN$h*Y7fg\u0006\u001bH*[:u\u0011\u00151\'\u00021\u0001h\u0003\u0011!\u0018mZ:\u0011\tqB7iO\u0005\u0003S\n\u00131!T1q\u0003u1XM]5gsB\u0013XmY8oI&$\u0018n\u001c8t\r>\u0014X*\u001a;i_\u0012\u001cHc\u00017pcB\u0011Q%\\\u0005\u0003]\u001a\u0012A!\u00168ji\")\u0001o\u0003a\u0001w\u0005IA/Z:u\u001d\u0006lWm\u001d\u0005\u0006M.\u0001\raZ\u0001\u000e[\u0016\u0014x-\u001a+fgR$\u0016mZ:\u0015\u0005\u001d$\b\"B;\r\u0001\u00041\u0018\u0001\u0004;fgR$\u0016mZ:MSN$\bcA\u0016bO\u0006!R.\u001a:hKR+7\u000f\u001e#z]\u0006l\u0017n\u0019+bON$BaZ={y\")a-\u0004a\u0001O\")10\u0004a\u0001\u0007\u000691/^5uK&#\u0007\"\u00029\u000e\u0001\u0004Y\u0014!B1qa2LHcB@\u0002\b\u0005%\u00111\u0002\t\u0005W\u0005\f\t\u0001E\u0003&\u0003\u0007\u0019E*C\u0002\u0002\u0006\u0019\u0012a\u0001V;qY\u0016\u0014\u0004\"\u00029\u000f\u0001\u0004Y\u0004\"\u00024\u000f\u0001\u00049\u0007\"B>\u000f\u0001\u0004\u0019E\u0003CA\b\u0003#\t)\"a\u0006\u0011\u000b\u0015\n\u0019\u0001\u0014\'\t\r\u0005Mq\u00021\u0001D\u0003!!Xm\u001d;OC6,\u0007\"\u00024\u0010\u0001\u00049\u0007\"B>\u0010\u0001\u0004\u0019\u0015!\u0005:v]:\f\'\r\\3UKN$8i\\;oiRA\u0011QDA\u0012\u0003K\tI\u0003E\u0002&\u0003?I1!!\t\'\u0005\rIe\u000e\u001e\u0005\u0006aB\u0001\ra\u000f\u0005\u0007\u0003O\u0001\u0002\u0019A4\u0002\u0011Q,7\u000f\u001e+bONDQa\u001f\tA\u0002\r\u000baAR5mi\u0016\u0014\bCA*\u0013\'\u0011\u0011B%!\r\u0011\t\u0005M\u0012QH\u0007\u0003\u0003kQA!a\u000e\u0002:\u0005\u0011\u0011n\u001c\u0006\u0003\u0003w\tAA[1wC&\u0019A\'!\u000e\u0015\u0005\u00055\u0012!C%h]>\u0014X\rV1h+\t\t)e\u0004\u0002\u0002H\u0005\u0012\u0011\u0011J\u0001\u0015_J<gf]2bY\u0006$Xm\u001d;/\u0013\u001etwN]3\u0002\u0015%;gn\u001c:f)\u0006<\u0007\u0005F\u0005Z\u0003\u001f\n\t&a\u0015\u0002V!9aG\u0006I\u0001\u0002\u0004A\u0004bB$\u0017!\u0003\u0005\ra\u000f\u0005\b\u0015Z\u0001\n\u00111\u0001M\u0011\u001d\u0001f\u0003%AA\u0002I\u000bq\"\u00199qYf$C-\u001a4bk2$H%M\u000b\u0003\u00037R3\u0001OA/W\t\ty\u0006\u0005\u0003\u0002b\u0005-TBAA2\u0015\u0011\t)\'a\u001a\u0002\u0013Ut7\r[3dW\u0016$\'bAA5M\u0005Q\u0011M\u001c8pi\u0006$\u0018n\u001c8\n\t\u00055\u00141\r\u0002\u0012k:\u001c\u0007.Z2lK\u00124\u0016M]5b]\u000e,\u0017aD1qa2LH\u0005Z3gCVdG\u000f\n\u001a\u0016\u0005\u0005M$fA\u001e\u0002^\u0005y\u0011\r\u001d9ms\u0012\"WMZ1vYR$3\'\u0006\u0002\u0002z)\u001aA*!\u0018\u0002\u001f\u0005\u0004\b\u000f\\=%I\u00164\u0017-\u001e7uIQ*\"!a +\u0007I\u000bi&A\u0004eK\u001a\fW\u000f\u001c;\u0016\u0003e\u000bAb\u001e:ji\u0016\u0014V\r\u001d7bG\u0016$\"!!#\u0011\t\u0005-\u0015\u0011S\u0007\u0003\u0003\u001bSA!a$\u0002:\u0005!A.\u00198h\u0013\u0011\t\u0019*!$\u0003\r=\u0013\'.Z2u\u0001
   #11 = Utf8               java/lang/invoke/MethodHandles$Lookup
   #12 = Class              #11           // java/lang/invoke/MethodHandles$Lookup
   #13 = Utf8               java/lang/invoke/MethodHandles
   #14 = Class              #13           // java/lang/invoke/MethodHandles
   #15 = Utf8               Lookup
   #16 = Utf8               org/scalactic/Requirements$RequirementsHelper
   #17 = Class              #16           // org/scalactic/Requirements$RequirementsHelper
   #18 = Utf8               org/scalactic/Requirements
   #19 = Class              #18           // org/scalactic/Requirements
   #20 = Utf8               RequirementsHelper
   #21 = Utf8               scala/collection/MapOps$WithFilter
   #22 = Class              #21           // scala/collection/MapOps$WithFilter
   #23 = Utf8               scala/collection/MapOps
   #24 = Class              #23           // scala/collection/MapOps
   #25 = Utf8               WithFilter
   #26 = Utf8               tagsToInclude
   #27 = Utf8               Lscala/Option;
   #28 = Utf8               Lscala/Option<Lscala/collection/immutable/Set<Ljava/lang/String;>;>;
   #29 = Utf8               tagsToExclude
   #30 = Utf8               Lscala/collection/immutable/Set;
   #31 = Utf8               Lscala/collection/immutable/Set<Ljava/lang/String;>;
   #32 = Utf8               excludeNestedSuites
   #33 = Utf8               Z
   #34 = Utf8               dynaTags
   #35 = Utf8               Lorg/scalatest/DynaTags;
   #36 = Utf8               default
   #37 = Utf8               ()Lorg/scalatest/Filter;
   #38 = Utf8               org/scalatest/Filter$
   #39 = Class              #38           // org/scalatest/Filter$
   #40 = Utf8               MODULE$
   #41 = Utf8               Lorg/scalatest/Filter$;
   #42 = NameAndType        #40:#41       // MODULE$:Lorg/scalatest/Filter$;
   #43 = Fieldref           #39.#42       // org/scalatest/Filter$.MODULE$:Lorg/scalatest/Filter$;
   #44 = NameAndType        #36:#37       // default:()Lorg/scalatest/Filter;
   #45 = Methodref          #39.#44       // org/scalatest/Filter$.default:()Lorg/scalatest/Filter;
   #46 = Utf8               apply$default$4
   #47 = Utf8               ()Lorg/scalatest/DynaTags;
   #48 = NameAndType        #46:#47       // apply$default$4:()Lorg/scalatest/DynaTags;
   #49 = Methodref          #39.#48       // org/scalatest/Filter$.apply$default$4:()Lorg/scalatest/DynaTags;
   #50 = Utf8               apply$default$3
   #51 = Utf8               ()Z
   #52 = NameAndType        #50:#51       // apply$default$3:()Z
   #53 = Methodref          #39.#52       // org/scalatest/Filter$.apply$default$3:()Z
   #54 = Utf8               apply$default$2
   #55 = Utf8               ()Lscala/collection/immutable/Set;
   #56 = Utf8               ()Lscala/collection/immutable/Set<Ljava/lang/String;>;
   #57 = NameAndType        #54:#55       // apply$default$2:()Lscala/collection/immutable/Set;
   #58 = Methodref          #39.#57       // org/scalatest/Filter$.apply$default$2:()Lscala/collection/immutable/Set;
   #59 = Utf8               apply$default$1
   #60 = Utf8               ()Lscala/Option;
   #61 = Utf8               ()Lscala/Option<Lscala/collection/immutable/Set<Ljava/lang/String;>;>;
   #62 = NameAndType        #59:#60       // apply$default$1:()Lscala/Option;
   #63 = Methodref          #39.#62       // org/scalatest/Filter$.apply$default$1:()Lscala/Option;
   #64 = NameAndType        #26:#27       // tagsToInclude:Lscala/Option;
   #65 = Fieldref           #2.#64        // org/scalatest/Filter.tagsToInclude:Lscala/Option;
   #66 = Utf8               this
   #67 = Utf8               Lorg/scalatest/Filter;
   #68 = NameAndType        #29:#30       // tagsToExclude:Lscala/collection/immutable/Set;
   #69 = Fieldref           #2.#68        // org/scalatest/Filter.tagsToExclude:Lscala/collection/immutable/Set;
   #70 = NameAndType        #32:#33       // excludeNestedSuites:Z
   #71 = Fieldref           #2.#70        // org/scalatest/Filter.excludeNestedSuites:Z
   #72 = NameAndType        #34:#35       // dynaTags:Lorg/scalatest/DynaTags;
   #73 = Fieldref           #2.#72        // org/scalatest/Filter.dynaTags:Lorg/scalatest/DynaTags;
   #74 = Utf8               includedTestNames
   #75 = Utf8               (Lscala/collection/immutable/List;Lscala/collection/immutable/Map;)Lscala/collection/immutable/List;
   #76 = Utf8               (Lscala/collection/immutable/List<Ljava/lang/String;>;Lscala/collection/immutable/Map<Ljava/lang/String;Lscala/collection/immutable/Set<Ljava/lang/String;>;>;)Lscala/collection/immutable/List<Ljava/lang/String;>;
   #77 = Utf8               testNamesAsList
   #78 = Utf8               tags
   #79 = NameAndType        #26:#60       // tagsToInclude:()Lscala/Option;
   #80 = Methodref          #2.#79        // org/scalatest/Filter.tagsToInclude:()Lscala/Option;
   #81 = Utf8               scala/None$
   #82 = Class              #81           // scala/None$
   #83 = Utf8               Lscala/None$;
   #84 = NameAndType        #40:#83       // MODULE$:Lscala/None$;
   #85 = Fieldref           #82.#84       // scala/None$.MODULE$:Lscala/None$;
   #86 = Utf8               equals
   #87 = Utf8               (Ljava/lang/Object;)Z
   #88 = NameAndType        #86:#87       // equals:(Ljava/lang/Object;)Z
   #89 = Methodref          #4.#88        // java/lang/Object.equals:(Ljava/lang/Object;)Z
   #90 = Utf8               scala/Some
   #91 = Class              #90           // scala/Some
   #92 = Utf8               value
   #93 = Utf8               ()Ljava/lang/Object;
   #94 = NameAndType        #92:#93       // value:()Ljava/lang/Object;
   #95 = Methodref          #91.#94       // scala/Some.value:()Ljava/lang/Object;
   #96 = Utf8               scala/collection/immutable/Set
   #97 = Class              #96           // scala/collection/immutable/Set
   #98 = Utf8               (Ljava/lang/Object;)Ljava/lang/Object;
   #99 = MethodType         #98           //  (Ljava/lang/Object;)Ljava/lang/Object;
  #100 = Utf8               $anonfun$includedTestNames$1$adapted
  #101 = Utf8               (Lscala/collection/immutable/Map;Ljava/lang/String;)Ljava/lang/Object;
  #102 = NameAndType        #100:#101     // $anonfun$includedTestNames$1$adapted:(Lscala/collection/immutable/Map;Ljava/lang/String;)Ljava/lang/Object;
  #103 = Methodref          #2.#102       // org/scalatest/Filter.$anonfun$includedTestNames$1$adapted:(Lscala/collection/immutable/Map;Ljava/lang/String;)Ljava/lang/Object;
  #104 = MethodHandle       6:#103        // REF_invokeStatic org/scalatest/Filter.$anonfun$includedTestNames$1$adapted:(Lscala/collection/immutable/Map;Ljava/lang/String;)Ljava/lang/Object;
  #105 = Utf8               (Ljava/lang/String;)Ljava/lang/Object;
  #106 = MethodType         #105          //  (Ljava/lang/String;)Ljava/lang/Object;
  #107 = Integer            5
  #108 = Integer            1
  #109 = Utf8               java/lang/invoke/LambdaMetafactory
  #110 = Class              #109          // java/lang/invoke/LambdaMetafactory
  #111 = Utf8               altMetafactory
  #112 = Utf8               (Ljava/lang/invoke/MethodHandles$Lookup;Ljava/lang/String;Ljava/lang/invoke/MethodType;[Ljava/lang/Object;)Ljava/lang/invoke/CallSite;
  #113 = NameAndType        #111:#112     // altMetafactory:(Ljava/lang/invoke/MethodHandles$Lookup;Ljava/lang/String;Ljava/lang/invoke/MethodType;[Ljava/lang/Object;)Ljava/lang/invoke/CallSite;
  #114 = Methodref          #110.#113     // java/lang/invoke/LambdaMetafactory.altMetafactory:(Ljava/lang/invoke/MethodHandles$Lookup;Ljava/lang/String;Ljava/lang/invoke/MethodType;[Ljava/lang/Object;)Ljava/lang/invoke/CallSite;
  #115 = MethodHandle       6:#114        // REF_invokeStatic java/lang/invoke/LambdaMetafactory.altMetafactory:(Ljava/lang/invoke/MethodHandles$Lookup;Ljava/lang/String;Ljava/lang/invoke/MethodType;[Ljava/lang/Object;)Ljava/lang/invoke/CallSite;
  #116 = Utf8               apply
  #117 = Utf8               (Lscala/collection/immutable/Map;)Lscala/Function1;
  #118 = NameAndType        #116:#117     // apply:(Lscala/collection/immutable/Map;)Lscala/Function1;
  #119 = InvokeDynamic      #0:#118       // #0:apply:(Lscala/collection/immutable/Map;)Lscala/Function1;
  #120 = Utf8               scala/collection/immutable/List
  #121 = Class              #120          // scala/collection/immutable/List
  #122 = Utf8               withFilter
  #123 = Utf8               (Lscala/Function1;)Lscala/collection/WithFilter;
  #124 = NameAndType        #122:#123     // withFilter:(Lscala/Function1;)Lscala/collection/WithFilter;
  #125 = Methodref          #121.#124     // scala/collection/immutable/List.withFilter:(Lscala/Function1;)Lscala/collection/WithFilter;
  #126 = Utf8               $anonfun$includedTestNames$2
  #127 = Utf8               (Lscala/collection/immutable/Set;Lscala/collection/immutable/Map;Ljava/lang/String;)Lscala/Tuple2;
  #128 = NameAndType        #126:#127     // $anonfun$includedTestNames$2:(Lscala/collection/immutable/Set;Lscala/collection/immutable/Map;Ljava/lang/String;)Lscala/Tuple2;
  #129 = Methodref          #2.#128       // org/scalatest/Filter.$anonfun$includedTestNames$2:(Lscala/collection/immutable/Set;Lscala/collection/immutable/Map;Ljava/lang/String;)Lscala/Tuple2;
  #130 = MethodHandle       6:#129        // REF_invokeStatic org/scalatest/Filter.$anonfun$includedTestNames$2:(Lscala/collection/immutable/Set;Lscala/collection/immutable/Map;Ljava/lang/String;)Lscala/Tuple2;
  #131 = Utf8               (Ljava/lang/String;)Lscala/Tuple2;
  #132 = MethodType         #131          //  (Ljava/lang/String;)Lscala/Tuple2;
  #133 = Utf8               (Lscala/collection/immutable/Set;Lscala/collection/immutable/Map;)Lscala/Function1;
  #134 = NameAndType        #116:#133     // apply:(Lscala/collection/immutable/Set;Lscala/collection/immutable/Map;)Lscala/Function1;
  #135 = InvokeDynamic      #1:#134       // #1:apply:(Lscala/collection/immutable/Set;Lscala/collection/immutable/Map;)Lscala/Function1;
  #136 = Utf8               scala/collection/WithFilter
  #137 = Class              #136          // scala/collection/WithFilter
  #138 = Utf8               map
  #139 = Utf8               (Lscala/Function1;)Ljava/lang/Object;
  #140 = NameAndType        #138:#139     // map:(Lscala/Function1;)Ljava/lang/Object;
  #141 = Methodref          #137.#140     // scala/collection/WithFilter.map:(Lscala/Function1;)Ljava/lang/Object;
  #142 = Utf8               scala/collection/IterableOps
  #143 = Class              #142          // scala/collection/IterableOps
  #144 = Utf8               $anonfun$includedTestNames$3$adapted
  #145 = Utf8               (Lscala/Tuple2;)Ljava/lang/Object;
  #146 = NameAndType        #144:#145     // $anonfun$includedTestNames$3$adapted:(Lscala/Tuple2;)Ljava/lang/Object;
  #147 = Methodref          #2.#146       // org/scalatest/Filter.$anonfun$includedTestNames$3$adapted:(Lscala/Tuple2;)Ljava/lang/Object;
  #148 = MethodHandle       6:#147        // REF_invokeStatic org/scalatest/Filter.$anonfun$includedTestNames$3$adapted:(Lscala/Tuple2;)Ljava/lang/Object;
  #149 = MethodType         #145          //  (Lscala/Tuple2;)Ljava/lang/Object;
  #150 = Utf8               ()Lscala/Function1;
  #151 = NameAndType        #116:#150     // apply:()Lscala/Function1;
  #152 = InvokeDynamic      #2:#151       // #2:apply:()Lscala/Function1;
  #153 = InterfaceMethodref #143.#124     // scala/collection/IterableOps.withFilter:(Lscala/Function1;)Lscala/collection/WithFilter;
  #154 = Utf8               $anonfun$includedTestNames$4
  #155 = Utf8               (Lscala/Tuple2;)Ljava/lang/String;
  #156 = NameAndType        #154:#155     // $anonfun$includedTestNames$4:(Lscala/Tuple2;)Ljava/lang/String;
  #157 = Methodref          #2.#156       // org/scalatest/Filter.$anonfun$includedTestNames$4:(Lscala/Tuple2;)Ljava/lang/String;
  #158 = MethodHandle       6:#157        // REF_invokeStatic org/scalatest/Filter.$anonfun$includedTestNames$4:(Lscala/Tuple2;)Ljava/lang/String;
  #159 = MethodType         #155          //  (Lscala/Tuple2;)Ljava/lang/String;
  #160 = InvokeDynamic      #3:#151       // #3:apply:()Lscala/Function1;
  #161 = Utf8               scala/MatchError
  #162 = Class              #161          // scala/MatchError
  #163 = Utf8               <init>
  #164 = Utf8               (Ljava/lang/Object;)V
  #165 = NameAndType        #163:#164     // "<init>":(Ljava/lang/Object;)V
  #166 = Methodref          #162.#165     // scala/MatchError."<init>":(Ljava/lang/Object;)V
  #167 = Utf8               Lscala/collection/immutable/List;
  #168 = Utf8               Lscala/collection/immutable/Map;
  #169 = Utf8               scala/Option
  #170 = Class              #169          // scala/Option
  #171 = Utf8               scala/collection/immutable/Map
  #172 = Class              #171          // scala/collection/immutable/Map
  #173 = Utf8               verifyPreconditionsForMethods
  #174 = Utf8               (Lscala/collection/immutable/Set;Lscala/collection/immutable/Map;)V
  #175 = Utf8               (Lscala/collection/immutable/Set<Ljava/lang/String;>;Lscala/collection/immutable/Map<Ljava/lang/String;Lscala/collection/immutable/Set<Ljava/lang/String;>;>;)V
  #176 = Utf8               testNames
  #177 = Utf8               $anonfun$verifyPreconditionsForMethods$1$adapted
  #178 = NameAndType        #177:#145     // $anonfun$verifyPreconditionsForMethods$1$adapted:(Lscala/Tuple2;)Ljava/lang/Object;
  #179 = Methodref          #2.#178       // org/scalatest/Filter.$anonfun$verifyPreconditionsForMethods$1$adapted:(Lscala/Tuple2;)Ljava/lang/Object;
  #180 = MethodHandle       6:#179        // REF_invokeStatic org/scalatest/Filter.$anonfun$verifyPreconditionsForMethods$1$adapted:(Lscala/Tuple2;)Ljava/lang/Object;
  #181 = InvokeDynamic      #4:#151       // #4:apply:()Lscala/Function1;
  #182 = Utf8               find
  #183 = Utf8               (Lscala/Function1;)Lscala/Option;
  #184 = NameAndType        #182:#183     // find:(Lscala/Function1;)Lscala/Option;
  #185 = InterfaceMethodref #172.#184     // scala/collection/immutable/Map.find:(Lscala/Function1;)Lscala/Option;
  #186 = Utf8               scala/Tuple2
  #187 = Class              #186          // scala/Tuple2
  #188 = Utf8               _1
  #189 = NameAndType        #188:#93      // _1:()Ljava/lang/Object;
  #190 = Methodref          #187.#189     // scala/Tuple2._1:()Ljava/lang/Object;
  #191 = Utf8               java/lang/String
  #192 = Class              #191          // java/lang/String
  #193 = Utf8               java/lang/IllegalArgumentException
  #194 = Class              #193          // java/lang/IllegalArgumentException
  #195 = Utf8               java/lang/StringBuilder
  #196 = Class              #195          // java/lang/StringBuilder
  #197 = Integer            60
  #198 = Utf8               (I)V
  #199 = NameAndType        #163:#198     // "<init>":(I)V
  #200 = Methodref          #196.#199     // java/lang/StringBuilder."<init>":(I)V
  #201 = Utf8               append
  #202 = Utf8               (Ljava/lang/String;)Ljava/lang/StringBuilder;
  #203 = NameAndType        #201:#202     // append:(Ljava/lang/String;)Ljava/lang/StringBuilder;
  #204 = Methodref          #196.#203     // java/lang/StringBuilder.append:(Ljava/lang/String;)Ljava/lang/StringBuilder;
  #205 = Utf8                was associated with an empty set in the map passsed as tags
  #206 = String             #205          //  was associated with an empty set in the map passsed as tags
  #207 = Utf8               toString
  #208 = Utf8               ()Ljava/lang/String;
  #209 = NameAndType        #207:#208     // toString:()Ljava/lang/String;
  #210 = Methodref          #196.#209     // java/lang/StringBuilder.toString:()Ljava/lang/String;
  #211 = Utf8               (Ljava/lang/String;)V
  #212 = NameAndType        #163:#211     // "<init>":(Ljava/lang/String;)V
  #213 = Methodref          #194.#212     // java/lang/IllegalArgumentException."<init>":(Ljava/lang/String;)V
  #214 = Utf8               scala/runtime/BoxedUnit
  #215 = Class              #214          // scala/runtime/BoxedUnit
  #216 = Utf8               UNIT
  #217 = Utf8               Lscala/runtime/BoxedUnit;
  #218 = NameAndType        #216:#217     // UNIT:Lscala/runtime/BoxedUnit;
  #219 = Fieldref           #215.#218     // scala/runtime/BoxedUnit.UNIT:Lscala/runtime/BoxedUnit;
  #220 = Utf8               testName
  #221 = Utf8               Ljava/lang/String;
  #222 = Utf8               testWithEmptyTagSet
  #223 = Utf8               mergeTestTags
  #224 = Utf8               (Lscala/collection/immutable/List;)Lscala/collection/immutable/Map;
  #225 = Utf8               (Lscala/collection/immutable/List<Lscala/collection/immutable/Map<Ljava/lang/String;Lscala/collection/immutable/Set<Ljava/lang/String;>;>;>;)Lscala/collection/immutable/Map<Ljava/lang/String;Lscala/collection/immutable/Set<Ljava/lang/String;>;>;
  #226 = Utf8               testTagsList
  #227 = Utf8               scala/collection/mutable/Map$
  #228 = Class              #227          // scala/collection/mutable/Map$
  #229 = Utf8               Lscala/collection/mutable/Map$;
  #230 = NameAndType        #40:#229      // MODULE$:Lscala/collection/mutable/Map$;
  #231 = Fieldref           #228.#230     // scala/collection/mutable/Map$.MODULE$:Lscala/collection/mutable/Map$;
  #232 = Utf8               scala/collection/immutable/Nil$
  #233 = Class              #232          // scala/collection/immutable/Nil$
  #234 = Utf8               Lscala/collection/immutable/Nil$;
  #235 = NameAndType        #40:#234      // MODULE$:Lscala/collection/immutable/Nil$;
  #236 = Fieldref           #233.#235     // scala/collection/immutable/Nil$.MODULE$:Lscala/collection/immutable/Nil$;
  #237 = Utf8               (Lscala/collection/immutable/Seq;)Ljava/lang/Object;
  #238 = NameAndType        #116:#237     // apply:(Lscala/collection/immutable/Seq;)Ljava/lang/Object;
  #239 = Methodref          #228.#238     // scala/collection/mutable/Map$.apply:(Lscala/collection/immutable/Seq;)Ljava/lang/Object;
  #240 = Utf8               head
  #241 = NameAndType        #240:#93      // head:()Ljava/lang/Object;
  #242 = Methodref          #121.#241     // scala/collection/immutable/List.head:()Ljava/lang/Object;
  #243 = Utf8               scala/collection/IterableOnce
  #244 = Class              #243          // scala/collection/IterableOnce
  #245 = Utf8               $plus$plus
  #246 = Utf8               (Lscala/collection/IterableOnce;)Lscala/collection/IterableOps;
  #247 = NameAndType        #245:#246     // $plus$plus:(Lscala/collection/IterableOnce;)Lscala/collection/IterableOps;
  #248 = InterfaceMethodref #24.#247      // scala/collection/MapOps.$plus$plus:(Lscala/collection/IterableOnce;)Lscala/collection/IterableOps;
  #249 = Utf8               scala/collection/mutable/Map
  #250 = Class              #249          // scala/collection/mutable/Map
  #251 = Utf8               tail
  #252 = NameAndType        #251:#93      // tail:()Ljava/lang/Object;
  #253 = Methodref          #121.#252     // scala/collection/immutable/List.tail:()Ljava/lang/Object;
  #254 = Utf8               $anonfun$mergeTestTags$1$adapted
  #255 = Utf8               (Lscala/collection/mutable/Map;Lscala/collection/immutable/Map;)Ljava/lang/Object;
  #256 = NameAndType        #254:#255     // $anonfun$mergeTestTags$1$adapted:(Lscala/collection/mutable/Map;Lscala/collection/immutable/Map;)Ljava/lang/Object;
  #257 = Methodref          #2.#256       // org/scalatest/Filter.$anonfun$mergeTestTags$1$adapted:(Lscala/collection/mutable/Map;Lscala/collection/immutable/Map;)Ljava/lang/Object;
  #258 = MethodHandle       6:#257        // REF_invokeStatic org/scalatest/Filter.$anonfun$mergeTestTags$1$adapted:(Lscala/collection/mutable/Map;Lscala/collection/immutable/Map;)Ljava/lang/Object;
  #259 = Utf8               (Lscala/collection/immutable/Map;)Ljava/lang/Object;
  #260 = MethodType         #259          //  (Lscala/collection/immutable/Map;)Ljava/lang/Object;
  #261 = Utf8               (Lscala/collection/mutable/Map;)Lscala/Function1;
  #262 = NameAndType        #116:#261     // apply:(Lscala/collection/mutable/Map;)Lscala/Function1;
  #263 = InvokeDynamic      #5:#262       // #5:apply:(Lscala/collection/mutable/Map;)Lscala/Function1;
  #264 = Utf8               foreach
  #265 = Utf8               (Lscala/Function1;)V
  #266 = NameAndType        #264:#265     // foreach:(Lscala/Function1;)V
  #267 = Methodref          #121.#266     // scala/collection/immutable/List.foreach:(Lscala/Function1;)V
  #268 = Utf8               scala/$less$colon$less$
  #269 = Class              #268          // scala/$less$colon$less$
  #270 = Utf8               Lscala/$less$colon$less$;
  #271 = NameAndType        #40:#270      // MODULE$:Lscala/$less$colon$less$;
  #272 = Fieldref           #269.#271     // scala/$less$colon$less$.MODULE$:Lscala/$less$colon$less$;
  #273 = Utf8               refl
  #274 = Utf8               ()Lscala/$eq$colon$eq;
  #275 = NameAndType        #273:#274     // refl:()Lscala/$eq$colon$eq;
  #276 = Methodref          #269.#275     // scala/$less$colon$less$.refl:()Lscala/$eq$colon$eq;
  #277 = Utf8               toMap
  #278 = Utf8               (Lscala/$less$colon$less;)Lscala/collection/immutable/Map;
  #279 = NameAndType        #277:#278     // toMap:(Lscala/$less$colon$less;)Lscala/collection/immutable/Map;
  #280 = InterfaceMethodref #250.#279     // scala/collection/mutable/Map.toMap:(Lscala/$less$colon$less;)Lscala/collection/immutable/Map;
  #281 = Utf8               mergedTags
  #282 = Utf8               Lscala/collection/mutable/Map;
  #283 = Utf8               mergeTestDynamicTags
  #284 = Utf8               (Lscala/collection/immutable/Map;Ljava/lang/String;Lscala/collection/immutable/Set;)Lscala/collection/immutable/Map;
  #285 = Utf8               (Lscala/collection/immutable/Map<Ljava/lang/String;Lscala/collection/immutable/Set<Ljava/lang/String;>;>;Ljava/lang/String;Lscala/collection/immutable/Set<Ljava/lang/String;>;)Lscala/collection/immutable/Map<Ljava/lang/String;Lscala/collection/immutable/Set<Ljava/lang/String;>;>;
  #286 = Utf8               suiteId
  #287 = NameAndType        #34:#47       // dynaTags:()Lorg/scalatest/DynaTags;
  #288 = Methodref          #2.#287       // org/scalatest/Filter.dynaTags:()Lorg/scalatest/DynaTags;
  #289 = Utf8               org/scalatest/DynaTags
  #290 = Class              #289          // org/scalatest/DynaTags
  #291 = Utf8               testTags
  #292 = Utf8               ()Lscala/collection/immutable/Map;
  #293 = NameAndType        #291:#292     // testTags:()Lscala/collection/immutable/Map;
  #294 = Methodref          #290.#293     // org/scalatest/DynaTags.testTags:()Lscala/collection/immutable/Map;
  #295 = Utf8               isDefinedAt
  #296 = NameAndType        #295:#87      // isDefinedAt:(Ljava/lang/Object;)Z
  #297 = InterfaceMethodref #172.#296     // scala/collection/immutable/Map.isDefinedAt:(Ljava/lang/Object;)Z
  #298 = NameAndType        #116:#98      // apply:(Ljava/lang/Object;)Ljava/lang/Object;
  #299 = InterfaceMethodref #172.#298     // scala/collection/immutable/Map.apply:(Ljava/lang/Object;)Ljava/lang/Object;
  #300 = Utf8               scala/Predef$
  #301 = Class              #300          // scala/Predef$
  #302 = Utf8               Lscala/Predef$;
  #303 = NameAndType        #40:#302      // MODULE$:Lscala/Predef$;
  #304 = Fieldref           #301.#303     // scala/Predef$.MODULE$:Lscala/Predef$;
  #305 = Utf8               Map
  #306 = Utf8               ()Lscala/collection/immutable/Map$;
  #307 = NameAndType        #305:#306     // Map:()Lscala/collection/immutable/Map$;
  #308 = Methodref          #301.#307     // scala/Predef$.Map:()Lscala/collection/immutable/Map$;
  #309 = Utf8               scala/collection/immutable/Map$
  #310 = Class              #309          // scala/collection/immutable/Map$
  #311 = Utf8               empty
  #312 = NameAndType        #311:#292     // empty:()Lscala/collection/immutable/Map;
  #313 = Methodref          #310.#312     // scala/collection/immutable/Map$.empty:()Lscala/collection/immutable/Map;
  #314 = Utf8               suiteTags
  #315 = NameAndType        #314:#292     // suiteTags:()Lscala/collection/immutable/Map;
  #316 = Methodref          #290.#315     // org/scalatest/DynaTags.suiteTags:()Lscala/collection/immutable/Map;
  #317 = Methodref          #310.#238     // scala/collection/immutable/Map$.apply:(Lscala/collection/immutable/Seq;)Ljava/lang/Object;
  #318 = Utf8               $anonfun$mergeTestDynamicTags$1
  #319 = Utf8               (Lscala/collection/immutable/Set;Ljava/lang/String;)Lscala/Tuple2;
  #320 = NameAndType        #318:#319     // $anonfun$mergeTestDynamicTags$1:(Lscala/collection/immutable/Set;Ljava/lang/String;)Lscala/Tuple2;
  #321 = Methodref          #2.#320       // org/scalatest/Filter.$anonfun$mergeTestDynamicTags$1:(Lscala/collection/immutable/Set;Ljava/lang/String;)Lscala/Tuple2;
  #322 = MethodHandle       6:#321        // REF_invokeStatic org/scalatest/Filter.$anonfun$mergeTestDynamicTags$1:(Lscala/collection/immutable/Set;Ljava/lang/String;)Lscala/Tuple2;
  #323 = Utf8               (Lscala/collection/immutable/Set;)Lscala/Function1;
  #324 = NameAndType        #116:#323     // apply:(Lscala/collection/immutable/Set;)Lscala/Function1;
  #325 = InvokeDynamic      #6:#324       // #6:apply:(Lscala/collection/immutable/Set;)Lscala/Function1;
  #326 = InterfaceMethodref #97.#140      // scala/collection/immutable/Set.map:(Lscala/Function1;)Ljava/lang/Object;
  #327 = Utf8               scala/package$
  #328 = Class              #327          // scala/package$
  #329 = Utf8               Lscala/package$;
  #330 = NameAndType        #40:#329      // MODULE$:Lscala/package$;
  #331 = Fieldref           #328.#330     // scala/package$.MODULE$:Lscala/package$;
  #332 = Utf8               List
  #333 = Utf8               ()Lscala/collection/immutable/List$;
  #334 = NameAndType        #332:#333     // List:()Lscala/collection/immutable/List$;
  #335 = Methodref          #328.#334     // scala/package$.List:()Lscala/collection/immutable/List$;
  #336 = Utf8               scala/runtime/ScalaRunTime$
  #337 = Class              #336          // scala/runtime/ScalaRunTime$
  #338 = Utf8               Lscala/runtime/ScalaRunTime$;
  #339 = NameAndType        #40:#338      // MODULE$:Lscala/runtime/ScalaRunTime$;
  #340 = Fieldref           #337.#339     // scala/runtime/ScalaRunTime$.MODULE$:Lscala/runtime/ScalaRunTime$;
  #341 = Utf8               [Ljava/lang/Object;
  #342 = Class              #341          // "[Ljava/lang/Object;"
  #343 = Utf8               wrapRefArray
  #344 = Utf8               ([Ljava/lang/Object;)Lscala/collection/immutable/ArraySeq;
  #345 = NameAndType        #343:#344     // wrapRefArray:([Ljava/lang/Object;)Lscala/collection/immutable/ArraySeq;
  #346 = Methodref          #337.#345     // scala/runtime/ScalaRunTime$.wrapRefArray:([Ljava/lang/Object;)Lscala/collection/immutable/ArraySeq;
  #347 = Utf8               scala/collection/immutable/List$
  #348 = Class              #347          // scala/collection/immutable/List$
  #349 = Methodref          #348.#238     // scala/collection/immutable/List$.apply:(Lscala/collection/immutable/Seq;)Ljava/lang/Object;
  #350 = NameAndType        #223:#224     // mergeTestTags:(Lscala/collection/immutable/List;)Lscala/collection/immutable/Map;
  #351 = Methodref          #2.#350       // org/scalatest/Filter.mergeTestTags:(Lscala/collection/immutable/List;)Lscala/collection/immutable/Map;
  #352 = Utf8               dynaTestTags
  #353 = Utf8               dynaSuiteTags
  #354 = Utf8               (Lscala/collection/immutable/Set;Lscala/collection/immutable/Map;Ljava/lang/String;)Lscala/collection/immutable/List;
  #355 = Utf8               (Lscala/collection/immutable/Set<Ljava/lang/String;>;Lscala/collection/immutable/Map<Ljava/lang/String;Lscala/collection/immutable/Set<Ljava/lang/String;>;>;Ljava/lang/String;)Lscala/collection/immutable/List<Lscala/Tuple2<Ljava/lang/String;Ljava/lang/Object;>;>;
  #356 = NameAndType        #283:#284     // mergeTestDynamicTags:(Lscala/collection/immutable/Map;Ljava/lang/String;Lscala/collection/immutable/Set;)Lscala/collection/immutable/Map;
  #357 = Methodref          #2.#356       // org/scalatest/Filter.mergeTestDynamicTags:(Lscala/collection/immutable/Map;Ljava/lang/String;Lscala/collection/immutable/Set;)Lscala/collection/immutable/Map;
  #358 = NameAndType        #173:#174     // verifyPreconditionsForMethods:(Lscala/collection/immutable/Set;Lscala/collection/immutable/Map;)V
  #359 = Methodref          #2.#358       // org/scalatest/Filter.verifyPreconditionsForMethods:(Lscala/collection/immutable/Set;Lscala/collection/immutable/Map;)V
  #360 = Utf8               toList
  #361 = Utf8               ()Lscala/collection/immutable/List;
  #362 = NameAndType        #360:#361     // toList:()Lscala/collection/immutable/List;
  #363 = InterfaceMethodref #97.#362      // scala/collection/immutable/Set.toList:()Lscala/collection/immutable/List;
  #364 = NameAndType        #74:#75       // includedTestNames:(Lscala/collection/immutable/List;Lscala/collection/immutable/Map;)Lscala/collection/immutable/List;
  #365 = Methodref          #2.#364       // org/scalatest/Filter.includedTestNames:(Lscala/collection/immutable/List;Lscala/collection/immutable/Map;)Lscala/collection/immutable/List;
  #366 = Utf8               $anonfun$apply$1$adapted
  #367 = Utf8               (Lorg/scalatest/Filter;Lscala/collection/immutable/Map;Ljava/lang/String;)Ljava/lang/Object;
  #368 = NameAndType        #366:#367     // $anonfun$apply$1$adapted:(Lorg/scalatest/Filter;Lscala/collection/immutable/Map;Ljava/lang/String;)Ljava/lang/Object;
  #369 = Methodref          #2.#368       // org/scalatest/Filter.$anonfun$apply$1$adapted:(Lorg/scalatest/Filter;Lscala/collection/immutable/Map;Ljava/lang/String;)Ljava/lang/Object;
  #370 = MethodHandle       6:#369        // REF_invokeStatic org/scalatest/Filter.$anonfun$apply$1$adapted:(Lorg/scalatest/Filter;Lscala/collection/immutable/Map;Ljava/lang/String;)Ljava/lang/Object;
  #371 = Utf8               (Lorg/scalatest/Filter;Lscala/collection/immutable/Map;)Lscala/Function1;
  #372 = NameAndType        #116:#371     // apply:(Lorg/scalatest/Filter;Lscala/collection/immutable/Map;)Lscala/Function1;
  #373 = InvokeDynamic      #7:#372       // #7:apply:(Lorg/scalatest/Filter;Lscala/collection/immutable/Map;)Lscala/Function1;
  #374 = Utf8               $anonfun$apply$2
  #375 = Utf8               (Lscala/collection/immutable/Map;Ljava/lang/String;)Lscala/Tuple2;
  #376 = NameAndType        #374:#375     // $anonfun$apply$2:(Lscala/collection/immutable/Map;Ljava/lang/String;)Lscala/Tuple2;
  #377 = Methodref          #2.#376       // org/scalatest/Filter.$anonfun$apply$2:(Lscala/collection/immutable/Map;Ljava/lang/String;)Lscala/Tuple2;
  #378 = MethodHandle       6:#377        // REF_invokeStatic org/scalatest/Filter.$anonfun$apply$2:(Lscala/collection/immutable/Map;Ljava/lang/String;)Lscala/Tuple2;
  #379 = InvokeDynamic      #8:#118       // #8:apply:(Lscala/collection/immutable/Map;)Lscala/Function1;
  #380 = Utf8               filtered
  #381 = Utf8               (Ljava/lang/String;Lscala/collection/immutable/Map;Ljava/lang/String;)Lscala/Tuple2;
  #382 = Utf8               (Ljava/lang/String;Lscala/collection/immutable/Map<Ljava/lang/String;Lscala/collection/immutable/Set<Ljava/lang/String;>;>;Ljava/lang/String;)Lscala/Tuple2<Ljava/lang/Object;Ljava/lang/Object;>;
  #383 = Utf8               Set
  #384 = Utf8               ()Lscala/collection/immutable/Set$;
  #385 = NameAndType        #383:#384     // Set:()Lscala/collection/immutable/Set$;
  #386 = Methodref          #301.#385     // scala/Predef$.Set:()Lscala/collection/immutable/Set$;
  #387 = Utf8               scala/collection/immutable/Set$
  #388 = Class              #387          // scala/collection/immutable/Set$
  #389 = Methodref          #388.#238     // scala/collection/immutable/Set$.apply:(Lscala/collection/immutable/Seq;)Ljava/lang/Object;
  #390 = Utf8               impl$1
  #391 = Utf8               (Lscala/collection/immutable/Set;Lscala/collection/immutable/Map;)Lscala/collection/immutable/List;
  #392 = NameAndType        #390:#391     // impl$1:(Lscala/collection/immutable/Set;Lscala/collection/immutable/Map;)Lscala/collection/immutable/List;
  #393 = Methodref          #2.#392       // org/scalatest/Filter.impl$1:(Lscala/collection/immutable/Set;Lscala/collection/immutable/Map;)Lscala/collection/immutable/List;
  #394 = Utf8               isEmpty
  #395 = NameAndType        #394:#51      // isEmpty:()Z
  #396 = Methodref          #121.#395     // scala/collection/immutable/List.isEmpty:()Z
  #397 = Utf8               scala/Tuple2$mcZZ$sp
  #398 = Class              #397          // scala/Tuple2$mcZZ$sp
  #399 = Utf8               (ZZ)V
  #400 = NameAndType        #163:#399     // "<init>":(ZZ)V
  #401 = Methodref          #398.#400     // scala/Tuple2$mcZZ$sp."<init>":(ZZ)V
  #402 = Utf8               _2$mcZ$sp
  #403 = NameAndType        #402:#51      // _2$mcZ$sp:()Z
  #404 = Methodref          #187.#403     // scala/Tuple2._2$mcZ$sp:()Z
  #405 = Utf8               list
  #406 = Utf8               runnableTestCount
  #407 = Utf8               (Lscala/collection/immutable/Set;Lscala/collection/immutable/Map;Ljava/lang/String;)I
  #408 = Utf8               (Lscala/collection/immutable/Set<Ljava/lang/String;>;Lscala/collection/immutable/Map<Ljava/lang/String;Lscala/collection/immutable/Set<Ljava/lang/String;>;>;Ljava/lang/String;)I
  #409 = Utf8               $anonfun$runnableTestCount$1$adapted
  #410 = NameAndType        #409:#367     // $anonfun$runnableTestCount$1$adapted:(Lorg/scalatest/Filter;Lscala/collection/immutable/Map;Ljava/lang/String;)Ljava/lang/Object;
  #411 = Methodref          #2.#410       // org/scalatest/Filter.$anonfun$runnableTestCount$1$adapted:(Lorg/scalatest/Filter;Lscala/collection/immutable/Map;Ljava/lang/String;)Ljava/lang/Object;
  #412 = MethodHandle       6:#411        // REF_invokeStatic org/scalatest/Filter.$anonfun$runnableTestCount$1$adapted:(Lorg/scalatest/Filter;Lscala/collection/immutable/Map;Ljava/lang/String;)Ljava/lang/Object;
  #413 = InvokeDynamic      #9:#372       // #9:apply:(Lorg/scalatest/Filter;Lscala/collection/immutable/Map;)Lscala/Function1;
  #414 = Utf8               $anonfun$runnableTestCount$2
  #415 = Utf8               (Ljava/lang/String;)Ljava/lang/String;
  #416 = NameAndType        #414:#415     // $anonfun$runnableTestCount$2:(Ljava/lang/String;)Ljava/lang/String;
  #417 = Methodref          #2.#416       // org/scalatest/Filter.$anonfun$runnableTestCount$2:(Ljava/lang/String;)Ljava/lang/String;
  #418 = MethodHandle       6:#417        // REF_invokeStatic org/scalatest/Filter.$anonfun$runnableTestCount$2:(Ljava/lang/String;)Ljava/lang/String;
  #419 = MethodType         #415          //  (Ljava/lang/String;)Ljava/lang/String;
  #420 = InvokeDynamic      #10:#151      // #10:apply:()Lscala/Function1;
  #421 = Utf8               size
  #422 = Utf8               ()I
  #423 = NameAndType        #421:#422     // size:()I
  #424 = Methodref          #121.#423     // scala/collection/immutable/List.size:()I
  #425 = Utf8               runnableTests
  #426 = Utf8               $anonfun$includedTestNames$1
  #427 = Utf8               (Lscala/collection/immutable/Map;Ljava/lang/String;)Z
  #428 = Utf8               tags$1
  #429 = Utf8               contains
  #430 = NameAndType        #429:#87      // contains:(Ljava/lang/Object;)Z
  #431 = InterfaceMethodref #172.#430     // scala/collection/immutable/Map.contains:(Ljava/lang/Object;)Z
  #432 = Utf8               tagsToInclude$1
  #433 = Utf8               scala/collection/Set
  #434 = Class              #433          // scala/collection/Set
  #435 = Utf8               intersect
  #436 = Utf8               (Lscala/collection/Set;)Lscala/collection/SetOps;
  #437 = NameAndType        #435:#436     // intersect:(Lscala/collection/Set;)Lscala/collection/SetOps;
  #438 = InterfaceMethodref #97.#437      // scala/collection/immutable/Set.intersect:(Lscala/collection/Set;)Lscala/collection/SetOps;
  #439 = Utf8               (Ljava/lang/Object;Ljava/lang/Object;)V
  #440 = NameAndType        #163:#439     // "<init>":(Ljava/lang/Object;Ljava/lang/Object;)V
  #441 = Methodref          #187.#440     // scala/Tuple2."<init>":(Ljava/lang/Object;Ljava/lang/Object;)V
  #442 = Utf8               intersection
  #443 = Utf8               $anonfun$includedTestNames$3
  #444 = Utf8               (Lscala/Tuple2;)Z
  #445 = Utf8               x$1
  #446 = Utf8               _2
  #447 = NameAndType        #446:#93      // _2:()Ljava/lang/Object;
  #448 = Methodref          #187.#447     // scala/Tuple2._2:()Ljava/lang/Object;
  #449 = InterfaceMethodref #97.#423      // scala/collection/immutable/Set.size:()I
  #450 = Utf8               Lscala/Tuple2;
  #451 = Utf8               x$2
  #452 = Utf8               $anonfun$verifyPreconditionsForMethods$1
  #453 = Utf8               tuple
  #454 = Utf8               scala/collection/IterableOnceOps
  #455 = Class              #454          // scala/collection/IterableOnceOps
  #456 = InterfaceMethodref #455.#395     // scala/collection/IterableOnceOps.isEmpty:()Z
  #457 = Utf8               $anonfun$mergeTestTags$2
  #458 = Utf8               check$ifrefutable$1
  #459 = Utf8               $anonfun$mergeTestTags$3
  #460 = Utf8               (Lscala/collection/mutable/Map;Lscala/Tuple2;)Ljava/lang/Object;
  #461 = Utf8               mergedTags$1
  #462 = Utf8               x$3
  #463 = Utf8               get
  #464 = Utf8               (Ljava/lang/Object;)Lscala/Option;
  #465 = NameAndType        #463:#464     // get:(Ljava/lang/Object;)Lscala/Option;
  #466 = InterfaceMethodref #250.#465     // scala/collection/mutable/Map.get:(Ljava/lang/Object;)Lscala/Option;
  #467 = Utf8               (Lscala/collection/IterableOnce;)Lscala/collection/SetOps;
  #468 = NameAndType        #245:#467     // $plus$plus:(Lscala/collection/IterableOnce;)Lscala/collection/SetOps;
  #469 = InterfaceMethodref #97.#468      // scala/collection/immutable/Set.$plus$plus:(Lscala/collection/IterableOnce;)Lscala/collection/SetOps;
  #470 = Utf8               update
  #471 = NameAndType        #470:#439     // update:(Ljava/lang/Object;Ljava/lang/Object;)V
  #472 = InterfaceMethodref #250.#471     // scala/collection/mutable/Map.update:(Ljava/lang/Object;Ljava/lang/Object;)V
  #473 = Utf8               $plus$eq
  #474 = Utf8               (Ljava/lang/Object;)Lscala/collection/mutable/Growable;
  #475 = NameAndType        #473:#474     // $plus$eq:(Ljava/lang/Object;)Lscala/collection/mutable/Growable;
  #476 = InterfaceMethodref #250.#475     // scala/collection/mutable/Map.$plus$eq:(Ljava/lang/Object;)Lscala/collection/mutable/Growable;
  #477 = Utf8               existingTagSet
  #478 = Utf8               existingTagSetOpt
  #479 = Utf8               tagSet
  #480 = Utf8               $anonfun$mergeTestTags$1
  #481 = Utf8               (Lscala/collection/mutable/Map;Lscala/collection/immutable/Map;)V
  #482 = Utf8               $anonfun$mergeTestTags$2$adapted
  #483 = NameAndType        #482:#145     // $anonfun$mergeTestTags$2$adapted:(Lscala/Tuple2;)Ljava/lang/Object;
  #484 = Methodref          #2.#483       // org/scalatest/Filter.$anonfun$mergeTestTags$2$adapted:(Lscala/Tuple2;)Ljava/lang/Object;
  #485 = MethodHandle       6:#484        // REF_invokeStatic org/scalatest/Filter.$anonfun$mergeTestTags$2$adapted:(Lscala/Tuple2;)Ljava/lang/Object;
  #486 = InvokeDynamic      #11:#151      // #11:apply:()Lscala/Function1;
  #487 = Utf8               (Lscala/Function1;)Lscala/collection/MapOps$WithFilter;
  #488 = NameAndType        #122:#487     // withFilter:(Lscala/Function1;)Lscala/collection/MapOps$WithFilter;
  #489 = InterfaceMethodref #172.#488     // scala/collection/immutable/Map.withFilter:(Lscala/Function1;)Lscala/collection/MapOps$WithFilter;
  #490 = NameAndType        #459:#460     // $anonfun$mergeTestTags$3:(Lscala/collection/mutable/Map;Lscala/Tuple2;)Ljava/lang/Object;
  #491 = Methodref          #2.#490       // org/scalatest/Filter.$anonfun$mergeTestTags$3:(Lscala/collection/mutable/Map;Lscala/Tuple2;)Ljava/lang/Object;
  #492 = MethodHandle       6:#491        // REF_invokeStatic org/scalatest/Filter.$anonfun$mergeTestTags$3:(Lscala/collection/mutable/Map;Lscala/Tuple2;)Ljava/lang/Object;
  #493 = InvokeDynamic      #12:#262      // #12:apply:(Lscala/collection/mutable/Map;)Lscala/Function1;
  #494 = Methodref          #22.#266      // scala/collection/MapOps$WithFilter.foreach:(Lscala/Function1;)V
  #495 = Utf8               suiteTags$1
  #496 = Utf8               tn
  #497 = Utf8               $anonfun$apply$1
  #498 = Utf8               (Lorg/scalatest/Filter;Lscala/collection/immutable/Map;Ljava/lang/String;)Z
  #499 = Utf8               $this
  #500 = Utf8               testTags$1
  #501 = Utf8               scala/collection/SetOps
  #502 = Class              #501          // scala/collection/SetOps
  #503 = Utf8               org.scalatest.Ignore
  #504 = String             #503          // org.scalatest.Ignore
  #505 = InterfaceMethodref #502.#430     // scala/collection/SetOps.contains:(Ljava/lang/Object;)Z
  #506 = NameAndType        #29:#55       // tagsToExclude:()Lscala/collection/immutable/Set;
  #507 = Methodref          #2.#506       // org/scalatest/Filter.tagsToExclude:()Lscala/collection/immutable/Set;
  #508 = Utf8               $plus
  #509 = Utf8               (Ljava/lang/Object;)Lscala/collection/immutable/SetOps;
  #510 = NameAndType        #508:#509     // $plus:(Ljava/lang/Object;)Lscala/collection/immutable/SetOps;
  #511 = InterfaceMethodref #97.#510      // scala/collection/immutable/Set.$plus:(Ljava/lang/Object;)Lscala/collection/immutable/SetOps;
  #512 = InterfaceMethodref #502.#437     // scala/collection/SetOps.intersect:(Lscala/collection/Set;)Lscala/collection/SetOps;
  #513 = InterfaceMethodref #502.#423     // scala/collection/SetOps.size:()I
  #514 = InterfaceMethodref #502.#395     // scala/collection/SetOps.isEmpty:()Z
  #515 = Utf8               scala/runtime/BoxesRunTime
  #516 = Class              #515          // scala/runtime/BoxesRunTime
  #517 = Utf8               boxToBoolean
  #518 = Utf8               (Z)Ljava/lang/Boolean;
  #519 = NameAndType        #517:#518     // boxToBoolean:(Z)Ljava/lang/Boolean;
  #520 = Methodref          #516.#519     // scala/runtime/BoxesRunTime.boxToBoolean:(Z)Ljava/lang/Boolean;
  #521 = Utf8               $anonfun$apply$3
  #522 = Utf8               tags$2
  #523 = Utf8               $anonfun$apply$4
  #524 = Utf8               $anonfun$apply$3$adapted
  #525 = NameAndType        #524:#367     // $anonfun$apply$3$adapted:(Lorg/scalatest/Filter;Lscala/collection/immutable/Map;Ljava/lang/String;)Ljava/lang/Object;
  #526 = Methodref          #2.#525       // org/scalatest/Filter.$anonfun$apply$3$adapted:(Lorg/scalatest/Filter;Lscala/collection/immutable/Map;Ljava/lang/String;)Ljava/lang/Object;
  #527 = MethodHandle       6:#526        // REF_invokeStatic org/scalatest/Filter.$anonfun$apply$3$adapted:(Lorg/scalatest/Filter;Lscala/collection/immutable/Map;Ljava/lang/String;)Ljava/lang/Object;
  #528 = InvokeDynamic      #13:#372      // #13:apply:(Lorg/scalatest/Filter;Lscala/collection/immutable/Map;)Lscala/Function1;
  #529 = NameAndType        #523:#375     // $anonfun$apply$4:(Lscala/collection/immutable/Map;Ljava/lang/String;)Lscala/Tuple2;
  #530 = Methodref          #2.#529       // org/scalatest/Filter.$anonfun$apply$4:(Lscala/collection/immutable/Map;Ljava/lang/String;)Lscala/Tuple2;
  #531 = MethodHandle       6:#530        // REF_invokeStatic org/scalatest/Filter.$anonfun$apply$4:(Lscala/collection/immutable/Map;Ljava/lang/String;)Lscala/Tuple2;
  #532 = InvokeDynamic      #14:#118      // #14:apply:(Lscala/collection/immutable/Map;)Lscala/Function1;
  #533 = Utf8               $anonfun$runnableTestCount$1
  #534 = Utf8               tags$3
  #535 = Utf8               (Lscala/Option;Lscala/collection/immutable/Set;ZLorg/scalatest/DynaTags;)V
  #536 = Utf8               (Lscala/Option<Lscala/collection/immutable/Set<Ljava/lang/String;>;>;Lscala/collection/immutable/Set<Ljava/lang/String;>;ZLorg/scalatest/DynaTags;)V
  #537 = Utf8               ()V
  #538 = NameAndType        #163:#537     // "<init>":()V
  #539 = Methodref          #4.#538       // java/lang/Object."<init>":()V
  #540 = Utf8               org/scalactic/Requirements$
  #541 = Class              #540          // org/scalactic/Requirements$
  #542 = Utf8               Lorg/scalactic/Requirements$;
  #543 = NameAndType        #40:#542      // MODULE$:Lorg/scalactic/Requirements$;
  #544 = Fieldref           #541.#543     // org/scalactic/Requirements$.MODULE$:Lorg/scalactic/Requirements$;
  #545 = Utf8               requirementsHelper
  #546 = Utf8               ()Lorg/scalactic/Requirements$RequirementsHelper;
  #547 = NameAndType        #545:#546     // requirementsHelper:()Lorg/scalactic/Requirements$RequirementsHelper;
  #548 = Methodref          #541.#547     // org/scalactic/Requirements$.requirementsHelper:()Lorg/scalactic/Requirements$RequirementsHelper;
  #549 = Utf8               Filter.this.tagsToInclude
  #550 = String             #549          // Filter.this.tagsToInclude
  #551 = Utf8               Filter.this.tagsToExclude
  #552 = String             #551          // Filter.this.tagsToExclude
  #553 = Utf8               Filter.this.dynaTags
  #554 = String             #553          // Filter.this.dynaTags
  #555 = Utf8               [Ljava/lang/String;
  #556 = Class              #555          // "[Ljava/lang/String;"
  #557 = Utf8               org/scalactic/Prettifier$
  #558 = Class              #557          // org/scalactic/Prettifier$
  #559 = Utf8               Lorg/scalactic/Prettifier$;
  #560 = NameAndType        #40:#559      // MODULE$:Lorg/scalactic/Prettifier$;
  #561 = Fieldref           #558.#560     // org/scalactic/Prettifier$.MODULE$:Lorg/scalactic/Prettifier$;
  #562 = Utf8               ()Lorg/scalactic/Prettifier;
  #563 = NameAndType        #36:#562      // default:()Lorg/scalactic/Prettifier;
  #564 = Methodref          #558.#563     // org/scalactic/Prettifier$.default:()Lorg/scalactic/Prettifier;
  #565 = Utf8               org/scalactic/source/Position
  #566 = Class              #565          // org/scalactic/source/Position
  #567 = String             #7            // Filter.scala
  #568 = Utf8               Please set the environment variable SCALACTIC_FILL_FILE_PATHNAMES to yes at compile time to enable this feature.
  #569 = String             #568          // Please set the environment variable SCALACTIC_FILL_FILE_PATHNAMES to yes at compile time to enable this feature.
  #570 = Utf8               (Ljava/lang/String;Ljava/lang/String;I)V
  #571 = NameAndType        #163:#570     // "<init>":(Ljava/lang/String;Ljava/lang/String;I)V
  #572 = Methodref          #566.#571     // org/scalactic/source/Position."<init>":(Ljava/lang/String;Ljava/lang/String;I)V
  #573 = Utf8               macroRequireNonNull
  #574 = Utf8               ([Ljava/lang/String;[Ljava/lang/Object;Lorg/scalactic/Prettifier;Lorg/scalactic/source/Position;)V
  #575 = NameAndType        #573:#574     // macroRequireNonNull:([Ljava/lang/String;[Ljava/lang/Object;Lorg/scalactic/Prettifier;Lorg/scalactic/source/Position;)V
  #576 = Methodref          #17.#575      // org/scalactic/Requirements$RequirementsHelper.macroRequireNonNull:([Ljava/lang/String;[Ljava/lang/Object;Lorg/scalactic/Prettifier;Lorg/scalactic/source/Position;)V
  #577 = InterfaceMethodref #97.#395      // scala/collection/immutable/Set.isEmpty:()Z
  #578 = Utf8               tagsToInclude was defined, but contained an empty set
  #579 = String             #578          // tagsToInclude was defined, but contained an empty set
  #580 = NameAndType        #426:#427     // $anonfun$includedTestNames$1:(Lscala/collection/immutable/Map;Ljava/lang/String;)Z
  #581 = Methodref          #2.#580       // org/scalatest/Filter.$anonfun$includedTestNames$1:(Lscala/collection/immutable/Map;Ljava/lang/String;)Z
  #582 = NameAndType        #443:#444     // $anonfun$includedTestNames$3:(Lscala/Tuple2;)Z
  #583 = Methodref          #2.#582       // org/scalatest/Filter.$anonfun$includedTestNames$3:(Lscala/Tuple2;)Z
  #584 = NameAndType        #452:#444     // $anonfun$verifyPreconditionsForMethods$1:(Lscala/Tuple2;)Z
  #585 = Methodref          #2.#584       // org/scalatest/Filter.$anonfun$verifyPreconditionsForMethods$1:(Lscala/Tuple2;)Z
  #586 = NameAndType        #480:#481     // $anonfun$mergeTestTags$1:(Lscala/collection/mutable/Map;Lscala/collection/immutable/Map;)V
  #587 = Methodref          #2.#586       // org/scalatest/Filter.$anonfun$mergeTestTags$1:(Lscala/collection/mutable/Map;Lscala/collection/immutable/Map;)V
  #588 = NameAndType        #497:#498     // $anonfun$apply$1:(Lorg/scalatest/Filter;Lscala/collection/immutable/Map;Ljava/lang/String;)Z
  #589 = Methodref          #2.#588       // org/scalatest/Filter.$anonfun$apply$1:(Lorg/scalatest/Filter;Lscala/collection/immutable/Map;Ljava/lang/String;)Z
  #590 = NameAndType        #533:#498     // $anonfun$runnableTestCount$1:(Lorg/scalatest/Filter;Lscala/collection/immutable/Map;Ljava/lang/String;)Z
  #591 = Methodref          #2.#590       // org/scalatest/Filter.$anonfun$runnableTestCount$1:(Lorg/scalatest/Filter;Lscala/collection/immutable/Map;Ljava/lang/String;)Z
  #592 = NameAndType        #457:#444     // $anonfun$mergeTestTags$2:(Lscala/Tuple2;)Z
  #593 = Methodref          #2.#592       // org/scalatest/Filter.$anonfun$mergeTestTags$2:(Lscala/Tuple2;)Z
  #594 = NameAndType        #521:#498     // $anonfun$apply$3:(Lorg/scalatest/Filter;Lscala/collection/immutable/Map;Ljava/lang/String;)Z
  #595 = Methodref          #2.#594       // org/scalatest/Filter.$anonfun$apply$3:(Lorg/scalatest/Filter;Lscala/collection/immutable/Map;Ljava/lang/String;)Z
  #596 = Utf8               $deserializeLambda$
  #597 = Utf8               (Ljava/lang/invoke/SerializedLambda;)Ljava/lang/Object;
  #598 = Utf8               scala/runtime/LambdaDeserialize
  #599 = Class              #598          // scala/runtime/LambdaDeserialize
  #600 = Utf8               bootstrap
  #601 = Utf8               (Ljava/lang/invoke/MethodHandles$Lookup;Ljava/lang/String;Ljava/lang/invoke/MethodType;[Ljava/lang/invoke/MethodHandle;)Ljava/lang/invoke/CallSite;
  #602 = NameAndType        #600:#601     // bootstrap:(Ljava/lang/invoke/MethodHandles$Lookup;Ljava/lang/String;Ljava/lang/invoke/MethodType;[Ljava/lang/invoke/MethodHandle;)Ljava/lang/invoke/CallSite;
  #603 = Methodref          #599.#602     // scala/runtime/LambdaDeserialize.bootstrap:(Ljava/lang/invoke/MethodHandles$Lookup;Ljava/lang/String;Ljava/lang/invoke/MethodType;[Ljava/lang/invoke/MethodHandle;)Ljava/lang/invoke/CallSite;
  #604 = MethodHandle       6:#603        // REF_invokeStatic scala/runtime/LambdaDeserialize.bootstrap:(Ljava/lang/invoke/MethodHandles$Lookup;Ljava/lang/String;Ljava/lang/invoke/MethodType;[Ljava/lang/invoke/MethodHandle;)Ljava/lang/invoke/CallSite;
  #605 = Utf8               lambdaDeserialize
  #606 = NameAndType        #605:#597     // lambdaDeserialize:(Ljava/lang/invoke/SerializedLambda;)Ljava/lang/Object;
  #607 = InvokeDynamic      #15:#606      // #15:lambdaDeserialize:(Ljava/lang/invoke/SerializedLambda;)Ljava/lang/Object;
  #608 = Utf8               Signature
  #609 = Utf8               Code
  #610 = Utf8               LineNumberTable
  #611 = Utf8               LocalVariableTable
  #612 = Utf8               StackMapTable
  #613 = Utf8               MethodParameters
  #614 = Utf8               InnerClasses
  #615 = Utf8               SourceFile
  #616 = Utf8               RuntimeVisibleAnnotations
  #617 = Utf8               BootstrapMethods
  #618 = Utf8               ScalaInlineInfo
  #619 = Utf8               ScalaSig
{
  private final scala.Option<scala.collection.immutable.Set<java.lang.String>> tagsToInclude;
    descriptor: Lscala/Option;
    flags: (0x0012) ACC_PRIVATE, ACC_FINAL
    Signature: #28                          // Lscala/Option<Lscala/collection/immutable/Set<Ljava/lang/String;>;>;

  private final scala.collection.immutable.Set<java.lang.String> tagsToExclude;
    descriptor: Lscala/collection/immutable/Set;
    flags: (0x0012) ACC_PRIVATE, ACC_FINAL
    Signature: #31                          // Lscala/collection/immutable/Set<Ljava/lang/String;>;

  private final boolean excludeNestedSuites;
    descriptor: Z
    flags: (0x0012) ACC_PRIVATE, ACC_FINAL

  private final org.scalatest.DynaTags dynaTags;
    descriptor: Lorg/scalatest/DynaTags;
    flags: (0x0012) ACC_PRIVATE, ACC_FINAL

  public static org.scalatest.Filter default();
    descriptor: ()Lorg/scalatest/Filter;
    flags: (0x0009) ACC_PUBLIC, ACC_STATIC
    Code:
      stack=1, locals=0, args_size=0
         0: getstatic     #43                 // Field org/scalatest/Filter$.MODULE$:Lorg/scalatest/Filter$;
         3: invokevirtual #45                 // Method org/scalatest/Filter$.default:()Lorg/scalatest/Filter;
         6: areturn

  public static org.scalatest.DynaTags apply$default$4();
    descriptor: ()Lorg/scalatest/DynaTags;
    flags: (0x0009) ACC_PUBLIC, ACC_STATIC
    Code:
      stack=1, locals=0, args_size=0
         0: getstatic     #43                 // Field org/scalatest/Filter$.MODULE$:Lorg/scalatest/Filter$;
         3: invokevirtual #49                 // Method org/scalatest/Filter$.apply$default$4:()Lorg/scalatest/DynaTags;
         6: areturn

  public static boolean apply$default$3();
    descriptor: ()Z
    flags: (0x0009) ACC_PUBLIC, ACC_STATIC
    Code:
      stack=1, locals=0, args_size=0
         0: getstatic     #43                 // Field org/scalatest/Filter$.MODULE$:Lorg/scalatest/Filter$;
         3: invokevirtual #53                 // Method org/scalatest/Filter$.apply$default$3:()Z
         6: ireturn

  public static scala.collection.immutable.Set<java.lang.String> apply$default$2();
    descriptor: ()Lscala/collection/immutable/Set;
    flags: (0x0009) ACC_PUBLIC, ACC_STATIC
    Code:
      stack=1, locals=0, args_size=0
         0: getstatic     #43                 // Field org/scalatest/Filter$.MODULE$:Lorg/scalatest/Filter$;
         3: invokevirtual #58                 // Method org/scalatest/Filter$.apply$default$2:()Lscala/collection/immutable/Set;
         6: areturn
    Signature: #56                          // ()Lscala/collection/immutable/Set<Ljava/lang/String;>;

  public static scala.Option<scala.collection.immutable.Set<java.lang.String>> apply$default$1();
    descriptor: ()Lscala/Option;
    flags: (0x0009) ACC_PUBLIC, ACC_STATIC
    Code:
      stack=1, locals=0, args_size=0
         0: getstatic     #43                 // Field org/scalatest/Filter$.MODULE$:Lorg/scalatest/Filter$;
         3: invokevirtual #63                 // Method org/scalatest/Filter$.apply$default$1:()Lscala/Option;
         6: areturn
    Signature: #61                          // ()Lscala/Option<Lscala/collection/immutable/Set<Ljava/lang/String;>;>;

  public scala.Option<scala.collection.immutable.Set<java.lang.String>> tagsToInclude();
    descriptor: ()Lscala/Option;
    flags: (0x0001) ACC_PUBLIC
    Code:
      stack=1, locals=1, args_size=1
         0: aload_0
         1: getfield      #65                 // Field tagsToInclude:Lscala/Option;
         4: areturn
      LineNumberTable:
        line 48: 0
      LocalVariableTable:
        Start  Length  Slot  Name   Signature
            0       5     0  this   Lorg/scalatest/Filter;
    Signature: #61                          // ()Lscala/Option<Lscala/collection/immutable/Set<Ljava/lang/String;>;>;

  public scala.collection.immutable.Set<java.lang.String> tagsToExclude();
    descriptor: ()Lscala/collection/immutable/Set;
    flags: (0x0001) ACC_PUBLIC
    Code:
      stack=1, locals=1, args_size=1
         0: aload_0
         1: getfield      #69                 // Field tagsToExclude:Lscala/collection/immutable/Set;
         4: areturn
      LineNumberTable:
        line 48: 0
      LocalVariableTable:
        Start  Length  Slot  Name   Signature
            0       5     0  this   Lorg/scalatest/Filter;
    Signature: #56                          // ()Lscala/collection/immutable/Set<Ljava/lang/String;>;

  public boolean excludeNestedSuites();
    descriptor: ()Z
    flags: (0x0001) ACC_PUBLIC
    Code:
      stack=1, locals=1, args_size=1
         0: aload_0
         1: getfield      #71                 // Field excludeNestedSuites:Z
         4: ireturn
      LineNumberTable:
        line 48: 0
      LocalVariableTable:
        Start  Length  Slot  Name   Signature
            0       5     0  this   Lorg/scalatest/Filter;

  public org.scalatest.DynaTags dynaTags();
    descriptor: ()Lorg/scalatest/DynaTags;
    flags: (0x0001) ACC_PUBLIC
    Code:
      stack=1, locals=1, args_size=1
         0: aload_0
         1: getfield      #73                 // Field dynaTags:Lorg/scalatest/DynaTags;
         4: areturn
      LineNumberTable:
        line 48: 0
      LocalVariableTable:
        Start  Length  Slot  Name   Signature
            0       5     0  this   Lorg/scalatest/Filter;

  private scala.collection.immutable.List<java.lang.String> includedTestNames(scala.collection.immutable.List<java.lang.String>, scala.collection.immutable.Map<java.lang.String, scala.collection.immutable.Set<java.lang.String>>);
    descriptor: (Lscala/collection/immutable/List;Lscala/collection/immutable/Map;)Lscala/collection/immutable/List;
    flags: (0x0002) ACC_PRIVATE
    Code:
      stack=3, locals=7, args_size=3
         0: aload_0
         1: invokevirtual #80                 // Method tagsToInclude:()Lscala/Option;
         4: astore        4
         6: getstatic     #85                 // Field scala/None$.MODULE$:Lscala/None$;
         9: aload         4
        11: invokevirtual #89                 // Method java/lang/Object.equals:(Ljava/lang/Object;)Z
        14: ifeq          22
        17: aload_1
        18: astore_3
        19: goto          112
        22: goto          25
        25: aload         4
        27: instanceof    #91                 // class scala/Some
        30: ifeq          99
        33: aload         4
        35: checkcast     #91                 // class scala/Some
        38: astore        5
        40: aload         5
        42: invokevirtual #95                 // Method scala/Some.value:()Ljava/lang/Object;
        45: checkcast     #97                 // class scala/collection/immutable/Set
        48: astore        6
        50: aload_1
        51: aload_2
        52: invokedynamic #119,  0            // InvokeDynamic #0:apply:(Lscala/collection/immutable/Map;)Lscala/Function1;
        57: invokevirtual #125                // Method scala/collection/immutable/List.withFilter:(Lscala/Function1;)Lscala/collection/WithFilter;
        60: aload         6
        62: aload_2
        63: invokedynamic #135,  0            // InvokeDynamic #1:apply:(Lscala/collection/immutable/Set;Lscala/collection/immutable/Map;)Lscala/Function1;
        68: invokevirtual #141                // Method scala/collection/WithFilter.map:(Lscala/Function1;)Ljava/lang/Object;
        71: checkcast     #143                // class scala/collection/IterableOps
        74: invokedynamic #152,  0            // InvokeDynamic #2:apply:()Lscala/Function1;
        79: invokeinterface #153,  2          // InterfaceMethod scala/collection/IterableOps.withFilter:(Lscala/Function1;)Lscala/collection/WithFilter;
        84: invokedynamic #160,  0            // InvokeDynamic #3:apply:()Lscala/Function1;
        89: invokevirtual #141                // Method scala/collection/WithFilter.map:(Lscala/Function1;)Ljava/lang/Object;
        92: checkcast     #121                // class scala/collection/immutable/List
        95: astore_3
        96: goto          112
        99: goto          102
       102: new           #162                // class scala/MatchError
       105: dup
       106: aload         4
       108: invokespecial #166                // Method scala/MatchError."<init>":(Ljava/lang/Object;)V
       111: athrow
       112: aload_3
       113: areturn
      StackMapTable: number_of_entries = 5
        frame_type = 253 /* append */
          offset_delta = 22
          locals = [ top, class scala/Option ]
        frame_type = 2 /* same */
        frame_type = 251 /* same_frame_extended */
          offset_delta = 73
        frame_type = 2 /* same */
        frame_type = 255 /* full_frame */
          offset_delta = 9
          locals = [ class org/scalatest/Filter, class scala/collection/immutable/List, class scala/collection/immutable/Map, class scala/collection/immutable/List, class scala/Option ]
          stack = []
      LineNumberTable:
        line 60: 0
        line 61: 6
        line 62: 25
        line 64: 50
        line 62: 99
        line 60: 102
      LocalVariableTable:
        Start  Length  Slot  Name   Signature
           50      49     6 tagsToInclude   Lscala/collection/immutable/Set;
            0     114     0  this   Lorg/scalatest/Filter;
            0     114     1 testNamesAsList   Lscala/collection/immutable/List;
            0     114     2  tags   Lscala/collection/immutable/Map;
    Signature: #76                          // (Lscala/collection/immutable/List<Ljava/lang/String;>;Lscala/collection/immutable/Map<Ljava/lang/String;Lscala/collection/immutable/Set<Ljava/lang/String;>;>;)Lscala/collection/immutable/List<Ljava/lang/String;>;
    MethodParameters:
      Name                           Flags
      testNamesAsList                final
      tags                           final

  private void verifyPreconditionsForMethods(scala.collection.immutable.Set<java.lang.String>, scala.collection.immutable.Map<java.lang.String, scala.collection.immutable.Set<java.lang.String>>);
    descriptor: (Lscala/collection/immutable/Set;Lscala/collection/immutable/Map;)V
    flags: (0x0002) ACC_PRIVATE
    Code:
      stack=5, locals=9, args_size=3
         0: aload_2
         1: invokedynamic #181,  0            // InvokeDynamic #4:apply:()Lscala/Function1;
         6: invokeinterface #185,  2          // InterfaceMethod scala/collection/immutable/Map.find:(Lscala/Function1;)Lscala/Option;
        11: astore        4
        13: aload         4
        15: astore        5
        17: aload         5
        19: instanceof    #91                 // class scala/Some
        22: ifeq          90
        25: aload         5
        27: checkcast     #91                 // class scala/Some
        30: astore        6
        32: aload         6
        34: invokevirtual #95                 // Method scala/Some.value:()Ljava/lang/Object;
        37: checkcast     #187                // class scala/Tuple2
        40: astore        7
        42: aload         7
        44: ifnull        87
        47: aload         7
        49: invokevirtual #190                // Method scala/Tuple2._1:()Ljava/lang/Object;
        52: checkcast     #192                // class java/lang/String
        55: astore        8
        57: new           #194                // class java/lang/IllegalArgumentException
        60: dup
        61: new           #196                // class java/lang/StringBuilder
        64: dup
        65: ldc           #197                // int 60
        67: invokespecial #200                // Method java/lang/StringBuilder."<init>":(I)V
        70: aload         8
        72: invokevirtual #204                // Method java/lang/StringBuilder.append:(Ljava/lang/String;)Ljava/lang/StringBuilder;
        75: ldc           #206                // String  was associated with an empty set in the map passsed as tags
        77: invokevirtual #204                // Method java/lang/StringBuilder.append:(Ljava/lang/String;)Ljava/lang/StringBuilder;
        80: invokevirtual #210                // Method java/lang/StringBuilder.toString:()Ljava/lang/String;
        83: invokespecial #213                // Method java/lang/IllegalArgumentException."<init>":(Ljava/lang/String;)V
        86: athrow
        87: goto          93
        90: goto          93
        93: getstatic     #85                 // Field scala/None$.MODULE$:Lscala/None$;
        96: aload         5
        98: invokevirtual #89                 // Method java/lang/Object.equals:(Ljava/lang/Object;)Z
       101: ifeq          111
       104: getstatic     #219                // Field scala/runtime/BoxedUnit.UNIT:Lscala/runtime/BoxedUnit;
       107: astore_3
       108: goto          124
       111: goto          114
       114: new           #162                // class scala/MatchError
       117: dup
       118: aload         5
       120: invokespecial #166                // Method scala/MatchError."<init>":(Ljava/lang/Object;)V
       123: athrow
       124: return
      StackMapTable: number_of_entries = 6
        frame_type = 255 /* full_frame */
          offset_delta = 87
          locals = [ class org/scalatest/Filter, class scala/collection/immutable/Set, class scala/collection/immutable/Map, top, class scala/Option, class scala/Option, class scala/Some, class scala/Tuple2 ]
          stack = []
        frame_type = 249 /* chop */
          offset_delta = 2
        frame_type = 2 /* same */
        frame_type = 17 /* same */
        frame_type = 2 /* same */
        frame_type = 255 /* full_frame */
          offset_delta = 9
          locals = [ class org/scalatest/Filter, class scala/collection/immutable/Set, class scala/collection/immutable/Map, class scala/runtime/BoxedUnit, class scala/Option, class scala/Option ]
          stack = []
      LineNumberTable:
        line 72: 0
        line 73: 13
        line 74: 17
        line 75: 93
        line 73: 114
      LocalVariableTable:
        Start  Length  Slot  Name   Signature
           57      30     8 testName   Ljava/lang/String;
           13     111     4 testWithEmptyTagSet   Lscala/Option;
            0     125     0  this   Lorg/scalatest/Filter;
            0     125     1 testNames   Lscala/collection/immutable/Set;
            0     125     2  tags   Lscala/collection/immutable/Map;
    Signature: #175                         // (Lscala/collection/immutable/Set<Ljava/lang/String;>;Lscala/collection/immutable/Map<Ljava/lang/String;Lscala/collection/immutable/Set<Ljava/lang/String;>;>;)V
    MethodParameters:
      Name                           Flags
      testNames                      final
      tags                           final

  private scala.collection.immutable.Map<java.lang.String, scala.collection.immutable.Set<java.lang.String>> mergeTestTags(scala.collection.immutable.List<scala.collection.immutable.Map<java.lang.String, scala.collection.immutable.Set<java.lang.String>>>);
    descriptor: (Lscala/collection/immutable/List;)Lscala/collection/immutable/Map;
    flags: (0x0002) ACC_PRIVATE
    Code:
      stack=2, locals=3, args_size=2
         0: getstatic     #231                // Field scala/collection/mutable/Map$.MODULE$:Lscala/collection/mutable/Map$;
         3: getstatic     #236                // Field scala/collection/immutable/Nil$.MODULE$:Lscala/collection/immutable/Nil$;
         6: invokevirtual #239                // Method scala/collection/mutable/Map$.apply:(Lscala/collection/immutable/Seq;)Ljava/lang/Object;
         9: checkcast     #24                 // class scala/collection/MapOps
        12: aload_1
        13: invokevirtual #242                // Method scala/collection/immutable/List.head:()Ljava/lang/Object;
        16: checkcast     #244                // class scala/collection/IterableOnce
        19: invokeinterface #248,  2          // InterfaceMethod scala/collection/MapOps.$plus$plus:(Lscala/collection/IterableOnce;)Lscala/collection/IterableOps;
        24: checkcast     #250                // class scala/collection/mutable/Map
        27: astore_2
        28: aload_1
        29: invokevirtual #253                // Method scala/collection/immutable/List.tail:()Ljava/lang/Object;
        32: checkcast     #121                // class scala/collection/immutable/List
        35: aload_2
        36: invokedynamic #263,  0            // InvokeDynamic #5:apply:(Lscala/collection/mutable/Map;)Lscala/Function1;
        41: invokevirtual #267                // Method scala/collection/immutable/List.foreach:(Lscala/Function1;)V
        44: aload_2
        45: getstatic     #272                // Field scala/$less$colon$less$.MODULE$:Lscala/$less$colon$less$;
        48: invokevirtual #276                // Method scala/$less$colon$less$.refl:()Lscala/$eq$colon$eq;
        51: invokeinterface #280,  2          // InterfaceMethod scala/collection/mutable/Map.toMap:(Lscala/$less$colon$less;)Lscala/collection/immutable/Map;
        56: areturn
      LineNumberTable:
        line 80: 0
        line 81: 28
        line 92: 44
      LocalVariableTable:
        Start  Length  Slot  Name   Signature
           28      28     2 mergedTags   Lscala/collection/mutable/Map;
            0      57     0  this   Lorg/scalatest/Filter;
            0      57     1 testTagsList   Lscala/collection/immutable/List;
    Signature: #225                         // (Lscala/collection/immutable/List<Lscala/collection/immutable/Map<Ljava/lang/String;Lscala/collection/immutable/Set<Ljava/lang/String;>;>;>;)Lscala/collection/immutable/Map<Ljava/lang/String;Lscala/collection/immutable/Set<Ljava/lang/String;>;>;
    MethodParameters:
      Name                           Flags
      testTagsList                   final

  public scala.collection.immutable.Map<java.lang.String, scala.collection.immutable.Set<java.lang.String>> mergeTestDynamicTags(scala.collection.immutable.Map<java.lang.String, scala.collection.immutable.Set<java.lang.String>>, java.lang.String, scala.collection.immutable.Set<java.lang.String>);
    descriptor: (Lscala/collection/immutable/Map;Ljava/lang/String;Lscala/collection/immutable/Set;)Lscala/collection/immutable/Map;
    flags: (0x0001) ACC_PUBLIC
    Code:
      stack=7, locals=7, args_size=4
         0: aload_0
         1: invokevirtual #288                // Method dynaTags:()Lorg/scalatest/DynaTags;
         4: invokevirtual #294                // Method org/scalatest/DynaTags.testTags:()Lscala/collection/immutable/Map;
         7: aload_2
         8: invokeinterface #297,  2          // InterfaceMethod scala/collection/immutable/Map.isDefinedAt:(Ljava/lang/Object;)Z
        13: ifeq          35
        16: aload_0
        17: invokevirtual #288                // Method dynaTags:()Lorg/scalatest/DynaTags;
        20: invokevirtual #294                // Method org/scalatest/DynaTags.testTags:()Lscala/collection/immutable/Map;
        23: aload_2
        24: invokeinterface #299,  2          // InterfaceMethod scala/collection/immutable/Map.apply:(Ljava/lang/Object;)Ljava/lang/Object;
        29: checkcast     #172                // class scala/collection/immutable/Map
        32: goto          44
        35: getstatic     #304                // Field scala/Predef$.MODULE$:Lscala/Predef$;
        38: invokevirtual #308                // Method scala/Predef$.Map:()Lscala/collection/immutable/Map$;
        41: invokevirtual #313                // Method scala/collection/immutable/Map$.empty:()Lscala/collection/immutable/Map;
        44: astore        4
        46: aload_0
        47: invokevirtual #288                // Method dynaTags:()Lorg/scalatest/DynaTags;
        50: invokevirtual #316                // Method org/scalatest/DynaTags.suiteTags:()Lscala/collection/immutable/Map;
        53: aload_2
        54: invokeinterface #297,  2          // InterfaceMethod scala/collection/immutable/Map.isDefinedAt:(Ljava/lang/Object;)Z
        59: ifeq          122
        62: aload_0
        63: invokevirtual #288                // Method dynaTags:()Lorg/scalatest/DynaTags;
        66: invokevirtual #316                // Method org/scalatest/DynaTags.suiteTags:()Lscala/collection/immutable/Map;
        69: aload_2
        70: invokeinterface #299,  2          // InterfaceMethod scala/collection/immutable/Map.apply:(Ljava/lang/Object;)Ljava/lang/Object;
        75: checkcast     #97                 // class scala/collection/immutable/Set
        78: astore        6
        80: getstatic     #304                // Field scala/Predef$.MODULE$:Lscala/Predef$;
        83: invokevirtual #308                // Method scala/Predef$.Map:()Lscala/collection/immutable/Map$;
        86: getstatic     #236                // Field scala/collection/immutable/Nil$.MODULE$:Lscala/collection/immutable/Nil$;
        89: invokevirtual #317                // Method scala/collection/immutable/Map$.apply:(Lscala/collection/immutable/Seq;)Ljava/lang/Object;
        92: checkcast     #24                 // class scala/collection/MapOps
        95: aload_3
        96: aload         6
        98: invokedynamic #325,  0            // InvokeDynamic #6:apply:(Lscala/collection/immutable/Set;)Lscala/Function1;
       103: invokeinterface #326,  2          // InterfaceMethod scala/collection/immutable/Set.map:(Lscala/Function1;)Ljava/lang/Object;
       108: checkcast     #244                // class scala/collection/IterableOnce
       111: invokeinterface #248,  2          // InterfaceMethod scala/collection/MapOps.$plus$plus:(Lscala/collection/IterableOnce;)Lscala/collection/IterableOps;
       116: checkcast     #172                // class scala/collection/immutable/Map
       119: goto          131
       122: getstatic     #304                // Field scala/Predef$.MODULE$:Lscala/Predef$;
       125: invokevirtual #308                // Method scala/Predef$.Map:()Lscala/collection/immutable/Map$;
       128: invokevirtual #313                // Method scala/collection/immutable/Map$.empty:()Lscala/collection/immutable/Map;
       131: astore        5
       133: aload_0
       134: getstatic     #331                // Field scala/package$.MODULE$:Lscala/package$;
       137: invokevirtual #335                // Method scala/package$.List:()Lscala/collection/immutable/List$;
       140: getstatic     #340                // Field scala/runtime/ScalaRunTime$.MODULE$:Lscala/runtime/ScalaRunTime$;
       143: iconst_3
       144: anewarray     #172                // class scala/collection/immutable/Map
       147: dup
       148: iconst_0
       149: aload_1
       150: aastore
       151: dup
       152: iconst_1
       153: aload         4
       155: aastore
       156: dup
       157: iconst_2
       158: aload         5
       160: aastore
       161: checkcast     #342                // class "[Ljava/lang/Object;"
       164: invokevirtual #346                // Method scala/runtime/ScalaRunTime$.wrapRefArray:([Ljava/lang/Object;)Lscala/collection/immutable/ArraySeq;
       167: invokevirtual #349                // Method scala/collection/immutable/List$.apply:(Lscala/collection/immutable/Seq;)Ljava/lang/Object;
       170: checkcast     #121                // class scala/collection/immutable/List
       173: invokespecial #351                // Method mergeTestTags:(Lscala/collection/immutable/List;)Lscala/collection/immutable/Map;
       176: areturn
      StackMapTable: number_of_entries = 4
        frame_type = 35 /* same */
        frame_type = 72 /* same_locals_1_stack_item */
          stack = [ class scala/collection/immutable/Map ]
        frame_type = 252 /* append */
          offset_delta = 77
          locals = [ class scala/collection/immutable/Map ]
        frame_type = 72 /* same_locals_1_stack_item */
          stack = [ class scala/collection/immutable/Map ]
      LineNumberTable:
        line 97: 0
        line 98: 16
        line 100: 35
        line 103: 46
        line 104: 62
        line 105: 80
        line 108: 122
        line 110: 133
      LocalVariableTable:
        Start  Length  Slot  Name   Signature
           80      39     6 suiteTags   Lscala/collection/immutable/Set;
           46     130     4 dynaTestTags   Lscala/collection/immutable/Map;
          133      43     5 dynaSuiteTags   Lscala/collection/immutable/Map;
            0     177     0  this   Lorg/scalatest/Filter;
            0     177     1  tags   Lscala/collection/immutable/Map;
            0     177     2 suiteId   Ljava/lang/String;
            0     177     3 testNames   Lscala/collection/immutable/Set;
    Signature: #285                         // (Lscala/collection/immutable/Map<Ljava/lang/String;Lscala/collection/immutable/Set<Ljava/lang/String;>;>;Ljava/lang/String;Lscala/collection/immutable/Set<Ljava/lang/String;>;)Lscala/collection/immutable/Map<Ljava/lang/String;Lscala/collection/immutable/Set<Ljava/lang/String;>;>;
    MethodParameters:
      Name                           Flags
      tags                           final
      suiteId                        final
      testNames                      final

  public scala.collection.immutable.List<scala.Tuple2<java.lang.String, java.lang.Object>> apply(scala.collection.immutable.Set<java.lang.String>, scala.collection.immutable.Map<java.lang.String, scala.collection.immutable.Set<java.lang.String>>, java.lang.String);
    descriptor: (Lscala/collection/immutable/Set;Lscala/collection/immutable/Map;Ljava/lang/String;)Lscala/collection/immutable/List;
    flags: (0x0001) ACC_PUBLIC
    Code:
      stack=4, locals=7, args_size=4
         0: aload_0
         1: aload_2
         2: aload_3
         3: aload_1
         4: invokevirtual #357                // Method mergeTestDynamicTags:(Lscala/collection/immutable/Map;Ljava/lang/String;Lscala/collection/immutable/Set;)Lscala/collection/immutable/Map;
         7: astore        4
         9: aload_0
        10: aload_1
        11: aload         4
        13: invokespecial #359                // Method verifyPreconditionsForMethods:(Lscala/collection/immutable/Set;Lscala/collection/immutable/Map;)V
        16: aload_1
        17: invokeinterface #363,  1          // InterfaceMethod scala/collection/immutable/Set.toList:()Lscala/collection/immutable/List;
        22: astore        5
        24: aload_0
        25: aload         5
        27: aload         4
        29: invokespecial #365                // Method includedTestNames:(Lscala/collection/immutable/List;Lscala/collection/immutable/Map;)Lscala/collection/immutable/List;
        32: aload_0
        33: aload         4
        35: invokedynamic #373,  0            // InvokeDynamic #7:apply:(Lorg/scalatest/Filter;Lscala/collection/immutable/Map;)Lscala/Function1;
        40: invokevirtual #125                // Method scala/collection/immutable/List.withFilter:(Lscala/Function1;)Lscala/collection/WithFilter;
        43: aload         4
        45: invokedynamic #379,  0            // InvokeDynamic #8:apply:(Lscala/collection/immutable/Map;)Lscala/Function1;
        50: invokevirtual #141                // Method scala/collection/WithFilter.map:(Lscala/Function1;)Ljava/lang/Object;
        53: checkcast     #121                // class scala/collection/immutable/List
        56: astore        6
        58: aload         6
        60: areturn
      LineNumberTable:
        line 143: 0
        line 144: 9
        line 146: 16
        line 149: 24
        line 155: 58
      LocalVariableTable:
        Start  Length  Slot  Name   Signature
            9      51     4 testTags   Lscala/collection/immutable/Map;
           24      36     5 testNamesAsList   Lscala/collection/immutable/List;
           58       2     6 filtered   Lscala/collection/immutable/List;
            0      61     0  this   Lorg/scalatest/Filter;
            0      61     1 testNames   Lscala/collection/immutable/Set;
            0      61     2  tags   Lscala/collection/immutable/Map;
            0      61     3 suiteId   Ljava/lang/String;
    Signature: #355                         // (Lscala/collection/immutable/Set<Ljava/lang/String;>;Lscala/collection/immutable/Map<Ljava/lang/String;Lscala/collection/immutable/Set<Ljava/lang/String;>;>;Ljava/lang/String;)Lscala/collection/immutable/List<Lscala/Tuple2<Ljava/lang/String;Ljava/lang/Object;>;>;
    MethodParameters:
      Name                           Flags
      testNames                      final
      tags                           final
      suiteId                        final

  public scala.Tuple2<java.lang.Object, java.lang.Object> apply(java.lang.String, scala.collection.immutable.Map<java.lang.String, scala.collection.immutable.Set<java.lang.String>>, java.lang.String);
    descriptor: (Ljava/lang/String;Lscala/collection/immutable/Map;Ljava/lang/String;)Lscala/Tuple2;
    flags: (0x0001) ACC_PUBLIC
    Code:
      stack=9, locals=6, args_size=4
         0: aload_0
         1: aload_2
         2: aload_3
         3: getstatic     #304                // Field scala/Predef$.MODULE$:Lscala/Predef$;
         6: invokevirtual #386                // Method scala/Predef$.Set:()Lscala/collection/immutable/Set$;
         9: getstatic     #340                // Field scala/runtime/ScalaRunTime$.MODULE$:Lscala/runtime/ScalaRunTime$;
        12: iconst_1
        13: anewarray     #192                // class java/lang/String
        16: dup
        17: iconst_0
        18: aload_1
        19: aastore
        20: checkcast     #342                // class "[Ljava/lang/Object;"
        23: invokevirtual #346                // Method scala/runtime/ScalaRunTime$.wrapRefArray:([Ljava/lang/Object;)Lscala/collection/immutable/ArraySeq;
        26: invokevirtual #389                // Method scala/collection/immutable/Set$.apply:(Lscala/collection/immutable/Seq;)Ljava/lang/Object;
        29: checkcast     #97                 // class scala/collection/immutable/Set
        32: invokevirtual #357                // Method mergeTestDynamicTags:(Lscala/collection/immutable/Map;Ljava/lang/String;Lscala/collection/immutable/Set;)Lscala/collection/immutable/Map;
        35: astore        4
        37: aload_0
        38: getstatic     #304                // Field scala/Predef$.MODULE$:Lscala/Predef$;
        41: invokevirtual #386                // Method scala/Predef$.Set:()Lscala/collection/immutable/Set$;
        44: getstatic     #340                // Field scala/runtime/ScalaRunTime$.MODULE$:Lscala/runtime/ScalaRunTime$;
        47: iconst_1
        48: anewarray     #192                // class java/lang/String
        51: dup
        52: iconst_0
        53: aload_1
        54: aastore
        55: checkcast     #342                // class "[Ljava/lang/Object;"
        58: invokevirtual #346                // Method scala/runtime/ScalaRunTime$.wrapRefArray:([Ljava/lang/Object;)Lscala/collection/immutable/ArraySeq;
        61: invokevirtual #389                // Method scala/collection/immutable/Set$.apply:(Lscala/collection/immutable/Seq;)Ljava/lang/Object;
        64: checkcast     #97                 // class scala/collection/immutable/Set
        67: aload         4
        69: invokespecial #393                // Method impl$1:(Lscala/collection/immutable/Set;Lscala/collection/immutable/Map;)Lscala/collection/immutable/List;
        72: astore        5
        74: aload         5
        76: invokevirtual #396                // Method scala/collection/immutable/List.isEmpty:()Z
        79: ifeq          94
        82: new           #398                // class scala/Tuple2$mcZZ$sp
        85: dup
        86: iconst_1
        87: iconst_0
        88: invokespecial #401                // Method scala/Tuple2$mcZZ$sp."<init>":(ZZ)V
        91: goto          113
        94: new           #398                // class scala/Tuple2$mcZZ$sp
        97: dup
        98: iconst_0
        99: aload         5
       101: invokevirtual #242                // Method scala/collection/immutable/List.head:()Ljava/lang/Object;
       104: checkcast     #187                // class scala/Tuple2
       107: invokevirtual #404                // Method scala/Tuple2._2$mcZ$sp:()Z
       110: invokespecial #401                // Method scala/Tuple2$mcZZ$sp."<init>":(ZZ)V
       113: areturn
      StackMapTable: number_of_entries = 2
        frame_type = 253 /* append */
          offset_delta = 94
          locals = [ class scala/collection/immutable/Map, class scala/collection/immutable/List ]
        frame_type = 82 /* same_locals_1_stack_item */
          stack = [ class scala/Tuple2$mcZZ$sp ]
      LineNumberTable:
        line 191: 0
        line 209: 37
        line 211: 74
        line 212: 82
        line 214: 94
      LocalVariableTable:
        Start  Length  Slot  Name   Signature
           37      76     4 testTags   Lscala/collection/immutable/Map;
           74      39     5  list   Lscala/collection/immutable/List;
            0     114     0  this   Lorg/scalatest/Filter;
            0     114     1 testName   Ljava/lang/String;
            0     114     2  tags   Lscala/collection/immutable/Map;
            0     114     3 suiteId   Ljava/lang/String;
    Signature: #382                         // (Ljava/lang/String;Lscala/collection/immutable/Map<Ljava/lang/String;Lscala/collection/immutable/Set<Ljava/lang/String;>;>;Ljava/lang/String;)Lscala/Tuple2<Ljava/lang/Object;Ljava/lang/Object;>;
    MethodParameters:
      Name                           Flags
      testName                       final
      tags                           final
      suiteId                        final

  public int runnableTestCount(scala.collection.immutable.Set<java.lang.String>, scala.collection.immutable.Map<java.lang.String, scala.collection.immutable.Set<java.lang.String>>, java.lang.String);
    descriptor: (Lscala/collection/immutable/Set;Lscala/collection/immutable/Map;Ljava/lang/String;)I
    flags: (0x0001) ACC_PUBLIC
    Code:
      stack=4, locals=7, args_size=4
         0: aload_0
         1: aload_2
         2: aload_3
         3: aload_1
         4: invokevirtual #357                // Method mergeTestDynamicTags:(Lscala/collection/immutable/Map;Ljava/lang/String;Lscala/collection/immutable/Set;)Lscala/collection/immutable/Map;
         7: astore        4
         9: aload_0
        10: aload_1
        11: aload         4
        13: invokespecial #359                // Method verifyPreconditionsForMethods:(Lscala/collection/immutable/Set;Lscala/collection/immutable/Map;)V
        16: aload_1
        17: invokeinterface #363,  1          // InterfaceMethod scala/collection/immutable/Set.toList:()Lscala/collection/immutable/List;
        22: astore        5
        24: aload_0
        25: aload         5
        27: aload         4
        29: invokespecial #365                // Method includedTestNames:(Lscala/collection/immutable/List;Lscala/collection/immutable/Map;)Lscala/collection/immutable/List;
        32: aload_0
        33: aload         4
        35: invokedynamic #413,  0            // InvokeDynamic #9:apply:(Lorg/scalatest/Filter;Lscala/collection/immutable/Map;)Lscala/Function1;
        40: invokevirtual #125                // Method scala/collection/immutable/List.withFilter:(Lscala/Function1;)Lscala/collection/WithFilter;
        43: invokedynamic #420,  0            // InvokeDynamic #10:apply:()Lscala/Function1;
        48: invokevirtual #141                // Method scala/collection/WithFilter.map:(Lscala/Function1;)Ljava/lang/Object;
        51: checkcast     #121                // class scala/collection/immutable/List
        54: astore        6
        56: aload         6
        58: invokevirtual #424                // Method scala/collection/immutable/List.size:()I
        61: ireturn
      LineNumberTable:
        line 235: 0
        line 236: 9
        line 238: 16
        line 241: 24
        line 245: 56
      LocalVariableTable:
        Start  Length  Slot  Name   Signature
            9      52     4  tags   Lscala/collection/immutable/Map;
           24      37     5 testNamesAsList   Lscala/collection/immutable/List;
           56       5     6 runnableTests   Lscala/collection/immutable/List;
            0      62     0  this   Lorg/scalatest/Filter;
            0      62     1 testNames   Lscala/collection/immutable/Set;
            0      62     2 testTags   Lscala/collection/immutable/Map;
            0      62     3 suiteId   Ljava/lang/String;
    Signature: #408                         // (Lscala/collection/immutable/Set<Ljava/lang/String;>;Lscala/collection/immutable/Map<Ljava/lang/String;Lscala/collection/immutable/Set<Ljava/lang/String;>;>;Ljava/lang/String;)I
    MethodParameters:
      Name                           Flags
      testNames                      final
      testTags                       final
      suiteId                        final

  public static final boolean $anonfun$includedTestNames$1(scala.collection.immutable.Map, java.lang.String);
    descriptor: (Lscala/collection/immutable/Map;Ljava/lang/String;)Z
    flags: (0x1019) ACC_PUBLIC, ACC_STATIC, ACC_FINAL, ACC_SYNTHETIC
    Code:
      stack=2, locals=2, args_size=2
         0: aload_0
         1: aload_1
         2: invokeinterface #431,  2          // InterfaceMethod scala/collection/immutable/Map.contains:(Ljava/lang/Object;)Z
         7: ireturn
      LineNumberTable:
        line 65: 0
      LocalVariableTable:
        Start  Length  Slot  Name   Signature
            0       8     0 tags$1   Lscala/collection/immutable/Map;
            0       8     1 testName   Ljava/lang/String;
    MethodParameters:
      Name                           Flags
      tags$1                         final
      testName                       final

  public static final scala.Tuple2 $anonfun$includedTestNames$2(scala.collection.immutable.Set, scala.collection.immutable.Map, java.lang.String);
    descriptor: (Lscala/collection/immutable/Set;Lscala/collection/immutable/Map;Ljava/lang/String;)Lscala/Tuple2;
    flags: (0x1019) ACC_PUBLIC, ACC_STATIC, ACC_FINAL, ACC_SYNTHETIC
    Code:
      stack=4, locals=4, args_size=3
         0: aload_0
         1: aload_1
         2: aload_2
         3: invokeinterface #299,  2          // InterfaceMethod scala/collection/immutable/Map.apply:(Ljava/lang/Object;)Ljava/lang/Object;
         8: checkcast     #434                // class scala/collection/Set
        11: invokeinterface #438,  2          // InterfaceMethod scala/collection/immutable/Set.intersect:(Lscala/collection/Set;)Lscala/collection/SetOps;
        16: checkcast     #97                 // class scala/collection/immutable/Set
        19: astore_3
        20: new           #187                // class scala/Tuple2
        23: dup
        24: aload_2
        25: aload_3
        26: invokespecial #441                // Method scala/Tuple2."<init>":(Ljava/lang/Object;Ljava/lang/Object;)V
        29: areturn
      LineNumberTable:
        line 66: 0
        line 64: 20
        line 66: 25
      LocalVariableTable:
        Start  Length  Slot  Name   Signature
           20       9     3 intersection   Lscala/collection/immutable/Set;
            0      30     0 tagsToInclude$1   Lscala/collection/immutable/Set;
            0      30     1 tags$1   Lscala/collection/immutable/Map;
            0      30     2 testName   Ljava/lang/String;
    MethodParameters:
      Name                           Flags
      tagsToInclude$1                final
      tags$1                         final
      testName                       final

  public static final boolean $anonfun$includedTestNames$3(scala.Tuple2);
    descriptor: (Lscala/Tuple2;)Z
    flags: (0x1019) ACC_PUBLIC, ACC_STATIC, ACC_FINAL, ACC_SYNTHETIC
    Code:
      stack=3, locals=4, args_size=1
         0: aload_0
         1: astore_2
         2: aload_2
         3: ifnull        33
         6: aload_2
         7: invokevirtual #448                // Method scala/Tuple2._2:()Ljava/lang/Object;
        10: checkcast     #97                 // class scala/collection/immutable/Set
        13: astore_3
        14: aload_3
        15: invokeinterface #449,  1          // InterfaceMethod scala/collection/immutable/Set.size:()I
        20: iconst_0
        21: if_icmple     28
        24: iconst_1
        25: goto          29
        28: iconst_0
        29: istore_1
        30: goto          45
        33: goto          36
        36: new           #162                // class scala/MatchError
        39: dup
        40: aload_2
        41: invokespecial #166                // Method scala/MatchError."<init>":(Ljava/lang/Object;)V
        44: athrow
        45: iload_1
        46: ireturn
      StackMapTable: number_of_entries = 5
        frame_type = 254 /* append */
          offset_delta = 28
          locals = [ top, class scala/Tuple2, class scala/collection/immutable/Set ]
        frame_type = 64 /* same_locals_1_stack_item */
          stack = [ int ]
        frame_type = 250 /* chop */
          offset_delta = 3
        frame_type = 2 /* same */
        frame_type = 255 /* full_frame */
          offset_delta = 8
          locals = [ class scala/Tuple2, int, class scala/Tuple2, class scala/collection/immutable/Set ]
          stack = []
      LineNumberTable:
        line 64: 0
        line 66: 6
        line 67: 14
        line 64: 33
      LocalVariableTable:
        Start  Length  Slot  Name   Signature
           14      19     3 intersection   Lscala/collection/immutable/Set;
            0      47     0   x$1   Lscala/Tuple2;
    MethodParameters:
      Name                           Flags
      x$1                            final

  public static final java.lang.String $anonfun$includedTestNames$4(scala.Tuple2);
    descriptor: (Lscala/Tuple2;)Ljava/lang/String;
    flags: (0x1019) ACC_PUBLIC, ACC_STATIC, ACC_FINAL, ACC_SYNTHETIC
    Code:
      stack=3, locals=4, args_size=1
         0: aload_0
         1: astore_2
         2: aload_2
         3: ifnull        19
         6: aload_2
         7: invokevirtual #190                // Method scala/Tuple2._1:()Ljava/lang/Object;
        10: checkcast     #192                // class java/lang/String
        13: astore_3
        14: aload_3
        15: astore_1
        16: goto          31
        19: goto          22
        22: new           #162                // class scala/MatchError
        25: dup
        26: aload_2
        27: invokespecial #166                // Method scala/MatchError."<init>":(Ljava/lang/Object;)V
        30: athrow
        31: aload_1
        32: areturn
      StackMapTable: number_of_entries = 3
        frame_type = 253 /* append */
          offset_delta = 19
          locals = [ top, class scala/Tuple2 ]
        frame_type = 2 /* same */
        frame_type = 255 /* full_frame */
          offset_delta = 8
          locals = [ class scala/Tuple2, class java/lang/String, class scala/Tuple2, class java/lang/String ]
          stack = []
      LineNumberTable:
        line 64: 0
        line 68: 14
        line 64: 19
      LocalVariableTable:
        Start  Length  Slot  Name   Signature
           14       5     3 testName   Ljava/lang/String;
            0      33     0   x$2   Lscala/Tuple2;
    MethodParameters:
      Name                           Flags
      x$2                            final

  public static final boolean $anonfun$verifyPreconditionsForMethods$1(scala.Tuple2);
    descriptor: (Lscala/Tuple2;)Z
    flags: (0x1019) ACC_PUBLIC, ACC_STATIC, ACC_FINAL, ACC_SYNTHETIC
    Code:
      stack=1, locals=1, args_size=1
         0: aload_0
         1: invokevirtual #448                // Method scala/Tuple2._2:()Ljava/lang/Object;
         4: checkcast     #455                // class scala/collection/IterableOnceOps
         7: invokeinterface #456,  1          // InterfaceMethod scala/collection/IterableOnceOps.isEmpty:()Z
        12: ireturn
      LineNumberTable:
        line 72: 0
      LocalVariableTable:
        Start  Length  Slot  Name   Signature
            0      13     0 tuple   Lscala/Tuple2;
    MethodParameters:
      Name                           Flags
      tuple                          final

  public static final boolean $anonfun$mergeTestTags$2(scala.Tuple2);
    descriptor: (Lscala/Tuple2;)Z
    flags: (0x1019) ACC_PUBLIC, ACC_STATIC, ACC_FINAL, ACC_SYNTHETIC
    Code:
      stack=1, locals=3, args_size=1
         0: aload_0
         1: astore_2
         2: aload_2
         3: ifnull        11
         6: iconst_1
         7: istore_1
         8: goto          19
        11: goto          14
        14: iconst_0
        15: istore_1
        16: goto          19
        19: iload_1
        20: ireturn
      StackMapTable: number_of_entries = 3
        frame_type = 253 /* append */
          offset_delta = 11
          locals = [ top, class scala/Tuple2 ]
        frame_type = 2 /* same */
        frame_type = 255 /* full_frame */
          offset_delta = 4
          locals = [ class scala/Tuple2, int, class scala/Tuple2 ]
          stack = []
      LineNumberTable:
        line 82: 0
      LocalVariableTable:
        Start  Length  Slot  Name   Signature
            0      21     0 check$ifrefutable$1   Lscala/Tuple2;
    MethodParameters:
      Name                           Flags
      check$ifrefutable$1            final

  public static final java.lang.Object $anonfun$mergeTestTags$3(scala.collection.mutable.Map, scala.Tuple2);
    descriptor: (Lscala/collection/mutable/Map;Lscala/Tuple2;)Ljava/lang/Object;
    flags: (0x1019) ACC_PUBLIC, ACC_STATIC, ACC_FINAL, ACC_SYNTHETIC
    Code:
      stack=5, locals=11, args_size=2
         0: aload_1
         1: astore        4
         3: aload         4
         5: ifnull        144
         8: aload         4
        10: invokevirtual #190                // Method scala/Tuple2._1:()Ljava/lang/Object;
        13: checkcast     #192                // class java/lang/String
        16: astore        5
        18: aload         4
        20: invokevirtual #448                // Method scala/Tuple2._2:()Ljava/lang/Object;
        23: checkcast     #97                 // class scala/collection/immutable/Set
        26: astore        6
        28: aload_0
        29: aload         5
        31: invokeinterface #466,  2          // InterfaceMethod scala/collection/mutable/Map.get:(Ljava/lang/Object;)Lscala/Option;
        36: astore        7
        38: aload         7
        40: astore        8
        42: aload         8
        44: instanceof    #91                 // class scala/Some
        47: ifeq          91
        50: aload         8
        52: checkcast     #91                 // class scala/Some
        55: astore        9
        57: aload         9
        59: invokevirtual #95                 // Method scala/Some.value:()Ljava/lang/Object;
        62: checkcast     #97                 // class scala/collection/immutable/Set
        65: astore        10
        67: aload_0
        68: aload         5
        70: aload         10
        72: aload         6
        74: invokeinterface #469,  2          // InterfaceMethod scala/collection/immutable/Set.$plus$plus:(Lscala/collection/IterableOnce;)Lscala/collection/SetOps;
        79: invokeinterface #472,  3          // InterfaceMethod scala/collection/mutable/Map.update:(Ljava/lang/Object;Ljava/lang/Object;)V
        84: getstatic     #219                // Field scala/runtime/BoxedUnit.UNIT:Lscala/runtime/BoxedUnit;
        87: astore_3
        88: goto          139
        91: goto          94
        94: getstatic     #85                 // Field scala/None$.MODULE$:Lscala/None$;
        97: aload         8
        99: invokevirtual #89                 // Method java/lang/Object.equals:(Ljava/lang/Object;)Z
       102: ifeq          126
       105: aload_0
       106: new           #187                // class scala/Tuple2
       109: dup
       110: aload         5
       112: aload         6
       114: invokespecial #441                // Method scala/Tuple2."<init>":(Ljava/lang/Object;Ljava/lang/Object;)V
       117: invokeinterface #476,  2          // InterfaceMethod scala/collection/mutable/Map.$plus$eq:(Ljava/lang/Object;)Lscala/collection/mutable/Growable;
       122: astore_3
       123: goto          139
       126: goto          129
       129: new           #162                // class scala/MatchError
       132: dup
       133: aload         8
       135: invokespecial #166                // Method scala/MatchError."<init>":(Ljava/lang/Object;)V
       138: athrow
       139: aload_3
       140: astore_2
       141: goto          157
       144: goto          147
       147: new           #162                // class scala/MatchError
       150: dup
       151: aload         4
       153: invokespecial #166                // Method scala/MatchError."<init>":(Ljava/lang/Object;)V
       156: athrow
       157: aload_2
       158: areturn
      StackMapTable: number_of_entries = 8
        frame_type = 255 /* full_frame */
          offset_delta = 91
          locals = [ class scala/collection/mutable/Map, class scala/Tuple2, top, top, class scala/Tuple2, class java/lang/String, class scala/collection/immutable/Set, class scala/Option, class scala/Option ]
          stack = []
        frame_type = 2 /* same */
        frame_type = 31 /* same */
        frame_type = 2 /* same */
        frame_type = 255 /* full_frame */
          offset_delta = 9
          locals = [ class scala/collection/mutable/Map, class scala/Tuple2, top, class java/lang/Object, class scala/Tuple2, class java/lang/String, class scala/collection/immutable/Set, class scala/Option, class scala/Option ]
          stack = []
        frame_type = 255 /* full_frame */
          offset_delta = 4
          locals = [ class scala/collection/mutable/Map, class scala/Tuple2, top, top, class scala/Tuple2 ]
          stack = []
        frame_type = 2 /* same */
        frame_type = 255 /* full_frame */
          offset_delta = 9
          locals = [ class scala/collection/mutable/Map, class scala/Tuple2, class java/lang/Object, class java/lang/Object, class scala/Tuple2, class java/lang/String, class scala/collection/immutable/Set, class scala/Option, class scala/Option ]
          stack = []
      LineNumberTable:
        line 82: 0
        line 83: 28
        line 84: 38
        line 85: 42
        line 86: 67
        line 85: 91
        line 87: 94
        line 88: 105
        line 87: 126
        line 84: 129
        line 82: 144
      LocalVariableTable:
        Start  Length  Slot  Name   Signature
           67      24    10 existingTagSet   Lscala/collection/immutable/Set;
           38     102     7 existingTagSetOpt   Lscala/Option;
           18     126     5 testName   Ljava/lang/String;
           28     116     6 tagSet   Lscala/collection/immutable/Set;
            0     159     0 mergedTags$1   Lscala/collection/mutable/Map;
            0     159     1   x$3   Lscala/Tuple2;
    MethodParameters:
      Name                           Flags
      mergedTags$1                   final
      x$3                            final

  public static final void $anonfun$mergeTestTags$1(scala.collection.mutable.Map, scala.collection.immutable.Map);
    descriptor: (Lscala/collection/mutable/Map;Lscala/collection/immutable/Map;)V
    flags: (0x1019) ACC_PUBLIC, ACC_STATIC, ACC_FINAL, ACC_SYNTHETIC
    Code:
      stack=2, locals=2, args_size=2
         0: aload_1
         1: invokedynamic #486,  0            // InvokeDynamic #11:apply:()Lscala/Function1;
         6: invokeinterface #489,  2          // InterfaceMethod scala/collection/immutable/Map.withFilter:(Lscala/Function1;)Lscala/collection/MapOps$WithFilter;
        11: aload_0
        12: invokedynamic #493,  0            // InvokeDynamic #12:apply:(Lscala/collection/mutable/Map;)Lscala/Function1;
        17: invokevirtual #494                // Method scala/collection/MapOps$WithFilter.foreach:(Lscala/Function1;)V
        20: return
      LineNumberTable:
        line 82: 0
      LocalVariableTable:
        Start  Length  Slot  Name   Signature
            0      21     0 mergedTags$1   Lscala/collection/mutable/Map;
            0      21     1 testTags   Lscala/collection/immutable/Map;
    MethodParameters:
      Name                           Flags
      mergedTags$1                   final
      testTags                       final

  public static final scala.Tuple2 $anonfun$mergeTestDynamicTags$1(scala.collection.immutable.Set, java.lang.String);
    descriptor: (Lscala/collection/immutable/Set;Ljava/lang/String;)Lscala/Tuple2;
    flags: (0x1019) ACC_PUBLIC, ACC_STATIC, ACC_FINAL, ACC_SYNTHETIC
    Code:
      stack=4, locals=2, args_size=2
         0: new           #187                // class scala/Tuple2
         3: dup
         4: aload_1
         5: aload_0
         6: invokespecial #441                // Method scala/Tuple2."<init>":(Ljava/lang/Object;Ljava/lang/Object;)V
         9: areturn
      LineNumberTable:
        line 105: 0
      LocalVariableTable:
        Start  Length  Slot  Name   Signature
            0      10     0 suiteTags$1   Lscala/collection/immutable/Set;
            0      10     1    tn   Ljava/lang/String;
    MethodParameters:
      Name                           Flags
      suiteTags$1                    final
      tn                             final

  public static final boolean $anonfun$apply$1(org.scalatest.Filter, scala.collection.immutable.Map, java.lang.String);
    descriptor: (Lorg/scalatest/Filter;Lscala/collection/immutable/Map;Ljava/lang/String;)Z
    flags: (0x1019) ACC_PUBLIC, ACC_STATIC, ACC_FINAL, ACC_SYNTHETIC
    Code:
      stack=3, locals=3, args_size=3
         0: aload_1
         1: aload_2
         2: invokeinterface #431,  2          // InterfaceMethod scala/collection/immutable/Map.contains:(Ljava/lang/Object;)Z
         7: ifeq          97
        10: aload_1
        11: aload_2
        12: invokeinterface #299,  2          // InterfaceMethod scala/collection/immutable/Map.apply:(Ljava/lang/Object;)Ljava/lang/Object;
        17: checkcast     #502                // class scala/collection/SetOps
        20: ldc_w         #504                // String org.scalatest.Ignore
        23: invokeinterface #505,  2          // InterfaceMethod scala/collection/SetOps.contains:(Ljava/lang/Object;)Z
        28: ifeq          70
        31: aload_1
        32: aload_2
        33: invokeinterface #299,  2          // InterfaceMethod scala/collection/immutable/Map.apply:(Ljava/lang/Object;)Ljava/lang/Object;
        38: checkcast     #502                // class scala/collection/SetOps
        41: aload_0
        42: invokevirtual #507                // Method tagsToExclude:()Lscala/collection/immutable/Set;
        45: ldc_w         #504                // String org.scalatest.Ignore
        48: invokeinterface #511,  2          // InterfaceMethod scala/collection/immutable/Set.$plus:(Ljava/lang/Object;)Lscala/collection/immutable/SetOps;
        53: checkcast     #434                // class scala/collection/Set
        56: invokeinterface #512,  2          // InterfaceMethod scala/collection/SetOps.intersect:(Lscala/collection/Set;)Lscala/collection/SetOps;
        61: invokeinterface #513,  1          // InterfaceMethod scala/collection/SetOps.size:()I
        66: iconst_1
        67: if_icmpeq     97
        70: aload_1
        71: aload_2
        72: invokeinterface #299,  2          // InterfaceMethod scala/collection/immutable/Map.apply:(Ljava/lang/Object;)Ljava/lang/Object;
        77: checkcast     #502                // class scala/collection/SetOps
        80: aload_0
        81: invokevirtual #507                // Method tagsToExclude:()Lscala/collection/immutable/Set;
        84: invokeinterface #512,  2          // InterfaceMethod scala/collection/SetOps.intersect:(Lscala/collection/Set;)Lscala/collection/SetOps;
        89: invokeinterface #514,  1          // InterfaceMethod scala/collection/SetOps.isEmpty:()Z
        94: ifeq          101
        97: iconst_1
        98: goto          102
       101: iconst_0
       102: ireturn
      StackMapTable: number_of_entries = 4
        frame_type = 251 /* same_frame_extended */
          offset_delta = 70
        frame_type = 26 /* same */
        frame_type = 3 /* same */
        frame_type = 64 /* same_locals_1_stack_item */
          stack = [ int ]
      LineNumberTable:
        line 150: 0
        line 151: 10
        line 152: 70
      LocalVariableTable:
        Start  Length  Slot  Name   Signature
            0     103     0 $this   Lorg/scalatest/Filter;
            0     103     1 testTags$1   Lscala/collection/immutable/Map;
            0     103     2 testName   Ljava/lang/String;
    MethodParameters:
      Name                           Flags
      $this                          final synthetic
      testTags$1                     final
      testName                       final

  public static final scala.Tuple2 $anonfun$apply$2(scala.collection.immutable.Map, java.lang.String);
    descriptor: (Lscala/collection/immutable/Map;Ljava/lang/String;)Lscala/Tuple2;
    flags: (0x1019) ACC_PUBLIC, ACC_STATIC, ACC_FINAL, ACC_SYNTHETIC
    Code:
      stack=5, locals=2, args_size=2
         0: new           #187                // class scala/Tuple2
         3: dup
         4: aload_1
         5: aload_0
         6: aload_1
         7: invokeinterface #431,  2          // InterfaceMethod scala/collection/immutable/Map.contains:(Ljava/lang/Object;)Z
        12: ifeq          40
        15: aload_0
        16: aload_1
        17: invokeinterface #299,  2          // InterfaceMethod scala/collection/immutable/Map.apply:(Ljava/lang/Object;)Ljava/lang/Object;
        22: checkcast     #502                // class scala/collection/SetOps
        25: ldc_w         #504                // String org.scalatest.Ignore
        28: invokeinterface #505,  2          // InterfaceMethod scala/collection/SetOps.contains:(Ljava/lang/Object;)Z
        33: ifeq          40
        36: iconst_1
        37: goto          41
        40: iconst_0
        41: invokestatic  #520                // Method scala/runtime/BoxesRunTime.boxToBoolean:(Z)Ljava/lang/Boolean;
        44: invokespecial #441                // Method scala/Tuple2."<init>":(Ljava/lang/Object;Ljava/lang/Object;)V
        47: areturn
      StackMapTable: number_of_entries = 2
        frame_type = 255 /* full_frame */
          offset_delta = 40
          locals = [ class scala/collection/immutable/Map, class java/lang/String ]
          stack = [ uninitialized 0, uninitialized 0, class java/lang/String ]
        frame_type = 255 /* full_frame */
          offset_delta = 0
          locals = [ class scala/collection/immutable/Map, class java/lang/String ]
          stack = [ uninitialized 0, uninitialized 0, class java/lang/String, int ]
      LineNumberTable:
        line 153: 0
      LocalVariableTable:
        Start  Length  Slot  Name   Signature
            0      48     0 testTags$1   Lscala/collection/immutable/Map;
            0      48     1 testName   Ljava/lang/String;
    MethodParameters:
      Name                           Flags
      testTags$1                     final
      testName                       final

  public static final boolean $anonfun$apply$3(org.scalatest.Filter, scala.collection.immutable.Map, java.lang.String);
    descriptor: (Lorg/scalatest/Filter;Lscala/collection/immutable/Map;Ljava/lang/String;)Z
    flags: (0x1019) ACC_PUBLIC, ACC_STATIC, ACC_FINAL, ACC_SYNTHETIC
    Code:
      stack=3, locals=3, args_size=3
         0: aload_1
         1: aload_2
         2: invokeinterface #431,  2          // InterfaceMethod scala/collection/immutable/Map.contains:(Ljava/lang/Object;)Z
         7: ifeq          97
        10: aload_1
        11: aload_2
        12: invokeinterface #299,  2          // InterfaceMethod scala/collection/immutable/Map.apply:(Ljava/lang/Object;)Ljava/lang/Object;
        17: checkcast     #502                // class scala/collection/SetOps
        20: ldc_w         #504                // String org.scalatest.Ignore
        23: invokeinterface #505,  2          // InterfaceMethod scala/collection/SetOps.contains:(Ljava/lang/Object;)Z
        28: ifeq          70
        31: aload_1
        32: aload_2
        33: invokeinterface #299,  2          // InterfaceMethod scala/collection/immutable/Map.apply:(Ljava/lang/Object;)Ljava/lang/Object;
        38: checkcast     #502                // class scala/collection/SetOps
        41: aload_0
        42: invokevirtual #507                // Method tagsToExclude:()Lscala/collection/immutable/Set;
        45: ldc_w         #504                // String org.scalatest.Ignore
        48: invokeinterface #511,  2          // InterfaceMethod scala/collection/immutable/Set.$plus:(Ljava/lang/Object;)Lscala/collection/immutable/SetOps;
        53: checkcast     #434                // class scala/collection/Set
        56: invokeinterface #512,  2          // InterfaceMethod scala/collection/SetOps.intersect:(Lscala/collection/Set;)Lscala/collection/SetOps;
        61: invokeinterface #513,  1          // InterfaceMethod scala/collection/SetOps.size:()I
        66: iconst_1
        67: if_icmpeq     97
        70: aload_1
        71: aload_2
        72: invokeinterface #299,  2          // InterfaceMethod scala/collection/immutable/Map.apply:(Ljava/lang/Object;)Ljava/lang/Object;
        77: checkcast     #502                // class scala/collection/SetOps
        80: aload_0
        81: invokevirtual #507                // Method tagsToExclude:()Lscala/collection/immutable/Set;
        84: invokeinterface #512,  2          // InterfaceMethod scala/collection/SetOps.intersect:(Lscala/collection/Set;)Lscala/collection/SetOps;
        89: invokeinterface #514,  1          // InterfaceMethod scala/collection/SetOps.isEmpty:()Z
        94: ifeq          101
        97: iconst_1
        98: goto          102
       101: iconst_0
       102: ireturn
      StackMapTable: number_of_entries = 4
        frame_type = 251 /* same_frame_extended */
          offset_delta = 70
        frame_type = 26 /* same */
        frame_type = 3 /* same */
        frame_type = 64 /* same_locals_1_stack_item */
          stack = [ int ]
      LineNumberTable:
        line 201: 0
        line 202: 10
        line 203: 70
      LocalVariableTable:
        Start  Length  Slot  Name   Signature
            0     103     0 $this   Lorg/scalatest/Filter;
            0     103     1 tags$2   Lscala/collection/immutable/Map;
            0     103     2 testName   Ljava/lang/String;
    MethodParameters:
      Name                           Flags
      $this                          final synthetic
      tags$2                         final
      testName                       final

  public static final scala.Tuple2 $anonfun$apply$4(scala.collection.immutable.Map, java.lang.String);
    descriptor: (Lscala/collection/immutable/Map;Ljava/lang/String;)Lscala/Tuple2;
    flags: (0x1019) ACC_PUBLIC, ACC_STATIC, ACC_FINAL, ACC_SYNTHETIC
    Code:
      stack=5, locals=2, args_size=2
         0: new           #187                // class scala/Tuple2
         3: dup
         4: aload_1
         5: aload_0
         6: aload_1
         7: invokeinterface #431,  2          // InterfaceMethod scala/collection/immutable/Map.contains:(Ljava/lang/Object;)Z
        12: ifeq          40
        15: aload_0
        16: aload_1
        17: invokeinterface #299,  2          // InterfaceMethod scala/collection/immutable/Map.apply:(Ljava/lang/Object;)Ljava/lang/Object;
        22: checkcast     #502                // class scala/collection/SetOps
        25: ldc_w         #504                // String org.scalatest.Ignore
        28: invokeinterface #505,  2          // InterfaceMethod scala/collection/SetOps.contains:(Ljava/lang/Object;)Z
        33: ifeq          40
        36: iconst_1
        37: goto          41
        40: iconst_0
        41: invokestatic  #520                // Method scala/runtime/BoxesRunTime.boxToBoolean:(Z)Ljava/lang/Boolean;
        44: invokespecial #441                // Method scala/Tuple2."<init>":(Ljava/lang/Object;Ljava/lang/Object;)V
        47: areturn
      StackMapTable: number_of_entries = 2
        frame_type = 255 /* full_frame */
          offset_delta = 40
          locals = [ class scala/collection/immutable/Map, class java/lang/String ]
          stack = [ uninitialized 0, uninitialized 0, class java/lang/String ]
        frame_type = 255 /* full_frame */
          offset_delta = 0
          locals = [ class scala/collection/immutable/Map, class java/lang/String ]
          stack = [ uninitialized 0, uninitialized 0, class java/lang/String, int ]
      LineNumberTable:
        line 204: 0
      LocalVariableTable:
        Start  Length  Slot  Name   Signature
            0      48     0 tags$2   Lscala/collection/immutable/Map;
            0      48     1 testName   Ljava/lang/String;
    MethodParameters:
      Name                           Flags
      tags$2                         final
      testName                       final

  private final scala.collection.immutable.List impl$1(scala.collection.immutable.Set, scala.collection.immutable.Map);
    descriptor: (Lscala/collection/immutable/Set;Lscala/collection/immutable/Map;)Lscala/collection/immutable/List;
    flags: (0x0012) ACC_PRIVATE, ACC_FINAL
    Code:
      stack=3, locals=5, args_size=3
         0: aload_0
         1: aload_1
         2: aload_2
         3: invokespecial #359                // Method verifyPreconditionsForMethods:(Lscala/collection/immutable/Set;Lscala/collection/immutable/Map;)V
         6: aload_1
         7: invokeinterface #363,  1          // InterfaceMethod scala/collection/immutable/Set.toList:()Lscala/collection/immutable/List;
        12: astore_3
        13: aload_0
        14: aload_3
        15: aload_2
        16: invokespecial #365                // Method includedTestNames:(Lscala/collection/immutable/List;Lscala/collection/immutable/Map;)Lscala/collection/immutable/List;
        19: aload_0
        20: aload_2
        21: invokedynamic #528,  0            // InvokeDynamic #13:apply:(Lorg/scalatest/Filter;Lscala/collection/immutable/Map;)Lscala/Function1;
        26: invokevirtual #125                // Method scala/collection/immutable/List.withFilter:(Lscala/Function1;)Lscala/collection/WithFilter;
        29: aload_2
        30: invokedynamic #532,  0            // InvokeDynamic #14:apply:(Lscala/collection/immutable/Map;)Lscala/Function1;
        35: invokevirtual #141                // Method scala/collection/WithFilter.map:(Lscala/Function1;)Ljava/lang/Object;
        38: checkcast     #121                // class scala/collection/immutable/List
        41: astore        4
        43: aload         4
        45: areturn
      LineNumberTable:
        line 195: 0
        line 197: 6
        line 200: 13
        line 206: 43
      LocalVariableTable:
        Start  Length  Slot  Name   Signature
           13      32     3 testNamesAsList   Lscala/collection/immutable/List;
           43       2     4 filtered   Lscala/collection/immutable/List;
            0      46     0  this   Lorg/scalatest/Filter;
            0      46     1 testNames   Lscala/collection/immutable/Set;
            0      46     2  tags   Lscala/collection/immutable/Map;
    MethodParameters:
      Name                           Flags
      testNames                      final
      tags                           final

  public static final boolean $anonfun$runnableTestCount$1(org.scalatest.Filter, scala.collection.immutable.Map, java.lang.String);
    descriptor: (Lorg/scalatest/Filter;Lscala/collection/immutable/Map;Ljava/lang/String;)Z
    flags: (0x1019) ACC_PUBLIC, ACC_STATIC, ACC_FINAL, ACC_SYNTHETIC
    Code:
      stack=2, locals=3, args_size=3
         0: aload_1
         1: aload_2
         2: invokeinterface #431,  2          // InterfaceMethod scala/collection/immutable/Map.contains:(Ljava/lang/Object;)Z
         7: ifeq          58
        10: aload_1
        11: aload_2
        12: invokeinterface #299,  2          // InterfaceMethod scala/collection/immutable/Map.apply:(Ljava/lang/Object;)Ljava/lang/Object;
        17: checkcast     #502                // class scala/collection/SetOps
        20: ldc_w         #504                // String org.scalatest.Ignore
        23: invokeinterface #505,  2          // InterfaceMethod scala/collection/SetOps.contains:(Ljava/lang/Object;)Z
        28: ifne          62
        31: aload_1
        32: aload_2
        33: invokeinterface #299,  2          // InterfaceMethod scala/collection/immutable/Map.apply:(Ljava/lang/Object;)Ljava/lang/Object;
        38: checkcast     #502                // class scala/collection/SetOps
        41: aload_0
        42: invokevirtual #507                // Method tagsToExclude:()Lscala/collection/immutable/Set;
        45: invokeinterface #512,  2          // InterfaceMethod scala/collection/SetOps.intersect:(Lscala/collection/Set;)Lscala/collection/SetOps;
        50: invokeinterface #514,  1          // InterfaceMethod scala/collection/SetOps.isEmpty:()Z
        55: ifeq          62
        58: iconst_1
        59: goto          63
        62: iconst_0
        63: ireturn
      StackMapTable: number_of_entries = 3
        frame_type = 58 /* same */
        frame_type = 3 /* same */
        frame_type = 64 /* same_locals_1_stack_item */
          stack = [ int ]
      LineNumberTable:
        line 242: 0
      LocalVariableTable:
        Start  Length  Slot  Name   Signature
            0      64     0 $this   Lorg/scalatest/Filter;
            0      64     1 tags$3   Lscala/collection/immutable/Map;
            0      64     2 testName   Ljava/lang/String;
    MethodParameters:
      Name                           Flags
      $this                          final synthetic
      tags$3                         final
      testName                       final

  public static final java.lang.String $anonfun$runnableTestCount$2(java.lang.String);
    descriptor: (Ljava/lang/String;)Ljava/lang/String;
    flags: (0x1019) ACC_PUBLIC, ACC_STATIC, ACC_FINAL, ACC_SYNTHETIC
    Code:
      stack=1, locals=1, args_size=1
         0: aload_0
         1: areturn
      LineNumberTable:
        line 243: 0
      LocalVariableTable:
        Start  Length  Slot  Name   Signature
            0       2     0 testName   Ljava/lang/String;
    MethodParameters:
      Name                           Flags
      testName                       final

  public org.scalatest.Filter(scala.Option<scala.collection.immutable.Set<java.lang.String>>, scala.collection.immutable.Set<java.lang.String>, boolean, org.scalatest.DynaTags);
    descriptor: (Lscala/Option;Lscala/collection/immutable/Set;ZLorg/scalatest/DynaTags;)V
    flags: (0x0001) ACC_PUBLIC
    Code:
      stack=9, locals=9, args_size=5
         0: aload_0
         1: aload_1
         2: putfield      #65                 // Field tagsToInclude:Lscala/Option;
         5: aload_0
         6: aload_2
         7: putfield      #69                 // Field tagsToExclude:Lscala/collection/immutable/Set;
        10: aload_0
        11: iload_3
        12: putfield      #71                 // Field excludeNestedSuites:Z
        15: aload_0
        16: aload         4
        18: putfield      #73                 // Field dynaTags:Lorg/scalatest/DynaTags;
        21: aload_0
        22: invokespecial #539                // Method java/lang/Object."<init>":()V
        25: getstatic     #544                // Field org/scalactic/Requirements$.MODULE$:Lorg/scalactic/Requirements$;
        28: invokevirtual #548                // Method org/scalactic/Requirements$.requirementsHelper:()Lorg/scalactic/Requirements$RequirementsHelper;
        31: iconst_3
        32: anewarray     #192                // class java/lang/String
        35: dup
        36: iconst_0
        37: ldc_w         #550                // String Filter.this.tagsToInclude
        40: aastore
        41: dup
        42: iconst_1
        43: ldc_w         #552                // String Filter.this.tagsToExclude
        46: aastore
        47: dup
        48: iconst_2
        49: ldc_w         #554                // String Filter.this.dynaTags
        52: aastore
        53: checkcast     #342                // class "[Ljava/lang/Object;"
        56: checkcast     #556                // class "[Ljava/lang/String;"
        59: iconst_3
        60: anewarray     #4                  // class java/lang/Object
        63: dup
        64: iconst_0
        65: aload_1
        66: aastore
        67: dup
        68: iconst_1
        69: aload_2
        70: aastore
        71: dup
        72: iconst_2
        73: aload         4
        75: aastore
        76: checkcast     #342                // class "[Ljava/lang/Object;"
        79: getstatic     #561                // Field org/scalactic/Prettifier$.MODULE$:Lorg/scalactic/Prettifier$;
        82: invokevirtual #564                // Method org/scalactic/Prettifier$.default:()Lorg/scalactic/Prettifier;
        85: new           #566                // class org/scalactic/source/Position
        88: dup
        89: ldc_w         #567                // String Filter.scala
        92: ldc_w         #569                // String Please set the environment variable SCALACTIC_FILL_FILE_PATHNAMES to yes at compile time to enable this feature.
        95: bipush        50
        97: invokespecial #572                // Method org/scalactic/source/Position."<init>":(Ljava/lang/String;Ljava/lang/String;I)V
       100: invokevirtual #576                // Method org/scalactic/Requirements$RequirementsHelper.macroRequireNonNull:([Ljava/lang/String;[Ljava/lang/Object;Lorg/scalactic/Prettifier;Lorg/scalactic/source/Position;)V
       103: aload_1
       104: astore        6
       106: aload         6
       108: instanceof    #91                 // class scala/Some
       111: ifeq          160
       114: aload         6
       116: checkcast     #91                 // class scala/Some
       119: astore        7
       121: aload         7
       123: invokevirtual #95                 // Method scala/Some.value:()Ljava/lang/Object;
       126: checkcast     #97                 // class scala/collection/immutable/Set
       129: astore        8
       131: aload         8
       133: invokeinterface #577,  1          // InterfaceMethod scala/collection/immutable/Set.isEmpty:()Z
       138: ifeq          152
       141: new           #194                // class java/lang/IllegalArgumentException
       144: dup
       145: ldc_w         #579                // String tagsToInclude was defined, but contained an empty set
       148: invokespecial #213                // Method java/lang/IllegalArgumentException."<init>":(Ljava/lang/String;)V
       151: athrow
       152: getstatic     #219                // Field scala/runtime/BoxedUnit.UNIT:Lscala/runtime/BoxedUnit;
       155: astore        5
       157: goto          195
       160: goto          163
       163: getstatic     #85                 // Field scala/None$.MODULE$:Lscala/None$;
       166: aload         6
       168: invokevirtual #89                 // Method java/lang/Object.equals:(Ljava/lang/Object;)Z
       171: ifeq          182
       174: getstatic     #219                // Field scala/runtime/BoxedUnit.UNIT:Lscala/runtime/BoxedUnit;
       177: astore        5
       179: goto          195
       182: goto          185
       185: new           #162                // class scala/MatchError
       188: dup
       189: aload         6
       191: invokespecial #166                // Method scala/MatchError."<init>":(Ljava/lang/Object;)V
       194: athrow
       195: return
      StackMapTable: number_of_entries = 6
        frame_type = 255 /* full_frame */
          offset_delta = 152
          locals = [ class org/scalatest/Filter, class scala/Option, class scala/collection/immutable/Set, int, class org/scalatest/DynaTags, top, class scala/Option, class scala/Some, class scala/collection/immutable/Set ]
          stack = []
        frame_type = 249 /* chop */
          offset_delta = 7
        frame_type = 2 /* same */
        frame_type = 18 /* same */
        frame_type = 2 /* same */
        frame_type = 255 /* full_frame */
          offset_delta = 9
          locals = [ class org/scalatest/Filter, class scala/Option, class scala/collection/immutable/Set, int, class org/scalatest/DynaTags, class scala/runtime/BoxedUnit, class scala/Option ]
          stack = []
      LineNumberTable:
        line 48: 0
        line 50: 25
        line 52: 103
        line 53: 106
        line 54: 131
        line 55: 141
        line 54: 152
        line 53: 160
        line 56: 163
        line 52: 185
        line 48: 195
      LocalVariableTable:
        Start  Length  Slot  Name   Signature
          131      29     8 tagsToInclude   Lscala/collection/immutable/Set;
            0     196     0  this   Lorg/scalatest/Filter;
            0     196     1 tagsToInclude   Lscala/Option;
            0     196     2 tagsToExclude   Lscala/collection/immutable/Set;
            0     196     3 excludeNestedSuites   Z
            0     196     4 dynaTags   Lorg/scalatest/DynaTags;
    Signature: #536                         // (Lscala/Option<Lscala/collection/immutable/Set<Ljava/lang/String;>;>;Lscala/collection/immutable/Set<Ljava/lang/String;>;ZLorg/scalatest/DynaTags;)V
    MethodParameters:
      Name                           Flags
      tagsToInclude                  final
      tagsToExclude                  final
      excludeNestedSuites            final
      dynaTags                       final

  public static final java.lang.Object $anonfun$includedTestNames$1$adapted(scala.collection.immutable.Map, java.lang.String);
    descriptor: (Lscala/collection/immutable/Map;Ljava/lang/String;)Ljava/lang/Object;
    flags: (0x1019) ACC_PUBLIC, ACC_STATIC, ACC_FINAL, ACC_SYNTHETIC
    Code:
      stack=2, locals=2, args_size=2
         0: aload_0
         1: aload_1
         2: invokestatic  #581                // Method $anonfun$includedTestNames$1:(Lscala/collection/immutable/Map;Ljava/lang/String;)Z
         5: invokestatic  #520                // Method scala/runtime/BoxesRunTime.boxToBoolean:(Z)Ljava/lang/Boolean;
         8: areturn
      LineNumberTable:
        line 64: 0
      LocalVariableTable:
        Start  Length  Slot  Name   Signature
            0       9     0 tags$1   Lscala/collection/immutable/Map;
            0       9     1 testName   Ljava/lang/String;
    MethodParameters:
      Name                           Flags
      tags$1                         final
      testName                       final

  public static final java.lang.Object $anonfun$includedTestNames$3$adapted(scala.Tuple2);
    descriptor: (Lscala/Tuple2;)Ljava/lang/Object;
    flags: (0x1019) ACC_PUBLIC, ACC_STATIC, ACC_FINAL, ACC_SYNTHETIC
    Code:
      stack=1, locals=1, args_size=1
         0: aload_0
         1: invokestatic  #583                // Method $anonfun$includedTestNames$3:(Lscala/Tuple2;)Z
         4: invokestatic  #520                // Method scala/runtime/BoxesRunTime.boxToBoolean:(Z)Ljava/lang/Boolean;
         7: areturn
      LineNumberTable:
        line 64: 0
      LocalVariableTable:
        Start  Length  Slot  Name   Signature
            0       8     0   x$1   Lscala/Tuple2;
    MethodParameters:
      Name                           Flags
      x$1                            final

  public static final java.lang.Object $anonfun$verifyPreconditionsForMethods$1$adapted(scala.Tuple2);
    descriptor: (Lscala/Tuple2;)Ljava/lang/Object;
    flags: (0x1019) ACC_PUBLIC, ACC_STATIC, ACC_FINAL, ACC_SYNTHETIC
    Code:
      stack=1, locals=1, args_size=1
         0: aload_0
         1: invokestatic  #585                // Method $anonfun$verifyPreconditionsForMethods$1:(Lscala/Tuple2;)Z
         4: invokestatic  #520                // Method scala/runtime/BoxesRunTime.boxToBoolean:(Z)Ljava/lang/Boolean;
         7: areturn
      LineNumberTable:
        line 72: 0
      LocalVariableTable:
        Start  Length  Slot  Name   Signature
            0       8     0 tuple   Lscala/Tuple2;
    MethodParameters:
      Name                           Flags
      tuple                          final

  public static final java.lang.Object $anonfun$mergeTestTags$1$adapted(scala.collection.mutable.Map, scala.collection.immutable.Map);
    descriptor: (Lscala/collection/mutable/Map;Lscala/collection/immutable/Map;)Ljava/lang/Object;
    flags: (0x1019) ACC_PUBLIC, ACC_STATIC, ACC_FINAL, ACC_SYNTHETIC
    Code:
      stack=2, locals=2, args_size=2
         0: aload_0
         1: aload_1
         2: invokestatic  #587                // Method $anonfun$mergeTestTags$1:(Lscala/collection/mutable/Map;Lscala/collection/immutable/Map;)V
         5: getstatic     #219                // Field scala/runtime/BoxedUnit.UNIT:Lscala/runtime/BoxedUnit;
         8: areturn
      LineNumberTable:
        line 81: 0
      LocalVariableTable:
        Start  Length  Slot  Name   Signature
            0       9     0 mergedTags$1   Lscala/collection/mutable/Map;
            0       9     1 testTags   Lscala/collection/immutable/Map;
    MethodParameters:
      Name                           Flags
      mergedTags$1                   final
      testTags                       final

  public static final java.lang.Object $anonfun$apply$1$adapted(org.scalatest.Filter, scala.collection.immutable.Map, java.lang.String);
    descriptor: (Lorg/scalatest/Filter;Lscala/collection/immutable/Map;Ljava/lang/String;)Ljava/lang/Object;
    flags: (0x1019) ACC_PUBLIC, ACC_STATIC, ACC_FINAL, ACC_SYNTHETIC
    Code:
      stack=3, locals=3, args_size=3
         0: aload_0
         1: aload_1
         2: aload_2
         3: invokestatic  #589                // Method $anonfun$apply$1:(Lorg/scalatest/Filter;Lscala/collection/immutable/Map;Ljava/lang/String;)Z
         6: invokestatic  #520                // Method scala/runtime/BoxesRunTime.boxToBoolean:(Z)Ljava/lang/Boolean;
         9: areturn
      LineNumberTable:
        line 149: 0
      LocalVariableTable:
        Start  Length  Slot  Name   Signature
            0      10     0 $this   Lorg/scalatest/Filter;
            0      10     1 testTags$1   Lscala/collection/immutable/Map;
            0      10     2 testName   Ljava/lang/String;
    MethodParameters:
      Name                           Flags
      $this                          final
      testTags$1                     final
      testName                       final

  public static final java.lang.Object $anonfun$runnableTestCount$1$adapted(org.scalatest.Filter, scala.collection.immutable.Map, java.lang.String);
    descriptor: (Lorg/scalatest/Filter;Lscala/collection/immutable/Map;Ljava/lang/String;)Ljava/lang/Object;
    flags: (0x1019) ACC_PUBLIC, ACC_STATIC, ACC_FINAL, ACC_SYNTHETIC
    Code:
      stack=3, locals=3, args_size=3
         0: aload_0
         1: aload_1
         2: aload_2
         3: invokestatic  #591                // Method $anonfun$runnableTestCount$1:(Lorg/scalatest/Filter;Lscala/collection/immutable/Map;Ljava/lang/String;)Z
         6: invokestatic  #520                // Method scala/runtime/BoxesRunTime.boxToBoolean:(Z)Ljava/lang/Boolean;
         9: areturn
      LineNumberTable:
        line 241: 0
      LocalVariableTable:
        Start  Length  Slot  Name   Signature
            0      10     0 $this   Lorg/scalatest/Filter;
            0      10     1 tags$3   Lscala/collection/immutable/Map;
            0      10     2 testName   Ljava/lang/String;
    MethodParameters:
      Name                           Flags
      $this                          final
      tags$3                         final
      testName                       final

  public static final java.lang.Object $anonfun$mergeTestTags$2$adapted(scala.Tuple2);
    descriptor: (Lscala/Tuple2;)Ljava/lang/Object;
    flags: (0x1019) ACC_PUBLIC, ACC_STATIC, ACC_FINAL, ACC_SYNTHETIC
    Code:
      stack=1, locals=1, args_size=1
         0: aload_0
         1: invokestatic  #593                // Method $anonfun$mergeTestTags$2:(Lscala/Tuple2;)Z
         4: invokestatic  #520                // Method scala/runtime/BoxesRunTime.boxToBoolean:(Z)Ljava/lang/Boolean;
         7: areturn
      LineNumberTable:
        line 82: 0
      LocalVariableTable:
        Start  Length  Slot  Name   Signature
            0       8     0 check$ifrefutable$1   Lscala/Tuple2;
    MethodParameters:
      Name                           Flags
      check$ifrefutable$1            final

  public static final java.lang.Object $anonfun$apply$3$adapted(org.scalatest.Filter, scala.collection.immutable.Map, java.lang.String);
    descriptor: (Lorg/scalatest/Filter;Lscala/collection/immutable/Map;Ljava/lang/String;)Ljava/lang/Object;
    flags: (0x1019) ACC_PUBLIC, ACC_STATIC, ACC_FINAL, ACC_SYNTHETIC
    Code:
      stack=3, locals=3, args_size=3
         0: aload_0
         1: aload_1
         2: aload_2
         3: invokestatic  #595                // Method $anonfun$apply$3:(Lorg/scalatest/Filter;Lscala/collection/immutable/Map;Ljava/lang/String;)Z
         6: invokestatic  #520                // Method scala/runtime/BoxesRunTime.boxToBoolean:(Z)Ljava/lang/Boolean;
         9: areturn
      LineNumberTable:
        line 200: 0
      LocalVariableTable:
        Start  Length  Slot  Name   Signature
            0      10     0 $this   Lorg/scalatest/Filter;
            0      10     1 tags$2   Lscala/collection/immutable/Map;
            0      10     2 testName   Ljava/lang/String;
    MethodParameters:
      Name                           Flags
      $this                          final
      tags$2                         final
      testName                       final

  private static java.lang.Object $deserializeLambda$(java.lang.invoke.SerializedLambda);
    descriptor: (Ljava/lang/invoke/SerializedLambda;)Ljava/lang/Object;
    flags: (0x100a) ACC_PRIVATE, ACC_STATIC, ACC_SYNTHETIC
    Code:
      stack=1, locals=1, args_size=1
         0: aload_0
         1: invokedynamic #607,  0            // InvokeDynamic #15:lambdaDeserialize:(Ljava/lang/invoke/SerializedLambda;)Ljava/lang/Object;
         6: areturn
}
InnerClasses:
  public static final #15= #12 of #14;    // Lookup=class java/lang/invoke/MethodHandles$Lookup of class java/lang/invoke/MethodHandles
  public static #20= #17 of #19;          // RequirementsHelper=class org/scalactic/Requirements$RequirementsHelper of class org/scalactic/Requirements
  public static #25= #22 of #24;          // WithFilter=class scala/collection/MapOps$WithFilter of class scala/collection/MapOps
SourceFile: "Filter.scala"
RuntimeVisibleAnnotations:
  0: #8(#9=s#10)
    scala.reflect.ScalaSignature(
      bytes="\u0006\u0005\u0005Ue\u0001B\u000f\u001f\u0005\rB\u0001B\u000e\u0001\u0003\u0006\u0004%\ta\u000e\u0005\t\r\u0002\u0011\t\u0011)A\u0005q!Aq\t\u0001BC\u0002\u0013\u0005\u0001\n\u0003\u0005J\u0001\t\u0005\t\u0015!\u0003<\u0011!Q\u0005A!b\u0001\n\u0003Y\u0005\u0002C(\u0001\u0005\u0003\u0005\u000b\u0011\u0002\'\t\u0011A\u0003!Q1A\u0005\u0002EC\u0001B\u0016\u0001\u0003\u0002\u0003\u0006IA\u0015\u0005\u0006/\u0002!I\u0001\u0017\u0005\u0006=\u0002!Ia\u0018\u0005\u0006U\u0002!Ia\u001b\u0005\u0006e\u0002!Ia\u001d\u0005\u0007o\u0002!\tA\b=\t\u000bu\u0004A\u0011\u0001@\t\ru\u0004A\u0011AA\u0007\u0011\u001d\tI\u0002\u0001C\u0001\u000379q!a\u000b\u001f\u0011\u0003\tiC\u0002\u0004\u001e=!\u0005\u0011q\u0006\u0005\u0007/J!\t!a\u0010\t\u0013\u0005\u0005#C1A\u0005\u000e\u0005\r\u0003\u0002CA&%\u0001\u0006i!!\u0012\t\ru\u0014B\u0011AA\'\u0011%\t9FEI\u0001\n\u0003\tI\u0006C\u0005\u0002pI\t\n\u0011\"\u0001\u0002r!I\u0011Q\u000f\n\u0012\u0002\u0013\u0005\u0011q\u000f\u0005\n\u0003w\u0012\u0012\u0013!C\u0001\u0003{Bq!!!\u0013\t\u0003\t\u0019\tC\u0005\u0002\u0006J\t\t\u0011\"\u0003\u0002\b\n1a)\u001b7uKJT!a\b\u0011\u0002\u0013M\u001c\u0017\r\\1uKN$(\"A\u0011\u0002\u0007=\u0014xm\u0001\u0001\u0014\u0007\u0001!#\u0006\u0005\u0002&Q5\taEC\u0001(\u0003\u0015\u00198-\u00197b\u0013\tIcE\u0001\u0004B]f\u0014VM\u001a\t\u0003WMr!\u0001L\u0019\u000f\u00055\u0002T\"\u0001\u0018\u000b\u0005=\u0012\u0013A\u0002\u001fs_>$h(C\u0001(\u0013\t\u0011d%A\u0004qC\u000e\\\u0017mZ3\n\u0005Q*$\u0001D*fe&\fG.\u001b>bE2,\'B\u0001\u001a\'\u00035!\u0018mZ:U_&s7\r\\;eKV\t\u0001\bE\u0002&smJ!A\u000f\u0014\u0003\r=\u0003H/[8o!\ra\u0004i\u0011\b\u0003{y\u0002\"!\f\u0014\n\u0005}2\u0013A\u0002)sK\u0012,g-\u0003\u0002B\u0005\n\u00191+\u001a;\u000b\u0005}2\u0003C\u0001\u001fE\u0013\t)%I\u0001\u0004TiJLgnZ\u0001\u000fi\u0006<7\u000fV8J]\u000edW\u000fZ3!\u00035!\u0018mZ:U_\u0016C8\r\\;eKV\t1(\u0001\buC\u001e\u001cHk\\#yG2,H-\u001a\u0011\u0002\'\u0015D8\r\\;eK:+7\u000f^3e\'VLG/Z:\u0016\u00031\u0003\"!J\'\n\u000593#a\u0002\"p_2,\u0017M\\\u0001\u0015Kb\u001cG.\u001e3f\u001d\u0016\u001cH/\u001a3Tk&$Xm\u001d\u0011\u0002\u0011\u0011Lh.\u0019+bON,\u0012A\u0015\t\u0003\'Rk\u0011AH\u0005\u0003+z\u0011\u0001\u0002R=oCR\u000bwm]\u0001\nIft\u0017\rV1hg\u0002\na\u0001P5oSRtD#B-[7rk\u0006CA*\u0001\u0011\u00151\u0014\u00021\u00019\u0011\u00159\u0015\u00021\u0001<\u0011\u0015Q\u0015\u00021\u0001M\u0011\u0015\u0001\u0016\u00021\u0001S\u0003EIgn\u00197vI\u0016$G+Z:u\u001d\u0006lWm\u001d\u000b\u0004A\u000e,\u0007cA\u0016b\u0007&\u0011!-\u000e\u0002\u0005\u0019&\u001cH\u000fC\u0003e\u0015\u0001\u0007\u0001-A\buKN$h*Y7fg\u0006\u001bH*[:u\u0011\u00151\'\u00021\u0001h\u0003\u0011!\u0018mZ:\u0011\tqB7iO\u0005\u0003S\n\u00131!T1q\u0003u1XM]5gsB\u0013XmY8oI&$\u0018n\u001c8t\r>\u0014X*\u001a;i_\u0012\u001cHc\u00017pcB\u0011Q%\\\u0005\u0003]\u001a\u0012A!\u00168ji\")\u0001o\u0003a\u0001w\u0005IA/Z:u\u001d\u0006lWm\u001d\u0005\u0006M.\u0001\raZ\u0001\u000e[\u0016\u0014x-\u001a+fgR$\u0016mZ:\u0015\u0005\u001d$\b\"B;\r\u0001\u00041\u0018\u0001\u0004;fgR$\u0016mZ:MSN$\bcA\u0016bO\u0006!R.\u001a:hKR+7\u000f\u001e#z]\u0006l\u0017n\u0019+bON$BaZ={y\")a-\u0004a\u0001O\")10\u0004a\u0001\u0007\u000691/^5uK&#\u0007\"\u00029\u000e\u0001\u0004Y\u0014!B1qa2LHcB@\u0002\b\u0005%\u00111\u0002\t\u0005W\u0005\f\t\u0001E\u0003&\u0003\u0007\u0019E*C\u0002\u0002\u0006\u0019\u0012a\u0001V;qY\u0016\u0014\u0004\"\u00029\u000f\u0001\u0004Y\u0004\"\u00024\u000f\u0001\u00049\u0007\"B>\u000f\u0001\u0004\u0019E\u0003CA\b\u0003#\t)\"a\u0006\u0011\u000b\u0015\n\u0019\u0001\u0014\'\t\r\u0005Mq\u00021\u0001D\u0003!!Xm\u001d;OC6,\u0007\"\u00024\u0010\u0001\u00049\u0007\"B>\u0010\u0001\u0004\u0019\u0015!\u0005:v]:\f\'\r\\3UKN$8i\\;oiRA\u0011QDA\u0012\u0003K\tI\u0003E\u0002&\u0003?I1!!\t\'\u0005\rIe\u000e\u001e\u0005\u0006aB\u0001\ra\u000f\u0005\u0007\u0003O\u0001\u0002\u0019A4\u0002\u0011Q,7\u000f\u001e+bONDQa\u001f\tA\u0002\r\u000baAR5mi\u0016\u0014\bCA*\u0013\'\u0011\u0011B%!\r\u0011\t\u0005M\u0012QH\u0007\u0003\u0003kQA!a\u000e\u0002:\u0005\u0011\u0011n\u001c\u0006\u0003\u0003w\tAA[1wC&\u0019A\'!\u000e\u0015\u0005\u00055\u0012!C%h]>\u0014X\rV1h+\t\t)e\u0004\u0002\u0002H\u0005\u0012\u0011\u0011J\u0001\u0015_J<gf]2bY\u0006$Xm\u001d;/\u0013\u001etwN]3\u0002\u0015%;gn\u001c:f)\u0006<\u0007\u0005F\u0005Z\u0003\u001f\n\t&a\u0015\u0002V!9aG\u0006I\u0001\u0002\u0004A\u0004bB$\u0017!\u0003\u0005\ra\u000f\u0005\b\u0015Z\u0001\n\u00111\u0001M\u0011\u001d\u0001f\u0003%AA\u0002I\u000bq\"\u00199qYf$C-\u001a4bk2$H%M\u000b\u0003\u00037R3\u0001OA/W\t\ty\u0006\u0005\u0003\u0002b\u0005-TBAA2\u0015\u0011\t)\'a\u001a\u0002\u0013Ut7\r[3dW\u0016$\'bAA5M\u0005Q\u0011M\u001c8pi\u0006$\u0018n\u001c8\n\t\u00055\u00141\r\u0002\u0012k:\u001c\u0007.Z2lK\u00124\u0016M]5b]\u000e,\u0017aD1qa2LH\u0005Z3gCVdG\u000f\n\u001a\u0016\u0005\u0005M$fA\u001e\u0002^\u0005y\u0011\r\u001d9ms\u0012\"WMZ1vYR$3\'\u0006\u0002\u0002z)\u001aA*!\u0018\u0002\u001f\u0005\u0004\b\u000f\\=%I\u00164\u0017-\u001e7uIQ*\"!a +\u0007I\u000bi&A\u0004eK\u001a\fW\u000f\u001c;\u0016\u0003e\u000bAb\u001e:ji\u0016\u0014V\r\u001d7bG\u0016$\"!!#\u0011\t\u0005-\u0015\u0011S\u0007\u0003\u0003\u001bSA!a$\u0002:\u0005!A.\u00198h\u0013\u0011\t\u0019*!$\u0003\r=\u0013\'.Z2u\u0001"
    )
BootstrapMethods:
  0: #115 REF_invokeStatic java/lang/invoke/LambdaMetafactory.altMetafactory:(Ljava/lang/invoke/MethodHandles$Lookup;Ljava/lang/String;Ljava/lang/invoke/MethodType;[Ljava/lang/Object;)Ljava/lang/invoke/CallSite;
    Method arguments:
      #99 (Ljava/lang/Object;)Ljava/lang/Object;
      #104 REF_invokeStatic org/scalatest/Filter.$anonfun$includedTestNames$1$adapted:(Lscala/collection/immutable/Map;Ljava/lang/String;)Ljava/lang/Object;
      #106 (Ljava/lang/String;)Ljava/lang/Object;
      #107 5
      #108 1
      #106 (Ljava/lang/String;)Ljava/lang/Object;
  1: #115 REF_invokeStatic java/lang/invoke/LambdaMetafactory.altMetafactory:(Ljava/lang/invoke/MethodHandles$Lookup;Ljava/lang/String;Ljava/lang/invoke/MethodType;[Ljava/lang/Object;)Ljava/lang/invoke/CallSite;
    Method arguments:
      #99 (Ljava/lang/Object;)Ljava/lang/Object;
      #130 REF_invokeStatic org/scalatest/Filter.$anonfun$includedTestNames$2:(Lscala/collection/immutable/Set;Lscala/collection/immutable/Map;Ljava/lang/String;)Lscala/Tuple2;
      #132 (Ljava/lang/String;)Lscala/Tuple2;
      #107 5
      #108 1
      #132 (Ljava/lang/String;)Lscala/Tuple2;
  2: #115 REF_invokeStatic java/lang/invoke/LambdaMetafactory.altMetafactory:(Ljava/lang/invoke/MethodHandles$Lookup;Ljava/lang/String;Ljava/lang/invoke/MethodType;[Ljava/lang/Object;)Ljava/lang/invoke/CallSite;
    Method arguments:
      #99 (Ljava/lang/Object;)Ljava/lang/Object;
      #148 REF_invokeStatic org/scalatest/Filter.$anonfun$includedTestNames$3$adapted:(Lscala/Tuple2;)Ljava/lang/Object;
      #149 (Lscala/Tuple2;)Ljava/lang/Object;
      #107 5
      #108 1
      #149 (Lscala/Tuple2;)Ljava/lang/Object;
  3: #115 REF_invokeStatic java/lang/invoke/LambdaMetafactory.altMetafactory:(Ljava/lang/invoke/MethodHandles$Lookup;Ljava/lang/String;Ljava/lang/invoke/MethodType;[Ljava/lang/Object;)Ljava/lang/invoke/CallSite;
    Method arguments:
      #99 (Ljava/lang/Object;)Ljava/lang/Object;
      #158 REF_invokeStatic org/scalatest/Filter.$anonfun$includedTestNames$4:(Lscala/Tuple2;)Ljava/lang/String;
      #159 (Lscala/Tuple2;)Ljava/lang/String;
      #107 5
      #108 1
      #159 (Lscala/Tuple2;)Ljava/lang/String;
  4: #115 REF_invokeStatic java/lang/invoke/LambdaMetafactory.altMetafactory:(Ljava/lang/invoke/MethodHandles$Lookup;Ljava/lang/String;Ljava/lang/invoke/MethodType;[Ljava/lang/Object;)Ljava/lang/invoke/CallSite;
    Method arguments:
      #99 (Ljava/lang/Object;)Ljava/lang/Object;
      #180 REF_invokeStatic org/scalatest/Filter.$anonfun$verifyPreconditionsForMethods$1$adapted:(Lscala/Tuple2;)Ljava/lang/Object;
      #149 (Lscala/Tuple2;)Ljava/lang/Object;
      #107 5
      #108 1
      #149 (Lscala/Tuple2;)Ljava/lang/Object;
  5: #115 REF_invokeStatic java/lang/invoke/LambdaMetafactory.altMetafactory:(Ljava/lang/invoke/MethodHandles$Lookup;Ljava/lang/String;Ljava/lang/invoke/MethodType;[Ljava/lang/Object;)Ljava/lang/invoke/CallSite;
    Method arguments:
      #99 (Ljava/lang/Object;)Ljava/lang/Object;
      #258 REF_invokeStatic org/scalatest/Filter.$anonfun$mergeTestTags$1$adapted:(Lscala/collection/mutable/Map;Lscala/collection/immutable/Map;)Ljava/lang/Object;
      #260 (Lscala/collection/immutable/Map;)Ljava/lang/Object;
      #107 5
      #108 1
      #260 (Lscala/collection/immutable/Map;)Ljava/lang/Object;
  6: #115 REF_invokeStatic java/lang/invoke/LambdaMetafactory.altMetafactory:(Ljava/lang/invoke/MethodHandles$Lookup;Ljava/lang/String;Ljava/lang/invoke/MethodType;[Ljava/lang/Object;)Ljava/lang/invoke/CallSite;
    Method arguments:
      #99 (Ljava/lang/Object;)Ljava/lang/Object;
      #322 REF_invokeStatic org/scalatest/Filter.$anonfun$mergeTestDynamicTags$1:(Lscala/collection/immutable/Set;Ljava/lang/String;)Lscala/Tuple2;
      #132 (Ljava/lang/String;)Lscala/Tuple2;
      #107 5
      #108 1
      #132 (Ljava/lang/String;)Lscala/Tuple2;
  7: #115 REF_invokeStatic java/lang/invoke/LambdaMetafactory.altMetafactory:(Ljava/lang/invoke/MethodHandles$Lookup;Ljava/lang/String;Ljava/lang/invoke/MethodType;[Ljava/lang/Object;)Ljava/lang/invoke/CallSite;
    Method arguments:
      #99 (Ljava/lang/Object;)Ljava/lang/Object;
      #370 REF_invokeStatic org/scalatest/Filter.$anonfun$apply$1$adapted:(Lorg/scalatest/Filter;Lscala/collection/immutable/Map;Ljava/lang/String;)Ljava/lang/Object;
      #106 (Ljava/lang/String;)Ljava/lang/Object;
      #107 5
      #108 1
      #106 (Ljava/lang/String;)Ljava/lang/Object;
  8: #115 REF_invokeStatic java/lang/invoke/LambdaMetafactory.altMetafactory:(Ljava/lang/invoke/MethodHandles$Lookup;Ljava/lang/String;Ljava/lang/invoke/MethodType;[Ljava/lang/Object;)Ljava/lang/invoke/CallSite;
    Method arguments:
      #99 (Ljava/lang/Object;)Ljava/lang/Object;
      #378 REF_invokeStatic org/scalatest/Filter.$anonfun$apply$2:(Lscala/collection/immutable/Map;Ljava/lang/String;)Lscala/Tuple2;
      #132 (Ljava/lang/String;)Lscala/Tuple2;
      #107 5
      #108 1
      #132 (Ljava/lang/String;)Lscala/Tuple2;
  9: #115 REF_invokeStatic java/lang/invoke/LambdaMetafactory.altMetafactory:(Ljava/lang/invoke/MethodHandles$Lookup;Ljava/lang/String;Ljava/lang/invoke/MethodType;[Ljava/lang/Object;)Ljava/lang/invoke/CallSite;
    Method arguments:
      #99 (Ljava/lang/Object;)Ljava/lang/Object;
      #412 REF_invokeStatic org/scalatest/Filter.$anonfun$runnableTestCount$1$adapted:(Lorg/scalatest/Filter;Lscala/collection/immutable/Map;Ljava/lang/String;)Ljava/lang/Object;
      #106 (Ljava/lang/String;)Ljava/lang/Object;
      #107 5
      #108 1
      #106 (Ljava/lang/String;)Ljava/lang/Object;
  10: #115 REF_invokeStatic java/lang/invoke/LambdaMetafactory.altMetafactory:(Ljava/lang/invoke/MethodHandles$Lookup;Ljava/lang/String;Ljava/lang/invoke/MethodType;[Ljava/lang/Object;)Ljava/lang/invoke/CallSite;
    Method arguments:
      #99 (Ljava/lang/Object;)Ljava/lang/Object;
      #418 REF_invokeStatic org/scalatest/Filter.$anonfun$runnableTestCount$2:(Ljava/lang/String;)Ljava/lang/String;
      #419 (Ljava/lang/String;)Ljava/lang/String;
      #107 5
      #108 1
      #419 (Ljava/lang/String;)Ljava/lang/String;
  11: #115 REF_invokeStatic java/lang/invoke/LambdaMetafactory.altMetafactory:(Ljava/lang/invoke/MethodHandles$Lookup;Ljava/lang/String;Ljava/lang/invoke/MethodType;[Ljava/lang/Object;)Ljava/lang/invoke/CallSite;
    Method arguments:
      #99 (Ljava/lang/Object;)Ljava/lang/Object;
      #485 REF_invokeStatic org/scalatest/Filter.$anonfun$mergeTestTags$2$adapted:(Lscala/Tuple2;)Ljava/lang/Object;
      #149 (Lscala/Tuple2;)Ljava/lang/Object;
      #107 5
      #108 1
      #149 (Lscala/Tuple2;)Ljava/lang/Object;
  12: #115 REF_invokeStatic java/lang/invoke/LambdaMetafactory.altMetafactory:(Ljava/lang/invoke/MethodHandles$Lookup;Ljava/lang/String;Ljava/lang/invoke/MethodType;[Ljava/lang/Object;)Ljava/lang/invoke/CallSite;
    Method arguments:
      #99 (Ljava/lang/Object;)Ljava/lang/Object;
      #492 REF_invokeStatic org/scalatest/Filter.$anonfun$mergeTestTags$3:(Lscala/collection/mutable/Map;Lscala/Tuple2;)Ljava/lang/Object;
      #149 (Lscala/Tuple2;)Ljava/lang/Object;
      #107 5
      #108 1
      #149 (Lscala/Tuple2;)Ljava/lang/Object;
  13: #115 REF_invokeStatic java/lang/invoke/LambdaMetafactory.altMetafactory:(Ljava/lang/invoke/MethodHandles$Lookup;Ljava/lang/String;Ljava/lang/invoke/MethodType;[Ljava/lang/Object;)Ljava/lang/invoke/CallSite;
    Method arguments:
      #99 (Ljava/lang/Object;)Ljava/lang/Object;
      #527 REF_invokeStatic org/scalatest/Filter.$anonfun$apply$3$adapted:(Lorg/scalatest/Filter;Lscala/collection/immutable/Map;Ljava/lang/String;)Ljava/lang/Object;
      #106 (Ljava/lang/String;)Ljava/lang/Object;
      #107 5
      #108 1
      #106 (Ljava/lang/String;)Ljava/lang/Object;
  14: #115 REF_invokeStatic java/lang/invoke/LambdaMetafactory.altMetafactory:(Ljava/lang/invoke/MethodHandles$Lookup;Ljava/lang/String;Ljava/lang/invoke/MethodType;[Ljava/lang/Object;)Ljava/lang/invoke/CallSite;
    Method arguments:
      #99 (Ljava/lang/Object;)Ljava/lang/Object;
      #531 REF_invokeStatic org/scalatest/Filter.$anonfun$apply$4:(Lscala/collection/immutable/Map;Ljava/lang/String;)Lscala/Tuple2;
      #132 (Ljava/lang/String;)Lscala/Tuple2;
      #107 5
      #108 1
      #132 (Ljava/lang/String;)Lscala/Tuple2;
  15: #604 REF_invokeStatic scala/runtime/LambdaDeserialize.bootstrap:(Ljava/lang/invoke/MethodHandles$Lookup;Ljava/lang/String;Ljava/lang/invoke/MethodType;[Ljava/lang/invoke/MethodHandle;)Ljava/lang/invoke/CallSite;
    Method arguments:
      #370 REF_invokeStatic org/scalatest/Filter.$anonfun$apply$1$adapted:(Lorg/scalatest/Filter;Lscala/collection/immutable/Map;Ljava/lang/String;)Ljava/lang/Object;
      #378 REF_invokeStatic org/scalatest/Filter.$anonfun$apply$2:(Lscala/collection/immutable/Map;Ljava/lang/String;)Lscala/Tuple2;
      #527 REF_invokeStatic org/scalatest/Filter.$anonfun$apply$3$adapted:(Lorg/scalatest/Filter;Lscala/collection/immutable/Map;Ljava/lang/String;)Ljava/lang/Object;
      #531 REF_invokeStatic org/scalatest/Filter.$anonfun$apply$4:(Lscala/collection/immutable/Map;Ljava/lang/String;)Lscala/Tuple2;
      #104 REF_invokeStatic org/scalatest/Filter.$anonfun$includedTestNames$1$adapted:(Lscala/collection/immutable/Map;Ljava/lang/String;)Ljava/lang/Object;
      #130 REF_invokeStatic org/scalatest/Filter.$anonfun$includedTestNames$2:(Lscala/collection/immutable/Set;Lscala/collection/immutable/Map;Ljava/lang/String;)Lscala/Tuple2;
      #148 REF_invokeStatic org/scalatest/Filter.$anonfun$includedTestNames$3$adapted:(Lscala/Tuple2;)Ljava/lang/Object;
      #158 REF_invokeStatic org/scalatest/Filter.$anonfun$includedTestNames$4:(Lscala/Tuple2;)Ljava/lang/String;
      #322 REF_invokeStatic org/scalatest/Filter.$anonfun$mergeTestDynamicTags$1:(Lscala/collection/immutable/Set;Ljava/lang/String;)Lscala/Tuple2;
      #258 REF_invokeStatic org/scalatest/Filter.$anonfun$mergeTestTags$1$adapted:(Lscala/collection/mutable/Map;Lscala/collection/immutable/Map;)Ljava/lang/Object;
      #485 REF_invokeStatic org/scalatest/Filter.$anonfun$mergeTestTags$2$adapted:(Lscala/Tuple2;)Ljava/lang/Object;
      #492 REF_invokeStatic org/scalatest/Filter.$anonfun$mergeTestTags$3:(Lscala/collection/mutable/Map;Lscala/Tuple2;)Ljava/lang/Object;
      #412 REF_invokeStatic org/scalatest/Filter.$anonfun$runnableTestCount$1$adapted:(Lorg/scalatest/Filter;Lscala/collection/immutable/Map;Ljava/lang/String;)Ljava/lang/Object;
      #418 REF_invokeStatic org/scalatest/Filter.$anonfun$runnableTestCount$2:(Ljava/lang/String;)Ljava/lang/String;
      #180 REF_invokeStatic org/scalatest/Filter.$anonfun$verifyPreconditionsForMethods$1$adapted:(Lscala/Tuple2;)Ljava/lang/Object;
  ScalaInlineInfo: length = 0xB8 (unknown attribute)
   01 01 00 24 01 F1 01 F2 01 01 6E 01 6F 01 01 76
   01 77 01 02 09 01 F2 01 02 0C 01 6F 01 02 0B 01
   77 01 01 AA 01 AB 01 00 64 00 65 01 00 7E 00 7F
   01 01 BB 01 BC 01 00 90 00 91 01 00 9A 00 9B 01
   01 3E 01 3F 01 01 E0 01 E1 01 00 FE 00 FF 01 01
   C9 01 BC 01 01 E2 00 91 01 01 CB 01 CC 01 02 15
   01 F2 01 01 99 01 6F 01 01 9E 01 9F 01 01 C4 01
   BC 01 00 B1 00 91 01 00 A3 02 17 01 00 74 01 7D
   01 00 74 01 62 01 00 22 00 2F 01 00 20 00 33 01
   01 86 01 87 01 00 4A 00 4B 01 01 1B 01 1C 01 00
   DF 00 E0 01 01 96 01 97 01 00 1D 00 37 01 00 1A
   00 3C 01 00 AD 00 AE 01
  ScalaSig: length = 0x3 (unknown attribute)
   05 02 00
