Classfile /Users/mw/Projects/slang-braindump/.jar/jar8/assemble/slang-braindump/assemble/content/org/scalatest/Filter$.class
  Last modified May 29, 2022; size 2989 bytes
  SHA-256 checksum 7e0133da982298a814393f05e62a302aa430272385dd996f6ce9cfc83d162411
  Compiled from "Filter.scala"
public final class org.scalatest.Filter$ implements java.io.Serializable
  minor version: 0
  major version: 52
  flags: (0x0031) ACC_PUBLIC, ACC_FINAL, ACC_SUPER
  this_class: #2                          // org/scalatest/Filter$
  super_class: #4                         // java/lang/Object
  interfaces: 1, fields: 1, methods: 10, attributes: 3
Constant pool:
    #1 = Utf8               org/scalatest/Filter$
    #2 = Class              #1            // org/scalatest/Filter$
    #3 = Utf8               java/lang/Object
    #4 = Class              #3            // java/lang/Object
    #5 = Utf8               java/io/Serializable
    #6 = Class              #5            // java/io/Serializable
    #7 = Utf8               Filter.scala
    #8 = Utf8               MODULE$
    #9 = Utf8               Lorg/scalatest/Filter$;
   #10 = Utf8               <clinit>
   #11 = Utf8               ()V
   #12 = Utf8               <init>
   #13 = NameAndType        #12:#11       // "<init>":()V
   #14 = Methodref          #2.#13        // org/scalatest/Filter$."<init>":()V
   #15 = NameAndType        #8:#9         // MODULE$:Lorg/scalatest/Filter$;
   #16 = Fieldref           #2.#15        // org/scalatest/Filter$.MODULE$:Lorg/scalatest/Filter$;
   #17 = Utf8               IgnoreTag
   #18 = Utf8               ()Ljava/lang/String;
   #19 = Utf8               org.scalatest.Ignore
   #20 = String             #19           // org.scalatest.Ignore
   #21 = Utf8               this
   #22 = Utf8               apply
   #23 = Utf8               (Lscala/Option;Lscala/collection/immutable/Set;ZLorg/scalatest/DynaTags;)Lorg/scalatest/Filter;
   #24 = Utf8               (Lscala/Option<Lscala/collection/immutable/Set<Ljava/lang/String;>;>;Lscala/collection/immutable/Set<Ljava/lang/String;>;ZLorg/scalatest/DynaTags;)Lorg/scalatest/Filter;
   #25 = Utf8               tagsToInclude
   #26 = Utf8               tagsToExclude
   #27 = Utf8               excludeNestedSuites
   #28 = Utf8               dynaTags
   #29 = Utf8               org/scalatest/Filter
   #30 = Class              #29           // org/scalatest/Filter
   #31 = Utf8               (Lscala/Option;Lscala/collection/immutable/Set;ZLorg/scalatest/DynaTags;)V
   #32 = NameAndType        #12:#31       // "<init>":(Lscala/Option;Lscala/collection/immutable/Set;ZLorg/scalatest/DynaTags;)V
   #33 = Methodref          #30.#32       // org/scalatest/Filter."<init>":(Lscala/Option;Lscala/collection/immutable/Set;ZLorg/scalatest/DynaTags;)V
   #34 = Utf8               Lscala/Option;
   #35 = Utf8               Lscala/collection/immutable/Set;
   #36 = Utf8               Z
   #37 = Utf8               Lorg/scalatest/DynaTags;
   #38 = Utf8               apply$default$1
   #39 = Utf8               ()Lscala/Option;
   #40 = Utf8               ()Lscala/Option<Lscala/collection/immutable/Set<Ljava/lang/String;>;>;
   #41 = Utf8               scala/None$
   #42 = Class              #41           // scala/None$
   #43 = Utf8               Lscala/None$;
   #44 = NameAndType        #8:#43        // MODULE$:Lscala/None$;
   #45 = Fieldref           #42.#44       // scala/None$.MODULE$:Lscala/None$;
   #46 = Utf8               apply$default$2
   #47 = Utf8               ()Lscala/collection/immutable/Set;
   #48 = Utf8               ()Lscala/collection/immutable/Set<Ljava/lang/String;>;
   #49 = Utf8               scala/Predef$
   #50 = Class              #49           // scala/Predef$
   #51 = Utf8               Lscala/Predef$;
   #52 = NameAndType        #8:#51        // MODULE$:Lscala/Predef$;
   #53 = Fieldref           #50.#52       // scala/Predef$.MODULE$:Lscala/Predef$;
   #54 = Utf8               Set
   #55 = Utf8               ()Lscala/collection/immutable/Set$;
   #56 = NameAndType        #54:#55       // Set:()Lscala/collection/immutable/Set$;
   #57 = Methodref          #50.#56       // scala/Predef$.Set:()Lscala/collection/immutable/Set$;
   #58 = Utf8               scala/runtime/ScalaRunTime$
   #59 = Class              #58           // scala/runtime/ScalaRunTime$
   #60 = Utf8               Lscala/runtime/ScalaRunTime$;
   #61 = NameAndType        #8:#60        // MODULE$:Lscala/runtime/ScalaRunTime$;
   #62 = Fieldref           #59.#61       // scala/runtime/ScalaRunTime$.MODULE$:Lscala/runtime/ScalaRunTime$;
   #63 = Utf8               java/lang/String
   #64 = Class              #63           // java/lang/String
   #65 = Utf8               [Ljava/lang/Object;
   #66 = Class              #65           // "[Ljava/lang/Object;"
   #67 = Utf8               wrapRefArray
   #68 = Utf8               ([Ljava/lang/Object;)Lscala/collection/immutable/ArraySeq;
   #69 = NameAndType        #67:#68       // wrapRefArray:([Ljava/lang/Object;)Lscala/collection/immutable/ArraySeq;
   #70 = Methodref          #59.#69       // scala/runtime/ScalaRunTime$.wrapRefArray:([Ljava/lang/Object;)Lscala/collection/immutable/ArraySeq;
   #71 = Utf8               scala/collection/immutable/Set$
   #72 = Class              #71           // scala/collection/immutable/Set$
   #73 = Utf8               (Lscala/collection/immutable/Seq;)Ljava/lang/Object;
   #74 = NameAndType        #22:#73       // apply:(Lscala/collection/immutable/Seq;)Ljava/lang/Object;
   #75 = Methodref          #72.#74       // scala/collection/immutable/Set$.apply:(Lscala/collection/immutable/Seq;)Ljava/lang/Object;
   #76 = Utf8               scala/collection/immutable/Set
   #77 = Class              #76           // scala/collection/immutable/Set
   #78 = Utf8               apply$default$3
   #79 = Utf8               ()Z
   #80 = Utf8               apply$default$4
   #81 = Utf8               ()Lorg/scalatest/DynaTags;
   #82 = Utf8               org/scalatest/DynaTags
   #83 = Class              #82           // org/scalatest/DynaTags
   #84 = Utf8               Map
   #85 = Utf8               ()Lscala/collection/immutable/Map$;
   #86 = NameAndType        #84:#85       // Map:()Lscala/collection/immutable/Map$;
   #87 = Methodref          #50.#86       // scala/Predef$.Map:()Lscala/collection/immutable/Map$;
   #88 = Utf8               scala/collection/immutable/Map$
   #89 = Class              #88           // scala/collection/immutable/Map$
   #90 = Utf8               empty
   #91 = Utf8               ()Lscala/collection/immutable/Map;
   #92 = NameAndType        #90:#91       // empty:()Lscala/collection/immutable/Map;
   #93 = Methodref          #89.#92       // scala/collection/immutable/Map$.empty:()Lscala/collection/immutable/Map;
   #94 = Utf8               (Lscala/collection/immutable/Map;Lscala/collection/immutable/Map;)V
   #95 = NameAndType        #12:#94       // "<init>":(Lscala/collection/immutable/Map;Lscala/collection/immutable/Map;)V
   #96 = Methodref          #83.#95       // org/scalatest/DynaTags."<init>":(Lscala/collection/immutable/Map;Lscala/collection/immutable/Map;)V
   #97 = Utf8               default
   #98 = Utf8               ()Lorg/scalatest/Filter;
   #99 = NameAndType        #38:#39       // apply$default$1:()Lscala/Option;
  #100 = Methodref          #2.#99        // org/scalatest/Filter$.apply$default$1:()Lscala/Option;
  #101 = NameAndType        #46:#47       // apply$default$2:()Lscala/collection/immutable/Set;
  #102 = Methodref          #2.#101       // org/scalatest/Filter$.apply$default$2:()Lscala/collection/immutable/Set;
  #103 = NameAndType        #78:#79       // apply$default$3:()Z
  #104 = Methodref          #2.#103       // org/scalatest/Filter$.apply$default$3:()Z
  #105 = NameAndType        #80:#81       // apply$default$4:()Lorg/scalatest/DynaTags;
  #106 = Methodref          #2.#105       // org/scalatest/Filter$.apply$default$4:()Lorg/scalatest/DynaTags;
  #107 = NameAndType        #22:#23       // apply:(Lscala/Option;Lscala/collection/immutable/Set;ZLorg/scalatest/DynaTags;)Lorg/scalatest/Filter;
  #108 = Methodref          #2.#107       // org/scalatest/Filter$.apply:(Lscala/Option;Lscala/collection/immutable/Set;ZLorg/scalatest/DynaTags;)Lorg/scalatest/Filter;
  #109 = Utf8               writeReplace
  #110 = Utf8               ()Ljava/lang/Object;
  #111 = Utf8               scala/runtime/ModuleSerializationProxy
  #112 = Class              #111          // scala/runtime/ModuleSerializationProxy
  #113 = Utf8               (Ljava/lang/Class;)V
  #114 = NameAndType        #12:#113      // "<init>":(Ljava/lang/Class;)V
  #115 = Methodref          #112.#114     // scala/runtime/ModuleSerializationProxy."<init>":(Ljava/lang/Class;)V
  #116 = Methodref          #4.#13        // java/lang/Object."<init>":()V
  #117 = Utf8               Code
  #118 = Utf8               LineNumberTable
  #119 = Utf8               LocalVariableTable
  #120 = Utf8               Signature
  #121 = Utf8               MethodParameters
  #122 = Utf8               SourceFile
  #123 = Utf8               ScalaInlineInfo
  #124 = Utf8               Scala
{
  public static final org.scalatest.Filter$ MODULE$;
    descriptor: Lorg/scalatest/Filter$;
    flags: (0x0019) ACC_PUBLIC, ACC_STATIC, ACC_FINAL

  public static {};
    descriptor: ()V
    flags: (0x0009) ACC_PUBLIC, ACC_STATIC
    Code:
      stack=2, locals=0, args_size=0
         0: new           #2                  // class org/scalatest/Filter$
         3: dup
         4: invokespecial #14                 // Method "<init>":()V
         7: putstatic     #16                 // Field MODULE$:Lorg/scalatest/Filter$;
        10: return
      LineNumberTable:
        line 252: 0

  private final java.lang.String IgnoreTag();
    descriptor: ()Ljava/lang/String;
    flags: (0x0012) ACC_PRIVATE, ACC_FINAL
    Code:
      stack=1, locals=1, args_size=1
         0: ldc           #20                 // String org.scalatest.Ignore
         2: areturn
      LocalVariableTable:
        Start  Length  Slot  Name   Signature
            0       3     0  this   Lorg/scalatest/Filter$;

  public org.scalatest.Filter apply(scala.Option<scala.collection.immutable.Set<java.lang.String>>, scala.collection.immutable.Set<java.lang.String>, boolean, org.scalatest.DynaTags);
    descriptor: (Lscala/Option;Lscala/collection/immutable/Set;ZLorg/scalatest/DynaTags;)Lorg/scalatest/Filter;
    flags: (0x0001) ACC_PUBLIC
    Code:
      stack=6, locals=5, args_size=5
         0: new           #30                 // class org/scalatest/Filter
         3: dup
         4: aload_1
         5: aload_2
         6: iload_3
         7: aload         4
         9: invokespecial #33                 // Method org/scalatest/Filter."<init>":(Lscala/Option;Lscala/collection/immutable/Set;ZLorg/scalatest/DynaTags;)V
        12: areturn
      LineNumberTable:
        line 268: 0
      LocalVariableTable:
        Start  Length  Slot  Name   Signature
            0      13     0  this   Lorg/scalatest/Filter$;
            0      13     1 tagsToInclude   Lscala/Option;
            0      13     2 tagsToExclude   Lscala/collection/immutable/Set;
            0      13     3 excludeNestedSuites   Z
            0      13     4 dynaTags   Lorg/scalatest/DynaTags;
    Signature: #24                          // (Lscala/Option<Lscala/collection/immutable/Set<Ljava/lang/String;>;>;Lscala/collection/immutable/Set<Ljava/lang/String;>;ZLorg/scalatest/DynaTags;)Lorg/scalatest/Filter;
    MethodParameters:
      Name                           Flags
      tagsToInclude                  final
      tagsToExclude                  final
      excludeNestedSuites            final
      dynaTags                       final

  public scala.Option<scala.collection.immutable.Set<java.lang.String>> apply$default$1();
    descriptor: ()Lscala/Option;
    flags: (0x0001) ACC_PUBLIC
    Code:
      stack=1, locals=1, args_size=1
         0: getstatic     #45                 // Field scala/None$.MODULE$:Lscala/None$;
         3: areturn
      LineNumberTable:
        line 267: 0
      LocalVariableTable:
        Start  Length  Slot  Name   Signature
            0       4     0  this   Lorg/scalatest/Filter$;
    Signature: #40                          // ()Lscala/Option<Lscala/collection/immutable/Set<Ljava/lang/String;>;>;

  public scala.collection.immutable.Set<java.lang.String> apply$default$2();
    descriptor: ()Lscala/collection/immutable/Set;
    flags: (0x0001) ACC_PUBLIC
    Code:
      stack=6, locals=1, args_size=1
         0: getstatic     #53                 // Field scala/Predef$.MODULE$:Lscala/Predef$;
         3: invokevirtual #57                 // Method scala/Predef$.Set:()Lscala/collection/immutable/Set$;
         6: getstatic     #62                 // Field scala/runtime/ScalaRunTime$.MODULE$:Lscala/runtime/ScalaRunTime$;
         9: iconst_1
        10: anewarray     #64                 // class java/lang/String
        13: dup
        14: iconst_0
        15: ldc           #20                 // String org.scalatest.Ignore
        17: aastore
        18: checkcast     #66                 // class "[Ljava/lang/Object;"
        21: invokevirtual #70                 // Method scala/runtime/ScalaRunTime$.wrapRefArray:([Ljava/lang/Object;)Lscala/collection/immutable/ArraySeq;
        24: invokevirtual #75                 // Method scala/collection/immutable/Set$.apply:(Lscala/collection/immutable/Seq;)Ljava/lang/Object;
        27: checkcast     #77                 // class scala/collection/immutable/Set
        30: areturn
      LineNumberTable:
        line 267: 0
      LocalVariableTable:
        Start  Length  Slot  Name   Signature
            0      31     0  this   Lorg/scalatest/Filter$;
    Signature: #48                          // ()Lscala/collection/immutable/Set<Ljava/lang/String;>;

  public boolean apply$default$3();
    descriptor: ()Z
    flags: (0x0001) ACC_PUBLIC
    Code:
      stack=1, locals=1, args_size=1
         0: iconst_0
         1: ireturn
      LineNumberTable:
        line 267: 0
      LocalVariableTable:
        Start  Length  Slot  Name   Signature
            0       2     0  this   Lorg/scalatest/Filter$;

  public org.scalatest.DynaTags apply$default$4();
    descriptor: ()Lorg/scalatest/DynaTags;
    flags: (0x0001) ACC_PUBLIC
    Code:
      stack=4, locals=1, args_size=1
         0: new           #83                 // class org/scalatest/DynaTags
         3: dup
         4: getstatic     #53                 // Field scala/Predef$.MODULE$:Lscala/Predef$;
         7: invokevirtual #87                 // Method scala/Predef$.Map:()Lscala/collection/immutable/Map$;
        10: invokevirtual #93                 // Method scala/collection/immutable/Map$.empty:()Lscala/collection/immutable/Map;
        13: getstatic     #53                 // Field scala/Predef$.MODULE$:Lscala/Predef$;
        16: invokevirtual #87                 // Method scala/Predef$.Map:()Lscala/collection/immutable/Map$;
        19: invokevirtual #93                 // Method scala/collection/immutable/Map$.empty:()Lscala/collection/immutable/Map;
        22: invokespecial #96                 // Method org/scalatest/DynaTags."<init>":(Lscala/collection/immutable/Map;Lscala/collection/immutable/Map;)V
        25: areturn
      LineNumberTable:
        line 267: 0
      LocalVariableTable:
        Start  Length  Slot  Name   Signature
            0      26     0  this   Lorg/scalatest/Filter$;

  public org.scalatest.Filter default();
    descriptor: ()Lorg/scalatest/Filter;
    flags: (0x0001) ACC_PUBLIC
    Code:
      stack=5, locals=1, args_size=1
         0: aload_0
         1: aload_0
         2: invokevirtual #100                // Method apply$default$1:()Lscala/Option;
         5: aload_0
         6: invokevirtual #102                // Method apply$default$2:()Lscala/collection/immutable/Set;
         9: aload_0
        10: invokevirtual #104                // Method apply$default$3:()Z
        13: aload_0
        14: invokevirtual #106                // Method apply$default$4:()Lorg/scalatest/DynaTags;
        17: invokevirtual #108                // Method apply:(Lscala/Option;Lscala/collection/immutable/Set;ZLorg/scalatest/DynaTags;)Lorg/scalatest/Filter;
        20: areturn
      LineNumberTable:
        line 276: 0
      LocalVariableTable:
        Start  Length  Slot  Name   Signature
            0      21     0  this   Lorg/scalatest/Filter$;

  private java.lang.Object writeReplace();
    descriptor: ()Ljava/lang/Object;
    flags: (0x0002) ACC_PRIVATE
    Code:
      stack=3, locals=1, args_size=1
         0: new           #112                // class scala/runtime/ModuleSerializationProxy
         3: dup
         4: ldc           #2                  // class org/scalatest/Filter$
         6: invokespecial #115                // Method scala/runtime/ModuleSerializationProxy."<init>":(Ljava/lang/Class;)V
         9: areturn
      LineNumberTable:
        line 252: 0
      LocalVariableTable:
        Start  Length  Slot  Name   Signature
            0      10     0  this   Lorg/scalatest/Filter$;

  private org.scalatest.Filter$();
    descriptor: ()V
    flags: (0x0002) ACC_PRIVATE
    Code:
      stack=1, locals=1, args_size=1
         0: aload_0
         1: invokespecial #116                // Method java/lang/Object."<init>":()V
         4: return
      LineNumberTable:
        line 277: 0
        line 252: 4
      LocalVariableTable:
        Start  Length  Slot  Name   Signature
            0       5     0  this   Lorg/scalatest/Filter$;
}
SourceFile: "Filter.scala"
  ScalaInlineInfo: length = 0x31 (unknown attribute)
   01 01 00 09 00 0C 00 0B 01 00 11 00 12 01 00 16
   00 17 01 00 26 00 27 01 00 2E 00 2F 01 00 4E 00
   4F 01 00 50 00 51 01 00 61 00 62 01 00 6D 00 6E
   01
  Scala: length = 0x0 (unknown attribute)

