Classfile /Users/mw/Projects/slang-braindump/.jar/jar8/assemble/slang-braindump/assemble/content/org/scalatest/FutureAsyncOutcome.class
  Last modified May 29, 2022; size 9848 bytes
  SHA-256 checksum 00108f03b8b6a948369a71913337bffe08a4aed2f018a8a9b5f34d411ab154e8
  Compiled from "AsyncOutcome.scala"
public class org.scalatest.FutureAsyncOutcome implements org.scalatest.AsyncOutcome,scala.Product,java.io.Serializable
  minor version: 0
  major version: 52
  flags: (0x0021) ACC_PUBLIC, ACC_SUPER
  this_class: #2                          // org/scalatest/FutureAsyncOutcome
  super_class: #4                         // java/lang/Object
  interfaces: 3, fields: 3, methods: 26, attributes: 6
Constant pool:
    #1 = Utf8               org/scalatest/FutureAsyncOutcome
    #2 = Class              #1            // org/scalatest/FutureAsyncOutcome
    #3 = Utf8               java/lang/Object
    #4 = Class              #3            // java/lang/Object
    #5 = Utf8               org/scalatest/AsyncOutcome
    #6 = Class              #5            // org/scalatest/AsyncOutcome
    #7 = Utf8               scala/Product
    #8 = Class              #7            // scala/Product
    #9 = Utf8               java/io/Serializable
   #10 = Class              #9            // java/io/Serializable
   #11 = Utf8               AsyncOutcome.scala
   #12 = Utf8               Lscala/reflect/ScalaSignature;
   #13 = Utf8               bytes
   #14 = Utf8               \u0006\u0005\u0005Uf!\u0002\u0011\"\u0001\u0006*\u0003\u0002\u0003!\u0001\u0005+\u0007I\u0011A!\t\u0011-\u0003!\u0011#Q\u0001\n\tC\u0001\u0002\u0014\u0001\u0003\u0016\u0004%\t!\u0014\u0005\t5\u0002\u0011\t\u0012)A\u0005\u001d\"A1\f\u0001B\u0001B\u0003-A\fC\u0003`\u0001\u0011\u0005\u0001\rC\u0004g\u0001\t\u0007IQB4\t\r-\u0004\u0001\u0015!\u0004i\u0011\u0015a\u0007\u0001\"\u0001n\u0011\u0015\t\b\u0001\"\u0001s\u0011\u0015\u0019\b\u0001\"\u0001B\u0011\u0015!\b\u0001\"\u0001v\u0011\u001dI\b!!A\u0005\u0002iD\u0001b \u0001\u0012\u0002\u0013\u0005\u0011\u0011\u0001\u0005\n\u0003/\u0001\u0011\u0013!C\u0001\u00033A\u0011\"!\b\u0001\u0003\u0003%\t%a\b\t\u0013\u0005E\u0002!!A\u0005\u0002\u0005M\u0002\"CA\u001e\u0001\u0005\u0005I\u0011AA\u001f\u0011%\tI\u0005AA\u0001\n\u0003\nY\u0005C\u0005\u0002Z\u0001\t\t\u0011\"\u0001\u0002\\!I\u0011Q\r\u0001\u0002\u0002\u0013\u0005\u0013q\r\u0005\n\u0003W\u0002\u0011\u0011!C!\u0003[B\u0011\"a\u001c\u0001\u0003\u0003%\t%!\u001d\t\u0013\u0005M\u0004!!A\u0005B\u0005UtACA=C\u0005\u0005\t\u0012A\u0011\u0002|\u0019I\u0001%IA\u0001\u0012\u0003\t\u0013Q\u0010\u0005\u0007?j!\t!!#\t\u0013\u0005=$$!A\u0005F\u0005E\u0004\"CAF5\u0005\u0005I\u0011QAG\u0011%\t9JGA\u0001\n\u0003\u000bI\nC\u0005\u0002,j\t\t\u0011\"\u0003\u0002.\n\u0011b)\u001e;ve\u0016\f5/\u001f8d\u001fV$8m\\7f\u0015\t\u00113%A\u0005tG\u0006d\u0017\r^3ti*\tA%A\u0002pe\u001e\u001cR\u0001\u0001\u0014-aM\u0002\"a\n\u0016\u000e\u0003!R\u0011!K\u0001\u0006g\u000e\fG.Y\u0005\u0003W!\u0012a!\u00118z%\u00164\u0007CA\u0017/\u001b\u0005\t\u0013BA\u0018\"\u00051\t5/\u001f8d\u001fV$8m\\7f!\t9\u0013\'\u0003\u00023Q\t9\u0001K]8ek\u000e$\bC\u0001\u001b>\u001d\t)4H\u0004\u00027u5\tqG\u0003\u00029s\u00051AH]8piz\u001a\u0001!C\u0001*\u0013\ta\u0004&A\u0004qC\u000e\\\u0017mZ3\n\u0005yz$\u0001D*fe&\fG.\u001b>bE2,\'B\u0001\u001f)\u0003\u00191W\u000f^;sKV\t!\tE\u0002D\r\"k\u0011\u0001\u0012\u0006\u0003\u000b\"\n!bY8oGV\u0014(/\u001a8u\u0013\t9EI\u0001\u0004GkR,(/\u001a\t\u0003[%K!AS\u0011\u0003\u000f=+HoY8nK\u00069a-\u001e;ve\u0016\u0004\u0013!D8o\u0007>l\u0007\u000f\\3uK\u001a+h.F\u0001O!\u00119s*U,\n\u0005AC#!\u0003$v]\u000e$\u0018n\u001c82!\r\u0011V\u000bS\u0007\u0002\'*\u0011A\u000bK\u0001\u0005kRLG.\u0003\u0002W\'\n\u0019AK]=\u0011\u0005\u001dB\u0016BA-)\u0005\u0011)f.\u001b;\u0002\u001d=t7i\\7qY\u0016$XMR;oA\u0005\u00191\r\u001e=\u0011\u0005\rk\u0016B\u00010E\u0005A)\u00050Z2vi&|gnQ8oi\u0016DH/\u0001\u0004=S:LGO\u0010\u000b\u0004C\u0012,GC\u00012d!\ti\u0003\u0001C\u0003\\\r\u0001\u000fA\fC\u0003A\r\u0001\u0007!\tC\u0003M\r\u0001\u0007a*\u0001\u0004ti\u0006$Xo]\u000b\u0002QB\u0011Q&[\u0005\u0003U\u0006\u0012qcU2bY\u0006$Vm\u001d;Ti\u0006$XMZ;m\'R\fG/^:\u0002\u000fM$\u0018\r^;tA\u0005AAo\\*uCR,8/F\u0001o!\tis.\u0003\u0002qC\t11\u000b^1ukN\f\u0011\u0002^8PkR\u001cw.\\3\u0016\u0003!\u000b\u0011\u0003^8GkR,(/Z(g\u001fV$8m\\7f\u0003=!xNR;ukJ,w*\u001e;d_6,W#\u0001<\u0011\u00055:\u0018B\u0001=\"\u000551U\u000f^;sK>+HoY8nK\u0006!1m\u001c9z)\rYXP \u000b\u0003ErDQaW\u0007A\u0004qCq\u0001Q\u0007\u0011\u0002\u0003\u0007!\tC\u0004M\u001bA\u0005\t\u0019\u0001(\u0002\u001d\r|\u0007/\u001f\u0013eK\u001a\fW\u000f\u001c;%cU\u0011\u00111\u0001\u0016\u0004\u0005\u0006\u00151FAA\u0004!\u0011\tI!a\u0005\u000e\u0005\u0005-!\u0002BA\u0007\u0003\u001f\t\u0011\"\u001e8dQ\u0016\u001c7.\u001a3\u000b\u0007\u0005E\u0001&\u0001\u0006b]:|G/\u0019;j_:LA!!\u0006\u0002\f\t\tRO\\2iK\u000e\\W\r\u001a,be&\fgnY3\u0002\u001d\r|\u0007/\u001f\u0013eK\u001a\fW\u000f\u001c;%eU\u0011\u00111\u0004\u0016\u0004\u001d\u0006\u0015\u0011!\u00049s_\u0012,8\r\u001e)sK\u001aL\u00070\u0006\u0002\u0002\"A!\u00111EA\u0017\u001b\t\t)C\u0003\u0003\u0002(\u0005%\u0012\u0001\u00027b]\u001eT!!a\u000b\u0002\t)\fg/Y\u0005\u0005\u0003_\t)C\u0001\u0004TiJLgnZ\u0001\raJ|G-^2u\u0003JLG/_\u000b\u0003\u0003k\u00012aJA\u001c\u0013\r\tI\u0004\u000b\u0002\u0004\u0013:$\u0018A\u00049s_\u0012,8\r^#mK6,g\u000e\u001e\u000b\u0005\u0003\u007f\t)\u0005E\u0002(\u0003\u0003J1!a\u0011)\u0005\r\te.\u001f\u0005\n\u0003\u000f\u0012\u0012\u0011!a\u0001\u0003k\t1\u0001\u001f\u00132\u0003=\u0001(o\u001c3vGRLE/\u001a:bi>\u0014XCAA\'!\u0019\ty%!\u0016\u0002@5\u0011\u0011\u0011\u000b\u0006\u0004\u0003\'B\u0013AC2pY2,7\r^5p]&!\u0011qKA)\u0005!IE/\u001a:bi>\u0014\u0018\u0001C2b]\u0016\u000bX/\u00197\u0015\t\u0005u\u00131\r\t\u0004O\u0005}\u0013bAA1Q\t9!i\\8mK\u0006t\u0007\"CA$)\u0005\u0005\t\u0019AA \u0003I\u0001(o\u001c3vGR,E.Z7f]Rt\u0015-\\3\u0015\t\u0005\u0005\u0012\u0011\u000e\u0005\n\u0003\u000f*\u0012\u0011!a\u0001\u0003k\t\u0001\u0002[1tQ\u000e{G-\u001a\u000b\u0003\u0003k\t\u0001\u0002^8TiJLgn\u001a\u000b\u0003\u0003C\ta!Z9vC2\u001cH\u0003BA/\u0003oB\u0011\"a\u0012\u0019\u0003\u0003\u0005\r!a\u0010\u0002%\u0019+H/\u001e:f\u0003NLhnY(vi\u000e|W.\u001a\t\u0003[i\u0019BA\u0007\u0014\u0002\u0000A!\u0011\u0011QAD\u001b\t\t\u0019I\u0003\u0003\u0002\u0006\u0006%\u0012AA5p\u0013\rq\u00141\u0011\u000b\u0003\u0003w\nQ!\u00199qYf$b!a$\u0002\u0014\u0006UEc\u00012\u0002\u0012\")1,\ba\u00029\")\u0001)\ba\u0001\u0005\")A*\ba\u0001\u001d\u00069QO\\1qa2LH\u0003BAN\u0003O\u0003RaJAO\u0003CK1!a()\u0005\u0019y\u0005\u000f^5p]B)q%a)C\u001d&\u0019\u0011Q\u0015\u0015\u0003\rQ+\b\u000f\\33\u0011!\tIKHA\u0001\u0002\u0004\u0011\u0017a\u0001=%a\u0005aqO]5uKJ+\u0007\u000f\\1dKR\u0011\u0011q\u0016\t\u0005\u0003G\t\t,\u0003\u0003\u00024\u0006\u0015\"AB(cU\u0016\u001cG\u000f
   #15 = Utf8               java/lang/invoke/MethodHandles$Lookup
   #16 = Class              #15           // java/lang/invoke/MethodHandles$Lookup
   #17 = Utf8               java/lang/invoke/MethodHandles
   #18 = Class              #17           // java/lang/invoke/MethodHandles
   #19 = Utf8               Lookup
   #20 = Utf8               scala/concurrent/duration/Duration$Infinite
   #21 = Class              #20           // scala/concurrent/duration/Duration$Infinite
   #22 = Utf8               scala/concurrent/duration/Duration
   #23 = Class              #22           // scala/concurrent/duration/Duration
   #24 = Utf8               Infinite
   #25 = Utf8               future
   #26 = Utf8               Lscala/concurrent/Future;
   #27 = Utf8               Lscala/concurrent/Future<Lorg/scalatest/Outcome;>;
   #28 = Utf8               onCompleteFun
   #29 = Utf8               Lscala/Function1;
   #30 = Utf8               Lscala/Function1<Lscala/util/Try<Lorg/scalatest/Outcome;>;Lscala/runtime/BoxedUnit;>;
   #31 = Utf8               status
   #32 = Utf8               Lorg/scalatest/ScalaTestStatefulStatus;
   #33 = Utf8               unapply
   #34 = Utf8               (Lorg/scalatest/FutureAsyncOutcome;)Lscala/Option;
   #35 = Utf8               (Lorg/scalatest/FutureAsyncOutcome;)Lscala/Option<Lscala/Tuple2<Lscala/concurrent/Future<Lorg/scalatest/Outcome;>;Lscala/Function1<Lscala/util/Try<Lorg/scalatest/Outcome;>;Lscala/runtime/BoxedUnit;>;>;>;
   #36 = Utf8               x$0
   #37 = Utf8               org/scalatest/FutureAsyncOutcome$
   #38 = Class              #37           // org/scalatest/FutureAsyncOutcome$
   #39 = Utf8               MODULE$
   #40 = Utf8               Lorg/scalatest/FutureAsyncOutcome$;
   #41 = NameAndType        #39:#40       // MODULE$:Lorg/scalatest/FutureAsyncOutcome$;
   #42 = Fieldref           #38.#41       // org/scalatest/FutureAsyncOutcome$.MODULE$:Lorg/scalatest/FutureAsyncOutcome$;
   #43 = NameAndType        #33:#34       // unapply:(Lorg/scalatest/FutureAsyncOutcome;)Lscala/Option;
   #44 = Methodref          #38.#43       // org/scalatest/FutureAsyncOutcome$.unapply:(Lorg/scalatest/FutureAsyncOutcome;)Lscala/Option;
   #45 = Utf8               Lorg/scalatest/FutureAsyncOutcome;
   #46 = Utf8               apply
   #47 = Utf8               (Lscala/concurrent/Future;Lscala/Function1;Lscala/concurrent/ExecutionContext;)Lorg/scalatest/FutureAsyncOutcome;
   #48 = Utf8               (Lscala/concurrent/Future<Lorg/scalatest/Outcome;>;Lscala/Function1<Lscala/util/Try<Lorg/scalatest/Outcome;>;Lscala/runtime/BoxedUnit;>;Lscala/concurrent/ExecutionContext;)Lorg/scalatest/FutureAsyncOutcome;
   #49 = Utf8               ctx
   #50 = NameAndType        #46:#47       // apply:(Lscala/concurrent/Future;Lscala/Function1;Lscala/concurrent/ExecutionContext;)Lorg/scalatest/FutureAsyncOutcome;
   #51 = Methodref          #38.#50       // org/scalatest/FutureAsyncOutcome$.apply:(Lscala/concurrent/Future;Lscala/Function1;Lscala/concurrent/ExecutionContext;)Lorg/scalatest/FutureAsyncOutcome;
   #52 = Utf8               Lscala/concurrent/ExecutionContext;
   #53 = Utf8               productElementNames
   #54 = Utf8               ()Lscala/collection/Iterator;
   #55 = Utf8               ()Lscala/collection/Iterator<Ljava/lang/String;>;
   #56 = Utf8               productElementNames$
   #57 = Utf8               (Lscala/Product;)Lscala/collection/Iterator;
   #58 = NameAndType        #56:#57       // productElementNames$:(Lscala/Product;)Lscala/collection/Iterator;
   #59 = InterfaceMethodref #8.#58        // scala/Product.productElementNames$:(Lscala/Product;)Lscala/collection/Iterator;
   #60 = Utf8               this
   #61 = Utf8               ()Lscala/concurrent/Future;
   #62 = Utf8               ()Lscala/concurrent/Future<Lorg/scalatest/Outcome;>;
   #63 = NameAndType        #25:#26       // future:Lscala/concurrent/Future;
   #64 = Fieldref           #2.#63        // org/scalatest/FutureAsyncOutcome.future:Lscala/concurrent/Future;
   #65 = Utf8               ()Lscala/Function1;
   #66 = Utf8               ()Lscala/Function1<Lscala/util/Try<Lorg/scalatest/Outcome;>;Lscala/runtime/BoxedUnit;>;
   #67 = NameAndType        #28:#29       // onCompleteFun:Lscala/Function1;
   #68 = Fieldref           #2.#67        // org/scalatest/FutureAsyncOutcome.onCompleteFun:Lscala/Function1;
   #69 = Utf8               ()Lorg/scalatest/ScalaTestStatefulStatus;
   #70 = NameAndType        #31:#32       // status:Lorg/scalatest/ScalaTestStatefulStatus;
   #71 = Fieldref           #2.#70        // org/scalatest/FutureAsyncOutcome.status:Lorg/scalatest/ScalaTestStatefulStatus;
   #72 = Utf8               toStatus
   #73 = Utf8               ()Lorg/scalatest/Status;
   #74 = NameAndType        #31:#69       // status:()Lorg/scalatest/ScalaTestStatefulStatus;
   #75 = Methodref          #2.#74        // org/scalatest/FutureAsyncOutcome.status:()Lorg/scalatest/ScalaTestStatefulStatus;
   #76 = Utf8               toOutcome
   #77 = Utf8               ()Lorg/scalatest/Outcome;
   #78 = Utf8               scala/concurrent/Await$
   #79 = Class              #78           // scala/concurrent/Await$
   #80 = Utf8               Lscala/concurrent/Await$;
   #81 = NameAndType        #39:#80       // MODULE$:Lscala/concurrent/Await$;
   #82 = Fieldref           #79.#81       // scala/concurrent/Await$.MODULE$:Lscala/concurrent/Await$;
   #83 = NameAndType        #25:#61       // future:()Lscala/concurrent/Future;
   #84 = Methodref          #2.#83        // org/scalatest/FutureAsyncOutcome.future:()Lscala/concurrent/Future;
   #85 = Utf8               scala/concurrent/duration/Duration$
   #86 = Class              #85           // scala/concurrent/duration/Duration$
   #87 = Utf8               Lscala/concurrent/duration/Duration$;
   #88 = NameAndType        #39:#87       // MODULE$:Lscala/concurrent/duration/Duration$;
   #89 = Fieldref           #86.#88       // scala/concurrent/duration/Duration$.MODULE$:Lscala/concurrent/duration/Duration$;
   #90 = Utf8               Inf
   #91 = Utf8               ()Lscala/concurrent/duration/Duration$Infinite;
   #92 = NameAndType        #90:#91       // Inf:()Lscala/concurrent/duration/Duration$Infinite;
   #93 = Methodref          #86.#92       // scala/concurrent/duration/Duration$.Inf:()Lscala/concurrent/duration/Duration$Infinite;
   #94 = Utf8               result
   #95 = Utf8               (Lscala/concurrent/Awaitable;Lscala/concurrent/duration/Duration;)Ljava/lang/Object;
   #96 = NameAndType        #94:#95       // result:(Lscala/concurrent/Awaitable;Lscala/concurrent/duration/Duration;)Ljava/lang/Object;
   #97 = Methodref          #79.#96       // scala/concurrent/Await$.result:(Lscala/concurrent/Awaitable;Lscala/concurrent/duration/Duration;)Ljava/lang/Object;
   #98 = Utf8               org/scalatest/Outcome
   #99 = Class              #98           // org/scalatest/Outcome
  #100 = Utf8               toFutureOfOutcome
  #101 = Utf8               toFutureOutcome
  #102 = Utf8               ()Lorg/scalatest/FutureOutcome;
  #103 = Utf8               org/scalatest/FutureOutcome$
  #104 = Class              #103          // org/scalatest/FutureOutcome$
  #105 = Utf8               Lorg/scalatest/FutureOutcome$;
  #106 = NameAndType        #39:#105      // MODULE$:Lorg/scalatest/FutureOutcome$;
  #107 = Fieldref           #104.#106     // org/scalatest/FutureOutcome$.MODULE$:Lorg/scalatest/FutureOutcome$;
  #108 = Utf8               (Lscala/concurrent/Future;)Lorg/scalatest/FutureOutcome;
  #109 = NameAndType        #46:#108      // apply:(Lscala/concurrent/Future;)Lorg/scalatest/FutureOutcome;
  #110 = Methodref          #104.#109     // org/scalatest/FutureOutcome$.apply:(Lscala/concurrent/Future;)Lorg/scalatest/FutureOutcome;
  #111 = Utf8               copy
  #112 = Utf8               <init>
  #113 = Utf8               (Lscala/concurrent/Future;Lscala/Function1;Lscala/concurrent/ExecutionContext;)V
  #114 = NameAndType        #112:#113     // "<init>":(Lscala/concurrent/Future;Lscala/Function1;Lscala/concurrent/ExecutionContext;)V
  #115 = Methodref          #2.#114       // org/scalatest/FutureAsyncOutcome."<init>":(Lscala/concurrent/Future;Lscala/Function1;Lscala/concurrent/ExecutionContext;)V
  #116 = Utf8               copy$default$1
  #117 = Utf8               copy$default$2
  #118 = NameAndType        #28:#65       // onCompleteFun:()Lscala/Function1;
  #119 = Methodref          #2.#118       // org/scalatest/FutureAsyncOutcome.onCompleteFun:()Lscala/Function1;
  #120 = Utf8               productPrefix
  #121 = Utf8               ()Ljava/lang/String;
  #122 = Utf8               FutureAsyncOutcome
  #123 = String             #122          // FutureAsyncOutcome
  #124 = Utf8               productArity
  #125 = Utf8               ()I
  #126 = Utf8               productElement
  #127 = Utf8               (I)Ljava/lang/Object;
  #128 = Utf8               x$1
  #129 = Utf8               scala/runtime/Statics
  #130 = Class              #129          // scala/runtime/Statics
  #131 = Utf8               ioobe
  #132 = NameAndType        #131:#127     // ioobe:(I)Ljava/lang/Object;
  #133 = Methodref          #130.#132     // scala/runtime/Statics.ioobe:(I)Ljava/lang/Object;
  #134 = Utf8               I
  #135 = Utf8               productIterator
  #136 = Utf8               ()Lscala/collection/Iterator<Ljava/lang/Object;>;
  #137 = Utf8               scala/runtime/ScalaRunTime$
  #138 = Class              #137          // scala/runtime/ScalaRunTime$
  #139 = Utf8               Lscala/runtime/ScalaRunTime$;
  #140 = NameAndType        #39:#139      // MODULE$:Lscala/runtime/ScalaRunTime$;
  #141 = Fieldref           #138.#140     // scala/runtime/ScalaRunTime$.MODULE$:Lscala/runtime/ScalaRunTime$;
  #142 = Utf8               typedProductIterator
  #143 = NameAndType        #142:#57      // typedProductIterator:(Lscala/Product;)Lscala/collection/Iterator;
  #144 = Methodref          #138.#143     // scala/runtime/ScalaRunTime$.typedProductIterator:(Lscala/Product;)Lscala/collection/Iterator;
  #145 = Utf8               canEqual
  #146 = Utf8               (Ljava/lang/Object;)Z
  #147 = Utf8               Ljava/lang/Object;
  #148 = Utf8               productElementName
  #149 = Utf8               (I)Ljava/lang/String;
  #150 = String             #25           // future
  #151 = String             #28           // onCompleteFun
  #152 = String             #49           // ctx
  #153 = Utf8               java/lang/String
  #154 = Class              #153          // java/lang/String
  #155 = Utf8               hashCode
  #156 = Utf8               _hashCode
  #157 = Utf8               (Lscala/Product;)I
  #158 = NameAndType        #156:#157     // _hashCode:(Lscala/Product;)I
  #159 = Methodref          #138.#158     // scala/runtime/ScalaRunTime$._hashCode:(Lscala/Product;)I
  #160 = Utf8               toString
  #161 = Utf8               _toString
  #162 = Utf8               (Lscala/Product;)Ljava/lang/String;
  #163 = NameAndType        #161:#162     // _toString:(Lscala/Product;)Ljava/lang/String;
  #164 = Methodref          #138.#163     // scala/runtime/ScalaRunTime$._toString:(Lscala/Product;)Ljava/lang/String;
  #165 = Utf8               equals
  #166 = NameAndType        #165:#146     // equals:(Ljava/lang/Object;)Z
  #167 = Methodref          #4.#166       // java/lang/Object.equals:(Ljava/lang/Object;)Z
  #168 = NameAndType        #145:#146     // canEqual:(Ljava/lang/Object;)Z
  #169 = Methodref          #2.#168       // org/scalatest/FutureAsyncOutcome.canEqual:(Ljava/lang/Object;)Z
  #170 = Utf8               scala/concurrent/Future
  #171 = Class              #170          // scala/concurrent/Future
  #172 = Utf8               scala/Function1
  #173 = Class              #172          // scala/Function1
  #174 = Utf8               $anonfun$new$1
  #175 = Utf8               (Lorg/scalatest/FutureAsyncOutcome;Lscala/util/Try;)V
  #176 = Utf8               $this
  #177 = Utf8               tri
  #178 = Utf8               (Ljava/lang/Object;)Ljava/lang/Object;
  #179 = NameAndType        #46:#178      // apply:(Ljava/lang/Object;)Ljava/lang/Object;
  #180 = InterfaceMethodref #173.#179     // scala/Function1.apply:(Ljava/lang/Object;)Ljava/lang/Object;
  #181 = Utf8               scala/util/Failure
  #182 = Class              #181          // scala/util/Failure
  #183 = Utf8               exception
  #184 = Utf8               ()Ljava/lang/Throwable;
  #185 = NameAndType        #183:#184     // exception:()Ljava/lang/Throwable;
  #186 = Methodref          #182.#185     // scala/util/Failure.exception:()Ljava/lang/Throwable;
  #187 = Utf8               org/scalatest/ScalaTestStatefulStatus
  #188 = Class              #187          // org/scalatest/ScalaTestStatefulStatus
  #189 = Utf8               setFailedWith
  #190 = Utf8               (Ljava/lang/Throwable;)V
  #191 = NameAndType        #189:#190     // setFailedWith:(Ljava/lang/Throwable;)V
  #192 = Methodref          #188.#191     // org/scalatest/ScalaTestStatefulStatus.setFailedWith:(Ljava/lang/Throwable;)V
  #193 = Utf8               scala/runtime/BoxedUnit
  #194 = Class              #193          // scala/runtime/BoxedUnit
  #195 = Utf8               UNIT
  #196 = Utf8               Lscala/runtime/BoxedUnit;
  #197 = NameAndType        #195:#196     // UNIT:Lscala/runtime/BoxedUnit;
  #198 = Fieldref           #194.#197     // scala/runtime/BoxedUnit.UNIT:Lscala/runtime/BoxedUnit;
  #199 = Utf8               setCompleted
  #200 = Utf8               ()V
  #201 = NameAndType        #199:#200     // setCompleted:()V
  #202 = Methodref          #188.#201     // org/scalatest/ScalaTestStatefulStatus.setCompleted:()V
  #203 = Utf8               ex
  #204 = Utf8               Ljava/lang/Throwable;
  #205 = Utf8               Lscala/util/Try;
  #206 = Utf8               scala/util/Try
  #207 = Class              #206          // scala/util/Try
  #208 = Utf8               (Lscala/concurrent/Future<Lorg/scalatest/Outcome;>;Lscala/Function1<Lscala/util/Try<Lorg/scalatest/Outcome;>;Lscala/runtime/BoxedUnit;>;Lscala/concurrent/ExecutionContext;)V
  #209 = NameAndType        #112:#200     // "<init>":()V
  #210 = Methodref          #4.#209       // java/lang/Object."<init>":()V
  #211 = Utf8               $init$
  #212 = Utf8               (Lscala/Product;)V
  #213 = NameAndType        #211:#212     // $init$:(Lscala/Product;)V
  #214 = InterfaceMethodref #8.#213       // scala/Product.$init$:(Lscala/Product;)V
  #215 = Methodref          #188.#209     // org/scalatest/ScalaTestStatefulStatus."<init>":()V
  #216 = MethodType         #178          //  (Ljava/lang/Object;)Ljava/lang/Object;
  #217 = Utf8               $anonfun$new$1$adapted
  #218 = Utf8               (Lorg/scalatest/FutureAsyncOutcome;Lscala/util/Try;)Ljava/lang/Object;
  #219 = NameAndType        #217:#218     // $anonfun$new$1$adapted:(Lorg/scalatest/FutureAsyncOutcome;Lscala/util/Try;)Ljava/lang/Object;
  #220 = Methodref          #2.#219       // org/scalatest/FutureAsyncOutcome.$anonfun$new$1$adapted:(Lorg/scalatest/FutureAsyncOutcome;Lscala/util/Try;)Ljava/lang/Object;
  #221 = MethodHandle       6:#220        // REF_invokeStatic org/scalatest/FutureAsyncOutcome.$anonfun$new$1$adapted:(Lorg/scalatest/FutureAsyncOutcome;Lscala/util/Try;)Ljava/lang/Object;
  #222 = Utf8               (Lscala/util/Try;)Ljava/lang/Object;
  #223 = MethodType         #222          //  (Lscala/util/Try;)Ljava/lang/Object;
  #224 = Integer            5
  #225 = Integer            1
  #226 = Utf8               java/lang/invoke/LambdaMetafactory
  #227 = Class              #226          // java/lang/invoke/LambdaMetafactory
  #228 = Utf8               altMetafactory
  #229 = Utf8               (Ljava/lang/invoke/MethodHandles$Lookup;Ljava/lang/String;Ljava/lang/invoke/MethodType;[Ljava/lang/Object;)Ljava/lang/invoke/CallSite;
  #230 = NameAndType        #228:#229     // altMetafactory:(Ljava/lang/invoke/MethodHandles$Lookup;Ljava/lang/String;Ljava/lang/invoke/MethodType;[Ljava/lang/Object;)Ljava/lang/invoke/CallSite;
  #231 = Methodref          #227.#230     // java/lang/invoke/LambdaMetafactory.altMetafactory:(Ljava/lang/invoke/MethodHandles$Lookup;Ljava/lang/String;Ljava/lang/invoke/MethodType;[Ljava/lang/Object;)Ljava/lang/invoke/CallSite;
  #232 = MethodHandle       6:#231        // REF_invokeStatic java/lang/invoke/LambdaMetafactory.altMetafactory:(Ljava/lang/invoke/MethodHandles$Lookup;Ljava/lang/String;Ljava/lang/invoke/MethodType;[Ljava/lang/Object;)Ljava/lang/invoke/CallSite;
  #233 = Utf8               (Lorg/scalatest/FutureAsyncOutcome;)Lscala/Function1;
  #234 = NameAndType        #46:#233      // apply:(Lorg/scalatest/FutureAsyncOutcome;)Lscala/Function1;
  #235 = InvokeDynamic      #0:#234       // #0:apply:(Lorg/scalatest/FutureAsyncOutcome;)Lscala/Function1;
  #236 = Utf8               onComplete
  #237 = Utf8               (Lscala/Function1;Lscala/concurrent/ExecutionContext;)V
  #238 = NameAndType        #236:#237     // onComplete:(Lscala/Function1;Lscala/concurrent/ExecutionContext;)V
  #239 = InterfaceMethodref #171.#238     // scala/concurrent/Future.onComplete:(Lscala/Function1;Lscala/concurrent/ExecutionContext;)V
  #240 = NameAndType        #174:#175     // $anonfun$new$1:(Lorg/scalatest/FutureAsyncOutcome;Lscala/util/Try;)V
  #241 = Methodref          #2.#240       // org/scalatest/FutureAsyncOutcome.$anonfun$new$1:(Lorg/scalatest/FutureAsyncOutcome;Lscala/util/Try;)V
  #242 = Utf8               $deserializeLambda$
  #243 = Utf8               (Ljava/lang/invoke/SerializedLambda;)Ljava/lang/Object;
  #244 = Utf8               scala/runtime/LambdaDeserialize
  #245 = Class              #244          // scala/runtime/LambdaDeserialize
  #246 = Utf8               bootstrap
  #247 = Utf8               (Ljava/lang/invoke/MethodHandles$Lookup;Ljava/lang/String;Ljava/lang/invoke/MethodType;[Ljava/lang/invoke/MethodHandle;)Ljava/lang/invoke/CallSite;
  #248 = NameAndType        #246:#247     // bootstrap:(Ljava/lang/invoke/MethodHandles$Lookup;Ljava/lang/String;Ljava/lang/invoke/MethodType;[Ljava/lang/invoke/MethodHandle;)Ljava/lang/invoke/CallSite;
  #249 = Methodref          #245.#248     // scala/runtime/LambdaDeserialize.bootstrap:(Ljava/lang/invoke/MethodHandles$Lookup;Ljava/lang/String;Ljava/lang/invoke/MethodType;[Ljava/lang/invoke/MethodHandle;)Ljava/lang/invoke/CallSite;
  #250 = MethodHandle       6:#249        // REF_invokeStatic scala/runtime/LambdaDeserialize.bootstrap:(Ljava/lang/invoke/MethodHandles$Lookup;Ljava/lang/String;Ljava/lang/invoke/MethodType;[Ljava/lang/invoke/MethodHandle;)Ljava/lang/invoke/CallSite;
  #251 = Utf8               lambdaDeserialize
  #252 = NameAndType        #251:#243     // lambdaDeserialize:(Ljava/lang/invoke/SerializedLambda;)Ljava/lang/Object;
  #253 = InvokeDynamic      #1:#252       // #1:lambdaDeserialize:(Ljava/lang/invoke/SerializedLambda;)Ljava/lang/Object;
  #254 = Utf8               Signature
  #255 = Utf8               Code
  #256 = Utf8               LocalVariableTable
  #257 = Utf8               MethodParameters
  #258 = Utf8               LineNumberTable
  #259 = Utf8               StackMapTable
  #260 = Utf8               InnerClasses
  #261 = Utf8               SourceFile
  #262 = Utf8               RuntimeVisibleAnnotations
  #263 = Utf8               BootstrapMethods
  #264 = Utf8               ScalaInlineInfo
  #265 = Utf8               ScalaSig
{
  private final scala.concurrent.Future<org.scalatest.Outcome> future;
    descriptor: Lscala/concurrent/Future;
    flags: (0x0012) ACC_PRIVATE, ACC_FINAL
    Signature: #27                          // Lscala/concurrent/Future<Lorg/scalatest/Outcome;>;

  private final scala.Function1<scala.util.Try<org.scalatest.Outcome>, scala.runtime.BoxedUnit> onCompleteFun;
    descriptor: Lscala/Function1;
    flags: (0x0012) ACC_PRIVATE, ACC_FINAL
    Signature: #30                          // Lscala/Function1<Lscala/util/Try<Lorg/scalatest/Outcome;>;Lscala/runtime/BoxedUnit;>;

  private final org.scalatest.ScalaTestStatefulStatus status;
    descriptor: Lorg/scalatest/ScalaTestStatefulStatus;
    flags: (0x0012) ACC_PRIVATE, ACC_FINAL

  public static scala.Option<scala.Tuple2<scala.concurrent.Future<org.scalatest.Outcome>, scala.Function1<scala.util.Try<org.scalatest.Outcome>, scala.runtime.BoxedUnit>>> unapply(org.scalatest.FutureAsyncOutcome);
    descriptor: (Lorg/scalatest/FutureAsyncOutcome;)Lscala/Option;
    flags: (0x0009) ACC_PUBLIC, ACC_STATIC
    Code:
      stack=2, locals=1, args_size=1
         0: getstatic     #42                 // Field org/scalatest/FutureAsyncOutcome$.MODULE$:Lorg/scalatest/FutureAsyncOutcome$;
         3: aload_0
         4: invokevirtual #44                 // Method org/scalatest/FutureAsyncOutcome$.unapply:(Lorg/scalatest/FutureAsyncOutcome;)Lscala/Option;
         7: areturn
      LocalVariableTable:
        Start  Length  Slot  Name   Signature
            0       8     0   x$0   Lorg/scalatest/FutureAsyncOutcome;
    Signature: #35                          // (Lorg/scalatest/FutureAsyncOutcome;)Lscala/Option<Lscala/Tuple2<Lscala/concurrent/Future<Lorg/scalatest/Outcome;>;Lscala/Function1<Lscala/util/Try<Lorg/scalatest/Outcome;>;Lscala/runtime/BoxedUnit;>;>;>;
    MethodParameters:
      Name                           Flags
      x$0                            final

  public static org.scalatest.FutureAsyncOutcome apply(scala.concurrent.Future<org.scalatest.Outcome>, scala.Function1<scala.util.Try<org.scalatest.Outcome>, scala.runtime.BoxedUnit>, scala.concurrent.ExecutionContext);
    descriptor: (Lscala/concurrent/Future;Lscala/Function1;Lscala/concurrent/ExecutionContext;)Lorg/scalatest/FutureAsyncOutcome;
    flags: (0x0009) ACC_PUBLIC, ACC_STATIC
    Code:
      stack=4, locals=3, args_size=3
         0: getstatic     #42                 // Field org/scalatest/FutureAsyncOutcome$.MODULE$:Lorg/scalatest/FutureAsyncOutcome$;
         3: aload_0
         4: aload_1
         5: aload_2
         6: invokevirtual #51                 // Method org/scalatest/FutureAsyncOutcome$.apply:(Lscala/concurrent/Future;Lscala/Function1;Lscala/concurrent/ExecutionContext;)Lorg/scalatest/FutureAsyncOutcome;
         9: areturn
      LocalVariableTable:
        Start  Length  Slot  Name   Signature
            0      10     0 future   Lscala/concurrent/Future;
            0      10     1 onCompleteFun   Lscala/Function1;
            0      10     2   ctx   Lscala/concurrent/ExecutionContext;
    Signature: #48                          // (Lscala/concurrent/Future<Lorg/scalatest/Outcome;>;Lscala/Function1<Lscala/util/Try<Lorg/scalatest/Outcome;>;Lscala/runtime/BoxedUnit;>;Lscala/concurrent/ExecutionContext;)Lorg/scalatest/FutureAsyncOutcome;
    MethodParameters:
      Name                           Flags
      future                         final
      onCompleteFun                  final
      ctx                            final

  public scala.collection.Iterator<java.lang.String> productElementNames();
    descriptor: ()Lscala/collection/Iterator;
    flags: (0x0001) ACC_PUBLIC
    Code:
      stack=1, locals=1, args_size=1
         0: aload_0
         1: invokestatic  #59                 // InterfaceMethod scala/Product.productElementNames$:(Lscala/Product;)Lscala/collection/Iterator;
         4: areturn
      LineNumberTable:
        line 33: 0
      LocalVariableTable:
        Start  Length  Slot  Name   Signature
            0       5     0  this   Lorg/scalatest/FutureAsyncOutcome;
    Signature: #55                          // ()Lscala/collection/Iterator<Ljava/lang/String;>;

  public scala.concurrent.Future<org.scalatest.Outcome> future();
    descriptor: ()Lscala/concurrent/Future;
    flags: (0x0001) ACC_PUBLIC
    Code:
      stack=1, locals=1, args_size=1
         0: aload_0
         1: getfield      #64                 // Field future:Lscala/concurrent/Future;
         4: areturn
      LineNumberTable:
        line 33: 0
      LocalVariableTable:
        Start  Length  Slot  Name   Signature
            0       5     0  this   Lorg/scalatest/FutureAsyncOutcome;
    Signature: #62                          // ()Lscala/concurrent/Future<Lorg/scalatest/Outcome;>;

  public scala.Function1<scala.util.Try<org.scalatest.Outcome>, scala.runtime.BoxedUnit> onCompleteFun();
    descriptor: ()Lscala/Function1;
    flags: (0x0001) ACC_PUBLIC
    Code:
      stack=1, locals=1, args_size=1
         0: aload_0
         1: getfield      #68                 // Field onCompleteFun:Lscala/Function1;
         4: areturn
      LineNumberTable:
        line 33: 0
      LocalVariableTable:
        Start  Length  Slot  Name   Signature
            0       5     0  this   Lorg/scalatest/FutureAsyncOutcome;
    Signature: #66                          // ()Lscala/Function1<Lscala/util/Try<Lorg/scalatest/Outcome;>;Lscala/runtime/BoxedUnit;>;

  private final org.scalatest.ScalaTestStatefulStatus status();
    descriptor: ()Lorg/scalatest/ScalaTestStatefulStatus;
    flags: (0x0012) ACC_PRIVATE, ACC_FINAL
    Code:
      stack=1, locals=1, args_size=1
         0: aload_0
         1: getfield      #71                 // Field status:Lorg/scalatest/ScalaTestStatefulStatus;
         4: areturn
      LineNumberTable:
        line 35: 0
      LocalVariableTable:
        Start  Length  Slot  Name   Signature
            0       5     0  this   Lorg/scalatest/FutureAsyncOutcome;

  public org.scalatest.Status toStatus();
    descriptor: ()Lorg/scalatest/Status;
    flags: (0x0001) ACC_PUBLIC
    Code:
      stack=1, locals=1, args_size=1
         0: aload_0
         1: invokespecial #75                 // Method status:()Lorg/scalatest/ScalaTestStatefulStatus;
         4: areturn
      LineNumberTable:
        line 48: 0
      LocalVariableTable:
        Start  Length  Slot  Name   Signature
            0       5     0  this   Lorg/scalatest/FutureAsyncOutcome;

  public org.scalatest.Outcome toOutcome();
    descriptor: ()Lorg/scalatest/Outcome;
    flags: (0x0001) ACC_PUBLIC
    Code:
      stack=3, locals=1, args_size=1
         0: getstatic     #82                 // Field scala/concurrent/Await$.MODULE$:Lscala/concurrent/Await$;
         3: aload_0
         4: invokevirtual #84                 // Method future:()Lscala/concurrent/Future;
         7: getstatic     #89                 // Field scala/concurrent/duration/Duration$.MODULE$:Lscala/concurrent/duration/Duration$;
        10: invokevirtual #93                 // Method scala/concurrent/duration/Duration$.Inf:()Lscala/concurrent/duration/Duration$Infinite;
        13: invokevirtual #97                 // Method scala/concurrent/Await$.result:(Lscala/concurrent/Awaitable;Lscala/concurrent/duration/Duration;)Ljava/lang/Object;
        16: checkcast     #99                 // class org/scalatest/Outcome
        19: areturn
      LineNumberTable:
        line 50: 0
      LocalVariableTable:
        Start  Length  Slot  Name   Signature
            0      20     0  this   Lorg/scalatest/FutureAsyncOutcome;

  public scala.concurrent.Future<org.scalatest.Outcome> toFutureOfOutcome();
    descriptor: ()Lscala/concurrent/Future;
    flags: (0x0001) ACC_PUBLIC
    Code:
      stack=1, locals=1, args_size=1
         0: aload_0
         1: invokevirtual #84                 // Method future:()Lscala/concurrent/Future;
         4: areturn
      LineNumberTable:
        line 52: 0
      LocalVariableTable:
        Start  Length  Slot  Name   Signature
            0       5     0  this   Lorg/scalatest/FutureAsyncOutcome;
    Signature: #62                          // ()Lscala/concurrent/Future<Lorg/scalatest/Outcome;>;

  public org.scalatest.FutureOutcome toFutureOutcome();
    descriptor: ()Lorg/scalatest/FutureOutcome;
    flags: (0x0001) ACC_PUBLIC
    Code:
      stack=2, locals=1, args_size=1
         0: getstatic     #107                // Field org/scalatest/FutureOutcome$.MODULE$:Lorg/scalatest/FutureOutcome$;
         3: aload_0
         4: invokevirtual #84                 // Method future:()Lscala/concurrent/Future;
         7: invokevirtual #110                // Method org/scalatest/FutureOutcome$.apply:(Lscala/concurrent/Future;)Lorg/scalatest/FutureOutcome;
        10: areturn
      LineNumberTable:
        line 53: 0
      LocalVariableTable:
        Start  Length  Slot  Name   Signature
            0      11     0  this   Lorg/scalatest/FutureAsyncOutcome;

  public org.scalatest.FutureAsyncOutcome copy(scala.concurrent.Future<org.scalatest.Outcome>, scala.Function1<scala.util.Try<org.scalatest.Outcome>, scala.runtime.BoxedUnit>, scala.concurrent.ExecutionContext);
    descriptor: (Lscala/concurrent/Future;Lscala/Function1;Lscala/concurrent/ExecutionContext;)Lorg/scalatest/FutureAsyncOutcome;
    flags: (0x0001) ACC_PUBLIC
    Code:
      stack=5, locals=4, args_size=4
         0: new           #2                  // class org/scalatest/FutureAsyncOutcome
         3: dup
         4: aload_1
         5: aload_2
         6: aload_3
         7: invokespecial #115                // Method "<init>":(Lscala/concurrent/Future;Lscala/Function1;Lscala/concurrent/ExecutionContext;)V
        10: areturn
      LineNumberTable:
        line 33: 0
      LocalVariableTable:
        Start  Length  Slot  Name   Signature
            0      11     0  this   Lorg/scalatest/FutureAsyncOutcome;
            0      11     1 future   Lscala/concurrent/Future;
            0      11     2 onCompleteFun   Lscala/Function1;
            0      11     3   ctx   Lscala/concurrent/ExecutionContext;
    Signature: #48                          // (Lscala/concurrent/Future<Lorg/scalatest/Outcome;>;Lscala/Function1<Lscala/util/Try<Lorg/scalatest/Outcome;>;Lscala/runtime/BoxedUnit;>;Lscala/concurrent/ExecutionContext;)Lorg/scalatest/FutureAsyncOutcome;
    MethodParameters:
      Name                           Flags
      future                         final
      onCompleteFun                  final
      ctx                            final

  public scala.concurrent.Future<org.scalatest.Outcome> copy$default$1();
    descriptor: ()Lscala/concurrent/Future;
    flags: (0x0001) ACC_PUBLIC
    Code:
      stack=1, locals=1, args_size=1
         0: aload_0
         1: invokevirtual #84                 // Method future:()Lscala/concurrent/Future;
         4: areturn
      LineNumberTable:
        line 33: 0
      LocalVariableTable:
        Start  Length  Slot  Name   Signature
            0       5     0  this   Lorg/scalatest/FutureAsyncOutcome;
    Signature: #62                          // ()Lscala/concurrent/Future<Lorg/scalatest/Outcome;>;

  public scala.Function1<scala.util.Try<org.scalatest.Outcome>, scala.runtime.BoxedUnit> copy$default$2();
    descriptor: ()Lscala/Function1;
    flags: (0x0001) ACC_PUBLIC
    Code:
      stack=1, locals=1, args_size=1
         0: aload_0
         1: invokevirtual #119                // Method onCompleteFun:()Lscala/Function1;
         4: areturn
      LineNumberTable:
        line 33: 0
      LocalVariableTable:
        Start  Length  Slot  Name   Signature
            0       5     0  this   Lorg/scalatest/FutureAsyncOutcome;
    Signature: #66                          // ()Lscala/Function1<Lscala/util/Try<Lorg/scalatest/Outcome;>;Lscala/runtime/BoxedUnit;>;

  public java.lang.String productPrefix();
    descriptor: ()Ljava/lang/String;
    flags: (0x0001) ACC_PUBLIC
    Code:
      stack=1, locals=1, args_size=1
         0: ldc           #123                // String FutureAsyncOutcome
         2: areturn
      LineNumberTable:
        line 33: 0
      LocalVariableTable:
        Start  Length  Slot  Name   Signature
            0       3     0  this   Lorg/scalatest/FutureAsyncOutcome;

  public int productArity();
    descriptor: ()I
    flags: (0x0001) ACC_PUBLIC
    Code:
      stack=1, locals=1, args_size=1
         0: iconst_2
         1: ireturn
      LineNumberTable:
        line 33: 0
      LocalVariableTable:
        Start  Length  Slot  Name   Signature
            0       2     0  this   Lorg/scalatest/FutureAsyncOutcome;

  public java.lang.Object productElement(int);
    descriptor: (I)Ljava/lang/Object;
    flags: (0x0001) ACC_PUBLIC
    Code:
      stack=1, locals=3, args_size=2
         0: iload_1
         1: istore_2
         2: iload_2
         3: tableswitch   { // 0 to 1
                       0: 24
                       1: 31
                 default: 38
            }
        24: aload_0
        25: invokevirtual #84                 // Method future:()Lscala/concurrent/Future;
        28: goto          45
        31: aload_0
        32: invokevirtual #119                // Method onCompleteFun:()Lscala/Function1;
        35: goto          45
        38: iload_1
        39: invokestatic  #133                // Method scala/runtime/Statics.ioobe:(I)Ljava/lang/Object;
        42: goto          45
        45: areturn
      StackMapTable: number_of_entries = 4
        frame_type = 252 /* append */
          offset_delta = 24
          locals = [ int ]
        frame_type = 6 /* same */
        frame_type = 6 /* same */
        frame_type = 70 /* same_locals_1_stack_item */
          stack = [ class java/lang/Object ]
      LineNumberTable:
        line 33: 0
      LocalVariableTable:
        Start  Length  Slot  Name   Signature
            0      46     0  this   Lorg/scalatest/FutureAsyncOutcome;
            0      46     1   x$1   I
    MethodParameters:
      Name                           Flags
      x$1                            final

  public scala.collection.Iterator<java.lang.Object> productIterator();
    descriptor: ()Lscala/collection/Iterator;
    flags: (0x0001) ACC_PUBLIC
    Code:
      stack=2, locals=1, args_size=1
         0: getstatic     #141                // Field scala/runtime/ScalaRunTime$.MODULE$:Lscala/runtime/ScalaRunTime$;
         3: aload_0
         4: invokevirtual #144                // Method scala/runtime/ScalaRunTime$.typedProductIterator:(Lscala/Product;)Lscala/collection/Iterator;
         7: areturn
      LineNumberTable:
        line 33: 0
      LocalVariableTable:
        Start  Length  Slot  Name   Signature
            0       8     0  this   Lorg/scalatest/FutureAsyncOutcome;
    Signature: #136                         // ()Lscala/collection/Iterator<Ljava/lang/Object;>;

  public boolean canEqual(java.lang.Object);
    descriptor: (Ljava/lang/Object;)Z
    flags: (0x0001) ACC_PUBLIC
    Code:
      stack=1, locals=2, args_size=2
         0: aload_1
         1: instanceof    #2                  // class org/scalatest/FutureAsyncOutcome
         4: ireturn
      LineNumberTable:
        line 33: 0
      LocalVariableTable:
        Start  Length  Slot  Name   Signature
            0       5     0  this   Lorg/scalatest/FutureAsyncOutcome;
            0       5     1   x$1   Ljava/lang/Object;
    MethodParameters:
      Name                           Flags
      x$1                            final

  public java.lang.String productElementName(int);
    descriptor: (I)Ljava/lang/String;
    flags: (0x0001) ACC_PUBLIC
    Code:
      stack=1, locals=3, args_size=2
         0: iload_1
         1: istore_2
         2: iload_2
         3: tableswitch   { // 0 to 2
                       0: 28
                       1: 33
                       2: 38
                 default: 43
            }
        28: ldc           #150                // String future
        30: goto          53
        33: ldc           #151                // String onCompleteFun
        35: goto          53
        38: ldc           #152                // String ctx
        40: goto          53
        43: iload_1
        44: invokestatic  #133                // Method scala/runtime/Statics.ioobe:(I)Ljava/lang/Object;
        47: checkcast     #154                // class java/lang/String
        50: goto          53
        53: areturn
      StackMapTable: number_of_entries = 5
        frame_type = 252 /* append */
          offset_delta = 28
          locals = [ int ]
        frame_type = 4 /* same */
        frame_type = 4 /* same */
        frame_type = 4 /* same */
        frame_type = 73 /* same_locals_1_stack_item */
          stack = [ class java/lang/String ]
      LineNumberTable:
        line 33: 0
      LocalVariableTable:
        Start  Length  Slot  Name   Signature
            0      54     0  this   Lorg/scalatest/FutureAsyncOutcome;
            0      54     1   x$1   I
    MethodParameters:
      Name                           Flags
      x$1                            final

  public int hashCode();
    descriptor: ()I
    flags: (0x0001) ACC_PUBLIC
    Code:
      stack=2, locals=1, args_size=1
         0: getstatic     #141                // Field scala/runtime/ScalaRunTime$.MODULE$:Lscala/runtime/ScalaRunTime$;
         3: aload_0
         4: invokevirtual #159                // Method scala/runtime/ScalaRunTime$._hashCode:(Lscala/Product;)I
         7: ireturn
      LineNumberTable:
        line 33: 0
      LocalVariableTable:
        Start  Length  Slot  Name   Signature
            0       8     0  this   Lorg/scalatest/FutureAsyncOutcome;

  public java.lang.String toString();
    descriptor: ()Ljava/lang/String;
    flags: (0x0001) ACC_PUBLIC
    Code:
      stack=2, locals=1, args_size=1
         0: getstatic     #141                // Field scala/runtime/ScalaRunTime$.MODULE$:Lscala/runtime/ScalaRunTime$;
         3: aload_0
         4: invokevirtual #164                // Method scala/runtime/ScalaRunTime$._toString:(Lscala/Product;)Ljava/lang/String;
         7: areturn
      LineNumberTable:
        line 33: 0
      LocalVariableTable:
        Start  Length  Slot  Name   Signature
            0       8     0  this   Lorg/scalatest/FutureAsyncOutcome;

  public boolean equals(java.lang.Object);
    descriptor: (Ljava/lang/Object;)Z
    flags: (0x0001) ACC_PUBLIC
    Code:
      stack=2, locals=7, args_size=2
         0: aload_0
         1: aload_1
         2: if_acmpeq     118
         5: aload_1
         6: astore_3
         7: aload_3
         8: instanceof    #2                  // class org/scalatest/FutureAsyncOutcome
        11: ifeq          19
        14: iconst_1
        15: istore_2
        16: goto          27
        19: goto          22
        22: iconst_0
        23: istore_2
        24: goto          27
        27: iload_2
        28: ifeq          122
        31: aload_1
        32: checkcast     #2                  // class org/scalatest/FutureAsyncOutcome
        35: astore        4
        37: aload_0
        38: invokevirtual #84                 // Method future:()Lscala/concurrent/Future;
        41: aload         4
        43: invokevirtual #84                 // Method future:()Lscala/concurrent/Future;
        46: astore        5
        48: dup
        49: ifnonnull     61
        52: pop
        53: aload         5
        55: ifnull        69
        58: goto          114
        61: aload         5
        63: invokevirtual #167                // Method java/lang/Object.equals:(Ljava/lang/Object;)Z
        66: ifeq          114
        69: aload_0
        70: invokevirtual #119                // Method onCompleteFun:()Lscala/Function1;
        73: aload         4
        75: invokevirtual #119                // Method onCompleteFun:()Lscala/Function1;
        78: astore        6
        80: dup
        81: ifnonnull     93
        84: pop
        85: aload         6
        87: ifnull        101
        90: goto          114
        93: aload         6
        95: invokevirtual #167                // Method java/lang/Object.equals:(Ljava/lang/Object;)Z
        98: ifeq          114
       101: aload         4
       103: aload_0
       104: invokevirtual #169                // Method canEqual:(Ljava/lang/Object;)Z
       107: ifeq          114
       110: iconst_1
       111: goto          115
       114: iconst_0
       115: ifeq          122
       118: iconst_1
       119: goto          123
       122: iconst_0
       123: ireturn
      StackMapTable: number_of_entries = 12
        frame_type = 253 /* append */
          offset_delta = 19
          locals = [ top, class java/lang/Object ]
        frame_type = 2 /* same */
        frame_type = 255 /* full_frame */
          offset_delta = 4
          locals = [ class org/scalatest/FutureAsyncOutcome, class java/lang/Object, int, class java/lang/Object ]
          stack = []
        frame_type = 255 /* full_frame */
          offset_delta = 33
          locals = [ class org/scalatest/FutureAsyncOutcome, class java/lang/Object, int, class java/lang/Object, class org/scalatest/FutureAsyncOutcome, class scala/concurrent/Future ]
          stack = [ class scala/concurrent/Future ]
        frame_type = 7 /* same */
        frame_type = 255 /* full_frame */
          offset_delta = 23
          locals = [ class org/scalatest/FutureAsyncOutcome, class java/lang/Object, int, class java/lang/Object, class org/scalatest/FutureAsyncOutcome, class scala/concurrent/Future, class scala/Function1 ]
          stack = [ class scala/Function1 ]
        frame_type = 7 /* same */
        frame_type = 250 /* chop */
          offset_delta = 12
        frame_type = 64 /* same_locals_1_stack_item */
          stack = [ int ]
        frame_type = 255 /* full_frame */
          offset_delta = 2
          locals = [ class org/scalatest/FutureAsyncOutcome, class java/lang/Object ]
          stack = []
        frame_type = 253 /* append */
          offset_delta = 3
          locals = [ int, class java/lang/Object ]
        frame_type = 255 /* full_frame */
          offset_delta = 0
          locals = [ class org/scalatest/FutureAsyncOutcome, class java/lang/Object ]
          stack = [ int ]
      LineNumberTable:
        line 33: 0
      LocalVariableTable:
        Start  Length  Slot  Name   Signature
            0     124     0  this   Lorg/scalatest/FutureAsyncOutcome;
            0     124     1   x$1   Ljava/lang/Object;
    MethodParameters:
      Name                           Flags
      x$1                            final

  public static final void $anonfun$new$1(org.scalatest.FutureAsyncOutcome, scala.util.Try);
    descriptor: (Lorg/scalatest/FutureAsyncOutcome;Lscala/util/Try;)V
    flags: (0x1019) ACC_PUBLIC, ACC_STATIC, ACC_FINAL, ACC_SYNTHETIC
    Code:
      stack=2, locals=6, args_size=2
         0: aload_0
         1: invokevirtual #119                // Method onCompleteFun:()Lscala/Function1;
         4: aload_1
         5: invokeinterface #180,  2          // InterfaceMethod scala/Function1.apply:(Ljava/lang/Object;)Ljava/lang/Object;
        10: pop
        11: aload_1
        12: astore_3
        13: aload_3
        14: instanceof    #182                // class scala/util/Failure
        17: ifeq          49
        20: aload_3
        21: checkcast     #182                // class scala/util/Failure
        24: astore        4
        26: aload         4
        28: invokevirtual #186                // Method scala/util/Failure.exception:()Ljava/lang/Throwable;
        31: astore        5
        33: aload_0
        34: invokespecial #75                 // Method status:()Lorg/scalatest/ScalaTestStatefulStatus;
        37: aload         5
        39: invokevirtual #192                // Method org/scalatest/ScalaTestStatefulStatus.setFailedWith:(Ljava/lang/Throwable;)V
        42: getstatic     #198                // Field scala/runtime/BoxedUnit.UNIT:Lscala/runtime/BoxedUnit;
        45: astore_2
        46: goto          59
        49: goto          52
        52: getstatic     #198                // Field scala/runtime/BoxedUnit.UNIT:Lscala/runtime/BoxedUnit;
        55: astore_2
        56: goto          59
        59: aload_0
        60: invokespecial #75                 // Method status:()Lorg/scalatest/ScalaTestStatefulStatus;
        63: invokevirtual #202                // Method org/scalatest/ScalaTestStatefulStatus.setCompleted:()V
        66: return
      StackMapTable: number_of_entries = 3
        frame_type = 253 /* append */
          offset_delta = 49
          locals = [ top, class scala/util/Try ]
        frame_type = 2 /* same */
        frame_type = 255 /* full_frame */
          offset_delta = 6
          locals = [ class org/scalatest/FutureAsyncOutcome, class scala/util/Try, class scala/runtime/BoxedUnit, class scala/util/Try ]
          stack = []
      LineNumberTable:
        line 40: 0
        line 41: 11
        line 42: 13
        line 43: 52
        line 45: 59
      LocalVariableTable:
        Start  Length  Slot  Name   Signature
           33      16     5    ex   Ljava/lang/Throwable;
            0      67     0 $this   Lorg/scalatest/FutureAsyncOutcome;
            0      67     1   tri   Lscala/util/Try;
    MethodParameters:
      Name                           Flags
      $this                          final synthetic
      tri                            final

  public org.scalatest.FutureAsyncOutcome(scala.concurrent.Future<org.scalatest.Outcome>, scala.Function1<scala.util.Try<org.scalatest.Outcome>, scala.runtime.BoxedUnit>, scala.concurrent.ExecutionContext);
    descriptor: (Lscala/concurrent/Future;Lscala/Function1;Lscala/concurrent/ExecutionContext;)V
    flags: (0x0001) ACC_PUBLIC
    Code:
      stack=3, locals=4, args_size=4
         0: aload_0
         1: aload_1
         2: putfield      #64                 // Field future:Lscala/concurrent/Future;
         5: aload_0
         6: aload_2
         7: putfield      #68                 // Field onCompleteFun:Lscala/Function1;
        10: aload_0
        11: invokespecial #210                // Method java/lang/Object."<init>":()V
        14: aload_0
        15: invokestatic  #214                // InterfaceMethod scala/Product.$init$:(Lscala/Product;)V
        18: aload_0
        19: new           #188                // class org/scalatest/ScalaTestStatefulStatus
        22: dup
        23: invokespecial #215                // Method org/scalatest/ScalaTestStatefulStatus."<init>":()V
        26: putfield      #71                 // Field status:Lorg/scalatest/ScalaTestStatefulStatus;
        29: aload_1
        30: aload_0
        31: invokedynamic #235,  0            // InvokeDynamic #0:apply:(Lorg/scalatest/FutureAsyncOutcome;)Lscala/Function1;
        36: aload_3
        37: invokeinterface #239,  3          // InterfaceMethod scala/concurrent/Future.onComplete:(Lscala/Function1;Lscala/concurrent/ExecutionContext;)V
        42: return
      LineNumberTable:
        line 33: 0
        line 35: 18
        line 39: 29
        line 33: 42
      LocalVariableTable:
        Start  Length  Slot  Name   Signature
            0      43     0  this   Lorg/scalatest/FutureAsyncOutcome;
            0      43     1 future   Lscala/concurrent/Future;
            0      43     2 onCompleteFun   Lscala/Function1;
            0      43     3   ctx   Lscala/concurrent/ExecutionContext;
    Signature: #208                         // (Lscala/concurrent/Future<Lorg/scalatest/Outcome;>;Lscala/Function1<Lscala/util/Try<Lorg/scalatest/Outcome;>;Lscala/runtime/BoxedUnit;>;Lscala/concurrent/ExecutionContext;)V
    MethodParameters:
      Name                           Flags
      future                         final
      onCompleteFun                  final
      ctx                            final

  public static final java.lang.Object $anonfun$new$1$adapted(org.scalatest.FutureAsyncOutcome, scala.util.Try);
    descriptor: (Lorg/scalatest/FutureAsyncOutcome;Lscala/util/Try;)Ljava/lang/Object;
    flags: (0x1019) ACC_PUBLIC, ACC_STATIC, ACC_FINAL, ACC_SYNTHETIC
    Code:
      stack=2, locals=2, args_size=2
         0: aload_0
         1: aload_1
         2: invokestatic  #241                // Method $anonfun$new$1:(Lorg/scalatest/FutureAsyncOutcome;Lscala/util/Try;)V
         5: getstatic     #198                // Field scala/runtime/BoxedUnit.UNIT:Lscala/runtime/BoxedUnit;
         8: areturn
      LineNumberTable:
        line 39: 0
      LocalVariableTable:
        Start  Length  Slot  Name   Signature
            0       9     0 $this   Lorg/scalatest/FutureAsyncOutcome;
            0       9     1   tri   Lscala/util/Try;
    MethodParameters:
      Name                           Flags
      $this                          final
      tri                            final

  private static java.lang.Object $deserializeLambda$(java.lang.invoke.SerializedLambda);
    descriptor: (Ljava/lang/invoke/SerializedLambda;)Ljava/lang/Object;
    flags: (0x100a) ACC_PRIVATE, ACC_STATIC, ACC_SYNTHETIC
    Code:
      stack=1, locals=1, args_size=1
         0: aload_0
         1: invokedynamic #253,  0            // InvokeDynamic #1:lambdaDeserialize:(Ljava/lang/invoke/SerializedLambda;)Ljava/lang/Object;
         6: areturn
}
InnerClasses:
  public static final #19= #16 of #18;    // Lookup=class java/lang/invoke/MethodHandles$Lookup of class java/lang/invoke/MethodHandles
  public static abstract #24= #21 of #23; // Infinite=class scala/concurrent/duration/Duration$Infinite of class scala/concurrent/duration/Duration
SourceFile: "AsyncOutcome.scala"
RuntimeVisibleAnnotations:
  0: #12(#13=s#14)
    scala.reflect.ScalaSignature(
      bytes="\u0006\u0005\u0005Uf!\u0002\u0011\"\u0001\u0006*\u0003\u0002\u0003!\u0001\u0005+\u0007I\u0011A!\t\u0011-\u0003!\u0011#Q\u0001\n\tC\u0001\u0002\u0014\u0001\u0003\u0016\u0004%\t!\u0014\u0005\t5\u0002\u0011\t\u0012)A\u0005\u001d\"A1\f\u0001B\u0001B\u0003-A\fC\u0003`\u0001\u0011\u0005\u0001\rC\u0004g\u0001\t\u0007IQB4\t\r-\u0004\u0001\u0015!\u0004i\u0011\u0015a\u0007\u0001\"\u0001n\u0011\u0015\t\b\u0001\"\u0001s\u0011\u0015\u0019\b\u0001\"\u0001B\u0011\u0015!\b\u0001\"\u0001v\u0011\u001dI\b!!A\u0005\u0002iD\u0001b \u0001\u0012\u0002\u0013\u0005\u0011\u0011\u0001\u0005\n\u0003/\u0001\u0011\u0013!C\u0001\u00033A\u0011\"!\b\u0001\u0003\u0003%\t%a\b\t\u0013\u0005E\u0002!!A\u0005\u0002\u0005M\u0002\"CA\u001e\u0001\u0005\u0005I\u0011AA\u001f\u0011%\tI\u0005AA\u0001\n\u0003\nY\u0005C\u0005\u0002Z\u0001\t\t\u0011\"\u0001\u0002\\!I\u0011Q\r\u0001\u0002\u0002\u0013\u0005\u0013q\r\u0005\n\u0003W\u0002\u0011\u0011!C!\u0003[B\u0011\"a\u001c\u0001\u0003\u0003%\t%!\u001d\t\u0013\u0005M\u0004!!A\u0005B\u0005UtACA=C\u0005\u0005\t\u0012A\u0011\u0002|\u0019I\u0001%IA\u0001\u0012\u0003\t\u0013Q\u0010\u0005\u0007?j!\t!!#\t\u0013\u0005=$$!A\u0005F\u0005E\u0004\"CAF5\u0005\u0005I\u0011QAG\u0011%\t9JGA\u0001\n\u0003\u000bI\nC\u0005\u0002,j\t\t\u0011\"\u0003\u0002.\n\u0011b)\u001e;ve\u0016\f5/\u001f8d\u001fV$8m\\7f\u0015\t\u00113%A\u0005tG\u0006d\u0017\r^3ti*\tA%A\u0002pe\u001e\u001cR\u0001\u0001\u0014-aM\u0002\"a\n\u0016\u000e\u0003!R\u0011!K\u0001\u0006g\u000e\fG.Y\u0005\u0003W!\u0012a!\u00118z%\u00164\u0007CA\u0017/\u001b\u0005\t\u0013BA\u0018\"\u00051\t5/\u001f8d\u001fV$8m\\7f!\t9\u0013\'\u0003\u00023Q\t9\u0001K]8ek\u000e$\bC\u0001\u001b>\u001d\t)4H\u0004\u00027u5\tqG\u0003\u00029s\u00051AH]8piz\u001a\u0001!C\u0001*\u0013\ta\u0004&A\u0004qC\u000e\\\u0017mZ3\n\u0005yz$\u0001D*fe&\fG.\u001b>bE2,\'B\u0001\u001f)\u0003\u00191W\u000f^;sKV\t!\tE\u0002D\r\"k\u0011\u0001\u0012\u0006\u0003\u000b\"\n!bY8oGV\u0014(/\u001a8u\u0013\t9EI\u0001\u0004GkR,(/\u001a\t\u0003[%K!AS\u0011\u0003\u000f=+HoY8nK\u00069a-\u001e;ve\u0016\u0004\u0013!D8o\u0007>l\u0007\u000f\\3uK\u001a+h.F\u0001O!\u00119s*U,\n\u0005AC#!\u0003$v]\u000e$\u0018n\u001c82!\r\u0011V\u000bS\u0007\u0002\'*\u0011A\u000bK\u0001\u0005kRLG.\u0003\u0002W\'\n\u0019AK]=\u0011\u0005\u001dB\u0016BA-)\u0005\u0011)f.\u001b;\u0002\u001d=t7i\\7qY\u0016$XMR;oA\u0005\u00191\r\u001e=\u0011\u0005\rk\u0016B\u00010E\u0005A)\u00050Z2vi&|gnQ8oi\u0016DH/\u0001\u0004=S:LGO\u0010\u000b\u0004C\u0012,GC\u00012d!\ti\u0003\u0001C\u0003\\\r\u0001\u000fA\fC\u0003A\r\u0001\u0007!\tC\u0003M\r\u0001\u0007a*\u0001\u0004ti\u0006$Xo]\u000b\u0002QB\u0011Q&[\u0005\u0003U\u0006\u0012qcU2bY\u0006$Vm\u001d;Ti\u0006$XMZ;m\'R\fG/^:\u0002\u000fM$\u0018\r^;tA\u0005AAo\\*uCR,8/F\u0001o!\tis.\u0003\u0002qC\t11\u000b^1ukN\f\u0011\u0002^8PkR\u001cw.\\3\u0016\u0003!\u000b\u0011\u0003^8GkR,(/Z(g\u001fV$8m\\7f\u0003=!xNR;ukJ,w*\u001e;d_6,W#\u0001<\u0011\u00055:\u0018B\u0001=\"\u000551U\u000f^;sK>+HoY8nK\u0006!1m\u001c9z)\rYXP \u000b\u0003ErDQaW\u0007A\u0004qCq\u0001Q\u0007\u0011\u0002\u0003\u0007!\tC\u0004M\u001bA\u0005\t\u0019\u0001(\u0002\u001d\r|\u0007/\u001f\u0013eK\u001a\fW\u000f\u001c;%cU\u0011\u00111\u0001\u0016\u0004\u0005\u0006\u00151FAA\u0004!\u0011\tI!a\u0005\u000e\u0005\u0005-!\u0002BA\u0007\u0003\u001f\t\u0011\"\u001e8dQ\u0016\u001c7.\u001a3\u000b\u0007\u0005E\u0001&\u0001\u0006b]:|G/\u0019;j_:LA!!\u0006\u0002\f\t\tRO\\2iK\u000e\\W\r\u001a,be&\fgnY3\u0002\u001d\r|\u0007/\u001f\u0013eK\u001a\fW\u000f\u001c;%eU\u0011\u00111\u0004\u0016\u0004\u001d\u0006\u0015\u0011!\u00049s_\u0012,8\r\u001e)sK\u001aL\u00070\u0006\u0002\u0002\"A!\u00111EA\u0017\u001b\t\t)C\u0003\u0003\u0002(\u0005%\u0012\u0001\u00027b]\u001eT!!a\u000b\u0002\t)\fg/Y\u0005\u0005\u0003_\t)C\u0001\u0004TiJLgnZ\u0001\raJ|G-^2u\u0003JLG/_\u000b\u0003\u0003k\u00012aJA\u001c\u0013\r\tI\u0004\u000b\u0002\u0004\u0013:$\u0018A\u00049s_\u0012,8\r^#mK6,g\u000e\u001e\u000b\u0005\u0003\u007f\t)\u0005E\u0002(\u0003\u0003J1!a\u0011)\u0005\r\te.\u001f\u0005\n\u0003\u000f\u0012\u0012\u0011!a\u0001\u0003k\t1\u0001\u001f\u00132\u0003=\u0001(o\u001c3vGRLE/\u001a:bi>\u0014XCAA\'!\u0019\ty%!\u0016\u0002@5\u0011\u0011\u0011\u000b\u0006\u0004\u0003\'B\u0013AC2pY2,7\r^5p]&!\u0011qKA)\u0005!IE/\u001a:bi>\u0014\u0018\u0001C2b]\u0016\u000bX/\u00197\u0015\t\u0005u\u00131\r\t\u0004O\u0005}\u0013bAA1Q\t9!i\\8mK\u0006t\u0007\"CA$)\u0005\u0005\t\u0019AA \u0003I\u0001(o\u001c3vGR,E.Z7f]Rt\u0015-\\3\u0015\t\u0005\u0005\u0012\u0011\u000e\u0005\n\u0003\u000f*\u0012\u0011!a\u0001\u0003k\t\u0001\u0002[1tQ\u000e{G-\u001a\u000b\u0003\u0003k\t\u0001\u0002^8TiJLgn\u001a\u000b\u0003\u0003C\ta!Z9vC2\u001cH\u0003BA/\u0003oB\u0011\"a\u0012\u0019\u0003\u0003\u0005\r!a\u0010\u0002%\u0019+H/\u001e:f\u0003NLhnY(vi\u000e|W.\u001a\t\u0003[i\u0019BA\u0007\u0014\u0002\u0000A!\u0011\u0011QAD\u001b\t\t\u0019I\u0003\u0003\u0002\u0006\u0006%\u0012AA5p\u0013\rq\u00141\u0011\u000b\u0003\u0003w\nQ!\u00199qYf$b!a$\u0002\u0014\u0006UEc\u00012\u0002\u0012\")1,\ba\u00029\")\u0001)\ba\u0001\u0005\")A*\ba\u0001\u001d\u00069QO\\1qa2LH\u0003BAN\u0003O\u0003RaJAO\u0003CK1!a()\u0005\u0019y\u0005\u000f^5p]B)q%a)C\u001d&\u0019\u0011Q\u0015\u0015\u0003\rQ+\b\u000f\\33\u0011!\tIKHA\u0001\u0002\u0004\u0011\u0017a\u0001=%a\u0005aqO]5uKJ+\u0007\u000f\\1dKR\u0011\u0011q\u0016\t\u0005\u0003G\t\t,\u0003\u0003\u00024\u0006\u0015\"AB(cU\u0016\u001cG\u000f"
    )
BootstrapMethods:
  0: #232 REF_invokeStatic java/lang/invoke/LambdaMetafactory.altMetafactory:(Ljava/lang/invoke/MethodHandles$Lookup;Ljava/lang/String;Ljava/lang/invoke/MethodType;[Ljava/lang/Object;)Ljava/lang/invoke/CallSite;
    Method arguments:
      #216 (Ljava/lang/Object;)Ljava/lang/Object;
      #221 REF_invokeStatic org/scalatest/FutureAsyncOutcome.$anonfun$new$1$adapted:(Lorg/scalatest/FutureAsyncOutcome;Lscala/util/Try;)Ljava/lang/Object;
      #223 (Lscala/util/Try;)Ljava/lang/Object;
      #224 5
      #225 1
      #223 (Lscala/util/Try;)Ljava/lang/Object;
  1: #250 REF_invokeStatic scala/runtime/LambdaDeserialize.bootstrap:(Ljava/lang/invoke/MethodHandles$Lookup;Ljava/lang/String;Ljava/lang/invoke/MethodType;[Ljava/lang/invoke/MethodHandle;)Ljava/lang/invoke/CallSite;
    Method arguments:
      #221 REF_invokeStatic org/scalatest/FutureAsyncOutcome.$anonfun$new$1$adapted:(Lorg/scalatest/FutureAsyncOutcome;Lscala/util/Try;)Ljava/lang/Object;
  ScalaInlineInfo: length = 0x77 (unknown attribute)
   01 00 00 17 00 AE 00 AF 01 00 D9 00 DA 01 00 70
   00 71 00 00 91 00 92 00 00 6F 00 2F 00 00 74 00
   3D 00 00 75 00 41 00 00 A5 00 92 00 00 19 00 3D
   00 00 9B 00 7D 00 00 1C 00 41 00 00 7C 00 7D 00
   00 7E 00 7F 00 00 94 00 95 00 00 35 00 36 00 00
   87 00 36 00 00 78 00 79 00 00 1F 00 45 01 00 64
   00 3D 00 00 65 00 66 00 00 4C 00 4D 00 00 48 00
   49 00 00 A0 00 79 00
  ScalaSig: length = 0x3 (unknown attribute)
   05 02 00
