Classfile /Users/mw/Projects/slang-braindump/.jar/jar8/assemble/slang-braindump/assemble/content/org/scalatest/GivenWhenThen.class
  Last modified May 29, 2022; size 2953 bytes
  SHA-256 checksum f91f6238528cd0f274246d796cc6c531b461fcd8ad9a20788a5759c5bb1a2b92
  Compiled from "GivenWhenThen.scala"
public interface org.scalatest.GivenWhenThen
  minor version: 0
  major version: 52
  flags: (0x0601) ACC_PUBLIC, ACC_INTERFACE, ACC_ABSTRACT
  this_class: #2                          // org/scalatest/GivenWhenThen
  super_class: #4                         // java/lang/Object
  interfaces: 0, fields: 0, methods: 9, attributes: 4
Constant pool:
   #1 = Utf8               org/scalatest/GivenWhenThen
   #2 = Class              #1             // org/scalatest/GivenWhenThen
   #3 = Utf8               java/lang/Object
   #4 = Class              #3             // java/lang/Object
   #5 = Utf8               GivenWhenThen.scala
   #6 = Utf8               Lscala/reflect/ScalaSignature;
   #7 = Utf8               bytes
   #8 = Utf8               \u0006\u0005%3\u0001BB\u0004\u0011\u0002\u0007\u0005A\"\u0011\u0005\u0006\'\u0001!\t\u0001\u0006\u0005\u00061\u0001!\t!\u0007\u0005\u0006e\u0001!\ta\r\u0005\u0006o\u0001!\t\u0001\u000f\u0005\u0006y\u0001!\t!\u0010\u0002\u000e\u000f&4XM\\,iK:$\u0006.\u001a8\u000b\u0005!I\u0011!C:dC2\fG/Z:u\u0015\u0005Q\u0011aA8sO\u000e\u00011C\u0001\u0001\u000e!\tq\u0011#D\u0001\u0010\u0015\u0005\u0001\u0012!B:dC2\f\u0017B\u0001\n\u0010\u0005\u0019\te.\u001f*fM\u00061A%\u001b8ji\u0012\"\u0012!\u0006\t\u0003\u001dYI!aF\b\u0003\tUs\u0017\u000e^\u0001\u0006\u000f&4XM\u001c\u000b\u00035\u0015\"\"!F\u000e\t\u000bq\u0011\u00019A\u000f\u0002\u0007A|7\u000f\u0005\u0002\u001fG5\tqD\u0003\u0002!C\u000511o\\;sG\u0016T!AI\u0005\u0002\u0013M\u001c\u0017\r\\1di&\u001c\u0017B\u0001\u0013 \u0005!\u0001vn]5uS>t\u0007\"\u0002\u0014\u0003\u0001\u00049\u0013aB7fgN\fw-\u001a\t\u0003Q=r!!K\u0017\u0011\u0005)zQ\"A\u0016\u000b\u00051Z\u0011A\u0002\u001fs_>$h(\u0003\u0002/\u001f\u00051\u0001K]3eK\u001aL!\u0001M\u0019\u0003\rM#(/\u001b8h\u0015\tqs\"\u0001\u0003XQ\u0016tGC\u0001\u001b7)\t)R\u0007C\u0003\u001d\u0007\u0001\u000fQ\u0004C\u0003\'\u0007\u0001\u0007q%\u0001\u0003UQ\u0016tGCA\u001d<)\t)\"\bC\u0003\u001d\t\u0001\u000fQ\u0004C\u0003\'\t\u0001\u0007q%A\u0002B]\u0012$\"A\u0010!\u0015\u0005Uy\u0004\"\u0002\u000f\u0006\u0001\bi\u0002\"\u0002\u0014\u0006\u0001\u00049#c\u0001\"E\r\u001a!1\t\u0001\u0001B\u00051a$/\u001a4j]\u0016lWM\u001c;?!\t)\u0005!D\u0001\b!\t)u)\u0003\u0002I\u000f\tI\u0011J\u001c4pe6Lgn\u001a
   #9 = Utf8               Given$
  #10 = Utf8               (Lorg/scalatest/GivenWhenThen;Ljava/lang/String;Lorg/scalactic/source/Position;)V
  #11 = Utf8               $this
  #12 = Utf8               message
  #13 = Utf8               pos
  #14 = Utf8               Given
  #15 = Utf8               (Ljava/lang/String;Lorg/scalactic/source/Position;)V
  #16 = NameAndType        #14:#15        // Given:(Ljava/lang/String;Lorg/scalactic/source/Position;)V
  #17 = InterfaceMethodref #2.#16         // org/scalatest/GivenWhenThen.Given:(Ljava/lang/String;Lorg/scalactic/source/Position;)V
  #18 = Utf8               Lorg/scalatest/GivenWhenThen;
  #19 = Utf8               Ljava/lang/String;
  #20 = Utf8               Lorg/scalactic/source/Position;
  #21 = Utf8               org/scalatest/Informing
  #22 = Class              #21            // org/scalatest/Informing
  #23 = Utf8               info
  #24 = Utf8               ()Lorg/scalatest/Informer;
  #25 = NameAndType        #23:#24        // info:()Lorg/scalatest/Informer;
  #26 = InterfaceMethodref #22.#25        // org/scalatest/Informing.info:()Lorg/scalatest/Informer;
  #27 = Utf8               org/scalatest/Resources$
  #28 = Class              #27            // org/scalatest/Resources$
  #29 = Utf8               MODULE$
  #30 = Utf8               Lorg/scalatest/Resources$;
  #31 = NameAndType        #29:#30        // MODULE$:Lorg/scalatest/Resources$;
  #32 = Fieldref           #28.#31        // org/scalatest/Resources$.MODULE$:Lorg/scalatest/Resources$;
  #33 = Utf8               givenMessage
  #34 = Utf8               (Ljava/lang/Object;)Ljava/lang/String;
  #35 = NameAndType        #33:#34        // givenMessage:(Ljava/lang/Object;)Ljava/lang/String;
  #36 = Methodref          #28.#35        // org/scalatest/Resources$.givenMessage:(Ljava/lang/Object;)Ljava/lang/String;
  #37 = Utf8               org/scalatest/Informer
  #38 = Class              #37            // org/scalatest/Informer
  #39 = Utf8               apply$default$2
  #40 = Utf8               ()Lscala/Option;
  #41 = NameAndType        #39:#40        // apply$default$2:()Lscala/Option;
  #42 = InterfaceMethodref #38.#41        // org/scalatest/Informer.apply$default$2:()Lscala/Option;
  #43 = Utf8               apply
  #44 = Utf8               (Ljava/lang/String;Lscala/Option;Lorg/scalactic/source/Position;)V
  #45 = NameAndType        #43:#44        // apply:(Ljava/lang/String;Lscala/Option;Lorg/scalactic/source/Position;)V
  #46 = InterfaceMethodref #38.#45        // org/scalatest/Informer.apply:(Ljava/lang/String;Lscala/Option;Lorg/scalactic/source/Position;)V
  #47 = Utf8               qual$1
  #48 = Utf8               Lorg/scalatest/Informer;
  #49 = Utf8               x$1
  #50 = Utf8               x$2
  #51 = Utf8               Lscala/Option;
  #52 = Utf8               x$3
  #53 = Utf8               this
  #54 = Utf8               When$
  #55 = Utf8               When
  #56 = NameAndType        #55:#15        // When:(Ljava/lang/String;Lorg/scalactic/source/Position;)V
  #57 = InterfaceMethodref #2.#56         // org/scalatest/GivenWhenThen.When:(Ljava/lang/String;Lorg/scalactic/source/Position;)V
  #58 = Utf8               whenMessage
  #59 = NameAndType        #58:#34        // whenMessage:(Ljava/lang/Object;)Ljava/lang/String;
  #60 = Methodref          #28.#59        // org/scalatest/Resources$.whenMessage:(Ljava/lang/Object;)Ljava/lang/String;
  #61 = Utf8               Then$
  #62 = Utf8               Then
  #63 = NameAndType        #62:#15        // Then:(Ljava/lang/String;Lorg/scalactic/source/Position;)V
  #64 = InterfaceMethodref #2.#63         // org/scalatest/GivenWhenThen.Then:(Ljava/lang/String;Lorg/scalactic/source/Position;)V
  #65 = Utf8               thenMessage
  #66 = NameAndType        #65:#34        // thenMessage:(Ljava/lang/Object;)Ljava/lang/String;
  #67 = Methodref          #28.#66        // org/scalatest/Resources$.thenMessage:(Ljava/lang/Object;)Ljava/lang/String;
  #68 = Utf8               And$
  #69 = Utf8               And
  #70 = NameAndType        #69:#15        // And:(Ljava/lang/String;Lorg/scalactic/source/Position;)V
  #71 = InterfaceMethodref #2.#70         // org/scalatest/GivenWhenThen.And:(Ljava/lang/String;Lorg/scalactic/source/Position;)V
  #72 = Utf8               andMessage
  #73 = NameAndType        #72:#34        // andMessage:(Ljava/lang/Object;)Ljava/lang/String;
  #74 = Methodref          #28.#73        // org/scalatest/Resources$.andMessage:(Ljava/lang/Object;)Ljava/lang/String;
  #75 = Utf8               $init$
  #76 = Utf8               (Lorg/scalatest/GivenWhenThen;)V
  #77 = Utf8               Code
  #78 = Utf8               LineNumberTable
  #79 = Utf8               LocalVariableTable
  #80 = Utf8               MethodParameters
  #81 = Utf8               SourceFile
  #82 = Utf8               RuntimeVisibleAnnotations
  #83 = Utf8               ScalaInlineInfo
  #84 = Utf8               ScalaSig
{
  public static void Given$(org.scalatest.GivenWhenThen, java.lang.String, org.scalactic.source.Position);
    descriptor: (Lorg/scalatest/GivenWhenThen;Ljava/lang/String;Lorg/scalactic/source/Position;)V
    flags: (0x1009) ACC_PUBLIC, ACC_STATIC, ACC_SYNTHETIC
    Code:
      stack=3, locals=3, args_size=3
         0: aload_0
         1: aload_1
         2: aload_2
         3: invokespecial #17                 // InterfaceMethod Given:(Ljava/lang/String;Lorg/scalactic/source/Position;)V
         6: return
      LineNumberTable:
        line 78: 0
      LocalVariableTable:
        Start  Length  Slot  Name   Signature
            0       7     0 $this   Lorg/scalatest/GivenWhenThen;
            0       7     1 message   Ljava/lang/String;
            0       7     2   pos   Lorg/scalactic/source/Position;
    MethodParameters:
      Name                           Flags
      $this                          final synthetic
      message                        final
      pos                            final

  public default void Given(java.lang.String, org.scalactic.source.Position);
    descriptor: (Ljava/lang/String;Lorg/scalactic/source/Position;)V
    flags: (0x0001) ACC_PUBLIC
    Code:
      stack=4, locals=7, args_size=3
         0: aload_0
         1: checkcast     #22                 // class org/scalatest/Informing
         4: invokeinterface #26,  1           // InterfaceMethod org/scalatest/Informing.info:()Lorg/scalatest/Informer;
         9: astore_3
        10: getstatic     #32                 // Field org/scalatest/Resources$.MODULE$:Lorg/scalatest/Resources$;
        13: aload_1
        14: invokevirtual #36                 // Method org/scalatest/Resources$.givenMessage:(Ljava/lang/Object;)Ljava/lang/String;
        17: astore        4
        19: aload_3
        20: invokeinterface #42,  1           // InterfaceMethod org/scalatest/Informer.apply$default$2:()Lscala/Option;
        25: astore        5
        27: aload_2
        28: astore        6
        30: aload_3
        31: aload         4
        33: aload         5
        35: aload         6
        37: invokeinterface #46,  4           // InterfaceMethod org/scalatest/Informer.apply:(Ljava/lang/String;Lscala/Option;Lorg/scalactic/source/Position;)V
        42: return
      LineNumberTable:
        line 79: 0
      LocalVariableTable:
        Start  Length  Slot  Name   Signature
           10      32     3 qual$1   Lorg/scalatest/Informer;
           19      23     4   x$1   Ljava/lang/String;
           27      15     5   x$2   Lscala/Option;
           30      12     6   x$3   Lorg/scalactic/source/Position;
            0      43     0  this   Lorg/scalatest/GivenWhenThen;
            0      43     1 message   Ljava/lang/String;
            0      43     2   pos   Lorg/scalactic/source/Position;
    MethodParameters:
      Name                           Flags
      message                        final
      pos                            final

  public static void When$(org.scalatest.GivenWhenThen, java.lang.String, org.scalactic.source.Position);
    descriptor: (Lorg/scalatest/GivenWhenThen;Ljava/lang/String;Lorg/scalactic/source/Position;)V
    flags: (0x1009) ACC_PUBLIC, ACC_STATIC, ACC_SYNTHETIC
    Code:
      stack=3, locals=3, args_size=3
         0: aload_0
         1: aload_1
         2: aload_2
         3: invokespecial #57                 // InterfaceMethod When:(Ljava/lang/String;Lorg/scalactic/source/Position;)V
         6: return
      LineNumberTable:
        line 87: 0
      LocalVariableTable:
        Start  Length  Slot  Name   Signature
            0       7     0 $this   Lorg/scalatest/GivenWhenThen;
            0       7     1 message   Ljava/lang/String;
            0       7     2   pos   Lorg/scalactic/source/Position;
    MethodParameters:
      Name                           Flags
      $this                          final synthetic
      message                        final
      pos                            final

  public default void When(java.lang.String, org.scalactic.source.Position);
    descriptor: (Ljava/lang/String;Lorg/scalactic/source/Position;)V
    flags: (0x0001) ACC_PUBLIC
    Code:
      stack=4, locals=7, args_size=3
         0: aload_0
         1: checkcast     #22                 // class org/scalatest/Informing
         4: invokeinterface #26,  1           // InterfaceMethod org/scalatest/Informing.info:()Lorg/scalatest/Informer;
         9: astore_3
        10: getstatic     #32                 // Field org/scalatest/Resources$.MODULE$:Lorg/scalatest/Resources$;
        13: aload_1
        14: invokevirtual #60                 // Method org/scalatest/Resources$.whenMessage:(Ljava/lang/Object;)Ljava/lang/String;
        17: astore        4
        19: aload_3
        20: invokeinterface #42,  1           // InterfaceMethod org/scalatest/Informer.apply$default$2:()Lscala/Option;
        25: astore        5
        27: aload_2
        28: astore        6
        30: aload_3
        31: aload         4
        33: aload         5
        35: aload         6
        37: invokeinterface #46,  4           // InterfaceMethod org/scalatest/Informer.apply:(Ljava/lang/String;Lscala/Option;Lorg/scalactic/source/Position;)V
        42: return
      LineNumberTable:
        line 88: 0
      LocalVariableTable:
        Start  Length  Slot  Name   Signature
           10      32     3 qual$1   Lorg/scalatest/Informer;
           19      23     4   x$1   Ljava/lang/String;
           27      15     5   x$2   Lscala/Option;
           30      12     6   x$3   Lorg/scalactic/source/Position;
            0      43     0  this   Lorg/scalatest/GivenWhenThen;
            0      43     1 message   Ljava/lang/String;
            0      43     2   pos   Lorg/scalactic/source/Position;
    MethodParameters:
      Name                           Flags
      message                        final
      pos                            final

  public static void Then$(org.scalatest.GivenWhenThen, java.lang.String, org.scalactic.source.Position);
    descriptor: (Lorg/scalatest/GivenWhenThen;Ljava/lang/String;Lorg/scalactic/source/Position;)V
    flags: (0x1009) ACC_PUBLIC, ACC_STATIC, ACC_SYNTHETIC
    Code:
      stack=3, locals=3, args_size=3
         0: aload_0
         1: aload_1
         2: aload_2
         3: invokespecial #64                 // InterfaceMethod Then:(Ljava/lang/String;Lorg/scalactic/source/Position;)V
         6: return
      LineNumberTable:
        line 96: 0
      LocalVariableTable:
        Start  Length  Slot  Name   Signature
            0       7     0 $this   Lorg/scalatest/GivenWhenThen;
            0       7     1 message   Ljava/lang/String;
            0       7     2   pos   Lorg/scalactic/source/Position;
    MethodParameters:
      Name                           Flags
      $this                          final synthetic
      message                        final
      pos                            final

  public default void Then(java.lang.String, org.scalactic.source.Position);
    descriptor: (Ljava/lang/String;Lorg/scalactic/source/Position;)V
    flags: (0x0001) ACC_PUBLIC
    Code:
      stack=4, locals=7, args_size=3
         0: aload_0
         1: checkcast     #22                 // class org/scalatest/Informing
         4: invokeinterface #26,  1           // InterfaceMethod org/scalatest/Informing.info:()Lorg/scalatest/Informer;
         9: astore_3
        10: getstatic     #32                 // Field org/scalatest/Resources$.MODULE$:Lorg/scalatest/Resources$;
        13: aload_1
        14: invokevirtual #67                 // Method org/scalatest/Resources$.thenMessage:(Ljava/lang/Object;)Ljava/lang/String;
        17: astore        4
        19: aload_3
        20: invokeinterface #42,  1           // InterfaceMethod org/scalatest/Informer.apply$default$2:()Lscala/Option;
        25: astore        5
        27: aload_2
        28: astore        6
        30: aload_3
        31: aload         4
        33: aload         5
        35: aload         6
        37: invokeinterface #46,  4           // InterfaceMethod org/scalatest/Informer.apply:(Ljava/lang/String;Lscala/Option;Lorg/scalactic/source/Position;)V
        42: return
      LineNumberTable:
        line 97: 0
      LocalVariableTable:
        Start  Length  Slot  Name   Signature
           10      32     3 qual$1   Lorg/scalatest/Informer;
           19      23     4   x$1   Ljava/lang/String;
           27      15     5   x$2   Lscala/Option;
           30      12     6   x$3   Lorg/scalactic/source/Position;
            0      43     0  this   Lorg/scalatest/GivenWhenThen;
            0      43     1 message   Ljava/lang/String;
            0      43     2   pos   Lorg/scalactic/source/Position;
    MethodParameters:
      Name                           Flags
      message                        final
      pos                            final

  public static void And$(org.scalatest.GivenWhenThen, java.lang.String, org.scalactic.source.Position);
    descriptor: (Lorg/scalatest/GivenWhenThen;Ljava/lang/String;Lorg/scalactic/source/Position;)V
    flags: (0x1009) ACC_PUBLIC, ACC_STATIC, ACC_SYNTHETIC
    Code:
      stack=3, locals=3, args_size=3
         0: aload_0
         1: aload_1
         2: aload_2
         3: invokespecial #71                 // InterfaceMethod And:(Ljava/lang/String;Lorg/scalactic/source/Position;)V
         6: return
      LineNumberTable:
        line 105: 0
      LocalVariableTable:
        Start  Length  Slot  Name   Signature
            0       7     0 $this   Lorg/scalatest/GivenWhenThen;
            0       7     1 message   Ljava/lang/String;
            0       7     2   pos   Lorg/scalactic/source/Position;
    MethodParameters:
      Name                           Flags
      $this                          final synthetic
      message                        final
      pos                            final

  public default void And(java.lang.String, org.scalactic.source.Position);
    descriptor: (Ljava/lang/String;Lorg/scalactic/source/Position;)V
    flags: (0x0001) ACC_PUBLIC
    Code:
      stack=4, locals=7, args_size=3
         0: aload_0
         1: checkcast     #22                 // class org/scalatest/Informing
         4: invokeinterface #26,  1           // InterfaceMethod org/scalatest/Informing.info:()Lorg/scalatest/Informer;
         9: astore_3
        10: getstatic     #32                 // Field org/scalatest/Resources$.MODULE$:Lorg/scalatest/Resources$;
        13: aload_1
        14: invokevirtual #74                 // Method org/scalatest/Resources$.andMessage:(Ljava/lang/Object;)Ljava/lang/String;
        17: astore        4
        19: aload_3
        20: invokeinterface #42,  1           // InterfaceMethod org/scalatest/Informer.apply$default$2:()Lscala/Option;
        25: astore        5
        27: aload_2
        28: astore        6
        30: aload_3
        31: aload         4
        33: aload         5
        35: aload         6
        37: invokeinterface #46,  4           // InterfaceMethod org/scalatest/Informer.apply:(Ljava/lang/String;Lscala/Option;Lorg/scalactic/source/Position;)V
        42: return
      LineNumberTable:
        line 106: 0
      LocalVariableTable:
        Start  Length  Slot  Name   Signature
           10      32     3 qual$1   Lorg/scalatest/Informer;
           19      23     4   x$1   Ljava/lang/String;
           27      15     5   x$2   Lscala/Option;
           30      12     6   x$3   Lorg/scalactic/source/Position;
            0      43     0  this   Lorg/scalatest/GivenWhenThen;
            0      43     1 message   Ljava/lang/String;
            0      43     2   pos   Lorg/scalactic/source/Position;
    MethodParameters:
      Name                           Flags
      message                        final
      pos                            final

  public static void $init$(org.scalatest.GivenWhenThen);
    descriptor: (Lorg/scalatest/GivenWhenThen;)V
    flags: (0x0009) ACC_PUBLIC, ACC_STATIC
    Code:
      stack=0, locals=1, args_size=1
         0: return
      LineNumberTable:
        line 71: 0
      LocalVariableTable:
        Start  Length  Slot  Name   Signature
            0       1     0 $this   Lorg/scalatest/GivenWhenThen;
    MethodParameters:
      Name                           Flags
      $this                          final synthetic
}
SourceFile: "GivenWhenThen.scala"
RuntimeVisibleAnnotations:
  0: #6(#7=s#8)
    scala.reflect.ScalaSignature(
      bytes="\u0006\u0005%3\u0001BB\u0004\u0011\u0002\u0007\u0005A\"\u0011\u0005\u0006\'\u0001!\t\u0001\u0006\u0005\u00061\u0001!\t!\u0007\u0005\u0006e\u0001!\ta\r\u0005\u0006o\u0001!\t\u0001\u000f\u0005\u0006y\u0001!\t!\u0010\u0002\u000e\u000f&4XM\\,iK:$\u0006.\u001a8\u000b\u0005!I\u0011!C:dC2\fG/Z:u\u0015\u0005Q\u0011aA8sO\u000e\u00011C\u0001\u0001\u000e!\tq\u0011#D\u0001\u0010\u0015\u0005\u0001\u0012!B:dC2\f\u0017B\u0001\n\u0010\u0005\u0019\te.\u001f*fM\u00061A%\u001b8ji\u0012\"\u0012!\u0006\t\u0003\u001dYI!aF\b\u0003\tUs\u0017\u000e^\u0001\u0006\u000f&4XM\u001c\u000b\u00035\u0015\"\"!F\u000e\t\u000bq\u0011\u00019A\u000f\u0002\u0007A|7\u000f\u0005\u0002\u001fG5\tqD\u0003\u0002!C\u000511o\\;sG\u0016T!AI\u0005\u0002\u0013M\u001c\u0017\r\\1di&\u001c\u0017B\u0001\u0013 \u0005!\u0001vn]5uS>t\u0007\"\u0002\u0014\u0003\u0001\u00049\u0013aB7fgN\fw-\u001a\t\u0003Q=r!!K\u0017\u0011\u0005)zQ\"A\u0016\u000b\u00051Z\u0011A\u0002\u001fs_>$h(\u0003\u0002/\u001f\u00051\u0001K]3eK\u001aL!\u0001M\u0019\u0003\rM#(/\u001b8h\u0015\tqs\"\u0001\u0003XQ\u0016tGC\u0001\u001b7)\t)R\u0007C\u0003\u001d\u0007\u0001\u000fQ\u0004C\u0003\'\u0007\u0001\u0007q%\u0001\u0003UQ\u0016tGCA\u001d<)\t)\"\bC\u0003\u001d\t\u0001\u000fQ\u0004C\u0003\'\t\u0001\u0007q%A\u0002B]\u0012$\"A\u0010!\u0015\u0005Uy\u0004\"\u0002\u000f\u0006\u0001\bi\u0002\"\u0002\u0014\u0006\u0001\u00049#c\u0001\"E\r\u001a!1\t\u0001\u0001B\u00051a$/\u001a4j]\u0016lWM\u001c;?!\t)\u0005!D\u0001\b!\t)u)\u0003\u0002I\u000f\tI\u0011J\u001c4pe6Lgn\u001a"
    )
  ScalaInlineInfo: length = 0x31 (unknown attribute)
   01 00 00 09 00 4B 00 4C 01 00 45 00 0F 00 00 44
   00 0A 01 00 0E 00 0F 00 00 09 00 0A 01 00 3E 00
   0F 00 00 3D 00 0A 01 00 37 00 0F 00 00 36 00 0A
   01
  ScalaSig: length = 0x3 (unknown attribute)
   05 02 00
