Classfile /Users/mw/Projects/slang-braindump/.jar/jar8/assemble/slang-braindump/assemble/content/org/scalatest/Inspectors.class
  Last modified May 29, 2022; size 29550 bytes
  SHA-256 checksum 45af6e06961bd312e45f5ea71109ccd4965a7fd40da68d61dbc6755c9d0bb10f
  Compiled from "Inspectors.scala"
public interface org.scalatest.Inspectors
  minor version: 0
  major version: 52
  flags: (0x0601) ACC_PUBLIC, ACC_INTERFACE, ACC_ABSTRACT
  this_class: #2                          // org/scalatest/Inspectors
  super_class: #4                         // java/lang/Object
  interfaces: 0, fields: 0, methods: 58, attributes: 4
Constant pool:
    #1 = Utf8               org/scalatest/Inspectors
    #2 = Class              #1            // org/scalatest/Inspectors
    #3 = Utf8               java/lang/Object
    #4 = Class              #3            // java/lang/Object
    #5 = Utf8               Inspectors.scala
    #6 = Utf8               Lscala/reflect/ScalaSignature;
    #7 = Utf8               bytes
    #8 = Utf8               \u0006\u0005\u001deaa\u0002\u0012$!\u0003\r\t\u0001\u000b\u0005\u0006_\u0001!\t\u0001\r\u0005\u0006i\u0001!\t!\u000e\u0005\u0006i\u0001!\t!\u001e\u0005\u0007i\u0001!\t!a\u0017\t\rQ\u0002A\u0011AAX\u0011\u001d\t9\u000f\u0001C\u0001\u0003SDq!a:\u0001\t\u0003\u0011\t\u0003C\u0004\u0002h\u0002!\tAa\u0019\t\u000f\u0005\u001d\b\u0001\"\u0001\u0003$\"9!Q\u0019\u0001\u0005\n\t\u001d\u0007b\u0002Bp\u0001\u0011\u0005!\u0011\u001d\u0005\b\u0005?\u0004A\u0011AB\n\u0011\u001d\u0011y\u000e\u0001C\u0001\u0007+BqAa8\u0001\t\u0003\u0019)\nC\u0004\u00048\u0002!\ta!/\t\u000f\r]\u0006\u0001\"\u0001\u0004l\"91q\u0017\u0001\u0005\u0002\u00115\u0002bBB\\\u0001\u0011\u0005AQ\u000e\u0005\t\t\u001f\u0003A\u0011A\u0012\u0005\u0012\"AAq\u0012\u0001\u0005\u0002\r\"y\f\u0003\u0005\u0005\u0010\u0002!\ta\tC\u0000\u0011!!y\t\u0001C\u0001G\u0015u\u0002bBC/\u0001\u0011\u0005Qq\f\u0005\b\u000b;\u0002A\u0011ACK\u0011\u001d)i\u0006\u0001C\u0001\u000b3Dq!\"\u0018\u0001\t\u00031Y\u0002C\u0004\u0007@\u0001!\tA\"\u0011\t\u000f\u0019}\u0002\u0001\"\u0001\u0007p!9aq\b\u0001\u0005\u0002\u0019=\u0006b\u0002D \u0001\u0011\u0005aQ^\u0004\b\u000f\u001b\u0019\u0003\u0012AD\b\r\u0019\u00113\u0005#\u0001\b\u0012!9qQ\u0003\u0011\u0005\u0002\u001d]!AC%ogB,7\r^8sg*\u0011A%J\u0001\ng\u000e\fG.\u0019;fgRT\u0011AJ\u0001\u0004_J<7\u0001A\n\u0003\u0001%\u0002\"AK\u0017\u000e\u0003-R\u0011\u0001L\u0001\u0006g\u000e\fG.Y\u0005\u0003]-\u0012a!\u00118z%\u00164\u0017A\u0002\u0013j]&$H\u0005F\u00012!\tQ#\'\u0003\u00024W\t!QK\\5u\u0003\u00191wN]!mYV!aGV-F)\t94\u000f\u0006\u00029]R)\u0011\b\u0015\u001f_MB\u0011!H\u0014\b\u0003wqb\u0001\u0001C\u0003>\u0005\u0001\u000fa(A\u0005bgN,\'\u000f^5oOB\u0019qH\u0011#\u000e\u0003\u0001S!!Q\u0012\u0002\u0011\u0015t\u0017M\u00197feNL!a\u0011!\u0003%%s7\u000f]3di>\u0014\u0018i]:feRLgn\u001a\t\u0003w\u0015#QA\u0012\u0002C\u0002\u001d\u0013\u0011\"Q*T\u000bJ#\u0016j\u0014(\u0012\u0005![\u0005C\u0001\u0016J\u0013\tQ5FA\u0004O_RD\u0017N\\4\u0011\u0005)b\u0015BA\',\u0005\r\te._\u0005\u0003\u001f\n\u0013aAU3tk2$\b\"B)\u0003\u0001\b\u0011\u0016AC2pY2,7\r^5oOB!qhU+Y\u0013\t!\u0006I\u0001\u0006D_2dWm\u0019;j]\u001e\u0004\"a\u000f,\u0005\u000b]\u0013!\u0019A$\u0003\u0003\u0015\u00032aO-V\t\u0015Q&A1\u0001\\\u0005\u0005\u0019UCA$]\t\u0015i\u0016L1\u0001H\u0005\u0005y\u0006\"B0\u0003\u0001\b\u0001\u0017A\u00039sKR$\u0018NZ5feB\u0011\u0011\rZ\u0007\u0002E*\u00111-J\u0001\ng\u000e\fG.Y2uS\u000eL!!\u001a2\u0003\u0015A\u0013X\r\u001e;jM&,\'\u000fC\u0003h\u0005\u0001\u000f\u0001.A\u0002q_N\u0004\"!\u001b7\u000e\u0003)T!a\u001b2\u0002\rM|WO]2f\u0013\ti\'N\u0001\u0005Q_NLG/[8o\u0011\u0015y\'\u00011\u0001q\u0003\r1WO\u001c\t\u0005UE,F)\u0003\u0002sW\tIa)\u001e8di&|g.\r\u0005\u0006i\n\u0001\r\u0001W\u0001\u0003qN,\u0002B^A\u0006\u0003#\t\tE \u000b\u0004o\u0006uBc\u0001=\u0002:Q9\u0011p`>\u00026\u0005]\u0002C\u0001>O\u001d\tY4\u0010C\u0003>\u0007\u0001\u000fA\u0010E\u0002@\u0005v\u0004\"a\u000f@\u0005\u000b\u0019\u001b!\u0019A$\t\rE\u001b\u00019AA\u0001!\u0019y4+a\u0001\u0002\u0016A9!&!\u0002\u0002\n\u0005=\u0011bAA\u0004W\t1A+\u001e9mKJ\u00022aOA\u0006\t\u0019\tia\u0001b\u0001\u000f\n\t1\nE\u0002<\u0003#!a!a\u0005\u0004\u0005\u00049%!\u0001,\u0011\r\u0005]\u0011qFA\u0002\u001d\u0011\tI\"!\u000b\u000f\t\u0005m\u0011Q\u0005\b\u0005\u0003;\t\u0019#\u0004\u0002\u0002 )\u0019\u0011\u0011E\u0014\u0002\rq\u0012xn\u001c;?\u0013\u0005a\u0013bAA\u0014W\u0005Q1m\u001c7mK\u000e$\u0018n\u001c8\n\t\u0005-\u0012QF\u0001\ba\u0006\u001c7.Y4f\u0015\r\t9cK\u0005\u0005\u0003c\t\u0019D\u0001\bHK:$&/\u0019<feN\f\'\r\\3\u000b\t\u0005-\u0012Q\u0006\u0005\u0006?\u000e\u0001\u001d\u0001\u0019\u0005\u0006O\u000e\u0001\u001d\u0001\u001b\u0005\u0007_\u000e\u0001\r!a\u000f\u0011\u000b)\n\u00181A?\t\rQ\u001c\u0001\u0019AA !\u001dY\u0014\u0011IA\u0005\u0003\u001f!q!a\u0011\u0004\u0005\u0004\t)EA\u0002N\u0003B+b!a\u0012\u0002R\u0005]\u0013c\u0001%\u0002JAA\u0011qCA&\u0003\u001f\n)&\u0003\u0003\u0002N\u0005M\"AB$f]6\u000b\u0007\u000fE\u0002<\u0003#\"q!a\u0015\u0002B\t\u0007qIA\u0001l!\rY\u0014q\u000b\u0003\b\u00033\n\tE1\u0001H\u0005\u00051XCCA/\u0003{\n\t)!\"\u0002nQ!\u0011qLAW)\u0011\t\t\'!+\u0015\u0015\u0005\r\u0014qNA4\u0003K\u000b9\u000bE\u0002\u0002f9s1aOA4\u0011\u0019iD\u0001q\u0001\u0002jA!qHQA6!\rY\u0014Q\u000e\u0003\u0006\r\u0012\u0011\ra\u0012\u0005\u0007#\u0012\u0001\u001d!!\u001d\u0011\r}\u001a\u00161OAB!!\t)(a\u001e\u0002|\u0005}T\"A\u0012\n\u0007\u0005e4EA\u0003F]R\u0014\u0018\u0010E\u0002<\u0003{\"a!!\u0004\u0005\u0005\u00049\u0005cA\u001e\u0002\u0002\u00121\u00111\u0003\u0003C\u0002\u001d\u0003raOAC\u0003w\ny\bB\u0004\u0002\b\u0012\u0011\r!!#\u0003\t)k\u0015\tU\u000b\u0007\u0003\u0017\u000by*a)\u0012\u0007!\u000bi\t\u0005\u0005\u0002\u0010\u0006e\u0015QTAQ\u001b\t\t\tJ\u0003\u0003\u0002\u0014\u0006U\u0015\u0001B;uS2T!!a&\u0002\t)\fg/Y\u0005\u0005\u00037\u000b\tJA\u0002NCB\u00042aOAP\t\u001d\t\u0019&!\"C\u0002\u001d\u00032aOAR\t\u001d\tI&!\"C\u0002\u001dCQa\u0018\u0003A\u0004\u0001DQa\u001a\u0003A\u0004!Daa\u001c\u0003A\u0002\u0005-\u0006C\u0002\u0016r\u0003g\nY\u0007\u0003\u0004u\t\u0001\u0007\u00111Q\u000b\u0005\u0003c\u000b\t\r\u0006\u0003\u00024\u0006\u0015H\u0003BA[\u0003C$\"\"a.\u0002D\u0006m\u0016Q\\Ap!\r\tIL\u0014\b\u0004w\u0005m\u0006BB\u001f\u0006\u0001\b\ti\f\u0005\u0003@\u0005\u0006}\u0006cA\u001e\u0002B\u0012)a)\u0002b\u0001\u000f\"1\u0011+\u0002a\u0002\u0003\u000b\u0004baP*\u0002H\u00065\u0007c\u0001\u0016\u0002J&\u0019\u00111Z\u0016\u0003\t\rC\u0017M\u001d\t\u0005\u0003\u001f\f9N\u0004\u0003\u0002R\u0006M\u0007cAA\u000fW%\u0019\u0011Q[\u0016\u0002\rA\u0013X\rZ3g\u0013\u0011\tI.a7\u0003\rM#(/\u001b8h\u0015\r\t)n\u000b\u0005\u0006?\u0016\u0001\u001d\u0001\u0019\u0005\u0006O\u0016\u0001\u001d\u0001\u001b\u0005\u0007_\u0016\u0001\r!a9\u0011\r)\n\u0018qYA`\u0011\u0019!X\u00011\u0001\u0002N\u0006Qam\u001c:Bi2+\u0017m\u001d;\u0016\u0011\u0005-(1\u0001B\u0004\u0003w$b!!<\u0003\u0016\t}A\u0003BAx\u0005#!\"\"!=\u0002~\u0006U(Q\u0002B\b!\r\t\u0019P\u0014\b\u0004w\u0005U\bBB\u001f\u0007\u0001\b\t9\u0010\u0005\u0003@\u0005\u0006e\bcA\u001e\u0002|\u0012)aI\u0002b\u0001\u000f\"1\u0011K\u0002a\u0002\u0003\u007f\u0004baP*\u0003\u0002\t\u0015\u0001cA\u001e\u0003\u0004\u0011)qK\u0002b\u0001\u000fB)1Ha\u0002\u0003\u0002\u00111!L\u0002b\u0001\u0005\u0013)2a\u0012B\u0006\t\u0019i&q\u0001b\u0001\u000f\")qL\u0002a\u0002A\")qM\u0002a\u0002Q\"1qN\u0002a\u0001\u0005\'\u0001bAK9\u0003\u0002\u0005e\bb\u0002B\f\r\u0001\u0007!\u0011D\u0001\u0004[&t\u0007c\u0001\u0016\u0003\u001c%\u0019!QD\u0016\u0003\u0007%sG\u000f\u0003\u0004u\r\u0001\u0007!QA\u000b\u000b\u0005G\u0011iD!\u0011\u0003T\tMBC\u0002B\u0013\u0005\u001b\u0012y\u0005\u0006\u0003\u0003(\t%CC\u0003B\u0015\u0005k\u0011iC!\u0012\u0003HA\u0019!1\u0006(\u000f\u0007m\u0012i\u0003\u0003\u0004>\u000f\u0001\u000f!q\u0006\t\u0005\u007f\t\u0013\t\u0004E\u0002<\u0005g!QAR\u0004C\u0002\u001dCa!U\u0004A\u0004\t]\u0002CB T\u0005s\u0011\u0019\u0005E\u0004+\u0003\u000b\u0011YDa\u0010\u0011\u0007m\u0012i\u0004\u0002\u0004\u0002\u000e\u001d\u0011\ra\u0012\t\u0004w\t\u0005CABA\n\u000f\t\u0007q\t\u0005\u0004\u0002\u0018\u0005=\"\u0011\b\u0005\u0006?\u001e\u0001\u001d\u0001\u0019\u0005\u0006O\u001e\u0001\u001d\u0001\u001b\u0005\u0007_\u001e\u0001\rAa\u0013\u0011\r)\n(\u0011\bB\u0019\u0011\u001d\u00119b\u0002a\u0001\u00053Aa\u0001^\u0004A\u0002\tE\u0003cB\u001e\u0003T\tm\"q\b\u0003\b\u0003\u0007:!\u0019\u0001B++\u0019\u00119F!\u0018\u0003bE\u0019\u0001J!\u0017\u0011\u0011\u0005]\u00111\nB.\u0005?\u00022a\u000fB/\t\u001d\t\u0019Fa\u0015C\u0002\u001d\u00032a\u000fB1\t\u001d\tIFa\u0015C\u0002\u001d+\"B!\u001a\u0003\u0000\t\r%q\u0011B;)\u0019\u00119Ga(\u0003\"R!!\u0011\u000eBN))\u0011YGa\u001e\u0003p\t]%\u0011\u0014\t\u0004\u0005[rebA\u001e\u0003p!1Q\b\u0003a\u0002\u0005c\u0002Ba\u0010\"\u0003tA\u00191H!\u001e\u0005\u000b\u0019C!\u0019A$\t\rEC\u00019\u0001B=!\u0019y4Ka\u001f\u0003\u0006BA\u0011QOA<\u0005{\u0012\t\tE\u0002<\u0005\u007f\"a!!\u0004\t\u0005\u00049\u0005cA\u001e\u0003\u0004\u00121\u00111\u0003\u0005C\u0002\u001d\u0003ra\u000fBD\u0005{\u0012\t\tB\u0004\u0002\b\"\u0011\rA!#\u0016\r\t-%\u0011\u0013BK#\rA%Q\u0012\t\t\u0003\u001f\u000bIJa$\u0003\u0014B\u00191H!%\u0005\u000f\u0005M#q\u0011b\u0001\u000fB\u00191H!&\u0005\u000f\u0005e#q\u0011b\u0001\u000f\")q\f\u0003a\u0002A\")q\r\u0003a\u0002Q\"1q\u000e\u0003a\u0001\u0005;\u0003bAK9\u0003|\tM\u0004b\u0002B\f\u0011\u0001\u0007!\u0011\u0004\u0005\u0007i\"\u0001\rA!\"\u0016\t\t\u0015&Q\u0017\u000b\u0007\u0005O\u0013\tMa1\u0015\t\t%&Q\u0018\u000b\u000b\u0005W\u00139La,\u0003:\nm\u0006c\u0001BW\u001d:\u00191Ha,\t\ruJ\u00019\u0001BY!\u0011y$Ia-\u0011\u0007m\u0012)\fB\u0003G\u0013\t\u0007q\t\u0003\u0004R\u0013\u0001\u000f\u0011Q\u0019\u0005\u0006?&\u0001\u001d\u0001\u0019\u0005\u0006O&\u0001\u001d\u0001\u001b\u0005\u0007_&\u0001\rAa0\u0011\r)\n\u0018q\u0019BZ\u0011\u001d\u00119\"\u0003a\u0001\u00053Aa\u0001^\u0005A\u0002\u00055\u0017AE:i_VdG-\u00138dYV$W-\u00138eKb,bA!3\u0003X\nmG\u0003\u0002Bf\u0005#\u00042A\u000bBg\u0013\r\u0011ym\u000b\u0002\b\u0005>|G.Z1o\u0011\u0019!(\u00021\u0001\u0003TB1\u0011qCA\u0018\u0005+\u00042a\u000fBl\t\u0019\u0011IN\u0003b\u0001\u000f\n\tA\u000b\u0002\u0004\u0003^*\u0011\ra\u0012\u0002\u0002%\u0006Iam\u001c:Bi6{7\u000f^\u000b\t\u0005G\u0014YPa@\u0003tR1!Q]B\u0007\u0007#!BAa:\u0004\nQQ!\u0011\u001eB{\u0005[\u001c)aa\u0002\u0011\u0007\t-hJD\u0002<\u0005[Da!P\u0006A\u0004\t=\b\u0003B C\u0005c\u00042a\u000fBz\t\u001515B1\u0001H\u0011\u0019\t6\u0002q\u0001\u0003xB1qh\u0015B}\u0005{\u00042a\u000fB~\t\u001596B1\u0001H!\u0015Y$q B}\t\u0019Q6B1\u0001\u0004\u0002U\u0019qia\u0001\u0005\ru\u0013yP1\u0001H\u0011\u0015y6\u0002q\u0001a\u0011\u001597\u0002q\u0001i\u0011\u0019y7\u00021\u0001\u0004\fA1!&\u001dB}\u0005cDqaa\u0004\f\u0001\u0004\u0011I\"A\u0002nCbDa\u0001^\u0006A\u0002\tuXCCB\u000b\u0007_\u0019\u0019d!\u0012\u0004&Q11qCB \u0007\u0003\"Ba!\u0007\u0004<QQ11DB\u0014\u0007?\u00199d!\u000f\u0011\u0007\ruaJD\u0002<\u0007?Aa!\u0010\u0007A\u0004\r\u0005\u0002\u0003B C\u0007G\u00012aOB\u0013\t\u00151EB1\u0001H\u0011\u0019\tF\u0002q\u0001\u0004*A1qhUB\u0016\u0007k\u0001rAKA\u0003\u0007[\u0019\t\u0004E\u0002<\u0007_!a!!\u0004\r\u0005\u00049\u0005cA\u001e\u00044\u00111\u00111\u0003\u0007C\u0002\u001d\u0003b!a\u0006\u00020\r-\u0002\"B0\r\u0001\b\u0001\u0007\"B4\r\u0001\bA\u0007BB8\r\u0001\u0004\u0019i\u0004\u0005\u0004+c\u000e-21\u0005\u0005\b\u0007\u001fa\u0001\u0019\u0001B\r\u0011\u0019!H\u00021\u0001\u0004DA91h!\u0012\u0004.\rEBaBA\"\u0019\t\u00071qI\u000b\u0007\u0007\u0013\u001ayea\u0015\u0012\u0007!\u001bY\u0005\u0005\u0005\u0002\u0018\u0005-3QJB)!\rY4q\n\u0003\b\u0003\'\u001a)E1\u0001H!\rY41\u000b\u0003\b\u00033\u001a)E1\u0001H+)\u00199f!\u001d\u0004v\re4q\r\u000b\u0007\u00073\u001a\tja%\u0015\t\rm3Q\u0012\u000b\u000b\u0007;\u001aIg!\u0019\u0004\n\u000e-\u0005cAB0\u001d:\u00191h!\u0019\t\ruj\u00019AB2!\u0011y$i!\u001a\u0011\u0007m\u001a9\u0007B\u0003G\u001b\t\u0007q\t\u0003\u0004R\u001b\u0001\u000f11\u000e\t\u0007\u007fM\u001biga\u001e\u0011\u0011\u0005U\u0014qOB8\u0007g\u00022aOB9\t\u0019\ti!\u0004b\u0001\u000fB\u00191h!\u001e\u0005\r\u0005MQB1\u0001H!\u001dY4\u0011PB8\u0007g\"q!a\"\u000e\u0005\u0004\u0019Y(\u0006\u0004\u0004~\r\r5qQ\t\u0004\u0011\u000e}\u0004\u0003CAH\u00033\u001b\ti!\"\u0011\u0007m\u001a\u0019\tB\u0004\u0002T\re$\u0019A$\u0011\u0007m\u001a9\tB\u0004\u0002Z\re$\u0019A$\t\u000b}k\u00019\u00011\t\u000b\u001dl\u00019\u00015\t\r=l\u0001\u0019ABH!\u0019Q\u0013o!\u001c\u0004f!91qB\u0007A\u0002\te\u0001B\u0002;\u000e\u0001\u0004\u00199(\u0006\u0003\u0004\u0018\u000e\u001dFCBBM\u0007g\u001b)\f\u0006\u0003\u0004\u001c\u000e=FCCBO\u0007S\u001b\tka+\u0004.B\u00191q\u0014(\u000f\u0007m\u001a\t\u000b\u0003\u0004>\u001d\u0001\u000f11\u0015\t\u0005\u007f\t\u001b)\u000bE\u0002<\u0007O#QA\u0012\bC\u0002\u001dCa!\u0015\bA\u0004\u0005\u0015\u0007\"B0\u000f\u0001\b\u0001\u0007\"B4\u000f\u0001\bA\u0007BB8\u000f\u0001\u0004\u0019\t\f\u0005\u0004+c\u0006\u001d7Q\u0015\u0005\b\u0007\u001fq\u0001\u0019\u0001B\r\u0011\u0019!h\u00021\u0001\u0002N\u0006Qam\u001c:Fq\u0006\u001cG\u000f\\=\u0016\u0011\rm61[Bl\u0007\u0017$ba!0\u0004f\u000e%H\u0003BB`\u0007C$\"b!1\u0004N\u000e\u00157Q\\Bp!\r\u0019\u0019M\u0014\b\u0004w\r\u0015\u0007BB\u001f\u0010\u0001\b\u00199\r\u0005\u0003@\u0005\u000e%\u0007cA\u001e\u0004L\u0012)ai\u0004b\u0001\u000f\"1\u0011k\u0004a\u0002\u0007\u001f\u0004baP*\u0004R\u000eU\u0007cA\u001e\u0004T\u0012)qk\u0004b\u0001\u000fB)1ha6\u0004R\u00121!l\u0004b\u0001\u00073,2aRBn\t\u0019i6q\u001bb\u0001\u000f\")ql\u0004a\u0002A\")qm\u0004a\u0002Q\"1qn\u0004a\u0001\u0007G\u0004bAK9\u0004R\u000e%\u0007bBBt\u001f\u0001\u0007!\u0011D\u0001\u000fgV\u001c7-Z3eK\u0012\u001cu.\u001e8u\u0011\u0019!x\u00021\u0001\u0004VVQ1Q\u001eC\u0004\t\u0017!ib!@\u0015\r\r=Hq\u0003C\r)\u0011\u0019\t\u0010b\u0005\u0015\u0015\rM8q`B|\t\u001f!\t\u0002E\u0002\u0004v:s1aOB|\u0011\u0019i\u0004\u0003q\u0001\u0004zB!qHQB~!\rY4Q \u0003\u0006\rB\u0011\ra\u0012\u0005\u0007#B\u0001\u001d\u0001\"\u0001\u0011\r}\u001aF1\u0001C\u0007!\u001dQ\u0013Q\u0001C\u0003\t\u0013\u00012a\u000fC\u0004\t\u0019\ti\u0001\u0005b\u0001\u000fB\u00191\bb\u0003\u0005\r\u0005M\u0001C1\u0001H!\u0019\t9\"a\f\u0005\u0004!)q\f\u0005a\u0002A\")q\r\u0005a\u0002Q\"1q\u000e\u0005a\u0001\t+\u0001bAK9\u0005\u0004\rm\bbBBt!\u0001\u0007!\u0011\u0004\u0005\u0007iB\u0001\r\u0001b\u0007\u0011\u000fm\"i\u0002\"\u0002\u0005\n\u00119\u00111\t\tC\u0002\u0011}QC\u0002C\u0011\tO!Y#E\u0002I\tG\u0001\u0002\"a\u0006\u0002L\u0011\u0015B\u0011\u0006\t\u0004w\u0011\u001dBaBA*\t;\u0011\ra\u0012\t\u0004w\u0011-BaBA-\t;\u0011\raR\u000b\u000b\t_!I\u0005\"\u0014\u0005R\u0011}BC\u0002C\u0019\tS\"Y\u0007\u0006\u0003\u00054\u0011\u0015DC\u0003C\u001b\t\u0003\"I\u0004\"\u0019\u0005dA\u0019Aq\u0007(\u000f\u0007m\"I\u0004\u0003\u0004>#\u0001\u000fA1\b\t\u0005\u007f\t#i\u0004E\u0002<\t\u007f!QAR\tC\u0002\u001dCa!U\tA\u0004\u0011\r\u0003CB T\t\u000b\"y\u0005\u0005\u0005\u0002v\u0005]Dq\tC&!\rYD\u0011\n\u0003\u0007\u0003\u001b\t\"\u0019A$\u0011\u0007m\"i\u0005\u0002\u0004\u0002\u0014E\u0011\ra\u0012\t\bw\u0011ECq\tC&\t\u001d\t9)\u0005b\u0001\t\'*b\u0001\"\u0016\u0005\\\u0011}\u0013c\u0001%\u0005XAA\u0011qRAM\t3\"i\u0006E\u0002<\t7\"q!a\u0015\u0005R\t\u0007q\tE\u0002<\t?\"q!!\u0017\u0005R\t\u0007q\tC\u0003`#\u0001\u000f\u0001\rC\u0003h#\u0001\u000f\u0001\u000e\u0003\u0004p#\u0001\u0007Aq\r\t\u0007UE$)\u0005\"\u0010\t\u000f\r\u001d\u0018\u00031\u0001\u0003\u001a!1A/\u0005a\u0001\t\u001f*B\u0001b\u001c\u0005\u0000Q1A\u0011\u000fCF\t\u001b#B\u0001b\u001d\u0005\bRQAQ\u000fCA\ts\"\u0019\t\"\"\u0011\u0007\u0011]dJD\u0002<\tsBa!\u0010\nA\u0004\u0011m\u0004\u0003B C\t{\u00022a\u000fC@\t\u00151%C1\u0001H\u0011\u0019\t&\u0003q\u0001\u0002F\")qL\u0005a\u0002A\")qM\u0005a\u0002Q\"1qN\u0005a\u0001\t\u0013\u0003bAK9\u0002H\u0012u\u0004bBBt%\u0001\u0007!\u0011\u0004\u0005\u0007iJ\u0001\r!!4\u0002\u000b\u0019|\'OT8\u0016\u0011\u0011ME1\u0016CX\tG#B\u0001\"&\u0005>R!Aq\u0013C]))!I\n\"*\u0005\u001e\u0012UFq\u0017\t\u0004\t7sebA\u001e\u0005\u001e\"1Qh\u0005a\u0002\t?\u0003Ba\u0010\"\u0005\"B\u00191\bb)\u0005\u000b\u0019\u001b\"\u0019A$\t\rE\u001b\u00029\u0001CT!\u0019y4\u000b\"+\u0005.B\u00191\bb+\u0005\u000b]\u001b\"\u0019A$\u0011\u000bm\"y\u000b\"+\u0005\ri\u001b\"\u0019\u0001CY+\r9E1\u0017\u0003\u0007;\u0012=&\u0019A$\t\u000b}\u001b\u00029\u00011\t\u000b\u001d\u001c\u00029\u00015\t\r=\u001c\u0002\u0019\u0001C^!\u0019Q\u0013\u000f\"+\u0005\"\"1Ao\u0005a\u0001\t[+\"\u0002\"1\u0005\\\u0012}Gq\u001eCi)\u0011!\u0019\rb;\u0015\t\u0011\u0015Gq\u001d\u000b\u000b\t\u000f$\u0019\u000eb3\u0005d\u0012\u0015\bc\u0001Ce\u001d:\u00191\bb3\t\ru\"\u00029\u0001Cg!\u0011y$\tb4\u0011\u0007m\"\t\u000eB\u0003G)\t\u0007q\t\u0003\u0004R)\u0001\u000fAQ\u001b\t\u0007\u007fM#9\u000e\"9\u0011\u000f)\n)\u0001\"7\u0005^B\u00191\bb7\u0005\r\u00055AC1\u0001H!\rYDq\u001c\u0003\u0007\u0003\'!\"\u0019A$\u0011\r\u0005]\u0011q\u0006Cl\u0011\u0015yF\u0003q\u0001a\u0011\u00159G\u0003q\u0001i\u0011\u0019yG\u00031\u0001\u0005jB1!&\u001dCl\t\u001fDa\u0001\u001e\u000bA\u0002\u00115\bcB\u001e\u0005p\u0012eGQ\u001c\u0003\b\u0003\u0007\"\"\u0019\u0001Cy+\u0019!\u0019\u0010\"?\u0005~F\u0019\u0001\n\">\u0011\u0011\u0005]\u00111\nC|\tw\u00042a\u000fC}\t\u001d\t\u0019\u0006b<C\u0002\u001d\u00032a\u000fC\u007f\t\u001d\tI\u0006b<C\u0002\u001d+\"\"\"\u0001\u0006\u001c\u0015}Q1EC\t)\u0011)\u0019!b\u000f\u0015\t\u0015\u0015Qq\u0007\u000b\u000b\u000b\u000f)\u0019\"b\u0003\u00064\u0015U\u0002cAC\u0005\u001d:\u00191(b\u0003\t\ru*\u00029AC\u0007!\u0011y$)b\u0004\u0011\u0007m*\t\u0002B\u0003G+\t\u0007q\t\u0003\u0004R+\u0001\u000fQQ\u0003\t\u0007\u007fM+9\"\"\t\u0011\u0011\u0005U\u0014qOC\r\u000b;\u00012aOC\u000e\t\u0019\ti!\u0006b\u0001\u000fB\u00191(b\b\u0005\r\u0005MQC1\u0001H!\u001dYT1EC\r\u000b;!q!a\"\u0016\u0005\u0004))#\u0006\u0004\u0006(\u00155R\u0011G\t\u0004\u0011\u0016%\u0002\u0003CAH\u00033+Y#b\f\u0011\u0007m*i\u0003B\u0004\u0002T\u0015\r\"\u0019A$\u0011\u0007m*\t\u0004B\u0004\u0002Z\u0015\r\"\u0019A$\t\u000b}+\u00029\u00011\t\u000b\u001d,\u00029\u00015\t\r=,\u0002\u0019AC\u001d!\u0019Q\u0013/b\u0006\u0006\u0010!1A/\u0006a\u0001\u000bC)B!b\u0010\u0006PQ!Q\u0011IC.)\u0011)\u0019%b\u0016\u0015\u0015\u0015\u0015S\u0011KC%\u000b\'*)\u0006E\u0002\u0006H9s1aOC%\u0011\u0019id\u0003q\u0001\u0006LA!qHQC\'!\rYTq\n\u0003\u0006\rZ\u0011\ra\u0012\u0005\u0007#Z\u0001\u001d!!2\t\u000b}3\u00029\u00011\t\u000b\u001d4\u00029\u00015\t\r=4\u0002\u0019AC-!\u0019Q\u0013/a2\u0006N!1AO\u0006a\u0001\u0003\u001b\f!BZ8s\u0005\u0016$x/Z3o+!)\t\'\"\u001f\u0006~\u0015ED\u0003CC2\u000b\u0017+y)b%\u0015\t\u0015\u0015Tq\u0011\u000b\u000b\u000bO*\u0019(b\u001b\u0006\u0004\u0016\u0015\u0005cAC5\u001d:\u00191(b\u001b\t\ru:\u00029AC7!\u0011y$)b\u001c\u0011\u0007m*\t\bB\u0003G/\t\u0007q\t\u0003\u0004R/\u0001\u000fQQ\u000f\t\u0007\u007fM+9(b\u001f\u0011\u0007m*I\bB\u0003X/\t\u0007q\tE\u0003<\u000b{*9\b\u0002\u0004[/\t\u0007QqP\u000b\u0004\u000f\u0016\u0005EAB/\u0006~\t\u0007q\tC\u0003`/\u0001\u000f\u0001\rC\u0003h/\u0001\u000f\u0001\u000e\u0003\u0004p/\u0001\u0007Q\u0011\u0012\t\u0007UE,9(b\u001c\t\u000f\u00155u\u00031\u0001\u0003\u001a\u0005!aM]8n\u0011\u001d)\tj\u0006a\u0001\u00053\tA!\u001e9U_\"1Ao\u0006a\u0001\u000bw*\"\"b&\u00062\u0016UV\u0011ZCT)!)I*\"1\u0006D\u0016\u0015G\u0003BCN\u000b{#\"\"\"(\u0006*\u0016\u0005V\u0011XC^!\r)yJ\u0014\b\u0004w\u0015\u0005\u0006BB\u001f\u0019\u0001\b)\u0019\u000b\u0005\u0003@\u0005\u0016\u0015\u0006cA\u001e\u0006(\u0012)a\t\u0007b\u0001\u000f\"1\u0011\u000b\u0007a\u0002\u000bW\u0003baP*\u0006.\u0016]\u0006c\u0002\u0016\u0002\u0006\u0015=V1\u0017\t\u0004w\u0015EFABA\u00071\t\u0007q\tE\u0002<\u000bk#a!a\u0005\u0019\u0005\u00049\u0005CBA\f\u0003_)i\u000bC\u0003`1\u0001\u000f\u0001\rC\u0003h1\u0001\u000f\u0001\u000e\u0003\u0004p1\u0001\u0007Qq\u0018\t\u0007UE,i+\"*\t\u000f\u00155\u0005\u00041\u0001\u0003\u001a!9Q\u0011\u0013\rA\u0002\te\u0001B\u0002;\u0019\u0001\u0004)9\rE\u0004<\u000b\u0013,y+b-\u0005\u000f\u0005\r\u0003D1\u0001\u0006LV1QQZCj\u000b/\f2\u0001SCh!!\t9\"a\u0013\u0006R\u0016U\u0007cA\u001e\u0006T\u00129\u00111KCe\u0005\u00049\u0005cA\u001e\u0006X\u00129\u0011\u0011LCe\u0005\u00049UCCCn\u000bk,I0\"@\u0006lRAQQ\u001cD\u000b\r/1I\u0002\u0006\u0003\u0006`\u001aEACCCq\u000b[,)O\"\u0004\u0007\u0010A\u0019Q1\u001d(\u000f\u0007m*)\u000f\u0003\u0004>3\u0001\u000fQq\u001d\t\u0005\u007f\t+I\u000fE\u0002<\u000bW$QAR\rC\u0002\u001dCa!U\rA\u0004\u0015=\bCB T\u000bc,Y\u0010\u0005\u0005\u0002v\u0005]T1_C|!\rYTQ\u001f\u0003\u0007\u0003\u001bI\"\u0019A$\u0011\u0007m*I\u0010\u0002\u0004\u0002\u0014e\u0011\ra\u0012\t\bw\u0015uX1_C|\t\u001d\t9)\u0007b\u0001\u000b\u007f,bA\"\u0001\u0007\b\u0019-\u0011c\u0001%\u0007\u0004AA\u0011qRAM\r\u000b1I\u0001E\u0002<\r\u000f!q!a\u0015\u0006~\n\u0007q\tE\u0002<\r\u0017!q!!\u0017\u0006~\n\u0007q\tC\u0003`3\u0001\u000f\u0001\rC\u0003h3\u0001\u000f\u0001\u000e\u0003\u0004p3\u0001\u0007a1\u0003\t\u0007UE,\t0\";\t\u000f\u00155\u0015\u00041\u0001\u0003\u001a!9Q\u0011S\rA\u0002\te\u0001B\u0002;\u001a\u0001\u0004)Y0\u0006\u0003\u0007\u001e\u00195B\u0003\u0003D\u0010\rs1YD\"\u0010\u0015\t\u0019\u0005bQ\u0007\u000b\u000b\rG1yCb\n\u00072\u0019M\u0002c\u0001D\u0013\u001d:\u00191Hb\n\t\ruR\u00029\u0001D\u0015!\u0011y$Ib\u000b\u0011\u0007m2i\u0003B\u0003G5\t\u0007q\t\u0003\u0004R5\u0001\u000f\u0011Q\u0019\u0005\u0006?j\u0001\u001d\u0001\u0019\u0005\u0006Oj\u0001\u001d\u0001\u001b\u0005\u0007_j\u0001\rAb\u000e\u0011\r)\n\u0018q\u0019D\u0016\u0011\u001d)iI\u0007a\u0001\u00053Aq!\"%\u001b\u0001\u0004\u0011I\u0002\u0003\u0004u5\u0001\u0007\u0011QZ\u0001\tM>\u0014XI^3ssVAa1\tD.\r?2\u0019\u0006\u0006\u0003\u0007F\u00195D\u0003\u0002D$\rS\"\"B\"\u0013\u0007V\u00195cQ\rD4!\r1YE\u0014\b\u0004w\u00195\u0003BB\u001f\u001c\u0001\b1y\u0005\u0005\u0003@\u0005\u001aE\u0003cA\u001e\u0007T\u0011)ai\u0007b\u0001\u000f\"1\u0011k\u0007a\u0002\r/\u0002baP*\u0007Z\u0019u\u0003cA\u001e\u0007\\\u0011)qk\u0007b\u0001\u000fB)1Hb\u0018\u0007Z\u00111!l\u0007b\u0001\rC*2a\u0012D2\t\u0019ifq\fb\u0001\u000f\")ql\u0007a\u0002A\")qm\u0007a\u0002Q\"1qn\u0007a\u0001\rW\u0002bAK9\u0007Z\u0019E\u0003B\u0002;\u001c\u0001\u00041i&\u0006\u0006\u0007r\u0019-eq\u0012DP\r\u0003#BAb\u001d\u0007\u001cR!aQ\u000fDL))19Hb!\u0007|\u0019MeQ\u0013\t\u0004\rsrebA\u001e\u0007|!1Q\b\ba\u0002\r{\u0002Ba\u0010\"\u0007\u0000A\u00191H\"!\u0005\u000b\u0019c\"\u0019A$\t\rEc\u00029\u0001DC!\u0019y4Kb\"\u0007\u0012B9!&!\u0002\u0007\n\u001a5\u0005cA\u001e\u0007\f\u00121\u0011Q\u0002\u000fC\u0002\u001d\u00032a\u000fDH\t\u0019\t\u0019\u0002\bb\u0001\u000fB1\u0011qCA\u0018\r\u000fCQa\u0018\u000fA\u0004\u0001DQa\u001a\u000fA\u0004!Daa\u001c\u000fA\u0002\u0019e\u0005C\u0002\u0016r\r\u000f3y\b\u0003\u0004u9\u0001\u0007aQ\u0014\t\bw\u0019}e\u0011\u0012DG\t\u001d\t\u0019\u0005\bb\u0001\rC+bAb)\u0007*\u001a5\u0016c\u0001%\u0007&BA\u0011qCA&\rO3Y\u000bE\u0002<\rS#q!a\u0015\u0007 \n\u0007q\tE\u0002<\r[#q!!\u0017\u0007 \n\u0007q)\u0006\u0006\u00072\u001a-gq\u001aDj\r\u0003$BAb-\u0007lR!aQ\u0017Dt))19Lb1\u0007<\u001a\rhQ\u001d\t\u0004\rssebA\u001e\u0007<\"1Q(\ba\u0002\r{\u0003Ba\u0010\"\u0007@B\u00191H\"1\u0005\u000b\u0019k\"\u0019A$\t\rEk\u00029\u0001Dc!\u0019y4Kb2\u0007RBA\u0011QOA<\r\u00134i\rE\u0002<\r\u0017$a!!\u0004\u001e\u0005\u00049\u0005cA\u001e\u0007P\u00121\u00111C\u000fC\u0002\u001d\u0003ra\u000fDj\r\u00134i\rB\u0004\u0002\bv\u0011\rA\"6\u0016\r\u0019]gQ\u001cDq#\rAe\u0011\u001c\t\t\u0003\u001f\u000bIJb7\u0007`B\u00191H\"8\u0005\u000f\u0005Mc1\u001bb\u0001\u000fB\u00191H\"9\u0005\u000f\u0005ec1\u001bb\u0001\u000f\")q,\ba\u0002A\")q-\ba\u0002Q\"1q.\ba\u0001\rS\u0004bAK9\u0007H\u001a}\u0006B\u0002;\u001e\u0001\u00041\t.\u0006\u0003\u0007p\u001a}H\u0003\u0002Dy\u000f\u0017!BAb=\b\bQQaQ_D\u0001\rs<\u0019a\"\u0002\u0011\u0007\u0019]hJD\u0002<\rsDa!\u0010\u0010A\u0004\u0019m\b\u0003B C\r{\u00042a\u000fD\u0000\t\u00151eD1\u0001H\u0011\u0019\tf\u0004q\u0001\u0002F\")qL\ba\u0002A\")qM\ba\u0002Q\"1qN\ba\u0001\u000f\u0013\u0001bAK9\u0002H\u001au\bB\u0002;\u001f\u0001\u0004\ti-\u0001\u0006J]N\u0004Xm\u0019;peN\u00042!!\u001e!\'\u0011\u0001\u0013fb\u0005\u0011\u0007\u0005U\u0004!\u0001\u0004=S:LGO\u0010\u000b\u0003\u000f\u001f\u0001
    #9 = Utf8               forAll$
   #10 = Utf8               (Lorg/scalatest/Inspectors;Ljava/lang/Object;Lscala/Function1;Lorg/scalatest/enablers/Collecting;Lorg/scalatest/enablers/InspectorAsserting;Lorg/scalactic/Prettifier;Lorg/scalactic/source/Position;)Ljava/lang/Object;
   #11 = Utf8               $this
   #12 = Utf8               xs
   #13 = Utf8               fun
   #14 = Utf8               collecting
   #15 = Utf8               asserting
   #16 = Utf8               prettifier
   #17 = Utf8               pos
   #18 = Utf8               forAll
   #19 = Utf8               (Ljava/lang/Object;Lscala/Function1;Lorg/scalatest/enablers/Collecting;Lorg/scalatest/enablers/InspectorAsserting;Lorg/scalactic/Prettifier;Lorg/scalactic/source/Position;)Ljava/lang/Object;
   #20 = NameAndType        #18:#19       // forAll:(Ljava/lang/Object;Lscala/Function1;Lorg/scalatest/enablers/Collecting;Lorg/scalatest/enablers/InspectorAsserting;Lorg/scalactic/Prettifier;Lorg/scalactic/source/Position;)Ljava/lang/Object;
   #21 = InterfaceMethodref #2.#20        // org/scalatest/Inspectors.forAll:(Ljava/lang/Object;Lscala/Function1;Lorg/scalatest/enablers/Collecting;Lorg/scalatest/enablers/InspectorAsserting;Lorg/scalactic/Prettifier;Lorg/scalactic/source/Position;)Ljava/lang/Object;
   #22 = Utf8               Lorg/scalatest/Inspectors;
   #23 = Utf8               Ljava/lang/Object;
   #24 = Utf8               Lscala/Function1;
   #25 = Utf8               Lorg/scalatest/enablers/Collecting;
   #26 = Utf8               Lorg/scalatest/enablers/InspectorAsserting;
   #27 = Utf8               Lorg/scalactic/Prettifier;
   #28 = Utf8               Lorg/scalactic/source/Position;
   #29 = Utf8               <E:Ljava/lang/Object;C:Ljava/lang/Object;ASSERTION:Ljava/lang/Object;>(TC;Lscala/Function1<TE;TASSERTION;>;Lorg/scalatest/enablers/Collecting<TE;TC;>;Lorg/scalatest/enablers/InspectorAsserting<TASSERTION;>;Lorg/scalactic/Prettifier;Lorg/scalactic/source/Position;)Ljava/lang/Object;
   #30 = Utf8               org/scalatest/enablers/Collecting
   #31 = Class              #30           // org/scalatest/enablers/Collecting
   #32 = Utf8               genTraversableFrom
   #33 = Utf8               (Ljava/lang/Object;)Lscala/collection/Iterable;
   #34 = NameAndType        #32:#33       // genTraversableFrom:(Ljava/lang/Object;)Lscala/collection/Iterable;
   #35 = InterfaceMethodref #31.#34       // org/scalatest/enablers/Collecting.genTraversableFrom:(Ljava/lang/Object;)Lscala/collection/Iterable;
   #36 = Utf8               org/scalatest/enablers/InspectorAsserting
   #37 = Class              #36           // org/scalatest/enablers/InspectorAsserting
   #38 = Utf8               (Lscala/collection/Iterable;Ljava/lang/Object;ZLorg/scalactic/Prettifier;Lorg/scalactic/source/Position;Lscala/Function1;)Ljava/lang/Object;
   #39 = NameAndType        #18:#38       // forAll:(Lscala/collection/Iterable;Ljava/lang/Object;ZLorg/scalactic/Prettifier;Lorg/scalactic/source/Position;Lscala/Function1;)Ljava/lang/Object;
   #40 = InterfaceMethodref #37.#39       // org/scalatest/enablers/InspectorAsserting.forAll:(Lscala/collection/Iterable;Ljava/lang/Object;ZLorg/scalactic/Prettifier;Lorg/scalactic/source/Position;Lscala/Function1;)Ljava/lang/Object;
   #41 = Utf8               this
   #42 = Utf8               (Lorg/scalatest/Inspectors;Lscala/collection/Map;Lscala/Function1;Lorg/scalatest/enablers/Collecting;Lorg/scalatest/enablers/InspectorAsserting;Lorg/scalactic/Prettifier;Lorg/scalactic/source/Position;)Ljava/lang/Object;
   #43 = Utf8               (Lscala/collection/Map;Lscala/Function1;Lorg/scalatest/enablers/Collecting;Lorg/scalatest/enablers/InspectorAsserting;Lorg/scalactic/Prettifier;Lorg/scalactic/source/Position;)Ljava/lang/Object;
   #44 = NameAndType        #18:#43       // forAll:(Lscala/collection/Map;Lscala/Function1;Lorg/scalatest/enablers/Collecting;Lorg/scalatest/enablers/InspectorAsserting;Lorg/scalactic/Prettifier;Lorg/scalactic/source/Position;)Ljava/lang/Object;
   #45 = InterfaceMethodref #2.#44        // org/scalatest/Inspectors.forAll:(Lscala/collection/Map;Lscala/Function1;Lorg/scalatest/enablers/Collecting;Lorg/scalatest/enablers/InspectorAsserting;Lorg/scalactic/Prettifier;Lorg/scalactic/source/Position;)Ljava/lang/Object;
   #46 = Utf8               Lscala/collection/Map;
   #47 = Utf8               <K:Ljava/lang/Object;V:Ljava/lang/Object;MAP::Lscala/collection/Map<Ljava/lang/Object;Ljava/lang/Object;>;ASSERTION:Ljava/lang/Object;>(TMAP;Lscala/Function1<Lscala/Tuple2<TK;TV;>;TASSERTION;>;Lorg/scalatest/enablers/Collecting<Lscala/Tuple2<TK;TV;>;Lscala/collection/Iterable<Lscala/Tuple2<TK;TV;>;>;>;Lorg/scalatest/enablers/InspectorAsserting<TASSERTION;>;Lorg/scalactic/Prettifier;Lorg/scalactic/source/Position;)Ljava/lang/Object;
   #48 = Utf8               (Lorg/scalatest/Inspectors;Ljava/util/Map;Lscala/Function1;Lorg/scalatest/enablers/Collecting;Lorg/scalatest/enablers/InspectorAsserting;Lorg/scalactic/Prettifier;Lorg/scalactic/source/Position;)Ljava/lang/Object;
   #49 = Utf8               (Ljava/util/Map;Lscala/Function1;Lorg/scalatest/enablers/Collecting;Lorg/scalatest/enablers/InspectorAsserting;Lorg/scalactic/Prettifier;Lorg/scalactic/source/Position;)Ljava/lang/Object;
   #50 = NameAndType        #18:#49       // forAll:(Ljava/util/Map;Lscala/Function1;Lorg/scalatest/enablers/Collecting;Lorg/scalatest/enablers/InspectorAsserting;Lorg/scalactic/Prettifier;Lorg/scalactic/source/Position;)Ljava/lang/Object;
   #51 = InterfaceMethodref #2.#50        // org/scalatest/Inspectors.forAll:(Ljava/util/Map;Lscala/Function1;Lorg/scalatest/enablers/Collecting;Lorg/scalatest/enablers/InspectorAsserting;Lorg/scalactic/Prettifier;Lorg/scalactic/source/Position;)Ljava/lang/Object;
   #52 = Utf8               Ljava/util/Map;
   #53 = Utf8               <K:Ljava/lang/Object;V:Ljava/lang/Object;JMAP::Ljava/util/Map<Ljava/lang/Object;Ljava/lang/Object;>;ASSERTION:Ljava/lang/Object;>(TJMAP;Lscala/Function1<Lorg/scalatest/Entry<TK;TV;>;TASSERTION;>;Lorg/scalatest/enablers/Collecting<Lorg/scalatest/Entry<TK;TV;>;TJMAP;>;Lorg/scalatest/enablers/InspectorAsserting<TASSERTION;>;Lorg/scalactic/Prettifier;Lorg/scalactic/source/Position;)Ljava/lang/Object;
   #54 = Utf8               (Lorg/scalatest/Inspectors;Ljava/lang/String;Lscala/Function1;Lorg/scalatest/enablers/Collecting;Lorg/scalatest/enablers/InspectorAsserting;Lorg/scalactic/Prettifier;Lorg/scalactic/source/Position;)Ljava/lang/Object;
   #55 = Utf8               (Ljava/lang/String;Lscala/Function1;Lorg/scalatest/enablers/Collecting;Lorg/scalatest/enablers/InspectorAsserting;Lorg/scalactic/Prettifier;Lorg/scalactic/source/Position;)Ljava/lang/Object;
   #56 = NameAndType        #18:#55       // forAll:(Ljava/lang/String;Lscala/Function1;Lorg/scalatest/enablers/Collecting;Lorg/scalatest/enablers/InspectorAsserting;Lorg/scalactic/Prettifier;Lorg/scalactic/source/Position;)Ljava/lang/Object;
   #57 = InterfaceMethodref #2.#56        // org/scalatest/Inspectors.forAll:(Ljava/lang/String;Lscala/Function1;Lorg/scalatest/enablers/Collecting;Lorg/scalatest/enablers/InspectorAsserting;Lorg/scalactic/Prettifier;Lorg/scalactic/source/Position;)Ljava/lang/Object;
   #58 = Utf8               Ljava/lang/String;
   #59 = Utf8               <ASSERTION:Ljava/lang/Object;>(Ljava/lang/String;Lscala/Function1<Ljava/lang/Object;TASSERTION;>;Lorg/scalatest/enablers/Collecting<Ljava/lang/Object;Ljava/lang/String;>;Lorg/scalatest/enablers/InspectorAsserting<TASSERTION;>;Lorg/scalactic/Prettifier;Lorg/scalactic/source/Position;)Ljava/lang/Object;
   #60 = Utf8               forAtLeast$
   #61 = Utf8               (Lorg/scalatest/Inspectors;ILjava/lang/Object;Lscala/Function1;Lorg/scalatest/enablers/Collecting;Lorg/scalatest/enablers/InspectorAsserting;Lorg/scalactic/Prettifier;Lorg/scalactic/source/Position;)Ljava/lang/Object;
   #62 = Utf8               min
   #63 = Utf8               forAtLeast
   #64 = Utf8               (ILjava/lang/Object;Lscala/Function1;Lorg/scalatest/enablers/Collecting;Lorg/scalatest/enablers/InspectorAsserting;Lorg/scalactic/Prettifier;Lorg/scalactic/source/Position;)Ljava/lang/Object;
   #65 = NameAndType        #63:#64       // forAtLeast:(ILjava/lang/Object;Lscala/Function1;Lorg/scalatest/enablers/Collecting;Lorg/scalatest/enablers/InspectorAsserting;Lorg/scalactic/Prettifier;Lorg/scalactic/source/Position;)Ljava/lang/Object;
   #66 = InterfaceMethodref #2.#65        // org/scalatest/Inspectors.forAtLeast:(ILjava/lang/Object;Lscala/Function1;Lorg/scalatest/enablers/Collecting;Lorg/scalatest/enablers/InspectorAsserting;Lorg/scalactic/Prettifier;Lorg/scalactic/source/Position;)Ljava/lang/Object;
   #67 = Utf8               I
   #68 = Utf8               <E:Ljava/lang/Object;C:Ljava/lang/Object;ASSERTION:Ljava/lang/Object;>(ITC;Lscala/Function1<TE;TASSERTION;>;Lorg/scalatest/enablers/Collecting<TE;TC;>;Lorg/scalatest/enablers/InspectorAsserting<TASSERTION;>;Lorg/scalactic/Prettifier;Lorg/scalactic/source/Position;)Ljava/lang/Object;
   #69 = Utf8               (ILscala/collection/Iterable;Ljava/lang/Object;ZLorg/scalactic/Prettifier;Lorg/scalactic/source/Position;Lscala/Function1;)Ljava/lang/Object;
   #70 = NameAndType        #63:#69       // forAtLeast:(ILscala/collection/Iterable;Ljava/lang/Object;ZLorg/scalactic/Prettifier;Lorg/scalactic/source/Position;Lscala/Function1;)Ljava/lang/Object;
   #71 = InterfaceMethodref #37.#70       // org/scalatest/enablers/InspectorAsserting.forAtLeast:(ILscala/collection/Iterable;Ljava/lang/Object;ZLorg/scalactic/Prettifier;Lorg/scalactic/source/Position;Lscala/Function1;)Ljava/lang/Object;
   #72 = Utf8               (Lorg/scalatest/Inspectors;ILscala/collection/Map;Lscala/Function1;Lorg/scalatest/enablers/Collecting;Lorg/scalatest/enablers/InspectorAsserting;Lorg/scalactic/Prettifier;Lorg/scalactic/source/Position;)Ljava/lang/Object;
   #73 = Utf8               (ILscala/collection/Map;Lscala/Function1;Lorg/scalatest/enablers/Collecting;Lorg/scalatest/enablers/InspectorAsserting;Lorg/scalactic/Prettifier;Lorg/scalactic/source/Position;)Ljava/lang/Object;
   #74 = NameAndType        #63:#73       // forAtLeast:(ILscala/collection/Map;Lscala/Function1;Lorg/scalatest/enablers/Collecting;Lorg/scalatest/enablers/InspectorAsserting;Lorg/scalactic/Prettifier;Lorg/scalactic/source/Position;)Ljava/lang/Object;
   #75 = InterfaceMethodref #2.#74        // org/scalatest/Inspectors.forAtLeast:(ILscala/collection/Map;Lscala/Function1;Lorg/scalatest/enablers/Collecting;Lorg/scalatest/enablers/InspectorAsserting;Lorg/scalactic/Prettifier;Lorg/scalactic/source/Position;)Ljava/lang/Object;
   #76 = Utf8               <K:Ljava/lang/Object;V:Ljava/lang/Object;MAP::Lscala/collection/Map<Ljava/lang/Object;Ljava/lang/Object;>;ASSERTION:Ljava/lang/Object;>(ITMAP;Lscala/Function1<Lscala/Tuple2<TK;TV;>;TASSERTION;>;Lorg/scalatest/enablers/Collecting<Lscala/Tuple2<TK;TV;>;Lscala/collection/Iterable<Lscala/Tuple2<TK;TV;>;>;>;Lorg/scalatest/enablers/InspectorAsserting<TASSERTION;>;Lorg/scalactic/Prettifier;Lorg/scalactic/source/Position;)Ljava/lang/Object;
   #77 = Utf8               (Lorg/scalatest/Inspectors;ILjava/util/Map;Lscala/Function1;Lorg/scalatest/enablers/Collecting;Lorg/scalatest/enablers/InspectorAsserting;Lorg/scalactic/Prettifier;Lorg/scalactic/source/Position;)Ljava/lang/Object;
   #78 = Utf8               (ILjava/util/Map;Lscala/Function1;Lorg/scalatest/enablers/Collecting;Lorg/scalatest/enablers/InspectorAsserting;Lorg/scalactic/Prettifier;Lorg/scalactic/source/Position;)Ljava/lang/Object;
   #79 = NameAndType        #63:#78       // forAtLeast:(ILjava/util/Map;Lscala/Function1;Lorg/scalatest/enablers/Collecting;Lorg/scalatest/enablers/InspectorAsserting;Lorg/scalactic/Prettifier;Lorg/scalactic/source/Position;)Ljava/lang/Object;
   #80 = InterfaceMethodref #2.#79        // org/scalatest/Inspectors.forAtLeast:(ILjava/util/Map;Lscala/Function1;Lorg/scalatest/enablers/Collecting;Lorg/scalatest/enablers/InspectorAsserting;Lorg/scalactic/Prettifier;Lorg/scalactic/source/Position;)Ljava/lang/Object;
   #81 = Utf8               <K:Ljava/lang/Object;V:Ljava/lang/Object;JMAP::Ljava/util/Map<Ljava/lang/Object;Ljava/lang/Object;>;ASSERTION:Ljava/lang/Object;>(ITJMAP;Lscala/Function1<Lorg/scalatest/Entry<TK;TV;>;TASSERTION;>;Lorg/scalatest/enablers/Collecting<Lorg/scalatest/Entry<TK;TV;>;TJMAP;>;Lorg/scalatest/enablers/InspectorAsserting<TASSERTION;>;Lorg/scalactic/Prettifier;Lorg/scalactic/source/Position;)Ljava/lang/Object;
   #82 = Utf8               (Lorg/scalatest/Inspectors;ILjava/lang/String;Lscala/Function1;Lorg/scalatest/enablers/Collecting;Lorg/scalatest/enablers/InspectorAsserting;Lorg/scalactic/Prettifier;Lorg/scalactic/source/Position;)Ljava/lang/Object;
   #83 = Utf8               (ILjava/lang/String;Lscala/Function1;Lorg/scalatest/enablers/Collecting;Lorg/scalatest/enablers/InspectorAsserting;Lorg/scalactic/Prettifier;Lorg/scalactic/source/Position;)Ljava/lang/Object;
   #84 = NameAndType        #63:#83       // forAtLeast:(ILjava/lang/String;Lscala/Function1;Lorg/scalatest/enablers/Collecting;Lorg/scalatest/enablers/InspectorAsserting;Lorg/scalactic/Prettifier;Lorg/scalactic/source/Position;)Ljava/lang/Object;
   #85 = InterfaceMethodref #2.#84        // org/scalatest/Inspectors.forAtLeast:(ILjava/lang/String;Lscala/Function1;Lorg/scalatest/enablers/Collecting;Lorg/scalatest/enablers/InspectorAsserting;Lorg/scalactic/Prettifier;Lorg/scalactic/source/Position;)Ljava/lang/Object;
   #86 = Utf8               <ASSERTION:Ljava/lang/Object;>(ILjava/lang/String;Lscala/Function1<Ljava/lang/Object;TASSERTION;>;Lorg/scalatest/enablers/Collecting<Ljava/lang/Object;Ljava/lang/String;>;Lorg/scalatest/enablers/InspectorAsserting<TASSERTION;>;Lorg/scalactic/Prettifier;Lorg/scalactic/source/Position;)Ljava/lang/Object;
   #87 = Utf8               shouldIncludeIndex
   #88 = Utf8               (Lscala/collection/Iterable;)Z
   #89 = Utf8               <T:Ljava/lang/Object;R:Ljava/lang/Object;>(Lscala/collection/Iterable<TT;>;)Z
   #90 = Utf8               scala/collection/Seq
   #91 = Class              #90           // scala/collection/Seq
   #92 = Utf8               Lscala/collection/Iterable;
   #93 = Utf8               forAtMost$
   #94 = Utf8               max
   #95 = Utf8               forAtMost
   #96 = NameAndType        #95:#64       // forAtMost:(ILjava/lang/Object;Lscala/Function1;Lorg/scalatest/enablers/Collecting;Lorg/scalatest/enablers/InspectorAsserting;Lorg/scalactic/Prettifier;Lorg/scalactic/source/Position;)Ljava/lang/Object;
   #97 = InterfaceMethodref #2.#96        // org/scalatest/Inspectors.forAtMost:(ILjava/lang/Object;Lscala/Function1;Lorg/scalatest/enablers/Collecting;Lorg/scalatest/enablers/InspectorAsserting;Lorg/scalactic/Prettifier;Lorg/scalactic/source/Position;)Ljava/lang/Object;
   #98 = NameAndType        #95:#69       // forAtMost:(ILscala/collection/Iterable;Ljava/lang/Object;ZLorg/scalactic/Prettifier;Lorg/scalactic/source/Position;Lscala/Function1;)Ljava/lang/Object;
   #99 = InterfaceMethodref #37.#98       // org/scalatest/enablers/InspectorAsserting.forAtMost:(ILscala/collection/Iterable;Ljava/lang/Object;ZLorg/scalactic/Prettifier;Lorg/scalactic/source/Position;Lscala/Function1;)Ljava/lang/Object;
  #100 = NameAndType        #95:#73       // forAtMost:(ILscala/collection/Map;Lscala/Function1;Lorg/scalatest/enablers/Collecting;Lorg/scalatest/enablers/InspectorAsserting;Lorg/scalactic/Prettifier;Lorg/scalactic/source/Position;)Ljava/lang/Object;
  #101 = InterfaceMethodref #2.#100       // org/scalatest/Inspectors.forAtMost:(ILscala/collection/Map;Lscala/Function1;Lorg/scalatest/enablers/Collecting;Lorg/scalatest/enablers/InspectorAsserting;Lorg/scalactic/Prettifier;Lorg/scalactic/source/Position;)Ljava/lang/Object;
  #102 = NameAndType        #95:#78       // forAtMost:(ILjava/util/Map;Lscala/Function1;Lorg/scalatest/enablers/Collecting;Lorg/scalatest/enablers/InspectorAsserting;Lorg/scalactic/Prettifier;Lorg/scalactic/source/Position;)Ljava/lang/Object;
  #103 = InterfaceMethodref #2.#102       // org/scalatest/Inspectors.forAtMost:(ILjava/util/Map;Lscala/Function1;Lorg/scalatest/enablers/Collecting;Lorg/scalatest/enablers/InspectorAsserting;Lorg/scalactic/Prettifier;Lorg/scalactic/source/Position;)Ljava/lang/Object;
  #104 = NameAndType        #95:#83       // forAtMost:(ILjava/lang/String;Lscala/Function1;Lorg/scalatest/enablers/Collecting;Lorg/scalatest/enablers/InspectorAsserting;Lorg/scalactic/Prettifier;Lorg/scalactic/source/Position;)Ljava/lang/Object;
  #105 = InterfaceMethodref #2.#104       // org/scalatest/Inspectors.forAtMost:(ILjava/lang/String;Lscala/Function1;Lorg/scalatest/enablers/Collecting;Lorg/scalatest/enablers/InspectorAsserting;Lorg/scalactic/Prettifier;Lorg/scalactic/source/Position;)Ljava/lang/Object;
  #106 = Utf8               forExactly$
  #107 = Utf8               succeededCount
  #108 = Utf8               forExactly
  #109 = NameAndType        #108:#64      // forExactly:(ILjava/lang/Object;Lscala/Function1;Lorg/scalatest/enablers/Collecting;Lorg/scalatest/enablers/InspectorAsserting;Lorg/scalactic/Prettifier;Lorg/scalactic/source/Position;)Ljava/lang/Object;
  #110 = InterfaceMethodref #2.#109       // org/scalatest/Inspectors.forExactly:(ILjava/lang/Object;Lscala/Function1;Lorg/scalatest/enablers/Collecting;Lorg/scalatest/enablers/InspectorAsserting;Lorg/scalactic/Prettifier;Lorg/scalactic/source/Position;)Ljava/lang/Object;
  #111 = NameAndType        #108:#69      // forExactly:(ILscala/collection/Iterable;Ljava/lang/Object;ZLorg/scalactic/Prettifier;Lorg/scalactic/source/Position;Lscala/Function1;)Ljava/lang/Object;
  #112 = InterfaceMethodref #37.#111      // org/scalatest/enablers/InspectorAsserting.forExactly:(ILscala/collection/Iterable;Ljava/lang/Object;ZLorg/scalactic/Prettifier;Lorg/scalactic/source/Position;Lscala/Function1;)Ljava/lang/Object;
  #113 = NameAndType        #108:#73      // forExactly:(ILscala/collection/Map;Lscala/Function1;Lorg/scalatest/enablers/Collecting;Lorg/scalatest/enablers/InspectorAsserting;Lorg/scalactic/Prettifier;Lorg/scalactic/source/Position;)Ljava/lang/Object;
  #114 = InterfaceMethodref #2.#113       // org/scalatest/Inspectors.forExactly:(ILscala/collection/Map;Lscala/Function1;Lorg/scalatest/enablers/Collecting;Lorg/scalatest/enablers/InspectorAsserting;Lorg/scalactic/Prettifier;Lorg/scalactic/source/Position;)Ljava/lang/Object;
  #115 = NameAndType        #108:#78      // forExactly:(ILjava/util/Map;Lscala/Function1;Lorg/scalatest/enablers/Collecting;Lorg/scalatest/enablers/InspectorAsserting;Lorg/scalactic/Prettifier;Lorg/scalactic/source/Position;)Ljava/lang/Object;
  #116 = InterfaceMethodref #2.#115       // org/scalatest/Inspectors.forExactly:(ILjava/util/Map;Lscala/Function1;Lorg/scalatest/enablers/Collecting;Lorg/scalatest/enablers/InspectorAsserting;Lorg/scalactic/Prettifier;Lorg/scalactic/source/Position;)Ljava/lang/Object;
  #117 = NameAndType        #108:#83      // forExactly:(ILjava/lang/String;Lscala/Function1;Lorg/scalatest/enablers/Collecting;Lorg/scalatest/enablers/InspectorAsserting;Lorg/scalactic/Prettifier;Lorg/scalactic/source/Position;)Ljava/lang/Object;
  #118 = InterfaceMethodref #2.#117       // org/scalatest/Inspectors.forExactly:(ILjava/lang/String;Lscala/Function1;Lorg/scalatest/enablers/Collecting;Lorg/scalatest/enablers/InspectorAsserting;Lorg/scalactic/Prettifier;Lorg/scalactic/source/Position;)Ljava/lang/Object;
  #119 = Utf8               forNo$
  #120 = Utf8               forNo
  #121 = NameAndType        #120:#19      // forNo:(Ljava/lang/Object;Lscala/Function1;Lorg/scalatest/enablers/Collecting;Lorg/scalatest/enablers/InspectorAsserting;Lorg/scalactic/Prettifier;Lorg/scalactic/source/Position;)Ljava/lang/Object;
  #122 = InterfaceMethodref #2.#121       // org/scalatest/Inspectors.forNo:(Ljava/lang/Object;Lscala/Function1;Lorg/scalatest/enablers/Collecting;Lorg/scalatest/enablers/InspectorAsserting;Lorg/scalactic/Prettifier;Lorg/scalactic/source/Position;)Ljava/lang/Object;
  #123 = NameAndType        #120:#38      // forNo:(Lscala/collection/Iterable;Ljava/lang/Object;ZLorg/scalactic/Prettifier;Lorg/scalactic/source/Position;Lscala/Function1;)Ljava/lang/Object;
  #124 = InterfaceMethodref #37.#123      // org/scalatest/enablers/InspectorAsserting.forNo:(Lscala/collection/Iterable;Ljava/lang/Object;ZLorg/scalactic/Prettifier;Lorg/scalactic/source/Position;Lscala/Function1;)Ljava/lang/Object;
  #125 = NameAndType        #120:#43      // forNo:(Lscala/collection/Map;Lscala/Function1;Lorg/scalatest/enablers/Collecting;Lorg/scalatest/enablers/InspectorAsserting;Lorg/scalactic/Prettifier;Lorg/scalactic/source/Position;)Ljava/lang/Object;
  #126 = InterfaceMethodref #2.#125       // org/scalatest/Inspectors.forNo:(Lscala/collection/Map;Lscala/Function1;Lorg/scalatest/enablers/Collecting;Lorg/scalatest/enablers/InspectorAsserting;Lorg/scalactic/Prettifier;Lorg/scalactic/source/Position;)Ljava/lang/Object;
  #127 = NameAndType        #120:#49      // forNo:(Ljava/util/Map;Lscala/Function1;Lorg/scalatest/enablers/Collecting;Lorg/scalatest/enablers/InspectorAsserting;Lorg/scalactic/Prettifier;Lorg/scalactic/source/Position;)Ljava/lang/Object;
  #128 = InterfaceMethodref #2.#127       // org/scalatest/Inspectors.forNo:(Ljava/util/Map;Lscala/Function1;Lorg/scalatest/enablers/Collecting;Lorg/scalatest/enablers/InspectorAsserting;Lorg/scalactic/Prettifier;Lorg/scalactic/source/Position;)Ljava/lang/Object;
  #129 = NameAndType        #120:#55      // forNo:(Ljava/lang/String;Lscala/Function1;Lorg/scalatest/enablers/Collecting;Lorg/scalatest/enablers/InspectorAsserting;Lorg/scalactic/Prettifier;Lorg/scalactic/source/Position;)Ljava/lang/Object;
  #130 = InterfaceMethodref #2.#129       // org/scalatest/Inspectors.forNo:(Ljava/lang/String;Lscala/Function1;Lorg/scalatest/enablers/Collecting;Lorg/scalatest/enablers/InspectorAsserting;Lorg/scalactic/Prettifier;Lorg/scalactic/source/Position;)Ljava/lang/Object;
  #131 = Utf8               forBetween$
  #132 = Utf8               (Lorg/scalatest/Inspectors;IILjava/lang/Object;Lscala/Function1;Lorg/scalatest/enablers/Collecting;Lorg/scalatest/enablers/InspectorAsserting;Lorg/scalactic/Prettifier;Lorg/scalactic/source/Position;)Ljava/lang/Object;
  #133 = Utf8               from
  #134 = Utf8               upTo
  #135 = Utf8               forBetween
  #136 = Utf8               (IILjava/lang/Object;Lscala/Function1;Lorg/scalatest/enablers/Collecting;Lorg/scalatest/enablers/InspectorAsserting;Lorg/scalactic/Prettifier;Lorg/scalactic/source/Position;)Ljava/lang/Object;
  #137 = NameAndType        #135:#136     // forBetween:(IILjava/lang/Object;Lscala/Function1;Lorg/scalatest/enablers/Collecting;Lorg/scalatest/enablers/InspectorAsserting;Lorg/scalactic/Prettifier;Lorg/scalactic/source/Position;)Ljava/lang/Object;
  #138 = InterfaceMethodref #2.#137       // org/scalatest/Inspectors.forBetween:(IILjava/lang/Object;Lscala/Function1;Lorg/scalatest/enablers/Collecting;Lorg/scalatest/enablers/InspectorAsserting;Lorg/scalactic/Prettifier;Lorg/scalactic/source/Position;)Ljava/lang/Object;
  #139 = Utf8               <E:Ljava/lang/Object;C:Ljava/lang/Object;ASSERTION:Ljava/lang/Object;>(IITC;Lscala/Function1<TE;TASSERTION;>;Lorg/scalatest/enablers/Collecting<TE;TC;>;Lorg/scalatest/enablers/InspectorAsserting<TASSERTION;>;Lorg/scalactic/Prettifier;Lorg/scalactic/source/Position;)Ljava/lang/Object;
  #140 = Utf8               (IILscala/collection/Iterable;Ljava/lang/Object;ZLorg/scalactic/Prettifier;Lorg/scalactic/source/Position;Lscala/Function1;)Ljava/lang/Object;
  #141 = NameAndType        #135:#140     // forBetween:(IILscala/collection/Iterable;Ljava/lang/Object;ZLorg/scalactic/Prettifier;Lorg/scalactic/source/Position;Lscala/Function1;)Ljava/lang/Object;
  #142 = InterfaceMethodref #37.#141      // org/scalatest/enablers/InspectorAsserting.forBetween:(IILscala/collection/Iterable;Ljava/lang/Object;ZLorg/scalactic/Prettifier;Lorg/scalactic/source/Position;Lscala/Function1;)Ljava/lang/Object;
  #143 = Utf8               (Lorg/scalatest/Inspectors;IILscala/collection/Map;Lscala/Function1;Lorg/scalatest/enablers/Collecting;Lorg/scalatest/enablers/InspectorAsserting;Lorg/scalactic/Prettifier;Lorg/scalactic/source/Position;)Ljava/lang/Object;
  #144 = Utf8               (IILscala/collection/Map;Lscala/Function1;Lorg/scalatest/enablers/Collecting;Lorg/scalatest/enablers/InspectorAsserting;Lorg/scalactic/Prettifier;Lorg/scalactic/source/Position;)Ljava/lang/Object;
  #145 = NameAndType        #135:#144     // forBetween:(IILscala/collection/Map;Lscala/Function1;Lorg/scalatest/enablers/Collecting;Lorg/scalatest/enablers/InspectorAsserting;Lorg/scalactic/Prettifier;Lorg/scalactic/source/Position;)Ljava/lang/Object;
  #146 = InterfaceMethodref #2.#145       // org/scalatest/Inspectors.forBetween:(IILscala/collection/Map;Lscala/Function1;Lorg/scalatest/enablers/Collecting;Lorg/scalatest/enablers/InspectorAsserting;Lorg/scalactic/Prettifier;Lorg/scalactic/source/Position;)Ljava/lang/Object;
  #147 = Utf8               <K:Ljava/lang/Object;V:Ljava/lang/Object;MAP::Lscala/collection/Map<Ljava/lang/Object;Ljava/lang/Object;>;ASSERTION:Ljava/lang/Object;>(IITMAP;Lscala/Function1<Lscala/Tuple2<TK;TV;>;TASSERTION;>;Lorg/scalatest/enablers/Collecting<Lscala/Tuple2<TK;TV;>;Lscala/collection/Iterable<Lscala/Tuple2<TK;TV;>;>;>;Lorg/scalatest/enablers/InspectorAsserting<TASSERTION;>;Lorg/scalactic/Prettifier;Lorg/scalactic/source/Position;)Ljava/lang/Object;
  #148 = Utf8               (Lorg/scalatest/Inspectors;IILjava/util/Map;Lscala/Function1;Lorg/scalatest/enablers/Collecting;Lorg/scalatest/enablers/InspectorAsserting;Lorg/scalactic/Prettifier;Lorg/scalactic/source/Position;)Ljava/lang/Object;
  #149 = Utf8               (IILjava/util/Map;Lscala/Function1;Lorg/scalatest/enablers/Collecting;Lorg/scalatest/enablers/InspectorAsserting;Lorg/scalactic/Prettifier;Lorg/scalactic/source/Position;)Ljava/lang/Object;
  #150 = NameAndType        #135:#149     // forBetween:(IILjava/util/Map;Lscala/Function1;Lorg/scalatest/enablers/Collecting;Lorg/scalatest/enablers/InspectorAsserting;Lorg/scalactic/Prettifier;Lorg/scalactic/source/Position;)Ljava/lang/Object;
  #151 = InterfaceMethodref #2.#150       // org/scalatest/Inspectors.forBetween:(IILjava/util/Map;Lscala/Function1;Lorg/scalatest/enablers/Collecting;Lorg/scalatest/enablers/InspectorAsserting;Lorg/scalactic/Prettifier;Lorg/scalactic/source/Position;)Ljava/lang/Object;
  #152 = Utf8               <K:Ljava/lang/Object;V:Ljava/lang/Object;JMAP::Ljava/util/Map<Ljava/lang/Object;Ljava/lang/Object;>;ASSERTION:Ljava/lang/Object;>(IITJMAP;Lscala/Function1<Lorg/scalatest/Entry<TK;TV;>;TASSERTION;>;Lorg/scalatest/enablers/Collecting<Lorg/scalatest/Entry<TK;TV;>;TJMAP;>;Lorg/scalatest/enablers/InspectorAsserting<TASSERTION;>;Lorg/scalactic/Prettifier;Lorg/scalactic/source/Position;)Ljava/lang/Object;
  #153 = Utf8               (Lorg/scalatest/Inspectors;IILjava/lang/String;Lscala/Function1;Lorg/scalatest/enablers/Collecting;Lorg/scalatest/enablers/InspectorAsserting;Lorg/scalactic/Prettifier;Lorg/scalactic/source/Position;)Ljava/lang/Object;
  #154 = Utf8               (IILjava/lang/String;Lscala/Function1;Lorg/scalatest/enablers/Collecting;Lorg/scalatest/enablers/InspectorAsserting;Lorg/scalactic/Prettifier;Lorg/scalactic/source/Position;)Ljava/lang/Object;
  #155 = NameAndType        #135:#154     // forBetween:(IILjava/lang/String;Lscala/Function1;Lorg/scalatest/enablers/Collecting;Lorg/scalatest/enablers/InspectorAsserting;Lorg/scalactic/Prettifier;Lorg/scalactic/source/Position;)Ljava/lang/Object;
  #156 = InterfaceMethodref #2.#155       // org/scalatest/Inspectors.forBetween:(IILjava/lang/String;Lscala/Function1;Lorg/scalatest/enablers/Collecting;Lorg/scalatest/enablers/InspectorAsserting;Lorg/scalactic/Prettifier;Lorg/scalactic/source/Position;)Ljava/lang/Object;
  #157 = Utf8               <ASSERTION:Ljava/lang/Object;>(IILjava/lang/String;Lscala/Function1<Ljava/lang/Object;TASSERTION;>;Lorg/scalatest/enablers/Collecting<Ljava/lang/Object;Ljava/lang/String;>;Lorg/scalatest/enablers/InspectorAsserting<TASSERTION;>;Lorg/scalactic/Prettifier;Lorg/scalactic/source/Position;)Ljava/lang/Object;
  #158 = Utf8               forEvery$
  #159 = Utf8               forEvery
  #160 = NameAndType        #159:#19      // forEvery:(Ljava/lang/Object;Lscala/Function1;Lorg/scalatest/enablers/Collecting;Lorg/scalatest/enablers/InspectorAsserting;Lorg/scalactic/Prettifier;Lorg/scalactic/source/Position;)Ljava/lang/Object;
  #161 = InterfaceMethodref #2.#160       // org/scalatest/Inspectors.forEvery:(Ljava/lang/Object;Lscala/Function1;Lorg/scalatest/enablers/Collecting;Lorg/scalatest/enablers/InspectorAsserting;Lorg/scalactic/Prettifier;Lorg/scalactic/source/Position;)Ljava/lang/Object;
  #162 = NameAndType        #159:#38      // forEvery:(Lscala/collection/Iterable;Ljava/lang/Object;ZLorg/scalactic/Prettifier;Lorg/scalactic/source/Position;Lscala/Function1;)Ljava/lang/Object;
  #163 = InterfaceMethodref #37.#162      // org/scalatest/enablers/InspectorAsserting.forEvery:(Lscala/collection/Iterable;Ljava/lang/Object;ZLorg/scalactic/Prettifier;Lorg/scalactic/source/Position;Lscala/Function1;)Ljava/lang/Object;
  #164 = NameAndType        #159:#43      // forEvery:(Lscala/collection/Map;Lscala/Function1;Lorg/scalatest/enablers/Collecting;Lorg/scalatest/enablers/InspectorAsserting;Lorg/scalactic/Prettifier;Lorg/scalactic/source/Position;)Ljava/lang/Object;
  #165 = InterfaceMethodref #2.#164       // org/scalatest/Inspectors.forEvery:(Lscala/collection/Map;Lscala/Function1;Lorg/scalatest/enablers/Collecting;Lorg/scalatest/enablers/InspectorAsserting;Lorg/scalactic/Prettifier;Lorg/scalactic/source/Position;)Ljava/lang/Object;
  #166 = NameAndType        #159:#49      // forEvery:(Ljava/util/Map;Lscala/Function1;Lorg/scalatest/enablers/Collecting;Lorg/scalatest/enablers/InspectorAsserting;Lorg/scalactic/Prettifier;Lorg/scalactic/source/Position;)Ljava/lang/Object;
  #167 = InterfaceMethodref #2.#166       // org/scalatest/Inspectors.forEvery:(Ljava/util/Map;Lscala/Function1;Lorg/scalatest/enablers/Collecting;Lorg/scalatest/enablers/InspectorAsserting;Lorg/scalactic/Prettifier;Lorg/scalactic/source/Position;)Ljava/lang/Object;
  #168 = NameAndType        #159:#55      // forEvery:(Ljava/lang/String;Lscala/Function1;Lorg/scalatest/enablers/Collecting;Lorg/scalatest/enablers/InspectorAsserting;Lorg/scalactic/Prettifier;Lorg/scalactic/source/Position;)Ljava/lang/Object;
  #169 = InterfaceMethodref #2.#168       // org/scalatest/Inspectors.forEvery:(Ljava/lang/String;Lscala/Function1;Lorg/scalatest/enablers/Collecting;Lorg/scalatest/enablers/InspectorAsserting;Lorg/scalactic/Prettifier;Lorg/scalactic/source/Position;)Ljava/lang/Object;
  #170 = Utf8               $init$
  #171 = Utf8               (Lorg/scalatest/Inspectors;)V
  #172 = Utf8               Code
  #173 = Utf8               LineNumberTable
  #174 = Utf8               LocalVariableTable
  #175 = Utf8               MethodParameters
  #176 = Utf8               Signature
  #177 = Utf8               SourceFile
  #178 = Utf8               RuntimeVisibleAnnotations
  #179 = Utf8               ScalaInlineInfo
  #180 = Utf8               ScalaSig
{
  public static java.lang.Object forAll$(org.scalatest.Inspectors, java.lang.Object, scala.Function1, org.scalatest.enablers.Collecting, org.scalatest.enablers.InspectorAsserting, org.scalactic.Prettifier, org.scalactic.source.Position);
    descriptor: (Lorg/scalatest/Inspectors;Ljava/lang/Object;Lscala/Function1;Lorg/scalatest/enablers/Collecting;Lorg/scalatest/enablers/InspectorAsserting;Lorg/scalactic/Prettifier;Lorg/scalactic/source/Position;)Ljava/lang/Object;
    flags: (0x1009) ACC_PUBLIC, ACC_STATIC, ACC_SYNTHETIC
    Code:
      stack=7, locals=7, args_size=7
         0: aload_0
         1: aload_1
         2: aload_2
         3: aload_3
         4: aload         4
         6: aload         5
         8: aload         6
        10: invokespecial #21                 // InterfaceMethod forAll:(Ljava/lang/Object;Lscala/Function1;Lorg/scalatest/enablers/Collecting;Lorg/scalatest/enablers/InspectorAsserting;Lorg/scalactic/Prettifier;Lorg/scalactic/source/Position;)Ljava/lang/Object;
        13: areturn
      LineNumberTable:
        line 222: 0
      LocalVariableTable:
        Start  Length  Slot  Name   Signature
            0      14     0 $this   Lorg/scalatest/Inspectors;
            0      14     1    xs   Ljava/lang/Object;
            0      14     2   fun   Lscala/Function1;
            0      14     3 collecting   Lorg/scalatest/enablers/Collecting;
            0      14     4 asserting   Lorg/scalatest/enablers/InspectorAsserting;
            0      14     5 prettifier   Lorg/scalactic/Prettifier;
            0      14     6   pos   Lorg/scalactic/source/Position;
    MethodParameters:
      Name                           Flags
      $this                          final synthetic
      xs                             final
      fun                            final
      collecting                     final
      asserting                      final
      prettifier                     final
      pos                            final

  public default <E extends java.lang.Object, C extends java.lang.Object, ASSERTION extends java.lang.Object> java.lang.Object forAll(C, scala.Function1<E, ASSERTION>, org.scalatest.enablers.Collecting<E, C>, org.scalatest.enablers.InspectorAsserting<ASSERTION>, org.scalactic.Prettifier, org.scalactic.source.Position);
    descriptor: (Ljava/lang/Object;Lscala/Function1;Lorg/scalatest/enablers/Collecting;Lorg/scalatest/enablers/InspectorAsserting;Lorg/scalactic/Prettifier;Lorg/scalactic/source/Position;)Ljava/lang/Object;
    flags: (0x0001) ACC_PUBLIC
    Code:
      stack=7, locals=7, args_size=7
         0: aload         4
         2: aload_3
         3: aload_1
         4: invokeinterface #35,  2           // InterfaceMethod org/scalatest/enablers/Collecting.genTraversableFrom:(Ljava/lang/Object;)Lscala/collection/Iterable;
         9: aload_1
        10: iconst_0
        11: aload         5
        13: aload         6
        15: aload_2
        16: invokeinterface #40,  7           // InterfaceMethod org/scalatest/enablers/InspectorAsserting.forAll:(Lscala/collection/Iterable;Ljava/lang/Object;ZLorg/scalactic/Prettifier;Lorg/scalactic/source/Position;Lscala/Function1;)Ljava/lang/Object;
        21: areturn
      LineNumberTable:
        line 223: 0
      LocalVariableTable:
        Start  Length  Slot  Name   Signature
            0      22     0  this   Lorg/scalatest/Inspectors;
            0      22     1    xs   Ljava/lang/Object;
            0      22     2   fun   Lscala/Function1;
            0      22     3 collecting   Lorg/scalatest/enablers/Collecting;
            0      22     4 asserting   Lorg/scalatest/enablers/InspectorAsserting;
            0      22     5 prettifier   Lorg/scalactic/Prettifier;
            0      22     6   pos   Lorg/scalactic/source/Position;
    Signature: #29                          // <E:Ljava/lang/Object;C:Ljava/lang/Object;ASSERTION:Ljava/lang/Object;>(TC;Lscala/Function1<TE;TASSERTION;>;Lorg/scalatest/enablers/Collecting<TE;TC;>;Lorg/scalatest/enablers/InspectorAsserting<TASSERTION;>;Lorg/scalactic/Prettifier;Lorg/scalactic/source/Position;)Ljava/lang/Object;
    MethodParameters:
      Name                           Flags
      xs                             final
      fun                            final
      collecting                     final
      asserting                      final
      prettifier                     final
      pos                            final

  public static java.lang.Object forAll$(org.scalatest.Inspectors, scala.collection.Map, scala.Function1, org.scalatest.enablers.Collecting, org.scalatest.enablers.InspectorAsserting, org.scalactic.Prettifier, org.scalactic.source.Position);
    descriptor: (Lorg/scalatest/Inspectors;Lscala/collection/Map;Lscala/Function1;Lorg/scalatest/enablers/Collecting;Lorg/scalatest/enablers/InspectorAsserting;Lorg/scalactic/Prettifier;Lorg/scalactic/source/Position;)Ljava/lang/Object;
    flags: (0x1009) ACC_PUBLIC, ACC_STATIC, ACC_SYNTHETIC
    Code:
      stack=7, locals=7, args_size=7
         0: aload_0
         1: aload_1
         2: aload_2
         3: aload_3
         4: aload         4
         6: aload         5
         8: aload         6
        10: invokespecial #45                 // InterfaceMethod forAll:(Lscala/collection/Map;Lscala/Function1;Lorg/scalatest/enablers/Collecting;Lorg/scalatest/enablers/InspectorAsserting;Lorg/scalactic/Prettifier;Lorg/scalactic/source/Position;)Ljava/lang/Object;
        13: areturn
      LineNumberTable:
        line 244: 0
      LocalVariableTable:
        Start  Length  Slot  Name   Signature
            0      14     0 $this   Lorg/scalatest/Inspectors;
            0      14     1    xs   Lscala/collection/Map;
            0      14     2   fun   Lscala/Function1;
            0      14     3 collecting   Lorg/scalatest/enablers/Collecting;
            0      14     4 asserting   Lorg/scalatest/enablers/InspectorAsserting;
            0      14     5 prettifier   Lorg/scalactic/Prettifier;
            0      14     6   pos   Lorg/scalactic/source/Position;
    MethodParameters:
      Name                           Flags
      $this                          final synthetic
      xs                             final
      fun                            final
      collecting                     final
      asserting                      final
      prettifier                     final
      pos                            final

  public default <K extends java.lang.Object, V extends java.lang.Object, MAP extends scala.collection.Map<java.lang.Object, java.lang.Object>, ASSERTION extends java.lang.Object> java.lang.Object forAll(MAP, scala.Function1<scala.Tuple2<K, V>, ASSERTION>, org.scalatest.enablers.Collecting<scala.Tuple2<K, V>, scala.collection.Iterable<scala.Tuple2<K, V>>>, org.scalatest.enablers.InspectorAsserting<ASSERTION>, org.scalactic.Prettifier, org.scalactic.source.Position);
    descriptor: (Lscala/collection/Map;Lscala/Function1;Lorg/scalatest/enablers/Collecting;Lorg/scalatest/enablers/InspectorAsserting;Lorg/scalactic/Prettifier;Lorg/scalactic/source/Position;)Ljava/lang/Object;
    flags: (0x0001) ACC_PUBLIC
    Code:
      stack=7, locals=7, args_size=7
         0: aload         4
         2: aload_3
         3: aload_1
         4: invokeinterface #35,  2           // InterfaceMethod org/scalatest/enablers/Collecting.genTraversableFrom:(Ljava/lang/Object;)Lscala/collection/Iterable;
         9: aload_1
        10: iconst_0
        11: aload         5
        13: aload         6
        15: aload_2
        16: invokeinterface #40,  7           // InterfaceMethod org/scalatest/enablers/InspectorAsserting.forAll:(Lscala/collection/Iterable;Ljava/lang/Object;ZLorg/scalactic/Prettifier;Lorg/scalactic/source/Position;Lscala/Function1;)Ljava/lang/Object;
        21: areturn
      LineNumberTable:
        line 245: 0
      LocalVariableTable:
        Start  Length  Slot  Name   Signature
            0      22     0  this   Lorg/scalatest/Inspectors;
            0      22     1    xs   Lscala/collection/Map;
            0      22     2   fun   Lscala/Function1;
            0      22     3 collecting   Lorg/scalatest/enablers/Collecting;
            0      22     4 asserting   Lorg/scalatest/enablers/InspectorAsserting;
            0      22     5 prettifier   Lorg/scalactic/Prettifier;
            0      22     6   pos   Lorg/scalactic/source/Position;
    Signature: #47                          // <K:Ljava/lang/Object;V:Ljava/lang/Object;MAP::Lscala/collection/Map<Ljava/lang/Object;Ljava/lang/Object;>;ASSERTION:Ljava/lang/Object;>(TMAP;Lscala/Function1<Lscala/Tuple2<TK;TV;>;TASSERTION;>;Lorg/scalatest/enablers/Collecting<Lscala/Tuple2<TK;TV;>;Lscala/collection/Iterable<Lscala/Tuple2<TK;TV;>;>;>;Lorg/scalatest/enablers/InspectorAsserting<TASSERTION;>;Lorg/scalactic/Prettifier;Lorg/scalactic/source/Position;)Ljava/lang/Object;
    MethodParameters:
      Name                           Flags
      xs                             final
      fun                            final
      collecting                     final
      asserting                      final
      prettifier                     final
      pos                            final

  public static java.lang.Object forAll$(org.scalatest.Inspectors, java.util.Map, scala.Function1, org.scalatest.enablers.Collecting, org.scalatest.enablers.InspectorAsserting, org.scalactic.Prettifier, org.scalactic.source.Position);
    descriptor: (Lorg/scalatest/Inspectors;Ljava/util/Map;Lscala/Function1;Lorg/scalatest/enablers/Collecting;Lorg/scalatest/enablers/InspectorAsserting;Lorg/scalactic/Prettifier;Lorg/scalactic/source/Position;)Ljava/lang/Object;
    flags: (0x1009) ACC_PUBLIC, ACC_STATIC, ACC_SYNTHETIC
    Code:
      stack=7, locals=7, args_size=7
         0: aload_0
         1: aload_1
         2: aload_2
         3: aload_3
         4: aload         4
         6: aload         5
         8: aload         6
        10: invokespecial #51                 // InterfaceMethod forAll:(Ljava/util/Map;Lscala/Function1;Lorg/scalatest/enablers/Collecting;Lorg/scalatest/enablers/InspectorAsserting;Lorg/scalactic/Prettifier;Lorg/scalactic/source/Position;)Ljava/lang/Object;
        13: areturn
      LineNumberTable:
        line 267: 0
      LocalVariableTable:
        Start  Length  Slot  Name   Signature
            0      14     0 $this   Lorg/scalatest/Inspectors;
            0      14     1    xs   Ljava/util/Map;
            0      14     2   fun   Lscala/Function1;
            0      14     3 collecting   Lorg/scalatest/enablers/Collecting;
            0      14     4 asserting   Lorg/scalatest/enablers/InspectorAsserting;
            0      14     5 prettifier   Lorg/scalactic/Prettifier;
            0      14     6   pos   Lorg/scalactic/source/Position;
    MethodParameters:
      Name                           Flags
      $this                          final synthetic
      xs                             final
      fun                            final
      collecting                     final
      asserting                      final
      prettifier                     final
      pos                            final

  public default <K extends java.lang.Object, V extends java.lang.Object, JMAP extends java.util.Map<java.lang.Object, java.lang.Object>, ASSERTION extends java.lang.Object> java.lang.Object forAll(JMAP, scala.Function1<org.scalatest.Entry<K, V>, ASSERTION>, org.scalatest.enablers.Collecting<org.scalatest.Entry<K, V>, JMAP>, org.scalatest.enablers.InspectorAsserting<ASSERTION>, org.scalactic.Prettifier, org.scalactic.source.Position);
    descriptor: (Ljava/util/Map;Lscala/Function1;Lorg/scalatest/enablers/Collecting;Lorg/scalatest/enablers/InspectorAsserting;Lorg/scalactic/Prettifier;Lorg/scalactic/source/Position;)Ljava/lang/Object;
    flags: (0x0001) ACC_PUBLIC
    Code:
      stack=7, locals=7, args_size=7
         0: aload         4
         2: aload_3
         3: aload_1
         4: invokeinterface #35,  2           // InterfaceMethod org/scalatest/enablers/Collecting.genTraversableFrom:(Ljava/lang/Object;)Lscala/collection/Iterable;
         9: aload_1
        10: iconst_0
        11: aload         5
        13: aload         6
        15: aload_2
        16: invokeinterface #40,  7           // InterfaceMethod org/scalatest/enablers/InspectorAsserting.forAll:(Lscala/collection/Iterable;Ljava/lang/Object;ZLorg/scalactic/Prettifier;Lorg/scalactic/source/Position;Lscala/Function1;)Ljava/lang/Object;
        21: areturn
      LineNumberTable:
        line 268: 0
      LocalVariableTable:
        Start  Length  Slot  Name   Signature
            0      22     0  this   Lorg/scalatest/Inspectors;
            0      22     1    xs   Ljava/util/Map;
            0      22     2   fun   Lscala/Function1;
            0      22     3 collecting   Lorg/scalatest/enablers/Collecting;
            0      22     4 asserting   Lorg/scalatest/enablers/InspectorAsserting;
            0      22     5 prettifier   Lorg/scalactic/Prettifier;
            0      22     6   pos   Lorg/scalactic/source/Position;
    Signature: #53                          // <K:Ljava/lang/Object;V:Ljava/lang/Object;JMAP::Ljava/util/Map<Ljava/lang/Object;Ljava/lang/Object;>;ASSERTION:Ljava/lang/Object;>(TJMAP;Lscala/Function1<Lorg/scalatest/Entry<TK;TV;>;TASSERTION;>;Lorg/scalatest/enablers/Collecting<Lorg/scalatest/Entry<TK;TV;>;TJMAP;>;Lorg/scalatest/enablers/InspectorAsserting<TASSERTION;>;Lorg/scalactic/Prettifier;Lorg/scalactic/source/Position;)Ljava/lang/Object;
    MethodParameters:
      Name                           Flags
      xs                             final
      fun                            final
      collecting                     final
      asserting                      final
      prettifier                     final
      pos                            final

  public static java.lang.Object forAll$(org.scalatest.Inspectors, java.lang.String, scala.Function1, org.scalatest.enablers.Collecting, org.scalatest.enablers.InspectorAsserting, org.scalactic.Prettifier, org.scalactic.source.Position);
    descriptor: (Lorg/scalatest/Inspectors;Ljava/lang/String;Lscala/Function1;Lorg/scalatest/enablers/Collecting;Lorg/scalatest/enablers/InspectorAsserting;Lorg/scalactic/Prettifier;Lorg/scalactic/source/Position;)Ljava/lang/Object;
    flags: (0x1009) ACC_PUBLIC, ACC_STATIC, ACC_SYNTHETIC
    Code:
      stack=7, locals=7, args_size=7
         0: aload_0
         1: aload_1
         2: aload_2
         3: aload_3
         4: aload         4
         6: aload         5
         8: aload         6
        10: invokespecial #57                 // InterfaceMethod forAll:(Ljava/lang/String;Lscala/Function1;Lorg/scalatest/enablers/Collecting;Lorg/scalatest/enablers/InspectorAsserting;Lorg/scalactic/Prettifier;Lorg/scalactic/source/Position;)Ljava/lang/Object;
        13: areturn
      LineNumberTable:
        line 287: 0
      LocalVariableTable:
        Start  Length  Slot  Name   Signature
            0      14     0 $this   Lorg/scalatest/Inspectors;
            0      14     1    xs   Ljava/lang/String;
            0      14     2   fun   Lscala/Function1;
            0      14     3 collecting   Lorg/scalatest/enablers/Collecting;
            0      14     4 asserting   Lorg/scalatest/enablers/InspectorAsserting;
            0      14     5 prettifier   Lorg/scalactic/Prettifier;
            0      14     6   pos   Lorg/scalactic/source/Position;
    MethodParameters:
      Name                           Flags
      $this                          final synthetic
      xs                             final
      fun                            final
      collecting                     final
      asserting                      final
      prettifier                     final
      pos                            final

  public default <ASSERTION extends java.lang.Object> java.lang.Object forAll(java.lang.String, scala.Function1<java.lang.Object, ASSERTION>, org.scalatest.enablers.Collecting<java.lang.Object, java.lang.String>, org.scalatest.enablers.InspectorAsserting<ASSERTION>, org.scalactic.Prettifier, org.scalactic.source.Position);
    descriptor: (Ljava/lang/String;Lscala/Function1;Lorg/scalatest/enablers/Collecting;Lorg/scalatest/enablers/InspectorAsserting;Lorg/scalactic/Prettifier;Lorg/scalactic/source/Position;)Ljava/lang/Object;
    flags: (0x0001) ACC_PUBLIC
    Code:
      stack=7, locals=7, args_size=7
         0: aload         4
         2: aload_3
         3: aload_1
         4: invokeinterface #35,  2           // InterfaceMethod org/scalatest/enablers/Collecting.genTraversableFrom:(Ljava/lang/Object;)Lscala/collection/Iterable;
         9: aload_1
        10: iconst_0
        11: aload         5
        13: aload         6
        15: aload_2
        16: invokeinterface #40,  7           // InterfaceMethod org/scalatest/enablers/InspectorAsserting.forAll:(Lscala/collection/Iterable;Ljava/lang/Object;ZLorg/scalactic/Prettifier;Lorg/scalactic/source/Position;Lscala/Function1;)Ljava/lang/Object;
        21: areturn
      LineNumberTable:
        line 288: 0
      LocalVariableTable:
        Start  Length  Slot  Name   Signature
            0      22     0  this   Lorg/scalatest/Inspectors;
            0      22     1    xs   Ljava/lang/String;
            0      22     2   fun   Lscala/Function1;
            0      22     3 collecting   Lorg/scalatest/enablers/Collecting;
            0      22     4 asserting   Lorg/scalatest/enablers/InspectorAsserting;
            0      22     5 prettifier   Lorg/scalactic/Prettifier;
            0      22     6   pos   Lorg/scalactic/source/Position;
    Signature: #59                          // <ASSERTION:Ljava/lang/Object;>(Ljava/lang/String;Lscala/Function1<Ljava/lang/Object;TASSERTION;>;Lorg/scalatest/enablers/Collecting<Ljava/lang/Object;Ljava/lang/String;>;Lorg/scalatest/enablers/InspectorAsserting<TASSERTION;>;Lorg/scalactic/Prettifier;Lorg/scalactic/source/Position;)Ljava/lang/Object;
    MethodParameters:
      Name                           Flags
      xs                             final
      fun                            final
      collecting                     final
      asserting                      final
      prettifier                     final
      pos                            final

  public static java.lang.Object forAtLeast$(org.scalatest.Inspectors, int, java.lang.Object, scala.Function1, org.scalatest.enablers.Collecting, org.scalatest.enablers.InspectorAsserting, org.scalactic.Prettifier, org.scalactic.source.Position);
    descriptor: (Lorg/scalatest/Inspectors;ILjava/lang/Object;Lscala/Function1;Lorg/scalatest/enablers/Collecting;Lorg/scalatest/enablers/InspectorAsserting;Lorg/scalactic/Prettifier;Lorg/scalactic/source/Position;)Ljava/lang/Object;
    flags: (0x1009) ACC_PUBLIC, ACC_STATIC, ACC_SYNTHETIC
    Code:
      stack=8, locals=8, args_size=8
         0: aload_0
         1: iload_1
         2: aload_2
         3: aload_3
         4: aload         4
         6: aload         5
         8: aload         6
        10: aload         7
        12: invokespecial #66                 // InterfaceMethod forAtLeast:(ILjava/lang/Object;Lscala/Function1;Lorg/scalatest/enablers/Collecting;Lorg/scalatest/enablers/InspectorAsserting;Lorg/scalactic/Prettifier;Lorg/scalactic/source/Position;)Ljava/lang/Object;
        15: areturn
      LineNumberTable:
        line 302: 0
      LocalVariableTable:
        Start  Length  Slot  Name   Signature
            0      16     0 $this   Lorg/scalatest/Inspectors;
            0      16     1   min   I
            0      16     2    xs   Ljava/lang/Object;
            0      16     3   fun   Lscala/Function1;
            0      16     4 collecting   Lorg/scalatest/enablers/Collecting;
            0      16     5 asserting   Lorg/scalatest/enablers/InspectorAsserting;
            0      16     6 prettifier   Lorg/scalactic/Prettifier;
            0      16     7   pos   Lorg/scalactic/source/Position;
    MethodParameters:
      Name                           Flags
      $this                          final synthetic
      min                            final
      xs                             final
      fun                            final
      collecting                     final
      asserting                      final
      prettifier                     final
      pos                            final

  public default <E extends java.lang.Object, C extends java.lang.Object, ASSERTION extends java.lang.Object> java.lang.Object forAtLeast(int, C, scala.Function1<E, ASSERTION>, org.scalatest.enablers.Collecting<E, C>, org.scalatest.enablers.InspectorAsserting<ASSERTION>, org.scalactic.Prettifier, org.scalactic.source.Position);
    descriptor: (ILjava/lang/Object;Lscala/Function1;Lorg/scalatest/enablers/Collecting;Lorg/scalatest/enablers/InspectorAsserting;Lorg/scalactic/Prettifier;Lorg/scalactic/source/Position;)Ljava/lang/Object;
    flags: (0x0001) ACC_PUBLIC
    Code:
      stack=8, locals=8, args_size=8
         0: aload         5
         2: iload_1
         3: aload         4
         5: aload_2
         6: invokeinterface #35,  2           // InterfaceMethod org/scalatest/enablers/Collecting.genTraversableFrom:(Ljava/lang/Object;)Lscala/collection/Iterable;
        11: aload_2
        12: iconst_0
        13: aload         6
        15: aload         7
        17: aload_3
        18: invokeinterface #71,  8           // InterfaceMethod org/scalatest/enablers/InspectorAsserting.forAtLeast:(ILscala/collection/Iterable;Ljava/lang/Object;ZLorg/scalactic/Prettifier;Lorg/scalactic/source/Position;Lscala/Function1;)Ljava/lang/Object;
        23: areturn
      LineNumberTable:
        line 303: 0
      LocalVariableTable:
        Start  Length  Slot  Name   Signature
            0      24     0  this   Lorg/scalatest/Inspectors;
            0      24     1   min   I
            0      24     2    xs   Ljava/lang/Object;
            0      24     3   fun   Lscala/Function1;
            0      24     4 collecting   Lorg/scalatest/enablers/Collecting;
            0      24     5 asserting   Lorg/scalatest/enablers/InspectorAsserting;
            0      24     6 prettifier   Lorg/scalactic/Prettifier;
            0      24     7   pos   Lorg/scalactic/source/Position;
    Signature: #68                          // <E:Ljava/lang/Object;C:Ljava/lang/Object;ASSERTION:Ljava/lang/Object;>(ITC;Lscala/Function1<TE;TASSERTION;>;Lorg/scalatest/enablers/Collecting<TE;TC;>;Lorg/scalatest/enablers/InspectorAsserting<TASSERTION;>;Lorg/scalactic/Prettifier;Lorg/scalactic/source/Position;)Ljava/lang/Object;
    MethodParameters:
      Name                           Flags
      min                            final
      xs                             final
      fun                            final
      collecting                     final
      asserting                      final
      prettifier                     final
      pos                            final

  public static java.lang.Object forAtLeast$(org.scalatest.Inspectors, int, scala.collection.Map, scala.Function1, org.scalatest.enablers.Collecting, org.scalatest.enablers.InspectorAsserting, org.scalactic.Prettifier, org.scalactic.source.Position);
    descriptor: (Lorg/scalatest/Inspectors;ILscala/collection/Map;Lscala/Function1;Lorg/scalatest/enablers/Collecting;Lorg/scalatest/enablers/InspectorAsserting;Lorg/scalactic/Prettifier;Lorg/scalactic/source/Position;)Ljava/lang/Object;
    flags: (0x1009) ACC_PUBLIC, ACC_STATIC, ACC_SYNTHETIC
    Code:
      stack=8, locals=8, args_size=8
         0: aload_0
         1: iload_1
         2: aload_2
         3: aload_3
         4: aload         4
         6: aload         5
         8: aload         6
        10: aload         7
        12: invokespecial #75                 // InterfaceMethod forAtLeast:(ILscala/collection/Map;Lscala/Function1;Lorg/scalatest/enablers/Collecting;Lorg/scalatest/enablers/InspectorAsserting;Lorg/scalactic/Prettifier;Lorg/scalactic/source/Position;)Ljava/lang/Object;
        15: areturn
      LineNumberTable:
        line 318: 0
      LocalVariableTable:
        Start  Length  Slot  Name   Signature
            0      16     0 $this   Lorg/scalatest/Inspectors;
            0      16     1   min   I
            0      16     2    xs   Lscala/collection/Map;
            0      16     3   fun   Lscala/Function1;
            0      16     4 collecting   Lorg/scalatest/enablers/Collecting;
            0      16     5 asserting   Lorg/scalatest/enablers/InspectorAsserting;
            0      16     6 prettifier   Lorg/scalactic/Prettifier;
            0      16     7   pos   Lorg/scalactic/source/Position;
    MethodParameters:
      Name                           Flags
      $this                          final synthetic
      min                            final
      xs                             final
      fun                            final
      collecting                     final
      asserting                      final
      prettifier                     final
      pos                            final

  public default <K extends java.lang.Object, V extends java.lang.Object, MAP extends scala.collection.Map<java.lang.Object, java.lang.Object>, ASSERTION extends java.lang.Object> java.lang.Object forAtLeast(int, MAP, scala.Function1<scala.Tuple2<K, V>, ASSERTION>, org.scalatest.enablers.Collecting<scala.Tuple2<K, V>, scala.collection.Iterable<scala.Tuple2<K, V>>>, org.scalatest.enablers.InspectorAsserting<ASSERTION>, org.scalactic.Prettifier, org.scalactic.source.Position);
    descriptor: (ILscala/collection/Map;Lscala/Function1;Lorg/scalatest/enablers/Collecting;Lorg/scalatest/enablers/InspectorAsserting;Lorg/scalactic/Prettifier;Lorg/scalactic/source/Position;)Ljava/lang/Object;
    flags: (0x0001) ACC_PUBLIC
    Code:
      stack=8, locals=8, args_size=8
         0: aload         5
         2: iload_1
         3: aload         4
         5: aload_2
         6: invokeinterface #35,  2           // InterfaceMethod org/scalatest/enablers/Collecting.genTraversableFrom:(Ljava/lang/Object;)Lscala/collection/Iterable;
        11: aload_2
        12: iconst_0
        13: aload         6
        15: aload         7
        17: aload_3
        18: invokeinterface #71,  8           // InterfaceMethod org/scalatest/enablers/InspectorAsserting.forAtLeast:(ILscala/collection/Iterable;Ljava/lang/Object;ZLorg/scalactic/Prettifier;Lorg/scalactic/source/Position;Lscala/Function1;)Ljava/lang/Object;
        23: areturn
      LineNumberTable:
        line 319: 0
      LocalVariableTable:
        Start  Length  Slot  Name   Signature
            0      24     0  this   Lorg/scalatest/Inspectors;
            0      24     1   min   I
            0      24     2    xs   Lscala/collection/Map;
            0      24     3   fun   Lscala/Function1;
            0      24     4 collecting   Lorg/scalatest/enablers/Collecting;
            0      24     5 asserting   Lorg/scalatest/enablers/InspectorAsserting;
            0      24     6 prettifier   Lorg/scalactic/Prettifier;
            0      24     7   pos   Lorg/scalactic/source/Position;
    Signature: #76                          // <K:Ljava/lang/Object;V:Ljava/lang/Object;MAP::Lscala/collection/Map<Ljava/lang/Object;Ljava/lang/Object;>;ASSERTION:Ljava/lang/Object;>(ITMAP;Lscala/Function1<Lscala/Tuple2<TK;TV;>;TASSERTION;>;Lorg/scalatest/enablers/Collecting<Lscala/Tuple2<TK;TV;>;Lscala/collection/Iterable<Lscala/Tuple2<TK;TV;>;>;>;Lorg/scalatest/enablers/InspectorAsserting<TASSERTION;>;Lorg/scalactic/Prettifier;Lorg/scalactic/source/Position;)Ljava/lang/Object;
    MethodParameters:
      Name                           Flags
      min                            final
      xs                             final
      fun                            final
      collecting                     final
      asserting                      final
      prettifier                     final
      pos                            final

  public static java.lang.Object forAtLeast$(org.scalatest.Inspectors, int, java.util.Map, scala.Function1, org.scalatest.enablers.Collecting, org.scalatest.enablers.InspectorAsserting, org.scalactic.Prettifier, org.scalactic.source.Position);
    descriptor: (Lorg/scalatest/Inspectors;ILjava/util/Map;Lscala/Function1;Lorg/scalatest/enablers/Collecting;Lorg/scalatest/enablers/InspectorAsserting;Lorg/scalactic/Prettifier;Lorg/scalactic/source/Position;)Ljava/lang/Object;
    flags: (0x1009) ACC_PUBLIC, ACC_STATIC, ACC_SYNTHETIC
    Code:
      stack=8, locals=8, args_size=8
         0: aload_0
         1: iload_1
         2: aload_2
         3: aload_3
         4: aload         4
         6: aload         5
         8: aload         6
        10: aload         7
        12: invokespecial #80                 // InterfaceMethod forAtLeast:(ILjava/util/Map;Lscala/Function1;Lorg/scalatest/enablers/Collecting;Lorg/scalatest/enablers/InspectorAsserting;Lorg/scalactic/Prettifier;Lorg/scalactic/source/Position;)Ljava/lang/Object;
        15: areturn
      LineNumberTable:
        line 335: 0
      LocalVariableTable:
        Start  Length  Slot  Name   Signature
            0      16     0 $this   Lorg/scalatest/Inspectors;
            0      16     1   min   I
            0      16     2    xs   Ljava/util/Map;
            0      16     3   fun   Lscala/Function1;
            0      16     4 collecting   Lorg/scalatest/enablers/Collecting;
            0      16     5 asserting   Lorg/scalatest/enablers/InspectorAsserting;
            0      16     6 prettifier   Lorg/scalactic/Prettifier;
            0      16     7   pos   Lorg/scalactic/source/Position;
    MethodParameters:
      Name                           Flags
      $this                          final synthetic
      min                            final
      xs                             final
      fun                            final
      collecting                     final
      asserting                      final
      prettifier                     final
      pos                            final

  public default <K extends java.lang.Object, V extends java.lang.Object, JMAP extends java.util.Map<java.lang.Object, java.lang.Object>, ASSERTION extends java.lang.Object> java.lang.Object forAtLeast(int, JMAP, scala.Function1<org.scalatest.Entry<K, V>, ASSERTION>, org.scalatest.enablers.Collecting<org.scalatest.Entry<K, V>, JMAP>, org.scalatest.enablers.InspectorAsserting<ASSERTION>, org.scalactic.Prettifier, org.scalactic.source.Position);
    descriptor: (ILjava/util/Map;Lscala/Function1;Lorg/scalatest/enablers/Collecting;Lorg/scalatest/enablers/InspectorAsserting;Lorg/scalactic/Prettifier;Lorg/scalactic/source/Position;)Ljava/lang/Object;
    flags: (0x0001) ACC_PUBLIC
    Code:
      stack=8, locals=8, args_size=8
         0: aload         5
         2: iload_1
         3: aload         4
         5: aload_2
         6: invokeinterface #35,  2           // InterfaceMethod org/scalatest/enablers/Collecting.genTraversableFrom:(Ljava/lang/Object;)Lscala/collection/Iterable;
        11: aload_2
        12: iconst_0
        13: aload         6
        15: aload         7
        17: aload_3
        18: invokeinterface #71,  8           // InterfaceMethod org/scalatest/enablers/InspectorAsserting.forAtLeast:(ILscala/collection/Iterable;Ljava/lang/Object;ZLorg/scalactic/Prettifier;Lorg/scalactic/source/Position;Lscala/Function1;)Ljava/lang/Object;
        23: areturn
      LineNumberTable:
        line 336: 0
      LocalVariableTable:
        Start  Length  Slot  Name   Signature
            0      24     0  this   Lorg/scalatest/Inspectors;
            0      24     1   min   I
            0      24     2    xs   Ljava/util/Map;
            0      24     3   fun   Lscala/Function1;
            0      24     4 collecting   Lorg/scalatest/enablers/Collecting;
            0      24     5 asserting   Lorg/scalatest/enablers/InspectorAsserting;
            0      24     6 prettifier   Lorg/scalactic/Prettifier;
            0      24     7   pos   Lorg/scalactic/source/Position;
    Signature: #81                          // <K:Ljava/lang/Object;V:Ljava/lang/Object;JMAP::Ljava/util/Map<Ljava/lang/Object;Ljava/lang/Object;>;ASSERTION:Ljava/lang/Object;>(ITJMAP;Lscala/Function1<Lorg/scalatest/Entry<TK;TV;>;TASSERTION;>;Lorg/scalatest/enablers/Collecting<Lorg/scalatest/Entry<TK;TV;>;TJMAP;>;Lorg/scalatest/enablers/InspectorAsserting<TASSERTION;>;Lorg/scalactic/Prettifier;Lorg/scalactic/source/Position;)Ljava/lang/Object;
    MethodParameters:
      Name                           Flags
      min                            final
      xs                             final
      fun                            final
      collecting                     final
      asserting                      final
      prettifier                     final
      pos                            final

  public static java.lang.Object forAtLeast$(org.scalatest.Inspectors, int, java.lang.String, scala.Function1, org.scalatest.enablers.Collecting, org.scalatest.enablers.InspectorAsserting, org.scalactic.Prettifier, org.scalactic.source.Position);
    descriptor: (Lorg/scalatest/Inspectors;ILjava/lang/String;Lscala/Function1;Lorg/scalatest/enablers/Collecting;Lorg/scalatest/enablers/InspectorAsserting;Lorg/scalactic/Prettifier;Lorg/scalactic/source/Position;)Ljava/lang/Object;
    flags: (0x1009) ACC_PUBLIC, ACC_STATIC, ACC_SYNTHETIC
    Code:
      stack=8, locals=8, args_size=8
         0: aload_0
         1: iload_1
         2: aload_2
         3: aload_3
         4: aload         4
         6: aload         5
         8: aload         6
        10: aload         7
        12: invokespecial #85                 // InterfaceMethod forAtLeast:(ILjava/lang/String;Lscala/Function1;Lorg/scalatest/enablers/Collecting;Lorg/scalatest/enablers/InspectorAsserting;Lorg/scalactic/Prettifier;Lorg/scalactic/source/Position;)Ljava/lang/Object;
        15: areturn
      LineNumberTable:
        line 349: 0
      LocalVariableTable:
        Start  Length  Slot  Name   Signature
            0      16     0 $this   Lorg/scalatest/Inspectors;
            0      16     1   min   I
            0      16     2    xs   Ljava/lang/String;
            0      16     3   fun   Lscala/Function1;
            0      16     4 collecting   Lorg/scalatest/enablers/Collecting;
            0      16     5 asserting   Lorg/scalatest/enablers/InspectorAsserting;
            0      16     6 prettifier   Lorg/scalactic/Prettifier;
            0      16     7   pos   Lorg/scalactic/source/Position;
    MethodParameters:
      Name                           Flags
      $this                          final synthetic
      min                            final
      xs                             final
      fun                            final
      collecting                     final
      asserting                      final
      prettifier                     final
      pos                            final

  public default <ASSERTION extends java.lang.Object> java.lang.Object forAtLeast(int, java.lang.String, scala.Function1<java.lang.Object, ASSERTION>, org.scalatest.enablers.Collecting<java.lang.Object, java.lang.String>, org.scalatest.enablers.InspectorAsserting<ASSERTION>, org.scalactic.Prettifier, org.scalactic.source.Position);
    descriptor: (ILjava/lang/String;Lscala/Function1;Lorg/scalatest/enablers/Collecting;Lorg/scalatest/enablers/InspectorAsserting;Lorg/scalactic/Prettifier;Lorg/scalactic/source/Position;)Ljava/lang/Object;
    flags: (0x0001) ACC_PUBLIC
    Code:
      stack=8, locals=8, args_size=8
         0: aload         5
         2: iload_1
         3: aload         4
         5: aload_2
         6: invokeinterface #35,  2           // InterfaceMethod org/scalatest/enablers/Collecting.genTraversableFrom:(Ljava/lang/Object;)Lscala/collection/Iterable;
        11: aload_2
        12: iconst_0
        13: aload         6
        15: aload         7
        17: aload_3
        18: invokeinterface #71,  8           // InterfaceMethod org/scalatest/enablers/InspectorAsserting.forAtLeast:(ILscala/collection/Iterable;Ljava/lang/Object;ZLorg/scalactic/Prettifier;Lorg/scalactic/source/Position;Lscala/Function1;)Ljava/lang/Object;
        23: areturn
      LineNumberTable:
        line 350: 0
      LocalVariableTable:
        Start  Length  Slot  Name   Signature
            0      24     0  this   Lorg/scalatest/Inspectors;
            0      24     1   min   I
            0      24     2    xs   Ljava/lang/String;
            0      24     3   fun   Lscala/Function1;
            0      24     4 collecting   Lorg/scalatest/enablers/Collecting;
            0      24     5 asserting   Lorg/scalatest/enablers/InspectorAsserting;
            0      24     6 prettifier   Lorg/scalactic/Prettifier;
            0      24     7   pos   Lorg/scalactic/source/Position;
    Signature: #86                          // <ASSERTION:Ljava/lang/Object;>(ILjava/lang/String;Lscala/Function1<Ljava/lang/Object;TASSERTION;>;Lorg/scalatest/enablers/Collecting<Ljava/lang/Object;Ljava/lang/String;>;Lorg/scalatest/enablers/InspectorAsserting<TASSERTION;>;Lorg/scalactic/Prettifier;Lorg/scalactic/source/Position;)Ljava/lang/Object;
    MethodParameters:
      Name                           Flags
      min                            final
      xs                             final
      fun                            final
      collecting                     final
      asserting                      final
      prettifier                     final
      pos                            final

  private <T extends java.lang.Object, R extends java.lang.Object> boolean shouldIncludeIndex(scala.collection.Iterable<T>);
    descriptor: (Lscala/collection/Iterable;)Z
    flags: (0x0002) ACC_PRIVATE
    Code:
      stack=1, locals=2, args_size=2
         0: aload_1
         1: instanceof    #91                 // class scala/collection/Seq
         4: ireturn
      LineNumberTable:
        line 353: 0
      LocalVariableTable:
        Start  Length  Slot  Name   Signature
            0       5     0  this   Lorg/scalatest/Inspectors;
            0       5     1    xs   Lscala/collection/Iterable;
    Signature: #89                          // <T:Ljava/lang/Object;R:Ljava/lang/Object;>(Lscala/collection/Iterable<TT;>;)Z
    MethodParameters:
      Name                           Flags
      xs                             final

  public static java.lang.Object forAtMost$(org.scalatest.Inspectors, int, java.lang.Object, scala.Function1, org.scalatest.enablers.Collecting, org.scalatest.enablers.InspectorAsserting, org.scalactic.Prettifier, org.scalactic.source.Position);
    descriptor: (Lorg/scalatest/Inspectors;ILjava/lang/Object;Lscala/Function1;Lorg/scalatest/enablers/Collecting;Lorg/scalatest/enablers/InspectorAsserting;Lorg/scalactic/Prettifier;Lorg/scalactic/source/Position;)Ljava/lang/Object;
    flags: (0x1009) ACC_PUBLIC, ACC_STATIC, ACC_SYNTHETIC
    Code:
      stack=8, locals=8, args_size=8
         0: aload_0
         1: iload_1
         2: aload_2
         3: aload_3
         4: aload         4
         6: aload         5
         8: aload         6
        10: aload         7
        12: invokespecial #97                 // InterfaceMethod forAtMost:(ILjava/lang/Object;Lscala/Function1;Lorg/scalatest/enablers/Collecting;Lorg/scalatest/enablers/InspectorAsserting;Lorg/scalactic/Prettifier;Lorg/scalactic/source/Position;)Ljava/lang/Object;
        15: areturn
      LineNumberTable:
        line 365: 0
      LocalVariableTable:
        Start  Length  Slot  Name   Signature
            0      16     0 $this   Lorg/scalatest/Inspectors;
            0      16     1   max   I
            0      16     2    xs   Ljava/lang/Object;
            0      16     3   fun   Lscala/Function1;
            0      16     4 collecting   Lorg/scalatest/enablers/Collecting;
            0      16     5 asserting   Lorg/scalatest/enablers/InspectorAsserting;
            0      16     6 prettifier   Lorg/scalactic/Prettifier;
            0      16     7   pos   Lorg/scalactic/source/Position;
    MethodParameters:
      Name                           Flags
      $this                          final synthetic
      max                            final
      xs                             final
      fun                            final
      collecting                     final
      asserting                      final
      prettifier                     final
      pos                            final

  public default <E extends java.lang.Object, C extends java.lang.Object, ASSERTION extends java.lang.Object> java.lang.Object forAtMost(int, C, scala.Function1<E, ASSERTION>, org.scalatest.enablers.Collecting<E, C>, org.scalatest.enablers.InspectorAsserting<ASSERTION>, org.scalactic.Prettifier, org.scalactic.source.Position);
    descriptor: (ILjava/lang/Object;Lscala/Function1;Lorg/scalatest/enablers/Collecting;Lorg/scalatest/enablers/InspectorAsserting;Lorg/scalactic/Prettifier;Lorg/scalactic/source/Position;)Ljava/lang/Object;
    flags: (0x0001) ACC_PUBLIC
    Code:
      stack=8, locals=8, args_size=8
         0: aload         5
         2: iload_1
         3: aload         4
         5: aload_2
         6: invokeinterface #35,  2           // InterfaceMethod org/scalatest/enablers/Collecting.genTraversableFrom:(Ljava/lang/Object;)Lscala/collection/Iterable;
        11: aload_2
        12: iconst_0
        13: aload         6
        15: aload         7
        17: aload_3
        18: invokeinterface #99,  8           // InterfaceMethod org/scalatest/enablers/InspectorAsserting.forAtMost:(ILscala/collection/Iterable;Ljava/lang/Object;ZLorg/scalactic/Prettifier;Lorg/scalactic/source/Position;Lscala/Function1;)Ljava/lang/Object;
        23: areturn
      LineNumberTable:
        line 366: 0
      LocalVariableTable:
        Start  Length  Slot  Name   Signature
            0      24     0  this   Lorg/scalatest/Inspectors;
            0      24     1   max   I
            0      24     2    xs   Ljava/lang/Object;
            0      24     3   fun   Lscala/Function1;
            0      24     4 collecting   Lorg/scalatest/enablers/Collecting;
            0      24     5 asserting   Lorg/scalatest/enablers/InspectorAsserting;
            0      24     6 prettifier   Lorg/scalactic/Prettifier;
            0      24     7   pos   Lorg/scalactic/source/Position;
    Signature: #68                          // <E:Ljava/lang/Object;C:Ljava/lang/Object;ASSERTION:Ljava/lang/Object;>(ITC;Lscala/Function1<TE;TASSERTION;>;Lorg/scalatest/enablers/Collecting<TE;TC;>;Lorg/scalatest/enablers/InspectorAsserting<TASSERTION;>;Lorg/scalactic/Prettifier;Lorg/scalactic/source/Position;)Ljava/lang/Object;
    MethodParameters:
      Name                           Flags
      max                            final
      xs                             final
      fun                            final
      collecting                     final
      asserting                      final
      prettifier                     final
      pos                            final

  public static java.lang.Object forAtMost$(org.scalatest.Inspectors, int, scala.collection.Map, scala.Function1, org.scalatest.enablers.Collecting, org.scalatest.enablers.InspectorAsserting, org.scalactic.Prettifier, org.scalactic.source.Position);
    descriptor: (Lorg/scalatest/Inspectors;ILscala/collection/Map;Lscala/Function1;Lorg/scalatest/enablers/Collecting;Lorg/scalatest/enablers/InspectorAsserting;Lorg/scalactic/Prettifier;Lorg/scalactic/source/Position;)Ljava/lang/Object;
    flags: (0x1009) ACC_PUBLIC, ACC_STATIC, ACC_SYNTHETIC
    Code:
      stack=8, locals=8, args_size=8
         0: aload_0
         1: iload_1
         2: aload_2
         3: aload_3
         4: aload         4
         6: aload         5
         8: aload         6
        10: aload         7
        12: invokespecial #101                // InterfaceMethod forAtMost:(ILscala/collection/Map;Lscala/Function1;Lorg/scalatest/enablers/Collecting;Lorg/scalatest/enablers/InspectorAsserting;Lorg/scalactic/Prettifier;Lorg/scalactic/source/Position;)Ljava/lang/Object;
        15: areturn
      LineNumberTable:
        line 380: 0
      LocalVariableTable:
        Start  Length  Slot  Name   Signature
            0      16     0 $this   Lorg/scalatest/Inspectors;
            0      16     1   max   I
            0      16     2    xs   Lscala/collection/Map;
            0      16     3   fun   Lscala/Function1;
            0      16     4 collecting   Lorg/scalatest/enablers/Collecting;
            0      16     5 asserting   Lorg/scalatest/enablers/InspectorAsserting;
            0      16     6 prettifier   Lorg/scalactic/Prettifier;
            0      16     7   pos   Lorg/scalactic/source/Position;
    MethodParameters:
      Name                           Flags
      $this                          final synthetic
      max                            final
      xs                             final
      fun                            final
      collecting                     final
      asserting                      final
      prettifier                     final
      pos                            final

  public default <K extends java.lang.Object, V extends java.lang.Object, MAP extends scala.collection.Map<java.lang.Object, java.lang.Object>, ASSERTION extends java.lang.Object> java.lang.Object forAtMost(int, MAP, scala.Function1<scala.Tuple2<K, V>, ASSERTION>, org.scalatest.enablers.Collecting<scala.Tuple2<K, V>, scala.collection.Iterable<scala.Tuple2<K, V>>>, org.scalatest.enablers.InspectorAsserting<ASSERTION>, org.scalactic.Prettifier, org.scalactic.source.Position);
    descriptor: (ILscala/collection/Map;Lscala/Function1;Lorg/scalatest/enablers/Collecting;Lorg/scalatest/enablers/InspectorAsserting;Lorg/scalactic/Prettifier;Lorg/scalactic/source/Position;)Ljava/lang/Object;
    flags: (0x0001) ACC_PUBLIC
    Code:
      stack=8, locals=8, args_size=8
         0: aload         5
         2: iload_1
         3: aload         4
         5: aload_2
         6: invokeinterface #35,  2           // InterfaceMethod org/scalatest/enablers/Collecting.genTraversableFrom:(Ljava/lang/Object;)Lscala/collection/Iterable;
        11: aload_2
        12: iconst_0
        13: aload         6
        15: aload         7
        17: aload_3
        18: invokeinterface #99,  8           // InterfaceMethod org/scalatest/enablers/InspectorAsserting.forAtMost:(ILscala/collection/Iterable;Ljava/lang/Object;ZLorg/scalactic/Prettifier;Lorg/scalactic/source/Position;Lscala/Function1;)Ljava/lang/Object;
        23: areturn
      LineNumberTable:
        line 381: 0
      LocalVariableTable:
        Start  Length  Slot  Name   Signature
            0      24     0  this   Lorg/scalatest/Inspectors;
            0      24     1   max   I
            0      24     2    xs   Lscala/collection/Map;
            0      24     3   fun   Lscala/Function1;
            0      24     4 collecting   Lorg/scalatest/enablers/Collecting;
            0      24     5 asserting   Lorg/scalatest/enablers/InspectorAsserting;
            0      24     6 prettifier   Lorg/scalactic/Prettifier;
            0      24     7   pos   Lorg/scalactic/source/Position;
    Signature: #76                          // <K:Ljava/lang/Object;V:Ljava/lang/Object;MAP::Lscala/collection/Map<Ljava/lang/Object;Ljava/lang/Object;>;ASSERTION:Ljava/lang/Object;>(ITMAP;Lscala/Function1<Lscala/Tuple2<TK;TV;>;TASSERTION;>;Lorg/scalatest/enablers/Collecting<Lscala/Tuple2<TK;TV;>;Lscala/collection/Iterable<Lscala/Tuple2<TK;TV;>;>;>;Lorg/scalatest/enablers/InspectorAsserting<TASSERTION;>;Lorg/scalactic/Prettifier;Lorg/scalactic/source/Position;)Ljava/lang/Object;
    MethodParameters:
      Name                           Flags
      max                            final
      xs                             final
      fun                            final
      collecting                     final
      asserting                      final
      prettifier                     final
      pos                            final

  public static java.lang.Object forAtMost$(org.scalatest.Inspectors, int, java.util.Map, scala.Function1, org.scalatest.enablers.Collecting, org.scalatest.enablers.InspectorAsserting, org.scalactic.Prettifier, org.scalactic.source.Position);
    descriptor: (Lorg/scalatest/Inspectors;ILjava/util/Map;Lscala/Function1;Lorg/scalatest/enablers/Collecting;Lorg/scalatest/enablers/InspectorAsserting;Lorg/scalactic/Prettifier;Lorg/scalactic/source/Position;)Ljava/lang/Object;
    flags: (0x1009) ACC_PUBLIC, ACC_STATIC, ACC_SYNTHETIC
    Code:
      stack=8, locals=8, args_size=8
         0: aload_0
         1: iload_1
         2: aload_2
         3: aload_3
         4: aload         4
         6: aload         5
         8: aload         6
        10: aload         7
        12: invokespecial #103                // InterfaceMethod forAtMost:(ILjava/util/Map;Lscala/Function1;Lorg/scalatest/enablers/Collecting;Lorg/scalatest/enablers/InspectorAsserting;Lorg/scalactic/Prettifier;Lorg/scalactic/source/Position;)Ljava/lang/Object;
        15: areturn
      LineNumberTable:
        line 396: 0
      LocalVariableTable:
        Start  Length  Slot  Name   Signature
            0      16     0 $this   Lorg/scalatest/Inspectors;
            0      16     1   max   I
            0      16     2    xs   Ljava/util/Map;
            0      16     3   fun   Lscala/Function1;
            0      16     4 collecting   Lorg/scalatest/enablers/Collecting;
            0      16     5 asserting   Lorg/scalatest/enablers/InspectorAsserting;
            0      16     6 prettifier   Lorg/scalactic/Prettifier;
            0      16     7   pos   Lorg/scalactic/source/Position;
    MethodParameters:
      Name                           Flags
      $this                          final synthetic
      max                            final
      xs                             final
      fun                            final
      collecting                     final
      asserting                      final
      prettifier                     final
      pos                            final

  public default <K extends java.lang.Object, V extends java.lang.Object, JMAP extends java.util.Map<java.lang.Object, java.lang.Object>, ASSERTION extends java.lang.Object> java.lang.Object forAtMost(int, JMAP, scala.Function1<org.scalatest.Entry<K, V>, ASSERTION>, org.scalatest.enablers.Collecting<org.scalatest.Entry<K, V>, JMAP>, org.scalatest.enablers.InspectorAsserting<ASSERTION>, org.scalactic.Prettifier, org.scalactic.source.Position);
    descriptor: (ILjava/util/Map;Lscala/Function1;Lorg/scalatest/enablers/Collecting;Lorg/scalatest/enablers/InspectorAsserting;Lorg/scalactic/Prettifier;Lorg/scalactic/source/Position;)Ljava/lang/Object;
    flags: (0x0001) ACC_PUBLIC
    Code:
      stack=8, locals=8, args_size=8
         0: aload         5
         2: iload_1
         3: aload         4
         5: aload_2
         6: invokeinterface #35,  2           // InterfaceMethod org/scalatest/enablers/Collecting.genTraversableFrom:(Ljava/lang/Object;)Lscala/collection/Iterable;
        11: aload_2
        12: iconst_0
        13: aload         6
        15: aload         7
        17: aload_3
        18: invokeinterface #99,  8           // InterfaceMethod org/scalatest/enablers/InspectorAsserting.forAtMost:(ILscala/collection/Iterable;Ljava/lang/Object;ZLorg/scalactic/Prettifier;Lorg/scalactic/source/Position;Lscala/Function1;)Ljava/lang/Object;
        23: areturn
      LineNumberTable:
        line 397: 0
      LocalVariableTable:
        Start  Length  Slot  Name   Signature
            0      24     0  this   Lorg/scalatest/Inspectors;
            0      24     1   max   I
            0      24     2    xs   Ljava/util/Map;
            0      24     3   fun   Lscala/Function1;
            0      24     4 collecting   Lorg/scalatest/enablers/Collecting;
            0      24     5 asserting   Lorg/scalatest/enablers/InspectorAsserting;
            0      24     6 prettifier   Lorg/scalactic/Prettifier;
            0      24     7   pos   Lorg/scalactic/source/Position;
    Signature: #81                          // <K:Ljava/lang/Object;V:Ljava/lang/Object;JMAP::Ljava/util/Map<Ljava/lang/Object;Ljava/lang/Object;>;ASSERTION:Ljava/lang/Object;>(ITJMAP;Lscala/Function1<Lorg/scalatest/Entry<TK;TV;>;TASSERTION;>;Lorg/scalatest/enablers/Collecting<Lorg/scalatest/Entry<TK;TV;>;TJMAP;>;Lorg/scalatest/enablers/InspectorAsserting<TASSERTION;>;Lorg/scalactic/Prettifier;Lorg/scalactic/source/Position;)Ljava/lang/Object;
    MethodParameters:
      Name                           Flags
      max                            final
      xs                             final
      fun                            final
      collecting                     final
      asserting                      final
      prettifier                     final
      pos                            final

  public static java.lang.Object forAtMost$(org.scalatest.Inspectors, int, java.lang.String, scala.Function1, org.scalatest.enablers.Collecting, org.scalatest.enablers.InspectorAsserting, org.scalactic.Prettifier, org.scalactic.source.Position);
    descriptor: (Lorg/scalatest/Inspectors;ILjava/lang/String;Lscala/Function1;Lorg/scalatest/enablers/Collecting;Lorg/scalatest/enablers/InspectorAsserting;Lorg/scalactic/Prettifier;Lorg/scalactic/source/Position;)Ljava/lang/Object;
    flags: (0x1009) ACC_PUBLIC, ACC_STATIC, ACC_SYNTHETIC
    Code:
      stack=8, locals=8, args_size=8
         0: aload_0
         1: iload_1
         2: aload_2
         3: aload_3
         4: aload         4
         6: aload         5
         8: aload         6
        10: aload         7
        12: invokespecial #105                // InterfaceMethod forAtMost:(ILjava/lang/String;Lscala/Function1;Lorg/scalatest/enablers/Collecting;Lorg/scalatest/enablers/InspectorAsserting;Lorg/scalactic/Prettifier;Lorg/scalactic/source/Position;)Ljava/lang/Object;
        15: areturn
      LineNumberTable:
        line 409: 0
      LocalVariableTable:
        Start  Length  Slot  Name   Signature
            0      16     0 $this   Lorg/scalatest/Inspectors;
            0      16     1   max   I
            0      16     2    xs   Ljava/lang/String;
            0      16     3   fun   Lscala/Function1;
            0      16     4 collecting   Lorg/scalatest/enablers/Collecting;
            0      16     5 asserting   Lorg/scalatest/enablers/InspectorAsserting;
            0      16     6 prettifier   Lorg/scalactic/Prettifier;
            0      16     7   pos   Lorg/scalactic/source/Position;
    MethodParameters:
      Name                           Flags
      $this                          final synthetic
      max                            final
      xs                             final
      fun                            final
      collecting                     final
      asserting                      final
      prettifier                     final
      pos                            final

  public default <ASSERTION extends java.lang.Object> java.lang.Object forAtMost(int, java.lang.String, scala.Function1<java.lang.Object, ASSERTION>, org.scalatest.enablers.Collecting<java.lang.Object, java.lang.String>, org.scalatest.enablers.InspectorAsserting<ASSERTION>, org.scalactic.Prettifier, org.scalactic.source.Position);
    descriptor: (ILjava/lang/String;Lscala/Function1;Lorg/scalatest/enablers/Collecting;Lorg/scalatest/enablers/InspectorAsserting;Lorg/scalactic/Prettifier;Lorg/scalactic/source/Position;)Ljava/lang/Object;
    flags: (0x0001) ACC_PUBLIC
    Code:
      stack=8, locals=8, args_size=8
         0: aload         5
         2: iload_1
         3: aload         4
         5: aload_2
         6: invokeinterface #35,  2           // InterfaceMethod org/scalatest/enablers/Collecting.genTraversableFrom:(Ljava/lang/Object;)Lscala/collection/Iterable;
        11: aload_2
        12: iconst_0
        13: aload         6
        15: aload         7
        17: aload_3
        18: invokeinterface #99,  8           // InterfaceMethod org/scalatest/enablers/InspectorAsserting.forAtMost:(ILscala/collection/Iterable;Ljava/lang/Object;ZLorg/scalactic/Prettifier;Lorg/scalactic/source/Position;Lscala/Function1;)Ljava/lang/Object;
        23: areturn
      LineNumberTable:
        line 410: 0
      LocalVariableTable:
        Start  Length  Slot  Name   Signature
            0      24     0  this   Lorg/scalatest/Inspectors;
            0      24     1   max   I
            0      24     2    xs   Ljava/lang/String;
            0      24     3   fun   Lscala/Function1;
            0      24     4 collecting   Lorg/scalatest/enablers/Collecting;
            0      24     5 asserting   Lorg/scalatest/enablers/InspectorAsserting;
            0      24     6 prettifier   Lorg/scalactic/Prettifier;
            0      24     7   pos   Lorg/scalactic/source/Position;
    Signature: #86                          // <ASSERTION:Ljava/lang/Object;>(ILjava/lang/String;Lscala/Function1<Ljava/lang/Object;TASSERTION;>;Lorg/scalatest/enablers/Collecting<Ljava/lang/Object;Ljava/lang/String;>;Lorg/scalatest/enablers/InspectorAsserting<TASSERTION;>;Lorg/scalactic/Prettifier;Lorg/scalactic/source/Position;)Ljava/lang/Object;
    MethodParameters:
      Name                           Flags
      max                            final
      xs                             final
      fun                            final
      collecting                     final
      asserting                      final
      prettifier                     final
      pos                            final

  public static java.lang.Object forExactly$(org.scalatest.Inspectors, int, java.lang.Object, scala.Function1, org.scalatest.enablers.Collecting, org.scalatest.enablers.InspectorAsserting, org.scalactic.Prettifier, org.scalactic.source.Position);
    descriptor: (Lorg/scalatest/Inspectors;ILjava/lang/Object;Lscala/Function1;Lorg/scalatest/enablers/Collecting;Lorg/scalatest/enablers/InspectorAsserting;Lorg/scalactic/Prettifier;Lorg/scalactic/source/Position;)Ljava/lang/Object;
    flags: (0x1009) ACC_PUBLIC, ACC_STATIC, ACC_SYNTHETIC
    Code:
      stack=8, locals=8, args_size=8
         0: aload_0
         1: iload_1
         2: aload_2
         3: aload_3
         4: aload         4
         6: aload         5
         8: aload         6
        10: aload         7
        12: invokespecial #110                // InterfaceMethod forExactly:(ILjava/lang/Object;Lscala/Function1;Lorg/scalatest/enablers/Collecting;Lorg/scalatest/enablers/InspectorAsserting;Lorg/scalactic/Prettifier;Lorg/scalactic/source/Position;)Ljava/lang/Object;
        15: areturn
      LineNumberTable:
        line 423: 0
      LocalVariableTable:
        Start  Length  Slot  Name   Signature
            0      16     0 $this   Lorg/scalatest/Inspectors;
            0      16     1 succeededCount   I
            0      16     2    xs   Ljava/lang/Object;
            0      16     3   fun   Lscala/Function1;
            0      16     4 collecting   Lorg/scalatest/enablers/Collecting;
            0      16     5 asserting   Lorg/scalatest/enablers/InspectorAsserting;
            0      16     6 prettifier   Lorg/scalactic/Prettifier;
            0      16     7   pos   Lorg/scalactic/source/Position;
    MethodParameters:
      Name                           Flags
      $this                          final synthetic
      succeededCount                 final
      xs                             final
      fun                            final
      collecting                     final
      asserting                      final
      prettifier                     final
      pos                            final

  public default <E extends java.lang.Object, C extends java.lang.Object, ASSERTION extends java.lang.Object> java.lang.Object forExactly(int, C, scala.Function1<E, ASSERTION>, org.scalatest.enablers.Collecting<E, C>, org.scalatest.enablers.InspectorAsserting<ASSERTION>, org.scalactic.Prettifier, org.scalactic.source.Position);
    descriptor: (ILjava/lang/Object;Lscala/Function1;Lorg/scalatest/enablers/Collecting;Lorg/scalatest/enablers/InspectorAsserting;Lorg/scalactic/Prettifier;Lorg/scalactic/source/Position;)Ljava/lang/Object;
    flags: (0x0001) ACC_PUBLIC
    Code:
      stack=8, locals=8, args_size=8
         0: aload         5
         2: iload_1
         3: aload         4
         5: aload_2
         6: invokeinterface #35,  2           // InterfaceMethod org/scalatest/enablers/Collecting.genTraversableFrom:(Ljava/lang/Object;)Lscala/collection/Iterable;
        11: aload_2
        12: iconst_0
        13: aload         6
        15: aload         7
        17: aload_3
        18: invokeinterface #112,  8          // InterfaceMethod org/scalatest/enablers/InspectorAsserting.forExactly:(ILscala/collection/Iterable;Ljava/lang/Object;ZLorg/scalactic/Prettifier;Lorg/scalactic/source/Position;Lscala/Function1;)Ljava/lang/Object;
        23: areturn
      LineNumberTable:
        line 424: 0
      LocalVariableTable:
        Start  Length  Slot  Name   Signature
            0      24     0  this   Lorg/scalatest/Inspectors;
            0      24     1 succeededCount   I
            0      24     2    xs   Ljava/lang/Object;
            0      24     3   fun   Lscala/Function1;
            0      24     4 collecting   Lorg/scalatest/enablers/Collecting;
            0      24     5 asserting   Lorg/scalatest/enablers/InspectorAsserting;
            0      24     6 prettifier   Lorg/scalactic/Prettifier;
            0      24     7   pos   Lorg/scalactic/source/Position;
    Signature: #68                          // <E:Ljava/lang/Object;C:Ljava/lang/Object;ASSERTION:Ljava/lang/Object;>(ITC;Lscala/Function1<TE;TASSERTION;>;Lorg/scalatest/enablers/Collecting<TE;TC;>;Lorg/scalatest/enablers/InspectorAsserting<TASSERTION;>;Lorg/scalactic/Prettifier;Lorg/scalactic/source/Position;)Ljava/lang/Object;
    MethodParameters:
      Name                           Flags
      succeededCount                 final
      xs                             final
      fun                            final
      collecting                     final
      asserting                      final
      prettifier                     final
      pos                            final

  public static java.lang.Object forExactly$(org.scalatest.Inspectors, int, scala.collection.Map, scala.Function1, org.scalatest.enablers.Collecting, org.scalatest.enablers.InspectorAsserting, org.scalactic.Prettifier, org.scalactic.source.Position);
    descriptor: (Lorg/scalatest/Inspectors;ILscala/collection/Map;Lscala/Function1;Lorg/scalatest/enablers/Collecting;Lorg/scalatest/enablers/InspectorAsserting;Lorg/scalactic/Prettifier;Lorg/scalactic/source/Position;)Ljava/lang/Object;
    flags: (0x1009) ACC_PUBLIC, ACC_STATIC, ACC_SYNTHETIC
    Code:
      stack=8, locals=8, args_size=8
         0: aload_0
         1: iload_1
         2: aload_2
         3: aload_3
         4: aload         4
         6: aload         5
         8: aload         6
        10: aload         7
        12: invokespecial #114                // InterfaceMethod forExactly:(ILscala/collection/Map;Lscala/Function1;Lorg/scalatest/enablers/Collecting;Lorg/scalatest/enablers/InspectorAsserting;Lorg/scalactic/Prettifier;Lorg/scalactic/source/Position;)Ljava/lang/Object;
        15: areturn
      LineNumberTable:
        line 438: 0
      LocalVariableTable:
        Start  Length  Slot  Name   Signature
            0      16     0 $this   Lorg/scalatest/Inspectors;
            0      16     1 succeededCount   I
            0      16     2    xs   Lscala/collection/Map;
            0      16     3   fun   Lscala/Function1;
            0      16     4 collecting   Lorg/scalatest/enablers/Collecting;
            0      16     5 asserting   Lorg/scalatest/enablers/InspectorAsserting;
            0      16     6 prettifier   Lorg/scalactic/Prettifier;
            0      16     7   pos   Lorg/scalactic/source/Position;
    MethodParameters:
      Name                           Flags
      $this                          final synthetic
      succeededCount                 final
      xs                             final
      fun                            final
      collecting                     final
      asserting                      final
      prettifier                     final
      pos                            final

  public default <K extends java.lang.Object, V extends java.lang.Object, MAP extends scala.collection.Map<java.lang.Object, java.lang.Object>, ASSERTION extends java.lang.Object> java.lang.Object forExactly(int, MAP, scala.Function1<scala.Tuple2<K, V>, ASSERTION>, org.scalatest.enablers.Collecting<scala.Tuple2<K, V>, scala.collection.Iterable<scala.Tuple2<K, V>>>, org.scalatest.enablers.InspectorAsserting<ASSERTION>, org.scalactic.Prettifier, org.scalactic.source.Position);
    descriptor: (ILscala/collection/Map;Lscala/Function1;Lorg/scalatest/enablers/Collecting;Lorg/scalatest/enablers/InspectorAsserting;Lorg/scalactic/Prettifier;Lorg/scalactic/source/Position;)Ljava/lang/Object;
    flags: (0x0001) ACC_PUBLIC
    Code:
      stack=8, locals=8, args_size=8
         0: aload         5
         2: iload_1
         3: aload         4
         5: aload_2
         6: invokeinterface #35,  2           // InterfaceMethod org/scalatest/enablers/Collecting.genTraversableFrom:(Ljava/lang/Object;)Lscala/collection/Iterable;
        11: aload_2
        12: iconst_0
        13: aload         6
        15: aload         7
        17: aload_3
        18: invokeinterface #112,  8          // InterfaceMethod org/scalatest/enablers/InspectorAsserting.forExactly:(ILscala/collection/Iterable;Ljava/lang/Object;ZLorg/scalactic/Prettifier;Lorg/scalactic/source/Position;Lscala/Function1;)Ljava/lang/Object;
        23: areturn
      LineNumberTable:
        line 439: 0
      LocalVariableTable:
        Start  Length  Slot  Name   Signature
            0      24     0  this   Lorg/scalatest/Inspectors;
            0      24     1 succeededCount   I
            0      24     2    xs   Lscala/collection/Map;
            0      24     3   fun   Lscala/Function1;
            0      24     4 collecting   Lorg/scalatest/enablers/Collecting;
            0      24     5 asserting   Lorg/scalatest/enablers/InspectorAsserting;
            0      24     6 prettifier   Lorg/scalactic/Prettifier;
            0      24     7   pos   Lorg/scalactic/source/Position;
    Signature: #76                          // <K:Ljava/lang/Object;V:Ljava/lang/Object;MAP::Lscala/collection/Map<Ljava/lang/Object;Ljava/lang/Object;>;ASSERTION:Ljava/lang/Object;>(ITMAP;Lscala/Function1<Lscala/Tuple2<TK;TV;>;TASSERTION;>;Lorg/scalatest/enablers/Collecting<Lscala/Tuple2<TK;TV;>;Lscala/collection/Iterable<Lscala/Tuple2<TK;TV;>;>;>;Lorg/scalatest/enablers/InspectorAsserting<TASSERTION;>;Lorg/scalactic/Prettifier;Lorg/scalactic/source/Position;)Ljava/lang/Object;
    MethodParameters:
      Name                           Flags
      succeededCount                 final
      xs                             final
      fun                            final
      collecting                     final
      asserting                      final
      prettifier                     final
      pos                            final

  public static java.lang.Object forExactly$(org.scalatest.Inspectors, int, java.util.Map, scala.Function1, org.scalatest.enablers.Collecting, org.scalatest.enablers.InspectorAsserting, org.scalactic.Prettifier, org.scalactic.source.Position);
    descriptor: (Lorg/scalatest/Inspectors;ILjava/util/Map;Lscala/Function1;Lorg/scalatest/enablers/Collecting;Lorg/scalatest/enablers/InspectorAsserting;Lorg/scalactic/Prettifier;Lorg/scalactic/source/Position;)Ljava/lang/Object;
    flags: (0x1009) ACC_PUBLIC, ACC_STATIC, ACC_SYNTHETIC
    Code:
      stack=8, locals=8, args_size=8
         0: aload_0
         1: iload_1
         2: aload_2
         3: aload_3
         4: aload         4
         6: aload         5
         8: aload         6
        10: aload         7
        12: invokespecial #116                // InterfaceMethod forExactly:(ILjava/util/Map;Lscala/Function1;Lorg/scalatest/enablers/Collecting;Lorg/scalatest/enablers/InspectorAsserting;Lorg/scalactic/Prettifier;Lorg/scalactic/source/Position;)Ljava/lang/Object;
        15: areturn
      LineNumberTable:
        line 454: 0
      LocalVariableTable:
        Start  Length  Slot  Name   Signature
            0      16     0 $this   Lorg/scalatest/Inspectors;
            0      16     1 succeededCount   I
            0      16     2    xs   Ljava/util/Map;
            0      16     3   fun   Lscala/Function1;
            0      16     4 collecting   Lorg/scalatest/enablers/Collecting;
            0      16     5 asserting   Lorg/scalatest/enablers/InspectorAsserting;
            0      16     6 prettifier   Lorg/scalactic/Prettifier;
            0      16     7   pos   Lorg/scalactic/source/Position;
    MethodParameters:
      Name                           Flags
      $this                          final synthetic
      succeededCount                 final
      xs                             final
      fun                            final
      collecting                     final
      asserting                      final
      prettifier                     final
      pos                            final

  public default <K extends java.lang.Object, V extends java.lang.Object, JMAP extends java.util.Map<java.lang.Object, java.lang.Object>, ASSERTION extends java.lang.Object> java.lang.Object forExactly(int, JMAP, scala.Function1<org.scalatest.Entry<K, V>, ASSERTION>, org.scalatest.enablers.Collecting<org.scalatest.Entry<K, V>, JMAP>, org.scalatest.enablers.InspectorAsserting<ASSERTION>, org.scalactic.Prettifier, org.scalactic.source.Position);
    descriptor: (ILjava/util/Map;Lscala/Function1;Lorg/scalatest/enablers/Collecting;Lorg/scalatest/enablers/InspectorAsserting;Lorg/scalactic/Prettifier;Lorg/scalactic/source/Position;)Ljava/lang/Object;
    flags: (0x0001) ACC_PUBLIC
    Code:
      stack=8, locals=8, args_size=8
         0: aload         5
         2: iload_1
         3: aload         4
         5: aload_2
         6: invokeinterface #35,  2           // InterfaceMethod org/scalatest/enablers/Collecting.genTraversableFrom:(Ljava/lang/Object;)Lscala/collection/Iterable;
        11: aload_2
        12: iconst_0
        13: aload         6
        15: aload         7
        17: aload_3
        18: invokeinterface #112,  8          // InterfaceMethod org/scalatest/enablers/InspectorAsserting.forExactly:(ILscala/collection/Iterable;Ljava/lang/Object;ZLorg/scalactic/Prettifier;Lorg/scalactic/source/Position;Lscala/Function1;)Ljava/lang/Object;
        23: areturn
      LineNumberTable:
        line 455: 0
      LocalVariableTable:
        Start  Length  Slot  Name   Signature
            0      24     0  this   Lorg/scalatest/Inspectors;
            0      24     1 succeededCount   I
            0      24     2    xs   Ljava/util/Map;
            0      24     3   fun   Lscala/Function1;
            0      24     4 collecting   Lorg/scalatest/enablers/Collecting;
            0      24     5 asserting   Lorg/scalatest/enablers/InspectorAsserting;
            0      24     6 prettifier   Lorg/scalactic/Prettifier;
            0      24     7   pos   Lorg/scalactic/source/Position;
    Signature: #81                          // <K:Ljava/lang/Object;V:Ljava/lang/Object;JMAP::Ljava/util/Map<Ljava/lang/Object;Ljava/lang/Object;>;ASSERTION:Ljava/lang/Object;>(ITJMAP;Lscala/Function1<Lorg/scalatest/Entry<TK;TV;>;TASSERTION;>;Lorg/scalatest/enablers/Collecting<Lorg/scalatest/Entry<TK;TV;>;TJMAP;>;Lorg/scalatest/enablers/InspectorAsserting<TASSERTION;>;Lorg/scalactic/Prettifier;Lorg/scalactic/source/Position;)Ljava/lang/Object;
    MethodParameters:
      Name                           Flags
      succeededCount                 final
      xs                             final
      fun                            final
      collecting                     final
      asserting                      final
      prettifier                     final
      pos                            final

  public static java.lang.Object forExactly$(org.scalatest.Inspectors, int, java.lang.String, scala.Function1, org.scalatest.enablers.Collecting, org.scalatest.enablers.InspectorAsserting, org.scalactic.Prettifier, org.scalactic.source.Position);
    descriptor: (Lorg/scalatest/Inspectors;ILjava/lang/String;Lscala/Function1;Lorg/scalatest/enablers/Collecting;Lorg/scalatest/enablers/InspectorAsserting;Lorg/scalactic/Prettifier;Lorg/scalactic/source/Position;)Ljava/lang/Object;
    flags: (0x1009) ACC_PUBLIC, ACC_STATIC, ACC_SYNTHETIC
    Code:
      stack=8, locals=8, args_size=8
         0: aload_0
         1: iload_1
         2: aload_2
         3: aload_3
         4: aload         4
         6: aload         5
         8: aload         6
        10: aload         7
        12: invokespecial #118                // InterfaceMethod forExactly:(ILjava/lang/String;Lscala/Function1;Lorg/scalatest/enablers/Collecting;Lorg/scalatest/enablers/InspectorAsserting;Lorg/scalactic/Prettifier;Lorg/scalactic/source/Position;)Ljava/lang/Object;
        15: areturn
      LineNumberTable:
        line 467: 0
      LocalVariableTable:
        Start  Length  Slot  Name   Signature
            0      16     0 $this   Lorg/scalatest/Inspectors;
            0      16     1 succeededCount   I
            0      16     2    xs   Ljava/lang/String;
            0      16     3   fun   Lscala/Function1;
            0      16     4 collecting   Lorg/scalatest/enablers/Collecting;
            0      16     5 asserting   Lorg/scalatest/enablers/InspectorAsserting;
            0      16     6 prettifier   Lorg/scalactic/Prettifier;
            0      16     7   pos   Lorg/scalactic/source/Position;
    MethodParameters:
      Name                           Flags
      $this                          final synthetic
      succeededCount                 final
      xs                             final
      fun                            final
      collecting                     final
      asserting                      final
      prettifier                     final
      pos                            final

  public default <ASSERTION extends java.lang.Object> java.lang.Object forExactly(int, java.lang.String, scala.Function1<java.lang.Object, ASSERTION>, org.scalatest.enablers.Collecting<java.lang.Object, java.lang.String>, org.scalatest.enablers.InspectorAsserting<ASSERTION>, org.scalactic.Prettifier, org.scalactic.source.Position);
    descriptor: (ILjava/lang/String;Lscala/Function1;Lorg/scalatest/enablers/Collecting;Lorg/scalatest/enablers/InspectorAsserting;Lorg/scalactic/Prettifier;Lorg/scalactic/source/Position;)Ljava/lang/Object;
    flags: (0x0001) ACC_PUBLIC
    Code:
      stack=8, locals=8, args_size=8
         0: aload         5
         2: iload_1
         3: aload         4
         5: aload_2
         6: invokeinterface #35,  2           // InterfaceMethod org/scalatest/enablers/Collecting.genTraversableFrom:(Ljava/lang/Object;)Lscala/collection/Iterable;
        11: aload_2
        12: iconst_0
        13: aload         6
        15: aload         7
        17: aload_3
        18: invokeinterface #112,  8          // InterfaceMethod org/scalatest/enablers/InspectorAsserting.forExactly:(ILscala/collection/Iterable;Ljava/lang/Object;ZLorg/scalactic/Prettifier;Lorg/scalactic/source/Position;Lscala/Function1;)Ljava/lang/Object;
        23: areturn
      LineNumberTable:
        line 468: 0
      LocalVariableTable:
        Start  Length  Slot  Name   Signature
            0      24     0  this   Lorg/scalatest/Inspectors;
            0      24     1 succeededCount   I
            0      24     2    xs   Ljava/lang/String;
            0      24     3   fun   Lscala/Function1;
            0      24     4 collecting   Lorg/scalatest/enablers/Collecting;
            0      24     5 asserting   Lorg/scalatest/enablers/InspectorAsserting;
            0      24     6 prettifier   Lorg/scalactic/Prettifier;
            0      24     7   pos   Lorg/scalactic/source/Position;
    Signature: #86                          // <ASSERTION:Ljava/lang/Object;>(ILjava/lang/String;Lscala/Function1<Ljava/lang/Object;TASSERTION;>;Lorg/scalatest/enablers/Collecting<Ljava/lang/Object;Ljava/lang/String;>;Lorg/scalatest/enablers/InspectorAsserting<TASSERTION;>;Lorg/scalactic/Prettifier;Lorg/scalactic/source/Position;)Ljava/lang/Object;
    MethodParameters:
      Name                           Flags
      succeededCount                 final
      xs                             final
      fun                            final
      collecting                     final
      asserting                      final
      prettifier                     final
      pos                            final

  public static java.lang.Object forNo$(org.scalatest.Inspectors, java.lang.Object, scala.Function1, org.scalatest.enablers.Collecting, org.scalatest.enablers.InspectorAsserting, org.scalactic.Prettifier, org.scalactic.source.Position);
    descriptor: (Lorg/scalatest/Inspectors;Ljava/lang/Object;Lscala/Function1;Lorg/scalatest/enablers/Collecting;Lorg/scalatest/enablers/InspectorAsserting;Lorg/scalactic/Prettifier;Lorg/scalactic/source/Position;)Ljava/lang/Object;
    flags: (0x1009) ACC_PUBLIC, ACC_STATIC, ACC_SYNTHETIC
    Code:
      stack=7, locals=7, args_size=7
         0: aload_0
         1: aload_1
         2: aload_2
         3: aload_3
         4: aload         4
         6: aload         5
         8: aload         6
        10: invokespecial #122                // InterfaceMethod forNo:(Ljava/lang/Object;Lscala/Function1;Lorg/scalatest/enablers/Collecting;Lorg/scalatest/enablers/InspectorAsserting;Lorg/scalactic/Prettifier;Lorg/scalactic/source/Position;)Ljava/lang/Object;
        13: areturn
      LineNumberTable:
        line 471: 0
      LocalVariableTable:
        Start  Length  Slot  Name   Signature
            0      14     0 $this   Lorg/scalatest/Inspectors;
            0      14     1    xs   Ljava/lang/Object;
            0      14     2   fun   Lscala/Function1;
            0      14     3 collecting   Lorg/scalatest/enablers/Collecting;
            0      14     4 asserting   Lorg/scalatest/enablers/InspectorAsserting;
            0      14     5 prettifier   Lorg/scalactic/Prettifier;
            0      14     6   pos   Lorg/scalactic/source/Position;
    MethodParameters:
      Name                           Flags
      $this                          final synthetic
      xs                             final
      fun                            final
      collecting                     final
      asserting                      final
      prettifier                     final
      pos                            final

  public default <E extends java.lang.Object, C extends java.lang.Object, ASSERTION extends java.lang.Object> java.lang.Object forNo(C, scala.Function1<E, ASSERTION>, org.scalatest.enablers.Collecting<E, C>, org.scalatest.enablers.InspectorAsserting<ASSERTION>, org.scalactic.Prettifier, org.scalactic.source.Position);
    descriptor: (Ljava/lang/Object;Lscala/Function1;Lorg/scalatest/enablers/Collecting;Lorg/scalatest/enablers/InspectorAsserting;Lorg/scalactic/Prettifier;Lorg/scalactic/source/Position;)Ljava/lang/Object;
    flags: (0x0001) ACC_PUBLIC
    Code:
      stack=7, locals=7, args_size=7
         0: aload         4
         2: aload_3
         3: aload_1
         4: invokeinterface #35,  2           // InterfaceMethod org/scalatest/enablers/Collecting.genTraversableFrom:(Ljava/lang/Object;)Lscala/collection/Iterable;
         9: aload_1
        10: iconst_0
        11: aload         5
        13: aload         6
        15: aload_2
        16: invokeinterface #124,  7          // InterfaceMethod org/scalatest/enablers/InspectorAsserting.forNo:(Lscala/collection/Iterable;Ljava/lang/Object;ZLorg/scalactic/Prettifier;Lorg/scalactic/source/Position;Lscala/Function1;)Ljava/lang/Object;
        21: areturn
      LineNumberTable:
        line 472: 0
      LocalVariableTable:
        Start  Length  Slot  Name   Signature
            0      22     0  this   Lorg/scalatest/Inspectors;
            0      22     1    xs   Ljava/lang/Object;
            0      22     2   fun   Lscala/Function1;
            0      22     3 collecting   Lorg/scalatest/enablers/Collecting;
            0      22     4 asserting   Lorg/scalatest/enablers/InspectorAsserting;
            0      22     5 prettifier   Lorg/scalactic/Prettifier;
            0      22     6   pos   Lorg/scalactic/source/Position;
    Signature: #29                          // <E:Ljava/lang/Object;C:Ljava/lang/Object;ASSERTION:Ljava/lang/Object;>(TC;Lscala/Function1<TE;TASSERTION;>;Lorg/scalatest/enablers/Collecting<TE;TC;>;Lorg/scalatest/enablers/InspectorAsserting<TASSERTION;>;Lorg/scalactic/Prettifier;Lorg/scalactic/source/Position;)Ljava/lang/Object;
    MethodParameters:
      Name                           Flags
      xs                             final
      fun                            final
      collecting                     final
      asserting                      final
      prettifier                     final
      pos                            final

  public static java.lang.Object forNo$(org.scalatest.Inspectors, scala.collection.Map, scala.Function1, org.scalatest.enablers.Collecting, org.scalatest.enablers.InspectorAsserting, org.scalactic.Prettifier, org.scalactic.source.Position);
    descriptor: (Lorg/scalatest/Inspectors;Lscala/collection/Map;Lscala/Function1;Lorg/scalatest/enablers/Collecting;Lorg/scalatest/enablers/InspectorAsserting;Lorg/scalactic/Prettifier;Lorg/scalactic/source/Position;)Ljava/lang/Object;
    flags: (0x1009) ACC_PUBLIC, ACC_STATIC, ACC_SYNTHETIC
    Code:
      stack=7, locals=7, args_size=7
         0: aload_0
         1: aload_1
         2: aload_2
         3: aload_3
         4: aload         4
         6: aload         5
         8: aload         6
        10: invokespecial #126                // InterfaceMethod forNo:(Lscala/collection/Map;Lscala/Function1;Lorg/scalatest/enablers/Collecting;Lorg/scalatest/enablers/InspectorAsserting;Lorg/scalactic/Prettifier;Lorg/scalactic/source/Position;)Ljava/lang/Object;
        13: areturn
      LineNumberTable:
        line 475: 0
      LocalVariableTable:
        Start  Length  Slot  Name   Signature
            0      14     0 $this   Lorg/scalatest/Inspectors;
            0      14     1    xs   Lscala/collection/Map;
            0      14     2   fun   Lscala/Function1;
            0      14     3 collecting   Lorg/scalatest/enablers/Collecting;
            0      14     4 asserting   Lorg/scalatest/enablers/InspectorAsserting;
            0      14     5 prettifier   Lorg/scalactic/Prettifier;
            0      14     6   pos   Lorg/scalactic/source/Position;
    MethodParameters:
      Name                           Flags
      $this                          final synthetic
      xs                             final
      fun                            final
      collecting                     final
      asserting                      final
      prettifier                     final
      pos                            final

  public default <K extends java.lang.Object, V extends java.lang.Object, MAP extends scala.collection.Map<java.lang.Object, java.lang.Object>, ASSERTION extends java.lang.Object> java.lang.Object forNo(MAP, scala.Function1<scala.Tuple2<K, V>, ASSERTION>, org.scalatest.enablers.Collecting<scala.Tuple2<K, V>, scala.collection.Iterable<scala.Tuple2<K, V>>>, org.scalatest.enablers.InspectorAsserting<ASSERTION>, org.scalactic.Prettifier, org.scalactic.source.Position);
    descriptor: (Lscala/collection/Map;Lscala/Function1;Lorg/scalatest/enablers/Collecting;Lorg/scalatest/enablers/InspectorAsserting;Lorg/scalactic/Prettifier;Lorg/scalactic/source/Position;)Ljava/lang/Object;
    flags: (0x0001) ACC_PUBLIC
    Code:
      stack=7, locals=7, args_size=7
         0: aload         4
         2: aload_3
         3: aload_1
         4: invokeinterface #35,  2           // InterfaceMethod org/scalatest/enablers/Collecting.genTraversableFrom:(Ljava/lang/Object;)Lscala/collection/Iterable;
         9: aload_1
        10: iconst_0
        11: aload         5
        13: aload         6
        15: aload_2
        16: invokeinterface #124,  7          // InterfaceMethod org/scalatest/enablers/InspectorAsserting.forNo:(Lscala/collection/Iterable;Ljava/lang/Object;ZLorg/scalactic/Prettifier;Lorg/scalactic/source/Position;Lscala/Function1;)Ljava/lang/Object;
        21: areturn
      LineNumberTable:
        line 476: 0
      LocalVariableTable:
        Start  Length  Slot  Name   Signature
            0      22     0  this   Lorg/scalatest/Inspectors;
            0      22     1    xs   Lscala/collection/Map;
            0      22     2   fun   Lscala/Function1;
            0      22     3 collecting   Lorg/scalatest/enablers/Collecting;
            0      22     4 asserting   Lorg/scalatest/enablers/InspectorAsserting;
            0      22     5 prettifier   Lorg/scalactic/Prettifier;
            0      22     6   pos   Lorg/scalactic/source/Position;
    Signature: #47                          // <K:Ljava/lang/Object;V:Ljava/lang/Object;MAP::Lscala/collection/Map<Ljava/lang/Object;Ljava/lang/Object;>;ASSERTION:Ljava/lang/Object;>(TMAP;Lscala/Function1<Lscala/Tuple2<TK;TV;>;TASSERTION;>;Lorg/scalatest/enablers/Collecting<Lscala/Tuple2<TK;TV;>;Lscala/collection/Iterable<Lscala/Tuple2<TK;TV;>;>;>;Lorg/scalatest/enablers/InspectorAsserting<TASSERTION;>;Lorg/scalactic/Prettifier;Lorg/scalactic/source/Position;)Ljava/lang/Object;
    MethodParameters:
      Name                           Flags
      xs                             final
      fun                            final
      collecting                     final
      asserting                      final
      prettifier                     final
      pos                            final

  public static java.lang.Object forNo$(org.scalatest.Inspectors, java.util.Map, scala.Function1, org.scalatest.enablers.Collecting, org.scalatest.enablers.InspectorAsserting, org.scalactic.Prettifier, org.scalactic.source.Position);
    descriptor: (Lorg/scalatest/Inspectors;Ljava/util/Map;Lscala/Function1;Lorg/scalatest/enablers/Collecting;Lorg/scalatest/enablers/InspectorAsserting;Lorg/scalactic/Prettifier;Lorg/scalactic/source/Position;)Ljava/lang/Object;
    flags: (0x1009) ACC_PUBLIC, ACC_STATIC, ACC_SYNTHETIC
    Code:
      stack=7, locals=7, args_size=7
         0: aload_0
         1: aload_1
         2: aload_2
         3: aload_3
         4: aload         4
         6: aload         5
         8: aload         6
        10: invokespecial #128                // InterfaceMethod forNo:(Ljava/util/Map;Lscala/Function1;Lorg/scalatest/enablers/Collecting;Lorg/scalatest/enablers/InspectorAsserting;Lorg/scalactic/Prettifier;Lorg/scalactic/source/Position;)Ljava/lang/Object;
        13: areturn
      LineNumberTable:
        line 480: 0
      LocalVariableTable:
        Start  Length  Slot  Name   Signature
            0      14     0 $this   Lorg/scalatest/Inspectors;
            0      14     1    xs   Ljava/util/Map;
            0      14     2   fun   Lscala/Function1;
            0      14     3 collecting   Lorg/scalatest/enablers/Collecting;
            0      14     4 asserting   Lorg/scalatest/enablers/InspectorAsserting;
            0      14     5 prettifier   Lorg/scalactic/Prettifier;
            0      14     6   pos   Lorg/scalactic/source/Position;
    MethodParameters:
      Name                           Flags
      $this                          final synthetic
      xs                             final
      fun                            final
      collecting                     final
      asserting                      final
      prettifier                     final
      pos                            final

  public default <K extends java.lang.Object, V extends java.lang.Object, JMAP extends java.util.Map<java.lang.Object, java.lang.Object>, ASSERTION extends java.lang.Object> java.lang.Object forNo(JMAP, scala.Function1<org.scalatest.Entry<K, V>, ASSERTION>, org.scalatest.enablers.Collecting<org.scalatest.Entry<K, V>, JMAP>, org.scalatest.enablers.InspectorAsserting<ASSERTION>, org.scalactic.Prettifier, org.scalactic.source.Position);
    descriptor: (Ljava/util/Map;Lscala/Function1;Lorg/scalatest/enablers/Collecting;Lorg/scalatest/enablers/InspectorAsserting;Lorg/scalactic/Prettifier;Lorg/scalactic/source/Position;)Ljava/lang/Object;
    flags: (0x0001) ACC_PUBLIC
    Code:
      stack=7, locals=7, args_size=7
         0: aload         4
         2: aload_3
         3: aload_1
         4: invokeinterface #35,  2           // InterfaceMethod org/scalatest/enablers/Collecting.genTraversableFrom:(Ljava/lang/Object;)Lscala/collection/Iterable;
         9: aload_1
        10: iconst_0
        11: aload         5
        13: aload         6
        15: aload_2
        16: invokeinterface #124,  7          // InterfaceMethod org/scalatest/enablers/InspectorAsserting.forNo:(Lscala/collection/Iterable;Ljava/lang/Object;ZLorg/scalactic/Prettifier;Lorg/scalactic/source/Position;Lscala/Function1;)Ljava/lang/Object;
        21: areturn
      LineNumberTable:
        line 481: 0
      LocalVariableTable:
        Start  Length  Slot  Name   Signature
            0      22     0  this   Lorg/scalatest/Inspectors;
            0      22     1    xs   Ljava/util/Map;
            0      22     2   fun   Lscala/Function1;
            0      22     3 collecting   Lorg/scalatest/enablers/Collecting;
            0      22     4 asserting   Lorg/scalatest/enablers/InspectorAsserting;
            0      22     5 prettifier   Lorg/scalactic/Prettifier;
            0      22     6   pos   Lorg/scalactic/source/Position;
    Signature: #53                          // <K:Ljava/lang/Object;V:Ljava/lang/Object;JMAP::Ljava/util/Map<Ljava/lang/Object;Ljava/lang/Object;>;ASSERTION:Ljava/lang/Object;>(TJMAP;Lscala/Function1<Lorg/scalatest/Entry<TK;TV;>;TASSERTION;>;Lorg/scalatest/enablers/Collecting<Lorg/scalatest/Entry<TK;TV;>;TJMAP;>;Lorg/scalatest/enablers/InspectorAsserting<TASSERTION;>;Lorg/scalactic/Prettifier;Lorg/scalactic/source/Position;)Ljava/lang/Object;
    MethodParameters:
      Name                           Flags
      xs                             final
      fun                            final
      collecting                     final
      asserting                      final
      prettifier                     final
      pos                            final

  public static java.lang.Object forNo$(org.scalatest.Inspectors, java.lang.String, scala.Function1, org.scalatest.enablers.Collecting, org.scalatest.enablers.InspectorAsserting, org.scalactic.Prettifier, org.scalactic.source.Position);
    descriptor: (Lorg/scalatest/Inspectors;Ljava/lang/String;Lscala/Function1;Lorg/scalatest/enablers/Collecting;Lorg/scalatest/enablers/InspectorAsserting;Lorg/scalactic/Prettifier;Lorg/scalactic/source/Position;)Ljava/lang/Object;
    flags: (0x1009) ACC_PUBLIC, ACC_STATIC, ACC_SYNTHETIC
    Code:
      stack=7, locals=7, args_size=7
         0: aload_0
         1: aload_1
         2: aload_2
         3: aload_3
         4: aload         4
         6: aload         5
         8: aload         6
        10: invokespecial #130                // InterfaceMethod forNo:(Ljava/lang/String;Lscala/Function1;Lorg/scalatest/enablers/Collecting;Lorg/scalatest/enablers/InspectorAsserting;Lorg/scalactic/Prettifier;Lorg/scalactic/source/Position;)Ljava/lang/Object;
        13: areturn
      LineNumberTable:
        line 485: 0
      LocalVariableTable:
        Start  Length  Slot  Name   Signature
            0      14     0 $this   Lorg/scalatest/Inspectors;
            0      14     1    xs   Ljava/lang/String;
            0      14     2   fun   Lscala/Function1;
            0      14     3 collecting   Lorg/scalatest/enablers/Collecting;
            0      14     4 asserting   Lorg/scalatest/enablers/InspectorAsserting;
            0      14     5 prettifier   Lorg/scalactic/Prettifier;
            0      14     6   pos   Lorg/scalactic/source/Position;
    MethodParameters:
      Name                           Flags
      $this                          final synthetic
      xs                             final
      fun                            final
      collecting                     final
      asserting                      final
      prettifier                     final
      pos                            final

  public default <ASSERTION extends java.lang.Object> java.lang.Object forNo(java.lang.String, scala.Function1<java.lang.Object, ASSERTION>, org.scalatest.enablers.Collecting<java.lang.Object, java.lang.String>, org.scalatest.enablers.InspectorAsserting<ASSERTION>, org.scalactic.Prettifier, org.scalactic.source.Position);
    descriptor: (Ljava/lang/String;Lscala/Function1;Lorg/scalatest/enablers/Collecting;Lorg/scalatest/enablers/InspectorAsserting;Lorg/scalactic/Prettifier;Lorg/scalactic/source/Position;)Ljava/lang/Object;
    flags: (0x0001) ACC_PUBLIC
    Code:
      stack=7, locals=7, args_size=7
         0: aload         4
         2: aload_3
         3: aload_1
         4: invokeinterface #35,  2           // InterfaceMethod org/scalatest/enablers/Collecting.genTraversableFrom:(Ljava/lang/Object;)Lscala/collection/Iterable;
         9: aload_1
        10: iconst_0
        11: aload         5
        13: aload         6
        15: aload_2
        16: invokeinterface #124,  7          // InterfaceMethod org/scalatest/enablers/InspectorAsserting.forNo:(Lscala/collection/Iterable;Ljava/lang/Object;ZLorg/scalactic/Prettifier;Lorg/scalactic/source/Position;Lscala/Function1;)Ljava/lang/Object;
        21: areturn
      LineNumberTable:
        line 486: 0
      LocalVariableTable:
        Start  Length  Slot  Name   Signature
            0      22     0  this   Lorg/scalatest/Inspectors;
            0      22     1    xs   Ljava/lang/String;
            0      22     2   fun   Lscala/Function1;
            0      22     3 collecting   Lorg/scalatest/enablers/Collecting;
            0      22     4 asserting   Lorg/scalatest/enablers/InspectorAsserting;
            0      22     5 prettifier   Lorg/scalactic/Prettifier;
            0      22     6   pos   Lorg/scalactic/source/Position;
    Signature: #59                          // <ASSERTION:Ljava/lang/Object;>(Ljava/lang/String;Lscala/Function1<Ljava/lang/Object;TASSERTION;>;Lorg/scalatest/enablers/Collecting<Ljava/lang/Object;Ljava/lang/String;>;Lorg/scalatest/enablers/InspectorAsserting<TASSERTION;>;Lorg/scalactic/Prettifier;Lorg/scalactic/source/Position;)Ljava/lang/Object;
    MethodParameters:
      Name                           Flags
      xs                             final
      fun                            final
      collecting                     final
      asserting                      final
      prettifier                     final
      pos                            final

  public static java.lang.Object forBetween$(org.scalatest.Inspectors, int, int, java.lang.Object, scala.Function1, org.scalatest.enablers.Collecting, org.scalatest.enablers.InspectorAsserting, org.scalactic.Prettifier, org.scalactic.source.Position);
    descriptor: (Lorg/scalatest/Inspectors;IILjava/lang/Object;Lscala/Function1;Lorg/scalatest/enablers/Collecting;Lorg/scalatest/enablers/InspectorAsserting;Lorg/scalactic/Prettifier;Lorg/scalactic/source/Position;)Ljava/lang/Object;
    flags: (0x1009) ACC_PUBLIC, ACC_STATIC, ACC_SYNTHETIC
    Code:
      stack=9, locals=9, args_size=9
         0: aload_0
         1: iload_1
         2: iload_2
         3: aload_3
         4: aload         4
         6: aload         5
         8: aload         6
        10: aload         7
        12: aload         8
        14: invokespecial #138                // InterfaceMethod forBetween:(IILjava/lang/Object;Lscala/Function1;Lorg/scalatest/enablers/Collecting;Lorg/scalatest/enablers/InspectorAsserting;Lorg/scalactic/Prettifier;Lorg/scalactic/source/Position;)Ljava/lang/Object;
        17: areturn
      LineNumberTable:
        line 500: 0
      LocalVariableTable:
        Start  Length  Slot  Name   Signature
            0      18     0 $this   Lorg/scalatest/Inspectors;
            0      18     1  from   I
            0      18     2  upTo   I
            0      18     3    xs   Ljava/lang/Object;
            0      18     4   fun   Lscala/Function1;
            0      18     5 collecting   Lorg/scalatest/enablers/Collecting;
            0      18     6 asserting   Lorg/scalatest/enablers/InspectorAsserting;
            0      18     7 prettifier   Lorg/scalactic/Prettifier;
            0      18     8   pos   Lorg/scalactic/source/Position;
    MethodParameters:
      Name                           Flags
      $this                          final synthetic
      from                           final
      upTo                           final
      xs                             final
      fun                            final
      collecting                     final
      asserting                      final
      prettifier                     final
      pos                            final

  public default <E extends java.lang.Object, C extends java.lang.Object, ASSERTION extends java.lang.Object> java.lang.Object forBetween(int, int, C, scala.Function1<E, ASSERTION>, org.scalatest.enablers.Collecting<E, C>, org.scalatest.enablers.InspectorAsserting<ASSERTION>, org.scalactic.Prettifier, org.scalactic.source.Position);
    descriptor: (IILjava/lang/Object;Lscala/Function1;Lorg/scalatest/enablers/Collecting;Lorg/scalatest/enablers/InspectorAsserting;Lorg/scalactic/Prettifier;Lorg/scalactic/source/Position;)Ljava/lang/Object;
    flags: (0x0001) ACC_PUBLIC
    Code:
      stack=9, locals=9, args_size=9
         0: aload         6
         2: iload_1
         3: iload_2
         4: aload         5
         6: aload_3
         7: invokeinterface #35,  2           // InterfaceMethod org/scalatest/enablers/Collecting.genTraversableFrom:(Ljava/lang/Object;)Lscala/collection/Iterable;
        12: aload_3
        13: iconst_0
        14: aload         7
        16: aload         8
        18: aload         4
        20: invokeinterface #142,  9          // InterfaceMethod org/scalatest/enablers/InspectorAsserting.forBetween:(IILscala/collection/Iterable;Ljava/lang/Object;ZLorg/scalactic/Prettifier;Lorg/scalactic/source/Position;Lscala/Function1;)Ljava/lang/Object;
        25: areturn
      LineNumberTable:
        line 501: 0
      LocalVariableTable:
        Start  Length  Slot  Name   Signature
            0      26     0  this   Lorg/scalatest/Inspectors;
            0      26     1  from   I
            0      26     2  upTo   I
            0      26     3    xs   Ljava/lang/Object;
            0      26     4   fun   Lscala/Function1;
            0      26     5 collecting   Lorg/scalatest/enablers/Collecting;
            0      26     6 asserting   Lorg/scalatest/enablers/InspectorAsserting;
            0      26     7 prettifier   Lorg/scalactic/Prettifier;
            0      26     8   pos   Lorg/scalactic/source/Position;
    Signature: #139                         // <E:Ljava/lang/Object;C:Ljava/lang/Object;ASSERTION:Ljava/lang/Object;>(IITC;Lscala/Function1<TE;TASSERTION;>;Lorg/scalatest/enablers/Collecting<TE;TC;>;Lorg/scalatest/enablers/InspectorAsserting<TASSERTION;>;Lorg/scalactic/Prettifier;Lorg/scalactic/source/Position;)Ljava/lang/Object;
    MethodParameters:
      Name                           Flags
      from                           final
      upTo                           final
      xs                             final
      fun                            final
      collecting                     final
      asserting                      final
      prettifier                     final
      pos                            final

  public static java.lang.Object forBetween$(org.scalatest.Inspectors, int, int, scala.collection.Map, scala.Function1, org.scalatest.enablers.Collecting, org.scalatest.enablers.InspectorAsserting, org.scalactic.Prettifier, org.scalactic.source.Position);
    descriptor: (Lorg/scalatest/Inspectors;IILscala/collection/Map;Lscala/Function1;Lorg/scalatest/enablers/Collecting;Lorg/scalatest/enablers/InspectorAsserting;Lorg/scalactic/Prettifier;Lorg/scalactic/source/Position;)Ljava/lang/Object;
    flags: (0x1009) ACC_PUBLIC, ACC_STATIC, ACC_SYNTHETIC
    Code:
      stack=9, locals=9, args_size=9
         0: aload_0
         1: iload_1
         2: iload_2
         3: aload_3
         4: aload         4
         6: aload         5
         8: aload         6
        10: aload         7
        12: aload         8
        14: invokespecial #146                // InterfaceMethod forBetween:(IILscala/collection/Map;Lscala/Function1;Lorg/scalatest/enablers/Collecting;Lorg/scalatest/enablers/InspectorAsserting;Lorg/scalactic/Prettifier;Lorg/scalactic/source/Position;)Ljava/lang/Object;
        17: areturn
      LineNumberTable:
        line 516: 0
      LocalVariableTable:
        Start  Length  Slot  Name   Signature
            0      18     0 $this   Lorg/scalatest/Inspectors;
            0      18     1  from   I
            0      18     2  upTo   I
            0      18     3    xs   Lscala/collection/Map;
            0      18     4   fun   Lscala/Function1;
            0      18     5 collecting   Lorg/scalatest/enablers/Collecting;
            0      18     6 asserting   Lorg/scalatest/enablers/InspectorAsserting;
            0      18     7 prettifier   Lorg/scalactic/Prettifier;
            0      18     8   pos   Lorg/scalactic/source/Position;
    MethodParameters:
      Name                           Flags
      $this                          final synthetic
      from                           final
      upTo                           final
      xs                             final
      fun                            final
      collecting                     final
      asserting                      final
      prettifier                     final
      pos                            final

  public default <K extends java.lang.Object, V extends java.lang.Object, MAP extends scala.collection.Map<java.lang.Object, java.lang.Object>, ASSERTION extends java.lang.Object> java.lang.Object forBetween(int, int, MAP, scala.Function1<scala.Tuple2<K, V>, ASSERTION>, org.scalatest.enablers.Collecting<scala.Tuple2<K, V>, scala.collection.Iterable<scala.Tuple2<K, V>>>, org.scalatest.enablers.InspectorAsserting<ASSERTION>, org.scalactic.Prettifier, org.scalactic.source.Position);
    descriptor: (IILscala/collection/Map;Lscala/Function1;Lorg/scalatest/enablers/Collecting;Lorg/scalatest/enablers/InspectorAsserting;Lorg/scalactic/Prettifier;Lorg/scalactic/source/Position;)Ljava/lang/Object;
    flags: (0x0001) ACC_PUBLIC
    Code:
      stack=9, locals=9, args_size=9
         0: aload         6
         2: iload_1
         3: iload_2
         4: aload         5
         6: aload_3
         7: invokeinterface #35,  2           // InterfaceMethod org/scalatest/enablers/Collecting.genTraversableFrom:(Ljava/lang/Object;)Lscala/collection/Iterable;
        12: aload_3
        13: iconst_0
        14: aload         7
        16: aload         8
        18: aload         4
        20: invokeinterface #142,  9          // InterfaceMethod org/scalatest/enablers/InspectorAsserting.forBetween:(IILscala/collection/Iterable;Ljava/lang/Object;ZLorg/scalactic/Prettifier;Lorg/scalactic/source/Position;Lscala/Function1;)Ljava/lang/Object;
        25: areturn
      LineNumberTable:
        line 517: 0
      LocalVariableTable:
        Start  Length  Slot  Name   Signature
            0      26     0  this   Lorg/scalatest/Inspectors;
            0      26     1  from   I
            0      26     2  upTo   I
            0      26     3    xs   Lscala/collection/Map;
            0      26     4   fun   Lscala/Function1;
            0      26     5 collecting   Lorg/scalatest/enablers/Collecting;
            0      26     6 asserting   Lorg/scalatest/enablers/InspectorAsserting;
            0      26     7 prettifier   Lorg/scalactic/Prettifier;
            0      26     8   pos   Lorg/scalactic/source/Position;
    Signature: #147                         // <K:Ljava/lang/Object;V:Ljava/lang/Object;MAP::Lscala/collection/Map<Ljava/lang/Object;Ljava/lang/Object;>;ASSERTION:Ljava/lang/Object;>(IITMAP;Lscala/Function1<Lscala/Tuple2<TK;TV;>;TASSERTION;>;Lorg/scalatest/enablers/Collecting<Lscala/Tuple2<TK;TV;>;Lscala/collection/Iterable<Lscala/Tuple2<TK;TV;>;>;>;Lorg/scalatest/enablers/InspectorAsserting<TASSERTION;>;Lorg/scalactic/Prettifier;Lorg/scalactic/source/Position;)Ljava/lang/Object;
    MethodParameters:
      Name                           Flags
      from                           final
      upTo                           final
      xs                             final
      fun                            final
      collecting                     final
      asserting                      final
      prettifier                     final
      pos                            final

  public static java.lang.Object forBetween$(org.scalatest.Inspectors, int, int, java.util.Map, scala.Function1, org.scalatest.enablers.Collecting, org.scalatest.enablers.InspectorAsserting, org.scalactic.Prettifier, org.scalactic.source.Position);
    descriptor: (Lorg/scalatest/Inspectors;IILjava/util/Map;Lscala/Function1;Lorg/scalatest/enablers/Collecting;Lorg/scalatest/enablers/InspectorAsserting;Lorg/scalactic/Prettifier;Lorg/scalactic/source/Position;)Ljava/lang/Object;
    flags: (0x1009) ACC_PUBLIC, ACC_STATIC, ACC_SYNTHETIC
    Code:
      stack=9, locals=9, args_size=9
         0: aload_0
         1: iload_1
         2: iload_2
         3: aload_3
         4: aload         4
         6: aload         5
         8: aload         6
        10: aload         7
        12: aload         8
        14: invokespecial #151                // InterfaceMethod forBetween:(IILjava/util/Map;Lscala/Function1;Lorg/scalatest/enablers/Collecting;Lorg/scalatest/enablers/InspectorAsserting;Lorg/scalactic/Prettifier;Lorg/scalactic/source/Position;)Ljava/lang/Object;
        17: areturn
      LineNumberTable:
        line 533: 0
      LocalVariableTable:
        Start  Length  Slot  Name   Signature
            0      18     0 $this   Lorg/scalatest/Inspectors;
            0      18     1  from   I
            0      18     2  upTo   I
            0      18     3    xs   Ljava/util/Map;
            0      18     4   fun   Lscala/Function1;
            0      18     5 collecting   Lorg/scalatest/enablers/Collecting;
            0      18     6 asserting   Lorg/scalatest/enablers/InspectorAsserting;
            0      18     7 prettifier   Lorg/scalactic/Prettifier;
            0      18     8   pos   Lorg/scalactic/source/Position;
    MethodParameters:
      Name                           Flags
      $this                          final synthetic
      from                           final
      upTo                           final
      xs                             final
      fun                            final
      collecting                     final
      asserting                      final
      prettifier                     final
      pos                            final

  public default <K extends java.lang.Object, V extends java.lang.Object, JMAP extends java.util.Map<java.lang.Object, java.lang.Object>, ASSERTION extends java.lang.Object> java.lang.Object forBetween(int, int, JMAP, scala.Function1<org.scalatest.Entry<K, V>, ASSERTION>, org.scalatest.enablers.Collecting<org.scalatest.Entry<K, V>, JMAP>, org.scalatest.enablers.InspectorAsserting<ASSERTION>, org.scalactic.Prettifier, org.scalactic.source.Position);
    descriptor: (IILjava/util/Map;Lscala/Function1;Lorg/scalatest/enablers/Collecting;Lorg/scalatest/enablers/InspectorAsserting;Lorg/scalactic/Prettifier;Lorg/scalactic/source/Position;)Ljava/lang/Object;
    flags: (0x0001) ACC_PUBLIC
    Code:
      stack=9, locals=9, args_size=9
         0: aload         6
         2: iload_1
         3: iload_2
         4: aload         5
         6: aload_3
         7: invokeinterface #35,  2           // InterfaceMethod org/scalatest/enablers/Collecting.genTraversableFrom:(Ljava/lang/Object;)Lscala/collection/Iterable;
        12: aload_3
        13: iconst_0
        14: aload         7
        16: aload         8
        18: aload         4
        20: invokeinterface #142,  9          // InterfaceMethod org/scalatest/enablers/InspectorAsserting.forBetween:(IILscala/collection/Iterable;Ljava/lang/Object;ZLorg/scalactic/Prettifier;Lorg/scalactic/source/Position;Lscala/Function1;)Ljava/lang/Object;
        25: areturn
      LineNumberTable:
        line 534: 0
      LocalVariableTable:
        Start  Length  Slot  Name   Signature
            0      26     0  this   Lorg/scalatest/Inspectors;
            0      26     1  from   I
            0      26     2  upTo   I
            0      26     3    xs   Ljava/util/Map;
            0      26     4   fun   Lscala/Function1;
            0      26     5 collecting   Lorg/scalatest/enablers/Collecting;
            0      26     6 asserting   Lorg/scalatest/enablers/InspectorAsserting;
            0      26     7 prettifier   Lorg/scalactic/Prettifier;
            0      26     8   pos   Lorg/scalactic/source/Position;
    Signature: #152                         // <K:Ljava/lang/Object;V:Ljava/lang/Object;JMAP::Ljava/util/Map<Ljava/lang/Object;Ljava/lang/Object;>;ASSERTION:Ljava/lang/Object;>(IITJMAP;Lscala/Function1<Lorg/scalatest/Entry<TK;TV;>;TASSERTION;>;Lorg/scalatest/enablers/Collecting<Lorg/scalatest/Entry<TK;TV;>;TJMAP;>;Lorg/scalatest/enablers/InspectorAsserting<TASSERTION;>;Lorg/scalactic/Prettifier;Lorg/scalactic/source/Position;)Ljava/lang/Object;
    MethodParameters:
      Name                           Flags
      from                           final
      upTo                           final
      xs                             final
      fun                            final
      collecting                     final
      asserting                      final
      prettifier                     final
      pos                            final

  public static java.lang.Object forBetween$(org.scalatest.Inspectors, int, int, java.lang.String, scala.Function1, org.scalatest.enablers.Collecting, org.scalatest.enablers.InspectorAsserting, org.scalactic.Prettifier, org.scalactic.source.Position);
    descriptor: (Lorg/scalatest/Inspectors;IILjava/lang/String;Lscala/Function1;Lorg/scalatest/enablers/Collecting;Lorg/scalatest/enablers/InspectorAsserting;Lorg/scalactic/Prettifier;Lorg/scalactic/source/Position;)Ljava/lang/Object;
    flags: (0x1009) ACC_PUBLIC, ACC_STATIC, ACC_SYNTHETIC
    Code:
      stack=9, locals=9, args_size=9
         0: aload_0
         1: iload_1
         2: iload_2
         3: aload_3
         4: aload         4
         6: aload         5
         8: aload         6
        10: aload         7
        12: aload         8
        14: invokespecial #156                // InterfaceMethod forBetween:(IILjava/lang/String;Lscala/Function1;Lorg/scalatest/enablers/Collecting;Lorg/scalatest/enablers/InspectorAsserting;Lorg/scalactic/Prettifier;Lorg/scalactic/source/Position;)Ljava/lang/Object;
        17: areturn
      LineNumberTable:
        line 547: 0
      LocalVariableTable:
        Start  Length  Slot  Name   Signature
            0      18     0 $this   Lorg/scalatest/Inspectors;
            0      18     1  from   I
            0      18     2  upTo   I
            0      18     3    xs   Ljava/lang/String;
            0      18     4   fun   Lscala/Function1;
            0      18     5 collecting   Lorg/scalatest/enablers/Collecting;
            0      18     6 asserting   Lorg/scalatest/enablers/InspectorAsserting;
            0      18     7 prettifier   Lorg/scalactic/Prettifier;
            0      18     8   pos   Lorg/scalactic/source/Position;
    MethodParameters:
      Name                           Flags
      $this                          final synthetic
      from                           final
      upTo                           final
      xs                             final
      fun                            final
      collecting                     final
      asserting                      final
      prettifier                     final
      pos                            final

  public default <ASSERTION extends java.lang.Object> java.lang.Object forBetween(int, int, java.lang.String, scala.Function1<java.lang.Object, ASSERTION>, org.scalatest.enablers.Collecting<java.lang.Object, java.lang.String>, org.scalatest.enablers.InspectorAsserting<ASSERTION>, org.scalactic.Prettifier, org.scalactic.source.Position);
    descriptor: (IILjava/lang/String;Lscala/Function1;Lorg/scalatest/enablers/Collecting;Lorg/scalatest/enablers/InspectorAsserting;Lorg/scalactic/Prettifier;Lorg/scalactic/source/Position;)Ljava/lang/Object;
    flags: (0x0001) ACC_PUBLIC
    Code:
      stack=9, locals=9, args_size=9
         0: aload         6
         2: iload_1
         3: iload_2
         4: aload         5
         6: aload_3
         7: invokeinterface #35,  2           // InterfaceMethod org/scalatest/enablers/Collecting.genTraversableFrom:(Ljava/lang/Object;)Lscala/collection/Iterable;
        12: aload_3
        13: iconst_0
        14: aload         7
        16: aload         8
        18: aload         4
        20: invokeinterface #142,  9          // InterfaceMethod org/scalatest/enablers/InspectorAsserting.forBetween:(IILscala/collection/Iterable;Ljava/lang/Object;ZLorg/scalactic/Prettifier;Lorg/scalactic/source/Position;Lscala/Function1;)Ljava/lang/Object;
        25: areturn
      LineNumberTable:
        line 548: 0
      LocalVariableTable:
        Start  Length  Slot  Name   Signature
            0      26     0  this   Lorg/scalatest/Inspectors;
            0      26     1  from   I
            0      26     2  upTo   I
            0      26     3    xs   Ljava/lang/String;
            0      26     4   fun   Lscala/Function1;
            0      26     5 collecting   Lorg/scalatest/enablers/Collecting;
            0      26     6 asserting   Lorg/scalatest/enablers/InspectorAsserting;
            0      26     7 prettifier   Lorg/scalactic/Prettifier;
            0      26     8   pos   Lorg/scalactic/source/Position;
    Signature: #157                         // <ASSERTION:Ljava/lang/Object;>(IILjava/lang/String;Lscala/Function1<Ljava/lang/Object;TASSERTION;>;Lorg/scalatest/enablers/Collecting<Ljava/lang/Object;Ljava/lang/String;>;Lorg/scalatest/enablers/InspectorAsserting<TASSERTION;>;Lorg/scalactic/Prettifier;Lorg/scalactic/source/Position;)Ljava/lang/Object;
    MethodParameters:
      Name                           Flags
      from                           final
      upTo                           final
      xs                             final
      fun                            final
      collecting                     final
      asserting                      final
      prettifier                     final
      pos                            final

  public static java.lang.Object forEvery$(org.scalatest.Inspectors, java.lang.Object, scala.Function1, org.scalatest.enablers.Collecting, org.scalatest.enablers.InspectorAsserting, org.scalactic.Prettifier, org.scalactic.source.Position);
    descriptor: (Lorg/scalatest/Inspectors;Ljava/lang/Object;Lscala/Function1;Lorg/scalatest/enablers/Collecting;Lorg/scalatest/enablers/InspectorAsserting;Lorg/scalactic/Prettifier;Lorg/scalactic/source/Position;)Ljava/lang/Object;
    flags: (0x1009) ACC_PUBLIC, ACC_STATIC, ACC_SYNTHETIC
    Code:
      stack=7, locals=7, args_size=7
         0: aload_0
         1: aload_1
         2: aload_2
         3: aload_3
         4: aload         4
         6: aload         5
         8: aload         6
        10: invokespecial #161                // InterfaceMethod forEvery:(Ljava/lang/Object;Lscala/Function1;Lorg/scalatest/enablers/Collecting;Lorg/scalatest/enablers/InspectorAsserting;Lorg/scalactic/Prettifier;Lorg/scalactic/source/Position;)Ljava/lang/Object;
        13: areturn
      LineNumberTable:
        line 567: 0
      LocalVariableTable:
        Start  Length  Slot  Name   Signature
            0      14     0 $this   Lorg/scalatest/Inspectors;
            0      14     1    xs   Ljava/lang/Object;
            0      14     2   fun   Lscala/Function1;
            0      14     3 collecting   Lorg/scalatest/enablers/Collecting;
            0      14     4 asserting   Lorg/scalatest/enablers/InspectorAsserting;
            0      14     5 prettifier   Lorg/scalactic/Prettifier;
            0      14     6   pos   Lorg/scalactic/source/Position;
    MethodParameters:
      Name                           Flags
      $this                          final synthetic
      xs                             final
      fun                            final
      collecting                     final
      asserting                      final
      prettifier                     final
      pos                            final

  public default <E extends java.lang.Object, C extends java.lang.Object, ASSERTION extends java.lang.Object> java.lang.Object forEvery(C, scala.Function1<E, ASSERTION>, org.scalatest.enablers.Collecting<E, C>, org.scalatest.enablers.InspectorAsserting<ASSERTION>, org.scalactic.Prettifier, org.scalactic.source.Position);
    descriptor: (Ljava/lang/Object;Lscala/Function1;Lorg/scalatest/enablers/Collecting;Lorg/scalatest/enablers/InspectorAsserting;Lorg/scalactic/Prettifier;Lorg/scalactic/source/Position;)Ljava/lang/Object;
    flags: (0x0001) ACC_PUBLIC
    Code:
      stack=7, locals=7, args_size=7
         0: aload         4
         2: aload_3
         3: aload_1
         4: invokeinterface #35,  2           // InterfaceMethod org/scalatest/enablers/Collecting.genTraversableFrom:(Ljava/lang/Object;)Lscala/collection/Iterable;
         9: aload_1
        10: iconst_0
        11: aload         5
        13: aload         6
        15: aload_2
        16: invokeinterface #163,  7          // InterfaceMethod org/scalatest/enablers/InspectorAsserting.forEvery:(Lscala/collection/Iterable;Ljava/lang/Object;ZLorg/scalactic/Prettifier;Lorg/scalactic/source/Position;Lscala/Function1;)Ljava/lang/Object;
        21: areturn
      LineNumberTable:
        line 568: 0
      LocalVariableTable:
        Start  Length  Slot  Name   Signature
            0      22     0  this   Lorg/scalatest/Inspectors;
            0      22     1    xs   Ljava/lang/Object;
            0      22     2   fun   Lscala/Function1;
            0      22     3 collecting   Lorg/scalatest/enablers/Collecting;
            0      22     4 asserting   Lorg/scalatest/enablers/InspectorAsserting;
            0      22     5 prettifier   Lorg/scalactic/Prettifier;
            0      22     6   pos   Lorg/scalactic/source/Position;
    Signature: #29                          // <E:Ljava/lang/Object;C:Ljava/lang/Object;ASSERTION:Ljava/lang/Object;>(TC;Lscala/Function1<TE;TASSERTION;>;Lorg/scalatest/enablers/Collecting<TE;TC;>;Lorg/scalatest/enablers/InspectorAsserting<TASSERTION;>;Lorg/scalactic/Prettifier;Lorg/scalactic/source/Position;)Ljava/lang/Object;
    MethodParameters:
      Name                           Flags
      xs                             final
      fun                            final
      collecting                     final
      asserting                      final
      prettifier                     final
      pos                            final

  public static java.lang.Object forEvery$(org.scalatest.Inspectors, scala.collection.Map, scala.Function1, org.scalatest.enablers.Collecting, org.scalatest.enablers.InspectorAsserting, org.scalactic.Prettifier, org.scalactic.source.Position);
    descriptor: (Lorg/scalatest/Inspectors;Lscala/collection/Map;Lscala/Function1;Lorg/scalatest/enablers/Collecting;Lorg/scalatest/enablers/InspectorAsserting;Lorg/scalactic/Prettifier;Lorg/scalactic/source/Position;)Ljava/lang/Object;
    flags: (0x1009) ACC_PUBLIC, ACC_STATIC, ACC_SYNTHETIC
    Code:
      stack=7, locals=7, args_size=7
         0: aload_0
         1: aload_1
         2: aload_2
         3: aload_3
         4: aload         4
         6: aload         5
         8: aload         6
        10: invokespecial #165                // InterfaceMethod forEvery:(Lscala/collection/Map;Lscala/Function1;Lorg/scalatest/enablers/Collecting;Lorg/scalatest/enablers/InspectorAsserting;Lorg/scalactic/Prettifier;Lorg/scalactic/source/Position;)Ljava/lang/Object;
        13: areturn
      LineNumberTable:
        line 588: 0
      LocalVariableTable:
        Start  Length  Slot  Name   Signature
            0      14     0 $this   Lorg/scalatest/Inspectors;
            0      14     1    xs   Lscala/collection/Map;
            0      14     2   fun   Lscala/Function1;
            0      14     3 collecting   Lorg/scalatest/enablers/Collecting;
            0      14     4 asserting   Lorg/scalatest/enablers/InspectorAsserting;
            0      14     5 prettifier   Lorg/scalactic/Prettifier;
            0      14     6   pos   Lorg/scalactic/source/Position;
    MethodParameters:
      Name                           Flags
      $this                          final synthetic
      xs                             final
      fun                            final
      collecting                     final
      asserting                      final
      prettifier                     final
      pos                            final

  public default <K extends java.lang.Object, V extends java.lang.Object, MAP extends scala.collection.Map<java.lang.Object, java.lang.Object>, ASSERTION extends java.lang.Object> java.lang.Object forEvery(MAP, scala.Function1<scala.Tuple2<K, V>, ASSERTION>, org.scalatest.enablers.Collecting<scala.Tuple2<K, V>, scala.collection.Iterable<scala.Tuple2<K, V>>>, org.scalatest.enablers.InspectorAsserting<ASSERTION>, org.scalactic.Prettifier, org.scalactic.source.Position);
    descriptor: (Lscala/collection/Map;Lscala/Function1;Lorg/scalatest/enablers/Collecting;Lorg/scalatest/enablers/InspectorAsserting;Lorg/scalactic/Prettifier;Lorg/scalactic/source/Position;)Ljava/lang/Object;
    flags: (0x0001) ACC_PUBLIC
    Code:
      stack=7, locals=7, args_size=7
         0: aload         4
         2: aload_3
         3: aload_1
         4: invokeinterface #35,  2           // InterfaceMethod org/scalatest/enablers/Collecting.genTraversableFrom:(Ljava/lang/Object;)Lscala/collection/Iterable;
         9: aload_1
        10: iconst_0
        11: aload         5
        13: aload         6
        15: aload_2
        16: invokeinterface #163,  7          // InterfaceMethod org/scalatest/enablers/InspectorAsserting.forEvery:(Lscala/collection/Iterable;Ljava/lang/Object;ZLorg/scalactic/Prettifier;Lorg/scalactic/source/Position;Lscala/Function1;)Ljava/lang/Object;
        21: areturn
      LineNumberTable:
        line 589: 0
      LocalVariableTable:
        Start  Length  Slot  Name   Signature
            0      22     0  this   Lorg/scalatest/Inspectors;
            0      22     1    xs   Lscala/collection/Map;
            0      22     2   fun   Lscala/Function1;
            0      22     3 collecting   Lorg/scalatest/enablers/Collecting;
            0      22     4 asserting   Lorg/scalatest/enablers/InspectorAsserting;
            0      22     5 prettifier   Lorg/scalactic/Prettifier;
            0      22     6   pos   Lorg/scalactic/source/Position;
    Signature: #47                          // <K:Ljava/lang/Object;V:Ljava/lang/Object;MAP::Lscala/collection/Map<Ljava/lang/Object;Ljava/lang/Object;>;ASSERTION:Ljava/lang/Object;>(TMAP;Lscala/Function1<Lscala/Tuple2<TK;TV;>;TASSERTION;>;Lorg/scalatest/enablers/Collecting<Lscala/Tuple2<TK;TV;>;Lscala/collection/Iterable<Lscala/Tuple2<TK;TV;>;>;>;Lorg/scalatest/enablers/InspectorAsserting<TASSERTION;>;Lorg/scalactic/Prettifier;Lorg/scalactic/source/Position;)Ljava/lang/Object;
    MethodParameters:
      Name                           Flags
      xs                             final
      fun                            final
      collecting                     final
      asserting                      final
      prettifier                     final
      pos                            final

  public static java.lang.Object forEvery$(org.scalatest.Inspectors, java.util.Map, scala.Function1, org.scalatest.enablers.Collecting, org.scalatest.enablers.InspectorAsserting, org.scalactic.Prettifier, org.scalactic.source.Position);
    descriptor: (Lorg/scalatest/Inspectors;Ljava/util/Map;Lscala/Function1;Lorg/scalatest/enablers/Collecting;Lorg/scalatest/enablers/InspectorAsserting;Lorg/scalactic/Prettifier;Lorg/scalactic/source/Position;)Ljava/lang/Object;
    flags: (0x1009) ACC_PUBLIC, ACC_STATIC, ACC_SYNTHETIC
    Code:
      stack=7, locals=7, args_size=7
         0: aload_0
         1: aload_1
         2: aload_2
         3: aload_3
         4: aload         4
         6: aload         5
         8: aload         6
        10: invokespecial #167                // InterfaceMethod forEvery:(Ljava/util/Map;Lscala/Function1;Lorg/scalatest/enablers/Collecting;Lorg/scalatest/enablers/InspectorAsserting;Lorg/scalactic/Prettifier;Lorg/scalactic/source/Position;)Ljava/lang/Object;
        13: areturn
      LineNumberTable:
        line 610: 0
      LocalVariableTable:
        Start  Length  Slot  Name   Signature
            0      14     0 $this   Lorg/scalatest/Inspectors;
            0      14     1    xs   Ljava/util/Map;
            0      14     2   fun   Lscala/Function1;
            0      14     3 collecting   Lorg/scalatest/enablers/Collecting;
            0      14     4 asserting   Lorg/scalatest/enablers/InspectorAsserting;
            0      14     5 prettifier   Lorg/scalactic/Prettifier;
            0      14     6   pos   Lorg/scalactic/source/Position;
    MethodParameters:
      Name                           Flags
      $this                          final synthetic
      xs                             final
      fun                            final
      collecting                     final
      asserting                      final
      prettifier                     final
      pos                            final

  public default <K extends java.lang.Object, V extends java.lang.Object, JMAP extends java.util.Map<java.lang.Object, java.lang.Object>, ASSERTION extends java.lang.Object> java.lang.Object forEvery(JMAP, scala.Function1<org.scalatest.Entry<K, V>, ASSERTION>, org.scalatest.enablers.Collecting<org.scalatest.Entry<K, V>, JMAP>, org.scalatest.enablers.InspectorAsserting<ASSERTION>, org.scalactic.Prettifier, org.scalactic.source.Position);
    descriptor: (Ljava/util/Map;Lscala/Function1;Lorg/scalatest/enablers/Collecting;Lorg/scalatest/enablers/InspectorAsserting;Lorg/scalactic/Prettifier;Lorg/scalactic/source/Position;)Ljava/lang/Object;
    flags: (0x0001) ACC_PUBLIC
    Code:
      stack=7, locals=7, args_size=7
         0: aload         4
         2: aload_3
         3: aload_1
         4: invokeinterface #35,  2           // InterfaceMethod org/scalatest/enablers/Collecting.genTraversableFrom:(Ljava/lang/Object;)Lscala/collection/Iterable;
         9: aload_1
        10: iconst_0
        11: aload         5
        13: aload         6
        15: aload_2
        16: invokeinterface #163,  7          // InterfaceMethod org/scalatest/enablers/InspectorAsserting.forEvery:(Lscala/collection/Iterable;Ljava/lang/Object;ZLorg/scalactic/Prettifier;Lorg/scalactic/source/Position;Lscala/Function1;)Ljava/lang/Object;
        21: areturn
      LineNumberTable:
        line 611: 0
      LocalVariableTable:
        Start  Length  Slot  Name   Signature
            0      22     0  this   Lorg/scalatest/Inspectors;
            0      22     1    xs   Ljava/util/Map;
            0      22     2   fun   Lscala/Function1;
            0      22     3 collecting   Lorg/scalatest/enablers/Collecting;
            0      22     4 asserting   Lorg/scalatest/enablers/InspectorAsserting;
            0      22     5 prettifier   Lorg/scalactic/Prettifier;
            0      22     6   pos   Lorg/scalactic/source/Position;
    Signature: #53                          // <K:Ljava/lang/Object;V:Ljava/lang/Object;JMAP::Ljava/util/Map<Ljava/lang/Object;Ljava/lang/Object;>;ASSERTION:Ljava/lang/Object;>(TJMAP;Lscala/Function1<Lorg/scalatest/Entry<TK;TV;>;TASSERTION;>;Lorg/scalatest/enablers/Collecting<Lorg/scalatest/Entry<TK;TV;>;TJMAP;>;Lorg/scalatest/enablers/InspectorAsserting<TASSERTION;>;Lorg/scalactic/Prettifier;Lorg/scalactic/source/Position;)Ljava/lang/Object;
    MethodParameters:
      Name                           Flags
      xs                             final
      fun                            final
      collecting                     final
      asserting                      final
      prettifier                     final
      pos                            final

  public static java.lang.Object forEvery$(org.scalatest.Inspectors, java.lang.String, scala.Function1, org.scalatest.enablers.Collecting, org.scalatest.enablers.InspectorAsserting, org.scalactic.Prettifier, org.scalactic.source.Position);
    descriptor: (Lorg/scalatest/Inspectors;Ljava/lang/String;Lscala/Function1;Lorg/scalatest/enablers/Collecting;Lorg/scalatest/enablers/InspectorAsserting;Lorg/scalactic/Prettifier;Lorg/scalactic/source/Position;)Ljava/lang/Object;
    flags: (0x1009) ACC_PUBLIC, ACC_STATIC, ACC_SYNTHETIC
    Code:
      stack=7, locals=7, args_size=7
         0: aload_0
         1: aload_1
         2: aload_2
         3: aload_3
         4: aload         4
         6: aload         5
         8: aload         6
        10: invokespecial #169                // InterfaceMethod forEvery:(Ljava/lang/String;Lscala/Function1;Lorg/scalatest/enablers/Collecting;Lorg/scalatest/enablers/InspectorAsserting;Lorg/scalactic/Prettifier;Lorg/scalactic/source/Position;)Ljava/lang/Object;
        13: areturn
      LineNumberTable:
        line 629: 0
      LocalVariableTable:
        Start  Length  Slot  Name   Signature
            0      14     0 $this   Lorg/scalatest/Inspectors;
            0      14     1    xs   Ljava/lang/String;
            0      14     2   fun   Lscala/Function1;
            0      14     3 collecting   Lorg/scalatest/enablers/Collecting;
            0      14     4 asserting   Lorg/scalatest/enablers/InspectorAsserting;
            0      14     5 prettifier   Lorg/scalactic/Prettifier;
            0      14     6   pos   Lorg/scalactic/source/Position;
    MethodParameters:
      Name                           Flags
      $this                          final synthetic
      xs                             final
      fun                            final
      collecting                     final
      asserting                      final
      prettifier                     final
      pos                            final

  public default <ASSERTION extends java.lang.Object> java.lang.Object forEvery(java.lang.String, scala.Function1<java.lang.Object, ASSERTION>, org.scalatest.enablers.Collecting<java.lang.Object, java.lang.String>, org.scalatest.enablers.InspectorAsserting<ASSERTION>, org.scalactic.Prettifier, org.scalactic.source.Position);
    descriptor: (Ljava/lang/String;Lscala/Function1;Lorg/scalatest/enablers/Collecting;Lorg/scalatest/enablers/InspectorAsserting;Lorg/scalactic/Prettifier;Lorg/scalactic/source/Position;)Ljava/lang/Object;
    flags: (0x0001) ACC_PUBLIC
    Code:
      stack=7, locals=7, args_size=7
         0: aload         4
         2: aload_3
         3: aload_1
         4: invokeinterface #35,  2           // InterfaceMethod org/scalatest/enablers/Collecting.genTraversableFrom:(Ljava/lang/Object;)Lscala/collection/Iterable;
         9: aload_1
        10: iconst_0
        11: aload         5
        13: aload         6
        15: aload_2
        16: invokeinterface #163,  7          // InterfaceMethod org/scalatest/enablers/InspectorAsserting.forEvery:(Lscala/collection/Iterable;Ljava/lang/Object;ZLorg/scalactic/Prettifier;Lorg/scalactic/source/Position;Lscala/Function1;)Ljava/lang/Object;
        21: areturn
      LineNumberTable:
        line 630: 0
      LocalVariableTable:
        Start  Length  Slot  Name   Signature
            0      22     0  this   Lorg/scalatest/Inspectors;
            0      22     1    xs   Ljava/lang/String;
            0      22     2   fun   Lscala/Function1;
            0      22     3 collecting   Lorg/scalatest/enablers/Collecting;
            0      22     4 asserting   Lorg/scalatest/enablers/InspectorAsserting;
            0      22     5 prettifier   Lorg/scalactic/Prettifier;
            0      22     6   pos   Lorg/scalactic/source/Position;
    Signature: #59                          // <ASSERTION:Ljava/lang/Object;>(Ljava/lang/String;Lscala/Function1<Ljava/lang/Object;TASSERTION;>;Lorg/scalatest/enablers/Collecting<Ljava/lang/Object;Ljava/lang/String;>;Lorg/scalatest/enablers/InspectorAsserting<TASSERTION;>;Lorg/scalactic/Prettifier;Lorg/scalactic/source/Position;)Ljava/lang/Object;
    MethodParameters:
      Name                           Flags
      xs                             final
      fun                            final
      collecting                     final
      asserting                      final
      prettifier                     final
      pos                            final

  public static void $init$(org.scalatest.Inspectors);
    descriptor: (Lorg/scalatest/Inspectors;)V
    flags: (0x0009) ACC_PUBLIC, ACC_STATIC
    Code:
      stack=0, locals=1, args_size=1
         0: return
      LineNumberTable:
        line 202: 0
      LocalVariableTable:
        Start  Length  Slot  Name   Signature
            0       1     0 $this   Lorg/scalatest/Inspectors;
    MethodParameters:
      Name                           Flags
      $this                          final synthetic
}
SourceFile: "Inspectors.scala"
RuntimeVisibleAnnotations:
  0: #6(#7=s#8)
    scala.reflect.ScalaSignature(
      bytes="\u0006\u0005\u001deaa\u0002\u0012$!\u0003\r\t\u0001\u000b\u0005\u0006_\u0001!\t\u0001\r\u0005\u0006i\u0001!\t!\u000e\u0005\u0006i\u0001!\t!\u001e\u0005\u0007i\u0001!\t!a\u0017\t\rQ\u0002A\u0011AAX\u0011\u001d\t9\u000f\u0001C\u0001\u0003SDq!a:\u0001\t\u0003\u0011\t\u0003C\u0004\u0002h\u0002!\tAa\u0019\t\u000f\u0005\u001d\b\u0001\"\u0001\u0003$\"9!Q\u0019\u0001\u0005\n\t\u001d\u0007b\u0002Bp\u0001\u0011\u0005!\u0011\u001d\u0005\b\u0005?\u0004A\u0011AB\n\u0011\u001d\u0011y\u000e\u0001C\u0001\u0007+BqAa8\u0001\t\u0003\u0019)\nC\u0004\u00048\u0002!\ta!/\t\u000f\r]\u0006\u0001\"\u0001\u0004l\"91q\u0017\u0001\u0005\u0002\u00115\u0002bBB\\\u0001\u0011\u0005AQ\u000e\u0005\t\t\u001f\u0003A\u0011A\u0012\u0005\u0012\"AAq\u0012\u0001\u0005\u0002\r\"y\f\u0003\u0005\u0005\u0010\u0002!\ta\tC\u0000\u0011!!y\t\u0001C\u0001G\u0015u\u0002bBC/\u0001\u0011\u0005Qq\f\u0005\b\u000b;\u0002A\u0011ACK\u0011\u001d)i\u0006\u0001C\u0001\u000b3Dq!\"\u0018\u0001\t\u00031Y\u0002C\u0004\u0007@\u0001!\tA\"\u0011\t\u000f\u0019}\u0002\u0001\"\u0001\u0007p!9aq\b\u0001\u0005\u0002\u0019=\u0006b\u0002D \u0001\u0011\u0005aQ^\u0004\b\u000f\u001b\u0019\u0003\u0012AD\b\r\u0019\u00113\u0005#\u0001\b\u0012!9qQ\u0003\u0011\u0005\u0002\u001d]!AC%ogB,7\r^8sg*\u0011A%J\u0001\ng\u000e\fG.\u0019;fgRT\u0011AJ\u0001\u0004_J<7\u0001A\n\u0003\u0001%\u0002\"AK\u0017\u000e\u0003-R\u0011\u0001L\u0001\u0006g\u000e\fG.Y\u0005\u0003]-\u0012a!\u00118z%\u00164\u0017A\u0002\u0013j]&$H\u0005F\u00012!\tQ#\'\u0003\u00024W\t!QK\\5u\u0003\u00191wN]!mYV!aGV-F)\t94\u000f\u0006\u00029]R)\u0011\b\u0015\u001f_MB\u0011!H\u0014\b\u0003wqb\u0001\u0001C\u0003>\u0005\u0001\u000fa(A\u0005bgN,\'\u000f^5oOB\u0019qH\u0011#\u000e\u0003\u0001S!!Q\u0012\u0002\u0011\u0015t\u0017M\u00197feNL!a\u0011!\u0003%%s7\u000f]3di>\u0014\u0018i]:feRLgn\u001a\t\u0003w\u0015#QA\u0012\u0002C\u0002\u001d\u0013\u0011\"Q*T\u000bJ#\u0016j\u0014(\u0012\u0005![\u0005C\u0001\u0016J\u0013\tQ5FA\u0004O_RD\u0017N\\4\u0011\u0005)b\u0015BA\',\u0005\r\te._\u0005\u0003\u001f\n\u0013aAU3tk2$\b\"B)\u0003\u0001\b\u0011\u0016AC2pY2,7\r^5oOB!qhU+Y\u0013\t!\u0006I\u0001\u0006D_2dWm\u0019;j]\u001e\u0004\"a\u000f,\u0005\u000b]\u0013!\u0019A$\u0003\u0003\u0015\u00032aO-V\t\u0015Q&A1\u0001\\\u0005\u0005\u0019UCA$]\t\u0015i\u0016L1\u0001H\u0005\u0005y\u0006\"B0\u0003\u0001\b\u0001\u0017A\u00039sKR$\u0018NZ5feB\u0011\u0011\rZ\u0007\u0002E*\u00111-J\u0001\ng\u000e\fG.Y2uS\u000eL!!\u001a2\u0003\u0015A\u0013X\r\u001e;jM&,\'\u000fC\u0003h\u0005\u0001\u000f\u0001.A\u0002q_N\u0004\"!\u001b7\u000e\u0003)T!a\u001b2\u0002\rM|WO]2f\u0013\ti\'N\u0001\u0005Q_NLG/[8o\u0011\u0015y\'\u00011\u0001q\u0003\r1WO\u001c\t\u0005UE,F)\u0003\u0002sW\tIa)\u001e8di&|g.\r\u0005\u0006i\n\u0001\r\u0001W\u0001\u0003qN,\u0002B^A\u0006\u0003#\t\tE \u000b\u0004o\u0006uBc\u0001=\u0002:Q9\u0011p`>\u00026\u0005]\u0002C\u0001>O\u001d\tY4\u0010C\u0003>\u0007\u0001\u000fA\u0010E\u0002@\u0005v\u0004\"a\u000f@\u0005\u000b\u0019\u001b!\u0019A$\t\rE\u001b\u00019AA\u0001!\u0019y4+a\u0001\u0002\u0016A9!&!\u0002\u0002\n\u0005=\u0011bAA\u0004W\t1A+\u001e9mKJ\u00022aOA\u0006\t\u0019\tia\u0001b\u0001\u000f\n\t1\nE\u0002<\u0003#!a!a\u0005\u0004\u0005\u00049%!\u0001,\u0011\r\u0005]\u0011qFA\u0002\u001d\u0011\tI\"!\u000b\u000f\t\u0005m\u0011Q\u0005\b\u0005\u0003;\t\u0019#\u0004\u0002\u0002 )\u0019\u0011\u0011E\u0014\u0002\rq\u0012xn\u001c;?\u0013\u0005a\u0013bAA\u0014W\u0005Q1m\u001c7mK\u000e$\u0018n\u001c8\n\t\u0005-\u0012QF\u0001\ba\u0006\u001c7.Y4f\u0015\r\t9cK\u0005\u0005\u0003c\t\u0019D\u0001\bHK:$&/\u0019<feN\f\'\r\\3\u000b\t\u0005-\u0012Q\u0006\u0005\u0006?\u000e\u0001\u001d\u0001\u0019\u0005\u0006O\u000e\u0001\u001d\u0001\u001b\u0005\u0007_\u000e\u0001\r!a\u000f\u0011\u000b)\n\u00181A?\t\rQ\u001c\u0001\u0019AA !\u001dY\u0014\u0011IA\u0005\u0003\u001f!q!a\u0011\u0004\u0005\u0004\t)EA\u0002N\u0003B+b!a\u0012\u0002R\u0005]\u0013c\u0001%\u0002JAA\u0011qCA&\u0003\u001f\n)&\u0003\u0003\u0002N\u0005M\"AB$f]6\u000b\u0007\u000fE\u0002<\u0003#\"q!a\u0015\u0002B\t\u0007qIA\u0001l!\rY\u0014q\u000b\u0003\b\u00033\n\tE1\u0001H\u0005\u00051XCCA/\u0003{\n\t)!\"\u0002nQ!\u0011qLAW)\u0011\t\t\'!+\u0015\u0015\u0005\r\u0014qNA4\u0003K\u000b9\u000bE\u0002\u0002f9s1aOA4\u0011\u0019iD\u0001q\u0001\u0002jA!qHQA6!\rY\u0014Q\u000e\u0003\u0006\r\u0012\u0011\ra\u0012\u0005\u0007#\u0012\u0001\u001d!!\u001d\u0011\r}\u001a\u00161OAB!!\t)(a\u001e\u0002|\u0005}T\"A\u0012\n\u0007\u0005e4EA\u0003F]R\u0014\u0018\u0010E\u0002<\u0003{\"a!!\u0004\u0005\u0005\u00049\u0005cA\u001e\u0002\u0002\u00121\u00111\u0003\u0003C\u0002\u001d\u0003raOAC\u0003w\ny\bB\u0004\u0002\b\u0012\u0011\r!!#\u0003\t)k\u0015\tU\u000b\u0007\u0003\u0017\u000by*a)\u0012\u0007!\u000bi\t\u0005\u0005\u0002\u0010\u0006e\u0015QTAQ\u001b\t\t\tJ\u0003\u0003\u0002\u0014\u0006U\u0015\u0001B;uS2T!!a&\u0002\t)\fg/Y\u0005\u0005\u00037\u000b\tJA\u0002NCB\u00042aOAP\t\u001d\t\u0019&!\"C\u0002\u001d\u00032aOAR\t\u001d\tI&!\"C\u0002\u001dCQa\u0018\u0003A\u0004\u0001DQa\u001a\u0003A\u0004!Daa\u001c\u0003A\u0002\u0005-\u0006C\u0002\u0016r\u0003g\nY\u0007\u0003\u0004u\t\u0001\u0007\u00111Q\u000b\u0005\u0003c\u000b\t\r\u0006\u0003\u00024\u0006\u0015H\u0003BA[\u0003C$\"\"a.\u0002D\u0006m\u0016Q\\Ap!\r\tIL\u0014\b\u0004w\u0005m\u0006BB\u001f\u0006\u0001\b\ti\f\u0005\u0003@\u0005\u0006}\u0006cA\u001e\u0002B\u0012)a)\u0002b\u0001\u000f\"1\u0011+\u0002a\u0002\u0003\u000b\u0004baP*\u0002H\u00065\u0007c\u0001\u0016\u0002J&\u0019\u00111Z\u0016\u0003\t\rC\u0017M\u001d\t\u0005\u0003\u001f\f9N\u0004\u0003\u0002R\u0006M\u0007cAA\u000fW%\u0019\u0011Q[\u0016\u0002\rA\u0013X\rZ3g\u0013\u0011\tI.a7\u0003\rM#(/\u001b8h\u0015\r\t)n\u000b\u0005\u0006?\u0016\u0001\u001d\u0001\u0019\u0005\u0006O\u0016\u0001\u001d\u0001\u001b\u0005\u0007_\u0016\u0001\r!a9\u0011\r)\n\u0018qYA`\u0011\u0019!X\u00011\u0001\u0002N\u0006Qam\u001c:Bi2+\u0017m\u001d;\u0016\u0011\u0005-(1\u0001B\u0004\u0003w$b!!<\u0003\u0016\t}A\u0003BAx\u0005#!\"\"!=\u0002~\u0006U(Q\u0002B\b!\r\t\u0019P\u0014\b\u0004w\u0005U\bBB\u001f\u0007\u0001\b\t9\u0010\u0005\u0003@\u0005\u0006e\bcA\u001e\u0002|\u0012)aI\u0002b\u0001\u000f\"1\u0011K\u0002a\u0002\u0003\u007f\u0004baP*\u0003\u0002\t\u0015\u0001cA\u001e\u0003\u0004\u0011)qK\u0002b\u0001\u000fB)1Ha\u0002\u0003\u0002\u00111!L\u0002b\u0001\u0005\u0013)2a\u0012B\u0006\t\u0019i&q\u0001b\u0001\u000f\")qL\u0002a\u0002A\")qM\u0002a\u0002Q\"1qN\u0002a\u0001\u0005\'\u0001bAK9\u0003\u0002\u0005e\bb\u0002B\f\r\u0001\u0007!\u0011D\u0001\u0004[&t\u0007c\u0001\u0016\u0003\u001c%\u0019!QD\u0016\u0003\u0007%sG\u000f\u0003\u0004u\r\u0001\u0007!QA\u000b\u000b\u0005G\u0011iD!\u0011\u0003T\tMBC\u0002B\u0013\u0005\u001b\u0012y\u0005\u0006\u0003\u0003(\t%CC\u0003B\u0015\u0005k\u0011iC!\u0012\u0003HA\u0019!1\u0006(\u000f\u0007m\u0012i\u0003\u0003\u0004>\u000f\u0001\u000f!q\u0006\t\u0005\u007f\t\u0013\t\u0004E\u0002<\u0005g!QAR\u0004C\u0002\u001dCa!U\u0004A\u0004\t]\u0002CB T\u0005s\u0011\u0019\u0005E\u0004+\u0003\u000b\u0011YDa\u0010\u0011\u0007m\u0012i\u0004\u0002\u0004\u0002\u000e\u001d\u0011\ra\u0012\t\u0004w\t\u0005CABA\n\u000f\t\u0007q\t\u0005\u0004\u0002\u0018\u0005=\"\u0011\b\u0005\u0006?\u001e\u0001\u001d\u0001\u0019\u0005\u0006O\u001e\u0001\u001d\u0001\u001b\u0005\u0007_\u001e\u0001\rAa\u0013\u0011\r)\n(\u0011\bB\u0019\u0011\u001d\u00119b\u0002a\u0001\u00053Aa\u0001^\u0004A\u0002\tE\u0003cB\u001e\u0003T\tm\"q\b\u0003\b\u0003\u0007:!\u0019\u0001B++\u0019\u00119F!\u0018\u0003bE\u0019\u0001J!\u0017\u0011\u0011\u0005]\u00111\nB.\u0005?\u00022a\u000fB/\t\u001d\t\u0019Fa\u0015C\u0002\u001d\u00032a\u000fB1\t\u001d\tIFa\u0015C\u0002\u001d+\"B!\u001a\u0003\u0000\t\r%q\u0011B;)\u0019\u00119Ga(\u0003\"R!!\u0011\u000eBN))\u0011YGa\u001e\u0003p\t]%\u0011\u0014\t\u0004\u0005[rebA\u001e\u0003p!1Q\b\u0003a\u0002\u0005c\u0002Ba\u0010\"\u0003tA\u00191H!\u001e\u0005\u000b\u0019C!\u0019A$\t\rEC\u00019\u0001B=!\u0019y4Ka\u001f\u0003\u0006BA\u0011QOA<\u0005{\u0012\t\tE\u0002<\u0005\u007f\"a!!\u0004\t\u0005\u00049\u0005cA\u001e\u0003\u0004\u00121\u00111\u0003\u0005C\u0002\u001d\u0003ra\u000fBD\u0005{\u0012\t\tB\u0004\u0002\b\"\u0011\rA!#\u0016\r\t-%\u0011\u0013BK#\rA%Q\u0012\t\t\u0003\u001f\u000bIJa$\u0003\u0014B\u00191H!%\u0005\u000f\u0005M#q\u0011b\u0001\u000fB\u00191H!&\u0005\u000f\u0005e#q\u0011b\u0001\u000f\")q\f\u0003a\u0002A\")q\r\u0003a\u0002Q\"1q\u000e\u0003a\u0001\u0005;\u0003bAK9\u0003|\tM\u0004b\u0002B\f\u0011\u0001\u0007!\u0011\u0004\u0005\u0007i\"\u0001\rA!\"\u0016\t\t\u0015&Q\u0017\u000b\u0007\u0005O\u0013\tMa1\u0015\t\t%&Q\u0018\u000b\u000b\u0005W\u00139La,\u0003:\nm\u0006c\u0001BW\u001d:\u00191Ha,\t\ruJ\u00019\u0001BY!\u0011y$Ia-\u0011\u0007m\u0012)\fB\u0003G\u0013\t\u0007q\t\u0003\u0004R\u0013\u0001\u000f\u0011Q\u0019\u0005\u0006?&\u0001\u001d\u0001\u0019\u0005\u0006O&\u0001\u001d\u0001\u001b\u0005\u0007_&\u0001\rAa0\u0011\r)\n\u0018q\u0019BZ\u0011\u001d\u00119\"\u0003a\u0001\u00053Aa\u0001^\u0005A\u0002\u00055\u0017AE:i_VdG-\u00138dYV$W-\u00138eKb,bA!3\u0003X\nmG\u0003\u0002Bf\u0005#\u00042A\u000bBg\u0013\r\u0011ym\u000b\u0002\b\u0005>|G.Z1o\u0011\u0019!(\u00021\u0001\u0003TB1\u0011qCA\u0018\u0005+\u00042a\u000fBl\t\u0019\u0011IN\u0003b\u0001\u000f\n\tA\u000b\u0002\u0004\u0003^*\u0011\ra\u0012\u0002\u0002%\u0006Iam\u001c:Bi6{7\u000f^\u000b\t\u0005G\u0014YPa@\u0003tR1!Q]B\u0007\u0007#!BAa:\u0004\nQQ!\u0011\u001eB{\u0005[\u001c)aa\u0002\u0011\u0007\t-hJD\u0002<\u0005[Da!P\u0006A\u0004\t=\b\u0003B C\u0005c\u00042a\u000fBz\t\u001515B1\u0001H\u0011\u0019\t6\u0002q\u0001\u0003xB1qh\u0015B}\u0005{\u00042a\u000fB~\t\u001596B1\u0001H!\u0015Y$q B}\t\u0019Q6B1\u0001\u0004\u0002U\u0019qia\u0001\u0005\ru\u0013yP1\u0001H\u0011\u0015y6\u0002q\u0001a\u0011\u001597\u0002q\u0001i\u0011\u0019y7\u00021\u0001\u0004\fA1!&\u001dB}\u0005cDqaa\u0004\f\u0001\u0004\u0011I\"A\u0002nCbDa\u0001^\u0006A\u0002\tuXCCB\u000b\u0007_\u0019\u0019d!\u0012\u0004&Q11qCB \u0007\u0003\"Ba!\u0007\u0004<QQ11DB\u0014\u0007?\u00199d!\u000f\u0011\u0007\ruaJD\u0002<\u0007?Aa!\u0010\u0007A\u0004\r\u0005\u0002\u0003B C\u0007G\u00012aOB\u0013\t\u00151EB1\u0001H\u0011\u0019\tF\u0002q\u0001\u0004*A1qhUB\u0016\u0007k\u0001rAKA\u0003\u0007[\u0019\t\u0004E\u0002<\u0007_!a!!\u0004\r\u0005\u00049\u0005cA\u001e\u00044\u00111\u00111\u0003\u0007C\u0002\u001d\u0003b!a\u0006\u00020\r-\u0002\"B0\r\u0001\b\u0001\u0007\"B4\r\u0001\bA\u0007BB8\r\u0001\u0004\u0019i\u0004\u0005\u0004+c\u000e-21\u0005\u0005\b\u0007\u001fa\u0001\u0019\u0001B\r\u0011\u0019!H\u00021\u0001\u0004DA91h!\u0012\u0004.\rEBaBA\"\u0019\t\u00071qI\u000b\u0007\u0007\u0013\u001ayea\u0015\u0012\u0007!\u001bY\u0005\u0005\u0005\u0002\u0018\u0005-3QJB)!\rY4q\n\u0003\b\u0003\'\u001a)E1\u0001H!\rY41\u000b\u0003\b\u00033\u001a)E1\u0001H+)\u00199f!\u001d\u0004v\re4q\r\u000b\u0007\u00073\u001a\tja%\u0015\t\rm3Q\u0012\u000b\u000b\u0007;\u001aIg!\u0019\u0004\n\u000e-\u0005cAB0\u001d:\u00191h!\u0019\t\ruj\u00019AB2!\u0011y$i!\u001a\u0011\u0007m\u001a9\u0007B\u0003G\u001b\t\u0007q\t\u0003\u0004R\u001b\u0001\u000f11\u000e\t\u0007\u007fM\u001biga\u001e\u0011\u0011\u0005U\u0014qOB8\u0007g\u00022aOB9\t\u0019\ti!\u0004b\u0001\u000fB\u00191h!\u001e\u0005\r\u0005MQB1\u0001H!\u001dY4\u0011PB8\u0007g\"q!a\"\u000e\u0005\u0004\u0019Y(\u0006\u0004\u0004~\r\r5qQ\t\u0004\u0011\u000e}\u0004\u0003CAH\u00033\u001b\ti!\"\u0011\u0007m\u001a\u0019\tB\u0004\u0002T\re$\u0019A$\u0011\u0007m\u001a9\tB\u0004\u0002Z\re$\u0019A$\t\u000b}k\u00019\u00011\t\u000b\u001dl\u00019\u00015\t\r=l\u0001\u0019ABH!\u0019Q\u0013o!\u001c\u0004f!91qB\u0007A\u0002\te\u0001B\u0002;\u000e\u0001\u0004\u00199(\u0006\u0003\u0004\u0018\u000e\u001dFCBBM\u0007g\u001b)\f\u0006\u0003\u0004\u001c\u000e=FCCBO\u0007S\u001b\tka+\u0004.B\u00191q\u0014(\u000f\u0007m\u001a\t\u000b\u0003\u0004>\u001d\u0001\u000f11\u0015\t\u0005\u007f\t\u001b)\u000bE\u0002<\u0007O#QA\u0012\bC\u0002\u001dCa!\u0015\bA\u0004\u0005\u0015\u0007\"B0\u000f\u0001\b\u0001\u0007\"B4\u000f\u0001\bA\u0007BB8\u000f\u0001\u0004\u0019\t\f\u0005\u0004+c\u0006\u001d7Q\u0015\u0005\b\u0007\u001fq\u0001\u0019\u0001B\r\u0011\u0019!h\u00021\u0001\u0002N\u0006Qam\u001c:Fq\u0006\u001cG\u000f\\=\u0016\u0011\rm61[Bl\u0007\u0017$ba!0\u0004f\u000e%H\u0003BB`\u0007C$\"b!1\u0004N\u000e\u00157Q\\Bp!\r\u0019\u0019M\u0014\b\u0004w\r\u0015\u0007BB\u001f\u0010\u0001\b\u00199\r\u0005\u0003@\u0005\u000e%\u0007cA\u001e\u0004L\u0012)ai\u0004b\u0001\u000f\"1\u0011k\u0004a\u0002\u0007\u001f\u0004baP*\u0004R\u000eU\u0007cA\u001e\u0004T\u0012)qk\u0004b\u0001\u000fB)1ha6\u0004R\u00121!l\u0004b\u0001\u00073,2aRBn\t\u0019i6q\u001bb\u0001\u000f\")ql\u0004a\u0002A\")qm\u0004a\u0002Q\"1qn\u0004a\u0001\u0007G\u0004bAK9\u0004R\u000e%\u0007bBBt\u001f\u0001\u0007!\u0011D\u0001\u000fgV\u001c7-Z3eK\u0012\u001cu.\u001e8u\u0011\u0019!x\u00021\u0001\u0004VVQ1Q\u001eC\u0004\t\u0017!ib!@\u0015\r\r=Hq\u0003C\r)\u0011\u0019\t\u0010b\u0005\u0015\u0015\rM8q`B|\t\u001f!\t\u0002E\u0002\u0004v:s1aOB|\u0011\u0019i\u0004\u0003q\u0001\u0004zB!qHQB~!\rY4Q \u0003\u0006\rB\u0011\ra\u0012\u0005\u0007#B\u0001\u001d\u0001\"\u0001\u0011\r}\u001aF1\u0001C\u0007!\u001dQ\u0013Q\u0001C\u0003\t\u0013\u00012a\u000fC\u0004\t\u0019\ti\u0001\u0005b\u0001\u000fB\u00191\bb\u0003\u0005\r\u0005M\u0001C1\u0001H!\u0019\t9\"a\f\u0005\u0004!)q\f\u0005a\u0002A\")q\r\u0005a\u0002Q\"1q\u000e\u0005a\u0001\t+\u0001bAK9\u0005\u0004\rm\bbBBt!\u0001\u0007!\u0011\u0004\u0005\u0007iB\u0001\r\u0001b\u0007\u0011\u000fm\"i\u0002\"\u0002\u0005\n\u00119\u00111\t\tC\u0002\u0011}QC\u0002C\u0011\tO!Y#E\u0002I\tG\u0001\u0002\"a\u0006\u0002L\u0011\u0015B\u0011\u0006\t\u0004w\u0011\u001dBaBA*\t;\u0011\ra\u0012\t\u0004w\u0011-BaBA-\t;\u0011\raR\u000b\u000b\t_!I\u0005\"\u0014\u0005R\u0011}BC\u0002C\u0019\tS\"Y\u0007\u0006\u0003\u00054\u0011\u0015DC\u0003C\u001b\t\u0003\"I\u0004\"\u0019\u0005dA\u0019Aq\u0007(\u000f\u0007m\"I\u0004\u0003\u0004>#\u0001\u000fA1\b\t\u0005\u007f\t#i\u0004E\u0002<\t\u007f!QAR\tC\u0002\u001dCa!U\tA\u0004\u0011\r\u0003CB T\t\u000b\"y\u0005\u0005\u0005\u0002v\u0005]Dq\tC&!\rYD\u0011\n\u0003\u0007\u0003\u001b\t\"\u0019A$\u0011\u0007m\"i\u0005\u0002\u0004\u0002\u0014E\u0011\ra\u0012\t\bw\u0011ECq\tC&\t\u001d\t9)\u0005b\u0001\t\'*b\u0001\"\u0016\u0005\\\u0011}\u0013c\u0001%\u0005XAA\u0011qRAM\t3\"i\u0006E\u0002<\t7\"q!a\u0015\u0005R\t\u0007q\tE\u0002<\t?\"q!!\u0017\u0005R\t\u0007q\tC\u0003`#\u0001\u000f\u0001\rC\u0003h#\u0001\u000f\u0001\u000e\u0003\u0004p#\u0001\u0007Aq\r\t\u0007UE$)\u0005\"\u0010\t\u000f\r\u001d\u0018\u00031\u0001\u0003\u001a!1A/\u0005a\u0001\t\u001f*B\u0001b\u001c\u0005\u0000Q1A\u0011\u000fCF\t\u001b#B\u0001b\u001d\u0005\bRQAQ\u000fCA\ts\"\u0019\t\"\"\u0011\u0007\u0011]dJD\u0002<\tsBa!\u0010\nA\u0004\u0011m\u0004\u0003B C\t{\u00022a\u000fC@\t\u00151%C1\u0001H\u0011\u0019\t&\u0003q\u0001\u0002F\")qL\u0005a\u0002A\")qM\u0005a\u0002Q\"1qN\u0005a\u0001\t\u0013\u0003bAK9\u0002H\u0012u\u0004bBBt%\u0001\u0007!\u0011\u0004\u0005\u0007iJ\u0001\r!!4\u0002\u000b\u0019|\'OT8\u0016\u0011\u0011ME1\u0016CX\tG#B\u0001\"&\u0005>R!Aq\u0013C]))!I\n\"*\u0005\u001e\u0012UFq\u0017\t\u0004\t7sebA\u001e\u0005\u001e\"1Qh\u0005a\u0002\t?\u0003Ba\u0010\"\u0005\"B\u00191\bb)\u0005\u000b\u0019\u001b\"\u0019A$\t\rE\u001b\u00029\u0001CT!\u0019y4\u000b\"+\u0005.B\u00191\bb+\u0005\u000b]\u001b\"\u0019A$\u0011\u000bm\"y\u000b\"+\u0005\ri\u001b\"\u0019\u0001CY+\r9E1\u0017\u0003\u0007;\u0012=&\u0019A$\t\u000b}\u001b\u00029\u00011\t\u000b\u001d\u001c\u00029\u00015\t\r=\u001c\u0002\u0019\u0001C^!\u0019Q\u0013\u000f\"+\u0005\"\"1Ao\u0005a\u0001\t[+\"\u0002\"1\u0005\\\u0012}Gq\u001eCi)\u0011!\u0019\rb;\u0015\t\u0011\u0015Gq\u001d\u000b\u000b\t\u000f$\u0019\u000eb3\u0005d\u0012\u0015\bc\u0001Ce\u001d:\u00191\bb3\t\ru\"\u00029\u0001Cg!\u0011y$\tb4\u0011\u0007m\"\t\u000eB\u0003G)\t\u0007q\t\u0003\u0004R)\u0001\u000fAQ\u001b\t\u0007\u007fM#9\u000e\"9\u0011\u000f)\n)\u0001\"7\u0005^B\u00191\bb7\u0005\r\u00055AC1\u0001H!\rYDq\u001c\u0003\u0007\u0003\'!\"\u0019A$\u0011\r\u0005]\u0011q\u0006Cl\u0011\u0015yF\u0003q\u0001a\u0011\u00159G\u0003q\u0001i\u0011\u0019yG\u00031\u0001\u0005jB1!&\u001dCl\t\u001fDa\u0001\u001e\u000bA\u0002\u00115\bcB\u001e\u0005p\u0012eGQ\u001c\u0003\b\u0003\u0007\"\"\u0019\u0001Cy+\u0019!\u0019\u0010\"?\u0005~F\u0019\u0001\n\">\u0011\u0011\u0005]\u00111\nC|\tw\u00042a\u000fC}\t\u001d\t\u0019\u0006b<C\u0002\u001d\u00032a\u000fC\u007f\t\u001d\tI\u0006b<C\u0002\u001d+\"\"\"\u0001\u0006\u001c\u0015}Q1EC\t)\u0011)\u0019!b\u000f\u0015\t\u0015\u0015Qq\u0007\u000b\u000b\u000b\u000f)\u0019\"b\u0003\u00064\u0015U\u0002cAC\u0005\u001d:\u00191(b\u0003\t\ru*\u00029AC\u0007!\u0011y$)b\u0004\u0011\u0007m*\t\u0002B\u0003G+\t\u0007q\t\u0003\u0004R+\u0001\u000fQQ\u0003\t\u0007\u007fM+9\"\"\t\u0011\u0011\u0005U\u0014qOC\r\u000b;\u00012aOC\u000e\t\u0019\ti!\u0006b\u0001\u000fB\u00191(b\b\u0005\r\u0005MQC1\u0001H!\u001dYT1EC\r\u000b;!q!a\"\u0016\u0005\u0004))#\u0006\u0004\u0006(\u00155R\u0011G\t\u0004\u0011\u0016%\u0002\u0003CAH\u00033+Y#b\f\u0011\u0007m*i\u0003B\u0004\u0002T\u0015\r\"\u0019A$\u0011\u0007m*\t\u0004B\u0004\u0002Z\u0015\r\"\u0019A$\t\u000b}+\u00029\u00011\t\u000b\u001d,\u00029\u00015\t\r=,\u0002\u0019AC\u001d!\u0019Q\u0013/b\u0006\u0006\u0010!1A/\u0006a\u0001\u000bC)B!b\u0010\u0006PQ!Q\u0011IC.)\u0011)\u0019%b\u0016\u0015\u0015\u0015\u0015S\u0011KC%\u000b\'*)\u0006E\u0002\u0006H9s1aOC%\u0011\u0019id\u0003q\u0001\u0006LA!qHQC\'!\rYTq\n\u0003\u0006\rZ\u0011\ra\u0012\u0005\u0007#Z\u0001\u001d!!2\t\u000b}3\u00029\u00011\t\u000b\u001d4\u00029\u00015\t\r=4\u0002\u0019AC-!\u0019Q\u0013/a2\u0006N!1AO\u0006a\u0001\u0003\u001b\f!BZ8s\u0005\u0016$x/Z3o+!)\t\'\"\u001f\u0006~\u0015ED\u0003CC2\u000b\u0017+y)b%\u0015\t\u0015\u0015Tq\u0011\u000b\u000b\u000bO*\u0019(b\u001b\u0006\u0004\u0016\u0015\u0005cAC5\u001d:\u00191(b\u001b\t\ru:\u00029AC7!\u0011y$)b\u001c\u0011\u0007m*\t\bB\u0003G/\t\u0007q\t\u0003\u0004R/\u0001\u000fQQ\u000f\t\u0007\u007fM+9(b\u001f\u0011\u0007m*I\bB\u0003X/\t\u0007q\tE\u0003<\u000b{*9\b\u0002\u0004[/\t\u0007QqP\u000b\u0004\u000f\u0016\u0005EAB/\u0006~\t\u0007q\tC\u0003`/\u0001\u000f\u0001\rC\u0003h/\u0001\u000f\u0001\u000e\u0003\u0004p/\u0001\u0007Q\u0011\u0012\t\u0007UE,9(b\u001c\t\u000f\u00155u\u00031\u0001\u0003\u001a\u0005!aM]8n\u0011\u001d)\tj\u0006a\u0001\u00053\tA!\u001e9U_\"1Ao\u0006a\u0001\u000bw*\"\"b&\u00062\u0016UV\u0011ZCT)!)I*\"1\u0006D\u0016\u0015G\u0003BCN\u000b{#\"\"\"(\u0006*\u0016\u0005V\u0011XC^!\r)yJ\u0014\b\u0004w\u0015\u0005\u0006BB\u001f\u0019\u0001\b)\u0019\u000b\u0005\u0003@\u0005\u0016\u0015\u0006cA\u001e\u0006(\u0012)a\t\u0007b\u0001\u000f\"1\u0011\u000b\u0007a\u0002\u000bW\u0003baP*\u0006.\u0016]\u0006c\u0002\u0016\u0002\u0006\u0015=V1\u0017\t\u0004w\u0015EFABA\u00071\t\u0007q\tE\u0002<\u000bk#a!a\u0005\u0019\u0005\u00049\u0005CBA\f\u0003_)i\u000bC\u0003`1\u0001\u000f\u0001\rC\u0003h1\u0001\u000f\u0001\u000e\u0003\u0004p1\u0001\u0007Qq\u0018\t\u0007UE,i+\"*\t\u000f\u00155\u0005\u00041\u0001\u0003\u001a!9Q\u0011\u0013\rA\u0002\te\u0001B\u0002;\u0019\u0001\u0004)9\rE\u0004<\u000b\u0013,y+b-\u0005\u000f\u0005\r\u0003D1\u0001\u0006LV1QQZCj\u000b/\f2\u0001SCh!!\t9\"a\u0013\u0006R\u0016U\u0007cA\u001e\u0006T\u00129\u00111KCe\u0005\u00049\u0005cA\u001e\u0006X\u00129\u0011\u0011LCe\u0005\u00049UCCCn\u000bk,I0\"@\u0006lRAQQ\u001cD\u000b\r/1I\u0002\u0006\u0003\u0006`\u001aEACCCq\u000b[,)O\"\u0004\u0007\u0010A\u0019Q1\u001d(\u000f\u0007m*)\u000f\u0003\u0004>3\u0001\u000fQq\u001d\t\u0005\u007f\t+I\u000fE\u0002<\u000bW$QAR\rC\u0002\u001dCa!U\rA\u0004\u0015=\bCB T\u000bc,Y\u0010\u0005\u0005\u0002v\u0005]T1_C|!\rYTQ\u001f\u0003\u0007\u0003\u001bI\"\u0019A$\u0011\u0007m*I\u0010\u0002\u0004\u0002\u0014e\u0011\ra\u0012\t\bw\u0015uX1_C|\t\u001d\t9)\u0007b\u0001\u000b\u007f,bA\"\u0001\u0007\b\u0019-\u0011c\u0001%\u0007\u0004AA\u0011qRAM\r\u000b1I\u0001E\u0002<\r\u000f!q!a\u0015\u0006~\n\u0007q\tE\u0002<\r\u0017!q!!\u0017\u0006~\n\u0007q\tC\u0003`3\u0001\u000f\u0001\rC\u0003h3\u0001\u000f\u0001\u000e\u0003\u0004p3\u0001\u0007a1\u0003\t\u0007UE,\t0\";\t\u000f\u00155\u0015\u00041\u0001\u0003\u001a!9Q\u0011S\rA\u0002\te\u0001B\u0002;\u001a\u0001\u0004)Y0\u0006\u0003\u0007\u001e\u00195B\u0003\u0003D\u0010\rs1YD\"\u0010\u0015\t\u0019\u0005bQ\u0007\u000b\u000b\rG1yCb\n\u00072\u0019M\u0002c\u0001D\u0013\u001d:\u00191Hb\n\t\ruR\u00029\u0001D\u0015!\u0011y$Ib\u000b\u0011\u0007m2i\u0003B\u0003G5\t\u0007q\t\u0003\u0004R5\u0001\u000f\u0011Q\u0019\u0005\u0006?j\u0001\u001d\u0001\u0019\u0005\u0006Oj\u0001\u001d\u0001\u001b\u0005\u0007_j\u0001\rAb\u000e\u0011\r)\n\u0018q\u0019D\u0016\u0011\u001d)iI\u0007a\u0001\u00053Aq!\"%\u001b\u0001\u0004\u0011I\u0002\u0003\u0004u5\u0001\u0007\u0011QZ\u0001\tM>\u0014XI^3ssVAa1\tD.\r?2\u0019\u0006\u0006\u0003\u0007F\u00195D\u0003\u0002D$\rS\"\"B\"\u0013\u0007V\u00195cQ\rD4!\r1YE\u0014\b\u0004w\u00195\u0003BB\u001f\u001c\u0001\b1y\u0005\u0005\u0003@\u0005\u001aE\u0003cA\u001e\u0007T\u0011)ai\u0007b\u0001\u000f\"1\u0011k\u0007a\u0002\r/\u0002baP*\u0007Z\u0019u\u0003cA\u001e\u0007\\\u0011)qk\u0007b\u0001\u000fB)1Hb\u0018\u0007Z\u00111!l\u0007b\u0001\rC*2a\u0012D2\t\u0019ifq\fb\u0001\u000f\")ql\u0007a\u0002A\")qm\u0007a\u0002Q\"1qn\u0007a\u0001\rW\u0002bAK9\u0007Z\u0019E\u0003B\u0002;\u001c\u0001\u00041i&\u0006\u0006\u0007r\u0019-eq\u0012DP\r\u0003#BAb\u001d\u0007\u001cR!aQ\u000fDL))19Hb!\u0007|\u0019MeQ\u0013\t\u0004\rsrebA\u001e\u0007|!1Q\b\ba\u0002\r{\u0002Ba\u0010\"\u0007\u0000A\u00191H\"!\u0005\u000b\u0019c\"\u0019A$\t\rEc\u00029\u0001DC!\u0019y4Kb\"\u0007\u0012B9!&!\u0002\u0007\n\u001a5\u0005cA\u001e\u0007\f\u00121\u0011Q\u0002\u000fC\u0002\u001d\u00032a\u000fDH\t\u0019\t\u0019\u0002\bb\u0001\u000fB1\u0011qCA\u0018\r\u000fCQa\u0018\u000fA\u0004\u0001DQa\u001a\u000fA\u0004!Daa\u001c\u000fA\u0002\u0019e\u0005C\u0002\u0016r\r\u000f3y\b\u0003\u0004u9\u0001\u0007aQ\u0014\t\bw\u0019}e\u0011\u0012DG\t\u001d\t\u0019\u0005\bb\u0001\rC+bAb)\u0007*\u001a5\u0016c\u0001%\u0007&BA\u0011qCA&\rO3Y\u000bE\u0002<\rS#q!a\u0015\u0007 \n\u0007q\tE\u0002<\r[#q!!\u0017\u0007 \n\u0007q)\u0006\u0006\u00072\u001a-gq\u001aDj\r\u0003$BAb-\u0007lR!aQ\u0017Dt))19Lb1\u0007<\u001a\rhQ\u001d\t\u0004\rssebA\u001e\u0007<\"1Q(\ba\u0002\r{\u0003Ba\u0010\"\u0007@B\u00191H\"1\u0005\u000b\u0019k\"\u0019A$\t\rEk\u00029\u0001Dc!\u0019y4Kb2\u0007RBA\u0011QOA<\r\u00134i\rE\u0002<\r\u0017$a!!\u0004\u001e\u0005\u00049\u0005cA\u001e\u0007P\u00121\u00111C\u000fC\u0002\u001d\u0003ra\u000fDj\r\u00134i\rB\u0004\u0002\bv\u0011\rA\"6\u0016\r\u0019]gQ\u001cDq#\rAe\u0011\u001c\t\t\u0003\u001f\u000bIJb7\u0007`B\u00191H\"8\u0005\u000f\u0005Mc1\u001bb\u0001\u000fB\u00191H\"9\u0005\u000f\u0005ec1\u001bb\u0001\u000f\")q,\ba\u0002A\")q-\ba\u0002Q\"1q.\ba\u0001\rS\u0004bAK9\u0007H\u001a}\u0006B\u0002;\u001e\u0001\u00041\t.\u0006\u0003\u0007p\u001a}H\u0003\u0002Dy\u000f\u0017!BAb=\b\bQQaQ_D\u0001\rs<\u0019a\"\u0002\u0011\u0007\u0019]hJD\u0002<\rsDa!\u0010\u0010A\u0004\u0019m\b\u0003B C\r{\u00042a\u000fD\u0000\t\u00151eD1\u0001H\u0011\u0019\tf\u0004q\u0001\u0002F\")qL\ba\u0002A\")qM\ba\u0002Q\"1qN\ba\u0001\u000f\u0013\u0001bAK9\u0002H\u001au\bB\u0002;\u001f\u0001\u0004\ti-\u0001\u0006J]N\u0004Xm\u0019;peN\u00042!!\u001e!\'\u0011\u0001\u0013fb\u0005\u0011\u0007\u0005U\u0004!\u0001\u0004=S:LGO\u0010\u000b\u0003\u000f\u001f\u0001"
    )
  ScalaInlineInfo: length = 0x126 (unknown attribute)
   01 00 00 3A 00 AA 00 AB 01 00 12 00 13 00 00 12
   00 37 00 00 12 00 31 00 00 12 00 2B 00 00 09 00
   0A 01 00 09 00 36 01 00 09 00 30 01 00 09 00 2A
   01 00 3F 00 40 00 00 3F 00 53 00 00 3F 00 4E 00
   00 3F 00 49 00 00 3C 00 3D 01 00 3C 00 52 01 00
   3C 00 4D 01 00 3C 00 48 01 00 5F 00 40 00 00 5F
   00 53 00 00 5F 00 4E 00 00 5F 00 49 00 00 5D 00
   3D 01 00 5D 00 52 01 00 5D 00 4D 01 00 5D 00 48
   01 00 87 00 88 00 00 87 00 9A 00 00 87 00 95 00
   00 87 00 90 00 00 83 00 84 01 00 83 00 99 01 00
   83 00 94 01 00 83 00 8F 01 00 9F 00 13 00 00 9F
   00 37 00 00 9F 00 31 00 00 9F 00 2B 00 00 9E 00
   0A 01 00 9E 00 36 01 00 9E 00 30 01 00 9E 00 2A
   01 00 6C 00 40 00 00 6C 00 53 00 00 6C 00 4E 00
   00 6C 00 49 00 00 6A 00 3D 01 00 6A 00 52 01 00
   6A 00 4D 01 00 6A 00 48 01 00 78 00 13 00 00 78
   00 37 00 00 78 00 31 00 00 78 00 2B 00 00 77 00
   0A 01 00 77 00 36 01 00 77 00 30 01 00 77 00 2A
   01 00 57 00 58 01
  ScalaSig: length = 0x3 (unknown attribute)
   05 02 00
