Classfile /Users/mw/Projects/slang-braindump/.jar/jar8/assemble/slang-braindump/assemble/content/org/scalatest/OptionValues$.class
  Last modified May 29, 2022; size 1197 bytes
  SHA-256 checksum e840e5864e9e745b7d2b73ef2ad27951cbc736c3e4cc81ec3fe99931bd22ad98
  Compiled from "OptionValues.scala"
public final class org.scalatest.OptionValues$ implements org.scalatest.OptionValues
  minor version: 0
  major version: 52
  flags: (0x0031) ACC_PUBLIC, ACC_FINAL, ACC_SUPER
  this_class: #2                          // org/scalatest/OptionValues$
  super_class: #4                         // java/lang/Object
  interfaces: 1, fields: 1, methods: 3, attributes: 4
Constant pool:
   #1 = Utf8               org/scalatest/OptionValues$
   #2 = Class              #1             // org/scalatest/OptionValues$
   #3 = Utf8               java/lang/Object
   #4 = Class              #3             // java/lang/Object
   #5 = Utf8               org/scalatest/OptionValues
   #6 = Class              #5             // org/scalatest/OptionValues
   #7 = Utf8               OptionValues.scala
   #8 = Utf8               org/scalatest/OptionValues$Valuable
   #9 = Class              #8             // org/scalatest/OptionValues$Valuable
  #10 = Utf8               Valuable
  #11 = Utf8               MODULE$
  #12 = Utf8               Lorg/scalatest/OptionValues$;
  #13 = Utf8               <clinit>
  #14 = Utf8               ()V
  #15 = Utf8               <init>
  #16 = NameAndType        #15:#14        // "<init>":()V
  #17 = Methodref          #2.#16         // org/scalatest/OptionValues$."<init>":()V
  #18 = NameAndType        #11:#12        // MODULE$:Lorg/scalatest/OptionValues$;
  #19 = Fieldref           #2.#18         // org/scalatest/OptionValues$.MODULE$:Lorg/scalatest/OptionValues$;
  #20 = Utf8               $init$
  #21 = Utf8               (Lorg/scalatest/OptionValues;)V
  #22 = NameAndType        #20:#21        // $init$:(Lorg/scalatest/OptionValues;)V
  #23 = InterfaceMethodref #6.#22         // org/scalatest/OptionValues.$init$:(Lorg/scalatest/OptionValues;)V
  #24 = Utf8               convertOptionToValuable
  #25 = Utf8               (Lscala/Option;Lorg/scalactic/source/Position;)Lorg/scalatest/OptionValues$Valuable;
  #26 = Utf8               <T:Ljava/lang/Object;>(Lscala/Option<TT;>;Lorg/scalactic/source/Position;)Lorg/scalatest/OptionValues$Valuable<TT;>;
  #27 = Utf8               opt
  #28 = Utf8               pos
  #29 = Utf8               convertOptionToValuable$
  #30 = Utf8               (Lorg/scalatest/OptionValues;Lscala/Option;Lorg/scalactic/source/Position;)Lorg/scalatest/OptionValues$Valuable;
  #31 = NameAndType        #29:#30        // convertOptionToValuable$:(Lorg/scalatest/OptionValues;Lscala/Option;Lorg/scalactic/source/Position;)Lorg/scalatest/OptionValues$Valuable;
  #32 = InterfaceMethodref #6.#31         // org/scalatest/OptionValues.convertOptionToValuable$:(Lorg/scalatest/OptionValues;Lscala/Option;Lorg/scalactic/source/Position;)Lorg/scalatest/OptionValues$Valuable;
  #33 = Utf8               this
  #34 = Utf8               Lscala/Option;
  #35 = Utf8               Lorg/scalactic/source/Position;
  #36 = Methodref          #4.#16         // java/lang/Object."<init>":()V
  #37 = Utf8               Code
  #38 = Utf8               LineNumberTable
  #39 = Utf8               LocalVariableTable
  #40 = Utf8               Signature
  #41 = Utf8               MethodParameters
  #42 = Utf8               InnerClasses
  #43 = Utf8               SourceFile
  #44 = Utf8               ScalaInlineInfo
  #45 = Utf8               Scala
{
  public static final org.scalatest.OptionValues$ MODULE$;
    descriptor: Lorg/scalatest/OptionValues$;
    flags: (0x0019) ACC_PUBLIC, ACC_STATIC, ACC_FINAL

  public static {};
    descriptor: ()V
    flags: (0x0009) ACC_PUBLIC, ACC_STATIC
    Code:
      stack=2, locals=0, args_size=0
         0: new           #2                  // class org/scalatest/OptionValues$
         3: dup
         4: invokespecial #17                 // Method "<init>":()V
         7: putstatic     #19                 // Field MODULE$:Lorg/scalatest/OptionValues$;
        10: getstatic     #19                 // Field MODULE$:Lorg/scalatest/OptionValues$;
        13: invokestatic  #23                 // InterfaceMethod org/scalatest/OptionValues.$init$:(Lorg/scalatest/OptionValues;)V
        16: return
      LineNumberTable:
        line 172: 0

  public <T extends java.lang.Object> org.scalatest.OptionValues$Valuable<T> convertOptionToValuable(scala.Option<T>, org.scalactic.source.Position);
    descriptor: (Lscala/Option;Lorg/scalactic/source/Position;)Lorg/scalatest/OptionValues$Valuable;
    flags: (0x0001) ACC_PUBLIC
    Code:
      stack=3, locals=3, args_size=3
         0: aload_0
         1: aload_1
         2: aload_2
         3: invokestatic  #32                 // InterfaceMethod org/scalatest/OptionValues.convertOptionToValuable$:(Lorg/scalatest/OptionValues;Lscala/Option;Lorg/scalactic/source/Position;)Lorg/scalatest/OptionValues$Valuable;
         6: areturn
      LineNumberTable:
        line 172: 0
      LocalVariableTable:
        Start  Length  Slot  Name   Signature
            0       7     0  this   Lorg/scalatest/OptionValues$;
            0       7     1   opt   Lscala/Option;
            0       7     2   pos   Lorg/scalactic/source/Position;
    Signature: #26                          // <T:Ljava/lang/Object;>(Lscala/Option<TT;>;Lorg/scalactic/source/Position;)Lorg/scalatest/OptionValues$Valuable<TT;>;
    MethodParameters:
      Name                           Flags
      opt                            final
      pos                            final

  private org.scalatest.OptionValues$();
    descriptor: ()V
    flags: (0x0002) ACC_PRIVATE
    Code:
      stack=1, locals=1, args_size=1
         0: aload_0
         1: invokespecial #36                 // Method java/lang/Object."<init>":()V
         4: return
      LineNumberTable:
        line 172: 0
      LocalVariableTable:
        Start  Length  Slot  Name   Signature
            0       5     0  this   Lorg/scalatest/OptionValues$;
}
InnerClasses:
  public #10= #9 of #6;                   // Valuable=class org/scalatest/OptionValues$Valuable of class org/scalatest/OptionValues
SourceFile: "OptionValues.scala"
  ScalaInlineInfo: length = 0xE (unknown attribute)
   01 01 00 02 00 0F 00 0E 01 00 18 00 19 01
  Scala: length = 0x0 (unknown attribute)

