Classfile /Users/mw/Projects/slang-braindump/.jar/jar8/assemble/slang-braindump/assemble/content/org/scalatest/package$.class
  Last modified May 29, 2022; size 3993 bytes
  SHA-256 checksum e04a6007343caa6fbd5543906fbd472b2809be784668647e800aebe0025a5387
  Compiled from "package.scala"
public final class org.scalatest.package$
  minor version: 0
  major version: 52
  flags: (0x0031) ACC_PUBLIC, ACC_FINAL, ACC_SUPER
  this_class: #2                          // org/scalatest/package$
  super_class: #4                         // java/lang/Object
  interfaces: 0, fields: 13, methods: 22, attributes: 3
Constant pool:
    #1 = Utf8               org/scalatest/package$
    #2 = Class              #1            // org/scalatest/package$
    #3 = Utf8               java/lang/Object
    #4 = Class              #3            // java/lang/Object
    #5 = Utf8               package.scala
    #6 = Utf8               MODULE$
    #7 = Utf8               Lorg/scalatest/package$;
    #8 = Utf8               color
    #9 = Utf8               Lorg/scalatest/Shell;
   #10 = Utf8               durations
   #11 = Utf8               shortstacks
   #12 = Utf8               fullstacks
   #13 = Utf8               stats
   #14 = Utf8               nocolor
   #15 = Utf8               nodurations
   #16 = Utf8               nostacks
   #17 = Utf8               nostats
   #18 = Utf8               defaultShell
   #19 = Utf8               Lorg/scalatest/ShellImpl;
   #20 = Utf8               ScalaTestVersion
   #21 = Utf8               Ljava/lang/String;
   #22 = Utf8               bitmap$0
   #23 = Utf8               I
   #24 = Utf8               <clinit>
   #25 = Utf8               ()V
   #26 = Utf8               <init>
   #27 = NameAndType        #26:#25       // "<init>":()V
   #28 = Methodref          #2.#27        // org/scalatest/package$."<init>":()V
   #29 = NameAndType        #6:#7         // MODULE$:Lorg/scalatest/package$;
   #30 = Fieldref           #2.#29        // org/scalatest/package$.MODULE$:Lorg/scalatest/package$;
   #31 = Utf8               org/scalatest/ShellImpl
   #32 = Class              #31           // org/scalatest/ShellImpl
   #33 = Utf8               org/scalatest/ShellImpl$
   #34 = Class              #33           // org/scalatest/ShellImpl$
   #35 = Utf8               Lorg/scalatest/ShellImpl$;
   #36 = NameAndType        #6:#35        // MODULE$:Lorg/scalatest/ShellImpl$;
   #37 = Fieldref           #34.#36       // org/scalatest/ShellImpl$.MODULE$:Lorg/scalatest/ShellImpl$;
   #38 = Utf8               apply$default$1
   #39 = Utf8               ()Z
   #40 = NameAndType        #38:#39       // apply$default$1:()Z
   #41 = Methodref          #34.#40       // org/scalatest/ShellImpl$.apply$default$1:()Z
   #42 = Utf8               apply$default$2
   #43 = NameAndType        #42:#39       // apply$default$2:()Z
   #44 = Methodref          #34.#43       // org/scalatest/ShellImpl$.apply$default$2:()Z
   #45 = Utf8               apply$default$3
   #46 = NameAndType        #45:#39       // apply$default$3:()Z
   #47 = Methodref          #34.#46       // org/scalatest/ShellImpl$.apply$default$3:()Z
   #48 = Utf8               apply$default$4
   #49 = NameAndType        #48:#39       // apply$default$4:()Z
   #50 = Methodref          #34.#49       // org/scalatest/ShellImpl$.apply$default$4:()Z
   #51 = Utf8               apply$default$5
   #52 = NameAndType        #51:#39       // apply$default$5:()Z
   #53 = Methodref          #34.#52       // org/scalatest/ShellImpl$.apply$default$5:()Z
   #54 = Utf8               (ZZZZZ)V
   #55 = NameAndType        #26:#54       // "<init>":(ZZZZZ)V
   #56 = Methodref          #32.#55       // org/scalatest/ShellImpl."<init>":(ZZZZZ)V
   #57 = NameAndType        #18:#19       // defaultShell:Lorg/scalatest/ShellImpl;
   #58 = Fieldref           #2.#57        // org/scalatest/package$.defaultShell:Lorg/scalatest/ShellImpl;
   #59 = Utf8               org/scalatest/ScalaTestVersions$
   #60 = Class              #59           // org/scalatest/ScalaTestVersions$
   #61 = Utf8               Lorg/scalatest/ScalaTestVersions$;
   #62 = NameAndType        #6:#61        // MODULE$:Lorg/scalatest/ScalaTestVersions$;
   #63 = Fieldref           #60.#62       // org/scalatest/ScalaTestVersions$.MODULE$:Lorg/scalatest/ScalaTestVersions$;
   #64 = Utf8               ()Ljava/lang/String;
   #65 = NameAndType        #20:#64       // ScalaTestVersion:()Ljava/lang/String;
   #66 = Methodref          #60.#65       // org/scalatest/ScalaTestVersions$.ScalaTestVersion:()Ljava/lang/String;
   #67 = NameAndType        #20:#21       // ScalaTestVersion:Ljava/lang/String;
   #68 = Fieldref           #2.#67        // org/scalatest/package$.ScalaTestVersion:Ljava/lang/String;
   #69 = Utf8               ()Lorg/scalatest/ShellImpl;
   #70 = Utf8               this
   #71 = Utf8               color$lzycompute
   #72 = Utf8               ()Lorg/scalatest/Shell;
   #73 = NameAndType        #22:#23       // bitmap$0:I
   #74 = Fieldref           #2.#73        // org/scalatest/package$.bitmap$0:I
   #75 = NameAndType        #18:#69       // defaultShell:()Lorg/scalatest/ShellImpl;
   #76 = Methodref          #2.#75        // org/scalatest/package$.defaultShell:()Lorg/scalatest/ShellImpl;
   #77 = NameAndType        #8:#72        // color:()Lorg/scalatest/Shell;
   #78 = Methodref          #32.#77       // org/scalatest/ShellImpl.color:()Lorg/scalatest/Shell;
   #79 = NameAndType        #8:#9         // color:Lorg/scalatest/Shell;
   #80 = Fieldref           #2.#79        // org/scalatest/package$.color:Lorg/scalatest/Shell;
   #81 = Utf8               java/lang/Throwable
   #82 = Class              #81           // java/lang/Throwable
   #83 = NameAndType        #71:#72       // color$lzycompute:()Lorg/scalatest/Shell;
   #84 = Methodref          #2.#83        // org/scalatest/package$.color$lzycompute:()Lorg/scalatest/Shell;
   #85 = Utf8               org/scalatest/Shell
   #86 = Class              #85           // org/scalatest/Shell
   #87 = Utf8               durations$lzycompute
   #88 = NameAndType        #10:#72       // durations:()Lorg/scalatest/Shell;
   #89 = Methodref          #32.#88       // org/scalatest/ShellImpl.durations:()Lorg/scalatest/Shell;
   #90 = NameAndType        #10:#9        // durations:Lorg/scalatest/Shell;
   #91 = Fieldref           #2.#90        // org/scalatest/package$.durations:Lorg/scalatest/Shell;
   #92 = NameAndType        #87:#72       // durations$lzycompute:()Lorg/scalatest/Shell;
   #93 = Methodref          #2.#92        // org/scalatest/package$.durations$lzycompute:()Lorg/scalatest/Shell;
   #94 = Utf8               shortstacks$lzycompute
   #95 = NameAndType        #11:#72       // shortstacks:()Lorg/scalatest/Shell;
   #96 = Methodref          #32.#95       // org/scalatest/ShellImpl.shortstacks:()Lorg/scalatest/Shell;
   #97 = NameAndType        #11:#9        // shortstacks:Lorg/scalatest/Shell;
   #98 = Fieldref           #2.#97        // org/scalatest/package$.shortstacks:Lorg/scalatest/Shell;
   #99 = NameAndType        #94:#72       // shortstacks$lzycompute:()Lorg/scalatest/Shell;
  #100 = Methodref          #2.#99        // org/scalatest/package$.shortstacks$lzycompute:()Lorg/scalatest/Shell;
  #101 = Utf8               fullstacks$lzycompute
  #102 = NameAndType        #12:#72       // fullstacks:()Lorg/scalatest/Shell;
  #103 = Methodref          #32.#102      // org/scalatest/ShellImpl.fullstacks:()Lorg/scalatest/Shell;
  #104 = NameAndType        #12:#9        // fullstacks:Lorg/scalatest/Shell;
  #105 = Fieldref           #2.#104       // org/scalatest/package$.fullstacks:Lorg/scalatest/Shell;
  #106 = NameAndType        #101:#72      // fullstacks$lzycompute:()Lorg/scalatest/Shell;
  #107 = Methodref          #2.#106       // org/scalatest/package$.fullstacks$lzycompute:()Lorg/scalatest/Shell;
  #108 = Utf8               stats$lzycompute
  #109 = NameAndType        #13:#72       // stats:()Lorg/scalatest/Shell;
  #110 = Methodref          #32.#109      // org/scalatest/ShellImpl.stats:()Lorg/scalatest/Shell;
  #111 = NameAndType        #13:#9        // stats:Lorg/scalatest/Shell;
  #112 = Fieldref           #2.#111       // org/scalatest/package$.stats:Lorg/scalatest/Shell;
  #113 = NameAndType        #108:#72      // stats$lzycompute:()Lorg/scalatest/Shell;
  #114 = Methodref          #2.#113       // org/scalatest/package$.stats$lzycompute:()Lorg/scalatest/Shell;
  #115 = Utf8               nocolor$lzycompute
  #116 = NameAndType        #14:#72       // nocolor:()Lorg/scalatest/Shell;
  #117 = Methodref          #32.#116      // org/scalatest/ShellImpl.nocolor:()Lorg/scalatest/Shell;
  #118 = NameAndType        #14:#9        // nocolor:Lorg/scalatest/Shell;
  #119 = Fieldref           #2.#118       // org/scalatest/package$.nocolor:Lorg/scalatest/Shell;
  #120 = NameAndType        #115:#72      // nocolor$lzycompute:()Lorg/scalatest/Shell;
  #121 = Methodref          #2.#120       // org/scalatest/package$.nocolor$lzycompute:()Lorg/scalatest/Shell;
  #122 = Utf8               nodurations$lzycompute
  #123 = NameAndType        #15:#72       // nodurations:()Lorg/scalatest/Shell;
  #124 = Methodref          #32.#123      // org/scalatest/ShellImpl.nodurations:()Lorg/scalatest/Shell;
  #125 = NameAndType        #15:#9        // nodurations:Lorg/scalatest/Shell;
  #126 = Fieldref           #2.#125       // org/scalatest/package$.nodurations:Lorg/scalatest/Shell;
  #127 = NameAndType        #122:#72      // nodurations$lzycompute:()Lorg/scalatest/Shell;
  #128 = Methodref          #2.#127       // org/scalatest/package$.nodurations$lzycompute:()Lorg/scalatest/Shell;
  #129 = Utf8               nostacks$lzycompute
  #130 = NameAndType        #16:#72       // nostacks:()Lorg/scalatest/Shell;
  #131 = Methodref          #32.#130      // org/scalatest/ShellImpl.nostacks:()Lorg/scalatest/Shell;
  #132 = NameAndType        #16:#9        // nostacks:Lorg/scalatest/Shell;
  #133 = Fieldref           #2.#132       // org/scalatest/package$.nostacks:Lorg/scalatest/Shell;
  #134 = NameAndType        #129:#72      // nostacks$lzycompute:()Lorg/scalatest/Shell;
  #135 = Methodref          #2.#134       // org/scalatest/package$.nostacks$lzycompute:()Lorg/scalatest/Shell;
  #136 = Utf8               nostats$lzycompute
  #137 = NameAndType        #17:#72       // nostats:()Lorg/scalatest/Shell;
  #138 = Methodref          #32.#137      // org/scalatest/ShellImpl.nostats:()Lorg/scalatest/Shell;
  #139 = NameAndType        #17:#9        // nostats:Lorg/scalatest/Shell;
  #140 = Fieldref           #2.#139       // org/scalatest/package$.nostats:Lorg/scalatest/Shell;
  #141 = NameAndType        #136:#72      // nostats$lzycompute:()Lorg/scalatest/Shell;
  #142 = Methodref          #2.#141       // org/scalatest/package$.nostats$lzycompute:()Lorg/scalatest/Shell;
  #143 = Methodref          #4.#27        // java/lang/Object."<init>":()V
  #144 = Utf8               Code
  #145 = Utf8               LineNumberTable
  #146 = Utf8               LocalVariableTable
  #147 = Utf8               StackMapTable
  #148 = Utf8               SourceFile
  #149 = Utf8               ScalaInlineInfo
  #150 = Utf8               Scala
{
  public static final org.scalatest.package$ MODULE$;
    descriptor: Lorg/scalatest/package$;
    flags: (0x0019) ACC_PUBLIC, ACC_STATIC, ACC_FINAL

  private static org.scalatest.Shell color;
    descriptor: Lorg/scalatest/Shell;
    flags: (0x000a) ACC_PRIVATE, ACC_STATIC

  private static org.scalatest.Shell durations;
    descriptor: Lorg/scalatest/Shell;
    flags: (0x000a) ACC_PRIVATE, ACC_STATIC

  private static org.scalatest.Shell shortstacks;
    descriptor: Lorg/scalatest/Shell;
    flags: (0x000a) ACC_PRIVATE, ACC_STATIC

  private static org.scalatest.Shell fullstacks;
    descriptor: Lorg/scalatest/Shell;
    flags: (0x000a) ACC_PRIVATE, ACC_STATIC

  private static org.scalatest.Shell stats;
    descriptor: Lorg/scalatest/Shell;
    flags: (0x000a) ACC_PRIVATE, ACC_STATIC

  private static org.scalatest.Shell nocolor;
    descriptor: Lorg/scalatest/Shell;
    flags: (0x000a) ACC_PRIVATE, ACC_STATIC

  private static org.scalatest.Shell nodurations;
    descriptor: Lorg/scalatest/Shell;
    flags: (0x000a) ACC_PRIVATE, ACC_STATIC

  private static org.scalatest.Shell nostacks;
    descriptor: Lorg/scalatest/Shell;
    flags: (0x000a) ACC_PRIVATE, ACC_STATIC

  private static org.scalatest.Shell nostats;
    descriptor: Lorg/scalatest/Shell;
    flags: (0x000a) ACC_PRIVATE, ACC_STATIC

  private static final org.scalatest.ShellImpl defaultShell;
    descriptor: Lorg/scalatest/ShellImpl;
    flags: (0x001a) ACC_PRIVATE, ACC_STATIC, ACC_FINAL

  private static final java.lang.String ScalaTestVersion;
    descriptor: Ljava/lang/String;
    flags: (0x001a) ACC_PRIVATE, ACC_STATIC, ACC_FINAL

  private static volatile int bitmap$0;
    descriptor: I
    flags: (0x004a) ACC_PRIVATE, ACC_STATIC, ACC_VOLATILE

  public static {};
    descriptor: ()V
    flags: (0x0009) ACC_PUBLIC, ACC_STATIC
    Code:
      stack=7, locals=0, args_size=0
         0: new           #2                  // class org/scalatest/package$
         3: dup
         4: invokespecial #28                 // Method "<init>":()V
         7: putstatic     #30                 // Field MODULE$:Lorg/scalatest/package$;
        10: new           #32                 // class org/scalatest/ShellImpl
        13: dup
        14: getstatic     #37                 // Field org/scalatest/ShellImpl$.MODULE$:Lorg/scalatest/ShellImpl$;
        17: invokevirtual #41                 // Method org/scalatest/ShellImpl$.apply$default$1:()Z
        20: getstatic     #37                 // Field org/scalatest/ShellImpl$.MODULE$:Lorg/scalatest/ShellImpl$;
        23: invokevirtual #44                 // Method org/scalatest/ShellImpl$.apply$default$2:()Z
        26: getstatic     #37                 // Field org/scalatest/ShellImpl$.MODULE$:Lorg/scalatest/ShellImpl$;
        29: invokevirtual #47                 // Method org/scalatest/ShellImpl$.apply$default$3:()Z
        32: getstatic     #37                 // Field org/scalatest/ShellImpl$.MODULE$:Lorg/scalatest/ShellImpl$;
        35: invokevirtual #50                 // Method org/scalatest/ShellImpl$.apply$default$4:()Z
        38: getstatic     #37                 // Field org/scalatest/ShellImpl$.MODULE$:Lorg/scalatest/ShellImpl$;
        41: invokevirtual #53                 // Method org/scalatest/ShellImpl$.apply$default$5:()Z
        44: invokespecial #56                 // Method org/scalatest/ShellImpl."<init>":(ZZZZZ)V
        47: putstatic     #58                 // Field defaultShell:Lorg/scalatest/ShellImpl;
        50: getstatic     #63                 // Field org/scalatest/ScalaTestVersions$.MODULE$:Lorg/scalatest/ScalaTestVersions$;
        53: invokevirtual #66                 // Method org/scalatest/ScalaTestVersions$.ScalaTestVersion:()Ljava/lang/String;
        56: putstatic     #68                 // Field ScalaTestVersion:Ljava/lang/String;
        59: return
      LineNumberTable:
        line 21: 0
        line 24: 10
        line 77: 50
        line 21: 59

  private org.scalatest.ShellImpl defaultShell();
    descriptor: ()Lorg/scalatest/ShellImpl;
    flags: (0x0002) ACC_PRIVATE
    Code:
      stack=1, locals=1, args_size=1
         0: getstatic     #58                 // Field defaultShell:Lorg/scalatest/ShellImpl;
         3: areturn
      LineNumberTable:
        line 24: 0
      LocalVariableTable:
        Start  Length  Slot  Name   Signature
            0       4     0  this   Lorg/scalatest/package$;

  private org.scalatest.Shell color$lzycompute();
    descriptor: ()Lorg/scalatest/Shell;
    flags: (0x0002) ACC_PRIVATE
    Code:
      stack=2, locals=2, args_size=1
         0: aload_0
         1: dup
         2: astore_1
         3: monitorenter
         4: getstatic     #74                 // Field bitmap$0:I
         7: iconst_1
         8: iand
         9: iconst_0
        10: if_icmpne     31
        13: aload_0
        14: invokespecial #76                 // Method defaultShell:()Lorg/scalatest/ShellImpl;
        17: invokevirtual #78                 // Method org/scalatest/ShellImpl.color:()Lorg/scalatest/Shell;
        20: putstatic     #80                 // Field color:Lorg/scalatest/Shell;
        23: getstatic     #74                 // Field bitmap$0:I
        26: iconst_1
        27: ior
        28: putstatic     #74                 // Field bitmap$0:I
        31: aload_1
        32: monitorexit
        33: goto          39
        36: aload_1
        37: monitorexit
        38: athrow
        39: getstatic     #80                 // Field color:Lorg/scalatest/Shell;
        42: areturn
      Exception table:
         from    to  target type
             4    31    36   any
      StackMapTable: number_of_entries = 3
        frame_type = 252 /* append */
          offset_delta = 31
          locals = [ class org/scalatest/package$ ]
        frame_type = 68 /* same_locals_1_stack_item */
          stack = [ class java/lang/Throwable ]
        frame_type = 2 /* same */
      LineNumberTable:
        line 29: 0
      LocalVariableTable:
        Start  Length  Slot  Name   Signature
            0      43     0  this   Lorg/scalatest/package$;

  public org.scalatest.Shell color();
    descriptor: ()Lorg/scalatest/Shell;
    flags: (0x0001) ACC_PUBLIC
    Code:
      stack=2, locals=1, args_size=1
         0: getstatic     #74                 // Field bitmap$0:I
         3: iconst_1
         4: iand
         5: iconst_0
         6: if_icmpne     16
         9: aload_0
        10: invokespecial #84                 // Method color$lzycompute:()Lorg/scalatest/Shell;
        13: goto          19
        16: getstatic     #80                 // Field color:Lorg/scalatest/Shell;
        19: areturn
      StackMapTable: number_of_entries = 2
        frame_type = 16 /* same */
        frame_type = 66 /* same_locals_1_stack_item */
          stack = [ class org/scalatest/Shell ]
      LineNumberTable:
        line 29: 0
      LocalVariableTable:
        Start  Length  Slot  Name   Signature
            0      20     0  this   Lorg/scalatest/package$;

  private org.scalatest.Shell durations$lzycompute();
    descriptor: ()Lorg/scalatest/Shell;
    flags: (0x0002) ACC_PRIVATE
    Code:
      stack=2, locals=2, args_size=1
         0: aload_0
         1: dup
         2: astore_1
         3: monitorenter
         4: getstatic     #74                 // Field bitmap$0:I
         7: iconst_2
         8: iand
         9: iconst_0
        10: if_icmpne     31
        13: aload_0
        14: invokespecial #76                 // Method defaultShell:()Lorg/scalatest/ShellImpl;
        17: invokevirtual #89                 // Method org/scalatest/ShellImpl.durations:()Lorg/scalatest/Shell;
        20: putstatic     #91                 // Field durations:Lorg/scalatest/Shell;
        23: getstatic     #74                 // Field bitmap$0:I
        26: iconst_2
        27: ior
        28: putstatic     #74                 // Field bitmap$0:I
        31: aload_1
        32: monitorexit
        33: goto          39
        36: aload_1
        37: monitorexit
        38: athrow
        39: getstatic     #91                 // Field durations:Lorg/scalatest/Shell;
        42: areturn
      Exception table:
         from    to  target type
             4    31    36   any
      StackMapTable: number_of_entries = 3
        frame_type = 252 /* append */
          offset_delta = 31
          locals = [ class org/scalatest/package$ ]
        frame_type = 68 /* same_locals_1_stack_item */
          stack = [ class java/lang/Throwable ]
        frame_type = 2 /* same */
      LineNumberTable:
        line 34: 0
      LocalVariableTable:
        Start  Length  Slot  Name   Signature
            0      43     0  this   Lorg/scalatest/package$;

  public org.scalatest.Shell durations();
    descriptor: ()Lorg/scalatest/Shell;
    flags: (0x0001) ACC_PUBLIC
    Code:
      stack=2, locals=1, args_size=1
         0: getstatic     #74                 // Field bitmap$0:I
         3: iconst_2
         4: iand
         5: iconst_0
         6: if_icmpne     16
         9: aload_0
        10: invokespecial #93                 // Method durations$lzycompute:()Lorg/scalatest/Shell;
        13: goto          19
        16: getstatic     #91                 // Field durations:Lorg/scalatest/Shell;
        19: areturn
      StackMapTable: number_of_entries = 2
        frame_type = 16 /* same */
        frame_type = 66 /* same_locals_1_stack_item */
          stack = [ class org/scalatest/Shell ]
      LineNumberTable:
        line 34: 0
      LocalVariableTable:
        Start  Length  Slot  Name   Signature
            0      20     0  this   Lorg/scalatest/package$;

  private org.scalatest.Shell shortstacks$lzycompute();
    descriptor: ()Lorg/scalatest/Shell;
    flags: (0x0002) ACC_PRIVATE
    Code:
      stack=2, locals=2, args_size=1
         0: aload_0
         1: dup
         2: astore_1
         3: monitorenter
         4: getstatic     #74                 // Field bitmap$0:I
         7: iconst_4
         8: iand
         9: iconst_0
        10: if_icmpne     31
        13: aload_0
        14: invokespecial #76                 // Method defaultShell:()Lorg/scalatest/ShellImpl;
        17: invokevirtual #96                 // Method org/scalatest/ShellImpl.shortstacks:()Lorg/scalatest/Shell;
        20: putstatic     #98                 // Field shortstacks:Lorg/scalatest/Shell;
        23: getstatic     #74                 // Field bitmap$0:I
        26: iconst_4
        27: ior
        28: putstatic     #74                 // Field bitmap$0:I
        31: aload_1
        32: monitorexit
        33: goto          39
        36: aload_1
        37: monitorexit
        38: athrow
        39: getstatic     #98                 // Field shortstacks:Lorg/scalatest/Shell;
        42: areturn
      Exception table:
         from    to  target type
             4    31    36   any
      StackMapTable: number_of_entries = 3
        frame_type = 252 /* append */
          offset_delta = 31
          locals = [ class org/scalatest/package$ ]
        frame_type = 68 /* same_locals_1_stack_item */
          stack = [ class java/lang/Throwable ]
        frame_type = 2 /* same */
      LineNumberTable:
        line 39: 0
      LocalVariableTable:
        Start  Length  Slot  Name   Signature
            0      43     0  this   Lorg/scalatest/package$;

  public org.scalatest.Shell shortstacks();
    descriptor: ()Lorg/scalatest/Shell;
    flags: (0x0001) ACC_PUBLIC
    Code:
      stack=2, locals=1, args_size=1
         0: getstatic     #74                 // Field bitmap$0:I
         3: iconst_4
         4: iand
         5: iconst_0
         6: if_icmpne     16
         9: aload_0
        10: invokespecial #100                // Method shortstacks$lzycompute:()Lorg/scalatest/Shell;
        13: goto          19
        16: getstatic     #98                 // Field shortstacks:Lorg/scalatest/Shell;
        19: areturn
      StackMapTable: number_of_entries = 2
        frame_type = 16 /* same */
        frame_type = 66 /* same_locals_1_stack_item */
          stack = [ class org/scalatest/Shell ]
      LineNumberTable:
        line 39: 0
      LocalVariableTable:
        Start  Length  Slot  Name   Signature
            0      20     0  this   Lorg/scalatest/package$;

  private org.scalatest.Shell fullstacks$lzycompute();
    descriptor: ()Lorg/scalatest/Shell;
    flags: (0x0002) ACC_PRIVATE
    Code:
      stack=2, locals=2, args_size=1
         0: aload_0
         1: dup
         2: astore_1
         3: monitorenter
         4: getstatic     #74                 // Field bitmap$0:I
         7: bipush        8
         9: iand
        10: iconst_0
        11: if_icmpne     33
        14: aload_0
        15: invokespecial #76                 // Method defaultShell:()Lorg/scalatest/ShellImpl;
        18: invokevirtual #103                // Method org/scalatest/ShellImpl.fullstacks:()Lorg/scalatest/Shell;
        21: putstatic     #105                // Field fullstacks:Lorg/scalatest/Shell;
        24: getstatic     #74                 // Field bitmap$0:I
        27: bipush        8
        29: ior
        30: putstatic     #74                 // Field bitmap$0:I
        33: aload_1
        34: monitorexit
        35: goto          41
        38: aload_1
        39: monitorexit
        40: athrow
        41: getstatic     #105                // Field fullstacks:Lorg/scalatest/Shell;
        44: areturn
      Exception table:
         from    to  target type
             4    33    38   any
      StackMapTable: number_of_entries = 3
        frame_type = 252 /* append */
          offset_delta = 33
          locals = [ class org/scalatest/package$ ]
        frame_type = 68 /* same_locals_1_stack_item */
          stack = [ class java/lang/Throwable ]
        frame_type = 2 /* same */
      LineNumberTable:
        line 44: 0
      LocalVariableTable:
        Start  Length  Slot  Name   Signature
            0      45     0  this   Lorg/scalatest/package$;

  public org.scalatest.Shell fullstacks();
    descriptor: ()Lorg/scalatest/Shell;
    flags: (0x0001) ACC_PUBLIC
    Code:
      stack=2, locals=1, args_size=1
         0: getstatic     #74                 // Field bitmap$0:I
         3: bipush        8
         5: iand
         6: iconst_0
         7: if_icmpne     17
        10: aload_0
        11: invokespecial #107                // Method fullstacks$lzycompute:()Lorg/scalatest/Shell;
        14: goto          20
        17: getstatic     #105                // Field fullstacks:Lorg/scalatest/Shell;
        20: areturn
      StackMapTable: number_of_entries = 2
        frame_type = 17 /* same */
        frame_type = 66 /* same_locals_1_stack_item */
          stack = [ class org/scalatest/Shell ]
      LineNumberTable:
        line 44: 0
      LocalVariableTable:
        Start  Length  Slot  Name   Signature
            0      21     0  this   Lorg/scalatest/package$;

  private org.scalatest.Shell stats$lzycompute();
    descriptor: ()Lorg/scalatest/Shell;
    flags: (0x0002) ACC_PRIVATE
    Code:
      stack=2, locals=2, args_size=1
         0: aload_0
         1: dup
         2: astore_1
         3: monitorenter
         4: getstatic     #74                 // Field bitmap$0:I
         7: bipush        16
         9: iand
        10: iconst_0
        11: if_icmpne     33
        14: aload_0
        15: invokespecial #76                 // Method defaultShell:()Lorg/scalatest/ShellImpl;
        18: invokevirtual #110                // Method org/scalatest/ShellImpl.stats:()Lorg/scalatest/Shell;
        21: putstatic     #112                // Field stats:Lorg/scalatest/Shell;
        24: getstatic     #74                 // Field bitmap$0:I
        27: bipush        16
        29: ior
        30: putstatic     #74                 // Field bitmap$0:I
        33: aload_1
        34: monitorexit
        35: goto          41
        38: aload_1
        39: monitorexit
        40: athrow
        41: getstatic     #112                // Field stats:Lorg/scalatest/Shell;
        44: areturn
      Exception table:
         from    to  target type
             4    33    38   any
      StackMapTable: number_of_entries = 3
        frame_type = 252 /* append */
          offset_delta = 33
          locals = [ class org/scalatest/package$ ]
        frame_type = 68 /* same_locals_1_stack_item */
          stack = [ class java/lang/Throwable ]
        frame_type = 2 /* same */
      LineNumberTable:
        line 49: 0
      LocalVariableTable:
        Start  Length  Slot  Name   Signature
            0      45     0  this   Lorg/scalatest/package$;

  public org.scalatest.Shell stats();
    descriptor: ()Lorg/scalatest/Shell;
    flags: (0x0001) ACC_PUBLIC
    Code:
      stack=2, locals=1, args_size=1
         0: getstatic     #74                 // Field bitmap$0:I
         3: bipush        16
         5: iand
         6: iconst_0
         7: if_icmpne     17
        10: aload_0
        11: invokespecial #114                // Method stats$lzycompute:()Lorg/scalatest/Shell;
        14: goto          20
        17: getstatic     #112                // Field stats:Lorg/scalatest/Shell;
        20: areturn
      StackMapTable: number_of_entries = 2
        frame_type = 17 /* same */
        frame_type = 66 /* same_locals_1_stack_item */
          stack = [ class org/scalatest/Shell ]
      LineNumberTable:
        line 49: 0
      LocalVariableTable:
        Start  Length  Slot  Name   Signature
            0      21     0  this   Lorg/scalatest/package$;

  private org.scalatest.Shell nocolor$lzycompute();
    descriptor: ()Lorg/scalatest/Shell;
    flags: (0x0002) ACC_PRIVATE
    Code:
      stack=2, locals=2, args_size=1
         0: aload_0
         1: dup
         2: astore_1
         3: monitorenter
         4: getstatic     #74                 // Field bitmap$0:I
         7: bipush        32
         9: iand
        10: iconst_0
        11: if_icmpne     33
        14: aload_0
        15: invokespecial #76                 // Method defaultShell:()Lorg/scalatest/ShellImpl;
        18: invokevirtual #117                // Method org/scalatest/ShellImpl.nocolor:()Lorg/scalatest/Shell;
        21: putstatic     #119                // Field nocolor:Lorg/scalatest/Shell;
        24: getstatic     #74                 // Field bitmap$0:I
        27: bipush        32
        29: ior
        30: putstatic     #74                 // Field bitmap$0:I
        33: aload_1
        34: monitorexit
        35: goto          41
        38: aload_1
        39: monitorexit
        40: athrow
        41: getstatic     #119                // Field nocolor:Lorg/scalatest/Shell;
        44: areturn
      Exception table:
         from    to  target type
             4    33    38   any
      StackMapTable: number_of_entries = 3
        frame_type = 252 /* append */
          offset_delta = 33
          locals = [ class org/scalatest/package$ ]
        frame_type = 68 /* same_locals_1_stack_item */
          stack = [ class java/lang/Throwable ]
        frame_type = 2 /* same */
      LineNumberTable:
        line 54: 0
      LocalVariableTable:
        Start  Length  Slot  Name   Signature
            0      45     0  this   Lorg/scalatest/package$;

  public org.scalatest.Shell nocolor();
    descriptor: ()Lorg/scalatest/Shell;
    flags: (0x0001) ACC_PUBLIC
    Code:
      stack=2, locals=1, args_size=1
         0: getstatic     #74                 // Field bitmap$0:I
         3: bipush        32
         5: iand
         6: iconst_0
         7: if_icmpne     17
        10: aload_0
        11: invokespecial #121                // Method nocolor$lzycompute:()Lorg/scalatest/Shell;
        14: goto          20
        17: getstatic     #119                // Field nocolor:Lorg/scalatest/Shell;
        20: areturn
      StackMapTable: number_of_entries = 2
        frame_type = 17 /* same */
        frame_type = 66 /* same_locals_1_stack_item */
          stack = [ class org/scalatest/Shell ]
      LineNumberTable:
        line 54: 0
      LocalVariableTable:
        Start  Length  Slot  Name   Signature
            0      21     0  this   Lorg/scalatest/package$;

  private org.scalatest.Shell nodurations$lzycompute();
    descriptor: ()Lorg/scalatest/Shell;
    flags: (0x0002) ACC_PRIVATE
    Code:
      stack=2, locals=2, args_size=1
         0: aload_0
         1: dup
         2: astore_1
         3: monitorenter
         4: getstatic     #74                 // Field bitmap$0:I
         7: bipush        64
         9: iand
        10: iconst_0
        11: if_icmpne     33
        14: aload_0
        15: invokespecial #76                 // Method defaultShell:()Lorg/scalatest/ShellImpl;
        18: invokevirtual #124                // Method org/scalatest/ShellImpl.nodurations:()Lorg/scalatest/Shell;
        21: putstatic     #126                // Field nodurations:Lorg/scalatest/Shell;
        24: getstatic     #74                 // Field bitmap$0:I
        27: bipush        64
        29: ior
        30: putstatic     #74                 // Field bitmap$0:I
        33: aload_1
        34: monitorexit
        35: goto          41
        38: aload_1
        39: monitorexit
        40: athrow
        41: getstatic     #126                // Field nodurations:Lorg/scalatest/Shell;
        44: areturn
      Exception table:
         from    to  target type
             4    33    38   any
      StackMapTable: number_of_entries = 3
        frame_type = 252 /* append */
          offset_delta = 33
          locals = [ class org/scalatest/package$ ]
        frame_type = 68 /* same_locals_1_stack_item */
          stack = [ class java/lang/Throwable ]
        frame_type = 2 /* same */
      LineNumberTable:
        line 59: 0
      LocalVariableTable:
        Start  Length  Slot  Name   Signature
            0      45     0  this   Lorg/scalatest/package$;

  public org.scalatest.Shell nodurations();
    descriptor: ()Lorg/scalatest/Shell;
    flags: (0x0001) ACC_PUBLIC
    Code:
      stack=2, locals=1, args_size=1
         0: getstatic     #74                 // Field bitmap$0:I
         3: bipush        64
         5: iand
         6: iconst_0
         7: if_icmpne     17
        10: aload_0
        11: invokespecial #128                // Method nodurations$lzycompute:()Lorg/scalatest/Shell;
        14: goto          20
        17: getstatic     #126                // Field nodurations:Lorg/scalatest/Shell;
        20: areturn
      StackMapTable: number_of_entries = 2
        frame_type = 17 /* same */
        frame_type = 66 /* same_locals_1_stack_item */
          stack = [ class org/scalatest/Shell ]
      LineNumberTable:
        line 59: 0
      LocalVariableTable:
        Start  Length  Slot  Name   Signature
            0      21     0  this   Lorg/scalatest/package$;

  private org.scalatest.Shell nostacks$lzycompute();
    descriptor: ()Lorg/scalatest/Shell;
    flags: (0x0002) ACC_PRIVATE
    Code:
      stack=2, locals=2, args_size=1
         0: aload_0
         1: dup
         2: astore_1
         3: monitorenter
         4: getstatic     #74                 // Field bitmap$0:I
         7: sipush        128
        10: iand
        11: iconst_0
        12: if_icmpne     35
        15: aload_0
        16: invokespecial #76                 // Method defaultShell:()Lorg/scalatest/ShellImpl;
        19: invokevirtual #131                // Method org/scalatest/ShellImpl.nostacks:()Lorg/scalatest/Shell;
        22: putstatic     #133                // Field nostacks:Lorg/scalatest/Shell;
        25: getstatic     #74                 // Field bitmap$0:I
        28: sipush        128
        31: ior
        32: putstatic     #74                 // Field bitmap$0:I
        35: aload_1
        36: monitorexit
        37: goto          43
        40: aload_1
        41: monitorexit
        42: athrow
        43: getstatic     #133                // Field nostacks:Lorg/scalatest/Shell;
        46: areturn
      Exception table:
         from    to  target type
             4    35    40   any
      StackMapTable: number_of_entries = 3
        frame_type = 252 /* append */
          offset_delta = 35
          locals = [ class org/scalatest/package$ ]
        frame_type = 68 /* same_locals_1_stack_item */
          stack = [ class java/lang/Throwable ]
        frame_type = 2 /* same */
      LineNumberTable:
        line 64: 0
      LocalVariableTable:
        Start  Length  Slot  Name   Signature
            0      47     0  this   Lorg/scalatest/package$;

  public org.scalatest.Shell nostacks();
    descriptor: ()Lorg/scalatest/Shell;
    flags: (0x0001) ACC_PUBLIC
    Code:
      stack=2, locals=1, args_size=1
         0: getstatic     #74                 // Field bitmap$0:I
         3: sipush        128
         6: iand
         7: iconst_0
         8: if_icmpne     18
        11: aload_0
        12: invokespecial #135                // Method nostacks$lzycompute:()Lorg/scalatest/Shell;
        15: goto          21
        18: getstatic     #133                // Field nostacks:Lorg/scalatest/Shell;
        21: areturn
      StackMapTable: number_of_entries = 2
        frame_type = 18 /* same */
        frame_type = 66 /* same_locals_1_stack_item */
          stack = [ class org/scalatest/Shell ]
      LineNumberTable:
        line 64: 0
      LocalVariableTable:
        Start  Length  Slot  Name   Signature
            0      22     0  this   Lorg/scalatest/package$;

  private org.scalatest.Shell nostats$lzycompute();
    descriptor: ()Lorg/scalatest/Shell;
    flags: (0x0002) ACC_PRIVATE
    Code:
      stack=2, locals=2, args_size=1
         0: aload_0
         1: dup
         2: astore_1
         3: monitorenter
         4: getstatic     #74                 // Field bitmap$0:I
         7: sipush        256
        10: iand
        11: iconst_0
        12: if_icmpne     35
        15: aload_0
        16: invokespecial #76                 // Method defaultShell:()Lorg/scalatest/ShellImpl;
        19: invokevirtual #138                // Method org/scalatest/ShellImpl.nostats:()Lorg/scalatest/Shell;
        22: putstatic     #140                // Field nostats:Lorg/scalatest/Shell;
        25: getstatic     #74                 // Field bitmap$0:I
        28: sipush        256
        31: ior
        32: putstatic     #74                 // Field bitmap$0:I
        35: aload_1
        36: monitorexit
        37: goto          43
        40: aload_1
        41: monitorexit
        42: athrow
        43: getstatic     #140                // Field nostats:Lorg/scalatest/Shell;
        46: areturn
      Exception table:
         from    to  target type
             4    35    40   any
      StackMapTable: number_of_entries = 3
        frame_type = 252 /* append */
          offset_delta = 35
          locals = [ class org/scalatest/package$ ]
        frame_type = 68 /* same_locals_1_stack_item */
          stack = [ class java/lang/Throwable ]
        frame_type = 2 /* same */
      LineNumberTable:
        line 69: 0
      LocalVariableTable:
        Start  Length  Slot  Name   Signature
            0      47     0  this   Lorg/scalatest/package$;

  public org.scalatest.Shell nostats();
    descriptor: ()Lorg/scalatest/Shell;
    flags: (0x0001) ACC_PUBLIC
    Code:
      stack=2, locals=1, args_size=1
         0: getstatic     #74                 // Field bitmap$0:I
         3: sipush        256
         6: iand
         7: iconst_0
         8: if_icmpne     18
        11: aload_0
        12: invokespecial #142                // Method nostats$lzycompute:()Lorg/scalatest/Shell;
        15: goto          21
        18: getstatic     #140                // Field nostats:Lorg/scalatest/Shell;
        21: areturn
      StackMapTable: number_of_entries = 2
        frame_type = 18 /* same */
        frame_type = 66 /* same_locals_1_stack_item */
          stack = [ class org/scalatest/Shell ]
      LineNumberTable:
        line 69: 0
      LocalVariableTable:
        Start  Length  Slot  Name   Signature
            0      22     0  this   Lorg/scalatest/package$;

  public java.lang.String ScalaTestVersion();
    descriptor: ()Ljava/lang/String;
    flags: (0x0001) ACC_PUBLIC
    Code:
      stack=1, locals=1, args_size=1
         0: getstatic     #68                 // Field ScalaTestVersion:Ljava/lang/String;
         3: areturn
      LineNumberTable:
        line 77: 0
      LocalVariableTable:
        Start  Length  Slot  Name   Signature
            0       4     0  this   Lorg/scalatest/package$;

  private org.scalatest.package$();
    descriptor: ()V
    flags: (0x0002) ACC_PRIVATE
    Code:
      stack=1, locals=1, args_size=1
         0: aload_0
         1: invokespecial #143                // Method java/lang/Object."<init>":()V
         4: return
      LineNumberTable:
        line 87: 0
        line 21: 4
      LocalVariableTable:
        Start  Length  Slot  Name   Signature
            0       5     0  this   Lorg/scalatest/package$;
}
SourceFile: "package.scala"
  ScalaInlineInfo: length = 0x6D (unknown attribute)
   01 01 00 15 00 1A 00 19 01 00 14 00 40 01 00 08
   00 48 01 00 47 00 48 01 00 12 00 45 01 00 0A 00
   48 01 00 57 00 48 01 00 0C 00 48 01 00 65 00 48
   01 00 0E 00 48 01 00 73 00 48 01 00 0F 00 48 01
   00 7A 00 48 01 00 10 00 48 01 00 81 00 48 01 00
   11 00 48 01 00 88 00 48 01 00 0B 00 48 01 00 5E
   00 48 01 00 0D 00 48 01 00 6C 00 48 01
  Scala: length = 0x0 (unknown attribute)

