Classfile /Users/mw/Projects/slang-braindump/.jar/jar8/assemble/slang-braindump/assemble/content/org/scalatest/PathMessageRecordingDocumenter.class
  Last modified May 29, 2022; size 7855 bytes
  SHA-256 checksum f9a1811e3224df3dbb7be94a4c96dc33465369b4b9863e589c2089cf022f045a
  Compiled from "ConcurrentInformer.scala"
public class org.scalatest.PathMessageRecordingDocumenter extends org.scalatest.ThreadAwareness implements org.scalatest.Documenter
  minor version: 0
  major version: 52
  flags: (0x0021) ACC_PUBLIC, ACC_SUPER
  this_class: #2                          // org/scalatest/PathMessageRecordingDocumenter
  super_class: #4                         // org/scalatest/ThreadAwareness
  interfaces: 1, fields: 2, methods: 7, attributes: 6
Constant pool:
    #1 = Utf8               org/scalatest/PathMessageRecordingDocumenter
    #2 = Class              #1            // org/scalatest/PathMessageRecordingDocumenter
    #3 = Utf8               org/scalatest/ThreadAwareness
    #4 = Class              #3            // org/scalatest/ThreadAwareness
    #5 = Utf8               org/scalatest/Documenter
    #6 = Class              #5            // org/scalatest/Documenter
    #7 = Utf8               ConcurrentInformer.scala
    #8 = Utf8               Lscala/reflect/ScalaSignature;
    #9 = Utf8               bytes
   #10 = Utf8               \u0006\u0005\u0005\u0005b!B\u0007\u000f\u00019\u0011\u0002\u0002\u0003\u000e\u0001\u0005\u0003\u0005\u000b\u0011\u0002\u000f\t\u000b)\u0003A\u0011A&\u0006\t9\u0003\u0001a\u0014\u0005\b%\u0002\u0011\r\u0011\"\u0003T\u0011\u0019I\u0006\u0001)A\u0005)\")!\f\u0001C\u00057\")\u0011\r\u0001C\u0001E\")q\u000e\u0001C\u0001a\u001eA\u0011q\u0002\b\t\u00029\t\tBB\u0004\u000e\u001d!\u0005a\"a\u0005\t\r)SA\u0011AA\u000e\u0011\u0019\t\'\u0002\"\u0001\u0002\u001e\tq\u0002+\u0019;i\u001b\u0016\u001c8/Y4f%\u0016\u001cwN\u001d3j]\u001e$unY;nK:$XM\u001d\u0006\u0003\u001fA\t\u0011b]2bY\u0006$Xm\u001d;\u000b\u0003E\t1a\u001c:h\'\r\u00011c\u0006\t\u0003)Ui\u0011AD\u0005\u0003-9\u0011q\u0002\u00165sK\u0006$\u0017i^1sK:,7o\u001d\t\u0003)aI!!\u0007\b\u0003\u0015\u0011{7-^7f]R,\'/\u0001\u0005fm\u0016tGOR;o\u0007\u0001\u0001R\"\b\u0011#[5\u00024G\u000e\u0012:[q\"U\"\u0001\u0010\u000b\u0003}\tQa]2bY\u0006L!!\t\u0010\u0003\u0015\u0019+hn\u0019;j_:\f\u0004\u0007\u0005\u0002$U9\u0011A\u0005\u000b\t\u0003Kyi\u0011A\n\u0006\u0003Om\ta\u0001\u0010:p_Rt\u0014BA\u0015\u001f\u0003\u0019\u0001&/\u001a3fM&\u00111\u0006\f\u0002\u0007\'R\u0014\u0018N\\4\u000b\u0005%r\u0002CA\u000f/\u0013\tycDA\u0004C_>dW-\u00198\u0011\u0005Q\t\u0014B\u0001\u001a\u000f\u0005\u0015\u0019V/\u001b;f!\t!B\'\u0003\u00026\u001d\tA!+\u001a9peR,\'\u000f\u0005\u0002\u0015o%\u0011\u0001H\u0004\u0002\b)J\f7m[3s!\ti\"(\u0003\u0002<=\t\u0019\u0011J\u001c;\u0011\u0005u\u0012U\"\u0001 \u000b\u0005}\u0002\u0015\u0001\u00027b]\u001eT\u0011!Q\u0001\u0005U\u00064\u0018-\u0003\u0002D}\t1A\u000b\u001b:fC\u0012\u0004\"!\u0012%\u000e\u0003\u0019S!a\u0012\b\u0002\r\u00154XM\u001c;t\u0013\tIeIA\bSK\u000e|\'\u000fZ1cY\u0016,e/\u001a8u\u0003\u0019a\u0014N\\5u}Q\u0011A*\u0014\t\u0003)\u0001AQA\u0007\u0002A\u0002q\u00111\u0001V;q!\u0015i\u0002K\t\u001f.\u0013\t\tfD\u0001\u0004UkBdWmM\u0001\t[\u0016\u001c8/Y4fgV\tA\u000bE\u0002\u0015+^K!A\u0016\b\u0003+\r{gnY;se\u0016tG\u000fT5oW\u0016$\u0017+^3vKB\u0011\u0001lA\u0007\u0002\u0001\u0005IQ.Z:tC\u001e,7\u000fI\u0001\u0007e\u0016\u001cwN\u001d3\u0015\u0005q{\u0006CA\u000f^\u0013\tqfD\u0001\u0003V]&$\b\"\u00021\u0007\u0001\u0004\u0011\u0013aB7fgN\fw-Z\u0001\u0006CB\u0004H.\u001f\u000b\u0003G:$\"\u0001\u00183\t\u000b\u0015<\u00019\u00014\u0002\u0007A|7\u000f\u0005\u0002hY6\t\u0001N\u0003\u0002jU\u000611o\\;sG\u0016T!a\u001b\t\u0002\u0013M\u001c\u0017\r\\1di&\u001c\u0017BA7i\u0005!\u0001vn]5uS>t\u0007\"\u00021\b\u0001\u0004\u0011\u0013A\u0004:fG>\u0014H-\u001a3Fm\u0016tGo\u001d\u000b\fcf\\Xp`A\u0002\u0003\u000f\tY\u0001E\u0002so\u0012k\u0011a\u001d\u0006\u0003iV\f\u0011\"[7nkR\f\'\r\\3\u000b\u0005Yt\u0012AC2pY2,7\r^5p]&\u0011\u0001p\u001d\u0002\u000b\u0013:$W\r_3e\'\u0016\f\b\"\u0002>\t\u0001\u0004i\u0013A\u0004;fgR<\u0016m\u001d)f]\u0012Lgn\u001a\u0005\u0006y\"\u0001\r\u0001M\u0001\ti\",7+^5uK\")a\u0010\u0003a\u0001g\u00051!/\u001a9peRDa!!\u0001\t\u0001\u00041\u0014a\u0002;sC\u000e\\WM\u001d\u0005\u0007\u0003\u000bA\u0001\u0019\u0001\u0012\u0002\u0011Q,7\u000f\u001e(b[\u0016Da!!\u0003\t\u0001\u0004I\u0014aC5oI\u0016tG/\u0019;j_:Da!!\u0004\t\u0001\u0004i\u0013aC5oG2,H-Z%d_:\fa\u0004U1uQ6+7o]1hKJ+7m\u001c:eS:<Gi\\2v[\u0016tG/\u001a:\u0011\u0005QQ1c\u0001\u0006\u0002\u0016A\u0019Q$a\u0006\n\u0007\u0005eaD\u0001\u0004B]f\u0014VM\u001a\u000b\u0003\u0003#!2\u0001TA\u0010\u0011\u0015QB\u00021\u0001\u001d\u0001
   #11 = Utf8               java/lang/invoke/MethodHandles$Lookup
   #12 = Class              #11           // java/lang/invoke/MethodHandles$Lookup
   #13 = Utf8               java/lang/invoke/MethodHandles
   #14 = Class              #13           // java/lang/invoke/MethodHandles
   #15 = Utf8               Lookup
   #16 = Utf8               org/scalactic/Requirements$RequirementsHelper
   #17 = Class              #16           // org/scalactic/Requirements$RequirementsHelper
   #18 = Utf8               org/scalactic/Requirements
   #19 = Class              #18           // org/scalactic/Requirements
   #20 = Utf8               RequirementsHelper
   #21 = Utf8               eventFun
   #22 = Utf8               Lscala/Function10;
   #23 = Utf8               Lscala/Function10<Ljava/lang/String;Ljava/lang/Object;Ljava/lang/Object;Lorg/scalatest/Suite;Lorg/scalatest/Reporter;Lorg/scalatest/Tracker;Ljava/lang/String;Ljava/lang/Object;Ljava/lang/Object;Ljava/lang/Thread;Lorg/scalatest/events/RecordableEvent;>;
   #24 = Utf8               messages
   #25 = Utf8               Lorg/scalatest/ConcurrentLinkedQueue;
   #26 = Utf8               Lorg/scalatest/ConcurrentLinkedQueue<Lscala/Tuple3<Ljava/lang/String;Ljava/lang/Thread;Ljava/lang/Object;>;>;
   #27 = Utf8               ()Lorg/scalatest/ConcurrentLinkedQueue;
   #28 = Utf8               ()Lorg/scalatest/ConcurrentLinkedQueue<Lscala/Tuple3<Ljava/lang/String;Ljava/lang/Thread;Ljava/lang/Object;>;>;
   #29 = NameAndType        #24:#25       // messages:Lorg/scalatest/ConcurrentLinkedQueue;
   #30 = Fieldref           #2.#29        // org/scalatest/PathMessageRecordingDocumenter.messages:Lorg/scalatest/ConcurrentLinkedQueue;
   #31 = Utf8               this
   #32 = Utf8               Lorg/scalatest/PathMessageRecordingDocumenter;
   #33 = Utf8               record
   #34 = Utf8               (Ljava/lang/String;)V
   #35 = Utf8               message
   #36 = NameAndType        #24:#27       // messages:()Lorg/scalatest/ConcurrentLinkedQueue;
   #37 = Methodref          #2.#36        // org/scalatest/PathMessageRecordingDocumenter.messages:()Lorg/scalatest/ConcurrentLinkedQueue;
   #38 = Utf8               scala/Tuple3
   #39 = Class              #38           // scala/Tuple3
   #40 = Utf8               java/lang/Thread
   #41 = Class              #40           // java/lang/Thread
   #42 = Utf8               currentThread
   #43 = Utf8               ()Ljava/lang/Thread;
   #44 = NameAndType        #42:#43       // currentThread:()Ljava/lang/Thread;
   #45 = Methodref          #41.#44       // java/lang/Thread.currentThread:()Ljava/lang/Thread;
   #46 = Utf8               isConstructingThread
   #47 = Utf8               ()Z
   #48 = NameAndType        #46:#47       // isConstructingThread:()Z
   #49 = Methodref          #2.#48        // org/scalatest/PathMessageRecordingDocumenter.isConstructingThread:()Z
   #50 = Utf8               scala/runtime/BoxesRunTime
   #51 = Class              #50           // scala/runtime/BoxesRunTime
   #52 = Utf8               boxToBoolean
   #53 = Utf8               (Z)Ljava/lang/Boolean;
   #54 = NameAndType        #52:#53       // boxToBoolean:(Z)Ljava/lang/Boolean;
   #55 = Methodref          #51.#54       // scala/runtime/BoxesRunTime.boxToBoolean:(Z)Ljava/lang/Boolean;
   #56 = Utf8               <init>
   #57 = Utf8               (Ljava/lang/Object;Ljava/lang/Object;Ljava/lang/Object;)V
   #58 = NameAndType        #56:#57       // "<init>":(Ljava/lang/Object;Ljava/lang/Object;Ljava/lang/Object;)V
   #59 = Methodref          #39.#58       // scala/Tuple3."<init>":(Ljava/lang/Object;Ljava/lang/Object;Ljava/lang/Object;)V
   #60 = Utf8               org/scalatest/ConcurrentLinkedQueue
   #61 = Class              #60           // org/scalatest/ConcurrentLinkedQueue
   #62 = Utf8               add
   #63 = Utf8               (Ljava/lang/Object;)V
   #64 = NameAndType        #62:#63       // add:(Ljava/lang/Object;)V
   #65 = Methodref          #61.#64       // org/scalatest/ConcurrentLinkedQueue.add:(Ljava/lang/Object;)V
   #66 = Utf8               Ljava/lang/String;
   #67 = Utf8               apply
   #68 = Utf8               (Ljava/lang/String;Lorg/scalactic/source/Position;)V
   #69 = Utf8               pos
   #70 = Utf8               org/scalactic/Requirements$
   #71 = Class              #70           // org/scalactic/Requirements$
   #72 = Utf8               MODULE$
   #73 = Utf8               Lorg/scalactic/Requirements$;
   #74 = NameAndType        #72:#73       // MODULE$:Lorg/scalactic/Requirements$;
   #75 = Fieldref           #71.#74       // org/scalactic/Requirements$.MODULE$:Lorg/scalactic/Requirements$;
   #76 = Utf8               requirementsHelper
   #77 = Utf8               ()Lorg/scalactic/Requirements$RequirementsHelper;
   #78 = NameAndType        #76:#77       // requirementsHelper:()Lorg/scalactic/Requirements$RequirementsHelper;
   #79 = Methodref          #71.#78       // org/scalactic/Requirements$.requirementsHelper:()Lorg/scalactic/Requirements$RequirementsHelper;
   #80 = Utf8               java/lang/String
   #81 = Class              #80           // java/lang/String
   #82 = String             #35           // message
   #83 = Utf8               [Ljava/lang/Object;
   #84 = Class              #83           // "[Ljava/lang/Object;"
   #85 = Utf8               [Ljava/lang/String;
   #86 = Class              #85           // "[Ljava/lang/String;"
   #87 = Utf8               java/lang/Object
   #88 = Class              #87           // java/lang/Object
   #89 = Utf8               org/scalactic/Prettifier$
   #90 = Class              #89           // org/scalactic/Prettifier$
   #91 = Utf8               Lorg/scalactic/Prettifier$;
   #92 = NameAndType        #72:#91       // MODULE$:Lorg/scalactic/Prettifier$;
   #93 = Fieldref           #90.#92       // org/scalactic/Prettifier$.MODULE$:Lorg/scalactic/Prettifier$;
   #94 = Utf8               default
   #95 = Utf8               ()Lorg/scalactic/Prettifier;
   #96 = NameAndType        #94:#95       // default:()Lorg/scalactic/Prettifier;
   #97 = Methodref          #90.#96       // org/scalactic/Prettifier$.default:()Lorg/scalactic/Prettifier;
   #98 = Utf8               macroRequireNonNull
   #99 = Utf8               ([Ljava/lang/String;[Ljava/lang/Object;Lorg/scalactic/Prettifier;Lorg/scalactic/source/Position;)V
  #100 = NameAndType        #98:#99       // macroRequireNonNull:([Ljava/lang/String;[Ljava/lang/Object;Lorg/scalactic/Prettifier;Lorg/scalactic/source/Position;)V
  #101 = Methodref          #17.#100      // org/scalactic/Requirements$RequirementsHelper.macroRequireNonNull:([Ljava/lang/String;[Ljava/lang/Object;Lorg/scalactic/Prettifier;Lorg/scalactic/source/Position;)V
  #102 = NameAndType        #33:#34       // record:(Ljava/lang/String;)V
  #103 = Methodref          #2.#102       // org/scalatest/PathMessageRecordingDocumenter.record:(Ljava/lang/String;)V
  #104 = Utf8               Lorg/scalactic/source/Position;
  #105 = Utf8               recordedEvents
  #106 = Utf8               (ZLorg/scalatest/Suite;Lorg/scalatest/Reporter;Lorg/scalatest/Tracker;Ljava/lang/String;IZ)Lscala/collection/immutable/IndexedSeq;
  #107 = Utf8               (ZLorg/scalatest/Suite;Lorg/scalatest/Reporter;Lorg/scalatest/Tracker;Ljava/lang/String;IZ)Lscala/collection/immutable/IndexedSeq<Lorg/scalatest/events/RecordableEvent;>;
  #108 = Utf8               testWasPending
  #109 = Utf8               theSuite
  #110 = Utf8               report
  #111 = Utf8               tracker
  #112 = Utf8               testName
  #113 = Utf8               indentation
  #114 = Utf8               includeIcon
  #115 = Utf8               scala/package$
  #116 = Class              #115          // scala/package$
  #117 = Utf8               Lscala/package$;
  #118 = NameAndType        #72:#117      // MODULE$:Lscala/package$;
  #119 = Fieldref           #116.#118     // scala/package$.MODULE$:Lscala/package$;
  #120 = Utf8               Vector
  #121 = Utf8               ()Lscala/collection/immutable/Vector$;
  #122 = NameAndType        #120:#121     // Vector:()Lscala/collection/immutable/Vector$;
  #123 = Methodref          #116.#122     // scala/package$.Vector:()Lscala/collection/immutable/Vector$;
  #124 = Utf8               scala/collection/immutable/Vector$
  #125 = Class              #124          // scala/collection/immutable/Vector$
  #126 = Utf8               empty
  #127 = Utf8               ()Lscala/collection/immutable/Vector;
  #128 = NameAndType        #126:#127     // empty:()Lscala/collection/immutable/Vector;
  #129 = Methodref          #125.#128     // scala/collection/immutable/Vector$.empty:()Lscala/collection/immutable/Vector;
  #130 = Utf8               asScala
  #131 = Utf8               ()Lscala/collection/Iterable;
  #132 = NameAndType        #130:#131     // asScala:()Lscala/collection/Iterable;
  #133 = Methodref          #61.#132      // org/scalatest/ConcurrentLinkedQueue.asScala:()Lscala/collection/Iterable;
  #134 = Utf8               (Ljava/lang/Object;)Ljava/lang/Object;
  #135 = MethodType         #134          //  (Ljava/lang/Object;)Ljava/lang/Object;
  #136 = Utf8               $anonfun$recordedEvents$5
  #137 = Utf8               (Lorg/scalatest/PathMessageRecordingDocumenter;ZLorg/scalatest/Suite;Lorg/scalatest/Reporter;Lorg/scalatest/Tracker;Ljava/lang/String;IZLscala/Tuple3;)Lorg/scalatest/events/RecordableEvent;
  #138 = NameAndType        #136:#137     // $anonfun$recordedEvents$5:(Lorg/scalatest/PathMessageRecordingDocumenter;ZLorg/scalatest/Suite;Lorg/scalatest/Reporter;Lorg/scalatest/Tracker;Ljava/lang/String;IZLscala/Tuple3;)Lorg/scalatest/events/RecordableEvent;
  #139 = Methodref          #2.#138       // org/scalatest/PathMessageRecordingDocumenter.$anonfun$recordedEvents$5:(Lorg/scalatest/PathMessageRecordingDocumenter;ZLorg/scalatest/Suite;Lorg/scalatest/Reporter;Lorg/scalatest/Tracker;Ljava/lang/String;IZLscala/Tuple3;)Lorg/scalatest/events/RecordableEvent;
  #140 = MethodHandle       6:#139        // REF_invokeStatic org/scalatest/PathMessageRecordingDocumenter.$anonfun$recordedEvents$5:(Lorg/scalatest/PathMessageRecordingDocumenter;ZLorg/scalatest/Suite;Lorg/scalatest/Reporter;Lorg/scalatest/Tracker;Ljava/lang/String;IZLscala/Tuple3;)Lorg/scalatest/events/RecordableEvent;
  #141 = Utf8               (Lscala/Tuple3;)Lorg/scalatest/events/RecordableEvent;
  #142 = MethodType         #141          //  (Lscala/Tuple3;)Lorg/scalatest/events/RecordableEvent;
  #143 = Integer            5
  #144 = Integer            1
  #145 = Utf8               java/lang/invoke/LambdaMetafactory
  #146 = Class              #145          // java/lang/invoke/LambdaMetafactory
  #147 = Utf8               altMetafactory
  #148 = Utf8               (Ljava/lang/invoke/MethodHandles$Lookup;Ljava/lang/String;Ljava/lang/invoke/MethodType;[Ljava/lang/Object;)Ljava/lang/invoke/CallSite;
  #149 = NameAndType        #147:#148     // altMetafactory:(Ljava/lang/invoke/MethodHandles$Lookup;Ljava/lang/String;Ljava/lang/invoke/MethodType;[Ljava/lang/Object;)Ljava/lang/invoke/CallSite;
  #150 = Methodref          #146.#149     // java/lang/invoke/LambdaMetafactory.altMetafactory:(Ljava/lang/invoke/MethodHandles$Lookup;Ljava/lang/String;Ljava/lang/invoke/MethodType;[Ljava/lang/Object;)Ljava/lang/invoke/CallSite;
  #151 = MethodHandle       6:#150        // REF_invokeStatic java/lang/invoke/LambdaMetafactory.altMetafactory:(Ljava/lang/invoke/MethodHandles$Lookup;Ljava/lang/String;Ljava/lang/invoke/MethodType;[Ljava/lang/Object;)Ljava/lang/invoke/CallSite;
  #152 = Utf8               (Lorg/scalatest/PathMessageRecordingDocumenter;ZLorg/scalatest/Suite;Lorg/scalatest/Reporter;Lorg/scalatest/Tracker;Ljava/lang/String;IZ)Lscala/Function1;
  #153 = NameAndType        #67:#152      // apply:(Lorg/scalatest/PathMessageRecordingDocumenter;ZLorg/scalatest/Suite;Lorg/scalatest/Reporter;Lorg/scalatest/Tracker;Ljava/lang/String;IZ)Lscala/Function1;
  #154 = InvokeDynamic      #0:#153       // #0:apply:(Lorg/scalatest/PathMessageRecordingDocumenter;ZLorg/scalatest/Suite;Lorg/scalatest/Reporter;Lorg/scalatest/Tracker;Ljava/lang/String;IZ)Lscala/Function1;
  #155 = Utf8               scala/collection/Iterable
  #156 = Class              #155          // scala/collection/Iterable
  #157 = Utf8               map
  #158 = Utf8               (Lscala/Function1;)Ljava/lang/Object;
  #159 = NameAndType        #157:#158     // map:(Lscala/Function1;)Ljava/lang/Object;
  #160 = InterfaceMethodref #156.#159     // scala/collection/Iterable.map:(Lscala/Function1;)Ljava/lang/Object;
  #161 = Utf8               scala/collection/IterableOnce
  #162 = Class              #161          // scala/collection/IterableOnce
  #163 = Utf8               scala/collection/immutable/Vector
  #164 = Class              #163          // scala/collection/immutable/Vector
  #165 = Utf8               $plus$plus
  #166 = Utf8               (Lscala/collection/IterableOnce;)Ljava/lang/Object;
  #167 = NameAndType        #165:#166     // $plus$plus:(Lscala/collection/IterableOnce;)Ljava/lang/Object;
  #168 = Methodref          #164.#167     // scala/collection/immutable/Vector.$plus$plus:(Lscala/collection/IterableOnce;)Ljava/lang/Object;
  #169 = Utf8               scala/collection/immutable/IndexedSeq
  #170 = Class              #169          // scala/collection/immutable/IndexedSeq
  #171 = Utf8               Z
  #172 = Utf8               Lorg/scalatest/Suite;
  #173 = Utf8               Lorg/scalatest/Reporter;
  #174 = Utf8               Lorg/scalatest/Tracker;
  #175 = Utf8               I
  #176 = Utf8               $this
  #177 = Utf8               testWasPending$5
  #178 = Utf8               theSuite$4
  #179 = Utf8               report$4
  #180 = Utf8               tracker$4
  #181 = Utf8               testName$4
  #182 = Utf8               indentation$4
  #183 = Utf8               includeIcon$4
  #184 = Utf8               x0$1
  #185 = Utf8               _1
  #186 = Utf8               ()Ljava/lang/Object;
  #187 = NameAndType        #185:#186     // _1:()Ljava/lang/Object;
  #188 = Methodref          #39.#187      // scala/Tuple3._1:()Ljava/lang/Object;
  #189 = Utf8               _2
  #190 = NameAndType        #189:#186     // _2:()Ljava/lang/Object;
  #191 = Methodref          #39.#190      // scala/Tuple3._2:()Ljava/lang/Object;
  #192 = Utf8               _3
  #193 = NameAndType        #192:#186     // _3:()Ljava/lang/Object;
  #194 = Methodref          #39.#193      // scala/Tuple3._3:()Ljava/lang/Object;
  #195 = Utf8               unboxToBoolean
  #196 = Utf8               (Ljava/lang/Object;)Z
  #197 = NameAndType        #195:#196     // unboxToBoolean:(Ljava/lang/Object;)Z
  #198 = Methodref          #51.#197      // scala/runtime/BoxesRunTime.unboxToBoolean:(Ljava/lang/Object;)Z
  #199 = NameAndType        #21:#22       // eventFun:Lscala/Function10;
  #200 = Fieldref           #2.#199       // org/scalatest/PathMessageRecordingDocumenter.eventFun:Lscala/Function10;
  #201 = Utf8               boxToInteger
  #202 = Utf8               (I)Ljava/lang/Integer;
  #203 = NameAndType        #201:#202     // boxToInteger:(I)Ljava/lang/Integer;
  #204 = Methodref          #51.#203      // scala/runtime/BoxesRunTime.boxToInteger:(I)Ljava/lang/Integer;
  #205 = Utf8               scala/Function10
  #206 = Class              #205          // scala/Function10
  #207 = Utf8               (Ljava/lang/Object;Ljava/lang/Object;Ljava/lang/Object;Ljava/lang/Object;Ljava/lang/Object;Ljava/lang/Object;Ljava/lang/Object;Ljava/lang/Object;Ljava/lang/Object;Ljava/lang/Object;)Ljava/lang/Object;
  #208 = NameAndType        #67:#207      // apply:(Ljava/lang/Object;Ljava/lang/Object;Ljava/lang/Object;Ljava/lang/Object;Ljava/lang/Object;Ljava/lang/Object;Ljava/lang/Object;Ljava/lang/Object;Ljava/lang/Object;Ljava/lang/Object;)Ljava/lang/Object;
  #209 = InterfaceMethodref #206.#208     // scala/Function10.apply:(Ljava/lang/Object;Ljava/lang/Object;Ljava/lang/Object;Ljava/lang/Object;Ljava/lang/Object;Ljava/lang/Object;Ljava/lang/Object;Ljava/lang/Object;Ljava/lang/Object;Ljava/lang/Object;)Ljava/lang/Object;
  #210 = Utf8               org/scalatest/events/RecordableEvent
  #211 = Class              #210          // org/scalatest/events/RecordableEvent
  #212 = Utf8               scala/MatchError
  #213 = Class              #212          // scala/MatchError
  #214 = NameAndType        #56:#63       // "<init>":(Ljava/lang/Object;)V
  #215 = Methodref          #213.#214     // scala/MatchError."<init>":(Ljava/lang/Object;)V
  #216 = Utf8               thread
  #217 = Utf8               Ljava/lang/Thread;
  #218 = Utf8               wasConstructingThread
  #219 = Utf8               Lscala/Tuple3;
  #220 = Utf8               org/scalatest/Suite
  #221 = Class              #220          // org/scalatest/Suite
  #222 = Utf8               org/scalatest/Reporter
  #223 = Class              #222          // org/scalatest/Reporter
  #224 = Utf8               org/scalatest/Tracker
  #225 = Class              #224          // org/scalatest/Tracker
  #226 = Utf8               (Lscala/Function10;)V
  #227 = Utf8               (Lscala/Function10<Ljava/lang/String;Ljava/lang/Object;Ljava/lang/Object;Lorg/scalatest/Suite;Lorg/scalatest/Reporter;Lorg/scalatest/Tracker;Ljava/lang/String;Ljava/lang/Object;Ljava/lang/Object;Ljava/lang/Thread;Lorg/scalatest/events/RecordableEvent;>;)V
  #228 = Utf8               ()V
  #229 = NameAndType        #56:#228      // "<init>":()V
  #230 = Methodref          #4.#229       // org/scalatest/ThreadAwareness."<init>":()V
  #231 = Methodref          #61.#229      // org/scalatest/ConcurrentLinkedQueue."<init>":()V
  #232 = Utf8               $deserializeLambda$
  #233 = Utf8               (Ljava/lang/invoke/SerializedLambda;)Ljava/lang/Object;
  #234 = Utf8               scala/runtime/LambdaDeserialize
  #235 = Class              #234          // scala/runtime/LambdaDeserialize
  #236 = Utf8               bootstrap
  #237 = Utf8               (Ljava/lang/invoke/MethodHandles$Lookup;Ljava/lang/String;Ljava/lang/invoke/MethodType;[Ljava/lang/invoke/MethodHandle;)Ljava/lang/invoke/CallSite;
  #238 = NameAndType        #236:#237     // bootstrap:(Ljava/lang/invoke/MethodHandles$Lookup;Ljava/lang/String;Ljava/lang/invoke/MethodType;[Ljava/lang/invoke/MethodHandle;)Ljava/lang/invoke/CallSite;
  #239 = Methodref          #235.#238     // scala/runtime/LambdaDeserialize.bootstrap:(Ljava/lang/invoke/MethodHandles$Lookup;Ljava/lang/String;Ljava/lang/invoke/MethodType;[Ljava/lang/invoke/MethodHandle;)Ljava/lang/invoke/CallSite;
  #240 = MethodHandle       6:#239        // REF_invokeStatic scala/runtime/LambdaDeserialize.bootstrap:(Ljava/lang/invoke/MethodHandles$Lookup;Ljava/lang/String;Ljava/lang/invoke/MethodType;[Ljava/lang/invoke/MethodHandle;)Ljava/lang/invoke/CallSite;
  #241 = Utf8               lambdaDeserialize
  #242 = NameAndType        #241:#233     // lambdaDeserialize:(Ljava/lang/invoke/SerializedLambda;)Ljava/lang/Object;
  #243 = InvokeDynamic      #1:#242       // #1:lambdaDeserialize:(Ljava/lang/invoke/SerializedLambda;)Ljava/lang/Object;
  #244 = Utf8               Signature
  #245 = Utf8               Code
  #246 = Utf8               LineNumberTable
  #247 = Utf8               LocalVariableTable
  #248 = Utf8               MethodParameters
  #249 = Utf8               StackMapTable
  #250 = Utf8               InnerClasses
  #251 = Utf8               SourceFile
  #252 = Utf8               RuntimeVisibleAnnotations
  #253 = Utf8               BootstrapMethods
  #254 = Utf8               ScalaInlineInfo
  #255 = Utf8               ScalaSig
{
  private final scala.Function10<java.lang.String, java.lang.Object, java.lang.Object, org.scalatest.Suite, org.scalatest.Reporter, org.scalatest.Tracker, java.lang.String, java.lang.Object, java.lang.Object, java.lang.Thread, org.scalatest.events.RecordableEvent> eventFun;
    descriptor: Lscala/Function10;
    flags: (0x0012) ACC_PRIVATE, ACC_FINAL
    Signature: #23                          // Lscala/Function10<Ljava/lang/String;Ljava/lang/Object;Ljava/lang/Object;Lorg/scalatest/Suite;Lorg/scalatest/Reporter;Lorg/scalatest/Tracker;Ljava/lang/String;Ljava/lang/Object;Ljava/lang/Object;Ljava/lang/Thread;Lorg/scalatest/events/RecordableEvent;>;

  private final org.scalatest.ConcurrentLinkedQueue<scala.Tuple3<java.lang.String, java.lang.Thread, java.lang.Object>> messages;
    descriptor: Lorg/scalatest/ConcurrentLinkedQueue;
    flags: (0x0012) ACC_PRIVATE, ACC_FINAL
    Signature: #26                          // Lorg/scalatest/ConcurrentLinkedQueue<Lscala/Tuple3<Ljava/lang/String;Ljava/lang/Thread;Ljava/lang/Object;>;>;

  private org.scalatest.ConcurrentLinkedQueue<scala.Tuple3<java.lang.String, java.lang.Thread, java.lang.Object>> messages();
    descriptor: ()Lorg/scalatest/ConcurrentLinkedQueue;
    flags: (0x0002) ACC_PRIVATE
    Code:
      stack=1, locals=1, args_size=1
         0: aload_0
         1: getfield      #30                 // Field messages:Lorg/scalatest/ConcurrentLinkedQueue;
         4: areturn
      LineNumberTable:
        line 291: 0
      LocalVariableTable:
        Start  Length  Slot  Name   Signature
            0       5     0  this   Lorg/scalatest/PathMessageRecordingDocumenter;
    Signature: #28                          // ()Lorg/scalatest/ConcurrentLinkedQueue<Lscala/Tuple3<Ljava/lang/String;Ljava/lang/Thread;Ljava/lang/Object;>;>;

  private void record(java.lang.String);
    descriptor: (Ljava/lang/String;)V
    flags: (0x0002) ACC_PRIVATE
    Code:
      stack=6, locals=2, args_size=2
         0: aload_0
         1: invokespecial #37                 // Method messages:()Lorg/scalatest/ConcurrentLinkedQueue;
         4: new           #39                 // class scala/Tuple3
         7: dup
         8: aload_1
         9: invokestatic  #45                 // Method java/lang/Thread.currentThread:()Ljava/lang/Thread;
        12: aload_0
        13: invokevirtual #49                 // Method isConstructingThread:()Z
        16: invokestatic  #55                 // Method scala/runtime/BoxesRunTime.boxToBoolean:(Z)Ljava/lang/Boolean;
        19: invokespecial #59                 // Method scala/Tuple3."<init>":(Ljava/lang/Object;Ljava/lang/Object;Ljava/lang/Object;)V
        22: invokevirtual #65                 // Method org/scalatest/ConcurrentLinkedQueue.add:(Ljava/lang/Object;)V
        25: return
      LineNumberTable:
        line 298: 0
      LocalVariableTable:
        Start  Length  Slot  Name   Signature
            0      26     0  this   Lorg/scalatest/PathMessageRecordingDocumenter;
            0      26     1 message   Ljava/lang/String;
    MethodParameters:
      Name                           Flags
      message                        final

  public void apply(java.lang.String, org.scalactic.source.Position);
    descriptor: (Ljava/lang/String;Lorg/scalactic/source/Position;)V
    flags: (0x0001) ACC_PUBLIC
    Code:
      stack=6, locals=3, args_size=3
         0: getstatic     #75                 // Field org/scalactic/Requirements$.MODULE$:Lorg/scalactic/Requirements$;
         3: invokevirtual #79                 // Method org/scalactic/Requirements$.requirementsHelper:()Lorg/scalactic/Requirements$RequirementsHelper;
         6: iconst_1
         7: anewarray     #81                 // class java/lang/String
        10: dup
        11: iconst_0
        12: ldc           #82                 // String message
        14: aastore
        15: checkcast     #84                 // class "[Ljava/lang/Object;"
        18: checkcast     #86                 // class "[Ljava/lang/String;"
        21: iconst_1
        22: anewarray     #88                 // class java/lang/Object
        25: dup
        26: iconst_0
        27: aload_1
        28: aastore
        29: checkcast     #84                 // class "[Ljava/lang/Object;"
        32: getstatic     #93                 // Field org/scalactic/Prettifier$.MODULE$:Lorg/scalactic/Prettifier$;
        35: invokevirtual #97                 // Method org/scalactic/Prettifier$.default:()Lorg/scalactic/Prettifier;
        38: aload_2
        39: invokevirtual #101                // Method org/scalactic/Requirements$RequirementsHelper.macroRequireNonNull:([Ljava/lang/String;[Ljava/lang/Object;Lorg/scalactic/Prettifier;Lorg/scalactic/source/Position;)V
        42: aload_0
        43: aload_1
        44: invokespecial #103                // Method record:(Ljava/lang/String;)V
        47: return
      LineNumberTable:
        line 302: 0
        line 303: 42
      LocalVariableTable:
        Start  Length  Slot  Name   Signature
            0      48     0  this   Lorg/scalatest/PathMessageRecordingDocumenter;
            0      48     1 message   Ljava/lang/String;
            0      48     2   pos   Lorg/scalactic/source/Position;
    MethodParameters:
      Name                           Flags
      message                        final
      pos                            final

  public scala.collection.immutable.IndexedSeq<org.scalatest.events.RecordableEvent> recordedEvents(boolean, org.scalatest.Suite, org.scalatest.Reporter, org.scalatest.Tracker, java.lang.String, int, boolean);
    descriptor: (ZLorg/scalatest/Suite;Lorg/scalatest/Reporter;Lorg/scalatest/Tracker;Ljava/lang/String;IZ)Lscala/collection/immutable/IndexedSeq;
    flags: (0x0001) ACC_PUBLIC
    Code:
      stack=10, locals=8, args_size=8
         0: getstatic     #119                // Field scala/package$.MODULE$:Lscala/package$;
         3: invokevirtual #123                // Method scala/package$.Vector:()Lscala/collection/immutable/Vector$;
         6: invokevirtual #129                // Method scala/collection/immutable/Vector$.empty:()Lscala/collection/immutable/Vector;
         9: aload_0
        10: invokespecial #37                 // Method messages:()Lorg/scalatest/ConcurrentLinkedQueue;
        13: invokevirtual #133                // Method org/scalatest/ConcurrentLinkedQueue.asScala:()Lscala/collection/Iterable;
        16: aload_0
        17: iload_1
        18: aload_2
        19: aload_3
        20: aload         4
        22: aload         5
        24: iload         6
        26: iload         7
        28: invokedynamic #154,  0            // InvokeDynamic #0:apply:(Lorg/scalatest/PathMessageRecordingDocumenter;ZLorg/scalatest/Suite;Lorg/scalatest/Reporter;Lorg/scalatest/Tracker;Ljava/lang/String;IZ)Lscala/Function1;
        33: invokeinterface #160,  2          // InterfaceMethod scala/collection/Iterable.map:(Lscala/Function1;)Ljava/lang/Object;
        38: checkcast     #162                // class scala/collection/IterableOnce
        41: invokevirtual #168                // Method scala/collection/immutable/Vector.$plus$plus:(Lscala/collection/IterableOnce;)Ljava/lang/Object;
        44: checkcast     #170                // class scala/collection/immutable/IndexedSeq
        47: areturn
      LineNumberTable:
        line 307: 0
      LocalVariableTable:
        Start  Length  Slot  Name   Signature
            0      48     0  this   Lorg/scalatest/PathMessageRecordingDocumenter;
            0      48     1 testWasPending   Z
            0      48     2 theSuite   Lorg/scalatest/Suite;
            0      48     3 report   Lorg/scalatest/Reporter;
            0      48     4 tracker   Lorg/scalatest/Tracker;
            0      48     5 testName   Ljava/lang/String;
            0      48     6 indentation   I
            0      48     7 includeIcon   Z
    Signature: #107                         // (ZLorg/scalatest/Suite;Lorg/scalatest/Reporter;Lorg/scalatest/Tracker;Ljava/lang/String;IZ)Lscala/collection/immutable/IndexedSeq<Lorg/scalatest/events/RecordableEvent;>;
    MethodParameters:
      Name                           Flags
      testWasPending                 final
      theSuite                       final
      report                         final
      tracker                        final
      testName                       final
      indentation                    final
      includeIcon                    final

  public static final org.scalatest.events.RecordableEvent $anonfun$recordedEvents$5(org.scalatest.PathMessageRecordingDocumenter, boolean, org.scalatest.Suite, org.scalatest.Reporter, org.scalatest.Tracker, java.lang.String, int, boolean, scala.Tuple3);
    descriptor: (Lorg/scalatest/PathMessageRecordingDocumenter;ZLorg/scalatest/Suite;Lorg/scalatest/Reporter;Lorg/scalatest/Tracker;Ljava/lang/String;IZLscala/Tuple3;)Lorg/scalatest/events/RecordableEvent;
    flags: (0x1019) ACC_PUBLIC, ACC_STATIC, ACC_FINAL, ACC_SYNTHETIC
    Code:
      stack=11, locals=14, args_size=9
         0: aload         8
         2: astore        10
         4: aload         10
         6: ifnull        85
         9: aload         10
        11: invokevirtual #188                // Method scala/Tuple3._1:()Ljava/lang/Object;
        14: checkcast     #81                 // class java/lang/String
        17: astore        11
        19: aload         10
        21: invokevirtual #191                // Method scala/Tuple3._2:()Ljava/lang/Object;
        24: checkcast     #41                 // class java/lang/Thread
        27: astore        12
        29: aload         10
        31: invokevirtual #194                // Method scala/Tuple3._3:()Ljava/lang/Object;
        34: invokestatic  #198                // Method scala/runtime/BoxesRunTime.unboxToBoolean:(Ljava/lang/Object;)Z
        37: istore        13
        39: aload_0
        40: getfield      #200                // Field eventFun:Lscala/Function10;
        43: aload         11
        45: iload         13
        47: invokestatic  #55                 // Method scala/runtime/BoxesRunTime.boxToBoolean:(Z)Ljava/lang/Boolean;
        50: iload_1
        51: invokestatic  #55                 // Method scala/runtime/BoxesRunTime.boxToBoolean:(Z)Ljava/lang/Boolean;
        54: aload_2
        55: aload_3
        56: aload         4
        58: aload         5
        60: iload         6
        62: invokestatic  #204                // Method scala/runtime/BoxesRunTime.boxToInteger:(I)Ljava/lang/Integer;
        65: iload         7
        67: invokestatic  #55                 // Method scala/runtime/BoxesRunTime.boxToBoolean:(Z)Ljava/lang/Boolean;
        70: aload         12
        72: invokeinterface #209,  11         // InterfaceMethod scala/Function10.apply:(Ljava/lang/Object;Ljava/lang/Object;Ljava/lang/Object;Ljava/lang/Object;Ljava/lang/Object;Ljava/lang/Object;Ljava/lang/Object;Ljava/lang/Object;Ljava/lang/Object;Ljava/lang/Object;)Ljava/lang/Object;
        77: checkcast     #211                // class org/scalatest/events/RecordableEvent
        80: astore        9
        82: goto          98
        85: goto          88
        88: new           #213                // class scala/MatchError
        91: dup
        92: aload         10
        94: invokespecial #215                // Method scala/MatchError."<init>":(Ljava/lang/Object;)V
        97: athrow
        98: aload         9
       100: areturn
      StackMapTable: number_of_entries = 3
        frame_type = 253 /* append */
          offset_delta = 85
          locals = [ top, class scala/Tuple3 ]
        frame_type = 2 /* same */
        frame_type = 255 /* full_frame */
          offset_delta = 9
          locals = [ class org/scalatest/PathMessageRecordingDocumenter, int, class org/scalatest/Suite, class org/scalatest/Reporter, class org/scalatest/Tracker, class java/lang/String, int, int, class scala/Tuple3, class org/scalatest/events/RecordableEvent, class scala/Tuple3, class java/lang/String, class java/lang/Thread, int ]
          stack = []
      LineNumberTable:
        line 307: 0
        line 308: 39
        line 307: 85
      LocalVariableTable:
        Start  Length  Slot  Name   Signature
           19      66    11 message   Ljava/lang/String;
           29      56    12 thread   Ljava/lang/Thread;
           39      46    13 wasConstructingThread   Z
            0     101     0 $this   Lorg/scalatest/PathMessageRecordingDocumenter;
            0     101     1 testWasPending$5   Z
            0     101     2 theSuite$4   Lorg/scalatest/Suite;
            0     101     3 report$4   Lorg/scalatest/Reporter;
            0     101     4 tracker$4   Lorg/scalatest/Tracker;
            0     101     5 testName$4   Ljava/lang/String;
            0     101     6 indentation$4   I
            0     101     7 includeIcon$4   Z
            0     101     8  x0$1   Lscala/Tuple3;
    MethodParameters:
      Name                           Flags
      $this                          final synthetic
      testWasPending$5               final
      theSuite$4                     final
      report$4                       final
      tracker$4                      final
      testName$4                     final
      indentation$4                  final
      includeIcon$4                  final
      x0$1                           final

  public org.scalatest.PathMessageRecordingDocumenter(scala.Function10<java.lang.String, java.lang.Object, java.lang.Object, org.scalatest.Suite, org.scalatest.Reporter, org.scalatest.Tracker, java.lang.String, java.lang.Object, java.lang.Object, java.lang.Thread, org.scalatest.events.RecordableEvent>);
    descriptor: (Lscala/Function10;)V
    flags: (0x0001) ACC_PUBLIC
    Code:
      stack=3, locals=2, args_size=2
         0: aload_0
         1: aload_1
         2: putfield      #200                // Field eventFun:Lscala/Function10;
         5: aload_0
         6: invokespecial #230                // Method org/scalatest/ThreadAwareness."<init>":()V
         9: aload_0
        10: new           #61                 // class org/scalatest/ConcurrentLinkedQueue
        13: dup
        14: invokespecial #231                // Method org/scalatest/ConcurrentLinkedQueue."<init>":()V
        17: putfield      #30                 // Field messages:Lorg/scalatest/ConcurrentLinkedQueue;
        20: return
      LineNumberTable:
        line 286: 0
        line 291: 9
        line 286: 20
      LocalVariableTable:
        Start  Length  Slot  Name   Signature
            0      21     0  this   Lorg/scalatest/PathMessageRecordingDocumenter;
            0      21     1 eventFun   Lscala/Function10;
    Signature: #227                         // (Lscala/Function10<Ljava/lang/String;Ljava/lang/Object;Ljava/lang/Object;Lorg/scalatest/Suite;Lorg/scalatest/Reporter;Lorg/scalatest/Tracker;Ljava/lang/String;Ljava/lang/Object;Ljava/lang/Object;Ljava/lang/Thread;Lorg/scalatest/events/RecordableEvent;>;)V
    MethodParameters:
      Name                           Flags
      eventFun                       final

  private static java.lang.Object $deserializeLambda$(java.lang.invoke.SerializedLambda);
    descriptor: (Ljava/lang/invoke/SerializedLambda;)Ljava/lang/Object;
    flags: (0x100a) ACC_PRIVATE, ACC_STATIC, ACC_SYNTHETIC
    Code:
      stack=1, locals=1, args_size=1
         0: aload_0
         1: invokedynamic #243,  0            // InvokeDynamic #1:lambdaDeserialize:(Ljava/lang/invoke/SerializedLambda;)Ljava/lang/Object;
         6: areturn
}
InnerClasses:
  public static final #15= #12 of #14;    // Lookup=class java/lang/invoke/MethodHandles$Lookup of class java/lang/invoke/MethodHandles
  public static #20= #17 of #19;          // RequirementsHelper=class org/scalactic/Requirements$RequirementsHelper of class org/scalactic/Requirements
SourceFile: "ConcurrentInformer.scala"
RuntimeVisibleAnnotations:
  0: #8(#9=s#10)
    scala.reflect.ScalaSignature(
      bytes="\u0006\u0005\u0005\u0005b!B\u0007\u000f\u00019\u0011\u0002\u0002\u0003\u000e\u0001\u0005\u0003\u0005\u000b\u0011\u0002\u000f\t\u000b)\u0003A\u0011A&\u0006\t9\u0003\u0001a\u0014\u0005\b%\u0002\u0011\r\u0011\"\u0003T\u0011\u0019I\u0006\u0001)A\u0005)\")!\f\u0001C\u00057\")\u0011\r\u0001C\u0001E\")q\u000e\u0001C\u0001a\u001eA\u0011q\u0002\b\t\u00029\t\tBB\u0004\u000e\u001d!\u0005a\"a\u0005\t\r)SA\u0011AA\u000e\u0011\u0019\t\'\u0002\"\u0001\u0002\u001e\tq\u0002+\u0019;i\u001b\u0016\u001c8/Y4f%\u0016\u001cwN\u001d3j]\u001e$unY;nK:$XM\u001d\u0006\u0003\u001fA\t\u0011b]2bY\u0006$Xm\u001d;\u000b\u0003E\t1a\u001c:h\'\r\u00011c\u0006\t\u0003)Ui\u0011AD\u0005\u0003-9\u0011q\u0002\u00165sK\u0006$\u0017i^1sK:,7o\u001d\t\u0003)aI!!\u0007\b\u0003\u0015\u0011{7-^7f]R,\'/\u0001\u0005fm\u0016tGOR;o\u0007\u0001\u0001R\"\b\u0011#[5\u00024G\u000e\u0012:[q\"U\"\u0001\u0010\u000b\u0003}\tQa]2bY\u0006L!!\t\u0010\u0003\u0015\u0019+hn\u0019;j_:\f\u0004\u0007\u0005\u0002$U9\u0011A\u0005\u000b\t\u0003Kyi\u0011A\n\u0006\u0003Om\ta\u0001\u0010:p_Rt\u0014BA\u0015\u001f\u0003\u0019\u0001&/\u001a3fM&\u00111\u0006\f\u0002\u0007\'R\u0014\u0018N\\4\u000b\u0005%r\u0002CA\u000f/\u0013\tycDA\u0004C_>dW-\u00198\u0011\u0005Q\t\u0014B\u0001\u001a\u000f\u0005\u0015\u0019V/\u001b;f!\t!B\'\u0003\u00026\u001d\tA!+\u001a9peR,\'\u000f\u0005\u0002\u0015o%\u0011\u0001H\u0004\u0002\b)J\f7m[3s!\ti\"(\u0003\u0002<=\t\u0019\u0011J\u001c;\u0011\u0005u\u0012U\"\u0001 \u000b\u0005}\u0002\u0015\u0001\u00027b]\u001eT\u0011!Q\u0001\u0005U\u00064\u0018-\u0003\u0002D}\t1A\u000b\u001b:fC\u0012\u0004\"!\u0012%\u000e\u0003\u0019S!a\u0012\b\u0002\r\u00154XM\u001c;t\u0013\tIeIA\bSK\u000e|\'\u000fZ1cY\u0016,e/\u001a8u\u0003\u0019a\u0014N\\5u}Q\u0011A*\u0014\t\u0003)\u0001AQA\u0007\u0002A\u0002q\u00111\u0001V;q!\u0015i\u0002K\t\u001f.\u0013\t\tfD\u0001\u0004UkBdWmM\u0001\t[\u0016\u001c8/Y4fgV\tA\u000bE\u0002\u0015+^K!A\u0016\b\u0003+\r{gnY;se\u0016tG\u000fT5oW\u0016$\u0017+^3vKB\u0011\u0001lA\u0007\u0002\u0001\u0005IQ.Z:tC\u001e,7\u000fI\u0001\u0007e\u0016\u001cwN\u001d3\u0015\u0005q{\u0006CA\u000f^\u0013\tqfD\u0001\u0003V]&$\b\"\u00021\u0007\u0001\u0004\u0011\u0013aB7fgN\fw-Z\u0001\u0006CB\u0004H.\u001f\u000b\u0003G:$\"\u0001\u00183\t\u000b\u0015<\u00019\u00014\u0002\u0007A|7\u000f\u0005\u0002hY6\t\u0001N\u0003\u0002jU\u000611o\\;sG\u0016T!a\u001b\t\u0002\u0013M\u001c\u0017\r\\1di&\u001c\u0017BA7i\u0005!\u0001vn]5uS>t\u0007\"\u00021\b\u0001\u0004\u0011\u0013A\u0004:fG>\u0014H-\u001a3Fm\u0016tGo\u001d\u000b\fcf\\Xp`A\u0002\u0003\u000f\tY\u0001E\u0002so\u0012k\u0011a\u001d\u0006\u0003iV\f\u0011\"[7nkR\f\'\r\\3\u000b\u0005Yt\u0012AC2pY2,7\r^5p]&\u0011\u0001p\u001d\u0002\u000b\u0013:$W\r_3e\'\u0016\f\b\"\u0002>\t\u0001\u0004i\u0013A\u0004;fgR<\u0016m\u001d)f]\u0012Lgn\u001a\u0005\u0006y\"\u0001\r\u0001M\u0001\ti\",7+^5uK\")a\u0010\u0003a\u0001g\u00051!/\u001a9peRDa!!\u0001\t\u0001\u00041\u0014a\u0002;sC\u000e\\WM\u001d\u0005\u0007\u0003\u000bA\u0001\u0019\u0001\u0012\u0002\u0011Q,7\u000f\u001e(b[\u0016Da!!\u0003\t\u0001\u0004I\u0014aC5oI\u0016tG/\u0019;j_:Da!!\u0004\t\u0001\u0004i\u0013aC5oG2,H-Z%d_:\fa\u0004U1uQ6+7o]1hKJ+7m\u001c:eS:<Gi\\2v[\u0016tG/\u001a:\u0011\u0005QQ1c\u0001\u0006\u0002\u0016A\u0019Q$a\u0006\n\u0007\u0005eaD\u0001\u0004B]f\u0014VM\u001a\u000b\u0003\u0003#!2\u0001TA\u0010\u0011\u0015QB\u00021\u0001\u001d\u0001"
    )
BootstrapMethods:
  0: #151 REF_invokeStatic java/lang/invoke/LambdaMetafactory.altMetafactory:(Ljava/lang/invoke/MethodHandles$Lookup;Ljava/lang/String;Ljava/lang/invoke/MethodType;[Ljava/lang/Object;)Ljava/lang/invoke/CallSite;
    Method arguments:
      #135 (Ljava/lang/Object;)Ljava/lang/Object;
      #140 REF_invokeStatic org/scalatest/PathMessageRecordingDocumenter.$anonfun$recordedEvents$5:(Lorg/scalatest/PathMessageRecordingDocumenter;ZLorg/scalatest/Suite;Lorg/scalatest/Reporter;Lorg/scalatest/Tracker;Ljava/lang/String;IZLscala/Tuple3;)Lorg/scalatest/events/RecordableEvent;
      #142 (Lscala/Tuple3;)Lorg/scalatest/events/RecordableEvent;
      #143 5
      #144 1
      #142 (Lscala/Tuple3;)Lorg/scalatest/events/RecordableEvent;
  1: #240 REF_invokeStatic scala/runtime/LambdaDeserialize.bootstrap:(Ljava/lang/invoke/MethodHandles$Lookup;Ljava/lang/String;Ljava/lang/invoke/MethodType;[Ljava/lang/invoke/MethodHandle;)Ljava/lang/invoke/CallSite;
    Method arguments:
      #140 REF_invokeStatic org/scalatest/PathMessageRecordingDocumenter.$anonfun$recordedEvents$5:(Lorg/scalatest/PathMessageRecordingDocumenter;ZLorg/scalatest/Suite;Lorg/scalatest/Reporter;Lorg/scalatest/Tracker;Ljava/lang/String;IZLscala/Tuple3;)Lorg/scalatest/events/RecordableEvent;
  ScalaInlineInfo: length = 0x22 (unknown attribute)
   01 00 00 06 00 88 00 89 01 00 38 00 E2 00 00 43
   00 44 00 00 18 00 1B 01 00 21 00 22 01 00 69 00
   6A 00
  ScalaSig: length = 0x3 (unknown attribute)
   05 02 00
