Classfile /Users/mw/Projects/slang-braindump/.jar/jar8/assemble/slang-braindump/assemble/content/org/scalatest/Payloads$.class
  Last modified May 29, 2022; size 949 bytes
  SHA-256 checksum bde2945317f6671861ce2a1c69d6ea6970be3100ad75b9ea1440f28e9fcb07e6
  Compiled from "Payloads.scala"
public final class org.scalatest.Payloads$ implements org.scalatest.Payloads
  minor version: 0
  major version: 52
  flags: (0x0031) ACC_PUBLIC, ACC_FINAL, ACC_SUPER
  this_class: #2                          // org/scalatest/Payloads$
  super_class: #4                         // java/lang/Object
  interfaces: 1, fields: 1, methods: 3, attributes: 3
Constant pool:
   #1 = Utf8               org/scalatest/Payloads$
   #2 = Class              #1             // org/scalatest/Payloads$
   #3 = Utf8               java/lang/Object
   #4 = Class              #3             // java/lang/Object
   #5 = Utf8               org/scalatest/Payloads
   #6 = Class              #5             // org/scalatest/Payloads
   #7 = Utf8               Payloads.scala
   #8 = Utf8               MODULE$
   #9 = Utf8               Lorg/scalatest/Payloads$;
  #10 = Utf8               <clinit>
  #11 = Utf8               ()V
  #12 = Utf8               <init>
  #13 = NameAndType        #12:#11        // "<init>":()V
  #14 = Methodref          #2.#13         // org/scalatest/Payloads$."<init>":()V
  #15 = NameAndType        #8:#9          // MODULE$:Lorg/scalatest/Payloads$;
  #16 = Fieldref           #2.#15         // org/scalatest/Payloads$.MODULE$:Lorg/scalatest/Payloads$;
  #17 = Utf8               $init$
  #18 = Utf8               (Lorg/scalatest/Payloads;)V
  #19 = NameAndType        #17:#18        // $init$:(Lorg/scalatest/Payloads;)V
  #20 = InterfaceMethodref #6.#19         // org/scalatest/Payloads.$init$:(Lorg/scalatest/Payloads;)V
  #21 = Utf8               withPayload
  #22 = Utf8               (Lscala/Function0;Lscala/Function0;)Ljava/lang/Object;
  #23 = Utf8               <T:Ljava/lang/Object;>(Lscala/Function0<Ljava/lang/Object;>;Lscala/Function0<TT;>;)TT;
  #24 = Utf8               payload
  #25 = Utf8               fun
  #26 = Utf8               withPayload$
  #27 = Utf8               (Lorg/scalatest/Payloads;Lscala/Function0;Lscala/Function0;)Ljava/lang/Object;
  #28 = NameAndType        #26:#27        // withPayload$:(Lorg/scalatest/Payloads;Lscala/Function0;Lscala/Function0;)Ljava/lang/Object;
  #29 = InterfaceMethodref #6.#28         // org/scalatest/Payloads.withPayload$:(Lorg/scalatest/Payloads;Lscala/Function0;Lscala/Function0;)Ljava/lang/Object;
  #30 = Utf8               this
  #31 = Utf8               Lscala/Function0;
  #32 = Methodref          #4.#13         // java/lang/Object."<init>":()V
  #33 = Utf8               Code
  #34 = Utf8               LineNumberTable
  #35 = Utf8               LocalVariableTable
  #36 = Utf8               Signature
  #37 = Utf8               MethodParameters
  #38 = Utf8               SourceFile
  #39 = Utf8               ScalaInlineInfo
  #40 = Utf8               Scala
{
  public static final org.scalatest.Payloads$ MODULE$;
    descriptor: Lorg/scalatest/Payloads$;
    flags: (0x0019) ACC_PUBLIC, ACC_STATIC, ACC_FINAL

  public static {};
    descriptor: ()V
    flags: (0x0009) ACC_PUBLIC, ACC_STATIC
    Code:
      stack=2, locals=0, args_size=0
         0: new           #2                  // class org/scalatest/Payloads$
         3: dup
         4: invokespecial #14                 // Method "<init>":()V
         7: putstatic     #16                 // Field MODULE$:Lorg/scalatest/Payloads$;
        10: getstatic     #16                 // Field MODULE$:Lorg/scalatest/Payloads$;
        13: invokestatic  #20                 // InterfaceMethod org/scalatest/Payloads.$init$:(Lorg/scalatest/Payloads;)V
        16: return
      LineNumberTable:
        line 92: 0

  public <T extends java.lang.Object> T withPayload(scala.Function0<java.lang.Object>, scala.Function0<T>);
    descriptor: (Lscala/Function0;Lscala/Function0;)Ljava/lang/Object;
    flags: (0x0001) ACC_PUBLIC
    Code:
      stack=3, locals=3, args_size=3
         0: aload_0
         1: aload_1
         2: aload_2
         3: invokestatic  #29                 // InterfaceMethod org/scalatest/Payloads.withPayload$:(Lorg/scalatest/Payloads;Lscala/Function0;Lscala/Function0;)Ljava/lang/Object;
         6: areturn
      LineNumberTable:
        line 92: 0
      LocalVariableTable:
        Start  Length  Slot  Name   Signature
            0       7     0  this   Lorg/scalatest/Payloads$;
            0       7     1 payload   Lscala/Function0;
            0       7     2   fun   Lscala/Function0;
    Signature: #23                          // <T:Ljava/lang/Object;>(Lscala/Function0<Ljava/lang/Object;>;Lscala/Function0<TT;>;)TT;
    MethodParameters:
      Name                           Flags
      payload                        final
      fun                            final

  private org.scalatest.Payloads$();
    descriptor: ()V
    flags: (0x0002) ACC_PRIVATE
    Code:
      stack=1, locals=1, args_size=1
         0: aload_0
         1: invokespecial #32                 // Method java/lang/Object."<init>":()V
         4: return
      LineNumberTable:
        line 92: 0
      LocalVariableTable:
        Start  Length  Slot  Name   Signature
            0       5     0  this   Lorg/scalatest/Payloads$;
}
SourceFile: "Payloads.scala"
  ScalaInlineInfo: length = 0xE (unknown attribute)
   01 01 00 02 00 0C 00 0B 01 00 15 00 16 01
  Scala: length = 0x0 (unknown attribute)

