Classfile /Users/mw/Projects/slang-braindump/.jar/jar8/assemble/slang-braindump/assemble/content/org/scalatest/Pending.class
  Last modified May 29, 2022; size 2501 bytes
  SHA-256 checksum c727f965e67ff5525893b1e1065bc27ba2574faaa925d4a5a002f4ea7dfd010a
  Compiled from "Outcome.scala"
public final class org.scalatest.Pending
  minor version: 0
  major version: 52
  flags: (0x0031) ACC_PUBLIC, ACC_FINAL, ACC_SUPER
  this_class: #2                          // org/scalatest/Pending
  super_class: #4                         // java/lang/Object
  interfaces: 0, fields: 0, methods: 16, attributes: 3
Constant pool:
   #1 = Utf8               org/scalatest/Pending
   #2 = Class              #1             // org/scalatest/Pending
   #3 = Utf8               java/lang/Object
   #4 = Class              #3             // java/lang/Object
   #5 = Utf8               Outcome.scala
   #6 = Utf8               Lscala/reflect/ScalaSignature;
   #7 = Utf8               bytes
   #8 = Utf8               \u0006\u0005\u0011<QAD\b\t\u0002R1QAF\b\t\u0002^AQ!L\u0001\u0005\u00029BqaL\u0001C\u0002\u0013\u0005\u0003\u0007\u0003\u00045\u0003\u0001\u0006I!\r\u0005\u0006k\u0005!\tA\u000e\u0005\bu\u0005\t\t\u0011\"\u0011<\u0011\u001d!\u0015!!A\u0005\u0002\u0015Cq!S\u0001\u0002\u0002\u0013\u0005!\nC\u0004Q\u0003\u0005\u0005I\u0011I)\t\u000fa\u000b\u0011\u0011!C\u00013\"91,AA\u0001\n\u0003b\u0006bB/\u0002\u0003\u0003%\tE\u0018\u0005\b?\u0006\t\t\u0011\"\u0003a\u0003\u001d\u0001VM\u001c3j]\u001eT!\u0001E\t\u0002\u0013M\u001c\u0017\r\\1uKN$(\"\u0001\n\u0002\u0007=\u0014xm\u0001\u0001\u0011\u0005U\tQ\"A\b\u0003\u000fA+g\u000eZ5oON!\u0011\u0001G\u000e\"!\t)\u0012$\u0003\u0002\u001b\u001f\t9q*\u001e;d_6,\u0007C\u0001\u000f \u001b\u0005i\"\"\u0001\u0010\u0002\u000bM\u001c\u0017\r\\1\n\u0005\u0001j\"a\u0002)s_\u0012,8\r\u001e\t\u0003E)r!a\t\u0015\u000f\u0005\u0011:S\"A\u0013\u000b\u0005\u0019\u001a\u0012A\u0002\u001fs_>$h(C\u0001\u001f\u0013\tIS$A\u0004qC\u000e\\\u0017mZ3\n\u0005-b#\u0001D*fe&\fG.\u001b>bE2,\'BA\u0015\u001e\u0003\u0019a\u0014N\\5u}Q\tA#A\u0005jgB+g\u000eZ5oOV\t\u0011\u0007\u0005\u0002\u001de%\u00111\'\b\u0002\b\u0005>|G.Z1o\u0003)I7\u000fU3oI&tw\rI\u0001\fi>\u001cVoY2fK\u0012,G-F\u00018\u001d\t)\u0002(\u0003\u0002:\u001f\u0005I1+^2dK\u0016$W\rZ\u0001\u000eaJ|G-^2u!J,g-\u001b=\u0016\u0003q\u0002\"!\u0010\"\u000e\u0003yR!a\u0010!\u0002\t1\fgn\u001a\u0006\u0002\u0003\u0006!!.\u0019<b\u0013\t\u0019eH\u0001\u0004TiJLgnZ\u0001\raJ|G-^2u\u0003JLG/_\u000b\u0002\rB\u0011AdR\u0005\u0003\u0011v\u00111!\u00138u\u00039\u0001(o\u001c3vGR,E.Z7f]R$\"a\u0013(\u0011\u0005qa\u0015BA\'\u001e\u0005\r\te.\u001f\u0005\b\u001f\"\t\t\u00111\u0001G\u0003\rAH%M\u0001\u0010aJ|G-^2u\u0013R,\'/\u0019;peV\t!\u000bE\u0002T-.k\u0011\u0001\u0016\u0006\u0003+v\t!bY8mY\u0016\u001cG/[8o\u0013\t9FK\u0001\u0005Ji\u0016\u0014\u0018\r^8s\u0003!\u0019\u0017M\\#rk\u0006dGCA\u0019[\u0011\u001dy%\"!AA\u0002-\u000b\u0001\u0002[1tQ\u000e{G-\u001a\u000b\u0002\r\u0006AAo\\*ue&tw\rF\u0001=\u000319(/\u001b;f%\u0016\u0004H.Y2f)\u0005\t\u0007CA\u001fc\u0013\t\u0019gH\u0001\u0004PE*,7\r\u001e
   #9 = Utf8               toString
  #10 = Utf8               ()Ljava/lang/String;
  #11 = Utf8               org/scalatest/Pending$
  #12 = Class              #11            // org/scalatest/Pending$
  #13 = Utf8               MODULE$
  #14 = Utf8               Lorg/scalatest/Pending$;
  #15 = NameAndType        #13:#14        // MODULE$:Lorg/scalatest/Pending$;
  #16 = Fieldref           #12.#15        // org/scalatest/Pending$.MODULE$:Lorg/scalatest/Pending$;
  #17 = NameAndType        #9:#10         // toString:()Ljava/lang/String;
  #18 = Methodref          #12.#17        // org/scalatest/Pending$.toString:()Ljava/lang/String;
  #19 = Utf8               hashCode
  #20 = Utf8               ()I
  #21 = NameAndType        #19:#20        // hashCode:()I
  #22 = Methodref          #12.#21        // org/scalatest/Pending$.hashCode:()I
  #23 = Utf8               canEqual
  #24 = Utf8               (Ljava/lang/Object;)Z
  #25 = Utf8               x$1
  #26 = NameAndType        #23:#24        // canEqual:(Ljava/lang/Object;)Z
  #27 = Methodref          #12.#26        // org/scalatest/Pending$.canEqual:(Ljava/lang/Object;)Z
  #28 = Utf8               Ljava/lang/Object;
  #29 = Utf8               productIterator
  #30 = Utf8               ()Lscala/collection/Iterator;
  #31 = Utf8               ()Lscala/collection/Iterator<Ljava/lang/Object;>;
  #32 = NameAndType        #29:#30        // productIterator:()Lscala/collection/Iterator;
  #33 = Methodref          #12.#32        // org/scalatest/Pending$.productIterator:()Lscala/collection/Iterator;
  #34 = Utf8               productElement
  #35 = Utf8               (I)Ljava/lang/Object;
  #36 = NameAndType        #34:#35        // productElement:(I)Ljava/lang/Object;
  #37 = Methodref          #12.#36        // org/scalatest/Pending$.productElement:(I)Ljava/lang/Object;
  #38 = Utf8               I
  #39 = Utf8               productArity
  #40 = NameAndType        #39:#20        // productArity:()I
  #41 = Methodref          #12.#40        // org/scalatest/Pending$.productArity:()I
  #42 = Utf8               productPrefix
  #43 = NameAndType        #42:#10        // productPrefix:()Ljava/lang/String;
  #44 = Methodref          #12.#43        // org/scalatest/Pending$.productPrefix:()Ljava/lang/String;
  #45 = Utf8               toSucceeded
  #46 = Utf8               ()Lorg/scalatest/Succeeded$;
  #47 = NameAndType        #45:#46        // toSucceeded:()Lorg/scalatest/Succeeded$;
  #48 = Methodref          #12.#47        // org/scalatest/Pending$.toSucceeded:()Lorg/scalatest/Succeeded$;
  #49 = Utf8               isPending
  #50 = Utf8               ()Z
  #51 = NameAndType        #49:#50        // isPending:()Z
  #52 = Methodref          #12.#51        // org/scalatest/Pending$.isPending:()Z
  #53 = Utf8               toOption
  #54 = Utf8               ()Lscala/Option;
  #55 = Utf8               ()Lscala/Option<Ljava/lang/Throwable;>;
  #56 = NameAndType        #53:#54        // toOption:()Lscala/Option;
  #57 = Methodref          #12.#56        // org/scalatest/Pending$.toOption:()Lscala/Option;
  #58 = Utf8               isExceptional
  #59 = NameAndType        #58:#50        // isExceptional:()Z
  #60 = Methodref          #12.#59        // org/scalatest/Pending$.isExceptional:()Z
  #61 = Utf8               isCanceled
  #62 = NameAndType        #61:#50        // isCanceled:()Z
  #63 = Methodref          #12.#62        // org/scalatest/Pending$.isCanceled:()Z
  #64 = Utf8               isFailed
  #65 = NameAndType        #64:#50        // isFailed:()Z
  #66 = Methodref          #12.#65        // org/scalatest/Pending$.isFailed:()Z
  #67 = Utf8               isSucceeded
  #68 = NameAndType        #67:#50        // isSucceeded:()Z
  #69 = Methodref          #12.#68        // org/scalatest/Pending$.isSucceeded:()Z
  #70 = Utf8               productElementNames
  #71 = Utf8               ()Lscala/collection/Iterator<Ljava/lang/String;>;
  #72 = NameAndType        #70:#30        // productElementNames:()Lscala/collection/Iterator;
  #73 = Methodref          #12.#72        // org/scalatest/Pending$.productElementNames:()Lscala/collection/Iterator;
  #74 = Utf8               productElementName
  #75 = Utf8               (I)Ljava/lang/String;
  #76 = Utf8               n
  #77 = NameAndType        #74:#75        // productElementName:(I)Ljava/lang/String;
  #78 = Methodref          #12.#77        // org/scalatest/Pending$.productElementName:(I)Ljava/lang/String;
  #79 = Utf8               Code
  #80 = Utf8               LocalVariableTable
  #81 = Utf8               MethodParameters
  #82 = Utf8               Signature
  #83 = Utf8               SourceFile
  #84 = Utf8               RuntimeVisibleAnnotations
  #85 = Utf8               ScalaSig
{
  public static java.lang.String toString();
    descriptor: ()Ljava/lang/String;
    flags: (0x0009) ACC_PUBLIC, ACC_STATIC
    Code:
      stack=1, locals=0, args_size=0
         0: getstatic     #16                 // Field org/scalatest/Pending$.MODULE$:Lorg/scalatest/Pending$;
         3: invokevirtual #18                 // Method org/scalatest/Pending$.toString:()Ljava/lang/String;
         6: areturn

  public static int hashCode();
    descriptor: ()I
    flags: (0x0009) ACC_PUBLIC, ACC_STATIC
    Code:
      stack=1, locals=0, args_size=0
         0: getstatic     #16                 // Field org/scalatest/Pending$.MODULE$:Lorg/scalatest/Pending$;
         3: invokevirtual #22                 // Method org/scalatest/Pending$.hashCode:()I
         6: ireturn

  public static boolean canEqual(java.lang.Object);
    descriptor: (Ljava/lang/Object;)Z
    flags: (0x0009) ACC_PUBLIC, ACC_STATIC
    Code:
      stack=2, locals=1, args_size=1
         0: getstatic     #16                 // Field org/scalatest/Pending$.MODULE$:Lorg/scalatest/Pending$;
         3: aload_0
         4: invokevirtual #27                 // Method org/scalatest/Pending$.canEqual:(Ljava/lang/Object;)Z
         7: ireturn
      LocalVariableTable:
        Start  Length  Slot  Name   Signature
            0       8     0   x$1   Ljava/lang/Object;
    MethodParameters:
      Name                           Flags
      x$1                            final

  public static scala.collection.Iterator<java.lang.Object> productIterator();
    descriptor: ()Lscala/collection/Iterator;
    flags: (0x0009) ACC_PUBLIC, ACC_STATIC
    Code:
      stack=1, locals=0, args_size=0
         0: getstatic     #16                 // Field org/scalatest/Pending$.MODULE$:Lorg/scalatest/Pending$;
         3: invokevirtual #33                 // Method org/scalatest/Pending$.productIterator:()Lscala/collection/Iterator;
         6: areturn
    Signature: #31                          // ()Lscala/collection/Iterator<Ljava/lang/Object;>;

  public static java.lang.Object productElement(int);
    descriptor: (I)Ljava/lang/Object;
    flags: (0x0009) ACC_PUBLIC, ACC_STATIC
    Code:
      stack=2, locals=1, args_size=1
         0: getstatic     #16                 // Field org/scalatest/Pending$.MODULE$:Lorg/scalatest/Pending$;
         3: iload_0
         4: invokevirtual #37                 // Method org/scalatest/Pending$.productElement:(I)Ljava/lang/Object;
         7: areturn
      LocalVariableTable:
        Start  Length  Slot  Name   Signature
            0       8     0   x$1   I
    MethodParameters:
      Name                           Flags
      x$1                            final

  public static int productArity();
    descriptor: ()I
    flags: (0x0009) ACC_PUBLIC, ACC_STATIC
    Code:
      stack=1, locals=0, args_size=0
         0: getstatic     #16                 // Field org/scalatest/Pending$.MODULE$:Lorg/scalatest/Pending$;
         3: invokevirtual #41                 // Method org/scalatest/Pending$.productArity:()I
         6: ireturn

  public static java.lang.String productPrefix();
    descriptor: ()Ljava/lang/String;
    flags: (0x0009) ACC_PUBLIC, ACC_STATIC
    Code:
      stack=1, locals=0, args_size=0
         0: getstatic     #16                 // Field org/scalatest/Pending$.MODULE$:Lorg/scalatest/Pending$;
         3: invokevirtual #44                 // Method org/scalatest/Pending$.productPrefix:()Ljava/lang/String;
         6: areturn

  public static org.scalatest.Succeeded$ toSucceeded();
    descriptor: ()Lorg/scalatest/Succeeded$;
    flags: (0x0009) ACC_PUBLIC, ACC_STATIC
    Code:
      stack=1, locals=0, args_size=0
         0: getstatic     #16                 // Field org/scalatest/Pending$.MODULE$:Lorg/scalatest/Pending$;
         3: invokevirtual #48                 // Method org/scalatest/Pending$.toSucceeded:()Lorg/scalatest/Succeeded$;
         6: areturn

  public static boolean isPending();
    descriptor: ()Z
    flags: (0x0009) ACC_PUBLIC, ACC_STATIC
    Code:
      stack=1, locals=0, args_size=0
         0: getstatic     #16                 // Field org/scalatest/Pending$.MODULE$:Lorg/scalatest/Pending$;
         3: invokevirtual #52                 // Method org/scalatest/Pending$.isPending:()Z
         6: ireturn

  public static scala.Option<java.lang.Throwable> toOption();
    descriptor: ()Lscala/Option;
    flags: (0x0009) ACC_PUBLIC, ACC_STATIC
    Code:
      stack=1, locals=0, args_size=0
         0: getstatic     #16                 // Field org/scalatest/Pending$.MODULE$:Lorg/scalatest/Pending$;
         3: invokevirtual #57                 // Method org/scalatest/Pending$.toOption:()Lscala/Option;
         6: areturn
    Signature: #55                          // ()Lscala/Option<Ljava/lang/Throwable;>;

  public static boolean isExceptional();
    descriptor: ()Z
    flags: (0x0009) ACC_PUBLIC, ACC_STATIC
    Code:
      stack=1, locals=0, args_size=0
         0: getstatic     #16                 // Field org/scalatest/Pending$.MODULE$:Lorg/scalatest/Pending$;
         3: invokevirtual #60                 // Method org/scalatest/Pending$.isExceptional:()Z
         6: ireturn

  public static boolean isCanceled();
    descriptor: ()Z
    flags: (0x0009) ACC_PUBLIC, ACC_STATIC
    Code:
      stack=1, locals=0, args_size=0
         0: getstatic     #16                 // Field org/scalatest/Pending$.MODULE$:Lorg/scalatest/Pending$;
         3: invokevirtual #63                 // Method org/scalatest/Pending$.isCanceled:()Z
         6: ireturn

  public static boolean isFailed();
    descriptor: ()Z
    flags: (0x0009) ACC_PUBLIC, ACC_STATIC
    Code:
      stack=1, locals=0, args_size=0
         0: getstatic     #16                 // Field org/scalatest/Pending$.MODULE$:Lorg/scalatest/Pending$;
         3: invokevirtual #66                 // Method org/scalatest/Pending$.isFailed:()Z
         6: ireturn

  public static boolean isSucceeded();
    descriptor: ()Z
    flags: (0x0009) ACC_PUBLIC, ACC_STATIC
    Code:
      stack=1, locals=0, args_size=0
         0: getstatic     #16                 // Field org/scalatest/Pending$.MODULE$:Lorg/scalatest/Pending$;
         3: invokevirtual #69                 // Method org/scalatest/Pending$.isSucceeded:()Z
         6: ireturn

  public static scala.collection.Iterator<java.lang.String> productElementNames();
    descriptor: ()Lscala/collection/Iterator;
    flags: (0x0009) ACC_PUBLIC, ACC_STATIC
    Code:
      stack=1, locals=0, args_size=0
         0: getstatic     #16                 // Field org/scalatest/Pending$.MODULE$:Lorg/scalatest/Pending$;
         3: invokevirtual #73                 // Method org/scalatest/Pending$.productElementNames:()Lscala/collection/Iterator;
         6: areturn
    Signature: #71                          // ()Lscala/collection/Iterator<Ljava/lang/String;>;

  public static java.lang.String productElementName(int);
    descriptor: (I)Ljava/lang/String;
    flags: (0x0009) ACC_PUBLIC, ACC_STATIC
    Code:
      stack=2, locals=1, args_size=1
         0: getstatic     #16                 // Field org/scalatest/Pending$.MODULE$:Lorg/scalatest/Pending$;
         3: iload_0
         4: invokevirtual #78                 // Method org/scalatest/Pending$.productElementName:(I)Ljava/lang/String;
         7: areturn
      LocalVariableTable:
        Start  Length  Slot  Name   Signature
            0       8     0     n   I
    MethodParameters:
      Name                           Flags
      n                              final
}
SourceFile: "Outcome.scala"
RuntimeVisibleAnnotations:
  0: #6(#7=s#8)
    scala.reflect.ScalaSignature(
      bytes="\u0006\u0005\u0011<QAD\b\t\u0002R1QAF\b\t\u0002^AQ!L\u0001\u0005\u00029BqaL\u0001C\u0002\u0013\u0005\u0003\u0007\u0003\u00045\u0003\u0001\u0006I!\r\u0005\u0006k\u0005!\tA\u000e\u0005\bu\u0005\t\t\u0011\"\u0011<\u0011\u001d!\u0015!!A\u0005\u0002\u0015Cq!S\u0001\u0002\u0002\u0013\u0005!\nC\u0004Q\u0003\u0005\u0005I\u0011I)\t\u000fa\u000b\u0011\u0011!C\u00013\"91,AA\u0001\n\u0003b\u0006bB/\u0002\u0003\u0003%\tE\u0018\u0005\b?\u0006\t\t\u0011\"\u0003a\u0003\u001d\u0001VM\u001c3j]\u001eT!\u0001E\t\u0002\u0013M\u001c\u0017\r\\1uKN$(\"\u0001\n\u0002\u0007=\u0014xm\u0001\u0001\u0011\u0005U\tQ\"A\b\u0003\u000fA+g\u000eZ5oON!\u0011\u0001G\u000e\"!\t)\u0012$\u0003\u0002\u001b\u001f\t9q*\u001e;d_6,\u0007C\u0001\u000f \u001b\u0005i\"\"\u0001\u0010\u0002\u000bM\u001c\u0017\r\\1\n\u0005\u0001j\"a\u0002)s_\u0012,8\r\u001e\t\u0003E)r!a\t\u0015\u000f\u0005\u0011:S\"A\u0013\u000b\u0005\u0019\u001a\u0012A\u0002\u001fs_>$h(C\u0001\u001f\u0013\tIS$A\u0004qC\u000e\\\u0017mZ3\n\u0005-b#\u0001D*fe&\fG.\u001b>bE2,\'BA\u0015\u001e\u0003\u0019a\u0014N\\5u}Q\tA#A\u0005jgB+g\u000eZ5oOV\t\u0011\u0007\u0005\u0002\u001de%\u00111\'\b\u0002\b\u0005>|G.Z1o\u0003)I7\u000fU3oI&tw\rI\u0001\fi>\u001cVoY2fK\u0012,G-F\u00018\u001d\t)\u0002(\u0003\u0002:\u001f\u0005I1+^2dK\u0016$W\rZ\u0001\u000eaJ|G-^2u!J,g-\u001b=\u0016\u0003q\u0002\"!\u0010\"\u000e\u0003yR!a\u0010!\u0002\t1\fgn\u001a\u0006\u0002\u0003\u0006!!.\u0019<b\u0013\t\u0019eH\u0001\u0004TiJLgnZ\u0001\raJ|G-^2u\u0003JLG/_\u000b\u0002\rB\u0011AdR\u0005\u0003\u0011v\u00111!\u00138u\u00039\u0001(o\u001c3vGR,E.Z7f]R$\"a\u0013(\u0011\u0005qa\u0015BA\'\u001e\u0005\r\te.\u001f\u0005\b\u001f\"\t\t\u00111\u0001G\u0003\rAH%M\u0001\u0010aJ|G-^2u\u0013R,\'/\u0019;peV\t!\u000bE\u0002T-.k\u0011\u0001\u0016\u0006\u0003+v\t!bY8mY\u0016\u001cG/[8o\u0013\t9FK\u0001\u0005Ji\u0016\u0014\u0018\r^8s\u0003!\u0019\u0017M\\#rk\u0006dGCA\u0019[\u0011\u001dy%\"!AA\u0002-\u000b\u0001\u0002[1tQ\u000e{G-\u001a\u000b\u0002\r\u0006AAo\\*ue&tw\rF\u0001=\u000319(/\u001b;f%\u0016\u0004H.Y2f)\u0005\t\u0007CA\u001fc\u0013\t\u0019gH\u0001\u0004PE*,7\r\u001e"
    )
  ScalaSig: length = 0x3 (unknown attribute)
   05 02 00
