Classfile /Users/mw/Projects/slang-braindump/.jar/jar8/assemble/slang-braindump/assemble/content/org/scalatest/Reporter.class
  Last modified May 29, 2022; size 1557 bytes
  SHA-256 checksum 0fa90c7db27675f47816f92a4f67da577b275eb2d4c2ed74829e1e0d28c5f1e8
  Compiled from "Reporter.scala"
public interface org.scalatest.Reporter
  minor version: 0
  major version: 52
  flags: (0x0601) ACC_PUBLIC, ACC_INTERFACE, ACC_ABSTRACT
  this_class: #2                          // org/scalatest/Reporter
  super_class: #4                         // java/lang/Object
  interfaces: 0, fields: 0, methods: 3, attributes: 4
Constant pool:
   #1 = Utf8               org/scalatest/Reporter
   #2 = Class              #1             // org/scalatest/Reporter
   #3 = Utf8               java/lang/Object
   #4 = Class              #3             // java/lang/Object
   #5 = Utf8               Reporter.scala
   #6 = Utf8               Lscala/reflect/ScalaSignature;
   #7 = Utf8               bytes
   #8 = Utf8               \u0006\u0005M3q\u0001C\u0005\u0011\u0002G\u0005a\u0002C\u0003\u0016\u0001\u0019\u0005ac\u0002\u0004#\u0013!\u0005\u0011b\t\u0004\u0007\u0011%A\t!C\u0013\t\u000b\u0019\u001aA\u0011A\u0014\t\r!\u001aA\u0011A\u0005*\u0011\u0015a4\u0001\"\u0001>\u0011\u0015q5\u0001\"\u0001P\u0005!\u0011V\r]8si\u0016\u0014(B\u0001\u0006\f\u0003%\u00198-\u00197bi\u0016\u001cHOC\u0001\r\u0003\ry\'oZ\u0002\u0001\'\t\u0001q\u0002\u0005\u0002\u0011\'5\t\u0011CC\u0001\u0013\u0003\u0015\u00198-\u00197b\u0013\t!\u0012C\u0001\u0004B]f\u0014VMZ\u0001\u0006CB\u0004H.\u001f\u000b\u0003/i\u0001\"\u0001\u0005\r\n\u0005e\t\"\u0001B+oSRDQaG\u0001A\u0002q\tQ!\u001a<f]R\u0004\"!\b\u0011\u000e\u0003yQ!aH\u0005\u0002\r\u00154XM\u001c;t\u0013\t\tcDA\u0003Fm\u0016tG/\u0001\u0005SKB|\'\u000f^3s!\t!3!D\u0001\n\'\t\u0019q\"\u0001\u0004=S:LGO\u0010\u000b\u0002G\u0005\u0001\u0012N\u001c3f]R\u001cF/Y2l)J\f7-\u001a\u000b\u0004UU:\u0004CA\u00163\u001d\ta\u0003\u0007\u0005\u0002.#5\taF\u0003\u00020\u001b\u00051AH]8pizJ!!M\t\u0002\rA\u0013X\rZ3g\u0013\t\u0019DG\u0001\u0004TiJLgn\u001a\u0006\u0003cEAQAN\u0003A\u0002)\n!b\u001d;bG.$&/Y2f\u0011\u0015AT\u00011\u0001:\u0003\u0015aWM^3m!\t\u0001\"(\u0003\u0002<#\t\u0019\u0011J\u001c;\u0002A5,7o]1hK>\u0013H\u000b\u001b:po\u0006\u0014G.Z:EKR\f\u0017\u000e\\\'fgN\fw-\u001a\u000b\u0004Uy\u0002\u0005\"B \u0007\u0001\u0004Q\u0013aB7fgN\fw-\u001a\u0005\u0006\u0003\u001a\u0001\rAQ\u0001\ni\"\u0014xn^1cY\u0016\u00042\u0001E\"F\u0013\t!\u0015C\u0001\u0004PaRLwN\u001c\t\u0003\r.s!aR%\u000f\u00055B\u0015\"\u0001\n\n\u0005)\u000b\u0012a\u00029bG.\fw-Z\u0005\u0003\u00196\u0013\u0011\u0002\u00165s_^\f\'\r\\3\u000b\u0005)\u000b\u0012\u0001\u00059s_B\fw-\u0019;f\t&\u001c\bo\\:f)\t9\u0002\u000bC\u0003R\u000f\u0001\u0007!+\u0001\u0005sKB|\'\u000f^3s!\t!\u0003\u0001
   #9 = Utf8               propagateDispose
  #10 = Utf8               (Lorg/scalatest/Reporter;)V
  #11 = Utf8               reporter
  #12 = Utf8               org/scalatest/Reporter$
  #13 = Class              #12            // org/scalatest/Reporter$
  #14 = Utf8               MODULE$
  #15 = Utf8               Lorg/scalatest/Reporter$;
  #16 = NameAndType        #14:#15        // MODULE$:Lorg/scalatest/Reporter$;
  #17 = Fieldref           #13.#16        // org/scalatest/Reporter$.MODULE$:Lorg/scalatest/Reporter$;
  #18 = NameAndType        #9:#10         // propagateDispose:(Lorg/scalatest/Reporter;)V
  #19 = Methodref          #13.#18        // org/scalatest/Reporter$.propagateDispose:(Lorg/scalatest/Reporter;)V
  #20 = Utf8               Lorg/scalatest/Reporter;
  #21 = Utf8               messageOrThrowablesDetailMessage
  #22 = Utf8               (Ljava/lang/String;Lscala/Option;)Ljava/lang/String;
  #23 = Utf8               (Ljava/lang/String;Lscala/Option<Ljava/lang/Throwable;>;)Ljava/lang/String;
  #24 = Utf8               message
  #25 = Utf8               throwable
  #26 = NameAndType        #21:#22        // messageOrThrowablesDetailMessage:(Ljava/lang/String;Lscala/Option;)Ljava/lang/String;
  #27 = Methodref          #13.#26        // org/scalatest/Reporter$.messageOrThrowablesDetailMessage:(Ljava/lang/String;Lscala/Option;)Ljava/lang/String;
  #28 = Utf8               Ljava/lang/String;
  #29 = Utf8               Lscala/Option;
  #30 = Utf8               apply
  #31 = Utf8               (Lorg/scalatest/events/Event;)V
  #32 = Utf8               event
  #33 = Utf8               Code
  #34 = Utf8               LocalVariableTable
  #35 = Utf8               MethodParameters
  #36 = Utf8               Signature
  #37 = Utf8               SourceFile
  #38 = Utf8               RuntimeVisibleAnnotations
  #39 = Utf8               ScalaInlineInfo
  #40 = Utf8               ScalaSig
{
  public static void propagateDispose(org.scalatest.Reporter);
    descriptor: (Lorg/scalatest/Reporter;)V
    flags: (0x0009) ACC_PUBLIC, ACC_STATIC
    Code:
      stack=2, locals=1, args_size=1
         0: getstatic     #17                 // Field org/scalatest/Reporter$.MODULE$:Lorg/scalatest/Reporter$;
         3: aload_0
         4: invokevirtual #19                 // Method org/scalatest/Reporter$.propagateDispose:(Lorg/scalatest/Reporter;)V
         7: return
      LocalVariableTable:
        Start  Length  Slot  Name   Signature
            0       8     0 reporter   Lorg/scalatest/Reporter;
    MethodParameters:
      Name                           Flags
      reporter                       final

  public static java.lang.String messageOrThrowablesDetailMessage(java.lang.String, scala.Option<java.lang.Throwable>);
    descriptor: (Ljava/lang/String;Lscala/Option;)Ljava/lang/String;
    flags: (0x0009) ACC_PUBLIC, ACC_STATIC
    Code:
      stack=3, locals=2, args_size=2
         0: getstatic     #17                 // Field org/scalatest/Reporter$.MODULE$:Lorg/scalatest/Reporter$;
         3: aload_0
         4: aload_1
         5: invokevirtual #27                 // Method org/scalatest/Reporter$.messageOrThrowablesDetailMessage:(Ljava/lang/String;Lscala/Option;)Ljava/lang/String;
         8: areturn
      LocalVariableTable:
        Start  Length  Slot  Name   Signature
            0       9     0 message   Ljava/lang/String;
            0       9     1 throwable   Lscala/Option;
    Signature: #23                          // (Ljava/lang/String;Lscala/Option<Ljava/lang/Throwable;>;)Ljava/lang/String;
    MethodParameters:
      Name                           Flags
      message                        final
      throwable                      final

  public abstract void apply(org.scalatest.events.Event);
    descriptor: (Lorg/scalatest/events/Event;)V
    flags: (0x0401) ACC_PUBLIC, ACC_ABSTRACT
    MethodParameters:
      Name                           Flags
      event                          final
}
SourceFile: "Reporter.scala"
RuntimeVisibleAnnotations:
  0: #6(#7=s#8)
    scala.reflect.ScalaSignature(
      bytes="\u0006\u0005M3q\u0001C\u0005\u0011\u0002G\u0005a\u0002C\u0003\u0016\u0001\u0019\u0005ac\u0002\u0004#\u0013!\u0005\u0011b\t\u0004\u0007\u0011%A\t!C\u0013\t\u000b\u0019\u001aA\u0011A\u0014\t\r!\u001aA\u0011A\u0005*\u0011\u0015a4\u0001\"\u0001>\u0011\u0015q5\u0001\"\u0001P\u0005!\u0011V\r]8si\u0016\u0014(B\u0001\u0006\f\u0003%\u00198-\u00197bi\u0016\u001cHOC\u0001\r\u0003\ry\'oZ\u0002\u0001\'\t\u0001q\u0002\u0005\u0002\u0011\'5\t\u0011CC\u0001\u0013\u0003\u0015\u00198-\u00197b\u0013\t!\u0012C\u0001\u0004B]f\u0014VMZ\u0001\u0006CB\u0004H.\u001f\u000b\u0003/i\u0001\"\u0001\u0005\r\n\u0005e\t\"\u0001B+oSRDQaG\u0001A\u0002q\tQ!\u001a<f]R\u0004\"!\b\u0011\u000e\u0003yQ!aH\u0005\u0002\r\u00154XM\u001c;t\u0013\t\tcDA\u0003Fm\u0016tG/\u0001\u0005SKB|\'\u000f^3s!\t!3!D\u0001\n\'\t\u0019q\"\u0001\u0004=S:LGO\u0010\u000b\u0002G\u0005\u0001\u0012N\u001c3f]R\u001cF/Y2l)J\f7-\u001a\u000b\u0004UU:\u0004CA\u00163\u001d\ta\u0003\u0007\u0005\u0002.#5\taF\u0003\u00020\u001b\u00051AH]8pizJ!!M\t\u0002\rA\u0013X\rZ3g\u0013\t\u0019DG\u0001\u0004TiJLgn\u001a\u0006\u0003cEAQAN\u0003A\u0002)\n!b\u001d;bG.$&/Y2f\u0011\u0015AT\u00011\u0001:\u0003\u0015aWM^3m!\t\u0001\"(\u0003\u0002<#\t\u0019\u0011J\u001c;\u0002A5,7o]1hK>\u0013H\u000b\u001b:po\u0006\u0014G.Z:EKR\f\u0017\u000e\\\'fgN\fw-\u001a\u000b\u0004Uy\u0002\u0005\"B \u0007\u0001\u0004Q\u0013aB7fgN\fw-\u001a\u0005\u0006\u0003\u001a\u0001\rAQ\u0001\ni\"\u0014xn^1cY\u0016\u00042\u0001E\"F\u0013\t!\u0015C\u0001\u0004PaRLwN\u001c\t\u0003\r.s!aR%\u000f\u00055B\u0015\"\u0001\n\n\u0005)\u000b\u0012a\u00029bG.\fw-Z\u0005\u0003\u00196\u0013\u0011\u0002\u00165s_^\f\'\r\\3\u000b\u0005)\u000b\u0012\u0001\u00059s_B\fw-\u0019;f\t&\u001c\bo\\:f)\t9\u0002\u000bC\u0003R\u000f\u0001\u0007!+\u0001\u0005sKB|\'\u000f^3s!\t!\u0003\u0001"
    )
  ScalaInlineInfo: length = 0x9 (unknown attribute)
   01 00 00 01 00 1E 00 1F 00
  ScalaSig: length = 0x3 (unknown attribute)
   05 02 00
