Classfile /Users/mw/Projects/slang-braindump/.jar/jar8/assemble/slang-braindump/assemble/content/org/scalatest/run$.class
  Last modified May 29, 2022; size 3841 bytes
  SHA-256 checksum 55f179b5e5929b317ce0c59ddafb39307c6894ab4db029985efa078bd05ea1be
  Compiled from "run.scala"
public final class org.scalatest.run$
  minor version: 0
  major version: 52
  flags: (0x0031) ACC_PUBLIC, ACC_FINAL, ACC_SUPER
  this_class: #2                          // org/scalatest/run$
  super_class: #4                         // java/lang/Object
  interfaces: 0, fields: 2, methods: 10, attributes: 5
Constant pool:
    #1 = Utf8               org/scalatest/run$
    #2 = Class              #1            // org/scalatest/run$
    #3 = Utf8               java/lang/Object
    #4 = Class              #3            // java/lang/Object
    #5 = Utf8               run.scala
    #6 = Utf8               java/lang/invoke/MethodHandles$Lookup
    #7 = Class              #6            // java/lang/invoke/MethodHandles$Lookup
    #8 = Utf8               java/lang/invoke/MethodHandles
    #9 = Class              #8            // java/lang/invoke/MethodHandles
   #10 = Utf8               Lookup
   #11 = Utf8               scala/collection/mutable/ArraySeq$ofRef
   #12 = Class              #11           // scala/collection/mutable/ArraySeq$ofRef
   #13 = Utf8               scala/collection/mutable/ArraySeq
   #14 = Class              #13           // scala/collection/mutable/ArraySeq
   #15 = Utf8               ofRef
   #16 = Utf8               MODULE$
   #17 = Utf8               Lorg/scalatest/run$;
   #18 = Utf8               defaultShell
   #19 = Utf8               Lorg/scalatest/ShellImpl;
   #20 = Utf8               <clinit>
   #21 = Utf8               ()V
   #22 = Utf8               <init>
   #23 = NameAndType        #22:#21       // "<init>":()V
   #24 = Methodref          #2.#23        // org/scalatest/run$."<init>":()V
   #25 = NameAndType        #16:#17       // MODULE$:Lorg/scalatest/run$;
   #26 = Fieldref           #2.#25        // org/scalatest/run$.MODULE$:Lorg/scalatest/run$;
   #27 = Utf8               org/scalatest/ShellImpl
   #28 = Class              #27           // org/scalatest/ShellImpl
   #29 = Utf8               org/scalatest/ShellImpl$
   #30 = Class              #29           // org/scalatest/ShellImpl$
   #31 = Utf8               Lorg/scalatest/ShellImpl$;
   #32 = NameAndType        #16:#31       // MODULE$:Lorg/scalatest/ShellImpl$;
   #33 = Fieldref           #30.#32       // org/scalatest/ShellImpl$.MODULE$:Lorg/scalatest/ShellImpl$;
   #34 = Utf8               apply$default$1
   #35 = Utf8               ()Z
   #36 = NameAndType        #34:#35       // apply$default$1:()Z
   #37 = Methodref          #30.#36       // org/scalatest/ShellImpl$.apply$default$1:()Z
   #38 = Utf8               apply$default$2
   #39 = NameAndType        #38:#35       // apply$default$2:()Z
   #40 = Methodref          #30.#39       // org/scalatest/ShellImpl$.apply$default$2:()Z
   #41 = Utf8               apply$default$3
   #42 = NameAndType        #41:#35       // apply$default$3:()Z
   #43 = Methodref          #30.#42       // org/scalatest/ShellImpl$.apply$default$3:()Z
   #44 = Utf8               apply$default$4
   #45 = NameAndType        #44:#35       // apply$default$4:()Z
   #46 = Methodref          #30.#45       // org/scalatest/ShellImpl$.apply$default$4:()Z
   #47 = Utf8               apply$default$5
   #48 = NameAndType        #47:#35       // apply$default$5:()Z
   #49 = Methodref          #30.#48       // org/scalatest/ShellImpl$.apply$default$5:()Z
   #50 = Utf8               (ZZZZZ)V
   #51 = NameAndType        #22:#50       // "<init>":(ZZZZZ)V
   #52 = Methodref          #28.#51       // org/scalatest/ShellImpl."<init>":(ZZZZZ)V
   #53 = NameAndType        #18:#19       // defaultShell:Lorg/scalatest/ShellImpl;
   #54 = Fieldref           #2.#53        // org/scalatest/run$.defaultShell:Lorg/scalatest/ShellImpl;
   #55 = Utf8               ()Lorg/scalatest/ShellImpl;
   #56 = Utf8               this
   #57 = Utf8               main
   #58 = Utf8               ([Ljava/lang/String;)V
   #59 = Utf8               args
   #60 = Utf8               org/scalatest/tools/Runner$
   #61 = Class              #60           // org/scalatest/tools/Runner$
   #62 = Utf8               Lorg/scalatest/tools/Runner$;
   #63 = NameAndType        #16:#62       // MODULE$:Lorg/scalatest/tools/Runner$;
   #64 = Fieldref           #61.#63       // org/scalatest/tools/Runner$.MODULE$:Lorg/scalatest/tools/Runner$;
   #65 = Utf8               scala/collection/ArrayOps$
   #66 = Class              #65           // scala/collection/ArrayOps$
   #67 = Utf8               Lscala/collection/ArrayOps$;
   #68 = NameAndType        #16:#67       // MODULE$:Lscala/collection/ArrayOps$;
   #69 = Fieldref           #66.#68       // scala/collection/ArrayOps$.MODULE$:Lscala/collection/ArrayOps$;
   #70 = Utf8               scala/Predef$
   #71 = Class              #70           // scala/Predef$
   #72 = Utf8               Lscala/Predef$;
   #73 = NameAndType        #16:#72       // MODULE$:Lscala/Predef$;
   #74 = Fieldref           #71.#73       // scala/Predef$.MODULE$:Lscala/Predef$;
   #75 = Utf8               java/lang/String
   #76 = Class              #75           // java/lang/String
   #77 = Utf8               -R
   #78 = String             #77           // -R
   #79 = Utf8               .
   #80 = String             #79           // .
   #81 = Utf8               -o
   #82 = String             #81           // -o
   #83 = Utf8               [Ljava/lang/Object;
   #84 = Class              #83           // "[Ljava/lang/Object;"
   #85 = Utf8               refArrayOps
   #86 = Utf8               ([Ljava/lang/Object;)Ljava/lang/Object;
   #87 = NameAndType        #85:#86       // refArrayOps:([Ljava/lang/Object;)Ljava/lang/Object;
   #88 = Methodref          #71.#87       // scala/Predef$.refArrayOps:([Ljava/lang/Object;)Ljava/lang/Object;
   #89 = Utf8               (Ljava/lang/Object;)Ljava/lang/Object;
   #90 = MethodType         #89           //  (Ljava/lang/Object;)Ljava/lang/Object;
   #91 = Utf8               $anonfun$main$1
   #92 = Utf8               (Ljava/lang/String;)[Ljava/lang/String;
   #93 = NameAndType        #91:#92       // $anonfun$main$1:(Ljava/lang/String;)[Ljava/lang/String;
   #94 = Methodref          #2.#93        // org/scalatest/run$.$anonfun$main$1:(Ljava/lang/String;)[Ljava/lang/String;
   #95 = MethodHandle       6:#94         // REF_invokeStatic org/scalatest/run$.$anonfun$main$1:(Ljava/lang/String;)[Ljava/lang/String;
   #96 = MethodType         #92           //  (Ljava/lang/String;)[Ljava/lang/String;
   #97 = Integer            5
   #98 = Integer            1
   #99 = Utf8               java/lang/invoke/LambdaMetafactory
  #100 = Class              #99           // java/lang/invoke/LambdaMetafactory
  #101 = Utf8               altMetafactory
  #102 = Utf8               (Ljava/lang/invoke/MethodHandles$Lookup;Ljava/lang/String;Ljava/lang/invoke/MethodType;[Ljava/lang/Object;)Ljava/lang/invoke/CallSite;
  #103 = NameAndType        #101:#102     // altMetafactory:(Ljava/lang/invoke/MethodHandles$Lookup;Ljava/lang/String;Ljava/lang/invoke/MethodType;[Ljava/lang/Object;)Ljava/lang/invoke/CallSite;
  #104 = Methodref          #100.#103     // java/lang/invoke/LambdaMetafactory.altMetafactory:(Ljava/lang/invoke/MethodHandles$Lookup;Ljava/lang/String;Ljava/lang/invoke/MethodType;[Ljava/lang/Object;)Ljava/lang/invoke/CallSite;
  #105 = MethodHandle       6:#104        // REF_invokeStatic java/lang/invoke/LambdaMetafactory.altMetafactory:(Ljava/lang/invoke/MethodHandles$Lookup;Ljava/lang/String;Ljava/lang/invoke/MethodType;[Ljava/lang/Object;)Ljava/lang/invoke/CallSite;
  #106 = Utf8               apply
  #107 = Utf8               ()Lscala/Function1;
  #108 = NameAndType        #106:#107     // apply:()Lscala/Function1;
  #109 = InvokeDynamic      #0:#108       // #0:apply:()Lscala/Function1;
  #110 = Utf8               $anonfun$main$2
  #111 = Utf8               ([Ljava/lang/String;)Lscala/collection/mutable/ArraySeq$ofRef;
  #112 = NameAndType        #110:#111     // $anonfun$main$2:([Ljava/lang/String;)Lscala/collection/mutable/ArraySeq$ofRef;
  #113 = Methodref          #2.#112       // org/scalatest/run$.$anonfun$main$2:([Ljava/lang/String;)Lscala/collection/mutable/ArraySeq$ofRef;
  #114 = MethodHandle       6:#113        // REF_invokeStatic org/scalatest/run$.$anonfun$main$2:([Ljava/lang/String;)Lscala/collection/mutable/ArraySeq$ofRef;
  #115 = MethodType         #111          //  ([Ljava/lang/String;)Lscala/collection/mutable/ArraySeq$ofRef;
  #116 = InvokeDynamic      #1:#108       // #1:apply:()Lscala/Function1;
  #117 = Utf8               scala/reflect/ClassTag$
  #118 = Class              #117          // scala/reflect/ClassTag$
  #119 = Utf8               Lscala/reflect/ClassTag$;
  #120 = NameAndType        #16:#119      // MODULE$:Lscala/reflect/ClassTag$;
  #121 = Fieldref           #118.#120     // scala/reflect/ClassTag$.MODULE$:Lscala/reflect/ClassTag$;
  #122 = Utf8               (Ljava/lang/Class;)Lscala/reflect/ClassTag;
  #123 = NameAndType        #106:#122     // apply:(Ljava/lang/Class;)Lscala/reflect/ClassTag;
  #124 = Methodref          #118.#123     // scala/reflect/ClassTag$.apply:(Ljava/lang/Class;)Lscala/reflect/ClassTag;
  #125 = Utf8               flatMap$extension
  #126 = Utf8               (Ljava/lang/Object;Lscala/Function1;Lscala/Function1;Lscala/reflect/ClassTag;)Ljava/lang/Object;
  #127 = NameAndType        #125:#126     // flatMap$extension:(Ljava/lang/Object;Lscala/Function1;Lscala/Function1;Lscala/reflect/ClassTag;)Ljava/lang/Object;
  #128 = Methodref          #66.#127      // scala/collection/ArrayOps$.flatMap$extension:(Ljava/lang/Object;Lscala/Function1;Lscala/Function1;Lscala/reflect/ClassTag;)Ljava/lang/Object;
  #129 = Utf8               $plus$plus$extension
  #130 = Utf8               (Ljava/lang/Object;Ljava/lang/Object;Lscala/reflect/ClassTag;)Ljava/lang/Object;
  #131 = NameAndType        #129:#130     // $plus$plus$extension:(Ljava/lang/Object;Ljava/lang/Object;Lscala/reflect/ClassTag;)Ljava/lang/Object;
  #132 = Methodref          #66.#131      // scala/collection/ArrayOps$.$plus$plus$extension:(Ljava/lang/Object;Ljava/lang/Object;Lscala/reflect/ClassTag;)Ljava/lang/Object;
  #133 = Utf8               [Ljava/lang/String;
  #134 = Class              #133          // "[Ljava/lang/String;"
  #135 = NameAndType        #57:#58       // main:([Ljava/lang/String;)V
  #136 = Methodref          #61.#135      // org/scalatest/tools/Runner$.main:([Ljava/lang/String;)V
  #137 = Utf8               (Lorg/scalatest/Suite;Ljava/lang/String;Lorg/scalatest/ConfigMap;)V
  #138 = Utf8               suite
  #139 = Utf8               testName
  #140 = Utf8               configMap
  #141 = NameAndType        #18:#55       // defaultShell:()Lorg/scalatest/ShellImpl;
  #142 = Methodref          #2.#141       // org/scalatest/run$.defaultShell:()Lorg/scalatest/ShellImpl;
  #143 = Utf8               run
  #144 = NameAndType        #143:#137     // run:(Lorg/scalatest/Suite;Ljava/lang/String;Lorg/scalatest/ConfigMap;)V
  #145 = Methodref          #28.#144      // org/scalatest/ShellImpl.run:(Lorg/scalatest/Suite;Ljava/lang/String;Lorg/scalatest/ConfigMap;)V
  #146 = Utf8               Lorg/scalatest/Suite;
  #147 = Utf8               Ljava/lang/String;
  #148 = Utf8               Lorg/scalatest/ConfigMap;
  #149 = Utf8               ()Ljava/lang/String;
  #150 = Utf8               ()Lorg/scalatest/ConfigMap;
  #151 = Utf8               org/scalatest/ConfigMap$
  #152 = Class              #151          // org/scalatest/ConfigMap$
  #153 = Utf8               Lorg/scalatest/ConfigMap$;
  #154 = NameAndType        #16:#153      // MODULE$:Lorg/scalatest/ConfigMap$;
  #155 = Fieldref           #152.#154     // org/scalatest/ConfigMap$.MODULE$:Lorg/scalatest/ConfigMap$;
  #156 = Utf8               empty
  #157 = NameAndType        #156:#150     // empty:()Lorg/scalatest/ConfigMap;
  #158 = Methodref          #152.#157     // org/scalatest/ConfigMap$.empty:()Lorg/scalatest/ConfigMap;
  #159 = Utf8               s
  #160 = Utf8               -s
  #161 = String             #160          // -s
  #162 = Utf8               xs
  #163 = Utf8               wrapRefArray
  #164 = Utf8               ([Ljava/lang/Object;)Lscala/collection/mutable/ArraySeq$ofRef;
  #165 = NameAndType        #163:#164     // wrapRefArray:([Ljava/lang/Object;)Lscala/collection/mutable/ArraySeq$ofRef;
  #166 = Methodref          #71.#165      // scala/Predef$.wrapRefArray:([Ljava/lang/Object;)Lscala/collection/mutable/ArraySeq$ofRef;
  #167 = Methodref          #4.#23        // java/lang/Object."<init>":()V
  #168 = Utf8               $deserializeLambda$
  #169 = Utf8               (Ljava/lang/invoke/SerializedLambda;)Ljava/lang/Object;
  #170 = Utf8               scala/runtime/LambdaDeserialize
  #171 = Class              #170          // scala/runtime/LambdaDeserialize
  #172 = Utf8               bootstrap
  #173 = Utf8               (Ljava/lang/invoke/MethodHandles$Lookup;Ljava/lang/String;Ljava/lang/invoke/MethodType;[Ljava/lang/invoke/MethodHandle;)Ljava/lang/invoke/CallSite;
  #174 = NameAndType        #172:#173     // bootstrap:(Ljava/lang/invoke/MethodHandles$Lookup;Ljava/lang/String;Ljava/lang/invoke/MethodType;[Ljava/lang/invoke/MethodHandle;)Ljava/lang/invoke/CallSite;
  #175 = Methodref          #171.#174     // scala/runtime/LambdaDeserialize.bootstrap:(Ljava/lang/invoke/MethodHandles$Lookup;Ljava/lang/String;Ljava/lang/invoke/MethodType;[Ljava/lang/invoke/MethodHandle;)Ljava/lang/invoke/CallSite;
  #176 = MethodHandle       6:#175        // REF_invokeStatic scala/runtime/LambdaDeserialize.bootstrap:(Ljava/lang/invoke/MethodHandles$Lookup;Ljava/lang/String;Ljava/lang/invoke/MethodType;[Ljava/lang/invoke/MethodHandle;)Ljava/lang/invoke/CallSite;
  #177 = Utf8               lambdaDeserialize
  #178 = NameAndType        #177:#169     // lambdaDeserialize:(Ljava/lang/invoke/SerializedLambda;)Ljava/lang/Object;
  #179 = InvokeDynamic      #2:#178       // #2:lambdaDeserialize:(Ljava/lang/invoke/SerializedLambda;)Ljava/lang/Object;
  #180 = Utf8               Code
  #181 = Utf8               LineNumberTable
  #182 = Utf8               LocalVariableTable
  #183 = Utf8               MethodParameters
  #184 = Utf8               InnerClasses
  #185 = Utf8               SourceFile
  #186 = Utf8               BootstrapMethods
  #187 = Utf8               ScalaInlineInfo
  #188 = Utf8               Scala
{
  public static final org.scalatest.run$ MODULE$;
    descriptor: Lorg/scalatest/run$;
    flags: (0x0019) ACC_PUBLIC, ACC_STATIC, ACC_FINAL

  private static final org.scalatest.ShellImpl defaultShell;
    descriptor: Lorg/scalatest/ShellImpl;
    flags: (0x001a) ACC_PRIVATE, ACC_STATIC, ACC_FINAL

  public static {};
    descriptor: ()V
    flags: (0x0009) ACC_PUBLIC, ACC_STATIC
    Code:
      stack=7, locals=0, args_size=0
         0: new           #2                  // class org/scalatest/run$
         3: dup
         4: invokespecial #24                 // Method "<init>":()V
         7: putstatic     #26                 // Field MODULE$:Lorg/scalatest/run$;
        10: new           #28                 // class org/scalatest/ShellImpl
        13: dup
        14: getstatic     #33                 // Field org/scalatest/ShellImpl$.MODULE$:Lorg/scalatest/ShellImpl$;
        17: invokevirtual #37                 // Method org/scalatest/ShellImpl$.apply$default$1:()Z
        20: getstatic     #33                 // Field org/scalatest/ShellImpl$.MODULE$:Lorg/scalatest/ShellImpl$;
        23: invokevirtual #40                 // Method org/scalatest/ShellImpl$.apply$default$2:()Z
        26: getstatic     #33                 // Field org/scalatest/ShellImpl$.MODULE$:Lorg/scalatest/ShellImpl$;
        29: invokevirtual #43                 // Method org/scalatest/ShellImpl$.apply$default$3:()Z
        32: getstatic     #33                 // Field org/scalatest/ShellImpl$.MODULE$:Lorg/scalatest/ShellImpl$;
        35: invokevirtual #46                 // Method org/scalatest/ShellImpl$.apply$default$4:()Z
        38: getstatic     #33                 // Field org/scalatest/ShellImpl$.MODULE$:Lorg/scalatest/ShellImpl$;
        41: invokevirtual #49                 // Method org/scalatest/ShellImpl$.apply$default$5:()Z
        44: invokespecial #52                 // Method org/scalatest/ShellImpl."<init>":(ZZZZZ)V
        47: putstatic     #54                 // Field defaultShell:Lorg/scalatest/ShellImpl;
        50: return
      LineNumberTable:
        line 91: 0
        line 93: 10
        line 91: 50

  private org.scalatest.ShellImpl defaultShell();
    descriptor: ()Lorg/scalatest/ShellImpl;
    flags: (0x0002) ACC_PRIVATE
    Code:
      stack=1, locals=1, args_size=1
         0: getstatic     #54                 // Field defaultShell:Lorg/scalatest/ShellImpl;
         3: areturn
      LineNumberTable:
        line 93: 0
      LocalVariableTable:
        Start  Length  Slot  Name   Signature
            0       4     0  this   Lorg/scalatest/run$;

  public void main(java.lang.String[]);
    descriptor: ([Ljava/lang/String;)V
    flags: (0x0001) ACC_PUBLIC
    Code:
      stack=9, locals=2, args_size=2
         0: getstatic     #64                 // Field org/scalatest/tools/Runner$.MODULE$:Lorg/scalatest/tools/Runner$;
         3: getstatic     #69                 // Field scala/collection/ArrayOps$.MODULE$:Lscala/collection/ArrayOps$;
         6: getstatic     #74                 // Field scala/Predef$.MODULE$:Lscala/Predef$;
         9: iconst_3
        10: anewarray     #76                 // class java/lang/String
        13: dup
        14: iconst_0
        15: ldc           #78                 // String -R
        17: aastore
        18: dup
        19: iconst_1
        20: ldc           #80                 // String .
        22: aastore
        23: dup
        24: iconst_2
        25: ldc           #82                 // String -o
        27: aastore
        28: checkcast     #84                 // class "[Ljava/lang/Object;"
        31: checkcast     #84                 // class "[Ljava/lang/Object;"
        34: invokevirtual #88                 // Method scala/Predef$.refArrayOps:([Ljava/lang/Object;)Ljava/lang/Object;
        37: getstatic     #69                 // Field scala/collection/ArrayOps$.MODULE$:Lscala/collection/ArrayOps$;
        40: getstatic     #74                 // Field scala/Predef$.MODULE$:Lscala/Predef$;
        43: aload_1
        44: checkcast     #84                 // class "[Ljava/lang/Object;"
        47: invokevirtual #88                 // Method scala/Predef$.refArrayOps:([Ljava/lang/Object;)Ljava/lang/Object;
        50: invokedynamic #109,  0            // InvokeDynamic #0:apply:()Lscala/Function1;
        55: invokedynamic #116,  0            // InvokeDynamic #1:apply:()Lscala/Function1;
        60: getstatic     #121                // Field scala/reflect/ClassTag$.MODULE$:Lscala/reflect/ClassTag$;
        63: ldc           #76                 // class java/lang/String
        65: invokevirtual #124                // Method scala/reflect/ClassTag$.apply:(Ljava/lang/Class;)Lscala/reflect/ClassTag;
        68: invokevirtual #128                // Method scala/collection/ArrayOps$.flatMap$extension:(Ljava/lang/Object;Lscala/Function1;Lscala/Function1;Lscala/reflect/ClassTag;)Ljava/lang/Object;
        71: getstatic     #121                // Field scala/reflect/ClassTag$.MODULE$:Lscala/reflect/ClassTag$;
        74: ldc           #76                 // class java/lang/String
        76: invokevirtual #124                // Method scala/reflect/ClassTag$.apply:(Ljava/lang/Class;)Lscala/reflect/ClassTag;
        79: invokevirtual #132                // Method scala/collection/ArrayOps$.$plus$plus$extension:(Ljava/lang/Object;Ljava/lang/Object;Lscala/reflect/ClassTag;)Ljava/lang/Object;
        82: checkcast     #134                // class "[Ljava/lang/String;"
        85: invokevirtual #136                // Method org/scalatest/tools/Runner$.main:([Ljava/lang/String;)V
        88: return
      LineNumberTable:
        line 120: 0
      LocalVariableTable:
        Start  Length  Slot  Name   Signature
            0      89     0  this   Lorg/scalatest/run$;
            0      89     1  args   [Ljava/lang/String;
    MethodParameters:
      Name                           Flags
      args                           final

  public void apply(org.scalatest.Suite, java.lang.String, org.scalatest.ConfigMap);
    descriptor: (Lorg/scalatest/Suite;Ljava/lang/String;Lorg/scalatest/ConfigMap;)V
    flags: (0x0001) ACC_PUBLIC
    Code:
      stack=4, locals=4, args_size=4
         0: aload_0
         1: invokespecial #142                // Method defaultShell:()Lorg/scalatest/ShellImpl;
         4: aload_1
         5: aload_2
         6: aload_3
         7: invokevirtual #145                // Method org/scalatest/ShellImpl.run:(Lorg/scalatest/Suite;Ljava/lang/String;Lorg/scalatest/ConfigMap;)V
        10: return
      LineNumberTable:
        line 134: 0
      LocalVariableTable:
        Start  Length  Slot  Name   Signature
            0      11     0  this   Lorg/scalatest/run$;
            0      11     1 suite   Lorg/scalatest/Suite;
            0      11     2 testName   Ljava/lang/String;
            0      11     3 configMap   Lorg/scalatest/ConfigMap;
    MethodParameters:
      Name                           Flags
      suite                          final
      testName                       final
      configMap                      final

  public java.lang.String apply$default$2();
    descriptor: ()Ljava/lang/String;
    flags: (0x0001) ACC_PUBLIC
    Code:
      stack=1, locals=1, args_size=1
         0: aconst_null
         1: areturn
      LineNumberTable:
        line 133: 0
      LocalVariableTable:
        Start  Length  Slot  Name   Signature
            0       2     0  this   Lorg/scalatest/run$;

  public org.scalatest.ConfigMap apply$default$3();
    descriptor: ()Lorg/scalatest/ConfigMap;
    flags: (0x0001) ACC_PUBLIC
    Code:
      stack=1, locals=1, args_size=1
         0: getstatic     #155                // Field org/scalatest/ConfigMap$.MODULE$:Lorg/scalatest/ConfigMap$;
         3: invokevirtual #158                // Method org/scalatest/ConfigMap$.empty:()Lorg/scalatest/ConfigMap;
         6: areturn
      LineNumberTable:
        line 133: 0
      LocalVariableTable:
        Start  Length  Slot  Name   Signature
            0       7     0  this   Lorg/scalatest/run$;

  public static final java.lang.String[] $anonfun$main$1(java.lang.String);
    descriptor: (Ljava/lang/String;)[Ljava/lang/String;
    flags: (0x1019) ACC_PUBLIC, ACC_STATIC, ACC_FINAL, ACC_SYNTHETIC
    Code:
      stack=4, locals=1, args_size=1
         0: iconst_2
         1: anewarray     #76                 // class java/lang/String
         4: dup
         5: iconst_0
         6: ldc           #161                // String -s
         8: aastore
         9: dup
        10: iconst_1
        11: aload_0
        12: aastore
        13: checkcast     #84                 // class "[Ljava/lang/Object;"
        16: checkcast     #134                // class "[Ljava/lang/String;"
        19: areturn
      LineNumberTable:
        line 120: 0
      LocalVariableTable:
        Start  Length  Slot  Name   Signature
            0      20     0     s   Ljava/lang/String;
    MethodParameters:
      Name                           Flags
      s                              final

  public static final scala.collection.mutable.ArraySeq$ofRef $anonfun$main$2(java.lang.String[]);
    descriptor: ([Ljava/lang/String;)Lscala/collection/mutable/ArraySeq$ofRef;
    flags: (0x1019) ACC_PUBLIC, ACC_STATIC, ACC_FINAL, ACC_SYNTHETIC
    Code:
      stack=2, locals=1, args_size=1
         0: getstatic     #74                 // Field scala/Predef$.MODULE$:Lscala/Predef$;
         3: aload_0
         4: checkcast     #84                 // class "[Ljava/lang/Object;"
         7: invokevirtual #166                // Method scala/Predef$.wrapRefArray:([Ljava/lang/Object;)Lscala/collection/mutable/ArraySeq$ofRef;
        10: areturn
      LineNumberTable:
        line 120: 0
      LocalVariableTable:
        Start  Length  Slot  Name   Signature
            0      11     0    xs   [Ljava/lang/String;
    MethodParameters:
      Name                           Flags
      xs                             final

  private org.scalatest.run$();
    descriptor: ()V
    flags: (0x0002) ACC_PRIVATE
    Code:
      stack=1, locals=1, args_size=1
         0: aload_0
         1: invokespecial #167                // Method java/lang/Object."<init>":()V
         4: return
      LineNumberTable:
        line 136: 0
        line 91: 4
      LocalVariableTable:
        Start  Length  Slot  Name   Signature
            0       5     0  this   Lorg/scalatest/run$;

  private static java.lang.Object $deserializeLambda$(java.lang.invoke.SerializedLambda);
    descriptor: (Ljava/lang/invoke/SerializedLambda;)Ljava/lang/Object;
    flags: (0x100a) ACC_PRIVATE, ACC_STATIC, ACC_SYNTHETIC
    Code:
      stack=1, locals=1, args_size=1
         0: aload_0
         1: invokedynamic #179,  0            // InvokeDynamic #2:lambdaDeserialize:(Ljava/lang/invoke/SerializedLambda;)Ljava/lang/Object;
         6: areturn
}
InnerClasses:
  public static final #10= #7 of #9;      // Lookup=class java/lang/invoke/MethodHandles$Lookup of class java/lang/invoke/MethodHandles
  public static final #15= #12 of #14;    // ofRef=class scala/collection/mutable/ArraySeq$ofRef of class scala/collection/mutable/ArraySeq
SourceFile: "run.scala"
BootstrapMethods:
  0: #105 REF_invokeStatic java/lang/invoke/LambdaMetafactory.altMetafactory:(Ljava/lang/invoke/MethodHandles$Lookup;Ljava/lang/String;Ljava/lang/invoke/MethodType;[Ljava/lang/Object;)Ljava/lang/invoke/CallSite;
    Method arguments:
      #90 (Ljava/lang/Object;)Ljava/lang/Object;
      #95 REF_invokeStatic org/scalatest/run$.$anonfun$main$1:(Ljava/lang/String;)[Ljava/lang/String;
      #96 (Ljava/lang/String;)[Ljava/lang/String;
      #97 5
      #98 1
      #96 (Ljava/lang/String;)[Ljava/lang/String;
  1: #105 REF_invokeStatic java/lang/invoke/LambdaMetafactory.altMetafactory:(Ljava/lang/invoke/MethodHandles$Lookup;Ljava/lang/String;Ljava/lang/invoke/MethodType;[Ljava/lang/Object;)Ljava/lang/invoke/CallSite;
    Method arguments:
      #90 (Ljava/lang/Object;)Ljava/lang/Object;
      #114 REF_invokeStatic org/scalatest/run$.$anonfun$main$2:([Ljava/lang/String;)Lscala/collection/mutable/ArraySeq$ofRef;
      #115 ([Ljava/lang/String;)Lscala/collection/mutable/ArraySeq$ofRef;
      #97 5
      #98 1
      #115 ([Ljava/lang/String;)Lscala/collection/mutable/ArraySeq$ofRef;
  2: #176 REF_invokeStatic scala/runtime/LambdaDeserialize.bootstrap:(Ljava/lang/invoke/MethodHandles$Lookup;Ljava/lang/String;Ljava/lang/invoke/MethodType;[Ljava/lang/invoke/MethodHandle;)Ljava/lang/invoke/CallSite;
    Method arguments:
      #95 REF_invokeStatic org/scalatest/run$.$anonfun$main$1:(Ljava/lang/String;)[Ljava/lang/String;
      #114 REF_invokeStatic org/scalatest/run$.$anonfun$main$2:([Ljava/lang/String;)Lscala/collection/mutable/ArraySeq$ofRef;
  ScalaInlineInfo: length = 0x2C (unknown attribute)
   01 01 00 08 00 5B 00 5C 01 00 6E 00 6F 01 00 16
   00 15 01 00 6A 00 89 01 00 26 00 95 01 00 29 00
   96 01 00 12 00 37 01 00 39 00 3A 01
  Scala: length = 0x0 (unknown attribute)

