Classfile /Users/mw/Projects/slang-braindump/.jar/jar8/assemble/slang-braindump/assemble/content/org/scalatest/SeveredStackTraces.class
  Last modified May 29, 2022; size 2199 bytes
  SHA-256 checksum f0c46eb5bf296c3f025d5bbf67a36f5026170402fd3d1177ec8bc935427488b0
  Compiled from "SeveredStackTraces.scala"
public interface org.scalatest.SeveredStackTraces extends org.scalatest.TestSuiteMixin
  minor version: 0
  major version: 52
  flags: (0x0601) ACC_PUBLIC, ACC_INTERFACE, ACC_ABSTRACT
  this_class: #2                          // org/scalatest/SeveredStackTraces
  super_class: #4                         // java/lang/Object
  interfaces: 1, fields: 0, methods: 4, attributes: 5
Constant pool:
   #1 = Utf8               org/scalatest/SeveredStackTraces
   #2 = Class              #1             // org/scalatest/SeveredStackTraces
   #3 = Utf8               java/lang/Object
   #4 = Class              #3             // java/lang/Object
   #5 = Utf8               org/scalatest/TestSuiteMixin
   #6 = Class              #5             // org/scalatest/TestSuiteMixin
   #7 = Utf8               SeveredStackTraces.scala
   #8 = Utf8               Lscala/reflect/ScalaSignature;
   #9 = Utf8               bytes
  #10 = Utf8               \u0006\u0005A2\u0001\u0002B\u0003\u0011\u0002\u0007\u0005!b\u000b\u0005\u0006+\u0001!\tA\u0006\u0005\u00075\u0001\u0001J\u0011A\u000e\t\u0017\u001d\u0002\u0001\u0013aA\u0001\u0002\u0013%\u0001F\u000b\u0002\u0013\'\u00164XM]3e\'R\f7m\u001b+sC\u000e,7O\u0003\u0002\u0007\u000f\u0005I1oY1mCR,7\u000f\u001e\u0006\u0002\u0011\u0005\u0019qN]4\u0004\u0001M\u0019\u0001aC\t\u0011\u00051yQ\"A\u0007\u000b\u00039\tQa]2bY\u0006L!\u0001E\u0007\u0003\r\u0005s\u0017PU3g!\t\u00112#D\u0001\u0006\u0013\t!RA\u0001\bUKN$8+^5uK6K\u00070\u001b8\u0002\r\u0011Jg.\u001b;%)\u00059\u0002C\u0001\u0007\u0019\u0013\tIRB\u0001\u0003V]&$\u0018aC<ji\"4\u0015\u000e\u001f;ve\u0016$\"\u0001H\u0010\u0011\u0005Ii\u0012B\u0001\u0010\u0006\u0005\u001dyU\u000f^2p[\u0016DQ\u0001\t\u0002A\u0002\u0005\nA\u0001^3tiB\u0011!eI\u0007\u0002\u0001%\u0011A%\n\u0002\n\u001d>\f%o\u001a+fgRL!AJ\u0003\u0003\u0013Q+7\u000f^*vSR,\u0017!E:va\u0016\u0014He^5uQ\u001aK\u0007\u0010^;sKR\u0011A$\u000b\u0005\u0006A\r\u0001\r!I\u0005\u00035M\u00112\u0001\f\u00180\r\u0011i\u0003\u0001A\u0016\u0003\u0019q\u0012XMZ5oK6,g\u000e\u001e \u0011\u0005I\u0001\u0001C\u0001\n&\u0001
  #11 = Utf8               org/scalatest/TestSuite$NoArgTest
  #12 = Class              #11            // org/scalatest/TestSuite$NoArgTest
  #13 = Utf8               org/scalatest/TestSuite
  #14 = Class              #13            // org/scalatest/TestSuite
  #15 = Utf8               NoArgTest
  #16 = Utf8               org$scalatest$SeveredStackTraces$$super$withFixture
  #17 = Utf8               (Lorg/scalatest/TestSuite$NoArgTest;)Lorg/scalatest/Outcome;
  #18 = Utf8               test
  #19 = Utf8               withFixture$
  #20 = Utf8               (Lorg/scalatest/SeveredStackTraces;Lorg/scalatest/TestSuite$NoArgTest;)Lorg/scalatest/Outcome;
  #21 = Utf8               $this
  #22 = Utf8               withFixture
  #23 = NameAndType        #22:#17        // withFixture:(Lorg/scalatest/TestSuite$NoArgTest;)Lorg/scalatest/Outcome;
  #24 = InterfaceMethodref #2.#23         // org/scalatest/SeveredStackTraces.withFixture:(Lorg/scalatest/TestSuite$NoArgTest;)Lorg/scalatest/Outcome;
  #25 = Utf8               Lorg/scalatest/SeveredStackTraces;
  #26 = Utf8               Lorg/scalatest/TestSuite$NoArgTest;
  #27 = NameAndType        #16:#17        // org$scalatest$SeveredStackTraces$$super$withFixture:(Lorg/scalatest/TestSuite$NoArgTest;)Lorg/scalatest/Outcome;
  #28 = InterfaceMethodref #2.#27         // org/scalatest/SeveredStackTraces.org$scalatest$SeveredStackTraces$$super$withFixture:(Lorg/scalatest/TestSuite$NoArgTest;)Lorg/scalatest/Outcome;
  #29 = Utf8               org/scalatest/Exceptional$
  #30 = Class              #29            // org/scalatest/Exceptional$
  #31 = Utf8               MODULE$
  #32 = Utf8               Lorg/scalatest/Exceptional$;
  #33 = NameAndType        #31:#32        // MODULE$:Lorg/scalatest/Exceptional$;
  #34 = Fieldref           #30.#33        // org/scalatest/Exceptional$.MODULE$:Lorg/scalatest/Exceptional$;
  #35 = Utf8               unapply
  #36 = Utf8               (Lorg/scalatest/Outcome;)Lscala/Option;
  #37 = NameAndType        #35:#36        // unapply:(Lorg/scalatest/Outcome;)Lscala/Option;
  #38 = Methodref          #30.#37        // org/scalatest/Exceptional$.unapply:(Lorg/scalatest/Outcome;)Lscala/Option;
  #39 = Utf8               scala/Option
  #40 = Class              #39            // scala/Option
  #41 = Utf8               isEmpty
  #42 = Utf8               ()Z
  #43 = NameAndType        #41:#42        // isEmpty:()Z
  #44 = Methodref          #40.#43        // scala/Option.isEmpty:()Z
  #45 = Utf8               get
  #46 = Utf8               ()Ljava/lang/Object;
  #47 = NameAndType        #45:#46        // get:()Ljava/lang/Object;
  #48 = Methodref          #40.#47        // scala/Option.get:()Ljava/lang/Object;
  #49 = Utf8               java/lang/Throwable
  #50 = Class              #49            // java/lang/Throwable
  #51 = Utf8               org/scalatest/exceptions/StackDepth
  #52 = Class              #51            // org/scalatest/exceptions/StackDepth
  #53 = Utf8               severedAtStackDepth
  #54 = Utf8               ()Ljava/lang/Throwable;
  #55 = NameAndType        #53:#54        // severedAtStackDepth:()Ljava/lang/Throwable;
  #56 = InterfaceMethodref #52.#55        // org/scalatest/exceptions/StackDepth.severedAtStackDepth:()Ljava/lang/Throwable;
  #57 = Utf8               apply
  #58 = Utf8               (Ljava/lang/Throwable;)Lorg/scalatest/Exceptional;
  #59 = NameAndType        #57:#58        // apply:(Ljava/lang/Throwable;)Lorg/scalatest/Exceptional;
  #60 = Methodref          #30.#59        // org/scalatest/Exceptional$.apply:(Ljava/lang/Throwable;)Lorg/scalatest/Exceptional;
  #61 = Utf8               e
  #62 = Utf8               Ljava/lang/Throwable;
  #63 = Utf8               this
  #64 = Utf8               org/scalatest/Outcome
  #65 = Class              #64            // org/scalatest/Outcome
  #66 = Utf8               $init$
  #67 = Utf8               (Lorg/scalatest/SeveredStackTraces;)V
  #68 = Utf8               MethodParameters
  #69 = Utf8               Code
  #70 = Utf8               LineNumberTable
  #71 = Utf8               LocalVariableTable
  #72 = Utf8               StackMapTable
  #73 = Utf8               InnerClasses
  #74 = Utf8               SourceFile
  #75 = Utf8               RuntimeVisibleAnnotations
  #76 = Utf8               ScalaInlineInfo
  #77 = Utf8               ScalaSig
{
  public abstract org.scalatest.Outcome org$scalatest$SeveredStackTraces$$super$withFixture(org.scalatest.TestSuite$NoArgTest);
    descriptor: (Lorg/scalatest/TestSuite$NoArgTest;)Lorg/scalatest/Outcome;
    flags: (0x1401) ACC_PUBLIC, ACC_ABSTRACT, ACC_SYNTHETIC
    MethodParameters:
      Name                           Flags
      test                           final

  public static org.scalatest.Outcome withFixture$(org.scalatest.SeveredStackTraces, org.scalatest.TestSuite$NoArgTest);
    descriptor: (Lorg/scalatest/SeveredStackTraces;Lorg/scalatest/TestSuite$NoArgTest;)Lorg/scalatest/Outcome;
    flags: (0x1009) ACC_PUBLIC, ACC_STATIC, ACC_SYNTHETIC
    Code:
      stack=2, locals=2, args_size=2
         0: aload_0
         1: aload_1
         2: invokespecial #24                 // InterfaceMethod withFixture:(Lorg/scalatest/TestSuite$NoArgTest;)Lorg/scalatest/Outcome;
         5: areturn
      LineNumberTable:
        line 35: 0
      LocalVariableTable:
        Start  Length  Slot  Name   Signature
            0       6     0 $this   Lorg/scalatest/SeveredStackTraces;
            0       6     1  test   Lorg/scalatest/TestSuite$NoArgTest;
    MethodParameters:
      Name                           Flags
      $this                          final synthetic
      test                           final

  public default org.scalatest.Outcome withFixture(org.scalatest.TestSuite$NoArgTest);
    descriptor: (Lorg/scalatest/TestSuite$NoArgTest;)Lorg/scalatest/Outcome;
    flags: (0x0001) ACC_PUBLIC
    Code:
      stack=2, locals=7, args_size=2
         0: aload_0
         1: aload_1
         2: invokeinterface #28,  2           // InterfaceMethod org$scalatest$SeveredStackTraces$$super$withFixture:(Lorg/scalatest/TestSuite$NoArgTest;)Lorg/scalatest/Outcome;
         7: astore_3
         8: aload_3
         9: ifnull        77
        12: getstatic     #34                 // Field org/scalatest/Exceptional$.MODULE$:Lorg/scalatest/Exceptional$;
        15: aload_3
        16: invokevirtual #38                 // Method org/scalatest/Exceptional$.unapply:(Lorg/scalatest/Outcome;)Lscala/Option;
        19: astore        4
        21: aload         4
        23: invokevirtual #44                 // Method scala/Option.isEmpty:()Z
        26: ifne          74
        29: aload         4
        31: invokevirtual #48                 // Method scala/Option.get:()Ljava/lang/Object;
        34: checkcast     #50                 // class java/lang/Throwable
        37: astore        5
        39: aload         5
        41: instanceof    #52                 // class org/scalatest/exceptions/StackDepth
        44: ifeq          71
        47: aload         5
        49: astore        6
        51: getstatic     #34                 // Field org/scalatest/Exceptional$.MODULE$:Lorg/scalatest/Exceptional$;
        54: aload         6
        56: checkcast     #52                 // class org/scalatest/exceptions/StackDepth
        59: invokeinterface #56,  1           // InterfaceMethod org/scalatest/exceptions/StackDepth.severedAtStackDepth:()Ljava/lang/Throwable;
        64: invokevirtual #60                 // Method org/scalatest/Exceptional$.apply:(Ljava/lang/Throwable;)Lorg/scalatest/Exceptional;
        67: astore_2
        68: goto          85
        71: goto          80
        74: goto          80
        77: goto          80
        80: aload_3
        81: astore_2
        82: goto          85
        85: aload_2
        86: areturn
      StackMapTable: number_of_entries = 5
        frame_type = 255 /* full_frame */
          offset_delta = 71
          locals = [ class org/scalatest/SeveredStackTraces, class org/scalatest/TestSuite$NoArgTest, top, class org/scalatest/Outcome, class scala/Option, class java/lang/Throwable ]
          stack = []
        frame_type = 250 /* chop */
          offset_delta = 2
        frame_type = 250 /* chop */
          offset_delta = 2
        frame_type = 2 /* same */
        frame_type = 255 /* full_frame */
          offset_delta = 4
          locals = [ class org/scalatest/SeveredStackTraces, class org/scalatest/TestSuite$NoArgTest, class org/scalatest/Outcome, class org/scalatest/Outcome ]
          stack = []
      LineNumberTable:
        line 36: 0
        line 37: 8
        line 36: 29
        line 37: 39
        line 38: 80
        line 36: 85
      LocalVariableTable:
        Start  Length  Slot  Name   Signature
           39      35     5     e   Ljava/lang/Throwable;
            0      87     0  this   Lorg/scalatest/SeveredStackTraces;
            0      87     1  test   Lorg/scalatest/TestSuite$NoArgTest;
    MethodParameters:
      Name                           Flags
      test                           final

  public static void $init$(org.scalatest.SeveredStackTraces);
    descriptor: (Lorg/scalatest/SeveredStackTraces;)V
    flags: (0x0009) ACC_PUBLIC, ACC_STATIC
    Code:
      stack=0, locals=1, args_size=1
         0: return
      LineNumberTable:
        line 29: 0
      LocalVariableTable:
        Start  Length  Slot  Name   Signature
            0       1     0 $this   Lorg/scalatest/SeveredStackTraces;
    MethodParameters:
      Name                           Flags
      $this                          final synthetic
}
InnerClasses:
  public #15= #12 of #14;                 // NoArgTest=class org/scalatest/TestSuite$NoArgTest of class org/scalatest/TestSuite
SourceFile: "SeveredStackTraces.scala"
RuntimeVisibleAnnotations:
  0: #8(#9=s#10)
    scala.reflect.ScalaSignature(
      bytes="\u0006\u0005A2\u0001\u0002B\u0003\u0011\u0002\u0007\u0005!b\u000b\u0005\u0006+\u0001!\tA\u0006\u0005\u00075\u0001\u0001J\u0011A\u000e\t\u0017\u001d\u0002\u0001\u0013aA\u0001\u0002\u0013%\u0001F\u000b\u0002\u0013\'\u00164XM]3e\'R\f7m\u001b+sC\u000e,7O\u0003\u0002\u0007\u000f\u0005I1oY1mCR,7\u000f\u001e\u0006\u0002\u0011\u0005\u0019qN]4\u0004\u0001M\u0019\u0001aC\t\u0011\u00051yQ\"A\u0007\u000b\u00039\tQa]2bY\u0006L!\u0001E\u0007\u0003\r\u0005s\u0017PU3g!\t\u00112#D\u0001\u0006\u0013\t!RA\u0001\bUKN$8+^5uK6K\u00070\u001b8\u0002\r\u0011Jg.\u001b;%)\u00059\u0002C\u0001\u0007\u0019\u0013\tIRB\u0001\u0003V]&$\u0018aC<ji\"4\u0015\u000e\u001f;ve\u0016$\"\u0001H\u0010\u0011\u0005Ii\u0012B\u0001\u0010\u0006\u0005\u001dyU\u000f^2p[\u0016DQ\u0001\t\u0002A\u0002\u0005\nA\u0001^3tiB\u0011!eI\u0007\u0002\u0001%\u0011A%\n\u0002\n\u001d>\f%o\u001a+fgRL!AJ\u0003\u0003\u0013Q+7\u000f^*vSR,\u0017!E:va\u0016\u0014He^5uQ\u001aK\u0007\u0010^;sKR\u0011A$\u000b\u0005\u0006A\r\u0001\r!I\u0005\u00035M\u00112\u0001\f\u00180\r\u0011i\u0003\u0001A\u0016\u0003\u0019q\u0012XMZ5oK6,g\u000e\u001e \u0011\u0005I\u0001\u0001C\u0001\n&\u0001"
    )
  ScalaInlineInfo: length = 0x18 (unknown attribute)
   01 00 00 04 00 42 00 43 01 00 10 00 11 01 00 16
   00 11 00 00 13 00 14 01
  ScalaSig: length = 0x3 (unknown attribute)
   05 02 00
