Classfile /Users/mw/Projects/slang-braindump/.jar/jar8/assemble/slang-braindump/assemble/content/org/scalatest/Shell.class
  Last modified May 29, 2022; size 1985 bytes
  SHA-256 checksum 1b13a8dbbc2e74598cc3327627210d4e8554a8d6fefa1d8ef63d0c1bee5d5e12
  Compiled from "Shell.scala"
public interface org.scalatest.Shell
  minor version: 0
  major version: 52
  flags: (0x0601) ACC_PUBLIC, ACC_INTERFACE, ACC_ABSTRACT
  this_class: #2                          // org/scalatest/Shell
  super_class: #4                         // java/lang/Object
  interfaces: 0, fields: 0, methods: 14, attributes: 4
Constant pool:
   #1 = Utf8               org/scalatest/Shell
   #2 = Class              #1             // org/scalatest/Shell
   #3 = Utf8               java/lang/Object
   #4 = Class              #3             // java/lang/Object
   #5 = Utf8               Shell.scala
   #6 = Utf8               Lscala/reflect/ScalaSignature;
   #7 = Utf8               bytes
   #8 = Utf8               \u0006\u0005Q3q!\u0004\b\u0011\u0002\u0007\u00052\u0003C\u0003\u001b\u0001\u0019\u00051\u0004C\u0003\u001f\u0001\u0019\u00051\u0004C\u0003 \u0001\u0019\u00051\u0004C\u0003!\u0001\u0019\u00051\u0004C\u0003\"\u0001\u0019\u00051\u0004C\u0003#\u0001\u0019\u00051\u0004C\u0003$\u0001\u0019\u00051\u0004C\u0003%\u0001\u0019\u00051\u0004C\u0003&\u0001\u0019\u00051\u0004C\u0003\'\u0001\u0019\u0005q\u0005C\u0004C\u0001E\u0005I\u0011A\"\t\u000f9\u0003\u0011\u0013!C\u0001\u001f\n)1\u000b[3mY*\u0011q\u0002E\u0001\ng\u000e\fG.\u0019;fgRT\u0011!E\u0001\u0004_J<7\u0001A\n\u0003\u0001Q\u0001\"!\u0006\r\u000e\u0003YQ\u0011aF\u0001\u0006g\u000e\fG.Y\u0005\u00033Y\u0011a!\u00118z%\u00164\u0017!B2pY>\u0014X#\u0001\u000f\u0011\u0005u\u0001Q\"\u0001\b\u0002\u0013\u0011,(/\u0019;j_:\u001c\u0018aC:i_J$8\u000f^1dWN\f!BZ;mYN$\u0018mY6t\u0003\u0015\u0019H/\u0019;t\u0003\u001dqwnY8m_J\f1B\\8ekJ\fG/[8og\u0006Aan\\:uC\u000e\\7/A\u0004o_N$\u0018\r^:\u0002\u0007I,h\u000e\u0006\u0003)WAj\u0004CA\u000b*\u0013\tQcC\u0001\u0003V]&$\b\"\u0002\u0017\u000b\u0001\u0004i\u0013!B:vSR,\u0007CA\u000f/\u0013\tycBA\u0003Tk&$X\rC\u00042\u0015A\u0005\t\u0019\u0001\u001a\u0002\u0011Q,7\u000f\u001e(b[\u0016\u0004\"a\r\u001e\u000f\u0005QB\u0004CA\u001b\u0017\u001b\u00051$BA\u001c\u0013\u0003\u0019a$o\\8u}%\u0011\u0011HF\u0001\u0007!J,G-\u001a4\n\u0005mb$AB*ue&twM\u0003\u0002:-!9aH\u0003I\u0001\u0002\u0004y\u0014!C2p]\u001aLw-T1q!\ti\u0002)\u0003\u0002B\u001d\tI1i\u001c8gS\u001el\u0015\r]\u0001\u000eeVtG\u0005Z3gCVdG\u000f\n\u001a\u0016\u0003\u0011S#AM#,\u0003\u0019\u0003\"a\u0012\'\u000e\u0003!S!!\u0013&\u0002\u0013Ut7\r[3dW\u0016$\'BA&\u0017\u0003)\tgN\\8uCRLwN\\\u0005\u0003\u001b\"\u0013\u0011#\u001e8dQ\u0016\u001c7.\u001a3WCJL\u0017M\\2f\u00035\u0011XO\u001c\u0013eK\u001a\fW\u000f\u001c;%gU\t\u0001K\u000b\u0002@\u000b&\u0012\u0001AU\u0005\u0003\':\u0011\u0011b\u00155fY2LU\u000e\u001d7
   #9 = Utf8               color
  #10 = Utf8               ()Lorg/scalatest/Shell;
  #11 = Utf8               durations
  #12 = Utf8               shortstacks
  #13 = Utf8               fullstacks
  #14 = Utf8               stats
  #15 = Utf8               nocolor
  #16 = Utf8               nodurations
  #17 = Utf8               nostacks
  #18 = Utf8               nostats
  #19 = Utf8               run
  #20 = Utf8               (Lorg/scalatest/Suite;Ljava/lang/String;Lorg/scalatest/ConfigMap;)V
  #21 = Utf8               suite
  #22 = Utf8               testName
  #23 = Utf8               configMap
  #24 = Utf8               run$default$2$
  #25 = Utf8               (Lorg/scalatest/Shell;)Ljava/lang/String;
  #26 = Utf8               $this
  #27 = Utf8               run$default$2
  #28 = Utf8               ()Ljava/lang/String;
  #29 = NameAndType        #27:#28        // run$default$2:()Ljava/lang/String;
  #30 = InterfaceMethodref #2.#29         // org/scalatest/Shell.run$default$2:()Ljava/lang/String;
  #31 = Utf8               Lorg/scalatest/Shell;
  #32 = Utf8               this
  #33 = Utf8               run$default$3$
  #34 = Utf8               (Lorg/scalatest/Shell;)Lorg/scalatest/ConfigMap;
  #35 = Utf8               run$default$3
  #36 = Utf8               ()Lorg/scalatest/ConfigMap;
  #37 = NameAndType        #35:#36        // run$default$3:()Lorg/scalatest/ConfigMap;
  #38 = InterfaceMethodref #2.#37         // org/scalatest/Shell.run$default$3:()Lorg/scalatest/ConfigMap;
  #39 = Utf8               org/scalatest/ConfigMap$
  #40 = Class              #39            // org/scalatest/ConfigMap$
  #41 = Utf8               MODULE$
  #42 = Utf8               Lorg/scalatest/ConfigMap$;
  #43 = NameAndType        #41:#42        // MODULE$:Lorg/scalatest/ConfigMap$;
  #44 = Fieldref           #40.#43        // org/scalatest/ConfigMap$.MODULE$:Lorg/scalatest/ConfigMap$;
  #45 = Utf8               empty
  #46 = NameAndType        #45:#36        // empty:()Lorg/scalatest/ConfigMap;
  #47 = Methodref          #40.#46        // org/scalatest/ConfigMap$.empty:()Lorg/scalatest/ConfigMap;
  #48 = Utf8               MethodParameters
  #49 = Utf8               Code
  #50 = Utf8               LineNumberTable
  #51 = Utf8               LocalVariableTable
  #52 = Utf8               SourceFile
  #53 = Utf8               RuntimeVisibleAnnotations
  #54 = Utf8               ScalaInlineInfo
  #55 = Utf8               ScalaSig
{
  public abstract org.scalatest.Shell color();
    descriptor: ()Lorg/scalatest/Shell;
    flags: (0x0401) ACC_PUBLIC, ACC_ABSTRACT

  public abstract org.scalatest.Shell durations();
    descriptor: ()Lorg/scalatest/Shell;
    flags: (0x0401) ACC_PUBLIC, ACC_ABSTRACT

  public abstract org.scalatest.Shell shortstacks();
    descriptor: ()Lorg/scalatest/Shell;
    flags: (0x0401) ACC_PUBLIC, ACC_ABSTRACT

  public abstract org.scalatest.Shell fullstacks();
    descriptor: ()Lorg/scalatest/Shell;
    flags: (0x0401) ACC_PUBLIC, ACC_ABSTRACT

  public abstract org.scalatest.Shell stats();
    descriptor: ()Lorg/scalatest/Shell;
    flags: (0x0401) ACC_PUBLIC, ACC_ABSTRACT

  public abstract org.scalatest.Shell nocolor();
    descriptor: ()Lorg/scalatest/Shell;
    flags: (0x0401) ACC_PUBLIC, ACC_ABSTRACT

  public abstract org.scalatest.Shell nodurations();
    descriptor: ()Lorg/scalatest/Shell;
    flags: (0x0401) ACC_PUBLIC, ACC_ABSTRACT

  public abstract org.scalatest.Shell nostacks();
    descriptor: ()Lorg/scalatest/Shell;
    flags: (0x0401) ACC_PUBLIC, ACC_ABSTRACT

  public abstract org.scalatest.Shell nostats();
    descriptor: ()Lorg/scalatest/Shell;
    flags: (0x0401) ACC_PUBLIC, ACC_ABSTRACT

  public abstract void run(org.scalatest.Suite, java.lang.String, org.scalatest.ConfigMap);
    descriptor: (Lorg/scalatest/Suite;Ljava/lang/String;Lorg/scalatest/ConfigMap;)V
    flags: (0x0401) ACC_PUBLIC, ACC_ABSTRACT
    MethodParameters:
      Name                           Flags
      suite                          final
      testName                       final
      configMap                      final

  public static java.lang.String run$default$2$(org.scalatest.Shell);
    descriptor: (Lorg/scalatest/Shell;)Ljava/lang/String;
    flags: (0x1009) ACC_PUBLIC, ACC_STATIC, ACC_SYNTHETIC
    Code:
      stack=1, locals=1, args_size=1
         0: aload_0
         1: invokespecial #30                 // InterfaceMethod run$default$2:()Ljava/lang/String;
         4: areturn
      LineNumberTable:
        line 380: 0
      LocalVariableTable:
        Start  Length  Slot  Name   Signature
            0       5     0 $this   Lorg/scalatest/Shell;
    MethodParameters:
      Name                           Flags
      $this                          final synthetic

  public default java.lang.String run$default$2();
    descriptor: ()Ljava/lang/String;
    flags: (0x0001) ACC_PUBLIC
    Code:
      stack=1, locals=1, args_size=1
         0: aconst_null
         1: areturn
      LineNumberTable:
        line 380: 0
      LocalVariableTable:
        Start  Length  Slot  Name   Signature
            0       2     0  this   Lorg/scalatest/Shell;

  public static org.scalatest.ConfigMap run$default$3$(org.scalatest.Shell);
    descriptor: (Lorg/scalatest/Shell;)Lorg/scalatest/ConfigMap;
    flags: (0x1009) ACC_PUBLIC, ACC_STATIC, ACC_SYNTHETIC
    Code:
      stack=1, locals=1, args_size=1
         0: aload_0
         1: invokespecial #38                 // InterfaceMethod run$default$3:()Lorg/scalatest/ConfigMap;
         4: areturn
      LineNumberTable:
        line 380: 0
      LocalVariableTable:
        Start  Length  Slot  Name   Signature
            0       5     0 $this   Lorg/scalatest/Shell;
    MethodParameters:
      Name                           Flags
      $this                          final synthetic

  public default org.scalatest.ConfigMap run$default$3();
    descriptor: ()Lorg/scalatest/ConfigMap;
    flags: (0x0001) ACC_PUBLIC
    Code:
      stack=1, locals=1, args_size=1
         0: getstatic     #44                 // Field org/scalatest/ConfigMap$.MODULE$:Lorg/scalatest/ConfigMap$;
         3: invokevirtual #47                 // Method org/scalatest/ConfigMap$.empty:()Lorg/scalatest/ConfigMap;
         6: areturn
      LineNumberTable:
        line 380: 0
      LocalVariableTable:
        Start  Length  Slot  Name   Signature
            0       7     0  this   Lorg/scalatest/Shell;
}
SourceFile: "Shell.scala"
RuntimeVisibleAnnotations:
  0: #6(#7=s#8)
    scala.reflect.ScalaSignature(
      bytes="\u0006\u0005Q3q!\u0004\b\u0011\u0002\u0007\u00052\u0003C\u0003\u001b\u0001\u0019\u00051\u0004C\u0003\u001f\u0001\u0019\u00051\u0004C\u0003 \u0001\u0019\u00051\u0004C\u0003!\u0001\u0019\u00051\u0004C\u0003\"\u0001\u0019\u00051\u0004C\u0003#\u0001\u0019\u00051\u0004C\u0003$\u0001\u0019\u00051\u0004C\u0003%\u0001\u0019\u00051\u0004C\u0003&\u0001\u0019\u00051\u0004C\u0003\'\u0001\u0019\u0005q\u0005C\u0004C\u0001E\u0005I\u0011A\"\t\u000f9\u0003\u0011\u0013!C\u0001\u001f\n)1\u000b[3mY*\u0011q\u0002E\u0001\ng\u000e\fG.\u0019;fgRT\u0011!E\u0001\u0004_J<7\u0001A\n\u0003\u0001Q\u0001\"!\u0006\r\u000e\u0003YQ\u0011aF\u0001\u0006g\u000e\fG.Y\u0005\u00033Y\u0011a!\u00118z%\u00164\u0017!B2pY>\u0014X#\u0001\u000f\u0011\u0005u\u0001Q\"\u0001\b\u0002\u0013\u0011,(/\u0019;j_:\u001c\u0018aC:i_J$8\u000f^1dWN\f!BZ;mYN$\u0018mY6t\u0003\u0015\u0019H/\u0019;t\u0003\u001dqwnY8m_J\f1B\\8ekJ\fG/[8og\u0006Aan\\:uC\u000e\\7/A\u0004o_N$\u0018\r^:\u0002\u0007I,h\u000e\u0006\u0003)WAj\u0004CA\u000b*\u0013\tQcC\u0001\u0003V]&$\b\"\u0002\u0017\u000b\u0001\u0004i\u0013!B:vSR,\u0007CA\u000f/\u0013\tycBA\u0003Tk&$X\rC\u00042\u0015A\u0005\t\u0019\u0001\u001a\u0002\u0011Q,7\u000f\u001e(b[\u0016\u0004\"a\r\u001e\u000f\u0005QB\u0004CA\u001b\u0017\u001b\u00051$BA\u001c\u0013\u0003\u0019a$o\\8u}%\u0011\u0011HF\u0001\u0007!J,G-\u001a4\n\u0005mb$AB*ue&twM\u0003\u0002:-!9aH\u0003I\u0001\u0002\u0004y\u0014!C2p]\u001aLw-T1q!\ti\u0002)\u0003\u0002B\u001d\tI1i\u001c8gS\u001el\u0015\r]\u0001\u000eeVtG\u0005Z3gCVdG\u000f\n\u001a\u0016\u0003\u0011S#AM#,\u0003\u0019\u0003\"a\u0012\'\u000e\u0003!S!!\u0013&\u0002\u0013Ut7\r[3dW\u0016$\'BA&\u0017\u0003)\tgN\\8uCRLwN\\\u0005\u0003\u001b\"\u0013\u0011#\u001e8dQ\u0016\u001c7.\u001a3WCJL\u0017M\\2f\u00035\u0011XO\u001c\u0013eK\u001a\fW\u000f\u001c;%gU\t\u0001K\u000b\u0002@\u000b&\u0012\u0001AU\u0005\u0003\':\u0011\u0011b\u00155fY2LU\u000e\u001d7"
    )
  ScalaInlineInfo: length = 0x4A (unknown attribute)
   01 00 00 0E 00 09 00 0A 00 00 0B 00 0A 00 00 0D
   00 0A 00 00 0F 00 0A 00 00 10 00 0A 00 00 11 00
   0A 00 00 12 00 0A 00 00 13 00 14 00 00 1B 00 1C
   00 00 18 00 19 01 00 23 00 24 00 00 21 00 22 01
   00 0C 00 0A 00 00 0E 00 0A 00
  ScalaSig: length = 0x3 (unknown attribute)
   05 02 00
