Classfile /Users/mw/Projects/slang-braindump/.jar/jar8/assemble/slang-braindump/assemble/content/org/scalatest/SlowpokeDetector.class
  Last modified May 29, 2022; size 8636 bytes
  SHA-256 checksum ae154ef739e39f6b9c43485d4443bde600ea528ea401f5a03cce59d79a00d4e2
  Compiled from "SlowpokeDetector.scala"
public class org.scalatest.SlowpokeDetector
  minor version: 0
  major version: 52
  flags: (0x0021) ACC_PUBLIC, ACC_SUPER
  this_class: #2                          // org/scalatest/SlowpokeDetector
  super_class: #4                         // java/lang/Object
  interfaces: 0, fields: 3, methods: 13, attributes: 6
Constant pool:
    #1 = Utf8               org/scalatest/SlowpokeDetector
    #2 = Class              #1            // org/scalatest/SlowpokeDetector
    #3 = Utf8               java/lang/Object
    #4 = Class              #3            // java/lang/Object
    #5 = Utf8               SlowpokeDetector.scala
    #6 = Utf8               Lscala/reflect/ScalaSignature;
    #7 = Utf8               bytes
    #8 = Utf8               \u0006\u0005q4QAD\b\u0001\u001fMA\u0001B\u0007\u0001\u0003\u0002\u0003\u0006I\u0001\b\u0005\t?\u0001\u0011\t\u0011)A\u0005A!)\u0001\u0006\u0001C\u0001S!9a\u0006\u0001b\u0001\n\u001by\u0003BB\u001e\u0001A\u00035\u0001\u0007C\u0003=\u0001\u0011\u0005Q\bC\u0003U\u0001\u0011\u0005Q\u000bC\u0003Z\u0001\u0011\u0005!l\u0002\u0005j\u001f\u0005\u0005\t\u0012A\bk\r!qq\"!A\t\u0002=Y\u0007\"\u0002\u0015\u000b\t\u0003a\u0007bB7\u000b#\u0003%\tA\u001c\u0005\bs*\t\n\u0011\"\u0001{\u0005A\u0019Fn\\<q_.,G)\u001a;fGR|\'O\u0003\u0002\u0011#\u0005I1oY1mCR,7\u000f\u001e\u0006\u0002%\u0005\u0019qN]4\u0014\u0005\u0001!\u0002CA\u000b\u0019\u001b\u00051\"\"A\f\u0002\u000bM\u001c\u0017\r\\1\n\u0005e1\"AB!osJ+g-A\u0004uS6,w.\u001e;\u0004\u0001A\u0011Q#H\u0005\u0003=Y\u0011A\u0001T8oO\u0006\u0019q.\u001e;\u0011\u0005\u00052S\"\u0001\u0012\u000b\u0005\r\"\u0013AA5p\u0015\u0005)\u0013\u0001\u00026bm\u0006L!a\n\u0012\u0003\u0017A\u0013\u0018N\u001c;TiJ,\u0017-\\\u0001\u0007y%t\u0017\u000e\u001e \u0015\u0007)bS\u0006\u0005\u0002,\u00015\tq\u0002C\u0004\u001b\u0007A\u0005\t\u0019\u0001\u000f\t\u000f}\u0019\u0001\u0013!a\u0001A\u0005a!/\u001e8oS:<G+Z:ugV\t\u0001\u0007E\u00022maj\u0011A\r\u0006\u0003gQ\n!bY8oGV\u0014(/\u001a8u\u0015\t)D%\u0001\u0003vi&d\u0017BA\u001c3\u0005U\u0019uN\\2veJ,g\u000e^*lSBd\u0015n\u001d;TKR\u0004\"aK\u001d\n\u0005iz!a\u0003*v]:Lgn\u001a+fgR\fQB];o]&tw\rV3tiN\u0004\u0013\u0001\u0004;fgR\u001cF/\u0019:uS:<G#\u0002 B\u001dB\u0013\u0006CA\u000b@\u0013\t\u0001eC\u0001\u0003V]&$\b\"\u0002\"\u0007\u0001\u0004\u0019\u0015!C:vSR,g*Y7f!\t!5J\u0004\u0002F\u0013B\u0011aIF\u0007\u0002\u000f*\u0011\u0001jG\u0001\u0007yI|w\u000e\u001e \n\u0005)3\u0012A\u0002)sK\u0012,g-\u0003\u0002M\u001b\n11\u000b\u001e:j]\u001eT!A\u0013\f\t\u000b=3\u0001\u0019A\"\u0002\u000fM,\u0018\u000e^3JI\")\u0011K\u0002a\u0001\u0007\u0006AA/Z:u\u001d\u0006lW\rC\u0003T\r\u0001\u0007A$A\u0005uS6,7\u000b^1na\u0006aA/Z:u\r&t\u0017n\u001d5fIR!aHV,Y\u0011\u0015\u0011u\u00011\u0001D\u0011\u0015yu\u00011\u0001D\u0011\u0015\tv\u00011\u0001D\u0003=!W\r^3diNcwn\u001e9pW\u0016\u001cHCA.h!\ra\u0016\r\u001a\b\u0003;~s!A\u00120\n\u0003]I!\u0001\u0019\f\u0002\u000fA\f7m[1hK&\u0011!m\u0019\u0002\u000b\u0013:$W\r_3e\'\u0016\f(B\u00011\u0017!\tYS-\u0003\u0002g\u001f\tA1\u000b\\8xa>\\W\rC\u0003i\u0011\u0001\u0007A$\u0001\tdkJ\u0014XM\u001c;US6,7\u000b^1na\u0006\u00012\u000b\\8xa>\\W\rR3uK\u000e$xN\u001d\t\u0003W)\u0019\"A\u0003\u000b\u0015\u0003)\f1\u0004\n7fgNLg.\u001b;%OJ,\u0017\r^3sI\u0011,g-Y;mi\u0012\nT#A8+\u0005q\u00018&A9\u0011\u0005I<X\"A:\u000b\u0005Q,\u0018!C;oG\",7m[3e\u0015\t1h#\u0001\u0006b]:|G/\u0019;j_:L!\u0001_:\u0003#Ut7\r[3dW\u0016$g+\u0019:jC:\u001cW-A\u000e%Y\u0016\u001c8/\u001b8ji\u0012:\'/Z1uKJ$C-\u001a4bk2$HEM\u000b\u0002w*\u0012\u0001\u0005\u001d
    #9 = Utf8               java/lang/invoke/MethodHandles$Lookup
   #10 = Class              #9            // java/lang/invoke/MethodHandles$Lookup
   #11 = Utf8               java/lang/invoke/MethodHandles
   #12 = Class              #11           // java/lang/invoke/MethodHandles
   #13 = Utf8               Lookup
   #14 = Utf8               org/scalactic/Requirements$RequirementsHelper
   #15 = Class              #14           // org/scalactic/Requirements$RequirementsHelper
   #16 = Utf8               org/scalactic/Requirements
   #17 = Class              #16           // org/scalactic/Requirements
   #18 = Utf8               RequirementsHelper
   #19 = Utf8               scala/collection/JavaConverters$AsScala
   #20 = Class              #19           // scala/collection/JavaConverters$AsScala
   #21 = Utf8               scala/collection/JavaConverters
   #22 = Class              #21           // scala/collection/JavaConverters
   #23 = Utf8               AsScala
   #24 = Utf8               scala/math/Ordering$Long$
   #25 = Class              #24           // scala/math/Ordering$Long$
   #26 = Utf8               scala/math/Ordering
   #27 = Class              #26           // scala/math/Ordering
   #28 = Utf8               Long$
   #29 = Utf8               timeout
   #30 = Utf8               J
   #31 = Utf8               out
   #32 = Utf8               Ljava/io/PrintStream;
   #33 = Utf8               runningTests
   #34 = Utf8               Ljava/util/concurrent/ConcurrentSkipListSet;
   #35 = Utf8               Ljava/util/concurrent/ConcurrentSkipListSet<Lorg/scalatest/RunningTest;>;
   #36 = Utf8               $lessinit$greater$default$2
   #37 = Utf8               ()Ljava/io/PrintStream;
   #38 = Utf8               org/scalatest/SlowpokeDetector$
   #39 = Class              #38           // org/scalatest/SlowpokeDetector$
   #40 = Utf8               MODULE$
   #41 = Utf8               Lorg/scalatest/SlowpokeDetector$;
   #42 = NameAndType        #40:#41       // MODULE$:Lorg/scalatest/SlowpokeDetector$;
   #43 = Fieldref           #39.#42       // org/scalatest/SlowpokeDetector$.MODULE$:Lorg/scalatest/SlowpokeDetector$;
   #44 = NameAndType        #36:#37       // $lessinit$greater$default$2:()Ljava/io/PrintStream;
   #45 = Methodref          #39.#44       // org/scalatest/SlowpokeDetector$.$lessinit$greater$default$2:()Ljava/io/PrintStream;
   #46 = Utf8               $lessinit$greater$default$1
   #47 = Utf8               ()J
   #48 = NameAndType        #46:#47       // $lessinit$greater$default$1:()J
   #49 = Methodref          #39.#48       // org/scalatest/SlowpokeDetector$.$lessinit$greater$default$1:()J
   #50 = Utf8               ()Ljava/util/concurrent/ConcurrentSkipListSet;
   #51 = Utf8               ()Ljava/util/concurrent/ConcurrentSkipListSet<Lorg/scalatest/RunningTest;>;
   #52 = NameAndType        #33:#34       // runningTests:Ljava/util/concurrent/ConcurrentSkipListSet;
   #53 = Fieldref           #2.#52        // org/scalatest/SlowpokeDetector.runningTests:Ljava/util/concurrent/ConcurrentSkipListSet;
   #54 = Utf8               this
   #55 = Utf8               Lorg/scalatest/SlowpokeDetector;
   #56 = Utf8               testStarting
   #57 = Utf8               (Ljava/lang/String;Ljava/lang/String;Ljava/lang/String;J)V
   #58 = Utf8               suiteName
   #59 = Utf8               suiteId
   #60 = Utf8               testName
   #61 = Utf8               timeStamp
   #62 = Utf8               org/scalactic/Requirements$
   #63 = Class              #62           // org/scalactic/Requirements$
   #64 = Utf8               Lorg/scalactic/Requirements$;
   #65 = NameAndType        #40:#64       // MODULE$:Lorg/scalactic/Requirements$;
   #66 = Fieldref           #63.#65       // org/scalactic/Requirements$.MODULE$:Lorg/scalactic/Requirements$;
   #67 = Utf8               requirementsHelper
   #68 = Utf8               ()Lorg/scalactic/Requirements$RequirementsHelper;
   #69 = NameAndType        #67:#68       // requirementsHelper:()Lorg/scalactic/Requirements$RequirementsHelper;
   #70 = Methodref          #63.#69       // org/scalactic/Requirements$.requirementsHelper:()Lorg/scalactic/Requirements$RequirementsHelper;
   #71 = Utf8               java/lang/String
   #72 = Class              #71           // java/lang/String
   #73 = String             #58           // suiteName
   #74 = String             #59           // suiteId
   #75 = String             #60           // testName
   #76 = Utf8               [Ljava/lang/Object;
   #77 = Class              #76           // "[Ljava/lang/Object;"
   #78 = Utf8               [Ljava/lang/String;
   #79 = Class              #78           // "[Ljava/lang/String;"
   #80 = Utf8               org/scalactic/Prettifier$
   #81 = Class              #80           // org/scalactic/Prettifier$
   #82 = Utf8               Lorg/scalactic/Prettifier$;
   #83 = NameAndType        #40:#82       // MODULE$:Lorg/scalactic/Prettifier$;
   #84 = Fieldref           #81.#83       // org/scalactic/Prettifier$.MODULE$:Lorg/scalactic/Prettifier$;
   #85 = Utf8               default
   #86 = Utf8               ()Lorg/scalactic/Prettifier;
   #87 = NameAndType        #85:#86       // default:()Lorg/scalactic/Prettifier;
   #88 = Methodref          #81.#87       // org/scalactic/Prettifier$.default:()Lorg/scalactic/Prettifier;
   #89 = Utf8               org/scalactic/source/Position
   #90 = Class              #89           // org/scalactic/source/Position
   #91 = String             #5            // SlowpokeDetector.scala
   #92 = Utf8               Please set the environment variable SCALACTIC_FILL_FILE_PATHNAMES to yes at compile time to enable this feature.
   #93 = String             #92           // Please set the environment variable SCALACTIC_FILL_FILE_PATHNAMES to yes at compile time to enable this feature.
   #94 = Utf8               <init>
   #95 = Utf8               (Ljava/lang/String;Ljava/lang/String;I)V
   #96 = NameAndType        #94:#95       // "<init>":(Ljava/lang/String;Ljava/lang/String;I)V
   #97 = Methodref          #90.#96       // org/scalactic/source/Position."<init>":(Ljava/lang/String;Ljava/lang/String;I)V
   #98 = Utf8               macroRequireNonNull
   #99 = Utf8               ([Ljava/lang/String;[Ljava/lang/Object;Lorg/scalactic/Prettifier;Lorg/scalactic/source/Position;)V
  #100 = NameAndType        #98:#99       // macroRequireNonNull:([Ljava/lang/String;[Ljava/lang/Object;Lorg/scalactic/Prettifier;Lorg/scalactic/source/Position;)V
  #101 = Methodref          #15.#100      // org/scalactic/Requirements$RequirementsHelper.macroRequireNonNull:([Ljava/lang/String;[Ljava/lang/Object;Lorg/scalactic/Prettifier;Lorg/scalactic/source/Position;)V
  #102 = Utf8               org/scalactic/Bool$
  #103 = Class              #102          // org/scalactic/Bool$
  #104 = Utf8               Lorg/scalactic/Bool$;
  #105 = NameAndType        #40:#104      // MODULE$:Lorg/scalactic/Bool$;
  #106 = Fieldref           #103.#105     // org/scalactic/Bool$.MODULE$:Lorg/scalactic/Bool$;
  #107 = Utf8               scala/runtime/BoxesRunTime
  #108 = Class              #107          // scala/runtime/BoxesRunTime
  #109 = Utf8               boxToLong
  #110 = Utf8               (J)Ljava/lang/Long;
  #111 = NameAndType        #109:#110     // boxToLong:(J)Ljava/lang/Long;
  #112 = Methodref          #108.#111     // scala/runtime/BoxesRunTime.boxToLong:(J)Ljava/lang/Long;
  #113 = Utf8               >=
  #114 = String             #113          // >=
  #115 = Utf8               boxToInteger
  #116 = Utf8               (I)Ljava/lang/Integer;
  #117 = NameAndType        #115:#116     // boxToInteger:(I)Ljava/lang/Integer;
  #118 = Methodref          #108.#117     // scala/runtime/BoxesRunTime.boxToInteger:(I)Ljava/lang/Integer;
  #119 = Utf8               binaryMacroBool
  #120 = Utf8               (Ljava/lang/Object;Ljava/lang/String;Ljava/lang/Object;ZLorg/scalactic/Prettifier;)Lorg/scalactic/Bool;
  #121 = NameAndType        #119:#120     // binaryMacroBool:(Ljava/lang/Object;Ljava/lang/String;Ljava/lang/Object;ZLorg/scalactic/Prettifier;)Lorg/scalactic/Bool;
  #122 = Methodref          #103.#121     // org/scalactic/Bool$.binaryMacroBool:(Ljava/lang/Object;Ljava/lang/String;Ljava/lang/Object;ZLorg/scalactic/Prettifier;)Lorg/scalactic/Bool;
  #123 = Utf8               timeStamp must be >= 0
  #124 = String             #123          // timeStamp must be >= 0
  #125 = Utf8               macroRequire
  #126 = Utf8               (Lorg/scalactic/Bool;Ljava/lang/Object;)V
  #127 = NameAndType        #125:#126     // macroRequire:(Lorg/scalactic/Bool;Ljava/lang/Object;)V
  #128 = Methodref          #15.#127      // org/scalactic/Requirements$RequirementsHelper.macroRequire:(Lorg/scalactic/Bool;Ljava/lang/Object;)V
  #129 = NameAndType        #33:#50       // runningTests:()Ljava/util/concurrent/ConcurrentSkipListSet;
  #130 = Methodref          #2.#129       // org/scalatest/SlowpokeDetector.runningTests:()Ljava/util/concurrent/ConcurrentSkipListSet;
  #131 = Utf8               org/scalatest/RunningTest
  #132 = Class              #131          // org/scalatest/RunningTest
  #133 = NameAndType        #94:#57       // "<init>":(Ljava/lang/String;Ljava/lang/String;Ljava/lang/String;J)V
  #134 = Methodref          #132.#133     // org/scalatest/RunningTest."<init>":(Ljava/lang/String;Ljava/lang/String;Ljava/lang/String;J)V
  #135 = Utf8               java/util/concurrent/ConcurrentSkipListSet
  #136 = Class              #135          // java/util/concurrent/ConcurrentSkipListSet
  #137 = Utf8               add
  #138 = Utf8               (Ljava/lang/Object;)Z
  #139 = NameAndType        #137:#138     // add:(Ljava/lang/Object;)Z
  #140 = Methodref          #136.#139     // java/util/concurrent/ConcurrentSkipListSet.add:(Ljava/lang/Object;)Z
  #141 = Utf8               $org_scalatest_assert_macro_left
  #142 = Utf8               $org_scalatest_assert_macro_right
  #143 = Utf8               I
  #144 = Utf8               $org_scalatest_assert_macro_expr
  #145 = Utf8               Lorg/scalactic/Bool;
  #146 = Utf8               Ljava/lang/String;
  #147 = Utf8               java/lang/Long
  #148 = Class              #147          // java/lang/Long
  #149 = Utf8               java/lang/Integer
  #150 = Class              #149          // java/lang/Integer
  #151 = Utf8               testFinished
  #152 = Utf8               (Ljava/lang/String;Ljava/lang/String;Ljava/lang/String;)V
  #153 = Utf8               remove
  #154 = NameAndType        #153:#138     // remove:(Ljava/lang/Object;)Z
  #155 = Methodref          #136.#154     // java/util/concurrent/ConcurrentSkipListSet.remove:(Ljava/lang/Object;)Z
  #156 = Utf8               org/scalatest/Resources$
  #157 = Class              #156          // org/scalatest/Resources$
  #158 = Utf8               Lorg/scalatest/Resources$;
  #159 = NameAndType        #40:#158      // MODULE$:Lorg/scalatest/Resources$;
  #160 = Fieldref           #157.#159     // org/scalatest/Resources$.MODULE$:Lorg/scalatest/Resources$;
  #161 = Utf8               slowpokeDetectorEventNotFound
  #162 = Utf8               (Ljava/lang/Object;Ljava/lang/Object;Ljava/lang/Object;)Ljava/lang/String;
  #163 = NameAndType        #161:#162     // slowpokeDetectorEventNotFound:(Ljava/lang/Object;Ljava/lang/Object;Ljava/lang/Object;)Ljava/lang/String;
  #164 = Methodref          #157.#163     // org/scalatest/Resources$.slowpokeDetectorEventNotFound:(Ljava/lang/Object;Ljava/lang/Object;Ljava/lang/Object;)Ljava/lang/String;
  #165 = NameAndType        #31:#32       // out:Ljava/io/PrintStream;
  #166 = Fieldref           #2.#165       // org/scalatest/SlowpokeDetector.out:Ljava/io/PrintStream;
  #167 = Utf8               java/io/PrintStream
  #168 = Class              #167          // java/io/PrintStream
  #169 = Utf8               println
  #170 = Utf8               (Ljava/lang/String;)V
  #171 = NameAndType        #169:#170     // println:(Ljava/lang/String;)V
  #172 = Methodref          #168.#171     // java/io/PrintStream.println:(Ljava/lang/String;)V
  #173 = Utf8               stringToPrint
  #174 = Utf8               wasRemoved
  #175 = Utf8               Z
  #176 = Utf8               detectSlowpokes
  #177 = Utf8               (J)Lscala/collection/immutable/IndexedSeq;
  #178 = Utf8               (J)Lscala/collection/immutable/IndexedSeq<Lorg/scalatest/Slowpoke;>;
  #179 = Utf8               currentTimeStamp
  #180 = Utf8               scala/collection/JavaConverters$
  #181 = Class              #180          // scala/collection/JavaConverters$
  #182 = Utf8               Lscala/collection/JavaConverters$;
  #183 = NameAndType        #40:#182      // MODULE$:Lscala/collection/JavaConverters$;
  #184 = Fieldref           #181.#183     // scala/collection/JavaConverters$.MODULE$:Lscala/collection/JavaConverters$;
  #185 = Utf8               iterator
  #186 = Utf8               ()Ljava/util/Iterator;
  #187 = NameAndType        #185:#186     // iterator:()Ljava/util/Iterator;
  #188 = Methodref          #136.#187     // java/util/concurrent/ConcurrentSkipListSet.iterator:()Ljava/util/Iterator;
  #189 = Utf8               asScalaIteratorConverter
  #190 = Utf8               (Ljava/util/Iterator;)Lscala/collection/JavaConverters$AsScala;
  #191 = NameAndType        #189:#190     // asScalaIteratorConverter:(Ljava/util/Iterator;)Lscala/collection/JavaConverters$AsScala;
  #192 = Methodref          #181.#191     // scala/collection/JavaConverters$.asScalaIteratorConverter:(Ljava/util/Iterator;)Lscala/collection/JavaConverters$AsScala;
  #193 = Utf8               asScala
  #194 = Utf8               ()Ljava/lang/Object;
  #195 = NameAndType        #193:#194     // asScala:()Ljava/lang/Object;
  #196 = Methodref          #20.#195      // scala/collection/JavaConverters$AsScala.asScala:()Ljava/lang/Object;
  #197 = Utf8               scala/collection/IterableOnceOps
  #198 = Class              #197          // scala/collection/IterableOnceOps
  #199 = Utf8               toVector
  #200 = Utf8               ()Lscala/collection/immutable/Vector;
  #201 = NameAndType        #199:#200     // toVector:()Lscala/collection/immutable/Vector;
  #202 = InterfaceMethodref #198.#201     // scala/collection/IterableOnceOps.toVector:()Lscala/collection/immutable/Vector;
  #203 = Utf8               (Ljava/lang/Object;)Ljava/lang/Object;
  #204 = MethodType         #203          //  (Ljava/lang/Object;)Ljava/lang/Object;
  #205 = Utf8               $anonfun$detectSlowpokes$1$adapted
  #206 = Utf8               (Lorg/scalatest/SlowpokeDetector;JLorg/scalatest/RunningTest;)Ljava/lang/Object;
  #207 = NameAndType        #205:#206     // $anonfun$detectSlowpokes$1$adapted:(Lorg/scalatest/SlowpokeDetector;JLorg/scalatest/RunningTest;)Ljava/lang/Object;
  #208 = Methodref          #2.#207       // org/scalatest/SlowpokeDetector.$anonfun$detectSlowpokes$1$adapted:(Lorg/scalatest/SlowpokeDetector;JLorg/scalatest/RunningTest;)Ljava/lang/Object;
  #209 = MethodHandle       6:#208        // REF_invokeStatic org/scalatest/SlowpokeDetector.$anonfun$detectSlowpokes$1$adapted:(Lorg/scalatest/SlowpokeDetector;JLorg/scalatest/RunningTest;)Ljava/lang/Object;
  #210 = Utf8               (Lorg/scalatest/RunningTest;)Ljava/lang/Object;
  #211 = MethodType         #210          //  (Lorg/scalatest/RunningTest;)Ljava/lang/Object;
  #212 = Integer            5
  #213 = Integer            1
  #214 = Utf8               java/lang/invoke/LambdaMetafactory
  #215 = Class              #214          // java/lang/invoke/LambdaMetafactory
  #216 = Utf8               altMetafactory
  #217 = Utf8               (Ljava/lang/invoke/MethodHandles$Lookup;Ljava/lang/String;Ljava/lang/invoke/MethodType;[Ljava/lang/Object;)Ljava/lang/invoke/CallSite;
  #218 = NameAndType        #216:#217     // altMetafactory:(Ljava/lang/invoke/MethodHandles$Lookup;Ljava/lang/String;Ljava/lang/invoke/MethodType;[Ljava/lang/Object;)Ljava/lang/invoke/CallSite;
  #219 = Methodref          #215.#218     // java/lang/invoke/LambdaMetafactory.altMetafactory:(Ljava/lang/invoke/MethodHandles$Lookup;Ljava/lang/String;Ljava/lang/invoke/MethodType;[Ljava/lang/Object;)Ljava/lang/invoke/CallSite;
  #220 = MethodHandle       6:#219        // REF_invokeStatic java/lang/invoke/LambdaMetafactory.altMetafactory:(Ljava/lang/invoke/MethodHandles$Lookup;Ljava/lang/String;Ljava/lang/invoke/MethodType;[Ljava/lang/Object;)Ljava/lang/invoke/CallSite;
  #221 = Utf8               apply
  #222 = Utf8               (Lorg/scalatest/SlowpokeDetector;J)Lscala/Function1;
  #223 = NameAndType        #221:#222     // apply:(Lorg/scalatest/SlowpokeDetector;J)Lscala/Function1;
  #224 = InvokeDynamic      #0:#223       // #0:apply:(Lorg/scalatest/SlowpokeDetector;J)Lscala/Function1;
  #225 = Utf8               scala/collection/immutable/Vector
  #226 = Class              #225          // scala/collection/immutable/Vector
  #227 = Utf8               filter
  #228 = Utf8               (Lscala/Function1;)Ljava/lang/Object;
  #229 = NameAndType        #227:#228     // filter:(Lscala/Function1;)Ljava/lang/Object;
  #230 = Methodref          #226.#229     // scala/collection/immutable/Vector.filter:(Lscala/Function1;)Ljava/lang/Object;
  #231 = Utf8               $anonfun$detectSlowpokes$2$adapted
  #232 = NameAndType        #231:#210     // $anonfun$detectSlowpokes$2$adapted:(Lorg/scalatest/RunningTest;)Ljava/lang/Object;
  #233 = Methodref          #2.#232       // org/scalatest/SlowpokeDetector.$anonfun$detectSlowpokes$2$adapted:(Lorg/scalatest/RunningTest;)Ljava/lang/Object;
  #234 = MethodHandle       6:#233        // REF_invokeStatic org/scalatest/SlowpokeDetector.$anonfun$detectSlowpokes$2$adapted:(Lorg/scalatest/RunningTest;)Ljava/lang/Object;
  #235 = Utf8               ()Lscala/Function1;
  #236 = NameAndType        #221:#235     // apply:()Lscala/Function1;
  #237 = InvokeDynamic      #1:#236       // #1:apply:()Lscala/Function1;
  #238 = Utf8               Lscala/math/Ordering$Long$;
  #239 = NameAndType        #40:#238      // MODULE$:Lscala/math/Ordering$Long$;
  #240 = Fieldref           #25.#239      // scala/math/Ordering$Long$.MODULE$:Lscala/math/Ordering$Long$;
  #241 = Utf8               sortBy
  #242 = Utf8               (Lscala/Function1;Lscala/math/Ordering;)Ljava/lang/Object;
  #243 = NameAndType        #241:#242     // sortBy:(Lscala/Function1;Lscala/math/Ordering;)Ljava/lang/Object;
  #244 = Methodref          #226.#243     // scala/collection/immutable/Vector.sortBy:(Lscala/Function1;Lscala/math/Ordering;)Ljava/lang/Object;
  #245 = Utf8               scala/collection/StrictOptimizedIterableOps
  #246 = Class              #245          // scala/collection/StrictOptimizedIterableOps
  #247 = Utf8               $anonfun$detectSlowpokes$3
  #248 = Utf8               (JLorg/scalatest/RunningTest;)Lorg/scalatest/Slowpoke;
  #249 = NameAndType        #247:#248     // $anonfun$detectSlowpokes$3:(JLorg/scalatest/RunningTest;)Lorg/scalatest/Slowpoke;
  #250 = Methodref          #2.#249       // org/scalatest/SlowpokeDetector.$anonfun$detectSlowpokes$3:(JLorg/scalatest/RunningTest;)Lorg/scalatest/Slowpoke;
  #251 = MethodHandle       6:#250        // REF_invokeStatic org/scalatest/SlowpokeDetector.$anonfun$detectSlowpokes$3:(JLorg/scalatest/RunningTest;)Lorg/scalatest/Slowpoke;
  #252 = Utf8               (Lorg/scalatest/RunningTest;)Lorg/scalatest/Slowpoke;
  #253 = MethodType         #252          //  (Lorg/scalatest/RunningTest;)Lorg/scalatest/Slowpoke;
  #254 = Utf8               (J)Lscala/Function1;
  #255 = NameAndType        #221:#254     // apply:(J)Lscala/Function1;
  #256 = InvokeDynamic      #2:#255       // #2:apply:(J)Lscala/Function1;
  #257 = Utf8               map
  #258 = NameAndType        #257:#228     // map:(Lscala/Function1;)Ljava/lang/Object;
  #259 = InterfaceMethodref #246.#258     // scala/collection/StrictOptimizedIterableOps.map:(Lscala/Function1;)Ljava/lang/Object;
  #260 = Utf8               scala/collection/immutable/IndexedSeq
  #261 = Class              #260          // scala/collection/immutable/IndexedSeq
  #262 = Utf8               rts
  #263 = Utf8               Lscala/collection/immutable/Vector;
  #264 = Utf8               slowTests
  #265 = Utf8               $anonfun$detectSlowpokes$1
  #266 = Utf8               (Lorg/scalatest/SlowpokeDetector;JLorg/scalatest/RunningTest;)Z
  #267 = Utf8               $this
  #268 = Utf8               currentTimeStamp$1
  #269 = Utf8               x$1
  #270 = Utf8               startTimeStamp
  #271 = NameAndType        #270:#47      // startTimeStamp:()J
  #272 = Methodref          #132.#271     // org/scalatest/RunningTest.startTimeStamp:()J
  #273 = NameAndType        #29:#30       // timeout:J
  #274 = Fieldref           #2.#273       // org/scalatest/SlowpokeDetector.timeout:J
  #275 = Utf8               Lorg/scalatest/RunningTest;
  #276 = Utf8               $anonfun$detectSlowpokes$2
  #277 = Utf8               (Lorg/scalatest/RunningTest;)J
  #278 = Utf8               x$2
  #279 = Utf8               x$3
  #280 = Utf8               toSlowpoke
  #281 = Utf8               (J)Lorg/scalatest/Slowpoke;
  #282 = NameAndType        #280:#281     // toSlowpoke:(J)Lorg/scalatest/Slowpoke;
  #283 = Methodref          #132.#282     // org/scalatest/RunningTest.toSlowpoke:(J)Lorg/scalatest/Slowpoke;
  #284 = Utf8               (JLjava/io/PrintStream;)V
  #285 = Utf8               ()V
  #286 = NameAndType        #94:#285      // "<init>":()V
  #287 = Methodref          #4.#286       // java/lang/Object."<init>":()V
  #288 = Methodref          #136.#286     // java/util/concurrent/ConcurrentSkipListSet."<init>":()V
  #289 = NameAndType        #265:#266     // $anonfun$detectSlowpokes$1:(Lorg/scalatest/SlowpokeDetector;JLorg/scalatest/RunningTest;)Z
  #290 = Methodref          #2.#289       // org/scalatest/SlowpokeDetector.$anonfun$detectSlowpokes$1:(Lorg/scalatest/SlowpokeDetector;JLorg/scalatest/RunningTest;)Z
  #291 = Utf8               boxToBoolean
  #292 = Utf8               (Z)Ljava/lang/Boolean;
  #293 = NameAndType        #291:#292     // boxToBoolean:(Z)Ljava/lang/Boolean;
  #294 = Methodref          #108.#293     // scala/runtime/BoxesRunTime.boxToBoolean:(Z)Ljava/lang/Boolean;
  #295 = NameAndType        #276:#277     // $anonfun$detectSlowpokes$2:(Lorg/scalatest/RunningTest;)J
  #296 = Methodref          #2.#295       // org/scalatest/SlowpokeDetector.$anonfun$detectSlowpokes$2:(Lorg/scalatest/RunningTest;)J
  #297 = Utf8               $deserializeLambda$
  #298 = Utf8               (Ljava/lang/invoke/SerializedLambda;)Ljava/lang/Object;
  #299 = Utf8               scala/runtime/LambdaDeserialize
  #300 = Class              #299          // scala/runtime/LambdaDeserialize
  #301 = Utf8               bootstrap
  #302 = Utf8               (Ljava/lang/invoke/MethodHandles$Lookup;Ljava/lang/String;Ljava/lang/invoke/MethodType;[Ljava/lang/invoke/MethodHandle;)Ljava/lang/invoke/CallSite;
  #303 = NameAndType        #301:#302     // bootstrap:(Ljava/lang/invoke/MethodHandles$Lookup;Ljava/lang/String;Ljava/lang/invoke/MethodType;[Ljava/lang/invoke/MethodHandle;)Ljava/lang/invoke/CallSite;
  #304 = Methodref          #300.#303     // scala/runtime/LambdaDeserialize.bootstrap:(Ljava/lang/invoke/MethodHandles$Lookup;Ljava/lang/String;Ljava/lang/invoke/MethodType;[Ljava/lang/invoke/MethodHandle;)Ljava/lang/invoke/CallSite;
  #305 = MethodHandle       6:#304        // REF_invokeStatic scala/runtime/LambdaDeserialize.bootstrap:(Ljava/lang/invoke/MethodHandles$Lookup;Ljava/lang/String;Ljava/lang/invoke/MethodType;[Ljava/lang/invoke/MethodHandle;)Ljava/lang/invoke/CallSite;
  #306 = Utf8               lambdaDeserialize
  #307 = NameAndType        #306:#298     // lambdaDeserialize:(Ljava/lang/invoke/SerializedLambda;)Ljava/lang/Object;
  #308 = InvokeDynamic      #3:#307       // #3:lambdaDeserialize:(Ljava/lang/invoke/SerializedLambda;)Ljava/lang/Object;
  #309 = Utf8               Signature
  #310 = Utf8               Code
  #311 = Utf8               LineNumberTable
  #312 = Utf8               LocalVariableTable
  #313 = Utf8               StackMapTable
  #314 = Utf8               MethodParameters
  #315 = Utf8               InnerClasses
  #316 = Utf8               SourceFile
  #317 = Utf8               RuntimeVisibleAnnotations
  #318 = Utf8               BootstrapMethods
  #319 = Utf8               ScalaInlineInfo
  #320 = Utf8               ScalaSig
{
  private final long timeout;
    descriptor: J
    flags: (0x0012) ACC_PRIVATE, ACC_FINAL

  private final java.io.PrintStream out;
    descriptor: Ljava/io/PrintStream;
    flags: (0x0012) ACC_PRIVATE, ACC_FINAL

  private final java.util.concurrent.ConcurrentSkipListSet<org.scalatest.RunningTest> runningTests;
    descriptor: Ljava/util/concurrent/ConcurrentSkipListSet;
    flags: (0x0012) ACC_PRIVATE, ACC_FINAL
    Signature: #35                          // Ljava/util/concurrent/ConcurrentSkipListSet<Lorg/scalatest/RunningTest;>;

  public static java.io.PrintStream $lessinit$greater$default$2();
    descriptor: ()Ljava/io/PrintStream;
    flags: (0x0009) ACC_PUBLIC, ACC_STATIC
    Code:
      stack=1, locals=0, args_size=0
         0: getstatic     #43                 // Field org/scalatest/SlowpokeDetector$.MODULE$:Lorg/scalatest/SlowpokeDetector$;
         3: invokevirtual #45                 // Method org/scalatest/SlowpokeDetector$.$lessinit$greater$default$2:()Ljava/io/PrintStream;
         6: areturn

  public static long $lessinit$greater$default$1();
    descriptor: ()J
    flags: (0x0009) ACC_PUBLIC, ACC_STATIC
    Code:
      stack=2, locals=0, args_size=0
         0: getstatic     #43                 // Field org/scalatest/SlowpokeDetector$.MODULE$:Lorg/scalatest/SlowpokeDetector$;
         3: invokevirtual #49                 // Method org/scalatest/SlowpokeDetector$.$lessinit$greater$default$1:()J
         6: lreturn

  private final java.util.concurrent.ConcurrentSkipListSet<org.scalatest.RunningTest> runningTests();
    descriptor: ()Ljava/util/concurrent/ConcurrentSkipListSet;
    flags: (0x0012) ACC_PRIVATE, ACC_FINAL
    Code:
      stack=1, locals=1, args_size=1
         0: aload_0
         1: getfield      #53                 // Field runningTests:Ljava/util/concurrent/ConcurrentSkipListSet;
         4: areturn
      LineNumberTable:
        line 27: 0
      LocalVariableTable:
        Start  Length  Slot  Name   Signature
            0       5     0  this   Lorg/scalatest/SlowpokeDetector;
    Signature: #51                          // ()Ljava/util/concurrent/ConcurrentSkipListSet<Lorg/scalatest/RunningTest;>;

  public void testStarting(java.lang.String, java.lang.String, java.lang.String, long);
    descriptor: (Ljava/lang/String;Ljava/lang/String;Ljava/lang/String;J)V
    flags: (0x0001) ACC_PUBLIC
    Code:
      stack=9, locals=10, args_size=5
         0: getstatic     #66                 // Field org/scalactic/Requirements$.MODULE$:Lorg/scalactic/Requirements$;
         3: invokevirtual #70                 // Method org/scalactic/Requirements$.requirementsHelper:()Lorg/scalactic/Requirements$RequirementsHelper;
         6: iconst_3
         7: anewarray     #72                 // class java/lang/String
        10: dup
        11: iconst_0
        12: ldc           #73                 // String suiteName
        14: aastore
        15: dup
        16: iconst_1
        17: ldc           #74                 // String suiteId
        19: aastore
        20: dup
        21: iconst_2
        22: ldc           #75                 // String testName
        24: aastore
        25: checkcast     #77                 // class "[Ljava/lang/Object;"
        28: checkcast     #79                 // class "[Ljava/lang/String;"
        31: iconst_3
        32: anewarray     #4                  // class java/lang/Object
        35: dup
        36: iconst_0
        37: aload_1
        38: aastore
        39: dup
        40: iconst_1
        41: aload_2
        42: aastore
        43: dup
        44: iconst_2
        45: aload_3
        46: aastore
        47: checkcast     #77                 // class "[Ljava/lang/Object;"
        50: getstatic     #84                 // Field org/scalactic/Prettifier$.MODULE$:Lorg/scalactic/Prettifier$;
        53: invokevirtual #88                 // Method org/scalactic/Prettifier$.default:()Lorg/scalactic/Prettifier;
        56: new           #90                 // class org/scalactic/source/Position
        59: dup
        60: ldc           #91                 // String SlowpokeDetector.scala
        62: ldc           #93                 // String Please set the environment variable SCALACTIC_FILL_FILE_PATHNAMES to yes at compile time to enable this feature.
        64: bipush        32
        66: invokespecial #97                 // Method org/scalactic/source/Position."<init>":(Ljava/lang/String;Ljava/lang/String;I)V
        69: invokevirtual #101                // Method org/scalactic/Requirements$RequirementsHelper.macroRequireNonNull:([Ljava/lang/String;[Ljava/lang/Object;Lorg/scalactic/Prettifier;Lorg/scalactic/source/Position;)V
        72: lload         4
        74: lstore        7
        76: iconst_0
        77: istore        9
        79: getstatic     #106                // Field org/scalactic/Bool$.MODULE$:Lorg/scalactic/Bool$;
        82: lload         7
        84: invokestatic  #112                // Method scala/runtime/BoxesRunTime.boxToLong:(J)Ljava/lang/Long;
        87: ldc           #114                // String >=
        89: iload         9
        91: invokestatic  #118                // Method scala/runtime/BoxesRunTime.boxToInteger:(I)Ljava/lang/Integer;
        94: lload         7
        96: iload         9
        98: i2l
        99: lcmp
       100: iflt          107
       103: iconst_1
       104: goto          108
       107: iconst_0
       108: getstatic     #84                 // Field org/scalactic/Prettifier$.MODULE$:Lorg/scalactic/Prettifier$;
       111: invokevirtual #88                 // Method org/scalactic/Prettifier$.default:()Lorg/scalactic/Prettifier;
       114: invokevirtual #122                // Method org/scalactic/Bool$.binaryMacroBool:(Ljava/lang/Object;Ljava/lang/String;Ljava/lang/Object;ZLorg/scalactic/Prettifier;)Lorg/scalactic/Bool;
       117: astore        6
       119: getstatic     #66                 // Field org/scalactic/Requirements$.MODULE$:Lorg/scalactic/Requirements$;
       122: invokevirtual #70                 // Method org/scalactic/Requirements$.requirementsHelper:()Lorg/scalactic/Requirements$RequirementsHelper;
       125: aload         6
       127: ldc           #124                // String timeStamp must be >= 0
       129: invokevirtual #128                // Method org/scalactic/Requirements$RequirementsHelper.macroRequire:(Lorg/scalactic/Bool;Ljava/lang/Object;)V
       132: aload_0
       133: invokespecial #130                // Method runningTests:()Ljava/util/concurrent/ConcurrentSkipListSet;
       136: new           #132                // class org/scalatest/RunningTest
       139: dup
       140: aload_1
       141: aload_2
       142: aload_3
       143: lload         4
       145: invokespecial #134                // Method org/scalatest/RunningTest."<init>":(Ljava/lang/String;Ljava/lang/String;Ljava/lang/String;J)V
       148: invokevirtual #140                // Method java/util/concurrent/ConcurrentSkipListSet.add:(Ljava/lang/Object;)Z
       151: pop
       152: return
      StackMapTable: number_of_entries = 2
        frame_type = 255 /* full_frame */
          offset_delta = 107
          locals = [ class org/scalatest/SlowpokeDetector, class java/lang/String, class java/lang/String, class java/lang/String, long, top, long, int ]
          stack = [ class org/scalactic/Bool$, class java/lang/Long, class java/lang/String, class java/lang/Integer ]
        frame_type = 255 /* full_frame */
          offset_delta = 0
          locals = [ class org/scalatest/SlowpokeDetector, class java/lang/String, class java/lang/String, class java/lang/String, long, top, long, int ]
          stack = [ class org/scalactic/Bool$, class java/lang/Long, class java/lang/String, class java/lang/Integer, int ]
      LineNumberTable:
        line 32: 0
        line 33: 72
        line 34: 132
        line 35: 136
        line 36: 140
        line 37: 141
        line 38: 142
        line 39: 143
        line 34: 152
      LocalVariableTable:
        Start  Length  Slot  Name   Signature
           76      41     7 $org_scalatest_assert_macro_left   J
           79      38     9 $org_scalatest_assert_macro_right   I
          119      13     6 $org_scalatest_assert_macro_expr   Lorg/scalactic/Bool;
            0     153     0  this   Lorg/scalatest/SlowpokeDetector;
            0     153     1 suiteName   Ljava/lang/String;
            0     153     2 suiteId   Ljava/lang/String;
            0     153     3 testName   Ljava/lang/String;
            0     153     4 timeStamp   J
    MethodParameters:
      Name                           Flags
      suiteName                      final
      suiteId                        final
      testName                       final
      timeStamp                      final

  public void testFinished(java.lang.String, java.lang.String, java.lang.String);
    descriptor: (Ljava/lang/String;Ljava/lang/String;Ljava/lang/String;)V
    flags: (0x0001) ACC_PUBLIC
    Code:
      stack=9, locals=6, args_size=4
         0: getstatic     #66                 // Field org/scalactic/Requirements$.MODULE$:Lorg/scalactic/Requirements$;
         3: invokevirtual #70                 // Method org/scalactic/Requirements$.requirementsHelper:()Lorg/scalactic/Requirements$RequirementsHelper;
         6: iconst_3
         7: anewarray     #72                 // class java/lang/String
        10: dup
        11: iconst_0
        12: ldc           #73                 // String suiteName
        14: aastore
        15: dup
        16: iconst_1
        17: ldc           #74                 // String suiteId
        19: aastore
        20: dup
        21: iconst_2
        22: ldc           #75                 // String testName
        24: aastore
        25: checkcast     #77                 // class "[Ljava/lang/Object;"
        28: checkcast     #79                 // class "[Ljava/lang/String;"
        31: iconst_3
        32: anewarray     #4                  // class java/lang/Object
        35: dup
        36: iconst_0
        37: aload_1
        38: aastore
        39: dup
        40: iconst_1
        41: aload_2
        42: aastore
        43: dup
        44: iconst_2
        45: aload_3
        46: aastore
        47: checkcast     #77                 // class "[Ljava/lang/Object;"
        50: getstatic     #84                 // Field org/scalactic/Prettifier$.MODULE$:Lorg/scalactic/Prettifier$;
        53: invokevirtual #88                 // Method org/scalactic/Prettifier$.default:()Lorg/scalactic/Prettifier;
        56: new           #90                 // class org/scalactic/source/Position
        59: dup
        60: ldc           #91                 // String SlowpokeDetector.scala
        62: ldc           #93                 // String Please set the environment variable SCALACTIC_FILL_FILE_PATHNAMES to yes at compile time to enable this feature.
        64: bipush        44
        66: invokespecial #97                 // Method org/scalactic/source/Position."<init>":(Ljava/lang/String;Ljava/lang/String;I)V
        69: invokevirtual #101                // Method org/scalactic/Requirements$RequirementsHelper.macroRequireNonNull:([Ljava/lang/String;[Ljava/lang/Object;Lorg/scalactic/Prettifier;Lorg/scalactic/source/Position;)V
        72: aload_0
        73: invokespecial #130                // Method runningTests:()Ljava/util/concurrent/ConcurrentSkipListSet;
        76: new           #132                // class org/scalatest/RunningTest
        79: dup
        80: aload_1
        81: aload_2
        82: aload_3
        83: lconst_0
        84: invokespecial #134                // Method org/scalatest/RunningTest."<init>":(Ljava/lang/String;Ljava/lang/String;Ljava/lang/String;J)V
        87: invokevirtual #155                // Method java/util/concurrent/ConcurrentSkipListSet.remove:(Ljava/lang/Object;)Z
        90: istore        4
        92: iload         4
        94: ifne          120
        97: getstatic     #160                // Field org/scalatest/Resources$.MODULE$:Lorg/scalatest/Resources$;
       100: aload_1
       101: aload_2
       102: aload_3
       103: invokevirtual #164                // Method org/scalatest/Resources$.slowpokeDetectorEventNotFound:(Ljava/lang/Object;Ljava/lang/Object;Ljava/lang/Object;)Ljava/lang/String;
       106: astore        5
       108: aload_0
       109: getfield      #166                // Field out:Ljava/io/PrintStream;
       112: aload         5
       114: invokevirtual #172                // Method java/io/PrintStream.println:(Ljava/lang/String;)V
       117: goto          120
       120: return
      StackMapTable: number_of_entries = 1
        frame_type = 252 /* append */
          offset_delta = 120
          locals = [ int ]
      LineNumberTable:
        line 44: 0
        line 46: 72
        line 47: 76
        line 48: 80
        line 49: 81
        line 50: 82
        line 51: 83
        line 54: 92
        line 55: 97
        line 56: 108
        line 54: 120
      LocalVariableTable:
        Start  Length  Slot  Name   Signature
          108       9     5 stringToPrint   Ljava/lang/String;
           92      28     4 wasRemoved   Z
            0     121     0  this   Lorg/scalatest/SlowpokeDetector;
            0     121     1 suiteName   Ljava/lang/String;
            0     121     2 suiteId   Ljava/lang/String;
            0     121     3 testName   Ljava/lang/String;
    MethodParameters:
      Name                           Flags
      suiteName                      final
      suiteId                        final
      testName                       final

  public scala.collection.immutable.IndexedSeq<org.scalatest.Slowpoke> detectSlowpokes(long);
    descriptor: (J)Lscala/collection/immutable/IndexedSeq;
    flags: (0x0001) ACC_PUBLIC
    Code:
      stack=4, locals=5, args_size=2
         0: getstatic     #184                // Field scala/collection/JavaConverters$.MODULE$:Lscala/collection/JavaConverters$;
         3: aload_0
         4: invokespecial #130                // Method runningTests:()Ljava/util/concurrent/ConcurrentSkipListSet;
         7: invokevirtual #188                // Method java/util/concurrent/ConcurrentSkipListSet.iterator:()Ljava/util/Iterator;
        10: invokevirtual #192                // Method scala/collection/JavaConverters$.asScalaIteratorConverter:(Ljava/util/Iterator;)Lscala/collection/JavaConverters$AsScala;
        13: invokevirtual #196                // Method scala/collection/JavaConverters$AsScala.asScala:()Ljava/lang/Object;
        16: checkcast     #198                // class scala/collection/IterableOnceOps
        19: invokeinterface #202,  1          // InterfaceMethod scala/collection/IterableOnceOps.toVector:()Lscala/collection/immutable/Vector;
        24: astore_3
        25: aload_3
        26: aload_0
        27: lload_1
        28: invokedynamic #224,  0            // InvokeDynamic #0:apply:(Lorg/scalatest/SlowpokeDetector;J)Lscala/Function1;
        33: invokevirtual #230                // Method scala/collection/immutable/Vector.filter:(Lscala/Function1;)Ljava/lang/Object;
        36: checkcast     #226                // class scala/collection/immutable/Vector
        39: astore        4
        41: aload         4
        43: invokedynamic #237,  0            // InvokeDynamic #1:apply:()Lscala/Function1;
        48: getstatic     #240                // Field scala/math/Ordering$Long$.MODULE$:Lscala/math/Ordering$Long$;
        51: invokevirtual #244                // Method scala/collection/immutable/Vector.sortBy:(Lscala/Function1;Lscala/math/Ordering;)Ljava/lang/Object;
        54: checkcast     #246                // class scala/collection/StrictOptimizedIterableOps
        57: lload_1
        58: invokedynamic #256,  0            // InvokeDynamic #2:apply:(J)Lscala/Function1;
        63: invokeinterface #259,  2          // InterfaceMethod scala/collection/StrictOptimizedIterableOps.map:(Lscala/Function1;)Ljava/lang/Object;
        68: checkcast     #261                // class scala/collection/immutable/IndexedSeq
        71: areturn
      LineNumberTable:
        line 62: 0
        line 65: 25
        line 66: 41
      LocalVariableTable:
        Start  Length  Slot  Name   Signature
           25      46     3   rts   Lscala/collection/immutable/Vector;
           41      30     4 slowTests   Lscala/collection/immutable/Vector;
            0      72     0  this   Lorg/scalatest/SlowpokeDetector;
            0      72     1 currentTimeStamp   J
    Signature: #178                         // (J)Lscala/collection/immutable/IndexedSeq<Lorg/scalatest/Slowpoke;>;
    MethodParameters:
      Name                           Flags
      currentTimeStamp               final

  public static final boolean $anonfun$detectSlowpokes$1(org.scalatest.SlowpokeDetector, long, org.scalatest.RunningTest);
    descriptor: (Lorg/scalatest/SlowpokeDetector;JLorg/scalatest/RunningTest;)Z
    flags: (0x1019) ACC_PUBLIC, ACC_STATIC, ACC_FINAL, ACC_SYNTHETIC
    Code:
      stack=4, locals=4, args_size=3
         0: lload_1
         1: aload_3
         2: invokevirtual #272                // Method org/scalatest/RunningTest.startTimeStamp:()J
         5: lsub
         6: aload_0
         7: getfield      #274                // Field timeout:J
        10: lcmp
        11: ifle          18
        14: iconst_1
        15: goto          19
        18: iconst_0
        19: ireturn
      StackMapTable: number_of_entries = 2
        frame_type = 18 /* same */
        frame_type = 64 /* same_locals_1_stack_item */
          stack = [ int ]
      LineNumberTable:
        line 65: 0
      LocalVariableTable:
        Start  Length  Slot  Name   Signature
            0      20     0 $this   Lorg/scalatest/SlowpokeDetector;
            0      20     1 currentTimeStamp$1   J
            0      20     3   x$1   Lorg/scalatest/RunningTest;
    MethodParameters:
      Name                           Flags
      $this                          final synthetic
      currentTimeStamp$1             final
      x$1                            final

  public static final long $anonfun$detectSlowpokes$2(org.scalatest.RunningTest);
    descriptor: (Lorg/scalatest/RunningTest;)J
    flags: (0x1019) ACC_PUBLIC, ACC_STATIC, ACC_FINAL, ACC_SYNTHETIC
    Code:
      stack=2, locals=1, args_size=1
         0: aload_0
         1: invokevirtual #272                // Method org/scalatest/RunningTest.startTimeStamp:()J
         4: lreturn
      LineNumberTable:
        line 66: 0
      LocalVariableTable:
        Start  Length  Slot  Name   Signature
            0       5     0   x$2   Lorg/scalatest/RunningTest;
    MethodParameters:
      Name                           Flags
      x$2                            final

  public static final org.scalatest.Slowpoke $anonfun$detectSlowpokes$3(long, org.scalatest.RunningTest);
    descriptor: (JLorg/scalatest/RunningTest;)Lorg/scalatest/Slowpoke;
    flags: (0x1019) ACC_PUBLIC, ACC_STATIC, ACC_FINAL, ACC_SYNTHETIC
    Code:
      stack=3, locals=3, args_size=2
         0: aload_2
         1: lload_0
         2: invokevirtual #283                // Method org/scalatest/RunningTest.toSlowpoke:(J)Lorg/scalatest/Slowpoke;
         5: areturn
      LineNumberTable:
        line 66: 0
      LocalVariableTable:
        Start  Length  Slot  Name   Signature
            0       6     0 currentTimeStamp$1   J
            0       6     2   x$3   Lorg/scalatest/RunningTest;
    MethodParameters:
      Name                           Flags
      currentTimeStamp$1             final
      x$3                            final

  public org.scalatest.SlowpokeDetector(long, java.io.PrintStream);
    descriptor: (JLjava/io/PrintStream;)V
    flags: (0x0001) ACC_PUBLIC
    Code:
      stack=3, locals=4, args_size=3
         0: aload_0
         1: lload_1
         2: putfield      #274                // Field timeout:J
         5: aload_0
         6: aload_3
         7: putfield      #166                // Field out:Ljava/io/PrintStream;
        10: aload_0
        11: invokespecial #287                // Method java/lang/Object."<init>":()V
        14: aload_0
        15: new           #136                // class java/util/concurrent/ConcurrentSkipListSet
        18: dup
        19: invokespecial #288                // Method java/util/concurrent/ConcurrentSkipListSet."<init>":()V
        22: putfield      #53                 // Field runningTests:Ljava/util/concurrent/ConcurrentSkipListSet;
        25: return
      LineNumberTable:
        line 24: 0
        line 68: 10
        line 27: 14
        line 24: 25
      LocalVariableTable:
        Start  Length  Slot  Name   Signature
            0      26     0  this   Lorg/scalatest/SlowpokeDetector;
            0      26     1 timeout   J
            0      26     3   out   Ljava/io/PrintStream;
    MethodParameters:
      Name                           Flags
      timeout                        final
      out                            final

  public static final java.lang.Object $anonfun$detectSlowpokes$1$adapted(org.scalatest.SlowpokeDetector, long, org.scalatest.RunningTest);
    descriptor: (Lorg/scalatest/SlowpokeDetector;JLorg/scalatest/RunningTest;)Ljava/lang/Object;
    flags: (0x1019) ACC_PUBLIC, ACC_STATIC, ACC_FINAL, ACC_SYNTHETIC
    Code:
      stack=4, locals=4, args_size=3
         0: aload_0
         1: lload_1
         2: aload_3
         3: invokestatic  #290                // Method $anonfun$detectSlowpokes$1:(Lorg/scalatest/SlowpokeDetector;JLorg/scalatest/RunningTest;)Z
         6: invokestatic  #294                // Method scala/runtime/BoxesRunTime.boxToBoolean:(Z)Ljava/lang/Boolean;
         9: areturn
      LineNumberTable:
        line 65: 0
      LocalVariableTable:
        Start  Length  Slot  Name   Signature
            0      10     0 $this   Lorg/scalatest/SlowpokeDetector;
            0      10     1 currentTimeStamp$1   J
            0      10     3   x$1   Lorg/scalatest/RunningTest;
    MethodParameters:
      Name                           Flags
      $this                          final
      currentTimeStamp$1             final
      x$1                            final

  public static final java.lang.Object $anonfun$detectSlowpokes$2$adapted(org.scalatest.RunningTest);
    descriptor: (Lorg/scalatest/RunningTest;)Ljava/lang/Object;
    flags: (0x1019) ACC_PUBLIC, ACC_STATIC, ACC_FINAL, ACC_SYNTHETIC
    Code:
      stack=2, locals=1, args_size=1
         0: aload_0
         1: invokestatic  #296                // Method $anonfun$detectSlowpokes$2:(Lorg/scalatest/RunningTest;)J
         4: invokestatic  #112                // Method scala/runtime/BoxesRunTime.boxToLong:(J)Ljava/lang/Long;
         7: areturn
      LineNumberTable:
        line 66: 0
      LocalVariableTable:
        Start  Length  Slot  Name   Signature
            0       8     0   x$2   Lorg/scalatest/RunningTest;
    MethodParameters:
      Name                           Flags
      x$2                            final

  private static java.lang.Object $deserializeLambda$(java.lang.invoke.SerializedLambda);
    descriptor: (Ljava/lang/invoke/SerializedLambda;)Ljava/lang/Object;
    flags: (0x100a) ACC_PRIVATE, ACC_STATIC, ACC_SYNTHETIC
    Code:
      stack=1, locals=1, args_size=1
         0: aload_0
         1: invokedynamic #308,  0            // InvokeDynamic #3:lambdaDeserialize:(Ljava/lang/invoke/SerializedLambda;)Ljava/lang/Object;
         6: areturn
}
InnerClasses:
  public static final #13= #10 of #12;    // Lookup=class java/lang/invoke/MethodHandles$Lookup of class java/lang/invoke/MethodHandles
  public static #18= #15 of #17;          // RequirementsHelper=class org/scalactic/Requirements$RequirementsHelper of class org/scalactic/Requirements
  public static #23= #20 of #22;          // AsScala=class scala/collection/JavaConverters$AsScala of class scala/collection/JavaConverters
  public static #28= #25 of #27;          // Long$=class scala/math/Ordering$Long$ of class scala/math/Ordering
SourceFile: "SlowpokeDetector.scala"
RuntimeVisibleAnnotations:
  0: #6(#7=s#8)
    scala.reflect.ScalaSignature(
      bytes="\u0006\u0005q4QAD\b\u0001\u001fMA\u0001B\u0007\u0001\u0003\u0002\u0003\u0006I\u0001\b\u0005\t?\u0001\u0011\t\u0011)A\u0005A!)\u0001\u0006\u0001C\u0001S!9a\u0006\u0001b\u0001\n\u001by\u0003BB\u001e\u0001A\u00035\u0001\u0007C\u0003=\u0001\u0011\u0005Q\bC\u0003U\u0001\u0011\u0005Q\u000bC\u0003Z\u0001\u0011\u0005!l\u0002\u0005j\u001f\u0005\u0005\t\u0012A\bk\r!qq\"!A\t\u0002=Y\u0007\"\u0002\u0015\u000b\t\u0003a\u0007bB7\u000b#\u0003%\tA\u001c\u0005\bs*\t\n\u0011\"\u0001{\u0005A\u0019Fn\\<q_.,G)\u001a;fGR|\'O\u0003\u0002\u0011#\u0005I1oY1mCR,7\u000f\u001e\u0006\u0002%\u0005\u0019qN]4\u0014\u0005\u0001!\u0002CA\u000b\u0019\u001b\u00051\"\"A\f\u0002\u000bM\u001c\u0017\r\\1\n\u0005e1\"AB!osJ+g-A\u0004uS6,w.\u001e;\u0004\u0001A\u0011Q#H\u0005\u0003=Y\u0011A\u0001T8oO\u0006\u0019q.\u001e;\u0011\u0005\u00052S\"\u0001\u0012\u000b\u0005\r\"\u0013AA5p\u0015\u0005)\u0013\u0001\u00026bm\u0006L!a\n\u0012\u0003\u0017A\u0013\u0018N\u001c;TiJ,\u0017-\\\u0001\u0007y%t\u0017\u000e\u001e \u0015\u0007)bS\u0006\u0005\u0002,\u00015\tq\u0002C\u0004\u001b\u0007A\u0005\t\u0019\u0001\u000f\t\u000f}\u0019\u0001\u0013!a\u0001A\u0005a!/\u001e8oS:<G+Z:ugV\t\u0001\u0007E\u00022maj\u0011A\r\u0006\u0003gQ\n!bY8oGV\u0014(/\u001a8u\u0015\t)D%\u0001\u0003vi&d\u0017BA\u001c3\u0005U\u0019uN\\2veJ,g\u000e^*lSBd\u0015n\u001d;TKR\u0004\"aK\u001d\n\u0005iz!a\u0003*v]:Lgn\u001a+fgR\fQB];o]&tw\rV3tiN\u0004\u0013\u0001\u0004;fgR\u001cF/\u0019:uS:<G#\u0002 B\u001dB\u0013\u0006CA\u000b@\u0013\t\u0001eC\u0001\u0003V]&$\b\"\u0002\"\u0007\u0001\u0004\u0019\u0015!C:vSR,g*Y7f!\t!5J\u0004\u0002F\u0013B\u0011aIF\u0007\u0002\u000f*\u0011\u0001jG\u0001\u0007yI|w\u000e\u001e \n\u0005)3\u0012A\u0002)sK\u0012,g-\u0003\u0002M\u001b\n11\u000b\u001e:j]\u001eT!A\u0013\f\t\u000b=3\u0001\u0019A\"\u0002\u000fM,\u0018\u000e^3JI\")\u0011K\u0002a\u0001\u0007\u0006AA/Z:u\u001d\u0006lW\rC\u0003T\r\u0001\u0007A$A\u0005uS6,7\u000b^1na\u0006aA/Z:u\r&t\u0017n\u001d5fIR!aHV,Y\u0011\u0015\u0011u\u00011\u0001D\u0011\u0015yu\u00011\u0001D\u0011\u0015\tv\u00011\u0001D\u0003=!W\r^3diNcwn\u001e9pW\u0016\u001cHCA.h!\ra\u0016\r\u001a\b\u0003;~s!A\u00120\n\u0003]I!\u0001\u0019\f\u0002\u000fA\f7m[1hK&\u0011!m\u0019\u0002\u000b\u0013:$W\r_3e\'\u0016\f(B\u00011\u0017!\tYS-\u0003\u0002g\u001f\tA1\u000b\\8xa>\\W\rC\u0003i\u0011\u0001\u0007A$\u0001\tdkJ\u0014XM\u001c;US6,7\u000b^1na\u0006\u00012\u000b\\8xa>\\W\rR3uK\u000e$xN\u001d\t\u0003W)\u0019\"A\u0003\u000b\u0015\u0003)\f1\u0004\n7fgNLg.\u001b;%OJ,\u0017\r^3sI\u0011,g-Y;mi\u0012\nT#A8+\u0005q\u00018&A9\u0011\u0005I<X\"A:\u000b\u0005Q,\u0018!C;oG\",7m[3e\u0015\t1h#\u0001\u0006b]:|G/\u0019;j_:L!\u0001_:\u0003#Ut7\r[3dW\u0016$g+\u0019:jC:\u001cW-A\u000e%Y\u0016\u001c8/\u001b8ji\u0012:\'/Z1uKJ$C-\u001a4bk2$HEM\u000b\u0002w*\u0012\u0001\u0005\u001d"
    )
BootstrapMethods:
  0: #220 REF_invokeStatic java/lang/invoke/LambdaMetafactory.altMetafactory:(Ljava/lang/invoke/MethodHandles$Lookup;Ljava/lang/String;Ljava/lang/invoke/MethodType;[Ljava/lang/Object;)Ljava/lang/invoke/CallSite;
    Method arguments:
      #204 (Ljava/lang/Object;)Ljava/lang/Object;
      #209 REF_invokeStatic org/scalatest/SlowpokeDetector.$anonfun$detectSlowpokes$1$adapted:(Lorg/scalatest/SlowpokeDetector;JLorg/scalatest/RunningTest;)Ljava/lang/Object;
      #211 (Lorg/scalatest/RunningTest;)Ljava/lang/Object;
      #212 5
      #213 1
      #211 (Lorg/scalatest/RunningTest;)Ljava/lang/Object;
  1: #220 REF_invokeStatic java/lang/invoke/LambdaMetafactory.altMetafactory:(Ljava/lang/invoke/MethodHandles$Lookup;Ljava/lang/String;Ljava/lang/invoke/MethodType;[Ljava/lang/Object;)Ljava/lang/invoke/CallSite;
    Method arguments:
      #204 (Ljava/lang/Object;)Ljava/lang/Object;
      #234 REF_invokeStatic org/scalatest/SlowpokeDetector.$anonfun$detectSlowpokes$2$adapted:(Lorg/scalatest/RunningTest;)Ljava/lang/Object;
      #211 (Lorg/scalatest/RunningTest;)Ljava/lang/Object;
      #212 5
      #213 1
      #211 (Lorg/scalatest/RunningTest;)Ljava/lang/Object;
  2: #220 REF_invokeStatic java/lang/invoke/LambdaMetafactory.altMetafactory:(Ljava/lang/invoke/MethodHandles$Lookup;Ljava/lang/String;Ljava/lang/invoke/MethodType;[Ljava/lang/Object;)Ljava/lang/invoke/CallSite;
    Method arguments:
      #204 (Ljava/lang/Object;)Ljava/lang/Object;
      #251 REF_invokeStatic org/scalatest/SlowpokeDetector.$anonfun$detectSlowpokes$3:(JLorg/scalatest/RunningTest;)Lorg/scalatest/Slowpoke;
      #253 (Lorg/scalatest/RunningTest;)Lorg/scalatest/Slowpoke;
      #212 5
      #213 1
      #253 (Lorg/scalatest/RunningTest;)Lorg/scalatest/Slowpoke;
  3: #305 REF_invokeStatic scala/runtime/LambdaDeserialize.bootstrap:(Ljava/lang/invoke/MethodHandles$Lookup;Ljava/lang/String;Ljava/lang/invoke/MethodType;[Ljava/lang/invoke/MethodHandle;)Ljava/lang/invoke/CallSite;
    Method arguments:
      #209 REF_invokeStatic org/scalatest/SlowpokeDetector.$anonfun$detectSlowpokes$1$adapted:(Lorg/scalatest/SlowpokeDetector;JLorg/scalatest/RunningTest;)Ljava/lang/Object;
      #234 REF_invokeStatic org/scalatest/SlowpokeDetector.$anonfun$detectSlowpokes$2$adapted:(Lorg/scalatest/RunningTest;)Ljava/lang/Object;
      #251 REF_invokeStatic org/scalatest/SlowpokeDetector.$anonfun$detectSlowpokes$3:(JLorg/scalatest/RunningTest;)Lorg/scalatest/Slowpoke;
  ScalaInlineInfo: length = 0x36 (unknown attribute)
   01 00 00 0A 01 09 01 0A 01 00 CD 00 CE 01 01 14
   01 15 01 00 E7 00 D2 01 00 F7 00 F8 01 00 5E 01
   1C 00 00 B0 00 B1 00 00 21 00 32 01 00 97 00 98
   00 00 38 00 39 00
  ScalaSig: length = 0x3 (unknown attribute)
   05 02 00
