Classfile /Users/mw/Projects/slang-braindump/.jar/jar8/assemble/slang-braindump/assemble/content/org/scalatest/StreamlinedXml$$anon$1.class
  Last modified May 29, 2022; size 6991 bytes
  SHA-256 checksum 1fc599cb62e5d765213daa0d145e74247aeb5084f8360f8fc39e0f69cea4e7fe
  Compiled from "StreamlinedXml.scala"
public final class org.scalatest.StreamlinedXml$$anon$1 extends java.lang.Object implements org.scalactic.Uniformity<T>
  minor version: 0
  major version: 52
  flags: (0x0031) ACC_PUBLIC, ACC_FINAL, ACC_SUPER
  this_class: #2                          // org/scalatest/StreamlinedXml$$anon$1
  super_class: #5                         // java/lang/Object
  interfaces: 1, fields: 1, methods: 12, attributes: 7
Constant pool:
    #1 = Utf8               org/scalatest/StreamlinedXml$$anon$1
    #2 = Class              #1            // org/scalatest/StreamlinedXml$$anon$1
    #3 = Utf8               Ljava/lang/Object;Lorg/scalactic/Uniformity<TT;>;
    #4 = Utf8               java/lang/Object
    #5 = Class              #4            // java/lang/Object
    #6 = Utf8               org/scalactic/Uniformity
    #7 = Class              #6            // org/scalactic/Uniformity
    #8 = Utf8               StreamlinedXml.scala
    #9 = Utf8               org/scalatest/StreamlinedXml
   #10 = Class              #9            // org/scalatest/StreamlinedXml
   #11 = Utf8               streamlined
   #12 = Utf8               ()Lorg/scalactic/Uniformity;
   #13 = NameAndType        #11:#12       // streamlined:()Lorg/scalactic/Uniformity;
   #14 = Utf8               java/lang/invoke/MethodHandles$Lookup
   #15 = Class              #14           // java/lang/invoke/MethodHandles$Lookup
   #16 = Utf8               java/lang/invoke/MethodHandles
   #17 = Class              #16           // java/lang/invoke/MethodHandles
   #18 = Utf8               Lookup
   #19 = Utf8               $outer
   #20 = Utf8               Lorg/scalatest/StreamlinedXml;
   #21 = Utf8               and
   #22 = Utf8               (Lorg/scalactic/Uniformity;)Lorg/scalactic/Uniformity;
   #23 = Utf8               (Lorg/scalactic/Uniformity<TT;>;)Lorg/scalactic/Uniformity<TT;>;
   #24 = Utf8               other
   #25 = Utf8               and$
   #26 = Utf8               (Lorg/scalactic/Uniformity;Lorg/scalactic/Uniformity;)Lorg/scalactic/Uniformity;
   #27 = NameAndType        #25:#26       // and$:(Lorg/scalactic/Uniformity;Lorg/scalactic/Uniformity;)Lorg/scalactic/Uniformity;
   #28 = InterfaceMethodref #7.#27        // org/scalactic/Uniformity.and$:(Lorg/scalactic/Uniformity;Lorg/scalactic/Uniformity;)Lorg/scalactic/Uniformity;
   #29 = Utf8               this
   #30 = Utf8               Lorg/scalatest/StreamlinedXml$$anon$1;
   #31 = Utf8               Lorg/scalactic/Uniformity;
   #32 = Utf8               toEquality
   #33 = Utf8               (Lorg/scalactic/Equality;)Lorg/scalactic/NormalizingEquality;
   #34 = Utf8               (Lorg/scalactic/Equality<TT;>;)Lorg/scalactic/NormalizingEquality<TT;>;
   #35 = Utf8               equality
   #36 = Utf8               toEquality$
   #37 = Utf8               (Lorg/scalactic/Uniformity;Lorg/scalactic/Equality;)Lorg/scalactic/NormalizingEquality;
   #38 = NameAndType        #36:#37       // toEquality$:(Lorg/scalactic/Uniformity;Lorg/scalactic/Equality;)Lorg/scalactic/NormalizingEquality;
   #39 = InterfaceMethodref #7.#38        // org/scalactic/Uniformity.toEquality$:(Lorg/scalactic/Uniformity;Lorg/scalactic/Equality;)Lorg/scalactic/NormalizingEquality;
   #40 = Utf8               Lorg/scalactic/Equality;
   #41 = Utf8               (Lorg/scalactic/Normalization;)Lorg/scalactic/Normalization;
   #42 = Utf8               (Lorg/scalactic/Normalization<TT;>;)Lorg/scalactic/Normalization<TT;>;
   #43 = Utf8               org/scalactic/Normalization
   #44 = Class              #43           // org/scalactic/Normalization
   #45 = Utf8               (Lorg/scalactic/Normalization;Lorg/scalactic/Normalization;)Lorg/scalactic/Normalization;
   #46 = NameAndType        #25:#45       // and$:(Lorg/scalactic/Normalization;Lorg/scalactic/Normalization;)Lorg/scalactic/Normalization;
   #47 = InterfaceMethodref #44.#46       // org/scalactic/Normalization.and$:(Lorg/scalactic/Normalization;Lorg/scalactic/Normalization;)Lorg/scalactic/Normalization;
   #48 = Utf8               Lorg/scalactic/Normalization;
   #49 = Utf8               toEquivalence
   #50 = Utf8               (Lorg/scalactic/Equivalence;)Lorg/scalactic/NormalizingEquivalence;
   #51 = Utf8               (Lorg/scalactic/Equivalence<TT;>;)Lorg/scalactic/NormalizingEquivalence<TT;>;
   #52 = Utf8               equivalence
   #53 = Utf8               toEquivalence$
   #54 = Utf8               (Lorg/scalactic/Normalization;Lorg/scalactic/Equivalence;)Lorg/scalactic/NormalizingEquivalence;
   #55 = NameAndType        #53:#54       // toEquivalence$:(Lorg/scalactic/Normalization;Lorg/scalactic/Equivalence;)Lorg/scalactic/NormalizingEquivalence;
   #56 = InterfaceMethodref #44.#55       // org/scalactic/Normalization.toEquivalence$:(Lorg/scalactic/Normalization;Lorg/scalactic/Equivalence;)Lorg/scalactic/NormalizingEquivalence;
   #57 = Utf8               Lorg/scalactic/Equivalence;
   #58 = Utf8               normalized
   #59 = Utf8               (Lscala/xml/NodeSeq;)Lscala/xml/NodeSeq;
   #60 = Utf8               (TT;)TT;
   #61 = Utf8               nodeSeq
   #62 = Utf8               scala/xml/Node
   #63 = Class              #62           // scala/xml/Node
   #64 = Utf8               scala/xml/Elem$
   #65 = Class              #64           // scala/xml/Elem$
   #66 = Utf8               MODULE$
   #67 = Utf8               Lscala/xml/Elem$;
   #68 = NameAndType        #66:#67       // MODULE$:Lscala/xml/Elem$;
   #69 = Fieldref           #65.#68       // scala/xml/Elem$.MODULE$:Lscala/xml/Elem$;
   #70 = Utf8               unapplySeq
   #71 = Utf8               (Lscala/xml/Node;)Lscala/Option;
   #72 = NameAndType        #70:#71       // unapplySeq:(Lscala/xml/Node;)Lscala/Option;
   #73 = Methodref          #65.#72       // scala/xml/Elem$.unapplySeq:(Lscala/xml/Node;)Lscala/Option;
   #74 = Utf8               scala/Option
   #75 = Class              #74           // scala/Option
   #76 = Utf8               isEmpty
   #77 = Utf8               ()Z
   #78 = NameAndType        #76:#77       // isEmpty:()Z
   #79 = Methodref          #75.#78       // scala/Option.isEmpty:()Z
   #80 = Utf8               get
   #81 = Utf8               ()Ljava/lang/Object;
   #82 = NameAndType        #80:#81       // get:()Ljava/lang/Object;
   #83 = Methodref          #75.#82       // scala/Option.get:()Ljava/lang/Object;
   #84 = Utf8               scala/Tuple5
   #85 = Class              #84           // scala/Tuple5
   #86 = Utf8               _1
   #87 = NameAndType        #86:#81       // _1:()Ljava/lang/Object;
   #88 = Methodref          #85.#87       // scala/Tuple5._1:()Ljava/lang/Object;
   #89 = Utf8               java/lang/String
   #90 = Class              #89           // java/lang/String
   #91 = Utf8               _2
   #92 = NameAndType        #91:#81       // _2:()Ljava/lang/Object;
   #93 = Methodref          #85.#92       // scala/Tuple5._2:()Ljava/lang/Object;
   #94 = Utf8               _3
   #95 = NameAndType        #94:#81       // _3:()Ljava/lang/Object;
   #96 = Methodref          #85.#95       // scala/Tuple5._3:()Ljava/lang/Object;
   #97 = Utf8               scala/xml/MetaData
   #98 = Class              #97           // scala/xml/MetaData
   #99 = Utf8               _4
  #100 = NameAndType        #99:#81       // _4:()Ljava/lang/Object;
  #101 = Methodref          #85.#100      // scala/Tuple5._4:()Ljava/lang/Object;
  #102 = Utf8               scala/xml/NamespaceBinding
  #103 = Class              #102          // scala/xml/NamespaceBinding
  #104 = Utf8               _5
  #105 = NameAndType        #104:#81      // _5:()Ljava/lang/Object;
  #106 = Methodref          #85.#105      // scala/Tuple5._5:()Ljava/lang/Object;
  #107 = Utf8               scala/collection/immutable/Seq
  #108 = Class              #107          // scala/collection/immutable/Seq
  #109 = Utf8               scala/package$
  #110 = Class              #109          // scala/package$
  #111 = Utf8               Lscala/package$;
  #112 = NameAndType        #66:#111      // MODULE$:Lscala/package$;
  #113 = Fieldref           #110.#112     // scala/package$.MODULE$:Lscala/package$;
  #114 = Utf8               Nil
  #115 = Utf8               ()Lscala/collection/immutable/Nil$;
  #116 = NameAndType        #114:#115     // Nil:()Lscala/collection/immutable/Nil$;
  #117 = Methodref          #110.#116     // scala/package$.Nil:()Lscala/collection/immutable/Nil$;
  #118 = Utf8               (Ljava/lang/Object;Ljava/lang/Object;)Ljava/lang/Object;
  #119 = MethodType         #118          //  (Ljava/lang/Object;Ljava/lang/Object;)Ljava/lang/Object;
  #120 = Utf8               $anonfun$normalized$1
  #121 = Utf8               (Lscala/collection/immutable/List;Lscala/xml/Node;)Lscala/collection/immutable/List;
  #122 = NameAndType        #120:#121     // $anonfun$normalized$1:(Lscala/collection/immutable/List;Lscala/xml/Node;)Lscala/collection/immutable/List;
  #123 = Methodref          #2.#122       // org/scalatest/StreamlinedXml$$anon$1.$anonfun$normalized$1:(Lscala/collection/immutable/List;Lscala/xml/Node;)Lscala/collection/immutable/List;
  #124 = MethodHandle       6:#123        // REF_invokeStatic org/scalatest/StreamlinedXml$$anon$1.$anonfun$normalized$1:(Lscala/collection/immutable/List;Lscala/xml/Node;)Lscala/collection/immutable/List;
  #125 = MethodType         #121          //  (Lscala/collection/immutable/List;Lscala/xml/Node;)Lscala/collection/immutable/List;
  #126 = Integer            5
  #127 = Integer            1
  #128 = Utf8               java/lang/invoke/LambdaMetafactory
  #129 = Class              #128          // java/lang/invoke/LambdaMetafactory
  #130 = Utf8               altMetafactory
  #131 = Utf8               (Ljava/lang/invoke/MethodHandles$Lookup;Ljava/lang/String;Ljava/lang/invoke/MethodType;[Ljava/lang/Object;)Ljava/lang/invoke/CallSite;
  #132 = NameAndType        #130:#131     // altMetafactory:(Ljava/lang/invoke/MethodHandles$Lookup;Ljava/lang/String;Ljava/lang/invoke/MethodType;[Ljava/lang/Object;)Ljava/lang/invoke/CallSite;
  #133 = Methodref          #129.#132     // java/lang/invoke/LambdaMetafactory.altMetafactory:(Ljava/lang/invoke/MethodHandles$Lookup;Ljava/lang/String;Ljava/lang/invoke/MethodType;[Ljava/lang/Object;)Ljava/lang/invoke/CallSite;
  #134 = MethodHandle       6:#133        // REF_invokeStatic java/lang/invoke/LambdaMetafactory.altMetafactory:(Ljava/lang/invoke/MethodHandles$Lookup;Ljava/lang/String;Ljava/lang/invoke/MethodType;[Ljava/lang/Object;)Ljava/lang/invoke/CallSite;
  #135 = Utf8               apply
  #136 = Utf8               ()Lscala/Function2;
  #137 = NameAndType        #135:#136     // apply:()Lscala/Function2;
  #138 = InvokeDynamic      #0:#137       // #0:apply:()Lscala/Function2;
  #139 = Utf8               foldLeft
  #140 = Utf8               (Ljava/lang/Object;Lscala/Function2;)Ljava/lang/Object;
  #141 = NameAndType        #139:#140     // foldLeft:(Ljava/lang/Object;Lscala/Function2;)Ljava/lang/Object;
  #142 = InterfaceMethodref #108.#141     // scala/collection/immutable/Seq.foldLeft:(Ljava/lang/Object;Lscala/Function2;)Ljava/lang/Object;
  #143 = Utf8               scala/collection/immutable/List
  #144 = Class              #143          // scala/collection/immutable/List
  #145 = Utf8               (Ljava/lang/Object;)Ljava/lang/Object;
  #146 = MethodType         #145          //  (Ljava/lang/Object;)Ljava/lang/Object;
  #147 = Utf8               $anonfun$normalized$2
  #148 = Utf8               (Lorg/scalatest/StreamlinedXml$$anon$1;Lscala/xml/Node;)Lscala/collection/immutable/Seq;
  #149 = NameAndType        #147:#148     // $anonfun$normalized$2:(Lorg/scalatest/StreamlinedXml$$anon$1;Lscala/xml/Node;)Lscala/collection/immutable/Seq;
  #150 = Methodref          #2.#149       // org/scalatest/StreamlinedXml$$anon$1.$anonfun$normalized$2:(Lorg/scalatest/StreamlinedXml$$anon$1;Lscala/xml/Node;)Lscala/collection/immutable/Seq;
  #151 = MethodHandle       6:#150        // REF_invokeStatic org/scalatest/StreamlinedXml$$anon$1.$anonfun$normalized$2:(Lorg/scalatest/StreamlinedXml$$anon$1;Lscala/xml/Node;)Lscala/collection/immutable/Seq;
  #152 = Utf8               (Lscala/xml/Node;)Lscala/collection/immutable/Seq;
  #153 = MethodType         #152          //  (Lscala/xml/Node;)Lscala/collection/immutable/Seq;
  #154 = Utf8               (Lorg/scalatest/StreamlinedXml$$anon$1;)Lscala/Function1;
  #155 = NameAndType        #135:#154     // apply:(Lorg/scalatest/StreamlinedXml$$anon$1;)Lscala/Function1;
  #156 = InvokeDynamic      #1:#155       // #1:apply:(Lorg/scalatest/StreamlinedXml$$anon$1;)Lscala/Function1;
  #157 = Utf8               flatMap
  #158 = Utf8               (Lscala/Function1;)Lscala/collection/immutable/List;
  #159 = NameAndType        #157:#158     // flatMap:(Lscala/Function1;)Lscala/collection/immutable/List;
  #160 = Methodref          #144.#159     // scala/collection/immutable/List.flatMap:(Lscala/Function1;)Lscala/collection/immutable/List;
  #161 = Utf8               (Ljava/lang/String;Ljava/lang/String;Lscala/xml/MetaData;Lscala/xml/NamespaceBinding;ZLscala/collection/immutable/Seq;)Lscala/xml/Elem;
  #162 = NameAndType        #135:#161     // apply:(Ljava/lang/String;Ljava/lang/String;Lscala/xml/MetaData;Lscala/xml/NamespaceBinding;ZLscala/collection/immutable/Seq;)Lscala/xml/Elem;
  #163 = Methodref          #65.#162      // scala/xml/Elem$.apply:(Ljava/lang/String;Ljava/lang/String;Lscala/xml/MetaData;Lscala/xml/NamespaceBinding;ZLscala/collection/immutable/Seq;)Lscala/xml/Elem;
  #164 = Utf8               mergedTextNodes
  #165 = Utf8               Lscala/collection/immutable/List;
  #166 = Utf8               pre
  #167 = Utf8               Ljava/lang/String;
  #168 = Utf8               lab
  #169 = Utf8               md
  #170 = Utf8               Lscala/xml/MetaData;
  #171 = Utf8               scp
  #172 = Utf8               Lscala/xml/NamespaceBinding;
  #173 = Utf8               children
  #174 = Utf8               Lscala/collection/immutable/Seq;
  #175 = Utf8               Lscala/xml/NodeSeq;
  #176 = Utf8               scala/xml/NodeSeq
  #177 = Class              #176          // scala/xml/NodeSeq
  #178 = Utf8               normalizedCanHandle
  #179 = Utf8               (Ljava/lang/Object;)Z
  #180 = Utf8               b
  #181 = Utf8               Ljava/lang/Object;
  #182 = Utf8               normalizedOrSame
  #183 = Utf8               org/scalatest/StreamlinedXml$
  #184 = Class              #183          // org/scalatest/StreamlinedXml$
  #185 = Utf8               Lorg/scalatest/StreamlinedXml$;
  #186 = NameAndType        #66:#185      // MODULE$:Lorg/scalatest/StreamlinedXml$;
  #187 = Fieldref           #184.#186     // org/scalatest/StreamlinedXml$.MODULE$:Lorg/scalatest/StreamlinedXml$;
  #188 = Methodref          #184.#13      // org/scalatest/StreamlinedXml$.streamlined:()Lorg/scalactic/Uniformity;
  #189 = NameAndType        #58:#145      // normalized:(Ljava/lang/Object;)Ljava/lang/Object;
  #190 = InterfaceMethodref #7.#189       // org/scalactic/Uniformity.normalized:(Ljava/lang/Object;)Ljava/lang/Object;
  #191 = Utf8               a
  #192 = NameAndType        #58:#59       // normalized:(Lscala/xml/NodeSeq;)Lscala/xml/NodeSeq;
  #193 = Methodref          #2.#192       // org/scalatest/StreamlinedXml$$anon$1.normalized:(Lscala/xml/NodeSeq;)Lscala/xml/NodeSeq;
  #194 = Utf8               acc
  #195 = Utf8               ele
  #196 = Utf8               scala/xml/Text
  #197 = Class              #196          // scala/xml/Text
  #198 = Utf8               headOption
  #199 = Utf8               ()Lscala/Option;
  #200 = NameAndType        #198:#199     // headOption:()Lscala/Option;
  #201 = Methodref          #144.#200     // scala/collection/immutable/List.headOption:()Lscala/Option;
  #202 = Utf8               scala/Some
  #203 = Class              #202          // scala/Some
  #204 = Utf8               value
  #205 = NameAndType        #204:#81      // value:()Ljava/lang/Object;
  #206 = Methodref          #203.#205     // scala/Some.value:()Ljava/lang/Object;
  #207 = Utf8               scala/xml/Text$
  #208 = Class              #207          // scala/xml/Text$
  #209 = Utf8               Lscala/xml/Text$;
  #210 = NameAndType        #66:#209      // MODULE$:Lscala/xml/Text$;
  #211 = Fieldref           #208.#210     // scala/xml/Text$.MODULE$:Lscala/xml/Text$;
  #212 = Utf8               java/lang/StringBuilder
  #213 = Class              #212          // java/lang/StringBuilder
  #214 = Integer            0
  #215 = Utf8               <init>
  #216 = Utf8               (I)V
  #217 = NameAndType        #215:#216     // "<init>":(I)V
  #218 = Methodref          #213.#217     // java/lang/StringBuilder."<init>":(I)V
  #219 = Utf8               text
  #220 = Utf8               ()Ljava/lang/String;
  #221 = NameAndType        #219:#220     // text:()Ljava/lang/String;
  #222 = Methodref          #197.#221     // scala/xml/Text.text:()Ljava/lang/String;
  #223 = Utf8               append
  #224 = Utf8               (Ljava/lang/String;)Ljava/lang/StringBuilder;
  #225 = NameAndType        #223:#224     // append:(Ljava/lang/String;)Ljava/lang/StringBuilder;
  #226 = Methodref          #213.#225     // java/lang/StringBuilder.append:(Ljava/lang/String;)Ljava/lang/StringBuilder;
  #227 = Utf8               toString
  #228 = NameAndType        #227:#220     // toString:()Ljava/lang/String;
  #229 = Methodref          #213.#228     // java/lang/StringBuilder.toString:()Ljava/lang/String;
  #230 = Utf8               (Ljava/lang/String;)Lscala/xml/Text;
  #231 = NameAndType        #135:#230     // apply:(Ljava/lang/String;)Lscala/xml/Text;
  #232 = Methodref          #208.#231     // scala/xml/Text$.apply:(Ljava/lang/String;)Lscala/xml/Text;
  #233 = Utf8               tail
  #234 = NameAndType        #233:#81      // tail:()Ljava/lang/Object;
  #235 = Methodref          #144.#234     // scala/collection/immutable/List.tail:()Ljava/lang/Object;
  #236 = Utf8               $colon$colon
  #237 = Utf8               (Ljava/lang/Object;)Lscala/collection/immutable/List;
  #238 = NameAndType        #236:#237     // $colon$colon:(Ljava/lang/Object;)Lscala/collection/immutable/List;
  #239 = Methodref          #144.#238     // scala/collection/immutable/List.$colon$colon:(Ljava/lang/Object;)Lscala/collection/immutable/List;
  #240 = Utf8               accTxt
  #241 = Utf8               Lscala/xml/Node;
  #242 = Utf8               $this
  #243 = Utf8               node
  #244 = Utf8               org$scalatest$StreamlinedXml$$trimTextZappingEmpty$1
  #245 = NameAndType        #244:#152     // org$scalatest$StreamlinedXml$$trimTextZappingEmpty$1:(Lscala/xml/Node;)Lscala/collection/immutable/Seq;
  #246 = InterfaceMethodref #10.#245      // org/scalatest/StreamlinedXml.org$scalatest$StreamlinedXml$$trimTextZappingEmpty$1:(Lscala/xml/Node;)Lscala/collection/immutable/Seq;
  #247 = Utf8               (Lorg/scalatest/StreamlinedXml;)V
  #248 = NameAndType        #19:#20       // $outer:Lorg/scalatest/StreamlinedXml;
  #249 = Fieldref           #2.#248       // org/scalatest/StreamlinedXml$$anon$1.$outer:Lorg/scalatest/StreamlinedXml;
  #250 = Utf8               ()V
  #251 = NameAndType        #215:#250     // "<init>":()V
  #252 = Methodref          #5.#251       // java/lang/Object."<init>":()V
  #253 = Utf8               $init$
  #254 = Utf8               (Lorg/scalactic/Normalization;)V
  #255 = NameAndType        #253:#254     // $init$:(Lorg/scalactic/Normalization;)V
  #256 = InterfaceMethodref #44.#255      // org/scalactic/Normalization.$init$:(Lorg/scalactic/Normalization;)V
  #257 = Utf8               (Lorg/scalactic/Uniformity;)V
  #258 = NameAndType        #253:#257     // $init$:(Lorg/scalactic/Uniformity;)V
  #259 = InterfaceMethodref #7.#258       // org/scalactic/Uniformity.$init$:(Lorg/scalactic/Uniformity;)V
  #260 = Utf8               $deserializeLambda$
  #261 = Utf8               (Ljava/lang/invoke/SerializedLambda;)Ljava/lang/Object;
  #262 = Utf8               scala/runtime/LambdaDeserialize
  #263 = Class              #262          // scala/runtime/LambdaDeserialize
  #264 = Utf8               bootstrap
  #265 = Utf8               (Ljava/lang/invoke/MethodHandles$Lookup;Ljava/lang/String;Ljava/lang/invoke/MethodType;[Ljava/lang/invoke/MethodHandle;)Ljava/lang/invoke/CallSite;
  #266 = NameAndType        #264:#265     // bootstrap:(Ljava/lang/invoke/MethodHandles$Lookup;Ljava/lang/String;Ljava/lang/invoke/MethodType;[Ljava/lang/invoke/MethodHandle;)Ljava/lang/invoke/CallSite;
  #267 = Methodref          #263.#266     // scala/runtime/LambdaDeserialize.bootstrap:(Ljava/lang/invoke/MethodHandles$Lookup;Ljava/lang/String;Ljava/lang/invoke/MethodType;[Ljava/lang/invoke/MethodHandle;)Ljava/lang/invoke/CallSite;
  #268 = MethodHandle       6:#267        // REF_invokeStatic scala/runtime/LambdaDeserialize.bootstrap:(Ljava/lang/invoke/MethodHandles$Lookup;Ljava/lang/String;Ljava/lang/invoke/MethodType;[Ljava/lang/invoke/MethodHandle;)Ljava/lang/invoke/CallSite;
  #269 = Utf8               lambdaDeserialize
  #270 = NameAndType        #269:#261     // lambdaDeserialize:(Ljava/lang/invoke/SerializedLambda;)Ljava/lang/Object;
  #271 = InvokeDynamic      #2:#270       // #2:lambdaDeserialize:(Ljava/lang/invoke/SerializedLambda;)Ljava/lang/Object;
  #272 = Utf8               Code
  #273 = Utf8               LineNumberTable
  #274 = Utf8               LocalVariableTable
  #275 = Utf8               Signature
  #276 = Utf8               MethodParameters
  #277 = Utf8               StackMapTable
  #278 = Utf8               InnerClasses
  #279 = Utf8               EnclosingMethod
  #280 = Utf8               SourceFile
  #281 = Utf8               BootstrapMethods
  #282 = Utf8               ScalaInlineInfo
  #283 = Utf8               Scala
{
  private final org.scalatest.StreamlinedXml $outer;
    descriptor: Lorg/scalatest/StreamlinedXml;
    flags: (0x1012) ACC_PRIVATE, ACC_FINAL, ACC_SYNTHETIC

  public final org.scalactic.Uniformity<T> and(org.scalactic.Uniformity<T>);
    descriptor: (Lorg/scalactic/Uniformity;)Lorg/scalactic/Uniformity;
    flags: (0x0011) ACC_PUBLIC, ACC_FINAL
    Code:
      stack=2, locals=2, args_size=2
         0: aload_0
         1: aload_1
         2: invokestatic  #28                 // InterfaceMethod org/scalactic/Uniformity.and$:(Lorg/scalactic/Uniformity;Lorg/scalactic/Uniformity;)Lorg/scalactic/Uniformity;
         5: areturn
      LineNumberTable:
        line 144: 0
      LocalVariableTable:
        Start  Length  Slot  Name   Signature
            0       6     0  this   Lorg/scalatest/StreamlinedXml$$anon$1;
            0       6     1 other   Lorg/scalactic/Uniformity;
    Signature: #23                          // (Lorg/scalactic/Uniformity<TT;>;)Lorg/scalactic/Uniformity<TT;>;
    MethodParameters:
      Name                           Flags
      other                          final

  public final org.scalactic.NormalizingEquality<T> toEquality(org.scalactic.Equality<T>);
    descriptor: (Lorg/scalactic/Equality;)Lorg/scalactic/NormalizingEquality;
    flags: (0x0011) ACC_PUBLIC, ACC_FINAL
    Code:
      stack=2, locals=2, args_size=2
         0: aload_0
         1: aload_1
         2: invokestatic  #39                 // InterfaceMethod org/scalactic/Uniformity.toEquality$:(Lorg/scalactic/Uniformity;Lorg/scalactic/Equality;)Lorg/scalactic/NormalizingEquality;
         5: areturn
      LineNumberTable:
        line 144: 0
      LocalVariableTable:
        Start  Length  Slot  Name   Signature
            0       6     0  this   Lorg/scalatest/StreamlinedXml$$anon$1;
            0       6     1 equality   Lorg/scalactic/Equality;
    Signature: #34                          // (Lorg/scalactic/Equality<TT;>;)Lorg/scalactic/NormalizingEquality<TT;>;
    MethodParameters:
      Name                           Flags
      equality                       final

  public final org.scalactic.Normalization<T> and(org.scalactic.Normalization<T>);
    descriptor: (Lorg/scalactic/Normalization;)Lorg/scalactic/Normalization;
    flags: (0x0011) ACC_PUBLIC, ACC_FINAL
    Code:
      stack=2, locals=2, args_size=2
         0: aload_0
         1: aload_1
         2: invokestatic  #47                 // InterfaceMethod org/scalactic/Normalization.and$:(Lorg/scalactic/Normalization;Lorg/scalactic/Normalization;)Lorg/scalactic/Normalization;
         5: areturn
      LineNumberTable:
        line 144: 0
      LocalVariableTable:
        Start  Length  Slot  Name   Signature
            0       6     0  this   Lorg/scalatest/StreamlinedXml$$anon$1;
            0       6     1 other   Lorg/scalactic/Normalization;
    Signature: #42                          // (Lorg/scalactic/Normalization<TT;>;)Lorg/scalactic/Normalization<TT;>;
    MethodParameters:
      Name                           Flags
      other                          final

  public final org.scalactic.NormalizingEquivalence<T> toEquivalence(org.scalactic.Equivalence<T>);
    descriptor: (Lorg/scalactic/Equivalence;)Lorg/scalactic/NormalizingEquivalence;
    flags: (0x0011) ACC_PUBLIC, ACC_FINAL
    Code:
      stack=2, locals=2, args_size=2
         0: aload_0
         1: aload_1
         2: invokestatic  #56                 // InterfaceMethod org/scalactic/Normalization.toEquivalence$:(Lorg/scalactic/Normalization;Lorg/scalactic/Equivalence;)Lorg/scalactic/NormalizingEquivalence;
         5: areturn
      LineNumberTable:
        line 144: 0
      LocalVariableTable:
        Start  Length  Slot  Name   Signature
            0       6     0  this   Lorg/scalatest/StreamlinedXml$$anon$1;
            0       6     1 equivalence   Lorg/scalactic/Equivalence;
    Signature: #51                          // (Lorg/scalactic/Equivalence<TT;>;)Lorg/scalactic/NormalizingEquivalence<TT;>;
    MethodParameters:
      Name                           Flags
      equivalence                    final

  public T normalized(T);
    descriptor: (Lscala/xml/NodeSeq;)Lscala/xml/NodeSeq;
    flags: (0x0001) ACC_PUBLIC
    Code:
      stack=8, locals=12, args_size=2
         0: aload_1
         1: astore_3
         2: aload_3
         3: instanceof    #63                 // class scala/xml/Node
         6: ifeq          169
         9: aload_3
        10: checkcast     #63                 // class scala/xml/Node
        13: astore        4
        15: getstatic     #69                 // Field scala/xml/Elem$.MODULE$:Lscala/xml/Elem$;
        18: aload         4
        20: invokevirtual #73                 // Method scala/xml/Elem$.unapplySeq:(Lscala/xml/Node;)Lscala/Option;
        23: astore        5
        25: aload         5
        27: invokevirtual #79                 // Method scala/Option.isEmpty:()Z
        30: ifne          166
        33: aload         5
        35: invokevirtual #83                 // Method scala/Option.get:()Ljava/lang/Object;
        38: checkcast     #85                 // class scala/Tuple5
        41: invokevirtual #88                 // Method scala/Tuple5._1:()Ljava/lang/Object;
        44: checkcast     #90                 // class java/lang/String
        47: astore        6
        49: aload         5
        51: invokevirtual #83                 // Method scala/Option.get:()Ljava/lang/Object;
        54: checkcast     #85                 // class scala/Tuple5
        57: invokevirtual #93                 // Method scala/Tuple5._2:()Ljava/lang/Object;
        60: checkcast     #90                 // class java/lang/String
        63: astore        7
        65: aload         5
        67: invokevirtual #83                 // Method scala/Option.get:()Ljava/lang/Object;
        70: checkcast     #85                 // class scala/Tuple5
        73: invokevirtual #96                 // Method scala/Tuple5._3:()Ljava/lang/Object;
        76: checkcast     #98                 // class scala/xml/MetaData
        79: astore        8
        81: aload         5
        83: invokevirtual #83                 // Method scala/Option.get:()Ljava/lang/Object;
        86: checkcast     #85                 // class scala/Tuple5
        89: invokevirtual #101                // Method scala/Tuple5._4:()Ljava/lang/Object;
        92: checkcast     #103                // class scala/xml/NamespaceBinding
        95: astore        9
        97: aload         5
        99: invokevirtual #83                 // Method scala/Option.get:()Ljava/lang/Object;
       102: checkcast     #85                 // class scala/Tuple5
       105: invokevirtual #106                // Method scala/Tuple5._5:()Ljava/lang/Object;
       108: checkcast     #108                // class scala/collection/immutable/Seq
       111: astore        10
       113: aload         10
       115: getstatic     #113                // Field scala/package$.MODULE$:Lscala/package$;
       118: invokevirtual #117                // Method scala/package$.Nil:()Lscala/collection/immutable/Nil$;
       121: invokedynamic #138,  0            // InvokeDynamic #0:apply:()Lscala/Function2;
       126: invokeinterface #142,  3          // InterfaceMethod scala/collection/immutable/Seq.foldLeft:(Ljava/lang/Object;Lscala/Function2;)Ljava/lang/Object;
       131: checkcast     #144                // class scala/collection/immutable/List
       134: astore        11
       136: getstatic     #69                 // Field scala/xml/Elem$.MODULE$:Lscala/xml/Elem$;
       139: aload         6
       141: aload         7
       143: aload         8
       145: aload         9
       147: iconst_0
       148: aload         11
       150: aload_0
       151: invokedynamic #156,  0            // InvokeDynamic #1:apply:(Lorg/scalatest/StreamlinedXml$$anon$1;)Lscala/Function1;
       156: invokevirtual #160                // Method scala/collection/immutable/List.flatMap:(Lscala/Function1;)Lscala/collection/immutable/List;
       159: invokevirtual #163                // Method scala/xml/Elem$.apply:(Ljava/lang/String;Ljava/lang/String;Lscala/xml/MetaData;Lscala/xml/NamespaceBinding;ZLscala/collection/immutable/Seq;)Lscala/xml/Elem;
       162: astore_2
       163: goto          177
       166: goto          172
       169: goto          172
       172: aload_1
       173: astore_2
       174: goto          177
       177: aload_2
       178: areturn
      StackMapTable: number_of_entries = 4
        frame_type = 255 /* full_frame */
          offset_delta = 166
          locals = [ class org/scalatest/StreamlinedXml$$anon$1, class scala/xml/NodeSeq, top, class scala/xml/NodeSeq, class scala/xml/Node, class scala/Option ]
          stack = []
        frame_type = 249 /* chop */
          offset_delta = 2
        frame_type = 2 /* same */
        frame_type = 255 /* full_frame */
          offset_delta = 4
          locals = [ class org/scalatest/StreamlinedXml$$anon$1, class scala/xml/NodeSeq, class scala/xml/NodeSeq, class scala/xml/NodeSeq ]
          stack = []
      LineNumberTable:
        line 146: 0
        line 147: 2
        line 146: 33
        line 146: 49
        line 146: 65
        line 146: 81
        line 146: 97
        line 149: 113
        line 160: 136
        line 147: 166
        line 161: 172
        line 146: 177
      LocalVariableTable:
        Start  Length  Slot  Name   Signature
          136      26    11 mergedTextNodes   Lscala/collection/immutable/List;
           49     117     6   pre   Ljava/lang/String;
           65     101     7   lab   Ljava/lang/String;
           81      85     8    md   Lscala/xml/MetaData;
           97      69     9   scp   Lscala/xml/NamespaceBinding;
          113      53    10 children   Lscala/collection/immutable/Seq;
            0     179     0  this   Lorg/scalatest/StreamlinedXml$$anon$1;
            0     179     1 nodeSeq   Lscala/xml/NodeSeq;
    Signature: #60                          // (TT;)TT;
    MethodParameters:
      Name                           Flags
      nodeSeq                        final

  public final boolean normalizedCanHandle(java.lang.Object);
    descriptor: (Ljava/lang/Object;)Z
    flags: (0x0011) ACC_PUBLIC, ACC_FINAL
    Code:
      stack=1, locals=2, args_size=2
         0: aload_1
         1: instanceof    #177                // class scala/xml/NodeSeq
         4: ireturn
      LineNumberTable:
        line 169: 0
      LocalVariableTable:
        Start  Length  Slot  Name   Signature
            0       5     0  this   Lorg/scalatest/StreamlinedXml$$anon$1;
            0       5     1     b   Ljava/lang/Object;
    MethodParameters:
      Name                           Flags
      b                              final

  public final java.lang.Object normalizedOrSame(java.lang.Object);
    descriptor: (Ljava/lang/Object;)Ljava/lang/Object;
    flags: (0x0011) ACC_PUBLIC, ACC_FINAL
    Code:
      stack=2, locals=5, args_size=2
         0: aload_1
         1: astore_3
         2: aload_3
         3: instanceof    #177                // class scala/xml/NodeSeq
         6: ifeq          32
         9: aload_3
        10: checkcast     #177                // class scala/xml/NodeSeq
        13: astore        4
        15: getstatic     #187                // Field org/scalatest/StreamlinedXml$.MODULE$:Lorg/scalatest/StreamlinedXml$;
        18: invokevirtual #188                // Method org/scalatest/StreamlinedXml$.streamlined:()Lorg/scalactic/Uniformity;
        21: aload         4
        23: invokeinterface #190,  2          // InterfaceMethod org/scalactic/Uniformity.normalized:(Ljava/lang/Object;)Ljava/lang/Object;
        28: astore_2
        29: goto          40
        32: goto          35
        35: aload_1
        36: astore_2
        37: goto          40
        40: aload_2
        41: areturn
      StackMapTable: number_of_entries = 3
        frame_type = 253 /* append */
          offset_delta = 32
          locals = [ top, class java/lang/Object ]
        frame_type = 2 /* same */
        frame_type = 255 /* full_frame */
          offset_delta = 4
          locals = [ class org/scalatest/StreamlinedXml$$anon$1, class java/lang/Object, class java/lang/Object, class java/lang/Object ]
          stack = []
      LineNumberTable:
        line 186: 0
        line 187: 2
        line 188: 35
        line 186: 40
      LocalVariableTable:
        Start  Length  Slot  Name   Signature
            0      42     0  this   Lorg/scalatest/StreamlinedXml$$anon$1;
            0      42     1     b   Ljava/lang/Object;
    MethodParameters:
      Name                           Flags
      b                              final

  public java.lang.Object normalized(java.lang.Object);
    descriptor: (Ljava/lang/Object;)Ljava/lang/Object;
    flags: (0x1041) ACC_PUBLIC, ACC_BRIDGE, ACC_SYNTHETIC
    Code:
      stack=2, locals=2, args_size=2
         0: aload_0
         1: aload_1
         2: checkcast     #177                // class scala/xml/NodeSeq
         5: invokevirtual #193                // Method normalized:(Lscala/xml/NodeSeq;)Lscala/xml/NodeSeq;
         8: areturn
      LineNumberTable:
        line 144: 0
      LocalVariableTable:
        Start  Length  Slot  Name   Signature
            0       9     0  this   Lorg/scalatest/StreamlinedXml$$anon$1;
            0       9     1     a   Ljava/lang/Object;
    MethodParameters:
      Name                           Flags
      a                              final

  public static final scala.collection.immutable.List $anonfun$normalized$1(scala.collection.immutable.List, scala.xml.Node);
    descriptor: (Lscala/collection/immutable/List;Lscala/xml/Node;)Lscala/collection/immutable/List;
    flags: (0x1019) ACC_PUBLIC, ACC_STATIC, ACC_FINAL, ACC_SYNTHETIC
    Code:
      stack=4, locals=13, args_size=2
         0: aload_1
         1: astore        4
         3: aload         4
         5: instanceof    #197                // class scala/xml/Text
         8: ifeq          140
        11: aload         4
        13: checkcast     #197                // class scala/xml/Text
        16: astore        5
        18: aload_0
        19: invokevirtual #201                // Method scala/collection/immutable/List.headOption:()Lscala/Option;
        22: astore        6
        24: aload         6
        26: instanceof    #203                // class scala/Some
        29: ifeq          119
        32: aload         6
        34: checkcast     #203                // class scala/Some
        37: astore        7
        39: aload         7
        41: invokevirtual #206                // Method scala/Some.value:()Ljava/lang/Object;
        44: checkcast     #63                 // class scala/xml/Node
        47: astore        8
        49: aload         8
        51: instanceof    #197                // class scala/xml/Text
        54: ifeq          116
        57: aload         8
        59: checkcast     #197                // class scala/xml/Text
        62: astore        9
        64: getstatic     #211                // Field scala/xml/Text$.MODULE$:Lscala/xml/Text$;
        67: new           #213                // class java/lang/StringBuilder
        70: dup
        71: ldc           #214                // int 0
        73: invokespecial #218                // Method java/lang/StringBuilder."<init>":(I)V
        76: aload         9
        78: invokevirtual #222                // Method scala/xml/Text.text:()Ljava/lang/String;
        81: invokevirtual #226                // Method java/lang/StringBuilder.append:(Ljava/lang/String;)Ljava/lang/StringBuilder;
        84: aload         5
        86: invokevirtual #222                // Method scala/xml/Text.text:()Ljava/lang/String;
        89: invokevirtual #226                // Method java/lang/StringBuilder.append:(Ljava/lang/String;)Ljava/lang/StringBuilder;
        92: invokevirtual #229                // Method java/lang/StringBuilder.toString:()Ljava/lang/String;
        95: invokevirtual #232                // Method scala/xml/Text$.apply:(Ljava/lang/String;)Lscala/xml/Text;
        98: astore        10
       100: aload_0
       101: invokevirtual #235                // Method scala/collection/immutable/List.tail:()Ljava/lang/Object;
       104: checkcast     #144                // class scala/collection/immutable/List
       107: aload         10
       109: invokevirtual #239                // Method scala/collection/immutable/List.$colon$colon:(Ljava/lang/Object;)Lscala/collection/immutable/List;
       112: astore_3
       113: goto          135
       116: goto          122
       119: goto          122
       122: aload_1
       123: astore        11
       125: aload_0
       126: aload         11
       128: invokevirtual #239                // Method scala/collection/immutable/List.$colon$colon:(Ljava/lang/Object;)Lscala/collection/immutable/List;
       131: astore_3
       132: goto          135
       135: aload_3
       136: astore_2
       137: goto          156
       140: goto          143
       143: aload_1
       144: astore        12
       146: aload_0
       147: aload         12
       149: invokevirtual #239                // Method scala/collection/immutable/List.$colon$colon:(Ljava/lang/Object;)Lscala/collection/immutable/List;
       152: astore_2
       153: goto          156
       156: aload_2
       157: areturn
      StackMapTable: number_of_entries = 7
        frame_type = 255 /* full_frame */
          offset_delta = 116
          locals = [ class scala/collection/immutable/List, class scala/xml/Node, top, top, class scala/xml/Node, class scala/xml/Text, class scala/Option, class scala/Some, class scala/xml/Node ]
          stack = []
        frame_type = 249 /* chop */
          offset_delta = 2
        frame_type = 2 /* same */
        frame_type = 255 /* full_frame */
          offset_delta = 12
          locals = [ class scala/collection/immutable/List, class scala/xml/Node, top, class scala/collection/immutable/List, class scala/xml/Node, class scala/xml/Text, class scala/Option ]
          stack = []
        frame_type = 255 /* full_frame */
          offset_delta = 4
          locals = [ class scala/collection/immutable/List, class scala/xml/Node, top, top, class scala/xml/Node ]
          stack = []
        frame_type = 2 /* same */
        frame_type = 255 /* full_frame */
          offset_delta = 12
          locals = [ class scala/collection/immutable/List, class scala/xml/Node, class scala/collection/immutable/List, top, class scala/xml/Node ]
          stack = []
      LineNumberTable:
        line 150: 0
        line 151: 3
        line 152: 18
        line 153: 24
        line 154: 64
        line 153: 116
        line 155: 122
        line 152: 135
        line 151: 140
        line 157: 143
        line 150: 156
      LocalVariableTable:
        Start  Length  Slot  Name   Signature
           49      70     8 accTxt   Lscala/xml/Node;
            0     158     0   acc   Lscala/collection/immutable/List;
            0     158     1   ele   Lscala/xml/Node;
    MethodParameters:
      Name                           Flags
      acc                            final
      ele                            final

  public static final scala.collection.immutable.Seq $anonfun$normalized$2(org.scalatest.StreamlinedXml$$anon$1, scala.xml.Node);
    descriptor: (Lorg/scalatest/StreamlinedXml$$anon$1;Lscala/xml/Node;)Lscala/collection/immutable/Seq;
    flags: (0x1019) ACC_PUBLIC, ACC_STATIC, ACC_FINAL, ACC_SYNTHETIC
    Code:
      stack=1, locals=2, args_size=2
         0: aload_1
         1: invokestatic  #246                // InterfaceMethod org/scalatest/StreamlinedXml.org$scalatest$StreamlinedXml$$trimTextZappingEmpty$1:(Lscala/xml/Node;)Lscala/collection/immutable/Seq;
         4: areturn
      LineNumberTable:
        line 160: 0
      LocalVariableTable:
        Start  Length  Slot  Name   Signature
            0       5     0 $this   Lorg/scalatest/StreamlinedXml$$anon$1;
            0       5     1  node   Lscala/xml/Node;
    MethodParameters:
      Name                           Flags
      $this                          final synthetic
      node                           final

  public org.scalatest.StreamlinedXml$$anon$1(org.scalatest.StreamlinedXml);
    descriptor: (Lorg/scalatest/StreamlinedXml;)V
    flags: (0x0001) ACC_PUBLIC
    Code:
      stack=2, locals=2, args_size=2
         0: aload_1
         1: ifnonnull     6
         4: aconst_null
         5: athrow
         6: aload_0
         7: aload_1
         8: putfield      #249                // Field $outer:Lorg/scalatest/StreamlinedXml;
        11: aload_0
        12: invokespecial #252                // Method java/lang/Object."<init>":()V
        15: aload_0
        16: invokestatic  #256                // InterfaceMethod org/scalactic/Normalization.$init$:(Lorg/scalactic/Normalization;)V
        19: aload_0
        20: invokestatic  #259                // InterfaceMethod org/scalactic/Uniformity.$init$:(Lorg/scalactic/Uniformity;)V
        23: return
      StackMapTable: number_of_entries = 1
        frame_type = 6 /* same */
      LineNumberTable:
        line 144: 0
      LocalVariableTable:
        Start  Length  Slot  Name   Signature
            0      24     0  this   Lorg/scalatest/StreamlinedXml$$anon$1;
            0      24     1 $outer   Lorg/scalatest/StreamlinedXml;
    MethodParameters:
      Name                           Flags
      $outer                         final synthetic

  private static java.lang.Object $deserializeLambda$(java.lang.invoke.SerializedLambda);
    descriptor: (Ljava/lang/invoke/SerializedLambda;)Ljava/lang/Object;
    flags: (0x100a) ACC_PRIVATE, ACC_STATIC, ACC_SYNTHETIC
    Code:
      stack=1, locals=1, args_size=1
         0: aload_0
         1: invokedynamic #271,  0            // InvokeDynamic #2:lambdaDeserialize:(Ljava/lang/invoke/SerializedLambda;)Ljava/lang/Object;
         6: areturn
}
InnerClasses:
  public static final #18= #15 of #17;    // Lookup=class java/lang/invoke/MethodHandles$Lookup of class java/lang/invoke/MethodHandles
  public final #2;                        // class org/scalatest/StreamlinedXml$$anon$1
EnclosingMethod: #10.#13                // org.scalatest.StreamlinedXml.streamlined
Signature: #3                           // Ljava/lang/Object;Lorg/scalactic/Uniformity<TT;>;
SourceFile: "StreamlinedXml.scala"
BootstrapMethods:
  0: #134 REF_invokeStatic java/lang/invoke/LambdaMetafactory.altMetafactory:(Ljava/lang/invoke/MethodHandles$Lookup;Ljava/lang/String;Ljava/lang/invoke/MethodType;[Ljava/lang/Object;)Ljava/lang/invoke/CallSite;
    Method arguments:
      #119 (Ljava/lang/Object;Ljava/lang/Object;)Ljava/lang/Object;
      #124 REF_invokeStatic org/scalatest/StreamlinedXml$$anon$1.$anonfun$normalized$1:(Lscala/collection/immutable/List;Lscala/xml/Node;)Lscala/collection/immutable/List;
      #125 (Lscala/collection/immutable/List;Lscala/xml/Node;)Lscala/collection/immutable/List;
      #126 5
      #127 1
      #125 (Lscala/collection/immutable/List;Lscala/xml/Node;)Lscala/collection/immutable/List;
  1: #134 REF_invokeStatic java/lang/invoke/LambdaMetafactory.altMetafactory:(Ljava/lang/invoke/MethodHandles$Lookup;Ljava/lang/String;Ljava/lang/invoke/MethodType;[Ljava/lang/Object;)Ljava/lang/invoke/CallSite;
    Method arguments:
      #146 (Ljava/lang/Object;)Ljava/lang/Object;
      #151 REF_invokeStatic org/scalatest/StreamlinedXml$$anon$1.$anonfun$normalized$2:(Lorg/scalatest/StreamlinedXml$$anon$1;Lscala/xml/Node;)Lscala/collection/immutable/Seq;
      #153 (Lscala/xml/Node;)Lscala/collection/immutable/Seq;
      #126 5
      #127 1
      #153 (Lscala/xml/Node;)Lscala/collection/immutable/Seq;
  2: #268 REF_invokeStatic scala/runtime/LambdaDeserialize.bootstrap:(Ljava/lang/invoke/MethodHandles$Lookup;Ljava/lang/String;Ljava/lang/invoke/MethodType;[Ljava/lang/invoke/MethodHandle;)Ljava/lang/invoke/CallSite;
    Method arguments:
      #124 REF_invokeStatic org/scalatest/StreamlinedXml$$anon$1.$anonfun$normalized$1:(Lscala/collection/immutable/List;Lscala/xml/Node;)Lscala/collection/immutable/List;
      #151 REF_invokeStatic org/scalatest/StreamlinedXml$$anon$1.$anonfun$normalized$2:(Lorg/scalatest/StreamlinedXml$$anon$1;Lscala/xml/Node;)Lscala/collection/immutable/Seq;
  ScalaInlineInfo: length = 0x3B (unknown attribute)
   01 01 00 0B 00 78 00 79 01 00 93 00 94 01 00 D7
   00 F7 01 00 15 00 29 01 00 15 00 16 01 00 3A 00
   91 01 00 3A 00 3B 01 00 B2 00 B3 01 00 B6 00 91
   01 00 20 00 21 01 00 31 00 32 01
  Scala: length = 0x0 (unknown attribute)

