Classfile /Users/mw/Projects/slang-braindump/.jar/jar8/assemble/slang-braindump/assemble/content/org/scalatest/Suite$$anon$1.class
  Last modified May 29, 2022; size 2505 bytes
  SHA-256 checksum bc07d7d1ec24717f5139b7475b9a576c329bb372c9fe51d7dff50171e097e18e
  Compiled from "Suite.scala"
public final class org.scalatest.Suite$$anon$1 implements org.scalatest.TestData
  minor version: 0
  major version: 52
  flags: (0x0031) ACC_PUBLIC, ACC_FINAL, ACC_SUPER
  this_class: #2                          // org/scalatest/Suite$$anon$1
  super_class: #4                         // java/lang/Object
  interfaces: 1, fields: 6, methods: 9, attributes: 5
Constant pool:
    #1 = Utf8               org/scalatest/Suite$$anon$1
    #2 = Class              #1            // org/scalatest/Suite$$anon$1
    #3 = Utf8               java/lang/Object
    #4 = Class              #3            // java/lang/Object
    #5 = Utf8               org/scalatest/TestData
    #6 = Class              #5            // org/scalatest/TestData
    #7 = Utf8               Suite.scala
    #8 = Utf8               org/scalatest/Suite
    #9 = Class              #8            // org/scalatest/Suite
   #10 = Utf8               testDataFor
   #11 = Utf8               (Ljava/lang/String;Lorg/scalatest/ConfigMap;)Lorg/scalatest/TestData;
   #12 = NameAndType        #10:#11       // testDataFor:(Ljava/lang/String;Lorg/scalatest/ConfigMap;)Lorg/scalatest/TestData;
   #13 = Utf8               configMap
   #14 = Utf8               Lorg/scalatest/ConfigMap;
   #15 = Utf8               name
   #16 = Utf8               Ljava/lang/String;
   #17 = Utf8               scopes
   #18 = Utf8               Lscala/collection/immutable/Vector;
   #19 = Utf8               Lscala/collection/immutable/Vector<Lscala/runtime/Nothing$;>;
   #20 = Utf8               text
   #21 = Utf8               tags
   #22 = Utf8               Lscala/collection/immutable/Set;
   #23 = Utf8               Lscala/collection/immutable/Set<Ljava/lang/String;>;
   #24 = Utf8               pos
   #25 = Utf8               Lscala/None$;
   #26 = Utf8               ()Lorg/scalatest/ConfigMap;
   #27 = NameAndType        #13:#14       // configMap:Lorg/scalatest/ConfigMap;
   #28 = Fieldref           #2.#27        // org/scalatest/Suite$$anon$1.configMap:Lorg/scalatest/ConfigMap;
   #29 = Utf8               this
   #30 = Utf8               Lorg/scalatest/Suite$$anon$1;
   #31 = Utf8               ()Ljava/lang/String;
   #32 = NameAndType        #15:#16       // name:Ljava/lang/String;
   #33 = Fieldref           #2.#32        // org/scalatest/Suite$$anon$1.name:Ljava/lang/String;
   #34 = Utf8               ()Lscala/collection/immutable/Vector;
   #35 = Utf8               ()Lscala/collection/immutable/Vector<Lscala/runtime/Nothing$;>;
   #36 = NameAndType        #17:#18       // scopes:Lscala/collection/immutable/Vector;
   #37 = Fieldref           #2.#36        // org/scalatest/Suite$$anon$1.scopes:Lscala/collection/immutable/Vector;
   #38 = NameAndType        #20:#16       // text:Ljava/lang/String;
   #39 = Fieldref           #2.#38        // org/scalatest/Suite$$anon$1.text:Ljava/lang/String;
   #40 = Utf8               ()Lscala/collection/immutable/Set;
   #41 = Utf8               ()Lscala/collection/immutable/Set<Ljava/lang/String;>;
   #42 = NameAndType        #21:#22       // tags:Lscala/collection/immutable/Set;
   #43 = Fieldref           #2.#42        // org/scalatest/Suite$$anon$1.tags:Lscala/collection/immutable/Set;
   #44 = Utf8               ()Lscala/None$;
   #45 = NameAndType        #24:#25       // pos:Lscala/None$;
   #46 = Fieldref           #2.#45        // org/scalatest/Suite$$anon$1.pos:Lscala/None$;
   #47 = Utf8               ()Lscala/Option;
   #48 = NameAndType        #24:#44       // pos:()Lscala/None$;
   #49 = Methodref          #2.#48        // org/scalatest/Suite$$anon$1.pos:()Lscala/None$;
   #50 = Utf8               ()Lscala/collection/immutable/IndexedSeq;
   #51 = NameAndType        #17:#34       // scopes:()Lscala/collection/immutable/Vector;
   #52 = Methodref          #2.#51        // org/scalatest/Suite$$anon$1.scopes:()Lscala/collection/immutable/Vector;
   #53 = Utf8               <init>
   #54 = Utf8               (Lorg/scalatest/Suite;Lorg/scalatest/ConfigMap;Ljava/lang/String;)V
   #55 = Utf8               $outer
   #56 = Utf8               theConfigMap$1
   #57 = Utf8               testName$2
   #58 = Utf8               ()V
   #59 = NameAndType        #53:#58       // "<init>":()V
   #60 = Methodref          #4.#59        // java/lang/Object."<init>":()V
   #61 = Utf8               scala/package$
   #62 = Class              #61           // scala/package$
   #63 = Utf8               MODULE$
   #64 = Utf8               Lscala/package$;
   #65 = NameAndType        #63:#64       // MODULE$:Lscala/package$;
   #66 = Fieldref           #62.#65       // scala/package$.MODULE$:Lscala/package$;
   #67 = Utf8               Vector
   #68 = Utf8               ()Lscala/collection/immutable/Vector$;
   #69 = NameAndType        #67:#68       // Vector:()Lscala/collection/immutable/Vector$;
   #70 = Methodref          #62.#69       // scala/package$.Vector:()Lscala/collection/immutable/Vector$;
   #71 = Utf8               scala/collection/immutable/Vector$
   #72 = Class              #71           // scala/collection/immutable/Vector$
   #73 = Utf8               empty
   #74 = NameAndType        #73:#34       // empty:()Lscala/collection/immutable/Vector;
   #75 = Methodref          #72.#74       // scala/collection/immutable/Vector$.empty:()Lscala/collection/immutable/Vector;
   #76 = Utf8               scala/Predef$
   #77 = Class              #76           // scala/Predef$
   #78 = Utf8               Lscala/Predef$;
   #79 = NameAndType        #63:#78       // MODULE$:Lscala/Predef$;
   #80 = Fieldref           #77.#79       // scala/Predef$.MODULE$:Lscala/Predef$;
   #81 = Utf8               Set
   #82 = Utf8               ()Lscala/collection/immutable/Set$;
   #83 = NameAndType        #81:#82       // Set:()Lscala/collection/immutable/Set$;
   #84 = Methodref          #77.#83       // scala/Predef$.Set:()Lscala/collection/immutable/Set$;
   #85 = Utf8               scala/collection/immutable/Set$
   #86 = Class              #85           // scala/collection/immutable/Set$
   #87 = NameAndType        #73:#40       // empty:()Lscala/collection/immutable/Set;
   #88 = Methodref          #86.#87       // scala/collection/immutable/Set$.empty:()Lscala/collection/immutable/Set;
   #89 = Utf8               scala/None$
   #90 = Class              #89           // scala/None$
   #91 = NameAndType        #63:#25       // MODULE$:Lscala/None$;
   #92 = Fieldref           #90.#91       // scala/None$.MODULE$:Lscala/None$;
   #93 = Utf8               Lorg/scalatest/Suite;
   #94 = Utf8               Signature
   #95 = Utf8               Code
   #96 = Utf8               LineNumberTable
   #97 = Utf8               LocalVariableTable
   #98 = Utf8               MethodParameters
   #99 = Utf8               InnerClasses
  #100 = Utf8               EnclosingMethod
  #101 = Utf8               SourceFile
  #102 = Utf8               ScalaInlineInfo
  #103 = Utf8               Scala
{
  private final org.scalatest.ConfigMap configMap;
    descriptor: Lorg/scalatest/ConfigMap;
    flags: (0x0012) ACC_PRIVATE, ACC_FINAL

  private final java.lang.String name;
    descriptor: Ljava/lang/String;
    flags: (0x0012) ACC_PRIVATE, ACC_FINAL

  private final scala.collection.immutable.Vector<scala.runtime.Nothing$> scopes;
    descriptor: Lscala/collection/immutable/Vector;
    flags: (0x0012) ACC_PRIVATE, ACC_FINAL
    Signature: #19                          // Lscala/collection/immutable/Vector<Lscala/runtime/Nothing$;>;

  private final java.lang.String text;
    descriptor: Ljava/lang/String;
    flags: (0x0012) ACC_PRIVATE, ACC_FINAL

  private final scala.collection.immutable.Set<java.lang.String> tags;
    descriptor: Lscala/collection/immutable/Set;
    flags: (0x0012) ACC_PRIVATE, ACC_FINAL
    Signature: #23                          // Lscala/collection/immutable/Set<Ljava/lang/String;>;

  private final scala.None$ pos;
    descriptor: Lscala/None$;
    flags: (0x0012) ACC_PRIVATE, ACC_FINAL

  public org.scalatest.ConfigMap configMap();
    descriptor: ()Lorg/scalatest/ConfigMap;
    flags: (0x0001) ACC_PUBLIC
    Code:
      stack=1, locals=1, args_size=1
         0: aload_0
         1: getfield      #28                 // Field configMap:Lorg/scalatest/ConfigMap;
         4: areturn
      LineNumberTable:
        line 1348: 0
      LocalVariableTable:
        Start  Length  Slot  Name   Signature
            0       5     0  this   Lorg/scalatest/Suite$$anon$1;

  public java.lang.String name();
    descriptor: ()Ljava/lang/String;
    flags: (0x0001) ACC_PUBLIC
    Code:
      stack=1, locals=1, args_size=1
         0: aload_0
         1: getfield      #33                 // Field name:Ljava/lang/String;
         4: areturn
      LineNumberTable:
        line 1349: 0
      LocalVariableTable:
        Start  Length  Slot  Name   Signature
            0       5     0  this   Lorg/scalatest/Suite$$anon$1;

  public scala.collection.immutable.Vector<scala.runtime.Nothing$> scopes();
    descriptor: ()Lscala/collection/immutable/Vector;
    flags: (0x0001) ACC_PUBLIC
    Code:
      stack=1, locals=1, args_size=1
         0: aload_0
         1: getfield      #37                 // Field scopes:Lscala/collection/immutable/Vector;
         4: areturn
      LineNumberTable:
        line 1350: 0
      LocalVariableTable:
        Start  Length  Slot  Name   Signature
            0       5     0  this   Lorg/scalatest/Suite$$anon$1;
    Signature: #35                          // ()Lscala/collection/immutable/Vector<Lscala/runtime/Nothing$;>;

  public java.lang.String text();
    descriptor: ()Ljava/lang/String;
    flags: (0x0001) ACC_PUBLIC
    Code:
      stack=1, locals=1, args_size=1
         0: aload_0
         1: getfield      #39                 // Field text:Ljava/lang/String;
         4: areturn
      LineNumberTable:
        line 1351: 0
      LocalVariableTable:
        Start  Length  Slot  Name   Signature
            0       5     0  this   Lorg/scalatest/Suite$$anon$1;

  public scala.collection.immutable.Set<java.lang.String> tags();
    descriptor: ()Lscala/collection/immutable/Set;
    flags: (0x0001) ACC_PUBLIC
    Code:
      stack=1, locals=1, args_size=1
         0: aload_0
         1: getfield      #43                 // Field tags:Lscala/collection/immutable/Set;
         4: areturn
      LineNumberTable:
        line 1352: 0
      LocalVariableTable:
        Start  Length  Slot  Name   Signature
            0       5     0  this   Lorg/scalatest/Suite$$anon$1;
    Signature: #41                          // ()Lscala/collection/immutable/Set<Ljava/lang/String;>;

  public scala.None$ pos();
    descriptor: ()Lscala/None$;
    flags: (0x0001) ACC_PUBLIC
    Code:
      stack=1, locals=1, args_size=1
         0: aload_0
         1: getfield      #46                 // Field pos:Lscala/None$;
         4: areturn
      LineNumberTable:
        line 1353: 0
      LocalVariableTable:
        Start  Length  Slot  Name   Signature
            0       5     0  this   Lorg/scalatest/Suite$$anon$1;

  public scala.Option pos();
    descriptor: ()Lscala/Option;
    flags: (0x1041) ACC_PUBLIC, ACC_BRIDGE, ACC_SYNTHETIC
    Code:
      stack=1, locals=1, args_size=1
         0: aload_0
         1: invokevirtual #49                 // Method pos:()Lscala/None$;
         4: areturn
      LineNumberTable:
        line 1347: 0
      LocalVariableTable:
        Start  Length  Slot  Name   Signature
            0       5     0  this   Lorg/scalatest/Suite$$anon$1;

  public scala.collection.immutable.IndexedSeq scopes();
    descriptor: ()Lscala/collection/immutable/IndexedSeq;
    flags: (0x1041) ACC_PUBLIC, ACC_BRIDGE, ACC_SYNTHETIC
    Code:
      stack=1, locals=1, args_size=1
         0: aload_0
         1: invokevirtual #52                 // Method scopes:()Lscala/collection/immutable/Vector;
         4: areturn
      LineNumberTable:
        line 1347: 0
      LocalVariableTable:
        Start  Length  Slot  Name   Signature
            0       5     0  this   Lorg/scalatest/Suite$$anon$1;

  public org.scalatest.Suite$$anon$1(org.scalatest.Suite, org.scalatest.ConfigMap, java.lang.String);
    descriptor: (Lorg/scalatest/Suite;Lorg/scalatest/ConfigMap;Ljava/lang/String;)V
    flags: (0x0001) ACC_PUBLIC
    Code:
      stack=2, locals=4, args_size=4
         0: aload_0
         1: invokespecial #60                 // Method java/lang/Object."<init>":()V
         4: aload_0
         5: aload_2
         6: putfield      #28                 // Field configMap:Lorg/scalatest/ConfigMap;
         9: aload_0
        10: aload_3
        11: putfield      #33                 // Field name:Ljava/lang/String;
        14: aload_0
        15: getstatic     #66                 // Field scala/package$.MODULE$:Lscala/package$;
        18: invokevirtual #70                 // Method scala/package$.Vector:()Lscala/collection/immutable/Vector$;
        21: invokevirtual #75                 // Method scala/collection/immutable/Vector$.empty:()Lscala/collection/immutable/Vector;
        24: putfield      #37                 // Field scopes:Lscala/collection/immutable/Vector;
        27: aload_0
        28: aload_3
        29: putfield      #39                 // Field text:Ljava/lang/String;
        32: aload_0
        33: getstatic     #80                 // Field scala/Predef$.MODULE$:Lscala/Predef$;
        36: invokevirtual #84                 // Method scala/Predef$.Set:()Lscala/collection/immutable/Set$;
        39: invokevirtual #88                 // Method scala/collection/immutable/Set$.empty:()Lscala/collection/immutable/Set;
        42: putfield      #43                 // Field tags:Lscala/collection/immutable/Set;
        45: aload_0
        46: getstatic     #92                 // Field scala/None$.MODULE$:Lscala/None$;
        49: putfield      #46                 // Field pos:Lscala/None$;
        52: return
      LineNumberTable:
        line 1347: 0
        line 1348: 4
        line 1349: 9
        line 1350: 14
        line 1351: 27
        line 1352: 32
        line 1353: 45
        line 1347: 52
      LocalVariableTable:
        Start  Length  Slot  Name   Signature
            0      53     0  this   Lorg/scalatest/Suite$$anon$1;
            0      53     1 $outer   Lorg/scalatest/Suite;
            0      53     2 theConfigMap$1   Lorg/scalatest/ConfigMap;
            0      53     3 testName$2   Ljava/lang/String;
    MethodParameters:
      Name                           Flags
      $outer                         final synthetic
      theConfigMap$1                 final
      testName$2                     final
}
InnerClasses:
  public final #2;                        // class org/scalatest/Suite$$anon$1
EnclosingMethod: #9.#12                 // org.scalatest.Suite.testDataFor
SourceFile: "Suite.scala"
  ScalaInlineInfo: length = 0x31 (unknown attribute)
   01 01 00 09 00 35 00 36 01 00 0D 00 1A 01 00 0F
   00 1F 01 00 18 00 2C 01 00 18 00 2F 01 00 11 00
   32 01 00 11 00 22 01 00 15 00 28 01 00 14 00 1F
   01
  Scala: length = 0x0 (unknown attribute)

