Classfile /Users/mw/Projects/slang-braindump/.jar/jar8/assemble/slang-braindump/assemble/content/org/scalatest/SuperEngine$Node.class
  Last modified May 29, 2022; size 1907 bytes
  SHA-256 checksum 241558881921c039efcd6b065d190c8a383fe0f4c696c07977173b4626f1905a
  Compiled from "Engine.scala"
public abstract class org.scalatest.SuperEngine$Node
  minor version: 0
  major version: 52
  flags: (0x0421) ACC_PUBLIC, ACC_SUPER, ACC_ABSTRACT
  this_class: #2                          // org/scalatest/SuperEngine$Node
  super_class: #4                         // java/lang/Object
  interfaces: 0, fields: 2, methods: 5, attributes: 4
Constant pool:
   #1 = Utf8               org/scalatest/SuperEngine$Node
   #2 = Class              #1             // org/scalatest/SuperEngine$Node
   #3 = Utf8               java/lang/Object
   #4 = Class              #3             // java/lang/Object
   #5 = Utf8               Engine.scala
   #6 = Utf8               org/scalatest/SuperEngine$Branch
   #7 = Class              #6             // org/scalatest/SuperEngine$Branch
   #8 = Utf8               org/scalatest/SuperEngine
   #9 = Class              #8             // org/scalatest/SuperEngine
  #10 = Utf8               Branch
  #11 = Utf8               Node
  #12 = Utf8               parentOption
  #13 = Utf8               Lscala/Option;
  #14 = Utf8               Lscala/Option<Lorg/scalatest/SuperEngine<TT;>.Branch;>;
  #15 = Utf8               $outer
  #16 = Utf8               Lorg/scalatest/SuperEngine;
  #17 = Utf8               ()Lscala/Option;
  #18 = Utf8               ()Lscala/Option<Lorg/scalatest/SuperEngine<TT;>.Branch;>;
  #19 = NameAndType        #12:#13        // parentOption:Lscala/Option;
  #20 = Fieldref           #2.#19         // org/scalatest/SuperEngine$Node.parentOption:Lscala/Option;
  #21 = Utf8               this
  #22 = Utf8               Lorg/scalatest/SuperEngine$Node;
  #23 = Utf8               indentationLevel
  #24 = Utf8               ()I
  #25 = NameAndType        #12:#17        // parentOption:()Lscala/Option;
  #26 = Methodref          #2.#25         // org/scalatest/SuperEngine$Node.parentOption:()Lscala/Option;
  #27 = Utf8               calcLevel$1
  #28 = Utf8               (Lscala/Option;I)I
  #29 = NameAndType        #27:#28        // calcLevel$1:(Lscala/Option;I)I
  #30 = Methodref          #2.#29         // org/scalatest/SuperEngine$Node.calcLevel$1:(Lscala/Option;I)I
  #31 = Utf8               level
  #32 = Utf8               I
  #33 = Utf8               org$scalatest$SuperEngine$Node$$$outer
  #34 = Utf8               ()Lorg/scalatest/SuperEngine;
  #35 = NameAndType        #15:#16        // $outer:Lorg/scalatest/SuperEngine;
  #36 = Fieldref           #2.#35         // org/scalatest/SuperEngine$Node.$outer:Lorg/scalatest/SuperEngine;
  #37 = Utf8               currentParentOpt
  #38 = Utf8               currentLevel
  #39 = Utf8               scala/None$
  #40 = Class              #39            // scala/None$
  #41 = Utf8               MODULE$
  #42 = Utf8               Lscala/None$;
  #43 = NameAndType        #41:#42        // MODULE$:Lscala/None$;
  #44 = Fieldref           #40.#43        // scala/None$.MODULE$:Lscala/None$;
  #45 = Utf8               equals
  #46 = Utf8               (Ljava/lang/Object;)Z
  #47 = NameAndType        #45:#46        // equals:(Ljava/lang/Object;)Z
  #48 = Methodref          #4.#47         // java/lang/Object.equals:(Ljava/lang/Object;)Z
  #49 = Utf8               scala/Some
  #50 = Class              #49            // scala/Some
  #51 = Utf8               value
  #52 = Utf8               ()Ljava/lang/Object;
  #53 = NameAndType        #51:#52        // value:()Ljava/lang/Object;
  #54 = Methodref          #50.#53        // scala/Some.value:()Ljava/lang/Object;
  #55 = Methodref          #7.#25         // org/scalatest/SuperEngine$Branch.parentOption:()Lscala/Option;
  #56 = Utf8               scala/MatchError
  #57 = Class              #56            // scala/MatchError
  #58 = Utf8               <init>
  #59 = Utf8               (Ljava/lang/Object;)V
  #60 = NameAndType        #58:#59        // "<init>":(Ljava/lang/Object;)V
  #61 = Methodref          #57.#60        // scala/MatchError."<init>":(Ljava/lang/Object;)V
  #62 = Utf8               parent
  #63 = Utf8               Lorg/scalatest/SuperEngine$Branch;
  #64 = Utf8               scala/Option
  #65 = Class              #64            // scala/Option
  #66 = Utf8               (Lorg/scalatest/SuperEngine;Lscala/Option;)V
  #67 = Utf8               (Lscala/Option<Lorg/scalatest/SuperEngine<TT;>.Branch;>;)V
  #68 = Utf8               ()V
  #69 = NameAndType        #58:#68        // "<init>":()V
  #70 = Methodref          #4.#69         // java/lang/Object."<init>":()V
  #71 = Utf8               Signature
  #72 = Utf8               Code
  #73 = Utf8               LineNumberTable
  #74 = Utf8               LocalVariableTable
  #75 = Utf8               StackMapTable
  #76 = Utf8               MethodParameters
  #77 = Utf8               InnerClasses
  #78 = Utf8               SourceFile
  #79 = Utf8               ScalaInlineInfo
  #80 = Utf8               Scala
{
  private final scala.Option<org.scalatest.SuperEngine<T>.Branch> parentOption;
    descriptor: Lscala/Option;
    flags: (0x0012) ACC_PRIVATE, ACC_FINAL
    Signature: #14                          // Lscala/Option<Lorg/scalatest/SuperEngine<TT;>.Branch;>;

  public final org.scalatest.SuperEngine $outer;
    descriptor: Lorg/scalatest/SuperEngine;
    flags: (0x1011) ACC_PUBLIC, ACC_FINAL, ACC_SYNTHETIC

  public scala.Option<org.scalatest.SuperEngine<T>.Branch> parentOption();
    descriptor: ()Lscala/Option;
    flags: (0x0001) ACC_PUBLIC
    Code:
      stack=1, locals=1, args_size=1
         0: aload_0
         1: getfield      #20                 // Field parentOption:Lscala/Option;
         4: areturn
      LineNumberTable:
        line 59: 0
      LocalVariableTable:
        Start  Length  Slot  Name   Signature
            0       5     0  this   Lorg/scalatest/SuperEngine$Node;
    Signature: #18                          // ()Lscala/Option<Lorg/scalatest/SuperEngine<TT;>.Branch;>;

  public int indentationLevel();
    descriptor: ()I
    flags: (0x0001) ACC_PUBLIC
    Code:
      stack=3, locals=2, args_size=1
         0: aload_0
         1: aload_0
         2: invokevirtual #26                 // Method parentOption:()Lscala/Option;
         5: iconst_m1
         6: invokespecial #30                 // Method calcLevel$1:(Lscala/Option;I)I
         9: istore_1
        10: iload_1
        11: iconst_0
        12: if_icmpge     19
        15: iconst_0
        16: goto          20
        19: iload_1
        20: ireturn
      StackMapTable: number_of_entries = 2
        frame_type = 252 /* append */
          offset_delta = 19
          locals = [ int ]
        frame_type = 64 /* same_locals_1_stack_item */
          stack = [ int ]
      LineNumberTable:
        line 66: 0
        line 67: 10
      LocalVariableTable:
        Start  Length  Slot  Name   Signature
           10      10     1 level   I
            0      21     0  this   Lorg/scalatest/SuperEngine$Node;

  public org.scalatest.SuperEngine org$scalatest$SuperEngine$Node$$$outer();
    descriptor: ()Lorg/scalatest/SuperEngine;
    flags: (0x1001) ACC_PUBLIC, ACC_SYNTHETIC
    Code:
      stack=1, locals=1, args_size=1
         0: aload_0
         1: getfield      #36                 // Field $outer:Lorg/scalatest/SuperEngine;
         4: areturn
      LineNumberTable:
        line 59: 0
      LocalVariableTable:
        Start  Length  Slot  Name   Signature
            0       5     0  this   Lorg/scalatest/SuperEngine$Node;

  private final int calcLevel$1(scala.Option, int);
    descriptor: (Lscala/Option;I)I
    flags: (0x0012) ACC_PRIVATE, ACC_FINAL
    Code:
      stack=3, locals=8, args_size=3
         0: aload_1
         1: astore        5
         3: getstatic     #44                 // Field scala/None$.MODULE$:Lscala/None$;
         6: aload         5
         8: invokevirtual #48                 // Method java/lang/Object.equals:(Ljava/lang/Object;)Z
        11: ifeq          20
        14: iload_2
        15: istore        4
        17: goto          74
        20: goto          23
        23: aload         5
        25: instanceof    #50                 // class scala/Some
        28: ifeq          61
        31: aload         5
        33: checkcast     #50                 // class scala/Some
        36: astore        6
        38: aload         6
        40: invokevirtual #54                 // Method scala/Some.value:()Ljava/lang/Object;
        43: checkcast     #7                  // class org/scalatest/SuperEngine$Branch
        46: astore        7
        48: aload         7
        50: invokevirtual #55                 // Method org/scalatest/SuperEngine$Branch.parentOption:()Lscala/Option;
        53: iload_2
        54: iconst_1
        55: iadd
        56: istore_2
        57: astore_1
        58: goto          0
        61: goto          64
        64: new           #57                 // class scala/MatchError
        67: dup
        68: aload         5
        70: invokespecial #61                 // Method scala/MatchError."<init>":(Ljava/lang/Object;)V
        73: athrow
        74: iload         4
        76: ireturn
      StackMapTable: number_of_entries = 6
        frame_type = 0 /* same */
        frame_type = 254 /* append */
          offset_delta = 19
          locals = [ top, top, class scala/Option ]
        frame_type = 2 /* same */
        frame_type = 37 /* same */
        frame_type = 2 /* same */
        frame_type = 255 /* full_frame */
          offset_delta = 9
          locals = [ class org/scalatest/SuperEngine$Node, class scala/Option, int, top, int, class scala/Option ]
          stack = []
      LineNumberTable:
        line 62: 0
        line 63: 3
        line 64: 23
        line 62: 64
      LocalVariableTable:
        Start  Length  Slot  Name   Signature
           48      13     7 parent   Lorg/scalatest/SuperEngine$Branch;
            0      77     0  this   Lorg/scalatest/SuperEngine$Node;
            0      77     1 currentParentOpt   Lscala/Option;
            0      77     2 currentLevel   I
    MethodParameters:
      Name                           Flags
      currentParentOpt               final
      currentLevel                   final

  public org.scalatest.SuperEngine$Node(scala.Option<org.scalatest.SuperEngine<T>.Branch>);
    descriptor: (Lorg/scalatest/SuperEngine;Lscala/Option;)V
    flags: (0x0001) ACC_PUBLIC
    Code:
      stack=2, locals=3, args_size=3
         0: aload_0
         1: aload_2
         2: putfield      #20                 // Field parentOption:Lscala/Option;
         5: aload_1
         6: ifnonnull     11
         9: aconst_null
        10: athrow
        11: aload_0
        12: aload_1
        13: putfield      #36                 // Field $outer:Lorg/scalatest/SuperEngine;
        16: aload_0
        17: invokespecial #70                 // Method java/lang/Object."<init>":()V
        20: return
      StackMapTable: number_of_entries = 1
        frame_type = 11 /* same */
      LineNumberTable:
        line 59: 0
        line 71: 16
        line 59: 20
      LocalVariableTable:
        Start  Length  Slot  Name   Signature
            0      21     0  this   Lorg/scalatest/SuperEngine$Node;
            0      21     1 $outer   Lorg/scalatest/SuperEngine;
            0      21     2 parentOption   Lscala/Option;
    Signature: #67                          // (Lscala/Option<Lorg/scalatest/SuperEngine<TT;>.Branch;>;)V
    MethodParameters:
      Name                           Flags
      $outer                         final synthetic
      parentOption                   final
}
InnerClasses:
  public abstract #10= #7 of #9;          // Branch=class org/scalatest/SuperEngine$Branch of class org/scalatest/SuperEngine
  public abstract #11= #2 of #9;          // Node=class org/scalatest/SuperEngine$Node of class org/scalatest/SuperEngine
SourceFile: "Engine.scala"
  ScalaInlineInfo: length = 0x1D (unknown attribute)
   01 00 00 05 00 3A 00 42 00 00 1B 00 1C 01 00 17
   00 18 00 00 21 00 22 00 00 0C 00 11 00
  Scala: length = 0x0 (unknown attribute)

