Classfile /Users/mw/Projects/slang-braindump/.jar/jar8/assemble/slang-braindump/assemble/content/org/scalatest/SuperEngine$DescriptionBranch.class
  Last modified May 29, 2022; size 5318 bytes
  SHA-256 checksum d72c830fb110ac7ce0004eb26b3fe5ad4c8a8dd7e8e131b05880b6687fb92dd2
  Compiled from "Engine.scala"
public class org.scalatest.SuperEngine$DescriptionBranch extends org.scalatest.SuperEngine<T>.Branch implements scala.Product, java.io.Serializable
  minor version: 0
  major version: 52
  flags: (0x0021) ACC_PUBLIC, ACC_SUPER
  this_class: #2                          // org/scalatest/SuperEngine$DescriptionBranch
  super_class: #5                         // org/scalatest/SuperEngine$Branch
  interfaces: 2, fields: 4, methods: 21, attributes: 5
Constant pool:
    #1 = Utf8               org/scalatest/SuperEngine$DescriptionBranch
    #2 = Class              #1            // org/scalatest/SuperEngine$DescriptionBranch
    #3 = Utf8               Lorg/scalatest/SuperEngine<TT;>.Branch;Lscala/Product;Ljava/io/Serializable;
    #4 = Utf8               org/scalatest/SuperEngine$Branch
    #5 = Class              #4            // org/scalatest/SuperEngine$Branch
    #6 = Utf8               scala/Product
    #7 = Class              #6            // scala/Product
    #8 = Utf8               java/io/Serializable
    #9 = Class              #8            // java/io/Serializable
   #10 = Utf8               Engine.scala
   #11 = Utf8               org/scalatest/SuperEngine
   #12 = Class              #11           // org/scalatest/SuperEngine
   #13 = Utf8               Branch
   #14 = Utf8               DescriptionBranch
   #15 = Utf8               parent
   #16 = Utf8               Lorg/scalatest/SuperEngine$Branch;
   #17 = Utf8               Lorg/scalatest/SuperEngine<TT;>.Branch;
   #18 = Utf8               descriptionText
   #19 = Utf8               Ljava/lang/String;
   #20 = Utf8               childPrefix
   #21 = Utf8               Lscala/Option;
   #22 = Utf8               Lscala/Option<Ljava/lang/String;>;
   #23 = Utf8               location
   #24 = Utf8               Lscala/Option<Lorg/scalatest/events/Location;>;
   #25 = Utf8               productElementNames
   #26 = Utf8               ()Lscala/collection/Iterator;
   #27 = Utf8               ()Lscala/collection/Iterator<Ljava/lang/String;>;
   #28 = Utf8               productElementNames$
   #29 = Utf8               (Lscala/Product;)Lscala/collection/Iterator;
   #30 = NameAndType        #28:#29       // productElementNames$:(Lscala/Product;)Lscala/collection/Iterator;
   #31 = InterfaceMethodref #7.#30        // scala/Product.productElementNames$:(Lscala/Product;)Lscala/collection/Iterator;
   #32 = Utf8               this
   #33 = Utf8               Lorg/scalatest/SuperEngine$DescriptionBranch;
   #34 = Utf8               ()Lorg/scalatest/SuperEngine$Branch;
   #35 = Utf8               ()Lorg/scalatest/SuperEngine<TT;>.Branch;
   #36 = NameAndType        #15:#16       // parent:Lorg/scalatest/SuperEngine$Branch;
   #37 = Fieldref           #2.#36        // org/scalatest/SuperEngine$DescriptionBranch.parent:Lorg/scalatest/SuperEngine$Branch;
   #38 = Utf8               ()Ljava/lang/String;
   #39 = NameAndType        #18:#19       // descriptionText:Ljava/lang/String;
   #40 = Fieldref           #2.#39        // org/scalatest/SuperEngine$DescriptionBranch.descriptionText:Ljava/lang/String;
   #41 = Utf8               ()Lscala/Option;
   #42 = Utf8               ()Lscala/Option<Ljava/lang/String;>;
   #43 = NameAndType        #20:#21       // childPrefix:Lscala/Option;
   #44 = Fieldref           #2.#43        // org/scalatest/SuperEngine$DescriptionBranch.childPrefix:Lscala/Option;
   #45 = Utf8               ()Lscala/Option<Lorg/scalatest/events/Location;>;
   #46 = NameAndType        #23:#21       // location:Lscala/Option;
   #47 = Fieldref           #2.#46        // org/scalatest/SuperEngine$DescriptionBranch.location:Lscala/Option;
   #48 = Utf8               copy
   #49 = Utf8               (Lorg/scalatest/SuperEngine$Branch;Ljava/lang/String;Lscala/Option;Lscala/Option;)Lorg/scalatest/SuperEngine$DescriptionBranch;
   #50 = Utf8               (Lorg/scalatest/SuperEngine<TT;>.Branch;Ljava/lang/String;Lscala/Option<Ljava/lang/String;>;Lscala/Option<Lorg/scalatest/events/Location;>;)Lorg/scalatest/SuperEngine<TT;>.DescriptionBranch;
   #51 = Utf8               org$scalatest$SuperEngine$DescriptionBranch$$$outer
   #52 = Utf8               ()Lorg/scalatest/SuperEngine;
   #53 = NameAndType        #51:#52       // org$scalatest$SuperEngine$DescriptionBranch$$$outer:()Lorg/scalatest/SuperEngine;
   #54 = Methodref          #2.#53        // org/scalatest/SuperEngine$DescriptionBranch.org$scalatest$SuperEngine$DescriptionBranch$$$outer:()Lorg/scalatest/SuperEngine;
   #55 = Utf8               <init>
   #56 = Utf8               (Lorg/scalatest/SuperEngine;Lorg/scalatest/SuperEngine$Branch;Ljava/lang/String;Lscala/Option;Lscala/Option;)V
   #57 = NameAndType        #55:#56       // "<init>":(Lorg/scalatest/SuperEngine;Lorg/scalatest/SuperEngine$Branch;Ljava/lang/String;Lscala/Option;Lscala/Option;)V
   #58 = Methodref          #2.#57        // org/scalatest/SuperEngine$DescriptionBranch."<init>":(Lorg/scalatest/SuperEngine;Lorg/scalatest/SuperEngine$Branch;Ljava/lang/String;Lscala/Option;Lscala/Option;)V
   #59 = Utf8               copy$default$1
   #60 = NameAndType        #15:#34       // parent:()Lorg/scalatest/SuperEngine$Branch;
   #61 = Methodref          #2.#60        // org/scalatest/SuperEngine$DescriptionBranch.parent:()Lorg/scalatest/SuperEngine$Branch;
   #62 = Utf8               copy$default$2
   #63 = NameAndType        #18:#38       // descriptionText:()Ljava/lang/String;
   #64 = Methodref          #2.#63        // org/scalatest/SuperEngine$DescriptionBranch.descriptionText:()Ljava/lang/String;
   #65 = Utf8               copy$default$3
   #66 = NameAndType        #20:#41       // childPrefix:()Lscala/Option;
   #67 = Methodref          #2.#66        // org/scalatest/SuperEngine$DescriptionBranch.childPrefix:()Lscala/Option;
   #68 = Utf8               copy$default$4
   #69 = NameAndType        #23:#41       // location:()Lscala/Option;
   #70 = Methodref          #2.#69        // org/scalatest/SuperEngine$DescriptionBranch.location:()Lscala/Option;
   #71 = Utf8               productPrefix
   #72 = String             #14           // DescriptionBranch
   #73 = Utf8               productArity
   #74 = Utf8               ()I
   #75 = Utf8               productElement
   #76 = Utf8               (I)Ljava/lang/Object;
   #77 = Utf8               x$1
   #78 = Utf8               scala/runtime/Statics
   #79 = Class              #78           // scala/runtime/Statics
   #80 = Utf8               ioobe
   #81 = NameAndType        #80:#76       // ioobe:(I)Ljava/lang/Object;
   #82 = Methodref          #79.#81       // scala/runtime/Statics.ioobe:(I)Ljava/lang/Object;
   #83 = Utf8               I
   #84 = Utf8               java/lang/Object
   #85 = Class              #84           // java/lang/Object
   #86 = Utf8               productIterator
   #87 = Utf8               ()Lscala/collection/Iterator<Ljava/lang/Object;>;
   #88 = Utf8               scala/runtime/ScalaRunTime$
   #89 = Class              #88           // scala/runtime/ScalaRunTime$
   #90 = Utf8               MODULE$
   #91 = Utf8               Lscala/runtime/ScalaRunTime$;
   #92 = NameAndType        #90:#91       // MODULE$:Lscala/runtime/ScalaRunTime$;
   #93 = Fieldref           #89.#92       // scala/runtime/ScalaRunTime$.MODULE$:Lscala/runtime/ScalaRunTime$;
   #94 = Utf8               typedProductIterator
   #95 = NameAndType        #94:#29       // typedProductIterator:(Lscala/Product;)Lscala/collection/Iterator;
   #96 = Methodref          #89.#95       // scala/runtime/ScalaRunTime$.typedProductIterator:(Lscala/Product;)Lscala/collection/Iterator;
   #97 = Utf8               canEqual
   #98 = Utf8               (Ljava/lang/Object;)Z
   #99 = Utf8               Ljava/lang/Object;
  #100 = Utf8               productElementName
  #101 = Utf8               (I)Ljava/lang/String;
  #102 = String             #15           // parent
  #103 = String             #18           // descriptionText
  #104 = String             #20           // childPrefix
  #105 = String             #23           // location
  #106 = Utf8               java/lang/String
  #107 = Class              #106          // java/lang/String
  #108 = Utf8               hashCode
  #109 = Utf8               _hashCode
  #110 = Utf8               (Lscala/Product;)I
  #111 = NameAndType        #109:#110     // _hashCode:(Lscala/Product;)I
  #112 = Methodref          #89.#111      // scala/runtime/ScalaRunTime$._hashCode:(Lscala/Product;)I
  #113 = Utf8               toString
  #114 = Utf8               _toString
  #115 = Utf8               (Lscala/Product;)Ljava/lang/String;
  #116 = NameAndType        #114:#115     // _toString:(Lscala/Product;)Ljava/lang/String;
  #117 = Methodref          #89.#116      // scala/runtime/ScalaRunTime$._toString:(Lscala/Product;)Ljava/lang/String;
  #118 = Utf8               equals
  #119 = NameAndType        #118:#98      // equals:(Ljava/lang/Object;)Z
  #120 = Methodref          #85.#119      // java/lang/Object.equals:(Ljava/lang/Object;)Z
  #121 = NameAndType        #97:#98       // canEqual:(Ljava/lang/Object;)Z
  #122 = Methodref          #2.#121       // org/scalatest/SuperEngine$DescriptionBranch.canEqual:(Ljava/lang/Object;)Z
  #123 = Utf8               scala/Option
  #124 = Class              #123          // scala/Option
  #125 = Utf8               $outer
  #126 = Utf8               Lorg/scalatest/SuperEngine;
  #127 = NameAndType        #125:#126     // $outer:Lorg/scalatest/SuperEngine;
  #128 = Fieldref           #2.#127       // org/scalatest/SuperEngine$DescriptionBranch.$outer:Lorg/scalatest/SuperEngine;
  #129 = Utf8               (Lorg/scalatest/SuperEngine<TT;>.Branch;Ljava/lang/String;Lscala/Option<Ljava/lang/String;>;Lscala/Option<Lorg/scalatest/events/Location;>;)V
  #130 = Utf8               scala/Some
  #131 = Class              #130          // scala/Some
  #132 = Utf8               (Ljava/lang/Object;)V
  #133 = NameAndType        #55:#132      // "<init>":(Ljava/lang/Object;)V
  #134 = Methodref          #131.#133     // scala/Some."<init>":(Ljava/lang/Object;)V
  #135 = Utf8               (Lorg/scalatest/SuperEngine;Lscala/Option;)V
  #136 = NameAndType        #55:#135      // "<init>":(Lorg/scalatest/SuperEngine;Lscala/Option;)V
  #137 = Methodref          #5.#136       // org/scalatest/SuperEngine$Branch."<init>":(Lorg/scalatest/SuperEngine;Lscala/Option;)V
  #138 = Utf8               $init$
  #139 = Utf8               (Lscala/Product;)V
  #140 = NameAndType        #138:#139     // $init$:(Lscala/Product;)V
  #141 = InterfaceMethodref #7.#140       // scala/Product.$init$:(Lscala/Product;)V
  #142 = Utf8               Signature
  #143 = Utf8               Code
  #144 = Utf8               LineNumberTable
  #145 = Utf8               LocalVariableTable
  #146 = Utf8               MethodParameters
  #147 = Utf8               StackMapTable
  #148 = Utf8               InnerClasses
  #149 = Utf8               SourceFile
  #150 = Utf8               ScalaInlineInfo
  #151 = Utf8               Scala
{
  private final org.scalatest.SuperEngine<T>.Branch parent;
    descriptor: Lorg/scalatest/SuperEngine$Branch;
    flags: (0x0012) ACC_PRIVATE, ACC_FINAL
    Signature: #17                          // Lorg/scalatest/SuperEngine<TT;>.Branch;

  private final java.lang.String descriptionText;
    descriptor: Ljava/lang/String;
    flags: (0x0012) ACC_PRIVATE, ACC_FINAL

  private final scala.Option<java.lang.String> childPrefix;
    descriptor: Lscala/Option;
    flags: (0x0012) ACC_PRIVATE, ACC_FINAL
    Signature: #22                          // Lscala/Option<Ljava/lang/String;>;

  private final scala.Option<org.scalatest.events.Location> location;
    descriptor: Lscala/Option;
    flags: (0x0012) ACC_PRIVATE, ACC_FINAL
    Signature: #24                          // Lscala/Option<Lorg/scalatest/events/Location;>;

  public scala.collection.Iterator<java.lang.String> productElementNames();
    descriptor: ()Lscala/collection/Iterator;
    flags: (0x0001) ACC_PUBLIC
    Code:
      stack=1, locals=1, args_size=1
         0: aload_0
         1: invokestatic  #31                 // InterfaceMethod scala/Product.productElementNames$:(Lscala/Product;)Lscala/collection/Iterator;
         4: areturn
      LineNumberTable:
        line 98: 0
      LocalVariableTable:
        Start  Length  Slot  Name   Signature
            0       5     0  this   Lorg/scalatest/SuperEngine$DescriptionBranch;
    Signature: #27                          // ()Lscala/collection/Iterator<Ljava/lang/String;>;

  public org.scalatest.SuperEngine<T>.Branch parent();
    descriptor: ()Lorg/scalatest/SuperEngine$Branch;
    flags: (0x0001) ACC_PUBLIC
    Code:
      stack=1, locals=1, args_size=1
         0: aload_0
         1: getfield      #37                 // Field parent:Lorg/scalatest/SuperEngine$Branch;
         4: areturn
      LineNumberTable:
        line 99: 0
      LocalVariableTable:
        Start  Length  Slot  Name   Signature
            0       5     0  this   Lorg/scalatest/SuperEngine$DescriptionBranch;
    Signature: #35                          // ()Lorg/scalatest/SuperEngine<TT;>.Branch;

  public java.lang.String descriptionText();
    descriptor: ()Ljava/lang/String;
    flags: (0x0001) ACC_PUBLIC
    Code:
      stack=1, locals=1, args_size=1
         0: aload_0
         1: getfield      #40                 // Field descriptionText:Ljava/lang/String;
         4: areturn
      LineNumberTable:
        line 100: 0
      LocalVariableTable:
        Start  Length  Slot  Name   Signature
            0       5     0  this   Lorg/scalatest/SuperEngine$DescriptionBranch;

  public scala.Option<java.lang.String> childPrefix();
    descriptor: ()Lscala/Option;
    flags: (0x0001) ACC_PUBLIC
    Code:
      stack=1, locals=1, args_size=1
         0: aload_0
         1: getfield      #44                 // Field childPrefix:Lscala/Option;
         4: areturn
      LineNumberTable:
        line 101: 0
      LocalVariableTable:
        Start  Length  Slot  Name   Signature
            0       5     0  this   Lorg/scalatest/SuperEngine$DescriptionBranch;
    Signature: #42                          // ()Lscala/Option<Ljava/lang/String;>;

  public scala.Option<org.scalatest.events.Location> location();
    descriptor: ()Lscala/Option;
    flags: (0x0001) ACC_PUBLIC
    Code:
      stack=1, locals=1, args_size=1
         0: aload_0
         1: getfield      #47                 // Field location:Lscala/Option;
         4: areturn
      LineNumberTable:
        line 102: 0
      LocalVariableTable:
        Start  Length  Slot  Name   Signature
            0       5     0  this   Lorg/scalatest/SuperEngine$DescriptionBranch;
    Signature: #45                          // ()Lscala/Option<Lorg/scalatest/events/Location;>;

  public org.scalatest.SuperEngine<T>.DescriptionBranch copy(org.scalatest.SuperEngine<T>.Branch, java.lang.String, scala.Option<java.lang.String>, scala.Option<org.scalatest.events.Location>);
    descriptor: (Lorg/scalatest/SuperEngine$Branch;Ljava/lang/String;Lscala/Option;Lscala/Option;)Lorg/scalatest/SuperEngine$DescriptionBranch;
    flags: (0x0001) ACC_PUBLIC
    Code:
      stack=7, locals=5, args_size=5
         0: new           #2                  // class org/scalatest/SuperEngine$DescriptionBranch
         3: dup
         4: aload_0
         5: invokevirtual #54                 // Method org$scalatest$SuperEngine$DescriptionBranch$$$outer:()Lorg/scalatest/SuperEngine;
         8: aload_1
         9: aload_2
        10: aload_3
        11: aload         4
        13: invokespecial #58                 // Method "<init>":(Lorg/scalatest/SuperEngine;Lorg/scalatest/SuperEngine$Branch;Ljava/lang/String;Lscala/Option;Lscala/Option;)V
        16: areturn
      LineNumberTable:
        line 98: 0
        line 99: 8
        line 100: 9
        line 101: 10
        line 102: 11
      LocalVariableTable:
        Start  Length  Slot  Name   Signature
            0      17     0  this   Lorg/scalatest/SuperEngine$DescriptionBranch;
            0      17     1 parent   Lorg/scalatest/SuperEngine$Branch;
            0      17     2 descriptionText   Ljava/lang/String;
            0      17     3 childPrefix   Lscala/Option;
            0      17     4 location   Lscala/Option;
    Signature: #50                          // (Lorg/scalatest/SuperEngine<TT;>.Branch;Ljava/lang/String;Lscala/Option<Ljava/lang/String;>;Lscala/Option<Lorg/scalatest/events/Location;>;)Lorg/scalatest/SuperEngine<TT;>.DescriptionBranch;
    MethodParameters:
      Name                           Flags
      parent                         final
      descriptionText                final
      childPrefix                    final
      location                       final

  public org.scalatest.SuperEngine<T>.Branch copy$default$1();
    descriptor: ()Lorg/scalatest/SuperEngine$Branch;
    flags: (0x0001) ACC_PUBLIC
    Code:
      stack=1, locals=1, args_size=1
         0: aload_0
         1: invokevirtual #61                 // Method parent:()Lorg/scalatest/SuperEngine$Branch;
         4: areturn
      LineNumberTable:
        line 99: 0
      LocalVariableTable:
        Start  Length  Slot  Name   Signature
            0       5     0  this   Lorg/scalatest/SuperEngine$DescriptionBranch;
    Signature: #35                          // ()Lorg/scalatest/SuperEngine<TT;>.Branch;

  public java.lang.String copy$default$2();
    descriptor: ()Ljava/lang/String;
    flags: (0x0001) ACC_PUBLIC
    Code:
      stack=1, locals=1, args_size=1
         0: aload_0
         1: invokevirtual #64                 // Method descriptionText:()Ljava/lang/String;
         4: areturn
      LineNumberTable:
        line 100: 0
      LocalVariableTable:
        Start  Length  Slot  Name   Signature
            0       5     0  this   Lorg/scalatest/SuperEngine$DescriptionBranch;

  public scala.Option<java.lang.String> copy$default$3();
    descriptor: ()Lscala/Option;
    flags: (0x0001) ACC_PUBLIC
    Code:
      stack=1, locals=1, args_size=1
         0: aload_0
         1: invokevirtual #67                 // Method childPrefix:()Lscala/Option;
         4: areturn
      LineNumberTable:
        line 101: 0
      LocalVariableTable:
        Start  Length  Slot  Name   Signature
            0       5     0  this   Lorg/scalatest/SuperEngine$DescriptionBranch;
    Signature: #42                          // ()Lscala/Option<Ljava/lang/String;>;

  public scala.Option<org.scalatest.events.Location> copy$default$4();
    descriptor: ()Lscala/Option;
    flags: (0x0001) ACC_PUBLIC
    Code:
      stack=1, locals=1, args_size=1
         0: aload_0
         1: invokevirtual #70                 // Method location:()Lscala/Option;
         4: areturn
      LineNumberTable:
        line 102: 0
      LocalVariableTable:
        Start  Length  Slot  Name   Signature
            0       5     0  this   Lorg/scalatest/SuperEngine$DescriptionBranch;
    Signature: #45                          // ()Lscala/Option<Lorg/scalatest/events/Location;>;

  public java.lang.String productPrefix();
    descriptor: ()Ljava/lang/String;
    flags: (0x0001) ACC_PUBLIC
    Code:
      stack=1, locals=1, args_size=1
         0: ldc           #72                 // String DescriptionBranch
         2: areturn
      LineNumberTable:
        line 98: 0
      LocalVariableTable:
        Start  Length  Slot  Name   Signature
            0       3     0  this   Lorg/scalatest/SuperEngine$DescriptionBranch;

  public int productArity();
    descriptor: ()I
    flags: (0x0001) ACC_PUBLIC
    Code:
      stack=1, locals=1, args_size=1
         0: iconst_4
         1: ireturn
      LineNumberTable:
        line 98: 0
      LocalVariableTable:
        Start  Length  Slot  Name   Signature
            0       2     0  this   Lorg/scalatest/SuperEngine$DescriptionBranch;

  public java.lang.Object productElement(int);
    descriptor: (I)Ljava/lang/Object;
    flags: (0x0001) ACC_PUBLIC
    Code:
      stack=1, locals=3, args_size=2
         0: iload_1
         1: istore_2
         2: iload_2
         3: tableswitch   { // 0 to 3
                       0: 32
                       1: 39
                       2: 46
                       3: 53
                 default: 60
            }
        32: aload_0
        33: invokevirtual #61                 // Method parent:()Lorg/scalatest/SuperEngine$Branch;
        36: goto          67
        39: aload_0
        40: invokevirtual #64                 // Method descriptionText:()Ljava/lang/String;
        43: goto          67
        46: aload_0
        47: invokevirtual #67                 // Method childPrefix:()Lscala/Option;
        50: goto          67
        53: aload_0
        54: invokevirtual #70                 // Method location:()Lscala/Option;
        57: goto          67
        60: iload_1
        61: invokestatic  #82                 // Method scala/runtime/Statics.ioobe:(I)Ljava/lang/Object;
        64: goto          67
        67: areturn
      StackMapTable: number_of_entries = 6
        frame_type = 252 /* append */
          offset_delta = 32
          locals = [ int ]
        frame_type = 6 /* same */
        frame_type = 6 /* same */
        frame_type = 6 /* same */
        frame_type = 6 /* same */
        frame_type = 70 /* same_locals_1_stack_item */
          stack = [ class java/lang/Object ]
      LineNumberTable:
        line 98: 0
      LocalVariableTable:
        Start  Length  Slot  Name   Signature
            0      68     0  this   Lorg/scalatest/SuperEngine$DescriptionBranch;
            0      68     1   x$1   I
    MethodParameters:
      Name                           Flags
      x$1                            final

  public scala.collection.Iterator<java.lang.Object> productIterator();
    descriptor: ()Lscala/collection/Iterator;
    flags: (0x0001) ACC_PUBLIC
    Code:
      stack=2, locals=1, args_size=1
         0: getstatic     #93                 // Field scala/runtime/ScalaRunTime$.MODULE$:Lscala/runtime/ScalaRunTime$;
         3: aload_0
         4: invokevirtual #96                 // Method scala/runtime/ScalaRunTime$.typedProductIterator:(Lscala/Product;)Lscala/collection/Iterator;
         7: areturn
      LineNumberTable:
        line 98: 0
      LocalVariableTable:
        Start  Length  Slot  Name   Signature
            0       8     0  this   Lorg/scalatest/SuperEngine$DescriptionBranch;
    Signature: #87                          // ()Lscala/collection/Iterator<Ljava/lang/Object;>;

  public boolean canEqual(java.lang.Object);
    descriptor: (Ljava/lang/Object;)Z
    flags: (0x0001) ACC_PUBLIC
    Code:
      stack=1, locals=2, args_size=2
         0: aload_1
         1: instanceof    #2                  // class org/scalatest/SuperEngine$DescriptionBranch
         4: ireturn
      LineNumberTable:
        line 98: 0
      LocalVariableTable:
        Start  Length  Slot  Name   Signature
            0       5     0  this   Lorg/scalatest/SuperEngine$DescriptionBranch;
            0       5     1   x$1   Ljava/lang/Object;
    MethodParameters:
      Name                           Flags
      x$1                            final

  public java.lang.String productElementName(int);
    descriptor: (I)Ljava/lang/String;
    flags: (0x0001) ACC_PUBLIC
    Code:
      stack=1, locals=3, args_size=2
         0: iload_1
         1: istore_2
         2: iload_2
         3: tableswitch   { // 0 to 3
                       0: 32
                       1: 37
                       2: 42
                       3: 47
                 default: 52
            }
        32: ldc           #102                // String parent
        34: goto          62
        37: ldc           #103                // String descriptionText
        39: goto          62
        42: ldc           #104                // String childPrefix
        44: goto          62
        47: ldc           #105                // String location
        49: goto          62
        52: iload_1
        53: invokestatic  #82                 // Method scala/runtime/Statics.ioobe:(I)Ljava/lang/Object;
        56: checkcast     #107                // class java/lang/String
        59: goto          62
        62: areturn
      StackMapTable: number_of_entries = 6
        frame_type = 252 /* append */
          offset_delta = 32
          locals = [ int ]
        frame_type = 4 /* same */
        frame_type = 4 /* same */
        frame_type = 4 /* same */
        frame_type = 4 /* same */
        frame_type = 73 /* same_locals_1_stack_item */
          stack = [ class java/lang/String ]
      LineNumberTable:
        line 98: 0
      LocalVariableTable:
        Start  Length  Slot  Name   Signature
            0      63     0  this   Lorg/scalatest/SuperEngine$DescriptionBranch;
            0      63     1   x$1   I
    MethodParameters:
      Name                           Flags
      x$1                            final

  public int hashCode();
    descriptor: ()I
    flags: (0x0001) ACC_PUBLIC
    Code:
      stack=2, locals=1, args_size=1
         0: getstatic     #93                 // Field scala/runtime/ScalaRunTime$.MODULE$:Lscala/runtime/ScalaRunTime$;
         3: aload_0
         4: invokevirtual #112                // Method scala/runtime/ScalaRunTime$._hashCode:(Lscala/Product;)I
         7: ireturn
      LineNumberTable:
        line 98: 0
      LocalVariableTable:
        Start  Length  Slot  Name   Signature
            0       8     0  this   Lorg/scalatest/SuperEngine$DescriptionBranch;

  public java.lang.String toString();
    descriptor: ()Ljava/lang/String;
    flags: (0x0001) ACC_PUBLIC
    Code:
      stack=2, locals=1, args_size=1
         0: getstatic     #93                 // Field scala/runtime/ScalaRunTime$.MODULE$:Lscala/runtime/ScalaRunTime$;
         3: aload_0
         4: invokevirtual #117                // Method scala/runtime/ScalaRunTime$._toString:(Lscala/Product;)Ljava/lang/String;
         7: areturn
      LineNumberTable:
        line 98: 0
      LocalVariableTable:
        Start  Length  Slot  Name   Signature
            0       8     0  this   Lorg/scalatest/SuperEngine$DescriptionBranch;

  public boolean equals(java.lang.Object);
    descriptor: (Ljava/lang/Object;)Z
    flags: (0x0001) ACC_PUBLIC
    Code:
      stack=2, locals=9, args_size=2
         0: aload_0
         1: aload_1
         2: if_acmpeq     196
         5: aload_1
         6: astore_3
         7: aload_3
         8: instanceof    #2                  // class org/scalatest/SuperEngine$DescriptionBranch
        11: ifeq          33
        14: aload_3
        15: checkcast     #2                  // class org/scalatest/SuperEngine$DescriptionBranch
        18: invokevirtual #54                 // Method org$scalatest$SuperEngine$DescriptionBranch$$$outer:()Lorg/scalatest/SuperEngine;
        21: aload_0
        22: invokevirtual #54                 // Method org$scalatest$SuperEngine$DescriptionBranch$$$outer:()Lorg/scalatest/SuperEngine;
        25: if_acmpne     33
        28: iconst_1
        29: istore_2
        30: goto          41
        33: goto          36
        36: iconst_0
        37: istore_2
        38: goto          41
        41: iload_2
        42: ifeq          200
        45: aload_1
        46: checkcast     #2                  // class org/scalatest/SuperEngine$DescriptionBranch
        49: astore        4
        51: aload_0
        52: invokevirtual #61                 // Method parent:()Lorg/scalatest/SuperEngine$Branch;
        55: aload         4
        57: invokevirtual #61                 // Method parent:()Lorg/scalatest/SuperEngine$Branch;
        60: astore        5
        62: dup
        63: ifnonnull     75
        66: pop
        67: aload         5
        69: ifnull        83
        72: goto          192
        75: aload         5
        77: invokevirtual #120                // Method java/lang/Object.equals:(Ljava/lang/Object;)Z
        80: ifeq          192
        83: aload_0
        84: invokevirtual #64                 // Method descriptionText:()Ljava/lang/String;
        87: aload         4
        89: invokevirtual #64                 // Method descriptionText:()Ljava/lang/String;
        92: astore        6
        94: dup
        95: ifnonnull     107
        98: pop
        99: aload         6
       101: ifnull        115
       104: goto          192
       107: aload         6
       109: invokevirtual #120                // Method java/lang/Object.equals:(Ljava/lang/Object;)Z
       112: ifeq          192
       115: aload_0
       116: invokevirtual #67                 // Method childPrefix:()Lscala/Option;
       119: aload         4
       121: invokevirtual #67                 // Method childPrefix:()Lscala/Option;
       124: astore        7
       126: dup
       127: ifnonnull     139
       130: pop
       131: aload         7
       133: ifnull        147
       136: goto          192
       139: aload         7
       141: invokevirtual #120                // Method java/lang/Object.equals:(Ljava/lang/Object;)Z
       144: ifeq          192
       147: aload_0
       148: invokevirtual #70                 // Method location:()Lscala/Option;
       151: aload         4
       153: invokevirtual #70                 // Method location:()Lscala/Option;
       156: astore        8
       158: dup
       159: ifnonnull     171
       162: pop
       163: aload         8
       165: ifnull        179
       168: goto          192
       171: aload         8
       173: invokevirtual #120                // Method java/lang/Object.equals:(Ljava/lang/Object;)Z
       176: ifeq          192
       179: aload         4
       181: aload_0
       182: invokevirtual #122                // Method canEqual:(Ljava/lang/Object;)Z
       185: ifeq          192
       188: iconst_1
       189: goto          193
       192: iconst_0
       193: ifeq          200
       196: iconst_1
       197: goto          201
       200: iconst_0
       201: ireturn
      StackMapTable: number_of_entries = 16
        frame_type = 253 /* append */
          offset_delta = 33
          locals = [ top, class java/lang/Object ]
        frame_type = 2 /* same */
        frame_type = 255 /* full_frame */
          offset_delta = 4
          locals = [ class org/scalatest/SuperEngine$DescriptionBranch, class java/lang/Object, int, class java/lang/Object ]
          stack = []
        frame_type = 255 /* full_frame */
          offset_delta = 33
          locals = [ class org/scalatest/SuperEngine$DescriptionBranch, class java/lang/Object, int, class java/lang/Object, class org/scalatest/SuperEngine$DescriptionBranch, class org/scalatest/SuperEngine$Branch ]
          stack = [ class org/scalatest/SuperEngine$Branch ]
        frame_type = 7 /* same */
        frame_type = 255 /* full_frame */
          offset_delta = 23
          locals = [ class org/scalatest/SuperEngine$DescriptionBranch, class java/lang/Object, int, class java/lang/Object, class org/scalatest/SuperEngine$DescriptionBranch, class org/scalatest/SuperEngine$Branch, class java/lang/String ]
          stack = [ class java/lang/String ]
        frame_type = 7 /* same */
        frame_type = 255 /* full_frame */
          offset_delta = 23
          locals = [ class org/scalatest/SuperEngine$DescriptionBranch, class java/lang/Object, int, class java/lang/Object, class org/scalatest/SuperEngine$DescriptionBranch, class org/scalatest/SuperEngine$Branch, class java/lang/String, class scala/Option ]
          stack = [ class scala/Option ]
        frame_type = 7 /* same */
        frame_type = 255 /* full_frame */
          offset_delta = 23
          locals = [ class org/scalatest/SuperEngine$DescriptionBranch, class java/lang/Object, int, class java/lang/Object, class org/scalatest/SuperEngine$DescriptionBranch, class org/scalatest/SuperEngine$Branch, class java/lang/String, class scala/Option, class scala/Option ]
          stack = [ class scala/Option ]
        frame_type = 7 /* same */
        frame_type = 248 /* chop */
          offset_delta = 12
        frame_type = 64 /* same_locals_1_stack_item */
          stack = [ int ]
        frame_type = 255 /* full_frame */
          offset_delta = 2
          locals = [ class org/scalatest/SuperEngine$DescriptionBranch, class java/lang/Object ]
          stack = []
        frame_type = 253 /* append */
          offset_delta = 3
          locals = [ int, class java/lang/Object ]
        frame_type = 255 /* full_frame */
          offset_delta = 0
          locals = [ class org/scalatest/SuperEngine$DescriptionBranch, class java/lang/Object ]
          stack = [ int ]
      LineNumberTable:
        line 98: 0
      LocalVariableTable:
        Start  Length  Slot  Name   Signature
            0     202     0  this   Lorg/scalatest/SuperEngine$DescriptionBranch;
            0     202     1   x$1   Ljava/lang/Object;
    MethodParameters:
      Name                           Flags
      x$1                            final

  public org.scalatest.SuperEngine org$scalatest$SuperEngine$DescriptionBranch$$$outer();
    descriptor: ()Lorg/scalatest/SuperEngine;
    flags: (0x1001) ACC_PUBLIC, ACC_SYNTHETIC
    Code:
      stack=1, locals=1, args_size=1
         0: aload_0
         1: getfield      #128                // Field $outer:Lorg/scalatest/SuperEngine;
         4: areturn
      LineNumberTable:
        line 98: 0
      LocalVariableTable:
        Start  Length  Slot  Name   Signature
            0       5     0  this   Lorg/scalatest/SuperEngine$DescriptionBranch;

  public org.scalatest.SuperEngine$DescriptionBranch(org.scalatest.SuperEngine<T>.Branch, java.lang.String, scala.Option<java.lang.String>, scala.Option<org.scalatest.events.Location>);
    descriptor: (Lorg/scalatest/SuperEngine;Lorg/scalatest/SuperEngine$Branch;Ljava/lang/String;Lscala/Option;Lscala/Option;)V
    flags: (0x0001) ACC_PUBLIC
    Code:
      stack=5, locals=6, args_size=6
         0: aload_0
         1: aload_2
         2: putfield      #37                 // Field parent:Lorg/scalatest/SuperEngine$Branch;
         5: aload_0
         6: aload_3
         7: putfield      #40                 // Field descriptionText:Ljava/lang/String;
        10: aload_0
        11: aload         4
        13: putfield      #44                 // Field childPrefix:Lscala/Option;
        16: aload_0
        17: aload         5
        19: putfield      #47                 // Field location:Lscala/Option;
        22: aload_0
        23: aload_1
        24: new           #131                // class scala/Some
        27: dup
        28: aload_2
        29: invokespecial #134                // Method scala/Some."<init>":(Ljava/lang/Object;)V
        32: invokespecial #137                // Method org/scalatest/SuperEngine$Branch."<init>":(Lorg/scalatest/SuperEngine;Lscala/Option;)V
        35: aload_0
        36: invokestatic  #141                // InterfaceMethod scala/Product.$init$:(Lscala/Product;)V
        39: return
      LineNumberTable:
        line 99: 0
        line 100: 5
        line 101: 10
        line 102: 16
        line 103: 22
        line 98: 39
      LocalVariableTable:
        Start  Length  Slot  Name   Signature
            0      40     0  this   Lorg/scalatest/SuperEngine$DescriptionBranch;
            0      40     1 $outer   Lorg/scalatest/SuperEngine;
            0      40     2 parent   Lorg/scalatest/SuperEngine$Branch;
            0      40     3 descriptionText   Ljava/lang/String;
            0      40     4 childPrefix   Lscala/Option;
            0      40     5 location   Lscala/Option;
    Signature: #129                         // (Lorg/scalatest/SuperEngine<TT;>.Branch;Ljava/lang/String;Lscala/Option<Ljava/lang/String;>;Lscala/Option<Lorg/scalatest/events/Location;>;)V
    MethodParameters:
      Name                           Flags
      $outer                         final synthetic
      parent                         final
      descriptionText                final
      childPrefix                    final
      location                       final
}
InnerClasses:
  public abstract #13= #5 of #12;         // Branch=class org/scalatest/SuperEngine$Branch of class org/scalatest/SuperEngine
  public #14= #2 of #12;                  // DescriptionBranch=class org/scalatest/SuperEngine$DescriptionBranch of class org/scalatest/SuperEngine
Signature: #3                           // Lorg/scalatest/SuperEngine<TT;>.Branch;Lscala/Product;Ljava/io/Serializable;
SourceFile: "Engine.scala"
  ScalaInlineInfo: length = 0x6D (unknown attribute)
   01 00 00 15 00 37 00 38 00 00 61 00 62 00 00 14
   00 29 00 00 30 00 31 00 00 3B 00 22 00 00 3E 00
   26 00 00 41 00 29 00 00 44 00 29 00 00 12 00 26
   00 00 76 00 62 00 00 6C 00 4A 00 00 17 00 29 00
   00 33 00 34 00 00 0F 00 22 00 00 49 00 4A 00 00
   4B 00 4C 00 00 64 00 65 00 00 19 00 1A 00 00 56
   00 1A 00 00 47 00 26 00 00 71 00 26 00
  Scala: length = 0x0 (unknown attribute)

