Classfile /Users/mw/Projects/slang-braindump/.jar/jar8/assemble/slang-braindump/assemble/content/org/scalatest/SuperEngine$Branch.class
  Last modified May 29, 2022; size 1815 bytes
  SHA-256 checksum 0a8a86bd0bfa39868f0d31b727792928772443426855058301545ec3fc51b0a7
  Compiled from "Engine.scala"
public abstract class org.scalatest.SuperEngine$Branch extends org.scalatest.SuperEngine<T>.Node
  minor version: 0
  major version: 52
  flags: (0x0421) ACC_PUBLIC, ACC_SUPER, ACC_ABSTRACT
  this_class: #2                          // org/scalatest/SuperEngine$Branch
  super_class: #5                         // org/scalatest/SuperEngine$Node
  interfaces: 0, fields: 2, methods: 6, attributes: 5
Constant pool:
   #1 = Utf8               org/scalatest/SuperEngine$Branch
   #2 = Class              #1             // org/scalatest/SuperEngine$Branch
   #3 = Utf8               Lorg/scalatest/SuperEngine<TT;>.Node;
   #4 = Utf8               org/scalatest/SuperEngine$Node
   #5 = Class              #4             // org/scalatest/SuperEngine$Node
   #6 = Utf8               Engine.scala
   #7 = Utf8               org/scalatest/SuperEngine
   #8 = Class              #7             // org/scalatest/SuperEngine
   #9 = Utf8               Branch
  #10 = Utf8               Node
  #11 = Utf8               subNodes
  #12 = Utf8               Lscala/collection/immutable/List;
  #13 = Utf8               Lscala/collection/immutable/List<Lorg/scalatest/SuperEngine<TT;>.Node;>;
  #14 = Utf8               pending
  #15 = Utf8               Z
  #16 = Utf8               ()Lscala/collection/immutable/List;
  #17 = Utf8               ()Lscala/collection/immutable/List<Lorg/scalatest/SuperEngine<TT;>.Node;>;
  #18 = NameAndType        #11:#12        // subNodes:Lscala/collection/immutable/List;
  #19 = Fieldref           #2.#18         // org/scalatest/SuperEngine$Branch.subNodes:Lscala/collection/immutable/List;
  #20 = Utf8               this
  #21 = Utf8               Lorg/scalatest/SuperEngine$Branch;
  #22 = Utf8               subNodes_$eq
  #23 = Utf8               (Lscala/collection/immutable/List;)V
  #24 = Utf8               (Lscala/collection/immutable/List<Lorg/scalatest/SuperEngine<TT;>.Node;>;)V
  #25 = Utf8               x$1
  #26 = Utf8               ()Z
  #27 = NameAndType        #14:#15        // pending:Z
  #28 = Fieldref           #2.#27         // org/scalatest/SuperEngine$Branch.pending:Z
  #29 = Utf8               pending_$eq
  #30 = Utf8               (Z)V
  #31 = Utf8               org$scalatest$SuperEngine$Branch$$$outer
  #32 = Utf8               ()Lorg/scalatest/SuperEngine;
  #33 = Utf8               $outer
  #34 = Utf8               Lorg/scalatest/SuperEngine;
  #35 = NameAndType        #33:#34        // $outer:Lorg/scalatest/SuperEngine;
  #36 = Fieldref           #2.#35         // org/scalatest/SuperEngine$Branch.$outer:Lorg/scalatest/SuperEngine;
  #37 = Utf8               <init>
  #38 = Utf8               (Lorg/scalatest/SuperEngine;Lscala/Option;)V
  #39 = Utf8               (Lscala/Option<Lorg/scalatest/SuperEngine<TT;>.Branch;>;)V
  #40 = Utf8               parentOption
  #41 = NameAndType        #37:#38        // "<init>":(Lorg/scalatest/SuperEngine;Lscala/Option;)V
  #42 = Methodref          #5.#41         // org/scalatest/SuperEngine$Node."<init>":(Lorg/scalatest/SuperEngine;Lscala/Option;)V
  #43 = Utf8               scala/package$
  #44 = Class              #43            // scala/package$
  #45 = Utf8               MODULE$
  #46 = Utf8               Lscala/package$;
  #47 = NameAndType        #45:#46        // MODULE$:Lscala/package$;
  #48 = Fieldref           #44.#47        // scala/package$.MODULE$:Lscala/package$;
  #49 = Utf8               Nil
  #50 = Utf8               ()Lscala/collection/immutable/Nil$;
  #51 = NameAndType        #49:#50        // Nil:()Lscala/collection/immutable/Nil$;
  #52 = Methodref          #44.#51        // scala/package$.Nil:()Lscala/collection/immutable/Nil$;
  #53 = Utf8               Lscala/Option;
  #54 = Utf8               Signature
  #55 = Utf8               Code
  #56 = Utf8               LineNumberTable
  #57 = Utf8               LocalVariableTable
  #58 = Utf8               MethodParameters
  #59 = Utf8               InnerClasses
  #60 = Utf8               SourceFile
  #61 = Utf8               ScalaInlineInfo
  #62 = Utf8               Scala
{
  private scala.collection.immutable.List<org.scalatest.SuperEngine<T>.Node> subNodes;
    descriptor: Lscala/collection/immutable/List;
    flags: (0x0002) ACC_PRIVATE
    Signature: #13                          // Lscala/collection/immutable/List<Lorg/scalatest/SuperEngine<TT;>.Node;>;

  private boolean pending;
    descriptor: Z
    flags: (0x0002) ACC_PRIVATE

  public scala.collection.immutable.List<org.scalatest.SuperEngine<T>.Node> subNodes();
    descriptor: ()Lscala/collection/immutable/List;
    flags: (0x0001) ACC_PUBLIC
    Code:
      stack=1, locals=1, args_size=1
         0: aload_0
         1: getfield      #19                 // Field subNodes:Lscala/collection/immutable/List;
         4: areturn
      LineNumberTable:
        line 72: 0
      LocalVariableTable:
        Start  Length  Slot  Name   Signature
            0       5     0  this   Lorg/scalatest/SuperEngine$Branch;
    Signature: #17                          // ()Lscala/collection/immutable/List<Lorg/scalatest/SuperEngine<TT;>.Node;>;

  public void subNodes_$eq(scala.collection.immutable.List<org.scalatest.SuperEngine<T>.Node>);
    descriptor: (Lscala/collection/immutable/List;)V
    flags: (0x0001) ACC_PUBLIC
    Code:
      stack=2, locals=2, args_size=2
         0: aload_0
         1: aload_1
         2: putfield      #19                 // Field subNodes:Lscala/collection/immutable/List;
         5: return
      LineNumberTable:
        line 72: 0
      LocalVariableTable:
        Start  Length  Slot  Name   Signature
            0       6     0  this   Lorg/scalatest/SuperEngine$Branch;
            0       6     1   x$1   Lscala/collection/immutable/List;
    Signature: #24                          // (Lscala/collection/immutable/List<Lorg/scalatest/SuperEngine<TT;>.Node;>;)V
    MethodParameters:
      Name                           Flags
      x$1                            final

  public boolean pending();
    descriptor: ()Z
    flags: (0x0001) ACC_PUBLIC
    Code:
      stack=1, locals=1, args_size=1
         0: aload_0
         1: getfield      #28                 // Field pending:Z
         4: ireturn
      LineNumberTable:
        line 73: 0
      LocalVariableTable:
        Start  Length  Slot  Name   Signature
            0       5     0  this   Lorg/scalatest/SuperEngine$Branch;

  public void pending_$eq(boolean);
    descriptor: (Z)V
    flags: (0x0001) ACC_PUBLIC
    Code:
      stack=2, locals=2, args_size=2
         0: aload_0
         1: iload_1
         2: putfield      #28                 // Field pending:Z
         5: return
      LineNumberTable:
        line 73: 0
      LocalVariableTable:
        Start  Length  Slot  Name   Signature
            0       6     0  this   Lorg/scalatest/SuperEngine$Branch;
            0       6     1   x$1   Z
    MethodParameters:
      Name                           Flags
      x$1                            final

  public org.scalatest.SuperEngine org$scalatest$SuperEngine$Branch$$$outer();
    descriptor: ()Lorg/scalatest/SuperEngine;
    flags: (0x1001) ACC_PUBLIC, ACC_SYNTHETIC
    Code:
      stack=1, locals=1, args_size=1
         0: aload_0
         1: getfield      #36                 // Field $outer:Lorg/scalatest/SuperEngine;
         4: areturn
      LineNumberTable:
        line 71: 0
      LocalVariableTable:
        Start  Length  Slot  Name   Signature
            0       5     0  this   Lorg/scalatest/SuperEngine$Branch;

  public org.scalatest.SuperEngine$Branch(scala.Option<org.scalatest.SuperEngine<T>.Branch>);
    descriptor: (Lorg/scalatest/SuperEngine;Lscala/Option;)V
    flags: (0x0001) ACC_PUBLIC
    Code:
      stack=3, locals=3, args_size=3
         0: aload_0
         1: aload_1
         2: aload_2
         3: invokespecial #42                 // Method org/scalatest/SuperEngine$Node."<init>":(Lorg/scalatest/SuperEngine;Lscala/Option;)V
         6: aload_0
         7: getstatic     #48                 // Field scala/package$.MODULE$:Lscala/package$;
        10: invokevirtual #52                 // Method scala/package$.Nil:()Lscala/collection/immutable/Nil$;
        13: putfield      #19                 // Field subNodes:Lscala/collection/immutable/List;
        16: aload_0
        17: iconst_0
        18: putfield      #28                 // Field pending:Z
        21: return
      LineNumberTable:
        line 71: 0
        line 72: 6
        line 73: 16
        line 71: 21
      LocalVariableTable:
        Start  Length  Slot  Name   Signature
            0      22     0  this   Lorg/scalatest/SuperEngine$Branch;
            0      22     1 $outer   Lorg/scalatest/SuperEngine;
            0      22     2 parentOption   Lscala/Option;
    Signature: #39                          // (Lscala/Option<Lorg/scalatest/SuperEngine<TT;>.Branch;>;)V
    MethodParameters:
      Name                           Flags
      $outer                         final synthetic
      parentOption                   final
}
InnerClasses:
  public abstract #9= #2 of #8;           // Branch=class org/scalatest/SuperEngine$Branch of class org/scalatest/SuperEngine
  public abstract #10= #5 of #8;          // Node=class org/scalatest/SuperEngine$Node of class org/scalatest/SuperEngine
Signature: #3                           // Lorg/scalatest/SuperEngine<TT;>.Node;
SourceFile: "Engine.scala"
  ScalaInlineInfo: length = 0x22 (unknown attribute)
   01 00 00 06 00 25 00 26 00 00 1F 00 20 00 00 0E
   00 1A 00 00 1D 00 1E 00 00 0B 00 10 00 00 16 00
   17 00
  Scala: length = 0x0 (unknown attribute)

