Classfile /Users/mw/Projects/slang-braindump/.jar/jar8/assemble/slang-braindump/assemble/content/org/scalatest/SuperEngine$AlertLeaf$.class
  Last modified May 29, 2022; size 2932 bytes
  SHA-256 checksum 3b357b3132cd084aeda12e4740ea2ff8e17d1986f3b33345167f0ec0c11079b6
  Compiled from "Engine.scala"
public class org.scalatest.SuperEngine$AlertLeaf$ extends scala.runtime.AbstractFunction4<org.scalatest.SuperEngine<T>.Branch, java.lang.String, scala.Option<java.lang.Object>, scala.Option<org.scalatest.events.LineInFile>, org.scalatest.SuperEngine<T>.AlertLeaf> implements java.io.Serializable
  minor version: 0
  major version: 52
  flags: (0x0021) ACC_PUBLIC, ACC_SUPER
  this_class: #2                          // org/scalatest/SuperEngine$AlertLeaf$
  super_class: #5                         // scala/runtime/AbstractFunction4
  interfaces: 1, fields: 1, methods: 5, attributes: 5
Constant pool:
   #1 = Utf8               org/scalatest/SuperEngine$AlertLeaf$
   #2 = Class              #1             // org/scalatest/SuperEngine$AlertLeaf$
   #3 = Utf8               Lscala/runtime/AbstractFunction4<Lorg/scalatest/SuperEngine<TT;>.Branch;Ljava/lang/String;Lscala/Option<Ljava/lang/Object;>;Lscala/Option<Lorg/scalatest/events/LineInFile;>;Lorg/scalatest/SuperEngine<TT;>.AlertLeaf;>;Ljava/io/Serializable;
   #4 = Utf8               scala/runtime/AbstractFunction4
   #5 = Class              #4             // scala/runtime/AbstractFunction4
   #6 = Utf8               java/io/Serializable
   #7 = Class              #6             // java/io/Serializable
   #8 = Utf8               Engine.scala
   #9 = Utf8               org/scalatest/SuperEngine$AlertLeaf
  #10 = Class              #9             // org/scalatest/SuperEngine$AlertLeaf
  #11 = Utf8               org/scalatest/SuperEngine
  #12 = Class              #11            // org/scalatest/SuperEngine
  #13 = Utf8               AlertLeaf
  #14 = Utf8               AlertLeaf$
  #15 = Utf8               org/scalatest/SuperEngine$Branch
  #16 = Class              #15            // org/scalatest/SuperEngine$Branch
  #17 = Utf8               Branch
  #18 = Utf8               $outer
  #19 = Utf8               Lorg/scalatest/SuperEngine;
  #20 = Utf8               toString
  #21 = Utf8               ()Ljava/lang/String;
  #22 = String             #13            // AlertLeaf
  #23 = Utf8               this
  #24 = Utf8               Lorg/scalatest/SuperEngine$AlertLeaf$;
  #25 = Utf8               apply
  #26 = Utf8               (Lorg/scalatest/SuperEngine$Branch;Ljava/lang/String;Lscala/Option;Lscala/Option;)Lorg/scalatest/SuperEngine$AlertLeaf;
  #27 = Utf8               (Lorg/scalatest/SuperEngine<TT;>.Branch;Ljava/lang/String;Lscala/Option<Ljava/lang/Object;>;Lscala/Option<Lorg/scalatest/events/LineInFile;>;)Lorg/scalatest/SuperEngine<TT;>.AlertLeaf;
  #28 = Utf8               parent
  #29 = Utf8               message
  #30 = Utf8               payload
  #31 = Utf8               location
  #32 = NameAndType        #18:#19        // $outer:Lorg/scalatest/SuperEngine;
  #33 = Fieldref           #2.#32         // org/scalatest/SuperEngine$AlertLeaf$.$outer:Lorg/scalatest/SuperEngine;
  #34 = Utf8               <init>
  #35 = Utf8               (Lorg/scalatest/SuperEngine;Lorg/scalatest/SuperEngine$Branch;Ljava/lang/String;Lscala/Option;Lscala/Option;)V
  #36 = NameAndType        #34:#35        // "<init>":(Lorg/scalatest/SuperEngine;Lorg/scalatest/SuperEngine$Branch;Ljava/lang/String;Lscala/Option;Lscala/Option;)V
  #37 = Methodref          #10.#36        // org/scalatest/SuperEngine$AlertLeaf."<init>":(Lorg/scalatest/SuperEngine;Lorg/scalatest/SuperEngine$Branch;Ljava/lang/String;Lscala/Option;Lscala/Option;)V
  #38 = Utf8               Lorg/scalatest/SuperEngine$Branch;
  #39 = Utf8               Ljava/lang/String;
  #40 = Utf8               Lscala/Option;
  #41 = Utf8               unapply
  #42 = Utf8               (Lorg/scalatest/SuperEngine$AlertLeaf;)Lscala/Option;
  #43 = Utf8               (Lorg/scalatest/SuperEngine<TT;>.AlertLeaf;)Lscala/Option<Lscala/Tuple4<Lorg/scalatest/SuperEngine<TT;>.Branch;Ljava/lang/String;Lscala/Option<Ljava/lang/Object;>;Lscala/Option<Lorg/scalatest/events/LineInFile;>;>;>;
  #44 = Utf8               x$0
  #45 = Utf8               scala/None$
  #46 = Class              #45            // scala/None$
  #47 = Utf8               MODULE$
  #48 = Utf8               Lscala/None$;
  #49 = NameAndType        #47:#48        // MODULE$:Lscala/None$;
  #50 = Fieldref           #46.#49        // scala/None$.MODULE$:Lscala/None$;
  #51 = Utf8               scala/Some
  #52 = Class              #51            // scala/Some
  #53 = Utf8               scala/Tuple4
  #54 = Class              #53            // scala/Tuple4
  #55 = Utf8               ()Lorg/scalatest/SuperEngine$Branch;
  #56 = NameAndType        #28:#55        // parent:()Lorg/scalatest/SuperEngine$Branch;
  #57 = Methodref          #10.#56        // org/scalatest/SuperEngine$AlertLeaf.parent:()Lorg/scalatest/SuperEngine$Branch;
  #58 = NameAndType        #29:#21        // message:()Ljava/lang/String;
  #59 = Methodref          #10.#58        // org/scalatest/SuperEngine$AlertLeaf.message:()Ljava/lang/String;
  #60 = Utf8               ()Lscala/Option;
  #61 = NameAndType        #30:#60        // payload:()Lscala/Option;
  #62 = Methodref          #10.#61        // org/scalatest/SuperEngine$AlertLeaf.payload:()Lscala/Option;
  #63 = NameAndType        #31:#60        // location:()Lscala/Option;
  #64 = Methodref          #10.#63        // org/scalatest/SuperEngine$AlertLeaf.location:()Lscala/Option;
  #65 = Utf8               (Ljava/lang/Object;Ljava/lang/Object;Ljava/lang/Object;Ljava/lang/Object;)V
  #66 = NameAndType        #34:#65        // "<init>":(Ljava/lang/Object;Ljava/lang/Object;Ljava/lang/Object;Ljava/lang/Object;)V
  #67 = Methodref          #54.#66        // scala/Tuple4."<init>":(Ljava/lang/Object;Ljava/lang/Object;Ljava/lang/Object;Ljava/lang/Object;)V
  #68 = Utf8               (Ljava/lang/Object;)V
  #69 = NameAndType        #34:#68        // "<init>":(Ljava/lang/Object;)V
  #70 = Methodref          #52.#69        // scala/Some."<init>":(Ljava/lang/Object;)V
  #71 = Utf8               Lorg/scalatest/SuperEngine$AlertLeaf;
  #72 = Utf8               scala/Option
  #73 = Class              #72            // scala/Option
  #74 = Utf8               (Ljava/lang/Object;Ljava/lang/Object;Ljava/lang/Object;Ljava/lang/Object;)Ljava/lang/Object;
  #75 = Utf8               v1
  #76 = Utf8               v2
  #77 = Utf8               v3
  #78 = Utf8               v4
  #79 = Utf8               java/lang/String
  #80 = Class              #79            // java/lang/String
  #81 = NameAndType        #25:#26        // apply:(Lorg/scalatest/SuperEngine$Branch;Ljava/lang/String;Lscala/Option;Lscala/Option;)Lorg/scalatest/SuperEngine$AlertLeaf;
  #82 = Methodref          #2.#81         // org/scalatest/SuperEngine$AlertLeaf$.apply:(Lorg/scalatest/SuperEngine$Branch;Ljava/lang/String;Lscala/Option;Lscala/Option;)Lorg/scalatest/SuperEngine$AlertLeaf;
  #83 = Utf8               Ljava/lang/Object;
  #84 = Utf8               (Lorg/scalatest/SuperEngine;)V
  #85 = Utf8               ()V
  #86 = NameAndType        #34:#85        // "<init>":()V
  #87 = Methodref          #5.#86         // scala/runtime/AbstractFunction4."<init>":()V
  #88 = Utf8               Code
  #89 = Utf8               LineNumberTable
  #90 = Utf8               LocalVariableTable
  #91 = Utf8               Signature
  #92 = Utf8               MethodParameters
  #93 = Utf8               StackMapTable
  #94 = Utf8               InnerClasses
  #95 = Utf8               SourceFile
  #96 = Utf8               ScalaInlineInfo
  #97 = Utf8               Scala
{
  private final org.scalatest.SuperEngine $outer;
    descriptor: Lorg/scalatest/SuperEngine;
    flags: (0x1012) ACC_PRIVATE, ACC_FINAL, ACC_SYNTHETIC

  public final java.lang.String toString();
    descriptor: ()Ljava/lang/String;
    flags: (0x0011) ACC_PUBLIC, ACC_FINAL
    Code:
      stack=1, locals=1, args_size=1
         0: ldc           #22                 // String AlertLeaf
         2: areturn
      LineNumberTable:
        line 95: 0
      LocalVariableTable:
        Start  Length  Slot  Name   Signature
            0       3     0  this   Lorg/scalatest/SuperEngine$AlertLeaf$;

  public org.scalatest.SuperEngine<T>.AlertLeaf apply(org.scalatest.SuperEngine<T>.Branch, java.lang.String, scala.Option<java.lang.Object>, scala.Option<org.scalatest.events.LineInFile>);
    descriptor: (Lorg/scalatest/SuperEngine$Branch;Ljava/lang/String;Lscala/Option;Lscala/Option;)Lorg/scalatest/SuperEngine$AlertLeaf;
    flags: (0x0001) ACC_PUBLIC
    Code:
      stack=7, locals=5, args_size=5
         0: new           #10                 // class org/scalatest/SuperEngine$AlertLeaf
         3: dup
         4: aload_0
         5: getfield      #33                 // Field $outer:Lorg/scalatest/SuperEngine;
         8: aload_1
         9: aload_2
        10: aload_3
        11: aload         4
        13: invokespecial #37                 // Method org/scalatest/SuperEngine$AlertLeaf."<init>":(Lorg/scalatest/SuperEngine;Lorg/scalatest/SuperEngine$Branch;Ljava/lang/String;Lscala/Option;Lscala/Option;)V
        16: areturn
      LineNumberTable:
        line 95: 0
      LocalVariableTable:
        Start  Length  Slot  Name   Signature
            0      17     0  this   Lorg/scalatest/SuperEngine$AlertLeaf$;
            0      17     1 parent   Lorg/scalatest/SuperEngine$Branch;
            0      17     2 message   Ljava/lang/String;
            0      17     3 payload   Lscala/Option;
            0      17     4 location   Lscala/Option;
    Signature: #27                          // (Lorg/scalatest/SuperEngine<TT;>.Branch;Ljava/lang/String;Lscala/Option<Ljava/lang/Object;>;Lscala/Option<Lorg/scalatest/events/LineInFile;>;)Lorg/scalatest/SuperEngine<TT;>.AlertLeaf;
    MethodParameters:
      Name                           Flags
      parent                         final
      message                        final
      payload                        final
      location                       final

  public scala.Option<scala.Tuple4<org.scalatest.SuperEngine<T>.Branch, java.lang.String, scala.Option<java.lang.Object>, scala.Option<org.scalatest.events.LineInFile>>> unapply(org.scalatest.SuperEngine<T>.AlertLeaf);
    descriptor: (Lorg/scalatest/SuperEngine$AlertLeaf;)Lscala/Option;
    flags: (0x0001) ACC_PUBLIC
    Code:
      stack=8, locals=2, args_size=2
         0: aload_1
         1: ifnonnull     10
         4: getstatic     #50                 // Field scala/None$.MODULE$:Lscala/None$;
         7: goto          40
        10: new           #52                 // class scala/Some
        13: dup
        14: new           #54                 // class scala/Tuple4
        17: dup
        18: aload_1
        19: invokevirtual #57                 // Method org/scalatest/SuperEngine$AlertLeaf.parent:()Lorg/scalatest/SuperEngine$Branch;
        22: aload_1
        23: invokevirtual #59                 // Method org/scalatest/SuperEngine$AlertLeaf.message:()Ljava/lang/String;
        26: aload_1
        27: invokevirtual #62                 // Method org/scalatest/SuperEngine$AlertLeaf.payload:()Lscala/Option;
        30: aload_1
        31: invokevirtual #64                 // Method org/scalatest/SuperEngine$AlertLeaf.location:()Lscala/Option;
        34: invokespecial #67                 // Method scala/Tuple4."<init>":(Ljava/lang/Object;Ljava/lang/Object;Ljava/lang/Object;Ljava/lang/Object;)V
        37: invokespecial #70                 // Method scala/Some."<init>":(Ljava/lang/Object;)V
        40: areturn
      StackMapTable: number_of_entries = 2
        frame_type = 10 /* same */
        frame_type = 93 /* same_locals_1_stack_item */
          stack = [ class scala/Option ]
      LineNumberTable:
        line 95: 0
      LocalVariableTable:
        Start  Length  Slot  Name   Signature
            0      41     0  this   Lorg/scalatest/SuperEngine$AlertLeaf$;
            0      41     1   x$0   Lorg/scalatest/SuperEngine$AlertLeaf;
    Signature: #43                          // (Lorg/scalatest/SuperEngine<TT;>.AlertLeaf;)Lscala/Option<Lscala/Tuple4<Lorg/scalatest/SuperEngine<TT;>.Branch;Ljava/lang/String;Lscala/Option<Ljava/lang/Object;>;Lscala/Option<Lorg/scalatest/events/LineInFile;>;>;>;
    MethodParameters:
      Name                           Flags
      x$0                            final

  public java.lang.Object apply(java.lang.Object, java.lang.Object, java.lang.Object, java.lang.Object);
    descriptor: (Ljava/lang/Object;Ljava/lang/Object;Ljava/lang/Object;Ljava/lang/Object;)Ljava/lang/Object;
    flags: (0x1041) ACC_PUBLIC, ACC_BRIDGE, ACC_SYNTHETIC
    Code:
      stack=5, locals=5, args_size=5
         0: aload_0
         1: aload_1
         2: checkcast     #16                 // class org/scalatest/SuperEngine$Branch
         5: aload_2
         6: checkcast     #80                 // class java/lang/String
         9: aload_3
        10: checkcast     #73                 // class scala/Option
        13: aload         4
        15: checkcast     #73                 // class scala/Option
        18: invokevirtual #82                 // Method apply:(Lorg/scalatest/SuperEngine$Branch;Ljava/lang/String;Lscala/Option;Lscala/Option;)Lorg/scalatest/SuperEngine$AlertLeaf;
        21: areturn
      LineNumberTable:
        line 95: 0
      LocalVariableTable:
        Start  Length  Slot  Name   Signature
            0      22     0  this   Lorg/scalatest/SuperEngine$AlertLeaf$;
            0      22     1    v1   Ljava/lang/Object;
            0      22     2    v2   Ljava/lang/Object;
            0      22     3    v3   Ljava/lang/Object;
            0      22     4    v4   Ljava/lang/Object;
    MethodParameters:
      Name                           Flags
      v1                             final
      v2                             final
      v3                             final
      v4                             final

  public org.scalatest.SuperEngine$AlertLeaf$(org.scalatest.SuperEngine);
    descriptor: (Lorg/scalatest/SuperEngine;)V
    flags: (0x0001) ACC_PUBLIC
    Code:
      stack=2, locals=2, args_size=2
         0: aload_1
         1: ifnonnull     6
         4: aconst_null
         5: athrow
         6: aload_0
         7: aload_1
         8: putfield      #33                 // Field $outer:Lorg/scalatest/SuperEngine;
        11: aload_0
        12: invokespecial #87                 // Method scala/runtime/AbstractFunction4."<init>":()V
        15: return
      StackMapTable: number_of_entries = 1
        frame_type = 6 /* same */
      LineNumberTable:
        line 95: 0
      LocalVariableTable:
        Start  Length  Slot  Name   Signature
            0      16     0  this   Lorg/scalatest/SuperEngine$AlertLeaf$;
            0      16     1 $outer   Lorg/scalatest/SuperEngine;
    MethodParameters:
      Name                           Flags
      $outer                         final synthetic
}
InnerClasses:
  public #13= #10 of #12;                 // AlertLeaf=class org/scalatest/SuperEngine$AlertLeaf of class org/scalatest/SuperEngine
  public #14= #2 of #12;                  // AlertLeaf$=class org/scalatest/SuperEngine$AlertLeaf$ of class org/scalatest/SuperEngine
  public abstract #17= #16 of #12;        // Branch=class org/scalatest/SuperEngine$Branch of class org/scalatest/SuperEngine
Signature: #3                           // Lscala/runtime/AbstractFunction4<Lorg/scalatest/SuperEngine<TT;>.Branch;Ljava/lang/String;Lscala/Option<Ljava/lang/Object;>;Lscala/Option<Lorg/scalatest/events/LineInFile;>;Lorg/scalatest/SuperEngine<TT;>.AlertLeaf;>;Ljava/io/Serializable;
SourceFile: "Engine.scala"
  ScalaInlineInfo: length = 0x1D (unknown attribute)
   01 01 00 05 00 22 00 54 01 00 19 00 4A 01 00 19
   00 1A 01 00 14 00 15 01 00 29 00 2A 01
  Scala: length = 0x0 (unknown attribute)

