Classfile /Users/mw/Projects/slang-braindump/.jar/jar8/assemble/slang-braindump/assemble/content/org/scalatest/Timer$$anon$2.class
  Last modified May 29, 2022; size 801 bytes
  SHA-256 checksum 5ebb639e34f4170bfb5222d84a4e5d88f7963ccd4018bf1ca05a6673972ec203
  Compiled from "JavaClassesWrappers.scala"
public final class org.scalatest.Timer$$anon$2 extends java.util.TimerTask
  minor version: 0
  major version: 52
  flags: (0x0031) ACC_PUBLIC, ACC_FINAL, ACC_SUPER
  this_class: #2                          // org/scalatest/Timer$$anon$2
  super_class: #4                         // java/util/TimerTask
  interfaces: 0, fields: 1, methods: 2, attributes: 5
Constant pool:
   #1 = Utf8               org/scalatest/Timer$$anon$2
   #2 = Class              #1             // org/scalatest/Timer$$anon$2
   #3 = Utf8               java/util/TimerTask
   #4 = Class              #3             // java/util/TimerTask
   #5 = Utf8               JavaClassesWrappers.scala
   #6 = Utf8               org/scalatest/Timer
   #7 = Class              #6             // org/scalatest/Timer
   #8 = Utf8               schedule
   #9 = Utf8               (Lorg/scalatest/TimerTask;JJ)V
  #10 = NameAndType        #8:#9          // schedule:(Lorg/scalatest/TimerTask;JJ)V
  #11 = Utf8               task$2
  #12 = Utf8               Lorg/scalatest/TimerTask;
  #13 = Utf8               run
  #14 = Utf8               ()V
  #15 = NameAndType        #11:#12        // task$2:Lorg/scalatest/TimerTask;
  #16 = Fieldref           #2.#15         // org/scalatest/Timer$$anon$2.task$2:Lorg/scalatest/TimerTask;
  #17 = Utf8               org/scalatest/TimerTask
  #18 = Class              #17            // org/scalatest/TimerTask
  #19 = NameAndType        #13:#14        // run:()V
  #20 = InterfaceMethodref #18.#19        // org/scalatest/TimerTask.run:()V
  #21 = Utf8               this
  #22 = Utf8               Lorg/scalatest/Timer$$anon$2;
  #23 = Utf8               <init>
  #24 = Utf8               (Lorg/scalatest/Timer;Lorg/scalatest/TimerTask;)V
  #25 = Utf8               $outer
  #26 = NameAndType        #23:#14        // "<init>":()V
  #27 = Methodref          #4.#26         // java/util/TimerTask."<init>":()V
  #28 = Utf8               Lorg/scalatest/Timer;
  #29 = Utf8               Code
  #30 = Utf8               LineNumberTable
  #31 = Utf8               LocalVariableTable
  #32 = Utf8               MethodParameters
  #33 = Utf8               InnerClasses
  #34 = Utf8               EnclosingMethod
  #35 = Utf8               SourceFile
  #36 = Utf8               ScalaInlineInfo
  #37 = Utf8               Scala
{
  private final org.scalatest.TimerTask task$2;
    descriptor: Lorg/scalatest/TimerTask;
    flags: (0x0012) ACC_PRIVATE, ACC_FINAL

  public void run();
    descriptor: ()V
    flags: (0x0001) ACC_PUBLIC
    Code:
      stack=1, locals=1, args_size=1
         0: aload_0
         1: getfield      #16                 // Field task$2:Lorg/scalatest/TimerTask;
         4: invokeinterface #20,  1           // InterfaceMethod org/scalatest/TimerTask.run:()V
         9: return
      LineNumberTable:
        line 101: 0
      LocalVariableTable:
        Start  Length  Slot  Name   Signature
            0      10     0  this   Lorg/scalatest/Timer$$anon$2;

  public org.scalatest.Timer$$anon$2(org.scalatest.Timer, org.scalatest.TimerTask);
    descriptor: (Lorg/scalatest/Timer;Lorg/scalatest/TimerTask;)V
    flags: (0x0001) ACC_PUBLIC
    Code:
      stack=2, locals=3, args_size=3
         0: aload_0
         1: aload_2
         2: putfield      #16                 // Field task$2:Lorg/scalatest/TimerTask;
         5: aload_0
         6: invokespecial #27                 // Method java/util/TimerTask."<init>":()V
         9: return
      LineNumberTable:
        line 98: 0
        line 99: 5
      LocalVariableTable:
        Start  Length  Slot  Name   Signature
            0      10     0  this   Lorg/scalatest/Timer$$anon$2;
            0      10     1 $outer   Lorg/scalatest/Timer;
            0      10     2 task$2   Lorg/scalatest/TimerTask;
    MethodParameters:
      Name                           Flags
      $outer                         final synthetic
      task$2                         final
}
InnerClasses:
  public final #2;                        // class org/scalatest/Timer$$anon$2
EnclosingMethod: #7.#10                 // org.scalatest.Timer.schedule
SourceFile: "JavaClassesWrappers.scala"
  ScalaInlineInfo: length = 0xE (unknown attribute)
   01 01 00 02 00 17 00 18 01 00 0D 00 0E 01
  Scala: length = 0x0 (unknown attribute)

