Classfile /Users/mw/Projects/slang-braindump/.jar/jar8/assemble/slang-braindump/assemble/content/com/fasterxml/jackson/databind/deser/std/CollectionDeserializer$CollectionReferringAccumulator.class
  Last modified May 29, 2022; size 3755 bytes
  SHA-256 checksum 27733600f73d0237e782719fbfe2f8113df982a2d705e704a5b2b7fbde46b26e
  Compiled from "CollectionDeserializer.java"
public class com.fasterxml.jackson.databind.deser.std.CollectionDeserializer$CollectionReferringAccumulator
  minor version: 0
  major version: 52
  flags: (0x0021) ACC_PUBLIC, ACC_SUPER
  this_class: #30                         // com/fasterxml/jackson/databind/deser/std/CollectionDeserializer$CollectionReferringAccumulator
  super_class: #31                        // java/lang/Object
  interfaces: 0, fields: 3, methods: 4, attributes: 2
Constant pool:
    #1 = Methodref          #31.#83       // java/lang/Object."<init>":()V
    #2 = Class              #84           // java/util/ArrayList
    #3 = Methodref          #2.#83        // java/util/ArrayList."<init>":()V
    #4 = Fieldref           #30.#85       // com/fasterxml/jackson/databind/deser/std/CollectionDeserializer$CollectionReferringAccumulator._accumulator:Ljava/util/List;
    #5 = Fieldref           #30.#86       // com/fasterxml/jackson/databind/deser/std/CollectionDeserializer$CollectionReferringAccumulator._elementType:Ljava/lang/Class;
    #6 = Fieldref           #30.#87       // com/fasterxml/jackson/databind/deser/std/CollectionDeserializer$CollectionReferringAccumulator._result:Ljava/util/Collection;
    #7 = InterfaceMethodref #88.#89       // java/util/List.isEmpty:()Z
    #8 = InterfaceMethodref #90.#91       // java/util/Collection.add:(Ljava/lang/Object;)Z
    #9 = InterfaceMethodref #88.#92       // java/util/List.size:()I
   #10 = InterfaceMethodref #88.#93       // java/util/List.get:(I)Ljava/lang/Object;
   #11 = Class              #95           // com/fasterxml/jackson/databind/deser/std/CollectionDeserializer$CollectionReferring
   #12 = Fieldref           #11.#96       // com/fasterxml/jackson/databind/deser/std/CollectionDeserializer$CollectionReferring.next:Ljava/util/List;
   #13 = InterfaceMethodref #88.#91       // java/util/List.add:(Ljava/lang/Object;)Z
   #14 = Methodref          #11.#97       // com/fasterxml/jackson/databind/deser/std/CollectionDeserializer$CollectionReferring."<init>":(Lcom/fasterxml/jackson/databind/deser/std/CollectionDeserializer$CollectionReferringAccumulator;Lcom/fasterxml/jackson/databind/deser/UnresolvedForwardReference;Ljava/lang/Class;)V
   #15 = InterfaceMethodref #88.#98       // java/util/List.iterator:()Ljava/util/Iterator;
   #16 = InterfaceMethodref #99.#100      // java/util/Iterator.hasNext:()Z
   #17 = InterfaceMethodref #99.#101      // java/util/Iterator.next:()Ljava/lang/Object;
   #18 = Methodref          #11.#102      // com/fasterxml/jackson/databind/deser/std/CollectionDeserializer$CollectionReferring.hasId:(Ljava/lang/Object;)Z
   #19 = InterfaceMethodref #99.#103      // java/util/Iterator.remove:()V
   #20 = InterfaceMethodref #90.#104      // java/util/Collection.addAll:(Ljava/util/Collection;)Z
   #21 = Class              #105          // java/lang/IllegalArgumentException
   #22 = Class              #106          // java/lang/StringBuilder
   #23 = Methodref          #22.#83       // java/lang/StringBuilder."<init>":()V
   #24 = String             #107          // Trying to resolve a forward reference with id [
   #25 = Methodref          #22.#108      // java/lang/StringBuilder.append:(Ljava/lang/String;)Ljava/lang/StringBuilder;
   #26 = Methodref          #22.#109      // java/lang/StringBuilder.append:(Ljava/lang/Object;)Ljava/lang/StringBuilder;
   #27 = String             #110          // ] that wasn\'t previously seen as unresolved.
   #28 = Methodref          #22.#111      // java/lang/StringBuilder.toString:()Ljava/lang/String;
   #29 = Methodref          #21.#112      // java/lang/IllegalArgumentException."<init>":(Ljava/lang/String;)V
   #30 = Class              #113          // com/fasterxml/jackson/databind/deser/std/CollectionDeserializer$CollectionReferringAccumulator
   #31 = Class              #114          // java/lang/Object
   #32 = Utf8               _elementType
   #33 = Utf8               Ljava/lang/Class;
   #34 = Utf8               Signature
   #35 = Utf8               Ljava/lang/Class<*>;
   #36 = Utf8               _result
   #37 = Utf8               Ljava/util/Collection;
   #38 = Utf8               Ljava/util/Collection<Ljava/lang/Object;>;
   #39 = Utf8               _accumulator
   #40 = Utf8               Ljava/util/List;
   #41 = Utf8               CollectionReferring
   #42 = Utf8               InnerClasses
   #43 = Utf8               Ljava/util/List<Lcom/fasterxml/jackson/databind/deser/std/CollectionDeserializer$CollectionReferring;>;
   #44 = Utf8               <init>
   #45 = Utf8               (Ljava/lang/Class;Ljava/util/Collection;)V
   #46 = Utf8               Code
   #47 = Utf8               LineNumberTable
   #48 = Utf8               LocalVariableTable
   #49 = Utf8               this
   #50 = Utf8               CollectionReferringAccumulator
   #51 = Utf8               Lcom/fasterxml/jackson/databind/deser/std/CollectionDeserializer$CollectionReferringAccumulator;
   #52 = Utf8               elementType
   #53 = Utf8               result
   #54 = Utf8               LocalVariableTypeTable
   #55 = Utf8               (Ljava/lang/Class<*>;Ljava/util/Collection<Ljava/lang/Object;>;)V
   #56 = Utf8               add
   #57 = Utf8               (Ljava/lang/Object;)V
   #58 = Utf8               ref
   #59 = Utf8               Lcom/fasterxml/jackson/databind/deser/std/CollectionDeserializer$CollectionReferring;
   #60 = Utf8               value
   #61 = Utf8               Ljava/lang/Object;
   #62 = Utf8               StackMapTable
   #63 = Utf8               handleUnresolvedReference
   #64 = Class              #116          // com/fasterxml/jackson/databind/deser/impl/ReadableObjectId$Referring
   #65 = Utf8               Referring
   #66 = Utf8               (Lcom/fasterxml/jackson/databind/deser/UnresolvedForwardReference;)Lcom/fasterxml/jackson/databind/deser/impl/ReadableObjectId$Referring;
   #67 = Utf8               reference
   #68 = Utf8               Lcom/fasterxml/jackson/databind/deser/UnresolvedForwardReference;
   #69 = Utf8               id
   #70 = Utf8               resolveForwardReference
   #71 = Utf8               (Ljava/lang/Object;Ljava/lang/Object;)V
   #72 = Utf8               iterator
   #73 = Utf8               Ljava/util/Iterator;
   #74 = Utf8               previous
   #75 = Utf8               Ljava/util/Iterator<Lcom/fasterxml/jackson/databind/deser/std/CollectionDeserializer$CollectionReferring;>;
   #76 = Class              #117          // java/util/Iterator
   #77 = Class              #118          // java/util/Collection
   #78 = Class              #95           // com/fasterxml/jackson/databind/deser/std/CollectionDeserializer$CollectionReferring
   #79 = Utf8               Exceptions
   #80 = Class              #119          // java/io/IOException
   #81 = Utf8               SourceFile
   #82 = Utf8               CollectionDeserializer.java
   #83 = NameAndType        #44:#120      // "<init>":()V
   #84 = Utf8               java/util/ArrayList
   #85 = NameAndType        #39:#40       // _accumulator:Ljava/util/List;
   #86 = NameAndType        #32:#33       // _elementType:Ljava/lang/Class;
   #87 = NameAndType        #36:#37       // _result:Ljava/util/Collection;
   #88 = Class              #121          // java/util/List
   #89 = NameAndType        #122:#123     // isEmpty:()Z
   #90 = Class              #118          // java/util/Collection
   #91 = NameAndType        #56:#124      // add:(Ljava/lang/Object;)Z
   #92 = NameAndType        #125:#126     // size:()I
   #93 = NameAndType        #127:#128     // get:(I)Ljava/lang/Object;
   #94 = Class              #129          // com/fasterxml/jackson/databind/deser/std/CollectionDeserializer
   #95 = Utf8               com/fasterxml/jackson/databind/deser/std/CollectionDeserializer$CollectionReferring
   #96 = NameAndType        #130:#40      // next:Ljava/util/List;
   #97 = NameAndType        #44:#131      // "<init>":(Lcom/fasterxml/jackson/databind/deser/std/CollectionDeserializer$CollectionReferringAccumulator;Lcom/fasterxml/jackson/databind/deser/UnresolvedForwardReference;Ljava/lang/Class;)V
   #98 = NameAndType        #72:#132      // iterator:()Ljava/util/Iterator;
   #99 = Class              #117          // java/util/Iterator
  #100 = NameAndType        #133:#123     // hasNext:()Z
  #101 = NameAndType        #130:#134     // next:()Ljava/lang/Object;
  #102 = NameAndType        #135:#124     // hasId:(Ljava/lang/Object;)Z
  #103 = NameAndType        #136:#120     // remove:()V
  #104 = NameAndType        #137:#138     // addAll:(Ljava/util/Collection;)Z
  #105 = Utf8               java/lang/IllegalArgumentException
  #106 = Utf8               java/lang/StringBuilder
  #107 = Utf8               Trying to resolve a forward reference with id [
  #108 = NameAndType        #139:#140     // append:(Ljava/lang/String;)Ljava/lang/StringBuilder;
  #109 = NameAndType        #139:#141     // append:(Ljava/lang/Object;)Ljava/lang/StringBuilder;
  #110 = Utf8               ] that wasn\'t previously seen as unresolved.
  #111 = NameAndType        #142:#143     // toString:()Ljava/lang/String;
  #112 = NameAndType        #44:#144      // "<init>":(Ljava/lang/String;)V
  #113 = Utf8               com/fasterxml/jackson/databind/deser/std/CollectionDeserializer$CollectionReferringAccumulator
  #114 = Utf8               java/lang/Object
  #115 = Class              #145          // com/fasterxml/jackson/databind/deser/impl/ReadableObjectId
  #116 = Utf8               com/fasterxml/jackson/databind/deser/impl/ReadableObjectId$Referring
  #117 = Utf8               java/util/Iterator
  #118 = Utf8               java/util/Collection
  #119 = Utf8               java/io/IOException
  #120 = Utf8               ()V
  #121 = Utf8               java/util/List
  #122 = Utf8               isEmpty
  #123 = Utf8               ()Z
  #124 = Utf8               (Ljava/lang/Object;)Z
  #125 = Utf8               size
  #126 = Utf8               ()I
  #127 = Utf8               get
  #128 = Utf8               (I)Ljava/lang/Object;
  #129 = Utf8               com/fasterxml/jackson/databind/deser/std/CollectionDeserializer
  #130 = Utf8               next
  #131 = Utf8               (Lcom/fasterxml/jackson/databind/deser/std/CollectionDeserializer$CollectionReferringAccumulator;Lcom/fasterxml/jackson/databind/deser/UnresolvedForwardReference;Ljava/lang/Class;)V
  #132 = Utf8               ()Ljava/util/Iterator;
  #133 = Utf8               hasNext
  #134 = Utf8               ()Ljava/lang/Object;
  #135 = Utf8               hasId
  #136 = Utf8               remove
  #137 = Utf8               addAll
  #138 = Utf8               (Ljava/util/Collection;)Z
  #139 = Utf8               append
  #140 = Utf8               (Ljava/lang/String;)Ljava/lang/StringBuilder;
  #141 = Utf8               (Ljava/lang/Object;)Ljava/lang/StringBuilder;
  #142 = Utf8               toString
  #143 = Utf8               ()Ljava/lang/String;
  #144 = Utf8               (Ljava/lang/String;)V
  #145 = Utf8               com/fasterxml/jackson/databind/deser/impl/ReadableObjectId
{
  private final java.lang.Class<?> _elementType;
    descriptor: Ljava/lang/Class;
    flags: (0x0012) ACC_PRIVATE, ACC_FINAL
    Signature: #35                          // Ljava/lang/Class<*>;

  private final java.util.Collection<java.lang.Object> _result;
    descriptor: Ljava/util/Collection;
    flags: (0x0012) ACC_PRIVATE, ACC_FINAL
    Signature: #38                          // Ljava/util/Collection<Ljava/lang/Object;>;

  private java.util.List<com.fasterxml.jackson.databind.deser.std.CollectionDeserializer$CollectionReferring> _accumulator;
    descriptor: Ljava/util/List;
    flags: (0x0002) ACC_PRIVATE
    Signature: #43                          // Ljava/util/List<Lcom/fasterxml/jackson/databind/deser/std/CollectionDeserializer$CollectionReferring;>;

  public com.fasterxml.jackson.databind.deser.std.CollectionDeserializer$CollectionReferringAccumulator(java.lang.Class<?>, java.util.Collection<java.lang.Object>);
    descriptor: (Ljava/lang/Class;Ljava/util/Collection;)V
    flags: (0x0001) ACC_PUBLIC
    Code:
      stack=3, locals=3, args_size=3
         0: aload_0
         1: invokespecial #1                  // Method java/lang/Object."<init>":()V
         4: aload_0
         5: new           #2                  // class java/util/ArrayList
         8: dup
         9: invokespecial #3                  // Method java/util/ArrayList."<init>":()V
        12: putfield      #4                  // Field _accumulator:Ljava/util/List;
        15: aload_0
        16: aload_1
        17: putfield      #5                  // Field _elementType:Ljava/lang/Class;
        20: aload_0
        21: aload_2
        22: putfield      #6                  // Field _result:Ljava/util/Collection;
        25: return
      LineNumberTable:
        line 481: 0
        line 479: 4
        line 482: 15
        line 483: 20
        line 484: 25
      LocalVariableTable:
        Start  Length  Slot  Name   Signature
            0      26     0  this   Lcom/fasterxml/jackson/databind/deser/std/CollectionDeserializer$CollectionReferringAccumulator;
            0      26     1 elementType   Ljava/lang/Class;
            0      26     2 result   Ljava/util/Collection;
      LocalVariableTypeTable:
        Start  Length  Slot  Name   Signature
            0      26     1 elementType   Ljava/lang/Class<*>;
            0      26     2 result   Ljava/util/Collection<Ljava/lang/Object;>;
    Signature: #55                          // (Ljava/lang/Class<*>;Ljava/util/Collection<Ljava/lang/Object;>;)V

  public void add(java.lang.Object);
    descriptor: (Ljava/lang/Object;)V
    flags: (0x0001) ACC_PUBLIC
    Code:
      stack=3, locals=3, args_size=2
         0: aload_0
         1: getfield      #4                  // Field _accumulator:Ljava/util/List;
         4: invokeinterface #7,  1            // InterfaceMethod java/util/List.isEmpty:()Z
         9: ifeq          26
        12: aload_0
        13: getfield      #6                  // Field _result:Ljava/util/Collection;
        16: aload_1
        17: invokeinterface #8,  2            // InterfaceMethod java/util/Collection.add:(Ljava/lang/Object;)Z
        22: pop
        23: goto          61
        26: aload_0
        27: getfield      #4                  // Field _accumulator:Ljava/util/List;
        30: aload_0
        31: getfield      #4                  // Field _accumulator:Ljava/util/List;
        34: invokeinterface #9,  1            // InterfaceMethod java/util/List.size:()I
        39: iconst_1
        40: isub
        41: invokeinterface #10,  2           // InterfaceMethod java/util/List.get:(I)Ljava/lang/Object;
        46: checkcast     #11                 // class com/fasterxml/jackson/databind/deser/std/CollectionDeserializer$CollectionReferring
        49: astore_2
        50: aload_2
        51: getfield      #12                 // Field com/fasterxml/jackson/databind/deser/std/CollectionDeserializer$CollectionReferring.next:Ljava/util/List;
        54: aload_1
        55: invokeinterface #13,  2           // InterfaceMethod java/util/List.add:(Ljava/lang/Object;)Z
        60: pop
        61: return
      LineNumberTable:
        line 488: 0
        line 489: 12
        line 491: 26
        line 492: 50
        line 494: 61
      LocalVariableTable:
        Start  Length  Slot  Name   Signature
           50      11     2   ref   Lcom/fasterxml/jackson/databind/deser/std/CollectionDeserializer$CollectionReferring;
            0      62     0  this   Lcom/fasterxml/jackson/databind/deser/std/CollectionDeserializer$CollectionReferringAccumulator;
            0      62     1 value   Ljava/lang/Object;
      StackMapTable: number_of_entries = 2
        frame_type = 26 /* same */
        frame_type = 34 /* same */

  public com.fasterxml.jackson.databind.deser.impl.ReadableObjectId$Referring handleUnresolvedReference(com.fasterxml.jackson.databind.deser.UnresolvedForwardReference);
    descriptor: (Lcom/fasterxml/jackson/databind/deser/UnresolvedForwardReference;)Lcom/fasterxml/jackson/databind/deser/impl/ReadableObjectId$Referring;
    flags: (0x0001) ACC_PUBLIC
    Code:
      stack=5, locals=3, args_size=2
         0: new           #11                 // class com/fasterxml/jackson/databind/deser/std/CollectionDeserializer$CollectionReferring
         3: dup
         4: aload_0
         5: aload_1
         6: aload_0
         7: getfield      #5                  // Field _elementType:Ljava/lang/Class;
        10: invokespecial #14                 // Method com/fasterxml/jackson/databind/deser/std/CollectionDeserializer$CollectionReferring."<init>":(Lcom/fasterxml/jackson/databind/deser/std/CollectionDeserializer$CollectionReferringAccumulator;Lcom/fasterxml/jackson/databind/deser/UnresolvedForwardReference;Ljava/lang/Class;)V
        13: astore_2
        14: aload_0
        15: getfield      #4                  // Field _accumulator:Ljava/util/List;
        18: aload_2
        19: invokeinterface #13,  2           // InterfaceMethod java/util/List.add:(Ljava/lang/Object;)Z
        24: pop
        25: aload_2
        26: areturn
      LineNumberTable:
        line 498: 0
        line 499: 14
        line 500: 25
      LocalVariableTable:
        Start  Length  Slot  Name   Signature
            0      27     0  this   Lcom/fasterxml/jackson/databind/deser/std/CollectionDeserializer$CollectionReferringAccumulator;
            0      27     1 reference   Lcom/fasterxml/jackson/databind/deser/UnresolvedForwardReference;
           14      13     2    id   Lcom/fasterxml/jackson/databind/deser/std/CollectionDeserializer$CollectionReferring;

  public void resolveForwardReference(java.lang.Object, java.lang.Object) throws java.io.IOException;
    descriptor: (Ljava/lang/Object;Ljava/lang/Object;)V
    flags: (0x0001) ACC_PUBLIC
    Code:
      stack=4, locals=6, args_size=3
         0: aload_0
         1: getfield      #4                  // Field _accumulator:Ljava/util/List;
         4: invokeinterface #15,  1           // InterfaceMethod java/util/List.iterator:()Ljava/util/Iterator;
         9: astore_3
        10: aload_0
        11: getfield      #6                  // Field _result:Ljava/util/Collection;
        14: astore        4
        16: aload_3
        17: invokeinterface #16,  1           // InterfaceMethod java/util/Iterator.hasNext:()Z
        22: ifeq          84
        25: aload_3
        26: invokeinterface #17,  1           // InterfaceMethod java/util/Iterator.next:()Ljava/lang/Object;
        31: checkcast     #11                 // class com/fasterxml/jackson/databind/deser/std/CollectionDeserializer$CollectionReferring
        34: astore        5
        36: aload         5
        38: aload_1
        39: invokevirtual #18                 // Method com/fasterxml/jackson/databind/deser/std/CollectionDeserializer$CollectionReferring.hasId:(Ljava/lang/Object;)Z
        42: ifeq          74
        45: aload_3
        46: invokeinterface #19,  1           // InterfaceMethod java/util/Iterator.remove:()V
        51: aload         4
        53: aload_2
        54: invokeinterface #8,  2            // InterfaceMethod java/util/Collection.add:(Ljava/lang/Object;)Z
        59: pop
        60: aload         4
        62: aload         5
        64: getfield      #12                 // Field com/fasterxml/jackson/databind/deser/std/CollectionDeserializer$CollectionReferring.next:Ljava/util/List;
        67: invokeinterface #20,  2           // InterfaceMethod java/util/Collection.addAll:(Ljava/util/Collection;)Z
        72: pop
        73: return
        74: aload         5
        76: getfield      #12                 // Field com/fasterxml/jackson/databind/deser/std/CollectionDeserializer$CollectionReferring.next:Ljava/util/List;
        79: astore        4
        81: goto          16
        84: new           #21                 // class java/lang/IllegalArgumentException
        87: dup
        88: new           #22                 // class java/lang/StringBuilder
        91: dup
        92: invokespecial #23                 // Method java/lang/StringBuilder."<init>":()V
        95: ldc           #24                 // String Trying to resolve a forward reference with id [
        97: invokevirtual #25                 // Method java/lang/StringBuilder.append:(Ljava/lang/String;)Ljava/lang/StringBuilder;
       100: aload_1
       101: invokevirtual #26                 // Method java/lang/StringBuilder.append:(Ljava/lang/Object;)Ljava/lang/StringBuilder;
       104: ldc           #27                 // String ] that wasn\'t previously seen as unresolved.
       106: invokevirtual #25                 // Method java/lang/StringBuilder.append:(Ljava/lang/String;)Ljava/lang/StringBuilder;
       109: invokevirtual #28                 // Method java/lang/StringBuilder.toString:()Ljava/lang/String;
       112: invokespecial #29                 // Method java/lang/IllegalArgumentException."<init>":(Ljava/lang/String;)V
       115: athrow
      LineNumberTable:
        line 505: 0
        line 509: 10
        line 510: 16
        line 511: 25
        line 512: 36
        line 513: 45
        line 514: 51
        line 515: 60
        line 516: 73
        line 518: 74
        line 519: 81
        line 521: 84
      LocalVariableTable:
        Start  Length  Slot  Name   Signature
           36      45     5   ref   Lcom/fasterxml/jackson/databind/deser/std/CollectionDeserializer$CollectionReferring;
            0     116     0  this   Lcom/fasterxml/jackson/databind/deser/std/CollectionDeserializer$CollectionReferringAccumulator;
            0     116     1    id   Ljava/lang/Object;
            0     116     2 value   Ljava/lang/Object;
           10     106     3 iterator   Ljava/util/Iterator;
           16     100     4 previous   Ljava/util/Collection;
      LocalVariableTypeTable:
        Start  Length  Slot  Name   Signature
           10     106     3 iterator   Ljava/util/Iterator<Lcom/fasterxml/jackson/databind/deser/std/CollectionDeserializer$CollectionReferring;>;
           16     100     4 previous   Ljava/util/Collection<Ljava/lang/Object;>;
      StackMapTable: number_of_entries = 3
        frame_type = 253 /* append */
          offset_delta = 16
          locals = [ class java/util/Iterator, class java/util/Collection ]
        frame_type = 252 /* append */
          offset_delta = 57
          locals = [ class com/fasterxml/jackson/databind/deser/std/CollectionDeserializer$CollectionReferring ]
        frame_type = 250 /* chop */
          offset_delta = 9
    Exceptions:
      throws java.io.IOException
}
SourceFile: "CollectionDeserializer.java"
InnerClasses:
  private static final #41= #11 of #94;   // CollectionReferring=class com/fasterxml/jackson/databind/deser/std/CollectionDeserializer$CollectionReferring of class com/fasterxml/jackson/databind/deser/std/CollectionDeserializer
  public static #50= #30 of #94;          // CollectionReferringAccumulator=class com/fasterxml/jackson/databind/deser/std/CollectionDeserializer$CollectionReferringAccumulator of class com/fasterxml/jackson/databind/deser/std/CollectionDeserializer
  public static abstract #65= #64 of #115; // Referring=class com/fasterxml/jackson/databind/deser/impl/ReadableObjectId$Referring of class com/fasterxml/jackson/databind/deser/impl/ReadableObjectId
