Classfile /Users/mw/Projects/slang-braindump/.jar/jar8/assemble/slang-braindump/assemble/content/com/fasterxml/jackson/databind/deser/std/CollectionDeserializer.class
  Last modified May 29, 2022; size 18879 bytes
  SHA-256 checksum 2e947930fb2a6e0092af41ea0b46c99d411fc8e342acec9abbed19fe6597002d
  Compiled from "CollectionDeserializer.java"
public class com.fasterxml.jackson.databind.deser.std.CollectionDeserializer extends com.fasterxml.jackson.databind.deser.std.ContainerDeserializerBase<java.util.Collection<java.lang.Object>> implements com.fasterxml.jackson.databind.deser.ContextualDeserializer
  minor version: 0
  major version: 52
  flags: (0x0021) ACC_PUBLIC, ACC_SUPER
  this_class: #8                          // com/fasterxml/jackson/databind/deser/std/CollectionDeserializer
  super_class: #91                        // com/fasterxml/jackson/databind/deser/std/ContainerDeserializerBase
  interfaces: 1, fields: 5, methods: 20, attributes: 4
Constant pool:
    #1 = Methodref          #8.#233       // com/fasterxml/jackson/databind/deser/std/CollectionDeserializer."<init>":(Lcom/fasterxml/jackson/databind/JavaType;Lcom/fasterxml/jackson/databind/JsonDeserializer;Lcom/fasterxml/jackson/databind/jsontype/TypeDeserializer;Lcom/fasterxml/jackson/databind/deser/ValueInstantiator;Lcom/fasterxml/jackson/databind/JsonDeserializer;Lcom/fasterxml/jackson/databind/deser/NullValueProvider;Ljava/lang/Boolean;)V
    #2 = Methodref          #91.#234      // com/fasterxml/jackson/databind/deser/std/ContainerDeserializerBase."<init>":(Lcom/fasterxml/jackson/databind/JavaType;Lcom/fasterxml/jackson/databind/deser/NullValueProvider;Ljava/lang/Boolean;)V
    #3 = Fieldref           #8.#235       // com/fasterxml/jackson/databind/deser/std/CollectionDeserializer._valueDeserializer:Lcom/fasterxml/jackson/databind/JsonDeserializer;
    #4 = Fieldref           #8.#236       // com/fasterxml/jackson/databind/deser/std/CollectionDeserializer._valueTypeDeserializer:Lcom/fasterxml/jackson/databind/jsontype/TypeDeserializer;
    #5 = Fieldref           #8.#237       // com/fasterxml/jackson/databind/deser/std/CollectionDeserializer._valueInstantiator:Lcom/fasterxml/jackson/databind/deser/ValueInstantiator;
    #6 = Fieldref           #8.#238       // com/fasterxml/jackson/databind/deser/std/CollectionDeserializer._delegateDeserializer:Lcom/fasterxml/jackson/databind/JsonDeserializer;
    #7 = Methodref          #91.#239      // com/fasterxml/jackson/databind/deser/std/ContainerDeserializerBase."<init>":(Lcom/fasterxml/jackson/databind/deser/std/ContainerDeserializerBase;)V
    #8 = Class              #240          // com/fasterxml/jackson/databind/deser/std/CollectionDeserializer
    #9 = Fieldref           #8.#241       // com/fasterxml/jackson/databind/deser/std/CollectionDeserializer._containerType:Lcom/fasterxml/jackson/databind/JavaType;
   #10 = Fieldref           #242.#243     // com/fasterxml/jackson/databind/type/LogicalType.Collection:Lcom/fasterxml/jackson/databind/type/LogicalType;
   #11 = Methodref          #244.#245     // com/fasterxml/jackson/databind/deser/ValueInstantiator.canCreateUsingDelegate:()Z
   #12 = Methodref          #246.#247     // com/fasterxml/jackson/databind/DeserializationContext.getConfig:()Lcom/fasterxml/jackson/databind/DeserializationConfig;
   #13 = Methodref          #244.#248     // com/fasterxml/jackson/databind/deser/ValueInstantiator.getDelegateType:(Lcom/fasterxml/jackson/databind/DeserializationConfig;)Lcom/fasterxml/jackson/databind/JavaType;
   #14 = String             #249          // Invalid delegate-creator definition for %s: value instantiator (%s) returned true for \'canCreateUsingDelegate()\', but null for \'getDelegateType()\'
   #15 = Class              #250          // java/lang/Object
   #16 = Methodref          #15.#251      // java/lang/Object.getClass:()Ljava/lang/Class;
   #17 = Methodref          #252.#253     // java/lang/Class.getName:()Ljava/lang/String;
   #18 = Methodref          #254.#255     // java/lang/String.format:(Ljava/lang/String;[Ljava/lang/Object;)Ljava/lang/String;
   #19 = Methodref          #246.#256     // com/fasterxml/jackson/databind/DeserializationContext.reportBadDefinition:(Lcom/fasterxml/jackson/databind/JavaType;Ljava/lang/String;)Ljava/lang/Object;
   #20 = Methodref          #8.#257       // com/fasterxml/jackson/databind/deser/std/CollectionDeserializer.findDeserializer:(Lcom/fasterxml/jackson/databind/DeserializationContext;Lcom/fasterxml/jackson/databind/JavaType;Lcom/fasterxml/jackson/databind/BeanProperty;)Lcom/fasterxml/jackson/databind/JsonDeserializer;
   #21 = Methodref          #244.#258     // com/fasterxml/jackson/databind/deser/ValueInstantiator.canCreateUsingArrayDelegate:()Z
   #22 = Methodref          #244.#259     // com/fasterxml/jackson/databind/deser/ValueInstantiator.getArrayDelegateType:(Lcom/fasterxml/jackson/databind/DeserializationConfig;)Lcom/fasterxml/jackson/databind/JavaType;
   #23 = String             #260          // Invalid delegate-creator definition for %s: value instantiator (%s) returned true for \'canCreateUsingArrayDelegate()\', but null for \'getArrayDelegateType()\'
   #24 = Class              #261          // java/util/Collection
   #25 = Fieldref           #262.#263     // com/fasterxml/jackson/annotation/JsonFormat$Feature.ACCEPT_SINGLE_VALUE_AS_ARRAY:Lcom/fasterxml/jackson/annotation/JsonFormat$Feature;
   #26 = Methodref          #8.#264       // com/fasterxml/jackson/databind/deser/std/CollectionDeserializer.findFormatFeature:(Lcom/fasterxml/jackson/databind/DeserializationContext;Lcom/fasterxml/jackson/databind/BeanProperty;Ljava/lang/Class;Lcom/fasterxml/jackson/annotation/JsonFormat$Feature;)Ljava/lang/Boolean;
   #27 = Methodref          #8.#265       // com/fasterxml/jackson/databind/deser/std/CollectionDeserializer.findConvertingContentDeserializer:(Lcom/fasterxml/jackson/databind/DeserializationContext;Lcom/fasterxml/jackson/databind/BeanProperty;Lcom/fasterxml/jackson/databind/JsonDeserializer;)Lcom/fasterxml/jackson/databind/JsonDeserializer;
   #28 = Methodref          #266.#267     // com/fasterxml/jackson/databind/JavaType.getContentType:()Lcom/fasterxml/jackson/databind/JavaType;
   #29 = Methodref          #246.#268     // com/fasterxml/jackson/databind/DeserializationContext.findContextualValueDeserializer:(Lcom/fasterxml/jackson/databind/JavaType;Lcom/fasterxml/jackson/databind/BeanProperty;)Lcom/fasterxml/jackson/databind/JsonDeserializer;
   #30 = Methodref          #246.#269     // com/fasterxml/jackson/databind/DeserializationContext.handleSecondaryContextualization:(Lcom/fasterxml/jackson/databind/JsonDeserializer;Lcom/fasterxml/jackson/databind/BeanProperty;Lcom/fasterxml/jackson/databind/JavaType;)Lcom/fasterxml/jackson/databind/JsonDeserializer;
   #31 = Methodref          #270.#271     // com/fasterxml/jackson/databind/jsontype/TypeDeserializer.forProperty:(Lcom/fasterxml/jackson/databind/BeanProperty;)Lcom/fasterxml/jackson/databind/jsontype/TypeDeserializer;
   #32 = Methodref          #8.#272       // com/fasterxml/jackson/databind/deser/std/CollectionDeserializer.findContentNullProvider:(Lcom/fasterxml/jackson/databind/DeserializationContext;Lcom/fasterxml/jackson/databind/BeanProperty;Lcom/fasterxml/jackson/databind/JsonDeserializer;)Lcom/fasterxml/jackson/databind/deser/NullValueProvider;
   #33 = Fieldref           #8.#273       // com/fasterxml/jackson/databind/deser/std/CollectionDeserializer._unwrapSingle:Ljava/lang/Boolean;
   #34 = Methodref          #274.#275     // java/util/Objects.equals:(Ljava/lang/Object;Ljava/lang/Object;)Z
   #35 = Fieldref           #8.#276       // com/fasterxml/jackson/databind/deser/std/CollectionDeserializer._nullProvider:Lcom/fasterxml/jackson/databind/deser/NullValueProvider;
   #36 = Methodref          #8.#277       // com/fasterxml/jackson/databind/deser/std/CollectionDeserializer.withResolved:(Lcom/fasterxml/jackson/databind/JsonDeserializer;Lcom/fasterxml/jackson/databind/JsonDeserializer;Lcom/fasterxml/jackson/databind/jsontype/TypeDeserializer;Lcom/fasterxml/jackson/databind/deser/NullValueProvider;Ljava/lang/Boolean;)Lcom/fasterxml/jackson/databind/deser/std/CollectionDeserializer;
   #37 = Methodref          #278.#279     // com/fasterxml/jackson/databind/JsonDeserializer.deserialize:(Lcom/fasterxml/jackson/core/JsonParser;Lcom/fasterxml/jackson/databind/DeserializationContext;)Ljava/lang/Object;
   #38 = Methodref          #244.#280     // com/fasterxml/jackson/databind/deser/ValueInstantiator.createUsingDelegate:(Lcom/fasterxml/jackson/databind/DeserializationContext;Ljava/lang/Object;)Ljava/lang/Object;
   #39 = Methodref          #281.#282     // com/fasterxml/jackson/core/JsonParser.isExpectedStartArrayToken:()Z
   #40 = Methodref          #8.#283       // com/fasterxml/jackson/databind/deser/std/CollectionDeserializer.createDefaultInstance:(Lcom/fasterxml/jackson/databind/DeserializationContext;)Ljava/util/Collection;
   #41 = Methodref          #8.#284       // com/fasterxml/jackson/databind/deser/std/CollectionDeserializer._deserializeFromArray:(Lcom/fasterxml/jackson/core/JsonParser;Lcom/fasterxml/jackson/databind/DeserializationContext;Ljava/util/Collection;)Ljava/util/Collection;
   #42 = Fieldref           #285.#286     // com/fasterxml/jackson/core/JsonToken.VALUE_STRING:Lcom/fasterxml/jackson/core/JsonToken;
   #43 = Methodref          #281.#287     // com/fasterxml/jackson/core/JsonParser.hasToken:(Lcom/fasterxml/jackson/core/JsonToken;)Z
   #44 = Methodref          #281.#288     // com/fasterxml/jackson/core/JsonParser.getText:()Ljava/lang/String;
   #45 = Methodref          #8.#289       // com/fasterxml/jackson/databind/deser/std/CollectionDeserializer._deserializeFromString:(Lcom/fasterxml/jackson/core/JsonParser;Lcom/fasterxml/jackson/databind/DeserializationContext;Ljava/lang/String;)Ljava/util/Collection;
   #46 = Methodref          #8.#290       // com/fasterxml/jackson/databind/deser/std/CollectionDeserializer.handleNonArray:(Lcom/fasterxml/jackson/core/JsonParser;Lcom/fasterxml/jackson/databind/DeserializationContext;Ljava/util/Collection;)Ljava/util/Collection;
   #47 = Methodref          #244.#291     // com/fasterxml/jackson/databind/deser/ValueInstantiator.createUsingDefault:(Lcom/fasterxml/jackson/databind/DeserializationContext;)Ljava/lang/Object;
   #48 = Methodref          #270.#292     // com/fasterxml/jackson/databind/jsontype/TypeDeserializer.deserializeTypedFromArray:(Lcom/fasterxml/jackson/core/JsonParser;Lcom/fasterxml/jackson/databind/DeserializationContext;)Ljava/lang/Object;
   #49 = Methodref          #8.#293       // com/fasterxml/jackson/databind/deser/std/CollectionDeserializer.handledType:()Ljava/lang/Class;
   #50 = Methodref          #254.#294     // java/lang/String.isEmpty:()Z
   #51 = Methodref          #8.#295       // com/fasterxml/jackson/databind/deser/std/CollectionDeserializer.logicalType:()Lcom/fasterxml/jackson/databind/type/LogicalType;
   #52 = Fieldref           #296.#297     // com/fasterxml/jackson/databind/cfg/CoercionInputShape.EmptyString:Lcom/fasterxml/jackson/databind/cfg/CoercionInputShape;
   #53 = Methodref          #246.#298     // com/fasterxml/jackson/databind/DeserializationContext.findCoercionAction:(Lcom/fasterxml/jackson/databind/type/LogicalType;Ljava/lang/Class;Lcom/fasterxml/jackson/databind/cfg/CoercionInputShape;)Lcom/fasterxml/jackson/databind/cfg/CoercionAction;
   #54 = String             #299          // empty String (\"\")
   #55 = Methodref          #8.#300       // com/fasterxml/jackson/databind/deser/std/CollectionDeserializer._checkCoercionFail:(Lcom/fasterxml/jackson/databind/DeserializationContext;Lcom/fasterxml/jackson/databind/cfg/CoercionAction;Ljava/lang/Class;Ljava/lang/Object;Ljava/lang/String;)Lcom/fasterxml/jackson/databind/cfg/CoercionAction;
   #56 = Methodref          #8.#301       // com/fasterxml/jackson/databind/deser/std/CollectionDeserializer._deserializeFromEmptyString:(Lcom/fasterxml/jackson/core/JsonParser;Lcom/fasterxml/jackson/databind/DeserializationContext;Lcom/fasterxml/jackson/databind/cfg/CoercionAction;Ljava/lang/Class;Ljava/lang/String;)Ljava/lang/Object;
   #57 = Methodref          #8.#302       // com/fasterxml/jackson/databind/deser/std/CollectionDeserializer._isBlank:(Ljava/lang/String;)Z
   #58 = Fieldref           #303.#304     // com/fasterxml/jackson/databind/cfg/CoercionAction.Fail:Lcom/fasterxml/jackson/databind/cfg/CoercionAction;
   #59 = Methodref          #246.#305     // com/fasterxml/jackson/databind/DeserializationContext.findCoercionFromBlankString:(Lcom/fasterxml/jackson/databind/type/LogicalType;Ljava/lang/Class;Lcom/fasterxml/jackson/databind/cfg/CoercionAction;)Lcom/fasterxml/jackson/databind/cfg/CoercionAction;
   #60 = String             #306          // blank String (all whitespace)
   #61 = Methodref          #281.#307     // com/fasterxml/jackson/core/JsonParser.setCurrentValue:(Ljava/lang/Object;)V
   #62 = Methodref          #278.#308     // com/fasterxml/jackson/databind/JsonDeserializer.getObjectIdReader:()Lcom/fasterxml/jackson/databind/deser/impl/ObjectIdReader;
   #63 = Methodref          #8.#309       // com/fasterxml/jackson/databind/deser/std/CollectionDeserializer._deserializeWithObjectId:(Lcom/fasterxml/jackson/core/JsonParser;Lcom/fasterxml/jackson/databind/DeserializationContext;Ljava/util/Collection;)Ljava/util/Collection;
   #64 = Methodref          #281.#310     // com/fasterxml/jackson/core/JsonParser.nextToken:()Lcom/fasterxml/jackson/core/JsonToken;
   #65 = Fieldref           #285.#311     // com/fasterxml/jackson/core/JsonToken.END_ARRAY:Lcom/fasterxml/jackson/core/JsonToken;
   #66 = Fieldref           #285.#312     // com/fasterxml/jackson/core/JsonToken.VALUE_NULL:Lcom/fasterxml/jackson/core/JsonToken;
   #67 = Fieldref           #8.#313       // com/fasterxml/jackson/databind/deser/std/CollectionDeserializer._skipNullValues:Z
   #68 = InterfaceMethodref #314.#315     // com/fasterxml/jackson/databind/deser/NullValueProvider.getNullValue:(Lcom/fasterxml/jackson/databind/DeserializationContext;)Ljava/lang/Object;
   #69 = Methodref          #278.#316     // com/fasterxml/jackson/databind/JsonDeserializer.deserializeWithType:(Lcom/fasterxml/jackson/core/JsonParser;Lcom/fasterxml/jackson/databind/DeserializationContext;Lcom/fasterxml/jackson/databind/jsontype/TypeDeserializer;)Ljava/lang/Object;
   #70 = InterfaceMethodref #24.#317      // java/util/Collection.add:(Ljava/lang/Object;)Z
   #71 = Class              #318          // java/lang/Exception
   #72 = Fieldref           #319.#320     // com/fasterxml/jackson/databind/DeserializationFeature.WRAP_EXCEPTIONS:Lcom/fasterxml/jackson/databind/DeserializationFeature;
   #73 = Methodref          #246.#321     // com/fasterxml/jackson/databind/DeserializationContext.isEnabled:(Lcom/fasterxml/jackson/databind/DeserializationFeature;)Z
   #74 = Methodref          #322.#323     // com/fasterxml/jackson/databind/util/ClassUtil.throwIfRTE:(Ljava/lang/Throwable;)Ljava/lang/Throwable;
   #75 = InterfaceMethodref #24.#324      // java/util/Collection.size:()I
   #76 = Methodref          #160.#325     // com/fasterxml/jackson/databind/JsonMappingException.wrapWithPath:(Ljava/lang/Throwable;Ljava/lang/Object;I)Lcom/fasterxml/jackson/databind/JsonMappingException;
   #77 = Fieldref           #326.#327     // java/lang/Boolean.TRUE:Ljava/lang/Boolean;
   #78 = Fieldref           #319.#328     // com/fasterxml/jackson/databind/DeserializationFeature.ACCEPT_SINGLE_VALUE_AS_ARRAY:Lcom/fasterxml/jackson/databind/DeserializationFeature;
   #79 = Methodref          #246.#329     // com/fasterxml/jackson/databind/DeserializationContext.handleUnexpectedToken:(Lcom/fasterxml/jackson/databind/JavaType;Lcom/fasterxml/jackson/core/JsonParser;)Ljava/lang/Object;
   #80 = Class              #330          // com/fasterxml/jackson/databind/deser/std/CollectionDeserializer$CollectionReferringAccumulator
   #81 = Methodref          #266.#331     // com/fasterxml/jackson/databind/JavaType.getRawClass:()Ljava/lang/Class;
   #82 = Methodref          #80.#332      // com/fasterxml/jackson/databind/deser/std/CollectionDeserializer$CollectionReferringAccumulator."<init>":(Ljava/lang/Class;Ljava/util/Collection;)V
   #83 = Methodref          #80.#333      // com/fasterxml/jackson/databind/deser/std/CollectionDeserializer$CollectionReferringAccumulator.add:(Ljava/lang/Object;)V
   #84 = Class              #334          // com/fasterxml/jackson/databind/deser/UnresolvedForwardReference
   #85 = Methodref          #80.#335      // com/fasterxml/jackson/databind/deser/std/CollectionDeserializer$CollectionReferringAccumulator.handleUnresolvedReference:(Lcom/fasterxml/jackson/databind/deser/UnresolvedForwardReference;)Lcom/fasterxml/jackson/databind/deser/impl/ReadableObjectId$Referring;
   #86 = Methodref          #84.#336      // com/fasterxml/jackson/databind/deser/UnresolvedForwardReference.getRoid:()Lcom/fasterxml/jackson/databind/deser/impl/ReadableObjectId;
   #87 = Methodref          #337.#338     // com/fasterxml/jackson/databind/deser/impl/ReadableObjectId.appendReferring:(Lcom/fasterxml/jackson/databind/deser/impl/ReadableObjectId$Referring;)V
   #88 = Methodref          #8.#339       // com/fasterxml/jackson/databind/deser/std/CollectionDeserializer.deserialize:(Lcom/fasterxml/jackson/core/JsonParser;Lcom/fasterxml/jackson/databind/DeserializationContext;Ljava/util/Collection;)Ljava/util/Collection;
   #89 = Methodref          #8.#340       // com/fasterxml/jackson/databind/deser/std/CollectionDeserializer.deserialize:(Lcom/fasterxml/jackson/core/JsonParser;Lcom/fasterxml/jackson/databind/DeserializationContext;)Ljava/util/Collection;
   #90 = Methodref          #8.#341       // com/fasterxml/jackson/databind/deser/std/CollectionDeserializer.createContextual:(Lcom/fasterxml/jackson/databind/DeserializationContext;Lcom/fasterxml/jackson/databind/BeanProperty;)Lcom/fasterxml/jackson/databind/deser/std/CollectionDeserializer;
   #91 = Class              #342          // com/fasterxml/jackson/databind/deser/std/ContainerDeserializerBase
   #92 = Class              #343          // com/fasterxml/jackson/databind/deser/ContextualDeserializer
   #93 = Class              #344          // com/fasterxml/jackson/databind/deser/std/CollectionDeserializer$CollectionReferring
   #94 = Utf8               CollectionReferring
   #95 = Utf8               InnerClasses
   #96 = Utf8               CollectionReferringAccumulator
   #97 = Utf8               serialVersionUID
   #98 = Utf8               J
   #99 = Utf8               ConstantValue
  #100 = Long               -1l
  #102 = Utf8               _valueDeserializer
  #103 = Utf8               Lcom/fasterxml/jackson/databind/JsonDeserializer;
  #104 = Utf8               Signature
  #105 = Utf8               Lcom/fasterxml/jackson/databind/JsonDeserializer<Ljava/lang/Object;>;
  #106 = Utf8               _valueTypeDeserializer
  #107 = Utf8               Lcom/fasterxml/jackson/databind/jsontype/TypeDeserializer;
  #108 = Utf8               _valueInstantiator
  #109 = Utf8               Lcom/fasterxml/jackson/databind/deser/ValueInstantiator;
  #110 = Utf8               _delegateDeserializer
  #111 = Utf8               <init>
  #112 = Utf8               (Lcom/fasterxml/jackson/databind/JavaType;Lcom/fasterxml/jackson/databind/JsonDeserializer;Lcom/fasterxml/jackson/databind/jsontype/TypeDeserializer;Lcom/fasterxml/jackson/databind/deser/ValueInstantiator;)V
  #113 = Utf8               Code
  #114 = Utf8               LineNumberTable
  #115 = Utf8               LocalVariableTable
  #116 = Utf8               this
  #117 = Utf8               Lcom/fasterxml/jackson/databind/deser/std/CollectionDeserializer;
  #118 = Utf8               collectionType
  #119 = Utf8               Lcom/fasterxml/jackson/databind/JavaType;
  #120 = Utf8               valueDeser
  #121 = Utf8               valueTypeDeser
  #122 = Utf8               valueInstantiator
  #123 = Utf8               LocalVariableTypeTable
  #124 = Utf8               (Lcom/fasterxml/jackson/databind/JavaType;Lcom/fasterxml/jackson/databind/JsonDeserializer<Ljava/lang/Object;>;Lcom/fasterxml/jackson/databind/jsontype/TypeDeserializer;Lcom/fasterxml/jackson/databind/deser/ValueInstantiator;)V
  #125 = Utf8               (Lcom/fasterxml/jackson/databind/JavaType;Lcom/fasterxml/jackson/databind/JsonDeserializer;Lcom/fasterxml/jackson/databind/jsontype/TypeDeserializer;Lcom/fasterxml/jackson/databind/deser/ValueInstantiator;Lcom/fasterxml/jackson/databind/JsonDeserializer;Lcom/fasterxml/jackson/databind/deser/NullValueProvider;Ljava/lang/Boolean;)V
  #126 = Utf8               delegateDeser
  #127 = Utf8               nuller
  #128 = Utf8               Lcom/fasterxml/jackson/databind/deser/NullValueProvider;
  #129 = Utf8               unwrapSingle
  #130 = Utf8               Ljava/lang/Boolean;
  #131 = Utf8               (Lcom/fasterxml/jackson/databind/JavaType;Lcom/fasterxml/jackson/databind/JsonDeserializer<Ljava/lang/Object;>;Lcom/fasterxml/jackson/databind/jsontype/TypeDeserializer;Lcom/fasterxml/jackson/databind/deser/ValueInstantiator;Lcom/fasterxml/jackson/databind/JsonDeserializer<Ljava/lang/Object;>;Lcom/fasterxml/jackson/databind/deser/NullValueProvider;Ljava/lang/Boolean;)V
  #132 = Utf8               (Lcom/fasterxml/jackson/databind/deser/std/CollectionDeserializer;)V
  #133 = Utf8               src
  #134 = Utf8               withResolved
  #135 = Utf8               (Lcom/fasterxml/jackson/databind/JsonDeserializer;Lcom/fasterxml/jackson/databind/JsonDeserializer;Lcom/fasterxml/jackson/databind/jsontype/TypeDeserializer;Lcom/fasterxml/jackson/databind/deser/NullValueProvider;Ljava/lang/Boolean;)Lcom/fasterxml/jackson/databind/deser/std/CollectionDeserializer;
  #136 = Utf8               dd
  #137 = Utf8               vd
  #138 = Utf8               vtd
  #139 = Utf8               Lcom/fasterxml/jackson/databind/JsonDeserializer<*>;
  #140 = Utf8               (Lcom/fasterxml/jackson/databind/JsonDeserializer<*>;Lcom/fasterxml/jackson/databind/JsonDeserializer<*>;Lcom/fasterxml/jackson/databind/jsontype/TypeDeserializer;Lcom/fasterxml/jackson/databind/deser/NullValueProvider;Ljava/lang/Boolean;)Lcom/fasterxml/jackson/databind/deser/std/CollectionDeserializer;
  #141 = Utf8               isCachable
  #142 = Utf8               ()Z
  #143 = Utf8               StackMapTable
  #144 = Utf8               logicalType
  #145 = Utf8               ()Lcom/fasterxml/jackson/databind/type/LogicalType;
  #146 = Utf8               createContextual
  #147 = Utf8               (Lcom/fasterxml/jackson/databind/DeserializationContext;Lcom/fasterxml/jackson/databind/BeanProperty;)Lcom/fasterxml/jackson/databind/deser/std/CollectionDeserializer;
  #148 = Utf8               delegateType
  #149 = Utf8               ctxt
  #150 = Utf8               Lcom/fasterxml/jackson/databind/DeserializationContext;
  #151 = Utf8               property
  #152 = Utf8               Lcom/fasterxml/jackson/databind/BeanProperty;
  #153 = Utf8               vt
  #154 = Class              #345          // com/fasterxml/jackson/databind/JsonDeserializer
  #155 = Class              #346          // com/fasterxml/jackson/databind/JavaType
  #156 = Class              #347          // java/lang/Boolean
  #157 = Class              #348          // com/fasterxml/jackson/databind/jsontype/TypeDeserializer
  #158 = Class              #349          // com/fasterxml/jackson/databind/deser/NullValueProvider
  #159 = Utf8               Exceptions
  #160 = Class              #350          // com/fasterxml/jackson/databind/JsonMappingException
  #161 = Utf8               getContentDeserializer
  #162 = Utf8               ()Lcom/fasterxml/jackson/databind/JsonDeserializer;
  #163 = Utf8               ()Lcom/fasterxml/jackson/databind/JsonDeserializer<Ljava/lang/Object;>;
  #164 = Utf8               getValueInstantiator
  #165 = Utf8               ()Lcom/fasterxml/jackson/databind/deser/ValueInstantiator;
  #166 = Utf8               deserialize
  #167 = Utf8               (Lcom/fasterxml/jackson/core/JsonParser;Lcom/fasterxml/jackson/databind/DeserializationContext;)Ljava/util/Collection;
  #168 = Utf8               p
  #169 = Utf8               Lcom/fasterxml/jackson/core/JsonParser;
  #170 = Class              #351          // java/io/IOException
  #171 = Utf8               (Lcom/fasterxml/jackson/core/JsonParser;Lcom/fasterxml/jackson/databind/DeserializationContext;)Ljava/util/Collection<Ljava/lang/Object;>;
  #172 = Utf8               createDefaultInstance
  #173 = Utf8               (Lcom/fasterxml/jackson/databind/DeserializationContext;)Ljava/util/Collection;
  #174 = Utf8               (Lcom/fasterxml/jackson/databind/DeserializationContext;)Ljava/util/Collection<Ljava/lang/Object;>;
  #175 = Utf8               (Lcom/fasterxml/jackson/core/JsonParser;Lcom/fasterxml/jackson/databind/DeserializationContext;Ljava/util/Collection;)Ljava/util/Collection;
  #176 = Utf8               result
  #177 = Utf8               Ljava/util/Collection;
  #178 = Utf8               Ljava/util/Collection<Ljava/lang/Object;>;
  #179 = Utf8               (Lcom/fasterxml/jackson/core/JsonParser;Lcom/fasterxml/jackson/databind/DeserializationContext;Ljava/util/Collection<Ljava/lang/Object;>;)Ljava/util/Collection<Ljava/lang/Object;>;
  #180 = Utf8               deserializeWithType
  #181 = Utf8               (Lcom/fasterxml/jackson/core/JsonParser;Lcom/fasterxml/jackson/databind/DeserializationContext;Lcom/fasterxml/jackson/databind/jsontype/TypeDeserializer;)Ljava/lang/Object;
  #182 = Utf8               typeDeserializer
  #183 = Utf8               _deserializeFromString
  #184 = Utf8               (Lcom/fasterxml/jackson/core/JsonParser;Lcom/fasterxml/jackson/databind/DeserializationContext;Ljava/lang/String;)Ljava/util/Collection;
  #185 = Utf8               act
  #186 = Utf8               Lcom/fasterxml/jackson/databind/cfg/CoercionAction;
  #187 = Utf8               value
  #188 = Utf8               Ljava/lang/String;
  #189 = Utf8               rawTargetType
  #190 = Utf8               Ljava/lang/Class;
  #191 = Utf8               Ljava/lang/Class<*>;
  #192 = Class              #352          // java/lang/Class
  #193 = Utf8               (Lcom/fasterxml/jackson/core/JsonParser;Lcom/fasterxml/jackson/databind/DeserializationContext;Ljava/lang/String;)Ljava/util/Collection<Ljava/lang/Object;>;
  #194 = Utf8               _deserializeFromArray
  #195 = Utf8               Ljava/lang/Object;
  #196 = Utf8               wrap
  #197 = Utf8               Z
  #198 = Utf8               e
  #199 = Utf8               Ljava/lang/Exception;
  #200 = Utf8               valueDes
  #201 = Utf8               typeDeser
  #202 = Utf8               t
  #203 = Utf8               Lcom/fasterxml/jackson/core/JsonToken;
  #204 = Class              #353          // com/fasterxml/jackson/core/JsonToken
  #205 = Class              #250          // java/lang/Object
  #206 = Class              #240          // com/fasterxml/jackson/databind/deser/std/CollectionDeserializer
  #207 = Class              #354          // com/fasterxml/jackson/core/JsonParser
  #208 = Class              #355          // com/fasterxml/jackson/databind/DeserializationContext
  #209 = Class              #261          // java/util/Collection
  #210 = Class              #318          // java/lang/Exception
  #211 = Utf8               handleNonArray
  #212 = Utf8               canWrap
  #213 = Utf8               _deserializeWithObjectId
  #214 = Utf8               ref
  #215 = Class              #356          // com/fasterxml/jackson/databind/deser/impl/ReadableObjectId$Referring
  #216 = Utf8               Referring
  #217 = Utf8               Lcom/fasterxml/jackson/databind/deser/impl/ReadableObjectId$Referring;
  #218 = Utf8               reference
  #219 = Utf8               Lcom/fasterxml/jackson/databind/deser/UnresolvedForwardReference;
  #220 = Utf8               referringAccumulator
  #221 = Utf8               Lcom/fasterxml/jackson/databind/deser/std/CollectionDeserializer$CollectionReferringAccumulator;
  #222 = Class              #330          // com/fasterxml/jackson/databind/deser/std/CollectionDeserializer$CollectionReferringAccumulator
  #223 = Class              #334          // com/fasterxml/jackson/databind/deser/UnresolvedForwardReference
  #224 = Utf8               (Lcom/fasterxml/jackson/core/JsonParser;Lcom/fasterxml/jackson/databind/DeserializationContext;Ljava/lang/Object;)Ljava/lang/Object;
  #225 = Class              #357          // com/fasterxml/jackson/core/JacksonException
  #226 = Utf8               (Lcom/fasterxml/jackson/core/JsonParser;Lcom/fasterxml/jackson/databind/DeserializationContext;)Ljava/lang/Object;
  #227 = Utf8               (Lcom/fasterxml/jackson/databind/DeserializationContext;Lcom/fasterxml/jackson/databind/BeanProperty;)Lcom/fasterxml/jackson/databind/JsonDeserializer;
  #228 = Utf8               Lcom/fasterxml/jackson/databind/deser/std/ContainerDeserializerBase<Ljava/util/Collection<Ljava/lang/Object;>;>;Lcom/fasterxml/jackson/databind/deser/ContextualDeserializer;
  #229 = Utf8               SourceFile
  #230 = Utf8               CollectionDeserializer.java
  #231 = Utf8               RuntimeVisibleAnnotations
  #232 = Utf8               Lcom/fasterxml/jackson/databind/annotation/JacksonStdImpl;
  #233 = NameAndType        #111:#125     // "<init>":(Lcom/fasterxml/jackson/databind/JavaType;Lcom/fasterxml/jackson/databind/JsonDeserializer;Lcom/fasterxml/jackson/databind/jsontype/TypeDeserializer;Lcom/fasterxml/jackson/databind/deser/ValueInstantiator;Lcom/fasterxml/jackson/databind/JsonDeserializer;Lcom/fasterxml/jackson/databind/deser/NullValueProvider;Ljava/lang/Boolean;)V
  #234 = NameAndType        #111:#358     // "<init>":(Lcom/fasterxml/jackson/databind/JavaType;Lcom/fasterxml/jackson/databind/deser/NullValueProvider;Ljava/lang/Boolean;)V
  #235 = NameAndType        #102:#103     // _valueDeserializer:Lcom/fasterxml/jackson/databind/JsonDeserializer;
  #236 = NameAndType        #106:#107     // _valueTypeDeserializer:Lcom/fasterxml/jackson/databind/jsontype/TypeDeserializer;
  #237 = NameAndType        #108:#109     // _valueInstantiator:Lcom/fasterxml/jackson/databind/deser/ValueInstantiator;
  #238 = NameAndType        #110:#103     // _delegateDeserializer:Lcom/fasterxml/jackson/databind/JsonDeserializer;
  #239 = NameAndType        #111:#359     // "<init>":(Lcom/fasterxml/jackson/databind/deser/std/ContainerDeserializerBase;)V
  #240 = Utf8               com/fasterxml/jackson/databind/deser/std/CollectionDeserializer
  #241 = NameAndType        #360:#119     // _containerType:Lcom/fasterxml/jackson/databind/JavaType;
  #242 = Class              #361          // com/fasterxml/jackson/databind/type/LogicalType
  #243 = NameAndType        #362:#363     // Collection:Lcom/fasterxml/jackson/databind/type/LogicalType;
  #244 = Class              #364          // com/fasterxml/jackson/databind/deser/ValueInstantiator
  #245 = NameAndType        #365:#142     // canCreateUsingDelegate:()Z
  #246 = Class              #355          // com/fasterxml/jackson/databind/DeserializationContext
  #247 = NameAndType        #366:#367     // getConfig:()Lcom/fasterxml/jackson/databind/DeserializationConfig;
  #248 = NameAndType        #368:#369     // getDelegateType:(Lcom/fasterxml/jackson/databind/DeserializationConfig;)Lcom/fasterxml/jackson/databind/JavaType;
  #249 = Utf8               Invalid delegate-creator definition for %s: value instantiator (%s) returned true for \'canCreateUsingDelegate()\', but null for \'getDelegateType()\'
  #250 = Utf8               java/lang/Object
  #251 = NameAndType        #370:#371     // getClass:()Ljava/lang/Class;
  #252 = Class              #352          // java/lang/Class
  #253 = NameAndType        #372:#373     // getName:()Ljava/lang/String;
  #254 = Class              #374          // java/lang/String
  #255 = NameAndType        #375:#376     // format:(Ljava/lang/String;[Ljava/lang/Object;)Ljava/lang/String;
  #256 = NameAndType        #377:#378     // reportBadDefinition:(Lcom/fasterxml/jackson/databind/JavaType;Ljava/lang/String;)Ljava/lang/Object;
  #257 = NameAndType        #379:#380     // findDeserializer:(Lcom/fasterxml/jackson/databind/DeserializationContext;Lcom/fasterxml/jackson/databind/JavaType;Lcom/fasterxml/jackson/databind/BeanProperty;)Lcom/fasterxml/jackson/databind/JsonDeserializer;
  #258 = NameAndType        #381:#142     // canCreateUsingArrayDelegate:()Z
  #259 = NameAndType        #382:#369     // getArrayDelegateType:(Lcom/fasterxml/jackson/databind/DeserializationConfig;)Lcom/fasterxml/jackson/databind/JavaType;
  #260 = Utf8               Invalid delegate-creator definition for %s: value instantiator (%s) returned true for \'canCreateUsingArrayDelegate()\', but null for \'getArrayDelegateType()\'
  #261 = Utf8               java/util/Collection
  #262 = Class              #384          // com/fasterxml/jackson/annotation/JsonFormat$Feature
  #263 = NameAndType        #386:#387     // ACCEPT_SINGLE_VALUE_AS_ARRAY:Lcom/fasterxml/jackson/annotation/JsonFormat$Feature;
  #264 = NameAndType        #388:#389     // findFormatFeature:(Lcom/fasterxml/jackson/databind/DeserializationContext;Lcom/fasterxml/jackson/databind/BeanProperty;Ljava/lang/Class;Lcom/fasterxml/jackson/annotation/JsonFormat$Feature;)Ljava/lang/Boolean;
  #265 = NameAndType        #390:#391     // findConvertingContentDeserializer:(Lcom/fasterxml/jackson/databind/DeserializationContext;Lcom/fasterxml/jackson/databind/BeanProperty;Lcom/fasterxml/jackson/databind/JsonDeserializer;)Lcom/fasterxml/jackson/databind/JsonDeserializer;
  #266 = Class              #346          // com/fasterxml/jackson/databind/JavaType
  #267 = NameAndType        #392:#393     // getContentType:()Lcom/fasterxml/jackson/databind/JavaType;
  #268 = NameAndType        #394:#395     // findContextualValueDeserializer:(Lcom/fasterxml/jackson/databind/JavaType;Lcom/fasterxml/jackson/databind/BeanProperty;)Lcom/fasterxml/jackson/databind/JsonDeserializer;
  #269 = NameAndType        #396:#397     // handleSecondaryContextualization:(Lcom/fasterxml/jackson/databind/JsonDeserializer;Lcom/fasterxml/jackson/databind/BeanProperty;Lcom/fasterxml/jackson/databind/JavaType;)Lcom/fasterxml/jackson/databind/JsonDeserializer;
  #270 = Class              #348          // com/fasterxml/jackson/databind/jsontype/TypeDeserializer
  #271 = NameAndType        #398:#399     // forProperty:(Lcom/fasterxml/jackson/databind/BeanProperty;)Lcom/fasterxml/jackson/databind/jsontype/TypeDeserializer;
  #272 = NameAndType        #400:#401     // findContentNullProvider:(Lcom/fasterxml/jackson/databind/DeserializationContext;Lcom/fasterxml/jackson/databind/BeanProperty;Lcom/fasterxml/jackson/databind/JsonDeserializer;)Lcom/fasterxml/jackson/databind/deser/NullValueProvider;
  #273 = NameAndType        #402:#130     // _unwrapSingle:Ljava/lang/Boolean;
  #274 = Class              #403          // java/util/Objects
  #275 = NameAndType        #404:#405     // equals:(Ljava/lang/Object;Ljava/lang/Object;)Z
  #276 = NameAndType        #406:#128     // _nullProvider:Lcom/fasterxml/jackson/databind/deser/NullValueProvider;
  #277 = NameAndType        #134:#135     // withResolved:(Lcom/fasterxml/jackson/databind/JsonDeserializer;Lcom/fasterxml/jackson/databind/JsonDeserializer;Lcom/fasterxml/jackson/databind/jsontype/TypeDeserializer;Lcom/fasterxml/jackson/databind/deser/NullValueProvider;Ljava/lang/Boolean;)Lcom/fasterxml/jackson/databind/deser/std/CollectionDeserializer;
  #278 = Class              #345          // com/fasterxml/jackson/databind/JsonDeserializer
  #279 = NameAndType        #166:#226     // deserialize:(Lcom/fasterxml/jackson/core/JsonParser;Lcom/fasterxml/jackson/databind/DeserializationContext;)Ljava/lang/Object;
  #280 = NameAndType        #407:#408     // createUsingDelegate:(Lcom/fasterxml/jackson/databind/DeserializationContext;Ljava/lang/Object;)Ljava/lang/Object;
  #281 = Class              #354          // com/fasterxml/jackson/core/JsonParser
  #282 = NameAndType        #409:#142     // isExpectedStartArrayToken:()Z
  #283 = NameAndType        #172:#173     // createDefaultInstance:(Lcom/fasterxml/jackson/databind/DeserializationContext;)Ljava/util/Collection;
  #284 = NameAndType        #194:#175     // _deserializeFromArray:(Lcom/fasterxml/jackson/core/JsonParser;Lcom/fasterxml/jackson/databind/DeserializationContext;Ljava/util/Collection;)Ljava/util/Collection;
  #285 = Class              #353          // com/fasterxml/jackson/core/JsonToken
  #286 = NameAndType        #410:#203     // VALUE_STRING:Lcom/fasterxml/jackson/core/JsonToken;
  #287 = NameAndType        #411:#412     // hasToken:(Lcom/fasterxml/jackson/core/JsonToken;)Z
  #288 = NameAndType        #413:#373     // getText:()Ljava/lang/String;
  #289 = NameAndType        #183:#184     // _deserializeFromString:(Lcom/fasterxml/jackson/core/JsonParser;Lcom/fasterxml/jackson/databind/DeserializationContext;Ljava/lang/String;)Ljava/util/Collection;
  #290 = NameAndType        #211:#175     // handleNonArray:(Lcom/fasterxml/jackson/core/JsonParser;Lcom/fasterxml/jackson/databind/DeserializationContext;Ljava/util/Collection;)Ljava/util/Collection;
  #291 = NameAndType        #414:#415     // createUsingDefault:(Lcom/fasterxml/jackson/databind/DeserializationContext;)Ljava/lang/Object;
  #292 = NameAndType        #416:#226     // deserializeTypedFromArray:(Lcom/fasterxml/jackson/core/JsonParser;Lcom/fasterxml/jackson/databind/DeserializationContext;)Ljava/lang/Object;
  #293 = NameAndType        #417:#371     // handledType:()Ljava/lang/Class;
  #294 = NameAndType        #418:#142     // isEmpty:()Z
  #295 = NameAndType        #144:#145     // logicalType:()Lcom/fasterxml/jackson/databind/type/LogicalType;
  #296 = Class              #419          // com/fasterxml/jackson/databind/cfg/CoercionInputShape
  #297 = NameAndType        #420:#421     // EmptyString:Lcom/fasterxml/jackson/databind/cfg/CoercionInputShape;
  #298 = NameAndType        #422:#423     // findCoercionAction:(Lcom/fasterxml/jackson/databind/type/LogicalType;Ljava/lang/Class;Lcom/fasterxml/jackson/databind/cfg/CoercionInputShape;)Lcom/fasterxml/jackson/databind/cfg/CoercionAction;
  #299 = Utf8               empty String (\"\")
  #300 = NameAndType        #424:#425     // _checkCoercionFail:(Lcom/fasterxml/jackson/databind/DeserializationContext;Lcom/fasterxml/jackson/databind/cfg/CoercionAction;Ljava/lang/Class;Ljava/lang/Object;Ljava/lang/String;)Lcom/fasterxml/jackson/databind/cfg/CoercionAction;
  #301 = NameAndType        #426:#427     // _deserializeFromEmptyString:(Lcom/fasterxml/jackson/core/JsonParser;Lcom/fasterxml/jackson/databind/DeserializationContext;Lcom/fasterxml/jackson/databind/cfg/CoercionAction;Ljava/lang/Class;Ljava/lang/String;)Ljava/lang/Object;
  #302 = NameAndType        #428:#429     // _isBlank:(Ljava/lang/String;)Z
  #303 = Class              #430          // com/fasterxml/jackson/databind/cfg/CoercionAction
  #304 = NameAndType        #431:#186     // Fail:Lcom/fasterxml/jackson/databind/cfg/CoercionAction;
  #305 = NameAndType        #432:#433     // findCoercionFromBlankString:(Lcom/fasterxml/jackson/databind/type/LogicalType;Ljava/lang/Class;Lcom/fasterxml/jackson/databind/cfg/CoercionAction;)Lcom/fasterxml/jackson/databind/cfg/CoercionAction;
  #306 = Utf8               blank String (all whitespace)
  #307 = NameAndType        #434:#435     // setCurrentValue:(Ljava/lang/Object;)V
  #308 = NameAndType        #436:#437     // getObjectIdReader:()Lcom/fasterxml/jackson/databind/deser/impl/ObjectIdReader;
  #309 = NameAndType        #213:#175     // _deserializeWithObjectId:(Lcom/fasterxml/jackson/core/JsonParser;Lcom/fasterxml/jackson/databind/DeserializationContext;Ljava/util/Collection;)Ljava/util/Collection;
  #310 = NameAndType        #438:#439     // nextToken:()Lcom/fasterxml/jackson/core/JsonToken;
  #311 = NameAndType        #440:#203     // END_ARRAY:Lcom/fasterxml/jackson/core/JsonToken;
  #312 = NameAndType        #441:#203     // VALUE_NULL:Lcom/fasterxml/jackson/core/JsonToken;
  #313 = NameAndType        #442:#197     // _skipNullValues:Z
  #314 = Class              #349          // com/fasterxml/jackson/databind/deser/NullValueProvider
  #315 = NameAndType        #443:#415     // getNullValue:(Lcom/fasterxml/jackson/databind/DeserializationContext;)Ljava/lang/Object;
  #316 = NameAndType        #180:#181     // deserializeWithType:(Lcom/fasterxml/jackson/core/JsonParser;Lcom/fasterxml/jackson/databind/DeserializationContext;Lcom/fasterxml/jackson/databind/jsontype/TypeDeserializer;)Ljava/lang/Object;
  #317 = NameAndType        #444:#445     // add:(Ljava/lang/Object;)Z
  #318 = Utf8               java/lang/Exception
  #319 = Class              #446          // com/fasterxml/jackson/databind/DeserializationFeature
  #320 = NameAndType        #447:#448     // WRAP_EXCEPTIONS:Lcom/fasterxml/jackson/databind/DeserializationFeature;
  #321 = NameAndType        #449:#450     // isEnabled:(Lcom/fasterxml/jackson/databind/DeserializationFeature;)Z
  #322 = Class              #451          // com/fasterxml/jackson/databind/util/ClassUtil
  #323 = NameAndType        #452:#453     // throwIfRTE:(Ljava/lang/Throwable;)Ljava/lang/Throwable;
  #324 = NameAndType        #454:#455     // size:()I
  #325 = NameAndType        #456:#457     // wrapWithPath:(Ljava/lang/Throwable;Ljava/lang/Object;I)Lcom/fasterxml/jackson/databind/JsonMappingException;
  #326 = Class              #347          // java/lang/Boolean
  #327 = NameAndType        #458:#130     // TRUE:Ljava/lang/Boolean;
  #328 = NameAndType        #386:#448     // ACCEPT_SINGLE_VALUE_AS_ARRAY:Lcom/fasterxml/jackson/databind/DeserializationFeature;
  #329 = NameAndType        #459:#460     // handleUnexpectedToken:(Lcom/fasterxml/jackson/databind/JavaType;Lcom/fasterxml/jackson/core/JsonParser;)Ljava/lang/Object;
  #330 = Utf8               com/fasterxml/jackson/databind/deser/std/CollectionDeserializer$CollectionReferringAccumulator
  #331 = NameAndType        #461:#371     // getRawClass:()Ljava/lang/Class;
  #332 = NameAndType        #111:#462     // "<init>":(Ljava/lang/Class;Ljava/util/Collection;)V
  #333 = NameAndType        #444:#435     // add:(Ljava/lang/Object;)V
  #334 = Utf8               com/fasterxml/jackson/databind/deser/UnresolvedForwardReference
  #335 = NameAndType        #463:#464     // handleUnresolvedReference:(Lcom/fasterxml/jackson/databind/deser/UnresolvedForwardReference;)Lcom/fasterxml/jackson/databind/deser/impl/ReadableObjectId$Referring;
  #336 = NameAndType        #465:#466     // getRoid:()Lcom/fasterxml/jackson/databind/deser/impl/ReadableObjectId;
  #337 = Class              #467          // com/fasterxml/jackson/databind/deser/impl/ReadableObjectId
  #338 = NameAndType        #468:#469     // appendReferring:(Lcom/fasterxml/jackson/databind/deser/impl/ReadableObjectId$Referring;)V
  #339 = NameAndType        #166:#175     // deserialize:(Lcom/fasterxml/jackson/core/JsonParser;Lcom/fasterxml/jackson/databind/DeserializationContext;Ljava/util/Collection;)Ljava/util/Collection;
  #340 = NameAndType        #166:#167     // deserialize:(Lcom/fasterxml/jackson/core/JsonParser;Lcom/fasterxml/jackson/databind/DeserializationContext;)Ljava/util/Collection;
  #341 = NameAndType        #146:#147     // createContextual:(Lcom/fasterxml/jackson/databind/DeserializationContext;Lcom/fasterxml/jackson/databind/BeanProperty;)Lcom/fasterxml/jackson/databind/deser/std/CollectionDeserializer;
  #342 = Utf8               com/fasterxml/jackson/databind/deser/std/ContainerDeserializerBase
  #343 = Utf8               com/fasterxml/jackson/databind/deser/ContextualDeserializer
  #344 = Utf8               com/fasterxml/jackson/databind/deser/std/CollectionDeserializer$CollectionReferring
  #345 = Utf8               com/fasterxml/jackson/databind/JsonDeserializer
  #346 = Utf8               com/fasterxml/jackson/databind/JavaType
  #347 = Utf8               java/lang/Boolean
  #348 = Utf8               com/fasterxml/jackson/databind/jsontype/TypeDeserializer
  #349 = Utf8               com/fasterxml/jackson/databind/deser/NullValueProvider
  #350 = Utf8               com/fasterxml/jackson/databind/JsonMappingException
  #351 = Utf8               java/io/IOException
  #352 = Utf8               java/lang/Class
  #353 = Utf8               com/fasterxml/jackson/core/JsonToken
  #354 = Utf8               com/fasterxml/jackson/core/JsonParser
  #355 = Utf8               com/fasterxml/jackson/databind/DeserializationContext
  #356 = Utf8               com/fasterxml/jackson/databind/deser/impl/ReadableObjectId$Referring
  #357 = Utf8               com/fasterxml/jackson/core/JacksonException
  #358 = Utf8               (Lcom/fasterxml/jackson/databind/JavaType;Lcom/fasterxml/jackson/databind/deser/NullValueProvider;Ljava/lang/Boolean;)V
  #359 = Utf8               (Lcom/fasterxml/jackson/databind/deser/std/ContainerDeserializerBase;)V
  #360 = Utf8               _containerType
  #361 = Utf8               com/fasterxml/jackson/databind/type/LogicalType
  #362 = Utf8               Collection
  #363 = Utf8               Lcom/fasterxml/jackson/databind/type/LogicalType;
  #364 = Utf8               com/fasterxml/jackson/databind/deser/ValueInstantiator
  #365 = Utf8               canCreateUsingDelegate
  #366 = Utf8               getConfig
  #367 = Utf8               ()Lcom/fasterxml/jackson/databind/DeserializationConfig;
  #368 = Utf8               getDelegateType
  #369 = Utf8               (Lcom/fasterxml/jackson/databind/DeserializationConfig;)Lcom/fasterxml/jackson/databind/JavaType;
  #370 = Utf8               getClass
  #371 = Utf8               ()Ljava/lang/Class;
  #372 = Utf8               getName
  #373 = Utf8               ()Ljava/lang/String;
  #374 = Utf8               java/lang/String
  #375 = Utf8               format
  #376 = Utf8               (Ljava/lang/String;[Ljava/lang/Object;)Ljava/lang/String;
  #377 = Utf8               reportBadDefinition
  #378 = Utf8               (Lcom/fasterxml/jackson/databind/JavaType;Ljava/lang/String;)Ljava/lang/Object;
  #379 = Utf8               findDeserializer
  #380 = Utf8               (Lcom/fasterxml/jackson/databind/DeserializationContext;Lcom/fasterxml/jackson/databind/JavaType;Lcom/fasterxml/jackson/databind/BeanProperty;)Lcom/fasterxml/jackson/databind/JsonDeserializer;
  #381 = Utf8               canCreateUsingArrayDelegate
  #382 = Utf8               getArrayDelegateType
  #383 = Class              #470          // com/fasterxml/jackson/annotation/JsonFormat
  #384 = Utf8               com/fasterxml/jackson/annotation/JsonFormat$Feature
  #385 = Utf8               Feature
  #386 = Utf8               ACCEPT_SINGLE_VALUE_AS_ARRAY
  #387 = Utf8               Lcom/fasterxml/jackson/annotation/JsonFormat$Feature;
  #388 = Utf8               findFormatFeature
  #389 = Utf8               (Lcom/fasterxml/jackson/databind/DeserializationContext;Lcom/fasterxml/jackson/databind/BeanProperty;Ljava/lang/Class;Lcom/fasterxml/jackson/annotation/JsonFormat$Feature;)Ljava/lang/Boolean;
  #390 = Utf8               findConvertingContentDeserializer
  #391 = Utf8               (Lcom/fasterxml/jackson/databind/DeserializationContext;Lcom/fasterxml/jackson/databind/BeanProperty;Lcom/fasterxml/jackson/databind/JsonDeserializer;)Lcom/fasterxml/jackson/databind/JsonDeserializer;
  #392 = Utf8               getContentType
  #393 = Utf8               ()Lcom/fasterxml/jackson/databind/JavaType;
  #394 = Utf8               findContextualValueDeserializer
  #395 = Utf8               (Lcom/fasterxml/jackson/databind/JavaType;Lcom/fasterxml/jackson/databind/BeanProperty;)Lcom/fasterxml/jackson/databind/JsonDeserializer;
  #396 = Utf8               handleSecondaryContextualization
  #397 = Utf8               (Lcom/fasterxml/jackson/databind/JsonDeserializer;Lcom/fasterxml/jackson/databind/BeanProperty;Lcom/fasterxml/jackson/databind/JavaType;)Lcom/fasterxml/jackson/databind/JsonDeserializer;
  #398 = Utf8               forProperty
  #399 = Utf8               (Lcom/fasterxml/jackson/databind/BeanProperty;)Lcom/fasterxml/jackson/databind/jsontype/TypeDeserializer;
  #400 = Utf8               findContentNullProvider
  #401 = Utf8               (Lcom/fasterxml/jackson/databind/DeserializationContext;Lcom/fasterxml/jackson/databind/BeanProperty;Lcom/fasterxml/jackson/databind/JsonDeserializer;)Lcom/fasterxml/jackson/databind/deser/NullValueProvider;
  #402 = Utf8               _unwrapSingle
  #403 = Utf8               java/util/Objects
  #404 = Utf8               equals
  #405 = Utf8               (Ljava/lang/Object;Ljava/lang/Object;)Z
  #406 = Utf8               _nullProvider
  #407 = Utf8               createUsingDelegate
  #408 = Utf8               (Lcom/fasterxml/jackson/databind/DeserializationContext;Ljava/lang/Object;)Ljava/lang/Object;
  #409 = Utf8               isExpectedStartArrayToken
  #410 = Utf8               VALUE_STRING
  #411 = Utf8               hasToken
  #412 = Utf8               (Lcom/fasterxml/jackson/core/JsonToken;)Z
  #413 = Utf8               getText
  #414 = Utf8               createUsingDefault
  #415 = Utf8               (Lcom/fasterxml/jackson/databind/DeserializationContext;)Ljava/lang/Object;
  #416 = Utf8               deserializeTypedFromArray
  #417 = Utf8               handledType
  #418 = Utf8               isEmpty
  #419 = Utf8               com/fasterxml/jackson/databind/cfg/CoercionInputShape
  #420 = Utf8               EmptyString
  #421 = Utf8               Lcom/fasterxml/jackson/databind/cfg/CoercionInputShape;
  #422 = Utf8               findCoercionAction
  #423 = Utf8               (Lcom/fasterxml/jackson/databind/type/LogicalType;Ljava/lang/Class;Lcom/fasterxml/jackson/databind/cfg/CoercionInputShape;)Lcom/fasterxml/jackson/databind/cfg/CoercionAction;
  #424 = Utf8               _checkCoercionFail
  #425 = Utf8               (Lcom/fasterxml/jackson/databind/DeserializationContext;Lcom/fasterxml/jackson/databind/cfg/CoercionAction;Ljava/lang/Class;Ljava/lang/Object;Ljava/lang/String;)Lcom/fasterxml/jackson/databind/cfg/CoercionAction;
  #426 = Utf8               _deserializeFromEmptyString
  #427 = Utf8               (Lcom/fasterxml/jackson/core/JsonParser;Lcom/fasterxml/jackson/databind/DeserializationContext;Lcom/fasterxml/jackson/databind/cfg/CoercionAction;Ljava/lang/Class;Ljava/lang/String;)Ljava/lang/Object;
  #428 = Utf8               _isBlank
  #429 = Utf8               (Ljava/lang/String;)Z
  #430 = Utf8               com/fasterxml/jackson/databind/cfg/CoercionAction
  #431 = Utf8               Fail
  #432 = Utf8               findCoercionFromBlankString
  #433 = Utf8               (Lcom/fasterxml/jackson/databind/type/LogicalType;Ljava/lang/Class;Lcom/fasterxml/jackson/databind/cfg/CoercionAction;)Lcom/fasterxml/jackson/databind/cfg/CoercionAction;
  #434 = Utf8               setCurrentValue
  #435 = Utf8               (Ljava/lang/Object;)V
  #436 = Utf8               getObjectIdReader
  #437 = Utf8               ()Lcom/fasterxml/jackson/databind/deser/impl/ObjectIdReader;
  #438 = Utf8               nextToken
  #439 = Utf8               ()Lcom/fasterxml/jackson/core/JsonToken;
  #440 = Utf8               END_ARRAY
  #441 = Utf8               VALUE_NULL
  #442 = Utf8               _skipNullValues
  #443 = Utf8               getNullValue
  #444 = Utf8               add
  #445 = Utf8               (Ljava/lang/Object;)Z
  #446 = Utf8               com/fasterxml/jackson/databind/DeserializationFeature
  #447 = Utf8               WRAP_EXCEPTIONS
  #448 = Utf8               Lcom/fasterxml/jackson/databind/DeserializationFeature;
  #449 = Utf8               isEnabled
  #450 = Utf8               (Lcom/fasterxml/jackson/databind/DeserializationFeature;)Z
  #451 = Utf8               com/fasterxml/jackson/databind/util/ClassUtil
  #452 = Utf8               throwIfRTE
  #453 = Utf8               (Ljava/lang/Throwable;)Ljava/lang/Throwable;
  #454 = Utf8               size
  #455 = Utf8               ()I
  #456 = Utf8               wrapWithPath
  #457 = Utf8               (Ljava/lang/Throwable;Ljava/lang/Object;I)Lcom/fasterxml/jackson/databind/JsonMappingException;
  #458 = Utf8               TRUE
  #459 = Utf8               handleUnexpectedToken
  #460 = Utf8               (Lcom/fasterxml/jackson/databind/JavaType;Lcom/fasterxml/jackson/core/JsonParser;)Ljava/lang/Object;
  #461 = Utf8               getRawClass
  #462 = Utf8               (Ljava/lang/Class;Ljava/util/Collection;)V
  #463 = Utf8               handleUnresolvedReference
  #464 = Utf8               (Lcom/fasterxml/jackson/databind/deser/UnresolvedForwardReference;)Lcom/fasterxml/jackson/databind/deser/impl/ReadableObjectId$Referring;
  #465 = Utf8               getRoid
  #466 = Utf8               ()Lcom/fasterxml/jackson/databind/deser/impl/ReadableObjectId;
  #467 = Utf8               com/fasterxml/jackson/databind/deser/impl/ReadableObjectId
  #468 = Utf8               appendReferring
  #469 = Utf8               (Lcom/fasterxml/jackson/databind/deser/impl/ReadableObjectId$Referring;)V
  #470 = Utf8               com/fasterxml/jackson/annotation/JsonFormat
{
  private static final long serialVersionUID;
    descriptor: J
    flags: (0x001a) ACC_PRIVATE, ACC_STATIC, ACC_FINAL
    ConstantValue: long -1l

  protected final com.fasterxml.jackson.databind.JsonDeserializer<java.lang.Object> _valueDeserializer;
    descriptor: Lcom/fasterxml/jackson/databind/JsonDeserializer;
    flags: (0x0014) ACC_PROTECTED, ACC_FINAL
    Signature: #105                         // Lcom/fasterxml/jackson/databind/JsonDeserializer<Ljava/lang/Object;>;

  protected final com.fasterxml.jackson.databind.jsontype.TypeDeserializer _valueTypeDeserializer;
    descriptor: Lcom/fasterxml/jackson/databind/jsontype/TypeDeserializer;
    flags: (0x0014) ACC_PROTECTED, ACC_FINAL

  protected final com.fasterxml.jackson.databind.deser.ValueInstantiator _valueInstantiator;
    descriptor: Lcom/fasterxml/jackson/databind/deser/ValueInstantiator;
    flags: (0x0014) ACC_PROTECTED, ACC_FINAL

  protected final com.fasterxml.jackson.databind.JsonDeserializer<java.lang.Object> _delegateDeserializer;
    descriptor: Lcom/fasterxml/jackson/databind/JsonDeserializer;
    flags: (0x0014) ACC_PROTECTED, ACC_FINAL
    Signature: #105                         // Lcom/fasterxml/jackson/databind/JsonDeserializer<Ljava/lang/Object;>;

  public com.fasterxml.jackson.databind.deser.std.CollectionDeserializer(com.fasterxml.jackson.databind.JavaType, com.fasterxml.jackson.databind.JsonDeserializer<java.lang.Object>, com.fasterxml.jackson.databind.jsontype.TypeDeserializer, com.fasterxml.jackson.databind.deser.ValueInstantiator);
    descriptor: (Lcom/fasterxml/jackson/databind/JavaType;Lcom/fasterxml/jackson/databind/JsonDeserializer;Lcom/fasterxml/jackson/databind/jsontype/TypeDeserializer;Lcom/fasterxml/jackson/databind/deser/ValueInstantiator;)V
    flags: (0x0001) ACC_PUBLIC
    Code:
      stack=8, locals=5, args_size=5
         0: aload_0
         1: aload_1
         2: aload_2
         3: aload_3
         4: aload         4
         6: aconst_null
         7: aconst_null
         8: aconst_null
         9: invokespecial #1                  // Method "<init>":(Lcom/fasterxml/jackson/databind/JavaType;Lcom/fasterxml/jackson/databind/JsonDeserializer;Lcom/fasterxml/jackson/databind/jsontype/TypeDeserializer;Lcom/fasterxml/jackson/databind/deser/ValueInstantiator;Lcom/fasterxml/jackson/databind/JsonDeserializer;Lcom/fasterxml/jackson/databind/deser/NullValueProvider;Ljava/lang/Boolean;)V
        12: return
      LineNumberTable:
        line 74: 0
        line 75: 12
      LocalVariableTable:
        Start  Length  Slot  Name   Signature
            0      13     0  this   Lcom/fasterxml/jackson/databind/deser/std/CollectionDeserializer;
            0      13     1 collectionType   Lcom/fasterxml/jackson/databind/JavaType;
            0      13     2 valueDeser   Lcom/fasterxml/jackson/databind/JsonDeserializer;
            0      13     3 valueTypeDeser   Lcom/fasterxml/jackson/databind/jsontype/TypeDeserializer;
            0      13     4 valueInstantiator   Lcom/fasterxml/jackson/databind/deser/ValueInstantiator;
      LocalVariableTypeTable:
        Start  Length  Slot  Name   Signature
            0      13     2 valueDeser   Lcom/fasterxml/jackson/databind/JsonDeserializer<Ljava/lang/Object;>;
    Signature: #124                         // (Lcom/fasterxml/jackson/databind/JavaType;Lcom/fasterxml/jackson/databind/JsonDeserializer<Ljava/lang/Object;>;Lcom/fasterxml/jackson/databind/jsontype/TypeDeserializer;Lcom/fasterxml/jackson/databind/deser/ValueInstantiator;)V

  protected com.fasterxml.jackson.databind.deser.std.CollectionDeserializer(com.fasterxml.jackson.databind.JavaType, com.fasterxml.jackson.databind.JsonDeserializer<java.lang.Object>, com.fasterxml.jackson.databind.jsontype.TypeDeserializer, com.fasterxml.jackson.databind.deser.ValueInstantiator, com.fasterxml.jackson.databind.JsonDeserializer<java.lang.Object>, com.fasterxml.jackson.databind.deser.NullValueProvider, java.lang.Boolean);
    descriptor: (Lcom/fasterxml/jackson/databind/JavaType;Lcom/fasterxml/jackson/databind/JsonDeserializer;Lcom/fasterxml/jackson/databind/jsontype/TypeDeserializer;Lcom/fasterxml/jackson/databind/deser/ValueInstantiator;Lcom/fasterxml/jackson/databind/JsonDeserializer;Lcom/fasterxml/jackson/databind/deser/NullValueProvider;Ljava/lang/Boolean;)V
    flags: (0x0004) ACC_PROTECTED
    Code:
      stack=4, locals=8, args_size=8
         0: aload_0
         1: aload_1
         2: aload         6
         4: aload         7
         6: invokespecial #2                  // Method com/fasterxml/jackson/databind/deser/std/ContainerDeserializerBase."<init>":(Lcom/fasterxml/jackson/databind/JavaType;Lcom/fasterxml/jackson/databind/deser/NullValueProvider;Ljava/lang/Boolean;)V
         9: aload_0
        10: aload_2
        11: putfield      #3                  // Field _valueDeserializer:Lcom/fasterxml/jackson/databind/JsonDeserializer;
        14: aload_0
        15: aload_3
        16: putfield      #4                  // Field _valueTypeDeserializer:Lcom/fasterxml/jackson/databind/jsontype/TypeDeserializer;
        19: aload_0
        20: aload         4
        22: putfield      #5                  // Field _valueInstantiator:Lcom/fasterxml/jackson/databind/deser/ValueInstantiator;
        25: aload_0
        26: aload         5
        28: putfield      #6                  // Field _delegateDeserializer:Lcom/fasterxml/jackson/databind/JsonDeserializer;
        31: return
      LineNumberTable:
        line 87: 0
        line 88: 9
        line 89: 14
        line 90: 19
        line 91: 25
        line 92: 31
      LocalVariableTable:
        Start  Length  Slot  Name   Signature
            0      32     0  this   Lcom/fasterxml/jackson/databind/deser/std/CollectionDeserializer;
            0      32     1 collectionType   Lcom/fasterxml/jackson/databind/JavaType;
            0      32     2 valueDeser   Lcom/fasterxml/jackson/databind/JsonDeserializer;
            0      32     3 valueTypeDeser   Lcom/fasterxml/jackson/databind/jsontype/TypeDeserializer;
            0      32     4 valueInstantiator   Lcom/fasterxml/jackson/databind/deser/ValueInstantiator;
            0      32     5 delegateDeser   Lcom/fasterxml/jackson/databind/JsonDeserializer;
            0      32     6 nuller   Lcom/fasterxml/jackson/databind/deser/NullValueProvider;
            0      32     7 unwrapSingle   Ljava/lang/Boolean;
      LocalVariableTypeTable:
        Start  Length  Slot  Name   Signature
            0      32     2 valueDeser   Lcom/fasterxml/jackson/databind/JsonDeserializer<Ljava/lang/Object;>;
            0      32     5 delegateDeser   Lcom/fasterxml/jackson/databind/JsonDeserializer<Ljava/lang/Object;>;
    Signature: #131                         // (Lcom/fasterxml/jackson/databind/JavaType;Lcom/fasterxml/jackson/databind/JsonDeserializer<Ljava/lang/Object;>;Lcom/fasterxml/jackson/databind/jsontype/TypeDeserializer;Lcom/fasterxml/jackson/databind/deser/ValueInstantiator;Lcom/fasterxml/jackson/databind/JsonDeserializer<Ljava/lang/Object;>;Lcom/fasterxml/jackson/databind/deser/NullValueProvider;Ljava/lang/Boolean;)V

  protected com.fasterxml.jackson.databind.deser.std.CollectionDeserializer(com.fasterxml.jackson.databind.deser.std.CollectionDeserializer);
    descriptor: (Lcom/fasterxml/jackson/databind/deser/std/CollectionDeserializer;)V
    flags: (0x0004) ACC_PROTECTED
    Code:
      stack=2, locals=2, args_size=2
         0: aload_0
         1: aload_1
         2: invokespecial #7                  // Method com/fasterxml/jackson/databind/deser/std/ContainerDeserializerBase."<init>":(Lcom/fasterxml/jackson/databind/deser/std/ContainerDeserializerBase;)V
         5: aload_0
         6: aload_1
         7: getfield      #3                  // Field _valueDeserializer:Lcom/fasterxml/jackson/databind/JsonDeserializer;
        10: putfield      #3                  // Field _valueDeserializer:Lcom/fasterxml/jackson/databind/JsonDeserializer;
        13: aload_0
        14: aload_1
        15: getfield      #4                  // Field _valueTypeDeserializer:Lcom/fasterxml/jackson/databind/jsontype/TypeDeserializer;
        18: putfield      #4                  // Field _valueTypeDeserializer:Lcom/fasterxml/jackson/databind/jsontype/TypeDeserializer;
        21: aload_0
        22: aload_1
        23: getfield      #5                  // Field _valueInstantiator:Lcom/fasterxml/jackson/databind/deser/ValueInstantiator;
        26: putfield      #5                  // Field _valueInstantiator:Lcom/fasterxml/jackson/databind/deser/ValueInstantiator;
        29: aload_0
        30: aload_1
        31: getfield      #6                  // Field _delegateDeserializer:Lcom/fasterxml/jackson/databind/JsonDeserializer;
        34: putfield      #6                  // Field _delegateDeserializer:Lcom/fasterxml/jackson/databind/JsonDeserializer;
        37: return
      LineNumberTable:
        line 100: 0
        line 101: 5
        line 102: 13
        line 103: 21
        line 104: 29
        line 105: 37
      LocalVariableTable:
        Start  Length  Slot  Name   Signature
            0      38     0  this   Lcom/fasterxml/jackson/databind/deser/std/CollectionDeserializer;
            0      38     1   src   Lcom/fasterxml/jackson/databind/deser/std/CollectionDeserializer;

  protected com.fasterxml.jackson.databind.deser.std.CollectionDeserializer withResolved(com.fasterxml.jackson.databind.JsonDeserializer<?>, com.fasterxml.jackson.databind.JsonDeserializer<?>, com.fasterxml.jackson.databind.jsontype.TypeDeserializer, com.fasterxml.jackson.databind.deser.NullValueProvider, java.lang.Boolean);
    descriptor: (Lcom/fasterxml/jackson/databind/JsonDeserializer;Lcom/fasterxml/jackson/databind/JsonDeserializer;Lcom/fasterxml/jackson/databind/jsontype/TypeDeserializer;Lcom/fasterxml/jackson/databind/deser/NullValueProvider;Ljava/lang/Boolean;)Lcom/fasterxml/jackson/databind/deser/std/CollectionDeserializer;
    flags: (0x0004) ACC_PROTECTED
    Code:
      stack=9, locals=6, args_size=6
         0: new           #8                  // class com/fasterxml/jackson/databind/deser/std/CollectionDeserializer
         3: dup
         4: aload_0
         5: getfield      #9                  // Field _containerType:Lcom/fasterxml/jackson/databind/JavaType;
         8: aload_2
         9: aload_3
        10: aload_0
        11: getfield      #5                  // Field _valueInstantiator:Lcom/fasterxml/jackson/databind/deser/ValueInstantiator;
        14: aload_1
        15: aload         4
        17: aload         5
        19: invokespecial #1                  // Method "<init>":(Lcom/fasterxml/jackson/databind/JavaType;Lcom/fasterxml/jackson/databind/JsonDeserializer;Lcom/fasterxml/jackson/databind/jsontype/TypeDeserializer;Lcom/fasterxml/jackson/databind/deser/ValueInstantiator;Lcom/fasterxml/jackson/databind/JsonDeserializer;Lcom/fasterxml/jackson/databind/deser/NullValueProvider;Ljava/lang/Boolean;)V
        22: areturn
      LineNumberTable:
        line 117: 0
      LocalVariableTable:
        Start  Length  Slot  Name   Signature
            0      23     0  this   Lcom/fasterxml/jackson/databind/deser/std/CollectionDeserializer;
            0      23     1    dd   Lcom/fasterxml/jackson/databind/JsonDeserializer;
            0      23     2    vd   Lcom/fasterxml/jackson/databind/JsonDeserializer;
            0      23     3   vtd   Lcom/fasterxml/jackson/databind/jsontype/TypeDeserializer;
            0      23     4 nuller   Lcom/fasterxml/jackson/databind/deser/NullValueProvider;
            0      23     5 unwrapSingle   Ljava/lang/Boolean;
      LocalVariableTypeTable:
        Start  Length  Slot  Name   Signature
            0      23     1    dd   Lcom/fasterxml/jackson/databind/JsonDeserializer<*>;
            0      23     2    vd   Lcom/fasterxml/jackson/databind/JsonDeserializer<*>;
    Signature: #140                         // (Lcom/fasterxml/jackson/databind/JsonDeserializer<*>;Lcom/fasterxml/jackson/databind/JsonDeserializer<*>;Lcom/fasterxml/jackson/databind/jsontype/TypeDeserializer;Lcom/fasterxml/jackson/databind/deser/NullValueProvider;Ljava/lang/Boolean;)Lcom/fasterxml/jackson/databind/deser/std/CollectionDeserializer;

  public boolean isCachable();
    descriptor: ()Z
    flags: (0x0001) ACC_PUBLIC
    Code:
      stack=1, locals=1, args_size=1
         0: aload_0
         1: getfield      #3                  // Field _valueDeserializer:Lcom/fasterxml/jackson/databind/JsonDeserializer;
         4: ifnonnull     25
         7: aload_0
         8: getfield      #4                  // Field _valueTypeDeserializer:Lcom/fasterxml/jackson/databind/jsontype/TypeDeserializer;
        11: ifnonnull     25
        14: aload_0
        15: getfield      #6                  // Field _delegateDeserializer:Lcom/fasterxml/jackson/databind/JsonDeserializer;
        18: ifnonnull     25
        21: iconst_1
        22: goto          26
        25: iconst_0
        26: ireturn
      LineNumberTable:
        line 127: 0
      LocalVariableTable:
        Start  Length  Slot  Name   Signature
            0      27     0  this   Lcom/fasterxml/jackson/databind/deser/std/CollectionDeserializer;
      StackMapTable: number_of_entries = 2
        frame_type = 25 /* same */
        frame_type = 64 /* same_locals_1_stack_item */
          stack = [ int ]

  public com.fasterxml.jackson.databind.type.LogicalType logicalType();
    descriptor: ()Lcom/fasterxml/jackson/databind/type/LogicalType;
    flags: (0x0001) ACC_PUBLIC
    Code:
      stack=1, locals=1, args_size=1
         0: getstatic     #10                 // Field com/fasterxml/jackson/databind/type/LogicalType.Collection:Lcom/fasterxml/jackson/databind/type/LogicalType;
         3: areturn
      LineNumberTable:
        line 135: 0
      LocalVariableTable:
        Start  Length  Slot  Name   Signature
            0       4     0  this   Lcom/fasterxml/jackson/databind/deser/std/CollectionDeserializer;

  public com.fasterxml.jackson.databind.deser.std.CollectionDeserializer createContextual(com.fasterxml.jackson.databind.DeserializationContext, com.fasterxml.jackson.databind.BeanProperty) throws com.fasterxml.jackson.databind.JsonMappingException;
    descriptor: (Lcom/fasterxml/jackson/databind/DeserializationContext;Lcom/fasterxml/jackson/databind/BeanProperty;)Lcom/fasterxml/jackson/databind/deser/std/CollectionDeserializer;
    flags: (0x0001) ACC_PUBLIC
    Code:
      stack=7, locals=9, args_size=3
         0: aconst_null
         1: astore_3
         2: aload_0
         3: getfield      #5                  // Field _valueInstantiator:Lcom/fasterxml/jackson/databind/deser/ValueInstantiator;
         6: ifnull        162
         9: aload_0
        10: getfield      #5                  // Field _valueInstantiator:Lcom/fasterxml/jackson/databind/deser/ValueInstantiator;
        13: invokevirtual #11                 // Method com/fasterxml/jackson/databind/deser/ValueInstantiator.canCreateUsingDelegate:()Z
        16: ifeq          87
        19: aload_0
        20: getfield      #5                  // Field _valueInstantiator:Lcom/fasterxml/jackson/databind/deser/ValueInstantiator;
        23: aload_1
        24: invokevirtual #12                 // Method com/fasterxml/jackson/databind/DeserializationContext.getConfig:()Lcom/fasterxml/jackson/databind/DeserializationConfig;
        27: invokevirtual #13                 // Method com/fasterxml/jackson/databind/deser/ValueInstantiator.getDelegateType:(Lcom/fasterxml/jackson/databind/DeserializationConfig;)Lcom/fasterxml/jackson/databind/JavaType;
        30: astore        4
        32: aload         4
        34: ifnonnull     75
        37: aload_1
        38: aload_0
        39: getfield      #9                  // Field _containerType:Lcom/fasterxml/jackson/databind/JavaType;
        42: ldc           #14                 // String Invalid delegate-creator definition for %s: value instantiator (%s) returned true for \'canCreateUsingDelegate()\', but null for \'getDelegateType()\'
        44: iconst_2
        45: anewarray     #15                 // class java/lang/Object
        48: dup
        49: iconst_0
        50: aload_0
        51: getfield      #9                  // Field _containerType:Lcom/fasterxml/jackson/databind/JavaType;
        54: aastore
        55: dup
        56: iconst_1
        57: aload_0
        58: getfield      #5                  // Field _valueInstantiator:Lcom/fasterxml/jackson/databind/deser/ValueInstantiator;
        61: invokevirtual #16                 // Method java/lang/Object.getClass:()Ljava/lang/Class;
        64: invokevirtual #17                 // Method java/lang/Class.getName:()Ljava/lang/String;
        67: aastore
        68: invokestatic  #18                 // Method java/lang/String.format:(Ljava/lang/String;[Ljava/lang/Object;)Ljava/lang/String;
        71: invokevirtual #19                 // Method com/fasterxml/jackson/databind/DeserializationContext.reportBadDefinition:(Lcom/fasterxml/jackson/databind/JavaType;Ljava/lang/String;)Ljava/lang/Object;
        74: pop
        75: aload_0
        76: aload_1
        77: aload         4
        79: aload_2
        80: invokevirtual #20                 // Method findDeserializer:(Lcom/fasterxml/jackson/databind/DeserializationContext;Lcom/fasterxml/jackson/databind/JavaType;Lcom/fasterxml/jackson/databind/BeanProperty;)Lcom/fasterxml/jackson/databind/JsonDeserializer;
        83: astore_3
        84: goto          162
        87: aload_0
        88: getfield      #5                  // Field _valueInstantiator:Lcom/fasterxml/jackson/databind/deser/ValueInstantiator;
        91: invokevirtual #21                 // Method com/fasterxml/jackson/databind/deser/ValueInstantiator.canCreateUsingArrayDelegate:()Z
        94: ifeq          162
        97: aload_0
        98: getfield      #5                  // Field _valueInstantiator:Lcom/fasterxml/jackson/databind/deser/ValueInstantiator;
       101: aload_1
       102: invokevirtual #12                 // Method com/fasterxml/jackson/databind/DeserializationContext.getConfig:()Lcom/fasterxml/jackson/databind/DeserializationConfig;
       105: invokevirtual #22                 // Method com/fasterxml/jackson/databind/deser/ValueInstantiator.getArrayDelegateType:(Lcom/fasterxml/jackson/databind/DeserializationConfig;)Lcom/fasterxml/jackson/databind/JavaType;
       108: astore        4
       110: aload         4
       112: ifnonnull     153
       115: aload_1
       116: aload_0
       117: getfield      #9                  // Field _containerType:Lcom/fasterxml/jackson/databind/JavaType;
       120: ldc           #23                 // String Invalid delegate-creator definition for %s: value instantiator (%s) returned true for \'canCreateUsingArrayDelegate()\', but null for \'getArrayDelegateType()\'
       122: iconst_2
       123: anewarray     #15                 // class java/lang/Object
       126: dup
       127: iconst_0
       128: aload_0
       129: getfield      #9                  // Field _containerType:Lcom/fasterxml/jackson/databind/JavaType;
       132: aastore
       133: dup
       134: iconst_1
       135: aload_0
       136: getfield      #5                  // Field _valueInstantiator:Lcom/fasterxml/jackson/databind/deser/ValueInstantiator;
       139: invokevirtual #16                 // Method java/lang/Object.getClass:()Ljava/lang/Class;
       142: invokevirtual #17                 // Method java/lang/Class.getName:()Ljava/lang/String;
       145: aastore
       146: invokestatic  #18                 // Method java/lang/String.format:(Ljava/lang/String;[Ljava/lang/Object;)Ljava/lang/String;
       149: invokevirtual #19                 // Method com/fasterxml/jackson/databind/DeserializationContext.reportBadDefinition:(Lcom/fasterxml/jackson/databind/JavaType;Ljava/lang/String;)Ljava/lang/Object;
       152: pop
       153: aload_0
       154: aload_1
       155: aload         4
       157: aload_2
       158: invokevirtual #20                 // Method findDeserializer:(Lcom/fasterxml/jackson/databind/DeserializationContext;Lcom/fasterxml/jackson/databind/JavaType;Lcom/fasterxml/jackson/databind/BeanProperty;)Lcom/fasterxml/jackson/databind/JsonDeserializer;
       161: astore_3
       162: aload_0
       163: aload_1
       164: aload_2
       165: ldc           #24                 // class java/util/Collection
       167: getstatic     #25                 // Field com/fasterxml/jackson/annotation/JsonFormat$Feature.ACCEPT_SINGLE_VALUE_AS_ARRAY:Lcom/fasterxml/jackson/annotation/JsonFormat$Feature;
       170: invokevirtual #26                 // Method findFormatFeature:(Lcom/fasterxml/jackson/databind/DeserializationContext;Lcom/fasterxml/jackson/databind/BeanProperty;Ljava/lang/Class;Lcom/fasterxml/jackson/annotation/JsonFormat$Feature;)Ljava/lang/Boolean;
       173: astore        4
       175: aload_0
       176: getfield      #3                  // Field _valueDeserializer:Lcom/fasterxml/jackson/databind/JsonDeserializer;
       179: astore        5
       181: aload_0
       182: aload_1
       183: aload_2
       184: aload         5
       186: invokevirtual #27                 // Method findConvertingContentDeserializer:(Lcom/fasterxml/jackson/databind/DeserializationContext;Lcom/fasterxml/jackson/databind/BeanProperty;Lcom/fasterxml/jackson/databind/JsonDeserializer;)Lcom/fasterxml/jackson/databind/JsonDeserializer;
       189: astore        5
       191: aload_0
       192: getfield      #9                  // Field _containerType:Lcom/fasterxml/jackson/databind/JavaType;
       195: invokevirtual #28                 // Method com/fasterxml/jackson/databind/JavaType.getContentType:()Lcom/fasterxml/jackson/databind/JavaType;
       198: astore        6
       200: aload         5
       202: ifnonnull     217
       205: aload_1
       206: aload         6
       208: aload_2
       209: invokevirtual #29                 // Method com/fasterxml/jackson/databind/DeserializationContext.findContextualValueDeserializer:(Lcom/fasterxml/jackson/databind/JavaType;Lcom/fasterxml/jackson/databind/BeanProperty;)Lcom/fasterxml/jackson/databind/JsonDeserializer;
       212: astore        5
       214: goto          228
       217: aload_1
       218: aload         5
       220: aload_2
       221: aload         6
       223: invokevirtual #30                 // Method com/fasterxml/jackson/databind/DeserializationContext.handleSecondaryContextualization:(Lcom/fasterxml/jackson/databind/JsonDeserializer;Lcom/fasterxml/jackson/databind/BeanProperty;Lcom/fasterxml/jackson/databind/JavaType;)Lcom/fasterxml/jackson/databind/JsonDeserializer;
       226: astore        5
       228: aload_0
       229: getfield      #4                  // Field _valueTypeDeserializer:Lcom/fasterxml/jackson/databind/jsontype/TypeDeserializer;
       232: astore        7
       234: aload         7
       236: ifnull        247
       239: aload         7
       241: aload_2
       242: invokevirtual #31                 // Method com/fasterxml/jackson/databind/jsontype/TypeDeserializer.forProperty:(Lcom/fasterxml/jackson/databind/BeanProperty;)Lcom/fasterxml/jackson/databind/jsontype/TypeDeserializer;
       245: astore        7
       247: aload_0
       248: aload_1
       249: aload_2
       250: aload         5
       252: invokevirtual #32                 // Method findContentNullProvider:(Lcom/fasterxml/jackson/databind/DeserializationContext;Lcom/fasterxml/jackson/databind/BeanProperty;Lcom/fasterxml/jackson/databind/JsonDeserializer;)Lcom/fasterxml/jackson/databind/deser/NullValueProvider;
       255: astore        8
       257: aload         4
       259: aload_0
       260: getfield      #33                 // Field _unwrapSingle:Ljava/lang/Boolean;
       263: invokestatic  #34                 // Method java/util/Objects.equals:(Ljava/lang/Object;Ljava/lang/Object;)Z
       266: ifeq          304
       269: aload         8
       271: aload_0
       272: getfield      #35                 // Field _nullProvider:Lcom/fasterxml/jackson/databind/deser/NullValueProvider;
       275: if_acmpne     304
       278: aload_3
       279: aload_0
       280: getfield      #6                  // Field _delegateDeserializer:Lcom/fasterxml/jackson/databind/JsonDeserializer;
       283: if_acmpne     304
       286: aload         5
       288: aload_0
       289: getfield      #3                  // Field _valueDeserializer:Lcom/fasterxml/jackson/databind/JsonDeserializer;
       292: if_acmpne     304
       295: aload         7
       297: aload_0
       298: getfield      #4                  // Field _valueTypeDeserializer:Lcom/fasterxml/jackson/databind/jsontype/TypeDeserializer;
       301: if_acmpeq     318
       304: aload_0
       305: aload_3
       306: aload         5
       308: aload         7
       310: aload         8
       312: aload         4
       314: invokevirtual #36                 // Method withResolved:(Lcom/fasterxml/jackson/databind/JsonDeserializer;Lcom/fasterxml/jackson/databind/JsonDeserializer;Lcom/fasterxml/jackson/databind/jsontype/TypeDeserializer;Lcom/fasterxml/jackson/databind/deser/NullValueProvider;Ljava/lang/Boolean;)Lcom/fasterxml/jackson/databind/deser/std/CollectionDeserializer;
       317: areturn
       318: aload_0
       319: areturn
      LineNumberTable:
        line 154: 0
        line 155: 2
        line 156: 9
        line 157: 19
        line 158: 32
        line 159: 37
        line 162: 61
        line 159: 68
        line 164: 75
        line 165: 84
        line 166: 97
        line 167: 110
        line 168: 115
        line 171: 139
        line 168: 146
        line 173: 153
        line 179: 162
        line 182: 175
        line 185: 181
        line 186: 191
        line 187: 200
        line 188: 205
        line 190: 217
        line 193: 228
        line 194: 234
        line 195: 239
        line 197: 247
        line 198: 257
        line 204: 304
        line 207: 318
      LocalVariableTable:
        Start  Length  Slot  Name   Signature
           32      52     4 delegateType   Lcom/fasterxml/jackson/databind/JavaType;
          110      52     4 delegateType   Lcom/fasterxml/jackson/databind/JavaType;
            0     320     0  this   Lcom/fasterxml/jackson/databind/deser/std/CollectionDeserializer;
            0     320     1  ctxt   Lcom/fasterxml/jackson/databind/DeserializationContext;
            0     320     2 property   Lcom/fasterxml/jackson/databind/BeanProperty;
            2     318     3 delegateDeser   Lcom/fasterxml/jackson/databind/JsonDeserializer;
          175     145     4 unwrapSingle   Ljava/lang/Boolean;
          181     139     5 valueDeser   Lcom/fasterxml/jackson/databind/JsonDeserializer;
          200     120     6    vt   Lcom/fasterxml/jackson/databind/JavaType;
          234      86     7 valueTypeDeser   Lcom/fasterxml/jackson/databind/jsontype/TypeDeserializer;
          257      63     8 nuller   Lcom/fasterxml/jackson/databind/deser/NullValueProvider;
      LocalVariableTypeTable:
        Start  Length  Slot  Name   Signature
            2     318     3 delegateDeser   Lcom/fasterxml/jackson/databind/JsonDeserializer<Ljava/lang/Object;>;
          181     139     5 valueDeser   Lcom/fasterxml/jackson/databind/JsonDeserializer<*>;
      StackMapTable: number_of_entries = 9
        frame_type = 253 /* append */
          offset_delta = 75
          locals = [ class com/fasterxml/jackson/databind/JsonDeserializer, class com/fasterxml/jackson/databind/JavaType ]
        frame_type = 250 /* chop */
          offset_delta = 11
        frame_type = 252 /* append */
          offset_delta = 65
          locals = [ class com/fasterxml/jackson/databind/JavaType ]
        frame_type = 250 /* chop */
          offset_delta = 8
        frame_type = 254 /* append */
          offset_delta = 54
          locals = [ class java/lang/Boolean, class com/fasterxml/jackson/databind/JsonDeserializer, class com/fasterxml/jackson/databind/JavaType ]
        frame_type = 10 /* same */
        frame_type = 252 /* append */
          offset_delta = 18
          locals = [ class com/fasterxml/jackson/databind/jsontype/TypeDeserializer ]
        frame_type = 252 /* append */
          offset_delta = 56
          locals = [ class com/fasterxml/jackson/databind/deser/NullValueProvider ]
        frame_type = 13 /* same */
    Exceptions:
      throws com.fasterxml.jackson.databind.JsonMappingException

  public com.fasterxml.jackson.databind.JsonDeserializer<java.lang.Object> getContentDeserializer();
    descriptor: ()Lcom/fasterxml/jackson/databind/JsonDeserializer;
    flags: (0x0001) ACC_PUBLIC
    Code:
      stack=1, locals=1, args_size=1
         0: aload_0
         1: getfield      #3                  // Field _valueDeserializer:Lcom/fasterxml/jackson/databind/JsonDeserializer;
         4: areturn
      LineNumberTable:
        line 218: 0
      LocalVariableTable:
        Start  Length  Slot  Name   Signature
            0       5     0  this   Lcom/fasterxml/jackson/databind/deser/std/CollectionDeserializer;
    Signature: #163                         // ()Lcom/fasterxml/jackson/databind/JsonDeserializer<Ljava/lang/Object;>;

  public com.fasterxml.jackson.databind.deser.ValueInstantiator getValueInstantiator();
    descriptor: ()Lcom/fasterxml/jackson/databind/deser/ValueInstantiator;
    flags: (0x0001) ACC_PUBLIC
    Code:
      stack=1, locals=1, args_size=1
         0: aload_0
         1: getfield      #5                  // Field _valueInstantiator:Lcom/fasterxml/jackson/databind/deser/ValueInstantiator;
         4: areturn
      LineNumberTable:
        line 223: 0
      LocalVariableTable:
        Start  Length  Slot  Name   Signature
            0       5     0  this   Lcom/fasterxml/jackson/databind/deser/std/CollectionDeserializer;

  public java.util.Collection<java.lang.Object> deserialize(com.fasterxml.jackson.core.JsonParser, com.fasterxml.jackson.databind.DeserializationContext) throws java.io.IOException;
    descriptor: (Lcom/fasterxml/jackson/core/JsonParser;Lcom/fasterxml/jackson/databind/DeserializationContext;)Ljava/util/Collection;
    flags: (0x0001) ACC_PUBLIC
    Code:
      stack=5, locals=3, args_size=3
         0: aload_0
         1: getfield      #6                  // Field _delegateDeserializer:Lcom/fasterxml/jackson/databind/JsonDeserializer;
         4: ifnull        28
         7: aload_0
         8: getfield      #5                  // Field _valueInstantiator:Lcom/fasterxml/jackson/databind/deser/ValueInstantiator;
        11: aload_2
        12: aload_0
        13: getfield      #6                  // Field _delegateDeserializer:Lcom/fasterxml/jackson/databind/JsonDeserializer;
        16: aload_1
        17: aload_2
        18: invokevirtual #37                 // Method com/fasterxml/jackson/databind/JsonDeserializer.deserialize:(Lcom/fasterxml/jackson/core/JsonParser;Lcom/fasterxml/jackson/databind/DeserializationContext;)Ljava/lang/Object;
        21: invokevirtual #38                 // Method com/fasterxml/jackson/databind/deser/ValueInstantiator.createUsingDelegate:(Lcom/fasterxml/jackson/databind/DeserializationContext;Ljava/lang/Object;)Ljava/lang/Object;
        24: checkcast     #24                 // class java/util/Collection
        27: areturn
        28: aload_1
        29: invokevirtual #39                 // Method com/fasterxml/jackson/core/JsonParser.isExpectedStartArrayToken:()Z
        32: ifeq          47
        35: aload_0
        36: aload_1
        37: aload_2
        38: aload_0
        39: aload_2
        40: invokevirtual #40                 // Method createDefaultInstance:(Lcom/fasterxml/jackson/databind/DeserializationContext;)Ljava/util/Collection;
        43: invokevirtual #41                 // Method _deserializeFromArray:(Lcom/fasterxml/jackson/core/JsonParser;Lcom/fasterxml/jackson/databind/DeserializationContext;Ljava/util/Collection;)Ljava/util/Collection;
        46: areturn
        47: aload_1
        48: getstatic     #42                 // Field com/fasterxml/jackson/core/JsonToken.VALUE_STRING:Lcom/fasterxml/jackson/core/JsonToken;
        51: invokevirtual #43                 // Method com/fasterxml/jackson/core/JsonParser.hasToken:(Lcom/fasterxml/jackson/core/JsonToken;)Z
        54: ifeq          68
        57: aload_0
        58: aload_1
        59: aload_2
        60: aload_1
        61: invokevirtual #44                 // Method com/fasterxml/jackson/core/JsonParser.getText:()Ljava/lang/String;
        64: invokevirtual #45                 // Method _deserializeFromString:(Lcom/fasterxml/jackson/core/JsonParser;Lcom/fasterxml/jackson/databind/DeserializationContext;Ljava/lang/String;)Ljava/util/Collection;
        67: areturn
        68: aload_0
        69: aload_1
        70: aload_2
        71: aload_0
        72: aload_2
        73: invokevirtual #40                 // Method createDefaultInstance:(Lcom/fasterxml/jackson/databind/DeserializationContext;)Ljava/util/Collection;
        76: invokevirtual #46                 // Method handleNonArray:(Lcom/fasterxml/jackson/core/JsonParser;Lcom/fasterxml/jackson/databind/DeserializationContext;Ljava/util/Collection;)Ljava/util/Collection;
        79: areturn
      LineNumberTable:
        line 237: 0
        line 238: 7
        line 239: 18
        line 238: 21
        line 243: 28
        line 244: 35
        line 249: 47
        line 250: 57
        line 252: 68
      LocalVariableTable:
        Start  Length  Slot  Name   Signature
            0      80     0  this   Lcom/fasterxml/jackson/databind/deser/std/CollectionDeserializer;
            0      80     1     p   Lcom/fasterxml/jackson/core/JsonParser;
            0      80     2  ctxt   Lcom/fasterxml/jackson/databind/DeserializationContext;
      StackMapTable: number_of_entries = 3
        frame_type = 28 /* same */
        frame_type = 18 /* same */
        frame_type = 20 /* same */
    Exceptions:
      throws java.io.IOException
    Signature: #171                         // (Lcom/fasterxml/jackson/core/JsonParser;Lcom/fasterxml/jackson/databind/DeserializationContext;)Ljava/util/Collection<Ljava/lang/Object;>;

  protected java.util.Collection<java.lang.Object> createDefaultInstance(com.fasterxml.jackson.databind.DeserializationContext) throws java.io.IOException;
    descriptor: (Lcom/fasterxml/jackson/databind/DeserializationContext;)Ljava/util/Collection;
    flags: (0x0004) ACC_PROTECTED
    Code:
      stack=2, locals=2, args_size=2
         0: aload_0
         1: getfield      #5                  // Field _valueInstantiator:Lcom/fasterxml/jackson/databind/deser/ValueInstantiator;
         4: aload_1
         5: invokevirtual #47                 // Method com/fasterxml/jackson/databind/deser/ValueInstantiator.createUsingDefault:(Lcom/fasterxml/jackson/databind/DeserializationContext;)Ljava/lang/Object;
         8: checkcast     #24                 // class java/util/Collection
        11: areturn
      LineNumberTable:
        line 262: 0
      LocalVariableTable:
        Start  Length  Slot  Name   Signature
            0      12     0  this   Lcom/fasterxml/jackson/databind/deser/std/CollectionDeserializer;
            0      12     1  ctxt   Lcom/fasterxml/jackson/databind/DeserializationContext;
    Exceptions:
      throws java.io.IOException
    Signature: #174                         // (Lcom/fasterxml/jackson/databind/DeserializationContext;)Ljava/util/Collection<Ljava/lang/Object;>;

  public java.util.Collection<java.lang.Object> deserialize(com.fasterxml.jackson.core.JsonParser, com.fasterxml.jackson.databind.DeserializationContext, java.util.Collection<java.lang.Object>) throws java.io.IOException;
    descriptor: (Lcom/fasterxml/jackson/core/JsonParser;Lcom/fasterxml/jackson/databind/DeserializationContext;Ljava/util/Collection;)Ljava/util/Collection;
    flags: (0x0001) ACC_PUBLIC
    Code:
      stack=4, locals=4, args_size=4
         0: aload_1
         1: invokevirtual #39                 // Method com/fasterxml/jackson/core/JsonParser.isExpectedStartArrayToken:()Z
         4: ifeq          15
         7: aload_0
         8: aload_1
         9: aload_2
        10: aload_3
        11: invokevirtual #41                 // Method _deserializeFromArray:(Lcom/fasterxml/jackson/core/JsonParser;Lcom/fasterxml/jackson/databind/DeserializationContext;Ljava/util/Collection;)Ljava/util/Collection;
        14: areturn
        15: aload_0
        16: aload_1
        17: aload_2
        18: aload_3
        19: invokevirtual #46                 // Method handleNonArray:(Lcom/fasterxml/jackson/core/JsonParser;Lcom/fasterxml/jackson/databind/DeserializationContext;Ljava/util/Collection;)Ljava/util/Collection;
        22: areturn
      LineNumberTable:
        line 271: 0
        line 272: 7
        line 274: 15
      LocalVariableTable:
        Start  Length  Slot  Name   Signature
            0      23     0  this   Lcom/fasterxml/jackson/databind/deser/std/CollectionDeserializer;
            0      23     1     p   Lcom/fasterxml/jackson/core/JsonParser;
            0      23     2  ctxt   Lcom/fasterxml/jackson/databind/DeserializationContext;
            0      23     3 result   Ljava/util/Collection;
      LocalVariableTypeTable:
        Start  Length  Slot  Name   Signature
            0      23     3 result   Ljava/util/Collection<Ljava/lang/Object;>;
      StackMapTable: number_of_entries = 1
        frame_type = 15 /* same */
    Exceptions:
      throws java.io.IOException
    Signature: #179                         // (Lcom/fasterxml/jackson/core/JsonParser;Lcom/fasterxml/jackson/databind/DeserializationContext;Ljava/util/Collection<Ljava/lang/Object;>;)Ljava/util/Collection<Ljava/lang/Object;>;

  public java.lang.Object deserializeWithType(com.fasterxml.jackson.core.JsonParser, com.fasterxml.jackson.databind.DeserializationContext, com.fasterxml.jackson.databind.jsontype.TypeDeserializer) throws java.io.IOException;
    descriptor: (Lcom/fasterxml/jackson/core/JsonParser;Lcom/fasterxml/jackson/databind/DeserializationContext;Lcom/fasterxml/jackson/databind/jsontype/TypeDeserializer;)Ljava/lang/Object;
    flags: (0x0001) ACC_PUBLIC
    Code:
      stack=3, locals=4, args_size=4
         0: aload_3
         1: aload_1
         2: aload_2
         3: invokevirtual #48                 // Method com/fasterxml/jackson/databind/jsontype/TypeDeserializer.deserializeTypedFromArray:(Lcom/fasterxml/jackson/core/JsonParser;Lcom/fasterxml/jackson/databind/DeserializationContext;)Ljava/lang/Object;
         6: areturn
      LineNumberTable:
        line 283: 0
      LocalVariableTable:
        Start  Length  Slot  Name   Signature
            0       7     0  this   Lcom/fasterxml/jackson/databind/deser/std/CollectionDeserializer;
            0       7     1     p   Lcom/fasterxml/jackson/core/JsonParser;
            0       7     2  ctxt   Lcom/fasterxml/jackson/databind/DeserializationContext;
            0       7     3 typeDeserializer   Lcom/fasterxml/jackson/databind/jsontype/TypeDeserializer;
    Exceptions:
      throws java.io.IOException

  protected java.util.Collection<java.lang.Object> _deserializeFromString(com.fasterxml.jackson.core.JsonParser, com.fasterxml.jackson.databind.DeserializationContext, java.lang.String) throws java.io.IOException;
    descriptor: (Lcom/fasterxml/jackson/core/JsonParser;Lcom/fasterxml/jackson/databind/DeserializationContext;Ljava/lang/String;)Ljava/util/Collection;
    flags: (0x0004) ACC_PROTECTED
    Code:
      stack=6, locals=6, args_size=4
         0: aload_0
         1: invokevirtual #49                 // Method handledType:()Ljava/lang/Class;
         4: astore        4
         6: aload_3
         7: invokevirtual #50                 // Method java/lang/String.isEmpty:()Z
        10: ifeq          66
        13: aload_2
        14: aload_0
        15: invokevirtual #51                 // Method logicalType:()Lcom/fasterxml/jackson/databind/type/LogicalType;
        18: aload         4
        20: getstatic     #52                 // Field com/fasterxml/jackson/databind/cfg/CoercionInputShape.EmptyString:Lcom/fasterxml/jackson/databind/cfg/CoercionInputShape;
        23: invokevirtual #53                 // Method com/fasterxml/jackson/databind/DeserializationContext.findCoercionAction:(Lcom/fasterxml/jackson/databind/type/LogicalType;Ljava/lang/Class;Lcom/fasterxml/jackson/databind/cfg/CoercionInputShape;)Lcom/fasterxml/jackson/databind/cfg/CoercionAction;
        26: astore        5
        28: aload_0
        29: aload_2
        30: aload         5
        32: aload         4
        34: aload_3
        35: ldc           #54                 // String empty String (\"\")
        37: invokevirtual #55                 // Method _checkCoercionFail:(Lcom/fasterxml/jackson/databind/DeserializationContext;Lcom/fasterxml/jackson/databind/cfg/CoercionAction;Ljava/lang/Class;Ljava/lang/Object;Ljava/lang/String;)Lcom/fasterxml/jackson/databind/cfg/CoercionAction;
        40: astore        5
        42: aload         5
        44: ifnull        63
        47: aload_0
        48: aload_1
        49: aload_2
        50: aload         5
        52: aload         4
        54: ldc           #54                 // String empty String (\"\")
        56: invokevirtual #56                 // Method _deserializeFromEmptyString:(Lcom/fasterxml/jackson/core/JsonParser;Lcom/fasterxml/jackson/databind/DeserializationContext;Lcom/fasterxml/jackson/databind/cfg/CoercionAction;Ljava/lang/Class;Ljava/lang/String;)Ljava/lang/Object;
        59: checkcast     #24                 // class java/util/Collection
        62: areturn
        63: goto          104
        66: aload_3
        67: invokestatic  #57                 // Method _isBlank:(Ljava/lang/String;)Z
        70: ifeq          104
        73: aload_2
        74: aload_0
        75: invokevirtual #51                 // Method logicalType:()Lcom/fasterxml/jackson/databind/type/LogicalType;
        78: aload         4
        80: getstatic     #58                 // Field com/fasterxml/jackson/databind/cfg/CoercionAction.Fail:Lcom/fasterxml/jackson/databind/cfg/CoercionAction;
        83: invokevirtual #59                 // Method com/fasterxml/jackson/databind/DeserializationContext.findCoercionFromBlankString:(Lcom/fasterxml/jackson/databind/type/LogicalType;Ljava/lang/Class;Lcom/fasterxml/jackson/databind/cfg/CoercionAction;)Lcom/fasterxml/jackson/databind/cfg/CoercionAction;
        86: astore        5
        88: aload_0
        89: aload_1
        90: aload_2
        91: aload         5
        93: aload         4
        95: ldc           #60                 // String blank String (all whitespace)
        97: invokevirtual #56                 // Method _deserializeFromEmptyString:(Lcom/fasterxml/jackson/core/JsonParser;Lcom/fasterxml/jackson/databind/DeserializationContext;Lcom/fasterxml/jackson/databind/cfg/CoercionAction;Ljava/lang/Class;Ljava/lang/String;)Ljava/lang/Object;
       100: checkcast     #24                 // class java/util/Collection
       103: areturn
       104: aload_0
       105: aload_1
       106: aload_2
       107: aload_0
       108: aload_2
       109: invokevirtual #40                 // Method createDefaultInstance:(Lcom/fasterxml/jackson/databind/DeserializationContext;)Ljava/util/Collection;
       112: invokevirtual #46                 // Method handleNonArray:(Lcom/fasterxml/jackson/core/JsonParser;Lcom/fasterxml/jackson/databind/DeserializationContext;Ljava/util/Collection;)Ljava/util/Collection;
       115: areturn
      LineNumberTable:
        line 296: 0
        line 305: 6
        line 306: 13
        line 308: 28
        line 310: 42
        line 314: 47
        line 317: 63
        line 320: 66
        line 321: 73
        line 323: 88
        line 326: 104
      LocalVariableTable:
        Start  Length  Slot  Name   Signature
           28      35     5   act   Lcom/fasterxml/jackson/databind/cfg/CoercionAction;
           88      16     5   act   Lcom/fasterxml/jackson/databind/cfg/CoercionAction;
            0     116     0  this   Lcom/fasterxml/jackson/databind/deser/std/CollectionDeserializer;
            0     116     1     p   Lcom/fasterxml/jackson/core/JsonParser;
            0     116     2  ctxt   Lcom/fasterxml/jackson/databind/DeserializationContext;
            0     116     3 value   Ljava/lang/String;
            6     110     4 rawTargetType   Ljava/lang/Class;
      LocalVariableTypeTable:
        Start  Length  Slot  Name   Signature
            6     110     4 rawTargetType   Ljava/lang/Class<*>;
      StackMapTable: number_of_entries = 3
        frame_type = 252 /* append */
          offset_delta = 63
          locals = [ class java/lang/Class ]
        frame_type = 2 /* same */
        frame_type = 37 /* same */
    Exceptions:
      throws java.io.IOException
    Signature: #193                         // (Lcom/fasterxml/jackson/core/JsonParser;Lcom/fasterxml/jackson/databind/DeserializationContext;Ljava/lang/String;)Ljava/util/Collection<Ljava/lang/Object;>;

  protected java.util.Collection<java.lang.Object> _deserializeFromArray(com.fasterxml.jackson.core.JsonParser, com.fasterxml.jackson.databind.DeserializationContext, java.util.Collection<java.lang.Object>) throws java.io.IOException;
    descriptor: (Lcom/fasterxml/jackson/core/JsonParser;Lcom/fasterxml/jackson/databind/DeserializationContext;Ljava/util/Collection;)Ljava/util/Collection;
    flags: (0x0004) ACC_PROTECTED
    Code:
      stack=4, locals=9, args_size=4
         0: aload_1
         1: aload_3
         2: invokevirtual #61                 // Method com/fasterxml/jackson/core/JsonParser.setCurrentValue:(Ljava/lang/Object;)V
         5: aload_0
         6: getfield      #3                  // Field _valueDeserializer:Lcom/fasterxml/jackson/databind/JsonDeserializer;
         9: astore        4
        11: aload         4
        13: invokevirtual #62                 // Method com/fasterxml/jackson/databind/JsonDeserializer.getObjectIdReader:()Lcom/fasterxml/jackson/databind/deser/impl/ObjectIdReader;
        16: ifnull        27
        19: aload_0
        20: aload_1
        21: aload_2
        22: aload_3
        23: invokevirtual #63                 // Method _deserializeWithObjectId:(Lcom/fasterxml/jackson/core/JsonParser;Lcom/fasterxml/jackson/databind/DeserializationContext;Ljava/util/Collection;)Ljava/util/Collection;
        26: areturn
        27: aload_0
        28: getfield      #4                  // Field _valueTypeDeserializer:Lcom/fasterxml/jackson/databind/jsontype/TypeDeserializer;
        31: astore        5
        33: aload_1
        34: invokevirtual #64                 // Method com/fasterxml/jackson/core/JsonParser.nextToken:()Lcom/fasterxml/jackson/core/JsonToken;
        37: dup
        38: astore        6
        40: getstatic     #65                 // Field com/fasterxml/jackson/core/JsonToken.END_ARRAY:Lcom/fasterxml/jackson/core/JsonToken;
        43: if_acmpeq     166
        46: aload         6
        48: getstatic     #66                 // Field com/fasterxml/jackson/core/JsonToken.VALUE_NULL:Lcom/fasterxml/jackson/core/JsonToken;
        51: if_acmpne     79
        54: aload_0
        55: getfield      #67                 // Field _skipNullValues:Z
        58: ifeq          64
        61: goto          33
        64: aload_0
        65: getfield      #35                 // Field _nullProvider:Lcom/fasterxml/jackson/databind/deser/NullValueProvider;
        68: aload_2
        69: invokeinterface #68,  2           // InterfaceMethod com/fasterxml/jackson/databind/deser/NullValueProvider.getNullValue:(Lcom/fasterxml/jackson/databind/DeserializationContext;)Ljava/lang/Object;
        74: astore        7
        76: goto          107
        79: aload         5
        81: ifnonnull     96
        84: aload         4
        86: aload_1
        87: aload_2
        88: invokevirtual #37                 // Method com/fasterxml/jackson/databind/JsonDeserializer.deserialize:(Lcom/fasterxml/jackson/core/JsonParser;Lcom/fasterxml/jackson/databind/DeserializationContext;)Ljava/lang/Object;
        91: astore        7
        93: goto          107
        96: aload         4
        98: aload_1
        99: aload_2
       100: aload         5
       102: invokevirtual #69                 // Method com/fasterxml/jackson/databind/JsonDeserializer.deserializeWithType:(Lcom/fasterxml/jackson/core/JsonParser;Lcom/fasterxml/jackson/databind/DeserializationContext;Lcom/fasterxml/jackson/databind/jsontype/TypeDeserializer;)Ljava/lang/Object;
       105: astore        7
       107: aload_3
       108: aload         7
       110: invokeinterface #70,  2           // InterfaceMethod java/util/Collection.add:(Ljava/lang/Object;)Z
       115: pop
       116: goto          33
       119: astore        7
       121: aload_2
       122: ifnull        135
       125: aload_2
       126: getstatic     #72                 // Field com/fasterxml/jackson/databind/DeserializationFeature.WRAP_EXCEPTIONS:Lcom/fasterxml/jackson/databind/DeserializationFeature;
       129: invokevirtual #73                 // Method com/fasterxml/jackson/databind/DeserializationContext.isEnabled:(Lcom/fasterxml/jackson/databind/DeserializationFeature;)Z
       132: ifeq          139
       135: iconst_1
       136: goto          140
       139: iconst_0
       140: istore        8
       142: iload         8
       144: ifne          153
       147: aload         7
       149: invokestatic  #74                 // Method com/fasterxml/jackson/databind/util/ClassUtil.throwIfRTE:(Ljava/lang/Throwable;)Ljava/lang/Throwable;
       152: pop
       153: aload         7
       155: aload_3
       156: aload_3
       157: invokeinterface #75,  1           // InterfaceMethod java/util/Collection.size:()I
       162: invokestatic  #76                 // Method com/fasterxml/jackson/databind/JsonMappingException.wrapWithPath:(Ljava/lang/Throwable;Ljava/lang/Object;I)Lcom/fasterxml/jackson/databind/JsonMappingException;
       165: athrow
       166: aload_3
       167: areturn
      Exception table:
         from    to  target type
            46    61   119   Class java/lang/Exception
            64   116   119   Class java/lang/Exception
      LineNumberTable:
        line 337: 0
        line 339: 5
        line 341: 11
        line 342: 19
        line 344: 27
        line 346: 33
        line 349: 46
        line 350: 54
        line 351: 61
        line 353: 64
        line 354: 79
        line 355: 84
        line 357: 96
        line 359: 107
        line 372: 116
        line 366: 119
        line 367: 121
        line 368: 142
        line 369: 147
        line 371: 153
        line 374: 166
      LocalVariableTable:
        Start  Length  Slot  Name   Signature
           76       3     7 value   Ljava/lang/Object;
           93       3     7 value   Ljava/lang/Object;
          107       9     7 value   Ljava/lang/Object;
          142      24     8  wrap   Z
          121      45     7     e   Ljava/lang/Exception;
            0     168     0  this   Lcom/fasterxml/jackson/databind/deser/std/CollectionDeserializer;
            0     168     1     p   Lcom/fasterxml/jackson/core/JsonParser;
            0     168     2  ctxt   Lcom/fasterxml/jackson/databind/DeserializationContext;
            0     168     3 result   Ljava/util/Collection;
           11     157     4 valueDes   Lcom/fasterxml/jackson/databind/JsonDeserializer;
           33     135     5 typeDeser   Lcom/fasterxml/jackson/databind/jsontype/TypeDeserializer;
           40     128     6     t   Lcom/fasterxml/jackson/core/JsonToken;
      LocalVariableTypeTable:
        Start  Length  Slot  Name   Signature
            0     168     3 result   Ljava/util/Collection<Ljava/lang/Object;>;
           11     157     4 valueDes   Lcom/fasterxml/jackson/databind/JsonDeserializer<Ljava/lang/Object;>;
      StackMapTable: number_of_entries = 12
        frame_type = 252 /* append */
          offset_delta = 27
          locals = [ class com/fasterxml/jackson/databind/JsonDeserializer ]
        frame_type = 252 /* append */
          offset_delta = 5
          locals = [ class com/fasterxml/jackson/databind/jsontype/TypeDeserializer ]
        frame_type = 252 /* append */
          offset_delta = 30
          locals = [ class com/fasterxml/jackson/core/JsonToken ]
        frame_type = 14 /* same */
        frame_type = 16 /* same */
        frame_type = 252 /* append */
          offset_delta = 10
          locals = [ class java/lang/Object ]
        frame_type = 255 /* full_frame */
          offset_delta = 11
          locals = [ class com/fasterxml/jackson/databind/deser/std/CollectionDeserializer, class com/fasterxml/jackson/core/JsonParser, class com/fasterxml/jackson/databind/DeserializationContext, class java/util/Collection, class com/fasterxml/jackson/databind/JsonDeserializer, class com/fasterxml/jackson/databind/jsontype/TypeDeserializer, class com/fasterxml/jackson/core/JsonToken ]
          stack = [ class java/lang/Exception ]
        frame_type = 252 /* append */
          offset_delta = 15
          locals = [ class java/lang/Exception ]
        frame_type = 3 /* same */
        frame_type = 64 /* same_locals_1_stack_item */
          stack = [ int ]
        frame_type = 252 /* append */
          offset_delta = 12
          locals = [ int ]
        frame_type = 249 /* chop */
          offset_delta = 12
    Exceptions:
      throws java.io.IOException
    Signature: #179                         // (Lcom/fasterxml/jackson/core/JsonParser;Lcom/fasterxml/jackson/databind/DeserializationContext;Ljava/util/Collection<Ljava/lang/Object;>;)Ljava/util/Collection<Ljava/lang/Object;>;

  protected final java.util.Collection<java.lang.Object> handleNonArray(com.fasterxml.jackson.core.JsonParser, com.fasterxml.jackson.databind.DeserializationContext, java.util.Collection<java.lang.Object>) throws java.io.IOException;
    descriptor: (Lcom/fasterxml/jackson/core/JsonParser;Lcom/fasterxml/jackson/databind/DeserializationContext;Ljava/util/Collection;)Ljava/util/Collection;
    flags: (0x0014) ACC_PROTECTED, ACC_FINAL
    Code:
      stack=4, locals=10, args_size=4
         0: aload_0
         1: getfield      #33                 // Field _unwrapSingle:Ljava/lang/Boolean;
         4: getstatic     #77                 // Field java/lang/Boolean.TRUE:Ljava/lang/Boolean;
         7: if_acmpeq     27
        10: aload_0
        11: getfield      #33                 // Field _unwrapSingle:Ljava/lang/Boolean;
        14: ifnonnull     31
        17: aload_2
        18: getstatic     #78                 // Field com/fasterxml/jackson/databind/DeserializationFeature.ACCEPT_SINGLE_VALUE_AS_ARRAY:Lcom/fasterxml/jackson/databind/DeserializationFeature;
        21: invokevirtual #73                 // Method com/fasterxml/jackson/databind/DeserializationContext.isEnabled:(Lcom/fasterxml/jackson/databind/DeserializationFeature;)Z
        24: ifeq          31
        27: iconst_1
        28: goto          32
        31: iconst_0
        32: istore        4
        34: iload         4
        36: ifne          52
        39: aload_2
        40: aload_0
        41: getfield      #9                  // Field _containerType:Lcom/fasterxml/jackson/databind/JavaType;
        44: aload_1
        45: invokevirtual #79                 // Method com/fasterxml/jackson/databind/DeserializationContext.handleUnexpectedToken:(Lcom/fasterxml/jackson/databind/JavaType;Lcom/fasterxml/jackson/core/JsonParser;)Ljava/lang/Object;
        48: checkcast     #24                 // class java/util/Collection
        51: areturn
        52: aload_0
        53: getfield      #3                  // Field _valueDeserializer:Lcom/fasterxml/jackson/databind/JsonDeserializer;
        56: astore        5
        58: aload_0
        59: getfield      #4                  // Field _valueTypeDeserializer:Lcom/fasterxml/jackson/databind/jsontype/TypeDeserializer;
        62: astore        6
        64: aload_1
        65: getstatic     #66                 // Field com/fasterxml/jackson/core/JsonToken.VALUE_NULL:Lcom/fasterxml/jackson/core/JsonToken;
        68: invokevirtual #43                 // Method com/fasterxml/jackson/core/JsonParser.hasToken:(Lcom/fasterxml/jackson/core/JsonToken;)Z
        71: ifeq          98
        74: aload_0
        75: getfield      #67                 // Field _skipNullValues:Z
        78: ifeq          83
        81: aload_3
        82: areturn
        83: aload_0
        84: getfield      #35                 // Field _nullProvider:Lcom/fasterxml/jackson/databind/deser/NullValueProvider;
        87: aload_2
        88: invokeinterface #68,  2           // InterfaceMethod com/fasterxml/jackson/databind/deser/NullValueProvider.getNullValue:(Lcom/fasterxml/jackson/databind/DeserializationContext;)Ljava/lang/Object;
        93: astore        7
        95: goto          126
        98: aload         6
       100: ifnonnull     115
       103: aload         5
       105: aload_1
       106: aload_2
       107: invokevirtual #37                 // Method com/fasterxml/jackson/databind/JsonDeserializer.deserialize:(Lcom/fasterxml/jackson/core/JsonParser;Lcom/fasterxml/jackson/databind/DeserializationContext;)Ljava/lang/Object;
       110: astore        7
       112: goto          126
       115: aload         5
       117: aload_1
       118: aload_2
       119: aload         6
       121: invokevirtual #69                 // Method com/fasterxml/jackson/databind/JsonDeserializer.deserializeWithType:(Lcom/fasterxml/jackson/core/JsonParser;Lcom/fasterxml/jackson/databind/DeserializationContext;Lcom/fasterxml/jackson/databind/jsontype/TypeDeserializer;)Ljava/lang/Object;
       124: astore        7
       126: goto          165
       129: astore        8
       131: aload_2
       132: getstatic     #72                 // Field com/fasterxml/jackson/databind/DeserializationFeature.WRAP_EXCEPTIONS:Lcom/fasterxml/jackson/databind/DeserializationFeature;
       135: invokevirtual #73                 // Method com/fasterxml/jackson/databind/DeserializationContext.isEnabled:(Lcom/fasterxml/jackson/databind/DeserializationFeature;)Z
       138: istore        9
       140: iload         9
       142: ifne          151
       145: aload         8
       147: invokestatic  #74                 // Method com/fasterxml/jackson/databind/util/ClassUtil.throwIfRTE:(Ljava/lang/Throwable;)Ljava/lang/Throwable;
       150: pop
       151: aload         8
       153: ldc           #15                 // class java/lang/Object
       155: aload_3
       156: invokeinterface #75,  1           // InterfaceMethod java/util/Collection.size:()I
       161: invokestatic  #76                 // Method com/fasterxml/jackson/databind/JsonMappingException.wrapWithPath:(Ljava/lang/Throwable;Ljava/lang/Object;I)Lcom/fasterxml/jackson/databind/JsonMappingException;
       164: athrow
       165: aload_3
       166: aload         7
       168: invokeinterface #70,  2           // InterfaceMethod java/util/Collection.add:(Ljava/lang/Object;)Z
       173: pop
       174: aload_3
       175: areturn
      Exception table:
         from    to  target type
            64    82   129   Class java/lang/Exception
            83   126   129   Class java/lang/Exception
      LineNumberTable:
        line 388: 0
        line 390: 21
        line 391: 34
        line 392: 39
        line 394: 52
        line 395: 58
        line 400: 64
        line 402: 74
        line 403: 81
        line 405: 83
        line 406: 98
        line 407: 103
        line 409: 115
        line 418: 126
        line 411: 129
        line 412: 131
        line 413: 140
        line 414: 145
        line 417: 151
        line 419: 165
        line 420: 174
      LocalVariableTable:
        Start  Length  Slot  Name   Signature
           95       3     7 value   Ljava/lang/Object;
          112       3     7 value   Ljava/lang/Object;
          126       3     7 value   Ljava/lang/Object;
          140      25     9  wrap   Z
          131      34     8     e   Ljava/lang/Exception;
            0     176     0  this   Lcom/fasterxml/jackson/databind/deser/std/CollectionDeserializer;
            0     176     1     p   Lcom/fasterxml/jackson/core/JsonParser;
            0     176     2  ctxt   Lcom/fasterxml/jackson/databind/DeserializationContext;
            0     176     3 result   Ljava/util/Collection;
           34     142     4 canWrap   Z
           58     118     5 valueDes   Lcom/fasterxml/jackson/databind/JsonDeserializer;
           64     112     6 typeDeser   Lcom/fasterxml/jackson/databind/jsontype/TypeDeserializer;
          165      11     7 value   Ljava/lang/Object;
      LocalVariableTypeTable:
        Start  Length  Slot  Name   Signature
            0     176     3 result   Ljava/util/Collection<Ljava/lang/Object;>;
           58     118     5 valueDes   Lcom/fasterxml/jackson/databind/JsonDeserializer<Ljava/lang/Object;>;
      StackMapTable: number_of_entries = 11
        frame_type = 27 /* same */
        frame_type = 3 /* same */
        frame_type = 64 /* same_locals_1_stack_item */
          stack = [ int ]
        frame_type = 252 /* append */
          offset_delta = 19
          locals = [ int ]
        frame_type = 253 /* append */
          offset_delta = 30
          locals = [ class com/fasterxml/jackson/databind/JsonDeserializer, class com/fasterxml/jackson/databind/jsontype/TypeDeserializer ]
        frame_type = 14 /* same */
        frame_type = 16 /* same */
        frame_type = 252 /* append */
          offset_delta = 10
          locals = [ class java/lang/Object ]
        frame_type = 255 /* full_frame */
          offset_delta = 2
          locals = [ class com/fasterxml/jackson/databind/deser/std/CollectionDeserializer, class com/fasterxml/jackson/core/JsonParser, class com/fasterxml/jackson/databind/DeserializationContext, class java/util/Collection, int, class com/fasterxml/jackson/databind/JsonDeserializer, class com/fasterxml/jackson/databind/jsontype/TypeDeserializer ]
          stack = [ class java/lang/Exception ]
        frame_type = 254 /* append */
          offset_delta = 21
          locals = [ top, class java/lang/Exception, int ]
        frame_type = 255 /* full_frame */
          offset_delta = 13
          locals = [ class com/fasterxml/jackson/databind/deser/std/CollectionDeserializer, class com/fasterxml/jackson/core/JsonParser, class com/fasterxml/jackson/databind/DeserializationContext, class java/util/Collection, int, class com/fasterxml/jackson/databind/JsonDeserializer, class com/fasterxml/jackson/databind/jsontype/TypeDeserializer, class java/lang/Object ]
          stack = []
    Exceptions:
      throws java.io.IOException
    Signature: #179                         // (Lcom/fasterxml/jackson/core/JsonParser;Lcom/fasterxml/jackson/databind/DeserializationContext;Ljava/util/Collection<Ljava/lang/Object;>;)Ljava/util/Collection<Ljava/lang/Object;>;

  protected java.util.Collection<java.lang.Object> _deserializeWithObjectId(com.fasterxml.jackson.core.JsonParser, com.fasterxml.jackson.databind.DeserializationContext, java.util.Collection<java.lang.Object>) throws java.io.IOException;
    descriptor: (Lcom/fasterxml/jackson/core/JsonParser;Lcom/fasterxml/jackson/databind/DeserializationContext;Ljava/util/Collection;)Ljava/util/Collection;
    flags: (0x0004) ACC_PROTECTED
    Code:
      stack=4, locals=10, args_size=4
         0: aload_1
         1: invokevirtual #39                 // Method com/fasterxml/jackson/core/JsonParser.isExpectedStartArrayToken:()Z
         4: ifne          15
         7: aload_0
         8: aload_1
         9: aload_2
        10: aload_3
        11: invokevirtual #46                 // Method handleNonArray:(Lcom/fasterxml/jackson/core/JsonParser;Lcom/fasterxml/jackson/databind/DeserializationContext;Ljava/util/Collection;)Ljava/util/Collection;
        14: areturn
        15: aload_1
        16: aload_3
        17: invokevirtual #61                 // Method com/fasterxml/jackson/core/JsonParser.setCurrentValue:(Ljava/lang/Object;)V
        20: aload_0
        21: getfield      #3                  // Field _valueDeserializer:Lcom/fasterxml/jackson/databind/JsonDeserializer;
        24: astore        4
        26: aload_0
        27: getfield      #4                  // Field _valueTypeDeserializer:Lcom/fasterxml/jackson/databind/jsontype/TypeDeserializer;
        30: astore        5
        32: new           #80                 // class com/fasterxml/jackson/databind/deser/std/CollectionDeserializer$CollectionReferringAccumulator
        35: dup
        36: aload_0
        37: getfield      #9                  // Field _containerType:Lcom/fasterxml/jackson/databind/JavaType;
        40: invokevirtual #28                 // Method com/fasterxml/jackson/databind/JavaType.getContentType:()Lcom/fasterxml/jackson/databind/JavaType;
        43: invokevirtual #81                 // Method com/fasterxml/jackson/databind/JavaType.getRawClass:()Ljava/lang/Class;
        46: aload_3
        47: invokespecial #82                 // Method com/fasterxml/jackson/databind/deser/std/CollectionDeserializer$CollectionReferringAccumulator."<init>":(Ljava/lang/Class;Ljava/util/Collection;)V
        50: astore        6
        52: aload_1
        53: invokevirtual #64                 // Method com/fasterxml/jackson/core/JsonParser.nextToken:()Lcom/fasterxml/jackson/core/JsonToken;
        56: dup
        57: astore        7
        59: getstatic     #65                 // Field com/fasterxml/jackson/core/JsonToken.END_ARRAY:Lcom/fasterxml/jackson/core/JsonToken;
        62: if_acmpeq     207
        65: aload         7
        67: getstatic     #66                 // Field com/fasterxml/jackson/core/JsonToken.VALUE_NULL:Lcom/fasterxml/jackson/core/JsonToken;
        70: if_acmpne     98
        73: aload_0
        74: getfield      #67                 // Field _skipNullValues:Z
        77: ifeq          83
        80: goto          52
        83: aload_0
        84: getfield      #35                 // Field _nullProvider:Lcom/fasterxml/jackson/databind/deser/NullValueProvider;
        87: aload_2
        88: invokeinterface #68,  2           // InterfaceMethod com/fasterxml/jackson/databind/deser/NullValueProvider.getNullValue:(Lcom/fasterxml/jackson/databind/DeserializationContext;)Ljava/lang/Object;
        93: astore        8
        95: goto          126
        98: aload         5
       100: ifnonnull     115
       103: aload         4
       105: aload_1
       106: aload_2
       107: invokevirtual #37                 // Method com/fasterxml/jackson/databind/JsonDeserializer.deserialize:(Lcom/fasterxml/jackson/core/JsonParser;Lcom/fasterxml/jackson/databind/DeserializationContext;)Ljava/lang/Object;
       110: astore        8
       112: goto          126
       115: aload         4
       117: aload_1
       118: aload_2
       119: aload         5
       121: invokevirtual #69                 // Method com/fasterxml/jackson/databind/JsonDeserializer.deserializeWithType:(Lcom/fasterxml/jackson/core/JsonParser;Lcom/fasterxml/jackson/databind/DeserializationContext;Lcom/fasterxml/jackson/databind/jsontype/TypeDeserializer;)Ljava/lang/Object;
       124: astore        8
       126: aload         6
       128: aload         8
       130: invokevirtual #83                 // Method com/fasterxml/jackson/databind/deser/std/CollectionDeserializer$CollectionReferringAccumulator.add:(Ljava/lang/Object;)V
       133: goto          52
       136: astore        8
       138: aload         6
       140: aload         8
       142: invokevirtual #85                 // Method com/fasterxml/jackson/databind/deser/std/CollectionDeserializer$CollectionReferringAccumulator.handleUnresolvedReference:(Lcom/fasterxml/jackson/databind/deser/UnresolvedForwardReference;)Lcom/fasterxml/jackson/databind/deser/impl/ReadableObjectId$Referring;
       145: astore        9
       147: aload         8
       149: invokevirtual #86                 // Method com/fasterxml/jackson/databind/deser/UnresolvedForwardReference.getRoid:()Lcom/fasterxml/jackson/databind/deser/impl/ReadableObjectId;
       152: aload         9
       154: invokevirtual #87                 // Method com/fasterxml/jackson/databind/deser/impl/ReadableObjectId.appendReferring:(Lcom/fasterxml/jackson/databind/deser/impl/ReadableObjectId$Referring;)V
       157: goto          52
       160: astore        8
       162: aload_2
       163: ifnull        176
       166: aload_2
       167: getstatic     #72                 // Field com/fasterxml/jackson/databind/DeserializationFeature.WRAP_EXCEPTIONS:Lcom/fasterxml/jackson/databind/DeserializationFeature;
       170: invokevirtual #73                 // Method com/fasterxml/jackson/databind/DeserializationContext.isEnabled:(Lcom/fasterxml/jackson/databind/DeserializationFeature;)Z
       173: ifeq          180
       176: iconst_1
       177: goto          181
       180: iconst_0
       181: istore        9
       183: iload         9
       185: ifne          194
       188: aload         8
       190: invokestatic  #74                 // Method com/fasterxml/jackson/databind/util/ClassUtil.throwIfRTE:(Ljava/lang/Throwable;)Ljava/lang/Throwable;
       193: pop
       194: aload         8
       196: aload_3
       197: aload_3
       198: invokeinterface #75,  1           // InterfaceMethod java/util/Collection.size:()I
       203: invokestatic  #76                 // Method com/fasterxml/jackson/databind/JsonMappingException.wrapWithPath:(Ljava/lang/Throwable;Ljava/lang/Object;I)Lcom/fasterxml/jackson/databind/JsonMappingException;
       206: athrow
       207: aload_3
       208: areturn
      Exception table:
         from    to  target type
            65    80   136   Class com/fasterxml/jackson/databind/deser/UnresolvedForwardReference
            83   133   136   Class com/fasterxml/jackson/databind/deser/UnresolvedForwardReference
            65    80   160   Class java/lang/Exception
            83   133   160   Class java/lang/Exception
      LineNumberTable:
        line 428: 0
        line 429: 7
        line 432: 15
        line 434: 20
        line 435: 26
        line 436: 32
        line 437: 40
        line 440: 52
        line 443: 65
        line 444: 73
        line 445: 80
        line 447: 83
        line 448: 98
        line 449: 103
        line 451: 115
        line 453: 126
        line 463: 133
        line 454: 136
        line 455: 138
        line 456: 147
        line 463: 157
        line 457: 160
        line 458: 162
        line 459: 183
        line 460: 188
        line 462: 194
        line 465: 207
      LocalVariableTable:
        Start  Length  Slot  Name   Signature
           95       3     8 value   Ljava/lang/Object;
          112       3     8 value   Ljava/lang/Object;
          126       7     8 value   Ljava/lang/Object;
          147      10     9   ref   Lcom/fasterxml/jackson/databind/deser/impl/ReadableObjectId$Referring;
          138      19     8 reference   Lcom/fasterxml/jackson/databind/deser/UnresolvedForwardReference;
          183      24     9  wrap   Z
          162      45     8     e   Ljava/lang/Exception;
            0     209     0  this   Lcom/fasterxml/jackson/databind/deser/std/CollectionDeserializer;
            0     209     1     p   Lcom/fasterxml/jackson/core/JsonParser;
            0     209     2  ctxt   Lcom/fasterxml/jackson/databind/DeserializationContext;
            0     209     3 result   Ljava/util/Collection;
           26     183     4 valueDes   Lcom/fasterxml/jackson/databind/JsonDeserializer;
           32     177     5 typeDeser   Lcom/fasterxml/jackson/databind/jsontype/TypeDeserializer;
           52     157     6 referringAccumulator   Lcom/fasterxml/jackson/databind/deser/std/CollectionDeserializer$CollectionReferringAccumulator;
           59     150     7     t   Lcom/fasterxml/jackson/core/JsonToken;
      LocalVariableTypeTable:
        Start  Length  Slot  Name   Signature
            0     209     3 result   Ljava/util/Collection<Ljava/lang/Object;>;
           26     183     4 valueDes   Lcom/fasterxml/jackson/databind/JsonDeserializer<Ljava/lang/Object;>;
      StackMapTable: number_of_entries = 13
        frame_type = 15 /* same */
        frame_type = 254 /* append */
          offset_delta = 36
          locals = [ class com/fasterxml/jackson/databind/JsonDeserializer, class com/fasterxml/jackson/databind/jsontype/TypeDeserializer, class com/fasterxml/jackson/databind/deser/std/CollectionDeserializer$CollectionReferringAccumulator ]
        frame_type = 252 /* append */
          offset_delta = 30
          locals = [ class com/fasterxml/jackson/core/JsonToken ]
        frame_type = 14 /* same */
        frame_type = 16 /* same */
        frame_type = 252 /* append */
          offset_delta = 10
          locals = [ class java/lang/Object ]
        frame_type = 255 /* full_frame */
          offset_delta = 9
          locals = [ class com/fasterxml/jackson/databind/deser/std/CollectionDeserializer, class com/fasterxml/jackson/core/JsonParser, class com/fasterxml/jackson/databind/DeserializationContext, class java/util/Collection, class com/fasterxml/jackson/databind/JsonDeserializer, class com/fasterxml/jackson/databind/jsontype/TypeDeserializer, class com/fasterxml/jackson/databind/deser/std/CollectionDeserializer$CollectionReferringAccumulator, class com/fasterxml/jackson/core/JsonToken ]
          stack = [ class com/fasterxml/jackson/databind/deser/UnresolvedForwardReference ]
        frame_type = 87 /* same_locals_1_stack_item */
          stack = [ class java/lang/Exception ]
        frame_type = 252 /* append */
          offset_delta = 15
          locals = [ class java/lang/Exception ]
        frame_type = 3 /* same */
        frame_type = 64 /* same_locals_1_stack_item */
          stack = [ int ]
        frame_type = 252 /* append */
          offset_delta = 12
          locals = [ int ]
        frame_type = 249 /* chop */
          offset_delta = 12
    Exceptions:
      throws java.io.IOException
    Signature: #179                         // (Lcom/fasterxml/jackson/core/JsonParser;Lcom/fasterxml/jackson/databind/DeserializationContext;Ljava/util/Collection<Ljava/lang/Object;>;)Ljava/util/Collection<Ljava/lang/Object;>;

  public java.lang.Object deserialize(com.fasterxml.jackson.core.JsonParser, com.fasterxml.jackson.databind.DeserializationContext, java.lang.Object) throws java.io.IOException, com.fasterxml.jackson.core.JacksonException;
    descriptor: (Lcom/fasterxml/jackson/core/JsonParser;Lcom/fasterxml/jackson/databind/DeserializationContext;Ljava/lang/Object;)Ljava/lang/Object;
    flags: (0x1041) ACC_PUBLIC, ACC_BRIDGE, ACC_SYNTHETIC
    Code:
      stack=4, locals=4, args_size=4
         0: aload_0
         1: aload_1
         2: aload_2
         3: aload_3
         4: checkcast     #24                 // class java/util/Collection
         7: invokevirtual #88                 // Method deserialize:(Lcom/fasterxml/jackson/core/JsonParser;Lcom/fasterxml/jackson/databind/DeserializationContext;Ljava/util/Collection;)Ljava/util/Collection;
        10: areturn
      LineNumberTable:
        line 28: 0
      LocalVariableTable:
        Start  Length  Slot  Name   Signature
            0      11     0  this   Lcom/fasterxml/jackson/databind/deser/std/CollectionDeserializer;
    Exceptions:
      throws java.io.IOException, com.fasterxml.jackson.core.JacksonException

  public java.lang.Object deserialize(com.fasterxml.jackson.core.JsonParser, com.fasterxml.jackson.databind.DeserializationContext) throws java.io.IOException, com.fasterxml.jackson.core.JacksonException;
    descriptor: (Lcom/fasterxml/jackson/core/JsonParser;Lcom/fasterxml/jackson/databind/DeserializationContext;)Ljava/lang/Object;
    flags: (0x1041) ACC_PUBLIC, ACC_BRIDGE, ACC_SYNTHETIC
    Code:
      stack=3, locals=3, args_size=3
         0: aload_0
         1: aload_1
         2: aload_2
         3: invokevirtual #89                 // Method deserialize:(Lcom/fasterxml/jackson/core/JsonParser;Lcom/fasterxml/jackson/databind/DeserializationContext;)Ljava/util/Collection;
         6: areturn
      LineNumberTable:
        line 28: 0
      LocalVariableTable:
        Start  Length  Slot  Name   Signature
            0       7     0  this   Lcom/fasterxml/jackson/databind/deser/std/CollectionDeserializer;
    Exceptions:
      throws java.io.IOException, com.fasterxml.jackson.core.JacksonException

  public com.fasterxml.jackson.databind.JsonDeserializer createContextual(com.fasterxml.jackson.databind.DeserializationContext, com.fasterxml.jackson.databind.BeanProperty) throws com.fasterxml.jackson.databind.JsonMappingException;
    descriptor: (Lcom/fasterxml/jackson/databind/DeserializationContext;Lcom/fasterxml/jackson/databind/BeanProperty;)Lcom/fasterxml/jackson/databind/JsonDeserializer;
    flags: (0x1041) ACC_PUBLIC, ACC_BRIDGE, ACC_SYNTHETIC
    Code:
      stack=3, locals=3, args_size=3
         0: aload_0
         1: aload_1
         2: aload_2
         3: invokevirtual #90                 // Method createContextual:(Lcom/fasterxml/jackson/databind/DeserializationContext;Lcom/fasterxml/jackson/databind/BeanProperty;)Lcom/fasterxml/jackson/databind/deser/std/CollectionDeserializer;
         6: areturn
      LineNumberTable:
        line 28: 0
      LocalVariableTable:
        Start  Length  Slot  Name   Signature
            0       7     0  this   Lcom/fasterxml/jackson/databind/deser/std/CollectionDeserializer;
    Exceptions:
      throws com.fasterxml.jackson.databind.JsonMappingException
}
Signature: #228                         // Lcom/fasterxml/jackson/databind/deser/std/ContainerDeserializerBase<Ljava/util/Collection<Ljava/lang/Object;>;>;Lcom/fasterxml/jackson/databind/deser/ContextualDeserializer;
SourceFile: "CollectionDeserializer.java"
RuntimeVisibleAnnotations:
  0: #232()
    com.fasterxml.jackson.databind.annotation.JacksonStdImpl
InnerClasses:
  private static final #94= #93 of #8;    // CollectionReferring=class com/fasterxml/jackson/databind/deser/std/CollectionDeserializer$CollectionReferring of class com/fasterxml/jackson/databind/deser/std/CollectionDeserializer
  public static #96= #80 of #8;           // CollectionReferringAccumulator=class com/fasterxml/jackson/databind/deser/std/CollectionDeserializer$CollectionReferringAccumulator of class com/fasterxml/jackson/databind/deser/std/CollectionDeserializer
  public static abstract #216= #215 of #337; // Referring=class com/fasterxml/jackson/databind/deser/impl/ReadableObjectId$Referring of class com/fasterxml/jackson/databind/deser/impl/ReadableObjectId
  public static final #385= #262 of #383; // Feature=class com/fasterxml/jackson/annotation/JsonFormat$Feature of class com/fasterxml/jackson/annotation/JsonFormat
