Classfile /Users/mw/Projects/slang-braindump/.jar/jar8/assemble/slang-braindump/assemble/content/com/fasterxml/jackson/databind/deser/std/DelegatingDeserializer.class
  Last modified May 29, 2022; size 5813 bytes
  SHA-256 checksum 014e3d3a036578af963914d3071c783f8bca6a80d6416b45cc012caf0f0f5bc7
  Compiled from "DelegatingDeserializer.java"
public abstract class com.fasterxml.jackson.databind.deser.std.DelegatingDeserializer extends com.fasterxml.jackson.databind.deser.std.StdDeserializer<java.lang.Object> implements com.fasterxml.jackson.databind.deser.ContextualDeserializer, com.fasterxml.jackson.databind.deser.ResolvableDeserializer
  minor version: 0
  major version: 52
  flags: (0x0421) ACC_PUBLIC, ACC_SUPER, ACC_ABSTRACT
  this_class: #21                         // com/fasterxml/jackson/databind/deser/std/DelegatingDeserializer
  super_class: #22                        // com/fasterxml/jackson/databind/deser/std/StdDeserializer
  interfaces: 2, fields: 2, methods: 18, attributes: 2
Constant pool:
    #1 = Methodref          #105.#106     // com/fasterxml/jackson/databind/JsonDeserializer.handledType:()Ljava/lang/Class;
    #2 = Methodref          #22.#107      // com/fasterxml/jackson/databind/deser/std/StdDeserializer."<init>":(Ljava/lang/Class;)V
    #3 = Fieldref           #21.#108      // com/fasterxml/jackson/databind/deser/std/DelegatingDeserializer._delegatee:Lcom/fasterxml/jackson/databind/JsonDeserializer;
    #4 = Class              #109          // com/fasterxml/jackson/databind/deser/ResolvableDeserializer
    #5 = InterfaceMethodref #4.#110       // com/fasterxml/jackson/databind/deser/ResolvableDeserializer.resolve:(Lcom/fasterxml/jackson/databind/DeserializationContext;)V
    #6 = Methodref          #111.#112     // com/fasterxml/jackson/databind/DeserializationContext.constructType:(Ljava/lang/Class;)Lcom/fasterxml/jackson/databind/JavaType;
    #7 = Methodref          #111.#113     // com/fasterxml/jackson/databind/DeserializationContext.handleSecondaryContextualization:(Lcom/fasterxml/jackson/databind/JsonDeserializer;Lcom/fasterxml/jackson/databind/BeanProperty;Lcom/fasterxml/jackson/databind/JavaType;)Lcom/fasterxml/jackson/databind/JsonDeserializer;
    #8 = Methodref          #21.#114      // com/fasterxml/jackson/databind/deser/std/DelegatingDeserializer.newDelegatingInstance:(Lcom/fasterxml/jackson/databind/JsonDeserializer;)Lcom/fasterxml/jackson/databind/JsonDeserializer;
    #9 = Methodref          #105.#115     // com/fasterxml/jackson/databind/JsonDeserializer.deserialize:(Lcom/fasterxml/jackson/core/JsonParser;Lcom/fasterxml/jackson/databind/DeserializationContext;)Ljava/lang/Object;
   #10 = Methodref          #105.#116     // com/fasterxml/jackson/databind/JsonDeserializer.deserialize:(Lcom/fasterxml/jackson/core/JsonParser;Lcom/fasterxml/jackson/databind/DeserializationContext;Ljava/lang/Object;)Ljava/lang/Object;
   #11 = Methodref          #105.#117     // com/fasterxml/jackson/databind/JsonDeserializer.deserializeWithType:(Lcom/fasterxml/jackson/core/JsonParser;Lcom/fasterxml/jackson/databind/DeserializationContext;Lcom/fasterxml/jackson/databind/jsontype/TypeDeserializer;)Ljava/lang/Object;
   #12 = Methodref          #105.#118     // com/fasterxml/jackson/databind/JsonDeserializer.isCachable:()Z
   #13 = Methodref          #105.#119     // com/fasterxml/jackson/databind/JsonDeserializer.supportsUpdate:(Lcom/fasterxml/jackson/databind/DeserializationConfig;)Ljava/lang/Boolean;
   #14 = Methodref          #105.#120     // com/fasterxml/jackson/databind/JsonDeserializer.findBackReference:(Ljava/lang/String;)Lcom/fasterxml/jackson/databind/deser/SettableBeanProperty;
   #15 = Methodref          #105.#121     // com/fasterxml/jackson/databind/JsonDeserializer.getNullAccessPattern:()Lcom/fasterxml/jackson/databind/util/AccessPattern;
   #16 = Methodref          #105.#122     // com/fasterxml/jackson/databind/JsonDeserializer.getNullValue:(Lcom/fasterxml/jackson/databind/DeserializationContext;)Ljava/lang/Object;
   #17 = Methodref          #105.#123     // com/fasterxml/jackson/databind/JsonDeserializer.getEmptyValue:(Lcom/fasterxml/jackson/databind/DeserializationContext;)Ljava/lang/Object;
   #18 = Methodref          #105.#124     // com/fasterxml/jackson/databind/JsonDeserializer.logicalType:()Lcom/fasterxml/jackson/databind/type/LogicalType;
   #19 = Methodref          #105.#125     // com/fasterxml/jackson/databind/JsonDeserializer.getKnownPropertyNames:()Ljava/util/Collection;
   #20 = Methodref          #105.#126     // com/fasterxml/jackson/databind/JsonDeserializer.getObjectIdReader:()Lcom/fasterxml/jackson/databind/deser/impl/ObjectIdReader;
   #21 = Class              #127          // com/fasterxml/jackson/databind/deser/std/DelegatingDeserializer
   #22 = Class              #128          // com/fasterxml/jackson/databind/deser/std/StdDeserializer
   #23 = Class              #129          // com/fasterxml/jackson/databind/deser/ContextualDeserializer
   #24 = Utf8               serialVersionUID
   #25 = Utf8               J
   #26 = Utf8               ConstantValue
   #27 = Long               1l
   #29 = Utf8               _delegatee
   #30 = Utf8               Lcom/fasterxml/jackson/databind/JsonDeserializer;
   #31 = Utf8               Signature
   #32 = Utf8               Lcom/fasterxml/jackson/databind/JsonDeserializer<*>;
   #33 = Utf8               <init>
   #34 = Utf8               (Lcom/fasterxml/jackson/databind/JsonDeserializer;)V
   #35 = Utf8               Code
   #36 = Utf8               LineNumberTable
   #37 = Utf8               LocalVariableTable
   #38 = Utf8               this
   #39 = Utf8               Lcom/fasterxml/jackson/databind/deser/std/DelegatingDeserializer;
   #40 = Utf8               d
   #41 = Utf8               LocalVariableTypeTable
   #42 = Utf8               (Lcom/fasterxml/jackson/databind/JsonDeserializer<*>;)V
   #43 = Utf8               newDelegatingInstance
   #44 = Utf8               (Lcom/fasterxml/jackson/databind/JsonDeserializer;)Lcom/fasterxml/jackson/databind/JsonDeserializer;
   #45 = Utf8               (Lcom/fasterxml/jackson/databind/JsonDeserializer<*>;)Lcom/fasterxml/jackson/databind/JsonDeserializer<*>;
   #46 = Utf8               resolve
   #47 = Utf8               (Lcom/fasterxml/jackson/databind/DeserializationContext;)V
   #48 = Utf8               ctxt
   #49 = Utf8               Lcom/fasterxml/jackson/databind/DeserializationContext;
   #50 = Utf8               StackMapTable
   #51 = Utf8               Exceptions
   #52 = Class              #130          // com/fasterxml/jackson/databind/JsonMappingException
   #53 = Utf8               createContextual
   #54 = Utf8               (Lcom/fasterxml/jackson/databind/DeserializationContext;Lcom/fasterxml/jackson/databind/BeanProperty;)Lcom/fasterxml/jackson/databind/JsonDeserializer;
   #55 = Utf8               property
   #56 = Utf8               Lcom/fasterxml/jackson/databind/BeanProperty;
   #57 = Utf8               vt
   #58 = Utf8               Lcom/fasterxml/jackson/databind/JavaType;
   #59 = Utf8               del
   #60 = Class              #131          // com/fasterxml/jackson/databind/JavaType
   #61 = Class              #132          // com/fasterxml/jackson/databind/JsonDeserializer
   #62 = Utf8               (Lcom/fasterxml/jackson/databind/DeserializationContext;Lcom/fasterxml/jackson/databind/BeanProperty;)Lcom/fasterxml/jackson/databind/JsonDeserializer<*>;
   #63 = Utf8               replaceDelegatee
   #64 = Utf8               delegatee
   #65 = Utf8               deserialize
   #66 = Utf8               (Lcom/fasterxml/jackson/core/JsonParser;Lcom/fasterxml/jackson/databind/DeserializationContext;)Ljava/lang/Object;
   #67 = Utf8               p
   #68 = Utf8               Lcom/fasterxml/jackson/core/JsonParser;
   #69 = Class              #133          // java/io/IOException
   #70 = Utf8               (Lcom/fasterxml/jackson/core/JsonParser;Lcom/fasterxml/jackson/databind/DeserializationContext;Ljava/lang/Object;)Ljava/lang/Object;
   #71 = Utf8               intoValue
   #72 = Utf8               Ljava/lang/Object;
   #73 = Utf8               deserializeWithType
   #74 = Utf8               (Lcom/fasterxml/jackson/core/JsonParser;Lcom/fasterxml/jackson/databind/DeserializationContext;Lcom/fasterxml/jackson/databind/jsontype/TypeDeserializer;)Ljava/lang/Object;
   #75 = Utf8               typeDeserializer
   #76 = Utf8               Lcom/fasterxml/jackson/databind/jsontype/TypeDeserializer;
   #77 = Utf8               isCachable
   #78 = Utf8               ()Z
   #79 = Utf8               supportsUpdate
   #80 = Utf8               (Lcom/fasterxml/jackson/databind/DeserializationConfig;)Ljava/lang/Boolean;
   #81 = Utf8               config
   #82 = Utf8               Lcom/fasterxml/jackson/databind/DeserializationConfig;
   #83 = Utf8               getDelegatee
   #84 = Utf8               ()Lcom/fasterxml/jackson/databind/JsonDeserializer;
   #85 = Utf8               ()Lcom/fasterxml/jackson/databind/JsonDeserializer<*>;
   #86 = Utf8               findBackReference
   #87 = Utf8               (Ljava/lang/String;)Lcom/fasterxml/jackson/databind/deser/SettableBeanProperty;
   #88 = Utf8               logicalName
   #89 = Utf8               Ljava/lang/String;
   #90 = Utf8               getNullAccessPattern
   #91 = Utf8               ()Lcom/fasterxml/jackson/databind/util/AccessPattern;
   #92 = Utf8               getNullValue
   #93 = Utf8               (Lcom/fasterxml/jackson/databind/DeserializationContext;)Ljava/lang/Object;
   #94 = Utf8               getEmptyValue
   #95 = Utf8               logicalType
   #96 = Utf8               ()Lcom/fasterxml/jackson/databind/type/LogicalType;
   #97 = Utf8               getKnownPropertyNames
   #98 = Utf8               ()Ljava/util/Collection;
   #99 = Utf8               ()Ljava/util/Collection<Ljava/lang/Object;>;
  #100 = Utf8               getObjectIdReader
  #101 = Utf8               ()Lcom/fasterxml/jackson/databind/deser/impl/ObjectIdReader;
  #102 = Utf8               Lcom/fasterxml/jackson/databind/deser/std/StdDeserializer<Ljava/lang/Object;>;Lcom/fasterxml/jackson/databind/deser/ContextualDeserializer;Lcom/fasterxml/jackson/databind/deser/ResolvableDeserializer;
  #103 = Utf8               SourceFile
  #104 = Utf8               DelegatingDeserializer.java
  #105 = Class              #132          // com/fasterxml/jackson/databind/JsonDeserializer
  #106 = NameAndType        #134:#135     // handledType:()Ljava/lang/Class;
  #107 = NameAndType        #33:#136      // "<init>":(Ljava/lang/Class;)V
  #108 = NameAndType        #29:#30       // _delegatee:Lcom/fasterxml/jackson/databind/JsonDeserializer;
  #109 = Utf8               com/fasterxml/jackson/databind/deser/ResolvableDeserializer
  #110 = NameAndType        #46:#47       // resolve:(Lcom/fasterxml/jackson/databind/DeserializationContext;)V
  #111 = Class              #137          // com/fasterxml/jackson/databind/DeserializationContext
  #112 = NameAndType        #138:#139     // constructType:(Ljava/lang/Class;)Lcom/fasterxml/jackson/databind/JavaType;
  #113 = NameAndType        #140:#141     // handleSecondaryContextualization:(Lcom/fasterxml/jackson/databind/JsonDeserializer;Lcom/fasterxml/jackson/databind/BeanProperty;Lcom/fasterxml/jackson/databind/JavaType;)Lcom/fasterxml/jackson/databind/JsonDeserializer;
  #114 = NameAndType        #43:#44       // newDelegatingInstance:(Lcom/fasterxml/jackson/databind/JsonDeserializer;)Lcom/fasterxml/jackson/databind/JsonDeserializer;
  #115 = NameAndType        #65:#66       // deserialize:(Lcom/fasterxml/jackson/core/JsonParser;Lcom/fasterxml/jackson/databind/DeserializationContext;)Ljava/lang/Object;
  #116 = NameAndType        #65:#70       // deserialize:(Lcom/fasterxml/jackson/core/JsonParser;Lcom/fasterxml/jackson/databind/DeserializationContext;Ljava/lang/Object;)Ljava/lang/Object;
  #117 = NameAndType        #73:#74       // deserializeWithType:(Lcom/fasterxml/jackson/core/JsonParser;Lcom/fasterxml/jackson/databind/DeserializationContext;Lcom/fasterxml/jackson/databind/jsontype/TypeDeserializer;)Ljava/lang/Object;
  #118 = NameAndType        #77:#78       // isCachable:()Z
  #119 = NameAndType        #79:#80       // supportsUpdate:(Lcom/fasterxml/jackson/databind/DeserializationConfig;)Ljava/lang/Boolean;
  #120 = NameAndType        #86:#87       // findBackReference:(Ljava/lang/String;)Lcom/fasterxml/jackson/databind/deser/SettableBeanProperty;
  #121 = NameAndType        #90:#91       // getNullAccessPattern:()Lcom/fasterxml/jackson/databind/util/AccessPattern;
  #122 = NameAndType        #92:#93       // getNullValue:(Lcom/fasterxml/jackson/databind/DeserializationContext;)Ljava/lang/Object;
  #123 = NameAndType        #94:#93       // getEmptyValue:(Lcom/fasterxml/jackson/databind/DeserializationContext;)Ljava/lang/Object;
  #124 = NameAndType        #95:#96       // logicalType:()Lcom/fasterxml/jackson/databind/type/LogicalType;
  #125 = NameAndType        #97:#98       // getKnownPropertyNames:()Ljava/util/Collection;
  #126 = NameAndType        #100:#101     // getObjectIdReader:()Lcom/fasterxml/jackson/databind/deser/impl/ObjectIdReader;
  #127 = Utf8               com/fasterxml/jackson/databind/deser/std/DelegatingDeserializer
  #128 = Utf8               com/fasterxml/jackson/databind/deser/std/StdDeserializer
  #129 = Utf8               com/fasterxml/jackson/databind/deser/ContextualDeserializer
  #130 = Utf8               com/fasterxml/jackson/databind/JsonMappingException
  #131 = Utf8               com/fasterxml/jackson/databind/JavaType
  #132 = Utf8               com/fasterxml/jackson/databind/JsonDeserializer
  #133 = Utf8               java/io/IOException
  #134 = Utf8               handledType
  #135 = Utf8               ()Ljava/lang/Class;
  #136 = Utf8               (Ljava/lang/Class;)V
  #137 = Utf8               com/fasterxml/jackson/databind/DeserializationContext
  #138 = Utf8               constructType
  #139 = Utf8               (Ljava/lang/Class;)Lcom/fasterxml/jackson/databind/JavaType;
  #140 = Utf8               handleSecondaryContextualization
  #141 = Utf8               (Lcom/fasterxml/jackson/databind/JsonDeserializer;Lcom/fasterxml/jackson/databind/BeanProperty;Lcom/fasterxml/jackson/databind/JavaType;)Lcom/fasterxml/jackson/databind/JsonDeserializer;
{
  private static final long serialVersionUID;
    descriptor: J
    flags: (0x001a) ACC_PRIVATE, ACC_STATIC, ACC_FINAL
    ConstantValue: long 1l

  protected final com.fasterxml.jackson.databind.JsonDeserializer<?> _delegatee;
    descriptor: Lcom/fasterxml/jackson/databind/JsonDeserializer;
    flags: (0x0014) ACC_PROTECTED, ACC_FINAL
    Signature: #32                          // Lcom/fasterxml/jackson/databind/JsonDeserializer<*>;

  public com.fasterxml.jackson.databind.deser.std.DelegatingDeserializer(com.fasterxml.jackson.databind.JsonDeserializer<?>);
    descriptor: (Lcom/fasterxml/jackson/databind/JsonDeserializer;)V
    flags: (0x0001) ACC_PUBLIC
    Code:
      stack=2, locals=2, args_size=2
         0: aload_0
         1: aload_1
         2: invokevirtual #1                  // Method com/fasterxml/jackson/databind/JsonDeserializer.handledType:()Ljava/lang/Class;
         5: invokespecial #2                  // Method com/fasterxml/jackson/databind/deser/std/StdDeserializer."<init>":(Ljava/lang/Class;)V
         8: aload_0
         9: aload_1
        10: putfield      #3                  // Field _delegatee:Lcom/fasterxml/jackson/databind/JsonDeserializer;
        13: return
      LineNumberTable:
        line 38: 0
        line 39: 8
        line 40: 13
      LocalVariableTable:
        Start  Length  Slot  Name   Signature
            0      14     0  this   Lcom/fasterxml/jackson/databind/deser/std/DelegatingDeserializer;
            0      14     1     d   Lcom/fasterxml/jackson/databind/JsonDeserializer;
      LocalVariableTypeTable:
        Start  Length  Slot  Name   Signature
            0      14     1     d   Lcom/fasterxml/jackson/databind/JsonDeserializer<*>;
    Signature: #42                          // (Lcom/fasterxml/jackson/databind/JsonDeserializer<*>;)V

  protected abstract com.fasterxml.jackson.databind.JsonDeserializer<?> newDelegatingInstance(com.fasterxml.jackson.databind.JsonDeserializer<?>);
    descriptor: (Lcom/fasterxml/jackson/databind/JsonDeserializer;)Lcom/fasterxml/jackson/databind/JsonDeserializer;
    flags: (0x0404) ACC_PROTECTED, ACC_ABSTRACT
    Signature: #45                          // (Lcom/fasterxml/jackson/databind/JsonDeserializer<*>;)Lcom/fasterxml/jackson/databind/JsonDeserializer<*>;

  public void resolve(com.fasterxml.jackson.databind.DeserializationContext) throws com.fasterxml.jackson.databind.JsonMappingException;
    descriptor: (Lcom/fasterxml/jackson/databind/DeserializationContext;)V
    flags: (0x0001) ACC_PUBLIC
    Code:
      stack=2, locals=2, args_size=2
         0: aload_0
         1: getfield      #3                  // Field _delegatee:Lcom/fasterxml/jackson/databind/JsonDeserializer;
         4: instanceof    #4                  // class com/fasterxml/jackson/databind/deser/ResolvableDeserializer
         7: ifeq          23
        10: aload_0
        11: getfield      #3                  // Field _delegatee:Lcom/fasterxml/jackson/databind/JsonDeserializer;
        14: checkcast     #4                  // class com/fasterxml/jackson/databind/deser/ResolvableDeserializer
        17: aload_1
        18: invokeinterface #5,  2            // InterfaceMethod com/fasterxml/jackson/databind/deser/ResolvableDeserializer.resolve:(Lcom/fasterxml/jackson/databind/DeserializationContext;)V
        23: return
      LineNumberTable:
        line 58: 0
        line 59: 10
        line 61: 23
      LocalVariableTable:
        Start  Length  Slot  Name   Signature
            0      24     0  this   Lcom/fasterxml/jackson/databind/deser/std/DelegatingDeserializer;
            0      24     1  ctxt   Lcom/fasterxml/jackson/databind/DeserializationContext;
      StackMapTable: number_of_entries = 1
        frame_type = 23 /* same */
    Exceptions:
      throws com.fasterxml.jackson.databind.JsonMappingException

  public com.fasterxml.jackson.databind.JsonDeserializer<?> createContextual(com.fasterxml.jackson.databind.DeserializationContext, com.fasterxml.jackson.databind.BeanProperty) throws com.fasterxml.jackson.databind.JsonMappingException;
    descriptor: (Lcom/fasterxml/jackson/databind/DeserializationContext;Lcom/fasterxml/jackson/databind/BeanProperty;)Lcom/fasterxml/jackson/databind/JsonDeserializer;
    flags: (0x0001) ACC_PUBLIC
    Code:
      stack=4, locals=5, args_size=3
         0: aload_1
         1: aload_0
         2: getfield      #3                  // Field _delegatee:Lcom/fasterxml/jackson/databind/JsonDeserializer;
         5: invokevirtual #1                  // Method com/fasterxml/jackson/databind/JsonDeserializer.handledType:()Ljava/lang/Class;
         8: invokevirtual #6                  // Method com/fasterxml/jackson/databind/DeserializationContext.constructType:(Ljava/lang/Class;)Lcom/fasterxml/jackson/databind/JavaType;
        11: astore_3
        12: aload_1
        13: aload_0
        14: getfield      #3                  // Field _delegatee:Lcom/fasterxml/jackson/databind/JsonDeserializer;
        17: aload_2
        18: aload_3
        19: invokevirtual #7                  // Method com/fasterxml/jackson/databind/DeserializationContext.handleSecondaryContextualization:(Lcom/fasterxml/jackson/databind/JsonDeserializer;Lcom/fasterxml/jackson/databind/BeanProperty;Lcom/fasterxml/jackson/databind/JavaType;)Lcom/fasterxml/jackson/databind/JsonDeserializer;
        22: astore        4
        24: aload         4
        26: aload_0
        27: getfield      #3                  // Field _delegatee:Lcom/fasterxml/jackson/databind/JsonDeserializer;
        30: if_acmpne     35
        33: aload_0
        34: areturn
        35: aload_0
        36: aload         4
        38: invokevirtual #8                  // Method newDelegatingInstance:(Lcom/fasterxml/jackson/databind/JsonDeserializer;)Lcom/fasterxml/jackson/databind/JsonDeserializer;
        41: areturn
      LineNumberTable:
        line 68: 0
        line 69: 12
        line 71: 24
        line 72: 33
        line 74: 35
      LocalVariableTable:
        Start  Length  Slot  Name   Signature
            0      42     0  this   Lcom/fasterxml/jackson/databind/deser/std/DelegatingDeserializer;
            0      42     1  ctxt   Lcom/fasterxml/jackson/databind/DeserializationContext;
            0      42     2 property   Lcom/fasterxml/jackson/databind/BeanProperty;
           12      30     3    vt   Lcom/fasterxml/jackson/databind/JavaType;
           24      18     4   del   Lcom/fasterxml/jackson/databind/JsonDeserializer;
      LocalVariableTypeTable:
        Start  Length  Slot  Name   Signature
           24      18     4   del   Lcom/fasterxml/jackson/databind/JsonDeserializer<*>;
      StackMapTable: number_of_entries = 1
        frame_type = 253 /* append */
          offset_delta = 35
          locals = [ class com/fasterxml/jackson/databind/JavaType, class com/fasterxml/jackson/databind/JsonDeserializer ]
    Exceptions:
      throws com.fasterxml.jackson.databind.JsonMappingException
    Signature: #62                          // (Lcom/fasterxml/jackson/databind/DeserializationContext;Lcom/fasterxml/jackson/databind/BeanProperty;)Lcom/fasterxml/jackson/databind/JsonDeserializer<*>;

  public com.fasterxml.jackson.databind.JsonDeserializer<?> replaceDelegatee(com.fasterxml.jackson.databind.JsonDeserializer<?>);
    descriptor: (Lcom/fasterxml/jackson/databind/JsonDeserializer;)Lcom/fasterxml/jackson/databind/JsonDeserializer;
    flags: (0x0001) ACC_PUBLIC
    Code:
      stack=2, locals=2, args_size=2
         0: aload_1
         1: aload_0
         2: getfield      #3                  // Field _delegatee:Lcom/fasterxml/jackson/databind/JsonDeserializer;
         5: if_acmpne     10
         8: aload_0
         9: areturn
        10: aload_0
        11: aload_1
        12: invokevirtual #8                  // Method newDelegatingInstance:(Lcom/fasterxml/jackson/databind/JsonDeserializer;)Lcom/fasterxml/jackson/databind/JsonDeserializer;
        15: areturn
      LineNumberTable:
        line 80: 0
        line 81: 8
        line 83: 10
      LocalVariableTable:
        Start  Length  Slot  Name   Signature
            0      16     0  this   Lcom/fasterxml/jackson/databind/deser/std/DelegatingDeserializer;
            0      16     1 delegatee   Lcom/fasterxml/jackson/databind/JsonDeserializer;
      LocalVariableTypeTable:
        Start  Length  Slot  Name   Signature
            0      16     1 delegatee   Lcom/fasterxml/jackson/databind/JsonDeserializer<*>;
      StackMapTable: number_of_entries = 1
        frame_type = 10 /* same */
    Signature: #45                          // (Lcom/fasterxml/jackson/databind/JsonDeserializer<*>;)Lcom/fasterxml/jackson/databind/JsonDeserializer<*>;

  public java.lang.Object deserialize(com.fasterxml.jackson.core.JsonParser, com.fasterxml.jackson.databind.DeserializationContext) throws java.io.IOException;
    descriptor: (Lcom/fasterxml/jackson/core/JsonParser;Lcom/fasterxml/jackson/databind/DeserializationContext;)Ljava/lang/Object;
    flags: (0x0001) ACC_PUBLIC
    Code:
      stack=3, locals=3, args_size=3
         0: aload_0
         1: getfield      #3                  // Field _delegatee:Lcom/fasterxml/jackson/databind/JsonDeserializer;
         4: aload_1
         5: aload_2
         6: invokevirtual #9                  // Method com/fasterxml/jackson/databind/JsonDeserializer.deserialize:(Lcom/fasterxml/jackson/core/JsonParser;Lcom/fasterxml/jackson/databind/DeserializationContext;)Ljava/lang/Object;
         9: areturn
      LineNumberTable:
        line 96: 0
      LocalVariableTable:
        Start  Length  Slot  Name   Signature
            0      10     0  this   Lcom/fasterxml/jackson/databind/deser/std/DelegatingDeserializer;
            0      10     1     p   Lcom/fasterxml/jackson/core/JsonParser;
            0      10     2  ctxt   Lcom/fasterxml/jackson/databind/DeserializationContext;
    Exceptions:
      throws java.io.IOException

  public java.lang.Object deserialize(com.fasterxml.jackson.core.JsonParser, com.fasterxml.jackson.databind.DeserializationContext, java.lang.Object) throws java.io.IOException;
    descriptor: (Lcom/fasterxml/jackson/core/JsonParser;Lcom/fasterxml/jackson/databind/DeserializationContext;Ljava/lang/Object;)Ljava/lang/Object;
    flags: (0x0001) ACC_PUBLIC
    Code:
      stack=4, locals=4, args_size=4
         0: aload_0
         1: getfield      #3                  // Field _delegatee:Lcom/fasterxml/jackson/databind/JsonDeserializer;
         4: aload_1
         5: aload_2
         6: aload_3
         7: invokevirtual #10                 // Method com/fasterxml/jackson/databind/JsonDeserializer.deserialize:(Lcom/fasterxml/jackson/core/JsonParser;Lcom/fasterxml/jackson/databind/DeserializationContext;Ljava/lang/Object;)Ljava/lang/Object;
        10: areturn
      LineNumberTable:
        line 105: 0
      LocalVariableTable:
        Start  Length  Slot  Name   Signature
            0      11     0  this   Lcom/fasterxml/jackson/databind/deser/std/DelegatingDeserializer;
            0      11     1     p   Lcom/fasterxml/jackson/core/JsonParser;
            0      11     2  ctxt   Lcom/fasterxml/jackson/databind/DeserializationContext;
            0      11     3 intoValue   Ljava/lang/Object;
    Exceptions:
      throws java.io.IOException

  public java.lang.Object deserializeWithType(com.fasterxml.jackson.core.JsonParser, com.fasterxml.jackson.databind.DeserializationContext, com.fasterxml.jackson.databind.jsontype.TypeDeserializer) throws java.io.IOException;
    descriptor: (Lcom/fasterxml/jackson/core/JsonParser;Lcom/fasterxml/jackson/databind/DeserializationContext;Lcom/fasterxml/jackson/databind/jsontype/TypeDeserializer;)Ljava/lang/Object;
    flags: (0x0001) ACC_PUBLIC
    Code:
      stack=4, locals=4, args_size=4
         0: aload_0
         1: getfield      #3                  // Field _delegatee:Lcom/fasterxml/jackson/databind/JsonDeserializer;
         4: aload_1
         5: aload_2
         6: aload_3
         7: invokevirtual #11                 // Method com/fasterxml/jackson/databind/JsonDeserializer.deserializeWithType:(Lcom/fasterxml/jackson/core/JsonParser;Lcom/fasterxml/jackson/databind/DeserializationContext;Lcom/fasterxml/jackson/databind/jsontype/TypeDeserializer;)Ljava/lang/Object;
        10: areturn
      LineNumberTable:
        line 113: 0
      LocalVariableTable:
        Start  Length  Slot  Name   Signature
            0      11     0  this   Lcom/fasterxml/jackson/databind/deser/std/DelegatingDeserializer;
            0      11     1     p   Lcom/fasterxml/jackson/core/JsonParser;
            0      11     2  ctxt   Lcom/fasterxml/jackson/databind/DeserializationContext;
            0      11     3 typeDeserializer   Lcom/fasterxml/jackson/databind/jsontype/TypeDeserializer;
    Exceptions:
      throws java.io.IOException

  public boolean isCachable();
    descriptor: ()Z
    flags: (0x0001) ACC_PUBLIC
    Code:
      stack=1, locals=1, args_size=1
         0: aload_0
         1: getfield      #3                  // Field _delegatee:Lcom/fasterxml/jackson/databind/JsonDeserializer;
         4: invokevirtual #12                 // Method com/fasterxml/jackson/databind/JsonDeserializer.isCachable:()Z
         7: ireturn
      LineNumberTable:
        line 123: 0
      LocalVariableTable:
        Start  Length  Slot  Name   Signature
            0       8     0  this   Lcom/fasterxml/jackson/databind/deser/std/DelegatingDeserializer;

  public java.lang.Boolean supportsUpdate(com.fasterxml.jackson.databind.DeserializationConfig);
    descriptor: (Lcom/fasterxml/jackson/databind/DeserializationConfig;)Ljava/lang/Boolean;
    flags: (0x0001) ACC_PUBLIC
    Code:
      stack=2, locals=2, args_size=2
         0: aload_0
         1: getfield      #3                  // Field _delegatee:Lcom/fasterxml/jackson/databind/JsonDeserializer;
         4: aload_1
         5: invokevirtual #13                 // Method com/fasterxml/jackson/databind/JsonDeserializer.supportsUpdate:(Lcom/fasterxml/jackson/databind/DeserializationConfig;)Ljava/lang/Boolean;
         8: areturn
      LineNumberTable:
        line 127: 0
      LocalVariableTable:
        Start  Length  Slot  Name   Signature
            0       9     0  this   Lcom/fasterxml/jackson/databind/deser/std/DelegatingDeserializer;
            0       9     1 config   Lcom/fasterxml/jackson/databind/DeserializationConfig;

  public com.fasterxml.jackson.databind.JsonDeserializer<?> getDelegatee();
    descriptor: ()Lcom/fasterxml/jackson/databind/JsonDeserializer;
    flags: (0x0001) ACC_PUBLIC
    Code:
      stack=1, locals=1, args_size=1
         0: aload_0
         1: getfield      #3                  // Field _delegatee:Lcom/fasterxml/jackson/databind/JsonDeserializer;
         4: areturn
      LineNumberTable:
        line 132: 0
      LocalVariableTable:
        Start  Length  Slot  Name   Signature
            0       5     0  this   Lcom/fasterxml/jackson/databind/deser/std/DelegatingDeserializer;
    Signature: #85                          // ()Lcom/fasterxml/jackson/databind/JsonDeserializer<*>;

  public com.fasterxml.jackson.databind.deser.SettableBeanProperty findBackReference(java.lang.String);
    descriptor: (Ljava/lang/String;)Lcom/fasterxml/jackson/databind/deser/SettableBeanProperty;
    flags: (0x0001) ACC_PUBLIC
    Code:
      stack=2, locals=2, args_size=2
         0: aload_0
         1: getfield      #3                  // Field _delegatee:Lcom/fasterxml/jackson/databind/JsonDeserializer;
         4: aload_1
         5: invokevirtual #14                 // Method com/fasterxml/jackson/databind/JsonDeserializer.findBackReference:(Ljava/lang/String;)Lcom/fasterxml/jackson/databind/deser/SettableBeanProperty;
         8: areturn
      LineNumberTable:
        line 138: 0
      LocalVariableTable:
        Start  Length  Slot  Name   Signature
            0       9     0  this   Lcom/fasterxml/jackson/databind/deser/std/DelegatingDeserializer;
            0       9     1 logicalName   Ljava/lang/String;

  public com.fasterxml.jackson.databind.util.AccessPattern getNullAccessPattern();
    descriptor: ()Lcom/fasterxml/jackson/databind/util/AccessPattern;
    flags: (0x0001) ACC_PUBLIC
    Code:
      stack=1, locals=1, args_size=1
         0: aload_0
         1: getfield      #3                  // Field _delegatee:Lcom/fasterxml/jackson/databind/JsonDeserializer;
         4: invokevirtual #15                 // Method com/fasterxml/jackson/databind/JsonDeserializer.getNullAccessPattern:()Lcom/fasterxml/jackson/databind/util/AccessPattern;
         7: areturn
      LineNumberTable:
        line 143: 0
      LocalVariableTable:
        Start  Length  Slot  Name   Signature
            0       8     0  this   Lcom/fasterxml/jackson/databind/deser/std/DelegatingDeserializer;

  public java.lang.Object getNullValue(com.fasterxml.jackson.databind.DeserializationContext) throws com.fasterxml.jackson.databind.JsonMappingException;
    descriptor: (Lcom/fasterxml/jackson/databind/DeserializationContext;)Ljava/lang/Object;
    flags: (0x0001) ACC_PUBLIC
    Code:
      stack=2, locals=2, args_size=2
         0: aload_0
         1: getfield      #3                  // Field _delegatee:Lcom/fasterxml/jackson/databind/JsonDeserializer;
         4: aload_1
         5: invokevirtual #16                 // Method com/fasterxml/jackson/databind/JsonDeserializer.getNullValue:(Lcom/fasterxml/jackson/databind/DeserializationContext;)Ljava/lang/Object;
         8: areturn
      LineNumberTable:
        line 148: 0
      LocalVariableTable:
        Start  Length  Slot  Name   Signature
            0       9     0  this   Lcom/fasterxml/jackson/databind/deser/std/DelegatingDeserializer;
            0       9     1  ctxt   Lcom/fasterxml/jackson/databind/DeserializationContext;
    Exceptions:
      throws com.fasterxml.jackson.databind.JsonMappingException

  public java.lang.Object getEmptyValue(com.fasterxml.jackson.databind.DeserializationContext) throws com.fasterxml.jackson.databind.JsonMappingException;
    descriptor: (Lcom/fasterxml/jackson/databind/DeserializationContext;)Ljava/lang/Object;
    flags: (0x0001) ACC_PUBLIC
    Code:
      stack=2, locals=2, args_size=2
         0: aload_0
         1: getfield      #3                  // Field _delegatee:Lcom/fasterxml/jackson/databind/JsonDeserializer;
         4: aload_1
         5: invokevirtual #17                 // Method com/fasterxml/jackson/databind/JsonDeserializer.getEmptyValue:(Lcom/fasterxml/jackson/databind/DeserializationContext;)Ljava/lang/Object;
         8: areturn
      LineNumberTable:
        line 153: 0
      LocalVariableTable:
        Start  Length  Slot  Name   Signature
            0       9     0  this   Lcom/fasterxml/jackson/databind/deser/std/DelegatingDeserializer;
            0       9     1  ctxt   Lcom/fasterxml/jackson/databind/DeserializationContext;
    Exceptions:
      throws com.fasterxml.jackson.databind.JsonMappingException

  public com.fasterxml.jackson.databind.type.LogicalType logicalType();
    descriptor: ()Lcom/fasterxml/jackson/databind/type/LogicalType;
    flags: (0x0001) ACC_PUBLIC
    Code:
      stack=1, locals=1, args_size=1
         0: aload_0
         1: getfield      #3                  // Field _delegatee:Lcom/fasterxml/jackson/databind/JsonDeserializer;
         4: invokevirtual #18                 // Method com/fasterxml/jackson/databind/JsonDeserializer.logicalType:()Lcom/fasterxml/jackson/databind/type/LogicalType;
         7: areturn
      LineNumberTable:
        line 158: 0
      LocalVariableTable:
        Start  Length  Slot  Name   Signature
            0       8     0  this   Lcom/fasterxml/jackson/databind/deser/std/DelegatingDeserializer;

  public java.util.Collection<java.lang.Object> getKnownPropertyNames();
    descriptor: ()Ljava/util/Collection;
    flags: (0x0001) ACC_PUBLIC
    Code:
      stack=1, locals=1, args_size=1
         0: aload_0
         1: getfield      #3                  // Field _delegatee:Lcom/fasterxml/jackson/databind/JsonDeserializer;
         4: invokevirtual #19                 // Method com/fasterxml/jackson/databind/JsonDeserializer.getKnownPropertyNames:()Ljava/util/Collection;
         7: areturn
      LineNumberTable:
        line 162: 0
      LocalVariableTable:
        Start  Length  Slot  Name   Signature
            0       8     0  this   Lcom/fasterxml/jackson/databind/deser/std/DelegatingDeserializer;
    Signature: #99                          // ()Ljava/util/Collection<Ljava/lang/Object;>;

  public com.fasterxml.jackson.databind.deser.impl.ObjectIdReader getObjectIdReader();
    descriptor: ()Lcom/fasterxml/jackson/databind/deser/impl/ObjectIdReader;
    flags: (0x0001) ACC_PUBLIC
    Code:
      stack=1, locals=1, args_size=1
         0: aload_0
         1: getfield      #3                  // Field _delegatee:Lcom/fasterxml/jackson/databind/JsonDeserializer;
         4: invokevirtual #20                 // Method com/fasterxml/jackson/databind/JsonDeserializer.getObjectIdReader:()Lcom/fasterxml/jackson/databind/deser/impl/ObjectIdReader;
         7: areturn
      LineNumberTable:
        line 165: 0
      LocalVariableTable:
        Start  Length  Slot  Name   Signature
            0       8     0  this   Lcom/fasterxml/jackson/databind/deser/std/DelegatingDeserializer;
}
Signature: #102                         // Lcom/fasterxml/jackson/databind/deser/std/StdDeserializer<Ljava/lang/Object;>;Lcom/fasterxml/jackson/databind/deser/ContextualDeserializer;Lcom/fasterxml/jackson/databind/deser/ResolvableDeserializer;
SourceFile: "DelegatingDeserializer.java"
