Classfile /Users/mw/Projects/slang-braindump/.jar/jar8/assemble/slang-braindump/assemble/content/org/apache/commons/lang3/mutable/MutableByte.class
  Last modified May 29, 2022; size 4199 bytes
  SHA-256 checksum 4a66ec49bdb77cfb3ee1b37022a5b72156759767bf7b3e5a6b5d946a1273518e
  Compiled from "MutableByte.java"
public class org.apache.commons.lang3.mutable.MutableByte extends java.lang.Number implements java.lang.Comparable<org.apache.commons.lang3.mutable.MutableByte>, org.apache.commons.lang3.mutable.Mutable<java.lang.Number>
  minor version: 0
  major version: 52
  flags: (0x0021) ACC_PUBLIC, ACC_SUPER
  this_class: #7                          // org/apache/commons/lang3/mutable/MutableByte
  super_class: #11                        // java/lang/Number
  interfaces: 2, fields: 2, methods: 34, attributes: 2
Constant pool:
    #1 = Methodref          #11.#81       // java/lang/Number."<init>":()V
    #2 = Fieldref           #7.#82        // org/apache/commons/lang3/mutable/MutableByte.value:B
    #3 = Methodref          #11.#83       // java/lang/Number.byteValue:()B
    #4 = Methodref          #84.#85       // java/lang/Byte.parseByte:(Ljava/lang/String;)B
    #5 = Methodref          #84.#86       // java/lang/Byte.valueOf:(B)Ljava/lang/Byte;
    #6 = Methodref          #7.#83        // org/apache/commons/lang3/mutable/MutableByte.byteValue:()B
    #7 = Class              #87           // org/apache/commons/lang3/mutable/MutableByte
    #8 = Methodref          #88.#89       // org/apache/commons/lang3/math/NumberUtils.compare:(BB)I
    #9 = Methodref          #90.#91       // java/lang/String.valueOf:(I)Ljava/lang/String;
   #10 = Methodref          #7.#92        // org/apache/commons/lang3/mutable/MutableByte.compareTo:(Lorg/apache/commons/lang3/mutable/MutableByte;)I
   #11 = Class              #93           // java/lang/Number
   #12 = Methodref          #7.#94        // org/apache/commons/lang3/mutable/MutableByte.setValue:(Ljava/lang/Number;)V
   #13 = Methodref          #7.#95        // org/apache/commons/lang3/mutable/MutableByte.getValue:()Ljava/lang/Byte;
   #14 = Class              #96           // java/lang/Comparable
   #15 = Class              #97           // org/apache/commons/lang3/mutable/Mutable
   #16 = Utf8               serialVersionUID
   #17 = Utf8               J
   #18 = Utf8               ConstantValue
   #19 = Long               -1585823265l
   #21 = Utf8               value
   #22 = Utf8               B
   #23 = Utf8               <init>
   #24 = Utf8               ()V
   #25 = Utf8               Code
   #26 = Utf8               LineNumberTable
   #27 = Utf8               LocalVariableTable
   #28 = Utf8               this
   #29 = Utf8               Lorg/apache/commons/lang3/mutable/MutableByte;
   #30 = Utf8               (B)V
   #31 = Utf8               (Ljava/lang/Number;)V
   #32 = Utf8               Ljava/lang/Number;
   #33 = Utf8               (Ljava/lang/String;)V
   #34 = Utf8               Ljava/lang/String;
   #35 = Utf8               getValue
   #36 = Utf8               ()Ljava/lang/Byte;
   #37 = Utf8               setValue
   #38 = Utf8               increment
   #39 = Utf8               getAndIncrement
   #40 = Utf8               ()B
   #41 = Utf8               last
   #42 = Utf8               incrementAndGet
   #43 = Utf8               decrement
   #44 = Utf8               getAndDecrement
   #45 = Utf8               decrementAndGet
   #46 = Utf8               add
   #47 = Utf8               operand
   #48 = Utf8               subtract
   #49 = Utf8               addAndGet
   #50 = Utf8               (B)B
   #51 = Utf8               (Ljava/lang/Number;)B
   #52 = Utf8               getAndAdd
   #53 = Utf8               byteValue
   #54 = Utf8               intValue
   #55 = Utf8               ()I
   #56 = Utf8               longValue
   #57 = Utf8               ()J
   #58 = Utf8               floatValue
   #59 = Utf8               ()F
   #60 = Utf8               doubleValue
   #61 = Utf8               ()D
   #62 = Utf8               toByte
   #63 = Utf8               equals
   #64 = Utf8               (Ljava/lang/Object;)Z
   #65 = Utf8               obj
   #66 = Utf8               Ljava/lang/Object;
   #67 = Utf8               StackMapTable
   #68 = Utf8               hashCode
   #69 = Utf8               compareTo
   #70 = Utf8               (Lorg/apache/commons/lang3/mutable/MutableByte;)I
   #71 = Utf8               other
   #72 = Utf8               toString
   #73 = Utf8               ()Ljava/lang/String;
   #74 = Utf8               (Ljava/lang/Object;)I
   #75 = Utf8               (Ljava/lang/Object;)V
   #76 = Utf8               ()Ljava/lang/Object;
   #77 = Utf8               Signature
   #78 = Utf8               Ljava/lang/Number;Ljava/lang/Comparable<Lorg/apache/commons/lang3/mutable/MutableByte;>;Lorg/apache/commons/lang3/mutable/Mutable<Ljava/lang/Number;>;
   #79 = Utf8               SourceFile
   #80 = Utf8               MutableByte.java
   #81 = NameAndType        #23:#24       // "<init>":()V
   #82 = NameAndType        #21:#22       // value:B
   #83 = NameAndType        #53:#40       // byteValue:()B
   #84 = Class              #98           // java/lang/Byte
   #85 = NameAndType        #99:#100      // parseByte:(Ljava/lang/String;)B
   #86 = NameAndType        #101:#102     // valueOf:(B)Ljava/lang/Byte;
   #87 = Utf8               org/apache/commons/lang3/mutable/MutableByte
   #88 = Class              #103          // org/apache/commons/lang3/math/NumberUtils
   #89 = NameAndType        #104:#105     // compare:(BB)I
   #90 = Class              #106          // java/lang/String
   #91 = NameAndType        #101:#107     // valueOf:(I)Ljava/lang/String;
   #92 = NameAndType        #69:#70       // compareTo:(Lorg/apache/commons/lang3/mutable/MutableByte;)I
   #93 = Utf8               java/lang/Number
   #94 = NameAndType        #37:#31       // setValue:(Ljava/lang/Number;)V
   #95 = NameAndType        #35:#36       // getValue:()Ljava/lang/Byte;
   #96 = Utf8               java/lang/Comparable
   #97 = Utf8               org/apache/commons/lang3/mutable/Mutable
   #98 = Utf8               java/lang/Byte
   #99 = Utf8               parseByte
  #100 = Utf8               (Ljava/lang/String;)B
  #101 = Utf8               valueOf
  #102 = Utf8               (B)Ljava/lang/Byte;
  #103 = Utf8               org/apache/commons/lang3/math/NumberUtils
  #104 = Utf8               compare
  #105 = Utf8               (BB)I
  #106 = Utf8               java/lang/String
  #107 = Utf8               (I)Ljava/lang/String;
{
  private static final long serialVersionUID;
    descriptor: J
    flags: (0x001a) ACC_PRIVATE, ACC_STATIC, ACC_FINAL
    ConstantValue: long -1585823265l

  private byte value;
    descriptor: B
    flags: (0x0002) ACC_PRIVATE

  public org.apache.commons.lang3.mutable.MutableByte();
    descriptor: ()V
    flags: (0x0001) ACC_PUBLIC
    Code:
      stack=1, locals=1, args_size=1
         0: aload_0
         1: invokespecial #1                  // Method java/lang/Number."<init>":()V
         4: return
      LineNumberTable:
        line 45: 0
        line 46: 4
      LocalVariableTable:
        Start  Length  Slot  Name   Signature
            0       5     0  this   Lorg/apache/commons/lang3/mutable/MutableByte;

  public org.apache.commons.lang3.mutable.MutableByte(byte);
    descriptor: (B)V
    flags: (0x0001) ACC_PUBLIC
    Code:
      stack=2, locals=2, args_size=2
         0: aload_0
         1: invokespecial #1                  // Method java/lang/Number."<init>":()V
         4: aload_0
         5: iload_1
         6: putfield      #2                  // Field value:B
         9: return
      LineNumberTable:
        line 54: 0
        line 55: 4
        line 56: 9
      LocalVariableTable:
        Start  Length  Slot  Name   Signature
            0      10     0  this   Lorg/apache/commons/lang3/mutable/MutableByte;
            0      10     1 value   B

  public org.apache.commons.lang3.mutable.MutableByte(java.lang.Number);
    descriptor: (Ljava/lang/Number;)V
    flags: (0x0001) ACC_PUBLIC
    Code:
      stack=2, locals=2, args_size=2
         0: aload_0
         1: invokespecial #1                  // Method java/lang/Number."<init>":()V
         4: aload_0
         5: aload_1
         6: invokevirtual #3                  // Method java/lang/Number.byteValue:()B
         9: putfield      #2                  // Field value:B
        12: return
      LineNumberTable:
        line 65: 0
        line 66: 4
        line 67: 12
      LocalVariableTable:
        Start  Length  Slot  Name   Signature
            0      13     0  this   Lorg/apache/commons/lang3/mutable/MutableByte;
            0      13     1 value   Ljava/lang/Number;

  public org.apache.commons.lang3.mutable.MutableByte(java.lang.String);
    descriptor: (Ljava/lang/String;)V
    flags: (0x0001) ACC_PUBLIC
    Code:
      stack=2, locals=2, args_size=2
         0: aload_0
         1: invokespecial #1                  // Method java/lang/Number."<init>":()V
         4: aload_0
         5: aload_1
         6: invokestatic  #4                  // Method java/lang/Byte.parseByte:(Ljava/lang/String;)B
         9: putfield      #2                  // Field value:B
        12: return
      LineNumberTable:
        line 77: 0
        line 78: 4
        line 79: 12
      LocalVariableTable:
        Start  Length  Slot  Name   Signature
            0      13     0  this   Lorg/apache/commons/lang3/mutable/MutableByte;
            0      13     1 value   Ljava/lang/String;

  public java.lang.Byte getValue();
    descriptor: ()Ljava/lang/Byte;
    flags: (0x0001) ACC_PUBLIC
    Code:
      stack=1, locals=1, args_size=1
         0: aload_0
         1: getfield      #2                  // Field value:B
         4: invokestatic  #5                  // Method java/lang/Byte.valueOf:(B)Ljava/lang/Byte;
         7: areturn
      LineNumberTable:
        line 89: 0
      LocalVariableTable:
        Start  Length  Slot  Name   Signature
            0       8     0  this   Lorg/apache/commons/lang3/mutable/MutableByte;

  public void setValue(byte);
    descriptor: (B)V
    flags: (0x0001) ACC_PUBLIC
    Code:
      stack=2, locals=2, args_size=2
         0: aload_0
         1: iload_1
         2: putfield      #2                  // Field value:B
         5: return
      LineNumberTable:
        line 98: 0
        line 99: 5
      LocalVariableTable:
        Start  Length  Slot  Name   Signature
            0       6     0  this   Lorg/apache/commons/lang3/mutable/MutableByte;
            0       6     1 value   B

  public void setValue(java.lang.Number);
    descriptor: (Ljava/lang/Number;)V
    flags: (0x0001) ACC_PUBLIC
    Code:
      stack=2, locals=2, args_size=2
         0: aload_0
         1: aload_1
         2: invokevirtual #3                  // Method java/lang/Number.byteValue:()B
         5: putfield      #2                  // Field value:B
         8: return
      LineNumberTable:
        line 109: 0
        line 110: 8
      LocalVariableTable:
        Start  Length  Slot  Name   Signature
            0       9     0  this   Lorg/apache/commons/lang3/mutable/MutableByte;
            0       9     1 value   Ljava/lang/Number;

  public void increment();
    descriptor: ()V
    flags: (0x0001) ACC_PUBLIC
    Code:
      stack=3, locals=1, args_size=1
         0: aload_0
         1: dup
         2: getfield      #2                  // Field value:B
         5: iconst_1
         6: iadd
         7: i2b
         8: putfield      #2                  // Field value:B
        11: return
      LineNumberTable:
        line 119: 0
        line 120: 11
      LocalVariableTable:
        Start  Length  Slot  Name   Signature
            0      12     0  this   Lorg/apache/commons/lang3/mutable/MutableByte;

  public byte getAndIncrement();
    descriptor: ()B
    flags: (0x0001) ACC_PUBLIC
    Code:
      stack=3, locals=2, args_size=1
         0: aload_0
         1: getfield      #2                  // Field value:B
         4: istore_1
         5: aload_0
         6: dup
         7: getfield      #2                  // Field value:B
        10: iconst_1
        11: iadd
        12: i2b
        13: putfield      #2                  // Field value:B
        16: iload_1
        17: ireturn
      LineNumberTable:
        line 130: 0
        line 131: 5
        line 132: 16
      LocalVariableTable:
        Start  Length  Slot  Name   Signature
            0      18     0  this   Lorg/apache/commons/lang3/mutable/MutableByte;
            5      13     1  last   B

  public byte incrementAndGet();
    descriptor: ()B
    flags: (0x0001) ACC_PUBLIC
    Code:
      stack=3, locals=1, args_size=1
         0: aload_0
         1: dup
         2: getfield      #2                  // Field value:B
         5: iconst_1
         6: iadd
         7: i2b
         8: putfield      #2                  // Field value:B
        11: aload_0
        12: getfield      #2                  // Field value:B
        15: ireturn
      LineNumberTable:
        line 143: 0
        line 144: 11
      LocalVariableTable:
        Start  Length  Slot  Name   Signature
            0      16     0  this   Lorg/apache/commons/lang3/mutable/MutableByte;

  public void decrement();
    descriptor: ()V
    flags: (0x0001) ACC_PUBLIC
    Code:
      stack=3, locals=1, args_size=1
         0: aload_0
         1: dup
         2: getfield      #2                  // Field value:B
         5: iconst_1
         6: isub
         7: i2b
         8: putfield      #2                  // Field value:B
        11: return
      LineNumberTable:
        line 153: 0
        line 154: 11
      LocalVariableTable:
        Start  Length  Slot  Name   Signature
            0      12     0  this   Lorg/apache/commons/lang3/mutable/MutableByte;

  public byte getAndDecrement();
    descriptor: ()B
    flags: (0x0001) ACC_PUBLIC
    Code:
      stack=3, locals=2, args_size=1
         0: aload_0
         1: getfield      #2                  // Field value:B
         4: istore_1
         5: aload_0
         6: dup
         7: getfield      #2                  // Field value:B
        10: iconst_1
        11: isub
        12: i2b
        13: putfield      #2                  // Field value:B
        16: iload_1
        17: ireturn
      LineNumberTable:
        line 164: 0
        line 165: 5
        line 166: 16
      LocalVariableTable:
        Start  Length  Slot  Name   Signature
            0      18     0  this   Lorg/apache/commons/lang3/mutable/MutableByte;
            5      13     1  last   B

  public byte decrementAndGet();
    descriptor: ()B
    flags: (0x0001) ACC_PUBLIC
    Code:
      stack=3, locals=1, args_size=1
         0: aload_0
         1: dup
         2: getfield      #2                  // Field value:B
         5: iconst_1
         6: isub
         7: i2b
         8: putfield      #2                  // Field value:B
        11: aload_0
        12: getfield      #2                  // Field value:B
        15: ireturn
      LineNumberTable:
        line 177: 0
        line 178: 11
      LocalVariableTable:
        Start  Length  Slot  Name   Signature
            0      16     0  this   Lorg/apache/commons/lang3/mutable/MutableByte;

  public void add(byte);
    descriptor: (B)V
    flags: (0x0001) ACC_PUBLIC
    Code:
      stack=3, locals=2, args_size=2
         0: aload_0
         1: dup
         2: getfield      #2                  // Field value:B
         5: iload_1
         6: iadd
         7: i2b
         8: putfield      #2                  // Field value:B
        11: return
      LineNumberTable:
        line 189: 0
        line 190: 11
      LocalVariableTable:
        Start  Length  Slot  Name   Signature
            0      12     0  this   Lorg/apache/commons/lang3/mutable/MutableByte;
            0      12     1 operand   B

  public void add(java.lang.Number);
    descriptor: (Ljava/lang/Number;)V
    flags: (0x0001) ACC_PUBLIC
    Code:
      stack=3, locals=2, args_size=2
         0: aload_0
         1: dup
         2: getfield      #2                  // Field value:B
         5: aload_1
         6: invokevirtual #3                  // Method java/lang/Number.byteValue:()B
         9: iadd
        10: i2b
        11: putfield      #2                  // Field value:B
        14: return
      LineNumberTable:
        line 200: 0
        line 201: 14
      LocalVariableTable:
        Start  Length  Slot  Name   Signature
            0      15     0  this   Lorg/apache/commons/lang3/mutable/MutableByte;
            0      15     1 operand   Ljava/lang/Number;

  public void subtract(byte);
    descriptor: (B)V
    flags: (0x0001) ACC_PUBLIC
    Code:
      stack=3, locals=2, args_size=2
         0: aload_0
         1: dup
         2: getfield      #2                  // Field value:B
         5: iload_1
         6: isub
         7: i2b
         8: putfield      #2                  // Field value:B
        11: return
      LineNumberTable:
        line 210: 0
        line 211: 11
      LocalVariableTable:
        Start  Length  Slot  Name   Signature
            0      12     0  this   Lorg/apache/commons/lang3/mutable/MutableByte;
            0      12     1 operand   B

  public void subtract(java.lang.Number);
    descriptor: (Ljava/lang/Number;)V
    flags: (0x0001) ACC_PUBLIC
    Code:
      stack=3, locals=2, args_size=2
         0: aload_0
         1: dup
         2: getfield      #2                  // Field value:B
         5: aload_1
         6: invokevirtual #3                  // Method java/lang/Number.byteValue:()B
         9: isub
        10: i2b
        11: putfield      #2                  // Field value:B
        14: return
      LineNumberTable:
        line 221: 0
        line 222: 14
      LocalVariableTable:
        Start  Length  Slot  Name   Signature
            0      15     0  this   Lorg/apache/commons/lang3/mutable/MutableByte;
            0      15     1 operand   Ljava/lang/Number;

  public byte addAndGet(byte);
    descriptor: (B)B
    flags: (0x0001) ACC_PUBLIC
    Code:
      stack=3, locals=2, args_size=2
         0: aload_0
         1: dup
         2: getfield      #2                  // Field value:B
         5: iload_1
         6: iadd
         7: i2b
         8: putfield      #2                  // Field value:B
        11: aload_0
        12: getfield      #2                  // Field value:B
        15: ireturn
      LineNumberTable:
        line 233: 0
        line 234: 11
      LocalVariableTable:
        Start  Length  Slot  Name   Signature
            0      16     0  this   Lorg/apache/commons/lang3/mutable/MutableByte;
            0      16     1 operand   B

  public byte addAndGet(java.lang.Number);
    descriptor: (Ljava/lang/Number;)B
    flags: (0x0001) ACC_PUBLIC
    Code:
      stack=3, locals=2, args_size=2
         0: aload_0
         1: dup
         2: getfield      #2                  // Field value:B
         5: aload_1
         6: invokevirtual #3                  // Method java/lang/Number.byteValue:()B
         9: iadd
        10: i2b
        11: putfield      #2                  // Field value:B
        14: aload_0
        15: getfield      #2                  // Field value:B
        18: ireturn
      LineNumberTable:
        line 247: 0
        line 248: 14
      LocalVariableTable:
        Start  Length  Slot  Name   Signature
            0      19     0  this   Lorg/apache/commons/lang3/mutable/MutableByte;
            0      19     1 operand   Ljava/lang/Number;

  public byte getAndAdd(byte);
    descriptor: (B)B
    flags: (0x0001) ACC_PUBLIC
    Code:
      stack=3, locals=3, args_size=2
         0: aload_0
         1: getfield      #2                  // Field value:B
         4: istore_2
         5: aload_0
         6: dup
         7: getfield      #2                  // Field value:B
        10: iload_1
        11: iadd
        12: i2b
        13: putfield      #2                  // Field value:B
        16: iload_2
        17: ireturn
      LineNumberTable:
        line 260: 0
        line 261: 5
        line 262: 16
      LocalVariableTable:
        Start  Length  Slot  Name   Signature
            0      18     0  this   Lorg/apache/commons/lang3/mutable/MutableByte;
            0      18     1 operand   B
            5      13     2  last   B

  public byte getAndAdd(java.lang.Number);
    descriptor: (Ljava/lang/Number;)B
    flags: (0x0001) ACC_PUBLIC
    Code:
      stack=3, locals=3, args_size=2
         0: aload_0
         1: getfield      #2                  // Field value:B
         4: istore_2
         5: aload_0
         6: dup
         7: getfield      #2                  // Field value:B
        10: aload_1
        11: invokevirtual #3                  // Method java/lang/Number.byteValue:()B
        14: iadd
        15: i2b
        16: putfield      #2                  // Field value:B
        19: iload_2
        20: ireturn
      LineNumberTable:
        line 275: 0
        line 276: 5
        line 277: 19
      LocalVariableTable:
        Start  Length  Slot  Name   Signature
            0      21     0  this   Lorg/apache/commons/lang3/mutable/MutableByte;
            0      21     1 operand   Ljava/lang/Number;
            5      16     2  last   B

  public byte byteValue();
    descriptor: ()B
    flags: (0x0001) ACC_PUBLIC
    Code:
      stack=1, locals=1, args_size=1
         0: aload_0
         1: getfield      #2                  // Field value:B
         4: ireturn
      LineNumberTable:
        line 289: 0
      LocalVariableTable:
        Start  Length  Slot  Name   Signature
            0       5     0  this   Lorg/apache/commons/lang3/mutable/MutableByte;

  public int intValue();
    descriptor: ()I
    flags: (0x0001) ACC_PUBLIC
    Code:
      stack=1, locals=1, args_size=1
         0: aload_0
         1: getfield      #2                  // Field value:B
         4: ireturn
      LineNumberTable:
        line 299: 0
      LocalVariableTable:
        Start  Length  Slot  Name   Signature
            0       5     0  this   Lorg/apache/commons/lang3/mutable/MutableByte;

  public long longValue();
    descriptor: ()J
    flags: (0x0001) ACC_PUBLIC
    Code:
      stack=2, locals=1, args_size=1
         0: aload_0
         1: getfield      #2                  // Field value:B
         4: i2l
         5: lreturn
      LineNumberTable:
        line 309: 0
      LocalVariableTable:
        Start  Length  Slot  Name   Signature
            0       6     0  this   Lorg/apache/commons/lang3/mutable/MutableByte;

  public float floatValue();
    descriptor: ()F
    flags: (0x0001) ACC_PUBLIC
    Code:
      stack=1, locals=1, args_size=1
         0: aload_0
         1: getfield      #2                  // Field value:B
         4: i2f
         5: freturn
      LineNumberTable:
        line 319: 0
      LocalVariableTable:
        Start  Length  Slot  Name   Signature
            0       6     0  this   Lorg/apache/commons/lang3/mutable/MutableByte;

  public double doubleValue();
    descriptor: ()D
    flags: (0x0001) ACC_PUBLIC
    Code:
      stack=2, locals=1, args_size=1
         0: aload_0
         1: getfield      #2                  // Field value:B
         4: i2d
         5: dreturn
      LineNumberTable:
        line 329: 0
      LocalVariableTable:
        Start  Length  Slot  Name   Signature
            0       6     0  this   Lorg/apache/commons/lang3/mutable/MutableByte;

  public java.lang.Byte toByte();
    descriptor: ()Ljava/lang/Byte;
    flags: (0x0001) ACC_PUBLIC
    Code:
      stack=1, locals=1, args_size=1
         0: aload_0
         1: invokevirtual #6                  // Method byteValue:()B
         4: invokestatic  #5                  // Method java/lang/Byte.valueOf:(B)Ljava/lang/Byte;
         7: areturn
      LineNumberTable:
        line 339: 0
      LocalVariableTable:
        Start  Length  Slot  Name   Signature
            0       8     0  this   Lorg/apache/commons/lang3/mutable/MutableByte;

  public boolean equals(java.lang.Object);
    descriptor: (Ljava/lang/Object;)Z
    flags: (0x0001) ACC_PUBLIC
    Code:
      stack=2, locals=2, args_size=2
         0: aload_1
         1: instanceof    #7                  // class org/apache/commons/lang3/mutable/MutableByte
         4: ifeq          27
         7: aload_0
         8: getfield      #2                  // Field value:B
        11: aload_1
        12: checkcast     #7                  // class org/apache/commons/lang3/mutable/MutableByte
        15: invokevirtual #6                  // Method byteValue:()B
        18: if_icmpne     25
        21: iconst_1
        22: goto          26
        25: iconst_0
        26: ireturn
        27: iconst_0
        28: ireturn
      LineNumberTable:
        line 353: 0
        line 354: 7
        line 356: 27
      LocalVariableTable:
        Start  Length  Slot  Name   Signature
            0      29     0  this   Lorg/apache/commons/lang3/mutable/MutableByte;
            0      29     1   obj   Ljava/lang/Object;
      StackMapTable: number_of_entries = 3
        frame_type = 25 /* same */
        frame_type = 64 /* same_locals_1_stack_item */
          stack = [ int ]
        frame_type = 0 /* same */

  public int hashCode();
    descriptor: ()I
    flags: (0x0001) ACC_PUBLIC
    Code:
      stack=1, locals=1, args_size=1
         0: aload_0
         1: getfield      #2                  // Field value:B
         4: ireturn
      LineNumberTable:
        line 366: 0
      LocalVariableTable:
        Start  Length  Slot  Name   Signature
            0       5     0  this   Lorg/apache/commons/lang3/mutable/MutableByte;

  public int compareTo(org.apache.commons.lang3.mutable.MutableByte);
    descriptor: (Lorg/apache/commons/lang3/mutable/MutableByte;)I
    flags: (0x0001) ACC_PUBLIC
    Code:
      stack=2, locals=2, args_size=2
         0: aload_0
         1: getfield      #2                  // Field value:B
         4: aload_1
         5: getfield      #2                  // Field value:B
         8: invokestatic  #8                  // Method org/apache/commons/lang3/math/NumberUtils.compare:(BB)I
        11: ireturn
      LineNumberTable:
        line 378: 0
      LocalVariableTable:
        Start  Length  Slot  Name   Signature
            0      12     0  this   Lorg/apache/commons/lang3/mutable/MutableByte;
            0      12     1 other   Lorg/apache/commons/lang3/mutable/MutableByte;

  public java.lang.String toString();
    descriptor: ()Ljava/lang/String;
    flags: (0x0001) ACC_PUBLIC
    Code:
      stack=1, locals=1, args_size=1
         0: aload_0
         1: getfield      #2                  // Field value:B
         4: invokestatic  #9                  // Method java/lang/String.valueOf:(I)Ljava/lang/String;
         7: areturn
      LineNumberTable:
        line 389: 0
      LocalVariableTable:
        Start  Length  Slot  Name   Signature
            0       8     0  this   Lorg/apache/commons/lang3/mutable/MutableByte;

  public int compareTo(java.lang.Object);
    descriptor: (Ljava/lang/Object;)I
    flags: (0x1041) ACC_PUBLIC, ACC_BRIDGE, ACC_SYNTHETIC
    Code:
      stack=2, locals=2, args_size=2
         0: aload_0
         1: aload_1
         2: checkcast     #7                  // class org/apache/commons/lang3/mutable/MutableByte
         5: invokevirtual #10                 // Method compareTo:(Lorg/apache/commons/lang3/mutable/MutableByte;)I
         8: ireturn
      LineNumberTable:
        line 29: 0
      LocalVariableTable:
        Start  Length  Slot  Name   Signature
            0       9     0  this   Lorg/apache/commons/lang3/mutable/MutableByte;

  public void setValue(java.lang.Object);
    descriptor: (Ljava/lang/Object;)V
    flags: (0x1041) ACC_PUBLIC, ACC_BRIDGE, ACC_SYNTHETIC
    Code:
      stack=2, locals=2, args_size=2
         0: aload_0
         1: aload_1
         2: checkcast     #11                 // class java/lang/Number
         5: invokevirtual #12                 // Method setValue:(Ljava/lang/Number;)V
         8: return
      LineNumberTable:
        line 29: 0
      LocalVariableTable:
        Start  Length  Slot  Name   Signature
            0       9     0  this   Lorg/apache/commons/lang3/mutable/MutableByte;

  public java.lang.Object getValue();
    descriptor: ()Ljava/lang/Object;
    flags: (0x1041) ACC_PUBLIC, ACC_BRIDGE, ACC_SYNTHETIC
    Code:
      stack=1, locals=1, args_size=1
         0: aload_0
         1: invokevirtual #13                 // Method getValue:()Ljava/lang/Byte;
         4: areturn
      LineNumberTable:
        line 29: 0
      LocalVariableTable:
        Start  Length  Slot  Name   Signature
            0       5     0  this   Lorg/apache/commons/lang3/mutable/MutableByte;
}
Signature: #78                          // Ljava/lang/Number;Ljava/lang/Comparable<Lorg/apache/commons/lang3/mutable/MutableByte;>;Lorg/apache/commons/lang3/mutable/Mutable<Ljava/lang/Number;>;
SourceFile: "MutableByte.java"
