Classfile /Users/mw/Projects/slang-braindump/.jar/jar8/assemble/slang-braindump/assemble/content/com/fasterxml/jackson/databind/cfg/HandlerInstantiator.class
  Last modified May 29, 2022; size 6244 bytes
  SHA-256 checksum 41a44c97fbb766c6f62b46eb0bdf87b348109cd052651ff42720c51850bc08c6
  Compiled from "HandlerInstantiator.java"
public abstract class com.fasterxml.jackson.databind.cfg.HandlerInstantiator
  minor version: 0
  major version: 52
  flags: (0x0421) ACC_PUBLIC, ACC_SUPER, ACC_ABSTRACT
  this_class: #2                          // com/fasterxml/jackson/databind/cfg/HandlerInstantiator
  super_class: #3                         // java/lang/Object
  interfaces: 0, fields: 0, methods: 13, attributes: 1
Constant pool:
   #1 = Methodref          #3.#64         // java/lang/Object."<init>":()V
   #2 = Class              #65            // com/fasterxml/jackson/databind/cfg/HandlerInstantiator
   #3 = Class              #66            // java/lang/Object
   #4 = Utf8               <init>
   #5 = Utf8               ()V
   #6 = Utf8               Code
   #7 = Utf8               LineNumberTable
   #8 = Utf8               LocalVariableTable
   #9 = Utf8               this
  #10 = Utf8               Lcom/fasterxml/jackson/databind/cfg/HandlerInstantiator;
  #11 = Utf8               deserializerInstance
  #12 = Utf8               (Lcom/fasterxml/jackson/databind/DeserializationConfig;Lcom/fasterxml/jackson/databind/introspect/Annotated;Ljava/lang/Class;)Lcom/fasterxml/jackson/databind/JsonDeserializer;
  #13 = Utf8               Signature
  #14 = Utf8               (Lcom/fasterxml/jackson/databind/DeserializationConfig;Lcom/fasterxml/jackson/databind/introspect/Annotated;Ljava/lang/Class<*>;)Lcom/fasterxml/jackson/databind/JsonDeserializer<*>;
  #15 = Utf8               keyDeserializerInstance
  #16 = Utf8               (Lcom/fasterxml/jackson/databind/DeserializationConfig;Lcom/fasterxml/jackson/databind/introspect/Annotated;Ljava/lang/Class;)Lcom/fasterxml/jackson/databind/KeyDeserializer;
  #17 = Utf8               (Lcom/fasterxml/jackson/databind/DeserializationConfig;Lcom/fasterxml/jackson/databind/introspect/Annotated;Ljava/lang/Class<*>;)Lcom/fasterxml/jackson/databind/KeyDeserializer;
  #18 = Utf8               serializerInstance
  #19 = Utf8               (Lcom/fasterxml/jackson/databind/SerializationConfig;Lcom/fasterxml/jackson/databind/introspect/Annotated;Ljava/lang/Class;)Lcom/fasterxml/jackson/databind/JsonSerializer;
  #20 = Utf8               (Lcom/fasterxml/jackson/databind/SerializationConfig;Lcom/fasterxml/jackson/databind/introspect/Annotated;Ljava/lang/Class<*>;)Lcom/fasterxml/jackson/databind/JsonSerializer<*>;
  #21 = Utf8               typeResolverBuilderInstance
  #22 = Utf8               (Lcom/fasterxml/jackson/databind/cfg/MapperConfig;Lcom/fasterxml/jackson/databind/introspect/Annotated;Ljava/lang/Class;)Lcom/fasterxml/jackson/databind/jsontype/TypeResolverBuilder;
  #23 = Utf8               (Lcom/fasterxml/jackson/databind/cfg/MapperConfig<*>;Lcom/fasterxml/jackson/databind/introspect/Annotated;Ljava/lang/Class<*>;)Lcom/fasterxml/jackson/databind/jsontype/TypeResolverBuilder<*>;
  #24 = Utf8               typeIdResolverInstance
  #25 = Utf8               (Lcom/fasterxml/jackson/databind/cfg/MapperConfig;Lcom/fasterxml/jackson/databind/introspect/Annotated;Ljava/lang/Class;)Lcom/fasterxml/jackson/databind/jsontype/TypeIdResolver;
  #26 = Utf8               (Lcom/fasterxml/jackson/databind/cfg/MapperConfig<*>;Lcom/fasterxml/jackson/databind/introspect/Annotated;Ljava/lang/Class<*>;)Lcom/fasterxml/jackson/databind/jsontype/TypeIdResolver;
  #27 = Utf8               valueInstantiatorInstance
  #28 = Utf8               (Lcom/fasterxml/jackson/databind/cfg/MapperConfig;Lcom/fasterxml/jackson/databind/introspect/Annotated;Ljava/lang/Class;)Lcom/fasterxml/jackson/databind/deser/ValueInstantiator;
  #29 = Utf8               config
  #30 = Utf8               Lcom/fasterxml/jackson/databind/cfg/MapperConfig;
  #31 = Utf8               annotated
  #32 = Utf8               Lcom/fasterxml/jackson/databind/introspect/Annotated;
  #33 = Utf8               resolverClass
  #34 = Utf8               Ljava/lang/Class;
  #35 = Utf8               LocalVariableTypeTable
  #36 = Utf8               Lcom/fasterxml/jackson/databind/cfg/MapperConfig<*>;
  #37 = Utf8               Ljava/lang/Class<*>;
  #38 = Utf8               (Lcom/fasterxml/jackson/databind/cfg/MapperConfig<*>;Lcom/fasterxml/jackson/databind/introspect/Annotated;Ljava/lang/Class<*>;)Lcom/fasterxml/jackson/databind/deser/ValueInstantiator;
  #39 = Utf8               objectIdGeneratorInstance
  #40 = Utf8               (Lcom/fasterxml/jackson/databind/cfg/MapperConfig;Lcom/fasterxml/jackson/databind/introspect/Annotated;Ljava/lang/Class;)Lcom/fasterxml/jackson/annotation/ObjectIdGenerator;
  #41 = Utf8               implClass
  #42 = Utf8               (Lcom/fasterxml/jackson/databind/cfg/MapperConfig<*>;Lcom/fasterxml/jackson/databind/introspect/Annotated;Ljava/lang/Class<*>;)Lcom/fasterxml/jackson/annotation/ObjectIdGenerator<*>;
  #43 = Utf8               resolverIdGeneratorInstance
  #44 = Utf8               (Lcom/fasterxml/jackson/databind/cfg/MapperConfig;Lcom/fasterxml/jackson/databind/introspect/Annotated;Ljava/lang/Class;)Lcom/fasterxml/jackson/annotation/ObjectIdResolver;
  #45 = Utf8               (Lcom/fasterxml/jackson/databind/cfg/MapperConfig<*>;Lcom/fasterxml/jackson/databind/introspect/Annotated;Ljava/lang/Class<*>;)Lcom/fasterxml/jackson/annotation/ObjectIdResolver;
  #46 = Utf8               namingStrategyInstance
  #47 = Utf8               (Lcom/fasterxml/jackson/databind/cfg/MapperConfig;Lcom/fasterxml/jackson/databind/introspect/Annotated;Ljava/lang/Class;)Lcom/fasterxml/jackson/databind/PropertyNamingStrategy;
  #48 = Utf8               (Lcom/fasterxml/jackson/databind/cfg/MapperConfig<*>;Lcom/fasterxml/jackson/databind/introspect/Annotated;Ljava/lang/Class<*>;)Lcom/fasterxml/jackson/databind/PropertyNamingStrategy;
  #49 = Utf8               converterInstance
  #50 = Utf8               (Lcom/fasterxml/jackson/databind/cfg/MapperConfig;Lcom/fasterxml/jackson/databind/introspect/Annotated;Ljava/lang/Class;)Lcom/fasterxml/jackson/databind/util/Converter;
  #51 = Utf8               (Lcom/fasterxml/jackson/databind/cfg/MapperConfig<*>;Lcom/fasterxml/jackson/databind/introspect/Annotated;Ljava/lang/Class<*>;)Lcom/fasterxml/jackson/databind/util/Converter<**>;
  #52 = Utf8               virtualPropertyWriterInstance
  #53 = Utf8               (Lcom/fasterxml/jackson/databind/cfg/MapperConfig;Ljava/lang/Class;)Lcom/fasterxml/jackson/databind/ser/VirtualBeanPropertyWriter;
  #54 = Utf8               (Lcom/fasterxml/jackson/databind/cfg/MapperConfig<*>;Ljava/lang/Class<*>;)Lcom/fasterxml/jackson/databind/ser/VirtualBeanPropertyWriter;
  #55 = Utf8               includeFilterInstance
  #56 = Utf8               (Lcom/fasterxml/jackson/databind/SerializationConfig;Lcom/fasterxml/jackson/databind/introspect/BeanPropertyDefinition;Ljava/lang/Class;)Ljava/lang/Object;
  #57 = Utf8               Lcom/fasterxml/jackson/databind/SerializationConfig;
  #58 = Utf8               forProperty
  #59 = Utf8               Lcom/fasterxml/jackson/databind/introspect/BeanPropertyDefinition;
  #60 = Utf8               filterClass
  #61 = Utf8               (Lcom/fasterxml/jackson/databind/SerializationConfig;Lcom/fasterxml/jackson/databind/introspect/BeanPropertyDefinition;Ljava/lang/Class<*>;)Ljava/lang/Object;
  #62 = Utf8               SourceFile
  #63 = Utf8               HandlerInstantiator.java
  #64 = NameAndType        #4:#5          // "<init>":()V
  #65 = Utf8               com/fasterxml/jackson/databind/cfg/HandlerInstantiator
  #66 = Utf8               java/lang/Object
{
  public com.fasterxml.jackson.databind.cfg.HandlerInstantiator();
    descriptor: ()V
    flags: (0x0001) ACC_PUBLIC
    Code:
      stack=1, locals=1, args_size=1
         0: aload_0
         1: invokespecial #1                  // Method java/lang/Object."<init>":()V
         4: return
      LineNumberTable:
        line 30: 0
      LocalVariableTable:
        Start  Length  Slot  Name   Signature
            0       5     0  this   Lcom/fasterxml/jackson/databind/cfg/HandlerInstantiator;

  public abstract com.fasterxml.jackson.databind.JsonDeserializer<?> deserializerInstance(com.fasterxml.jackson.databind.DeserializationConfig, com.fasterxml.jackson.databind.introspect.Annotated, java.lang.Class<?>);
    descriptor: (Lcom/fasterxml/jackson/databind/DeserializationConfig;Lcom/fasterxml/jackson/databind/introspect/Annotated;Ljava/lang/Class;)Lcom/fasterxml/jackson/databind/JsonDeserializer;
    flags: (0x0401) ACC_PUBLIC, ACC_ABSTRACT
    Signature: #14                          // (Lcom/fasterxml/jackson/databind/DeserializationConfig;Lcom/fasterxml/jackson/databind/introspect/Annotated;Ljava/lang/Class<*>;)Lcom/fasterxml/jackson/databind/JsonDeserializer<*>;

  public abstract com.fasterxml.jackson.databind.KeyDeserializer keyDeserializerInstance(com.fasterxml.jackson.databind.DeserializationConfig, com.fasterxml.jackson.databind.introspect.Annotated, java.lang.Class<?>);
    descriptor: (Lcom/fasterxml/jackson/databind/DeserializationConfig;Lcom/fasterxml/jackson/databind/introspect/Annotated;Ljava/lang/Class;)Lcom/fasterxml/jackson/databind/KeyDeserializer;
    flags: (0x0401) ACC_PUBLIC, ACC_ABSTRACT
    Signature: #17                          // (Lcom/fasterxml/jackson/databind/DeserializationConfig;Lcom/fasterxml/jackson/databind/introspect/Annotated;Ljava/lang/Class<*>;)Lcom/fasterxml/jackson/databind/KeyDeserializer;

  public abstract com.fasterxml.jackson.databind.JsonSerializer<?> serializerInstance(com.fasterxml.jackson.databind.SerializationConfig, com.fasterxml.jackson.databind.introspect.Annotated, java.lang.Class<?>);
    descriptor: (Lcom/fasterxml/jackson/databind/SerializationConfig;Lcom/fasterxml/jackson/databind/introspect/Annotated;Ljava/lang/Class;)Lcom/fasterxml/jackson/databind/JsonSerializer;
    flags: (0x0401) ACC_PUBLIC, ACC_ABSTRACT
    Signature: #20                          // (Lcom/fasterxml/jackson/databind/SerializationConfig;Lcom/fasterxml/jackson/databind/introspect/Annotated;Ljava/lang/Class<*>;)Lcom/fasterxml/jackson/databind/JsonSerializer<*>;

  public abstract com.fasterxml.jackson.databind.jsontype.TypeResolverBuilder<?> typeResolverBuilderInstance(com.fasterxml.jackson.databind.cfg.MapperConfig<?>, com.fasterxml.jackson.databind.introspect.Annotated, java.lang.Class<?>);
    descriptor: (Lcom/fasterxml/jackson/databind/cfg/MapperConfig;Lcom/fasterxml/jackson/databind/introspect/Annotated;Ljava/lang/Class;)Lcom/fasterxml/jackson/databind/jsontype/TypeResolverBuilder;
    flags: (0x0401) ACC_PUBLIC, ACC_ABSTRACT
    Signature: #23                          // (Lcom/fasterxml/jackson/databind/cfg/MapperConfig<*>;Lcom/fasterxml/jackson/databind/introspect/Annotated;Ljava/lang/Class<*>;)Lcom/fasterxml/jackson/databind/jsontype/TypeResolverBuilder<*>;

  public abstract com.fasterxml.jackson.databind.jsontype.TypeIdResolver typeIdResolverInstance(com.fasterxml.jackson.databind.cfg.MapperConfig<?>, com.fasterxml.jackson.databind.introspect.Annotated, java.lang.Class<?>);
    descriptor: (Lcom/fasterxml/jackson/databind/cfg/MapperConfig;Lcom/fasterxml/jackson/databind/introspect/Annotated;Ljava/lang/Class;)Lcom/fasterxml/jackson/databind/jsontype/TypeIdResolver;
    flags: (0x0401) ACC_PUBLIC, ACC_ABSTRACT
    Signature: #26                          // (Lcom/fasterxml/jackson/databind/cfg/MapperConfig<*>;Lcom/fasterxml/jackson/databind/introspect/Annotated;Ljava/lang/Class<*>;)Lcom/fasterxml/jackson/databind/jsontype/TypeIdResolver;

  public com.fasterxml.jackson.databind.deser.ValueInstantiator valueInstantiatorInstance(com.fasterxml.jackson.databind.cfg.MapperConfig<?>, com.fasterxml.jackson.databind.introspect.Annotated, java.lang.Class<?>);
    descriptor: (Lcom/fasterxml/jackson/databind/cfg/MapperConfig;Lcom/fasterxml/jackson/databind/introspect/Annotated;Ljava/lang/Class;)Lcom/fasterxml/jackson/databind/deser/ValueInstantiator;
    flags: (0x0001) ACC_PUBLIC
    Code:
      stack=1, locals=4, args_size=4
         0: aconst_null
         1: areturn
      LineNumberTable:
        line 115: 0
      LocalVariableTable:
        Start  Length  Slot  Name   Signature
            0       2     0  this   Lcom/fasterxml/jackson/databind/cfg/HandlerInstantiator;
            0       2     1 config   Lcom/fasterxml/jackson/databind/cfg/MapperConfig;
            0       2     2 annotated   Lcom/fasterxml/jackson/databind/introspect/Annotated;
            0       2     3 resolverClass   Ljava/lang/Class;
      LocalVariableTypeTable:
        Start  Length  Slot  Name   Signature
            0       2     1 config   Lcom/fasterxml/jackson/databind/cfg/MapperConfig<*>;
            0       2     3 resolverClass   Ljava/lang/Class<*>;
    Signature: #38                          // (Lcom/fasterxml/jackson/databind/cfg/MapperConfig<*>;Lcom/fasterxml/jackson/databind/introspect/Annotated;Ljava/lang/Class<*>;)Lcom/fasterxml/jackson/databind/deser/ValueInstantiator;

  public com.fasterxml.jackson.annotation.ObjectIdGenerator<?> objectIdGeneratorInstance(com.fasterxml.jackson.databind.cfg.MapperConfig<?>, com.fasterxml.jackson.databind.introspect.Annotated, java.lang.Class<?>);
    descriptor: (Lcom/fasterxml/jackson/databind/cfg/MapperConfig;Lcom/fasterxml/jackson/databind/introspect/Annotated;Ljava/lang/Class;)Lcom/fasterxml/jackson/annotation/ObjectIdGenerator;
    flags: (0x0001) ACC_PUBLIC
    Code:
      stack=1, locals=4, args_size=4
         0: aconst_null
         1: areturn
      LineNumberTable:
        line 126: 0
      LocalVariableTable:
        Start  Length  Slot  Name   Signature
            0       2     0  this   Lcom/fasterxml/jackson/databind/cfg/HandlerInstantiator;
            0       2     1 config   Lcom/fasterxml/jackson/databind/cfg/MapperConfig;
            0       2     2 annotated   Lcom/fasterxml/jackson/databind/introspect/Annotated;
            0       2     3 implClass   Ljava/lang/Class;
      LocalVariableTypeTable:
        Start  Length  Slot  Name   Signature
            0       2     1 config   Lcom/fasterxml/jackson/databind/cfg/MapperConfig<*>;
            0       2     3 implClass   Ljava/lang/Class<*>;
    Signature: #42                          // (Lcom/fasterxml/jackson/databind/cfg/MapperConfig<*>;Lcom/fasterxml/jackson/databind/introspect/Annotated;Ljava/lang/Class<*>;)Lcom/fasterxml/jackson/annotation/ObjectIdGenerator<*>;

  public com.fasterxml.jackson.annotation.ObjectIdResolver resolverIdGeneratorInstance(com.fasterxml.jackson.databind.cfg.MapperConfig<?>, com.fasterxml.jackson.databind.introspect.Annotated, java.lang.Class<?>);
    descriptor: (Lcom/fasterxml/jackson/databind/cfg/MapperConfig;Lcom/fasterxml/jackson/databind/introspect/Annotated;Ljava/lang/Class;)Lcom/fasterxml/jackson/annotation/ObjectIdResolver;
    flags: (0x0001) ACC_PUBLIC
    Code:
      stack=1, locals=4, args_size=4
         0: aconst_null
         1: areturn
      LineNumberTable:
        line 130: 0
      LocalVariableTable:
        Start  Length  Slot  Name   Signature
            0       2     0  this   Lcom/fasterxml/jackson/databind/cfg/HandlerInstantiator;
            0       2     1 config   Lcom/fasterxml/jackson/databind/cfg/MapperConfig;
            0       2     2 annotated   Lcom/fasterxml/jackson/databind/introspect/Annotated;
            0       2     3 implClass   Ljava/lang/Class;
      LocalVariableTypeTable:
        Start  Length  Slot  Name   Signature
            0       2     1 config   Lcom/fasterxml/jackson/databind/cfg/MapperConfig<*>;
            0       2     3 implClass   Ljava/lang/Class<*>;
    Signature: #45                          // (Lcom/fasterxml/jackson/databind/cfg/MapperConfig<*>;Lcom/fasterxml/jackson/databind/introspect/Annotated;Ljava/lang/Class<*>;)Lcom/fasterxml/jackson/annotation/ObjectIdResolver;

  public com.fasterxml.jackson.databind.PropertyNamingStrategy namingStrategyInstance(com.fasterxml.jackson.databind.cfg.MapperConfig<?>, com.fasterxml.jackson.databind.introspect.Annotated, java.lang.Class<?>);
    descriptor: (Lcom/fasterxml/jackson/databind/cfg/MapperConfig;Lcom/fasterxml/jackson/databind/introspect/Annotated;Ljava/lang/Class;)Lcom/fasterxml/jackson/databind/PropertyNamingStrategy;
    flags: (0x0001) ACC_PUBLIC
    Code:
      stack=1, locals=4, args_size=4
         0: aconst_null
         1: areturn
      LineNumberTable:
        line 141: 0
      LocalVariableTable:
        Start  Length  Slot  Name   Signature
            0       2     0  this   Lcom/fasterxml/jackson/databind/cfg/HandlerInstantiator;
            0       2     1 config   Lcom/fasterxml/jackson/databind/cfg/MapperConfig;
            0       2     2 annotated   Lcom/fasterxml/jackson/databind/introspect/Annotated;
            0       2     3 implClass   Ljava/lang/Class;
      LocalVariableTypeTable:
        Start  Length  Slot  Name   Signature
            0       2     1 config   Lcom/fasterxml/jackson/databind/cfg/MapperConfig<*>;
            0       2     3 implClass   Ljava/lang/Class<*>;
    Signature: #48                          // (Lcom/fasterxml/jackson/databind/cfg/MapperConfig<*>;Lcom/fasterxml/jackson/databind/introspect/Annotated;Ljava/lang/Class<*>;)Lcom/fasterxml/jackson/databind/PropertyNamingStrategy;

  public com.fasterxml.jackson.databind.util.Converter<?, ?> converterInstance(com.fasterxml.jackson.databind.cfg.MapperConfig<?>, com.fasterxml.jackson.databind.introspect.Annotated, java.lang.Class<?>);
    descriptor: (Lcom/fasterxml/jackson/databind/cfg/MapperConfig;Lcom/fasterxml/jackson/databind/introspect/Annotated;Ljava/lang/Class;)Lcom/fasterxml/jackson/databind/util/Converter;
    flags: (0x0001) ACC_PUBLIC
    Code:
      stack=1, locals=4, args_size=4
         0: aconst_null
         1: areturn
      LineNumberTable:
        line 151: 0
      LocalVariableTable:
        Start  Length  Slot  Name   Signature
            0       2     0  this   Lcom/fasterxml/jackson/databind/cfg/HandlerInstantiator;
            0       2     1 config   Lcom/fasterxml/jackson/databind/cfg/MapperConfig;
            0       2     2 annotated   Lcom/fasterxml/jackson/databind/introspect/Annotated;
            0       2     3 implClass   Ljava/lang/Class;
      LocalVariableTypeTable:
        Start  Length  Slot  Name   Signature
            0       2     1 config   Lcom/fasterxml/jackson/databind/cfg/MapperConfig<*>;
            0       2     3 implClass   Ljava/lang/Class<*>;
    Signature: #51                          // (Lcom/fasterxml/jackson/databind/cfg/MapperConfig<*>;Lcom/fasterxml/jackson/databind/introspect/Annotated;Ljava/lang/Class<*>;)Lcom/fasterxml/jackson/databind/util/Converter<**>;

  public com.fasterxml.jackson.databind.ser.VirtualBeanPropertyWriter virtualPropertyWriterInstance(com.fasterxml.jackson.databind.cfg.MapperConfig<?>, java.lang.Class<?>);
    descriptor: (Lcom/fasterxml/jackson/databind/cfg/MapperConfig;Ljava/lang/Class;)Lcom/fasterxml/jackson/databind/ser/VirtualBeanPropertyWriter;
    flags: (0x0001) ACC_PUBLIC
    Code:
      stack=1, locals=3, args_size=3
         0: aconst_null
         1: areturn
      LineNumberTable:
        line 162: 0
      LocalVariableTable:
        Start  Length  Slot  Name   Signature
            0       2     0  this   Lcom/fasterxml/jackson/databind/cfg/HandlerInstantiator;
            0       2     1 config   Lcom/fasterxml/jackson/databind/cfg/MapperConfig;
            0       2     2 implClass   Ljava/lang/Class;
      LocalVariableTypeTable:
        Start  Length  Slot  Name   Signature
            0       2     1 config   Lcom/fasterxml/jackson/databind/cfg/MapperConfig<*>;
            0       2     2 implClass   Ljava/lang/Class<*>;
    Signature: #54                          // (Lcom/fasterxml/jackson/databind/cfg/MapperConfig<*>;Ljava/lang/Class<*>;)Lcom/fasterxml/jackson/databind/ser/VirtualBeanPropertyWriter;

  public java.lang.Object includeFilterInstance(com.fasterxml.jackson.databind.SerializationConfig, com.fasterxml.jackson.databind.introspect.BeanPropertyDefinition, java.lang.Class<?>);
    descriptor: (Lcom/fasterxml/jackson/databind/SerializationConfig;Lcom/fasterxml/jackson/databind/introspect/BeanPropertyDefinition;Ljava/lang/Class;)Ljava/lang/Object;
    flags: (0x0001) ACC_PUBLIC
    Code:
      stack=1, locals=4, args_size=4
         0: aconst_null
         1: areturn
      LineNumberTable:
        line 180: 0
      LocalVariableTable:
        Start  Length  Slot  Name   Signature
            0       2     0  this   Lcom/fasterxml/jackson/databind/cfg/HandlerInstantiator;
            0       2     1 config   Lcom/fasterxml/jackson/databind/SerializationConfig;
            0       2     2 forProperty   Lcom/fasterxml/jackson/databind/introspect/BeanPropertyDefinition;
            0       2     3 filterClass   Ljava/lang/Class;
      LocalVariableTypeTable:
        Start  Length  Slot  Name   Signature
            0       2     3 filterClass   Ljava/lang/Class<*>;
    Signature: #61                          // (Lcom/fasterxml/jackson/databind/SerializationConfig;Lcom/fasterxml/jackson/databind/introspect/BeanPropertyDefinition;Ljava/lang/Class<*>;)Ljava/lang/Object;
}
SourceFile: "HandlerInstantiator.java"
