Classfile /Users/mw/Projects/slang-braindump/.jar/jar11/assemble/slang-braindump/assemble/content/com/fasterxml/jackson/databind/ser/impl/IndexedListSerializer.class
  Last modified May 29, 2022; size 9986 bytes
  SHA-256 checksum f5cee8663525efafecfdb61c0451cf73d80383dda6421b628d1260ee4fd2905e
  Compiled from "IndexedListSerializer.java"
public final class com.fasterxml.jackson.databind.ser.impl.IndexedListSerializer extends com.fasterxml.jackson.databind.ser.std.AsArraySerializerBase<java.util.List<?>>
  minor version: 0
  major version: 52
  flags: (0x0031) ACC_PUBLIC, ACC_FINAL, ACC_SUPER
  this_class: #4                          // com/fasterxml/jackson/databind/ser/impl/IndexedListSerializer
  super_class: #38                        // com/fasterxml/jackson/databind/ser/std/AsArraySerializerBase
  interfaces: 0, fields: 1, methods: 15, attributes: 3
Constant pool:
    #1 = Class              #135          // java/util/List
    #2 = Methodref          #38.#136      // com/fasterxml/jackson/databind/ser/std/AsArraySerializerBase."<init>":(Ljava/lang/Class;Lcom/fasterxml/jackson/databind/JavaType;ZLcom/fasterxml/jackson/databind/jsontype/TypeSerializer;Lcom/fasterxml/jackson/databind/JsonSerializer;)V
    #3 = Methodref          #38.#137      // com/fasterxml/jackson/databind/ser/std/AsArraySerializerBase."<init>":(Lcom/fasterxml/jackson/databind/ser/std/AsArraySerializerBase;Lcom/fasterxml/jackson/databind/BeanProperty;Lcom/fasterxml/jackson/databind/jsontype/TypeSerializer;Lcom/fasterxml/jackson/databind/JsonSerializer;Ljava/lang/Boolean;)V
    #4 = Class              #138          // com/fasterxml/jackson/databind/ser/impl/IndexedListSerializer
    #5 = Methodref          #4.#139       // com/fasterxml/jackson/databind/ser/impl/IndexedListSerializer."<init>":(Lcom/fasterxml/jackson/databind/ser/impl/IndexedListSerializer;Lcom/fasterxml/jackson/databind/BeanProperty;Lcom/fasterxml/jackson/databind/jsontype/TypeSerializer;Lcom/fasterxml/jackson/databind/JsonSerializer;Ljava/lang/Boolean;)V
    #6 = InterfaceMethodref #1.#140       // java/util/List.isEmpty:()Z
    #7 = InterfaceMethodref #1.#141       // java/util/List.size:()I
    #8 = Fieldref           #4.#142       // com/fasterxml/jackson/databind/ser/impl/IndexedListSerializer._property:Lcom/fasterxml/jackson/databind/BeanProperty;
    #9 = Fieldref           #4.#143       // com/fasterxml/jackson/databind/ser/impl/IndexedListSerializer._elementSerializer:Lcom/fasterxml/jackson/databind/JsonSerializer;
   #10 = Fieldref           #4.#144       // com/fasterxml/jackson/databind/ser/impl/IndexedListSerializer._unwrapSingle:Ljava/lang/Boolean;
   #11 = Fieldref           #145.#146     // com/fasterxml/jackson/databind/SerializationFeature.WRITE_SINGLE_ELEM_ARRAYS_UNWRAPPED:Lcom/fasterxml/jackson/databind/SerializationFeature;
   #12 = Methodref          #147.#148     // com/fasterxml/jackson/databind/SerializerProvider.isEnabled:(Lcom/fasterxml/jackson/databind/SerializationFeature;)Z
   #13 = Fieldref           #149.#150     // java/lang/Boolean.TRUE:Ljava/lang/Boolean;
   #14 = Methodref          #4.#151       // com/fasterxml/jackson/databind/ser/impl/IndexedListSerializer.serializeContents:(Ljava/util/List;Lcom/fasterxml/jackson/core/JsonGenerator;Lcom/fasterxml/jackson/databind/SerializerProvider;)V
   #15 = Methodref          #152.#153     // com/fasterxml/jackson/core/JsonGenerator.writeStartArray:(Ljava/lang/Object;I)V
   #16 = Methodref          #152.#154     // com/fasterxml/jackson/core/JsonGenerator.writeEndArray:()V
   #17 = Methodref          #4.#155       // com/fasterxml/jackson/databind/ser/impl/IndexedListSerializer.serializeContentsUsing:(Ljava/util/List;Lcom/fasterxml/jackson/core/JsonGenerator;Lcom/fasterxml/jackson/databind/SerializerProvider;Lcom/fasterxml/jackson/databind/JsonSerializer;)V
   #18 = Fieldref           #4.#156       // com/fasterxml/jackson/databind/ser/impl/IndexedListSerializer._valueTypeSerializer:Lcom/fasterxml/jackson/databind/jsontype/TypeSerializer;
   #19 = Methodref          #4.#157       // com/fasterxml/jackson/databind/ser/impl/IndexedListSerializer.serializeTypedContents:(Ljava/util/List;Lcom/fasterxml/jackson/core/JsonGenerator;Lcom/fasterxml/jackson/databind/SerializerProvider;)V
   #20 = Fieldref           #4.#158       // com/fasterxml/jackson/databind/ser/impl/IndexedListSerializer._dynamicSerializers:Lcom/fasterxml/jackson/databind/ser/impl/PropertySerializerMap;
   #21 = InterfaceMethodref #1.#159       // java/util/List.get:(I)Ljava/lang/Object;
   #22 = Methodref          #147.#160     // com/fasterxml/jackson/databind/SerializerProvider.defaultSerializeNull:(Lcom/fasterxml/jackson/core/JsonGenerator;)V
   #23 = Methodref          #161.#162     // java/lang/Object.getClass:()Ljava/lang/Class;
   #24 = Methodref          #163.#164     // com/fasterxml/jackson/databind/ser/impl/PropertySerializerMap.serializerFor:(Ljava/lang/Class;)Lcom/fasterxml/jackson/databind/JsonSerializer;
   #25 = Fieldref           #4.#165       // com/fasterxml/jackson/databind/ser/impl/IndexedListSerializer._elementType:Lcom/fasterxml/jackson/databind/JavaType;
   #26 = Methodref          #166.#167     // com/fasterxml/jackson/databind/JavaType.hasGenericTypes:()Z
   #27 = Methodref          #147.#168     // com/fasterxml/jackson/databind/SerializerProvider.constructSpecializedType:(Lcom/fasterxml/jackson/databind/JavaType;Ljava/lang/Class;)Lcom/fasterxml/jackson/databind/JavaType;
   #28 = Methodref          #4.#169       // com/fasterxml/jackson/databind/ser/impl/IndexedListSerializer._findAndAddDynamic:(Lcom/fasterxml/jackson/databind/ser/impl/PropertySerializerMap;Lcom/fasterxml/jackson/databind/JavaType;Lcom/fasterxml/jackson/databind/SerializerProvider;)Lcom/fasterxml/jackson/databind/JsonSerializer;
   #29 = Methodref          #4.#170       // com/fasterxml/jackson/databind/ser/impl/IndexedListSerializer._findAndAddDynamic:(Lcom/fasterxml/jackson/databind/ser/impl/PropertySerializerMap;Ljava/lang/Class;Lcom/fasterxml/jackson/databind/SerializerProvider;)Lcom/fasterxml/jackson/databind/JsonSerializer;
   #30 = Methodref          #171.#172     // com/fasterxml/jackson/databind/JsonSerializer.serialize:(Ljava/lang/Object;Lcom/fasterxml/jackson/core/JsonGenerator;Lcom/fasterxml/jackson/databind/SerializerProvider;)V
   #31 = Class              #173          // java/lang/Exception
   #32 = Methodref          #4.#174       // com/fasterxml/jackson/databind/ser/impl/IndexedListSerializer.wrapAndThrow:(Lcom/fasterxml/jackson/databind/SerializerProvider;Ljava/lang/Throwable;Ljava/lang/Object;I)V
   #33 = Methodref          #171.#175     // com/fasterxml/jackson/databind/JsonSerializer.serializeWithType:(Ljava/lang/Object;Lcom/fasterxml/jackson/core/JsonGenerator;Lcom/fasterxml/jackson/databind/SerializerProvider;Lcom/fasterxml/jackson/databind/jsontype/TypeSerializer;)V
   #34 = Methodref          #4.#176       // com/fasterxml/jackson/databind/ser/impl/IndexedListSerializer.serialize:(Ljava/util/List;Lcom/fasterxml/jackson/core/JsonGenerator;Lcom/fasterxml/jackson/databind/SerializerProvider;)V
   #35 = Methodref          #4.#177       // com/fasterxml/jackson/databind/ser/impl/IndexedListSerializer.withResolved:(Lcom/fasterxml/jackson/databind/BeanProperty;Lcom/fasterxml/jackson/databind/jsontype/TypeSerializer;Lcom/fasterxml/jackson/databind/JsonSerializer;Ljava/lang/Boolean;)Lcom/fasterxml/jackson/databind/ser/impl/IndexedListSerializer;
   #36 = Methodref          #4.#178       // com/fasterxml/jackson/databind/ser/impl/IndexedListSerializer.hasSingleElement:(Ljava/util/List;)Z
   #37 = Methodref          #4.#179       // com/fasterxml/jackson/databind/ser/impl/IndexedListSerializer.isEmpty:(Lcom/fasterxml/jackson/databind/SerializerProvider;Ljava/util/List;)Z
   #38 = Class              #180          // com/fasterxml/jackson/databind/ser/std/AsArraySerializerBase
   #39 = Utf8               serialVersionUID
   #40 = Utf8               J
   #41 = Utf8               ConstantValue
   #42 = Long               1l
   #44 = Utf8               <init>
   #45 = Utf8               (Lcom/fasterxml/jackson/databind/JavaType;ZLcom/fasterxml/jackson/databind/jsontype/TypeSerializer;Lcom/fasterxml/jackson/databind/JsonSerializer;)V
   #46 = Utf8               Code
   #47 = Utf8               LineNumberTable
   #48 = Utf8               LocalVariableTable
   #49 = Utf8               this
   #50 = Utf8               Lcom/fasterxml/jackson/databind/ser/impl/IndexedListSerializer;
   #51 = Utf8               elemType
   #52 = Utf8               Lcom/fasterxml/jackson/databind/JavaType;
   #53 = Utf8               staticTyping
   #54 = Utf8               Z
   #55 = Utf8               vts
   #56 = Utf8               Lcom/fasterxml/jackson/databind/jsontype/TypeSerializer;
   #57 = Utf8               valueSerializer
   #58 = Utf8               Lcom/fasterxml/jackson/databind/JsonSerializer;
   #59 = Utf8               LocalVariableTypeTable
   #60 = Utf8               Lcom/fasterxml/jackson/databind/JsonSerializer<Ljava/lang/Object;>;
   #61 = Utf8               Signature
   #62 = Utf8               (Lcom/fasterxml/jackson/databind/JavaType;ZLcom/fasterxml/jackson/databind/jsontype/TypeSerializer;Lcom/fasterxml/jackson/databind/JsonSerializer<Ljava/lang/Object;>;)V
   #63 = Utf8               (Lcom/fasterxml/jackson/databind/ser/impl/IndexedListSerializer;Lcom/fasterxml/jackson/databind/BeanProperty;Lcom/fasterxml/jackson/databind/jsontype/TypeSerializer;Lcom/fasterxml/jackson/databind/JsonSerializer;Ljava/lang/Boolean;)V
   #64 = Utf8               src
   #65 = Utf8               property
   #66 = Utf8               Lcom/fasterxml/jackson/databind/BeanProperty;
   #67 = Utf8               unwrapSingle
   #68 = Utf8               Ljava/lang/Boolean;
   #69 = Utf8               Lcom/fasterxml/jackson/databind/JsonSerializer<*>;
   #70 = Utf8               (Lcom/fasterxml/jackson/databind/ser/impl/IndexedListSerializer;Lcom/fasterxml/jackson/databind/BeanProperty;Lcom/fasterxml/jackson/databind/jsontype/TypeSerializer;Lcom/fasterxml/jackson/databind/JsonSerializer<*>;Ljava/lang/Boolean;)V
   #71 = Utf8               withResolved
   #72 = Utf8               (Lcom/fasterxml/jackson/databind/BeanProperty;Lcom/fasterxml/jackson/databind/jsontype/TypeSerializer;Lcom/fasterxml/jackson/databind/JsonSerializer;Ljava/lang/Boolean;)Lcom/fasterxml/jackson/databind/ser/impl/IndexedListSerializer;
   #73 = Utf8               elementSerializer
   #74 = Utf8               (Lcom/fasterxml/jackson/databind/BeanProperty;Lcom/fasterxml/jackson/databind/jsontype/TypeSerializer;Lcom/fasterxml/jackson/databind/JsonSerializer<*>;Ljava/lang/Boolean;)Lcom/fasterxml/jackson/databind/ser/impl/IndexedListSerializer;
   #75 = Utf8               isEmpty
   #76 = Utf8               (Lcom/fasterxml/jackson/databind/SerializerProvider;Ljava/util/List;)Z
   #77 = Utf8               prov
   #78 = Utf8               Lcom/fasterxml/jackson/databind/SerializerProvider;
   #79 = Utf8               value
   #80 = Utf8               Ljava/util/List;
   #81 = Utf8               Ljava/util/List<*>;
   #82 = Utf8               (Lcom/fasterxml/jackson/databind/SerializerProvider;Ljava/util/List<*>;)Z
   #83 = Utf8               hasSingleElement
   #84 = Utf8               (Ljava/util/List;)Z
   #85 = Utf8               StackMapTable
   #86 = Utf8               (Ljava/util/List<*>;)Z
   #87 = Utf8               _withValueTypeSerializer
   #88 = Utf8               (Lcom/fasterxml/jackson/databind/jsontype/TypeSerializer;)Lcom/fasterxml/jackson/databind/ser/ContainerSerializer;
   #89 = Utf8               (Lcom/fasterxml/jackson/databind/jsontype/TypeSerializer;)Lcom/fasterxml/jackson/databind/ser/ContainerSerializer<*>;
   #90 = Utf8               serialize
   #91 = Utf8               (Ljava/util/List;Lcom/fasterxml/jackson/core/JsonGenerator;Lcom/fasterxml/jackson/databind/SerializerProvider;)V
   #92 = Utf8               gen
   #93 = Utf8               Lcom/fasterxml/jackson/core/JsonGenerator;
   #94 = Utf8               provider
   #95 = Utf8               len
   #96 = Utf8               I
   #97 = Utf8               Exceptions
   #98 = Class              #181          // java/io/IOException
   #99 = Utf8               (Ljava/util/List<*>;Lcom/fasterxml/jackson/core/JsonGenerator;Lcom/fasterxml/jackson/databind/SerializerProvider;)V
  #100 = Utf8               serializeContents
  #101 = Utf8               cc
  #102 = Utf8               Ljava/lang/Class;
  #103 = Utf8               serializer
  #104 = Utf8               elem
  #105 = Utf8               Ljava/lang/Object;
  #106 = Utf8               serializers
  #107 = Utf8               Lcom/fasterxml/jackson/databind/ser/impl/PropertySerializerMap;
  #108 = Utf8               e
  #109 = Utf8               Ljava/lang/Exception;
  #110 = Utf8               g
  #111 = Utf8               i
  #112 = Utf8               Ljava/lang/Class<*>;
  #113 = Class              #182          // com/fasterxml/jackson/databind/ser/impl/PropertySerializerMap
  #114 = Class              #183          // java/lang/Object
  #115 = Class              #184          // java/lang/Class
  #116 = Class              #185          // com/fasterxml/jackson/databind/JsonSerializer
  #117 = Class              #173          // java/lang/Exception
  #118 = Utf8               serializeContentsUsing
  #119 = Utf8               (Ljava/util/List;Lcom/fasterxml/jackson/core/JsonGenerator;Lcom/fasterxml/jackson/databind/SerializerProvider;Lcom/fasterxml/jackson/databind/JsonSerializer;)V
  #120 = Utf8               jgen
  #121 = Utf8               ser
  #122 = Utf8               typeSer
  #123 = Class              #186          // com/fasterxml/jackson/databind/jsontype/TypeSerializer
  #124 = Utf8               (Ljava/util/List<*>;Lcom/fasterxml/jackson/core/JsonGenerator;Lcom/fasterxml/jackson/databind/SerializerProvider;Lcom/fasterxml/jackson/databind/JsonSerializer<Ljava/lang/Object;>;)V
  #125 = Utf8               serializeTypedContents
  #126 = Utf8               (Ljava/lang/Object;Lcom/fasterxml/jackson/core/JsonGenerator;Lcom/fasterxml/jackson/databind/SerializerProvider;)V
  #127 = Utf8               (Lcom/fasterxml/jackson/databind/BeanProperty;Lcom/fasterxml/jackson/databind/jsontype/TypeSerializer;Lcom/fasterxml/jackson/databind/JsonSerializer;Ljava/lang/Boolean;)Lcom/fasterxml/jackson/databind/ser/std/AsArraySerializerBase;
  #128 = Utf8               (Ljava/lang/Object;)Z
  #129 = Utf8               (Lcom/fasterxml/jackson/databind/SerializerProvider;Ljava/lang/Object;)Z
  #130 = Utf8               Lcom/fasterxml/jackson/databind/ser/std/AsArraySerializerBase<Ljava/util/List<*>;>;
  #131 = Utf8               SourceFile
  #132 = Utf8               IndexedListSerializer.java
  #133 = Utf8               RuntimeVisibleAnnotations
  #134 = Utf8               Lcom/fasterxml/jackson/databind/annotation/JacksonStdImpl;
  #135 = Utf8               java/util/List
  #136 = NameAndType        #44:#187      // "<init>":(Ljava/lang/Class;Lcom/fasterxml/jackson/databind/JavaType;ZLcom/fasterxml/jackson/databind/jsontype/TypeSerializer;Lcom/fasterxml/jackson/databind/JsonSerializer;)V
  #137 = NameAndType        #44:#188      // "<init>":(Lcom/fasterxml/jackson/databind/ser/std/AsArraySerializerBase;Lcom/fasterxml/jackson/databind/BeanProperty;Lcom/fasterxml/jackson/databind/jsontype/TypeSerializer;Lcom/fasterxml/jackson/databind/JsonSerializer;Ljava/lang/Boolean;)V
  #138 = Utf8               com/fasterxml/jackson/databind/ser/impl/IndexedListSerializer
  #139 = NameAndType        #44:#63       // "<init>":(Lcom/fasterxml/jackson/databind/ser/impl/IndexedListSerializer;Lcom/fasterxml/jackson/databind/BeanProperty;Lcom/fasterxml/jackson/databind/jsontype/TypeSerializer;Lcom/fasterxml/jackson/databind/JsonSerializer;Ljava/lang/Boolean;)V
  #140 = NameAndType        #75:#189      // isEmpty:()Z
  #141 = NameAndType        #190:#191     // size:()I
  #142 = NameAndType        #192:#66      // _property:Lcom/fasterxml/jackson/databind/BeanProperty;
  #143 = NameAndType        #193:#58      // _elementSerializer:Lcom/fasterxml/jackson/databind/JsonSerializer;
  #144 = NameAndType        #194:#68      // _unwrapSingle:Ljava/lang/Boolean;
  #145 = Class              #195          // com/fasterxml/jackson/databind/SerializationFeature
  #146 = NameAndType        #196:#197     // WRITE_SINGLE_ELEM_ARRAYS_UNWRAPPED:Lcom/fasterxml/jackson/databind/SerializationFeature;
  #147 = Class              #198          // com/fasterxml/jackson/databind/SerializerProvider
  #148 = NameAndType        #199:#200     // isEnabled:(Lcom/fasterxml/jackson/databind/SerializationFeature;)Z
  #149 = Class              #201          // java/lang/Boolean
  #150 = NameAndType        #202:#68      // TRUE:Ljava/lang/Boolean;
  #151 = NameAndType        #100:#91      // serializeContents:(Ljava/util/List;Lcom/fasterxml/jackson/core/JsonGenerator;Lcom/fasterxml/jackson/databind/SerializerProvider;)V
  #152 = Class              #203          // com/fasterxml/jackson/core/JsonGenerator
  #153 = NameAndType        #204:#205     // writeStartArray:(Ljava/lang/Object;I)V
  #154 = NameAndType        #206:#207     // writeEndArray:()V
  #155 = NameAndType        #118:#119     // serializeContentsUsing:(Ljava/util/List;Lcom/fasterxml/jackson/core/JsonGenerator;Lcom/fasterxml/jackson/databind/SerializerProvider;Lcom/fasterxml/jackson/databind/JsonSerializer;)V
  #156 = NameAndType        #208:#56      // _valueTypeSerializer:Lcom/fasterxml/jackson/databind/jsontype/TypeSerializer;
  #157 = NameAndType        #125:#91      // serializeTypedContents:(Ljava/util/List;Lcom/fasterxml/jackson/core/JsonGenerator;Lcom/fasterxml/jackson/databind/SerializerProvider;)V
  #158 = NameAndType        #209:#107     // _dynamicSerializers:Lcom/fasterxml/jackson/databind/ser/impl/PropertySerializerMap;
  #159 = NameAndType        #210:#211     // get:(I)Ljava/lang/Object;
  #160 = NameAndType        #212:#213     // defaultSerializeNull:(Lcom/fasterxml/jackson/core/JsonGenerator;)V
  #161 = Class              #183          // java/lang/Object
  #162 = NameAndType        #214:#215     // getClass:()Ljava/lang/Class;
  #163 = Class              #182          // com/fasterxml/jackson/databind/ser/impl/PropertySerializerMap
  #164 = NameAndType        #216:#217     // serializerFor:(Ljava/lang/Class;)Lcom/fasterxml/jackson/databind/JsonSerializer;
  #165 = NameAndType        #218:#52      // _elementType:Lcom/fasterxml/jackson/databind/JavaType;
  #166 = Class              #219          // com/fasterxml/jackson/databind/JavaType
  #167 = NameAndType        #220:#189     // hasGenericTypes:()Z
  #168 = NameAndType        #221:#222     // constructSpecializedType:(Lcom/fasterxml/jackson/databind/JavaType;Ljava/lang/Class;)Lcom/fasterxml/jackson/databind/JavaType;
  #169 = NameAndType        #223:#224     // _findAndAddDynamic:(Lcom/fasterxml/jackson/databind/ser/impl/PropertySerializerMap;Lcom/fasterxml/jackson/databind/JavaType;Lcom/fasterxml/jackson/databind/SerializerProvider;)Lcom/fasterxml/jackson/databind/JsonSerializer;
  #170 = NameAndType        #223:#225     // _findAndAddDynamic:(Lcom/fasterxml/jackson/databind/ser/impl/PropertySerializerMap;Ljava/lang/Class;Lcom/fasterxml/jackson/databind/SerializerProvider;)Lcom/fasterxml/jackson/databind/JsonSerializer;
  #171 = Class              #185          // com/fasterxml/jackson/databind/JsonSerializer
  #172 = NameAndType        #90:#126      // serialize:(Ljava/lang/Object;Lcom/fasterxml/jackson/core/JsonGenerator;Lcom/fasterxml/jackson/databind/SerializerProvider;)V
  #173 = Utf8               java/lang/Exception
  #174 = NameAndType        #226:#227     // wrapAndThrow:(Lcom/fasterxml/jackson/databind/SerializerProvider;Ljava/lang/Throwable;Ljava/lang/Object;I)V
  #175 = NameAndType        #228:#229     // serializeWithType:(Ljava/lang/Object;Lcom/fasterxml/jackson/core/JsonGenerator;Lcom/fasterxml/jackson/databind/SerializerProvider;Lcom/fasterxml/jackson/databind/jsontype/TypeSerializer;)V
  #176 = NameAndType        #90:#91       // serialize:(Ljava/util/List;Lcom/fasterxml/jackson/core/JsonGenerator;Lcom/fasterxml/jackson/databind/SerializerProvider;)V
  #177 = NameAndType        #71:#72       // withResolved:(Lcom/fasterxml/jackson/databind/BeanProperty;Lcom/fasterxml/jackson/databind/jsontype/TypeSerializer;Lcom/fasterxml/jackson/databind/JsonSerializer;Ljava/lang/Boolean;)Lcom/fasterxml/jackson/databind/ser/impl/IndexedListSerializer;
  #178 = NameAndType        #83:#84       // hasSingleElement:(Ljava/util/List;)Z
  #179 = NameAndType        #75:#76       // isEmpty:(Lcom/fasterxml/jackson/databind/SerializerProvider;Ljava/util/List;)Z
  #180 = Utf8               com/fasterxml/jackson/databind/ser/std/AsArraySerializerBase
  #181 = Utf8               java/io/IOException
  #182 = Utf8               com/fasterxml/jackson/databind/ser/impl/PropertySerializerMap
  #183 = Utf8               java/lang/Object
  #184 = Utf8               java/lang/Class
  #185 = Utf8               com/fasterxml/jackson/databind/JsonSerializer
  #186 = Utf8               com/fasterxml/jackson/databind/jsontype/TypeSerializer
  #187 = Utf8               (Ljava/lang/Class;Lcom/fasterxml/jackson/databind/JavaType;ZLcom/fasterxml/jackson/databind/jsontype/TypeSerializer;Lcom/fasterxml/jackson/databind/JsonSerializer;)V
  #188 = Utf8               (Lcom/fasterxml/jackson/databind/ser/std/AsArraySerializerBase;Lcom/fasterxml/jackson/databind/BeanProperty;Lcom/fasterxml/jackson/databind/jsontype/TypeSerializer;Lcom/fasterxml/jackson/databind/JsonSerializer;Ljava/lang/Boolean;)V
  #189 = Utf8               ()Z
  #190 = Utf8               size
  #191 = Utf8               ()I
  #192 = Utf8               _property
  #193 = Utf8               _elementSerializer
  #194 = Utf8               _unwrapSingle
  #195 = Utf8               com/fasterxml/jackson/databind/SerializationFeature
  #196 = Utf8               WRITE_SINGLE_ELEM_ARRAYS_UNWRAPPED
  #197 = Utf8               Lcom/fasterxml/jackson/databind/SerializationFeature;
  #198 = Utf8               com/fasterxml/jackson/databind/SerializerProvider
  #199 = Utf8               isEnabled
  #200 = Utf8               (Lcom/fasterxml/jackson/databind/SerializationFeature;)Z
  #201 = Utf8               java/lang/Boolean
  #202 = Utf8               TRUE
  #203 = Utf8               com/fasterxml/jackson/core/JsonGenerator
  #204 = Utf8               writeStartArray
  #205 = Utf8               (Ljava/lang/Object;I)V
  #206 = Utf8               writeEndArray
  #207 = Utf8               ()V
  #208 = Utf8               _valueTypeSerializer
  #209 = Utf8               _dynamicSerializers
  #210 = Utf8               get
  #211 = Utf8               (I)Ljava/lang/Object;
  #212 = Utf8               defaultSerializeNull
  #213 = Utf8               (Lcom/fasterxml/jackson/core/JsonGenerator;)V
  #214 = Utf8               getClass
  #215 = Utf8               ()Ljava/lang/Class;
  #216 = Utf8               serializerFor
  #217 = Utf8               (Ljava/lang/Class;)Lcom/fasterxml/jackson/databind/JsonSerializer;
  #218 = Utf8               _elementType
  #219 = Utf8               com/fasterxml/jackson/databind/JavaType
  #220 = Utf8               hasGenericTypes
  #221 = Utf8               constructSpecializedType
  #222 = Utf8               (Lcom/fasterxml/jackson/databind/JavaType;Ljava/lang/Class;)Lcom/fasterxml/jackson/databind/JavaType;
  #223 = Utf8               _findAndAddDynamic
  #224 = Utf8               (Lcom/fasterxml/jackson/databind/ser/impl/PropertySerializerMap;Lcom/fasterxml/jackson/databind/JavaType;Lcom/fasterxml/jackson/databind/SerializerProvider;)Lcom/fasterxml/jackson/databind/JsonSerializer;
  #225 = Utf8               (Lcom/fasterxml/jackson/databind/ser/impl/PropertySerializerMap;Ljava/lang/Class;Lcom/fasterxml/jackson/databind/SerializerProvider;)Lcom/fasterxml/jackson/databind/JsonSerializer;
  #226 = Utf8               wrapAndThrow
  #227 = Utf8               (Lcom/fasterxml/jackson/databind/SerializerProvider;Ljava/lang/Throwable;Ljava/lang/Object;I)V
  #228 = Utf8               serializeWithType
  #229 = Utf8               (Ljava/lang/Object;Lcom/fasterxml/jackson/core/JsonGenerator;Lcom/fasterxml/jackson/databind/SerializerProvider;Lcom/fasterxml/jackson/databind/jsontype/TypeSerializer;)V
{
  private static final long serialVersionUID;
    descriptor: J
    flags: (0x001a) ACC_PRIVATE, ACC_STATIC, ACC_FINAL
    ConstantValue: long 1l

  public com.fasterxml.jackson.databind.ser.impl.IndexedListSerializer(com.fasterxml.jackson.databind.JavaType, boolean, com.fasterxml.jackson.databind.jsontype.TypeSerializer, com.fasterxml.jackson.databind.JsonSerializer<java.lang.Object>);
    descriptor: (Lcom/fasterxml/jackson/databind/JavaType;ZLcom/fasterxml/jackson/databind/jsontype/TypeSerializer;Lcom/fasterxml/jackson/databind/JsonSerializer;)V
    flags: (0x0001) ACC_PUBLIC
    Code:
      stack=6, locals=5, args_size=5
         0: aload_0
         1: ldc           #1                  // class java/util/List
         3: aload_1
         4: iload_2
         5: aload_3
         6: aload         4
         8: invokespecial #2                  // Method com/fasterxml/jackson/databind/ser/std/AsArraySerializerBase."<init>":(Ljava/lang/Class;Lcom/fasterxml/jackson/databind/JavaType;ZLcom/fasterxml/jackson/databind/jsontype/TypeSerializer;Lcom/fasterxml/jackson/databind/JsonSerializer;)V
        11: return
      LineNumberTable:
        line 27: 0
        line 28: 11
      LocalVariableTable:
        Start  Length  Slot  Name   Signature
            0      12     0  this   Lcom/fasterxml/jackson/databind/ser/impl/IndexedListSerializer;
            0      12     1 elemType   Lcom/fasterxml/jackson/databind/JavaType;
            0      12     2 staticTyping   Z
            0      12     3   vts   Lcom/fasterxml/jackson/databind/jsontype/TypeSerializer;
            0      12     4 valueSerializer   Lcom/fasterxml/jackson/databind/JsonSerializer;
      LocalVariableTypeTable:
        Start  Length  Slot  Name   Signature
            0      12     4 valueSerializer   Lcom/fasterxml/jackson/databind/JsonSerializer<Ljava/lang/Object;>;
    Signature: #62                          // (Lcom/fasterxml/jackson/databind/JavaType;ZLcom/fasterxml/jackson/databind/jsontype/TypeSerializer;Lcom/fasterxml/jackson/databind/JsonSerializer<Ljava/lang/Object;>;)V

  public com.fasterxml.jackson.databind.ser.impl.IndexedListSerializer(com.fasterxml.jackson.databind.ser.impl.IndexedListSerializer, com.fasterxml.jackson.databind.BeanProperty, com.fasterxml.jackson.databind.jsontype.TypeSerializer, com.fasterxml.jackson.databind.JsonSerializer<?>, java.lang.Boolean);
    descriptor: (Lcom/fasterxml/jackson/databind/ser/impl/IndexedListSerializer;Lcom/fasterxml/jackson/databind/BeanProperty;Lcom/fasterxml/jackson/databind/jsontype/TypeSerializer;Lcom/fasterxml/jackson/databind/JsonSerializer;Ljava/lang/Boolean;)V
    flags: (0x0001) ACC_PUBLIC
    Code:
      stack=6, locals=6, args_size=6
         0: aload_0
         1: aload_1
         2: aload_2
         3: aload_3
         4: aload         4
         6: aload         5
         8: invokespecial #3                  // Method com/fasterxml/jackson/databind/ser/std/AsArraySerializerBase."<init>":(Lcom/fasterxml/jackson/databind/ser/std/AsArraySerializerBase;Lcom/fasterxml/jackson/databind/BeanProperty;Lcom/fasterxml/jackson/databind/jsontype/TypeSerializer;Lcom/fasterxml/jackson/databind/JsonSerializer;Ljava/lang/Boolean;)V
        11: return
      LineNumberTable:
        line 33: 0
        line 34: 11
      LocalVariableTable:
        Start  Length  Slot  Name   Signature
            0      12     0  this   Lcom/fasterxml/jackson/databind/ser/impl/IndexedListSerializer;
            0      12     1   src   Lcom/fasterxml/jackson/databind/ser/impl/IndexedListSerializer;
            0      12     2 property   Lcom/fasterxml/jackson/databind/BeanProperty;
            0      12     3   vts   Lcom/fasterxml/jackson/databind/jsontype/TypeSerializer;
            0      12     4 valueSerializer   Lcom/fasterxml/jackson/databind/JsonSerializer;
            0      12     5 unwrapSingle   Ljava/lang/Boolean;
      LocalVariableTypeTable:
        Start  Length  Slot  Name   Signature
            0      12     4 valueSerializer   Lcom/fasterxml/jackson/databind/JsonSerializer<*>;
    Signature: #70                          // (Lcom/fasterxml/jackson/databind/ser/impl/IndexedListSerializer;Lcom/fasterxml/jackson/databind/BeanProperty;Lcom/fasterxml/jackson/databind/jsontype/TypeSerializer;Lcom/fasterxml/jackson/databind/JsonSerializer<*>;Ljava/lang/Boolean;)V

  public com.fasterxml.jackson.databind.ser.impl.IndexedListSerializer withResolved(com.fasterxml.jackson.databind.BeanProperty, com.fasterxml.jackson.databind.jsontype.TypeSerializer, com.fasterxml.jackson.databind.JsonSerializer<?>, java.lang.Boolean);
    descriptor: (Lcom/fasterxml/jackson/databind/BeanProperty;Lcom/fasterxml/jackson/databind/jsontype/TypeSerializer;Lcom/fasterxml/jackson/databind/JsonSerializer;Ljava/lang/Boolean;)Lcom/fasterxml/jackson/databind/ser/impl/IndexedListSerializer;
    flags: (0x0001) ACC_PUBLIC
    Code:
      stack=7, locals=5, args_size=5
         0: new           #4                  // class com/fasterxml/jackson/databind/ser/impl/IndexedListSerializer
         3: dup
         4: aload_0
         5: aload_1
         6: aload_2
         7: aload_3
         8: aload         4
        10: invokespecial #5                  // Method "<init>":(Lcom/fasterxml/jackson/databind/ser/impl/IndexedListSerializer;Lcom/fasterxml/jackson/databind/BeanProperty;Lcom/fasterxml/jackson/databind/jsontype/TypeSerializer;Lcom/fasterxml/jackson/databind/JsonSerializer;Ljava/lang/Boolean;)V
        13: areturn
      LineNumberTable:
        line 40: 0
      LocalVariableTable:
        Start  Length  Slot  Name   Signature
            0      14     0  this   Lcom/fasterxml/jackson/databind/ser/impl/IndexedListSerializer;
            0      14     1 property   Lcom/fasterxml/jackson/databind/BeanProperty;
            0      14     2   vts   Lcom/fasterxml/jackson/databind/jsontype/TypeSerializer;
            0      14     3 elementSerializer   Lcom/fasterxml/jackson/databind/JsonSerializer;
            0      14     4 unwrapSingle   Ljava/lang/Boolean;
      LocalVariableTypeTable:
        Start  Length  Slot  Name   Signature
            0      14     3 elementSerializer   Lcom/fasterxml/jackson/databind/JsonSerializer<*>;
    Signature: #74                          // (Lcom/fasterxml/jackson/databind/BeanProperty;Lcom/fasterxml/jackson/databind/jsontype/TypeSerializer;Lcom/fasterxml/jackson/databind/JsonSerializer<*>;Ljava/lang/Boolean;)Lcom/fasterxml/jackson/databind/ser/impl/IndexedListSerializer;

  public boolean isEmpty(com.fasterxml.jackson.databind.SerializerProvider, java.util.List<?>);
    descriptor: (Lcom/fasterxml/jackson/databind/SerializerProvider;Ljava/util/List;)Z
    flags: (0x0001) ACC_PUBLIC
    Code:
      stack=1, locals=3, args_size=3
         0: aload_2
         1: invokeinterface #6,  1            // InterfaceMethod java/util/List.isEmpty:()Z
         6: ireturn
      LineNumberTable:
        line 51: 0
      LocalVariableTable:
        Start  Length  Slot  Name   Signature
            0       7     0  this   Lcom/fasterxml/jackson/databind/ser/impl/IndexedListSerializer;
            0       7     1  prov   Lcom/fasterxml/jackson/databind/SerializerProvider;
            0       7     2 value   Ljava/util/List;
      LocalVariableTypeTable:
        Start  Length  Slot  Name   Signature
            0       7     2 value   Ljava/util/List<*>;
    Signature: #82                          // (Lcom/fasterxml/jackson/databind/SerializerProvider;Ljava/util/List<*>;)Z

  public boolean hasSingleElement(java.util.List<?>);
    descriptor: (Ljava/util/List;)Z
    flags: (0x0001) ACC_PUBLIC
    Code:
      stack=2, locals=2, args_size=2
         0: aload_1
         1: invokeinterface #7,  1            // InterfaceMethod java/util/List.size:()I
         6: iconst_1
         7: if_icmpne     14
        10: iconst_1
        11: goto          15
        14: iconst_0
        15: ireturn
      LineNumberTable:
        line 56: 0
      LocalVariableTable:
        Start  Length  Slot  Name   Signature
            0      16     0  this   Lcom/fasterxml/jackson/databind/ser/impl/IndexedListSerializer;
            0      16     1 value   Ljava/util/List;
      LocalVariableTypeTable:
        Start  Length  Slot  Name   Signature
            0      16     1 value   Ljava/util/List<*>;
      StackMapTable: number_of_entries = 2
        frame_type = 14 /* same */
        frame_type = 64 /* same_locals_1_stack_item */
          stack = [ int ]
    Signature: #86                          // (Ljava/util/List<*>;)Z

  public com.fasterxml.jackson.databind.ser.ContainerSerializer<?> _withValueTypeSerializer(com.fasterxml.jackson.databind.jsontype.TypeSerializer);
    descriptor: (Lcom/fasterxml/jackson/databind/jsontype/TypeSerializer;)Lcom/fasterxml/jackson/databind/ser/ContainerSerializer;
    flags: (0x0001) ACC_PUBLIC
    Code:
      stack=7, locals=2, args_size=2
         0: new           #4                  // class com/fasterxml/jackson/databind/ser/impl/IndexedListSerializer
         3: dup
         4: aload_0
         5: aload_0
         6: getfield      #8                  // Field _property:Lcom/fasterxml/jackson/databind/BeanProperty;
         9: aload_1
        10: aload_0
        11: getfield      #9                  // Field _elementSerializer:Lcom/fasterxml/jackson/databind/JsonSerializer;
        14: aload_0
        15: getfield      #10                 // Field _unwrapSingle:Ljava/lang/Boolean;
        18: invokespecial #5                  // Method "<init>":(Lcom/fasterxml/jackson/databind/ser/impl/IndexedListSerializer;Lcom/fasterxml/jackson/databind/BeanProperty;Lcom/fasterxml/jackson/databind/jsontype/TypeSerializer;Lcom/fasterxml/jackson/databind/JsonSerializer;Ljava/lang/Boolean;)V
        21: areturn
      LineNumberTable:
        line 61: 0
      LocalVariableTable:
        Start  Length  Slot  Name   Signature
            0      22     0  this   Lcom/fasterxml/jackson/databind/ser/impl/IndexedListSerializer;
            0      22     1   vts   Lcom/fasterxml/jackson/databind/jsontype/TypeSerializer;
    Signature: #89                          // (Lcom/fasterxml/jackson/databind/jsontype/TypeSerializer;)Lcom/fasterxml/jackson/databind/ser/ContainerSerializer<*>;

  public final void serialize(java.util.List<?>, com.fasterxml.jackson.core.JsonGenerator, com.fasterxml.jackson.databind.SerializerProvider) throws java.io.IOException;
    descriptor: (Ljava/util/List;Lcom/fasterxml/jackson/core/JsonGenerator;Lcom/fasterxml/jackson/databind/SerializerProvider;)V
    flags: (0x0011) ACC_PUBLIC, ACC_FINAL
    Code:
      stack=4, locals=5, args_size=4
         0: aload_1
         1: invokeinterface #7,  1            // InterfaceMethod java/util/List.size:()I
         6: istore        4
         8: iload         4
        10: iconst_1
        11: if_icmpne     49
        14: aload_0
        15: getfield      #10                 // Field _unwrapSingle:Ljava/lang/Boolean;
        18: ifnonnull     31
        21: aload_3
        22: getstatic     #11                 // Field com/fasterxml/jackson/databind/SerializationFeature.WRITE_SINGLE_ELEM_ARRAYS_UNWRAPPED:Lcom/fasterxml/jackson/databind/SerializationFeature;
        25: invokevirtual #12                 // Method com/fasterxml/jackson/databind/SerializerProvider.isEnabled:(Lcom/fasterxml/jackson/databind/SerializationFeature;)Z
        28: ifne          41
        31: aload_0
        32: getfield      #10                 // Field _unwrapSingle:Ljava/lang/Boolean;
        35: getstatic     #13                 // Field java/lang/Boolean.TRUE:Ljava/lang/Boolean;
        38: if_acmpne     49
        41: aload_0
        42: aload_1
        43: aload_2
        44: aload_3
        45: invokevirtual #14                 // Method serializeContents:(Ljava/util/List;Lcom/fasterxml/jackson/core/JsonGenerator;Lcom/fasterxml/jackson/databind/SerializerProvider;)V
        48: return
        49: aload_2
        50: aload_1
        51: iload         4
        53: invokevirtual #15                 // Method com/fasterxml/jackson/core/JsonGenerator.writeStartArray:(Ljava/lang/Object;I)V
        56: aload_0
        57: aload_1
        58: aload_2
        59: aload_3
        60: invokevirtual #14                 // Method serializeContents:(Ljava/util/List;Lcom/fasterxml/jackson/core/JsonGenerator;Lcom/fasterxml/jackson/databind/SerializerProvider;)V
        63: aload_2
        64: invokevirtual #16                 // Method com/fasterxml/jackson/core/JsonGenerator.writeEndArray:()V
        67: return
      LineNumberTable:
        line 69: 0
        line 70: 8
        line 71: 14
        line 72: 25
        line 74: 41
        line 75: 48
        line 78: 49
        line 79: 56
        line 80: 63
        line 81: 67
      LocalVariableTable:
        Start  Length  Slot  Name   Signature
            0      68     0  this   Lcom/fasterxml/jackson/databind/ser/impl/IndexedListSerializer;
            0      68     1 value   Ljava/util/List;
            0      68     2   gen   Lcom/fasterxml/jackson/core/JsonGenerator;
            0      68     3 provider   Lcom/fasterxml/jackson/databind/SerializerProvider;
            8      60     4   len   I
      LocalVariableTypeTable:
        Start  Length  Slot  Name   Signature
            0      68     1 value   Ljava/util/List<*>;
      StackMapTable: number_of_entries = 3
        frame_type = 252 /* append */
          offset_delta = 31
          locals = [ int ]
        frame_type = 9 /* same */
        frame_type = 7 /* same */
    Exceptions:
      throws java.io.IOException
    Signature: #99                          // (Ljava/util/List<*>;Lcom/fasterxml/jackson/core/JsonGenerator;Lcom/fasterxml/jackson/databind/SerializerProvider;)V

  public void serializeContents(java.util.List<?>, com.fasterxml.jackson.core.JsonGenerator, com.fasterxml.jackson.databind.SerializerProvider) throws java.io.IOException;
    descriptor: (Ljava/util/List;Lcom/fasterxml/jackson/core/JsonGenerator;Lcom/fasterxml/jackson/databind/SerializerProvider;)V
    flags: (0x0001) ACC_PUBLIC
    Code:
      stack=5, locals=10, args_size=4
         0: aload_0
         1: getfield      #9                  // Field _elementSerializer:Lcom/fasterxml/jackson/databind/JsonSerializer;
         4: ifnull        19
         7: aload_0
         8: aload_1
         9: aload_2
        10: aload_3
        11: aload_0
        12: getfield      #9                  // Field _elementSerializer:Lcom/fasterxml/jackson/databind/JsonSerializer;
        15: invokevirtual #17                 // Method serializeContentsUsing:(Ljava/util/List;Lcom/fasterxml/jackson/core/JsonGenerator;Lcom/fasterxml/jackson/databind/SerializerProvider;Lcom/fasterxml/jackson/databind/JsonSerializer;)V
        18: return
        19: aload_0
        20: getfield      #18                 // Field _valueTypeSerializer:Lcom/fasterxml/jackson/databind/jsontype/TypeSerializer;
        23: ifnull        34
        26: aload_0
        27: aload_1
        28: aload_2
        29: aload_3
        30: invokevirtual #19                 // Method serializeTypedContents:(Ljava/util/List;Lcom/fasterxml/jackson/core/JsonGenerator;Lcom/fasterxml/jackson/databind/SerializerProvider;)V
        33: return
        34: aload_1
        35: invokeinterface #7,  1            // InterfaceMethod java/util/List.size:()I
        40: istore        4
        42: iload         4
        44: ifne          48
        47: return
        48: iconst_0
        49: istore        5
        51: aload_0
        52: getfield      #20                 // Field _dynamicSerializers:Lcom/fasterxml/jackson/databind/ser/impl/PropertySerializerMap;
        55: astore        6
        57: iload         5
        59: iload         4
        61: if_icmpge     172
        64: aload_1
        65: iload         5
        67: invokeinterface #21,  2           // InterfaceMethod java/util/List.get:(I)Ljava/lang/Object;
        72: astore        7
        74: aload         7
        76: ifnonnull     87
        79: aload_3
        80: aload_2
        81: invokevirtual #22                 // Method com/fasterxml/jackson/databind/SerializerProvider.defaultSerializeNull:(Lcom/fasterxml/jackson/core/JsonGenerator;)V
        84: goto          166
        87: aload         7
        89: invokevirtual #23                 // Method java/lang/Object.getClass:()Ljava/lang/Class;
        92: astore        8
        94: aload         6
        96: aload         8
        98: invokevirtual #24                 // Method com/fasterxml/jackson/databind/ser/impl/PropertySerializerMap.serializerFor:(Ljava/lang/Class;)Lcom/fasterxml/jackson/databind/JsonSerializer;
       101: astore        9
       103: aload         9
       105: ifnonnull     157
       108: aload_0
       109: getfield      #25                 // Field _elementType:Lcom/fasterxml/jackson/databind/JavaType;
       112: invokevirtual #26                 // Method com/fasterxml/jackson/databind/JavaType.hasGenericTypes:()Z
       115: ifeq          140
       118: aload_0
       119: aload         6
       121: aload_3
       122: aload_0
       123: getfield      #25                 // Field _elementType:Lcom/fasterxml/jackson/databind/JavaType;
       126: aload         8
       128: invokevirtual #27                 // Method com/fasterxml/jackson/databind/SerializerProvider.constructSpecializedType:(Lcom/fasterxml/jackson/databind/JavaType;Ljava/lang/Class;)Lcom/fasterxml/jackson/databind/JavaType;
       131: aload_3
       132: invokevirtual #28                 // Method _findAndAddDynamic:(Lcom/fasterxml/jackson/databind/ser/impl/PropertySerializerMap;Lcom/fasterxml/jackson/databind/JavaType;Lcom/fasterxml/jackson/databind/SerializerProvider;)Lcom/fasterxml/jackson/databind/JsonSerializer;
       135: astore        9
       137: goto          151
       140: aload_0
       141: aload         6
       143: aload         8
       145: aload_3
       146: invokevirtual #29                 // Method _findAndAddDynamic:(Lcom/fasterxml/jackson/databind/ser/impl/PropertySerializerMap;Ljava/lang/Class;Lcom/fasterxml/jackson/databind/SerializerProvider;)Lcom/fasterxml/jackson/databind/JsonSerializer;
       149: astore        9
       151: aload_0
       152: getfield      #20                 // Field _dynamicSerializers:Lcom/fasterxml/jackson/databind/ser/impl/PropertySerializerMap;
       155: astore        6
       157: aload         9
       159: aload         7
       161: aload_2
       162: aload_3
       163: invokevirtual #30                 // Method com/fasterxml/jackson/databind/JsonSerializer.serialize:(Ljava/lang/Object;Lcom/fasterxml/jackson/core/JsonGenerator;Lcom/fasterxml/jackson/databind/SerializerProvider;)V
       166: iinc          5, 1
       169: goto          57
       172: goto          187
       175: astore        6
       177: aload_0
       178: aload_3
       179: aload         6
       181: aload_1
       182: iload         5
       184: invokevirtual #32                 // Method wrapAndThrow:(Lcom/fasterxml/jackson/databind/SerializerProvider;Ljava/lang/Throwable;Ljava/lang/Object;I)V
       187: return
      Exception table:
         from    to  target type
            51   172   175   Class java/lang/Exception
      LineNumberTable:
        line 87: 0
        line 88: 7
        line 89: 18
        line 91: 19
        line 92: 26
        line 93: 33
        line 95: 34
        line 96: 42
        line 97: 47
        line 99: 48
        line 101: 51
        line 102: 57
        line 103: 64
        line 104: 74
        line 105: 79
        line 107: 87
        line 108: 94
        line 109: 103
        line 111: 108
        line 112: 118
        line 113: 128
        line 112: 132
        line 115: 140
        line 117: 151
        line 119: 157
        line 102: 166
        line 124: 172
        line 122: 175
        line 123: 177
        line 125: 187
      LocalVariableTable:
        Start  Length  Slot  Name   Signature
           94      72     8    cc   Ljava/lang/Class;
          103      63     9 serializer   Lcom/fasterxml/jackson/databind/JsonSerializer;
           74      92     7  elem   Ljava/lang/Object;
           57     115     6 serializers   Lcom/fasterxml/jackson/databind/ser/impl/PropertySerializerMap;
          177      10     6     e   Ljava/lang/Exception;
            0     188     0  this   Lcom/fasterxml/jackson/databind/ser/impl/IndexedListSerializer;
            0     188     1 value   Ljava/util/List;
            0     188     2     g   Lcom/fasterxml/jackson/core/JsonGenerator;
            0     188     3 provider   Lcom/fasterxml/jackson/databind/SerializerProvider;
           42     146     4   len   I
           51     137     5     i   I
      LocalVariableTypeTable:
        Start  Length  Slot  Name   Signature
           94      72     8    cc   Ljava/lang/Class<*>;
          103      63     9 serializer   Lcom/fasterxml/jackson/databind/JsonSerializer<Ljava/lang/Object;>;
            0     188     1 value   Ljava/util/List<*>;
      StackMapTable: number_of_entries = 12
        frame_type = 19 /* same */
        frame_type = 14 /* same */
        frame_type = 252 /* append */
          offset_delta = 13
          locals = [ int ]
        frame_type = 253 /* append */
          offset_delta = 8
          locals = [ int, class com/fasterxml/jackson/databind/ser/impl/PropertySerializerMap ]
        frame_type = 252 /* append */
          offset_delta = 29
          locals = [ class java/lang/Object ]
        frame_type = 253 /* append */
          offset_delta = 52
          locals = [ class java/lang/Class, class com/fasterxml/jackson/databind/JsonSerializer ]
        frame_type = 10 /* same */
        frame_type = 5 /* same */
        frame_type = 248 /* chop */
          offset_delta = 8
        frame_type = 250 /* chop */
          offset_delta = 5
        frame_type = 66 /* same_locals_1_stack_item */
          stack = [ class java/lang/Exception ]
        frame_type = 11 /* same */
    Exceptions:
      throws java.io.IOException
    Signature: #99                          // (Ljava/util/List<*>;Lcom/fasterxml/jackson/core/JsonGenerator;Lcom/fasterxml/jackson/databind/SerializerProvider;)V

  public void serializeContentsUsing(java.util.List<?>, com.fasterxml.jackson.core.JsonGenerator, com.fasterxml.jackson.databind.SerializerProvider, com.fasterxml.jackson.databind.JsonSerializer<java.lang.Object>) throws java.io.IOException;
    descriptor: (Ljava/util/List;Lcom/fasterxml/jackson/core/JsonGenerator;Lcom/fasterxml/jackson/databind/SerializerProvider;Lcom/fasterxml/jackson/databind/JsonSerializer;)V
    flags: (0x0001) ACC_PUBLIC
    Code:
      stack=5, locals=10, args_size=5
         0: aload_1
         1: invokeinterface #7,  1            // InterfaceMethod java/util/List.size:()I
         6: istore        5
         8: iload         5
        10: ifne          14
        13: return
        14: aload_0
        15: getfield      #18                 // Field _valueTypeSerializer:Lcom/fasterxml/jackson/databind/jsontype/TypeSerializer;
        18: astore        6
        20: iconst_0
        21: istore        7
        23: iload         7
        25: iload         5
        27: if_icmpge     102
        30: aload_1
        31: iload         7
        33: invokeinterface #21,  2           // InterfaceMethod java/util/List.get:(I)Ljava/lang/Object;
        38: astore        8
        40: aload         8
        42: ifnonnull     53
        45: aload_3
        46: aload_2
        47: invokevirtual #22                 // Method com/fasterxml/jackson/databind/SerializerProvider.defaultSerializeNull:(Lcom/fasterxml/jackson/core/JsonGenerator;)V
        50: goto          81
        53: aload         6
        55: ifnonnull     70
        58: aload         4
        60: aload         8
        62: aload_2
        63: aload_3
        64: invokevirtual #30                 // Method com/fasterxml/jackson/databind/JsonSerializer.serialize:(Ljava/lang/Object;Lcom/fasterxml/jackson/core/JsonGenerator;Lcom/fasterxml/jackson/databind/SerializerProvider;)V
        67: goto          81
        70: aload         4
        72: aload         8
        74: aload_2
        75: aload_3
        76: aload         6
        78: invokevirtual #33                 // Method com/fasterxml/jackson/databind/JsonSerializer.serializeWithType:(Ljava/lang/Object;Lcom/fasterxml/jackson/core/JsonGenerator;Lcom/fasterxml/jackson/databind/SerializerProvider;Lcom/fasterxml/jackson/databind/jsontype/TypeSerializer;)V
        81: goto          96
        84: astore        9
        86: aload_0
        87: aload_3
        88: aload         9
        90: aload_1
        91: iload         7
        93: invokevirtual #32                 // Method wrapAndThrow:(Lcom/fasterxml/jackson/databind/SerializerProvider;Ljava/lang/Throwable;Ljava/lang/Object;I)V
        96: iinc          7, 1
        99: goto          23
       102: return
      Exception table:
         from    to  target type
            40    81    84   Class java/lang/Exception
      LineNumberTable:
        line 131: 0
        line 132: 8
        line 133: 13
        line 135: 14
        line 136: 20
        line 137: 30
        line 139: 40
        line 140: 45
        line 141: 53
        line 142: 58
        line 144: 70
        line 149: 81
        line 146: 84
        line 148: 86
        line 136: 96
        line 151: 102
      LocalVariableTable:
        Start  Length  Slot  Name   Signature
           86      10     9     e   Ljava/lang/Exception;
           40      56     8  elem   Ljava/lang/Object;
           23      79     7     i   I
            0     103     0  this   Lcom/fasterxml/jackson/databind/ser/impl/IndexedListSerializer;
            0     103     1 value   Ljava/util/List;
            0     103     2  jgen   Lcom/fasterxml/jackson/core/JsonGenerator;
            0     103     3 provider   Lcom/fasterxml/jackson/databind/SerializerProvider;
            0     103     4   ser   Lcom/fasterxml/jackson/databind/JsonSerializer;
            8      95     5   len   I
           20      83     6 typeSer   Lcom/fasterxml/jackson/databind/jsontype/TypeSerializer;
      LocalVariableTypeTable:
        Start  Length  Slot  Name   Signature
            0     103     1 value   Ljava/util/List<*>;
            0     103     4   ser   Lcom/fasterxml/jackson/databind/JsonSerializer<Ljava/lang/Object;>;
      StackMapTable: number_of_entries = 8
        frame_type = 252 /* append */
          offset_delta = 14
          locals = [ int ]
        frame_type = 253 /* append */
          offset_delta = 8
          locals = [ class com/fasterxml/jackson/databind/jsontype/TypeSerializer, int ]
        frame_type = 252 /* append */
          offset_delta = 29
          locals = [ class java/lang/Object ]
        frame_type = 16 /* same */
        frame_type = 10 /* same */
        frame_type = 66 /* same_locals_1_stack_item */
          stack = [ class java/lang/Exception ]
        frame_type = 250 /* chop */
          offset_delta = 11
        frame_type = 250 /* chop */
          offset_delta = 5
    Exceptions:
      throws java.io.IOException
    Signature: #124                         // (Ljava/util/List<*>;Lcom/fasterxml/jackson/core/JsonGenerator;Lcom/fasterxml/jackson/databind/SerializerProvider;Lcom/fasterxml/jackson/databind/JsonSerializer<Ljava/lang/Object;>;)V

  public void serializeTypedContents(java.util.List<?>, com.fasterxml.jackson.core.JsonGenerator, com.fasterxml.jackson.databind.SerializerProvider) throws java.io.IOException;
    descriptor: (Ljava/util/List;Lcom/fasterxml/jackson/core/JsonGenerator;Lcom/fasterxml/jackson/databind/SerializerProvider;)V
    flags: (0x0001) ACC_PUBLIC
    Code:
      stack=5, locals=11, args_size=4
         0: aload_1
         1: invokeinterface #7,  1            // InterfaceMethod java/util/List.size:()I
         6: istore        4
         8: iload         4
        10: ifne          14
        13: return
        14: iconst_0
        15: istore        5
        17: aload_0
        18: getfield      #18                 // Field _valueTypeSerializer:Lcom/fasterxml/jackson/databind/jsontype/TypeSerializer;
        21: astore        6
        23: aload_0
        24: getfield      #20                 // Field _dynamicSerializers:Lcom/fasterxml/jackson/databind/ser/impl/PropertySerializerMap;
        27: astore        7
        29: iload         5
        31: iload         4
        33: if_icmpge     146
        36: aload_1
        37: iload         5
        39: invokeinterface #21,  2           // InterfaceMethod java/util/List.get:(I)Ljava/lang/Object;
        44: astore        8
        46: aload         8
        48: ifnonnull     59
        51: aload_3
        52: aload_2
        53: invokevirtual #22                 // Method com/fasterxml/jackson/databind/SerializerProvider.defaultSerializeNull:(Lcom/fasterxml/jackson/core/JsonGenerator;)V
        56: goto          140
        59: aload         8
        61: invokevirtual #23                 // Method java/lang/Object.getClass:()Ljava/lang/Class;
        64: astore        9
        66: aload         7
        68: aload         9
        70: invokevirtual #24                 // Method com/fasterxml/jackson/databind/ser/impl/PropertySerializerMap.serializerFor:(Ljava/lang/Class;)Lcom/fasterxml/jackson/databind/JsonSerializer;
        73: astore        10
        75: aload         10
        77: ifnonnull     129
        80: aload_0
        81: getfield      #25                 // Field _elementType:Lcom/fasterxml/jackson/databind/JavaType;
        84: invokevirtual #26                 // Method com/fasterxml/jackson/databind/JavaType.hasGenericTypes:()Z
        87: ifeq          112
        90: aload_0
        91: aload         7
        93: aload_3
        94: aload_0
        95: getfield      #25                 // Field _elementType:Lcom/fasterxml/jackson/databind/JavaType;
        98: aload         9
       100: invokevirtual #27                 // Method com/fasterxml/jackson/databind/SerializerProvider.constructSpecializedType:(Lcom/fasterxml/jackson/databind/JavaType;Ljava/lang/Class;)Lcom/fasterxml/jackson/databind/JavaType;
       103: aload_3
       104: invokevirtual #28                 // Method _findAndAddDynamic:(Lcom/fasterxml/jackson/databind/ser/impl/PropertySerializerMap;Lcom/fasterxml/jackson/databind/JavaType;Lcom/fasterxml/jackson/databind/SerializerProvider;)Lcom/fasterxml/jackson/databind/JsonSerializer;
       107: astore        10
       109: goto          123
       112: aload_0
       113: aload         7
       115: aload         9
       117: aload_3
       118: invokevirtual #29                 // Method _findAndAddDynamic:(Lcom/fasterxml/jackson/databind/ser/impl/PropertySerializerMap;Ljava/lang/Class;Lcom/fasterxml/jackson/databind/SerializerProvider;)Lcom/fasterxml/jackson/databind/JsonSerializer;
       121: astore        10
       123: aload_0
       124: getfield      #20                 // Field _dynamicSerializers:Lcom/fasterxml/jackson/databind/ser/impl/PropertySerializerMap;
       127: astore        7
       129: aload         10
       131: aload         8
       133: aload_2
       134: aload_3
       135: aload         6
       137: invokevirtual #33                 // Method com/fasterxml/jackson/databind/JsonSerializer.serializeWithType:(Ljava/lang/Object;Lcom/fasterxml/jackson/core/JsonGenerator;Lcom/fasterxml/jackson/databind/SerializerProvider;Lcom/fasterxml/jackson/databind/jsontype/TypeSerializer;)V
       140: iinc          5, 1
       143: goto          29
       146: goto          161
       149: astore        6
       151: aload_0
       152: aload_3
       153: aload         6
       155: aload_1
       156: iload         5
       158: invokevirtual #32                 // Method wrapAndThrow:(Lcom/fasterxml/jackson/databind/SerializerProvider;Ljava/lang/Throwable;Ljava/lang/Object;I)V
       161: return
      Exception table:
         from    to  target type
            17   146   149   Class java/lang/Exception
      LineNumberTable:
        line 156: 0
        line 157: 8
        line 158: 13
        line 160: 14
        line 162: 17
        line 163: 23
        line 164: 29
        line 165: 36
        line 166: 46
        line 167: 51
        line 169: 59
        line 170: 66
        line 171: 75
        line 173: 80
        line 174: 90
        line 175: 100
        line 174: 104
        line 177: 112
        line 179: 123
        line 181: 129
        line 164: 140
        line 186: 146
        line 184: 149
        line 185: 151
        line 187: 161
      LocalVariableTable:
        Start  Length  Slot  Name   Signature
           66      74     9    cc   Ljava/lang/Class;
           75      65    10 serializer   Lcom/fasterxml/jackson/databind/JsonSerializer;
           46      94     8  elem   Ljava/lang/Object;
           23     123     6 typeSer   Lcom/fasterxml/jackson/databind/jsontype/TypeSerializer;
           29     117     7 serializers   Lcom/fasterxml/jackson/databind/ser/impl/PropertySerializerMap;
          151      10     6     e   Ljava/lang/Exception;
            0     162     0  this   Lcom/fasterxml/jackson/databind/ser/impl/IndexedListSerializer;
            0     162     1 value   Ljava/util/List;
            0     162     2  jgen   Lcom/fasterxml/jackson/core/JsonGenerator;
            0     162     3 provider   Lcom/fasterxml/jackson/databind/SerializerProvider;
            8     154     4   len   I
           17     145     5     i   I
      LocalVariableTypeTable:
        Start  Length  Slot  Name   Signature
           66      74     9    cc   Ljava/lang/Class<*>;
           75      65    10 serializer   Lcom/fasterxml/jackson/databind/JsonSerializer<Ljava/lang/Object;>;
            0     162     1 value   Ljava/util/List<*>;
      StackMapTable: number_of_entries = 10
        frame_type = 252 /* append */
          offset_delta = 14
          locals = [ int ]
        frame_type = 254 /* append */
          offset_delta = 14
          locals = [ int, class com/fasterxml/jackson/databind/jsontype/TypeSerializer, class com/fasterxml/jackson/databind/ser/impl/PropertySerializerMap ]
        frame_type = 252 /* append */
          offset_delta = 29
          locals = [ class java/lang/Object ]
        frame_type = 253 /* append */
          offset_delta = 52
          locals = [ class java/lang/Class, class com/fasterxml/jackson/databind/JsonSerializer ]
        frame_type = 10 /* same */
        frame_type = 5 /* same */
        frame_type = 248 /* chop */
          offset_delta = 10
        frame_type = 249 /* chop */
          offset_delta = 5
        frame_type = 66 /* same_locals_1_stack_item */
          stack = [ class java/lang/Exception ]
        frame_type = 11 /* same */
    Exceptions:
      throws java.io.IOException
    Signature: #99                          // (Ljava/util/List<*>;Lcom/fasterxml/jackson/core/JsonGenerator;Lcom/fasterxml/jackson/databind/SerializerProvider;)V

  public void serializeContents(java.lang.Object, com.fasterxml.jackson.core.JsonGenerator, com.fasterxml.jackson.databind.SerializerProvider) throws java.io.IOException;
    descriptor: (Ljava/lang/Object;Lcom/fasterxml/jackson/core/JsonGenerator;Lcom/fasterxml/jackson/databind/SerializerProvider;)V
    flags: (0x1041) ACC_PUBLIC, ACC_BRIDGE, ACC_SYNTHETIC
    Code:
      stack=4, locals=4, args_size=4
         0: aload_0
         1: aload_1
         2: checkcast     #1                  // class java/util/List
         5: aload_2
         6: aload_3
         7: invokevirtual #14                 // Method serializeContents:(Ljava/util/List;Lcom/fasterxml/jackson/core/JsonGenerator;Lcom/fasterxml/jackson/databind/SerializerProvider;)V
        10: return
      LineNumberTable:
        line 18: 0
      LocalVariableTable:
        Start  Length  Slot  Name   Signature
            0      11     0  this   Lcom/fasterxml/jackson/databind/ser/impl/IndexedListSerializer;
    Exceptions:
      throws java.io.IOException

  public void serialize(java.lang.Object, com.fasterxml.jackson.core.JsonGenerator, com.fasterxml.jackson.databind.SerializerProvider) throws java.io.IOException;
    descriptor: (Ljava/lang/Object;Lcom/fasterxml/jackson/core/JsonGenerator;Lcom/fasterxml/jackson/databind/SerializerProvider;)V
    flags: (0x1041) ACC_PUBLIC, ACC_BRIDGE, ACC_SYNTHETIC
    Code:
      stack=4, locals=4, args_size=4
         0: aload_0
         1: aload_1
         2: checkcast     #1                  // class java/util/List
         5: aload_2
         6: aload_3
         7: invokevirtual #34                 // Method serialize:(Ljava/util/List;Lcom/fasterxml/jackson/core/JsonGenerator;Lcom/fasterxml/jackson/databind/SerializerProvider;)V
        10: return
      LineNumberTable:
        line 18: 0
      LocalVariableTable:
        Start  Length  Slot  Name   Signature
            0      11     0  this   Lcom/fasterxml/jackson/databind/ser/impl/IndexedListSerializer;
    Exceptions:
      throws java.io.IOException

  public com.fasterxml.jackson.databind.ser.std.AsArraySerializerBase withResolved(com.fasterxml.jackson.databind.BeanProperty, com.fasterxml.jackson.databind.jsontype.TypeSerializer, com.fasterxml.jackson.databind.JsonSerializer, java.lang.Boolean);
    descriptor: (Lcom/fasterxml/jackson/databind/BeanProperty;Lcom/fasterxml/jackson/databind/jsontype/TypeSerializer;Lcom/fasterxml/jackson/databind/JsonSerializer;Ljava/lang/Boolean;)Lcom/fasterxml/jackson/databind/ser/std/AsArraySerializerBase;
    flags: (0x1041) ACC_PUBLIC, ACC_BRIDGE, ACC_SYNTHETIC
    Code:
      stack=5, locals=5, args_size=5
         0: aload_0
         1: aload_1
         2: aload_2
         3: aload_3
         4: aload         4
         6: invokevirtual #35                 // Method withResolved:(Lcom/fasterxml/jackson/databind/BeanProperty;Lcom/fasterxml/jackson/databind/jsontype/TypeSerializer;Lcom/fasterxml/jackson/databind/JsonSerializer;Ljava/lang/Boolean;)Lcom/fasterxml/jackson/databind/ser/impl/IndexedListSerializer;
         9: areturn
      LineNumberTable:
        line 18: 0
      LocalVariableTable:
        Start  Length  Slot  Name   Signature
            0      10     0  this   Lcom/fasterxml/jackson/databind/ser/impl/IndexedListSerializer;

  public boolean hasSingleElement(java.lang.Object);
    descriptor: (Ljava/lang/Object;)Z
    flags: (0x1041) ACC_PUBLIC, ACC_BRIDGE, ACC_SYNTHETIC
    Code:
      stack=2, locals=2, args_size=2
         0: aload_0
         1: aload_1
         2: checkcast     #1                  // class java/util/List
         5: invokevirtual #36                 // Method hasSingleElement:(Ljava/util/List;)Z
         8: ireturn
      LineNumberTable:
        line 18: 0
      LocalVariableTable:
        Start  Length  Slot  Name   Signature
            0       9     0  this   Lcom/fasterxml/jackson/databind/ser/impl/IndexedListSerializer;

  public boolean isEmpty(com.fasterxml.jackson.databind.SerializerProvider, java.lang.Object);
    descriptor: (Lcom/fasterxml/jackson/databind/SerializerProvider;Ljava/lang/Object;)Z
    flags: (0x1041) ACC_PUBLIC, ACC_BRIDGE, ACC_SYNTHETIC
    Code:
      stack=3, locals=3, args_size=3
         0: aload_0
         1: aload_1
         2: aload_2
         3: checkcast     #1                  // class java/util/List
         6: invokevirtual #37                 // Method isEmpty:(Lcom/fasterxml/jackson/databind/SerializerProvider;Ljava/util/List;)Z
         9: ireturn
      LineNumberTable:
        line 18: 0
      LocalVariableTable:
        Start  Length  Slot  Name   Signature
            0      10     0  this   Lcom/fasterxml/jackson/databind/ser/impl/IndexedListSerializer;
}
Signature: #130                         // Lcom/fasterxml/jackson/databind/ser/std/AsArraySerializerBase<Ljava/util/List<*>;>;
SourceFile: "IndexedListSerializer.java"
RuntimeVisibleAnnotations:
  0: #134()
    com.fasterxml.jackson.databind.annotation.JacksonStdImpl
