Classfile /Users/mw/Projects/slang-braindump/.jar/jar11/assemble/slang-braindump/assemble/content/com/fasterxml/jackson/databind/ser/impl/SimpleBeanPropertyFilter$FilterExceptFilter.class
  Last modified May 29, 2022; size 1508 bytes
  SHA-256 checksum b6efecdc6068ce63e13d31be7ed11fdb33e4feba88e5214788aec1c61ac73526
  Compiled from "SimpleBeanPropertyFilter.java"
public class com.fasterxml.jackson.databind.ser.impl.SimpleBeanPropertyFilter$FilterExceptFilter extends com.fasterxml.jackson.databind.ser.impl.SimpleBeanPropertyFilter implements java.io.Serializable
  minor version: 0
  major version: 52
  flags: (0x0021) ACC_PUBLIC, ACC_SUPER
  this_class: #6                          // com/fasterxml/jackson/databind/ser/impl/SimpleBeanPropertyFilter$FilterExceptFilter
  super_class: #7                         // com/fasterxml/jackson/databind/ser/impl/SimpleBeanPropertyFilter
  interfaces: 1, fields: 2, methods: 3, attributes: 2
Constant pool:
   #1 = Methodref          #7.#38         // com/fasterxml/jackson/databind/ser/impl/SimpleBeanPropertyFilter."<init>":()V
   #2 = Fieldref           #6.#39         // com/fasterxml/jackson/databind/ser/impl/SimpleBeanPropertyFilter$FilterExceptFilter._propertiesToInclude:Ljava/util/Set;
   #3 = Methodref          #40.#41        // com/fasterxml/jackson/databind/ser/BeanPropertyWriter.getName:()Ljava/lang/String;
   #4 = InterfaceMethodref #42.#43        // java/util/Set.contains:(Ljava/lang/Object;)Z
   #5 = Methodref          #44.#41        // com/fasterxml/jackson/databind/ser/PropertyWriter.getName:()Ljava/lang/String;
   #6 = Class              #45            // com/fasterxml/jackson/databind/ser/impl/SimpleBeanPropertyFilter$FilterExceptFilter
   #7 = Class              #46            // com/fasterxml/jackson/databind/ser/impl/SimpleBeanPropertyFilter
   #8 = Class              #47            // java/io/Serializable
   #9 = Utf8               serialVersionUID
  #10 = Utf8               J
  #11 = Utf8               ConstantValue
  #12 = Long               1l
  #14 = Utf8               _propertiesToInclude
  #15 = Utf8               Ljava/util/Set;
  #16 = Utf8               Signature
  #17 = Utf8               Ljava/util/Set<Ljava/lang/String;>;
  #18 = Utf8               <init>
  #19 = Utf8               (Ljava/util/Set;)V
  #20 = Utf8               Code
  #21 = Utf8               LineNumberTable
  #22 = Utf8               LocalVariableTable
  #23 = Utf8               this
  #24 = Utf8               FilterExceptFilter
  #25 = Utf8               InnerClasses
  #26 = Utf8               Lcom/fasterxml/jackson/databind/ser/impl/SimpleBeanPropertyFilter$FilterExceptFilter;
  #27 = Utf8               properties
  #28 = Utf8               LocalVariableTypeTable
  #29 = Utf8               (Ljava/util/Set<Ljava/lang/String;>;)V
  #30 = Utf8               include
  #31 = Utf8               (Lcom/fasterxml/jackson/databind/ser/BeanPropertyWriter;)Z
  #32 = Utf8               writer
  #33 = Utf8               Lcom/fasterxml/jackson/databind/ser/BeanPropertyWriter;
  #34 = Utf8               (Lcom/fasterxml/jackson/databind/ser/PropertyWriter;)Z
  #35 = Utf8               Lcom/fasterxml/jackson/databind/ser/PropertyWriter;
  #36 = Utf8               SourceFile
  #37 = Utf8               SimpleBeanPropertyFilter.java
  #38 = NameAndType        #18:#48        // "<init>":()V
  #39 = NameAndType        #14:#15        // _propertiesToInclude:Ljava/util/Set;
  #40 = Class              #49            // com/fasterxml/jackson/databind/ser/BeanPropertyWriter
  #41 = NameAndType        #50:#51        // getName:()Ljava/lang/String;
  #42 = Class              #52            // java/util/Set
  #43 = NameAndType        #53:#54        // contains:(Ljava/lang/Object;)Z
  #44 = Class              #55            // com/fasterxml/jackson/databind/ser/PropertyWriter
  #45 = Utf8               com/fasterxml/jackson/databind/ser/impl/SimpleBeanPropertyFilter$FilterExceptFilter
  #46 = Utf8               com/fasterxml/jackson/databind/ser/impl/SimpleBeanPropertyFilter
  #47 = Utf8               java/io/Serializable
  #48 = Utf8               ()V
  #49 = Utf8               com/fasterxml/jackson/databind/ser/BeanPropertyWriter
  #50 = Utf8               getName
  #51 = Utf8               ()Ljava/lang/String;
  #52 = Utf8               java/util/Set
  #53 = Utf8               contains
  #54 = Utf8               (Ljava/lang/Object;)Z
  #55 = Utf8               com/fasterxml/jackson/databind/ser/PropertyWriter
{
  private static final long serialVersionUID;
    descriptor: J
    flags: (0x001a) ACC_PRIVATE, ACC_STATIC, ACC_FINAL
    ConstantValue: long 1l

  protected final java.util.Set<java.lang.String> _propertiesToInclude;
    descriptor: Ljava/util/Set;
    flags: (0x0014) ACC_PROTECTED, ACC_FINAL
    Signature: #17                          // Ljava/util/Set<Ljava/lang/String;>;

  public com.fasterxml.jackson.databind.ser.impl.SimpleBeanPropertyFilter$FilterExceptFilter(java.util.Set<java.lang.String>);
    descriptor: (Ljava/util/Set;)V
    flags: (0x0001) ACC_PUBLIC
    Code:
      stack=2, locals=2, args_size=2
         0: aload_0
         1: invokespecial #1                  // Method com/fasterxml/jackson/databind/ser/impl/SimpleBeanPropertyFilter."<init>":()V
         4: aload_0
         5: aload_1
         6: putfield      #2                  // Field _propertiesToInclude:Ljava/util/Set;
         9: return
      LineNumberTable:
        line 266: 0
        line 267: 4
        line 268: 9
      LocalVariableTable:
        Start  Length  Slot  Name   Signature
            0      10     0  this   Lcom/fasterxml/jackson/databind/ser/impl/SimpleBeanPropertyFilter$FilterExceptFilter;
            0      10     1 properties   Ljava/util/Set;
      LocalVariableTypeTable:
        Start  Length  Slot  Name   Signature
            0      10     1 properties   Ljava/util/Set<Ljava/lang/String;>;
    Signature: #29                          // (Ljava/util/Set<Ljava/lang/String;>;)V

  protected boolean include(com.fasterxml.jackson.databind.ser.BeanPropertyWriter);
    descriptor: (Lcom/fasterxml/jackson/databind/ser/BeanPropertyWriter;)Z
    flags: (0x0004) ACC_PROTECTED
    Code:
      stack=2, locals=2, args_size=2
         0: aload_0
         1: getfield      #2                  // Field _propertiesToInclude:Ljava/util/Set;
         4: aload_1
         5: invokevirtual #3                  // Method com/fasterxml/jackson/databind/ser/BeanPropertyWriter.getName:()Ljava/lang/String;
         8: invokeinterface #4,  2            // InterfaceMethod java/util/Set.contains:(Ljava/lang/Object;)Z
        13: ireturn
      LineNumberTable:
        line 272: 0
      LocalVariableTable:
        Start  Length  Slot  Name   Signature
            0      14     0  this   Lcom/fasterxml/jackson/databind/ser/impl/SimpleBeanPropertyFilter$FilterExceptFilter;
            0      14     1 writer   Lcom/fasterxml/jackson/databind/ser/BeanPropertyWriter;

  protected boolean include(com.fasterxml.jackson.databind.ser.PropertyWriter);
    descriptor: (Lcom/fasterxml/jackson/databind/ser/PropertyWriter;)Z
    flags: (0x0004) ACC_PROTECTED
    Code:
      stack=2, locals=2, args_size=2
         0: aload_0
         1: getfield      #2                  // Field _propertiesToInclude:Ljava/util/Set;
         4: aload_1
         5: invokevirtual #5                  // Method com/fasterxml/jackson/databind/ser/PropertyWriter.getName:()Ljava/lang/String;
         8: invokeinterface #4,  2            // InterfaceMethod java/util/Set.contains:(Ljava/lang/Object;)Z
        13: ireturn
      LineNumberTable:
        line 277: 0
      LocalVariableTable:
        Start  Length  Slot  Name   Signature
            0      14     0  this   Lcom/fasterxml/jackson/databind/ser/impl/SimpleBeanPropertyFilter$FilterExceptFilter;
            0      14     1 writer   Lcom/fasterxml/jackson/databind/ser/PropertyWriter;
}
SourceFile: "SimpleBeanPropertyFilter.java"
InnerClasses:
  public static #24= #6 of #7;            // FilterExceptFilter=class com/fasterxml/jackson/databind/ser/impl/SimpleBeanPropertyFilter$FilterExceptFilter of class com/fasterxml/jackson/databind/ser/impl/SimpleBeanPropertyFilter
