Classfile /Users/mw/Projects/slang-braindump/.jar/jar11/assemble/slang-braindump/assemble/content/com/fasterxml/jackson/core/base/ParserMinimalBase.class
  Last modified May 29, 2022; size 16048 bytes
  SHA-256 checksum 7cd6e0d514c5ce2e069d09661cacf902c2e0dd079a800b12c65cb2fe1317b631
  Compiled from "ParserMinimalBase.java"
public abstract class com.fasterxml.jackson.core.base.ParserMinimalBase extends com.fasterxml.jackson.core.JsonParser
  minor version: 0
  major version: 50
  flags: (0x0421) ACC_PUBLIC, ACC_SUPER, ACC_ABSTRACT
  this_class: #144                        // com/fasterxml/jackson/core/base/ParserMinimalBase
  super_class: #145                       // com/fasterxml/jackson/core/JsonParser
  interfaces: 0, fields: 50, methods: 68, attributes: 1
Constant pool:
    #1 = Class              #388          // java/lang/Integer
    #2 = Class              #389          // java/lang/Long
    #3 = Class              #390          // com/fasterxml/jackson/core/JsonTokenId
    #4 = Methodref          #145.#391     // com/fasterxml/jackson/core/JsonParser."<init>":()V
    #5 = Methodref          #145.#392     // com/fasterxml/jackson/core/JsonParser."<init>":(I)V
    #6 = Fieldref           #144.#393     // com/fasterxml/jackson/core/base/ParserMinimalBase._currToken:Lcom/fasterxml/jackson/core/JsonToken;
    #7 = Methodref          #394.#395     // com/fasterxml/jackson/core/JsonToken.id:()I
    #8 = Fieldref           #394.#396     // com/fasterxml/jackson/core/JsonToken.START_ARRAY:Lcom/fasterxml/jackson/core/JsonToken;
    #9 = Fieldref           #394.#397     // com/fasterxml/jackson/core/JsonToken.START_OBJECT:Lcom/fasterxml/jackson/core/JsonToken;
   #10 = Fieldref           #394.#398     // com/fasterxml/jackson/core/JsonToken.VALUE_NUMBER_INT:Lcom/fasterxml/jackson/core/JsonToken;
   #11 = Methodref          #144.#399     // com/fasterxml/jackson/core/base/ParserMinimalBase.nextToken:()Lcom/fasterxml/jackson/core/JsonToken;
   #12 = Fieldref           #394.#400     // com/fasterxml/jackson/core/JsonToken.FIELD_NAME:Lcom/fasterxml/jackson/core/JsonToken;
   #13 = Methodref          #144.#401     // com/fasterxml/jackson/core/base/ParserMinimalBase._handleEOF:()V
   #14 = Methodref          #394.#402     // com/fasterxml/jackson/core/JsonToken.isStructStart:()Z
   #15 = Methodref          #394.#403     // com/fasterxml/jackson/core/JsonToken.isStructEnd:()Z
   #16 = Fieldref           #394.#404     // com/fasterxml/jackson/core/JsonToken.NOT_AVAILABLE:Lcom/fasterxml/jackson/core/JsonToken;
   #17 = String             #405          // Not enough content available for `skipChildren()`: non-blocking parser? (%s)
   #18 = Methodref          #55.#406      // java/lang/Object.getClass:()Ljava/lang/Class;
   #19 = Methodref          #407.#408     // java/lang/Class.getName:()Ljava/lang/String;
   #20 = Methodref          #144.#409     // com/fasterxml/jackson/core/base/ParserMinimalBase._reportError:(Ljava/lang/String;Ljava/lang/Object;)V
   #21 = Fieldref           #144.#410     // com/fasterxml/jackson/core/base/ParserMinimalBase._lastClearedToken:Lcom/fasterxml/jackson/core/JsonToken;
   #22 = Methodref          #144.#411     // com/fasterxml/jackson/core/base/ParserMinimalBase.getText:()Ljava/lang/String;
   #23 = Methodref          #121.#412     // java/lang/String.trim:()Ljava/lang/String;
   #24 = String             #413          // true
   #25 = Methodref          #121.#414     // java/lang/String.equals:(Ljava/lang/Object;)Z
   #26 = String             #415          // false
   #27 = Methodref          #144.#416     // com/fasterxml/jackson/core/base/ParserMinimalBase._hasTextualNull:(Ljava/lang/String;)Z
   #28 = Methodref          #144.#417     // com/fasterxml/jackson/core/base/ParserMinimalBase.getIntValue:()I
   #29 = Methodref          #144.#418     // com/fasterxml/jackson/core/base/ParserMinimalBase.getEmbeddedObject:()Ljava/lang/Object;
   #30 = Class              #419          // java/lang/Boolean
   #31 = Methodref          #30.#420      // java/lang/Boolean.booleanValue:()Z
   #32 = Fieldref           #394.#421     // com/fasterxml/jackson/core/JsonToken.VALUE_NUMBER_FLOAT:Lcom/fasterxml/jackson/core/JsonToken;
   #33 = Methodref          #144.#422     // com/fasterxml/jackson/core/base/ParserMinimalBase.getValueAsInt:(I)I
   #34 = Methodref          #423.#424     // com/fasterxml/jackson/core/io/NumberInput.parseAsInt:(Ljava/lang/String;I)I
   #35 = Class              #425          // java/lang/Number
   #36 = Methodref          #35.#426      // java/lang/Number.intValue:()I
   #37 = Methodref          #144.#427     // com/fasterxml/jackson/core/base/ParserMinimalBase.getLongValue:()J
   #38 = Methodref          #144.#428     // com/fasterxml/jackson/core/base/ParserMinimalBase.getValueAsLong:(J)J
   #39 = Methodref          #423.#429     // com/fasterxml/jackson/core/io/NumberInput.parseAsLong:(Ljava/lang/String;J)J
   #40 = Methodref          #35.#430      // java/lang/Number.longValue:()J
   #41 = Methodref          #423.#431     // com/fasterxml/jackson/core/io/NumberInput.parseAsDouble:(Ljava/lang/String;D)D
   #42 = Methodref          #144.#432     // com/fasterxml/jackson/core/base/ParserMinimalBase.getDoubleValue:()D
   #43 = Methodref          #35.#433      // java/lang/Number.doubleValue:()D
   #44 = Methodref          #144.#434     // com/fasterxml/jackson/core/base/ParserMinimalBase.getValueAsString:(Ljava/lang/String;)Ljava/lang/String;
   #45 = Fieldref           #394.#435     // com/fasterxml/jackson/core/JsonToken.VALUE_STRING:Lcom/fasterxml/jackson/core/JsonToken;
   #46 = Methodref          #144.#436     // com/fasterxml/jackson/core/base/ParserMinimalBase.getCurrentName:()Ljava/lang/String;
   #47 = Fieldref           #394.#437     // com/fasterxml/jackson/core/JsonToken.VALUE_NULL:Lcom/fasterxml/jackson/core/JsonToken;
   #48 = Methodref          #394.#438     // com/fasterxml/jackson/core/JsonToken.isScalarValue:()Z
   #49 = Methodref          #439.#440     // com/fasterxml/jackson/core/Base64Variant.decode:(Ljava/lang/String;Lcom/fasterxml/jackson/core/util/ByteArrayBuilder;)V
   #50 = Class              #441          // java/lang/IllegalArgumentException
   #51 = Methodref          #50.#442      // java/lang/IllegalArgumentException.getMessage:()Ljava/lang/String;
   #52 = Methodref          #144.#443     // com/fasterxml/jackson/core/base/ParserMinimalBase._reportError:(Ljava/lang/String;)V
   #53 = String             #444          // null
   #54 = String             #445          // Unexpected character (%s) in numeric value
   #55 = Class              #446          // java/lang/Object
   #56 = Methodref          #144.#447     // com/fasterxml/jackson/core/base/ParserMinimalBase._getCharDesc:(I)Ljava/lang/String;
   #57 = Methodref          #121.#448     // java/lang/String.format:(Ljava/lang/String;[Ljava/lang/Object;)Ljava/lang/String;
   #58 = Class              #449          // java/lang/StringBuilder
   #59 = Methodref          #58.#391      // java/lang/StringBuilder."<init>":()V
   #60 = Methodref          #58.#450      // java/lang/StringBuilder.append:(Ljava/lang/String;)Ljava/lang/StringBuilder;
   #61 = String             #451          // :
   #62 = Methodref          #58.#452      // java/lang/StringBuilder.toString:()Ljava/lang/String;
   #63 = String             #453          // Invalid numeric value:
   #64 = Methodref          #144.#454     // com/fasterxml/jackson/core/base/ParserMinimalBase.reportOverflowInt:(Ljava/lang/String;)V
   #65 = Methodref          #144.#455     // com/fasterxml/jackson/core/base/ParserMinimalBase.currentToken:()Lcom/fasterxml/jackson/core/JsonToken;
   #66 = Methodref          #144.#456     // com/fasterxml/jackson/core/base/ParserMinimalBase.reportOverflowInt:(Ljava/lang/String;Lcom/fasterxml/jackson/core/JsonToken;)V
   #67 = String             #457          // Numeric value (%s) out of range of int (%d - %s)
   #68 = Methodref          #144.#458     // com/fasterxml/jackson/core/base/ParserMinimalBase._longIntegerDesc:(Ljava/lang/String;)Ljava/lang/String;
   #69 = Integer            -2147483648
   #70 = Methodref          #1.#459       // java/lang/Integer.valueOf:(I)Ljava/lang/Integer;
   #71 = Integer            2147483647
   #72 = Fieldref           #1.#460       // java/lang/Integer.TYPE:Ljava/lang/Class;
   #73 = Methodref          #144.#461     // com/fasterxml/jackson/core/base/ParserMinimalBase._reportInputCoercion:(Ljava/lang/String;Lcom/fasterxml/jackson/core/JsonToken;Ljava/lang/Class;)V
   #74 = Methodref          #144.#462     // com/fasterxml/jackson/core/base/ParserMinimalBase.reportOverflowLong:(Ljava/lang/String;)V
   #75 = Methodref          #144.#463     // com/fasterxml/jackson/core/base/ParserMinimalBase.reportOverflowLong:(Ljava/lang/String;Lcom/fasterxml/jackson/core/JsonToken;)V
   #76 = String             #464          // Numeric value (%s) out of range of long (%d - %s)
   #77 = Long               -9223372036854775808l
   #79 = Methodref          #2.#465       // java/lang/Long.valueOf:(J)Ljava/lang/Long;
   #80 = Long               9223372036854775807l
   #82 = Fieldref           #2.#460       // java/lang/Long.TYPE:Ljava/lang/Class;
   #83 = Class              #466          // com/fasterxml/jackson/core/exc/InputCoercionException
   #84 = Methodref          #83.#467      // com/fasterxml/jackson/core/exc/InputCoercionException."<init>":(Lcom/fasterxml/jackson/core/JsonParser;Ljava/lang/String;Lcom/fasterxml/jackson/core/JsonToken;Ljava/lang/Class;)V
   #85 = Methodref          #121.#468     // java/lang/String.length:()I
   #86 = String             #469          // -
   #87 = Methodref          #121.#470     // java/lang/String.startsWith:(Ljava/lang/String;)Z
   #88 = String             #471          // [Integer with %d digits]
   #89 = String             #472          // [number with %d characters]
   #90 = Methodref          #144.#473     // com/fasterxml/jackson/core/base/ParserMinimalBase._reportInvalidEOF:()V
   #91 = String             #474          // Unexpected character (%s)
   #92 = String             #475          //  in
   #93 = Methodref          #58.#476      // java/lang/StringBuilder.append:(Ljava/lang/Object;)Ljava/lang/StringBuilder;
   #94 = Methodref          #144.#477     // com/fasterxml/jackson/core/base/ParserMinimalBase._reportInvalidEOF:(Ljava/lang/String;Lcom/fasterxml/jackson/core/JsonToken;)V
   #95 = String             #478          //  in a String value
   #96 = String             #479          //  in a Number value
   #97 = String             #480          //  in a value
   #98 = Class              #481          // com/fasterxml/jackson/core/io/JsonEOFException
   #99 = String             #482          // Unexpected end-of-input
  #100 = Methodref          #98.#483      // com/fasterxml/jackson/core/io/JsonEOFException."<init>":(Lcom/fasterxml/jackson/core/JsonParser;Lcom/fasterxml/jackson/core/JsonToken;Ljava/lang/String;)V
  #101 = Methodref          #144.#484     // com/fasterxml/jackson/core/base/ParserMinimalBase._reportInvalidEOF:(Ljava/lang/String;)V
  #102 = String             #485          // Expected space separating root-level values
  #103 = Methodref          #144.#486     // com/fasterxml/jackson/core/base/ParserMinimalBase._reportUnexpectedChar:(ILjava/lang/String;)V
  #104 = String             #487          // Illegal character (
  #105 = String             #488          // ): only regular white space (\\r, \\n, \\t) is allowed between tokens
  #106 = Methodref          #489.#490     // java/lang/Character.isISOControl:(C)Z
  #107 = String             #491          // (CTRL-CHAR, code
  #108 = Methodref          #58.#492      // java/lang/StringBuilder.append:(I)Ljava/lang/StringBuilder;
  #109 = String             #493          // )
  #110 = String             #494          // \'
  #111 = Methodref          #58.#495      // java/lang/StringBuilder.append:(C)Ljava/lang/StringBuilder;
  #112 = String             #496          // \' (code
  #113 = String             #497          //  / 0x
  #114 = Methodref          #1.#498       // java/lang/Integer.toHexString:(I)Ljava/lang/String;
  #115 = Methodref          #144.#499     // com/fasterxml/jackson/core/base/ParserMinimalBase._constructError:(Ljava/lang/String;)Lcom/fasterxml/jackson/core/JsonParseException;
  #116 = Methodref          #144.#500     // com/fasterxml/jackson/core/base/ParserMinimalBase._constructError:(Ljava/lang/String;Ljava/lang/Throwable;)Lcom/fasterxml/jackson/core/JsonParseException;
  #117 = Methodref          #501.#502     // com/fasterxml/jackson/core/util/VersionUtil.throwInternal:()V
  #118 = Class              #503          // com/fasterxml/jackson/core/JsonParseException
  #119 = Methodref          #118.#504     // com/fasterxml/jackson/core/JsonParseException."<init>":(Lcom/fasterxml/jackson/core/JsonParser;Ljava/lang/String;Ljava/lang/Throwable;)V
  #120 = Methodref          #121.#505     // java/lang/String.charAt:(I)C
  #121 = Class              #506          // java/lang/String
  #122 = String             #507          // US-ASCII
  #123 = Methodref          #121.#508     // java/lang/String."<init>":([BLjava/lang/String;)V
  #124 = Class              #509          // java/io/IOException
  #125 = Class              #510          // java/lang/RuntimeException
  #126 = Methodref          #125.#511     // java/lang/RuntimeException."<init>":(Ljava/lang/Throwable;)V
  #127 = Fieldref           #144.#512     // com/fasterxml/jackson/core/base/ParserMinimalBase.NO_BYTES:[B
  #128 = Fieldref           #144.#513     // com/fasterxml/jackson/core/base/ParserMinimalBase.NO_INTS:[I
  #129 = Long               -2147483648l
  #131 = Methodref          #514.#515     // java/math/BigInteger.valueOf:(J)Ljava/math/BigInteger;
  #132 = Fieldref           #144.#516     // com/fasterxml/jackson/core/base/ParserMinimalBase.BI_MIN_INT:Ljava/math/BigInteger;
  #133 = Long               2147483647l
  #135 = Fieldref           #144.#517     // com/fasterxml/jackson/core/base/ParserMinimalBase.BI_MAX_INT:Ljava/math/BigInteger;
  #136 = Fieldref           #144.#518     // com/fasterxml/jackson/core/base/ParserMinimalBase.BI_MIN_LONG:Ljava/math/BigInteger;
  #137 = Fieldref           #144.#519     // com/fasterxml/jackson/core/base/ParserMinimalBase.BI_MAX_LONG:Ljava/math/BigInteger;
  #138 = Class              #520          // java/math/BigDecimal
  #139 = Methodref          #138.#521     // java/math/BigDecimal."<init>":(Ljava/math/BigInteger;)V
  #140 = Fieldref           #144.#522     // com/fasterxml/jackson/core/base/ParserMinimalBase.BD_MIN_LONG:Ljava/math/BigDecimal;
  #141 = Fieldref           #144.#523     // com/fasterxml/jackson/core/base/ParserMinimalBase.BD_MAX_LONG:Ljava/math/BigDecimal;
  #142 = Fieldref           #144.#524     // com/fasterxml/jackson/core/base/ParserMinimalBase.BD_MIN_INT:Ljava/math/BigDecimal;
  #143 = Fieldref           #144.#525     // com/fasterxml/jackson/core/base/ParserMinimalBase.BD_MAX_INT:Ljava/math/BigDecimal;
  #144 = Class              #526          // com/fasterxml/jackson/core/base/ParserMinimalBase
  #145 = Class              #527          // com/fasterxml/jackson/core/JsonParser
  #146 = Utf8               INT_TAB
  #147 = Utf8               I
  #148 = Utf8               ConstantValue
  #149 = Integer            9
  #150 = Utf8               INT_LF
  #151 = Integer            10
  #152 = Utf8               INT_CR
  #153 = Integer            13
  #154 = Utf8               INT_SPACE
  #155 = Integer            32
  #156 = Utf8               INT_LBRACKET
  #157 = Integer            91
  #158 = Utf8               INT_RBRACKET
  #159 = Integer            93
  #160 = Utf8               INT_LCURLY
  #161 = Integer            123
  #162 = Utf8               INT_RCURLY
  #163 = Integer            125
  #164 = Utf8               INT_QUOTE
  #165 = Integer            34
  #166 = Utf8               INT_APOS
  #167 = Integer            39
  #168 = Utf8               INT_BACKSLASH
  #169 = Integer            92
  #170 = Utf8               INT_SLASH
  #171 = Integer            47
  #172 = Utf8               INT_ASTERISK
  #173 = Integer            42
  #174 = Utf8               INT_COLON
  #175 = Integer            58
  #176 = Utf8               INT_COMMA
  #177 = Integer            44
  #178 = Utf8               INT_HASH
  #179 = Integer            35
  #180 = Utf8               INT_0
  #181 = Integer            48
  #182 = Utf8               INT_9
  #183 = Integer            57
  #184 = Utf8               INT_MINUS
  #185 = Integer            45
  #186 = Utf8               INT_PLUS
  #187 = Integer            43
  #188 = Utf8               INT_PERIOD
  #189 = Integer            46
  #190 = Utf8               INT_e
  #191 = Integer            101
  #192 = Utf8               INT_E
  #193 = Integer            69
  #194 = Utf8               CHAR_NULL
  #195 = Utf8               C
  #196 = Integer            0
  #197 = Utf8               NO_BYTES
  #198 = Utf8               [B
  #199 = Utf8               NO_INTS
  #200 = Utf8               [I
  #201 = Utf8               NR_UNKNOWN
  #202 = Utf8               NR_INT
  #203 = Integer            1
  #204 = Utf8               NR_LONG
  #205 = Integer            2
  #206 = Utf8               NR_BIGINT
  #207 = Integer            4
  #208 = Utf8               NR_DOUBLE
  #209 = Integer            8
  #210 = Utf8               NR_BIGDECIMAL
  #211 = Integer            16
  #212 = Utf8               NR_FLOAT
  #213 = Utf8               BI_MIN_INT
  #214 = Utf8               Ljava/math/BigInteger;
  #215 = Utf8               BI_MAX_INT
  #216 = Utf8               BI_MIN_LONG
  #217 = Utf8               BI_MAX_LONG
  #218 = Utf8               BD_MIN_LONG
  #219 = Utf8               Ljava/math/BigDecimal;
  #220 = Utf8               BD_MAX_LONG
  #221 = Utf8               BD_MIN_INT
  #222 = Utf8               BD_MAX_INT
  #223 = Utf8               MIN_INT_L
  #224 = Utf8               J
  #225 = Utf8               MAX_INT_L
  #226 = Utf8               MIN_LONG_D
  #227 = Utf8               D
  #228 = Double             -9.223372036854776E18d
  #230 = Utf8               MAX_LONG_D
  #231 = Double             9.223372036854776E18d
  #233 = Utf8               MIN_INT_D
  #234 = Double             -2.147483648E9d
  #236 = Utf8               MAX_INT_D
  #237 = Double             2.147483647E9d
  #239 = Utf8               MAX_ERROR_TOKEN_LENGTH
  #240 = Integer            256
  #241 = Utf8               _currToken
  #242 = Utf8               Lcom/fasterxml/jackson/core/JsonToken;
  #243 = Utf8               _lastClearedToken
  #244 = Utf8               <init>
  #245 = Utf8               ()V
  #246 = Utf8               Code
  #247 = Utf8               LineNumberTable
  #248 = Utf8               LocalVariableTable
  #249 = Utf8               this
  #250 = Utf8               Lcom/fasterxml/jackson/core/base/ParserMinimalBase;
  #251 = Utf8               (I)V
  #252 = Utf8               features
  #253 = Utf8               nextToken
  #254 = Utf8               ()Lcom/fasterxml/jackson/core/JsonToken;
  #255 = Utf8               Exceptions
  #256 = Utf8               currentToken
  #257 = Utf8               currentTokenId
  #258 = Utf8               ()I
  #259 = Utf8               t
  #260 = Utf8               StackMapTable
  #261 = Class              #528          // com/fasterxml/jackson/core/JsonToken
  #262 = Utf8               getCurrentToken
  #263 = Utf8               getCurrentTokenId
  #264 = Utf8               Deprecated
  #265 = Utf8               RuntimeVisibleAnnotations
  #266 = Utf8               Ljava/lang/Deprecated;
  #267 = Utf8               hasCurrentToken
  #268 = Utf8               ()Z
  #269 = Utf8               hasTokenId
  #270 = Utf8               (I)Z
  #271 = Utf8               id
  #272 = Utf8               hasToken
  #273 = Utf8               (Lcom/fasterxml/jackson/core/JsonToken;)Z
  #274 = Utf8               isExpectedStartArrayToken
  #275 = Utf8               isExpectedStartObjectToken
  #276 = Utf8               isExpectedNumberIntToken
  #277 = Utf8               nextValue
  #278 = Utf8               skipChildren
  #279 = Utf8               ()Lcom/fasterxml/jackson/core/JsonParser;
  #280 = Utf8               open
  #281 = Utf8               _handleEOF
  #282 = Utf8               getCurrentName
  #283 = Utf8               ()Ljava/lang/String;
  #284 = Utf8               close
  #285 = Utf8               isClosed
  #286 = Utf8               getParsingContext
  #287 = Utf8               ()Lcom/fasterxml/jackson/core/JsonStreamContext;
  #288 = Utf8               clearCurrentToken
  #289 = Utf8               getLastClearedToken
  #290 = Utf8               overrideCurrentName
  #291 = Utf8               (Ljava/lang/String;)V
  #292 = Utf8               getText
  #293 = Utf8               getTextCharacters
  #294 = Utf8               ()[C
  #295 = Utf8               hasTextCharacters
  #296 = Utf8               getTextLength
  #297 = Utf8               getTextOffset
  #298 = Utf8               getBinaryValue
  #299 = Utf8               (Lcom/fasterxml/jackson/core/Base64Variant;)[B
  #300 = Utf8               getValueAsBoolean
  #301 = Utf8               (Z)Z
  #302 = Utf8               str
  #303 = Utf8               Ljava/lang/String;
  #304 = Utf8               value
  #305 = Utf8               Ljava/lang/Object;
  #306 = Utf8               defaultValue
  #307 = Utf8               Z
  #308 = Class              #506          // java/lang/String
  #309 = Utf8               getValueAsInt
  #310 = Utf8               (I)I
  #311 = Utf8               getValueAsLong
  #312 = Utf8               ()J
  #313 = Utf8               (J)J
  #314 = Utf8               getValueAsDouble
  #315 = Utf8               (D)D
  #316 = Utf8               getValueAsString
  #317 = Utf8               (Ljava/lang/String;)Ljava/lang/String;
  #318 = Utf8               _decodeBase64
  #319 = Utf8               (Ljava/lang/String;Lcom/fasterxml/jackson/core/util/ByteArrayBuilder;Lcom/fasterxml/jackson/core/Base64Variant;)V
  #320 = Utf8               e
  #321 = Utf8               Ljava/lang/IllegalArgumentException;
  #322 = Utf8               builder
  #323 = Utf8               Lcom/fasterxml/jackson/core/util/ByteArrayBuilder;
  #324 = Utf8               b64variant
  #325 = Utf8               Lcom/fasterxml/jackson/core/Base64Variant;
  #326 = Class              #441          // java/lang/IllegalArgumentException
  #327 = Utf8               _hasTextualNull
  #328 = Utf8               (Ljava/lang/String;)Z
  #329 = Utf8               reportUnexpectedNumberChar
  #330 = Utf8               (ILjava/lang/String;)V
  #331 = Utf8               ch
  #332 = Utf8               comment
  #333 = Utf8               msg
  #334 = Utf8               reportInvalidNumber
  #335 = Utf8               reportOverflowInt
  #336 = Utf8               numDesc
  #337 = Utf8               (Ljava/lang/String;Lcom/fasterxml/jackson/core/JsonToken;)V
  #338 = Utf8               inputType
  #339 = Utf8               reportOverflowLong
  #340 = Utf8               _reportInputCoercion
  #341 = Utf8               (Ljava/lang/String;Lcom/fasterxml/jackson/core/JsonToken;Ljava/lang/Class;)V
  #342 = Utf8               targetType
  #343 = Utf8               Ljava/lang/Class;
  #344 = Utf8               LocalVariableTypeTable
  #345 = Utf8               Ljava/lang/Class<*>;
  #346 = Utf8               Signature
  #347 = Utf8               (Ljava/lang/String;Lcom/fasterxml/jackson/core/JsonToken;Ljava/lang/Class<*>;)V
  #348 = Utf8               _longIntegerDesc
  #349 = Utf8               rawNum
  #350 = Utf8               rawLen
  #351 = Utf8               _longNumberDesc
  #352 = Utf8               _reportUnexpectedChar
  #353 = Utf8               _reportInvalidEOF
  #354 = Utf8               _reportInvalidEOFInValue
  #355 = Utf8               (Lcom/fasterxml/jackson/core/JsonToken;)V
  #356 = Utf8               type
  #357 = Utf8               currToken
  #358 = Utf8               _reportMissingRootWS
  #359 = Utf8               _throwInvalidSpace
  #360 = Utf8               i
  #361 = Utf8               c
  #362 = Utf8               _getCharDesc
  #363 = Utf8               (I)Ljava/lang/String;
  #364 = Utf8               _reportError
  #365 = Utf8               (Ljava/lang/String;Ljava/lang/Object;)V
  #366 = Utf8               arg
  #367 = Utf8               (Ljava/lang/String;Ljava/lang/Object;Ljava/lang/Object;)V
  #368 = Utf8               arg1
  #369 = Utf8               arg2
  #370 = Utf8               _wrapError
  #371 = Utf8               (Ljava/lang/String;Ljava/lang/Throwable;)V
  #372 = Utf8               Ljava/lang/Throwable;
  #373 = Utf8               _throwInternal
  #374 = Utf8               _constructError
  #375 = Utf8               (Ljava/lang/String;Ljava/lang/Throwable;)Lcom/fasterxml/jackson/core/JsonParseException;
  #376 = Utf8               _asciiBytes
  #377 = Utf8               (Ljava/lang/String;)[B
  #378 = Utf8               len
  #379 = Utf8               b
  #380 = Class              #198          // "[B"
  #381 = Utf8               _ascii
  #382 = Utf8               ([B)Ljava/lang/String;
  #383 = Utf8               Ljava/io/IOException;
  #384 = Class              #509          // java/io/IOException
  #385 = Utf8               <clinit>
  #386 = Utf8               SourceFile
  #387 = Utf8               ParserMinimalBase.java
  #388 = Utf8               java/lang/Integer
  #389 = Utf8               java/lang/Long
  #390 = Utf8               com/fasterxml/jackson/core/JsonTokenId
  #391 = NameAndType        #244:#245     // "<init>":()V
  #392 = NameAndType        #244:#251     // "<init>":(I)V
  #393 = NameAndType        #241:#242     // _currToken:Lcom/fasterxml/jackson/core/JsonToken;
  #394 = Class              #528          // com/fasterxml/jackson/core/JsonToken
  #395 = NameAndType        #271:#258     // id:()I
  #396 = NameAndType        #529:#242     // START_ARRAY:Lcom/fasterxml/jackson/core/JsonToken;
  #397 = NameAndType        #530:#242     // START_OBJECT:Lcom/fasterxml/jackson/core/JsonToken;
  #398 = NameAndType        #531:#242     // VALUE_NUMBER_INT:Lcom/fasterxml/jackson/core/JsonToken;
  #399 = NameAndType        #253:#254     // nextToken:()Lcom/fasterxml/jackson/core/JsonToken;
  #400 = NameAndType        #532:#242     // FIELD_NAME:Lcom/fasterxml/jackson/core/JsonToken;
  #401 = NameAndType        #281:#245     // _handleEOF:()V
  #402 = NameAndType        #533:#268     // isStructStart:()Z
  #403 = NameAndType        #534:#268     // isStructEnd:()Z
  #404 = NameAndType        #535:#242     // NOT_AVAILABLE:Lcom/fasterxml/jackson/core/JsonToken;
  #405 = Utf8               Not enough content available for `skipChildren()`: non-blocking parser? (%s)
  #406 = NameAndType        #536:#537     // getClass:()Ljava/lang/Class;
  #407 = Class              #538          // java/lang/Class
  #408 = NameAndType        #539:#283     // getName:()Ljava/lang/String;
  #409 = NameAndType        #364:#365     // _reportError:(Ljava/lang/String;Ljava/lang/Object;)V
  #410 = NameAndType        #243:#242     // _lastClearedToken:Lcom/fasterxml/jackson/core/JsonToken;
  #411 = NameAndType        #292:#283     // getText:()Ljava/lang/String;
  #412 = NameAndType        #540:#283     // trim:()Ljava/lang/String;
  #413 = Utf8               true
  #414 = NameAndType        #541:#542     // equals:(Ljava/lang/Object;)Z
  #415 = Utf8               false
  #416 = NameAndType        #327:#328     // _hasTextualNull:(Ljava/lang/String;)Z
  #417 = NameAndType        #543:#258     // getIntValue:()I
  #418 = NameAndType        #544:#545     // getEmbeddedObject:()Ljava/lang/Object;
  #419 = Utf8               java/lang/Boolean
  #420 = NameAndType        #546:#268     // booleanValue:()Z
  #421 = NameAndType        #547:#242     // VALUE_NUMBER_FLOAT:Lcom/fasterxml/jackson/core/JsonToken;
  #422 = NameAndType        #309:#310     // getValueAsInt:(I)I
  #423 = Class              #548          // com/fasterxml/jackson/core/io/NumberInput
  #424 = NameAndType        #549:#550     // parseAsInt:(Ljava/lang/String;I)I
  #425 = Utf8               java/lang/Number
  #426 = NameAndType        #551:#258     // intValue:()I
  #427 = NameAndType        #552:#312     // getLongValue:()J
  #428 = NameAndType        #311:#313     // getValueAsLong:(J)J
  #429 = NameAndType        #553:#554     // parseAsLong:(Ljava/lang/String;J)J
  #430 = NameAndType        #555:#312     // longValue:()J
  #431 = NameAndType        #556:#557     // parseAsDouble:(Ljava/lang/String;D)D
  #432 = NameAndType        #558:#559     // getDoubleValue:()D
  #433 = NameAndType        #560:#559     // doubleValue:()D
  #434 = NameAndType        #316:#317     // getValueAsString:(Ljava/lang/String;)Ljava/lang/String;
  #435 = NameAndType        #561:#242     // VALUE_STRING:Lcom/fasterxml/jackson/core/JsonToken;
  #436 = NameAndType        #282:#283     // getCurrentName:()Ljava/lang/String;
  #437 = NameAndType        #562:#242     // VALUE_NULL:Lcom/fasterxml/jackson/core/JsonToken;
  #438 = NameAndType        #563:#268     // isScalarValue:()Z
  #439 = Class              #564          // com/fasterxml/jackson/core/Base64Variant
  #440 = NameAndType        #565:#566     // decode:(Ljava/lang/String;Lcom/fasterxml/jackson/core/util/ByteArrayBuilder;)V
  #441 = Utf8               java/lang/IllegalArgumentException
  #442 = NameAndType        #567:#283     // getMessage:()Ljava/lang/String;
  #443 = NameAndType        #364:#291     // _reportError:(Ljava/lang/String;)V
  #444 = Utf8               null
  #445 = Utf8               Unexpected character (%s) in numeric value
  #446 = Utf8               java/lang/Object
  #447 = NameAndType        #362:#363     // _getCharDesc:(I)Ljava/lang/String;
  #448 = NameAndType        #568:#569     // format:(Ljava/lang/String;[Ljava/lang/Object;)Ljava/lang/String;
  #449 = Utf8               java/lang/StringBuilder
  #450 = NameAndType        #570:#571     // append:(Ljava/lang/String;)Ljava/lang/StringBuilder;
  #451 = Utf8               :
  #452 = NameAndType        #572:#283     // toString:()Ljava/lang/String;
  #453 = Utf8               Invalid numeric value:
  #454 = NameAndType        #335:#291     // reportOverflowInt:(Ljava/lang/String;)V
  #455 = NameAndType        #256:#254     // currentToken:()Lcom/fasterxml/jackson/core/JsonToken;
  #456 = NameAndType        #335:#337     // reportOverflowInt:(Ljava/lang/String;Lcom/fasterxml/jackson/core/JsonToken;)V
  #457 = Utf8               Numeric value (%s) out of range of int (%d - %s)
  #458 = NameAndType        #348:#317     // _longIntegerDesc:(Ljava/lang/String;)Ljava/lang/String;
  #459 = NameAndType        #573:#574     // valueOf:(I)Ljava/lang/Integer;
  #460 = NameAndType        #575:#343     // TYPE:Ljava/lang/Class;
  #461 = NameAndType        #340:#341     // _reportInputCoercion:(Ljava/lang/String;Lcom/fasterxml/jackson/core/JsonToken;Ljava/lang/Class;)V
  #462 = NameAndType        #339:#291     // reportOverflowLong:(Ljava/lang/String;)V
  #463 = NameAndType        #339:#337     // reportOverflowLong:(Ljava/lang/String;Lcom/fasterxml/jackson/core/JsonToken;)V
  #464 = Utf8               Numeric value (%s) out of range of long (%d - %s)
  #465 = NameAndType        #573:#576     // valueOf:(J)Ljava/lang/Long;
  #466 = Utf8               com/fasterxml/jackson/core/exc/InputCoercionException
  #467 = NameAndType        #244:#577     // "<init>":(Lcom/fasterxml/jackson/core/JsonParser;Ljava/lang/String;Lcom/fasterxml/jackson/core/JsonToken;Ljava/lang/Class;)V
  #468 = NameAndType        #578:#258     // length:()I
  #469 = Utf8               -
  #470 = NameAndType        #579:#328     // startsWith:(Ljava/lang/String;)Z
  #471 = Utf8               [Integer with %d digits]
  #472 = Utf8               [number with %d characters]
  #473 = NameAndType        #353:#245     // _reportInvalidEOF:()V
  #474 = Utf8               Unexpected character (%s)
  #475 = Utf8                in
  #476 = NameAndType        #570:#580     // append:(Ljava/lang/Object;)Ljava/lang/StringBuilder;
  #477 = NameAndType        #353:#337     // _reportInvalidEOF:(Ljava/lang/String;Lcom/fasterxml/jackson/core/JsonToken;)V
  #478 = Utf8                in a String value
  #479 = Utf8                in a Number value
  #480 = Utf8                in a value
  #481 = Utf8               com/fasterxml/jackson/core/io/JsonEOFException
  #482 = Utf8               Unexpected end-of-input
  #483 = NameAndType        #244:#581     // "<init>":(Lcom/fasterxml/jackson/core/JsonParser;Lcom/fasterxml/jackson/core/JsonToken;Ljava/lang/String;)V
  #484 = NameAndType        #353:#291     // _reportInvalidEOF:(Ljava/lang/String;)V
  #485 = Utf8               Expected space separating root-level values
  #486 = NameAndType        #352:#330     // _reportUnexpectedChar:(ILjava/lang/String;)V
  #487 = Utf8               Illegal character (
  #488 = Utf8               ): only regular white space (\\r, \\n, \\t) is allowed between tokens
  #489 = Class              #582          // java/lang/Character
  #490 = NameAndType        #583:#584     // isISOControl:(C)Z
  #491 = Utf8               (CTRL-CHAR, code
  #492 = NameAndType        #570:#585     // append:(I)Ljava/lang/StringBuilder;
  #493 = Utf8               )
  #494 = Utf8               \'
  #495 = NameAndType        #570:#586     // append:(C)Ljava/lang/StringBuilder;
  #496 = Utf8               \' (code
  #497 = Utf8                / 0x
  #498 = NameAndType        #587:#363     // toHexString:(I)Ljava/lang/String;
  #499 = NameAndType        #374:#588     // _constructError:(Ljava/lang/String;)Lcom/fasterxml/jackson/core/JsonParseException;
  #500 = NameAndType        #374:#375     // _constructError:(Ljava/lang/String;Ljava/lang/Throwable;)Lcom/fasterxml/jackson/core/JsonParseException;
  #501 = Class              #589          // com/fasterxml/jackson/core/util/VersionUtil
  #502 = NameAndType        #590:#245     // throwInternal:()V
  #503 = Utf8               com/fasterxml/jackson/core/JsonParseException
  #504 = NameAndType        #244:#591     // "<init>":(Lcom/fasterxml/jackson/core/JsonParser;Ljava/lang/String;Ljava/lang/Throwable;)V
  #505 = NameAndType        #592:#593     // charAt:(I)C
  #506 = Utf8               java/lang/String
  #507 = Utf8               US-ASCII
  #508 = NameAndType        #244:#594     // "<init>":([BLjava/lang/String;)V
  #509 = Utf8               java/io/IOException
  #510 = Utf8               java/lang/RuntimeException
  #511 = NameAndType        #244:#595     // "<init>":(Ljava/lang/Throwable;)V
  #512 = NameAndType        #197:#198     // NO_BYTES:[B
  #513 = NameAndType        #199:#200     // NO_INTS:[I
  #514 = Class              #596          // java/math/BigInteger
  #515 = NameAndType        #573:#597     // valueOf:(J)Ljava/math/BigInteger;
  #516 = NameAndType        #213:#214     // BI_MIN_INT:Ljava/math/BigInteger;
  #517 = NameAndType        #215:#214     // BI_MAX_INT:Ljava/math/BigInteger;
  #518 = NameAndType        #216:#214     // BI_MIN_LONG:Ljava/math/BigInteger;
  #519 = NameAndType        #217:#214     // BI_MAX_LONG:Ljava/math/BigInteger;
  #520 = Utf8               java/math/BigDecimal
  #521 = NameAndType        #244:#598     // "<init>":(Ljava/math/BigInteger;)V
  #522 = NameAndType        #218:#219     // BD_MIN_LONG:Ljava/math/BigDecimal;
  #523 = NameAndType        #220:#219     // BD_MAX_LONG:Ljava/math/BigDecimal;
  #524 = NameAndType        #221:#219     // BD_MIN_INT:Ljava/math/BigDecimal;
  #525 = NameAndType        #222:#219     // BD_MAX_INT:Ljava/math/BigDecimal;
  #526 = Utf8               com/fasterxml/jackson/core/base/ParserMinimalBase
  #527 = Utf8               com/fasterxml/jackson/core/JsonParser
  #528 = Utf8               com/fasterxml/jackson/core/JsonToken
  #529 = Utf8               START_ARRAY
  #530 = Utf8               START_OBJECT
  #531 = Utf8               VALUE_NUMBER_INT
  #532 = Utf8               FIELD_NAME
  #533 = Utf8               isStructStart
  #534 = Utf8               isStructEnd
  #535 = Utf8               NOT_AVAILABLE
  #536 = Utf8               getClass
  #537 = Utf8               ()Ljava/lang/Class;
  #538 = Utf8               java/lang/Class
  #539 = Utf8               getName
  #540 = Utf8               trim
  #541 = Utf8               equals
  #542 = Utf8               (Ljava/lang/Object;)Z
  #543 = Utf8               getIntValue
  #544 = Utf8               getEmbeddedObject
  #545 = Utf8               ()Ljava/lang/Object;
  #546 = Utf8               booleanValue
  #547 = Utf8               VALUE_NUMBER_FLOAT
  #548 = Utf8               com/fasterxml/jackson/core/io/NumberInput
  #549 = Utf8               parseAsInt
  #550 = Utf8               (Ljava/lang/String;I)I
  #551 = Utf8               intValue
  #552 = Utf8               getLongValue
  #553 = Utf8               parseAsLong
  #554 = Utf8               (Ljava/lang/String;J)J
  #555 = Utf8               longValue
  #556 = Utf8               parseAsDouble
  #557 = Utf8               (Ljava/lang/String;D)D
  #558 = Utf8               getDoubleValue
  #559 = Utf8               ()D
  #560 = Utf8               doubleValue
  #561 = Utf8               VALUE_STRING
  #562 = Utf8               VALUE_NULL
  #563 = Utf8               isScalarValue
  #564 = Utf8               com/fasterxml/jackson/core/Base64Variant
  #565 = Utf8               decode
  #566 = Utf8               (Ljava/lang/String;Lcom/fasterxml/jackson/core/util/ByteArrayBuilder;)V
  #567 = Utf8               getMessage
  #568 = Utf8               format
  #569 = Utf8               (Ljava/lang/String;[Ljava/lang/Object;)Ljava/lang/String;
  #570 = Utf8               append
  #571 = Utf8               (Ljava/lang/String;)Ljava/lang/StringBuilder;
  #572 = Utf8               toString
  #573 = Utf8               valueOf
  #574 = Utf8               (I)Ljava/lang/Integer;
  #575 = Utf8               TYPE
  #576 = Utf8               (J)Ljava/lang/Long;
  #577 = Utf8               (Lcom/fasterxml/jackson/core/JsonParser;Ljava/lang/String;Lcom/fasterxml/jackson/core/JsonToken;Ljava/lang/Class;)V
  #578 = Utf8               length
  #579 = Utf8               startsWith
  #580 = Utf8               (Ljava/lang/Object;)Ljava/lang/StringBuilder;
  #581 = Utf8               (Lcom/fasterxml/jackson/core/JsonParser;Lcom/fasterxml/jackson/core/JsonToken;Ljava/lang/String;)V
  #582 = Utf8               java/lang/Character
  #583 = Utf8               isISOControl
  #584 = Utf8               (C)Z
  #585 = Utf8               (I)Ljava/lang/StringBuilder;
  #586 = Utf8               (C)Ljava/lang/StringBuilder;
  #587 = Utf8               toHexString
  #588 = Utf8               (Ljava/lang/String;)Lcom/fasterxml/jackson/core/JsonParseException;
  #589 = Utf8               com/fasterxml/jackson/core/util/VersionUtil
  #590 = Utf8               throwInternal
  #591 = Utf8               (Lcom/fasterxml/jackson/core/JsonParser;Ljava/lang/String;Ljava/lang/Throwable;)V
  #592 = Utf8               charAt
  #593 = Utf8               (I)C
  #594 = Utf8               ([BLjava/lang/String;)V
  #595 = Utf8               (Ljava/lang/Throwable;)V
  #596 = Utf8               java/math/BigInteger
  #597 = Utf8               (J)Ljava/math/BigInteger;
  #598 = Utf8               (Ljava/math/BigInteger;)V
{
  protected static final int INT_TAB;
    descriptor: I
    flags: (0x001c) ACC_PROTECTED, ACC_STATIC, ACC_FINAL
    ConstantValue: int 9

  protected static final int INT_LF;
    descriptor: I
    flags: (0x001c) ACC_PROTECTED, ACC_STATIC, ACC_FINAL
    ConstantValue: int 10

  protected static final int INT_CR;
    descriptor: I
    flags: (0x001c) ACC_PROTECTED, ACC_STATIC, ACC_FINAL
    ConstantValue: int 13

  protected static final int INT_SPACE;
    descriptor: I
    flags: (0x001c) ACC_PROTECTED, ACC_STATIC, ACC_FINAL
    ConstantValue: int 32

  protected static final int INT_LBRACKET;
    descriptor: I
    flags: (0x001c) ACC_PROTECTED, ACC_STATIC, ACC_FINAL
    ConstantValue: int 91

  protected static final int INT_RBRACKET;
    descriptor: I
    flags: (0x001c) ACC_PROTECTED, ACC_STATIC, ACC_FINAL
    ConstantValue: int 93

  protected static final int INT_LCURLY;
    descriptor: I
    flags: (0x001c) ACC_PROTECTED, ACC_STATIC, ACC_FINAL
    ConstantValue: int 123

  protected static final int INT_RCURLY;
    descriptor: I
    flags: (0x001c) ACC_PROTECTED, ACC_STATIC, ACC_FINAL
    ConstantValue: int 125

  protected static final int INT_QUOTE;
    descriptor: I
    flags: (0x001c) ACC_PROTECTED, ACC_STATIC, ACC_FINAL
    ConstantValue: int 34

  protected static final int INT_APOS;
    descriptor: I
    flags: (0x001c) ACC_PROTECTED, ACC_STATIC, ACC_FINAL
    ConstantValue: int 39

  protected static final int INT_BACKSLASH;
    descriptor: I
    flags: (0x001c) ACC_PROTECTED, ACC_STATIC, ACC_FINAL
    ConstantValue: int 92

  protected static final int INT_SLASH;
    descriptor: I
    flags: (0x001c) ACC_PROTECTED, ACC_STATIC, ACC_FINAL
    ConstantValue: int 47

  protected static final int INT_ASTERISK;
    descriptor: I
    flags: (0x001c) ACC_PROTECTED, ACC_STATIC, ACC_FINAL
    ConstantValue: int 42

  protected static final int INT_COLON;
    descriptor: I
    flags: (0x001c) ACC_PROTECTED, ACC_STATIC, ACC_FINAL
    ConstantValue: int 58

  protected static final int INT_COMMA;
    descriptor: I
    flags: (0x001c) ACC_PROTECTED, ACC_STATIC, ACC_FINAL
    ConstantValue: int 44

  protected static final int INT_HASH;
    descriptor: I
    flags: (0x001c) ACC_PROTECTED, ACC_STATIC, ACC_FINAL
    ConstantValue: int 35

  protected static final int INT_0;
    descriptor: I
    flags: (0x001c) ACC_PROTECTED, ACC_STATIC, ACC_FINAL
    ConstantValue: int 48

  protected static final int INT_9;
    descriptor: I
    flags: (0x001c) ACC_PROTECTED, ACC_STATIC, ACC_FINAL
    ConstantValue: int 57

  protected static final int INT_MINUS;
    descriptor: I
    flags: (0x001c) ACC_PROTECTED, ACC_STATIC, ACC_FINAL
    ConstantValue: int 45

  protected static final int INT_PLUS;
    descriptor: I
    flags: (0x001c) ACC_PROTECTED, ACC_STATIC, ACC_FINAL
    ConstantValue: int 43

  protected static final int INT_PERIOD;
    descriptor: I
    flags: (0x001c) ACC_PROTECTED, ACC_STATIC, ACC_FINAL
    ConstantValue: int 46

  protected static final int INT_e;
    descriptor: I
    flags: (0x001c) ACC_PROTECTED, ACC_STATIC, ACC_FINAL
    ConstantValue: int 101

  protected static final int INT_E;
    descriptor: I
    flags: (0x001c) ACC_PROTECTED, ACC_STATIC, ACC_FINAL
    ConstantValue: int 69

  protected static final char CHAR_NULL;
    descriptor: C
    flags: (0x001c) ACC_PROTECTED, ACC_STATIC, ACC_FINAL
    ConstantValue: int 0

  protected static final byte[] NO_BYTES;
    descriptor: [B
    flags: (0x001c) ACC_PROTECTED, ACC_STATIC, ACC_FINAL

  protected static final int[] NO_INTS;
    descriptor: [I
    flags: (0x001c) ACC_PROTECTED, ACC_STATIC, ACC_FINAL

  protected static final int NR_UNKNOWN;
    descriptor: I
    flags: (0x001c) ACC_PROTECTED, ACC_STATIC, ACC_FINAL
    ConstantValue: int 0

  protected static final int NR_INT;
    descriptor: I
    flags: (0x001c) ACC_PROTECTED, ACC_STATIC, ACC_FINAL
    ConstantValue: int 1

  protected static final int NR_LONG;
    descriptor: I
    flags: (0x001c) ACC_PROTECTED, ACC_STATIC, ACC_FINAL
    ConstantValue: int 2

  protected static final int NR_BIGINT;
    descriptor: I
    flags: (0x001c) ACC_PROTECTED, ACC_STATIC, ACC_FINAL
    ConstantValue: int 4

  protected static final int NR_DOUBLE;
    descriptor: I
    flags: (0x001c) ACC_PROTECTED, ACC_STATIC, ACC_FINAL
    ConstantValue: int 8

  protected static final int NR_BIGDECIMAL;
    descriptor: I
    flags: (0x001c) ACC_PROTECTED, ACC_STATIC, ACC_FINAL
    ConstantValue: int 16

  protected static final int NR_FLOAT;
    descriptor: I
    flags: (0x001c) ACC_PROTECTED, ACC_STATIC, ACC_FINAL
    ConstantValue: int 32

  protected static final java.math.BigInteger BI_MIN_INT;
    descriptor: Ljava/math/BigInteger;
    flags: (0x001c) ACC_PROTECTED, ACC_STATIC, ACC_FINAL

  protected static final java.math.BigInteger BI_MAX_INT;
    descriptor: Ljava/math/BigInteger;
    flags: (0x001c) ACC_PROTECTED, ACC_STATIC, ACC_FINAL

  protected static final java.math.BigInteger BI_MIN_LONG;
    descriptor: Ljava/math/BigInteger;
    flags: (0x001c) ACC_PROTECTED, ACC_STATIC, ACC_FINAL

  protected static final java.math.BigInteger BI_MAX_LONG;
    descriptor: Ljava/math/BigInteger;
    flags: (0x001c) ACC_PROTECTED, ACC_STATIC, ACC_FINAL

  protected static final java.math.BigDecimal BD_MIN_LONG;
    descriptor: Ljava/math/BigDecimal;
    flags: (0x001c) ACC_PROTECTED, ACC_STATIC, ACC_FINAL

  protected static final java.math.BigDecimal BD_MAX_LONG;
    descriptor: Ljava/math/BigDecimal;
    flags: (0x001c) ACC_PROTECTED, ACC_STATIC, ACC_FINAL

  protected static final java.math.BigDecimal BD_MIN_INT;
    descriptor: Ljava/math/BigDecimal;
    flags: (0x001c) ACC_PROTECTED, ACC_STATIC, ACC_FINAL

  protected static final java.math.BigDecimal BD_MAX_INT;
    descriptor: Ljava/math/BigDecimal;
    flags: (0x001c) ACC_PROTECTED, ACC_STATIC, ACC_FINAL

  protected static final long MIN_INT_L;
    descriptor: J
    flags: (0x001c) ACC_PROTECTED, ACC_STATIC, ACC_FINAL
    ConstantValue: long -2147483648l

  protected static final long MAX_INT_L;
    descriptor: J
    flags: (0x001c) ACC_PROTECTED, ACC_STATIC, ACC_FINAL
    ConstantValue: long 2147483647l

  protected static final double MIN_LONG_D;
    descriptor: D
    flags: (0x001c) ACC_PROTECTED, ACC_STATIC, ACC_FINAL
    ConstantValue: double -9.223372036854776E18d

  protected static final double MAX_LONG_D;
    descriptor: D
    flags: (0x001c) ACC_PROTECTED, ACC_STATIC, ACC_FINAL
    ConstantValue: double 9.223372036854776E18d

  protected static final double MIN_INT_D;
    descriptor: D
    flags: (0x001c) ACC_PROTECTED, ACC_STATIC, ACC_FINAL
    ConstantValue: double -2.147483648E9d

  protected static final double MAX_INT_D;
    descriptor: D
    flags: (0x001c) ACC_PROTECTED, ACC_STATIC, ACC_FINAL
    ConstantValue: double 2.147483647E9d

  protected static final int MAX_ERROR_TOKEN_LENGTH;
    descriptor: I
    flags: (0x001c) ACC_PROTECTED, ACC_STATIC, ACC_FINAL
    ConstantValue: int 256

  protected com.fasterxml.jackson.core.JsonToken _currToken;
    descriptor: Lcom/fasterxml/jackson/core/JsonToken;
    flags: (0x0004) ACC_PROTECTED

  protected com.fasterxml.jackson.core.JsonToken _lastClearedToken;
    descriptor: Lcom/fasterxml/jackson/core/JsonToken;
    flags: (0x0004) ACC_PROTECTED

  protected com.fasterxml.jackson.core.base.ParserMinimalBase();
    descriptor: ()V
    flags: (0x0004) ACC_PROTECTED
    Code:
      stack=1, locals=1, args_size=1
         0: aload_0
         1: invokespecial #4                  // Method com/fasterxml/jackson/core/JsonParser."<init>":()V
         4: return
      LineNumberTable:
        line 159: 0
      LocalVariableTable:
        Start  Length  Slot  Name   Signature
            0       5     0  this   Lcom/fasterxml/jackson/core/base/ParserMinimalBase;

  protected com.fasterxml.jackson.core.base.ParserMinimalBase(int);
    descriptor: (I)V
    flags: (0x0004) ACC_PROTECTED
    Code:
      stack=2, locals=2, args_size=2
         0: aload_0
         1: iload_1
         2: invokespecial #5                  // Method com/fasterxml/jackson/core/JsonParser."<init>":(I)V
         5: return
      LineNumberTable:
        line 160: 0
      LocalVariableTable:
        Start  Length  Slot  Name   Signature
            0       6     0  this   Lcom/fasterxml/jackson/core/base/ParserMinimalBase;
            0       6     1 features   I

  public abstract com.fasterxml.jackson.core.JsonToken nextToken() throws java.io.IOException;
    descriptor: ()Lcom/fasterxml/jackson/core/JsonToken;
    flags: (0x0401) ACC_PUBLIC, ACC_ABSTRACT
    Exceptions:
      throws java.io.IOException

  public com.fasterxml.jackson.core.JsonToken currentToken();
    descriptor: ()Lcom/fasterxml/jackson/core/JsonToken;
    flags: (0x0001) ACC_PUBLIC
    Code:
      stack=1, locals=1, args_size=1
         0: aload_0
         1: getfield      #6                  // Field _currToken:Lcom/fasterxml/jackson/core/JsonToken;
         4: areturn
      LineNumberTable:
        line 186: 0
      LocalVariableTable:
        Start  Length  Slot  Name   Signature
            0       5     0  this   Lcom/fasterxml/jackson/core/base/ParserMinimalBase;

  public int currentTokenId();
    descriptor: ()I
    flags: (0x0001) ACC_PUBLIC
    Code:
      stack=1, locals=2, args_size=1
         0: aload_0
         1: getfield      #6                  // Field _currToken:Lcom/fasterxml/jackson/core/JsonToken;
         4: astore_1
         5: aload_1
         6: ifnonnull     13
         9: iconst_0
        10: goto          17
        13: aload_1
        14: invokevirtual #7                  // Method com/fasterxml/jackson/core/JsonToken.id:()I
        17: ireturn
      LineNumberTable:
        line 188: 0
        line 189: 5
      LocalVariableTable:
        Start  Length  Slot  Name   Signature
            0      18     0  this   Lcom/fasterxml/jackson/core/base/ParserMinimalBase;
            5      13     1     t   Lcom/fasterxml/jackson/core/JsonToken;
      StackMapTable: number_of_entries = 2
        frame_type = 252 /* append */
          offset_delta = 13
          locals = [ class com/fasterxml/jackson/core/JsonToken ]
        frame_type = 67 /* same_locals_1_stack_item */
          stack = [ int ]

  public com.fasterxml.jackson.core.JsonToken getCurrentToken();
    descriptor: ()Lcom/fasterxml/jackson/core/JsonToken;
    flags: (0x0001) ACC_PUBLIC
    Code:
      stack=1, locals=1, args_size=1
         0: aload_0
         1: getfield      #6                  // Field _currToken:Lcom/fasterxml/jackson/core/JsonToken;
         4: areturn
      LineNumberTable:
        line 192: 0
      LocalVariableTable:
        Start  Length  Slot  Name   Signature
            0       5     0  this   Lcom/fasterxml/jackson/core/base/ParserMinimalBase;

  public int getCurrentTokenId();
    descriptor: ()I
    flags: (0x0001) ACC_PUBLIC
    Code:
      stack=1, locals=2, args_size=1
         0: aload_0
         1: getfield      #6                  // Field _currToken:Lcom/fasterxml/jackson/core/JsonToken;
         4: astore_1
         5: aload_1
         6: ifnonnull     13
         9: iconst_0
        10: goto          17
        13: aload_1
        14: invokevirtual #7                  // Method com/fasterxml/jackson/core/JsonToken.id:()I
        17: ireturn
      LineNumberTable:
        line 196: 0
        line 197: 5
      LocalVariableTable:
        Start  Length  Slot  Name   Signature
            0      18     0  this   Lcom/fasterxml/jackson/core/base/ParserMinimalBase;
            5      13     1     t   Lcom/fasterxml/jackson/core/JsonToken;
      StackMapTable: number_of_entries = 2
        frame_type = 252 /* append */
          offset_delta = 13
          locals = [ class com/fasterxml/jackson/core/JsonToken ]
        frame_type = 67 /* same_locals_1_stack_item */
          stack = [ int ]
    Deprecated: true
    RuntimeVisibleAnnotations:
      0: #266()
        java.lang.Deprecated

  public boolean hasCurrentToken();
    descriptor: ()Z
    flags: (0x0001) ACC_PUBLIC
    Code:
      stack=1, locals=1, args_size=1
         0: aload_0
         1: getfield      #6                  // Field _currToken:Lcom/fasterxml/jackson/core/JsonToken;
         4: ifnull        11
         7: iconst_1
         8: goto          12
        11: iconst_0
        12: ireturn
      LineNumberTable:
        line 200: 0
      LocalVariableTable:
        Start  Length  Slot  Name   Signature
            0      13     0  this   Lcom/fasterxml/jackson/core/base/ParserMinimalBase;
      StackMapTable: number_of_entries = 2
        frame_type = 11 /* same */
        frame_type = 64 /* same_locals_1_stack_item */
          stack = [ int ]

  public boolean hasTokenId(int);
    descriptor: (I)Z
    flags: (0x0001) ACC_PUBLIC
    Code:
      stack=2, locals=3, args_size=2
         0: aload_0
         1: getfield      #6                  // Field _currToken:Lcom/fasterxml/jackson/core/JsonToken;
         4: astore_2
         5: aload_2
         6: ifnonnull     20
         9: iconst_0
        10: iload_1
        11: if_icmpne     18
        14: iconst_1
        15: goto          19
        18: iconst_0
        19: ireturn
        20: aload_2
        21: invokevirtual #7                  // Method com/fasterxml/jackson/core/JsonToken.id:()I
        24: iload_1
        25: if_icmpne     32
        28: iconst_1
        29: goto          33
        32: iconst_0
        33: ireturn
      LineNumberTable:
        line 202: 0
        line 203: 5
        line 204: 9
        line 206: 20
      LocalVariableTable:
        Start  Length  Slot  Name   Signature
            0      34     0  this   Lcom/fasterxml/jackson/core/base/ParserMinimalBase;
            0      34     1    id   I
            5      29     2     t   Lcom/fasterxml/jackson/core/JsonToken;
      StackMapTable: number_of_entries = 5
        frame_type = 252 /* append */
          offset_delta = 18
          locals = [ class com/fasterxml/jackson/core/JsonToken ]
        frame_type = 64 /* same_locals_1_stack_item */
          stack = [ int ]
        frame_type = 0 /* same */
        frame_type = 11 /* same */
        frame_type = 64 /* same_locals_1_stack_item */
          stack = [ int ]

  public boolean hasToken(com.fasterxml.jackson.core.JsonToken);
    descriptor: (Lcom/fasterxml/jackson/core/JsonToken;)Z
    flags: (0x0001) ACC_PUBLIC
    Code:
      stack=2, locals=2, args_size=2
         0: aload_0
         1: getfield      #6                  // Field _currToken:Lcom/fasterxml/jackson/core/JsonToken;
         4: aload_1
         5: if_acmpne     12
         8: iconst_1
         9: goto          13
        12: iconst_0
        13: ireturn
      LineNumberTable:
        line 210: 0
      LocalVariableTable:
        Start  Length  Slot  Name   Signature
            0      14     0  this   Lcom/fasterxml/jackson/core/base/ParserMinimalBase;
            0      14     1     t   Lcom/fasterxml/jackson/core/JsonToken;
      StackMapTable: number_of_entries = 2
        frame_type = 12 /* same */
        frame_type = 64 /* same_locals_1_stack_item */
          stack = [ int ]

  public boolean isExpectedStartArrayToken();
    descriptor: ()Z
    flags: (0x0001) ACC_PUBLIC
    Code:
      stack=2, locals=1, args_size=1
         0: aload_0
         1: getfield      #6                  // Field _currToken:Lcom/fasterxml/jackson/core/JsonToken;
         4: getstatic     #8                  // Field com/fasterxml/jackson/core/JsonToken.START_ARRAY:Lcom/fasterxml/jackson/core/JsonToken;
         7: if_acmpne     14
        10: iconst_1
        11: goto          15
        14: iconst_0
        15: ireturn
      LineNumberTable:
        line 213: 0
      LocalVariableTable:
        Start  Length  Slot  Name   Signature
            0      16     0  this   Lcom/fasterxml/jackson/core/base/ParserMinimalBase;
      StackMapTable: number_of_entries = 2
        frame_type = 14 /* same */
        frame_type = 64 /* same_locals_1_stack_item */
          stack = [ int ]

  public boolean isExpectedStartObjectToken();
    descriptor: ()Z
    flags: (0x0001) ACC_PUBLIC
    Code:
      stack=2, locals=1, args_size=1
         0: aload_0
         1: getfield      #6                  // Field _currToken:Lcom/fasterxml/jackson/core/JsonToken;
         4: getstatic     #9                  // Field com/fasterxml/jackson/core/JsonToken.START_OBJECT:Lcom/fasterxml/jackson/core/JsonToken;
         7: if_acmpne     14
        10: iconst_1
        11: goto          15
        14: iconst_0
        15: ireturn
      LineNumberTable:
        line 214: 0
      LocalVariableTable:
        Start  Length  Slot  Name   Signature
            0      16     0  this   Lcom/fasterxml/jackson/core/base/ParserMinimalBase;
      StackMapTable: number_of_entries = 2
        frame_type = 14 /* same */
        frame_type = 64 /* same_locals_1_stack_item */
          stack = [ int ]

  public boolean isExpectedNumberIntToken();
    descriptor: ()Z
    flags: (0x0001) ACC_PUBLIC
    Code:
      stack=2, locals=1, args_size=1
         0: aload_0
         1: getfield      #6                  // Field _currToken:Lcom/fasterxml/jackson/core/JsonToken;
         4: getstatic     #10                 // Field com/fasterxml/jackson/core/JsonToken.VALUE_NUMBER_INT:Lcom/fasterxml/jackson/core/JsonToken;
         7: if_acmpne     14
        10: iconst_1
        11: goto          15
        14: iconst_0
        15: ireturn
      LineNumberTable:
        line 215: 0
      LocalVariableTable:
        Start  Length  Slot  Name   Signature
            0      16     0  this   Lcom/fasterxml/jackson/core/base/ParserMinimalBase;
      StackMapTable: number_of_entries = 2
        frame_type = 14 /* same */
        frame_type = 64 /* same_locals_1_stack_item */
          stack = [ int ]

  public com.fasterxml.jackson.core.JsonToken nextValue() throws java.io.IOException;
    descriptor: ()Lcom/fasterxml/jackson/core/JsonToken;
    flags: (0x0001) ACC_PUBLIC
    Code:
      stack=2, locals=2, args_size=1
         0: aload_0
         1: invokevirtual #11                 // Method nextToken:()Lcom/fasterxml/jackson/core/JsonToken;
         4: astore_1
         5: aload_1
         6: getstatic     #12                 // Field com/fasterxml/jackson/core/JsonToken.FIELD_NAME:Lcom/fasterxml/jackson/core/JsonToken;
         9: if_acmpne     17
        12: aload_0
        13: invokevirtual #11                 // Method nextToken:()Lcom/fasterxml/jackson/core/JsonToken;
        16: astore_1
        17: aload_1
        18: areturn
      LineNumberTable:
        line 221: 0
        line 222: 5
        line 223: 12
        line 225: 17
      LocalVariableTable:
        Start  Length  Slot  Name   Signature
            0      19     0  this   Lcom/fasterxml/jackson/core/base/ParserMinimalBase;
            5      14     1     t   Lcom/fasterxml/jackson/core/JsonToken;
      StackMapTable: number_of_entries = 1
        frame_type = 252 /* append */
          offset_delta = 17
          locals = [ class com/fasterxml/jackson/core/JsonToken ]
    Exceptions:
      throws java.io.IOException

  public com.fasterxml.jackson.core.JsonParser skipChildren() throws java.io.IOException;
    descriptor: ()Lcom/fasterxml/jackson/core/JsonParser;
    flags: (0x0001) ACC_PUBLIC
    Code:
      stack=3, locals=3, args_size=1
         0: aload_0
         1: getfield      #6                  // Field _currToken:Lcom/fasterxml/jackson/core/JsonToken;
         4: getstatic     #9                  // Field com/fasterxml/jackson/core/JsonToken.START_OBJECT:Lcom/fasterxml/jackson/core/JsonToken;
         7: if_acmpeq     22
        10: aload_0
        11: getfield      #6                  // Field _currToken:Lcom/fasterxml/jackson/core/JsonToken;
        14: getstatic     #8                  // Field com/fasterxml/jackson/core/JsonToken.START_ARRAY:Lcom/fasterxml/jackson/core/JsonToken;
        17: if_acmpeq     22
        20: aload_0
        21: areturn
        22: iconst_1
        23: istore_1
        24: aload_0
        25: invokevirtual #11                 // Method nextToken:()Lcom/fasterxml/jackson/core/JsonToken;
        28: astore_2
        29: aload_2
        30: ifnonnull     39
        33: aload_0
        34: invokevirtual #13                 // Method _handleEOF:()V
        37: aload_0
        38: areturn
        39: aload_2
        40: invokevirtual #14                 // Method com/fasterxml/jackson/core/JsonToken.isStructStart:()Z
        43: ifeq          52
        46: iinc          1, 1
        49: goto          88
        52: aload_2
        53: invokevirtual #15                 // Method com/fasterxml/jackson/core/JsonToken.isStructEnd:()Z
        56: ifeq          68
        59: iinc          1, -1
        62: iload_1
        63: ifne          88
        66: aload_0
        67: areturn
        68: aload_2
        69: getstatic     #16                 // Field com/fasterxml/jackson/core/JsonToken.NOT_AVAILABLE:Lcom/fasterxml/jackson/core/JsonToken;
        72: if_acmpne     88
        75: aload_0
        76: ldc           #17                 // String Not enough content available for `skipChildren()`: non-blocking parser? (%s)
        78: aload_0
        79: invokevirtual #18                 // Method java/lang/Object.getClass:()Ljava/lang/Class;
        82: invokevirtual #19                 // Method java/lang/Class.getName:()Ljava/lang/String;
        85: invokevirtual #20                 // Method _reportError:(Ljava/lang/String;Ljava/lang/Object;)V
        88: goto          24
      LineNumberTable:
        line 231: 0
        line 233: 20
        line 235: 22
        line 240: 24
        line 241: 29
        line 242: 33
        line 247: 37
        line 249: 39
        line 250: 46
        line 251: 52
        line 252: 59
        line 253: 66
        line 256: 68
        line 259: 75
        line 260: 79
        line 259: 85
        line 262: 88
      LocalVariableTable:
        Start  Length  Slot  Name   Signature
           29      59     2     t   Lcom/fasterxml/jackson/core/JsonToken;
            0      91     0  this   Lcom/fasterxml/jackson/core/base/ParserMinimalBase;
           24      67     1  open   I
      StackMapTable: number_of_entries = 6
        frame_type = 22 /* same */
        frame_type = 252 /* append */
          offset_delta = 1
          locals = [ int ]
        frame_type = 252 /* append */
          offset_delta = 14
          locals = [ class com/fasterxml/jackson/core/JsonToken ]
        frame_type = 12 /* same */
        frame_type = 15 /* same */
        frame_type = 250 /* chop */
          offset_delta = 19
    Exceptions:
      throws java.io.IOException

  protected abstract void _handleEOF() throws com.fasterxml.jackson.core.JsonParseException;
    descriptor: ()V
    flags: (0x0404) ACC_PROTECTED, ACC_ABSTRACT
    Exceptions:
      throws com.fasterxml.jackson.core.JsonParseException

  public abstract java.lang.String getCurrentName() throws java.io.IOException;
    descriptor: ()Ljava/lang/String;
    flags: (0x0401) ACC_PUBLIC, ACC_ABSTRACT
    Exceptions:
      throws java.io.IOException

  public abstract void close() throws java.io.IOException;
    descriptor: ()V
    flags: (0x0401) ACC_PUBLIC, ACC_ABSTRACT
    Exceptions:
      throws java.io.IOException

  public abstract boolean isClosed();
    descriptor: ()Z
    flags: (0x0401) ACC_PUBLIC, ACC_ABSTRACT

  public abstract com.fasterxml.jackson.core.JsonStreamContext getParsingContext();
    descriptor: ()Lcom/fasterxml/jackson/core/JsonStreamContext;
    flags: (0x0401) ACC_PUBLIC, ACC_ABSTRACT

  public void clearCurrentToken();
    descriptor: ()V
    flags: (0x0001) ACC_PUBLIC
    Code:
      stack=2, locals=1, args_size=1
         0: aload_0
         1: getfield      #6                  // Field _currToken:Lcom/fasterxml/jackson/core/JsonToken;
         4: ifnull        20
         7: aload_0
         8: aload_0
         9: getfield      #6                  // Field _currToken:Lcom/fasterxml/jackson/core/JsonToken;
        12: putfield      #21                 // Field _lastClearedToken:Lcom/fasterxml/jackson/core/JsonToken;
        15: aload_0
        16: aconst_null
        17: putfield      #6                  // Field _currToken:Lcom/fasterxml/jackson/core/JsonToken;
        20: return
      LineNumberTable:
        line 294: 0
        line 295: 7
        line 296: 15
        line 298: 20
      LocalVariableTable:
        Start  Length  Slot  Name   Signature
            0      21     0  this   Lcom/fasterxml/jackson/core/base/ParserMinimalBase;
      StackMapTable: number_of_entries = 1
        frame_type = 20 /* same */

  public com.fasterxml.jackson.core.JsonToken getLastClearedToken();
    descriptor: ()Lcom/fasterxml/jackson/core/JsonToken;
    flags: (0x0001) ACC_PUBLIC
    Code:
      stack=1, locals=1, args_size=1
         0: aload_0
         1: getfield      #21                 // Field _lastClearedToken:Lcom/fasterxml/jackson/core/JsonToken;
         4: areturn
      LineNumberTable:
        line 300: 0
      LocalVariableTable:
        Start  Length  Slot  Name   Signature
            0       5     0  this   Lcom/fasterxml/jackson/core/base/ParserMinimalBase;

  public abstract void overrideCurrentName(java.lang.String);
    descriptor: (Ljava/lang/String;)V
    flags: (0x0401) ACC_PUBLIC, ACC_ABSTRACT

  public abstract java.lang.String getText() throws java.io.IOException;
    descriptor: ()Ljava/lang/String;
    flags: (0x0401) ACC_PUBLIC, ACC_ABSTRACT
    Exceptions:
      throws java.io.IOException

  public abstract char[] getTextCharacters() throws java.io.IOException;
    descriptor: ()[C
    flags: (0x0401) ACC_PUBLIC, ACC_ABSTRACT
    Exceptions:
      throws java.io.IOException

  public abstract boolean hasTextCharacters();
    descriptor: ()Z
    flags: (0x0401) ACC_PUBLIC, ACC_ABSTRACT

  public abstract int getTextLength() throws java.io.IOException;
    descriptor: ()I
    flags: (0x0401) ACC_PUBLIC, ACC_ABSTRACT
    Exceptions:
      throws java.io.IOException

  public abstract int getTextOffset() throws java.io.IOException;
    descriptor: ()I
    flags: (0x0401) ACC_PUBLIC, ACC_ABSTRACT
    Exceptions:
      throws java.io.IOException

  public abstract byte[] getBinaryValue(com.fasterxml.jackson.core.Base64Variant) throws java.io.IOException;
    descriptor: (Lcom/fasterxml/jackson/core/Base64Variant;)[B
    flags: (0x0401) ACC_PUBLIC, ACC_ABSTRACT
    Exceptions:
      throws java.io.IOException

  public boolean getValueAsBoolean(boolean) throws java.io.IOException;
    descriptor: (Z)Z
    flags: (0x0001) ACC_PUBLIC
    Code:
      stack=2, locals=5, args_size=2
         0: aload_0
         1: getfield      #6                  // Field _currToken:Lcom/fasterxml/jackson/core/JsonToken;
         4: astore_2
         5: aload_2
         6: ifnull        136
         9: aload_2
        10: invokevirtual #7                  // Method com/fasterxml/jackson/core/JsonToken.id:()I
        13: tableswitch   { // 6 to 12
                       6: 56
                       7: 96
                       8: 136
                       9: 109
                      10: 111
                      11: 111
                      12: 113
                 default: 136
            }
        56: aload_0
        57: invokevirtual #22                 // Method getText:()Ljava/lang/String;
        60: invokevirtual #23                 // Method java/lang/String.trim:()Ljava/lang/String;
        63: astore_3
        64: ldc           #24                 // String true
        66: aload_3
        67: invokevirtual #25                 // Method java/lang/String.equals:(Ljava/lang/Object;)Z
        70: ifeq          75
        73: iconst_1
        74: ireturn
        75: ldc           #26                 // String false
        77: aload_3
        78: invokevirtual #25                 // Method java/lang/String.equals:(Ljava/lang/Object;)Z
        81: ifeq          86
        84: iconst_0
        85: ireturn
        86: aload_0
        87: aload_3
        88: invokevirtual #27                 // Method _hasTextualNull:(Ljava/lang/String;)Z
        91: ifeq          136
        94: iconst_0
        95: ireturn
        96: aload_0
        97: invokevirtual #28                 // Method getIntValue:()I
       100: ifeq          107
       103: iconst_1
       104: goto          108
       107: iconst_0
       108: ireturn
       109: iconst_1
       110: ireturn
       111: iconst_0
       112: ireturn
       113: aload_0
       114: invokevirtual #29                 // Method getEmbeddedObject:()Ljava/lang/Object;
       117: astore        4
       119: aload         4
       121: instanceof    #30                 // class java/lang/Boolean
       124: ifeq          136
       127: aload         4
       129: checkcast     #30                 // class java/lang/Boolean
       132: invokevirtual #31                 // Method java/lang/Boolean.booleanValue:()Z
       135: ireturn
       136: iload_1
       137: ireturn
      LineNumberTable:
        line 333: 0
        line 334: 5
        line 335: 9
        line 337: 56
        line 338: 64
        line 339: 73
        line 341: 75
        line 342: 84
        line 344: 86
        line 345: 94
        line 349: 96
        line 351: 109
        line 354: 111
        line 356: 113
        line 357: 119
        line 358: 127
        line 364: 136
      LocalVariableTable:
        Start  Length  Slot  Name   Signature
           64      32     3   str   Ljava/lang/String;
          119      17     4 value   Ljava/lang/Object;
            0     138     0  this   Lcom/fasterxml/jackson/core/base/ParserMinimalBase;
            0     138     1 defaultValue   Z
            5     133     2     t   Lcom/fasterxml/jackson/core/JsonToken;
      StackMapTable: number_of_entries = 10
        frame_type = 252 /* append */
          offset_delta = 56
          locals = [ class com/fasterxml/jackson/core/JsonToken ]
        frame_type = 252 /* append */
          offset_delta = 18
          locals = [ class java/lang/String ]
        frame_type = 10 /* same */
        frame_type = 250 /* chop */
          offset_delta = 9
        frame_type = 10 /* same */
        frame_type = 64 /* same_locals_1_stack_item */
          stack = [ int ]
        frame_type = 0 /* same */
        frame_type = 1 /* same */
        frame_type = 1 /* same */
        frame_type = 22 /* same */
    Exceptions:
      throws java.io.IOException

  public int getValueAsInt() throws java.io.IOException;
    descriptor: ()I
    flags: (0x0001) ACC_PUBLIC
    Code:
      stack=2, locals=2, args_size=1
         0: aload_0
         1: getfield      #6                  // Field _currToken:Lcom/fasterxml/jackson/core/JsonToken;
         4: astore_1
         5: aload_1
         6: getstatic     #10                 // Field com/fasterxml/jackson/core/JsonToken.VALUE_NUMBER_INT:Lcom/fasterxml/jackson/core/JsonToken;
         9: if_acmpeq     19
        12: aload_1
        13: getstatic     #32                 // Field com/fasterxml/jackson/core/JsonToken.VALUE_NUMBER_FLOAT:Lcom/fasterxml/jackson/core/JsonToken;
        16: if_acmpne     24
        19: aload_0
        20: invokevirtual #28                 // Method getIntValue:()I
        23: ireturn
        24: aload_0
        25: iconst_0
        26: invokevirtual #33                 // Method getValueAsInt:(I)I
        29: ireturn
      LineNumberTable:
        line 370: 0
        line 371: 5
        line 372: 19
        line 374: 24
      LocalVariableTable:
        Start  Length  Slot  Name   Signature
            0      30     0  this   Lcom/fasterxml/jackson/core/base/ParserMinimalBase;
            5      25     1     t   Lcom/fasterxml/jackson/core/JsonToken;
      StackMapTable: number_of_entries = 2
        frame_type = 252 /* append */
          offset_delta = 19
          locals = [ class com/fasterxml/jackson/core/JsonToken ]
        frame_type = 4 /* same */
    Exceptions:
      throws java.io.IOException

  public int getValueAsInt(int) throws java.io.IOException;
    descriptor: (I)I
    flags: (0x0001) ACC_PUBLIC
    Code:
      stack=2, locals=5, args_size=2
         0: aload_0
         1: getfield      #6                  // Field _currToken:Lcom/fasterxml/jackson/core/JsonToken;
         4: astore_2
         5: aload_2
         6: getstatic     #10                 // Field com/fasterxml/jackson/core/JsonToken.VALUE_NUMBER_INT:Lcom/fasterxml/jackson/core/JsonToken;
         9: if_acmpeq     19
        12: aload_2
        13: getstatic     #32                 // Field com/fasterxml/jackson/core/JsonToken.VALUE_NUMBER_FLOAT:Lcom/fasterxml/jackson/core/JsonToken;
        16: if_acmpne     24
        19: aload_0
        20: invokevirtual #28                 // Method getIntValue:()I
        23: ireturn
        24: aload_2
        25: ifnull        126
        28: aload_2
        29: invokevirtual #7                  // Method com/fasterxml/jackson/core/JsonToken.id:()I
        32: tableswitch   { // 6 to 12
                       6: 76
                       7: 126
                       8: 126
                       9: 97
                      10: 99
                      11: 101
                      12: 103
                 default: 126
            }
        76: aload_0
        77: invokevirtual #22                 // Method getText:()Ljava/lang/String;
        80: astore_3
        81: aload_0
        82: aload_3
        83: invokevirtual #27                 // Method _hasTextualNull:(Ljava/lang/String;)Z
        86: ifeq          91
        89: iconst_0
        90: ireturn
        91: aload_3
        92: iload_1
        93: invokestatic  #34                 // Method com/fasterxml/jackson/core/io/NumberInput.parseAsInt:(Ljava/lang/String;I)I
        96: ireturn
        97: iconst_1
        98: ireturn
        99: iconst_0
       100: ireturn
       101: iconst_0
       102: ireturn
       103: aload_0
       104: invokevirtual #29                 // Method getEmbeddedObject:()Ljava/lang/Object;
       107: astore        4
       109: aload         4
       111: instanceof    #35                 // class java/lang/Number
       114: ifeq          126
       117: aload         4
       119: checkcast     #35                 // class java/lang/Number
       122: invokevirtual #36                 // Method java/lang/Number.intValue:()I
       125: ireturn
       126: iload_1
       127: ireturn
      LineNumberTable:
        line 380: 0
        line 381: 5
        line 382: 19
        line 384: 24
        line 385: 28
        line 387: 76
        line 388: 81
        line 389: 89
        line 391: 91
        line 393: 97
        line 395: 99
        line 397: 101
        line 399: 103
        line 400: 109
        line 401: 117
        line 405: 126
      LocalVariableTable:
        Start  Length  Slot  Name   Signature
           81      16     3   str   Ljava/lang/String;
          109      17     4 value   Ljava/lang/Object;
            0     128     0  this   Lcom/fasterxml/jackson/core/base/ParserMinimalBase;
            0     128     1 defaultValue   I
            5     123     2     t   Lcom/fasterxml/jackson/core/JsonToken;
      StackMapTable: number_of_entries = 9
        frame_type = 252 /* append */
          offset_delta = 19
          locals = [ class com/fasterxml/jackson/core/JsonToken ]
        frame_type = 4 /* same */
        frame_type = 51 /* same */
        frame_type = 252 /* append */
          offset_delta = 14
          locals = [ class java/lang/String ]
        frame_type = 250 /* chop */
          offset_delta = 5
        frame_type = 1 /* same */
        frame_type = 1 /* same */
        frame_type = 1 /* same */
        frame_type = 22 /* same */
    Exceptions:
      throws java.io.IOException

  public long getValueAsLong() throws java.io.IOException;
    descriptor: ()J
    flags: (0x0001) ACC_PUBLIC
    Code:
      stack=3, locals=2, args_size=1
         0: aload_0
         1: getfield      #6                  // Field _currToken:Lcom/fasterxml/jackson/core/JsonToken;
         4: astore_1
         5: aload_1
         6: getstatic     #10                 // Field com/fasterxml/jackson/core/JsonToken.VALUE_NUMBER_INT:Lcom/fasterxml/jackson/core/JsonToken;
         9: if_acmpeq     19
        12: aload_1
        13: getstatic     #32                 // Field com/fasterxml/jackson/core/JsonToken.VALUE_NUMBER_FLOAT:Lcom/fasterxml/jackson/core/JsonToken;
        16: if_acmpne     24
        19: aload_0
        20: invokevirtual #37                 // Method getLongValue:()J
        23: lreturn
        24: aload_0
        25: lconst_0
        26: invokevirtual #38                 // Method getValueAsLong:(J)J
        29: lreturn
      LineNumberTable:
        line 411: 0
        line 412: 5
        line 413: 19
        line 415: 24
      LocalVariableTable:
        Start  Length  Slot  Name   Signature
            0      30     0  this   Lcom/fasterxml/jackson/core/base/ParserMinimalBase;
            5      25     1     t   Lcom/fasterxml/jackson/core/JsonToken;
      StackMapTable: number_of_entries = 2
        frame_type = 252 /* append */
          offset_delta = 19
          locals = [ class com/fasterxml/jackson/core/JsonToken ]
        frame_type = 4 /* same */
    Exceptions:
      throws java.io.IOException

  public long getValueAsLong(long) throws java.io.IOException;
    descriptor: (J)J
    flags: (0x0001) ACC_PUBLIC
    Code:
      stack=3, locals=6, args_size=2
         0: aload_0
         1: getfield      #6                  // Field _currToken:Lcom/fasterxml/jackson/core/JsonToken;
         4: astore_3
         5: aload_3
         6: getstatic     #10                 // Field com/fasterxml/jackson/core/JsonToken.VALUE_NUMBER_INT:Lcom/fasterxml/jackson/core/JsonToken;
         9: if_acmpeq     19
        12: aload_3
        13: getstatic     #32                 // Field com/fasterxml/jackson/core/JsonToken.VALUE_NUMBER_FLOAT:Lcom/fasterxml/jackson/core/JsonToken;
        16: if_acmpne     24
        19: aload_0
        20: invokevirtual #37                 // Method getLongValue:()J
        23: lreturn
        24: aload_3
        25: ifnull        127
        28: aload_3
        29: invokevirtual #7                  // Method com/fasterxml/jackson/core/JsonToken.id:()I
        32: tableswitch   { // 6 to 12
                       6: 76
                       7: 127
                       8: 127
                       9: 100
                      10: 102
                      11: 102
                      12: 104
                 default: 127
            }
        76: aload_0
        77: invokevirtual #22                 // Method getText:()Ljava/lang/String;
        80: astore        4
        82: aload_0
        83: aload         4
        85: invokevirtual #27                 // Method _hasTextualNull:(Ljava/lang/String;)Z
        88: ifeq          93
        91: lconst_0
        92: lreturn
        93: aload         4
        95: lload_1
        96: invokestatic  #39                 // Method com/fasterxml/jackson/core/io/NumberInput.parseAsLong:(Ljava/lang/String;J)J
        99: lreturn
       100: lconst_1
       101: lreturn
       102: lconst_0
       103: lreturn
       104: aload_0
       105: invokevirtual #29                 // Method getEmbeddedObject:()Ljava/lang/Object;
       108: astore        5
       110: aload         5
       112: instanceof    #35                 // class java/lang/Number
       115: ifeq          127
       118: aload         5
       120: checkcast     #35                 // class java/lang/Number
       123: invokevirtual #40                 // Method java/lang/Number.longValue:()J
       126: lreturn
       127: lload_1
       128: lreturn
      LineNumberTable:
        line 421: 0
        line 422: 5
        line 423: 19
        line 425: 24
        line 426: 28
        line 428: 76
        line 429: 82
        line 430: 91
        line 432: 93
        line 434: 100
        line 437: 102
        line 439: 104
        line 440: 110
        line 441: 118
        line 445: 127
      LocalVariableTable:
        Start  Length  Slot  Name   Signature
           82      18     4   str   Ljava/lang/String;
          110      17     5 value   Ljava/lang/Object;
            0     129     0  this   Lcom/fasterxml/jackson/core/base/ParserMinimalBase;
            0     129     1 defaultValue   J
            5     124     3     t   Lcom/fasterxml/jackson/core/JsonToken;
      StackMapTable: number_of_entries = 8
        frame_type = 252 /* append */
          offset_delta = 19
          locals = [ class com/fasterxml/jackson/core/JsonToken ]
        frame_type = 4 /* same */
        frame_type = 51 /* same */
        frame_type = 252 /* append */
          offset_delta = 16
          locals = [ class java/lang/String ]
        frame_type = 250 /* chop */
          offset_delta = 6
        frame_type = 1 /* same */
        frame_type = 1 /* same */
        frame_type = 22 /* same */
    Exceptions:
      throws java.io.IOException

  public double getValueAsDouble(double) throws java.io.IOException;
    descriptor: (D)D
    flags: (0x0001) ACC_PUBLIC
    Code:
      stack=3, locals=6, args_size=2
         0: aload_0
         1: getfield      #6                  // Field _currToken:Lcom/fasterxml/jackson/core/JsonToken;
         4: astore_3
         5: aload_3
         6: ifnull        112
         9: aload_3
        10: invokevirtual #7                  // Method com/fasterxml/jackson/core/JsonToken.id:()I
        13: tableswitch   { // 6 to 12
                       6: 56
                       7: 80
                       8: 80
                       9: 85
                      10: 87
                      11: 87
                      12: 89
                 default: 112
            }
        56: aload_0
        57: invokevirtual #22                 // Method getText:()Ljava/lang/String;
        60: astore        4
        62: aload_0
        63: aload         4
        65: invokevirtual #27                 // Method _hasTextualNull:(Ljava/lang/String;)Z
        68: ifeq          73
        71: dconst_0
        72: dreturn
        73: aload         4
        75: dload_1
        76: invokestatic  #41                 // Method com/fasterxml/jackson/core/io/NumberInput.parseAsDouble:(Ljava/lang/String;D)D
        79: dreturn
        80: aload_0
        81: invokevirtual #42                 // Method getDoubleValue:()D
        84: dreturn
        85: dconst_1
        86: dreturn
        87: dconst_0
        88: dreturn
        89: aload_0
        90: invokevirtual #29                 // Method getEmbeddedObject:()Ljava/lang/Object;
        93: astore        5
        95: aload         5
        97: instanceof    #35                 // class java/lang/Number
       100: ifeq          112
       103: aload         5
       105: checkcast     #35                 // class java/lang/Number
       108: invokevirtual #43                 // Method java/lang/Number.doubleValue:()D
       111: dreturn
       112: dload_1
       113: dreturn
      LineNumberTable:
        line 451: 0
        line 452: 5
        line 453: 9
        line 455: 56
        line 456: 62
        line 457: 71
        line 459: 73
        line 462: 80
        line 464: 85
        line 467: 87
        line 469: 89
        line 470: 95
        line 471: 103
        line 475: 112
      LocalVariableTable:
        Start  Length  Slot  Name   Signature
           62      18     4   str   Ljava/lang/String;
           95      17     5 value   Ljava/lang/Object;
            0     114     0  this   Lcom/fasterxml/jackson/core/base/ParserMinimalBase;
            0     114     1 defaultValue   D
            5     109     3     t   Lcom/fasterxml/jackson/core/JsonToken;
      StackMapTable: number_of_entries = 7
        frame_type = 252 /* append */
          offset_delta = 56
          locals = [ class com/fasterxml/jackson/core/JsonToken ]
        frame_type = 252 /* append */
          offset_delta = 16
          locals = [ class java/lang/String ]
        frame_type = 250 /* chop */
          offset_delta = 6
        frame_type = 4 /* same */
        frame_type = 1 /* same */
        frame_type = 1 /* same */
        frame_type = 22 /* same */
    Exceptions:
      throws java.io.IOException

  public java.lang.String getValueAsString() throws java.io.IOException;
    descriptor: ()Ljava/lang/String;
    flags: (0x0001) ACC_PUBLIC
    Code:
      stack=2, locals=1, args_size=1
         0: aload_0
         1: aconst_null
         2: invokevirtual #44                 // Method getValueAsString:(Ljava/lang/String;)Ljava/lang/String;
         5: areturn
      LineNumberTable:
        line 481: 0
      LocalVariableTable:
        Start  Length  Slot  Name   Signature
            0       6     0  this   Lcom/fasterxml/jackson/core/base/ParserMinimalBase;
    Exceptions:
      throws java.io.IOException

  public java.lang.String getValueAsString(java.lang.String) throws java.io.IOException;
    descriptor: (Ljava/lang/String;)Ljava/lang/String;
    flags: (0x0001) ACC_PUBLIC
    Code:
      stack=2, locals=2, args_size=2
         0: aload_0
         1: getfield      #6                  // Field _currToken:Lcom/fasterxml/jackson/core/JsonToken;
         4: getstatic     #45                 // Field com/fasterxml/jackson/core/JsonToken.VALUE_STRING:Lcom/fasterxml/jackson/core/JsonToken;
         7: if_acmpne     15
        10: aload_0
        11: invokevirtual #22                 // Method getText:()Ljava/lang/String;
        14: areturn
        15: aload_0
        16: getfield      #6                  // Field _currToken:Lcom/fasterxml/jackson/core/JsonToken;
        19: getstatic     #12                 // Field com/fasterxml/jackson/core/JsonToken.FIELD_NAME:Lcom/fasterxml/jackson/core/JsonToken;
        22: if_acmpne     30
        25: aload_0
        26: invokevirtual #46                 // Method getCurrentName:()Ljava/lang/String;
        29: areturn
        30: aload_0
        31: getfield      #6                  // Field _currToken:Lcom/fasterxml/jackson/core/JsonToken;
        34: ifnull        57
        37: aload_0
        38: getfield      #6                  // Field _currToken:Lcom/fasterxml/jackson/core/JsonToken;
        41: getstatic     #47                 // Field com/fasterxml/jackson/core/JsonToken.VALUE_NULL:Lcom/fasterxml/jackson/core/JsonToken;
        44: if_acmpeq     57
        47: aload_0
        48: getfield      #6                  // Field _currToken:Lcom/fasterxml/jackson/core/JsonToken;
        51: invokevirtual #48                 // Method com/fasterxml/jackson/core/JsonToken.isScalarValue:()Z
        54: ifne          59
        57: aload_1
        58: areturn
        59: aload_0
        60: invokevirtual #22                 // Method getText:()Ljava/lang/String;
        63: areturn
      LineNumberTable:
        line 486: 0
        line 487: 10
        line 489: 15
        line 490: 25
        line 492: 30
        line 493: 57
        line 495: 59
      LocalVariableTable:
        Start  Length  Slot  Name   Signature
            0      64     0  this   Lcom/fasterxml/jackson/core/base/ParserMinimalBase;
            0      64     1 defaultValue   Ljava/lang/String;
      StackMapTable: number_of_entries = 4
        frame_type = 15 /* same */
        frame_type = 14 /* same */
        frame_type = 26 /* same */
        frame_type = 1 /* same */
    Exceptions:
      throws java.io.IOException

  protected void _decodeBase64(java.lang.String, com.fasterxml.jackson.core.util.ByteArrayBuilder, com.fasterxml.jackson.core.Base64Variant) throws java.io.IOException;
    descriptor: (Ljava/lang/String;Lcom/fasterxml/jackson/core/util/ByteArrayBuilder;Lcom/fasterxml/jackson/core/Base64Variant;)V
    flags: (0x0004) ACC_PROTECTED
    Code:
      stack=3, locals=5, args_size=4
         0: aload_3
         1: aload_1
         2: aload_2
         3: invokevirtual #49                 // Method com/fasterxml/jackson/core/Base64Variant.decode:(Ljava/lang/String;Lcom/fasterxml/jackson/core/util/ByteArrayBuilder;)V
         6: goto          20
         9: astore        4
        11: aload_0
        12: aload         4
        14: invokevirtual #51                 // Method java/lang/IllegalArgumentException.getMessage:()Ljava/lang/String;
        17: invokevirtual #52                 // Method _reportError:(Ljava/lang/String;)V
        20: return
      Exception table:
         from    to  target type
             0     6     9   Class java/lang/IllegalArgumentException
      LineNumberTable:
        line 518: 0
        line 521: 6
        line 519: 9
        line 520: 11
        line 522: 20
      LocalVariableTable:
        Start  Length  Slot  Name   Signature
           11       9     4     e   Ljava/lang/IllegalArgumentException;
            0      21     0  this   Lcom/fasterxml/jackson/core/base/ParserMinimalBase;
            0      21     1   str   Ljava/lang/String;
            0      21     2 builder   Lcom/fasterxml/jackson/core/util/ByteArrayBuilder;
            0      21     3 b64variant   Lcom/fasterxml/jackson/core/Base64Variant;
      StackMapTable: number_of_entries = 2
        frame_type = 73 /* same_locals_1_stack_item */
          stack = [ class java/lang/IllegalArgumentException ]
        frame_type = 10 /* same */
    Exceptions:
      throws java.io.IOException

  protected boolean _hasTextualNull(java.lang.String);
    descriptor: (Ljava/lang/String;)Z
    flags: (0x0004) ACC_PROTECTED
    Code:
      stack=2, locals=2, args_size=2
         0: ldc           #53                 // String null
         2: aload_1
         3: invokevirtual #25                 // Method java/lang/String.equals:(Ljava/lang/Object;)Z
         6: ireturn
      LineNumberTable:
        line 544: 0
      LocalVariableTable:
        Start  Length  Slot  Name   Signature
            0       7     0  this   Lcom/fasterxml/jackson/core/base/ParserMinimalBase;
            0       7     1 value   Ljava/lang/String;

  protected void reportUnexpectedNumberChar(int, java.lang.String) throws com.fasterxml.jackson.core.JsonParseException;
    descriptor: (ILjava/lang/String;)V
    flags: (0x0004) ACC_PROTECTED
    Code:
      stack=5, locals=4, args_size=3
         0: ldc           #54                 // String Unexpected character (%s) in numeric value
         2: iconst_1
         3: anewarray     #55                 // class java/lang/Object
         6: dup
         7: iconst_0
         8: iload_1
         9: invokestatic  #56                 // Method _getCharDesc:(I)Ljava/lang/String;
        12: aastore
        13: invokestatic  #57                 // Method java/lang/String.format:(Ljava/lang/String;[Ljava/lang/Object;)Ljava/lang/String;
        16: astore_3
        17: aload_2
        18: ifnull        45
        21: new           #58                 // class java/lang/StringBuilder
        24: dup
        25: invokespecial #59                 // Method java/lang/StringBuilder."<init>":()V
        28: aload_3
        29: invokevirtual #60                 // Method java/lang/StringBuilder.append:(Ljava/lang/String;)Ljava/lang/StringBuilder;
        32: ldc           #61                 // String :
        34: invokevirtual #60                 // Method java/lang/StringBuilder.append:(Ljava/lang/String;)Ljava/lang/StringBuilder;
        37: aload_2
        38: invokevirtual #60                 // Method java/lang/StringBuilder.append:(Ljava/lang/String;)Ljava/lang/StringBuilder;
        41: invokevirtual #62                 // Method java/lang/StringBuilder.toString:()Ljava/lang/String;
        44: astore_3
        45: aload_0
        46: aload_3
        47: invokevirtual #52                 // Method _reportError:(Ljava/lang/String;)V
        50: return
      LineNumberTable:
        line 553: 0
        line 554: 17
        line 555: 21
        line 557: 45
        line 558: 50
      LocalVariableTable:
        Start  Length  Slot  Name   Signature
            0      51     0  this   Lcom/fasterxml/jackson/core/base/ParserMinimalBase;
            0      51     1    ch   I
            0      51     2 comment   Ljava/lang/String;
           17      34     3   msg   Ljava/lang/String;
      StackMapTable: number_of_entries = 1
        frame_type = 252 /* append */
          offset_delta = 45
          locals = [ class java/lang/String ]
    Exceptions:
      throws com.fasterxml.jackson.core.JsonParseException

  protected void reportInvalidNumber(java.lang.String) throws com.fasterxml.jackson.core.JsonParseException;
    descriptor: (Ljava/lang/String;)V
    flags: (0x0004) ACC_PROTECTED
    Code:
      stack=3, locals=2, args_size=2
         0: aload_0
         1: new           #58                 // class java/lang/StringBuilder
         4: dup
         5: invokespecial #59                 // Method java/lang/StringBuilder."<init>":()V
         8: ldc           #63                 // String Invalid numeric value:
        10: invokevirtual #60                 // Method java/lang/StringBuilder.append:(Ljava/lang/String;)Ljava/lang/StringBuilder;
        13: aload_1
        14: invokevirtual #60                 // Method java/lang/StringBuilder.append:(Ljava/lang/String;)Ljava/lang/StringBuilder;
        17: invokevirtual #62                 // Method java/lang/StringBuilder.toString:()Ljava/lang/String;
        20: invokevirtual #52                 // Method _reportError:(Ljava/lang/String;)V
        23: return
      LineNumberTable:
        line 571: 0
        line 572: 23
      LocalVariableTable:
        Start  Length  Slot  Name   Signature
            0      24     0  this   Lcom/fasterxml/jackson/core/base/ParserMinimalBase;
            0      24     1   msg   Ljava/lang/String;
    Exceptions:
      throws com.fasterxml.jackson.core.JsonParseException

  protected void reportOverflowInt() throws java.io.IOException;
    descriptor: ()V
    flags: (0x0004) ACC_PROTECTED
    Code:
      stack=2, locals=1, args_size=1
         0: aload_0
         1: aload_0
         2: invokevirtual #22                 // Method getText:()Ljava/lang/String;
         5: invokevirtual #64                 // Method reportOverflowInt:(Ljava/lang/String;)V
         8: return
      LineNumberTable:
        line 582: 0
        line 583: 8
      LocalVariableTable:
        Start  Length  Slot  Name   Signature
            0       9     0  this   Lcom/fasterxml/jackson/core/base/ParserMinimalBase;
    Exceptions:
      throws java.io.IOException

  protected void reportOverflowInt(java.lang.String) throws java.io.IOException;
    descriptor: (Ljava/lang/String;)V
    flags: (0x0004) ACC_PROTECTED
    Code:
      stack=3, locals=2, args_size=2
         0: aload_0
         1: aload_1
         2: aload_0
         3: invokevirtual #65                 // Method currentToken:()Lcom/fasterxml/jackson/core/JsonToken;
         6: invokevirtual #66                 // Method reportOverflowInt:(Ljava/lang/String;Lcom/fasterxml/jackson/core/JsonToken;)V
         9: return
      LineNumberTable:
        line 587: 0
        line 588: 9
      LocalVariableTable:
        Start  Length  Slot  Name   Signature
            0      10     0  this   Lcom/fasterxml/jackson/core/base/ParserMinimalBase;
            0      10     1 numDesc   Ljava/lang/String;
    Exceptions:
      throws java.io.IOException

  protected void reportOverflowInt(java.lang.String, com.fasterxml.jackson.core.JsonToken) throws java.io.IOException;
    descriptor: (Ljava/lang/String;Lcom/fasterxml/jackson/core/JsonToken;)V
    flags: (0x0004) ACC_PROTECTED
    Code:
      stack=7, locals=3, args_size=3
         0: aload_0
         1: ldc           #67                 // String Numeric value (%s) out of range of int (%d - %s)
         3: iconst_3
         4: anewarray     #55                 // class java/lang/Object
         7: dup
         8: iconst_0
         9: aload_0
        10: aload_1
        11: invokevirtual #68                 // Method _longIntegerDesc:(Ljava/lang/String;)Ljava/lang/String;
        14: aastore
        15: dup
        16: iconst_1
        17: ldc           #69                 // int -2147483648
        19: invokestatic  #70                 // Method java/lang/Integer.valueOf:(I)Ljava/lang/Integer;
        22: aastore
        23: dup
        24: iconst_2
        25: ldc           #71                 // int 2147483647
        27: invokestatic  #70                 // Method java/lang/Integer.valueOf:(I)Ljava/lang/Integer;
        30: aastore
        31: invokestatic  #57                 // Method java/lang/String.format:(Ljava/lang/String;[Ljava/lang/Object;)Ljava/lang/String;
        34: aload_2
        35: getstatic     #72                 // Field java/lang/Integer.TYPE:Ljava/lang/Class;
        38: invokevirtual #73                 // Method _reportInputCoercion:(Ljava/lang/String;Lcom/fasterxml/jackson/core/JsonToken;Ljava/lang/Class;)V
        41: return
      LineNumberTable:
        line 592: 0
        line 593: 11
        line 592: 31
        line 595: 41
      LocalVariableTable:
        Start  Length  Slot  Name   Signature
            0      42     0  this   Lcom/fasterxml/jackson/core/base/ParserMinimalBase;
            0      42     1 numDesc   Ljava/lang/String;
            0      42     2 inputType   Lcom/fasterxml/jackson/core/JsonToken;
    Exceptions:
      throws java.io.IOException

  protected void reportOverflowLong() throws java.io.IOException;
    descriptor: ()V
    flags: (0x0004) ACC_PROTECTED
    Code:
      stack=2, locals=1, args_size=1
         0: aload_0
         1: aload_0
         2: invokevirtual #22                 // Method getText:()Ljava/lang/String;
         5: invokevirtual #74                 // Method reportOverflowLong:(Ljava/lang/String;)V
         8: return
      LineNumberTable:
        line 605: 0
        line 606: 8
      LocalVariableTable:
        Start  Length  Slot  Name   Signature
            0       9     0  this   Lcom/fasterxml/jackson/core/base/ParserMinimalBase;
    Exceptions:
      throws java.io.IOException

  protected void reportOverflowLong(java.lang.String) throws java.io.IOException;
    descriptor: (Ljava/lang/String;)V
    flags: (0x0004) ACC_PROTECTED
    Code:
      stack=3, locals=2, args_size=2
         0: aload_0
         1: aload_1
         2: aload_0
         3: invokevirtual #65                 // Method currentToken:()Lcom/fasterxml/jackson/core/JsonToken;
         6: invokevirtual #75                 // Method reportOverflowLong:(Ljava/lang/String;Lcom/fasterxml/jackson/core/JsonToken;)V
         9: return
      LineNumberTable:
        line 610: 0
        line 611: 9
      LocalVariableTable:
        Start  Length  Slot  Name   Signature
            0      10     0  this   Lcom/fasterxml/jackson/core/base/ParserMinimalBase;
            0      10     1 numDesc   Ljava/lang/String;
    Exceptions:
      throws java.io.IOException

  protected void reportOverflowLong(java.lang.String, com.fasterxml.jackson.core.JsonToken) throws java.io.IOException;
    descriptor: (Ljava/lang/String;Lcom/fasterxml/jackson/core/JsonToken;)V
    flags: (0x0004) ACC_PROTECTED
    Code:
      stack=7, locals=3, args_size=3
         0: aload_0
         1: ldc           #76                 // String Numeric value (%s) out of range of long (%d - %s)
         3: iconst_3
         4: anewarray     #55                 // class java/lang/Object
         7: dup
         8: iconst_0
         9: aload_0
        10: aload_1
        11: invokevirtual #68                 // Method _longIntegerDesc:(Ljava/lang/String;)Ljava/lang/String;
        14: aastore
        15: dup
        16: iconst_1
        17: ldc2_w        #77                 // long -9223372036854775808l
        20: invokestatic  #79                 // Method java/lang/Long.valueOf:(J)Ljava/lang/Long;
        23: aastore
        24: dup
        25: iconst_2
        26: ldc2_w        #80                 // long 9223372036854775807l
        29: invokestatic  #79                 // Method java/lang/Long.valueOf:(J)Ljava/lang/Long;
        32: aastore
        33: invokestatic  #57                 // Method java/lang/String.format:(Ljava/lang/String;[Ljava/lang/Object;)Ljava/lang/String;
        36: aload_2
        37: getstatic     #82                 // Field java/lang/Long.TYPE:Ljava/lang/Class;
        40: invokevirtual #73                 // Method _reportInputCoercion:(Ljava/lang/String;Lcom/fasterxml/jackson/core/JsonToken;Ljava/lang/Class;)V
        43: return
      LineNumberTable:
        line 615: 0
        line 616: 11
        line 615: 33
        line 618: 43
      LocalVariableTable:
        Start  Length  Slot  Name   Signature
            0      44     0  this   Lcom/fasterxml/jackson/core/base/ParserMinimalBase;
            0      44     1 numDesc   Ljava/lang/String;
            0      44     2 inputType   Lcom/fasterxml/jackson/core/JsonToken;
    Exceptions:
      throws java.io.IOException

  protected void _reportInputCoercion(java.lang.String, com.fasterxml.jackson.core.JsonToken, java.lang.Class<?>) throws com.fasterxml.jackson.core.exc.InputCoercionException;
    descriptor: (Ljava/lang/String;Lcom/fasterxml/jackson/core/JsonToken;Ljava/lang/Class;)V
    flags: (0x0004) ACC_PROTECTED
    Code:
      stack=6, locals=4, args_size=4
         0: new           #83                 // class com/fasterxml/jackson/core/exc/InputCoercionException
         3: dup
         4: aload_0
         5: aload_1
         6: aload_2
         7: aload_3
         8: invokespecial #84                 // Method com/fasterxml/jackson/core/exc/InputCoercionException."<init>":(Lcom/fasterxml/jackson/core/JsonParser;Ljava/lang/String;Lcom/fasterxml/jackson/core/JsonToken;Ljava/lang/Class;)V
        11: athrow
      LineNumberTable:
        line 623: 0
      LocalVariableTable:
        Start  Length  Slot  Name   Signature
            0      12     0  this   Lcom/fasterxml/jackson/core/base/ParserMinimalBase;
            0      12     1   msg   Ljava/lang/String;
            0      12     2 inputType   Lcom/fasterxml/jackson/core/JsonToken;
            0      12     3 targetType   Ljava/lang/Class;
      LocalVariableTypeTable:
        Start  Length  Slot  Name   Signature
            0      12     3 targetType   Ljava/lang/Class<*>;
    Exceptions:
      throws com.fasterxml.jackson.core.exc.InputCoercionException
    Signature: #347                         // (Ljava/lang/String;Lcom/fasterxml/jackson/core/JsonToken;Ljava/lang/Class<*>;)V

  protected java.lang.String _longIntegerDesc(java.lang.String);
    descriptor: (Ljava/lang/String;)Ljava/lang/String;
    flags: (0x0004) ACC_PROTECTED
    Code:
      stack=5, locals=3, args_size=2
         0: aload_1
         1: invokevirtual #85                 // Method java/lang/String.length:()I
         4: istore_2
         5: iload_2
         6: sipush        1000
         9: if_icmpge     14
        12: aload_1
        13: areturn
        14: aload_1
        15: ldc           #86                 // String -
        17: invokevirtual #87                 // Method java/lang/String.startsWith:(Ljava/lang/String;)Z
        20: ifeq          26
        23: iinc          2, -1
        26: ldc           #88                 // String [Integer with %d digits]
        28: iconst_1
        29: anewarray     #55                 // class java/lang/Object
        32: dup
        33: iconst_0
        34: iload_2
        35: invokestatic  #70                 // Method java/lang/Integer.valueOf:(I)Ljava/lang/Integer;
        38: aastore
        39: invokestatic  #57                 // Method java/lang/String.format:(Ljava/lang/String;[Ljava/lang/Object;)Ljava/lang/String;
        42: areturn
      LineNumberTable:
        line 628: 0
        line 629: 5
        line 630: 12
        line 632: 14
        line 633: 23
        line 635: 26
      LocalVariableTable:
        Start  Length  Slot  Name   Signature
            0      43     0  this   Lcom/fasterxml/jackson/core/base/ParserMinimalBase;
            0      43     1 rawNum   Ljava/lang/String;
            5      38     2 rawLen   I
      StackMapTable: number_of_entries = 2
        frame_type = 252 /* append */
          offset_delta = 14
          locals = [ int ]
        frame_type = 11 /* same */

  protected java.lang.String _longNumberDesc(java.lang.String);
    descriptor: (Ljava/lang/String;)Ljava/lang/String;
    flags: (0x0004) ACC_PROTECTED
    Code:
      stack=5, locals=3, args_size=2
         0: aload_1
         1: invokevirtual #85                 // Method java/lang/String.length:()I
         4: istore_2
         5: iload_2
         6: sipush        1000
         9: if_icmpge     14
        12: aload_1
        13: areturn
        14: aload_1
        15: ldc           #86                 // String -
        17: invokevirtual #87                 // Method java/lang/String.startsWith:(Ljava/lang/String;)Z
        20: ifeq          26
        23: iinc          2, -1
        26: ldc           #89                 // String [number with %d characters]
        28: iconst_1
        29: anewarray     #55                 // class java/lang/Object
        32: dup
        33: iconst_0
        34: iload_2
        35: invokestatic  #70                 // Method java/lang/Integer.valueOf:(I)Ljava/lang/Integer;
        38: aastore
        39: invokestatic  #57                 // Method java/lang/String.format:(Ljava/lang/String;[Ljava/lang/Object;)Ljava/lang/String;
        42: areturn
      LineNumberTable:
        line 640: 0
        line 641: 5
        line 642: 12
        line 644: 14
        line 645: 23
        line 647: 26
      LocalVariableTable:
        Start  Length  Slot  Name   Signature
            0      43     0  this   Lcom/fasterxml/jackson/core/base/ParserMinimalBase;
            0      43     1 rawNum   Ljava/lang/String;
            5      38     2 rawLen   I
      StackMapTable: number_of_entries = 2
        frame_type = 252 /* append */
          offset_delta = 14
          locals = [ int ]
        frame_type = 11 /* same */

  protected void _reportUnexpectedChar(int, java.lang.String) throws com.fasterxml.jackson.core.JsonParseException;
    descriptor: (ILjava/lang/String;)V
    flags: (0x0004) ACC_PROTECTED
    Code:
      stack=5, locals=4, args_size=3
         0: iload_1
         1: ifge          8
         4: aload_0
         5: invokevirtual #90                 // Method _reportInvalidEOF:()V
         8: ldc           #91                 // String Unexpected character (%s)
        10: iconst_1
        11: anewarray     #55                 // class java/lang/Object
        14: dup
        15: iconst_0
        16: iload_1
        17: invokestatic  #56                 // Method _getCharDesc:(I)Ljava/lang/String;
        20: aastore
        21: invokestatic  #57                 // Method java/lang/String.format:(Ljava/lang/String;[Ljava/lang/Object;)Ljava/lang/String;
        24: astore_3
        25: aload_2
        26: ifnull        53
        29: new           #58                 // class java/lang/StringBuilder
        32: dup
        33: invokespecial #59                 // Method java/lang/StringBuilder."<init>":()V
        36: aload_3
        37: invokevirtual #60                 // Method java/lang/StringBuilder.append:(Ljava/lang/String;)Ljava/lang/StringBuilder;
        40: ldc           #61                 // String :
        42: invokevirtual #60                 // Method java/lang/StringBuilder.append:(Ljava/lang/String;)Ljava/lang/StringBuilder;
        45: aload_2
        46: invokevirtual #60                 // Method java/lang/StringBuilder.append:(Ljava/lang/String;)Ljava/lang/StringBuilder;
        49: invokevirtual #62                 // Method java/lang/StringBuilder.toString:()Ljava/lang/String;
        52: astore_3
        53: aload_0
        54: aload_3
        55: invokevirtual #52                 // Method _reportError:(Ljava/lang/String;)V
        58: return
      LineNumberTable:
        line 652: 0
        line 653: 4
        line 655: 8
        line 656: 25
        line 657: 29
        line 659: 53
        line 660: 58
      LocalVariableTable:
        Start  Length  Slot  Name   Signature
            0      59     0  this   Lcom/fasterxml/jackson/core/base/ParserMinimalBase;
            0      59     1    ch   I
            0      59     2 comment   Ljava/lang/String;
           25      34     3   msg   Ljava/lang/String;
      StackMapTable: number_of_entries = 2
        frame_type = 8 /* same */
        frame_type = 252 /* append */
          offset_delta = 44
          locals = [ class java/lang/String ]
    Exceptions:
      throws com.fasterxml.jackson.core.JsonParseException

  protected void _reportInvalidEOF() throws com.fasterxml.jackson.core.JsonParseException;
    descriptor: ()V
    flags: (0x0004) ACC_PROTECTED
    Code:
      stack=3, locals=1, args_size=1
         0: aload_0
         1: new           #58                 // class java/lang/StringBuilder
         4: dup
         5: invokespecial #59                 // Method java/lang/StringBuilder."<init>":()V
         8: ldc           #92                 // String  in
        10: invokevirtual #60                 // Method java/lang/StringBuilder.append:(Ljava/lang/String;)Ljava/lang/StringBuilder;
        13: aload_0
        14: getfield      #6                  // Field _currToken:Lcom/fasterxml/jackson/core/JsonToken;
        17: invokevirtual #93                 // Method java/lang/StringBuilder.append:(Ljava/lang/Object;)Ljava/lang/StringBuilder;
        20: invokevirtual #62                 // Method java/lang/StringBuilder.toString:()Ljava/lang/String;
        23: aload_0
        24: getfield      #6                  // Field _currToken:Lcom/fasterxml/jackson/core/JsonToken;
        27: invokevirtual #94                 // Method _reportInvalidEOF:(Ljava/lang/String;Lcom/fasterxml/jackson/core/JsonToken;)V
        30: return
      LineNumberTable:
        line 663: 0
        line 664: 30
      LocalVariableTable:
        Start  Length  Slot  Name   Signature
            0      31     0  this   Lcom/fasterxml/jackson/core/base/ParserMinimalBase;
    Exceptions:
      throws com.fasterxml.jackson.core.JsonParseException

  protected void _reportInvalidEOFInValue(com.fasterxml.jackson.core.JsonToken) throws com.fasterxml.jackson.core.JsonParseException;
    descriptor: (Lcom/fasterxml/jackson/core/JsonToken;)V
    flags: (0x0004) ACC_PROTECTED
    Code:
      stack=3, locals=3, args_size=2
         0: aload_1
         1: getstatic     #45                 // Field com/fasterxml/jackson/core/JsonToken.VALUE_STRING:Lcom/fasterxml/jackson/core/JsonToken;
         4: if_acmpne     13
         7: ldc           #95                 // String  in a String value
         9: astore_2
        10: goto          36
        13: aload_1
        14: getstatic     #10                 // Field com/fasterxml/jackson/core/JsonToken.VALUE_NUMBER_INT:Lcom/fasterxml/jackson/core/JsonToken;
        17: if_acmpeq     27
        20: aload_1
        21: getstatic     #32                 // Field com/fasterxml/jackson/core/JsonToken.VALUE_NUMBER_FLOAT:Lcom/fasterxml/jackson/core/JsonToken;
        24: if_acmpne     33
        27: ldc           #96                 // String  in a Number value
        29: astore_2
        30: goto          36
        33: ldc           #97                 // String  in a value
        35: astore_2
        36: aload_0
        37: aload_2
        38: aload_1
        39: invokevirtual #94                 // Method _reportInvalidEOF:(Ljava/lang/String;Lcom/fasterxml/jackson/core/JsonToken;)V
        42: return
      LineNumberTable:
        line 669: 0
        line 670: 7
        line 671: 13
        line 673: 27
        line 675: 33
        line 677: 36
        line 678: 42
      LocalVariableTable:
        Start  Length  Slot  Name   Signature
           10       3     2   msg   Ljava/lang/String;
           30       3     2   msg   Ljava/lang/String;
            0      43     0  this   Lcom/fasterxml/jackson/core/base/ParserMinimalBase;
            0      43     1  type   Lcom/fasterxml/jackson/core/JsonToken;
           36       7     2   msg   Ljava/lang/String;
      StackMapTable: number_of_entries = 4
        frame_type = 13 /* same */
        frame_type = 13 /* same */
        frame_type = 5 /* same */
        frame_type = 252 /* append */
          offset_delta = 2
          locals = [ class java/lang/String ]
    Exceptions:
      throws com.fasterxml.jackson.core.JsonParseException

  protected void _reportInvalidEOF(java.lang.String, com.fasterxml.jackson.core.JsonToken) throws com.fasterxml.jackson.core.JsonParseException;
    descriptor: (Ljava/lang/String;Lcom/fasterxml/jackson/core/JsonToken;)V
    flags: (0x0004) ACC_PROTECTED
    Code:
      stack=6, locals=3, args_size=3
         0: new           #98                 // class com/fasterxml/jackson/core/io/JsonEOFException
         3: dup
         4: aload_0
         5: aload_2
         6: new           #58                 // class java/lang/StringBuilder
         9: dup
        10: invokespecial #59                 // Method java/lang/StringBuilder."<init>":()V
        13: ldc           #99                 // String Unexpected end-of-input
        15: invokevirtual #60                 // Method java/lang/StringBuilder.append:(Ljava/lang/String;)Ljava/lang/StringBuilder;
        18: aload_1
        19: invokevirtual #60                 // Method java/lang/StringBuilder.append:(Ljava/lang/String;)Ljava/lang/StringBuilder;
        22: invokevirtual #62                 // Method java/lang/StringBuilder.toString:()Ljava/lang/String;
        25: invokespecial #100                // Method com/fasterxml/jackson/core/io/JsonEOFException."<init>":(Lcom/fasterxml/jackson/core/JsonParser;Lcom/fasterxml/jackson/core/JsonToken;Ljava/lang/String;)V
        28: athrow
      LineNumberTable:
        line 682: 0
      LocalVariableTable:
        Start  Length  Slot  Name   Signature
            0      29     0  this   Lcom/fasterxml/jackson/core/base/ParserMinimalBase;
            0      29     1   msg   Ljava/lang/String;
            0      29     2 currToken   Lcom/fasterxml/jackson/core/JsonToken;
    Exceptions:
      throws com.fasterxml.jackson.core.JsonParseException

  protected void _reportInvalidEOFInValue() throws com.fasterxml.jackson.core.JsonParseException;
    descriptor: ()V
    flags: (0x0004) ACC_PROTECTED
    Code:
      stack=2, locals=1, args_size=1
         0: aload_0
         1: ldc           #97                 // String  in a value
         3: invokevirtual #101                // Method _reportInvalidEOF:(Ljava/lang/String;)V
         6: return
      LineNumberTable:
        line 692: 0
        line 693: 6
      LocalVariableTable:
        Start  Length  Slot  Name   Signature
            0       7     0  this   Lcom/fasterxml/jackson/core/base/ParserMinimalBase;
    Exceptions:
      throws com.fasterxml.jackson.core.JsonParseException
    Deprecated: true
    RuntimeVisibleAnnotations:
      0: #266()
        java.lang.Deprecated

  protected void _reportInvalidEOF(java.lang.String) throws com.fasterxml.jackson.core.JsonParseException;
    descriptor: (Ljava/lang/String;)V
    flags: (0x0004) ACC_PROTECTED
    Code:
      stack=6, locals=2, args_size=2
         0: new           #98                 // class com/fasterxml/jackson/core/io/JsonEOFException
         3: dup
         4: aload_0
         5: aconst_null
         6: new           #58                 // class java/lang/StringBuilder
         9: dup
        10: invokespecial #59                 // Method java/lang/StringBuilder."<init>":()V
        13: ldc           #99                 // String Unexpected end-of-input
        15: invokevirtual #60                 // Method java/lang/StringBuilder.append:(Ljava/lang/String;)Ljava/lang/StringBuilder;
        18: aload_1
        19: invokevirtual #60                 // Method java/lang/StringBuilder.append:(Ljava/lang/String;)Ljava/lang/StringBuilder;
        22: invokevirtual #62                 // Method java/lang/StringBuilder.toString:()Ljava/lang/String;
        25: invokespecial #100                // Method com/fasterxml/jackson/core/io/JsonEOFException."<init>":(Lcom/fasterxml/jackson/core/JsonParser;Lcom/fasterxml/jackson/core/JsonToken;Ljava/lang/String;)V
        28: athrow
      LineNumberTable:
        line 703: 0
      LocalVariableTable:
        Start  Length  Slot  Name   Signature
            0      29     0  this   Lcom/fasterxml/jackson/core/base/ParserMinimalBase;
            0      29     1   msg   Ljava/lang/String;
    Exceptions:
      throws com.fasterxml.jackson.core.JsonParseException
    Deprecated: true
    RuntimeVisibleAnnotations:
      0: #266()
        java.lang.Deprecated

  protected void _reportMissingRootWS(int) throws com.fasterxml.jackson.core.JsonParseException;
    descriptor: (I)V
    flags: (0x0004) ACC_PROTECTED
    Code:
      stack=3, locals=2, args_size=2
         0: aload_0
         1: iload_1
         2: ldc           #102                // String Expected space separating root-level values
         4: invokevirtual #103                // Method _reportUnexpectedChar:(ILjava/lang/String;)V
         7: return
      LineNumberTable:
        line 707: 0
        line 708: 7
      LocalVariableTable:
        Start  Length  Slot  Name   Signature
            0       8     0  this   Lcom/fasterxml/jackson/core/base/ParserMinimalBase;
            0       8     1    ch   I
    Exceptions:
      throws com.fasterxml.jackson.core.JsonParseException

  protected void _throwInvalidSpace(int) throws com.fasterxml.jackson.core.JsonParseException;
    descriptor: (I)V
    flags: (0x0004) ACC_PROTECTED
    Code:
      stack=2, locals=4, args_size=2
         0: iload_1
         1: i2c
         2: istore_2
         3: new           #58                 // class java/lang/StringBuilder
         6: dup
         7: invokespecial #59                 // Method java/lang/StringBuilder."<init>":()V
        10: ldc           #104                // String Illegal character (
        12: invokevirtual #60                 // Method java/lang/StringBuilder.append:(Ljava/lang/String;)Ljava/lang/StringBuilder;
        15: iload_2
        16: invokestatic  #56                 // Method _getCharDesc:(I)Ljava/lang/String;
        19: invokevirtual #60                 // Method java/lang/StringBuilder.append:(Ljava/lang/String;)Ljava/lang/StringBuilder;
        22: ldc           #105                // String ): only regular white space (\\r, \\n, \\t) is allowed between tokens
        24: invokevirtual #60                 // Method java/lang/StringBuilder.append:(Ljava/lang/String;)Ljava/lang/StringBuilder;
        27: invokevirtual #62                 // Method java/lang/StringBuilder.toString:()Ljava/lang/String;
        30: astore_3
        31: aload_0
        32: aload_3
        33: invokevirtual #52                 // Method _reportError:(Ljava/lang/String;)V
        36: return
      LineNumberTable:
        line 711: 0
        line 712: 3
        line 713: 31
        line 714: 36
      LocalVariableTable:
        Start  Length  Slot  Name   Signature
            0      37     0  this   Lcom/fasterxml/jackson/core/base/ParserMinimalBase;
            0      37     1     i   I
            3      34     2     c   C
           31       6     3   msg   Ljava/lang/String;
    Exceptions:
      throws com.fasterxml.jackson.core.JsonParseException

  protected static final java.lang.String _getCharDesc(int);
    descriptor: (I)Ljava/lang/String;
    flags: (0x001c) ACC_PROTECTED, ACC_STATIC, ACC_FINAL
    Code:
      stack=2, locals=2, args_size=1
         0: iload_0
         1: i2c
         2: istore_1
         3: iload_1
         4: invokestatic  #106                // Method java/lang/Character.isISOControl:(C)Z
         7: ifeq          35
        10: new           #58                 // class java/lang/StringBuilder
        13: dup
        14: invokespecial #59                 // Method java/lang/StringBuilder."<init>":()V
        17: ldc           #107                // String (CTRL-CHAR, code
        19: invokevirtual #60                 // Method java/lang/StringBuilder.append:(Ljava/lang/String;)Ljava/lang/StringBuilder;
        22: iload_0
        23: invokevirtual #108                // Method java/lang/StringBuilder.append:(I)Ljava/lang/StringBuilder;
        26: ldc           #109                // String )
        28: invokevirtual #60                 // Method java/lang/StringBuilder.append:(Ljava/lang/String;)Ljava/lang/StringBuilder;
        31: invokevirtual #62                 // Method java/lang/StringBuilder.toString:()Ljava/lang/String;
        34: areturn
        35: iload_0
        36: sipush        255
        39: if_icmple     88
        42: new           #58                 // class java/lang/StringBuilder
        45: dup
        46: invokespecial #59                 // Method java/lang/StringBuilder."<init>":()V
        49: ldc           #110                // String \'
        51: invokevirtual #60                 // Method java/lang/StringBuilder.append:(Ljava/lang/String;)Ljava/lang/StringBuilder;
        54: iload_1
        55: invokevirtual #111                // Method java/lang/StringBuilder.append:(C)Ljava/lang/StringBuilder;
        58: ldc           #112                // String \' (code
        60: invokevirtual #60                 // Method java/lang/StringBuilder.append:(Ljava/lang/String;)Ljava/lang/StringBuilder;
        63: iload_0
        64: invokevirtual #108                // Method java/lang/StringBuilder.append:(I)Ljava/lang/StringBuilder;
        67: ldc           #113                // String  / 0x
        69: invokevirtual #60                 // Method java/lang/StringBuilder.append:(Ljava/lang/String;)Ljava/lang/StringBuilder;
        72: iload_0
        73: invokestatic  #114                // Method java/lang/Integer.toHexString:(I)Ljava/lang/String;
        76: invokevirtual #60                 // Method java/lang/StringBuilder.append:(Ljava/lang/String;)Ljava/lang/StringBuilder;
        79: ldc           #109                // String )
        81: invokevirtual #60                 // Method java/lang/StringBuilder.append:(Ljava/lang/String;)Ljava/lang/StringBuilder;
        84: invokevirtual #62                 // Method java/lang/StringBuilder.toString:()Ljava/lang/String;
        87: areturn
        88: new           #58                 // class java/lang/StringBuilder
        91: dup
        92: invokespecial #59                 // Method java/lang/StringBuilder."<init>":()V
        95: ldc           #110                // String \'
        97: invokevirtual #60                 // Method java/lang/StringBuilder.append:(Ljava/lang/String;)Ljava/lang/StringBuilder;
       100: iload_1
       101: invokevirtual #111                // Method java/lang/StringBuilder.append:(C)Ljava/lang/StringBuilder;
       104: ldc           #112                // String \' (code
       106: invokevirtual #60                 // Method java/lang/StringBuilder.append:(Ljava/lang/String;)Ljava/lang/StringBuilder;
       109: iload_0
       110: invokevirtual #108                // Method java/lang/StringBuilder.append:(I)Ljava/lang/StringBuilder;
       113: ldc           #109                // String )
       115: invokevirtual #60                 // Method java/lang/StringBuilder.append:(Ljava/lang/String;)Ljava/lang/StringBuilder;
       118: invokevirtual #62                 // Method java/lang/StringBuilder.toString:()Ljava/lang/String;
       121: areturn
      LineNumberTable:
        line 724: 0
        line 725: 3
        line 726: 10
        line 728: 35
        line 729: 42
        line 731: 88
      LocalVariableTable:
        Start  Length  Slot  Name   Signature
            0     122     0    ch   I
            3     119     1     c   C
      StackMapTable: number_of_entries = 2
        frame_type = 252 /* append */
          offset_delta = 35
          locals = [ int ]
        frame_type = 52 /* same */

  protected final void _reportError(java.lang.String) throws com.fasterxml.jackson.core.JsonParseException;
    descriptor: (Ljava/lang/String;)V
    flags: (0x0014) ACC_PROTECTED, ACC_FINAL
    Code:
      stack=2, locals=2, args_size=2
         0: aload_0
         1: aload_1
         2: invokevirtual #115                // Method _constructError:(Ljava/lang/String;)Lcom/fasterxml/jackson/core/JsonParseException;
         5: athrow
      LineNumberTable:
        line 735: 0
      LocalVariableTable:
        Start  Length  Slot  Name   Signature
            0       6     0  this   Lcom/fasterxml/jackson/core/base/ParserMinimalBase;
            0       6     1   msg   Ljava/lang/String;
    Exceptions:
      throws com.fasterxml.jackson.core.JsonParseException

  protected final void _reportError(java.lang.String, java.lang.Object) throws com.fasterxml.jackson.core.JsonParseException;
    descriptor: (Ljava/lang/String;Ljava/lang/Object;)V
    flags: (0x0014) ACC_PROTECTED, ACC_FINAL
    Code:
      stack=6, locals=3, args_size=3
         0: aload_0
         1: aload_1
         2: iconst_1
         3: anewarray     #55                 // class java/lang/Object
         6: dup
         7: iconst_0
         8: aload_2
         9: aastore
        10: invokestatic  #57                 // Method java/lang/String.format:(Ljava/lang/String;[Ljava/lang/Object;)Ljava/lang/String;
        13: invokevirtual #115                // Method _constructError:(Ljava/lang/String;)Lcom/fasterxml/jackson/core/JsonParseException;
        16: athrow
      LineNumberTable:
        line 740: 0
      LocalVariableTable:
        Start  Length  Slot  Name   Signature
            0      17     0  this   Lcom/fasterxml/jackson/core/base/ParserMinimalBase;
            0      17     1   msg   Ljava/lang/String;
            0      17     2   arg   Ljava/lang/Object;
    Exceptions:
      throws com.fasterxml.jackson.core.JsonParseException

  protected final void _reportError(java.lang.String, java.lang.Object, java.lang.Object) throws com.fasterxml.jackson.core.JsonParseException;
    descriptor: (Ljava/lang/String;Ljava/lang/Object;Ljava/lang/Object;)V
    flags: (0x0014) ACC_PROTECTED, ACC_FINAL
    Code:
      stack=6, locals=4, args_size=4
         0: aload_0
         1: aload_1
         2: iconst_2
         3: anewarray     #55                 // class java/lang/Object
         6: dup
         7: iconst_0
         8: aload_2
         9: aastore
        10: dup
        11: iconst_1
        12: aload_3
        13: aastore
        14: invokestatic  #57                 // Method java/lang/String.format:(Ljava/lang/String;[Ljava/lang/Object;)Ljava/lang/String;
        17: invokevirtual #115                // Method _constructError:(Ljava/lang/String;)Lcom/fasterxml/jackson/core/JsonParseException;
        20: athrow
      LineNumberTable:
        line 745: 0
      LocalVariableTable:
        Start  Length  Slot  Name   Signature
            0      21     0  this   Lcom/fasterxml/jackson/core/base/ParserMinimalBase;
            0      21     1   msg   Ljava/lang/String;
            0      21     2  arg1   Ljava/lang/Object;
            0      21     3  arg2   Ljava/lang/Object;
    Exceptions:
      throws com.fasterxml.jackson.core.JsonParseException

  protected final void _wrapError(java.lang.String, java.lang.Throwable) throws com.fasterxml.jackson.core.JsonParseException;
    descriptor: (Ljava/lang/String;Ljava/lang/Throwable;)V
    flags: (0x0014) ACC_PROTECTED, ACC_FINAL
    Code:
      stack=3, locals=3, args_size=3
         0: aload_0
         1: aload_1
         2: aload_2
         3: invokevirtual #116                // Method _constructError:(Ljava/lang/String;Ljava/lang/Throwable;)Lcom/fasterxml/jackson/core/JsonParseException;
         6: athrow
      LineNumberTable:
        line 749: 0
      LocalVariableTable:
        Start  Length  Slot  Name   Signature
            0       7     0  this   Lcom/fasterxml/jackson/core/base/ParserMinimalBase;
            0       7     1   msg   Ljava/lang/String;
            0       7     2     t   Ljava/lang/Throwable;
    Exceptions:
      throws com.fasterxml.jackson.core.JsonParseException

  protected final void _throwInternal();
    descriptor: ()V
    flags: (0x0014) ACC_PROTECTED, ACC_FINAL
    Code:
      stack=0, locals=1, args_size=1
         0: invokestatic  #117                // Method com/fasterxml/jackson/core/util/VersionUtil.throwInternal:()V
         3: return
      LineNumberTable:
        line 753: 0
        line 754: 3
      LocalVariableTable:
        Start  Length  Slot  Name   Signature
            0       4     0  this   Lcom/fasterxml/jackson/core/base/ParserMinimalBase;

  protected final com.fasterxml.jackson.core.JsonParseException _constructError(java.lang.String, java.lang.Throwable);
    descriptor: (Ljava/lang/String;Ljava/lang/Throwable;)Lcom/fasterxml/jackson/core/JsonParseException;
    flags: (0x0014) ACC_PROTECTED, ACC_FINAL
    Code:
      stack=5, locals=3, args_size=3
         0: new           #118                // class com/fasterxml/jackson/core/JsonParseException
         3: dup
         4: aload_0
         5: aload_1
         6: aload_2
         7: invokespecial #119                // Method com/fasterxml/jackson/core/JsonParseException."<init>":(Lcom/fasterxml/jackson/core/JsonParser;Ljava/lang/String;Ljava/lang/Throwable;)V
        10: areturn
      LineNumberTable:
        line 757: 0
      LocalVariableTable:
        Start  Length  Slot  Name   Signature
            0      11     0  this   Lcom/fasterxml/jackson/core/base/ParserMinimalBase;
            0      11     1   msg   Ljava/lang/String;
            0      11     2     t   Ljava/lang/Throwable;

  protected static byte[] _asciiBytes(java.lang.String);
    descriptor: (Ljava/lang/String;)[B
    flags: (0x000c) ACC_PROTECTED, ACC_STATIC
    Code:
      stack=4, locals=4, args_size=1
         0: aload_0
         1: invokevirtual #85                 // Method java/lang/String.length:()I
         4: newarray       byte
         6: astore_1
         7: iconst_0
         8: istore_2
         9: aload_0
        10: invokevirtual #85                 // Method java/lang/String.length:()I
        13: istore_3
        14: iload_2
        15: iload_3
        16: if_icmpge     34
        19: aload_1
        20: iload_2
        21: aload_0
        22: iload_2
        23: invokevirtual #120                // Method java/lang/String.charAt:(I)C
        26: i2b
        27: bastore
        28: iinc          2, 1
        31: goto          14
        34: aload_1
        35: areturn
      LineNumberTable:
        line 762: 0
        line 763: 7
        line 764: 19
        line 763: 28
        line 766: 34
      LocalVariableTable:
        Start  Length  Slot  Name   Signature
            9      25     2     i   I
           14      20     3   len   I
            0      36     0   str   Ljava/lang/String;
            7      29     1     b   [B
      StackMapTable: number_of_entries = 2
        frame_type = 254 /* append */
          offset_delta = 14
          locals = [ class "[B", int, int ]
        frame_type = 249 /* chop */
          offset_delta = 19
    Deprecated: true
    RuntimeVisibleAnnotations:
      0: #266()
        java.lang.Deprecated

  protected static java.lang.String _ascii(byte[]);
    descriptor: ([B)Ljava/lang/String;
    flags: (0x000c) ACC_PROTECTED, ACC_STATIC
    Code:
      stack=4, locals=2, args_size=1
         0: new           #121                // class java/lang/String
         3: dup
         4: aload_0
         5: ldc           #122                // String US-ASCII
         7: invokespecial #123                // Method java/lang/String."<init>":([BLjava/lang/String;)V
        10: areturn
        11: astore_1
        12: new           #125                // class java/lang/RuntimeException
        15: dup
        16: aload_1
        17: invokespecial #126                // Method java/lang/RuntimeException."<init>":(Ljava/lang/Throwable;)V
        20: athrow
      Exception table:
         from    to  target type
             0    10    11   Class java/io/IOException
      LineNumberTable:
        line 772: 0
        line 773: 11
        line 774: 12
      LocalVariableTable:
        Start  Length  Slot  Name   Signature
           12       9     1     e   Ljava/io/IOException;
            0      21     0     b   [B
      StackMapTable: number_of_entries = 1
        frame_type = 75 /* same_locals_1_stack_item */
          stack = [ class java/io/IOException ]
    Deprecated: true
    RuntimeVisibleAnnotations:
      0: #266()
        java.lang.Deprecated

  static {};
    descriptor: ()V
    flags: (0x0008) ACC_STATIC
    Code:
      stack=3, locals=0, args_size=0
         0: iconst_0
         1: newarray       byte
         3: putstatic     #127                // Field NO_BYTES:[B
         6: iconst_0
         7: newarray       int
         9: putstatic     #128                // Field NO_INTS:[I
        12: ldc2_w        #129                // long -2147483648l
        15: invokestatic  #131                // Method java/math/BigInteger.valueOf:(J)Ljava/math/BigInteger;
        18: putstatic     #132                // Field BI_MIN_INT:Ljava/math/BigInteger;
        21: ldc2_w        #133                // long 2147483647l
        24: invokestatic  #131                // Method java/math/BigInteger.valueOf:(J)Ljava/math/BigInteger;
        27: putstatic     #135                // Field BI_MAX_INT:Ljava/math/BigInteger;
        30: ldc2_w        #77                 // long -9223372036854775808l
        33: invokestatic  #131                // Method java/math/BigInteger.valueOf:(J)Ljava/math/BigInteger;
        36: putstatic     #136                // Field BI_MIN_LONG:Ljava/math/BigInteger;
        39: ldc2_w        #80                 // long 9223372036854775807l
        42: invokestatic  #131                // Method java/math/BigInteger.valueOf:(J)Ljava/math/BigInteger;
        45: putstatic     #137                // Field BI_MAX_LONG:Ljava/math/BigInteger;
        48: new           #138                // class java/math/BigDecimal
        51: dup
        52: getstatic     #136                // Field BI_MIN_LONG:Ljava/math/BigInteger;
        55: invokespecial #139                // Method java/math/BigDecimal."<init>":(Ljava/math/BigInteger;)V
        58: putstatic     #140                // Field BD_MIN_LONG:Ljava/math/BigDecimal;
        61: new           #138                // class java/math/BigDecimal
        64: dup
        65: getstatic     #137                // Field BI_MAX_LONG:Ljava/math/BigInteger;
        68: invokespecial #139                // Method java/math/BigDecimal."<init>":(Ljava/math/BigInteger;)V
        71: putstatic     #141                // Field BD_MAX_LONG:Ljava/math/BigDecimal;
        74: new           #138                // class java/math/BigDecimal
        77: dup
        78: getstatic     #132                // Field BI_MIN_INT:Ljava/math/BigInteger;
        81: invokespecial #139                // Method java/math/BigDecimal."<init>":(Ljava/math/BigInteger;)V
        84: putstatic     #142                // Field BD_MIN_INT:Ljava/math/BigDecimal;
        87: new           #138                // class java/math/BigDecimal
        90: dup
        91: getstatic     #135                // Field BI_MAX_INT:Ljava/math/BigInteger;
        94: invokespecial #139                // Method java/math/BigDecimal."<init>":(Ljava/math/BigInteger;)V
        97: putstatic     #143                // Field BD_MAX_INT:Ljava/math/BigDecimal;
       100: return
      LineNumberTable:
        line 62: 0
        line 67: 6
        line 97: 12
        line 98: 21
        line 100: 30
        line 101: 39
        line 103: 48
        line 104: 61
        line 106: 74
        line 107: 87
}
SourceFile: "ParserMinimalBase.java"
