Classfile /Users/mw/Projects/slang-braindump/.jar/jar11/assemble/slang-braindump/assemble/content/org/scalatest/AppendedClues.class
  Last modified May 29, 2022; size 1746 bytes
  SHA-256 checksum 5acd32970fa72cbf277f06c077090d65cd7d340a85e9dc77ccd5a164559895bc
  Compiled from "AppendedClues.scala"
public interface org.scalatest.AppendedClues
  minor version: 0
  major version: 52
  flags: (0x0601) ACC_PUBLIC, ACC_INTERFACE, ACC_ABSTRACT
  this_class: #2                          // org/scalatest/AppendedClues
  super_class: #4                         // java/lang/Object
  interfaces: 0, fields: 0, methods: 3, attributes: 5
Constant pool:
   #1 = Utf8               org/scalatest/AppendedClues
   #2 = Class              #1             // org/scalatest/AppendedClues
   #3 = Utf8               java/lang/Object
   #4 = Class              #3             // java/lang/Object
   #5 = Utf8               AppendedClues.scala
   #6 = Utf8               Lscala/reflect/ScalaSignature;
   #7 = Utf8               bytes
   #8 = Utf8               \u0006\u0005Y3qa\u0003\u0007\u0011\u0002\u0007\u0005\u0011\u0003C\u0003\u0019\u0001\u0011\u0005\u0011D\u0002\u0003\u001e\u0001\u0001q\u0002\u0002\u0003\u0011\u0003\u0005\u0003%\u000b\u0011B\u0011\t\u000b=\u0012A\u0011\u0001\u0019\t\u000bQ\u0012A\u0011A\u001b\t\u000ba\u0002A1A\u001d\b\u000b\u0001c\u0001\u0012A!\u0007\u000b-a\u0001\u0012A\"\t\u000b=BA\u0011A#\t\r\u0019CA\u0011\u0001\u0007H\u00055\t\u0005\u000f]3oI\u0016$7\t\\;fg*\u0011QBD\u0001\ng\u000e\fG.\u0019;fgRT\u0011aD\u0001\u0004_J<7\u0001A\n\u0003\u0001I\u0001\"a\u0005\f\u000e\u0003QQ\u0011!F\u0001\u0006g\u000e\fG.Y\u0005\u0003/Q\u0011a!\u00118z%\u00164\u0017A\u0002\u0013j]&$H\u0005F\u0001\u001b!\t\u00192$\u0003\u0002\u001d)\t!QK\\5u\u0005\u001d\u0019E.^3gk2,\"a\b\u0014\u0014\u0005\t\u0011\u0012a\u00014v]B\u00191C\t\u0013\n\u0005\r\"\"\u0001\u0003\u001fcs:\fW.\u001a \u0011\u0005\u00152C\u0002\u0001\u0003\u0006O\t\u0011\r\u0001\u000b\u0002\u0002)F\u0011\u0011\u0006\f\t\u0003\')J!a\u000b\u000b\u0003\u000f9{G\u000f[5oOB\u00111#L\u0005\u0003]Q\u00111!\u00118z\u0003\u0019a\u0014N\\5u}Q\u0011\u0011g\r\t\u0004e\t!S\"\u0001\u0001\t\r\u0001\"A\u00111\u0001\"\u0003!9\u0018\u000e\u001e5DYV,GC\u0001\u00137\u0011\u00159T\u00011\u0001-\u0003\u0011\u0019G.^3\u0002!\r|gN^3siR{7\t\\;fMVdWC\u0001\u001e>)\tYd\bE\u00023\u0005q\u0002\"!J\u001f\u0005\u000b\u001d2!\u0019\u0001\u0015\t\r\u00012A\u00111\u0001@!\r\u0019\"\u0005P\u0001\u000e\u0003B\u0004XM\u001c3fI\u000ecW/Z:\u0011\u0005\tCQ\"\u0001\u0007\u0014\u0007!\u0011B\t\u0005\u0002C\u0001Q\t\u0011)\u0001\u0006baB,g\u000eZ\"mk\u0016$2\u0001S*V!\tI\u0005K\u0004\u0002K\u001dB\u00111\nF\u0007\u0002\u0019*\u0011Q\nE\u0001\u0007yI|w\u000e\u001e \n\u0005=#\u0012A\u0002)sK\u0012,g-\u0003\u0002R%\n11\u000b\u001e:j]\u001eT!a\u0014\u000b\t\u000bQS\u0001\u0019\u0001%\u0002\u0011=\u0014\u0018nZ5oC2DQa\u000e\u0006A\u0002!\u0003
   #9 = Utf8               org/scalatest/AppendedClues$Clueful
  #10 = Class              #9             // org/scalatest/AppendedClues$Clueful
  #11 = Utf8               Clueful
  #12 = Utf8               convertToClueful$
  #13 = Utf8               (Lorg/scalatest/AppendedClues;Lscala/Function0;)Lorg/scalatest/AppendedClues$Clueful;
  #14 = Utf8               $this
  #15 = Utf8               fun
  #16 = Utf8               convertToClueful
  #17 = Utf8               (Lscala/Function0;)Lorg/scalatest/AppendedClues$Clueful;
  #18 = NameAndType        #16:#17        // convertToClueful:(Lscala/Function0;)Lorg/scalatest/AppendedClues$Clueful;
  #19 = InterfaceMethodref #2.#18         // org/scalatest/AppendedClues.convertToClueful:(Lscala/Function0;)Lorg/scalatest/AppendedClues$Clueful;
  #20 = Utf8               Lorg/scalatest/AppendedClues;
  #21 = Utf8               Lscala/Function0;
  #22 = Utf8               <T:Ljava/lang/Object;>(Lscala/Function0<TT;>;)Lorg/scalatest/AppendedClues$Clueful<TT;>;
  #23 = Utf8               <init>
  #24 = Utf8               (Lorg/scalatest/AppendedClues;Lscala/Function0;)V
  #25 = NameAndType        #23:#24        // "<init>":(Lorg/scalatest/AppendedClues;Lscala/Function0;)V
  #26 = Methodref          #10.#25        // org/scalatest/AppendedClues$Clueful."<init>":(Lorg/scalatest/AppendedClues;Lscala/Function0;)V
  #27 = Utf8               this
  #28 = Utf8               $init$
  #29 = Utf8               (Lorg/scalatest/AppendedClues;)V
  #30 = Utf8               Code
  #31 = Utf8               LineNumberTable
  #32 = Utf8               LocalVariableTable
  #33 = Utf8               MethodParameters
  #34 = Utf8               Signature
  #35 = Utf8               InnerClasses
  #36 = Utf8               SourceFile
  #37 = Utf8               RuntimeVisibleAnnotations
  #38 = Utf8               ScalaInlineInfo
  #39 = Utf8               ScalaSig
{
  public static org.scalatest.AppendedClues$Clueful convertToClueful$(org.scalatest.AppendedClues, scala.Function0);
    descriptor: (Lorg/scalatest/AppendedClues;Lscala/Function0;)Lorg/scalatest/AppendedClues$Clueful;
    flags: (0x1009) ACC_PUBLIC, ACC_STATIC, ACC_SYNTHETIC
    Code:
      stack=2, locals=2, args_size=2
         0: aload_0
         1: aload_1
         2: invokespecial #19                 // InterfaceMethod convertToClueful:(Lscala/Function0;)Lorg/scalatest/AppendedClues$Clueful;
         5: areturn
      LineNumberTable:
        line 175: 0
      LocalVariableTable:
        Start  Length  Slot  Name   Signature
            0       6     0 $this   Lorg/scalatest/AppendedClues;
            0       6     1   fun   Lscala/Function0;
    MethodParameters:
      Name                           Flags
      $this                          final synthetic
      fun                            final

  public default <T extends java.lang.Object> org.scalatest.AppendedClues$Clueful<T> convertToClueful(scala.Function0<T>);
    descriptor: (Lscala/Function0;)Lorg/scalatest/AppendedClues$Clueful;
    flags: (0x0001) ACC_PUBLIC
    Code:
      stack=4, locals=2, args_size=2
         0: new           #10                 // class org/scalatest/AppendedClues$Clueful
         3: dup
         4: aload_0
         5: aload_1
         6: invokespecial #26                 // Method org/scalatest/AppendedClues$Clueful."<init>":(Lorg/scalatest/AppendedClues;Lscala/Function0;)V
         9: areturn
      LineNumberTable:
        line 175: 0
      LocalVariableTable:
        Start  Length  Slot  Name   Signature
            0      10     0  this   Lorg/scalatest/AppendedClues;
            0      10     1   fun   Lscala/Function0;
    Signature: #22                          // <T:Ljava/lang/Object;>(Lscala/Function0<TT;>;)Lorg/scalatest/AppendedClues$Clueful<TT;>;
    MethodParameters:
      Name                           Flags
      fun                            final

  public static void $init$(org.scalatest.AppendedClues);
    descriptor: (Lorg/scalatest/AppendedClues;)V
    flags: (0x0009) ACC_PUBLIC, ACC_STATIC
    Code:
      stack=0, locals=1, args_size=1
         0: return
      LineNumberTable:
        line 103: 0
      LocalVariableTable:
        Start  Length  Slot  Name   Signature
            0       1     0 $this   Lorg/scalatest/AppendedClues;
    MethodParameters:
      Name                           Flags
      $this                          final synthetic
}
InnerClasses:
  public #11= #10 of #2;                  // Clueful=class org/scalatest/AppendedClues$Clueful of class org/scalatest/AppendedClues
SourceFile: "AppendedClues.scala"
RuntimeVisibleAnnotations:
  0: #6(#7=s#8)
    scala.reflect.ScalaSignature(
      bytes="\u0006\u0005Y3qa\u0003\u0007\u0011\u0002\u0007\u0005\u0011\u0003C\u0003\u0019\u0001\u0011\u0005\u0011D\u0002\u0003\u001e\u0001\u0001q\u0002\u0002\u0003\u0011\u0003\u0005\u0003%\u000b\u0011B\u0011\t\u000b=\u0012A\u0011\u0001\u0019\t\u000bQ\u0012A\u0011A\u001b\t\u000ba\u0002A1A\u001d\b\u000b\u0001c\u0001\u0012A!\u0007\u000b-a\u0001\u0012A\"\t\u000b=BA\u0011A#\t\r\u0019CA\u0011\u0001\u0007H\u00055\t\u0005\u000f]3oI\u0016$7\t\\;fg*\u0011QBD\u0001\ng\u000e\fG.\u0019;fgRT\u0011aD\u0001\u0004_J<7\u0001A\n\u0003\u0001I\u0001\"a\u0005\f\u000e\u0003QQ\u0011!F\u0001\u0006g\u000e\fG.Y\u0005\u0003/Q\u0011a!\u00118z%\u00164\u0017A\u0002\u0013j]&$H\u0005F\u0001\u001b!\t\u00192$\u0003\u0002\u001d)\t!QK\\5u\u0005\u001d\u0019E.^3gk2,\"a\b\u0014\u0014\u0005\t\u0011\u0012a\u00014v]B\u00191C\t\u0013\n\u0005\r\"\"\u0001\u0003\u001fcs:\fW.\u001a \u0011\u0005\u00152C\u0002\u0001\u0003\u0006O\t\u0011\r\u0001\u000b\u0002\u0002)F\u0011\u0011\u0006\f\t\u0003\')J!a\u000b\u000b\u0003\u000f9{G\u000f[5oOB\u00111#L\u0005\u0003]Q\u00111!\u00118z\u0003\u0019a\u0014N\\5u}Q\u0011\u0011g\r\t\u0004e\t!S\"\u0001\u0001\t\r\u0001\"A\u00111\u0001\"\u0003!9\u0018\u000e\u001e5DYV,GC\u0001\u00137\u0011\u00159T\u00011\u0001-\u0003\u0011\u0019G.^3\u0002!\r|gN^3siR{7\t\\;fMVdWC\u0001\u001e>)\tYd\bE\u00023\u0005q\u0002\"!J\u001f\u0005\u000b\u001d2!\u0019\u0001\u0015\t\r\u00012A\u00111\u0001@!\r\u0019\"\u0005P\u0001\u000e\u0003B\u0004XM\u001c3fI\u000ecW/Z:\u0011\u0005\tCQ\"\u0001\u0007\u0014\u0007!\u0011B\t\u0005\u0002C\u0001Q\t\u0011)\u0001\u0006baB,g\u000eZ\"mk\u0016$2\u0001S*V!\tI\u0005K\u0004\u0002K\u001dB\u00111\nF\u0007\u0002\u0019*\u0011Q\nE\u0001\u0007yI|w\u000e\u001e \n\u0005=#\u0012A\u0002)sK\u0012,g-\u0003\u0002R%\n11\u000b\u001e:j]\u001eT!a\u0014\u000b\t\u000bQS\u0001\u0019\u0001%\u0002\u0011=\u0014\u0018nZ5oC2DQa\u000e\u0006A\u0002!\u0003"
    )
  ScalaInlineInfo: length = 0x13 (unknown attribute)
   01 00 00 03 00 1C 00 1D 01 00 10 00 11 00 00 0C
   00 0D 01
  ScalaSig: length = 0x3 (unknown attribute)
   05 02 00
