Classfile /Users/mw/Projects/slang-braindump/.jar/jar11/assemble/slang-braindump/assemble/content/org/scalatest/AssertionsMacro$.class
  Last modified May 29, 2022; size 4731 bytes
  SHA-256 checksum e1abc4959b3442bffd15be841cd92b21e507496ffa836871ffab6494f745064e
  Compiled from "AssertionsMacro.scala"
public final class org.scalatest.AssertionsMacro$
  minor version: 0
  major version: 52
  flags: (0x0031) ACC_PUBLIC, ACC_FINAL, ACC_SUPER
  this_class: #2                          // org/scalatest/AssertionsMacro$
  super_class: #4                         // java/lang/Object
  interfaces: 0, fields: 1, methods: 6, attributes: 4
Constant pool:
    #1 = Utf8               org/scalatest/AssertionsMacro$
    #2 = Class              #1            // org/scalatest/AssertionsMacro$
    #3 = Utf8               java/lang/Object
    #4 = Class              #3            // java/lang/Object
    #5 = Utf8               AssertionsMacro.scala
    #6 = Utf8               scala/reflect/api/Exprs$Expr
    #7 = Class              #6            // scala/reflect/api/Exprs$Expr
    #8 = Utf8               scala/reflect/api/Exprs
    #9 = Class              #8            // scala/reflect/api/Exprs
   #10 = Utf8               Expr
   #11 = Utf8               scala/reflect/api/Names$NameApi
   #12 = Class              #11           // scala/reflect/api/Names$NameApi
   #13 = Utf8               scala/reflect/api/Names
   #14 = Class              #13           // scala/reflect/api/Names
   #15 = Utf8               NameApi
   #16 = Utf8               scala/reflect/api/Names$TermNameApi
   #17 = Class              #16           // scala/reflect/api/Names$TermNameApi
   #18 = Utf8               TermNameApi
   #19 = Utf8               scala/reflect/api/Trees$IdentApi
   #20 = Class              #19           // scala/reflect/api/Trees$IdentApi
   #21 = Utf8               scala/reflect/api/Trees
   #22 = Class              #21           // scala/reflect/api/Trees
   #23 = Utf8               IdentApi
   #24 = Utf8               scala/reflect/api/Trees$IdentExtractor
   #25 = Class              #24           // scala/reflect/api/Trees$IdentExtractor
   #26 = Utf8               IdentExtractor
   #27 = Utf8               scala/reflect/api/Trees$SelectApi
   #28 = Class              #27           // scala/reflect/api/Trees$SelectApi
   #29 = Utf8               SelectApi
   #30 = Utf8               scala/reflect/api/Trees$SelectExtractor
   #31 = Class              #30           // scala/reflect/api/Trees$SelectExtractor
   #32 = Utf8               SelectExtractor
   #33 = Utf8               scala/reflect/api/Trees$TreeApi
   #34 = Class              #33           // scala/reflect/api/Trees$TreeApi
   #35 = Utf8               TreeApi
   #36 = Utf8               MODULE$
   #37 = Utf8               Lorg/scalatest/AssertionsMacro$;
   #38 = Utf8               <clinit>
   #39 = Utf8               ()V
   #40 = Utf8               <init>
   #41 = NameAndType        #40:#39       // "<init>":()V
   #42 = Methodref          #2.#41        // org/scalatest/AssertionsMacro$."<init>":()V
   #43 = NameAndType        #36:#37       // MODULE$:Lorg/scalatest/AssertionsMacro$;
   #44 = Fieldref           #2.#43        // org/scalatest/AssertionsMacro$.MODULE$:Lorg/scalatest/AssertionsMacro$;
   #45 = Utf8               assert
   #46 = Utf8               (Lscala/reflect/macros/whitebox/Context;Lscala/reflect/api/Exprs$Expr;Lscala/reflect/api/Exprs$Expr;Lscala/reflect/api/Exprs$Expr;)Lscala/reflect/api/Exprs$Expr;
   #47 = Utf8               (Lscala/reflect/macros/whitebox/Context;Lscala/reflect/api/Exprs$Expr<Ljava/lang/Object;>;Lscala/reflect/api/Exprs$Expr<Lorg/scalactic/Prettifier;>;Lscala/reflect/api/Exprs$Expr<Lorg/scalactic/source/Position;>;)Lscala/reflect/api/Exprs$Expr<Lorg/scalatest/compatible/Assertion;>;
   #48 = Utf8               context
   #49 = Utf8               condition
   #50 = Utf8               prettifier
   #51 = Utf8               pos
   #52 = Utf8               org/scalactic/BooleanMacro
   #53 = Class              #52           // org/scalactic/BooleanMacro
   #54 = Utf8               (Lscala/reflect/macros/whitebox/Context;)V
   #55 = NameAndType        #40:#54       // "<init>":(Lscala/reflect/macros/whitebox/Context;)V
   #56 = Methodref          #53.#55       // org/scalactic/BooleanMacro."<init>":(Lscala/reflect/macros/whitebox/Context;)V
   #57 = Utf8               scala/reflect/macros/whitebox/Context
   #58 = Class              #57           // scala/reflect/macros/whitebox/Context
   #59 = Utf8               universe
   #60 = Utf8               ()Lscala/reflect/macros/Universe;
   #61 = NameAndType        #59:#60       // universe:()Lscala/reflect/macros/Universe;
   #62 = InterfaceMethodref #58.#61       // scala/reflect/macros/whitebox/Context.universe:()Lscala/reflect/macros/Universe;
   #63 = Utf8               scala/reflect/macros/Universe
   #64 = Class              #63           // scala/reflect/macros/Universe
   #65 = Utf8               Select
   #66 = Utf8               ()Lscala/reflect/api/Trees$SelectExtractor;
   #67 = NameAndType        #65:#66       // Select:()Lscala/reflect/api/Trees$SelectExtractor;
   #68 = Methodref          #64.#67       // scala/reflect/macros/Universe.Select:()Lscala/reflect/api/Trees$SelectExtractor;
   #69 = Utf8               Ident
   #70 = Utf8               ()Lscala/reflect/api/Trees$IdentExtractor;
   #71 = NameAndType        #69:#70       // Ident:()Lscala/reflect/api/Trees$IdentExtractor;
   #72 = Methodref          #64.#71       // scala/reflect/macros/Universe.Ident:()Lscala/reflect/api/Trees$IdentExtractor;
   #73 = Utf8               _root_
   #74 = String             #73           // _root_
   #75 = Utf8               newTermName
   #76 = Utf8               (Ljava/lang/String;)Lscala/reflect/api/Names$TermNameApi;
   #77 = NameAndType        #75:#76       // newTermName:(Ljava/lang/String;)Lscala/reflect/api/Names$TermNameApi;
   #78 = Methodref          #64.#77       // scala/reflect/macros/Universe.newTermName:(Ljava/lang/String;)Lscala/reflect/api/Names$TermNameApi;
   #79 = Utf8               apply
   #80 = Utf8               (Lscala/reflect/api/Names$NameApi;)Lscala/reflect/api/Trees$IdentApi;
   #81 = NameAndType        #79:#80       // apply:(Lscala/reflect/api/Names$NameApi;)Lscala/reflect/api/Trees$IdentApi;
   #82 = Methodref          #25.#81       // scala/reflect/api/Trees$IdentExtractor.apply:(Lscala/reflect/api/Names$NameApi;)Lscala/reflect/api/Trees$IdentApi;
   #83 = Utf8               org
   #84 = String             #83           // org
   #85 = Utf8               (Lscala/reflect/api/Trees$TreeApi;Lscala/reflect/api/Names$NameApi;)Lscala/reflect/api/Trees$SelectApi;
   #86 = NameAndType        #79:#85       // apply:(Lscala/reflect/api/Trees$TreeApi;Lscala/reflect/api/Names$NameApi;)Lscala/reflect/api/Trees$SelectApi;
   #87 = Methodref          #31.#86       // scala/reflect/api/Trees$SelectExtractor.apply:(Lscala/reflect/api/Trees$TreeApi;Lscala/reflect/api/Names$NameApi;)Lscala/reflect/api/Trees$SelectApi;
   #88 = Utf8               scalatest
   #89 = String             #88           // scalatest
   #90 = Utf8               Assertions
   #91 = String             #90           // Assertions
   #92 = Utf8               assertionsHelper
   #93 = String             #92           // assertionsHelper
   #94 = Utf8               macroAssert
   #95 = String             #94           // macroAssert
   #96 = Utf8
   #97 = String             #96           //
   #98 = Utf8               literal
   #99 = Utf8               (Ljava/lang/String;)Lscala/reflect/api/Exprs$Expr;
  #100 = NameAndType        #98:#99       // literal:(Ljava/lang/String;)Lscala/reflect/api/Exprs$Expr;
  #101 = InterfaceMethodref #58.#100      // scala/reflect/macros/whitebox/Context.literal:(Ljava/lang/String;)Lscala/reflect/api/Exprs$Expr;
  #102 = Utf8               genMacro
  #103 = Utf8               (Lscala/reflect/api/Trees$TreeApi;Lscala/reflect/api/Exprs$Expr;Ljava/lang/String;Lscala/reflect/api/Exprs$Expr;Lscala/reflect/api/Exprs$Expr;Lscala/reflect/api/Exprs$Expr;)Lscala/reflect/api/Exprs$Expr;
  #104 = NameAndType        #102:#103     // genMacro:(Lscala/reflect/api/Trees$TreeApi;Lscala/reflect/api/Exprs$Expr;Ljava/lang/String;Lscala/reflect/api/Exprs$Expr;Lscala/reflect/api/Exprs$Expr;Lscala/reflect/api/Exprs$Expr;)Lscala/reflect/api/Exprs$Expr;
  #105 = Methodref          #53.#104      // org/scalactic/BooleanMacro.genMacro:(Lscala/reflect/api/Trees$TreeApi;Lscala/reflect/api/Exprs$Expr;Ljava/lang/String;Lscala/reflect/api/Exprs$Expr;Lscala/reflect/api/Exprs$Expr;Lscala/reflect/api/Exprs$Expr;)Lscala/reflect/api/Exprs$Expr;
  #106 = Utf8               this
  #107 = Utf8               Lscala/reflect/macros/whitebox/Context;
  #108 = Utf8               Lscala/reflect/api/Exprs$Expr;
  #109 = Utf8               assertWithClue
  #110 = Utf8               (Lscala/reflect/macros/whitebox/Context;Lscala/reflect/api/Exprs$Expr;Lscala/reflect/api/Exprs$Expr;Lscala/reflect/api/Exprs$Expr;Lscala/reflect/api/Exprs$Expr;)Lscala/reflect/api/Exprs$Expr;
  #111 = Utf8               (Lscala/reflect/macros/whitebox/Context;Lscala/reflect/api/Exprs$Expr<Ljava/lang/Object;>;Lscala/reflect/api/Exprs$Expr<Ljava/lang/Object;>;Lscala/reflect/api/Exprs$Expr<Lorg/scalactic/Prettifier;>;Lscala/reflect/api/Exprs$Expr<Lorg/scalactic/source/Position;>;)Lscala/reflect/api/Exprs$Expr<Lorg/scalatest/compatible/Assertion;>;
  #112 = Utf8               clue
  #113 = Utf8               assume
  #114 = Utf8               macroAssume
  #115 = String             #114          // macroAssume
  #116 = Utf8               assumeWithClue
  #117 = Methodref          #4.#41        // java/lang/Object."<init>":()V
  #118 = Utf8               Code
  #119 = Utf8               LineNumberTable
  #120 = Utf8               LocalVariableTable
  #121 = Utf8               Signature
  #122 = Utf8               MethodParameters
  #123 = Utf8               InnerClasses
  #124 = Utf8               SourceFile
  #125 = Utf8               ScalaInlineInfo
  #126 = Utf8               Scala
{
  public static final org.scalatest.AssertionsMacro$ MODULE$;
    descriptor: Lorg/scalatest/AssertionsMacro$;
    flags: (0x0019) ACC_PUBLIC, ACC_STATIC, ACC_FINAL

  public static {};
    descriptor: ()V
    flags: (0x0009) ACC_PUBLIC, ACC_STATIC
    Code:
      stack=2, locals=0, args_size=0
         0: new           #2                  // class org/scalatest/AssertionsMacro$
         3: dup
         4: invokespecial #42                 // Method "<init>":()V
         7: putstatic     #44                 // Field MODULE$:Lorg/scalatest/AssertionsMacro$;
        10: return
      LineNumberTable:
        line 24: 0

  public scala.reflect.api.Exprs$Expr<org.scalatest.compatible.Assertion> assert(scala.reflect.macros.whitebox.Context, scala.reflect.api.Exprs$Expr<java.lang.Object>, scala.reflect.api.Exprs$Expr<org.scalactic.Prettifier>, scala.reflect.api.Exprs$Expr<org.scalactic.source.Position>);
    descriptor: (Lscala/reflect/macros/whitebox/Context;Lscala/reflect/api/Exprs$Expr;Lscala/reflect/api/Exprs$Expr;Lscala/reflect/api/Exprs$Expr;)Lscala/reflect/api/Exprs$Expr;
    flags: (0x0001) ACC_PUBLIC
    Code:
      stack=8, locals=8, args_size=5
         0: aload_2
         1: astore        5
         3: aload_3
         4: astore        6
         6: aload         4
         8: astore        7
        10: new           #53                 // class org/scalactic/BooleanMacro
        13: dup
        14: aload_1
        15: invokespecial #56                 // Method org/scalactic/BooleanMacro."<init>":(Lscala/reflect/macros/whitebox/Context;)V
        18: aload_1
        19: invokeinterface #62,  1           // InterfaceMethod scala/reflect/macros/whitebox/Context.universe:()Lscala/reflect/macros/Universe;
        24: invokevirtual #68                 // Method scala/reflect/macros/Universe.Select:()Lscala/reflect/api/Trees$SelectExtractor;
        27: aload_1
        28: invokeinterface #62,  1           // InterfaceMethod scala/reflect/macros/whitebox/Context.universe:()Lscala/reflect/macros/Universe;
        33: invokevirtual #68                 // Method scala/reflect/macros/Universe.Select:()Lscala/reflect/api/Trees$SelectExtractor;
        36: aload_1
        37: invokeinterface #62,  1           // InterfaceMethod scala/reflect/macros/whitebox/Context.universe:()Lscala/reflect/macros/Universe;
        42: invokevirtual #68                 // Method scala/reflect/macros/Universe.Select:()Lscala/reflect/api/Trees$SelectExtractor;
        45: aload_1
        46: invokeinterface #62,  1           // InterfaceMethod scala/reflect/macros/whitebox/Context.universe:()Lscala/reflect/macros/Universe;
        51: invokevirtual #68                 // Method scala/reflect/macros/Universe.Select:()Lscala/reflect/api/Trees$SelectExtractor;
        54: aload_1
        55: invokeinterface #62,  1           // InterfaceMethod scala/reflect/macros/whitebox/Context.universe:()Lscala/reflect/macros/Universe;
        60: invokevirtual #72                 // Method scala/reflect/macros/Universe.Ident:()Lscala/reflect/api/Trees$IdentExtractor;
        63: aload_1
        64: invokeinterface #62,  1           // InterfaceMethod scala/reflect/macros/whitebox/Context.universe:()Lscala/reflect/macros/Universe;
        69: ldc           #74                 // String _root_
        71: invokevirtual #78                 // Method scala/reflect/macros/Universe.newTermName:(Ljava/lang/String;)Lscala/reflect/api/Names$TermNameApi;
        74: checkcast     #12                 // class scala/reflect/api/Names$NameApi
        77: invokevirtual #82                 // Method scala/reflect/api/Trees$IdentExtractor.apply:(Lscala/reflect/api/Names$NameApi;)Lscala/reflect/api/Trees$IdentApi;
        80: aload_1
        81: invokeinterface #62,  1           // InterfaceMethod scala/reflect/macros/whitebox/Context.universe:()Lscala/reflect/macros/Universe;
        86: ldc           #84                 // String org
        88: invokevirtual #78                 // Method scala/reflect/macros/Universe.newTermName:(Ljava/lang/String;)Lscala/reflect/api/Names$TermNameApi;
        91: checkcast     #12                 // class scala/reflect/api/Names$NameApi
        94: invokevirtual #87                 // Method scala/reflect/api/Trees$SelectExtractor.apply:(Lscala/reflect/api/Trees$TreeApi;Lscala/reflect/api/Names$NameApi;)Lscala/reflect/api/Trees$SelectApi;
        97: aload_1
        98: invokeinterface #62,  1           // InterfaceMethod scala/reflect/macros/whitebox/Context.universe:()Lscala/reflect/macros/Universe;
       103: ldc           #89                 // String scalatest
       105: invokevirtual #78                 // Method scala/reflect/macros/Universe.newTermName:(Ljava/lang/String;)Lscala/reflect/api/Names$TermNameApi;
       108: checkcast     #12                 // class scala/reflect/api/Names$NameApi
       111: invokevirtual #87                 // Method scala/reflect/api/Trees$SelectExtractor.apply:(Lscala/reflect/api/Trees$TreeApi;Lscala/reflect/api/Names$NameApi;)Lscala/reflect/api/Trees$SelectApi;
       114: aload_1
       115: invokeinterface #62,  1           // InterfaceMethod scala/reflect/macros/whitebox/Context.universe:()Lscala/reflect/macros/Universe;
       120: ldc           #91                 // String Assertions
       122: invokevirtual #78                 // Method scala/reflect/macros/Universe.newTermName:(Ljava/lang/String;)Lscala/reflect/api/Names$TermNameApi;
       125: checkcast     #12                 // class scala/reflect/api/Names$NameApi
       128: invokevirtual #87                 // Method scala/reflect/api/Trees$SelectExtractor.apply:(Lscala/reflect/api/Trees$TreeApi;Lscala/reflect/api/Names$NameApi;)Lscala/reflect/api/Trees$SelectApi;
       131: aload_1
       132: invokeinterface #62,  1           // InterfaceMethod scala/reflect/macros/whitebox/Context.universe:()Lscala/reflect/macros/Universe;
       137: ldc           #93                 // String assertionsHelper
       139: invokevirtual #78                 // Method scala/reflect/macros/Universe.newTermName:(Ljava/lang/String;)Lscala/reflect/api/Names$TermNameApi;
       142: checkcast     #12                 // class scala/reflect/api/Names$NameApi
       145: invokevirtual #87                 // Method scala/reflect/api/Trees$SelectExtractor.apply:(Lscala/reflect/api/Trees$TreeApi;Lscala/reflect/api/Names$NameApi;)Lscala/reflect/api/Trees$SelectApi;
       148: aload         5
       150: ldc           #95                 // String macroAssert
       152: aload_1
       153: ldc           #97                 // String
       155: invokeinterface #101,  2          // InterfaceMethod scala/reflect/macros/whitebox/Context.literal:(Ljava/lang/String;)Lscala/reflect/api/Exprs$Expr;
       160: aload         6
       162: aload         7
       164: invokevirtual #105                // Method org/scalactic/BooleanMacro.genMacro:(Lscala/reflect/api/Trees$TreeApi;Lscala/reflect/api/Exprs$Expr;Ljava/lang/String;Lscala/reflect/api/Exprs$Expr;Lscala/reflect/api/Exprs$Expr;Lscala/reflect/api/Exprs$Expr;)Lscala/reflect/api/Exprs$Expr;
       167: areturn
      LineNumberTable:
        line 33: 0
        line 35: 10
        line 36: 18
        line 37: 27
        line 38: 36
        line 39: 45
        line 40: 54
        line 41: 80
        line 43: 97
        line 45: 114
        line 47: 131
        line 49: 148
        line 50: 150
        line 51: 152
        line 52: 160
        line 53: 162
      LocalVariableTable:
        Start  Length  Slot  Name   Signature
            0     168     0  this   Lorg/scalatest/AssertionsMacro$;
            0     168     1 context   Lscala/reflect/macros/whitebox/Context;
            0     168     2 condition   Lscala/reflect/api/Exprs$Expr;
            0     168     3 prettifier   Lscala/reflect/api/Exprs$Expr;
            0     168     4   pos   Lscala/reflect/api/Exprs$Expr;
    Signature: #47                          // (Lscala/reflect/macros/whitebox/Context;Lscala/reflect/api/Exprs$Expr<Ljava/lang/Object;>;Lscala/reflect/api/Exprs$Expr<Lorg/scalactic/Prettifier;>;Lscala/reflect/api/Exprs$Expr<Lorg/scalactic/source/Position;>;)Lscala/reflect/api/Exprs$Expr<Lorg/scalatest/compatible/Assertion;>;
    MethodParameters:
      Name                           Flags
      context                        final
      condition                      final
      prettifier                     final
      pos                            final

  public scala.reflect.api.Exprs$Expr<org.scalatest.compatible.Assertion> assertWithClue(scala.reflect.macros.whitebox.Context, scala.reflect.api.Exprs$Expr<java.lang.Object>, scala.reflect.api.Exprs$Expr<java.lang.Object>, scala.reflect.api.Exprs$Expr<org.scalactic.Prettifier>, scala.reflect.api.Exprs$Expr<org.scalactic.source.Position>);
    descriptor: (Lscala/reflect/macros/whitebox/Context;Lscala/reflect/api/Exprs$Expr;Lscala/reflect/api/Exprs$Expr;Lscala/reflect/api/Exprs$Expr;Lscala/reflect/api/Exprs$Expr;)Lscala/reflect/api/Exprs$Expr;
    flags: (0x0001) ACC_PUBLIC
    Code:
      stack=8, locals=10, args_size=6
         0: aload_2
         1: astore        6
         3: aload_3
         4: astore        7
         6: aload         4
         8: astore        8
        10: aload         5
        12: astore        9
        14: new           #53                 // class org/scalactic/BooleanMacro
        17: dup
        18: aload_1
        19: invokespecial #56                 // Method org/scalactic/BooleanMacro."<init>":(Lscala/reflect/macros/whitebox/Context;)V
        22: aload_1
        23: invokeinterface #62,  1           // InterfaceMethod scala/reflect/macros/whitebox/Context.universe:()Lscala/reflect/macros/Universe;
        28: invokevirtual #68                 // Method scala/reflect/macros/Universe.Select:()Lscala/reflect/api/Trees$SelectExtractor;
        31: aload_1
        32: invokeinterface #62,  1           // InterfaceMethod scala/reflect/macros/whitebox/Context.universe:()Lscala/reflect/macros/Universe;
        37: invokevirtual #68                 // Method scala/reflect/macros/Universe.Select:()Lscala/reflect/api/Trees$SelectExtractor;
        40: aload_1
        41: invokeinterface #62,  1           // InterfaceMethod scala/reflect/macros/whitebox/Context.universe:()Lscala/reflect/macros/Universe;
        46: invokevirtual #68                 // Method scala/reflect/macros/Universe.Select:()Lscala/reflect/api/Trees$SelectExtractor;
        49: aload_1
        50: invokeinterface #62,  1           // InterfaceMethod scala/reflect/macros/whitebox/Context.universe:()Lscala/reflect/macros/Universe;
        55: invokevirtual #68                 // Method scala/reflect/macros/Universe.Select:()Lscala/reflect/api/Trees$SelectExtractor;
        58: aload_1
        59: invokeinterface #62,  1           // InterfaceMethod scala/reflect/macros/whitebox/Context.universe:()Lscala/reflect/macros/Universe;
        64: invokevirtual #72                 // Method scala/reflect/macros/Universe.Ident:()Lscala/reflect/api/Trees$IdentExtractor;
        67: aload_1
        68: invokeinterface #62,  1           // InterfaceMethod scala/reflect/macros/whitebox/Context.universe:()Lscala/reflect/macros/Universe;
        73: ldc           #74                 // String _root_
        75: invokevirtual #78                 // Method scala/reflect/macros/Universe.newTermName:(Ljava/lang/String;)Lscala/reflect/api/Names$TermNameApi;
        78: checkcast     #12                 // class scala/reflect/api/Names$NameApi
        81: invokevirtual #82                 // Method scala/reflect/api/Trees$IdentExtractor.apply:(Lscala/reflect/api/Names$NameApi;)Lscala/reflect/api/Trees$IdentApi;
        84: aload_1
        85: invokeinterface #62,  1           // InterfaceMethod scala/reflect/macros/whitebox/Context.universe:()Lscala/reflect/macros/Universe;
        90: ldc           #84                 // String org
        92: invokevirtual #78                 // Method scala/reflect/macros/Universe.newTermName:(Ljava/lang/String;)Lscala/reflect/api/Names$TermNameApi;
        95: checkcast     #12                 // class scala/reflect/api/Names$NameApi
        98: invokevirtual #87                 // Method scala/reflect/api/Trees$SelectExtractor.apply:(Lscala/reflect/api/Trees$TreeApi;Lscala/reflect/api/Names$NameApi;)Lscala/reflect/api/Trees$SelectApi;
       101: aload_1
       102: invokeinterface #62,  1           // InterfaceMethod scala/reflect/macros/whitebox/Context.universe:()Lscala/reflect/macros/Universe;
       107: ldc           #89                 // String scalatest
       109: invokevirtual #78                 // Method scala/reflect/macros/Universe.newTermName:(Ljava/lang/String;)Lscala/reflect/api/Names$TermNameApi;
       112: checkcast     #12                 // class scala/reflect/api/Names$NameApi
       115: invokevirtual #87                 // Method scala/reflect/api/Trees$SelectExtractor.apply:(Lscala/reflect/api/Trees$TreeApi;Lscala/reflect/api/Names$NameApi;)Lscala/reflect/api/Trees$SelectApi;
       118: aload_1
       119: invokeinterface #62,  1           // InterfaceMethod scala/reflect/macros/whitebox/Context.universe:()Lscala/reflect/macros/Universe;
       124: ldc           #91                 // String Assertions
       126: invokevirtual #78                 // Method scala/reflect/macros/Universe.newTermName:(Ljava/lang/String;)Lscala/reflect/api/Names$TermNameApi;
       129: checkcast     #12                 // class scala/reflect/api/Names$NameApi
       132: invokevirtual #87                 // Method scala/reflect/api/Trees$SelectExtractor.apply:(Lscala/reflect/api/Trees$TreeApi;Lscala/reflect/api/Names$NameApi;)Lscala/reflect/api/Trees$SelectApi;
       135: aload_1
       136: invokeinterface #62,  1           // InterfaceMethod scala/reflect/macros/whitebox/Context.universe:()Lscala/reflect/macros/Universe;
       141: ldc           #93                 // String assertionsHelper
       143: invokevirtual #78                 // Method scala/reflect/macros/Universe.newTermName:(Ljava/lang/String;)Lscala/reflect/api/Names$TermNameApi;
       146: checkcast     #12                 // class scala/reflect/api/Names$NameApi
       149: invokevirtual #87                 // Method scala/reflect/api/Trees$SelectExtractor.apply:(Lscala/reflect/api/Trees$TreeApi;Lscala/reflect/api/Names$NameApi;)Lscala/reflect/api/Trees$SelectApi;
       152: aload         6
       154: ldc           #95                 // String macroAssert
       156: aload         7
       158: aload         8
       160: aload         9
       162: invokevirtual #105                // Method org/scalactic/BooleanMacro.genMacro:(Lscala/reflect/api/Trees$TreeApi;Lscala/reflect/api/Exprs$Expr;Ljava/lang/String;Lscala/reflect/api/Exprs$Expr;Lscala/reflect/api/Exprs$Expr;Lscala/reflect/api/Exprs$Expr;)Lscala/reflect/api/Exprs$Expr;
       165: areturn
      LineNumberTable:
        line 64: 0
        line 66: 14
        line 67: 22
        line 68: 31
        line 69: 40
        line 70: 49
        line 71: 58
        line 72: 84
        line 74: 101
        line 76: 118
        line 78: 135
        line 80: 152
        line 81: 154
        line 82: 156
        line 83: 158
        line 84: 160
      LocalVariableTable:
        Start  Length  Slot  Name   Signature
            0     166     0  this   Lorg/scalatest/AssertionsMacro$;
            0     166     1 context   Lscala/reflect/macros/whitebox/Context;
            0     166     2 condition   Lscala/reflect/api/Exprs$Expr;
            0     166     3  clue   Lscala/reflect/api/Exprs$Expr;
            0     166     4 prettifier   Lscala/reflect/api/Exprs$Expr;
            0     166     5   pos   Lscala/reflect/api/Exprs$Expr;
    Signature: #111                         // (Lscala/reflect/macros/whitebox/Context;Lscala/reflect/api/Exprs$Expr<Ljava/lang/Object;>;Lscala/reflect/api/Exprs$Expr<Ljava/lang/Object;>;Lscala/reflect/api/Exprs$Expr<Lorg/scalactic/Prettifier;>;Lscala/reflect/api/Exprs$Expr<Lorg/scalactic/source/Position;>;)Lscala/reflect/api/Exprs$Expr<Lorg/scalatest/compatible/Assertion;>;
    MethodParameters:
      Name                           Flags
      context                        final
      condition                      final
      clue                           final
      prettifier                     final
      pos                            final

  public scala.reflect.api.Exprs$Expr<org.scalatest.compatible.Assertion> assume(scala.reflect.macros.whitebox.Context, scala.reflect.api.Exprs$Expr<java.lang.Object>, scala.reflect.api.Exprs$Expr<org.scalactic.Prettifier>, scala.reflect.api.Exprs$Expr<org.scalactic.source.Position>);
    descriptor: (Lscala/reflect/macros/whitebox/Context;Lscala/reflect/api/Exprs$Expr;Lscala/reflect/api/Exprs$Expr;Lscala/reflect/api/Exprs$Expr;)Lscala/reflect/api/Exprs$Expr;
    flags: (0x0001) ACC_PUBLIC
    Code:
      stack=8, locals=8, args_size=5
         0: aload_2
         1: astore        5
         3: aload_3
         4: astore        6
         6: aload         4
         8: astore        7
        10: new           #53                 // class org/scalactic/BooleanMacro
        13: dup
        14: aload_1
        15: invokespecial #56                 // Method org/scalactic/BooleanMacro."<init>":(Lscala/reflect/macros/whitebox/Context;)V
        18: aload_1
        19: invokeinterface #62,  1           // InterfaceMethod scala/reflect/macros/whitebox/Context.universe:()Lscala/reflect/macros/Universe;
        24: invokevirtual #68                 // Method scala/reflect/macros/Universe.Select:()Lscala/reflect/api/Trees$SelectExtractor;
        27: aload_1
        28: invokeinterface #62,  1           // InterfaceMethod scala/reflect/macros/whitebox/Context.universe:()Lscala/reflect/macros/Universe;
        33: invokevirtual #68                 // Method scala/reflect/macros/Universe.Select:()Lscala/reflect/api/Trees$SelectExtractor;
        36: aload_1
        37: invokeinterface #62,  1           // InterfaceMethod scala/reflect/macros/whitebox/Context.universe:()Lscala/reflect/macros/Universe;
        42: invokevirtual #68                 // Method scala/reflect/macros/Universe.Select:()Lscala/reflect/api/Trees$SelectExtractor;
        45: aload_1
        46: invokeinterface #62,  1           // InterfaceMethod scala/reflect/macros/whitebox/Context.universe:()Lscala/reflect/macros/Universe;
        51: invokevirtual #68                 // Method scala/reflect/macros/Universe.Select:()Lscala/reflect/api/Trees$SelectExtractor;
        54: aload_1
        55: invokeinterface #62,  1           // InterfaceMethod scala/reflect/macros/whitebox/Context.universe:()Lscala/reflect/macros/Universe;
        60: invokevirtual #72                 // Method scala/reflect/macros/Universe.Ident:()Lscala/reflect/api/Trees$IdentExtractor;
        63: aload_1
        64: invokeinterface #62,  1           // InterfaceMethod scala/reflect/macros/whitebox/Context.universe:()Lscala/reflect/macros/Universe;
        69: ldc           #74                 // String _root_
        71: invokevirtual #78                 // Method scala/reflect/macros/Universe.newTermName:(Ljava/lang/String;)Lscala/reflect/api/Names$TermNameApi;
        74: checkcast     #12                 // class scala/reflect/api/Names$NameApi
        77: invokevirtual #82                 // Method scala/reflect/api/Trees$IdentExtractor.apply:(Lscala/reflect/api/Names$NameApi;)Lscala/reflect/api/Trees$IdentApi;
        80: aload_1
        81: invokeinterface #62,  1           // InterfaceMethod scala/reflect/macros/whitebox/Context.universe:()Lscala/reflect/macros/Universe;
        86: ldc           #84                 // String org
        88: invokevirtual #78                 // Method scala/reflect/macros/Universe.newTermName:(Ljava/lang/String;)Lscala/reflect/api/Names$TermNameApi;
        91: checkcast     #12                 // class scala/reflect/api/Names$NameApi
        94: invokevirtual #87                 // Method scala/reflect/api/Trees$SelectExtractor.apply:(Lscala/reflect/api/Trees$TreeApi;Lscala/reflect/api/Names$NameApi;)Lscala/reflect/api/Trees$SelectApi;
        97: aload_1
        98: invokeinterface #62,  1           // InterfaceMethod scala/reflect/macros/whitebox/Context.universe:()Lscala/reflect/macros/Universe;
       103: ldc           #89                 // String scalatest
       105: invokevirtual #78                 // Method scala/reflect/macros/Universe.newTermName:(Ljava/lang/String;)Lscala/reflect/api/Names$TermNameApi;
       108: checkcast     #12                 // class scala/reflect/api/Names$NameApi
       111: invokevirtual #87                 // Method scala/reflect/api/Trees$SelectExtractor.apply:(Lscala/reflect/api/Trees$TreeApi;Lscala/reflect/api/Names$NameApi;)Lscala/reflect/api/Trees$SelectApi;
       114: aload_1
       115: invokeinterface #62,  1           // InterfaceMethod scala/reflect/macros/whitebox/Context.universe:()Lscala/reflect/macros/Universe;
       120: ldc           #91                 // String Assertions
       122: invokevirtual #78                 // Method scala/reflect/macros/Universe.newTermName:(Ljava/lang/String;)Lscala/reflect/api/Names$TermNameApi;
       125: checkcast     #12                 // class scala/reflect/api/Names$NameApi
       128: invokevirtual #87                 // Method scala/reflect/api/Trees$SelectExtractor.apply:(Lscala/reflect/api/Trees$TreeApi;Lscala/reflect/api/Names$NameApi;)Lscala/reflect/api/Trees$SelectApi;
       131: aload_1
       132: invokeinterface #62,  1           // InterfaceMethod scala/reflect/macros/whitebox/Context.universe:()Lscala/reflect/macros/Universe;
       137: ldc           #93                 // String assertionsHelper
       139: invokevirtual #78                 // Method scala/reflect/macros/Universe.newTermName:(Ljava/lang/String;)Lscala/reflect/api/Names$TermNameApi;
       142: checkcast     #12                 // class scala/reflect/api/Names$NameApi
       145: invokevirtual #87                 // Method scala/reflect/api/Trees$SelectExtractor.apply:(Lscala/reflect/api/Trees$TreeApi;Lscala/reflect/api/Names$NameApi;)Lscala/reflect/api/Trees$SelectApi;
       148: aload         5
       150: ldc           #115                // String macroAssume
       152: aload_1
       153: ldc           #97                 // String
       155: invokeinterface #101,  2          // InterfaceMethod scala/reflect/macros/whitebox/Context.literal:(Ljava/lang/String;)Lscala/reflect/api/Exprs$Expr;
       160: aload         6
       162: aload         7
       164: invokevirtual #105                // Method org/scalactic/BooleanMacro.genMacro:(Lscala/reflect/api/Trees$TreeApi;Lscala/reflect/api/Exprs$Expr;Ljava/lang/String;Lscala/reflect/api/Exprs$Expr;Lscala/reflect/api/Exprs$Expr;Lscala/reflect/api/Exprs$Expr;)Lscala/reflect/api/Exprs$Expr;
       167: areturn
      LineNumberTable:
        line 94: 0
        line 96: 10
        line 97: 18
        line 98: 27
        line 99: 36
        line 100: 45
        line 101: 54
        line 102: 80
        line 104: 97
        line 106: 114
        line 108: 131
        line 110: 148
        line 111: 150
        line 112: 152
        line 113: 160
        line 114: 162
      LocalVariableTable:
        Start  Length  Slot  Name   Signature
            0     168     0  this   Lorg/scalatest/AssertionsMacro$;
            0     168     1 context   Lscala/reflect/macros/whitebox/Context;
            0     168     2 condition   Lscala/reflect/api/Exprs$Expr;
            0     168     3 prettifier   Lscala/reflect/api/Exprs$Expr;
            0     168     4   pos   Lscala/reflect/api/Exprs$Expr;
    Signature: #47                          // (Lscala/reflect/macros/whitebox/Context;Lscala/reflect/api/Exprs$Expr<Ljava/lang/Object;>;Lscala/reflect/api/Exprs$Expr<Lorg/scalactic/Prettifier;>;Lscala/reflect/api/Exprs$Expr<Lorg/scalactic/source/Position;>;)Lscala/reflect/api/Exprs$Expr<Lorg/scalatest/compatible/Assertion;>;
    MethodParameters:
      Name                           Flags
      context                        final
      condition                      final
      prettifier                     final
      pos                            final

  public scala.reflect.api.Exprs$Expr<org.scalatest.compatible.Assertion> assumeWithClue(scala.reflect.macros.whitebox.Context, scala.reflect.api.Exprs$Expr<java.lang.Object>, scala.reflect.api.Exprs$Expr<java.lang.Object>, scala.reflect.api.Exprs$Expr<org.scalactic.Prettifier>, scala.reflect.api.Exprs$Expr<org.scalactic.source.Position>);
    descriptor: (Lscala/reflect/macros/whitebox/Context;Lscala/reflect/api/Exprs$Expr;Lscala/reflect/api/Exprs$Expr;Lscala/reflect/api/Exprs$Expr;Lscala/reflect/api/Exprs$Expr;)Lscala/reflect/api/Exprs$Expr;
    flags: (0x0001) ACC_PUBLIC
    Code:
      stack=8, locals=10, args_size=6
         0: aload_2
         1: astore        6
         3: aload_3
         4: astore        7
         6: aload         4
         8: astore        8
        10: aload         5
        12: astore        9
        14: new           #53                 // class org/scalactic/BooleanMacro
        17: dup
        18: aload_1
        19: invokespecial #56                 // Method org/scalactic/BooleanMacro."<init>":(Lscala/reflect/macros/whitebox/Context;)V
        22: aload_1
        23: invokeinterface #62,  1           // InterfaceMethod scala/reflect/macros/whitebox/Context.universe:()Lscala/reflect/macros/Universe;
        28: invokevirtual #68                 // Method scala/reflect/macros/Universe.Select:()Lscala/reflect/api/Trees$SelectExtractor;
        31: aload_1
        32: invokeinterface #62,  1           // InterfaceMethod scala/reflect/macros/whitebox/Context.universe:()Lscala/reflect/macros/Universe;
        37: invokevirtual #68                 // Method scala/reflect/macros/Universe.Select:()Lscala/reflect/api/Trees$SelectExtractor;
        40: aload_1
        41: invokeinterface #62,  1           // InterfaceMethod scala/reflect/macros/whitebox/Context.universe:()Lscala/reflect/macros/Universe;
        46: invokevirtual #68                 // Method scala/reflect/macros/Universe.Select:()Lscala/reflect/api/Trees$SelectExtractor;
        49: aload_1
        50: invokeinterface #62,  1           // InterfaceMethod scala/reflect/macros/whitebox/Context.universe:()Lscala/reflect/macros/Universe;
        55: invokevirtual #68                 // Method scala/reflect/macros/Universe.Select:()Lscala/reflect/api/Trees$SelectExtractor;
        58: aload_1
        59: invokeinterface #62,  1           // InterfaceMethod scala/reflect/macros/whitebox/Context.universe:()Lscala/reflect/macros/Universe;
        64: invokevirtual #72                 // Method scala/reflect/macros/Universe.Ident:()Lscala/reflect/api/Trees$IdentExtractor;
        67: aload_1
        68: invokeinterface #62,  1           // InterfaceMethod scala/reflect/macros/whitebox/Context.universe:()Lscala/reflect/macros/Universe;
        73: ldc           #74                 // String _root_
        75: invokevirtual #78                 // Method scala/reflect/macros/Universe.newTermName:(Ljava/lang/String;)Lscala/reflect/api/Names$TermNameApi;
        78: checkcast     #12                 // class scala/reflect/api/Names$NameApi
        81: invokevirtual #82                 // Method scala/reflect/api/Trees$IdentExtractor.apply:(Lscala/reflect/api/Names$NameApi;)Lscala/reflect/api/Trees$IdentApi;
        84: aload_1
        85: invokeinterface #62,  1           // InterfaceMethod scala/reflect/macros/whitebox/Context.universe:()Lscala/reflect/macros/Universe;
        90: ldc           #84                 // String org
        92: invokevirtual #78                 // Method scala/reflect/macros/Universe.newTermName:(Ljava/lang/String;)Lscala/reflect/api/Names$TermNameApi;
        95: checkcast     #12                 // class scala/reflect/api/Names$NameApi
        98: invokevirtual #87                 // Method scala/reflect/api/Trees$SelectExtractor.apply:(Lscala/reflect/api/Trees$TreeApi;Lscala/reflect/api/Names$NameApi;)Lscala/reflect/api/Trees$SelectApi;
       101: aload_1
       102: invokeinterface #62,  1           // InterfaceMethod scala/reflect/macros/whitebox/Context.universe:()Lscala/reflect/macros/Universe;
       107: ldc           #89                 // String scalatest
       109: invokevirtual #78                 // Method scala/reflect/macros/Universe.newTermName:(Ljava/lang/String;)Lscala/reflect/api/Names$TermNameApi;
       112: checkcast     #12                 // class scala/reflect/api/Names$NameApi
       115: invokevirtual #87                 // Method scala/reflect/api/Trees$SelectExtractor.apply:(Lscala/reflect/api/Trees$TreeApi;Lscala/reflect/api/Names$NameApi;)Lscala/reflect/api/Trees$SelectApi;
       118: aload_1
       119: invokeinterface #62,  1           // InterfaceMethod scala/reflect/macros/whitebox/Context.universe:()Lscala/reflect/macros/Universe;
       124: ldc           #91                 // String Assertions
       126: invokevirtual #78                 // Method scala/reflect/macros/Universe.newTermName:(Ljava/lang/String;)Lscala/reflect/api/Names$TermNameApi;
       129: checkcast     #12                 // class scala/reflect/api/Names$NameApi
       132: invokevirtual #87                 // Method scala/reflect/api/Trees$SelectExtractor.apply:(Lscala/reflect/api/Trees$TreeApi;Lscala/reflect/api/Names$NameApi;)Lscala/reflect/api/Trees$SelectApi;
       135: aload_1
       136: invokeinterface #62,  1           // InterfaceMethod scala/reflect/macros/whitebox/Context.universe:()Lscala/reflect/macros/Universe;
       141: ldc           #93                 // String assertionsHelper
       143: invokevirtual #78                 // Method scala/reflect/macros/Universe.newTermName:(Ljava/lang/String;)Lscala/reflect/api/Names$TermNameApi;
       146: checkcast     #12                 // class scala/reflect/api/Names$NameApi
       149: invokevirtual #87                 // Method scala/reflect/api/Trees$SelectExtractor.apply:(Lscala/reflect/api/Trees$TreeApi;Lscala/reflect/api/Names$NameApi;)Lscala/reflect/api/Trees$SelectApi;
       152: aload         6
       154: ldc           #115                // String macroAssume
       156: aload         7
       158: aload         8
       160: aload         9
       162: invokevirtual #105                // Method org/scalactic/BooleanMacro.genMacro:(Lscala/reflect/api/Trees$TreeApi;Lscala/reflect/api/Exprs$Expr;Ljava/lang/String;Lscala/reflect/api/Exprs$Expr;Lscala/reflect/api/Exprs$Expr;Lscala/reflect/api/Exprs$Expr;)Lscala/reflect/api/Exprs$Expr;
       165: areturn
      LineNumberTable:
        line 125: 0
        line 127: 14
        line 128: 22
        line 129: 31
        line 130: 40
        line 131: 49
        line 132: 58
        line 133: 84
        line 135: 101
        line 137: 118
        line 139: 135
        line 141: 152
        line 142: 154
        line 143: 156
        line 144: 158
        line 145: 160
      LocalVariableTable:
        Start  Length  Slot  Name   Signature
            0     166     0  this   Lorg/scalatest/AssertionsMacro$;
            0     166     1 context   Lscala/reflect/macros/whitebox/Context;
            0     166     2 condition   Lscala/reflect/api/Exprs$Expr;
            0     166     3  clue   Lscala/reflect/api/Exprs$Expr;
            0     166     4 prettifier   Lscala/reflect/api/Exprs$Expr;
            0     166     5   pos   Lscala/reflect/api/Exprs$Expr;
    Signature: #111                         // (Lscala/reflect/macros/whitebox/Context;Lscala/reflect/api/Exprs$Expr<Ljava/lang/Object;>;Lscala/reflect/api/Exprs$Expr<Ljava/lang/Object;>;Lscala/reflect/api/Exprs$Expr<Lorg/scalactic/Prettifier;>;Lscala/reflect/api/Exprs$Expr<Lorg/scalactic/source/Position;>;)Lscala/reflect/api/Exprs$Expr<Lorg/scalatest/compatible/Assertion;>;
    MethodParameters:
      Name                           Flags
      context                        final
      condition                      final
      clue                           final
      prettifier                     final
      pos                            final

  private org.scalatest.AssertionsMacro$();
    descriptor: ()V
    flags: (0x0002) ACC_PRIVATE
    Code:
      stack=1, locals=1, args_size=1
         0: aload_0
         1: invokespecial #117                // Method java/lang/Object."<init>":()V
         4: return
      LineNumberTable:
        line 147: 0
        line 24: 4
      LocalVariableTable:
        Start  Length  Slot  Name   Signature
            0       5     0  this   Lorg/scalatest/AssertionsMacro$;
}
InnerClasses:
  public #10= #7 of #9;                   // Expr=class scala/reflect/api/Exprs$Expr of class scala/reflect/api/Exprs
  public abstract #15= #12 of #14;        // NameApi=class scala/reflect/api/Names$NameApi of class scala/reflect/api/Names
  public #18= #17 of #14;                 // TermNameApi=class scala/reflect/api/Names$TermNameApi of class scala/reflect/api/Names
  public #23= #20 of #22;                 // IdentApi=class scala/reflect/api/Trees$IdentApi of class scala/reflect/api/Trees
  public abstract #26= #25 of #22;        // IdentExtractor=class scala/reflect/api/Trees$IdentExtractor of class scala/reflect/api/Trees
  public #29= #28 of #22;                 // SelectApi=class scala/reflect/api/Trees$SelectApi of class scala/reflect/api/Trees
  public abstract #32= #31 of #22;        // SelectExtractor=class scala/reflect/api/Trees$SelectExtractor of class scala/reflect/api/Trees
  public #35= #34 of #22;                 // TreeApi=class scala/reflect/api/Trees$TreeApi of class scala/reflect/api/Trees
SourceFile: "AssertionsMacro.scala"
  ScalaInlineInfo: length = 0x1D (unknown attribute)
   01 01 00 05 00 28 00 27 01 00 2D 00 2E 01 00 6D
   00 6E 01 00 71 00 2E 01 00 74 00 6E 01
  Scala: length = 0x0 (unknown attribute)

