Classfile /Users/mw/Projects/slang-braindump/.jar/jar11/assemble/slang-braindump/assemble/content/org/scalatest/AsyncTestSuite.class
  Last modified May 29, 2022; size 7865 bytes
  SHA-256 checksum 2c547ea9cd51e55c470450813f993c977bdf72e95e076437ffaa7a5c3fde444a
  Compiled from "AsyncTestSuite.scala"
public interface org.scalatest.AsyncTestSuite extends org.scalatest.Suite,org.scalatest.RecoverMethods,org.scalatest.CompleteLastly
  minor version: 0
  major version: 52
  flags: (0x0601) ACC_PUBLIC, ACC_INTERFACE, ACC_ABSTRACT
  this_class: #2                          // org/scalatest/AsyncTestSuite
  super_class: #4                         // java/lang/Object
  interfaces: 3, fields: 0, methods: 20, attributes: 6
Constant pool:
    #1 = Utf8               org/scalatest/AsyncTestSuite
    #2 = Class              #1            // org/scalatest/AsyncTestSuite
    #3 = Utf8               java/lang/Object
    #4 = Class              #3            // java/lang/Object
    #5 = Utf8               org/scalatest/Suite
    #6 = Class              #5            // org/scalatest/Suite
    #7 = Utf8               org/scalatest/RecoverMethods
    #8 = Class              #7            // org/scalatest/RecoverMethods
    #9 = Utf8               org/scalatest/CompleteLastly
   #10 = Class              #9            // org/scalatest/CompleteLastly
   #11 = Utf8               AsyncTestSuite.scala
   #12 = Utf8               Lscala/reflect/ScalaSignature;
   #13 = Utf8               bytes
   #14 = Utf8               \u0006\u0005\u0005-aa\u0002\u0007\u000e!\u0003\r\tA\u0005\u0005\u0006G\u0001!\t\u0001\n\u0005\bQ\u0001\u0011\r\u0011\"\u0004*\u0011\u0015\u0001\u0004\u0001b\u0001*\u0011\u0015\t\u0004\u0001\"\u00033\u0011\u0019!\u0005\u0001\"\u0001\u000e\u000b\")!\f\u0001C\u00027\"1a\f\u0001C\t\u001b}3q\u0001\u0019\u0001\u0011\u0002G\u0005\u0011\rC\u0003j\u0011\u0019\u0005!\u000eC\u0003l\u0001\u0011\u0005A\u000eC\u0003r\u0001\u0011E#O\u0001\bBgft7\rV3tiN+\u0018\u000e^3\u000b\u00059y\u0011!C:dC2\fG/Z:u\u0015\u0005\u0001\u0012aA8sO\u000e\u00011#\u0002\u0001\u00143u\u0001\u0003C\u0001\u000b\u0018\u001b\u0005)\"\"\u0001\f\u0002\u000bM\u001c\u0017\r\\1\n\u0005a)\"AB!osJ+g\r\u0005\u0002\u001b75\tQ\"\u0003\u0002\u001d\u001b\t)1+^5uKB\u0011!DH\u0005\u0003?5\u0011aBU3d_Z,\'/T3uQ>$7\u000f\u0005\u0002\u001bC%\u0011!%\u0004\u0002\u000f\u0007>l\u0007\u000f\\3uK2\u000b7\u000f\u001e7z\u0003\u0019!\u0013N\\5uIQ\tQ\u0005\u0005\u0002\u0015M%\u0011q%\u0006\u0002\u0005+:LG/\u0001\ftKJL\u0017\r\\#yK\u000e,H/[8o\u0007>tG/\u001a=u+\u0005Q\u0003CA\u0016/\u001b\u0005a#BA\u0017\u0016\u0003)\u0019wN\\2veJ,g\u000e^\u0005\u0003_1\u0012\u0001#\u0012=fGV$\u0018n\u001c8D_:$X\r\u001f;\u0002!\u0015DXmY;uS>t7i\u001c8uKb$\u0018AJ1o\u0003NLhnY#yG\u0016\u0004H/[8o)\"\fGo\u00155pk2$7)Y;tK\u0006s\u0017IY8siR\u00111G\u000e\t\u0003)QJ!!N\u000b\u0003\u000f\t{w\u000e\\3b]\")q\u0007\u0002a\u0001q\u0005\u0011Q\r\u001f\t\u0003s\u0005s!AO \u000f\u0005mrT\"\u0001\u001f\u000b\u0005u\n\u0012A\u0002\u001fs_>$h(C\u0001\u0017\u0013\t\u0001U#A\u0004qC\u000e\\\u0017mZ3\n\u0005\t\u001b%!\u0003+ie><\u0018M\u00197f\u0015\t\u0001U#\u0001\nue\u0006t7OZ8s[R{w*\u001e;d_6,GC\u0001$M!\r!r)S\u0005\u0003\u0011V\u0011\u0011BR;oGRLwN\u001c\u0019\u0011\u0005iQ\u0015BA&\u000e\u0005=\t5/\u001f8d)\u0016\u001cH\u000fS8mI\u0016\u0014\bBB\'\u0006\t\u0003\u0007a*A\u0004uKN$h)\u001e8\u0011\u0007Qy\u0015+\u0003\u0002Q+\tAAHY=oC6,g\bE\u0002,%RK!a\u0015\u0017\u0003\r\u0019+H/\u001e:f!\t)\u0006,D\u0001W\u0015\t9V\"\u0001\u0006d_6\u0004\u0018\r^5cY\u0016L!!\u0017,\u0003\u0013\u0005\u001b8/\u001a:uS>t\u0017!I2p]Z,\'\u000f^!tg\u0016\u0014H/[8o)>4U\u000f^;sK\u0006\u001b8/\u001a:uS>tGCA)]\u0011\u0015if\u00011\u0001U\u0003%\t7o]3si&|g.\u0001\u000eqCJ\fG\u000e\\3m\u0003NLhn\u0019+fgR,\u00050Z2vi&|g.F\u00014\u00059qu.\u0011:h\u0003NLhn\u0019+fgR\u001cB\u0001C\ncMB\u0019AcR2\u0011\u0005i!\u0017BA3\u000e\u000551U\u000f^;sK>+HoY8nKB\u0011!dZ\u0005\u0003Q6\u0011\u0001\u0002V3ti\u0012\u000bG/Y\u0001\u0006CB\u0004H.\u001f\u000b\u0002G\u0006Yq/\u001b;i\r&DH/\u001e:f)\t\u0019W\u000eC\u0003o\u0015\u0001\u0007q.\u0001\u0003uKN$\bC\u00019\t\u001b\u0005\u0001\u0011a\u0002:v]R+7\u000f\u001e\u000b\u0005gZ\f\t\u0001\u0005\u0002\u001bi&\u0011Q/\u0004\u0002\u0007\'R\fG/^:\t\u000b]\\\u0001\u0019\u0001=\u0002\u0011Q,7\u000f\u001e(b[\u0016\u0004\"!_?\u000f\u0005i\\\bCA\u001e\u0016\u0013\taX#\u0001\u0004Qe\u0016$WMZ\u0005\u0003}~\u0014aa\u0015;sS:<\'B\u0001?\u0016\u0011\u001d\t\u0019a\u0003a\u0001\u0003\u000b\tA!\u0019:hgB\u0019!$a\u0002\n\u0007\u0005%QB\u0001\u0003Be\u001e\u001c\b
   #15 = Utf8               java/lang/invoke/MethodHandles$Lookup
   #16 = Class              #15           // java/lang/invoke/MethodHandles$Lookup
   #17 = Utf8               java/lang/invoke/MethodHandles
   #18 = Class              #17           // java/lang/invoke/MethodHandles
   #19 = Utf8               Lookup
   #20 = Utf8               org/scalatest/AsyncTestSuite$$anonfun$$nestedInanonfun$transformToOutcome$1$1
   #21 = Class              #20           // org/scalatest/AsyncTestSuite$$anonfun$$nestedInanonfun$transformToOutcome$1$1
   #22 = Utf8               org/scalatest/AsyncTestSuite$NoArgAsyncTest
   #23 = Class              #22           // org/scalatest/AsyncTestSuite$NoArgAsyncTest
   #24 = Utf8               NoArgAsyncTest
   #25 = Utf8               org$scalatest$AsyncTestSuite$_setter_$org$scalatest$AsyncTestSuite$$serialExecutionContext_$eq
   #26 = Utf8               (Lscala/concurrent/ExecutionContext;)V
   #27 = Utf8               x$1
   #28 = Utf8               org$scalatest$AsyncTestSuite$$serialExecutionContext
   #29 = Utf8               ()Lscala/concurrent/ExecutionContext;
   #30 = Utf8               executionContext$
   #31 = Utf8               (Lorg/scalatest/AsyncTestSuite;)Lscala/concurrent/ExecutionContext;
   #32 = Utf8               $this
   #33 = Utf8               executionContext
   #34 = NameAndType        #33:#29       // executionContext:()Lscala/concurrent/ExecutionContext;
   #35 = InterfaceMethodref #2.#34        // org/scalatest/AsyncTestSuite.executionContext:()Lscala/concurrent/ExecutionContext;
   #36 = Utf8               Lorg/scalatest/AsyncTestSuite;
   #37 = NameAndType        #28:#29       // org$scalatest$AsyncTestSuite$$serialExecutionContext:()Lscala/concurrent/ExecutionContext;
   #38 = InterfaceMethodref #2.#37        // org/scalatest/AsyncTestSuite.org$scalatest$AsyncTestSuite$$serialExecutionContext:()Lscala/concurrent/ExecutionContext;
   #39 = Utf8               this
   #40 = Utf8               org$scalatest$AsyncTestSuite$$anAsyncExceptionThatShouldCauseAnAbort$
   #41 = Utf8               (Lorg/scalatest/AsyncTestSuite;Ljava/lang/Throwable;)Z
   #42 = Utf8               ex
   #43 = Utf8               org$scalatest$AsyncTestSuite$$anAsyncExceptionThatShouldCauseAnAbort
   #44 = Utf8               (Ljava/lang/Throwable;)Z
   #45 = NameAndType        #43:#44       // org$scalatest$AsyncTestSuite$$anAsyncExceptionThatShouldCauseAnAbort:(Ljava/lang/Throwable;)Z
   #46 = InterfaceMethodref #2.#45        // org/scalatest/AsyncTestSuite.org$scalatest$AsyncTestSuite$$anAsyncExceptionThatShouldCauseAnAbort:(Ljava/lang/Throwable;)Z
   #47 = Utf8               Ljava/lang/Throwable;
   #48 = Utf8               java/util/concurrent/ExecutionException
   #49 = Class              #48           // java/util/concurrent/ExecutionException
   #50 = Utf8               java/lang/Throwable
   #51 = Class              #50           // java/lang/Throwable
   #52 = Utf8               getCause
   #53 = Utf8               ()Ljava/lang/Throwable;
   #54 = NameAndType        #52:#53       // getCause:()Ljava/lang/Throwable;
   #55 = Methodref          #51.#54       // java/lang/Throwable.getCause:()Ljava/lang/Throwable;
   #56 = Utf8               org/scalatest/Suite$
   #57 = Class              #56           // org/scalatest/Suite$
   #58 = Utf8               MODULE$
   #59 = Utf8               Lorg/scalatest/Suite$;
   #60 = NameAndType        #58:#59       // MODULE$:Lorg/scalatest/Suite$;
   #61 = Fieldref           #57.#60       // org/scalatest/Suite$.MODULE$:Lorg/scalatest/Suite$;
   #62 = Utf8               anExceptionThatShouldCauseAnAbort
   #63 = NameAndType        #62:#44       // anExceptionThatShouldCauseAnAbort:(Ljava/lang/Throwable;)Z
   #64 = Methodref          #57.#63       // org/scalatest/Suite$.anExceptionThatShouldCauseAnAbort:(Ljava/lang/Throwable;)Z
   #65 = Utf8               transformToOutcome$
   #66 = Utf8               (Lorg/scalatest/AsyncTestSuite;Lscala/Function0;)Lscala/Function0;
   #67 = Utf8               testFun
   #68 = Utf8               transformToOutcome
   #69 = Utf8               (Lscala/Function0;)Lscala/Function0;
   #70 = NameAndType        #68:#69       // transformToOutcome:(Lscala/Function0;)Lscala/Function0;
   #71 = InterfaceMethodref #2.#70        // org/scalatest/AsyncTestSuite.transformToOutcome:(Lscala/Function0;)Lscala/Function0;
   #72 = Utf8               Lscala/Function0;
   #73 = Utf8               (Lscala/Function0<Lscala/concurrent/Future<Lorg/scalatest/compatible/Assertion;>;>;)Lscala/Function0<Lorg/scalatest/AsyncTestHolder;>;
   #74 = Utf8               ()Ljava/lang/Object;
   #75 = MethodType         #74           //  ()Ljava/lang/Object;
   #76 = Utf8               $anonfun$transformToOutcome$1
   #77 = Utf8               (Lorg/scalatest/AsyncTestSuite;Lscala/Function0;)Lorg/scalatest/FutureAsyncTestHolder;
   #78 = NameAndType        #76:#77       // $anonfun$transformToOutcome$1:(Lorg/scalatest/AsyncTestSuite;Lscala/Function0;)Lorg/scalatest/FutureAsyncTestHolder;
   #79 = InterfaceMethodref #2.#78        // org/scalatest/AsyncTestSuite.$anonfun$transformToOutcome$1:(Lorg/scalatest/AsyncTestSuite;Lscala/Function0;)Lorg/scalatest/FutureAsyncTestHolder;
   #80 = MethodHandle       6:#79         // REF_invokeStatic org/scalatest/AsyncTestSuite.$anonfun$transformToOutcome$1:(Lorg/scalatest/AsyncTestSuite;Lscala/Function0;)Lorg/scalatest/FutureAsyncTestHolder;
   #81 = Utf8               ()Lorg/scalatest/FutureAsyncTestHolder;
   #82 = MethodType         #81           //  ()Lorg/scalatest/FutureAsyncTestHolder;
   #83 = Integer            5
   #84 = Integer            1
   #85 = Utf8               java/lang/invoke/LambdaMetafactory
   #86 = Class              #85           // java/lang/invoke/LambdaMetafactory
   #87 = Utf8               altMetafactory
   #88 = Utf8               (Ljava/lang/invoke/MethodHandles$Lookup;Ljava/lang/String;Ljava/lang/invoke/MethodType;[Ljava/lang/Object;)Ljava/lang/invoke/CallSite;
   #89 = NameAndType        #87:#88       // altMetafactory:(Ljava/lang/invoke/MethodHandles$Lookup;Ljava/lang/String;Ljava/lang/invoke/MethodType;[Ljava/lang/Object;)Ljava/lang/invoke/CallSite;
   #90 = Methodref          #86.#89       // java/lang/invoke/LambdaMetafactory.altMetafactory:(Ljava/lang/invoke/MethodHandles$Lookup;Ljava/lang/String;Ljava/lang/invoke/MethodType;[Ljava/lang/Object;)Ljava/lang/invoke/CallSite;
   #91 = MethodHandle       6:#90         // REF_invokeStatic java/lang/invoke/LambdaMetafactory.altMetafactory:(Ljava/lang/invoke/MethodHandles$Lookup;Ljava/lang/String;Ljava/lang/invoke/MethodType;[Ljava/lang/Object;)Ljava/lang/invoke/CallSite;
   #92 = Utf8               apply
   #93 = NameAndType        #92:#66       // apply:(Lorg/scalatest/AsyncTestSuite;Lscala/Function0;)Lscala/Function0;
   #94 = InvokeDynamic      #0:#93        // #0:apply:(Lorg/scalatest/AsyncTestSuite;Lscala/Function0;)Lscala/Function0;
   #95 = Utf8               convertAssertionToFutureAssertion$
   #96 = Utf8               (Lorg/scalatest/AsyncTestSuite;Lorg/scalatest/compatible/Assertion;)Lscala/concurrent/Future;
   #97 = Utf8               assertion
   #98 = Utf8               convertAssertionToFutureAssertion
   #99 = Utf8               (Lorg/scalatest/compatible/Assertion;)Lscala/concurrent/Future;
  #100 = NameAndType        #98:#99       // convertAssertionToFutureAssertion:(Lorg/scalatest/compatible/Assertion;)Lscala/concurrent/Future;
  #101 = InterfaceMethodref #2.#100       // org/scalatest/AsyncTestSuite.convertAssertionToFutureAssertion:(Lorg/scalatest/compatible/Assertion;)Lscala/concurrent/Future;
  #102 = Utf8               Lorg/scalatest/compatible/Assertion;
  #103 = Utf8               (Lorg/scalatest/compatible/Assertion;)Lscala/concurrent/Future<Lorg/scalatest/compatible/Assertion;>;
  #104 = Utf8               scala/concurrent/Future$
  #105 = Class              #104          // scala/concurrent/Future$
  #106 = Utf8               Lscala/concurrent/Future$;
  #107 = NameAndType        #58:#106      // MODULE$:Lscala/concurrent/Future$;
  #108 = Fieldref           #105.#107     // scala/concurrent/Future$.MODULE$:Lscala/concurrent/Future$;
  #109 = Utf8               successful
  #110 = Utf8               (Ljava/lang/Object;)Lscala/concurrent/Future;
  #111 = NameAndType        #109:#110     // successful:(Ljava/lang/Object;)Lscala/concurrent/Future;
  #112 = Methodref          #105.#111     // scala/concurrent/Future$.successful:(Ljava/lang/Object;)Lscala/concurrent/Future;
  #113 = Utf8               parallelAsyncTestExecution$
  #114 = Utf8               (Lorg/scalatest/AsyncTestSuite;)Z
  #115 = Utf8               parallelAsyncTestExecution
  #116 = Utf8               ()Z
  #117 = NameAndType        #115:#116     // parallelAsyncTestExecution:()Z
  #118 = InterfaceMethodref #2.#117       // org/scalatest/AsyncTestSuite.parallelAsyncTestExecution:()Z
  #119 = Utf8               org/scalatest/ParallelTestExecution
  #120 = Class              #119          // org/scalatest/ParallelTestExecution
  #121 = Utf8               org/scalatest/RandomTestOrder
  #122 = Class              #121          // org/scalatest/RandomTestOrder
  #123 = Utf8               withFixture$
  #124 = Utf8               (Lorg/scalatest/AsyncTestSuite;Lorg/scalatest/AsyncTestSuite$NoArgAsyncTest;)Lorg/scalatest/FutureOutcome;
  #125 = Utf8               test
  #126 = Utf8               withFixture
  #127 = Utf8               (Lorg/scalatest/AsyncTestSuite$NoArgAsyncTest;)Lorg/scalatest/FutureOutcome;
  #128 = NameAndType        #126:#127     // withFixture:(Lorg/scalatest/AsyncTestSuite$NoArgAsyncTest;)Lorg/scalatest/FutureOutcome;
  #129 = InterfaceMethodref #2.#128       // org/scalatest/AsyncTestSuite.withFixture:(Lorg/scalatest/AsyncTestSuite$NoArgAsyncTest;)Lorg/scalatest/FutureOutcome;
  #130 = Utf8               Lorg/scalatest/AsyncTestSuite$NoArgAsyncTest;
  #131 = Utf8               ()Lorg/scalatest/FutureOutcome;
  #132 = NameAndType        #92:#131      // apply:()Lorg/scalatest/FutureOutcome;
  #133 = InterfaceMethodref #23.#132      // org/scalatest/AsyncTestSuite$NoArgAsyncTest.apply:()Lorg/scalatest/FutureOutcome;
  #134 = Utf8               runTest$
  #135 = Utf8               (Lorg/scalatest/AsyncTestSuite;Ljava/lang/String;Lorg/scalatest/Args;)Lorg/scalatest/Status;
  #136 = Utf8               testName
  #137 = Utf8               args
  #138 = Utf8               runTest
  #139 = Utf8               (Ljava/lang/String;Lorg/scalatest/Args;)Lorg/scalatest/Status;
  #140 = NameAndType        #138:#139     // runTest:(Ljava/lang/String;Lorg/scalatest/Args;)Lorg/scalatest/Status;
  #141 = InterfaceMethodref #2.#140       // org/scalatest/AsyncTestSuite.runTest:(Ljava/lang/String;Lorg/scalatest/Args;)Lorg/scalatest/Status;
  #142 = Utf8               Ljava/lang/String;
  #143 = Utf8               Lorg/scalatest/Args;
  #144 = Utf8               org/scalatest/SucceededStatus$
  #145 = Class              #144          // org/scalatest/SucceededStatus$
  #146 = Utf8               Lorg/scalatest/SucceededStatus$;
  #147 = NameAndType        #58:#146      // MODULE$:Lorg/scalatest/SucceededStatus$;
  #148 = Fieldref           #145.#147     // org/scalatest/SucceededStatus$.MODULE$:Lorg/scalatest/SucceededStatus$;
  #149 = Utf8               $anonfun$transformToOutcome$2
  #150 = Utf8               (Lorg/scalatest/compatible/Assertion;)Lorg/scalatest/Succeeded$;
  #151 = Utf8               org/scalatest/Succeeded$
  #152 = Class              #151          // org/scalatest/Succeeded$
  #153 = Utf8               Lorg/scalatest/Succeeded$;
  #154 = NameAndType        #58:#153      // MODULE$:Lorg/scalatest/Succeeded$;
  #155 = Fieldref           #152.#154     // org/scalatest/Succeeded$.MODULE$:Lorg/scalatest/Succeeded$;
  #156 = Utf8               testFun$1
  #157 = Utf8               scala/Function0
  #158 = Class              #157          // scala/Function0
  #159 = NameAndType        #92:#74       // apply:()Ljava/lang/Object;
  #160 = InterfaceMethodref #158.#159     // scala/Function0.apply:()Ljava/lang/Object;
  #161 = Utf8               scala/concurrent/Future
  #162 = Class              #161          // scala/concurrent/Future
  #163 = Utf8               (Ljava/lang/Object;)Ljava/lang/Object;
  #164 = MethodType         #163          //  (Ljava/lang/Object;)Ljava/lang/Object;
  #165 = NameAndType        #149:#150     // $anonfun$transformToOutcome$2:(Lorg/scalatest/compatible/Assertion;)Lorg/scalatest/Succeeded$;
  #166 = InterfaceMethodref #2.#165       // org/scalatest/AsyncTestSuite.$anonfun$transformToOutcome$2:(Lorg/scalatest/compatible/Assertion;)Lorg/scalatest/Succeeded$;
  #167 = MethodHandle       6:#166        // REF_invokeStatic org/scalatest/AsyncTestSuite.$anonfun$transformToOutcome$2:(Lorg/scalatest/compatible/Assertion;)Lorg/scalatest/Succeeded$;
  #168 = MethodType         #150          //  (Lorg/scalatest/compatible/Assertion;)Lorg/scalatest/Succeeded$;
  #169 = Utf8               ()Lscala/Function1;
  #170 = NameAndType        #92:#169      // apply:()Lscala/Function1;
  #171 = InvokeDynamic      #1:#170       // #1:apply:()Lscala/Function1;
  #172 = Utf8               map
  #173 = Utf8               (Lscala/Function1;Lscala/concurrent/ExecutionContext;)Lscala/concurrent/Future;
  #174 = NameAndType        #172:#173     // map:(Lscala/Function1;Lscala/concurrent/ExecutionContext;)Lscala/concurrent/Future;
  #175 = InterfaceMethodref #162.#174     // scala/concurrent/Future.map:(Lscala/Function1;Lscala/concurrent/ExecutionContext;)Lscala/concurrent/Future;
  #176 = Utf8               org/scalatest/FutureAsyncTestHolder
  #177 = Class              #176          // org/scalatest/FutureAsyncTestHolder
  #178 = Utf8               <init>
  #179 = Utf8               (Lorg/scalatest/AsyncTestSuite;)V
  #180 = NameAndType        #178:#179     // "<init>":(Lorg/scalatest/AsyncTestSuite;)V
  #181 = Methodref          #21.#180      // org/scalatest/AsyncTestSuite$$anonfun$$nestedInanonfun$transformToOutcome$1$1."<init>":(Lorg/scalatest/AsyncTestSuite;)V
  #182 = Utf8               recover
  #183 = Utf8               (Lscala/PartialFunction;Lscala/concurrent/ExecutionContext;)Lscala/concurrent/Future;
  #184 = NameAndType        #182:#183     // recover:(Lscala/PartialFunction;Lscala/concurrent/ExecutionContext;)Lscala/concurrent/Future;
  #185 = InterfaceMethodref #162.#184     // scala/concurrent/Future.recover:(Lscala/PartialFunction;Lscala/concurrent/ExecutionContext;)Lscala/concurrent/Future;
  #186 = Utf8               (Lscala/concurrent/Future;)V
  #187 = NameAndType        #178:#186     // "<init>":(Lscala/concurrent/Future;)V
  #188 = Methodref          #177.#187     // org/scalatest/FutureAsyncTestHolder."<init>":(Lscala/concurrent/Future;)V
  #189 = Utf8               futureSucceeded
  #190 = Utf8               Lscala/concurrent/Future;
  #191 = Utf8               $init$
  #192 = Utf8               org/scalatest/concurrent/SerialExecutionContext
  #193 = Class              #192          // org/scalatest/concurrent/SerialExecutionContext
  #194 = Utf8               ()V
  #195 = NameAndType        #178:#194     // "<init>":()V
  #196 = Methodref          #193.#195     // org/scalatest/concurrent/SerialExecutionContext."<init>":()V
  #197 = NameAndType        #25:#26       // org$scalatest$AsyncTestSuite$_setter_$org$scalatest$AsyncTestSuite$$serialExecutionContext_$eq:(Lscala/concurrent/ExecutionContext;)V
  #198 = InterfaceMethodref #2.#197       // org/scalatest/AsyncTestSuite.org$scalatest$AsyncTestSuite$_setter_$org$scalatest$AsyncTestSuite$$serialExecutionContext_$eq:(Lscala/concurrent/ExecutionContext;)V
  #199 = Utf8               $deserializeLambda$
  #200 = Utf8               (Ljava/lang/invoke/SerializedLambda;)Ljava/lang/Object;
  #201 = Utf8               scala/runtime/LambdaDeserialize
  #202 = Class              #201          // scala/runtime/LambdaDeserialize
  #203 = Utf8               bootstrap
  #204 = Utf8               (Ljava/lang/invoke/MethodHandles$Lookup;Ljava/lang/String;Ljava/lang/invoke/MethodType;[Ljava/lang/invoke/MethodHandle;)Ljava/lang/invoke/CallSite;
  #205 = NameAndType        #203:#204     // bootstrap:(Ljava/lang/invoke/MethodHandles$Lookup;Ljava/lang/String;Ljava/lang/invoke/MethodType;[Ljava/lang/invoke/MethodHandle;)Ljava/lang/invoke/CallSite;
  #206 = Methodref          #202.#205     // scala/runtime/LambdaDeserialize.bootstrap:(Ljava/lang/invoke/MethodHandles$Lookup;Ljava/lang/String;Ljava/lang/invoke/MethodType;[Ljava/lang/invoke/MethodHandle;)Ljava/lang/invoke/CallSite;
  #207 = MethodHandle       6:#206        // REF_invokeStatic scala/runtime/LambdaDeserialize.bootstrap:(Ljava/lang/invoke/MethodHandles$Lookup;Ljava/lang/String;Ljava/lang/invoke/MethodType;[Ljava/lang/invoke/MethodHandle;)Ljava/lang/invoke/CallSite;
  #208 = Utf8               lambdaDeserialize
  #209 = NameAndType        #208:#200     // lambdaDeserialize:(Ljava/lang/invoke/SerializedLambda;)Ljava/lang/Object;
  #210 = InvokeDynamic      #2:#209       // #2:lambdaDeserialize:(Ljava/lang/invoke/SerializedLambda;)Ljava/lang/Object;
  #211 = Utf8               MethodParameters
  #212 = Utf8               Code
  #213 = Utf8               LineNumberTable
  #214 = Utf8               LocalVariableTable
  #215 = Utf8               StackMapTable
  #216 = Utf8               Signature
  #217 = Utf8               InnerClasses
  #218 = Utf8               SourceFile
  #219 = Utf8               RuntimeVisibleAnnotations
  #220 = Utf8               BootstrapMethods
  #221 = Utf8               ScalaInlineInfo
  #222 = Utf8               ScalaSig
{
  public abstract void org$scalatest$AsyncTestSuite$_setter_$org$scalatest$AsyncTestSuite$$serialExecutionContext_$eq(scala.concurrent.ExecutionContext);
    descriptor: (Lscala/concurrent/ExecutionContext;)V
    flags: (0x0401) ACC_PUBLIC, ACC_ABSTRACT
    MethodParameters:
      Name                           Flags
      x$1                            final

  public abstract scala.concurrent.ExecutionContext org$scalatest$AsyncTestSuite$$serialExecutionContext();
    descriptor: ()Lscala/concurrent/ExecutionContext;
    flags: (0x0401) ACC_PUBLIC, ACC_ABSTRACT

  public static scala.concurrent.ExecutionContext executionContext$(org.scalatest.AsyncTestSuite);
    descriptor: (Lorg/scalatest/AsyncTestSuite;)Lscala/concurrent/ExecutionContext;
    flags: (0x1009) ACC_PUBLIC, ACC_STATIC, ACC_SYNTHETIC
    Code:
      stack=1, locals=1, args_size=1
         0: aload_0
         1: invokespecial #35                 // InterfaceMethod executionContext:()Lscala/concurrent/ExecutionContext;
         4: areturn
      LineNumberTable:
        line 222: 0
      LocalVariableTable:
        Start  Length  Slot  Name   Signature
            0       5     0 $this   Lorg/scalatest/AsyncTestSuite;
    MethodParameters:
      Name                           Flags
      $this                          final synthetic

  public default scala.concurrent.ExecutionContext executionContext();
    descriptor: ()Lscala/concurrent/ExecutionContext;
    flags: (0x0001) ACC_PUBLIC
    Code:
      stack=1, locals=1, args_size=1
         0: aload_0
         1: invokeinterface #38,  1           // InterfaceMethod org$scalatest$AsyncTestSuite$$serialExecutionContext:()Lscala/concurrent/ExecutionContext;
         6: areturn
      LineNumberTable:
        line 222: 0
      LocalVariableTable:
        Start  Length  Slot  Name   Signature
            0       7     0  this   Lorg/scalatest/AsyncTestSuite;

  public static boolean org$scalatest$AsyncTestSuite$$anAsyncExceptionThatShouldCauseAnAbort$(org.scalatest.AsyncTestSuite, java.lang.Throwable);
    descriptor: (Lorg/scalatest/AsyncTestSuite;Ljava/lang/Throwable;)Z
    flags: (0x1009) ACC_PUBLIC, ACC_STATIC, ACC_SYNTHETIC
    Code:
      stack=2, locals=2, args_size=2
         0: aload_0
         1: aload_1
         2: invokespecial #46                 // InterfaceMethod org$scalatest$AsyncTestSuite$$anAsyncExceptionThatShouldCauseAnAbort:(Ljava/lang/Throwable;)Z
         5: ireturn
      LineNumberTable:
        line 224: 0
      LocalVariableTable:
        Start  Length  Slot  Name   Signature
            0       6     0 $this   Lorg/scalatest/AsyncTestSuite;
            0       6     1    ex   Ljava/lang/Throwable;
    MethodParameters:
      Name                           Flags
      $this                          final synthetic
      ex                             final

  public default boolean org$scalatest$AsyncTestSuite$$anAsyncExceptionThatShouldCauseAnAbort(java.lang.Throwable);
    descriptor: (Ljava/lang/Throwable;)Z
    flags: (0x0001) ACC_PUBLIC
    Code:
      stack=2, locals=4, args_size=2
         0: aload_1
         1: astore_3
         2: aload_3
         3: instanceof    #49                 // class java/util/concurrent/ExecutionException
         6: ifeq          30
         9: aload_1
        10: invokevirtual #55                 // Method java/lang/Throwable.getCause:()Ljava/lang/Throwable;
        13: ifnull        30
        16: getstatic     #61                 // Field org/scalatest/Suite$.MODULE$:Lorg/scalatest/Suite$;
        19: aload_1
        20: invokevirtual #55                 // Method java/lang/Throwable.getCause:()Ljava/lang/Throwable;
        23: invokevirtual #64                 // Method org/scalatest/Suite$.anExceptionThatShouldCauseAnAbort:(Ljava/lang/Throwable;)Z
        26: istore_2
        27: goto          44
        30: goto          33
        33: getstatic     #61                 // Field org/scalatest/Suite$.MODULE$:Lorg/scalatest/Suite$;
        36: aload_3
        37: invokevirtual #64                 // Method org/scalatest/Suite$.anExceptionThatShouldCauseAnAbort:(Ljava/lang/Throwable;)Z
        40: istore_2
        41: goto          44
        44: iload_2
        45: ireturn
      StackMapTable: number_of_entries = 3
        frame_type = 253 /* append */
          offset_delta = 30
          locals = [ top, class java/lang/Throwable ]
        frame_type = 2 /* same */
        frame_type = 255 /* full_frame */
          offset_delta = 10
          locals = [ class org/scalatest/AsyncTestSuite, class java/lang/Throwable, int, class java/lang/Throwable ]
          stack = []
      LineNumberTable:
        line 225: 0
        line 228: 2
        line 229: 33
        line 225: 44
      LocalVariableTable:
        Start  Length  Slot  Name   Signature
            0      46     0  this   Lorg/scalatest/AsyncTestSuite;
            0      46     1    ex   Ljava/lang/Throwable;
    MethodParameters:
      Name                           Flags
      ex                             final

  public static scala.Function0 transformToOutcome$(org.scalatest.AsyncTestSuite, scala.Function0);
    descriptor: (Lorg/scalatest/AsyncTestSuite;Lscala/Function0;)Lscala/Function0;
    flags: (0x1009) ACC_PUBLIC, ACC_STATIC, ACC_SYNTHETIC
    Code:
      stack=2, locals=2, args_size=2
         0: aload_0
         1: aload_1
         2: invokespecial #71                 // InterfaceMethod transformToOutcome:(Lscala/Function0;)Lscala/Function0;
         5: areturn
      LineNumberTable:
        line 238: 0
      LocalVariableTable:
        Start  Length  Slot  Name   Signature
            0       6     0 $this   Lorg/scalatest/AsyncTestSuite;
            0       6     1 testFun   Lscala/Function0;
    MethodParameters:
      Name                           Flags
      $this                          final synthetic
      testFun                        final

  public default scala.Function0<org.scalatest.AsyncTestHolder> transformToOutcome(scala.Function0<scala.concurrent.Future<org.scalatest.compatible.Assertion>>);
    descriptor: (Lscala/Function0;)Lscala/Function0;
    flags: (0x0001) ACC_PUBLIC
    Code:
      stack=2, locals=2, args_size=2
         0: aload_0
         1: aload_1
         2: invokedynamic #94,  0             // InvokeDynamic #0:apply:(Lorg/scalatest/AsyncTestSuite;Lscala/Function0;)Lscala/Function0;
         7: areturn
      LineNumberTable:
        line 239: 0
      LocalVariableTable:
        Start  Length  Slot  Name   Signature
            0       8     0  this   Lorg/scalatest/AsyncTestSuite;
            0       8     1 testFun   Lscala/Function0;
    Signature: #73                          // (Lscala/Function0<Lscala/concurrent/Future<Lorg/scalatest/compatible/Assertion;>;>;)Lscala/Function0<Lorg/scalatest/AsyncTestHolder;>;
    MethodParameters:
      Name                           Flags
      testFun                        final

  public static scala.concurrent.Future convertAssertionToFutureAssertion$(org.scalatest.AsyncTestSuite, org.scalatest.compatible.Assertion);
    descriptor: (Lorg/scalatest/AsyncTestSuite;Lorg/scalatest/compatible/Assertion;)Lscala/concurrent/Future;
    flags: (0x1009) ACC_PUBLIC, ACC_STATIC, ACC_SYNTHETIC
    Code:
      stack=2, locals=2, args_size=2
         0: aload_0
         1: aload_1
         2: invokespecial #101                // InterfaceMethod convertAssertionToFutureAssertion:(Lorg/scalatest/compatible/Assertion;)Lscala/concurrent/Future;
         5: areturn
      LineNumberTable:
        line 263: 0
      LocalVariableTable:
        Start  Length  Slot  Name   Signature
            0       6     0 $this   Lorg/scalatest/AsyncTestSuite;
            0       6     1 assertion   Lorg/scalatest/compatible/Assertion;
    MethodParameters:
      Name                           Flags
      $this                          final synthetic
      assertion                      final

  public default scala.concurrent.Future<org.scalatest.compatible.Assertion> convertAssertionToFutureAssertion(org.scalatest.compatible.Assertion);
    descriptor: (Lorg/scalatest/compatible/Assertion;)Lscala/concurrent/Future;
    flags: (0x0001) ACC_PUBLIC
    Code:
      stack=2, locals=2, args_size=2
         0: getstatic     #108                // Field scala/concurrent/Future$.MODULE$:Lscala/concurrent/Future$;
         3: aload_1
         4: invokevirtual #112                // Method scala/concurrent/Future$.successful:(Ljava/lang/Object;)Lscala/concurrent/Future;
         7: areturn
      LineNumberTable:
        line 263: 0
      LocalVariableTable:
        Start  Length  Slot  Name   Signature
            0       8     0  this   Lorg/scalatest/AsyncTestSuite;
            0       8     1 assertion   Lorg/scalatest/compatible/Assertion;
    Signature: #103                         // (Lorg/scalatest/compatible/Assertion;)Lscala/concurrent/Future<Lorg/scalatest/compatible/Assertion;>;
    MethodParameters:
      Name                           Flags
      assertion                      final

  public static boolean parallelAsyncTestExecution$(org.scalatest.AsyncTestSuite);
    descriptor: (Lorg/scalatest/AsyncTestSuite;)Z
    flags: (0x1009) ACC_PUBLIC, ACC_STATIC, ACC_SYNTHETIC
    Code:
      stack=1, locals=1, args_size=1
         0: aload_0
         1: invokespecial #118                // InterfaceMethod parallelAsyncTestExecution:()Z
         4: ireturn
      LineNumberTable:
        line 268: 0
      LocalVariableTable:
        Start  Length  Slot  Name   Signature
            0       5     0 $this   Lorg/scalatest/AsyncTestSuite;
    MethodParameters:
      Name                           Flags
      $this                          final synthetic

  public default boolean parallelAsyncTestExecution();
    descriptor: ()Z
    flags: (0x0001) ACC_PUBLIC
    Code:
      stack=1, locals=1, args_size=1
         0: aload_0
         1: instanceof    #120                // class org/scalatest/ParallelTestExecution
         4: ifne          14
         7: aload_0
         8: instanceof    #122                // class org/scalatest/RandomTestOrder
        11: ifeq          18
        14: iconst_1
        15: goto          19
        18: iconst_0
        19: ireturn
      StackMapTable: number_of_entries = 3
        frame_type = 14 /* same */
        frame_type = 3 /* same */
        frame_type = 64 /* same_locals_1_stack_item */
          stack = [ int ]
      LineNumberTable:
        line 268: 0
        line 269: 7
      LocalVariableTable:
        Start  Length  Slot  Name   Signature
            0      20     0  this   Lorg/scalatest/AsyncTestSuite;

  public static org.scalatest.FutureOutcome withFixture$(org.scalatest.AsyncTestSuite, org.scalatest.AsyncTestSuite$NoArgAsyncTest);
    descriptor: (Lorg/scalatest/AsyncTestSuite;Lorg/scalatest/AsyncTestSuite$NoArgAsyncTest;)Lorg/scalatest/FutureOutcome;
    flags: (0x1009) ACC_PUBLIC, ACC_STATIC, ACC_SYNTHETIC
    Code:
      stack=2, locals=2, args_size=2
         0: aload_0
         1: aload_1
         2: invokespecial #129                // InterfaceMethod withFixture:(Lorg/scalatest/AsyncTestSuite$NoArgAsyncTest;)Lorg/scalatest/FutureOutcome;
         5: areturn
      LineNumberTable:
        line 315: 0
      LocalVariableTable:
        Start  Length  Slot  Name   Signature
            0       6     0 $this   Lorg/scalatest/AsyncTestSuite;
            0       6     1  test   Lorg/scalatest/AsyncTestSuite$NoArgAsyncTest;
    MethodParameters:
      Name                           Flags
      $this                          final synthetic
      test                           final

  public default org.scalatest.FutureOutcome withFixture(org.scalatest.AsyncTestSuite$NoArgAsyncTest);
    descriptor: (Lorg/scalatest/AsyncTestSuite$NoArgAsyncTest;)Lorg/scalatest/FutureOutcome;
    flags: (0x0001) ACC_PUBLIC
    Code:
      stack=1, locals=2, args_size=2
         0: aload_1
         1: invokeinterface #133,  1          // InterfaceMethod org/scalatest/AsyncTestSuite$NoArgAsyncTest.apply:()Lorg/scalatest/FutureOutcome;
         6: areturn
      LineNumberTable:
        line 316: 0
      LocalVariableTable:
        Start  Length  Slot  Name   Signature
            0       7     0  this   Lorg/scalatest/AsyncTestSuite;
            0       7     1  test   Lorg/scalatest/AsyncTestSuite$NoArgAsyncTest;
    MethodParameters:
      Name                           Flags
      test                           final

  public static org.scalatest.Status runTest$(org.scalatest.AsyncTestSuite, java.lang.String, org.scalatest.Args);
    descriptor: (Lorg/scalatest/AsyncTestSuite;Ljava/lang/String;Lorg/scalatest/Args;)Lorg/scalatest/Status;
    flags: (0x1009) ACC_PUBLIC, ACC_STATIC, ACC_SYNTHETIC
    Code:
      stack=3, locals=3, args_size=3
         0: aload_0
         1: aload_1
         2: aload_2
         3: invokespecial #141                // InterfaceMethod runTest:(Ljava/lang/String;Lorg/scalatest/Args;)Lorg/scalatest/Status;
         6: areturn
      LineNumberTable:
        line 360: 0
      LocalVariableTable:
        Start  Length  Slot  Name   Signature
            0       7     0 $this   Lorg/scalatest/AsyncTestSuite;
            0       7     1 testName   Ljava/lang/String;
            0       7     2  args   Lorg/scalatest/Args;
    MethodParameters:
      Name                           Flags
      $this                          final synthetic
      testName                       final
      args                           final

  public default org.scalatest.Status runTest(java.lang.String, org.scalatest.Args);
    descriptor: (Ljava/lang/String;Lorg/scalatest/Args;)Lorg/scalatest/Status;
    flags: (0x0001) ACC_PUBLIC
    Code:
      stack=1, locals=3, args_size=3
         0: getstatic     #148                // Field org/scalatest/SucceededStatus$.MODULE$:Lorg/scalatest/SucceededStatus$;
         3: areturn
      LineNumberTable:
        line 360: 0
      LocalVariableTable:
        Start  Length  Slot  Name   Signature
            0       4     0  this   Lorg/scalatest/AsyncTestSuite;
            0       4     1 testName   Ljava/lang/String;
            0       4     2  args   Lorg/scalatest/Args;
    MethodParameters:
      Name                           Flags
      testName                       final
      args                           final

  public static org.scalatest.Succeeded$ $anonfun$transformToOutcome$2(org.scalatest.compatible.Assertion);
    descriptor: (Lorg/scalatest/compatible/Assertion;)Lorg/scalatest/Succeeded$;
    flags: (0x1009) ACC_PUBLIC, ACC_STATIC, ACC_SYNTHETIC
    Code:
      stack=1, locals=1, args_size=1
         0: getstatic     #155                // Field org/scalatest/Succeeded$.MODULE$:Lorg/scalatest/Succeeded$;
         3: areturn
      LineNumberTable:
        line 240: 0
      LocalVariableTable:
        Start  Length  Slot  Name   Signature
            0       4     0   x$1   Lorg/scalatest/compatible/Assertion;
    MethodParameters:
      Name                           Flags
      x$1                            final

  public static org.scalatest.FutureAsyncTestHolder $anonfun$transformToOutcome$1(org.scalatest.AsyncTestSuite, scala.Function0);
    descriptor: (Lorg/scalatest/AsyncTestSuite;Lscala/Function0;)Lorg/scalatest/FutureAsyncTestHolder;
    flags: (0x1009) ACC_PUBLIC, ACC_STATIC, ACC_SYNTHETIC
    Code:
      stack=6, locals=3, args_size=2
         0: aload_1
         1: invokeinterface #160,  1          // InterfaceMethod scala/Function0.apply:()Ljava/lang/Object;
         6: checkcast     #162                // class scala/concurrent/Future
         9: invokedynamic #171,  0            // InvokeDynamic #1:apply:()Lscala/Function1;
        14: aload_0
        15: invokeinterface #35,  1           // InterfaceMethod executionContext:()Lscala/concurrent/ExecutionContext;
        20: invokeinterface #175,  3          // InterfaceMethod scala/concurrent/Future.map:(Lscala/Function1;Lscala/concurrent/ExecutionContext;)Lscala/concurrent/Future;
        25: astore_2
        26: new           #177                // class org/scalatest/FutureAsyncTestHolder
        29: dup
        30: aload_2
        31: new           #21                 // class org/scalatest/AsyncTestSuite$$anonfun$$nestedInanonfun$transformToOutcome$1$1
        34: dup
        35: aload_0
        36: invokespecial #181                // Method org/scalatest/AsyncTestSuite$$anonfun$$nestedInanonfun$transformToOutcome$1$1."<init>":(Lorg/scalatest/AsyncTestSuite;)V
        39: aload_0
        40: invokeinterface #35,  1           // InterfaceMethod executionContext:()Lscala/concurrent/ExecutionContext;
        45: invokeinterface #185,  3          // InterfaceMethod scala/concurrent/Future.recover:(Lscala/PartialFunction;Lscala/concurrent/ExecutionContext;)Lscala/concurrent/Future;
        50: invokespecial #188                // Method org/scalatest/FutureAsyncTestHolder."<init>":(Lscala/concurrent/Future;)V
        53: areturn
      LineNumberTable:
        line 240: 0
        line 241: 26
        line 242: 30
      LocalVariableTable:
        Start  Length  Slot  Name   Signature
           26      27     2 futureSucceeded   Lscala/concurrent/Future;
            0      54     0 $this   Lorg/scalatest/AsyncTestSuite;
            0      54     1 testFun$1   Lscala/Function0;
    MethodParameters:
      Name                           Flags
      $this                          final synthetic
      testFun$1                      final

  public static void $init$(org.scalatest.AsyncTestSuite);
    descriptor: (Lorg/scalatest/AsyncTestSuite;)V
    flags: (0x0009) ACC_PUBLIC, ACC_STATIC
    Code:
      stack=3, locals=1, args_size=1
         0: aload_0
         1: new           #193                // class org/scalatest/concurrent/SerialExecutionContext
         4: dup
         5: invokespecial #196                // Method org/scalatest/concurrent/SerialExecutionContext."<init>":()V
         8: invokeinterface #198,  2          // InterfaceMethod org$scalatest$AsyncTestSuite$_setter_$org$scalatest$AsyncTestSuite$$serialExecutionContext_$eq:(Lscala/concurrent/ExecutionContext;)V
        13: return
      LineNumberTable:
        line 221: 0
        line 214: 13
      LocalVariableTable:
        Start  Length  Slot  Name   Signature
            0      14     0 $this   Lorg/scalatest/AsyncTestSuite;
    MethodParameters:
      Name                           Flags
      $this                          final synthetic

  private static java.lang.Object $deserializeLambda$(java.lang.invoke.SerializedLambda);
    descriptor: (Ljava/lang/invoke/SerializedLambda;)Ljava/lang/Object;
    flags: (0x100a) ACC_PRIVATE, ACC_STATIC, ACC_SYNTHETIC
    Code:
      stack=1, locals=1, args_size=1
         0: aload_0
         1: invokedynamic #210,  0            // InvokeDynamic #2:lambdaDeserialize:(Ljava/lang/invoke/SerializedLambda;)Ljava/lang/Object;
         6: areturn
}
InnerClasses:
  public static final #19= #16 of #18;    // Lookup=class java/lang/invoke/MethodHandles$Lookup of class java/lang/invoke/MethodHandles
  public final #21;                       // class org/scalatest/AsyncTestSuite$$anonfun$$nestedInanonfun$transformToOutcome$1$1
  public #24= #23 of #2;                  // NoArgAsyncTest=class org/scalatest/AsyncTestSuite$NoArgAsyncTest of class org/scalatest/AsyncTestSuite
SourceFile: "AsyncTestSuite.scala"
RuntimeVisibleAnnotations:
  0: #12(#13=s#14)
    scala.reflect.ScalaSignature(
      bytes="\u0006\u0005\u0005-aa\u0002\u0007\u000e!\u0003\r\tA\u0005\u0005\u0006G\u0001!\t\u0001\n\u0005\bQ\u0001\u0011\r\u0011\"\u0004*\u0011\u0015\u0001\u0004\u0001b\u0001*\u0011\u0015\t\u0004\u0001\"\u00033\u0011\u0019!\u0005\u0001\"\u0001\u000e\u000b\")!\f\u0001C\u00027\"1a\f\u0001C\t\u001b}3q\u0001\u0019\u0001\u0011\u0002G\u0005\u0011\rC\u0003j\u0011\u0019\u0005!\u000eC\u0003l\u0001\u0011\u0005A\u000eC\u0003r\u0001\u0011E#O\u0001\bBgft7\rV3tiN+\u0018\u000e^3\u000b\u00059y\u0011!C:dC2\fG/Z:u\u0015\u0005\u0001\u0012aA8sO\u000e\u00011#\u0002\u0001\u00143u\u0001\u0003C\u0001\u000b\u0018\u001b\u0005)\"\"\u0001\f\u0002\u000bM\u001c\u0017\r\\1\n\u0005a)\"AB!osJ+g\r\u0005\u0002\u001b75\tQ\"\u0003\u0002\u001d\u001b\t)1+^5uKB\u0011!DH\u0005\u0003?5\u0011aBU3d_Z,\'/T3uQ>$7\u000f\u0005\u0002\u001bC%\u0011!%\u0004\u0002\u000f\u0007>l\u0007\u000f\\3uK2\u000b7\u000f\u001e7z\u0003\u0019!\u0013N\\5uIQ\tQ\u0005\u0005\u0002\u0015M%\u0011q%\u0006\u0002\u0005+:LG/\u0001\ftKJL\u0017\r\\#yK\u000e,H/[8o\u0007>tG/\u001a=u+\u0005Q\u0003CA\u0016/\u001b\u0005a#BA\u0017\u0016\u0003)\u0019wN\\2veJ,g\u000e^\u0005\u0003_1\u0012\u0001#\u0012=fGV$\u0018n\u001c8D_:$X\r\u001f;\u0002!\u0015DXmY;uS>t7i\u001c8uKb$\u0018AJ1o\u0003NLhnY#yG\u0016\u0004H/[8o)\"\fGo\u00155pk2$7)Y;tK\u0006s\u0017IY8siR\u00111G\u000e\t\u0003)QJ!!N\u000b\u0003\u000f\t{w\u000e\\3b]\")q\u0007\u0002a\u0001q\u0005\u0011Q\r\u001f\t\u0003s\u0005s!AO \u000f\u0005mrT\"\u0001\u001f\u000b\u0005u\n\u0012A\u0002\u001fs_>$h(C\u0001\u0017\u0013\t\u0001U#A\u0004qC\u000e\\\u0017mZ3\n\u0005\t\u001b%!\u0003+ie><\u0018M\u00197f\u0015\t\u0001U#\u0001\nue\u0006t7OZ8s[R{w*\u001e;d_6,GC\u0001$M!\r!r)S\u0005\u0003\u0011V\u0011\u0011BR;oGRLwN\u001c\u0019\u0011\u0005iQ\u0015BA&\u000e\u0005=\t5/\u001f8d)\u0016\u001cH\u000fS8mI\u0016\u0014\bBB\'\u0006\t\u0003\u0007a*A\u0004uKN$h)\u001e8\u0011\u0007Qy\u0015+\u0003\u0002Q+\tAAHY=oC6,g\bE\u0002,%RK!a\u0015\u0017\u0003\r\u0019+H/\u001e:f!\t)\u0006,D\u0001W\u0015\t9V\"\u0001\u0006d_6\u0004\u0018\r^5cY\u0016L!!\u0017,\u0003\u0013\u0005\u001b8/\u001a:uS>t\u0017!I2p]Z,\'\u000f^!tg\u0016\u0014H/[8o)>4U\u000f^;sK\u0006\u001b8/\u001a:uS>tGCA)]\u0011\u0015if\u00011\u0001U\u0003%\t7o]3si&|g.\u0001\u000eqCJ\fG\u000e\\3m\u0003NLhn\u0019+fgR,\u00050Z2vi&|g.F\u00014\u00059qu.\u0011:h\u0003NLhn\u0019+fgR\u001cB\u0001C\ncMB\u0019AcR2\u0011\u0005i!\u0017BA3\u000e\u000551U\u000f^;sK>+HoY8nKB\u0011!dZ\u0005\u0003Q6\u0011\u0001\u0002V3ti\u0012\u000bG/Y\u0001\u0006CB\u0004H.\u001f\u000b\u0002G\u0006Yq/\u001b;i\r&DH/\u001e:f)\t\u0019W\u000eC\u0003o\u0015\u0001\u0007q.\u0001\u0003uKN$\bC\u00019\t\u001b\u0005\u0001\u0011a\u0002:v]R+7\u000f\u001e\u000b\u0005gZ\f\t\u0001\u0005\u0002\u001bi&\u0011Q/\u0004\u0002\u0007\'R\fG/^:\t\u000b]\\\u0001\u0019\u0001=\u0002\u0011Q,7\u000f\u001e(b[\u0016\u0004\"!_?\u000f\u0005i\\\bCA\u001e\u0016\u0013\taX#\u0001\u0004Qe\u0016$WMZ\u0005\u0003}~\u0014aa\u0015;sS:<\'B\u0001?\u0016\u0011\u001d\t\u0019a\u0003a\u0001\u0003\u000b\tA!\u0019:hgB\u0019!$a\u0002\n\u0007\u0005%QB\u0001\u0003Be\u001e\u001c\b"
    )
BootstrapMethods:
  0: #91 REF_invokeStatic java/lang/invoke/LambdaMetafactory.altMetafactory:(Ljava/lang/invoke/MethodHandles$Lookup;Ljava/lang/String;Ljava/lang/invoke/MethodType;[Ljava/lang/Object;)Ljava/lang/invoke/CallSite;
    Method arguments:
      #75 ()Ljava/lang/Object;
      #80 REF_invokeStatic org/scalatest/AsyncTestSuite.$anonfun$transformToOutcome$1:(Lorg/scalatest/AsyncTestSuite;Lscala/Function0;)Lorg/scalatest/FutureAsyncTestHolder;
      #82 ()Lorg/scalatest/FutureAsyncTestHolder;
      #83 5
      #84 1
      #82 ()Lorg/scalatest/FutureAsyncTestHolder;
  1: #91 REF_invokeStatic java/lang/invoke/LambdaMetafactory.altMetafactory:(Ljava/lang/invoke/MethodHandles$Lookup;Ljava/lang/String;Ljava/lang/invoke/MethodType;[Ljava/lang/Object;)Ljava/lang/invoke/CallSite;
    Method arguments:
      #164 (Ljava/lang/Object;)Ljava/lang/Object;
      #167 REF_invokeStatic org/scalatest/AsyncTestSuite.$anonfun$transformToOutcome$2:(Lorg/scalatest/compatible/Assertion;)Lorg/scalatest/Succeeded$;
      #168 (Lorg/scalatest/compatible/Assertion;)Lorg/scalatest/Succeeded$;
      #83 5
      #84 1
      #168 (Lorg/scalatest/compatible/Assertion;)Lorg/scalatest/Succeeded$;
  2: #207 REF_invokeStatic scala/runtime/LambdaDeserialize.bootstrap:(Ljava/lang/invoke/MethodHandles$Lookup;Ljava/lang/String;Ljava/lang/invoke/MethodType;[Ljava/lang/invoke/MethodHandle;)Ljava/lang/invoke/CallSite;
    Method arguments:
      #80 REF_invokeStatic org/scalatest/AsyncTestSuite.$anonfun$transformToOutcome$1:(Lorg/scalatest/AsyncTestSuite;Lscala/Function0;)Lorg/scalatest/FutureAsyncTestHolder;
      #167 REF_invokeStatic org/scalatest/AsyncTestSuite.$anonfun$transformToOutcome$2:(Lorg/scalatest/compatible/Assertion;)Lorg/scalatest/Succeeded$;
  ScalaInlineInfo: length = 0x63 (unknown attribute)
   01 00 00 13 00 4C 00 4D 01 00 95 00 96 01 00 BF
   00 B3 01 00 62 00 63 00 00 5F 00 60 01 00 21 00
   1D 00 00 1E 00 1F 01 00 2B 00 2C 01 00 28 00 29
   01 00 1C 00 1D 00 00 19 00 1A 00 00 73 00 74 00
   00 71 00 72 01 00 8A 00 8B 00 00 86 00 87 01 00
   44 00 45 00 00 41 00 42 01 00 7E 00 7F 00 00 7B
   00 7C 01
  ScalaSig: length = 0x3 (unknown attribute)
   05 02 00
