Classfile /Users/mw/Projects/slang-braindump/.jar/jar11/assemble/slang-braindump/assemble/content/org/scalatest/BeforeAndAfterAll.class
  Last modified May 29, 2022; size 5731 bytes
  SHA-256 checksum 6425e2ae55381132f39e51fd6964db3759e2b0e87883e0a6d52a15a337ec447f
  Compiled from "BeforeAndAfterAll.scala"
public interface org.scalatest.BeforeAndAfterAll extends org.scalatest.SuiteMixin
  minor version: 0
  major version: 52
  flags: (0x0601) ACC_PUBLIC, ACC_INTERFACE, ACC_ABSTRACT
  this_class: #2                          // org/scalatest/BeforeAndAfterAll
  super_class: #4                         // java/lang/Object
  interfaces: 1, fields: 0, methods: 13, attributes: 6
Constant pool:
    #1 = Utf8               org/scalatest/BeforeAndAfterAll
    #2 = Class              #1            // org/scalatest/BeforeAndAfterAll
    #3 = Utf8               java/lang/Object
    #4 = Class              #3            // java/lang/Object
    #5 = Utf8               org/scalatest/SuiteMixin
    #6 = Class              #5            // org/scalatest/SuiteMixin
    #7 = Utf8               BeforeAndAfterAll.scala
    #8 = Utf8               Lscala/reflect/ScalaSignature;
    #9 = Utf8               bytes
   #10 = Utf8               \u0006\u0005)3\u0001b\u0002\u0005\u0011\u0002\u0007\u0005Qb\u0011\u0005\u00061\u0001!\t!\u0007\u0005\b;\u0001\u0011\r\u0011\"\u0001\u001f\u0011\u0015\u0011\u0003\u0001\"\u0005\u001a\u0011\u0015\u0019\u0003\u0001\"\u0005\u001a\u0011\u0019!\u0003\u0001%C\u0001K!Ya\b\u0001I\u0001\u0004\u0003\u0005I\u0011B C\u0005E\u0011UMZ8sK\u0006sG-\u00114uKJ\fE\u000e\u001c\u0006\u0003\u0013)\t\u0011b]2bY\u0006$Xm\u001d;\u000b\u0003-\t1a\u001c:h\u0007\u0001\u00192\u0001\u0001\b\u0015!\ty!#D\u0001\u0011\u0015\u0005\t\u0012!B:dC2\f\u0017BA\n\u0011\u0005\u0019\te.\u001f*fMB\u0011QCF\u0007\u0002\u0011%\u0011q\u0003\u0003\u0002\u000b\'VLG/Z\'jq&t\u0017A\u0002\u0013j]&$H\u0005F\u0001\u001b!\ty1$\u0003\u0002\u001d!\t!QK\\5u\u0003IJgN^8lK\n+gm\u001c:f\u00032d\u0017I\u001c3BMR,\'/\u00117m\u000bZ,g.\u00134O_R+7\u000f^:Be\u0016,\u0005\u0010]3di\u0016$W#A\u0010\u0011\u0005=\u0001\u0013BA\u0011\u0011\u0005\u001d\u0011un\u001c7fC:\f\u0011BY3g_J,\u0017\t\u001c7\u0002\u0011\u00054G/\u001a:BY2\f1A];o)\r1\u0013&\u000f\t\u0003+\u001dJ!\u0001\u000b\u0005\u0003\rM#\u0018\r^;t\u0011\u0015QS\u00011\u0001,\u0003!!Xm\u001d;OC6,\u0007cA\b-]%\u0011Q\u0006\u0005\u0002\u0007\u001fB$\u0018n\u001c8\u0011\u0005=2dB\u0001\u00195!\t\t\u0004#D\u00013\u0015\t\u0019D\"\u0001\u0004=e>|GOP\u0005\u0003kA\ta\u0001\u0015:fI\u00164\u0017BA\u001c9\u0005\u0019\u0019FO]5oO*\u0011Q\u0007\u0005\u0005\u0006u\u0015\u0001\raO\u0001\u0005CJ<7\u000f\u0005\u0002\u0016y%\u0011Q\b\u0003\u0002\u0005\u0003J<7/A\u0005tkB,\'\u000f\n:v]R\u0019a\u0005Q!\t\u000b)2\u0001\u0019A\u0016\t\u000bi2\u0001\u0019A\u001e\n\u0005\u00112\"c\u0001#G\u000f\u001a!Q\t\u0001\u0001D\u00051a$/\u001a4j]\u0016lWM\u001c;?!\t)\u0002\u0001\u0005\u0002\u0016\u0011&\u0011\u0011\n\u0003\u0002\u0006\'VLG/\u001a
   #11 = Utf8               java/lang/invoke/MethodHandles$Lookup
   #12 = Class              #11           // java/lang/invoke/MethodHandles$Lookup
   #13 = Utf8               java/lang/invoke/MethodHandles
   #14 = Class              #13           // java/lang/invoke/MethodHandles
   #15 = Utf8               Lookup
   #16 = Utf8               org$scalatest$BeforeAndAfterAll$_setter_$invokeBeforeAllAndAfterAllEvenIfNoTestsAreExpected_$eq
   #17 = Utf8               (Z)V
   #18 = Utf8               x$1
   #19 = Utf8               org$scalatest$BeforeAndAfterAll$$super$run
   #20 = Utf8               (Lscala/Option;Lorg/scalatest/Args;)Lorg/scalatest/Status;
   #21 = Utf8               testName
   #22 = Utf8               args
   #23 = Utf8               invokeBeforeAllAndAfterAllEvenIfNoTestsAreExpected
   #24 = Utf8               ()Z
   #25 = Utf8               beforeAll$
   #26 = Utf8               (Lorg/scalatest/BeforeAndAfterAll;)V
   #27 = Utf8               $this
   #28 = Utf8               beforeAll
   #29 = Utf8               ()V
   #30 = NameAndType        #28:#29       // beforeAll:()V
   #31 = InterfaceMethodref #2.#30        // org/scalatest/BeforeAndAfterAll.beforeAll:()V
   #32 = Utf8               Lorg/scalatest/BeforeAndAfterAll;
   #33 = Utf8               this
   #34 = Utf8               afterAll$
   #35 = Utf8               afterAll
   #36 = NameAndType        #35:#29       // afterAll:()V
   #37 = InterfaceMethodref #2.#36        // org/scalatest/BeforeAndAfterAll.afterAll:()V
   #38 = Utf8               run$
   #39 = Utf8               (Lorg/scalatest/BeforeAndAfterAll;Lscala/Option;Lorg/scalatest/Args;)Lorg/scalatest/Status;
   #40 = Utf8               run
   #41 = NameAndType        #40:#20       // run:(Lscala/Option;Lorg/scalatest/Args;)Lorg/scalatest/Status;
   #42 = InterfaceMethodref #2.#41        // org/scalatest/BeforeAndAfterAll.run:(Lscala/Option;Lorg/scalatest/Args;)Lorg/scalatest/Status;
   #43 = Utf8               Lscala/Option;
   #44 = Utf8               Lorg/scalatest/Args;
   #45 = Utf8               (Lscala/Option<Ljava/lang/String;>;Lorg/scalatest/Args;)Lorg/scalatest/Status;
   #46 = Utf8               java/lang/Exception
   #47 = Class              #46           // java/lang/Exception
   #48 = Utf8               liftedTree1$1
   #49 = Utf8               (Lorg/scalatest/Args;Lscala/Option;)Lscala/Tuple2;
   #50 = NameAndType        #48:#49       // liftedTree1$1:(Lorg/scalatest/Args;Lscala/Option;)Lscala/Tuple2;
   #51 = InterfaceMethodref #2.#50        // org/scalatest/BeforeAndAfterAll.liftedTree1$1:(Lorg/scalatest/Args;Lscala/Option;)Lscala/Tuple2;
   #52 = Utf8               scala/Tuple2
   #53 = Class              #52           // scala/Tuple2
   #54 = Utf8               _1
   #55 = Utf8               ()Ljava/lang/Object;
   #56 = NameAndType        #54:#55       // _1:()Ljava/lang/Object;
   #57 = Methodref          #53.#56       // scala/Tuple2._1:()Ljava/lang/Object;
   #58 = Utf8               org/scalatest/Status
   #59 = Class              #58           // org/scalatest/Status
   #60 = Utf8               _2
   #61 = NameAndType        #60:#55       // _2:()Ljava/lang/Object;
   #62 = Methodref          #53.#61       // scala/Tuple2._2:()Ljava/lang/Object;
   #63 = Utf8               scala/Option
   #64 = Class              #63           // scala/Option
   #65 = Utf8               <init>
   #66 = Utf8               (Ljava/lang/Object;Ljava/lang/Object;)V
   #67 = NameAndType        #65:#66       // "<init>":(Ljava/lang/Object;Ljava/lang/Object;)V
   #68 = Methodref          #53.#67       // scala/Tuple2."<init>":(Ljava/lang/Object;Ljava/lang/Object;)V
   #69 = Utf8               scala/MatchError
   #70 = Class              #69           // scala/MatchError
   #71 = Utf8               (Ljava/lang/Object;)V
   #72 = NameAndType        #65:#71       // "<init>":(Ljava/lang/Object;)V
   #73 = Methodref          #70.#72       // scala/MatchError."<init>":(Ljava/lang/Object;)V
   #74 = Utf8               org/scalatest/Args
   #75 = Class              #74           // org/scalatest/Args
   #76 = Utf8               runTestInNewInstance
   #77 = NameAndType        #76:#24       // runTestInNewInstance:()Z
   #78 = Methodref          #75.#77       // org/scalatest/Args.runTestInNewInstance:()Z
   #79 = Utf8               org/scalatest/Suite
   #80 = Class              #79           // org/scalatest/Suite
   #81 = Utf8               filter
   #82 = Utf8               ()Lorg/scalatest/Filter;
   #83 = NameAndType        #81:#82       // filter:()Lorg/scalatest/Filter;
   #84 = Methodref          #75.#83       // org/scalatest/Args.filter:()Lorg/scalatest/Filter;
   #85 = Utf8               expectedTestCount
   #86 = Utf8               (Lorg/scalatest/Filter;)I
   #87 = NameAndType        #85:#86       // expectedTestCount:(Lorg/scalatest/Filter;)I
   #88 = InterfaceMethodref #80.#87       // org/scalatest/Suite.expectedTestCount:(Lorg/scalatest/Filter;)I
   #89 = NameAndType        #23:#24       // invokeBeforeAllAndAfterAllEvenIfNoTestsAreExpected:()Z
   #90 = InterfaceMethodref #2.#89        // org/scalatest/BeforeAndAfterAll.invokeBeforeAllAndAfterAllEvenIfNoTestsAreExpected:()Z
   #91 = MethodType         #29           //  ()V
   #92 = Utf8               $anonfun$run$1
   #93 = Utf8               (Lorg/scalatest/BeforeAndAfterAll;Lscala/Option;)V
   #94 = NameAndType        #92:#93       // $anonfun$run$1:(Lorg/scalatest/BeforeAndAfterAll;Lscala/Option;)V
   #95 = InterfaceMethodref #2.#94        // org/scalatest/BeforeAndAfterAll.$anonfun$run$1:(Lorg/scalatest/BeforeAndAfterAll;Lscala/Option;)V
   #96 = MethodHandle       6:#95         // REF_invokeStatic org/scalatest/BeforeAndAfterAll.$anonfun$run$1:(Lorg/scalatest/BeforeAndAfterAll;Lscala/Option;)V
   #97 = Integer            1
   #98 = Utf8               java/lang/invoke/LambdaMetafactory
   #99 = Class              #98           // java/lang/invoke/LambdaMetafactory
  #100 = Utf8               altMetafactory
  #101 = Utf8               (Ljava/lang/invoke/MethodHandles$Lookup;Ljava/lang/String;Ljava/lang/invoke/MethodType;[Ljava/lang/Object;)Ljava/lang/invoke/CallSite;
  #102 = NameAndType        #100:#101     // altMetafactory:(Ljava/lang/invoke/MethodHandles$Lookup;Ljava/lang/String;Ljava/lang/invoke/MethodType;[Ljava/lang/Object;)Ljava/lang/invoke/CallSite;
  #103 = Methodref          #99.#102      // java/lang/invoke/LambdaMetafactory.altMetafactory:(Ljava/lang/invoke/MethodHandles$Lookup;Ljava/lang/String;Ljava/lang/invoke/MethodType;[Ljava/lang/Object;)Ljava/lang/invoke/CallSite;
  #104 = MethodHandle       6:#103        // REF_invokeStatic java/lang/invoke/LambdaMetafactory.altMetafactory:(Ljava/lang/invoke/MethodHandles$Lookup;Ljava/lang/String;Ljava/lang/invoke/MethodType;[Ljava/lang/Object;)Ljava/lang/invoke/CallSite;
  #105 = Utf8               apply$mcV$sp
  #106 = Utf8               (Lorg/scalatest/BeforeAndAfterAll;Lscala/Option;)Lscala/runtime/java8/JFunction0$mcV$sp;
  #107 = NameAndType        #105:#106     // apply$mcV$sp:(Lorg/scalatest/BeforeAndAfterAll;Lscala/Option;)Lscala/runtime/java8/JFunction0$mcV$sp;
  #108 = InvokeDynamic      #0:#107       // #0:apply$mcV$sp:(Lorg/scalatest/BeforeAndAfterAll;Lscala/Option;)Lscala/runtime/java8/JFunction0$mcV$sp;
  #109 = Utf8               withAfterEffect
  #110 = Utf8               (Lscala/Function0;)Lorg/scalatest/Status;
  #111 = NameAndType        #109:#110     // withAfterEffect:(Lscala/Function0;)Lorg/scalatest/Status;
  #112 = InterfaceMethodref #59.#111      // org/scalatest/Status.withAfterEffect:(Lscala/Function0;)Lorg/scalatest/Status;
  #113 = Utf8               scala/Some
  #114 = Class              #113          // scala/Some
  #115 = Utf8               value
  #116 = NameAndType        #115:#55      // value:()Ljava/lang/Object;
  #117 = Methodref          #114.#116     // scala/Some.value:()Ljava/lang/Object;
  #118 = Utf8               scala/None$
  #119 = Class              #118          // scala/None$
  #120 = Utf8               MODULE$
  #121 = Utf8               Lscala/None$;
  #122 = NameAndType        #120:#121     // MODULE$:Lscala/None$;
  #123 = Fieldref           #119.#122     // scala/None$.MODULE$:Lscala/None$;
  #124 = Utf8               equals
  #125 = Utf8               (Ljava/lang/Object;)Z
  #126 = NameAndType        #124:#125     // equals:(Ljava/lang/Object;)Z
  #127 = Methodref          #4.#126       // java/lang/Object.equals:(Ljava/lang/Object;)Z
  #128 = Utf8               scala/runtime/BoxedUnit
  #129 = Class              #128          // scala/runtime/BoxedUnit
  #130 = Utf8               UNIT
  #131 = Utf8               Lscala/runtime/BoxedUnit;
  #132 = NameAndType        #130:#131     // UNIT:Lscala/runtime/BoxedUnit;
  #133 = Fieldref           #129.#132     // scala/runtime/BoxedUnit.UNIT:Lscala/runtime/BoxedUnit;
  #134 = Utf8               runStatus
  #135 = Utf8               Lorg/scalatest/Status;
  #136 = Utf8               thrownException
  #137 = Utf8               e
  #138 = Utf8               Ljava/lang/Exception;
  #139 = Utf8               statusToReturn
  #140 = Utf8               earlierException
  #141 = Utf8               laterException
  #142 = Utf8               args$1
  #143 = Utf8               testName$1
  #144 = NameAndType        #19:#20       // org$scalatest$BeforeAndAfterAll$$super$run:(Lscala/Option;Lorg/scalatest/Args;)Lorg/scalatest/Status;
  #145 = InterfaceMethodref #2.#144       // org/scalatest/BeforeAndAfterAll.org$scalatest$BeforeAndAfterAll$$super$run:(Lscala/Option;Lorg/scalatest/Args;)Lorg/scalatest/Status;
  #146 = Utf8               org/scalatest/FailedStatus$
  #147 = Class              #146          // org/scalatest/FailedStatus$
  #148 = Utf8               Lorg/scalatest/FailedStatus$;
  #149 = NameAndType        #120:#148     // MODULE$:Lorg/scalatest/FailedStatus$;
  #150 = Fieldref           #147.#149     // org/scalatest/FailedStatus$.MODULE$:Lorg/scalatest/FailedStatus$;
  #151 = Methodref          #114.#72      // scala/Some."<init>":(Ljava/lang/Object;)V
  #152 = Utf8               thrownException$1
  #153 = Utf8               java/lang/Throwable
  #154 = Class              #153          // java/lang/Throwable
  #155 = Utf8               org/scalatest/Suite$
  #156 = Class              #155          // org/scalatest/Suite$
  #157 = Utf8               Lorg/scalatest/Suite$;
  #158 = NameAndType        #120:#157     // MODULE$:Lorg/scalatest/Suite$;
  #159 = Fieldref           #156.#158     // org/scalatest/Suite$.MODULE$:Lorg/scalatest/Suite$;
  #160 = Utf8               anExceptionThatShouldCauseAnAbort
  #161 = Utf8               (Ljava/lang/Throwable;)Z
  #162 = NameAndType        #160:#161     // anExceptionThatShouldCauseAnAbort:(Ljava/lang/Throwable;)Z
  #163 = Methodref          #156.#162     // org/scalatest/Suite$.anExceptionThatShouldCauseAnAbort:(Ljava/lang/Throwable;)Z
  #164 = Utf8               isDefined
  #165 = NameAndType        #164:#24      // isDefined:()Z
  #166 = Methodref          #64.#165      // scala/Option.isDefined:()Z
  #167 = Utf8               $init$
  #168 = NameAndType        #16:#17       // org$scalatest$BeforeAndAfterAll$_setter_$invokeBeforeAllAndAfterAllEvenIfNoTestsAreExpected_$eq:(Z)V
  #169 = InterfaceMethodref #2.#168       // org/scalatest/BeforeAndAfterAll.org$scalatest$BeforeAndAfterAll$_setter_$invokeBeforeAllAndAfterAllEvenIfNoTestsAreExpected_$eq:(Z)V
  #170 = Utf8               $deserializeLambda$
  #171 = Utf8               (Ljava/lang/invoke/SerializedLambda;)Ljava/lang/Object;
  #172 = Utf8               scala/runtime/LambdaDeserialize
  #173 = Class              #172          // scala/runtime/LambdaDeserialize
  #174 = Utf8               bootstrap
  #175 = Utf8               (Ljava/lang/invoke/MethodHandles$Lookup;Ljava/lang/String;Ljava/lang/invoke/MethodType;[Ljava/lang/invoke/MethodHandle;)Ljava/lang/invoke/CallSite;
  #176 = NameAndType        #174:#175     // bootstrap:(Ljava/lang/invoke/MethodHandles$Lookup;Ljava/lang/String;Ljava/lang/invoke/MethodType;[Ljava/lang/invoke/MethodHandle;)Ljava/lang/invoke/CallSite;
  #177 = Methodref          #173.#176     // scala/runtime/LambdaDeserialize.bootstrap:(Ljava/lang/invoke/MethodHandles$Lookup;Ljava/lang/String;Ljava/lang/invoke/MethodType;[Ljava/lang/invoke/MethodHandle;)Ljava/lang/invoke/CallSite;
  #178 = MethodHandle       6:#177        // REF_invokeStatic scala/runtime/LambdaDeserialize.bootstrap:(Ljava/lang/invoke/MethodHandles$Lookup;Ljava/lang/String;Ljava/lang/invoke/MethodType;[Ljava/lang/invoke/MethodHandle;)Ljava/lang/invoke/CallSite;
  #179 = Utf8               lambdaDeserialize
  #180 = NameAndType        #179:#171     // lambdaDeserialize:(Ljava/lang/invoke/SerializedLambda;)Ljava/lang/Object;
  #181 = InvokeDynamic      #1:#180       // #1:lambdaDeserialize:(Ljava/lang/invoke/SerializedLambda;)Ljava/lang/Object;
  #182 = Utf8               MethodParameters
  #183 = Utf8               Code
  #184 = Utf8               LineNumberTable
  #185 = Utf8               LocalVariableTable
  #186 = Utf8               StackMapTable
  #187 = Utf8               Signature
  #188 = Utf8               InnerClasses
  #189 = Utf8               SourceFile
  #190 = Utf8               RuntimeVisibleAnnotations
  #191 = Utf8               BootstrapMethods
  #192 = Utf8               ScalaInlineInfo
  #193 = Utf8               ScalaSig
{
  public abstract void org$scalatest$BeforeAndAfterAll$_setter_$invokeBeforeAllAndAfterAllEvenIfNoTestsAreExpected_$eq(boolean);
    descriptor: (Z)V
    flags: (0x0401) ACC_PUBLIC, ACC_ABSTRACT
    MethodParameters:
      Name                           Flags
      x$1                            final

  public abstract org.scalatest.Status org$scalatest$BeforeAndAfterAll$$super$run(scala.Option, org.scalatest.Args);
    descriptor: (Lscala/Option;Lorg/scalatest/Args;)Lorg/scalatest/Status;
    flags: (0x1401) ACC_PUBLIC, ACC_ABSTRACT, ACC_SYNTHETIC
    MethodParameters:
      Name                           Flags
      testName                       final
      args                           final

  public abstract boolean invokeBeforeAllAndAfterAllEvenIfNoTestsAreExpected();
    descriptor: ()Z
    flags: (0x0401) ACC_PUBLIC, ACC_ABSTRACT

  public static void beforeAll$(org.scalatest.BeforeAndAfterAll);
    descriptor: (Lorg/scalatest/BeforeAndAfterAll;)V
    flags: (0x1009) ACC_PUBLIC, ACC_STATIC, ACC_SYNTHETIC
    Code:
      stack=1, locals=1, args_size=1
         0: aload_0
         1: invokespecial #31                 // InterfaceMethod beforeAll:()V
         4: return
      LineNumberTable:
        line 159: 0
      LocalVariableTable:
        Start  Length  Slot  Name   Signature
            0       5     0 $this   Lorg/scalatest/BeforeAndAfterAll;
    MethodParameters:
      Name                           Flags
      $this                          final synthetic

  public default void beforeAll();
    descriptor: ()V
    flags: (0x0001) ACC_PUBLIC
    Code:
      stack=0, locals=1, args_size=1
         0: return
      LineNumberTable:
        line 159: 0
      LocalVariableTable:
        Start  Length  Slot  Name   Signature
            0       1     0  this   Lorg/scalatest/BeforeAndAfterAll;

  public static void afterAll$(org.scalatest.BeforeAndAfterAll);
    descriptor: (Lorg/scalatest/BeforeAndAfterAll;)V
    flags: (0x1009) ACC_PUBLIC, ACC_STATIC, ACC_SYNTHETIC
    Code:
      stack=1, locals=1, args_size=1
         0: aload_0
         1: invokespecial #37                 // InterfaceMethod afterAll:()V
         4: return
      LineNumberTable:
        line 171: 0
      LocalVariableTable:
        Start  Length  Slot  Name   Signature
            0       5     0 $this   Lorg/scalatest/BeforeAndAfterAll;
    MethodParameters:
      Name                           Flags
      $this                          final synthetic

  public default void afterAll();
    descriptor: ()V
    flags: (0x0001) ACC_PUBLIC
    Code:
      stack=0, locals=1, args_size=1
         0: return
      LineNumberTable:
        line 171: 0
      LocalVariableTable:
        Start  Length  Slot  Name   Signature
            0       1     0  this   Lorg/scalatest/BeforeAndAfterAll;

  public static org.scalatest.Status run$(org.scalatest.BeforeAndAfterAll, scala.Option, org.scalatest.Args);
    descriptor: (Lorg/scalatest/BeforeAndAfterAll;Lscala/Option;Lorg/scalatest/Args;)Lorg/scalatest/Status;
    flags: (0x1009) ACC_PUBLIC, ACC_STATIC, ACC_SYNTHETIC
    Code:
      stack=3, locals=3, args_size=3
         0: aload_0
         1: aload_1
         2: aload_2
         3: invokespecial #42                 // InterfaceMethod run:(Lscala/Option;Lorg/scalatest/Args;)Lorg/scalatest/Status;
         6: areturn
      LineNumberTable:
        line 208: 0
      LocalVariableTable:
        Start  Length  Slot  Name   Signature
            0       7     0 $this   Lorg/scalatest/BeforeAndAfterAll;
            0       7     1 testName   Lscala/Option;
            0       7     2  args   Lorg/scalatest/Args;
    MethodParameters:
      Name                           Flags
      $this                          final synthetic
      testName                       final
      args                           final

  public default org.scalatest.Status run(scala.Option<java.lang.String>, org.scalatest.Args);
    descriptor: (Lscala/Option;Lorg/scalatest/Args;)Lorg/scalatest/Status;
    flags: (0x0001) ACC_PUBLIC
    Code:
      stack=4, locals=20, args_size=3
         0: aload_0
         1: aload_2
         2: aload_1
         3: invokespecial #51                 // InterfaceMethod liftedTree1$1:(Lorg/scalatest/Args;Lscala/Option;)Lscala/Tuple2;
         6: astore        7
         8: aload         7
        10: ifnull        49
        13: aload         7
        15: invokevirtual #57                 // Method scala/Tuple2._1:()Ljava/lang/Object;
        18: checkcast     #59                 // class org/scalatest/Status
        21: astore        8
        23: aload         7
        25: invokevirtual #62                 // Method scala/Tuple2._2:()Ljava/lang/Object;
        28: checkcast     #64                 // class scala/Option
        31: astore        9
        33: new           #53                 // class scala/Tuple2
        36: dup
        37: aload         8
        39: aload         9
        41: invokespecial #68                 // Method scala/Tuple2."<init>":(Ljava/lang/Object;Ljava/lang/Object;)V
        44: astore        5
        46: goto          62
        49: goto          52
        52: new           #70                 // class scala/MatchError
        55: dup
        56: aload         7
        58: invokespecial #73                 // Method scala/MatchError."<init>":(Ljava/lang/Object;)V
        61: athrow
        62: aload         5
        64: astore        6
        66: aload         6
        68: invokevirtual #57                 // Method scala/Tuple2._1:()Ljava/lang/Object;
        71: checkcast     #59                 // class org/scalatest/Status
        74: astore        10
        76: aload         6
        78: invokevirtual #62                 // Method scala/Tuple2._2:()Ljava/lang/Object;
        81: checkcast     #64                 // class scala/Option
        84: astore        11
        86: aload_2
        87: invokevirtual #78                 // Method org/scalatest/Args.runTestInNewInstance:()Z
        90: ifne          137
        93: aload_0
        94: checkcast     #80                 // class org/scalatest/Suite
        97: aload_2
        98: invokevirtual #84                 // Method org/scalatest/Args.filter:()Lorg/scalatest/Filter;
       101: invokeinterface #88,  2           // InterfaceMethod org/scalatest/Suite.expectedTestCount:(Lorg/scalatest/Filter;)I
       106: iconst_0
       107: if_icmpgt     119
       110: aload_0
       111: invokeinterface #90,  1           // InterfaceMethod invokeBeforeAllAndAfterAllEvenIfNoTestsAreExpected:()Z
       116: ifeq          137
       119: aload         10
       121: aload_0
       122: aload         11
       124: invokedynamic #108,  0            // InvokeDynamic #0:apply$mcV$sp:(Lorg/scalatest/BeforeAndAfterAll;Lscala/Option;)Lscala/runtime/java8/JFunction0$mcV$sp;
       129: invokeinterface #112,  2          // InterfaceMethod org/scalatest/Status.withAfterEffect:(Lscala/Function0;)Lorg/scalatest/Status;
       134: goto          139
       137: aload         10
       139: astore        12
       141: aload         11
       143: astore        13
       145: aload         13
       147: instanceof    #114                // class scala/Some
       150: ifeq          173
       153: aload         13
       155: checkcast     #114                // class scala/Some
       158: astore        14
       160: aload         14
       162: invokevirtual #117                // Method scala/Some.value:()Ljava/lang/Object;
       165: checkcast     #47                 // class java/lang/Exception
       168: astore        15
       170: aload         15
       172: athrow
       173: goto          176
       176: getstatic     #123                // Field scala/None$.MODULE$:Lscala/None$;
       179: aload         13
       181: invokevirtual #127                // Method java/lang/Object.equals:(Ljava/lang/Object;)Z
       184: ifeq          195
       187: getstatic     #133                // Field scala/runtime/BoxedUnit.UNIT:Lscala/runtime/BoxedUnit;
       190: astore        4
       192: goto          208
       195: goto          198
       198: new           #70                 // class scala/MatchError
       201: dup
       202: aload         13
       204: invokespecial #73                 // Method scala/MatchError."<init>":(Ljava/lang/Object;)V
       207: athrow
       208: aload         12
       210: goto          277
       213: astore        16
       215: aload         11
       217: astore        17
       219: aload         17
       221: instanceof    #114                // class scala/Some
       224: ifeq          247
       227: aload         17
       229: checkcast     #114                // class scala/Some
       232: astore        18
       234: aload         18
       236: invokevirtual #117                // Method scala/Some.value:()Ljava/lang/Object;
       239: checkcast     #47                 // class java/lang/Exception
       242: astore        19
       244: aload         19
       246: athrow
       247: goto          250
       250: getstatic     #123                // Field scala/None$.MODULE$:Lscala/None$;
       253: aload         17
       255: invokevirtual #127                // Method java/lang/Object.equals:(Ljava/lang/Object;)Z
       258: ifeq          264
       261: aload         16
       263: athrow
       264: goto          267
       267: new           #70                 // class scala/MatchError
       270: dup
       271: aload         17
       273: invokespecial #73                 // Method scala/MatchError."<init>":(Ljava/lang/Object;)V
       276: athrow
       277: areturn
      Exception table:
         from    to  target type
            86   210   213   Class java/lang/Exception
      StackMapTable: number_of_entries = 17
        frame_type = 255 /* full_frame */
          offset_delta = 49
          locals = [ class org/scalatest/BeforeAndAfterAll, class scala/Option, class org/scalatest/Args, top, top, top, top, class scala/Tuple2 ]
          stack = []
        frame_type = 2 /* same */
        frame_type = 255 /* full_frame */
          offset_delta = 9
          locals = [ class org/scalatest/BeforeAndAfterAll, class scala/Option, class org/scalatest/Args, top, top, class scala/Tuple2, top, class scala/Tuple2, class org/scalatest/Status, class scala/Option ]
          stack = []
        frame_type = 255 /* full_frame */
          offset_delta = 56
          locals = [ class org/scalatest/BeforeAndAfterAll, class scala/Option, class org/scalatest/Args, top, top, class scala/Tuple2, class scala/Tuple2, class scala/Tuple2, class org/scalatest/Status, class scala/Option, class org/scalatest/Status, class scala/Option ]
          stack = []
        frame_type = 17 /* same */
        frame_type = 65 /* same_locals_1_stack_item */
          stack = [ class org/scalatest/Status ]
        frame_type = 253 /* append */
          offset_delta = 33
          locals = [ class org/scalatest/Status, class scala/Option ]
        frame_type = 2 /* same */
        frame_type = 18 /* same */
        frame_type = 2 /* same */
        frame_type = 255 /* full_frame */
          offset_delta = 9
          locals = [ class org/scalatest/BeforeAndAfterAll, class scala/Option, class org/scalatest/Args, top, class scala/runtime/BoxedUnit, class scala/Tuple2, class scala/Tuple2, class scala/Tuple2, class org/scalatest/Status, class scala/Option, class org/scalatest/Status, class scala/Option, class org/scalatest/Status, class scala/Option ]
          stack = []
        frame_type = 255 /* full_frame */
          offset_delta = 4
          locals = [ class org/scalatest/BeforeAndAfterAll, class scala/Option, class org/scalatest/Args, top, top, class scala/Tuple2, class scala/Tuple2, class scala/Tuple2, class org/scalatest/Status, class scala/Option, class org/scalatest/Status, class scala/Option ]
          stack = [ class java/lang/Exception ]
        frame_type = 255 /* full_frame */
          offset_delta = 33
          locals = [ class org/scalatest/BeforeAndAfterAll, class scala/Option, class org/scalatest/Args, top, top, class scala/Tuple2, class scala/Tuple2, class scala/Tuple2, class org/scalatest/Status, class scala/Option, class org/scalatest/Status, class scala/Option, top, top, top, top, class java/lang/Exception, class scala/Option ]
          stack = []
        frame_type = 2 /* same */
        frame_type = 13 /* same */
        frame_type = 2 /* same */
        frame_type = 255 /* full_frame */
          offset_delta = 9
          locals = [ class org/scalatest/BeforeAndAfterAll, class scala/Option, class org/scalatest/Args, top, class scala/runtime/BoxedUnit, class scala/Tuple2, class scala/Tuple2, class scala/Tuple2, class org/scalatest/Status, class scala/Option, class org/scalatest/Status, class scala/Option, class org/scalatest/Status, class scala/Option ]
          stack = [ class org/scalatest/Status ]
      LineNumberTable:
        line 210: 0
        line 209: 8
        line 210: 52
        line 209: 66
        line 221: 86
        line 223: 119
        line 224: 121
        line 233: 137
        line 234: 141
        line 235: 145
        line 236: 176
        line 234: 198
        line 238: 208
        line 242: 215
        line 243: 219
        line 244: 250
        line 242: 267
      LocalVariableTable:
        Start  Length  Slot  Name   Signature
           23      26     8 runStatus   Lorg/scalatest/Status;
           33      16     9 thrownException   Lscala/Option;
          170       3    15     e   Ljava/lang/Exception;
          141      69    12 statusToReturn   Lorg/scalatest/Status;
          244       3    19 earlierException   Ljava/lang/Exception;
          213      64    16 laterException   Ljava/lang/Exception;
           76     201    10 runStatus   Lorg/scalatest/Status;
           86     191    11 thrownException   Lscala/Option;
            0     278     0  this   Lorg/scalatest/BeforeAndAfterAll;
            0     278     1 testName   Lscala/Option;
            0     278     2  args   Lorg/scalatest/Args;
    Signature: #45                          // (Lscala/Option<Ljava/lang/String;>;Lorg/scalatest/Args;)Lorg/scalatest/Status;
    MethodParameters:
      Name                           Flags
      testName                       final
      args                           final

  private scala.Tuple2 liftedTree1$1(org.scalatest.Args, scala.Option);
    descriptor: (Lorg/scalatest/Args;Lscala/Option;)Lscala/Tuple2;
    flags: (0x1002) ACC_PRIVATE, ACC_SYNTHETIC
    Code:
      stack=6, locals=4, args_size=3
         0: aload_1
         1: invokevirtual #78                 // Method org/scalatest/Args.runTestInNewInstance:()Z
         4: ifne          42
         7: aload_0
         8: checkcast     #80                 // class org/scalatest/Suite
        11: aload_1
        12: invokevirtual #84                 // Method org/scalatest/Args.filter:()Lorg/scalatest/Filter;
        15: invokeinterface #88,  2           // InterfaceMethod org/scalatest/Suite.expectedTestCount:(Lorg/scalatest/Filter;)I
        20: iconst_0
        21: if_icmpgt     33
        24: aload_0
        25: invokeinterface #90,  1           // InterfaceMethod invokeBeforeAllAndAfterAllEvenIfNoTestsAreExpected:()Z
        30: ifeq          42
        33: aload_0
        34: invokeinterface #31,  1           // InterfaceMethod beforeAll:()V
        39: goto          42
        42: new           #53                 // class scala/Tuple2
        45: dup
        46: aload_0
        47: aload_2
        48: aload_1
        49: invokeinterface #145,  3          // InterfaceMethod org$scalatest$BeforeAndAfterAll$$super$run:(Lscala/Option;Lorg/scalatest/Args;)Lorg/scalatest/Status;
        54: getstatic     #123                // Field scala/None$.MODULE$:Lscala/None$;
        57: invokespecial #68                 // Method scala/Tuple2."<init>":(Ljava/lang/Object;Ljava/lang/Object;)V
        60: goto          85
        63: astore_3
        64: new           #53                 // class scala/Tuple2
        67: dup
        68: getstatic     #150                // Field org/scalatest/FailedStatus$.MODULE$:Lorg/scalatest/FailedStatus$;
        71: new           #114                // class scala/Some
        74: dup
        75: aload_3
        76: invokespecial #151                // Method scala/Some."<init>":(Ljava/lang/Object;)V
        79: invokespecial #68                 // Method scala/Tuple2."<init>":(Ljava/lang/Object;Ljava/lang/Object;)V
        82: goto          85
        85: areturn
      Exception table:
         from    to  target type
             0    60    63   Class java/lang/Exception
      StackMapTable: number_of_entries = 4
        frame_type = 33 /* same */
        frame_type = 8 /* same */
        frame_type = 84 /* same_locals_1_stack_item */
          stack = [ class java/lang/Exception ]
        frame_type = 85 /* same_locals_1_stack_item */
          stack = [ class scala/Tuple2 ]
      LineNumberTable:
        line 211: 0
        line 212: 33
        line 213: 42
        line 216: 64
      LocalVariableTable:
        Start  Length  Slot  Name   Signature
           63      19     3     e   Ljava/lang/Exception;
            0      86     0  this   Lorg/scalatest/BeforeAndAfterAll;
            0      86     1 args$1   Lorg/scalatest/Args;
            0      86     2 testName$1   Lscala/Option;
    MethodParameters:
      Name                           Flags
      args$1                         final
      testName$1                     final

  public static void $anonfun$run$1(org.scalatest.BeforeAndAfterAll, scala.Option);
    descriptor: (Lorg/scalatest/BeforeAndAfterAll;Lscala/Option;)V
    flags: (0x1009) ACC_PUBLIC, ACC_STATIC, ACC_SYNTHETIC
    Code:
      stack=2, locals=6, args_size=2
         0: aload_0
         1: invokeinterface #37,  1           // InterfaceMethod afterAll:()V
         6: goto          64
         9: astore_3
        10: aload_3
        11: astore        4
        13: aload         4
        15: instanceof    #47                 // class java/lang/Exception
        18: ifeq          56
        21: aload         4
        23: checkcast     #47                 // class java/lang/Exception
        26: astore        5
        28: getstatic     #159                // Field org/scalatest/Suite$.MODULE$:Lorg/scalatest/Suite$;
        31: aload         5
        33: invokevirtual #163                // Method org/scalatest/Suite$.anExceptionThatShouldCauseAnAbort:(Ljava/lang/Throwable;)Z
        36: ifne          53
        39: aload_1
        40: invokevirtual #166                // Method scala/Option.isDefined:()Z
        43: ifeq          53
        46: getstatic     #133                // Field scala/runtime/BoxedUnit.UNIT:Lscala/runtime/BoxedUnit;
        49: astore_2
        50: goto          61
        53: goto          59
        56: goto          59
        59: aload_3
        60: athrow
        61: goto          64
        64: return
      Exception table:
         from    to  target type
             0     6     9   Class java/lang/Throwable
      StackMapTable: number_of_entries = 6
        frame_type = 73 /* same_locals_1_stack_item */
          stack = [ class java/lang/Throwable ]
        frame_type = 255 /* full_frame */
          offset_delta = 43
          locals = [ class org/scalatest/BeforeAndAfterAll, class scala/Option, top, class java/lang/Throwable, class java/lang/Throwable, class java/lang/Exception ]
          stack = []
        frame_type = 250 /* chop */
          offset_delta = 2
        frame_type = 2 /* same */
        frame_type = 255 /* full_frame */
          offset_delta = 1
          locals = [ class org/scalatest/BeforeAndAfterAll, class scala/Option, class scala/runtime/BoxedUnit, class java/lang/Throwable, class java/lang/Throwable, class java/lang/Exception ]
          stack = []
        frame_type = 255 /* full_frame */
          offset_delta = 2
          locals = [ class org/scalatest/BeforeAndAfterAll, class scala/Option ]
          stack = []
      LineNumberTable:
        line 225: 0
        line 228: 10
        line 228: 13
        line 224: 59
      LocalVariableTable:
        Start  Length  Slot  Name   Signature
            0      65     0 $this   Lorg/scalatest/BeforeAndAfterAll;
            0      65     1 thrownException$1   Lscala/Option;
    MethodParameters:
      Name                           Flags
      $this                          final synthetic
      thrownException$1              final

  public static void $init$(org.scalatest.BeforeAndAfterAll);
    descriptor: (Lorg/scalatest/BeforeAndAfterAll;)V
    flags: (0x0009) ACC_PUBLIC, ACC_STATIC
    Code:
      stack=2, locals=1, args_size=1
         0: aload_0
         1: iconst_0
         2: invokeinterface #169,  2          // InterfaceMethod org$scalatest$BeforeAndAfterAll$_setter_$invokeBeforeAllAndAfterAllEvenIfNoTestsAreExpected_$eq:(Z)V
         7: return
      LineNumberTable:
        line 148: 0
        line 135: 7
      LocalVariableTable:
        Start  Length  Slot  Name   Signature
            0       8     0 $this   Lorg/scalatest/BeforeAndAfterAll;
    MethodParameters:
      Name                           Flags
      $this                          final synthetic

  private static java.lang.Object $deserializeLambda$(java.lang.invoke.SerializedLambda);
    descriptor: (Ljava/lang/invoke/SerializedLambda;)Ljava/lang/Object;
    flags: (0x100a) ACC_PRIVATE, ACC_STATIC, ACC_SYNTHETIC
    Code:
      stack=1, locals=1, args_size=1
         0: aload_0
         1: invokedynamic #181,  0            // InvokeDynamic #1:lambdaDeserialize:(Ljava/lang/invoke/SerializedLambda;)Ljava/lang/Object;
         6: areturn
}
InnerClasses:
  public static final #15= #12 of #14;    // Lookup=class java/lang/invoke/MethodHandles$Lookup of class java/lang/invoke/MethodHandles
SourceFile: "BeforeAndAfterAll.scala"
RuntimeVisibleAnnotations:
  0: #8(#9=s#10)
    scala.reflect.ScalaSignature(
      bytes="\u0006\u0005)3\u0001b\u0002\u0005\u0011\u0002\u0007\u0005Qb\u0011\u0005\u00061\u0001!\t!\u0007\u0005\b;\u0001\u0011\r\u0011\"\u0001\u001f\u0011\u0015\u0011\u0003\u0001\"\u0005\u001a\u0011\u0015\u0019\u0003\u0001\"\u0005\u001a\u0011\u0019!\u0003\u0001%C\u0001K!Ya\b\u0001I\u0001\u0004\u0003\u0005I\u0011B C\u0005E\u0011UMZ8sK\u0006sG-\u00114uKJ\fE\u000e\u001c\u0006\u0003\u0013)\t\u0011b]2bY\u0006$Xm\u001d;\u000b\u0003-\t1a\u001c:h\u0007\u0001\u00192\u0001\u0001\b\u0015!\ty!#D\u0001\u0011\u0015\u0005\t\u0012!B:dC2\f\u0017BA\n\u0011\u0005\u0019\te.\u001f*fMB\u0011QCF\u0007\u0002\u0011%\u0011q\u0003\u0003\u0002\u000b\'VLG/Z\'jq&t\u0017A\u0002\u0013j]&$H\u0005F\u0001\u001b!\ty1$\u0003\u0002\u001d!\t!QK\\5u\u0003IJgN^8lK\n+gm\u001c:f\u00032d\u0017I\u001c3BMR,\'/\u00117m\u000bZ,g.\u00134O_R+7\u000f^:Be\u0016,\u0005\u0010]3di\u0016$W#A\u0010\u0011\u0005=\u0001\u0013BA\u0011\u0011\u0005\u001d\u0011un\u001c7fC:\f\u0011BY3g_J,\u0017\t\u001c7\u0002\u0011\u00054G/\u001a:BY2\f1A];o)\r1\u0013&\u000f\t\u0003+\u001dJ!\u0001\u000b\u0005\u0003\rM#\u0018\r^;t\u0011\u0015QS\u00011\u0001,\u0003!!Xm\u001d;OC6,\u0007cA\b-]%\u0011Q\u0006\u0005\u0002\u0007\u001fB$\u0018n\u001c8\u0011\u0005=2dB\u0001\u00195!\t\t\u0004#D\u00013\u0015\t\u0019D\"\u0001\u0004=e>|GOP\u0005\u0003kA\ta\u0001\u0015:fI\u00164\u0017BA\u001c9\u0005\u0019\u0019FO]5oO*\u0011Q\u0007\u0005\u0005\u0006u\u0015\u0001\raO\u0001\u0005CJ<7\u000f\u0005\u0002\u0016y%\u0011Q\b\u0003\u0002\u0005\u0003J<7/A\u0005tkB,\'\u000f\n:v]R\u0019a\u0005Q!\t\u000b)2\u0001\u0019A\u0016\t\u000bi2\u0001\u0019A\u001e\n\u0005\u00112\"c\u0001#G\u000f\u001a!Q\t\u0001\u0001D\u00051a$/\u001a4j]\u0016lWM\u001c;?!\t)\u0002\u0001\u0005\u0002\u0016\u0011&\u0011\u0011\n\u0003\u0002\u0006\'VLG/\u001a"
    )
BootstrapMethods:
  0: #104 REF_invokeStatic java/lang/invoke/LambdaMetafactory.altMetafactory:(Ljava/lang/invoke/MethodHandles$Lookup;Ljava/lang/String;Ljava/lang/invoke/MethodType;[Ljava/lang/Object;)Ljava/lang/invoke/CallSite;
    Method arguments:
      #91 ()V
      #96 REF_invokeStatic org/scalatest/BeforeAndAfterAll.$anonfun$run$1:(Lorg/scalatest/BeforeAndAfterAll;Lscala/Option;)V
      #91 ()V
      #97 1
  1: #178 REF_invokeStatic scala/runtime/LambdaDeserialize.bootstrap:(Ljava/lang/invoke/MethodHandles$Lookup;Ljava/lang/String;Ljava/lang/invoke/MethodType;[Ljava/lang/invoke/MethodHandle;)Ljava/lang/invoke/CallSite;
    Method arguments:
      #96 REF_invokeStatic org/scalatest/BeforeAndAfterAll.$anonfun$run$1:(Lorg/scalatest/BeforeAndAfterAll;Lscala/Option;)V
  ScalaInlineInfo: length = 0x40 (unknown attribute)
   01 00 00 0C 00 5C 00 5D 01 00 A7 00 1A 01 00 23
   00 1D 00 00 22 00 1A 01 00 1C 00 1D 00 00 19 00
   1A 01 00 17 00 18 00 00 30 00 31 01 00 13 00 14
   01 00 10 00 11 00 00 28 00 14 00 00 26 00 27 01

  ScalaSig: length = 0x3 (unknown attribute)
   05 02 00
