Classfile /Users/mw/Projects/slang-braindump/.jar/jar11/assemble/slang-braindump/assemble/content/org/scalatest/Canceled$.class
  Last modified May 29, 2022; size 6295 bytes
  SHA-256 checksum 5cd43e407274f934b7eebb4c47e9cb581806f47ec8bac3186dd0fc0bf40b2240
  Compiled from "Outcome.scala"
public final class org.scalatest.Canceled$ implements java.io.Serializable
  minor version: 0
  major version: 52
  flags: (0x0031) ACC_PUBLIC, ACC_FINAL, ACC_SUPER
  this_class: #2                          // org/scalatest/Canceled$
  super_class: #4                         // java/lang/Object
  interfaces: 1, fields: 1, methods: 18, attributes: 5
Constant pool:
    #1 = Utf8               org/scalatest/Canceled$
    #2 = Class              #1            // org/scalatest/Canceled$
    #3 = Utf8               java/lang/Object
    #4 = Class              #3            // java/lang/Object
    #5 = Utf8               java/io/Serializable
    #6 = Class              #5            // java/io/Serializable
    #7 = Utf8               Outcome.scala
    #8 = Utf8               java/lang/invoke/MethodHandles$Lookup
    #9 = Class              #8            // java/lang/invoke/MethodHandles$Lookup
   #10 = Utf8               java/lang/invoke/MethodHandles
   #11 = Class              #10           // java/lang/invoke/MethodHandles
   #12 = Utf8               Lookup
   #13 = Utf8               org/scalactic/Requirements$RequirementsHelper
   #14 = Class              #13           // org/scalactic/Requirements$RequirementsHelper
   #15 = Utf8               org/scalactic/Requirements
   #16 = Class              #15           // org/scalactic/Requirements
   #17 = Utf8               RequirementsHelper
   #18 = Utf8               MODULE$
   #19 = Utf8               Lorg/scalatest/Canceled$;
   #20 = Utf8               <clinit>
   #21 = Utf8               ()V
   #22 = Utf8               <init>
   #23 = NameAndType        #22:#21       // "<init>":()V
   #24 = Methodref          #2.#23        // org/scalatest/Canceled$."<init>":()V
   #25 = NameAndType        #18:#19       // MODULE$:Lorg/scalatest/Canceled$;
   #26 = Fieldref           #2.#25        // org/scalatest/Canceled$.MODULE$:Lorg/scalatest/Canceled$;
   #27 = Utf8               apply
   #28 = Utf8               (Lorg/scalactic/source/Position;)Lorg/scalatest/Canceled;
   #29 = Utf8               pos
   #30 = Utf8               org/scalatest/Canceled
   #31 = Class              #30           // org/scalatest/Canceled
   #32 = Utf8               org/scalatest/exceptions/TestCanceledException
   #33 = Class              #32           // org/scalatest/exceptions/TestCanceledException
   #34 = Utf8               (Ljava/lang/Object;)Ljava/lang/Object;
   #35 = MethodType         #34           //  (Ljava/lang/Object;)Ljava/lang/Object;
   #36 = Utf8               $anonfun$apply$6
   #37 = Utf8               (Lorg/scalatest/exceptions/StackDepthException;)Lscala/None$;
   #38 = NameAndType        #36:#37       // $anonfun$apply$6:(Lorg/scalatest/exceptions/StackDepthException;)Lscala/None$;
   #39 = Methodref          #2.#38        // org/scalatest/Canceled$.$anonfun$apply$6:(Lorg/scalatest/exceptions/StackDepthException;)Lscala/None$;
   #40 = MethodHandle       6:#39         // REF_invokeStatic org/scalatest/Canceled$.$anonfun$apply$6:(Lorg/scalatest/exceptions/StackDepthException;)Lscala/None$;
   #41 = MethodType         #37           //  (Lorg/scalatest/exceptions/StackDepthException;)Lscala/None$;
   #42 = Integer            5
   #43 = Integer            1
   #44 = Utf8               java/lang/invoke/LambdaMetafactory
   #45 = Class              #44           // java/lang/invoke/LambdaMetafactory
   #46 = Utf8               altMetafactory
   #47 = Utf8               (Ljava/lang/invoke/MethodHandles$Lookup;Ljava/lang/String;Ljava/lang/invoke/MethodType;[Ljava/lang/Object;)Ljava/lang/invoke/CallSite;
   #48 = NameAndType        #46:#47       // altMetafactory:(Ljava/lang/invoke/MethodHandles$Lookup;Ljava/lang/String;Ljava/lang/invoke/MethodType;[Ljava/lang/Object;)Ljava/lang/invoke/CallSite;
   #49 = Methodref          #45.#48       // java/lang/invoke/LambdaMetafactory.altMetafactory:(Ljava/lang/invoke/MethodHandles$Lookup;Ljava/lang/String;Ljava/lang/invoke/MethodType;[Ljava/lang/Object;)Ljava/lang/invoke/CallSite;
   #50 = MethodHandle       6:#49         // REF_invokeStatic java/lang/invoke/LambdaMetafactory.altMetafactory:(Ljava/lang/invoke/MethodHandles$Lookup;Ljava/lang/String;Ljava/lang/invoke/MethodType;[Ljava/lang/Object;)Ljava/lang/invoke/CallSite;
   #51 = Utf8               ()Lscala/Function1;
   #52 = NameAndType        #27:#51       // apply:()Lscala/Function1;
   #53 = InvokeDynamic      #0:#52        // #0:apply:()Lscala/Function1;
   #54 = Utf8               scala/None$
   #55 = Class              #54           // scala/None$
   #56 = Utf8               Lscala/None$;
   #57 = NameAndType        #18:#56       // MODULE$:Lscala/None$;
   #58 = Fieldref           #55.#57       // scala/None$.MODULE$:Lscala/None$;
   #59 = Utf8               scala/package$
   #60 = Class              #59           // scala/package$
   #61 = Utf8               Lscala/package$;
   #62 = NameAndType        #18:#61       // MODULE$:Lscala/package$;
   #63 = Fieldref           #60.#62       // scala/package$.MODULE$:Lscala/package$;
   #64 = Utf8               Left
   #65 = Utf8               ()Lscala/util/Left$;
   #66 = NameAndType        #64:#65       // Left:()Lscala/util/Left$;
   #67 = Methodref          #60.#66       // scala/package$.Left:()Lscala/util/Left$;
   #68 = Utf8               scala/util/Left$
   #69 = Class              #68           // scala/util/Left$
   #70 = Utf8               (Ljava/lang/Object;)Lscala/util/Left;
   #71 = NameAndType        #27:#70       // apply:(Ljava/lang/Object;)Lscala/util/Left;
   #72 = Methodref          #69.#71       // scala/util/Left$.apply:(Ljava/lang/Object;)Lscala/util/Left;
   #73 = Utf8               (Lscala/Function1;Lscala/Option;Lscala/util/Either;Lscala/Option;)V
   #74 = NameAndType        #22:#73       // "<init>":(Lscala/Function1;Lscala/Option;Lscala/util/Either;Lscala/Option;)V
   #75 = Methodref          #33.#74       // org/scalatest/exceptions/TestCanceledException."<init>":(Lscala/Function1;Lscala/Option;Lscala/util/Either;Lscala/Option;)V
   #76 = Utf8               (Lorg/scalatest/exceptions/TestCanceledException;)V
   #77 = NameAndType        #22:#76       // "<init>":(Lorg/scalatest/exceptions/TestCanceledException;)V
   #78 = Methodref          #31.#77       // org/scalatest/Canceled."<init>":(Lorg/scalatest/exceptions/TestCanceledException;)V
   #79 = Utf8               this
   #80 = Utf8               Lorg/scalactic/source/Position;
   #81 = Utf8               (Ljava/lang/String;Ljava/lang/Throwable;Lorg/scalactic/source/Position;)Lorg/scalatest/Canceled;
   #82 = Utf8               message
   #83 = Utf8               cause
   #84 = Utf8               $anonfun$apply$7
   #85 = Utf8               (Ljava/lang/String;Lorg/scalatest/exceptions/StackDepthException;)Lscala/Some;
   #86 = NameAndType        #84:#85       // $anonfun$apply$7:(Ljava/lang/String;Lorg/scalatest/exceptions/StackDepthException;)Lscala/Some;
   #87 = Methodref          #2.#86        // org/scalatest/Canceled$.$anonfun$apply$7:(Ljava/lang/String;Lorg/scalatest/exceptions/StackDepthException;)Lscala/Some;
   #88 = MethodHandle       6:#87         // REF_invokeStatic org/scalatest/Canceled$.$anonfun$apply$7:(Ljava/lang/String;Lorg/scalatest/exceptions/StackDepthException;)Lscala/Some;
   #89 = Utf8               (Lorg/scalatest/exceptions/StackDepthException;)Lscala/Some;
   #90 = MethodType         #89           //  (Lorg/scalatest/exceptions/StackDepthException;)Lscala/Some;
   #91 = Utf8               (Ljava/lang/String;)Lscala/Function1;
   #92 = NameAndType        #27:#91       // apply:(Ljava/lang/String;)Lscala/Function1;
   #93 = InvokeDynamic      #1:#92        // #1:apply:(Ljava/lang/String;)Lscala/Function1;
   #94 = Utf8               scala/Some
   #95 = Class              #94           // scala/Some
   #96 = Utf8               (Ljava/lang/Object;)V
   #97 = NameAndType        #22:#96       // "<init>":(Ljava/lang/Object;)V
   #98 = Methodref          #95.#97       // scala/Some."<init>":(Ljava/lang/Object;)V
   #99 = Utf8               Ljava/lang/String;
  #100 = Utf8               Ljava/lang/Throwable;
  #101 = Utf8               (Ljava/lang/Throwable;Lorg/scalactic/source/Position;)Lorg/scalatest/Canceled;
  #102 = Utf8               ex
  #103 = Utf8               java/lang/Throwable
  #104 = Class              #103          // java/lang/Throwable
  #105 = Utf8               getMessage
  #106 = Utf8               ()Ljava/lang/String;
  #107 = NameAndType        #105:#106     // getMessage:()Ljava/lang/String;
  #108 = Methodref          #104.#107     // java/lang/Throwable.getMessage:()Ljava/lang/String;
  #109 = Utf8               $anonfun$apply$8
  #110 = NameAndType        #109:#37      // $anonfun$apply$8:(Lorg/scalatest/exceptions/StackDepthException;)Lscala/None$;
  #111 = Methodref          #2.#110       // org/scalatest/Canceled$.$anonfun$apply$8:(Lorg/scalatest/exceptions/StackDepthException;)Lscala/None$;
  #112 = MethodHandle       6:#111        // REF_invokeStatic org/scalatest/Canceled$.$anonfun$apply$8:(Lorg/scalatest/exceptions/StackDepthException;)Lscala/None$;
  #113 = InvokeDynamic      #2:#52        // #2:apply:()Lscala/Function1;
  #114 = Utf8               $anonfun$apply$9
  #115 = NameAndType        #114:#85      // $anonfun$apply$9:(Ljava/lang/String;Lorg/scalatest/exceptions/StackDepthException;)Lscala/Some;
  #116 = Methodref          #2.#115       // org/scalatest/Canceled$.$anonfun$apply$9:(Ljava/lang/String;Lorg/scalatest/exceptions/StackDepthException;)Lscala/Some;
  #117 = MethodHandle       6:#116        // REF_invokeStatic org/scalatest/Canceled$.$anonfun$apply$9:(Ljava/lang/String;Lorg/scalatest/exceptions/StackDepthException;)Lscala/Some;
  #118 = InvokeDynamic      #3:#92        // #3:apply:(Ljava/lang/String;)Lscala/Function1;
  #119 = Utf8               msg
  #120 = Utf8               java/lang/String
  #121 = Class              #120          // java/lang/String
  #122 = Utf8               org/scalactic/source/Position
  #123 = Class              #122          // org/scalactic/source/Position
  #124 = Utf8               (Ljava/lang/String;Lorg/scalactic/source/Position;)Lorg/scalatest/Canceled;
  #125 = Utf8               org/scalactic/Requirements$
  #126 = Class              #125          // org/scalactic/Requirements$
  #127 = Utf8               Lorg/scalactic/Requirements$;
  #128 = NameAndType        #18:#127      // MODULE$:Lorg/scalactic/Requirements$;
  #129 = Fieldref           #126.#128     // org/scalactic/Requirements$.MODULE$:Lorg/scalactic/Requirements$;
  #130 = Utf8               requirementsHelper
  #131 = Utf8               ()Lorg/scalactic/Requirements$RequirementsHelper;
  #132 = NameAndType        #130:#131     // requirementsHelper:()Lorg/scalactic/Requirements$RequirementsHelper;
  #133 = Methodref          #126.#132     // org/scalactic/Requirements$.requirementsHelper:()Lorg/scalactic/Requirements$RequirementsHelper;
  #134 = String             #82           // message
  #135 = Utf8               [Ljava/lang/Object;
  #136 = Class              #135          // "[Ljava/lang/Object;"
  #137 = Utf8               [Ljava/lang/String;
  #138 = Class              #137          // "[Ljava/lang/String;"
  #139 = Utf8               org/scalactic/Prettifier$
  #140 = Class              #139          // org/scalactic/Prettifier$
  #141 = Utf8               Lorg/scalactic/Prettifier$;
  #142 = NameAndType        #18:#141      // MODULE$:Lorg/scalactic/Prettifier$;
  #143 = Fieldref           #140.#142     // org/scalactic/Prettifier$.MODULE$:Lorg/scalactic/Prettifier$;
  #144 = Utf8               default
  #145 = Utf8               ()Lorg/scalactic/Prettifier;
  #146 = NameAndType        #144:#145     // default:()Lorg/scalactic/Prettifier;
  #147 = Methodref          #140.#146     // org/scalactic/Prettifier$.default:()Lorg/scalactic/Prettifier;
  #148 = Utf8               macroRequireNonNull
  #149 = Utf8               ([Ljava/lang/String;[Ljava/lang/Object;Lorg/scalactic/Prettifier;Lorg/scalactic/source/Position;)V
  #150 = NameAndType        #148:#149     // macroRequireNonNull:([Ljava/lang/String;[Ljava/lang/Object;Lorg/scalactic/Prettifier;Lorg/scalactic/source/Position;)V
  #151 = Methodref          #14.#150      // org/scalactic/Requirements$RequirementsHelper.macroRequireNonNull:([Ljava/lang/String;[Ljava/lang/Object;Lorg/scalactic/Prettifier;Lorg/scalactic/source/Position;)V
  #152 = Utf8               $anonfun$apply$10
  #153 = NameAndType        #152:#85      // $anonfun$apply$10:(Ljava/lang/String;Lorg/scalatest/exceptions/StackDepthException;)Lscala/Some;
  #154 = Methodref          #2.#153       // org/scalatest/Canceled$.$anonfun$apply$10:(Ljava/lang/String;Lorg/scalatest/exceptions/StackDepthException;)Lscala/Some;
  #155 = MethodHandle       6:#154        // REF_invokeStatic org/scalatest/Canceled$.$anonfun$apply$10:(Ljava/lang/String;Lorg/scalatest/exceptions/StackDepthException;)Lscala/Some;
  #156 = InvokeDynamic      #4:#92        // #4:apply:(Ljava/lang/String;)Lscala/Function1;
  #157 = Utf8               e
  #158 = Utf8               Lorg/scalatest/exceptions/TestCanceledException;
  #159 = Utf8               here
  #160 = Utf8               $anonfun$here$5
  #161 = Utf8               (Ljava/lang/Throwable;Lorg/scalatest/exceptions/StackDepthException;)Lscala/Some;
  #162 = NameAndType        #160:#161     // $anonfun$here$5:(Ljava/lang/Throwable;Lorg/scalatest/exceptions/StackDepthException;)Lscala/Some;
  #163 = Methodref          #2.#162       // org/scalatest/Canceled$.$anonfun$here$5:(Ljava/lang/Throwable;Lorg/scalatest/exceptions/StackDepthException;)Lscala/Some;
  #164 = MethodHandle       6:#163        // REF_invokeStatic org/scalatest/Canceled$.$anonfun$here$5:(Ljava/lang/Throwable;Lorg/scalatest/exceptions/StackDepthException;)Lscala/Some;
  #165 = Utf8               (Ljava/lang/Throwable;)Lscala/Function1;
  #166 = NameAndType        #27:#165      // apply:(Ljava/lang/Throwable;)Lscala/Function1;
  #167 = InvokeDynamic      #5:#166       // #5:apply:(Ljava/lang/Throwable;)Lscala/Function1;
  #168 = Utf8               $anonfun$here$6
  #169 = NameAndType        #168:#37      // $anonfun$here$6:(Lorg/scalatest/exceptions/StackDepthException;)Lscala/None$;
  #170 = Methodref          #2.#169       // org/scalatest/Canceled$.$anonfun$here$6:(Lorg/scalatest/exceptions/StackDepthException;)Lscala/None$;
  #171 = MethodHandle       6:#170        // REF_invokeStatic org/scalatest/Canceled$.$anonfun$here$6:(Lorg/scalatest/exceptions/StackDepthException;)Lscala/None$;
  #172 = InvokeDynamic      #6:#52        // #6:apply:()Lscala/Function1;
  #173 = Utf8               (Lorg/scalatest/exceptions/TestCanceledException;)Lorg/scalatest/Canceled;
  #174 = Utf8               exception
  #175 = Utf8               unapply
  #176 = Utf8               (Lorg/scalatest/Canceled;)Lscala/Option;
  #177 = Utf8               (Lorg/scalatest/Canceled;)Lscala/Option<Lorg/scalatest/exceptions/TestCanceledException;>;
  #178 = Utf8               x$0
  #179 = Utf8               ()Lorg/scalatest/exceptions/TestCanceledException;
  #180 = NameAndType        #174:#179     // exception:()Lorg/scalatest/exceptions/TestCanceledException;
  #181 = Methodref          #31.#180      // org/scalatest/Canceled.exception:()Lorg/scalatest/exceptions/TestCanceledException;
  #182 = Utf8               Lorg/scalatest/Canceled;
  #183 = Utf8               scala/Option
  #184 = Class              #183          // scala/Option
  #185 = Utf8               writeReplace
  #186 = Utf8               ()Ljava/lang/Object;
  #187 = Utf8               scala/runtime/ModuleSerializationProxy
  #188 = Class              #187          // scala/runtime/ModuleSerializationProxy
  #189 = Utf8               (Ljava/lang/Class;)V
  #190 = NameAndType        #22:#189      // "<init>":(Ljava/lang/Class;)V
  #191 = Methodref          #188.#190     // scala/runtime/ModuleSerializationProxy."<init>":(Ljava/lang/Class;)V
  #192 = Utf8               x$6
  #193 = Utf8               Lorg/scalatest/exceptions/StackDepthException;
  #194 = Utf8               message$3
  #195 = Utf8               x$7
  #196 = Utf8               x$8
  #197 = Utf8               msg$1
  #198 = Utf8               x$9
  #199 = Utf8               message$4
  #200 = Utf8               x$10
  #201 = Utf8               cause$2
  #202 = Utf8               x$11
  #203 = Utf8               x$12
  #204 = Methodref          #4.#23        // java/lang/Object."<init>":()V
  #205 = Utf8               $deserializeLambda$
  #206 = Utf8               (Ljava/lang/invoke/SerializedLambda;)Ljava/lang/Object;
  #207 = Utf8               scala/runtime/LambdaDeserialize
  #208 = Class              #207          // scala/runtime/LambdaDeserialize
  #209 = Utf8               bootstrap
  #210 = Utf8               (Ljava/lang/invoke/MethodHandles$Lookup;Ljava/lang/String;Ljava/lang/invoke/MethodType;[Ljava/lang/invoke/MethodHandle;)Ljava/lang/invoke/CallSite;
  #211 = NameAndType        #209:#210     // bootstrap:(Ljava/lang/invoke/MethodHandles$Lookup;Ljava/lang/String;Ljava/lang/invoke/MethodType;[Ljava/lang/invoke/MethodHandle;)Ljava/lang/invoke/CallSite;
  #212 = Methodref          #208.#211     // scala/runtime/LambdaDeserialize.bootstrap:(Ljava/lang/invoke/MethodHandles$Lookup;Ljava/lang/String;Ljava/lang/invoke/MethodType;[Ljava/lang/invoke/MethodHandle;)Ljava/lang/invoke/CallSite;
  #213 = MethodHandle       6:#212        // REF_invokeStatic scala/runtime/LambdaDeserialize.bootstrap:(Ljava/lang/invoke/MethodHandles$Lookup;Ljava/lang/String;Ljava/lang/invoke/MethodType;[Ljava/lang/invoke/MethodHandle;)Ljava/lang/invoke/CallSite;
  #214 = Utf8               lambdaDeserialize
  #215 = NameAndType        #214:#206     // lambdaDeserialize:(Ljava/lang/invoke/SerializedLambda;)Ljava/lang/Object;
  #216 = InvokeDynamic      #7:#215       // #7:lambdaDeserialize:(Ljava/lang/invoke/SerializedLambda;)Ljava/lang/Object;
  #217 = Utf8               Code
  #218 = Utf8               LineNumberTable
  #219 = Utf8               LocalVariableTable
  #220 = Utf8               MethodParameters
  #221 = Utf8               StackMapTable
  #222 = Utf8               Signature
  #223 = Utf8               InnerClasses
  #224 = Utf8               SourceFile
  #225 = Utf8               BootstrapMethods
  #226 = Utf8               ScalaInlineInfo
  #227 = Utf8               Scala
{
  public static final org.scalatest.Canceled$ MODULE$;
    descriptor: Lorg/scalatest/Canceled$;
    flags: (0x0019) ACC_PUBLIC, ACC_STATIC, ACC_FINAL

  public static {};
    descriptor: ()V
    flags: (0x0009) ACC_PUBLIC, ACC_STATIC
    Code:
      stack=2, locals=0, args_size=0
         0: new           #2                  // class org/scalatest/Canceled$
         3: dup
         4: invokespecial #24                 // Method "<init>":()V
         7: putstatic     #26                 // Field MODULE$:Lorg/scalatest/Canceled$;
        10: return
      LineNumberTable:
        line 504: 0

  public org.scalatest.Canceled apply(org.scalactic.source.Position);
    descriptor: (Lorg/scalactic/source/Position;)Lorg/scalatest/Canceled;
    flags: (0x0001) ACC_PUBLIC
    Code:
      stack=8, locals=2, args_size=2
         0: new           #31                 // class org/scalatest/Canceled
         3: dup
         4: new           #33                 // class org/scalatest/exceptions/TestCanceledException
         7: dup
         8: invokedynamic #53,  0             // InvokeDynamic #0:apply:()Lscala/Function1;
        13: getstatic     #58                 // Field scala/None$.MODULE$:Lscala/None$;
        16: getstatic     #63                 // Field scala/package$.MODULE$:Lscala/package$;
        19: invokevirtual #67                 // Method scala/package$.Left:()Lscala/util/Left$;
        22: aload_1
        23: invokevirtual #72                 // Method scala/util/Left$.apply:(Ljava/lang/Object;)Lscala/util/Left;
        26: getstatic     #58                 // Field scala/None$.MODULE$:Lscala/None$;
        29: invokespecial #75                 // Method org/scalatest/exceptions/TestCanceledException."<init>":(Lscala/Function1;Lscala/Option;Lscala/util/Either;Lscala/Option;)V
        32: invokespecial #78                 // Method org/scalatest/Canceled."<init>":(Lorg/scalatest/exceptions/TestCanceledException;)V
        35: areturn
      LineNumberTable:
        line 511: 0
      LocalVariableTable:
        Start  Length  Slot  Name   Signature
            0      36     0  this   Lorg/scalatest/Canceled$;
            0      36     1   pos   Lorg/scalactic/source/Position;
    MethodParameters:
      Name                           Flags
      pos                            final

  public org.scalatest.Canceled apply(java.lang.String, java.lang.Throwable, org.scalactic.source.Position);
    descriptor: (Ljava/lang/String;Ljava/lang/Throwable;Lorg/scalactic/source/Position;)Lorg/scalatest/Canceled;
    flags: (0x0001) ACC_PUBLIC
    Code:
      stack=8, locals=4, args_size=4
         0: new           #31                 // class org/scalatest/Canceled
         3: dup
         4: new           #33                 // class org/scalatest/exceptions/TestCanceledException
         7: dup
         8: aload_1
         9: invokedynamic #93,  0             // InvokeDynamic #1:apply:(Ljava/lang/String;)Lscala/Function1;
        14: new           #95                 // class scala/Some
        17: dup
        18: aload_2
        19: invokespecial #98                 // Method scala/Some."<init>":(Ljava/lang/Object;)V
        22: getstatic     #63                 // Field scala/package$.MODULE$:Lscala/package$;
        25: invokevirtual #67                 // Method scala/package$.Left:()Lscala/util/Left$;
        28: aload_3
        29: invokevirtual #72                 // Method scala/util/Left$.apply:(Ljava/lang/Object;)Lscala/util/Left;
        32: getstatic     #58                 // Field scala/None$.MODULE$:Lscala/None$;
        35: invokespecial #75                 // Method org/scalatest/exceptions/TestCanceledException."<init>":(Lscala/Function1;Lscala/Option;Lscala/util/Either;Lscala/Option;)V
        38: invokespecial #78                 // Method org/scalatest/Canceled."<init>":(Lorg/scalatest/exceptions/TestCanceledException;)V
        41: areturn
      LineNumberTable:
        line 521: 0
      LocalVariableTable:
        Start  Length  Slot  Name   Signature
            0      42     0  this   Lorg/scalatest/Canceled$;
            0      42     1 message   Ljava/lang/String;
            0      42     2 cause   Ljava/lang/Throwable;
            0      42     3   pos   Lorg/scalactic/source/Position;
    MethodParameters:
      Name                           Flags
      message                        final
      cause                          final
      pos                            final

  public org.scalatest.Canceled apply(java.lang.Throwable, org.scalactic.source.Position);
    descriptor: (Ljava/lang/Throwable;Lorg/scalactic/source/Position;)Lorg/scalatest/Canceled;
    flags: (0x0001) ACC_PUBLIC
    Code:
      stack=8, locals=7, args_size=3
         0: aload_1
         1: astore        4
         3: aload         4
         5: instanceof    #33                 // class org/scalatest/exceptions/TestCanceledException
         8: ifeq          31
        11: aload         4
        13: checkcast     #33                 // class org/scalatest/exceptions/TestCanceledException
        16: astore        5
        18: new           #31                 // class org/scalatest/Canceled
        21: dup
        22: aload         5
        24: invokespecial #78                 // Method org/scalatest/Canceled."<init>":(Lorg/scalatest/exceptions/TestCanceledException;)V
        27: astore_3
        28: goto          134
        31: goto          34
        34: aload_1
        35: invokevirtual #108                // Method java/lang/Throwable.getMessage:()Ljava/lang/String;
        38: astore        6
        40: aload         6
        42: ifnonnull     88
        45: new           #31                 // class org/scalatest/Canceled
        48: dup
        49: new           #33                 // class org/scalatest/exceptions/TestCanceledException
        52: dup
        53: invokedynamic #113,  0            // InvokeDynamic #2:apply:()Lscala/Function1;
        58: new           #95                 // class scala/Some
        61: dup
        62: aload_1
        63: invokespecial #98                 // Method scala/Some."<init>":(Ljava/lang/Object;)V
        66: getstatic     #63                 // Field scala/package$.MODULE$:Lscala/package$;
        69: invokevirtual #67                 // Method scala/package$.Left:()Lscala/util/Left$;
        72: aload_2
        73: invokevirtual #72                 // Method scala/util/Left$.apply:(Ljava/lang/Object;)Lscala/util/Left;
        76: getstatic     #58                 // Field scala/None$.MODULE$:Lscala/None$;
        79: invokespecial #75                 // Method org/scalatest/exceptions/TestCanceledException."<init>":(Lscala/Function1;Lscala/Option;Lscala/util/Either;Lscala/Option;)V
        82: invokespecial #78                 // Method org/scalatest/Canceled."<init>":(Lorg/scalatest/exceptions/TestCanceledException;)V
        85: goto          130
        88: new           #31                 // class org/scalatest/Canceled
        91: dup
        92: new           #33                 // class org/scalatest/exceptions/TestCanceledException
        95: dup
        96: aload         6
        98: invokedynamic #118,  0            // InvokeDynamic #3:apply:(Ljava/lang/String;)Lscala/Function1;
       103: new           #95                 // class scala/Some
       106: dup
       107: aload_1
       108: invokespecial #98                 // Method scala/Some."<init>":(Ljava/lang/Object;)V
       111: getstatic     #63                 // Field scala/package$.MODULE$:Lscala/package$;
       114: invokevirtual #67                 // Method scala/package$.Left:()Lscala/util/Left$;
       117: aload_2
       118: invokevirtual #72                 // Method scala/util/Left$.apply:(Ljava/lang/Object;)Lscala/util/Left;
       121: getstatic     #58                 // Field scala/None$.MODULE$:Lscala/None$;
       124: invokespecial #75                 // Method org/scalatest/exceptions/TestCanceledException."<init>":(Lscala/Function1;Lscala/Option;Lscala/util/Either;Lscala/Option;)V
       127: invokespecial #78                 // Method org/scalatest/Canceled."<init>":(Lorg/scalatest/exceptions/TestCanceledException;)V
       130: astore_3
       131: goto          134
       134: aload_3
       135: areturn
      StackMapTable: number_of_entries = 5
        frame_type = 253 /* append */
          offset_delta = 31
          locals = [ top, class java/lang/Throwable ]
        frame_type = 2 /* same */
        frame_type = 253 /* append */
          offset_delta = 53
          locals = [ top, class java/lang/String ]
        frame_type = 105 /* same_locals_1_stack_item */
          stack = [ class org/scalatest/Canceled ]
        frame_type = 255 /* full_frame */
          offset_delta = 3
          locals = [ class org/scalatest/Canceled$, class java/lang/Throwable, class org/scalactic/source/Position, class org/scalatest/Canceled, class java/lang/Throwable ]
          stack = []
      LineNumberTable:
        line 531: 0
        line 532: 3
        line 533: 18
        line 532: 31
        line 535: 34
        line 536: 40
        line 537: 45
        line 539: 88
        line 531: 134
      LocalVariableTable:
        Start  Length  Slot  Name   Signature
           40      90     6   msg   Ljava/lang/String;
            0     136     0  this   Lorg/scalatest/Canceled$;
            0     136     1    ex   Ljava/lang/Throwable;
            0     136     2   pos   Lorg/scalactic/source/Position;
    MethodParameters:
      Name                           Flags
      ex                             final
      pos                            final

  public org.scalatest.Canceled apply(java.lang.String, org.scalactic.source.Position);
    descriptor: (Ljava/lang/String;Lorg/scalactic/source/Position;)Lorg/scalatest/Canceled;
    flags: (0x0001) ACC_PUBLIC
    Code:
      stack=6, locals=4, args_size=3
         0: getstatic     #129                // Field org/scalactic/Requirements$.MODULE$:Lorg/scalactic/Requirements$;
         3: invokevirtual #133                // Method org/scalactic/Requirements$.requirementsHelper:()Lorg/scalactic/Requirements$RequirementsHelper;
         6: iconst_1
         7: anewarray     #121                // class java/lang/String
        10: dup
        11: iconst_0
        12: ldc           #134                // String message
        14: aastore
        15: checkcast     #136                // class "[Ljava/lang/Object;"
        18: checkcast     #138                // class "[Ljava/lang/String;"
        21: iconst_1
        22: anewarray     #4                  // class java/lang/Object
        25: dup
        26: iconst_0
        27: aload_1
        28: aastore
        29: checkcast     #136                // class "[Ljava/lang/Object;"
        32: getstatic     #143                // Field org/scalactic/Prettifier$.MODULE$:Lorg/scalactic/Prettifier$;
        35: invokevirtual #147                // Method org/scalactic/Prettifier$.default:()Lorg/scalactic/Prettifier;
        38: aload_2
        39: invokevirtual #151                // Method org/scalactic/Requirements$RequirementsHelper.macroRequireNonNull:([Ljava/lang/String;[Ljava/lang/Object;Lorg/scalactic/Prettifier;Lorg/scalactic/source/Position;)V
        42: new           #33                 // class org/scalatest/exceptions/TestCanceledException
        45: dup
        46: aload_1
        47: invokedynamic #156,  0            // InvokeDynamic #4:apply:(Ljava/lang/String;)Lscala/Function1;
        52: getstatic     #58                 // Field scala/None$.MODULE$:Lscala/None$;
        55: getstatic     #63                 // Field scala/package$.MODULE$:Lscala/package$;
        58: invokevirtual #67                 // Method scala/package$.Left:()Lscala/util/Left$;
        61: aload_2
        62: invokevirtual #72                 // Method scala/util/Left$.apply:(Ljava/lang/Object;)Lscala/util/Left;
        65: getstatic     #58                 // Field scala/None$.MODULE$:Lscala/None$;
        68: invokespecial #75                 // Method org/scalatest/exceptions/TestCanceledException."<init>":(Lscala/Function1;Lscala/Option;Lscala/util/Either;Lscala/Option;)V
        71: astore_3
        72: new           #31                 // class org/scalatest/Canceled
        75: dup
        76: aload_3
        77: invokespecial #78                 // Method org/scalatest/Canceled."<init>":(Lorg/scalatest/exceptions/TestCanceledException;)V
        80: areturn
      LineNumberTable:
        line 567: 0
        line 568: 42
        line 570: 72
      LocalVariableTable:
        Start  Length  Slot  Name   Signature
           72       8     3     e   Lorg/scalatest/exceptions/TestCanceledException;
            0      81     0  this   Lorg/scalatest/Canceled$;
            0      81     1 message   Ljava/lang/String;
            0      81     2   pos   Lorg/scalactic/source/Position;
    MethodParameters:
      Name                           Flags
      message                        final
      pos                            final

  public org.scalatest.Canceled here(java.lang.Throwable, org.scalactic.source.Position);
    descriptor: (Ljava/lang/Throwable;Lorg/scalactic/source/Position;)Lorg/scalatest/Canceled;
    flags: (0x0001) ACC_PUBLIC
    Code:
      stack=8, locals=3, args_size=3
         0: new           #31                 // class org/scalatest/Canceled
         3: dup
         4: aload_1
         5: invokevirtual #108                // Method java/lang/Throwable.getMessage:()Ljava/lang/String;
         8: ifnull        48
        11: new           #33                 // class org/scalatest/exceptions/TestCanceledException
        14: dup
        15: aload_1
        16: invokedynamic #167,  0            // InvokeDynamic #5:apply:(Ljava/lang/Throwable;)Lscala/Function1;
        21: new           #95                 // class scala/Some
        24: dup
        25: aload_1
        26: invokespecial #98                 // Method scala/Some."<init>":(Ljava/lang/Object;)V
        29: getstatic     #63                 // Field scala/package$.MODULE$:Lscala/package$;
        32: invokevirtual #67                 // Method scala/package$.Left:()Lscala/util/Left$;
        35: aload_2
        36: invokevirtual #72                 // Method scala/util/Left$.apply:(Ljava/lang/Object;)Lscala/util/Left;
        39: getstatic     #58                 // Field scala/None$.MODULE$:Lscala/None$;
        42: invokespecial #75                 // Method org/scalatest/exceptions/TestCanceledException."<init>":(Lscala/Function1;Lscala/Option;Lscala/util/Either;Lscala/Option;)V
        45: goto          81
        48: new           #33                 // class org/scalatest/exceptions/TestCanceledException
        51: dup
        52: invokedynamic #172,  0            // InvokeDynamic #6:apply:()Lscala/Function1;
        57: new           #95                 // class scala/Some
        60: dup
        61: aload_1
        62: invokespecial #98                 // Method scala/Some."<init>":(Ljava/lang/Object;)V
        65: getstatic     #63                 // Field scala/package$.MODULE$:Lscala/package$;
        68: invokevirtual #67                 // Method scala/package$.Left:()Lscala/util/Left$;
        71: aload_2
        72: invokevirtual #72                 // Method scala/util/Left$.apply:(Ljava/lang/Object;)Lscala/util/Left;
        75: getstatic     #58                 // Field scala/None$.MODULE$:Lscala/None$;
        78: invokespecial #75                 // Method org/scalatest/exceptions/TestCanceledException."<init>":(Lscala/Function1;Lscala/Option;Lscala/util/Either;Lscala/Option;)V
        81: invokespecial #78                 // Method org/scalatest/Canceled."<init>":(Lorg/scalatest/exceptions/TestCanceledException;)V
        84: areturn
      StackMapTable: number_of_entries = 2
        frame_type = 255 /* full_frame */
          offset_delta = 48
          locals = [ class org/scalatest/Canceled$, class java/lang/Throwable, class org/scalactic/source/Position ]
          stack = [ uninitialized 0, uninitialized 0 ]
        frame_type = 255 /* full_frame */
          offset_delta = 32
          locals = [ class org/scalatest/Canceled$, class java/lang/Throwable, class org/scalactic/source/Position ]
          stack = [ uninitialized 0, uninitialized 0, class org/scalatest/exceptions/TestCanceledException ]
      LineNumberTable:
        line 580: 0
        line 581: 4
        line 582: 11
        line 584: 48
      LocalVariableTable:
        Start  Length  Slot  Name   Signature
            0      85     0  this   Lorg/scalatest/Canceled$;
            0      85     1 cause   Ljava/lang/Throwable;
            0      85     2   pos   Lorg/scalactic/source/Position;
    MethodParameters:
      Name                           Flags
      cause                          final
      pos                            final

  public org.scalatest.Canceled apply(org.scalatest.exceptions.TestCanceledException);
    descriptor: (Lorg/scalatest/exceptions/TestCanceledException;)Lorg/scalatest/Canceled;
    flags: (0x0001) ACC_PUBLIC
    Code:
      stack=3, locals=2, args_size=2
         0: new           #31                 // class org/scalatest/Canceled
         3: dup
         4: aload_1
         5: invokespecial #78                 // Method org/scalatest/Canceled."<init>":(Lorg/scalatest/exceptions/TestCanceledException;)V
         8: areturn
      LineNumberTable:
        line 476: 0
      LocalVariableTable:
        Start  Length  Slot  Name   Signature
            0       9     0  this   Lorg/scalatest/Canceled$;
            0       9     1 exception   Lorg/scalatest/exceptions/TestCanceledException;
    MethodParameters:
      Name                           Flags
      exception                      final

  public scala.Option<org.scalatest.exceptions.TestCanceledException> unapply(org.scalatest.Canceled);
    descriptor: (Lorg/scalatest/Canceled;)Lscala/Option;
    flags: (0x0001) ACC_PUBLIC
    Code:
      stack=3, locals=2, args_size=2
         0: aload_1
         1: ifnonnull     10
         4: getstatic     #58                 // Field scala/None$.MODULE$:Lscala/None$;
         7: goto          21
        10: new           #95                 // class scala/Some
        13: dup
        14: aload_1
        15: invokevirtual #181                // Method org/scalatest/Canceled.exception:()Lorg/scalatest/exceptions/TestCanceledException;
        18: invokespecial #98                 // Method scala/Some."<init>":(Ljava/lang/Object;)V
        21: areturn
      StackMapTable: number_of_entries = 2
        frame_type = 10 /* same */
        frame_type = 74 /* same_locals_1_stack_item */
          stack = [ class scala/Option ]
      LineNumberTable:
        line 476: 0
      LocalVariableTable:
        Start  Length  Slot  Name   Signature
            0      22     0  this   Lorg/scalatest/Canceled$;
            0      22     1   x$0   Lorg/scalatest/Canceled;
    Signature: #177                         // (Lorg/scalatest/Canceled;)Lscala/Option<Lorg/scalatest/exceptions/TestCanceledException;>;
    MethodParameters:
      Name                           Flags
      x$0                            final

  private java.lang.Object writeReplace();
    descriptor: ()Ljava/lang/Object;
    flags: (0x0002) ACC_PRIVATE
    Code:
      stack=3, locals=1, args_size=1
         0: new           #188                // class scala/runtime/ModuleSerializationProxy
         3: dup
         4: ldc           #2                  // class org/scalatest/Canceled$
         6: invokespecial #191                // Method scala/runtime/ModuleSerializationProxy."<init>":(Ljava/lang/Class;)V
         9: areturn
      LineNumberTable:
        line 504: 0
      LocalVariableTable:
        Start  Length  Slot  Name   Signature
            0      10     0  this   Lorg/scalatest/Canceled$;

  public static final scala.None$ $anonfun$apply$6(org.scalatest.exceptions.StackDepthException);
    descriptor: (Lorg/scalatest/exceptions/StackDepthException;)Lscala/None$;
    flags: (0x1019) ACC_PUBLIC, ACC_STATIC, ACC_FINAL, ACC_SYNTHETIC
    Code:
      stack=1, locals=1, args_size=1
         0: getstatic     #58                 // Field scala/None$.MODULE$:Lscala/None$;
         3: areturn
      LineNumberTable:
        line 511: 0
      LocalVariableTable:
        Start  Length  Slot  Name   Signature
            0       4     0   x$6   Lorg/scalatest/exceptions/StackDepthException;
    MethodParameters:
      Name                           Flags
      x$6                            final

  public static final scala.Some $anonfun$apply$7(java.lang.String, org.scalatest.exceptions.StackDepthException);
    descriptor: (Ljava/lang/String;Lorg/scalatest/exceptions/StackDepthException;)Lscala/Some;
    flags: (0x1019) ACC_PUBLIC, ACC_STATIC, ACC_FINAL, ACC_SYNTHETIC
    Code:
      stack=3, locals=2, args_size=2
         0: new           #95                 // class scala/Some
         3: dup
         4: aload_0
         5: invokespecial #98                 // Method scala/Some."<init>":(Ljava/lang/Object;)V
         8: areturn
      LineNumberTable:
        line 521: 0
      LocalVariableTable:
        Start  Length  Slot  Name   Signature
            0       9     0 message$3   Ljava/lang/String;
            0       9     1   x$7   Lorg/scalatest/exceptions/StackDepthException;
    MethodParameters:
      Name                           Flags
      message$3                      final
      x$7                            final

  public static final scala.None$ $anonfun$apply$8(org.scalatest.exceptions.StackDepthException);
    descriptor: (Lorg/scalatest/exceptions/StackDepthException;)Lscala/None$;
    flags: (0x1019) ACC_PUBLIC, ACC_STATIC, ACC_FINAL, ACC_SYNTHETIC
    Code:
      stack=1, locals=1, args_size=1
         0: getstatic     #58                 // Field scala/None$.MODULE$:Lscala/None$;
         3: areturn
      LineNumberTable:
        line 537: 0
      LocalVariableTable:
        Start  Length  Slot  Name   Signature
            0       4     0   x$8   Lorg/scalatest/exceptions/StackDepthException;
    MethodParameters:
      Name                           Flags
      x$8                            final

  public static final scala.Some $anonfun$apply$9(java.lang.String, org.scalatest.exceptions.StackDepthException);
    descriptor: (Ljava/lang/String;Lorg/scalatest/exceptions/StackDepthException;)Lscala/Some;
    flags: (0x1019) ACC_PUBLIC, ACC_STATIC, ACC_FINAL, ACC_SYNTHETIC
    Code:
      stack=3, locals=2, args_size=2
         0: new           #95                 // class scala/Some
         3: dup
         4: aload_0
         5: invokespecial #98                 // Method scala/Some."<init>":(Ljava/lang/Object;)V
         8: areturn
      LineNumberTable:
        line 539: 0
      LocalVariableTable:
        Start  Length  Slot  Name   Signature
            0       9     0 msg$1   Ljava/lang/String;
            0       9     1   x$9   Lorg/scalatest/exceptions/StackDepthException;
    MethodParameters:
      Name                           Flags
      msg$1                          final
      x$9                            final

  public static final scala.Some $anonfun$apply$10(java.lang.String, org.scalatest.exceptions.StackDepthException);
    descriptor: (Ljava/lang/String;Lorg/scalatest/exceptions/StackDepthException;)Lscala/Some;
    flags: (0x1019) ACC_PUBLIC, ACC_STATIC, ACC_FINAL, ACC_SYNTHETIC
    Code:
      stack=3, locals=2, args_size=2
         0: new           #95                 // class scala/Some
         3: dup
         4: aload_0
         5: invokespecial #98                 // Method scala/Some."<init>":(Ljava/lang/Object;)V
         8: areturn
      LineNumberTable:
        line 568: 0
      LocalVariableTable:
        Start  Length  Slot  Name   Signature
            0       9     0 message$4   Ljava/lang/String;
            0       9     1  x$10   Lorg/scalatest/exceptions/StackDepthException;
    MethodParameters:
      Name                           Flags
      message$4                      final
      x$10                           final

  public static final scala.Some $anonfun$here$5(java.lang.Throwable, org.scalatest.exceptions.StackDepthException);
    descriptor: (Ljava/lang/Throwable;Lorg/scalatest/exceptions/StackDepthException;)Lscala/Some;
    flags: (0x1019) ACC_PUBLIC, ACC_STATIC, ACC_FINAL, ACC_SYNTHETIC
    Code:
      stack=3, locals=2, args_size=2
         0: new           #95                 // class scala/Some
         3: dup
         4: aload_0
         5: invokevirtual #108                // Method java/lang/Throwable.getMessage:()Ljava/lang/String;
         8: invokespecial #98                 // Method scala/Some."<init>":(Ljava/lang/Object;)V
        11: areturn
      LineNumberTable:
        line 582: 0
      LocalVariableTable:
        Start  Length  Slot  Name   Signature
            0      12     0 cause$2   Ljava/lang/Throwable;
            0      12     1  x$11   Lorg/scalatest/exceptions/StackDepthException;
    MethodParameters:
      Name                           Flags
      cause$2                        final
      x$11                           final

  public static final scala.None$ $anonfun$here$6(org.scalatest.exceptions.StackDepthException);
    descriptor: (Lorg/scalatest/exceptions/StackDepthException;)Lscala/None$;
    flags: (0x1019) ACC_PUBLIC, ACC_STATIC, ACC_FINAL, ACC_SYNTHETIC
    Code:
      stack=1, locals=1, args_size=1
         0: getstatic     #58                 // Field scala/None$.MODULE$:Lscala/None$;
         3: areturn
      LineNumberTable:
        line 584: 0
      LocalVariableTable:
        Start  Length  Slot  Name   Signature
            0       4     0  x$12   Lorg/scalatest/exceptions/StackDepthException;
    MethodParameters:
      Name                           Flags
      x$12                           final

  private org.scalatest.Canceled$();
    descriptor: ()V
    flags: (0x0002) ACC_PRIVATE
    Code:
      stack=1, locals=1, args_size=1
         0: aload_0
         1: invokespecial #204                // Method java/lang/Object."<init>":()V
         4: return
      LineNumberTable:
        line 595: 0
        line 504: 4
      LocalVariableTable:
        Start  Length  Slot  Name   Signature
            0       5     0  this   Lorg/scalatest/Canceled$;

  private static java.lang.Object $deserializeLambda$(java.lang.invoke.SerializedLambda);
    descriptor: (Ljava/lang/invoke/SerializedLambda;)Ljava/lang/Object;
    flags: (0x100a) ACC_PRIVATE, ACC_STATIC, ACC_SYNTHETIC
    Code:
      stack=1, locals=1, args_size=1
         0: aload_0
         1: invokedynamic #216,  0            // InvokeDynamic #7:lambdaDeserialize:(Ljava/lang/invoke/SerializedLambda;)Ljava/lang/Object;
         6: areturn
}
InnerClasses:
  public static final #12= #9 of #11;     // Lookup=class java/lang/invoke/MethodHandles$Lookup of class java/lang/invoke/MethodHandles
  public static #17= #14 of #16;          // RequirementsHelper=class org/scalactic/Requirements$RequirementsHelper of class org/scalactic/Requirements
SourceFile: "Outcome.scala"
BootstrapMethods:
  0: #50 REF_invokeStatic java/lang/invoke/LambdaMetafactory.altMetafactory:(Ljava/lang/invoke/MethodHandles$Lookup;Ljava/lang/String;Ljava/lang/invoke/MethodType;[Ljava/lang/Object;)Ljava/lang/invoke/CallSite;
    Method arguments:
      #35 (Ljava/lang/Object;)Ljava/lang/Object;
      #40 REF_invokeStatic org/scalatest/Canceled$.$anonfun$apply$6:(Lorg/scalatest/exceptions/StackDepthException;)Lscala/None$;
      #41 (Lorg/scalatest/exceptions/StackDepthException;)Lscala/None$;
      #42 5
      #43 1
      #41 (Lorg/scalatest/exceptions/StackDepthException;)Lscala/None$;
  1: #50 REF_invokeStatic java/lang/invoke/LambdaMetafactory.altMetafactory:(Ljava/lang/invoke/MethodHandles$Lookup;Ljava/lang/String;Ljava/lang/invoke/MethodType;[Ljava/lang/Object;)Ljava/lang/invoke/CallSite;
    Method arguments:
      #35 (Ljava/lang/Object;)Ljava/lang/Object;
      #88 REF_invokeStatic org/scalatest/Canceled$.$anonfun$apply$7:(Ljava/lang/String;Lorg/scalatest/exceptions/StackDepthException;)Lscala/Some;
      #90 (Lorg/scalatest/exceptions/StackDepthException;)Lscala/Some;
      #42 5
      #43 1
      #90 (Lorg/scalatest/exceptions/StackDepthException;)Lscala/Some;
  2: #50 REF_invokeStatic java/lang/invoke/LambdaMetafactory.altMetafactory:(Ljava/lang/invoke/MethodHandles$Lookup;Ljava/lang/String;Ljava/lang/invoke/MethodType;[Ljava/lang/Object;)Ljava/lang/invoke/CallSite;
    Method arguments:
      #35 (Ljava/lang/Object;)Ljava/lang/Object;
      #112 REF_invokeStatic org/scalatest/Canceled$.$anonfun$apply$8:(Lorg/scalatest/exceptions/StackDepthException;)Lscala/None$;
      #41 (Lorg/scalatest/exceptions/StackDepthException;)Lscala/None$;
      #42 5
      #43 1
      #41 (Lorg/scalatest/exceptions/StackDepthException;)Lscala/None$;
  3: #50 REF_invokeStatic java/lang/invoke/LambdaMetafactory.altMetafactory:(Ljava/lang/invoke/MethodHandles$Lookup;Ljava/lang/String;Ljava/lang/invoke/MethodType;[Ljava/lang/Object;)Ljava/lang/invoke/CallSite;
    Method arguments:
      #35 (Ljava/lang/Object;)Ljava/lang/Object;
      #117 REF_invokeStatic org/scalatest/Canceled$.$anonfun$apply$9:(Ljava/lang/String;Lorg/scalatest/exceptions/StackDepthException;)Lscala/Some;
      #90 (Lorg/scalatest/exceptions/StackDepthException;)Lscala/Some;
      #42 5
      #43 1
      #90 (Lorg/scalatest/exceptions/StackDepthException;)Lscala/Some;
  4: #50 REF_invokeStatic java/lang/invoke/LambdaMetafactory.altMetafactory:(Ljava/lang/invoke/MethodHandles$Lookup;Ljava/lang/String;Ljava/lang/invoke/MethodType;[Ljava/lang/Object;)Ljava/lang/invoke/CallSite;
    Method arguments:
      #35 (Ljava/lang/Object;)Ljava/lang/Object;
      #155 REF_invokeStatic org/scalatest/Canceled$.$anonfun$apply$10:(Ljava/lang/String;Lorg/scalatest/exceptions/StackDepthException;)Lscala/Some;
      #90 (Lorg/scalatest/exceptions/StackDepthException;)Lscala/Some;
      #42 5
      #43 1
      #90 (Lorg/scalatest/exceptions/StackDepthException;)Lscala/Some;
  5: #50 REF_invokeStatic java/lang/invoke/LambdaMetafactory.altMetafactory:(Ljava/lang/invoke/MethodHandles$Lookup;Ljava/lang/String;Ljava/lang/invoke/MethodType;[Ljava/lang/Object;)Ljava/lang/invoke/CallSite;
    Method arguments:
      #35 (Ljava/lang/Object;)Ljava/lang/Object;
      #164 REF_invokeStatic org/scalatest/Canceled$.$anonfun$here$5:(Ljava/lang/Throwable;Lorg/scalatest/exceptions/StackDepthException;)Lscala/Some;
      #90 (Lorg/scalatest/exceptions/StackDepthException;)Lscala/Some;
      #42 5
      #43 1
      #90 (Lorg/scalatest/exceptions/StackDepthException;)Lscala/Some;
  6: #50 REF_invokeStatic java/lang/invoke/LambdaMetafactory.altMetafactory:(Ljava/lang/invoke/MethodHandles$Lookup;Ljava/lang/String;Ljava/lang/invoke/MethodType;[Ljava/lang/Object;)Ljava/lang/invoke/CallSite;
    Method arguments:
      #35 (Ljava/lang/Object;)Ljava/lang/Object;
      #171 REF_invokeStatic org/scalatest/Canceled$.$anonfun$here$6:(Lorg/scalatest/exceptions/StackDepthException;)Lscala/None$;
      #41 (Lorg/scalatest/exceptions/StackDepthException;)Lscala/None$;
      #42 5
      #43 1
      #41 (Lorg/scalatest/exceptions/StackDepthException;)Lscala/None$;
  7: #213 REF_invokeStatic scala/runtime/LambdaDeserialize.bootstrap:(Ljava/lang/invoke/MethodHandles$Lookup;Ljava/lang/String;Ljava/lang/invoke/MethodType;[Ljava/lang/invoke/MethodHandle;)Ljava/lang/invoke/CallSite;
    Method arguments:
      #155 REF_invokeStatic org/scalatest/Canceled$.$anonfun$apply$10:(Ljava/lang/String;Lorg/scalatest/exceptions/StackDepthException;)Lscala/Some;
      #40 REF_invokeStatic org/scalatest/Canceled$.$anonfun$apply$6:(Lorg/scalatest/exceptions/StackDepthException;)Lscala/None$;
      #88 REF_invokeStatic org/scalatest/Canceled$.$anonfun$apply$7:(Ljava/lang/String;Lorg/scalatest/exceptions/StackDepthException;)Lscala/Some;
      #112 REF_invokeStatic org/scalatest/Canceled$.$anonfun$apply$8:(Lorg/scalatest/exceptions/StackDepthException;)Lscala/None$;
      #117 REF_invokeStatic org/scalatest/Canceled$.$anonfun$apply$9:(Ljava/lang/String;Lorg/scalatest/exceptions/StackDepthException;)Lscala/Some;
      #164 REF_invokeStatic org/scalatest/Canceled$.$anonfun$here$5:(Ljava/lang/Throwable;Lorg/scalatest/exceptions/StackDepthException;)Lscala/Some;
      #171 REF_invokeStatic org/scalatest/Canceled$.$anonfun$here$6:(Lorg/scalatest/exceptions/StackDepthException;)Lscala/None$;
  ScalaInlineInfo: length = 0x54 (unknown attribute)
   01 01 00 10 00 98 00 55 01 00 24 00 25 01 00 54
   00 55 01 00 6D 00 25 01 00 72 00 55 01 00 A0 00
   A1 01 00 A8 00 25 01 00 16 00 15 01 00 1B 00 51
   01 00 1B 00 7C 01 00 1B 00 65 01 00 1B 00 1C 01
   00 1B 00 AD 01 00 9F 00 65 01 00 AF 00 B0 01 00
   B9 00 BA 01
  Scala: length = 0x0 (unknown attribute)

