Classfile /Users/mw/Projects/slang-braindump/.jar/jar11/assemble/slang-braindump/assemble/content/org/scalatest/CompileMacro$$treecreator2$11.class
  Last modified May 29, 2022; size 6416 bytes
  SHA-256 checksum e1a020ef2790727dff8d6de8fcf43324dfd341e8ce20f5de1932a4cfb7a3383d
  Compiled from "CompileMacro.scala"
public final class org.scalatest.CompileMacro$$treecreator2$11 extends scala.reflect.api.TreeCreator
  minor version: 0
  major version: 52
  flags: (0x0031) ACC_PUBLIC, ACC_FINAL, ACC_SUPER
  this_class: #2                          // org/scalatest/CompileMacro$$treecreator2$11
  super_class: #4                         // scala/reflect/api/TreeCreator
  interfaces: 0, fields: 2, methods: 2, attributes: 5
Constant pool:
    #1 = Utf8               org/scalatest/CompileMacro$$treecreator2$11
    #2 = Class              #1            // org/scalatest/CompileMacro$$treecreator2$11
    #3 = Utf8               scala/reflect/api/TreeCreator
    #4 = Class              #3            // scala/reflect/api/TreeCreator
    #5 = Utf8               CompileMacro.scala
    #6 = Utf8               org/scalatest/CompileMacro$
    #7 = Class              #6            // org/scalatest/CompileMacro$
    #8 = Utf8               checkCompile$1
    #9 = Utf8               (Ljava/lang/String;Lscala/reflect/macros/whitebox/Context;Lscala/reflect/api/Exprs$Expr;)Lscala/reflect/api/Exprs$Expr;
   #10 = NameAndType        #8:#9         // checkCompile$1:(Ljava/lang/String;Lscala/reflect/macros/whitebox/Context;Lscala/reflect/api/Exprs$Expr;)Lscala/reflect/api/Exprs$Expr;
   #11 = Utf8               $treecreator2$11
   #12 = Utf8               scala/reflect/api/Exprs$Expr
   #13 = Class              #12           // scala/reflect/api/Exprs$Expr
   #14 = Utf8               scala/reflect/api/Exprs
   #15 = Class              #14           // scala/reflect/api/Exprs
   #16 = Utf8               Expr
   #17 = Utf8               scala/reflect/api/Internals$InternalApi
   #18 = Class              #17           // scala/reflect/api/Internals$InternalApi
   #19 = Utf8               scala/reflect/api/Internals
   #20 = Class              #19           // scala/reflect/api/Internals
   #21 = Utf8               InternalApi
   #22 = Utf8               scala/reflect/api/Internals$ReificationSupportApi
   #23 = Class              #22           // scala/reflect/api/Internals$ReificationSupportApi
   #24 = Utf8               ReificationSupportApi
   #25 = Utf8               scala/reflect/api/Internals$ReificationSupportApi$FlagsReprExtractor
   #26 = Class              #25           // scala/reflect/api/Internals$ReificationSupportApi$FlagsReprExtractor
   #27 = Utf8               FlagsReprExtractor
   #28 = Utf8               scala/reflect/api/Names$NameApi
   #29 = Class              #28           // scala/reflect/api/Names$NameApi
   #30 = Utf8               scala/reflect/api/Names
   #31 = Class              #30           // scala/reflect/api/Names
   #32 = Utf8               NameApi
   #33 = Utf8               scala/reflect/api/Names$TermNameApi
   #34 = Class              #33           // scala/reflect/api/Names$TermNameApi
   #35 = Utf8               TermNameApi
   #36 = Utf8               scala/reflect/api/Names$TermNameExtractor
   #37 = Class              #36           // scala/reflect/api/Names$TermNameExtractor
   #38 = Utf8               TermNameExtractor
   #39 = Utf8               scala/reflect/api/Names$TypeNameApi
   #40 = Class              #39           // scala/reflect/api/Names$TypeNameApi
   #41 = Utf8               TypeNameApi
   #42 = Utf8               scala/reflect/api/Names$TypeNameExtractor
   #43 = Class              #42           // scala/reflect/api/Names$TypeNameExtractor
   #44 = Utf8               TypeNameExtractor
   #45 = Utf8               scala/reflect/api/Symbols$ClassSymbolApi
   #46 = Class              #45           // scala/reflect/api/Symbols$ClassSymbolApi
   #47 = Utf8               scala/reflect/api/Symbols
   #48 = Class              #47           // scala/reflect/api/Symbols
   #49 = Utf8               ClassSymbolApi
   #50 = Utf8               scala/reflect/api/Symbols$ModuleSymbolApi
   #51 = Class              #50           // scala/reflect/api/Symbols$ModuleSymbolApi
   #52 = Utf8               ModuleSymbolApi
   #53 = Utf8               scala/reflect/api/Symbols$SymbolApi
   #54 = Class              #53           // scala/reflect/api/Symbols$SymbolApi
   #55 = Utf8               SymbolApi
   #56 = Utf8               scala/reflect/api/Trees$ApplyApi
   #57 = Class              #56           // scala/reflect/api/Trees$ApplyApi
   #58 = Utf8               scala/reflect/api/Trees
   #59 = Class              #58           // scala/reflect/api/Trees
   #60 = Utf8               ApplyApi
   #61 = Utf8               scala/reflect/api/Trees$ApplyExtractor
   #62 = Class              #61           // scala/reflect/api/Trees$ApplyExtractor
   #63 = Utf8               ApplyExtractor
   #64 = Utf8               scala/reflect/api/Trees$FunctionApi
   #65 = Class              #64           // scala/reflect/api/Trees$FunctionApi
   #66 = Utf8               FunctionApi
   #67 = Utf8               scala/reflect/api/Trees$FunctionExtractor
   #68 = Class              #67           // scala/reflect/api/Trees$FunctionExtractor
   #69 = Utf8               FunctionExtractor
   #70 = Utf8               scala/reflect/api/Trees$IdentApi
   #71 = Class              #70           // scala/reflect/api/Trees$IdentApi
   #72 = Utf8               IdentApi
   #73 = Utf8               scala/reflect/api/Trees$ModifiersApi
   #74 = Class              #73           // scala/reflect/api/Trees$ModifiersApi
   #75 = Utf8               ModifiersApi
   #76 = Utf8               scala/reflect/api/Trees$ModifiersExtractor
   #77 = Class              #76           // scala/reflect/api/Trees$ModifiersExtractor
   #78 = Utf8               ModifiersExtractor
   #79 = Utf8               scala/reflect/api/Trees$NewApi
   #80 = Class              #79           // scala/reflect/api/Trees$NewApi
   #81 = Utf8               NewApi
   #82 = Utf8               scala/reflect/api/Trees$NewExtractor
   #83 = Class              #82           // scala/reflect/api/Trees$NewExtractor
   #84 = Utf8               NewExtractor
   #85 = Utf8               scala/reflect/api/Trees$SelectApi
   #86 = Class              #85           // scala/reflect/api/Trees$SelectApi
   #87 = Utf8               SelectApi
   #88 = Utf8               scala/reflect/api/Trees$SelectExtractor
   #89 = Class              #88           // scala/reflect/api/Trees$SelectExtractor
   #90 = Utf8               SelectExtractor
   #91 = Utf8               scala/reflect/api/Trees$ThrowApi
   #92 = Class              #91           // scala/reflect/api/Trees$ThrowApi
   #93 = Utf8               ThrowApi
   #94 = Utf8               scala/reflect/api/Trees$ThrowExtractor
   #95 = Class              #94           // scala/reflect/api/Trees$ThrowExtractor
   #96 = Utf8               ThrowExtractor
   #97 = Utf8               scala/reflect/api/Trees$TreeApi
   #98 = Class              #97           // scala/reflect/api/Trees$TreeApi
   #99 = Utf8               TreeApi
  #100 = Utf8               scala/reflect/api/Trees$ValDefApi
  #101 = Class              #100          // scala/reflect/api/Trees$ValDefApi
  #102 = Utf8               ValDefApi
  #103 = Utf8               scala/reflect/api/Trees$ValDefExtractor
  #104 = Class              #103          // scala/reflect/api/Trees$ValDefExtractor
  #105 = Utf8               ValDefExtractor
  #106 = Utf8               messageExpr$28
  #107 = Utf8               Lscala/reflect/api/Exprs$Expr;
  #108 = Utf8               pos$15$1
  #109 = Utf8               apply
  #110 = Utf8               (Lscala/reflect/api/Mirror;)Lscala/reflect/api/Trees$TreeApi;
  #111 = Utf8               <U:Lscala/reflect/api/Universe;:Ljava/lang/Object;>(Lscala/reflect/api/Mirror<TU;>;)Lscala/reflect/api/Trees$TreeApi;
  #112 = Utf8               $m$untyped
  #113 = Utf8               scala/reflect/api/Mirror
  #114 = Class              #113          // scala/reflect/api/Mirror
  #115 = Utf8               universe
  #116 = Utf8               ()Lscala/reflect/api/Universe;
  #117 = NameAndType        #115:#116     // universe:()Lscala/reflect/api/Universe;
  #118 = Methodref          #114.#117     // scala/reflect/api/Mirror.universe:()Lscala/reflect/api/Universe;
  #119 = Utf8               scala/reflect/api/Universe
  #120 = Class              #119          // scala/reflect/api/Universe
  #121 = Utf8               Throw
  #122 = Utf8               ()Lscala/reflect/api/Trees$ThrowExtractor;
  #123 = NameAndType        #121:#122     // Throw:()Lscala/reflect/api/Trees$ThrowExtractor;
  #124 = Methodref          #120.#123     // scala/reflect/api/Universe.Throw:()Lscala/reflect/api/Trees$ThrowExtractor;
  #125 = Utf8               Apply
  #126 = Utf8               ()Lscala/reflect/api/Trees$ApplyExtractor;
  #127 = NameAndType        #125:#126     // Apply:()Lscala/reflect/api/Trees$ApplyExtractor;
  #128 = Methodref          #120.#127     // scala/reflect/api/Universe.Apply:()Lscala/reflect/api/Trees$ApplyExtractor;
  #129 = Utf8               Select
  #130 = Utf8               ()Lscala/reflect/api/Trees$SelectExtractor;
  #131 = NameAndType        #129:#130     // Select:()Lscala/reflect/api/Trees$SelectExtractor;
  #132 = Methodref          #120.#131     // scala/reflect/api/Universe.Select:()Lscala/reflect/api/Trees$SelectExtractor;
  #133 = Utf8               New
  #134 = Utf8               ()Lscala/reflect/api/Trees$NewExtractor;
  #135 = NameAndType        #133:#134     // New:()Lscala/reflect/api/Trees$NewExtractor;
  #136 = Methodref          #120.#135     // scala/reflect/api/Universe.New:()Lscala/reflect/api/Trees$NewExtractor;
  #137 = Utf8               internal
  #138 = Utf8               ()Lscala/reflect/api/Internals$InternalApi;
  #139 = NameAndType        #137:#138     // internal:()Lscala/reflect/api/Internals$InternalApi;
  #140 = Methodref          #120.#139     // scala/reflect/api/Universe.internal:()Lscala/reflect/api/Internals$InternalApi;
  #141 = Utf8               reificationSupport
  #142 = Utf8               ()Lscala/reflect/api/Internals$ReificationSupportApi;
  #143 = NameAndType        #141:#142     // reificationSupport:()Lscala/reflect/api/Internals$ReificationSupportApi;
  #144 = InterfaceMethodref #18.#143      // scala/reflect/api/Internals$InternalApi.reificationSupport:()Lscala/reflect/api/Internals$ReificationSupportApi;
  #145 = Utf8               org.scalatest.exceptions.TestFailedException
  #146 = String             #145          // org.scalatest.exceptions.TestFailedException
  #147 = Utf8               staticClass
  #148 = Utf8               (Ljava/lang/String;)Lscala/reflect/api/Symbols$ClassSymbolApi;
  #149 = NameAndType        #147:#148     // staticClass:(Ljava/lang/String;)Lscala/reflect/api/Symbols$ClassSymbolApi;
  #150 = Methodref          #114.#149     // scala/reflect/api/Mirror.staticClass:(Ljava/lang/String;)Lscala/reflect/api/Symbols$ClassSymbolApi;
  #151 = Utf8               mkIdent
  #152 = Utf8               (Lscala/reflect/api/Symbols$SymbolApi;)Lscala/reflect/api/Trees$IdentApi;
  #153 = NameAndType        #151:#152     // mkIdent:(Lscala/reflect/api/Symbols$SymbolApi;)Lscala/reflect/api/Trees$IdentApi;
  #154 = InterfaceMethodref #23.#153      // scala/reflect/api/Internals$ReificationSupportApi.mkIdent:(Lscala/reflect/api/Symbols$SymbolApi;)Lscala/reflect/api/Trees$IdentApi;
  #155 = Utf8               (Lscala/reflect/api/Trees$TreeApi;)Lscala/reflect/api/Trees$NewApi;
  #156 = NameAndType        #109:#155     // apply:(Lscala/reflect/api/Trees$TreeApi;)Lscala/reflect/api/Trees$NewApi;
  #157 = Methodref          #83.#156      // scala/reflect/api/Trees$NewExtractor.apply:(Lscala/reflect/api/Trees$TreeApi;)Lscala/reflect/api/Trees$NewApi;
  #158 = Utf8               TermName
  #159 = Utf8               ()Lscala/reflect/api/Names$TermNameExtractor;
  #160 = NameAndType        #158:#159     // TermName:()Lscala/reflect/api/Names$TermNameExtractor;
  #161 = Methodref          #120.#160     // scala/reflect/api/Universe.TermName:()Lscala/reflect/api/Names$TermNameExtractor;
  #162 = Utf8               <init>
  #163 = String             #162          // <init>
  #164 = Utf8               (Ljava/lang/String;)Lscala/reflect/api/Names$TermNameApi;
  #165 = NameAndType        #109:#164     // apply:(Ljava/lang/String;)Lscala/reflect/api/Names$TermNameApi;
  #166 = Methodref          #37.#165      // scala/reflect/api/Names$TermNameExtractor.apply:(Ljava/lang/String;)Lscala/reflect/api/Names$TermNameApi;
  #167 = Utf8               (Lscala/reflect/api/Trees$TreeApi;Lscala/reflect/api/Names$NameApi;)Lscala/reflect/api/Trees$SelectApi;
  #168 = NameAndType        #109:#167     // apply:(Lscala/reflect/api/Trees$TreeApi;Lscala/reflect/api/Names$NameApi;)Lscala/reflect/api/Trees$SelectApi;
  #169 = Methodref          #89.#168      // scala/reflect/api/Trees$SelectExtractor.apply:(Lscala/reflect/api/Trees$TreeApi;Lscala/reflect/api/Names$NameApi;)Lscala/reflect/api/Trees$SelectApi;
  #170 = Utf8               scala/collection/immutable/$colon$colon
  #171 = Class              #170          // scala/collection/immutable/$colon$colon
  #172 = Utf8               Function
  #173 = Utf8               ()Lscala/reflect/api/Trees$FunctionExtractor;
  #174 = NameAndType        #172:#173     // Function:()Lscala/reflect/api/Trees$FunctionExtractor;
  #175 = Methodref          #120.#174     // scala/reflect/api/Universe.Function:()Lscala/reflect/api/Trees$FunctionExtractor;
  #176 = Utf8               ValDef
  #177 = Utf8               ()Lscala/reflect/api/Trees$ValDefExtractor;
  #178 = NameAndType        #176:#177     // ValDef:()Lscala/reflect/api/Trees$ValDefExtractor;
  #179 = Methodref          #120.#178     // scala/reflect/api/Universe.ValDef:()Lscala/reflect/api/Trees$ValDefExtractor;
  #180 = Utf8               Modifiers
  #181 = Utf8               ()Lscala/reflect/api/Trees$ModifiersExtractor;
  #182 = NameAndType        #180:#181     // Modifiers:()Lscala/reflect/api/Trees$ModifiersExtractor;
  #183 = Methodref          #120.#182     // scala/reflect/api/Universe.Modifiers:()Lscala/reflect/api/Trees$ModifiersExtractor;
  #184 = Utf8               FlagsRepr
  #185 = Utf8               ()Lscala/reflect/api/Internals$ReificationSupportApi$FlagsReprExtractor;
  #186 = NameAndType        #184:#185     // FlagsRepr:()Lscala/reflect/api/Internals$ReificationSupportApi$FlagsReprExtractor;
  #187 = InterfaceMethodref #23.#186      // scala/reflect/api/Internals$ReificationSupportApi.FlagsRepr:()Lscala/reflect/api/Internals$ReificationSupportApi$FlagsReprExtractor;
  #188 = Long               8192l
  #190 = Utf8               (J)Ljava/lang/Object;
  #191 = NameAndType        #109:#190     // apply:(J)Ljava/lang/Object;
  #192 = InterfaceMethodref #26.#191      // scala/reflect/api/Internals$ReificationSupportApi$FlagsReprExtractor.apply:(J)Ljava/lang/Object;
  #193 = Utf8               TypeName
  #194 = Utf8               ()Lscala/reflect/api/Names$TypeNameExtractor;
  #195 = NameAndType        #193:#194     // TypeName:()Lscala/reflect/api/Names$TypeNameExtractor;
  #196 = Methodref          #120.#195     // scala/reflect/api/Universe.TypeName:()Lscala/reflect/api/Names$TypeNameExtractor;
  #197 = Utf8
  #198 = String             #197          //
  #199 = Utf8               (Ljava/lang/String;)Lscala/reflect/api/Names$TypeNameApi;
  #200 = NameAndType        #109:#199     // apply:(Ljava/lang/String;)Lscala/reflect/api/Names$TypeNameApi;
  #201 = Methodref          #43.#200      // scala/reflect/api/Names$TypeNameExtractor.apply:(Ljava/lang/String;)Lscala/reflect/api/Names$TypeNameApi;
  #202 = Utf8               scala/collection/immutable/Nil$
  #203 = Class              #202          // scala/collection/immutable/Nil$
  #204 = Utf8               MODULE$
  #205 = Utf8               Lscala/collection/immutable/Nil$;
  #206 = NameAndType        #204:#205     // MODULE$:Lscala/collection/immutable/Nil$;
  #207 = Fieldref           #203.#206     // scala/collection/immutable/Nil$.MODULE$:Lscala/collection/immutable/Nil$;
  #208 = Utf8               (Ljava/lang/Object;Lscala/reflect/api/Names$NameApi;Lscala/collection/immutable/List;)Lscala/reflect/api/Trees$ModifiersApi;
  #209 = NameAndType        #109:#208     // apply:(Ljava/lang/Object;Lscala/reflect/api/Names$NameApi;Lscala/collection/immutable/List;)Lscala/reflect/api/Trees$ModifiersApi;
  #210 = Methodref          #77.#209      // scala/reflect/api/Trees$ModifiersExtractor.apply:(Ljava/lang/Object;Lscala/reflect/api/Names$NameApi;Lscala/collection/immutable/List;)Lscala/reflect/api/Trees$ModifiersApi;
  #211 = Utf8               x$9
  #212 = String             #211          // x$9
  #213 = Utf8               org.scalatest.exceptions.StackDepthException
  #214 = String             #213          // org.scalatest.exceptions.StackDepthException
  #215 = Utf8               EmptyTree
  #216 = Utf8               ()Lscala/reflect/api/Trees$TreeApi;
  #217 = NameAndType        #215:#216     // EmptyTree:()Lscala/reflect/api/Trees$TreeApi;
  #218 = Methodref          #120.#217     // scala/reflect/api/Universe.EmptyTree:()Lscala/reflect/api/Trees$TreeApi;
  #219 = Utf8               (Lscala/reflect/api/Trees$ModifiersApi;Lscala/reflect/api/Names$TermNameApi;Lscala/reflect/api/Trees$TreeApi;Lscala/reflect/api/Trees$TreeApi;)Lscala/reflect/api/Trees$ValDefApi;
  #220 = NameAndType        #109:#219     // apply:(Lscala/reflect/api/Trees$ModifiersApi;Lscala/reflect/api/Names$TermNameApi;Lscala/reflect/api/Trees$TreeApi;Lscala/reflect/api/Trees$TreeApi;)Lscala/reflect/api/Trees$ValDefApi;
  #221 = Methodref          #104.#220     // scala/reflect/api/Trees$ValDefExtractor.apply:(Lscala/reflect/api/Trees$ModifiersApi;Lscala/reflect/api/Names$TermNameApi;Lscala/reflect/api/Trees$TreeApi;Lscala/reflect/api/Trees$TreeApi;)Lscala/reflect/api/Trees$ValDefApi;
  #222 = Utf8               (Ljava/lang/Object;Lscala/collection/immutable/List;)V
  #223 = NameAndType        #162:#222     // "<init>":(Ljava/lang/Object;Lscala/collection/immutable/List;)V
  #224 = Methodref          #171.#223     // scala/collection/immutable/$colon$colon."<init>":(Ljava/lang/Object;Lscala/collection/immutable/List;)V
  #225 = Utf8               scala/collection/immutable/List
  #226 = Class              #225          // scala/collection/immutable/List
  #227 = Utf8               scala.Some
  #228 = String             #227          // scala.Some
  #229 = Utf8               staticModule
  #230 = Utf8               (Ljava/lang/String;)Lscala/reflect/api/Symbols$ModuleSymbolApi;
  #231 = NameAndType        #229:#230     // staticModule:(Ljava/lang/String;)Lscala/reflect/api/Symbols$ModuleSymbolApi;
  #232 = Methodref          #114.#231     // scala/reflect/api/Mirror.staticModule:(Ljava/lang/String;)Lscala/reflect/api/Symbols$ModuleSymbolApi;
  #233 = String             #109          // apply
  #234 = NameAndType        #106:#107     // messageExpr$28:Lscala/reflect/api/Exprs$Expr;
  #235 = Fieldref           #2.#234       // org/scalatest/CompileMacro$$treecreator2$11.messageExpr$28:Lscala/reflect/api/Exprs$Expr;
  #236 = Utf8               in
  #237 = Utf8               (Lscala/reflect/api/Mirror;)Lscala/reflect/api/Exprs$Expr;
  #238 = NameAndType        #236:#237     // in:(Lscala/reflect/api/Mirror;)Lscala/reflect/api/Exprs$Expr;
  #239 = InterfaceMethodref #13.#238      // scala/reflect/api/Exprs$Expr.in:(Lscala/reflect/api/Mirror;)Lscala/reflect/api/Exprs$Expr;
  #240 = Utf8               tree
  #241 = NameAndType        #240:#216     // tree:()Lscala/reflect/api/Trees$TreeApi;
  #242 = InterfaceMethodref #13.#241      // scala/reflect/api/Exprs$Expr.tree:()Lscala/reflect/api/Trees$TreeApi;
  #243 = Utf8               (Lscala/reflect/api/Trees$TreeApi;Lscala/collection/immutable/List;)Lscala/reflect/api/Trees$ApplyApi;
  #244 = NameAndType        #109:#243     // apply:(Lscala/reflect/api/Trees$TreeApi;Lscala/collection/immutable/List;)Lscala/reflect/api/Trees$ApplyApi;
  #245 = Methodref          #62.#244      // scala/reflect/api/Trees$ApplyExtractor.apply:(Lscala/reflect/api/Trees$TreeApi;Lscala/collection/immutable/List;)Lscala/reflect/api/Trees$ApplyApi;
  #246 = Utf8               (Lscala/collection/immutable/List;Lscala/reflect/api/Trees$TreeApi;)Lscala/reflect/api/Trees$FunctionApi;
  #247 = NameAndType        #109:#246     // apply:(Lscala/collection/immutable/List;Lscala/reflect/api/Trees$TreeApi;)Lscala/reflect/api/Trees$FunctionApi;
  #248 = Methodref          #68.#247      // scala/reflect/api/Trees$FunctionExtractor.apply:(Lscala/collection/immutable/List;Lscala/reflect/api/Trees$TreeApi;)Lscala/reflect/api/Trees$FunctionApi;
  #249 = Utf8               scala.None
  #250 = String             #249          // scala.None
  #251 = NameAndType        #108:#107     // pos$15$1:Lscala/reflect/api/Exprs$Expr;
  #252 = Fieldref           #2.#251       // org/scalatest/CompileMacro$$treecreator2$11.pos$15$1:Lscala/reflect/api/Exprs$Expr;
  #253 = Utf8               (Lscala/reflect/api/Trees$TreeApi;)Lscala/reflect/api/Trees$ThrowApi;
  #254 = NameAndType        #109:#253     // apply:(Lscala/reflect/api/Trees$TreeApi;)Lscala/reflect/api/Trees$ThrowApi;
  #255 = Methodref          #95.#254      // scala/reflect/api/Trees$ThrowExtractor.apply:(Lscala/reflect/api/Trees$TreeApi;)Lscala/reflect/api/Trees$ThrowApi;
  #256 = Utf8               $u
  #257 = Utf8               Lscala/reflect/api/Universe;
  #258 = Utf8               $m
  #259 = Utf8               Lscala/reflect/api/Mirror;
  #260 = Utf8               this
  #261 = Utf8               Lorg/scalatest/CompileMacro$$treecreator2$11;
  #262 = Utf8               (Lscala/reflect/api/Exprs$Expr;Lscala/reflect/api/Exprs$Expr;)V
  #263 = Utf8               ()V
  #264 = NameAndType        #162:#263     // "<init>":()V
  #265 = Methodref          #4.#264       // scala/reflect/api/TreeCreator."<init>":()V
  #266 = Utf8               Code
  #267 = Utf8               LineNumberTable
  #268 = Utf8               LocalVariableTable
  #269 = Utf8               Signature
  #270 = Utf8               MethodParameters
  #271 = Utf8               InnerClasses
  #272 = Utf8               EnclosingMethod
  #273 = Utf8               SourceFile
  #274 = Utf8               ScalaInlineInfo
  #275 = Utf8               Scala
{
  private final scala.reflect.api.Exprs$Expr messageExpr$28;
    descriptor: Lscala/reflect/api/Exprs$Expr;
    flags: (0x0012) ACC_PRIVATE, ACC_FINAL

  private final scala.reflect.api.Exprs$Expr pos$15$1;
    descriptor: Lscala/reflect/api/Exprs$Expr;
    flags: (0x0012) ACC_PRIVATE, ACC_FINAL

  public <U extends scala.reflect.api.Universe & java.lang.Object> scala.reflect.api.Trees$TreeApi apply(scala.reflect.api.Mirror<U>);
    descriptor: (Lscala/reflect/api/Mirror;)Lscala/reflect/api/Trees$TreeApi;
    flags: (0x0001) ACC_PUBLIC
    Code:
      stack=14, locals=4, args_size=2
         0: aload_1
         1: invokevirtual #118                // Method scala/reflect/api/Mirror.universe:()Lscala/reflect/api/Universe;
         4: astore_2
         5: aload_1
         6: astore_3
         7: aload_2
         8: invokevirtual #124                // Method scala/reflect/api/Universe.Throw:()Lscala/reflect/api/Trees$ThrowExtractor;
        11: aload_2
        12: invokevirtual #128                // Method scala/reflect/api/Universe.Apply:()Lscala/reflect/api/Trees$ApplyExtractor;
        15: aload_2
        16: invokevirtual #132                // Method scala/reflect/api/Universe.Select:()Lscala/reflect/api/Trees$SelectExtractor;
        19: aload_2
        20: invokevirtual #136                // Method scala/reflect/api/Universe.New:()Lscala/reflect/api/Trees$NewExtractor;
        23: aload_2
        24: invokevirtual #140                // Method scala/reflect/api/Universe.internal:()Lscala/reflect/api/Internals$InternalApi;
        27: invokeinterface #144,  1          // InterfaceMethod scala/reflect/api/Internals$InternalApi.reificationSupport:()Lscala/reflect/api/Internals$ReificationSupportApi;
        32: aload_3
        33: ldc           #146                // String org.scalatest.exceptions.TestFailedException
        35: invokevirtual #150                // Method scala/reflect/api/Mirror.staticClass:(Ljava/lang/String;)Lscala/reflect/api/Symbols$ClassSymbolApi;
        38: invokeinterface #154,  2          // InterfaceMethod scala/reflect/api/Internals$ReificationSupportApi.mkIdent:(Lscala/reflect/api/Symbols$SymbolApi;)Lscala/reflect/api/Trees$IdentApi;
        43: invokevirtual #157                // Method scala/reflect/api/Trees$NewExtractor.apply:(Lscala/reflect/api/Trees$TreeApi;)Lscala/reflect/api/Trees$NewApi;
        46: aload_2
        47: invokevirtual #161                // Method scala/reflect/api/Universe.TermName:()Lscala/reflect/api/Names$TermNameExtractor;
        50: ldc           #163                // String <init>
        52: invokevirtual #166                // Method scala/reflect/api/Names$TermNameExtractor.apply:(Ljava/lang/String;)Lscala/reflect/api/Names$TermNameApi;
        55: checkcast     #29                 // class scala/reflect/api/Names$NameApi
        58: invokevirtual #169                // Method scala/reflect/api/Trees$SelectExtractor.apply:(Lscala/reflect/api/Trees$TreeApi;Lscala/reflect/api/Names$NameApi;)Lscala/reflect/api/Trees$SelectApi;
        61: new           #171                // class scala/collection/immutable/$colon$colon
        64: dup
        65: aload_2
        66: invokevirtual #175                // Method scala/reflect/api/Universe.Function:()Lscala/reflect/api/Trees$FunctionExtractor;
        69: new           #171                // class scala/collection/immutable/$colon$colon
        72: dup
        73: aload_2
        74: invokevirtual #179                // Method scala/reflect/api/Universe.ValDef:()Lscala/reflect/api/Trees$ValDefExtractor;
        77: aload_2
        78: invokevirtual #183                // Method scala/reflect/api/Universe.Modifiers:()Lscala/reflect/api/Trees$ModifiersExtractor;
        81: aload_2
        82: invokevirtual #140                // Method scala/reflect/api/Universe.internal:()Lscala/reflect/api/Internals$InternalApi;
        85: invokeinterface #144,  1          // InterfaceMethod scala/reflect/api/Internals$InternalApi.reificationSupport:()Lscala/reflect/api/Internals$ReificationSupportApi;
        90: invokeinterface #187,  1          // InterfaceMethod scala/reflect/api/Internals$ReificationSupportApi.FlagsRepr:()Lscala/reflect/api/Internals$ReificationSupportApi$FlagsReprExtractor;
        95: ldc2_w        #188                // long 8192l
        98: invokeinterface #192,  3          // InterfaceMethod scala/reflect/api/Internals$ReificationSupportApi$FlagsReprExtractor.apply:(J)Ljava/lang/Object;
       103: aload_2
       104: invokevirtual #196                // Method scala/reflect/api/Universe.TypeName:()Lscala/reflect/api/Names$TypeNameExtractor;
       107: ldc           #198                // String
       109: invokevirtual #201                // Method scala/reflect/api/Names$TypeNameExtractor.apply:(Ljava/lang/String;)Lscala/reflect/api/Names$TypeNameApi;
       112: checkcast     #29                 // class scala/reflect/api/Names$NameApi
       115: getstatic     #207                // Field scala/collection/immutable/Nil$.MODULE$:Lscala/collection/immutable/Nil$;
       118: invokevirtual #210                // Method scala/reflect/api/Trees$ModifiersExtractor.apply:(Ljava/lang/Object;Lscala/reflect/api/Names$NameApi;Lscala/collection/immutable/List;)Lscala/reflect/api/Trees$ModifiersApi;
       121: aload_2
       122: invokevirtual #161                // Method scala/reflect/api/Universe.TermName:()Lscala/reflect/api/Names$TermNameExtractor;
       125: ldc           #212                // String x$9
       127: invokevirtual #166                // Method scala/reflect/api/Names$TermNameExtractor.apply:(Ljava/lang/String;)Lscala/reflect/api/Names$TermNameApi;
       130: aload_2
       131: invokevirtual #140                // Method scala/reflect/api/Universe.internal:()Lscala/reflect/api/Internals$InternalApi;
       134: invokeinterface #144,  1          // InterfaceMethod scala/reflect/api/Internals$InternalApi.reificationSupport:()Lscala/reflect/api/Internals$ReificationSupportApi;
       139: aload_3
       140: ldc           #214                // String org.scalatest.exceptions.StackDepthException
       142: invokevirtual #150                // Method scala/reflect/api/Mirror.staticClass:(Ljava/lang/String;)Lscala/reflect/api/Symbols$ClassSymbolApi;
       145: invokeinterface #154,  2          // InterfaceMethod scala/reflect/api/Internals$ReificationSupportApi.mkIdent:(Lscala/reflect/api/Symbols$SymbolApi;)Lscala/reflect/api/Trees$IdentApi;
       150: aload_2
       151: invokevirtual #218                // Method scala/reflect/api/Universe.EmptyTree:()Lscala/reflect/api/Trees$TreeApi;
       154: invokevirtual #221                // Method scala/reflect/api/Trees$ValDefExtractor.apply:(Lscala/reflect/api/Trees$ModifiersApi;Lscala/reflect/api/Names$TermNameApi;Lscala/reflect/api/Trees$TreeApi;Lscala/reflect/api/Trees$TreeApi;)Lscala/reflect/api/Trees$ValDefApi;
       157: getstatic     #207                // Field scala/collection/immutable/Nil$.MODULE$:Lscala/collection/immutable/Nil$;
       160: invokespecial #224                // Method scala/collection/immutable/$colon$colon."<init>":(Ljava/lang/Object;Lscala/collection/immutable/List;)V
       163: checkcast     #226                // class scala/collection/immutable/List
       166: aload_2
       167: invokevirtual #128                // Method scala/reflect/api/Universe.Apply:()Lscala/reflect/api/Trees$ApplyExtractor;
       170: aload_2
       171: invokevirtual #132                // Method scala/reflect/api/Universe.Select:()Lscala/reflect/api/Trees$SelectExtractor;
       174: aload_2
       175: invokevirtual #140                // Method scala/reflect/api/Universe.internal:()Lscala/reflect/api/Internals$InternalApi;
       178: invokeinterface #144,  1          // InterfaceMethod scala/reflect/api/Internals$InternalApi.reificationSupport:()Lscala/reflect/api/Internals$ReificationSupportApi;
       183: aload_3
       184: ldc           #228                // String scala.Some
       186: invokevirtual #232                // Method scala/reflect/api/Mirror.staticModule:(Ljava/lang/String;)Lscala/reflect/api/Symbols$ModuleSymbolApi;
       189: invokeinterface #154,  2          // InterfaceMethod scala/reflect/api/Internals$ReificationSupportApi.mkIdent:(Lscala/reflect/api/Symbols$SymbolApi;)Lscala/reflect/api/Trees$IdentApi;
       194: aload_2
       195: invokevirtual #161                // Method scala/reflect/api/Universe.TermName:()Lscala/reflect/api/Names$TermNameExtractor;
       198: ldc           #233                // String apply
       200: invokevirtual #166                // Method scala/reflect/api/Names$TermNameExtractor.apply:(Ljava/lang/String;)Lscala/reflect/api/Names$TermNameApi;
       203: checkcast     #29                 // class scala/reflect/api/Names$NameApi
       206: invokevirtual #169                // Method scala/reflect/api/Trees$SelectExtractor.apply:(Lscala/reflect/api/Trees$TreeApi;Lscala/reflect/api/Names$NameApi;)Lscala/reflect/api/Trees$SelectApi;
       209: new           #171                // class scala/collection/immutable/$colon$colon
       212: dup
       213: aload_0
       214: getfield      #235                // Field messageExpr$28:Lscala/reflect/api/Exprs$Expr;
       217: aload_3
       218: invokeinterface #239,  2          // InterfaceMethod scala/reflect/api/Exprs$Expr.in:(Lscala/reflect/api/Mirror;)Lscala/reflect/api/Exprs$Expr;
       223: invokeinterface #242,  1          // InterfaceMethod scala/reflect/api/Exprs$Expr.tree:()Lscala/reflect/api/Trees$TreeApi;
       228: getstatic     #207                // Field scala/collection/immutable/Nil$.MODULE$:Lscala/collection/immutable/Nil$;
       231: invokespecial #224                // Method scala/collection/immutable/$colon$colon."<init>":(Ljava/lang/Object;Lscala/collection/immutable/List;)V
       234: checkcast     #226                // class scala/collection/immutable/List
       237: invokevirtual #245                // Method scala/reflect/api/Trees$ApplyExtractor.apply:(Lscala/reflect/api/Trees$TreeApi;Lscala/collection/immutable/List;)Lscala/reflect/api/Trees$ApplyApi;
       240: invokevirtual #248                // Method scala/reflect/api/Trees$FunctionExtractor.apply:(Lscala/collection/immutable/List;Lscala/reflect/api/Trees$TreeApi;)Lscala/reflect/api/Trees$FunctionApi;
       243: new           #171                // class scala/collection/immutable/$colon$colon
       246: dup
       247: aload_2
       248: invokevirtual #140                // Method scala/reflect/api/Universe.internal:()Lscala/reflect/api/Internals$InternalApi;
       251: invokeinterface #144,  1          // InterfaceMethod scala/reflect/api/Internals$InternalApi.reificationSupport:()Lscala/reflect/api/Internals$ReificationSupportApi;
       256: aload_3
       257: ldc           #250                // String scala.None
       259: invokevirtual #232                // Method scala/reflect/api/Mirror.staticModule:(Ljava/lang/String;)Lscala/reflect/api/Symbols$ModuleSymbolApi;
       262: invokeinterface #154,  2          // InterfaceMethod scala/reflect/api/Internals$ReificationSupportApi.mkIdent:(Lscala/reflect/api/Symbols$SymbolApi;)Lscala/reflect/api/Trees$IdentApi;
       267: new           #171                // class scala/collection/immutable/$colon$colon
       270: dup
       271: aload_0
       272: getfield      #252                // Field pos$15$1:Lscala/reflect/api/Exprs$Expr;
       275: aload_3
       276: invokeinterface #239,  2          // InterfaceMethod scala/reflect/api/Exprs$Expr.in:(Lscala/reflect/api/Mirror;)Lscala/reflect/api/Exprs$Expr;
       281: invokeinterface #242,  1          // InterfaceMethod scala/reflect/api/Exprs$Expr.tree:()Lscala/reflect/api/Trees$TreeApi;
       286: getstatic     #207                // Field scala/collection/immutable/Nil$.MODULE$:Lscala/collection/immutable/Nil$;
       289: invokespecial #224                // Method scala/collection/immutable/$colon$colon."<init>":(Ljava/lang/Object;Lscala/collection/immutable/List;)V
       292: invokespecial #224                // Method scala/collection/immutable/$colon$colon."<init>":(Ljava/lang/Object;Lscala/collection/immutable/List;)V
       295: invokespecial #224                // Method scala/collection/immutable/$colon$colon."<init>":(Ljava/lang/Object;Lscala/collection/immutable/List;)V
       298: checkcast     #226                // class scala/collection/immutable/List
       301: invokevirtual #245                // Method scala/reflect/api/Trees$ApplyExtractor.apply:(Lscala/reflect/api/Trees$TreeApi;Lscala/collection/immutable/List;)Lscala/reflect/api/Trees$ApplyApi;
       304: invokevirtual #255                // Method scala/reflect/api/Trees$ThrowExtractor.apply:(Lscala/reflect/api/Trees$TreeApi;)Lscala/reflect/api/Trees$ThrowApi;
       307: areturn
      LineNumberTable:
        line 810: 0
        line 811: 213
        line 810: 217
        line 811: 271
        line 810: 275
      LocalVariableTable:
        Start  Length  Slot  Name   Signature
            5     302     2    $u   Lscala/reflect/api/Universe;
            7     300     3    $m   Lscala/reflect/api/Mirror;
            0     308     0  this   Lorg/scalatest/CompileMacro$$treecreator2$11;
            0     308     1 $m$untyped   Lscala/reflect/api/Mirror;
    Signature: #111                         // <U:Lscala/reflect/api/Universe;:Ljava/lang/Object;>(Lscala/reflect/api/Mirror<TU;>;)Lscala/reflect/api/Trees$TreeApi;
    MethodParameters:
      Name                           Flags
      $m$untyped                     final

  public org.scalatest.CompileMacro$$treecreator2$11(scala.reflect.api.Exprs$Expr, scala.reflect.api.Exprs$Expr);
    descriptor: (Lscala/reflect/api/Exprs$Expr;Lscala/reflect/api/Exprs$Expr;)V
    flags: (0x0001) ACC_PUBLIC
    Code:
      stack=2, locals=3, args_size=3
         0: aload_0
         1: aload_1
         2: putfield      #235                // Field messageExpr$28:Lscala/reflect/api/Exprs$Expr;
         5: aload_0
         6: aload_2
         7: putfield      #252                // Field pos$15$1:Lscala/reflect/api/Exprs$Expr;
        10: aload_0
        11: invokespecial #265                // Method scala/reflect/api/TreeCreator."<init>":()V
        14: return
      LineNumberTable:
        line 809: 0
        line 795: 5
        line 810: 10
      LocalVariableTable:
        Start  Length  Slot  Name   Signature
            0      15     0  this   Lorg/scalatest/CompileMacro$$treecreator2$11;
            0      15     1 messageExpr$28   Lscala/reflect/api/Exprs$Expr;
            0      15     2 pos$15$1   Lscala/reflect/api/Exprs$Expr;
    MethodParameters:
      Name                           Flags
      messageExpr$28                 final
      pos$15$1                       final
}
InnerClasses:
  public final #11= #2;                   // $treecreator2$11=class org/scalatest/CompileMacro$$treecreator2$11
  public #16= #13 of #15;                 // Expr=class scala/reflect/api/Exprs$Expr of class scala/reflect/api/Exprs
  public #21= #18 of #20;                 // InternalApi=class scala/reflect/api/Internals$InternalApi of class scala/reflect/api/Internals
  public #24= #23 of #20;                 // ReificationSupportApi=class scala/reflect/api/Internals$ReificationSupportApi of class scala/reflect/api/Internals
  public #27= #26 of #23;                 // FlagsReprExtractor=class scala/reflect/api/Internals$ReificationSupportApi$FlagsReprExtractor of class scala/reflect/api/Internals$ReificationSupportApi
  public abstract #32= #29 of #31;        // NameApi=class scala/reflect/api/Names$NameApi of class scala/reflect/api/Names
  public #35= #34 of #31;                 // TermNameApi=class scala/reflect/api/Names$TermNameApi of class scala/reflect/api/Names
  public abstract #38= #37 of #31;        // TermNameExtractor=class scala/reflect/api/Names$TermNameExtractor of class scala/reflect/api/Names
  public #41= #40 of #31;                 // TypeNameApi=class scala/reflect/api/Names$TypeNameApi of class scala/reflect/api/Names
  public abstract #44= #43 of #31;        // TypeNameExtractor=class scala/reflect/api/Names$TypeNameExtractor of class scala/reflect/api/Names
  public #49= #46 of #48;                 // ClassSymbolApi=class scala/reflect/api/Symbols$ClassSymbolApi of class scala/reflect/api/Symbols
  public #52= #51 of #48;                 // ModuleSymbolApi=class scala/reflect/api/Symbols$ModuleSymbolApi of class scala/reflect/api/Symbols
  public #55= #54 of #48;                 // SymbolApi=class scala/reflect/api/Symbols$SymbolApi of class scala/reflect/api/Symbols
  public #60= #57 of #59;                 // ApplyApi=class scala/reflect/api/Trees$ApplyApi of class scala/reflect/api/Trees
  public abstract #63= #62 of #59;        // ApplyExtractor=class scala/reflect/api/Trees$ApplyExtractor of class scala/reflect/api/Trees
  public #66= #65 of #59;                 // FunctionApi=class scala/reflect/api/Trees$FunctionApi of class scala/reflect/api/Trees
  public abstract #69= #68 of #59;        // FunctionExtractor=class scala/reflect/api/Trees$FunctionExtractor of class scala/reflect/api/Trees
  public #72= #71 of #59;                 // IdentApi=class scala/reflect/api/Trees$IdentApi of class scala/reflect/api/Trees
  public abstract #75= #74 of #59;        // ModifiersApi=class scala/reflect/api/Trees$ModifiersApi of class scala/reflect/api/Trees
  public abstract #78= #77 of #59;        // ModifiersExtractor=class scala/reflect/api/Trees$ModifiersExtractor of class scala/reflect/api/Trees
  public #81= #80 of #59;                 // NewApi=class scala/reflect/api/Trees$NewApi of class scala/reflect/api/Trees
  public abstract #84= #83 of #59;        // NewExtractor=class scala/reflect/api/Trees$NewExtractor of class scala/reflect/api/Trees
  public #87= #86 of #59;                 // SelectApi=class scala/reflect/api/Trees$SelectApi of class scala/reflect/api/Trees
  public abstract #90= #89 of #59;        // SelectExtractor=class scala/reflect/api/Trees$SelectExtractor of class scala/reflect/api/Trees
  public #93= #92 of #59;                 // ThrowApi=class scala/reflect/api/Trees$ThrowApi of class scala/reflect/api/Trees
  public abstract #96= #95 of #59;        // ThrowExtractor=class scala/reflect/api/Trees$ThrowExtractor of class scala/reflect/api/Trees
  public #99= #98 of #59;                 // TreeApi=class scala/reflect/api/Trees$TreeApi of class scala/reflect/api/Trees
  public #102= #101 of #59;               // ValDefApi=class scala/reflect/api/Trees$ValDefApi of class scala/reflect/api/Trees
  public abstract #105= #104 of #59;      // ValDefExtractor=class scala/reflect/api/Trees$ValDefExtractor of class scala/reflect/api/Trees
EnclosingMethod: #7.#10                 // org.scalatest.CompileMacro$.checkCompile$1
SourceFile: "CompileMacro.scala"
  ScalaInlineInfo: length = 0xE (unknown attribute)
   01 01 00 02 00 A2 01 06 01 00 6D 00 6E 01
  Scala: length = 0x0 (unknown attribute)

