Classfile /Users/mw/Projects/slang-braindump/.jar/jar11/assemble/slang-braindump/assemble/content/org/scalatest/CompositeStatus$.class
  Last modified May 29, 2022; size 7071 bytes
  SHA-256 checksum d63d6c430324a36c5982bd121fa063f5e95c99ba04fc652f76a78b4d80c9f9fb
  Compiled from "Status.scala"
public final class org.scalatest.CompositeStatus$ implements java.io.Serializable
  minor version: 0
  major version: 52
  flags: (0x0031) ACC_PUBLIC, ACC_FINAL, ACC_SUPER
  this_class: #2                          // org/scalatest/CompositeStatus$
  super_class: #4                         // java/lang/Object
  interfaces: 1, fields: 1, methods: 9, attributes: 5
Constant pool:
    #1 = Utf8               org/scalatest/CompositeStatus$
    #2 = Class              #1            // org/scalatest/CompositeStatus$
    #3 = Utf8               java/lang/Object
    #4 = Class              #3            // java/lang/Object
    #5 = Utf8               java/io/Serializable
    #6 = Class              #5            // java/io/Serializable
    #7 = Utf8               Status.scala
    #8 = Utf8               java/lang/invoke/MethodHandles$Lookup
    #9 = Class              #8            // java/lang/invoke/MethodHandles$Lookup
   #10 = Utf8               java/lang/invoke/MethodHandles
   #11 = Class              #10           // java/lang/invoke/MethodHandles
   #12 = Utf8               Lookup
   #13 = Utf8               org/scalatest/CompositeStatus$Bundle
   #14 = Class              #13           // org/scalatest/CompositeStatus$Bundle
   #15 = Utf8               org/scalatest/CompositeStatus
   #16 = Class              #15           // org/scalatest/CompositeStatus
   #17 = Utf8               Bundle
   #18 = Utf8               MODULE$
   #19 = Utf8               Lorg/scalatest/CompositeStatus$;
   #20 = Utf8               <clinit>
   #21 = Utf8               ()V
   #22 = Utf8               <init>
   #23 = NameAndType        #22:#21       // "<init>":()V
   #24 = Methodref          #2.#23        // org/scalatest/CompositeStatus$."<init>":()V
   #25 = NameAndType        #18:#19       // MODULE$:Lorg/scalatest/CompositeStatus$;
   #26 = Fieldref           #2.#25        // org/scalatest/CompositeStatus$.MODULE$:Lorg/scalatest/CompositeStatus$;
   #27 = Utf8               intializeBundle
   #28 = Utf8               (Lscala/collection/immutable/Set;Ljava/lang/Object;Lorg/scalatest/ConcurrentLinkedQueue;Lorg/scalatest/CountDownLatch;Ljava/util/concurrent/atomic/AtomicReference;)V
   #29 = Utf8               (Lscala/collection/immutable/Set<Lorg/scalatest/Status;>;Ljava/lang/Object;Lorg/scalatest/ConcurrentLinkedQueue<Lscala/Function1<Lscala/util/Try<Ljava/lang/Object;>;Lscala/runtime/BoxedUnit;>;>;Lorg/scalatest/CountDownLatch;Ljava/util/concurrent/atomic/AtomicReference<Lorg/scalatest/CompositeStatus$Bundle;>;)V
   #30 = Utf8               statuses
   #31 = Utf8               mutex
   #32 = Utf8               queue
   #33 = Utf8               latch
   #34 = Utf8               bundleRef
   #35 = Utf8               (Ljava/lang/Object;)Ljava/lang/Object;
   #36 = MethodType         #35           //  (Ljava/lang/Object;)Ljava/lang/Object;
   #37 = Utf8               $anonfun$intializeBundle$1$adapted
   #38 = Utf8               (Ljava/lang/Object;Ljava/util/concurrent/atomic/AtomicReference;Lorg/scalatest/CountDownLatch;Lorg/scalatest/ConcurrentLinkedQueue;Lorg/scalatest/Status;)Ljava/lang/Object;
   #39 = NameAndType        #37:#38       // $anonfun$intializeBundle$1$adapted:(Ljava/lang/Object;Ljava/util/concurrent/atomic/AtomicReference;Lorg/scalatest/CountDownLatch;Lorg/scalatest/ConcurrentLinkedQueue;Lorg/scalatest/Status;)Ljava/lang/Object;
   #40 = Methodref          #2.#39        // org/scalatest/CompositeStatus$.$anonfun$intializeBundle$1$adapted:(Ljava/lang/Object;Ljava/util/concurrent/atomic/AtomicReference;Lorg/scalatest/CountDownLatch;Lorg/scalatest/ConcurrentLinkedQueue;Lorg/scalatest/Status;)Ljava/lang/Object;
   #41 = MethodHandle       6:#40         // REF_invokeStatic org/scalatest/CompositeStatus$.$anonfun$intializeBundle$1$adapted:(Ljava/lang/Object;Ljava/util/concurrent/atomic/AtomicReference;Lorg/scalatest/CountDownLatch;Lorg/scalatest/ConcurrentLinkedQueue;Lorg/scalatest/Status;)Ljava/lang/Object;
   #42 = Utf8               (Lorg/scalatest/Status;)Ljava/lang/Object;
   #43 = MethodType         #42           //  (Lorg/scalatest/Status;)Ljava/lang/Object;
   #44 = Integer            5
   #45 = Integer            1
   #46 = Utf8               java/lang/invoke/LambdaMetafactory
   #47 = Class              #46           // java/lang/invoke/LambdaMetafactory
   #48 = Utf8               altMetafactory
   #49 = Utf8               (Ljava/lang/invoke/MethodHandles$Lookup;Ljava/lang/String;Ljava/lang/invoke/MethodType;[Ljava/lang/Object;)Ljava/lang/invoke/CallSite;
   #50 = NameAndType        #48:#49       // altMetafactory:(Ljava/lang/invoke/MethodHandles$Lookup;Ljava/lang/String;Ljava/lang/invoke/MethodType;[Ljava/lang/Object;)Ljava/lang/invoke/CallSite;
   #51 = Methodref          #47.#50       // java/lang/invoke/LambdaMetafactory.altMetafactory:(Ljava/lang/invoke/MethodHandles$Lookup;Ljava/lang/String;Ljava/lang/invoke/MethodType;[Ljava/lang/Object;)Ljava/lang/invoke/CallSite;
   #52 = MethodHandle       6:#51         // REF_invokeStatic java/lang/invoke/LambdaMetafactory.altMetafactory:(Ljava/lang/invoke/MethodHandles$Lookup;Ljava/lang/String;Ljava/lang/invoke/MethodType;[Ljava/lang/Object;)Ljava/lang/invoke/CallSite;
   #53 = Utf8               apply
   #54 = Utf8               (Ljava/lang/Object;Ljava/util/concurrent/atomic/AtomicReference;Lorg/scalatest/CountDownLatch;Lorg/scalatest/ConcurrentLinkedQueue;)Lscala/Function1;
   #55 = NameAndType        #53:#54       // apply:(Ljava/lang/Object;Ljava/util/concurrent/atomic/AtomicReference;Lorg/scalatest/CountDownLatch;Lorg/scalatest/ConcurrentLinkedQueue;)Lscala/Function1;
   #56 = InvokeDynamic      #0:#55        // #0:apply:(Ljava/lang/Object;Ljava/util/concurrent/atomic/AtomicReference;Lorg/scalatest/CountDownLatch;Lorg/scalatest/ConcurrentLinkedQueue;)Lscala/Function1;
   #57 = Utf8               scala/collection/immutable/Set
   #58 = Class              #57           // scala/collection/immutable/Set
   #59 = Utf8               foreach
   #60 = Utf8               (Lscala/Function1;)V
   #61 = NameAndType        #59:#60       // foreach:(Lscala/Function1;)V
   #62 = InterfaceMethodref #58.#61       // scala/collection/immutable/Set.foreach:(Lscala/Function1;)V
   #63 = Utf8               this
   #64 = Utf8               Lscala/collection/immutable/Set;
   #65 = Utf8               Ljava/lang/Object;
   #66 = Utf8               Lorg/scalatest/ConcurrentLinkedQueue;
   #67 = Utf8               Lorg/scalatest/CountDownLatch;
   #68 = Utf8               Ljava/util/concurrent/atomic/AtomicReference;
   #69 = Utf8               writeReplace
   #70 = Utf8               ()Ljava/lang/Object;
   #71 = Utf8               scala/runtime/ModuleSerializationProxy
   #72 = Class              #71           // scala/runtime/ModuleSerializationProxy
   #73 = Utf8               (Ljava/lang/Class;)V
   #74 = NameAndType        #22:#73       // "<init>":(Ljava/lang/Class;)V
   #75 = Methodref          #72.#74       // scala/runtime/ModuleSerializationProxy."<init>":(Ljava/lang/Class;)V
   #76 = Utf8               $anonfun$intializeBundle$2
   #77 = Utf8               (Ljava/lang/Object;Ljava/util/concurrent/atomic/AtomicReference;Lorg/scalatest/CountDownLatch;Lorg/scalatest/ConcurrentLinkedQueue;Lscala/util/Try;)V
   #78 = Utf8               mutex$1
   #79 = Utf8               bundleRef$1
   #80 = Utf8               latch$1
   #81 = Utf8               queue$1
   #82 = Utf8               tri
   #83 = Utf8               java/util/concurrent/atomic/AtomicReference
   #84 = Class              #83           // java/util/concurrent/atomic/AtomicReference
   #85 = Utf8               get
   #86 = NameAndType        #85:#70       // get:()Ljava/lang/Object;
   #87 = Methodref          #84.#86       // java/util/concurrent/atomic/AtomicReference.get:()Ljava/lang/Object;
   #88 = Utf8               scala/util/Success
   #89 = Class              #88           // scala/util/Success
   #90 = Utf8               value
   #91 = NameAndType        #90:#70       // value:()Ljava/lang/Object;
   #92 = Methodref          #89.#91       // scala/util/Success.value:()Ljava/lang/Object;
   #93 = Utf8               scala/runtime/BoxesRunTime
   #94 = Class              #93           // scala/runtime/BoxesRunTime
   #95 = Utf8               unboxToBoolean
   #96 = Utf8               (Ljava/lang/Object;)Z
   #97 = NameAndType        #95:#96       // unboxToBoolean:(Ljava/lang/Object;)Z
   #98 = Methodref          #94.#97       // scala/runtime/BoxesRunTime.unboxToBoolean:(Ljava/lang/Object;)Z
   #99 = Utf8               scala/Tuple2
  #100 = Class              #99           // scala/Tuple2
  #101 = Utf8               succeeded
  #102 = Utf8               ()Z
  #103 = NameAndType        #101:#102     // succeeded:()Z
  #104 = Methodref          #14.#103      // org/scalatest/CompositeStatus$Bundle.succeeded:()Z
  #105 = Utf8               boxToBoolean
  #106 = Utf8               (Z)Ljava/lang/Boolean;
  #107 = NameAndType        #105:#106     // boxToBoolean:(Z)Ljava/lang/Boolean;
  #108 = Methodref          #94.#107      // scala/runtime/BoxesRunTime.boxToBoolean:(Z)Ljava/lang/Boolean;
  #109 = Utf8               asyncException
  #110 = Utf8               ()Lscala/Option;
  #111 = NameAndType        #109:#110     // asyncException:()Lscala/Option;
  #112 = Methodref          #14.#111      // org/scalatest/CompositeStatus$Bundle.asyncException:()Lscala/Option;
  #113 = Utf8               (Ljava/lang/Object;Ljava/lang/Object;)V
  #114 = NameAndType        #22:#113      // "<init>":(Ljava/lang/Object;Ljava/lang/Object;)V
  #115 = Methodref          #100.#114     // scala/Tuple2."<init>":(Ljava/lang/Object;Ljava/lang/Object;)V
  #116 = Utf8               scala/util/Failure
  #117 = Class              #116          // scala/util/Failure
  #118 = Utf8               exception
  #119 = Utf8               ()Ljava/lang/Throwable;
  #120 = NameAndType        #118:#119     // exception:()Ljava/lang/Throwable;
  #121 = Methodref          #117.#120     // scala/util/Failure.exception:()Ljava/lang/Throwable;
  #122 = Utf8               scala/Option
  #123 = Class              #122          // scala/Option
  #124 = Utf8               isEmpty
  #125 = NameAndType        #124:#102     // isEmpty:()Z
  #126 = Methodref          #123.#125     // scala/Option.isEmpty:()Z
  #127 = Utf8               scala/Some
  #128 = Class              #127          // scala/Some
  #129 = Utf8               (Ljava/lang/Object;)V
  #130 = NameAndType        #22:#129      // "<init>":(Ljava/lang/Object;)V
  #131 = Methodref          #128.#130     // scala/Some."<init>":(Ljava/lang/Object;)V
  #132 = Utf8               scala/Predef$
  #133 = Class              #132          // scala/Predef$
  #134 = Utf8               Lscala/Predef$;
  #135 = NameAndType        #18:#134      // MODULE$:Lscala/Predef$;
  #136 = Fieldref           #133.#135     // scala/Predef$.MODULE$:Lscala/Predef$;
  #137 = Utf8               ScalaTest can\'t report this exception because another preceded it, so printing its stack trace:
  #138 = String             #137          // ScalaTest can\'t report this exception because another preceded it, so printing its stack trace:
  #139 = Utf8               println
  #140 = NameAndType        #139:#129     // println:(Ljava/lang/Object;)V
  #141 = Methodref          #133.#140     // scala/Predef$.println:(Ljava/lang/Object;)V
  #142 = Utf8               java/lang/Throwable
  #143 = Class              #142          // java/lang/Throwable
  #144 = Utf8               printStackTrace
  #145 = NameAndType        #144:#21      // printStackTrace:()V
  #146 = Methodref          #143.#145     // java/lang/Throwable.printStackTrace:()V
  #147 = Utf8               scala/MatchError
  #148 = Class              #147          // scala/MatchError
  #149 = Methodref          #148.#130     // scala/MatchError."<init>":(Ljava/lang/Object;)V
  #150 = Utf8               _1$mcZ$sp
  #151 = NameAndType        #150:#102     // _1$mcZ$sp:()Z
  #152 = Methodref          #100.#151     // scala/Tuple2._1$mcZ$sp:()Z
  #153 = Utf8               _2
  #154 = NameAndType        #153:#70      // _2:()Ljava/lang/Object;
  #155 = Methodref          #100.#154     // scala/Tuple2._2:()Ljava/lang/Object;
  #156 = Utf8               (ZLscala/Option;)V
  #157 = NameAndType        #22:#156      // "<init>":(ZLscala/Option;)V
  #158 = Methodref          #14.#157      // org/scalatest/CompositeStatus$Bundle."<init>":(ZLscala/Option;)V
  #159 = Utf8               set
  #160 = NameAndType        #159:#129     // set:(Ljava/lang/Object;)V
  #161 = Methodref          #84.#160      // java/util/concurrent/atomic/AtomicReference.set:(Ljava/lang/Object;)V
  #162 = Utf8               org/scalatest/CountDownLatch
  #163 = Class              #162          // org/scalatest/CountDownLatch
  #164 = Utf8               getCount
  #165 = Utf8               ()J
  #166 = NameAndType        #164:#165     // getCount:()J
  #167 = Methodref          #163.#166     // org/scalatest/CountDownLatch.getCount:()J
  #168 = Methodref          #128.#91      // scala/Some.value:()Ljava/lang/Object;
  #169 = Utf8               (Ljava/lang/Throwable;)V
  #170 = NameAndType        #22:#169      // "<init>":(Ljava/lang/Throwable;)V
  #171 = Methodref          #117.#170     // scala/util/Failure."<init>":(Ljava/lang/Throwable;)V
  #172 = Utf8               scala/None$
  #173 = Class              #172          // scala/None$
  #174 = Utf8               Lscala/None$;
  #175 = NameAndType        #18:#174      // MODULE$:Lscala/None$;
  #176 = Fieldref           #173.#175     // scala/None$.MODULE$:Lscala/None$;
  #177 = Utf8               equals
  #178 = NameAndType        #177:#96      // equals:(Ljava/lang/Object;)Z
  #179 = Methodref          #4.#178       // java/lang/Object.equals:(Ljava/lang/Object;)Z
  #180 = Methodref          #89.#130      // scala/util/Success."<init>":(Ljava/lang/Object;)V
  #181 = Utf8               org/scalatest/Status$
  #182 = Class              #181          // org/scalatest/Status$
  #183 = Utf8               Lorg/scalatest/Status$;
  #184 = NameAndType        #18:#183      // MODULE$:Lorg/scalatest/Status$;
  #185 = Fieldref           #182.#184     // org/scalatest/Status$.MODULE$:Lorg/scalatest/Status$;
  #186 = Utf8               executeQueue
  #187 = Utf8               (Lorg/scalatest/ConcurrentLinkedQueue;Lscala/util/Try;)V
  #188 = NameAndType        #186:#187     // executeQueue:(Lorg/scalatest/ConcurrentLinkedQueue;Lscala/util/Try;)V
  #189 = Methodref          #182.#188     // org/scalatest/Status$.executeQueue:(Lorg/scalatest/ConcurrentLinkedQueue;Lscala/util/Try;)V
  #190 = Utf8               countDown
  #191 = NameAndType        #190:#21      // countDown:()V
  #192 = Methodref          #163.#191     // org/scalatest/CountDownLatch.countDown:()V
  #193 = Utf8               res
  #194 = Utf8               Z
  #195 = Utf8               ex
  #196 = Utf8               Ljava/lang/Throwable;
  #197 = Utf8               newSucceeded
  #198 = Utf8               newAsyncException
  #199 = Utf8               Lscala/Option;
  #200 = Utf8               completionTri
  #201 = Utf8               Lscala/util/Try;
  #202 = Utf8               bundle
  #203 = Utf8               Lorg/scalatest/CompositeStatus$Bundle;
  #204 = Utf8               org/scalatest/ConcurrentLinkedQueue
  #205 = Class              #204          // org/scalatest/ConcurrentLinkedQueue
  #206 = Utf8               scala/util/Try
  #207 = Class              #206          // scala/util/Try
  #208 = Utf8               $anonfun$intializeBundle$1
  #209 = Utf8               (Ljava/lang/Object;Ljava/util/concurrent/atomic/AtomicReference;Lorg/scalatest/CountDownLatch;Lorg/scalatest/ConcurrentLinkedQueue;Lorg/scalatest/Status;)V
  #210 = Utf8               status
  #211 = Utf8               $anonfun$intializeBundle$2$adapted
  #212 = Utf8               (Ljava/lang/Object;Ljava/util/concurrent/atomic/AtomicReference;Lorg/scalatest/CountDownLatch;Lorg/scalatest/ConcurrentLinkedQueue;Lscala/util/Try;)Ljava/lang/Object;
  #213 = NameAndType        #211:#212     // $anonfun$intializeBundle$2$adapted:(Ljava/lang/Object;Ljava/util/concurrent/atomic/AtomicReference;Lorg/scalatest/CountDownLatch;Lorg/scalatest/ConcurrentLinkedQueue;Lscala/util/Try;)Ljava/lang/Object;
  #214 = Methodref          #2.#213       // org/scalatest/CompositeStatus$.$anonfun$intializeBundle$2$adapted:(Ljava/lang/Object;Ljava/util/concurrent/atomic/AtomicReference;Lorg/scalatest/CountDownLatch;Lorg/scalatest/ConcurrentLinkedQueue;Lscala/util/Try;)Ljava/lang/Object;
  #215 = MethodHandle       6:#214        // REF_invokeStatic org/scalatest/CompositeStatus$.$anonfun$intializeBundle$2$adapted:(Ljava/lang/Object;Ljava/util/concurrent/atomic/AtomicReference;Lorg/scalatest/CountDownLatch;Lorg/scalatest/ConcurrentLinkedQueue;Lscala/util/Try;)Ljava/lang/Object;
  #216 = Utf8               (Lscala/util/Try;)Ljava/lang/Object;
  #217 = MethodType         #216          //  (Lscala/util/Try;)Ljava/lang/Object;
  #218 = InvokeDynamic      #1:#55        // #1:apply:(Ljava/lang/Object;Ljava/util/concurrent/atomic/AtomicReference;Lorg/scalatest/CountDownLatch;Lorg/scalatest/ConcurrentLinkedQueue;)Lscala/Function1;
  #219 = Utf8               org/scalatest/Status
  #220 = Class              #219          // org/scalatest/Status
  #221 = Utf8               whenCompleted
  #222 = NameAndType        #221:#60      // whenCompleted:(Lscala/Function1;)V
  #223 = InterfaceMethodref #220.#222     // org/scalatest/Status.whenCompleted:(Lscala/Function1;)V
  #224 = Utf8               Lorg/scalatest/Status;
  #225 = Methodref          #4.#23        // java/lang/Object."<init>":()V
  #226 = NameAndType        #208:#209     // $anonfun$intializeBundle$1:(Ljava/lang/Object;Ljava/util/concurrent/atomic/AtomicReference;Lorg/scalatest/CountDownLatch;Lorg/scalatest/ConcurrentLinkedQueue;Lorg/scalatest/Status;)V
  #227 = Methodref          #2.#226       // org/scalatest/CompositeStatus$.$anonfun$intializeBundle$1:(Ljava/lang/Object;Ljava/util/concurrent/atomic/AtomicReference;Lorg/scalatest/CountDownLatch;Lorg/scalatest/ConcurrentLinkedQueue;Lorg/scalatest/Status;)V
  #228 = Utf8               scala/runtime/BoxedUnit
  #229 = Class              #228          // scala/runtime/BoxedUnit
  #230 = Utf8               UNIT
  #231 = Utf8               Lscala/runtime/BoxedUnit;
  #232 = NameAndType        #230:#231     // UNIT:Lscala/runtime/BoxedUnit;
  #233 = Fieldref           #229.#232     // scala/runtime/BoxedUnit.UNIT:Lscala/runtime/BoxedUnit;
  #234 = NameAndType        #76:#77       // $anonfun$intializeBundle$2:(Ljava/lang/Object;Ljava/util/concurrent/atomic/AtomicReference;Lorg/scalatest/CountDownLatch;Lorg/scalatest/ConcurrentLinkedQueue;Lscala/util/Try;)V
  #235 = Methodref          #2.#234       // org/scalatest/CompositeStatus$.$anonfun$intializeBundle$2:(Ljava/lang/Object;Ljava/util/concurrent/atomic/AtomicReference;Lorg/scalatest/CountDownLatch;Lorg/scalatest/ConcurrentLinkedQueue;Lscala/util/Try;)V
  #236 = Utf8               $deserializeLambda$
  #237 = Utf8               (Ljava/lang/invoke/SerializedLambda;)Ljava/lang/Object;
  #238 = Utf8               scala/runtime/LambdaDeserialize
  #239 = Class              #238          // scala/runtime/LambdaDeserialize
  #240 = Utf8               bootstrap
  #241 = Utf8               (Ljava/lang/invoke/MethodHandles$Lookup;Ljava/lang/String;Ljava/lang/invoke/MethodType;[Ljava/lang/invoke/MethodHandle;)Ljava/lang/invoke/CallSite;
  #242 = NameAndType        #240:#241     // bootstrap:(Ljava/lang/invoke/MethodHandles$Lookup;Ljava/lang/String;Ljava/lang/invoke/MethodType;[Ljava/lang/invoke/MethodHandle;)Ljava/lang/invoke/CallSite;
  #243 = Methodref          #239.#242     // scala/runtime/LambdaDeserialize.bootstrap:(Ljava/lang/invoke/MethodHandles$Lookup;Ljava/lang/String;Ljava/lang/invoke/MethodType;[Ljava/lang/invoke/MethodHandle;)Ljava/lang/invoke/CallSite;
  #244 = MethodHandle       6:#243        // REF_invokeStatic scala/runtime/LambdaDeserialize.bootstrap:(Ljava/lang/invoke/MethodHandles$Lookup;Ljava/lang/String;Ljava/lang/invoke/MethodType;[Ljava/lang/invoke/MethodHandle;)Ljava/lang/invoke/CallSite;
  #245 = Utf8               lambdaDeserialize
  #246 = NameAndType        #245:#237     // lambdaDeserialize:(Ljava/lang/invoke/SerializedLambda;)Ljava/lang/Object;
  #247 = InvokeDynamic      #2:#246       // #2:lambdaDeserialize:(Ljava/lang/invoke/SerializedLambda;)Ljava/lang/Object;
  #248 = Utf8               Code
  #249 = Utf8               LineNumberTable
  #250 = Utf8               LocalVariableTable
  #251 = Utf8               Signature
  #252 = Utf8               MethodParameters
  #253 = Utf8               StackMapTable
  #254 = Utf8               InnerClasses
  #255 = Utf8               SourceFile
  #256 = Utf8               BootstrapMethods
  #257 = Utf8               ScalaInlineInfo
  #258 = Utf8               Scala
{
  public static final org.scalatest.CompositeStatus$ MODULE$;
    descriptor: Lorg/scalatest/CompositeStatus$;
    flags: (0x0019) ACC_PUBLIC, ACC_STATIC, ACC_FINAL

  public static {};
    descriptor: ()V
    flags: (0x0009) ACC_PUBLIC, ACC_STATIC
    Code:
      stack=2, locals=0, args_size=0
         0: new           #2                  // class org/scalatest/CompositeStatus$
         3: dup
         4: invokespecial #24                 // Method "<init>":()V
         7: putstatic     #26                 // Field MODULE$:Lorg/scalatest/CompositeStatus$;
        10: return
      LineNumberTable:
        line 991: 0

  public void intializeBundle(scala.collection.immutable.Set<org.scalatest.Status>, java.lang.Object, org.scalatest.ConcurrentLinkedQueue<scala.Function1<scala.util.Try<java.lang.Object>, scala.runtime.BoxedUnit>>, org.scalatest.CountDownLatch, java.util.concurrent.atomic.AtomicReference<org.scalatest.CompositeStatus$Bundle>);
    descriptor: (Lscala/collection/immutable/Set;Ljava/lang/Object;Lorg/scalatest/ConcurrentLinkedQueue;Lorg/scalatest/CountDownLatch;Ljava/util/concurrent/atomic/AtomicReference;)V
    flags: (0x0001) ACC_PUBLIC
    Code:
      stack=5, locals=6, args_size=6
         0: aload_1
         1: aload_2
         2: aload         5
         4: aload         4
         6: aload_3
         7: invokedynamic #56,  0             // InvokeDynamic #0:apply:(Ljava/lang/Object;Ljava/util/concurrent/atomic/AtomicReference;Lorg/scalatest/CountDownLatch;Lorg/scalatest/ConcurrentLinkedQueue;)Lscala/Function1;
        12: invokeinterface #62,  2           // InterfaceMethod scala/collection/immutable/Set.foreach:(Lscala/Function1;)V
        17: return
      LineNumberTable:
        line 1011: 0
      LocalVariableTable:
        Start  Length  Slot  Name   Signature
            0      18     0  this   Lorg/scalatest/CompositeStatus$;
            0      18     1 statuses   Lscala/collection/immutable/Set;
            0      18     2 mutex   Ljava/lang/Object;
            0      18     3 queue   Lorg/scalatest/ConcurrentLinkedQueue;
            0      18     4 latch   Lorg/scalatest/CountDownLatch;
            0      18     5 bundleRef   Ljava/util/concurrent/atomic/AtomicReference;
    Signature: #29                          // (Lscala/collection/immutable/Set<Lorg/scalatest/Status;>;Ljava/lang/Object;Lorg/scalatest/ConcurrentLinkedQueue<Lscala/Function1<Lscala/util/Try<Ljava/lang/Object;>;Lscala/runtime/BoxedUnit;>;>;Lorg/scalatest/CountDownLatch;Ljava/util/concurrent/atomic/AtomicReference<Lorg/scalatest/CompositeStatus$Bundle;>;)V
    MethodParameters:
      Name                           Flags
      statuses                       final
      mutex                          final
      queue                          final
      latch                          final
      bundleRef                      final

  private java.lang.Object writeReplace();
    descriptor: ()Ljava/lang/Object;
    flags: (0x0002) ACC_PRIVATE
    Code:
      stack=3, locals=1, args_size=1
         0: new           #72                 // class scala/runtime/ModuleSerializationProxy
         3: dup
         4: ldc           #2                  // class org/scalatest/CompositeStatus$
         6: invokespecial #75                 // Method scala/runtime/ModuleSerializationProxy."<init>":(Ljava/lang/Class;)V
         9: areturn
      LineNumberTable:
        line 991: 0
      LocalVariableTable:
        Start  Length  Slot  Name   Signature
            0      10     0  this   Lorg/scalatest/CompositeStatus$;

  public static final void $anonfun$intializeBundle$2(java.lang.Object, java.util.concurrent.atomic.AtomicReference, org.scalatest.CountDownLatch, org.scalatest.ConcurrentLinkedQueue, scala.util.Try);
    descriptor: (Ljava/lang/Object;Ljava/util/concurrent/atomic/AtomicReference;Lorg/scalatest/CountDownLatch;Lorg/scalatest/ConcurrentLinkedQueue;Lscala/util/Try;)V
    flags: (0x1019) ACC_PUBLIC, ACC_STATIC, ACC_FINAL, ACC_SYNTHETIC
    Code:
      stack=6, locals=25, args_size=5
         0: aload_0
         1: dup
         2: astore        8
         4: monitorenter
         5: aload_1
         6: invokevirtual #87                 // Method java/util/concurrent/atomic/AtomicReference.get:()Ljava/lang/Object;
         9: checkcast     #14                 // class org/scalatest/CompositeStatus$Bundle
        12: astore        9
        14: aload         4
        16: astore        12
        18: aload         12
        20: instanceof    #89                 // class scala/util/Success
        23: ifeq          81
        26: aload         12
        28: checkcast     #89                 // class scala/util/Success
        31: astore        13
        33: aload         13
        35: invokevirtual #92                 // Method scala/util/Success.value:()Ljava/lang/Object;
        38: invokestatic  #98                 // Method scala/runtime/BoxesRunTime.unboxToBoolean:(Ljava/lang/Object;)Z
        41: istore        14
        43: new           #100                // class scala/Tuple2
        46: dup
        47: aload         9
        49: invokevirtual #104                // Method org/scalatest/CompositeStatus$Bundle.succeeded:()Z
        52: ifeq          64
        55: iload         14
        57: ifeq          64
        60: iconst_1
        61: goto          65
        64: iconst_0
        65: invokestatic  #108                // Method scala/runtime/BoxesRunTime.boxToBoolean:(Z)Ljava/lang/Boolean;
        68: aload         9
        70: invokevirtual #112                // Method org/scalatest/CompositeStatus$Bundle.asyncException:()Lscala/Option;
        73: invokespecial #115                // Method scala/Tuple2."<init>":(Ljava/lang/Object;Ljava/lang/Object;)V
        76: astore        7
        78: goto          187
        81: goto          84
        84: aload         12
        86: instanceof    #117                // class scala/util/Failure
        89: ifeq          174
        92: aload         12
        94: checkcast     #117                // class scala/util/Failure
        97: astore        15
        99: aload         15
       101: invokevirtual #121                // Method scala/util/Failure.exception:()Ljava/lang/Throwable;
       104: astore        16
       106: aload         9
       108: invokevirtual #112                // Method org/scalatest/CompositeStatus$Bundle.asyncException:()Lscala/Option;
       111: invokevirtual #126                // Method scala/Option.isEmpty:()Z
       114: ifeq          140
       117: new           #100                // class scala/Tuple2
       120: dup
       121: iconst_0
       122: invokestatic  #108                // Method scala/runtime/BoxesRunTime.boxToBoolean:(Z)Ljava/lang/Boolean;
       125: new           #128                // class scala/Some
       128: dup
       129: aload         16
       131: invokespecial #131                // Method scala/Some."<init>":(Ljava/lang/Object;)V
       134: invokespecial #115                // Method scala/Tuple2."<init>":(Ljava/lang/Object;Ljava/lang/Object;)V
       137: goto          169
       140: getstatic     #136                // Field scala/Predef$.MODULE$:Lscala/Predef$;
       143: ldc           #138                // String ScalaTest can\'t report this exception because another preceded it, so printing its stack trace:
       145: invokevirtual #141                // Method scala/Predef$.println:(Ljava/lang/Object;)V
       148: aload         16
       150: invokevirtual #146                // Method java/lang/Throwable.printStackTrace:()V
       153: new           #100                // class scala/Tuple2
       156: dup
       157: iconst_0
       158: invokestatic  #108                // Method scala/runtime/BoxesRunTime.boxToBoolean:(Z)Ljava/lang/Boolean;
       161: aload         9
       163: invokevirtual #112                // Method org/scalatest/CompositeStatus$Bundle.asyncException:()Lscala/Option;
       166: invokespecial #115                // Method scala/Tuple2."<init>":(Ljava/lang/Object;Ljava/lang/Object;)V
       169: astore        7
       171: goto          187
       174: goto          177
       177: new           #148                // class scala/MatchError
       180: dup
       181: aload         12
       183: invokespecial #149                // Method scala/MatchError."<init>":(Ljava/lang/Object;)V
       186: athrow
       187: aload         7
       189: astore        11
       191: aload         11
       193: ifnull        232
       196: aload         11
       198: invokevirtual #152                // Method scala/Tuple2._1$mcZ$sp:()Z
       201: istore        17
       203: aload         11
       205: invokevirtual #155                // Method scala/Tuple2._2:()Ljava/lang/Object;
       208: checkcast     #123                // class scala/Option
       211: astore        18
       213: new           #100                // class scala/Tuple2
       216: dup
       217: iload         17
       219: invokestatic  #108                // Method scala/runtime/BoxesRunTime.boxToBoolean:(Z)Ljava/lang/Boolean;
       222: aload         18
       224: invokespecial #115                // Method scala/Tuple2."<init>":(Ljava/lang/Object;Ljava/lang/Object;)V
       227: astore        6
       229: goto          245
       232: goto          235
       235: new           #148                // class scala/MatchError
       238: dup
       239: aload         11
       241: invokespecial #149                // Method scala/MatchError."<init>":(Ljava/lang/Object;)V
       244: athrow
       245: aload         6
       247: astore        10
       249: aload         10
       251: invokevirtual #152                // Method scala/Tuple2._1$mcZ$sp:()Z
       254: istore        19
       256: aload         10
       258: invokevirtual #155                // Method scala/Tuple2._2:()Ljava/lang/Object;
       261: checkcast     #123                // class scala/Option
       264: astore        20
       266: aload_1
       267: new           #14                 // class org/scalatest/CompositeStatus$Bundle
       270: dup
       271: iload         19
       273: aload         20
       275: invokespecial #158                // Method org/scalatest/CompositeStatus$Bundle."<init>":(ZLscala/Option;)V
       278: invokevirtual #161                // Method java/util/concurrent/atomic/AtomicReference.set:(Ljava/lang/Object;)V
       281: aload_2
       282: invokevirtual #167                // Method org/scalatest/CountDownLatch.getCount:()J
       285: lconst_1
       286: lcmp
       287: ifne          393
       290: aload         20
       292: astore        22
       294: aload         22
       296: instanceof    #128                // class scala/Some
       299: ifeq          333
       302: aload         22
       304: checkcast     #128                // class scala/Some
       307: astore        23
       309: aload         23
       311: invokevirtual #168                // Method scala/Some.value:()Ljava/lang/Object;
       314: checkcast     #143                // class java/lang/Throwable
       317: astore        24
       319: new           #117                // class scala/util/Failure
       322: dup
       323: aload         24
       325: invokespecial #171                // Method scala/util/Failure."<init>":(Ljava/lang/Throwable;)V
       328: astore        5
       330: goto          377
       333: goto          336
       336: getstatic     #176                // Field scala/None$.MODULE$:Lscala/None$;
       339: aload         22
       341: invokevirtual #179                // Method java/lang/Object.equals:(Ljava/lang/Object;)Z
       344: ifeq          364
       347: new           #89                 // class scala/util/Success
       350: dup
       351: iload         19
       353: invokestatic  #108                // Method scala/runtime/BoxesRunTime.boxToBoolean:(Z)Ljava/lang/Boolean;
       356: invokespecial #180                // Method scala/util/Success."<init>":(Ljava/lang/Object;)V
       359: astore        5
       361: goto          377
       364: goto          367
       367: new           #148                // class scala/MatchError
       370: dup
       371: aload         22
       373: invokespecial #149                // Method scala/MatchError."<init>":(Ljava/lang/Object;)V
       376: athrow
       377: aload         5
       379: astore        21
       381: getstatic     #185                // Field org/scalatest/Status$.MODULE$:Lorg/scalatest/Status$;
       384: aload_3
       385: aload         21
       387: invokevirtual #189                // Method org/scalatest/Status$.executeQueue:(Lorg/scalatest/ConcurrentLinkedQueue;Lscala/util/Try;)V
       390: goto          393
       393: aload_2
       394: invokevirtual #192                // Method org/scalatest/CountDownLatch.countDown:()V
       397: aload         8
       399: monitorexit
       400: goto          407
       403: aload         8
       405: monitorexit
       406: athrow
       407: return
      Exception table:
         from    to  target type
             5   397   403   any
      StackMapTable: number_of_entries = 20
        frame_type = 255 /* full_frame */
          offset_delta = 64
          locals = [ class java/lang/Object, class java/util/concurrent/atomic/AtomicReference, class org/scalatest/CountDownLatch, class org/scalatest/ConcurrentLinkedQueue, class scala/util/Try, top, top, top, class java/lang/Object, class org/scalatest/CompositeStatus$Bundle, top, top, class scala/util/Try, class scala/util/Success, int ]
          stack = [ uninitialized 43, uninitialized 43 ]
        frame_type = 255 /* full_frame */
          offset_delta = 0
          locals = [ class java/lang/Object, class java/util/concurrent/atomic/AtomicReference, class org/scalatest/CountDownLatch, class org/scalatest/ConcurrentLinkedQueue, class scala/util/Try, top, top, top, class java/lang/Object, class org/scalatest/CompositeStatus$Bundle, top, top, class scala/util/Try, class scala/util/Success, int ]
          stack = [ uninitialized 43, uninitialized 43, int ]
        frame_type = 249 /* chop */
          offset_delta = 15
        frame_type = 2 /* same */
        frame_type = 255 /* full_frame */
          offset_delta = 55
          locals = [ class java/lang/Object, class java/util/concurrent/atomic/AtomicReference, class org/scalatest/CountDownLatch, class org/scalatest/ConcurrentLinkedQueue, class scala/util/Try, top, top, top, class java/lang/Object, class org/scalatest/CompositeStatus$Bundle, top, top, class scala/util/Try, top, top, class scala/util/Failure, class java/lang/Throwable ]
          stack = []
        frame_type = 92 /* same_locals_1_stack_item */
          stack = [ class scala/Tuple2 ]
        frame_type = 255 /* full_frame */
          offset_delta = 4
          locals = [ class java/lang/Object, class java/util/concurrent/atomic/AtomicReference, class org/scalatest/CountDownLatch, class org/scalatest/ConcurrentLinkedQueue, class scala/util/Try, top, top, top, class java/lang/Object, class org/scalatest/CompositeStatus$Bundle, top, top, class scala/util/Try ]
          stack = []
        frame_type = 2 /* same */
        frame_type = 255 /* full_frame */
          offset_delta = 9
          locals = [ class java/lang/Object, class java/util/concurrent/atomic/AtomicReference, class org/scalatest/CountDownLatch, class org/scalatest/ConcurrentLinkedQueue, class scala/util/Try, top, top, class scala/Tuple2, class java/lang/Object, class org/scalatest/CompositeStatus$Bundle, top, top, class scala/util/Try ]
          stack = []
        frame_type = 255 /* full_frame */
          offset_delta = 44
          locals = [ class java/lang/Object, class java/util/concurrent/atomic/AtomicReference, class org/scalatest/CountDownLatch, class org/scalatest/ConcurrentLinkedQueue, class scala/util/Try, top, top, class scala/Tuple2, class java/lang/Object, class org/scalatest/CompositeStatus$Bundle, top, class scala/Tuple2, class scala/util/Try ]
          stack = []
        frame_type = 2 /* same */
        frame_type = 255 /* full_frame */
          offset_delta = 9
          locals = [ class java/lang/Object, class java/util/concurrent/atomic/AtomicReference, class org/scalatest/CountDownLatch, class org/scalatest/ConcurrentLinkedQueue, class scala/util/Try, top, class scala/Tuple2, class scala/Tuple2, class java/lang/Object, class org/scalatest/CompositeStatus$Bundle, top, class scala/Tuple2, class scala/util/Try, top, top, top, top, int, class scala/Option ]
          stack = []
        frame_type = 255 /* full_frame */
          offset_delta = 87
          locals = [ class java/lang/Object, class java/util/concurrent/atomic/AtomicReference, class org/scalatest/CountDownLatch, class org/scalatest/ConcurrentLinkedQueue, class scala/util/Try, top, class scala/Tuple2, class scala/Tuple2, class java/lang/Object, class org/scalatest/CompositeStatus$Bundle, class scala/Tuple2, class scala/Tuple2, class scala/util/Try, top, top, top, top, int, class scala/Option, int, class scala/Option, top, class scala/Option ]
          stack = []
        frame_type = 2 /* same */
        frame_type = 27 /* same */
        frame_type = 2 /* same */
        frame_type = 255 /* full_frame */
          offset_delta = 9
          locals = [ class java/lang/Object, class java/util/concurrent/atomic/AtomicReference, class org/scalatest/CountDownLatch, class org/scalatest/ConcurrentLinkedQueue, class scala/util/Try, class scala/util/Try, class scala/Tuple2, class scala/Tuple2, class java/lang/Object, class org/scalatest/CompositeStatus$Bundle, class scala/Tuple2, class scala/Tuple2, class scala/util/Try, top, top, top, top, int, class scala/Option, int, class scala/Option, top, class scala/Option ]
          stack = []
        frame_type = 255 /* full_frame */
          offset_delta = 15
          locals = [ class java/lang/Object, class java/util/concurrent/atomic/AtomicReference, class org/scalatest/CountDownLatch, class org/scalatest/ConcurrentLinkedQueue, class scala/util/Try, top, class scala/Tuple2, class scala/Tuple2, class java/lang/Object, class org/scalatest/CompositeStatus$Bundle, class scala/Tuple2, class scala/Tuple2, class scala/util/Try, top, top, top, top, int, class scala/Option, int, class scala/Option ]
          stack = []
        frame_type = 255 /* full_frame */
          offset_delta = 9
          locals = [ class java/lang/Object, class java/util/concurrent/atomic/AtomicReference, class org/scalatest/CountDownLatch, class org/scalatest/ConcurrentLinkedQueue, class scala/util/Try, top, top, top, class java/lang/Object ]
          stack = [ class java/lang/Throwable ]
        frame_type = 255 /* full_frame */
          offset_delta = 3
          locals = [ class java/lang/Object, class java/util/concurrent/atomic/AtomicReference, class org/scalatest/CountDownLatch, class org/scalatest/ConcurrentLinkedQueue, class scala/util/Try, top, class scala/Tuple2, class scala/Tuple2, class java/lang/Object, class org/scalatest/CompositeStatus$Bundle, class scala/Tuple2, class scala/Tuple2, class scala/util/Try, top, top, top, top, int, class scala/Option, int, class scala/Option ]
          stack = []
      LineNumberTable:
        line 1013: 0
        line 1014: 5
        line 1016: 14
        line 1017: 18
        line 1021: 43
        line 1017: 81
        line 1022: 84
        line 1025: 106
        line 1027: 117
        line 1031: 140
        line 1032: 148
        line 1033: 153
        line 1022: 174
        line 1016: 177
        line 1015: 191
        line 1016: 235
        line 1015: 249
        line 1036: 266
        line 1038: 281
        line 1045: 290
        line 1046: 294
        line 1047: 336
        line 1045: 367
        line 1057: 381
        line 1062: 393
        line 1013: 407
      LocalVariableTable:
        Start  Length  Slot  Name   Signature
           43      38    14   res   Z
          106      68    16    ex   Ljava/lang/Throwable;
          203      29    17 newSucceeded   Z
          213      19    18 newAsyncException   Lscala/Option;
          319      14    24    ex   Ljava/lang/Throwable;
          381       9    21 completionTri   Lscala/util/Try;
           14     383     9 bundle   Lorg/scalatest/CompositeStatus$Bundle;
          256     141    19 newSucceeded   Z
          266     131    20 newAsyncException   Lscala/Option;
            0     408     0 mutex$1   Ljava/lang/Object;
            0     408     1 bundleRef$1   Ljava/util/concurrent/atomic/AtomicReference;
            0     408     2 latch$1   Lorg/scalatest/CountDownLatch;
            0     408     3 queue$1   Lorg/scalatest/ConcurrentLinkedQueue;
            0     408     4   tri   Lscala/util/Try;
    MethodParameters:
      Name                           Flags
      mutex$1                        final
      bundleRef$1                    final
      latch$1                        final
      queue$1                        final
      tri                            final

  public static final void $anonfun$intializeBundle$1(java.lang.Object, java.util.concurrent.atomic.AtomicReference, org.scalatest.CountDownLatch, org.scalatest.ConcurrentLinkedQueue, org.scalatest.Status);
    descriptor: (Ljava/lang/Object;Ljava/util/concurrent/atomic/AtomicReference;Lorg/scalatest/CountDownLatch;Lorg/scalatest/ConcurrentLinkedQueue;Lorg/scalatest/Status;)V
    flags: (0x1019) ACC_PUBLIC, ACC_STATIC, ACC_FINAL, ACC_SYNTHETIC
    Code:
      stack=5, locals=5, args_size=5
         0: aload         4
         2: aload_0
         3: aload_1
         4: aload_2
         5: aload_3
         6: invokedynamic #218,  0            // InvokeDynamic #1:apply:(Ljava/lang/Object;Ljava/util/concurrent/atomic/AtomicReference;Lorg/scalatest/CountDownLatch;Lorg/scalatest/ConcurrentLinkedQueue;)Lscala/Function1;
        11: invokeinterface #223,  2          // InterfaceMethod org/scalatest/Status.whenCompleted:(Lscala/Function1;)V
        16: return
      LineNumberTable:
        line 1012: 0
      LocalVariableTable:
        Start  Length  Slot  Name   Signature
            0      17     0 mutex$1   Ljava/lang/Object;
            0      17     1 bundleRef$1   Ljava/util/concurrent/atomic/AtomicReference;
            0      17     2 latch$1   Lorg/scalatest/CountDownLatch;
            0      17     3 queue$1   Lorg/scalatest/ConcurrentLinkedQueue;
            0      17     4 status   Lorg/scalatest/Status;
    MethodParameters:
      Name                           Flags
      mutex$1                        final
      bundleRef$1                    final
      latch$1                        final
      queue$1                        final
      status                         final

  private org.scalatest.CompositeStatus$();
    descriptor: ()V
    flags: (0x0002) ACC_PRIVATE
    Code:
      stack=1, locals=1, args_size=1
         0: aload_0
         1: invokespecial #225                // Method java/lang/Object."<init>":()V
         4: return
      LineNumberTable:
        line 1068: 0
        line 991: 4
      LocalVariableTable:
        Start  Length  Slot  Name   Signature
            0       5     0  this   Lorg/scalatest/CompositeStatus$;

  public static final java.lang.Object $anonfun$intializeBundle$1$adapted(java.lang.Object, java.util.concurrent.atomic.AtomicReference, org.scalatest.CountDownLatch, org.scalatest.ConcurrentLinkedQueue, org.scalatest.Status);
    descriptor: (Ljava/lang/Object;Ljava/util/concurrent/atomic/AtomicReference;Lorg/scalatest/CountDownLatch;Lorg/scalatest/ConcurrentLinkedQueue;Lorg/scalatest/Status;)Ljava/lang/Object;
    flags: (0x1019) ACC_PUBLIC, ACC_STATIC, ACC_FINAL, ACC_SYNTHETIC
    Code:
      stack=5, locals=5, args_size=5
         0: aload_0
         1: aload_1
         2: aload_2
         3: aload_3
         4: aload         4
         6: invokestatic  #227                // Method $anonfun$intializeBundle$1:(Ljava/lang/Object;Ljava/util/concurrent/atomic/AtomicReference;Lorg/scalatest/CountDownLatch;Lorg/scalatest/ConcurrentLinkedQueue;Lorg/scalatest/Status;)V
         9: getstatic     #233                // Field scala/runtime/BoxedUnit.UNIT:Lscala/runtime/BoxedUnit;
        12: areturn
      LineNumberTable:
        line 1011: 0
      LocalVariableTable:
        Start  Length  Slot  Name   Signature
            0      13     0 mutex$1   Ljava/lang/Object;
            0      13     1 bundleRef$1   Ljava/util/concurrent/atomic/AtomicReference;
            0      13     2 latch$1   Lorg/scalatest/CountDownLatch;
            0      13     3 queue$1   Lorg/scalatest/ConcurrentLinkedQueue;
            0      13     4 status   Lorg/scalatest/Status;
    MethodParameters:
      Name                           Flags
      mutex$1                        final
      bundleRef$1                    final
      latch$1                        final
      queue$1                        final
      status                         final

  public static final java.lang.Object $anonfun$intializeBundle$2$adapted(java.lang.Object, java.util.concurrent.atomic.AtomicReference, org.scalatest.CountDownLatch, org.scalatest.ConcurrentLinkedQueue, scala.util.Try);
    descriptor: (Ljava/lang/Object;Ljava/util/concurrent/atomic/AtomicReference;Lorg/scalatest/CountDownLatch;Lorg/scalatest/ConcurrentLinkedQueue;Lscala/util/Try;)Ljava/lang/Object;
    flags: (0x1019) ACC_PUBLIC, ACC_STATIC, ACC_FINAL, ACC_SYNTHETIC
    Code:
      stack=5, locals=5, args_size=5
         0: aload_0
         1: aload_1
         2: aload_2
         3: aload_3
         4: aload         4
         6: invokestatic  #235                // Method $anonfun$intializeBundle$2:(Ljava/lang/Object;Ljava/util/concurrent/atomic/AtomicReference;Lorg/scalatest/CountDownLatch;Lorg/scalatest/ConcurrentLinkedQueue;Lscala/util/Try;)V
         9: getstatic     #233                // Field scala/runtime/BoxedUnit.UNIT:Lscala/runtime/BoxedUnit;
        12: areturn
      LineNumberTable:
        line 1012: 0
      LocalVariableTable:
        Start  Length  Slot  Name   Signature
            0      13     0 mutex$1   Ljava/lang/Object;
            0      13     1 bundleRef$1   Ljava/util/concurrent/atomic/AtomicReference;
            0      13     2 latch$1   Lorg/scalatest/CountDownLatch;
            0      13     3 queue$1   Lorg/scalatest/ConcurrentLinkedQueue;
            0      13     4   tri   Lscala/util/Try;
    MethodParameters:
      Name                           Flags
      mutex$1                        final
      bundleRef$1                    final
      latch$1                        final
      queue$1                        final
      tri                            final

  private static java.lang.Object $deserializeLambda$(java.lang.invoke.SerializedLambda);
    descriptor: (Ljava/lang/invoke/SerializedLambda;)Ljava/lang/Object;
    flags: (0x100a) ACC_PRIVATE, ACC_STATIC, ACC_SYNTHETIC
    Code:
      stack=1, locals=1, args_size=1
         0: aload_0
         1: invokedynamic #247,  0            // InvokeDynamic #2:lambdaDeserialize:(Ljava/lang/invoke/SerializedLambda;)Ljava/lang/Object;
         6: areturn
}
InnerClasses:
  public static final #12= #9 of #11;     // Lookup=class java/lang/invoke/MethodHandles$Lookup of class java/lang/invoke/MethodHandles
  public static #17= #14 of #16;          // Bundle=class org/scalatest/CompositeStatus$Bundle of class org/scalatest/CompositeStatus
SourceFile: "Status.scala"
BootstrapMethods:
  0: #52 REF_invokeStatic java/lang/invoke/LambdaMetafactory.altMetafactory:(Ljava/lang/invoke/MethodHandles$Lookup;Ljava/lang/String;Ljava/lang/invoke/MethodType;[Ljava/lang/Object;)Ljava/lang/invoke/CallSite;
    Method arguments:
      #36 (Ljava/lang/Object;)Ljava/lang/Object;
      #41 REF_invokeStatic org/scalatest/CompositeStatus$.$anonfun$intializeBundle$1$adapted:(Ljava/lang/Object;Ljava/util/concurrent/atomic/AtomicReference;Lorg/scalatest/CountDownLatch;Lorg/scalatest/ConcurrentLinkedQueue;Lorg/scalatest/Status;)Ljava/lang/Object;
      #43 (Lorg/scalatest/Status;)Ljava/lang/Object;
      #44 5
      #45 1
      #43 (Lorg/scalatest/Status;)Ljava/lang/Object;
  1: #52 REF_invokeStatic java/lang/invoke/LambdaMetafactory.altMetafactory:(Ljava/lang/invoke/MethodHandles$Lookup;Ljava/lang/String;Ljava/lang/invoke/MethodType;[Ljava/lang/Object;)Ljava/lang/invoke/CallSite;
    Method arguments:
      #36 (Ljava/lang/Object;)Ljava/lang/Object;
      #215 REF_invokeStatic org/scalatest/CompositeStatus$.$anonfun$intializeBundle$2$adapted:(Ljava/lang/Object;Ljava/util/concurrent/atomic/AtomicReference;Lorg/scalatest/CountDownLatch;Lorg/scalatest/ConcurrentLinkedQueue;Lscala/util/Try;)Ljava/lang/Object;
      #217 (Lscala/util/Try;)Ljava/lang/Object;
      #44 5
      #45 1
      #217 (Lscala/util/Try;)Ljava/lang/Object;
  2: #244 REF_invokeStatic scala/runtime/LambdaDeserialize.bootstrap:(Ljava/lang/invoke/MethodHandles$Lookup;Ljava/lang/String;Ljava/lang/invoke/MethodType;[Ljava/lang/invoke/MethodHandle;)Ljava/lang/invoke/CallSite;
    Method arguments:
      #41 REF_invokeStatic org/scalatest/CompositeStatus$.$anonfun$intializeBundle$1$adapted:(Ljava/lang/Object;Ljava/util/concurrent/atomic/AtomicReference;Lorg/scalatest/CountDownLatch;Lorg/scalatest/ConcurrentLinkedQueue;Lorg/scalatest/Status;)Ljava/lang/Object;
      #215 REF_invokeStatic org/scalatest/CompositeStatus$.$anonfun$intializeBundle$2$adapted:(Ljava/lang/Object;Ljava/util/concurrent/atomic/AtomicReference;Lorg/scalatest/CountDownLatch;Lorg/scalatest/ConcurrentLinkedQueue;Lscala/util/Try;)Ljava/lang/Object;
  ScalaInlineInfo: length = 0x27 (unknown attribute)
   01 01 00 07 00 D0 00 D1 01 00 25 00 26 01 00 4C
   00 4D 01 00 D3 00 D4 01 00 16 00 15 01 00 1B 00
   1C 01 00 45 00 46 01
  Scala: length = 0x0 (unknown attribute)

