Classfile /Users/mw/Projects/slang-braindump/.jar/jar11/assemble/slang-braindump/assemble/content/org/scalatest/CompileMacro$$treecreator1$2.class
  Last modified May 29, 2022; size 4599 bytes
  SHA-256 checksum 6e04dc87569f7ac39b2f9f8b12dc4f5a368e98642e2165a99214bf5993a179fe
  Compiled from "CompileMacro.scala"
public final class org.scalatest.CompileMacro$$treecreator1$2 extends scala.reflect.api.TreeCreator
  minor version: 0
  major version: 52
  flags: (0x0031) ACC_PUBLIC, ACC_FINAL, ACC_SUPER
  this_class: #2                          // org/scalatest/CompileMacro$$treecreator1$2
  super_class: #4                         // scala/reflect/api/TreeCreator
  interfaces: 0, fields: 2, methods: 2, attributes: 5
Constant pool:
    #1 = Utf8               org/scalatest/CompileMacro$$treecreator1$2
    #2 = Class              #1            // org/scalatest/CompileMacro$$treecreator1$2
    #3 = Utf8               scala/reflect/api/TreeCreator
    #4 = Class              #3            // scala/reflect/api/TreeCreator
    #5 = Utf8               CompileMacro.scala
    #6 = Utf8               org/scalatest/CompileMacro$
    #7 = Class              #6            // org/scalatest/CompileMacro$
    #8 = Utf8               expectTypeErrorImpl
    #9 = Utf8               (Lscala/reflect/macros/whitebox/Context;Lscala/reflect/api/Exprs$Expr;Lscala/reflect/api/Exprs$Expr;Lscala/reflect/api/Exprs$Expr;)Lscala/reflect/api/Exprs$Expr;
   #10 = NameAndType        #8:#9         // expectTypeErrorImpl:(Lscala/reflect/macros/whitebox/Context;Lscala/reflect/api/Exprs$Expr;Lscala/reflect/api/Exprs$Expr;Lscala/reflect/api/Exprs$Expr;)Lscala/reflect/api/Exprs$Expr;
   #11 = Utf8               $treecreator1$2
   #12 = Utf8               scala/reflect/api/Exprs$Expr
   #13 = Class              #12           // scala/reflect/api/Exprs$Expr
   #14 = Utf8               scala/reflect/api/Exprs
   #15 = Class              #14           // scala/reflect/api/Exprs
   #16 = Utf8               Expr
   #17 = Utf8               scala/reflect/api/Internals$InternalApi
   #18 = Class              #17           // scala/reflect/api/Internals$InternalApi
   #19 = Utf8               scala/reflect/api/Internals
   #20 = Class              #19           // scala/reflect/api/Internals
   #21 = Utf8               InternalApi
   #22 = Utf8               scala/reflect/api/Internals$ReificationSupportApi
   #23 = Class              #22           // scala/reflect/api/Internals$ReificationSupportApi
   #24 = Utf8               ReificationSupportApi
   #25 = Utf8               scala/reflect/api/Names$NameApi
   #26 = Class              #25           // scala/reflect/api/Names$NameApi
   #27 = Utf8               scala/reflect/api/Names
   #28 = Class              #27           // scala/reflect/api/Names
   #29 = Utf8               NameApi
   #30 = Utf8               scala/reflect/api/Names$TermNameApi
   #31 = Class              #30           // scala/reflect/api/Names$TermNameApi
   #32 = Utf8               TermNameApi
   #33 = Utf8               scala/reflect/api/Names$TermNameExtractor
   #34 = Class              #33           // scala/reflect/api/Names$TermNameExtractor
   #35 = Utf8               TermNameExtractor
   #36 = Utf8               scala/reflect/api/Symbols$ModuleSymbolApi
   #37 = Class              #36           // scala/reflect/api/Symbols$ModuleSymbolApi
   #38 = Utf8               scala/reflect/api/Symbols
   #39 = Class              #38           // scala/reflect/api/Symbols
   #40 = Utf8               ModuleSymbolApi
   #41 = Utf8               scala/reflect/api/Symbols$SymbolApi
   #42 = Class              #41           // scala/reflect/api/Symbols$SymbolApi
   #43 = Utf8               SymbolApi
   #44 = Utf8               scala/reflect/api/Trees$ApplyApi
   #45 = Class              #44           // scala/reflect/api/Trees$ApplyApi
   #46 = Utf8               scala/reflect/api/Trees
   #47 = Class              #46           // scala/reflect/api/Trees
   #48 = Utf8               ApplyApi
   #49 = Utf8               scala/reflect/api/Trees$ApplyExtractor
   #50 = Class              #49           // scala/reflect/api/Trees$ApplyExtractor
   #51 = Utf8               ApplyExtractor
   #52 = Utf8               scala/reflect/api/Trees$IdentApi
   #53 = Class              #52           // scala/reflect/api/Trees$IdentApi
   #54 = Utf8               IdentApi
   #55 = Utf8               scala/reflect/api/Trees$SelectApi
   #56 = Class              #55           // scala/reflect/api/Trees$SelectApi
   #57 = Utf8               SelectApi
   #58 = Utf8               scala/reflect/api/Trees$SelectExtractor
   #59 = Class              #58           // scala/reflect/api/Trees$SelectExtractor
   #60 = Utf8               SelectExtractor
   #61 = Utf8               scala/reflect/api/Trees$TreeApi
   #62 = Class              #61           // scala/reflect/api/Trees$TreeApi
   #63 = Utf8               TreeApi
   #64 = Utf8               messageExpr$3
   #65 = Utf8               Lscala/reflect/api/Exprs$Expr;
   #66 = Utf8               prettifier$1$1
   #67 = Utf8               apply
   #68 = Utf8               (Lscala/reflect/api/Mirror;)Lscala/reflect/api/Trees$TreeApi;
   #69 = Utf8               <U:Lscala/reflect/api/Universe;:Ljava/lang/Object;>(Lscala/reflect/api/Mirror<TU;>;)Lscala/reflect/api/Trees$TreeApi;
   #70 = Utf8               $m$untyped
   #71 = Utf8               scala/reflect/api/Mirror
   #72 = Class              #71           // scala/reflect/api/Mirror
   #73 = Utf8               universe
   #74 = Utf8               ()Lscala/reflect/api/Universe;
   #75 = NameAndType        #73:#74       // universe:()Lscala/reflect/api/Universe;
   #76 = Methodref          #72.#75       // scala/reflect/api/Mirror.universe:()Lscala/reflect/api/Universe;
   #77 = Utf8               scala/reflect/api/Universe
   #78 = Class              #77           // scala/reflect/api/Universe
   #79 = Utf8               Apply
   #80 = Utf8               ()Lscala/reflect/api/Trees$ApplyExtractor;
   #81 = NameAndType        #79:#80       // Apply:()Lscala/reflect/api/Trees$ApplyExtractor;
   #82 = Methodref          #78.#81       // scala/reflect/api/Universe.Apply:()Lscala/reflect/api/Trees$ApplyExtractor;
   #83 = Utf8               Select
   #84 = Utf8               ()Lscala/reflect/api/Trees$SelectExtractor;
   #85 = NameAndType        #83:#84       // Select:()Lscala/reflect/api/Trees$SelectExtractor;
   #86 = Methodref          #78.#85       // scala/reflect/api/Universe.Select:()Lscala/reflect/api/Trees$SelectExtractor;
   #87 = Utf8               internal
   #88 = Utf8               ()Lscala/reflect/api/Internals$InternalApi;
   #89 = NameAndType        #87:#88       // internal:()Lscala/reflect/api/Internals$InternalApi;
   #90 = Methodref          #78.#89       // scala/reflect/api/Universe.internal:()Lscala/reflect/api/Internals$InternalApi;
   #91 = Utf8               reificationSupport
   #92 = Utf8               ()Lscala/reflect/api/Internals$ReificationSupportApi;
   #93 = NameAndType        #91:#92       // reificationSupport:()Lscala/reflect/api/Internals$ReificationSupportApi;
   #94 = InterfaceMethodref #18.#93       // scala/reflect/api/Internals$InternalApi.reificationSupport:()Lscala/reflect/api/Internals$ReificationSupportApi;
   #95 = Utf8               org.scalatest.Fact
   #96 = String             #95           // org.scalatest.Fact
   #97 = Utf8               staticModule
   #98 = Utf8               (Ljava/lang/String;)Lscala/reflect/api/Symbols$ModuleSymbolApi;
   #99 = NameAndType        #97:#98       // staticModule:(Ljava/lang/String;)Lscala/reflect/api/Symbols$ModuleSymbolApi;
  #100 = Methodref          #72.#99       // scala/reflect/api/Mirror.staticModule:(Ljava/lang/String;)Lscala/reflect/api/Symbols$ModuleSymbolApi;
  #101 = Utf8               mkIdent
  #102 = Utf8               (Lscala/reflect/api/Symbols$SymbolApi;)Lscala/reflect/api/Trees$IdentApi;
  #103 = NameAndType        #101:#102     // mkIdent:(Lscala/reflect/api/Symbols$SymbolApi;)Lscala/reflect/api/Trees$IdentApi;
  #104 = InterfaceMethodref #23.#103      // scala/reflect/api/Internals$ReificationSupportApi.mkIdent:(Lscala/reflect/api/Symbols$SymbolApi;)Lscala/reflect/api/Trees$IdentApi;
  #105 = Utf8               TermName
  #106 = Utf8               ()Lscala/reflect/api/Names$TermNameExtractor;
  #107 = NameAndType        #105:#106     // TermName:()Lscala/reflect/api/Names$TermNameExtractor;
  #108 = Methodref          #78.#107      // scala/reflect/api/Universe.TermName:()Lscala/reflect/api/Names$TermNameExtractor;
  #109 = Utf8               No
  #110 = String             #109          // No
  #111 = Utf8               (Ljava/lang/String;)Lscala/reflect/api/Names$TermNameApi;
  #112 = NameAndType        #67:#111      // apply:(Ljava/lang/String;)Lscala/reflect/api/Names$TermNameApi;
  #113 = Methodref          #34.#112      // scala/reflect/api/Names$TermNameExtractor.apply:(Ljava/lang/String;)Lscala/reflect/api/Names$TermNameApi;
  #114 = Utf8               (Lscala/reflect/api/Trees$TreeApi;Lscala/reflect/api/Names$NameApi;)Lscala/reflect/api/Trees$SelectApi;
  #115 = NameAndType        #67:#114      // apply:(Lscala/reflect/api/Trees$TreeApi;Lscala/reflect/api/Names$NameApi;)Lscala/reflect/api/Trees$SelectApi;
  #116 = Methodref          #59.#115      // scala/reflect/api/Trees$SelectExtractor.apply:(Lscala/reflect/api/Trees$TreeApi;Lscala/reflect/api/Names$NameApi;)Lscala/reflect/api/Trees$SelectApi;
  #117 = String             #67           // apply
  #118 = Utf8               scala/collection/immutable/List$
  #119 = Class              #118          // scala/collection/immutable/List$
  #120 = Utf8               MODULE$
  #121 = Utf8               Lscala/collection/immutable/List$;
  #122 = NameAndType        #120:#121     // MODULE$:Lscala/collection/immutable/List$;
  #123 = Fieldref           #119.#122     // scala/collection/immutable/List$.MODULE$:Lscala/collection/immutable/List$;
  #124 = Utf8               scala/runtime/ScalaRunTime$
  #125 = Class              #124          // scala/runtime/ScalaRunTime$
  #126 = Utf8               Lscala/runtime/ScalaRunTime$;
  #127 = NameAndType        #120:#126     // MODULE$:Lscala/runtime/ScalaRunTime$;
  #128 = Fieldref           #125.#127     // scala/runtime/ScalaRunTime$.MODULE$:Lscala/runtime/ScalaRunTime$;
  #129 = NameAndType        #64:#65       // messageExpr$3:Lscala/reflect/api/Exprs$Expr;
  #130 = Fieldref           #2.#129       // org/scalatest/CompileMacro$$treecreator1$2.messageExpr$3:Lscala/reflect/api/Exprs$Expr;
  #131 = Utf8               in
  #132 = Utf8               (Lscala/reflect/api/Mirror;)Lscala/reflect/api/Exprs$Expr;
  #133 = NameAndType        #131:#132     // in:(Lscala/reflect/api/Mirror;)Lscala/reflect/api/Exprs$Expr;
  #134 = InterfaceMethodref #13.#133      // scala/reflect/api/Exprs$Expr.in:(Lscala/reflect/api/Mirror;)Lscala/reflect/api/Exprs$Expr;
  #135 = Utf8               tree
  #136 = Utf8               ()Lscala/reflect/api/Trees$TreeApi;
  #137 = NameAndType        #135:#136     // tree:()Lscala/reflect/api/Trees$TreeApi;
  #138 = InterfaceMethodref #13.#137      // scala/reflect/api/Exprs$Expr.tree:()Lscala/reflect/api/Trees$TreeApi;
  #139 = Utf8               scala.package
  #140 = String             #139          // scala.package
  #141 = Utf8               Vector
  #142 = String             #141          // Vector
  #143 = Utf8               empty
  #144 = String             #143          // empty
  #145 = Utf8               [Ljava/lang/Object;
  #146 = Class              #145          // "[Ljava/lang/Object;"
  #147 = Utf8               wrapRefArray
  #148 = Utf8               ([Ljava/lang/Object;)Lscala/collection/immutable/ArraySeq;
  #149 = NameAndType        #147:#148     // wrapRefArray:([Ljava/lang/Object;)Lscala/collection/immutable/ArraySeq;
  #150 = Methodref          #125.#149     // scala/runtime/ScalaRunTime$.wrapRefArray:([Ljava/lang/Object;)Lscala/collection/immutable/ArraySeq;
  #151 = Utf8               (Lscala/collection/immutable/Seq;)Ljava/lang/Object;
  #152 = NameAndType        #67:#151      // apply:(Lscala/collection/immutable/Seq;)Ljava/lang/Object;
  #153 = Methodref          #119.#152     // scala/collection/immutable/List$.apply:(Lscala/collection/immutable/Seq;)Ljava/lang/Object;
  #154 = Utf8               scala/collection/immutable/List
  #155 = Class              #154          // scala/collection/immutable/List
  #156 = Utf8               (Lscala/reflect/api/Trees$TreeApi;Lscala/collection/immutable/List;)Lscala/reflect/api/Trees$ApplyApi;
  #157 = NameAndType        #67:#156      // apply:(Lscala/reflect/api/Trees$TreeApi;Lscala/collection/immutable/List;)Lscala/reflect/api/Trees$ApplyApi;
  #158 = Methodref          #50.#157      // scala/reflect/api/Trees$ApplyExtractor.apply:(Lscala/reflect/api/Trees$TreeApi;Lscala/collection/immutable/List;)Lscala/reflect/api/Trees$ApplyApi;
  #159 = Utf8               scala/collection/immutable/$colon$colon
  #160 = Class              #159          // scala/collection/immutable/$colon$colon
  #161 = NameAndType        #66:#65       // prettifier$1$1:Lscala/reflect/api/Exprs$Expr;
  #162 = Fieldref           #2.#161       // org/scalatest/CompileMacro$$treecreator1$2.prettifier$1$1:Lscala/reflect/api/Exprs$Expr;
  #163 = Utf8               scala/collection/immutable/Nil$
  #164 = Class              #163          // scala/collection/immutable/Nil$
  #165 = Utf8               Lscala/collection/immutable/Nil$;
  #166 = NameAndType        #120:#165     // MODULE$:Lscala/collection/immutable/Nil$;
  #167 = Fieldref           #164.#166     // scala/collection/immutable/Nil$.MODULE$:Lscala/collection/immutable/Nil$;
  #168 = Utf8               <init>
  #169 = Utf8               (Ljava/lang/Object;Lscala/collection/immutable/List;)V
  #170 = NameAndType        #168:#169     // "<init>":(Ljava/lang/Object;Lscala/collection/immutable/List;)V
  #171 = Methodref          #160.#170     // scala/collection/immutable/$colon$colon."<init>":(Ljava/lang/Object;Lscala/collection/immutable/List;)V
  #172 = Utf8               $u
  #173 = Utf8               Lscala/reflect/api/Universe;
  #174 = Utf8               $m
  #175 = Utf8               Lscala/reflect/api/Mirror;
  #176 = Utf8               this
  #177 = Utf8               Lorg/scalatest/CompileMacro$$treecreator1$2;
  #178 = Utf8               (Lscala/reflect/api/Exprs$Expr;Lscala/reflect/api/Exprs$Expr;)V
  #179 = Utf8               ()V
  #180 = NameAndType        #168:#179     // "<init>":()V
  #181 = Methodref          #4.#180       // scala/reflect/api/TreeCreator."<init>":()V
  #182 = Utf8               Code
  #183 = Utf8               LineNumberTable
  #184 = Utf8               LocalVariableTable
  #185 = Utf8               Signature
  #186 = Utf8               MethodParameters
  #187 = Utf8               InnerClasses
  #188 = Utf8               EnclosingMethod
  #189 = Utf8               SourceFile
  #190 = Utf8               ScalaInlineInfo
  #191 = Utf8               Scala
{
  private final scala.reflect.api.Exprs$Expr messageExpr$3;
    descriptor: Lscala/reflect/api/Exprs$Expr;
    flags: (0x0012) ACC_PRIVATE, ACC_FINAL

  private final scala.reflect.api.Exprs$Expr prettifier$1$1;
    descriptor: Lscala/reflect/api/Exprs$Expr;
    flags: (0x0012) ACC_PRIVATE, ACC_FINAL

  public <U extends scala.reflect.api.Universe & java.lang.Object> scala.reflect.api.Trees$TreeApi apply(scala.reflect.api.Mirror<U>);
    descriptor: (Lscala/reflect/api/Mirror;)Lscala/reflect/api/Trees$TreeApi;
    flags: (0x0001) ACC_PUBLIC
    Code:
      stack=13, locals=4, args_size=2
         0: aload_1
         1: invokevirtual #76                 // Method scala/reflect/api/Mirror.universe:()Lscala/reflect/api/Universe;
         4: astore_2
         5: aload_1
         6: astore_3
         7: aload_2
         8: invokevirtual #82                 // Method scala/reflect/api/Universe.Apply:()Lscala/reflect/api/Trees$ApplyExtractor;
        11: aload_2
        12: invokevirtual #82                 // Method scala/reflect/api/Universe.Apply:()Lscala/reflect/api/Trees$ApplyExtractor;
        15: aload_2
        16: invokevirtual #86                 // Method scala/reflect/api/Universe.Select:()Lscala/reflect/api/Trees$SelectExtractor;
        19: aload_2
        20: invokevirtual #86                 // Method scala/reflect/api/Universe.Select:()Lscala/reflect/api/Trees$SelectExtractor;
        23: aload_2
        24: invokevirtual #90                 // Method scala/reflect/api/Universe.internal:()Lscala/reflect/api/Internals$InternalApi;
        27: invokeinterface #94,  1           // InterfaceMethod scala/reflect/api/Internals$InternalApi.reificationSupport:()Lscala/reflect/api/Internals$ReificationSupportApi;
        32: aload_3
        33: ldc           #96                 // String org.scalatest.Fact
        35: invokevirtual #100                // Method scala/reflect/api/Mirror.staticModule:(Ljava/lang/String;)Lscala/reflect/api/Symbols$ModuleSymbolApi;
        38: invokeinterface #104,  2          // InterfaceMethod scala/reflect/api/Internals$ReificationSupportApi.mkIdent:(Lscala/reflect/api/Symbols$SymbolApi;)Lscala/reflect/api/Trees$IdentApi;
        43: aload_2
        44: invokevirtual #108                // Method scala/reflect/api/Universe.TermName:()Lscala/reflect/api/Names$TermNameExtractor;
        47: ldc           #110                // String No
        49: invokevirtual #113                // Method scala/reflect/api/Names$TermNameExtractor.apply:(Ljava/lang/String;)Lscala/reflect/api/Names$TermNameApi;
        52: checkcast     #26                 // class scala/reflect/api/Names$NameApi
        55: invokevirtual #116                // Method scala/reflect/api/Trees$SelectExtractor.apply:(Lscala/reflect/api/Trees$TreeApi;Lscala/reflect/api/Names$NameApi;)Lscala/reflect/api/Trees$SelectApi;
        58: aload_2
        59: invokevirtual #108                // Method scala/reflect/api/Universe.TermName:()Lscala/reflect/api/Names$TermNameExtractor;
        62: ldc           #117                // String apply
        64: invokevirtual #113                // Method scala/reflect/api/Names$TermNameExtractor.apply:(Ljava/lang/String;)Lscala/reflect/api/Names$TermNameApi;
        67: checkcast     #26                 // class scala/reflect/api/Names$NameApi
        70: invokevirtual #116                // Method scala/reflect/api/Trees$SelectExtractor.apply:(Lscala/reflect/api/Trees$TreeApi;Lscala/reflect/api/Names$NameApi;)Lscala/reflect/api/Trees$SelectApi;
        73: getstatic     #123                // Field scala/collection/immutable/List$.MODULE$:Lscala/collection/immutable/List$;
        76: getstatic     #128                // Field scala/runtime/ScalaRunTime$.MODULE$:Lscala/runtime/ScalaRunTime$;
        79: bipush        8
        81: anewarray     #62                 // class scala/reflect/api/Trees$TreeApi
        84: dup
        85: iconst_0
        86: aload_0
        87: getfield      #130                // Field messageExpr$3:Lscala/reflect/api/Exprs$Expr;
        90: aload_3
        91: invokeinterface #134,  2          // InterfaceMethod scala/reflect/api/Exprs$Expr.in:(Lscala/reflect/api/Mirror;)Lscala/reflect/api/Exprs$Expr;
        96: invokeinterface #138,  1          // InterfaceMethod scala/reflect/api/Exprs$Expr.tree:()Lscala/reflect/api/Trees$TreeApi;
       101: aastore
       102: dup
       103: iconst_1
       104: aload_0
       105: getfield      #130                // Field messageExpr$3:Lscala/reflect/api/Exprs$Expr;
       108: aload_3
       109: invokeinterface #134,  2          // InterfaceMethod scala/reflect/api/Exprs$Expr.in:(Lscala/reflect/api/Mirror;)Lscala/reflect/api/Exprs$Expr;
       114: invokeinterface #138,  1          // InterfaceMethod scala/reflect/api/Exprs$Expr.tree:()Lscala/reflect/api/Trees$TreeApi;
       119: aastore
       120: dup
       121: iconst_2
       122: aload_0
       123: getfield      #130                // Field messageExpr$3:Lscala/reflect/api/Exprs$Expr;
       126: aload_3
       127: invokeinterface #134,  2          // InterfaceMethod scala/reflect/api/Exprs$Expr.in:(Lscala/reflect/api/Mirror;)Lscala/reflect/api/Exprs$Expr;
       132: invokeinterface #138,  1          // InterfaceMethod scala/reflect/api/Exprs$Expr.tree:()Lscala/reflect/api/Trees$TreeApi;
       137: aastore
       138: dup
       139: iconst_3
       140: aload_0
       141: getfield      #130                // Field messageExpr$3:Lscala/reflect/api/Exprs$Expr;
       144: aload_3
       145: invokeinterface #134,  2          // InterfaceMethod scala/reflect/api/Exprs$Expr.in:(Lscala/reflect/api/Mirror;)Lscala/reflect/api/Exprs$Expr;
       150: invokeinterface #138,  1          // InterfaceMethod scala/reflect/api/Exprs$Expr.tree:()Lscala/reflect/api/Trees$TreeApi;
       155: aastore
       156: dup
       157: iconst_4
       158: aload_2
       159: invokevirtual #86                 // Method scala/reflect/api/Universe.Select:()Lscala/reflect/api/Trees$SelectExtractor;
       162: aload_2
       163: invokevirtual #86                 // Method scala/reflect/api/Universe.Select:()Lscala/reflect/api/Trees$SelectExtractor;
       166: aload_2
       167: invokevirtual #90                 // Method scala/reflect/api/Universe.internal:()Lscala/reflect/api/Internals$InternalApi;
       170: invokeinterface #94,  1           // InterfaceMethod scala/reflect/api/Internals$InternalApi.reificationSupport:()Lscala/reflect/api/Internals$ReificationSupportApi;
       175: aload_3
       176: ldc           #140                // String scala.package
       178: invokevirtual #100                // Method scala/reflect/api/Mirror.staticModule:(Ljava/lang/String;)Lscala/reflect/api/Symbols$ModuleSymbolApi;
       181: invokeinterface #104,  2          // InterfaceMethod scala/reflect/api/Internals$ReificationSupportApi.mkIdent:(Lscala/reflect/api/Symbols$SymbolApi;)Lscala/reflect/api/Trees$IdentApi;
       186: aload_2
       187: invokevirtual #108                // Method scala/reflect/api/Universe.TermName:()Lscala/reflect/api/Names$TermNameExtractor;
       190: ldc           #142                // String Vector
       192: invokevirtual #113                // Method scala/reflect/api/Names$TermNameExtractor.apply:(Ljava/lang/String;)Lscala/reflect/api/Names$TermNameApi;
       195: checkcast     #26                 // class scala/reflect/api/Names$NameApi
       198: invokevirtual #116                // Method scala/reflect/api/Trees$SelectExtractor.apply:(Lscala/reflect/api/Trees$TreeApi;Lscala/reflect/api/Names$NameApi;)Lscala/reflect/api/Trees$SelectApi;
       201: aload_2
       202: invokevirtual #108                // Method scala/reflect/api/Universe.TermName:()Lscala/reflect/api/Names$TermNameExtractor;
       205: ldc           #144                // String empty
       207: invokevirtual #113                // Method scala/reflect/api/Names$TermNameExtractor.apply:(Ljava/lang/String;)Lscala/reflect/api/Names$TermNameApi;
       210: checkcast     #26                 // class scala/reflect/api/Names$NameApi
       213: invokevirtual #116                // Method scala/reflect/api/Trees$SelectExtractor.apply:(Lscala/reflect/api/Trees$TreeApi;Lscala/reflect/api/Names$NameApi;)Lscala/reflect/api/Trees$SelectApi;
       216: aastore
       217: dup
       218: iconst_5
       219: aload_2
       220: invokevirtual #86                 // Method scala/reflect/api/Universe.Select:()Lscala/reflect/api/Trees$SelectExtractor;
       223: aload_2
       224: invokevirtual #86                 // Method scala/reflect/api/Universe.Select:()Lscala/reflect/api/Trees$SelectExtractor;
       227: aload_2
       228: invokevirtual #90                 // Method scala/reflect/api/Universe.internal:()Lscala/reflect/api/Internals$InternalApi;
       231: invokeinterface #94,  1           // InterfaceMethod scala/reflect/api/Internals$InternalApi.reificationSupport:()Lscala/reflect/api/Internals$ReificationSupportApi;
       236: aload_3
       237: ldc           #140                // String scala.package
       239: invokevirtual #100                // Method scala/reflect/api/Mirror.staticModule:(Ljava/lang/String;)Lscala/reflect/api/Symbols$ModuleSymbolApi;
       242: invokeinterface #104,  2          // InterfaceMethod scala/reflect/api/Internals$ReificationSupportApi.mkIdent:(Lscala/reflect/api/Symbols$SymbolApi;)Lscala/reflect/api/Trees$IdentApi;
       247: aload_2
       248: invokevirtual #108                // Method scala/reflect/api/Universe.TermName:()Lscala/reflect/api/Names$TermNameExtractor;
       251: ldc           #142                // String Vector
       253: invokevirtual #113                // Method scala/reflect/api/Names$TermNameExtractor.apply:(Ljava/lang/String;)Lscala/reflect/api/Names$TermNameApi;
       256: checkcast     #26                 // class scala/reflect/api/Names$NameApi
       259: invokevirtual #116                // Method scala/reflect/api/Trees$SelectExtractor.apply:(Lscala/reflect/api/Trees$TreeApi;Lscala/reflect/api/Names$NameApi;)Lscala/reflect/api/Trees$SelectApi;
       262: aload_2
       263: invokevirtual #108                // Method scala/reflect/api/Universe.TermName:()Lscala/reflect/api/Names$TermNameExtractor;
       266: ldc           #144                // String empty
       268: invokevirtual #113                // Method scala/reflect/api/Names$TermNameExtractor.apply:(Ljava/lang/String;)Lscala/reflect/api/Names$TermNameApi;
       271: checkcast     #26                 // class scala/reflect/api/Names$NameApi
       274: invokevirtual #116                // Method scala/reflect/api/Trees$SelectExtractor.apply:(Lscala/reflect/api/Trees$TreeApi;Lscala/reflect/api/Names$NameApi;)Lscala/reflect/api/Trees$SelectApi;
       277: aastore
       278: dup
       279: bipush        6
       281: aload_2
       282: invokevirtual #86                 // Method scala/reflect/api/Universe.Select:()Lscala/reflect/api/Trees$SelectExtractor;
       285: aload_2
       286: invokevirtual #86                 // Method scala/reflect/api/Universe.Select:()Lscala/reflect/api/Trees$SelectExtractor;
       289: aload_2
       290: invokevirtual #90                 // Method scala/reflect/api/Universe.internal:()Lscala/reflect/api/Internals$InternalApi;
       293: invokeinterface #94,  1           // InterfaceMethod scala/reflect/api/Internals$InternalApi.reificationSupport:()Lscala/reflect/api/Internals$ReificationSupportApi;
       298: aload_3
       299: ldc           #140                // String scala.package
       301: invokevirtual #100                // Method scala/reflect/api/Mirror.staticModule:(Ljava/lang/String;)Lscala/reflect/api/Symbols$ModuleSymbolApi;
       304: invokeinterface #104,  2          // InterfaceMethod scala/reflect/api/Internals$ReificationSupportApi.mkIdent:(Lscala/reflect/api/Symbols$SymbolApi;)Lscala/reflect/api/Trees$IdentApi;
       309: aload_2
       310: invokevirtual #108                // Method scala/reflect/api/Universe.TermName:()Lscala/reflect/api/Names$TermNameExtractor;
       313: ldc           #142                // String Vector
       315: invokevirtual #113                // Method scala/reflect/api/Names$TermNameExtractor.apply:(Ljava/lang/String;)Lscala/reflect/api/Names$TermNameApi;
       318: checkcast     #26                 // class scala/reflect/api/Names$NameApi
       321: invokevirtual #116                // Method scala/reflect/api/Trees$SelectExtractor.apply:(Lscala/reflect/api/Trees$TreeApi;Lscala/reflect/api/Names$NameApi;)Lscala/reflect/api/Trees$SelectApi;
       324: aload_2
       325: invokevirtual #108                // Method scala/reflect/api/Universe.TermName:()Lscala/reflect/api/Names$TermNameExtractor;
       328: ldc           #144                // String empty
       330: invokevirtual #113                // Method scala/reflect/api/Names$TermNameExtractor.apply:(Ljava/lang/String;)Lscala/reflect/api/Names$TermNameApi;
       333: checkcast     #26                 // class scala/reflect/api/Names$NameApi
       336: invokevirtual #116                // Method scala/reflect/api/Trees$SelectExtractor.apply:(Lscala/reflect/api/Trees$TreeApi;Lscala/reflect/api/Names$NameApi;)Lscala/reflect/api/Trees$SelectApi;
       339: aastore
       340: dup
       341: bipush        7
       343: aload_2
       344: invokevirtual #86                 // Method scala/reflect/api/Universe.Select:()Lscala/reflect/api/Trees$SelectExtractor;
       347: aload_2
       348: invokevirtual #86                 // Method scala/reflect/api/Universe.Select:()Lscala/reflect/api/Trees$SelectExtractor;
       351: aload_2
       352: invokevirtual #90                 // Method scala/reflect/api/Universe.internal:()Lscala/reflect/api/Internals$InternalApi;
       355: invokeinterface #94,  1           // InterfaceMethod scala/reflect/api/Internals$InternalApi.reificationSupport:()Lscala/reflect/api/Internals$ReificationSupportApi;
       360: aload_3
       361: ldc           #140                // String scala.package
       363: invokevirtual #100                // Method scala/reflect/api/Mirror.staticModule:(Ljava/lang/String;)Lscala/reflect/api/Symbols$ModuleSymbolApi;
       366: invokeinterface #104,  2          // InterfaceMethod scala/reflect/api/Internals$ReificationSupportApi.mkIdent:(Lscala/reflect/api/Symbols$SymbolApi;)Lscala/reflect/api/Trees$IdentApi;
       371: aload_2
       372: invokevirtual #108                // Method scala/reflect/api/Universe.TermName:()Lscala/reflect/api/Names$TermNameExtractor;
       375: ldc           #142                // String Vector
       377: invokevirtual #113                // Method scala/reflect/api/Names$TermNameExtractor.apply:(Ljava/lang/String;)Lscala/reflect/api/Names$TermNameApi;
       380: checkcast     #26                 // class scala/reflect/api/Names$NameApi
       383: invokevirtual #116                // Method scala/reflect/api/Trees$SelectExtractor.apply:(Lscala/reflect/api/Trees$TreeApi;Lscala/reflect/api/Names$NameApi;)Lscala/reflect/api/Trees$SelectApi;
       386: aload_2
       387: invokevirtual #108                // Method scala/reflect/api/Universe.TermName:()Lscala/reflect/api/Names$TermNameExtractor;
       390: ldc           #144                // String empty
       392: invokevirtual #113                // Method scala/reflect/api/Names$TermNameExtractor.apply:(Ljava/lang/String;)Lscala/reflect/api/Names$TermNameApi;
       395: checkcast     #26                 // class scala/reflect/api/Names$NameApi
       398: invokevirtual #116                // Method scala/reflect/api/Trees$SelectExtractor.apply:(Lscala/reflect/api/Trees$TreeApi;Lscala/reflect/api/Names$NameApi;)Lscala/reflect/api/Trees$SelectApi;
       401: aastore
       402: checkcast     #146                // class "[Ljava/lang/Object;"
       405: invokevirtual #150                // Method scala/runtime/ScalaRunTime$.wrapRefArray:([Ljava/lang/Object;)Lscala/collection/immutable/ArraySeq;
       408: invokevirtual #153                // Method scala/collection/immutable/List$.apply:(Lscala/collection/immutable/Seq;)Ljava/lang/Object;
       411: checkcast     #155                // class scala/collection/immutable/List
       414: invokevirtual #158                // Method scala/reflect/api/Trees$ApplyExtractor.apply:(Lscala/reflect/api/Trees$TreeApi;Lscala/collection/immutable/List;)Lscala/reflect/api/Trees$ApplyApi;
       417: new           #160                // class scala/collection/immutable/$colon$colon
       420: dup
       421: aload_0
       422: getfield      #162                // Field prettifier$1$1:Lscala/reflect/api/Exprs$Expr;
       425: aload_3
       426: invokeinterface #134,  2          // InterfaceMethod scala/reflect/api/Exprs$Expr.in:(Lscala/reflect/api/Mirror;)Lscala/reflect/api/Exprs$Expr;
       431: invokeinterface #138,  1          // InterfaceMethod scala/reflect/api/Exprs$Expr.tree:()Lscala/reflect/api/Trees$TreeApi;
       436: getstatic     #167                // Field scala/collection/immutable/Nil$.MODULE$:Lscala/collection/immutable/Nil$;
       439: invokespecial #171                // Method scala/collection/immutable/$colon$colon."<init>":(Ljava/lang/Object;Lscala/collection/immutable/List;)V
       442: checkcast     #155                // class scala/collection/immutable/List
       445: invokevirtual #158                // Method scala/reflect/api/Trees$ApplyExtractor.apply:(Lscala/reflect/api/Trees$TreeApi;Lscala/collection/immutable/List;)Lscala/reflect/api/Trees$ApplyApi;
       448: areturn
      LineNumberTable:
        line 118: 0
        line 120: 86
        line 118: 90
        line 121: 104
        line 118: 108
        line 122: 122
        line 118: 126
        line 123: 140
        line 118: 144
        line 128: 421
        line 118: 425
      LocalVariableTable:
        Start  Length  Slot  Name   Signature
            5     443     2    $u   Lscala/reflect/api/Universe;
            7     441     3    $m   Lscala/reflect/api/Mirror;
            0     449     0  this   Lorg/scalatest/CompileMacro$$treecreator1$2;
            0     449     1 $m$untyped   Lscala/reflect/api/Mirror;
    Signature: #69                          // <U:Lscala/reflect/api/Universe;:Ljava/lang/Object;>(Lscala/reflect/api/Mirror<TU;>;)Lscala/reflect/api/Trees$TreeApi;
    MethodParameters:
      Name                           Flags
      $m$untyped                     final

  public org.scalatest.CompileMacro$$treecreator1$2(scala.reflect.api.Exprs$Expr, scala.reflect.api.Exprs$Expr);
    descriptor: (Lscala/reflect/api/Exprs$Expr;Lscala/reflect/api/Exprs$Expr;)V
    flags: (0x0001) ACC_PUBLIC
    Code:
      stack=2, locals=3, args_size=3
         0: aload_0
         1: aload_1
         2: putfield      #130                // Field messageExpr$3:Lscala/reflect/api/Exprs$Expr;
         5: aload_0
         6: aload_2
         7: putfield      #162                // Field prettifier$1$1:Lscala/reflect/api/Exprs$Expr;
        10: aload_0
        11: invokespecial #181                // Method scala/reflect/api/TreeCreator."<init>":()V
        14: return
      LineNumberTable:
        line 117: 0
        line 106: 5
        line 118: 10
      LocalVariableTable:
        Start  Length  Slot  Name   Signature
            0      15     0  this   Lorg/scalatest/CompileMacro$$treecreator1$2;
            0      15     1 messageExpr$3   Lscala/reflect/api/Exprs$Expr;
            0      15     2 prettifier$1$1   Lscala/reflect/api/Exprs$Expr;
    MethodParameters:
      Name                           Flags
      messageExpr$3                  final
      prettifier$1$1                 final
}
InnerClasses:
  public final #11= #2;                   // $treecreator1$2=class org/scalatest/CompileMacro$$treecreator1$2
  public #16= #13 of #15;                 // Expr=class scala/reflect/api/Exprs$Expr of class scala/reflect/api/Exprs
  public #21= #18 of #20;                 // InternalApi=class scala/reflect/api/Internals$InternalApi of class scala/reflect/api/Internals
  public #24= #23 of #20;                 // ReificationSupportApi=class scala/reflect/api/Internals$ReificationSupportApi of class scala/reflect/api/Internals
  public abstract #29= #26 of #28;        // NameApi=class scala/reflect/api/Names$NameApi of class scala/reflect/api/Names
  public #32= #31 of #28;                 // TermNameApi=class scala/reflect/api/Names$TermNameApi of class scala/reflect/api/Names
  public abstract #35= #34 of #28;        // TermNameExtractor=class scala/reflect/api/Names$TermNameExtractor of class scala/reflect/api/Names
  public #40= #37 of #39;                 // ModuleSymbolApi=class scala/reflect/api/Symbols$ModuleSymbolApi of class scala/reflect/api/Symbols
  public #43= #42 of #39;                 // SymbolApi=class scala/reflect/api/Symbols$SymbolApi of class scala/reflect/api/Symbols
  public #48= #45 of #47;                 // ApplyApi=class scala/reflect/api/Trees$ApplyApi of class scala/reflect/api/Trees
  public abstract #51= #50 of #47;        // ApplyExtractor=class scala/reflect/api/Trees$ApplyExtractor of class scala/reflect/api/Trees
  public #54= #53 of #47;                 // IdentApi=class scala/reflect/api/Trees$IdentApi of class scala/reflect/api/Trees
  public #57= #56 of #47;                 // SelectApi=class scala/reflect/api/Trees$SelectApi of class scala/reflect/api/Trees
  public abstract #60= #59 of #47;        // SelectExtractor=class scala/reflect/api/Trees$SelectExtractor of class scala/reflect/api/Trees
  public #63= #62 of #47;                 // TreeApi=class scala/reflect/api/Trees$TreeApi of class scala/reflect/api/Trees
EnclosingMethod: #7.#10                 // org.scalatest.CompileMacro$.expectTypeErrorImpl
SourceFile: "CompileMacro.scala"
  ScalaInlineInfo: length = 0xE (unknown attribute)
   01 01 00 02 00 A8 00 B2 01 00 43 00 44 01
  Scala: length = 0x0 (unknown attribute)

