Classfile /Users/mw/Projects/slang-braindump/.jar/jar11/assemble/slang-braindump/assemble/content/org/scalatest/CompositeStatus$Bundle$.class
  Last modified May 29, 2022; size 2412 bytes
  SHA-256 checksum 10671ca72ae9a8e669851d7661621a10cd263089ceb29d346e84d4d9c024e739
  Compiled from "Status.scala"
public class org.scalatest.CompositeStatus$Bundle$ extends scala.runtime.AbstractFunction2<java.lang.Object, scala.Option<java.lang.Throwable>, org.scalatest.CompositeStatus$Bundle> implements java.io.Serializable
  minor version: 0
  major version: 52
  flags: (0x0021) ACC_PUBLIC, ACC_SUPER
  this_class: #2                          // org/scalatest/CompositeStatus$Bundle$
  super_class: #5                         // scala/runtime/AbstractFunction2
  interfaces: 1, fields: 1, methods: 7, attributes: 5
Constant pool:
    #1 = Utf8               org/scalatest/CompositeStatus$Bundle$
    #2 = Class              #1            // org/scalatest/CompositeStatus$Bundle$
    #3 = Utf8               Lscala/runtime/AbstractFunction2<Ljava/lang/Object;Lscala/Option<Ljava/lang/Throwable;>;Lorg/scalatest/CompositeStatus$Bundle;>;Ljava/io/Serializable;
    #4 = Utf8               scala/runtime/AbstractFunction2
    #5 = Class              #4            // scala/runtime/AbstractFunction2
    #6 = Utf8               java/io/Serializable
    #7 = Class              #6            // java/io/Serializable
    #8 = Utf8               Status.scala
    #9 = Utf8               org/scalatest/CompositeStatus$Bundle
   #10 = Class              #9            // org/scalatest/CompositeStatus$Bundle
   #11 = Utf8               org/scalatest/CompositeStatus
   #12 = Class              #11           // org/scalatest/CompositeStatus
   #13 = Utf8               Bundle
   #14 = Utf8               Bundle$
   #15 = Utf8               MODULE$
   #16 = Utf8               Lorg/scalatest/CompositeStatus$Bundle$;
   #17 = Utf8               <clinit>
   #18 = Utf8               ()V
   #19 = Utf8               <init>
   #20 = NameAndType        #19:#18       // "<init>":()V
   #21 = Methodref          #2.#20        // org/scalatest/CompositeStatus$Bundle$."<init>":()V
   #22 = NameAndType        #15:#16       // MODULE$:Lorg/scalatest/CompositeStatus$Bundle$;
   #23 = Fieldref           #2.#22        // org/scalatest/CompositeStatus$Bundle$.MODULE$:Lorg/scalatest/CompositeStatus$Bundle$;
   #24 = Utf8               toString
   #25 = Utf8               ()Ljava/lang/String;
   #26 = String             #13           // Bundle
   #27 = Utf8               this
   #28 = Utf8               apply
   #29 = Utf8               (ZLscala/Option;)Lorg/scalatest/CompositeStatus$Bundle;
   #30 = Utf8               (ZLscala/Option<Ljava/lang/Throwable;>;)Lorg/scalatest/CompositeStatus$Bundle;
   #31 = Utf8               succeeded
   #32 = Utf8               asyncException
   #33 = Utf8               (ZLscala/Option;)V
   #34 = NameAndType        #19:#33       // "<init>":(ZLscala/Option;)V
   #35 = Methodref          #10.#34       // org/scalatest/CompositeStatus$Bundle."<init>":(ZLscala/Option;)V
   #36 = Utf8               Z
   #37 = Utf8               Lscala/Option;
   #38 = Utf8               unapply
   #39 = Utf8               (Lorg/scalatest/CompositeStatus$Bundle;)Lscala/Option;
   #40 = Utf8               (Lorg/scalatest/CompositeStatus$Bundle;)Lscala/Option<Lscala/Tuple2<Ljava/lang/Object;Lscala/Option<Ljava/lang/Throwable;>;>;>;
   #41 = Utf8               x$0
   #42 = Utf8               scala/None$
   #43 = Class              #42           // scala/None$
   #44 = Utf8               Lscala/None$;
   #45 = NameAndType        #15:#44       // MODULE$:Lscala/None$;
   #46 = Fieldref           #43.#45       // scala/None$.MODULE$:Lscala/None$;
   #47 = Utf8               scala/Some
   #48 = Class              #47           // scala/Some
   #49 = Utf8               scala/Tuple2
   #50 = Class              #49           // scala/Tuple2
   #51 = Utf8               ()Z
   #52 = NameAndType        #31:#51       // succeeded:()Z
   #53 = Methodref          #10.#52       // org/scalatest/CompositeStatus$Bundle.succeeded:()Z
   #54 = Utf8               scala/runtime/BoxesRunTime
   #55 = Class              #54           // scala/runtime/BoxesRunTime
   #56 = Utf8               boxToBoolean
   #57 = Utf8               (Z)Ljava/lang/Boolean;
   #58 = NameAndType        #56:#57       // boxToBoolean:(Z)Ljava/lang/Boolean;
   #59 = Methodref          #55.#58       // scala/runtime/BoxesRunTime.boxToBoolean:(Z)Ljava/lang/Boolean;
   #60 = Utf8               ()Lscala/Option;
   #61 = NameAndType        #32:#60       // asyncException:()Lscala/Option;
   #62 = Methodref          #10.#61       // org/scalatest/CompositeStatus$Bundle.asyncException:()Lscala/Option;
   #63 = Utf8               (Ljava/lang/Object;Ljava/lang/Object;)V
   #64 = NameAndType        #19:#63       // "<init>":(Ljava/lang/Object;Ljava/lang/Object;)V
   #65 = Methodref          #50.#64       // scala/Tuple2."<init>":(Ljava/lang/Object;Ljava/lang/Object;)V
   #66 = Utf8               (Ljava/lang/Object;)V
   #67 = NameAndType        #19:#66       // "<init>":(Ljava/lang/Object;)V
   #68 = Methodref          #48.#67       // scala/Some."<init>":(Ljava/lang/Object;)V
   #69 = Utf8               Lorg/scalatest/CompositeStatus$Bundle;
   #70 = Utf8               scala/Option
   #71 = Class              #70           // scala/Option
   #72 = Utf8               writeReplace
   #73 = Utf8               ()Ljava/lang/Object;
   #74 = Utf8               scala/runtime/ModuleSerializationProxy
   #75 = Class              #74           // scala/runtime/ModuleSerializationProxy
   #76 = Utf8               (Ljava/lang/Class;)V
   #77 = NameAndType        #19:#76       // "<init>":(Ljava/lang/Class;)V
   #78 = Methodref          #75.#77       // scala/runtime/ModuleSerializationProxy."<init>":(Ljava/lang/Class;)V
   #79 = Utf8               (Ljava/lang/Object;Ljava/lang/Object;)Ljava/lang/Object;
   #80 = Utf8               v1
   #81 = Utf8               v2
   #82 = Utf8               unboxToBoolean
   #83 = Utf8               (Ljava/lang/Object;)Z
   #84 = NameAndType        #82:#83       // unboxToBoolean:(Ljava/lang/Object;)Z
   #85 = Methodref          #55.#84       // scala/runtime/BoxesRunTime.unboxToBoolean:(Ljava/lang/Object;)Z
   #86 = NameAndType        #28:#29       // apply:(ZLscala/Option;)Lorg/scalatest/CompositeStatus$Bundle;
   #87 = Methodref          #2.#86        // org/scalatest/CompositeStatus$Bundle$.apply:(ZLscala/Option;)Lorg/scalatest/CompositeStatus$Bundle;
   #88 = Utf8               Ljava/lang/Object;
   #89 = Methodref          #5.#20        // scala/runtime/AbstractFunction2."<init>":()V
   #90 = Utf8               Code
   #91 = Utf8               LineNumberTable
   #92 = Utf8               LocalVariableTable
   #93 = Utf8               Signature
   #94 = Utf8               MethodParameters
   #95 = Utf8               StackMapTable
   #96 = Utf8               InnerClasses
   #97 = Utf8               SourceFile
   #98 = Utf8               ScalaInlineInfo
   #99 = Utf8               Scala
{
  public static final org.scalatest.CompositeStatus$Bundle$ MODULE$;
    descriptor: Lorg/scalatest/CompositeStatus$Bundle$;
    flags: (0x0019) ACC_PUBLIC, ACC_STATIC, ACC_FINAL

  public static {};
    descriptor: ()V
    flags: (0x0009) ACC_PUBLIC, ACC_STATIC
    Code:
      stack=2, locals=0, args_size=0
         0: new           #2                  // class org/scalatest/CompositeStatus$Bundle$
         3: dup
         4: invokespecial #21                 // Method "<init>":()V
         7: putstatic     #23                 // Field MODULE$:Lorg/scalatest/CompositeStatus$Bundle$;
        10: return
      LineNumberTable:
        line 993: 0

  public final java.lang.String toString();
    descriptor: ()Ljava/lang/String;
    flags: (0x0011) ACC_PUBLIC, ACC_FINAL
    Code:
      stack=1, locals=1, args_size=1
         0: ldc           #26                 // String Bundle
         2: areturn
      LineNumberTable:
        line 993: 0
      LocalVariableTable:
        Start  Length  Slot  Name   Signature
            0       3     0  this   Lorg/scalatest/CompositeStatus$Bundle$;

  public org.scalatest.CompositeStatus$Bundle apply(boolean, scala.Option<java.lang.Throwable>);
    descriptor: (ZLscala/Option;)Lorg/scalatest/CompositeStatus$Bundle;
    flags: (0x0001) ACC_PUBLIC
    Code:
      stack=4, locals=3, args_size=3
         0: new           #10                 // class org/scalatest/CompositeStatus$Bundle
         3: dup
         4: iload_1
         5: aload_2
         6: invokespecial #35                 // Method org/scalatest/CompositeStatus$Bundle."<init>":(ZLscala/Option;)V
         9: areturn
      LineNumberTable:
        line 993: 0
      LocalVariableTable:
        Start  Length  Slot  Name   Signature
            0      10     0  this   Lorg/scalatest/CompositeStatus$Bundle$;
            0      10     1 succeeded   Z
            0      10     2 asyncException   Lscala/Option;
    Signature: #30                          // (ZLscala/Option<Ljava/lang/Throwable;>;)Lorg/scalatest/CompositeStatus$Bundle;
    MethodParameters:
      Name                           Flags
      succeeded                      final
      asyncException                 final

  public scala.Option<scala.Tuple2<java.lang.Object, scala.Option<java.lang.Throwable>>> unapply(org.scalatest.CompositeStatus$Bundle);
    descriptor: (Lorg/scalatest/CompositeStatus$Bundle;)Lscala/Option;
    flags: (0x0001) ACC_PUBLIC
    Code:
      stack=6, locals=2, args_size=2
         0: aload_1
         1: ifnonnull     10
         4: getstatic     #46                 // Field scala/None$.MODULE$:Lscala/None$;
         7: goto          35
        10: new           #48                 // class scala/Some
        13: dup
        14: new           #50                 // class scala/Tuple2
        17: dup
        18: aload_1
        19: invokevirtual #53                 // Method org/scalatest/CompositeStatus$Bundle.succeeded:()Z
        22: invokestatic  #59                 // Method scala/runtime/BoxesRunTime.boxToBoolean:(Z)Ljava/lang/Boolean;
        25: aload_1
        26: invokevirtual #62                 // Method org/scalatest/CompositeStatus$Bundle.asyncException:()Lscala/Option;
        29: invokespecial #65                 // Method scala/Tuple2."<init>":(Ljava/lang/Object;Ljava/lang/Object;)V
        32: invokespecial #68                 // Method scala/Some."<init>":(Ljava/lang/Object;)V
        35: areturn
      StackMapTable: number_of_entries = 2
        frame_type = 10 /* same */
        frame_type = 88 /* same_locals_1_stack_item */
          stack = [ class scala/Option ]
      LineNumberTable:
        line 993: 0
      LocalVariableTable:
        Start  Length  Slot  Name   Signature
            0      36     0  this   Lorg/scalatest/CompositeStatus$Bundle$;
            0      36     1   x$0   Lorg/scalatest/CompositeStatus$Bundle;
    Signature: #40                          // (Lorg/scalatest/CompositeStatus$Bundle;)Lscala/Option<Lscala/Tuple2<Ljava/lang/Object;Lscala/Option<Ljava/lang/Throwable;>;>;>;
    MethodParameters:
      Name                           Flags
      x$0                            final

  private java.lang.Object writeReplace();
    descriptor: ()Ljava/lang/Object;
    flags: (0x0002) ACC_PRIVATE
    Code:
      stack=3, locals=1, args_size=1
         0: new           #75                 // class scala/runtime/ModuleSerializationProxy
         3: dup
         4: ldc           #2                  // class org/scalatest/CompositeStatus$Bundle$
         6: invokespecial #78                 // Method scala/runtime/ModuleSerializationProxy."<init>":(Ljava/lang/Class;)V
         9: areturn
      LineNumberTable:
        line 993: 0
      LocalVariableTable:
        Start  Length  Slot  Name   Signature
            0      10     0  this   Lorg/scalatest/CompositeStatus$Bundle$;

  public java.lang.Object apply(java.lang.Object, java.lang.Object);
    descriptor: (Ljava/lang/Object;Ljava/lang/Object;)Ljava/lang/Object;
    flags: (0x1041) ACC_PUBLIC, ACC_BRIDGE, ACC_SYNTHETIC
    Code:
      stack=3, locals=3, args_size=3
         0: aload_0
         1: aload_1
         2: invokestatic  #85                 // Method scala/runtime/BoxesRunTime.unboxToBoolean:(Ljava/lang/Object;)Z
         5: aload_2
         6: checkcast     #71                 // class scala/Option
         9: invokevirtual #87                 // Method apply:(ZLscala/Option;)Lorg/scalatest/CompositeStatus$Bundle;
        12: areturn
      LineNumberTable:
        line 993: 0
      LocalVariableTable:
        Start  Length  Slot  Name   Signature
            0      13     0  this   Lorg/scalatest/CompositeStatus$Bundle$;
            0      13     1    v1   Ljava/lang/Object;
            0      13     2    v2   Ljava/lang/Object;
    MethodParameters:
      Name                           Flags
      v1                             final
      v2                             final

  public org.scalatest.CompositeStatus$Bundle$();
    descriptor: ()V
    flags: (0x0001) ACC_PUBLIC
    Code:
      stack=1, locals=1, args_size=1
         0: aload_0
         1: invokespecial #89                 // Method scala/runtime/AbstractFunction2."<init>":()V
         4: return
      LineNumberTable:
        line 993: 0
      LocalVariableTable:
        Start  Length  Slot  Name   Signature
            0       5     0  this   Lorg/scalatest/CompositeStatus$Bundle$;
}
InnerClasses:
  public static #13= #10 of #12;          // Bundle=class org/scalatest/CompositeStatus$Bundle of class org/scalatest/CompositeStatus
  public static #14= #2 of #12;           // Bundle$=class org/scalatest/CompositeStatus$Bundle$ of class org/scalatest/CompositeStatus
Signature: #3                           // Lscala/runtime/AbstractFunction2<Ljava/lang/Object;Lscala/Option<Ljava/lang/Throwable;>;Lorg/scalatest/CompositeStatus$Bundle;>;Ljava/io/Serializable;
SourceFile: "Status.scala"
  ScalaInlineInfo: length = 0x22 (unknown attribute)
   01 01 00 06 00 13 00 12 01 00 1C 00 4F 01 00 1C
   00 1D 01 00 18 00 19 01 00 26 00 27 01 00 48 00
   49 01
  Scala: length = 0x0 (unknown attribute)

