Classfile /Users/mw/Projects/slang-braindump/.jar/jar11/assemble/slang-braindump/assemble/content/org/scalatest/ConcurrentLinkedQueue.class
  Last modified May 29, 2022; size 2886 bytes
  SHA-256 checksum 9dce98a1a24c50691be831bcb194a24665b5d598001c47ad38528ad3cf1638a1
  Compiled from "JavaClassesWrappers.scala"
public class org.scalatest.ConcurrentLinkedQueue<T extends java.lang.Object> extends java.lang.Object implements java.io.Serializable
  minor version: 0
  major version: 52
  flags: (0x0021) ACC_PUBLIC, ACC_SUPER
  this_class: #2                          // org/scalatest/ConcurrentLinkedQueue
  super_class: #5                         // java/lang/Object
  interfaces: 1, fields: 1, methods: 7, attributes: 6
Constant pool:
   #1 = Utf8               org/scalatest/ConcurrentLinkedQueue
   #2 = Class              #1             // org/scalatest/ConcurrentLinkedQueue
   #3 = Utf8               <T:Ljava/lang/Object;>Ljava/lang/Object;Ljava/io/Serializable;
   #4 = Utf8               java/lang/Object
   #5 = Class              #4             // java/lang/Object
   #6 = Utf8               java/io/Serializable
   #7 = Class              #6             // java/io/Serializable
   #8 = Utf8               JavaClassesWrappers.scala
   #9 = Utf8               Lscala/reflect/ScalaSignature;
  #10 = Utf8               bytes
  #11 = Utf8               \u0006\u0005u3Q!\u0003\u0006\u0001\u00159AQa\t\u0001\u0005\u0002\u0011BqA\r\u0001C\u0002\u001351\u0007\u0003\u0004>\u0001\u0001\u0006i\u0001\u000e\u0005\u0006}\u0001!\ta\u0010\u0005\u0006\u000b\u0002!\tA\u0012\u0005\u0006\u0015\u0002!\ta\u0013\u0005\u0006\u001f\u0002!\t\u0001\u0015\u0005\u00067\u0002!\t\u0001\u0018\u0002\u0016\u0007>t7-\u001e:sK:$H*\u001b8lK\u0012\fV/Z;f\u0015\tYA\"A\u0005tG\u0006d\u0017\r^3ti*\tQ\"A\u0002pe\u001e,\"aD\u0015\u0014\u0007\u0001\u0001b\u0003\u0005\u0002\u0012)5\t!CC\u0001\u0014\u0003\u0015\u00198-\u00197b\u0013\t)\"C\u0001\u0004B]f\u0014VM\u001a\t\u0003/\u0001r!\u0001\u0007\u0010\u000f\u0005eiR\"\u0001\u000e\u000b\u0005ma\u0012A\u0002\u001fs_>$hh\u0001\u0001\n\u0003MI!a\b\n\u0002\u000fA\f7m[1hK&\u0011\u0011E\t\u0002\r\'\u0016\u0014\u0018.\u00197ju\u0006\u0014G.\u001a\u0006\u0003?I\ta\u0001P5oSRtD#A\u0013\u0011\u0007\u0019\u0002q%D\u0001\u000b!\tA\u0013\u0006\u0004\u0001\u0005\u000b)\u0002!\u0019A\u0016\u0003\u0003Q\u000b\"\u0001L\u0018\u0011\u0005Ei\u0013B\u0001\u0018\u0013\u0005\u001dqu\u000e\u001e5j]\u001e\u0004\"!\u0005\u0019\n\u0005E\u0012\"aA!os\u0006)\u0011/^3vKV\tA\u0007E\u00026y\u001dj\u0011A\u000e\u0006\u0003oa\n!bY8oGV\u0014(/\u001a8u\u0015\tI$(\u0001\u0003vi&d\'\"A\u001e\u0002\t)\fg/Y\u0005\u0003\u0013Y\na!];fk\u0016\u0004\u0013aA1eIR\u0011\u0001i\u0011\t\u0003#\u0005K!A\u0011\n\u0003\tUs\u0017\u000e\u001e\u0005\u0006\t\u0012\u0001\raJ\u0001\u0004K2,\u0017\u0001C5uKJ\fGo\u001c:\u0016\u0003\u001d\u00032a\u0006%(\u0013\tI%E\u0001\u0005Ji\u0016\u0014\u0018\r^8s\u0003\u001dI7/R7qif,\u0012\u0001\u0014\t\u0003#5K!A\u0014\n\u0003\u000f\t{w\u000e\\3b]\u00069\u0011m]*dC2\fW#A)\u0011\u0007ICvE\u0004\u0002T-:\u0011\u0001\u0004V\u0005\u0003+J\t!bY8mY\u0016\u001cG/[8o\u0013\tyrK\u0003\u0002V%%\u0011\u0011L\u0017\u0002\u000f\u000f\u0016tGK]1wKJ\u001c\u0018M\u00197f\u0015\tyr+\u0001\u0003q_2dW#A\u0014
  #12 = Utf8               scala/collection/JavaConverters$AsScala
  #13 = Class              #12            // scala/collection/JavaConverters$AsScala
  #14 = Utf8               scala/collection/JavaConverters
  #15 = Class              #14            // scala/collection/JavaConverters
  #16 = Utf8               AsScala
  #17 = Utf8               queue
  #18 = Utf8               Ljava/util/concurrent/ConcurrentLinkedQueue;
  #19 = Utf8               Ljava/util/concurrent/ConcurrentLinkedQueue<TT;>;
  #20 = Utf8               ()Ljava/util/concurrent/ConcurrentLinkedQueue;
  #21 = Utf8               ()Ljava/util/concurrent/ConcurrentLinkedQueue<TT;>;
  #22 = NameAndType        #17:#18        // queue:Ljava/util/concurrent/ConcurrentLinkedQueue;
  #23 = Fieldref           #2.#22         // org/scalatest/ConcurrentLinkedQueue.queue:Ljava/util/concurrent/ConcurrentLinkedQueue;
  #24 = Utf8               this
  #25 = Utf8               Lorg/scalatest/ConcurrentLinkedQueue;
  #26 = Utf8               add
  #27 = Utf8               (Ljava/lang/Object;)V
  #28 = Utf8               (TT;)V
  #29 = Utf8               ele
  #30 = NameAndType        #17:#20        // queue:()Ljava/util/concurrent/ConcurrentLinkedQueue;
  #31 = Methodref          #2.#30         // org/scalatest/ConcurrentLinkedQueue.queue:()Ljava/util/concurrent/ConcurrentLinkedQueue;
  #32 = Utf8               java/util/concurrent/ConcurrentLinkedQueue
  #33 = Class              #32            // java/util/concurrent/ConcurrentLinkedQueue
  #34 = Utf8               (Ljava/lang/Object;)Z
  #35 = NameAndType        #26:#34        // add:(Ljava/lang/Object;)Z
  #36 = Methodref          #33.#35        // java/util/concurrent/ConcurrentLinkedQueue.add:(Ljava/lang/Object;)Z
  #37 = Utf8               Ljava/lang/Object;
  #38 = Utf8               iterator
  #39 = Utf8               ()Lscala/collection/Iterator;
  #40 = Utf8               ()Lscala/collection/Iterator<TT;>;
  #41 = Utf8               scala/collection/JavaConverters$
  #42 = Class              #41            // scala/collection/JavaConverters$
  #43 = Utf8               MODULE$
  #44 = Utf8               Lscala/collection/JavaConverters$;
  #45 = NameAndType        #43:#44        // MODULE$:Lscala/collection/JavaConverters$;
  #46 = Fieldref           #42.#45        // scala/collection/JavaConverters$.MODULE$:Lscala/collection/JavaConverters$;
  #47 = Utf8               ()Ljava/util/Iterator;
  #48 = NameAndType        #38:#47        // iterator:()Ljava/util/Iterator;
  #49 = Methodref          #33.#48        // java/util/concurrent/ConcurrentLinkedQueue.iterator:()Ljava/util/Iterator;
  #50 = Utf8               asScalaIteratorConverter
  #51 = Utf8               (Ljava/util/Iterator;)Lscala/collection/JavaConverters$AsScala;
  #52 = NameAndType        #50:#51        // asScalaIteratorConverter:(Ljava/util/Iterator;)Lscala/collection/JavaConverters$AsScala;
  #53 = Methodref          #42.#52        // scala/collection/JavaConverters$.asScalaIteratorConverter:(Ljava/util/Iterator;)Lscala/collection/JavaConverters$AsScala;
  #54 = Utf8               asScala
  #55 = Utf8               ()Ljava/lang/Object;
  #56 = NameAndType        #54:#55        // asScala:()Ljava/lang/Object;
  #57 = Methodref          #13.#56        // scala/collection/JavaConverters$AsScala.asScala:()Ljava/lang/Object;
  #58 = Utf8               scala/collection/Iterator
  #59 = Class              #58            // scala/collection/Iterator
  #60 = Utf8               isEmpty
  #61 = Utf8               ()Z
  #62 = NameAndType        #60:#61        // isEmpty:()Z
  #63 = Methodref          #33.#62        // java/util/concurrent/ConcurrentLinkedQueue.isEmpty:()Z
  #64 = Utf8               ()Lscala/collection/Iterable;
  #65 = Utf8               ()Lscala/collection/Iterable<TT;>;
  #66 = Utf8               collectionAsScalaIterableConverter
  #67 = Utf8               (Ljava/util/Collection;)Lscala/collection/JavaConverters$AsScala;
  #68 = NameAndType        #66:#67        // collectionAsScalaIterableConverter:(Ljava/util/Collection;)Lscala/collection/JavaConverters$AsScala;
  #69 = Methodref          #42.#68        // scala/collection/JavaConverters$.collectionAsScalaIterableConverter:(Ljava/util/Collection;)Lscala/collection/JavaConverters$AsScala;
  #70 = Utf8               scala/collection/Iterable
  #71 = Class              #70            // scala/collection/Iterable
  #72 = Utf8               poll
  #73 = Utf8               ()TT;
  #74 = NameAndType        #72:#55        // poll:()Ljava/lang/Object;
  #75 = Methodref          #33.#74        // java/util/concurrent/ConcurrentLinkedQueue.poll:()Ljava/lang/Object;
  #76 = Utf8               <init>
  #77 = Utf8               ()V
  #78 = NameAndType        #76:#77        // "<init>":()V
  #79 = Methodref          #5.#78         // java/lang/Object."<init>":()V
  #80 = Methodref          #33.#78        // java/util/concurrent/ConcurrentLinkedQueue."<init>":()V
  #81 = Utf8               Signature
  #82 = Utf8               Code
  #83 = Utf8               LineNumberTable
  #84 = Utf8               LocalVariableTable
  #85 = Utf8               MethodParameters
  #86 = Utf8               InnerClasses
  #87 = Utf8               SourceFile
  #88 = Utf8               RuntimeVisibleAnnotations
  #89 = Utf8               ScalaInlineInfo
  #90 = Utf8               ScalaSig
{
  private final java.util.concurrent.ConcurrentLinkedQueue<T> queue;
    descriptor: Ljava/util/concurrent/ConcurrentLinkedQueue;
    flags: (0x0012) ACC_PRIVATE, ACC_FINAL
    Signature: #19                          // Ljava/util/concurrent/ConcurrentLinkedQueue<TT;>;

  private final java.util.concurrent.ConcurrentLinkedQueue<T> queue();
    descriptor: ()Ljava/util/concurrent/ConcurrentLinkedQueue;
    flags: (0x0012) ACC_PRIVATE, ACC_FINAL
    Code:
      stack=1, locals=1, args_size=1
         0: aload_0
         1: getfield      #23                 // Field queue:Ljava/util/concurrent/ConcurrentLinkedQueue;
         4: areturn
      LineNumberTable:
        line 24: 0
      LocalVariableTable:
        Start  Length  Slot  Name   Signature
            0       5     0  this   Lorg/scalatest/ConcurrentLinkedQueue;
    Signature: #21                          // ()Ljava/util/concurrent/ConcurrentLinkedQueue<TT;>;

  public void add(T);
    descriptor: (Ljava/lang/Object;)V
    flags: (0x0001) ACC_PUBLIC
    Code:
      stack=2, locals=2, args_size=2
         0: aload_0
         1: invokespecial #31                 // Method queue:()Ljava/util/concurrent/ConcurrentLinkedQueue;
         4: aload_1
         5: invokevirtual #36                 // Method java/util/concurrent/ConcurrentLinkedQueue.add:(Ljava/lang/Object;)Z
         8: pop
         9: return
      LineNumberTable:
        line 27: 0
      LocalVariableTable:
        Start  Length  Slot  Name   Signature
            0      10     0  this   Lorg/scalatest/ConcurrentLinkedQueue;
            0      10     1   ele   Ljava/lang/Object;
    Signature: #28                          // (TT;)V
    MethodParameters:
      Name                           Flags
      ele                            final

  public scala.collection.Iterator<T> iterator();
    descriptor: ()Lscala/collection/Iterator;
    flags: (0x0001) ACC_PUBLIC
    Code:
      stack=2, locals=1, args_size=1
         0: getstatic     #46                 // Field scala/collection/JavaConverters$.MODULE$:Lscala/collection/JavaConverters$;
         3: aload_0
         4: invokespecial #31                 // Method queue:()Ljava/util/concurrent/ConcurrentLinkedQueue;
         7: invokevirtual #49                 // Method java/util/concurrent/ConcurrentLinkedQueue.iterator:()Ljava/util/Iterator;
        10: invokevirtual #53                 // Method scala/collection/JavaConverters$.asScalaIteratorConverter:(Ljava/util/Iterator;)Lscala/collection/JavaConverters$AsScala;
        13: invokevirtual #57                 // Method scala/collection/JavaConverters$AsScala.asScala:()Ljava/lang/Object;
        16: checkcast     #59                 // class scala/collection/Iterator
        19: areturn
      LineNumberTable:
        line 30: 0
      LocalVariableTable:
        Start  Length  Slot  Name   Signature
            0      20     0  this   Lorg/scalatest/ConcurrentLinkedQueue;
    Signature: #40                          // ()Lscala/collection/Iterator<TT;>;

  public boolean isEmpty();
    descriptor: ()Z
    flags: (0x0001) ACC_PUBLIC
    Code:
      stack=1, locals=1, args_size=1
         0: aload_0
         1: invokespecial #31                 // Method queue:()Ljava/util/concurrent/ConcurrentLinkedQueue;
         4: invokevirtual #63                 // Method java/util/concurrent/ConcurrentLinkedQueue.isEmpty:()Z
         7: ireturn
      LineNumberTable:
        line 32: 0
      LocalVariableTable:
        Start  Length  Slot  Name   Signature
            0       8     0  this   Lorg/scalatest/ConcurrentLinkedQueue;

  public scala.collection.Iterable<T> asScala();
    descriptor: ()Lscala/collection/Iterable;
    flags: (0x0001) ACC_PUBLIC
    Code:
      stack=2, locals=1, args_size=1
         0: getstatic     #46                 // Field scala/collection/JavaConverters$.MODULE$:Lscala/collection/JavaConverters$;
         3: aload_0
         4: invokespecial #31                 // Method queue:()Ljava/util/concurrent/ConcurrentLinkedQueue;
         7: invokevirtual #69                 // Method scala/collection/JavaConverters$.collectionAsScalaIterableConverter:(Ljava/util/Collection;)Lscala/collection/JavaConverters$AsScala;
        10: invokevirtual #57                 // Method scala/collection/JavaConverters$AsScala.asScala:()Ljava/lang/Object;
        13: checkcast     #71                 // class scala/collection/Iterable
        16: areturn
      LineNumberTable:
        line 34: 0
      LocalVariableTable:
        Start  Length  Slot  Name   Signature
            0      17     0  this   Lorg/scalatest/ConcurrentLinkedQueue;
    Signature: #65                          // ()Lscala/collection/Iterable<TT;>;

  public T poll();
    descriptor: ()Ljava/lang/Object;
    flags: (0x0001) ACC_PUBLIC
    Code:
      stack=1, locals=1, args_size=1
         0: aload_0
         1: invokespecial #31                 // Method queue:()Ljava/util/concurrent/ConcurrentLinkedQueue;
         4: invokevirtual #75                 // Method java/util/concurrent/ConcurrentLinkedQueue.poll:()Ljava/lang/Object;
         7: areturn
      LineNumberTable:
        line 36: 0
      LocalVariableTable:
        Start  Length  Slot  Name   Signature
            0       8     0  this   Lorg/scalatest/ConcurrentLinkedQueue;
    Signature: #73                          // ()TT;

  public org.scalatest.ConcurrentLinkedQueue();
    descriptor: ()V
    flags: (0x0001) ACC_PUBLIC
    Code:
      stack=3, locals=1, args_size=1
         0: aload_0
         1: invokespecial #79                 // Method java/lang/Object."<init>":()V
         4: aload_0
         5: new           #33                 // class java/util/concurrent/ConcurrentLinkedQueue
         8: dup
         9: invokespecial #80                 // Method java/util/concurrent/ConcurrentLinkedQueue."<init>":()V
        12: putfield      #23                 // Field queue:Ljava/util/concurrent/ConcurrentLinkedQueue;
        15: return
      LineNumberTable:
        line 22: 0
        line 24: 4
        line 22: 15
      LocalVariableTable:
        Start  Length  Slot  Name   Signature
            0      16     0  this   Lorg/scalatest/ConcurrentLinkedQueue;
}
InnerClasses:
  public static #16= #13 of #15;          // AsScala=class scala/collection/JavaConverters$AsScala of class scala/collection/JavaConverters
Signature: #3                           // <T:Ljava/lang/Object;>Ljava/lang/Object;Ljava/io/Serializable;
SourceFile: "JavaClassesWrappers.scala"
RuntimeVisibleAnnotations:
  0: #9(#10=s#11)
    scala.reflect.ScalaSignature(
      bytes="\u0006\u0005u3Q!\u0003\u0006\u0001\u00159AQa\t\u0001\u0005\u0002\u0011BqA\r\u0001C\u0002\u001351\u0007\u0003\u0004>\u0001\u0001\u0006i\u0001\u000e\u0005\u0006}\u0001!\ta\u0010\u0005\u0006\u000b\u0002!\tA\u0012\u0005\u0006\u0015\u0002!\ta\u0013\u0005\u0006\u001f\u0002!\t\u0001\u0015\u0005\u00067\u0002!\t\u0001\u0018\u0002\u0016\u0007>t7-\u001e:sK:$H*\u001b8lK\u0012\fV/Z;f\u0015\tYA\"A\u0005tG\u0006d\u0017\r^3ti*\tQ\"A\u0002pe\u001e,\"aD\u0015\u0014\u0007\u0001\u0001b\u0003\u0005\u0002\u0012)5\t!CC\u0001\u0014\u0003\u0015\u00198-\u00197b\u0013\t)\"C\u0001\u0004B]f\u0014VM\u001a\t\u0003/\u0001r!\u0001\u0007\u0010\u000f\u0005eiR\"\u0001\u000e\u000b\u0005ma\u0012A\u0002\u001fs_>$hh\u0001\u0001\n\u0003MI!a\b\n\u0002\u000fA\f7m[1hK&\u0011\u0011E\t\u0002\r\'\u0016\u0014\u0018.\u00197ju\u0006\u0014G.\u001a\u0006\u0003?I\ta\u0001P5oSRtD#A\u0013\u0011\u0007\u0019\u0002q%D\u0001\u000b!\tA\u0013\u0006\u0004\u0001\u0005\u000b)\u0002!\u0019A\u0016\u0003\u0003Q\u000b\"\u0001L\u0018\u0011\u0005Ei\u0013B\u0001\u0018\u0013\u0005\u001dqu\u000e\u001e5j]\u001e\u0004\"!\u0005\u0019\n\u0005E\u0012\"aA!os\u0006)\u0011/^3vKV\tA\u0007E\u00026y\u001dj\u0011A\u000e\u0006\u0003oa\n!bY8oGV\u0014(/\u001a8u\u0015\tI$(\u0001\u0003vi&d\'\"A\u001e\u0002\t)\fg/Y\u0005\u0003\u0013Y\na!];fk\u0016\u0004\u0013aA1eIR\u0011\u0001i\u0011\t\u0003#\u0005K!A\u0011\n\u0003\tUs\u0017\u000e\u001e\u0005\u0006\t\u0012\u0001\raJ\u0001\u0004K2,\u0017\u0001C5uKJ\fGo\u001c:\u0016\u0003\u001d\u00032a\u0006%(\u0013\tI%E\u0001\u0005Ji\u0016\u0014\u0018\r^8s\u0003\u001dI7/R7qif,\u0012\u0001\u0014\t\u0003#5K!A\u0014\n\u0003\u000f\t{w\u000e\\3b]\u00069\u0011m]*dC2\fW#A)\u0011\u0007ICvE\u0004\u0002T-:\u0011\u0001\u0004V\u0005\u0003+J\t!bY8mY\u0016\u001cG/[8o\u0013\tyrK\u0003\u0002V%%\u0011\u0011L\u0017\u0002\u000f\u000f\u0016tGK]1wKJ\u001c\u0018M\u00197f\u0015\tyr+\u0001\u0003q_2dW#A\u0014"
    )
  ScalaInlineInfo: length = 0x27 (unknown attribute)
   01 00 00 07 00 4C 00 4D 00 00 1A 00 1B 00 00 36
   00 40 00 00 3C 00 3D 00 00 26 00 27 00 00 48 00
   37 00 00 11 00 14 01
  ScalaSig: length = 0x3 (unknown attribute)
   05 02 00
