Classfile /Users/mw/Projects/slang-braindump/.jar/jar11/assemble/slang-braindump/assemble/content/org/scalatest/DispatchReporter$Propagator$Counter$1.class
  Last modified May 29, 2022; size 2562 bytes
  SHA-256 checksum 3a5f5895ab80f6db717c5cbd94f8bca79592a8db917ccc6cba297e9181c48a30
  Compiled from "DispatchReporter.scala"
public class org.scalatest.DispatchReporter$Propagator$Counter$1
  minor version: 0
  major version: 52
  flags: (0x0021) ACC_PUBLIC, ACC_SUPER
  this_class: #2                          // org/scalatest/DispatchReporter$Propagator$Counter$1
  super_class: #4                         // java/lang/Object
  interfaces: 0, fields: 8, methods: 17, attributes: 5
Constant pool:
   #1 = Utf8               org/scalatest/DispatchReporter$Propagator$Counter$1
   #2 = Class              #1             // org/scalatest/DispatchReporter$Propagator$Counter$1
   #3 = Utf8               java/lang/Object
   #4 = Class              #3             // java/lang/Object
   #5 = Utf8               DispatchReporter.scala
   #6 = Utf8               org/scalatest/DispatchReporter$Propagator
   #7 = Class              #6             // org/scalatest/DispatchReporter$Propagator
   #8 = Utf8               run
   #9 = Utf8               ()V
  #10 = NameAndType        #8:#9          // run:()V
  #11 = Utf8               org/scalatest/DispatchReporter
  #12 = Class              #11            // org/scalatest/DispatchReporter
  #13 = Utf8               Propagator
  #14 = Utf8               Counter$1
  #15 = Utf8               testsSucceededCount
  #16 = Utf8               I
  #17 = Utf8               testsFailedCount
  #18 = Utf8               testsIgnoredCount
  #19 = Utf8               testsCanceledCount
  #20 = Utf8               testsPendingCount
  #21 = Utf8               suitesCompletedCount
  #22 = Utf8               suitesAbortedCount
  #23 = Utf8               scopesPendingCount
  #24 = Utf8               ()I
  #25 = NameAndType        #15:#16        // testsSucceededCount:I
  #26 = Fieldref           #2.#25         // org/scalatest/DispatchReporter$Propagator$Counter$1.testsSucceededCount:I
  #27 = Utf8               this
  #28 = Utf8               Lorg/scalatest/DispatchReporter$Propagator$Counter$1;
  #29 = Utf8               testsSucceededCount_$eq
  #30 = Utf8               (I)V
  #31 = Utf8               x$1
  #32 = NameAndType        #17:#16        // testsFailedCount:I
  #33 = Fieldref           #2.#32         // org/scalatest/DispatchReporter$Propagator$Counter$1.testsFailedCount:I
  #34 = Utf8               testsFailedCount_$eq
  #35 = NameAndType        #18:#16        // testsIgnoredCount:I
  #36 = Fieldref           #2.#35         // org/scalatest/DispatchReporter$Propagator$Counter$1.testsIgnoredCount:I
  #37 = Utf8               testsIgnoredCount_$eq
  #38 = NameAndType        #19:#16        // testsCanceledCount:I
  #39 = Fieldref           #2.#38         // org/scalatest/DispatchReporter$Propagator$Counter$1.testsCanceledCount:I
  #40 = Utf8               testsCanceledCount_$eq
  #41 = NameAndType        #20:#16        // testsPendingCount:I
  #42 = Fieldref           #2.#41         // org/scalatest/DispatchReporter$Propagator$Counter$1.testsPendingCount:I
  #43 = Utf8               testsPendingCount_$eq
  #44 = NameAndType        #21:#16        // suitesCompletedCount:I
  #45 = Fieldref           #2.#44         // org/scalatest/DispatchReporter$Propagator$Counter$1.suitesCompletedCount:I
  #46 = Utf8               suitesCompletedCount_$eq
  #47 = NameAndType        #22:#16        // suitesAbortedCount:I
  #48 = Fieldref           #2.#47         // org/scalatest/DispatchReporter$Propagator$Counter$1.suitesAbortedCount:I
  #49 = Utf8               suitesAbortedCount_$eq
  #50 = NameAndType        #23:#16        // scopesPendingCount:I
  #51 = Fieldref           #2.#50         // org/scalatest/DispatchReporter$Propagator$Counter$1.scopesPendingCount:I
  #52 = Utf8               scopesPendingCount_$eq
  #53 = Utf8               <init>
  #54 = Utf8               (Lorg/scalatest/DispatchReporter$Propagator;)V
  #55 = Utf8               $outer
  #56 = NameAndType        #53:#9         // "<init>":()V
  #57 = Methodref          #4.#56         // java/lang/Object."<init>":()V
  #58 = Utf8               Lorg/scalatest/DispatchReporter$Propagator;
  #59 = Utf8               Code
  #60 = Utf8               LineNumberTable
  #61 = Utf8               LocalVariableTable
  #62 = Utf8               MethodParameters
  #63 = Utf8               InnerClasses
  #64 = Utf8               EnclosingMethod
  #65 = Utf8               SourceFile
  #66 = Utf8               ScalaInlineInfo
  #67 = Utf8               Scala
{
  private int testsSucceededCount;
    descriptor: I
    flags: (0x0002) ACC_PRIVATE

  private int testsFailedCount;
    descriptor: I
    flags: (0x0002) ACC_PRIVATE

  private int testsIgnoredCount;
    descriptor: I
    flags: (0x0002) ACC_PRIVATE

  private int testsCanceledCount;
    descriptor: I
    flags: (0x0002) ACC_PRIVATE

  private int testsPendingCount;
    descriptor: I
    flags: (0x0002) ACC_PRIVATE

  private int suitesCompletedCount;
    descriptor: I
    flags: (0x0002) ACC_PRIVATE

  private int suitesAbortedCount;
    descriptor: I
    flags: (0x0002) ACC_PRIVATE

  private int scopesPendingCount;
    descriptor: I
    flags: (0x0002) ACC_PRIVATE

  public int testsSucceededCount();
    descriptor: ()I
    flags: (0x0001) ACC_PUBLIC
    Code:
      stack=1, locals=1, args_size=1
         0: aload_0
         1: getfield      #26                 // Field testsSucceededCount:I
         4: ireturn
      LineNumberTable:
        line 116: 0
      LocalVariableTable:
        Start  Length  Slot  Name   Signature
            0       5     0  this   Lorg/scalatest/DispatchReporter$Propagator$Counter$1;

  public void testsSucceededCount_$eq(int);
    descriptor: (I)V
    flags: (0x0001) ACC_PUBLIC
    Code:
      stack=2, locals=2, args_size=2
         0: aload_0
         1: iload_1
         2: putfield      #26                 // Field testsSucceededCount:I
         5: return
      LineNumberTable:
        line 116: 0
      LocalVariableTable:
        Start  Length  Slot  Name   Signature
            0       6     0  this   Lorg/scalatest/DispatchReporter$Propagator$Counter$1;
            0       6     1   x$1   I
    MethodParameters:
      Name                           Flags
      x$1                            final

  public int testsFailedCount();
    descriptor: ()I
    flags: (0x0001) ACC_PUBLIC
    Code:
      stack=1, locals=1, args_size=1
         0: aload_0
         1: getfield      #33                 // Field testsFailedCount:I
         4: ireturn
      LineNumberTable:
        line 117: 0
      LocalVariableTable:
        Start  Length  Slot  Name   Signature
            0       5     0  this   Lorg/scalatest/DispatchReporter$Propagator$Counter$1;

  public void testsFailedCount_$eq(int);
    descriptor: (I)V
    flags: (0x0001) ACC_PUBLIC
    Code:
      stack=2, locals=2, args_size=2
         0: aload_0
         1: iload_1
         2: putfield      #33                 // Field testsFailedCount:I
         5: return
      LineNumberTable:
        line 117: 0
      LocalVariableTable:
        Start  Length  Slot  Name   Signature
            0       6     0  this   Lorg/scalatest/DispatchReporter$Propagator$Counter$1;
            0       6     1   x$1   I
    MethodParameters:
      Name                           Flags
      x$1                            final

  public int testsIgnoredCount();
    descriptor: ()I
    flags: (0x0001) ACC_PUBLIC
    Code:
      stack=1, locals=1, args_size=1
         0: aload_0
         1: getfield      #36                 // Field testsIgnoredCount:I
         4: ireturn
      LineNumberTable:
        line 118: 0
      LocalVariableTable:
        Start  Length  Slot  Name   Signature
            0       5     0  this   Lorg/scalatest/DispatchReporter$Propagator$Counter$1;

  public void testsIgnoredCount_$eq(int);
    descriptor: (I)V
    flags: (0x0001) ACC_PUBLIC
    Code:
      stack=2, locals=2, args_size=2
         0: aload_0
         1: iload_1
         2: putfield      #36                 // Field testsIgnoredCount:I
         5: return
      LineNumberTable:
        line 118: 0
      LocalVariableTable:
        Start  Length  Slot  Name   Signature
            0       6     0  this   Lorg/scalatest/DispatchReporter$Propagator$Counter$1;
            0       6     1   x$1   I
    MethodParameters:
      Name                           Flags
      x$1                            final

  public int testsCanceledCount();
    descriptor: ()I
    flags: (0x0001) ACC_PUBLIC
    Code:
      stack=1, locals=1, args_size=1
         0: aload_0
         1: getfield      #39                 // Field testsCanceledCount:I
         4: ireturn
      LineNumberTable:
        line 119: 0
      LocalVariableTable:
        Start  Length  Slot  Name   Signature
            0       5     0  this   Lorg/scalatest/DispatchReporter$Propagator$Counter$1;

  public void testsCanceledCount_$eq(int);
    descriptor: (I)V
    flags: (0x0001) ACC_PUBLIC
    Code:
      stack=2, locals=2, args_size=2
         0: aload_0
         1: iload_1
         2: putfield      #39                 // Field testsCanceledCount:I
         5: return
      LineNumberTable:
        line 119: 0
      LocalVariableTable:
        Start  Length  Slot  Name   Signature
            0       6     0  this   Lorg/scalatest/DispatchReporter$Propagator$Counter$1;
            0       6     1   x$1   I
    MethodParameters:
      Name                           Flags
      x$1                            final

  public int testsPendingCount();
    descriptor: ()I
    flags: (0x0001) ACC_PUBLIC
    Code:
      stack=1, locals=1, args_size=1
         0: aload_0
         1: getfield      #42                 // Field testsPendingCount:I
         4: ireturn
      LineNumberTable:
        line 120: 0
      LocalVariableTable:
        Start  Length  Slot  Name   Signature
            0       5     0  this   Lorg/scalatest/DispatchReporter$Propagator$Counter$1;

  public void testsPendingCount_$eq(int);
    descriptor: (I)V
    flags: (0x0001) ACC_PUBLIC
    Code:
      stack=2, locals=2, args_size=2
         0: aload_0
         1: iload_1
         2: putfield      #42                 // Field testsPendingCount:I
         5: return
      LineNumberTable:
        line 120: 0
      LocalVariableTable:
        Start  Length  Slot  Name   Signature
            0       6     0  this   Lorg/scalatest/DispatchReporter$Propagator$Counter$1;
            0       6     1   x$1   I
    MethodParameters:
      Name                           Flags
      x$1                            final

  public int suitesCompletedCount();
    descriptor: ()I
    flags: (0x0001) ACC_PUBLIC
    Code:
      stack=1, locals=1, args_size=1
         0: aload_0
         1: getfield      #45                 // Field suitesCompletedCount:I
         4: ireturn
      LineNumberTable:
        line 121: 0
      LocalVariableTable:
        Start  Length  Slot  Name   Signature
            0       5     0  this   Lorg/scalatest/DispatchReporter$Propagator$Counter$1;

  public void suitesCompletedCount_$eq(int);
    descriptor: (I)V
    flags: (0x0001) ACC_PUBLIC
    Code:
      stack=2, locals=2, args_size=2
         0: aload_0
         1: iload_1
         2: putfield      #45                 // Field suitesCompletedCount:I
         5: return
      LineNumberTable:
        line 121: 0
      LocalVariableTable:
        Start  Length  Slot  Name   Signature
            0       6     0  this   Lorg/scalatest/DispatchReporter$Propagator$Counter$1;
            0       6     1   x$1   I
    MethodParameters:
      Name                           Flags
      x$1                            final

  public int suitesAbortedCount();
    descriptor: ()I
    flags: (0x0001) ACC_PUBLIC
    Code:
      stack=1, locals=1, args_size=1
         0: aload_0
         1: getfield      #48                 // Field suitesAbortedCount:I
         4: ireturn
      LineNumberTable:
        line 122: 0
      LocalVariableTable:
        Start  Length  Slot  Name   Signature
            0       5     0  this   Lorg/scalatest/DispatchReporter$Propagator$Counter$1;

  public void suitesAbortedCount_$eq(int);
    descriptor: (I)V
    flags: (0x0001) ACC_PUBLIC
    Code:
      stack=2, locals=2, args_size=2
         0: aload_0
         1: iload_1
         2: putfield      #48                 // Field suitesAbortedCount:I
         5: return
      LineNumberTable:
        line 122: 0
      LocalVariableTable:
        Start  Length  Slot  Name   Signature
            0       6     0  this   Lorg/scalatest/DispatchReporter$Propagator$Counter$1;
            0       6     1   x$1   I
    MethodParameters:
      Name                           Flags
      x$1                            final

  public int scopesPendingCount();
    descriptor: ()I
    flags: (0x0001) ACC_PUBLIC
    Code:
      stack=1, locals=1, args_size=1
         0: aload_0
         1: getfield      #51                 // Field scopesPendingCount:I
         4: ireturn
      LineNumberTable:
        line 123: 0
      LocalVariableTable:
        Start  Length  Slot  Name   Signature
            0       5     0  this   Lorg/scalatest/DispatchReporter$Propagator$Counter$1;

  public void scopesPendingCount_$eq(int);
    descriptor: (I)V
    flags: (0x0001) ACC_PUBLIC
    Code:
      stack=2, locals=2, args_size=2
         0: aload_0
         1: iload_1
         2: putfield      #51                 // Field scopesPendingCount:I
         5: return
      LineNumberTable:
        line 123: 0
      LocalVariableTable:
        Start  Length  Slot  Name   Signature
            0       6     0  this   Lorg/scalatest/DispatchReporter$Propagator$Counter$1;
            0       6     1   x$1   I
    MethodParameters:
      Name                           Flags
      x$1                            final

  public org.scalatest.DispatchReporter$Propagator$Counter$1(org.scalatest.DispatchReporter$Propagator);
    descriptor: (Lorg/scalatest/DispatchReporter$Propagator;)V
    flags: (0x0001) ACC_PUBLIC
    Code:
      stack=2, locals=2, args_size=2
         0: aload_0
         1: invokespecial #57                 // Method java/lang/Object."<init>":()V
         4: aload_0
         5: iconst_0
         6: putfield      #26                 // Field testsSucceededCount:I
         9: aload_0
        10: iconst_0
        11: putfield      #33                 // Field testsFailedCount:I
        14: aload_0
        15: iconst_0
        16: putfield      #36                 // Field testsIgnoredCount:I
        19: aload_0
        20: iconst_0
        21: putfield      #39                 // Field testsCanceledCount:I
        24: aload_0
        25: iconst_0
        26: putfield      #42                 // Field testsPendingCount:I
        29: aload_0
        30: iconst_0
        31: putfield      #45                 // Field suitesCompletedCount:I
        34: aload_0
        35: iconst_0
        36: putfield      #48                 // Field suitesAbortedCount:I
        39: aload_0
        40: iconst_0
        41: putfield      #51                 // Field scopesPendingCount:I
        44: return
      LineNumberTable:
        line 126: 0
        line 116: 4
        line 117: 9
        line 118: 14
        line 119: 19
        line 120: 24
        line 121: 29
        line 122: 34
        line 123: 39
        line 115: 44
      LocalVariableTable:
        Start  Length  Slot  Name   Signature
            0      45     0  this   Lorg/scalatest/DispatchReporter$Propagator$Counter$1;
            0      45     1 $outer   Lorg/scalatest/DispatchReporter$Propagator;
    MethodParameters:
      Name                           Flags
      $outer                         final synthetic
}
InnerClasses:
  public #13= #7 of #12;                  // Propagator=class org/scalatest/DispatchReporter$Propagator of class org/scalatest/DispatchReporter
  public #14= #2;                         // Counter$1=class org/scalatest/DispatchReporter$Propagator$Counter$1
EnclosingMethod: #7.#10                 // org.scalatest.DispatchReporter$Propagator.run
SourceFile: "DispatchReporter.scala"
  ScalaInlineInfo: length = 0x59 (unknown attribute)
   01 01 00 11 00 35 00 36 01 00 17 00 18 01 00 34
   00 1E 01 00 16 00 18 01 00 31 00 1E 01 00 15 00
   18 01 00 2E 00 1E 01 00 13 00 18 01 00 28 00 1E
   01 00 11 00 18 01 00 22 00 1E 01 00 12 00 18 01
   00 25 00 1E 01 00 14 00 18 01 00 2B 00 1E 01 00
   0F 00 18 01 00 1D 00 1E 01
  Scala: length = 0x0 (unknown attribute)

