Classfile /Users/mw/Projects/slang-braindump/.jar/jar11/assemble/slang-braindump/assemble/content/org/scalatest/Doc$.class
  Last modified May 29, 2022; size 6046 bytes
  SHA-256 checksum 341b1d9276cfac25ee8d54f7bbcdd2c60f86b2edb028fcff8457ea0ea2ac33b0
  Compiled from "Doc.scala"
public final class org.scalatest.Doc$ implements java.io.Serializable
  minor version: 0
  major version: 52
  flags: (0x0031) ACC_PUBLIC, ACC_FINAL, ACC_SUPER
  this_class: #2                          // org/scalatest/Doc$
  super_class: #4                         // java/lang/Object
  interfaces: 1, fields: 1, methods: 15, attributes: 5
Constant pool:
    #1 = Utf8               org/scalatest/Doc$
    #2 = Class              #1            // org/scalatest/Doc$
    #3 = Utf8               java/lang/Object
    #4 = Class              #3            // java/lang/Object
    #5 = Utf8               java/io/Serializable
    #6 = Class              #5            // java/io/Serializable
    #7 = Utf8               Doc.scala
    #8 = Utf8               java/lang/invoke/MethodHandles$Lookup
    #9 = Class              #8            // java/lang/invoke/MethodHandles$Lookup
   #10 = Utf8               java/lang/invoke/MethodHandles
   #11 = Class              #10           // java/lang/invoke/MethodHandles
   #12 = Utf8               Lookup
   #13 = Utf8               MODULE$
   #14 = Utf8               Lorg/scalatest/Doc$;
   #15 = Utf8               <clinit>
   #16 = Utf8               ()V
   #17 = Utf8               <init>
   #18 = NameAndType        #17:#16       // "<init>":()V
   #19 = Methodref          #2.#18        // org/scalatest/Doc$."<init>":()V
   #20 = NameAndType        #13:#14       // MODULE$:Lorg/scalatest/Doc$;
   #21 = Fieldref           #2.#20        // org/scalatest/Doc$.MODULE$:Lorg/scalatest/Doc$;
   #22 = Utf8               trimMarkup
   #23 = Utf8               (Ljava/lang/String;)Ljava/lang/String;
   #24 = Utf8               text
   #25 = Utf8               scala/collection/StringOps$
   #26 = Class              #25           // scala/collection/StringOps$
   #27 = Utf8               Lscala/collection/StringOps$;
   #28 = NameAndType        #13:#27       // MODULE$:Lscala/collection/StringOps$;
   #29 = Fieldref           #26.#28       // scala/collection/StringOps$.MODULE$:Lscala/collection/StringOps$;
   #30 = Utf8               scala/Predef$
   #31 = Class              #30           // scala/Predef$
   #32 = Utf8               Lscala/Predef$;
   #33 = NameAndType        #13:#32       // MODULE$:Lscala/Predef$;
   #34 = Fieldref           #31.#33       // scala/Predef$.MODULE$:Lscala/Predef$;
   #35 = Utf8               augmentString
   #36 = NameAndType        #35:#23       // augmentString:(Ljava/lang/String;)Ljava/lang/String;
   #37 = Methodref          #31.#36       // scala/Predef$.augmentString:(Ljava/lang/String;)Ljava/lang/String;
   #38 = Utf8               linesIterator$extension
   #39 = Utf8               (Ljava/lang/String;)Lscala/collection/Iterator;
   #40 = NameAndType        #38:#39       // linesIterator$extension:(Ljava/lang/String;)Lscala/collection/Iterator;
   #41 = Methodref          #26.#40       // scala/collection/StringOps$.linesIterator$extension:(Ljava/lang/String;)Lscala/collection/Iterator;
   #42 = Utf8               scala/collection/Iterator
   #43 = Class              #42           // scala/collection/Iterator
   #44 = Utf8               toList
   #45 = Utf8               ()Lscala/collection/immutable/List;
   #46 = NameAndType        #44:#45       // toList:()Lscala/collection/immutable/List;
   #47 = InterfaceMethodref #43.#46       // scala/collection/Iterator.toList:()Lscala/collection/immutable/List;
   #48 = Utf8               scala/collection/immutable/List
   #49 = Class              #48           // scala/collection/immutable/List
   #50 = Utf8               zipWithIndex
   #51 = Utf8               ()Ljava/lang/Object;
   #52 = NameAndType        #50:#51       // zipWithIndex:()Ljava/lang/Object;
   #53 = Methodref          #49.#52       // scala/collection/immutable/List.zipWithIndex:()Ljava/lang/Object;
   #54 = Utf8               (Ljava/lang/Object;)Ljava/lang/Object;
   #55 = MethodType         #54           //  (Ljava/lang/Object;)Ljava/lang/Object;
   #56 = Utf8               $anonfun$trimMarkup$1$adapted
   #57 = Utf8               (Lscala/Tuple2;)Ljava/lang/Object;
   #58 = NameAndType        #56:#57       // $anonfun$trimMarkup$1$adapted:(Lscala/Tuple2;)Ljava/lang/Object;
   #59 = Methodref          #2.#58        // org/scalatest/Doc$.$anonfun$trimMarkup$1$adapted:(Lscala/Tuple2;)Ljava/lang/Object;
   #60 = MethodHandle       6:#59         // REF_invokeStatic org/scalatest/Doc$.$anonfun$trimMarkup$1$adapted:(Lscala/Tuple2;)Ljava/lang/Object;
   #61 = MethodType         #57           //  (Lscala/Tuple2;)Ljava/lang/Object;
   #62 = Integer            5
   #63 = Integer            1
   #64 = Utf8               java/lang/invoke/LambdaMetafactory
   #65 = Class              #64           // java/lang/invoke/LambdaMetafactory
   #66 = Utf8               altMetafactory
   #67 = Utf8               (Ljava/lang/invoke/MethodHandles$Lookup;Ljava/lang/String;Ljava/lang/invoke/MethodType;[Ljava/lang/Object;)Ljava/lang/invoke/CallSite;
   #68 = NameAndType        #66:#67       // altMetafactory:(Ljava/lang/invoke/MethodHandles$Lookup;Ljava/lang/String;Ljava/lang/invoke/MethodType;[Ljava/lang/Object;)Ljava/lang/invoke/CallSite;
   #69 = Methodref          #65.#68       // java/lang/invoke/LambdaMetafactory.altMetafactory:(Ljava/lang/invoke/MethodHandles$Lookup;Ljava/lang/String;Ljava/lang/invoke/MethodType;[Ljava/lang/Object;)Ljava/lang/invoke/CallSite;
   #70 = MethodHandle       6:#69         // REF_invokeStatic java/lang/invoke/LambdaMetafactory.altMetafactory:(Ljava/lang/invoke/MethodHandles$Lookup;Ljava/lang/String;Ljava/lang/invoke/MethodType;[Ljava/lang/Object;)Ljava/lang/invoke/CallSite;
   #71 = Utf8               apply
   #72 = Utf8               ()Lscala/Function1;
   #73 = NameAndType        #71:#72       // apply:()Lscala/Function1;
   #74 = InvokeDynamic      #0:#73        // #0:apply:()Lscala/Function1;
   #75 = Utf8               find
   #76 = Utf8               (Lscala/Function1;)Lscala/Option;
   #77 = NameAndType        #75:#76       // find:(Lscala/Function1;)Lscala/Option;
   #78 = Methodref          #49.#77       // scala/collection/immutable/List.find:(Lscala/Function1;)Lscala/Option;
   #79 = Utf8               reverse
   #80 = NameAndType        #79:#45       // reverse:()Lscala/collection/immutable/List;
   #81 = Methodref          #49.#80       // scala/collection/immutable/List.reverse:()Lscala/collection/immutable/List;
   #82 = Utf8               $anonfun$trimMarkup$2$adapted
   #83 = NameAndType        #82:#57       // $anonfun$trimMarkup$2$adapted:(Lscala/Tuple2;)Ljava/lang/Object;
   #84 = Methodref          #2.#83        // org/scalatest/Doc$.$anonfun$trimMarkup$2$adapted:(Lscala/Tuple2;)Ljava/lang/Object;
   #85 = MethodHandle       6:#84         // REF_invokeStatic org/scalatest/Doc$.$anonfun$trimMarkup$2$adapted:(Lscala/Tuple2;)Ljava/lang/Object;
   #86 = InvokeDynamic      #1:#73        // #1:apply:()Lscala/Function1;
   #87 = Utf8               scala/Tuple2
   #88 = Class              #87           // scala/Tuple2
   #89 = Utf8               (Ljava/lang/Object;Ljava/lang/Object;)V
   #90 = NameAndType        #17:#89       // "<init>":(Ljava/lang/Object;Ljava/lang/Object;)V
   #91 = Methodref          #88.#90       // scala/Tuple2."<init>":(Ljava/lang/Object;Ljava/lang/Object;)V
   #92 = Utf8               _1
   #93 = NameAndType        #92:#51       // _1:()Ljava/lang/Object;
   #94 = Methodref          #88.#93       // scala/Tuple2._1:()Ljava/lang/Object;
   #95 = Utf8               scala/Option
   #96 = Class              #95           // scala/Option
   #97 = Utf8               _2
   #98 = NameAndType        #97:#51       // _2:()Ljava/lang/Object;
   #99 = Methodref          #88.#98       // scala/Tuple2._2:()Ljava/lang/Object;
  #100 = Utf8               scala/None$
  #101 = Class              #100          // scala/None$
  #102 = Utf8               Lscala/None$;
  #103 = NameAndType        #13:#102      // MODULE$:Lscala/None$;
  #104 = Fieldref           #101.#103     // scala/None$.MODULE$:Lscala/None$;
  #105 = Utf8               equals
  #106 = Utf8               (Ljava/lang/Object;)Z
  #107 = NameAndType        #105:#106     // equals:(Ljava/lang/Object;)Z
  #108 = Methodref          #4.#107       // java/lang/Object.equals:(Ljava/lang/Object;)Z
  #109 = Utf8               java/lang/String
  #110 = Class              #109          // java/lang/String
  #111 = Utf8               trim
  #112 = Utf8               ()Ljava/lang/String;
  #113 = NameAndType        #111:#112     // trim:()Ljava/lang/String;
  #114 = Methodref          #110.#113     // java/lang/String.trim:()Ljava/lang/String;
  #115 = Utf8               scala/Some
  #116 = Class              #115          // scala/Some
  #117 = Utf8               value
  #118 = NameAndType        #117:#51      // value:()Ljava/lang/Object;
  #119 = Methodref          #116.#118     // scala/Some.value:()Ljava/lang/Object;
  #120 = Utf8               _2$mcI$sp
  #121 = Utf8               ()I
  #122 = NameAndType        #120:#121     // _2$mcI$sp:()I
  #123 = Methodref          #88.#122      // scala/Tuple2._2$mcI$sp:()I
  #124 = Utf8               take
  #125 = Utf8               (I)Lscala/collection/immutable/List;
  #126 = NameAndType        #124:#125     // take:(I)Lscala/collection/immutable/List;
  #127 = Methodref          #49.#126      // scala/collection/immutable/List.take:(I)Lscala/collection/immutable/List;
  #128 = Utf8               drop
  #129 = Utf8               (I)Lscala/collection/LinearSeq;
  #130 = NameAndType        #128:#129     // drop:(I)Lscala/collection/LinearSeq;
  #131 = Methodref          #49.#130      // scala/collection/immutable/List.drop:(I)Lscala/collection/LinearSeq;
  #132 = Utf8               \n
  #133 = String             #132          // \n
  #134 = Utf8               scala/collection/LinearSeq
  #135 = Class              #134          // scala/collection/LinearSeq
  #136 = Utf8               mkString
  #137 = NameAndType        #136:#23      // mkString:(Ljava/lang/String;)Ljava/lang/String;
  #138 = InterfaceMethodref #135.#137     // scala/collection/LinearSeq.mkString:(Ljava/lang/String;)Ljava/lang/String;
  #139 = Utf8               scala/MatchError
  #140 = Class              #139          // scala/MatchError
  #141 = Utf8               (Ljava/lang/Object;)V
  #142 = NameAndType        #17:#141      // "<init>":(Ljava/lang/Object;)V
  #143 = Methodref          #140.#142     // scala/MatchError."<init>":(Ljava/lang/Object;)V
  #144 = Utf8               backIdx
  #145 = Utf8               I
  #146 = Utf8               frontIdx
  #147 = Utf8               lines
  #148 = Utf8               Lscala/collection/immutable/List;
  #149 = Utf8               zipLines
  #150 = Utf8               firstNonWhiteLine
  #151 = Utf8               Lscala/Option;
  #152 = Utf8               lastNonWhiteLine
  #153 = Utf8               this
  #154 = Utf8               Ljava/lang/String;
  #155 = Utf8               stripMargin
  #156 = Utf8               $anonfun$stripMargin$1$adapted
  #157 = Utf8               (Ljava/lang/String;)Ljava/lang/Object;
  #158 = NameAndType        #156:#157     // $anonfun$stripMargin$1$adapted:(Ljava/lang/String;)Ljava/lang/Object;
  #159 = Methodref          #2.#158       // org/scalatest/Doc$.$anonfun$stripMargin$1$adapted:(Ljava/lang/String;)Ljava/lang/Object;
  #160 = MethodHandle       6:#159        // REF_invokeStatic org/scalatest/Doc$.$anonfun$stripMargin$1$adapted:(Ljava/lang/String;)Ljava/lang/Object;
  #161 = MethodType         #157          //  (Ljava/lang/String;)Ljava/lang/Object;
  #162 = InvokeDynamic      #2:#73        // #2:apply:()Lscala/Function1;
  #163 = Utf8               $anonfun$stripMargin$2$adapted
  #164 = NameAndType        #163:#54      // $anonfun$stripMargin$2$adapted:(Ljava/lang/Object;)Ljava/lang/Object;
  #165 = Methodref          #2.#164       // org/scalatest/Doc$.$anonfun$stripMargin$2$adapted:(Ljava/lang/Object;)Ljava/lang/Object;
  #166 = MethodHandle       6:#165        // REF_invokeStatic org/scalatest/Doc$.$anonfun$stripMargin$2$adapted:(Ljava/lang/Object;)Ljava/lang/Object;
  #167 = InvokeDynamic      #3:#73        // #3:apply:()Lscala/Function1;
  #168 = Utf8               dropWhile$extension
  #169 = Utf8               (Ljava/lang/String;Lscala/Function1;)Ljava/lang/String;
  #170 = NameAndType        #168:#169     // dropWhile$extension:(Ljava/lang/String;Lscala/Function1;)Ljava/lang/String;
  #171 = Methodref          #26.#170      // scala/collection/StringOps$.dropWhile$extension:(Ljava/lang/String;Lscala/Function1;)Ljava/lang/String;
  #172 = Utf8               length
  #173 = NameAndType        #172:#121     // length:()I
  #174 = Methodref          #110.#173     // java/lang/String.length:()I
  #175 = Utf8               $anonfun$stripMargin$3
  #176 = Utf8               (ILjava/lang/String;)Ljava/lang/String;
  #177 = NameAndType        #175:#176     // $anonfun$stripMargin$3:(ILjava/lang/String;)Ljava/lang/String;
  #178 = Methodref          #2.#177       // org/scalatest/Doc$.$anonfun$stripMargin$3:(ILjava/lang/String;)Ljava/lang/String;
  #179 = MethodHandle       6:#178        // REF_invokeStatic org/scalatest/Doc$.$anonfun$stripMargin$3:(ILjava/lang/String;)Ljava/lang/String;
  #180 = MethodType         #23           //  (Ljava/lang/String;)Ljava/lang/String;
  #181 = Utf8               (I)Lscala/Function1;
  #182 = NameAndType        #71:#181      // apply:(I)Lscala/Function1;
  #183 = InvokeDynamic      #4:#182       // #4:apply:(I)Lscala/Function1;
  #184 = Utf8               map
  #185 = Utf8               (Lscala/Function1;)Lscala/collection/immutable/List;
  #186 = NameAndType        #184:#185     // map:(Lscala/Function1;)Lscala/collection/immutable/List;
  #187 = Methodref          #49.#186      // scala/collection/immutable/List.map:(Lscala/Function1;)Lscala/collection/immutable/List;
  #188 = Methodref          #49.#137      // scala/collection/immutable/List.mkString:(Ljava/lang/String;)Ljava/lang/String;
  #189 = Utf8               initialWhite
  #190 = Utf8               margin
  #191 = Utf8               choppedLines
  #192 = Utf8               nonWhiteLine
  #193 = Utf8               writeReplace
  #194 = Utf8               scala/runtime/ModuleSerializationProxy
  #195 = Class              #194          // scala/runtime/ModuleSerializationProxy
  #196 = Utf8               (Ljava/lang/Class;)V
  #197 = NameAndType        #17:#196      // "<init>":(Ljava/lang/Class;)V
  #198 = Methodref          #195.#197     // scala/runtime/ModuleSerializationProxy."<init>":(Ljava/lang/Class;)V
  #199 = Utf8               $anonfun$trimMarkup$1
  #200 = Utf8               (Lscala/Tuple2;)Z
  #201 = Utf8               x0$1
  #202 = Utf8               isEmpty
  #203 = Utf8               ()Z
  #204 = NameAndType        #202:#203     // isEmpty:()Z
  #205 = Methodref          #110.#204     // java/lang/String.isEmpty:()Z
  #206 = Utf8               line
  #207 = Utf8               Lscala/Tuple2;
  #208 = Utf8               $anonfun$trimMarkup$2
  #209 = Utf8               x0$2
  #210 = Utf8               $anonfun$stripMargin$1
  #211 = Utf8               (Ljava/lang/String;)Z
  #212 = Utf8               x$3
  #213 = Utf8               $anonfun$stripMargin$2
  #214 = Utf8               (C)Z
  #215 = Utf8               x$4
  #216 = Utf8               scala/runtime/RichChar$
  #217 = Class              #216          // scala/runtime/RichChar$
  #218 = Utf8               Lscala/runtime/RichChar$;
  #219 = NameAndType        #13:#218      // MODULE$:Lscala/runtime/RichChar$;
  #220 = Fieldref           #217.#219     // scala/runtime/RichChar$.MODULE$:Lscala/runtime/RichChar$;
  #221 = Utf8               charWrapper
  #222 = Utf8               (C)C
  #223 = NameAndType        #221:#222     // charWrapper:(C)C
  #224 = Methodref          #31.#223      // scala/Predef$.charWrapper:(C)C
  #225 = Utf8               isWhitespace$extension
  #226 = NameAndType        #225:#214     // isWhitespace$extension:(C)Z
  #227 = Methodref          #217.#226     // scala/runtime/RichChar$.isWhitespace$extension:(C)Z
  #228 = Utf8               C
  #229 = Utf8               margin$1
  #230 = Utf8               substring
  #231 = Utf8               (I)Ljava/lang/String;
  #232 = NameAndType        #230:#231     // substring:(I)Ljava/lang/String;
  #233 = Methodref          #110.#232     // java/lang/String.substring:(I)Ljava/lang/String;
  #234 = Utf8               strip
  #235 = Methodref          #4.#18        // java/lang/Object."<init>":()V
  #236 = NameAndType        #199:#200     // $anonfun$trimMarkup$1:(Lscala/Tuple2;)Z
  #237 = Methodref          #2.#236       // org/scalatest/Doc$.$anonfun$trimMarkup$1:(Lscala/Tuple2;)Z
  #238 = Utf8               scala/runtime/BoxesRunTime
  #239 = Class              #238          // scala/runtime/BoxesRunTime
  #240 = Utf8               boxToBoolean
  #241 = Utf8               (Z)Ljava/lang/Boolean;
  #242 = NameAndType        #240:#241     // boxToBoolean:(Z)Ljava/lang/Boolean;
  #243 = Methodref          #239.#242     // scala/runtime/BoxesRunTime.boxToBoolean:(Z)Ljava/lang/Boolean;
  #244 = NameAndType        #208:#200     // $anonfun$trimMarkup$2:(Lscala/Tuple2;)Z
  #245 = Methodref          #2.#244       // org/scalatest/Doc$.$anonfun$trimMarkup$2:(Lscala/Tuple2;)Z
  #246 = NameAndType        #210:#211     // $anonfun$stripMargin$1:(Ljava/lang/String;)Z
  #247 = Methodref          #2.#246       // org/scalatest/Doc$.$anonfun$stripMargin$1:(Ljava/lang/String;)Z
  #248 = Utf8               unboxToChar
  #249 = Utf8               (Ljava/lang/Object;)C
  #250 = NameAndType        #248:#249     // unboxToChar:(Ljava/lang/Object;)C
  #251 = Methodref          #239.#250     // scala/runtime/BoxesRunTime.unboxToChar:(Ljava/lang/Object;)C
  #252 = NameAndType        #213:#214     // $anonfun$stripMargin$2:(C)Z
  #253 = Methodref          #2.#252       // org/scalatest/Doc$.$anonfun$stripMargin$2:(C)Z
  #254 = Utf8               Ljava/lang/Object;
  #255 = Utf8               $deserializeLambda$
  #256 = Utf8               (Ljava/lang/invoke/SerializedLambda;)Ljava/lang/Object;
  #257 = Utf8               scala/runtime/LambdaDeserialize
  #258 = Class              #257          // scala/runtime/LambdaDeserialize
  #259 = Utf8               bootstrap
  #260 = Utf8               (Ljava/lang/invoke/MethodHandles$Lookup;Ljava/lang/String;Ljava/lang/invoke/MethodType;[Ljava/lang/invoke/MethodHandle;)Ljava/lang/invoke/CallSite;
  #261 = NameAndType        #259:#260     // bootstrap:(Ljava/lang/invoke/MethodHandles$Lookup;Ljava/lang/String;Ljava/lang/invoke/MethodType;[Ljava/lang/invoke/MethodHandle;)Ljava/lang/invoke/CallSite;
  #262 = Methodref          #258.#261     // scala/runtime/LambdaDeserialize.bootstrap:(Ljava/lang/invoke/MethodHandles$Lookup;Ljava/lang/String;Ljava/lang/invoke/MethodType;[Ljava/lang/invoke/MethodHandle;)Ljava/lang/invoke/CallSite;
  #263 = MethodHandle       6:#262        // REF_invokeStatic scala/runtime/LambdaDeserialize.bootstrap:(Ljava/lang/invoke/MethodHandles$Lookup;Ljava/lang/String;Ljava/lang/invoke/MethodType;[Ljava/lang/invoke/MethodHandle;)Ljava/lang/invoke/CallSite;
  #264 = Utf8               lambdaDeserialize
  #265 = NameAndType        #264:#256     // lambdaDeserialize:(Ljava/lang/invoke/SerializedLambda;)Ljava/lang/Object;
  #266 = InvokeDynamic      #5:#265       // #5:lambdaDeserialize:(Ljava/lang/invoke/SerializedLambda;)Ljava/lang/Object;
  #267 = Utf8               Code
  #268 = Utf8               LineNumberTable
  #269 = Utf8               StackMapTable
  #270 = Utf8               LocalVariableTable
  #271 = Utf8               MethodParameters
  #272 = Utf8               InnerClasses
  #273 = Utf8               SourceFile
  #274 = Utf8               BootstrapMethods
  #275 = Utf8               ScalaInlineInfo
  #276 = Utf8               Scala
{
  public static final org.scalatest.Doc$ MODULE$;
    descriptor: Lorg/scalatest/Doc$;
    flags: (0x0019) ACC_PUBLIC, ACC_STATIC, ACC_FINAL

  public static {};
    descriptor: ()V
    flags: (0x0009) ACC_PUBLIC, ACC_STATIC
    Code:
      stack=2, locals=0, args_size=0
         0: new           #2                  // class org/scalatest/Doc$
         3: dup
         4: invokespecial #19                 // Method "<init>":()V
         7: putstatic     #21                 // Field MODULE$:Lorg/scalatest/Doc$;
        10: return
      LineNumberTable:
        line 186: 0

  public java.lang.String trimMarkup(java.lang.String);
    descriptor: (Ljava/lang/String;)Ljava/lang/String;
    flags: (0x0001) ACC_PUBLIC
    Code:
      stack=4, locals=18, args_size=2
         0: getstatic     #29                 // Field scala/collection/StringOps$.MODULE$:Lscala/collection/StringOps$;
         3: getstatic     #34                 // Field scala/Predef$.MODULE$:Lscala/Predef$;
         6: aload_1
         7: invokevirtual #37                 // Method scala/Predef$.augmentString:(Ljava/lang/String;)Ljava/lang/String;
        10: invokevirtual #41                 // Method scala/collection/StringOps$.linesIterator$extension:(Ljava/lang/String;)Lscala/collection/Iterator;
        13: invokeinterface #47,  1           // InterfaceMethod scala/collection/Iterator.toList:()Lscala/collection/immutable/List;
        18: astore_3
        19: aload_3
        20: invokevirtual #53                 // Method scala/collection/immutable/List.zipWithIndex:()Ljava/lang/Object;
        23: checkcast     #49                 // class scala/collection/immutable/List
        26: astore        4
        28: aload         4
        30: invokedynamic #74,  0             // InvokeDynamic #0:apply:()Lscala/Function1;
        35: invokevirtual #78                 // Method scala/collection/immutable/List.find:(Lscala/Function1;)Lscala/Option;
        38: astore        5
        40: aload         4
        42: invokevirtual #81                 // Method scala/collection/immutable/List.reverse:()Lscala/collection/immutable/List;
        45: invokedynamic #86,  0             // InvokeDynamic #1:apply:()Lscala/Function1;
        50: invokevirtual #78                 // Method scala/collection/immutable/List.find:(Lscala/Function1;)Lscala/Option;
        53: astore        6
        55: new           #88                 // class scala/Tuple2
        58: dup
        59: aload         5
        61: aload         6
        63: invokespecial #91                 // Method scala/Tuple2."<init>":(Ljava/lang/Object;Ljava/lang/Object;)V
        66: astore        7
        68: aload         7
        70: ifnull        126
        73: aload         7
        75: invokevirtual #94                 // Method scala/Tuple2._1:()Ljava/lang/Object;
        78: checkcast     #96                 // class scala/Option
        81: astore        8
        83: aload         7
        85: invokevirtual #99                 // Method scala/Tuple2._2:()Ljava/lang/Object;
        88: checkcast     #96                 // class scala/Option
        91: astore        9
        93: getstatic     #104                // Field scala/None$.MODULE$:Lscala/None$;
        96: aload         8
        98: invokevirtual #108                // Method java/lang/Object.equals:(Ljava/lang/Object;)Z
       101: ifeq          123
       104: getstatic     #104                // Field scala/None$.MODULE$:Lscala/None$;
       107: aload         9
       109: invokevirtual #108                // Method java/lang/Object.equals:(Ljava/lang/Object;)Z
       112: ifeq          123
       115: aload_1
       116: invokevirtual #114                // Method java/lang/String.trim:()Ljava/lang/String;
       119: astore_2
       120: goto          277
       123: goto          129
       126: goto          129
       129: aload         7
       131: ifnull        264
       134: aload         7
       136: invokevirtual #94                 // Method scala/Tuple2._1:()Ljava/lang/Object;
       139: checkcast     #96                 // class scala/Option
       142: astore        10
       144: aload         7
       146: invokevirtual #99                 // Method scala/Tuple2._2:()Ljava/lang/Object;
       149: checkcast     #96                 // class scala/Option
       152: astore        11
       154: aload         10
       156: instanceof    #116                // class scala/Some
       159: ifeq          261
       162: aload         10
       164: checkcast     #116                // class scala/Some
       167: astore        12
       169: aload         12
       171: invokevirtual #119                // Method scala/Some.value:()Ljava/lang/Object;
       174: checkcast     #88                 // class scala/Tuple2
       177: astore        13
       179: aload         13
       181: ifnull        258
       184: aload         13
       186: invokevirtual #123                // Method scala/Tuple2._2$mcI$sp:()I
       189: istore        14
       191: aload         11
       193: instanceof    #116                // class scala/Some
       196: ifeq          255
       199: aload         11
       201: checkcast     #116                // class scala/Some
       204: astore        15
       206: aload         15
       208: invokevirtual #119                // Method scala/Some.value:()Ljava/lang/Object;
       211: checkcast     #88                 // class scala/Tuple2
       214: astore        16
       216: aload         16
       218: ifnull        252
       221: aload         16
       223: invokevirtual #123                // Method scala/Tuple2._2$mcI$sp:()I
       226: istore        17
       228: aload_3
       229: iload         17
       231: iconst_1
       232: iadd
       233: invokevirtual #127                // Method scala/collection/immutable/List.take:(I)Lscala/collection/immutable/List;
       236: iload         14
       238: invokevirtual #131                // Method scala/collection/immutable/List.drop:(I)Lscala/collection/LinearSeq;
       241: ldc           #133                // String \n
       243: invokeinterface #138,  2          // InterfaceMethod scala/collection/LinearSeq.mkString:(Ljava/lang/String;)Ljava/lang/String;
       248: astore_2
       249: goto          277
       252: goto          267
       255: goto          267
       258: goto          267
       261: goto          267
       264: goto          267
       267: new           #140                // class scala/MatchError
       270: dup
       271: aload         7
       273: invokespecial #143                // Method scala/MatchError."<init>":(Ljava/lang/Object;)V
       276: athrow
       277: aload_2
       278: areturn
      StackMapTable: number_of_entries = 10
        frame_type = 255 /* full_frame */
          offset_delta = 123
          locals = [ class org/scalatest/Doc$, class java/lang/String, top, class scala/collection/immutable/List, class scala/collection/immutable/List, class scala/Option, class scala/Option, class scala/Tuple2, class scala/Option, class scala/Option ]
          stack = []
        frame_type = 249 /* chop */
          offset_delta = 2
        frame_type = 2 /* same */
        frame_type = 255 /* full_frame */
          offset_delta = 122
          locals = [ class org/scalatest/Doc$, class java/lang/String, top, class scala/collection/immutable/List, class scala/collection/immutable/List, class scala/Option, class scala/Option, class scala/Tuple2, top, top, class scala/Option, class scala/Option, class scala/Some, class scala/Tuple2, int, class scala/Some, class scala/Tuple2 ]
          stack = []
        frame_type = 249 /* chop */
          offset_delta = 2
        frame_type = 250 /* chop */
          offset_delta = 2
        frame_type = 249 /* chop */
          offset_delta = 2
        frame_type = 255 /* full_frame */
          offset_delta = 2
          locals = [ class org/scalatest/Doc$, class java/lang/String, top, class scala/collection/immutable/List, class scala/collection/immutable/List, class scala/Option, class scala/Option, class scala/Tuple2 ]
          stack = []
        frame_type = 2 /* same */
        frame_type = 255 /* full_frame */
          offset_delta = 9
          locals = [ class org/scalatest/Doc$, class java/lang/String, class java/lang/String, class scala/collection/immutable/List, class scala/collection/immutable/List, class scala/Option, class scala/Option, class scala/Tuple2 ]
          stack = []
      LineNumberTable:
        line 189: 0
        line 190: 19
        line 191: 28
        line 192: 40
        line 193: 55
        line 194: 68
        line 195: 129
        line 193: 267
      LocalVariableTable:
        Start  Length  Slot  Name   Signature
          228      24    17 backIdx   I
          191      67    14 frontIdx   I
           19     259     3 lines   Lscala/collection/immutable/List;
           28     250     4 zipLines   Lscala/collection/immutable/List;
           40     238     5 firstNonWhiteLine   Lscala/Option;
           55     223     6 lastNonWhiteLine   Lscala/Option;
            0     279     0  this   Lorg/scalatest/Doc$;
            0     279     1  text   Ljava/lang/String;
    MethodParameters:
      Name                           Flags
      text                           final

  public java.lang.String stripMargin(java.lang.String);
    descriptor: (Ljava/lang/String;)Ljava/lang/String;
    flags: (0x0001) ACC_PUBLIC
    Code:
      stack=3, locals=11, args_size=2
         0: getstatic     #29                 // Field scala/collection/StringOps$.MODULE$:Lscala/collection/StringOps$;
         3: getstatic     #34                 // Field scala/Predef$.MODULE$:Lscala/Predef$;
         6: aload_1
         7: invokevirtual #37                 // Method scala/Predef$.augmentString:(Ljava/lang/String;)Ljava/lang/String;
        10: invokevirtual #41                 // Method scala/collection/StringOps$.linesIterator$extension:(Ljava/lang/String;)Lscala/collection/Iterator;
        13: invokeinterface #47,  1           // InterfaceMethod scala/collection/Iterator.toList:()Lscala/collection/immutable/List;
        18: astore_3
        19: aload_3
        20: invokedynamic #162,  0            // InvokeDynamic #2:apply:()Lscala/Function1;
        25: invokevirtual #78                 // Method scala/collection/immutable/List.find:(Lscala/Function1;)Lscala/Option;
        28: astore        4
        30: aload         4
        32: astore        5
        34: getstatic     #104                // Field scala/None$.MODULE$:Lscala/None$;
        37: aload         5
        39: invokevirtual #108                // Method java/lang/Object.equals:(Ljava/lang/Object;)Z
        42: ifeq          53
        45: aload_1
        46: invokevirtual #114                // Method java/lang/String.trim:()Ljava/lang/String;
        49: astore_2
        50: goto          152
        53: goto          56
        56: aload         5
        58: instanceof    #116                // class scala/Some
        61: ifeq          139
        64: aload         5
        66: checkcast     #116                // class scala/Some
        69: astore        6
        71: aload         6
        73: invokevirtual #119                // Method scala/Some.value:()Ljava/lang/Object;
        76: checkcast     #110                // class java/lang/String
        79: astore        7
        81: getstatic     #29                 // Field scala/collection/StringOps$.MODULE$:Lscala/collection/StringOps$;
        84: getstatic     #34                 // Field scala/Predef$.MODULE$:Lscala/Predef$;
        87: aload         7
        89: invokevirtual #37                 // Method scala/Predef$.augmentString:(Ljava/lang/String;)Ljava/lang/String;
        92: invokedynamic #167,  0            // InvokeDynamic #3:apply:()Lscala/Function1;
        97: invokevirtual #171                // Method scala/collection/StringOps$.dropWhile$extension:(Ljava/lang/String;Lscala/Function1;)Ljava/lang/String;
       100: astore        8
       102: aload         7
       104: invokevirtual #174                // Method java/lang/String.length:()I
       107: aload         8
       109: invokevirtual #174                // Method java/lang/String.length:()I
       112: isub
       113: istore        9
       115: aload_3
       116: iload         9
       118: invokedynamic #183,  0            // InvokeDynamic #4:apply:(I)Lscala/Function1;
       123: invokevirtual #187                // Method scala/collection/immutable/List.map:(Lscala/Function1;)Lscala/collection/immutable/List;
       126: astore        10
       128: aload         10
       130: ldc           #133                // String \n
       132: invokevirtual #188                // Method scala/collection/immutable/List.mkString:(Ljava/lang/String;)Ljava/lang/String;
       135: astore_2
       136: goto          152
       139: goto          142
       142: new           #140                // class scala/MatchError
       145: dup
       146: aload         5
       148: invokespecial #143                // Method scala/MatchError."<init>":(Ljava/lang/Object;)V
       151: athrow
       152: aload_2
       153: areturn
      StackMapTable: number_of_entries = 5
        frame_type = 255 /* full_frame */
          offset_delta = 53
          locals = [ class org/scalatest/Doc$, class java/lang/String, top, class scala/collection/immutable/List, class scala/Option, class scala/Option ]
          stack = []
        frame_type = 2 /* same */
        frame_type = 251 /* same_frame_extended */
          offset_delta = 82
        frame_type = 2 /* same */
        frame_type = 255 /* full_frame */
          offset_delta = 9
          locals = [ class org/scalatest/Doc$, class java/lang/String, class java/lang/String, class scala/collection/immutable/List, class scala/Option, class scala/Option ]
          stack = []
      LineNumberTable:
        line 200: 0
        line 201: 19
        line 202: 30
        line 203: 34
        line 204: 56
        line 205: 81
        line 206: 102
        line 207: 115
        line 211: 128
        line 204: 139
        line 202: 142
      LocalVariableTable:
        Start  Length  Slot  Name   Signature
          102      33     8 initialWhite   Ljava/lang/String;
          115      20     9 margin   I
          128       7    10 choppedLines   Lscala/collection/immutable/List;
           81      58     7 nonWhiteLine   Ljava/lang/String;
           19     134     3 lines   Lscala/collection/immutable/List;
           30     123     4 firstNonWhiteLine   Lscala/Option;
            0     154     0  this   Lorg/scalatest/Doc$;
            0     154     1  text   Ljava/lang/String;
    MethodParameters:
      Name                           Flags
      text                           final

  private java.lang.Object writeReplace();
    descriptor: ()Ljava/lang/Object;
    flags: (0x0002) ACC_PRIVATE
    Code:
      stack=3, locals=1, args_size=1
         0: new           #195                // class scala/runtime/ModuleSerializationProxy
         3: dup
         4: ldc           #2                  // class org/scalatest/Doc$
         6: invokespecial #198                // Method scala/runtime/ModuleSerializationProxy."<init>":(Ljava/lang/Class;)V
         9: areturn
      LineNumberTable:
        line 186: 0
      LocalVariableTable:
        Start  Length  Slot  Name   Signature
            0      10     0  this   Lorg/scalatest/Doc$;

  public static final boolean $anonfun$trimMarkup$1(scala.Tuple2);
    descriptor: (Lscala/Tuple2;)Z
    flags: (0x1019) ACC_PUBLIC, ACC_STATIC, ACC_FINAL, ACC_SYNTHETIC
    Code:
      stack=3, locals=4, args_size=1
         0: aload_0
         1: astore_2
         2: aload_2
         3: ifnull        33
         6: aload_2
         7: invokevirtual #94                 // Method scala/Tuple2._1:()Ljava/lang/Object;
        10: checkcast     #110                // class java/lang/String
        13: astore_3
        14: aload_3
        15: invokevirtual #114                // Method java/lang/String.trim:()Ljava/lang/String;
        18: invokevirtual #205                // Method java/lang/String.isEmpty:()Z
        21: ifne          28
        24: iconst_1
        25: goto          29
        28: iconst_0
        29: istore_1
        30: goto          45
        33: goto          36
        36: new           #140                // class scala/MatchError
        39: dup
        40: aload_2
        41: invokespecial #143                // Method scala/MatchError."<init>":(Ljava/lang/Object;)V
        44: athrow
        45: iload_1
        46: ireturn
      StackMapTable: number_of_entries = 5
        frame_type = 254 /* append */
          offset_delta = 28
          locals = [ top, class scala/Tuple2, class java/lang/String ]
        frame_type = 64 /* same_locals_1_stack_item */
          stack = [ int ]
        frame_type = 250 /* chop */
          offset_delta = 3
        frame_type = 2 /* same */
        frame_type = 255 /* full_frame */
          offset_delta = 8
          locals = [ class scala/Tuple2, int, class scala/Tuple2, class java/lang/String ]
          stack = []
      LineNumberTable:
        line 191: 0
      LocalVariableTable:
        Start  Length  Slot  Name   Signature
           14      19     3  line   Ljava/lang/String;
            0      47     0  x0$1   Lscala/Tuple2;
    MethodParameters:
      Name                           Flags
      x0$1                           final

  public static final boolean $anonfun$trimMarkup$2(scala.Tuple2);
    descriptor: (Lscala/Tuple2;)Z
    flags: (0x1019) ACC_PUBLIC, ACC_STATIC, ACC_FINAL, ACC_SYNTHETIC
    Code:
      stack=3, locals=4, args_size=1
         0: aload_0
         1: astore_2
         2: aload_2
         3: ifnull        33
         6: aload_2
         7: invokevirtual #94                 // Method scala/Tuple2._1:()Ljava/lang/Object;
        10: checkcast     #110                // class java/lang/String
        13: astore_3
        14: aload_3
        15: invokevirtual #114                // Method java/lang/String.trim:()Ljava/lang/String;
        18: invokevirtual #205                // Method java/lang/String.isEmpty:()Z
        21: ifne          28
        24: iconst_1
        25: goto          29
        28: iconst_0
        29: istore_1
        30: goto          45
        33: goto          36
        36: new           #140                // class scala/MatchError
        39: dup
        40: aload_2
        41: invokespecial #143                // Method scala/MatchError."<init>":(Ljava/lang/Object;)V
        44: athrow
        45: iload_1
        46: ireturn
      StackMapTable: number_of_entries = 5
        frame_type = 254 /* append */
          offset_delta = 28
          locals = [ top, class scala/Tuple2, class java/lang/String ]
        frame_type = 64 /* same_locals_1_stack_item */
          stack = [ int ]
        frame_type = 250 /* chop */
          offset_delta = 3
        frame_type = 2 /* same */
        frame_type = 255 /* full_frame */
          offset_delta = 8
          locals = [ class scala/Tuple2, int, class scala/Tuple2, class java/lang/String ]
          stack = []
      LineNumberTable:
        line 192: 0
      LocalVariableTable:
        Start  Length  Slot  Name   Signature
           14      19     3  line   Ljava/lang/String;
            0      47     0  x0$2   Lscala/Tuple2;
    MethodParameters:
      Name                           Flags
      x0$2                           final

  public static final boolean $anonfun$stripMargin$1(java.lang.String);
    descriptor: (Ljava/lang/String;)Z
    flags: (0x1019) ACC_PUBLIC, ACC_STATIC, ACC_FINAL, ACC_SYNTHETIC
    Code:
      stack=1, locals=1, args_size=1
         0: aload_0
         1: invokevirtual #114                // Method java/lang/String.trim:()Ljava/lang/String;
         4: invokevirtual #205                // Method java/lang/String.isEmpty:()Z
         7: ifne          14
        10: iconst_1
        11: goto          15
        14: iconst_0
        15: ireturn
      StackMapTable: number_of_entries = 2
        frame_type = 14 /* same */
        frame_type = 64 /* same_locals_1_stack_item */
          stack = [ int ]
      LineNumberTable:
        line 201: 0
      LocalVariableTable:
        Start  Length  Slot  Name   Signature
            0      16     0   x$3   Ljava/lang/String;
    MethodParameters:
      Name                           Flags
      x$3                            final

  public static final boolean $anonfun$stripMargin$2(char);
    descriptor: (C)Z
    flags: (0x1019) ACC_PUBLIC, ACC_STATIC, ACC_FINAL, ACC_SYNTHETIC
    Code:
      stack=3, locals=1, args_size=1
         0: getstatic     #220                // Field scala/runtime/RichChar$.MODULE$:Lscala/runtime/RichChar$;
         3: getstatic     #34                 // Field scala/Predef$.MODULE$:Lscala/Predef$;
         6: iload_0
         7: invokevirtual #224                // Method scala/Predef$.charWrapper:(C)C
        10: invokevirtual #227                // Method scala/runtime/RichChar$.isWhitespace$extension:(C)Z
        13: ireturn
      LineNumberTable:
        line 205: 3
      LocalVariableTable:
        Start  Length  Slot  Name   Signature
            0      14     0   x$4   C
    MethodParameters:
      Name                           Flags
      x$4                            final

  public static final java.lang.String $anonfun$stripMargin$3(int, java.lang.String);
    descriptor: (ILjava/lang/String;)Ljava/lang/String;
    flags: (0x1019) ACC_PUBLIC, ACC_STATIC, ACC_FINAL, ACC_SYNTHETIC
    Code:
      stack=2, locals=3, args_size=2
         0: aload_1
         1: invokevirtual #174                // Method java/lang/String.length:()I
         4: iload_0
         5: if_icmple     12
         8: iload_0
         9: goto          16
        12: aload_1
        13: invokevirtual #174                // Method java/lang/String.length:()I
        16: istore_2
        17: aload_1
        18: iload_2
        19: invokevirtual #233                // Method java/lang/String.substring:(I)Ljava/lang/String;
        22: areturn
      StackMapTable: number_of_entries = 2
        frame_type = 12 /* same */
        frame_type = 67 /* same_locals_1_stack_item */
          stack = [ int ]
      LineNumberTable:
        line 208: 0
        line 209: 17
      LocalVariableTable:
        Start  Length  Slot  Name   Signature
           17       5     2 strip   I
            0      23     0 margin$1   I
            0      23     1  line   Ljava/lang/String;
    MethodParameters:
      Name                           Flags
      margin$1                       final
      line                           final

  private org.scalatest.Doc$();
    descriptor: ()V
    flags: (0x0002) ACC_PRIVATE
    Code:
      stack=1, locals=1, args_size=1
         0: aload_0
         1: invokespecial #235                // Method java/lang/Object."<init>":()V
         4: return
      LineNumberTable:
        line 215: 0
        line 186: 4
      LocalVariableTable:
        Start  Length  Slot  Name   Signature
            0       5     0  this   Lorg/scalatest/Doc$;

  public static final java.lang.Object $anonfun$trimMarkup$1$adapted(scala.Tuple2);
    descriptor: (Lscala/Tuple2;)Ljava/lang/Object;
    flags: (0x1019) ACC_PUBLIC, ACC_STATIC, ACC_FINAL, ACC_SYNTHETIC
    Code:
      stack=1, locals=1, args_size=1
         0: aload_0
         1: invokestatic  #237                // Method $anonfun$trimMarkup$1:(Lscala/Tuple2;)Z
         4: invokestatic  #243                // Method scala/runtime/BoxesRunTime.boxToBoolean:(Z)Ljava/lang/Boolean;
         7: areturn
      LineNumberTable:
        line 191: 0
      LocalVariableTable:
        Start  Length  Slot  Name   Signature
            0       8     0  x0$1   Lscala/Tuple2;
    MethodParameters:
      Name                           Flags
      x0$1                           final

  public static final java.lang.Object $anonfun$trimMarkup$2$adapted(scala.Tuple2);
    descriptor: (Lscala/Tuple2;)Ljava/lang/Object;
    flags: (0x1019) ACC_PUBLIC, ACC_STATIC, ACC_FINAL, ACC_SYNTHETIC
    Code:
      stack=1, locals=1, args_size=1
         0: aload_0
         1: invokestatic  #245                // Method $anonfun$trimMarkup$2:(Lscala/Tuple2;)Z
         4: invokestatic  #243                // Method scala/runtime/BoxesRunTime.boxToBoolean:(Z)Ljava/lang/Boolean;
         7: areturn
      LineNumberTable:
        line 192: 0
      LocalVariableTable:
        Start  Length  Slot  Name   Signature
            0       8     0  x0$2   Lscala/Tuple2;
    MethodParameters:
      Name                           Flags
      x0$2                           final

  public static final java.lang.Object $anonfun$stripMargin$1$adapted(java.lang.String);
    descriptor: (Ljava/lang/String;)Ljava/lang/Object;
    flags: (0x1019) ACC_PUBLIC, ACC_STATIC, ACC_FINAL, ACC_SYNTHETIC
    Code:
      stack=1, locals=1, args_size=1
         0: aload_0
         1: invokestatic  #247                // Method $anonfun$stripMargin$1:(Ljava/lang/String;)Z
         4: invokestatic  #243                // Method scala/runtime/BoxesRunTime.boxToBoolean:(Z)Ljava/lang/Boolean;
         7: areturn
      LineNumberTable:
        line 201: 0
      LocalVariableTable:
        Start  Length  Slot  Name   Signature
            0       8     0   x$3   Ljava/lang/String;
    MethodParameters:
      Name                           Flags
      x$3                            final

  public static final java.lang.Object $anonfun$stripMargin$2$adapted(java.lang.Object);
    descriptor: (Ljava/lang/Object;)Ljava/lang/Object;
    flags: (0x1019) ACC_PUBLIC, ACC_STATIC, ACC_FINAL, ACC_SYNTHETIC
    Code:
      stack=1, locals=1, args_size=1
         0: aload_0
         1: invokestatic  #251                // Method scala/runtime/BoxesRunTime.unboxToChar:(Ljava/lang/Object;)C
         4: invokestatic  #253                // Method $anonfun$stripMargin$2:(C)Z
         7: invokestatic  #243                // Method scala/runtime/BoxesRunTime.boxToBoolean:(Z)Ljava/lang/Boolean;
        10: areturn
      LineNumberTable:
        line 205: 0
      LocalVariableTable:
        Start  Length  Slot  Name   Signature
            0      11     0   x$4   Ljava/lang/Object;
    MethodParameters:
      Name                           Flags
      x$4                            final

  private static java.lang.Object $deserializeLambda$(java.lang.invoke.SerializedLambda);
    descriptor: (Ljava/lang/invoke/SerializedLambda;)Ljava/lang/Object;
    flags: (0x100a) ACC_PRIVATE, ACC_STATIC, ACC_SYNTHETIC
    Code:
      stack=1, locals=1, args_size=1
         0: aload_0
         1: invokedynamic #266,  0            // InvokeDynamic #5:lambdaDeserialize:(Ljava/lang/invoke/SerializedLambda;)Ljava/lang/Object;
         6: areturn
}
InnerClasses:
  public static final #12= #9 of #11;     // Lookup=class java/lang/invoke/MethodHandles$Lookup of class java/lang/invoke/MethodHandles
SourceFile: "Doc.scala"
BootstrapMethods:
  0: #70 REF_invokeStatic java/lang/invoke/LambdaMetafactory.altMetafactory:(Ljava/lang/invoke/MethodHandles$Lookup;Ljava/lang/String;Ljava/lang/invoke/MethodType;[Ljava/lang/Object;)Ljava/lang/invoke/CallSite;
    Method arguments:
      #55 (Ljava/lang/Object;)Ljava/lang/Object;
      #60 REF_invokeStatic org/scalatest/Doc$.$anonfun$trimMarkup$1$adapted:(Lscala/Tuple2;)Ljava/lang/Object;
      #61 (Lscala/Tuple2;)Ljava/lang/Object;
      #62 5
      #63 1
      #61 (Lscala/Tuple2;)Ljava/lang/Object;
  1: #70 REF_invokeStatic java/lang/invoke/LambdaMetafactory.altMetafactory:(Ljava/lang/invoke/MethodHandles$Lookup;Ljava/lang/String;Ljava/lang/invoke/MethodType;[Ljava/lang/Object;)Ljava/lang/invoke/CallSite;
    Method arguments:
      #55 (Ljava/lang/Object;)Ljava/lang/Object;
      #85 REF_invokeStatic org/scalatest/Doc$.$anonfun$trimMarkup$2$adapted:(Lscala/Tuple2;)Ljava/lang/Object;
      #61 (Lscala/Tuple2;)Ljava/lang/Object;
      #62 5
      #63 1
      #61 (Lscala/Tuple2;)Ljava/lang/Object;
  2: #70 REF_invokeStatic java/lang/invoke/LambdaMetafactory.altMetafactory:(Ljava/lang/invoke/MethodHandles$Lookup;Ljava/lang/String;Ljava/lang/invoke/MethodType;[Ljava/lang/Object;)Ljava/lang/invoke/CallSite;
    Method arguments:
      #55 (Ljava/lang/Object;)Ljava/lang/Object;
      #160 REF_invokeStatic org/scalatest/Doc$.$anonfun$stripMargin$1$adapted:(Ljava/lang/String;)Ljava/lang/Object;
      #161 (Ljava/lang/String;)Ljava/lang/Object;
      #62 5
      #63 1
      #161 (Ljava/lang/String;)Ljava/lang/Object;
  3: #70 REF_invokeStatic java/lang/invoke/LambdaMetafactory.altMetafactory:(Ljava/lang/invoke/MethodHandles$Lookup;Ljava/lang/String;Ljava/lang/invoke/MethodType;[Ljava/lang/Object;)Ljava/lang/invoke/CallSite;
    Method arguments:
      #55 (Ljava/lang/Object;)Ljava/lang/Object;
      #166 REF_invokeStatic org/scalatest/Doc$.$anonfun$stripMargin$2$adapted:(Ljava/lang/Object;)Ljava/lang/Object;
      #55 (Ljava/lang/Object;)Ljava/lang/Object;
      #63 1
  4: #70 REF_invokeStatic java/lang/invoke/LambdaMetafactory.altMetafactory:(Ljava/lang/invoke/MethodHandles$Lookup;Ljava/lang/String;Ljava/lang/invoke/MethodType;[Ljava/lang/Object;)Ljava/lang/invoke/CallSite;
    Method arguments:
      #55 (Ljava/lang/Object;)Ljava/lang/Object;
      #179 REF_invokeStatic org/scalatest/Doc$.$anonfun$stripMargin$3:(ILjava/lang/String;)Ljava/lang/String;
      #180 (Ljava/lang/String;)Ljava/lang/String;
      #62 5
      #63 1
      #180 (Ljava/lang/String;)Ljava/lang/String;
  5: #263 REF_invokeStatic scala/runtime/LambdaDeserialize.bootstrap:(Ljava/lang/invoke/MethodHandles$Lookup;Ljava/lang/String;Ljava/lang/invoke/MethodType;[Ljava/lang/invoke/MethodHandle;)Ljava/lang/invoke/CallSite;
    Method arguments:
      #160 REF_invokeStatic org/scalatest/Doc$.$anonfun$stripMargin$1$adapted:(Ljava/lang/String;)Ljava/lang/Object;
      #166 REF_invokeStatic org/scalatest/Doc$.$anonfun$stripMargin$2$adapted:(Ljava/lang/Object;)Ljava/lang/Object;
      #179 REF_invokeStatic org/scalatest/Doc$.$anonfun$stripMargin$3:(ILjava/lang/String;)Ljava/lang/String;
      #60 REF_invokeStatic org/scalatest/Doc$.$anonfun$trimMarkup$1$adapted:(Lscala/Tuple2;)Ljava/lang/Object;
      #85 REF_invokeStatic org/scalatest/Doc$.$anonfun$trimMarkup$2$adapted:(Lscala/Tuple2;)Ljava/lang/Object;
  ScalaInlineInfo: length = 0x45 (unknown attribute)
   01 01 00 0D 00 D2 00 D3 01 00 9C 00 9D 01 00 D5
   00 D6 01 00 A3 00 36 01 00 AF 00 B0 01 00 C7 00
   C8 01 00 38 00 39 01 00 D0 00 C8 01 00 52 00 39
   01 00 11 00 10 01 00 9B 00 17 01 00 16 00 17 01
   00 C1 00 33 01
  Scala: length = 0x0 (unknown attribute)

