Classfile /Users/mw/Projects/slang-braindump/.jar/jar11/assemble/slang-braindump/assemble/content/org/scalatest/Doc.class
  Last modified May 29, 2022; size 17137 bytes
  SHA-256 checksum 1829dd77b39a9d10de6ff8954332073ffdfde2d4153dd121c8c97f0ebe8e880f
  Compiled from "Doc.scala"
public interface org.scalatest.Doc extends org.scalatest.Suite
  minor version: 0
  major version: 52
  flags: (0x0601) ACC_PUBLIC, ACC_INTERFACE, ACC_ABSTRACT
  this_class: #2                          // org/scalatest/Doc
  super_class: #4                         // java/lang/Object
  interfaces: 1, fields: 0, methods: 29, attributes: 6
Constant pool:
    #1 = Utf8               org/scalatest/Doc
    #2 = Class              #1            // org/scalatest/Doc
    #3 = Utf8               java/lang/Object
    #4 = Class              #3            // java/lang/Object
    #5 = Utf8               org/scalatest/Suite
    #6 = Class              #5            // org/scalatest/Suite
    #7 = Utf8               Doc.scala
    #8 = Utf8               Lscala/reflect/ScalaSignature;
    #9 = Utf8               bytes
   #10 = Utf8               \u0006\u0005\tef\u0001\u0003%J!\u0003\r\t!S\'\t\u000ba\u0003A\u0011\u0001.\u0007\ty\u0003Aa\u0018\u0005\tA\n\u0011)\u0019!C\u0001C\"A\u0001O\u0001B\u0001B\u0003%!\r\u0003\u0005r\u0005\t\u0015\r\u0011\"\u0001s\u0011!1(A!A!\u0002\u0013\u0019\b\"B<\u0003\t\u0013A\b\"B?\u0003\t\u0003qxaBA\u0003\u0001!%\u0011q\u0001\u0004\u0007=\u0002AI!!\u0003\t\r]TA\u0011AA\u0006\u0011\u001d\tiA\u0003C\u0001\u0003\u001fA\u0011\"!\u0006\u0001\u0005\u0004%i!a\u0006\t\u000f\u0005=\u0002\u0001\"\u0003\u00022!A\u00111\b\u0001A\u0002\u0013%\u0011\rC\u0005\u0002>\u0001\u0001\r\u0011\"\u0003\u0002@!9\u0011Q\t\u0001\u0005\u0002\u0005\u001d\u0003bBA-\u0001\u0011E\u00111\f\u0005\u000b\u0003C\u0002\u0001R1A\u0005\n\u0005\r\u0004B\u0003B\u001a\u0001!\u0015\r\u0011\"\u0012\u00036!9!1\t\u0001\u0005R\t\u0015\u0003\u0002\u0003B,\u0001\u0011\u0005\u0011J!\u0017\u0007\u0015\u0005e\u0004\u0001%A\u0012\"%\u000bYHB\u0004\u0003\f\u0001\u0001\u0015J!\u0004\t\u0015\t=\u0001D!f\u0001\n\u0003\u0011\t\u0002C\u0005\u0003\u0014a\u0011\t\u0012)A\u0005K\"1q\u000f\u0007C\u0001\u0005+A\u0011\"!\'\u0019\u0003\u0003%\tAa\u0007\t\u0013\u0005}\u0005$%A\u0005\u0002\t}\u0001\"CA\\1\u0005\u0005I\u0011IA]\u0011%\t)\rGA\u0001\n\u0003\t9\rC\u0005\u0002Pb\t\t\u0011\"\u0001\u0003$!I\u00111\u001c\r\u0002\u0002\u0013\u0005\u0013Q\u001c\u0005\n\u0003WD\u0012\u0011!C\u0001\u0005OA\u0011\"a>\u0019\u0003\u0003%\tEa\u000b\t\u0013\u0005u\b$!A\u0005B\u0005}\b\"\u0003B\u00011\u0005\u0005I\u0011\tB\u0002\u0011%\u0011)\u0001GA\u0001\n\u0003\u0012yc\u0002\u0006\u0003^\u0001\t\t\u0011#\u0001J\u0005?2!Ba\u0003\u0001\u0003\u0003E\t!\u0013B1\u0011\u00199\b\u0006\"\u0001\u0003z!I!\u0011\u0001\u0015\u0002\u0002\u0013\u0015#1\u0001\u0005\n\u0003\u001bA\u0013\u0011!CA\u0005wB\u0011Ba )\u0003\u0003%\tI!!\u0007\u000f\u0005-\u0005\u0001Q%\u0002\u000e\"Q\u0011qL\u0017\u0003\u0016\u0004%\t!a$\t\u0013\u0005EUF!E!\u0002\u0013!\u0006BB<.\t\u0003\t\u0019\nC\u0005\u0002\u001a6\n\t\u0011\"\u0001\u0002\u001c\"I\u0011qT\u0017\u0012\u0002\u0013\u0005\u0011\u0011\u0015\u0005\n\u0003ok\u0013\u0011!C!\u0003sC\u0011\"!2.\u0003\u0003%\t!a2\t\u0013\u0005=W&!A\u0005\u0002\u0005E\u0007\"CAn[\u0005\u0005I\u0011IAo\u0011%\tY/LA\u0001\n\u0003\ti\u000fC\u0005\u0002x6\n\t\u0011\"\u0011\u0002z\"I\u0011Q`\u0017\u0002\u0002\u0013\u0005\u0013q \u0005\n\u0005\u0003i\u0013\u0011!C!\u0005\u0007A\u0011B!\u0002.\u0003\u0003%\tEa\u0002\b\u0015\t\u001d\u0005!!A\t\u0002%\u0013II\u0002\u0006\u0002\f\u0002\t\t\u0011#\u0001J\u0005\u0017Caa^\u001f\u0005\u0002\t=\u0005\"\u0003B\u0001{\u0005\u0005IQ\tB\u0002\u0011%\ti!PA\u0001\n\u0003\u0013\t\nC\u0005\u0003\u0000u\n\t\u0011\"!\u0003\u0016\u001eA!1T%\t\u0002%\u0013iJB\u0004I\u0013\"\u0005\u0011Ja(\t\r]\u001cE\u0011\u0001BQ\u0011!\u0011\u0019k\u0011C\u0001\u0013\n\u0015\u0006\u0002\u0003BU\u0007\u0012\u0005\u0011Ja+\t\u0013\t=6)!A\u0005\n\tE&a\u0001#pG*\u0011!jS\u0001\ng\u000e\fG.\u0019;fgRT\u0011\u0001T\u0001\u0004_J<7c\u0001\u0001O)B\u0011qJU\u0007\u0002!*\t\u0011+A\u0003tG\u0006d\u0017-\u0003\u0002T!\n1\u0011I\\=SK\u001a\u0004\"!\u0016,\u000e\u0003%K!aV%\u0003\u000bM+\u0018\u000e^3\u0002\r\u0011Jg.\u001b;%\u0007\u0001!\u0012a\u0017\t\u0003\u001frK!!\u0018)\u0003\tUs\u0017\u000e\u001e\u0002\u0007\u0005VtG\r\\3\u0014\u0005\tq\u0015A\u0006:fO&\u001cHO]1uS>tG\u000b\u001b:fC\u0012t\u0015-\\3\u0016\u0003\t\u00042aT2f\u0013\t!\u0007K\u0001\u0004PaRLwN\u001c\t\u0003M6t!aZ6\u0011\u0005!\u0004V\"A5\u000b\u0005)L\u0016A\u0002\u001fs_>$h(\u0003\u0002m!\u00061\u0001K]3eK\u001aL!A\\8\u0003\rM#(/\u001b8h\u0015\ta\u0007+A\fsK\u001eL7\u000f\u001e:bi&|g\u000e\u00165sK\u0006$g*Y7fA\u0005\u0001\"/Z4jgR,\'/\u001a3Tk&$Xm]\u000b\u0002gB!a\r^3U\u0013\t)xNA\u0002NCB\f\u0011C]3hSN$XM]3e\'VLG/Z:!\u0003\u0019a\u0014N\\5u}Q\u0019\u0011p\u001f?\u0011\u0005i\u0014Q\"\u0001\u0001\t\u000b\u0001<\u0001\u0019\u00012\t\u000bE<\u0001\u0019A:\u0002\rUt\u0007/Y2l+\u0005y\b#B(\u0002\u0002\t\u001c\u0018bAA\u0002!\n1A+\u001e9mKJ\naAQ;oI2,\u0007C\u0001>\u000b\'\tQa\n\u0006\u0002\u0002\b\u0005)\u0011\r\u001d9msR)\u00110!\u0005\u0002\u0014!)\u0001\r\u0004a\u0001E\")\u0011\u000f\u0004a\u0001g\u00061\u0011\r^8nS\u000e,\"!!\u0007\u0011\u000b\u0005m\u00111F=\u000e\u0005\u0005u!\u0002BA\u000b\u0003?QA!!\t\u0002$\u0005Q1m\u001c8dkJ\u0014XM\u001c;\u000b\t\u0005\u0015\u0012qE\u0001\u0005kRLGN\u0003\u0002\u0002*\u0005!!.\u0019<b\u0013\u0011\ti#!\b\u0003\u001f\u0005#x.\\5d%\u00164WM]3oG\u0016\fA\"\u001e9eCR,\u0017\t^8nS\u000e$RaWA\u001a\u0003oAa!!\u000e\u000f\u0001\u0004I\u0018!C8mI\n+h\u000e\u001a7f\u0011\u0019\tID\u0004a\u0001s\u0006Ia.Z<Ck:$G.Z\u0001\tE>$\u0017\u0010V3yi\u0006a!m\u001c3z)\u0016DHo\u0018\u0013fcR\u00191,!\u0011\t\u0011\u0005\r\u0003#!AA\u0002\t\f1\u0001\u001f\u00132\u0003\u0011\u0011w\u000eZ=\u0015\u0007m\u000bI\u0005C\u0004\u0002LE\u0001\r!!\u0014\u0002\t\u0015dW-\u001c\t\u0005\u0003\u001f\n)&\u0004\u0002\u0002R)\u0019\u00111\u000b)\u0002\u0007alG.\u0003\u0003\u0002X\u0005E#\u0001B#mK6\fq!\u001b8dYV$W\rF\u0002f\u0003;Ba!a\u0018\u0013\u0001\u0004!\u0016!B:vSR,\u0017\u0001C:oSB\u0004X\r^:\u0016\u0005\u0005\u0015\u0004CBA4\u0003c\n9H\u0004\u0003\u0002j\u00055db\u00015\u0002l%\t\u0011+C\u0002\u0002pA\u000bq\u0001]1dW\u0006<W-\u0003\u0003\u0002t\u0005U$A\u0002,fGR|\'OC\u0002\u0002pA\u0003\"A_\f\u0003\u000fMs\u0017\u000e\u001d9fiN1qCTA?\u0003\u0007\u00032aTA@\u0013\r\t\t\t\u0015\u0002\b!J|G-^2u!\u0011\t9\'!\"\n\t\u0005\u001d\u0015Q\u000f\u0002\r\'\u0016\u0014\u0018.\u00197ju\u0006\u0014G.Z\u0015\u0004/5B\"!D%oG2,H-\u001a3Tk&$Xm\u0005\u0005.\u001d\u0006]\u0014QPAB+\u0005!\u0016AB:vSR,\u0007\u0005\u0006\u0003\u0002\u0016\u0006]\u0005C\u0001>.\u0011\u0019\ty\u0006\ra\u0001)\u0006!1m\u001c9z)\u0011\t)*!(\t\u0011\u0005}\u0013\u0007%AA\u0002Q\u000babY8qs\u0012\"WMZ1vYR$\u0013\'\u0006\u0002\u0002$*\u001aA+!*,\u0005\u0005\u001d\u0006\u0003BAU\u0003gk!!a+\u000b\t\u00055\u0016qV\u0001\nk:\u001c\u0007.Z2lK\u0012T1!!-Q\u0003)\tgN\\8uCRLwN\\\u0005\u0005\u0003k\u000bYKA\tv]\u000eDWmY6fIZ\u000b\'/[1oG\u0016\fQ\u0002\u001d:pIV\u001cG\u000f\u0015:fM&DXCAA^!\u0011\ti,a1\u000e\u0005\u0005}&\u0002BAa\u0003O\tA\u0001\\1oO&\u0019a.a0\u0002\u0019A\u0014x\u000eZ;di\u0006\u0013\u0018\u000e^=\u0016\u0005\u0005%\u0007cA(\u0002L&\u0019\u0011Q\u001a)\u0003\u0007%sG/\u0001\bqe>$Wo\u0019;FY\u0016lWM\u001c;\u0015\t\u0005M\u0017\u0011\u001c\t\u0004\u001f\u0006U\u0017bAAl!\n\u0019\u0011I\\=\t\u0013\u0005\rS\'!AA\u0002\u0005%\u0017a\u00049s_\u0012,8\r^%uKJ\fGo\u001c:\u0016\u0005\u0005}\u0007CBAq\u0003O\f\u0019.\u0004\u0002\u0002d*\u0019\u0011Q\u001d)\u0002\u0015\r|G\u000e\\3di&|g.\u0003\u0003\u0002j\u0006\r(\u0001C%uKJ\fGo\u001c:\u0002\u0011\r\fg.R9vC2$B!a<\u0002vB\u0019q*!=\n\u0007\u0005M\bKA\u0004C_>dW-\u00198\t\u0013\u0005\rs\'!AA\u0002\u0005M\u0017A\u00059s_\u0012,8\r^#mK6,g\u000e\u001e(b[\u0016$B!a/\u0002|\"I\u00111\t\u001d\u0002\u0002\u0003\u0007\u0011\u0011Z\u0001\tQ\u0006\u001c\bnQ8eKR\u0011\u0011\u0011Z\u0001\ti>\u001cFO]5oOR\u0011\u00111X\u0001\u0007KF,\u0018\r\\:\u0015\t\u0005=(\u0011\u0002\u0005\n\u0003\u0007Z\u0014\u0011!a\u0001\u0003\'\u0014a!T1sWV\u00048\u0003\u0003\rO\u0003o\ni(a!\u0002\tQ,\u0007\u0010^\u000b\u0002K\u0006)A/\u001a=uAQ!!q\u0003B\r!\tQ\b\u0004\u0003\u0004\u0003\u0010m\u0001\r!\u001a\u000b\u0005\u0005/\u0011i\u0002\u0003\u0005\u0003\u0010q\u0001\n\u00111\u0001f+\t\u0011\tCK\u0002f\u0003K#B!a5\u0003&!I\u00111\t\u0011\u0002\u0002\u0003\u0007\u0011\u0011\u001a\u000b\u0005\u0003_\u0014I\u0003C\u0005\u0002D\t\n\t\u00111\u0001\u0002TR!\u00111\u0018B\u0017\u0011%\t\u0019eIA\u0001\u0002\u0004\tI\r\u0006\u0003\u0002p\nE\u0002\"CA\"M\u0005\u0005\t\u0019AAj\u00031qWm\u001d;fIN+\u0018\u000e^3t+\t\u00119\u0004E\u0003\u0003:\t}B+\u0004\u0002\u0003<)!!QHAr\u0003%IW.\\;uC\ndW-\u0003\u0003\u0003B\tm\"AC%oI\u0016DX\rZ*fc\u0006y!/\u001e8OKN$X\rZ*vSR,7\u000f\u0006\u0003\u0003H\t5\u0003cA+\u0003J%\u0019!1J%\u0003\rM#\u0018\r^;t\u0011\u001d\u0011y%\u0006a\u0001\u0005#\nA!\u0019:hgB\u0019QKa\u0015\n\u0007\tU\u0013J\u0001\u0003Be\u001e\u001c\u0018aC4fiNs\u0017\u000e\u001d9fiN$B!!\u001a\u0003\\!1!q\u0002\fA\u0002\u0015\fa!T1sWV\u0004\bC\u0001>)\'\u0015A#1\rB8!\u001d\u0011)Ga\u001bf\u0005/i!Aa\u001a\u000b\u0007\t%\u0004+A\u0004sk:$\u0018.\\3\n\t\t5$q\r\u0002\u0012\u0003\n\u001cHO]1di\u001a+hn\u0019;j_:\f\u0004\u0003\u0002B9\u0005oj!Aa\u001d\u000b\t\tU\u0014qE\u0001\u0003S>LA!a\"\u0003tQ\u0011!q\f\u000b\u0005\u0005/\u0011i\b\u0003\u0004\u0003\u0010-\u0002\r!Z\u0001\bk:\f\u0007\u000f\u001d7z)\r\u0011\'1\u0011\u0005\n\u0005\u000bc\u0013\u0011!a\u0001\u0005/\t1\u0001\u001f\u00131\u00035Ien\u00197vI\u0016$7+^5uKB\u0011!0P\n\u0006{\t5%q\u000e\t\b\u0005K\u0012Y\u0007VAK)\t\u0011I\t\u0006\u0003\u0002\u0016\nM\u0005BBA0\u0001\u0002\u0007A\u000b\u0006\u0003\u0003\u0018\ne\u0005cA(d)\"I!QQ!\u0002\u0002\u0003\u0007\u0011QS\u0001\u0004\t>\u001c\u0007CA+D\'\u0011\u0019eJa\u001c\u0015\u0005\tu\u0015A\u0003;sS6l\u0015M]6vaR\u0019QMa*\t\r\t=Q\t1\u0001f\u0003-\u0019HO]5q\u001b\u0006\u0014x-\u001b8\u0015\u0007\u0015\u0014i\u000b\u0003\u0004\u0003\u0010\u0019\u0003\r!Z\u0001\roJLG/\u001a*fa2\f7-\u001a\u000b\u0003\u0005g\u0003B!!0\u00036&!!qWA`\u0005\u0019y%M[3di\u0002
   #11 = Utf8               java/lang/invoke/MethodHandles$Lookup
   #12 = Class              #11           // java/lang/invoke/MethodHandles$Lookup
   #13 = Utf8               java/lang/invoke/MethodHandles
   #14 = Class              #13           // java/lang/invoke/MethodHandles
   #15 = Utf8               Lookup
   #16 = Utf8               org/scalatest/Doc$Bundle
   #17 = Class              #16           // org/scalatest/Doc$Bundle
   #18 = Utf8               Bundle
   #19 = Utf8               org/scalatest/Doc$Bundle$
   #20 = Class              #19           // org/scalatest/Doc$Bundle$
   #21 = Utf8               Bundle$
   #22 = Utf8               org/scalatest/Doc$IncludedSuite
   #23 = Class              #22           // org/scalatest/Doc$IncludedSuite
   #24 = Utf8               IncludedSuite
   #25 = Utf8               org/scalatest/Doc$IncludedSuite$
   #26 = Class              #25           // org/scalatest/Doc$IncludedSuite$
   #27 = Utf8               IncludedSuite$
   #28 = Utf8               org/scalatest/Doc$Markup
   #29 = Class              #28           // org/scalatest/Doc$Markup
   #30 = Utf8               Markup
   #31 = Utf8               org/scalatest/Doc$Markup$
   #32 = Class              #31           // org/scalatest/Doc$Markup$
   #33 = Utf8               Markup$
   #34 = Utf8               org/scalatest/Doc$Snippet
   #35 = Class              #34           // org/scalatest/Doc$Snippet
   #36 = Utf8               Snippet
   #37 = Utf8               scala/Predef$ArrowAssoc$
   #38 = Class              #37           // scala/Predef$ArrowAssoc$
   #39 = Utf8               scala/Predef
   #40 = Class              #39           // scala/Predef
   #41 = Utf8               ArrowAssoc$
   #42 = Utf8               org$scalatest$Doc$$Bundle
   #43 = Utf8               ()Lorg/scalatest/Doc$Bundle$;
   #44 = Utf8               ()Lorg/scalatest/Doc$Markup$;
   #45 = Utf8               ()Lorg/scalatest/Doc$IncludedSuite$;
   #46 = Utf8               org$scalatest$Doc$_setter_$org$scalatest$Doc$$atomic_$eq
   #47 = Utf8               (Ljava/util/concurrent/atomic/AtomicReference;)V
   #48 = Utf8               (Ljava/util/concurrent/atomic/AtomicReference<Lorg/scalatest/Doc$Bundle;>;)V
   #49 = Utf8               x$1
   #50 = Utf8               org$scalatest$Doc$$atomic
   #51 = Utf8               ()Ljava/util/concurrent/atomic/AtomicReference;
   #52 = Utf8               ()Ljava/util/concurrent/atomic/AtomicReference<Lorg/scalatest/Doc$Bundle;>;
   #53 = Utf8               updateAtomic
   #54 = Utf8               (Lorg/scalatest/Doc$Bundle;Lorg/scalatest/Doc$Bundle;)V
   #55 = Utf8               oldBundle
   #56 = Utf8               newBundle
   #57 = NameAndType        #50:#51       // org$scalatest$Doc$$atomic:()Ljava/util/concurrent/atomic/AtomicReference;
   #58 = InterfaceMethodref #2.#57        // org/scalatest/Doc.org$scalatest$Doc$$atomic:()Ljava/util/concurrent/atomic/AtomicReference;
   #59 = Utf8               java/util/concurrent/atomic/AtomicReference
   #60 = Class              #59           // java/util/concurrent/atomic/AtomicReference
   #61 = Utf8               getAndSet
   #62 = Utf8               (Ljava/lang/Object;)Ljava/lang/Object;
   #63 = NameAndType        #61:#62       // getAndSet:(Ljava/lang/Object;)Ljava/lang/Object;
   #64 = Methodref          #60.#63       // java/util/concurrent/atomic/AtomicReference.getAndSet:(Ljava/lang/Object;)Ljava/lang/Object;
   #65 = Utf8               java/util/ConcurrentModificationException
   #66 = Class              #65           // java/util/ConcurrentModificationException
   #67 = Utf8               concurrentDocSpecMod
   #68 = String             #67           // concurrentDocSpecMod
   #69 = Utf8               <init>
   #70 = Utf8               (Ljava/lang/String;)V
   #71 = NameAndType        #69:#70       // "<init>":(Ljava/lang/String;)V
   #72 = Methodref          #66.#71       // java/util/ConcurrentModificationException."<init>":(Ljava/lang/String;)V
   #73 = Utf8               shouldBeOldBundle
   #74 = Utf8               Lorg/scalatest/Doc$Bundle;
   #75 = Utf8               this
   #76 = Utf8               Lorg/scalatest/Doc;
   #77 = Utf8               org$scalatest$Doc$$bodyText
   #78 = Utf8               ()Lscala/Option;
   #79 = Utf8               ()Lscala/Option<Ljava/lang/String;>;
   #80 = Utf8               org$scalatest$Doc$$bodyText_$eq
   #81 = Utf8               (Lscala/Option;)V
   #82 = Utf8               (Lscala/Option<Ljava/lang/String;>;)V
   #83 = Utf8               body$
   #84 = Utf8               (Lorg/scalatest/Doc;Lscala/xml/Elem;)V
   #85 = Utf8               $this
   #86 = Utf8               elem
   #87 = Utf8               body
   #88 = Utf8               (Lscala/xml/Elem;)V
   #89 = NameAndType        #87:#88       // body:(Lscala/xml/Elem;)V
   #90 = InterfaceMethodref #2.#89        // org/scalatest/Doc.body:(Lscala/xml/Elem;)V
   #91 = Utf8               Lscala/xml/Elem;
   #92 = Utf8               scala/Some
   #93 = Class              #92           // scala/Some
   #94 = Utf8               scala/xml/Elem
   #95 = Class              #94           // scala/xml/Elem
   #96 = Utf8               text
   #97 = Utf8               ()Ljava/lang/String;
   #98 = NameAndType        #96:#97       // text:()Ljava/lang/String;
   #99 = Methodref          #95.#98       // scala/xml/Elem.text:()Ljava/lang/String;
  #100 = Utf8               (Ljava/lang/Object;)V
  #101 = NameAndType        #69:#100      // "<init>":(Ljava/lang/Object;)V
  #102 = Methodref          #93.#101      // scala/Some."<init>":(Ljava/lang/Object;)V
  #103 = NameAndType        #80:#81       // org$scalatest$Doc$$bodyText_$eq:(Lscala/Option;)V
  #104 = InterfaceMethodref #2.#103       // org/scalatest/Doc.org$scalatest$Doc$$bodyText_$eq:(Lscala/Option;)V
  #105 = Utf8               include$
  #106 = Utf8               (Lorg/scalatest/Doc;Lorg/scalatest/Suite;)Ljava/lang/String;
  #107 = Utf8               suite
  #108 = Utf8               include
  #109 = Utf8               (Lorg/scalatest/Suite;)Ljava/lang/String;
  #110 = NameAndType        #108:#109     // include:(Lorg/scalatest/Suite;)Ljava/lang/String;
  #111 = InterfaceMethodref #2.#110       // org/scalatest/Doc.include:(Lorg/scalatest/Suite;)Ljava/lang/String;
  #112 = Utf8               Lorg/scalatest/Suite;
  #113 = Utf8               get
  #114 = Utf8               ()Ljava/lang/Object;
  #115 = NameAndType        #113:#114     // get:()Ljava/lang/Object;
  #116 = Methodref          #60.#115      // java/util/concurrent/atomic/AtomicReference.get:()Ljava/lang/Object;
  #117 = Utf8               unpack
  #118 = Utf8               ()Lscala/Tuple2;
  #119 = NameAndType        #117:#118     // unpack:()Lscala/Tuple2;
  #120 = Methodref          #17.#119      // org/scalatest/Doc$Bundle.unpack:()Lscala/Tuple2;
  #121 = Utf8               scala/Tuple2
  #122 = Class              #121          // scala/Tuple2
  #123 = Utf8               _1
  #124 = NameAndType        #123:#114     // _1:()Ljava/lang/Object;
  #125 = Methodref          #122.#124     // scala/Tuple2._1:()Ljava/lang/Object;
  #126 = Utf8               scala/Option
  #127 = Class              #126          // scala/Option
  #128 = Utf8               _2
  #129 = NameAndType        #128:#114     // _2:()Ljava/lang/Object;
  #130 = Methodref          #122.#129     // scala/Tuple2._2:()Ljava/lang/Object;
  #131 = Utf8               scala/collection/immutable/Map
  #132 = Class              #131          // scala/collection/immutable/Map
  #133 = Utf8               (Ljava/lang/Object;Ljava/lang/Object;)V
  #134 = NameAndType        #69:#133      // "<init>":(Ljava/lang/Object;Ljava/lang/Object;)V
  #135 = Methodref          #122.#134     // scala/Tuple2."<init>":(Ljava/lang/Object;Ljava/lang/Object;)V
  #136 = Utf8               scala/MatchError
  #137 = Class              #136          // scala/MatchError
  #138 = Methodref          #137.#101     // scala/MatchError."<init>":(Ljava/lang/Object;)V
  #139 = Utf8               MODULE$
  #140 = Utf8               Lscala/Predef$ArrowAssoc$;
  #141 = NameAndType        #139:#140     // MODULE$:Lscala/Predef$ArrowAssoc$;
  #142 = Fieldref           #38.#141      // scala/Predef$ArrowAssoc$.MODULE$:Lscala/Predef$ArrowAssoc$;
  #143 = Utf8               scala/Predef$
  #144 = Class              #143          // scala/Predef$
  #145 = Utf8               Lscala/Predef$;
  #146 = NameAndType        #139:#145     // MODULE$:Lscala/Predef$;
  #147 = Fieldref           #144.#146     // scala/Predef$.MODULE$:Lscala/Predef$;
  #148 = Utf8               getClass
  #149 = Utf8               ()Ljava/lang/Class;
  #150 = NameAndType        #148:#149     // getClass:()Ljava/lang/Class;
  #151 = Methodref          #4.#150       // java/lang/Object.getClass:()Ljava/lang/Class;
  #152 = Utf8               java/lang/Class
  #153 = Class              #152          // java/lang/Class
  #154 = Utf8               getName
  #155 = NameAndType        #154:#97      // getName:()Ljava/lang/String;
  #156 = Methodref          #153.#155     // java/lang/Class.getName:()Ljava/lang/String;
  #157 = Utf8               ArrowAssoc
  #158 = NameAndType        #157:#62      // ArrowAssoc:(Ljava/lang/Object;)Ljava/lang/Object;
  #159 = Methodref          #144.#158     // scala/Predef$.ArrowAssoc:(Ljava/lang/Object;)Ljava/lang/Object;
  #160 = Utf8               $minus$greater$extension
  #161 = Utf8               (Ljava/lang/Object;Ljava/lang/Object;)Lscala/Tuple2;
  #162 = NameAndType        #160:#161     // $minus$greater$extension:(Ljava/lang/Object;Ljava/lang/Object;)Lscala/Tuple2;
  #163 = Methodref          #38.#162      // scala/Predef$ArrowAssoc$.$minus$greater$extension:(Ljava/lang/Object;Ljava/lang/Object;)Lscala/Tuple2;
  #164 = Utf8               $plus
  #165 = Utf8               (Lscala/Tuple2;)Lscala/collection/immutable/MapOps;
  #166 = NameAndType        #164:#165     // $plus:(Lscala/Tuple2;)Lscala/collection/immutable/MapOps;
  #167 = InterfaceMethodref #132.#166     // scala/collection/immutable/Map.$plus:(Lscala/Tuple2;)Lscala/collection/immutable/MapOps;
  #168 = NameAndType        #42:#43       // org$scalatest$Doc$$Bundle:()Lorg/scalatest/Doc$Bundle$;
  #169 = InterfaceMethodref #2.#168       // org/scalatest/Doc.org$scalatest$Doc$$Bundle:()Lorg/scalatest/Doc$Bundle$;
  #170 = Utf8               apply
  #171 = Utf8               (Lscala/Option;Lscala/collection/immutable/Map;)Lorg/scalatest/Doc$Bundle;
  #172 = NameAndType        #170:#171     // apply:(Lscala/Option;Lscala/collection/immutable/Map;)Lorg/scalatest/Doc$Bundle;
  #173 = Methodref          #20.#172      // org/scalatest/Doc$Bundle$.apply:(Lscala/Option;Lscala/collection/immutable/Map;)Lorg/scalatest/Doc$Bundle;
  #174 = NameAndType        #53:#54       // updateAtomic:(Lorg/scalatest/Doc$Bundle;Lorg/scalatest/Doc$Bundle;)V
  #175 = InterfaceMethodref #2.#174       // org/scalatest/Doc.updateAtomic:(Lorg/scalatest/Doc$Bundle;Lorg/scalatest/Doc$Bundle;)V
  #176 = Utf8               java/lang/StringBuilder
  #177 = Class              #176          // java/lang/StringBuilder
  #178 = Integer            11
  #179 = Utf8               (I)V
  #180 = NameAndType        #69:#179      // "<init>":(I)V
  #181 = Methodref          #177.#180     // java/lang/StringBuilder."<init>":(I)V
  #182 = Utf8               \ninclude[
  #183 = String             #182          // \ninclude[
  #184 = Utf8               append
  #185 = Utf8               (Ljava/lang/String;)Ljava/lang/StringBuilder;
  #186 = NameAndType        #184:#185     // append:(Ljava/lang/String;)Ljava/lang/StringBuilder;
  #187 = Methodref          #177.#186     // java/lang/StringBuilder.append:(Ljava/lang/String;)Ljava/lang/StringBuilder;
  #188 = Utf8               ]\n
  #189 = String             #188          // ]\n
  #190 = Utf8               toString
  #191 = NameAndType        #190:#97      // toString:()Ljava/lang/String;
  #192 = Methodref          #177.#191     // java/lang/StringBuilder.toString:()Ljava/lang/String;
  #193 = Utf8               registrationThreadName
  #194 = Utf8               Lscala/Option;
  #195 = Utf8               registeredSuites
  #196 = Utf8               Lscala/collection/immutable/Map;
  #197 = Utf8               org$scalatest$Doc$$snippets$
  #198 = Utf8               (Lorg/scalatest/Doc;)Lscala/collection/immutable/Vector;
  #199 = Utf8               org$scalatest$Doc$$snippets
  #200 = Utf8               ()Lscala/collection/immutable/Vector;
  #201 = NameAndType        #199:#200     // org$scalatest$Doc$$snippets:()Lscala/collection/immutable/Vector;
  #202 = InterfaceMethodref #2.#201       // org/scalatest/Doc.org$scalatest$Doc$$snippets:()Lscala/collection/immutable/Vector;
  #203 = Utf8               ()Lscala/collection/immutable/Vector<Lorg/scalatest/Doc$Snippet;>;
  #204 = NameAndType        #77:#78       // org$scalatest$Doc$$bodyText:()Lscala/Option;
  #205 = InterfaceMethodref #2.#204       // org/scalatest/Doc.org$scalatest$Doc$$bodyText:()Lscala/Option;
  #206 = Methodref          #127.#115     // scala/Option.get:()Ljava/lang/Object;
  #207 = Utf8               java/lang/String
  #208 = Class              #207          // java/lang/String
  #209 = Utf8               getSnippets
  #210 = Utf8               (Ljava/lang/String;)Lscala/collection/immutable/Vector;
  #211 = NameAndType        #209:#210     // getSnippets:(Ljava/lang/String;)Lscala/collection/immutable/Vector;
  #212 = InterfaceMethodref #2.#211       // org/scalatest/Doc.getSnippets:(Ljava/lang/String;)Lscala/collection/immutable/Vector;
  #213 = Utf8               nestedSuites$
  #214 = Utf8               (Lorg/scalatest/Doc;)Lscala/collection/immutable/IndexedSeq;
  #215 = Utf8               nestedSuites
  #216 = Utf8               ()Lscala/collection/immutable/IndexedSeq;
  #217 = NameAndType        #215:#216     // nestedSuites:()Lscala/collection/immutable/IndexedSeq;
  #218 = InterfaceMethodref #2.#217       // org/scalatest/Doc.nestedSuites:()Lscala/collection/immutable/IndexedSeq;
  #219 = Utf8               ()Lscala/collection/immutable/IndexedSeq<Lorg/scalatest/Suite;>;
  #220 = MethodType         #62           //  (Ljava/lang/Object;)Ljava/lang/Object;
  #221 = Utf8               $anonfun$nestedSuites$1$adapted
  #222 = Utf8               (Lorg/scalatest/Doc$Snippet;)Ljava/lang/Object;
  #223 = NameAndType        #221:#222     // $anonfun$nestedSuites$1$adapted:(Lorg/scalatest/Doc$Snippet;)Ljava/lang/Object;
  #224 = InterfaceMethodref #2.#223       // org/scalatest/Doc.$anonfun$nestedSuites$1$adapted:(Lorg/scalatest/Doc$Snippet;)Ljava/lang/Object;
  #225 = MethodHandle       6:#224        // REF_invokeStatic org/scalatest/Doc.$anonfun$nestedSuites$1$adapted:(Lorg/scalatest/Doc$Snippet;)Ljava/lang/Object;
  #226 = MethodType         #222          //  (Lorg/scalatest/Doc$Snippet;)Ljava/lang/Object;
  #227 = Integer            5
  #228 = Integer            1
  #229 = Utf8               java/lang/invoke/LambdaMetafactory
  #230 = Class              #229          // java/lang/invoke/LambdaMetafactory
  #231 = Utf8               altMetafactory
  #232 = Utf8               (Ljava/lang/invoke/MethodHandles$Lookup;Ljava/lang/String;Ljava/lang/invoke/MethodType;[Ljava/lang/Object;)Ljava/lang/invoke/CallSite;
  #233 = NameAndType        #231:#232     // altMetafactory:(Ljava/lang/invoke/MethodHandles$Lookup;Ljava/lang/String;Ljava/lang/invoke/MethodType;[Ljava/lang/Object;)Ljava/lang/invoke/CallSite;
  #234 = Methodref          #230.#233     // java/lang/invoke/LambdaMetafactory.altMetafactory:(Ljava/lang/invoke/MethodHandles$Lookup;Ljava/lang/String;Ljava/lang/invoke/MethodType;[Ljava/lang/Object;)Ljava/lang/invoke/CallSite;
  #235 = MethodHandle       6:#234        // REF_invokeStatic java/lang/invoke/LambdaMetafactory.altMetafactory:(Ljava/lang/invoke/MethodHandles$Lookup;Ljava/lang/String;Ljava/lang/invoke/MethodType;[Ljava/lang/Object;)Ljava/lang/invoke/CallSite;
  #236 = Utf8               ()Lscala/Function1;
  #237 = NameAndType        #170:#236     // apply:()Lscala/Function1;
  #238 = InvokeDynamic      #0:#237       // #0:apply:()Lscala/Function1;
  #239 = Utf8               scala/collection/immutable/Vector
  #240 = Class              #239          // scala/collection/immutable/Vector
  #241 = Utf8               withFilter
  #242 = Utf8               (Lscala/Function1;)Lscala/collection/WithFilter;
  #243 = NameAndType        #241:#242     // withFilter:(Lscala/Function1;)Lscala/collection/WithFilter;
  #244 = Methodref          #240.#243     // scala/collection/immutable/Vector.withFilter:(Lscala/Function1;)Lscala/collection/WithFilter;
  #245 = Utf8               $anonfun$nestedSuites$2
  #246 = Utf8               (Lorg/scalatest/Doc$Snippet;)Lorg/scalatest/Suite;
  #247 = NameAndType        #245:#246     // $anonfun$nestedSuites$2:(Lorg/scalatest/Doc$Snippet;)Lorg/scalatest/Suite;
  #248 = InterfaceMethodref #2.#247       // org/scalatest/Doc.$anonfun$nestedSuites$2:(Lorg/scalatest/Doc$Snippet;)Lorg/scalatest/Suite;
  #249 = MethodHandle       6:#248        // REF_invokeStatic org/scalatest/Doc.$anonfun$nestedSuites$2:(Lorg/scalatest/Doc$Snippet;)Lorg/scalatest/Suite;
  #250 = MethodType         #246          //  (Lorg/scalatest/Doc$Snippet;)Lorg/scalatest/Suite;
  #251 = InvokeDynamic      #1:#237       // #1:apply:()Lscala/Function1;
  #252 = Utf8               scala/collection/WithFilter
  #253 = Class              #252          // scala/collection/WithFilter
  #254 = Utf8               map
  #255 = Utf8               (Lscala/Function1;)Ljava/lang/Object;
  #256 = NameAndType        #254:#255     // map:(Lscala/Function1;)Ljava/lang/Object;
  #257 = Methodref          #253.#256     // scala/collection/WithFilter.map:(Lscala/Function1;)Ljava/lang/Object;
  #258 = Utf8               scala/collection/immutable/IndexedSeq
  #259 = Class              #258          // scala/collection/immutable/IndexedSeq
  #260 = Utf8               runNestedSuites$
  #261 = Utf8               (Lorg/scalatest/Doc;Lorg/scalatest/Args;)Lorg/scalatest/Status;
  #262 = Utf8               args
  #263 = Utf8               runNestedSuites
  #264 = Utf8               (Lorg/scalatest/Args;)Lorg/scalatest/Status;
  #265 = NameAndType        #263:#264     // runNestedSuites:(Lorg/scalatest/Args;)Lorg/scalatest/Status;
  #266 = InterfaceMethodref #2.#265       // org/scalatest/Doc.runNestedSuites:(Lorg/scalatest/Args;)Lorg/scalatest/Status;
  #267 = Utf8               Lorg/scalatest/Args;
  #268 = Utf8               scala/collection/mutable/ListBuffer
  #269 = Class              #268          // scala/collection/mutable/ListBuffer
  #270 = Utf8               ()V
  #271 = NameAndType        #69:#270      // "<init>":()V
  #272 = Methodref          #269.#271     // scala/collection/mutable/ListBuffer."<init>":()V
  #273 = Utf8               $anonfun$runNestedSuites$1$adapted
  #274 = Utf8               (Lorg/scalatest/Doc;Lorg/scalatest/Args;Lscala/collection/mutable/ListBuffer;Lorg/scalatest/Doc$Snippet;)Ljava/lang/Object;
  #275 = NameAndType        #273:#274     // $anonfun$runNestedSuites$1$adapted:(Lorg/scalatest/Doc;Lorg/scalatest/Args;Lscala/collection/mutable/ListBuffer;Lorg/scalatest/Doc$Snippet;)Ljava/lang/Object;
  #276 = InterfaceMethodref #2.#275       // org/scalatest/Doc.$anonfun$runNestedSuites$1$adapted:(Lorg/scalatest/Doc;Lorg/scalatest/Args;Lscala/collection/mutable/ListBuffer;Lorg/scalatest/Doc$Snippet;)Ljava/lang/Object;
  #277 = MethodHandle       6:#276        // REF_invokeStatic org/scalatest/Doc.$anonfun$runNestedSuites$1$adapted:(Lorg/scalatest/Doc;Lorg/scalatest/Args;Lscala/collection/mutable/ListBuffer;Lorg/scalatest/Doc$Snippet;)Ljava/lang/Object;
  #278 = Utf8               (Lorg/scalatest/Doc;Lorg/scalatest/Args;Lscala/collection/mutable/ListBuffer;)Lscala/Function1;
  #279 = NameAndType        #170:#278     // apply:(Lorg/scalatest/Doc;Lorg/scalatest/Args;Lscala/collection/mutable/ListBuffer;)Lscala/Function1;
  #280 = InvokeDynamic      #2:#279       // #2:apply:(Lorg/scalatest/Doc;Lorg/scalatest/Args;Lscala/collection/mutable/ListBuffer;)Lscala/Function1;
  #281 = Utf8               foreach
  #282 = Utf8               (Lscala/Function1;)V
  #283 = NameAndType        #281:#282     // foreach:(Lscala/Function1;)V
  #284 = Methodref          #240.#283     // scala/collection/immutable/Vector.foreach:(Lscala/Function1;)V
  #285 = Utf8               org/scalatest/CompositeStatus
  #286 = Class              #285          // org/scalatest/CompositeStatus
  #287 = Utf8               Set
  #288 = Utf8               ()Lscala/collection/immutable/Set$;
  #289 = NameAndType        #287:#288     // Set:()Lscala/collection/immutable/Set$;
  #290 = Methodref          #144.#289     // scala/Predef$.Set:()Lscala/collection/immutable/Set$;
  #291 = Utf8               scala/collection/immutable/Set$
  #292 = Class              #291          // scala/collection/immutable/Set$
  #293 = Utf8               empty
  #294 = Utf8               ()Lscala/collection/immutable/Set;
  #295 = NameAndType        #293:#294     // empty:()Lscala/collection/immutable/Set;
  #296 = Methodref          #292.#295     // scala/collection/immutable/Set$.empty:()Lscala/collection/immutable/Set;
  #297 = Utf8               scala/collection/immutable/Set
  #298 = Class              #297          // scala/collection/immutable/Set
  #299 = Utf8               $plus$plus
  #300 = Utf8               (Lscala/collection/IterableOnce;)Lscala/collection/SetOps;
  #301 = NameAndType        #299:#300     // $plus$plus:(Lscala/collection/IterableOnce;)Lscala/collection/SetOps;
  #302 = InterfaceMethodref #298.#301     // scala/collection/immutable/Set.$plus$plus:(Lscala/collection/IterableOnce;)Lscala/collection/SetOps;
  #303 = Utf8               (Lscala/collection/immutable/Set;)V
  #304 = NameAndType        #69:#303      // "<init>":(Lscala/collection/immutable/Set;)V
  #305 = Methodref          #286.#304     // org/scalatest/CompositeStatus."<init>":(Lscala/collection/immutable/Set;)V
  #306 = Utf8               statusBuffer
  #307 = Utf8               Lscala/collection/mutable/ListBuffer;
  #308 = Utf8               org/scalatest/Args
  #309 = Class              #308          // org/scalatest/Args
  #310 = Utf8               getSnippets$
  #311 = Utf8               (Lorg/scalatest/Doc;Ljava/lang/String;)Lscala/collection/immutable/Vector;
  #312 = Utf8               Ljava/lang/String;
  #313 = Utf8               (Ljava/lang/String;)Lscala/collection/immutable/Vector<Lorg/scalatest/Doc$Snippet;>;
  #314 = Utf8               scala/package$
  #315 = Class              #314          // scala/package$
  #316 = Utf8               Lscala/package$;
  #317 = NameAndType        #139:#316     // MODULE$:Lscala/package$;
  #318 = Fieldref           #315.#317     // scala/package$.MODULE$:Lscala/package$;
  #319 = Utf8               Vector
  #320 = Utf8               ()Lscala/collection/immutable/Vector$;
  #321 = NameAndType        #319:#320     // Vector:()Lscala/collection/immutable/Vector$;
  #322 = Methodref          #315.#321     // scala/package$.Vector:()Lscala/collection/immutable/Vector$;
  #323 = Utf8               scala/collection/immutable/Vector$
  #324 = Class              #323          // scala/collection/immutable/Vector$
  #325 = NameAndType        #293:#200     // empty:()Lscala/collection/immutable/Vector;
  #326 = Methodref          #324.#325     // scala/collection/immutable/Vector$.empty:()Lscala/collection/immutable/Vector;
  #327 = Utf8               scala/collection/IterableOnceExtensionMethods$
  #328 = Class              #327          // scala/collection/IterableOnceExtensionMethods$
  #329 = Utf8               Lscala/collection/IterableOnceExtensionMethods$;
  #330 = NameAndType        #139:#329     // MODULE$:Lscala/collection/IterableOnceExtensionMethods$;
  #331 = Fieldref           #328.#330     // scala/collection/IterableOnceExtensionMethods$.MODULE$:Lscala/collection/IterableOnceExtensionMethods$;
  #332 = Utf8               scala/collection/IterableOnce$
  #333 = Class              #332          // scala/collection/IterableOnce$
  #334 = Utf8               Lscala/collection/IterableOnce$;
  #335 = NameAndType        #139:#334     // MODULE$:Lscala/collection/IterableOnce$;
  #336 = Fieldref           #333.#335     // scala/collection/IterableOnce$.MODULE$:Lscala/collection/IterableOnce$;
  #337 = Utf8               scala/collection/StringOps$
  #338 = Class              #337          // scala/collection/StringOps$
  #339 = Utf8               Lscala/collection/StringOps$;
  #340 = NameAndType        #139:#339     // MODULE$:Lscala/collection/StringOps$;
  #341 = Fieldref           #338.#340     // scala/collection/StringOps$.MODULE$:Lscala/collection/StringOps$;
  #342 = Utf8               augmentString
  #343 = Utf8               (Ljava/lang/String;)Ljava/lang/String;
  #344 = NameAndType        #342:#343     // augmentString:(Ljava/lang/String;)Ljava/lang/String;
  #345 = Methodref          #144.#344     // scala/Predef$.augmentString:(Ljava/lang/String;)Ljava/lang/String;
  #346 = Utf8               linesIterator$extension
  #347 = Utf8               (Ljava/lang/String;)Lscala/collection/Iterator;
  #348 = NameAndType        #346:#347     // linesIterator$extension:(Ljava/lang/String;)Lscala/collection/Iterator;
  #349 = Methodref          #338.#348     // scala/collection/StringOps$.linesIterator$extension:(Ljava/lang/String;)Lscala/collection/Iterator;
  #350 = Utf8               iterableOnceExtensionMethods
  #351 = Utf8               (Lscala/collection/IterableOnce;)Lscala/collection/IterableOnce;
  #352 = NameAndType        #350:#351     // iterableOnceExtensionMethods:(Lscala/collection/IterableOnce;)Lscala/collection/IterableOnce;
  #353 = Methodref          #333.#352     // scala/collection/IterableOnce$.iterableOnceExtensionMethods:(Lscala/collection/IterableOnce;)Lscala/collection/IterableOnce;
  #354 = Utf8               toIterable$extension
  #355 = Utf8               (Lscala/collection/IterableOnce;)Lscala/collection/Iterable;
  #356 = NameAndType        #354:#355     // toIterable$extension:(Lscala/collection/IterableOnce;)Lscala/collection/Iterable;
  #357 = Methodref          #328.#356     // scala/collection/IterableOnceExtensionMethods$.toIterable$extension:(Lscala/collection/IterableOnce;)Lscala/collection/Iterable;
  #358 = Utf8               (Lscala/collection/IterableOnce;)Ljava/lang/Object;
  #359 = NameAndType        #299:#358     // $plus$plus:(Lscala/collection/IterableOnce;)Ljava/lang/Object;
  #360 = Methodref          #240.#359     // scala/collection/immutable/Vector.$plus$plus:(Lscala/collection/IterableOnce;)Ljava/lang/Object;
  #361 = Utf8               $anonfun$getSnippets$1
  #362 = Utf8               (Ljava/lang/String;)Lscala/Tuple2;
  #363 = NameAndType        #361:#362     // $anonfun$getSnippets$1:(Ljava/lang/String;)Lscala/Tuple2;
  #364 = InterfaceMethodref #2.#363       // org/scalatest/Doc.$anonfun$getSnippets$1:(Ljava/lang/String;)Lscala/Tuple2;
  #365 = MethodHandle       6:#364        // REF_invokeStatic org/scalatest/Doc.$anonfun$getSnippets$1:(Ljava/lang/String;)Lscala/Tuple2;
  #366 = MethodType         #362          //  (Ljava/lang/String;)Lscala/Tuple2;
  #367 = InvokeDynamic      #3:#237       // #3:apply:()Lscala/Function1;
  #368 = Methodref          #240.#256     // scala/collection/immutable/Vector.map:(Lscala/Function1;)Ljava/lang/Object;
  #369 = Utf8               scala/runtime/ScalaRunTime$
  #370 = Class              #369          // scala/runtime/ScalaRunTime$
  #371 = Utf8               Lscala/runtime/ScalaRunTime$;
  #372 = NameAndType        #139:#371     // MODULE$:Lscala/runtime/ScalaRunTime$;
  #373 = Fieldref           #370.#372     // scala/runtime/ScalaRunTime$.MODULE$:Lscala/runtime/ScalaRunTime$;
  #374 = Utf8
  #375 = String             #374          //
  #376 = Utf8               (Lorg/scalatest/Doc;Ljava/lang/String;)V
  #377 = NameAndType        #69:#376      // "<init>":(Lorg/scalatest/Doc;Ljava/lang/String;)V
  #378 = Methodref          #29.#377      // org/scalatest/Doc$Markup."<init>":(Lorg/scalatest/Doc;Ljava/lang/String;)V
  #379 = Utf8               [Ljava/lang/Object;
  #380 = Class              #379          // "[Ljava/lang/Object;"
  #381 = Utf8               wrapRefArray
  #382 = Utf8               ([Ljava/lang/Object;)Lscala/collection/immutable/ArraySeq;
  #383 = NameAndType        #381:#382     // wrapRefArray:([Ljava/lang/Object;)Lscala/collection/immutable/ArraySeq;
  #384 = Methodref          #370.#383     // scala/runtime/ScalaRunTime$.wrapRefArray:([Ljava/lang/Object;)Lscala/collection/immutable/ArraySeq;
  #385 = Utf8               (Lscala/collection/immutable/Seq;)Ljava/lang/Object;
  #386 = NameAndType        #170:#385     // apply:(Lscala/collection/immutable/Seq;)Ljava/lang/Object;
  #387 = Methodref          #324.#386     // scala/collection/immutable/Vector$.apply:(Lscala/collection/immutable/Seq;)Ljava/lang/Object;
  #388 = Utf8               (Ljava/lang/Object;Ljava/lang/Object;)Ljava/lang/Object;
  #389 = MethodType         #388          //  (Ljava/lang/Object;Ljava/lang/Object;)Ljava/lang/Object;
  #390 = Utf8               $anonfun$getSnippets$2
  #391 = Utf8               (Lorg/scalatest/Doc;Lscala/collection/immutable/Vector;Lscala/Tuple2;)Lscala/collection/immutable/Vector;
  #392 = NameAndType        #390:#391     // $anonfun$getSnippets$2:(Lorg/scalatest/Doc;Lscala/collection/immutable/Vector;Lscala/Tuple2;)Lscala/collection/immutable/Vector;
  #393 = InterfaceMethodref #2.#392       // org/scalatest/Doc.$anonfun$getSnippets$2:(Lorg/scalatest/Doc;Lscala/collection/immutable/Vector;Lscala/Tuple2;)Lscala/collection/immutable/Vector;
  #394 = MethodHandle       6:#393        // REF_invokeStatic org/scalatest/Doc.$anonfun$getSnippets$2:(Lorg/scalatest/Doc;Lscala/collection/immutable/Vector;Lscala/Tuple2;)Lscala/collection/immutable/Vector;
  #395 = Utf8               (Lscala/collection/immutable/Vector;Lscala/Tuple2;)Lscala/collection/immutable/Vector;
  #396 = MethodType         #395          //  (Lscala/collection/immutable/Vector;Lscala/Tuple2;)Lscala/collection/immutable/Vector;
  #397 = Utf8               (Lorg/scalatest/Doc;)Lscala/Function2;
  #398 = NameAndType        #170:#397     // apply:(Lorg/scalatest/Doc;)Lscala/Function2;
  #399 = InvokeDynamic      #4:#398       // #4:apply:(Lorg/scalatest/Doc;)Lscala/Function2;
  #400 = Utf8               $div$colon
  #401 = Utf8               (Ljava/lang/Object;Lscala/Function2;)Ljava/lang/Object;
  #402 = NameAndType        #400:#401     // $div$colon:(Ljava/lang/Object;Lscala/Function2;)Ljava/lang/Object;
  #403 = Methodref          #240.#402     // scala/collection/immutable/Vector.$div$colon:(Ljava/lang/Object;Lscala/Function2;)Ljava/lang/Object;
  #404 = Utf8               reverse
  #405 = NameAndType        #404:#114     // reverse:()Ljava/lang/Object;
  #406 = Methodref          #240.#405     // scala/collection/immutable/Vector.reverse:()Ljava/lang/Object;
  #407 = Utf8               lines
  #408 = Utf8               Lscala/collection/immutable/Vector;
  #409 = Utf8               pairs
  #410 = Utf8               backwards
  #411 = Utf8               $anonfun$nestedSuites$1
  #412 = Utf8               (Lorg/scalatest/Doc$Snippet;)Z
  #413 = Utf8               check$ifrefutable$1
  #414 = Utf8               Lorg/scalatest/Doc$Snippet;
  #415 = Utf8               x$2
  #416 = Utf8               ()Lorg/scalatest/Suite;
  #417 = NameAndType        #107:#416     // suite:()Lorg/scalatest/Suite;
  #418 = Methodref          #23.#417      // org/scalatest/Doc$IncludedSuite.suite:()Lorg/scalatest/Suite;
  #419 = Utf8               $anonfun$runNestedSuites$1
  #420 = Utf8               (Lorg/scalatest/Doc;Lorg/scalatest/Args;Lscala/collection/mutable/ListBuffer;Lorg/scalatest/Doc$Snippet;)V
  #421 = Utf8               args$1
  #422 = Utf8               statusBuffer$1
  #423 = Utf8               x0$1
  #424 = Methodref          #29.#98       // org/scalatest/Doc$Markup.text:()Ljava/lang/String;
  #425 = Utf8               org/scalatest/Suite$
  #426 = Class              #425          // org/scalatest/Suite$
  #427 = Utf8               Lorg/scalatest/Suite$;
  #428 = NameAndType        #139:#427     // MODULE$:Lorg/scalatest/Suite$;
  #429 = Fieldref           #426.#428     // org/scalatest/Suite$.MODULE$:Lorg/scalatest/Suite$;
  #430 = Utf8               reporter
  #431 = Utf8               ()Lorg/scalatest/Reporter;
  #432 = NameAndType        #430:#431     // reporter:()Lorg/scalatest/Reporter;
  #433 = Methodref          #309.#432     // org/scalatest/Args.reporter:()Lorg/scalatest/Reporter;
  #434 = Utf8               tracker
  #435 = Utf8               ()Lorg/scalatest/Tracker;
  #436 = NameAndType        #434:#435     // tracker:()Lorg/scalatest/Tracker;
  #437 = Methodref          #309.#436     // org/scalatest/Args.tracker:()Lorg/scalatest/Tracker;
  #438 = Utf8               scala/None$
  #439 = Class              #438          // scala/None$
  #440 = Utf8               Lscala/None$;
  #441 = NameAndType        #139:#440     // MODULE$:Lscala/None$;
  #442 = Fieldref           #439.#441     // scala/None$.MODULE$:Lscala/None$;
  #443 = Utf8               org/scalatest/Doc$
  #444 = Class              #443          // org/scalatest/Doc$
  #445 = Utf8               Lorg/scalatest/Doc$;
  #446 = NameAndType        #139:#445     // MODULE$:Lorg/scalatest/Doc$;
  #447 = Fieldref           #444.#446     // org/scalatest/Doc$.MODULE$:Lorg/scalatest/Doc$;
  #448 = Utf8               stripMargin
  #449 = NameAndType        #448:#343     // stripMargin:(Ljava/lang/String;)Ljava/lang/String;
  #450 = Methodref          #444.#449     // org/scalatest/Doc$.stripMargin:(Ljava/lang/String;)Ljava/lang/String;
  #451 = Utf8               trimMarkup
  #452 = NameAndType        #451:#343     // trimMarkup:(Ljava/lang/String;)Ljava/lang/String;
  #453 = Methodref          #444.#452     // org/scalatest/Doc$.trimMarkup:(Ljava/lang/String;)Ljava/lang/String;
  #454 = Utf8               reportMarkupProvided$default$9
  #455 = Utf8               ()Z
  #456 = NameAndType        #454:#455     // reportMarkupProvided$default$9:()Z
  #457 = Methodref          #426.#456     // org/scalatest/Suite$.reportMarkupProvided$default$9:()Z
  #458 = Utf8               reportMarkupProvided
  #459 = Utf8               (Lorg/scalatest/Suite;Lorg/scalatest/Reporter;Lorg/scalatest/Tracker;Lscala/Option;Ljava/lang/String;ILscala/Option;ZZ)V
  #460 = NameAndType        #458:#459     // reportMarkupProvided:(Lorg/scalatest/Suite;Lorg/scalatest/Reporter;Lorg/scalatest/Tracker;Lscala/Option;Ljava/lang/String;ILscala/Option;ZZ)V
  #461 = Methodref          #426.#460     // org/scalatest/Suite$.reportMarkupProvided:(Lorg/scalatest/Suite;Lorg/scalatest/Reporter;Lorg/scalatest/Tracker;Lscala/Option;Ljava/lang/String;ILscala/Option;ZZ)V
  #462 = Utf8               scala/runtime/BoxedUnit
  #463 = Class              #462          // scala/runtime/BoxedUnit
  #464 = Utf8               UNIT
  #465 = Utf8               Lscala/runtime/BoxedUnit;
  #466 = NameAndType        #464:#465     // UNIT:Lscala/runtime/BoxedUnit;
  #467 = Fieldref           #463.#466     // scala/runtime/BoxedUnit.UNIT:Lscala/runtime/BoxedUnit;
  #468 = Utf8               Send SuiteStarting ...
  #469 = String             #468          // Send SuiteStarting ...
  #470 = Utf8               println
  #471 = NameAndType        #470:#100     // println:(Ljava/lang/Object;)V
  #472 = Methodref          #144.#471     // scala/Predef$.println:(Ljava/lang/Object;)V
  #473 = Utf8               run
  #474 = Utf8               (Lscala/Option;Lorg/scalatest/Args;)Lorg/scalatest/Status;
  #475 = NameAndType        #473:#474     // run:(Lscala/Option;Lorg/scalatest/Args;)Lorg/scalatest/Status;
  #476 = InterfaceMethodref #6.#475       // org/scalatest/Suite.run:(Lscala/Option;Lorg/scalatest/Args;)Lorg/scalatest/Status;
  #477 = Utf8               $plus$eq
  #478 = Utf8               (Ljava/lang/Object;)Lscala/collection/mutable/Growable;
  #479 = NameAndType        #477:#478     // $plus$eq:(Ljava/lang/Object;)Lscala/collection/mutable/Growable;
  #480 = Methodref          #269.#479     // scala/collection/mutable/ListBuffer.$plus$eq:(Ljava/lang/Object;)Lscala/collection/mutable/Growable;
  #481 = Utf8               Send SuiteCompleted or Aborted ...
  #482 = String             #481          // Send SuiteCompleted or Aborted ...
  #483 = Utf8               line
  #484 = Utf8               trim
  #485 = NameAndType        #484:#97      // trim:()Ljava/lang/String;
  #486 = Methodref          #208.#485     // java/lang/String.trim:()Ljava/lang/String;
  #487 = Utf8               include[
  #488 = String             #487          // include[
  #489 = Utf8               startsWith
  #490 = Utf8               (Ljava/lang/String;)Z
  #491 = NameAndType        #489:#490     // startsWith:(Ljava/lang/String;)Z
  #492 = Methodref          #208.#491     // java/lang/String.startsWith:(Ljava/lang/String;)Z
  #493 = Utf8               ]
  #494 = String             #493          // ]
  #495 = Utf8               endsWith
  #496 = NameAndType        #495:#490     // endsWith:(Ljava/lang/String;)Z
  #497 = Methodref          #208.#496     // java/lang/String.endsWith:(Ljava/lang/String;)Z
  #498 = Utf8               substring
  #499 = Utf8               (I)Ljava/lang/String;
  #500 = NameAndType        #498:#499     // substring:(I)Ljava/lang/String;
  #501 = Methodref          #208.#500     // java/lang/String.substring:(I)Ljava/lang/String;
  #502 = Utf8               init$extension
  #503 = NameAndType        #502:#343     // init$extension:(Ljava/lang/String;)Ljava/lang/String;
  #504 = Methodref          #338.#503     // scala/collection/StringOps$.init$extension:(Ljava/lang/String;)Ljava/lang/String;
  #505 = Utf8               trimmed
  #506 = Utf8               left
  #507 = Utf8               right
  #508 = Utf8               value
  #509 = NameAndType        #508:#114     // value:()Ljava/lang/Object;
  #510 = Methodref          #93.#509      // scala/Some.value:()Ljava/lang/Object;
  #511 = NameAndType        #170:#62      // apply:(Ljava/lang/Object;)Ljava/lang/Object;
  #512 = InterfaceMethodref #132.#511     // scala/collection/immutable/Map.apply:(Ljava/lang/Object;)Ljava/lang/Object;
  #513 = Utf8               (Lorg/scalatest/Doc;Lorg/scalatest/Suite;)V
  #514 = NameAndType        #69:#513      // "<init>":(Lorg/scalatest/Doc;Lorg/scalatest/Suite;)V
  #515 = Methodref          #23.#514      // org/scalatest/Doc$IncludedSuite."<init>":(Lorg/scalatest/Doc;Lorg/scalatest/Suite;)V
  #516 = Utf8               $plus$colon
  #517 = NameAndType        #516:#62      // $plus$colon:(Ljava/lang/Object;)Ljava/lang/Object;
  #518 = Methodref          #240.#517     // scala/collection/immutable/Vector.$plus$colon:(Ljava/lang/Object;)Ljava/lang/Object;
  #519 = Utf8               equals
  #520 = Utf8               (Ljava/lang/Object;)Z
  #521 = NameAndType        #519:#520     // equals:(Ljava/lang/Object;)Z
  #522 = Methodref          #4.#521       // java/lang/Object.equals:(Ljava/lang/Object;)Z
  #523 = Utf8               head
  #524 = NameAndType        #523:#114     // head:()Ljava/lang/Object;
  #525 = Methodref          #240.#524     // scala/collection/immutable/Vector.head:()Ljava/lang/Object;
  #526 = Utf8               \n
  #527 = String             #526          // \n
  #528 = Utf8               tail
  #529 = NameAndType        #528:#200     // tail:()Lscala/collection/immutable/Vector;
  #530 = Methodref          #240.#529     // scala/collection/immutable/Vector.tail:()Lscala/collection/immutable/Vector;
  #531 = Utf8               key
  #532 = Utf8               Lscala/Tuple2;
  #533 = Utf8               $init$
  #534 = Utf8               (Lorg/scalatest/Doc;)V
  #535 = Utf8               Map
  #536 = Utf8               ()Lscala/collection/immutable/Map$;
  #537 = NameAndType        #535:#536     // Map:()Lscala/collection/immutable/Map$;
  #538 = Methodref          #144.#537     // scala/Predef$.Map:()Lscala/collection/immutable/Map$;
  #539 = Utf8               scala/collection/immutable/Nil$
  #540 = Class              #539          // scala/collection/immutable/Nil$
  #541 = Utf8               Lscala/collection/immutable/Nil$;
  #542 = NameAndType        #139:#541     // MODULE$:Lscala/collection/immutable/Nil$;
  #543 = Fieldref           #540.#542     // scala/collection/immutable/Nil$.MODULE$:Lscala/collection/immutable/Nil$;
  #544 = Utf8               scala/collection/immutable/Map$
  #545 = Class              #544          // scala/collection/immutable/Map$
  #546 = Methodref          #545.#386     // scala/collection/immutable/Map$.apply:(Lscala/collection/immutable/Seq;)Ljava/lang/Object;
  #547 = Methodref          #60.#101      // java/util/concurrent/atomic/AtomicReference."<init>":(Ljava/lang/Object;)V
  #548 = NameAndType        #46:#47       // org$scalatest$Doc$_setter_$org$scalatest$Doc$$atomic_$eq:(Ljava/util/concurrent/atomic/AtomicReference;)V
  #549 = InterfaceMethodref #2.#548       // org/scalatest/Doc.org$scalatest$Doc$_setter_$org$scalatest$Doc$$atomic_$eq:(Ljava/util/concurrent/atomic/AtomicReference;)V
  #550 = NameAndType        #411:#412     // $anonfun$nestedSuites$1:(Lorg/scalatest/Doc$Snippet;)Z
  #551 = InterfaceMethodref #2.#550       // org/scalatest/Doc.$anonfun$nestedSuites$1:(Lorg/scalatest/Doc$Snippet;)Z
  #552 = Utf8               scala/runtime/BoxesRunTime
  #553 = Class              #552          // scala/runtime/BoxesRunTime
  #554 = Utf8               boxToBoolean
  #555 = Utf8               (Z)Ljava/lang/Boolean;
  #556 = NameAndType        #554:#555     // boxToBoolean:(Z)Ljava/lang/Boolean;
  #557 = Methodref          #553.#556     // scala/runtime/BoxesRunTime.boxToBoolean:(Z)Ljava/lang/Boolean;
  #558 = NameAndType        #419:#420     // $anonfun$runNestedSuites$1:(Lorg/scalatest/Doc;Lorg/scalatest/Args;Lscala/collection/mutable/ListBuffer;Lorg/scalatest/Doc$Snippet;)V
  #559 = InterfaceMethodref #2.#558       // org/scalatest/Doc.$anonfun$runNestedSuites$1:(Lorg/scalatest/Doc;Lorg/scalatest/Args;Lscala/collection/mutable/ListBuffer;Lorg/scalatest/Doc$Snippet;)V
  #560 = Utf8               $deserializeLambda$
  #561 = Utf8               (Ljava/lang/invoke/SerializedLambda;)Ljava/lang/Object;
  #562 = Utf8               scala/runtime/LambdaDeserialize
  #563 = Class              #562          // scala/runtime/LambdaDeserialize
  #564 = Utf8               bootstrap
  #565 = Utf8               (Ljava/lang/invoke/MethodHandles$Lookup;Ljava/lang/String;Ljava/lang/invoke/MethodType;[Ljava/lang/invoke/MethodHandle;)Ljava/lang/invoke/CallSite;
  #566 = NameAndType        #564:#565     // bootstrap:(Ljava/lang/invoke/MethodHandles$Lookup;Ljava/lang/String;Ljava/lang/invoke/MethodType;[Ljava/lang/invoke/MethodHandle;)Ljava/lang/invoke/CallSite;
  #567 = Methodref          #563.#566     // scala/runtime/LambdaDeserialize.bootstrap:(Ljava/lang/invoke/MethodHandles$Lookup;Ljava/lang/String;Ljava/lang/invoke/MethodType;[Ljava/lang/invoke/MethodHandle;)Ljava/lang/invoke/CallSite;
  #568 = MethodHandle       6:#567        // REF_invokeStatic scala/runtime/LambdaDeserialize.bootstrap:(Ljava/lang/invoke/MethodHandles$Lookup;Ljava/lang/String;Ljava/lang/invoke/MethodType;[Ljava/lang/invoke/MethodHandle;)Ljava/lang/invoke/CallSite;
  #569 = Utf8               lambdaDeserialize
  #570 = NameAndType        #569:#561     // lambdaDeserialize:(Ljava/lang/invoke/SerializedLambda;)Ljava/lang/Object;
  #571 = InvokeDynamic      #5:#570       // #5:lambdaDeserialize:(Ljava/lang/invoke/SerializedLambda;)Ljava/lang/Object;
  #572 = Utf8               Signature
  #573 = Utf8               MethodParameters
  #574 = Utf8               Code
  #575 = Utf8               StackMapTable
  #576 = Utf8               LineNumberTable
  #577 = Utf8               LocalVariableTable
  #578 = Utf8               InnerClasses
  #579 = Utf8               SourceFile
  #580 = Utf8               RuntimeVisibleAnnotations
  #581 = Utf8               BootstrapMethods
  #582 = Utf8               ScalaInlineInfo
  #583 = Utf8               ScalaSig
{
  public abstract org.scalatest.Doc$Bundle$ org$scalatest$Doc$$Bundle();
    descriptor: ()Lorg/scalatest/Doc$Bundle$;
    flags: (0x0401) ACC_PUBLIC, ACC_ABSTRACT

  public abstract org.scalatest.Doc$Markup$ Markup();
    descriptor: ()Lorg/scalatest/Doc$Markup$;
    flags: (0x0401) ACC_PUBLIC, ACC_ABSTRACT

  public abstract org.scalatest.Doc$IncludedSuite$ IncludedSuite();
    descriptor: ()Lorg/scalatest/Doc$IncludedSuite$;
    flags: (0x0401) ACC_PUBLIC, ACC_ABSTRACT

  public abstract void org$scalatest$Doc$_setter_$org$scalatest$Doc$$atomic_$eq(java.util.concurrent.atomic.AtomicReference<org.scalatest.Doc$Bundle>);
    descriptor: (Ljava/util/concurrent/atomic/AtomicReference;)V
    flags: (0x0401) ACC_PUBLIC, ACC_ABSTRACT
    Signature: #48                          // (Ljava/util/concurrent/atomic/AtomicReference<Lorg/scalatest/Doc$Bundle;>;)V
    MethodParameters:
      Name                           Flags
      x$1                            final

  public abstract java.util.concurrent.atomic.AtomicReference<org.scalatest.Doc$Bundle> org$scalatest$Doc$$atomic();
    descriptor: ()Ljava/util/concurrent/atomic/AtomicReference;
    flags: (0x0401) ACC_PUBLIC, ACC_ABSTRACT
    Signature: #52                          // ()Ljava/util/concurrent/atomic/AtomicReference<Lorg/scalatest/Doc$Bundle;>;

  private void updateAtomic(org.scalatest.Doc$Bundle, org.scalatest.Doc$Bundle);
    descriptor: (Lorg/scalatest/Doc$Bundle;Lorg/scalatest/Doc$Bundle;)V
    flags: (0x0002) ACC_PRIVATE
    Code:
      stack=3, locals=4, args_size=3
         0: aload_0
         1: invokeinterface #58,  1           // InterfaceMethod org$scalatest$Doc$$atomic:()Ljava/util/concurrent/atomic/AtomicReference;
         6: aload_2
         7: invokevirtual #64                 // Method java/util/concurrent/atomic/AtomicReference.getAndSet:(Ljava/lang/Object;)Ljava/lang/Object;
        10: checkcast     #17                 // class org/scalatest/Doc$Bundle
        13: astore_3
        14: aload_3
        15: aload_1
        16: if_acmpeq     29
        19: new           #66                 // class java/util/ConcurrentModificationException
        22: dup
        23: ldc           #68                 // String concurrentDocSpecMod
        25: invokespecial #72                 // Method java/util/ConcurrentModificationException."<init>":(Ljava/lang/String;)V
        28: athrow
        29: return
      StackMapTable: number_of_entries = 1
        frame_type = 252 /* append */
          offset_delta = 29
          locals = [ class org/scalatest/Doc$Bundle ]
      LineNumberTable:
        line 81: 0
        line 82: 14
        line 83: 19
        line 82: 29
      LocalVariableTable:
        Start  Length  Slot  Name   Signature
           14      15     3 shouldBeOldBundle   Lorg/scalatest/Doc$Bundle;
            0      30     0  this   Lorg/scalatest/Doc;
            0      30     1 oldBundle   Lorg/scalatest/Doc$Bundle;
            0      30     2 newBundle   Lorg/scalatest/Doc$Bundle;
    MethodParameters:
      Name                           Flags
      oldBundle                      final
      newBundle                      final

  public abstract scala.Option<java.lang.String> org$scalatest$Doc$$bodyText();
    descriptor: ()Lscala/Option;
    flags: (0x0401) ACC_PUBLIC, ACC_ABSTRACT
    Signature: #79                          // ()Lscala/Option<Ljava/lang/String;>;

  public abstract void org$scalatest$Doc$$bodyText_$eq(scala.Option<java.lang.String>);
    descriptor: (Lscala/Option;)V
    flags: (0x0401) ACC_PUBLIC, ACC_ABSTRACT
    Signature: #82                          // (Lscala/Option<Ljava/lang/String;>;)V
    MethodParameters:
      Name                           Flags
      x$1                            final

  public static void body$(org.scalatest.Doc, scala.xml.Elem);
    descriptor: (Lorg/scalatest/Doc;Lscala/xml/Elem;)V
    flags: (0x1009) ACC_PUBLIC, ACC_STATIC, ACC_SYNTHETIC
    Code:
      stack=2, locals=2, args_size=2
         0: aload_0
         1: aload_1
         2: invokespecial #90                 // InterfaceMethod body:(Lscala/xml/Elem;)V
         5: return
      LineNumberTable:
        line 90: 0
      LocalVariableTable:
        Start  Length  Slot  Name   Signature
            0       6     0 $this   Lorg/scalatest/Doc;
            0       6     1  elem   Lscala/xml/Elem;
    MethodParameters:
      Name                           Flags
      $this                          final synthetic
      elem                           final

  public default void body(scala.xml.Elem);
    descriptor: (Lscala/xml/Elem;)V
    flags: (0x0001) ACC_PUBLIC
    Code:
      stack=4, locals=2, args_size=2
         0: aload_0
         1: new           #93                 // class scala/Some
         4: dup
         5: aload_1
         6: invokevirtual #99                 // Method scala/xml/Elem.text:()Ljava/lang/String;
         9: invokespecial #102                // Method scala/Some."<init>":(Ljava/lang/Object;)V
        12: invokeinterface #104,  2          // InterfaceMethod org$scalatest$Doc$$bodyText_$eq:(Lscala/Option;)V
        17: return
      LineNumberTable:
        line 91: 0
      LocalVariableTable:
        Start  Length  Slot  Name   Signature
            0      18     0  this   Lorg/scalatest/Doc;
            0      18     1  elem   Lscala/xml/Elem;
    MethodParameters:
      Name                           Flags
      elem                           final

  public static java.lang.String include$(org.scalatest.Doc, org.scalatest.Suite);
    descriptor: (Lorg/scalatest/Doc;Lorg/scalatest/Suite;)Ljava/lang/String;
    flags: (0x1009) ACC_PUBLIC, ACC_STATIC, ACC_SYNTHETIC
    Code:
      stack=2, locals=2, args_size=2
         0: aload_0
         1: aload_1
         2: invokespecial #111                // InterfaceMethod include:(Lorg/scalatest/Suite;)Ljava/lang/String;
         5: areturn
      LineNumberTable:
        line 94: 0
      LocalVariableTable:
        Start  Length  Slot  Name   Signature
            0       6     0 $this   Lorg/scalatest/Doc;
            0       6     1 suite   Lorg/scalatest/Suite;
    MethodParameters:
      Name                           Flags
      $this                          final synthetic
      suite                          final

  public default java.lang.String include(org.scalatest.Suite);
    descriptor: (Lorg/scalatest/Suite;)Ljava/lang/String;
    flags: (0x0001) ACC_PUBLIC
    Code:
      stack=5, locals=10, args_size=2
         0: aload_0
         1: invokeinterface #58,  1           // InterfaceMethod org$scalatest$Doc$$atomic:()Ljava/util/concurrent/atomic/AtomicReference;
         6: invokevirtual #116                // Method java/util/concurrent/atomic/AtomicReference.get:()Ljava/lang/Object;
         9: checkcast     #17                 // class org/scalatest/Doc$Bundle
        12: astore_3
        13: aload_3
        14: invokevirtual #120                // Method org/scalatest/Doc$Bundle.unpack:()Lscala/Tuple2;
        17: astore        5
        19: aload         5
        21: ifnull        59
        24: aload         5
        26: invokevirtual #125                // Method scala/Tuple2._1:()Ljava/lang/Object;
        29: checkcast     #127                // class scala/Option
        32: astore        6
        34: aload         5
        36: invokevirtual #130                // Method scala/Tuple2._2:()Ljava/lang/Object;
        39: checkcast     #132                // class scala/collection/immutable/Map
        42: astore        7
        44: new           #122                // class scala/Tuple2
        47: dup
        48: aload         6
        50: aload         7
        52: invokespecial #135                // Method scala/Tuple2."<init>":(Ljava/lang/Object;Ljava/lang/Object;)V
        55: astore_2
        56: goto          72
        59: goto          62
        62: new           #137                // class scala/MatchError
        65: dup
        66: aload         5
        68: invokespecial #138                // Method scala/MatchError."<init>":(Ljava/lang/Object;)V
        71: athrow
        72: aload_2
        73: astore        4
        75: aload         4
        77: invokevirtual #125                // Method scala/Tuple2._1:()Ljava/lang/Object;
        80: checkcast     #127                // class scala/Option
        83: astore        8
        85: aload         4
        87: invokevirtual #130                // Method scala/Tuple2._2:()Ljava/lang/Object;
        90: checkcast     #132                // class scala/collection/immutable/Map
        93: astore        9
        95: aload         9
        97: getstatic     #142                // Field scala/Predef$ArrowAssoc$.MODULE$:Lscala/Predef$ArrowAssoc$;
       100: getstatic     #147                // Field scala/Predef$.MODULE$:Lscala/Predef$;
       103: aload_1
       104: invokevirtual #151                // Method java/lang/Object.getClass:()Ljava/lang/Class;
       107: invokevirtual #156                // Method java/lang/Class.getName:()Ljava/lang/String;
       110: invokevirtual #159                // Method scala/Predef$.ArrowAssoc:(Ljava/lang/Object;)Ljava/lang/Object;
       113: aload_1
       114: invokevirtual #163                // Method scala/Predef$ArrowAssoc$.$minus$greater$extension:(Ljava/lang/Object;Ljava/lang/Object;)Lscala/Tuple2;
       117: invokeinterface #167,  2          // InterfaceMethod scala/collection/immutable/Map.$plus:(Lscala/Tuple2;)Lscala/collection/immutable/MapOps;
       122: checkcast     #132                // class scala/collection/immutable/Map
       125: astore        9
       127: aload_0
       128: aload_3
       129: aload_0
       130: invokeinterface #169,  1          // InterfaceMethod org$scalatest$Doc$$Bundle:()Lorg/scalatest/Doc$Bundle$;
       135: aload         8
       137: aload         9
       139: invokevirtual #173                // Method org/scalatest/Doc$Bundle$.apply:(Lscala/Option;Lscala/collection/immutable/Map;)Lorg/scalatest/Doc$Bundle;
       142: invokespecial #175                // InterfaceMethod updateAtomic:(Lorg/scalatest/Doc$Bundle;Lorg/scalatest/Doc$Bundle;)V
       145: new           #177                // class java/lang/StringBuilder
       148: dup
       149: ldc           #178                // int 11
       151: invokespecial #181                // Method java/lang/StringBuilder."<init>":(I)V
       154: ldc           #183                // String \ninclude[
       156: invokevirtual #187                // Method java/lang/StringBuilder.append:(Ljava/lang/String;)Ljava/lang/StringBuilder;
       159: aload_1
       160: invokevirtual #151                // Method java/lang/Object.getClass:()Ljava/lang/Class;
       163: invokevirtual #156                // Method java/lang/Class.getName:()Ljava/lang/String;
       166: invokevirtual #187                // Method java/lang/StringBuilder.append:(Ljava/lang/String;)Ljava/lang/StringBuilder;
       169: ldc           #189                // String ]\n
       171: invokevirtual #187                // Method java/lang/StringBuilder.append:(Ljava/lang/String;)Ljava/lang/StringBuilder;
       174: invokevirtual #192                // Method java/lang/StringBuilder.toString:()Ljava/lang/String;
       177: areturn
      StackMapTable: number_of_entries = 3
        frame_type = 255 /* full_frame */
          offset_delta = 59
          locals = [ class org/scalatest/Doc, class org/scalatest/Suite, top, class org/scalatest/Doc$Bundle, top, class scala/Tuple2 ]
          stack = []
        frame_type = 2 /* same */
        frame_type = 255 /* full_frame */
          offset_delta = 9
          locals = [ class org/scalatest/Doc, class org/scalatest/Suite, class scala/Tuple2, class org/scalatest/Doc$Bundle, top, class scala/Tuple2, class scala/Option, class scala/collection/immutable/Map ]
          stack = []
      LineNumberTable:
        line 96: 0
        line 97: 13
        line 99: 95
        line 100: 127
        line 101: 145
      LocalVariableTable:
        Start  Length  Slot  Name   Signature
           34      25     6 registrationThreadName   Lscala/Option;
           44      15     7 registeredSuites   Lscala/collection/immutable/Map;
           13     164     3 oldBundle   Lorg/scalatest/Doc$Bundle;
           85      92     8 registrationThreadName   Lscala/Option;
           95      82     9 registeredSuites   Lscala/collection/immutable/Map;
            0     178     0  this   Lorg/scalatest/Doc;
            0     178     1 suite   Lorg/scalatest/Suite;
    MethodParameters:
      Name                           Flags
      suite                          final

  public static scala.collection.immutable.Vector org$scalatest$Doc$$snippets$(org.scalatest.Doc);
    descriptor: (Lorg/scalatest/Doc;)Lscala/collection/immutable/Vector;
    flags: (0x1009) ACC_PUBLIC, ACC_STATIC, ACC_SYNTHETIC
    Code:
      stack=1, locals=1, args_size=1
         0: aload_0
         1: invokespecial #202                // InterfaceMethod org$scalatest$Doc$$snippets:()Lscala/collection/immutable/Vector;
         4: areturn
      LineNumberTable:
        line 106: 0
      LocalVariableTable:
        Start  Length  Slot  Name   Signature
            0       5     0 $this   Lorg/scalatest/Doc;
    MethodParameters:
      Name                           Flags
      $this                          final synthetic

  public default scala.collection.immutable.Vector<org.scalatest.Doc$Snippet> org$scalatest$Doc$$snippets();
    descriptor: ()Lscala/collection/immutable/Vector;
    flags: (0x0001) ACC_PUBLIC
    Code:
      stack=2, locals=1, args_size=1
         0: aload_0
         1: aload_0
         2: invokeinterface #205,  1          // InterfaceMethod org$scalatest$Doc$$bodyText:()Lscala/Option;
         7: invokevirtual #206                // Method scala/Option.get:()Ljava/lang/Object;
        10: checkcast     #208                // class java/lang/String
        13: invokeinterface #212,  2          // InterfaceMethod getSnippets:(Ljava/lang/String;)Lscala/collection/immutable/Vector;
        18: areturn
      LineNumberTable:
        line 106: 0
      LocalVariableTable:
        Start  Length  Slot  Name   Signature
            0      19     0  this   Lorg/scalatest/Doc;
    Signature: #203                         // ()Lscala/collection/immutable/Vector<Lorg/scalatest/Doc$Snippet;>;

  public static scala.collection.immutable.IndexedSeq nestedSuites$(org.scalatest.Doc);
    descriptor: (Lorg/scalatest/Doc;)Lscala/collection/immutable/IndexedSeq;
    flags: (0x1009) ACC_PUBLIC, ACC_STATIC, ACC_SYNTHETIC
    Code:
      stack=1, locals=1, args_size=1
         0: aload_0
         1: invokespecial #218                // InterfaceMethod nestedSuites:()Lscala/collection/immutable/IndexedSeq;
         4: areturn
      LineNumberTable:
        line 112: 0
      LocalVariableTable:
        Start  Length  Slot  Name   Signature
            0       5     0 $this   Lorg/scalatest/Doc;
    MethodParameters:
      Name                           Flags
      $this                          final synthetic

  public default scala.collection.immutable.IndexedSeq<org.scalatest.Suite> nestedSuites();
    descriptor: ()Lscala/collection/immutable/IndexedSeq;
    flags: (0x0001) ACC_PUBLIC
    Code:
      stack=2, locals=1, args_size=1
         0: aload_0
         1: invokeinterface #202,  1          // InterfaceMethod org$scalatest$Doc$$snippets:()Lscala/collection/immutable/Vector;
         6: invokedynamic #238,  0            // InvokeDynamic #0:apply:()Lscala/Function1;
        11: invokevirtual #244                // Method scala/collection/immutable/Vector.withFilter:(Lscala/Function1;)Lscala/collection/WithFilter;
        14: invokedynamic #251,  0            // InvokeDynamic #1:apply:()Lscala/Function1;
        19: invokevirtual #257                // Method scala/collection/WithFilter.map:(Lscala/Function1;)Ljava/lang/Object;
        22: checkcast     #259                // class scala/collection/immutable/IndexedSeq
        25: areturn
      LineNumberTable:
        line 112: 0
      LocalVariableTable:
        Start  Length  Slot  Name   Signature
            0      26     0  this   Lorg/scalatest/Doc;
    Signature: #219                         // ()Lscala/collection/immutable/IndexedSeq<Lorg/scalatest/Suite;>;

  public static org.scalatest.Status runNestedSuites$(org.scalatest.Doc, org.scalatest.Args);
    descriptor: (Lorg/scalatest/Doc;Lorg/scalatest/Args;)Lorg/scalatest/Status;
    flags: (0x1009) ACC_PUBLIC, ACC_STATIC, ACC_SYNTHETIC
    Code:
      stack=2, locals=2, args_size=2
         0: aload_0
         1: aload_1
         2: invokespecial #266                // InterfaceMethod runNestedSuites:(Lorg/scalatest/Args;)Lorg/scalatest/Status;
         5: areturn
      LineNumberTable:
        line 127: 0
      LocalVariableTable:
        Start  Length  Slot  Name   Signature
            0       6     0 $this   Lorg/scalatest/Doc;
            0       6     1  args   Lorg/scalatest/Args;
    MethodParameters:
      Name                           Flags
      $this                          final synthetic
      args                           final

  public default org.scalatest.Status runNestedSuites(org.scalatest.Args);
    descriptor: (Lorg/scalatest/Args;)Lorg/scalatest/Status;
    flags: (0x0001) ACC_PUBLIC
    Code:
      stack=4, locals=7, args_size=2
         0: new           #269                // class scala/collection/mutable/ListBuffer
         3: dup
         4: invokespecial #272                // Method scala/collection/mutable/ListBuffer."<init>":()V
         7: astore_3
         8: aload_0
         9: invokeinterface #58,  1           // InterfaceMethod org$scalatest$Doc$$atomic:()Ljava/util/concurrent/atomic/AtomicReference;
        14: invokevirtual #116                // Method java/util/concurrent/atomic/AtomicReference.get:()Ljava/lang/Object;
        17: checkcast     #17                 // class org/scalatest/Doc$Bundle
        20: invokevirtual #120                // Method org/scalatest/Doc$Bundle.unpack:()Lscala/Tuple2;
        23: astore        5
        25: aload         5
        27: ifnull        46
        30: aload         5
        32: invokevirtual #130                // Method scala/Tuple2._2:()Ljava/lang/Object;
        35: checkcast     #132                // class scala/collection/immutable/Map
        38: astore        6
        40: aload         6
        42: astore_2
        43: goto          59
        46: goto          49
        49: new           #137                // class scala/MatchError
        52: dup
        53: aload         5
        55: invokespecial #138                // Method scala/MatchError."<init>":(Ljava/lang/Object;)V
        58: athrow
        59: aload_2
        60: astore        4
        62: aload_0
        63: invokeinterface #202,  1          // InterfaceMethod org$scalatest$Doc$$snippets:()Lscala/collection/immutable/Vector;
        68: aload_0
        69: aload_1
        70: aload_3
        71: invokedynamic #280,  0            // InvokeDynamic #2:apply:(Lorg/scalatest/Doc;Lorg/scalatest/Args;Lscala/collection/mutable/ListBuffer;)Lscala/Function1;
        76: invokevirtual #284                // Method scala/collection/immutable/Vector.foreach:(Lscala/Function1;)V
        79: new           #286                // class org/scalatest/CompositeStatus
        82: dup
        83: getstatic     #147                // Field scala/Predef$.MODULE$:Lscala/Predef$;
        86: invokevirtual #290                // Method scala/Predef$.Set:()Lscala/collection/immutable/Set$;
        89: invokevirtual #296                // Method scala/collection/immutable/Set$.empty:()Lscala/collection/immutable/Set;
        92: aload_3
        93: invokeinterface #302,  2          // InterfaceMethod scala/collection/immutable/Set.$plus$plus:(Lscala/collection/IterableOnce;)Lscala/collection/SetOps;
        98: checkcast     #298                // class scala/collection/immutable/Set
       101: invokespecial #305                // Method org/scalatest/CompositeStatus."<init>":(Lscala/collection/immutable/Set;)V
       104: areturn
      StackMapTable: number_of_entries = 3
        frame_type = 255 /* full_frame */
          offset_delta = 46
          locals = [ class org/scalatest/Doc, class org/scalatest/Args, top, class scala/collection/mutable/ListBuffer, top, class scala/Tuple2 ]
          stack = []
        frame_type = 2 /* same */
        frame_type = 255 /* full_frame */
          offset_delta = 9
          locals = [ class org/scalatest/Doc, class org/scalatest/Args, class scala/collection/immutable/Map, class scala/collection/mutable/ListBuffer, top, class scala/Tuple2, class scala/collection/immutable/Map ]
          stack = []
      LineNumberTable:
        line 131: 0
        line 133: 8
        line 134: 62
        line 142: 79
      LocalVariableTable:
        Start  Length  Slot  Name   Signature
           40       6     6 registeredSuites   Lscala/collection/immutable/Map;
            8      96     3 statusBuffer   Lscala/collection/mutable/ListBuffer;
           62      42     4 registeredSuites   Lscala/collection/immutable/Map;
            0     105     0  this   Lorg/scalatest/Doc;
            0     105     1  args   Lorg/scalatest/Args;
    MethodParameters:
      Name                           Flags
      args                           final

  public static scala.collection.immutable.Vector getSnippets$(org.scalatest.Doc, java.lang.String);
    descriptor: (Lorg/scalatest/Doc;Ljava/lang/String;)Lscala/collection/immutable/Vector;
    flags: (0x1009) ACC_PUBLIC, ACC_STATIC, ACC_SYNTHETIC
    Code:
      stack=2, locals=2, args_size=2
         0: aload_0
         1: aload_1
         2: invokespecial #212                // InterfaceMethod getSnippets:(Ljava/lang/String;)Lscala/collection/immutable/Vector;
         5: areturn
      LineNumberTable:
        line 145: 0
      LocalVariableTable:
        Start  Length  Slot  Name   Signature
            0       6     0 $this   Lorg/scalatest/Doc;
            0       6     1  text   Ljava/lang/String;
    MethodParameters:
      Name                           Flags
      $this                          final synthetic
      text                           final

  public default scala.collection.immutable.Vector<org.scalatest.Doc$Snippet> getSnippets(java.lang.String);
    descriptor: (Ljava/lang/String;)Lscala/collection/immutable/Vector;
    flags: (0x0001) ACC_PUBLIC
    Code:
      stack=9, locals=6, args_size=2
         0: getstatic     #318                // Field scala/package$.MODULE$:Lscala/package$;
         3: invokevirtual #322                // Method scala/package$.Vector:()Lscala/collection/immutable/Vector$;
         6: invokevirtual #326                // Method scala/collection/immutable/Vector$.empty:()Lscala/collection/immutable/Vector;
         9: getstatic     #331                // Field scala/collection/IterableOnceExtensionMethods$.MODULE$:Lscala/collection/IterableOnceExtensionMethods$;
        12: getstatic     #336                // Field scala/collection/IterableOnce$.MODULE$:Lscala/collection/IterableOnce$;
        15: getstatic     #341                // Field scala/collection/StringOps$.MODULE$:Lscala/collection/StringOps$;
        18: getstatic     #147                // Field scala/Predef$.MODULE$:Lscala/Predef$;
        21: aload_1
        22: invokevirtual #345                // Method scala/Predef$.augmentString:(Ljava/lang/String;)Ljava/lang/String;
        25: invokevirtual #349                // Method scala/collection/StringOps$.linesIterator$extension:(Ljava/lang/String;)Lscala/collection/Iterator;
        28: invokevirtual #353                // Method scala/collection/IterableOnce$.iterableOnceExtensionMethods:(Lscala/collection/IterableOnce;)Lscala/collection/IterableOnce;
        31: invokevirtual #357                // Method scala/collection/IterableOnceExtensionMethods$.toIterable$extension:(Lscala/collection/IterableOnce;)Lscala/collection/Iterable;
        34: invokevirtual #360                // Method scala/collection/immutable/Vector.$plus$plus:(Lscala/collection/IterableOnce;)Ljava/lang/Object;
        37: checkcast     #240                // class scala/collection/immutable/Vector
        40: astore_2
        41: aload_2
        42: invokedynamic #367,  0            // InvokeDynamic #3:apply:()Lscala/Function1;
        47: invokevirtual #368                // Method scala/collection/immutable/Vector.map:(Lscala/Function1;)Ljava/lang/Object;
        50: checkcast     #240                // class scala/collection/immutable/Vector
        53: astore_3
        54: getstatic     #318                // Field scala/package$.MODULE$:Lscala/package$;
        57: invokevirtual #322                // Method scala/package$.Vector:()Lscala/collection/immutable/Vector$;
        60: getstatic     #373                // Field scala/runtime/ScalaRunTime$.MODULE$:Lscala/runtime/ScalaRunTime$;
        63: iconst_1
        64: anewarray     #35                 // class org/scalatest/Doc$Snippet
        67: dup
        68: iconst_0
        69: new           #29                 // class org/scalatest/Doc$Markup
        72: dup
        73: aload_0
        74: ldc_w         #375                // String
        77: invokespecial #378                // Method org/scalatest/Doc$Markup."<init>":(Lorg/scalatest/Doc;Ljava/lang/String;)V
        80: aastore
        81: checkcast     #380                // class "[Ljava/lang/Object;"
        84: invokevirtual #384                // Method scala/runtime/ScalaRunTime$.wrapRefArray:([Ljava/lang/Object;)Lscala/collection/immutable/ArraySeq;
        87: invokevirtual #387                // Method scala/collection/immutable/Vector$.apply:(Lscala/collection/immutable/Seq;)Ljava/lang/Object;
        90: checkcast     #240                // class scala/collection/immutable/Vector
        93: astore        5
        95: aload_3
        96: aload         5
        98: aload_0
        99: invokedynamic #399,  0            // InvokeDynamic #4:apply:(Lorg/scalatest/Doc;)Lscala/Function2;
       104: invokevirtual #403                // Method scala/collection/immutable/Vector.$div$colon:(Ljava/lang/Object;Lscala/Function2;)Ljava/lang/Object;
       107: checkcast     #240                // class scala/collection/immutable/Vector
       110: astore        4
       112: aload         4
       114: invokevirtual #406                // Method scala/collection/immutable/Vector.reverse:()Ljava/lang/Object;
       117: checkcast     #240                // class scala/collection/immutable/Vector
       120: areturn
      LineNumberTable:
        line 147: 0
        line 149: 41
        line 165: 54
        line 178: 112
      LocalVariableTable:
        Start  Length  Slot  Name   Signature
           41      79     2 lines   Lscala/collection/immutable/Vector;
           54      66     3 pairs   Lscala/collection/immutable/Vector;
          112       8     4 backwards   Lscala/collection/immutable/Vector;
            0     121     0  this   Lorg/scalatest/Doc;
            0     121     1  text   Ljava/lang/String;
    Signature: #313                         // (Ljava/lang/String;)Lscala/collection/immutable/Vector<Lorg/scalatest/Doc$Snippet;>;
    MethodParameters:
      Name                           Flags
      text                           final

  public static boolean $anonfun$nestedSuites$1(org.scalatest.Doc$Snippet);
    descriptor: (Lorg/scalatest/Doc$Snippet;)Z
    flags: (0x1009) ACC_PUBLIC, ACC_STATIC, ACC_SYNTHETIC
    Code:
      stack=1, locals=3, args_size=1
         0: aload_0
         1: astore_2
         2: aload_2
         3: instanceof    #23                 // class org/scalatest/Doc$IncludedSuite
         6: ifeq          14
         9: iconst_1
        10: istore_1
        11: goto          22
        14: goto          17
        17: iconst_0
        18: istore_1
        19: goto          22
        22: iload_1
        23: ireturn
      StackMapTable: number_of_entries = 3
        frame_type = 253 /* append */
          offset_delta = 14
          locals = [ top, class org/scalatest/Doc$Snippet ]
        frame_type = 2 /* same */
        frame_type = 255 /* full_frame */
          offset_delta = 4
          locals = [ class org/scalatest/Doc$Snippet, int, class org/scalatest/Doc$Snippet ]
          stack = []
      LineNumberTable:
        line 112: 0
      LocalVariableTable:
        Start  Length  Slot  Name   Signature
            0      24     0 check$ifrefutable$1   Lorg/scalatest/Doc$Snippet;
    MethodParameters:
      Name                           Flags
      check$ifrefutable$1            final

  public static org.scalatest.Suite $anonfun$nestedSuites$2(org.scalatest.Doc$Snippet);
    descriptor: (Lorg/scalatest/Doc$Snippet;)Lorg/scalatest/Suite;
    flags: (0x1009) ACC_PUBLIC, ACC_STATIC, ACC_SYNTHETIC
    Code:
      stack=3, locals=5, args_size=1
         0: aload_0
         1: astore_2
         2: aload_2
         3: instanceof    #23                 // class org/scalatest/Doc$IncludedSuite
         6: ifeq          26
         9: aload_2
        10: checkcast     #23                 // class org/scalatest/Doc$IncludedSuite
        13: astore_3
        14: aload_3
        15: invokevirtual #418                // Method org/scalatest/Doc$IncludedSuite.suite:()Lorg/scalatest/Suite;
        18: astore        4
        20: aload         4
        22: astore_1
        23: goto          38
        26: goto          29
        29: new           #137                // class scala/MatchError
        32: dup
        33: aload_2
        34: invokespecial #138                // Method scala/MatchError."<init>":(Ljava/lang/Object;)V
        37: athrow
        38: aload_1
        39: areturn
      StackMapTable: number_of_entries = 3
        frame_type = 253 /* append */
          offset_delta = 26
          locals = [ top, class org/scalatest/Doc$Snippet ]
        frame_type = 2 /* same */
        frame_type = 255 /* full_frame */
          offset_delta = 8
          locals = [ class org/scalatest/Doc$Snippet, class org/scalatest/Suite, class org/scalatest/Doc$Snippet, class org/scalatest/Doc$IncludedSuite, class org/scalatest/Suite ]
          stack = []
      LineNumberTable:
        line 112: 0
      LocalVariableTable:
        Start  Length  Slot  Name   Signature
           20       6     4 suite   Lorg/scalatest/Suite;
            0      40     0   x$2   Lorg/scalatest/Doc$Snippet;
    MethodParameters:
      Name                           Flags
      x$2                            final

  public static void $anonfun$runNestedSuites$1(org.scalatest.Doc, org.scalatest.Args, scala.collection.mutable.ListBuffer, org.scalatest.Doc$Snippet);
    descriptor: (Lorg/scalatest/Doc;Lorg/scalatest/Args;Lscala/collection/mutable/ListBuffer;Lorg/scalatest/Doc$Snippet;)V
    flags: (0x1009) ACC_PUBLIC, ACC_STATIC, ACC_SYNTHETIC
    Code:
      stack=10, locals=10, args_size=4
         0: aload_3
         1: astore        5
         3: aload         5
         5: instanceof    #29                 // class org/scalatest/Doc$Markup
         8: ifeq          76
        11: aload         5
        13: checkcast     #29                 // class org/scalatest/Doc$Markup
        16: astore        6
        18: aload         6
        20: invokevirtual #424                // Method org/scalatest/Doc$Markup.text:()Ljava/lang/String;
        23: astore        7
        25: getstatic     #429                // Field org/scalatest/Suite$.MODULE$:Lorg/scalatest/Suite$;
        28: aload_0
        29: aload_1
        30: invokevirtual #433                // Method org/scalatest/Args.reporter:()Lorg/scalatest/Reporter;
        33: aload_1
        34: invokevirtual #437                // Method org/scalatest/Args.tracker:()Lorg/scalatest/Tracker;
        37: getstatic     #442                // Field scala/None$.MODULE$:Lscala/None$;
        40: getstatic     #447                // Field org/scalatest/Doc$.MODULE$:Lorg/scalatest/Doc$;
        43: getstatic     #447                // Field org/scalatest/Doc$.MODULE$:Lorg/scalatest/Doc$;
        46: aload         7
        48: invokevirtual #450                // Method org/scalatest/Doc$.stripMargin:(Ljava/lang/String;)Ljava/lang/String;
        51: invokevirtual #453                // Method org/scalatest/Doc$.trimMarkup:(Ljava/lang/String;)Ljava/lang/String;
        54: iconst_0
        55: getstatic     #442                // Field scala/None$.MODULE$:Lscala/None$;
        58: iconst_1
        59: getstatic     #429                // Field org/scalatest/Suite$.MODULE$:Lorg/scalatest/Suite$;
        62: invokevirtual #457                // Method org/scalatest/Suite$.reportMarkupProvided$default$9:()Z
        65: invokevirtual #461                // Method org/scalatest/Suite$.reportMarkupProvided:(Lorg/scalatest/Suite;Lorg/scalatest/Reporter;Lorg/scalatest/Tracker;Lscala/Option;Ljava/lang/String;ILscala/Option;ZZ)V
        68: getstatic     #467                // Field scala/runtime/BoxedUnit.UNIT:Lscala/runtime/BoxedUnit;
        71: astore        4
        73: goto          156
        76: goto          79
        79: aload         5
        81: instanceof    #23                 // class org/scalatest/Doc$IncludedSuite
        84: ifeq          143
        87: aload         5
        89: checkcast     #23                 // class org/scalatest/Doc$IncludedSuite
        92: astore        8
        94: aload         8
        96: invokevirtual #418                // Method org/scalatest/Doc$IncludedSuite.suite:()Lorg/scalatest/Suite;
        99: astore        9
       101: getstatic     #147                // Field scala/Predef$.MODULE$:Lscala/Predef$;
       104: ldc_w         #469                // String Send SuiteStarting ...
       107: invokevirtual #472                // Method scala/Predef$.println:(Ljava/lang/Object;)V
       110: aload_2
       111: aload         9
       113: getstatic     #442                // Field scala/None$.MODULE$:Lscala/None$;
       116: aload_1
       117: invokeinterface #476,  3          // InterfaceMethod org/scalatest/Suite.run:(Lscala/Option;Lorg/scalatest/Args;)Lorg/scalatest/Status;
       122: invokevirtual #480                // Method scala/collection/mutable/ListBuffer.$plus$eq:(Ljava/lang/Object;)Lscala/collection/mutable/Growable;
       125: pop
       126: getstatic     #147                // Field scala/Predef$.MODULE$:Lscala/Predef$;
       129: ldc_w         #482                // String Send SuiteCompleted or Aborted ...
       132: invokevirtual #472                // Method scala/Predef$.println:(Ljava/lang/Object;)V
       135: getstatic     #467                // Field scala/runtime/BoxedUnit.UNIT:Lscala/runtime/BoxedUnit;
       138: astore        4
       140: goto          156
       143: goto          146
       146: new           #137                // class scala/MatchError
       149: dup
       150: aload         5
       152: invokespecial #138                // Method scala/MatchError."<init>":(Ljava/lang/Object;)V
       155: athrow
       156: return
      StackMapTable: number_of_entries = 5
        frame_type = 253 /* append */
          offset_delta = 76
          locals = [ top, class org/scalatest/Doc$Snippet ]
        frame_type = 2 /* same */
        frame_type = 63 /* same */
        frame_type = 2 /* same */
        frame_type = 255 /* full_frame */
          offset_delta = 9
          locals = [ class org/scalatest/Doc, class org/scalatest/Args, class scala/collection/mutable/ListBuffer, class org/scalatest/Doc$Snippet, class scala/runtime/BoxedUnit, class org/scalatest/Doc$Snippet ]
          stack = []
      LineNumberTable:
        line 134: 0
        line 135: 3
        line 136: 25
        line 135: 76
        line 137: 79
        line 138: 101
        line 139: 110
        line 140: 126
        line 137: 143
        line 134: 146
      LocalVariableTable:
        Start  Length  Slot  Name   Signature
           25      51     7  text   Ljava/lang/String;
          101      42     9 suite   Lorg/scalatest/Suite;
            0     157     0 $this   Lorg/scalatest/Doc;
            0     157     1 args$1   Lorg/scalatest/Args;
            0     157     2 statusBuffer$1   Lscala/collection/mutable/ListBuffer;
            0     157     3  x0$1   Lorg/scalatest/Doc$Snippet;
    MethodParameters:
      Name                           Flags
      $this                          final synthetic
      args$1                         final
      statusBuffer$1                 final
      x0$1                           final

  public static scala.Tuple2 $anonfun$getSnippets$1(java.lang.String);
    descriptor: (Ljava/lang/String;)Lscala/Tuple2;
    flags: (0x1009) ACC_PUBLIC, ACC_STATIC, ACC_SYNTHETIC
    Code:
      stack=6, locals=3, args_size=1
         0: aload_0
         1: invokevirtual #486                // Method java/lang/String.trim:()Ljava/lang/String;
         4: astore_1
         5: aload_1
         6: ldc_w         #488                // String include[
         9: invokevirtual #492                // Method java/lang/String.startsWith:(Ljava/lang/String;)Z
        12: ifeq          53
        15: aload_1
        16: ldc_w         #494                // String ]
        19: invokevirtual #497                // Method java/lang/String.endsWith:(Ljava/lang/String;)Z
        22: ifeq          53
        25: new           #93                 // class scala/Some
        28: dup
        29: getstatic     #341                // Field scala/collection/StringOps$.MODULE$:Lscala/collection/StringOps$;
        32: getstatic     #147                // Field scala/Predef$.MODULE$:Lscala/Predef$;
        35: aload_1
        36: bipush        8
        38: invokevirtual #501                // Method java/lang/String.substring:(I)Ljava/lang/String;
        41: invokevirtual #345                // Method scala/Predef$.augmentString:(Ljava/lang/String;)Ljava/lang/String;
        44: invokevirtual #504                // Method scala/collection/StringOps$.init$extension:(Ljava/lang/String;)Ljava/lang/String;
        47: invokespecial #102                // Method scala/Some."<init>":(Ljava/lang/Object;)V
        50: goto          56
        53: getstatic     #442                // Field scala/None$.MODULE$:Lscala/None$;
        56: astore_2
        57: new           #122                // class scala/Tuple2
        60: dup
        61: aload_0
        62: aload_2
        63: invokespecial #135                // Method scala/Tuple2."<init>":(Ljava/lang/Object;Ljava/lang/Object;)V
        66: areturn
      StackMapTable: number_of_entries = 2
        frame_type = 252 /* append */
          offset_delta = 53
          locals = [ class java/lang/String ]
        frame_type = 66 /* same_locals_1_stack_item */
          stack = [ class scala/Option ]
      LineNumberTable:
        line 150: 0
        line 152: 5
        line 154: 25
        line 157: 53
        line 158: 57
      LocalVariableTable:
        Start  Length  Slot  Name   Signature
            5      61     1 trimmed   Ljava/lang/String;
           57       9     2 suite   Lscala/Option;
            0      67     0  line   Ljava/lang/String;
    MethodParameters:
      Name                           Flags
      line                           final

  public static scala.collection.immutable.Vector $anonfun$getSnippets$2(org.scalatest.Doc, scala.collection.immutable.Vector, scala.Tuple2);
    descriptor: (Lorg/scalatest/Doc;Lscala/collection/immutable/Vector;Lscala/Tuple2;)Lscala/collection/immutable/Vector;
    flags: (0x1009) ACC_PUBLIC, ACC_STATIC, ACC_SYNTHETIC
    Code:
      stack=6, locals=21, args_size=3
         0: aload_2
         1: astore        6
         3: aload         6
         5: ifnull        137
         8: aload         6
        10: invokevirtual #130                // Method scala/Tuple2._2:()Ljava/lang/Object;
        13: checkcast     #127                // class scala/Option
        16: astore        7
        18: aload         7
        20: instanceof    #93                 // class scala/Some
        23: ifeq          134
        26: aload         7
        28: checkcast     #93                 // class scala/Some
        31: astore        8
        33: aload         8
        35: invokevirtual #510                // Method scala/Some.value:()Ljava/lang/Object;
        38: checkcast     #208                // class java/lang/String
        41: astore        9
        43: aload_0
        44: invokeinterface #58,  1           // InterfaceMethod org$scalatest$Doc$$atomic:()Ljava/util/concurrent/atomic/AtomicReference;
        49: invokevirtual #116                // Method java/util/concurrent/atomic/AtomicReference.get:()Ljava/lang/Object;
        52: checkcast     #17                 // class org/scalatest/Doc$Bundle
        55: invokevirtual #120                // Method org/scalatest/Doc$Bundle.unpack:()Lscala/Tuple2;
        58: astore        11
        60: aload         11
        62: ifnull        82
        65: aload         11
        67: invokevirtual #130                // Method scala/Tuple2._2:()Ljava/lang/Object;
        70: checkcast     #132                // class scala/collection/immutable/Map
        73: astore        12
        75: aload         12
        77: astore        5
        79: goto          95
        82: goto          85
        85: new           #137                // class scala/MatchError
        88: dup
        89: aload         11
        91: invokespecial #138                // Method scala/MatchError."<init>":(Ljava/lang/Object;)V
        94: athrow
        95: aload         5
        97: astore        10
        99: new           #23                 // class org/scalatest/Doc$IncludedSuite
       102: dup
       103: aload_0
       104: aload         10
       106: aload         9
       108: invokeinterface #512,  2          // InterfaceMethod scala/collection/immutable/Map.apply:(Ljava/lang/Object;)Ljava/lang/Object;
       113: checkcast     #6                  // class org/scalatest/Suite
       116: invokespecial #515                // Method org/scalatest/Doc$IncludedSuite."<init>":(Lorg/scalatest/Doc;Lorg/scalatest/Suite;)V
       119: astore        13
       121: aload_1
       122: aload         13
       124: invokevirtual #518                // Method scala/collection/immutable/Vector.$plus$colon:(Ljava/lang/Object;)Ljava/lang/Object;
       127: checkcast     #240                // class scala/collection/immutable/Vector
       130: astore_3
       131: goto          313
       134: goto          140
       137: goto          140
       140: aload         6
       142: ifnull        300
       145: aload         6
       147: invokevirtual #125                // Method scala/Tuple2._1:()Ljava/lang/Object;
       150: checkcast     #208                // class java/lang/String
       153: astore        14
       155: aload         6
       157: invokevirtual #130                // Method scala/Tuple2._2:()Ljava/lang/Object;
       160: checkcast     #127                // class scala/Option
       163: astore        15
       165: getstatic     #442                // Field scala/None$.MODULE$:Lscala/None$;
       168: aload         15
       170: invokevirtual #522                // Method java/lang/Object.equals:(Ljava/lang/Object;)Z
       173: ifeq          297
       176: aload_1
       177: invokevirtual #525                // Method scala/collection/immutable/Vector.head:()Ljava/lang/Object;
       180: checkcast     #35                 // class org/scalatest/Doc$Snippet
       183: astore        16
       185: aload         16
       187: instanceof    #29                 // class org/scalatest/Doc$Markup
       190: ifeq          262
       193: aload         16
       195: checkcast     #29                 // class org/scalatest/Doc$Markup
       198: astore        17
       200: aload         17
       202: invokevirtual #424                // Method org/scalatest/Doc$Markup.text:()Ljava/lang/String;
       205: astore        18
       207: new           #29                 // class org/scalatest/Doc$Markup
       210: dup
       211: aload_0
       212: new           #177                // class java/lang/StringBuilder
       215: dup
       216: ldc           #228                // int 1
       218: invokespecial #181                // Method java/lang/StringBuilder."<init>":(I)V
       221: aload         18
       223: invokevirtual #187                // Method java/lang/StringBuilder.append:(Ljava/lang/String;)Ljava/lang/StringBuilder;
       226: ldc_w         #527                // String \n
       229: invokevirtual #187                // Method java/lang/StringBuilder.append:(Ljava/lang/String;)Ljava/lang/StringBuilder;
       232: aload         14
       234: invokevirtual #187                // Method java/lang/StringBuilder.append:(Ljava/lang/String;)Ljava/lang/StringBuilder;
       237: invokevirtual #192                // Method java/lang/StringBuilder.toString:()Ljava/lang/String;
       240: invokespecial #378                // Method org/scalatest/Doc$Markup."<init>":(Lorg/scalatest/Doc;Ljava/lang/String;)V
       243: astore        19
       245: aload_1
       246: invokevirtual #530                // Method scala/collection/immutable/Vector.tail:()Lscala/collection/immutable/Vector;
       249: aload         19
       251: invokevirtual #518                // Method scala/collection/immutable/Vector.$plus$colon:(Ljava/lang/Object;)Ljava/lang/Object;
       254: checkcast     #240                // class scala/collection/immutable/Vector
       257: astore        4
       259: goto          291
       262: goto          265
       265: new           #29                 // class org/scalatest/Doc$Markup
       268: dup
       269: aload_0
       270: aload         14
       272: invokespecial #378                // Method org/scalatest/Doc$Markup."<init>":(Lorg/scalatest/Doc;Ljava/lang/String;)V
       275: astore        20
       277: aload_1
       278: aload         20
       280: invokevirtual #518                // Method scala/collection/immutable/Vector.$plus$colon:(Ljava/lang/Object;)Ljava/lang/Object;
       283: checkcast     #240                // class scala/collection/immutable/Vector
       286: astore        4
       288: goto          291
       291: aload         4
       293: astore_3
       294: goto          313
       297: goto          303
       300: goto          303
       303: new           #137                // class scala/MatchError
       306: dup
       307: aload         6
       309: invokespecial #138                // Method scala/MatchError."<init>":(Ljava/lang/Object;)V
       312: athrow
       313: aload_3
       314: areturn
      StackMapTable: number_of_entries = 13
        frame_type = 255 /* full_frame */
          offset_delta = 82
          locals = [ class org/scalatest/Doc, class scala/collection/immutable/Vector, class scala/Tuple2, top, top, top, class scala/Tuple2, class scala/Option, class scala/Some, class java/lang/String, top, class scala/Tuple2 ]
          stack = []
        frame_type = 2 /* same */
        frame_type = 255 /* full_frame */
          offset_delta = 9
          locals = [ class org/scalatest/Doc, class scala/collection/immutable/Vector, class scala/Tuple2, top, top, class scala/collection/immutable/Map, class scala/Tuple2, class scala/Option, class scala/Some, class java/lang/String, top, class scala/Tuple2, class scala/collection/immutable/Map ]
          stack = []
        frame_type = 255 /* full_frame */
          offset_delta = 38
          locals = [ class org/scalatest/Doc, class scala/collection/immutable/Vector, class scala/Tuple2, top, top, top, class scala/Tuple2, class scala/Option ]
          stack = []
        frame_type = 250 /* chop */
          offset_delta = 2
        frame_type = 2 /* same */
        frame_type = 255 /* full_frame */
          offset_delta = 121
          locals = [ class org/scalatest/Doc, class scala/collection/immutable/Vector, class scala/Tuple2, top, top, top, class scala/Tuple2, top, top, top, top, top, top, top, class java/lang/String, class scala/Option, class org/scalatest/Doc$Snippet ]
          stack = []
        frame_type = 2 /* same */
        frame_type = 255 /* full_frame */
          offset_delta = 25
          locals = [ class org/scalatest/Doc, class scala/collection/immutable/Vector, class scala/Tuple2, top, class scala/collection/immutable/Vector, top, class scala/Tuple2, top, top, top, top, top, top, top, class java/lang/String, class scala/Option, class org/scalatest/Doc$Snippet ]
          stack = []
        frame_type = 255 /* full_frame */
          offset_delta = 5
          locals = [ class org/scalatest/Doc, class scala/collection/immutable/Vector, class scala/Tuple2, top, top, top, class scala/Tuple2, top, top, top, top, top, top, top, class java/lang/String, class scala/Option ]
          stack = []
        frame_type = 255 /* full_frame */
          offset_delta = 2
          locals = [ class org/scalatest/Doc, class scala/collection/immutable/Vector, class scala/Tuple2, top, top, top, class scala/Tuple2 ]
          stack = []
        frame_type = 2 /* same */
        frame_type = 255 /* full_frame */
          offset_delta = 9
          locals = [ class org/scalatest/Doc, class scala/collection/immutable/Vector, class scala/Tuple2, class scala/collection/immutable/Vector, top, top, class scala/Tuple2 ]
          stack = []
      LineNumberTable:
        line 166: 0
        line 167: 3
        line 168: 43
        line 170: 99
        line 167: 134
        line 171: 140
        line 172: 176
        line 173: 185
        line 174: 265
        line 172: 291
        line 171: 297
        line 166: 303
      LocalVariableTable:
        Start  Length  Slot  Name   Signature
           75       7    12 registeredSuites   Lscala/collection/immutable/Map;
           99      31    10 registeredSuites   Lscala/collection/immutable/Map;
           43      91     9   key   Ljava/lang/String;
          207      55    18  text   Ljava/lang/String;
          155     145    14  line   Ljava/lang/String;
            0     315     0 $this   Lorg/scalatest/Doc;
            0     315     1  left   Lscala/collection/immutable/Vector;
            0     315     2 right   Lscala/Tuple2;
    MethodParameters:
      Name                           Flags
      $this                          final synthetic
      left                           final
      right                          final

  public static void $init$(org.scalatest.Doc);
    descriptor: (Lorg/scalatest/Doc;)V
    flags: (0x0009) ACC_PUBLIC, ACC_STATIC
    Code:
      stack=7, locals=1, args_size=1
         0: aload_0
         1: new           #60                 // class java/util/concurrent/atomic/AtomicReference
         4: dup
         5: aload_0
         6: invokeinterface #169,  1          // InterfaceMethod org$scalatest$Doc$$Bundle:()Lorg/scalatest/Doc$Bundle$;
        11: getstatic     #442                // Field scala/None$.MODULE$:Lscala/None$;
        14: getstatic     #147                // Field scala/Predef$.MODULE$:Lscala/Predef$;
        17: invokevirtual #538                // Method scala/Predef$.Map:()Lscala/collection/immutable/Map$;
        20: getstatic     #543                // Field scala/collection/immutable/Nil$.MODULE$:Lscala/collection/immutable/Nil$;
        23: invokevirtual #546                // Method scala/collection/immutable/Map$.apply:(Lscala/collection/immutable/Seq;)Ljava/lang/Object;
        26: checkcast     #132                // class scala/collection/immutable/Map
        29: invokevirtual #173                // Method org/scalatest/Doc$Bundle$.apply:(Lscala/Option;Lscala/collection/immutable/Map;)Lorg/scalatest/Doc$Bundle;
        32: invokespecial #547                // Method java/util/concurrent/atomic/AtomicReference."<init>":(Ljava/lang/Object;)V
        35: invokeinterface #549,  2          // InterfaceMethod org$scalatest$Doc$_setter_$org$scalatest$Doc$$atomic_$eq:(Ljava/util/concurrent/atomic/AtomicReference;)V
        40: aload_0
        41: getstatic     #442                // Field scala/None$.MODULE$:Lscala/None$;
        44: invokeinterface #104,  2          // InterfaceMethod org$scalatest$Doc$$bodyText_$eq:(Lscala/Option;)V
        49: return
      LineNumberTable:
        line 78: 0
        line 89: 40
        line 58: 49
      LocalVariableTable:
        Start  Length  Slot  Name   Signature
            0      50     0 $this   Lorg/scalatest/Doc;
    MethodParameters:
      Name                           Flags
      $this                          final synthetic

  public static java.lang.Object $anonfun$nestedSuites$1$adapted(org.scalatest.Doc$Snippet);
    descriptor: (Lorg/scalatest/Doc$Snippet;)Ljava/lang/Object;
    flags: (0x1009) ACC_PUBLIC, ACC_STATIC, ACC_SYNTHETIC
    Code:
      stack=1, locals=1, args_size=1
         0: aload_0
         1: invokestatic  #551                // InterfaceMethod $anonfun$nestedSuites$1:(Lorg/scalatest/Doc$Snippet;)Z
         4: invokestatic  #557                // Method scala/runtime/BoxesRunTime.boxToBoolean:(Z)Ljava/lang/Boolean;
         7: areturn
      LineNumberTable:
        line 112: 0
      LocalVariableTable:
        Start  Length  Slot  Name   Signature
            0       8     0 check$ifrefutable$1   Lorg/scalatest/Doc$Snippet;
    MethodParameters:
      Name                           Flags
      check$ifrefutable$1            final

  public static java.lang.Object $anonfun$runNestedSuites$1$adapted(org.scalatest.Doc, org.scalatest.Args, scala.collection.mutable.ListBuffer, org.scalatest.Doc$Snippet);
    descriptor: (Lorg/scalatest/Doc;Lorg/scalatest/Args;Lscala/collection/mutable/ListBuffer;Lorg/scalatest/Doc$Snippet;)Ljava/lang/Object;
    flags: (0x1009) ACC_PUBLIC, ACC_STATIC, ACC_SYNTHETIC
    Code:
      stack=4, locals=4, args_size=4
         0: aload_0
         1: aload_1
         2: aload_2
         3: aload_3
         4: invokestatic  #559                // InterfaceMethod $anonfun$runNestedSuites$1:(Lorg/scalatest/Doc;Lorg/scalatest/Args;Lscala/collection/mutable/ListBuffer;Lorg/scalatest/Doc$Snippet;)V
         7: getstatic     #467                // Field scala/runtime/BoxedUnit.UNIT:Lscala/runtime/BoxedUnit;
        10: areturn
      LineNumberTable:
        line 134: 0
      LocalVariableTable:
        Start  Length  Slot  Name   Signature
            0      11     0 $this   Lorg/scalatest/Doc;
            0      11     1 args$1   Lorg/scalatest/Args;
            0      11     2 statusBuffer$1   Lscala/collection/mutable/ListBuffer;
            0      11     3  x0$1   Lorg/scalatest/Doc$Snippet;
    MethodParameters:
      Name                           Flags
      $this                          final
      args$1                         final
      statusBuffer$1                 final
      x0$1                           final

  private static java.lang.Object $deserializeLambda$(java.lang.invoke.SerializedLambda);
    descriptor: (Ljava/lang/invoke/SerializedLambda;)Ljava/lang/Object;
    flags: (0x100a) ACC_PRIVATE, ACC_STATIC, ACC_SYNTHETIC
    Code:
      stack=1, locals=1, args_size=1
         0: aload_0
         1: invokedynamic #571,  0            // InvokeDynamic #5:lambdaDeserialize:(Ljava/lang/invoke/SerializedLambda;)Ljava/lang/Object;
         6: areturn
}
InnerClasses:
  public static final #15= #12 of #14;    // Lookup=class java/lang/invoke/MethodHandles$Lookup of class java/lang/invoke/MethodHandles
  private #18= #17 of #2;                 // Bundle=class org/scalatest/Doc$Bundle of class org/scalatest/Doc
  private #21= #20 of #2;                 // Bundle$=class org/scalatest/Doc$Bundle$ of class org/scalatest/Doc
  public #24= #23 of #2;                  // IncludedSuite=class org/scalatest/Doc$IncludedSuite of class org/scalatest/Doc
  public #27= #26 of #2;                  // IncludedSuite$=class org/scalatest/Doc$IncludedSuite$ of class org/scalatest/Doc
  public #30= #29 of #2;                  // Markup=class org/scalatest/Doc$Markup of class org/scalatest/Doc
  public #33= #32 of #2;                  // Markup$=class org/scalatest/Doc$Markup$ of class org/scalatest/Doc
  public #36= #35 of #2;                  // Snippet=class org/scalatest/Doc$Snippet of class org/scalatest/Doc
  public static #41= #38 of #40;          // ArrowAssoc$=class scala/Predef$ArrowAssoc$ of class scala/Predef
SourceFile: "Doc.scala"
RuntimeVisibleAnnotations:
  0: #8(#9=s#10)
    scala.reflect.ScalaSignature(
      bytes="\u0006\u0005\tef\u0001\u0003%J!\u0003\r\t!S\'\t\u000ba\u0003A\u0011\u0001.\u0007\ty\u0003Aa\u0018\u0005\tA\n\u0011)\u0019!C\u0001C\"A\u0001O\u0001B\u0001B\u0003%!\r\u0003\u0005r\u0005\t\u0015\r\u0011\"\u0001s\u0011!1(A!A!\u0002\u0013\u0019\b\"B<\u0003\t\u0013A\b\"B?\u0003\t\u0003qxaBA\u0003\u0001!%\u0011q\u0001\u0004\u0007=\u0002AI!!\u0003\t\r]TA\u0011AA\u0006\u0011\u001d\tiA\u0003C\u0001\u0003\u001fA\u0011\"!\u0006\u0001\u0005\u0004%i!a\u0006\t\u000f\u0005=\u0002\u0001\"\u0003\u00022!A\u00111\b\u0001A\u0002\u0013%\u0011\rC\u0005\u0002>\u0001\u0001\r\u0011\"\u0003\u0002@!9\u0011Q\t\u0001\u0005\u0002\u0005\u001d\u0003bBA-\u0001\u0011E\u00111\f\u0005\u000b\u0003C\u0002\u0001R1A\u0005\n\u0005\r\u0004B\u0003B\u001a\u0001!\u0015\r\u0011\"\u0012\u00036!9!1\t\u0001\u0005R\t\u0015\u0003\u0002\u0003B,\u0001\u0011\u0005\u0011J!\u0017\u0007\u0015\u0005e\u0004\u0001%A\u0012\"%\u000bYHB\u0004\u0003\f\u0001\u0001\u0015J!\u0004\t\u0015\t=\u0001D!f\u0001\n\u0003\u0011\t\u0002C\u0005\u0003\u0014a\u0011\t\u0012)A\u0005K\"1q\u000f\u0007C\u0001\u0005+A\u0011\"!\'\u0019\u0003\u0003%\tAa\u0007\t\u0013\u0005}\u0005$%A\u0005\u0002\t}\u0001\"CA\\1\u0005\u0005I\u0011IA]\u0011%\t)\rGA\u0001\n\u0003\t9\rC\u0005\u0002Pb\t\t\u0011\"\u0001\u0003$!I\u00111\u001c\r\u0002\u0002\u0013\u0005\u0013Q\u001c\u0005\n\u0003WD\u0012\u0011!C\u0001\u0005OA\u0011\"a>\u0019\u0003\u0003%\tEa\u000b\t\u0013\u0005u\b$!A\u0005B\u0005}\b\"\u0003B\u00011\u0005\u0005I\u0011\tB\u0002\u0011%\u0011)\u0001GA\u0001\n\u0003\u0012yc\u0002\u0006\u0003^\u0001\t\t\u0011#\u0001J\u0005?2!Ba\u0003\u0001\u0003\u0003E\t!\u0013B1\u0011\u00199\b\u0006\"\u0001\u0003z!I!\u0011\u0001\u0015\u0002\u0002\u0013\u0015#1\u0001\u0005\n\u0003\u001bA\u0013\u0011!CA\u0005wB\u0011Ba )\u0003\u0003%\tI!!\u0007\u000f\u0005-\u0005\u0001Q%\u0002\u000e\"Q\u0011qL\u0017\u0003\u0016\u0004%\t!a$\t\u0013\u0005EUF!E!\u0002\u0013!\u0006BB<.\t\u0003\t\u0019\nC\u0005\u0002\u001a6\n\t\u0011\"\u0001\u0002\u001c\"I\u0011qT\u0017\u0012\u0002\u0013\u0005\u0011\u0011\u0015\u0005\n\u0003ok\u0013\u0011!C!\u0003sC\u0011\"!2.\u0003\u0003%\t!a2\t\u0013\u0005=W&!A\u0005\u0002\u0005E\u0007\"CAn[\u0005\u0005I\u0011IAo\u0011%\tY/LA\u0001\n\u0003\ti\u000fC\u0005\u0002x6\n\t\u0011\"\u0011\u0002z\"I\u0011Q`\u0017\u0002\u0002\u0013\u0005\u0013q \u0005\n\u0005\u0003i\u0013\u0011!C!\u0005\u0007A\u0011B!\u0002.\u0003\u0003%\tEa\u0002\b\u0015\t\u001d\u0005!!A\t\u0002%\u0013II\u0002\u0006\u0002\f\u0002\t\t\u0011#\u0001J\u0005\u0017Caa^\u001f\u0005\u0002\t=\u0005\"\u0003B\u0001{\u0005\u0005IQ\tB\u0002\u0011%\ti!PA\u0001\n\u0003\u0013\t\nC\u0005\u0003\u0000u\n\t\u0011\"!\u0003\u0016\u001eA!1T%\t\u0002%\u0013iJB\u0004I\u0013\"\u0005\u0011Ja(\t\r]\u001cE\u0011\u0001BQ\u0011!\u0011\u0019k\u0011C\u0001\u0013\n\u0015\u0006\u0002\u0003BU\u0007\u0012\u0005\u0011Ja+\t\u0013\t=6)!A\u0005\n\tE&a\u0001#pG*\u0011!jS\u0001\ng\u000e\fG.\u0019;fgRT\u0011\u0001T\u0001\u0004_J<7c\u0001\u0001O)B\u0011qJU\u0007\u0002!*\t\u0011+A\u0003tG\u0006d\u0017-\u0003\u0002T!\n1\u0011I\\=SK\u001a\u0004\"!\u0016,\u000e\u0003%K!aV%\u0003\u000bM+\u0018\u000e^3\u0002\r\u0011Jg.\u001b;%\u0007\u0001!\u0012a\u0017\t\u0003\u001frK!!\u0018)\u0003\tUs\u0017\u000e\u001e\u0002\u0007\u0005VtG\r\\3\u0014\u0005\tq\u0015A\u0006:fO&\u001cHO]1uS>tG\u000b\u001b:fC\u0012t\u0015-\\3\u0016\u0003\t\u00042aT2f\u0013\t!\u0007K\u0001\u0004PaRLwN\u001c\t\u0003M6t!aZ6\u0011\u0005!\u0004V\"A5\u000b\u0005)L\u0016A\u0002\u001fs_>$h(\u0003\u0002m!\u00061\u0001K]3eK\u001aL!A\\8\u0003\rM#(/\u001b8h\u0015\ta\u0007+A\fsK\u001eL7\u000f\u001e:bi&|g\u000e\u00165sK\u0006$g*Y7fA\u0005\u0001\"/Z4jgR,\'/\u001a3Tk&$Xm]\u000b\u0002gB!a\r^3U\u0013\t)xNA\u0002NCB\f\u0011C]3hSN$XM]3e\'VLG/Z:!\u0003\u0019a\u0014N\\5u}Q\u0019\u0011p\u001f?\u0011\u0005i\u0014Q\"\u0001\u0001\t\u000b\u0001<\u0001\u0019\u00012\t\u000bE<\u0001\u0019A:\u0002\rUt\u0007/Y2l+\u0005y\b#B(\u0002\u0002\t\u001c\u0018bAA\u0002!\n1A+\u001e9mKJ\naAQ;oI2,\u0007C\u0001>\u000b\'\tQa\n\u0006\u0002\u0002\b\u0005)\u0011\r\u001d9msR)\u00110!\u0005\u0002\u0014!)\u0001\r\u0004a\u0001E\")\u0011\u000f\u0004a\u0001g\u00061\u0011\r^8nS\u000e,\"!!\u0007\u0011\u000b\u0005m\u00111F=\u000e\u0005\u0005u!\u0002BA\u000b\u0003?QA!!\t\u0002$\u0005Q1m\u001c8dkJ\u0014XM\u001c;\u000b\t\u0005\u0015\u0012qE\u0001\u0005kRLGN\u0003\u0002\u0002*\u0005!!.\u0019<b\u0013\u0011\ti#!\b\u0003\u001f\u0005#x.\\5d%\u00164WM]3oG\u0016\fA\"\u001e9eCR,\u0017\t^8nS\u000e$RaWA\u001a\u0003oAa!!\u000e\u000f\u0001\u0004I\u0018!C8mI\n+h\u000e\u001a7f\u0011\u0019\tID\u0004a\u0001s\u0006Ia.Z<Ck:$G.Z\u0001\tE>$\u0017\u0010V3yi\u0006a!m\u001c3z)\u0016DHo\u0018\u0013fcR\u00191,!\u0011\t\u0011\u0005\r\u0003#!AA\u0002\t\f1\u0001\u001f\u00132\u0003\u0011\u0011w\u000eZ=\u0015\u0007m\u000bI\u0005C\u0004\u0002LE\u0001\r!!\u0014\u0002\t\u0015dW-\u001c\t\u0005\u0003\u001f\n)&\u0004\u0002\u0002R)\u0019\u00111\u000b)\u0002\u0007alG.\u0003\u0003\u0002X\u0005E#\u0001B#mK6\fq!\u001b8dYV$W\rF\u0002f\u0003;Ba!a\u0018\u0013\u0001\u0004!\u0016!B:vSR,\u0017\u0001C:oSB\u0004X\r^:\u0016\u0005\u0005\u0015\u0004CBA4\u0003c\n9H\u0004\u0003\u0002j\u00055db\u00015\u0002l%\t\u0011+C\u0002\u0002pA\u000bq\u0001]1dW\u0006<W-\u0003\u0003\u0002t\u0005U$A\u0002,fGR|\'OC\u0002\u0002pA\u0003\"A_\f\u0003\u000fMs\u0017\u000e\u001d9fiN1qCTA?\u0003\u0007\u00032aTA@\u0013\r\t\t\t\u0015\u0002\b!J|G-^2u!\u0011\t9\'!\"\n\t\u0005\u001d\u0015Q\u000f\u0002\r\'\u0016\u0014\u0018.\u00197ju\u0006\u0014G.Z\u0015\u0004/5B\"!D%oG2,H-\u001a3Tk&$Xm\u0005\u0005.\u001d\u0006]\u0014QPAB+\u0005!\u0016AB:vSR,\u0007\u0005\u0006\u0003\u0002\u0016\u0006]\u0005C\u0001>.\u0011\u0019\ty\u0006\ra\u0001)\u0006!1m\u001c9z)\u0011\t)*!(\t\u0011\u0005}\u0013\u0007%AA\u0002Q\u000babY8qs\u0012\"WMZ1vYR$\u0013\'\u0006\u0002\u0002$*\u001aA+!*,\u0005\u0005\u001d\u0006\u0003BAU\u0003gk!!a+\u000b\t\u00055\u0016qV\u0001\nk:\u001c\u0007.Z2lK\u0012T1!!-Q\u0003)\tgN\\8uCRLwN\\\u0005\u0005\u0003k\u000bYKA\tv]\u000eDWmY6fIZ\u000b\'/[1oG\u0016\fQ\u0002\u001d:pIV\u001cG\u000f\u0015:fM&DXCAA^!\u0011\ti,a1\u000e\u0005\u0005}&\u0002BAa\u0003O\tA\u0001\\1oO&\u0019a.a0\u0002\u0019A\u0014x\u000eZ;di\u0006\u0013\u0018\u000e^=\u0016\u0005\u0005%\u0007cA(\u0002L&\u0019\u0011Q\u001a)\u0003\u0007%sG/\u0001\bqe>$Wo\u0019;FY\u0016lWM\u001c;\u0015\t\u0005M\u0017\u0011\u001c\t\u0004\u001f\u0006U\u0017bAAl!\n\u0019\u0011I\\=\t\u0013\u0005\rS\'!AA\u0002\u0005%\u0017a\u00049s_\u0012,8\r^%uKJ\fGo\u001c:\u0016\u0005\u0005}\u0007CBAq\u0003O\f\u0019.\u0004\u0002\u0002d*\u0019\u0011Q\u001d)\u0002\u0015\r|G\u000e\\3di&|g.\u0003\u0003\u0002j\u0006\r(\u0001C%uKJ\fGo\u001c:\u0002\u0011\r\fg.R9vC2$B!a<\u0002vB\u0019q*!=\n\u0007\u0005M\bKA\u0004C_>dW-\u00198\t\u0013\u0005\rs\'!AA\u0002\u0005M\u0017A\u00059s_\u0012,8\r^#mK6,g\u000e\u001e(b[\u0016$B!a/\u0002|\"I\u00111\t\u001d\u0002\u0002\u0003\u0007\u0011\u0011Z\u0001\tQ\u0006\u001c\bnQ8eKR\u0011\u0011\u0011Z\u0001\ti>\u001cFO]5oOR\u0011\u00111X\u0001\u0007KF,\u0018\r\\:\u0015\t\u0005=(\u0011\u0002\u0005\n\u0003\u0007Z\u0014\u0011!a\u0001\u0003\'\u0014a!T1sWV\u00048\u0003\u0003\rO\u0003o\ni(a!\u0002\tQ,\u0007\u0010^\u000b\u0002K\u0006)A/\u001a=uAQ!!q\u0003B\r!\tQ\b\u0004\u0003\u0004\u0003\u0010m\u0001\r!\u001a\u000b\u0005\u0005/\u0011i\u0002\u0003\u0005\u0003\u0010q\u0001\n\u00111\u0001f+\t\u0011\tCK\u0002f\u0003K#B!a5\u0003&!I\u00111\t\u0011\u0002\u0002\u0003\u0007\u0011\u0011\u001a\u000b\u0005\u0003_\u0014I\u0003C\u0005\u0002D\t\n\t\u00111\u0001\u0002TR!\u00111\u0018B\u0017\u0011%\t\u0019eIA\u0001\u0002\u0004\tI\r\u0006\u0003\u0002p\nE\u0002\"CA\"M\u0005\u0005\t\u0019AAj\u00031qWm\u001d;fIN+\u0018\u000e^3t+\t\u00119\u0004E\u0003\u0003:\t}B+\u0004\u0002\u0003<)!!QHAr\u0003%IW.\\;uC\ndW-\u0003\u0003\u0003B\tm\"AC%oI\u0016DX\rZ*fc\u0006y!/\u001e8OKN$X\rZ*vSR,7\u000f\u0006\u0003\u0003H\t5\u0003cA+\u0003J%\u0019!1J%\u0003\rM#\u0018\r^;t\u0011\u001d\u0011y%\u0006a\u0001\u0005#\nA!\u0019:hgB\u0019QKa\u0015\n\u0007\tU\u0013J\u0001\u0003Be\u001e\u001c\u0018aC4fiNs\u0017\u000e\u001d9fiN$B!!\u001a\u0003\\!1!q\u0002\fA\u0002\u0015\fa!T1sWV\u0004\bC\u0001>)\'\u0015A#1\rB8!\u001d\u0011)Ga\u001bf\u0005/i!Aa\u001a\u000b\u0007\t%\u0004+A\u0004sk:$\u0018.\\3\n\t\t5$q\r\u0002\u0012\u0003\n\u001cHO]1di\u001a+hn\u0019;j_:\f\u0004\u0003\u0002B9\u0005oj!Aa\u001d\u000b\t\tU\u0014qE\u0001\u0003S>LA!a\"\u0003tQ\u0011!q\f\u000b\u0005\u0005/\u0011i\b\u0003\u0004\u0003\u0010-\u0002\r!Z\u0001\bk:\f\u0007\u000f\u001d7z)\r\u0011\'1\u0011\u0005\n\u0005\u000bc\u0013\u0011!a\u0001\u0005/\t1\u0001\u001f\u00131\u00035Ien\u00197vI\u0016$7+^5uKB\u0011!0P\n\u0006{\t5%q\u000e\t\b\u0005K\u0012Y\u0007VAK)\t\u0011I\t\u0006\u0003\u0002\u0016\nM\u0005BBA0\u0001\u0002\u0007A\u000b\u0006\u0003\u0003\u0018\ne\u0005cA(d)\"I!QQ!\u0002\u0002\u0003\u0007\u0011QS\u0001\u0004\t>\u001c\u0007CA+D\'\u0011\u0019eJa\u001c\u0015\u0005\tu\u0015A\u0003;sS6l\u0015M]6vaR\u0019QMa*\t\r\t=Q\t1\u0001f\u0003-\u0019HO]5q\u001b\u0006\u0014x-\u001b8\u0015\u0007\u0015\u0014i\u000b\u0003\u0004\u0003\u0010\u0019\u0003\r!Z\u0001\roJLG/\u001a*fa2\f7-\u001a\u000b\u0003\u0005g\u0003B!!0\u00036&!!qWA`\u0005\u0019y%M[3di\u0002"
    )
BootstrapMethods:
  0: #235 REF_invokeStatic java/lang/invoke/LambdaMetafactory.altMetafactory:(Ljava/lang/invoke/MethodHandles$Lookup;Ljava/lang/String;Ljava/lang/invoke/MethodType;[Ljava/lang/Object;)Ljava/lang/invoke/CallSite;
    Method arguments:
      #220 (Ljava/lang/Object;)Ljava/lang/Object;
      #225 REF_invokeStatic org/scalatest/Doc.$anonfun$nestedSuites$1$adapted:(Lorg/scalatest/Doc$Snippet;)Ljava/lang/Object;
      #226 (Lorg/scalatest/Doc$Snippet;)Ljava/lang/Object;
      #227 5
      #228 1
      #226 (Lorg/scalatest/Doc$Snippet;)Ljava/lang/Object;
  1: #235 REF_invokeStatic java/lang/invoke/LambdaMetafactory.altMetafactory:(Ljava/lang/invoke/MethodHandles$Lookup;Ljava/lang/String;Ljava/lang/invoke/MethodType;[Ljava/lang/Object;)Ljava/lang/invoke/CallSite;
    Method arguments:
      #220 (Ljava/lang/Object;)Ljava/lang/Object;
      #249 REF_invokeStatic org/scalatest/Doc.$anonfun$nestedSuites$2:(Lorg/scalatest/Doc$Snippet;)Lorg/scalatest/Suite;
      #250 (Lorg/scalatest/Doc$Snippet;)Lorg/scalatest/Suite;
      #227 5
      #228 1
      #250 (Lorg/scalatest/Doc$Snippet;)Lorg/scalatest/Suite;
  2: #235 REF_invokeStatic java/lang/invoke/LambdaMetafactory.altMetafactory:(Ljava/lang/invoke/MethodHandles$Lookup;Ljava/lang/String;Ljava/lang/invoke/MethodType;[Ljava/lang/Object;)Ljava/lang/invoke/CallSite;
    Method arguments:
      #220 (Ljava/lang/Object;)Ljava/lang/Object;
      #277 REF_invokeStatic org/scalatest/Doc.$anonfun$runNestedSuites$1$adapted:(Lorg/scalatest/Doc;Lorg/scalatest/Args;Lscala/collection/mutable/ListBuffer;Lorg/scalatest/Doc$Snippet;)Ljava/lang/Object;
      #226 (Lorg/scalatest/Doc$Snippet;)Ljava/lang/Object;
      #227 5
      #228 1
      #226 (Lorg/scalatest/Doc$Snippet;)Ljava/lang/Object;
  3: #235 REF_invokeStatic java/lang/invoke/LambdaMetafactory.altMetafactory:(Ljava/lang/invoke/MethodHandles$Lookup;Ljava/lang/String;Ljava/lang/invoke/MethodType;[Ljava/lang/Object;)Ljava/lang/invoke/CallSite;
    Method arguments:
      #220 (Ljava/lang/Object;)Ljava/lang/Object;
      #365 REF_invokeStatic org/scalatest/Doc.$anonfun$getSnippets$1:(Ljava/lang/String;)Lscala/Tuple2;
      #366 (Ljava/lang/String;)Lscala/Tuple2;
      #227 5
      #228 1
      #366 (Ljava/lang/String;)Lscala/Tuple2;
  4: #235 REF_invokeStatic java/lang/invoke/LambdaMetafactory.altMetafactory:(Ljava/lang/invoke/MethodHandles$Lookup;Ljava/lang/String;Ljava/lang/invoke/MethodType;[Ljava/lang/Object;)Ljava/lang/invoke/CallSite;
    Method arguments:
      #389 (Ljava/lang/Object;Ljava/lang/Object;)Ljava/lang/Object;
      #394 REF_invokeStatic org/scalatest/Doc.$anonfun$getSnippets$2:(Lorg/scalatest/Doc;Lscala/collection/immutable/Vector;Lscala/Tuple2;)Lscala/collection/immutable/Vector;
      #396 (Lscala/collection/immutable/Vector;Lscala/Tuple2;)Lscala/collection/immutable/Vector;
      #227 5
      #228 1
      #396 (Lscala/collection/immutable/Vector;Lscala/Tuple2;)Lscala/collection/immutable/Vector;
  5: #568 REF_invokeStatic scala/runtime/LambdaDeserialize.bootstrap:(Ljava/lang/invoke/MethodHandles$Lookup;Ljava/lang/String;Ljava/lang/invoke/MethodType;[Ljava/lang/invoke/MethodHandle;)Ljava/lang/invoke/CallSite;
    Method arguments:
      #365 REF_invokeStatic org/scalatest/Doc.$anonfun$getSnippets$1:(Ljava/lang/String;)Lscala/Tuple2;
      #394 REF_invokeStatic org/scalatest/Doc.$anonfun$getSnippets$2:(Lorg/scalatest/Doc;Lscala/collection/immutable/Vector;Lscala/Tuple2;)Lscala/collection/immutable/Vector;
      #225 REF_invokeStatic org/scalatest/Doc.$anonfun$nestedSuites$1$adapted:(Lorg/scalatest/Doc$Snippet;)Ljava/lang/Object;
      #249 REF_invokeStatic org/scalatest/Doc.$anonfun$nestedSuites$2:(Lorg/scalatest/Doc$Snippet;)Lorg/scalatest/Suite;
      #277 REF_invokeStatic org/scalatest/Doc.$anonfun$runNestedSuites$1$adapted:(Lorg/scalatest/Doc;Lorg/scalatest/Args;Lscala/collection/mutable/ListBuffer;Lorg/scalatest/Doc$Snippet;)Ljava/lang/Object;
  ScalaInlineInfo: length = 0x90 (unknown attribute)
   01 00 00 1C 01 69 01 6A 01 01 86 01 87 01 01 9B
   01 9C 01 00 DD 00 DE 01 00 F5 00 F6 01 01 A3 01
   A4 01 01 11 01 12 01 02 15 02 16 01 00 18 00 2D
   00 00 1E 00 2C 00 00 57 00 58 00 00 53 00 54 01
   00 D1 00 D2 00 01 36 01 37 01 00 6C 00 6D 00 00
   69 00 6A 01 00 D7 00 D8 00 00 D5 00 D6 01 00 2A
   00 2B 00 00 32 00 33 00 00 4D 00 4E 00 00 50 00
   51 00 00 C7 00 C8 00 00 C5 00 C6 01 00 2E 00 2F
   00 01 07 01 08 00 01 04 01 05 01 00 35 00 36 01

  ScalaSig: length = 0x3 (unknown attribute)
   05 02 00
