Classfile /Users/mw/Projects/slang-braindump/.jar/jar11/assemble/slang-braindump/assemble/content/org/scalatest/EitherValues.class
  Last modified May 29, 2022; size 5140 bytes
  SHA-256 checksum b50d463808d1a9f1b211a07b0efb770760fd4cb44ba3e516406a7e3b89812fe5
  Compiled from "EitherValues.scala"
public interface org.scalatest.EitherValues extends java.io.Serializable
  minor version: 0
  major version: 52
  flags: (0x0601) ACC_PUBLIC, ACC_INTERFACE, ACC_ABSTRACT
  this_class: #2                          // org/scalatest/EitherValues
  super_class: #4                         // java/lang/Object
  interfaces: 1, fields: 0, methods: 7, attributes: 5
Constant pool:
   #1 = Utf8               org/scalatest/EitherValues
   #2 = Class              #1             // org/scalatest/EitherValues
   #3 = Utf8               java/lang/Object
   #4 = Class              #3             // java/lang/Object
   #5 = Utf8               java/io/Serializable
   #6 = Class              #5             // java/io/Serializable
   #7 = Utf8               EitherValues.scala
   #8 = Utf8               Lscala/reflect/ScalaSignature;
   #9 = Utf8               bytes
  #10 = Utf8               \u0006\u0005\u0005mda\u0002\r\u001a!\u0003\r\tA\b\u0005\u0006c\u0001!\tA\r\u0005\u0006m\u0001!\u0019a\u000e\u0005\u0006]\u0002!\u0019a\u001c\u0005\b\u0003G\u0001A1AA\u0013\r\u0011a\u0004\u0001A\u001f\t\u0011}*!\u0011!Q\u0001\n\u0001C\u0001bV\u0003\u0003\u0002\u0003\u0006I\u0001\u0017\u0005\u0006A\u0016!\t!\u0019\u0005\u0006K\u0016!\tA\u001a\u0004\u0005g\u0002\u0001A\u000f\u0003\u0005w\u0015\t\u0005\t\u0015!\u0003x\u0011!9&B!A!\u0002\u0013A\u0006\"\u00021\u000b\t\u0003q\bBB3\u000b\t\u0003\t)A\u0002\u0004\u0002.\u0001\u0001\u0011q\u0006\u0005\u000b\u0003gy!\u0011!Q\u0001\n\u0005U\u0002\u0002C,\u0010\u0005\u0003\u0005\u000b\u0011\u0002-\t\r\u0001|A\u0011AA\"\u0011\u0019)w\u0002\"\u0001\u0002L\u001d9\u00111L\r\t\u0002\u0005ucA\u0002\r\u001a\u0011\u0003\t\t\u0007\u0003\u0004a+\u0011\u0005\u0011Q\r\u0005\n\u0003O*\u0012\u0011!C\u0005\u0003S\u0012A\"R5uQ\u0016\u0014h+\u00197vKNT!AG\u000e\u0002\u0013M\u001c\u0017\r\\1uKN$(\"\u0001\u000f\u0002\u0007=\u0014xm\u0001\u0001\u0014\u0007\u0001yR\u0005\u0005\u0002!G5\t\u0011EC\u0001#\u0003\u0015\u00198-\u00197b\u0013\t!\u0013E\u0001\u0004B]f\u0014VM\u001a\t\u0003M9r!a\n\u0017\u000f\u0005!ZS\"A\u0015\u000b\u0005)j\u0012A\u0002\u001fs_>$h(C\u0001#\u0013\ti\u0013%A\u0004qC\u000e\\\u0017mZ3\n\u0005=\u0002$\u0001D*fe&\fG.\u001b>bE2,\'BA\u0017\"\u0003\u0019!\u0013N\\5uIQ\t1\u0007\u0005\u0002!i%\u0011Q\'\t\u0002\u0005+:LG/A\u0010d_:4XM\u001d;MK\u001a$\bK]8kK\u000e$\u0018n\u001c8U_Z\u000bG.^1cY\u0016,2\u0001\u000f5k)\tID\u000e\u0006\u0002;WB!1(B4j\u001b\u0005\u0001!\u0001\u0004\'fMR4\u0016\r\\;bE2,Wc\u0001 L+N\u0019QaH\u0013\u0002\u00111,g\r\u001e)s_*\u0004B!\u0011#J):\u0011aEQ\u0005\u0003\u0007B\na!R5uQ\u0016\u0014\u0018BA#G\u00059aUM\u001a;Qe>TWm\u0019;j_:T!aQ$\u000b\u0005!\u000b\u0013\u0001B;uS2\u0004\"AS&\r\u0001\u0011)A*\u0002b\u0001\u001b\n\tA*\u0005\u0002O#B\u0011\u0001eT\u0005\u0003!\u0006\u0012qAT8uQ&tw\r\u0005\u0002!%&\u00111+\t\u0002\u0004\u0003:L\bC\u0001&V\t\u00151VA1\u0001N\u0005\u0005\u0011\u0016a\u00019pgB\u0011\u0011LX\u0007\u00025*\u00111\fX\u0001\u0007g>,(oY3\u000b\u0005u[\u0012!C:dC2\f7\r^5d\u0013\ty&L\u0001\u0005Q_NLG/[8o\u0003\u0019a\u0014N\\5u}Q\u0019!m\u00193\u0011\tm*\u0011\n\u0016\u0005\u0006\u007f!\u0001\r\u0001\u0011\u0005\u0006/\"\u0001\r\u0001W\u0001\u0006m\u0006dW/Z\u000b\u0002\u0013B\u0011!\n\u001b\u0003\u0006\u0019\n\u0011\r!\u0014\t\u0003\u0015*$QA\u0016\u0002C\u00025CQa\u0016\u0002A\u0004aCQa\u0010\u0002A\u00025\u0004B!\u0011#hS\u0006\u00013m\u001c8wKJ$(+[4iiB\u0013xN[3di&|g\u000eV8WC2,\u0018M\u00197f+\u0015\u0001\u0018\u0011BA\u0007)\r\t\u0018\u0011\u0003\u000b\u0004e\u0006=\u0001CB\u001e\u000b\u0003\u000f\tYAA\u0007SS\u001eDGOV1mk\u0006\u0014G.Z\u000b\u0004knl8c\u0001\u0006 K\u0005I!/[4iiB\u0013xN\u001b\t\u0005\u0003bTH0\u0003\u0002z\r\ny!+[4iiB\u0013xN[3di&|g\u000e\u0005\u0002Kw\u0012)AJ\u0003b\u0001\u001bB\u0011!* \u0003\u0006-*\u0011\r!\u0014\u000b\u0006\u007f\u0006\u0005\u00111\u0001\t\u0005w)QH\u0010C\u0003w\u001b\u0001\u0007q\u000fC\u0003X\u001b\u0001\u0007\u0001,F\u0001}!\rQ\u0015\u0011\u0002\u0003\u0006\u0019\u000e\u0011\r!\u0014\t\u0004\u0015\u00065A!\u0002,\u0004\u0005\u0004i\u0005\"B,\u0004\u0001\bA\u0006B\u0002<\u0004\u0001\u0004\t\u0019\u0002\u0005\u0004Bq\u0006\u001d\u00111\u0002\u0015\b\u0007\u0005]\u0011QDA\u0010!\r\u0001\u0013\u0011D\u0005\u0004\u00037\t#A\u00033faJ,7-\u0019;fI\u00069Q.Z:tC\u001e,\u0017EAA\u0011\u0003\u00055A\u000b[3!]ILw\r\u001b;/m\u0006dW/\u001a\u0011ts:$\u0018\r\u001f\u0011p]\u0002*\u0015\u000e\u001e5fe\u0002B\u0017m\u001d\u0011cK\u0016t\u0007\u0005Z3qe\u0016\u001c\u0017\r^3eA\u0005tG\rI<jY2\u0004#-\u001a\u0011sK6|g/\u001a3!S:\u0004\u0013\r\t4viV\u0014X\r\t<feNLwN\u001c\u0011pM\u0002\u001a6-\u00197b)\u0016\u001cHO\f\u0011QY\u0016\f7/\u001a\u0011vg\u0016\u0004cF^1mk\u0016\u0004\u0013N\\:uK\u0006$g&A\fd_:4XM\u001d;FSRDWM\u001d+p-\u0006dW/\u00192mKV1\u0011qEA(\u0003\'\"B!!\u000b\u0002XQ!\u00111FA+!\u0019Yt\"!\u0014\u0002R\tAa+\u00197vC\ndW-\u0006\u0004\u00022\u0005u\u0012\u0011I\n\u0004\u001f})\u0013AB3ji\",\'\u000fE\u0004\'\u0003o\tY$a\u0010\n\u0007\u0005e\u0002G\u0001\u0004FSRDWM\u001d\t\u0004\u0015\u0006uB!\u0002\'\u0010\u0005\u0004i\u0005c\u0001&\u0002B\u0011)ak\u0004b\u0001\u001bR1\u0011QIA$\u0003\u0013\u0002baO\b\u0002<\u0005}\u0002bBA\u001a%\u0001\u0007\u0011Q\u0007\u0005\u0006/J\u0001\r\u0001W\u000b\u0003\u0003\u007f\u00012ASA(\t\u0015aEA1\u0001N!\rQ\u00151\u000b\u0003\u0006-\u0012\u0011\r!\u0014\u0005\u0006/\u0012\u0001\u001d\u0001\u0017\u0005\b\u0003g!\u0001\u0019AA-!\u001d1\u0013qGA\'\u0003#\nA\"R5uQ\u0016\u0014h+\u00197vKN\u00042!a\u0018\u0016\u001b\u0005I2\u0003B\u000b \u0003G\u00022!a\u0018\u0001)\t\ti&\u0001\u0007xe&$XMU3qY\u0006\u001cW\r\u0006\u0002\u0002lA!\u0011QNA<\u001b\t\tyG\u0003\u0003\u0002r\u0005M\u0014\u0001\u00027b]\u001eT!!!\u001e\u0002\t)\fg/Y\u0005\u0005\u0003s\nyG\u0001\u0004PE*,7\r\u001e
  #11 = Utf8               org/scalatest/EitherValues$LeftValuable
  #12 = Class              #11            // org/scalatest/EitherValues$LeftValuable
  #13 = Utf8               LeftValuable
  #14 = Utf8               org/scalatest/EitherValues$RightValuable
  #15 = Class              #14            // org/scalatest/EitherValues$RightValuable
  #16 = Utf8               RightValuable
  #17 = Utf8               org/scalatest/EitherValues$Valuable
  #18 = Class              #17            // org/scalatest/EitherValues$Valuable
  #19 = Utf8               Valuable
  #20 = Utf8               scala/util/Either$LeftProjection
  #21 = Class              #20            // scala/util/Either$LeftProjection
  #22 = Utf8               scala/util/Either
  #23 = Class              #22            // scala/util/Either
  #24 = Utf8               LeftProjection
  #25 = Utf8               scala/util/Either$RightProjection
  #26 = Class              #25            // scala/util/Either$RightProjection
  #27 = Utf8               RightProjection
  #28 = Utf8               convertLeftProjectionToValuable$
  #29 = Utf8               (Lorg/scalatest/EitherValues;Lscala/util/Either$LeftProjection;Lorg/scalactic/source/Position;)Lorg/scalatest/EitherValues$LeftValuable;
  #30 = Utf8               $this
  #31 = Utf8               leftProj
  #32 = Utf8               pos
  #33 = Utf8               convertLeftProjectionToValuable
  #34 = Utf8               (Lscala/util/Either$LeftProjection;Lorg/scalactic/source/Position;)Lorg/scalatest/EitherValues$LeftValuable;
  #35 = NameAndType        #33:#34        // convertLeftProjectionToValuable:(Lscala/util/Either$LeftProjection;Lorg/scalactic/source/Position;)Lorg/scalatest/EitherValues$LeftValuable;
  #36 = InterfaceMethodref #2.#35         // org/scalatest/EitherValues.convertLeftProjectionToValuable:(Lscala/util/Either$LeftProjection;Lorg/scalactic/source/Position;)Lorg/scalatest/EitherValues$LeftValuable;
  #37 = Utf8               Lorg/scalatest/EitherValues;
  #38 = Utf8               Lscala/util/Either$LeftProjection;
  #39 = Utf8               Lorg/scalactic/source/Position;
  #40 = Utf8               <L:Ljava/lang/Object;R:Ljava/lang/Object;>(Lscala/util/Either$LeftProjection<TL;TR;>;Lorg/scalactic/source/Position;)Lorg/scalatest/EitherValues$LeftValuable<TL;TR;>;
  #41 = Utf8               <init>
  #42 = Utf8               (Lorg/scalatest/EitherValues;Lscala/util/Either$LeftProjection;Lorg/scalactic/source/Position;)V
  #43 = NameAndType        #41:#42        // "<init>":(Lorg/scalatest/EitherValues;Lscala/util/Either$LeftProjection;Lorg/scalactic/source/Position;)V
  #44 = Methodref          #12.#43        // org/scalatest/EitherValues$LeftValuable."<init>":(Lorg/scalatest/EitherValues;Lscala/util/Either$LeftProjection;Lorg/scalactic/source/Position;)V
  #45 = Utf8               this
  #46 = Utf8               convertRightProjectionToValuable$
  #47 = Utf8               (Lorg/scalatest/EitherValues;Lscala/util/Either$RightProjection;Lorg/scalactic/source/Position;)Lorg/scalatest/EitherValues$RightValuable;
  #48 = Utf8               rightProj
  #49 = Utf8               convertRightProjectionToValuable
  #50 = Utf8               (Lscala/util/Either$RightProjection;Lorg/scalactic/source/Position;)Lorg/scalatest/EitherValues$RightValuable;
  #51 = NameAndType        #49:#50        // convertRightProjectionToValuable:(Lscala/util/Either$RightProjection;Lorg/scalactic/source/Position;)Lorg/scalatest/EitherValues$RightValuable;
  #52 = InterfaceMethodref #2.#51         // org/scalatest/EitherValues.convertRightProjectionToValuable:(Lscala/util/Either$RightProjection;Lorg/scalactic/source/Position;)Lorg/scalatest/EitherValues$RightValuable;
  #53 = Utf8               Lscala/util/Either$RightProjection;
  #54 = Utf8               <L:Ljava/lang/Object;R:Ljava/lang/Object;>(Lscala/util/Either$RightProjection<TL;TR;>;Lorg/scalactic/source/Position;)Lorg/scalatest/EitherValues$RightValuable<TL;TR;>;
  #55 = Utf8               (Lorg/scalatest/EitherValues;Lscala/util/Either$RightProjection;Lorg/scalactic/source/Position;)V
  #56 = NameAndType        #41:#55        // "<init>":(Lorg/scalatest/EitherValues;Lscala/util/Either$RightProjection;Lorg/scalactic/source/Position;)V
  #57 = Methodref          #15.#56        // org/scalatest/EitherValues$RightValuable."<init>":(Lorg/scalatest/EitherValues;Lscala/util/Either$RightProjection;Lorg/scalactic/source/Position;)V
  #58 = Utf8               convertEitherToValuable$
  #59 = Utf8               (Lorg/scalatest/EitherValues;Lscala/util/Either;Lorg/scalactic/source/Position;)Lorg/scalatest/EitherValues$Valuable;
  #60 = Utf8               either
  #61 = Utf8               convertEitherToValuable
  #62 = Utf8               (Lscala/util/Either;Lorg/scalactic/source/Position;)Lorg/scalatest/EitherValues$Valuable;
  #63 = NameAndType        #61:#62        // convertEitherToValuable:(Lscala/util/Either;Lorg/scalactic/source/Position;)Lorg/scalatest/EitherValues$Valuable;
  #64 = InterfaceMethodref #2.#63         // org/scalatest/EitherValues.convertEitherToValuable:(Lscala/util/Either;Lorg/scalactic/source/Position;)Lorg/scalatest/EitherValues$Valuable;
  #65 = Utf8               Lscala/util/Either;
  #66 = Utf8               <L:Ljava/lang/Object;R:Ljava/lang/Object;>(Lscala/util/Either<TL;TR;>;Lorg/scalactic/source/Position;)Lorg/scalatest/EitherValues$Valuable<TL;TR;>;
  #67 = Utf8               (Lorg/scalatest/EitherValues;Lscala/util/Either;Lorg/scalactic/source/Position;)V
  #68 = NameAndType        #41:#67        // "<init>":(Lorg/scalatest/EitherValues;Lscala/util/Either;Lorg/scalactic/source/Position;)V
  #69 = Methodref          #18.#68        // org/scalatest/EitherValues$Valuable."<init>":(Lorg/scalatest/EitherValues;Lscala/util/Either;Lorg/scalactic/source/Position;)V
  #70 = Utf8               $init$
  #71 = Utf8               (Lorg/scalatest/EitherValues;)V
  #72 = Utf8               Code
  #73 = Utf8               LineNumberTable
  #74 = Utf8               LocalVariableTable
  #75 = Utf8               MethodParameters
  #76 = Utf8               Signature
  #77 = Utf8               Deprecated
  #78 = Utf8               InnerClasses
  #79 = Utf8               SourceFile
  #80 = Utf8               RuntimeVisibleAnnotations
  #81 = Utf8               ScalaInlineInfo
  #82 = Utf8               ScalaSig
{
  public static org.scalatest.EitherValues$LeftValuable convertLeftProjectionToValuable$(org.scalatest.EitherValues, scala.util.Either$LeftProjection, org.scalactic.source.Position);
    descriptor: (Lorg/scalatest/EitherValues;Lscala/util/Either$LeftProjection;Lorg/scalactic/source/Position;)Lorg/scalatest/EitherValues$LeftValuable;
    flags: (0x1009) ACC_PUBLIC, ACC_STATIC, ACC_SYNTHETIC
    Code:
      stack=3, locals=3, args_size=3
         0: aload_0
         1: aload_1
         2: aload_2
         3: invokespecial #36                 // InterfaceMethod convertLeftProjectionToValuable:(Lscala/util/Either$LeftProjection;Lorg/scalactic/source/Position;)Lorg/scalatest/EitherValues$LeftValuable;
         6: areturn
      LineNumberTable:
        line 93: 0
      LocalVariableTable:
        Start  Length  Slot  Name   Signature
            0       7     0 $this   Lorg/scalatest/EitherValues;
            0       7     1 leftProj   Lscala/util/Either$LeftProjection;
            0       7     2   pos   Lorg/scalactic/source/Position;
    MethodParameters:
      Name                           Flags
      $this                          final synthetic
      leftProj                       final
      pos                            final

  public default <L extends java.lang.Object, R extends java.lang.Object> org.scalatest.EitherValues$LeftValuable<L, R> convertLeftProjectionToValuable(scala.util.Either$LeftProjection<L, R>, org.scalactic.source.Position);
    descriptor: (Lscala/util/Either$LeftProjection;Lorg/scalactic/source/Position;)Lorg/scalatest/EitherValues$LeftValuable;
    flags: (0x0001) ACC_PUBLIC
    Code:
      stack=5, locals=3, args_size=3
         0: new           #12                 // class org/scalatest/EitherValues$LeftValuable
         3: dup
         4: aload_0
         5: aload_1
         6: aload_2
         7: invokespecial #44                 // Method org/scalatest/EitherValues$LeftValuable."<init>":(Lorg/scalatest/EitherValues;Lscala/util/Either$LeftProjection;Lorg/scalactic/source/Position;)V
        10: areturn
      LineNumberTable:
        line 93: 0
      LocalVariableTable:
        Start  Length  Slot  Name   Signature
            0      11     0  this   Lorg/scalatest/EitherValues;
            0      11     1 leftProj   Lscala/util/Either$LeftProjection;
            0      11     2   pos   Lorg/scalactic/source/Position;
    Signature: #40                          // <L:Ljava/lang/Object;R:Ljava/lang/Object;>(Lscala/util/Either$LeftProjection<TL;TR;>;Lorg/scalactic/source/Position;)Lorg/scalatest/EitherValues$LeftValuable<TL;TR;>;
    MethodParameters:
      Name                           Flags
      leftProj                       final
      pos                            final

  public static org.scalatest.EitherValues$RightValuable convertRightProjectionToValuable$(org.scalatest.EitherValues, scala.util.Either$RightProjection, org.scalactic.source.Position);
    descriptor: (Lorg/scalatest/EitherValues;Lscala/util/Either$RightProjection;Lorg/scalactic/source/Position;)Lorg/scalatest/EitherValues$RightValuable;
    flags: (0x1009) ACC_PUBLIC, ACC_STATIC, ACC_SYNTHETIC
    Code:
      stack=3, locals=3, args_size=3
         0: aload_0
         1: aload_1
         2: aload_2
         3: invokespecial #52                 // InterfaceMethod convertRightProjectionToValuable:(Lscala/util/Either$RightProjection;Lorg/scalactic/source/Position;)Lorg/scalatest/EitherValues$RightValuable;
         6: areturn
      LineNumberTable:
        line 101: 0
      LocalVariableTable:
        Start  Length  Slot  Name   Signature
            0       7     0 $this   Lorg/scalatest/EitherValues;
            0       7     1 rightProj   Lscala/util/Either$RightProjection;
            0       7     2   pos   Lorg/scalactic/source/Position;
    MethodParameters:
      Name                           Flags
      $this                          final synthetic
      rightProj                      final
      pos                            final

  public default <L extends java.lang.Object, R extends java.lang.Object> org.scalatest.EitherValues$RightValuable<L, R> convertRightProjectionToValuable(scala.util.Either$RightProjection<L, R>, org.scalactic.source.Position);
    descriptor: (Lscala/util/Either$RightProjection;Lorg/scalactic/source/Position;)Lorg/scalatest/EitherValues$RightValuable;
    flags: (0x0001) ACC_PUBLIC
    Code:
      stack=5, locals=3, args_size=3
         0: new           #15                 // class org/scalatest/EitherValues$RightValuable
         3: dup
         4: aload_0
         5: aload_1
         6: aload_2
         7: invokespecial #57                 // Method org/scalatest/EitherValues$RightValuable."<init>":(Lorg/scalatest/EitherValues;Lscala/util/Either$RightProjection;Lorg/scalactic/source/Position;)V
        10: areturn
      LineNumberTable:
        line 101: 0
      LocalVariableTable:
        Start  Length  Slot  Name   Signature
            0      11     0  this   Lorg/scalatest/EitherValues;
            0      11     1 rightProj   Lscala/util/Either$RightProjection;
            0      11     2   pos   Lorg/scalactic/source/Position;
    Signature: #54                          // <L:Ljava/lang/Object;R:Ljava/lang/Object;>(Lscala/util/Either$RightProjection<TL;TR;>;Lorg/scalactic/source/Position;)Lorg/scalatest/EitherValues$RightValuable<TL;TR;>;
    Deprecated: true
    MethodParameters:
      Name                           Flags
      rightProj                      final
      pos                            final

  public static org.scalatest.EitherValues$Valuable convertEitherToValuable$(org.scalatest.EitherValues, scala.util.Either, org.scalactic.source.Position);
    descriptor: (Lorg/scalatest/EitherValues;Lscala/util/Either;Lorg/scalactic/source/Position;)Lorg/scalatest/EitherValues$Valuable;
    flags: (0x1009) ACC_PUBLIC, ACC_STATIC, ACC_SYNTHETIC
    Code:
      stack=3, locals=3, args_size=3
         0: aload_0
         1: aload_1
         2: aload_2
         3: invokespecial #64                 // InterfaceMethod convertEitherToValuable:(Lscala/util/Either;Lorg/scalactic/source/Position;)Lorg/scalatest/EitherValues$Valuable;
         6: areturn
      LineNumberTable:
        line 110: 0
      LocalVariableTable:
        Start  Length  Slot  Name   Signature
            0       7     0 $this   Lorg/scalatest/EitherValues;
            0       7     1 either   Lscala/util/Either;
            0       7     2   pos   Lorg/scalactic/source/Position;
    MethodParameters:
      Name                           Flags
      $this                          final synthetic
      either                         final
      pos                            final

  public default <L extends java.lang.Object, R extends java.lang.Object> org.scalatest.EitherValues$Valuable<L, R> convertEitherToValuable(scala.util.Either<L, R>, org.scalactic.source.Position);
    descriptor: (Lscala/util/Either;Lorg/scalactic/source/Position;)Lorg/scalatest/EitherValues$Valuable;
    flags: (0x0001) ACC_PUBLIC
    Code:
      stack=5, locals=3, args_size=3
         0: new           #18                 // class org/scalatest/EitherValues$Valuable
         3: dup
         4: aload_0
         5: aload_1
         6: aload_2
         7: invokespecial #69                 // Method org/scalatest/EitherValues$Valuable."<init>":(Lorg/scalatest/EitherValues;Lscala/util/Either;Lorg/scalactic/source/Position;)V
        10: areturn
      LineNumberTable:
        line 110: 0
      LocalVariableTable:
        Start  Length  Slot  Name   Signature
            0      11     0  this   Lorg/scalatest/EitherValues;
            0      11     1 either   Lscala/util/Either;
            0      11     2   pos   Lorg/scalactic/source/Position;
    Signature: #66                          // <L:Ljava/lang/Object;R:Ljava/lang/Object;>(Lscala/util/Either<TL;TR;>;Lorg/scalactic/source/Position;)Lorg/scalatest/EitherValues$Valuable<TL;TR;>;
    MethodParameters:
      Name                           Flags
      either                         final
      pos                            final

  public static void $init$(org.scalatest.EitherValues);
    descriptor: (Lorg/scalatest/EitherValues;)V
    flags: (0x0009) ACC_PUBLIC, ACC_STATIC
    Code:
      stack=0, locals=1, args_size=1
         0: return
      LineNumberTable:
        line 84: 0
      LocalVariableTable:
        Start  Length  Slot  Name   Signature
            0       1     0 $this   Lorg/scalatest/EitherValues;
    MethodParameters:
      Name                           Flags
      $this                          final synthetic
}
InnerClasses:
  public #13= #12 of #2;                  // LeftValuable=class org/scalatest/EitherValues$LeftValuable of class org/scalatest/EitherValues
  public #16= #15 of #2;                  // RightValuable=class org/scalatest/EitherValues$RightValuable of class org/scalatest/EitherValues
  public #19= #18 of #2;                  // Valuable=class org/scalatest/EitherValues$Valuable of class org/scalatest/EitherValues
  public static final #24= #21 of #23;    // LeftProjection=class scala/util/Either$LeftProjection of class scala/util/Either
  public static final #27= #26 of #23;    // RightProjection=class scala/util/Either$RightProjection of class scala/util/Either
SourceFile: "EitherValues.scala"
RuntimeVisibleAnnotations:
  0: #8(#9=s#10)
    scala.reflect.ScalaSignature(
      bytes="\u0006\u0005\u0005mda\u0002\r\u001a!\u0003\r\tA\b\u0005\u0006c\u0001!\tA\r\u0005\u0006m\u0001!\u0019a\u000e\u0005\u0006]\u0002!\u0019a\u001c\u0005\b\u0003G\u0001A1AA\u0013\r\u0011a\u0004\u0001A\u001f\t\u0011}*!\u0011!Q\u0001\n\u0001C\u0001bV\u0003\u0003\u0002\u0003\u0006I\u0001\u0017\u0005\u0006A\u0016!\t!\u0019\u0005\u0006K\u0016!\tA\u001a\u0004\u0005g\u0002\u0001A\u000f\u0003\u0005w\u0015\t\u0005\t\u0015!\u0003x\u0011!9&B!A!\u0002\u0013A\u0006\"\u00021\u000b\t\u0003q\bBB3\u000b\t\u0003\t)A\u0002\u0004\u0002.\u0001\u0001\u0011q\u0006\u0005\u000b\u0003gy!\u0011!Q\u0001\n\u0005U\u0002\u0002C,\u0010\u0005\u0003\u0005\u000b\u0011\u0002-\t\r\u0001|A\u0011AA\"\u0011\u0019)w\u0002\"\u0001\u0002L\u001d9\u00111L\r\t\u0002\u0005ucA\u0002\r\u001a\u0011\u0003\t\t\u0007\u0003\u0004a+\u0011\u0005\u0011Q\r\u0005\n\u0003O*\u0012\u0011!C\u0005\u0003S\u0012A\"R5uQ\u0016\u0014h+\u00197vKNT!AG\u000e\u0002\u0013M\u001c\u0017\r\\1uKN$(\"\u0001\u000f\u0002\u0007=\u0014xm\u0001\u0001\u0014\u0007\u0001yR\u0005\u0005\u0002!G5\t\u0011EC\u0001#\u0003\u0015\u00198-\u00197b\u0013\t!\u0013E\u0001\u0004B]f\u0014VM\u001a\t\u0003M9r!a\n\u0017\u000f\u0005!ZS\"A\u0015\u000b\u0005)j\u0012A\u0002\u001fs_>$h(C\u0001#\u0013\ti\u0013%A\u0004qC\u000e\\\u0017mZ3\n\u0005=\u0002$\u0001D*fe&\fG.\u001b>bE2,\'BA\u0017\"\u0003\u0019!\u0013N\\5uIQ\t1\u0007\u0005\u0002!i%\u0011Q\'\t\u0002\u0005+:LG/A\u0010d_:4XM\u001d;MK\u001a$\bK]8kK\u000e$\u0018n\u001c8U_Z\u000bG.^1cY\u0016,2\u0001\u000f5k)\tID\u000e\u0006\u0002;WB!1(B4j\u001b\u0005\u0001!\u0001\u0004\'fMR4\u0016\r\\;bE2,Wc\u0001 L+N\u0019QaH\u0013\u0002\u00111,g\r\u001e)s_*\u0004B!\u0011#J):\u0011aEQ\u0005\u0003\u0007B\na!R5uQ\u0016\u0014\u0018BA#G\u00059aUM\u001a;Qe>TWm\u0019;j_:T!aQ$\u000b\u0005!\u000b\u0013\u0001B;uS2\u0004\"AS&\r\u0001\u0011)A*\u0002b\u0001\u001b\n\tA*\u0005\u0002O#B\u0011\u0001eT\u0005\u0003!\u0006\u0012qAT8uQ&tw\r\u0005\u0002!%&\u00111+\t\u0002\u0004\u0003:L\bC\u0001&V\t\u00151VA1\u0001N\u0005\u0005\u0011\u0016a\u00019pgB\u0011\u0011LX\u0007\u00025*\u00111\fX\u0001\u0007g>,(oY3\u000b\u0005u[\u0012!C:dC2\f7\r^5d\u0013\ty&L\u0001\u0005Q_NLG/[8o\u0003\u0019a\u0014N\\5u}Q\u0019!m\u00193\u0011\tm*\u0011\n\u0016\u0005\u0006\u007f!\u0001\r\u0001\u0011\u0005\u0006/\"\u0001\r\u0001W\u0001\u0006m\u0006dW/Z\u000b\u0002\u0013B\u0011!\n\u001b\u0003\u0006\u0019\n\u0011\r!\u0014\t\u0003\u0015*$QA\u0016\u0002C\u00025CQa\u0016\u0002A\u0004aCQa\u0010\u0002A\u00025\u0004B!\u0011#hS\u0006\u00013m\u001c8wKJ$(+[4iiB\u0013xN[3di&|g\u000eV8WC2,\u0018M\u00197f+\u0015\u0001\u0018\u0011BA\u0007)\r\t\u0018\u0011\u0003\u000b\u0004e\u0006=\u0001CB\u001e\u000b\u0003\u000f\tYAA\u0007SS\u001eDGOV1mk\u0006\u0014G.Z\u000b\u0004knl8c\u0001\u0006 K\u0005I!/[4iiB\u0013xN\u001b\t\u0005\u0003bTH0\u0003\u0002z\r\ny!+[4iiB\u0013xN[3di&|g\u000e\u0005\u0002Kw\u0012)AJ\u0003b\u0001\u001bB\u0011!* \u0003\u0006-*\u0011\r!\u0014\u000b\u0006\u007f\u0006\u0005\u00111\u0001\t\u0005w)QH\u0010C\u0003w\u001b\u0001\u0007q\u000fC\u0003X\u001b\u0001\u0007\u0001,F\u0001}!\rQ\u0015\u0011\u0002\u0003\u0006\u0019\u000e\u0011\r!\u0014\t\u0004\u0015\u00065A!\u0002,\u0004\u0005\u0004i\u0005\"B,\u0004\u0001\bA\u0006B\u0002<\u0004\u0001\u0004\t\u0019\u0002\u0005\u0004Bq\u0006\u001d\u00111\u0002\u0015\b\u0007\u0005]\u0011QDA\u0010!\r\u0001\u0013\u0011D\u0005\u0004\u00037\t#A\u00033faJ,7-\u0019;fI\u00069Q.Z:tC\u001e,\u0017EAA\u0011\u0003\u00055A\u000b[3!]ILw\r\u001b;/m\u0006dW/\u001a\u0011ts:$\u0018\r\u001f\u0011p]\u0002*\u0015\u000e\u001e5fe\u0002B\u0017m\u001d\u0011cK\u0016t\u0007\u0005Z3qe\u0016\u001c\u0017\r^3eA\u0005tG\rI<jY2\u0004#-\u001a\u0011sK6|g/\u001a3!S:\u0004\u0013\r\t4viV\u0014X\r\t<feNLwN\u001c\u0011pM\u0002\u001a6-\u00197b)\u0016\u001cHO\f\u0011QY\u0016\f7/\u001a\u0011vg\u0016\u0004cF^1mk\u0016\u0004\u0013N\\:uK\u0006$g&A\fd_:4XM\u001d;FSRDWM\u001d+p-\u0006dW/\u00192mKV1\u0011qEA(\u0003\'\"B!!\u000b\u0002XQ!\u00111FA+!\u0019Yt\"!\u0014\u0002R\tAa+\u00197vC\ndW-\u0006\u0004\u00022\u0005u\u0012\u0011I\n\u0004\u001f})\u0013AB3ji\",\'\u000fE\u0004\'\u0003o\tY$a\u0010\n\u0007\u0005e\u0002G\u0001\u0004FSRDWM\u001d\t\u0004\u0015\u0006uB!\u0002\'\u0010\u0005\u0004i\u0005c\u0001&\u0002B\u0011)ak\u0004b\u0001\u001bR1\u0011QIA$\u0003\u0013\u0002baO\b\u0002<\u0005}\u0002bBA\u001a%\u0001\u0007\u0011Q\u0007\u0005\u0006/J\u0001\r\u0001W\u000b\u0003\u0003\u007f\u00012ASA(\t\u0015aEA1\u0001N!\rQ\u00151\u000b\u0003\u0006-\u0012\u0011\r!\u0014\u0005\u0006/\u0012\u0001\u001d\u0001\u0017\u0005\b\u0003g!\u0001\u0019AA-!\u001d1\u0013qGA\'\u0003#\nA\"R5uQ\u0016\u0014h+\u00197vKN\u00042!a\u0018\u0016\u001b\u0005I2\u0003B\u000b \u0003G\u00022!a\u0018\u0001)\t\ti&\u0001\u0007xe&$XMU3qY\u0006\u001cW\r\u0006\u0002\u0002lA!\u0011QNA<\u001b\t\tyG\u0003\u0003\u0002r\u0005M\u0014\u0001\u00027b]\u001eT!!!\u001e\u0002\t)\fg/Y\u0005\u0005\u0003s\nyG\u0001\u0004PE*,7\r\u001e"
    )
  ScalaInlineInfo: length = 0x27 (unknown attribute)
   01 00 00 07 00 46 00 47 01 00 3D 00 3E 00 00 3A
   00 3B 01 00 21 00 22 00 00 1C 00 1D 01 00 31 00
   32 00 00 2E 00 2F 01
  ScalaSig: length = 0x3 (unknown attribute)
   05 02 00
