Classfile /Users/mw/Projects/slang-braindump/.jar/jar11/assemble/slang-braindump/assemble/content/org/scalatest/EitherValues$.class
  Last modified May 29, 2022; size 3064 bytes
  SHA-256 checksum 9758f7de4d9f384460db6ded6d04b595a39c66188817e4bf3ebed6bbbcd87825
  Compiled from "EitherValues.scala"
public final class org.scalatest.EitherValues$ implements org.scalatest.EitherValues
  minor version: 0
  major version: 52
  flags: (0x0031) ACC_PUBLIC, ACC_FINAL, ACC_SUPER
  this_class: #2                          // org/scalatest/EitherValues$
  super_class: #4                         // java/lang/Object
  interfaces: 1, fields: 1, methods: 6, attributes: 4
Constant pool:
   #1 = Utf8               org/scalatest/EitherValues$
   #2 = Class              #1             // org/scalatest/EitherValues$
   #3 = Utf8               java/lang/Object
   #4 = Class              #3             // java/lang/Object
   #5 = Utf8               org/scalatest/EitherValues
   #6 = Class              #5             // org/scalatest/EitherValues
   #7 = Utf8               EitherValues.scala
   #8 = Utf8               org/scalatest/EitherValues$LeftValuable
   #9 = Class              #8             // org/scalatest/EitherValues$LeftValuable
  #10 = Utf8               LeftValuable
  #11 = Utf8               org/scalatest/EitherValues$RightValuable
  #12 = Class              #11            // org/scalatest/EitherValues$RightValuable
  #13 = Utf8               RightValuable
  #14 = Utf8               org/scalatest/EitherValues$Valuable
  #15 = Class              #14            // org/scalatest/EitherValues$Valuable
  #16 = Utf8               Valuable
  #17 = Utf8               scala/util/Either$LeftProjection
  #18 = Class              #17            // scala/util/Either$LeftProjection
  #19 = Utf8               scala/util/Either
  #20 = Class              #19            // scala/util/Either
  #21 = Utf8               LeftProjection
  #22 = Utf8               scala/util/Either$RightProjection
  #23 = Class              #22            // scala/util/Either$RightProjection
  #24 = Utf8               RightProjection
  #25 = Utf8               MODULE$
  #26 = Utf8               Lorg/scalatest/EitherValues$;
  #27 = Utf8               <clinit>
  #28 = Utf8               ()V
  #29 = Utf8               <init>
  #30 = NameAndType        #29:#28        // "<init>":()V
  #31 = Methodref          #2.#30         // org/scalatest/EitherValues$."<init>":()V
  #32 = NameAndType        #25:#26        // MODULE$:Lorg/scalatest/EitherValues$;
  #33 = Fieldref           #2.#32         // org/scalatest/EitherValues$.MODULE$:Lorg/scalatest/EitherValues$;
  #34 = Utf8               $init$
  #35 = Utf8               (Lorg/scalatest/EitherValues;)V
  #36 = NameAndType        #34:#35        // $init$:(Lorg/scalatest/EitherValues;)V
  #37 = InterfaceMethodref #6.#36         // org/scalatest/EitherValues.$init$:(Lorg/scalatest/EitherValues;)V
  #38 = Utf8               convertLeftProjectionToValuable
  #39 = Utf8               (Lscala/util/Either$LeftProjection;Lorg/scalactic/source/Position;)Lorg/scalatest/EitherValues$LeftValuable;
  #40 = Utf8               <L:Ljava/lang/Object;R:Ljava/lang/Object;>(Lscala/util/Either$LeftProjection<TL;TR;>;Lorg/scalactic/source/Position;)Lorg/scalatest/EitherValues$LeftValuable<TL;TR;>;
  #41 = Utf8               leftProj
  #42 = Utf8               pos
  #43 = Utf8               convertLeftProjectionToValuable$
  #44 = Utf8               (Lorg/scalatest/EitherValues;Lscala/util/Either$LeftProjection;Lorg/scalactic/source/Position;)Lorg/scalatest/EitherValues$LeftValuable;
  #45 = NameAndType        #43:#44        // convertLeftProjectionToValuable$:(Lorg/scalatest/EitherValues;Lscala/util/Either$LeftProjection;Lorg/scalactic/source/Position;)Lorg/scalatest/EitherValues$LeftValuable;
  #46 = InterfaceMethodref #6.#45         // org/scalatest/EitherValues.convertLeftProjectionToValuable$:(Lorg/scalatest/EitherValues;Lscala/util/Either$LeftProjection;Lorg/scalactic/source/Position;)Lorg/scalatest/EitherValues$LeftValuable;
  #47 = Utf8               this
  #48 = Utf8               Lscala/util/Either$LeftProjection;
  #49 = Utf8               Lorg/scalactic/source/Position;
  #50 = Utf8               convertRightProjectionToValuable
  #51 = Utf8               (Lscala/util/Either$RightProjection;Lorg/scalactic/source/Position;)Lorg/scalatest/EitherValues$RightValuable;
  #52 = Utf8               <L:Ljava/lang/Object;R:Ljava/lang/Object;>(Lscala/util/Either$RightProjection<TL;TR;>;Lorg/scalactic/source/Position;)Lorg/scalatest/EitherValues$RightValuable<TL;TR;>;
  #53 = Utf8               rightProj
  #54 = Utf8               convertRightProjectionToValuable$
  #55 = Utf8               (Lorg/scalatest/EitherValues;Lscala/util/Either$RightProjection;Lorg/scalactic/source/Position;)Lorg/scalatest/EitherValues$RightValuable;
  #56 = NameAndType        #54:#55        // convertRightProjectionToValuable$:(Lorg/scalatest/EitherValues;Lscala/util/Either$RightProjection;Lorg/scalactic/source/Position;)Lorg/scalatest/EitherValues$RightValuable;
  #57 = InterfaceMethodref #6.#56         // org/scalatest/EitherValues.convertRightProjectionToValuable$:(Lorg/scalatest/EitherValues;Lscala/util/Either$RightProjection;Lorg/scalactic/source/Position;)Lorg/scalatest/EitherValues$RightValuable;
  #58 = Utf8               Lscala/util/Either$RightProjection;
  #59 = Utf8               convertEitherToValuable
  #60 = Utf8               (Lscala/util/Either;Lorg/scalactic/source/Position;)Lorg/scalatest/EitherValues$Valuable;
  #61 = Utf8               <L:Ljava/lang/Object;R:Ljava/lang/Object;>(Lscala/util/Either<TL;TR;>;Lorg/scalactic/source/Position;)Lorg/scalatest/EitherValues$Valuable<TL;TR;>;
  #62 = Utf8               either
  #63 = Utf8               convertEitherToValuable$
  #64 = Utf8               (Lorg/scalatest/EitherValues;Lscala/util/Either;Lorg/scalactic/source/Position;)Lorg/scalatest/EitherValues$Valuable;
  #65 = NameAndType        #63:#64        // convertEitherToValuable$:(Lorg/scalatest/EitherValues;Lscala/util/Either;Lorg/scalactic/source/Position;)Lorg/scalatest/EitherValues$Valuable;
  #66 = InterfaceMethodref #6.#65         // org/scalatest/EitherValues.convertEitherToValuable$:(Lorg/scalatest/EitherValues;Lscala/util/Either;Lorg/scalactic/source/Position;)Lorg/scalatest/EitherValues$Valuable;
  #67 = Utf8               Lscala/util/Either;
  #68 = Utf8               writeReplace
  #69 = Utf8               ()Ljava/lang/Object;
  #70 = Utf8               scala/runtime/ModuleSerializationProxy
  #71 = Class              #70            // scala/runtime/ModuleSerializationProxy
  #72 = Utf8               (Ljava/lang/Class;)V
  #73 = NameAndType        #29:#72        // "<init>":(Ljava/lang/Class;)V
  #74 = Methodref          #71.#73        // scala/runtime/ModuleSerializationProxy."<init>":(Ljava/lang/Class;)V
  #75 = Methodref          #4.#30         // java/lang/Object."<init>":()V
  #76 = Utf8               Code
  #77 = Utf8               LineNumberTable
  #78 = Utf8               LocalVariableTable
  #79 = Utf8               Signature
  #80 = Utf8               MethodParameters
  #81 = Utf8               Deprecated
  #82 = Utf8               InnerClasses
  #83 = Utf8               SourceFile
  #84 = Utf8               ScalaInlineInfo
  #85 = Utf8               Scala
{
  public static final org.scalatest.EitherValues$ MODULE$;
    descriptor: Lorg/scalatest/EitherValues$;
    flags: (0x0019) ACC_PUBLIC, ACC_STATIC, ACC_FINAL

  public static {};
    descriptor: ()V
    flags: (0x0009) ACC_PUBLIC, ACC_STATIC
    Code:
      stack=2, locals=0, args_size=0
         0: new           #2                  // class org/scalatest/EitherValues$
         3: dup
         4: invokespecial #31                 // Method "<init>":()V
         7: putstatic     #33                 // Field MODULE$:Lorg/scalatest/EitherValues$;
        10: getstatic     #33                 // Field MODULE$:Lorg/scalatest/EitherValues$;
        13: invokestatic  #37                 // InterfaceMethod org/scalatest/EitherValues.$init$:(Lorg/scalatest/EitherValues;)V
        16: return
      LineNumberTable:
        line 243: 0

  public <L extends java.lang.Object, R extends java.lang.Object> org.scalatest.EitherValues$LeftValuable<L, R> convertLeftProjectionToValuable(scala.util.Either$LeftProjection<L, R>, org.scalactic.source.Position);
    descriptor: (Lscala/util/Either$LeftProjection;Lorg/scalactic/source/Position;)Lorg/scalatest/EitherValues$LeftValuable;
    flags: (0x0001) ACC_PUBLIC
    Code:
      stack=3, locals=3, args_size=3
         0: aload_0
         1: aload_1
         2: aload_2
         3: invokestatic  #46                 // InterfaceMethod org/scalatest/EitherValues.convertLeftProjectionToValuable$:(Lorg/scalatest/EitherValues;Lscala/util/Either$LeftProjection;Lorg/scalactic/source/Position;)Lorg/scalatest/EitherValues$LeftValuable;
         6: areturn
      LineNumberTable:
        line 243: 0
      LocalVariableTable:
        Start  Length  Slot  Name   Signature
            0       7     0  this   Lorg/scalatest/EitherValues$;
            0       7     1 leftProj   Lscala/util/Either$LeftProjection;
            0       7     2   pos   Lorg/scalactic/source/Position;
    Signature: #40                          // <L:Ljava/lang/Object;R:Ljava/lang/Object;>(Lscala/util/Either$LeftProjection<TL;TR;>;Lorg/scalactic/source/Position;)Lorg/scalatest/EitherValues$LeftValuable<TL;TR;>;
    MethodParameters:
      Name                           Flags
      leftProj                       final
      pos                            final

  public <L extends java.lang.Object, R extends java.lang.Object> org.scalatest.EitherValues$RightValuable<L, R> convertRightProjectionToValuable(scala.util.Either$RightProjection<L, R>, org.scalactic.source.Position);
    descriptor: (Lscala/util/Either$RightProjection;Lorg/scalactic/source/Position;)Lorg/scalatest/EitherValues$RightValuable;
    flags: (0x0001) ACC_PUBLIC
    Code:
      stack=3, locals=3, args_size=3
         0: aload_0
         1: aload_1
         2: aload_2
         3: invokestatic  #57                 // InterfaceMethod org/scalatest/EitherValues.convertRightProjectionToValuable$:(Lorg/scalatest/EitherValues;Lscala/util/Either$RightProjection;Lorg/scalactic/source/Position;)Lorg/scalatest/EitherValues$RightValuable;
         6: areturn
      LineNumberTable:
        line 243: 0
      LocalVariableTable:
        Start  Length  Slot  Name   Signature
            0       7     0  this   Lorg/scalatest/EitherValues$;
            0       7     1 rightProj   Lscala/util/Either$RightProjection;
            0       7     2   pos   Lorg/scalactic/source/Position;
    Signature: #52                          // <L:Ljava/lang/Object;R:Ljava/lang/Object;>(Lscala/util/Either$RightProjection<TL;TR;>;Lorg/scalactic/source/Position;)Lorg/scalatest/EitherValues$RightValuable<TL;TR;>;
    Deprecated: true
    MethodParameters:
      Name                           Flags
      rightProj                      final
      pos                            final

  public <L extends java.lang.Object, R extends java.lang.Object> org.scalatest.EitherValues$Valuable<L, R> convertEitherToValuable(scala.util.Either<L, R>, org.scalactic.source.Position);
    descriptor: (Lscala/util/Either;Lorg/scalactic/source/Position;)Lorg/scalatest/EitherValues$Valuable;
    flags: (0x0001) ACC_PUBLIC
    Code:
      stack=3, locals=3, args_size=3
         0: aload_0
         1: aload_1
         2: aload_2
         3: invokestatic  #66                 // InterfaceMethod org/scalatest/EitherValues.convertEitherToValuable$:(Lorg/scalatest/EitherValues;Lscala/util/Either;Lorg/scalactic/source/Position;)Lorg/scalatest/EitherValues$Valuable;
         6: areturn
      LineNumberTable:
        line 243: 0
      LocalVariableTable:
        Start  Length  Slot  Name   Signature
            0       7     0  this   Lorg/scalatest/EitherValues$;
            0       7     1 either   Lscala/util/Either;
            0       7     2   pos   Lorg/scalactic/source/Position;
    Signature: #61                          // <L:Ljava/lang/Object;R:Ljava/lang/Object;>(Lscala/util/Either<TL;TR;>;Lorg/scalactic/source/Position;)Lorg/scalatest/EitherValues$Valuable<TL;TR;>;
    MethodParameters:
      Name                           Flags
      either                         final
      pos                            final

  private java.lang.Object writeReplace();
    descriptor: ()Ljava/lang/Object;
    flags: (0x0002) ACC_PRIVATE
    Code:
      stack=3, locals=1, args_size=1
         0: new           #71                 // class scala/runtime/ModuleSerializationProxy
         3: dup
         4: ldc           #2                  // class org/scalatest/EitherValues$
         6: invokespecial #74                 // Method scala/runtime/ModuleSerializationProxy."<init>":(Ljava/lang/Class;)V
         9: areturn
      LineNumberTable:
        line 243: 0
      LocalVariableTable:
        Start  Length  Slot  Name   Signature
            0      10     0  this   Lorg/scalatest/EitherValues$;

  private org.scalatest.EitherValues$();
    descriptor: ()V
    flags: (0x0002) ACC_PRIVATE
    Code:
      stack=1, locals=1, args_size=1
         0: aload_0
         1: invokespecial #75                 // Method java/lang/Object."<init>":()V
         4: return
      LineNumberTable:
        line 243: 0
      LocalVariableTable:
        Start  Length  Slot  Name   Signature
            0       5     0  this   Lorg/scalatest/EitherValues$;
}
InnerClasses:
  public #10= #9 of #6;                   // LeftValuable=class org/scalatest/EitherValues$LeftValuable of class org/scalatest/EitherValues
  public #13= #12 of #6;                  // RightValuable=class org/scalatest/EitherValues$RightValuable of class org/scalatest/EitherValues
  public #16= #15 of #6;                  // Valuable=class org/scalatest/EitherValues$Valuable of class org/scalatest/EitherValues
  public static final #21= #18 of #20;    // LeftProjection=class scala/util/Either$LeftProjection of class scala/util/Either
  public static final #24= #23 of #20;    // RightProjection=class scala/util/Either$RightProjection of class scala/util/Either
SourceFile: "EitherValues.scala"
  ScalaInlineInfo: length = 0x1D (unknown attribute)
   01 01 00 05 00 1D 00 1C 01 00 3B 00 3C 01 00 26
   00 27 01 00 32 00 33 01 00 44 00 45 01
  Scala: length = 0x0 (unknown attribute)

