Classfile /Users/mw/Projects/slang-braindump/.jar/jar11/assemble/slang-braindump/assemble/content/org/scalatest/FailedStatus.class
  Last modified May 29, 2022; size 1943 bytes
  SHA-256 checksum 61c05dfdeb3ca91cf9faa8edbc61ee06dbc4a0c3ce371515e8b729805c8c0669
  Compiled from "Status.scala"
public final class org.scalatest.FailedStatus
  minor version: 0
  major version: 52
  flags: (0x0031) ACC_PUBLIC, ACC_FINAL, ACC_SUPER
  this_class: #2                          // org/scalatest/FailedStatus
  super_class: #4                         // java/lang/Object
  interfaces: 0, fields: 0, methods: 8, attributes: 3
Constant pool:
   #1 = Utf8               org/scalatest/FailedStatus
   #2 = Class              #1             // org/scalatest/FailedStatus
   #3 = Utf8               java/lang/Object
   #4 = Class              #3             // java/lang/Object
   #5 = Utf8               Status.scala
   #6 = Utf8               Lscala/reflect/ScalaSignature;
   #7 = Utf8               bytes
   #8 = Utf8               \u0006\u0005\u0015;Q\u0001C\u0005\t\u000291Q\u0001E\u0005\t\u0002EAQaI\u0001\u0005\u0002\u0011BQ!J\u0001\u0005\u0002\u0019BQAK\u0001\u0005\u0002\u0019BQaK\u0001\u0005\u00021BQ\u0001M\u0001\u0005\u0002EBq!P\u0001\u0002\u0002\u0013%a(\u0001\u0007GC&dW\rZ*uCR,8O\u0003\u0002\u000b\u0017\u0005I1oY1mCR,7\u000f\u001e\u0006\u0002\u0019\u0005\u0019qN]4\u0004\u0001A\u0011q\"A\u0007\u0002\u0013\taa)Y5mK\u0012\u001cF/\u0019;vgN!\u0011A\u0005\r\u001c!\t\u0019b#D\u0001\u0015\u0015\u0005)\u0012!B:dC2\f\u0017BA\f\u0015\u0005\u0019\te.\u001f*fMB\u0011q\"G\u0005\u00035%\u0011aa\u0015;biV\u001c\bC\u0001\u000f\"\u001b\u0005i\"B\u0001\u0010 \u0003\tIwNC\u0001!\u0003\u0011Q\u0017M^1\n\u0005\tj\"\u0001D*fe&\fG.\u001b>bE2,\u0017A\u0002\u001fj]&$h\bF\u0001\u000f\u0003!\u0019XoY2fK\u0012\u001cH#A\u0014\u0011\u0005MA\u0013BA\u0015\u0015\u0005\u001d\u0011un\u001c7fC:\f1\"[:D_6\u0004H.\u001a;fI\u0006\u0011r/Y5u+:$\u0018\u000e\\\"p[BdW\r^3e)\u0005i\u0003CA\n/\u0013\tyCC\u0001\u0003V]&$\u0018!D<iK:\u001cu.\u001c9mKR,G\r\u0006\u0002.e!)1G\u0002a\u0001i\u0005\ta\r\u0005\u0003\u0014k]j\u0013B\u0001\u001c\u0015\u0005%1UO\\2uS>t\u0017\u0007E\u00029w\u001dj\u0011!\u000f\u0006\u0003uQ\tA!\u001e;jY&\u0011A(\u000f\u0002\u0004)JL\u0018\u0001D<sSR,\'+\u001a9mC\u000e,G#A \u0011\u0005\u0001\u001bU\"A!\u000b\u0005\t{\u0012\u0001\u00027b]\u001eL!\u0001R!\u0003\r=\u0013\'.Z2u\u0001
   #9 = Utf8               whenCompleted
  #10 = Utf8               (Lscala/Function1;)V
  #11 = Utf8               (Lscala/Function1<Lscala/util/Try<Ljava/lang/Object;>;Lscala/runtime/BoxedUnit;>;)V
  #12 = Utf8               f
  #13 = Utf8               org/scalatest/FailedStatus$
  #14 = Class              #13            // org/scalatest/FailedStatus$
  #15 = Utf8               MODULE$
  #16 = Utf8               Lorg/scalatest/FailedStatus$;
  #17 = NameAndType        #15:#16        // MODULE$:Lorg/scalatest/FailedStatus$;
  #18 = Fieldref           #14.#17        // org/scalatest/FailedStatus$.MODULE$:Lorg/scalatest/FailedStatus$;
  #19 = NameAndType        #9:#10         // whenCompleted:(Lscala/Function1;)V
  #20 = Methodref          #14.#19        // org/scalatest/FailedStatus$.whenCompleted:(Lscala/Function1;)V
  #21 = Utf8               Lscala/Function1;
  #22 = Utf8               waitUntilCompleted
  #23 = Utf8               ()V
  #24 = NameAndType        #22:#23        // waitUntilCompleted:()V
  #25 = Methodref          #14.#24        // org/scalatest/FailedStatus$.waitUntilCompleted:()V
  #26 = Utf8               isCompleted
  #27 = Utf8               ()Z
  #28 = NameAndType        #26:#27        // isCompleted:()Z
  #29 = Methodref          #14.#28        // org/scalatest/FailedStatus$.isCompleted:()Z
  #30 = Utf8               succeeds
  #31 = NameAndType        #30:#27        // succeeds:()Z
  #32 = Methodref          #14.#31        // org/scalatest/FailedStatus$.succeeds:()Z
  #33 = Utf8               withAfterEffect
  #34 = Utf8               (Lscala/Function0;)Lorg/scalatest/Status;
  #35 = Utf8               (Lscala/Function0<Lscala/runtime/BoxedUnit;>;)Lorg/scalatest/Status;
  #36 = NameAndType        #33:#34        // withAfterEffect:(Lscala/Function0;)Lorg/scalatest/Status;
  #37 = Methodref          #14.#36        // org/scalatest/FailedStatus$.withAfterEffect:(Lscala/Function0;)Lorg/scalatest/Status;
  #38 = Utf8               Lscala/Function0;
  #39 = Utf8               unreportedException
  #40 = Utf8               ()Lscala/Option;
  #41 = Utf8               ()Lscala/Option<Ljava/lang/Throwable;>;
  #42 = NameAndType        #39:#40        // unreportedException:()Lscala/Option;
  #43 = Methodref          #14.#42        // org/scalatest/FailedStatus$.unreportedException:()Lscala/Option;
  #44 = Utf8               toFuture
  #45 = Utf8               ()Lscala/concurrent/Future;
  #46 = Utf8               ()Lscala/concurrent/Future<Ljava/lang/Object;>;
  #47 = NameAndType        #44:#45        // toFuture:()Lscala/concurrent/Future;
  #48 = Methodref          #14.#47        // org/scalatest/FailedStatus$.toFuture:()Lscala/concurrent/Future;
  #49 = Utf8               thenRun
  #50 = Utf8               (Lscala/Function0<Lorg/scalatest/Status;>;)Lorg/scalatest/Status;
  #51 = NameAndType        #49:#34        // thenRun:(Lscala/Function0;)Lorg/scalatest/Status;
  #52 = Methodref          #14.#51        // org/scalatest/FailedStatus$.thenRun:(Lscala/Function0;)Lorg/scalatest/Status;
  #53 = Utf8               Code
  #54 = Utf8               LocalVariableTable
  #55 = Utf8               Signature
  #56 = Utf8               MethodParameters
  #57 = Utf8               SourceFile
  #58 = Utf8               RuntimeVisibleAnnotations
  #59 = Utf8               ScalaSig
{
  public static void whenCompleted(scala.Function1<scala.util.Try<java.lang.Object>, scala.runtime.BoxedUnit>);
    descriptor: (Lscala/Function1;)V
    flags: (0x0009) ACC_PUBLIC, ACC_STATIC
    Code:
      stack=2, locals=1, args_size=1
         0: getstatic     #18                 // Field org/scalatest/FailedStatus$.MODULE$:Lorg/scalatest/FailedStatus$;
         3: aload_0
         4: invokevirtual #20                 // Method org/scalatest/FailedStatus$.whenCompleted:(Lscala/Function1;)V
         7: return
      LocalVariableTable:
        Start  Length  Slot  Name   Signature
            0       8     0     f   Lscala/Function1;
    Signature: #11                          // (Lscala/Function1<Lscala/util/Try<Ljava/lang/Object;>;Lscala/runtime/BoxedUnit;>;)V
    MethodParameters:
      Name                           Flags
      f                              final

  public static void waitUntilCompleted();
    descriptor: ()V
    flags: (0x0009) ACC_PUBLIC, ACC_STATIC
    Code:
      stack=1, locals=0, args_size=0
         0: getstatic     #18                 // Field org/scalatest/FailedStatus$.MODULE$:Lorg/scalatest/FailedStatus$;
         3: invokevirtual #25                 // Method org/scalatest/FailedStatus$.waitUntilCompleted:()V
         6: return

  public static boolean isCompleted();
    descriptor: ()Z
    flags: (0x0009) ACC_PUBLIC, ACC_STATIC
    Code:
      stack=1, locals=0, args_size=0
         0: getstatic     #18                 // Field org/scalatest/FailedStatus$.MODULE$:Lorg/scalatest/FailedStatus$;
         3: invokevirtual #29                 // Method org/scalatest/FailedStatus$.isCompleted:()Z
         6: ireturn

  public static boolean succeeds();
    descriptor: ()Z
    flags: (0x0009) ACC_PUBLIC, ACC_STATIC
    Code:
      stack=1, locals=0, args_size=0
         0: getstatic     #18                 // Field org/scalatest/FailedStatus$.MODULE$:Lorg/scalatest/FailedStatus$;
         3: invokevirtual #32                 // Method org/scalatest/FailedStatus$.succeeds:()Z
         6: ireturn

  public static org.scalatest.Status withAfterEffect(scala.Function0<scala.runtime.BoxedUnit>);
    descriptor: (Lscala/Function0;)Lorg/scalatest/Status;
    flags: (0x0009) ACC_PUBLIC, ACC_STATIC
    Code:
      stack=2, locals=1, args_size=1
         0: getstatic     #18                 // Field org/scalatest/FailedStatus$.MODULE$:Lorg/scalatest/FailedStatus$;
         3: aload_0
         4: invokevirtual #37                 // Method org/scalatest/FailedStatus$.withAfterEffect:(Lscala/Function0;)Lorg/scalatest/Status;
         7: areturn
      LocalVariableTable:
        Start  Length  Slot  Name   Signature
            0       8     0     f   Lscala/Function0;
    Signature: #35                          // (Lscala/Function0<Lscala/runtime/BoxedUnit;>;)Lorg/scalatest/Status;
    MethodParameters:
      Name                           Flags
      f                              final

  public static scala.Option<java.lang.Throwable> unreportedException();
    descriptor: ()Lscala/Option;
    flags: (0x0009) ACC_PUBLIC, ACC_STATIC
    Code:
      stack=1, locals=0, args_size=0
         0: getstatic     #18                 // Field org/scalatest/FailedStatus$.MODULE$:Lorg/scalatest/FailedStatus$;
         3: invokevirtual #43                 // Method org/scalatest/FailedStatus$.unreportedException:()Lscala/Option;
         6: areturn
    Signature: #41                          // ()Lscala/Option<Ljava/lang/Throwable;>;

  public static scala.concurrent.Future<java.lang.Object> toFuture();
    descriptor: ()Lscala/concurrent/Future;
    flags: (0x0009) ACC_PUBLIC, ACC_STATIC
    Code:
      stack=1, locals=0, args_size=0
         0: getstatic     #18                 // Field org/scalatest/FailedStatus$.MODULE$:Lorg/scalatest/FailedStatus$;
         3: invokevirtual #48                 // Method org/scalatest/FailedStatus$.toFuture:()Lscala/concurrent/Future;
         6: areturn
    Signature: #46                          // ()Lscala/concurrent/Future<Ljava/lang/Object;>;

  public static org.scalatest.Status thenRun(scala.Function0<org.scalatest.Status>);
    descriptor: (Lscala/Function0;)Lorg/scalatest/Status;
    flags: (0x0009) ACC_PUBLIC, ACC_STATIC
    Code:
      stack=2, locals=1, args_size=1
         0: getstatic     #18                 // Field org/scalatest/FailedStatus$.MODULE$:Lorg/scalatest/FailedStatus$;
         3: aload_0
         4: invokevirtual #52                 // Method org/scalatest/FailedStatus$.thenRun:(Lscala/Function0;)Lorg/scalatest/Status;
         7: areturn
      LocalVariableTable:
        Start  Length  Slot  Name   Signature
            0       8     0     f   Lscala/Function0;
    Signature: #50                          // (Lscala/Function0<Lorg/scalatest/Status;>;)Lorg/scalatest/Status;
    MethodParameters:
      Name                           Flags
      f                              final
}
SourceFile: "Status.scala"
RuntimeVisibleAnnotations:
  0: #6(#7=s#8)
    scala.reflect.ScalaSignature(
      bytes="\u0006\u0005\u0015;Q\u0001C\u0005\t\u000291Q\u0001E\u0005\t\u0002EAQaI\u0001\u0005\u0002\u0011BQ!J\u0001\u0005\u0002\u0019BQAK\u0001\u0005\u0002\u0019BQaK\u0001\u0005\u00021BQ\u0001M\u0001\u0005\u0002EBq!P\u0001\u0002\u0002\u0013%a(\u0001\u0007GC&dW\rZ*uCR,8O\u0003\u0002\u000b\u0017\u0005I1oY1mCR,7\u000f\u001e\u0006\u0002\u0019\u0005\u0019qN]4\u0004\u0001A\u0011q\"A\u0007\u0002\u0013\taa)Y5mK\u0012\u001cF/\u0019;vgN!\u0011A\u0005\r\u001c!\t\u0019b#D\u0001\u0015\u0015\u0005)\u0012!B:dC2\f\u0017BA\f\u0015\u0005\u0019\te.\u001f*fMB\u0011q\"G\u0005\u00035%\u0011aa\u0015;biV\u001c\bC\u0001\u000f\"\u001b\u0005i\"B\u0001\u0010 \u0003\tIwNC\u0001!\u0003\u0011Q\u0017M^1\n\u0005\tj\"\u0001D*fe&\fG.\u001b>bE2,\u0017A\u0002\u001fj]&$h\bF\u0001\u000f\u0003!\u0019XoY2fK\u0012\u001cH#A\u0014\u0011\u0005MA\u0013BA\u0015\u0015\u0005\u001d\u0011un\u001c7fC:\f1\"[:D_6\u0004H.\u001a;fI\u0006\u0011r/Y5u+:$\u0018\u000e\\\"p[BdW\r^3e)\u0005i\u0003CA\n/\u0013\tyCC\u0001\u0003V]&$\u0018!D<iK:\u001cu.\u001c9mKR,G\r\u0006\u0002.e!)1G\u0002a\u0001i\u0005\ta\r\u0005\u0003\u0014k]j\u0013B\u0001\u001c\u0015\u0005%1UO\\2uS>t\u0017\u0007E\u00029w\u001dj\u0011!\u000f\u0006\u0003uQ\tA!\u001e;jY&\u0011A(\u000f\u0002\u0004)JL\u0018\u0001D<sSR,\'+\u001a9mC\u000e,G#A \u0011\u0005\u0001\u001bU\"A!\u000b\u0005\t{\u0012\u0001\u00027b]\u001eL!\u0001R!\u0003\r=\u0013\'.Z2u\u0001"
    )
  ScalaSig: length = 0x3 (unknown attribute)
   05 02 00
