Classfile /Users/mw/Projects/slang-braindump/.jar/jar11/assemble/slang-braindump/assemble/content/org/scalatest/FixtureTestSuite$OneArgTest.class
  Last modified May 29, 2022; size 1526 bytes
  SHA-256 checksum e7bbcfc25fbde0ec8704dcd7f958b11115c5584445c1f0d2e5f8b3c75e2f3fcd
  Compiled from "FixtureTestSuite.scala"
public interface org.scalatest.FixtureTestSuite$OneArgTest extends scala.Function1<java.lang.Object, org.scalatest.Outcome>, org.scalatest.TestData
  minor version: 0
  major version: 52
  flags: (0x0601) ACC_PUBLIC, ACC_INTERFACE, ACC_ABSTRACT
  this_class: #2                          // org/scalatest/FixtureTestSuite$OneArgTest
  super_class: #5                         // java/lang/Object
  interfaces: 2, fields: 0, methods: 5, attributes: 5
Constant pool:
   #1 = Utf8               org/scalatest/FixtureTestSuite$OneArgTest
   #2 = Class              #1             // org/scalatest/FixtureTestSuite$OneArgTest
   #3 = Utf8               Ljava/lang/Object;Lscala/Function1<Ljava/lang/Object;Lorg/scalatest/Outcome;>;Lorg/scalatest/TestData;
   #4 = Utf8               java/lang/Object
   #5 = Class              #4             // java/lang/Object
   #6 = Utf8               scala/Function1
   #7 = Class              #6             // scala/Function1
   #8 = Utf8               org/scalatest/TestData
   #9 = Class              #8             // org/scalatest/TestData
  #10 = Utf8               FixtureTestSuite.scala
  #11 = Utf8               org/scalatest/FixtureTestSuite
  #12 = Class              #11            // org/scalatest/FixtureTestSuite
  #13 = Utf8               OneArgTest
  #14 = Utf8               org/scalatest/FixtureTestSuite$OneArgTest$$anon$1
  #15 = Class              #14            // org/scalatest/FixtureTestSuite$OneArgTest$$anon$1
  #16 = Utf8               org/scalatest/TestSuite$NoArgTest
  #17 = Class              #16            // org/scalatest/TestSuite$NoArgTest
  #18 = Utf8               org/scalatest/TestSuite
  #19 = Class              #18            // org/scalatest/TestSuite
  #20 = Utf8               NoArgTest
  #21 = Utf8               apply
  #22 = Utf8               (Ljava/lang/Object;)Lorg/scalatest/Outcome;
  #23 = Utf8               fixture
  #24 = Utf8               toNoArgTest$
  #25 = Utf8               (Lorg/scalatest/FixtureTestSuite$OneArgTest;Ljava/lang/Object;)Lorg/scalatest/TestSuite$NoArgTest;
  #26 = Utf8               $this
  #27 = Utf8               toNoArgTest
  #28 = Utf8               (Ljava/lang/Object;)Lorg/scalatest/TestSuite$NoArgTest;
  #29 = NameAndType        #27:#28        // toNoArgTest:(Ljava/lang/Object;)Lorg/scalatest/TestSuite$NoArgTest;
  #30 = InterfaceMethodref #2.#29         // org/scalatest/FixtureTestSuite$OneArgTest.toNoArgTest:(Ljava/lang/Object;)Lorg/scalatest/TestSuite$NoArgTest;
  #31 = Utf8               Lorg/scalatest/FixtureTestSuite$OneArgTest;
  #32 = Utf8               Ljava/lang/Object;
  #33 = Utf8               <init>
  #34 = Utf8               (Lorg/scalatest/FixtureTestSuite$OneArgTest;Ljava/lang/Object;)V
  #35 = NameAndType        #33:#34        // "<init>":(Lorg/scalatest/FixtureTestSuite$OneArgTest;Ljava/lang/Object;)V
  #36 = Methodref          #15.#35        // org/scalatest/FixtureTestSuite$OneArgTest$$anon$1."<init>":(Lorg/scalatest/FixtureTestSuite$OneArgTest;Ljava/lang/Object;)V
  #37 = Utf8               this
  #38 = Utf8               org$scalatest$FixtureTestSuite$OneArgTest$$$outer
  #39 = Utf8               ()Lorg/scalatest/FixtureTestSuite;
  #40 = Utf8               $init$
  #41 = Utf8               (Lorg/scalatest/FixtureTestSuite$OneArgTest;)V
  #42 = Utf8               MethodParameters
  #43 = Utf8               Code
  #44 = Utf8               LineNumberTable
  #45 = Utf8               LocalVariableTable
  #46 = Utf8               InnerClasses
  #47 = Utf8               Signature
  #48 = Utf8               SourceFile
  #49 = Utf8               ScalaInlineInfo
  #50 = Utf8               Scala
{
  public abstract org.scalatest.Outcome apply(java.lang.Object);
    descriptor: (Ljava/lang/Object;)Lorg/scalatest/Outcome;
    flags: (0x0401) ACC_PUBLIC, ACC_ABSTRACT
    MethodParameters:
      Name                           Flags
      fixture                        final

  public static org.scalatest.TestSuite$NoArgTest toNoArgTest$(org.scalatest.FixtureTestSuite$OneArgTest, java.lang.Object);
    descriptor: (Lorg/scalatest/FixtureTestSuite$OneArgTest;Ljava/lang/Object;)Lorg/scalatest/TestSuite$NoArgTest;
    flags: (0x1009) ACC_PUBLIC, ACC_STATIC, ACC_SYNTHETIC
    Code:
      stack=2, locals=2, args_size=2
         0: aload_0
         1: aload_1
         2: invokespecial #30                 // InterfaceMethod toNoArgTest:(Ljava/lang/Object;)Lorg/scalatest/TestSuite$NoArgTest;
         5: areturn
      LineNumberTable:
        line 219: 0
      LocalVariableTable:
        Start  Length  Slot  Name   Signature
            0       6     0 $this   Lorg/scalatest/FixtureTestSuite$OneArgTest;
            0       6     1 fixture   Ljava/lang/Object;
    MethodParameters:
      Name                           Flags
      $this                          final synthetic
      fixture                        final

  public default org.scalatest.TestSuite$NoArgTest toNoArgTest(java.lang.Object);
    descriptor: (Ljava/lang/Object;)Lorg/scalatest/TestSuite$NoArgTest;
    flags: (0x0001) ACC_PUBLIC
    Code:
      stack=4, locals=2, args_size=2
         0: new           #15                 // class org/scalatest/FixtureTestSuite$OneArgTest$$anon$1
         3: dup
         4: aload_0
         5: aload_1
         6: invokespecial #36                 // Method org/scalatest/FixtureTestSuite$OneArgTest$$anon$1."<init>":(Lorg/scalatest/FixtureTestSuite$OneArgTest;Ljava/lang/Object;)V
         9: areturn
      LineNumberTable:
        line 220: 0
      LocalVariableTable:
        Start  Length  Slot  Name   Signature
            0      10     0  this   Lorg/scalatest/FixtureTestSuite$OneArgTest;
            0      10     1 fixture   Ljava/lang/Object;
    MethodParameters:
      Name                           Flags
      fixture                        final

  public abstract org.scalatest.FixtureTestSuite org$scalatest$FixtureTestSuite$OneArgTest$$$outer();
    descriptor: ()Lorg/scalatest/FixtureTestSuite;
    flags: (0x1401) ACC_PUBLIC, ACC_ABSTRACT, ACC_SYNTHETIC

  public static void $init$(org.scalatest.FixtureTestSuite$OneArgTest);
    descriptor: (Lorg/scalatest/FixtureTestSuite$OneArgTest;)V
    flags: (0x0009) ACC_PUBLIC, ACC_STATIC
    Code:
      stack=0, locals=1, args_size=1
         0: return
      LineNumberTable:
        line 175: 0
      LocalVariableTable:
        Start  Length  Slot  Name   Signature
            0       1     0 $this   Lorg/scalatest/FixtureTestSuite$OneArgTest;
    MethodParameters:
      Name                           Flags
      $this                          final synthetic
}
InnerClasses:
  public #13= #2 of #12;                  // OneArgTest=class org/scalatest/FixtureTestSuite$OneArgTest of class org/scalatest/FixtureTestSuite
  public final #15;                       // class org/scalatest/FixtureTestSuite$OneArgTest$$anon$1
  public #20= #17 of #19;                 // NoArgTest=class org/scalatest/TestSuite$NoArgTest of class org/scalatest/TestSuite
Signature: #3                           // Ljava/lang/Object;Lscala/Function1<Ljava/lang/Object;Lorg/scalatest/Outcome;>;Lorg/scalatest/TestData;
SourceFile: "FixtureTestSuite.scala"
  ScalaInlineInfo: length = 0x1D (unknown attribute)
   01 00 00 05 00 28 00 29 01 00 15 00 16 00 00 26
   00 27 00 00 1B 00 1C 00 00 18 00 19 01
  Scala: length = 0x0 (unknown attribute)

