Classfile /Users/mw/Projects/slang-braindump/.jar/jar11/assemble/slang-braindump/assemble/content/org/scalatest/FutureOutcome$.class
  Last modified May 29, 2022; size 3494 bytes
  SHA-256 checksum 6659045d9f36abf78ca7bf7509ae3c6847131328980c2daa797ac6cc4c0937c2
  Compiled from "FutureOutcome.scala"
public final class org.scalatest.FutureOutcome$
  minor version: 0
  major version: 52
  flags: (0x0031) ACC_PUBLIC, ACC_FINAL, ACC_SUPER
  this_class: #2                          // org/scalatest/FutureOutcome$
  super_class: #4                         // java/lang/Object
  interfaces: 0, fields: 1, methods: 13, attributes: 3
Constant pool:
    #1 = Utf8               org/scalatest/FutureOutcome$
    #2 = Class              #1            // org/scalatest/FutureOutcome$
    #3 = Utf8               java/lang/Object
    #4 = Class              #3            // java/lang/Object
    #5 = Utf8               FutureOutcome.scala
    #6 = Utf8               MODULE$
    #7 = Utf8               Lorg/scalatest/FutureOutcome$;
    #8 = Utf8               <clinit>
    #9 = Utf8               ()V
   #10 = Utf8               <init>
   #11 = NameAndType        #10:#9        // "<init>":()V
   #12 = Methodref          #2.#11        // org/scalatest/FutureOutcome$."<init>":()V
   #13 = NameAndType        #6:#7         // MODULE$:Lorg/scalatest/FutureOutcome$;
   #14 = Fieldref           #2.#13        // org/scalatest/FutureOutcome$.MODULE$:Lorg/scalatest/FutureOutcome$;
   #15 = Utf8               apply
   #16 = Utf8               (Lscala/concurrent/Future;)Lorg/scalatest/FutureOutcome;
   #17 = Utf8               (Lscala/concurrent/Future<Lorg/scalatest/Outcome;>;)Lorg/scalatest/FutureOutcome;
   #18 = Utf8               underlying
   #19 = Utf8               org/scalatest/FutureOutcome
   #20 = Class              #19           // org/scalatest/FutureOutcome
   #21 = Utf8               (Lscala/concurrent/Future;)V
   #22 = NameAndType        #10:#21       // "<init>":(Lscala/concurrent/Future;)V
   #23 = Methodref          #20.#22       // org/scalatest/FutureOutcome."<init>":(Lscala/concurrent/Future;)V
   #24 = Utf8               this
   #25 = Utf8               Lscala/concurrent/Future;
   #26 = Utf8               canceled
   #27 = Utf8               ()Lorg/scalatest/FutureOutcome;
   #28 = Utf8               scala/concurrent/Future$
   #29 = Class              #28           // scala/concurrent/Future$
   #30 = Utf8               Lscala/concurrent/Future$;
   #31 = NameAndType        #6:#30        // MODULE$:Lscala/concurrent/Future$;
   #32 = Fieldref           #29.#31       // scala/concurrent/Future$.MODULE$:Lscala/concurrent/Future$;
   #33 = Utf8               org/scalatest/Canceled$
   #34 = Class              #33           // org/scalatest/Canceled$
   #35 = Utf8               Lorg/scalatest/Canceled$;
   #36 = NameAndType        #6:#35        // MODULE$:Lorg/scalatest/Canceled$;
   #37 = Fieldref           #34.#36       // org/scalatest/Canceled$.MODULE$:Lorg/scalatest/Canceled$;
   #38 = Utf8               org/scalactic/source/Position
   #39 = Class              #38           // org/scalactic/source/Position
   #40 = String             #5            // FutureOutcome.scala
   #41 = Utf8               Please set the environment variable SCALACTIC_FILL_FILE_PATHNAMES to yes at compile time to enable this feature.
   #42 = String             #41           // Please set the environment variable SCALACTIC_FILL_FILE_PATHNAMES to yes at compile time to enable this feature.
   #43 = Utf8               (Ljava/lang/String;Ljava/lang/String;I)V
   #44 = NameAndType        #10:#43       // "<init>":(Ljava/lang/String;Ljava/lang/String;I)V
   #45 = Methodref          #39.#44       // org/scalactic/source/Position."<init>":(Ljava/lang/String;Ljava/lang/String;I)V
   #46 = Utf8               (Lorg/scalactic/source/Position;)Lorg/scalatest/Canceled;
   #47 = NameAndType        #15:#46       // apply:(Lorg/scalactic/source/Position;)Lorg/scalatest/Canceled;
   #48 = Methodref          #34.#47       // org/scalatest/Canceled$.apply:(Lorg/scalactic/source/Position;)Lorg/scalatest/Canceled;
   #49 = Utf8               successful
   #50 = Utf8               (Ljava/lang/Object;)Lscala/concurrent/Future;
   #51 = NameAndType        #49:#50       // successful:(Ljava/lang/Object;)Lscala/concurrent/Future;
   #52 = Methodref          #29.#51       // scala/concurrent/Future$.successful:(Ljava/lang/Object;)Lscala/concurrent/Future;
   #53 = NameAndType        #15:#16       // apply:(Lscala/concurrent/Future;)Lorg/scalatest/FutureOutcome;
   #54 = Methodref          #2.#53        // org/scalatest/FutureOutcome$.apply:(Lscala/concurrent/Future;)Lorg/scalatest/FutureOutcome;
   #55 = Utf8               (Ljava/lang/String;)Lorg/scalatest/FutureOutcome;
   #56 = Utf8               message
   #57 = Utf8               (Ljava/lang/String;Lorg/scalactic/source/Position;)Lorg/scalatest/Canceled;
   #58 = NameAndType        #15:#57       // apply:(Ljava/lang/String;Lorg/scalactic/source/Position;)Lorg/scalatest/Canceled;
   #59 = Methodref          #34.#58       // org/scalatest/Canceled$.apply:(Ljava/lang/String;Lorg/scalactic/source/Position;)Lorg/scalatest/Canceled;
   #60 = Utf8               Ljava/lang/String;
   #61 = Utf8               (Ljava/lang/Throwable;)Lorg/scalatest/FutureOutcome;
   #62 = Utf8               cause
   #63 = Utf8               (Ljava/lang/Throwable;Lorg/scalactic/source/Position;)Lorg/scalatest/Canceled;
   #64 = NameAndType        #15:#63       // apply:(Ljava/lang/Throwable;Lorg/scalactic/source/Position;)Lorg/scalatest/Canceled;
   #65 = Methodref          #34.#64       // org/scalatest/Canceled$.apply:(Ljava/lang/Throwable;Lorg/scalactic/source/Position;)Lorg/scalatest/Canceled;
   #66 = Utf8               Ljava/lang/Throwable;
   #67 = Utf8               (Ljava/lang/String;Ljava/lang/Throwable;)Lorg/scalatest/FutureOutcome;
   #68 = Utf8               (Ljava/lang/String;Ljava/lang/Throwable;Lorg/scalactic/source/Position;)Lorg/scalatest/Canceled;
   #69 = NameAndType        #15:#68       // apply:(Ljava/lang/String;Ljava/lang/Throwable;Lorg/scalactic/source/Position;)Lorg/scalatest/Canceled;
   #70 = Methodref          #34.#69       // org/scalatest/Canceled$.apply:(Ljava/lang/String;Ljava/lang/Throwable;Lorg/scalactic/source/Position;)Lorg/scalatest/Canceled;
   #71 = Utf8               succeeded
   #72 = Utf8               org/scalatest/Succeeded$
   #73 = Class              #72           // org/scalatest/Succeeded$
   #74 = Utf8               Lorg/scalatest/Succeeded$;
   #75 = NameAndType        #6:#74        // MODULE$:Lorg/scalatest/Succeeded$;
   #76 = Fieldref           #73.#75       // org/scalatest/Succeeded$.MODULE$:Lorg/scalatest/Succeeded$;
   #77 = Utf8               failed
   #78 = Utf8               org/scalatest/Failed$
   #79 = Class              #78           // org/scalatest/Failed$
   #80 = Utf8               Lorg/scalatest/Failed$;
   #81 = NameAndType        #6:#80        // MODULE$:Lorg/scalatest/Failed$;
   #82 = Fieldref           #79.#81       // org/scalatest/Failed$.MODULE$:Lorg/scalatest/Failed$;
   #83 = Utf8               (Lorg/scalactic/source/Position;)Lorg/scalatest/Failed;
   #84 = NameAndType        #15:#83       // apply:(Lorg/scalactic/source/Position;)Lorg/scalatest/Failed;
   #85 = Methodref          #79.#84       // org/scalatest/Failed$.apply:(Lorg/scalactic/source/Position;)Lorg/scalatest/Failed;
   #86 = Utf8               (Ljava/lang/String;Lorg/scalactic/source/Position;)Lorg/scalatest/Failed;
   #87 = NameAndType        #15:#86       // apply:(Ljava/lang/String;Lorg/scalactic/source/Position;)Lorg/scalatest/Failed;
   #88 = Methodref          #79.#87       // org/scalatest/Failed$.apply:(Ljava/lang/String;Lorg/scalactic/source/Position;)Lorg/scalatest/Failed;
   #89 = Utf8               (Ljava/lang/String;Ljava/lang/Throwable;Lorg/scalactic/source/Position;)Lorg/scalatest/Failed;
   #90 = NameAndType        #15:#89       // apply:(Ljava/lang/String;Ljava/lang/Throwable;Lorg/scalactic/source/Position;)Lorg/scalatest/Failed;
   #91 = Methodref          #79.#90       // org/scalatest/Failed$.apply:(Ljava/lang/String;Ljava/lang/Throwable;Lorg/scalactic/source/Position;)Lorg/scalatest/Failed;
   #92 = Utf8               org/scalatest/Failed
   #93 = Class              #92           // org/scalatest/Failed
   #94 = Utf8               (Ljava/lang/Throwable;)V
   #95 = NameAndType        #10:#94       // "<init>":(Ljava/lang/Throwable;)V
   #96 = Methodref          #93.#95       // org/scalatest/Failed."<init>":(Ljava/lang/Throwable;)V
   #97 = Utf8               pending
   #98 = Utf8               org/scalatest/Pending$
   #99 = Class              #98           // org/scalatest/Pending$
  #100 = Utf8               Lorg/scalatest/Pending$;
  #101 = NameAndType        #6:#100       // MODULE$:Lorg/scalatest/Pending$;
  #102 = Fieldref           #99.#101      // org/scalatest/Pending$.MODULE$:Lorg/scalatest/Pending$;
  #103 = Methodref          #4.#11        // java/lang/Object."<init>":()V
  #104 = Utf8               Code
  #105 = Utf8               LineNumberTable
  #106 = Utf8               LocalVariableTable
  #107 = Utf8               Signature
  #108 = Utf8               MethodParameters
  #109 = Utf8               SourceFile
  #110 = Utf8               ScalaInlineInfo
  #111 = Utf8               Scala
{
  public static final org.scalatest.FutureOutcome$ MODULE$;
    descriptor: Lorg/scalatest/FutureOutcome$;
    flags: (0x0019) ACC_PUBLIC, ACC_STATIC, ACC_FINAL

  public static {};
    descriptor: ()V
    flags: (0x0009) ACC_PUBLIC, ACC_STATIC
    Code:
      stack=2, locals=0, args_size=0
         0: new           #2                  // class org/scalatest/FutureOutcome$
         3: dup
         4: invokespecial #12                 // Method "<init>":()V
         7: putstatic     #14                 // Field MODULE$:Lorg/scalatest/FutureOutcome$;
        10: return
      LineNumberTable:
        line 546: 0

  public org.scalatest.FutureOutcome apply(scala.concurrent.Future<org.scalatest.Outcome>);
    descriptor: (Lscala/concurrent/Future;)Lorg/scalatest/FutureOutcome;
    flags: (0x0001) ACC_PUBLIC
    Code:
      stack=3, locals=2, args_size=2
         0: new           #20                 // class org/scalatest/FutureOutcome
         3: dup
         4: aload_1
         5: invokespecial #23                 // Method org/scalatest/FutureOutcome."<init>":(Lscala/concurrent/Future;)V
         8: areturn
      LineNumberTable:
        line 550: 0
      LocalVariableTable:
        Start  Length  Slot  Name   Signature
            0       9     0  this   Lorg/scalatest/FutureOutcome$;
            0       9     1 underlying   Lscala/concurrent/Future;
    Signature: #17                          // (Lscala/concurrent/Future<Lorg/scalatest/Outcome;>;)Lorg/scalatest/FutureOutcome;
    MethodParameters:
      Name                           Flags
      underlying                     final

  public org.scalatest.FutureOutcome canceled();
    descriptor: ()Lorg/scalatest/FutureOutcome;
    flags: (0x0001) ACC_PUBLIC
    Code:
      stack=8, locals=1, args_size=1
         0: aload_0
         1: getstatic     #32                 // Field scala/concurrent/Future$.MODULE$:Lscala/concurrent/Future$;
         4: getstatic     #37                 // Field org/scalatest/Canceled$.MODULE$:Lorg/scalatest/Canceled$;
         7: new           #39                 // class org/scalactic/source/Position
        10: dup
        11: ldc           #40                 // String FutureOutcome.scala
        13: ldc           #42                 // String Please set the environment variable SCALACTIC_FILL_FILE_PATHNAMES to yes at compile time to enable this feature.
        15: sipush        556
        18: invokespecial #45                 // Method org/scalactic/source/Position."<init>":(Ljava/lang/String;Ljava/lang/String;I)V
        21: invokevirtual #48                 // Method org/scalatest/Canceled$.apply:(Lorg/scalactic/source/Position;)Lorg/scalatest/Canceled;
        24: invokevirtual #52                 // Method scala/concurrent/Future$.successful:(Ljava/lang/Object;)Lscala/concurrent/Future;
        27: invokevirtual #54                 // Method apply:(Lscala/concurrent/Future;)Lorg/scalatest/FutureOutcome;
        30: areturn
      LineNumberTable:
        line 556: 0
      LocalVariableTable:
        Start  Length  Slot  Name   Signature
            0      31     0  this   Lorg/scalatest/FutureOutcome$;

  public org.scalatest.FutureOutcome canceled(java.lang.String);
    descriptor: (Ljava/lang/String;)Lorg/scalatest/FutureOutcome;
    flags: (0x0001) ACC_PUBLIC
    Code:
      stack=9, locals=2, args_size=2
         0: aload_0
         1: getstatic     #32                 // Field scala/concurrent/Future$.MODULE$:Lscala/concurrent/Future$;
         4: getstatic     #37                 // Field org/scalatest/Canceled$.MODULE$:Lorg/scalatest/Canceled$;
         7: aload_1
         8: new           #39                 // class org/scalactic/source/Position
        11: dup
        12: ldc           #40                 // String FutureOutcome.scala
        14: ldc           #42                 // String Please set the environment variable SCALACTIC_FILL_FILE_PATHNAMES to yes at compile time to enable this feature.
        16: sipush        565
        19: invokespecial #45                 // Method org/scalactic/source/Position."<init>":(Ljava/lang/String;Ljava/lang/String;I)V
        22: invokevirtual #59                 // Method org/scalatest/Canceled$.apply:(Ljava/lang/String;Lorg/scalactic/source/Position;)Lorg/scalatest/Canceled;
        25: invokevirtual #52                 // Method scala/concurrent/Future$.successful:(Ljava/lang/Object;)Lscala/concurrent/Future;
        28: invokevirtual #54                 // Method apply:(Lscala/concurrent/Future;)Lorg/scalatest/FutureOutcome;
        31: areturn
      LineNumberTable:
        line 565: 0
      LocalVariableTable:
        Start  Length  Slot  Name   Signature
            0      32     0  this   Lorg/scalatest/FutureOutcome$;
            0      32     1 message   Ljava/lang/String;
    MethodParameters:
      Name                           Flags
      message                        final

  public org.scalatest.FutureOutcome canceled(java.lang.Throwable);
    descriptor: (Ljava/lang/Throwable;)Lorg/scalatest/FutureOutcome;
    flags: (0x0001) ACC_PUBLIC
    Code:
      stack=9, locals=2, args_size=2
         0: aload_0
         1: getstatic     #32                 // Field scala/concurrent/Future$.MODULE$:Lscala/concurrent/Future$;
         4: getstatic     #37                 // Field org/scalatest/Canceled$.MODULE$:Lorg/scalatest/Canceled$;
         7: aload_1
         8: new           #39                 // class org/scalactic/source/Position
        11: dup
        12: ldc           #40                 // String FutureOutcome.scala
        14: ldc           #42                 // String Please set the environment variable SCALACTIC_FILL_FILE_PATHNAMES to yes at compile time to enable this feature.
        16: sipush        574
        19: invokespecial #45                 // Method org/scalactic/source/Position."<init>":(Ljava/lang/String;Ljava/lang/String;I)V
        22: invokevirtual #65                 // Method org/scalatest/Canceled$.apply:(Ljava/lang/Throwable;Lorg/scalactic/source/Position;)Lorg/scalatest/Canceled;
        25: invokevirtual #52                 // Method scala/concurrent/Future$.successful:(Ljava/lang/Object;)Lscala/concurrent/Future;
        28: invokevirtual #54                 // Method apply:(Lscala/concurrent/Future;)Lorg/scalatest/FutureOutcome;
        31: areturn
      LineNumberTable:
        line 574: 0
      LocalVariableTable:
        Start  Length  Slot  Name   Signature
            0      32     0  this   Lorg/scalatest/FutureOutcome$;
            0      32     1 cause   Ljava/lang/Throwable;
    MethodParameters:
      Name                           Flags
      cause                          final

  public org.scalatest.FutureOutcome canceled(java.lang.String, java.lang.Throwable);
    descriptor: (Ljava/lang/String;Ljava/lang/Throwable;)Lorg/scalatest/FutureOutcome;
    flags: (0x0001) ACC_PUBLIC
    Code:
      stack=10, locals=3, args_size=3
         0: aload_0
         1: getstatic     #32                 // Field scala/concurrent/Future$.MODULE$:Lscala/concurrent/Future$;
         4: getstatic     #37                 // Field org/scalatest/Canceled$.MODULE$:Lorg/scalatest/Canceled$;
         7: aload_1
         8: aload_2
         9: new           #39                 // class org/scalactic/source/Position
        12: dup
        13: ldc           #40                 // String FutureOutcome.scala
        15: ldc           #42                 // String Please set the environment variable SCALACTIC_FILL_FILE_PATHNAMES to yes at compile time to enable this feature.
        17: sipush        584
        20: invokespecial #45                 // Method org/scalactic/source/Position."<init>":(Ljava/lang/String;Ljava/lang/String;I)V
        23: invokevirtual #70                 // Method org/scalatest/Canceled$.apply:(Ljava/lang/String;Ljava/lang/Throwable;Lorg/scalactic/source/Position;)Lorg/scalatest/Canceled;
        26: invokevirtual #52                 // Method scala/concurrent/Future$.successful:(Ljava/lang/Object;)Lscala/concurrent/Future;
        29: invokevirtual #54                 // Method apply:(Lscala/concurrent/Future;)Lorg/scalatest/FutureOutcome;
        32: areturn
      LineNumberTable:
        line 584: 0
      LocalVariableTable:
        Start  Length  Slot  Name   Signature
            0      33     0  this   Lorg/scalatest/FutureOutcome$;
            0      33     1 message   Ljava/lang/String;
            0      33     2 cause   Ljava/lang/Throwable;
    MethodParameters:
      Name                           Flags
      message                        final
      cause                          final

  public org.scalatest.FutureOutcome succeeded();
    descriptor: ()Lorg/scalatest/FutureOutcome;
    flags: (0x0001) ACC_PUBLIC
    Code:
      stack=3, locals=1, args_size=1
         0: aload_0
         1: getstatic     #32                 // Field scala/concurrent/Future$.MODULE$:Lscala/concurrent/Future$;
         4: getstatic     #76                 // Field org/scalatest/Succeeded$.MODULE$:Lorg/scalatest/Succeeded$;
         7: invokevirtual #52                 // Method scala/concurrent/Future$.successful:(Ljava/lang/Object;)Lscala/concurrent/Future;
        10: invokevirtual #54                 // Method apply:(Lscala/concurrent/Future;)Lorg/scalatest/FutureOutcome;
        13: areturn
      LineNumberTable:
        line 590: 0
      LocalVariableTable:
        Start  Length  Slot  Name   Signature
            0      14     0  this   Lorg/scalatest/FutureOutcome$;

  public org.scalatest.FutureOutcome failed();
    descriptor: ()Lorg/scalatest/FutureOutcome;
    flags: (0x0001) ACC_PUBLIC
    Code:
      stack=8, locals=1, args_size=1
         0: aload_0
         1: getstatic     #32                 // Field scala/concurrent/Future$.MODULE$:Lscala/concurrent/Future$;
         4: getstatic     #82                 // Field org/scalatest/Failed$.MODULE$:Lorg/scalatest/Failed$;
         7: new           #39                 // class org/scalactic/source/Position
        10: dup
        11: ldc           #40                 // String FutureOutcome.scala
        13: ldc           #42                 // String Please set the environment variable SCALACTIC_FILL_FILE_PATHNAMES to yes at compile time to enable this feature.
        15: sipush        596
        18: invokespecial #45                 // Method org/scalactic/source/Position."<init>":(Ljava/lang/String;Ljava/lang/String;I)V
        21: invokevirtual #85                 // Method org/scalatest/Failed$.apply:(Lorg/scalactic/source/Position;)Lorg/scalatest/Failed;
        24: invokevirtual #52                 // Method scala/concurrent/Future$.successful:(Ljava/lang/Object;)Lscala/concurrent/Future;
        27: invokevirtual #54                 // Method apply:(Lscala/concurrent/Future;)Lorg/scalatest/FutureOutcome;
        30: areturn
      LineNumberTable:
        line 596: 0
      LocalVariableTable:
        Start  Length  Slot  Name   Signature
            0      31     0  this   Lorg/scalatest/FutureOutcome$;

  public org.scalatest.FutureOutcome failed(java.lang.String);
    descriptor: (Ljava/lang/String;)Lorg/scalatest/FutureOutcome;
    flags: (0x0001) ACC_PUBLIC
    Code:
      stack=9, locals=2, args_size=2
         0: aload_0
         1: getstatic     #32                 // Field scala/concurrent/Future$.MODULE$:Lscala/concurrent/Future$;
         4: getstatic     #82                 // Field org/scalatest/Failed$.MODULE$:Lorg/scalatest/Failed$;
         7: aload_1
         8: new           #39                 // class org/scalactic/source/Position
        11: dup
        12: ldc           #40                 // String FutureOutcome.scala
        14: ldc           #42                 // String Please set the environment variable SCALACTIC_FILL_FILE_PATHNAMES to yes at compile time to enable this feature.
        16: sipush        605
        19: invokespecial #45                 // Method org/scalactic/source/Position."<init>":(Ljava/lang/String;Ljava/lang/String;I)V
        22: invokevirtual #88                 // Method org/scalatest/Failed$.apply:(Ljava/lang/String;Lorg/scalactic/source/Position;)Lorg/scalatest/Failed;
        25: invokevirtual #52                 // Method scala/concurrent/Future$.successful:(Ljava/lang/Object;)Lscala/concurrent/Future;
        28: invokevirtual #54                 // Method apply:(Lscala/concurrent/Future;)Lorg/scalatest/FutureOutcome;
        31: areturn
      LineNumberTable:
        line 605: 0
      LocalVariableTable:
        Start  Length  Slot  Name   Signature
            0      32     0  this   Lorg/scalatest/FutureOutcome$;
            0      32     1 message   Ljava/lang/String;
    MethodParameters:
      Name                           Flags
      message                        final

  public org.scalatest.FutureOutcome failed(java.lang.String, java.lang.Throwable);
    descriptor: (Ljava/lang/String;Ljava/lang/Throwable;)Lorg/scalatest/FutureOutcome;
    flags: (0x0001) ACC_PUBLIC
    Code:
      stack=10, locals=3, args_size=3
         0: aload_0
         1: getstatic     #32                 // Field scala/concurrent/Future$.MODULE$:Lscala/concurrent/Future$;
         4: getstatic     #82                 // Field org/scalatest/Failed$.MODULE$:Lorg/scalatest/Failed$;
         7: aload_1
         8: aload_2
         9: new           #39                 // class org/scalactic/source/Position
        12: dup
        13: ldc           #40                 // String FutureOutcome.scala
        15: ldc           #42                 // String Please set the environment variable SCALACTIC_FILL_FILE_PATHNAMES to yes at compile time to enable this feature.
        17: sipush        615
        20: invokespecial #45                 // Method org/scalactic/source/Position."<init>":(Ljava/lang/String;Ljava/lang/String;I)V
        23: invokevirtual #91                 // Method org/scalatest/Failed$.apply:(Ljava/lang/String;Ljava/lang/Throwable;Lorg/scalactic/source/Position;)Lorg/scalatest/Failed;
        26: invokevirtual #52                 // Method scala/concurrent/Future$.successful:(Ljava/lang/Object;)Lscala/concurrent/Future;
        29: invokevirtual #54                 // Method apply:(Lscala/concurrent/Future;)Lorg/scalatest/FutureOutcome;
        32: areturn
      LineNumberTable:
        line 615: 0
      LocalVariableTable:
        Start  Length  Slot  Name   Signature
            0      33     0  this   Lorg/scalatest/FutureOutcome$;
            0      33     1 message   Ljava/lang/String;
            0      33     2 cause   Ljava/lang/Throwable;
    MethodParameters:
      Name                           Flags
      message                        final
      cause                          final

  public org.scalatest.FutureOutcome failed(java.lang.Throwable);
    descriptor: (Ljava/lang/Throwable;)Lorg/scalatest/FutureOutcome;
    flags: (0x0001) ACC_PUBLIC
    Code:
      stack=5, locals=2, args_size=2
         0: aload_0
         1: getstatic     #32                 // Field scala/concurrent/Future$.MODULE$:Lscala/concurrent/Future$;
         4: new           #93                 // class org/scalatest/Failed
         7: dup
         8: aload_1
         9: invokespecial #96                 // Method org/scalatest/Failed."<init>":(Ljava/lang/Throwable;)V
        12: invokevirtual #52                 // Method scala/concurrent/Future$.successful:(Ljava/lang/Object;)Lscala/concurrent/Future;
        15: invokevirtual #54                 // Method apply:(Lscala/concurrent/Future;)Lorg/scalatest/FutureOutcome;
        18: areturn
      LineNumberTable:
        line 624: 0
      LocalVariableTable:
        Start  Length  Slot  Name   Signature
            0      19     0  this   Lorg/scalatest/FutureOutcome$;
            0      19     1 cause   Ljava/lang/Throwable;
    MethodParameters:
      Name                           Flags
      cause                          final

  public org.scalatest.FutureOutcome pending();
    descriptor: ()Lorg/scalatest/FutureOutcome;
    flags: (0x0001) ACC_PUBLIC
    Code:
      stack=3, locals=1, args_size=1
         0: aload_0
         1: getstatic     #32                 // Field scala/concurrent/Future$.MODULE$:Lscala/concurrent/Future$;
         4: getstatic     #102                // Field org/scalatest/Pending$.MODULE$:Lorg/scalatest/Pending$;
         7: invokevirtual #52                 // Method scala/concurrent/Future$.successful:(Ljava/lang/Object;)Lscala/concurrent/Future;
        10: invokevirtual #54                 // Method apply:(Lscala/concurrent/Future;)Lorg/scalatest/FutureOutcome;
        13: areturn
      LineNumberTable:
        line 630: 0
      LocalVariableTable:
        Start  Length  Slot  Name   Signature
            0      14     0  this   Lorg/scalatest/FutureOutcome$;

  private org.scalatest.FutureOutcome$();
    descriptor: ()V
    flags: (0x0002) ACC_PRIVATE
    Code:
      stack=1, locals=1, args_size=1
         0: aload_0
         1: invokespecial #103                // Method java/lang/Object."<init>":()V
         4: return
      LineNumberTable:
        line 636: 0
        line 546: 4
      LocalVariableTable:
        Start  Length  Slot  Name   Signature
            0       5     0  this   Lorg/scalatest/FutureOutcome$;
}
SourceFile: "FutureOutcome.scala"
  ScalaInlineInfo: length = 0x40 (unknown attribute)
   01 01 00 0C 00 0A 00 09 01 00 0F 00 10 01 00 1A
   00 1B 01 00 1A 00 37 01 00 1A 00 43 01 00 1A 00
   3D 01 00 4D 00 1B 01 00 4D 00 37 01 00 4D 00 43
   01 00 4D 00 3D 01 00 61 00 1B 01 00 47 00 1B 01

  Scala: length = 0x0 (unknown attribute)

