Classfile /Users/mw/Projects/slang-braindump/.jar/jar11/assemble/slang-braindump/assemble/content/org/scalatest/InsertionOrderSet$.class
  Last modified May 29, 2022; size 1157 bytes
  SHA-256 checksum d74ff788d8b33149ac202e196534de45937f9661e54fa1c45023c1c3234f05e4
  Compiled from "InsertionOrderSet.scala"
public final class org.scalatest.InsertionOrderSet$
  minor version: 0
  major version: 52
  flags: (0x0031) ACC_PUBLIC, ACC_FINAL, ACC_SUPER
  this_class: #2                          // org/scalatest/InsertionOrderSet$
  super_class: #4                         // java/lang/Object
  interfaces: 0, fields: 1, methods: 3, attributes: 4
Constant pool:
   #1 = Utf8               org/scalatest/InsertionOrderSet$
   #2 = Class              #1             // org/scalatest/InsertionOrderSet$
   #3 = Utf8               java/lang/Object
   #4 = Class              #3             // java/lang/Object
   #5 = Utf8               InsertionOrderSet.scala
   #6 = Utf8               org/scalatest/InsertionOrderSet$$anon$1
   #7 = Class              #6             // org/scalatest/InsertionOrderSet$$anon$1
   #8 = Utf8               MODULE$
   #9 = Utf8               Lorg/scalatest/InsertionOrderSet$;
  #10 = Utf8               <clinit>
  #11 = Utf8               ()V
  #12 = Utf8               <init>
  #13 = NameAndType        #12:#11        // "<init>":()V
  #14 = Methodref          #2.#13         // org/scalatest/InsertionOrderSet$."<init>":()V
  #15 = NameAndType        #8:#9          // MODULE$:Lorg/scalatest/InsertionOrderSet$;
  #16 = Fieldref           #2.#15         // org/scalatest/InsertionOrderSet$.MODULE$:Lorg/scalatest/InsertionOrderSet$;
  #17 = Utf8               apply
  #18 = Utf8               (Lscala/collection/immutable/List;)Lscala/collection/immutable/Set;
  #19 = Utf8               <A:Ljava/lang/Object;>(Lscala/collection/immutable/List<TA;>;)Lscala/collection/immutable/Set<TA;>;
  #20 = Utf8               elements
  #21 = Utf8               scala/collection/immutable/SortedSet$
  #22 = Class              #21            // scala/collection/immutable/SortedSet$
  #23 = Utf8               Lscala/collection/immutable/SortedSet$;
  #24 = NameAndType        #8:#23         // MODULE$:Lscala/collection/immutable/SortedSet$;
  #25 = Fieldref           #22.#24        // scala/collection/immutable/SortedSet$.MODULE$:Lscala/collection/immutable/SortedSet$;
  #26 = Utf8               (Lscala/collection/immutable/List;)V
  #27 = NameAndType        #12:#26        // "<init>":(Lscala/collection/immutable/List;)V
  #28 = Methodref          #7.#27         // org/scalatest/InsertionOrderSet$$anon$1."<init>":(Lscala/collection/immutable/List;)V
  #29 = Utf8               (Lscala/collection/immutable/Seq;Ljava/lang/Object;)Ljava/lang/Object;
  #30 = NameAndType        #17:#29        // apply:(Lscala/collection/immutable/Seq;Ljava/lang/Object;)Ljava/lang/Object;
  #31 = Methodref          #22.#30        // scala/collection/immutable/SortedSet$.apply:(Lscala/collection/immutable/Seq;Ljava/lang/Object;)Ljava/lang/Object;
  #32 = Utf8               scala/collection/immutable/Set
  #33 = Class              #32            // scala/collection/immutable/Set
  #34 = Utf8               this
  #35 = Utf8               Lscala/collection/immutable/List;
  #36 = Methodref          #4.#13         // java/lang/Object."<init>":()V
  #37 = Utf8               Code
  #38 = Utf8               LineNumberTable
  #39 = Utf8               LocalVariableTable
  #40 = Utf8               Signature
  #41 = Utf8               MethodParameters
  #42 = Utf8               InnerClasses
  #43 = Utf8               SourceFile
  #44 = Utf8               ScalaInlineInfo
  #45 = Utf8               Scala
{
  public static final org.scalatest.InsertionOrderSet$ MODULE$;
    descriptor: Lorg/scalatest/InsertionOrderSet$;
    flags: (0x0019) ACC_PUBLIC, ACC_STATIC, ACC_FINAL

  public static {};
    descriptor: ()V
    flags: (0x0009) ACC_PUBLIC, ACC_STATIC
    Code:
      stack=2, locals=0, args_size=0
         0: new           #2                  // class org/scalatest/InsertionOrderSet$
         3: dup
         4: invokespecial #14                 // Method "<init>":()V
         7: putstatic     #16                 // Field MODULE$:Lorg/scalatest/InsertionOrderSet$;
        10: return
      LineNumberTable:
        line 18: 0

  public <A extends java.lang.Object> scala.collection.immutable.Set<A> apply(scala.collection.immutable.List<A>);
    descriptor: (Lscala/collection/immutable/List;)Lscala/collection/immutable/Set;
    flags: (0x0001) ACC_PUBLIC
    Code:
      stack=5, locals=2, args_size=2
         0: getstatic     #25                 // Field scala/collection/immutable/SortedSet$.MODULE$:Lscala/collection/immutable/SortedSet$;
         3: aload_1
         4: new           #7                  // class org/scalatest/InsertionOrderSet$$anon$1
         7: dup
         8: aload_1
         9: invokespecial #28                 // Method org/scalatest/InsertionOrderSet$$anon$1."<init>":(Lscala/collection/immutable/List;)V
        12: invokevirtual #31                 // Method scala/collection/immutable/SortedSet$.apply:(Lscala/collection/immutable/Seq;Ljava/lang/Object;)Ljava/lang/Object;
        15: checkcast     #33                 // class scala/collection/immutable/Set
        18: areturn
      LineNumberTable:
        line 20: 0
      LocalVariableTable:
        Start  Length  Slot  Name   Signature
            0      19     0  this   Lorg/scalatest/InsertionOrderSet$;
            0      19     1 elements   Lscala/collection/immutable/List;
    Signature: #19                          // <A:Ljava/lang/Object;>(Lscala/collection/immutable/List<TA;>;)Lscala/collection/immutable/Set<TA;>;
    MethodParameters:
      Name                           Flags
      elements                       final

  private org.scalatest.InsertionOrderSet$();
    descriptor: ()V
    flags: (0x0002) ACC_PRIVATE
    Code:
      stack=1, locals=1, args_size=1
         0: aload_0
         1: invokespecial #36                 // Method java/lang/Object."<init>":()V
         4: return
      LineNumberTable:
        line 23: 0
        line 18: 4
      LocalVariableTable:
        Start  Length  Slot  Name   Signature
            0       5     0  this   Lorg/scalatest/InsertionOrderSet$;
}
InnerClasses:
  public final #7;                        // class org/scalatest/InsertionOrderSet$$anon$1
SourceFile: "InsertionOrderSet.scala"
  ScalaInlineInfo: length = 0xE (unknown attribute)
   01 01 00 02 00 0C 00 0B 01 00 11 00 12 01
  Scala: length = 0x0 (unknown attribute)

