Classfile /Users/mw/Projects/slang-braindump/.jar/jar11/assemble/slang-braindump/assemble/content/org/scalatest/LinkedBlockingQueue.class
  Last modified May 29, 2022; size 1821 bytes
  SHA-256 checksum c27a161fae38a705f1e069406d638003cf04d6ebd2d7b25aa05b77738fed0ee1
  Compiled from "JavaClassesWrappers.scala"
public class org.scalatest.LinkedBlockingQueue<T extends java.lang.Object> extends java.lang.Object implements java.io.Serializable
  minor version: 0
  major version: 52
  flags: (0x0021) ACC_PUBLIC, ACC_SUPER
  this_class: #2                          // org/scalatest/LinkedBlockingQueue
  super_class: #5                         // java/lang/Object
  interfaces: 1, fields: 1, methods: 5, attributes: 5
Constant pool:
   #1 = Utf8               org/scalatest/LinkedBlockingQueue
   #2 = Class              #1             // org/scalatest/LinkedBlockingQueue
   #3 = Utf8               <T:Ljava/lang/Object;>Ljava/lang/Object;Ljava/io/Serializable;
   #4 = Utf8               java/lang/Object
   #5 = Class              #4             // java/lang/Object
   #6 = Utf8               java/io/Serializable
   #7 = Class              #6             // java/io/Serializable
   #8 = Utf8               JavaClassesWrappers.scala
   #9 = Utf8               Lscala/reflect/ScalaSignature;
  #10 = Utf8               bytes
  #11 = Utf8               \u0006\u0005)3Qa\u0002\u0005\u0001\u00111AQ!\t\u0001\u0005\u0002\tBq\u0001\r\u0001C\u0002\u00135\u0011\u0007\u0003\u0004<\u0001\u0001\u0006iA\r\u0005\u0006y\u0001!\t!\u0010\u0005\u0006\u0007\u0002!\t\u0001\u0012\u0005\u0006\u000b\u0002!\tA\u0012\u0002\u0014\u0019&t7.\u001a3CY>\u001c7.\u001b8h#V,W/\u001a\u0006\u0003\u0013)\t\u0011b]2bY\u0006$Xm\u001d;\u000b\u0003-\t1a\u001c:h+\tiqeE\u0002\u0001\u001dQ\u0001\"a\u0004\n\u000e\u0003AQ\u0011!E\u0001\u0006g\u000e\fG.Y\u0005\u0003\'A\u0011a!\u00118z%\u00164\u0007CA\u000b\u001f\u001d\t1BD\u0004\u0002\u001875\t\u0001D\u0003\u0002\u001a5\u00051AH]8piz\u001a\u0001!C\u0001\u0012\u0013\ti\u0002#A\u0004qC\u000e\\\u0017mZ3\n\u0005}\u0001#\u0001D*fe&\fG.\u001b>bE2,\'BA\u000f\u0011\u0003\u0019a\u0014N\\5u}Q\t1\u0005E\u0002%\u0001\u0015j\u0011\u0001\u0003\t\u0003M\u001db\u0001\u0001B\u0003)\u0001\t\u0007\u0011FA\u0001U#\tQS\u0006\u0005\u0002\u0010W%\u0011A\u0006\u0005\u0002\b\u001d>$\b.\u001b8h!\tya&\u0003\u00020!\t\u0019\u0011I\\=\u0002\u000bE,X-^3\u0016\u0003I\u00022a\r\u001e&\u001b\u0005!$BA\u001b7\u0003)\u0019wN\\2veJ,g\u000e\u001e\u0006\u0003oa\nA!\u001e;jY*\t\u0011(\u0001\u0003kCZ\f\u0017BA\u00045\u0003\u0019\tX/Z;fA\u0005\u0019\u0001/\u001e;\u0015\u0005y\n\u0005CA\b@\u0013\t\u0001\u0005C\u0001\u0003V]&$\b\"\u0002\"\u0005\u0001\u0004)\u0013aA3mK\u0006!A/Y6f)\u0005)\u0013\u0001B:ju\u0016,\u0012a\u0012\t\u0003\u001f!K!!\u0013\t\u0003\u0007%sG\u000f
  #12 = Utf8               queue
  #13 = Utf8               Ljava/util/concurrent/LinkedBlockingQueue;
  #14 = Utf8               Ljava/util/concurrent/LinkedBlockingQueue<TT;>;
  #15 = Utf8               ()Ljava/util/concurrent/LinkedBlockingQueue;
  #16 = Utf8               ()Ljava/util/concurrent/LinkedBlockingQueue<TT;>;
  #17 = NameAndType        #12:#13        // queue:Ljava/util/concurrent/LinkedBlockingQueue;
  #18 = Fieldref           #2.#17         // org/scalatest/LinkedBlockingQueue.queue:Ljava/util/concurrent/LinkedBlockingQueue;
  #19 = Utf8               this
  #20 = Utf8               Lorg/scalatest/LinkedBlockingQueue;
  #21 = Utf8               put
  #22 = Utf8               (Ljava/lang/Object;)V
  #23 = Utf8               (TT;)V
  #24 = Utf8               ele
  #25 = NameAndType        #12:#15        // queue:()Ljava/util/concurrent/LinkedBlockingQueue;
  #26 = Methodref          #2.#25         // org/scalatest/LinkedBlockingQueue.queue:()Ljava/util/concurrent/LinkedBlockingQueue;
  #27 = Utf8               java/util/concurrent/LinkedBlockingQueue
  #28 = Class              #27            // java/util/concurrent/LinkedBlockingQueue
  #29 = NameAndType        #21:#22        // put:(Ljava/lang/Object;)V
  #30 = Methodref          #28.#29        // java/util/concurrent/LinkedBlockingQueue.put:(Ljava/lang/Object;)V
  #31 = Utf8               Ljava/lang/Object;
  #32 = Utf8               take
  #33 = Utf8               ()Ljava/lang/Object;
  #34 = Utf8               ()TT;
  #35 = NameAndType        #32:#33        // take:()Ljava/lang/Object;
  #36 = Methodref          #28.#35        // java/util/concurrent/LinkedBlockingQueue.take:()Ljava/lang/Object;
  #37 = Utf8               size
  #38 = Utf8               ()I
  #39 = NameAndType        #37:#38        // size:()I
  #40 = Methodref          #28.#39        // java/util/concurrent/LinkedBlockingQueue.size:()I
  #41 = Utf8               <init>
  #42 = Utf8               ()V
  #43 = NameAndType        #41:#42        // "<init>":()V
  #44 = Methodref          #5.#43         // java/lang/Object."<init>":()V
  #45 = Methodref          #28.#43        // java/util/concurrent/LinkedBlockingQueue."<init>":()V
  #46 = Utf8               Signature
  #47 = Utf8               Code
  #48 = Utf8               LineNumberTable
  #49 = Utf8               LocalVariableTable
  #50 = Utf8               MethodParameters
  #51 = Utf8               SourceFile
  #52 = Utf8               RuntimeVisibleAnnotations
  #53 = Utf8               ScalaInlineInfo
  #54 = Utf8               ScalaSig
{
  private final java.util.concurrent.LinkedBlockingQueue<T> queue;
    descriptor: Ljava/util/concurrent/LinkedBlockingQueue;
    flags: (0x0012) ACC_PRIVATE, ACC_FINAL
    Signature: #14                          // Ljava/util/concurrent/LinkedBlockingQueue<TT;>;

  private final java.util.concurrent.LinkedBlockingQueue<T> queue();
    descriptor: ()Ljava/util/concurrent/LinkedBlockingQueue;
    flags: (0x0012) ACC_PRIVATE, ACC_FINAL
    Code:
      stack=1, locals=1, args_size=1
         0: aload_0
         1: getfield      #18                 // Field queue:Ljava/util/concurrent/LinkedBlockingQueue;
         4: areturn
      LineNumberTable:
        line 41: 0
      LocalVariableTable:
        Start  Length  Slot  Name   Signature
            0       5     0  this   Lorg/scalatest/LinkedBlockingQueue;
    Signature: #16                          // ()Ljava/util/concurrent/LinkedBlockingQueue<TT;>;

  public void put(T);
    descriptor: (Ljava/lang/Object;)V
    flags: (0x0001) ACC_PUBLIC
    Code:
      stack=2, locals=2, args_size=2
         0: aload_0
         1: invokespecial #26                 // Method queue:()Ljava/util/concurrent/LinkedBlockingQueue;
         4: aload_1
         5: invokevirtual #30                 // Method java/util/concurrent/LinkedBlockingQueue.put:(Ljava/lang/Object;)V
         8: return
      LineNumberTable:
        line 43: 0
      LocalVariableTable:
        Start  Length  Slot  Name   Signature
            0       9     0  this   Lorg/scalatest/LinkedBlockingQueue;
            0       9     1   ele   Ljava/lang/Object;
    Signature: #23                          // (TT;)V
    MethodParameters:
      Name                           Flags
      ele                            final

  public T take();
    descriptor: ()Ljava/lang/Object;
    flags: (0x0001) ACC_PUBLIC
    Code:
      stack=1, locals=1, args_size=1
         0: aload_0
         1: invokespecial #26                 // Method queue:()Ljava/util/concurrent/LinkedBlockingQueue;
         4: invokevirtual #36                 // Method java/util/concurrent/LinkedBlockingQueue.take:()Ljava/lang/Object;
         7: areturn
      LineNumberTable:
        line 45: 0
      LocalVariableTable:
        Start  Length  Slot  Name   Signature
            0       8     0  this   Lorg/scalatest/LinkedBlockingQueue;
    Signature: #34                          // ()TT;

  public int size();
    descriptor: ()I
    flags: (0x0001) ACC_PUBLIC
    Code:
      stack=1, locals=1, args_size=1
         0: aload_0
         1: invokespecial #26                 // Method queue:()Ljava/util/concurrent/LinkedBlockingQueue;
         4: invokevirtual #40                 // Method java/util/concurrent/LinkedBlockingQueue.size:()I
         7: ireturn
      LineNumberTable:
        line 47: 0
      LocalVariableTable:
        Start  Length  Slot  Name   Signature
            0       8     0  this   Lorg/scalatest/LinkedBlockingQueue;

  public org.scalatest.LinkedBlockingQueue();
    descriptor: ()V
    flags: (0x0001) ACC_PUBLIC
    Code:
      stack=3, locals=1, args_size=1
         0: aload_0
         1: invokespecial #44                 // Method java/lang/Object."<init>":()V
         4: aload_0
         5: new           #28                 // class java/util/concurrent/LinkedBlockingQueue
         8: dup
         9: invokespecial #45                 // Method java/util/concurrent/LinkedBlockingQueue."<init>":()V
        12: putfield      #18                 // Field queue:Ljava/util/concurrent/LinkedBlockingQueue;
        15: return
      LineNumberTable:
        line 39: 0
        line 41: 4
        line 39: 15
      LocalVariableTable:
        Start  Length  Slot  Name   Signature
            0      16     0  this   Lorg/scalatest/LinkedBlockingQueue;
}
Signature: #3                           // <T:Ljava/lang/Object;>Ljava/lang/Object;Ljava/io/Serializable;
SourceFile: "JavaClassesWrappers.scala"
RuntimeVisibleAnnotations:
  0: #9(#10=s#11)
    scala.reflect.ScalaSignature(
      bytes="\u0006\u0005)3Qa\u0002\u0005\u0001\u00111AQ!\t\u0001\u0005\u0002\tBq\u0001\r\u0001C\u0002\u00135\u0011\u0007\u0003\u0004<\u0001\u0001\u0006iA\r\u0005\u0006y\u0001!\t!\u0010\u0005\u0006\u0007\u0002!\t\u0001\u0012\u0005\u0006\u000b\u0002!\tA\u0012\u0002\u0014\u0019&t7.\u001a3CY>\u001c7.\u001b8h#V,W/\u001a\u0006\u0003\u0013)\t\u0011b]2bY\u0006$Xm\u001d;\u000b\u0003-\t1a\u001c:h+\tiqeE\u0002\u0001\u001dQ\u0001\"a\u0004\n\u000e\u0003AQ\u0011!E\u0001\u0006g\u000e\fG.Y\u0005\u0003\'A\u0011a!\u00118z%\u00164\u0007CA\u000b\u001f\u001d\t1BD\u0004\u0002\u001875\t\u0001D\u0003\u0002\u001a5\u00051AH]8piz\u001a\u0001!C\u0001\u0012\u0013\ti\u0002#A\u0004qC\u000e\\\u0017mZ3\n\u0005}\u0001#\u0001D*fe&\fG.\u001b>bE2,\'BA\u000f\u0011\u0003\u0019a\u0014N\\5u}Q\t1\u0005E\u0002%\u0001\u0015j\u0011\u0001\u0003\t\u0003M\u001db\u0001\u0001B\u0003)\u0001\t\u0007\u0011FA\u0001U#\tQS\u0006\u0005\u0002\u0010W%\u0011A\u0006\u0005\u0002\b\u001d>$\b.\u001b8h!\tya&\u0003\u00020!\t\u0019\u0011I\\=\u0002\u000bE,X-^3\u0016\u0003I\u00022a\r\u001e&\u001b\u0005!$BA\u001b7\u0003)\u0019wN\\2veJ,g\u000e\u001e\u0006\u0003oa\nA!\u001e;jY*\t\u0011(\u0001\u0003kCZ\f\u0017BA\u00045\u0003\u0019\tX/Z;fA\u0005\u0019\u0001/\u001e;\u0015\u0005y\n\u0005CA\b@\u0013\t\u0001\u0005C\u0001\u0003V]&$\b\"\u0002\"\u0005\u0001\u0004)\u0013aA3mK\u0006!A/Y6f)\u0005)\u0013\u0001B:ju\u0016,\u0012a\u0012\t\u0003\u001f!K!!\u0013\t\u0003\u0007%sG\u000f"
    )
  ScalaInlineInfo: length = 0x1D (unknown attribute)
   01 00 00 05 00 29 00 2A 00 00 15 00 16 00 00 0C
   00 0F 01 00 25 00 26 00 00 20 00 21 00
  ScalaSig: length = 0x3 (unknown attribute)
   05 02 00
