Classfile /Users/mw/Projects/slang-braindump/.jar/jar11/assemble/slang-braindump/assemble/content/org/scalatest/MessageRecordingInformer.class
  Last modified May 29, 2022; size 2945 bytes
  SHA-256 checksum c3ccfb949cc9b645ccc76d2e8cbeac308ec29d39def0b93e0254575a1bcc87bb
  Compiled from "ConcurrentInformer.scala"
public class org.scalatest.MessageRecordingInformer implements org.scalatest.Informer
  minor version: 0
  major version: 52
  flags: (0x0021) ACC_PUBLIC, ACC_SUPER
  this_class: #2                          // org/scalatest/MessageRecordingInformer
  super_class: #4                         // java/lang/Object
  interfaces: 1, fields: 2, methods: 3, attributes: 4
Constant pool:
   #1 = Utf8               org/scalatest/MessageRecordingInformer
   #2 = Class              #1             // org/scalatest/MessageRecordingInformer
   #3 = Utf8               java/lang/Object
   #4 = Class              #3             // java/lang/Object
   #5 = Utf8               org/scalatest/Informer
   #6 = Class              #5             // org/scalatest/Informer
   #7 = Utf8               ConcurrentInformer.scala
   #8 = Utf8               Lscala/reflect/ScalaSignature;
   #9 = Utf8               bytes
  #10 = Utf8               \u0006\u0005]3Q!\u0003\u0006\u0001\u00159A\u0001\"\u0007\u0001\u0003\u0002\u0003\u0006Ia\u0007\u0005\t=\u0001\u0011\t\u0011)A\u0005?!)a\u0005\u0001C\u0001O!)1\u0006\u0001C\u0001Y\u001d1\u0001K\u0003E\u0001\u0015E3a!\u0003\u0006\t\u0002)\u0011\u0006\"\u0002\u0014\u0007\t\u0003\u0019\u0006\"B\u0016\u0007\t\u0003!&\u0001G\'fgN\fw-\u001a*fG>\u0014H-\u001b8h\u0013:4wN]7fe*\u00111\u0002D\u0001\ng\u000e\fG.\u0019;fgRT\u0011!D\u0001\u0004_J<7c\u0001\u0001\u0010+A\u0011\u0001cE\u0007\u0002#)\t!#A\u0003tG\u0006d\u0017-\u0003\u0002\u0015#\t1\u0011I\\=SK\u001a\u0004\"AF\f\u000e\u0003)I!\u0001\u0007\u0006\u0003\u0011%sgm\u001c:nKJ\f\u0001B]3d_J$WM]\u0002\u0001!\t1B$\u0003\u0002\u001e\u0015\tyQ*Z:tC\u001e,\'+Z2pe\u0012,\'/\u0001\u0005fm\u0016tGOR;o!\t\u00013E\u0004\u0002\u0017C%\u0011!EC\u0001\u0010\u001b\u0016\u001c8/Y4f%\u0016\u001cwN\u001d3fe&\u0011A%\n\u0002\u0018%\u0016\u001cwN\u001d3fI6+7o]1hK\u00163XM\u001c;Gk:T!A\t\u0006\u0002\rqJg.\u001b;?)\rA\u0013F\u000b\t\u0003-\u0001AQ!G\u0002A\u0002mAQAH\u0002A\u0002}\tQ!\u00199qYf$2!L\u001eI)\tq\u0013\u0007\u0005\u0002\u0011_%\u0011\u0001\'\u0005\u0002\u0005+:LG\u000fC\u00033\t\u0001\u000f1\'A\u0002q_N\u0004\"\u0001N\u001d\u000e\u0003UR!AN\u001c\u0002\rM|WO]2f\u0015\tAD\"A\u0005tG\u0006d\u0017m\u0019;jG&\u0011!(\u000e\u0002\t!>\u001c\u0018\u000e^5p]\")A\b\u0002a\u0001{\u00059Q.Z:tC\u001e,\u0007C\u0001 F\u001d\ty4\t\u0005\u0002A#5\t\u0011I\u0003\u0002C5\u00051AH]8pizJ!\u0001R\t\u0002\rA\u0013X\rZ3g\u0013\t1uI\u0001\u0004TiJLgn\u001a\u0006\u0003\tFAq!\u0013\u0003\u0011\u0002\u0003\u0007!*A\u0004qCfdw.\u00193\u0011\u0007AYU*\u0003\u0002M#\t1q\n\u001d;j_:\u0004\"\u0001\u0005(\n\u0005=\u000b\"aA!os\u0006AR*Z:tC\u001e,\'+Z2pe\u0012LgnZ%oM>\u0014X.\u001a:\u0011\u0005Y11C\u0001\u0004\u0010)\u0005\tFc\u0001\u0015V-\")\u0011\u0004\u0003a\u00017!)a\u0004\u0003a\u0001?\u0001
  #11 = Utf8               recorder
  #12 = Utf8               Lorg/scalatest/MessageRecorder;
  #13 = Utf8               eventFun
  #14 = Utf8               Lscala/Function6;
  #15 = Utf8               Lscala/Function6<Ljava/lang/String;Lscala/Option<Ljava/lang/Object;>;Ljava/lang/Object;Ljava/lang/Object;Ljava/lang/Object;Lscala/Option<Lorg/scalatest/events/Location;>;Lorg/scalatest/events/RecordableEvent;>;
  #16 = Utf8               apply$default$2
  #17 = Utf8               ()Lscala/Option;
  #18 = Utf8               ()Lscala/Option<Ljava/lang/Object;>;
  #19 = Utf8               apply$default$2$
  #20 = Utf8               (Lorg/scalatest/Informer;)Lscala/Option;
  #21 = NameAndType        #19:#20        // apply$default$2$:(Lorg/scalatest/Informer;)Lscala/Option;
  #22 = InterfaceMethodref #6.#21         // org/scalatest/Informer.apply$default$2$:(Lorg/scalatest/Informer;)Lscala/Option;
  #23 = Utf8               this
  #24 = Utf8               Lorg/scalatest/MessageRecordingInformer;
  #25 = Utf8               apply
  #26 = Utf8               (Ljava/lang/String;Lscala/Option;Lorg/scalactic/source/Position;)V
  #27 = Utf8               (Ljava/lang/String;Lscala/Option<Ljava/lang/Object;>;Lorg/scalactic/source/Position;)V
  #28 = Utf8               message
  #29 = Utf8               payload
  #30 = Utf8               pos
  #31 = NameAndType        #11:#12        // recorder:Lorg/scalatest/MessageRecorder;
  #32 = Fieldref           #2.#31         // org/scalatest/MessageRecordingInformer.recorder:Lorg/scalatest/MessageRecorder;
  #33 = NameAndType        #13:#14        // eventFun:Lscala/Function6;
  #34 = Fieldref           #2.#33         // org/scalatest/MessageRecordingInformer.eventFun:Lscala/Function6;
  #35 = Utf8               scala/Some
  #36 = Class              #35            // scala/Some
  #37 = Utf8               org/scalatest/events/LineInFile
  #38 = Class              #37            // org/scalatest/events/LineInFile
  #39 = Utf8               org/scalactic/source/Position
  #40 = Class              #39            // org/scalactic/source/Position
  #41 = Utf8               lineNumber
  #42 = Utf8               ()I
  #43 = NameAndType        #41:#42        // lineNumber:()I
  #44 = Methodref          #40.#43        // org/scalactic/source/Position.lineNumber:()I
  #45 = Utf8               fileName
  #46 = Utf8               ()Ljava/lang/String;
  #47 = NameAndType        #45:#46        // fileName:()Ljava/lang/String;
  #48 = Methodref          #40.#47        // org/scalactic/source/Position.fileName:()Ljava/lang/String;
  #49 = Utf8               filePathname
  #50 = NameAndType        #49:#46        // filePathname:()Ljava/lang/String;
  #51 = Methodref          #40.#50        // org/scalactic/source/Position.filePathname:()Ljava/lang/String;
  #52 = Utf8               <init>
  #53 = Utf8               (Ljava/lang/Object;)V
  #54 = NameAndType        #52:#53        // "<init>":(Ljava/lang/Object;)V
  #55 = Methodref          #36.#54        // scala/Some."<init>":(Ljava/lang/Object;)V
  #56 = Utf8               (ILjava/lang/String;Lscala/Option;)V
  #57 = NameAndType        #52:#56        // "<init>":(ILjava/lang/String;Lscala/Option;)V
  #58 = Methodref          #38.#57        // org/scalatest/events/LineInFile."<init>":(ILjava/lang/String;Lscala/Option;)V
  #59 = Utf8               org/scalatest/MessageRecorder
  #60 = Class              #59            // org/scalatest/MessageRecorder
  #61 = Utf8               (Ljava/lang/String;Lscala/Option;Lscala/Function6;Lscala/Option;)V
  #62 = NameAndType        #25:#61        // apply:(Ljava/lang/String;Lscala/Option;Lscala/Function6;Lscala/Option;)V
  #63 = Methodref          #60.#62        // org/scalatest/MessageRecorder.apply:(Ljava/lang/String;Lscala/Option;Lscala/Function6;Lscala/Option;)V
  #64 = Utf8               stackDepth
  #65 = Utf8               I
  #66 = Utf8               Ljava/lang/String;
  #67 = Utf8               Lscala/Option;
  #68 = Utf8               Lorg/scalactic/source/Position;
  #69 = Utf8               (Lorg/scalatest/MessageRecorder;Lscala/Function6;)V
  #70 = Utf8               (Lorg/scalatest/MessageRecorder;Lscala/Function6<Ljava/lang/String;Lscala/Option<Ljava/lang/Object;>;Ljava/lang/Object;Ljava/lang/Object;Ljava/lang/Object;Lscala/Option<Lorg/scalatest/events/Location;>;Lorg/scalatest/events/RecordableEvent;>;)V
  #71 = Utf8               ()V
  #72 = NameAndType        #52:#71        // "<init>":()V
  #73 = Methodref          #4.#72         // java/lang/Object."<init>":()V
  #74 = Utf8               Signature
  #75 = Utf8               Code
  #76 = Utf8               LineNumberTable
  #77 = Utf8               LocalVariableTable
  #78 = Utf8               MethodParameters
  #79 = Utf8               SourceFile
  #80 = Utf8               RuntimeVisibleAnnotations
  #81 = Utf8               ScalaInlineInfo
  #82 = Utf8               ScalaSig
{
  private final org.scalatest.MessageRecorder recorder;
    descriptor: Lorg/scalatest/MessageRecorder;
    flags: (0x0012) ACC_PRIVATE, ACC_FINAL

  private final scala.Function6<java.lang.String, scala.Option<java.lang.Object>, java.lang.Object, java.lang.Object, java.lang.Object, scala.Option<org.scalatest.events.Location>, org.scalatest.events.RecordableEvent> eventFun;
    descriptor: Lscala/Function6;
    flags: (0x0012) ACC_PRIVATE, ACC_FINAL
    Signature: #15                          // Lscala/Function6<Ljava/lang/String;Lscala/Option<Ljava/lang/Object;>;Ljava/lang/Object;Ljava/lang/Object;Ljava/lang/Object;Lscala/Option<Lorg/scalatest/events/Location;>;Lorg/scalatest/events/RecordableEvent;>;

  public scala.Option<java.lang.Object> apply$default$2();
    descriptor: ()Lscala/Option;
    flags: (0x0001) ACC_PUBLIC
    Code:
      stack=1, locals=1, args_size=1
         0: aload_0
         1: invokestatic  #22                 // InterfaceMethod org/scalatest/Informer.apply$default$2$:(Lorg/scalatest/Informer;)Lscala/Option;
         4: areturn
      LineNumberTable:
        line 155: 0
      LocalVariableTable:
        Start  Length  Slot  Name   Signature
            0       5     0  this   Lorg/scalatest/MessageRecordingInformer;
    Signature: #18                          // ()Lscala/Option<Ljava/lang/Object;>;

  public void apply(java.lang.String, scala.Option<java.lang.Object>, org.scalactic.source.Position);
    descriptor: (Ljava/lang/String;Lscala/Option;Lorg/scalactic/source/Position;)V
    flags: (0x0001) ACC_PUBLIC
    Code:
      stack=13, locals=5, args_size=4
         0: iconst_2
         1: istore        4
         3: aload_0
         4: getfield      #32                 // Field recorder:Lorg/scalatest/MessageRecorder;
         7: aload_1
         8: aload_2
         9: aload_0
        10: getfield      #34                 // Field eventFun:Lscala/Function6;
        13: new           #36                 // class scala/Some
        16: dup
        17: new           #38                 // class org/scalatest/events/LineInFile
        20: dup
        21: aload_3
        22: invokevirtual #44                 // Method org/scalactic/source/Position.lineNumber:()I
        25: aload_3
        26: invokevirtual #48                 // Method org/scalactic/source/Position.fileName:()Ljava/lang/String;
        29: new           #36                 // class scala/Some
        32: dup
        33: aload_3
        34: invokevirtual #51                 // Method org/scalactic/source/Position.filePathname:()Ljava/lang/String;
        37: invokespecial #55                 // Method scala/Some."<init>":(Ljava/lang/Object;)V
        40: invokespecial #58                 // Method org/scalatest/events/LineInFile."<init>":(ILjava/lang/String;Lscala/Option;)V
        43: invokespecial #55                 // Method scala/Some."<init>":(Ljava/lang/Object;)V
        46: invokevirtual #63                 // Method org/scalatest/MessageRecorder.apply:(Ljava/lang/String;Lscala/Option;Lscala/Function6;Lscala/Option;)V
        49: return
      LineNumberTable:
        line 158: 0
        line 161: 3
      LocalVariableTable:
        Start  Length  Slot  Name   Signature
            3      46     4 stackDepth   I
            0      50     0  this   Lorg/scalatest/MessageRecordingInformer;
            0      50     1 message   Ljava/lang/String;
            0      50     2 payload   Lscala/Option;
            0      50     3   pos   Lorg/scalactic/source/Position;
    Signature: #27                          // (Ljava/lang/String;Lscala/Option<Ljava/lang/Object;>;Lorg/scalactic/source/Position;)V
    MethodParameters:
      Name                           Flags
      message                        final
      payload                        final
      pos                            final

  public org.scalatest.MessageRecordingInformer(org.scalatest.MessageRecorder, scala.Function6<java.lang.String, scala.Option<java.lang.Object>, java.lang.Object, java.lang.Object, java.lang.Object, scala.Option<org.scalatest.events.Location>, org.scalatest.events.RecordableEvent>);
    descriptor: (Lorg/scalatest/MessageRecorder;Lscala/Function6;)V
    flags: (0x0001) ACC_PUBLIC
    Code:
      stack=2, locals=3, args_size=3
         0: aload_0
         1: aload_1
         2: putfield      #32                 // Field recorder:Lorg/scalatest/MessageRecorder;
         5: aload_0
         6: aload_2
         7: putfield      #34                 // Field eventFun:Lscala/Function6;
        10: aload_0
        11: invokespecial #73                 // Method java/lang/Object."<init>":()V
        14: return
      LineNumberTable:
        line 155: 0
      LocalVariableTable:
        Start  Length  Slot  Name   Signature
            0      15     0  this   Lorg/scalatest/MessageRecordingInformer;
            0      15     1 recorder   Lorg/scalatest/MessageRecorder;
            0      15     2 eventFun   Lscala/Function6;
    Signature: #70                          // (Lorg/scalatest/MessageRecorder;Lscala/Function6<Ljava/lang/String;Lscala/Option<Ljava/lang/Object;>;Ljava/lang/Object;Ljava/lang/Object;Ljava/lang/Object;Lscala/Option<Lorg/scalatest/events/Location;>;Lorg/scalatest/events/RecordableEvent;>;)V
    MethodParameters:
      Name                           Flags
      recorder                       final
      eventFun                       final
}
SourceFile: "ConcurrentInformer.scala"
RuntimeVisibleAnnotations:
  0: #8(#9=s#10)
    scala.reflect.ScalaSignature(
      bytes="\u0006\u0005]3Q!\u0003\u0006\u0001\u00159A\u0001\"\u0007\u0001\u0003\u0002\u0003\u0006Ia\u0007\u0005\t=\u0001\u0011\t\u0011)A\u0005?!)a\u0005\u0001C\u0001O!)1\u0006\u0001C\u0001Y\u001d1\u0001K\u0003E\u0001\u0015E3a!\u0003\u0006\t\u0002)\u0011\u0006\"\u0002\u0014\u0007\t\u0003\u0019\u0006\"B\u0016\u0007\t\u0003!&\u0001G\'fgN\fw-\u001a*fG>\u0014H-\u001b8h\u0013:4wN]7fe*\u00111\u0002D\u0001\ng\u000e\fG.\u0019;fgRT\u0011!D\u0001\u0004_J<7c\u0001\u0001\u0010+A\u0011\u0001cE\u0007\u0002#)\t!#A\u0003tG\u0006d\u0017-\u0003\u0002\u0015#\t1\u0011I\\=SK\u001a\u0004\"AF\f\u000e\u0003)I!\u0001\u0007\u0006\u0003\u0011%sgm\u001c:nKJ\f\u0001B]3d_J$WM]\u0002\u0001!\t1B$\u0003\u0002\u001e\u0015\tyQ*Z:tC\u001e,\'+Z2pe\u0012,\'/\u0001\u0005fm\u0016tGOR;o!\t\u00013E\u0004\u0002\u0017C%\u0011!EC\u0001\u0010\u001b\u0016\u001c8/Y4f%\u0016\u001cwN\u001d3fe&\u0011A%\n\u0002\u0018%\u0016\u001cwN\u001d3fI6+7o]1hK\u00163XM\u001c;Gk:T!A\t\u0006\u0002\rqJg.\u001b;?)\rA\u0013F\u000b\t\u0003-\u0001AQ!G\u0002A\u0002mAQAH\u0002A\u0002}\tQ!\u00199qYf$2!L\u001eI)\tq\u0013\u0007\u0005\u0002\u0011_%\u0011\u0001\'\u0005\u0002\u0005+:LG\u000fC\u00033\t\u0001\u000f1\'A\u0002q_N\u0004\"\u0001N\u001d\u000e\u0003UR!AN\u001c\u0002\rM|WO]2f\u0015\tAD\"A\u0005tG\u0006d\u0017m\u0019;jG&\u0011!(\u000e\u0002\t!>\u001c\u0018\u000e^5p]\")A\b\u0002a\u0001{\u00059Q.Z:tC\u001e,\u0007C\u0001 F\u001d\ty4\t\u0005\u0002A#5\t\u0011I\u0003\u0002C5\u00051AH]8pizJ!\u0001R\t\u0002\rA\u0013X\rZ3g\u0013\t1uI\u0001\u0004TiJLgn\u001a\u0006\u0003\tFAq!\u0013\u0003\u0011\u0002\u0003\u0007!*A\u0004qCfdw.\u00193\u0011\u0007AYU*\u0003\u0002M#\t1q\n\u001d;j_:\u0004\"\u0001\u0005(\n\u0005=\u000b\"aA!os\u0006AR*Z:tC\u001e,\'+Z2pe\u0012LgnZ%oM>\u0014X.\u001a:\u0011\u0005Y11C\u0001\u0004\u0010)\u0005\tFc\u0001\u0015V-\")\u0011\u0004\u0003a\u00017!)a\u0004\u0003a\u0001?\u0001"
    )
  ScalaInlineInfo: length = 0x13 (unknown attribute)
   01 00 00 03 00 34 00 45 00 00 19 00 1A 00 00 10
   00 11 00
  ScalaSig: length = 0x3 (unknown attribute)
   05 02 00
