Classfile /Users/mw/Projects/slang-braindump/.jar/jar11/assemble/slang-braindump/assemble/content/org/scalatest/OutcomeOf.class
  Last modified May 29, 2022; size 2177 bytes
  SHA-256 checksum 55300e08feb00d990a05111ab5b76b375570a320b049ddac6b6df4ad8302765e
  Compiled from "OutcomeOf.scala"
public interface org.scalatest.OutcomeOf
  minor version: 0
  major version: 52
  flags: (0x0601) ACC_PUBLIC, ACC_INTERFACE, ACC_ABSTRACT
  this_class: #2                          // org/scalatest/OutcomeOf
  super_class: #4                         // java/lang/Object
  interfaces: 0, fields: 0, methods: 3, attributes: 4
Constant pool:
   #1 = Utf8               org/scalatest/OutcomeOf
   #2 = Class              #1             // org/scalatest/OutcomeOf
   #3 = Utf8               java/lang/Object
   #4 = Class              #3             // java/lang/Object
   #5 = Utf8               OutcomeOf.scala
   #6 = Utf8               Lscala/reflect/ScalaSignature;
   #7 = Utf8               bytes
   #8 = Utf8               \u0006\u000512qAB\u0004\u0011\u0002\u0007\u0005A\u0002C\u0003\u0014\u0001\u0011\u0005A\u0003C\u0003\u0019\u0001\u0011\u0005\u0011dB\u0003\'\u000f!\u0005qEB\u0003\u0007\u000f!\u0005\u0001\u0006C\u0003+\t\u0011\u00051FA\u0005PkR\u001cw.\\3PM*\u0011\u0001\"C\u0001\ng\u000e\fG.\u0019;fgRT\u0011AC\u0001\u0004_J<7\u0001A\n\u0003\u00015\u0001\"AD\t\u000e\u0003=Q\u0011\u0001E\u0001\u0006g\u000e\fG.Y\u0005\u0003%=\u0011a!\u00118z%\u00164\u0017A\u0002\u0013j]&$H\u0005F\u0001\u0016!\tqa#\u0003\u0002\u0018\u001f\t!QK\\5u\u0003%yW\u000f^2p[\u0016|e\r\u0006\u0002\u001b=A\u00111\u0004H\u0007\u0002\u000f%\u0011Qd\u0002\u0002\b\u001fV$8m\\7f\u0011\u0019y\"\u0001\"a\u0001A\u0005\ta\rE\u0002\u000fC\rJ!AI\b\u0003\u0011q\u0012\u0017P\\1nKz\u0002\"A\u0004\u0013\n\u0005\u0015z!aA!os\u0006Iq*\u001e;d_6,wJ\u001a\t\u00037\u0011\u00192\u0001B\u0007*!\tY\u0002!\u0001\u0004=S:LGO\u0010\u000b\u0002O\u0001
   #9 = Utf8               outcomeOf$
  #10 = Utf8               (Lorg/scalatest/OutcomeOf;Lscala/Function0;)Lorg/scalatest/Outcome;
  #11 = Utf8               $this
  #12 = Utf8               f
  #13 = Utf8               outcomeOf
  #14 = Utf8               (Lscala/Function0;)Lorg/scalatest/Outcome;
  #15 = NameAndType        #13:#14        // outcomeOf:(Lscala/Function0;)Lorg/scalatest/Outcome;
  #16 = InterfaceMethodref #2.#15         // org/scalatest/OutcomeOf.outcomeOf:(Lscala/Function0;)Lorg/scalatest/Outcome;
  #17 = Utf8               Lorg/scalatest/OutcomeOf;
  #18 = Utf8               Lscala/Function0;
  #19 = Utf8               (Lscala/Function0<Ljava/lang/Object;>;)Lorg/scalatest/Outcome;
  #20 = Utf8               java/lang/Throwable
  #21 = Class              #20            // java/lang/Throwable
  #22 = Utf8               scala/Function0
  #23 = Class              #22            // scala/Function0
  #24 = Utf8               apply
  #25 = Utf8               ()Ljava/lang/Object;
  #26 = NameAndType        #24:#25        // apply:()Ljava/lang/Object;
  #27 = InterfaceMethodref #23.#26        // scala/Function0.apply:()Ljava/lang/Object;
  #28 = Utf8               org/scalatest/Succeeded$
  #29 = Class              #28            // org/scalatest/Succeeded$
  #30 = Utf8               MODULE$
  #31 = Utf8               Lorg/scalatest/Succeeded$;
  #32 = NameAndType        #30:#31        // MODULE$:Lorg/scalatest/Succeeded$;
  #33 = Fieldref           #29.#32        // org/scalatest/Succeeded$.MODULE$:Lorg/scalatest/Succeeded$;
  #34 = Utf8               org/scalatest/exceptions/TestCanceledException
  #35 = Class              #34            // org/scalatest/exceptions/TestCanceledException
  #36 = Utf8               org/scalatest/Canceled
  #37 = Class              #36            // org/scalatest/Canceled
  #38 = Utf8               <init>
  #39 = Utf8               (Lorg/scalatest/exceptions/TestCanceledException;)V
  #40 = NameAndType        #38:#39        // "<init>":(Lorg/scalatest/exceptions/TestCanceledException;)V
  #41 = Methodref          #37.#40        // org/scalatest/Canceled."<init>":(Lorg/scalatest/exceptions/TestCanceledException;)V
  #42 = Utf8               org/scalatest/exceptions/TestPendingException
  #43 = Class              #42            // org/scalatest/exceptions/TestPendingException
  #44 = Utf8               org/scalatest/Pending$
  #45 = Class              #44            // org/scalatest/Pending$
  #46 = Utf8               Lorg/scalatest/Pending$;
  #47 = NameAndType        #30:#46        // MODULE$:Lorg/scalatest/Pending$;
  #48 = Fieldref           #45.#47        // org/scalatest/Pending$.MODULE$:Lorg/scalatest/Pending$;
  #49 = Utf8               org/scalatest/exceptions/TestFailedException
  #50 = Class              #49            // org/scalatest/exceptions/TestFailedException
  #51 = Utf8               org/scalatest/Failed
  #52 = Class              #51            // org/scalatest/Failed
  #53 = Utf8               (Ljava/lang/Throwable;)V
  #54 = NameAndType        #38:#53        // "<init>":(Ljava/lang/Throwable;)V
  #55 = Methodref          #52.#54        // org/scalatest/Failed."<init>":(Ljava/lang/Throwable;)V
  #56 = Utf8               org/scalatest/Suite$
  #57 = Class              #56            // org/scalatest/Suite$
  #58 = Utf8               Lorg/scalatest/Suite$;
  #59 = NameAndType        #30:#58        // MODULE$:Lorg/scalatest/Suite$;
  #60 = Fieldref           #57.#59        // org/scalatest/Suite$.MODULE$:Lorg/scalatest/Suite$;
  #61 = Utf8               anExceptionThatShouldCauseAnAbort
  #62 = Utf8               (Ljava/lang/Throwable;)Z
  #63 = NameAndType        #61:#62        // anExceptionThatShouldCauseAnAbort:(Ljava/lang/Throwable;)Z
  #64 = Methodref          #57.#63        // org/scalatest/Suite$.anExceptionThatShouldCauseAnAbort:(Ljava/lang/Throwable;)Z
  #65 = Utf8               this
  #66 = Utf8               org/scalatest/Outcome
  #67 = Class              #66            // org/scalatest/Outcome
  #68 = Utf8               $init$
  #69 = Utf8               (Lorg/scalatest/OutcomeOf;)V
  #70 = Utf8               Code
  #71 = Utf8               LineNumberTable
  #72 = Utf8               LocalVariableTable
  #73 = Utf8               MethodParameters
  #74 = Utf8               StackMapTable
  #75 = Utf8               Signature
  #76 = Utf8               SourceFile
  #77 = Utf8               RuntimeVisibleAnnotations
  #78 = Utf8               ScalaInlineInfo
  #79 = Utf8               ScalaSig
{
  public static org.scalatest.Outcome outcomeOf$(org.scalatest.OutcomeOf, scala.Function0);
    descriptor: (Lorg/scalatest/OutcomeOf;Lscala/Function0;)Lorg/scalatest/Outcome;
    flags: (0x1009) ACC_PUBLIC, ACC_STATIC, ACC_SYNTHETIC
    Code:
      stack=2, locals=2, args_size=2
         0: aload_0
         1: aload_1
         2: invokespecial #16                 // InterfaceMethod outcomeOf:(Lscala/Function0;)Lorg/scalatest/Outcome;
         5: areturn
      LineNumberTable:
        line 83: 0
      LocalVariableTable:
        Start  Length  Slot  Name   Signature
            0       6     0 $this   Lorg/scalatest/OutcomeOf;
            0       6     1     f   Lscala/Function0;
    MethodParameters:
      Name                           Flags
      $this                          final synthetic
      f                              final

  public default org.scalatest.Outcome outcomeOf(scala.Function0<java.lang.Object>);
    descriptor: (Lscala/Function0;)Lorg/scalatest/Outcome;
    flags: (0x0001) ACC_PUBLIC
    Code:
      stack=3, locals=8, args_size=2
         0: aload_1
         1: invokeinterface #27,  1           // InterfaceMethod scala/Function0.apply:()Ljava/lang/Object;
         6: pop
         7: getstatic     #33                 // Field org/scalatest/Succeeded$.MODULE$:Lorg/scalatest/Succeeded$;
        10: goto          142
        13: astore_3
        14: aload_3
        15: astore        4
        17: aload         4
        19: instanceof    #35                 // class org/scalatest/exceptions/TestCanceledException
        22: ifeq          45
        25: aload         4
        27: checkcast     #35                 // class org/scalatest/exceptions/TestCanceledException
        30: astore        5
        32: new           #37                 // class org/scalatest/Canceled
        35: dup
        36: aload         5
        38: invokespecial #41                 // Method org/scalatest/Canceled."<init>":(Lorg/scalatest/exceptions/TestCanceledException;)V
        41: astore_2
        42: goto          138
        45: goto          48
        48: aload         4
        50: instanceof    #43                 // class org/scalatest/exceptions/TestPendingException
        53: ifeq          63
        56: getstatic     #48                 // Field org/scalatest/Pending$.MODULE$:Lorg/scalatest/Pending$;
        59: astore_2
        60: goto          138
        63: goto          66
        66: aload         4
        68: instanceof    #50                 // class org/scalatest/exceptions/TestFailedException
        71: ifeq          94
        74: aload         4
        76: checkcast     #50                 // class org/scalatest/exceptions/TestFailedException
        79: astore        6
        81: new           #52                 // class org/scalatest/Failed
        84: dup
        85: aload         6
        87: invokespecial #55                 // Method org/scalatest/Failed."<init>":(Ljava/lang/Throwable;)V
        90: astore_2
        91: goto          138
        94: goto          97
        97: aload         4
        99: ifnull        133
       102: aload         4
       104: astore        7
       106: getstatic     #60                 // Field org/scalatest/Suite$.MODULE$:Lorg/scalatest/Suite$;
       109: aload         7
       111: invokevirtual #64                 // Method org/scalatest/Suite$.anExceptionThatShouldCauseAnAbort:(Ljava/lang/Throwable;)Z
       114: ifne          130
       117: new           #52                 // class org/scalatest/Failed
       120: dup
       121: aload         7
       123: invokespecial #55                 // Method org/scalatest/Failed."<init>":(Ljava/lang/Throwable;)V
       126: astore_2
       127: goto          138
       130: goto          136
       133: goto          136
       136: aload_3
       137: athrow
       138: aload_2
       139: goto          142
       142: areturn
      Exception table:
         from    to  target type
             0    10    13   Class java/lang/Throwable
      StackMapTable: number_of_entries = 12
        frame_type = 77 /* same_locals_1_stack_item */
          stack = [ class java/lang/Throwable ]
        frame_type = 254 /* append */
          offset_delta = 31
          locals = [ top, class java/lang/Throwable, class java/lang/Throwable ]
        frame_type = 2 /* same */
        frame_type = 14 /* same */
        frame_type = 2 /* same */
        frame_type = 27 /* same */
        frame_type = 2 /* same */
        frame_type = 254 /* append */
          offset_delta = 32
          locals = [ top, top, class java/lang/Throwable ]
        frame_type = 248 /* chop */
          offset_delta = 2
        frame_type = 2 /* same */
        frame_type = 255 /* full_frame */
          offset_delta = 1
          locals = [ class org/scalatest/OutcomeOf, class scala/Function0, class org/scalatest/Outcome, class java/lang/Throwable, class java/lang/Throwable ]
          stack = []
        frame_type = 255 /* full_frame */
          offset_delta = 3
          locals = [ class org/scalatest/OutcomeOf, class scala/Function0 ]
          stack = [ class org/scalatest/Outcome ]
      LineNumberTable:
        line 85: 0
        line 86: 7
        line 89: 14
        line 89: 17
        line 90: 48
        line 91: 66
        line 92: 97
        line 84: 136
      LocalVariableTable:
        Start  Length  Slot  Name   Signature
            0     143     0  this   Lorg/scalatest/OutcomeOf;
            0     143     1     f   Lscala/Function0;
    Signature: #19                          // (Lscala/Function0<Ljava/lang/Object;>;)Lorg/scalatest/Outcome;
    MethodParameters:
      Name                           Flags
      f                              final

  public static void $init$(org.scalatest.OutcomeOf);
    descriptor: (Lorg/scalatest/OutcomeOf;)V
    flags: (0x0009) ACC_PUBLIC, ACC_STATIC
    Code:
      stack=0, locals=1, args_size=1
         0: return
      LineNumberTable:
        line 31: 0
      LocalVariableTable:
        Start  Length  Slot  Name   Signature
            0       1     0 $this   Lorg/scalatest/OutcomeOf;
    MethodParameters:
      Name                           Flags
      $this                          final synthetic
}
SourceFile: "OutcomeOf.scala"
RuntimeVisibleAnnotations:
  0: #6(#7=s#8)
    scala.reflect.ScalaSignature(
      bytes="\u0006\u000512qAB\u0004\u0011\u0002\u0007\u0005A\u0002C\u0003\u0014\u0001\u0011\u0005A\u0003C\u0003\u0019\u0001\u0011\u0005\u0011dB\u0003\'\u000f!\u0005qEB\u0003\u0007\u000f!\u0005\u0001\u0006C\u0003+\t\u0011\u00051FA\u0005PkR\u001cw.\\3PM*\u0011\u0001\"C\u0001\ng\u000e\fG.\u0019;fgRT\u0011AC\u0001\u0004_J<7\u0001A\n\u0003\u00015\u0001\"AD\t\u000e\u0003=Q\u0011\u0001E\u0001\u0006g\u000e\fG.Y\u0005\u0003%=\u0011a!\u00118z%\u00164\u0017A\u0002\u0013j]&$H\u0005F\u0001\u0016!\tqa#\u0003\u0002\u0018\u001f\t!QK\\5u\u0003%yW\u000f^2p[\u0016|e\r\u0006\u0002\u001b=A\u00111\u0004H\u0007\u0002\u000f%\u0011Qd\u0002\u0002\b\u001fV$8m\\7f\u0011\u0019y\"\u0001\"a\u0001A\u0005\ta\rE\u0002\u000fC\rJ!AI\b\u0003\u0011q\u0012\u0017P\\1nKz\u0002\"A\u0004\u0013\n\u0005\u0015z!aA!os\u0006Iq*\u001e;d_6,wJ\u001a\t\u00037\u0011\u00192\u0001B\u0007*!\tY\u0002!\u0001\u0004=S:LGO\u0010\u000b\u0002O\u0001"
    )
  ScalaInlineInfo: length = 0x13 (unknown attribute)
   01 00 00 03 00 44 00 45 01 00 0D 00 0E 00 00 09
   00 0A 01
  ScalaSig: length = 0x3 (unknown attribute)
   05 02 00
