Classfile /Users/mw/Projects/slang-braindump/.jar/jar11/assemble/slang-braindump/assemble/content/org/scalatest/PartialFunctionValues$.class
  Last modified May 29, 2022; size 1366 bytes
  SHA-256 checksum ab1a990e5ff24f215382b411674a998d9039347bcdc1a35e70b9c3be4f52ac95
  Compiled from "PartialFunctionValues.scala"
public final class org.scalatest.PartialFunctionValues$ implements org.scalatest.PartialFunctionValues
  minor version: 0
  major version: 52
  flags: (0x0031) ACC_PUBLIC, ACC_FINAL, ACC_SUPER
  this_class: #2                          // org/scalatest/PartialFunctionValues$
  super_class: #4                         // java/lang/Object
  interfaces: 1, fields: 1, methods: 3, attributes: 4
Constant pool:
   #1 = Utf8               org/scalatest/PartialFunctionValues$
   #2 = Class              #1             // org/scalatest/PartialFunctionValues$
   #3 = Utf8               java/lang/Object
   #4 = Class              #3             // java/lang/Object
   #5 = Utf8               org/scalatest/PartialFunctionValues
   #6 = Class              #5             // org/scalatest/PartialFunctionValues
   #7 = Utf8               PartialFunctionValues.scala
   #8 = Utf8               org/scalatest/PartialFunctionValues$Valuable
   #9 = Class              #8             // org/scalatest/PartialFunctionValues$Valuable
  #10 = Utf8               Valuable
  #11 = Utf8               MODULE$
  #12 = Utf8               Lorg/scalatest/PartialFunctionValues$;
  #13 = Utf8               <clinit>
  #14 = Utf8               ()V
  #15 = Utf8               <init>
  #16 = NameAndType        #15:#14        // "<init>":()V
  #17 = Methodref          #2.#16         // org/scalatest/PartialFunctionValues$."<init>":()V
  #18 = NameAndType        #11:#12        // MODULE$:Lorg/scalatest/PartialFunctionValues$;
  #19 = Fieldref           #2.#18         // org/scalatest/PartialFunctionValues$.MODULE$:Lorg/scalatest/PartialFunctionValues$;
  #20 = Utf8               $init$
  #21 = Utf8               (Lorg/scalatest/PartialFunctionValues;)V
  #22 = NameAndType        #20:#21        // $init$:(Lorg/scalatest/PartialFunctionValues;)V
  #23 = InterfaceMethodref #6.#22         // org/scalatest/PartialFunctionValues.$init$:(Lorg/scalatest/PartialFunctionValues;)V
  #24 = Utf8               convertPartialFunctionToValuable
  #25 = Utf8               (Lscala/PartialFunction;Lorg/scalactic/source/Position;)Lorg/scalatest/PartialFunctionValues$Valuable;
  #26 = Utf8               <A:Ljava/lang/Object;B:Ljava/lang/Object;>(Lscala/PartialFunction<TA;TB;>;Lorg/scalactic/source/Position;)Lorg/scalatest/PartialFunctionValues$Valuable<TA;TB;>;
  #27 = Utf8               pf
  #28 = Utf8               pos
  #29 = Utf8               convertPartialFunctionToValuable$
  #30 = Utf8               (Lorg/scalatest/PartialFunctionValues;Lscala/PartialFunction;Lorg/scalactic/source/Position;)Lorg/scalatest/PartialFunctionValues$Valuable;
  #31 = NameAndType        #29:#30        // convertPartialFunctionToValuable$:(Lorg/scalatest/PartialFunctionValues;Lscala/PartialFunction;Lorg/scalactic/source/Position;)Lorg/scalatest/PartialFunctionValues$Valuable;
  #32 = InterfaceMethodref #6.#31         // org/scalatest/PartialFunctionValues.convertPartialFunctionToValuable$:(Lorg/scalatest/PartialFunctionValues;Lscala/PartialFunction;Lorg/scalactic/source/Position;)Lorg/scalatest/PartialFunctionValues$Valuable;
  #33 = Utf8               this
  #34 = Utf8               Lscala/PartialFunction;
  #35 = Utf8               Lorg/scalactic/source/Position;
  #36 = Methodref          #4.#16         // java/lang/Object."<init>":()V
  #37 = Utf8               Code
  #38 = Utf8               LineNumberTable
  #39 = Utf8               LocalVariableTable
  #40 = Utf8               Signature
  #41 = Utf8               MethodParameters
  #42 = Utf8               InnerClasses
  #43 = Utf8               SourceFile
  #44 = Utf8               ScalaInlineInfo
  #45 = Utf8               Scala
{
  public static final org.scalatest.PartialFunctionValues$ MODULE$;
    descriptor: Lorg/scalatest/PartialFunctionValues$;
    flags: (0x0019) ACC_PUBLIC, ACC_STATIC, ACC_FINAL

  public static {};
    descriptor: ()V
    flags: (0x0009) ACC_PUBLIC, ACC_STATIC
    Code:
      stack=2, locals=0, args_size=0
         0: new           #2                  // class org/scalatest/PartialFunctionValues$
         3: dup
         4: invokespecial #17                 // Method "<init>":()V
         7: putstatic     #19                 // Field MODULE$:Lorg/scalatest/PartialFunctionValues$;
        10: getstatic     #19                 // Field MODULE$:Lorg/scalatest/PartialFunctionValues$;
        13: invokestatic  #23                 // InterfaceMethod org/scalatest/PartialFunctionValues.$init$:(Lorg/scalatest/PartialFunctionValues;)V
        16: return
      LineNumberTable:
        line 151: 0

  public <A extends java.lang.Object, B extends java.lang.Object> org.scalatest.PartialFunctionValues$Valuable<A, B> convertPartialFunctionToValuable(scala.PartialFunction<A, B>, org.scalactic.source.Position);
    descriptor: (Lscala/PartialFunction;Lorg/scalactic/source/Position;)Lorg/scalatest/PartialFunctionValues$Valuable;
    flags: (0x0001) ACC_PUBLIC
    Code:
      stack=3, locals=3, args_size=3
         0: aload_0
         1: aload_1
         2: aload_2
         3: invokestatic  #32                 // InterfaceMethod org/scalatest/PartialFunctionValues.convertPartialFunctionToValuable$:(Lorg/scalatest/PartialFunctionValues;Lscala/PartialFunction;Lorg/scalactic/source/Position;)Lorg/scalatest/PartialFunctionValues$Valuable;
         6: areturn
      LineNumberTable:
        line 151: 0
      LocalVariableTable:
        Start  Length  Slot  Name   Signature
            0       7     0  this   Lorg/scalatest/PartialFunctionValues$;
            0       7     1    pf   Lscala/PartialFunction;
            0       7     2   pos   Lorg/scalactic/source/Position;
    Signature: #26                          // <A:Ljava/lang/Object;B:Ljava/lang/Object;>(Lscala/PartialFunction<TA;TB;>;Lorg/scalactic/source/Position;)Lorg/scalatest/PartialFunctionValues$Valuable<TA;TB;>;
    MethodParameters:
      Name                           Flags
      pf                             final
      pos                            final

  private org.scalatest.PartialFunctionValues$();
    descriptor: ()V
    flags: (0x0002) ACC_PRIVATE
    Code:
      stack=1, locals=1, args_size=1
         0: aload_0
         1: invokespecial #36                 // Method java/lang/Object."<init>":()V
         4: return
      LineNumberTable:
        line 151: 0
      LocalVariableTable:
        Start  Length  Slot  Name   Signature
            0       5     0  this   Lorg/scalatest/PartialFunctionValues$;
}
InnerClasses:
  public #10= #9 of #6;                   // Valuable=class org/scalatest/PartialFunctionValues$Valuable of class org/scalatest/PartialFunctionValues
SourceFile: "PartialFunctionValues.scala"
  ScalaInlineInfo: length = 0xE (unknown attribute)
   01 01 00 02 00 0F 00 0E 01 00 18 00 19 01
  Scala: length = 0x0 (unknown attribute)

