Classfile /Users/mw/Projects/slang-braindump/.jar/jar11/assemble/slang-braindump/assemble/content/org/scalatest/PathMessageRecordingNotifier.class
  Last modified May 29, 2022; size 8758 bytes
  SHA-256 checksum 3cbe159b9f4cc1addd384c1198a3bb35c67dd8a811c6289b654cc4224ed9dca0
  Compiled from "ConcurrentInformer.scala"
public class org.scalatest.PathMessageRecordingNotifier extends org.scalatest.ThreadAwareness implements org.scalatest.Notifier
  minor version: 0
  major version: 52
  flags: (0x0021) ACC_PUBLIC, ACC_SUPER
  this_class: #2                          // org/scalatest/PathMessageRecordingNotifier
  super_class: #4                         // org/scalatest/ThreadAwareness
  interfaces: 1, fields: 2, methods: 8, attributes: 6
Constant pool:
    #1 = Utf8               org/scalatest/PathMessageRecordingNotifier
    #2 = Class              #1            // org/scalatest/PathMessageRecordingNotifier
    #3 = Utf8               org/scalatest/ThreadAwareness
    #4 = Class              #3            // org/scalatest/ThreadAwareness
    #5 = Utf8               org/scalatest/Notifier
    #6 = Class              #5            // org/scalatest/Notifier
    #7 = Utf8               ConcurrentInformer.scala
    #8 = Utf8               Lscala/reflect/ScalaSignature;
    #9 = Utf8               bytes
   #10 = Utf8               \u0006\u0005\u0005Mc!\u0002\b\u0010\u0001=\u0019\u0002\u0002C\u000e\u0001\u0005\u0003\u0005\u000b\u0011B\u000f\t\u000bE\u0003A\u0011\u0001*\u0006\tU\u0003\u0001A\u0016\u0005\b3\u0002\u0011\r\u0011\"\u0003[\u0011\u0019\u0001\u0007\u0001)A\u00057\")\u0011\r\u0001C\u0005E\")!\u000e\u0001C\u0001W\"9\u0011\u0010AI\u0001\n\u0003Q\bbBA\u0006\u0001\u0011\u0005\u0011QB\u0004\t\u0003\u0003z\u0001\u0012A\b\u0002D\u00199ab\u0004E\u0001\u001f\u0005\u0015\u0003BB)\f\t\u0003\ti\u0005\u0003\u0004k\u0017\u0011\u0005\u0011q\n\u0002\u001d!\u0006$\b.T3tg\u0006<WMU3d_J$\u0017N\\4O_RLg-[3s\u0015\t\u0001\u0012#A\u0005tG\u0006d\u0017\r^3ti*\t!#A\u0002pe\u001e\u001c2\u0001\u0001\u000b\u0019!\t)b#D\u0001\u0010\u0013\t9rBA\bUQJ,\u0017\rZ!xCJ,g.Z:t!\t)\u0012$\u0003\u0002\u001b\u001f\tAaj\u001c;jM&,\'/\u0001\u0005fm\u0016tGOR;o\u0007\u0001\u0001bBH\u0011$]Q\"tGO\u001f$\u0001R\u001a5*D\u0001 \u0015\u0005\u0001\u0013!B:dC2\f\u0017B\u0001\u0012 \u0005)1UO\\2uS>t\u0017\'\r\t\u0003I-r!!J\u0015\u0011\u0005\u0019zR\"A\u0014\u000b\u0005!b\u0012A\u0002\u001fs_>$h(\u0003\u0002+?\u00051\u0001K]3eK\u001aL!\u0001L\u0017\u0003\rM#(/\u001b8h\u0015\tQs\u0004E\u0002\u001f_EJ!\u0001M\u0010\u0003\r=\u0003H/[8o!\tq\"\'\u0003\u00024?\t\u0019\u0011I\\=\u0011\u0005y)\u0014B\u0001\u001c \u0005\u001d\u0011un\u001c7fC:\u0004\"!\u0006\u001d\n\u0005ez!!B*vSR,\u0007CA\u000b<\u0013\tatB\u0001\u0005SKB|\'\u000f^3s!\t)b(\u0003\u0002@\u001f\t9AK]1dW\u0016\u0014\bC\u0001\u0010B\u0013\t\u0011uDA\u0002J]R\u0004\"\u0001R%\u000e\u0003\u0015S!AR$\u0002\t1\fgn\u001a\u0006\u0002\u0011\u0006!!.\u0019<b\u0013\tQUI\u0001\u0004UQJ,\u0017\r\u001a\t\u0003\u0019>k\u0011!\u0014\u0006\u0003\u001d>\ta!\u001a<f]R\u001c\u0018B\u0001)N\u00051qu\u000e^3Qe>4\u0018\u000eZ3e\u0003\u0019a\u0014N\\5u}Q\u00111\u000b\u0016\t\u0003+\u0001AQa\u0007\u0002A\u0002u\u00111\u0001V;q!\u0019qrk\t\u0018Di%\u0011\u0001l\b\u0002\u0007)V\u0004H.\u001a\u001b\u0002\u00115,7o]1hKN,\u0012a\u0017\t\u0004+qs\u0016BA/\u0010\u0005U\u0019uN\\2veJ,g\u000e\u001e\'j].,G-U;fk\u0016\u0004\"aX\u0002\u000e\u0003\u0001\t\u0011\"\\3tg\u0006<Wm\u001d\u0011\u0002\rI,7m\u001c:e)\r\u0019g\r\u001b\t\u0003=\u0011L!!Z\u0010\u0003\tUs\u0017\u000e\u001e\u0005\u0006O\u001a\u0001\raI\u0001\b[\u0016\u001c8/Y4f\u0011\u0015Ig\u00011\u0001/\u0003\u001d\u0001\u0018-\u001f7pC\u0012\fQ!\u00199qYf$2\u0001\\<y)\t\u0019W\u000eC\u0003o\u000f\u0001\u000fq.A\u0002q_N\u0004\"\u0001];\u000e\u0003ET!A]:\u0002\rM|WO]2f\u0015\t!\u0018#A\u0005tG\u0006d\u0017m\u0019;jG&\u0011a/\u001d\u0002\t!>\u001c\u0018\u000e^5p]\")qm\u0002a\u0001G!9\u0011n\u0002I\u0001\u0002\u0004q\u0013aD1qa2LH\u0005Z3gCVdG\u000f\n\u001a\u0016\u0003mT#A\f?,\u0003u\u00042A`A\u0004\u001b\u0005y(\u0002BA\u0001\u0003\u0007\t\u0011\"\u001e8dQ\u0016\u001c7.\u001a3\u000b\u0007\u0005\u0015q$\u0001\u0006b]:|G/\u0019;j_:L1!!\u0003\u0000\u0005E)hn\u00195fG.,GMV1sS\u0006t7-Z\u0001\u000fe\u0016\u001cwN\u001d3fI\u00163XM\u001c;t)A\ty!!\n\u0002*\u00055\u0012\u0011GA\u001b\u0003s\ti\u0004\u0005\u0004\u0002\u0012\u0005m\u0011qD\u0007\u0003\u0003\'QA!!\u0006\u0002\u0018\u0005I\u0011.\\7vi\u0006\u0014G.\u001a\u0006\u0004\u00033y\u0012AC2pY2,7\r^5p]&!\u0011QDA\n\u0005)Ie\u000eZ3yK\u0012\u001cV-\u001d\t\u0004\u0019\u0006\u0005\u0012bAA\u0012\u001b\n\tbj\u001c;jM&\u001c\u0017\r^5p]\u00163XM\u001c;\t\r\u0005\u001d\u0012\u00021\u00015\u00039!Xm\u001d;XCN\u0004VM\u001c3j]\u001eDa!a\u000b\n\u0001\u00049\u0014\u0001\u0003;iKN+\u0018\u000e^3\t\r\u0005=\u0012\u00021\u0001;\u0003\u0019\u0011X\r]8si\"1\u00111G\u0005A\u0002u\nq\u0001\u001e:bG.,\'\u000f\u0003\u0004\u00028%\u0001\raI\u0001\ti\u0016\u001cHOT1nK\"1\u00111H\u0005A\u0002\u0001\u000b1\"\u001b8eK:$\u0018\r^5p]\"1\u0011qH\u0005A\u0002Q\n1\"\u001b8dYV$W-S2p]\u0006a\u0002+\u0019;i\u001b\u0016\u001c8/Y4f%\u0016\u001cwN\u001d3j]\u001etu\u000e^5gS\u0016\u0014\bCA\u000b\f\'\rY\u0011q\t\t\u0004=\u0005%\u0013bAA&?\t1\u0011I\\=SK\u001a$\"!a\u0011\u0015\u0007M\u000b\t\u0006C\u0003\u001c\u001b\u0001\u0007Q\u0004
   #11 = Utf8               java/lang/invoke/MethodHandles$Lookup
   #12 = Class              #11           // java/lang/invoke/MethodHandles$Lookup
   #13 = Utf8               java/lang/invoke/MethodHandles
   #14 = Class              #13           // java/lang/invoke/MethodHandles
   #15 = Utf8               Lookup
   #16 = Utf8               org/scalactic/Requirements$RequirementsHelper
   #17 = Class              #16           // org/scalactic/Requirements$RequirementsHelper
   #18 = Utf8               org/scalactic/Requirements
   #19 = Class              #18           // org/scalactic/Requirements
   #20 = Utf8               RequirementsHelper
   #21 = Utf8               eventFun
   #22 = Utf8               Lscala/Function11;
   #23 = Utf8               Lscala/Function11<Ljava/lang/String;Lscala/Option<Ljava/lang/Object;>;Ljava/lang/Object;Ljava/lang/Object;Lorg/scalatest/Suite;Lorg/scalatest/Reporter;Lorg/scalatest/Tracker;Ljava/lang/String;Ljava/lang/Object;Ljava/lang/Object;Ljava/lang/Thread;Lorg/scalatest/events/NoteProvided;>;
   #24 = Utf8               messages
   #25 = Utf8               Lorg/scalatest/ConcurrentLinkedQueue;
   #26 = Utf8               Lorg/scalatest/ConcurrentLinkedQueue<Lscala/Tuple4<Ljava/lang/String;Lscala/Option<Ljava/lang/Object;>;Ljava/lang/Thread;Ljava/lang/Object;>;>;
   #27 = Utf8               ()Lorg/scalatest/ConcurrentLinkedQueue;
   #28 = Utf8               ()Lorg/scalatest/ConcurrentLinkedQueue<Lscala/Tuple4<Ljava/lang/String;Lscala/Option<Ljava/lang/Object;>;Ljava/lang/Thread;Ljava/lang/Object;>;>;
   #29 = NameAndType        #24:#25       // messages:Lorg/scalatest/ConcurrentLinkedQueue;
   #30 = Fieldref           #2.#29        // org/scalatest/PathMessageRecordingNotifier.messages:Lorg/scalatest/ConcurrentLinkedQueue;
   #31 = Utf8               this
   #32 = Utf8               Lorg/scalatest/PathMessageRecordingNotifier;
   #33 = Utf8               record
   #34 = Utf8               (Ljava/lang/String;Lscala/Option;)V
   #35 = Utf8               (Ljava/lang/String;Lscala/Option<Ljava/lang/Object;>;)V
   #36 = Utf8               message
   #37 = Utf8               payload
   #38 = NameAndType        #24:#27       // messages:()Lorg/scalatest/ConcurrentLinkedQueue;
   #39 = Methodref          #2.#38        // org/scalatest/PathMessageRecordingNotifier.messages:()Lorg/scalatest/ConcurrentLinkedQueue;
   #40 = Utf8               scala/Tuple4
   #41 = Class              #40           // scala/Tuple4
   #42 = Utf8               java/lang/Thread
   #43 = Class              #42           // java/lang/Thread
   #44 = Utf8               currentThread
   #45 = Utf8               ()Ljava/lang/Thread;
   #46 = NameAndType        #44:#45       // currentThread:()Ljava/lang/Thread;
   #47 = Methodref          #43.#46       // java/lang/Thread.currentThread:()Ljava/lang/Thread;
   #48 = Utf8               isConstructingThread
   #49 = Utf8               ()Z
   #50 = NameAndType        #48:#49       // isConstructingThread:()Z
   #51 = Methodref          #2.#50        // org/scalatest/PathMessageRecordingNotifier.isConstructingThread:()Z
   #52 = Utf8               scala/runtime/BoxesRunTime
   #53 = Class              #52           // scala/runtime/BoxesRunTime
   #54 = Utf8               boxToBoolean
   #55 = Utf8               (Z)Ljava/lang/Boolean;
   #56 = NameAndType        #54:#55       // boxToBoolean:(Z)Ljava/lang/Boolean;
   #57 = Methodref          #53.#56       // scala/runtime/BoxesRunTime.boxToBoolean:(Z)Ljava/lang/Boolean;
   #58 = Utf8               <init>
   #59 = Utf8               (Ljava/lang/Object;Ljava/lang/Object;Ljava/lang/Object;Ljava/lang/Object;)V
   #60 = NameAndType        #58:#59       // "<init>":(Ljava/lang/Object;Ljava/lang/Object;Ljava/lang/Object;Ljava/lang/Object;)V
   #61 = Methodref          #41.#60       // scala/Tuple4."<init>":(Ljava/lang/Object;Ljava/lang/Object;Ljava/lang/Object;Ljava/lang/Object;)V
   #62 = Utf8               org/scalatest/ConcurrentLinkedQueue
   #63 = Class              #62           // org/scalatest/ConcurrentLinkedQueue
   #64 = Utf8               add
   #65 = Utf8               (Ljava/lang/Object;)V
   #66 = NameAndType        #64:#65       // add:(Ljava/lang/Object;)V
   #67 = Methodref          #63.#66       // org/scalatest/ConcurrentLinkedQueue.add:(Ljava/lang/Object;)V
   #68 = Utf8               Ljava/lang/String;
   #69 = Utf8               Lscala/Option;
   #70 = Utf8               apply
   #71 = Utf8               (Ljava/lang/String;Lscala/Option;Lorg/scalactic/source/Position;)V
   #72 = Utf8               (Ljava/lang/String;Lscala/Option<Ljava/lang/Object;>;Lorg/scalactic/source/Position;)V
   #73 = Utf8               pos
   #74 = Utf8               org/scalactic/Requirements$
   #75 = Class              #74           // org/scalactic/Requirements$
   #76 = Utf8               MODULE$
   #77 = Utf8               Lorg/scalactic/Requirements$;
   #78 = NameAndType        #76:#77       // MODULE$:Lorg/scalactic/Requirements$;
   #79 = Fieldref           #75.#78       // org/scalactic/Requirements$.MODULE$:Lorg/scalactic/Requirements$;
   #80 = Utf8               requirementsHelper
   #81 = Utf8               ()Lorg/scalactic/Requirements$RequirementsHelper;
   #82 = NameAndType        #80:#81       // requirementsHelper:()Lorg/scalactic/Requirements$RequirementsHelper;
   #83 = Methodref          #75.#82       // org/scalactic/Requirements$.requirementsHelper:()Lorg/scalactic/Requirements$RequirementsHelper;
   #84 = Utf8               java/lang/String
   #85 = Class              #84           // java/lang/String
   #86 = String             #36           // message
   #87 = String             #37           // payload
   #88 = Utf8               [Ljava/lang/Object;
   #89 = Class              #88           // "[Ljava/lang/Object;"
   #90 = Utf8               [Ljava/lang/String;
   #91 = Class              #90           // "[Ljava/lang/String;"
   #92 = Utf8               java/lang/Object
   #93 = Class              #92           // java/lang/Object
   #94 = Utf8               org/scalactic/Prettifier$
   #95 = Class              #94           // org/scalactic/Prettifier$
   #96 = Utf8               Lorg/scalactic/Prettifier$;
   #97 = NameAndType        #76:#96       // MODULE$:Lorg/scalactic/Prettifier$;
   #98 = Fieldref           #95.#97       // org/scalactic/Prettifier$.MODULE$:Lorg/scalactic/Prettifier$;
   #99 = Utf8               default
  #100 = Utf8               ()Lorg/scalactic/Prettifier;
  #101 = NameAndType        #99:#100      // default:()Lorg/scalactic/Prettifier;
  #102 = Methodref          #95.#101      // org/scalactic/Prettifier$.default:()Lorg/scalactic/Prettifier;
  #103 = Utf8               macroRequireNonNull
  #104 = Utf8               ([Ljava/lang/String;[Ljava/lang/Object;Lorg/scalactic/Prettifier;Lorg/scalactic/source/Position;)V
  #105 = NameAndType        #103:#104     // macroRequireNonNull:([Ljava/lang/String;[Ljava/lang/Object;Lorg/scalactic/Prettifier;Lorg/scalactic/source/Position;)V
  #106 = Methodref          #17.#105      // org/scalactic/Requirements$RequirementsHelper.macroRequireNonNull:([Ljava/lang/String;[Ljava/lang/Object;Lorg/scalactic/Prettifier;Lorg/scalactic/source/Position;)V
  #107 = NameAndType        #33:#34       // record:(Ljava/lang/String;Lscala/Option;)V
  #108 = Methodref          #2.#107       // org/scalatest/PathMessageRecordingNotifier.record:(Ljava/lang/String;Lscala/Option;)V
  #109 = Utf8               Lorg/scalactic/source/Position;
  #110 = Utf8               apply$default$2
  #111 = Utf8               ()Lscala/Option;
  #112 = Utf8               ()Lscala/Option<Ljava/lang/Object;>;
  #113 = Utf8               scala/None$
  #114 = Class              #113          // scala/None$
  #115 = Utf8               Lscala/None$;
  #116 = NameAndType        #76:#115      // MODULE$:Lscala/None$;
  #117 = Fieldref           #114.#116     // scala/None$.MODULE$:Lscala/None$;
  #118 = Utf8               recordedEvents
  #119 = Utf8               (ZLorg/scalatest/Suite;Lorg/scalatest/Reporter;Lorg/scalatest/Tracker;Ljava/lang/String;IZ)Lscala/collection/immutable/IndexedSeq;
  #120 = Utf8               (ZLorg/scalatest/Suite;Lorg/scalatest/Reporter;Lorg/scalatest/Tracker;Ljava/lang/String;IZ)Lscala/collection/immutable/IndexedSeq<Lorg/scalatest/events/NotificationEvent;>;
  #121 = Utf8               testWasPending
  #122 = Utf8               theSuite
  #123 = Utf8               report
  #124 = Utf8               tracker
  #125 = Utf8               testName
  #126 = Utf8               indentation
  #127 = Utf8               includeIcon
  #128 = Utf8               scala/package$
  #129 = Class              #128          // scala/package$
  #130 = Utf8               Lscala/package$;
  #131 = NameAndType        #76:#130      // MODULE$:Lscala/package$;
  #132 = Fieldref           #129.#131     // scala/package$.MODULE$:Lscala/package$;
  #133 = Utf8               Vector
  #134 = Utf8               ()Lscala/collection/immutable/Vector$;
  #135 = NameAndType        #133:#134     // Vector:()Lscala/collection/immutable/Vector$;
  #136 = Methodref          #129.#135     // scala/package$.Vector:()Lscala/collection/immutable/Vector$;
  #137 = Utf8               scala/collection/immutable/Vector$
  #138 = Class              #137          // scala/collection/immutable/Vector$
  #139 = Utf8               empty
  #140 = Utf8               ()Lscala/collection/immutable/Vector;
  #141 = NameAndType        #139:#140     // empty:()Lscala/collection/immutable/Vector;
  #142 = Methodref          #138.#141     // scala/collection/immutable/Vector$.empty:()Lscala/collection/immutable/Vector;
  #143 = Utf8               asScala
  #144 = Utf8               ()Lscala/collection/Iterable;
  #145 = NameAndType        #143:#144     // asScala:()Lscala/collection/Iterable;
  #146 = Methodref          #63.#145      // org/scalatest/ConcurrentLinkedQueue.asScala:()Lscala/collection/Iterable;
  #147 = Utf8               (Ljava/lang/Object;)Ljava/lang/Object;
  #148 = MethodType         #147          //  (Ljava/lang/Object;)Ljava/lang/Object;
  #149 = Utf8               $anonfun$recordedEvents$3
  #150 = Utf8               (Lorg/scalatest/PathMessageRecordingNotifier;ZLorg/scalatest/Suite;Lorg/scalatest/Reporter;Lorg/scalatest/Tracker;Ljava/lang/String;IZLscala/Tuple4;)Lorg/scalatest/events/NotificationEvent;
  #151 = NameAndType        #149:#150     // $anonfun$recordedEvents$3:(Lorg/scalatest/PathMessageRecordingNotifier;ZLorg/scalatest/Suite;Lorg/scalatest/Reporter;Lorg/scalatest/Tracker;Ljava/lang/String;IZLscala/Tuple4;)Lorg/scalatest/events/NotificationEvent;
  #152 = Methodref          #2.#151       // org/scalatest/PathMessageRecordingNotifier.$anonfun$recordedEvents$3:(Lorg/scalatest/PathMessageRecordingNotifier;ZLorg/scalatest/Suite;Lorg/scalatest/Reporter;Lorg/scalatest/Tracker;Ljava/lang/String;IZLscala/Tuple4;)Lorg/scalatest/events/NotificationEvent;
  #153 = MethodHandle       6:#152        // REF_invokeStatic org/scalatest/PathMessageRecordingNotifier.$anonfun$recordedEvents$3:(Lorg/scalatest/PathMessageRecordingNotifier;ZLorg/scalatest/Suite;Lorg/scalatest/Reporter;Lorg/scalatest/Tracker;Ljava/lang/String;IZLscala/Tuple4;)Lorg/scalatest/events/NotificationEvent;
  #154 = Utf8               (Lscala/Tuple4;)Lorg/scalatest/events/NotificationEvent;
  #155 = MethodType         #154          //  (Lscala/Tuple4;)Lorg/scalatest/events/NotificationEvent;
  #156 = Integer            5
  #157 = Integer            1
  #158 = Utf8               java/lang/invoke/LambdaMetafactory
  #159 = Class              #158          // java/lang/invoke/LambdaMetafactory
  #160 = Utf8               altMetafactory
  #161 = Utf8               (Ljava/lang/invoke/MethodHandles$Lookup;Ljava/lang/String;Ljava/lang/invoke/MethodType;[Ljava/lang/Object;)Ljava/lang/invoke/CallSite;
  #162 = NameAndType        #160:#161     // altMetafactory:(Ljava/lang/invoke/MethodHandles$Lookup;Ljava/lang/String;Ljava/lang/invoke/MethodType;[Ljava/lang/Object;)Ljava/lang/invoke/CallSite;
  #163 = Methodref          #159.#162     // java/lang/invoke/LambdaMetafactory.altMetafactory:(Ljava/lang/invoke/MethodHandles$Lookup;Ljava/lang/String;Ljava/lang/invoke/MethodType;[Ljava/lang/Object;)Ljava/lang/invoke/CallSite;
  #164 = MethodHandle       6:#163        // REF_invokeStatic java/lang/invoke/LambdaMetafactory.altMetafactory:(Ljava/lang/invoke/MethodHandles$Lookup;Ljava/lang/String;Ljava/lang/invoke/MethodType;[Ljava/lang/Object;)Ljava/lang/invoke/CallSite;
  #165 = Utf8               (Lorg/scalatest/PathMessageRecordingNotifier;ZLorg/scalatest/Suite;Lorg/scalatest/Reporter;Lorg/scalatest/Tracker;Ljava/lang/String;IZ)Lscala/Function1;
  #166 = NameAndType        #70:#165      // apply:(Lorg/scalatest/PathMessageRecordingNotifier;ZLorg/scalatest/Suite;Lorg/scalatest/Reporter;Lorg/scalatest/Tracker;Ljava/lang/String;IZ)Lscala/Function1;
  #167 = InvokeDynamic      #0:#166       // #0:apply:(Lorg/scalatest/PathMessageRecordingNotifier;ZLorg/scalatest/Suite;Lorg/scalatest/Reporter;Lorg/scalatest/Tracker;Ljava/lang/String;IZ)Lscala/Function1;
  #168 = Utf8               scala/collection/Iterable
  #169 = Class              #168          // scala/collection/Iterable
  #170 = Utf8               map
  #171 = Utf8               (Lscala/Function1;)Ljava/lang/Object;
  #172 = NameAndType        #170:#171     // map:(Lscala/Function1;)Ljava/lang/Object;
  #173 = InterfaceMethodref #169.#172     // scala/collection/Iterable.map:(Lscala/Function1;)Ljava/lang/Object;
  #174 = Utf8               scala/collection/IterableOnce
  #175 = Class              #174          // scala/collection/IterableOnce
  #176 = Utf8               scala/collection/immutable/Vector
  #177 = Class              #176          // scala/collection/immutable/Vector
  #178 = Utf8               $plus$plus
  #179 = Utf8               (Lscala/collection/IterableOnce;)Ljava/lang/Object;
  #180 = NameAndType        #178:#179     // $plus$plus:(Lscala/collection/IterableOnce;)Ljava/lang/Object;
  #181 = Methodref          #177.#180     // scala/collection/immutable/Vector.$plus$plus:(Lscala/collection/IterableOnce;)Ljava/lang/Object;
  #182 = Utf8               scala/collection/immutable/IndexedSeq
  #183 = Class              #182          // scala/collection/immutable/IndexedSeq
  #184 = Utf8               Z
  #185 = Utf8               Lorg/scalatest/Suite;
  #186 = Utf8               Lorg/scalatest/Reporter;
  #187 = Utf8               Lorg/scalatest/Tracker;
  #188 = Utf8               I
  #189 = Utf8               $this
  #190 = Utf8               testWasPending$3
  #191 = Utf8               theSuite$2
  #192 = Utf8               report$2
  #193 = Utf8               tracker$2
  #194 = Utf8               testName$2
  #195 = Utf8               indentation$2
  #196 = Utf8               includeIcon$2
  #197 = Utf8               x0$1
  #198 = Utf8               _1
  #199 = Utf8               ()Ljava/lang/Object;
  #200 = NameAndType        #198:#199     // _1:()Ljava/lang/Object;
  #201 = Methodref          #41.#200      // scala/Tuple4._1:()Ljava/lang/Object;
  #202 = Utf8               _2
  #203 = NameAndType        #202:#199     // _2:()Ljava/lang/Object;
  #204 = Methodref          #41.#203      // scala/Tuple4._2:()Ljava/lang/Object;
  #205 = Utf8               scala/Option
  #206 = Class              #205          // scala/Option
  #207 = Utf8               _3
  #208 = NameAndType        #207:#199     // _3:()Ljava/lang/Object;
  #209 = Methodref          #41.#208      // scala/Tuple4._3:()Ljava/lang/Object;
  #210 = Utf8               _4
  #211 = NameAndType        #210:#199     // _4:()Ljava/lang/Object;
  #212 = Methodref          #41.#211      // scala/Tuple4._4:()Ljava/lang/Object;
  #213 = Utf8               unboxToBoolean
  #214 = Utf8               (Ljava/lang/Object;)Z
  #215 = NameAndType        #213:#214     // unboxToBoolean:(Ljava/lang/Object;)Z
  #216 = Methodref          #53.#215      // scala/runtime/BoxesRunTime.unboxToBoolean:(Ljava/lang/Object;)Z
  #217 = NameAndType        #21:#22       // eventFun:Lscala/Function11;
  #218 = Fieldref           #2.#217       // org/scalatest/PathMessageRecordingNotifier.eventFun:Lscala/Function11;
  #219 = Utf8               boxToInteger
  #220 = Utf8               (I)Ljava/lang/Integer;
  #221 = NameAndType        #219:#220     // boxToInteger:(I)Ljava/lang/Integer;
  #222 = Methodref          #53.#221      // scala/runtime/BoxesRunTime.boxToInteger:(I)Ljava/lang/Integer;
  #223 = Utf8               scala/Function11
  #224 = Class              #223          // scala/Function11
  #225 = Utf8               (Ljava/lang/Object;Ljava/lang/Object;Ljava/lang/Object;Ljava/lang/Object;Ljava/lang/Object;Ljava/lang/Object;Ljava/lang/Object;Ljava/lang/Object;Ljava/lang/Object;Ljava/lang/Object;Ljava/lang/Object;)Ljava/lang/Object;
  #226 = NameAndType        #70:#225      // apply:(Ljava/lang/Object;Ljava/lang/Object;Ljava/lang/Object;Ljava/lang/Object;Ljava/lang/Object;Ljava/lang/Object;Ljava/lang/Object;Ljava/lang/Object;Ljava/lang/Object;Ljava/lang/Object;Ljava/lang/Object;)Ljava/lang/Object;
  #227 = InterfaceMethodref #224.#226     // scala/Function11.apply:(Ljava/lang/Object;Ljava/lang/Object;Ljava/lang/Object;Ljava/lang/Object;Ljava/lang/Object;Ljava/lang/Object;Ljava/lang/Object;Ljava/lang/Object;Ljava/lang/Object;Ljava/lang/Object;Ljava/lang/Object;)Ljava/lang/Object;
  #228 = Utf8               org/scalatest/events/NotificationEvent
  #229 = Class              #228          // org/scalatest/events/NotificationEvent
  #230 = Utf8               scala/MatchError
  #231 = Class              #230          // scala/MatchError
  #232 = NameAndType        #58:#65       // "<init>":(Ljava/lang/Object;)V
  #233 = Methodref          #231.#232     // scala/MatchError."<init>":(Ljava/lang/Object;)V
  #234 = Utf8               thread
  #235 = Utf8               Ljava/lang/Thread;
  #236 = Utf8               wasConstructingThread
  #237 = Utf8               Lscala/Tuple4;
  #238 = Utf8               org/scalatest/Suite
  #239 = Class              #238          // org/scalatest/Suite
  #240 = Utf8               org/scalatest/Reporter
  #241 = Class              #240          // org/scalatest/Reporter
  #242 = Utf8               org/scalatest/Tracker
  #243 = Class              #242          // org/scalatest/Tracker
  #244 = Utf8               (Lscala/Function11;)V
  #245 = Utf8               (Lscala/Function11<Ljava/lang/String;Lscala/Option<Ljava/lang/Object;>;Ljava/lang/Object;Ljava/lang/Object;Lorg/scalatest/Suite;Lorg/scalatest/Reporter;Lorg/scalatest/Tracker;Ljava/lang/String;Ljava/lang/Object;Ljava/lang/Object;Ljava/lang/Thread;Lorg/scalatest/events/NoteProvided;>;)V
  #246 = Utf8               ()V
  #247 = NameAndType        #58:#246      // "<init>":()V
  #248 = Methodref          #4.#247       // org/scalatest/ThreadAwareness."<init>":()V
  #249 = Methodref          #63.#247      // org/scalatest/ConcurrentLinkedQueue."<init>":()V
  #250 = Utf8               $deserializeLambda$
  #251 = Utf8               (Ljava/lang/invoke/SerializedLambda;)Ljava/lang/Object;
  #252 = Utf8               scala/runtime/LambdaDeserialize
  #253 = Class              #252          // scala/runtime/LambdaDeserialize
  #254 = Utf8               bootstrap
  #255 = Utf8               (Ljava/lang/invoke/MethodHandles$Lookup;Ljava/lang/String;Ljava/lang/invoke/MethodType;[Ljava/lang/invoke/MethodHandle;)Ljava/lang/invoke/CallSite;
  #256 = NameAndType        #254:#255     // bootstrap:(Ljava/lang/invoke/MethodHandles$Lookup;Ljava/lang/String;Ljava/lang/invoke/MethodType;[Ljava/lang/invoke/MethodHandle;)Ljava/lang/invoke/CallSite;
  #257 = Methodref          #253.#256     // scala/runtime/LambdaDeserialize.bootstrap:(Ljava/lang/invoke/MethodHandles$Lookup;Ljava/lang/String;Ljava/lang/invoke/MethodType;[Ljava/lang/invoke/MethodHandle;)Ljava/lang/invoke/CallSite;
  #258 = MethodHandle       6:#257        // REF_invokeStatic scala/runtime/LambdaDeserialize.bootstrap:(Ljava/lang/invoke/MethodHandles$Lookup;Ljava/lang/String;Ljava/lang/invoke/MethodType;[Ljava/lang/invoke/MethodHandle;)Ljava/lang/invoke/CallSite;
  #259 = Utf8               lambdaDeserialize
  #260 = NameAndType        #259:#251     // lambdaDeserialize:(Ljava/lang/invoke/SerializedLambda;)Ljava/lang/Object;
  #261 = InvokeDynamic      #1:#260       // #1:lambdaDeserialize:(Ljava/lang/invoke/SerializedLambda;)Ljava/lang/Object;
  #262 = Utf8               Signature
  #263 = Utf8               Code
  #264 = Utf8               LineNumberTable
  #265 = Utf8               LocalVariableTable
  #266 = Utf8               MethodParameters
  #267 = Utf8               StackMapTable
  #268 = Utf8               InnerClasses
  #269 = Utf8               SourceFile
  #270 = Utf8               RuntimeVisibleAnnotations
  #271 = Utf8               BootstrapMethods
  #272 = Utf8               ScalaInlineInfo
  #273 = Utf8               ScalaSig
{
  private final scala.Function11<java.lang.String, scala.Option<java.lang.Object>, java.lang.Object, java.lang.Object, org.scalatest.Suite, org.scalatest.Reporter, org.scalatest.Tracker, java.lang.String, java.lang.Object, java.lang.Object, java.lang.Thread, org.scalatest.events.NoteProvided> eventFun;
    descriptor: Lscala/Function11;
    flags: (0x0012) ACC_PRIVATE, ACC_FINAL
    Signature: #23                          // Lscala/Function11<Ljava/lang/String;Lscala/Option<Ljava/lang/Object;>;Ljava/lang/Object;Ljava/lang/Object;Lorg/scalatest/Suite;Lorg/scalatest/Reporter;Lorg/scalatest/Tracker;Ljava/lang/String;Ljava/lang/Object;Ljava/lang/Object;Ljava/lang/Thread;Lorg/scalatest/events/NoteProvided;>;

  private final org.scalatest.ConcurrentLinkedQueue<scala.Tuple4<java.lang.String, scala.Option<java.lang.Object>, java.lang.Thread, java.lang.Object>> messages;
    descriptor: Lorg/scalatest/ConcurrentLinkedQueue;
    flags: (0x0012) ACC_PRIVATE, ACC_FINAL
    Signature: #26                          // Lorg/scalatest/ConcurrentLinkedQueue<Lscala/Tuple4<Ljava/lang/String;Lscala/Option<Ljava/lang/Object;>;Ljava/lang/Thread;Ljava/lang/Object;>;>;

  private org.scalatest.ConcurrentLinkedQueue<scala.Tuple4<java.lang.String, scala.Option<java.lang.Object>, java.lang.Thread, java.lang.Object>> messages();
    descriptor: ()Lorg/scalatest/ConcurrentLinkedQueue;
    flags: (0x0002) ACC_PRIVATE
    Code:
      stack=1, locals=1, args_size=1
         0: aload_0
         1: getfield      #30                 // Field messages:Lorg/scalatest/ConcurrentLinkedQueue;
         4: areturn
      LineNumberTable:
        line 229: 0
      LocalVariableTable:
        Start  Length  Slot  Name   Signature
            0       5     0  this   Lorg/scalatest/PathMessageRecordingNotifier;
    Signature: #28                          // ()Lorg/scalatest/ConcurrentLinkedQueue<Lscala/Tuple4<Ljava/lang/String;Lscala/Option<Ljava/lang/Object;>;Ljava/lang/Thread;Ljava/lang/Object;>;>;

  private void record(java.lang.String, scala.Option<java.lang.Object>);
    descriptor: (Ljava/lang/String;Lscala/Option;)V
    flags: (0x0002) ACC_PRIVATE
    Code:
      stack=7, locals=3, args_size=3
         0: aload_0
         1: invokespecial #39                 // Method messages:()Lorg/scalatest/ConcurrentLinkedQueue;
         4: new           #41                 // class scala/Tuple4
         7: dup
         8: aload_1
         9: aload_2
        10: invokestatic  #47                 // Method java/lang/Thread.currentThread:()Ljava/lang/Thread;
        13: aload_0
        14: invokevirtual #51                 // Method isConstructingThread:()Z
        17: invokestatic  #57                 // Method scala/runtime/BoxesRunTime.boxToBoolean:(Z)Ljava/lang/Boolean;
        20: invokespecial #61                 // Method scala/Tuple4."<init>":(Ljava/lang/Object;Ljava/lang/Object;Ljava/lang/Object;Ljava/lang/Object;)V
        23: invokevirtual #67                 // Method org/scalatest/ConcurrentLinkedQueue.add:(Ljava/lang/Object;)V
        26: return
      LineNumberTable:
        line 236: 0
      LocalVariableTable:
        Start  Length  Slot  Name   Signature
            0      27     0  this   Lorg/scalatest/PathMessageRecordingNotifier;
            0      27     1 message   Ljava/lang/String;
            0      27     2 payload   Lscala/Option;
    Signature: #35                          // (Ljava/lang/String;Lscala/Option<Ljava/lang/Object;>;)V
    MethodParameters:
      Name                           Flags
      message                        final
      payload                        final

  public void apply(java.lang.String, scala.Option<java.lang.Object>, org.scalactic.source.Position);
    descriptor: (Ljava/lang/String;Lscala/Option;Lorg/scalactic/source/Position;)V
    flags: (0x0001) ACC_PUBLIC
    Code:
      stack=6, locals=4, args_size=4
         0: getstatic     #79                 // Field org/scalactic/Requirements$.MODULE$:Lorg/scalactic/Requirements$;
         3: invokevirtual #83                 // Method org/scalactic/Requirements$.requirementsHelper:()Lorg/scalactic/Requirements$RequirementsHelper;
         6: iconst_2
         7: anewarray     #85                 // class java/lang/String
        10: dup
        11: iconst_0
        12: ldc           #86                 // String message
        14: aastore
        15: dup
        16: iconst_1
        17: ldc           #87                 // String payload
        19: aastore
        20: checkcast     #89                 // class "[Ljava/lang/Object;"
        23: checkcast     #91                 // class "[Ljava/lang/String;"
        26: iconst_2
        27: anewarray     #93                 // class java/lang/Object
        30: dup
        31: iconst_0
        32: aload_1
        33: aastore
        34: dup
        35: iconst_1
        36: aload_2
        37: aastore
        38: checkcast     #89                 // class "[Ljava/lang/Object;"
        41: getstatic     #98                 // Field org/scalactic/Prettifier$.MODULE$:Lorg/scalactic/Prettifier$;
        44: invokevirtual #102                // Method org/scalactic/Prettifier$.default:()Lorg/scalactic/Prettifier;
        47: aload_3
        48: invokevirtual #106                // Method org/scalactic/Requirements$RequirementsHelper.macroRequireNonNull:([Ljava/lang/String;[Ljava/lang/Object;Lorg/scalactic/Prettifier;Lorg/scalactic/source/Position;)V
        51: aload_0
        52: aload_1
        53: aload_2
        54: invokespecial #108                // Method record:(Ljava/lang/String;Lscala/Option;)V
        57: return
      LineNumberTable:
        line 240: 0
        line 241: 51
      LocalVariableTable:
        Start  Length  Slot  Name   Signature
            0      58     0  this   Lorg/scalatest/PathMessageRecordingNotifier;
            0      58     1 message   Ljava/lang/String;
            0      58     2 payload   Lscala/Option;
            0      58     3   pos   Lorg/scalactic/source/Position;
    Signature: #72                          // (Ljava/lang/String;Lscala/Option<Ljava/lang/Object;>;Lorg/scalactic/source/Position;)V
    MethodParameters:
      Name                           Flags
      message                        final
      payload                        final
      pos                            final

  public scala.Option<java.lang.Object> apply$default$2();
    descriptor: ()Lscala/Option;
    flags: (0x0001) ACC_PUBLIC
    Code:
      stack=1, locals=1, args_size=1
         0: getstatic     #117                // Field scala/None$.MODULE$:Lscala/None$;
         3: areturn
      LineNumberTable:
        line 239: 0
      LocalVariableTable:
        Start  Length  Slot  Name   Signature
            0       4     0  this   Lorg/scalatest/PathMessageRecordingNotifier;
    Signature: #112                         // ()Lscala/Option<Ljava/lang/Object;>;

  public scala.collection.immutable.IndexedSeq<org.scalatest.events.NotificationEvent> recordedEvents(boolean, org.scalatest.Suite, org.scalatest.Reporter, org.scalatest.Tracker, java.lang.String, int, boolean);
    descriptor: (ZLorg/scalatest/Suite;Lorg/scalatest/Reporter;Lorg/scalatest/Tracker;Ljava/lang/String;IZ)Lscala/collection/immutable/IndexedSeq;
    flags: (0x0001) ACC_PUBLIC
    Code:
      stack=10, locals=8, args_size=8
         0: getstatic     #132                // Field scala/package$.MODULE$:Lscala/package$;
         3: invokevirtual #136                // Method scala/package$.Vector:()Lscala/collection/immutable/Vector$;
         6: invokevirtual #142                // Method scala/collection/immutable/Vector$.empty:()Lscala/collection/immutable/Vector;
         9: aload_0
        10: invokespecial #39                 // Method messages:()Lorg/scalatest/ConcurrentLinkedQueue;
        13: invokevirtual #146                // Method org/scalatest/ConcurrentLinkedQueue.asScala:()Lscala/collection/Iterable;
        16: aload_0
        17: iload_1
        18: aload_2
        19: aload_3
        20: aload         4
        22: aload         5
        24: iload         6
        26: iload         7
        28: invokedynamic #167,  0            // InvokeDynamic #0:apply:(Lorg/scalatest/PathMessageRecordingNotifier;ZLorg/scalatest/Suite;Lorg/scalatest/Reporter;Lorg/scalatest/Tracker;Ljava/lang/String;IZ)Lscala/Function1;
        33: invokeinterface #173,  2          // InterfaceMethod scala/collection/Iterable.map:(Lscala/Function1;)Ljava/lang/Object;
        38: checkcast     #175                // class scala/collection/IterableOnce
        41: invokevirtual #181                // Method scala/collection/immutable/Vector.$plus$plus:(Lscala/collection/IterableOnce;)Ljava/lang/Object;
        44: checkcast     #183                // class scala/collection/immutable/IndexedSeq
        47: areturn
      LineNumberTable:
        line 245: 0
      LocalVariableTable:
        Start  Length  Slot  Name   Signature
            0      48     0  this   Lorg/scalatest/PathMessageRecordingNotifier;
            0      48     1 testWasPending   Z
            0      48     2 theSuite   Lorg/scalatest/Suite;
            0      48     3 report   Lorg/scalatest/Reporter;
            0      48     4 tracker   Lorg/scalatest/Tracker;
            0      48     5 testName   Ljava/lang/String;
            0      48     6 indentation   I
            0      48     7 includeIcon   Z
    Signature: #120                         // (ZLorg/scalatest/Suite;Lorg/scalatest/Reporter;Lorg/scalatest/Tracker;Ljava/lang/String;IZ)Lscala/collection/immutable/IndexedSeq<Lorg/scalatest/events/NotificationEvent;>;
    MethodParameters:
      Name                           Flags
      testWasPending                 final
      theSuite                       final
      report                         final
      tracker                        final
      testName                       final
      indentation                    final
      includeIcon                    final

  public static final org.scalatest.events.NotificationEvent $anonfun$recordedEvents$3(org.scalatest.PathMessageRecordingNotifier, boolean, org.scalatest.Suite, org.scalatest.Reporter, org.scalatest.Tracker, java.lang.String, int, boolean, scala.Tuple4);
    descriptor: (Lorg/scalatest/PathMessageRecordingNotifier;ZLorg/scalatest/Suite;Lorg/scalatest/Reporter;Lorg/scalatest/Tracker;Ljava/lang/String;IZLscala/Tuple4;)Lorg/scalatest/events/NotificationEvent;
    flags: (0x1019) ACC_PUBLIC, ACC_STATIC, ACC_FINAL, ACC_SYNTHETIC
    Code:
      stack=12, locals=15, args_size=9
         0: aload         8
         2: astore        10
         4: aload         10
         6: ifnull        97
         9: aload         10
        11: invokevirtual #201                // Method scala/Tuple4._1:()Ljava/lang/Object;
        14: checkcast     #85                 // class java/lang/String
        17: astore        11
        19: aload         10
        21: invokevirtual #204                // Method scala/Tuple4._2:()Ljava/lang/Object;
        24: checkcast     #206                // class scala/Option
        27: astore        12
        29: aload         10
        31: invokevirtual #209                // Method scala/Tuple4._3:()Ljava/lang/Object;
        34: checkcast     #43                 // class java/lang/Thread
        37: astore        13
        39: aload         10
        41: invokevirtual #212                // Method scala/Tuple4._4:()Ljava/lang/Object;
        44: invokestatic  #216                // Method scala/runtime/BoxesRunTime.unboxToBoolean:(Ljava/lang/Object;)Z
        47: istore        14
        49: aload_0
        50: getfield      #218                // Field eventFun:Lscala/Function11;
        53: aload         11
        55: aload         12
        57: iload         14
        59: invokestatic  #57                 // Method scala/runtime/BoxesRunTime.boxToBoolean:(Z)Ljava/lang/Boolean;
        62: iload_1
        63: invokestatic  #57                 // Method scala/runtime/BoxesRunTime.boxToBoolean:(Z)Ljava/lang/Boolean;
        66: aload_2
        67: aload_3
        68: aload         4
        70: aload         5
        72: iload         6
        74: invokestatic  #222                // Method scala/runtime/BoxesRunTime.boxToInteger:(I)Ljava/lang/Integer;
        77: iload         7
        79: invokestatic  #57                 // Method scala/runtime/BoxesRunTime.boxToBoolean:(Z)Ljava/lang/Boolean;
        82: aload         13
        84: invokeinterface #227,  12         // InterfaceMethod scala/Function11.apply:(Ljava/lang/Object;Ljava/lang/Object;Ljava/lang/Object;Ljava/lang/Object;Ljava/lang/Object;Ljava/lang/Object;Ljava/lang/Object;Ljava/lang/Object;Ljava/lang/Object;Ljava/lang/Object;Ljava/lang/Object;)Ljava/lang/Object;
        89: checkcast     #229                // class org/scalatest/events/NotificationEvent
        92: astore        9
        94: goto          110
        97: goto          100
       100: new           #231                // class scala/MatchError
       103: dup
       104: aload         10
       106: invokespecial #233                // Method scala/MatchError."<init>":(Ljava/lang/Object;)V
       109: athrow
       110: aload         9
       112: areturn
      StackMapTable: number_of_entries = 3
        frame_type = 253 /* append */
          offset_delta = 97
          locals = [ top, class scala/Tuple4 ]
        frame_type = 2 /* same */
        frame_type = 255 /* full_frame */
          offset_delta = 9
          locals = [ class org/scalatest/PathMessageRecordingNotifier, int, class org/scalatest/Suite, class org/scalatest/Reporter, class org/scalatest/Tracker, class java/lang/String, int, int, class scala/Tuple4, class org/scalatest/events/NotificationEvent, class scala/Tuple4, class java/lang/String, class scala/Option, class java/lang/Thread, int ]
          stack = []
      LineNumberTable:
        line 245: 0
        line 246: 49
        line 245: 97
      LocalVariableTable:
        Start  Length  Slot  Name   Signature
           19      78    11 message   Ljava/lang/String;
           29      68    12 payload   Lscala/Option;
           39      58    13 thread   Ljava/lang/Thread;
           49      48    14 wasConstructingThread   Z
            0     113     0 $this   Lorg/scalatest/PathMessageRecordingNotifier;
            0     113     1 testWasPending$3   Z
            0     113     2 theSuite$2   Lorg/scalatest/Suite;
            0     113     3 report$2   Lorg/scalatest/Reporter;
            0     113     4 tracker$2   Lorg/scalatest/Tracker;
            0     113     5 testName$2   Ljava/lang/String;
            0     113     6 indentation$2   I
            0     113     7 includeIcon$2   Z
            0     113     8  x0$1   Lscala/Tuple4;
    MethodParameters:
      Name                           Flags
      $this                          final synthetic
      testWasPending$3               final
      theSuite$2                     final
      report$2                       final
      tracker$2                      final
      testName$2                     final
      indentation$2                  final
      includeIcon$2                  final
      x0$1                           final

  public org.scalatest.PathMessageRecordingNotifier(scala.Function11<java.lang.String, scala.Option<java.lang.Object>, java.lang.Object, java.lang.Object, org.scalatest.Suite, org.scalatest.Reporter, org.scalatest.Tracker, java.lang.String, java.lang.Object, java.lang.Object, java.lang.Thread, org.scalatest.events.NoteProvided>);
    descriptor: (Lscala/Function11;)V
    flags: (0x0001) ACC_PUBLIC
    Code:
      stack=3, locals=2, args_size=2
         0: aload_0
         1: aload_1
         2: putfield      #218                // Field eventFun:Lscala/Function11;
         5: aload_0
         6: invokespecial #248                // Method org/scalatest/ThreadAwareness."<init>":()V
         9: aload_0
        10: new           #63                 // class org/scalatest/ConcurrentLinkedQueue
        13: dup
        14: invokespecial #249                // Method org/scalatest/ConcurrentLinkedQueue."<init>":()V
        17: putfield      #30                 // Field messages:Lorg/scalatest/ConcurrentLinkedQueue;
        20: return
      LineNumberTable:
        line 224: 0
        line 229: 9
        line 224: 20
      LocalVariableTable:
        Start  Length  Slot  Name   Signature
            0      21     0  this   Lorg/scalatest/PathMessageRecordingNotifier;
            0      21     1 eventFun   Lscala/Function11;
    Signature: #245                         // (Lscala/Function11<Ljava/lang/String;Lscala/Option<Ljava/lang/Object;>;Ljava/lang/Object;Ljava/lang/Object;Lorg/scalatest/Suite;Lorg/scalatest/Reporter;Lorg/scalatest/Tracker;Ljava/lang/String;Ljava/lang/Object;Ljava/lang/Object;Ljava/lang/Thread;Lorg/scalatest/events/NoteProvided;>;)V
    MethodParameters:
      Name                           Flags
      eventFun                       final

  private static java.lang.Object $deserializeLambda$(java.lang.invoke.SerializedLambda);
    descriptor: (Ljava/lang/invoke/SerializedLambda;)Ljava/lang/Object;
    flags: (0x100a) ACC_PRIVATE, ACC_STATIC, ACC_SYNTHETIC
    Code:
      stack=1, locals=1, args_size=1
         0: aload_0
         1: invokedynamic #261,  0            // InvokeDynamic #1:lambdaDeserialize:(Ljava/lang/invoke/SerializedLambda;)Ljava/lang/Object;
         6: areturn
}
InnerClasses:
  public static final #15= #12 of #14;    // Lookup=class java/lang/invoke/MethodHandles$Lookup of class java/lang/invoke/MethodHandles
  public static #20= #17 of #19;          // RequirementsHelper=class org/scalactic/Requirements$RequirementsHelper of class org/scalactic/Requirements
SourceFile: "ConcurrentInformer.scala"
RuntimeVisibleAnnotations:
  0: #8(#9=s#10)
    scala.reflect.ScalaSignature(
      bytes="\u0006\u0005\u0005Mc!\u0002\b\u0010\u0001=\u0019\u0002\u0002C\u000e\u0001\u0005\u0003\u0005\u000b\u0011B\u000f\t\u000bE\u0003A\u0011\u0001*\u0006\tU\u0003\u0001A\u0016\u0005\b3\u0002\u0011\r\u0011\"\u0003[\u0011\u0019\u0001\u0007\u0001)A\u00057\")\u0011\r\u0001C\u0005E\")!\u000e\u0001C\u0001W\"9\u0011\u0010AI\u0001\n\u0003Q\bbBA\u0006\u0001\u0011\u0005\u0011QB\u0004\t\u0003\u0003z\u0001\u0012A\b\u0002D\u00199ab\u0004E\u0001\u001f\u0005\u0015\u0003BB)\f\t\u0003\ti\u0005\u0003\u0004k\u0017\u0011\u0005\u0011q\n\u0002\u001d!\u0006$\b.T3tg\u0006<WMU3d_J$\u0017N\\4O_RLg-[3s\u0015\t\u0001\u0012#A\u0005tG\u0006d\u0017\r^3ti*\t!#A\u0002pe\u001e\u001c2\u0001\u0001\u000b\u0019!\t)b#D\u0001\u0010\u0013\t9rBA\bUQJ,\u0017\rZ!xCJ,g.Z:t!\t)\u0012$\u0003\u0002\u001b\u001f\tAaj\u001c;jM&,\'/\u0001\u0005fm\u0016tGOR;o\u0007\u0001\u0001bBH\u0011$]Q\"tGO\u001f$\u0001R\u001a5*D\u0001 \u0015\u0005\u0001\u0013!B:dC2\f\u0017B\u0001\u0012 \u0005)1UO\\2uS>t\u0017\'\r\t\u0003I-r!!J\u0015\u0011\u0005\u0019zR\"A\u0014\u000b\u0005!b\u0012A\u0002\u001fs_>$h(\u0003\u0002+?\u00051\u0001K]3eK\u001aL!\u0001L\u0017\u0003\rM#(/\u001b8h\u0015\tQs\u0004E\u0002\u001f_EJ!\u0001M\u0010\u0003\r=\u0003H/[8o!\tq\"\'\u0003\u00024?\t\u0019\u0011I\\=\u0011\u0005y)\u0014B\u0001\u001c \u0005\u001d\u0011un\u001c7fC:\u0004\"!\u0006\u001d\n\u0005ez!!B*vSR,\u0007CA\u000b<\u0013\tatB\u0001\u0005SKB|\'\u000f^3s!\t)b(\u0003\u0002@\u001f\t9AK]1dW\u0016\u0014\bC\u0001\u0010B\u0013\t\u0011uDA\u0002J]R\u0004\"\u0001R%\u000e\u0003\u0015S!AR$\u0002\t1\fgn\u001a\u0006\u0002\u0011\u0006!!.\u0019<b\u0013\tQUI\u0001\u0004UQJ,\u0017\r\u001a\t\u0003\u0019>k\u0011!\u0014\u0006\u0003\u001d>\ta!\u001a<f]R\u001c\u0018B\u0001)N\u00051qu\u000e^3Qe>4\u0018\u000eZ3e\u0003\u0019a\u0014N\\5u}Q\u00111\u000b\u0016\t\u0003+\u0001AQa\u0007\u0002A\u0002u\u00111\u0001V;q!\u0019qrk\t\u0018Di%\u0011\u0001l\b\u0002\u0007)V\u0004H.\u001a\u001b\u0002\u00115,7o]1hKN,\u0012a\u0017\t\u0004+qs\u0016BA/\u0010\u0005U\u0019uN\\2veJ,g\u000e\u001e\'j].,G-U;fk\u0016\u0004\"aX\u0002\u000e\u0003\u0001\t\u0011\"\\3tg\u0006<Wm\u001d\u0011\u0002\rI,7m\u001c:e)\r\u0019g\r\u001b\t\u0003=\u0011L!!Z\u0010\u0003\tUs\u0017\u000e\u001e\u0005\u0006O\u001a\u0001\raI\u0001\b[\u0016\u001c8/Y4f\u0011\u0015Ig\u00011\u0001/\u0003\u001d\u0001\u0018-\u001f7pC\u0012\fQ!\u00199qYf$2\u0001\\<y)\t\u0019W\u000eC\u0003o\u000f\u0001\u000fq.A\u0002q_N\u0004\"\u0001];\u000e\u0003ET!A]:\u0002\rM|WO]2f\u0015\t!\u0018#A\u0005tG\u0006d\u0017m\u0019;jG&\u0011a/\u001d\u0002\t!>\u001c\u0018\u000e^5p]\")qm\u0002a\u0001G!9\u0011n\u0002I\u0001\u0002\u0004q\u0013aD1qa2LH\u0005Z3gCVdG\u000f\n\u001a\u0016\u0003mT#A\f?,\u0003u\u00042A`A\u0004\u001b\u0005y(\u0002BA\u0001\u0003\u0007\t\u0011\"\u001e8dQ\u0016\u001c7.\u001a3\u000b\u0007\u0005\u0015q$\u0001\u0006b]:|G/\u0019;j_:L1!!\u0003\u0000\u0005E)hn\u00195fG.,GMV1sS\u0006t7-Z\u0001\u000fe\u0016\u001cwN\u001d3fI\u00163XM\u001c;t)A\ty!!\n\u0002*\u00055\u0012\u0011GA\u001b\u0003s\ti\u0004\u0005\u0004\u0002\u0012\u0005m\u0011qD\u0007\u0003\u0003\'QA!!\u0006\u0002\u0018\u0005I\u0011.\\7vi\u0006\u0014G.\u001a\u0006\u0004\u00033y\u0012AC2pY2,7\r^5p]&!\u0011QDA\n\u0005)Ie\u000eZ3yK\u0012\u001cV-\u001d\t\u0004\u0019\u0006\u0005\u0012bAA\u0012\u001b\n\tbj\u001c;jM&\u001c\u0017\r^5p]\u00163XM\u001c;\t\r\u0005\u001d\u0012\u00021\u00015\u00039!Xm\u001d;XCN\u0004VM\u001c3j]\u001eDa!a\u000b\n\u0001\u00049\u0014\u0001\u0003;iKN+\u0018\u000e^3\t\r\u0005=\u0012\u00021\u0001;\u0003\u0019\u0011X\r]8si\"1\u00111G\u0005A\u0002u\nq\u0001\u001e:bG.,\'\u000f\u0003\u0004\u00028%\u0001\raI\u0001\ti\u0016\u001cHOT1nK\"1\u00111H\u0005A\u0002\u0001\u000b1\"\u001b8eK:$\u0018\r^5p]\"1\u0011qH\u0005A\u0002Q\n1\"\u001b8dYV$W-S2p]\u0006a\u0002+\u0019;i\u001b\u0016\u001c8/Y4f%\u0016\u001cwN\u001d3j]\u001etu\u000e^5gS\u0016\u0014\bCA\u000b\f\'\rY\u0011q\t\t\u0004=\u0005%\u0013bAA&?\t1\u0011I\\=SK\u001a$\"!a\u0011\u0015\u0007M\u000b\t\u0006C\u0003\u001c\u001b\u0001\u0007Q\u0004"
    )
BootstrapMethods:
  0: #164 REF_invokeStatic java/lang/invoke/LambdaMetafactory.altMetafactory:(Ljava/lang/invoke/MethodHandles$Lookup;Ljava/lang/String;Ljava/lang/invoke/MethodType;[Ljava/lang/Object;)Ljava/lang/invoke/CallSite;
    Method arguments:
      #148 (Ljava/lang/Object;)Ljava/lang/Object;
      #153 REF_invokeStatic org/scalatest/PathMessageRecordingNotifier.$anonfun$recordedEvents$3:(Lorg/scalatest/PathMessageRecordingNotifier;ZLorg/scalatest/Suite;Lorg/scalatest/Reporter;Lorg/scalatest/Tracker;Ljava/lang/String;IZLscala/Tuple4;)Lorg/scalatest/events/NotificationEvent;
      #155 (Lscala/Tuple4;)Lorg/scalatest/events/NotificationEvent;
      #156 5
      #157 1
      #155 (Lscala/Tuple4;)Lorg/scalatest/events/NotificationEvent;
  1: #258 REF_invokeStatic scala/runtime/LambdaDeserialize.bootstrap:(Ljava/lang/invoke/MethodHandles$Lookup;Ljava/lang/String;Ljava/lang/invoke/MethodType;[Ljava/lang/invoke/MethodHandle;)Ljava/lang/invoke/CallSite;
    Method arguments:
      #153 REF_invokeStatic org/scalatest/PathMessageRecordingNotifier.$anonfun$recordedEvents$3:(Lorg/scalatest/PathMessageRecordingNotifier;ZLorg/scalatest/Suite;Lorg/scalatest/Reporter;Lorg/scalatest/Tracker;Ljava/lang/String;IZLscala/Tuple4;)Lorg/scalatest/events/NotificationEvent;
  ScalaInlineInfo: length = 0x27 (unknown attribute)
   01 00 00 07 00 95 00 96 01 00 3A 00 F4 00 00 46
   00 47 00 00 6E 00 6F 00 00 18 00 1B 01 00 21 00
   22 01 00 76 00 77 00
  ScalaSig: length = 0x3 (unknown attribute)
   05 02 00
