Classfile /Users/mw/Projects/slang-braindump/.jar/jar11/assemble/slang-braindump/assemble/content/org/scalatest/RandomTestOrder$TestSpecificReporter$1.class
  Last modified May 29, 2022; size 1274 bytes
  SHA-256 checksum 516a94165e6dafb60992aa07af1d8aad1efa63f0352531605bbb00fcdf2d0bb2
  Compiled from "RandomTestOrder.scala"
public class org.scalatest.RandomTestOrder$TestSpecificReporter$1 implements org.scalatest.Reporter
  minor version: 0
  major version: 52
  flags: (0x0021) ACC_PUBLIC, ACC_SUPER
  this_class: #2                          // org/scalatest/RandomTestOrder$TestSpecificReporter$1
  super_class: #4                         // java/lang/Object
  interfaces: 1, fields: 2, methods: 2, attributes: 5
Constant pool:
   #1 = Utf8               org/scalatest/RandomTestOrder$TestSpecificReporter$1
   #2 = Class              #1             // org/scalatest/RandomTestOrder$TestSpecificReporter$1
   #3 = Utf8               java/lang/Object
   #4 = Class              #3             // java/lang/Object
   #5 = Utf8               org/scalatest/Reporter
   #6 = Class              #5             // org/scalatest/Reporter
   #7 = Utf8               RandomTestOrder.scala
   #8 = Utf8               org/scalatest/RandomTestOrder
   #9 = Class              #8             // org/scalatest/RandomTestOrder
  #10 = Utf8               createTestSpecificReporter
  #11 = Utf8               (Lorg/scalatest/DistributedTestSorter;Ljava/lang/String;)Lorg/scalatest/Reporter;
  #12 = NameAndType        #10:#11        // createTestSpecificReporter:(Lorg/scalatest/DistributedTestSorter;Ljava/lang/String;)Lorg/scalatest/Reporter;
  #13 = Utf8               TestSpecificReporter$1
  #14 = Utf8               testSorter
  #15 = Utf8               Lorg/scalatest/DistributedTestSorter;
  #16 = Utf8               testName
  #17 = Utf8               Ljava/lang/String;
  #18 = Utf8               apply
  #19 = Utf8               (Lorg/scalatest/events/Event;)V
  #20 = Utf8               event
  #21 = NameAndType        #14:#15        // testSorter:Lorg/scalatest/DistributedTestSorter;
  #22 = Fieldref           #2.#21         // org/scalatest/RandomTestOrder$TestSpecificReporter$1.testSorter:Lorg/scalatest/DistributedTestSorter;
  #23 = NameAndType        #16:#17        // testName:Ljava/lang/String;
  #24 = Fieldref           #2.#23         // org/scalatest/RandomTestOrder$TestSpecificReporter$1.testName:Ljava/lang/String;
  #25 = Utf8               org/scalatest/DistributedTestSorter
  #26 = Class              #25            // org/scalatest/DistributedTestSorter
  #27 = Utf8               (Ljava/lang/String;Lorg/scalatest/events/Event;)V
  #28 = NameAndType        #18:#27        // apply:(Ljava/lang/String;Lorg/scalatest/events/Event;)V
  #29 = InterfaceMethodref #26.#28        // org/scalatest/DistributedTestSorter.apply:(Ljava/lang/String;Lorg/scalatest/events/Event;)V
  #30 = Utf8               this
  #31 = Utf8               Lorg/scalatest/RandomTestOrder$TestSpecificReporter$1;
  #32 = Utf8               Lorg/scalatest/events/Event;
  #33 = Utf8               <init>
  #34 = Utf8               (Lorg/scalatest/RandomTestOrder;Lorg/scalatest/DistributedTestSorter;Ljava/lang/String;)V
  #35 = Utf8               $outer
  #36 = Utf8               ()V
  #37 = NameAndType        #33:#36        // "<init>":()V
  #38 = Methodref          #4.#37         // java/lang/Object."<init>":()V
  #39 = Utf8               Lorg/scalatest/RandomTestOrder;
  #40 = Utf8               Code
  #41 = Utf8               LineNumberTable
  #42 = Utf8               LocalVariableTable
  #43 = Utf8               MethodParameters
  #44 = Utf8               InnerClasses
  #45 = Utf8               EnclosingMethod
  #46 = Utf8               SourceFile
  #47 = Utf8               ScalaInlineInfo
  #48 = Utf8               Scala
{
  private final org.scalatest.DistributedTestSorter testSorter;
    descriptor: Lorg/scalatest/DistributedTestSorter;
    flags: (0x0012) ACC_PRIVATE, ACC_FINAL

  private final java.lang.String testName;
    descriptor: Ljava/lang/String;
    flags: (0x0012) ACC_PRIVATE, ACC_FINAL

  public void apply(org.scalatest.events.Event);
    descriptor: (Lorg/scalatest/events/Event;)V
    flags: (0x0001) ACC_PUBLIC
    Code:
      stack=3, locals=2, args_size=2
         0: aload_0
         1: getfield      #22                 // Field testSorter:Lorg/scalatest/DistributedTestSorter;
         4: aload_0
         5: getfield      #24                 // Field testName:Ljava/lang/String;
         8: aload_1
         9: invokeinterface #29,  3           // InterfaceMethod org/scalatest/DistributedTestSorter.apply:(Ljava/lang/String;Lorg/scalatest/events/Event;)V
        14: return
      LineNumberTable:
        line 211: 0
      LocalVariableTable:
        Start  Length  Slot  Name   Signature
            0      15     0  this   Lorg/scalatest/RandomTestOrder$TestSpecificReporter$1;
            0      15     1 event   Lorg/scalatest/events/Event;
    MethodParameters:
      Name                           Flags
      event                          final

  public org.scalatest.RandomTestOrder$TestSpecificReporter$1(org.scalatest.RandomTestOrder, org.scalatest.DistributedTestSorter, java.lang.String);
    descriptor: (Lorg/scalatest/RandomTestOrder;Lorg/scalatest/DistributedTestSorter;Ljava/lang/String;)V
    flags: (0x0001) ACC_PUBLIC
    Code:
      stack=2, locals=4, args_size=4
         0: aload_0
         1: aload_2
         2: putfield      #22                 // Field testSorter:Lorg/scalatest/DistributedTestSorter;
         5: aload_0
         6: aload_3
         7: putfield      #24                 // Field testName:Ljava/lang/String;
        10: aload_0
        11: invokespecial #38                 // Method java/lang/Object."<init>":()V
        14: return
      LineNumberTable:
        line 209: 0
      LocalVariableTable:
        Start  Length  Slot  Name   Signature
            0      15     0  this   Lorg/scalatest/RandomTestOrder$TestSpecificReporter$1;
            0      15     1 $outer   Lorg/scalatest/RandomTestOrder;
            0      15     2 testSorter   Lorg/scalatest/DistributedTestSorter;
            0      15     3 testName   Ljava/lang/String;
    MethodParameters:
      Name                           Flags
      $outer                         final synthetic
      testSorter                     final
      testName                       final
}
InnerClasses:
  public #13= #2;                         // TestSpecificReporter$1=class org/scalatest/RandomTestOrder$TestSpecificReporter$1
EnclosingMethod: #9.#12                 // org.scalatest.RandomTestOrder.createTestSpecificReporter
SourceFile: "RandomTestOrder.scala"
  ScalaInlineInfo: length = 0xE (unknown attribute)
   01 01 00 02 00 21 00 22 01 00 12 00 13 01
  Scala: length = 0x0 (unknown attribute)

