Classfile /Users/mw/Projects/slang-braindump/.jar/jar11/assemble/slang-braindump/assemble/content/org/scalatest/Sequential$.class
  Last modified May 29, 2022; size 1059 bytes
  SHA-256 checksum 434db276af6bc6be313e056ea2671dcc7a7c045a88e7e565d9728f720f2c2a06
  Compiled from "Sequential.scala"
public final class org.scalatest.Sequential$ implements java.io.Serializable
  minor version: 0
  major version: 52
  flags: (0x0031) ACC_PUBLIC, ACC_FINAL, ACC_SUPER
  this_class: #2                          // org/scalatest/Sequential$
  super_class: #4                         // java/lang/Object
  interfaces: 1, fields: 1, methods: 4, attributes: 3
Constant pool:
   #1 = Utf8               org/scalatest/Sequential$
   #2 = Class              #1             // org/scalatest/Sequential$
   #3 = Utf8               java/lang/Object
   #4 = Class              #3             // java/lang/Object
   #5 = Utf8               java/io/Serializable
   #6 = Class              #5             // java/io/Serializable
   #7 = Utf8               Sequential.scala
   #8 = Utf8               MODULE$
   #9 = Utf8               Lorg/scalatest/Sequential$;
  #10 = Utf8               <clinit>
  #11 = Utf8               ()V
  #12 = Utf8               <init>
  #13 = NameAndType        #12:#11        // "<init>":()V
  #14 = Methodref          #2.#13         // org/scalatest/Sequential$."<init>":()V
  #15 = NameAndType        #8:#9          // MODULE$:Lorg/scalatest/Sequential$;
  #16 = Fieldref           #2.#15         // org/scalatest/Sequential$.MODULE$:Lorg/scalatest/Sequential$;
  #17 = Utf8               apply
  #18 = Utf8               (Lscala/collection/immutable/Seq;)Lorg/scalatest/Sequential;
  #19 = Utf8               (Lscala/collection/immutable/Seq<Lorg/scalatest/Suite;>;)Lorg/scalatest/Sequential;
  #20 = Utf8               suitesToNest
  #21 = Utf8               org/scalatest/Sequential
  #22 = Class              #21            // org/scalatest/Sequential
  #23 = Utf8               (Lscala/collection/immutable/Seq;)V
  #24 = NameAndType        #12:#23        // "<init>":(Lscala/collection/immutable/Seq;)V
  #25 = Methodref          #22.#24        // org/scalatest/Sequential."<init>":(Lscala/collection/immutable/Seq;)V
  #26 = Utf8               this
  #27 = Utf8               Lscala/collection/immutable/Seq;
  #28 = Utf8               writeReplace
  #29 = Utf8               ()Ljava/lang/Object;
  #30 = Utf8               scala/runtime/ModuleSerializationProxy
  #31 = Class              #30            // scala/runtime/ModuleSerializationProxy
  #32 = Utf8               (Ljava/lang/Class;)V
  #33 = NameAndType        #12:#32        // "<init>":(Ljava/lang/Class;)V
  #34 = Methodref          #31.#33        // scala/runtime/ModuleSerializationProxy."<init>":(Ljava/lang/Class;)V
  #35 = Methodref          #4.#13         // java/lang/Object."<init>":()V
  #36 = Utf8               Code
  #37 = Utf8               LineNumberTable
  #38 = Utf8               LocalVariableTable
  #39 = Utf8               Signature
  #40 = Utf8               MethodParameters
  #41 = Utf8               SourceFile
  #42 = Utf8               ScalaInlineInfo
  #43 = Utf8               Scala
{
  public static final org.scalatest.Sequential$ MODULE$;
    descriptor: Lorg/scalatest/Sequential$;
    flags: (0x0019) ACC_PUBLIC, ACC_STATIC, ACC_FINAL

  public static {};
    descriptor: ()V
    flags: (0x0009) ACC_PUBLIC, ACC_STATIC
    Code:
      stack=2, locals=0, args_size=0
         0: new           #2                  // class org/scalatest/Sequential$
         3: dup
         4: invokespecial #14                 // Method "<init>":()V
         7: putstatic     #16                 // Field MODULE$:Lorg/scalatest/Sequential$;
        10: return
      LineNumberTable:
        line 104: 0

  public org.scalatest.Sequential apply(scala.collection.immutable.Seq<org.scalatest.Suite>);
    descriptor: (Lscala/collection/immutable/Seq;)Lorg/scalatest/Sequential;
    flags: (0x0001) ACC_PUBLIC
    Code:
      stack=3, locals=2, args_size=2
         0: new           #22                 // class org/scalatest/Sequential
         3: dup
         4: aload_1
         5: invokespecial #25                 // Method org/scalatest/Sequential."<init>":(Lscala/collection/immutable/Seq;)V
         8: areturn
      LineNumberTable:
        line 109: 0
      LocalVariableTable:
        Start  Length  Slot  Name   Signature
            0       9     0  this   Lorg/scalatest/Sequential$;
            0       9     1 suitesToNest   Lscala/collection/immutable/Seq;
    Signature: #19                          // (Lscala/collection/immutable/Seq<Lorg/scalatest/Suite;>;)Lorg/scalatest/Sequential;
    MethodParameters:
      Name                           Flags
      suitesToNest                   final

  private java.lang.Object writeReplace();
    descriptor: ()Ljava/lang/Object;
    flags: (0x0002) ACC_PRIVATE
    Code:
      stack=3, locals=1, args_size=1
         0: new           #31                 // class scala/runtime/ModuleSerializationProxy
         3: dup
         4: ldc           #2                  // class org/scalatest/Sequential$
         6: invokespecial #34                 // Method scala/runtime/ModuleSerializationProxy."<init>":(Ljava/lang/Class;)V
         9: areturn
      LineNumberTable:
        line 104: 0
      LocalVariableTable:
        Start  Length  Slot  Name   Signature
            0      10     0  this   Lorg/scalatest/Sequential$;

  private org.scalatest.Sequential$();
    descriptor: ()V
    flags: (0x0002) ACC_PRIVATE
    Code:
      stack=1, locals=1, args_size=1
         0: aload_0
         1: invokespecial #35                 // Method java/lang/Object."<init>":()V
         4: return
      LineNumberTable:
        line 111: 0
        line 104: 4
      LocalVariableTable:
        Start  Length  Slot  Name   Signature
            0       5     0  this   Lorg/scalatest/Sequential$;
}
SourceFile: "Sequential.scala"
  ScalaInlineInfo: length = 0x13 (unknown attribute)
   01 01 00 03 00 0C 00 0B 01 00 11 00 12 01 00 1C
   00 1D 01
  Scala: length = 0x0 (unknown attribute)

