Classfile /Users/mw/Projects/slang-braindump/.jar/jar11/assemble/slang-braindump/assemble/content/org/scalatest/StreamlinedXmlNormMethods.class
  Last modified May 29, 2022; size 1561 bytes
  SHA-256 checksum 0f9bb32fb00313574772682c02ff13e5950b0854cd56ac27169396d75b85f93e
  Compiled from "StreamlinedXmlNormMethods.scala"
public interface org.scalatest.StreamlinedXmlNormMethods extends org.scalatest.StreamlinedXml,org.scalactic.NormMethods
  minor version: 0
  major version: 52
  flags: (0x0601) ACC_PUBLIC, ACC_INTERFACE, ACC_ABSTRACT
  this_class: #2                          // org/scalatest/StreamlinedXmlNormMethods
  super_class: #4                         // java/lang/Object
  interfaces: 2, fields: 0, methods: 4, attributes: 4
Constant pool:
   #1 = Utf8               org/scalatest/StreamlinedXmlNormMethods
   #2 = Class              #1             // org/scalatest/StreamlinedXmlNormMethods
   #3 = Utf8               java/lang/Object
   #4 = Class              #3             // java/lang/Object
   #5 = Utf8               org/scalatest/StreamlinedXml
   #6 = Class              #5             // org/scalatest/StreamlinedXml
   #7 = Utf8               org/scalactic/NormMethods
   #8 = Class              #7             // org/scalactic/NormMethods
   #9 = Utf8               StreamlinedXmlNormMethods.scala
  #10 = Utf8               Lscala/reflect/ScalaSignature;
  #11 = Utf8               bytes
  #12 = Utf8               \u0006\u0005\u00113qa\u0002\u0005\u0011\u0002\u0007\u0005Q\u0002C\u0003\u001f\u0001\u0011\u0005q\u0004C\u0003$\u0001\u0011\rC\u0005C\u00068\u0001A\u0005\u0019\u0011!A\u0005\najt!\u0002 \t\u0011\u0003yd!B\u0004\t\u0011\u0003\u0001\u0005\"\u0002\"\u0006\t\u0003\u0019%!G*ue\u0016\fW\u000e\\5oK\u0012DV\u000e\u001c(pe6lU\r\u001e5pINT!!\u0003\u0006\u0002\u0013M\u001c\u0017\r\\1uKN$(\"A\u0006\u0002\u0007=\u0014xm\u0001\u0001\u0014\t\u0001qA\u0003\u0007\t\u0003\u001fIi\u0011\u0001\u0005\u0006\u0002#\u0005)1oY1mC&\u00111\u0003\u0005\u0002\u0007\u0003:L(+\u001a4\u0011\u0005U1R\"\u0001\u0005\n\u0005]A!AD*ue\u0016\fW\u000e\\5oK\u0012DV\u000e\u001c\t\u00033qi\u0011A\u0007\u0006\u00037)\t\u0011b]2bY\u0006\u001cG/[2\n\u0005uQ\"a\u0003(pe6lU\r\u001e5pIN\fa\u0001J5oSR$C#\u0001\u0011\u0011\u0005=\t\u0013B\u0001\u0012\u0011\u0005\u0011)f.\u001b;\u0002\u0017M$(/Z1nY&tW\rZ\u000b\u0003K-*\u0012A\n\t\u00043\u001dJ\u0013B\u0001\u0015\u001b\u0005))f.\u001b4pe6LG/\u001f\t\u0003U-b\u0001\u0001B\u0003-\u0005\t\u0007QFA\u0001U#\tq\u0013\u0007\u0005\u0002\u0010_%\u0011\u0001\u0007\u0005\u0002\b\u001d>$\b.\u001b8h!\t\u0011T\'D\u00014\u0015\t!\u0004#A\u0002y[2L!AN\u001a\u0003\u000f9{G-Z*fc\u0006\t2/\u001e9fe\u0012\u001aHO]3b[2Lg.\u001a3\u0016\u0005ebT#\u0001\u001e\u0011\u0007e93\b\u0005\u0002+y\u0011)Af\u0001b\u0001[%\u00111EF\u0001\u001a\'R\u0014X-Y7mS:,G\rW7m\u001d>\u0014X.T3uQ>$7\u000f\u0005\u0002\u0016\u000bM\u0019QAD!\u0011\u0005U\u0001\u0011A\u0002\u001fj]&$h\bF\u0001@\u0001
  #13 = Utf8               org$scalatest$StreamlinedXmlNormMethods$$super$streamlined
  #14 = Utf8               ()Lorg/scalactic/Uniformity;
  #15 = Utf8               streamlined$
  #16 = Utf8               (Lorg/scalatest/StreamlinedXmlNormMethods;)Lorg/scalactic/Uniformity;
  #17 = Utf8               $this
  #18 = Utf8               streamlined
  #19 = NameAndType        #18:#14        // streamlined:()Lorg/scalactic/Uniformity;
  #20 = InterfaceMethodref #2.#19         // org/scalatest/StreamlinedXmlNormMethods.streamlined:()Lorg/scalactic/Uniformity;
  #21 = Utf8               Lorg/scalatest/StreamlinedXmlNormMethods;
  #22 = Utf8               <T:Lscala/xml/NodeSeq;>()Lorg/scalactic/Uniformity<TT;>;
  #23 = NameAndType        #13:#14        // org$scalatest$StreamlinedXmlNormMethods$$super$streamlined:()Lorg/scalactic/Uniformity;
  #24 = InterfaceMethodref #2.#23         // org/scalatest/StreamlinedXmlNormMethods.org$scalatest$StreamlinedXmlNormMethods$$super$streamlined:()Lorg/scalactic/Uniformity;
  #25 = Utf8               this
  #26 = Utf8               $init$
  #27 = Utf8               (Lorg/scalatest/StreamlinedXmlNormMethods;)V
  #28 = Utf8               Code
  #29 = Utf8               LineNumberTable
  #30 = Utf8               LocalVariableTable
  #31 = Utf8               MethodParameters
  #32 = Utf8               Signature
  #33 = Utf8               SourceFile
  #34 = Utf8               RuntimeVisibleAnnotations
  #35 = Utf8               ScalaInlineInfo
  #36 = Utf8               ScalaSig
{
  public abstract org.scalactic.Uniformity org$scalatest$StreamlinedXmlNormMethods$$super$streamlined();
    descriptor: ()Lorg/scalactic/Uniformity;
    flags: (0x1401) ACC_PUBLIC, ACC_ABSTRACT, ACC_SYNTHETIC

  public static org.scalactic.Uniformity streamlined$(org.scalatest.StreamlinedXmlNormMethods);
    descriptor: (Lorg/scalatest/StreamlinedXmlNormMethods;)Lorg/scalactic/Uniformity;
    flags: (0x1009) ACC_PUBLIC, ACC_STATIC, ACC_SYNTHETIC
    Code:
      stack=1, locals=1, args_size=1
         0: aload_0
         1: invokespecial #20                 // InterfaceMethod streamlined:()Lorg/scalactic/Uniformity;
         4: areturn
      LineNumberTable:
        line 70: 0
      LocalVariableTable:
        Start  Length  Slot  Name   Signature
            0       5     0 $this   Lorg/scalatest/StreamlinedXmlNormMethods;
    MethodParameters:
      Name                           Flags
      $this                          final synthetic

  public default <T extends scala.xml.NodeSeq> org.scalactic.Uniformity<T> streamlined();
    descriptor: ()Lorg/scalactic/Uniformity;
    flags: (0x0001) ACC_PUBLIC
    Code:
      stack=1, locals=1, args_size=1
         0: aload_0
         1: invokeinterface #24,  1           // InterfaceMethod org$scalatest$StreamlinedXmlNormMethods$$super$streamlined:()Lorg/scalactic/Uniformity;
         6: areturn
      LineNumberTable:
        line 70: 0
      LocalVariableTable:
        Start  Length  Slot  Name   Signature
            0       7     0  this   Lorg/scalatest/StreamlinedXmlNormMethods;
    Signature: #22                          // <T:Lscala/xml/NodeSeq;>()Lorg/scalactic/Uniformity<TT;>;

  public static void $init$(org.scalatest.StreamlinedXmlNormMethods);
    descriptor: (Lorg/scalatest/StreamlinedXmlNormMethods;)V
    flags: (0x0009) ACC_PUBLIC, ACC_STATIC
    Code:
      stack=0, locals=1, args_size=1
         0: return
      LineNumberTable:
        line 55: 0
      LocalVariableTable:
        Start  Length  Slot  Name   Signature
            0       1     0 $this   Lorg/scalatest/StreamlinedXmlNormMethods;
    MethodParameters:
      Name                           Flags
      $this                          final synthetic
}
SourceFile: "StreamlinedXmlNormMethods.scala"
RuntimeVisibleAnnotations:
  0: #10(#11=s#12)
    scala.reflect.ScalaSignature(
      bytes="\u0006\u0005\u00113qa\u0002\u0005\u0011\u0002\u0007\u0005Q\u0002C\u0003\u001f\u0001\u0011\u0005q\u0004C\u0003$\u0001\u0011\rC\u0005C\u00068\u0001A\u0005\u0019\u0011!A\u0005\najt!\u0002 \t\u0011\u0003yd!B\u0004\t\u0011\u0003\u0001\u0005\"\u0002\"\u0006\t\u0003\u0019%!G*ue\u0016\fW\u000e\\5oK\u0012DV\u000e\u001c(pe6lU\r\u001e5pINT!!\u0003\u0006\u0002\u0013M\u001c\u0017\r\\1uKN$(\"A\u0006\u0002\u0007=\u0014xm\u0001\u0001\u0014\t\u0001qA\u0003\u0007\t\u0003\u001fIi\u0011\u0001\u0005\u0006\u0002#\u0005)1oY1mC&\u00111\u0003\u0005\u0002\u0007\u0003:L(+\u001a4\u0011\u0005U1R\"\u0001\u0005\n\u0005]A!AD*ue\u0016\fW\u000e\\5oK\u0012DV\u000e\u001c\t\u00033qi\u0011A\u0007\u0006\u00037)\t\u0011b]2bY\u0006\u001cG/[2\n\u0005uQ\"a\u0003(pe6lU\r\u001e5pIN\fa\u0001J5oSR$C#\u0001\u0011\u0011\u0005=\t\u0013B\u0001\u0012\u0011\u0005\u0011)f.\u001b;\u0002\u0017M$(/Z1nY&tW\rZ\u000b\u0003K-*\u0012A\n\t\u00043\u001dJ\u0013B\u0001\u0015\u001b\u0005))f.\u001b4pe6LG/\u001f\t\u0003U-b\u0001\u0001B\u0003-\u0005\t\u0007QFA\u0001U#\tq\u0013\u0007\u0005\u0002\u0010_%\u0011\u0001\u0007\u0005\u0002\b\u001d>$\b.\u001b8h!\t\u0011T\'D\u00014\u0015\t!\u0004#A\u0002y[2L!AN\u001a\u0003\u000f9{G-Z*fc\u0006\t2/\u001e9fe\u0012\u001aHO]3b[2Lg.\u001a3\u0016\u0005ebT#\u0001\u001e\u0011\u0007e93\b\u0005\u0002+y\u0011)Af\u0001b\u0001[%\u00111EF\u0001\u001a\'R\u0014X-Y7mS:,G\rW7m\u001d>\u0014X.T3uQ>$7\u000f\u0005\u0002\u0016\u000bM\u0019QAD!\u0011\u0005U\u0001\u0011A\u0002\u001fj]&$h\bF\u0001@\u0001"
    )
  ScalaInlineInfo: length = 0x18 (unknown attribute)
   01 00 00 04 00 1A 00 1B 01 00 0D 00 0E 01 00 12
   00 0E 00 00 0F 00 10 01
  ScalaSig: length = 0x3 (unknown attribute)
   05 02 00
