Classfile /Users/mw/Projects/slang-braindump/.jar/jar11/assemble/slang-braindump/assemble/content/org/scalatest/StreamlinedXmlNormMethods$.class
  Last modified May 29, 2022; size 1899 bytes
  SHA-256 checksum b58f15a30026f20aa3ecd76593fd437ca7f783089ec1b51ccd23a2f56f518865
  Compiled from "StreamlinedXmlNormMethods.scala"
public final class org.scalatest.StreamlinedXmlNormMethods$ implements org.scalatest.StreamlinedXmlNormMethods
  minor version: 0
  major version: 52
  flags: (0x0031) ACC_PUBLIC, ACC_FINAL, ACC_SUPER
  this_class: #2                          // org/scalatest/StreamlinedXmlNormMethods$
  super_class: #4                         // java/lang/Object
  interfaces: 1, fields: 1, methods: 5, attributes: 4
Constant pool:
   #1 = Utf8               org/scalatest/StreamlinedXmlNormMethods$
   #2 = Class              #1             // org/scalatest/StreamlinedXmlNormMethods$
   #3 = Utf8               java/lang/Object
   #4 = Class              #3             // java/lang/Object
   #5 = Utf8               org/scalatest/StreamlinedXmlNormMethods
   #6 = Class              #5             // org/scalatest/StreamlinedXmlNormMethods
   #7 = Utf8               StreamlinedXmlNormMethods.scala
   #8 = Utf8               org/scalactic/NormMethods$Normalizer
   #9 = Class              #8             // org/scalactic/NormMethods$Normalizer
  #10 = Utf8               org/scalactic/NormMethods
  #11 = Class              #10            // org/scalactic/NormMethods
  #12 = Utf8               Normalizer
  #13 = Utf8               MODULE$
  #14 = Utf8               Lorg/scalatest/StreamlinedXmlNormMethods$;
  #15 = Utf8               <clinit>
  #16 = Utf8               ()V
  #17 = Utf8               <init>
  #18 = NameAndType        #17:#16        // "<init>":()V
  #19 = Methodref          #2.#18         // org/scalatest/StreamlinedXmlNormMethods$."<init>":()V
  #20 = NameAndType        #13:#14        // MODULE$:Lorg/scalatest/StreamlinedXmlNormMethods$;
  #21 = Fieldref           #2.#20         // org/scalatest/StreamlinedXmlNormMethods$.MODULE$:Lorg/scalatest/StreamlinedXmlNormMethods$;
  #22 = Utf8               org/scalatest/StreamlinedXml
  #23 = Class              #22            // org/scalatest/StreamlinedXml
  #24 = Utf8               $init$
  #25 = Utf8               (Lorg/scalatest/StreamlinedXml;)V
  #26 = NameAndType        #24:#25        // $init$:(Lorg/scalatest/StreamlinedXml;)V
  #27 = InterfaceMethodref #23.#26        // org/scalatest/StreamlinedXml.$init$:(Lorg/scalatest/StreamlinedXml;)V
  #28 = Utf8               (Lorg/scalactic/NormMethods;)V
  #29 = NameAndType        #24:#28        // $init$:(Lorg/scalactic/NormMethods;)V
  #30 = InterfaceMethodref #11.#29        // org/scalactic/NormMethods.$init$:(Lorg/scalactic/NormMethods;)V
  #31 = Utf8               (Lorg/scalatest/StreamlinedXmlNormMethods;)V
  #32 = NameAndType        #24:#31        // $init$:(Lorg/scalatest/StreamlinedXmlNormMethods;)V
  #33 = InterfaceMethodref #6.#32         // org/scalatest/StreamlinedXmlNormMethods.$init$:(Lorg/scalatest/StreamlinedXmlNormMethods;)V
  #34 = Utf8               org$scalatest$StreamlinedXmlNormMethods$$super$streamlined
  #35 = Utf8               ()Lorg/scalactic/Uniformity;
  #36 = Utf8               streamlined$
  #37 = Utf8               (Lorg/scalatest/StreamlinedXml;)Lorg/scalactic/Uniformity;
  #38 = NameAndType        #36:#37        // streamlined$:(Lorg/scalatest/StreamlinedXml;)Lorg/scalactic/Uniformity;
  #39 = InterfaceMethodref #23.#38        // org/scalatest/StreamlinedXml.streamlined$:(Lorg/scalatest/StreamlinedXml;)Lorg/scalactic/Uniformity;
  #40 = Utf8               this
  #41 = Utf8               streamlined
  #42 = Utf8               <T:Lscala/xml/NodeSeq;>()Lorg/scalactic/Uniformity<TT;>;
  #43 = Utf8               (Lorg/scalatest/StreamlinedXmlNormMethods;)Lorg/scalactic/Uniformity;
  #44 = NameAndType        #36:#43        // streamlined$:(Lorg/scalatest/StreamlinedXmlNormMethods;)Lorg/scalactic/Uniformity;
  #45 = InterfaceMethodref #6.#44         // org/scalatest/StreamlinedXmlNormMethods.streamlined$:(Lorg/scalatest/StreamlinedXmlNormMethods;)Lorg/scalactic/Uniformity;
  #46 = Utf8               convertToNormalizer
  #47 = Utf8               (Ljava/lang/Object;Lorg/scalactic/Normalization;)Lorg/scalactic/NormMethods$Normalizer;
  #48 = Utf8               <T:Ljava/lang/Object;>(TT;Lorg/scalactic/Normalization<TT;>;)Lorg/scalactic/NormMethods$Normalizer<TT;>;
  #49 = Utf8               o
  #50 = Utf8               normalization
  #51 = Utf8               convertToNormalizer$
  #52 = Utf8               (Lorg/scalactic/NormMethods;Ljava/lang/Object;Lorg/scalactic/Normalization;)Lorg/scalactic/NormMethods$Normalizer;
  #53 = NameAndType        #51:#52        // convertToNormalizer$:(Lorg/scalactic/NormMethods;Ljava/lang/Object;Lorg/scalactic/Normalization;)Lorg/scalactic/NormMethods$Normalizer;
  #54 = InterfaceMethodref #11.#53        // org/scalactic/NormMethods.convertToNormalizer$:(Lorg/scalactic/NormMethods;Ljava/lang/Object;Lorg/scalactic/Normalization;)Lorg/scalactic/NormMethods$Normalizer;
  #55 = Utf8               Ljava/lang/Object;
  #56 = Utf8               Lorg/scalactic/Normalization;
  #57 = Methodref          #4.#18         // java/lang/Object."<init>":()V
  #58 = Utf8               Code
  #59 = Utf8               LineNumberTable
  #60 = Utf8               LocalVariableTable
  #61 = Utf8               Signature
  #62 = Utf8               MethodParameters
  #63 = Utf8               InnerClasses
  #64 = Utf8               SourceFile
  #65 = Utf8               ScalaInlineInfo
  #66 = Utf8               Scala
{
  public static final org.scalatest.StreamlinedXmlNormMethods$ MODULE$;
    descriptor: Lorg/scalatest/StreamlinedXmlNormMethods$;
    flags: (0x0019) ACC_PUBLIC, ACC_STATIC, ACC_FINAL

  public static {};
    descriptor: ()V
    flags: (0x0009) ACC_PUBLIC, ACC_STATIC
    Code:
      stack=2, locals=0, args_size=0
         0: new           #2                  // class org/scalatest/StreamlinedXmlNormMethods$
         3: dup
         4: invokespecial #19                 // Method "<init>":()V
         7: putstatic     #21                 // Field MODULE$:Lorg/scalatest/StreamlinedXmlNormMethods$;
        10: getstatic     #21                 // Field MODULE$:Lorg/scalatest/StreamlinedXmlNormMethods$;
        13: invokestatic  #27                 // InterfaceMethod org/scalatest/StreamlinedXml.$init$:(Lorg/scalatest/StreamlinedXml;)V
        16: getstatic     #21                 // Field MODULE$:Lorg/scalatest/StreamlinedXmlNormMethods$;
        19: invokestatic  #30                 // InterfaceMethod org/scalactic/NormMethods.$init$:(Lorg/scalactic/NormMethods;)V
        22: getstatic     #21                 // Field MODULE$:Lorg/scalatest/StreamlinedXmlNormMethods$;
        25: invokestatic  #33                 // InterfaceMethod org/scalatest/StreamlinedXmlNormMethods.$init$:(Lorg/scalatest/StreamlinedXmlNormMethods;)V
        28: return
      LineNumberTable:
        line 80: 0

  public org.scalactic.Uniformity org$scalatest$StreamlinedXmlNormMethods$$super$streamlined();
    descriptor: ()Lorg/scalactic/Uniformity;
    flags: (0x1001) ACC_PUBLIC, ACC_SYNTHETIC
    Code:
      stack=1, locals=1, args_size=1
         0: aload_0
         1: invokestatic  #39                 // InterfaceMethod org/scalatest/StreamlinedXml.streamlined$:(Lorg/scalatest/StreamlinedXml;)Lorg/scalactic/Uniformity;
         4: areturn
      LineNumberTable:
        line 80: 0
      LocalVariableTable:
        Start  Length  Slot  Name   Signature
            0       5     0  this   Lorg/scalatest/StreamlinedXmlNormMethods$;

  public <T extends scala.xml.NodeSeq> org.scalactic.Uniformity<T> streamlined();
    descriptor: ()Lorg/scalactic/Uniformity;
    flags: (0x0001) ACC_PUBLIC
    Code:
      stack=1, locals=1, args_size=1
         0: aload_0
         1: invokestatic  #45                 // InterfaceMethod org/scalatest/StreamlinedXmlNormMethods.streamlined$:(Lorg/scalatest/StreamlinedXmlNormMethods;)Lorg/scalactic/Uniformity;
         4: areturn
      LineNumberTable:
        line 80: 0
      LocalVariableTable:
        Start  Length  Slot  Name   Signature
            0       5     0  this   Lorg/scalatest/StreamlinedXmlNormMethods$;
    Signature: #42                          // <T:Lscala/xml/NodeSeq;>()Lorg/scalactic/Uniformity<TT;>;

  public <T extends java.lang.Object> org.scalactic.NormMethods$Normalizer<T> convertToNormalizer(T, org.scalactic.Normalization<T>);
    descriptor: (Ljava/lang/Object;Lorg/scalactic/Normalization;)Lorg/scalactic/NormMethods$Normalizer;
    flags: (0x0001) ACC_PUBLIC
    Code:
      stack=3, locals=3, args_size=3
         0: aload_0
         1: aload_1
         2: aload_2
         3: invokestatic  #54                 // InterfaceMethod org/scalactic/NormMethods.convertToNormalizer$:(Lorg/scalactic/NormMethods;Ljava/lang/Object;Lorg/scalactic/Normalization;)Lorg/scalactic/NormMethods$Normalizer;
         6: areturn
      LineNumberTable:
        line 80: 0
      LocalVariableTable:
        Start  Length  Slot  Name   Signature
            0       7     0  this   Lorg/scalatest/StreamlinedXmlNormMethods$;
            0       7     1     o   Ljava/lang/Object;
            0       7     2 normalization   Lorg/scalactic/Normalization;
    Signature: #48                          // <T:Ljava/lang/Object;>(TT;Lorg/scalactic/Normalization<TT;>;)Lorg/scalactic/NormMethods$Normalizer<TT;>;
    MethodParameters:
      Name                           Flags
      o                              final
      normalization                  final

  private org.scalatest.StreamlinedXmlNormMethods$();
    descriptor: ()V
    flags: (0x0002) ACC_PRIVATE
    Code:
      stack=1, locals=1, args_size=1
         0: aload_0
         1: invokespecial #57                 // Method java/lang/Object."<init>":()V
         4: return
      LineNumberTable:
        line 80: 0
      LocalVariableTable:
        Start  Length  Slot  Name   Signature
            0       5     0  this   Lorg/scalatest/StreamlinedXmlNormMethods$;
}
InnerClasses:
  public final #12= #9 of #11;            // Normalizer=class org/scalactic/NormMethods$Normalizer of class org/scalactic/NormMethods
SourceFile: "StreamlinedXmlNormMethods.scala"
  ScalaInlineInfo: length = 0x18 (unknown attribute)
   01 01 00 04 00 11 00 10 01 00 2E 00 2F 01 00 22
   00 23 01 00 29 00 23 01
  Scala: length = 0x0 (unknown attribute)

