Classfile /Users/mw/Projects/slang-braindump/.jar/jar11/assemble/slang-braindump/assemble/content/org/scalatest/StreamlinedXmlEquality$$anon$1.class
  Last modified May 29, 2022; size 2068 bytes
  SHA-256 checksum bd49146de6ce5356a3a6066f718df42a94dce6e3a3d8022896904f29b153309b
  Compiled from "StreamlinedXmlEquality.scala"
public final class org.scalatest.StreamlinedXmlEquality$$anon$1 extends java.lang.Object implements org.scalactic.Equality<T>
  minor version: 0
  major version: 52
  flags: (0x0031) ACC_PUBLIC, ACC_FINAL, ACC_SUPER
  this_class: #2                          // org/scalatest/StreamlinedXmlEquality$$anon$1
  super_class: #5                         // java/lang/Object
  interfaces: 1, fields: 1, methods: 5, attributes: 6
Constant pool:
   #1 = Utf8               org/scalatest/StreamlinedXmlEquality$$anon$1
   #2 = Class              #1             // org/scalatest/StreamlinedXmlEquality$$anon$1
   #3 = Utf8               Ljava/lang/Object;Lorg/scalactic/Equality<TT;>;
   #4 = Utf8               java/lang/Object
   #5 = Class              #4             // java/lang/Object
   #6 = Utf8               org/scalactic/Equality
   #7 = Class              #6             // org/scalactic/Equality
   #8 = Utf8               StreamlinedXmlEquality.scala
   #9 = Utf8               org/scalatest/StreamlinedXmlEquality
  #10 = Class              #9             // org/scalatest/StreamlinedXmlEquality
  #11 = Utf8               streamlinedXmlEquality
  #12 = Utf8               ()Lorg/scalactic/Equality;
  #13 = NameAndType        #11:#12        // streamlinedXmlEquality:()Lorg/scalactic/Equality;
  #14 = Utf8               xu
  #15 = Utf8               Lorg/scalactic/Uniformity;
  #16 = Utf8               Lorg/scalactic/Uniformity<TT;>;
  #17 = Utf8               areEquivalent
  #18 = Utf8               (Ljava/lang/Object;Ljava/lang/Object;)Z
  #19 = Utf8               a
  #20 = Utf8               b
  #21 = Utf8               areEquivalent$
  #22 = Utf8               (Lorg/scalactic/Equality;Ljava/lang/Object;Ljava/lang/Object;)Z
  #23 = NameAndType        #21:#22        // areEquivalent$:(Lorg/scalactic/Equality;Ljava/lang/Object;Ljava/lang/Object;)Z
  #24 = InterfaceMethodref #7.#23         // org/scalactic/Equality.areEquivalent$:(Lorg/scalactic/Equality;Ljava/lang/Object;Ljava/lang/Object;)Z
  #25 = Utf8               this
  #26 = Utf8               Lorg/scalatest/StreamlinedXmlEquality$$anon$1;
  #27 = Utf8               Ljava/lang/Object;
  #28 = Utf8               ()Lorg/scalactic/Uniformity;
  #29 = Utf8               ()Lorg/scalactic/Uniformity<TT;>;
  #30 = NameAndType        #14:#15        // xu:Lorg/scalactic/Uniformity;
  #31 = Fieldref           #2.#30         // org/scalatest/StreamlinedXmlEquality$$anon$1.xu:Lorg/scalactic/Uniformity;
  #32 = Utf8               areEqual
  #33 = Utf8               (Lscala/xml/NodeSeq;Ljava/lang/Object;)Z
  #34 = Utf8               (TT;Ljava/lang/Object;)Z
  #35 = NameAndType        #14:#28        // xu:()Lorg/scalactic/Uniformity;
  #36 = Methodref          #2.#35         // org/scalatest/StreamlinedXmlEquality$$anon$1.xu:()Lorg/scalactic/Uniformity;
  #37 = Utf8               org/scalactic/Uniformity
  #38 = Class              #37            // org/scalactic/Uniformity
  #39 = Utf8               normalized
  #40 = Utf8               (Ljava/lang/Object;)Ljava/lang/Object;
  #41 = NameAndType        #39:#40        // normalized:(Ljava/lang/Object;)Ljava/lang/Object;
  #42 = InterfaceMethodref #38.#41        // org/scalactic/Uniformity.normalized:(Ljava/lang/Object;)Ljava/lang/Object;
  #43 = Utf8               normalizedOrSame
  #44 = NameAndType        #43:#40        // normalizedOrSame:(Ljava/lang/Object;)Ljava/lang/Object;
  #45 = InterfaceMethodref #38.#44        // org/scalactic/Uniformity.normalizedOrSame:(Ljava/lang/Object;)Ljava/lang/Object;
  #46 = Utf8               scala/runtime/BoxesRunTime
  #47 = Class              #46            // scala/runtime/BoxesRunTime
  #48 = Utf8               equals
  #49 = NameAndType        #48:#18        // equals:(Ljava/lang/Object;Ljava/lang/Object;)Z
  #50 = Methodref          #47.#49        // scala/runtime/BoxesRunTime.equals:(Ljava/lang/Object;Ljava/lang/Object;)Z
  #51 = Utf8               Lscala/xml/NodeSeq;
  #52 = Utf8               scala/xml/NodeSeq
  #53 = Class              #52            // scala/xml/NodeSeq
  #54 = NameAndType        #32:#33        // areEqual:(Lscala/xml/NodeSeq;Ljava/lang/Object;)Z
  #55 = Methodref          #2.#54         // org/scalatest/StreamlinedXmlEquality$$anon$1.areEqual:(Lscala/xml/NodeSeq;Ljava/lang/Object;)Z
  #56 = Utf8               <init>
  #57 = Utf8               (Lorg/scalatest/StreamlinedXmlEquality;)V
  #58 = Utf8               $outer
  #59 = Utf8               ()V
  #60 = NameAndType        #56:#59        // "<init>":()V
  #61 = Methodref          #5.#60         // java/lang/Object."<init>":()V
  #62 = Utf8               $init$
  #63 = Utf8               (Lorg/scalactic/Equality;)V
  #64 = NameAndType        #62:#63        // $init$:(Lorg/scalactic/Equality;)V
  #65 = InterfaceMethodref #7.#64         // org/scalactic/Equality.$init$:(Lorg/scalactic/Equality;)V
  #66 = Utf8               org/scalatest/StreamlinedXml$
  #67 = Class              #66            // org/scalatest/StreamlinedXml$
  #68 = Utf8               MODULE$
  #69 = Utf8               Lorg/scalatest/StreamlinedXml$;
  #70 = NameAndType        #68:#69        // MODULE$:Lorg/scalatest/StreamlinedXml$;
  #71 = Fieldref           #67.#70        // org/scalatest/StreamlinedXml$.MODULE$:Lorg/scalatest/StreamlinedXml$;
  #72 = Utf8               streamlined
  #73 = NameAndType        #72:#28        // streamlined:()Lorg/scalactic/Uniformity;
  #74 = Methodref          #67.#73        // org/scalatest/StreamlinedXml$.streamlined:()Lorg/scalactic/Uniformity;
  #75 = Utf8               Lorg/scalatest/StreamlinedXmlEquality;
  #76 = Utf8               Signature
  #77 = Utf8               Code
  #78 = Utf8               LineNumberTable
  #79 = Utf8               LocalVariableTable
  #80 = Utf8               MethodParameters
  #81 = Utf8               StackMapTable
  #82 = Utf8               InnerClasses
  #83 = Utf8               EnclosingMethod
  #84 = Utf8               SourceFile
  #85 = Utf8               ScalaInlineInfo
  #86 = Utf8               Scala
{
  private final org.scalactic.Uniformity<T> xu;
    descriptor: Lorg/scalactic/Uniformity;
    flags: (0x0012) ACC_PRIVATE, ACC_FINAL
    Signature: #16                          // Lorg/scalactic/Uniformity<TT;>;

  public final boolean areEquivalent(java.lang.Object, java.lang.Object);
    descriptor: (Ljava/lang/Object;Ljava/lang/Object;)Z
    flags: (0x0011) ACC_PUBLIC, ACC_FINAL
    Code:
      stack=3, locals=3, args_size=3
         0: aload_0
         1: aload_1
         2: aload_2
         3: invokestatic  #24                 // InterfaceMethod org/scalactic/Equality.areEquivalent$:(Lorg/scalactic/Equality;Ljava/lang/Object;Ljava/lang/Object;)Z
         6: ireturn
      LineNumberTable:
        line 117: 0
      LocalVariableTable:
        Start  Length  Slot  Name   Signature
            0       7     0  this   Lorg/scalatest/StreamlinedXmlEquality$$anon$1;
            0       7     1     a   Ljava/lang/Object;
            0       7     2     b   Ljava/lang/Object;
    MethodParameters:
      Name                           Flags
      a                              final
      b                              final

  private org.scalactic.Uniformity<T> xu();
    descriptor: ()Lorg/scalactic/Uniformity;
    flags: (0x0002) ACC_PRIVATE
    Code:
      stack=1, locals=1, args_size=1
         0: aload_0
         1: getfield      #31                 // Field xu:Lorg/scalactic/Uniformity;
         4: areturn
      LineNumberTable:
        line 118: 0
      LocalVariableTable:
        Start  Length  Slot  Name   Signature
            0       5     0  this   Lorg/scalatest/StreamlinedXmlEquality$$anon$1;
    Signature: #29                          // ()Lorg/scalactic/Uniformity<TT;>;

  public boolean areEqual(T, java.lang.Object);
    descriptor: (Lscala/xml/NodeSeq;Ljava/lang/Object;)Z
    flags: (0x0001) ACC_PUBLIC
    Code:
      stack=3, locals=3, args_size=3
         0: aload_0
         1: invokespecial #36                 // Method xu:()Lorg/scalactic/Uniformity;
         4: aload_1
         5: invokeinterface #42,  2           // InterfaceMethod org/scalactic/Uniformity.normalized:(Ljava/lang/Object;)Ljava/lang/Object;
        10: aload_0
        11: invokespecial #36                 // Method xu:()Lorg/scalactic/Uniformity;
        14: aload_2
        15: invokeinterface #45,  2           // InterfaceMethod org/scalactic/Uniformity.normalizedOrSame:(Ljava/lang/Object;)Ljava/lang/Object;
        20: invokestatic  #50                 // Method scala/runtime/BoxesRunTime.equals:(Ljava/lang/Object;Ljava/lang/Object;)Z
        23: ifeq          30
        26: iconst_1
        27: goto          31
        30: iconst_0
        31: ireturn
      StackMapTable: number_of_entries = 2
        frame_type = 30 /* same */
        frame_type = 64 /* same_locals_1_stack_item */
          stack = [ int ]
      LineNumberTable:
        line 120: 0
      LocalVariableTable:
        Start  Length  Slot  Name   Signature
            0      32     0  this   Lorg/scalatest/StreamlinedXmlEquality$$anon$1;
            0      32     1     a   Lscala/xml/NodeSeq;
            0      32     2     b   Ljava/lang/Object;
    Signature: #34                          // (TT;Ljava/lang/Object;)Z
    MethodParameters:
      Name                           Flags
      a                              final
      b                              final

  public boolean areEqual(java.lang.Object, java.lang.Object);
    descriptor: (Ljava/lang/Object;Ljava/lang/Object;)Z
    flags: (0x1041) ACC_PUBLIC, ACC_BRIDGE, ACC_SYNTHETIC
    Code:
      stack=3, locals=3, args_size=3
         0: aload_0
         1: aload_1
         2: checkcast     #53                 // class scala/xml/NodeSeq
         5: aload_2
         6: invokevirtual #55                 // Method areEqual:(Lscala/xml/NodeSeq;Ljava/lang/Object;)Z
         9: ireturn
      LineNumberTable:
        line 117: 0
      LocalVariableTable:
        Start  Length  Slot  Name   Signature
            0      10     0  this   Lorg/scalatest/StreamlinedXmlEquality$$anon$1;
            0      10     1     a   Ljava/lang/Object;
            0      10     2     b   Ljava/lang/Object;
    MethodParameters:
      Name                           Flags
      a                              final
      b                              final

  public org.scalatest.StreamlinedXmlEquality$$anon$1(org.scalatest.StreamlinedXmlEquality);
    descriptor: (Lorg/scalatest/StreamlinedXmlEquality;)V
    flags: (0x0001) ACC_PUBLIC
    Code:
      stack=2, locals=2, args_size=2
         0: aload_0
         1: invokespecial #61                 // Method java/lang/Object."<init>":()V
         4: aload_0
         5: invokestatic  #65                 // InterfaceMethod org/scalactic/Equality.$init$:(Lorg/scalactic/Equality;)V
         8: aload_0
         9: getstatic     #71                 // Field org/scalatest/StreamlinedXml$.MODULE$:Lorg/scalatest/StreamlinedXml$;
        12: invokevirtual #74                 // Method org/scalatest/StreamlinedXml$.streamlined:()Lorg/scalactic/Uniformity;
        15: putfield      #31                 // Field xu:Lorg/scalactic/Uniformity;
        18: return
      LineNumberTable:
        line 117: 0
        line 118: 8
        line 117: 18
      LocalVariableTable:
        Start  Length  Slot  Name   Signature
            0      19     0  this   Lorg/scalatest/StreamlinedXmlEquality$$anon$1;
            0      19     1 $outer   Lorg/scalatest/StreamlinedXmlEquality;
    MethodParameters:
      Name                           Flags
      $outer                         final synthetic
}
InnerClasses:
  public final #2;                        // class org/scalatest/StreamlinedXmlEquality$$anon$1
EnclosingMethod: #10.#13                // org.scalatest.StreamlinedXmlEquality.streamlinedXmlEquality
Signature: #3                           // Ljava/lang/Object;Lorg/scalactic/Equality<TT;>;
SourceFile: "StreamlinedXmlEquality.scala"
  ScalaInlineInfo: length = 0x1D (unknown attribute)
   01 01 00 05 00 38 00 39 01 00 20 00 12 01 00 20
   00 21 01 00 11 00 12 01 00 0E 00 1C 01
  Scala: length = 0x0 (unknown attribute)

