Classfile /Users/mw/Projects/slang-braindump/.jar/jar11/assemble/slang-braindump/assemble/content/org/scalatest/Succeeded.class
  Last modified May 29, 2022; size 2544 bytes
  SHA-256 checksum dbf203d9fa23a5939e35b6c6fda64e15e6204e8bccedccc35d0e50b44dd8c73f
  Compiled from "Outcome.scala"
public final class org.scalatest.Succeeded
  minor version: 0
  major version: 52
  flags: (0x0031) ACC_PUBLIC, ACC_FINAL, ACC_SUPER
  this_class: #2                          // org/scalatest/Succeeded
  super_class: #4                         // java/lang/Object
  interfaces: 0, fields: 0, methods: 16, attributes: 3
Constant pool:
   #1 = Utf8               org/scalatest/Succeeded
   #2 = Class              #1             // org/scalatest/Succeeded
   #3 = Utf8               java/lang/Object
   #4 = Class              #3             // java/lang/Object
   #5 = Utf8               Outcome.scala
   #6 = Utf8               Lscala/reflect/ScalaSignature;
   #7 = Utf8               bytes
   #8 = Utf8               \u0006\u0005!<QAD\b\t\u0002R1QAF\b\t\u0002^AQaM\u0001\u0005\u0002QBq!N\u0001C\u0002\u0013\u0005c\u0007\u0003\u0004;\u0003\u0001\u0006Ia\u000e\u0005\u0006w\u0005!\t\u0001\u0010\u0005\b}\u0005\t\t\u0011\"\u0011@\u0011\u001dA\u0015!!A\u0005\u0002%Cq!T\u0001\u0002\u0002\u0013\u0005a\nC\u0004U\u0003\u0005\u0005I\u0011I+\t\u000fq\u000b\u0011\u0011!C\u0001;\"9q,AA\u0001\n\u0003\u0002\u0007bB1\u0002\u0003\u0003%\tE\u0019\u0005\bG\u0006\t\t\u0011\"\u0003e\u0003%\u0019VoY2fK\u0012,GM\u0003\u0002\u0011#\u0005I1oY1mCR,7\u000f\u001e\u0006\u0002%\u0005\u0019qN]4\u0004\u0001A\u0011Q#A\u0007\u0002\u001f\tI1+^2dK\u0016$W\rZ\n\u0006\u0003aY\u0012e\n\t\u0003+eI!AG\b\u0003\u000f=+HoY8nKB\u0011AdH\u0007\u0002;)\u0011adD\u0001\u000bG>l\u0007/\u0019;jE2,\u0017B\u0001\u0011\u001e\u0005%\t5o]3si&|g\u000e\u0005\u0002#K5\t1EC\u0001%\u0003\u0015\u00198-\u00197b\u0013\t13EA\u0004Qe>$Wo\u0019;\u0011\u0005!\u0002dBA\u0015/\u001d\tQS&D\u0001,\u0015\ta3#\u0001\u0004=e>|GOP\u0005\u0002I%\u0011qfI\u0001\ba\u0006\u001c7.Y4f\u0013\t\t$G\u0001\u0007TKJL\u0017\r\\5{C\ndWM\u0003\u00020G\u00051A(\u001b8jiz\"\u0012\u0001F\u0001\fSN\u001cVoY2fK\u0012,G-F\u00018!\t\u0011\u0003(\u0003\u0002:G\t9!i\\8mK\u0006t\u0017\u0001D5t\'V\u001c7-Z3eK\u0012\u0004\u0013a\u0003;p\'V\u001c7-Z3eK\u0012,\u0012!\u0010\b\u0003+\u0001\tQ\u0002\u001d:pIV\u001cG\u000f\u0015:fM&DX#\u0001!\u0011\u0005\u00053U\"\u0001\"\u000b\u0005\r#\u0015\u0001\u00027b]\u001eT\u0011!R\u0001\u0005U\u00064\u0018-\u0003\u0002H\u0005\n11\u000b\u001e:j]\u001e\fA\u0002\u001d:pIV\u001cG/\u0011:jif,\u0012A\u0013\t\u0003E-K!\u0001T\u0012\u0003\u0007%sG/\u0001\bqe>$Wo\u0019;FY\u0016lWM\u001c;\u0015\u0005=\u0013\u0006C\u0001\u0012Q\u0013\t\t6EA\u0002B]fDqa\u0015\u0005\u0002\u0002\u0003\u0007!*A\u0002yIE\nq\u0002\u001d:pIV\u001cG/\u0013;fe\u0006$xN]\u000b\u0002-B\u0019qKW(\u000e\u0003aS!!W\u0012\u0002\u0015\r|G\u000e\\3di&|g.\u0003\u0002\\1\nA\u0011\n^3sCR|\'/\u0001\u0005dC:,\u0015/^1m)\t9d\fC\u0004T\u0015\u0005\u0005\t\u0019A(\u0002\u0011!\f7\u000f[\"pI\u0016$\u0012AS\u0001\ti>\u001cFO]5oOR\t\u0001)\u0001\u0007xe&$XMU3qY\u0006\u001cW\rF\u0001f!\t\te-\u0003\u0002h\u0005\n1qJ\u00196fGR\u0004
   #9 = Utf8               toString
  #10 = Utf8               ()Ljava/lang/String;
  #11 = Utf8               org/scalatest/Succeeded$
  #12 = Class              #11            // org/scalatest/Succeeded$
  #13 = Utf8               MODULE$
  #14 = Utf8               Lorg/scalatest/Succeeded$;
  #15 = NameAndType        #13:#14        // MODULE$:Lorg/scalatest/Succeeded$;
  #16 = Fieldref           #12.#15        // org/scalatest/Succeeded$.MODULE$:Lorg/scalatest/Succeeded$;
  #17 = NameAndType        #9:#10         // toString:()Ljava/lang/String;
  #18 = Methodref          #12.#17        // org/scalatest/Succeeded$.toString:()Ljava/lang/String;
  #19 = Utf8               hashCode
  #20 = Utf8               ()I
  #21 = NameAndType        #19:#20        // hashCode:()I
  #22 = Methodref          #12.#21        // org/scalatest/Succeeded$.hashCode:()I
  #23 = Utf8               canEqual
  #24 = Utf8               (Ljava/lang/Object;)Z
  #25 = Utf8               x$1
  #26 = NameAndType        #23:#24        // canEqual:(Ljava/lang/Object;)Z
  #27 = Methodref          #12.#26        // org/scalatest/Succeeded$.canEqual:(Ljava/lang/Object;)Z
  #28 = Utf8               Ljava/lang/Object;
  #29 = Utf8               productIterator
  #30 = Utf8               ()Lscala/collection/Iterator;
  #31 = Utf8               ()Lscala/collection/Iterator<Ljava/lang/Object;>;
  #32 = NameAndType        #29:#30        // productIterator:()Lscala/collection/Iterator;
  #33 = Methodref          #12.#32        // org/scalatest/Succeeded$.productIterator:()Lscala/collection/Iterator;
  #34 = Utf8               productElement
  #35 = Utf8               (I)Ljava/lang/Object;
  #36 = NameAndType        #34:#35        // productElement:(I)Ljava/lang/Object;
  #37 = Methodref          #12.#36        // org/scalatest/Succeeded$.productElement:(I)Ljava/lang/Object;
  #38 = Utf8               I
  #39 = Utf8               productArity
  #40 = NameAndType        #39:#20        // productArity:()I
  #41 = Methodref          #12.#40        // org/scalatest/Succeeded$.productArity:()I
  #42 = Utf8               productPrefix
  #43 = NameAndType        #42:#10        // productPrefix:()Ljava/lang/String;
  #44 = Methodref          #12.#43        // org/scalatest/Succeeded$.productPrefix:()Ljava/lang/String;
  #45 = Utf8               toSucceeded
  #46 = Utf8               ()Lorg/scalatest/Succeeded$;
  #47 = NameAndType        #45:#46        // toSucceeded:()Lorg/scalatest/Succeeded$;
  #48 = Methodref          #12.#47        // org/scalatest/Succeeded$.toSucceeded:()Lorg/scalatest/Succeeded$;
  #49 = Utf8               isSucceeded
  #50 = Utf8               ()Z
  #51 = NameAndType        #49:#50        // isSucceeded:()Z
  #52 = Methodref          #12.#51        // org/scalatest/Succeeded$.isSucceeded:()Z
  #53 = Utf8               toOption
  #54 = Utf8               ()Lscala/Option;
  #55 = Utf8               ()Lscala/Option<Ljava/lang/Throwable;>;
  #56 = NameAndType        #53:#54        // toOption:()Lscala/Option;
  #57 = Methodref          #12.#56        // org/scalatest/Succeeded$.toOption:()Lscala/Option;
  #58 = Utf8               isExceptional
  #59 = NameAndType        #58:#50        // isExceptional:()Z
  #60 = Methodref          #12.#59        // org/scalatest/Succeeded$.isExceptional:()Z
  #61 = Utf8               isPending
  #62 = NameAndType        #61:#50        // isPending:()Z
  #63 = Methodref          #12.#62        // org/scalatest/Succeeded$.isPending:()Z
  #64 = Utf8               isCanceled
  #65 = NameAndType        #64:#50        // isCanceled:()Z
  #66 = Methodref          #12.#65        // org/scalatest/Succeeded$.isCanceled:()Z
  #67 = Utf8               isFailed
  #68 = NameAndType        #67:#50        // isFailed:()Z
  #69 = Methodref          #12.#68        // org/scalatest/Succeeded$.isFailed:()Z
  #70 = Utf8               productElementNames
  #71 = Utf8               ()Lscala/collection/Iterator<Ljava/lang/String;>;
  #72 = NameAndType        #70:#30        // productElementNames:()Lscala/collection/Iterator;
  #73 = Methodref          #12.#72        // org/scalatest/Succeeded$.productElementNames:()Lscala/collection/Iterator;
  #74 = Utf8               productElementName
  #75 = Utf8               (I)Ljava/lang/String;
  #76 = Utf8               n
  #77 = NameAndType        #74:#75        // productElementName:(I)Ljava/lang/String;
  #78 = Methodref          #12.#77        // org/scalatest/Succeeded$.productElementName:(I)Ljava/lang/String;
  #79 = Utf8               Code
  #80 = Utf8               LocalVariableTable
  #81 = Utf8               MethodParameters
  #82 = Utf8               Signature
  #83 = Utf8               SourceFile
  #84 = Utf8               RuntimeVisibleAnnotations
  #85 = Utf8               ScalaSig
{
  public static java.lang.String toString();
    descriptor: ()Ljava/lang/String;
    flags: (0x0009) ACC_PUBLIC, ACC_STATIC
    Code:
      stack=1, locals=0, args_size=0
         0: getstatic     #16                 // Field org/scalatest/Succeeded$.MODULE$:Lorg/scalatest/Succeeded$;
         3: invokevirtual #18                 // Method org/scalatest/Succeeded$.toString:()Ljava/lang/String;
         6: areturn

  public static int hashCode();
    descriptor: ()I
    flags: (0x0009) ACC_PUBLIC, ACC_STATIC
    Code:
      stack=1, locals=0, args_size=0
         0: getstatic     #16                 // Field org/scalatest/Succeeded$.MODULE$:Lorg/scalatest/Succeeded$;
         3: invokevirtual #22                 // Method org/scalatest/Succeeded$.hashCode:()I
         6: ireturn

  public static boolean canEqual(java.lang.Object);
    descriptor: (Ljava/lang/Object;)Z
    flags: (0x0009) ACC_PUBLIC, ACC_STATIC
    Code:
      stack=2, locals=1, args_size=1
         0: getstatic     #16                 // Field org/scalatest/Succeeded$.MODULE$:Lorg/scalatest/Succeeded$;
         3: aload_0
         4: invokevirtual #27                 // Method org/scalatest/Succeeded$.canEqual:(Ljava/lang/Object;)Z
         7: ireturn
      LocalVariableTable:
        Start  Length  Slot  Name   Signature
            0       8     0   x$1   Ljava/lang/Object;
    MethodParameters:
      Name                           Flags
      x$1                            final

  public static scala.collection.Iterator<java.lang.Object> productIterator();
    descriptor: ()Lscala/collection/Iterator;
    flags: (0x0009) ACC_PUBLIC, ACC_STATIC
    Code:
      stack=1, locals=0, args_size=0
         0: getstatic     #16                 // Field org/scalatest/Succeeded$.MODULE$:Lorg/scalatest/Succeeded$;
         3: invokevirtual #33                 // Method org/scalatest/Succeeded$.productIterator:()Lscala/collection/Iterator;
         6: areturn
    Signature: #31                          // ()Lscala/collection/Iterator<Ljava/lang/Object;>;

  public static java.lang.Object productElement(int);
    descriptor: (I)Ljava/lang/Object;
    flags: (0x0009) ACC_PUBLIC, ACC_STATIC
    Code:
      stack=2, locals=1, args_size=1
         0: getstatic     #16                 // Field org/scalatest/Succeeded$.MODULE$:Lorg/scalatest/Succeeded$;
         3: iload_0
         4: invokevirtual #37                 // Method org/scalatest/Succeeded$.productElement:(I)Ljava/lang/Object;
         7: areturn
      LocalVariableTable:
        Start  Length  Slot  Name   Signature
            0       8     0   x$1   I
    MethodParameters:
      Name                           Flags
      x$1                            final

  public static int productArity();
    descriptor: ()I
    flags: (0x0009) ACC_PUBLIC, ACC_STATIC
    Code:
      stack=1, locals=0, args_size=0
         0: getstatic     #16                 // Field org/scalatest/Succeeded$.MODULE$:Lorg/scalatest/Succeeded$;
         3: invokevirtual #41                 // Method org/scalatest/Succeeded$.productArity:()I
         6: ireturn

  public static java.lang.String productPrefix();
    descriptor: ()Ljava/lang/String;
    flags: (0x0009) ACC_PUBLIC, ACC_STATIC
    Code:
      stack=1, locals=0, args_size=0
         0: getstatic     #16                 // Field org/scalatest/Succeeded$.MODULE$:Lorg/scalatest/Succeeded$;
         3: invokevirtual #44                 // Method org/scalatest/Succeeded$.productPrefix:()Ljava/lang/String;
         6: areturn

  public static org.scalatest.Succeeded$ toSucceeded();
    descriptor: ()Lorg/scalatest/Succeeded$;
    flags: (0x0009) ACC_PUBLIC, ACC_STATIC
    Code:
      stack=1, locals=0, args_size=0
         0: getstatic     #16                 // Field org/scalatest/Succeeded$.MODULE$:Lorg/scalatest/Succeeded$;
         3: invokevirtual #48                 // Method org/scalatest/Succeeded$.toSucceeded:()Lorg/scalatest/Succeeded$;
         6: areturn

  public static boolean isSucceeded();
    descriptor: ()Z
    flags: (0x0009) ACC_PUBLIC, ACC_STATIC
    Code:
      stack=1, locals=0, args_size=0
         0: getstatic     #16                 // Field org/scalatest/Succeeded$.MODULE$:Lorg/scalatest/Succeeded$;
         3: invokevirtual #52                 // Method org/scalatest/Succeeded$.isSucceeded:()Z
         6: ireturn

  public static scala.Option<java.lang.Throwable> toOption();
    descriptor: ()Lscala/Option;
    flags: (0x0009) ACC_PUBLIC, ACC_STATIC
    Code:
      stack=1, locals=0, args_size=0
         0: getstatic     #16                 // Field org/scalatest/Succeeded$.MODULE$:Lorg/scalatest/Succeeded$;
         3: invokevirtual #57                 // Method org/scalatest/Succeeded$.toOption:()Lscala/Option;
         6: areturn
    Signature: #55                          // ()Lscala/Option<Ljava/lang/Throwable;>;

  public static boolean isExceptional();
    descriptor: ()Z
    flags: (0x0009) ACC_PUBLIC, ACC_STATIC
    Code:
      stack=1, locals=0, args_size=0
         0: getstatic     #16                 // Field org/scalatest/Succeeded$.MODULE$:Lorg/scalatest/Succeeded$;
         3: invokevirtual #60                 // Method org/scalatest/Succeeded$.isExceptional:()Z
         6: ireturn

  public static boolean isPending();
    descriptor: ()Z
    flags: (0x0009) ACC_PUBLIC, ACC_STATIC
    Code:
      stack=1, locals=0, args_size=0
         0: getstatic     #16                 // Field org/scalatest/Succeeded$.MODULE$:Lorg/scalatest/Succeeded$;
         3: invokevirtual #63                 // Method org/scalatest/Succeeded$.isPending:()Z
         6: ireturn

  public static boolean isCanceled();
    descriptor: ()Z
    flags: (0x0009) ACC_PUBLIC, ACC_STATIC
    Code:
      stack=1, locals=0, args_size=0
         0: getstatic     #16                 // Field org/scalatest/Succeeded$.MODULE$:Lorg/scalatest/Succeeded$;
         3: invokevirtual #66                 // Method org/scalatest/Succeeded$.isCanceled:()Z
         6: ireturn

  public static boolean isFailed();
    descriptor: ()Z
    flags: (0x0009) ACC_PUBLIC, ACC_STATIC
    Code:
      stack=1, locals=0, args_size=0
         0: getstatic     #16                 // Field org/scalatest/Succeeded$.MODULE$:Lorg/scalatest/Succeeded$;
         3: invokevirtual #69                 // Method org/scalatest/Succeeded$.isFailed:()Z
         6: ireturn

  public static scala.collection.Iterator<java.lang.String> productElementNames();
    descriptor: ()Lscala/collection/Iterator;
    flags: (0x0009) ACC_PUBLIC, ACC_STATIC
    Code:
      stack=1, locals=0, args_size=0
         0: getstatic     #16                 // Field org/scalatest/Succeeded$.MODULE$:Lorg/scalatest/Succeeded$;
         3: invokevirtual #73                 // Method org/scalatest/Succeeded$.productElementNames:()Lscala/collection/Iterator;
         6: areturn
    Signature: #71                          // ()Lscala/collection/Iterator<Ljava/lang/String;>;

  public static java.lang.String productElementName(int);
    descriptor: (I)Ljava/lang/String;
    flags: (0x0009) ACC_PUBLIC, ACC_STATIC
    Code:
      stack=2, locals=1, args_size=1
         0: getstatic     #16                 // Field org/scalatest/Succeeded$.MODULE$:Lorg/scalatest/Succeeded$;
         3: iload_0
         4: invokevirtual #78                 // Method org/scalatest/Succeeded$.productElementName:(I)Ljava/lang/String;
         7: areturn
      LocalVariableTable:
        Start  Length  Slot  Name   Signature
            0       8     0     n   I
    MethodParameters:
      Name                           Flags
      n                              final
}
SourceFile: "Outcome.scala"
RuntimeVisibleAnnotations:
  0: #6(#7=s#8)
    scala.reflect.ScalaSignature(
      bytes="\u0006\u0005!<QAD\b\t\u0002R1QAF\b\t\u0002^AQaM\u0001\u0005\u0002QBq!N\u0001C\u0002\u0013\u0005c\u0007\u0003\u0004;\u0003\u0001\u0006Ia\u000e\u0005\u0006w\u0005!\t\u0001\u0010\u0005\b}\u0005\t\t\u0011\"\u0011@\u0011\u001dA\u0015!!A\u0005\u0002%Cq!T\u0001\u0002\u0002\u0013\u0005a\nC\u0004U\u0003\u0005\u0005I\u0011I+\t\u000fq\u000b\u0011\u0011!C\u0001;\"9q,AA\u0001\n\u0003\u0002\u0007bB1\u0002\u0003\u0003%\tE\u0019\u0005\bG\u0006\t\t\u0011\"\u0003e\u0003%\u0019VoY2fK\u0012,GM\u0003\u0002\u0011#\u0005I1oY1mCR,7\u000f\u001e\u0006\u0002%\u0005\u0019qN]4\u0004\u0001A\u0011Q#A\u0007\u0002\u001f\tI1+^2dK\u0016$W\rZ\n\u0006\u0003aY\u0012e\n\t\u0003+eI!AG\b\u0003\u000f=+HoY8nKB\u0011AdH\u0007\u0002;)\u0011adD\u0001\u000bG>l\u0007/\u0019;jE2,\u0017B\u0001\u0011\u001e\u0005%\t5o]3si&|g\u000e\u0005\u0002#K5\t1EC\u0001%\u0003\u0015\u00198-\u00197b\u0013\t13EA\u0004Qe>$Wo\u0019;\u0011\u0005!\u0002dBA\u0015/\u001d\tQS&D\u0001,\u0015\ta3#\u0001\u0004=e>|GOP\u0005\u0002I%\u0011qfI\u0001\ba\u0006\u001c7.Y4f\u0013\t\t$G\u0001\u0007TKJL\u0017\r\\5{C\ndWM\u0003\u00020G\u00051A(\u001b8jiz\"\u0012\u0001F\u0001\fSN\u001cVoY2fK\u0012,G-F\u00018!\t\u0011\u0003(\u0003\u0002:G\t9!i\\8mK\u0006t\u0017\u0001D5t\'V\u001c7-Z3eK\u0012\u0004\u0013a\u0003;p\'V\u001c7-Z3eK\u0012,\u0012!\u0010\b\u0003+\u0001\tQ\u0002\u001d:pIV\u001cG\u000f\u0015:fM&DX#\u0001!\u0011\u0005\u00053U\"\u0001\"\u000b\u0005\r#\u0015\u0001\u00027b]\u001eT\u0011!R\u0001\u0005U\u00064\u0018-\u0003\u0002H\u0005\n11\u000b\u001e:j]\u001e\fA\u0002\u001d:pIV\u001cG/\u0011:jif,\u0012A\u0013\t\u0003E-K!\u0001T\u0012\u0003\u0007%sG/\u0001\bqe>$Wo\u0019;FY\u0016lWM\u001c;\u0015\u0005=\u0013\u0006C\u0001\u0012Q\u0013\t\t6EA\u0002B]fDqa\u0015\u0005\u0002\u0002\u0003\u0007!*A\u0002yIE\nq\u0002\u001d:pIV\u001cG/\u0013;fe\u0006$xN]\u000b\u0002-B\u0019qKW(\u000e\u0003aS!!W\u0012\u0002\u0015\r|G\u000e\\3di&|g.\u0003\u0002\\1\nA\u0011\n^3sCR|\'/\u0001\u0005dC:,\u0015/^1m)\t9d\fC\u0004T\u0015\u0005\u0005\t\u0019A(\u0002\u0011!\f7\u000f[\"pI\u0016$\u0012AS\u0001\ti>\u001cFO]5oOR\t\u0001)\u0001\u0007xe&$XMU3qY\u0006\u001cW\rF\u0001f!\t\te-\u0003\u0002h\u0005\n1qJ\u00196fGR\u0004"
    )
  ScalaSig: length = 0x3 (unknown attribute)
   05 02 00
