Classfile /Users/mw/Projects/slang-braindump/.jar/jar11/assemble/slang-braindump/assemble/content/org/scalatest/SuiteRerunner.class
  Last modified May 29, 2022; size 11417 bytes
  SHA-256 checksum 4b3f29fc451d3ece405737f6298bd4d022d5de0a9a78b351cfdad6fff86dbad6
  Compiled from "SuiteRerunner.scala"
public class org.scalatest.SuiteRerunner implements org.scalatest.Rerunner,java.io.Serializable
  minor version: 0
  major version: 52
  flags: (0x0021) ACC_PUBLIC, ACC_SUPER
  this_class: #2                          // org/scalatest/SuiteRerunner
  super_class: #4                         // java/lang/Object
  interfaces: 2, fields: 1, methods: 2, attributes: 5
Constant pool:
    #1 = Utf8               org/scalatest/SuiteRerunner
    #2 = Class              #1            // org/scalatest/SuiteRerunner
    #3 = Utf8               java/lang/Object
    #4 = Class              #3            // java/lang/Object
    #5 = Utf8               org/scalatest/Rerunner
    #6 = Class              #5            // org/scalatest/Rerunner
    #7 = Utf8               java/io/Serializable
    #8 = Class              #7            // java/io/Serializable
    #9 = Utf8               SuiteRerunner.scala
   #10 = Utf8               Lscala/reflect/ScalaSignature;
   #11 = Utf8               bytes
   #12 = Utf8               \u0006\u0005m3Q\u0001B\u0003\u0001\u000b%A\u0001\u0002\b\u0001\u0003\u0002\u0003\u0006IA\b\u0005\u0006S\u0001!\tA\u000b\u0005\u0006[\u0001!\tA\f\u0002\u000e\'VLG/\u001a*feVtg.\u001a:\u000b\u0005\u00199\u0011!C:dC2\fG/Z:u\u0015\u0005A\u0011aA8sON!\u0001A\u0003\t\u0015!\tYa\"D\u0001\r\u0015\u0005i\u0011!B:dC2\f\u0017BA\b\r\u0005\u0019\te.\u001f*fMB\u0011\u0011CE\u0007\u0002\u000b%\u00111#\u0002\u0002\t%\u0016\u0014XO\u001c8feB\u0011QCG\u0007\u0002-)\u0011q\u0003G\u0001\u0003S>T\u0011!G\u0001\u0005U\u00064\u0018-\u0003\u0002\u001c-\ta1+\u001a:jC2L\'0\u00192mK\u0006q1/^5uK\u000ec\u0017m]:OC6,7\u0001\u0001\t\u0003?\u0019r!\u0001\t\u0013\u0011\u0005\u0005bQ\"\u0001\u0012\u000b\u0005\rj\u0012A\u0002\u001fs_>$h(\u0003\u0002&\u0019\u00051\u0001K]3eK\u001aL!a\n\u0015\u0003\rM#(/\u001b8h\u0015\t)C\"\u0001\u0004=S:LGO\u0010\u000b\u0003W1\u0002\"!\u0005\u0001\t\u000bq\u0011\u0001\u0019\u0001\u0010\u0002\u000b\u0005\u0004\b\u000f\\=\u0015\u0011=\u0012t\u0007P!G\u001dN\u0003\"a\u0003\u0019\n\u0005Eb!\u0001B+oSRDQaM\u0002A\u0002Q\naA]3q_J$\bCA\t6\u0013\t1TA\u0001\u0005SKB|\'\u000f^3s\u0011\u0015A4\u00011\u0001:\u0003\u001d\u0019Ho\u001c9qKJ\u0004\"!\u0005\u001e\n\u0005m*!aB*u_B\u0004XM\u001d\u0005\u0006{\r\u0001\rAP\u0001\u0007M&dG/\u001a:\u0011\u0005Ey\u0014B\u0001!\u0006\u0005\u00191\u0015\u000e\u001c;fe\")!i\u0001a\u0001\u0007\u0006I1m\u001c8gS\u001el\u0015\r\u001d\t\u0003#\u0011K!!R\u0003\u0003\u0013\r{gNZ5h\u001b\u0006\u0004\b\"B$\u0004\u0001\u0004A\u0015a\u00033jgR\u0014\u0018NY;u_J\u00042aC%L\u0013\tQEB\u0001\u0004PaRLwN\u001c\t\u0003#1K!!T\u0003\u0003\u0017\u0011K7\u000f\u001e:jEV$xN\u001d\u0005\u0006\u001f\u000e\u0001\r\u0001U\u0001\biJ\f7m[3s!\t\t\u0012+\u0003\u0002S\u000b\t9AK]1dW\u0016\u0014\b\"\u0002+\u0004\u0001\u0004)\u0016A\u00027pC\u0012,\'\u000f\u0005\u0002W36\tqK\u0003\u0002Y1\u0005!A.\u00198h\u0013\tQvKA\u0006DY\u0006\u001c8\u000fT8bI\u0016\u0014\b
   #13 = Utf8               org/scalactic/Requirements$RequirementsHelper
   #14 = Class              #13           // org/scalactic/Requirements$RequirementsHelper
   #15 = Utf8               org/scalactic/Requirements
   #16 = Class              #15           // org/scalactic/Requirements
   #17 = Utf8               RequirementsHelper
   #18 = Utf8               suiteClassName
   #19 = Utf8               Ljava/lang/String;
   #20 = Utf8               apply
   #21 = Utf8               (Lorg/scalatest/Reporter;Lorg/scalatest/Stopper;Lorg/scalatest/Filter;Lorg/scalatest/ConfigMap;Lscala/Option;Lorg/scalatest/Tracker;Ljava/lang/ClassLoader;)V
   #22 = Utf8               (Lorg/scalatest/Reporter;Lorg/scalatest/Stopper;Lorg/scalatest/Filter;Lorg/scalatest/ConfigMap;Lscala/Option<Lorg/scalatest/Distributor;>;Lorg/scalatest/Tracker;Ljava/lang/ClassLoader;)V
   #23 = Utf8               report
   #24 = Utf8               stopper
   #25 = Utf8               filter
   #26 = Utf8               configMap
   #27 = Utf8               distributor
   #28 = Utf8               tracker
   #29 = Utf8               loader
   #30 = Utf8               java/lang/RuntimeException
   #31 = Class              #30           // java/lang/RuntimeException
   #32 = Utf8               java/lang/ClassNotFoundException
   #33 = Class              #32           // java/lang/ClassNotFoundException
   #34 = Utf8               java/lang/InstantiationException
   #35 = Class              #34           // java/lang/InstantiationException
   #36 = Utf8               java/lang/IllegalAccessException
   #37 = Class              #36           // java/lang/IllegalAccessException
   #38 = Utf8               java/lang/SecurityException
   #39 = Class              #38           // java/lang/SecurityException
   #40 = Utf8               java/lang/NoClassDefFoundError
   #41 = Class              #40           // java/lang/NoClassDefFoundError
   #42 = Utf8               java/lang/Throwable
   #43 = Class              #42           // java/lang/Throwable
   #44 = Utf8               org/scalatest/Filter
   #45 = Class              #44           // org/scalatest/Filter
   #46 = Utf8               tagsToInclude
   #47 = Utf8               ()Lscala/Option;
   #48 = NameAndType        #46:#47       // tagsToInclude:()Lscala/Option;
   #49 = Methodref          #45.#48       // org/scalatest/Filter.tagsToInclude:()Lscala/Option;
   #50 = Utf8               scala/None$
   #51 = Class              #50           // scala/None$
   #52 = Utf8               MODULE$
   #53 = Utf8               Lscala/None$;
   #54 = NameAndType        #52:#53       // MODULE$:Lscala/None$;
   #55 = Fieldref           #51.#54       // scala/None$.MODULE$:Lscala/None$;
   #56 = Utf8               equals
   #57 = Utf8               (Ljava/lang/Object;)Z
   #58 = NameAndType        #56:#57       // equals:(Ljava/lang/Object;)Z
   #59 = Methodref          #4.#58        // java/lang/Object.equals:(Ljava/lang/Object;)Z
   #60 = Utf8               scala/Predef$
   #61 = Class              #60           // scala/Predef$
   #62 = Utf8               Lscala/Predef$;
   #63 = NameAndType        #52:#62       // MODULE$:Lscala/Predef$;
   #64 = Fieldref           #61.#63       // scala/Predef$.MODULE$:Lscala/Predef$;
   #65 = Utf8               Set
   #66 = Utf8               ()Lscala/collection/immutable/Set$;
   #67 = NameAndType        #65:#66       // Set:()Lscala/collection/immutable/Set$;
   #68 = Methodref          #61.#67       // scala/Predef$.Set:()Lscala/collection/immutable/Set$;
   #69 = Utf8               scala/collection/immutable/Nil$
   #70 = Class              #69           // scala/collection/immutable/Nil$
   #71 = Utf8               Lscala/collection/immutable/Nil$;
   #72 = NameAndType        #52:#71       // MODULE$:Lscala/collection/immutable/Nil$;
   #73 = Fieldref           #70.#72       // scala/collection/immutable/Nil$.MODULE$:Lscala/collection/immutable/Nil$;
   #74 = Utf8               scala/collection/immutable/Set$
   #75 = Class              #74           // scala/collection/immutable/Set$
   #76 = Utf8               (Lscala/collection/immutable/Seq;)Ljava/lang/Object;
   #77 = NameAndType        #20:#76       // apply:(Lscala/collection/immutable/Seq;)Ljava/lang/Object;
   #78 = Methodref          #75.#77       // scala/collection/immutable/Set$.apply:(Lscala/collection/immutable/Seq;)Ljava/lang/Object;
   #79 = Utf8               scala/collection/immutable/Set
   #80 = Class              #79           // scala/collection/immutable/Set
   #81 = Utf8               scala/Some
   #82 = Class              #81           // scala/Some
   #83 = Utf8               value
   #84 = Utf8               ()Ljava/lang/Object;
   #85 = NameAndType        #83:#84       // value:()Ljava/lang/Object;
   #86 = Methodref          #82.#85       // scala/Some.value:()Ljava/lang/Object;
   #87 = Utf8               scala/MatchError
   #88 = Class              #87           // scala/MatchError
   #89 = Utf8               <init>
   #90 = Utf8               (Ljava/lang/Object;)V
   #91 = NameAndType        #89:#90       // "<init>":(Ljava/lang/Object;)V
   #92 = Methodref          #88.#91       // scala/MatchError."<init>":(Ljava/lang/Object;)V
   #93 = Utf8               tagsToExclude
   #94 = Utf8               ()Lscala/collection/immutable/Set;
   #95 = NameAndType        #93:#94       // tagsToExclude:()Lscala/collection/immutable/Set;
   #96 = Methodref          #45.#95       // org/scalatest/Filter.tagsToExclude:()Lscala/collection/immutable/Set;
   #97 = Utf8               java/lang/System
   #98 = Class              #97           // java/lang/System
   #99 = Utf8               currentTimeMillis
  #100 = Utf8               ()J
  #101 = NameAndType        #99:#100      // currentTimeMillis:()J
  #102 = Methodref          #98.#101      // java/lang/System.currentTimeMillis:()J
  #103 = NameAndType        #18:#19       // suiteClassName:Ljava/lang/String;
  #104 = Fieldref           #2.#103       // org/scalatest/SuiteRerunner.suiteClassName:Ljava/lang/String;
  #105 = Utf8               java/lang/ClassLoader
  #106 = Class              #105          // java/lang/ClassLoader
  #107 = Utf8               loadClass
  #108 = Utf8               (Ljava/lang/String;)Ljava/lang/Class;
  #109 = NameAndType        #107:#108     // loadClass:(Ljava/lang/String;)Ljava/lang/Class;
  #110 = Methodref          #106.#109     // java/lang/ClassLoader.loadClass:(Ljava/lang/String;)Ljava/lang/Class;
  #111 = Utf8               java/lang/Class
  #112 = Class              #111          // java/lang/Class
  #113 = Utf8               newInstance
  #114 = NameAndType        #113:#84      // newInstance:()Ljava/lang/Object;
  #115 = Methodref          #112.#114     // java/lang/Class.newInstance:()Ljava/lang/Object;
  #116 = Utf8               org/scalatest/Suite
  #117 = Class              #116          // org/scalatest/Suite
  #118 = Utf8               expectedTestCount
  #119 = Utf8               (Lorg/scalatest/Filter;)I
  #120 = NameAndType        #118:#119     // expectedTestCount:(Lorg/scalatest/Filter;)I
  #121 = InterfaceMethodref #117.#120     // org/scalatest/Suite.expectedTestCount:(Lorg/scalatest/Filter;)I
  #122 = Utf8               org/scalatest/Suite$
  #123 = Class              #122          // org/scalatest/Suite$
  #124 = Utf8               Lorg/scalatest/Suite$;
  #125 = NameAndType        #52:#124      // MODULE$:Lorg/scalatest/Suite$;
  #126 = Fieldref           #123.#125     // org/scalatest/Suite$.MODULE$:Lorg/scalatest/Suite$;
  #127 = Utf8               getClass
  #128 = Utf8               ()Ljava/lang/Class;
  #129 = NameAndType        #127:#128     // getClass:()Ljava/lang/Class;
  #130 = Methodref          #4.#129       // java/lang/Object.getClass:()Ljava/lang/Class;
  #131 = Utf8               checkForPublicNoArgConstructor
  #132 = Utf8               (Ljava/lang/Class;)Z
  #133 = NameAndType        #131:#132     // checkForPublicNoArgConstructor:(Ljava/lang/Class;)Z
  #134 = Methodref          #123.#133     // org/scalatest/Suite$.checkForPublicNoArgConstructor:(Ljava/lang/Class;)Z
  #135 = Utf8               getName
  #136 = Utf8               ()Ljava/lang/String;
  #137 = NameAndType        #135:#136     // getName:()Ljava/lang/String;
  #138 = Methodref          #112.#137     // java/lang/Class.getName:()Ljava/lang/String;
  #139 = Utf8               (Ljava/lang/String;)V
  #140 = NameAndType        #89:#139      // "<init>":(Ljava/lang/String;)V
  #141 = Methodref          #2.#140       // org/scalatest/SuiteRerunner."<init>":(Ljava/lang/String;)V
  #142 = Methodref          #82.#91       // scala/Some."<init>":(Ljava/lang/Object;)V
  #143 = Utf8               org/scalatest/events/RunStarting
  #144 = Class              #143          // org/scalatest/events/RunStarting
  #145 = Utf8               org/scalatest/Tracker
  #146 = Class              #145          // org/scalatest/Tracker
  #147 = Utf8               nextOrdinal
  #148 = Utf8               ()Lorg/scalatest/events/Ordinal;
  #149 = NameAndType        #147:#148     // nextOrdinal:()Lorg/scalatest/events/Ordinal;
  #150 = Methodref          #146.#149     // org/scalatest/Tracker.nextOrdinal:()Lorg/scalatest/events/Ordinal;
  #151 = Utf8               org/scalatest/events/RunStarting$
  #152 = Class              #151          // org/scalatest/events/RunStarting$
  #153 = Utf8               Lorg/scalatest/events/RunStarting$;
  #154 = NameAndType        #52:#153      // MODULE$:Lorg/scalatest/events/RunStarting$;
  #155 = Fieldref           #152.#154     // org/scalatest/events/RunStarting$.MODULE$:Lorg/scalatest/events/RunStarting$;
  #156 = Utf8               apply$default$4
  #157 = NameAndType        #156:#47      // apply$default$4:()Lscala/Option;
  #158 = Methodref          #152.#157     // org/scalatest/events/RunStarting$.apply$default$4:()Lscala/Option;
  #159 = Utf8               apply$default$5
  #160 = NameAndType        #159:#47      // apply$default$5:()Lscala/Option;
  #161 = Methodref          #152.#160     // org/scalatest/events/RunStarting$.apply$default$5:()Lscala/Option;
  #162 = Utf8               apply$default$6
  #163 = NameAndType        #162:#47      // apply$default$6:()Lscala/Option;
  #164 = Methodref          #152.#163     // org/scalatest/events/RunStarting$.apply$default$6:()Lscala/Option;
  #165 = Utf8               apply$default$7
  #166 = NameAndType        #165:#136     // apply$default$7:()Ljava/lang/String;
  #167 = Methodref          #152.#166     // org/scalatest/events/RunStarting$.apply$default$7:()Ljava/lang/String;
  #168 = Utf8               apply$default$8
  #169 = NameAndType        #168:#100     // apply$default$8:()J
  #170 = Methodref          #152.#169     // org/scalatest/events/RunStarting$.apply$default$8:()J
  #171 = Utf8               (Lorg/scalatest/events/Ordinal;ILorg/scalatest/ConfigMap;Lscala/Option;Lscala/Option;Lscala/Option;Ljava/lang/String;J)V
  #172 = NameAndType        #89:#171      // "<init>":(Lorg/scalatest/events/Ordinal;ILorg/scalatest/ConfigMap;Lscala/Option;Lscala/Option;Lscala/Option;Ljava/lang/String;J)V
  #173 = Methodref          #144.#172     // org/scalatest/events/RunStarting."<init>":(Lorg/scalatest/events/Ordinal;ILorg/scalatest/ConfigMap;Lscala/Option;Lscala/Option;Lscala/Option;Ljava/lang/String;J)V
  #174 = Utf8               org/scalatest/Reporter
  #175 = Class              #174          // org/scalatest/Reporter
  #176 = Utf8               (Lorg/scalatest/events/Event;)V
  #177 = NameAndType        #20:#176      // apply:(Lorg/scalatest/events/Event;)V
  #178 = InterfaceMethodref #175.#177     // org/scalatest/Reporter.apply:(Lorg/scalatest/events/Event;)V
  #179 = Utf8               org/scalatest/Resources$
  #180 = Class              #179          // org/scalatest/Resources$
  #181 = Utf8               Lorg/scalatest/Resources$;
  #182 = NameAndType        #52:#181      // MODULE$:Lorg/scalatest/Resources$;
  #183 = Fieldref           #180.#182     // org/scalatest/Resources$.MODULE$:Lorg/scalatest/Resources$;
  #184 = Utf8               suiteExecutionStarting
  #185 = NameAndType        #184:#136     // suiteExecutionStarting:()Ljava/lang/String;
  #186 = Methodref          #180.#185     // org/scalatest/Resources$.suiteExecutionStarting:()Ljava/lang/String;
  #187 = Utf8               formatterForSuiteStarting
  #188 = Utf8               (Lorg/scalatest/Suite;)Lscala/Option;
  #189 = NameAndType        #187:#188     // formatterForSuiteStarting:(Lorg/scalatest/Suite;)Lscala/Option;
  #190 = Methodref          #123.#189     // org/scalatest/Suite$.formatterForSuiteStarting:(Lorg/scalatest/Suite;)Lscala/Option;
  #191 = Utf8               org/scalatest/events/SuiteStarting
  #192 = Class              #191          // org/scalatest/events/SuiteStarting
  #193 = Utf8               suiteName
  #194 = NameAndType        #193:#136     // suiteName:()Ljava/lang/String;
  #195 = InterfaceMethodref #117.#194     // org/scalatest/Suite.suiteName:()Ljava/lang/String;
  #196 = Utf8               suiteId
  #197 = NameAndType        #196:#136     // suiteId:()Ljava/lang/String;
  #198 = InterfaceMethodref #117.#197     // org/scalatest/Suite.suiteId:()Ljava/lang/String;
  #199 = Utf8               org/scalatest/events/TopOfClass
  #200 = Class              #199          // org/scalatest/events/TopOfClass
  #201 = Methodref          #200.#140     // org/scalatest/events/TopOfClass."<init>":(Ljava/lang/String;)V
  #202 = Utf8               rerunner
  #203 = NameAndType        #202:#47      // rerunner:()Lscala/Option;
  #204 = InterfaceMethodref #117.#203     // org/scalatest/Suite.rerunner:()Lscala/Option;
  #205 = Utf8               org/scalatest/events/SuiteStarting$
  #206 = Class              #205          // org/scalatest/events/SuiteStarting$
  #207 = Utf8               Lorg/scalatest/events/SuiteStarting$;
  #208 = NameAndType        #52:#207      // MODULE$:Lorg/scalatest/events/SuiteStarting$;
  #209 = Fieldref           #206.#208     // org/scalatest/events/SuiteStarting$.MODULE$:Lorg/scalatest/events/SuiteStarting$;
  #210 = NameAndType        #168:#47      // apply$default$8:()Lscala/Option;
  #211 = Methodref          #206.#210     // org/scalatest/events/SuiteStarting$.apply$default$8:()Lscala/Option;
  #212 = Utf8               apply$default$9
  #213 = NameAndType        #212:#136     // apply$default$9:()Ljava/lang/String;
  #214 = Methodref          #206.#213     // org/scalatest/events/SuiteStarting$.apply$default$9:()Ljava/lang/String;
  #215 = Utf8               apply$default$10
  #216 = NameAndType        #215:#100     // apply$default$10:()J
  #217 = Methodref          #206.#216     // org/scalatest/events/SuiteStarting$.apply$default$10:()J
  #218 = Utf8               (Lorg/scalatest/events/Ordinal;Ljava/lang/String;Ljava/lang/String;Lscala/Option;Lscala/Option;Lscala/Option;Lscala/Option;Lscala/Option;Ljava/lang/String;J)V
  #219 = NameAndType        #89:#218      // "<init>":(Lorg/scalatest/events/Ordinal;Ljava/lang/String;Ljava/lang/String;Lscala/Option;Lscala/Option;Lscala/Option;Lscala/Option;Lscala/Option;Ljava/lang/String;J)V
  #220 = Methodref          #192.#219     // org/scalatest/events/SuiteStarting."<init>":(Lorg/scalatest/events/Ordinal;Ljava/lang/String;Ljava/lang/String;Lscala/Option;Lscala/Option;Lscala/Option;Lscala/Option;Lscala/Option;Ljava/lang/String;J)V
  #221 = Utf8               org/scalatest/Args
  #222 = Class              #221          // org/scalatest/Args
  #223 = Utf8               empty
  #224 = NameAndType        #223:#94      // empty:()Lscala/collection/immutable/Set;
  #225 = Methodref          #75.#224      // scala/collection/immutable/Set$.empty:()Lscala/collection/immutable/Set;
  #226 = Utf8               org/scalatest/Args$
  #227 = Class              #226          // org/scalatest/Args$
  #228 = Utf8               Lorg/scalatest/Args$;
  #229 = NameAndType        #52:#228      // MODULE$:Lorg/scalatest/Args$;
  #230 = Fieldref           #227.#229     // org/scalatest/Args$.MODULE$:Lorg/scalatest/Args$;
  #231 = Utf8               ()Z
  #232 = NameAndType        #168:#231     // apply$default$8:()Z
  #233 = Methodref          #227.#232     // org/scalatest/Args$.apply$default$8:()Z
  #234 = NameAndType        #212:#47      // apply$default$9:()Lscala/Option;
  #235 = Methodref          #227.#234     // org/scalatest/Args$.apply$default$9:()Lscala/Option;
  #236 = NameAndType        #215:#47      // apply$default$10:()Lscala/Option;
  #237 = Methodref          #227.#236     // org/scalatest/Args$.apply$default$10:()Lscala/Option;
  #238 = Utf8               (Lorg/scalatest/Reporter;Lorg/scalatest/Stopper;Lorg/scalatest/Filter;Lorg/scalatest/ConfigMap;Lscala/Option;Lorg/scalatest/Tracker;Lscala/collection/immutable/Set;ZLscala/Option;Lscala/Option;)V
  #239 = NameAndType        #89:#238      // "<init>":(Lorg/scalatest/Reporter;Lorg/scalatest/Stopper;Lorg/scalatest/Filter;Lorg/scalatest/ConfigMap;Lscala/Option;Lorg/scalatest/Tracker;Lscala/collection/immutable/Set;ZLscala/Option;Lscala/Option;)V
  #240 = Methodref          #222.#239     // org/scalatest/Args."<init>":(Lorg/scalatest/Reporter;Lorg/scalatest/Stopper;Lorg/scalatest/Filter;Lorg/scalatest/ConfigMap;Lscala/Option;Lorg/scalatest/Tracker;Lscala/collection/immutable/Set;ZLscala/Option;Lscala/Option;)V
  #241 = Utf8               run
  #242 = Utf8               (Lscala/Option;Lorg/scalatest/Args;)Lorg/scalatest/Status;
  #243 = NameAndType        #241:#242     // run:(Lscala/Option;Lorg/scalatest/Args;)Lorg/scalatest/Status;
  #244 = InterfaceMethodref #117.#243     // org/scalatest/Suite.run:(Lscala/Option;Lorg/scalatest/Args;)Lorg/scalatest/Status;
  #245 = Utf8               suiteCompletedNormally
  #246 = NameAndType        #245:#136     // suiteCompletedNormally:()Ljava/lang/String;
  #247 = Methodref          #180.#246     // org/scalatest/Resources$.suiteCompletedNormally:()Ljava/lang/String;
  #248 = Utf8               formatterForSuiteCompleted
  #249 = NameAndType        #248:#188     // formatterForSuiteCompleted:(Lorg/scalatest/Suite;)Lscala/Option;
  #250 = Methodref          #123.#249     // org/scalatest/Suite$.formatterForSuiteCompleted:(Lorg/scalatest/Suite;)Lscala/Option;
  #251 = Utf8               org/scalatest/events/SuiteCompleted
  #252 = Class              #251          // org/scalatest/events/SuiteCompleted
  #253 = Utf8               scala/runtime/BoxesRunTime
  #254 = Class              #253          // scala/runtime/BoxesRunTime
  #255 = Utf8               boxToLong
  #256 = Utf8               (J)Ljava/lang/Long;
  #257 = NameAndType        #255:#256     // boxToLong:(J)Ljava/lang/Long;
  #258 = Methodref          #254.#257     // scala/runtime/BoxesRunTime.boxToLong:(J)Ljava/lang/Long;
  #259 = Utf8               org/scalatest/events/SuiteCompleted$
  #260 = Class              #259          // org/scalatest/events/SuiteCompleted$
  #261 = Utf8               Lorg/scalatest/events/SuiteCompleted$;
  #262 = NameAndType        #52:#261      // MODULE$:Lorg/scalatest/events/SuiteCompleted$;
  #263 = Fieldref           #260.#262     // org/scalatest/events/SuiteCompleted$.MODULE$:Lorg/scalatest/events/SuiteCompleted$;
  #264 = Methodref          #260.#234     // org/scalatest/events/SuiteCompleted$.apply$default$9:()Lscala/Option;
  #265 = NameAndType        #215:#136     // apply$default$10:()Ljava/lang/String;
  #266 = Methodref          #260.#265     // org/scalatest/events/SuiteCompleted$.apply$default$10:()Ljava/lang/String;
  #267 = Utf8               apply$default$11
  #268 = NameAndType        #267:#100     // apply$default$11:()J
  #269 = Methodref          #260.#268     // org/scalatest/events/SuiteCompleted$.apply$default$11:()J
  #270 = Utf8               (Lorg/scalatest/events/Ordinal;Ljava/lang/String;Ljava/lang/String;Lscala/Option;Lscala/Option;Lscala/Option;Lscala/Option;Lscala/Option;Lscala/Option;Ljava/lang/String;J)V
  #271 = NameAndType        #89:#270      // "<init>":(Lorg/scalatest/events/Ordinal;Ljava/lang/String;Ljava/lang/String;Lscala/Option;Lscala/Option;Lscala/Option;Lscala/Option;Lscala/Option;Lscala/Option;Ljava/lang/String;J)V
  #272 = Methodref          #252.#271     // org/scalatest/events/SuiteCompleted."<init>":(Lorg/scalatest/events/Ordinal;Ljava/lang/String;Ljava/lang/String;Lscala/Option;Lscala/Option;Lscala/Option;Lscala/Option;Lscala/Option;Lscala/Option;Ljava/lang/String;J)V
  #273 = Utf8               getMessage
  #274 = NameAndType        #273:#136     // getMessage:()Ljava/lang/String;
  #275 = Methodref          #31.#274      // java/lang/RuntimeException.getMessage:()Ljava/lang/String;
  #276 = Utf8               java/lang/String
  #277 = Class              #276          // java/lang/String
  #278 = Utf8               length
  #279 = Utf8               ()I
  #280 = NameAndType        #278:#279     // length:()I
  #281 = Methodref          #277.#280     // java/lang/String.length:()I
  #282 = Utf8               executeExceptionWithMessage
  #283 = Utf8               (Ljava/lang/Object;)Ljava/lang/String;
  #284 = NameAndType        #282:#283     // executeExceptionWithMessage:(Ljava/lang/Object;)Ljava/lang/String;
  #285 = Methodref          #180.#284     // org/scalatest/Resources$.executeExceptionWithMessage:(Ljava/lang/Object;)Ljava/lang/String;
  #286 = Utf8               executeException
  #287 = NameAndType        #286:#136     // executeException:()Ljava/lang/String;
  #288 = Methodref          #180.#287     // org/scalatest/Resources$.executeException:()Ljava/lang/String;
  #289 = Utf8               formatterForSuiteAborted
  #290 = Utf8               (Lorg/scalatest/Suite;Ljava/lang/String;)Lscala/Option;
  #291 = NameAndType        #289:#290     // formatterForSuiteAborted:(Lorg/scalatest/Suite;Ljava/lang/String;)Lscala/Option;
  #292 = Methodref          #123.#291     // org/scalatest/Suite$.formatterForSuiteAborted:(Lorg/scalatest/Suite;Ljava/lang/String;)Lscala/Option;
  #293 = Utf8               org/scalatest/events/SuiteAborted
  #294 = Class              #293          // org/scalatest/events/SuiteAborted
  #295 = Utf8               org/scalatest/events/SeeStackDepthException$
  #296 = Class              #295          // org/scalatest/events/SeeStackDepthException$
  #297 = Utf8               Lorg/scalatest/events/SeeStackDepthException$;
  #298 = NameAndType        #52:#297      // MODULE$:Lorg/scalatest/events/SeeStackDepthException$;
  #299 = Fieldref           #296.#298     // org/scalatest/events/SeeStackDepthException$.MODULE$:Lorg/scalatest/events/SeeStackDepthException$;
  #300 = Utf8               org/scalatest/events/SuiteAborted$
  #301 = Class              #300          // org/scalatest/events/SuiteAborted$
  #302 = Utf8               Lorg/scalatest/events/SuiteAborted$;
  #303 = NameAndType        #52:#302      // MODULE$:Lorg/scalatest/events/SuiteAborted$;
  #304 = Fieldref           #301.#303     // org/scalatest/events/SuiteAborted$.MODULE$:Lorg/scalatest/events/SuiteAborted$;
  #305 = NameAndType        #267:#47      // apply$default$11:()Lscala/Option;
  #306 = Methodref          #301.#305     // org/scalatest/events/SuiteAborted$.apply$default$11:()Lscala/Option;
  #307 = Utf8               apply$default$12
  #308 = NameAndType        #307:#136     // apply$default$12:()Ljava/lang/String;
  #309 = Methodref          #301.#308     // org/scalatest/events/SuiteAborted$.apply$default$12:()Ljava/lang/String;
  #310 = Utf8               apply$default$13
  #311 = NameAndType        #310:#100     // apply$default$13:()J
  #312 = Methodref          #301.#311     // org/scalatest/events/SuiteAborted$.apply$default$13:()J
  #313 = Utf8               (Lorg/scalatest/events/Ordinal;Ljava/lang/String;Ljava/lang/String;Ljava/lang/String;Lscala/Option;Lscala/Option;Lscala/Option;Lscala/Option;Lscala/Option;Lscala/Option;Lscala/Option;Ljava/lang/String;J)V
  #314 = NameAndType        #89:#313      // "<init>":(Lorg/scalatest/events/Ordinal;Ljava/lang/String;Ljava/lang/String;Ljava/lang/String;Lscala/Option;Lscala/Option;Lscala/Option;Lscala/Option;Lscala/Option;Lscala/Option;Lscala/Option;Ljava/lang/String;J)V
  #315 = Methodref          #294.#314     // org/scalatest/events/SuiteAborted."<init>":(Lorg/scalatest/events/Ordinal;Ljava/lang/String;Ljava/lang/String;Ljava/lang/String;Lscala/Option;Lscala/Option;Lscala/Option;Lscala/Option;Lscala/Option;Lscala/Option;Lscala/Option;Ljava/lang/String;J)V
  #316 = Utf8               org/scalatest/Stopper
  #317 = Class              #316          // org/scalatest/Stopper
  #318 = Utf8               stopRequested
  #319 = NameAndType        #318:#231     // stopRequested:()Z
  #320 = InterfaceMethodref #317.#319     // org/scalatest/Stopper.stopRequested:()Z
  #321 = Utf8               org/scalatest/events/RunStopped
  #322 = Class              #321          // org/scalatest/events/RunStopped
  #323 = Utf8               org/scalatest/events/RunStopped$
  #324 = Class              #323          // org/scalatest/events/RunStopped$
  #325 = Utf8               Lorg/scalatest/events/RunStopped$;
  #326 = NameAndType        #52:#325      // MODULE$:Lorg/scalatest/events/RunStopped$;
  #327 = Fieldref           #324.#326     // org/scalatest/events/RunStopped$.MODULE$:Lorg/scalatest/events/RunStopped$;
  #328 = Utf8               apply$default$3
  #329 = NameAndType        #328:#47      // apply$default$3:()Lscala/Option;
  #330 = Methodref          #324.#329     // org/scalatest/events/RunStopped$.apply$default$3:()Lscala/Option;
  #331 = Methodref          #324.#157     // org/scalatest/events/RunStopped$.apply$default$4:()Lscala/Option;
  #332 = Methodref          #324.#160     // org/scalatest/events/RunStopped$.apply$default$5:()Lscala/Option;
  #333 = Methodref          #324.#163     // org/scalatest/events/RunStopped$.apply$default$6:()Lscala/Option;
  #334 = Methodref          #324.#166     // org/scalatest/events/RunStopped$.apply$default$7:()Ljava/lang/String;
  #335 = Methodref          #324.#169     // org/scalatest/events/RunStopped$.apply$default$8:()J
  #336 = Utf8               (Lorg/scalatest/events/Ordinal;Lscala/Option;Lscala/Option;Lscala/Option;Lscala/Option;Lscala/Option;Ljava/lang/String;J)V
  #337 = NameAndType        #89:#336      // "<init>":(Lorg/scalatest/events/Ordinal;Lscala/Option;Lscala/Option;Lscala/Option;Lscala/Option;Lscala/Option;Ljava/lang/String;J)V
  #338 = Methodref          #322.#337     // org/scalatest/events/RunStopped."<init>":(Lorg/scalatest/events/Ordinal;Lscala/Option;Lscala/Option;Lscala/Option;Lscala/Option;Lscala/Option;Ljava/lang/String;J)V
  #339 = Utf8               org/scalatest/events/RunCompleted
  #340 = Class              #339          // org/scalatest/events/RunCompleted
  #341 = Utf8               org/scalatest/events/RunCompleted$
  #342 = Class              #341          // org/scalatest/events/RunCompleted$
  #343 = Utf8               Lorg/scalatest/events/RunCompleted$;
  #344 = NameAndType        #52:#343      // MODULE$:Lorg/scalatest/events/RunCompleted$;
  #345 = Fieldref           #342.#344     // org/scalatest/events/RunCompleted$.MODULE$:Lorg/scalatest/events/RunCompleted$;
  #346 = Methodref          #342.#329     // org/scalatest/events/RunCompleted$.apply$default$3:()Lscala/Option;
  #347 = Methodref          #342.#157     // org/scalatest/events/RunCompleted$.apply$default$4:()Lscala/Option;
  #348 = Methodref          #342.#160     // org/scalatest/events/RunCompleted$.apply$default$5:()Lscala/Option;
  #349 = Methodref          #342.#163     // org/scalatest/events/RunCompleted$.apply$default$6:()Lscala/Option;
  #350 = Methodref          #342.#166     // org/scalatest/events/RunCompleted$.apply$default$7:()Ljava/lang/String;
  #351 = Methodref          #342.#169     // org/scalatest/events/RunCompleted$.apply$default$8:()J
  #352 = Methodref          #340.#337     // org/scalatest/events/RunCompleted."<init>":(Lorg/scalatest/events/Ordinal;Lscala/Option;Lscala/Option;Lscala/Option;Lscala/Option;Lscala/Option;Ljava/lang/String;J)V
  #353 = Utf8               org/scalatest/events/RunAborted
  #354 = Class              #353          // org/scalatest/events/RunAborted
  #355 = Methodref          #33.#274      // java/lang/ClassNotFoundException.getMessage:()Ljava/lang/String;
  #356 = Utf8               cannotLoadSuite
  #357 = NameAndType        #356:#283     // cannotLoadSuite:(Ljava/lang/Object;)Ljava/lang/String;
  #358 = Methodref          #180.#357     // org/scalatest/Resources$.cannotLoadSuite:(Ljava/lang/Object;)Ljava/lang/String;
  #359 = Utf8               org/scalatest/events/RunAborted$
  #360 = Class              #359          // org/scalatest/events/RunAborted$
  #361 = Utf8               Lorg/scalatest/events/RunAborted$;
  #362 = NameAndType        #52:#361      // MODULE$:Lorg/scalatest/events/RunAborted$;
  #363 = Fieldref           #360.#362     // org/scalatest/events/RunAborted$.MODULE$:Lorg/scalatest/events/RunAborted$;
  #364 = Methodref          #360.#160     // org/scalatest/events/RunAborted$.apply$default$5:()Lscala/Option;
  #365 = Methodref          #360.#163     // org/scalatest/events/RunAborted$.apply$default$6:()Lscala/Option;
  #366 = NameAndType        #165:#47      // apply$default$7:()Lscala/Option;
  #367 = Methodref          #360.#366     // org/scalatest/events/RunAborted$.apply$default$7:()Lscala/Option;
  #368 = Methodref          #360.#210     // org/scalatest/events/RunAborted$.apply$default$8:()Lscala/Option;
  #369 = Methodref          #360.#213     // org/scalatest/events/RunAborted$.apply$default$9:()Ljava/lang/String;
  #370 = Methodref          #360.#216     // org/scalatest/events/RunAborted$.apply$default$10:()J
  #371 = Utf8               (Lorg/scalatest/events/Ordinal;Ljava/lang/String;Lscala/Option;Lscala/Option;Lscala/Option;Lscala/Option;Lscala/Option;Lscala/Option;Ljava/lang/String;J)V
  #372 = NameAndType        #89:#371      // "<init>":(Lorg/scalatest/events/Ordinal;Ljava/lang/String;Lscala/Option;Lscala/Option;Lscala/Option;Lscala/Option;Lscala/Option;Lscala/Option;Ljava/lang/String;J)V
  #373 = Methodref          #354.#372     // org/scalatest/events/RunAborted."<init>":(Lorg/scalatest/events/Ordinal;Ljava/lang/String;Lscala/Option;Lscala/Option;Lscala/Option;Lscala/Option;Lscala/Option;Lscala/Option;Ljava/lang/String;J)V
  #374 = Methodref          #35.#274      // java/lang/InstantiationException.getMessage:()Ljava/lang/String;
  #375 = Utf8               cannotInstantiateSuite
  #376 = NameAndType        #375:#283     // cannotInstantiateSuite:(Ljava/lang/Object;)Ljava/lang/String;
  #377 = Methodref          #180.#376     // org/scalatest/Resources$.cannotInstantiateSuite:(Ljava/lang/Object;)Ljava/lang/String;
  #378 = Methodref          #37.#274      // java/lang/IllegalAccessException.getMessage:()Ljava/lang/String;
  #379 = Methodref          #39.#274      // java/lang/SecurityException.getMessage:()Ljava/lang/String;
  #380 = Utf8               securityWhenRerunning
  #381 = NameAndType        #380:#283     // securityWhenRerunning:(Ljava/lang/Object;)Ljava/lang/String;
  #382 = Methodref          #180.#381     // org/scalatest/Resources$.securityWhenRerunning:(Ljava/lang/Object;)Ljava/lang/String;
  #383 = Methodref          #41.#274      // java/lang/NoClassDefFoundError.getMessage:()Ljava/lang/String;
  #384 = Utf8               cannotLoadClass
  #385 = NameAndType        #384:#283     // cannotLoadClass:(Ljava/lang/Object;)Ljava/lang/String;
  #386 = Methodref          #180.#385     // org/scalatest/Resources$.cannotLoadClass:(Ljava/lang/Object;)Ljava/lang/String;
  #387 = Utf8               bigProblems
  #388 = Utf8               (Ljava/lang/Throwable;)Ljava/lang/String;
  #389 = NameAndType        #387:#388     // bigProblems:(Ljava/lang/Throwable;)Ljava/lang/String;
  #390 = Methodref          #180.#389     // org/scalatest/Resources$.bigProblems:(Ljava/lang/Throwable;)Ljava/lang/String;
  #391 = Utf8               tti
  #392 = Utf8               Lscala/collection/immutable/Set;
  #393 = Utf8               rawString
  #394 = Utf8               formatter
  #395 = Utf8               Lscala/Option;
  #396 = Utf8               rawString2
  #397 = Utf8               formatter2
  #398 = Utf8               duration
  #399 = Utf8               J
  #400 = Utf8               eMessage
  #401 = Utf8               rawString3
  #402 = Utf8               formatter3
  #403 = Utf8               e
  #404 = Utf8               Ljava/lang/RuntimeException;
  #405 = Utf8               suiteClass
  #406 = Utf8               Ljava/lang/Class;
  #407 = Utf8               suite
  #408 = Utf8               Lorg/scalatest/Suite;
  #409 = Utf8               I
  #410 = Utf8               rerunnable
  #411 = Utf8               suiteStartTime
  #412 = Utf8               Ljava/lang/ClassNotFoundException;
  #413 = Utf8               Ljava/lang/InstantiationException;
  #414 = Utf8               Ljava/lang/IllegalAccessException;
  #415 = Utf8               Ljava/lang/SecurityException;
  #416 = Utf8               Ljava/lang/NoClassDefFoundError;
  #417 = Utf8               Ljava/lang/Throwable;
  #418 = Utf8               runStartTime
  #419 = Utf8               this
  #420 = Utf8               Lorg/scalatest/SuiteRerunner;
  #421 = Utf8               Lorg/scalatest/Reporter;
  #422 = Utf8               Lorg/scalatest/Stopper;
  #423 = Utf8               Lorg/scalatest/Filter;
  #424 = Utf8               Lorg/scalatest/ConfigMap;
  #425 = Utf8               Lorg/scalatest/Tracker;
  #426 = Utf8               Ljava/lang/ClassLoader;
  #427 = Utf8               scala/Option
  #428 = Class              #427          // scala/Option
  #429 = Utf8               org/scalatest/ConfigMap
  #430 = Class              #429          // org/scalatest/ConfigMap
  #431 = Utf8               ()V
  #432 = NameAndType        #89:#431      // "<init>":()V
  #433 = Methodref          #4.#432       // java/lang/Object."<init>":()V
  #434 = Utf8               org/scalactic/Requirements$
  #435 = Class              #434          // org/scalactic/Requirements$
  #436 = Utf8               Lorg/scalactic/Requirements$;
  #437 = NameAndType        #52:#436      // MODULE$:Lorg/scalactic/Requirements$;
  #438 = Fieldref           #435.#437     // org/scalactic/Requirements$.MODULE$:Lorg/scalactic/Requirements$;
  #439 = Utf8               requirementsHelper
  #440 = Utf8               ()Lorg/scalactic/Requirements$RequirementsHelper;
  #441 = NameAndType        #439:#440     // requirementsHelper:()Lorg/scalactic/Requirements$RequirementsHelper;
  #442 = Methodref          #435.#441     // org/scalactic/Requirements$.requirementsHelper:()Lorg/scalactic/Requirements$RequirementsHelper;
  #443 = Utf8               SuiteRerunner.this.suiteClassName
  #444 = String             #443          // SuiteRerunner.this.suiteClassName
  #445 = Utf8               [Ljava/lang/Object;
  #446 = Class              #445          // "[Ljava/lang/Object;"
  #447 = Utf8               [Ljava/lang/String;
  #448 = Class              #447          // "[Ljava/lang/String;"
  #449 = Utf8               org/scalactic/Prettifier$
  #450 = Class              #449          // org/scalactic/Prettifier$
  #451 = Utf8               Lorg/scalactic/Prettifier$;
  #452 = NameAndType        #52:#451      // MODULE$:Lorg/scalactic/Prettifier$;
  #453 = Fieldref           #450.#452     // org/scalactic/Prettifier$.MODULE$:Lorg/scalactic/Prettifier$;
  #454 = Utf8               default
  #455 = Utf8               ()Lorg/scalactic/Prettifier;
  #456 = NameAndType        #454:#455     // default:()Lorg/scalactic/Prettifier;
  #457 = Methodref          #450.#456     // org/scalactic/Prettifier$.default:()Lorg/scalactic/Prettifier;
  #458 = Utf8               org/scalactic/source/Position
  #459 = Class              #458          // org/scalactic/source/Position
  #460 = String             #9            // SuiteRerunner.scala
  #461 = Utf8               Please set the environment variable SCALACTIC_FILL_FILE_PATHNAMES to yes at compile time to enable this feature.
  #462 = String             #461          // Please set the environment variable SCALACTIC_FILL_FILE_PATHNAMES to yes at compile time to enable this feature.
  #463 = Utf8               (Ljava/lang/String;Ljava/lang/String;I)V
  #464 = NameAndType        #89:#463      // "<init>":(Ljava/lang/String;Ljava/lang/String;I)V
  #465 = Methodref          #459.#464     // org/scalactic/source/Position."<init>":(Ljava/lang/String;Ljava/lang/String;I)V
  #466 = Utf8               macroRequireNonNull
  #467 = Utf8               ([Ljava/lang/String;[Ljava/lang/Object;Lorg/scalactic/Prettifier;Lorg/scalactic/source/Position;)V
  #468 = NameAndType        #466:#467     // macroRequireNonNull:([Ljava/lang/String;[Ljava/lang/Object;Lorg/scalactic/Prettifier;Lorg/scalactic/source/Position;)V
  #469 = Methodref          #14.#468      // org/scalactic/Requirements$RequirementsHelper.macroRequireNonNull:([Ljava/lang/String;[Ljava/lang/Object;Lorg/scalactic/Prettifier;Lorg/scalactic/source/Position;)V
  #470 = Utf8               Code
  #471 = Utf8               StackMapTable
  #472 = Utf8               LineNumberTable
  #473 = Utf8               LocalVariableTable
  #474 = Utf8               Signature
  #475 = Utf8               MethodParameters
  #476 = Utf8               InnerClasses
  #477 = Utf8               SourceFile
  #478 = Utf8               RuntimeVisibleAnnotations
  #479 = Utf8               ScalaInlineInfo
  #480 = Utf8               ScalaSig
{
  private final java.lang.String suiteClassName;
    descriptor: Ljava/lang/String;
    flags: (0x0012) ACC_PRIVATE, ACC_FINAL

  public void apply(org.scalatest.Reporter, org.scalatest.Stopper, org.scalatest.Filter, org.scalatest.ConfigMap, scala.Option<org.scalatest.Distributor>, org.scalatest.Tracker, java.lang.ClassLoader);
    descriptor: (Lorg/scalatest/Reporter;Lorg/scalatest/Stopper;Lorg/scalatest/Filter;Lorg/scalatest/ConfigMap;Lscala/Option;Lorg/scalatest/Tracker;Ljava/lang/ClassLoader;)V
    flags: (0x0001) ACC_PUBLIC
    Code:
      stack=17, locals=54, args_size=8
         0: aload_3
         1: invokevirtual #49                 // Method org/scalatest/Filter.tagsToInclude:()Lscala/Option;
         4: astore        10
         6: getstatic     #55                 // Field scala/None$.MODULE$:Lscala/None$;
         9: aload         10
        11: invokevirtual #59                 // Method java/lang/Object.equals:(Ljava/lang/Object;)Z
        14: ifeq          37
        17: getstatic     #64                 // Field scala/Predef$.MODULE$:Lscala/Predef$;
        20: invokevirtual #68                 // Method scala/Predef$.Set:()Lscala/collection/immutable/Set$;
        23: getstatic     #73                 // Field scala/collection/immutable/Nil$.MODULE$:Lscala/collection/immutable/Nil$;
        26: invokevirtual #78                 // Method scala/collection/immutable/Set$.apply:(Lscala/collection/immutable/Seq;)Ljava/lang/Object;
        29: checkcast     #80                 // class scala/collection/immutable/Set
        32: astore        8
        34: goto          85
        37: goto          40
        40: aload         10
        42: instanceof    #82                 // class scala/Some
        45: ifeq          72
        48: aload         10
        50: checkcast     #82                 // class scala/Some
        53: astore        11
        55: aload         11
        57: invokevirtual #86                 // Method scala/Some.value:()Ljava/lang/Object;
        60: checkcast     #80                 // class scala/collection/immutable/Set
        63: astore        12
        65: aload         12
        67: astore        8
        69: goto          85
        72: goto          75
        75: new           #88                 // class scala/MatchError
        78: dup
        79: aload         10
        81: invokespecial #92                 // Method scala/MatchError."<init>":(Ljava/lang/Object;)V
        84: athrow
        85: aload         8
        87: astore        9
        89: aload_3
        90: invokevirtual #96                 // Method org/scalatest/Filter.tagsToExclude:()Lscala/collection/immutable/Set;
        93: astore        13
        95: invokestatic  #102                // Method java/lang/System.currentTimeMillis:()J
        98: lstore        14
       100: aload         7
       102: aload_0
       103: getfield      #104                // Field suiteClassName:Ljava/lang/String;
       106: invokevirtual #110                // Method java/lang/ClassLoader.loadClass:(Ljava/lang/String;)Ljava/lang/Class;
       109: astore        16
       111: aload         16
       113: invokevirtual #115                // Method java/lang/Class.newInstance:()Ljava/lang/Object;
       116: checkcast     #117                // class org/scalatest/Suite
       119: astore        17
       121: aload         17
       123: aload_3
       124: invokeinterface #121,  2          // InterfaceMethod org/scalatest/Suite.expectedTestCount:(Lorg/scalatest/Filter;)I
       129: istore        18
       131: getstatic     #126                // Field org/scalatest/Suite$.MODULE$:Lorg/scalatest/Suite$;
       134: aload         17
       136: invokevirtual #130                // Method java/lang/Object.getClass:()Ljava/lang/Class;
       139: invokevirtual #134                // Method org/scalatest/Suite$.checkForPublicNoArgConstructor:(Ljava/lang/Class;)Z
       142: ifeq          170
       145: new           #82                 // class scala/Some
       148: dup
       149: new           #2                  // class org/scalatest/SuiteRerunner
       152: dup
       153: aload         17
       155: invokevirtual #130                // Method java/lang/Object.getClass:()Ljava/lang/Class;
       158: invokevirtual #138                // Method java/lang/Class.getName:()Ljava/lang/String;
       161: invokespecial #141                // Method "<init>":(Ljava/lang/String;)V
       164: invokespecial #142                // Method scala/Some."<init>":(Ljava/lang/Object;)V
       167: goto          173
       170: getstatic     #55                 // Field scala/None$.MODULE$:Lscala/None$;
       173: astore        19
       175: aload_1
       176: new           #144                // class org/scalatest/events/RunStarting
       179: dup
       180: aload         6
       182: invokevirtual #150                // Method org/scalatest/Tracker.nextOrdinal:()Lorg/scalatest/events/Ordinal;
       185: iload         18
       187: aload         4
       189: getstatic     #155                // Field org/scalatest/events/RunStarting$.MODULE$:Lorg/scalatest/events/RunStarting$;
       192: invokevirtual #158                // Method org/scalatest/events/RunStarting$.apply$default$4:()Lscala/Option;
       195: getstatic     #155                // Field org/scalatest/events/RunStarting$.MODULE$:Lorg/scalatest/events/RunStarting$;
       198: invokevirtual #161                // Method org/scalatest/events/RunStarting$.apply$default$5:()Lscala/Option;
       201: getstatic     #155                // Field org/scalatest/events/RunStarting$.MODULE$:Lorg/scalatest/events/RunStarting$;
       204: invokevirtual #164                // Method org/scalatest/events/RunStarting$.apply$default$6:()Lscala/Option;
       207: getstatic     #155                // Field org/scalatest/events/RunStarting$.MODULE$:Lorg/scalatest/events/RunStarting$;
       210: invokevirtual #167                // Method org/scalatest/events/RunStarting$.apply$default$7:()Ljava/lang/String;
       213: getstatic     #155                // Field org/scalatest/events/RunStarting$.MODULE$:Lorg/scalatest/events/RunStarting$;
       216: invokevirtual #170                // Method org/scalatest/events/RunStarting$.apply$default$8:()J
       219: invokespecial #173                // Method org/scalatest/events/RunStarting."<init>":(Lorg/scalatest/events/Ordinal;ILorg/scalatest/ConfigMap;Lscala/Option;Lscala/Option;Lscala/Option;Ljava/lang/String;J)V
       222: invokeinterface #178,  2          // InterfaceMethod org/scalatest/Reporter.apply:(Lorg/scalatest/events/Event;)V
       227: invokestatic  #102                // Method java/lang/System.currentTimeMillis:()J
       230: lstore        20
       232: getstatic     #183                // Field org/scalatest/Resources$.MODULE$:Lorg/scalatest/Resources$;
       235: invokevirtual #186                // Method org/scalatest/Resources$.suiteExecutionStarting:()Ljava/lang/String;
       238: astore        22
       240: getstatic     #126                // Field org/scalatest/Suite$.MODULE$:Lorg/scalatest/Suite$;
       243: aload         17
       245: invokevirtual #190                // Method org/scalatest/Suite$.formatterForSuiteStarting:(Lorg/scalatest/Suite;)Lscala/Option;
       248: astore        23
       250: aload_1
       251: new           #192                // class org/scalatest/events/SuiteStarting
       254: dup
       255: aload         6
       257: invokevirtual #150                // Method org/scalatest/Tracker.nextOrdinal:()Lorg/scalatest/events/Ordinal;
       260: aload         17
       262: invokeinterface #195,  1          // InterfaceMethod org/scalatest/Suite.suiteName:()Ljava/lang/String;
       267: aload         17
       269: invokeinterface #198,  1          // InterfaceMethod org/scalatest/Suite.suiteId:()Ljava/lang/String;
       274: new           #82                 // class scala/Some
       277: dup
       278: aload         17
       280: invokevirtual #130                // Method java/lang/Object.getClass:()Ljava/lang/Class;
       283: invokevirtual #138                // Method java/lang/Class.getName:()Ljava/lang/String;
       286: invokespecial #142                // Method scala/Some."<init>":(Ljava/lang/Object;)V
       289: aload         23
       291: new           #82                 // class scala/Some
       294: dup
       295: new           #200                // class org/scalatest/events/TopOfClass
       298: dup
       299: aload         17
       301: invokevirtual #130                // Method java/lang/Object.getClass:()Ljava/lang/Class;
       304: invokevirtual #138                // Method java/lang/Class.getName:()Ljava/lang/String;
       307: invokespecial #201                // Method org/scalatest/events/TopOfClass."<init>":(Ljava/lang/String;)V
       310: invokespecial #142                // Method scala/Some."<init>":(Ljava/lang/Object;)V
       313: aload         17
       315: invokeinterface #204,  1          // InterfaceMethod org/scalatest/Suite.rerunner:()Lscala/Option;
       320: getstatic     #209                // Field org/scalatest/events/SuiteStarting$.MODULE$:Lorg/scalatest/events/SuiteStarting$;
       323: invokevirtual #211                // Method org/scalatest/events/SuiteStarting$.apply$default$8:()Lscala/Option;
       326: getstatic     #209                // Field org/scalatest/events/SuiteStarting$.MODULE$:Lorg/scalatest/events/SuiteStarting$;
       329: invokevirtual #214                // Method org/scalatest/events/SuiteStarting$.apply$default$9:()Ljava/lang/String;
       332: getstatic     #209                // Field org/scalatest/events/SuiteStarting$.MODULE$:Lorg/scalatest/events/SuiteStarting$;
       335: invokevirtual #217                // Method org/scalatest/events/SuiteStarting$.apply$default$10:()J
       338: invokespecial #220                // Method org/scalatest/events/SuiteStarting."<init>":(Lorg/scalatest/events/Ordinal;Ljava/lang/String;Ljava/lang/String;Lscala/Option;Lscala/Option;Lscala/Option;Lscala/Option;Lscala/Option;Ljava/lang/String;J)V
       341: invokeinterface #178,  2          // InterfaceMethod org/scalatest/Reporter.apply:(Lorg/scalatest/events/Event;)V
       346: aload         17
       348: getstatic     #55                 // Field scala/None$.MODULE$:Lscala/None$;
       351: new           #222                // class org/scalatest/Args
       354: dup
       355: aload_1
       356: aload_2
       357: aload_3
       358: aload         4
       360: aload         5
       362: aload         6
       364: getstatic     #64                 // Field scala/Predef$.MODULE$:Lscala/Predef$;
       367: invokevirtual #68                 // Method scala/Predef$.Set:()Lscala/collection/immutable/Set$;
       370: invokevirtual #225                // Method scala/collection/immutable/Set$.empty:()Lscala/collection/immutable/Set;
       373: getstatic     #230                // Field org/scalatest/Args$.MODULE$:Lorg/scalatest/Args$;
       376: invokevirtual #233                // Method org/scalatest/Args$.apply$default$8:()Z
       379: getstatic     #230                // Field org/scalatest/Args$.MODULE$:Lorg/scalatest/Args$;
       382: invokevirtual #235                // Method org/scalatest/Args$.apply$default$9:()Lscala/Option;
       385: getstatic     #230                // Field org/scalatest/Args$.MODULE$:Lorg/scalatest/Args$;
       388: invokevirtual #237                // Method org/scalatest/Args$.apply$default$10:()Lscala/Option;
       391: invokespecial #240                // Method org/scalatest/Args."<init>":(Lorg/scalatest/Reporter;Lorg/scalatest/Stopper;Lorg/scalatest/Filter;Lorg/scalatest/ConfigMap;Lscala/Option;Lorg/scalatest/Tracker;Lscala/collection/immutable/Set;ZLscala/Option;Lscala/Option;)V
       394: invokeinterface #244,  3          // InterfaceMethod org/scalatest/Suite.run:(Lscala/Option;Lorg/scalatest/Args;)Lorg/scalatest/Status;
       399: pop
       400: getstatic     #183                // Field org/scalatest/Resources$.MODULE$:Lorg/scalatest/Resources$;
       403: invokevirtual #247                // Method org/scalatest/Resources$.suiteCompletedNormally:()Ljava/lang/String;
       406: astore        24
       408: getstatic     #126                // Field org/scalatest/Suite$.MODULE$:Lorg/scalatest/Suite$;
       411: aload         17
       413: invokevirtual #250                // Method org/scalatest/Suite$.formatterForSuiteCompleted:(Lorg/scalatest/Suite;)Lscala/Option;
       416: astore        25
       418: invokestatic  #102                // Method java/lang/System.currentTimeMillis:()J
       421: lload         20
       423: lsub
       424: lstore        26
       426: aload_1
       427: new           #252                // class org/scalatest/events/SuiteCompleted
       430: dup
       431: aload         6
       433: invokevirtual #150                // Method org/scalatest/Tracker.nextOrdinal:()Lorg/scalatest/events/Ordinal;
       436: aload         17
       438: invokeinterface #195,  1          // InterfaceMethod org/scalatest/Suite.suiteName:()Ljava/lang/String;
       443: aload         17
       445: invokeinterface #198,  1          // InterfaceMethod org/scalatest/Suite.suiteId:()Ljava/lang/String;
       450: new           #82                 // class scala/Some
       453: dup
       454: aload         17
       456: invokevirtual #130                // Method java/lang/Object.getClass:()Ljava/lang/Class;
       459: invokevirtual #138                // Method java/lang/Class.getName:()Ljava/lang/String;
       462: invokespecial #142                // Method scala/Some."<init>":(Ljava/lang/Object;)V
       465: new           #82                 // class scala/Some
       468: dup
       469: lload         26
       471: invokestatic  #258                // Method scala/runtime/BoxesRunTime.boxToLong:(J)Ljava/lang/Long;
       474: invokespecial #142                // Method scala/Some."<init>":(Ljava/lang/Object;)V
       477: aload         25
       479: new           #82                 // class scala/Some
       482: dup
       483: new           #200                // class org/scalatest/events/TopOfClass
       486: dup
       487: aload         17
       489: invokevirtual #130                // Method java/lang/Object.getClass:()Ljava/lang/Class;
       492: invokevirtual #138                // Method java/lang/Class.getName:()Ljava/lang/String;
       495: invokespecial #201                // Method org/scalatest/events/TopOfClass."<init>":(Ljava/lang/String;)V
       498: invokespecial #142                // Method scala/Some."<init>":(Ljava/lang/Object;)V
       501: aload         17
       503: invokeinterface #204,  1          // InterfaceMethod org/scalatest/Suite.rerunner:()Lscala/Option;
       508: getstatic     #263                // Field org/scalatest/events/SuiteCompleted$.MODULE$:Lorg/scalatest/events/SuiteCompleted$;
       511: invokevirtual #264                // Method org/scalatest/events/SuiteCompleted$.apply$default$9:()Lscala/Option;
       514: getstatic     #263                // Field org/scalatest/events/SuiteCompleted$.MODULE$:Lorg/scalatest/events/SuiteCompleted$;
       517: invokevirtual #266                // Method org/scalatest/events/SuiteCompleted$.apply$default$10:()Ljava/lang/String;
       520: getstatic     #263                // Field org/scalatest/events/SuiteCompleted$.MODULE$:Lorg/scalatest/events/SuiteCompleted$;
       523: invokevirtual #269                // Method org/scalatest/events/SuiteCompleted$.apply$default$11:()J
       526: invokespecial #272                // Method org/scalatest/events/SuiteCompleted."<init>":(Lorg/scalatest/events/Ordinal;Ljava/lang/String;Ljava/lang/String;Lscala/Option;Lscala/Option;Lscala/Option;Lscala/Option;Lscala/Option;Lscala/Option;Ljava/lang/String;J)V
       529: invokeinterface #178,  2          // InterfaceMethod org/scalatest/Reporter.apply:(Lorg/scalatest/events/Event;)V
       534: goto          709
       537: astore        28
       539: aload         28
       541: invokevirtual #275                // Method java/lang/RuntimeException.getMessage:()Ljava/lang/String;
       544: astore        29
       546: aload         29
       548: ifnull        571
       551: aload         29
       553: invokevirtual #281                // Method java/lang/String.length:()I
       556: iconst_0
       557: if_icmple     571
       560: getstatic     #183                // Field org/scalatest/Resources$.MODULE$:Lorg/scalatest/Resources$;
       563: aload         29
       565: invokevirtual #285                // Method org/scalatest/Resources$.executeExceptionWithMessage:(Ljava/lang/Object;)Ljava/lang/String;
       568: goto          577
       571: getstatic     #183                // Field org/scalatest/Resources$.MODULE$:Lorg/scalatest/Resources$;
       574: invokevirtual #288                // Method org/scalatest/Resources$.executeException:()Ljava/lang/String;
       577: astore        30
       579: getstatic     #126                // Field org/scalatest/Suite$.MODULE$:Lorg/scalatest/Suite$;
       582: aload         17
       584: aload         30
       586: invokevirtual #292                // Method org/scalatest/Suite$.formatterForSuiteAborted:(Lorg/scalatest/Suite;Ljava/lang/String;)Lscala/Option;
       589: astore        31
       591: invokestatic  #102                // Method java/lang/System.currentTimeMillis:()J
       594: lload         20
       596: lsub
       597: lstore        32
       599: aload_1
       600: new           #294                // class org/scalatest/events/SuiteAborted
       603: dup
       604: aload         6
       606: invokevirtual #150                // Method org/scalatest/Tracker.nextOrdinal:()Lorg/scalatest/events/Ordinal;
       609: aload         30
       611: aload         17
       613: invokeinterface #195,  1          // InterfaceMethod org/scalatest/Suite.suiteName:()Ljava/lang/String;
       618: aload         17
       620: invokeinterface #198,  1          // InterfaceMethod org/scalatest/Suite.suiteId:()Ljava/lang/String;
       625: new           #82                 // class scala/Some
       628: dup
       629: aload         17
       631: invokevirtual #130                // Method java/lang/Object.getClass:()Ljava/lang/Class;
       634: invokevirtual #138                // Method java/lang/Class.getName:()Ljava/lang/String;
       637: invokespecial #142                // Method scala/Some."<init>":(Ljava/lang/Object;)V
       640: new           #82                 // class scala/Some
       643: dup
       644: aload         28
       646: invokespecial #142                // Method scala/Some."<init>":(Ljava/lang/Object;)V
       649: new           #82                 // class scala/Some
       652: dup
       653: lload         32
       655: invokestatic  #258                // Method scala/runtime/BoxesRunTime.boxToLong:(J)Ljava/lang/Long;
       658: invokespecial #142                // Method scala/Some."<init>":(Ljava/lang/Object;)V
       661: aload         31
       663: new           #82                 // class scala/Some
       666: dup
       667: getstatic     #299                // Field org/scalatest/events/SeeStackDepthException$.MODULE$:Lorg/scalatest/events/SeeStackDepthException$;
       670: invokespecial #142                // Method scala/Some."<init>":(Ljava/lang/Object;)V
       673: aload         17
       675: invokeinterface #204,  1          // InterfaceMethod org/scalatest/Suite.rerunner:()Lscala/Option;
       680: getstatic     #304                // Field org/scalatest/events/SuiteAborted$.MODULE$:Lorg/scalatest/events/SuiteAborted$;
       683: invokevirtual #306                // Method org/scalatest/events/SuiteAborted$.apply$default$11:()Lscala/Option;
       686: getstatic     #304                // Field org/scalatest/events/SuiteAborted$.MODULE$:Lorg/scalatest/events/SuiteAborted$;
       689: invokevirtual #309                // Method org/scalatest/events/SuiteAborted$.apply$default$12:()Ljava/lang/String;
       692: getstatic     #304                // Field org/scalatest/events/SuiteAborted$.MODULE$:Lorg/scalatest/events/SuiteAborted$;
       695: invokevirtual #312                // Method org/scalatest/events/SuiteAborted$.apply$default$13:()J
       698: invokespecial #315                // Method org/scalatest/events/SuiteAborted."<init>":(Lorg/scalatest/events/Ordinal;Ljava/lang/String;Ljava/lang/String;Ljava/lang/String;Lscala/Option;Lscala/Option;Lscala/Option;Lscala/Option;Lscala/Option;Lscala/Option;Lscala/Option;Ljava/lang/String;J)V
       701: invokeinterface #178,  2          // InterfaceMethod org/scalatest/Reporter.apply:(Lorg/scalatest/events/Event;)V
       706: goto          709
       709: invokestatic  #102                // Method java/lang/System.currentTimeMillis:()J
       712: lload         14
       714: lsub
       715: lstore        34
       717: aload_2
       718: invokeinterface #320,  1          // InterfaceMethod org/scalatest/Stopper.stopRequested:()Z
       723: ifeq          795
       726: aload_1
       727: new           #322                // class org/scalatest/events/RunStopped
       730: dup
       731: aload         6
       733: invokevirtual #150                // Method org/scalatest/Tracker.nextOrdinal:()Lorg/scalatest/events/Ordinal;
       736: new           #82                 // class scala/Some
       739: dup
       740: lload         34
       742: invokestatic  #258                // Method scala/runtime/BoxesRunTime.boxToLong:(J)Ljava/lang/Long;
       745: invokespecial #142                // Method scala/Some."<init>":(Ljava/lang/Object;)V
       748: getstatic     #327                // Field org/scalatest/events/RunStopped$.MODULE$:Lorg/scalatest/events/RunStopped$;
       751: invokevirtual #330                // Method org/scalatest/events/RunStopped$.apply$default$3:()Lscala/Option;
       754: getstatic     #327                // Field org/scalatest/events/RunStopped$.MODULE$:Lorg/scalatest/events/RunStopped$;
       757: invokevirtual #331                // Method org/scalatest/events/RunStopped$.apply$default$4:()Lscala/Option;
       760: getstatic     #327                // Field org/scalatest/events/RunStopped$.MODULE$:Lorg/scalatest/events/RunStopped$;
       763: invokevirtual #332                // Method org/scalatest/events/RunStopped$.apply$default$5:()Lscala/Option;
       766: getstatic     #327                // Field org/scalatest/events/RunStopped$.MODULE$:Lorg/scalatest/events/RunStopped$;
       769: invokevirtual #333                // Method org/scalatest/events/RunStopped$.apply$default$6:()Lscala/Option;
       772: getstatic     #327                // Field org/scalatest/events/RunStopped$.MODULE$:Lorg/scalatest/events/RunStopped$;
       775: invokevirtual #334                // Method org/scalatest/events/RunStopped$.apply$default$7:()Ljava/lang/String;
       778: getstatic     #327                // Field org/scalatest/events/RunStopped$.MODULE$:Lorg/scalatest/events/RunStopped$;
       781: invokevirtual #335                // Method org/scalatest/events/RunStopped$.apply$default$8:()J
       784: invokespecial #338                // Method org/scalatest/events/RunStopped."<init>":(Lorg/scalatest/events/Ordinal;Lscala/Option;Lscala/Option;Lscala/Option;Lscala/Option;Lscala/Option;Ljava/lang/String;J)V
       787: invokeinterface #178,  2          // InterfaceMethod org/scalatest/Reporter.apply:(Lorg/scalatest/events/Event;)V
       792: goto          861
       795: aload_1
       796: new           #340                // class org/scalatest/events/RunCompleted
       799: dup
       800: aload         6
       802: invokevirtual #150                // Method org/scalatest/Tracker.nextOrdinal:()Lorg/scalatest/events/Ordinal;
       805: new           #82                 // class scala/Some
       808: dup
       809: lload         34
       811: invokestatic  #258                // Method scala/runtime/BoxesRunTime.boxToLong:(J)Ljava/lang/Long;
       814: invokespecial #142                // Method scala/Some."<init>":(Ljava/lang/Object;)V
       817: getstatic     #345                // Field org/scalatest/events/RunCompleted$.MODULE$:Lorg/scalatest/events/RunCompleted$;
       820: invokevirtual #346                // Method org/scalatest/events/RunCompleted$.apply$default$3:()Lscala/Option;
       823: getstatic     #345                // Field org/scalatest/events/RunCompleted$.MODULE$:Lorg/scalatest/events/RunCompleted$;
       826: invokevirtual #347                // Method org/scalatest/events/RunCompleted$.apply$default$4:()Lscala/Option;
       829: getstatic     #345                // Field org/scalatest/events/RunCompleted$.MODULE$:Lorg/scalatest/events/RunCompleted$;
       832: invokevirtual #348                // Method org/scalatest/events/RunCompleted$.apply$default$5:()Lscala/Option;
       835: getstatic     #345                // Field org/scalatest/events/RunCompleted$.MODULE$:Lorg/scalatest/events/RunCompleted$;
       838: invokevirtual #349                // Method org/scalatest/events/RunCompleted$.apply$default$6:()Lscala/Option;
       841: getstatic     #345                // Field org/scalatest/events/RunCompleted$.MODULE$:Lorg/scalatest/events/RunCompleted$;
       844: invokevirtual #350                // Method org/scalatest/events/RunCompleted$.apply$default$7:()Ljava/lang/String;
       847: getstatic     #345                // Field org/scalatest/events/RunCompleted$.MODULE$:Lorg/scalatest/events/RunCompleted$;
       850: invokevirtual #351                // Method org/scalatest/events/RunCompleted$.apply$default$8:()J
       853: invokespecial #352                // Method org/scalatest/events/RunCompleted."<init>":(Lorg/scalatest/events/Ordinal;Lscala/Option;Lscala/Option;Lscala/Option;Lscala/Option;Lscala/Option;Ljava/lang/String;J)V
       856: invokeinterface #178,  2          // InterfaceMethod org/scalatest/Reporter.apply:(Lorg/scalatest/events/Event;)V
       861: goto          1455
       864: astore        36
       866: invokestatic  #102                // Method java/lang/System.currentTimeMillis:()J
       869: lload         14
       871: lsub
       872: lstore        37
       874: aload_1
       875: new           #354                // class org/scalatest/events/RunAborted
       878: dup
       879: aload         6
       881: invokevirtual #150                // Method org/scalatest/Tracker.nextOrdinal:()Lorg/scalatest/events/Ordinal;
       884: getstatic     #183                // Field org/scalatest/Resources$.MODULE$:Lorg/scalatest/Resources$;
       887: aload         36
       889: invokevirtual #355                // Method java/lang/ClassNotFoundException.getMessage:()Ljava/lang/String;
       892: invokevirtual #358                // Method org/scalatest/Resources$.cannotLoadSuite:(Ljava/lang/Object;)Ljava/lang/String;
       895: new           #82                 // class scala/Some
       898: dup
       899: aload         36
       901: invokespecial #142                // Method scala/Some."<init>":(Ljava/lang/Object;)V
       904: new           #82                 // class scala/Some
       907: dup
       908: lload         37
       910: invokestatic  #258                // Method scala/runtime/BoxesRunTime.boxToLong:(J)Ljava/lang/Long;
       913: invokespecial #142                // Method scala/Some."<init>":(Ljava/lang/Object;)V
       916: getstatic     #363                // Field org/scalatest/events/RunAborted$.MODULE$:Lorg/scalatest/events/RunAborted$;
       919: invokevirtual #364                // Method org/scalatest/events/RunAborted$.apply$default$5:()Lscala/Option;
       922: getstatic     #363                // Field org/scalatest/events/RunAborted$.MODULE$:Lorg/scalatest/events/RunAborted$;
       925: invokevirtual #365                // Method org/scalatest/events/RunAborted$.apply$default$6:()Lscala/Option;
       928: getstatic     #363                // Field org/scalatest/events/RunAborted$.MODULE$:Lorg/scalatest/events/RunAborted$;
       931: invokevirtual #367                // Method org/scalatest/events/RunAborted$.apply$default$7:()Lscala/Option;
       934: getstatic     #363                // Field org/scalatest/events/RunAborted$.MODULE$:Lorg/scalatest/events/RunAborted$;
       937: invokevirtual #368                // Method org/scalatest/events/RunAborted$.apply$default$8:()Lscala/Option;
       940: getstatic     #363                // Field org/scalatest/events/RunAborted$.MODULE$:Lorg/scalatest/events/RunAborted$;
       943: invokevirtual #369                // Method org/scalatest/events/RunAborted$.apply$default$9:()Ljava/lang/String;
       946: getstatic     #363                // Field org/scalatest/events/RunAborted$.MODULE$:Lorg/scalatest/events/RunAborted$;
       949: invokevirtual #370                // Method org/scalatest/events/RunAborted$.apply$default$10:()J
       952: invokespecial #373                // Method org/scalatest/events/RunAborted."<init>":(Lorg/scalatest/events/Ordinal;Ljava/lang/String;Lscala/Option;Lscala/Option;Lscala/Option;Lscala/Option;Lscala/Option;Lscala/Option;Ljava/lang/String;J)V
       955: invokeinterface #178,  2          // InterfaceMethod org/scalatest/Reporter.apply:(Lorg/scalatest/events/Event;)V
       960: goto          1455
       963: astore        39
       965: invokestatic  #102                // Method java/lang/System.currentTimeMillis:()J
       968: lload         14
       970: lsub
       971: lstore        40
       973: aload_1
       974: new           #354                // class org/scalatest/events/RunAborted
       977: dup
       978: aload         6
       980: invokevirtual #150                // Method org/scalatest/Tracker.nextOrdinal:()Lorg/scalatest/events/Ordinal;
       983: getstatic     #183                // Field org/scalatest/Resources$.MODULE$:Lorg/scalatest/Resources$;
       986: aload         39
       988: invokevirtual #374                // Method java/lang/InstantiationException.getMessage:()Ljava/lang/String;
       991: invokevirtual #377                // Method org/scalatest/Resources$.cannotInstantiateSuite:(Ljava/lang/Object;)Ljava/lang/String;
       994: new           #82                 // class scala/Some
       997: dup
       998: aload         39
      1000: invokespecial #142                // Method scala/Some."<init>":(Ljava/lang/Object;)V
      1003: new           #82                 // class scala/Some
      1006: dup
      1007: lload         40
      1009: invokestatic  #258                // Method scala/runtime/BoxesRunTime.boxToLong:(J)Ljava/lang/Long;
      1012: invokespecial #142                // Method scala/Some."<init>":(Ljava/lang/Object;)V
      1015: getstatic     #363                // Field org/scalatest/events/RunAborted$.MODULE$:Lorg/scalatest/events/RunAborted$;
      1018: invokevirtual #364                // Method org/scalatest/events/RunAborted$.apply$default$5:()Lscala/Option;
      1021: getstatic     #363                // Field org/scalatest/events/RunAborted$.MODULE$:Lorg/scalatest/events/RunAborted$;
      1024: invokevirtual #365                // Method org/scalatest/events/RunAborted$.apply$default$6:()Lscala/Option;
      1027: getstatic     #363                // Field org/scalatest/events/RunAborted$.MODULE$:Lorg/scalatest/events/RunAborted$;
      1030: invokevirtual #367                // Method org/scalatest/events/RunAborted$.apply$default$7:()Lscala/Option;
      1033: getstatic     #363                // Field org/scalatest/events/RunAborted$.MODULE$:Lorg/scalatest/events/RunAborted$;
      1036: invokevirtual #368                // Method org/scalatest/events/RunAborted$.apply$default$8:()Lscala/Option;
      1039: getstatic     #363                // Field org/scalatest/events/RunAborted$.MODULE$:Lorg/scalatest/events/RunAborted$;
      1042: invokevirtual #369                // Method org/scalatest/events/RunAborted$.apply$default$9:()Ljava/lang/String;
      1045: getstatic     #363                // Field org/scalatest/events/RunAborted$.MODULE$:Lorg/scalatest/events/RunAborted$;
      1048: invokevirtual #370                // Method org/scalatest/events/RunAborted$.apply$default$10:()J
      1051: invokespecial #373                // Method org/scalatest/events/RunAborted."<init>":(Lorg/scalatest/events/Ordinal;Ljava/lang/String;Lscala/Option;Lscala/Option;Lscala/Option;Lscala/Option;Lscala/Option;Lscala/Option;Ljava/lang/String;J)V
      1054: invokeinterface #178,  2          // InterfaceMethod org/scalatest/Reporter.apply:(Lorg/scalatest/events/Event;)V
      1059: goto          1455
      1062: astore        42
      1064: invokestatic  #102                // Method java/lang/System.currentTimeMillis:()J
      1067: lload         14
      1069: lsub
      1070: lstore        43
      1072: aload_1
      1073: new           #354                // class org/scalatest/events/RunAborted
      1076: dup
      1077: aload         6
      1079: invokevirtual #150                // Method org/scalatest/Tracker.nextOrdinal:()Lorg/scalatest/events/Ordinal;
      1082: getstatic     #183                // Field org/scalatest/Resources$.MODULE$:Lorg/scalatest/Resources$;
      1085: aload         42
      1087: invokevirtual #378                // Method java/lang/IllegalAccessException.getMessage:()Ljava/lang/String;
      1090: invokevirtual #377                // Method org/scalatest/Resources$.cannotInstantiateSuite:(Ljava/lang/Object;)Ljava/lang/String;
      1093: new           #82                 // class scala/Some
      1096: dup
      1097: aload         42
      1099: invokespecial #142                // Method scala/Some."<init>":(Ljava/lang/Object;)V
      1102: new           #82                 // class scala/Some
      1105: dup
      1106: lload         43
      1108: invokestatic  #258                // Method scala/runtime/BoxesRunTime.boxToLong:(J)Ljava/lang/Long;
      1111: invokespecial #142                // Method scala/Some."<init>":(Ljava/lang/Object;)V
      1114: getstatic     #363                // Field org/scalatest/events/RunAborted$.MODULE$:Lorg/scalatest/events/RunAborted$;
      1117: invokevirtual #364                // Method org/scalatest/events/RunAborted$.apply$default$5:()Lscala/Option;
      1120: getstatic     #363                // Field org/scalatest/events/RunAborted$.MODULE$:Lorg/scalatest/events/RunAborted$;
      1123: invokevirtual #365                // Method org/scalatest/events/RunAborted$.apply$default$6:()Lscala/Option;
      1126: getstatic     #363                // Field org/scalatest/events/RunAborted$.MODULE$:Lorg/scalatest/events/RunAborted$;
      1129: invokevirtual #367                // Method org/scalatest/events/RunAborted$.apply$default$7:()Lscala/Option;
      1132: getstatic     #363                // Field org/scalatest/events/RunAborted$.MODULE$:Lorg/scalatest/events/RunAborted$;
      1135: invokevirtual #368                // Method org/scalatest/events/RunAborted$.apply$default$8:()Lscala/Option;
      1138: getstatic     #363                // Field org/scalatest/events/RunAborted$.MODULE$:Lorg/scalatest/events/RunAborted$;
      1141: invokevirtual #369                // Method org/scalatest/events/RunAborted$.apply$default$9:()Ljava/lang/String;
      1144: getstatic     #363                // Field org/scalatest/events/RunAborted$.MODULE$:Lorg/scalatest/events/RunAborted$;
      1147: invokevirtual #370                // Method org/scalatest/events/RunAborted$.apply$default$10:()J
      1150: invokespecial #373                // Method org/scalatest/events/RunAborted."<init>":(Lorg/scalatest/events/Ordinal;Ljava/lang/String;Lscala/Option;Lscala/Option;Lscala/Option;Lscala/Option;Lscala/Option;Lscala/Option;Ljava/lang/String;J)V
      1153: invokeinterface #178,  2          // InterfaceMethod org/scalatest/Reporter.apply:(Lorg/scalatest/events/Event;)V
      1158: goto          1455
      1161: astore        45
      1163: invokestatic  #102                // Method java/lang/System.currentTimeMillis:()J
      1166: lload         14
      1168: lsub
      1169: lstore        46
      1171: aload_1
      1172: new           #354                // class org/scalatest/events/RunAborted
      1175: dup
      1176: aload         6
      1178: invokevirtual #150                // Method org/scalatest/Tracker.nextOrdinal:()Lorg/scalatest/events/Ordinal;
      1181: getstatic     #183                // Field org/scalatest/Resources$.MODULE$:Lorg/scalatest/Resources$;
      1184: aload         45
      1186: invokevirtual #379                // Method java/lang/SecurityException.getMessage:()Ljava/lang/String;
      1189: invokevirtual #382                // Method org/scalatest/Resources$.securityWhenRerunning:(Ljava/lang/Object;)Ljava/lang/String;
      1192: new           #82                 // class scala/Some
      1195: dup
      1196: aload         45
      1198: invokespecial #142                // Method scala/Some."<init>":(Ljava/lang/Object;)V
      1201: new           #82                 // class scala/Some
      1204: dup
      1205: lload         46
      1207: invokestatic  #258                // Method scala/runtime/BoxesRunTime.boxToLong:(J)Ljava/lang/Long;
      1210: invokespecial #142                // Method scala/Some."<init>":(Ljava/lang/Object;)V
      1213: getstatic     #363                // Field org/scalatest/events/RunAborted$.MODULE$:Lorg/scalatest/events/RunAborted$;
      1216: invokevirtual #364                // Method org/scalatest/events/RunAborted$.apply$default$5:()Lscala/Option;
      1219: getstatic     #363                // Field org/scalatest/events/RunAborted$.MODULE$:Lorg/scalatest/events/RunAborted$;
      1222: invokevirtual #365                // Method org/scalatest/events/RunAborted$.apply$default$6:()Lscala/Option;
      1225: getstatic     #363                // Field org/scalatest/events/RunAborted$.MODULE$:Lorg/scalatest/events/RunAborted$;
      1228: invokevirtual #367                // Method org/scalatest/events/RunAborted$.apply$default$7:()Lscala/Option;
      1231: getstatic     #363                // Field org/scalatest/events/RunAborted$.MODULE$:Lorg/scalatest/events/RunAborted$;
      1234: invokevirtual #368                // Method org/scalatest/events/RunAborted$.apply$default$8:()Lscala/Option;
      1237: getstatic     #363                // Field org/scalatest/events/RunAborted$.MODULE$:Lorg/scalatest/events/RunAborted$;
      1240: invokevirtual #369                // Method org/scalatest/events/RunAborted$.apply$default$9:()Ljava/lang/String;
      1243: getstatic     #363                // Field org/scalatest/events/RunAborted$.MODULE$:Lorg/scalatest/events/RunAborted$;
      1246: invokevirtual #370                // Method org/scalatest/events/RunAborted$.apply$default$10:()J
      1249: invokespecial #373                // Method org/scalatest/events/RunAborted."<init>":(Lorg/scalatest/events/Ordinal;Ljava/lang/String;Lscala/Option;Lscala/Option;Lscala/Option;Lscala/Option;Lscala/Option;Lscala/Option;Ljava/lang/String;J)V
      1252: invokeinterface #178,  2          // InterfaceMethod org/scalatest/Reporter.apply:(Lorg/scalatest/events/Event;)V
      1257: goto          1455
      1260: astore        48
      1262: invokestatic  #102                // Method java/lang/System.currentTimeMillis:()J
      1265: lload         14
      1267: lsub
      1268: lstore        49
      1270: aload_1
      1271: new           #354                // class org/scalatest/events/RunAborted
      1274: dup
      1275: aload         6
      1277: invokevirtual #150                // Method org/scalatest/Tracker.nextOrdinal:()Lorg/scalatest/events/Ordinal;
      1280: getstatic     #183                // Field org/scalatest/Resources$.MODULE$:Lorg/scalatest/Resources$;
      1283: aload         48
      1285: invokevirtual #383                // Method java/lang/NoClassDefFoundError.getMessage:()Ljava/lang/String;
      1288: invokevirtual #386                // Method org/scalatest/Resources$.cannotLoadClass:(Ljava/lang/Object;)Ljava/lang/String;
      1291: new           #82                 // class scala/Some
      1294: dup
      1295: aload         48
      1297: invokespecial #142                // Method scala/Some."<init>":(Ljava/lang/Object;)V
      1300: new           #82                 // class scala/Some
      1303: dup
      1304: lload         49
      1306: invokestatic  #258                // Method scala/runtime/BoxesRunTime.boxToLong:(J)Ljava/lang/Long;
      1309: invokespecial #142                // Method scala/Some."<init>":(Ljava/lang/Object;)V
      1312: getstatic     #363                // Field org/scalatest/events/RunAborted$.MODULE$:Lorg/scalatest/events/RunAborted$;
      1315: invokevirtual #364                // Method org/scalatest/events/RunAborted$.apply$default$5:()Lscala/Option;
      1318: getstatic     #363                // Field org/scalatest/events/RunAborted$.MODULE$:Lorg/scalatest/events/RunAborted$;
      1321: invokevirtual #365                // Method org/scalatest/events/RunAborted$.apply$default$6:()Lscala/Option;
      1324: getstatic     #363                // Field org/scalatest/events/RunAborted$.MODULE$:Lorg/scalatest/events/RunAborted$;
      1327: invokevirtual #367                // Method org/scalatest/events/RunAborted$.apply$default$7:()Lscala/Option;
      1330: getstatic     #363                // Field org/scalatest/events/RunAborted$.MODULE$:Lorg/scalatest/events/RunAborted$;
      1333: invokevirtual #368                // Method org/scalatest/events/RunAborted$.apply$default$8:()Lscala/Option;
      1336: getstatic     #363                // Field org/scalatest/events/RunAborted$.MODULE$:Lorg/scalatest/events/RunAborted$;
      1339: invokevirtual #369                // Method org/scalatest/events/RunAborted$.apply$default$9:()Ljava/lang/String;
      1342: getstatic     #363                // Field org/scalatest/events/RunAborted$.MODULE$:Lorg/scalatest/events/RunAborted$;
      1345: invokevirtual #370                // Method org/scalatest/events/RunAborted$.apply$default$10:()J
      1348: invokespecial #373                // Method org/scalatest/events/RunAborted."<init>":(Lorg/scalatest/events/Ordinal;Ljava/lang/String;Lscala/Option;Lscala/Option;Lscala/Option;Lscala/Option;Lscala/Option;Lscala/Option;Ljava/lang/String;J)V
      1351: invokeinterface #178,  2          // InterfaceMethod org/scalatest/Reporter.apply:(Lorg/scalatest/events/Event;)V
      1356: goto          1455
      1359: astore        51
      1361: invokestatic  #102                // Method java/lang/System.currentTimeMillis:()J
      1364: lload         14
      1366: lsub
      1367: lstore        52
      1369: aload_1
      1370: new           #354                // class org/scalatest/events/RunAborted
      1373: dup
      1374: aload         6
      1376: invokevirtual #150                // Method org/scalatest/Tracker.nextOrdinal:()Lorg/scalatest/events/Ordinal;
      1379: getstatic     #183                // Field org/scalatest/Resources$.MODULE$:Lorg/scalatest/Resources$;
      1382: aload         51
      1384: invokevirtual #390                // Method org/scalatest/Resources$.bigProblems:(Ljava/lang/Throwable;)Ljava/lang/String;
      1387: new           #82                 // class scala/Some
      1390: dup
      1391: aload         51
      1393: invokespecial #142                // Method scala/Some."<init>":(Ljava/lang/Object;)V
      1396: new           #82                 // class scala/Some
      1399: dup
      1400: lload         52
      1402: invokestatic  #258                // Method scala/runtime/BoxesRunTime.boxToLong:(J)Ljava/lang/Long;
      1405: invokespecial #142                // Method scala/Some."<init>":(Ljava/lang/Object;)V
      1408: getstatic     #363                // Field org/scalatest/events/RunAborted$.MODULE$:Lorg/scalatest/events/RunAborted$;
      1411: invokevirtual #364                // Method org/scalatest/events/RunAborted$.apply$default$5:()Lscala/Option;
      1414: getstatic     #363                // Field org/scalatest/events/RunAborted$.MODULE$:Lorg/scalatest/events/RunAborted$;
      1417: invokevirtual #365                // Method org/scalatest/events/RunAborted$.apply$default$6:()Lscala/Option;
      1420: getstatic     #363                // Field org/scalatest/events/RunAborted$.MODULE$:Lorg/scalatest/events/RunAborted$;
      1423: invokevirtual #367                // Method org/scalatest/events/RunAborted$.apply$default$7:()Lscala/Option;
      1426: getstatic     #363                // Field org/scalatest/events/RunAborted$.MODULE$:Lorg/scalatest/events/RunAborted$;
      1429: invokevirtual #368                // Method org/scalatest/events/RunAborted$.apply$default$8:()Lscala/Option;
      1432: getstatic     #363                // Field org/scalatest/events/RunAborted$.MODULE$:Lorg/scalatest/events/RunAborted$;
      1435: invokevirtual #369                // Method org/scalatest/events/RunAborted$.apply$default$9:()Ljava/lang/String;
      1438: getstatic     #363                // Field org/scalatest/events/RunAborted$.MODULE$:Lorg/scalatest/events/RunAborted$;
      1441: invokevirtual #370                // Method org/scalatest/events/RunAborted$.apply$default$10:()J
      1444: invokespecial #373                // Method org/scalatest/events/RunAborted."<init>":(Lorg/scalatest/events/Ordinal;Ljava/lang/String;Lscala/Option;Lscala/Option;Lscala/Option;Lscala/Option;Lscala/Option;Lscala/Option;Ljava/lang/String;J)V
      1447: invokeinterface #178,  2          // InterfaceMethod org/scalatest/Reporter.apply:(Lorg/scalatest/events/Event;)V
      1452: goto          1455
      1455: return
      Exception table:
         from    to  target type
           232   534   537   Class java/lang/RuntimeException
           100   861   864   Class java/lang/ClassNotFoundException
           100   861   963   Class java/lang/InstantiationException
           100   861  1062   Class java/lang/IllegalAccessException
           100   861  1161   Class java/lang/SecurityException
           100   861  1260   Class java/lang/NoClassDefFoundError
           100   861  1359   Class java/lang/Throwable
      StackMapTable: number_of_entries = 20
        frame_type = 254 /* append */
          offset_delta = 37
          locals = [ top, top, class scala/Option ]
        frame_type = 2 /* same */
        frame_type = 31 /* same */
        frame_type = 2 /* same */
        frame_type = 255 /* full_frame */
          offset_delta = 9
          locals = [ class org/scalatest/SuiteRerunner, class org/scalatest/Reporter, class org/scalatest/Stopper, class org/scalatest/Filter, class org/scalatest/ConfigMap, class scala/Option, class org/scalatest/Tracker, class java/lang/ClassLoader, class scala/collection/immutable/Set, top, class scala/Option ]
          stack = []
        frame_type = 255 /* full_frame */
          offset_delta = 84
          locals = [ class org/scalatest/SuiteRerunner, class org/scalatest/Reporter, class org/scalatest/Stopper, class org/scalatest/Filter, class org/scalatest/ConfigMap, class scala/Option, class org/scalatest/Tracker, class java/lang/ClassLoader, class scala/collection/immutable/Set, class scala/collection/immutable/Set, class scala/Option, top, top, class scala/collection/immutable/Set, long, class java/lang/Class, class org/scalatest/Suite, int ]
          stack = []
        frame_type = 66 /* same_locals_1_stack_item */
          stack = [ class scala/Option ]
        frame_type = 255 /* full_frame */
          offset_delta = 363
          locals = [ class org/scalatest/SuiteRerunner, class org/scalatest/Reporter, class org/scalatest/Stopper, class org/scalatest/Filter, class org/scalatest/ConfigMap, class scala/Option, class org/scalatest/Tracker, class java/lang/ClassLoader, class scala/collection/immutable/Set, class scala/collection/immutable/Set, class scala/Option, top, top, class scala/collection/immutable/Set, long, class java/lang/Class, class org/scalatest/Suite, int, class scala/Option, long ]
          stack = [ class java/lang/RuntimeException ]
        frame_type = 255 /* full_frame */
          offset_delta = 33
          locals = [ class org/scalatest/SuiteRerunner, class org/scalatest/Reporter, class org/scalatest/Stopper, class org/scalatest/Filter, class org/scalatest/ConfigMap, class scala/Option, class org/scalatest/Tracker, class java/lang/ClassLoader, class scala/collection/immutable/Set, class scala/collection/immutable/Set, class scala/Option, top, top, class scala/collection/immutable/Set, long, class java/lang/Class, class org/scalatest/Suite, int, class scala/Option, long, top, top, top, top, top, top, class java/lang/RuntimeException, class java/lang/String ]
          stack = []
        frame_type = 69 /* same_locals_1_stack_item */
          stack = [ class java/lang/String ]
        frame_type = 255 /* full_frame */
          offset_delta = 131
          locals = [ class org/scalatest/SuiteRerunner, class org/scalatest/Reporter, class org/scalatest/Stopper, class org/scalatest/Filter, class org/scalatest/ConfigMap, class scala/Option, class org/scalatest/Tracker, class java/lang/ClassLoader, class scala/collection/immutable/Set, class scala/collection/immutable/Set, class scala/Option, top, top, class scala/collection/immutable/Set, long, class java/lang/Class, class org/scalatest/Suite, int, class scala/Option, long ]
          stack = []
        frame_type = 255 /* full_frame */
          offset_delta = 85
          locals = [ class org/scalatest/SuiteRerunner, class org/scalatest/Reporter, class org/scalatest/Stopper, class org/scalatest/Filter, class org/scalatest/ConfigMap, class scala/Option, class org/scalatest/Tracker, class java/lang/ClassLoader, class scala/collection/immutable/Set, class scala/collection/immutable/Set, class scala/Option, top, top, class scala/collection/immutable/Set, long, class java/lang/Class, class org/scalatest/Suite, int, class scala/Option, long, top, top, top, top, top, top, top, top, top, top, top, top, long ]
          stack = []
        frame_type = 251 /* same_frame_extended */
          offset_delta = 65
        frame_type = 255 /* full_frame */
          offset_delta = 2
          locals = [ class org/scalatest/SuiteRerunner, class org/scalatest/Reporter, class org/scalatest/Stopper, class org/scalatest/Filter, class org/scalatest/ConfigMap, class scala/Option, class org/scalatest/Tracker, class java/lang/ClassLoader, class scala/collection/immutable/Set, class scala/collection/immutable/Set, class scala/Option, top, top, class scala/collection/immutable/Set, long ]
          stack = [ class java/lang/ClassNotFoundException ]
        frame_type = 247 /* same_locals_1_stack_item_frame_extended */
          offset_delta = 98
          stack = [ class java/lang/InstantiationException ]
        frame_type = 247 /* same_locals_1_stack_item_frame_extended */
          offset_delta = 98
          stack = [ class java/lang/IllegalAccessException ]
        frame_type = 247 /* same_locals_1_stack_item_frame_extended */
          offset_delta = 98
          stack = [ class java/lang/SecurityException ]
        frame_type = 247 /* same_locals_1_stack_item_frame_extended */
          offset_delta = 98
          stack = [ class java/lang/NoClassDefFoundError ]
        frame_type = 247 /* same_locals_1_stack_item_frame_extended */
          offset_delta = 98
          stack = [ class java/lang/Throwable ]
        frame_type = 251 /* same_frame_extended */
          offset_delta = 95
      LineNumberTable:
        line 39: 0
        line 40: 6
        line 41: 40
        line 39: 75
        line 43: 89
        line 45: 95
        line 48: 100
        line 49: 111
        line 50: 121
        line 54: 131
        line 55: 145
        line 57: 170
        line 59: 175
        line 61: 227
        line 64: 232
        line 65: 240
        line 67: 250
        line 69: 346
        line 71: 400
        line 72: 408
        line 73: 418
        line 75: 426
        line 79: 539
        line 81: 546
        line 82: 560
        line 84: 571
        line 85: 579
        line 87: 591
        line 88: 599
        line 92: 709
        line 93: 717
        line 94: 726
        line 97: 795
        line 102: 866
        line 103: 874
        line 106: 965
        line 107: 973
        line 110: 1064
        line 111: 1072
        line 114: 1163
        line 115: 1171
        line 120: 1262
        line 121: 1270
        line 124: 1361
        line 125: 1369
      LocalVariableTable:
        Start  Length  Slot  Name   Signature
           65       7    12   tti   Lscala/collection/immutable/Set;
          240     294    22 rawString   Ljava/lang/String;
          250     284    23 formatter   Lscala/Option;
          408     126    24 rawString2   Ljava/lang/String;
          418     116    25 formatter2   Lscala/Option;
          426     108    26 duration   J
          546     160    29 eMessage   Ljava/lang/String;
          579     127    30 rawString3   Ljava/lang/String;
          591     115    31 formatter3   Lscala/Option;
          599     107    32 duration   J
          537     169    28     e   Ljava/lang/RuntimeException;
          111     750    16 suiteClass   Ljava/lang/Class;
          121     740    17 suite   Lorg/scalatest/Suite;
          131     730    18 expectedTestCount   I
          175     686    19 rerunnable   Lscala/Option;
          232     629    20 suiteStartTime   J
          717     144    34 duration   J
          874      86    37 duration   J
          864      96    36     e   Ljava/lang/ClassNotFoundException;
          973      86    40 duration   J
          963      96    39     e   Ljava/lang/InstantiationException;
         1072      86    43 duration   J
         1062      96    42     e   Ljava/lang/IllegalAccessException;
         1171      86    46 duration   J
         1161      96    45     e   Ljava/lang/SecurityException;
         1270      86    49 duration   J
         1260      96    48     e   Ljava/lang/NoClassDefFoundError;
         1369      83    52 duration   J
         1359      93    51     e   Ljava/lang/Throwable;
           89    1366     9 tagsToInclude   Lscala/collection/immutable/Set;
           95    1360    13 tagsToExclude   Lscala/collection/immutable/Set;
          100    1355    14 runStartTime   J
            0    1456     0  this   Lorg/scalatest/SuiteRerunner;
            0    1456     1 report   Lorg/scalatest/Reporter;
            0    1456     2 stopper   Lorg/scalatest/Stopper;
            0    1456     3 filter   Lorg/scalatest/Filter;
            0    1456     4 configMap   Lorg/scalatest/ConfigMap;
            0    1456     5 distributor   Lscala/Option;
            0    1456     6 tracker   Lorg/scalatest/Tracker;
            0    1456     7 loader   Ljava/lang/ClassLoader;
    Signature: #22                          // (Lorg/scalatest/Reporter;Lorg/scalatest/Stopper;Lorg/scalatest/Filter;Lorg/scalatest/ConfigMap;Lscala/Option<Lorg/scalatest/Distributor;>;Lorg/scalatest/Tracker;Ljava/lang/ClassLoader;)V
    MethodParameters:
      Name                           Flags
      report                         final
      stopper                        final
      filter                         final
      configMap                      final
      distributor                    final
      tracker                        final
      loader                         final

  public org.scalatest.SuiteRerunner(java.lang.String);
    descriptor: (Ljava/lang/String;)V
    flags: (0x0001) ACC_PUBLIC
    Code:
      stack=9, locals=2, args_size=2
         0: aload_0
         1: aload_1
         2: putfield      #104                // Field suiteClassName:Ljava/lang/String;
         5: aload_0
         6: invokespecial #433                // Method java/lang/Object."<init>":()V
         9: getstatic     #438                // Field org/scalactic/Requirements$.MODULE$:Lorg/scalactic/Requirements$;
        12: invokevirtual #442                // Method org/scalactic/Requirements$.requirementsHelper:()Lorg/scalactic/Requirements$RequirementsHelper;
        15: iconst_1
        16: anewarray     #277                // class java/lang/String
        19: dup
        20: iconst_0
        21: ldc_w         #444                // String SuiteRerunner.this.suiteClassName
        24: aastore
        25: checkcast     #446                // class "[Ljava/lang/Object;"
        28: checkcast     #448                // class "[Ljava/lang/String;"
        31: iconst_1
        32: anewarray     #4                  // class java/lang/Object
        35: dup
        36: iconst_0
        37: aload_1
        38: aastore
        39: checkcast     #446                // class "[Ljava/lang/Object;"
        42: getstatic     #453                // Field org/scalactic/Prettifier$.MODULE$:Lorg/scalactic/Prettifier$;
        45: invokevirtual #457                // Method org/scalactic/Prettifier$.default:()Lorg/scalactic/Prettifier;
        48: new           #459                // class org/scalactic/source/Position
        51: dup
        52: ldc_w         #460                // String SuiteRerunner.scala
        55: ldc_w         #462                // String Please set the environment variable SCALACTIC_FILL_FILE_PATHNAMES to yes at compile time to enable this feature.
        58: bipush        33
        60: invokespecial #465                // Method org/scalactic/source/Position."<init>":(Ljava/lang/String;Ljava/lang/String;I)V
        63: invokevirtual #469                // Method org/scalactic/Requirements$RequirementsHelper.macroRequireNonNull:([Ljava/lang/String;[Ljava/lang/Object;Lorg/scalactic/Prettifier;Lorg/scalactic/source/Position;)V
        66: return
      LineNumberTable:
        line 31: 0
        line 33: 9
        line 31: 66
      LocalVariableTable:
        Start  Length  Slot  Name   Signature
            0      67     0  this   Lorg/scalatest/SuiteRerunner;
            0      67     1 suiteClassName   Ljava/lang/String;
    MethodParameters:
      Name                           Flags
      suiteClassName                 final
}
InnerClasses:
  public static #17= #14 of #16;          // RequirementsHelper=class org/scalactic/Requirements$RequirementsHelper of class org/scalactic/Requirements
SourceFile: "SuiteRerunner.scala"
RuntimeVisibleAnnotations:
  0: #10(#11=s#12)
    scala.reflect.ScalaSignature(
      bytes="\u0006\u0005m3Q\u0001B\u0003\u0001\u000b%A\u0001\u0002\b\u0001\u0003\u0002\u0003\u0006IA\b\u0005\u0006S\u0001!\tA\u000b\u0005\u0006[\u0001!\tA\f\u0002\u000e\'VLG/\u001a*feVtg.\u001a:\u000b\u0005\u00199\u0011!C:dC2\fG/Z:u\u0015\u0005A\u0011aA8sON!\u0001A\u0003\t\u0015!\tYa\"D\u0001\r\u0015\u0005i\u0011!B:dC2\f\u0017BA\b\r\u0005\u0019\te.\u001f*fMB\u0011\u0011CE\u0007\u0002\u000b%\u00111#\u0002\u0002\t%\u0016\u0014XO\u001c8feB\u0011QCG\u0007\u0002-)\u0011q\u0003G\u0001\u0003S>T\u0011!G\u0001\u0005U\u00064\u0018-\u0003\u0002\u001c-\ta1+\u001a:jC2L\'0\u00192mK\u0006q1/^5uK\u000ec\u0017m]:OC6,7\u0001\u0001\t\u0003?\u0019r!\u0001\t\u0013\u0011\u0005\u0005bQ\"\u0001\u0012\u000b\u0005\rj\u0012A\u0002\u001fs_>$h(\u0003\u0002&\u0019\u00051\u0001K]3eK\u001aL!a\n\u0015\u0003\rM#(/\u001b8h\u0015\t)C\"\u0001\u0004=S:LGO\u0010\u000b\u0003W1\u0002\"!\u0005\u0001\t\u000bq\u0011\u0001\u0019\u0001\u0010\u0002\u000b\u0005\u0004\b\u000f\\=\u0015\u0011=\u0012t\u0007P!G\u001dN\u0003\"a\u0003\u0019\n\u0005Eb!\u0001B+oSRDQaM\u0002A\u0002Q\naA]3q_J$\bCA\t6\u0013\t1TA\u0001\u0005SKB|\'\u000f^3s\u0011\u0015A4\u00011\u0001:\u0003\u001d\u0019Ho\u001c9qKJ\u0004\"!\u0005\u001e\n\u0005m*!aB*u_B\u0004XM\u001d\u0005\u0006{\r\u0001\rAP\u0001\u0007M&dG/\u001a:\u0011\u0005Ey\u0014B\u0001!\u0006\u0005\u00191\u0015\u000e\u001c;fe\")!i\u0001a\u0001\u0007\u0006I1m\u001c8gS\u001el\u0015\r\u001d\t\u0003#\u0011K!!R\u0003\u0003\u0013\r{gNZ5h\u001b\u0006\u0004\b\"B$\u0004\u0001\u0004A\u0015a\u00033jgR\u0014\u0018NY;u_J\u00042aC%L\u0013\tQEB\u0001\u0004PaRLwN\u001c\t\u0003#1K!!T\u0003\u0003\u0017\u0011K7\u000f\u001e:jEV$xN\u001d\u0005\u0006\u001f\u000e\u0001\r\u0001U\u0001\biJ\f7m[3s!\t\t\u0012+\u0003\u0002S\u000b\t9AK]1dW\u0016\u0014\b\"\u0002+\u0004\u0001\u0004)\u0016A\u00027pC\u0012,\'\u000f\u0005\u0002W36\tqK\u0003\u0002Y1\u0005!A.\u00198h\u0013\tQvKA\u0006DY\u0006\u001c8\u000fT8bI\u0016\u0014\b"
    )
  ScalaInlineInfo: length = 0xE (unknown attribute)
   01 00 00 02 00 59 00 8B 00 00 14 00 15 00
  ScalaSig: length = 0x3 (unknown attribute)
   05 02 00
