Classfile /Users/mw/Projects/slang-braindump/.jar/jar11/assemble/slang-braindump/assemble/content/org/scalatest/Tracker$.class
  Last modified May 29, 2022; size 954 bytes
  SHA-256 checksum 23f4bf03ddf4c4be6b02f1f826f12dc843cc9991b61a7b28a6bc2a6c104f21f5
  Compiled from "Tracker.scala"
public final class org.scalatest.Tracker$
  minor version: 0
  major version: 52
  flags: (0x0031) ACC_PUBLIC, ACC_FINAL, ACC_SUPER
  this_class: #2                          // org/scalatest/Tracker$
  super_class: #4                         // java/lang/Object
  interfaces: 0, fields: 2, methods: 5, attributes: 3
Constant pool:
   #1 = Utf8               org/scalatest/Tracker$
   #2 = Class              #1             // org/scalatest/Tracker$
   #3 = Utf8               java/lang/Object
   #4 = Class              #3             // java/lang/Object
   #5 = Utf8               Tracker.scala
   #6 = Utf8               MODULE$
   #7 = Utf8               Lorg/scalatest/Tracker$;
   #8 = Utf8               defaultTracker
   #9 = Utf8               Lorg/scalatest/Tracker;
  #10 = Utf8               <clinit>
  #11 = Utf8               ()V
  #12 = Utf8               <init>
  #13 = NameAndType        #12:#11        // "<init>":()V
  #14 = Methodref          #2.#13         // org/scalatest/Tracker$."<init>":()V
  #15 = NameAndType        #6:#7          // MODULE$:Lorg/scalatest/Tracker$;
  #16 = Fieldref           #2.#15         // org/scalatest/Tracker$.MODULE$:Lorg/scalatest/Tracker$;
  #17 = Utf8               org/scalatest/Tracker
  #18 = Class              #17            // org/scalatest/Tracker
  #19 = Utf8               $lessinit$greater$default$1
  #20 = Utf8               ()Lorg/scalatest/events/Ordinal;
  #21 = NameAndType        #19:#20        // $lessinit$greater$default$1:()Lorg/scalatest/events/Ordinal;
  #22 = Methodref          #2.#21         // org/scalatest/Tracker$.$lessinit$greater$default$1:()Lorg/scalatest/events/Ordinal;
  #23 = Utf8               (Lorg/scalatest/events/Ordinal;)V
  #24 = NameAndType        #12:#23        // "<init>":(Lorg/scalatest/events/Ordinal;)V
  #25 = Methodref          #18.#24        // org/scalatest/Tracker."<init>":(Lorg/scalatest/events/Ordinal;)V
  #26 = NameAndType        #8:#9          // defaultTracker:Lorg/scalatest/Tracker;
  #27 = Fieldref           #2.#26         // org/scalatest/Tracker$.defaultTracker:Lorg/scalatest/Tracker;
  #28 = Utf8               org/scalatest/events/Ordinal
  #29 = Class              #28            // org/scalatest/events/Ordinal
  #30 = Utf8               (I)V
  #31 = NameAndType        #12:#30        // "<init>":(I)V
  #32 = Methodref          #29.#31        // org/scalatest/events/Ordinal."<init>":(I)V
  #33 = Utf8               this
  #34 = Utf8               ()Lorg/scalatest/Tracker;
  #35 = Utf8               default
  #36 = NameAndType        #8:#34         // defaultTracker:()Lorg/scalatest/Tracker;
  #37 = Methodref          #2.#36         // org/scalatest/Tracker$.defaultTracker:()Lorg/scalatest/Tracker;
  #38 = Methodref          #4.#13         // java/lang/Object."<init>":()V
  #39 = Utf8               Code
  #40 = Utf8               LineNumberTable
  #41 = Utf8               LocalVariableTable
  #42 = Utf8               SourceFile
  #43 = Utf8               ScalaInlineInfo
  #44 = Utf8               Scala
{
  public static final org.scalatest.Tracker$ MODULE$;
    descriptor: Lorg/scalatest/Tracker$;
    flags: (0x0019) ACC_PUBLIC, ACC_STATIC, ACC_FINAL

  private static final org.scalatest.Tracker defaultTracker;
    descriptor: Lorg/scalatest/Tracker;
    flags: (0x001a) ACC_PRIVATE, ACC_STATIC, ACC_FINAL

  public static {};
    descriptor: ()V
    flags: (0x0009) ACC_PUBLIC, ACC_STATIC
    Code:
      stack=3, locals=0, args_size=0
         0: new           #2                  // class org/scalatest/Tracker$
         3: dup
         4: invokespecial #14                 // Method "<init>":()V
         7: putstatic     #16                 // Field MODULE$:Lorg/scalatest/Tracker$;
        10: new           #18                 // class org/scalatest/Tracker
        13: dup
        14: getstatic     #16                 // Field MODULE$:Lorg/scalatest/Tracker$;
        17: invokevirtual #22                 // Method $lessinit$greater$default$1:()Lorg/scalatest/events/Ordinal;
        20: invokespecial #25                 // Method org/scalatest/Tracker."<init>":(Lorg/scalatest/events/Ordinal;)V
        23: putstatic     #27                 // Field defaultTracker:Lorg/scalatest/Tracker;
        26: return
      LineNumberTable:
        line 100: 0
        line 101: 10
        line 100: 26

  public org.scalatest.events.Ordinal $lessinit$greater$default$1();
    descriptor: ()Lorg/scalatest/events/Ordinal;
    flags: (0x0001) ACC_PUBLIC
    Code:
      stack=3, locals=1, args_size=1
         0: new           #29                 // class org/scalatest/events/Ordinal
         3: dup
         4: iconst_0
         5: invokespecial #32                 // Method org/scalatest/events/Ordinal."<init>":(I)V
         8: areturn
      LineNumberTable:
        line 48: 0
      LocalVariableTable:
        Start  Length  Slot  Name   Signature
            0       9     0  this   Lorg/scalatest/Tracker$;

  private org.scalatest.Tracker defaultTracker();
    descriptor: ()Lorg/scalatest/Tracker;
    flags: (0x0002) ACC_PRIVATE
    Code:
      stack=1, locals=1, args_size=1
         0: getstatic     #27                 // Field defaultTracker:Lorg/scalatest/Tracker;
         3: areturn
      LineNumberTable:
        line 101: 0
      LocalVariableTable:
        Start  Length  Slot  Name   Signature
            0       4     0  this   Lorg/scalatest/Tracker$;

  public org.scalatest.Tracker default();
    descriptor: ()Lorg/scalatest/Tracker;
    flags: (0x0001) ACC_PUBLIC
    Code:
      stack=1, locals=1, args_size=1
         0: aload_0
         1: invokespecial #37                 // Method defaultTracker:()Lorg/scalatest/Tracker;
         4: areturn
      LineNumberTable:
        line 105: 0
      LocalVariableTable:
        Start  Length  Slot  Name   Signature
            0       5     0  this   Lorg/scalatest/Tracker$;

  private org.scalatest.Tracker$();
    descriptor: ()V
    flags: (0x0002) ACC_PRIVATE
    Code:
      stack=1, locals=1, args_size=1
         0: aload_0
         1: invokespecial #38                 // Method java/lang/Object."<init>":()V
         4: return
      LineNumberTable:
        line 106: 0
        line 100: 4
      LocalVariableTable:
        Start  Length  Slot  Name   Signature
            0       5     0  this   Lorg/scalatest/Tracker$;
}
SourceFile: "Tracker.scala"
  ScalaInlineInfo: length = 0x18 (unknown attribute)
   01 01 00 04 00 13 00 14 01 00 0C 00 0B 01 00 23
   00 22 01 00 08 00 22 01
  Scala: length = 0x0 (unknown attribute)

