Classfile /Users/mw/Projects/slang-braindump/.jar/jar11/assemble/slang-braindump/assemble/content/com/fasterxml/jackson/databind/jsontype/PolymorphicTypeValidator$Validity.class
  Last modified May 29, 2022; size 1445 bytes
  SHA-256 checksum c9a5eb70c48bc64f36be59916257e46dda2daab9318a99ca09fcb47687200dc6
  Compiled from "PolymorphicTypeValidator.java"
public final class com.fasterxml.jackson.databind.jsontype.PolymorphicTypeValidator$Validity extends java.lang.Enum<com.fasterxml.jackson.databind.jsontype.PolymorphicTypeValidator$Validity>
  minor version: 0
  major version: 52
  flags: (0x4031) ACC_PUBLIC, ACC_FINAL, ACC_SUPER, ACC_ENUM
  this_class: #4                          // com/fasterxml/jackson/databind/jsontype/PolymorphicTypeValidator$Validity
  super_class: #14                        // java/lang/Enum
  interfaces: 0, fields: 4, methods: 4, attributes: 3
Constant pool:
   #1 = Fieldref           #4.#41         // com/fasterxml/jackson/databind/jsontype/PolymorphicTypeValidator$Validity.$VALUES:[Lcom/fasterxml/jackson/databind/jsontype/PolymorphicTypeValidator$Validity;
   #2 = Methodref          #42.#43        // "[Lcom/fasterxml/jackson/databind/jsontype/PolymorphicTypeValidator$Validity;".clone:()Ljava/lang/Object;
   #3 = Class              #22            // "[Lcom/fasterxml/jackson/databind/jsontype/PolymorphicTypeValidator$Validity;"
   #4 = Class              #45            // com/fasterxml/jackson/databind/jsontype/PolymorphicTypeValidator$Validity
   #5 = Methodref          #14.#46        // java/lang/Enum.valueOf:(Ljava/lang/Class;Ljava/lang/String;)Ljava/lang/Enum;
   #6 = Methodref          #14.#47        // java/lang/Enum."<init>":(Ljava/lang/String;I)V
   #7 = String             #15            // ALLOWED
   #8 = Methodref          #4.#47         // com/fasterxml/jackson/databind/jsontype/PolymorphicTypeValidator$Validity."<init>":(Ljava/lang/String;I)V
   #9 = Fieldref           #4.#48         // com/fasterxml/jackson/databind/jsontype/PolymorphicTypeValidator$Validity.ALLOWED:Lcom/fasterxml/jackson/databind/jsontype/PolymorphicTypeValidator$Validity;
  #10 = String             #19            // DENIED
  #11 = Fieldref           #4.#49         // com/fasterxml/jackson/databind/jsontype/PolymorphicTypeValidator$Validity.DENIED:Lcom/fasterxml/jackson/databind/jsontype/PolymorphicTypeValidator$Validity;
  #12 = String             #20            // INDETERMINATE
  #13 = Fieldref           #4.#50         // com/fasterxml/jackson/databind/jsontype/PolymorphicTypeValidator$Validity.INDETERMINATE:Lcom/fasterxml/jackson/databind/jsontype/PolymorphicTypeValidator$Validity;
  #14 = Class              #51            // java/lang/Enum
  #15 = Utf8               ALLOWED
  #16 = Utf8               Validity
  #17 = Utf8               InnerClasses
  #18 = Utf8               Lcom/fasterxml/jackson/databind/jsontype/PolymorphicTypeValidator$Validity;
  #19 = Utf8               DENIED
  #20 = Utf8               INDETERMINATE
  #21 = Utf8               $VALUES
  #22 = Utf8               [Lcom/fasterxml/jackson/databind/jsontype/PolymorphicTypeValidator$Validity;
  #23 = Utf8               values
  #24 = Utf8               ()[Lcom/fasterxml/jackson/databind/jsontype/PolymorphicTypeValidator$Validity;
  #25 = Utf8               Code
  #26 = Utf8               LineNumberTable
  #27 = Utf8               valueOf
  #28 = Utf8               (Ljava/lang/String;)Lcom/fasterxml/jackson/databind/jsontype/PolymorphicTypeValidator$Validity;
  #29 = Utf8               LocalVariableTable
  #30 = Utf8               name
  #31 = Utf8               Ljava/lang/String;
  #32 = Utf8               <init>
  #33 = Utf8               (Ljava/lang/String;I)V
  #34 = Utf8               this
  #35 = Utf8               Signature
  #36 = Utf8               ()V
  #37 = Utf8               <clinit>
  #38 = Utf8               Ljava/lang/Enum<Lcom/fasterxml/jackson/databind/jsontype/PolymorphicTypeValidator$Validity;>;
  #39 = Utf8               SourceFile
  #40 = Utf8               PolymorphicTypeValidator.java
  #41 = NameAndType        #21:#22        // $VALUES:[Lcom/fasterxml/jackson/databind/jsontype/PolymorphicTypeValidator$Validity;
  #42 = Class              #22            // "[Lcom/fasterxml/jackson/databind/jsontype/PolymorphicTypeValidator$Validity;"
  #43 = NameAndType        #52:#53        // clone:()Ljava/lang/Object;
  #44 = Class              #54            // com/fasterxml/jackson/databind/jsontype/PolymorphicTypeValidator
  #45 = Utf8               com/fasterxml/jackson/databind/jsontype/PolymorphicTypeValidator$Validity
  #46 = NameAndType        #27:#55        // valueOf:(Ljava/lang/Class;Ljava/lang/String;)Ljava/lang/Enum;
  #47 = NameAndType        #32:#33        // "<init>":(Ljava/lang/String;I)V
  #48 = NameAndType        #15:#18        // ALLOWED:Lcom/fasterxml/jackson/databind/jsontype/PolymorphicTypeValidator$Validity;
  #49 = NameAndType        #19:#18        // DENIED:Lcom/fasterxml/jackson/databind/jsontype/PolymorphicTypeValidator$Validity;
  #50 = NameAndType        #20:#18        // INDETERMINATE:Lcom/fasterxml/jackson/databind/jsontype/PolymorphicTypeValidator$Validity;
  #51 = Utf8               java/lang/Enum
  #52 = Utf8               clone
  #53 = Utf8               ()Ljava/lang/Object;
  #54 = Utf8               com/fasterxml/jackson/databind/jsontype/PolymorphicTypeValidator
  #55 = Utf8               (Ljava/lang/Class;Ljava/lang/String;)Ljava/lang/Enum;
{
  public static final com.fasterxml.jackson.databind.jsontype.PolymorphicTypeValidator$Validity ALLOWED;
    descriptor: Lcom/fasterxml/jackson/databind/jsontype/PolymorphicTypeValidator$Validity;
    flags: (0x4019) ACC_PUBLIC, ACC_STATIC, ACC_FINAL, ACC_ENUM

  public static final com.fasterxml.jackson.databind.jsontype.PolymorphicTypeValidator$Validity DENIED;
    descriptor: Lcom/fasterxml/jackson/databind/jsontype/PolymorphicTypeValidator$Validity;
    flags: (0x4019) ACC_PUBLIC, ACC_STATIC, ACC_FINAL, ACC_ENUM

  public static final com.fasterxml.jackson.databind.jsontype.PolymorphicTypeValidator$Validity INDETERMINATE;
    descriptor: Lcom/fasterxml/jackson/databind/jsontype/PolymorphicTypeValidator$Validity;
    flags: (0x4019) ACC_PUBLIC, ACC_STATIC, ACC_FINAL, ACC_ENUM

  private static final com.fasterxml.jackson.databind.jsontype.PolymorphicTypeValidator$Validity[] $VALUES;
    descriptor: [Lcom/fasterxml/jackson/databind/jsontype/PolymorphicTypeValidator$Validity;
    flags: (0x101a) ACC_PRIVATE, ACC_STATIC, ACC_FINAL, ACC_SYNTHETIC

  public static com.fasterxml.jackson.databind.jsontype.PolymorphicTypeValidator$Validity[] values();
    descriptor: ()[Lcom/fasterxml/jackson/databind/jsontype/PolymorphicTypeValidator$Validity;
    flags: (0x0009) ACC_PUBLIC, ACC_STATIC
    Code:
      stack=1, locals=0, args_size=0
         0: getstatic     #1                  // Field $VALUES:[Lcom/fasterxml/jackson/databind/jsontype/PolymorphicTypeValidator$Validity;
         3: invokevirtual #2                  // Method "[Lcom/fasterxml/jackson/databind/jsontype/PolymorphicTypeValidator$Validity;".clone:()Ljava/lang/Object;
         6: checkcast     #3                  // class "[Lcom/fasterxml/jackson/databind/jsontype/PolymorphicTypeValidator$Validity;"
         9: areturn
      LineNumberTable:
        line 58: 0

  public static com.fasterxml.jackson.databind.jsontype.PolymorphicTypeValidator$Validity valueOf(java.lang.String);
    descriptor: (Ljava/lang/String;)Lcom/fasterxml/jackson/databind/jsontype/PolymorphicTypeValidator$Validity;
    flags: (0x0009) ACC_PUBLIC, ACC_STATIC
    Code:
      stack=2, locals=1, args_size=1
         0: ldc           #4                  // class com/fasterxml/jackson/databind/jsontype/PolymorphicTypeValidator$Validity
         2: aload_0
         3: invokestatic  #5                  // Method java/lang/Enum.valueOf:(Ljava/lang/Class;Ljava/lang/String;)Ljava/lang/Enum;
         6: checkcast     #4                  // class com/fasterxml/jackson/databind/jsontype/PolymorphicTypeValidator$Validity
         9: areturn
      LineNumberTable:
        line 58: 0
      LocalVariableTable:
        Start  Length  Slot  Name   Signature
            0      10     0  name   Ljava/lang/String;

  private com.fasterxml.jackson.databind.jsontype.PolymorphicTypeValidator$Validity();
    descriptor: (Ljava/lang/String;I)V
    flags: (0x0002) ACC_PRIVATE
    Code:
      stack=3, locals=3, args_size=3
         0: aload_0
         1: aload_1
         2: iload_2
         3: invokespecial #6                  // Method java/lang/Enum."<init>":(Ljava/lang/String;I)V
         6: return
      LineNumberTable:
        line 58: 0
      LocalVariableTable:
        Start  Length  Slot  Name   Signature
            0       7     0  this   Lcom/fasterxml/jackson/databind/jsontype/PolymorphicTypeValidator$Validity;
    Signature: #36                          // ()V

  static {};
    descriptor: ()V
    flags: (0x0008) ACC_STATIC
    Code:
      stack=4, locals=0, args_size=0
         0: new           #4                  // class com/fasterxml/jackson/databind/jsontype/PolymorphicTypeValidator$Validity
         3: dup
         4: ldc           #7                  // String ALLOWED
         6: iconst_0
         7: invokespecial #8                  // Method "<init>":(Ljava/lang/String;I)V
        10: putstatic     #9                  // Field ALLOWED:Lcom/fasterxml/jackson/databind/jsontype/PolymorphicTypeValidator$Validity;
        13: new           #4                  // class com/fasterxml/jackson/databind/jsontype/PolymorphicTypeValidator$Validity
        16: dup
        17: ldc           #10                 // String DENIED
        19: iconst_1
        20: invokespecial #8                  // Method "<init>":(Ljava/lang/String;I)V
        23: putstatic     #11                 // Field DENIED:Lcom/fasterxml/jackson/databind/jsontype/PolymorphicTypeValidator$Validity;
        26: new           #4                  // class com/fasterxml/jackson/databind/jsontype/PolymorphicTypeValidator$Validity
        29: dup
        30: ldc           #12                 // String INDETERMINATE
        32: iconst_2
        33: invokespecial #8                  // Method "<init>":(Ljava/lang/String;I)V
        36: putstatic     #13                 // Field INDETERMINATE:Lcom/fasterxml/jackson/databind/jsontype/PolymorphicTypeValidator$Validity;
        39: iconst_3
        40: anewarray     #4                  // class com/fasterxml/jackson/databind/jsontype/PolymorphicTypeValidator$Validity
        43: dup
        44: iconst_0
        45: getstatic     #9                  // Field ALLOWED:Lcom/fasterxml/jackson/databind/jsontype/PolymorphicTypeValidator$Validity;
        48: aastore
        49: dup
        50: iconst_1
        51: getstatic     #11                 // Field DENIED:Lcom/fasterxml/jackson/databind/jsontype/PolymorphicTypeValidator$Validity;
        54: aastore
        55: dup
        56: iconst_2
        57: getstatic     #13                 // Field INDETERMINATE:Lcom/fasterxml/jackson/databind/jsontype/PolymorphicTypeValidator$Validity;
        60: aastore
        61: putstatic     #1                  // Field $VALUES:[Lcom/fasterxml/jackson/databind/jsontype/PolymorphicTypeValidator$Validity;
        64: return
      LineNumberTable:
        line 62: 0
        line 67: 13
        line 76: 26
        line 58: 39
}
Signature: #38                          // Ljava/lang/Enum<Lcom/fasterxml/jackson/databind/jsontype/PolymorphicTypeValidator$Validity;>;
SourceFile: "PolymorphicTypeValidator.java"
InnerClasses:
  public static final #16= #4 of #44;     // Validity=class com/fasterxml/jackson/databind/jsontype/PolymorphicTypeValidator$Validity of class com/fasterxml/jackson/databind/jsontype/PolymorphicTypeValidator
