Classfile /Users/mw/Projects/slang-braindump/.jar/jar8/assemble/slang-braindump/assemble/content/scala/collection/concurrent/INodeBase.class
  Last modified May 29, 2022; size 1625 bytes
  SHA-256 checksum c6c2849db11ea7f5e872711f8c4f1735f0c0ff7955360ed1c57c33ae934e4750
  Compiled from "INodeBase.java"
abstract class scala.collection.concurrent.INodeBase<K extends java.lang.Object, V extends java.lang.Object> extends scala.collection.concurrent.BasicNode
  minor version: 0
  major version: 52
  flags: (0x0420) ACC_SUPER, ACC_ABSTRACT
  this_class: #4                          // scala/collection/concurrent/INodeBase
  super_class: #13                        // scala/collection/concurrent/BasicNode
  interfaces: 0, fields: 5, methods: 3, attributes: 2
Constant pool:
   #1 = Methodref          #13.#43        // scala/collection/concurrent/BasicNode."<init>":()V
   #2 = Fieldref           #4.#44         // scala/collection/concurrent/INodeBase.mainnode:Lscala/collection/concurrent/MainNode;
   #3 = Fieldref           #4.#45         // scala/collection/concurrent/INodeBase.gen:Lscala/collection/concurrent/Gen;
   #4 = Class              #46            // scala/collection/concurrent/INodeBase
   #5 = Class              #47            // scala/collection/concurrent/MainNode
   #6 = String             #21            // mainnode
   #7 = Methodref          #48.#49        // java/util/concurrent/atomic/AtomicReferenceFieldUpdater.newUpdater:(Ljava/lang/Class;Ljava/lang/Class;Ljava/lang/String;)Ljava/util/concurrent/atomic/AtomicReferenceFieldUpdater;
   #8 = Fieldref           #4.#50         // scala/collection/concurrent/INodeBase.updater:Ljava/util/concurrent/atomic/AtomicReferenceFieldUpdater;
   #9 = Class              #51            // java/lang/Object
  #10 = Methodref          #9.#43         // java/lang/Object."<init>":()V
  #11 = Fieldref           #4.#52         // scala/collection/concurrent/INodeBase.RESTART:Ljava/lang/Object;
  #12 = Fieldref           #4.#53         // scala/collection/concurrent/INodeBase.NO_SUCH_ELEMENT_SENTINEL:Ljava/lang/Object;
  #13 = Class              #54            // scala/collection/concurrent/BasicNode
  #14 = Utf8               updater
  #15 = Utf8               Ljava/util/concurrent/atomic/AtomicReferenceFieldUpdater;
  #16 = Utf8               Signature
  #17 = Utf8               Ljava/util/concurrent/atomic/AtomicReferenceFieldUpdater<Lscala/collection/concurrent/INodeBase<**>;Lscala/collection/concurrent/MainNode<**>;>;
  #18 = Utf8               RESTART
  #19 = Utf8               Ljava/lang/Object;
  #20 = Utf8               NO_SUCH_ELEMENT_SENTINEL
  #21 = Utf8               mainnode
  #22 = Utf8               Lscala/collection/concurrent/MainNode;
  #23 = Utf8               Lscala/collection/concurrent/MainNode<TK;TV;>;
  #24 = Utf8               gen
  #25 = Utf8               Lscala/collection/concurrent/Gen;
  #26 = Utf8               <init>
  #27 = Utf8               (Lscala/collection/concurrent/Gen;)V
  #28 = Utf8               Code
  #29 = Utf8               LineNumberTable
  #30 = Utf8               LocalVariableTable
  #31 = Utf8               this
  #32 = Utf8               Lscala/collection/concurrent/INodeBase;
  #33 = Utf8               generation
  #34 = Utf8               LocalVariableTypeTable
  #35 = Utf8               Lscala/collection/concurrent/INodeBase<TK;TV;>;
  #36 = Utf8               prev
  #37 = Utf8               ()Lscala/collection/concurrent/BasicNode;
  #38 = Utf8               <clinit>
  #39 = Utf8               ()V
  #40 = Utf8               <K:Ljava/lang/Object;V:Ljava/lang/Object;>Lscala/collection/concurrent/BasicNode;
  #41 = Utf8               SourceFile
  #42 = Utf8               INodeBase.java
  #43 = NameAndType        #26:#39        // "<init>":()V
  #44 = NameAndType        #21:#22        // mainnode:Lscala/collection/concurrent/MainNode;
  #45 = NameAndType        #24:#25        // gen:Lscala/collection/concurrent/Gen;
  #46 = Utf8               scala/collection/concurrent/INodeBase
  #47 = Utf8               scala/collection/concurrent/MainNode
  #48 = Class              #55            // java/util/concurrent/atomic/AtomicReferenceFieldUpdater
  #49 = NameAndType        #56:#57        // newUpdater:(Ljava/lang/Class;Ljava/lang/Class;Ljava/lang/String;)Ljava/util/concurrent/atomic/AtomicReferenceFieldUpdater;
  #50 = NameAndType        #14:#15        // updater:Ljava/util/concurrent/atomic/AtomicReferenceFieldUpdater;
  #51 = Utf8               java/lang/Object
  #52 = NameAndType        #18:#19        // RESTART:Ljava/lang/Object;
  #53 = NameAndType        #20:#19        // NO_SUCH_ELEMENT_SENTINEL:Ljava/lang/Object;
  #54 = Utf8               scala/collection/concurrent/BasicNode
  #55 = Utf8               java/util/concurrent/atomic/AtomicReferenceFieldUpdater
  #56 = Utf8               newUpdater
  #57 = Utf8               (Ljava/lang/Class;Ljava/lang/Class;Ljava/lang/String;)Ljava/util/concurrent/atomic/AtomicReferenceFieldUpdater;
{
  public static final java.util.concurrent.atomic.AtomicReferenceFieldUpdater<scala.collection.concurrent.INodeBase<?, ?>, scala.collection.concurrent.MainNode<?, ?>> updater;
    descriptor: Ljava/util/concurrent/atomic/AtomicReferenceFieldUpdater;
    flags: (0x0019) ACC_PUBLIC, ACC_STATIC, ACC_FINAL
    Signature: #17                          // Ljava/util/concurrent/atomic/AtomicReferenceFieldUpdater<Lscala/collection/concurrent/INodeBase<**>;Lscala/collection/concurrent/MainNode<**>;>;

  static final java.lang.Object RESTART;
    descriptor: Ljava/lang/Object;
    flags: (0x0018) ACC_STATIC, ACC_FINAL

  static final java.lang.Object NO_SUCH_ELEMENT_SENTINEL;
    descriptor: Ljava/lang/Object;
    flags: (0x0018) ACC_STATIC, ACC_FINAL

  public volatile scala.collection.concurrent.MainNode<K, V> mainnode;
    descriptor: Lscala/collection/concurrent/MainNode;
    flags: (0x0041) ACC_PUBLIC, ACC_VOLATILE
    Signature: #23                          // Lscala/collection/concurrent/MainNode<TK;TV;>;

  public final scala.collection.concurrent.Gen gen;
    descriptor: Lscala/collection/concurrent/Gen;
    flags: (0x0011) ACC_PUBLIC, ACC_FINAL

  public scala.collection.concurrent.INodeBase(scala.collection.concurrent.Gen);
    descriptor: (Lscala/collection/concurrent/Gen;)V
    flags: (0x0001) ACC_PUBLIC
    Code:
      stack=2, locals=2, args_size=2
         0: aload_0
         1: invokespecial #1                  // Method scala/collection/concurrent/BasicNode."<init>":()V
         4: aload_0
         5: aconst_null
         6: putfield      #2                  // Field mainnode:Lscala/collection/concurrent/MainNode;
         9: aload_0
        10: aload_1
        11: putfield      #3                  // Field gen:Lscala/collection/concurrent/Gen;
        14: return
      LineNumberTable:
        line 31: 0
        line 27: 4
        line 32: 9
        line 33: 14
      LocalVariableTable:
        Start  Length  Slot  Name   Signature
            0      15     0  this   Lscala/collection/concurrent/INodeBase;
            0      15     1 generation   Lscala/collection/concurrent/Gen;
      LocalVariableTypeTable:
        Start  Length  Slot  Name   Signature
            0      15     0  this   Lscala/collection/concurrent/INodeBase<TK;TV;>;

  public scala.collection.concurrent.BasicNode prev();
    descriptor: ()Lscala/collection/concurrent/BasicNode;
    flags: (0x0001) ACC_PUBLIC
    Code:
      stack=1, locals=1, args_size=1
         0: aconst_null
         1: areturn
      LineNumberTable:
        line 36: 0
      LocalVariableTable:
        Start  Length  Slot  Name   Signature
            0       2     0  this   Lscala/collection/concurrent/INodeBase;
      LocalVariableTypeTable:
        Start  Length  Slot  Name   Signature
            0       2     0  this   Lscala/collection/concurrent/INodeBase<TK;TV;>;

  static {};
    descriptor: ()V
    flags: (0x0008) ACC_STATIC
    Code:
      stack=3, locals=0, args_size=0
         0: ldc           #4                  // class scala/collection/concurrent/INodeBase
         2: ldc           #5                  // class scala/collection/concurrent/MainNode
         4: ldc           #6                  // String mainnode
         6: invokestatic  #7                  // Method java/util/concurrent/atomic/AtomicReferenceFieldUpdater.newUpdater:(Ljava/lang/Class;Ljava/lang/Class;Ljava/lang/String;)Ljava/util/concurrent/atomic/AtomicReferenceFieldUpdater;
         9: putstatic     #8                  // Field updater:Ljava/util/concurrent/atomic/AtomicReferenceFieldUpdater;
        12: new           #9                  // class java/lang/Object
        15: dup
        16: invokespecial #10                 // Method java/lang/Object."<init>":()V
        19: putstatic     #11                 // Field RESTART:Ljava/lang/Object;
        22: new           #9                  // class java/lang/Object
        25: dup
        26: invokespecial #10                 // Method java/lang/Object."<init>":()V
        29: putstatic     #12                 // Field NO_SUCH_ELEMENT_SENTINEL:Ljava/lang/Object;
        32: return
      LineNumberTable:
        line 20: 0
        line 21: 6
        line 23: 12
        line 25: 22
}
Signature: #40                          // <K:Ljava/lang/Object;V:Ljava/lang/Object;>Lscala/collection/concurrent/BasicNode;
SourceFile: "INodeBase.java"
