Classfile /Users/mw/Projects/slang-braindump/.jar/jar8/assemble/slang-braindump/assemble/content/org/scalactic/AndBool.class
  Last modified May 29, 2022; size 6721 bytes
  SHA-256 checksum db1650a704fa4d6046f0fb5161c9dde7dea5ab587098df03acda459b7e6286e7
  Compiled from "Bool.scala"
public class org.scalactic.AndBool implements org.scalactic.Bool
  minor version: 0
  major version: 52
  flags: (0x0021) ACC_PUBLIC, ACC_SUPER
  this_class: #2                          // org/scalactic/AndBool
  super_class: #4                         // java/lang/Object
  interfaces: 1, fields: 6, methods: 27, attributes: 4
Constant pool:
    #1 = Utf8               org/scalactic/AndBool
    #2 = Class              #1            // org/scalactic/AndBool
    #3 = Utf8               java/lang/Object
    #4 = Class              #3            // java/lang/Object
    #5 = Utf8               org/scalactic/Bool
    #6 = Class              #5            // org/scalactic/Bool
    #7 = Utf8               Bool.scala
    #8 = Utf8               Lscala/reflect/ScalaSignature;
    #9 = Utf8               bytes
   #10 = Utf8               \u0006\u0005Y3Qa\u0004\t\u0001!QA\u0001b\b\u0001\u0003\u0002\u0003\u0006Ia\u0007\u0005\tC\u0001\u0011\t\u0011*A\u0005E!AQ\u0005\u0001BC\u0002\u0013\u0005a\u0005\u0003\u0005+\u0001\t\u0005\t\u0015!\u0003(\u0011\u0015Y\u0003\u0001\"\u0001-\u0011!\t\u0004\u0001#b\u0001\n\u0003\u0011\u0004\"\u0002\u001c\u0001\t\u00039\u0004\"B\"\u0001\t\u00039\u0004\"\u0002#\u0001\t\u00039\u0004\"B#\u0001\t\u00039\u0004\"\u0002$\u0001\t\u00039\u0005\"B*\u0001\t\u00039\u0005\"\u0002+\u0001\t\u00039\u0005\"B+\u0001\t\u00039%aB!oI\n{w\u000e\u001c\u0006\u0003#I\t\u0011b]2bY\u0006\u001cG/[2\u000b\u0003M\t1a\u001c:h\'\r\u0001Qc\u0007\t\u0003-ei\u0011a\u0006\u0006\u00021\u0005)1oY1mC&\u0011!d\u0006\u0002\u0007\u0003:L(+\u001a4\u0011\u0005qiR\"\u0001\t\n\u0005y\u0001\"\u0001\u0002\"p_2\fQAY8pYF\u001a\u0001!A\u0003c_>d\'\u0007E\u0002\u0017GmI!\u0001J\f\u0003\u0011q\u0012\u0017P\\1nKz\n!\u0002\u001d:fiRLg-[3s+\u00059\u0003C\u0001\u000f)\u0013\tI\u0003C\u0001\u0006Qe\u0016$H/\u001b4jKJ\f1\u0002\u001d:fiRLg-[3sA\u00051A(\u001b8jiz\"B!\f\u00180aA\u0011A\u0004\u0001\u0005\u0006?\u0015\u0001\ra\u0007\u0005\u0007C\u0015!\t\u0019\u0001\u0012\t\u000b\u0015*\u0001\u0019A\u0014\u0002\u000bY\fG.^3\u0016\u0003M\u0002\"A\u0006\u001b\n\u0005U:\"a\u0002\"p_2,\u0017M\\\u0001\u0012e\u0006<h)Y5mkJ,W*Z:tC\u001e,W#\u0001\u001d\u0011\u0005e\u0002eB\u0001\u001e?!\tYt#D\u0001=\u0015\ti\u0004%\u0001\u0004=e>|GOP\u0005\u0003\u007f]\ta\u0001\u0015:fI\u00164\u0017BA!C\u0005\u0019\u0019FO]5oO*\u0011qhF\u0001\u0019e\u0006<h*Z4bi\u0016$g)Y5mkJ,W*Z:tC\u001e,\u0017\u0001\b:bo6KGmU3oi\u0016t7-\u001a$bS2,(/Z\'fgN\fw-Z\u0001$e\u0006<X*\u001b3TK:$XM\\2f\u001d\u0016<\u0017\r^3e\r\u0006LG.\u001e:f\u001b\u0016\u001c8/Y4f\u0003I1\u0017-\u001b7ve\u0016lUm]:bO\u0016\f%oZ:\u0016\u0003!\u00032!\u0013(Q\u001b\u0005Q%BA&M\u0003%IW.\\;uC\ndWM\u0003\u0002N/\u0005Q1m\u001c7mK\u000e$\u0018n\u001c8\n\u0005=S%A\u0002,fGR|\'\u000f\u0005\u0002\u001d#&\u0011!\u000b\u0005\u0002\u000f+:\fXo\u001c;fIN#(/\u001b8h\u0003eqWmZ1uK\u00124\u0015-\u001b7ve\u0016lUm]:bO\u0016\f%oZ:\u0002;5LGmU3oi\u0016t7-\u001a$bS2,(/Z\'fgN\fw-Z!sON\fA%\\5e\'\u0016tG/\u001a8dK:+w-\u0019;fI\u001a\u000b\u0017\u000e\\;sK6+7o]1hK\u0006\u0013xm\u001d
   #11 = Utf8               value
   #12 = Utf8               Z
   #13 = Utf8               bool1
   #14 = Utf8               Lorg/scalactic/Bool;
   #15 = Utf8               bool2
   #16 = Utf8               Lscala/Function0;
   #17 = Utf8               Lscala/Function0<Lorg/scalactic/Bool;>;
   #18 = Utf8               prettifier
   #19 = Utf8               Lorg/scalactic/Prettifier;
   #20 = Utf8               analysis
   #21 = Utf8               Lscala/collection/immutable/IndexedSeq;
   #22 = Utf8               Lscala/collection/immutable/IndexedSeq<Ljava/lang/String;>;
   #23 = Utf8               bitmap$0
   #24 = Utf8               B
   #25 = Utf8               failureMessage
   #26 = Utf8               ()Ljava/lang/String;
   #27 = Utf8               failureMessage$
   #28 = Utf8               (Lorg/scalactic/Bool;)Ljava/lang/String;
   #29 = NameAndType        #27:#28       // failureMessage$:(Lorg/scalactic/Bool;)Ljava/lang/String;
   #30 = InterfaceMethodref #6.#29        // org/scalactic/Bool.failureMessage$:(Lorg/scalactic/Bool;)Ljava/lang/String;
   #31 = Utf8               this
   #32 = Utf8               Lorg/scalactic/AndBool;
   #33 = Utf8               negatedFailureMessage
   #34 = Utf8               negatedFailureMessage$
   #35 = NameAndType        #34:#28       // negatedFailureMessage$:(Lorg/scalactic/Bool;)Ljava/lang/String;
   #36 = InterfaceMethodref #6.#35        // org/scalactic/Bool.negatedFailureMessage$:(Lorg/scalactic/Bool;)Ljava/lang/String;
   #37 = Utf8               midSentenceFailureMessage
   #38 = Utf8               midSentenceFailureMessage$
   #39 = NameAndType        #38:#28       // midSentenceFailureMessage$:(Lorg/scalactic/Bool;)Ljava/lang/String;
   #40 = InterfaceMethodref #6.#39        // org/scalactic/Bool.midSentenceFailureMessage$:(Lorg/scalactic/Bool;)Ljava/lang/String;
   #41 = Utf8               midSentenceNegatedFailureMessage
   #42 = Utf8               midSentenceNegatedFailureMessage$
   #43 = NameAndType        #42:#28       // midSentenceNegatedFailureMessage$:(Lorg/scalactic/Bool;)Ljava/lang/String;
   #44 = InterfaceMethodref #6.#43        // org/scalactic/Bool.midSentenceNegatedFailureMessage$:(Lorg/scalactic/Bool;)Ljava/lang/String;
   #45 = Utf8               $amp$amp
   #46 = Utf8               (Lscala/Function0;)Lorg/scalactic/Bool;
   #47 = Utf8               (Lscala/Function0<Lorg/scalactic/Bool;>;)Lorg/scalactic/Bool;
   #48 = Utf8               bool
   #49 = Utf8               $amp$amp$
   #50 = Utf8               (Lorg/scalactic/Bool;Lscala/Function0;)Lorg/scalactic/Bool;
   #51 = NameAndType        #49:#50       // $amp$amp$:(Lorg/scalactic/Bool;Lscala/Function0;)Lorg/scalactic/Bool;
   #52 = InterfaceMethodref #6.#51        // org/scalactic/Bool.$amp$amp$:(Lorg/scalactic/Bool;Lscala/Function0;)Lorg/scalactic/Bool;
   #53 = Utf8               $amp
   #54 = Utf8               $amp$
   #55 = NameAndType        #54:#50       // $amp$:(Lorg/scalactic/Bool;Lscala/Function0;)Lorg/scalactic/Bool;
   #56 = InterfaceMethodref #6.#55        // org/scalactic/Bool.$amp$:(Lorg/scalactic/Bool;Lscala/Function0;)Lorg/scalactic/Bool;
   #57 = Utf8               $bar$bar
   #58 = Utf8               $bar$bar$
   #59 = NameAndType        #58:#50       // $bar$bar$:(Lorg/scalactic/Bool;Lscala/Function0;)Lorg/scalactic/Bool;
   #60 = InterfaceMethodref #6.#59        // org/scalactic/Bool.$bar$bar$:(Lorg/scalactic/Bool;Lscala/Function0;)Lorg/scalactic/Bool;
   #61 = Utf8               $bar
   #62 = Utf8               $bar$
   #63 = NameAndType        #62:#50       // $bar$:(Lorg/scalactic/Bool;Lscala/Function0;)Lorg/scalactic/Bool;
   #64 = InterfaceMethodref #6.#63        // org/scalactic/Bool.$bar$:(Lorg/scalactic/Bool;Lscala/Function0;)Lorg/scalactic/Bool;
   #65 = Utf8               unary_$bang
   #66 = Utf8               ()Lorg/scalactic/Bool;
   #67 = Utf8               unary_$bang$
   #68 = Utf8               (Lorg/scalactic/Bool;)Lorg/scalactic/Bool;
   #69 = NameAndType        #67:#68       // unary_$bang$:(Lorg/scalactic/Bool;)Lorg/scalactic/Bool;
   #70 = InterfaceMethodref #6.#69        // org/scalactic/Bool.unary_$bang$:(Lorg/scalactic/Bool;)Lorg/scalactic/Bool;
   #71 = Utf8               analysis$lzycompute
   #72 = Utf8               ()Lscala/collection/immutable/IndexedSeq;
   #73 = Utf8               ()Lscala/collection/immutable/IndexedSeq<Ljava/lang/String;>;
   #74 = NameAndType        #23:#24       // bitmap$0:B
   #75 = Fieldref           #2.#74        // org/scalactic/AndBool.bitmap$0:B
   #76 = Utf8               analysis$
   #77 = Utf8               (Lorg/scalactic/Bool;)Lscala/collection/immutable/IndexedSeq;
   #78 = NameAndType        #76:#77       // analysis$:(Lorg/scalactic/Bool;)Lscala/collection/immutable/IndexedSeq;
   #79 = InterfaceMethodref #6.#78        // org/scalactic/Bool.analysis$:(Lorg/scalactic/Bool;)Lscala/collection/immutable/IndexedSeq;
   #80 = NameAndType        #20:#21       // analysis:Lscala/collection/immutable/IndexedSeq;
   #81 = Fieldref           #2.#80        // org/scalactic/AndBool.analysis:Lscala/collection/immutable/IndexedSeq;
   #82 = Utf8               java/lang/Throwable
   #83 = Class              #82           // java/lang/Throwable
   #84 = NameAndType        #71:#72       // analysis$lzycompute:()Lscala/collection/immutable/IndexedSeq;
   #85 = Methodref          #2.#84        // org/scalactic/AndBool.analysis$lzycompute:()Lscala/collection/immutable/IndexedSeq;
   #86 = Utf8               scala/collection/immutable/IndexedSeq
   #87 = Class              #86           // scala/collection/immutable/IndexedSeq
   #88 = Utf8               ()Lorg/scalactic/Prettifier;
   #89 = NameAndType        #18:#19       // prettifier:Lorg/scalactic/Prettifier;
   #90 = Fieldref           #2.#89        // org/scalactic/AndBool.prettifier:Lorg/scalactic/Prettifier;
   #91 = Utf8               value$lzycompute
   #92 = Utf8               ()Z
   #93 = NameAndType        #13:#14       // bool1:Lorg/scalactic/Bool;
   #94 = Fieldref           #2.#93        // org/scalactic/AndBool.bool1:Lorg/scalactic/Bool;
   #95 = NameAndType        #11:#92       // value:()Z
   #96 = InterfaceMethodref #6.#95        // org/scalactic/Bool.value:()Z
   #97 = NameAndType        #15:#16       // bool2:Lscala/Function0;
   #98 = Fieldref           #2.#97        // org/scalactic/AndBool.bool2:Lscala/Function0;
   #99 = Utf8               scala/Function0
  #100 = Class              #99           // scala/Function0
  #101 = Utf8               apply
  #102 = Utf8               ()Ljava/lang/Object;
  #103 = NameAndType        #101:#102     // apply:()Ljava/lang/Object;
  #104 = InterfaceMethodref #100.#103     // scala/Function0.apply:()Ljava/lang/Object;
  #105 = NameAndType        #11:#12       // value:Z
  #106 = Fieldref           #2.#105       // org/scalactic/AndBool.value:Z
  #107 = NameAndType        #91:#92       // value$lzycompute:()Z
  #108 = Methodref          #2.#107       // org/scalactic/AndBool.value$lzycompute:()Z
  #109 = Utf8               rawFailureMessage
  #110 = Utf8               org/scalactic/Resources$
  #111 = Class              #110          // org/scalactic/Resources$
  #112 = Utf8               MODULE$
  #113 = Utf8               Lorg/scalactic/Resources$;
  #114 = NameAndType        #112:#113     // MODULE$:Lorg/scalactic/Resources$;
  #115 = Fieldref           #111.#114     // org/scalactic/Resources$.MODULE$:Lorg/scalactic/Resources$;
  #116 = Utf8               rawCommaBut
  #117 = NameAndType        #116:#26      // rawCommaBut:()Ljava/lang/String;
  #118 = Methodref          #111.#117     // org/scalactic/Resources$.rawCommaBut:()Ljava/lang/String;
  #119 = Utf8               rawNegatedFailureMessage
  #120 = Utf8               rawCommaAnd
  #121 = NameAndType        #120:#26      // rawCommaAnd:()Ljava/lang/String;
  #122 = Methodref          #111.#121     // org/scalactic/Resources$.rawCommaAnd:()Ljava/lang/String;
  #123 = Utf8               rawMidSentenceFailureMessage
  #124 = Utf8               rawMidSentenceNegatedFailureMessage
  #125 = Utf8               failureMessageArgs
  #126 = Utf8               ()Lscala/collection/immutable/Vector;
  #127 = Utf8               ()Lscala/collection/immutable/Vector<Lorg/scalactic/UnquotedString;>;
  #128 = Utf8               scala/package$
  #129 = Class              #128          // scala/package$
  #130 = Utf8               Lscala/package$;
  #131 = NameAndType        #112:#130     // MODULE$:Lscala/package$;
  #132 = Fieldref           #129.#131     // scala/package$.MODULE$:Lscala/package$;
  #133 = Utf8               Vector
  #134 = Utf8               ()Lscala/collection/immutable/Vector$;
  #135 = NameAndType        #133:#134     // Vector:()Lscala/collection/immutable/Vector$;
  #136 = Methodref          #129.#135     // scala/package$.Vector:()Lscala/collection/immutable/Vector$;
  #137 = Utf8               scala/runtime/ScalaRunTime$
  #138 = Class              #137          // scala/runtime/ScalaRunTime$
  #139 = Utf8               Lscala/runtime/ScalaRunTime$;
  #140 = NameAndType        #112:#139     // MODULE$:Lscala/runtime/ScalaRunTime$;
  #141 = Fieldref           #138.#140     // scala/runtime/ScalaRunTime$.MODULE$:Lscala/runtime/ScalaRunTime$;
  #142 = Utf8               org/scalactic/UnquotedString
  #143 = Class              #142          // org/scalactic/UnquotedString
  #144 = Utf8               org/scalactic/UnquotedString$
  #145 = Class              #144          // org/scalactic/UnquotedString$
  #146 = Utf8               Lorg/scalactic/UnquotedString$;
  #147 = NameAndType        #112:#146     // MODULE$:Lorg/scalactic/UnquotedString$;
  #148 = Fieldref           #145.#147     // org/scalactic/UnquotedString$.MODULE$:Lorg/scalactic/UnquotedString$;
  #149 = NameAndType        #33:#26       // negatedFailureMessage:()Ljava/lang/String;
  #150 = InterfaceMethodref #6.#149       // org/scalactic/Bool.negatedFailureMessage:()Ljava/lang/String;
  #151 = Utf8               (Ljava/lang/String;)Lorg/scalactic/UnquotedString;
  #152 = NameAndType        #101:#151     // apply:(Ljava/lang/String;)Lorg/scalactic/UnquotedString;
  #153 = Methodref          #145.#152     // org/scalactic/UnquotedString$.apply:(Ljava/lang/String;)Lorg/scalactic/UnquotedString;
  #154 = NameAndType        #37:#26       // midSentenceFailureMessage:()Ljava/lang/String;
  #155 = InterfaceMethodref #6.#154       // org/scalactic/Bool.midSentenceFailureMessage:()Ljava/lang/String;
  #156 = Utf8               [Ljava/lang/Object;
  #157 = Class              #156          // "[Ljava/lang/Object;"
  #158 = Utf8               wrapRefArray
  #159 = Utf8               ([Ljava/lang/Object;)Lscala/collection/immutable/ArraySeq;
  #160 = NameAndType        #158:#159     // wrapRefArray:([Ljava/lang/Object;)Lscala/collection/immutable/ArraySeq;
  #161 = Methodref          #138.#160     // scala/runtime/ScalaRunTime$.wrapRefArray:([Ljava/lang/Object;)Lscala/collection/immutable/ArraySeq;
  #162 = Utf8               scala/collection/immutable/Vector$
  #163 = Class              #162          // scala/collection/immutable/Vector$
  #164 = Utf8               (Lscala/collection/immutable/Seq;)Ljava/lang/Object;
  #165 = NameAndType        #101:#164     // apply:(Lscala/collection/immutable/Seq;)Ljava/lang/Object;
  #166 = Methodref          #163.#165     // scala/collection/immutable/Vector$.apply:(Lscala/collection/immutable/Seq;)Ljava/lang/Object;
  #167 = Utf8               scala/collection/immutable/Vector
  #168 = Class              #167          // scala/collection/immutable/Vector
  #169 = Utf8               negatedFailureMessageArgs
  #170 = NameAndType        #41:#26       // midSentenceNegatedFailureMessage:()Ljava/lang/String;
  #171 = InterfaceMethodref #6.#170       // org/scalactic/Bool.midSentenceNegatedFailureMessage:()Ljava/lang/String;
  #172 = Utf8               midSentenceFailureMessageArgs
  #173 = Utf8               midSentenceNegatedFailureMessageArgs
  #174 = NameAndType        #173:#126     // midSentenceNegatedFailureMessageArgs:()Lscala/collection/immutable/Vector;
  #175 = Methodref          #2.#174       // org/scalactic/AndBool.midSentenceNegatedFailureMessageArgs:()Lscala/collection/immutable/Vector;
  #176 = NameAndType        #172:#126     // midSentenceFailureMessageArgs:()Lscala/collection/immutable/Vector;
  #177 = Methodref          #2.#176       // org/scalactic/AndBool.midSentenceFailureMessageArgs:()Lscala/collection/immutable/Vector;
  #178 = NameAndType        #169:#126     // negatedFailureMessageArgs:()Lscala/collection/immutable/Vector;
  #179 = Methodref          #2.#178       // org/scalactic/AndBool.negatedFailureMessageArgs:()Lscala/collection/immutable/Vector;
  #180 = NameAndType        #125:#126     // failureMessageArgs:()Lscala/collection/immutable/Vector;
  #181 = Methodref          #2.#180       // org/scalactic/AndBool.failureMessageArgs:()Lscala/collection/immutable/Vector;
  #182 = Utf8               <init>
  #183 = Utf8               (Lorg/scalactic/Bool;Lscala/Function0;Lorg/scalactic/Prettifier;)V
  #184 = Utf8               (Lorg/scalactic/Bool;Lscala/Function0<Lorg/scalactic/Bool;>;Lorg/scalactic/Prettifier;)V
  #185 = Utf8               ()V
  #186 = NameAndType        #182:#185     // "<init>":()V
  #187 = Methodref          #4.#186       // java/lang/Object."<init>":()V
  #188 = Utf8               $init$
  #189 = Utf8               (Lorg/scalactic/Bool;)V
  #190 = NameAndType        #188:#189     // $init$:(Lorg/scalactic/Bool;)V
  #191 = InterfaceMethodref #6.#190       // org/scalactic/Bool.$init$:(Lorg/scalactic/Bool;)V
  #192 = Utf8               Signature
  #193 = Utf8               Code
  #194 = Utf8               LineNumberTable
  #195 = Utf8               LocalVariableTable
  #196 = Utf8               MethodParameters
  #197 = Utf8               StackMapTable
  #198 = Utf8               SourceFile
  #199 = Utf8               RuntimeVisibleAnnotations
  #200 = Utf8               ScalaInlineInfo
  #201 = Utf8               ScalaSig
{
  private boolean value;
    descriptor: Z
    flags: (0x0002) ACC_PRIVATE

  private final org.scalactic.Bool bool1;
    descriptor: Lorg/scalactic/Bool;
    flags: (0x0012) ACC_PRIVATE, ACC_FINAL

  private final scala.Function0<org.scalactic.Bool> bool2;
    descriptor: Lscala/Function0;
    flags: (0x0012) ACC_PRIVATE, ACC_FINAL
    Signature: #17                          // Lscala/Function0<Lorg/scalactic/Bool;>;

  private final org.scalactic.Prettifier prettifier;
    descriptor: Lorg/scalactic/Prettifier;
    flags: (0x0012) ACC_PRIVATE, ACC_FINAL

  private scala.collection.immutable.IndexedSeq<java.lang.String> analysis;
    descriptor: Lscala/collection/immutable/IndexedSeq;
    flags: (0x0002) ACC_PRIVATE
    Signature: #22                          // Lscala/collection/immutable/IndexedSeq<Ljava/lang/String;>;

  private volatile byte bitmap$0;
    descriptor: B
    flags: (0x0042) ACC_PRIVATE, ACC_VOLATILE

  public java.lang.String failureMessage();
    descriptor: ()Ljava/lang/String;
    flags: (0x0001) ACC_PUBLIC
    Code:
      stack=1, locals=1, args_size=1
         0: aload_0
         1: invokestatic  #30                 // InterfaceMethod org/scalactic/Bool.failureMessage$:(Lorg/scalactic/Bool;)Ljava/lang/String;
         4: areturn
      LineNumberTable:
        line 372: 0
      LocalVariableTable:
        Start  Length  Slot  Name   Signature
            0       5     0  this   Lorg/scalactic/AndBool;

  public java.lang.String negatedFailureMessage();
    descriptor: ()Ljava/lang/String;
    flags: (0x0001) ACC_PUBLIC
    Code:
      stack=1, locals=1, args_size=1
         0: aload_0
         1: invokestatic  #36                 // InterfaceMethod org/scalactic/Bool.negatedFailureMessage$:(Lorg/scalactic/Bool;)Ljava/lang/String;
         4: areturn
      LineNumberTable:
        line 372: 0
      LocalVariableTable:
        Start  Length  Slot  Name   Signature
            0       5     0  this   Lorg/scalactic/AndBool;

  public java.lang.String midSentenceFailureMessage();
    descriptor: ()Ljava/lang/String;
    flags: (0x0001) ACC_PUBLIC
    Code:
      stack=1, locals=1, args_size=1
         0: aload_0
         1: invokestatic  #40                 // InterfaceMethod org/scalactic/Bool.midSentenceFailureMessage$:(Lorg/scalactic/Bool;)Ljava/lang/String;
         4: areturn
      LineNumberTable:
        line 372: 0
      LocalVariableTable:
        Start  Length  Slot  Name   Signature
            0       5     0  this   Lorg/scalactic/AndBool;

  public java.lang.String midSentenceNegatedFailureMessage();
    descriptor: ()Ljava/lang/String;
    flags: (0x0001) ACC_PUBLIC
    Code:
      stack=1, locals=1, args_size=1
         0: aload_0
         1: invokestatic  #44                 // InterfaceMethod org/scalactic/Bool.midSentenceNegatedFailureMessage$:(Lorg/scalactic/Bool;)Ljava/lang/String;
         4: areturn
      LineNumberTable:
        line 372: 0
      LocalVariableTable:
        Start  Length  Slot  Name   Signature
            0       5     0  this   Lorg/scalactic/AndBool;

  public org.scalactic.Bool $amp$amp(scala.Function0<org.scalactic.Bool>);
    descriptor: (Lscala/Function0;)Lorg/scalactic/Bool;
    flags: (0x0001) ACC_PUBLIC
    Code:
      stack=2, locals=2, args_size=2
         0: aload_0
         1: aload_1
         2: invokestatic  #52                 // InterfaceMethod org/scalactic/Bool.$amp$amp$:(Lorg/scalactic/Bool;Lscala/Function0;)Lorg/scalactic/Bool;
         5: areturn
      LineNumberTable:
        line 372: 0
      LocalVariableTable:
        Start  Length  Slot  Name   Signature
            0       6     0  this   Lorg/scalactic/AndBool;
            0       6     1  bool   Lscala/Function0;
    Signature: #47                          // (Lscala/Function0<Lorg/scalactic/Bool;>;)Lorg/scalactic/Bool;
    MethodParameters:
      Name                           Flags
      bool                           final

  public org.scalactic.Bool $amp(scala.Function0<org.scalactic.Bool>);
    descriptor: (Lscala/Function0;)Lorg/scalactic/Bool;
    flags: (0x0001) ACC_PUBLIC
    Code:
      stack=2, locals=2, args_size=2
         0: aload_0
         1: aload_1
         2: invokestatic  #56                 // InterfaceMethod org/scalactic/Bool.$amp$:(Lorg/scalactic/Bool;Lscala/Function0;)Lorg/scalactic/Bool;
         5: areturn
      LineNumberTable:
        line 372: 0
      LocalVariableTable:
        Start  Length  Slot  Name   Signature
            0       6     0  this   Lorg/scalactic/AndBool;
            0       6     1  bool   Lscala/Function0;
    Signature: #47                          // (Lscala/Function0<Lorg/scalactic/Bool;>;)Lorg/scalactic/Bool;
    MethodParameters:
      Name                           Flags
      bool                           final

  public org.scalactic.Bool $bar$bar(scala.Function0<org.scalactic.Bool>);
    descriptor: (Lscala/Function0;)Lorg/scalactic/Bool;
    flags: (0x0001) ACC_PUBLIC
    Code:
      stack=2, locals=2, args_size=2
         0: aload_0
         1: aload_1
         2: invokestatic  #60                 // InterfaceMethod org/scalactic/Bool.$bar$bar$:(Lorg/scalactic/Bool;Lscala/Function0;)Lorg/scalactic/Bool;
         5: areturn
      LineNumberTable:
        line 372: 0
      LocalVariableTable:
        Start  Length  Slot  Name   Signature
            0       6     0  this   Lorg/scalactic/AndBool;
            0       6     1  bool   Lscala/Function0;
    Signature: #47                          // (Lscala/Function0<Lorg/scalactic/Bool;>;)Lorg/scalactic/Bool;
    MethodParameters:
      Name                           Flags
      bool                           final

  public org.scalactic.Bool $bar(scala.Function0<org.scalactic.Bool>);
    descriptor: (Lscala/Function0;)Lorg/scalactic/Bool;
    flags: (0x0001) ACC_PUBLIC
    Code:
      stack=2, locals=2, args_size=2
         0: aload_0
         1: aload_1
         2: invokestatic  #64                 // InterfaceMethod org/scalactic/Bool.$bar$:(Lorg/scalactic/Bool;Lscala/Function0;)Lorg/scalactic/Bool;
         5: areturn
      LineNumberTable:
        line 372: 0
      LocalVariableTable:
        Start  Length  Slot  Name   Signature
            0       6     0  this   Lorg/scalactic/AndBool;
            0       6     1  bool   Lscala/Function0;
    Signature: #47                          // (Lscala/Function0<Lorg/scalactic/Bool;>;)Lorg/scalactic/Bool;
    MethodParameters:
      Name                           Flags
      bool                           final

  public org.scalactic.Bool unary_$bang();
    descriptor: ()Lorg/scalactic/Bool;
    flags: (0x0001) ACC_PUBLIC
    Code:
      stack=1, locals=1, args_size=1
         0: aload_0
         1: invokestatic  #70                 // InterfaceMethod org/scalactic/Bool.unary_$bang$:(Lorg/scalactic/Bool;)Lorg/scalactic/Bool;
         4: areturn
      LineNumberTable:
        line 372: 0
      LocalVariableTable:
        Start  Length  Slot  Name   Signature
            0       5     0  this   Lorg/scalactic/AndBool;

  private scala.collection.immutable.IndexedSeq<java.lang.String> analysis$lzycompute();
    descriptor: ()Lscala/collection/immutable/IndexedSeq;
    flags: (0x0002) ACC_PRIVATE
    Code:
      stack=3, locals=2, args_size=1
         0: aload_0
         1: dup
         2: astore_1
         3: monitorenter
         4: aload_0
         5: getfield      #75                 // Field bitmap$0:B
         8: iconst_2
         9: iand
        10: i2b
        11: iconst_0
        12: if_icmpne     34
        15: aload_0
        16: aload_0
        17: invokestatic  #79                 // InterfaceMethod org/scalactic/Bool.analysis$:(Lorg/scalactic/Bool;)Lscala/collection/immutable/IndexedSeq;
        20: putfield      #81                 // Field analysis:Lscala/collection/immutable/IndexedSeq;
        23: aload_0
        24: aload_0
        25: getfield      #75                 // Field bitmap$0:B
        28: iconst_2
        29: ior
        30: i2b
        31: putfield      #75                 // Field bitmap$0:B
        34: aload_1
        35: monitorexit
        36: goto          42
        39: aload_1
        40: monitorexit
        41: athrow
        42: aload_0
        43: getfield      #81                 // Field analysis:Lscala/collection/immutable/IndexedSeq;
        46: areturn
      Exception table:
         from    to  target type
             4    34    39   any
      StackMapTable: number_of_entries = 3
        frame_type = 252 /* append */
          offset_delta = 34
          locals = [ class org/scalactic/AndBool ]
        frame_type = 68 /* same_locals_1_stack_item */
          stack = [ class java/lang/Throwable ]
        frame_type = 2 /* same */
      LineNumberTable:
        line 372: 0
      LocalVariableTable:
        Start  Length  Slot  Name   Signature
            0      47     0  this   Lorg/scalactic/AndBool;
    Signature: #73                          // ()Lscala/collection/immutable/IndexedSeq<Ljava/lang/String;>;

  public scala.collection.immutable.IndexedSeq<java.lang.String> analysis();
    descriptor: ()Lscala/collection/immutable/IndexedSeq;
    flags: (0x0001) ACC_PUBLIC
    Code:
      stack=2, locals=1, args_size=1
         0: aload_0
         1: getfield      #75                 // Field bitmap$0:B
         4: iconst_2
         5: iand
         6: i2b
         7: iconst_0
         8: if_icmpne     18
        11: aload_0
        12: invokespecial #85                 // Method analysis$lzycompute:()Lscala/collection/immutable/IndexedSeq;
        15: goto          22
        18: aload_0
        19: getfield      #81                 // Field analysis:Lscala/collection/immutable/IndexedSeq;
        22: areturn
      StackMapTable: number_of_entries = 2
        frame_type = 18 /* same */
        frame_type = 67 /* same_locals_1_stack_item */
          stack = [ class scala/collection/immutable/IndexedSeq ]
      LineNumberTable:
        line 372: 0
      LocalVariableTable:
        Start  Length  Slot  Name   Signature
            0      23     0  this   Lorg/scalactic/AndBool;
    Signature: #73                          // ()Lscala/collection/immutable/IndexedSeq<Ljava/lang/String;>;

  public org.scalactic.Prettifier prettifier();
    descriptor: ()Lorg/scalactic/Prettifier;
    flags: (0x0001) ACC_PUBLIC
    Code:
      stack=1, locals=1, args_size=1
         0: aload_0
         1: getfield      #90                 // Field prettifier:Lorg/scalactic/Prettifier;
         4: areturn
      LineNumberTable:
        line 372: 0
      LocalVariableTable:
        Start  Length  Slot  Name   Signature
            0       5     0  this   Lorg/scalactic/AndBool;

  private boolean value$lzycompute();
    descriptor: ()Z
    flags: (0x0002) ACC_PRIVATE
    Code:
      stack=3, locals=2, args_size=1
         0: aload_0
         1: dup
         2: astore_1
         3: monitorenter
         4: aload_0
         5: getfield      #75                 // Field bitmap$0:B
         8: iconst_1
         9: iand
        10: i2b
        11: iconst_0
        12: if_icmpne     67
        15: aload_0
        16: aload_0
        17: getfield      #94                 // Field bool1:Lorg/scalactic/Bool;
        20: invokeinterface #96,  1           // InterfaceMethod org/scalactic/Bool.value:()Z
        25: ifeq          52
        28: aload_0
        29: getfield      #98                 // Field bool2:Lscala/Function0;
        32: invokeinterface #104,  1          // InterfaceMethod scala/Function0.apply:()Ljava/lang/Object;
        37: checkcast     #6                  // class org/scalactic/Bool
        40: invokeinterface #96,  1           // InterfaceMethod org/scalactic/Bool.value:()Z
        45: ifeq          52
        48: iconst_1
        49: goto          53
        52: iconst_0
        53: putfield      #106                // Field value:Z
        56: aload_0
        57: aload_0
        58: getfield      #75                 // Field bitmap$0:B
        61: iconst_1
        62: ior
        63: i2b
        64: putfield      #75                 // Field bitmap$0:B
        67: aload_1
        68: monitorexit
        69: goto          75
        72: aload_1
        73: monitorexit
        74: athrow
        75: aload_0
        76: getfield      #106                // Field value:Z
        79: ireturn
      Exception table:
         from    to  target type
             4    67    72   any
      StackMapTable: number_of_entries = 5
        frame_type = 255 /* full_frame */
          offset_delta = 52
          locals = [ class org/scalactic/AndBool, class org/scalactic/AndBool ]
          stack = [ class org/scalactic/AndBool ]
        frame_type = 255 /* full_frame */
          offset_delta = 0
          locals = [ class org/scalactic/AndBool, class org/scalactic/AndBool ]
          stack = [ class org/scalactic/AndBool, int ]
        frame_type = 13 /* same */
        frame_type = 68 /* same_locals_1_stack_item */
          stack = [ class java/lang/Throwable ]
        frame_type = 2 /* same */
      LineNumberTable:
        line 377: 0
      LocalVariableTable:
        Start  Length  Slot  Name   Signature
            0      80     0  this   Lorg/scalactic/AndBool;

  public boolean value();
    descriptor: ()Z
    flags: (0x0001) ACC_PUBLIC
    Code:
      stack=2, locals=1, args_size=1
         0: aload_0
         1: getfield      #75                 // Field bitmap$0:B
         4: iconst_1
         5: iand
         6: i2b
         7: iconst_0
         8: if_icmpne     18
        11: aload_0
        12: invokespecial #108                // Method value$lzycompute:()Z
        15: goto          22
        18: aload_0
        19: getfield      #106                // Field value:Z
        22: ireturn
      StackMapTable: number_of_entries = 2
        frame_type = 18 /* same */
        frame_type = 67 /* same_locals_1_stack_item */
          stack = [ int ]
      LineNumberTable:
        line 377: 0
      LocalVariableTable:
        Start  Length  Slot  Name   Signature
            0      23     0  this   Lorg/scalactic/AndBool;

  public java.lang.String rawFailureMessage();
    descriptor: ()Ljava/lang/String;
    flags: (0x0001) ACC_PUBLIC
    Code:
      stack=1, locals=1, args_size=1
         0: getstatic     #115                // Field org/scalactic/Resources$.MODULE$:Lorg/scalactic/Resources$;
         3: invokevirtual #118                // Method org/scalactic/Resources$.rawCommaBut:()Ljava/lang/String;
         6: areturn
      LineNumberTable:
        line 384: 0
      LocalVariableTable:
        Start  Length  Slot  Name   Signature
            0       7     0  this   Lorg/scalactic/AndBool;

  public java.lang.String rawNegatedFailureMessage();
    descriptor: ()Ljava/lang/String;
    flags: (0x0001) ACC_PUBLIC
    Code:
      stack=1, locals=1, args_size=1
         0: getstatic     #115                // Field org/scalactic/Resources$.MODULE$:Lorg/scalactic/Resources$;
         3: invokevirtual #122                // Method org/scalactic/Resources$.rawCommaAnd:()Ljava/lang/String;
         6: areturn
      LineNumberTable:
        line 391: 0
      LocalVariableTable:
        Start  Length  Slot  Name   Signature
            0       7     0  this   Lorg/scalactic/AndBool;

  public java.lang.String rawMidSentenceFailureMessage();
    descriptor: ()Ljava/lang/String;
    flags: (0x0001) ACC_PUBLIC
    Code:
      stack=1, locals=1, args_size=1
         0: getstatic     #115                // Field org/scalactic/Resources$.MODULE$:Lorg/scalactic/Resources$;
         3: invokevirtual #118                // Method org/scalactic/Resources$.rawCommaBut:()Ljava/lang/String;
         6: areturn
      LineNumberTable:
        line 398: 0
      LocalVariableTable:
        Start  Length  Slot  Name   Signature
            0       7     0  this   Lorg/scalactic/AndBool;

  public java.lang.String rawMidSentenceNegatedFailureMessage();
    descriptor: ()Ljava/lang/String;
    flags: (0x0001) ACC_PUBLIC
    Code:
      stack=1, locals=1, args_size=1
         0: getstatic     #115                // Field org/scalactic/Resources$.MODULE$:Lorg/scalactic/Resources$;
         3: invokevirtual #122                // Method org/scalactic/Resources$.rawCommaAnd:()Ljava/lang/String;
         6: areturn
      LineNumberTable:
        line 405: 0
      LocalVariableTable:
        Start  Length  Slot  Name   Signature
            0       7     0  this   Lorg/scalactic/AndBool;

  public scala.collection.immutable.Vector<org.scalactic.UnquotedString> failureMessageArgs();
    descriptor: ()Lscala/collection/immutable/Vector;
    flags: (0x0001) ACC_PUBLIC
    Code:
      stack=7, locals=1, args_size=1
         0: getstatic     #132                // Field scala/package$.MODULE$:Lscala/package$;
         3: invokevirtual #136                // Method scala/package$.Vector:()Lscala/collection/immutable/Vector$;
         6: getstatic     #141                // Field scala/runtime/ScalaRunTime$.MODULE$:Lscala/runtime/ScalaRunTime$;
         9: iconst_2
        10: anewarray     #143                // class org/scalactic/UnquotedString
        13: dup
        14: iconst_0
        15: getstatic     #148                // Field org/scalactic/UnquotedString$.MODULE$:Lorg/scalactic/UnquotedString$;
        18: aload_0
        19: getfield      #94                 // Field bool1:Lorg/scalactic/Bool;
        22: invokeinterface #150,  1          // InterfaceMethod org/scalactic/Bool.negatedFailureMessage:()Ljava/lang/String;
        27: invokevirtual #153                // Method org/scalactic/UnquotedString$.apply:(Ljava/lang/String;)Lorg/scalactic/UnquotedString;
        30: aastore
        31: dup
        32: iconst_1
        33: getstatic     #148                // Field org/scalactic/UnquotedString$.MODULE$:Lorg/scalactic/UnquotedString$;
        36: aload_0
        37: getfield      #98                 // Field bool2:Lscala/Function0;
        40: invokeinterface #104,  1          // InterfaceMethod scala/Function0.apply:()Ljava/lang/Object;
        45: checkcast     #6                  // class org/scalactic/Bool
        48: invokeinterface #155,  1          // InterfaceMethod org/scalactic/Bool.midSentenceFailureMessage:()Ljava/lang/String;
        53: invokevirtual #153                // Method org/scalactic/UnquotedString$.apply:(Ljava/lang/String;)Lorg/scalactic/UnquotedString;
        56: aastore
        57: checkcast     #157                // class "[Ljava/lang/Object;"
        60: invokevirtual #161                // Method scala/runtime/ScalaRunTime$.wrapRefArray:([Ljava/lang/Object;)Lscala/collection/immutable/ArraySeq;
        63: invokevirtual #166                // Method scala/collection/immutable/Vector$.apply:(Lscala/collection/immutable/Seq;)Ljava/lang/Object;
        66: checkcast     #168                // class scala/collection/immutable/Vector
        69: areturn
      LineNumberTable:
        line 412: 0
      LocalVariableTable:
        Start  Length  Slot  Name   Signature
            0      70     0  this   Lorg/scalactic/AndBool;
    Signature: #127                         // ()Lscala/collection/immutable/Vector<Lorg/scalactic/UnquotedString;>;

  public scala.collection.immutable.Vector<org.scalactic.UnquotedString> negatedFailureMessageArgs();
    descriptor: ()Lscala/collection/immutable/Vector;
    flags: (0x0001) ACC_PUBLIC
    Code:
      stack=7, locals=1, args_size=1
         0: getstatic     #132                // Field scala/package$.MODULE$:Lscala/package$;
         3: invokevirtual #136                // Method scala/package$.Vector:()Lscala/collection/immutable/Vector$;
         6: getstatic     #141                // Field scala/runtime/ScalaRunTime$.MODULE$:Lscala/runtime/ScalaRunTime$;
         9: iconst_2
        10: anewarray     #143                // class org/scalactic/UnquotedString
        13: dup
        14: iconst_0
        15: getstatic     #148                // Field org/scalactic/UnquotedString$.MODULE$:Lorg/scalactic/UnquotedString$;
        18: aload_0
        19: getfield      #94                 // Field bool1:Lorg/scalactic/Bool;
        22: invokeinterface #150,  1          // InterfaceMethod org/scalactic/Bool.negatedFailureMessage:()Ljava/lang/String;
        27: invokevirtual #153                // Method org/scalactic/UnquotedString$.apply:(Ljava/lang/String;)Lorg/scalactic/UnquotedString;
        30: aastore
        31: dup
        32: iconst_1
        33: getstatic     #148                // Field org/scalactic/UnquotedString$.MODULE$:Lorg/scalactic/UnquotedString$;
        36: aload_0
        37: getfield      #98                 // Field bool2:Lscala/Function0;
        40: invokeinterface #104,  1          // InterfaceMethod scala/Function0.apply:()Ljava/lang/Object;
        45: checkcast     #6                  // class org/scalactic/Bool
        48: invokeinterface #171,  1          // InterfaceMethod org/scalactic/Bool.midSentenceNegatedFailureMessage:()Ljava/lang/String;
        53: invokevirtual #153                // Method org/scalactic/UnquotedString$.apply:(Ljava/lang/String;)Lorg/scalactic/UnquotedString;
        56: aastore
        57: checkcast     #157                // class "[Ljava/lang/Object;"
        60: invokevirtual #161                // Method scala/runtime/ScalaRunTime$.wrapRefArray:([Ljava/lang/Object;)Lscala/collection/immutable/ArraySeq;
        63: invokevirtual #166                // Method scala/collection/immutable/Vector$.apply:(Lscala/collection/immutable/Seq;)Ljava/lang/Object;
        66: checkcast     #168                // class scala/collection/immutable/Vector
        69: areturn
      LineNumberTable:
        line 419: 0
      LocalVariableTable:
        Start  Length  Slot  Name   Signature
            0      70     0  this   Lorg/scalactic/AndBool;
    Signature: #127                         // ()Lscala/collection/immutable/Vector<Lorg/scalactic/UnquotedString;>;

  public scala.collection.immutable.Vector<org.scalactic.UnquotedString> midSentenceFailureMessageArgs();
    descriptor: ()Lscala/collection/immutable/Vector;
    flags: (0x0001) ACC_PUBLIC
    Code:
      stack=7, locals=1, args_size=1
         0: getstatic     #132                // Field scala/package$.MODULE$:Lscala/package$;
         3: invokevirtual #136                // Method scala/package$.Vector:()Lscala/collection/immutable/Vector$;
         6: getstatic     #141                // Field scala/runtime/ScalaRunTime$.MODULE$:Lscala/runtime/ScalaRunTime$;
         9: iconst_2
        10: anewarray     #143                // class org/scalactic/UnquotedString
        13: dup
        14: iconst_0
        15: getstatic     #148                // Field org/scalactic/UnquotedString$.MODULE$:Lorg/scalactic/UnquotedString$;
        18: aload_0
        19: getfield      #94                 // Field bool1:Lorg/scalactic/Bool;
        22: invokeinterface #171,  1          // InterfaceMethod org/scalactic/Bool.midSentenceNegatedFailureMessage:()Ljava/lang/String;
        27: invokevirtual #153                // Method org/scalactic/UnquotedString$.apply:(Ljava/lang/String;)Lorg/scalactic/UnquotedString;
        30: aastore
        31: dup
        32: iconst_1
        33: getstatic     #148                // Field org/scalactic/UnquotedString$.MODULE$:Lorg/scalactic/UnquotedString$;
        36: aload_0
        37: getfield      #98                 // Field bool2:Lscala/Function0;
        40: invokeinterface #104,  1          // InterfaceMethod scala/Function0.apply:()Ljava/lang/Object;
        45: checkcast     #6                  // class org/scalactic/Bool
        48: invokeinterface #155,  1          // InterfaceMethod org/scalactic/Bool.midSentenceFailureMessage:()Ljava/lang/String;
        53: invokevirtual #153                // Method org/scalactic/UnquotedString$.apply:(Ljava/lang/String;)Lorg/scalactic/UnquotedString;
        56: aastore
        57: checkcast     #157                // class "[Ljava/lang/Object;"
        60: invokevirtual #161                // Method scala/runtime/ScalaRunTime$.wrapRefArray:([Ljava/lang/Object;)Lscala/collection/immutable/ArraySeq;
        63: invokevirtual #166                // Method scala/collection/immutable/Vector$.apply:(Lscala/collection/immutable/Seq;)Ljava/lang/Object;
        66: checkcast     #168                // class scala/collection/immutable/Vector
        69: areturn
      LineNumberTable:
        line 426: 0
      LocalVariableTable:
        Start  Length  Slot  Name   Signature
            0      70     0  this   Lorg/scalactic/AndBool;
    Signature: #127                         // ()Lscala/collection/immutable/Vector<Lorg/scalactic/UnquotedString;>;

  public scala.collection.immutable.Vector<org.scalactic.UnquotedString> midSentenceNegatedFailureMessageArgs();
    descriptor: ()Lscala/collection/immutable/Vector;
    flags: (0x0001) ACC_PUBLIC
    Code:
      stack=7, locals=1, args_size=1
         0: getstatic     #132                // Field scala/package$.MODULE$:Lscala/package$;
         3: invokevirtual #136                // Method scala/package$.Vector:()Lscala/collection/immutable/Vector$;
         6: getstatic     #141                // Field scala/runtime/ScalaRunTime$.MODULE$:Lscala/runtime/ScalaRunTime$;
         9: iconst_2
        10: anewarray     #143                // class org/scalactic/UnquotedString
        13: dup
        14: iconst_0
        15: getstatic     #148                // Field org/scalactic/UnquotedString$.MODULE$:Lorg/scalactic/UnquotedString$;
        18: aload_0
        19: getfield      #94                 // Field bool1:Lorg/scalactic/Bool;
        22: invokeinterface #171,  1          // InterfaceMethod org/scalactic/Bool.midSentenceNegatedFailureMessage:()Ljava/lang/String;
        27: invokevirtual #153                // Method org/scalactic/UnquotedString$.apply:(Ljava/lang/String;)Lorg/scalactic/UnquotedString;
        30: aastore
        31: dup
        32: iconst_1
        33: getstatic     #148                // Field org/scalactic/UnquotedString$.MODULE$:Lorg/scalactic/UnquotedString$;
        36: aload_0
        37: getfield      #98                 // Field bool2:Lscala/Function0;
        40: invokeinterface #104,  1          // InterfaceMethod scala/Function0.apply:()Ljava/lang/Object;
        45: checkcast     #6                  // class org/scalactic/Bool
        48: invokeinterface #171,  1          // InterfaceMethod org/scalactic/Bool.midSentenceNegatedFailureMessage:()Ljava/lang/String;
        53: invokevirtual #153                // Method org/scalactic/UnquotedString$.apply:(Ljava/lang/String;)Lorg/scalactic/UnquotedString;
        56: aastore
        57: checkcast     #157                // class "[Ljava/lang/Object;"
        60: invokevirtual #161                // Method scala/runtime/ScalaRunTime$.wrapRefArray:([Ljava/lang/Object;)Lscala/collection/immutable/ArraySeq;
        63: invokevirtual #166                // Method scala/collection/immutable/Vector$.apply:(Lscala/collection/immutable/Seq;)Ljava/lang/Object;
        66: checkcast     #168                // class scala/collection/immutable/Vector
        69: areturn
      LineNumberTable:
        line 433: 0
      LocalVariableTable:
        Start  Length  Slot  Name   Signature
            0      70     0  this   Lorg/scalactic/AndBool;
    Signature: #127                         // ()Lscala/collection/immutable/Vector<Lorg/scalactic/UnquotedString;>;

  public scala.collection.immutable.IndexedSeq midSentenceNegatedFailureMessageArgs();
    descriptor: ()Lscala/collection/immutable/IndexedSeq;
    flags: (0x1041) ACC_PUBLIC, ACC_BRIDGE, ACC_SYNTHETIC
    Code:
      stack=1, locals=1, args_size=1
         0: aload_0
         1: invokevirtual #175                // Method midSentenceNegatedFailureMessageArgs:()Lscala/collection/immutable/Vector;
         4: areturn
      LineNumberTable:
        line 372: 0
      LocalVariableTable:
        Start  Length  Slot  Name   Signature
            0       5     0  this   Lorg/scalactic/AndBool;

  public scala.collection.immutable.IndexedSeq midSentenceFailureMessageArgs();
    descriptor: ()Lscala/collection/immutable/IndexedSeq;
    flags: (0x1041) ACC_PUBLIC, ACC_BRIDGE, ACC_SYNTHETIC
    Code:
      stack=1, locals=1, args_size=1
         0: aload_0
         1: invokevirtual #177                // Method midSentenceFailureMessageArgs:()Lscala/collection/immutable/Vector;
         4: areturn
      LineNumberTable:
        line 372: 0
      LocalVariableTable:
        Start  Length  Slot  Name   Signature
            0       5     0  this   Lorg/scalactic/AndBool;

  public scala.collection.immutable.IndexedSeq negatedFailureMessageArgs();
    descriptor: ()Lscala/collection/immutable/IndexedSeq;
    flags: (0x1041) ACC_PUBLIC, ACC_BRIDGE, ACC_SYNTHETIC
    Code:
      stack=1, locals=1, args_size=1
         0: aload_0
         1: invokevirtual #179                // Method negatedFailureMessageArgs:()Lscala/collection/immutable/Vector;
         4: areturn
      LineNumberTable:
        line 372: 0
      LocalVariableTable:
        Start  Length  Slot  Name   Signature
            0       5     0  this   Lorg/scalactic/AndBool;

  public scala.collection.immutable.IndexedSeq failureMessageArgs();
    descriptor: ()Lscala/collection/immutable/IndexedSeq;
    flags: (0x1041) ACC_PUBLIC, ACC_BRIDGE, ACC_SYNTHETIC
    Code:
      stack=1, locals=1, args_size=1
         0: aload_0
         1: invokevirtual #181                // Method failureMessageArgs:()Lscala/collection/immutable/Vector;
         4: areturn
      LineNumberTable:
        line 372: 0
      LocalVariableTable:
        Start  Length  Slot  Name   Signature
            0       5     0  this   Lorg/scalactic/AndBool;

  public org.scalactic.AndBool(org.scalactic.Bool, scala.Function0<org.scalactic.Bool>, org.scalactic.Prettifier);
    descriptor: (Lorg/scalactic/Bool;Lscala/Function0;Lorg/scalactic/Prettifier;)V
    flags: (0x0001) ACC_PUBLIC
    Code:
      stack=2, locals=4, args_size=4
         0: aload_0
         1: aload_1
         2: putfield      #94                 // Field bool1:Lorg/scalactic/Bool;
         5: aload_0
         6: aload_2
         7: putfield      #98                 // Field bool2:Lscala/Function0;
        10: aload_0
        11: aload_3
        12: putfield      #90                 // Field prettifier:Lorg/scalactic/Prettifier;
        15: aload_0
        16: invokespecial #187                // Method java/lang/Object."<init>":()V
        19: aload_0
        20: invokestatic  #191                // InterfaceMethod org/scalactic/Bool.$init$:(Lorg/scalactic/Bool;)V
        23: return
      LineNumberTable:
        line 372: 0
      LocalVariableTable:
        Start  Length  Slot  Name   Signature
            0      24     0  this   Lorg/scalactic/AndBool;
            0      24     1 bool1   Lorg/scalactic/Bool;
            0      24     2 bool2   Lscala/Function0;
            0      24     3 prettifier   Lorg/scalactic/Prettifier;
    Signature: #184                         // (Lorg/scalactic/Bool;Lscala/Function0<Lorg/scalactic/Bool;>;Lorg/scalactic/Prettifier;)V
    MethodParameters:
      Name                           Flags
      bool1                          final
      bool2                          final
      prettifier                     final
}
SourceFile: "Bool.scala"
RuntimeVisibleAnnotations:
  0: #8(#9=s#10)
    scala.reflect.ScalaSignature(
      bytes="\u0006\u0005Y3Qa\u0004\t\u0001!QA\u0001b\b\u0001\u0003\u0002\u0003\u0006Ia\u0007\u0005\tC\u0001\u0011\t\u0011*A\u0005E!AQ\u0005\u0001BC\u0002\u0013\u0005a\u0005\u0003\u0005+\u0001\t\u0005\t\u0015!\u0003(\u0011\u0015Y\u0003\u0001\"\u0001-\u0011!\t\u0004\u0001#b\u0001\n\u0003\u0011\u0004\"\u0002\u001c\u0001\t\u00039\u0004\"B\"\u0001\t\u00039\u0004\"\u0002#\u0001\t\u00039\u0004\"B#\u0001\t\u00039\u0004\"\u0002$\u0001\t\u00039\u0005\"B*\u0001\t\u00039\u0005\"\u0002+\u0001\t\u00039\u0005\"B+\u0001\t\u00039%aB!oI\n{w\u000e\u001c\u0006\u0003#I\t\u0011b]2bY\u0006\u001cG/[2\u000b\u0003M\t1a\u001c:h\'\r\u0001Qc\u0007\t\u0003-ei\u0011a\u0006\u0006\u00021\u0005)1oY1mC&\u0011!d\u0006\u0002\u0007\u0003:L(+\u001a4\u0011\u0005qiR\"\u0001\t\n\u0005y\u0001\"\u0001\u0002\"p_2\fQAY8pYF\u001a\u0001!A\u0003c_>d\'\u0007E\u0002\u0017GmI!\u0001J\f\u0003\u0011q\u0012\u0017P\\1nKz\n!\u0002\u001d:fiRLg-[3s+\u00059\u0003C\u0001\u000f)\u0013\tI\u0003C\u0001\u0006Qe\u0016$H/\u001b4jKJ\f1\u0002\u001d:fiRLg-[3sA\u00051A(\u001b8jiz\"B!\f\u00180aA\u0011A\u0004\u0001\u0005\u0006?\u0015\u0001\ra\u0007\u0005\u0007C\u0015!\t\u0019\u0001\u0012\t\u000b\u0015*\u0001\u0019A\u0014\u0002\u000bY\fG.^3\u0016\u0003M\u0002\"A\u0006\u001b\n\u0005U:\"a\u0002\"p_2,\u0017M\\\u0001\u0012e\u0006<h)Y5mkJ,W*Z:tC\u001e,W#\u0001\u001d\u0011\u0005e\u0002eB\u0001\u001e?!\tYt#D\u0001=\u0015\ti\u0004%\u0001\u0004=e>|GOP\u0005\u0003\u007f]\ta\u0001\u0015:fI\u00164\u0017BA!C\u0005\u0019\u0019FO]5oO*\u0011qhF\u0001\u0019e\u0006<h*Z4bi\u0016$g)Y5mkJ,W*Z:tC\u001e,\u0017\u0001\b:bo6KGmU3oi\u0016t7-\u001a$bS2,(/Z\'fgN\fw-Z\u0001$e\u0006<X*\u001b3TK:$XM\\2f\u001d\u0016<\u0017\r^3e\r\u0006LG.\u001e:f\u001b\u0016\u001c8/Y4f\u0003I1\u0017-\u001b7ve\u0016lUm]:bO\u0016\f%oZ:\u0016\u0003!\u00032!\u0013(Q\u001b\u0005Q%BA&M\u0003%IW.\\;uC\ndWM\u0003\u0002N/\u0005Q1m\u001c7mK\u000e$\u0018n\u001c8\n\u0005=S%A\u0002,fGR|\'\u000f\u0005\u0002\u001d#&\u0011!\u000b\u0005\u0002\u000f+:\fXo\u001c;fIN#(/\u001b8h\u0003eqWmZ1uK\u00124\u0015-\u001b7ve\u0016lUm]:bO\u0016\f%oZ:\u0002;5LGmU3oi\u0016t7-\u001a$bS2,(/Z\'fgN\fw-Z!sON\fA%\\5e\'\u0016tG/\u001a8dK:+w-\u0019;fI\u001a\u000b\u0017\u000e\\;sK6+7o]1hK\u0006\u0013xm\u001d"
    )
  ScalaInlineInfo: length = 0x8B (unknown attribute)
   01 00 00 1B 00 35 00 2E 00 00 2D 00 2E 00 00 3D
   00 2E 00 00 39 00 2E 00 00 B6 00 B7 00 00 14 00
   48 00 00 47 00 48 01 00 19 00 1A 00 00 7D 00 48
   00 00 7D 00 7E 00 00 25 00 1A 00 00 AC 00 48 00
   00 AC 00 7E 00 00 29 00 1A 00 00 AD 00 48 00 00
   AD 00 7E 00 00 21 00 1A 00 00 A9 00 48 00 00 A9
   00 7E 00 00 12 00 58 00 00 6D 00 1A 00 00 7B 00
   1A 00 00 7C 00 1A 00 00 77 00 1A 00 00 41 00 42
   00 00 0B 00 5C 00 00 5B 00 5C 01
  ScalaSig: length = 0x3 (unknown attribute)
   05 02 00
