Classfile /Users/mw/Projects/slang-braindump/.jar/jar8/assemble/slang-braindump/assemble/content/org/scalactic/BasicPrettifier.class
  Last modified May 29, 2022; size 4475 bytes
  SHA-256 checksum 28c047d6565c5f5a46e6528e56c8f4cb8c8072c19829bc4cb527223a2cd9eca7
  Compiled from "Prettifier.scala"
public class org.scalactic.BasicPrettifier implements org.scalactic.Prettifier
  minor version: 0
  major version: 52
  flags: (0x0021) ACC_PUBLIC, ACC_SUPER
  this_class: #2                          // org/scalactic/BasicPrettifier
  super_class: #4                         // java/lang/Object
  interfaces: 1, fields: 0, methods: 7, attributes: 6
Constant pool:
    #1 = Utf8               org/scalactic/BasicPrettifier
    #2 = Class              #1            // org/scalactic/BasicPrettifier
    #3 = Utf8               java/lang/Object
    #4 = Class              #3            // java/lang/Object
    #5 = Utf8               org/scalactic/Prettifier
    #6 = Class              #5            // org/scalactic/Prettifier
    #7 = Utf8               Prettifier.scala
    #8 = Utf8               Lscala/reflect/ScalaSignature;
    #9 = Utf8               bytes
   #10 = Utf8               \u0006\u000552Q\u0001B\u0003\u0001\u000b%AQ\u0001\u0006\u0001\u0005\u0002YAQ\u0001\u0007\u0001\u0005\u0002eAQA\u000b\u0001\u0005\n-\u0012qBQ1tS\u000e\u0004&/\u001a;uS\u001aLWM\u001d\u0006\u0003\r\u001d\t\u0011b]2bY\u0006\u001cG/[2\u000b\u0003!\t1a\u001c:h\'\r\u0001!\u0002\u0005\t\u0003\u00179i\u0011\u0001\u0004\u0006\u0002\u001b\u0005)1oY1mC&\u0011q\u0002\u0004\u0002\u0007\u0003:L(+\u001a4\u0011\u0005E\u0011R\"A\u0003\n\u0005M)!A\u0003)sKR$\u0018NZ5fe\u00061A(\u001b8jiz\u001a\u0001\u0001F\u0001\u0018!\t\t\u0002!A\u0003baBd\u0017\u0010\u0006\u0002\u001bKA\u00111D\t\b\u00039\u0001\u0002\"!\b\u0007\u000e\u0003yQ!aH\u000b\u0002\rq\u0012xn\u001c;?\u0013\t\tC\"\u0001\u0004Qe\u0016$WMZ\u0005\u0003G\u0011\u0012aa\u0015;sS:<\'BA\u0011\r\u0011\u00151#\u00011\u0001(\u0003\u0005y\u0007CA\u0006)\u0013\tICBA\u0002B]f\fa\u0002\u001d:fiRLg-_!se\u0006L8\u000f\u0006\u0002\u001bY!)ae\u0001a\u0001O\u0001
   #11 = Utf8               java/lang/invoke/MethodHandles$Lookup
   #12 = Class              #11           // java/lang/invoke/MethodHandles$Lookup
   #13 = Utf8               java/lang/invoke/MethodHandles
   #14 = Class              #13           // java/lang/invoke/MethodHandles
   #15 = Utf8               Lookup
   #16 = Utf8               scala/collection/mutable/ArraySeq$ofRef
   #17 = Class              #16           // scala/collection/mutable/ArraySeq$ofRef
   #18 = Utf8               scala/collection/mutable/ArraySeq
   #19 = Class              #18           // scala/collection/mutable/ArraySeq
   #20 = Utf8               ofRef
   #21 = Utf8               apply
   #22 = Utf8               (Ljava/lang/Object;Ljava/lang/Object;)Lorg/scalactic/PrettyPair;
   #23 = Utf8               left
   #24 = Utf8               right
   #25 = Utf8               apply$
   #26 = Utf8               (Lorg/scalactic/Prettifier;Ljava/lang/Object;Ljava/lang/Object;)Lorg/scalactic/PrettyPair;
   #27 = NameAndType        #25:#26       // apply$:(Lorg/scalactic/Prettifier;Ljava/lang/Object;Ljava/lang/Object;)Lorg/scalactic/PrettyPair;
   #28 = InterfaceMethodref #6.#27        // org/scalactic/Prettifier.apply$:(Lorg/scalactic/Prettifier;Ljava/lang/Object;Ljava/lang/Object;)Lorg/scalactic/PrettyPair;
   #29 = Utf8               this
   #30 = Utf8               Lorg/scalactic/BasicPrettifier;
   #31 = Utf8               Ljava/lang/Object;
   #32 = Utf8               (Ljava/lang/Object;)Ljava/lang/String;
   #33 = Utf8               o
   #34 = Utf8               null
   #35 = String             #34           // null
   #36 = Utf8               scala/runtime/BoxedUnit
   #37 = Class              #36           // scala/runtime/BoxedUnit
   #38 = Utf8               <(), the Unit value>
   #39 = String             #38           // <(), the Unit value>
   #40 = Utf8               java/lang/String
   #41 = Class              #40           // java/lang/String
   #42 = Utf8               java/lang/StringBuilder
   #43 = Class              #42           // java/lang/StringBuilder
   #44 = Integer            2
   #45 = Utf8               <init>
   #46 = Utf8               (I)V
   #47 = NameAndType        #45:#46       // "<init>":(I)V
   #48 = Methodref          #43.#47       // java/lang/StringBuilder."<init>":(I)V
   #49 = Utf8               \"
   #50 = String             #49           // \"
   #51 = Utf8               append
   #52 = Utf8               (Ljava/lang/String;)Ljava/lang/StringBuilder;
   #53 = NameAndType        #51:#52       // append:(Ljava/lang/String;)Ljava/lang/StringBuilder;
   #54 = Methodref          #43.#53       // java/lang/StringBuilder.append:(Ljava/lang/String;)Ljava/lang/StringBuilder;
   #55 = Utf8               toString
   #56 = Utf8               ()Ljava/lang/String;
   #57 = NameAndType        #55:#56       // toString:()Ljava/lang/String;
   #58 = Methodref          #43.#57       // java/lang/StringBuilder.toString:()Ljava/lang/String;
   #59 = Utf8               java/lang/Character
   #60 = Class              #59           // java/lang/Character
   #61 = Utf8               scala/runtime/BoxesRunTime
   #62 = Class              #61           // scala/runtime/BoxesRunTime
   #63 = Utf8               unboxToChar
   #64 = Utf8               (Ljava/lang/Object;)C
   #65 = NameAndType        #63:#64       // unboxToChar:(Ljava/lang/Object;)C
   #66 = Methodref          #62.#65       // scala/runtime/BoxesRunTime.unboxToChar:(Ljava/lang/Object;)C
   #67 = Utf8               \'
   #68 = String             #67           // \'
   #69 = Utf8               (C)Ljava/lang/StringBuilder;
   #70 = NameAndType        #51:#69       // append:(C)Ljava/lang/StringBuilder;
   #71 = Methodref          #43.#70       // java/lang/StringBuilder.append:(C)Ljava/lang/StringBuilder;
   #72 = Utf8               scala/runtime/ScalaRunTime$
   #73 = Class              #72           // scala/runtime/ScalaRunTime$
   #74 = Utf8               MODULE$
   #75 = Utf8               Lscala/runtime/ScalaRunTime$;
   #76 = NameAndType        #74:#75       // MODULE$:Lscala/runtime/ScalaRunTime$;
   #77 = Fieldref           #73.#76       // scala/runtime/ScalaRunTime$.MODULE$:Lscala/runtime/ScalaRunTime$;
   #78 = Utf8               isArray
   #79 = Utf8               (Ljava/lang/Object;I)Z
   #80 = NameAndType        #78:#79       // isArray:(Ljava/lang/Object;I)Z
   #81 = Methodref          #73.#80       // scala/runtime/ScalaRunTime$.isArray:(Ljava/lang/Object;I)Z
   #82 = Utf8               prettifyArrays
   #83 = NameAndType        #82:#32       // prettifyArrays:(Ljava/lang/Object;)Ljava/lang/String;
   #84 = Methodref          #2.#83        // org/scalactic/BasicPrettifier.prettifyArrays:(Ljava/lang/Object;)Ljava/lang/String;
   #85 = Methodref          #4.#57        // java/lang/Object.toString:()Ljava/lang/String;
   #86 = Integer            7
   #87 = Utf8               Array(
   #88 = String             #87           // Array(
   #89 = Utf8               scala/Predef$
   #90 = Class              #89           // scala/Predef$
   #91 = Utf8               Lscala/Predef$;
   #92 = NameAndType        #74:#91       // MODULE$:Lscala/Predef$;
   #93 = Fieldref           #90.#92       // scala/Predef$.MODULE$:Lscala/Predef$;
   #94 = Utf8               scala/collection/ArrayOps$
   #95 = Class              #94           // scala/collection/ArrayOps$
   #96 = Utf8               Lscala/collection/ArrayOps$;
   #97 = NameAndType        #74:#96       // MODULE$:Lscala/collection/ArrayOps$;
   #98 = Fieldref           #95.#97       // scala/collection/ArrayOps$.MODULE$:Lscala/collection/ArrayOps$;
   #99 = Utf8               genericArrayOps
  #100 = Utf8               (Ljava/lang/Object;)Ljava/lang/Object;
  #101 = NameAndType        #99:#100      // genericArrayOps:(Ljava/lang/Object;)Ljava/lang/Object;
  #102 = Methodref          #90.#101      // scala/Predef$.genericArrayOps:(Ljava/lang/Object;)Ljava/lang/Object;
  #103 = MethodType         #100          //  (Ljava/lang/Object;)Ljava/lang/Object;
  #104 = Utf8               $anonfun$prettifyArrays$1
  #105 = Utf8               (Lorg/scalactic/BasicPrettifier;Ljava/lang/Object;)Ljava/lang/String;
  #106 = NameAndType        #104:#105     // $anonfun$prettifyArrays$1:(Lorg/scalactic/BasicPrettifier;Ljava/lang/Object;)Ljava/lang/String;
  #107 = Methodref          #2.#106       // org/scalactic/BasicPrettifier.$anonfun$prettifyArrays$1:(Lorg/scalactic/BasicPrettifier;Ljava/lang/Object;)Ljava/lang/String;
  #108 = MethodHandle       6:#107        // REF_invokeStatic org/scalactic/BasicPrettifier.$anonfun$prettifyArrays$1:(Lorg/scalactic/BasicPrettifier;Ljava/lang/Object;)Ljava/lang/String;
  #109 = MethodType         #32           //  (Ljava/lang/Object;)Ljava/lang/String;
  #110 = Integer            5
  #111 = Integer            1
  #112 = Utf8               java/lang/invoke/LambdaMetafactory
  #113 = Class              #112          // java/lang/invoke/LambdaMetafactory
  #114 = Utf8               altMetafactory
  #115 = Utf8               (Ljava/lang/invoke/MethodHandles$Lookup;Ljava/lang/String;Ljava/lang/invoke/MethodType;[Ljava/lang/Object;)Ljava/lang/invoke/CallSite;
  #116 = NameAndType        #114:#115     // altMetafactory:(Ljava/lang/invoke/MethodHandles$Lookup;Ljava/lang/String;Ljava/lang/invoke/MethodType;[Ljava/lang/Object;)Ljava/lang/invoke/CallSite;
  #117 = Methodref          #113.#116     // java/lang/invoke/LambdaMetafactory.altMetafactory:(Ljava/lang/invoke/MethodHandles$Lookup;Ljava/lang/String;Ljava/lang/invoke/MethodType;[Ljava/lang/Object;)Ljava/lang/invoke/CallSite;
  #118 = MethodHandle       6:#117        // REF_invokeStatic java/lang/invoke/LambdaMetafactory.altMetafactory:(Ljava/lang/invoke/MethodHandles$Lookup;Ljava/lang/String;Ljava/lang/invoke/MethodType;[Ljava/lang/Object;)Ljava/lang/invoke/CallSite;
  #119 = Utf8               (Lorg/scalactic/BasicPrettifier;)Lscala/Function1;
  #120 = NameAndType        #21:#119      // apply:(Lorg/scalactic/BasicPrettifier;)Lscala/Function1;
  #121 = InvokeDynamic      #0:#120       // #0:apply:(Lorg/scalactic/BasicPrettifier;)Lscala/Function1;
  #122 = Utf8               scala/reflect/ClassTag$
  #123 = Class              #122          // scala/reflect/ClassTag$
  #124 = Utf8               Lscala/reflect/ClassTag$;
  #125 = NameAndType        #74:#124      // MODULE$:Lscala/reflect/ClassTag$;
  #126 = Fieldref           #123.#125     // scala/reflect/ClassTag$.MODULE$:Lscala/reflect/ClassTag$;
  #127 = Utf8               (Ljava/lang/Class;)Lscala/reflect/ClassTag;
  #128 = NameAndType        #21:#127      // apply:(Ljava/lang/Class;)Lscala/reflect/ClassTag;
  #129 = Methodref          #123.#128     // scala/reflect/ClassTag$.apply:(Ljava/lang/Class;)Lscala/reflect/ClassTag;
  #130 = Utf8               map$extension
  #131 = Utf8               (Ljava/lang/Object;Lscala/Function1;Lscala/reflect/ClassTag;)Ljava/lang/Object;
  #132 = NameAndType        #130:#131     // map$extension:(Ljava/lang/Object;Lscala/Function1;Lscala/reflect/ClassTag;)Ljava/lang/Object;
  #133 = Methodref          #95.#132      // scala/collection/ArrayOps$.map$extension:(Ljava/lang/Object;Lscala/Function1;Lscala/reflect/ClassTag;)Ljava/lang/Object;
  #134 = Utf8               [Ljava/lang/Object;
  #135 = Class              #134          // "[Ljava/lang/Object;"
  #136 = Utf8               wrapRefArray
  #137 = Utf8               ([Ljava/lang/Object;)Lscala/collection/mutable/ArraySeq$ofRef;
  #138 = NameAndType        #136:#137     // wrapRefArray:([Ljava/lang/Object;)Lscala/collection/mutable/ArraySeq$ofRef;
  #139 = Methodref          #90.#138      // scala/Predef$.wrapRefArray:([Ljava/lang/Object;)Lscala/collection/mutable/ArraySeq$ofRef;
  #140 = Utf8               ,
  #141 = String             #140          // ,
  #142 = Utf8               mkString
  #143 = Utf8               (Ljava/lang/String;)Ljava/lang/String;
  #144 = NameAndType        #142:#143     // mkString:(Ljava/lang/String;)Ljava/lang/String;
  #145 = Methodref          #17.#144      // scala/collection/mutable/ArraySeq$ofRef.mkString:(Ljava/lang/String;)Ljava/lang/String;
  #146 = Utf8               )
  #147 = String             #146          // )
  #148 = Utf8               $anonfun$prettifyArrays$2
  #149 = NameAndType        #148:#105     // $anonfun$prettifyArrays$2:(Lorg/scalactic/BasicPrettifier;Ljava/lang/Object;)Ljava/lang/String;
  #150 = Methodref          #2.#149       // org/scalactic/BasicPrettifier.$anonfun$prettifyArrays$2:(Lorg/scalactic/BasicPrettifier;Ljava/lang/Object;)Ljava/lang/String;
  #151 = MethodHandle       6:#150        // REF_invokeStatic org/scalactic/BasicPrettifier.$anonfun$prettifyArrays$2:(Lorg/scalactic/BasicPrettifier;Ljava/lang/Object;)Ljava/lang/String;
  #152 = InvokeDynamic      #1:#120       // #1:apply:(Lorg/scalactic/BasicPrettifier;)Lscala/Function1;
  #153 = Utf8               map
  #154 = Utf8               (Lscala/Function1;)Ljava/lang/Object;
  #155 = NameAndType        #153:#154     // map:(Lscala/Function1;)Ljava/lang/Object;
  #156 = Methodref          #19.#155      // scala/collection/mutable/ArraySeq.map:(Lscala/Function1;)Ljava/lang/Object;
  #157 = Utf8               scala/collection/IterableOnceOps
  #158 = Class              #157          // scala/collection/IterableOnceOps
  #159 = InterfaceMethodref #158.#144     // scala/collection/IterableOnceOps.mkString:(Ljava/lang/String;)Ljava/lang/String;
  #160 = Utf8               $this
  #161 = Utf8               a
  #162 = Utf8               ()V
  #163 = NameAndType        #45:#162      // "<init>":()V
  #164 = Methodref          #4.#163       // java/lang/Object."<init>":()V
  #165 = Utf8               $init$
  #166 = Utf8               (Lorg/scalactic/Prettifier;)V
  #167 = NameAndType        #165:#166     // $init$:(Lorg/scalactic/Prettifier;)V
  #168 = InterfaceMethodref #6.#167       // org/scalactic/Prettifier.$init$:(Lorg/scalactic/Prettifier;)V
  #169 = Utf8               $deserializeLambda$
  #170 = Utf8               (Ljava/lang/invoke/SerializedLambda;)Ljava/lang/Object;
  #171 = Utf8               scala/runtime/LambdaDeserialize
  #172 = Class              #171          // scala/runtime/LambdaDeserialize
  #173 = Utf8               bootstrap
  #174 = Utf8               (Ljava/lang/invoke/MethodHandles$Lookup;Ljava/lang/String;Ljava/lang/invoke/MethodType;[Ljava/lang/invoke/MethodHandle;)Ljava/lang/invoke/CallSite;
  #175 = NameAndType        #173:#174     // bootstrap:(Ljava/lang/invoke/MethodHandles$Lookup;Ljava/lang/String;Ljava/lang/invoke/MethodType;[Ljava/lang/invoke/MethodHandle;)Ljava/lang/invoke/CallSite;
  #176 = Methodref          #172.#175     // scala/runtime/LambdaDeserialize.bootstrap:(Ljava/lang/invoke/MethodHandles$Lookup;Ljava/lang/String;Ljava/lang/invoke/MethodType;[Ljava/lang/invoke/MethodHandle;)Ljava/lang/invoke/CallSite;
  #177 = MethodHandle       6:#176        // REF_invokeStatic scala/runtime/LambdaDeserialize.bootstrap:(Ljava/lang/invoke/MethodHandles$Lookup;Ljava/lang/String;Ljava/lang/invoke/MethodType;[Ljava/lang/invoke/MethodHandle;)Ljava/lang/invoke/CallSite;
  #178 = Utf8               lambdaDeserialize
  #179 = NameAndType        #178:#170     // lambdaDeserialize:(Ljava/lang/invoke/SerializedLambda;)Ljava/lang/Object;
  #180 = InvokeDynamic      #2:#179       // #2:lambdaDeserialize:(Ljava/lang/invoke/SerializedLambda;)Ljava/lang/Object;
  #181 = Utf8               Code
  #182 = Utf8               LineNumberTable
  #183 = Utf8               LocalVariableTable
  #184 = Utf8               MethodParameters
  #185 = Utf8               StackMapTable
  #186 = Utf8               InnerClasses
  #187 = Utf8               SourceFile
  #188 = Utf8               RuntimeVisibleAnnotations
  #189 = Utf8               BootstrapMethods
  #190 = Utf8               ScalaInlineInfo
  #191 = Utf8               ScalaSig
{
  public org.scalactic.PrettyPair apply(java.lang.Object, java.lang.Object);
    descriptor: (Ljava/lang/Object;Ljava/lang/Object;)Lorg/scalactic/PrettyPair;
    flags: (0x0001) ACC_PUBLIC
    Code:
      stack=3, locals=3, args_size=3
         0: aload_0
         1: aload_1
         2: aload_2
         3: invokestatic  #28                 // InterfaceMethod org/scalactic/Prettifier.apply$:(Lorg/scalactic/Prettifier;Ljava/lang/Object;Ljava/lang/Object;)Lorg/scalactic/PrettyPair;
         6: areturn
      LineNumberTable:
        line 349: 0
      LocalVariableTable:
        Start  Length  Slot  Name   Signature
            0       7     0  this   Lorg/scalactic/BasicPrettifier;
            0       7     1  left   Ljava/lang/Object;
            0       7     2 right   Ljava/lang/Object;
    MethodParameters:
      Name                           Flags
      left                           final
      right                          final

  public java.lang.String apply(java.lang.Object);
    descriptor: (Ljava/lang/Object;)Ljava/lang/String;
    flags: (0x0001) ACC_PUBLIC
    Code:
      stack=3, locals=8, args_size=2
         0: aload_1
         1: astore_3
         2: aload_3
         3: ifnonnull     12
         6: ldc           #35                 // String null
         8: astore_2
         9: goto          186
        12: goto          15
        15: aload_3
        16: instanceof    #37                 // class scala/runtime/BoxedUnit
        19: ifeq          28
        22: ldc           #39                 // String <(), the Unit value>
        24: astore_2
        25: goto          186
        28: goto          31
        31: aload_3
        32: instanceof    #41                 // class java/lang/String
        35: ifeq          75
        38: aload_3
        39: checkcast     #41                 // class java/lang/String
        42: astore        4
        44: new           #43                 // class java/lang/StringBuilder
        47: dup
        48: ldc           #44                 // int 2
        50: invokespecial #48                 // Method java/lang/StringBuilder."<init>":(I)V
        53: ldc           #50                 // String \"
        55: invokevirtual #54                 // Method java/lang/StringBuilder.append:(Ljava/lang/String;)Ljava/lang/StringBuilder;
        58: aload         4
        60: invokevirtual #54                 // Method java/lang/StringBuilder.append:(Ljava/lang/String;)Ljava/lang/StringBuilder;
        63: ldc           #50                 // String \"
        65: invokevirtual #54                 // Method java/lang/StringBuilder.append:(Ljava/lang/String;)Ljava/lang/StringBuilder;
        68: invokevirtual #58                 // Method java/lang/StringBuilder.toString:()Ljava/lang/String;
        71: astore_2
        72: goto          186
        75: goto          78
        78: aload_3
        79: instanceof    #60                 // class java/lang/Character
        82: ifeq          122
        85: aload_3
        86: invokestatic  #66                 // Method scala/runtime/BoxesRunTime.unboxToChar:(Ljava/lang/Object;)C
        89: istore        5
        91: new           #43                 // class java/lang/StringBuilder
        94: dup
        95: ldc           #44                 // int 2
        97: invokespecial #48                 // Method java/lang/StringBuilder."<init>":(I)V
       100: ldc           #68                 // String \'
       102: invokevirtual #54                 // Method java/lang/StringBuilder.append:(Ljava/lang/String;)Ljava/lang/StringBuilder;
       105: iload         5
       107: invokevirtual #71                 // Method java/lang/StringBuilder.append:(C)Ljava/lang/StringBuilder;
       110: ldc           #68                 // String \'
       112: invokevirtual #54                 // Method java/lang/StringBuilder.append:(Ljava/lang/String;)Ljava/lang/StringBuilder;
       115: invokevirtual #58                 // Method java/lang/StringBuilder.toString:()Ljava/lang/String;
       118: astore_2
       119: goto          186
       122: goto          125
       125: getstatic     #77                 // Field scala/runtime/ScalaRunTime$.MODULE$:Lscala/runtime/ScalaRunTime$;
       128: aload_3
       129: iconst_1
       130: invokevirtual #81                 // Method scala/runtime/ScalaRunTime$.isArray:(Ljava/lang/Object;I)Z
       133: ifeq          149
       136: aload_3
       137: astore        6
       139: aload_0
       140: aload         6
       142: invokespecial #84                 // Method prettifyArrays:(Ljava/lang/Object;)Ljava/lang/String;
       145: astore_2
       146: goto          186
       149: goto          152
       152: aload_3
       153: instanceof    #19                 // class scala/collection/mutable/ArraySeq
       156: ifeq          175
       159: aload_3
       160: checkcast     #19                 // class scala/collection/mutable/ArraySeq
       163: astore        7
       165: aload_0
       166: aload         7
       168: invokespecial #84                 // Method prettifyArrays:(Ljava/lang/Object;)Ljava/lang/String;
       171: astore_2
       172: goto          186
       175: goto          178
       178: aload_3
       179: invokevirtual #85                 // Method java/lang/Object.toString:()Ljava/lang/String;
       182: astore_2
       183: goto          186
       186: aload_2
       187: areturn
      StackMapTable: number_of_entries = 13
        frame_type = 253 /* append */
          offset_delta = 12
          locals = [ top, class java/lang/Object ]
        frame_type = 2 /* same */
        frame_type = 12 /* same */
        frame_type = 2 /* same */
        frame_type = 43 /* same */
        frame_type = 2 /* same */
        frame_type = 43 /* same */
        frame_type = 2 /* same */
        frame_type = 23 /* same */
        frame_type = 2 /* same */
        frame_type = 22 /* same */
        frame_type = 2 /* same */
        frame_type = 255 /* full_frame */
          offset_delta = 7
          locals = [ class org/scalactic/BasicPrettifier, class java/lang/Object, class java/lang/String, class java/lang/Object ]
          stack = []
      LineNumberTable:
        line 352: 0
        line 353: 2
        line 354: 15
        line 355: 31
        line 356: 78
        line 357: 125
        line 358: 152
        line 359: 178
        line 352: 186
      LocalVariableTable:
        Start  Length  Slot  Name   Signature
            0     188     0  this   Lorg/scalactic/BasicPrettifier;
            0     188     1     o   Ljava/lang/Object;
    MethodParameters:
      Name                           Flags
      o                              final

  private java.lang.String prettifyArrays(java.lang.Object);
    descriptor: (Ljava/lang/Object;)Ljava/lang/String;
    flags: (0x0002) ACC_PRIVATE
    Code:
      stack=7, locals=6, args_size=2
         0: aload_1
         1: astore_3
         2: getstatic     #77                 // Field scala/runtime/ScalaRunTime$.MODULE$:Lscala/runtime/ScalaRunTime$;
         5: aload_3
         6: iconst_1
         7: invokevirtual #81                 // Method scala/runtime/ScalaRunTime$.isArray:(Ljava/lang/Object;I)Z
        10: ifeq          87
        13: aload_3
        14: astore        4
        16: new           #43                 // class java/lang/StringBuilder
        19: dup
        20: ldc           #86                 // int 7
        22: invokespecial #48                 // Method java/lang/StringBuilder."<init>":(I)V
        25: ldc           #88                 // String Array(
        27: invokevirtual #54                 // Method java/lang/StringBuilder.append:(Ljava/lang/String;)Ljava/lang/StringBuilder;
        30: getstatic     #93                 // Field scala/Predef$.MODULE$:Lscala/Predef$;
        33: getstatic     #98                 // Field scala/collection/ArrayOps$.MODULE$:Lscala/collection/ArrayOps$;
        36: getstatic     #93                 // Field scala/Predef$.MODULE$:Lscala/Predef$;
        39: aload         4
        41: invokevirtual #102                // Method scala/Predef$.genericArrayOps:(Ljava/lang/Object;)Ljava/lang/Object;
        44: aload_0
        45: invokedynamic #121,  0            // InvokeDynamic #0:apply:(Lorg/scalactic/BasicPrettifier;)Lscala/Function1;
        50: getstatic     #126                // Field scala/reflect/ClassTag$.MODULE$:Lscala/reflect/ClassTag$;
        53: ldc           #41                 // class java/lang/String
        55: invokevirtual #129                // Method scala/reflect/ClassTag$.apply:(Ljava/lang/Class;)Lscala/reflect/ClassTag;
        58: invokevirtual #133                // Method scala/collection/ArrayOps$.map$extension:(Ljava/lang/Object;Lscala/Function1;Lscala/reflect/ClassTag;)Ljava/lang/Object;
        61: checkcast     #135                // class "[Ljava/lang/Object;"
        64: invokevirtual #139                // Method scala/Predef$.wrapRefArray:([Ljava/lang/Object;)Lscala/collection/mutable/ArraySeq$ofRef;
        67: ldc           #141                // String ,
        69: invokevirtual #145                // Method scala/collection/mutable/ArraySeq$ofRef.mkString:(Ljava/lang/String;)Ljava/lang/String;
        72: invokevirtual #54                 // Method java/lang/StringBuilder.append:(Ljava/lang/String;)Ljava/lang/StringBuilder;
        75: ldc           #147                // String )
        77: invokevirtual #54                 // Method java/lang/StringBuilder.append:(Ljava/lang/String;)Ljava/lang/StringBuilder;
        80: invokevirtual #58                 // Method java/lang/StringBuilder.toString:()Ljava/lang/String;
        83: astore_2
        84: goto          173
        87: goto          90
        90: aload_3
        91: instanceof    #19                 // class scala/collection/mutable/ArraySeq
        94: ifeq          153
        97: aload_3
        98: checkcast     #19                 // class scala/collection/mutable/ArraySeq
       101: astore        5
       103: new           #43                 // class java/lang/StringBuilder
       106: dup
       107: ldc           #86                 // int 7
       109: invokespecial #48                 // Method java/lang/StringBuilder."<init>":(I)V
       112: ldc           #88                 // String Array(
       114: invokevirtual #54                 // Method java/lang/StringBuilder.append:(Ljava/lang/String;)Ljava/lang/StringBuilder;
       117: aload         5
       119: aload_0
       120: invokedynamic #152,  0            // InvokeDynamic #1:apply:(Lorg/scalactic/BasicPrettifier;)Lscala/Function1;
       125: invokevirtual #156                // Method scala/collection/mutable/ArraySeq.map:(Lscala/Function1;)Ljava/lang/Object;
       128: checkcast     #158                // class scala/collection/IterableOnceOps
       131: ldc           #141                // String ,
       133: invokeinterface #159,  2          // InterfaceMethod scala/collection/IterableOnceOps.mkString:(Ljava/lang/String;)Ljava/lang/String;
       138: invokevirtual #54                 // Method java/lang/StringBuilder.append:(Ljava/lang/String;)Ljava/lang/StringBuilder;
       141: ldc           #147                // String )
       143: invokevirtual #54                 // Method java/lang/StringBuilder.append:(Ljava/lang/String;)Ljava/lang/StringBuilder;
       146: invokevirtual #58                 // Method java/lang/StringBuilder.toString:()Ljava/lang/String;
       149: astore_2
       150: goto          173
       153: goto          156
       156: aload_1
       157: ifnull        167
       160: aload_1
       161: invokevirtual #85                 // Method java/lang/Object.toString:()Ljava/lang/String;
       164: goto          169
       167: ldc           #35                 // String null
       169: astore_2
       170: goto          173
       173: aload_2
       174: areturn
      StackMapTable: number_of_entries = 7
        frame_type = 253 /* append */
          offset_delta = 87
          locals = [ top, class java/lang/Object ]
        frame_type = 2 /* same */
        frame_type = 62 /* same */
        frame_type = 2 /* same */
        frame_type = 10 /* same */
        frame_type = 65 /* same_locals_1_stack_item */
          stack = [ class java/lang/String ]
        frame_type = 255 /* full_frame */
          offset_delta = 3
          locals = [ class org/scalactic/BasicPrettifier, class java/lang/Object, class java/lang/String, class java/lang/Object ]
          stack = []
      LineNumberTable:
        line 363: 0
        line 364: 2
        line 365: 90
        line 366: 156
        line 363: 173
      LocalVariableTable:
        Start  Length  Slot  Name   Signature
            0     175     0  this   Lorg/scalactic/BasicPrettifier;
            0     175     1     o   Ljava/lang/Object;
    MethodParameters:
      Name                           Flags
      o                              final

  public static final java.lang.String $anonfun$prettifyArrays$1(org.scalactic.BasicPrettifier, java.lang.Object);
    descriptor: (Lorg/scalactic/BasicPrettifier;Ljava/lang/Object;)Ljava/lang/String;
    flags: (0x1019) ACC_PUBLIC, ACC_STATIC, ACC_FINAL, ACC_SYNTHETIC
    Code:
      stack=2, locals=2, args_size=2
         0: aload_0
         1: aload_1
         2: invokespecial #84                 // Method prettifyArrays:(Ljava/lang/Object;)Ljava/lang/String;
         5: areturn
      LineNumberTable:
        line 364: 0
      LocalVariableTable:
        Start  Length  Slot  Name   Signature
            0       6     0 $this   Lorg/scalactic/BasicPrettifier;
            0       6     1     a   Ljava/lang/Object;
    MethodParameters:
      Name                           Flags
      $this                          final synthetic
      a                              final

  public static final java.lang.String $anonfun$prettifyArrays$2(org.scalactic.BasicPrettifier, java.lang.Object);
    descriptor: (Lorg/scalactic/BasicPrettifier;Ljava/lang/Object;)Ljava/lang/String;
    flags: (0x1019) ACC_PUBLIC, ACC_STATIC, ACC_FINAL, ACC_SYNTHETIC
    Code:
      stack=2, locals=2, args_size=2
         0: aload_0
         1: aload_1
         2: invokespecial #84                 // Method prettifyArrays:(Ljava/lang/Object;)Ljava/lang/String;
         5: areturn
      LineNumberTable:
        line 365: 0
      LocalVariableTable:
        Start  Length  Slot  Name   Signature
            0       6     0 $this   Lorg/scalactic/BasicPrettifier;
            0       6     1     a   Ljava/lang/Object;
    MethodParameters:
      Name                           Flags
      $this                          final synthetic
      a                              final

  public org.scalactic.BasicPrettifier();
    descriptor: ()V
    flags: (0x0001) ACC_PUBLIC
    Code:
      stack=1, locals=1, args_size=1
         0: aload_0
         1: invokespecial #164                // Method java/lang/Object."<init>":()V
         4: aload_0
         5: invokestatic  #168                // InterfaceMethod org/scalactic/Prettifier.$init$:(Lorg/scalactic/Prettifier;)V
         8: return
      LineNumberTable:
        line 349: 0
      LocalVariableTable:
        Start  Length  Slot  Name   Signature
            0       9     0  this   Lorg/scalactic/BasicPrettifier;

  private static java.lang.Object $deserializeLambda$(java.lang.invoke.SerializedLambda);
    descriptor: (Ljava/lang/invoke/SerializedLambda;)Ljava/lang/Object;
    flags: (0x100a) ACC_PRIVATE, ACC_STATIC, ACC_SYNTHETIC
    Code:
      stack=1, locals=1, args_size=1
         0: aload_0
         1: invokedynamic #180,  0            // InvokeDynamic #2:lambdaDeserialize:(Ljava/lang/invoke/SerializedLambda;)Ljava/lang/Object;
         6: areturn
}
InnerClasses:
  public static final #15= #12 of #14;    // Lookup=class java/lang/invoke/MethodHandles$Lookup of class java/lang/invoke/MethodHandles
  public static final #20= #17 of #19;    // ofRef=class scala/collection/mutable/ArraySeq$ofRef of class scala/collection/mutable/ArraySeq
SourceFile: "Prettifier.scala"
RuntimeVisibleAnnotations:
  0: #8(#9=s#10)
    scala.reflect.ScalaSignature(
      bytes="\u0006\u000552Q\u0001B\u0003\u0001\u000b%AQ\u0001\u0006\u0001\u0005\u0002YAQ\u0001\u0007\u0001\u0005\u0002eAQA\u000b\u0001\u0005\n-\u0012qBQ1tS\u000e\u0004&/\u001a;uS\u001aLWM\u001d\u0006\u0003\r\u001d\t\u0011b]2bY\u0006\u001cG/[2\u000b\u0003!\t1a\u001c:h\'\r\u0001!\u0002\u0005\t\u0003\u00179i\u0011\u0001\u0004\u0006\u0002\u001b\u0005)1oY1mC&\u0011q\u0002\u0004\u0002\u0007\u0003:L(+\u001a4\u0011\u0005E\u0011R\"A\u0003\n\u0005M)!A\u0003)sKR$\u0018NZ5fe\u00061A(\u001b8jiz\u001a\u0001\u0001F\u0001\u0018!\t\t\u0002!A\u0003baBd\u0017\u0010\u0006\u0002\u001bKA\u00111D\t\b\u00039\u0001\u0002\"!\b\u0007\u000e\u0003yQ!aH\u000b\u0002\rq\u0012xn\u001c;?\u0013\t\tC\"\u0001\u0004Qe\u0016$WMZ\u0005\u0003G\u0011\u0012aa\u0015;sS:<\'BA\u0011\r\u0011\u00151#\u00011\u0001(\u0003\u0005y\u0007CA\u0006)\u0013\tICBA\u0002B]f\fa\u0002\u001d:fiRLg-_!se\u0006L8\u000f\u0006\u0002\u001bY!)ae\u0001a\u0001O\u0001"
    )
BootstrapMethods:
  0: #118 REF_invokeStatic java/lang/invoke/LambdaMetafactory.altMetafactory:(Ljava/lang/invoke/MethodHandles$Lookup;Ljava/lang/String;Ljava/lang/invoke/MethodType;[Ljava/lang/Object;)Ljava/lang/invoke/CallSite;
    Method arguments:
      #103 (Ljava/lang/Object;)Ljava/lang/Object;
      #108 REF_invokeStatic org/scalactic/BasicPrettifier.$anonfun$prettifyArrays$1:(Lorg/scalactic/BasicPrettifier;Ljava/lang/Object;)Ljava/lang/String;
      #109 (Ljava/lang/Object;)Ljava/lang/String;
      #110 5
      #111 1
      #109 (Ljava/lang/Object;)Ljava/lang/String;
  1: #118 REF_invokeStatic java/lang/invoke/LambdaMetafactory.altMetafactory:(Ljava/lang/invoke/MethodHandles$Lookup;Ljava/lang/String;Ljava/lang/invoke/MethodType;[Ljava/lang/Object;)Ljava/lang/invoke/CallSite;
    Method arguments:
      #103 (Ljava/lang/Object;)Ljava/lang/Object;
      #151 REF_invokeStatic org/scalactic/BasicPrettifier.$anonfun$prettifyArrays$2:(Lorg/scalactic/BasicPrettifier;Ljava/lang/Object;)Ljava/lang/String;
      #109 (Ljava/lang/Object;)Ljava/lang/String;
      #110 5
      #111 1
      #109 (Ljava/lang/Object;)Ljava/lang/String;
  2: #177 REF_invokeStatic scala/runtime/LambdaDeserialize.bootstrap:(Ljava/lang/invoke/MethodHandles$Lookup;Ljava/lang/String;Ljava/lang/invoke/MethodType;[Ljava/lang/invoke/MethodHandle;)Ljava/lang/invoke/CallSite;
    Method arguments:
      #108 REF_invokeStatic org/scalactic/BasicPrettifier.$anonfun$prettifyArrays$1:(Lorg/scalactic/BasicPrettifier;Ljava/lang/Object;)Ljava/lang/String;
      #151 REF_invokeStatic org/scalactic/BasicPrettifier.$anonfun$prettifyArrays$2:(Lorg/scalactic/BasicPrettifier;Ljava/lang/Object;)Ljava/lang/String;
  ScalaInlineInfo: length = 0x22 (unknown attribute)
   01 00 00 06 00 68 00 69 01 00 94 00 69 01 00 2D
   00 A2 00 00 15 00 20 00 00 15 00 16 00 00 52 00
   20 01
  ScalaSig: length = 0x3 (unknown attribute)
   05 02 00
