Classfile /Users/mw/Projects/slang-braindump/.jar/jar8/assemble/slang-braindump/assemble/content/org/scalactic/Bool.class
  Last modified May 29, 2022; size 11261 bytes
  SHA-256 checksum 52b7b0fd1e1f35c859f34d79d72f62f892c86fded9a1e1c8c176643849b1f38c
  Compiled from "Bool.scala"
public interface org.scalactic.Bool
  minor version: 0
  major version: 52
  flags: (0x0601) ACC_PUBLIC, ACC_INTERFACE, ACC_ABSTRACT
  this_class: #2                          // org/scalactic/Bool
  super_class: #4                         // java/lang/Object
  interfaces: 0, fields: 0, methods: 45, attributes: 6
Constant pool:
    #1 = Utf8               org/scalactic/Bool
    #2 = Class              #1            // org/scalactic/Bool
    #3 = Utf8               java/lang/Object
    #4 = Class              #3            // java/lang/Object
    #5 = Utf8               Bool.scala
    #6 = Utf8               Lscala/reflect/ScalaSignature;
    #7 = Utf8               bytes
    #8 = Utf8               \u0006\u0005\u0005=faB\u0013\'!\u0003\r\ta\u000b\u0005\u0006e\u0001!\ta\r\u0005\bo\u0001\u0011\rQ\"\u00019\u0011\u0015i\u0004\u0001\"\u0003?\u0011!!\u0006\u0001#b\u0001\n\u0003)\u0006\"\u00020\u0001\t\u0003y\u0006\"\u00021\u0001\t\u0003y\u0006\"B1\u0001\t\u0003y\u0006\"\u00022\u0001\t\u0003y\u0006\"B2\u0001\r\u0003!\u0007\"\u00025\u0001\r\u0003y\u0006\"B5\u0001\r\u0003y\u0006\"\u00026\u0001\r\u0003y\u0006\"B6\u0001\r\u0003y\u0006\"\u00027\u0001\r\u0003i\u0007\"\u0002<\u0001\r\u0003i\u0007\"B<\u0001\r\u0003i\u0007\"\u0002=\u0001\r\u0003i\u0007\"B=\u0001\t\u0003Q\bbBA\u0002\u0001\u0011\u0005\u0011Q\u0001\u0005\b\u0003\u0013\u0001A\u0011AA\u0006\u0011\u001d\ty\u0001\u0001C\u0001\u0003#Aq!!\u0006\u0001\t\u0003\t9bB\u0004\u0002\u001a\u0019B\t!a\u0007\u0007\r\u00152\u0003\u0012AA\u000f\u0011\u001d\ty\u0002\u0007C\u0001\u0003CAq!a\t\u0019\t\u0003\t)\u0003C\u0004\u0002,a!\t!!\f\t\u000f\u0005e\u0002\u0004\"\u0001\u0002<!9\u0011\u0011\b\r\u0005\u0002\u00055\u0003bBA-1\u0011\u0005\u00111\f\u0005\b\u00033BB\u0011AA3\u0011\u001d\ty\u0007\u0007C\u0001\u0003cBq!a\u001c\u0019\t\u0003\ty\bC\u0004\u0002\fb!\t!!$\t\u000f\u0005u\u0005\u0004\"\u0001\u0002 \"9\u0011\u0011\u0016\r\u0005\u0002\u0005-&\u0001\u0002\"p_2T!a\n\u0015\u0002\u0013M\u001c\u0017\r\\1di&\u001c\'\"A\u0015\u0002\u0007=\u0014xm\u0001\u0001\u0014\u0005\u0001a\u0003CA\u00171\u001b\u0005q#\"A\u0018\u0002\u000bM\u001c\u0017\r\\1\n\u0005Er#AB!osJ+g-\u0001\u0004%S:LG\u000f\n\u000b\u0002iA\u0011Q&N\u0005\u0003m9\u0012A!\u00168ji\u0006Q\u0001O]3ui&4\u0017.\u001a:\u0016\u0003e\u0002\"AO\u001e\u000e\u0003\u0019J!\u0001\u0010\u0014\u0003\u0015A\u0013X\r\u001e;jM&,\'/\u0001\u0006nC.,7\u000b\u001e:j]\u001e$2a\u0010&M!\t\u0001uI\u0004\u0002B\u000bB\u0011!IL\u0007\u0002\u0007*\u0011AIK\u0001\u0007yI|w\u000e\u001e \n\u0005\u0019s\u0013A\u0002)sK\u0012,g-\u0003\u0002I\u0013\n11\u000b\u001e:j]\u001eT!A\u0012\u0018\t\u000b-\u001b\u0001\u0019A \u0002\u0007I\fw\u000fC\u0003N\u0007\u0001\u0007a*\u0001\u0003be\u001e\u001c\bcA\u0017P#&\u0011\u0001K\f\u0002\u0006\u0003J\u0014\u0018-\u001f\t\u0003[IK!a\u0015\u0018\u0003\u0007\u0005s\u00170\u0001\u0005b]\u0006d\u0017p]5t+\u00051\u0006cA,]\u007f5\t\u0001L\u0003\u0002Z5\u0006I\u0011.\\7vi\u0006\u0014G.\u001a\u0006\u00037:\n!bY8mY\u0016\u001cG/[8o\u0013\ti\u0006L\u0001\u0006J]\u0012,\u00070\u001a3TKF\faBZ1jYV\u0014X-T3tg\u0006<W-F\u0001@\u0003UqWmZ1uK\u00124\u0015-\u001b7ve\u0016lUm]:bO\u0016\f\u0011$\\5e\'\u0016tG/\u001a8dK\u001a\u000b\u0017\u000e\\;sK6+7o]1hK\u0006\u0001S.\u001b3TK:$XM\\2f\u001d\u0016<\u0017\r^3e\r\u0006LG.\u001e:f\u001b\u0016\u001c8/Y4f\u0003\u00151\u0018\r\\;f+\u0005)\u0007CA\u0017g\u0013\t9gFA\u0004C_>dW-\u00198\u0002#I\fwOR1jYV\u0014X-T3tg\u0006<W-\u0001\rsC^tUmZ1uK\u00124\u0015-\u001b7ve\u0016lUm]:bO\u0016\fAD]1x\u001b&$7+\u001a8uK:\u001cWMR1jYV\u0014X-T3tg\u0006<W-A\u0012sC^l\u0015\u000eZ*f]R,gnY3OK\u001e\fG/\u001a3GC&dWO]3NKN\u001c\u0018mZ3\u0002%\u0019\f\u0017\u000e\\;sK6+7o]1hK\u0006\u0013xm]\u000b\u0002]B\u0019q\u000e^)\u000f\u0005A\u0014hB\u0001\"r\u0013\u0005y\u0013BA:/\u0003\u001d\u0001\u0018mY6bO\u0016L!!X;\u000b\u0005Mt\u0013!\u00078fO\u0006$X\r\u001a$bS2,(/Z\'fgN\fw-Z!sON\fQ$\\5e\'\u0016tG/\u001a8dK\u001a\u000b\u0017\u000e\\;sK6+7o]1hK\u0006\u0013xm]\u0001%[&$7+\u001a8uK:\u001cWMT3hCR,GMR1jYV\u0014X-T3tg\u0006<W-\u0011:hg\u0006AA%Y7qI\u0005l\u0007\u000f\u0006\u0002|yB\u0011!\b\u0001\u0005\u0007{J!\t\u0019\u0001@\u0002\t\t|w\u000e\u001c\t\u0004[}\\\u0018bAA\u0001]\tAAHY=oC6,g(\u0001\u0003%C6\u0004HcA>\u0002\b!1Qp\u0005CA\u0002y\f\u0001\u0002\n2be\u0012\u0012\u0017M\u001d\u000b\u0004w\u00065\u0001BB?\u0015\t\u0003\u0007a0\u0001\u0003%E\u0006\u0014HcA>\u0002\u0014!1Q0\u0006CA\u0002y\f1\"\u001e8bef|FEY1oOV\t10\u0001\u0003C_>d\u0007C\u0001\u001e\u0019\'\tAB&\u0001\u0004=S:LGO\u0010\u000b\u0003\u00037\tqA\\8u\u0005>|G\u000eF\u0003|\u0003O\tI\u0003C\u0003~5\u0001\u00071\u0010C\u000385\u0001\u0007\u0011(A\btS6\u0004H.Z\'bGJ|\'i\\8m)\u001dY\u0018qFA\u001a\u0003oAa!!\r\u001c\u0001\u0004)\u0017AC3yaJ,7o]5p]\"1\u0011QG\u000eA\u0002}\na\"\u001a=qe\u0016\u001c8/[8o)\u0016DH\u000fC\u000387\u0001\u0007\u0011(A\bcS:\f\'/_\'bGJ|\'i\\8m)-Y\u0018QHA!\u0003\u000b\nI%a\u0013\t\r\u0005}B\u00041\u0001R\u0003\u0011aWM\u001a;\t\r\u0005\rC\u00041\u0001@\u0003!y\u0007/\u001a:bi>\u0014\bBBA$9\u0001\u0007\u0011+A\u0003sS\u001eDG\u000f\u0003\u0004\u00022q\u0001\r!\u001a\u0005\u0006oq\u0001\r!\u000f\u000b\fw\u0006=\u0013\u0011KA*\u0003+\n9\u0006\u0003\u0004\u0002@u\u0001\r!\u0015\u0005\u0007\u0003\u0007j\u0002\u0019A \t\r\u0005\u001dS\u00041\u0001R\u0011\u0015iX\u00041\u0001|\u0011\u00159T\u00041\u0001:\u00039)h.\u0019:z\u001b\u0006\u001c\'o\u001c\"p_2$\u0012b_A/\u0003?\n\t\'a\u0019\t\r\u0005}b\u00041\u0001R\u0011\u0019\t\u0019E\ba\u0001\u007f!1\u0011\u0011\u0007\u0010A\u0002\u0015DQa\u000e\u0010A\u0002e\"\u0012b_A4\u0003S\nY\'!\u001c\t\r\u0005}r\u00041\u0001R\u0011\u0019\t\u0019e\ba\u0001\u007f!)Qp\ba\u0001w\")qg\ba\u0001s\u0005)\u0012n]%ogR\fgnY3PM6\u000b7M]8C_>dGcC>\u0002t\u0005U\u0014qOA>\u0003{Ba!a\u0010!\u0001\u0004\t\u0006BBA\"A\u0001\u0007q\b\u0003\u0004\u0002z\u0001\u0002\raP\u0001\nG2\f7o\u001d(b[\u0016Da!!\r!\u0001\u0004)\u0007\"B\u001c!\u0001\u0004IDcC>\u0002\u0002\u0006\r\u0015QQAD\u0003\u0013Ca!a\u0010\"\u0001\u0004\t\u0006BBA\"C\u0001\u0007q\b\u0003\u0004\u0002z\u0005\u0002\ra\u0010\u0005\u0006{\u0006\u0002\ra\u001f\u0005\u0006o\u0005\u0002\r!O\u0001\u0014Y\u0016tw\r\u001e5TSj,W*Y2s_\n{w\u000e\u001c\u000b\fw\u0006=\u0015\u0011SAJ\u0003/\u000bY\n\u0003\u0004\u0002@\t\u0002\r!\u0015\u0005\u0007\u0003\u0007\u0012\u0003\u0019A \t\r\u0005U%\u00051\u0001R\u0003\u0019\t7\r^;bY\"1\u0011\u0011\u0014\u0012A\u0002E\u000b\u0001\"\u001a=qK\u000e$X\r\u001a\u0005\u0006o\t\u0002\r!O\u0001\u0010KbL7\u000f^:NC\u000e\u0014xNQ8pYRI10!)\u0002$\u0006\u0015\u0016q\u0015\u0005\u0007\u0003\u007f\u0019\u0003\u0019A)\t\r\u0005\u001d3\u00051\u0001R\u0011\u0019\t\td\ta\u0001K\")qg\ta\u0001s\u0005i\u0012n]*j[BdWmV5uQ>,H/\u0012=qe\u0016\u001c8/[8o)\u0016DH\u000fF\u0002f\u0003[CQ! \u0013A\u0002m\u0004
    #9 = Utf8               java/lang/invoke/MethodHandles$Lookup
   #10 = Class              #9            // java/lang/invoke/MethodHandles$Lookup
   #11 = Utf8               java/lang/invoke/MethodHandles
   #12 = Class              #11           // java/lang/invoke/MethodHandles
   #13 = Utf8               Lookup
   #14 = Utf8               isSimpleWithoutExpressionText
   #15 = Utf8               (Lorg/scalactic/Bool;)Z
   #16 = Utf8               bool
   #17 = Utf8               org/scalactic/Bool$
   #18 = Class              #17           // org/scalactic/Bool$
   #19 = Utf8               MODULE$
   #20 = Utf8               Lorg/scalactic/Bool$;
   #21 = NameAndType        #19:#20       // MODULE$:Lorg/scalactic/Bool$;
   #22 = Fieldref           #18.#21       // org/scalactic/Bool$.MODULE$:Lorg/scalactic/Bool$;
   #23 = NameAndType        #14:#15       // isSimpleWithoutExpressionText:(Lorg/scalactic/Bool;)Z
   #24 = Methodref          #18.#23       // org/scalactic/Bool$.isSimpleWithoutExpressionText:(Lorg/scalactic/Bool;)Z
   #25 = Utf8               Lorg/scalactic/Bool;
   #26 = Utf8               existsMacroBool
   #27 = Utf8               (Ljava/lang/Object;Ljava/lang/Object;ZLorg/scalactic/Prettifier;)Lorg/scalactic/Bool;
   #28 = Utf8               left
   #29 = Utf8               right
   #30 = Utf8               expression
   #31 = Utf8               prettifier
   #32 = NameAndType        #26:#27       // existsMacroBool:(Ljava/lang/Object;Ljava/lang/Object;ZLorg/scalactic/Prettifier;)Lorg/scalactic/Bool;
   #33 = Methodref          #18.#32       // org/scalactic/Bool$.existsMacroBool:(Ljava/lang/Object;Ljava/lang/Object;ZLorg/scalactic/Prettifier;)Lorg/scalactic/Bool;
   #34 = Utf8               Ljava/lang/Object;
   #35 = Utf8               Z
   #36 = Utf8               Lorg/scalactic/Prettifier;
   #37 = Utf8               lengthSizeMacroBool
   #38 = Utf8               (Ljava/lang/Object;Ljava/lang/String;Ljava/lang/Object;Ljava/lang/Object;Lorg/scalactic/Prettifier;)Lorg/scalactic/Bool;
   #39 = Utf8               operator
   #40 = Utf8               actual
   #41 = Utf8               expected
   #42 = NameAndType        #37:#38       // lengthSizeMacroBool:(Ljava/lang/Object;Ljava/lang/String;Ljava/lang/Object;Ljava/lang/Object;Lorg/scalactic/Prettifier;)Lorg/scalactic/Bool;
   #43 = Methodref          #18.#42       // org/scalactic/Bool$.lengthSizeMacroBool:(Ljava/lang/Object;Ljava/lang/String;Ljava/lang/Object;Ljava/lang/Object;Lorg/scalactic/Prettifier;)Lorg/scalactic/Bool;
   #44 = Utf8               Ljava/lang/String;
   #45 = Utf8               isInstanceOfMacroBool
   #46 = Utf8               (Ljava/lang/Object;Ljava/lang/String;Ljava/lang/String;Lorg/scalactic/Bool;Lorg/scalactic/Prettifier;)Lorg/scalactic/Bool;
   #47 = Utf8               className
   #48 = NameAndType        #45:#46       // isInstanceOfMacroBool:(Ljava/lang/Object;Ljava/lang/String;Ljava/lang/String;Lorg/scalactic/Bool;Lorg/scalactic/Prettifier;)Lorg/scalactic/Bool;
   #49 = Methodref          #18.#48       // org/scalactic/Bool$.isInstanceOfMacroBool:(Ljava/lang/Object;Ljava/lang/String;Ljava/lang/String;Lorg/scalactic/Bool;Lorg/scalactic/Prettifier;)Lorg/scalactic/Bool;
   #50 = Utf8               (Ljava/lang/Object;Ljava/lang/String;Ljava/lang/String;ZLorg/scalactic/Prettifier;)Lorg/scalactic/Bool;
   #51 = NameAndType        #45:#50       // isInstanceOfMacroBool:(Ljava/lang/Object;Ljava/lang/String;Ljava/lang/String;ZLorg/scalactic/Prettifier;)Lorg/scalactic/Bool;
   #52 = Methodref          #18.#51       // org/scalactic/Bool$.isInstanceOfMacroBool:(Ljava/lang/Object;Ljava/lang/String;Ljava/lang/String;ZLorg/scalactic/Prettifier;)Lorg/scalactic/Bool;
   #53 = Utf8               unaryMacroBool
   #54 = Utf8               (Ljava/lang/Object;Ljava/lang/String;Lorg/scalactic/Bool;Lorg/scalactic/Prettifier;)Lorg/scalactic/Bool;
   #55 = NameAndType        #53:#54       // unaryMacroBool:(Ljava/lang/Object;Ljava/lang/String;Lorg/scalactic/Bool;Lorg/scalactic/Prettifier;)Lorg/scalactic/Bool;
   #56 = Methodref          #18.#55       // org/scalactic/Bool$.unaryMacroBool:(Ljava/lang/Object;Ljava/lang/String;Lorg/scalactic/Bool;Lorg/scalactic/Prettifier;)Lorg/scalactic/Bool;
   #57 = Utf8               (Ljava/lang/Object;Ljava/lang/String;ZLorg/scalactic/Prettifier;)Lorg/scalactic/Bool;
   #58 = NameAndType        #53:#57       // unaryMacroBool:(Ljava/lang/Object;Ljava/lang/String;ZLorg/scalactic/Prettifier;)Lorg/scalactic/Bool;
   #59 = Methodref          #18.#58       // org/scalactic/Bool$.unaryMacroBool:(Ljava/lang/Object;Ljava/lang/String;ZLorg/scalactic/Prettifier;)Lorg/scalactic/Bool;
   #60 = Utf8               binaryMacroBool
   #61 = Utf8               (Ljava/lang/Object;Ljava/lang/String;Ljava/lang/Object;Lorg/scalactic/Bool;Lorg/scalactic/Prettifier;)Lorg/scalactic/Bool;
   #62 = NameAndType        #60:#61       // binaryMacroBool:(Ljava/lang/Object;Ljava/lang/String;Ljava/lang/Object;Lorg/scalactic/Bool;Lorg/scalactic/Prettifier;)Lorg/scalactic/Bool;
   #63 = Methodref          #18.#62       // org/scalactic/Bool$.binaryMacroBool:(Ljava/lang/Object;Ljava/lang/String;Ljava/lang/Object;Lorg/scalactic/Bool;Lorg/scalactic/Prettifier;)Lorg/scalactic/Bool;
   #64 = Utf8               (Ljava/lang/Object;Ljava/lang/String;Ljava/lang/Object;ZLorg/scalactic/Prettifier;)Lorg/scalactic/Bool;
   #65 = NameAndType        #60:#64       // binaryMacroBool:(Ljava/lang/Object;Ljava/lang/String;Ljava/lang/Object;ZLorg/scalactic/Prettifier;)Lorg/scalactic/Bool;
   #66 = Methodref          #18.#65       // org/scalactic/Bool$.binaryMacroBool:(Ljava/lang/Object;Ljava/lang/String;Ljava/lang/Object;ZLorg/scalactic/Prettifier;)Lorg/scalactic/Bool;
   #67 = Utf8               simpleMacroBool
   #68 = Utf8               (ZLjava/lang/String;Lorg/scalactic/Prettifier;)Lorg/scalactic/Bool;
   #69 = Utf8               expressionText
   #70 = NameAndType        #67:#68       // simpleMacroBool:(ZLjava/lang/String;Lorg/scalactic/Prettifier;)Lorg/scalactic/Bool;
   #71 = Methodref          #18.#70       // org/scalactic/Bool$.simpleMacroBool:(ZLjava/lang/String;Lorg/scalactic/Prettifier;)Lorg/scalactic/Bool;
   #72 = Utf8               notBool
   #73 = Utf8               (Lorg/scalactic/Bool;Lorg/scalactic/Prettifier;)Lorg/scalactic/Bool;
   #74 = NameAndType        #72:#73       // notBool:(Lorg/scalactic/Bool;Lorg/scalactic/Prettifier;)Lorg/scalactic/Bool;
   #75 = Methodref          #18.#74       // org/scalactic/Bool$.notBool:(Lorg/scalactic/Bool;Lorg/scalactic/Prettifier;)Lorg/scalactic/Bool;
   #76 = Utf8               ()Lorg/scalactic/Prettifier;
   #77 = Utf8               makeString
   #78 = Utf8               (Ljava/lang/String;[Ljava/lang/Object;)Ljava/lang/String;
   #79 = Utf8               raw
   #80 = Utf8               args
   #81 = Utf8               org/scalactic/Resources$
   #82 = Class              #81           // org/scalactic/Resources$
   #83 = Utf8               Lorg/scalactic/Resources$;
   #84 = NameAndType        #19:#83       // MODULE$:Lorg/scalactic/Resources$;
   #85 = Fieldref           #82.#84       // org/scalactic/Resources$.MODULE$:Lorg/scalactic/Resources$;
   #86 = Utf8               scala/collection/ArrayOps$
   #87 = Class              #86           // scala/collection/ArrayOps$
   #88 = Utf8               Lscala/collection/ArrayOps$;
   #89 = NameAndType        #19:#88       // MODULE$:Lscala/collection/ArrayOps$;
   #90 = Fieldref           #87.#89       // scala/collection/ArrayOps$.MODULE$:Lscala/collection/ArrayOps$;
   #91 = Utf8               scala/Predef$
   #92 = Class              #91           // scala/Predef$
   #93 = Utf8               Lscala/Predef$;
   #94 = NameAndType        #19:#93       // MODULE$:Lscala/Predef$;
   #95 = Fieldref           #92.#94       // scala/Predef$.MODULE$:Lscala/Predef$;
   #96 = Utf8               genericArrayOps
   #97 = Utf8               (Ljava/lang/Object;)Ljava/lang/Object;
   #98 = NameAndType        #96:#97       // genericArrayOps:(Ljava/lang/Object;)Ljava/lang/Object;
   #99 = Methodref          #92.#98       // scala/Predef$.genericArrayOps:(Ljava/lang/Object;)Ljava/lang/Object;
  #100 = MethodType         #97           //  (Ljava/lang/Object;)Ljava/lang/Object;
  #101 = Utf8               $anonfun$makeString$1
  #102 = Utf8               (Lorg/scalactic/Bool;Ljava/lang/Object;)Ljava/lang/String;
  #103 = NameAndType        #101:#102     // $anonfun$makeString$1:(Lorg/scalactic/Bool;Ljava/lang/Object;)Ljava/lang/String;
  #104 = InterfaceMethodref #2.#103       // org/scalactic/Bool.$anonfun$makeString$1:(Lorg/scalactic/Bool;Ljava/lang/Object;)Ljava/lang/String;
  #105 = MethodHandle       6:#104        // REF_invokeStatic org/scalactic/Bool.$anonfun$makeString$1:(Lorg/scalactic/Bool;Ljava/lang/Object;)Ljava/lang/String;
  #106 = Utf8               (Ljava/lang/Object;)Ljava/lang/String;
  #107 = MethodType         #106          //  (Ljava/lang/Object;)Ljava/lang/String;
  #108 = Integer            5
  #109 = Integer            1
  #110 = Utf8               java/lang/invoke/LambdaMetafactory
  #111 = Class              #110          // java/lang/invoke/LambdaMetafactory
  #112 = Utf8               altMetafactory
  #113 = Utf8               (Ljava/lang/invoke/MethodHandles$Lookup;Ljava/lang/String;Ljava/lang/invoke/MethodType;[Ljava/lang/Object;)Ljava/lang/invoke/CallSite;
  #114 = NameAndType        #112:#113     // altMetafactory:(Ljava/lang/invoke/MethodHandles$Lookup;Ljava/lang/String;Ljava/lang/invoke/MethodType;[Ljava/lang/Object;)Ljava/lang/invoke/CallSite;
  #115 = Methodref          #111.#114     // java/lang/invoke/LambdaMetafactory.altMetafactory:(Ljava/lang/invoke/MethodHandles$Lookup;Ljava/lang/String;Ljava/lang/invoke/MethodType;[Ljava/lang/Object;)Ljava/lang/invoke/CallSite;
  #116 = MethodHandle       6:#115        // REF_invokeStatic java/lang/invoke/LambdaMetafactory.altMetafactory:(Ljava/lang/invoke/MethodHandles$Lookup;Ljava/lang/String;Ljava/lang/invoke/MethodType;[Ljava/lang/Object;)Ljava/lang/invoke/CallSite;
  #117 = Utf8               apply
  #118 = Utf8               (Lorg/scalactic/Bool;)Lscala/Function1;
  #119 = NameAndType        #117:#118     // apply:(Lorg/scalactic/Bool;)Lscala/Function1;
  #120 = InvokeDynamic      #0:#119       // #0:apply:(Lorg/scalactic/Bool;)Lscala/Function1;
  #121 = Utf8               scala/reflect/ClassTag$
  #122 = Class              #121          // scala/reflect/ClassTag$
  #123 = Utf8               Lscala/reflect/ClassTag$;
  #124 = NameAndType        #19:#123      // MODULE$:Lscala/reflect/ClassTag$;
  #125 = Fieldref           #122.#124     // scala/reflect/ClassTag$.MODULE$:Lscala/reflect/ClassTag$;
  #126 = Utf8               Any
  #127 = Utf8               ()Lscala/reflect/ClassTag;
  #128 = NameAndType        #126:#127     // Any:()Lscala/reflect/ClassTag;
  #129 = Methodref          #122.#128     // scala/reflect/ClassTag$.Any:()Lscala/reflect/ClassTag;
  #130 = Utf8               map$extension
  #131 = Utf8               (Ljava/lang/Object;Lscala/Function1;Lscala/reflect/ClassTag;)Ljava/lang/Object;
  #132 = NameAndType        #130:#131     // map$extension:(Ljava/lang/Object;Lscala/Function1;Lscala/reflect/ClassTag;)Ljava/lang/Object;
  #133 = Methodref          #87.#132      // scala/collection/ArrayOps$.map$extension:(Ljava/lang/Object;Lscala/Function1;Lscala/reflect/ClassTag;)Ljava/lang/Object;
  #134 = Utf8               [Ljava/lang/Object;
  #135 = Class              #134          // "[Ljava/lang/Object;"
  #136 = Utf8               formatString
  #137 = NameAndType        #136:#78      // formatString:(Ljava/lang/String;[Ljava/lang/Object;)Ljava/lang/String;
  #138 = Methodref          #82.#137      // org/scalactic/Resources$.formatString:(Ljava/lang/String;[Ljava/lang/Object;)Ljava/lang/String;
  #139 = Utf8               this
  #140 = Utf8               analysis$
  #141 = Utf8               (Lorg/scalactic/Bool;)Lscala/collection/immutable/IndexedSeq;
  #142 = Utf8               $this
  #143 = Utf8               analysis
  #144 = Utf8               ()Lscala/collection/immutable/IndexedSeq;
  #145 = NameAndType        #143:#144     // analysis:()Lscala/collection/immutable/IndexedSeq;
  #146 = InterfaceMethodref #2.#145       // org/scalactic/Bool.analysis:()Lscala/collection/immutable/IndexedSeq;
  #147 = Utf8               ()Lscala/collection/immutable/IndexedSeq<Ljava/lang/String;>;
  #148 = Utf8               scala/package$
  #149 = Class              #148          // scala/package$
  #150 = Utf8               Lscala/package$;
  #151 = NameAndType        #19:#150      // MODULE$:Lscala/package$;
  #152 = Fieldref           #149.#151     // scala/package$.MODULE$:Lscala/package$;
  #153 = Utf8               Vector
  #154 = Utf8               ()Lscala/collection/immutable/Vector$;
  #155 = NameAndType        #153:#154     // Vector:()Lscala/collection/immutable/Vector$;
  #156 = Methodref          #149.#155     // scala/package$.Vector:()Lscala/collection/immutable/Vector$;
  #157 = Utf8               scala/collection/immutable/Vector$
  #158 = Class              #157          // scala/collection/immutable/Vector$
  #159 = Utf8               empty
  #160 = Utf8               ()Lscala/collection/immutable/Vector;
  #161 = NameAndType        #159:#160     // empty:()Lscala/collection/immutable/Vector;
  #162 = Methodref          #158.#161     // scala/collection/immutable/Vector$.empty:()Lscala/collection/immutable/Vector;
  #163 = Utf8               failureMessage$
  #164 = Utf8               (Lorg/scalactic/Bool;)Ljava/lang/String;
  #165 = Utf8               failureMessage
  #166 = Utf8               ()Ljava/lang/String;
  #167 = NameAndType        #165:#166     // failureMessage:()Ljava/lang/String;
  #168 = InterfaceMethodref #2.#167       // org/scalactic/Bool.failureMessage:()Ljava/lang/String;
  #169 = Utf8               failureMessageArgs
  #170 = NameAndType        #169:#144     // failureMessageArgs:()Lscala/collection/immutable/IndexedSeq;
  #171 = InterfaceMethodref #2.#170       // org/scalactic/Bool.failureMessageArgs:()Lscala/collection/immutable/IndexedSeq;
  #172 = Utf8               scala/collection/immutable/IndexedSeq
  #173 = Class              #172          // scala/collection/immutable/IndexedSeq
  #174 = Utf8               isEmpty
  #175 = Utf8               ()Z
  #176 = NameAndType        #174:#175     // isEmpty:()Z
  #177 = InterfaceMethodref #173.#176     // scala/collection/immutable/IndexedSeq.isEmpty:()Z
  #178 = Utf8               rawFailureMessage
  #179 = NameAndType        #178:#166     // rawFailureMessage:()Ljava/lang/String;
  #180 = InterfaceMethodref #2.#179       // org/scalactic/Bool.rawFailureMessage:()Ljava/lang/String;
  #181 = Utf8               toArray
  #182 = Utf8               (Lscala/reflect/ClassTag;)Ljava/lang/Object;
  #183 = NameAndType        #181:#182     // toArray:(Lscala/reflect/ClassTag;)Ljava/lang/Object;
  #184 = InterfaceMethodref #173.#183     // scala/collection/immutable/IndexedSeq.toArray:(Lscala/reflect/ClassTag;)Ljava/lang/Object;
  #185 = NameAndType        #77:#78       // makeString:(Ljava/lang/String;[Ljava/lang/Object;)Ljava/lang/String;
  #186 = InterfaceMethodref #2.#185       // org/scalactic/Bool.makeString:(Ljava/lang/String;[Ljava/lang/Object;)Ljava/lang/String;
  #187 = Utf8               java/lang/String
  #188 = Class              #187          // java/lang/String
  #189 = Utf8               negatedFailureMessage$
  #190 = Utf8               negatedFailureMessage
  #191 = NameAndType        #190:#166     // negatedFailureMessage:()Ljava/lang/String;
  #192 = InterfaceMethodref #2.#191       // org/scalactic/Bool.negatedFailureMessage:()Ljava/lang/String;
  #193 = Utf8               negatedFailureMessageArgs
  #194 = NameAndType        #193:#144     // negatedFailureMessageArgs:()Lscala/collection/immutable/IndexedSeq;
  #195 = InterfaceMethodref #2.#194       // org/scalactic/Bool.negatedFailureMessageArgs:()Lscala/collection/immutable/IndexedSeq;
  #196 = Utf8               rawNegatedFailureMessage
  #197 = NameAndType        #196:#166     // rawNegatedFailureMessage:()Ljava/lang/String;
  #198 = InterfaceMethodref #2.#197       // org/scalactic/Bool.rawNegatedFailureMessage:()Ljava/lang/String;
  #199 = Utf8               midSentenceFailureMessage$
  #200 = Utf8               midSentenceFailureMessage
  #201 = NameAndType        #200:#166     // midSentenceFailureMessage:()Ljava/lang/String;
  #202 = InterfaceMethodref #2.#201       // org/scalactic/Bool.midSentenceFailureMessage:()Ljava/lang/String;
  #203 = Utf8               midSentenceFailureMessageArgs
  #204 = NameAndType        #203:#144     // midSentenceFailureMessageArgs:()Lscala/collection/immutable/IndexedSeq;
  #205 = InterfaceMethodref #2.#204       // org/scalactic/Bool.midSentenceFailureMessageArgs:()Lscala/collection/immutable/IndexedSeq;
  #206 = Utf8               rawMidSentenceFailureMessage
  #207 = NameAndType        #206:#166     // rawMidSentenceFailureMessage:()Ljava/lang/String;
  #208 = InterfaceMethodref #2.#207       // org/scalactic/Bool.rawMidSentenceFailureMessage:()Ljava/lang/String;
  #209 = Utf8               midSentenceNegatedFailureMessage$
  #210 = Utf8               midSentenceNegatedFailureMessage
  #211 = NameAndType        #210:#166     // midSentenceNegatedFailureMessage:()Ljava/lang/String;
  #212 = InterfaceMethodref #2.#211       // org/scalactic/Bool.midSentenceNegatedFailureMessage:()Ljava/lang/String;
  #213 = Utf8               midSentenceNegatedFailureMessageArgs
  #214 = NameAndType        #213:#144     // midSentenceNegatedFailureMessageArgs:()Lscala/collection/immutable/IndexedSeq;
  #215 = InterfaceMethodref #2.#214       // org/scalactic/Bool.midSentenceNegatedFailureMessageArgs:()Lscala/collection/immutable/IndexedSeq;
  #216 = Utf8               rawMidSentenceNegatedFailureMessage
  #217 = NameAndType        #216:#166     // rawMidSentenceNegatedFailureMessage:()Ljava/lang/String;
  #218 = InterfaceMethodref #2.#217       // org/scalactic/Bool.rawMidSentenceNegatedFailureMessage:()Ljava/lang/String;
  #219 = Utf8               value
  #220 = Utf8               ()Lscala/collection/immutable/IndexedSeq<Ljava/lang/Object;>;
  #221 = Utf8               $amp$amp$
  #222 = Utf8               (Lorg/scalactic/Bool;Lscala/Function0;)Lorg/scalactic/Bool;
  #223 = Utf8               $amp$amp
  #224 = Utf8               (Lscala/Function0;)Lorg/scalactic/Bool;
  #225 = NameAndType        #223:#224     // $amp$amp:(Lscala/Function0;)Lorg/scalactic/Bool;
  #226 = InterfaceMethodref #2.#225       // org/scalactic/Bool.$amp$amp:(Lscala/Function0;)Lorg/scalactic/Bool;
  #227 = Utf8               Lscala/Function0;
  #228 = Utf8               (Lscala/Function0<Lorg/scalactic/Bool;>;)Lorg/scalactic/Bool;
  #229 = NameAndType        #219:#175     // value:()Z
  #230 = InterfaceMethodref #2.#229       // org/scalactic/Bool.value:()Z
  #231 = Utf8               org/scalactic/AndBool
  #232 = Class              #231          // org/scalactic/AndBool
  #233 = NameAndType        #31:#76       // prettifier:()Lorg/scalactic/Prettifier;
  #234 = InterfaceMethodref #2.#233       // org/scalactic/Bool.prettifier:()Lorg/scalactic/Prettifier;
  #235 = Utf8               <init>
  #236 = Utf8               (Lorg/scalactic/Bool;Lscala/Function0;Lorg/scalactic/Prettifier;)V
  #237 = NameAndType        #235:#236     // "<init>":(Lorg/scalactic/Bool;Lscala/Function0;Lorg/scalactic/Prettifier;)V
  #238 = Methodref          #232.#237     // org/scalactic/AndBool."<init>":(Lorg/scalactic/Bool;Lscala/Function0;Lorg/scalactic/Prettifier;)V
  #239 = Utf8               $amp$
  #240 = Utf8               $amp
  #241 = NameAndType        #240:#224     // $amp:(Lscala/Function0;)Lorg/scalactic/Bool;
  #242 = InterfaceMethodref #2.#241       // org/scalactic/Bool.$amp:(Lscala/Function0;)Lorg/scalactic/Bool;
  #243 = Utf8               $bar$bar$
  #244 = Utf8               $bar$bar
  #245 = NameAndType        #244:#224     // $bar$bar:(Lscala/Function0;)Lorg/scalactic/Bool;
  #246 = InterfaceMethodref #2.#245       // org/scalactic/Bool.$bar$bar:(Lscala/Function0;)Lorg/scalactic/Bool;
  #247 = Utf8               org/scalactic/OrBool
  #248 = Class              #247          // org/scalactic/OrBool
  #249 = Methodref          #248.#237     // org/scalactic/OrBool."<init>":(Lorg/scalactic/Bool;Lscala/Function0;Lorg/scalactic/Prettifier;)V
  #250 = Utf8               $bar$
  #251 = Utf8               $bar
  #252 = NameAndType        #251:#224     // $bar:(Lscala/Function0;)Lorg/scalactic/Bool;
  #253 = InterfaceMethodref #2.#252       // org/scalactic/Bool.$bar:(Lscala/Function0;)Lorg/scalactic/Bool;
  #254 = Utf8               unary_$bang$
  #255 = Utf8               (Lorg/scalactic/Bool;)Lorg/scalactic/Bool;
  #256 = Utf8               unary_$bang
  #257 = Utf8               ()Lorg/scalactic/Bool;
  #258 = NameAndType        #256:#257     // unary_$bang:()Lorg/scalactic/Bool;
  #259 = InterfaceMethodref #2.#258       // org/scalactic/Bool.unary_$bang:()Lorg/scalactic/Bool;
  #260 = Utf8               org/scalactic/NotBool
  #261 = Class              #260          // org/scalactic/NotBool
  #262 = Utf8               (Lorg/scalactic/Bool;Lorg/scalactic/Prettifier;)V
  #263 = NameAndType        #235:#262     // "<init>":(Lorg/scalactic/Bool;Lorg/scalactic/Prettifier;)V
  #264 = Methodref          #261.#263     // org/scalactic/NotBool."<init>":(Lorg/scalactic/Bool;Lorg/scalactic/Prettifier;)V
  #265 = Utf8               o
  #266 = Utf8               org/scalactic/Prettifier
  #267 = Class              #266          // org/scalactic/Prettifier
  #268 = NameAndType        #117:#106     // apply:(Ljava/lang/Object;)Ljava/lang/String;
  #269 = InterfaceMethodref #267.#268     // org/scalactic/Prettifier.apply:(Ljava/lang/Object;)Ljava/lang/String;
  #270 = Utf8               $init$
  #271 = Utf8               (Lorg/scalactic/Bool;)V
  #272 = Utf8               $deserializeLambda$
  #273 = Utf8               (Ljava/lang/invoke/SerializedLambda;)Ljava/lang/Object;
  #274 = Utf8               scala/runtime/LambdaDeserialize
  #275 = Class              #274          // scala/runtime/LambdaDeserialize
  #276 = Utf8               bootstrap
  #277 = Utf8               (Ljava/lang/invoke/MethodHandles$Lookup;Ljava/lang/String;Ljava/lang/invoke/MethodType;[Ljava/lang/invoke/MethodHandle;)Ljava/lang/invoke/CallSite;
  #278 = NameAndType        #276:#277     // bootstrap:(Ljava/lang/invoke/MethodHandles$Lookup;Ljava/lang/String;Ljava/lang/invoke/MethodType;[Ljava/lang/invoke/MethodHandle;)Ljava/lang/invoke/CallSite;
  #279 = Methodref          #275.#278     // scala/runtime/LambdaDeserialize.bootstrap:(Ljava/lang/invoke/MethodHandles$Lookup;Ljava/lang/String;Ljava/lang/invoke/MethodType;[Ljava/lang/invoke/MethodHandle;)Ljava/lang/invoke/CallSite;
  #280 = MethodHandle       6:#279        // REF_invokeStatic scala/runtime/LambdaDeserialize.bootstrap:(Ljava/lang/invoke/MethodHandles$Lookup;Ljava/lang/String;Ljava/lang/invoke/MethodType;[Ljava/lang/invoke/MethodHandle;)Ljava/lang/invoke/CallSite;
  #281 = Utf8               lambdaDeserialize
  #282 = NameAndType        #281:#273     // lambdaDeserialize:(Ljava/lang/invoke/SerializedLambda;)Ljava/lang/Object;
  #283 = InvokeDynamic      #1:#282       // #1:lambdaDeserialize:(Ljava/lang/invoke/SerializedLambda;)Ljava/lang/Object;
  #284 = Utf8               Code
  #285 = Utf8               LocalVariableTable
  #286 = Utf8               MethodParameters
  #287 = Utf8               LineNumberTable
  #288 = Utf8               Signature
  #289 = Utf8               StackMapTable
  #290 = Utf8               InnerClasses
  #291 = Utf8               SourceFile
  #292 = Utf8               RuntimeVisibleAnnotations
  #293 = Utf8               BootstrapMethods
  #294 = Utf8               ScalaInlineInfo
  #295 = Utf8               ScalaSig
{
  public static boolean isSimpleWithoutExpressionText(org.scalactic.Bool);
    descriptor: (Lorg/scalactic/Bool;)Z
    flags: (0x0009) ACC_PUBLIC, ACC_STATIC
    Code:
      stack=2, locals=1, args_size=1
         0: getstatic     #22                 // Field org/scalactic/Bool$.MODULE$:Lorg/scalactic/Bool$;
         3: aload_0
         4: invokevirtual #24                 // Method org/scalactic/Bool$.isSimpleWithoutExpressionText:(Lorg/scalactic/Bool;)Z
         7: ireturn
      LocalVariableTable:
        Start  Length  Slot  Name   Signature
            0       8     0  bool   Lorg/scalactic/Bool;
    MethodParameters:
      Name                           Flags
      bool                           final

  public static org.scalactic.Bool existsMacroBool(java.lang.Object, java.lang.Object, boolean, org.scalactic.Prettifier);
    descriptor: (Ljava/lang/Object;Ljava/lang/Object;ZLorg/scalactic/Prettifier;)Lorg/scalactic/Bool;
    flags: (0x0009) ACC_PUBLIC, ACC_STATIC
    Code:
      stack=5, locals=4, args_size=4
         0: getstatic     #22                 // Field org/scalactic/Bool$.MODULE$:Lorg/scalactic/Bool$;
         3: aload_0
         4: aload_1
         5: iload_2
         6: aload_3
         7: invokevirtual #33                 // Method org/scalactic/Bool$.existsMacroBool:(Ljava/lang/Object;Ljava/lang/Object;ZLorg/scalactic/Prettifier;)Lorg/scalactic/Bool;
        10: areturn
      LocalVariableTable:
        Start  Length  Slot  Name   Signature
            0      11     0  left   Ljava/lang/Object;
            0      11     1 right   Ljava/lang/Object;
            0      11     2 expression   Z
            0      11     3 prettifier   Lorg/scalactic/Prettifier;
    MethodParameters:
      Name                           Flags
      left                           final
      right                          final
      expression                     final
      prettifier                     final

  public static org.scalactic.Bool lengthSizeMacroBool(java.lang.Object, java.lang.String, java.lang.Object, java.lang.Object, org.scalactic.Prettifier);
    descriptor: (Ljava/lang/Object;Ljava/lang/String;Ljava/lang/Object;Ljava/lang/Object;Lorg/scalactic/Prettifier;)Lorg/scalactic/Bool;
    flags: (0x0009) ACC_PUBLIC, ACC_STATIC
    Code:
      stack=6, locals=5, args_size=5
         0: getstatic     #22                 // Field org/scalactic/Bool$.MODULE$:Lorg/scalactic/Bool$;
         3: aload_0
         4: aload_1
         5: aload_2
         6: aload_3
         7: aload         4
         9: invokevirtual #43                 // Method org/scalactic/Bool$.lengthSizeMacroBool:(Ljava/lang/Object;Ljava/lang/String;Ljava/lang/Object;Ljava/lang/Object;Lorg/scalactic/Prettifier;)Lorg/scalactic/Bool;
        12: areturn
      LocalVariableTable:
        Start  Length  Slot  Name   Signature
            0      13     0  left   Ljava/lang/Object;
            0      13     1 operator   Ljava/lang/String;
            0      13     2 actual   Ljava/lang/Object;
            0      13     3 expected   Ljava/lang/Object;
            0      13     4 prettifier   Lorg/scalactic/Prettifier;
    MethodParameters:
      Name                           Flags
      left                           final
      operator                       final
      actual                         final
      expected                       final
      prettifier                     final

  public static org.scalactic.Bool isInstanceOfMacroBool(java.lang.Object, java.lang.String, java.lang.String, org.scalactic.Bool, org.scalactic.Prettifier);
    descriptor: (Ljava/lang/Object;Ljava/lang/String;Ljava/lang/String;Lorg/scalactic/Bool;Lorg/scalactic/Prettifier;)Lorg/scalactic/Bool;
    flags: (0x0009) ACC_PUBLIC, ACC_STATIC
    Code:
      stack=6, locals=5, args_size=5
         0: getstatic     #22                 // Field org/scalactic/Bool$.MODULE$:Lorg/scalactic/Bool$;
         3: aload_0
         4: aload_1
         5: aload_2
         6: aload_3
         7: aload         4
         9: invokevirtual #49                 // Method org/scalactic/Bool$.isInstanceOfMacroBool:(Ljava/lang/Object;Ljava/lang/String;Ljava/lang/String;Lorg/scalactic/Bool;Lorg/scalactic/Prettifier;)Lorg/scalactic/Bool;
        12: areturn
      LocalVariableTable:
        Start  Length  Slot  Name   Signature
            0      13     0  left   Ljava/lang/Object;
            0      13     1 operator   Ljava/lang/String;
            0      13     2 className   Ljava/lang/String;
            0      13     3  bool   Lorg/scalactic/Bool;
            0      13     4 prettifier   Lorg/scalactic/Prettifier;
    MethodParameters:
      Name                           Flags
      left                           final
      operator                       final
      className                      final
      bool                           final
      prettifier                     final

  public static org.scalactic.Bool isInstanceOfMacroBool(java.lang.Object, java.lang.String, java.lang.String, boolean, org.scalactic.Prettifier);
    descriptor: (Ljava/lang/Object;Ljava/lang/String;Ljava/lang/String;ZLorg/scalactic/Prettifier;)Lorg/scalactic/Bool;
    flags: (0x0009) ACC_PUBLIC, ACC_STATIC
    Code:
      stack=6, locals=5, args_size=5
         0: getstatic     #22                 // Field org/scalactic/Bool$.MODULE$:Lorg/scalactic/Bool$;
         3: aload_0
         4: aload_1
         5: aload_2
         6: iload_3
         7: aload         4
         9: invokevirtual #52                 // Method org/scalactic/Bool$.isInstanceOfMacroBool:(Ljava/lang/Object;Ljava/lang/String;Ljava/lang/String;ZLorg/scalactic/Prettifier;)Lorg/scalactic/Bool;
        12: areturn
      LocalVariableTable:
        Start  Length  Slot  Name   Signature
            0      13     0  left   Ljava/lang/Object;
            0      13     1 operator   Ljava/lang/String;
            0      13     2 className   Ljava/lang/String;
            0      13     3 expression   Z
            0      13     4 prettifier   Lorg/scalactic/Prettifier;
    MethodParameters:
      Name                           Flags
      left                           final
      operator                       final
      className                      final
      expression                     final
      prettifier                     final

  public static org.scalactic.Bool unaryMacroBool(java.lang.Object, java.lang.String, org.scalactic.Bool, org.scalactic.Prettifier);
    descriptor: (Ljava/lang/Object;Ljava/lang/String;Lorg/scalactic/Bool;Lorg/scalactic/Prettifier;)Lorg/scalactic/Bool;
    flags: (0x0009) ACC_PUBLIC, ACC_STATIC
    Code:
      stack=5, locals=4, args_size=4
         0: getstatic     #22                 // Field org/scalactic/Bool$.MODULE$:Lorg/scalactic/Bool$;
         3: aload_0
         4: aload_1
         5: aload_2
         6: aload_3
         7: invokevirtual #56                 // Method org/scalactic/Bool$.unaryMacroBool:(Ljava/lang/Object;Ljava/lang/String;Lorg/scalactic/Bool;Lorg/scalactic/Prettifier;)Lorg/scalactic/Bool;
        10: areturn
      LocalVariableTable:
        Start  Length  Slot  Name   Signature
            0      11     0  left   Ljava/lang/Object;
            0      11     1 operator   Ljava/lang/String;
            0      11     2  bool   Lorg/scalactic/Bool;
            0      11     3 prettifier   Lorg/scalactic/Prettifier;
    MethodParameters:
      Name                           Flags
      left                           final
      operator                       final
      bool                           final
      prettifier                     final

  public static org.scalactic.Bool unaryMacroBool(java.lang.Object, java.lang.String, boolean, org.scalactic.Prettifier);
    descriptor: (Ljava/lang/Object;Ljava/lang/String;ZLorg/scalactic/Prettifier;)Lorg/scalactic/Bool;
    flags: (0x0009) ACC_PUBLIC, ACC_STATIC
    Code:
      stack=5, locals=4, args_size=4
         0: getstatic     #22                 // Field org/scalactic/Bool$.MODULE$:Lorg/scalactic/Bool$;
         3: aload_0
         4: aload_1
         5: iload_2
         6: aload_3
         7: invokevirtual #59                 // Method org/scalactic/Bool$.unaryMacroBool:(Ljava/lang/Object;Ljava/lang/String;ZLorg/scalactic/Prettifier;)Lorg/scalactic/Bool;
        10: areturn
      LocalVariableTable:
        Start  Length  Slot  Name   Signature
            0      11     0  left   Ljava/lang/Object;
            0      11     1 operator   Ljava/lang/String;
            0      11     2 expression   Z
            0      11     3 prettifier   Lorg/scalactic/Prettifier;
    MethodParameters:
      Name                           Flags
      left                           final
      operator                       final
      expression                     final
      prettifier                     final

  public static org.scalactic.Bool binaryMacroBool(java.lang.Object, java.lang.String, java.lang.Object, org.scalactic.Bool, org.scalactic.Prettifier);
    descriptor: (Ljava/lang/Object;Ljava/lang/String;Ljava/lang/Object;Lorg/scalactic/Bool;Lorg/scalactic/Prettifier;)Lorg/scalactic/Bool;
    flags: (0x0009) ACC_PUBLIC, ACC_STATIC
    Code:
      stack=6, locals=5, args_size=5
         0: getstatic     #22                 // Field org/scalactic/Bool$.MODULE$:Lorg/scalactic/Bool$;
         3: aload_0
         4: aload_1
         5: aload_2
         6: aload_3
         7: aload         4
         9: invokevirtual #63                 // Method org/scalactic/Bool$.binaryMacroBool:(Ljava/lang/Object;Ljava/lang/String;Ljava/lang/Object;Lorg/scalactic/Bool;Lorg/scalactic/Prettifier;)Lorg/scalactic/Bool;
        12: areturn
      LocalVariableTable:
        Start  Length  Slot  Name   Signature
            0      13     0  left   Ljava/lang/Object;
            0      13     1 operator   Ljava/lang/String;
            0      13     2 right   Ljava/lang/Object;
            0      13     3  bool   Lorg/scalactic/Bool;
            0      13     4 prettifier   Lorg/scalactic/Prettifier;
    MethodParameters:
      Name                           Flags
      left                           final
      operator                       final
      right                          final
      bool                           final
      prettifier                     final

  public static org.scalactic.Bool binaryMacroBool(java.lang.Object, java.lang.String, java.lang.Object, boolean, org.scalactic.Prettifier);
    descriptor: (Ljava/lang/Object;Ljava/lang/String;Ljava/lang/Object;ZLorg/scalactic/Prettifier;)Lorg/scalactic/Bool;
    flags: (0x0009) ACC_PUBLIC, ACC_STATIC
    Code:
      stack=6, locals=5, args_size=5
         0: getstatic     #22                 // Field org/scalactic/Bool$.MODULE$:Lorg/scalactic/Bool$;
         3: aload_0
         4: aload_1
         5: aload_2
         6: iload_3
         7: aload         4
         9: invokevirtual #66                 // Method org/scalactic/Bool$.binaryMacroBool:(Ljava/lang/Object;Ljava/lang/String;Ljava/lang/Object;ZLorg/scalactic/Prettifier;)Lorg/scalactic/Bool;
        12: areturn
      LocalVariableTable:
        Start  Length  Slot  Name   Signature
            0      13     0  left   Ljava/lang/Object;
            0      13     1 operator   Ljava/lang/String;
            0      13     2 right   Ljava/lang/Object;
            0      13     3 expression   Z
            0      13     4 prettifier   Lorg/scalactic/Prettifier;
    MethodParameters:
      Name                           Flags
      left                           final
      operator                       final
      right                          final
      expression                     final
      prettifier                     final

  public static org.scalactic.Bool simpleMacroBool(boolean, java.lang.String, org.scalactic.Prettifier);
    descriptor: (ZLjava/lang/String;Lorg/scalactic/Prettifier;)Lorg/scalactic/Bool;
    flags: (0x0009) ACC_PUBLIC, ACC_STATIC
    Code:
      stack=4, locals=3, args_size=3
         0: getstatic     #22                 // Field org/scalactic/Bool$.MODULE$:Lorg/scalactic/Bool$;
         3: iload_0
         4: aload_1
         5: aload_2
         6: invokevirtual #71                 // Method org/scalactic/Bool$.simpleMacroBool:(ZLjava/lang/String;Lorg/scalactic/Prettifier;)Lorg/scalactic/Bool;
         9: areturn
      LocalVariableTable:
        Start  Length  Slot  Name   Signature
            0      10     0 expression   Z
            0      10     1 expressionText   Ljava/lang/String;
            0      10     2 prettifier   Lorg/scalactic/Prettifier;
    MethodParameters:
      Name                           Flags
      expression                     final
      expressionText                 final
      prettifier                     final

  public static org.scalactic.Bool notBool(org.scalactic.Bool, org.scalactic.Prettifier);
    descriptor: (Lorg/scalactic/Bool;Lorg/scalactic/Prettifier;)Lorg/scalactic/Bool;
    flags: (0x0009) ACC_PUBLIC, ACC_STATIC
    Code:
      stack=3, locals=2, args_size=2
         0: getstatic     #22                 // Field org/scalactic/Bool$.MODULE$:Lorg/scalactic/Bool$;
         3: aload_0
         4: aload_1
         5: invokevirtual #75                 // Method org/scalactic/Bool$.notBool:(Lorg/scalactic/Bool;Lorg/scalactic/Prettifier;)Lorg/scalactic/Bool;
         8: areturn
      LocalVariableTable:
        Start  Length  Slot  Name   Signature
            0       9     0  bool   Lorg/scalactic/Bool;
            0       9     1 prettifier   Lorg/scalactic/Prettifier;
    MethodParameters:
      Name                           Flags
      bool                           final
      prettifier                     final

  public abstract org.scalactic.Prettifier prettifier();
    descriptor: ()Lorg/scalactic/Prettifier;
    flags: (0x0401) ACC_PUBLIC, ACC_ABSTRACT

  private java.lang.String makeString(java.lang.String, java.lang.Object[]);
    descriptor: (Ljava/lang/String;[Ljava/lang/Object;)Ljava/lang/String;
    flags: (0x0002) ACC_PRIVATE
    Code:
      stack=6, locals=3, args_size=3
         0: getstatic     #85                 // Field org/scalactic/Resources$.MODULE$:Lorg/scalactic/Resources$;
         3: aload_1
         4: getstatic     #90                 // Field scala/collection/ArrayOps$.MODULE$:Lscala/collection/ArrayOps$;
         7: getstatic     #95                 // Field scala/Predef$.MODULE$:Lscala/Predef$;
        10: aload_2
        11: invokevirtual #99                 // Method scala/Predef$.genericArrayOps:(Ljava/lang/Object;)Ljava/lang/Object;
        14: aload_0
        15: invokedynamic #120,  0            // InvokeDynamic #0:apply:(Lorg/scalactic/Bool;)Lscala/Function1;
        20: getstatic     #125                // Field scala/reflect/ClassTag$.MODULE$:Lscala/reflect/ClassTag$;
        23: invokevirtual #129                // Method scala/reflect/ClassTag$.Any:()Lscala/reflect/ClassTag;
        26: invokevirtual #133                // Method scala/collection/ArrayOps$.map$extension:(Ljava/lang/Object;Lscala/Function1;Lscala/reflect/ClassTag;)Ljava/lang/Object;
        29: checkcast     #135                // class "[Ljava/lang/Object;"
        32: invokevirtual #138                // Method org/scalactic/Resources$.formatString:(Ljava/lang/String;[Ljava/lang/Object;)Ljava/lang/String;
        35: areturn
      LineNumberTable:
        line 35: 0
      LocalVariableTable:
        Start  Length  Slot  Name   Signature
            0      36     0  this   Lorg/scalactic/Bool;
            0      36     1   raw   Ljava/lang/String;
            0      36     2  args   [Ljava/lang/Object;
    MethodParameters:
      Name                           Flags
      raw                            final
      args                           final

  public static scala.collection.immutable.IndexedSeq analysis$(org.scalactic.Bool);
    descriptor: (Lorg/scalactic/Bool;)Lscala/collection/immutable/IndexedSeq;
    flags: (0x1009) ACC_PUBLIC, ACC_STATIC, ACC_SYNTHETIC
    Code:
      stack=1, locals=1, args_size=1
         0: aload_0
         1: invokespecial #146                // InterfaceMethod analysis:()Lscala/collection/immutable/IndexedSeq;
         4: areturn
      LineNumberTable:
        line 37: 0
      LocalVariableTable:
        Start  Length  Slot  Name   Signature
            0       5     0 $this   Lorg/scalactic/Bool;
    MethodParameters:
      Name                           Flags
      $this                          final synthetic

  public default scala.collection.immutable.IndexedSeq<java.lang.String> analysis();
    descriptor: ()Lscala/collection/immutable/IndexedSeq;
    flags: (0x0001) ACC_PUBLIC
    Code:
      stack=1, locals=1, args_size=1
         0: getstatic     #152                // Field scala/package$.MODULE$:Lscala/package$;
         3: invokevirtual #156                // Method scala/package$.Vector:()Lscala/collection/immutable/Vector$;
         6: invokevirtual #162                // Method scala/collection/immutable/Vector$.empty:()Lscala/collection/immutable/Vector;
         9: areturn
      LineNumberTable:
        line 37: 0
      LocalVariableTable:
        Start  Length  Slot  Name   Signature
            0      10     0  this   Lorg/scalactic/Bool;
    Signature: #147                         // ()Lscala/collection/immutable/IndexedSeq<Ljava/lang/String;>;

  public static java.lang.String failureMessage$(org.scalactic.Bool);
    descriptor: (Lorg/scalactic/Bool;)Ljava/lang/String;
    flags: (0x1009) ACC_PUBLIC, ACC_STATIC, ACC_SYNTHETIC
    Code:
      stack=1, locals=1, args_size=1
         0: aload_0
         1: invokespecial #168                // InterfaceMethod failureMessage:()Ljava/lang/String;
         4: areturn
      LineNumberTable:
        line 43: 0
      LocalVariableTable:
        Start  Length  Slot  Name   Signature
            0       5     0 $this   Lorg/scalactic/Bool;
    MethodParameters:
      Name                           Flags
      $this                          final synthetic

  public default java.lang.String failureMessage();
    descriptor: ()Ljava/lang/String;
    flags: (0x0001) ACC_PUBLIC
    Code:
      stack=4, locals=1, args_size=1
         0: aload_0
         1: invokeinterface #171,  1          // InterfaceMethod failureMessageArgs:()Lscala/collection/immutable/IndexedSeq;
         6: invokeinterface #177,  1          // InterfaceMethod scala/collection/immutable/IndexedSeq.isEmpty:()Z
        11: ifeq          23
        14: aload_0
        15: invokeinterface #180,  1          // InterfaceMethod rawFailureMessage:()Ljava/lang/String;
        20: goto          53
        23: aload_0
        24: aload_0
        25: invokeinterface #180,  1          // InterfaceMethod rawFailureMessage:()Ljava/lang/String;
        30: aload_0
        31: invokeinterface #171,  1          // InterfaceMethod failureMessageArgs:()Lscala/collection/immutable/IndexedSeq;
        36: getstatic     #125                // Field scala/reflect/ClassTag$.MODULE$:Lscala/reflect/ClassTag$;
        39: invokevirtual #129                // Method scala/reflect/ClassTag$.Any:()Lscala/reflect/ClassTag;
        42: invokeinterface #184,  2          // InterfaceMethod scala/collection/immutable/IndexedSeq.toArray:(Lscala/reflect/ClassTag;)Ljava/lang/Object;
        47: checkcast     #135                // class "[Ljava/lang/Object;"
        50: invokespecial #186                // InterfaceMethod makeString:(Ljava/lang/String;[Ljava/lang/Object;)Ljava/lang/String;
        53: areturn
      StackMapTable: number_of_entries = 2
        frame_type = 23 /* same */
        frame_type = 93 /* same_locals_1_stack_item */
          stack = [ class java/lang/String ]
      LineNumberTable:
        line 44: 0
      LocalVariableTable:
        Start  Length  Slot  Name   Signature
            0      54     0  this   Lorg/scalactic/Bool;

  public static java.lang.String negatedFailureMessage$(org.scalactic.Bool);
    descriptor: (Lorg/scalactic/Bool;)Ljava/lang/String;
    flags: (0x1009) ACC_PUBLIC, ACC_STATIC, ACC_SYNTHETIC
    Code:
      stack=1, locals=1, args_size=1
         0: aload_0
         1: invokespecial #192                // InterfaceMethod negatedFailureMessage:()Ljava/lang/String;
         4: areturn
      LineNumberTable:
        line 50: 0
      LocalVariableTable:
        Start  Length  Slot  Name   Signature
            0       5     0 $this   Lorg/scalactic/Bool;
    MethodParameters:
      Name                           Flags
      $this                          final synthetic

  public default java.lang.String negatedFailureMessage();
    descriptor: ()Ljava/lang/String;
    flags: (0x0001) ACC_PUBLIC
    Code:
      stack=4, locals=1, args_size=1
         0: aload_0
         1: invokeinterface #195,  1          // InterfaceMethod negatedFailureMessageArgs:()Lscala/collection/immutable/IndexedSeq;
         6: invokeinterface #177,  1          // InterfaceMethod scala/collection/immutable/IndexedSeq.isEmpty:()Z
        11: ifeq          23
        14: aload_0
        15: invokeinterface #198,  1          // InterfaceMethod rawNegatedFailureMessage:()Ljava/lang/String;
        20: goto          53
        23: aload_0
        24: aload_0
        25: invokeinterface #198,  1          // InterfaceMethod rawNegatedFailureMessage:()Ljava/lang/String;
        30: aload_0
        31: invokeinterface #195,  1          // InterfaceMethod negatedFailureMessageArgs:()Lscala/collection/immutable/IndexedSeq;
        36: getstatic     #125                // Field scala/reflect/ClassTag$.MODULE$:Lscala/reflect/ClassTag$;
        39: invokevirtual #129                // Method scala/reflect/ClassTag$.Any:()Lscala/reflect/ClassTag;
        42: invokeinterface #184,  2          // InterfaceMethod scala/collection/immutable/IndexedSeq.toArray:(Lscala/reflect/ClassTag;)Ljava/lang/Object;
        47: checkcast     #135                // class "[Ljava/lang/Object;"
        50: invokespecial #186                // InterfaceMethod makeString:(Ljava/lang/String;[Ljava/lang/Object;)Ljava/lang/String;
        53: areturn
      StackMapTable: number_of_entries = 2
        frame_type = 23 /* same */
        frame_type = 93 /* same_locals_1_stack_item */
          stack = [ class java/lang/String ]
      LineNumberTable:
        line 51: 0
      LocalVariableTable:
        Start  Length  Slot  Name   Signature
            0      54     0  this   Lorg/scalactic/Bool;

  public static java.lang.String midSentenceFailureMessage$(org.scalactic.Bool);
    descriptor: (Lorg/scalactic/Bool;)Ljava/lang/String;
    flags: (0x1009) ACC_PUBLIC, ACC_STATIC, ACC_SYNTHETIC
    Code:
      stack=1, locals=1, args_size=1
         0: aload_0
         1: invokespecial #202                // InterfaceMethod midSentenceFailureMessage:()Ljava/lang/String;
         4: areturn
      LineNumberTable:
        line 57: 0
      LocalVariableTable:
        Start  Length  Slot  Name   Signature
            0       5     0 $this   Lorg/scalactic/Bool;
    MethodParameters:
      Name                           Flags
      $this                          final synthetic

  public default java.lang.String midSentenceFailureMessage();
    descriptor: ()Ljava/lang/String;
    flags: (0x0001) ACC_PUBLIC
    Code:
      stack=4, locals=1, args_size=1
         0: aload_0
         1: invokeinterface #205,  1          // InterfaceMethod midSentenceFailureMessageArgs:()Lscala/collection/immutable/IndexedSeq;
         6: invokeinterface #177,  1          // InterfaceMethod scala/collection/immutable/IndexedSeq.isEmpty:()Z
        11: ifeq          23
        14: aload_0
        15: invokeinterface #208,  1          // InterfaceMethod rawMidSentenceFailureMessage:()Ljava/lang/String;
        20: goto          53
        23: aload_0
        24: aload_0
        25: invokeinterface #208,  1          // InterfaceMethod rawMidSentenceFailureMessage:()Ljava/lang/String;
        30: aload_0
        31: invokeinterface #205,  1          // InterfaceMethod midSentenceFailureMessageArgs:()Lscala/collection/immutable/IndexedSeq;
        36: getstatic     #125                // Field scala/reflect/ClassTag$.MODULE$:Lscala/reflect/ClassTag$;
        39: invokevirtual #129                // Method scala/reflect/ClassTag$.Any:()Lscala/reflect/ClassTag;
        42: invokeinterface #184,  2          // InterfaceMethod scala/collection/immutable/IndexedSeq.toArray:(Lscala/reflect/ClassTag;)Ljava/lang/Object;
        47: checkcast     #135                // class "[Ljava/lang/Object;"
        50: invokespecial #186                // InterfaceMethod makeString:(Ljava/lang/String;[Ljava/lang/Object;)Ljava/lang/String;
        53: areturn
      StackMapTable: number_of_entries = 2
        frame_type = 23 /* same */
        frame_type = 93 /* same_locals_1_stack_item */
          stack = [ class java/lang/String ]
      LineNumberTable:
        line 58: 0
      LocalVariableTable:
        Start  Length  Slot  Name   Signature
            0      54     0  this   Lorg/scalactic/Bool;

  public static java.lang.String midSentenceNegatedFailureMessage$(org.scalactic.Bool);
    descriptor: (Lorg/scalactic/Bool;)Ljava/lang/String;
    flags: (0x1009) ACC_PUBLIC, ACC_STATIC, ACC_SYNTHETIC
    Code:
      stack=1, locals=1, args_size=1
         0: aload_0
         1: invokespecial #212                // InterfaceMethod midSentenceNegatedFailureMessage:()Ljava/lang/String;
         4: areturn
      LineNumberTable:
        line 64: 0
      LocalVariableTable:
        Start  Length  Slot  Name   Signature
            0       5     0 $this   Lorg/scalactic/Bool;
    MethodParameters:
      Name                           Flags
      $this                          final synthetic

  public default java.lang.String midSentenceNegatedFailureMessage();
    descriptor: ()Ljava/lang/String;
    flags: (0x0001) ACC_PUBLIC
    Code:
      stack=4, locals=1, args_size=1
         0: aload_0
         1: invokeinterface #215,  1          // InterfaceMethod midSentenceNegatedFailureMessageArgs:()Lscala/collection/immutable/IndexedSeq;
         6: invokeinterface #177,  1          // InterfaceMethod scala/collection/immutable/IndexedSeq.isEmpty:()Z
        11: ifeq          23
        14: aload_0
        15: invokeinterface #218,  1          // InterfaceMethod rawMidSentenceNegatedFailureMessage:()Ljava/lang/String;
        20: goto          53
        23: aload_0
        24: aload_0
        25: invokeinterface #218,  1          // InterfaceMethod rawMidSentenceNegatedFailureMessage:()Ljava/lang/String;
        30: aload_0
        31: invokeinterface #215,  1          // InterfaceMethod midSentenceNegatedFailureMessageArgs:()Lscala/collection/immutable/IndexedSeq;
        36: getstatic     #125                // Field scala/reflect/ClassTag$.MODULE$:Lscala/reflect/ClassTag$;
        39: invokevirtual #129                // Method scala/reflect/ClassTag$.Any:()Lscala/reflect/ClassTag;
        42: invokeinterface #184,  2          // InterfaceMethod scala/collection/immutable/IndexedSeq.toArray:(Lscala/reflect/ClassTag;)Ljava/lang/Object;
        47: checkcast     #135                // class "[Ljava/lang/Object;"
        50: invokespecial #186                // InterfaceMethod makeString:(Ljava/lang/String;[Ljava/lang/Object;)Ljava/lang/String;
        53: areturn
      StackMapTable: number_of_entries = 2
        frame_type = 23 /* same */
        frame_type = 93 /* same_locals_1_stack_item */
          stack = [ class java/lang/String ]
      LineNumberTable:
        line 65: 0
      LocalVariableTable:
        Start  Length  Slot  Name   Signature
            0      54     0  this   Lorg/scalactic/Bool;

  public abstract boolean value();
    descriptor: ()Z
    flags: (0x0401) ACC_PUBLIC, ACC_ABSTRACT

  public abstract java.lang.String rawFailureMessage();
    descriptor: ()Ljava/lang/String;
    flags: (0x0401) ACC_PUBLIC, ACC_ABSTRACT

  public abstract java.lang.String rawNegatedFailureMessage();
    descriptor: ()Ljava/lang/String;
    flags: (0x0401) ACC_PUBLIC, ACC_ABSTRACT

  public abstract java.lang.String rawMidSentenceFailureMessage();
    descriptor: ()Ljava/lang/String;
    flags: (0x0401) ACC_PUBLIC, ACC_ABSTRACT

  public abstract java.lang.String rawMidSentenceNegatedFailureMessage();
    descriptor: ()Ljava/lang/String;
    flags: (0x0401) ACC_PUBLIC, ACC_ABSTRACT

  public abstract scala.collection.immutable.IndexedSeq<java.lang.Object> failureMessageArgs();
    descriptor: ()Lscala/collection/immutable/IndexedSeq;
    flags: (0x0401) ACC_PUBLIC, ACC_ABSTRACT
    Signature: #220                         // ()Lscala/collection/immutable/IndexedSeq<Ljava/lang/Object;>;

  public abstract scala.collection.immutable.IndexedSeq<java.lang.Object> negatedFailureMessageArgs();
    descriptor: ()Lscala/collection/immutable/IndexedSeq;
    flags: (0x0401) ACC_PUBLIC, ACC_ABSTRACT
    Signature: #220                         // ()Lscala/collection/immutable/IndexedSeq<Ljava/lang/Object;>;

  public abstract scala.collection.immutable.IndexedSeq<java.lang.Object> midSentenceFailureMessageArgs();
    descriptor: ()Lscala/collection/immutable/IndexedSeq;
    flags: (0x0401) ACC_PUBLIC, ACC_ABSTRACT
    Signature: #220                         // ()Lscala/collection/immutable/IndexedSeq<Ljava/lang/Object;>;

  public abstract scala.collection.immutable.IndexedSeq<java.lang.Object> midSentenceNegatedFailureMessageArgs();
    descriptor: ()Lscala/collection/immutable/IndexedSeq;
    flags: (0x0401) ACC_PUBLIC, ACC_ABSTRACT
    Signature: #220                         // ()Lscala/collection/immutable/IndexedSeq<Ljava/lang/Object;>;

  public static org.scalactic.Bool $amp$amp$(org.scalactic.Bool, scala.Function0);
    descriptor: (Lorg/scalactic/Bool;Lscala/Function0;)Lorg/scalactic/Bool;
    flags: (0x1009) ACC_PUBLIC, ACC_STATIC, ACC_SYNTHETIC
    Code:
      stack=2, locals=2, args_size=2
         0: aload_0
         1: aload_1
         2: invokespecial #226                // InterfaceMethod $amp$amp:(Lscala/Function0;)Lorg/scalactic/Bool;
         5: areturn
      LineNumberTable:
        line 118: 0
      LocalVariableTable:
        Start  Length  Slot  Name   Signature
            0       6     0 $this   Lorg/scalactic/Bool;
            0       6     1  bool   Lscala/Function0;
    MethodParameters:
      Name                           Flags
      $this                          final synthetic
      bool                           final

  public default org.scalactic.Bool $amp$amp(scala.Function0<org.scalactic.Bool>);
    descriptor: (Lscala/Function0;)Lorg/scalactic/Bool;
    flags: (0x0001) ACC_PUBLIC
    Code:
      stack=5, locals=2, args_size=2
         0: aload_0
         1: invokeinterface #230,  1          // InterfaceMethod value:()Z
         6: ifeq          27
         9: new           #232                // class org/scalactic/AndBool
        12: dup
        13: aload_0
        14: aload_1
        15: aload_0
        16: invokeinterface #234,  1          // InterfaceMethod prettifier:()Lorg/scalactic/Prettifier;
        21: invokespecial #238                // Method org/scalactic/AndBool."<init>":(Lorg/scalactic/Bool;Lscala/Function0;Lorg/scalactic/Prettifier;)V
        24: goto          28
        27: aload_0
        28: areturn
      StackMapTable: number_of_entries = 2
        frame_type = 27 /* same */
        frame_type = 64 /* same_locals_1_stack_item */
          stack = [ class org/scalactic/Bool ]
      LineNumberTable:
        line 119: 0
        line 120: 9
        line 122: 27
      LocalVariableTable:
        Start  Length  Slot  Name   Signature
            0      29     0  this   Lorg/scalactic/Bool;
            0      29     1  bool   Lscala/Function0;
    Signature: #228                         // (Lscala/Function0<Lorg/scalactic/Bool;>;)Lorg/scalactic/Bool;
    MethodParameters:
      Name                           Flags
      bool                           final

  public static org.scalactic.Bool $amp$(org.scalactic.Bool, scala.Function0);
    descriptor: (Lorg/scalactic/Bool;Lscala/Function0;)Lorg/scalactic/Bool;
    flags: (0x1009) ACC_PUBLIC, ACC_STATIC, ACC_SYNTHETIC
    Code:
      stack=2, locals=2, args_size=2
         0: aload_0
         1: aload_1
         2: invokespecial #242                // InterfaceMethod $amp:(Lscala/Function0;)Lorg/scalactic/Bool;
         5: areturn
      LineNumberTable:
        line 130: 0
      LocalVariableTable:
        Start  Length  Slot  Name   Signature
            0       6     0 $this   Lorg/scalactic/Bool;
            0       6     1  bool   Lscala/Function0;
    MethodParameters:
      Name                           Flags
      $this                          final synthetic
      bool                           final

  public default org.scalactic.Bool $amp(scala.Function0<org.scalactic.Bool>);
    descriptor: (Lscala/Function0;)Lorg/scalactic/Bool;
    flags: (0x0001) ACC_PUBLIC
    Code:
      stack=2, locals=2, args_size=2
         0: aload_0
         1: aload_1
         2: invokeinterface #226,  2          // InterfaceMethod $amp$amp:(Lscala/Function0;)Lorg/scalactic/Bool;
         7: areturn
      LineNumberTable:
        line 130: 0
      LocalVariableTable:
        Start  Length  Slot  Name   Signature
            0       8     0  this   Lorg/scalactic/Bool;
            0       8     1  bool   Lscala/Function0;
    Signature: #228                         // (Lscala/Function0<Lorg/scalactic/Bool;>;)Lorg/scalactic/Bool;
    MethodParameters:
      Name                           Flags
      bool                           final

  public static org.scalactic.Bool $bar$bar$(org.scalactic.Bool, scala.Function0);
    descriptor: (Lorg/scalactic/Bool;Lscala/Function0;)Lorg/scalactic/Bool;
    flags: (0x1009) ACC_PUBLIC, ACC_STATIC, ACC_SYNTHETIC
    Code:
      stack=2, locals=2, args_size=2
         0: aload_0
         1: aload_1
         2: invokespecial #246                // InterfaceMethod $bar$bar:(Lscala/Function0;)Lorg/scalactic/Bool;
         5: areturn
      LineNumberTable:
        line 138: 0
      LocalVariableTable:
        Start  Length  Slot  Name   Signature
            0       6     0 $this   Lorg/scalactic/Bool;
            0       6     1  bool   Lscala/Function0;
    MethodParameters:
      Name                           Flags
      $this                          final synthetic
      bool                           final

  public default org.scalactic.Bool $bar$bar(scala.Function0<org.scalactic.Bool>);
    descriptor: (Lscala/Function0;)Lorg/scalactic/Bool;
    flags: (0x0001) ACC_PUBLIC
    Code:
      stack=5, locals=2, args_size=2
         0: new           #248                // class org/scalactic/OrBool
         3: dup
         4: aload_0
         5: aload_1
         6: aload_0
         7: invokeinterface #234,  1          // InterfaceMethod prettifier:()Lorg/scalactic/Prettifier;
        12: invokespecial #249                // Method org/scalactic/OrBool."<init>":(Lorg/scalactic/Bool;Lscala/Function0;Lorg/scalactic/Prettifier;)V
        15: areturn
      LineNumberTable:
        line 138: 0
      LocalVariableTable:
        Start  Length  Slot  Name   Signature
            0      16     0  this   Lorg/scalactic/Bool;
            0      16     1  bool   Lscala/Function0;
    Signature: #228                         // (Lscala/Function0<Lorg/scalactic/Bool;>;)Lorg/scalactic/Bool;
    MethodParameters:
      Name                           Flags
      bool                           final

  public static org.scalactic.Bool $bar$(org.scalactic.Bool, scala.Function0);
    descriptor: (Lorg/scalactic/Bool;Lscala/Function0;)Lorg/scalactic/Bool;
    flags: (0x1009) ACC_PUBLIC, ACC_STATIC, ACC_SYNTHETIC
    Code:
      stack=2, locals=2, args_size=2
         0: aload_0
         1: aload_1
         2: invokespecial #253                // InterfaceMethod $bar:(Lscala/Function0;)Lorg/scalactic/Bool;
         5: areturn
      LineNumberTable:
        line 146: 0
      LocalVariableTable:
        Start  Length  Slot  Name   Signature
            0       6     0 $this   Lorg/scalactic/Bool;
            0       6     1  bool   Lscala/Function0;
    MethodParameters:
      Name                           Flags
      $this                          final synthetic
      bool                           final

  public default org.scalactic.Bool $bar(scala.Function0<org.scalactic.Bool>);
    descriptor: (Lscala/Function0;)Lorg/scalactic/Bool;
    flags: (0x0001) ACC_PUBLIC
    Code:
      stack=2, locals=2, args_size=2
         0: aload_0
         1: aload_1
         2: invokeinterface #246,  2          // InterfaceMethod $bar$bar:(Lscala/Function0;)Lorg/scalactic/Bool;
         7: areturn
      LineNumberTable:
        line 146: 0
      LocalVariableTable:
        Start  Length  Slot  Name   Signature
            0       8     0  this   Lorg/scalactic/Bool;
            0       8     1  bool   Lscala/Function0;
    Signature: #228                         // (Lscala/Function0<Lorg/scalactic/Bool;>;)Lorg/scalactic/Bool;
    MethodParameters:
      Name                           Flags
      bool                           final

  public static org.scalactic.Bool unary_$bang$(org.scalactic.Bool);
    descriptor: (Lorg/scalactic/Bool;)Lorg/scalactic/Bool;
    flags: (0x1009) ACC_PUBLIC, ACC_STATIC, ACC_SYNTHETIC
    Code:
      stack=1, locals=1, args_size=1
         0: aload_0
         1: invokespecial #259                // InterfaceMethod unary_$bang:()Lorg/scalactic/Bool;
         4: areturn
      LineNumberTable:
        line 153: 0
      LocalVariableTable:
        Start  Length  Slot  Name   Signature
            0       5     0 $this   Lorg/scalactic/Bool;
    MethodParameters:
      Name                           Flags
      $this                          final synthetic

  public default org.scalactic.Bool unary_$bang();
    descriptor: ()Lorg/scalactic/Bool;
    flags: (0x0001) ACC_PUBLIC
    Code:
      stack=4, locals=1, args_size=1
         0: new           #261                // class org/scalactic/NotBool
         3: dup
         4: aload_0
         5: aload_0
         6: invokeinterface #234,  1          // InterfaceMethod prettifier:()Lorg/scalactic/Prettifier;
        11: invokespecial #264                // Method org/scalactic/NotBool."<init>":(Lorg/scalactic/Bool;Lorg/scalactic/Prettifier;)V
        14: areturn
      LineNumberTable:
        line 153: 0
      LocalVariableTable:
        Start  Length  Slot  Name   Signature
            0      15     0  this   Lorg/scalactic/Bool;

  public static java.lang.String $anonfun$makeString$1(org.scalactic.Bool, java.lang.Object);
    descriptor: (Lorg/scalactic/Bool;Ljava/lang/Object;)Ljava/lang/String;
    flags: (0x1009) ACC_PUBLIC, ACC_STATIC, ACC_SYNTHETIC
    Code:
      stack=2, locals=2, args_size=2
         0: aload_0
         1: invokeinterface #234,  1          // InterfaceMethod prettifier:()Lorg/scalactic/Prettifier;
         6: aload_1
         7: invokeinterface #269,  2          // InterfaceMethod org/scalactic/Prettifier.apply:(Ljava/lang/Object;)Ljava/lang/String;
        12: areturn
      LineNumberTable:
        line 35: 0
      LocalVariableTable:
        Start  Length  Slot  Name   Signature
            0      13     0 $this   Lorg/scalactic/Bool;
            0      13     1     o   Ljava/lang/Object;
    MethodParameters:
      Name                           Flags
      $this                          final synthetic
      o                              final

  public static void $init$(org.scalactic.Bool);
    descriptor: (Lorg/scalactic/Bool;)V
    flags: (0x0009) ACC_PUBLIC, ACC_STATIC
    Code:
      stack=0, locals=1, args_size=1
         0: return
      LineNumberTable:
        line 30: 0
      LocalVariableTable:
        Start  Length  Slot  Name   Signature
            0       1     0 $this   Lorg/scalactic/Bool;
    MethodParameters:
      Name                           Flags
      $this                          final synthetic

  private static java.lang.Object $deserializeLambda$(java.lang.invoke.SerializedLambda);
    descriptor: (Ljava/lang/invoke/SerializedLambda;)Ljava/lang/Object;
    flags: (0x100a) ACC_PRIVATE, ACC_STATIC, ACC_SYNTHETIC
    Code:
      stack=1, locals=1, args_size=1
         0: aload_0
         1: invokedynamic #283,  0            // InvokeDynamic #1:lambdaDeserialize:(Ljava/lang/invoke/SerializedLambda;)Ljava/lang/Object;
         6: areturn
}
InnerClasses:
  public static final #13= #10 of #12;    // Lookup=class java/lang/invoke/MethodHandles$Lookup of class java/lang/invoke/MethodHandles
SourceFile: "Bool.scala"
RuntimeVisibleAnnotations:
  0: #6(#7=s#8)
    scala.reflect.ScalaSignature(
      bytes="\u0006\u0005\u0005=faB\u0013\'!\u0003\r\ta\u000b\u0005\u0006e\u0001!\ta\r\u0005\bo\u0001\u0011\rQ\"\u00019\u0011\u0015i\u0004\u0001\"\u0003?\u0011!!\u0006\u0001#b\u0001\n\u0003)\u0006\"\u00020\u0001\t\u0003y\u0006\"\u00021\u0001\t\u0003y\u0006\"B1\u0001\t\u0003y\u0006\"\u00022\u0001\t\u0003y\u0006\"B2\u0001\r\u0003!\u0007\"\u00025\u0001\r\u0003y\u0006\"B5\u0001\r\u0003y\u0006\"\u00026\u0001\r\u0003y\u0006\"B6\u0001\r\u0003y\u0006\"\u00027\u0001\r\u0003i\u0007\"\u0002<\u0001\r\u0003i\u0007\"B<\u0001\r\u0003i\u0007\"\u0002=\u0001\r\u0003i\u0007\"B=\u0001\t\u0003Q\bbBA\u0002\u0001\u0011\u0005\u0011Q\u0001\u0005\b\u0003\u0013\u0001A\u0011AA\u0006\u0011\u001d\ty\u0001\u0001C\u0001\u0003#Aq!!\u0006\u0001\t\u0003\t9bB\u0004\u0002\u001a\u0019B\t!a\u0007\u0007\r\u00152\u0003\u0012AA\u000f\u0011\u001d\ty\u0002\u0007C\u0001\u0003CAq!a\t\u0019\t\u0003\t)\u0003C\u0004\u0002,a!\t!!\f\t\u000f\u0005e\u0002\u0004\"\u0001\u0002<!9\u0011\u0011\b\r\u0005\u0002\u00055\u0003bBA-1\u0011\u0005\u00111\f\u0005\b\u00033BB\u0011AA3\u0011\u001d\ty\u0007\u0007C\u0001\u0003cBq!a\u001c\u0019\t\u0003\ty\bC\u0004\u0002\fb!\t!!$\t\u000f\u0005u\u0005\u0004\"\u0001\u0002 \"9\u0011\u0011\u0016\r\u0005\u0002\u0005-&\u0001\u0002\"p_2T!a\n\u0015\u0002\u0013M\u001c\u0017\r\\1di&\u001c\'\"A\u0015\u0002\u0007=\u0014xm\u0001\u0001\u0014\u0005\u0001a\u0003CA\u00171\u001b\u0005q#\"A\u0018\u0002\u000bM\u001c\u0017\r\\1\n\u0005Er#AB!osJ+g-\u0001\u0004%S:LG\u000f\n\u000b\u0002iA\u0011Q&N\u0005\u0003m9\u0012A!\u00168ji\u0006Q\u0001O]3ui&4\u0017.\u001a:\u0016\u0003e\u0002\"AO\u001e\u000e\u0003\u0019J!\u0001\u0010\u0014\u0003\u0015A\u0013X\r\u001e;jM&,\'/\u0001\u0006nC.,7\u000b\u001e:j]\u001e$2a\u0010&M!\t\u0001uI\u0004\u0002B\u000bB\u0011!IL\u0007\u0002\u0007*\u0011AIK\u0001\u0007yI|w\u000e\u001e \n\u0005\u0019s\u0013A\u0002)sK\u0012,g-\u0003\u0002I\u0013\n11\u000b\u001e:j]\u001eT!A\u0012\u0018\t\u000b-\u001b\u0001\u0019A \u0002\u0007I\fw\u000fC\u0003N\u0007\u0001\u0007a*\u0001\u0003be\u001e\u001c\bcA\u0017P#&\u0011\u0001K\f\u0002\u0006\u0003J\u0014\u0018-\u001f\t\u0003[IK!a\u0015\u0018\u0003\u0007\u0005s\u00170\u0001\u0005b]\u0006d\u0017p]5t+\u00051\u0006cA,]\u007f5\t\u0001L\u0003\u0002Z5\u0006I\u0011.\\7vi\u0006\u0014G.\u001a\u0006\u00037:\n!bY8mY\u0016\u001cG/[8o\u0013\ti\u0006L\u0001\u0006J]\u0012,\u00070\u001a3TKF\faBZ1jYV\u0014X-T3tg\u0006<W-F\u0001@\u0003UqWmZ1uK\u00124\u0015-\u001b7ve\u0016lUm]:bO\u0016\f\u0011$\\5e\'\u0016tG/\u001a8dK\u001a\u000b\u0017\u000e\\;sK6+7o]1hK\u0006\u0001S.\u001b3TK:$XM\\2f\u001d\u0016<\u0017\r^3e\r\u0006LG.\u001e:f\u001b\u0016\u001c8/Y4f\u0003\u00151\u0018\r\\;f+\u0005)\u0007CA\u0017g\u0013\t9gFA\u0004C_>dW-\u00198\u0002#I\fwOR1jYV\u0014X-T3tg\u0006<W-\u0001\rsC^tUmZ1uK\u00124\u0015-\u001b7ve\u0016lUm]:bO\u0016\fAD]1x\u001b&$7+\u001a8uK:\u001cWMR1jYV\u0014X-T3tg\u0006<W-A\u0012sC^l\u0015\u000eZ*f]R,gnY3OK\u001e\fG/\u001a3GC&dWO]3NKN\u001c\u0018mZ3\u0002%\u0019\f\u0017\u000e\\;sK6+7o]1hK\u0006\u0013xm]\u000b\u0002]B\u0019q\u000e^)\u000f\u0005A\u0014hB\u0001\"r\u0013\u0005y\u0013BA:/\u0003\u001d\u0001\u0018mY6bO\u0016L!!X;\u000b\u0005Mt\u0013!\u00078fO\u0006$X\r\u001a$bS2,(/Z\'fgN\fw-Z!sON\fQ$\\5e\'\u0016tG/\u001a8dK\u001a\u000b\u0017\u000e\\;sK6+7o]1hK\u0006\u0013xm]\u0001%[&$7+\u001a8uK:\u001cWMT3hCR,GMR1jYV\u0014X-T3tg\u0006<W-\u0011:hg\u0006AA%Y7qI\u0005l\u0007\u000f\u0006\u0002|yB\u0011!\b\u0001\u0005\u0007{J!\t\u0019\u0001@\u0002\t\t|w\u000e\u001c\t\u0004[}\\\u0018bAA\u0001]\tAAHY=oC6,g(\u0001\u0003%C6\u0004HcA>\u0002\b!1Qp\u0005CA\u0002y\f\u0001\u0002\n2be\u0012\u0012\u0017M\u001d\u000b\u0004w\u00065\u0001BB?\u0015\t\u0003\u0007a0\u0001\u0003%E\u0006\u0014HcA>\u0002\u0014!1Q0\u0006CA\u0002y\f1\"\u001e8bef|FEY1oOV\t10\u0001\u0003C_>d\u0007C\u0001\u001e\u0019\'\tAB&\u0001\u0004=S:LGO\u0010\u000b\u0003\u00037\tqA\\8u\u0005>|G\u000eF\u0003|\u0003O\tI\u0003C\u0003~5\u0001\u00071\u0010C\u000385\u0001\u0007\u0011(A\btS6\u0004H.Z\'bGJ|\'i\\8m)\u001dY\u0018qFA\u001a\u0003oAa!!\r\u001c\u0001\u0004)\u0017AC3yaJ,7o]5p]\"1\u0011QG\u000eA\u0002}\na\"\u001a=qe\u0016\u001c8/[8o)\u0016DH\u000fC\u000387\u0001\u0007\u0011(A\bcS:\f\'/_\'bGJ|\'i\\8m)-Y\u0018QHA!\u0003\u000b\nI%a\u0013\t\r\u0005}B\u00041\u0001R\u0003\u0011aWM\u001a;\t\r\u0005\rC\u00041\u0001@\u0003!y\u0007/\u001a:bi>\u0014\bBBA$9\u0001\u0007\u0011+A\u0003sS\u001eDG\u000f\u0003\u0004\u00022q\u0001\r!\u001a\u0005\u0006oq\u0001\r!\u000f\u000b\fw\u0006=\u0013\u0011KA*\u0003+\n9\u0006\u0003\u0004\u0002@u\u0001\r!\u0015\u0005\u0007\u0003\u0007j\u0002\u0019A \t\r\u0005\u001dS\u00041\u0001R\u0011\u0015iX\u00041\u0001|\u0011\u00159T\u00041\u0001:\u00039)h.\u0019:z\u001b\u0006\u001c\'o\u001c\"p_2$\u0012b_A/\u0003?\n\t\'a\u0019\t\r\u0005}b\u00041\u0001R\u0011\u0019\t\u0019E\ba\u0001\u007f!1\u0011\u0011\u0007\u0010A\u0002\u0015DQa\u000e\u0010A\u0002e\"\u0012b_A4\u0003S\nY\'!\u001c\t\r\u0005}r\u00041\u0001R\u0011\u0019\t\u0019e\ba\u0001\u007f!)Qp\ba\u0001w\")qg\ba\u0001s\u0005)\u0012n]%ogR\fgnY3PM6\u000b7M]8C_>dGcC>\u0002t\u0005U\u0014qOA>\u0003{Ba!a\u0010!\u0001\u0004\t\u0006BBA\"A\u0001\u0007q\b\u0003\u0004\u0002z\u0001\u0002\raP\u0001\nG2\f7o\u001d(b[\u0016Da!!\r!\u0001\u0004)\u0007\"B\u001c!\u0001\u0004IDcC>\u0002\u0002\u0006\r\u0015QQAD\u0003\u0013Ca!a\u0010\"\u0001\u0004\t\u0006BBA\"C\u0001\u0007q\b\u0003\u0004\u0002z\u0005\u0002\ra\u0010\u0005\u0006{\u0006\u0002\ra\u001f\u0005\u0006o\u0005\u0002\r!O\u0001\u0014Y\u0016tw\r\u001e5TSj,W*Y2s_\n{w\u000e\u001c\u000b\fw\u0006=\u0015\u0011SAJ\u0003/\u000bY\n\u0003\u0004\u0002@\t\u0002\r!\u0015\u0005\u0007\u0003\u0007\u0012\u0003\u0019A \t\r\u0005U%\u00051\u0001R\u0003\u0019\t7\r^;bY\"1\u0011\u0011\u0014\u0012A\u0002E\u000b\u0001\"\u001a=qK\u000e$X\r\u001a\u0005\u0006o\t\u0002\r!O\u0001\u0010KbL7\u000f^:NC\u000e\u0014xNQ8pYRI10!)\u0002$\u0006\u0015\u0016q\u0015\u0005\u0007\u0003\u007f\u0019\u0003\u0019A)\t\r\u0005\u001d3\u00051\u0001R\u0011\u0019\t\td\ta\u0001K\")qg\ta\u0001s\u0005i\u0012n]*j[BdWmV5uQ>,H/\u0012=qe\u0016\u001c8/[8o)\u0016DH\u000fF\u0002f\u0003[CQ! \u0013A\u0002m\u0004"
    )
BootstrapMethods:
  0: #116 REF_invokeStatic java/lang/invoke/LambdaMetafactory.altMetafactory:(Ljava/lang/invoke/MethodHandles$Lookup;Ljava/lang/String;Ljava/lang/invoke/MethodType;[Ljava/lang/Object;)Ljava/lang/invoke/CallSite;
    Method arguments:
      #100 (Ljava/lang/Object;)Ljava/lang/Object;
      #105 REF_invokeStatic org/scalactic/Bool.$anonfun$makeString$1:(Lorg/scalactic/Bool;Ljava/lang/Object;)Ljava/lang/String;
      #107 (Ljava/lang/Object;)Ljava/lang/String;
      #108 5
      #109 1
      #107 (Ljava/lang/Object;)Ljava/lang/String;
  1: #280 REF_invokeStatic scala/runtime/LambdaDeserialize.bootstrap:(Ljava/lang/invoke/MethodHandles$Lookup;Ljava/lang/String;Ljava/lang/invoke/MethodType;[Ljava/lang/invoke/MethodHandle;)Ljava/lang/invoke/CallSite;
    Method arguments:
      #105 REF_invokeStatic org/scalactic/Bool.$anonfun$makeString$1:(Lorg/scalactic/Bool;Ljava/lang/Object;)Ljava/lang/String;
  ScalaInlineInfo: length = 0xA9 (unknown attribute)
   01 00 00 21 00 F0 00 E0 00 00 EF 00 DE 01 00 DF
   00 E0 00 00 DD 00 DE 01 00 65 00 66 01 00 FB 00
   E0 00 00 FA 00 DE 01 00 F4 00 E0 00 00 F3 00 DE
   01 01 0E 01 0F 01 00 8F 00 90 00 00 8C 00 8D 01
   00 A5 00 A6 00 00 A3 00 A4 01 00 A9 00 90 00 00
   4D 00 4E 01 00 C8 00 A6 00 00 C7 00 A4 01 00 CB
   00 90 00 00 D2 00 A6 00 00 D1 00 A4 01 00 D5 00
   90 00 00 BE 00 A6 00 00 BD 00 A4 01 00 C1 00 90
   00 00 1F 00 4C 00 00 B2 00 A6 00 00 CE 00 A6 00
   00 D8 00 A6 00 00 C4 00 A6 00 01 00 01 01 00 00
   FE 00 FF 01 00 DB 00 AF 00
  ScalaSig: length = 0x3 (unknown attribute)
   05 02 00
