Classfile /Users/mw/Projects/slang-braindump/.jar/jar8/assemble/slang-braindump/assemble/content/org/scalactic/ComposedNormalizingEquality.class
  Last modified May 29, 2022; size 8333 bytes
  SHA-256 checksum b6a9a53ba081ee18eef4722d91defc9c0a80009a8c924549b6fd90370e464d01
  Compiled from "ComposedNormalizingEquality.scala"
public final class org.scalactic.ComposedNormalizingEquality<A extends java.lang.Object> extends java.lang.Object implements org.scalactic.NormalizingEquality<A>, scala.Product, java.io.Serializable
  minor version: 0
  major version: 52
  flags: (0x0031) ACC_PUBLIC, ACC_FINAL, ACC_SUPER
  this_class: #2                          // org/scalactic/ComposedNormalizingEquality
  super_class: #5                         // java/lang/Object
  interfaces: 3, fields: 2, methods: 26, attributes: 5
Constant pool:
    #1 = Utf8               org/scalactic/ComposedNormalizingEquality
    #2 = Class              #1            // org/scalactic/ComposedNormalizingEquality
    #3 = Utf8               <A:Ljava/lang/Object;>Ljava/lang/Object;Lorg/scalactic/NormalizingEquality<TA;>;Lscala/Product;Ljava/io/Serializable;
    #4 = Utf8               java/lang/Object
    #5 = Class              #4            // java/lang/Object
    #6 = Utf8               org/scalactic/NormalizingEquality
    #7 = Class              #6            // org/scalactic/NormalizingEquality
    #8 = Utf8               scala/Product
    #9 = Class              #8            // scala/Product
   #10 = Utf8               java/io/Serializable
   #11 = Class              #10           // java/io/Serializable
   #12 = Utf8               ComposedNormalizingEquality.scala
   #13 = Utf8               Lscala/reflect/ScalaSignature;
   #14 = Utf8               bytes
   #15 = Utf8               \u0006\u0005\u0005%f!\u0002\u000f\u001e\u0005v\t\u0003\u0002\u0003%\u0001\u0005+\u0007I\u0011I%\t\u00115\u0003!\u0011#Q\u0001\n)C\u0001B\u0014\u0001\u0003\u0016\u0004%\ta\u0014\u0005\t\'\u0002\u0011\t\u0012)A\u0005!\")A\u000b\u0001C\u0001+\")\u0011\f\u0001C\u00015\")Q\f\u0001C\u0001=\")A\r\u0001C\u0001K\"9q\rAA\u0001\n\u0003A\u0007bB9\u0001#\u0003%\tA\u001d\u0005\t\u007f\u0002\t\n\u0011\"\u0001\u0002\u0002!I\u0011\u0011\u0002\u0001\u0002\u0002\u0013\u0005\u00131\u0002\u0005\n\u0003;\u0001\u0011\u0011!C\u0001\u0003?A\u0011\"a\n\u0001\u0003\u0003%\t!!\u000b\t\u0013\u0005=\u0002!!A\u0005B\u0005E\u0002\"CA \u0001\u0005\u0005I\u0011AA!\u0011%\t)\u0005AA\u0001\n\u0003\n9\u0005C\u0005\u0002L\u0001\t\t\u0011\"\u0011\u0002N!I\u0011q\n\u0001\u0002\u0002\u0013\u0005\u0013\u0011\u000b\u0005\n\u0003\'\u0002\u0011\u0011!C!\u0003+:!\"!\u0017\u001e\u0003\u0003E\t!HA.\r%aR$!A\t\u0002u\ti\u0006\u0003\u0004U-\u0011\u0005\u0011\u0011\u000e\u0005\n\u0003\u001f2\u0012\u0011!C#\u0003#B\u0011\"a\u001b\u0017\u0003\u0003%\t)!\u001c\t\u0013\u0005}d#!A\u0005\u0002\u0006\u0005\u0005\"CAP-\u0005\u0005I\u0011BAQ\u0005m\u0019u.\u001c9pg\u0016$gj\u001c:nC2L\'0\u001b8h\u000bF,\u0018\r\\5us*\u0011adH\u0001\ng\u000e\fG.Y2uS\u000eT\u0011\u0001I\u0001\u0004_J<WC\u0001\u00120\'\u0015\u00011%K\u001d=!\t!s%D\u0001&\u0015\u00051\u0013!B:dC2\f\u0017B\u0001\u0015&\u0005\u0019\te.\u001f*fMB\u0019!fK\u0017\u000e\u0003uI!\u0001L\u000f\u0003\'9{\'/\\1mSjLgnZ#rk\u0006d\u0017\u000e^=\u0011\u00059zC\u0002\u0001\u0003\u0006a\u0001\u0011\rA\r\u0002\u0002\u0003\u000e\u0001\u0011CA\u001a7!\t!C\'\u0003\u00026K\t9aj\u001c;iS:<\u0007C\u0001\u00138\u0013\tATEA\u0002B]f\u0004\"\u0001\n\u001e\n\u0005m*#a\u0002)s_\u0012,8\r\u001e\t\u0003{\u0015s!AP\"\u000f\u0005}\u0012U\"\u0001!\u000b\u0005\u0005\u000b\u0014A\u0002\u001fs_>$h(C\u0001\'\u0013\t!U%A\u0004qC\u000e\\\u0017mZ3\n\u0005\u0019;%\u0001D*fe&\fG.\u001b>bE2,\'B\u0001#&\u0003i\tg\r^3s\u001d>\u0014X.\u00197ju\u0006$\u0018n\u001c8FcV\fG.\u001b;z+\u0005Q\u0005c\u0001\u0016L[%\u0011A*\b\u0002\t\u000bF,\u0018\r\\5us\u0006Y\u0012M\u001a;fe:{\'/\\1mSj\fG/[8o\u000bF,\u0018\r\\5us\u0002\n!\"\u001e8jM>\u0014X.\u001b;z+\u0005\u0001\u0006c\u0001\u0016R[%\u0011!+\b\u0002\u000b+:Lgm\u001c:nSRL\u0018aC;oS\u001a|\'/\\5us\u0002\na\u0001P5oSRtDc\u0001,X1B\u0019!\u0006A\u0017\t\u000b!+\u0001\u0019\u0001&\t\u000b9+\u0001\u0019\u0001)\u0002\u00159|\'/\\1mSj,G\r\u0006\u0002.7\")AL\u0002a\u0001[\u0005\t\u0011-A\no_Jl\u0017\r\\5{K\u0012\u001c\u0015M\u001c%b]\u0012dW\r\u0006\u0002`EB\u0011A\u0005Y\u0005\u0003C\u0016\u0012qAQ8pY\u0016\fg\u000eC\u0003d\u000f\u0001\u0007a\'A\u0001c\u0003AqwN]7bY&TX\rZ(s\'\u0006lW\r\u0006\u00027M\")1\r\u0003a\u0001m\u0005!1m\u001c9z+\tIG\u000eF\u0002k[>\u00042A\u000b\u0001l!\tqC\u000eB\u00031\u0013\t\u0007!\u0007C\u0004I\u0013A\u0005\t\u0019\u00018\u0011\u0007)Z5\u000eC\u0004O\u0013A\u0005\t\u0019\u00019\u0011\u0007)\n6.\u0001\bd_BLH\u0005Z3gCVdG\u000fJ\u0019\u0016\u0005MtX#\u0001;+\u0005)+8&\u0001<\u0011\u0005]dX\"\u0001=\u000b\u0005eT\u0018!C;oG\",7m[3e\u0015\tYX%\u0001\u0006b]:|G/\u0019;j_:L!! =\u0003#Ut7\r[3dW\u0016$g+\u0019:jC:\u001cW\rB\u00031\u0015\t\u0007!\'\u0001\bd_BLH\u0005Z3gCVdG\u000f\n\u001a\u0016\t\u0005\r\u0011qA\u000b\u0003\u0003\u000bQ#\u0001U;\u0005\u000bAZ!\u0019\u0001\u001a\u0002\u001bA\u0014x\u000eZ;diB\u0013XMZ5y+\t\ti\u0001\u0005\u0003\u0002\u0010\u0005eQBAA\t\u0015\u0011\t\u0019\"!\u0006\u0002\t1\fgn\u001a\u0006\u0003\u0003/\tAA[1wC&!\u00111DA\t\u0005\u0019\u0019FO]5oO\u0006a\u0001O]8ek\u000e$\u0018I]5usV\u0011\u0011\u0011\u0005\t\u0004I\u0005\r\u0012bAA\u0013K\t\u0019\u0011J\u001c;\u0002\u001dA\u0014x\u000eZ;di\u0016cW-\\3oiR\u0019a\'a\u000b\t\u0013\u00055b\"!AA\u0002\u0005\u0005\u0012a\u0001=%c\u0005y\u0001O]8ek\u000e$\u0018\n^3sCR|\'/\u0006\u0002\u00024A)\u0011QGA\u001em5\u0011\u0011q\u0007\u0006\u0004\u0003s)\u0013AC2pY2,7\r^5p]&!\u0011QHA\u001c\u0005!IE/\u001a:bi>\u0014\u0018\u0001C2b]\u0016\u000bX/\u00197\u0015\u0007}\u000b\u0019\u0005\u0003\u0005\u0002.A\t\t\u00111\u00017\u0003I\u0001(o\u001c3vGR,E.Z7f]Rt\u0015-\\3\u0015\t\u00055\u0011\u0011\n\u0005\n\u0003[\t\u0012\u0011!a\u0001\u0003C\t\u0001\u0002[1tQ\u000e{G-\u001a\u000b\u0003\u0003C\t\u0001\u0002^8TiJLgn\u001a\u000b\u0003\u0003\u001b\ta!Z9vC2\u001cHcA0\u0002X!A\u0011Q\u0006\u000b\u0002\u0002\u0003\u0007a\'A\u000eD_6\u0004xn]3e\u001d>\u0014X.\u00197ju&tw-R9vC2LG/\u001f\t\u0003UY\u0019BAF\u0012\u0002`A!\u0011\u0011MA4\u001b\t\t\u0019G\u0003\u0003\u0002f\u0005U\u0011AA5p\u0013\r1\u00151\r\u000b\u0003\u00037\nQ!\u00199qYf,B!a\u001c\u0002vQ1\u0011\u0011OA<\u0003w\u0002BA\u000b\u0001\u0002tA\u0019a&!\u001e\u0005\u000bAJ\"\u0019\u0001\u001a\t\r!K\u0002\u0019AA=!\u0011Q3*a\u001d\t\r9K\u0002\u0019AA?!\u0011Q\u0013+a\u001d\u0002\u000fUt\u0017\r\u001d9msV!\u00111QAK)\u0011\t))!\'\u0011\u000b\u0011\n9)a#\n\u0007\u0005%UE\u0001\u0004PaRLwN\u001c\t\bI\u00055\u0015\u0011SAL\u0013\r\ty)\n\u0002\u0007)V\u0004H.\u001a\u001a\u0011\t)Z\u00151\u0013\t\u0004]\u0005UE!\u0002\u0019\u001b\u0005\u0004\u0011\u0004\u0003\u0002\u0016R\u0003\'C\u0011\"a\'\u001b\u0003\u0003\u0005\r!!(\u0002\u0007a$\u0003\u0007\u0005\u0003+\u0001\u0005M\u0015\u0001D<sSR,\'+\u001a9mC\u000e,GCAAR!\u0011\ty!!*\n\t\u0005\u001d\u0016\u0011\u0003\u0002\u0007\u001f\nTWm\u0019;
   #16 = Utf8               afterNormalizationEquality
   #17 = Utf8               Lorg/scalactic/Equality;
   #18 = Utf8               Lorg/scalactic/Equality<TA;>;
   #19 = Utf8               uniformity
   #20 = Utf8               Lorg/scalactic/Uniformity;
   #21 = Utf8               Lorg/scalactic/Uniformity<TA;>;
   #22 = Utf8               unapply
   #23 = Utf8               (Lorg/scalactic/ComposedNormalizingEquality;)Lscala/Option;
   #24 = Utf8               <A:Ljava/lang/Object;>(Lorg/scalactic/ComposedNormalizingEquality<TA;>;)Lscala/Option<Lscala/Tuple2<Lorg/scalactic/Equality<TA;>;Lorg/scalactic/Uniformity<TA;>;>;>;
   #25 = Utf8               x$0
   #26 = Utf8               org/scalactic/ComposedNormalizingEquality$
   #27 = Class              #26           // org/scalactic/ComposedNormalizingEquality$
   #28 = Utf8               MODULE$
   #29 = Utf8               Lorg/scalactic/ComposedNormalizingEquality$;
   #30 = NameAndType        #28:#29       // MODULE$:Lorg/scalactic/ComposedNormalizingEquality$;
   #31 = Fieldref           #27.#30       // org/scalactic/ComposedNormalizingEquality$.MODULE$:Lorg/scalactic/ComposedNormalizingEquality$;
   #32 = NameAndType        #22:#23       // unapply:(Lorg/scalactic/ComposedNormalizingEquality;)Lscala/Option;
   #33 = Methodref          #27.#32       // org/scalactic/ComposedNormalizingEquality$.unapply:(Lorg/scalactic/ComposedNormalizingEquality;)Lscala/Option;
   #34 = Utf8               Lorg/scalactic/ComposedNormalizingEquality;
   #35 = Utf8               apply
   #36 = Utf8               (Lorg/scalactic/Equality;Lorg/scalactic/Uniformity;)Lorg/scalactic/ComposedNormalizingEquality;
   #37 = Utf8               <A:Ljava/lang/Object;>(Lorg/scalactic/Equality<TA;>;Lorg/scalactic/Uniformity<TA;>;)Lorg/scalactic/ComposedNormalizingEquality<TA;>;
   #38 = NameAndType        #35:#36       // apply:(Lorg/scalactic/Equality;Lorg/scalactic/Uniformity;)Lorg/scalactic/ComposedNormalizingEquality;
   #39 = Methodref          #27.#38       // org/scalactic/ComposedNormalizingEquality$.apply:(Lorg/scalactic/Equality;Lorg/scalactic/Uniformity;)Lorg/scalactic/ComposedNormalizingEquality;
   #40 = Utf8               productElementNames
   #41 = Utf8               ()Lscala/collection/Iterator;
   #42 = Utf8               ()Lscala/collection/Iterator<Ljava/lang/String;>;
   #43 = Utf8               productElementNames$
   #44 = Utf8               (Lscala/Product;)Lscala/collection/Iterator;
   #45 = NameAndType        #43:#44       // productElementNames$:(Lscala/Product;)Lscala/collection/Iterator;
   #46 = InterfaceMethodref #9.#45        // scala/Product.productElementNames$:(Lscala/Product;)Lscala/collection/Iterator;
   #47 = Utf8               this
   #48 = Utf8               areEqual
   #49 = Utf8               (Ljava/lang/Object;Ljava/lang/Object;)Z
   #50 = Utf8               (TA;Ljava/lang/Object;)Z
   #51 = Utf8               a
   #52 = Utf8               b
   #53 = Utf8               areEqual$
   #54 = Utf8               (Lorg/scalactic/NormalizingEquality;Ljava/lang/Object;Ljava/lang/Object;)Z
   #55 = NameAndType        #53:#54       // areEqual$:(Lorg/scalactic/NormalizingEquality;Ljava/lang/Object;Ljava/lang/Object;)Z
   #56 = InterfaceMethodref #7.#55        // org/scalactic/NormalizingEquality.areEqual$:(Lorg/scalactic/NormalizingEquality;Ljava/lang/Object;Ljava/lang/Object;)Z
   #57 = Utf8               Ljava/lang/Object;
   #58 = Utf8               and
   #59 = Utf8               (Lorg/scalactic/Uniformity;)Lorg/scalactic/NormalizingEquality;
   #60 = Utf8               (Lorg/scalactic/Uniformity<TA;>;)Lorg/scalactic/NormalizingEquality<TA;>;
   #61 = Utf8               other
   #62 = Utf8               and$
   #63 = Utf8               (Lorg/scalactic/NormalizingEquality;Lorg/scalactic/Uniformity;)Lorg/scalactic/NormalizingEquality;
   #64 = NameAndType        #62:#63       // and$:(Lorg/scalactic/NormalizingEquality;Lorg/scalactic/Uniformity;)Lorg/scalactic/NormalizingEquality;
   #65 = InterfaceMethodref #7.#64        // org/scalactic/NormalizingEquality.and$:(Lorg/scalactic/NormalizingEquality;Lorg/scalactic/Uniformity;)Lorg/scalactic/NormalizingEquality;
   #66 = Utf8               toUniformity
   #67 = Utf8               ()Lorg/scalactic/Uniformity;
   #68 = Utf8               ()Lorg/scalactic/Uniformity<TA;>;
   #69 = Utf8               toUniformity$
   #70 = Utf8               (Lorg/scalactic/NormalizingEquality;)Lorg/scalactic/Uniformity;
   #71 = NameAndType        #69:#70       // toUniformity$:(Lorg/scalactic/NormalizingEquality;)Lorg/scalactic/Uniformity;
   #72 = InterfaceMethodref #7.#71        // org/scalactic/NormalizingEquality.toUniformity$:(Lorg/scalactic/NormalizingEquality;)Lorg/scalactic/Uniformity;
   #73 = Utf8               areEquivalent
   #74 = Utf8               (TA;TA;)Z
   #75 = Utf8               org/scalactic/Equality
   #76 = Class              #75           // org/scalactic/Equality
   #77 = Utf8               areEquivalent$
   #78 = Utf8               (Lorg/scalactic/Equality;Ljava/lang/Object;Ljava/lang/Object;)Z
   #79 = NameAndType        #77:#78       // areEquivalent$:(Lorg/scalactic/Equality;Ljava/lang/Object;Ljava/lang/Object;)Z
   #80 = InterfaceMethodref #76.#79       // org/scalactic/Equality.areEquivalent$:(Lorg/scalactic/Equality;Ljava/lang/Object;Ljava/lang/Object;)Z
   #81 = Utf8               org$scalactic$NormalizingEquality$_setter_$afterNormalizationEquality_$eq
   #82 = Utf8               (Lorg/scalactic/Equality;)V
   #83 = Utf8               (Lorg/scalactic/Equality<TA;>;)V
   #84 = Utf8               x$1
   #85 = Utf8               ()Lorg/scalactic/Equality;
   #86 = Utf8               ()Lorg/scalactic/Equality<TA;>;
   #87 = NameAndType        #16:#17       // afterNormalizationEquality:Lorg/scalactic/Equality;
   #88 = Fieldref           #2.#87        // org/scalactic/ComposedNormalizingEquality.afterNormalizationEquality:Lorg/scalactic/Equality;
   #89 = NameAndType        #19:#20       // uniformity:Lorg/scalactic/Uniformity;
   #90 = Fieldref           #2.#89        // org/scalactic/ComposedNormalizingEquality.uniformity:Lorg/scalactic/Uniformity;
   #91 = Utf8               normalized
   #92 = Utf8               (Ljava/lang/Object;)Ljava/lang/Object;
   #93 = Utf8               (TA;)TA;
   #94 = NameAndType        #19:#67       // uniformity:()Lorg/scalactic/Uniformity;
   #95 = Methodref          #2.#94        // org/scalactic/ComposedNormalizingEquality.uniformity:()Lorg/scalactic/Uniformity;
   #96 = Utf8               org/scalactic/Uniformity
   #97 = Class              #96           // org/scalactic/Uniformity
   #98 = NameAndType        #91:#92       // normalized:(Ljava/lang/Object;)Ljava/lang/Object;
   #99 = InterfaceMethodref #97.#98       // org/scalactic/Uniformity.normalized:(Ljava/lang/Object;)Ljava/lang/Object;
  #100 = Utf8               normalizedCanHandle
  #101 = Utf8               (Ljava/lang/Object;)Z
  #102 = NameAndType        #100:#101     // normalizedCanHandle:(Ljava/lang/Object;)Z
  #103 = InterfaceMethodref #97.#102      // org/scalactic/Uniformity.normalizedCanHandle:(Ljava/lang/Object;)Z
  #104 = Utf8               normalizedOrSame
  #105 = NameAndType        #104:#92      // normalizedOrSame:(Ljava/lang/Object;)Ljava/lang/Object;
  #106 = InterfaceMethodref #97.#105      // org/scalactic/Uniformity.normalizedOrSame:(Ljava/lang/Object;)Ljava/lang/Object;
  #107 = Utf8               copy
  #108 = Utf8               <init>
  #109 = Utf8               (Lorg/scalactic/Equality;Lorg/scalactic/Uniformity;)V
  #110 = NameAndType        #108:#109     // "<init>":(Lorg/scalactic/Equality;Lorg/scalactic/Uniformity;)V
  #111 = Methodref          #2.#110       // org/scalactic/ComposedNormalizingEquality."<init>":(Lorg/scalactic/Equality;Lorg/scalactic/Uniformity;)V
  #112 = Utf8               copy$default$1
  #113 = Utf8               <A:Ljava/lang/Object;>()Lorg/scalactic/Equality<TA;>;
  #114 = NameAndType        #16:#85       // afterNormalizationEquality:()Lorg/scalactic/Equality;
  #115 = Methodref          #2.#114       // org/scalactic/ComposedNormalizingEquality.afterNormalizationEquality:()Lorg/scalactic/Equality;
  #116 = Utf8               copy$default$2
  #117 = Utf8               <A:Ljava/lang/Object;>()Lorg/scalactic/Uniformity<TA;>;
  #118 = Utf8               productPrefix
  #119 = Utf8               ()Ljava/lang/String;
  #120 = Utf8               ComposedNormalizingEquality
  #121 = String             #120          // ComposedNormalizingEquality
  #122 = Utf8               productArity
  #123 = Utf8               ()I
  #124 = Utf8               productElement
  #125 = Utf8               (I)Ljava/lang/Object;
  #126 = Utf8               scala/runtime/Statics
  #127 = Class              #126          // scala/runtime/Statics
  #128 = Utf8               ioobe
  #129 = NameAndType        #128:#125     // ioobe:(I)Ljava/lang/Object;
  #130 = Methodref          #127.#129     // scala/runtime/Statics.ioobe:(I)Ljava/lang/Object;
  #131 = Utf8               I
  #132 = Utf8               productIterator
  #133 = Utf8               ()Lscala/collection/Iterator<Ljava/lang/Object;>;
  #134 = Utf8               scala/runtime/ScalaRunTime$
  #135 = Class              #134          // scala/runtime/ScalaRunTime$
  #136 = Utf8               Lscala/runtime/ScalaRunTime$;
  #137 = NameAndType        #28:#136      // MODULE$:Lscala/runtime/ScalaRunTime$;
  #138 = Fieldref           #135.#137     // scala/runtime/ScalaRunTime$.MODULE$:Lscala/runtime/ScalaRunTime$;
  #139 = Utf8               typedProductIterator
  #140 = NameAndType        #139:#44      // typedProductIterator:(Lscala/Product;)Lscala/collection/Iterator;
  #141 = Methodref          #135.#140     // scala/runtime/ScalaRunTime$.typedProductIterator:(Lscala/Product;)Lscala/collection/Iterator;
  #142 = Utf8               canEqual
  #143 = Utf8               productElementName
  #144 = Utf8               (I)Ljava/lang/String;
  #145 = String             #16           // afterNormalizationEquality
  #146 = String             #19           // uniformity
  #147 = Utf8               java/lang/String
  #148 = Class              #147          // java/lang/String
  #149 = Utf8               hashCode
  #150 = Utf8               _hashCode
  #151 = Utf8               (Lscala/Product;)I
  #152 = NameAndType        #150:#151     // _hashCode:(Lscala/Product;)I
  #153 = Methodref          #135.#152     // scala/runtime/ScalaRunTime$._hashCode:(Lscala/Product;)I
  #154 = Utf8               toString
  #155 = Utf8               _toString
  #156 = Utf8               (Lscala/Product;)Ljava/lang/String;
  #157 = NameAndType        #155:#156     // _toString:(Lscala/Product;)Ljava/lang/String;
  #158 = Methodref          #135.#157     // scala/runtime/ScalaRunTime$._toString:(Lscala/Product;)Ljava/lang/String;
  #159 = Utf8               equals
  #160 = NameAndType        #159:#101     // equals:(Ljava/lang/Object;)Z
  #161 = Methodref          #5.#160       // java/lang/Object.equals:(Ljava/lang/Object;)Z
  #162 = Utf8               (Lorg/scalactic/Equality<TA;>;Lorg/scalactic/Uniformity<TA;>;)V
  #163 = Utf8               ()V
  #164 = NameAndType        #108:#163     // "<init>":()V
  #165 = Methodref          #5.#164       // java/lang/Object."<init>":()V
  #166 = Utf8               $init$
  #167 = NameAndType        #166:#82      // $init$:(Lorg/scalactic/Equality;)V
  #168 = InterfaceMethodref #76.#167      // org/scalactic/Equality.$init$:(Lorg/scalactic/Equality;)V
  #169 = Utf8               (Lorg/scalactic/NormalizingEquality;)V
  #170 = NameAndType        #166:#169     // $init$:(Lorg/scalactic/NormalizingEquality;)V
  #171 = InterfaceMethodref #7.#170       // org/scalactic/NormalizingEquality.$init$:(Lorg/scalactic/NormalizingEquality;)V
  #172 = Utf8               (Lscala/Product;)V
  #173 = NameAndType        #166:#172     // $init$:(Lscala/Product;)V
  #174 = InterfaceMethodref #9.#173       // scala/Product.$init$:(Lscala/Product;)V
  #175 = Utf8               Signature
  #176 = Utf8               Code
  #177 = Utf8               LocalVariableTable
  #178 = Utf8               MethodParameters
  #179 = Utf8               LineNumberTable
  #180 = Utf8               StackMapTable
  #181 = Utf8               SourceFile
  #182 = Utf8               RuntimeVisibleAnnotations
  #183 = Utf8               ScalaInlineInfo
  #184 = Utf8               ScalaSig
{
  private final org.scalactic.Equality<A> afterNormalizationEquality;
    descriptor: Lorg/scalactic/Equality;
    flags: (0x0012) ACC_PRIVATE, ACC_FINAL
    Signature: #18                          // Lorg/scalactic/Equality<TA;>;

  private final org.scalactic.Uniformity<A> uniformity;
    descriptor: Lorg/scalactic/Uniformity;
    flags: (0x0012) ACC_PRIVATE, ACC_FINAL
    Signature: #21                          // Lorg/scalactic/Uniformity<TA;>;

  public static <A extends java.lang.Object> scala.Option<scala.Tuple2<org.scalactic.Equality<A>, org.scalactic.Uniformity<A>>> unapply(org.scalactic.ComposedNormalizingEquality<A>);
    descriptor: (Lorg/scalactic/ComposedNormalizingEquality;)Lscala/Option;
    flags: (0x0009) ACC_PUBLIC, ACC_STATIC
    Code:
      stack=2, locals=1, args_size=1
         0: getstatic     #31                 // Field org/scalactic/ComposedNormalizingEquality$.MODULE$:Lorg/scalactic/ComposedNormalizingEquality$;
         3: aload_0
         4: invokevirtual #33                 // Method org/scalactic/ComposedNormalizingEquality$.unapply:(Lorg/scalactic/ComposedNormalizingEquality;)Lscala/Option;
         7: areturn
      LocalVariableTable:
        Start  Length  Slot  Name   Signature
            0       8     0   x$0   Lorg/scalactic/ComposedNormalizingEquality;
    Signature: #24                          // <A:Ljava/lang/Object;>(Lorg/scalactic/ComposedNormalizingEquality<TA;>;)Lscala/Option<Lscala/Tuple2<Lorg/scalactic/Equality<TA;>;Lorg/scalactic/Uniformity<TA;>;>;>;
    MethodParameters:
      Name                           Flags
      x$0                            final

  public static <A extends java.lang.Object> org.scalactic.ComposedNormalizingEquality<A> apply(org.scalactic.Equality<A>, org.scalactic.Uniformity<A>);
    descriptor: (Lorg/scalactic/Equality;Lorg/scalactic/Uniformity;)Lorg/scalactic/ComposedNormalizingEquality;
    flags: (0x0009) ACC_PUBLIC, ACC_STATIC
    Code:
      stack=3, locals=2, args_size=2
         0: getstatic     #31                 // Field org/scalactic/ComposedNormalizingEquality$.MODULE$:Lorg/scalactic/ComposedNormalizingEquality$;
         3: aload_0
         4: aload_1
         5: invokevirtual #39                 // Method org/scalactic/ComposedNormalizingEquality$.apply:(Lorg/scalactic/Equality;Lorg/scalactic/Uniformity;)Lorg/scalactic/ComposedNormalizingEquality;
         8: areturn
      LocalVariableTable:
        Start  Length  Slot  Name   Signature
            0       9     0 afterNormalizationEquality   Lorg/scalactic/Equality;
            0       9     1 uniformity   Lorg/scalactic/Uniformity;
    Signature: #37                          // <A:Ljava/lang/Object;>(Lorg/scalactic/Equality<TA;>;Lorg/scalactic/Uniformity<TA;>;)Lorg/scalactic/ComposedNormalizingEquality<TA;>;
    MethodParameters:
      Name                           Flags
      afterNormalizationEquality     final
      uniformity                     final

  public scala.collection.Iterator<java.lang.String> productElementNames();
    descriptor: ()Lscala/collection/Iterator;
    flags: (0x0001) ACC_PUBLIC
    Code:
      stack=1, locals=1, args_size=1
         0: aload_0
         1: invokestatic  #46                 // InterfaceMethod scala/Product.productElementNames$:(Lscala/Product;)Lscala/collection/Iterator;
         4: areturn
      LineNumberTable:
        line 18: 0
      LocalVariableTable:
        Start  Length  Slot  Name   Signature
            0       5     0  this   Lorg/scalactic/ComposedNormalizingEquality;
    Signature: #42                          // ()Lscala/collection/Iterator<Ljava/lang/String;>;

  public final boolean areEqual(A, java.lang.Object);
    descriptor: (Ljava/lang/Object;Ljava/lang/Object;)Z
    flags: (0x0011) ACC_PUBLIC, ACC_FINAL
    Code:
      stack=3, locals=3, args_size=3
         0: aload_0
         1: aload_1
         2: aload_2
         3: invokestatic  #56                 // InterfaceMethod org/scalactic/NormalizingEquality.areEqual$:(Lorg/scalactic/NormalizingEquality;Ljava/lang/Object;Ljava/lang/Object;)Z
         6: ireturn
      LineNumberTable:
        line 18: 0
      LocalVariableTable:
        Start  Length  Slot  Name   Signature
            0       7     0  this   Lorg/scalactic/ComposedNormalizingEquality;
            0       7     1     a   Ljava/lang/Object;
            0       7     2     b   Ljava/lang/Object;
    Signature: #50                          // (TA;Ljava/lang/Object;)Z
    MethodParameters:
      Name                           Flags
      a                              final
      b                              final

  public final org.scalactic.NormalizingEquality<A> and(org.scalactic.Uniformity<A>);
    descriptor: (Lorg/scalactic/Uniformity;)Lorg/scalactic/NormalizingEquality;
    flags: (0x0011) ACC_PUBLIC, ACC_FINAL
    Code:
      stack=2, locals=2, args_size=2
         0: aload_0
         1: aload_1
         2: invokestatic  #65                 // InterfaceMethod org/scalactic/NormalizingEquality.and$:(Lorg/scalactic/NormalizingEquality;Lorg/scalactic/Uniformity;)Lorg/scalactic/NormalizingEquality;
         5: areturn
      LineNumberTable:
        line 18: 0
      LocalVariableTable:
        Start  Length  Slot  Name   Signature
            0       6     0  this   Lorg/scalactic/ComposedNormalizingEquality;
            0       6     1 other   Lorg/scalactic/Uniformity;
    Signature: #60                          // (Lorg/scalactic/Uniformity<TA;>;)Lorg/scalactic/NormalizingEquality<TA;>;
    MethodParameters:
      Name                           Flags
      other                          final

  public final org.scalactic.Uniformity<A> toUniformity();
    descriptor: ()Lorg/scalactic/Uniformity;
    flags: (0x0011) ACC_PUBLIC, ACC_FINAL
    Code:
      stack=1, locals=1, args_size=1
         0: aload_0
         1: invokestatic  #72                 // InterfaceMethod org/scalactic/NormalizingEquality.toUniformity$:(Lorg/scalactic/NormalizingEquality;)Lorg/scalactic/Uniformity;
         4: areturn
      LineNumberTable:
        line 18: 0
      LocalVariableTable:
        Start  Length  Slot  Name   Signature
            0       5     0  this   Lorg/scalactic/ComposedNormalizingEquality;
    Signature: #68                          // ()Lorg/scalactic/Uniformity<TA;>;

  public final boolean areEquivalent(A, A);
    descriptor: (Ljava/lang/Object;Ljava/lang/Object;)Z
    flags: (0x0011) ACC_PUBLIC, ACC_FINAL
    Code:
      stack=3, locals=3, args_size=3
         0: aload_0
         1: aload_1
         2: aload_2
         3: invokestatic  #80                 // InterfaceMethod org/scalactic/Equality.areEquivalent$:(Lorg/scalactic/Equality;Ljava/lang/Object;Ljava/lang/Object;)Z
         6: ireturn
      LineNumberTable:
        line 18: 0
      LocalVariableTable:
        Start  Length  Slot  Name   Signature
            0       7     0  this   Lorg/scalactic/ComposedNormalizingEquality;
            0       7     1     a   Ljava/lang/Object;
            0       7     2     b   Ljava/lang/Object;
    Signature: #74                          // (TA;TA;)Z
    MethodParameters:
      Name                           Flags
      a                              final
      b                              final

  public void org$scalactic$NormalizingEquality$_setter_$afterNormalizationEquality_$eq(org.scalactic.Equality<A>);
    descriptor: (Lorg/scalactic/Equality;)V
    flags: (0x0001) ACC_PUBLIC
    Code:
      stack=0, locals=2, args_size=2
         0: return
      LineNumberTable:
        line 18: 0
      LocalVariableTable:
        Start  Length  Slot  Name   Signature
            0       1     0  this   Lorg/scalactic/ComposedNormalizingEquality;
            0       1     1   x$1   Lorg/scalactic/Equality;
    Signature: #83                          // (Lorg/scalactic/Equality<TA;>;)V
    MethodParameters:
      Name                           Flags
      x$1                            final

  public org.scalactic.Equality<A> afterNormalizationEquality();
    descriptor: ()Lorg/scalactic/Equality;
    flags: (0x0001) ACC_PUBLIC
    Code:
      stack=1, locals=1, args_size=1
         0: aload_0
         1: getfield      #88                 // Field afterNormalizationEquality:Lorg/scalactic/Equality;
         4: areturn
      LineNumberTable:
        line 19: 0
      LocalVariableTable:
        Start  Length  Slot  Name   Signature
            0       5     0  this   Lorg/scalactic/ComposedNormalizingEquality;
    Signature: #86                          // ()Lorg/scalactic/Equality<TA;>;

  public org.scalactic.Uniformity<A> uniformity();
    descriptor: ()Lorg/scalactic/Uniformity;
    flags: (0x0001) ACC_PUBLIC
    Code:
      stack=1, locals=1, args_size=1
         0: aload_0
         1: getfield      #90                 // Field uniformity:Lorg/scalactic/Uniformity;
         4: areturn
      LineNumberTable:
        line 20: 0
      LocalVariableTable:
        Start  Length  Slot  Name   Signature
            0       5     0  this   Lorg/scalactic/ComposedNormalizingEquality;
    Signature: #68                          // ()Lorg/scalactic/Uniformity<TA;>;

  public A normalized(A);
    descriptor: (Ljava/lang/Object;)Ljava/lang/Object;
    flags: (0x0001) ACC_PUBLIC
    Code:
      stack=2, locals=2, args_size=2
         0: aload_0
         1: invokevirtual #95                 // Method uniformity:()Lorg/scalactic/Uniformity;
         4: aload_1
         5: invokeinterface #99,  2           // InterfaceMethod org/scalactic/Uniformity.normalized:(Ljava/lang/Object;)Ljava/lang/Object;
        10: areturn
      LineNumberTable:
        line 23: 0
      LocalVariableTable:
        Start  Length  Slot  Name   Signature
            0      11     0  this   Lorg/scalactic/ComposedNormalizingEquality;
            0      11     1     a   Ljava/lang/Object;
    Signature: #93                          // (TA;)TA;
    MethodParameters:
      Name                           Flags
      a                              final

  public boolean normalizedCanHandle(java.lang.Object);
    descriptor: (Ljava/lang/Object;)Z
    flags: (0x0001) ACC_PUBLIC
    Code:
      stack=2, locals=2, args_size=2
         0: aload_0
         1: invokevirtual #95                 // Method uniformity:()Lorg/scalactic/Uniformity;
         4: aload_1
         5: invokeinterface #103,  2          // InterfaceMethod org/scalactic/Uniformity.normalizedCanHandle:(Ljava/lang/Object;)Z
        10: ireturn
      LineNumberTable:
        line 25: 0
      LocalVariableTable:
        Start  Length  Slot  Name   Signature
            0      11     0  this   Lorg/scalactic/ComposedNormalizingEquality;
            0      11     1     b   Ljava/lang/Object;
    MethodParameters:
      Name                           Flags
      b                              final

  public java.lang.Object normalizedOrSame(java.lang.Object);
    descriptor: (Ljava/lang/Object;)Ljava/lang/Object;
    flags: (0x0001) ACC_PUBLIC
    Code:
      stack=2, locals=2, args_size=2
         0: aload_0
         1: invokevirtual #95                 // Method uniformity:()Lorg/scalactic/Uniformity;
         4: aload_1
         5: invokeinterface #106,  2          // InterfaceMethod org/scalactic/Uniformity.normalizedOrSame:(Ljava/lang/Object;)Ljava/lang/Object;
        10: areturn
      LineNumberTable:
        line 27: 0
      LocalVariableTable:
        Start  Length  Slot  Name   Signature
            0      11     0  this   Lorg/scalactic/ComposedNormalizingEquality;
            0      11     1     b   Ljava/lang/Object;
    MethodParameters:
      Name                           Flags
      b                              final

  public <A extends java.lang.Object> org.scalactic.ComposedNormalizingEquality<A> copy(org.scalactic.Equality<A>, org.scalactic.Uniformity<A>);
    descriptor: (Lorg/scalactic/Equality;Lorg/scalactic/Uniformity;)Lorg/scalactic/ComposedNormalizingEquality;
    flags: (0x0001) ACC_PUBLIC
    Code:
      stack=4, locals=3, args_size=3
         0: new           #2                  // class org/scalactic/ComposedNormalizingEquality
         3: dup
         4: aload_1
         5: aload_2
         6: invokespecial #111                // Method "<init>":(Lorg/scalactic/Equality;Lorg/scalactic/Uniformity;)V
         9: areturn
      LineNumberTable:
        line 18: 0
        line 19: 4
        line 20: 5
      LocalVariableTable:
        Start  Length  Slot  Name   Signature
            0      10     0  this   Lorg/scalactic/ComposedNormalizingEquality;
            0      10     1 afterNormalizationEquality   Lorg/scalactic/Equality;
            0      10     2 uniformity   Lorg/scalactic/Uniformity;
    Signature: #37                          // <A:Ljava/lang/Object;>(Lorg/scalactic/Equality<TA;>;Lorg/scalactic/Uniformity<TA;>;)Lorg/scalactic/ComposedNormalizingEquality<TA;>;
    MethodParameters:
      Name                           Flags
      afterNormalizationEquality     final
      uniformity                     final

  public <A extends java.lang.Object> org.scalactic.Equality<A> copy$default$1();
    descriptor: ()Lorg/scalactic/Equality;
    flags: (0x0001) ACC_PUBLIC
    Code:
      stack=1, locals=1, args_size=1
         0: aload_0
         1: invokevirtual #115                // Method afterNormalizationEquality:()Lorg/scalactic/Equality;
         4: areturn
      LineNumberTable:
        line 19: 0
      LocalVariableTable:
        Start  Length  Slot  Name   Signature
            0       5     0  this   Lorg/scalactic/ComposedNormalizingEquality;
    Signature: #113                         // <A:Ljava/lang/Object;>()Lorg/scalactic/Equality<TA;>;

  public <A extends java.lang.Object> org.scalactic.Uniformity<A> copy$default$2();
    descriptor: ()Lorg/scalactic/Uniformity;
    flags: (0x0001) ACC_PUBLIC
    Code:
      stack=1, locals=1, args_size=1
         0: aload_0
         1: invokevirtual #95                 // Method uniformity:()Lorg/scalactic/Uniformity;
         4: areturn
      LineNumberTable:
        line 20: 0
      LocalVariableTable:
        Start  Length  Slot  Name   Signature
            0       5     0  this   Lorg/scalactic/ComposedNormalizingEquality;
    Signature: #117                         // <A:Ljava/lang/Object;>()Lorg/scalactic/Uniformity<TA;>;

  public java.lang.String productPrefix();
    descriptor: ()Ljava/lang/String;
    flags: (0x0001) ACC_PUBLIC
    Code:
      stack=1, locals=1, args_size=1
         0: ldc           #121                // String ComposedNormalizingEquality
         2: areturn
      LineNumberTable:
        line 18: 0
      LocalVariableTable:
        Start  Length  Slot  Name   Signature
            0       3     0  this   Lorg/scalactic/ComposedNormalizingEquality;

  public int productArity();
    descriptor: ()I
    flags: (0x0001) ACC_PUBLIC
    Code:
      stack=1, locals=1, args_size=1
         0: iconst_2
         1: ireturn
      LineNumberTable:
        line 18: 0
      LocalVariableTable:
        Start  Length  Slot  Name   Signature
            0       2     0  this   Lorg/scalactic/ComposedNormalizingEquality;

  public java.lang.Object productElement(int);
    descriptor: (I)Ljava/lang/Object;
    flags: (0x0001) ACC_PUBLIC
    Code:
      stack=1, locals=3, args_size=2
         0: iload_1
         1: istore_2
         2: iload_2
         3: tableswitch   { // 0 to 1
                       0: 24
                       1: 31
                 default: 38
            }
        24: aload_0
        25: invokevirtual #115                // Method afterNormalizationEquality:()Lorg/scalactic/Equality;
        28: goto          45
        31: aload_0
        32: invokevirtual #95                 // Method uniformity:()Lorg/scalactic/Uniformity;
        35: goto          45
        38: iload_1
        39: invokestatic  #130                // Method scala/runtime/Statics.ioobe:(I)Ljava/lang/Object;
        42: goto          45
        45: areturn
      StackMapTable: number_of_entries = 4
        frame_type = 252 /* append */
          offset_delta = 24
          locals = [ int ]
        frame_type = 6 /* same */
        frame_type = 6 /* same */
        frame_type = 70 /* same_locals_1_stack_item */
          stack = [ class java/lang/Object ]
      LineNumberTable:
        line 18: 0
      LocalVariableTable:
        Start  Length  Slot  Name   Signature
            0      46     0  this   Lorg/scalactic/ComposedNormalizingEquality;
            0      46     1   x$1   I
    MethodParameters:
      Name                           Flags
      x$1                            final

  public scala.collection.Iterator<java.lang.Object> productIterator();
    descriptor: ()Lscala/collection/Iterator;
    flags: (0x0001) ACC_PUBLIC
    Code:
      stack=2, locals=1, args_size=1
         0: getstatic     #138                // Field scala/runtime/ScalaRunTime$.MODULE$:Lscala/runtime/ScalaRunTime$;
         3: aload_0
         4: invokevirtual #141                // Method scala/runtime/ScalaRunTime$.typedProductIterator:(Lscala/Product;)Lscala/collection/Iterator;
         7: areturn
      LineNumberTable:
        line 18: 0
      LocalVariableTable:
        Start  Length  Slot  Name   Signature
            0       8     0  this   Lorg/scalactic/ComposedNormalizingEquality;
    Signature: #133                         // ()Lscala/collection/Iterator<Ljava/lang/Object;>;

  public boolean canEqual(java.lang.Object);
    descriptor: (Ljava/lang/Object;)Z
    flags: (0x0001) ACC_PUBLIC
    Code:
      stack=1, locals=2, args_size=2
         0: aload_1
         1: instanceof    #2                  // class org/scalactic/ComposedNormalizingEquality
         4: ireturn
      LineNumberTable:
        line 18: 0
      LocalVariableTable:
        Start  Length  Slot  Name   Signature
            0       5     0  this   Lorg/scalactic/ComposedNormalizingEquality;
            0       5     1   x$1   Ljava/lang/Object;
    MethodParameters:
      Name                           Flags
      x$1                            final

  public java.lang.String productElementName(int);
    descriptor: (I)Ljava/lang/String;
    flags: (0x0001) ACC_PUBLIC
    Code:
      stack=1, locals=3, args_size=2
         0: iload_1
         1: istore_2
         2: iload_2
         3: tableswitch   { // 0 to 1
                       0: 24
                       1: 29
                 default: 34
            }
        24: ldc           #145                // String afterNormalizationEquality
        26: goto          44
        29: ldc           #146                // String uniformity
        31: goto          44
        34: iload_1
        35: invokestatic  #130                // Method scala/runtime/Statics.ioobe:(I)Ljava/lang/Object;
        38: checkcast     #148                // class java/lang/String
        41: goto          44
        44: areturn
      StackMapTable: number_of_entries = 4
        frame_type = 252 /* append */
          offset_delta = 24
          locals = [ int ]
        frame_type = 4 /* same */
        frame_type = 4 /* same */
        frame_type = 73 /* same_locals_1_stack_item */
          stack = [ class java/lang/String ]
      LineNumberTable:
        line 18: 0
      LocalVariableTable:
        Start  Length  Slot  Name   Signature
            0      45     0  this   Lorg/scalactic/ComposedNormalizingEquality;
            0      45     1   x$1   I
    MethodParameters:
      Name                           Flags
      x$1                            final

  public int hashCode();
    descriptor: ()I
    flags: (0x0001) ACC_PUBLIC
    Code:
      stack=2, locals=1, args_size=1
         0: getstatic     #138                // Field scala/runtime/ScalaRunTime$.MODULE$:Lscala/runtime/ScalaRunTime$;
         3: aload_0
         4: invokevirtual #153                // Method scala/runtime/ScalaRunTime$._hashCode:(Lscala/Product;)I
         7: ireturn
      LineNumberTable:
        line 18: 0
      LocalVariableTable:
        Start  Length  Slot  Name   Signature
            0       8     0  this   Lorg/scalactic/ComposedNormalizingEquality;

  public java.lang.String toString();
    descriptor: ()Ljava/lang/String;
    flags: (0x0001) ACC_PUBLIC
    Code:
      stack=2, locals=1, args_size=1
         0: getstatic     #138                // Field scala/runtime/ScalaRunTime$.MODULE$:Lscala/runtime/ScalaRunTime$;
         3: aload_0
         4: invokevirtual #158                // Method scala/runtime/ScalaRunTime$._toString:(Lscala/Product;)Ljava/lang/String;
         7: areturn
      LineNumberTable:
        line 18: 0
      LocalVariableTable:
        Start  Length  Slot  Name   Signature
            0       8     0  this   Lorg/scalactic/ComposedNormalizingEquality;

  public boolean equals(java.lang.Object);
    descriptor: (Ljava/lang/Object;)Z
    flags: (0x0001) ACC_PUBLIC
    Code:
      stack=2, locals=7, args_size=2
         0: aload_0
         1: aload_1
         2: if_acmpeq     109
         5: aload_1
         6: astore_3
         7: aload_3
         8: instanceof    #2                  // class org/scalactic/ComposedNormalizingEquality
        11: ifeq          19
        14: iconst_1
        15: istore_2
        16: goto          27
        19: goto          22
        22: iconst_0
        23: istore_2
        24: goto          27
        27: iload_2
        28: ifeq          113
        31: aload_1
        32: checkcast     #2                  // class org/scalactic/ComposedNormalizingEquality
        35: astore        4
        37: aload_0
        38: invokevirtual #115                // Method afterNormalizationEquality:()Lorg/scalactic/Equality;
        41: aload         4
        43: invokevirtual #115                // Method afterNormalizationEquality:()Lorg/scalactic/Equality;
        46: astore        5
        48: dup
        49: ifnonnull     61
        52: pop
        53: aload         5
        55: ifnull        69
        58: goto          105
        61: aload         5
        63: invokevirtual #161                // Method java/lang/Object.equals:(Ljava/lang/Object;)Z
        66: ifeq          105
        69: aload_0
        70: invokevirtual #95                 // Method uniformity:()Lorg/scalactic/Uniformity;
        73: aload         4
        75: invokevirtual #95                 // Method uniformity:()Lorg/scalactic/Uniformity;
        78: astore        6
        80: dup
        81: ifnonnull     93
        84: pop
        85: aload         6
        87: ifnull        101
        90: goto          105
        93: aload         6
        95: invokevirtual #161                // Method java/lang/Object.equals:(Ljava/lang/Object;)Z
        98: ifeq          105
       101: iconst_1
       102: goto          106
       105: iconst_0
       106: ifeq          113
       109: iconst_1
       110: goto          114
       113: iconst_0
       114: ireturn
      StackMapTable: number_of_entries = 12
        frame_type = 253 /* append */
          offset_delta = 19
          locals = [ top, class java/lang/Object ]
        frame_type = 2 /* same */
        frame_type = 255 /* full_frame */
          offset_delta = 4
          locals = [ class org/scalactic/ComposedNormalizingEquality, class java/lang/Object, int, class java/lang/Object ]
          stack = []
        frame_type = 255 /* full_frame */
          offset_delta = 33
          locals = [ class org/scalactic/ComposedNormalizingEquality, class java/lang/Object, int, class java/lang/Object, class org/scalactic/ComposedNormalizingEquality, class org/scalactic/Equality ]
          stack = [ class org/scalactic/Equality ]
        frame_type = 7 /* same */
        frame_type = 255 /* full_frame */
          offset_delta = 23
          locals = [ class org/scalactic/ComposedNormalizingEquality, class java/lang/Object, int, class java/lang/Object, class org/scalactic/ComposedNormalizingEquality, class org/scalactic/Equality, class org/scalactic/Uniformity ]
          stack = [ class org/scalactic/Uniformity ]
        frame_type = 7 /* same */
        frame_type = 250 /* chop */
          offset_delta = 3
        frame_type = 64 /* same_locals_1_stack_item */
          stack = [ int ]
        frame_type = 255 /* full_frame */
          offset_delta = 2
          locals = [ class org/scalactic/ComposedNormalizingEquality, class java/lang/Object ]
          stack = []
        frame_type = 253 /* append */
          offset_delta = 3
          locals = [ int, class java/lang/Object ]
        frame_type = 255 /* full_frame */
          offset_delta = 0
          locals = [ class org/scalactic/ComposedNormalizingEquality, class java/lang/Object ]
          stack = [ int ]
      LineNumberTable:
        line 18: 0
      LocalVariableTable:
        Start  Length  Slot  Name   Signature
            0     115     0  this   Lorg/scalactic/ComposedNormalizingEquality;
            0     115     1   x$1   Ljava/lang/Object;
    MethodParameters:
      Name                           Flags
      x$1                            final

  public org.scalactic.ComposedNormalizingEquality(org.scalactic.Equality<A>, org.scalactic.Uniformity<A>);
    descriptor: (Lorg/scalactic/Equality;Lorg/scalactic/Uniformity;)V
    flags: (0x0001) ACC_PUBLIC
    Code:
      stack=2, locals=3, args_size=3
         0: aload_0
         1: aload_1
         2: putfield      #88                 // Field afterNormalizationEquality:Lorg/scalactic/Equality;
         5: aload_0
         6: aload_2
         7: putfield      #90                 // Field uniformity:Lorg/scalactic/Uniformity;
        10: aload_0
        11: invokespecial #165                // Method java/lang/Object."<init>":()V
        14: aload_0
        15: invokestatic  #168                // InterfaceMethod org/scalactic/Equality.$init$:(Lorg/scalactic/Equality;)V
        18: aload_0
        19: invokestatic  #171                // InterfaceMethod org/scalactic/NormalizingEquality.$init$:(Lorg/scalactic/NormalizingEquality;)V
        22: aload_0
        23: invokestatic  #174                // InterfaceMethod scala/Product.$init$:(Lscala/Product;)V
        26: return
      LineNumberTable:
        line 19: 0
        line 20: 5
        line 21: 10
        line 18: 26
      LocalVariableTable:
        Start  Length  Slot  Name   Signature
            0      27     0  this   Lorg/scalactic/ComposedNormalizingEquality;
            0      27     1 afterNormalizationEquality   Lorg/scalactic/Equality;
            0      27     2 uniformity   Lorg/scalactic/Uniformity;
    Signature: #162                         // (Lorg/scalactic/Equality<TA;>;Lorg/scalactic/Uniformity<TA;>;)V
    MethodParameters:
      Name                           Flags
      afterNormalizationEquality     final
      uniformity                     final
}
Signature: #3                           // <A:Ljava/lang/Object;>Ljava/lang/Object;Lorg/scalactic/NormalizingEquality<TA;>;Lscala/Product;Ljava/io/Serializable;
SourceFile: "ComposedNormalizingEquality.scala"
RuntimeVisibleAnnotations:
  0: #13(#14=s#15)
    scala.reflect.ScalaSignature(
      bytes="\u0006\u0005\u0005%f!\u0002\u000f\u001e\u0005v\t\u0003\u0002\u0003%\u0001\u0005+\u0007I\u0011I%\t\u00115\u0003!\u0011#Q\u0001\n)C\u0001B\u0014\u0001\u0003\u0016\u0004%\ta\u0014\u0005\t\'\u0002\u0011\t\u0012)A\u0005!\")A\u000b\u0001C\u0001+\")\u0011\f\u0001C\u00015\")Q\f\u0001C\u0001=\")A\r\u0001C\u0001K\"9q\rAA\u0001\n\u0003A\u0007bB9\u0001#\u0003%\tA\u001d\u0005\t\u007f\u0002\t\n\u0011\"\u0001\u0002\u0002!I\u0011\u0011\u0002\u0001\u0002\u0002\u0013\u0005\u00131\u0002\u0005\n\u0003;\u0001\u0011\u0011!C\u0001\u0003?A\u0011\"a\n\u0001\u0003\u0003%\t!!\u000b\t\u0013\u0005=\u0002!!A\u0005B\u0005E\u0002\"CA \u0001\u0005\u0005I\u0011AA!\u0011%\t)\u0005AA\u0001\n\u0003\n9\u0005C\u0005\u0002L\u0001\t\t\u0011\"\u0011\u0002N!I\u0011q\n\u0001\u0002\u0002\u0013\u0005\u0013\u0011\u000b\u0005\n\u0003\'\u0002\u0011\u0011!C!\u0003+:!\"!\u0017\u001e\u0003\u0003E\t!HA.\r%aR$!A\t\u0002u\ti\u0006\u0003\u0004U-\u0011\u0005\u0011\u0011\u000e\u0005\n\u0003\u001f2\u0012\u0011!C#\u0003#B\u0011\"a\u001b\u0017\u0003\u0003%\t)!\u001c\t\u0013\u0005}d#!A\u0005\u0002\u0006\u0005\u0005\"CAP-\u0005\u0005I\u0011BAQ\u0005m\u0019u.\u001c9pg\u0016$gj\u001c:nC2L\'0\u001b8h\u000bF,\u0018\r\\5us*\u0011adH\u0001\ng\u000e\fG.Y2uS\u000eT\u0011\u0001I\u0001\u0004_J<WC\u0001\u00120\'\u0015\u00011%K\u001d=!\t!s%D\u0001&\u0015\u00051\u0013!B:dC2\f\u0017B\u0001\u0015&\u0005\u0019\te.\u001f*fMB\u0019!fK\u0017\u000e\u0003uI!\u0001L\u000f\u0003\'9{\'/\\1mSjLgnZ#rk\u0006d\u0017\u000e^=\u0011\u00059zC\u0002\u0001\u0003\u0006a\u0001\u0011\rA\r\u0002\u0002\u0003\u000e\u0001\u0011CA\u001a7!\t!C\'\u0003\u00026K\t9aj\u001c;iS:<\u0007C\u0001\u00138\u0013\tATEA\u0002B]f\u0004\"\u0001\n\u001e\n\u0005m*#a\u0002)s_\u0012,8\r\u001e\t\u0003{\u0015s!AP\"\u000f\u0005}\u0012U\"\u0001!\u000b\u0005\u0005\u000b\u0014A\u0002\u001fs_>$h(C\u0001\'\u0013\t!U%A\u0004qC\u000e\\\u0017mZ3\n\u0005\u0019;%\u0001D*fe&\fG.\u001b>bE2,\'B\u0001#&\u0003i\tg\r^3s\u001d>\u0014X.\u00197ju\u0006$\u0018n\u001c8FcV\fG.\u001b;z+\u0005Q\u0005c\u0001\u0016L[%\u0011A*\b\u0002\t\u000bF,\u0018\r\\5us\u0006Y\u0012M\u001a;fe:{\'/\\1mSj\fG/[8o\u000bF,\u0018\r\\5us\u0002\n!\"\u001e8jM>\u0014X.\u001b;z+\u0005\u0001\u0006c\u0001\u0016R[%\u0011!+\b\u0002\u000b+:Lgm\u001c:nSRL\u0018aC;oS\u001a|\'/\\5us\u0002\na\u0001P5oSRtDc\u0001,X1B\u0019!\u0006A\u0017\t\u000b!+\u0001\u0019\u0001&\t\u000b9+\u0001\u0019\u0001)\u0002\u00159|\'/\\1mSj,G\r\u0006\u0002.7\")AL\u0002a\u0001[\u0005\t\u0011-A\no_Jl\u0017\r\\5{K\u0012\u001c\u0015M\u001c%b]\u0012dW\r\u0006\u0002`EB\u0011A\u0005Y\u0005\u0003C\u0016\u0012qAQ8pY\u0016\fg\u000eC\u0003d\u000f\u0001\u0007a\'A\u0001c\u0003AqwN]7bY&TX\rZ(s\'\u0006lW\r\u0006\u00027M\")1\r\u0003a\u0001m\u0005!1m\u001c9z+\tIG\u000eF\u0002k[>\u00042A\u000b\u0001l!\tqC\u000eB\u00031\u0013\t\u0007!\u0007C\u0004I\u0013A\u0005\t\u0019\u00018\u0011\u0007)Z5\u000eC\u0004O\u0013A\u0005\t\u0019\u00019\u0011\u0007)\n6.\u0001\bd_BLH\u0005Z3gCVdG\u000fJ\u0019\u0016\u0005MtX#\u0001;+\u0005)+8&\u0001<\u0011\u0005]dX\"\u0001=\u000b\u0005eT\u0018!C;oG\",7m[3e\u0015\tYX%\u0001\u0006b]:|G/\u0019;j_:L!! =\u0003#Ut7\r[3dW\u0016$g+\u0019:jC:\u001cW\rB\u00031\u0015\t\u0007!\'\u0001\bd_BLH\u0005Z3gCVdG\u000f\n\u001a\u0016\t\u0005\r\u0011qA\u000b\u0003\u0003\u000bQ#\u0001U;\u0005\u000bAZ!\u0019\u0001\u001a\u0002\u001bA\u0014x\u000eZ;diB\u0013XMZ5y+\t\ti\u0001\u0005\u0003\u0002\u0010\u0005eQBAA\t\u0015\u0011\t\u0019\"!\u0006\u0002\t1\fgn\u001a\u0006\u0003\u0003/\tAA[1wC&!\u00111DA\t\u0005\u0019\u0019FO]5oO\u0006a\u0001O]8ek\u000e$\u0018I]5usV\u0011\u0011\u0011\u0005\t\u0004I\u0005\r\u0012bAA\u0013K\t\u0019\u0011J\u001c;\u0002\u001dA\u0014x\u000eZ;di\u0016cW-\\3oiR\u0019a\'a\u000b\t\u0013\u00055b\"!AA\u0002\u0005\u0005\u0012a\u0001=%c\u0005y\u0001O]8ek\u000e$\u0018\n^3sCR|\'/\u0006\u0002\u00024A)\u0011QGA\u001em5\u0011\u0011q\u0007\u0006\u0004\u0003s)\u0013AC2pY2,7\r^5p]&!\u0011QHA\u001c\u0005!IE/\u001a:bi>\u0014\u0018\u0001C2b]\u0016\u000bX/\u00197\u0015\u0007}\u000b\u0019\u0005\u0003\u0005\u0002.A\t\t\u00111\u00017\u0003I\u0001(o\u001c3vGR,E.Z7f]Rt\u0015-\\3\u0015\t\u00055\u0011\u0011\n\u0005\n\u0003[\t\u0012\u0011!a\u0001\u0003C\t\u0001\u0002[1tQ\u000e{G-\u001a\u000b\u0003\u0003C\t\u0001\u0002^8TiJLgn\u001a\u000b\u0003\u0003\u001b\ta!Z9vC2\u001cHcA0\u0002X!A\u0011Q\u0006\u000b\u0002\u0002\u0003\u0007a\'A\u000eD_6\u0004xn]3e\u001d>\u0014X.\u00197ju&tw-R9vC2LG/\u001f\t\u0003UY\u0019BAF\u0012\u0002`A!\u0011\u0011MA4\u001b\t\t\u0019G\u0003\u0003\u0002f\u0005U\u0011AA5p\u0013\r1\u00151\r\u000b\u0003\u00037\nQ!\u00199qYf,B!a\u001c\u0002vQ1\u0011\u0011OA<\u0003w\u0002BA\u000b\u0001\u0002tA\u0019a&!\u001e\u0005\u000bAJ\"\u0019\u0001\u001a\t\r!K\u0002\u0019AA=!\u0011Q3*a\u001d\t\r9K\u0002\u0019AA?!\u0011Q\u0013+a\u001d\u0002\u000fUt\u0017\r\u001d9msV!\u00111QAK)\u0011\t))!\'\u0011\u000b\u0011\n9)a#\n\u0007\u0005%UE\u0001\u0004PaRLwN\u001c\t\bI\u00055\u0015\u0011SAL\u0013\r\ty)\n\u0002\u0007)V\u0004H.\u001a\u001a\u0011\t)Z\u00151\u0013\t\u0004]\u0005UE!\u0002\u0019\u001b\u0005\u0004\u0011\u0004\u0003\u0002\u0016R\u0003\'C\u0011\"a\'\u001b\u0003\u0003\u0005\r!!(\u0002\u0007a$\u0003\u0007\u0005\u0003+\u0001\u0005M\u0015\u0001D<sSR,\'+\u001a9mC\u000e,GCAAR!\u0011\ty!!*\n\t\u0005\u001d\u0016\u0011\u0003\u0002\u0007\u001f\nTWm\u0019;"
    )
  ScalaInlineInfo: length = 0x7C (unknown attribute)
   01 01 00 18 00 6C 00 6D 01 00 10 00 55 01 00 3A
   00 3B 01 00 30 00 31 01 00 49 00 31 01 00 8E 00
   65 01 00 6B 00 24 01 00 70 00 55 01 00 74 00 43
   01 00 9F 00 65 01 00 95 00 7B 01 00 5B 00 5C 01
   00 64 00 65 01 00 68 00 5C 01 00 51 00 52 01 00
   7A 00 7B 01 00 7C 00 7D 01 00 8F 00 90 01 00 28
   00 29 01 00 84 00 29 01 00 76 00 77 01 00 9A 00
   77 01 00 42 00 43 01 00 13 00 43 01
  ScalaSig: length = 0x3 (unknown attribute)
   05 02 00
