Classfile /Users/mw/Projects/slang-braindump/.jar/jar8/assemble/slang-braindump/assemble/content/org/scalactic/Differ.class
  Last modified May 29, 2022; size 1072 bytes
  SHA-256 checksum a036e6778923a349c3b5ff4a8a9f9c467e43670f068853a7456eca0bdd898056
  Compiled from "Differ.scala"
public interface org.scalactic.Differ
  minor version: 0
  major version: 52
  flags: (0x0601) ACC_PUBLIC, ACC_INTERFACE, ACC_ABSTRACT
  this_class: #2                          // org/scalactic/Differ
  super_class: #4                         // java/lang/Object
  interfaces: 0, fields: 0, methods: 2, attributes: 4
Constant pool:
   #1 = Utf8               org/scalactic/Differ
   #2 = Class              #1             // org/scalactic/Differ
   #3 = Utf8               java/lang/Object
   #4 = Class              #3             // java/lang/Object
   #5 = Utf8               Differ.scala
   #6 = Utf8               Lscala/reflect/ScalaSignature;
   #7 = Utf8               bytes
   #8 = Utf8               \u0006\u0005e2\u0001BB\u0004\u0011\u0002G\u0005qa\u0003\u0005\u0006%\u00011\t\u0001F\u0004\u0007K\u001dA\ta\u0002\u0014\u0007\r\u00199\u0001\u0012A\u0004(\u0011\u0015A3\u0001\"\u0001*\u0011\u0015Q3\u0001\"\u0001,\u0005\u0019!\u0015N\u001a4fe*\u0011\u0001\"C\u0001\ng\u000e\fG.Y2uS\u000eT\u0011AC\u0001\u0004_J<7C\u0001\u0001\r!\ti\u0001#D\u0001\u000f\u0015\u0005y\u0011!B:dC2\f\u0017BA\t\u000f\u0005\u0019\te.\u001f*fM\u0006QA-\u001b4gKJ,gnY3\u0004\u0001Q!Q#\u0007\u0010!!\t1r#D\u0001\b\u0013\tArA\u0001\u0006Qe\u0016$H/\u001f)bSJDQAG\u0001A\u0002m\t\u0011!\u0019\t\u0003\u001bqI!!\b\b\u0003\u0007\u0005s\u0017\u0010C\u0003 \u0003\u0001\u00071$A\u0001c\u0011\u0015\t\u0013\u00011\u0001#\u0003)\u0001(/\u001a;uS\u001aLWM\u001d\t\u0003-\rJ!\u0001J\u0004\u0003\u0015A\u0013X\r\u001e;jM&,\'/\u0001\u0004ES\u001a4WM\u001d\t\u0003-\r\u0019\"a\u0001\u0007\u0002\rqJg.\u001b;?)\u00051\u0013aD:j[BdWm\u00117bgNt\u0015-\\3\u0015\u00051:\u0004CA\u00175\u001d\tq#\u0007\u0005\u00020\u001d5\t\u0001G\u0003\u00022\'\u00051AH]8pizJ!a\r\b\u0002\rA\u0013X\rZ3g\u0013\t)dG\u0001\u0004TiJLgn\u001a\u0006\u0003g9AQ\u0001O\u0003A\u0002m\t\u0011A\u001e
   #9 = Utf8               simpleClassName
  #10 = Utf8               (Ljava/lang/Object;)Ljava/lang/String;
  #11 = Utf8               v
  #12 = Utf8               org/scalactic/Differ$
  #13 = Class              #12            // org/scalactic/Differ$
  #14 = Utf8               MODULE$
  #15 = Utf8               Lorg/scalactic/Differ$;
  #16 = NameAndType        #14:#15        // MODULE$:Lorg/scalactic/Differ$;
  #17 = Fieldref           #13.#16        // org/scalactic/Differ$.MODULE$:Lorg/scalactic/Differ$;
  #18 = NameAndType        #9:#10         // simpleClassName:(Ljava/lang/Object;)Ljava/lang/String;
  #19 = Methodref          #13.#18        // org/scalactic/Differ$.simpleClassName:(Ljava/lang/Object;)Ljava/lang/String;
  #20 = Utf8               Ljava/lang/Object;
  #21 = Utf8               difference
  #22 = Utf8               (Ljava/lang/Object;Ljava/lang/Object;Lorg/scalactic/Prettifier;)Lorg/scalactic/PrettyPair;
  #23 = Utf8               a
  #24 = Utf8               b
  #25 = Utf8               prettifier
  #26 = Utf8               Code
  #27 = Utf8               LocalVariableTable
  #28 = Utf8               MethodParameters
  #29 = Utf8               SourceFile
  #30 = Utf8               RuntimeVisibleAnnotations
  #31 = Utf8               ScalaInlineInfo
  #32 = Utf8               ScalaSig
{
  public static java.lang.String simpleClassName(java.lang.Object);
    descriptor: (Ljava/lang/Object;)Ljava/lang/String;
    flags: (0x0009) ACC_PUBLIC, ACC_STATIC
    Code:
      stack=2, locals=1, args_size=1
         0: getstatic     #17                 // Field org/scalactic/Differ$.MODULE$:Lorg/scalactic/Differ$;
         3: aload_0
         4: invokevirtual #19                 // Method org/scalactic/Differ$.simpleClassName:(Ljava/lang/Object;)Ljava/lang/String;
         7: areturn
      LocalVariableTable:
        Start  Length  Slot  Name   Signature
            0       8     0     v   Ljava/lang/Object;
    MethodParameters:
      Name                           Flags
      v                              final

  public abstract org.scalactic.PrettyPair difference(java.lang.Object, java.lang.Object, org.scalactic.Prettifier);
    descriptor: (Ljava/lang/Object;Ljava/lang/Object;Lorg/scalactic/Prettifier;)Lorg/scalactic/PrettyPair;
    flags: (0x0401) ACC_PUBLIC, ACC_ABSTRACT
    MethodParameters:
      Name                           Flags
      a                              final
      b                              final
      prettifier                     final
}
SourceFile: "Differ.scala"
RuntimeVisibleAnnotations:
  0: #6(#7=s#8)
    scala.reflect.ScalaSignature(
      bytes="\u0006\u0005e2\u0001BB\u0004\u0011\u0002G\u0005qa\u0003\u0005\u0006%\u00011\t\u0001F\u0004\u0007K\u001dA\ta\u0002\u0014\u0007\r\u00199\u0001\u0012A\u0004(\u0011\u0015A3\u0001\"\u0001*\u0011\u0015Q3\u0001\"\u0001,\u0005\u0019!\u0015N\u001a4fe*\u0011\u0001\"C\u0001\ng\u000e\fG.Y2uS\u000eT\u0011AC\u0001\u0004_J<7C\u0001\u0001\r!\ti\u0001#D\u0001\u000f\u0015\u0005y\u0011!B:dC2\f\u0017BA\t\u000f\u0005\u0019\te.\u001f*fM\u0006QA-\u001b4gKJ,gnY3\u0004\u0001Q!Q#\u0007\u0010!!\t1r#D\u0001\b\u0013\tArA\u0001\u0006Qe\u0016$H/\u001f)bSJDQAG\u0001A\u0002m\t\u0011!\u0019\t\u0003\u001bqI!!\b\b\u0003\u0007\u0005s\u0017\u0010C\u0003 \u0003\u0001\u00071$A\u0001c\u0011\u0015\t\u0013\u00011\u0001#\u0003)\u0001(/\u001a;uS\u001aLWM\u001d\t\u0003-\rJ!\u0001J\u0004\u0003\u0015A\u0013X\r\u001e;jM&,\'/\u0001\u0004ES\u001a4WM\u001d\t\u0003-\r\u0019\"a\u0001\u0007\u0002\rqJg.\u001b;?)\u00051\u0013aD:j[BdWm\u00117bgNt\u0015-\\3\u0015\u00051:\u0004CA\u00175\u001d\tq#\u0007\u0005\u00020\u001d5\t\u0001G\u0003\u00022\'\u00051AH]8pizJ!a\r\b\u0002\rA\u0013X\rZ3g\u0013\t)dG\u0001\u0004TiJLgn\u001a\u0006\u0003g9AQ\u0001O\u0003A\u0002m\t\u0011A\u001e"
    )
  ScalaInlineInfo: length = 0x9 (unknown attribute)
   01 00 00 01 00 15 00 16 00
  ScalaSig: length = 0x3 (unknown attribute)
   05 02 00
