Classfile /Users/mw/Projects/slang-braindump/.jar/jar8/assemble/slang-braindump/assemble/content/org/scalactic/EitherSugar$NothingRightEitherizer.class
  Last modified May 29, 2022; size 1355 bytes
  SHA-256 checksum 4419b66eff0a5f039c6e355297d06b2aa4617493bc304e4bd6beac4e9fcb2525
  Compiled from "EitherSugar.scala"
public class org.scalactic.EitherSugar$NothingRightEitherizer<L extends java.lang.Object> extends java.lang.Object
  minor version: 0
  major version: 52
  flags: (0x0021) ACC_PUBLIC, ACC_SUPER
  this_class: #2                          // org/scalactic/EitherSugar$NothingRightEitherizer
  super_class: #5                         // java/lang/Object
  interfaces: 0, fields: 2, methods: 3, attributes: 5
Constant pool:
   #1 = Utf8               org/scalactic/EitherSugar$NothingRightEitherizer
   #2 = Class              #1             // org/scalactic/EitherSugar$NothingRightEitherizer
   #3 = Utf8               <L:Ljava/lang/Object;>Ljava/lang/Object;
   #4 = Utf8               java/lang/Object
   #5 = Class              #4             // java/lang/Object
   #6 = Utf8               EitherSugar.scala
   #7 = Utf8               org/scalactic/EitherSugar
   #8 = Class              #7             // org/scalactic/EitherSugar
   #9 = Utf8               NothingRightEitherizer
  #10 = Utf8               either
  #11 = Utf8               Lscala/util/Either;
  #12 = Utf8               Lscala/util/Either<TL;Lscala/runtime/Nothing$;>;
  #13 = Utf8               $outer
  #14 = Utf8               Lorg/scalactic/EitherSugar;
  #15 = Utf8               toOr
  #16 = Utf8               ()Lorg/scalactic/Or;
  #17 = Utf8               ()Lorg/scalactic/Or<Lscala/runtime/Nothing$;TL;>;
  #18 = Utf8               org/scalactic/Or$
  #19 = Class              #18            // org/scalactic/Or$
  #20 = Utf8               MODULE$
  #21 = Utf8               Lorg/scalactic/Or$;
  #22 = NameAndType        #20:#21        // MODULE$:Lorg/scalactic/Or$;
  #23 = Fieldref           #19.#22        // org/scalactic/Or$.MODULE$:Lorg/scalactic/Or$;
  #24 = NameAndType        #10:#11        // either:Lscala/util/Either;
  #25 = Fieldref           #2.#24         // org/scalactic/EitherSugar$NothingRightEitherizer.either:Lscala/util/Either;
  #26 = Utf8               from
  #27 = Utf8               (Lscala/util/Either;)Lorg/scalactic/Or;
  #28 = NameAndType        #26:#27        // from:(Lscala/util/Either;)Lorg/scalactic/Or;
  #29 = Methodref          #19.#28        // org/scalactic/Or$.from:(Lscala/util/Either;)Lorg/scalactic/Or;
  #30 = Utf8               this
  #31 = Utf8               Lorg/scalactic/EitherSugar$NothingRightEitherizer;
  #32 = Utf8               org$scalactic$EitherSugar$NothingRightEitherizer$$$outer
  #33 = Utf8               ()Lorg/scalactic/EitherSugar;
  #34 = NameAndType        #13:#14        // $outer:Lorg/scalactic/EitherSugar;
  #35 = Fieldref           #2.#34         // org/scalactic/EitherSugar$NothingRightEitherizer.$outer:Lorg/scalactic/EitherSugar;
  #36 = Utf8               <init>
  #37 = Utf8               (Lorg/scalactic/EitherSugar;Lscala/util/Either;)V
  #38 = Utf8               (Lscala/util/Either<TL;Lscala/runtime/Nothing$;>;)V
  #39 = Utf8               ()V
  #40 = NameAndType        #36:#39        // "<init>":()V
  #41 = Methodref          #5.#40         // java/lang/Object."<init>":()V
  #42 = Utf8               Signature
  #43 = Utf8               Code
  #44 = Utf8               LineNumberTable
  #45 = Utf8               LocalVariableTable
  #46 = Utf8               StackMapTable
  #47 = Utf8               MethodParameters
  #48 = Utf8               InnerClasses
  #49 = Utf8               SourceFile
  #50 = Utf8               ScalaInlineInfo
  #51 = Utf8               Scala
{
  private final scala.util.Either<L, scala.runtime.Nothing$> either;
    descriptor: Lscala/util/Either;
    flags: (0x0012) ACC_PRIVATE, ACC_FINAL
    Signature: #12                          // Lscala/util/Either<TL;Lscala/runtime/Nothing$;>;

  public final org.scalactic.EitherSugar $outer;
    descriptor: Lorg/scalactic/EitherSugar;
    flags: (0x1011) ACC_PUBLIC, ACC_FINAL, ACC_SYNTHETIC

  public org.scalactic.Or<scala.runtime.Nothing$, L> toOr();
    descriptor: ()Lorg/scalactic/Or;
    flags: (0x0001) ACC_PUBLIC
    Code:
      stack=2, locals=1, args_size=1
         0: getstatic     #23                 // Field org/scalactic/Or$.MODULE$:Lorg/scalactic/Or$;
         3: aload_0
         4: getfield      #25                 // Field either:Lscala/util/Either;
         7: invokevirtual #29                 // Method org/scalactic/Or$.from:(Lscala/util/Either;)Lorg/scalactic/Or;
        10: areturn
      LineNumberTable:
        line 47: 0
      LocalVariableTable:
        Start  Length  Slot  Name   Signature
            0      11     0  this   Lorg/scalactic/EitherSugar$NothingRightEitherizer;
    Signature: #17                          // ()Lorg/scalactic/Or<Lscala/runtime/Nothing$;TL;>;

  public org.scalactic.EitherSugar org$scalactic$EitherSugar$NothingRightEitherizer$$$outer();
    descriptor: ()Lorg/scalactic/EitherSugar;
    flags: (0x1001) ACC_PUBLIC, ACC_SYNTHETIC
    Code:
      stack=1, locals=1, args_size=1
         0: aload_0
         1: getfield      #35                 // Field $outer:Lorg/scalactic/EitherSugar;
         4: areturn
      LineNumberTable:
        line 46: 0
      LocalVariableTable:
        Start  Length  Slot  Name   Signature
            0       5     0  this   Lorg/scalactic/EitherSugar$NothingRightEitherizer;

  public org.scalactic.EitherSugar$NothingRightEitherizer(scala.util.Either<L, scala.runtime.Nothing$>);
    descriptor: (Lorg/scalactic/EitherSugar;Lscala/util/Either;)V
    flags: (0x0001) ACC_PUBLIC
    Code:
      stack=2, locals=3, args_size=3
         0: aload_0
         1: aload_2
         2: putfield      #25                 // Field either:Lscala/util/Either;
         5: aload_1
         6: ifnonnull     11
         9: aconst_null
        10: athrow
        11: aload_0
        12: aload_1
        13: putfield      #35                 // Field $outer:Lorg/scalactic/EitherSugar;
        16: aload_0
        17: invokespecial #41                 // Method java/lang/Object."<init>":()V
        20: return
      StackMapTable: number_of_entries = 1
        frame_type = 11 /* same */
      LineNumberTable:
        line 46: 0
        line 49: 16
        line 46: 20
      LocalVariableTable:
        Start  Length  Slot  Name   Signature
            0      21     0  this   Lorg/scalactic/EitherSugar$NothingRightEitherizer;
            0      21     1 $outer   Lorg/scalactic/EitherSugar;
            0      21     2 either   Lscala/util/Either;
    Signature: #38                          // (Lscala/util/Either<TL;Lscala/runtime/Nothing$;>;)V
    MethodParameters:
      Name                           Flags
      $outer                         final synthetic
      either                         final
}
InnerClasses:
  public #9= #2 of #8;                    // NothingRightEitherizer=class org/scalactic/EitherSugar$NothingRightEitherizer of class org/scalactic/EitherSugar
Signature: #3                           // <L:Ljava/lang/Object;>Ljava/lang/Object;
SourceFile: "EitherSugar.scala"
  ScalaInlineInfo: length = 0x13 (unknown attribute)
   01 00 00 03 00 24 00 25 00 00 20 00 21 00 00 0F
   00 10 00
  Scala: length = 0x0 (unknown attribute)

