Classfile /Users/mw/Projects/slang-braindump/.jar/jar8/assemble/slang-braindump/assemble/content/org/scalactic/GenMapDiffer.class
  Last modified May 29, 2022; size 6134 bytes
  SHA-256 checksum 32c0431d5d260e767d8318447dccaaad5c1598c41d2cbfd9ad9386ab89eea932
  Compiled from "Differ.scala"
public class org.scalactic.GenMapDiffer<K extends java.lang.Object, V extends java.lang.Object> extends java.lang.Object implements org.scalactic.Differ
  minor version: 0
  major version: 52
  flags: (0x0021) ACC_PUBLIC, ACC_SUPER
  this_class: #2                          // org/scalactic/GenMapDiffer
  super_class: #5                         // java/lang/Object
  interfaces: 1, fields: 0, methods: 6, attributes: 7
Constant pool:
    #1 = Utf8               org/scalactic/GenMapDiffer
    #2 = Class              #1            // org/scalactic/GenMapDiffer
    #3 = Utf8               <K:Ljava/lang/Object;V:Ljava/lang/Object;>Ljava/lang/Object;Lorg/scalactic/Differ;
    #4 = Utf8               java/lang/Object
    #5 = Class              #4            // java/lang/Object
    #6 = Utf8               org/scalactic/Differ
    #7 = Class              #6            // org/scalactic/Differ
    #8 = Utf8               Differ.scala
    #9 = Utf8               Lscala/reflect/ScalaSignature;
   #10 = Utf8               bytes
   #11 = Utf8               \u0006\u0005q2QAB\u0004\u0001\u000f-AQa\u0006\u0001\u0005\u0002eAQ!\u000b\u0001\u0005\u0002):aaN\u0004\t\u0002\u001dAdA\u0002\u0004\b\u0011\u00039\u0011\bC\u0003\u0018\t\u0011\u00051H\u0001\u0007HK:l\u0015\r\u001d#jM\u001a,\'O\u0003\u0002\t\u0013\u0005I1oY1mC\u000e$\u0018n\u0019\u0006\u0002\u0015\u0005\u0019qN]4\u0016\u00071ireE\u0002\u0001\u001bM\u0001\"AD\t\u000e\u0003=Q\u0011\u0001E\u0001\u0006g\u000e\fG.Y\u0005\u0003%=\u0011a!\u00118z%\u00164\u0007C\u0001\u000b\u0016\u001b\u00059\u0011B\u0001\f\b\u0005\u0019!\u0015N\u001a4fe\u00061A(\u001b8jiz\u001a\u0001\u0001F\u0001\u001b!\u0011!\u0002a\u0007\u0014\u0011\u0005qiB\u0002\u0001\u0003\u0006=\u0001\u0011\ra\b\u0002\u0002\u0017F\u0011\u0001e\t\t\u0003\u001d\u0005J!AI\b\u0003\u000f9{G\u000f[5oOB\u0011a\u0002J\u0005\u0003K=\u00111!\u00118z!\tar\u0005B\u0003)\u0001\t\u0007qDA\u0001W\u0003)!\u0017N\u001a4fe\u0016t7-\u001a\u000b\u0005W9\u0002$\u0007\u0005\u0002\u0015Y%\u0011Qf\u0002\u0002\u000b!J,G\u000f^=QC&\u0014\b\"B\u0018\u0003\u0001\u0004\u0019\u0013!A1\t\u000bE\u0012\u0001\u0019A\u0012\u0002\u0003\tDQa\r\u0002A\u0002Q\n!\u0002\u001d:fiRLg-[3s!\t!R\'\u0003\u00027\u000f\tQ\u0001K]3ui&4\u0017.\u001a:\u0002\u0019\u001d+g.T1q\t&4g-\u001a:\u0011\u0005Q!1C\u0001\u0003;!\u0011!\u0002aI\u0012\u0015\u0003a\u0002
   #12 = Utf8               java/lang/invoke/MethodHandles$Lookup
   #13 = Class              #12           // java/lang/invoke/MethodHandles$Lookup
   #14 = Utf8               java/lang/invoke/MethodHandles
   #15 = Class              #14           // java/lang/invoke/MethodHandles
   #16 = Utf8               Lookup
   #17 = Utf8               org/scalactic/GenMapDiffer$$anonfun$1
   #18 = Class              #17           // org/scalactic/GenMapDiffer$$anonfun$1
   #19 = Utf8               scala/math/Ordering$String$
   #20 = Class              #19           // scala/math/Ordering$String$
   #21 = Utf8               scala/math/Ordering
   #22 = Class              #21           // scala/math/Ordering
   #23 = Utf8               String$
   #24 = Utf8               difference
   #25 = Utf8               (Ljava/lang/Object;Ljava/lang/Object;Lorg/scalactic/Prettifier;)Lorg/scalactic/PrettyPair;
   #26 = Utf8               a
   #27 = Utf8               b
   #28 = Utf8               prettifier
   #29 = Utf8               scala/Tuple2
   #30 = Class              #29           // scala/Tuple2
   #31 = Utf8               <init>
   #32 = Utf8               (Ljava/lang/Object;Ljava/lang/Object;)V
   #33 = NameAndType        #31:#32       // "<init>":(Ljava/lang/Object;Ljava/lang/Object;)V
   #34 = Methodref          #30.#33       // scala/Tuple2."<init>":(Ljava/lang/Object;Ljava/lang/Object;)V
   #35 = Utf8               _1
   #36 = Utf8               ()Ljava/lang/Object;
   #37 = NameAndType        #35:#36       // _1:()Ljava/lang/Object;
   #38 = Methodref          #30.#37       // scala/Tuple2._1:()Ljava/lang/Object;
   #39 = Utf8               _2
   #40 = NameAndType        #39:#36       // _2:()Ljava/lang/Object;
   #41 = Methodref          #30.#40       // scala/Tuple2._2:()Ljava/lang/Object;
   #42 = Utf8               scala/collection/Map
   #43 = Class              #42           // scala/collection/Map
   #44 = Utf8               keySet
   #45 = Utf8               ()Lscala/collection/Set;
   #46 = NameAndType        #44:#45       // keySet:()Lscala/collection/Set;
   #47 = InterfaceMethodref #43.#46       // scala/collection/Map.keySet:()Lscala/collection/Set;
   #48 = Utf8               scala/collection/Set
   #49 = Class              #48           // scala/collection/Set
   #50 = Utf8               toList
   #51 = Utf8               ()Lscala/collection/immutable/List;
   #52 = NameAndType        #50:#51       // toList:()Lscala/collection/immutable/List;
   #53 = InterfaceMethodref #49.#52       // scala/collection/Set.toList:()Lscala/collection/immutable/List;
   #54 = Utf8               scala/collection/immutable/List
   #55 = Class              #54           // scala/collection/immutable/List
   #56 = Utf8               diff
   #57 = Utf8               (Lscala/collection/Seq;)Ljava/lang/Object;
   #58 = NameAndType        #56:#57       // diff:(Lscala/collection/Seq;)Ljava/lang/Object;
   #59 = Methodref          #55.#58       // scala/collection/immutable/List.diff:(Lscala/collection/Seq;)Ljava/lang/Object;
   #60 = Utf8               intersect
   #61 = NameAndType        #60:#57       // intersect:(Lscala/collection/Seq;)Ljava/lang/Object;
   #62 = Methodref          #55.#61       // scala/collection/immutable/List.intersect:(Lscala/collection/Seq;)Ljava/lang/Object;
   #63 = Utf8               (Ljava/lang/Object;)Ljava/lang/Object;
   #64 = MethodType         #63           //  (Ljava/lang/Object;)Ljava/lang/Object;
   #65 = Utf8               $anonfun$difference$4
   #66 = Utf8               (Lscala/collection/Map;Lscala/collection/Map;Ljava/lang/Object;)Lscala/Option;
   #67 = NameAndType        #65:#66       // $anonfun$difference$4:(Lscala/collection/Map;Lscala/collection/Map;Ljava/lang/Object;)Lscala/Option;
   #68 = Methodref          #2.#67        // org/scalactic/GenMapDiffer.$anonfun$difference$4:(Lscala/collection/Map;Lscala/collection/Map;Ljava/lang/Object;)Lscala/Option;
   #69 = MethodHandle       6:#68         // REF_invokeStatic org/scalactic/GenMapDiffer.$anonfun$difference$4:(Lscala/collection/Map;Lscala/collection/Map;Ljava/lang/Object;)Lscala/Option;
   #70 = Utf8               (Ljava/lang/Object;)Lscala/Option;
   #71 = MethodType         #70           //  (Ljava/lang/Object;)Lscala/Option;
   #72 = Integer            5
   #73 = Integer            1
   #74 = Utf8               java/lang/invoke/LambdaMetafactory
   #75 = Class              #74           // java/lang/invoke/LambdaMetafactory
   #76 = Utf8               altMetafactory
   #77 = Utf8               (Ljava/lang/invoke/MethodHandles$Lookup;Ljava/lang/String;Ljava/lang/invoke/MethodType;[Ljava/lang/Object;)Ljava/lang/invoke/CallSite;
   #78 = NameAndType        #76:#77       // altMetafactory:(Ljava/lang/invoke/MethodHandles$Lookup;Ljava/lang/String;Ljava/lang/invoke/MethodType;[Ljava/lang/Object;)Ljava/lang/invoke/CallSite;
   #79 = Methodref          #75.#78       // java/lang/invoke/LambdaMetafactory.altMetafactory:(Ljava/lang/invoke/MethodHandles$Lookup;Ljava/lang/String;Ljava/lang/invoke/MethodType;[Ljava/lang/Object;)Ljava/lang/invoke/CallSite;
   #80 = MethodHandle       6:#79         // REF_invokeStatic java/lang/invoke/LambdaMetafactory.altMetafactory:(Ljava/lang/invoke/MethodHandles$Lookup;Ljava/lang/String;Ljava/lang/invoke/MethodType;[Ljava/lang/Object;)Ljava/lang/invoke/CallSite;
   #81 = Utf8               apply
   #82 = Utf8               (Lscala/collection/Map;Lscala/collection/Map;)Lscala/Function1;
   #83 = NameAndType        #81:#82       // apply:(Lscala/collection/Map;Lscala/collection/Map;)Lscala/Function1;
   #84 = InvokeDynamic      #0:#83        // #0:apply:(Lscala/collection/Map;Lscala/collection/Map;)Lscala/Function1;
   #85 = Utf8               flatMap
   #86 = Utf8               (Lscala/Function1;)Lscala/collection/immutable/List;
   #87 = NameAndType        #85:#86       // flatMap:(Lscala/Function1;)Lscala/collection/immutable/List;
   #88 = Methodref          #55.#87       // scala/collection/immutable/List.flatMap:(Lscala/Function1;)Lscala/collection/immutable/List;
   #89 = Utf8               toSet
   #90 = Utf8               ()Lscala/collection/immutable/Set;
   #91 = NameAndType        #89:#90       // toSet:()Lscala/collection/immutable/Set;
   #92 = Methodref          #55.#91       // scala/collection/immutable/List.toSet:()Lscala/collection/immutable/Set;
   #93 = Utf8               $anonfun$difference$5
   #94 = Utf8               (Lscala/collection/Map;Ljava/lang/Object;)Lscala/Option;
   #95 = NameAndType        #93:#94       // $anonfun$difference$5:(Lscala/collection/Map;Ljava/lang/Object;)Lscala/Option;
   #96 = Methodref          #2.#95        // org/scalactic/GenMapDiffer.$anonfun$difference$5:(Lscala/collection/Map;Ljava/lang/Object;)Lscala/Option;
   #97 = MethodHandle       6:#96         // REF_invokeStatic org/scalactic/GenMapDiffer.$anonfun$difference$5:(Lscala/collection/Map;Ljava/lang/Object;)Lscala/Option;
   #98 = Utf8               (Lscala/collection/Map;)Lscala/Function1;
   #99 = NameAndType        #81:#98       // apply:(Lscala/collection/Map;)Lscala/Function1;
  #100 = InvokeDynamic      #1:#99        // #1:apply:(Lscala/collection/Map;)Lscala/Function1;
  #101 = Utf8               scala/collection/immutable/Set
  #102 = Class              #101          // scala/collection/immutable/Set
  #103 = Utf8               $plus$plus
  #104 = Utf8               (Lscala/collection/IterableOnce;)Lscala/collection/SetOps;
  #105 = NameAndType        #103:#104     // $plus$plus:(Lscala/collection/IterableOnce;)Lscala/collection/SetOps;
  #106 = InterfaceMethodref #102.#105     // scala/collection/immutable/Set.$plus$plus:(Lscala/collection/IterableOnce;)Lscala/collection/SetOps;
  #107 = Utf8               $anonfun$difference$6
  #108 = NameAndType        #107:#94      // $anonfun$difference$6:(Lscala/collection/Map;Ljava/lang/Object;)Lscala/Option;
  #109 = Methodref          #2.#108       // org/scalactic/GenMapDiffer.$anonfun$difference$6:(Lscala/collection/Map;Ljava/lang/Object;)Lscala/Option;
  #110 = MethodHandle       6:#109        // REF_invokeStatic org/scalactic/GenMapDiffer.$anonfun$difference$6:(Lscala/collection/Map;Ljava/lang/Object;)Lscala/Option;
  #111 = InvokeDynamic      #2:#99        // #2:apply:(Lscala/collection/Map;)Lscala/Function1;
  #112 = Utf8               scala/collection/SetOps
  #113 = Class              #112          // scala/collection/SetOps
  #114 = InterfaceMethodref #113.#105     // scala/collection/SetOps.$plus$plus:(Lscala/collection/IterableOnce;)Lscala/collection/SetOps;
  #115 = Utf8               org/scalactic/Differ$
  #116 = Class              #115          // org/scalactic/Differ$
  #117 = Utf8               MODULE$
  #118 = Utf8               Lorg/scalactic/Differ$;
  #119 = NameAndType        #117:#118     // MODULE$:Lorg/scalactic/Differ$;
  #120 = Fieldref           #116.#119     // org/scalactic/Differ$.MODULE$:Lorg/scalactic/Differ$;
  #121 = Utf8               simpleClassName
  #122 = Utf8               (Ljava/lang/Object;)Ljava/lang/String;
  #123 = NameAndType        #121:#122     // simpleClassName:(Ljava/lang/Object;)Ljava/lang/String;
  #124 = Methodref          #116.#123     // org/scalactic/Differ$.simpleClassName:(Ljava/lang/Object;)Ljava/lang/String;
  #125 = Utf8               isEmpty
  #126 = Utf8               ()Z
  #127 = NameAndType        #125:#126     // isEmpty:()Z
  #128 = InterfaceMethodref #102.#127     // scala/collection/immutable/Set.isEmpty:()Z
  #129 = Utf8               org/scalactic/PrettyPair
  #130 = Class              #129          // org/scalactic/PrettyPair
  #131 = Utf8               org/scalactic/Prettifier
  #132 = Class              #131          // org/scalactic/Prettifier
  #133 = NameAndType        #81:#122      // apply:(Ljava/lang/Object;)Ljava/lang/String;
  #134 = InterfaceMethodref #132.#133     // org/scalactic/Prettifier.apply:(Ljava/lang/Object;)Ljava/lang/String;
  #135 = Utf8               scala/None$
  #136 = Class              #135          // scala/None$
  #137 = Utf8               Lscala/None$;
  #138 = NameAndType        #117:#137     // MODULE$:Lscala/None$;
  #139 = Fieldref           #136.#138     // scala/None$.MODULE$:Lscala/None$;
  #140 = Utf8               (Ljava/lang/String;Ljava/lang/String;Lscala/Option;)V
  #141 = NameAndType        #31:#140      // "<init>":(Ljava/lang/String;Ljava/lang/String;Lscala/Option;)V
  #142 = Methodref          #130.#141     // org/scalactic/PrettyPair."<init>":(Ljava/lang/String;Ljava/lang/String;Lscala/Option;)V
  #143 = Utf8               scala/Some
  #144 = Class              #143          // scala/Some
  #145 = Utf8               java/lang/StringBuilder
  #146 = Class              #145          // java/lang/StringBuilder
  #147 = Integer            2
  #148 = Utf8               (I)V
  #149 = NameAndType        #31:#148      // "<init>":(I)V
  #150 = Methodref          #146.#149     // java/lang/StringBuilder."<init>":(I)V
  #151 = Utf8               append
  #152 = Utf8               (Ljava/lang/String;)Ljava/lang/StringBuilder;
  #153 = NameAndType        #151:#152     // append:(Ljava/lang/String;)Ljava/lang/StringBuilder;
  #154 = Methodref          #146.#153     // java/lang/StringBuilder.append:(Ljava/lang/String;)Ljava/lang/StringBuilder;
  #155 = Utf8               (
  #156 = String             #155          // (
  #157 = InterfaceMethodref #102.#52      // scala/collection/immutable/Set.toList:()Lscala/collection/immutable/List;
  #158 = Utf8               Lscala/math/Ordering$String$;
  #159 = NameAndType        #117:#158     // MODULE$:Lscala/math/Ordering$String$;
  #160 = Fieldref           #20.#159      // scala/math/Ordering$String$.MODULE$:Lscala/math/Ordering$String$;
  #161 = Utf8               sorted
  #162 = Utf8               (Lscala/math/Ordering;)Ljava/lang/Object;
  #163 = NameAndType        #161:#162     // sorted:(Lscala/math/Ordering;)Ljava/lang/Object;
  #164 = Methodref          #55.#163      // scala/collection/immutable/List.sorted:(Lscala/math/Ordering;)Ljava/lang/Object;
  #165 = Utf8               scala/collection/IterableOnceOps
  #166 = Class              #165          // scala/collection/IterableOnceOps
  #167 = Utf8               ,
  #168 = String             #167          // ,
  #169 = Utf8               mkString
  #170 = Utf8               (Ljava/lang/String;)Ljava/lang/String;
  #171 = NameAndType        #169:#170     // mkString:(Ljava/lang/String;)Ljava/lang/String;
  #172 = InterfaceMethodref #166.#171     // scala/collection/IterableOnceOps.mkString:(Ljava/lang/String;)Ljava/lang/String;
  #173 = Utf8               )
  #174 = String             #173          // )
  #175 = Utf8               toString
  #176 = Utf8               ()Ljava/lang/String;
  #177 = NameAndType        #175:#176     // toString:()Ljava/lang/String;
  #178 = Methodref          #146.#177     // java/lang/StringBuilder.toString:()Ljava/lang/String;
  #179 = Utf8               (Ljava/lang/Object;)V
  #180 = NameAndType        #31:#179      // "<init>":(Ljava/lang/Object;)V
  #181 = Methodref          #144.#180     // scala/Some."<init>":(Ljava/lang/Object;)V
  #182 = Utf8               leftKeySet
  #183 = Utf8               Lscala/collection/Set;
  #184 = Utf8               rightKeySet
  #185 = Utf8               missingKeyInRight
  #186 = Utf8               Lscala/collection/immutable/List;
  #187 = Utf8               missingKeyInLeft
  #188 = Utf8               intersectKeys
  #189 = Utf8               diffSet
  #190 = Utf8               Lscala/collection/immutable/Set;
  #191 = Utf8               shortName
  #192 = Utf8               Ljava/lang/String;
  #193 = Utf8               aMap
  #194 = Utf8               Ljava/lang/Object;
  #195 = Utf8               bMap
  #196 = Utf8               this
  #197 = Utf8               Lorg/scalactic/GenMapDiffer;
  #198 = Utf8               Lorg/scalactic/Prettifier;
  #199 = Utf8               java/lang/String
  #200 = Class              #199          // java/lang/String
  #201 = Utf8               x2$2
  #202 = Utf8               x3$2
  #203 = Utf8               k
  #204 = NameAndType        #81:#63       // apply:(Ljava/lang/Object;)Ljava/lang/Object;
  #205 = InterfaceMethodref #43.#204      // scala/collection/Map.apply:(Ljava/lang/Object;)Ljava/lang/Object;
  #206 = Utf8               (Lorg/scalactic/GenMapDiffer;Ljava/lang/Object;)V
  #207 = NameAndType        #31:#206      // "<init>":(Lorg/scalactic/GenMapDiffer;Ljava/lang/Object;)V
  #208 = Methodref          #18.#207      // org/scalactic/GenMapDiffer$$anonfun$1."<init>":(Lorg/scalactic/GenMapDiffer;Ljava/lang/Object;)V
  #209 = Utf8               collect
  #210 = Utf8               (Lscala/PartialFunction;)Ljava/lang/Object;
  #211 = NameAndType        #209:#210     // collect:(Lscala/PartialFunction;)Ljava/lang/Object;
  #212 = InterfaceMethodref #43.#211      // scala/collection/Map.collect:(Lscala/PartialFunction;)Ljava/lang/Object;
  #213 = Utf8               scala/collection/IterableOps
  #214 = Class              #213          // scala/collection/IterableOps
  #215 = Utf8               head
  #216 = NameAndType        #215:#36      // head:()Ljava/lang/Object;
  #217 = InterfaceMethodref #214.#216     // scala/collection/IterableOps.head:()Ljava/lang/Object;
  #218 = Utf8               scala/runtime/BoxesRunTime
  #219 = Class              #218          // scala/runtime/BoxesRunTime
  #220 = Utf8               equals
  #221 = Utf8               (Ljava/lang/Object;Ljava/lang/Object;)Z
  #222 = NameAndType        #220:#221     // equals:(Ljava/lang/Object;Ljava/lang/Object;)Z
  #223 = Methodref          #219.#222     // scala/runtime/BoxesRunTime.equals:(Ljava/lang/Object;Ljava/lang/Object;)Z
  #224 = Integer            6
  #225 = Methodref          #5.#177       // java/lang/Object.toString:()Ljava/lang/String;
  #226 = Utf8               :
  #227 = String             #226          // :
  #228 = Utf8               (Ljava/lang/Object;)Ljava/lang/StringBuilder;
  #229 = NameAndType        #151:#228     // append:(Ljava/lang/Object;)Ljava/lang/StringBuilder;
  #230 = Methodref          #146.#229     // java/lang/StringBuilder.append:(Ljava/lang/Object;)Ljava/lang/StringBuilder;
  #231 = Utf8                ->
  #232 = String             #231          //  ->
  #233 = Utf8               leftValue
  #234 = Utf8               rightValue
  #235 = Utf8               Lscala/collection/Map;
  #236 = Utf8               scala/Option
  #237 = Class              #236          // scala/Option
  #238 = Utf8               scala/Option$
  #239 = Class              #238          // scala/Option$
  #240 = Utf8               Lscala/Option$;
  #241 = NameAndType        #117:#240     // MODULE$:Lscala/Option$;
  #242 = Fieldref           #239.#241     // scala/Option$.MODULE$:Lscala/Option$;
  #243 = Utf8               : ->
  #244 = String             #243          // : ->
  #245 = NameAndType        #81:#70       // apply:(Ljava/lang/Object;)Lscala/Option;
  #246 = Methodref          #239.#245     // scala/Option$.apply:(Ljava/lang/Object;)Lscala/Option;
  #247 = Utf8               ()V
  #248 = NameAndType        #31:#247      // "<init>":()V
  #249 = Methodref          #5.#248       // java/lang/Object."<init>":()V
  #250 = Utf8               $deserializeLambda$
  #251 = Utf8               (Ljava/lang/invoke/SerializedLambda;)Ljava/lang/Object;
  #252 = Utf8               scala/runtime/LambdaDeserialize
  #253 = Class              #252          // scala/runtime/LambdaDeserialize
  #254 = Utf8               bootstrap
  #255 = Utf8               (Ljava/lang/invoke/MethodHandles$Lookup;Ljava/lang/String;Ljava/lang/invoke/MethodType;[Ljava/lang/invoke/MethodHandle;)Ljava/lang/invoke/CallSite;
  #256 = NameAndType        #254:#255     // bootstrap:(Ljava/lang/invoke/MethodHandles$Lookup;Ljava/lang/String;Ljava/lang/invoke/MethodType;[Ljava/lang/invoke/MethodHandle;)Ljava/lang/invoke/CallSite;
  #257 = Methodref          #253.#256     // scala/runtime/LambdaDeserialize.bootstrap:(Ljava/lang/invoke/MethodHandles$Lookup;Ljava/lang/String;Ljava/lang/invoke/MethodType;[Ljava/lang/invoke/MethodHandle;)Ljava/lang/invoke/CallSite;
  #258 = MethodHandle       6:#257        // REF_invokeStatic scala/runtime/LambdaDeserialize.bootstrap:(Ljava/lang/invoke/MethodHandles$Lookup;Ljava/lang/String;Ljava/lang/invoke/MethodType;[Ljava/lang/invoke/MethodHandle;)Ljava/lang/invoke/CallSite;
  #259 = Utf8               lambdaDeserialize
  #260 = NameAndType        #259:#251     // lambdaDeserialize:(Ljava/lang/invoke/SerializedLambda;)Ljava/lang/Object;
  #261 = InvokeDynamic      #3:#260       // #3:lambdaDeserialize:(Ljava/lang/invoke/SerializedLambda;)Ljava/lang/Object;
  #262 = Utf8               Code
  #263 = Utf8               StackMapTable
  #264 = Utf8               LineNumberTable
  #265 = Utf8               LocalVariableTable
  #266 = Utf8               MethodParameters
  #267 = Utf8               InnerClasses
  #268 = Utf8               Signature
  #269 = Utf8               SourceFile
  #270 = Utf8               RuntimeVisibleAnnotations
  #271 = Utf8               BootstrapMethods
  #272 = Utf8               ScalaInlineInfo
  #273 = Utf8               ScalaSig
{
  public org.scalactic.PrettyPair difference(java.lang.Object, java.lang.Object, org.scalactic.Prettifier);
    descriptor: (Ljava/lang/Object;Ljava/lang/Object;Lorg/scalactic/Prettifier;)Lorg/scalactic/PrettyPair;
    flags: (0x0001) ACC_PUBLIC
    Code:
      stack=9, locals=17, args_size=4
         0: new           #30                 // class scala/Tuple2
         3: dup
         4: aload_1
         5: aload_2
         6: invokespecial #34                 // Method scala/Tuple2."<init>":(Ljava/lang/Object;Ljava/lang/Object;)V
         9: astore        5
        11: aload         5
        13: ifnull        345
        16: aload         5
        18: invokevirtual #38                 // Method scala/Tuple2._1:()Ljava/lang/Object;
        21: astore        6
        23: aload         5
        25: invokevirtual #41                 // Method scala/Tuple2._2:()Ljava/lang/Object;
        28: astore        7
        30: aload         6
        32: instanceof    #43                 // class scala/collection/Map
        35: ifeq          342
        38: aload         6
        40: checkcast     #43                 // class scala/collection/Map
        43: astore        8
        45: aload         7
        47: instanceof    #43                 // class scala/collection/Map
        50: ifeq          339
        53: aload         7
        55: checkcast     #43                 // class scala/collection/Map
        58: astore        9
        60: aload         8
        62: invokeinterface #47,  1           // InterfaceMethod scala/collection/Map.keySet:()Lscala/collection/Set;
        67: astore        10
        69: aload         9
        71: invokeinterface #47,  1           // InterfaceMethod scala/collection/Map.keySet:()Lscala/collection/Set;
        76: astore        11
        78: aload         10
        80: invokeinterface #53,  1           // InterfaceMethod scala/collection/Set.toList:()Lscala/collection/immutable/List;
        85: aload         11
        87: invokeinterface #53,  1           // InterfaceMethod scala/collection/Set.toList:()Lscala/collection/immutable/List;
        92: invokevirtual #59                 // Method scala/collection/immutable/List.diff:(Lscala/collection/Seq;)Ljava/lang/Object;
        95: checkcast     #55                 // class scala/collection/immutable/List
        98: astore        12
       100: aload         11
       102: invokeinterface #53,  1           // InterfaceMethod scala/collection/Set.toList:()Lscala/collection/immutable/List;
       107: aload         10
       109: invokeinterface #53,  1           // InterfaceMethod scala/collection/Set.toList:()Lscala/collection/immutable/List;
       114: invokevirtual #59                 // Method scala/collection/immutable/List.diff:(Lscala/collection/Seq;)Ljava/lang/Object;
       117: checkcast     #55                 // class scala/collection/immutable/List
       120: astore        13
       122: aload         10
       124: invokeinterface #53,  1           // InterfaceMethod scala/collection/Set.toList:()Lscala/collection/immutable/List;
       129: aload         11
       131: invokeinterface #53,  1           // InterfaceMethod scala/collection/Set.toList:()Lscala/collection/immutable/List;
       136: invokevirtual #62                 // Method scala/collection/immutable/List.intersect:(Lscala/collection/Seq;)Ljava/lang/Object;
       139: checkcast     #55                 // class scala/collection/immutable/List
       142: astore        14
       144: aload         14
       146: aload         8
       148: aload         9
       150: invokedynamic #84,  0             // InvokeDynamic #0:apply:(Lscala/collection/Map;Lscala/collection/Map;)Lscala/Function1;
       155: invokevirtual #88                 // Method scala/collection/immutable/List.flatMap:(Lscala/Function1;)Lscala/collection/immutable/List;
       158: invokevirtual #92                 // Method scala/collection/immutable/List.toSet:()Lscala/collection/immutable/Set;
       161: aload         13
       163: aload         9
       165: invokedynamic #100,  0            // InvokeDynamic #1:apply:(Lscala/collection/Map;)Lscala/Function1;
       170: invokevirtual #88                 // Method scala/collection/immutable/List.flatMap:(Lscala/Function1;)Lscala/collection/immutable/List;
       173: invokevirtual #92                 // Method scala/collection/immutable/List.toSet:()Lscala/collection/immutable/Set;
       176: invokeinterface #106,  2          // InterfaceMethod scala/collection/immutable/Set.$plus$plus:(Lscala/collection/IterableOnce;)Lscala/collection/SetOps;
       181: aload         12
       183: aload         8
       185: invokedynamic #111,  0            // InvokeDynamic #2:apply:(Lscala/collection/Map;)Lscala/Function1;
       190: invokevirtual #88                 // Method scala/collection/immutable/List.flatMap:(Lscala/Function1;)Lscala/collection/immutable/List;
       193: invokevirtual #92                 // Method scala/collection/immutable/List.toSet:()Lscala/collection/immutable/Set;
       196: invokeinterface #114,  2          // InterfaceMethod scala/collection/SetOps.$plus$plus:(Lscala/collection/IterableOnce;)Lscala/collection/SetOps;
       201: checkcast     #102                // class scala/collection/immutable/Set
       204: astore        15
       206: getstatic     #120                // Field org/scalactic/Differ$.MODULE$:Lorg/scalactic/Differ$;
       209: aload         8
       211: invokevirtual #124                // Method org/scalactic/Differ$.simpleClassName:(Ljava/lang/Object;)Ljava/lang/String;
       214: astore        16
       216: aload         15
       218: invokeinterface #128,  1          // InterfaceMethod scala/collection/immutable/Set.isEmpty:()Z
       223: ifeq          253
       226: new           #130                // class org/scalactic/PrettyPair
       229: dup
       230: aload_3
       231: aload_1
       232: invokeinterface #134,  2          // InterfaceMethod org/scalactic/Prettifier.apply:(Ljava/lang/Object;)Ljava/lang/String;
       237: aload_3
       238: aload_2
       239: invokeinterface #134,  2          // InterfaceMethod org/scalactic/Prettifier.apply:(Ljava/lang/Object;)Ljava/lang/String;
       244: getstatic     #139                // Field scala/None$.MODULE$:Lscala/None$;
       247: invokespecial #142                // Method org/scalactic/PrettyPair."<init>":(Ljava/lang/String;Ljava/lang/String;Lscala/Option;)V
       250: goto          334
       253: new           #130                // class org/scalactic/PrettyPair
       256: dup
       257: aload_3
       258: aload_1
       259: invokeinterface #134,  2          // InterfaceMethod org/scalactic/Prettifier.apply:(Ljava/lang/Object;)Ljava/lang/String;
       264: aload_3
       265: aload_2
       266: invokeinterface #134,  2          // InterfaceMethod org/scalactic/Prettifier.apply:(Ljava/lang/Object;)Ljava/lang/String;
       271: new           #144                // class scala/Some
       274: dup
       275: new           #146                // class java/lang/StringBuilder
       278: dup
       279: ldc           #147                // int 2
       281: invokespecial #150                // Method java/lang/StringBuilder."<init>":(I)V
       284: aload         16
       286: invokevirtual #154                // Method java/lang/StringBuilder.append:(Ljava/lang/String;)Ljava/lang/StringBuilder;
       289: ldc           #156                // String (
       291: invokevirtual #154                // Method java/lang/StringBuilder.append:(Ljava/lang/String;)Ljava/lang/StringBuilder;
       294: aload         15
       296: invokeinterface #157,  1          // InterfaceMethod scala/collection/immutable/Set.toList:()Lscala/collection/immutable/List;
       301: getstatic     #160                // Field scala/math/Ordering$String$.MODULE$:Lscala/math/Ordering$String$;
       304: invokevirtual #164                // Method scala/collection/immutable/List.sorted:(Lscala/math/Ordering;)Ljava/lang/Object;
       307: checkcast     #166                // class scala/collection/IterableOnceOps
       310: ldc           #168                // String ,
       312: invokeinterface #172,  2          // InterfaceMethod scala/collection/IterableOnceOps.mkString:(Ljava/lang/String;)Ljava/lang/String;
       317: invokevirtual #154                // Method java/lang/StringBuilder.append:(Ljava/lang/String;)Ljava/lang/StringBuilder;
       320: ldc           #174                // String )
       322: invokevirtual #154                // Method java/lang/StringBuilder.append:(Ljava/lang/String;)Ljava/lang/StringBuilder;
       325: invokevirtual #178                // Method java/lang/StringBuilder.toString:()Ljava/lang/String;
       328: invokespecial #181                // Method scala/Some."<init>":(Ljava/lang/Object;)V
       331: invokespecial #142                // Method org/scalactic/PrettyPair."<init>":(Ljava/lang/String;Ljava/lang/String;Lscala/Option;)V
       334: astore        4
       336: goto          377
       339: goto          348
       342: goto          348
       345: goto          348
       348: new           #130                // class org/scalactic/PrettyPair
       351: dup
       352: aload_3
       353: aload_1
       354: invokeinterface #134,  2          // InterfaceMethod org/scalactic/Prettifier.apply:(Ljava/lang/Object;)Ljava/lang/String;
       359: aload_3
       360: aload_2
       361: invokeinterface #134,  2          // InterfaceMethod org/scalactic/Prettifier.apply:(Ljava/lang/Object;)Ljava/lang/String;
       366: getstatic     #139                // Field scala/None$.MODULE$:Lscala/None$;
       369: invokespecial #142                // Method org/scalactic/PrettyPair."<init>":(Ljava/lang/String;Ljava/lang/String;Lscala/Option;)V
       372: astore        4
       374: goto          377
       377: aload         4
       379: areturn
      StackMapTable: number_of_entries = 7
        frame_type = 255 /* full_frame */
          offset_delta = 253
          locals = [ class org/scalactic/GenMapDiffer, class java/lang/Object, class java/lang/Object, class org/scalactic/Prettifier, top, class scala/Tuple2, class java/lang/Object, class java/lang/Object, class scala/collection/Map, class scala/collection/Map, class scala/collection/Set, class scala/collection/Set, class scala/collection/immutable/List, class scala/collection/immutable/List, class scala/collection/immutable/List, class scala/collection/immutable/Set, class java/lang/String ]
          stack = []
        frame_type = 247 /* same_locals_1_stack_item_frame_extended */
          offset_delta = 80
          stack = [ class org/scalactic/PrettyPair ]
        frame_type = 255 /* full_frame */
          offset_delta = 4
          locals = [ class org/scalactic/GenMapDiffer, class java/lang/Object, class java/lang/Object, class org/scalactic/Prettifier, top, class scala/Tuple2, class java/lang/Object, class java/lang/Object, class scala/collection/Map ]
          stack = []
        frame_type = 250 /* chop */
          offset_delta = 2
        frame_type = 249 /* chop */
          offset_delta = 2
        frame_type = 2 /* same */
        frame_type = 255 /* full_frame */
          offset_delta = 28
          locals = [ class org/scalactic/GenMapDiffer, class java/lang/Object, class java/lang/Object, class org/scalactic/Prettifier, class org/scalactic/PrettyPair, class scala/Tuple2 ]
          stack = []
      LineNumberTable:
        line 183: 0
        line 184: 11
        line 185: 60
        line 186: 69
        line 187: 78
        line 188: 100
        line 189: 122
        line 191: 144
        line 205: 161
        line 209: 181
        line 214: 206
        line 215: 216
        line 216: 226
        line 218: 253
        line 184: 339
        line 221: 348
        line 183: 377
      LocalVariableTable:
        Start  Length  Slot  Name   Signature
           69     265    10 leftKeySet   Lscala/collection/Set;
           78     256    11 rightKeySet   Lscala/collection/Set;
          100     234    12 missingKeyInRight   Lscala/collection/immutable/List;
          122     212    13 missingKeyInLeft   Lscala/collection/immutable/List;
          144     190    14 intersectKeys   Lscala/collection/immutable/List;
          206     128    15 diffSet   Lscala/collection/immutable/Set;
          216     118    16 shortName   Ljava/lang/String;
           23     322     6  aMap   Ljava/lang/Object;
           30     315     7  bMap   Ljava/lang/Object;
            0     380     0  this   Lorg/scalactic/GenMapDiffer;
            0     380     1     a   Ljava/lang/Object;
            0     380     2     b   Ljava/lang/Object;
            0     380     3 prettifier   Lorg/scalactic/Prettifier;
    MethodParameters:
      Name                           Flags
      a                              final
      b                              final
      prettifier                     final

  public static final scala.Option $anonfun$difference$4(scala.collection.Map, scala.collection.Map, java.lang.Object);
    descriptor: (Lscala/collection/Map;Lscala/collection/Map;Ljava/lang/Object;)Lscala/Option;
    flags: (0x1019) ACC_PUBLIC, ACC_STATIC, ACC_FINAL, ACC_SYNTHETIC
    Code:
      stack=5, locals=5, args_size=3
         0: aload_0
         1: aload_2
         2: invokeinterface #205,  2          // InterfaceMethod scala/collection/Map.apply:(Ljava/lang/Object;)Ljava/lang/Object;
         7: astore_3
         8: aload_1
         9: new           #18                 // class org/scalactic/GenMapDiffer$$anonfun$1
        12: dup
        13: aconst_null
        14: aload_2
        15: invokespecial #208                // Method org/scalactic/GenMapDiffer$$anonfun$1."<init>":(Lorg/scalactic/GenMapDiffer;Ljava/lang/Object;)V
        18: invokeinterface #212,  2          // InterfaceMethod scala/collection/Map.collect:(Lscala/PartialFunction;)Ljava/lang/Object;
        23: checkcast     #214                // class scala/collection/IterableOps
        26: invokeinterface #217,  1          // InterfaceMethod scala/collection/IterableOps.head:()Ljava/lang/Object;
        31: astore        4
        33: aload_3
        34: aload         4
        36: invokestatic  #223                // Method scala/runtime/BoxesRunTime.equals:(Ljava/lang/Object;Ljava/lang/Object;)Z
        39: ifne          90
        42: new           #144                // class scala/Some
        45: dup
        46: new           #146                // class java/lang/StringBuilder
        49: dup
        50: ldc           #224                // int 6
        52: invokespecial #150                // Method java/lang/StringBuilder."<init>":(I)V
        55: aload_2
        56: invokevirtual #225                // Method java/lang/Object.toString:()Ljava/lang/String;
        59: invokevirtual #154                // Method java/lang/StringBuilder.append:(Ljava/lang/String;)Ljava/lang/StringBuilder;
        62: ldc           #227                // String :
        64: invokevirtual #154                // Method java/lang/StringBuilder.append:(Ljava/lang/String;)Ljava/lang/StringBuilder;
        67: aload_3
        68: invokevirtual #230                // Method java/lang/StringBuilder.append:(Ljava/lang/Object;)Ljava/lang/StringBuilder;
        71: ldc           #232                // String  ->
        73: invokevirtual #154                // Method java/lang/StringBuilder.append:(Ljava/lang/String;)Ljava/lang/StringBuilder;
        76: aload         4
        78: invokevirtual #230                // Method java/lang/StringBuilder.append:(Ljava/lang/Object;)Ljava/lang/StringBuilder;
        81: invokevirtual #178                // Method java/lang/StringBuilder.toString:()Ljava/lang/String;
        84: invokespecial #181                // Method scala/Some."<init>":(Ljava/lang/Object;)V
        87: goto          93
        90: getstatic     #139                // Field scala/None$.MODULE$:Lscala/None$;
        93: areturn
      StackMapTable: number_of_entries = 2
        frame_type = 253 /* append */
          offset_delta = 90
          locals = [ class java/lang/Object, class java/lang/Object ]
        frame_type = 66 /* same_locals_1_stack_item */
          stack = [ class scala/Option ]
      LineNumberTable:
        line 192: 0
        line 199: 8
        line 200: 33
        line 201: 42
        line 203: 90
      LocalVariableTable:
        Start  Length  Slot  Name   Signature
            8      85     3 leftValue   Ljava/lang/Object;
           33      60     4 rightValue   Ljava/lang/Object;
            0      94     0  x2$2   Lscala/collection/Map;
            0      94     1  x3$2   Lscala/collection/Map;
            0      94     2     k   Ljava/lang/Object;
    MethodParameters:
      Name                           Flags
      x2$2                           final
      x3$2                           final
      k                              final

  public static final scala.Option $anonfun$difference$5(scala.collection.Map, java.lang.Object);
    descriptor: (Lscala/collection/Map;Ljava/lang/Object;)Lscala/Option;
    flags: (0x1019) ACC_PUBLIC, ACC_STATIC, ACC_FINAL, ACC_SYNTHETIC
    Code:
      stack=4, locals=3, args_size=2
         0: aload_0
         1: aload_1
         2: invokeinterface #205,  2          // InterfaceMethod scala/collection/Map.apply:(Ljava/lang/Object;)Ljava/lang/Object;
         7: astore_2
         8: getstatic     #242                // Field scala/Option$.MODULE$:Lscala/Option$;
        11: new           #146                // class java/lang/StringBuilder
        14: dup
        15: ldc           #72                 // int 5
        17: invokespecial #150                // Method java/lang/StringBuilder."<init>":(I)V
        20: aload_1
        21: invokevirtual #225                // Method java/lang/Object.toString:()Ljava/lang/String;
        24: invokevirtual #154                // Method java/lang/StringBuilder.append:(Ljava/lang/String;)Ljava/lang/StringBuilder;
        27: ldc           #244                // String : ->
        29: invokevirtual #154                // Method java/lang/StringBuilder.append:(Ljava/lang/String;)Ljava/lang/StringBuilder;
        32: aload_2
        33: invokevirtual #230                // Method java/lang/StringBuilder.append:(Ljava/lang/Object;)Ljava/lang/StringBuilder;
        36: invokevirtual #178                // Method java/lang/StringBuilder.toString:()Ljava/lang/String;
        39: invokevirtual #246                // Method scala/Option$.apply:(Ljava/lang/Object;)Lscala/Option;
        42: areturn
      LineNumberTable:
        line 206: 0
        line 207: 8
      LocalVariableTable:
        Start  Length  Slot  Name   Signature
            8      34     2 rightValue   Ljava/lang/Object;
            0      43     0  x3$2   Lscala/collection/Map;
            0      43     1     k   Ljava/lang/Object;
    MethodParameters:
      Name                           Flags
      x3$2                           final
      k                              final

  public static final scala.Option $anonfun$difference$6(scala.collection.Map, java.lang.Object);
    descriptor: (Lscala/collection/Map;Ljava/lang/Object;)Lscala/Option;
    flags: (0x1019) ACC_PUBLIC, ACC_STATIC, ACC_FINAL, ACC_SYNTHETIC
    Code:
      stack=4, locals=3, args_size=2
         0: aload_0
         1: aload_1
         2: invokeinterface #205,  2          // InterfaceMethod scala/collection/Map.apply:(Ljava/lang/Object;)Ljava/lang/Object;
         7: astore_2
         8: getstatic     #242                // Field scala/Option$.MODULE$:Lscala/Option$;
        11: new           #146                // class java/lang/StringBuilder
        14: dup
        15: ldc           #224                // int 6
        17: invokespecial #150                // Method java/lang/StringBuilder."<init>":(I)V
        20: aload_1
        21: invokevirtual #225                // Method java/lang/Object.toString:()Ljava/lang/String;
        24: invokevirtual #154                // Method java/lang/StringBuilder.append:(Ljava/lang/String;)Ljava/lang/StringBuilder;
        27: ldc           #227                // String :
        29: invokevirtual #154                // Method java/lang/StringBuilder.append:(Ljava/lang/String;)Ljava/lang/StringBuilder;
        32: aload_2
        33: invokevirtual #230                // Method java/lang/StringBuilder.append:(Ljava/lang/Object;)Ljava/lang/StringBuilder;
        36: ldc           #232                // String  ->
        38: invokevirtual #154                // Method java/lang/StringBuilder.append:(Ljava/lang/String;)Ljava/lang/StringBuilder;
        41: invokevirtual #178                // Method java/lang/StringBuilder.toString:()Ljava/lang/String;
        44: invokevirtual #246                // Method scala/Option$.apply:(Ljava/lang/Object;)Lscala/Option;
        47: areturn
      LineNumberTable:
        line 210: 0
        line 211: 8
      LocalVariableTable:
        Start  Length  Slot  Name   Signature
            8      39     2 leftValue   Ljava/lang/Object;
            0      48     0  x2$2   Lscala/collection/Map;
            0      48     1     k   Ljava/lang/Object;
    MethodParameters:
      Name                           Flags
      x2$2                           final
      k                              final

  public org.scalactic.GenMapDiffer();
    descriptor: ()V
    flags: (0x0001) ACC_PUBLIC
    Code:
      stack=1, locals=1, args_size=1
         0: aload_0
         1: invokespecial #249                // Method java/lang/Object."<init>":()V
         4: return
      LineNumberTable:
        line 180: 0
      LocalVariableTable:
        Start  Length  Slot  Name   Signature
            0       5     0  this   Lorg/scalactic/GenMapDiffer;

  private static java.lang.Object $deserializeLambda$(java.lang.invoke.SerializedLambda);
    descriptor: (Ljava/lang/invoke/SerializedLambda;)Ljava/lang/Object;
    flags: (0x100a) ACC_PRIVATE, ACC_STATIC, ACC_SYNTHETIC
    Code:
      stack=1, locals=1, args_size=1
         0: aload_0
         1: invokedynamic #261,  0            // InvokeDynamic #3:lambdaDeserialize:(Ljava/lang/invoke/SerializedLambda;)Ljava/lang/Object;
         6: areturn
}
InnerClasses:
  public static final #16= #13 of #15;    // Lookup=class java/lang/invoke/MethodHandles$Lookup of class java/lang/invoke/MethodHandles
  public final #18;                       // class org/scalactic/GenMapDiffer$$anonfun$1
  public static #23= #20 of #22;          // String$=class scala/math/Ordering$String$ of class scala/math/Ordering
Signature: #3                           // <K:Ljava/lang/Object;V:Ljava/lang/Object;>Ljava/lang/Object;Lorg/scalactic/Differ;
SourceFile: "Differ.scala"
RuntimeVisibleAnnotations:
  0: #9(#10=s#11)
    scala.reflect.ScalaSignature(
      bytes="\u0006\u0005q2QAB\u0004\u0001\u000f-AQa\u0006\u0001\u0005\u0002eAQ!\u000b\u0001\u0005\u0002):aaN\u0004\t\u0002\u001dAdA\u0002\u0004\b\u0011\u00039\u0011\bC\u0003\u0018\t\u0011\u00051H\u0001\u0007HK:l\u0015\r\u001d#jM\u001a,\'O\u0003\u0002\t\u0013\u0005I1oY1mC\u000e$\u0018n\u0019\u0006\u0002\u0015\u0005\u0019qN]4\u0016\u00071ireE\u0002\u0001\u001bM\u0001\"AD\t\u000e\u0003=Q\u0011\u0001E\u0001\u0006g\u000e\fG.Y\u0005\u0003%=\u0011a!\u00118z%\u00164\u0007C\u0001\u000b\u0016\u001b\u00059\u0011B\u0001\f\b\u0005\u0019!\u0015N\u001a4fe\u00061A(\u001b8jiz\u001a\u0001\u0001F\u0001\u001b!\u0011!\u0002a\u0007\u0014\u0011\u0005qiB\u0002\u0001\u0003\u0006=\u0001\u0011\ra\b\u0002\u0002\u0017F\u0011\u0001e\t\t\u0003\u001d\u0005J!AI\b\u0003\u000f9{G\u000f[5oOB\u0011a\u0002J\u0005\u0003K=\u00111!\u00118z!\tar\u0005B\u0003)\u0001\t\u0007qDA\u0001W\u0003)!\u0017N\u001a4fe\u0016t7-\u001a\u000b\u0005W9\u0002$\u0007\u0005\u0002\u0015Y%\u0011Qf\u0002\u0002\u000b!J,G\u000f^=QC&\u0014\b\"B\u0018\u0003\u0001\u0004\u0019\u0013!A1\t\u000bE\u0012\u0001\u0019A\u0012\u0002\u0003\tDQa\r\u0002A\u0002Q\n!\u0002\u001d:fiRLg-[3s!\t!R\'\u0003\u00027\u000f\tQ\u0001K]3ui&4\u0017.\u001a:\u0002\u0019\u001d+g.T1q\t&4g-\u001a:\u0011\u0005Q!1C\u0001\u0003;!\u0011!\u0002aI\u0012\u0015\u0003a\u0002"
    )
BootstrapMethods:
  0: #80 REF_invokeStatic java/lang/invoke/LambdaMetafactory.altMetafactory:(Ljava/lang/invoke/MethodHandles$Lookup;Ljava/lang/String;Ljava/lang/invoke/MethodType;[Ljava/lang/Object;)Ljava/lang/invoke/CallSite;
    Method arguments:
      #64 (Ljava/lang/Object;)Ljava/lang/Object;
      #69 REF_invokeStatic org/scalactic/GenMapDiffer.$anonfun$difference$4:(Lscala/collection/Map;Lscala/collection/Map;Ljava/lang/Object;)Lscala/Option;
      #71 (Ljava/lang/Object;)Lscala/Option;
      #72 5
      #73 1
      #71 (Ljava/lang/Object;)Lscala/Option;
  1: #80 REF_invokeStatic java/lang/invoke/LambdaMetafactory.altMetafactory:(Ljava/lang/invoke/MethodHandles$Lookup;Ljava/lang/String;Ljava/lang/invoke/MethodType;[Ljava/lang/Object;)Ljava/lang/invoke/CallSite;
    Method arguments:
      #64 (Ljava/lang/Object;)Ljava/lang/Object;
      #97 REF_invokeStatic org/scalactic/GenMapDiffer.$anonfun$difference$5:(Lscala/collection/Map;Ljava/lang/Object;)Lscala/Option;
      #71 (Ljava/lang/Object;)Lscala/Option;
      #72 5
      #73 1
      #71 (Ljava/lang/Object;)Lscala/Option;
  2: #80 REF_invokeStatic java/lang/invoke/LambdaMetafactory.altMetafactory:(Ljava/lang/invoke/MethodHandles$Lookup;Ljava/lang/String;Ljava/lang/invoke/MethodType;[Ljava/lang/Object;)Ljava/lang/invoke/CallSite;
    Method arguments:
      #64 (Ljava/lang/Object;)Ljava/lang/Object;
      #110 REF_invokeStatic org/scalactic/GenMapDiffer.$anonfun$difference$6:(Lscala/collection/Map;Ljava/lang/Object;)Lscala/Option;
      #71 (Ljava/lang/Object;)Lscala/Option;
      #72 5
      #73 1
      #71 (Ljava/lang/Object;)Lscala/Option;
  3: #258 REF_invokeStatic scala/runtime/LambdaDeserialize.bootstrap:(Ljava/lang/invoke/MethodHandles$Lookup;Ljava/lang/String;Ljava/lang/invoke/MethodType;[Ljava/lang/invoke/MethodHandle;)Ljava/lang/invoke/CallSite;
    Method arguments:
      #69 REF_invokeStatic org/scalactic/GenMapDiffer.$anonfun$difference$4:(Lscala/collection/Map;Lscala/collection/Map;Ljava/lang/Object;)Lscala/Option;
      #97 REF_invokeStatic org/scalactic/GenMapDiffer.$anonfun$difference$5:(Lscala/collection/Map;Ljava/lang/Object;)Lscala/Option;
      #110 REF_invokeStatic org/scalactic/GenMapDiffer.$anonfun$difference$6:(Lscala/collection/Map;Ljava/lang/Object;)Lscala/Option;
  ScalaInlineInfo: length = 0x1D (unknown attribute)
   01 00 00 05 00 41 00 42 01 00 5D 00 5E 01 00 6B
   00 5E 01 00 1F 00 F7 00 00 18 00 19 00
  ScalaSig: length = 0x3 (unknown attribute)
   05 02 00
