Classfile /Users/mw/Projects/slang-braindump/.jar/jar8/assemble/slang-braindump/assemble/content/org/scalactic/NameUtil$.class
  Last modified May 29, 2022; size 3504 bytes
  SHA-256 checksum 6bc1b07318a3ee88280735eec2421205f2170e2e81adbb50054867a684dc5a64
  Compiled from "NameUtil.scala"
public final class org.scalactic.NameUtil$
  minor version: 0
  major version: 52
  flags: (0x0031) ACC_PUBLIC, ACC_FINAL, ACC_SUPER
  this_class: #2                          // org/scalactic/NameUtil$
  super_class: #4                         // java/lang/Object
  interfaces: 0, fields: 1, methods: 8, attributes: 5
Constant pool:
    #1 = Utf8               org/scalactic/NameUtil$
    #2 = Class              #1            // org/scalactic/NameUtil$
    #3 = Utf8               java/lang/Object
    #4 = Class              #3            // java/lang/Object
    #5 = Utf8               NameUtil.scala
    #6 = Utf8               java/lang/invoke/MethodHandles$Lookup
    #7 = Class              #6            // java/lang/invoke/MethodHandles$Lookup
    #8 = Utf8               java/lang/invoke/MethodHandles
    #9 = Class              #8            // java/lang/invoke/MethodHandles
   #10 = Utf8               Lookup
   #11 = Utf8               MODULE$
   #12 = Utf8               Lorg/scalactic/NameUtil$;
   #13 = Utf8               <clinit>
   #14 = Utf8               ()V
   #15 = Utf8               <init>
   #16 = NameAndType        #15:#14       // "<init>":()V
   #17 = Methodref          #2.#16        // org/scalactic/NameUtil$."<init>":()V
   #18 = NameAndType        #11:#12       // MODULE$:Lorg/scalactic/NameUtil$;
   #19 = Fieldref           #2.#18        // org/scalactic/NameUtil$.MODULE$:Lorg/scalactic/NameUtil$;
   #20 = Utf8               stripDollars
   #21 = Utf8               (Ljava/lang/String;)Ljava/lang/String;
   #22 = Utf8               s
   #23 = Utf8               java/lang/String
   #24 = Class              #23           // java/lang/String
   #25 = Utf8               lastIndexOf
   #26 = Utf8               (I)I
   #27 = NameAndType        #25:#26       // lastIndexOf:(I)I
   #28 = Methodref          #24.#27       // java/lang/String.lastIndexOf:(I)I
   #29 = Utf8               length
   #30 = Utf8               ()I
   #31 = NameAndType        #29:#30       // length:()I
   #32 = Methodref          #24.#31       // java/lang/String.length:()I
   #33 = Utf8               $iw$
   #34 = String             #33           // $iw$
   #35 = Utf8               contains
   #36 = Utf8               (Ljava/lang/CharSequence;)Z
   #37 = NameAndType        #35:#36       // contains:(Ljava/lang/CharSequence;)Z
   #38 = Methodref          #24.#37       // java/lang/String.contains:(Ljava/lang/CharSequence;)Z
   #39 = Utf8               substring
   #40 = Utf8               (I)Ljava/lang/String;
   #41 = NameAndType        #39:#40       // substring:(I)Ljava/lang/String;
   #42 = Methodref          #24.#41       // java/lang/String.substring:(I)Ljava/lang/String;
   #43 = Utf8               scala/collection/StringOps$
   #44 = Class              #43           // scala/collection/StringOps$
   #45 = Utf8               Lscala/collection/StringOps$;
   #46 = NameAndType        #11:#45       // MODULE$:Lscala/collection/StringOps$;
   #47 = Fieldref           #44.#46       // scala/collection/StringOps$.MODULE$:Lscala/collection/StringOps$;
   #48 = Utf8               scala/Predef$
   #49 = Class              #48           // scala/Predef$
   #50 = Utf8               Lscala/Predef$;
   #51 = NameAndType        #11:#50       // MODULE$:Lscala/Predef$;
   #52 = Fieldref           #49.#51       // scala/Predef$.MODULE$:Lscala/Predef$;
   #53 = Utf8               augmentString
   #54 = NameAndType        #53:#21       // augmentString:(Ljava/lang/String;)Ljava/lang/String;
   #55 = Methodref          #49.#54       // scala/Predef$.augmentString:(Ljava/lang/String;)Ljava/lang/String;
   #56 = Utf8               reverse$extension
   #57 = NameAndType        #56:#21       // reverse$extension:(Ljava/lang/String;)Ljava/lang/String;
   #58 = Methodref          #44.#57       // scala/collection/StringOps$.reverse$extension:(Ljava/lang/String;)Ljava/lang/String;
   #59 = Utf8               (Ljava/lang/Object;)Ljava/lang/Object;
   #60 = MethodType         #59           //  (Ljava/lang/Object;)Ljava/lang/Object;
   #61 = Utf8               $anonfun$stripDollars$1$adapted
   #62 = NameAndType        #61:#59       // $anonfun$stripDollars$1$adapted:(Ljava/lang/Object;)Ljava/lang/Object;
   #63 = Methodref          #2.#62        // org/scalactic/NameUtil$.$anonfun$stripDollars$1$adapted:(Ljava/lang/Object;)Ljava/lang/Object;
   #64 = MethodHandle       6:#63         // REF_invokeStatic org/scalactic/NameUtil$.$anonfun$stripDollars$1$adapted:(Ljava/lang/Object;)Ljava/lang/Object;
   #65 = Integer            1
   #66 = Utf8               java/lang/invoke/LambdaMetafactory
   #67 = Class              #66           // java/lang/invoke/LambdaMetafactory
   #68 = Utf8               altMetafactory
   #69 = Utf8               (Ljava/lang/invoke/MethodHandles$Lookup;Ljava/lang/String;Ljava/lang/invoke/MethodType;[Ljava/lang/Object;)Ljava/lang/invoke/CallSite;
   #70 = NameAndType        #68:#69       // altMetafactory:(Ljava/lang/invoke/MethodHandles$Lookup;Ljava/lang/String;Ljava/lang/invoke/MethodType;[Ljava/lang/Object;)Ljava/lang/invoke/CallSite;
   #71 = Methodref          #67.#70       // java/lang/invoke/LambdaMetafactory.altMetafactory:(Ljava/lang/invoke/MethodHandles$Lookup;Ljava/lang/String;Ljava/lang/invoke/MethodType;[Ljava/lang/Object;)Ljava/lang/invoke/CallSite;
   #72 = MethodHandle       6:#71         // REF_invokeStatic java/lang/invoke/LambdaMetafactory.altMetafactory:(Ljava/lang/invoke/MethodHandles$Lookup;Ljava/lang/String;Ljava/lang/invoke/MethodType;[Ljava/lang/Object;)Ljava/lang/invoke/CallSite;
   #73 = Utf8               apply
   #74 = Utf8               ()Lscala/Function1;
   #75 = NameAndType        #73:#74       // apply:()Lscala/Function1;
   #76 = InvokeDynamic      #0:#75        // #0:apply:()Lscala/Function1;
   #77 = Utf8               find$extension
   #78 = Utf8               (Ljava/lang/String;Lscala/Function1;)Lscala/Option;
   #79 = NameAndType        #77:#78       // find$extension:(Ljava/lang/String;Lscala/Function1;)Lscala/Option;
   #80 = Methodref          #44.#79       // scala/collection/StringOps$.find$extension:(Ljava/lang/String;Lscala/Function1;)Lscala/Option;
   #81 = Utf8               scala/None$
   #82 = Class              #81           // scala/None$
   #83 = Utf8               Lscala/None$;
   #84 = NameAndType        #11:#83       // MODULE$:Lscala/None$;
   #85 = Fieldref           #82.#84       // scala/None$.MODULE$:Lscala/None$;
   #86 = Utf8               equals
   #87 = Utf8               (Ljava/lang/Object;)Z
   #88 = NameAndType        #86:#87       // equals:(Ljava/lang/Object;)Z
   #89 = Methodref          #4.#88        // java/lang/Object.equals:(Ljava/lang/Object;)Z
   #90 = Utf8               scala/Some
   #91 = Class              #90           // scala/Some
   #92 = Utf8               value
   #93 = Utf8               ()Ljava/lang/Object;
   #94 = NameAndType        #92:#93       // value:()Ljava/lang/Object;
   #95 = Methodref          #91.#94       // scala/Some.value:()Ljava/lang/Object;
   #96 = Utf8               scala/runtime/BoxesRunTime
   #97 = Class              #96           // scala/runtime/BoxesRunTime
   #98 = Utf8               unboxToChar
   #99 = Utf8               (Ljava/lang/Object;)C
  #100 = NameAndType        #98:#99       // unboxToChar:(Ljava/lang/Object;)C
  #101 = Methodref          #97.#100      // scala/runtime/BoxesRunTime.unboxToChar:(Ljava/lang/Object;)C
  #102 = Utf8               (II)Ljava/lang/String;
  #103 = NameAndType        #39:#102      // substring:(II)Ljava/lang/String;
  #104 = Methodref          #24.#103      // java/lang/String.substring:(II)Ljava/lang/String;
  #105 = Utf8               scala/MatchError
  #106 = Class              #105          // scala/MatchError
  #107 = Utf8               (Ljava/lang/Object;)V
  #108 = NameAndType        #15:#107      // "<init>":(Ljava/lang/Object;)V
  #109 = Methodref          #106.#108     // scala/MatchError."<init>":(Ljava/lang/Object;)V
  #110 = Utf8               lastNonDollarIndex
  #111 = Utf8               I
  #112 = Utf8               c
  #113 = Utf8               C
  #114 = Utf8               lastNonDollarChar
  #115 = Utf8               Lscala/Option;
  #116 = Utf8               lastDollarIndex
  #117 = Utf8               this
  #118 = Utf8               Ljava/lang/String;
  #119 = Utf8               scala/Option
  #120 = Class              #119          // scala/Option
  #121 = Utf8               getSimpleNameOfAnObjectsClass
  #122 = Utf8               (Ljava/lang/Object;)Ljava/lang/String;
  #123 = Utf8               o
  #124 = Utf8               getClass
  #125 = Utf8               ()Ljava/lang/Class;
  #126 = NameAndType        #124:#125     // getClass:()Ljava/lang/Class;
  #127 = Methodref          #4.#126       // java/lang/Object.getClass:()Ljava/lang/Class;
  #128 = Utf8               java/lang/Class
  #129 = Class              #128          // java/lang/Class
  #130 = Utf8               getName
  #131 = Utf8               ()Ljava/lang/String;
  #132 = NameAndType        #130:#131     // getName:()Ljava/lang/String;
  #133 = Methodref          #129.#132     // java/lang/Class.getName:()Ljava/lang/String;
  #134 = Utf8               parseSimpleName
  #135 = NameAndType        #134:#21      // parseSimpleName:(Ljava/lang/String;)Ljava/lang/String;
  #136 = Methodref          #2.#135       // org/scalactic/NameUtil$.parseSimpleName:(Ljava/lang/String;)Ljava/lang/String;
  #137 = NameAndType        #20:#21       // stripDollars:(Ljava/lang/String;)Ljava/lang/String;
  #138 = Methodref          #2.#137       // org/scalactic/NameUtil$.stripDollars:(Ljava/lang/String;)Ljava/lang/String;
  #139 = Utf8               Ljava/lang/Object;
  #140 = Utf8               fullyQualifiedName
  #141 = Utf8               dotPos
  #142 = Utf8               $anonfun$stripDollars$1
  #143 = Utf8               (C)Z
  #144 = Utf8               x$1
  #145 = Methodref          #4.#16        // java/lang/Object."<init>":()V
  #146 = NameAndType        #142:#143     // $anonfun$stripDollars$1:(C)Z
  #147 = Methodref          #2.#146       // org/scalactic/NameUtil$.$anonfun$stripDollars$1:(C)Z
  #148 = Utf8               boxToBoolean
  #149 = Utf8               (Z)Ljava/lang/Boolean;
  #150 = NameAndType        #148:#149     // boxToBoolean:(Z)Ljava/lang/Boolean;
  #151 = Methodref          #97.#150      // scala/runtime/BoxesRunTime.boxToBoolean:(Z)Ljava/lang/Boolean;
  #152 = Utf8               $deserializeLambda$
  #153 = Utf8               (Ljava/lang/invoke/SerializedLambda;)Ljava/lang/Object;
  #154 = Utf8               scala/runtime/LambdaDeserialize
  #155 = Class              #154          // scala/runtime/LambdaDeserialize
  #156 = Utf8               bootstrap
  #157 = Utf8               (Ljava/lang/invoke/MethodHandles$Lookup;Ljava/lang/String;Ljava/lang/invoke/MethodType;[Ljava/lang/invoke/MethodHandle;)Ljava/lang/invoke/CallSite;
  #158 = NameAndType        #156:#157     // bootstrap:(Ljava/lang/invoke/MethodHandles$Lookup;Ljava/lang/String;Ljava/lang/invoke/MethodType;[Ljava/lang/invoke/MethodHandle;)Ljava/lang/invoke/CallSite;
  #159 = Methodref          #155.#158     // scala/runtime/LambdaDeserialize.bootstrap:(Ljava/lang/invoke/MethodHandles$Lookup;Ljava/lang/String;Ljava/lang/invoke/MethodType;[Ljava/lang/invoke/MethodHandle;)Ljava/lang/invoke/CallSite;
  #160 = MethodHandle       6:#159        // REF_invokeStatic scala/runtime/LambdaDeserialize.bootstrap:(Ljava/lang/invoke/MethodHandles$Lookup;Ljava/lang/String;Ljava/lang/invoke/MethodType;[Ljava/lang/invoke/MethodHandle;)Ljava/lang/invoke/CallSite;
  #161 = Utf8               lambdaDeserialize
  #162 = NameAndType        #161:#153     // lambdaDeserialize:(Ljava/lang/invoke/SerializedLambda;)Ljava/lang/Object;
  #163 = InvokeDynamic      #1:#162       // #1:lambdaDeserialize:(Ljava/lang/invoke/SerializedLambda;)Ljava/lang/Object;
  #164 = Utf8               Code
  #165 = Utf8               LineNumberTable
  #166 = Utf8               StackMapTable
  #167 = Utf8               LocalVariableTable
  #168 = Utf8               MethodParameters
  #169 = Utf8               InnerClasses
  #170 = Utf8               SourceFile
  #171 = Utf8               BootstrapMethods
  #172 = Utf8               ScalaInlineInfo
  #173 = Utf8               Scala
{
  public static final org.scalactic.NameUtil$ MODULE$;
    descriptor: Lorg/scalactic/NameUtil$;
    flags: (0x0019) ACC_PUBLIC, ACC_STATIC, ACC_FINAL

  public static {};
    descriptor: ()V
    flags: (0x0009) ACC_PUBLIC, ACC_STATIC
    Code:
      stack=2, locals=0, args_size=0
         0: new           #2                  // class org/scalactic/NameUtil$
         3: dup
         4: invokespecial #17                 // Method "<init>":()V
         7: putstatic     #19                 // Field MODULE$:Lorg/scalactic/NameUtil$;
        10: return
      LineNumberTable:
        line 18: 0

  public java.lang.String stripDollars(java.lang.String);
    descriptor: (Ljava/lang/String;)Ljava/lang/String;
    flags: (0x0001) ACC_PUBLIC
    Code:
      stack=5, locals=10, args_size=2
         0: aload_1
         1: bipush        36
         3: invokevirtual #28                 // Method java/lang/String.lastIndexOf:(I)I
         6: istore        4
         8: iload         4
        10: aload_1
        11: invokevirtual #32                 // Method java/lang/String.length:()I
        14: iconst_1
        15: isub
        16: if_icmpge     49
        19: iload         4
        21: iconst_m1
        22: if_icmpeq     34
        25: aload_1
        26: ldc           #34                 // String $iw$
        28: invokevirtual #38                 // Method java/lang/String.contains:(Ljava/lang/CharSequence;)Z
        31: ifne          38
        34: aload_1
        35: goto          46
        38: aload_1
        39: iload         4
        41: iconst_1
        42: iadd
        43: invokevirtual #42                 // Method java/lang/String.substring:(I)Ljava/lang/String;
        46: goto          178
        49: getstatic     #47                 // Field scala/collection/StringOps$.MODULE$:Lscala/collection/StringOps$;
        52: getstatic     #52                 // Field scala/Predef$.MODULE$:Lscala/Predef$;
        55: getstatic     #47                 // Field scala/collection/StringOps$.MODULE$:Lscala/collection/StringOps$;
        58: getstatic     #52                 // Field scala/Predef$.MODULE$:Lscala/Predef$;
        61: aload_1
        62: invokevirtual #55                 // Method scala/Predef$.augmentString:(Ljava/lang/String;)Ljava/lang/String;
        65: invokevirtual #58                 // Method scala/collection/StringOps$.reverse$extension:(Ljava/lang/String;)Ljava/lang/String;
        68: invokevirtual #55                 // Method scala/Predef$.augmentString:(Ljava/lang/String;)Ljava/lang/String;
        71: invokedynamic #76,  0             // InvokeDynamic #0:apply:()Lscala/Function1;
        76: invokevirtual #80                 // Method scala/collection/StringOps$.find$extension:(Ljava/lang/String;Lscala/Function1;)Lscala/Option;
        79: astore        5
        81: aload         5
        83: astore        6
        85: getstatic     #85                 // Field scala/None$.MODULE$:Lscala/None$;
        88: aload         6
        90: invokevirtual #89                 // Method java/lang/Object.equals:(Ljava/lang/Object;)Z
        93: ifeq          101
        96: aload_1
        97: astore_3
        98: goto          177
       101: goto          104
       104: aload         6
       106: instanceof    #91                 // class scala/Some
       109: ifeq          164
       112: aload         6
       114: checkcast     #91                 // class scala/Some
       117: astore        7
       119: aload         7
       121: invokevirtual #95                 // Method scala/Some.value:()Ljava/lang/Object;
       124: invokestatic  #101                // Method scala/runtime/BoxesRunTime.unboxToChar:(Ljava/lang/Object;)C
       127: istore        8
       129: aload_1
       130: iload         8
       132: invokevirtual #28                 // Method java/lang/String.lastIndexOf:(I)I
       135: istore        9
       137: iload         9
       139: iconst_m1
       140: if_icmpne     147
       143: aload_1
       144: goto          160
       147: aload_1
       148: iconst_0
       149: iload         9
       151: iconst_1
       152: iadd
       153: invokevirtual #104                // Method java/lang/String.substring:(II)Ljava/lang/String;
       156: astore_1
       157: goto          0
       160: astore_3
       161: goto          177
       164: goto          167
       167: new           #106                // class scala/MatchError
       170: dup
       171: aload         6
       173: invokespecial #109                // Method scala/MatchError."<init>":(Ljava/lang/Object;)V
       176: athrow
       177: aload_3
       178: areturn
      StackMapTable: number_of_entries = 13
        frame_type = 0 /* same */
        frame_type = 254 /* append */
          offset_delta = 33
          locals = [ top, top, int ]
        frame_type = 3 /* same */
        frame_type = 71 /* same_locals_1_stack_item */
          stack = [ class java/lang/String ]
        frame_type = 2 /* same */
        frame_type = 253 /* append */
          offset_delta = 51
          locals = [ class scala/Option, class scala/Option ]
        frame_type = 2 /* same */
        frame_type = 254 /* append */
          offset_delta = 42
          locals = [ class scala/Some, int, int ]
        frame_type = 76 /* same_locals_1_stack_item */
          stack = [ class java/lang/String ]
        frame_type = 248 /* chop */
          offset_delta = 3
        frame_type = 2 /* same */
        frame_type = 255 /* full_frame */
          offset_delta = 9
          locals = [ class org/scalactic/NameUtil$, class java/lang/String, top, class java/lang/String, int, class scala/Option, class scala/Option ]
          stack = []
        frame_type = 255 /* full_frame */
          offset_delta = 0
          locals = [ class org/scalactic/NameUtil$, class java/lang/String, top, top, int ]
          stack = [ class java/lang/String ]
      LineNumberTable:
        line 26: 0
        line 27: 8
        line 28: 19
        line 31: 49
        line 32: 81
        line 33: 85
        line 34: 104
        line 35: 129
        line 36: 137
        line 37: 147
        line 34: 164
        line 32: 167
      LocalVariableTable:
        Start  Length  Slot  Name   Signature
          137      23     9 lastNonDollarIndex   I
          129      35     8     c   C
           81      97     5 lastNonDollarChar   Lscala/Option;
            8     170     4 lastDollarIndex   I
            0     179     0  this   Lorg/scalactic/NameUtil$;
            0     179     1     s   Ljava/lang/String;
    MethodParameters:
      Name                           Flags
      s                              final

  public java.lang.String getSimpleNameOfAnObjectsClass(java.lang.Object);
    descriptor: (Ljava/lang/Object;)Ljava/lang/String;
    flags: (0x0001) ACC_PUBLIC
    Code:
      stack=3, locals=2, args_size=2
         0: aload_0
         1: aload_0
         2: aload_1
         3: invokevirtual #127                // Method java/lang/Object.getClass:()Ljava/lang/Class;
         6: invokevirtual #133                // Method java/lang/Class.getName:()Ljava/lang/String;
         9: invokevirtual #136                // Method parseSimpleName:(Ljava/lang/String;)Ljava/lang/String;
        12: invokevirtual #138                // Method stripDollars:(Ljava/lang/String;)Ljava/lang/String;
        15: areturn
      LineNumberTable:
        line 43: 0
      LocalVariableTable:
        Start  Length  Slot  Name   Signature
            0      16     0  this   Lorg/scalactic/NameUtil$;
            0      16     1     o   Ljava/lang/Object;
    MethodParameters:
      Name                           Flags
      o                              final

  public java.lang.String parseSimpleName(java.lang.String);
    descriptor: (Ljava/lang/String;)Ljava/lang/String;
    flags: (0x0001) ACC_PUBLIC
    Code:
      stack=3, locals=3, args_size=2
         0: aload_1
         1: bipush        46
         3: invokevirtual #28                 // Method java/lang/String.lastIndexOf:(I)I
         6: istore_2
         7: iload_2
         8: iconst_m1
         9: if_icmpeq     30
        12: iload_2
        13: aload_1
        14: invokevirtual #32                 // Method java/lang/String.length:()I
        17: if_icmpeq     30
        20: aload_1
        21: iload_2
        22: iconst_1
        23: iadd
        24: invokevirtual #42                 // Method java/lang/String.substring:(I)Ljava/lang/String;
        27: goto          31
        30: aload_1
        31: areturn
      StackMapTable: number_of_entries = 2
        frame_type = 252 /* append */
          offset_delta = 30
          locals = [ int ]
        frame_type = 64 /* same_locals_1_stack_item */
          stack = [ class java/lang/String ]
      LineNumberTable:
        line 49: 0
        line 52: 7
        line 53: 20
        line 55: 30
      LocalVariableTable:
        Start  Length  Slot  Name   Signature
            7      24     2 dotPos   I
            0      32     0  this   Lorg/scalactic/NameUtil$;
            0      32     1 fullyQualifiedName   Ljava/lang/String;
    MethodParameters:
      Name                           Flags
      fullyQualifiedName             final

  public static final boolean $anonfun$stripDollars$1(char);
    descriptor: (C)Z
    flags: (0x1019) ACC_PUBLIC, ACC_STATIC, ACC_FINAL, ACC_SYNTHETIC
    Code:
      stack=2, locals=1, args_size=1
         0: iload_0
         1: bipush        36
         3: if_icmpeq     10
         6: iconst_1
         7: goto          11
        10: iconst_0
        11: ireturn
      StackMapTable: number_of_entries = 2
        frame_type = 10 /* same */
        frame_type = 64 /* same_locals_1_stack_item */
          stack = [ int ]
      LineNumberTable:
        line 31: 0
      LocalVariableTable:
        Start  Length  Slot  Name   Signature
            0      12     0   x$1   C
    MethodParameters:
      Name                           Flags
      x$1                            final

  private org.scalactic.NameUtil$();
    descriptor: ()V
    flags: (0x0002) ACC_PRIVATE
    Code:
      stack=1, locals=1, args_size=1
         0: aload_0
         1: invokespecial #145                // Method java/lang/Object."<init>":()V
         4: return
      LineNumberTable:
        line 58: 0
        line 18: 4
      LocalVariableTable:
        Start  Length  Slot  Name   Signature
            0       5     0  this   Lorg/scalactic/NameUtil$;

  public static final java.lang.Object $anonfun$stripDollars$1$adapted(java.lang.Object);
    descriptor: (Ljava/lang/Object;)Ljava/lang/Object;
    flags: (0x1019) ACC_PUBLIC, ACC_STATIC, ACC_FINAL, ACC_SYNTHETIC
    Code:
      stack=1, locals=1, args_size=1
         0: aload_0
         1: invokestatic  #101                // Method scala/runtime/BoxesRunTime.unboxToChar:(Ljava/lang/Object;)C
         4: invokestatic  #147                // Method $anonfun$stripDollars$1:(C)Z
         7: invokestatic  #151                // Method scala/runtime/BoxesRunTime.boxToBoolean:(Z)Ljava/lang/Boolean;
        10: areturn
      LineNumberTable:
        line 31: 0
      LocalVariableTable:
        Start  Length  Slot  Name   Signature
            0      11     0   x$1   Ljava/lang/Object;
    MethodParameters:
      Name                           Flags
      x$1                            final

  private static java.lang.Object $deserializeLambda$(java.lang.invoke.SerializedLambda);
    descriptor: (Ljava/lang/invoke/SerializedLambda;)Ljava/lang/Object;
    flags: (0x100a) ACC_PRIVATE, ACC_STATIC, ACC_SYNTHETIC
    Code:
      stack=1, locals=1, args_size=1
         0: aload_0
         1: invokedynamic #163,  0            // InvokeDynamic #1:lambdaDeserialize:(Ljava/lang/invoke/SerializedLambda;)Ljava/lang/Object;
         6: areturn
}
InnerClasses:
  public static final #10= #7 of #9;      // Lookup=class java/lang/invoke/MethodHandles$Lookup of class java/lang/invoke/MethodHandles
SourceFile: "NameUtil.scala"
BootstrapMethods:
  0: #72 REF_invokeStatic java/lang/invoke/LambdaMetafactory.altMetafactory:(Ljava/lang/invoke/MethodHandles$Lookup;Ljava/lang/String;Ljava/lang/invoke/MethodType;[Ljava/lang/Object;)Ljava/lang/invoke/CallSite;
    Method arguments:
      #60 (Ljava/lang/Object;)Ljava/lang/Object;
      #64 REF_invokeStatic org/scalactic/NameUtil$.$anonfun$stripDollars$1$adapted:(Ljava/lang/Object;)Ljava/lang/Object;
      #60 (Ljava/lang/Object;)Ljava/lang/Object;
      #65 1
  1: #160 REF_invokeStatic scala/runtime/LambdaDeserialize.bootstrap:(Ljava/lang/invoke/MethodHandles$Lookup;Ljava/lang/String;Ljava/lang/invoke/MethodType;[Ljava/lang/invoke/MethodHandle;)Ljava/lang/invoke/CallSite;
    Method arguments:
      #64 REF_invokeStatic org/scalactic/NameUtil$.$anonfun$stripDollars$1$adapted:(Ljava/lang/Object;)Ljava/lang/Object;
  ScalaInlineInfo: length = 0x22 (unknown attribute)
   01 01 00 06 00 8E 00 8F 01 00 3D 00 3B 01 00 0F
   00 0E 01 00 79 00 7A 01 00 86 00 15 01 00 14 00
   15 01
  Scala: length = 0x0 (unknown attribute)

