Classfile /Users/mw/Projects/slang-braindump/.jar/jar8/assemble/slang-braindump/assemble/content/org/scalactic/Normalization.class
  Last modified May 29, 2022; size 2299 bytes
  SHA-256 checksum 5779ea9c8d2324cb39d09b63e9220a6e00dc8a65000ac2df4d2507acd507cb6f
  Compiled from "Normalization.scala"
public interface org.scalactic.Normalization<A extends java.lang.Object>
  minor version: 0
  major version: 52
  flags: (0x0601) ACC_PUBLIC, ACC_INTERFACE, ACC_ABSTRACT
  this_class: #2                          // org/scalactic/Normalization
  super_class: #5                         // java/lang/Object
  interfaces: 0, fields: 0, methods: 6, attributes: 6
Constant pool:
   #1 = Utf8               org/scalactic/Normalization
   #2 = Class              #1             // org/scalactic/Normalization
   #3 = Utf8               <A:Ljava/lang/Object;>Ljava/lang/Object;
   #4 = Utf8               java/lang/Object
   #5 = Class              #4             // java/lang/Object
   #6 = Utf8               Normalization.scala
   #7 = Utf8               Lscala/reflect/ScalaSignature;
   #8 = Utf8               bytes
   #9 = Utf8               \u0006\u0005]2q!\u0002\u0004\u0011\u0002\u0007\u00051\u0002C\u0003\u0014\u0001\u0011\u0005A\u0003C\u0003\u0019\u0001\u0019\u0005\u0011\u0004C\u0003(\u0001\u0011\u0015\u0001\u0006C\u0003.\u0001\u0011\u0015aFA\u0007O_Jl\u0017\r\\5{CRLwN\u001c\u0006\u0003\u000f!\t\u0011b]2bY\u0006\u001cG/[2\u000b\u0003%\t1a\u001c:h\u0007\u0001)\"\u0001\u0004\u000f\u0014\u0005\u0001i\u0001C\u0001\b\u0012\u001b\u0005y!\"\u0001\t\u0002\u000bM\u001c\u0017\r\\1\n\u0005Iy!AB!osJ+g-\u0001\u0004%S:LG\u000f\n\u000b\u0002+A\u0011aBF\u0005\u0003/=\u0011A!\u00168ji\u0006Qan\u001c:nC2L\'0\u001a3\u0015\u0005i)\u0003CA\u000e\u001d\u0019\u0001!Q!\b\u0001C\u0002y\u0011\u0011!Q\t\u0003?\t\u0002\"A\u0004\u0011\n\u0005\u0005z!a\u0002(pi\"Lgn\u001a\t\u0003\u001d\rJ!\u0001J\b\u0003\u0007\u0005s\u0017\u0010C\u0003\'\u0005\u0001\u0007!$A\u0001b\u0003\r\tg\u000e\u001a\u000b\u0003S-\u00022A\u000b\u0001\u001b\u001b\u00051\u0001\"\u0002\u0017\u0004\u0001\u0004I\u0013!B8uQ\u0016\u0014\u0018!\u0004;p\u000bF,\u0018N^1mK:\u001cW\r\u0006\u00020eA\u0019!\u0006\r\u000e\n\u0005E2!A\u0006(pe6\fG.\u001b>j]\u001e,\u0015/^5wC2,gnY3\t\u000bM\"\u00019\u0001\u001b\u0002\u0017\u0015\fX/\u001b<bY\u0016t7-\u001a\t\u0004UUR\u0012B\u0001\u001c\u0007\u0005-)\u0015/^5wC2,gnY3
  #10 = Utf8               org/scalactic/Normalization$$anon$1
  #11 = Class              #10            // org/scalactic/Normalization$$anon$1
  #12 = Utf8               org/scalactic/Normalization$$anon$2
  #13 = Class              #12            // org/scalactic/Normalization$$anon$2
  #14 = Utf8               normalized
  #15 = Utf8               (Ljava/lang/Object;)Ljava/lang/Object;
  #16 = Utf8               (TA;)TA;
  #17 = Utf8               a
  #18 = Utf8               and$
  #19 = Utf8               (Lorg/scalactic/Normalization;Lorg/scalactic/Normalization;)Lorg/scalactic/Normalization;
  #20 = Utf8               $this
  #21 = Utf8               other
  #22 = Utf8               and
  #23 = Utf8               (Lorg/scalactic/Normalization;)Lorg/scalactic/Normalization;
  #24 = NameAndType        #22:#23        // and:(Lorg/scalactic/Normalization;)Lorg/scalactic/Normalization;
  #25 = InterfaceMethodref #2.#24         // org/scalactic/Normalization.and:(Lorg/scalactic/Normalization;)Lorg/scalactic/Normalization;
  #26 = Utf8               Lorg/scalactic/Normalization;
  #27 = Utf8               (Lorg/scalactic/Normalization<TA;>;)Lorg/scalactic/Normalization<TA;>;
  #28 = Utf8               <init>
  #29 = Utf8               (Lorg/scalactic/Normalization;Lorg/scalactic/Normalization;)V
  #30 = NameAndType        #28:#29        // "<init>":(Lorg/scalactic/Normalization;Lorg/scalactic/Normalization;)V
  #31 = Methodref          #11.#30        // org/scalactic/Normalization$$anon$1."<init>":(Lorg/scalactic/Normalization;Lorg/scalactic/Normalization;)V
  #32 = Utf8               this
  #33 = Utf8               toEquivalence$
  #34 = Utf8               (Lorg/scalactic/Normalization;Lorg/scalactic/Equivalence;)Lorg/scalactic/NormalizingEquivalence;
  #35 = Utf8               equivalence
  #36 = Utf8               toEquivalence
  #37 = Utf8               (Lorg/scalactic/Equivalence;)Lorg/scalactic/NormalizingEquivalence;
  #38 = NameAndType        #36:#37        // toEquivalence:(Lorg/scalactic/Equivalence;)Lorg/scalactic/NormalizingEquivalence;
  #39 = InterfaceMethodref #2.#38         // org/scalactic/Normalization.toEquivalence:(Lorg/scalactic/Equivalence;)Lorg/scalactic/NormalizingEquivalence;
  #40 = Utf8               Lorg/scalactic/Equivalence;
  #41 = Utf8               (Lorg/scalactic/Equivalence<TA;>;)Lorg/scalactic/NormalizingEquivalence<TA;>;
  #42 = Utf8               (Lorg/scalactic/Normalization;Lorg/scalactic/Equivalence;)V
  #43 = NameAndType        #28:#42        // "<init>":(Lorg/scalactic/Normalization;Lorg/scalactic/Equivalence;)V
  #44 = Methodref          #13.#43        // org/scalactic/Normalization$$anon$2."<init>":(Lorg/scalactic/Normalization;Lorg/scalactic/Equivalence;)V
  #45 = Utf8               $init$
  #46 = Utf8               (Lorg/scalactic/Normalization;)V
  #47 = Utf8               Signature
  #48 = Utf8               MethodParameters
  #49 = Utf8               Code
  #50 = Utf8               LineNumberTable
  #51 = Utf8               LocalVariableTable
  #52 = Utf8               InnerClasses
  #53 = Utf8               SourceFile
  #54 = Utf8               RuntimeVisibleAnnotations
  #55 = Utf8               ScalaInlineInfo
  #56 = Utf8               ScalaSig
{
  public abstract A normalized(A);
    descriptor: (Ljava/lang/Object;)Ljava/lang/Object;
    flags: (0x0401) ACC_PUBLIC, ACC_ABSTRACT
    Signature: #16                          // (TA;)TA;
    MethodParameters:
      Name                           Flags
      a                              final

  public static org.scalactic.Normalization and$(org.scalactic.Normalization, org.scalactic.Normalization);
    descriptor: (Lorg/scalactic/Normalization;Lorg/scalactic/Normalization;)Lorg/scalactic/Normalization;
    flags: (0x1009) ACC_PUBLIC, ACC_STATIC, ACC_SYNTHETIC
    Code:
      stack=2, locals=2, args_size=2
         0: aload_0
         1: aload_1
         2: invokespecial #25                 // InterfaceMethod and:(Lorg/scalactic/Normalization;)Lorg/scalactic/Normalization;
         5: areturn
      LineNumberTable:
        line 101: 0
      LocalVariableTable:
        Start  Length  Slot  Name   Signature
            0       6     0 $this   Lorg/scalactic/Normalization;
            0       6     1 other   Lorg/scalactic/Normalization;
    MethodParameters:
      Name                           Flags
      $this                          final synthetic
      other                          final

  public default org.scalactic.Normalization<A> and(org.scalactic.Normalization<A>);
    descriptor: (Lorg/scalactic/Normalization;)Lorg/scalactic/Normalization;
    flags: (0x0001) ACC_PUBLIC
    Code:
      stack=4, locals=2, args_size=2
         0: new           #11                 // class org/scalactic/Normalization$$anon$1
         3: dup
         4: aload_0
         5: aload_1
         6: invokespecial #31                 // Method org/scalactic/Normalization$$anon$1."<init>":(Lorg/scalactic/Normalization;Lorg/scalactic/Normalization;)V
         9: areturn
      LineNumberTable:
        line 102: 0
      LocalVariableTable:
        Start  Length  Slot  Name   Signature
            0      10     0  this   Lorg/scalactic/Normalization;
            0      10     1 other   Lorg/scalactic/Normalization;
    Signature: #27                          // (Lorg/scalactic/Normalization<TA;>;)Lorg/scalactic/Normalization<TA;>;
    MethodParameters:
      Name                           Flags
      other                          final

  public static org.scalactic.NormalizingEquivalence toEquivalence$(org.scalactic.Normalization, org.scalactic.Equivalence);
    descriptor: (Lorg/scalactic/Normalization;Lorg/scalactic/Equivalence;)Lorg/scalactic/NormalizingEquivalence;
    flags: (0x1009) ACC_PUBLIC, ACC_STATIC, ACC_SYNTHETIC
    Code:
      stack=2, locals=2, args_size=2
         0: aload_0
         1: aload_1
         2: invokespecial #39                 // InterfaceMethod toEquivalence:(Lorg/scalactic/Equivalence;)Lorg/scalactic/NormalizingEquivalence;
         5: areturn
      LineNumberTable:
        line 114: 0
      LocalVariableTable:
        Start  Length  Slot  Name   Signature
            0       6     0 $this   Lorg/scalactic/Normalization;
            0       6     1 equivalence   Lorg/scalactic/Equivalence;
    MethodParameters:
      Name                           Flags
      $this                          final synthetic
      equivalence                    final

  public default org.scalactic.NormalizingEquivalence<A> toEquivalence(org.scalactic.Equivalence<A>);
    descriptor: (Lorg/scalactic/Equivalence;)Lorg/scalactic/NormalizingEquivalence;
    flags: (0x0001) ACC_PUBLIC
    Code:
      stack=4, locals=2, args_size=2
         0: new           #13                 // class org/scalactic/Normalization$$anon$2
         3: dup
         4: aload_0
         5: aload_1
         6: invokespecial #44                 // Method org/scalactic/Normalization$$anon$2."<init>":(Lorg/scalactic/Normalization;Lorg/scalactic/Equivalence;)V
         9: areturn
      LineNumberTable:
        line 115: 0
      LocalVariableTable:
        Start  Length  Slot  Name   Signature
            0      10     0  this   Lorg/scalactic/Normalization;
            0      10     1 equivalence   Lorg/scalactic/Equivalence;
    Signature: #41                          // (Lorg/scalactic/Equivalence<TA;>;)Lorg/scalactic/NormalizingEquivalence<TA;>;
    MethodParameters:
      Name                           Flags
      equivalence                    final

  public static void $init$(org.scalactic.Normalization);
    descriptor: (Lorg/scalactic/Normalization;)V
    flags: (0x0009) ACC_PUBLIC, ACC_STATIC
    Code:
      stack=0, locals=1, args_size=1
         0: return
      LineNumberTable:
        line 69: 0
      LocalVariableTable:
        Start  Length  Slot  Name   Signature
            0       1     0 $this   Lorg/scalactic/Normalization;
    MethodParameters:
      Name                           Flags
      $this                          final synthetic
}
InnerClasses:
  public final #11;                       // class org/scalactic/Normalization$$anon$1
  public final #13;                       // class org/scalactic/Normalization$$anon$2
Signature: #3                           // <A:Ljava/lang/Object;>Ljava/lang/Object;
SourceFile: "Normalization.scala"
RuntimeVisibleAnnotations:
  0: #7(#8=s#9)
    scala.reflect.ScalaSignature(
      bytes="\u0006\u0005]2q!\u0002\u0004\u0011\u0002\u0007\u00051\u0002C\u0003\u0014\u0001\u0011\u0005A\u0003C\u0003\u0019\u0001\u0019\u0005\u0011\u0004C\u0003(\u0001\u0011\u0015\u0001\u0006C\u0003.\u0001\u0011\u0015aFA\u0007O_Jl\u0017\r\\5{CRLwN\u001c\u0006\u0003\u000f!\t\u0011b]2bY\u0006\u001cG/[2\u000b\u0003%\t1a\u001c:h\u0007\u0001)\"\u0001\u0004\u000f\u0014\u0005\u0001i\u0001C\u0001\b\u0012\u001b\u0005y!\"\u0001\t\u0002\u000bM\u001c\u0017\r\\1\n\u0005Iy!AB!osJ+g-\u0001\u0004%S:LG\u000f\n\u000b\u0002+A\u0011aBF\u0005\u0003/=\u0011A!\u00168ji\u0006Qan\u001c:nC2L\'0\u001a3\u0015\u0005i)\u0003CA\u000e\u001d\u0019\u0001!Q!\b\u0001C\u0002y\u0011\u0011!Q\t\u0003?\t\u0002\"A\u0004\u0011\n\u0005\u0005z!a\u0002(pi\"Lgn\u001a\t\u0003\u001d\rJ!\u0001J\b\u0003\u0007\u0005s\u0017\u0010C\u0003\'\u0005\u0001\u0007!$A\u0001b\u0003\r\tg\u000e\u001a\u000b\u0003S-\u00022A\u000b\u0001\u001b\u001b\u00051\u0001\"\u0002\u0017\u0004\u0001\u0004I\u0013!B8uQ\u0016\u0014\u0018!\u0004;p\u000bF,\u0018N^1mK:\u001cW\r\u0006\u00020eA\u0019!\u0006\r\u000e\n\u0005E2!A\u0006(pe6\fG.\u001b>j]\u001e,\u0015/^5wC2,gnY3\t\u000bM\"\u00019\u0001\u001b\u0002\u0017\u0015\fX/\u001b<bY\u0016t7-\u001a\t\u0004UUR\u0012B\u0001\u001c\u0007\u0005-)\u0015/^5wC2,gnY3"
    )
  ScalaInlineInfo: length = 0x22 (unknown attribute)
   01 00 00 06 00 2D 00 2E 01 00 16 00 17 01 00 12
   00 13 01 00 0E 00 0F 00 00 24 00 25 01 00 21 00
   22 01
  ScalaSig: length = 0x3 (unknown attribute)
   05 02 00
