Classfile /Users/mw/Projects/slang-braindump/.jar/jar8/assemble/slang-braindump/assemble/content/org/scalactic/NormMethods$.class
  Last modified May 29, 2022; size 1190 bytes
  SHA-256 checksum 5726108698ab5a6e461149dcf9c9aed4695098c3f353b203efc61cb94f2d18de
  Compiled from "NormMethods.scala"
public final class org.scalactic.NormMethods$ implements org.scalactic.NormMethods
  minor version: 0
  major version: 52
  flags: (0x0031) ACC_PUBLIC, ACC_FINAL, ACC_SUPER
  this_class: #2                          // org/scalactic/NormMethods$
  super_class: #4                         // java/lang/Object
  interfaces: 1, fields: 1, methods: 3, attributes: 4
Constant pool:
   #1 = Utf8               org/scalactic/NormMethods$
   #2 = Class              #1             // org/scalactic/NormMethods$
   #3 = Utf8               java/lang/Object
   #4 = Class              #3             // java/lang/Object
   #5 = Utf8               org/scalactic/NormMethods
   #6 = Class              #5             // org/scalactic/NormMethods
   #7 = Utf8               NormMethods.scala
   #8 = Utf8               org/scalactic/NormMethods$Normalizer
   #9 = Class              #8             // org/scalactic/NormMethods$Normalizer
  #10 = Utf8               Normalizer
  #11 = Utf8               MODULE$
  #12 = Utf8               Lorg/scalactic/NormMethods$;
  #13 = Utf8               <clinit>
  #14 = Utf8               ()V
  #15 = Utf8               <init>
  #16 = NameAndType        #15:#14        // "<init>":()V
  #17 = Methodref          #2.#16         // org/scalactic/NormMethods$."<init>":()V
  #18 = NameAndType        #11:#12        // MODULE$:Lorg/scalactic/NormMethods$;
  #19 = Fieldref           #2.#18         // org/scalactic/NormMethods$.MODULE$:Lorg/scalactic/NormMethods$;
  #20 = Utf8               $init$
  #21 = Utf8               (Lorg/scalactic/NormMethods;)V
  #22 = NameAndType        #20:#21        // $init$:(Lorg/scalactic/NormMethods;)V
  #23 = InterfaceMethodref #6.#22         // org/scalactic/NormMethods.$init$:(Lorg/scalactic/NormMethods;)V
  #24 = Utf8               convertToNormalizer
  #25 = Utf8               (Ljava/lang/Object;Lorg/scalactic/Normalization;)Lorg/scalactic/NormMethods$Normalizer;
  #26 = Utf8               <T:Ljava/lang/Object;>(TT;Lorg/scalactic/Normalization<TT;>;)Lorg/scalactic/NormMethods$Normalizer<TT;>;
  #27 = Utf8               o
  #28 = Utf8               normalization
  #29 = Utf8               convertToNormalizer$
  #30 = Utf8               (Lorg/scalactic/NormMethods;Ljava/lang/Object;Lorg/scalactic/Normalization;)Lorg/scalactic/NormMethods$Normalizer;
  #31 = NameAndType        #29:#30        // convertToNormalizer$:(Lorg/scalactic/NormMethods;Ljava/lang/Object;Lorg/scalactic/Normalization;)Lorg/scalactic/NormMethods$Normalizer;
  #32 = InterfaceMethodref #6.#31         // org/scalactic/NormMethods.convertToNormalizer$:(Lorg/scalactic/NormMethods;Ljava/lang/Object;Lorg/scalactic/Normalization;)Lorg/scalactic/NormMethods$Normalizer;
  #33 = Utf8               this
  #34 = Utf8               Ljava/lang/Object;
  #35 = Utf8               Lorg/scalactic/Normalization;
  #36 = Methodref          #4.#16         // java/lang/Object."<init>":()V
  #37 = Utf8               Code
  #38 = Utf8               LineNumberTable
  #39 = Utf8               LocalVariableTable
  #40 = Utf8               Signature
  #41 = Utf8               MethodParameters
  #42 = Utf8               InnerClasses
  #43 = Utf8               SourceFile
  #44 = Utf8               ScalaInlineInfo
  #45 = Utf8               Scala
{
  public static final org.scalactic.NormMethods$ MODULE$;
    descriptor: Lorg/scalactic/NormMethods$;
    flags: (0x0019) ACC_PUBLIC, ACC_STATIC, ACC_FINAL

  public static {};
    descriptor: ()V
    flags: (0x0009) ACC_PUBLIC, ACC_STATIC
    Code:
      stack=2, locals=0, args_size=0
         0: new           #2                  // class org/scalactic/NormMethods$
         3: dup
         4: invokespecial #17                 // Method "<init>":()V
         7: putstatic     #19                 // Field MODULE$:Lorg/scalactic/NormMethods$;
        10: getstatic     #19                 // Field MODULE$:Lorg/scalactic/NormMethods$;
        13: invokestatic  #23                 // InterfaceMethod org/scalactic/NormMethods.$init$:(Lorg/scalactic/NormMethods;)V
        16: return
      LineNumberTable:
        line 81: 0

  public <T extends java.lang.Object> org.scalactic.NormMethods$Normalizer<T> convertToNormalizer(T, org.scalactic.Normalization<T>);
    descriptor: (Ljava/lang/Object;Lorg/scalactic/Normalization;)Lorg/scalactic/NormMethods$Normalizer;
    flags: (0x0001) ACC_PUBLIC
    Code:
      stack=3, locals=3, args_size=3
         0: aload_0
         1: aload_1
         2: aload_2
         3: invokestatic  #32                 // InterfaceMethod org/scalactic/NormMethods.convertToNormalizer$:(Lorg/scalactic/NormMethods;Ljava/lang/Object;Lorg/scalactic/Normalization;)Lorg/scalactic/NormMethods$Normalizer;
         6: areturn
      LineNumberTable:
        line 81: 0
      LocalVariableTable:
        Start  Length  Slot  Name   Signature
            0       7     0  this   Lorg/scalactic/NormMethods$;
            0       7     1     o   Ljava/lang/Object;
            0       7     2 normalization   Lorg/scalactic/Normalization;
    Signature: #26                          // <T:Ljava/lang/Object;>(TT;Lorg/scalactic/Normalization<TT;>;)Lorg/scalactic/NormMethods$Normalizer<TT;>;
    MethodParameters:
      Name                           Flags
      o                              final
      normalization                  final

  private org.scalactic.NormMethods$();
    descriptor: ()V
    flags: (0x0002) ACC_PRIVATE
    Code:
      stack=1, locals=1, args_size=1
         0: aload_0
         1: invokespecial #36                 // Method java/lang/Object."<init>":()V
         4: return
      LineNumberTable:
        line 81: 0
      LocalVariableTable:
        Start  Length  Slot  Name   Signature
            0       5     0  this   Lorg/scalactic/NormMethods$;
}
InnerClasses:
  public final #10= #9 of #6;             // Normalizer=class org/scalactic/NormMethods$Normalizer of class org/scalactic/NormMethods
SourceFile: "NormMethods.scala"
  ScalaInlineInfo: length = 0xE (unknown attribute)
   01 01 00 02 00 0F 00 0E 01 00 18 00 19 01
  Scala: length = 0x0 (unknown attribute)

