Classfile /Users/mw/Projects/slang-braindump/.jar/jar8/assemble/slang-braindump/assemble/content/org/scalactic/package$.class
  Last modified May 29, 2022; size 1934 bytes
  SHA-256 checksum 3a6c99d66555933de39dcdab1c8a94c92600ddd43f093b246916bbc165f6ac0f
  Compiled from "package.scala"
public final class org.scalactic.package$
  minor version: 0
  major version: 52
  flags: (0x0031) ACC_PUBLIC, ACC_FINAL, ACC_SUPER
  this_class: #2                          // org/scalactic/package$
  super_class: #4                         // java/lang/Object
  interfaces: 0, fields: 4, methods: 6, attributes: 3
Constant pool:
   #1 = Utf8               org/scalactic/package$
   #2 = Class              #1             // org/scalactic/package$
   #3 = Utf8               java/lang/Object
   #4 = Class              #3             // java/lang/Object
   #5 = Utf8               package.scala
   #6 = Utf8               MODULE$
   #7 = Utf8               Lorg/scalactic/package$;
   #8 = Utf8               ScalacticVersion
   #9 = Utf8               Ljava/lang/String;
  #10 = Utf8               Chain
  #11 = Utf8               Lorg/scalactic/anyvals/NonEmptyList$;
  #12 = Utf8               End
  #13 = Utf8               Lorg/scalactic/anyvals/End$;
  #14 = Utf8               <clinit>
  #15 = Utf8               ()V
  #16 = Utf8               <init>
  #17 = NameAndType        #16:#15        // "<init>":()V
  #18 = Methodref          #2.#17         // org/scalactic/package$."<init>":()V
  #19 = NameAndType        #6:#7          // MODULE$:Lorg/scalactic/package$;
  #20 = Fieldref           #2.#19         // org/scalactic/package$.MODULE$:Lorg/scalactic/package$;
  #21 = Utf8               org/scalactic/ScalacticVersions$
  #22 = Class              #21            // org/scalactic/ScalacticVersions$
  #23 = Utf8               Lorg/scalactic/ScalacticVersions$;
  #24 = NameAndType        #6:#23         // MODULE$:Lorg/scalactic/ScalacticVersions$;
  #25 = Fieldref           #22.#24        // org/scalactic/ScalacticVersions$.MODULE$:Lorg/scalactic/ScalacticVersions$;
  #26 = Utf8               ()Ljava/lang/String;
  #27 = NameAndType        #8:#26         // ScalacticVersion:()Ljava/lang/String;
  #28 = Methodref          #22.#27        // org/scalactic/ScalacticVersions$.ScalacticVersion:()Ljava/lang/String;
  #29 = NameAndType        #8:#9          // ScalacticVersion:Ljava/lang/String;
  #30 = Fieldref           #2.#29         // org/scalactic/package$.ScalacticVersion:Ljava/lang/String;
  #31 = Utf8               org/scalactic/anyvals/NonEmptyList$
  #32 = Class              #31            // org/scalactic/anyvals/NonEmptyList$
  #33 = NameAndType        #6:#11         // MODULE$:Lorg/scalactic/anyvals/NonEmptyList$;
  #34 = Fieldref           #32.#33        // org/scalactic/anyvals/NonEmptyList$.MODULE$:Lorg/scalactic/anyvals/NonEmptyList$;
  #35 = NameAndType        #10:#11        // Chain:Lorg/scalactic/anyvals/NonEmptyList$;
  #36 = Fieldref           #2.#35         // org/scalactic/package$.Chain:Lorg/scalactic/anyvals/NonEmptyList$;
  #37 = Utf8               org/scalactic/anyvals/End$
  #38 = Class              #37            // org/scalactic/anyvals/End$
  #39 = NameAndType        #6:#13         // MODULE$:Lorg/scalactic/anyvals/End$;
  #40 = Fieldref           #38.#39        // org/scalactic/anyvals/End$.MODULE$:Lorg/scalactic/anyvals/End$;
  #41 = NameAndType        #12:#13        // End:Lorg/scalactic/anyvals/End$;
  #42 = Fieldref           #2.#41         // org/scalactic/package$.End:Lorg/scalactic/anyvals/End$;
  #43 = Utf8               attempt
  #44 = Utf8               (Lscala/Function0;)Lorg/scalactic/Or;
  #45 = Utf8               <R:Ljava/lang/Object;>(Lscala/Function0<TR;>;)Lorg/scalactic/Or<TR;Ljava/lang/Throwable;>;
  #46 = Utf8               f
  #47 = Utf8               java/lang/Throwable
  #48 = Class              #47            // java/lang/Throwable
  #49 = Utf8               org/scalactic/Good
  #50 = Class              #49            // org/scalactic/Good
  #51 = Utf8               scala/Function0
  #52 = Class              #51            // scala/Function0
  #53 = Utf8               apply
  #54 = Utf8               ()Ljava/lang/Object;
  #55 = NameAndType        #53:#54        // apply:()Ljava/lang/Object;
  #56 = InterfaceMethodref #52.#55        // scala/Function0.apply:()Ljava/lang/Object;
  #57 = Utf8               (Ljava/lang/Object;)V
  #58 = NameAndType        #16:#57        // "<init>":(Ljava/lang/Object;)V
  #59 = Methodref          #50.#58        // org/scalactic/Good."<init>":(Ljava/lang/Object;)V
  #60 = Utf8               scala/util/control/NonFatal$
  #61 = Class              #60            // scala/util/control/NonFatal$
  #62 = Utf8               Lscala/util/control/NonFatal$;
  #63 = NameAndType        #6:#62         // MODULE$:Lscala/util/control/NonFatal$;
  #64 = Fieldref           #61.#63        // scala/util/control/NonFatal$.MODULE$:Lscala/util/control/NonFatal$;
  #65 = Utf8               (Ljava/lang/Throwable;)Z
  #66 = NameAndType        #53:#65        // apply:(Ljava/lang/Throwable;)Z
  #67 = Methodref          #61.#66        // scala/util/control/NonFatal$.apply:(Ljava/lang/Throwable;)Z
  #68 = Utf8               org/scalactic/Bad
  #69 = Class              #68            // org/scalactic/Bad
  #70 = Methodref          #69.#58        // org/scalactic/Bad."<init>":(Ljava/lang/Object;)V
  #71 = Utf8               this
  #72 = Utf8               Lscala/Function0;
  #73 = Utf8               org/scalactic/Or
  #74 = Class              #73            // org/scalactic/Or
  #75 = Utf8               ()Lorg/scalactic/anyvals/NonEmptyList$;
  #76 = Utf8               ()Lorg/scalactic/anyvals/End$;
  #77 = Methodref          #4.#17         // java/lang/Object."<init>":()V
  #78 = Utf8               Deprecated
  #79 = Utf8               Code
  #80 = Utf8               LineNumberTable
  #81 = Utf8               StackMapTable
  #82 = Utf8               LocalVariableTable
  #83 = Utf8               Signature
  #84 = Utf8               MethodParameters
  #85 = Utf8               SourceFile
  #86 = Utf8               ScalaInlineInfo
  #87 = Utf8               Scala
{
  public static final org.scalactic.package$ MODULE$;
    descriptor: Lorg/scalactic/package$;
    flags: (0x0019) ACC_PUBLIC, ACC_STATIC, ACC_FINAL

  private static final java.lang.String ScalacticVersion;
    descriptor: Ljava/lang/String;
    flags: (0x001a) ACC_PRIVATE, ACC_STATIC, ACC_FINAL

  private static final org.scalactic.anyvals.NonEmptyList$ Chain;
    descriptor: Lorg/scalactic/anyvals/NonEmptyList$;
    flags: (0x001a) ACC_PRIVATE, ACC_STATIC, ACC_FINAL
    Deprecated: true

  private static final org.scalactic.anyvals.End$ End;
    descriptor: Lorg/scalactic/anyvals/End$;
    flags: (0x001a) ACC_PRIVATE, ACC_STATIC, ACC_FINAL
    Deprecated: true

  public static {};
    descriptor: ()V
    flags: (0x0009) ACC_PUBLIC, ACC_STATIC
    Code:
      stack=2, locals=0, args_size=0
         0: new           #2                  // class org/scalactic/package$
         3: dup
         4: invokespecial #18                 // Method "<init>":()V
         7: putstatic     #20                 // Field MODULE$:Lorg/scalactic/package$;
        10: getstatic     #25                 // Field org/scalactic/ScalacticVersions$.MODULE$:Lorg/scalactic/ScalacticVersions$;
        13: invokevirtual #28                 // Method org/scalactic/ScalacticVersions$.ScalacticVersion:()Ljava/lang/String;
        16: putstatic     #30                 // Field ScalacticVersion:Ljava/lang/String;
        19: getstatic     #34                 // Field org/scalactic/anyvals/NonEmptyList$.MODULE$:Lorg/scalactic/anyvals/NonEmptyList$;
        22: putstatic     #36                 // Field Chain:Lorg/scalactic/anyvals/NonEmptyList$;
        25: getstatic     #40                 // Field org/scalactic/anyvals/End$.MODULE$:Lorg/scalactic/anyvals/End$;
        28: putstatic     #42                 // Field End:Lorg/scalactic/anyvals/End$;
        31: return
      LineNumberTable:
        line 20: 0
        line 61: 10
        line 79: 19
        line 88: 25
        line 20: 31

  public <R extends java.lang.Object> org.scalactic.Or<R, java.lang.Throwable> attempt(scala.Function0<R>);
    descriptor: (Lscala/Function0;)Lorg/scalactic/Or;
    flags: (0x0001) ACC_PUBLIC
    Code:
      stack=3, locals=6, args_size=2
         0: new           #50                 // class org/scalactic/Good
         3: dup
         4: aload_1
         5: invokeinterface #56,  1           // InterfaceMethod scala/Function0.apply:()Ljava/lang/Object;
        10: invokespecial #59                 // Method org/scalactic/Good."<init>":(Ljava/lang/Object;)V
        13: goto          65
        16: astore_3
        17: aload_3
        18: astore        4
        20: aload         4
        22: ifnull        56
        25: aload         4
        27: astore        5
        29: getstatic     #64                 // Field scala/util/control/NonFatal$.MODULE$:Lscala/util/control/NonFatal$;
        32: aload         5
        34: invokevirtual #67                 // Method scala/util/control/NonFatal$.apply:(Ljava/lang/Throwable;)Z
        37: ifeq          53
        40: new           #69                 // class org/scalactic/Bad
        43: dup
        44: aload         5
        46: invokespecial #70                 // Method org/scalactic/Bad."<init>":(Ljava/lang/Object;)V
        49: astore_2
        50: goto          61
        53: goto          59
        56: goto          59
        59: aload_3
        60: athrow
        61: aload_2
        62: goto          65
        65: areturn
      Exception table:
         from    to  target type
             0    13    16   Class java/lang/Throwable
      StackMapTable: number_of_entries = 6
        frame_type = 80 /* same_locals_1_stack_item */
          stack = [ class java/lang/Throwable ]
        frame_type = 255 /* full_frame */
          offset_delta = 36
          locals = [ class org/scalactic/package$, class scala/Function0, top, class java/lang/Throwable, class java/lang/Throwable, class java/lang/Throwable ]
          stack = []
        frame_type = 250 /* chop */
          offset_delta = 2
        frame_type = 2 /* same */
        frame_type = 255 /* full_frame */
          offset_delta = 1
          locals = [ class org/scalactic/package$, class scala/Function0, class org/scalactic/Bad, class java/lang/Throwable, class java/lang/Throwable, class java/lang/Throwable ]
          stack = []
        frame_type = 255 /* full_frame */
          offset_delta = 3
          locals = [ class org/scalactic/package$, class scala/Function0 ]
          stack = [ class org/scalactic/Or ]
      LineNumberTable:
        line 51: 0
        line 53: 17
        line 53: 20
        line 51: 59
      LocalVariableTable:
        Start  Length  Slot  Name   Signature
            0      66     0  this   Lorg/scalactic/package$;
            0      66     1     f   Lscala/Function0;
    Signature: #45                          // <R:Ljava/lang/Object;>(Lscala/Function0<TR;>;)Lorg/scalactic/Or<TR;Ljava/lang/Throwable;>;
    MethodParameters:
      Name                           Flags
      f                              final

  public java.lang.String ScalacticVersion();
    descriptor: ()Ljava/lang/String;
    flags: (0x0001) ACC_PUBLIC
    Code:
      stack=1, locals=1, args_size=1
         0: getstatic     #30                 // Field ScalacticVersion:Ljava/lang/String;
         3: areturn
      LineNumberTable:
        line 61: 0
      LocalVariableTable:
        Start  Length  Slot  Name   Signature
            0       4     0  this   Lorg/scalactic/package$;

  public org.scalactic.anyvals.NonEmptyList$ Chain();
    descriptor: ()Lorg/scalactic/anyvals/NonEmptyList$;
    flags: (0x0001) ACC_PUBLIC
    Code:
      stack=1, locals=1, args_size=1
         0: getstatic     #36                 // Field Chain:Lorg/scalactic/anyvals/NonEmptyList$;
         3: areturn
      LineNumberTable:
        line 79: 0
      LocalVariableTable:
        Start  Length  Slot  Name   Signature
            0       4     0  this   Lorg/scalactic/package$;
    Deprecated: true

  public org.scalactic.anyvals.End$ End();
    descriptor: ()Lorg/scalactic/anyvals/End$;
    flags: (0x0001) ACC_PUBLIC
    Code:
      stack=1, locals=1, args_size=1
         0: getstatic     #42                 // Field End:Lorg/scalactic/anyvals/End$;
         3: areturn
      LineNumberTable:
        line 88: 0
      LocalVariableTable:
        Start  Length  Slot  Name   Signature
            0       4     0  this   Lorg/scalactic/package$;
    Deprecated: true

  private org.scalactic.package$();
    descriptor: ()V
    flags: (0x0002) ACC_PRIVATE
    Code:
      stack=1, locals=1, args_size=1
         0: aload_0
         1: invokespecial #77                 // Method java/lang/Object."<init>":()V
         4: return
      LineNumberTable:
        line 89: 0
        line 20: 4
      LocalVariableTable:
        Start  Length  Slot  Name   Signature
            0       5     0  this   Lorg/scalactic/package$;
}
SourceFile: "package.scala"
  ScalaInlineInfo: length = 0x1D (unknown attribute)
   01 01 00 05 00 10 00 0F 01 00 0A 00 4B 01 00 0C
   00 4C 01 00 08 00 1A 01 00 2B 00 2C 01
  Scala: length = 0x0 (unknown attribute)

