Classfile /Users/mw/Projects/slang-braindump/.jar/jar8/assemble/slang-braindump/assemble/content/org/scalactic/PrettyMethods.class
  Last modified May 29, 2022; size 1669 bytes
  SHA-256 checksum 3015583cc75484de5aef5fc5fcae928ff38704caa91891ebdf7a4412f2f71b1f
  Compiled from "PrettyMethods.scala"
public interface org.scalactic.PrettyMethods
  minor version: 0
  major version: 52
  flags: (0x0601) ACC_PUBLIC, ACC_INTERFACE, ACC_ABSTRACT
  this_class: #2                          // org/scalactic/PrettyMethods
  super_class: #4                         // java/lang/Object
  interfaces: 0, fields: 0, methods: 3, attributes: 5
Constant pool:
   #1 = Utf8               org/scalactic/PrettyMethods
   #2 = Class              #1             // org/scalactic/PrettyMethods
   #3 = Utf8               java/lang/Object
   #4 = Class              #3             // java/lang/Object
   #5 = Utf8               PrettyMethods.scala
   #6 = Utf8               Lscala/reflect/ScalaSignature;
   #7 = Utf8               bytes
   #8 = Utf8               \u0006\u0005\u00193qa\u0003\u0007\u0011\u0002\u0007\u0005\u0011\u0003C\u0003\u0019\u0001\u0011\u0005\u0011D\u0002\u0003\u001e\u0001\u0005q\u0002\u0002C\u0010\u0003\u0005\u0003\u0005\u000b\u0011\u0002\u0011\t\u0011\r\u0012!\u0011!Q\u0001\f\u0011BQ\u0001\u000b\u0002\u0005\u0002%BQa\f\u0002\u0005\u0002ABq\u0001\u0010\u0001\u0002\u0002\u0013\rQhB\u0003B\u0019!\u0005!IB\u0003\f\u0019!\u00051\tC\u0003)\u0013\u0011\u0005QIA\u0007Qe\u0016$H/_\'fi\"|Gm\u001d\u0006\u0003\u001b9\t\u0011b]2bY\u0006\u001cG/[2\u000b\u0003=\t1a\u001c:h\u0007\u0001\u0019\"\u0001\u0001\n\u0011\u0005M1R\"\u0001\u000b\u000b\u0003U\tQa]2bY\u0006L!a\u0006\u000b\u0003\r\u0005s\u0017PU3g\u0003\u0019!\u0013N\\5uIQ\t!\u0004\u0005\u0002\u00147%\u0011A\u0004\u0006\u0002\u0005+:LGO\u0001\u0006Qe\u0016$H/_5{KJ\u001c\"A\u0001\n\u0002\u0003=\u0004\"aE\u0011\n\u0005\t\"\"aA!os\u0006Q\u0001O]3ui&4\u0017.\u001a:\u0011\u0005\u00152S\"\u0001\u0007\n\u0005\u001db!A\u0003)sKR$\u0018NZ5fe\u00061A(\u001b8jiz\"\"A\u000b\u0018\u0015\u0005-j\u0003C\u0001\u0017\u0003\u001b\u0005\u0001\u0001\"B\u0012\u0006\u0001\b!\u0003\"B\u0010\u0006\u0001\u0004\u0001\u0013A\u00029sKR$\u00180F\u00012!\t\u0011\u0014H\u0004\u00024oA\u0011A\u0007F\u0007\u0002k)\u0011a\u0007E\u0001\u0007yI|w\u000e\u001e \n\u0005a\"\u0012A\u0002)sK\u0012,g-\u0003\u0002;w\t11\u000b\u001e:j]\u001eT!\u0001\u000f\u000b\u0002\u0015A\u0013X\r\u001e;zSj,\'\u000f\u0006\u0002?\u0001R\u00111f\u0010\u0005\u0006G\u001d\u0001\u001d\u0001\n\u0005\u0006?\u001d\u0001\r\u0001I\u0001\u000e!J,G\u000f^=NKRDw\u000eZ:\u0011\u0005\u0015J1cA\u0005\u0013\tB\u0011Q\u0005\u0001\u000b\u0002\u0005\u0002
   #9 = Utf8               org/scalactic/PrettyMethods$Prettyizer
  #10 = Class              #9             // org/scalactic/PrettyMethods$Prettyizer
  #11 = Utf8               Prettyizer
  #12 = Utf8               Prettyizer$
  #13 = Utf8               (Lorg/scalactic/PrettyMethods;Ljava/lang/Object;Lorg/scalactic/Prettifier;)Lorg/scalactic/PrettyMethods$Prettyizer;
  #14 = Utf8               $this
  #15 = Utf8               o
  #16 = Utf8               prettifier
  #17 = Utf8               (Ljava/lang/Object;Lorg/scalactic/Prettifier;)Lorg/scalactic/PrettyMethods$Prettyizer;
  #18 = NameAndType        #11:#17        // Prettyizer:(Ljava/lang/Object;Lorg/scalactic/Prettifier;)Lorg/scalactic/PrettyMethods$Prettyizer;
  #19 = InterfaceMethodref #2.#18         // org/scalactic/PrettyMethods.Prettyizer:(Ljava/lang/Object;Lorg/scalactic/Prettifier;)Lorg/scalactic/PrettyMethods$Prettyizer;
  #20 = Utf8               Lorg/scalactic/PrettyMethods;
  #21 = Utf8               Ljava/lang/Object;
  #22 = Utf8               Lorg/scalactic/Prettifier;
  #23 = Utf8               <init>
  #24 = Utf8               (Lorg/scalactic/PrettyMethods;Ljava/lang/Object;Lorg/scalactic/Prettifier;)V
  #25 = NameAndType        #23:#24        // "<init>":(Lorg/scalactic/PrettyMethods;Ljava/lang/Object;Lorg/scalactic/Prettifier;)V
  #26 = Methodref          #10.#25        // org/scalactic/PrettyMethods$Prettyizer."<init>":(Lorg/scalactic/PrettyMethods;Ljava/lang/Object;Lorg/scalactic/Prettifier;)V
  #27 = Utf8               this
  #28 = Utf8               $init$
  #29 = Utf8               (Lorg/scalactic/PrettyMethods;)V
  #30 = Utf8               Code
  #31 = Utf8               LineNumberTable
  #32 = Utf8               LocalVariableTable
  #33 = Utf8               MethodParameters
  #34 = Utf8               InnerClasses
  #35 = Utf8               SourceFile
  #36 = Utf8               RuntimeVisibleAnnotations
  #37 = Utf8               ScalaInlineInfo
  #38 = Utf8               ScalaSig
{
  public static org.scalactic.PrettyMethods$Prettyizer Prettyizer$(org.scalactic.PrettyMethods, java.lang.Object, org.scalactic.Prettifier);
    descriptor: (Lorg/scalactic/PrettyMethods;Ljava/lang/Object;Lorg/scalactic/Prettifier;)Lorg/scalactic/PrettyMethods$Prettyizer;
    flags: (0x1009) ACC_PUBLIC, ACC_STATIC, ACC_SYNTHETIC
    Code:
      stack=3, locals=3, args_size=3
         0: aload_0
         1: aload_1
         2: aload_2
         3: invokespecial #19                 // InterfaceMethod Prettyizer:(Ljava/lang/Object;Lorg/scalactic/Prettifier;)Lorg/scalactic/PrettyMethods$Prettyizer;
         6: areturn
      LineNumberTable:
        line 37: 0
      LocalVariableTable:
        Start  Length  Slot  Name   Signature
            0       7     0 $this   Lorg/scalactic/PrettyMethods;
            0       7     1     o   Ljava/lang/Object;
            0       7     2 prettifier   Lorg/scalactic/Prettifier;
    MethodParameters:
      Name                           Flags
      $this                          final synthetic
      o                              final
      prettifier                     final

  public default org.scalactic.PrettyMethods$Prettyizer Prettyizer(java.lang.Object, org.scalactic.Prettifier);
    descriptor: (Ljava/lang/Object;Lorg/scalactic/Prettifier;)Lorg/scalactic/PrettyMethods$Prettyizer;
    flags: (0x0001) ACC_PUBLIC
    Code:
      stack=5, locals=3, args_size=3
         0: new           #10                 // class org/scalactic/PrettyMethods$Prettyizer
         3: dup
         4: aload_0
         5: aload_1
         6: aload_2
         7: invokespecial #26                 // Method org/scalactic/PrettyMethods$Prettyizer."<init>":(Lorg/scalactic/PrettyMethods;Ljava/lang/Object;Lorg/scalactic/Prettifier;)V
        10: areturn
      LineNumberTable:
        line 37: 0
      LocalVariableTable:
        Start  Length  Slot  Name   Signature
            0      11     0  this   Lorg/scalactic/PrettyMethods;
            0      11     1     o   Ljava/lang/Object;
            0      11     2 prettifier   Lorg/scalactic/Prettifier;
    MethodParameters:
      Name                           Flags
      o                              final
      prettifier                     final

  public static void $init$(org.scalactic.PrettyMethods);
    descriptor: (Lorg/scalactic/PrettyMethods;)V
    flags: (0x0009) ACC_PUBLIC, ACC_STATIC
    Code:
      stack=0, locals=1, args_size=1
         0: return
      LineNumberTable:
        line 22: 0
      LocalVariableTable:
        Start  Length  Slot  Name   Signature
            0       1     0 $this   Lorg/scalactic/PrettyMethods;
    MethodParameters:
      Name                           Flags
      $this                          final synthetic
}
InnerClasses:
  public #11= #10 of #2;                  // Prettyizer=class org/scalactic/PrettyMethods$Prettyizer of class org/scalactic/PrettyMethods
SourceFile: "PrettyMethods.scala"
RuntimeVisibleAnnotations:
  0: #6(#7=s#8)
    scala.reflect.ScalaSignature(
      bytes="\u0006\u0005\u00193qa\u0003\u0007\u0011\u0002\u0007\u0005\u0011\u0003C\u0003\u0019\u0001\u0011\u0005\u0011D\u0002\u0003\u001e\u0001\u0005q\u0002\u0002C\u0010\u0003\u0005\u0003\u0005\u000b\u0011\u0002\u0011\t\u0011\r\u0012!\u0011!Q\u0001\f\u0011BQ\u0001\u000b\u0002\u0005\u0002%BQa\f\u0002\u0005\u0002ABq\u0001\u0010\u0001\u0002\u0002\u0013\rQhB\u0003B\u0019!\u0005!IB\u0003\f\u0019!\u00051\tC\u0003)\u0013\u0011\u0005QIA\u0007Qe\u0016$H/_\'fi\"|Gm\u001d\u0006\u0003\u001b9\t\u0011b]2bY\u0006\u001cG/[2\u000b\u0003=\t1a\u001c:h\u0007\u0001\u0019\"\u0001\u0001\n\u0011\u0005M1R\"\u0001\u000b\u000b\u0003U\tQa]2bY\u0006L!a\u0006\u000b\u0003\r\u0005s\u0017PU3g\u0003\u0019!\u0013N\\5uIQ\t!\u0004\u0005\u0002\u00147%\u0011A\u0004\u0006\u0002\u0005+:LGO\u0001\u0006Qe\u0016$H/_5{KJ\u001c\"A\u0001\n\u0002\u0003=\u0004\"aE\u0011\n\u0005\t\"\"aA!os\u0006Q\u0001O]3ui&4\u0017.\u001a:\u0011\u0005\u00152S\"\u0001\u0007\n\u0005\u001db!A\u0003)sKR$\u0018NZ5fe\u00061A(\u001b8jiz\"\"A\u000b\u0018\u0015\u0005-j\u0003C\u0001\u0017\u0003\u001b\u0005\u0001\u0001\"B\u0012\u0006\u0001\b!\u0003\"B\u0010\u0006\u0001\u0004\u0001\u0013A\u00029sKR$\u00180F\u00012!\t\u0011\u0014H\u0004\u00024oA\u0011A\u0007F\u0007\u0002k)\u0011a\u0007E\u0001\u0007yI|w\u000e\u001e \n\u0005a\"\u0012A\u0002)sK\u0012,g-\u0003\u0002;w\t11\u000b\u001e:j]\u001eT!\u0001\u000f\u000b\u0002\u0015A\u0013X\r\u001e;zSj,\'\u000f\u0006\u0002?\u0001R\u00111f\u0010\u0005\u0006G\u001d\u0001\u001d\u0001\n\u0005\u0006?\u001d\u0001\r\u0001I\u0001\u000e!J,G\u000f^=NKRDw\u000eZ:\u0011\u0005\u0015J1cA\u0005\u0013\tB\u0011Q\u0005\u0001\u000b\u0002\u0005\u0002"
    )
  ScalaInlineInfo: length = 0x13 (unknown attribute)
   01 00 00 03 00 1C 00 1D 01 00 0B 00 11 00 00 0C
   00 0D 01
  ScalaSig: length = 0x3 (unknown attribute)
   05 02 00
