Classfile /Users/mw/Projects/slang-braindump/.jar/jar8/assemble/slang-braindump/assemble/content/org/scalactic/Prettifier$$anon$1.class
  Last modified May 29, 2022; size 1280 bytes
  SHA-256 checksum 1d643d8b32a6ff2fe36e5a1f4a0ae689477e66c4e85e9dd2c65cfeb62f507a20
  Compiled from "Prettifier.scala"
public final class org.scalactic.Prettifier$$anon$1 implements org.scalactic.Prettifier
  minor version: 0
  major version: 52
  flags: (0x0031) ACC_PUBLIC, ACC_FINAL, ACC_SUPER
  this_class: #2                          // org/scalactic/Prettifier$$anon$1
  super_class: #4                         // java/lang/Object
  interfaces: 1, fields: 1, methods: 3, attributes: 5
Constant pool:
   #1 = Utf8               org/scalactic/Prettifier$$anon$1
   #2 = Class              #1             // org/scalactic/Prettifier$$anon$1
   #3 = Utf8               java/lang/Object
   #4 = Class              #3             // java/lang/Object
   #5 = Utf8               org/scalactic/Prettifier
   #6 = Class              #5             // org/scalactic/Prettifier
   #7 = Utf8               Prettifier.scala
   #8 = Utf8               org/scalactic/Prettifier$
   #9 = Class              #8             // org/scalactic/Prettifier$
  #10 = Utf8               apply
  #11 = Utf8               (Lscala/PartialFunction;)Lorg/scalactic/Prettifier;
  #12 = NameAndType        #10:#11        // apply:(Lscala/PartialFunction;)Lorg/scalactic/Prettifier;
  #13 = Utf8               fun$1
  #14 = Utf8               Lscala/PartialFunction;
  #15 = Utf8               (Ljava/lang/Object;Ljava/lang/Object;)Lorg/scalactic/PrettyPair;
  #16 = Utf8               left
  #17 = Utf8               right
  #18 = Utf8               apply$
  #19 = Utf8               (Lorg/scalactic/Prettifier;Ljava/lang/Object;Ljava/lang/Object;)Lorg/scalactic/PrettyPair;
  #20 = NameAndType        #18:#19        // apply$:(Lorg/scalactic/Prettifier;Ljava/lang/Object;Ljava/lang/Object;)Lorg/scalactic/PrettyPair;
  #21 = InterfaceMethodref #6.#20         // org/scalactic/Prettifier.apply$:(Lorg/scalactic/Prettifier;Ljava/lang/Object;Ljava/lang/Object;)Lorg/scalactic/PrettyPair;
  #22 = Utf8               this
  #23 = Utf8               Lorg/scalactic/Prettifier$$anon$1;
  #24 = Utf8               Ljava/lang/Object;
  #25 = Utf8               (Ljava/lang/Object;)Ljava/lang/String;
  #26 = Utf8               o
  #27 = NameAndType        #13:#14        // fun$1:Lscala/PartialFunction;
  #28 = Fieldref           #2.#27         // org/scalactic/Prettifier$$anon$1.fun$1:Lscala/PartialFunction;
  #29 = Utf8               scala/PartialFunction
  #30 = Class              #29            // scala/PartialFunction
  #31 = Utf8               (Ljava/lang/Object;)Ljava/lang/Object;
  #32 = NameAndType        #10:#31        // apply:(Ljava/lang/Object;)Ljava/lang/Object;
  #33 = InterfaceMethodref #30.#32        // scala/PartialFunction.apply:(Ljava/lang/Object;)Ljava/lang/Object;
  #34 = Utf8               java/lang/String
  #35 = Class              #34            // java/lang/String
  #36 = Utf8               <init>
  #37 = Utf8               (Lscala/PartialFunction;)V
  #38 = Utf8               ()V
  #39 = NameAndType        #36:#38        // "<init>":()V
  #40 = Methodref          #4.#39         // java/lang/Object."<init>":()V
  #41 = Utf8               $init$
  #42 = Utf8               (Lorg/scalactic/Prettifier;)V
  #43 = NameAndType        #41:#42        // $init$:(Lorg/scalactic/Prettifier;)V
  #44 = InterfaceMethodref #6.#43         // org/scalactic/Prettifier.$init$:(Lorg/scalactic/Prettifier;)V
  #45 = Utf8               Code
  #46 = Utf8               LineNumberTable
  #47 = Utf8               LocalVariableTable
  #48 = Utf8               MethodParameters
  #49 = Utf8               InnerClasses
  #50 = Utf8               EnclosingMethod
  #51 = Utf8               SourceFile
  #52 = Utf8               ScalaInlineInfo
  #53 = Utf8               Scala
{
  private final scala.PartialFunction fun$1;
    descriptor: Lscala/PartialFunction;
    flags: (0x0012) ACC_PRIVATE, ACC_FINAL

  public org.scalactic.PrettyPair apply(java.lang.Object, java.lang.Object);
    descriptor: (Ljava/lang/Object;Ljava/lang/Object;)Lorg/scalactic/PrettyPair;
    flags: (0x0001) ACC_PUBLIC
    Code:
      stack=3, locals=3, args_size=3
         0: aload_0
         1: aload_1
         2: aload_2
         3: invokestatic  #21                 // InterfaceMethod org/scalactic/Prettifier.apply$:(Lorg/scalactic/Prettifier;Ljava/lang/Object;Ljava/lang/Object;)Lorg/scalactic/PrettyPair;
         6: areturn
      LineNumberTable:
        line 145: 0
      LocalVariableTable:
        Start  Length  Slot  Name   Signature
            0       7     0  this   Lorg/scalactic/Prettifier$$anon$1;
            0       7     1  left   Ljava/lang/Object;
            0       7     2 right   Ljava/lang/Object;
    MethodParameters:
      Name                           Flags
      left                           final
      right                          final

  public java.lang.String apply(java.lang.Object);
    descriptor: (Ljava/lang/Object;)Ljava/lang/String;
    flags: (0x0001) ACC_PUBLIC
    Code:
      stack=2, locals=2, args_size=2
         0: aload_0
         1: getfield      #28                 // Field fun$1:Lscala/PartialFunction;
         4: aload_1
         5: invokeinterface #33,  2           // InterfaceMethod scala/PartialFunction.apply:(Ljava/lang/Object;)Ljava/lang/Object;
        10: checkcast     #35                 // class java/lang/String
        13: areturn
      LineNumberTable:
        line 146: 0
      LocalVariableTable:
        Start  Length  Slot  Name   Signature
            0      14     0  this   Lorg/scalactic/Prettifier$$anon$1;
            0      14     1     o   Ljava/lang/Object;
    MethodParameters:
      Name                           Flags
      o                              final

  public org.scalactic.Prettifier$$anon$1(scala.PartialFunction);
    descriptor: (Lscala/PartialFunction;)V
    flags: (0x0001) ACC_PUBLIC
    Code:
      stack=2, locals=2, args_size=2
         0: aload_0
         1: aload_1
         2: putfield      #28                 // Field fun$1:Lscala/PartialFunction;
         5: aload_0
         6: invokespecial #40                 // Method java/lang/Object."<init>":()V
         9: aload_0
        10: invokestatic  #44                 // InterfaceMethod org/scalactic/Prettifier.$init$:(Lorg/scalactic/Prettifier;)V
        13: return
      LineNumberTable:
        line 144: 0
        line 145: 5
      LocalVariableTable:
        Start  Length  Slot  Name   Signature
            0      14     0  this   Lorg/scalactic/Prettifier$$anon$1;
            0      14     1 fun$1   Lscala/PartialFunction;
    MethodParameters:
      Name                           Flags
      fun$1                          final
}
InnerClasses:
  public final #2;                        // class org/scalactic/Prettifier$$anon$1
EnclosingMethod: #9.#12                 // org.scalactic.Prettifier$.apply
SourceFile: "Prettifier.scala"
  ScalaInlineInfo: length = 0x13 (unknown attribute)
   01 01 00 03 00 24 00 25 01 00 0A 00 19 01 00 0A
   00 0F 01
  Scala: length = 0x0 (unknown attribute)

