Classfile /Users/mw/Projects/slang-braindump/.jar/jar8/assemble/slang-braindump/assemble/content/org/scalactic/PrettyMethods$Prettyizer.class
  Last modified May 29, 2022; size 1147 bytes
  SHA-256 checksum fd69aba22af1e76ee6bef879e2e2f675f1c914df6defebb8706604f8b57321de
  Compiled from "PrettyMethods.scala"
public class org.scalactic.PrettyMethods$Prettyizer
  minor version: 0
  major version: 52
  flags: (0x0021) ACC_PUBLIC, ACC_SUPER
  this_class: #2                          // org/scalactic/PrettyMethods$Prettyizer
  super_class: #4                         // java/lang/Object
  interfaces: 0, fields: 3, methods: 3, attributes: 4
Constant pool:
   #1 = Utf8               org/scalactic/PrettyMethods$Prettyizer
   #2 = Class              #1             // org/scalactic/PrettyMethods$Prettyizer
   #3 = Utf8               java/lang/Object
   #4 = Class              #3             // java/lang/Object
   #5 = Utf8               PrettyMethods.scala
   #6 = Utf8               org/scalactic/PrettyMethods
   #7 = Class              #6             // org/scalactic/PrettyMethods
   #8 = Utf8               Prettyizer
   #9 = Utf8               o
  #10 = Utf8               Ljava/lang/Object;
  #11 = Utf8               prettifier
  #12 = Utf8               Lorg/scalactic/Prettifier;
  #13 = Utf8               $outer
  #14 = Utf8               Lorg/scalactic/PrettyMethods;
  #15 = Utf8               pretty
  #16 = Utf8               ()Ljava/lang/String;
  #17 = NameAndType        #11:#12        // prettifier:Lorg/scalactic/Prettifier;
  #18 = Fieldref           #2.#17         // org/scalactic/PrettyMethods$Prettyizer.prettifier:Lorg/scalactic/Prettifier;
  #19 = NameAndType        #9:#10         // o:Ljava/lang/Object;
  #20 = Fieldref           #2.#19         // org/scalactic/PrettyMethods$Prettyizer.o:Ljava/lang/Object;
  #21 = Utf8               org/scalactic/Prettifier
  #22 = Class              #21            // org/scalactic/Prettifier
  #23 = Utf8               apply
  #24 = Utf8               (Ljava/lang/Object;)Ljava/lang/String;
  #25 = NameAndType        #23:#24        // apply:(Ljava/lang/Object;)Ljava/lang/String;
  #26 = InterfaceMethodref #22.#25        // org/scalactic/Prettifier.apply:(Ljava/lang/Object;)Ljava/lang/String;
  #27 = Utf8               this
  #28 = Utf8               Lorg/scalactic/PrettyMethods$Prettyizer;
  #29 = Utf8               org$scalactic$PrettyMethods$Prettyizer$$$outer
  #30 = Utf8               ()Lorg/scalactic/PrettyMethods;
  #31 = NameAndType        #13:#14        // $outer:Lorg/scalactic/PrettyMethods;
  #32 = Fieldref           #2.#31         // org/scalactic/PrettyMethods$Prettyizer.$outer:Lorg/scalactic/PrettyMethods;
  #33 = Utf8               <init>
  #34 = Utf8               (Lorg/scalactic/PrettyMethods;Ljava/lang/Object;Lorg/scalactic/Prettifier;)V
  #35 = Utf8               ()V
  #36 = NameAndType        #33:#35        // "<init>":()V
  #37 = Methodref          #4.#36         // java/lang/Object."<init>":()V
  #38 = Utf8               Code
  #39 = Utf8               LineNumberTable
  #40 = Utf8               LocalVariableTable
  #41 = Utf8               StackMapTable
  #42 = Utf8               MethodParameters
  #43 = Utf8               InnerClasses
  #44 = Utf8               SourceFile
  #45 = Utf8               ScalaInlineInfo
  #46 = Utf8               Scala
{
  private final java.lang.Object o;
    descriptor: Ljava/lang/Object;
    flags: (0x0012) ACC_PRIVATE, ACC_FINAL

  private final org.scalactic.Prettifier prettifier;
    descriptor: Lorg/scalactic/Prettifier;
    flags: (0x0012) ACC_PRIVATE, ACC_FINAL

  public final org.scalactic.PrettyMethods $outer;
    descriptor: Lorg/scalactic/PrettyMethods;
    flags: (0x1011) ACC_PUBLIC, ACC_FINAL, ACC_SYNTHETIC

  public java.lang.String pretty();
    descriptor: ()Ljava/lang/String;
    flags: (0x0001) ACC_PUBLIC
    Code:
      stack=2, locals=1, args_size=1
         0: aload_0
         1: getfield      #18                 // Field prettifier:Lorg/scalactic/Prettifier;
         4: aload_0
         5: getfield      #20                 // Field o:Ljava/lang/Object;
         8: invokeinterface #26,  2           // InterfaceMethod org/scalactic/Prettifier.apply:(Ljava/lang/Object;)Ljava/lang/String;
        13: areturn
      LineNumberTable:
        line 42: 0
      LocalVariableTable:
        Start  Length  Slot  Name   Signature
            0      14     0  this   Lorg/scalactic/PrettyMethods$Prettyizer;

  public org.scalactic.PrettyMethods org$scalactic$PrettyMethods$Prettyizer$$$outer();
    descriptor: ()Lorg/scalactic/PrettyMethods;
    flags: (0x1001) ACC_PUBLIC, ACC_SYNTHETIC
    Code:
      stack=1, locals=1, args_size=1
         0: aload_0
         1: getfield      #32                 // Field $outer:Lorg/scalactic/PrettyMethods;
         4: areturn
      LineNumberTable:
        line 37: 0
      LocalVariableTable:
        Start  Length  Slot  Name   Signature
            0       5     0  this   Lorg/scalactic/PrettyMethods$Prettyizer;

  public org.scalactic.PrettyMethods$Prettyizer(org.scalactic.PrettyMethods, java.lang.Object, org.scalactic.Prettifier);
    descriptor: (Lorg/scalactic/PrettyMethods;Ljava/lang/Object;Lorg/scalactic/Prettifier;)V
    flags: (0x0001) ACC_PUBLIC
    Code:
      stack=2, locals=4, args_size=4
         0: aload_0
         1: aload_2
         2: putfield      #20                 // Field o:Ljava/lang/Object;
         5: aload_0
         6: aload_3
         7: putfield      #18                 // Field prettifier:Lorg/scalactic/Prettifier;
        10: aload_1
        11: ifnonnull     16
        14: aconst_null
        15: athrow
        16: aload_0
        17: aload_1
        18: putfield      #32                 // Field $outer:Lorg/scalactic/PrettyMethods;
        21: aload_0
        22: invokespecial #37                 // Method java/lang/Object."<init>":()V
        25: return
      StackMapTable: number_of_entries = 1
        frame_type = 16 /* same */
      LineNumberTable:
        line 37: 0
        line 44: 21
        line 37: 25
      LocalVariableTable:
        Start  Length  Slot  Name   Signature
            0      26     0  this   Lorg/scalactic/PrettyMethods$Prettyizer;
            0      26     1 $outer   Lorg/scalactic/PrettyMethods;
            0      26     2     o   Ljava/lang/Object;
            0      26     3 prettifier   Lorg/scalactic/Prettifier;
    MethodParameters:
      Name                           Flags
      $outer                         final synthetic
      o                              final
      prettifier                     final
}
InnerClasses:
  public #8= #2 of #7;                    // Prettyizer=class org/scalactic/PrettyMethods$Prettyizer of class org/scalactic/PrettyMethods
SourceFile: "PrettyMethods.scala"
  ScalaInlineInfo: length = 0x13 (unknown attribute)
   01 00 00 03 00 21 00 22 00 00 1D 00 1E 00 00 0F
   00 10 00
  Scala: length = 0x0 (unknown attribute)

