Classfile /Users/mw/Projects/slang-braindump/.jar/jar8/assemble/slang-braindump/assemble/content/org/scalactic/PrettyMethods$.class
  Last modified May 29, 2022; size 1038 bytes
  SHA-256 checksum 76c9adad8dd4f98bb1130a9538bbb8cec49d00c8dbf216594300bcff2543a513
  Compiled from "PrettyMethods.scala"
public final class org.scalactic.PrettyMethods$ implements org.scalactic.PrettyMethods
  minor version: 0
  major version: 52
  flags: (0x0031) ACC_PUBLIC, ACC_FINAL, ACC_SUPER
  this_class: #2                          // org/scalactic/PrettyMethods$
  super_class: #4                         // java/lang/Object
  interfaces: 1, fields: 1, methods: 3, attributes: 4
Constant pool:
   #1 = Utf8               org/scalactic/PrettyMethods$
   #2 = Class              #1             // org/scalactic/PrettyMethods$
   #3 = Utf8               java/lang/Object
   #4 = Class              #3             // java/lang/Object
   #5 = Utf8               org/scalactic/PrettyMethods
   #6 = Class              #5             // org/scalactic/PrettyMethods
   #7 = Utf8               PrettyMethods.scala
   #8 = Utf8               org/scalactic/PrettyMethods$Prettyizer
   #9 = Class              #8             // org/scalactic/PrettyMethods$Prettyizer
  #10 = Utf8               Prettyizer
  #11 = Utf8               MODULE$
  #12 = Utf8               Lorg/scalactic/PrettyMethods$;
  #13 = Utf8               <clinit>
  #14 = Utf8               ()V
  #15 = Utf8               <init>
  #16 = NameAndType        #15:#14        // "<init>":()V
  #17 = Methodref          #2.#16         // org/scalactic/PrettyMethods$."<init>":()V
  #18 = NameAndType        #11:#12        // MODULE$:Lorg/scalactic/PrettyMethods$;
  #19 = Fieldref           #2.#18         // org/scalactic/PrettyMethods$.MODULE$:Lorg/scalactic/PrettyMethods$;
  #20 = Utf8               $init$
  #21 = Utf8               (Lorg/scalactic/PrettyMethods;)V
  #22 = NameAndType        #20:#21        // $init$:(Lorg/scalactic/PrettyMethods;)V
  #23 = InterfaceMethodref #6.#22         // org/scalactic/PrettyMethods.$init$:(Lorg/scalactic/PrettyMethods;)V
  #24 = Utf8               (Ljava/lang/Object;Lorg/scalactic/Prettifier;)Lorg/scalactic/PrettyMethods$Prettyizer;
  #25 = Utf8               o
  #26 = Utf8               prettifier
  #27 = Utf8               Prettyizer$
  #28 = Utf8               (Lorg/scalactic/PrettyMethods;Ljava/lang/Object;Lorg/scalactic/Prettifier;)Lorg/scalactic/PrettyMethods$Prettyizer;
  #29 = NameAndType        #27:#28        // Prettyizer$:(Lorg/scalactic/PrettyMethods;Ljava/lang/Object;Lorg/scalactic/Prettifier;)Lorg/scalactic/PrettyMethods$Prettyizer;
  #30 = InterfaceMethodref #6.#29         // org/scalactic/PrettyMethods.Prettyizer$:(Lorg/scalactic/PrettyMethods;Ljava/lang/Object;Lorg/scalactic/Prettifier;)Lorg/scalactic/PrettyMethods$Prettyizer;
  #31 = Utf8               this
  #32 = Utf8               Ljava/lang/Object;
  #33 = Utf8               Lorg/scalactic/Prettifier;
  #34 = Methodref          #4.#16         // java/lang/Object."<init>":()V
  #35 = Utf8               Code
  #36 = Utf8               LineNumberTable
  #37 = Utf8               LocalVariableTable
  #38 = Utf8               MethodParameters
  #39 = Utf8               InnerClasses
  #40 = Utf8               SourceFile
  #41 = Utf8               ScalaInlineInfo
  #42 = Utf8               Scala
{
  public static final org.scalactic.PrettyMethods$ MODULE$;
    descriptor: Lorg/scalactic/PrettyMethods$;
    flags: (0x0019) ACC_PUBLIC, ACC_STATIC, ACC_FINAL

  public static {};
    descriptor: ()V
    flags: (0x0009) ACC_PUBLIC, ACC_STATIC
    Code:
      stack=2, locals=0, args_size=0
         0: new           #2                  // class org/scalactic/PrettyMethods$
         3: dup
         4: invokespecial #17                 // Method "<init>":()V
         7: putstatic     #19                 // Field MODULE$:Lorg/scalactic/PrettyMethods$;
        10: getstatic     #19                 // Field MODULE$:Lorg/scalactic/PrettyMethods$;
        13: invokestatic  #23                 // InterfaceMethod org/scalactic/PrettyMethods.$init$:(Lorg/scalactic/PrettyMethods;)V
        16: return
      LineNumberTable:
        line 50: 0

  public org.scalactic.PrettyMethods$Prettyizer Prettyizer(java.lang.Object, org.scalactic.Prettifier);
    descriptor: (Ljava/lang/Object;Lorg/scalactic/Prettifier;)Lorg/scalactic/PrettyMethods$Prettyizer;
    flags: (0x0001) ACC_PUBLIC
    Code:
      stack=3, locals=3, args_size=3
         0: aload_0
         1: aload_1
         2: aload_2
         3: invokestatic  #30                 // InterfaceMethod org/scalactic/PrettyMethods.Prettyizer$:(Lorg/scalactic/PrettyMethods;Ljava/lang/Object;Lorg/scalactic/Prettifier;)Lorg/scalactic/PrettyMethods$Prettyizer;
         6: areturn
      LineNumberTable:
        line 50: 0
      LocalVariableTable:
        Start  Length  Slot  Name   Signature
            0       7     0  this   Lorg/scalactic/PrettyMethods$;
            0       7     1     o   Ljava/lang/Object;
            0       7     2 prettifier   Lorg/scalactic/Prettifier;
    MethodParameters:
      Name                           Flags
      o                              final
      prettifier                     final

  private org.scalactic.PrettyMethods$();
    descriptor: ()V
    flags: (0x0002) ACC_PRIVATE
    Code:
      stack=1, locals=1, args_size=1
         0: aload_0
         1: invokespecial #34                 // Method java/lang/Object."<init>":()V
         4: return
      LineNumberTable:
        line 50: 0
      LocalVariableTable:
        Start  Length  Slot  Name   Signature
            0       5     0  this   Lorg/scalactic/PrettyMethods$;
}
InnerClasses:
  public #10= #9 of #6;                   // Prettyizer=class org/scalactic/PrettyMethods$Prettyizer of class org/scalactic/PrettyMethods
SourceFile: "PrettyMethods.scala"
  ScalaInlineInfo: length = 0xE (unknown attribute)
   01 01 00 02 00 0F 00 0E 01 00 0A 00 18 01
  Scala: length = 0x0 (unknown attribute)

