Classfile /Users/mw/Projects/slang-braindump/.jar/jar8/assemble/slang-braindump/assemble/content/org/scalactic/SetEqualityConstraints.class
  Last modified May 29, 2022; size 2120 bytes
  SHA-256 checksum 34ba2358303f989d7e6891a464208c91e94cc3b94cccc67ea423757c362b5838
  Compiled from "SetEqualityConstraints.scala"
public interface org.scalactic.SetEqualityConstraints
  minor version: 0
  major version: 52
  flags: (0x0601) ACC_PUBLIC, ACC_INTERFACE, ACC_ABSTRACT
  this_class: #2                          // org/scalactic/SetEqualityConstraints
  super_class: #4                         // java/lang/Object
  interfaces: 0, fields: 0, methods: 3, attributes: 5
Constant pool:
   #1 = Utf8               org/scalactic/SetEqualityConstraints
   #2 = Class              #1             // org/scalactic/SetEqualityConstraints
   #3 = Utf8               java/lang/Object
   #4 = Class              #3             // java/lang/Object
   #5 = Utf8               SetEqualityConstraints.scala
   #6 = Utf8               Lscala/reflect/ScalaSignature;
   #7 = Utf8               bytes
   #8 = Utf8               \u0006\u0005]3qAB\u0004\u0011\u0002\u0007\u0005A\u0002C\u0003\u0014\u0001\u0011\u0005A\u0003C\u0003\u0019\u0001\u0011\r\u0011dB\u0003R\u000f!\u0005!KB\u0003\u0007\u000f!\u00051\u000bC\u0003V\t\u0011\u0005aK\u0001\fTKR,\u0015/^1mSRL8i\u001c8tiJ\f\u0017N\u001c;t\u0015\tA\u0011\"A\u0005tG\u0006d\u0017m\u0019;jG*\t!\"A\u0002pe\u001e\u001c\u0001a\u0005\u0002\u0001\u001bA\u0011a\"E\u0007\u0002\u001f)\t\u0001#A\u0003tG\u0006d\u0017-\u0003\u0002\u0013\u001f\t1\u0011I\\=SK\u001a\fa\u0001J5oSR$C#A\u000b\u0011\u000591\u0012BA\f\u0010\u0005\u0011)f.\u001b;\u0002+M,G/R9vC2LG/_\"p]N$(/Y5oiV)!dO\u0011H}Q\u00191$\u0013(\u0011\tqir$P\u0007\u0002\u000f%\u0011ad\u0002\u0002\t\u0007\u0006tW)];bYB\u0019\u0001%\t\u001e\r\u0001\u0011)!E\u0001b\u0001G\t\u00111)Q\u000b\u0003IQ\n\"!\n\u0015\u0011\u000591\u0013BA\u0014\u0010\u0005\u001dqu\u000e\u001e5j]\u001e\u00042!\u000b\u00194\u001d\tQSF\u0004\u0002\u000fW%\u0011AfD\u0001\u000bG>dG.Z2uS>t\u0017B\u0001\u00180\u0003\u001d\u0001\u0018mY6bO\u0016T!\u0001L\b\n\u0005E\u0012$AB$f]N+GO\u0003\u0002/_A\u0011\u0001\u0005\u000e\u0003\u0006k\u0005\u0012\rA\u000e\u0002\u0003K\u0006\f\"!J\u001c\u0011\u00059A\u0014BA\u001d\u0010\u0005\r\te.\u001f\t\u0003Am\"Q\u0001\u0010\u0002C\u0002Y\u0012!!R!\u0011\u0007\u0001rd\tB\u0003@\u0005\t\u0007\u0001I\u0001\u0002D\u0005V\u0011\u0011\tR\t\u0003K\t\u00032!\u000b\u0019D!\t\u0001C\tB\u0003F}\t\u0007aG\u0001\u0002fEB\u0011\u0001e\u0012\u0003\u0006\u0011\n\u0011\rA\u000e\u0002\u0003\u000b\nCQA\u0013\u0002A\u0004-\u000b1\"Z9vC2LG/_(g\u0003B\u0019A\u0004T\u0010\n\u00055;!\u0001C#rk\u0006d\u0017\u000e^=\t\u000b=\u0013\u00019\u0001)\u0002\u0005\u00154\b\u0003\u0002\u000f\u001eu\u0019\u000bacU3u\u000bF,\u0018\r\\5us\u000e{gn\u001d;sC&tGo\u001d\t\u00039\u0011\u00192\u0001B\u0007U!\ta\u0002!\u0001\u0004=S:LGO\u0010\u000b\u0002%\u0002
   #9 = Utf8               org/scalactic/TripleEqualsSupport$EqualityConstraint
  #10 = Class              #9             // org/scalactic/TripleEqualsSupport$EqualityConstraint
  #11 = Utf8               org/scalactic/TripleEqualsSupport
  #12 = Class              #11            // org/scalactic/TripleEqualsSupport
  #13 = Utf8               EqualityConstraint
  #14 = Utf8               setEqualityConstraint$
  #15 = Utf8               (Lorg/scalactic/SetEqualityConstraints;Lorg/scalactic/Equality;Lorg/scalactic/CanEqual;)Lorg/scalactic/CanEqual;
  #16 = Utf8               $this
  #17 = Utf8               equalityOfA
  #18 = Utf8               ev
  #19 = Utf8               setEqualityConstraint
  #20 = Utf8               (Lorg/scalactic/Equality;Lorg/scalactic/CanEqual;)Lorg/scalactic/CanEqual;
  #21 = NameAndType        #19:#20        // setEqualityConstraint:(Lorg/scalactic/Equality;Lorg/scalactic/CanEqual;)Lorg/scalactic/CanEqual;
  #22 = InterfaceMethodref #2.#21         // org/scalactic/SetEqualityConstraints.setEqualityConstraint:(Lorg/scalactic/Equality;Lorg/scalactic/CanEqual;)Lorg/scalactic/CanEqual;
  #23 = Utf8               Lorg/scalactic/SetEqualityConstraints;
  #24 = Utf8               Lorg/scalactic/Equality;
  #25 = Utf8               Lorg/scalactic/CanEqual;
  #26 = Utf8               <EA:Ljava/lang/Object;CA::Lscala/collection/Set<Ljava/lang/Object;>;EB:Ljava/lang/Object;CB::Lscala/collection/Set<Ljava/lang/Object;>;>(Lorg/scalactic/Equality<TCA;>;Lorg/scalactic/CanEqual<TEA;TEB;>;)Lorg/scalactic/CanEqual<TCA;TCB;>;
  #27 = Utf8               <init>
  #28 = Utf8               (Lorg/scalactic/Equality;)V
  #29 = NameAndType        #27:#28        // "<init>":(Lorg/scalactic/Equality;)V
  #30 = Methodref          #10.#29        // org/scalactic/TripleEqualsSupport$EqualityConstraint."<init>":(Lorg/scalactic/Equality;)V
  #31 = Utf8               this
  #32 = Utf8               $init$
  #33 = Utf8               (Lorg/scalactic/SetEqualityConstraints;)V
  #34 = Utf8               Code
  #35 = Utf8               LineNumberTable
  #36 = Utf8               LocalVariableTable
  #37 = Utf8               MethodParameters
  #38 = Utf8               Signature
  #39 = Utf8               InnerClasses
  #40 = Utf8               SourceFile
  #41 = Utf8               RuntimeVisibleAnnotations
  #42 = Utf8               ScalaInlineInfo
  #43 = Utf8               ScalaSig
{
  public static org.scalactic.CanEqual setEqualityConstraint$(org.scalactic.SetEqualityConstraints, org.scalactic.Equality, org.scalactic.CanEqual);
    descriptor: (Lorg/scalactic/SetEqualityConstraints;Lorg/scalactic/Equality;Lorg/scalactic/CanEqual;)Lorg/scalactic/CanEqual;
    flags: (0x1009) ACC_PUBLIC, ACC_STATIC, ACC_SYNTHETIC
    Code:
      stack=3, locals=3, args_size=3
         0: aload_0
         1: aload_1
         2: aload_2
         3: invokespecial #22                 // InterfaceMethod setEqualityConstraint:(Lorg/scalactic/Equality;Lorg/scalactic/CanEqual;)Lorg/scalactic/CanEqual;
         6: areturn
      LineNumberTable:
        line 108: 0
      LocalVariableTable:
        Start  Length  Slot  Name   Signature
            0       7     0 $this   Lorg/scalactic/SetEqualityConstraints;
            0       7     1 equalityOfA   Lorg/scalactic/Equality;
            0       7     2    ev   Lorg/scalactic/CanEqual;
    MethodParameters:
      Name                           Flags
      $this                          final synthetic
      equalityOfA                    final
      ev                             final

  public default <EA extends java.lang.Object, CA extends scala.collection.Set<java.lang.Object>, EB extends java.lang.Object, CB extends scala.collection.Set<java.lang.Object>> org.scalactic.CanEqual<CA, CB> setEqualityConstraint(org.scalactic.Equality<CA>, org.scalactic.CanEqual<EA, EB>);
    descriptor: (Lorg/scalactic/Equality;Lorg/scalactic/CanEqual;)Lorg/scalactic/CanEqual;
    flags: (0x0001) ACC_PUBLIC
    Code:
      stack=3, locals=3, args_size=3
         0: new           #10                 // class org/scalactic/TripleEqualsSupport$EqualityConstraint
         3: dup
         4: aload_1
         5: invokespecial #30                 // Method org/scalactic/TripleEqualsSupport$EqualityConstraint."<init>":(Lorg/scalactic/Equality;)V
         8: areturn
      LineNumberTable:
        line 108: 0
      LocalVariableTable:
        Start  Length  Slot  Name   Signature
            0       9     0  this   Lorg/scalactic/SetEqualityConstraints;
            0       9     1 equalityOfA   Lorg/scalactic/Equality;
            0       9     2    ev   Lorg/scalactic/CanEqual;
    Signature: #26                          // <EA:Ljava/lang/Object;CA::Lscala/collection/Set<Ljava/lang/Object;>;EB:Ljava/lang/Object;CB::Lscala/collection/Set<Ljava/lang/Object;>;>(Lorg/scalactic/Equality<TCA;>;Lorg/scalactic/CanEqual<TEA;TEB;>;)Lorg/scalactic/CanEqual<TCA;TCB;>;
    MethodParameters:
      Name                           Flags
      equalityOfA                    final
      ev                             final

  public static void $init$(org.scalactic.SetEqualityConstraints);
    descriptor: (Lorg/scalactic/SetEqualityConstraints;)V
    flags: (0x0009) ACC_PUBLIC, ACC_STATIC
    Code:
      stack=0, locals=1, args_size=1
         0: return
      LineNumberTable:
        line 100: 0
      LocalVariableTable:
        Start  Length  Slot  Name   Signature
            0       1     0 $this   Lorg/scalactic/SetEqualityConstraints;
    MethodParameters:
      Name                           Flags
      $this                          final synthetic
}
InnerClasses:
  public static final #13= #10 of #12;    // EqualityConstraint=class org/scalactic/TripleEqualsSupport$EqualityConstraint of class org/scalactic/TripleEqualsSupport
SourceFile: "SetEqualityConstraints.scala"
RuntimeVisibleAnnotations:
  0: #6(#7=s#8)
    scala.reflect.ScalaSignature(
      bytes="\u0006\u0005]3qAB\u0004\u0011\u0002\u0007\u0005A\u0002C\u0003\u0014\u0001\u0011\u0005A\u0003C\u0003\u0019\u0001\u0011\r\u0011dB\u0003R\u000f!\u0005!KB\u0003\u0007\u000f!\u00051\u000bC\u0003V\t\u0011\u0005aK\u0001\fTKR,\u0015/^1mSRL8i\u001c8tiJ\f\u0017N\u001c;t\u0015\tA\u0011\"A\u0005tG\u0006d\u0017m\u0019;jG*\t!\"A\u0002pe\u001e\u001c\u0001a\u0005\u0002\u0001\u001bA\u0011a\"E\u0007\u0002\u001f)\t\u0001#A\u0003tG\u0006d\u0017-\u0003\u0002\u0013\u001f\t1\u0011I\\=SK\u001a\fa\u0001J5oSR$C#A\u000b\u0011\u000591\u0012BA\f\u0010\u0005\u0011)f.\u001b;\u0002+M,G/R9vC2LG/_\"p]N$(/Y5oiV)!dO\u0011H}Q\u00191$\u0013(\u0011\tqir$P\u0007\u0002\u000f%\u0011ad\u0002\u0002\t\u0007\u0006tW)];bYB\u0019\u0001%\t\u001e\r\u0001\u0011)!E\u0001b\u0001G\t\u00111)Q\u000b\u0003IQ\n\"!\n\u0015\u0011\u000591\u0013BA\u0014\u0010\u0005\u001dqu\u000e\u001e5j]\u001e\u00042!\u000b\u00194\u001d\tQSF\u0004\u0002\u000fW%\u0011AfD\u0001\u000bG>dG.Z2uS>t\u0017B\u0001\u00180\u0003\u001d\u0001\u0018mY6bO\u0016T!\u0001L\b\n\u0005E\u0012$AB$f]N+GO\u0003\u0002/_A\u0011\u0001\u0005\u000e\u0003\u0006k\u0005\u0012\rA\u000e\u0002\u0003K\u0006\f\"!J\u001c\u0011\u00059A\u0014BA\u001d\u0010\u0005\r\te.\u001f\t\u0003Am\"Q\u0001\u0010\u0002C\u0002Y\u0012!!R!\u0011\u0007\u0001rd\tB\u0003@\u0005\t\u0007\u0001I\u0001\u0002D\u0005V\u0011\u0011\tR\t\u0003K\t\u00032!\u000b\u0019D!\t\u0001C\tB\u0003F}\t\u0007aG\u0001\u0002fEB\u0011\u0001e\u0012\u0003\u0006\u0011\n\u0011\rA\u000e\u0002\u0003\u000b\nCQA\u0013\u0002A\u0004-\u000b1\"Z9vC2LG/_(g\u0003B\u0019A\u0004T\u0010\n\u00055;!\u0001C#rk\u0006d\u0017\u000e^=\t\u000b=\u0013\u00019\u0001)\u0002\u0005\u00154\b\u0003\u0002\u000f\u001eu\u0019\u000bacU3u\u000bF,\u0018\r\\5us\u000e{gn\u001d;sC&tGo\u001d\t\u00039\u0011\u00192\u0001B\u0007U!\ta\u0002!\u0001\u0004=S:LGO\u0010\u000b\u0002%\u0002"
    )
  ScalaInlineInfo: length = 0x13 (unknown attribute)
   01 00 00 03 00 20 00 21 01 00 13 00 14 00 00 0E
   00 0F 01
  ScalaSig: length = 0x3 (unknown attribute)
   05 02 00
