Classfile /Users/mw/Projects/slang-braindump/.jar/jar8/assemble/slang-braindump/assemble/content/org/scalactic/StringNormalizations.class
  Last modified May 29, 2022; size 1765 bytes
  SHA-256 checksum 37673e77583d1eb45e8c3016592348d9295d5c66305fb7068669e059b7a81b05
  Compiled from "StringNormalizations.scala"
public interface org.scalactic.StringNormalizations
  minor version: 0
  major version: 52
  flags: (0x0601) ACC_PUBLIC, ACC_INTERFACE, ACC_ABSTRACT
  this_class: #2                          // org/scalactic/StringNormalizations
  super_class: #4                         // java/lang/Object
  interfaces: 0, fields: 0, methods: 7, attributes: 5
Constant pool:
   #1 = Utf8               org/scalactic/StringNormalizations
   #2 = Class              #1             // org/scalactic/StringNormalizations
   #3 = Utf8               java/lang/Object
   #4 = Class              #3             // java/lang/Object
   #5 = Utf8               StringNormalizations.scala
   #6 = Utf8               Lscala/reflect/ScalaSignature;
   #7 = Utf8               bytes
   #8 = Utf8               \u0006\u0005M2q\u0001C\u0005\u0011\u0002\u0007\u0005a\u0002C\u0003\u0016\u0001\u0011\u0005a\u0003C\u0004\u001b\u0001\t\u0007I\u0011A\u000e\t\u000f-\u0002!\u0019!C\u00017!9A\u0006\u0001b\u0001\n\u0003Yr!B\u0017\n\u0011\u0003qc!\u0002\u0005\n\u0011\u0003y\u0003\"B\u0019\u0007\t\u0003\u0011$\u0001F*ue&twMT8s[\u0006d\u0017N_1uS>t7O\u0003\u0002\u000b\u0017\u0005I1oY1mC\u000e$\u0018n\u0019\u0006\u0002\u0019\u0005\u0019qN]4\u0004\u0001M\u0011\u0001a\u0004\t\u0003!Mi\u0011!\u0005\u0006\u0002%\u0005)1oY1mC&\u0011A#\u0005\u0002\u0007\u0003:L(+\u001a4\u0002\r\u0011Jg.\u001b;%)\u00059\u0002C\u0001\t\u0019\u0013\tI\u0012C\u0001\u0003V]&$\u0018A\u00037po\u0016\u00148)Y:fIV\tA\u0004E\u0002\u001e=\u0001j\u0011!C\u0005\u0003?%\u0011!\"\u00168jM>\u0014X.\u001b;z!\t\t\u0003F\u0004\u0002#MA\u00111%E\u0007\u0002I)\u0011Q%D\u0001\u0007yI|w\u000e\u001e \n\u0005\u001d\n\u0012A\u0002)sK\u0012,g-\u0003\u0002*U\t11\u000b\u001e:j]\u001eT!aJ\t\u0002\u0015U\u0004\b/\u001a:DCN,G-A\u0004ue&lW.\u001a3\u0002)M#(/\u001b8h\u001d>\u0014X.\u00197ju\u0006$\u0018n\u001c8t!\tibaE\u0002\u0007\u001fA\u0002\"!\b\u0001\u0002\rqJg.\u001b;?)\u0005q\u0003
   #9 = Utf8               org/scalactic/StringNormalizations$$anon$1
  #10 = Class              #9             // org/scalactic/StringNormalizations$$anon$1
  #11 = Utf8               org/scalactic/StringNormalizations$$anon$2
  #12 = Class              #11            // org/scalactic/StringNormalizations$$anon$2
  #13 = Utf8               org/scalactic/StringNormalizations$$anon$3
  #14 = Class              #13            // org/scalactic/StringNormalizations$$anon$3
  #15 = Utf8               org$scalactic$StringNormalizations$_setter_$lowerCased_$eq
  #16 = Utf8               (Lorg/scalactic/Uniformity;)V
  #17 = Utf8               (Lorg/scalactic/Uniformity<Ljava/lang/String;>;)V
  #18 = Utf8               x$1
  #19 = Utf8               org$scalactic$StringNormalizations$_setter_$upperCased_$eq
  #20 = Utf8               org$scalactic$StringNormalizations$_setter_$trimmed_$eq
  #21 = Utf8               lowerCased
  #22 = Utf8               ()Lorg/scalactic/Uniformity;
  #23 = Utf8               ()Lorg/scalactic/Uniformity<Ljava/lang/String;>;
  #24 = Utf8               upperCased
  #25 = Utf8               trimmed
  #26 = Utf8               $init$
  #27 = Utf8               (Lorg/scalactic/StringNormalizations;)V
  #28 = Utf8               $this
  #29 = Utf8               <init>
  #30 = NameAndType        #29:#27        // "<init>":(Lorg/scalactic/StringNormalizations;)V
  #31 = Methodref          #10.#30        // org/scalactic/StringNormalizations$$anon$1."<init>":(Lorg/scalactic/StringNormalizations;)V
  #32 = NameAndType        #15:#16        // org$scalactic$StringNormalizations$_setter_$lowerCased_$eq:(Lorg/scalactic/Uniformity;)V
  #33 = InterfaceMethodref #2.#32         // org/scalactic/StringNormalizations.org$scalactic$StringNormalizations$_setter_$lowerCased_$eq:(Lorg/scalactic/Uniformity;)V
  #34 = Methodref          #12.#30        // org/scalactic/StringNormalizations$$anon$2."<init>":(Lorg/scalactic/StringNormalizations;)V
  #35 = NameAndType        #19:#16        // org$scalactic$StringNormalizations$_setter_$upperCased_$eq:(Lorg/scalactic/Uniformity;)V
  #36 = InterfaceMethodref #2.#35         // org/scalactic/StringNormalizations.org$scalactic$StringNormalizations$_setter_$upperCased_$eq:(Lorg/scalactic/Uniformity;)V
  #37 = Methodref          #14.#30        // org/scalactic/StringNormalizations$$anon$3."<init>":(Lorg/scalactic/StringNormalizations;)V
  #38 = NameAndType        #20:#16        // org$scalactic$StringNormalizations$_setter_$trimmed_$eq:(Lorg/scalactic/Uniformity;)V
  #39 = InterfaceMethodref #2.#38         // org/scalactic/StringNormalizations.org$scalactic$StringNormalizations$_setter_$trimmed_$eq:(Lorg/scalactic/Uniformity;)V
  #40 = Utf8               Lorg/scalactic/StringNormalizations;
  #41 = Utf8               Signature
  #42 = Utf8               MethodParameters
  #43 = Utf8               Code
  #44 = Utf8               LineNumberTable
  #45 = Utf8               LocalVariableTable
  #46 = Utf8               InnerClasses
  #47 = Utf8               SourceFile
  #48 = Utf8               RuntimeVisibleAnnotations
  #49 = Utf8               ScalaInlineInfo
  #50 = Utf8               ScalaSig
{
  public abstract void org$scalactic$StringNormalizations$_setter_$lowerCased_$eq(org.scalactic.Uniformity<java.lang.String>);
    descriptor: (Lorg/scalactic/Uniformity;)V
    flags: (0x0401) ACC_PUBLIC, ACC_ABSTRACT
    Signature: #17                          // (Lorg/scalactic/Uniformity<Ljava/lang/String;>;)V
    MethodParameters:
      Name                           Flags
      x$1                            final

  public abstract void org$scalactic$StringNormalizations$_setter_$upperCased_$eq(org.scalactic.Uniformity<java.lang.String>);
    descriptor: (Lorg/scalactic/Uniformity;)V
    flags: (0x0401) ACC_PUBLIC, ACC_ABSTRACT
    Signature: #17                          // (Lorg/scalactic/Uniformity<Ljava/lang/String;>;)V
    MethodParameters:
      Name                           Flags
      x$1                            final

  public abstract void org$scalactic$StringNormalizations$_setter_$trimmed_$eq(org.scalactic.Uniformity<java.lang.String>);
    descriptor: (Lorg/scalactic/Uniformity;)V
    flags: (0x0401) ACC_PUBLIC, ACC_ABSTRACT
    Signature: #17                          // (Lorg/scalactic/Uniformity<Ljava/lang/String;>;)V
    MethodParameters:
      Name                           Flags
      x$1                            final

  public abstract org.scalactic.Uniformity<java.lang.String> lowerCased();
    descriptor: ()Lorg/scalactic/Uniformity;
    flags: (0x0401) ACC_PUBLIC, ACC_ABSTRACT
    Signature: #23                          // ()Lorg/scalactic/Uniformity<Ljava/lang/String;>;

  public abstract org.scalactic.Uniformity<java.lang.String> upperCased();
    descriptor: ()Lorg/scalactic/Uniformity;
    flags: (0x0401) ACC_PUBLIC, ACC_ABSTRACT
    Signature: #23                          // ()Lorg/scalactic/Uniformity<Ljava/lang/String;>;

  public abstract org.scalactic.Uniformity<java.lang.String> trimmed();
    descriptor: ()Lorg/scalactic/Uniformity;
    flags: (0x0401) ACC_PUBLIC, ACC_ABSTRACT
    Signature: #23                          // ()Lorg/scalactic/Uniformity<Ljava/lang/String;>;

  public static void $init$(org.scalactic.StringNormalizations);
    descriptor: (Lorg/scalactic/StringNormalizations;)V
    flags: (0x0009) ACC_PUBLIC, ACC_STATIC
    Code:
      stack=4, locals=1, args_size=1
         0: aload_0
         1: new           #10                 // class org/scalactic/StringNormalizations$$anon$1
         4: dup
         5: aconst_null
         6: invokespecial #31                 // Method org/scalactic/StringNormalizations$$anon$1."<init>":(Lorg/scalactic/StringNormalizations;)V
         9: invokeinterface #33,  2           // InterfaceMethod org$scalactic$StringNormalizations$_setter_$lowerCased_$eq:(Lorg/scalactic/Uniformity;)V
        14: aload_0
        15: new           #12                 // class org/scalactic/StringNormalizations$$anon$2
        18: dup
        19: aconst_null
        20: invokespecial #34                 // Method org/scalactic/StringNormalizations$$anon$2."<init>":(Lorg/scalactic/StringNormalizations;)V
        23: invokeinterface #36,  2           // InterfaceMethod org$scalactic$StringNormalizations$_setter_$upperCased_$eq:(Lorg/scalactic/Uniformity;)V
        28: aload_0
        29: new           #14                 // class org/scalactic/StringNormalizations$$anon$3
        32: dup
        33: aconst_null
        34: invokespecial #37                 // Method org/scalactic/StringNormalizations$$anon$3."<init>":(Lorg/scalactic/StringNormalizations;)V
        37: invokeinterface #39,  2           // InterfaceMethod org$scalactic$StringNormalizations$_setter_$trimmed_$eq:(Lorg/scalactic/Uniformity;)V
        42: return
      LineNumberTable:
        line 32: 0
        line 33: 1
        line 51: 14
        line 52: 15
        line 70: 28
        line 71: 29
        line 24: 42
      LocalVariableTable:
        Start  Length  Slot  Name   Signature
            0      43     0 $this   Lorg/scalactic/StringNormalizations;
    MethodParameters:
      Name                           Flags
      $this                          final synthetic
}
InnerClasses:
  public final #10;                       // class org/scalactic/StringNormalizations$$anon$1
  public final #12;                       // class org/scalactic/StringNormalizations$$anon$2
  public final #14;                       // class org/scalactic/StringNormalizations$$anon$3
SourceFile: "StringNormalizations.scala"
RuntimeVisibleAnnotations:
  0: #6(#7=s#8)
    scala.reflect.ScalaSignature(
      bytes="\u0006\u0005M2q\u0001C\u0005\u0011\u0002\u0007\u0005a\u0002C\u0003\u0016\u0001\u0011\u0005a\u0003C\u0004\u001b\u0001\t\u0007I\u0011A\u000e\t\u000f-\u0002!\u0019!C\u00017!9A\u0006\u0001b\u0001\n\u0003Yr!B\u0017\n\u0011\u0003qc!\u0002\u0005\n\u0011\u0003y\u0003\"B\u0019\u0007\t\u0003\u0011$\u0001F*ue&twMT8s[\u0006d\u0017N_1uS>t7O\u0003\u0002\u000b\u0017\u0005I1oY1mC\u000e$\u0018n\u0019\u0006\u0002\u0019\u0005\u0019qN]4\u0004\u0001M\u0011\u0001a\u0004\t\u0003!Mi\u0011!\u0005\u0006\u0002%\u0005)1oY1mC&\u0011A#\u0005\u0002\u0007\u0003:L(+\u001a4\u0002\r\u0011Jg.\u001b;%)\u00059\u0002C\u0001\t\u0019\u0013\tI\u0012C\u0001\u0003V]&$\u0018A\u00037po\u0016\u00148)Y:fIV\tA\u0004E\u0002\u001e=\u0001j\u0011!C\u0005\u0003?%\u0011!\"\u00168jM>\u0014X.\u001b;z!\t\t\u0003F\u0004\u0002#MA\u00111%E\u0007\u0002I)\u0011Q%D\u0001\u0007yI|w\u000e\u001e \n\u0005\u001d\n\u0012A\u0002)sK\u0012,g-\u0003\u0002*U\t11\u000b\u001e:j]\u001eT!aJ\t\u0002\u0015U\u0004\b/\u001a:DCN,G-A\u0004ue&lW.\u001a3\u0002)M#(/\u001b8h\u001d>\u0014X.\u00197ju\u0006$\u0018n\u001c8t!\tibaE\u0002\u0007\u001fA\u0002\"!\b\u0001\u0002\rqJg.\u001b;?)\u0005q\u0003"
    )
  ScalaInlineInfo: length = 0x27 (unknown attribute)
   01 00 00 07 00 1A 00 1B 01 00 15 00 16 00 00 0F
   00 10 00 00 14 00 10 00 00 13 00 10 00 00 19 00
   16 00 00 18 00 16 00
  ScalaSig: length = 0x3 (unknown attribute)
   05 02 00
