Classfile /Users/mw/Projects/slang-braindump/.jar/jar8/assemble/slang-braindump/assemble/content/org/scalactic/TimesOnInt.class
  Last modified May 29, 2022; size 1354 bytes
  SHA-256 checksum bfee292ec52ccb3ebf176d27a752b6079310a3fd5bd2849b5ec89d99ed2e2364
  Compiled from "TimesOnInt.scala"
public interface org.scalactic.TimesOnInt
  minor version: 0
  major version: 52
  flags: (0x0601) ACC_PUBLIC, ACC_INTERFACE, ACC_ABSTRACT
  this_class: #2                          // org/scalactic/TimesOnInt
  super_class: #4                         // java/lang/Object
  interfaces: 0, fields: 0, methods: 3, attributes: 5
Constant pool:
   #1 = Utf8               org/scalactic/TimesOnInt
   #2 = Class              #1             // org/scalactic/TimesOnInt
   #3 = Utf8               java/lang/Object
   #4 = Class              #3             // java/lang/Object
   #5 = Utf8               TimesOnInt.scala
   #6 = Utf8               Lscala/reflect/ScalaSignature;
   #7 = Utf8               bytes
   #8 = Utf8               \u0006\u0005]2qAC\u0006\u0011\u0002\u0007\u0005\u0001\u0003C\u0003\u0018\u0001\u0011\u0005\u0001D\u0002\u0003\u001d\u0001\u0001i\u0002\u0002\u0003\u0010\u0003\u0005\u0003\u0005\u000b\u0011B\u0010\t\u000b\t\u0012A\u0011A\u0012\t\u000b\u001d\u0012A\u0011\u0001\u0015\t\u000b9\u0002A1A\u0018\b\u000bEZ\u0001\u0012\u0001\u001a\u0007\u000b)Y\u0001\u0012\u0001\u001b\t\u000b\tBA\u0011\u0001\u001c\u0003\u0015QKW.Z:P]&sGO\u0003\u0002\r\u001b\u0005I1oY1mC\u000e$\u0018n\u0019\u0006\u0002\u001d\u0005\u0019qN]4\u0004\u0001M\u0011\u0001!\u0005\t\u0003%Ui\u0011a\u0005\u0006\u0002)\u0005)1oY1mC&\u0011ac\u0005\u0002\u0007\u0003:L(+\u001a4\u0002\r\u0011Jg.\u001b;%)\u0005I\u0002C\u0001\n\u001b\u0013\tY2C\u0001\u0003V]&$(\u0001\u0003*fa\u0016\fG/\u001a:\u0014\u0005\t\t\u0012a\u00018v[B\u0011!\u0003I\u0005\u0003CM\u00111!\u00138u\u0003\u0019a\u0014N\\5u}Q\u0011AE\n\t\u0003K\ti\u0011\u0001\u0001\u0005\u0006=\u0011\u0001\raH\u0001\u0006i&lWm\u001d\u000b\u00033%BaAK\u0003\u0005\u0002\u0004Y\u0013a\u00014v]B\u0019!\u0003L\r\n\u00055\u001a\"\u0001\u0003\u001fcs:\fW.\u001a \u0002)\r|gN^3si&sG\u000fV8SKB,\u0017\r^3s)\t!\u0003\u0007C\u0003\u001f\r\u0001\u0007q$\u0001\u0006US6,7o\u00148J]R\u0004\"a\r\u0005\u000e\u0003-\u00192\u0001C\t6!\t\u0019\u0004\u0001F\u00013\u0001
   #9 = Utf8               org/scalactic/TimesOnInt$Repeater
  #10 = Class              #9             // org/scalactic/TimesOnInt$Repeater
  #11 = Utf8               Repeater
  #12 = Utf8               convertIntToRepeater$
  #13 = Utf8               (Lorg/scalactic/TimesOnInt;I)Lorg/scalactic/TimesOnInt$Repeater;
  #14 = Utf8               $this
  #15 = Utf8               num
  #16 = Utf8               convertIntToRepeater
  #17 = Utf8               (I)Lorg/scalactic/TimesOnInt$Repeater;
  #18 = NameAndType        #16:#17        // convertIntToRepeater:(I)Lorg/scalactic/TimesOnInt$Repeater;
  #19 = InterfaceMethodref #2.#18         // org/scalactic/TimesOnInt.convertIntToRepeater:(I)Lorg/scalactic/TimesOnInt$Repeater;
  #20 = Utf8               Lorg/scalactic/TimesOnInt;
  #21 = Utf8               I
  #22 = Utf8               <init>
  #23 = Utf8               (Lorg/scalactic/TimesOnInt;I)V
  #24 = NameAndType        #22:#23        // "<init>":(Lorg/scalactic/TimesOnInt;I)V
  #25 = Methodref          #10.#24        // org/scalactic/TimesOnInt$Repeater."<init>":(Lorg/scalactic/TimesOnInt;I)V
  #26 = Utf8               this
  #27 = Utf8               $init$
  #28 = Utf8               (Lorg/scalactic/TimesOnInt;)V
  #29 = Utf8               Code
  #30 = Utf8               LineNumberTable
  #31 = Utf8               LocalVariableTable
  #32 = Utf8               MethodParameters
  #33 = Utf8               InnerClasses
  #34 = Utf8               SourceFile
  #35 = Utf8               RuntimeVisibleAnnotations
  #36 = Utf8               ScalaInlineInfo
  #37 = Utf8               ScalaSig
{
  public static org.scalactic.TimesOnInt$Repeater convertIntToRepeater$(org.scalactic.TimesOnInt, int);
    descriptor: (Lorg/scalactic/TimesOnInt;I)Lorg/scalactic/TimesOnInt$Repeater;
    flags: (0x1009) ACC_PUBLIC, ACC_STATIC, ACC_SYNTHETIC
    Code:
      stack=2, locals=2, args_size=2
         0: aload_0
         1: iload_1
         2: invokespecial #19                 // InterfaceMethod convertIntToRepeater:(I)Lorg/scalactic/TimesOnInt$Repeater;
         5: areturn
      LineNumberTable:
        line 116: 0
      LocalVariableTable:
        Start  Length  Slot  Name   Signature
            0       6     0 $this   Lorg/scalactic/TimesOnInt;
            0       6     1   num   I
    MethodParameters:
      Name                           Flags
      $this                          final synthetic
      num                            final

  public default org.scalactic.TimesOnInt$Repeater convertIntToRepeater(int);
    descriptor: (I)Lorg/scalactic/TimesOnInt$Repeater;
    flags: (0x0001) ACC_PUBLIC
    Code:
      stack=4, locals=2, args_size=2
         0: new           #10                 // class org/scalactic/TimesOnInt$Repeater
         3: dup
         4: aload_0
         5: iload_1
         6: invokespecial #25                 // Method org/scalactic/TimesOnInt$Repeater."<init>":(Lorg/scalactic/TimesOnInt;I)V
         9: areturn
      LineNumberTable:
        line 116: 0
      LocalVariableTable:
        Start  Length  Slot  Name   Signature
            0      10     0  this   Lorg/scalactic/TimesOnInt;
            0      10     1   num   I
    MethodParameters:
      Name                           Flags
      num                            final

  public static void $init$(org.scalactic.TimesOnInt);
    descriptor: (Lorg/scalactic/TimesOnInt;)V
    flags: (0x0009) ACC_PUBLIC, ACC_STATIC
    Code:
      stack=0, locals=1, args_size=1
         0: return
      LineNumberTable:
        line 68: 0
      LocalVariableTable:
        Start  Length  Slot  Name   Signature
            0       1     0 $this   Lorg/scalactic/TimesOnInt;
    MethodParameters:
      Name                           Flags
      $this                          final synthetic
}
InnerClasses:
  public #11= #10 of #2;                  // Repeater=class org/scalactic/TimesOnInt$Repeater of class org/scalactic/TimesOnInt
SourceFile: "TimesOnInt.scala"
RuntimeVisibleAnnotations:
  0: #6(#7=s#8)
    scala.reflect.ScalaSignature(
      bytes="\u0006\u0005]2qAC\u0006\u0011\u0002\u0007\u0005\u0001\u0003C\u0003\u0018\u0001\u0011\u0005\u0001D\u0002\u0003\u001d\u0001\u0001i\u0002\u0002\u0003\u0010\u0003\u0005\u0003\u0005\u000b\u0011B\u0010\t\u000b\t\u0012A\u0011A\u0012\t\u000b\u001d\u0012A\u0011\u0001\u0015\t\u000b9\u0002A1A\u0018\b\u000bEZ\u0001\u0012\u0001\u001a\u0007\u000b)Y\u0001\u0012\u0001\u001b\t\u000b\tBA\u0011\u0001\u001c\u0003\u0015QKW.Z:P]&sGO\u0003\u0002\r\u001b\u0005I1oY1mC\u000e$\u0018n\u0019\u0006\u0002\u001d\u0005\u0019qN]4\u0004\u0001M\u0011\u0001!\u0005\t\u0003%Ui\u0011a\u0005\u0006\u0002)\u0005)1oY1mC&\u0011ac\u0005\u0002\u0007\u0003:L(+\u001a4\u0002\r\u0011Jg.\u001b;%)\u0005I\u0002C\u0001\n\u001b\u0013\tY2C\u0001\u0003V]&$(\u0001\u0003*fa\u0016\fG/\u001a:\u0014\u0005\t\t\u0012a\u00018v[B\u0011!\u0003I\u0005\u0003CM\u00111!\u00138u\u0003\u0019a\u0014N\\5u}Q\u0011AE\n\t\u0003K\ti\u0011\u0001\u0001\u0005\u0006=\u0011\u0001\raH\u0001\u0006i&lWm\u001d\u000b\u00033%BaAK\u0003\u0005\u0002\u0004Y\u0013a\u00014v]B\u0019!\u0003L\r\n\u00055\u001a\"\u0001\u0003\u001fcs:\fW.\u001a \u0002)\r|gN^3si&sG\u000fV8SKB,\u0017\r^3s)\t!\u0003\u0007C\u0003\u001f\r\u0001\u0007q$\u0001\u0006US6,7o\u00148J]R\u0004\"a\r\u0005\u000e\u0003-\u00192\u0001C\t6!\t\u0019\u0004\u0001F\u00013\u0001"
    )
  ScalaInlineInfo: length = 0x13 (unknown attribute)
   01 00 00 03 00 1B 00 1C 01 00 10 00 11 00 00 0C
   00 0D 01
  ScalaSig: length = 0x3 (unknown attribute)
   05 02 00
