Classfile /Users/mw/Projects/slang-braindump/.jar/jar8/assemble/slang-braindump/assemble/content/org/scalactic/TimesOnInt$Repeater.class
  Last modified May 29, 2022; size 2551 bytes
  SHA-256 checksum 82a4fd1ff309954da1109b5eeb1c354fb4189467fcf560cf1662d6bf2a4f741a
  Compiled from "TimesOnInt.scala"
public class org.scalactic.TimesOnInt$Repeater
  minor version: 0
  major version: 52
  flags: (0x0021) ACC_PUBLIC, ACC_SUPER
  this_class: #2                          // org/scalactic/TimesOnInt$Repeater
  super_class: #4                         // java/lang/Object
  interfaces: 0, fields: 2, methods: 5, attributes: 5
Constant pool:
    #1 = Utf8               org/scalactic/TimesOnInt$Repeater
    #2 = Class              #1            // org/scalactic/TimesOnInt$Repeater
    #3 = Utf8               java/lang/Object
    #4 = Class              #3            // java/lang/Object
    #5 = Utf8               TimesOnInt.scala
    #6 = Utf8               java/lang/invoke/MethodHandles$Lookup
    #7 = Class              #6            // java/lang/invoke/MethodHandles$Lookup
    #8 = Utf8               java/lang/invoke/MethodHandles
    #9 = Class              #8            // java/lang/invoke/MethodHandles
   #10 = Utf8               Lookup
   #11 = Utf8               org/scalactic/TimesOnInt
   #12 = Class              #11           // org/scalactic/TimesOnInt
   #13 = Utf8               Repeater
   #14 = Utf8               num
   #15 = Utf8               I
   #16 = Utf8               $outer
   #17 = Utf8               Lorg/scalactic/TimesOnInt;
   #18 = Utf8               times
   #19 = Utf8               (Lscala/Function0;)V
   #20 = Utf8               (Lscala/Function0<Lscala/runtime/BoxedUnit;>;)V
   #21 = Utf8               fun
   #22 = NameAndType        #14:#15       // num:I
   #23 = Fieldref           #2.#22        // org/scalactic/TimesOnInt$Repeater.num:I
   #24 = Utf8               scala/Function0
   #25 = Class              #24           // scala/Function0
   #26 = Utf8               apply$mcV$sp
   #27 = Utf8               ()V
   #28 = NameAndType        #26:#27       // apply$mcV$sp:()V
   #29 = InterfaceMethodref #25.#28       // scala/Function0.apply$mcV$sp:()V
   #30 = Utf8               i
   #31 = Utf8               this
   #32 = Utf8               Lorg/scalactic/TimesOnInt$Repeater;
   #33 = Utf8               Lscala/Function0;
   #34 = Utf8               org$scalactic$TimesOnInt$Repeater$$$outer
   #35 = Utf8               ()Lorg/scalactic/TimesOnInt;
   #36 = NameAndType        #16:#17       // $outer:Lorg/scalactic/TimesOnInt;
   #37 = Fieldref           #2.#36        // org/scalactic/TimesOnInt$Repeater.$outer:Lorg/scalactic/TimesOnInt;
   #38 = Utf8               $anonfun$new$1
   #39 = Utf8               (Lorg/scalactic/TimesOnInt$Repeater;)Ljava/lang/String;
   #40 = Utf8               $this
   #41 = Utf8               java/lang/StringBuilder
   #42 = Class              #41           // java/lang/StringBuilder
   #43 = Integer            59
   #44 = Utf8               <init>
   #45 = Utf8               (I)V
   #46 = NameAndType        #44:#45       // "<init>":(I)V
   #47 = Methodref          #42.#46       // java/lang/StringBuilder."<init>":(I)V
   #48 = Utf8               The integer on which times was invoked was less than zero:
   #49 = String             #48           // The integer on which times was invoked was less than zero:
   #50 = Utf8               append
   #51 = Utf8               (Ljava/lang/String;)Ljava/lang/StringBuilder;
   #52 = NameAndType        #50:#51       // append:(Ljava/lang/String;)Ljava/lang/StringBuilder;
   #53 = Methodref          #42.#52       // java/lang/StringBuilder.append:(Ljava/lang/String;)Ljava/lang/StringBuilder;
   #54 = Utf8               (I)Ljava/lang/StringBuilder;
   #55 = NameAndType        #50:#54       // append:(I)Ljava/lang/StringBuilder;
   #56 = Methodref          #42.#55       // java/lang/StringBuilder.append:(I)Ljava/lang/StringBuilder;
   #57 = Utf8               toString
   #58 = Utf8               ()Ljava/lang/String;
   #59 = NameAndType        #57:#58       // toString:()Ljava/lang/String;
   #60 = Methodref          #42.#59       // java/lang/StringBuilder.toString:()Ljava/lang/String;
   #61 = Utf8               (Lorg/scalactic/TimesOnInt;I)V
   #62 = NameAndType        #44:#27       // "<init>":()V
   #63 = Methodref          #4.#62        // java/lang/Object."<init>":()V
   #64 = Utf8               scala/Predef$
   #65 = Class              #64           // scala/Predef$
   #66 = Utf8               MODULE$
   #67 = Utf8               Lscala/Predef$;
   #68 = NameAndType        #66:#67       // MODULE$:Lscala/Predef$;
   #69 = Fieldref           #65.#68       // scala/Predef$.MODULE$:Lscala/Predef$;
   #70 = Utf8               ()Ljava/lang/Object;
   #71 = MethodType         #70           //  ()Ljava/lang/Object;
   #72 = NameAndType        #38:#39       // $anonfun$new$1:(Lorg/scalactic/TimesOnInt$Repeater;)Ljava/lang/String;
   #73 = Methodref          #2.#72        // org/scalactic/TimesOnInt$Repeater.$anonfun$new$1:(Lorg/scalactic/TimesOnInt$Repeater;)Ljava/lang/String;
   #74 = MethodHandle       6:#73         // REF_invokeStatic org/scalactic/TimesOnInt$Repeater.$anonfun$new$1:(Lorg/scalactic/TimesOnInt$Repeater;)Ljava/lang/String;
   #75 = MethodType         #58           //  ()Ljava/lang/String;
   #76 = Integer            5
   #77 = Integer            1
   #78 = Utf8               java/lang/invoke/LambdaMetafactory
   #79 = Class              #78           // java/lang/invoke/LambdaMetafactory
   #80 = Utf8               altMetafactory
   #81 = Utf8               (Ljava/lang/invoke/MethodHandles$Lookup;Ljava/lang/String;Ljava/lang/invoke/MethodType;[Ljava/lang/Object;)Ljava/lang/invoke/CallSite;
   #82 = NameAndType        #80:#81       // altMetafactory:(Ljava/lang/invoke/MethodHandles$Lookup;Ljava/lang/String;Ljava/lang/invoke/MethodType;[Ljava/lang/Object;)Ljava/lang/invoke/CallSite;
   #83 = Methodref          #79.#82       // java/lang/invoke/LambdaMetafactory.altMetafactory:(Ljava/lang/invoke/MethodHandles$Lookup;Ljava/lang/String;Ljava/lang/invoke/MethodType;[Ljava/lang/Object;)Ljava/lang/invoke/CallSite;
   #84 = MethodHandle       6:#83         // REF_invokeStatic java/lang/invoke/LambdaMetafactory.altMetafactory:(Ljava/lang/invoke/MethodHandles$Lookup;Ljava/lang/String;Ljava/lang/invoke/MethodType;[Ljava/lang/Object;)Ljava/lang/invoke/CallSite;
   #85 = Utf8               apply
   #86 = Utf8               (Lorg/scalactic/TimesOnInt$Repeater;)Lscala/Function0;
   #87 = NameAndType        #85:#86       // apply:(Lorg/scalactic/TimesOnInt$Repeater;)Lscala/Function0;
   #88 = InvokeDynamic      #0:#87        // #0:apply:(Lorg/scalactic/TimesOnInt$Repeater;)Lscala/Function0;
   #89 = Utf8               require
   #90 = Utf8               (ZLscala/Function0;)V
   #91 = NameAndType        #89:#90       // require:(ZLscala/Function0;)V
   #92 = Methodref          #65.#91       // scala/Predef$.require:(ZLscala/Function0;)V
   #93 = Utf8               $deserializeLambda$
   #94 = Utf8               (Ljava/lang/invoke/SerializedLambda;)Ljava/lang/Object;
   #95 = Utf8               scala/runtime/LambdaDeserialize
   #96 = Class              #95           // scala/runtime/LambdaDeserialize
   #97 = Utf8               bootstrap
   #98 = Utf8               (Ljava/lang/invoke/MethodHandles$Lookup;Ljava/lang/String;Ljava/lang/invoke/MethodType;[Ljava/lang/invoke/MethodHandle;)Ljava/lang/invoke/CallSite;
   #99 = NameAndType        #97:#98       // bootstrap:(Ljava/lang/invoke/MethodHandles$Lookup;Ljava/lang/String;Ljava/lang/invoke/MethodType;[Ljava/lang/invoke/MethodHandle;)Ljava/lang/invoke/CallSite;
  #100 = Methodref          #96.#99       // scala/runtime/LambdaDeserialize.bootstrap:(Ljava/lang/invoke/MethodHandles$Lookup;Ljava/lang/String;Ljava/lang/invoke/MethodType;[Ljava/lang/invoke/MethodHandle;)Ljava/lang/invoke/CallSite;
  #101 = MethodHandle       6:#100        // REF_invokeStatic scala/runtime/LambdaDeserialize.bootstrap:(Ljava/lang/invoke/MethodHandles$Lookup;Ljava/lang/String;Ljava/lang/invoke/MethodType;[Ljava/lang/invoke/MethodHandle;)Ljava/lang/invoke/CallSite;
  #102 = Utf8               lambdaDeserialize
  #103 = NameAndType        #102:#94      // lambdaDeserialize:(Ljava/lang/invoke/SerializedLambda;)Ljava/lang/Object;
  #104 = InvokeDynamic      #1:#103       // #1:lambdaDeserialize:(Ljava/lang/invoke/SerializedLambda;)Ljava/lang/Object;
  #105 = Utf8               Code
  #106 = Utf8               StackMapTable
  #107 = Utf8               LineNumberTable
  #108 = Utf8               LocalVariableTable
  #109 = Utf8               Signature
  #110 = Utf8               MethodParameters
  #111 = Utf8               InnerClasses
  #112 = Utf8               SourceFile
  #113 = Utf8               BootstrapMethods
  #114 = Utf8               ScalaInlineInfo
  #115 = Utf8               Scala
{
  private final int num;
    descriptor: I
    flags: (0x0012) ACC_PRIVATE, ACC_FINAL

  public final org.scalactic.TimesOnInt $outer;
    descriptor: Lorg/scalactic/TimesOnInt;
    flags: (0x1011) ACC_PUBLIC, ACC_FINAL, ACC_SYNTHETIC

  public void times(scala.Function0<scala.runtime.BoxedUnit>);
    descriptor: (Lscala/Function0;)V
    flags: (0x0001) ACC_PUBLIC
    Code:
      stack=2, locals=3, args_size=2
         0: iconst_0
         1: istore_2
         2: iload_2
         3: aload_0
         4: getfield      #23                 // Field num:I
         7: if_icmpge     23
        10: aload_1
        11: invokeinterface #29,  1           // InterfaceMethod scala/Function0.apply$mcV$sp:()V
        16: iload_2
        17: iconst_1
        18: iadd
        19: istore_2
        20: goto          2
        23: return
      StackMapTable: number_of_entries = 2
        frame_type = 252 /* append */
          offset_delta = 2
          locals = [ int ]
        frame_type = 20 /* same */
      LineNumberTable:
        line 100: 0
        line 101: 2
        line 102: 10
        line 103: 16
        line 101: 20
      LocalVariableTable:
        Start  Length  Slot  Name   Signature
            2      21     2     i   I
            0      24     0  this   Lorg/scalactic/TimesOnInt$Repeater;
            0      24     1   fun   Lscala/Function0;
    Signature: #20                          // (Lscala/Function0<Lscala/runtime/BoxedUnit;>;)V
    MethodParameters:
      Name                           Flags
      fun                            final

  public org.scalactic.TimesOnInt org$scalactic$TimesOnInt$Repeater$$$outer();
    descriptor: ()Lorg/scalactic/TimesOnInt;
    flags: (0x1001) ACC_PUBLIC, ACC_SYNTHETIC
    Code:
      stack=1, locals=1, args_size=1
         0: aload_0
         1: getfield      #37                 // Field $outer:Lorg/scalactic/TimesOnInt;
         4: areturn
      LineNumberTable:
        line 84: 0
      LocalVariableTable:
        Start  Length  Slot  Name   Signature
            0       5     0  this   Lorg/scalactic/TimesOnInt$Repeater;

  public static final java.lang.String $anonfun$new$1(org.scalactic.TimesOnInt$Repeater);
    descriptor: (Lorg/scalactic/TimesOnInt$Repeater;)Ljava/lang/String;
    flags: (0x1019) ACC_PUBLIC, ACC_STATIC, ACC_FINAL, ACC_SYNTHETIC
    Code:
      stack=3, locals=1, args_size=1
         0: new           #42                 // class java/lang/StringBuilder
         3: dup
         4: ldc           #43                 // int 59
         6: invokespecial #47                 // Method java/lang/StringBuilder."<init>":(I)V
         9: ldc           #49                 // String The integer on which times was invoked was less than zero:
        11: invokevirtual #53                 // Method java/lang/StringBuilder.append:(Ljava/lang/String;)Ljava/lang/StringBuilder;
        14: aload_0
        15: getfield      #23                 // Field num:I
        18: invokevirtual #56                 // Method java/lang/StringBuilder.append:(I)Ljava/lang/StringBuilder;
        21: invokevirtual #60                 // Method java/lang/StringBuilder.toString:()Ljava/lang/String;
        24: areturn
      LineNumberTable:
        line 86: 0
      LocalVariableTable:
        Start  Length  Slot  Name   Signature
            0      25     0 $this   Lorg/scalactic/TimesOnInt$Repeater;
    MethodParameters:
      Name                           Flags
      $this                          final synthetic

  public org.scalactic.TimesOnInt$Repeater(org.scalactic.TimesOnInt, int);
    descriptor: (Lorg/scalactic/TimesOnInt;I)V
    flags: (0x0001) ACC_PUBLIC
    Code:
      stack=3, locals=3, args_size=3
         0: aload_0
         1: iload_2
         2: putfield      #23                 // Field num:I
         5: aload_1
         6: ifnonnull     11
         9: aconst_null
        10: athrow
        11: aload_0
        12: aload_1
        13: putfield      #37                 // Field $outer:Lorg/scalactic/TimesOnInt;
        16: aload_0
        17: invokespecial #63                 // Method java/lang/Object."<init>":()V
        20: getstatic     #69                 // Field scala/Predef$.MODULE$:Lscala/Predef$;
        23: iload_2
        24: iconst_0
        25: if_icmplt     32
        28: iconst_1
        29: goto          33
        32: iconst_0
        33: aload_0
        34: invokedynamic #88,  0             // InvokeDynamic #0:apply:(Lorg/scalactic/TimesOnInt$Repeater;)Lscala/Function0;
        39: invokevirtual #92                 // Method scala/Predef$.require:(ZLscala/Function0;)V
        42: return
      StackMapTable: number_of_entries = 3
        frame_type = 11 /* same */
        frame_type = 255 /* full_frame */
          offset_delta = 20
          locals = [ class org/scalactic/TimesOnInt$Repeater, class org/scalactic/TimesOnInt, int ]
          stack = [ class scala/Predef$ ]
        frame_type = 255 /* full_frame */
          offset_delta = 0
          locals = [ class org/scalactic/TimesOnInt$Repeater, class org/scalactic/TimesOnInt, int ]
          stack = [ class scala/Predef$, int ]
      LineNumberTable:
        line 84: 0
        line 108: 16
        line 86: 20
        line 84: 42
      LocalVariableTable:
        Start  Length  Slot  Name   Signature
            0      43     0  this   Lorg/scalactic/TimesOnInt$Repeater;
            0      43     1 $outer   Lorg/scalactic/TimesOnInt;
            0      43     2   num   I
    MethodParameters:
      Name                           Flags
      $outer                         final synthetic
      num                            final

  private static java.lang.Object $deserializeLambda$(java.lang.invoke.SerializedLambda);
    descriptor: (Ljava/lang/invoke/SerializedLambda;)Ljava/lang/Object;
    flags: (0x100a) ACC_PRIVATE, ACC_STATIC, ACC_SYNTHETIC
    Code:
      stack=1, locals=1, args_size=1
         0: aload_0
         1: invokedynamic #104,  0            // InvokeDynamic #1:lambdaDeserialize:(Ljava/lang/invoke/SerializedLambda;)Ljava/lang/Object;
         6: areturn
}
InnerClasses:
  public static final #10= #7 of #9;      // Lookup=class java/lang/invoke/MethodHandles$Lookup of class java/lang/invoke/MethodHandles
  public #13= #2 of #12;                  // Repeater=class org/scalactic/TimesOnInt$Repeater of class org/scalactic/TimesOnInt
SourceFile: "TimesOnInt.scala"
BootstrapMethods:
  0: #84 REF_invokeStatic java/lang/invoke/LambdaMetafactory.altMetafactory:(Ljava/lang/invoke/MethodHandles$Lookup;Ljava/lang/String;Ljava/lang/invoke/MethodType;[Ljava/lang/Object;)Ljava/lang/invoke/CallSite;
    Method arguments:
      #71 ()Ljava/lang/Object;
      #74 REF_invokeStatic org/scalactic/TimesOnInt$Repeater.$anonfun$new$1:(Lorg/scalactic/TimesOnInt$Repeater;)Ljava/lang/String;
      #75 ()Ljava/lang/String;
      #76 5
      #77 1
      #75 ()Ljava/lang/String;
  1: #101 REF_invokeStatic scala/runtime/LambdaDeserialize.bootstrap:(Ljava/lang/invoke/MethodHandles$Lookup;Ljava/lang/String;Ljava/lang/invoke/MethodType;[Ljava/lang/invoke/MethodHandle;)Ljava/lang/invoke/CallSite;
    Method arguments:
      #74 REF_invokeStatic org/scalactic/TimesOnInt$Repeater.$anonfun$new$1:(Lorg/scalactic/TimesOnInt$Repeater;)Ljava/lang/String;
  ScalaInlineInfo: length = 0x18 (unknown attribute)
   01 00 00 04 00 26 00 27 01 00 2C 00 3D 00 00 22
   00 23 00 00 12 00 13 00
  Scala: length = 0x0 (unknown attribute)

