Classfile /Users/mw/Projects/slang-braindump/.jar/jar8/assemble/slang-braindump/assemble/content/org/scalactic/TripleEqualsSupport$AToBEquivalenceConstraint.class
  Last modified May 29, 2022; size 1340 bytes
  SHA-256 checksum 2ca384b9ae39e300184316ca12b73f443c5de4235967d544f3a90dda6ac59ea5
  Compiled from "TripleEqualsSupport.scala"
public final class org.scalactic.TripleEqualsSupport$AToBEquivalenceConstraint<A extends java.lang.Object, B extends java.lang.Object> extends org.scalactic.CanEqual<A, B>
  minor version: 0
  major version: 52
  flags: (0x0031) ACC_PUBLIC, ACC_FINAL, ACC_SUPER
  this_class: #2                          // org/scalactic/TripleEqualsSupport$AToBEquivalenceConstraint
  super_class: #5                         // org/scalactic/CanEqual
  interfaces: 0, fields: 2, methods: 2, attributes: 5
Constant pool:
   #1 = Utf8               org/scalactic/TripleEqualsSupport$AToBEquivalenceConstraint
   #2 = Class              #1             // org/scalactic/TripleEqualsSupport$AToBEquivalenceConstraint
   #3 = Utf8               <A:Ljava/lang/Object;B:Ljava/lang/Object;>Lorg/scalactic/CanEqual<TA;TB;>;
   #4 = Utf8               org/scalactic/CanEqual
   #5 = Class              #4             // org/scalactic/CanEqual
   #6 = Utf8               TripleEqualsSupport.scala
   #7 = Utf8               org/scalactic/TripleEqualsSupport
   #8 = Class              #7             // org/scalactic/TripleEqualsSupport
   #9 = Utf8               AToBEquivalenceConstraint
  #10 = Utf8               equivalenceOfB
  #11 = Utf8               Lorg/scalactic/Equivalence;
  #12 = Utf8               Lorg/scalactic/Equivalence<TB;>;
  #13 = Utf8               cnv
  #14 = Utf8               Lscala/Function1;
  #15 = Utf8               Lscala/Function1<TA;TB;>;
  #16 = Utf8               areEqual
  #17 = Utf8               (Ljava/lang/Object;Ljava/lang/Object;)Z
  #18 = Utf8               (TA;TB;)Z
  #19 = Utf8               a
  #20 = Utf8               b
  #21 = NameAndType        #10:#11        // equivalenceOfB:Lorg/scalactic/Equivalence;
  #22 = Fieldref           #2.#21         // org/scalactic/TripleEqualsSupport$AToBEquivalenceConstraint.equivalenceOfB:Lorg/scalactic/Equivalence;
  #23 = NameAndType        #13:#14        // cnv:Lscala/Function1;
  #24 = Fieldref           #2.#23         // org/scalactic/TripleEqualsSupport$AToBEquivalenceConstraint.cnv:Lscala/Function1;
  #25 = Utf8               scala/Function1
  #26 = Class              #25            // scala/Function1
  #27 = Utf8               apply
  #28 = Utf8               (Ljava/lang/Object;)Ljava/lang/Object;
  #29 = NameAndType        #27:#28        // apply:(Ljava/lang/Object;)Ljava/lang/Object;
  #30 = InterfaceMethodref #26.#29        // scala/Function1.apply:(Ljava/lang/Object;)Ljava/lang/Object;
  #31 = Utf8               org/scalactic/Equivalence
  #32 = Class              #31            // org/scalactic/Equivalence
  #33 = Utf8               areEquivalent
  #34 = NameAndType        #33:#17        // areEquivalent:(Ljava/lang/Object;Ljava/lang/Object;)Z
  #35 = InterfaceMethodref #32.#34        // org/scalactic/Equivalence.areEquivalent:(Ljava/lang/Object;Ljava/lang/Object;)Z
  #36 = Utf8               this
  #37 = Utf8               Lorg/scalactic/TripleEqualsSupport$AToBEquivalenceConstraint;
  #38 = Utf8               Ljava/lang/Object;
  #39 = Utf8               <init>
  #40 = Utf8               (Lorg/scalactic/Equivalence;Lscala/Function1;)V
  #41 = Utf8               (Lorg/scalactic/Equivalence<TB;>;Lscala/Function1<TA;TB;>;)V
  #42 = Utf8               ()V
  #43 = NameAndType        #39:#42        // "<init>":()V
  #44 = Methodref          #5.#43         // org/scalactic/CanEqual."<init>":()V
  #45 = Utf8               Signature
  #46 = Utf8               Code
  #47 = Utf8               LineNumberTable
  #48 = Utf8               LocalVariableTable
  #49 = Utf8               MethodParameters
  #50 = Utf8               InnerClasses
  #51 = Utf8               SourceFile
  #52 = Utf8               ScalaInlineInfo
  #53 = Utf8               Scala
{
  private final org.scalactic.Equivalence<B> equivalenceOfB;
    descriptor: Lorg/scalactic/Equivalence;
    flags: (0x0012) ACC_PRIVATE, ACC_FINAL
    Signature: #12                          // Lorg/scalactic/Equivalence<TB;>;

  private final scala.Function1<A, B> cnv;
    descriptor: Lscala/Function1;
    flags: (0x0012) ACC_PRIVATE, ACC_FINAL
    Signature: #15                          // Lscala/Function1<TA;TB;>;

  public boolean areEqual(A, B);
    descriptor: (Ljava/lang/Object;Ljava/lang/Object;)Z
    flags: (0x0001) ACC_PUBLIC
    Code:
      stack=3, locals=3, args_size=3
         0: aload_0
         1: getfield      #22                 // Field equivalenceOfB:Lorg/scalactic/Equivalence;
         4: aload_0
         5: getfield      #24                 // Field cnv:Lscala/Function1;
         8: aload_1
         9: invokeinterface #30,  2           // InterfaceMethod scala/Function1.apply:(Ljava/lang/Object;)Ljava/lang/Object;
        14: aload_2
        15: invokeinterface #35,  3           // InterfaceMethod org/scalactic/Equivalence.areEquivalent:(Ljava/lang/Object;Ljava/lang/Object;)Z
        20: ireturn
      LineNumberTable:
        line 630: 0
      LocalVariableTable:
        Start  Length  Slot  Name   Signature
            0      21     0  this   Lorg/scalactic/TripleEqualsSupport$AToBEquivalenceConstraint;
            0      21     1     a   Ljava/lang/Object;
            0      21     2     b   Ljava/lang/Object;
    Signature: #18                          // (TA;TB;)Z
    MethodParameters:
      Name                           Flags
      a                              final
      b                              final

  public org.scalactic.TripleEqualsSupport$AToBEquivalenceConstraint(org.scalactic.Equivalence<B>, scala.Function1<A, B>);
    descriptor: (Lorg/scalactic/Equivalence;Lscala/Function1;)V
    flags: (0x0001) ACC_PUBLIC
    Code:
      stack=2, locals=3, args_size=3
         0: aload_0
         1: aload_1
         2: putfield      #22                 // Field equivalenceOfB:Lorg/scalactic/Equivalence;
         5: aload_0
         6: aload_2
         7: putfield      #24                 // Field cnv:Lscala/Function1;
        10: aload_0
        11: invokespecial #44                 // Method org/scalactic/CanEqual."<init>":()V
        14: return
      LineNumberTable:
        line 616: 0
      LocalVariableTable:
        Start  Length  Slot  Name   Signature
            0      15     0  this   Lorg/scalactic/TripleEqualsSupport$AToBEquivalenceConstraint;
            0      15     1 equivalenceOfB   Lorg/scalactic/Equivalence;
            0      15     2   cnv   Lscala/Function1;
    Signature: #41                          // (Lorg/scalactic/Equivalence<TB;>;Lscala/Function1<TA;TB;>;)V
    MethodParameters:
      Name                           Flags
      equivalenceOfB                 final
      cnv                            final
}
InnerClasses:
  public static final #9= #2 of #8;       // AToBEquivalenceConstraint=class org/scalactic/TripleEqualsSupport$AToBEquivalenceConstraint of class org/scalactic/TripleEqualsSupport
Signature: #3                           // <A:Ljava/lang/Object;B:Ljava/lang/Object;>Lorg/scalactic/CanEqual<TA;TB;>;
SourceFile: "TripleEqualsSupport.scala"
  ScalaInlineInfo: length = 0xE (unknown attribute)
   01 01 00 02 00 27 00 28 01 00 10 00 11 01
  Scala: length = 0x0 (unknown attribute)

