Classfile /Users/mw/Projects/slang-braindump/.jar/jar8/assemble/slang-braindump/assemble/content/org/scalactic/TripleEqualsSupport$Equalizer.class
  Last modified May 29, 2022; size 2555 bytes
  SHA-256 checksum 159343a0180fdc88e8601b9927bbbaf665c808fc9fe08c52e8b358d99b61970e
  Compiled from "TripleEqualsSupport.scala"
public class org.scalactic.TripleEqualsSupport$Equalizer<L extends java.lang.Object> extends java.lang.Object
  minor version: 0
  major version: 52
  flags: (0x0021) ACC_PUBLIC, ACC_SUPER
  this_class: #2                          // org/scalactic/TripleEqualsSupport$Equalizer
  super_class: #5                         // java/lang/Object
  interfaces: 0, fields: 2, methods: 9, attributes: 5
Constant pool:
   #1 = Utf8               org/scalactic/TripleEqualsSupport$Equalizer
   #2 = Class              #1             // org/scalactic/TripleEqualsSupport$Equalizer
   #3 = Utf8               <L:Ljava/lang/Object;>Ljava/lang/Object;
   #4 = Utf8               java/lang/Object
   #5 = Class              #4             // java/lang/Object
   #6 = Utf8               TripleEqualsSupport.scala
   #7 = Utf8               org/scalactic/TripleEqualsSupport
   #8 = Class              #7             // org/scalactic/TripleEqualsSupport
   #9 = Utf8               Equalizer
  #10 = Utf8               org/scalactic/TripleEqualsSupport$Spread
  #11 = Class              #10            // org/scalactic/TripleEqualsSupport$Spread
  #12 = Utf8               Spread
  #13 = Utf8               leftSide
  #14 = Utf8               Ljava/lang/Object;
  #15 = Utf8               TL;
  #16 = Utf8               $outer
  #17 = Utf8               Lorg/scalactic/TripleEqualsSupport;
  #18 = Utf8               ()Ljava/lang/Object;
  #19 = Utf8               ()TL;
  #20 = NameAndType        #13:#14        // leftSide:Ljava/lang/Object;
  #21 = Fieldref           #2.#20         // org/scalactic/TripleEqualsSupport$Equalizer.leftSide:Ljava/lang/Object;
  #22 = Utf8               this
  #23 = Utf8               Lorg/scalactic/TripleEqualsSupport$Equalizer;
  #24 = Utf8               $eq$eq$eq
  #25 = Utf8               (Ljava/lang/Object;Lorg/scalactic/Equality;)Z
  #26 = Utf8               (Ljava/lang/Object;Lorg/scalactic/Equality<TL;>;)Z
  #27 = Utf8               rightSide
  #28 = Utf8               equality
  #29 = NameAndType        #13:#18        // leftSide:()Ljava/lang/Object;
  #30 = Methodref          #2.#29         // org/scalactic/TripleEqualsSupport$Equalizer.leftSide:()Ljava/lang/Object;
  #31 = Utf8               org/scalactic/Equality
  #32 = Class              #31            // org/scalactic/Equality
  #33 = Utf8               areEqual
  #34 = Utf8               (Ljava/lang/Object;Ljava/lang/Object;)Z
  #35 = NameAndType        #33:#34        // areEqual:(Ljava/lang/Object;Ljava/lang/Object;)Z
  #36 = InterfaceMethodref #32.#35        // org/scalactic/Equality.areEqual:(Ljava/lang/Object;Ljava/lang/Object;)Z
  #37 = Utf8               Lorg/scalactic/Equality;
  #38 = Utf8               $bang$eq$eq
  #39 = Utf8               (Lorg/scalactic/TripleEqualsSupport$Spread;)Z
  #40 = Utf8               (Lorg/scalactic/TripleEqualsSupport$Spread<TL;>;)Z
  #41 = Utf8               spread
  #42 = Utf8               isWithin
  #43 = Utf8               (Ljava/lang/Object;)Z
  #44 = NameAndType        #42:#43        // isWithin:(Ljava/lang/Object;)Z
  #45 = Methodref          #11.#44        // org/scalactic/TripleEqualsSupport$Spread.isWithin:(Ljava/lang/Object;)Z
  #46 = Utf8               equals
  #47 = NameAndType        #46:#43        // equals:(Ljava/lang/Object;)Z
  #48 = Methodref          #5.#47         // java/lang/Object.equals:(Ljava/lang/Object;)Z
  #49 = Utf8               Lorg/scalactic/TripleEqualsSupport$Spread;
  #50 = Utf8               (Lscala/runtime/Null$;)Z
  #51 = Utf8               literalNull
  #52 = Utf8               Lscala/runtime/Null$;
  #53 = Utf8               org$scalactic$TripleEqualsSupport$Equalizer$$$outer
  #54 = Utf8               ()Lorg/scalactic/TripleEqualsSupport;
  #55 = NameAndType        #16:#17        // $outer:Lorg/scalactic/TripleEqualsSupport;
  #56 = Fieldref           #2.#55         // org/scalactic/TripleEqualsSupport$Equalizer.$outer:Lorg/scalactic/TripleEqualsSupport;
  #57 = Utf8               <init>
  #58 = Utf8               (Lorg/scalactic/TripleEqualsSupport;Ljava/lang/Object;)V
  #59 = Utf8               (TL;)V
  #60 = Utf8               ()V
  #61 = NameAndType        #57:#60        // "<init>":()V
  #62 = Methodref          #5.#61         // java/lang/Object."<init>":()V
  #63 = Utf8               Signature
  #64 = Utf8               Code
  #65 = Utf8               LineNumberTable
  #66 = Utf8               LocalVariableTable
  #67 = Utf8               MethodParameters
  #68 = Utf8               StackMapTable
  #69 = Utf8               InnerClasses
  #70 = Utf8               SourceFile
  #71 = Utf8               ScalaInlineInfo
  #72 = Utf8               Scala
{
  private final L leftSide;
    descriptor: Ljava/lang/Object;
    flags: (0x0012) ACC_PRIVATE, ACC_FINAL
    Signature: #15                          // TL;

  public final org.scalactic.TripleEqualsSupport $outer;
    descriptor: Lorg/scalactic/TripleEqualsSupport;
    flags: (0x1011) ACC_PUBLIC, ACC_FINAL, ACC_SYNTHETIC

  public L leftSide();
    descriptor: ()Ljava/lang/Object;
    flags: (0x0001) ACC_PUBLIC
    Code:
      stack=1, locals=1, args_size=1
         0: aload_0
         1: getfield      #21                 // Field leftSide:Ljava/lang/Object;
         4: areturn
      LineNumberTable:
        line 108: 0
      LocalVariableTable:
        Start  Length  Slot  Name   Signature
            0       5     0  this   Lorg/scalactic/TripleEqualsSupport$Equalizer;
    Signature: #19                          // ()TL;

  public boolean $eq$eq$eq(java.lang.Object, org.scalactic.Equality<L>);
    descriptor: (Ljava/lang/Object;Lorg/scalactic/Equality;)Z
    flags: (0x0001) ACC_PUBLIC
    Code:
      stack=3, locals=3, args_size=3
         0: aload_2
         1: aload_0
         2: invokevirtual #30                 // Method leftSide:()Ljava/lang/Object;
         5: aload_1
         6: invokeinterface #36,  3           // InterfaceMethod org/scalactic/Equality.areEqual:(Ljava/lang/Object;Ljava/lang/Object;)Z
        11: ireturn
      LineNumberTable:
        line 117: 0
      LocalVariableTable:
        Start  Length  Slot  Name   Signature
            0      12     0  this   Lorg/scalactic/TripleEqualsSupport$Equalizer;
            0      12     1 rightSide   Ljava/lang/Object;
            0      12     2 equality   Lorg/scalactic/Equality;
    Signature: #26                          // (Ljava/lang/Object;Lorg/scalactic/Equality<TL;>;)Z
    MethodParameters:
      Name                           Flags
      rightSide                      final
      equality                       final

  public boolean $bang$eq$eq(java.lang.Object, org.scalactic.Equality<L>);
    descriptor: (Ljava/lang/Object;Lorg/scalactic/Equality;)Z
    flags: (0x0001) ACC_PUBLIC
    Code:
      stack=3, locals=3, args_size=3
         0: aload_2
         1: aload_0
         2: invokevirtual #30                 // Method leftSide:()Ljava/lang/Object;
         5: aload_1
         6: invokeinterface #36,  3           // InterfaceMethod org/scalactic/Equality.areEqual:(Ljava/lang/Object;Ljava/lang/Object;)Z
        11: ifne          18
        14: iconst_1
        15: goto          19
        18: iconst_0
        19: ireturn
      StackMapTable: number_of_entries = 2
        frame_type = 18 /* same */
        frame_type = 64 /* same_locals_1_stack_item */
          stack = [ int ]
      LineNumberTable:
        line 126: 0
      LocalVariableTable:
        Start  Length  Slot  Name   Signature
            0      20     0  this   Lorg/scalactic/TripleEqualsSupport$Equalizer;
            0      20     1 rightSide   Ljava/lang/Object;
            0      20     2 equality   Lorg/scalactic/Equality;
    Signature: #26                          // (Ljava/lang/Object;Lorg/scalactic/Equality<TL;>;)Z
    MethodParameters:
      Name                           Flags
      rightSide                      final
      equality                       final

  public boolean $eq$eq$eq(org.scalactic.TripleEqualsSupport$Spread<L>);
    descriptor: (Lorg/scalactic/TripleEqualsSupport$Spread;)Z
    flags: (0x0001) ACC_PUBLIC
    Code:
      stack=2, locals=3, args_size=2
         0: aload_1
         1: ifnull        15
         4: aload_1
         5: aload_0
         6: invokevirtual #30                 // Method leftSide:()Ljava/lang/Object;
         9: invokevirtual #45                 // Method org/scalactic/TripleEqualsSupport$Spread.isWithin:(Ljava/lang/Object;)Z
        12: goto          45
        15: aload_0
        16: invokevirtual #30                 // Method leftSide:()Ljava/lang/Object;
        19: aload_1
        20: astore_2
        21: dup
        22: ifnonnull     33
        25: pop
        26: aload_2
        27: ifnull        40
        30: goto          44
        33: aload_2
        34: invokevirtual #48                 // Method java/lang/Object.equals:(Ljava/lang/Object;)Z
        37: ifeq          44
        40: iconst_1
        41: goto          45
        44: iconst_0
        45: ireturn
      StackMapTable: number_of_entries = 5
        frame_type = 15 /* same */
        frame_type = 255 /* full_frame */
          offset_delta = 17
          locals = [ class org/scalactic/TripleEqualsSupport$Equalizer, class org/scalactic/TripleEqualsSupport$Spread, class org/scalactic/TripleEqualsSupport$Spread ]
          stack = [ class java/lang/Object ]
        frame_type = 6 /* same */
        frame_type = 3 /* same */
        frame_type = 255 /* full_frame */
          offset_delta = 0
          locals = [ class org/scalactic/TripleEqualsSupport$Equalizer, class org/scalactic/TripleEqualsSupport$Spread ]
          stack = [ int ]
      LineNumberTable:
        line 134: 0
      LocalVariableTable:
        Start  Length  Slot  Name   Signature
            0      46     0  this   Lorg/scalactic/TripleEqualsSupport$Equalizer;
            0      46     1 spread   Lorg/scalactic/TripleEqualsSupport$Spread;
    Signature: #40                          // (Lorg/scalactic/TripleEqualsSupport$Spread<TL;>;)Z
    MethodParameters:
      Name                           Flags
      spread                         final

  public boolean $bang$eq$eq(org.scalactic.TripleEqualsSupport$Spread<L>);
    descriptor: (Lorg/scalactic/TripleEqualsSupport$Spread;)Z
    flags: (0x0001) ACC_PUBLIC
    Code:
      stack=2, locals=3, args_size=2
         0: aload_1
         1: ifnull        23
         4: aload_1
         5: aload_0
         6: invokevirtual #30                 // Method leftSide:()Ljava/lang/Object;
         9: invokevirtual #45                 // Method org/scalactic/TripleEqualsSupport$Spread.isWithin:(Ljava/lang/Object;)Z
        12: ifne          19
        15: iconst_1
        16: goto          20
        19: iconst_0
        20: goto          53
        23: aload_0
        24: invokevirtual #30                 // Method leftSide:()Ljava/lang/Object;
        27: aload_1
        28: astore_2
        29: dup
        30: ifnonnull     41
        33: pop
        34: aload_2
        35: ifnull        52
        38: goto          48
        41: aload_2
        42: invokevirtual #48                 // Method java/lang/Object.equals:(Ljava/lang/Object;)Z
        45: ifne          52
        48: iconst_1
        49: goto          53
        52: iconst_0
        53: ireturn
      StackMapTable: number_of_entries = 7
        frame_type = 19 /* same */
        frame_type = 64 /* same_locals_1_stack_item */
          stack = [ int ]
        frame_type = 2 /* same */
        frame_type = 255 /* full_frame */
          offset_delta = 17
          locals = [ class org/scalactic/TripleEqualsSupport$Equalizer, class org/scalactic/TripleEqualsSupport$Spread, class org/scalactic/TripleEqualsSupport$Spread ]
          stack = [ class java/lang/Object ]
        frame_type = 6 /* same */
        frame_type = 3 /* same */
        frame_type = 255 /* full_frame */
          offset_delta = 0
          locals = [ class org/scalactic/TripleEqualsSupport$Equalizer, class org/scalactic/TripleEqualsSupport$Spread ]
          stack = [ int ]
      LineNumberTable:
        line 142: 0
      LocalVariableTable:
        Start  Length  Slot  Name   Signature
            0      54     0  this   Lorg/scalactic/TripleEqualsSupport$Equalizer;
            0      54     1 spread   Lorg/scalactic/TripleEqualsSupport$Spread;
    Signature: #40                          // (Lorg/scalactic/TripleEqualsSupport$Spread<TL;>;)Z
    MethodParameters:
      Name                           Flags
      spread                         final

  public boolean $eq$eq$eq(scala.runtime.Null$);
    descriptor: (Lscala/runtime/Null$;)Z
    flags: (0x0001) ACC_PUBLIC
    Code:
      stack=1, locals=2, args_size=2
         0: aload_0
         1: invokevirtual #30                 // Method leftSide:()Ljava/lang/Object;
         4: ifnonnull     11
         7: iconst_1
         8: goto          12
        11: iconst_0
        12: ireturn
      StackMapTable: number_of_entries = 2
        frame_type = 11 /* same */
        frame_type = 64 /* same_locals_1_stack_item */
          stack = [ int ]
      LineNumberTable:
        line 150: 0
      LocalVariableTable:
        Start  Length  Slot  Name   Signature
            0      13     0  this   Lorg/scalactic/TripleEqualsSupport$Equalizer;
            0      13     1 literalNull   Lscala/runtime/Null$;
    MethodParameters:
      Name                           Flags
      literalNull                    final

  public boolean $bang$eq$eq(scala.runtime.Null$);
    descriptor: (Lscala/runtime/Null$;)Z
    flags: (0x0001) ACC_PUBLIC
    Code:
      stack=1, locals=2, args_size=2
         0: aload_0
         1: invokevirtual #30                 // Method leftSide:()Ljava/lang/Object;
         4: ifnull        11
         7: iconst_1
         8: goto          12
        11: iconst_0
        12: ireturn
      StackMapTable: number_of_entries = 2
        frame_type = 11 /* same */
        frame_type = 64 /* same_locals_1_stack_item */
          stack = [ int ]
      LineNumberTable:
        line 158: 0
      LocalVariableTable:
        Start  Length  Slot  Name   Signature
            0      13     0  this   Lorg/scalactic/TripleEqualsSupport$Equalizer;
            0      13     1 literalNull   Lscala/runtime/Null$;
    MethodParameters:
      Name                           Flags
      literalNull                    final

  public org.scalactic.TripleEqualsSupport org$scalactic$TripleEqualsSupport$Equalizer$$$outer();
    descriptor: ()Lorg/scalactic/TripleEqualsSupport;
    flags: (0x1001) ACC_PUBLIC, ACC_SYNTHETIC
    Code:
      stack=1, locals=1, args_size=1
         0: aload_0
         1: getfield      #56                 // Field $outer:Lorg/scalactic/TripleEqualsSupport;
         4: areturn
      LineNumberTable:
        line 108: 0
      LocalVariableTable:
        Start  Length  Slot  Name   Signature
            0       5     0  this   Lorg/scalactic/TripleEqualsSupport$Equalizer;

  public org.scalactic.TripleEqualsSupport$Equalizer(L);
    descriptor: (Lorg/scalactic/TripleEqualsSupport;Ljava/lang/Object;)V
    flags: (0x0001) ACC_PUBLIC
    Code:
      stack=2, locals=3, args_size=3
         0: aload_0
         1: aload_2
         2: putfield      #21                 // Field leftSide:Ljava/lang/Object;
         5: aload_1
         6: ifnonnull     11
         9: aconst_null
        10: athrow
        11: aload_0
        12: aload_1
        13: putfield      #56                 // Field $outer:Lorg/scalactic/TripleEqualsSupport;
        16: aload_0
        17: invokespecial #62                 // Method java/lang/Object."<init>":()V
        20: return
      StackMapTable: number_of_entries = 1
        frame_type = 11 /* same */
      LineNumberTable:
        line 108: 0
        line 185: 16
        line 108: 20
      LocalVariableTable:
        Start  Length  Slot  Name   Signature
            0      21     0  this   Lorg/scalactic/TripleEqualsSupport$Equalizer;
            0      21     1 $outer   Lorg/scalactic/TripleEqualsSupport;
            0      21     2 leftSide   Ljava/lang/Object;
    Signature: #59                          // (TL;)V
    MethodParameters:
      Name                           Flags
      $outer                         final synthetic
      leftSide                       final
}
InnerClasses:
  public #9= #2 of #8;                    // Equalizer=class org/scalactic/TripleEqualsSupport$Equalizer of class org/scalactic/TripleEqualsSupport
  public static final #12= #11 of #8;     // Spread=class org/scalactic/TripleEqualsSupport$Spread of class org/scalactic/TripleEqualsSupport
Signature: #3                           // <L:Ljava/lang/Object;>Ljava/lang/Object;
SourceFile: "TripleEqualsSupport.scala"
  ScalaInlineInfo: length = 0x31 (unknown attribute)
   01 00 00 09 00 26 00 19 00 00 26 00 27 00 00 26
   00 32 00 00 18 00 19 00 00 18 00 27 00 00 18 00
   32 00 00 39 00 3A 00 00 0D 00 12 00 00 35 00 36
   00
  Scala: length = 0x0 (unknown attribute)

