Classfile /Users/mw/Projects/slang-braindump/.jar/jar8/assemble/slang-braindump/assemble/content/org/scalactic/TripleEqualsSupport$Spread.class
  Last modified May 29, 2022; size 6431 bytes
  SHA-256 checksum b02c7fa24cc42b2119baa79d36a7f229acfe01bbbc2e398bb5c019fd332fddda
  Compiled from "TripleEqualsSupport.scala"
public final class org.scalactic.TripleEqualsSupport$Spread<T extends java.lang.Object> extends java.lang.Object implements scala.Product, java.io.Serializable
  minor version: 0
  major version: 52
  flags: (0x0031) ACC_PUBLIC, ACC_FINAL, ACC_SUPER
  this_class: #2                          // org/scalactic/TripleEqualsSupport$Spread
  super_class: #5                         // java/lang/Object
  interfaces: 2, fields: 5, methods: 24, attributes: 6
Constant pool:
    #1 = Utf8               org/scalactic/TripleEqualsSupport$Spread
    #2 = Class              #1            // org/scalactic/TripleEqualsSupport$Spread
    #3 = Utf8               <T:Ljava/lang/Object;>Ljava/lang/Object;Lscala/Product;Ljava/io/Serializable;
    #4 = Utf8               java/lang/Object
    #5 = Class              #4            // java/lang/Object
    #6 = Utf8               scala/Product
    #7 = Class              #6            // scala/Product
    #8 = Utf8               java/io/Serializable
    #9 = Class              #8            // java/io/Serializable
   #10 = Utf8               TripleEqualsSupport.scala
   #11 = Utf8               java/lang/invoke/MethodHandles$Lookup
   #12 = Class              #11           // java/lang/invoke/MethodHandles$Lookup
   #13 = Utf8               java/lang/invoke/MethodHandles
   #14 = Class              #13           // java/lang/invoke/MethodHandles
   #15 = Utf8               Lookup
   #16 = Utf8               org/scalactic/TripleEqualsSupport
   #17 = Class              #16           // org/scalactic/TripleEqualsSupport
   #18 = Utf8               Spread
   #19 = Utf8               pivot
   #20 = Utf8               Ljava/lang/Object;
   #21 = Utf8               TT;
   #22 = Utf8               tolerance
   #23 = Utf8               numeric
   #24 = Utf8               Lscala/math/Numeric;
   #25 = Utf8               Lscala/math/Numeric<TT;>;
   #26 = Utf8               max
   #27 = Utf8               min
   #28 = Utf8               productElementNames
   #29 = Utf8               ()Lscala/collection/Iterator;
   #30 = Utf8               ()Lscala/collection/Iterator<Ljava/lang/String;>;
   #31 = Utf8               productElementNames$
   #32 = Utf8               (Lscala/Product;)Lscala/collection/Iterator;
   #33 = NameAndType        #31:#32       // productElementNames$:(Lscala/Product;)Lscala/collection/Iterator;
   #34 = InterfaceMethodref #7.#33        // scala/Product.productElementNames$:(Lscala/Product;)Lscala/collection/Iterator;
   #35 = Utf8               this
   #36 = Utf8               Lorg/scalactic/TripleEqualsSupport$Spread;
   #37 = Utf8               ()Ljava/lang/Object;
   #38 = Utf8               ()TT;
   #39 = NameAndType        #19:#20       // pivot:Ljava/lang/Object;
   #40 = Fieldref           #2.#39        // org/scalactic/TripleEqualsSupport$Spread.pivot:Ljava/lang/Object;
   #41 = NameAndType        #22:#20       // tolerance:Ljava/lang/Object;
   #42 = Fieldref           #2.#41        // org/scalactic/TripleEqualsSupport$Spread.tolerance:Ljava/lang/Object;
   #43 = Utf8               ()Lscala/math/Numeric;
   #44 = Utf8               ()Lscala/math/Numeric<TT;>;
   #45 = NameAndType        #23:#24       // numeric:Lscala/math/Numeric;
   #46 = Fieldref           #2.#45        // org/scalactic/TripleEqualsSupport$Spread.numeric:Lscala/math/Numeric;
   #47 = NameAndType        #26:#20       // max:Ljava/lang/Object;
   #48 = Fieldref           #2.#47        // org/scalactic/TripleEqualsSupport$Spread.max:Ljava/lang/Object;
   #49 = NameAndType        #27:#20       // min:Ljava/lang/Object;
   #50 = Fieldref           #2.#49        // org/scalactic/TripleEqualsSupport$Spread.min:Ljava/lang/Object;
   #51 = Utf8               isWithin
   #52 = Utf8               (Ljava/lang/Object;)Z
   #53 = Utf8               (TT;)Z
   #54 = Utf8               n
   #55 = NameAndType        #23:#43       // numeric:()Lscala/math/Numeric;
   #56 = Methodref          #2.#55        // org/scalactic/TripleEqualsSupport$Spread.numeric:()Lscala/math/Numeric;
   #57 = NameAndType        #27:#37       // min:()Ljava/lang/Object;
   #58 = Methodref          #2.#57        // org/scalactic/TripleEqualsSupport$Spread.min:()Ljava/lang/Object;
   #59 = Utf8               scala/math/Numeric
   #60 = Class              #59           // scala/math/Numeric
   #61 = Utf8               gteq
   #62 = Utf8               (Ljava/lang/Object;Ljava/lang/Object;)Z
   #63 = NameAndType        #61:#62       // gteq:(Ljava/lang/Object;Ljava/lang/Object;)Z
   #64 = InterfaceMethodref #60.#63       // scala/math/Numeric.gteq:(Ljava/lang/Object;Ljava/lang/Object;)Z
   #65 = NameAndType        #26:#37       // max:()Ljava/lang/Object;
   #66 = Methodref          #2.#65        // org/scalactic/TripleEqualsSupport$Spread.max:()Ljava/lang/Object;
   #67 = Utf8               lteq
   #68 = NameAndType        #67:#62       // lteq:(Ljava/lang/Object;Ljava/lang/Object;)Z
   #69 = InterfaceMethodref #60.#68       // scala/math/Numeric.lteq:(Ljava/lang/Object;Ljava/lang/Object;)Z
   #70 = Utf8               $eq$eq$eq
   #71 = NameAndType        #51:#52       // isWithin:(Ljava/lang/Object;)Z
   #72 = Methodref          #2.#71        // org/scalactic/TripleEqualsSupport$Spread.isWithin:(Ljava/lang/Object;)Z
   #73 = Utf8               $bang$eq$eq
   #74 = Utf8               toString
   #75 = Utf8               ()Ljava/lang/String;
   #76 = Utf8               java/lang/StringBuilder
   #77 = Class              #76           // java/lang/StringBuilder
   #78 = Integer            4
   #79 = Utf8               <init>
   #80 = Utf8               (I)V
   #81 = NameAndType        #79:#80       // "<init>":(I)V
   #82 = Methodref          #77.#81       // java/lang/StringBuilder."<init>":(I)V
   #83 = Utf8               org/scalactic/Prettifier$
   #84 = Class              #83           // org/scalactic/Prettifier$
   #85 = Utf8               MODULE$
   #86 = Utf8               Lorg/scalactic/Prettifier$;
   #87 = NameAndType        #85:#86       // MODULE$:Lorg/scalactic/Prettifier$;
   #88 = Fieldref           #84.#87       // org/scalactic/Prettifier$.MODULE$:Lorg/scalactic/Prettifier$;
   #89 = Utf8               default
   #90 = Utf8               ()Lorg/scalactic/Prettifier;
   #91 = NameAndType        #89:#90       // default:()Lorg/scalactic/Prettifier;
   #92 = Methodref          #84.#91       // org/scalactic/Prettifier$.default:()Lorg/scalactic/Prettifier;
   #93 = NameAndType        #19:#37       // pivot:()Ljava/lang/Object;
   #94 = Methodref          #2.#93        // org/scalactic/TripleEqualsSupport$Spread.pivot:()Ljava/lang/Object;
   #95 = Utf8               org/scalactic/Prettifier
   #96 = Class              #95           // org/scalactic/Prettifier
   #97 = Utf8               apply
   #98 = Utf8               (Ljava/lang/Object;)Ljava/lang/String;
   #99 = NameAndType        #97:#98       // apply:(Ljava/lang/Object;)Ljava/lang/String;
  #100 = InterfaceMethodref #96.#99       // org/scalactic/Prettifier.apply:(Ljava/lang/Object;)Ljava/lang/String;
  #101 = Utf8               append
  #102 = Utf8               (Ljava/lang/String;)Ljava/lang/StringBuilder;
  #103 = NameAndType        #101:#102     // append:(Ljava/lang/String;)Ljava/lang/StringBuilder;
  #104 = Methodref          #77.#103      // java/lang/StringBuilder.append:(Ljava/lang/String;)Ljava/lang/StringBuilder;
  #105 = Utf8                +-
  #106 = String             #105          //  +-
  #107 = NameAndType        #22:#37       // tolerance:()Ljava/lang/Object;
  #108 = Methodref          #2.#107       // org/scalactic/TripleEqualsSupport$Spread.tolerance:()Ljava/lang/Object;
  #109 = NameAndType        #74:#75       // toString:()Ljava/lang/String;
  #110 = Methodref          #77.#109      // java/lang/StringBuilder.toString:()Ljava/lang/String;
  #111 = Utf8               copy
  #112 = Utf8               (Ljava/lang/Object;Ljava/lang/Object;Lscala/math/Numeric;)Lorg/scalactic/TripleEqualsSupport$Spread;
  #113 = Utf8               <T:Ljava/lang/Object;>(TT;TT;Lscala/math/Numeric<TT;>;)Lorg/scalactic/TripleEqualsSupport$Spread<TT;>;
  #114 = Utf8               evidence$1
  #115 = Utf8               (Ljava/lang/Object;Ljava/lang/Object;Lscala/math/Numeric;)V
  #116 = NameAndType        #79:#115      // "<init>":(Ljava/lang/Object;Ljava/lang/Object;Lscala/math/Numeric;)V
  #117 = Methodref          #2.#116       // org/scalactic/TripleEqualsSupport$Spread."<init>":(Ljava/lang/Object;Ljava/lang/Object;Lscala/math/Numeric;)V
  #118 = Utf8               copy$default$1
  #119 = Utf8               <T:Ljava/lang/Object;>()TT;
  #120 = Utf8               copy$default$2
  #121 = Utf8               productPrefix
  #122 = String             #18           // Spread
  #123 = Utf8               productArity
  #124 = Utf8               ()I
  #125 = Utf8               productElement
  #126 = Utf8               (I)Ljava/lang/Object;
  #127 = Utf8               x$1
  #128 = Utf8               scala/runtime/Statics
  #129 = Class              #128          // scala/runtime/Statics
  #130 = Utf8               ioobe
  #131 = NameAndType        #130:#126     // ioobe:(I)Ljava/lang/Object;
  #132 = Methodref          #129.#131     // scala/runtime/Statics.ioobe:(I)Ljava/lang/Object;
  #133 = Utf8               I
  #134 = Utf8               productIterator
  #135 = Utf8               ()Lscala/collection/Iterator<Ljava/lang/Object;>;
  #136 = Utf8               scala/runtime/ScalaRunTime$
  #137 = Class              #136          // scala/runtime/ScalaRunTime$
  #138 = Utf8               Lscala/runtime/ScalaRunTime$;
  #139 = NameAndType        #85:#138      // MODULE$:Lscala/runtime/ScalaRunTime$;
  #140 = Fieldref           #137.#139     // scala/runtime/ScalaRunTime$.MODULE$:Lscala/runtime/ScalaRunTime$;
  #141 = Utf8               typedProductIterator
  #142 = NameAndType        #141:#32      // typedProductIterator:(Lscala/Product;)Lscala/collection/Iterator;
  #143 = Methodref          #137.#142     // scala/runtime/ScalaRunTime$.typedProductIterator:(Lscala/Product;)Lscala/collection/Iterator;
  #144 = Utf8               canEqual
  #145 = Utf8               productElementName
  #146 = Utf8               (I)Ljava/lang/String;
  #147 = String             #19           // pivot
  #148 = String             #22           // tolerance
  #149 = String             #114          // evidence$1
  #150 = Utf8               java/lang/String
  #151 = Class              #150          // java/lang/String
  #152 = Utf8               hashCode
  #153 = Utf8               _hashCode
  #154 = Utf8               (Lscala/Product;)I
  #155 = NameAndType        #153:#154     // _hashCode:(Lscala/Product;)I
  #156 = Methodref          #137.#155     // scala/runtime/ScalaRunTime$._hashCode:(Lscala/Product;)I
  #157 = Utf8               equals
  #158 = Utf8               scala/runtime/BoxesRunTime
  #159 = Class              #158          // scala/runtime/BoxesRunTime
  #160 = NameAndType        #157:#62      // equals:(Ljava/lang/Object;Ljava/lang/Object;)Z
  #161 = Methodref          #159.#160     // scala/runtime/BoxesRunTime.equals:(Ljava/lang/Object;Ljava/lang/Object;)Z
  #162 = Utf8               $anonfun$new$1
  #163 = Utf8               (Lorg/scalactic/TripleEqualsSupport$Spread;)Ljava/lang/String;
  #164 = Utf8               $this
  #165 = Integer            43
  #166 = Utf8               tolerance must be zero or greater, but was
  #167 = String             #166          // tolerance must be zero or greater, but was
  #168 = Utf8               (Ljava/lang/Object;)Ljava/lang/StringBuilder;
  #169 = NameAndType        #101:#168     // append:(Ljava/lang/Object;)Ljava/lang/StringBuilder;
  #170 = Methodref          #77.#169      // java/lang/StringBuilder.append:(Ljava/lang/Object;)Ljava/lang/StringBuilder;
  #171 = Utf8               (TT;TT;Lscala/math/Numeric<TT;>;)V
  #172 = Utf8               ()V
  #173 = NameAndType        #79:#172      // "<init>":()V
  #174 = Methodref          #5.#173       // java/lang/Object."<init>":()V
  #175 = Utf8               $init$
  #176 = Utf8               (Lscala/Product;)V
  #177 = NameAndType        #175:#176     // $init$:(Lscala/Product;)V
  #178 = InterfaceMethodref #7.#177       // scala/Product.$init$:(Lscala/Product;)V
  #179 = Utf8               scala/Predef$
  #180 = Class              #179          // scala/Predef$
  #181 = Utf8               Lscala/Predef$;
  #182 = NameAndType        #85:#181      // MODULE$:Lscala/Predef$;
  #183 = Fieldref           #180.#182     // scala/Predef$.MODULE$:Lscala/Predef$;
  #184 = Utf8               implicitly
  #185 = Utf8               (Ljava/lang/Object;)Ljava/lang/Object;
  #186 = NameAndType        #184:#185     // implicitly:(Ljava/lang/Object;)Ljava/lang/Object;
  #187 = Methodref          #180.#186     // scala/Predef$.implicitly:(Ljava/lang/Object;)Ljava/lang/Object;
  #188 = Utf8               signum
  #189 = Utf8               (Ljava/lang/Object;)I
  #190 = NameAndType        #188:#189     // signum:(Ljava/lang/Object;)I
  #191 = InterfaceMethodref #60.#190      // scala/math/Numeric.signum:(Ljava/lang/Object;)I
  #192 = MethodType         #37           //  ()Ljava/lang/Object;
  #193 = NameAndType        #162:#163     // $anonfun$new$1:(Lorg/scalactic/TripleEqualsSupport$Spread;)Ljava/lang/String;
  #194 = Methodref          #2.#193       // org/scalactic/TripleEqualsSupport$Spread.$anonfun$new$1:(Lorg/scalactic/TripleEqualsSupport$Spread;)Ljava/lang/String;
  #195 = MethodHandle       6:#194        // REF_invokeStatic org/scalactic/TripleEqualsSupport$Spread.$anonfun$new$1:(Lorg/scalactic/TripleEqualsSupport$Spread;)Ljava/lang/String;
  #196 = MethodType         #75           //  ()Ljava/lang/String;
  #197 = Integer            5
  #198 = Integer            1
  #199 = Utf8               java/lang/invoke/LambdaMetafactory
  #200 = Class              #199          // java/lang/invoke/LambdaMetafactory
  #201 = Utf8               altMetafactory
  #202 = Utf8               (Ljava/lang/invoke/MethodHandles$Lookup;Ljava/lang/String;Ljava/lang/invoke/MethodType;[Ljava/lang/Object;)Ljava/lang/invoke/CallSite;
  #203 = NameAndType        #201:#202     // altMetafactory:(Ljava/lang/invoke/MethodHandles$Lookup;Ljava/lang/String;Ljava/lang/invoke/MethodType;[Ljava/lang/Object;)Ljava/lang/invoke/CallSite;
  #204 = Methodref          #200.#203     // java/lang/invoke/LambdaMetafactory.altMetafactory:(Ljava/lang/invoke/MethodHandles$Lookup;Ljava/lang/String;Ljava/lang/invoke/MethodType;[Ljava/lang/Object;)Ljava/lang/invoke/CallSite;
  #205 = MethodHandle       6:#204        // REF_invokeStatic java/lang/invoke/LambdaMetafactory.altMetafactory:(Ljava/lang/invoke/MethodHandles$Lookup;Ljava/lang/String;Ljava/lang/invoke/MethodType;[Ljava/lang/Object;)Ljava/lang/invoke/CallSite;
  #206 = Utf8               (Lorg/scalactic/TripleEqualsSupport$Spread;)Lscala/Function0;
  #207 = NameAndType        #97:#206      // apply:(Lorg/scalactic/TripleEqualsSupport$Spread;)Lscala/Function0;
  #208 = InvokeDynamic      #0:#207       // #0:apply:(Lorg/scalactic/TripleEqualsSupport$Spread;)Lscala/Function0;
  #209 = Utf8               require
  #210 = Utf8               (ZLscala/Function0;)V
  #211 = NameAndType        #209:#210     // require:(ZLscala/Function0;)V
  #212 = Methodref          #180.#211     // scala/Predef$.require:(ZLscala/Function0;)V
  #213 = Utf8               plus
  #214 = Utf8               (Ljava/lang/Object;Ljava/lang/Object;)Ljava/lang/Object;
  #215 = NameAndType        #213:#214     // plus:(Ljava/lang/Object;Ljava/lang/Object;)Ljava/lang/Object;
  #216 = InterfaceMethodref #60.#215      // scala/math/Numeric.plus:(Ljava/lang/Object;Ljava/lang/Object;)Ljava/lang/Object;
  #217 = Utf8               minus
  #218 = NameAndType        #217:#214     // minus:(Ljava/lang/Object;Ljava/lang/Object;)Ljava/lang/Object;
  #219 = InterfaceMethodref #60.#218      // scala/math/Numeric.minus:(Ljava/lang/Object;Ljava/lang/Object;)Ljava/lang/Object;
  #220 = Utf8               $deserializeLambda$
  #221 = Utf8               (Ljava/lang/invoke/SerializedLambda;)Ljava/lang/Object;
  #222 = Utf8               scala/runtime/LambdaDeserialize
  #223 = Class              #222          // scala/runtime/LambdaDeserialize
  #224 = Utf8               bootstrap
  #225 = Utf8               (Ljava/lang/invoke/MethodHandles$Lookup;Ljava/lang/String;Ljava/lang/invoke/MethodType;[Ljava/lang/invoke/MethodHandle;)Ljava/lang/invoke/CallSite;
  #226 = NameAndType        #224:#225     // bootstrap:(Ljava/lang/invoke/MethodHandles$Lookup;Ljava/lang/String;Ljava/lang/invoke/MethodType;[Ljava/lang/invoke/MethodHandle;)Ljava/lang/invoke/CallSite;
  #227 = Methodref          #223.#226     // scala/runtime/LambdaDeserialize.bootstrap:(Ljava/lang/invoke/MethodHandles$Lookup;Ljava/lang/String;Ljava/lang/invoke/MethodType;[Ljava/lang/invoke/MethodHandle;)Ljava/lang/invoke/CallSite;
  #228 = MethodHandle       6:#227        // REF_invokeStatic scala/runtime/LambdaDeserialize.bootstrap:(Ljava/lang/invoke/MethodHandles$Lookup;Ljava/lang/String;Ljava/lang/invoke/MethodType;[Ljava/lang/invoke/MethodHandle;)Ljava/lang/invoke/CallSite;
  #229 = Utf8               lambdaDeserialize
  #230 = NameAndType        #229:#221     // lambdaDeserialize:(Ljava/lang/invoke/SerializedLambda;)Ljava/lang/Object;
  #231 = InvokeDynamic      #1:#230       // #1:lambdaDeserialize:(Ljava/lang/invoke/SerializedLambda;)Ljava/lang/Object;
  #232 = Utf8               Signature
  #233 = Utf8               Code
  #234 = Utf8               LineNumberTable
  #235 = Utf8               LocalVariableTable
  #236 = Utf8               StackMapTable
  #237 = Utf8               MethodParameters
  #238 = Utf8               InnerClasses
  #239 = Utf8               SourceFile
  #240 = Utf8               BootstrapMethods
  #241 = Utf8               ScalaInlineInfo
  #242 = Utf8               Scala
{
  private final T pivot;
    descriptor: Ljava/lang/Object;
    flags: (0x0012) ACC_PRIVATE, ACC_FINAL
    Signature: #21                          // TT;

  private final T tolerance;
    descriptor: Ljava/lang/Object;
    flags: (0x0012) ACC_PRIVATE, ACC_FINAL
    Signature: #21                          // TT;

  private final scala.math.Numeric<T> numeric;
    descriptor: Lscala/math/Numeric;
    flags: (0x0012) ACC_PRIVATE, ACC_FINAL
    Signature: #25                          // Lscala/math/Numeric<TT;>;

  private final T max;
    descriptor: Ljava/lang/Object;
    flags: (0x0012) ACC_PRIVATE, ACC_FINAL
    Signature: #21                          // TT;

  private final T min;
    descriptor: Ljava/lang/Object;
    flags: (0x0012) ACC_PRIVATE, ACC_FINAL
    Signature: #21                          // TT;

  public scala.collection.Iterator<java.lang.String> productElementNames();
    descriptor: ()Lscala/collection/Iterator;
    flags: (0x0001) ACC_PUBLIC
    Code:
      stack=1, locals=1, args_size=1
         0: aload_0
         1: invokestatic  #34                 // InterfaceMethod scala/Product.productElementNames$:(Lscala/Product;)Lscala/collection/Iterator;
         4: areturn
      LineNumberTable:
        line 697: 0
      LocalVariableTable:
        Start  Length  Slot  Name   Signature
            0       5     0  this   Lorg/scalactic/TripleEqualsSupport$Spread;
    Signature: #30                          // ()Lscala/collection/Iterator<Ljava/lang/String;>;

  public T pivot();
    descriptor: ()Ljava/lang/Object;
    flags: (0x0001) ACC_PUBLIC
    Code:
      stack=1, locals=1, args_size=1
         0: aload_0
         1: getfield      #40                 // Field pivot:Ljava/lang/Object;
         4: areturn
      LineNumberTable:
        line 697: 0
      LocalVariableTable:
        Start  Length  Slot  Name   Signature
            0       5     0  this   Lorg/scalactic/TripleEqualsSupport$Spread;
    Signature: #38                          // ()TT;

  public T tolerance();
    descriptor: ()Ljava/lang/Object;
    flags: (0x0001) ACC_PUBLIC
    Code:
      stack=1, locals=1, args_size=1
         0: aload_0
         1: getfield      #42                 // Field tolerance:Ljava/lang/Object;
         4: areturn
      LineNumberTable:
        line 697: 0
      LocalVariableTable:
        Start  Length  Slot  Name   Signature
            0       5     0  this   Lorg/scalactic/TripleEqualsSupport$Spread;
    Signature: #38                          // ()TT;

  private scala.math.Numeric<T> numeric();
    descriptor: ()Lscala/math/Numeric;
    flags: (0x0002) ACC_PRIVATE
    Code:
      stack=1, locals=1, args_size=1
         0: aload_0
         1: getfield      #46                 // Field numeric:Lscala/math/Numeric;
         4: areturn
      LineNumberTable:
        line 699: 0
      LocalVariableTable:
        Start  Length  Slot  Name   Signature
            0       5     0  this   Lorg/scalactic/TripleEqualsSupport$Spread;
    Signature: #44                          // ()Lscala/math/Numeric<TT;>;

  private T max();
    descriptor: ()Ljava/lang/Object;
    flags: (0x0002) ACC_PRIVATE
    Code:
      stack=1, locals=1, args_size=1
         0: aload_0
         1: getfield      #48                 // Field max:Ljava/lang/Object;
         4: areturn
      LineNumberTable:
        line 703: 0
      LocalVariableTable:
        Start  Length  Slot  Name   Signature
            0       5     0  this   Lorg/scalactic/TripleEqualsSupport$Spread;
    Signature: #38                          // ()TT;

  private T min();
    descriptor: ()Ljava/lang/Object;
    flags: (0x0002) ACC_PRIVATE
    Code:
      stack=1, locals=1, args_size=1
         0: aload_0
         1: getfield      #50                 // Field min:Ljava/lang/Object;
         4: areturn
      LineNumberTable:
        line 704: 0
      LocalVariableTable:
        Start  Length  Slot  Name   Signature
            0       5     0  this   Lorg/scalactic/TripleEqualsSupport$Spread;
    Signature: #38                          // ()TT;

  public boolean isWithin(T);
    descriptor: (Ljava/lang/Object;)Z
    flags: (0x0001) ACC_PUBLIC
    Code:
      stack=3, locals=2, args_size=2
         0: aload_0
         1: invokespecial #56                 // Method numeric:()Lscala/math/Numeric;
         4: aload_1
         5: aload_0
         6: invokespecial #58                 // Method min:()Ljava/lang/Object;
         9: invokeinterface #64,  3           // InterfaceMethod scala/math/Numeric.gteq:(Ljava/lang/Object;Ljava/lang/Object;)Z
        14: ifeq          38
        17: aload_0
        18: invokespecial #56                 // Method numeric:()Lscala/math/Numeric;
        21: aload_1
        22: aload_0
        23: invokespecial #66                 // Method max:()Ljava/lang/Object;
        26: invokeinterface #69,  3           // InterfaceMethod scala/math/Numeric.lteq:(Ljava/lang/Object;Ljava/lang/Object;)Z
        31: ifeq          38
        34: iconst_1
        35: goto          39
        38: iconst_0
        39: ireturn
      StackMapTable: number_of_entries = 2
        frame_type = 38 /* same */
        frame_type = 64 /* same_locals_1_stack_item */
          stack = [ int ]
      LineNumberTable:
        line 711: 0
      LocalVariableTable:
        Start  Length  Slot  Name   Signature
            0      40     0  this   Lorg/scalactic/TripleEqualsSupport$Spread;
            0      40     1     n   Ljava/lang/Object;
    Signature: #53                          // (TT;)Z
    MethodParameters:
      Name                           Flags
      n                              final

  public boolean $eq$eq$eq(T);
    descriptor: (Ljava/lang/Object;)Z
    flags: (0x0001) ACC_PUBLIC
    Code:
      stack=2, locals=2, args_size=2
         0: aload_0
         1: aload_1
         2: invokevirtual #72                 // Method isWithin:(Ljava/lang/Object;)Z
         5: ireturn
      LineNumberTable:
        line 736: 0
      LocalVariableTable:
        Start  Length  Slot  Name   Signature
            0       6     0  this   Lorg/scalactic/TripleEqualsSupport$Spread;
            0       6     1     n   Ljava/lang/Object;
    Signature: #53                          // (TT;)Z
    MethodParameters:
      Name                           Flags
      n                              final

  public boolean $bang$eq$eq(T);
    descriptor: (Ljava/lang/Object;)Z
    flags: (0x0001) ACC_PUBLIC
    Code:
      stack=2, locals=2, args_size=2
         0: aload_0
         1: aload_1
         2: invokevirtual #72                 // Method isWithin:(Ljava/lang/Object;)Z
         5: ifne          12
         8: iconst_1
         9: goto          13
        12: iconst_0
        13: ireturn
      StackMapTable: number_of_entries = 2
        frame_type = 12 /* same */
        frame_type = 64 /* same_locals_1_stack_item */
          stack = [ int ]
      LineNumberTable:
        line 760: 0
      LocalVariableTable:
        Start  Length  Slot  Name   Signature
            0      14     0  this   Lorg/scalactic/TripleEqualsSupport$Spread;
            0      14     1     n   Ljava/lang/Object;
    Signature: #53                          // (TT;)Z
    MethodParameters:
      Name                           Flags
      n                              final

  public java.lang.String toString();
    descriptor: ()Ljava/lang/String;
    flags: (0x0001) ACC_PUBLIC
    Code:
      stack=3, locals=1, args_size=1
         0: new           #77                 // class java/lang/StringBuilder
         3: dup
         4: ldc           #78                 // int 4
         6: invokespecial #82                 // Method java/lang/StringBuilder."<init>":(I)V
         9: getstatic     #88                 // Field org/scalactic/Prettifier$.MODULE$:Lorg/scalactic/Prettifier$;
        12: invokevirtual #92                 // Method org/scalactic/Prettifier$.default:()Lorg/scalactic/Prettifier;
        15: aload_0
        16: invokevirtual #94                 // Method pivot:()Ljava/lang/Object;
        19: invokeinterface #100,  2          // InterfaceMethod org/scalactic/Prettifier.apply:(Ljava/lang/Object;)Ljava/lang/String;
        24: invokevirtual #104                // Method java/lang/StringBuilder.append:(Ljava/lang/String;)Ljava/lang/StringBuilder;
        27: ldc           #106                // String  +-
        29: invokevirtual #104                // Method java/lang/StringBuilder.append:(Ljava/lang/String;)Ljava/lang/StringBuilder;
        32: getstatic     #88                 // Field org/scalactic/Prettifier$.MODULE$:Lorg/scalactic/Prettifier$;
        35: invokevirtual #92                 // Method org/scalactic/Prettifier$.default:()Lorg/scalactic/Prettifier;
        38: aload_0
        39: invokevirtual #108                // Method tolerance:()Ljava/lang/Object;
        42: invokeinterface #100,  2          // InterfaceMethod org/scalactic/Prettifier.apply:(Ljava/lang/Object;)Ljava/lang/String;
        47: invokevirtual #104                // Method java/lang/StringBuilder.append:(Ljava/lang/String;)Ljava/lang/StringBuilder;
        50: invokevirtual #110                // Method java/lang/StringBuilder.toString:()Ljava/lang/String;
        53: areturn
      LineNumberTable:
        line 765: 0
      LocalVariableTable:
        Start  Length  Slot  Name   Signature
            0      54     0  this   Lorg/scalactic/TripleEqualsSupport$Spread;

  public <T extends java.lang.Object> org.scalactic.TripleEqualsSupport$Spread<T> copy(T, T, scala.math.Numeric<T>);
    descriptor: (Ljava/lang/Object;Ljava/lang/Object;Lscala/math/Numeric;)Lorg/scalactic/TripleEqualsSupport$Spread;
    flags: (0x0001) ACC_PUBLIC
    Code:
      stack=5, locals=4, args_size=4
         0: new           #2                  // class org/scalactic/TripleEqualsSupport$Spread
         3: dup
         4: aload_1
         5: aload_2
         6: aload_3
         7: invokespecial #117                // Method "<init>":(Ljava/lang/Object;Ljava/lang/Object;Lscala/math/Numeric;)V
        10: areturn
      LineNumberTable:
        line 697: 0
      LocalVariableTable:
        Start  Length  Slot  Name   Signature
            0      11     0  this   Lorg/scalactic/TripleEqualsSupport$Spread;
            0      11     1 pivot   Ljava/lang/Object;
            0      11     2 tolerance   Ljava/lang/Object;
            0      11     3 evidence$1   Lscala/math/Numeric;
    Signature: #113                         // <T:Ljava/lang/Object;>(TT;TT;Lscala/math/Numeric<TT;>;)Lorg/scalactic/TripleEqualsSupport$Spread<TT;>;
    MethodParameters:
      Name                           Flags
      pivot                          final
      tolerance                      final
      evidence$1                     final

  public <T extends java.lang.Object> T copy$default$1();
    descriptor: ()Ljava/lang/Object;
    flags: (0x0001) ACC_PUBLIC
    Code:
      stack=1, locals=1, args_size=1
         0: aload_0
         1: invokevirtual #94                 // Method pivot:()Ljava/lang/Object;
         4: areturn
      LineNumberTable:
        line 697: 0
      LocalVariableTable:
        Start  Length  Slot  Name   Signature
            0       5     0  this   Lorg/scalactic/TripleEqualsSupport$Spread;
    Signature: #119                         // <T:Ljava/lang/Object;>()TT;

  public <T extends java.lang.Object> T copy$default$2();
    descriptor: ()Ljava/lang/Object;
    flags: (0x0001) ACC_PUBLIC
    Code:
      stack=1, locals=1, args_size=1
         0: aload_0
         1: invokevirtual #108                // Method tolerance:()Ljava/lang/Object;
         4: areturn
      LineNumberTable:
        line 697: 0
      LocalVariableTable:
        Start  Length  Slot  Name   Signature
            0       5     0  this   Lorg/scalactic/TripleEqualsSupport$Spread;
    Signature: #119                         // <T:Ljava/lang/Object;>()TT;

  public java.lang.String productPrefix();
    descriptor: ()Ljava/lang/String;
    flags: (0x0001) ACC_PUBLIC
    Code:
      stack=1, locals=1, args_size=1
         0: ldc           #122                // String Spread
         2: areturn
      LineNumberTable:
        line 697: 0
      LocalVariableTable:
        Start  Length  Slot  Name   Signature
            0       3     0  this   Lorg/scalactic/TripleEqualsSupport$Spread;

  public int productArity();
    descriptor: ()I
    flags: (0x0001) ACC_PUBLIC
    Code:
      stack=1, locals=1, args_size=1
         0: iconst_2
         1: ireturn
      LineNumberTable:
        line 697: 0
      LocalVariableTable:
        Start  Length  Slot  Name   Signature
            0       2     0  this   Lorg/scalactic/TripleEqualsSupport$Spread;

  public java.lang.Object productElement(int);
    descriptor: (I)Ljava/lang/Object;
    flags: (0x0001) ACC_PUBLIC
    Code:
      stack=1, locals=3, args_size=2
         0: iload_1
         1: istore_2
         2: iload_2
         3: tableswitch   { // 0 to 1
                       0: 24
                       1: 31
                 default: 38
            }
        24: aload_0
        25: invokevirtual #94                 // Method pivot:()Ljava/lang/Object;
        28: goto          45
        31: aload_0
        32: invokevirtual #108                // Method tolerance:()Ljava/lang/Object;
        35: goto          45
        38: iload_1
        39: invokestatic  #132                // Method scala/runtime/Statics.ioobe:(I)Ljava/lang/Object;
        42: goto          45
        45: areturn
      StackMapTable: number_of_entries = 4
        frame_type = 252 /* append */
          offset_delta = 24
          locals = [ int ]
        frame_type = 6 /* same */
        frame_type = 6 /* same */
        frame_type = 70 /* same_locals_1_stack_item */
          stack = [ class java/lang/Object ]
      LineNumberTable:
        line 697: 0
      LocalVariableTable:
        Start  Length  Slot  Name   Signature
            0      46     0  this   Lorg/scalactic/TripleEqualsSupport$Spread;
            0      46     1   x$1   I
    MethodParameters:
      Name                           Flags
      x$1                            final

  public scala.collection.Iterator<java.lang.Object> productIterator();
    descriptor: ()Lscala/collection/Iterator;
    flags: (0x0001) ACC_PUBLIC
    Code:
      stack=2, locals=1, args_size=1
         0: getstatic     #140                // Field scala/runtime/ScalaRunTime$.MODULE$:Lscala/runtime/ScalaRunTime$;
         3: aload_0
         4: invokevirtual #143                // Method scala/runtime/ScalaRunTime$.typedProductIterator:(Lscala/Product;)Lscala/collection/Iterator;
         7: areturn
      LineNumberTable:
        line 697: 0
      LocalVariableTable:
        Start  Length  Slot  Name   Signature
            0       8     0  this   Lorg/scalactic/TripleEqualsSupport$Spread;
    Signature: #135                         // ()Lscala/collection/Iterator<Ljava/lang/Object;>;

  public boolean canEqual(java.lang.Object);
    descriptor: (Ljava/lang/Object;)Z
    flags: (0x0001) ACC_PUBLIC
    Code:
      stack=1, locals=2, args_size=2
         0: aload_1
         1: instanceof    #2                  // class org/scalactic/TripleEqualsSupport$Spread
         4: ireturn
      LineNumberTable:
        line 697: 0
      LocalVariableTable:
        Start  Length  Slot  Name   Signature
            0       5     0  this   Lorg/scalactic/TripleEqualsSupport$Spread;
            0       5     1   x$1   Ljava/lang/Object;
    MethodParameters:
      Name                           Flags
      x$1                            final

  public java.lang.String productElementName(int);
    descriptor: (I)Ljava/lang/String;
    flags: (0x0001) ACC_PUBLIC
    Code:
      stack=1, locals=3, args_size=2
         0: iload_1
         1: istore_2
         2: iload_2
         3: tableswitch   { // 0 to 2
                       0: 28
                       1: 33
                       2: 38
                 default: 43
            }
        28: ldc           #147                // String pivot
        30: goto          53
        33: ldc           #148                // String tolerance
        35: goto          53
        38: ldc           #149                // String evidence$1
        40: goto          53
        43: iload_1
        44: invokestatic  #132                // Method scala/runtime/Statics.ioobe:(I)Ljava/lang/Object;
        47: checkcast     #151                // class java/lang/String
        50: goto          53
        53: areturn
      StackMapTable: number_of_entries = 5
        frame_type = 252 /* append */
          offset_delta = 28
          locals = [ int ]
        frame_type = 4 /* same */
        frame_type = 4 /* same */
        frame_type = 4 /* same */
        frame_type = 73 /* same_locals_1_stack_item */
          stack = [ class java/lang/String ]
      LineNumberTable:
        line 697: 0
      LocalVariableTable:
        Start  Length  Slot  Name   Signature
            0      54     0  this   Lorg/scalactic/TripleEqualsSupport$Spread;
            0      54     1   x$1   I
    MethodParameters:
      Name                           Flags
      x$1                            final

  public int hashCode();
    descriptor: ()I
    flags: (0x0001) ACC_PUBLIC
    Code:
      stack=2, locals=1, args_size=1
         0: getstatic     #140                // Field scala/runtime/ScalaRunTime$.MODULE$:Lscala/runtime/ScalaRunTime$;
         3: aload_0
         4: invokevirtual #156                // Method scala/runtime/ScalaRunTime$._hashCode:(Lscala/Product;)I
         7: ireturn
      LineNumberTable:
        line 697: 0
      LocalVariableTable:
        Start  Length  Slot  Name   Signature
            0       8     0  this   Lorg/scalactic/TripleEqualsSupport$Spread;

  public boolean equals(java.lang.Object);
    descriptor: (Ljava/lang/Object;)Z
    flags: (0x0001) ACC_PUBLIC
    Code:
      stack=2, locals=5, args_size=2
         0: aload_0
         1: aload_1
         2: if_acmpeq     75
         5: aload_1
         6: astore_3
         7: aload_3
         8: instanceof    #2                  // class org/scalactic/TripleEqualsSupport$Spread
        11: ifeq          19
        14: iconst_1
        15: istore_2
        16: goto          27
        19: goto          22
        22: iconst_0
        23: istore_2
        24: goto          27
        27: iload_2
        28: ifeq          79
        31: aload_1
        32: checkcast     #2                  // class org/scalactic/TripleEqualsSupport$Spread
        35: astore        4
        37: aload_0
        38: invokevirtual #94                 // Method pivot:()Ljava/lang/Object;
        41: aload         4
        43: invokevirtual #94                 // Method pivot:()Ljava/lang/Object;
        46: invokestatic  #161                // Method scala/runtime/BoxesRunTime.equals:(Ljava/lang/Object;Ljava/lang/Object;)Z
        49: ifeq          71
        52: aload_0
        53: invokevirtual #108                // Method tolerance:()Ljava/lang/Object;
        56: aload         4
        58: invokevirtual #108                // Method tolerance:()Ljava/lang/Object;
        61: invokestatic  #161                // Method scala/runtime/BoxesRunTime.equals:(Ljava/lang/Object;Ljava/lang/Object;)Z
        64: ifeq          71
        67: iconst_1
        68: goto          72
        71: iconst_0
        72: ifeq          79
        75: iconst_1
        76: goto          80
        79: iconst_0
        80: ireturn
      StackMapTable: number_of_entries = 8
        frame_type = 253 /* append */
          offset_delta = 19
          locals = [ top, class java/lang/Object ]
        frame_type = 2 /* same */
        frame_type = 255 /* full_frame */
          offset_delta = 4
          locals = [ class org/scalactic/TripleEqualsSupport$Spread, class java/lang/Object, int, class java/lang/Object ]
          stack = []
        frame_type = 252 /* append */
          offset_delta = 43
          locals = [ class org/scalactic/TripleEqualsSupport$Spread ]
        frame_type = 64 /* same_locals_1_stack_item */
          stack = [ int ]
        frame_type = 248 /* chop */
          offset_delta = 2
        frame_type = 253 /* append */
          offset_delta = 3
          locals = [ int, class java/lang/Object ]
        frame_type = 255 /* full_frame */
          offset_delta = 0
          locals = [ class org/scalactic/TripleEqualsSupport$Spread, class java/lang/Object ]
          stack = [ int ]
      LineNumberTable:
        line 697: 0
      LocalVariableTable:
        Start  Length  Slot  Name   Signature
            0      81     0  this   Lorg/scalactic/TripleEqualsSupport$Spread;
            0      81     1   x$1   Ljava/lang/Object;
    MethodParameters:
      Name                           Flags
      x$1                            final

  public static final java.lang.String $anonfun$new$1(org.scalactic.TripleEqualsSupport$Spread);
    descriptor: (Lorg/scalactic/TripleEqualsSupport$Spread;)Ljava/lang/String;
    flags: (0x1019) ACC_PUBLIC, ACC_STATIC, ACC_FINAL, ACC_SYNTHETIC
    Code:
      stack=3, locals=1, args_size=1
         0: new           #77                 // class java/lang/StringBuilder
         3: dup
         4: ldc           #165                // int 43
         6: invokespecial #82                 // Method java/lang/StringBuilder."<init>":(I)V
         9: ldc           #167                // String tolerance must be zero or greater, but was
        11: invokevirtual #104                // Method java/lang/StringBuilder.append:(Ljava/lang/String;)Ljava/lang/StringBuilder;
        14: aload_0
        15: invokevirtual #108                // Method tolerance:()Ljava/lang/Object;
        18: invokevirtual #170                // Method java/lang/StringBuilder.append:(Ljava/lang/Object;)Ljava/lang/StringBuilder;
        21: invokevirtual #110                // Method java/lang/StringBuilder.toString:()Ljava/lang/String;
        24: areturn
      LineNumberTable:
        line 701: 0
      LocalVariableTable:
        Start  Length  Slot  Name   Signature
            0      25     0 $this   Lorg/scalactic/TripleEqualsSupport$Spread;
    MethodParameters:
      Name                           Flags
      $this                          final synthetic

  public org.scalactic.TripleEqualsSupport$Spread(T, T, scala.math.Numeric<T>);
    descriptor: (Ljava/lang/Object;Ljava/lang/Object;Lscala/math/Numeric;)V
    flags: (0x0001) ACC_PUBLIC
    Code:
      stack=4, locals=4, args_size=4
         0: aload_0
         1: aload_1
         2: putfield      #40                 // Field pivot:Ljava/lang/Object;
         5: aload_0
         6: aload_2
         7: putfield      #42                 // Field tolerance:Ljava/lang/Object;
        10: aload_0
        11: invokespecial #174                // Method java/lang/Object."<init>":()V
        14: aload_0
        15: invokestatic  #178                // InterfaceMethod scala/Product.$init$:(Lscala/Product;)V
        18: aload_0
        19: getstatic     #183                // Field scala/Predef$.MODULE$:Lscala/Predef$;
        22: aload_3
        23: invokevirtual #187                // Method scala/Predef$.implicitly:(Ljava/lang/Object;)Ljava/lang/Object;
        26: checkcast     #60                 // class scala/math/Numeric
        29: putfield      #46                 // Field numeric:Lscala/math/Numeric;
        32: getstatic     #183                // Field scala/Predef$.MODULE$:Lscala/Predef$;
        35: aload_0
        36: invokespecial #56                 // Method numeric:()Lscala/math/Numeric;
        39: aload_2
        40: invokeinterface #191,  2          // InterfaceMethod scala/math/Numeric.signum:(Ljava/lang/Object;)I
        45: iconst_0
        46: if_icmplt     53
        49: iconst_1
        50: goto          54
        53: iconst_0
        54: aload_0
        55: invokedynamic #208,  0            // InvokeDynamic #0:apply:(Lorg/scalactic/TripleEqualsSupport$Spread;)Lscala/Function0;
        60: invokevirtual #212                // Method scala/Predef$.require:(ZLscala/Function0;)V
        63: aload_0
        64: aload_0
        65: invokespecial #56                 // Method numeric:()Lscala/math/Numeric;
        68: aload_1
        69: aload_2
        70: invokeinterface #216,  3          // InterfaceMethod scala/math/Numeric.plus:(Ljava/lang/Object;Ljava/lang/Object;)Ljava/lang/Object;
        75: putfield      #48                 // Field max:Ljava/lang/Object;
        78: aload_0
        79: aload_0
        80: invokespecial #56                 // Method numeric:()Lscala/math/Numeric;
        83: aload_1
        84: aload_2
        85: invokeinterface #219,  3          // InterfaceMethod scala/math/Numeric.minus:(Ljava/lang/Object;Ljava/lang/Object;)Ljava/lang/Object;
        90: putfield      #50                 // Field min:Ljava/lang/Object;
        93: return
      StackMapTable: number_of_entries = 2
        frame_type = 255 /* full_frame */
          offset_delta = 53
          locals = [ class org/scalactic/TripleEqualsSupport$Spread, class java/lang/Object, class java/lang/Object, class scala/math/Numeric ]
          stack = [ class scala/Predef$ ]
        frame_type = 255 /* full_frame */
          offset_delta = 0
          locals = [ class org/scalactic/TripleEqualsSupport$Spread, class java/lang/Object, class java/lang/Object, class scala/math/Numeric ]
          stack = [ class scala/Predef$, int ]
      LineNumberTable:
        line 697: 0
        line 699: 18
        line 701: 32
        line 703: 63
        line 704: 78
        line 697: 93
      LocalVariableTable:
        Start  Length  Slot  Name   Signature
            0      94     0  this   Lorg/scalactic/TripleEqualsSupport$Spread;
            0      94     1 pivot   Ljava/lang/Object;
            0      94     2 tolerance   Ljava/lang/Object;
            0      94     3 evidence$1   Lscala/math/Numeric;
    Signature: #171                         // (TT;TT;Lscala/math/Numeric<TT;>;)V
    MethodParameters:
      Name                           Flags
      pivot                          final
      tolerance                      final
      evidence$1                     final

  private static java.lang.Object $deserializeLambda$(java.lang.invoke.SerializedLambda);
    descriptor: (Ljava/lang/invoke/SerializedLambda;)Ljava/lang/Object;
    flags: (0x100a) ACC_PRIVATE, ACC_STATIC, ACC_SYNTHETIC
    Code:
      stack=1, locals=1, args_size=1
         0: aload_0
         1: invokedynamic #231,  0            // InvokeDynamic #1:lambdaDeserialize:(Ljava/lang/invoke/SerializedLambda;)Ljava/lang/Object;
         6: areturn
}
InnerClasses:
  public static final #15= #12 of #14;    // Lookup=class java/lang/invoke/MethodHandles$Lookup of class java/lang/invoke/MethodHandles
  public static final #18= #2 of #17;     // Spread=class org/scalactic/TripleEqualsSupport$Spread of class org/scalactic/TripleEqualsSupport
Signature: #3                           // <T:Ljava/lang/Object;>Ljava/lang/Object;Lscala/Product;Ljava/io/Serializable;
SourceFile: "TripleEqualsSupport.scala"
BootstrapMethods:
  0: #205 REF_invokeStatic java/lang/invoke/LambdaMetafactory.altMetafactory:(Ljava/lang/invoke/MethodHandles$Lookup;Ljava/lang/String;Ljava/lang/invoke/MethodType;[Ljava/lang/Object;)Ljava/lang/invoke/CallSite;
    Method arguments:
      #192 ()Ljava/lang/Object;
      #195 REF_invokeStatic org/scalactic/TripleEqualsSupport$Spread.$anonfun$new$1:(Lorg/scalactic/TripleEqualsSupport$Spread;)Ljava/lang/String;
      #196 ()Ljava/lang/String;
      #197 5
      #198 1
      #196 ()Ljava/lang/String;
  1: #228 REF_invokeStatic scala/runtime/LambdaDeserialize.bootstrap:(Ljava/lang/invoke/MethodHandles$Lookup;Ljava/lang/String;Ljava/lang/invoke/MethodType;[Ljava/lang/invoke/MethodHandle;)Ljava/lang/invoke/CallSite;
    Method arguments:
      #195 REF_invokeStatic org/scalactic/TripleEqualsSupport$Spread.$anonfun$new$1:(Lorg/scalactic/TripleEqualsSupport$Spread;)Ljava/lang/String;
  ScalaInlineInfo: length = 0x77 (unknown attribute)
   01 01 00 17 00 A2 00 A3 01 00 49 00 34 01 00 46
   00 34 01 00 4F 00 73 01 00 90 00 34 01 00 6F 00
   70 01 00 76 00 25 01 00 78 00 25 01 00 9D 00 34
   01 00 98 00 7C 01 00 33 00 34 01 00 1A 00 25 01
   00 1B 00 25 01 00 17 00 2B 01 00 13 00 25 01 00
   7B 00 7C 01 00 7D 00 7E 01 00 91 00 92 01 00 1C
   00 1D 01 00 86 00 1D 01 00 79 00 4B 01 00 4A 00
   4B 01 00 16 00 25 01
  Scala: length = 0x0 (unknown attribute)

