Classfile /Users/mw/Projects/slang-braindump/.jar/jar8/assemble/slang-braindump/assemble/content/org/scalactic/TrySugar.class
  Last modified May 29, 2022; size 1942 bytes
  SHA-256 checksum 43bafc10982457f706af8d51af075781c5d61a431e855fb80892a3d9ec3acb40
  Compiled from "TrySugar.scala"
public interface org.scalactic.TrySugar
  minor version: 0
  major version: 52
  flags: (0x0601) ACC_PUBLIC, ACC_INTERFACE, ACC_ABSTRACT
  this_class: #2                          // org/scalactic/TrySugar
  super_class: #4                         // java/lang/Object
  interfaces: 0, fields: 0, methods: 3, attributes: 5
Constant pool:
   #1 = Utf8               org/scalactic/TrySugar
   #2 = Class              #1             // org/scalactic/TrySugar
   #3 = Utf8               java/lang/Object
   #4 = Class              #3             // java/lang/Object
   #5 = Utf8               TrySugar.scala
   #6 = Utf8               Lscala/reflect/ScalaSignature;
   #7 = Utf8               bytes
   #8 = Utf8               \u0006\u0005\u0005%aa\u0002\u0007\u000e!\u0003\r\tA\u0005\u0005\u00063\u0001!\tA\u0007\u0004\u0005=\u0001\tq\u0004\u0003\u0005\"\u0005\t\u0005\t\u0015!\u0003#\u0011\u0015\u0019$\u0001\"\u00015\u0011\u0015A$\u0001\"\u0001:\u0011\u0015Q%\u0001\"\u0001L\u0011\u001dy\u0006!!A\u0005\u0004\u0001<QaZ\u0007\t\u0002!4Q\u0001D\u0007\t\u0002%DQaM\u0005\u0005\u0002-Da\u0001\\\u0005\u0005\u00025i\'\u0001\u0003+ssN+x-\u0019:\u000b\u00059y\u0011!C:dC2\f7\r^5d\u0015\u0005\u0001\u0012aA8sO\u000e\u00011C\u0001\u0001\u0014!\t!r#D\u0001\u0016\u0015\u00051\u0012!B:dC2\f\u0017B\u0001\r\u0016\u0005\u0019\te.\u001f*fM\u00061A%\u001b8ji\u0012\"\u0012a\u0007\t\u0003)qI!!H\u000b\u0003\tUs\u0017\u000e\u001e\u0002\b)JL\u0018N_3s+\t\u0001#f\u0005\u0002\u0003\'\u00051A\u000f[3Uef\u00042a\t\u0014)\u001b\u0005!#BA\u0013\u0016\u0003\u0011)H/\u001b7\n\u0005\u001d\"#a\u0001+ssB\u0011\u0011F\u000b\u0007\u0001\t\u0015Y#A1\u0001-\u0005\u0005!\u0016CA\u00171!\t!b&\u0003\u00020+\t9aj\u001c;iS:<\u0007C\u0001\u000b2\u0013\t\u0011TCA\u0002B]f\fa\u0001P5oSRtDCA\u001b8!\r1$\u0001K\u0007\u0002\u0001!)\u0011\u0005\u0002a\u0001E\u0005!Ao\\(s+\u0005Q\u0004\u0003B\u001e=Qyj\u0011!D\u0005\u0003{5\u0011!a\u0014:\u0011\u0005}:eB\u0001!F\u001d\t\tE)D\u0001C\u0015\t\u0019\u0015#\u0001\u0004=e>|GOP\u0005\u0002-%\u0011a)F\u0001\ba\u0006\u001c7.Y4f\u0013\tA\u0015JA\u0005UQJ|w/\u00192mK*\u0011a)F\u0001\u000bm\u0006d\u0017\u000eZ1uS:<Gc\u0001\u0012M5\")QJ\u0002a\u0001\u001d\u0006\u0011\u0001\u000e\u001a\t\u0005)=C\u0013+\u0003\u0002Q+\tIa)\u001e8di&|g.\r\t\u0004wI#\u0016BA*\u000e\u0005)1\u0016\r\\5eCRLwN\u001c\t\u0003+^s!a\u000f,\n\u0005\u0019k\u0011B\u0001-Z\u00051)%O]8s\u001b\u0016\u001c8/Y4f\u0015\t1U\u0002C\u0003\\\r\u0001\u0007A,\u0001\u0002uYB\u0019A#\u0018(\n\u0005y+\"A\u0003\u001fsKB,\u0017\r^3e}\u00059AK]=ju\u0016\u0014XCA1e)\t\u0011W\rE\u00027\u0005\r\u0004\"!\u000b3\u0005\u000b-:!\u0019\u0001\u0017\t\u000b\u0005:\u0001\u0019\u00014\u0011\u0007\r23-\u0001\u0005Uef\u001cVoZ1s!\tY\u0014bE\u0002\n\')\u0004\"a\u000f\u0001\u0015\u0003!\fq\u0002]1tg>\u0013h)\u001b:ti\u001a\u000b\u0017\u000e\\\u000b\u0004]Z\fHcA8toB\u00191H\u00159\u0011\u0005%\nH!\u0002:\f\u0005\u0004a#!A#\t\u000bQ\\\u0001\u0019A;\u0002\u0003=\u0004\"!\u000b<\u0005\u000b-Z!\u0019\u0001\u0017\t\u000ba\\\u0001\u0019A=\u0002\u0005\u0019\u001c\bcA {y&\u001110\u0013\u0002\u0005\u0019&\u001cH\u000f\u0005\u0003\u0015\u001fV|\u0007FA\u0006\u007f!\ry\u0018QA\u0007\u0003\u0003\u0003Q1!a\u0001\u0016\u0003)\tgN\\8uCRLwN\\\u0005\u0005\u0003\u000f\t\tAA\u0004uC&d\'/Z2
   #9 = Utf8               org/scalactic/TrySugar$Tryizer
  #10 = Class              #9             // org/scalactic/TrySugar$Tryizer
  #11 = Utf8               Tryizer
  #12 = Utf8               Tryizer$
  #13 = Utf8               (Lorg/scalactic/TrySugar;Lscala/util/Try;)Lorg/scalactic/TrySugar$Tryizer;
  #14 = Utf8               $this
  #15 = Utf8               theTry
  #16 = Utf8               (Lscala/util/Try;)Lorg/scalactic/TrySugar$Tryizer;
  #17 = NameAndType        #11:#16        // Tryizer:(Lscala/util/Try;)Lorg/scalactic/TrySugar$Tryizer;
  #18 = InterfaceMethodref #2.#17         // org/scalactic/TrySugar.Tryizer:(Lscala/util/Try;)Lorg/scalactic/TrySugar$Tryizer;
  #19 = Utf8               Lorg/scalactic/TrySugar;
  #20 = Utf8               Lscala/util/Try;
  #21 = Utf8               <T:Ljava/lang/Object;>(Lscala/util/Try<TT;>;)Lorg/scalactic/TrySugar$Tryizer<TT;>;
  #22 = Utf8               <init>
  #23 = Utf8               (Lorg/scalactic/TrySugar;Lscala/util/Try;)V
  #24 = NameAndType        #22:#23        // "<init>":(Lorg/scalactic/TrySugar;Lscala/util/Try;)V
  #25 = Methodref          #10.#24        // org/scalactic/TrySugar$Tryizer."<init>":(Lorg/scalactic/TrySugar;Lscala/util/Try;)V
  #26 = Utf8               this
  #27 = Utf8               $init$
  #28 = Utf8               (Lorg/scalactic/TrySugar;)V
  #29 = Utf8               Code
  #30 = Utf8               LineNumberTable
  #31 = Utf8               LocalVariableTable
  #32 = Utf8               MethodParameters
  #33 = Utf8               Signature
  #34 = Utf8               InnerClasses
  #35 = Utf8               SourceFile
  #36 = Utf8               RuntimeVisibleAnnotations
  #37 = Utf8               ScalaInlineInfo
  #38 = Utf8               ScalaSig
{
  public static org.scalactic.TrySugar$Tryizer Tryizer$(org.scalactic.TrySugar, scala.util.Try);
    descriptor: (Lorg/scalactic/TrySugar;Lscala/util/Try;)Lorg/scalactic/TrySugar$Tryizer;
    flags: (0x1009) ACC_PUBLIC, ACC_STATIC, ACC_SYNTHETIC
    Code:
      stack=2, locals=2, args_size=2
         0: aload_0
         1: aload_1
         2: invokespecial #18                 // InterfaceMethod Tryizer:(Lscala/util/Try;)Lorg/scalactic/TrySugar$Tryizer;
         5: areturn
      LineNumberTable:
        line 148: 0
      LocalVariableTable:
        Start  Length  Slot  Name   Signature
            0       6     0 $this   Lorg/scalactic/TrySugar;
            0       6     1 theTry   Lscala/util/Try;
    MethodParameters:
      Name                           Flags
      $this                          final synthetic
      theTry                         final

  public default <T extends java.lang.Object> org.scalactic.TrySugar$Tryizer<T> Tryizer(scala.util.Try<T>);
    descriptor: (Lscala/util/Try;)Lorg/scalactic/TrySugar$Tryizer;
    flags: (0x0001) ACC_PUBLIC
    Code:
      stack=4, locals=2, args_size=2
         0: new           #10                 // class org/scalactic/TrySugar$Tryizer
         3: dup
         4: aload_0
         5: aload_1
         6: invokespecial #25                 // Method org/scalactic/TrySugar$Tryizer."<init>":(Lorg/scalactic/TrySugar;Lscala/util/Try;)V
         9: areturn
      LineNumberTable:
        line 148: 0
      LocalVariableTable:
        Start  Length  Slot  Name   Signature
            0      10     0  this   Lorg/scalactic/TrySugar;
            0      10     1 theTry   Lscala/util/Try;
    Signature: #21                          // <T:Ljava/lang/Object;>(Lscala/util/Try<TT;>;)Lorg/scalactic/TrySugar$Tryizer<TT;>;
    MethodParameters:
      Name                           Flags
      theTry                         final

  public static void $init$(org.scalactic.TrySugar);
    descriptor: (Lorg/scalactic/TrySugar;)V
    flags: (0x0009) ACC_PUBLIC, ACC_STATIC
    Code:
      stack=0, locals=1, args_size=1
         0: return
      LineNumberTable:
        line 133: 0
      LocalVariableTable:
        Start  Length  Slot  Name   Signature
            0       1     0 $this   Lorg/scalactic/TrySugar;
    MethodParameters:
      Name                           Flags
      $this                          final synthetic
}
InnerClasses:
  public #11= #10 of #2;                  // Tryizer=class org/scalactic/TrySugar$Tryizer of class org/scalactic/TrySugar
SourceFile: "TrySugar.scala"
RuntimeVisibleAnnotations:
  0: #6(#7=s#8)
    scala.reflect.ScalaSignature(
      bytes="\u0006\u0005\u0005%aa\u0002\u0007\u000e!\u0003\r\tA\u0005\u0005\u00063\u0001!\tA\u0007\u0004\u0005=\u0001\tq\u0004\u0003\u0005\"\u0005\t\u0005\t\u0015!\u0003#\u0011\u0015\u0019$\u0001\"\u00015\u0011\u0015A$\u0001\"\u0001:\u0011\u0015Q%\u0001\"\u0001L\u0011\u001dy\u0006!!A\u0005\u0004\u0001<QaZ\u0007\t\u0002!4Q\u0001D\u0007\t\u0002%DQaM\u0005\u0005\u0002-Da\u0001\\\u0005\u0005\u00025i\'\u0001\u0003+ssN+x-\u0019:\u000b\u00059y\u0011!C:dC2\f7\r^5d\u0015\u0005\u0001\u0012aA8sO\u000e\u00011C\u0001\u0001\u0014!\t!r#D\u0001\u0016\u0015\u00051\u0012!B:dC2\f\u0017B\u0001\r\u0016\u0005\u0019\te.\u001f*fM\u00061A%\u001b8ji\u0012\"\u0012a\u0007\t\u0003)qI!!H\u000b\u0003\tUs\u0017\u000e\u001e\u0002\b)JL\u0018N_3s+\t\u0001#f\u0005\u0002\u0003\'\u00051A\u000f[3Uef\u00042a\t\u0014)\u001b\u0005!#BA\u0013\u0016\u0003\u0011)H/\u001b7\n\u0005\u001d\"#a\u0001+ssB\u0011\u0011F\u000b\u0007\u0001\t\u0015Y#A1\u0001-\u0005\u0005!\u0016CA\u00171!\t!b&\u0003\u00020+\t9aj\u001c;iS:<\u0007C\u0001\u000b2\u0013\t\u0011TCA\u0002B]f\fa\u0001P5oSRtDCA\u001b8!\r1$\u0001K\u0007\u0002\u0001!)\u0011\u0005\u0002a\u0001E\u0005!Ao\\(s+\u0005Q\u0004\u0003B\u001e=Qyj\u0011!D\u0005\u0003{5\u0011!a\u0014:\u0011\u0005}:eB\u0001!F\u001d\t\tE)D\u0001C\u0015\t\u0019\u0015#\u0001\u0004=e>|GOP\u0005\u0002-%\u0011a)F\u0001\ba\u0006\u001c7.Y4f\u0013\tA\u0015JA\u0005UQJ|w/\u00192mK*\u0011a)F\u0001\u000bm\u0006d\u0017\u000eZ1uS:<Gc\u0001\u0012M5\")QJ\u0002a\u0001\u001d\u0006\u0011\u0001\u000e\u001a\t\u0005)=C\u0013+\u0003\u0002Q+\tIa)\u001e8di&|g.\r\t\u0004wI#\u0016BA*\u000e\u0005)1\u0016\r\\5eCRLwN\u001c\t\u0003+^s!a\u000f,\n\u0005\u0019k\u0011B\u0001-Z\u00051)%O]8s\u001b\u0016\u001c8/Y4f\u0015\t1U\u0002C\u0003\\\r\u0001\u0007A,\u0001\u0002uYB\u0019A#\u0018(\n\u0005y+\"A\u0003\u001fsKB,\u0017\r^3e}\u00059AK]=ju\u0016\u0014XCA1e)\t\u0011W\rE\u00027\u0005\r\u0004\"!\u000b3\u0005\u000b-:!\u0019\u0001\u0017\t\u000b\u0005:\u0001\u0019\u00014\u0011\u0007\r23-\u0001\u0005Uef\u001cVoZ1s!\tY\u0014bE\u0002\n\')\u0004\"a\u000f\u0001\u0015\u0003!\fq\u0002]1tg>\u0013h)\u001b:ti\u001a\u000b\u0017\u000e\\\u000b\u0004]Z\fHcA8toB\u00191H\u00159\u0011\u0005%\nH!\u0002:\f\u0005\u0004a#!A#\t\u000bQ\\\u0001\u0019A;\u0002\u0003=\u0004\"!\u000b<\u0005\u000b-Z!\u0019\u0001\u0017\t\u000ba\\\u0001\u0019A=\u0002\u0005\u0019\u001c\bcA {y&\u001110\u0013\u0002\u0005\u0019&\u001cH\u000f\u0005\u0003\u0015\u001fV|\u0007FA\u0006\u007f!\ry\u0018QA\u0007\u0003\u0003\u0003Q1!a\u0001\u0016\u0003)\tgN\\8uCRLwN\\\u0005\u0005\u0003\u000f\t\tAA\u0004uC&d\'/Z2"
    )
  ScalaInlineInfo: length = 0x13 (unknown attribute)
   01 00 00 03 00 1B 00 1C 01 00 0B 00 10 00 00 0C
   00 0D 01
  ScalaSig: length = 0x3 (unknown attribute)
   05 02 00
