Classfile /Users/mw/Projects/slang-braindump/.jar/jar8/assemble/slang-braindump/assemble/content/org/scalactic/TypeCheckedTripleEquals$.class
  Last modified May 29, 2022; size 7444 bytes
  SHA-256 checksum 2eb1ed611fb0c4f0e42b8f8c3dd222fe6d82feebd5ad13a4582b043e77b43b3d
  Compiled from "TypeCheckedTripleEquals.scala"
public final class org.scalactic.TypeCheckedTripleEquals$ implements org.scalactic.TypeCheckedTripleEquals
  minor version: 0
  major version: 52
  flags: (0x0031) ACC_PUBLIC, ACC_FINAL, ACC_SUPER
  this_class: #2                          // org/scalactic/TypeCheckedTripleEquals$
  super_class: #4                         // java/lang/Object
  interfaces: 1, fields: 1, methods: 20, attributes: 4
Constant pool:
    #1 = Utf8               org/scalactic/TypeCheckedTripleEquals$
    #2 = Class              #1            // org/scalactic/TypeCheckedTripleEquals$
    #3 = Utf8               java/lang/Object
    #4 = Class              #3            // java/lang/Object
    #5 = Utf8               org/scalactic/TypeCheckedTripleEquals
    #6 = Class              #5            // org/scalactic/TypeCheckedTripleEquals
    #7 = Utf8               TypeCheckedTripleEquals.scala
    #8 = Utf8               org/scalactic/TripleEqualsSupport$CheckingEqualizer
    #9 = Class              #8            // org/scalactic/TripleEqualsSupport$CheckingEqualizer
   #10 = Utf8               org/scalactic/TripleEqualsSupport
   #11 = Class              #10           // org/scalactic/TripleEqualsSupport
   #12 = Utf8               CheckingEqualizer
   #13 = Utf8               org/scalactic/TripleEqualsSupport$Equalizer
   #14 = Class              #13           // org/scalactic/TripleEqualsSupport$Equalizer
   #15 = Utf8               Equalizer
   #16 = Utf8               org/scalactic/TripleEqualsSupport$Spread
   #17 = Class              #16           // org/scalactic/TripleEqualsSupport$Spread
   #18 = Utf8               Spread
   #19 = Utf8               org/scalactic/TripleEqualsSupport$TripleEqualsInvocation
   #20 = Class              #19           // org/scalactic/TripleEqualsSupport$TripleEqualsInvocation
   #21 = Utf8               TripleEqualsInvocation
   #22 = Utf8               org/scalactic/TripleEqualsSupport$TripleEqualsInvocationOnSpread
   #23 = Class              #22           // org/scalactic/TripleEqualsSupport$TripleEqualsInvocationOnSpread
   #24 = Utf8               TripleEqualsInvocationOnSpread
   #25 = Utf8               MODULE$
   #26 = Utf8               Lorg/scalactic/TypeCheckedTripleEquals$;
   #27 = Utf8               <clinit>
   #28 = Utf8               ()V
   #29 = Utf8               <init>
   #30 = NameAndType        #29:#28       // "<init>":()V
   #31 = Methodref          #2.#30        // org/scalactic/TypeCheckedTripleEquals$."<init>":()V
   #32 = NameAndType        #25:#26       // MODULE$:Lorg/scalactic/TypeCheckedTripleEquals$;
   #33 = Fieldref           #2.#32        // org/scalactic/TypeCheckedTripleEquals$.MODULE$:Lorg/scalactic/TypeCheckedTripleEquals$;
   #34 = Utf8               $init$
   #35 = Utf8               (Lorg/scalactic/TripleEqualsSupport;)V
   #36 = NameAndType        #34:#35       // $init$:(Lorg/scalactic/TripleEqualsSupport;)V
   #37 = InterfaceMethodref #11.#36       // org/scalactic/TripleEqualsSupport.$init$:(Lorg/scalactic/TripleEqualsSupport;)V
   #38 = Utf8               org/scalactic/LowPriorityTypeCheckedConstraint
   #39 = Class              #38           // org/scalactic/LowPriorityTypeCheckedConstraint
   #40 = Utf8               (Lorg/scalactic/LowPriorityTypeCheckedConstraint;)V
   #41 = NameAndType        #34:#40       // $init$:(Lorg/scalactic/LowPriorityTypeCheckedConstraint;)V
   #42 = InterfaceMethodref #39.#41       // org/scalactic/LowPriorityTypeCheckedConstraint.$init$:(Lorg/scalactic/LowPriorityTypeCheckedConstraint;)V
   #43 = Utf8               (Lorg/scalactic/TypeCheckedTripleEquals;)V
   #44 = NameAndType        #34:#43       // $init$:(Lorg/scalactic/TypeCheckedTripleEquals;)V
   #45 = InterfaceMethodref #6.#44        // org/scalactic/TypeCheckedTripleEquals.$init$:(Lorg/scalactic/TypeCheckedTripleEquals;)V
   #46 = Utf8               convertToEqualizer
   #47 = Utf8               (Ljava/lang/Object;)Lorg/scalactic/TripleEqualsSupport$Equalizer;
   #48 = Utf8               <T:Ljava/lang/Object;>(TT;)Lorg/scalactic/TripleEqualsSupport$Equalizer<TT;>;
   #49 = Utf8               left
   #50 = Utf8               convertToEqualizer$
   #51 = Utf8               (Lorg/scalactic/TypeCheckedTripleEquals;Ljava/lang/Object;)Lorg/scalactic/TripleEqualsSupport$Equalizer;
   #52 = NameAndType        #50:#51       // convertToEqualizer$:(Lorg/scalactic/TypeCheckedTripleEquals;Ljava/lang/Object;)Lorg/scalactic/TripleEqualsSupport$Equalizer;
   #53 = InterfaceMethodref #6.#52        // org/scalactic/TypeCheckedTripleEquals.convertToEqualizer$:(Lorg/scalactic/TypeCheckedTripleEquals;Ljava/lang/Object;)Lorg/scalactic/TripleEqualsSupport$Equalizer;
   #54 = Utf8               this
   #55 = Utf8               Ljava/lang/Object;
   #56 = Utf8               convertToCheckingEqualizer
   #57 = Utf8               (Ljava/lang/Object;)Lorg/scalactic/TripleEqualsSupport$CheckingEqualizer;
   #58 = Utf8               <T:Ljava/lang/Object;>(TT;)Lorg/scalactic/TripleEqualsSupport$CheckingEqualizer<TT;>;
   #59 = Utf8               convertToCheckingEqualizer$
   #60 = Utf8               (Lorg/scalactic/TypeCheckedTripleEquals;Ljava/lang/Object;)Lorg/scalactic/TripleEqualsSupport$CheckingEqualizer;
   #61 = NameAndType        #59:#60       // convertToCheckingEqualizer$:(Lorg/scalactic/TypeCheckedTripleEquals;Ljava/lang/Object;)Lorg/scalactic/TripleEqualsSupport$CheckingEqualizer;
   #62 = InterfaceMethodref #6.#61        // org/scalactic/TypeCheckedTripleEquals.convertToCheckingEqualizer$:(Lorg/scalactic/TypeCheckedTripleEquals;Ljava/lang/Object;)Lorg/scalactic/TripleEqualsSupport$CheckingEqualizer;
   #63 = Utf8               unconstrainedEquality
   #64 = Utf8               (Lorg/scalactic/Equality;)Lorg/scalactic/CanEqual;
   #65 = Utf8               <A:Ljava/lang/Object;B:Ljava/lang/Object;>(Lorg/scalactic/Equality<TA;>;)Lorg/scalactic/CanEqual<TA;TB;>;
   #66 = Utf8               equalityOfA
   #67 = Utf8               unconstrainedEquality$
   #68 = Utf8               (Lorg/scalactic/TypeCheckedTripleEquals;Lorg/scalactic/Equality;)Lorg/scalactic/CanEqual;
   #69 = NameAndType        #67:#68       // unconstrainedEquality$:(Lorg/scalactic/TypeCheckedTripleEquals;Lorg/scalactic/Equality;)Lorg/scalactic/CanEqual;
   #70 = InterfaceMethodref #6.#69        // org/scalactic/TypeCheckedTripleEquals.unconstrainedEquality$:(Lorg/scalactic/TypeCheckedTripleEquals;Lorg/scalactic/Equality;)Lorg/scalactic/CanEqual;
   #71 = Utf8               Lorg/scalactic/Equality;
   #72 = Utf8               typeCheckedConstraint
   #73 = Utf8               (Lorg/scalactic/Equivalence;Lscala/$less$colon$less;)Lorg/scalactic/CanEqual;
   #74 = Utf8               <A:Ljava/lang/Object;B:Ljava/lang/Object;>(Lorg/scalactic/Equivalence<TA;>;Lscala/$less$colon$less<TB;TA;>;)Lorg/scalactic/CanEqual<TA;TB;>;
   #75 = Utf8               equivalenceOfA
   #76 = Utf8               ev
   #77 = Utf8               typeCheckedConstraint$
   #78 = Utf8               (Lorg/scalactic/TypeCheckedTripleEquals;Lorg/scalactic/Equivalence;Lscala/$less$colon$less;)Lorg/scalactic/CanEqual;
   #79 = NameAndType        #77:#78       // typeCheckedConstraint$:(Lorg/scalactic/TypeCheckedTripleEquals;Lorg/scalactic/Equivalence;Lscala/$less$colon$less;)Lorg/scalactic/CanEqual;
   #80 = InterfaceMethodref #6.#79        // org/scalactic/TypeCheckedTripleEquals.typeCheckedConstraint$:(Lorg/scalactic/TypeCheckedTripleEquals;Lorg/scalactic/Equivalence;Lscala/$less$colon$less;)Lorg/scalactic/CanEqual;
   #81 = Utf8               Lorg/scalactic/Equivalence;
   #82 = Utf8               Lscala/$less$colon$less;
   #83 = Utf8               convertEquivalenceToBToAConstraint
   #84 = Utf8               convertEquivalenceToBToAConstraint$
   #85 = NameAndType        #84:#78       // convertEquivalenceToBToAConstraint$:(Lorg/scalactic/TypeCheckedTripleEquals;Lorg/scalactic/Equivalence;Lscala/$less$colon$less;)Lorg/scalactic/CanEqual;
   #86 = InterfaceMethodref #6.#85        // org/scalactic/TypeCheckedTripleEquals.convertEquivalenceToBToAConstraint$:(Lorg/scalactic/TypeCheckedTripleEquals;Lorg/scalactic/Equivalence;Lscala/$less$colon$less;)Lorg/scalactic/CanEqual;
   #87 = Utf8               lowPriorityConversionCheckedConstraint
   #88 = Utf8               (Lorg/scalactic/Equivalence;Lscala/Function1;)Lorg/scalactic/CanEqual;
   #89 = Utf8               <A:Ljava/lang/Object;B:Ljava/lang/Object;>(Lorg/scalactic/Equivalence<TB;>;Lscala/Function1<TA;TB;>;)Lorg/scalactic/CanEqual<TA;TB;>;
   #90 = Utf8               equivalenceOfB
   #91 = Utf8               cnv
   #92 = Utf8               lowPriorityConversionCheckedConstraint$
   #93 = Utf8               (Lorg/scalactic/TypeCheckedTripleEquals;Lorg/scalactic/Equivalence;Lscala/Function1;)Lorg/scalactic/CanEqual;
   #94 = NameAndType        #92:#93       // lowPriorityConversionCheckedConstraint$:(Lorg/scalactic/TypeCheckedTripleEquals;Lorg/scalactic/Equivalence;Lscala/Function1;)Lorg/scalactic/CanEqual;
   #95 = InterfaceMethodref #6.#94        // org/scalactic/TypeCheckedTripleEquals.lowPriorityConversionCheckedConstraint$:(Lorg/scalactic/TypeCheckedTripleEquals;Lorg/scalactic/Equivalence;Lscala/Function1;)Lorg/scalactic/CanEqual;
   #96 = Utf8               Lscala/Function1;
   #97 = Utf8               convertEquivalenceToAToBConversionConstraint
   #98 = Utf8               convertEquivalenceToAToBConversionConstraint$
   #99 = NameAndType        #98:#93       // convertEquivalenceToAToBConversionConstraint$:(Lorg/scalactic/TypeCheckedTripleEquals;Lorg/scalactic/Equivalence;Lscala/Function1;)Lorg/scalactic/CanEqual;
  #100 = InterfaceMethodref #6.#99        // org/scalactic/TypeCheckedTripleEquals.convertEquivalenceToAToBConversionConstraint$:(Lorg/scalactic/TypeCheckedTripleEquals;Lorg/scalactic/Equivalence;Lscala/Function1;)Lorg/scalactic/CanEqual;
  #101 = Utf8               conversionCheckedConstraint
  #102 = Utf8               <A:Ljava/lang/Object;B:Ljava/lang/Object;>(Lorg/scalactic/Equivalence<TA;>;Lscala/Function1<TB;TA;>;)Lorg/scalactic/CanEqual<TA;TB;>;
  #103 = Utf8               conversionCheckedConstraint$
  #104 = NameAndType        #103:#93      // conversionCheckedConstraint$:(Lorg/scalactic/TypeCheckedTripleEquals;Lorg/scalactic/Equivalence;Lscala/Function1;)Lorg/scalactic/CanEqual;
  #105 = InterfaceMethodref #6.#104       // org/scalactic/TypeCheckedTripleEquals.conversionCheckedConstraint$:(Lorg/scalactic/TypeCheckedTripleEquals;Lorg/scalactic/Equivalence;Lscala/Function1;)Lorg/scalactic/CanEqual;
  #106 = Utf8               convertEquivalenceToBToAConversionConstraint
  #107 = Utf8               convertEquivalenceToBToAConversionConstraint$
  #108 = NameAndType        #107:#93      // convertEquivalenceToBToAConversionConstraint$:(Lorg/scalactic/TypeCheckedTripleEquals;Lorg/scalactic/Equivalence;Lscala/Function1;)Lorg/scalactic/CanEqual;
  #109 = InterfaceMethodref #6.#108       // org/scalactic/TypeCheckedTripleEquals.convertEquivalenceToBToAConversionConstraint$:(Lorg/scalactic/TypeCheckedTripleEquals;Lorg/scalactic/Equivalence;Lscala/Function1;)Lorg/scalactic/CanEqual;
  #110 = Utf8               lowPriorityTypeCheckedConstraint
  #111 = Utf8               <A:Ljava/lang/Object;B:Ljava/lang/Object;>(Lorg/scalactic/Equivalence<TB;>;Lscala/$less$colon$less<TA;TB;>;)Lorg/scalactic/CanEqual<TA;TB;>;
  #112 = Utf8               lowPriorityTypeCheckedConstraint$
  #113 = Utf8               (Lorg/scalactic/LowPriorityTypeCheckedConstraint;Lorg/scalactic/Equivalence;Lscala/$less$colon$less;)Lorg/scalactic/CanEqual;
  #114 = NameAndType        #112:#113     // lowPriorityTypeCheckedConstraint$:(Lorg/scalactic/LowPriorityTypeCheckedConstraint;Lorg/scalactic/Equivalence;Lscala/$less$colon$less;)Lorg/scalactic/CanEqual;
  #115 = InterfaceMethodref #39.#114      // org/scalactic/LowPriorityTypeCheckedConstraint.lowPriorityTypeCheckedConstraint$:(Lorg/scalactic/LowPriorityTypeCheckedConstraint;Lorg/scalactic/Equivalence;Lscala/$less$colon$less;)Lorg/scalactic/CanEqual;
  #116 = Utf8               convertEquivalenceToAToBConstraint
  #117 = Utf8               convertEquivalenceToAToBConstraint$
  #118 = NameAndType        #117:#113     // convertEquivalenceToAToBConstraint$:(Lorg/scalactic/LowPriorityTypeCheckedConstraint;Lorg/scalactic/Equivalence;Lscala/$less$colon$less;)Lorg/scalactic/CanEqual;
  #119 = InterfaceMethodref #39.#118      // org/scalactic/LowPriorityTypeCheckedConstraint.convertEquivalenceToAToBConstraint$:(Lorg/scalactic/LowPriorityTypeCheckedConstraint;Lorg/scalactic/Equivalence;Lscala/$less$colon$less;)Lorg/scalactic/CanEqual;
  #120 = Utf8               defaultEquality
  #121 = Utf8               ()Lorg/scalactic/Equality;
  #122 = Utf8               <A:Ljava/lang/Object;>()Lorg/scalactic/Equality<TA;>;
  #123 = Utf8               defaultEquality$
  #124 = Utf8               (Lorg/scalactic/TripleEqualsSupport;)Lorg/scalactic/Equality;
  #125 = NameAndType        #123:#124     // defaultEquality$:(Lorg/scalactic/TripleEqualsSupport;)Lorg/scalactic/Equality;
  #126 = InterfaceMethodref #11.#125      // org/scalactic/TripleEqualsSupport.defaultEquality$:(Lorg/scalactic/TripleEqualsSupport;)Lorg/scalactic/Equality;
  #127 = Utf8               $eq$eq$eq
  #128 = Utf8               (Ljava/lang/Object;)Lorg/scalactic/TripleEqualsSupport$TripleEqualsInvocation;
  #129 = Utf8               <T:Ljava/lang/Object;>(TT;)Lorg/scalactic/TripleEqualsSupport$TripleEqualsInvocation<TT;>;
  #130 = Utf8               right
  #131 = Utf8               $eq$eq$eq$
  #132 = Utf8               (Lorg/scalactic/TripleEqualsSupport;Ljava/lang/Object;)Lorg/scalactic/TripleEqualsSupport$TripleEqualsInvocation;
  #133 = NameAndType        #131:#132     // $eq$eq$eq$:(Lorg/scalactic/TripleEqualsSupport;Ljava/lang/Object;)Lorg/scalactic/TripleEqualsSupport$TripleEqualsInvocation;
  #134 = InterfaceMethodref #11.#133      // org/scalactic/TripleEqualsSupport.$eq$eq$eq$:(Lorg/scalactic/TripleEqualsSupport;Ljava/lang/Object;)Lorg/scalactic/TripleEqualsSupport$TripleEqualsInvocation;
  #135 = Utf8               $bang$eq$eq
  #136 = Utf8               $bang$eq$eq$
  #137 = NameAndType        #136:#132     // $bang$eq$eq$:(Lorg/scalactic/TripleEqualsSupport;Ljava/lang/Object;)Lorg/scalactic/TripleEqualsSupport$TripleEqualsInvocation;
  #138 = InterfaceMethodref #11.#137      // org/scalactic/TripleEqualsSupport.$bang$eq$eq$:(Lorg/scalactic/TripleEqualsSupport;Ljava/lang/Object;)Lorg/scalactic/TripleEqualsSupport$TripleEqualsInvocation;
  #139 = Utf8               (Lscala/runtime/Null$;)Lorg/scalactic/TripleEqualsSupport$TripleEqualsInvocation;
  #140 = Utf8               (Lscala/runtime/Null$;)Lorg/scalactic/TripleEqualsSupport$TripleEqualsInvocation<Lscala/runtime/Null$;>;
  #141 = Utf8               (Lorg/scalactic/TripleEqualsSupport;Lscala/runtime/Null$;)Lorg/scalactic/TripleEqualsSupport$TripleEqualsInvocation;
  #142 = NameAndType        #131:#141     // $eq$eq$eq$:(Lorg/scalactic/TripleEqualsSupport;Lscala/runtime/Null$;)Lorg/scalactic/TripleEqualsSupport$TripleEqualsInvocation;
  #143 = InterfaceMethodref #11.#142      // org/scalactic/TripleEqualsSupport.$eq$eq$eq$:(Lorg/scalactic/TripleEqualsSupport;Lscala/runtime/Null$;)Lorg/scalactic/TripleEqualsSupport$TripleEqualsInvocation;
  #144 = Utf8               Lscala/runtime/Null$;
  #145 = NameAndType        #136:#141     // $bang$eq$eq$:(Lorg/scalactic/TripleEqualsSupport;Lscala/runtime/Null$;)Lorg/scalactic/TripleEqualsSupport$TripleEqualsInvocation;
  #146 = InterfaceMethodref #11.#145      // org/scalactic/TripleEqualsSupport.$bang$eq$eq$:(Lorg/scalactic/TripleEqualsSupport;Lscala/runtime/Null$;)Lorg/scalactic/TripleEqualsSupport$TripleEqualsInvocation;
  #147 = Utf8               (Lorg/scalactic/TripleEqualsSupport$Spread;)Lorg/scalactic/TripleEqualsSupport$TripleEqualsInvocationOnSpread;
  #148 = Utf8               <T:Ljava/lang/Object;>(Lorg/scalactic/TripleEqualsSupport$Spread<TT;>;)Lorg/scalactic/TripleEqualsSupport$TripleEqualsInvocationOnSpread<TT;>;
  #149 = Utf8               (Lorg/scalactic/TripleEqualsSupport;Lorg/scalactic/TripleEqualsSupport$Spread;)Lorg/scalactic/TripleEqualsSupport$TripleEqualsInvocationOnSpread;
  #150 = NameAndType        #131:#149     // $eq$eq$eq$:(Lorg/scalactic/TripleEqualsSupport;Lorg/scalactic/TripleEqualsSupport$Spread;)Lorg/scalactic/TripleEqualsSupport$TripleEqualsInvocationOnSpread;
  #151 = InterfaceMethodref #11.#150      // org/scalactic/TripleEqualsSupport.$eq$eq$eq$:(Lorg/scalactic/TripleEqualsSupport;Lorg/scalactic/TripleEqualsSupport$Spread;)Lorg/scalactic/TripleEqualsSupport$TripleEqualsInvocationOnSpread;
  #152 = Utf8               Lorg/scalactic/TripleEqualsSupport$Spread;
  #153 = NameAndType        #136:#149     // $bang$eq$eq$:(Lorg/scalactic/TripleEqualsSupport;Lorg/scalactic/TripleEqualsSupport$Spread;)Lorg/scalactic/TripleEqualsSupport$TripleEqualsInvocationOnSpread;
  #154 = InterfaceMethodref #11.#153      // org/scalactic/TripleEqualsSupport.$bang$eq$eq$:(Lorg/scalactic/TripleEqualsSupport;Lorg/scalactic/TripleEqualsSupport$Spread;)Lorg/scalactic/TripleEqualsSupport$TripleEqualsInvocationOnSpread;
  #155 = Methodref          #4.#30        // java/lang/Object."<init>":()V
  #156 = Utf8               Code
  #157 = Utf8               LineNumberTable
  #158 = Utf8               LocalVariableTable
  #159 = Utf8               Signature
  #160 = Utf8               MethodParameters
  #161 = Utf8               Deprecated
  #162 = Utf8               InnerClasses
  #163 = Utf8               SourceFile
  #164 = Utf8               ScalaInlineInfo
  #165 = Utf8               Scala
{
  public static final org.scalactic.TypeCheckedTripleEquals$ MODULE$;
    descriptor: Lorg/scalactic/TypeCheckedTripleEquals$;
    flags: (0x0019) ACC_PUBLIC, ACC_STATIC, ACC_FINAL

  public static {};
    descriptor: ()V
    flags: (0x0009) ACC_PUBLIC, ACC_STATIC
    Code:
      stack=2, locals=0, args_size=0
         0: new           #2                  // class org/scalactic/TypeCheckedTripleEquals$
         3: dup
         4: invokespecial #31                 // Method "<init>":()V
         7: putstatic     #33                 // Field MODULE$:Lorg/scalactic/TypeCheckedTripleEquals$;
        10: getstatic     #33                 // Field MODULE$:Lorg/scalactic/TypeCheckedTripleEquals$;
        13: invokestatic  #37                 // InterfaceMethod org/scalactic/TripleEqualsSupport.$init$:(Lorg/scalactic/TripleEqualsSupport;)V
        16: getstatic     #33                 // Field MODULE$:Lorg/scalactic/TypeCheckedTripleEquals$;
        19: invokestatic  #42                 // InterfaceMethod org/scalactic/LowPriorityTypeCheckedConstraint.$init$:(Lorg/scalactic/LowPriorityTypeCheckedConstraint;)V
        22: getstatic     #33                 // Field MODULE$:Lorg/scalactic/TypeCheckedTripleEquals$;
        25: invokestatic  #45                 // InterfaceMethod org/scalactic/TypeCheckedTripleEquals.$init$:(Lorg/scalactic/TypeCheckedTripleEquals;)V
        28: return
      LineNumberTable:
        line 339: 0

  public <T extends java.lang.Object> org.scalactic.TripleEqualsSupport$Equalizer<T> convertToEqualizer(T);
    descriptor: (Ljava/lang/Object;)Lorg/scalactic/TripleEqualsSupport$Equalizer;
    flags: (0x0001) ACC_PUBLIC
    Code:
      stack=2, locals=2, args_size=2
         0: aload_0
         1: aload_1
         2: invokestatic  #53                 // InterfaceMethod org/scalactic/TypeCheckedTripleEquals.convertToEqualizer$:(Lorg/scalactic/TypeCheckedTripleEquals;Ljava/lang/Object;)Lorg/scalactic/TripleEqualsSupport$Equalizer;
         5: areturn
      LineNumberTable:
        line 339: 0
      LocalVariableTable:
        Start  Length  Slot  Name   Signature
            0       6     0  this   Lorg/scalactic/TypeCheckedTripleEquals$;
            0       6     1  left   Ljava/lang/Object;
    Signature: #48                          // <T:Ljava/lang/Object;>(TT;)Lorg/scalactic/TripleEqualsSupport$Equalizer<TT;>;
    MethodParameters:
      Name                           Flags
      left                           final

  public <T extends java.lang.Object> org.scalactic.TripleEqualsSupport$CheckingEqualizer<T> convertToCheckingEqualizer(T);
    descriptor: (Ljava/lang/Object;)Lorg/scalactic/TripleEqualsSupport$CheckingEqualizer;
    flags: (0x0001) ACC_PUBLIC
    Code:
      stack=2, locals=2, args_size=2
         0: aload_0
         1: aload_1
         2: invokestatic  #62                 // InterfaceMethod org/scalactic/TypeCheckedTripleEquals.convertToCheckingEqualizer$:(Lorg/scalactic/TypeCheckedTripleEquals;Ljava/lang/Object;)Lorg/scalactic/TripleEqualsSupport$CheckingEqualizer;
         5: areturn
      LineNumberTable:
        line 339: 0
      LocalVariableTable:
        Start  Length  Slot  Name   Signature
            0       6     0  this   Lorg/scalactic/TypeCheckedTripleEquals$;
            0       6     1  left   Ljava/lang/Object;
    Signature: #58                          // <T:Ljava/lang/Object;>(TT;)Lorg/scalactic/TripleEqualsSupport$CheckingEqualizer<TT;>;
    MethodParameters:
      Name                           Flags
      left                           final

  public <A extends java.lang.Object, B extends java.lang.Object> org.scalactic.CanEqual<A, B> unconstrainedEquality(org.scalactic.Equality<A>);
    descriptor: (Lorg/scalactic/Equality;)Lorg/scalactic/CanEqual;
    flags: (0x0001) ACC_PUBLIC
    Code:
      stack=2, locals=2, args_size=2
         0: aload_0
         1: aload_1
         2: invokestatic  #70                 // InterfaceMethod org/scalactic/TypeCheckedTripleEquals.unconstrainedEquality$:(Lorg/scalactic/TypeCheckedTripleEquals;Lorg/scalactic/Equality;)Lorg/scalactic/CanEqual;
         5: areturn
      LineNumberTable:
        line 339: 0
      LocalVariableTable:
        Start  Length  Slot  Name   Signature
            0       6     0  this   Lorg/scalactic/TypeCheckedTripleEquals$;
            0       6     1 equalityOfA   Lorg/scalactic/Equality;
    Signature: #65                          // <A:Ljava/lang/Object;B:Ljava/lang/Object;>(Lorg/scalactic/Equality<TA;>;)Lorg/scalactic/CanEqual<TA;TB;>;
    MethodParameters:
      Name                           Flags
      equalityOfA                    final

  public <A extends java.lang.Object, B extends java.lang.Object> org.scalactic.CanEqual<A, B> typeCheckedConstraint(org.scalactic.Equivalence<A>, scala.$less$colon$less<B, A>);
    descriptor: (Lorg/scalactic/Equivalence;Lscala/$less$colon$less;)Lorg/scalactic/CanEqual;
    flags: (0x0001) ACC_PUBLIC
    Code:
      stack=3, locals=3, args_size=3
         0: aload_0
         1: aload_1
         2: aload_2
         3: invokestatic  #80                 // InterfaceMethod org/scalactic/TypeCheckedTripleEquals.typeCheckedConstraint$:(Lorg/scalactic/TypeCheckedTripleEquals;Lorg/scalactic/Equivalence;Lscala/$less$colon$less;)Lorg/scalactic/CanEqual;
         6: areturn
      LineNumberTable:
        line 339: 0
      LocalVariableTable:
        Start  Length  Slot  Name   Signature
            0       7     0  this   Lorg/scalactic/TypeCheckedTripleEquals$;
            0       7     1 equivalenceOfA   Lorg/scalactic/Equivalence;
            0       7     2    ev   Lscala/$less$colon$less;
    Signature: #74                          // <A:Ljava/lang/Object;B:Ljava/lang/Object;>(Lorg/scalactic/Equivalence<TA;>;Lscala/$less$colon$less<TB;TA;>;)Lorg/scalactic/CanEqual<TA;TB;>;
    MethodParameters:
      Name                           Flags
      equivalenceOfA                 final
      ev                             final

  public <A extends java.lang.Object, B extends java.lang.Object> org.scalactic.CanEqual<A, B> convertEquivalenceToBToAConstraint(org.scalactic.Equivalence<A>, scala.$less$colon$less<B, A>);
    descriptor: (Lorg/scalactic/Equivalence;Lscala/$less$colon$less;)Lorg/scalactic/CanEqual;
    flags: (0x0001) ACC_PUBLIC
    Code:
      stack=3, locals=3, args_size=3
         0: aload_0
         1: aload_1
         2: aload_2
         3: invokestatic  #86                 // InterfaceMethod org/scalactic/TypeCheckedTripleEquals.convertEquivalenceToBToAConstraint$:(Lorg/scalactic/TypeCheckedTripleEquals;Lorg/scalactic/Equivalence;Lscala/$less$colon$less;)Lorg/scalactic/CanEqual;
         6: areturn
      LineNumberTable:
        line 339: 0
      LocalVariableTable:
        Start  Length  Slot  Name   Signature
            0       7     0  this   Lorg/scalactic/TypeCheckedTripleEquals$;
            0       7     1 equivalenceOfA   Lorg/scalactic/Equivalence;
            0       7     2    ev   Lscala/$less$colon$less;
    Signature: #74                          // <A:Ljava/lang/Object;B:Ljava/lang/Object;>(Lorg/scalactic/Equivalence<TA;>;Lscala/$less$colon$less<TB;TA;>;)Lorg/scalactic/CanEqual<TA;TB;>;
    MethodParameters:
      Name                           Flags
      equivalenceOfA                 final
      ev                             final

  public <A extends java.lang.Object, B extends java.lang.Object> org.scalactic.CanEqual<A, B> lowPriorityConversionCheckedConstraint(org.scalactic.Equivalence<B>, scala.Function1<A, B>);
    descriptor: (Lorg/scalactic/Equivalence;Lscala/Function1;)Lorg/scalactic/CanEqual;
    flags: (0x0001) ACC_PUBLIC
    Code:
      stack=3, locals=3, args_size=3
         0: aload_0
         1: aload_1
         2: aload_2
         3: invokestatic  #95                 // InterfaceMethod org/scalactic/TypeCheckedTripleEquals.lowPriorityConversionCheckedConstraint$:(Lorg/scalactic/TypeCheckedTripleEquals;Lorg/scalactic/Equivalence;Lscala/Function1;)Lorg/scalactic/CanEqual;
         6: areturn
      LineNumberTable:
        line 339: 0
      LocalVariableTable:
        Start  Length  Slot  Name   Signature
            0       7     0  this   Lorg/scalactic/TypeCheckedTripleEquals$;
            0       7     1 equivalenceOfB   Lorg/scalactic/Equivalence;
            0       7     2   cnv   Lscala/Function1;
    Signature: #89                          // <A:Ljava/lang/Object;B:Ljava/lang/Object;>(Lorg/scalactic/Equivalence<TB;>;Lscala/Function1<TA;TB;>;)Lorg/scalactic/CanEqual<TA;TB;>;
    Deprecated: true
    MethodParameters:
      Name                           Flags
      equivalenceOfB                 final
      cnv                            final

  public <A extends java.lang.Object, B extends java.lang.Object> org.scalactic.CanEqual<A, B> convertEquivalenceToAToBConversionConstraint(org.scalactic.Equivalence<B>, scala.Function1<A, B>);
    descriptor: (Lorg/scalactic/Equivalence;Lscala/Function1;)Lorg/scalactic/CanEqual;
    flags: (0x0001) ACC_PUBLIC
    Code:
      stack=3, locals=3, args_size=3
         0: aload_0
         1: aload_1
         2: aload_2
         3: invokestatic  #100                // InterfaceMethod org/scalactic/TypeCheckedTripleEquals.convertEquivalenceToAToBConversionConstraint$:(Lorg/scalactic/TypeCheckedTripleEquals;Lorg/scalactic/Equivalence;Lscala/Function1;)Lorg/scalactic/CanEqual;
         6: areturn
      LineNumberTable:
        line 339: 0
      LocalVariableTable:
        Start  Length  Slot  Name   Signature
            0       7     0  this   Lorg/scalactic/TypeCheckedTripleEquals$;
            0       7     1 equivalenceOfB   Lorg/scalactic/Equivalence;
            0       7     2    ev   Lscala/Function1;
    Signature: #89                          // <A:Ljava/lang/Object;B:Ljava/lang/Object;>(Lorg/scalactic/Equivalence<TB;>;Lscala/Function1<TA;TB;>;)Lorg/scalactic/CanEqual<TA;TB;>;
    Deprecated: true
    MethodParameters:
      Name                           Flags
      equivalenceOfB                 final
      ev                             final

  public <A extends java.lang.Object, B extends java.lang.Object> org.scalactic.CanEqual<A, B> conversionCheckedConstraint(org.scalactic.Equivalence<A>, scala.Function1<B, A>);
    descriptor: (Lorg/scalactic/Equivalence;Lscala/Function1;)Lorg/scalactic/CanEqual;
    flags: (0x0001) ACC_PUBLIC
    Code:
      stack=3, locals=3, args_size=3
         0: aload_0
         1: aload_1
         2: aload_2
         3: invokestatic  #105                // InterfaceMethod org/scalactic/TypeCheckedTripleEquals.conversionCheckedConstraint$:(Lorg/scalactic/TypeCheckedTripleEquals;Lorg/scalactic/Equivalence;Lscala/Function1;)Lorg/scalactic/CanEqual;
         6: areturn
      LineNumberTable:
        line 339: 0
      LocalVariableTable:
        Start  Length  Slot  Name   Signature
            0       7     0  this   Lorg/scalactic/TypeCheckedTripleEquals$;
            0       7     1 equivalenceOfA   Lorg/scalactic/Equivalence;
            0       7     2   cnv   Lscala/Function1;
    Signature: #102                         // <A:Ljava/lang/Object;B:Ljava/lang/Object;>(Lorg/scalactic/Equivalence<TA;>;Lscala/Function1<TB;TA;>;)Lorg/scalactic/CanEqual<TA;TB;>;
    Deprecated: true
    MethodParameters:
      Name                           Flags
      equivalenceOfA                 final
      cnv                            final

  public <A extends java.lang.Object, B extends java.lang.Object> org.scalactic.CanEqual<A, B> convertEquivalenceToBToAConversionConstraint(org.scalactic.Equivalence<A>, scala.Function1<B, A>);
    descriptor: (Lorg/scalactic/Equivalence;Lscala/Function1;)Lorg/scalactic/CanEqual;
    flags: (0x0001) ACC_PUBLIC
    Code:
      stack=3, locals=3, args_size=3
         0: aload_0
         1: aload_1
         2: aload_2
         3: invokestatic  #109                // InterfaceMethod org/scalactic/TypeCheckedTripleEquals.convertEquivalenceToBToAConversionConstraint$:(Lorg/scalactic/TypeCheckedTripleEquals;Lorg/scalactic/Equivalence;Lscala/Function1;)Lorg/scalactic/CanEqual;
         6: areturn
      LineNumberTable:
        line 339: 0
      LocalVariableTable:
        Start  Length  Slot  Name   Signature
            0       7     0  this   Lorg/scalactic/TypeCheckedTripleEquals$;
            0       7     1 equivalenceOfA   Lorg/scalactic/Equivalence;
            0       7     2    ev   Lscala/Function1;
    Signature: #102                         // <A:Ljava/lang/Object;B:Ljava/lang/Object;>(Lorg/scalactic/Equivalence<TA;>;Lscala/Function1<TB;TA;>;)Lorg/scalactic/CanEqual<TA;TB;>;
    Deprecated: true
    MethodParameters:
      Name                           Flags
      equivalenceOfA                 final
      ev                             final

  public <A extends java.lang.Object, B extends java.lang.Object> org.scalactic.CanEqual<A, B> lowPriorityTypeCheckedConstraint(org.scalactic.Equivalence<B>, scala.$less$colon$less<A, B>);
    descriptor: (Lorg/scalactic/Equivalence;Lscala/$less$colon$less;)Lorg/scalactic/CanEqual;
    flags: (0x0001) ACC_PUBLIC
    Code:
      stack=3, locals=3, args_size=3
         0: aload_0
         1: aload_1
         2: aload_2
         3: invokestatic  #115                // InterfaceMethod org/scalactic/LowPriorityTypeCheckedConstraint.lowPriorityTypeCheckedConstraint$:(Lorg/scalactic/LowPriorityTypeCheckedConstraint;Lorg/scalactic/Equivalence;Lscala/$less$colon$less;)Lorg/scalactic/CanEqual;
         6: areturn
      LineNumberTable:
        line 339: 0
      LocalVariableTable:
        Start  Length  Slot  Name   Signature
            0       7     0  this   Lorg/scalactic/TypeCheckedTripleEquals$;
            0       7     1 equivalenceOfB   Lorg/scalactic/Equivalence;
            0       7     2    ev   Lscala/$less$colon$less;
    Signature: #111                         // <A:Ljava/lang/Object;B:Ljava/lang/Object;>(Lorg/scalactic/Equivalence<TB;>;Lscala/$less$colon$less<TA;TB;>;)Lorg/scalactic/CanEqual<TA;TB;>;
    MethodParameters:
      Name                           Flags
      equivalenceOfB                 final
      ev                             final

  public <A extends java.lang.Object, B extends java.lang.Object> org.scalactic.CanEqual<A, B> convertEquivalenceToAToBConstraint(org.scalactic.Equivalence<B>, scala.$less$colon$less<A, B>);
    descriptor: (Lorg/scalactic/Equivalence;Lscala/$less$colon$less;)Lorg/scalactic/CanEqual;
    flags: (0x0001) ACC_PUBLIC
    Code:
      stack=3, locals=3, args_size=3
         0: aload_0
         1: aload_1
         2: aload_2
         3: invokestatic  #119                // InterfaceMethod org/scalactic/LowPriorityTypeCheckedConstraint.convertEquivalenceToAToBConstraint$:(Lorg/scalactic/LowPriorityTypeCheckedConstraint;Lorg/scalactic/Equivalence;Lscala/$less$colon$less;)Lorg/scalactic/CanEqual;
         6: areturn
      LineNumberTable:
        line 339: 0
      LocalVariableTable:
        Start  Length  Slot  Name   Signature
            0       7     0  this   Lorg/scalactic/TypeCheckedTripleEquals$;
            0       7     1 equivalenceOfB   Lorg/scalactic/Equivalence;
            0       7     2    ev   Lscala/$less$colon$less;
    Signature: #111                         // <A:Ljava/lang/Object;B:Ljava/lang/Object;>(Lorg/scalactic/Equivalence<TB;>;Lscala/$less$colon$less<TA;TB;>;)Lorg/scalactic/CanEqual<TA;TB;>;
    MethodParameters:
      Name                           Flags
      equivalenceOfB                 final
      ev                             final

  public <A extends java.lang.Object> org.scalactic.Equality<A> defaultEquality();
    descriptor: ()Lorg/scalactic/Equality;
    flags: (0x0001) ACC_PUBLIC
    Code:
      stack=1, locals=1, args_size=1
         0: aload_0
         1: invokestatic  #126                // InterfaceMethod org/scalactic/TripleEqualsSupport.defaultEquality$:(Lorg/scalactic/TripleEqualsSupport;)Lorg/scalactic/Equality;
         4: areturn
      LineNumberTable:
        line 339: 0
      LocalVariableTable:
        Start  Length  Slot  Name   Signature
            0       5     0  this   Lorg/scalactic/TypeCheckedTripleEquals$;
    Signature: #122                         // <A:Ljava/lang/Object;>()Lorg/scalactic/Equality<TA;>;

  public <T extends java.lang.Object> org.scalactic.TripleEqualsSupport$TripleEqualsInvocation<T> $eq$eq$eq(T);
    descriptor: (Ljava/lang/Object;)Lorg/scalactic/TripleEqualsSupport$TripleEqualsInvocation;
    flags: (0x0001) ACC_PUBLIC
    Code:
      stack=2, locals=2, args_size=2
         0: aload_0
         1: aload_1
         2: invokestatic  #134                // InterfaceMethod org/scalactic/TripleEqualsSupport.$eq$eq$eq$:(Lorg/scalactic/TripleEqualsSupport;Ljava/lang/Object;)Lorg/scalactic/TripleEqualsSupport$TripleEqualsInvocation;
         5: areturn
      LineNumberTable:
        line 339: 0
      LocalVariableTable:
        Start  Length  Slot  Name   Signature
            0       6     0  this   Lorg/scalactic/TypeCheckedTripleEquals$;
            0       6     1 right   Ljava/lang/Object;
    Signature: #129                         // <T:Ljava/lang/Object;>(TT;)Lorg/scalactic/TripleEqualsSupport$TripleEqualsInvocation<TT;>;
    MethodParameters:
      Name                           Flags
      right                          final

  public <T extends java.lang.Object> org.scalactic.TripleEqualsSupport$TripleEqualsInvocation<T> $bang$eq$eq(T);
    descriptor: (Ljava/lang/Object;)Lorg/scalactic/TripleEqualsSupport$TripleEqualsInvocation;
    flags: (0x0001) ACC_PUBLIC
    Code:
      stack=2, locals=2, args_size=2
         0: aload_0
         1: aload_1
         2: invokestatic  #138                // InterfaceMethod org/scalactic/TripleEqualsSupport.$bang$eq$eq$:(Lorg/scalactic/TripleEqualsSupport;Ljava/lang/Object;)Lorg/scalactic/TripleEqualsSupport$TripleEqualsInvocation;
         5: areturn
      LineNumberTable:
        line 339: 0
      LocalVariableTable:
        Start  Length  Slot  Name   Signature
            0       6     0  this   Lorg/scalactic/TypeCheckedTripleEquals$;
            0       6     1 right   Ljava/lang/Object;
    Signature: #129                         // <T:Ljava/lang/Object;>(TT;)Lorg/scalactic/TripleEqualsSupport$TripleEqualsInvocation<TT;>;
    MethodParameters:
      Name                           Flags
      right                          final

  public org.scalactic.TripleEqualsSupport$TripleEqualsInvocation<scala.runtime.Null$> $eq$eq$eq(scala.runtime.Null$);
    descriptor: (Lscala/runtime/Null$;)Lorg/scalactic/TripleEqualsSupport$TripleEqualsInvocation;
    flags: (0x0001) ACC_PUBLIC
    Code:
      stack=2, locals=2, args_size=2
         0: aload_0
         1: aload_1
         2: invokestatic  #143                // InterfaceMethod org/scalactic/TripleEqualsSupport.$eq$eq$eq$:(Lorg/scalactic/TripleEqualsSupport;Lscala/runtime/Null$;)Lorg/scalactic/TripleEqualsSupport$TripleEqualsInvocation;
         5: areturn
      LineNumberTable:
        line 339: 0
      LocalVariableTable:
        Start  Length  Slot  Name   Signature
            0       6     0  this   Lorg/scalactic/TypeCheckedTripleEquals$;
            0       6     1 right   Lscala/runtime/Null$;
    Signature: #140                         // (Lscala/runtime/Null$;)Lorg/scalactic/TripleEqualsSupport$TripleEqualsInvocation<Lscala/runtime/Null$;>;
    MethodParameters:
      Name                           Flags
      right                          final

  public org.scalactic.TripleEqualsSupport$TripleEqualsInvocation<scala.runtime.Null$> $bang$eq$eq(scala.runtime.Null$);
    descriptor: (Lscala/runtime/Null$;)Lorg/scalactic/TripleEqualsSupport$TripleEqualsInvocation;
    flags: (0x0001) ACC_PUBLIC
    Code:
      stack=2, locals=2, args_size=2
         0: aload_0
         1: aload_1
         2: invokestatic  #146                // InterfaceMethod org/scalactic/TripleEqualsSupport.$bang$eq$eq$:(Lorg/scalactic/TripleEqualsSupport;Lscala/runtime/Null$;)Lorg/scalactic/TripleEqualsSupport$TripleEqualsInvocation;
         5: areturn
      LineNumberTable:
        line 339: 0
      LocalVariableTable:
        Start  Length  Slot  Name   Signature
            0       6     0  this   Lorg/scalactic/TypeCheckedTripleEquals$;
            0       6     1 right   Lscala/runtime/Null$;
    Signature: #140                         // (Lscala/runtime/Null$;)Lorg/scalactic/TripleEqualsSupport$TripleEqualsInvocation<Lscala/runtime/Null$;>;
    MethodParameters:
      Name                           Flags
      right                          final

  public <T extends java.lang.Object> org.scalactic.TripleEqualsSupport$TripleEqualsInvocationOnSpread<T> $eq$eq$eq(org.scalactic.TripleEqualsSupport$Spread<T>);
    descriptor: (Lorg/scalactic/TripleEqualsSupport$Spread;)Lorg/scalactic/TripleEqualsSupport$TripleEqualsInvocationOnSpread;
    flags: (0x0001) ACC_PUBLIC
    Code:
      stack=2, locals=2, args_size=2
         0: aload_0
         1: aload_1
         2: invokestatic  #151                // InterfaceMethod org/scalactic/TripleEqualsSupport.$eq$eq$eq$:(Lorg/scalactic/TripleEqualsSupport;Lorg/scalactic/TripleEqualsSupport$Spread;)Lorg/scalactic/TripleEqualsSupport$TripleEqualsInvocationOnSpread;
         5: areturn
      LineNumberTable:
        line 339: 0
      LocalVariableTable:
        Start  Length  Slot  Name   Signature
            0       6     0  this   Lorg/scalactic/TypeCheckedTripleEquals$;
            0       6     1 right   Lorg/scalactic/TripleEqualsSupport$Spread;
    Signature: #148                         // <T:Ljava/lang/Object;>(Lorg/scalactic/TripleEqualsSupport$Spread<TT;>;)Lorg/scalactic/TripleEqualsSupport$TripleEqualsInvocationOnSpread<TT;>;
    MethodParameters:
      Name                           Flags
      right                          final

  public <T extends java.lang.Object> org.scalactic.TripleEqualsSupport$TripleEqualsInvocationOnSpread<T> $bang$eq$eq(org.scalactic.TripleEqualsSupport$Spread<T>);
    descriptor: (Lorg/scalactic/TripleEqualsSupport$Spread;)Lorg/scalactic/TripleEqualsSupport$TripleEqualsInvocationOnSpread;
    flags: (0x0001) ACC_PUBLIC
    Code:
      stack=2, locals=2, args_size=2
         0: aload_0
         1: aload_1
         2: invokestatic  #154                // InterfaceMethod org/scalactic/TripleEqualsSupport.$bang$eq$eq$:(Lorg/scalactic/TripleEqualsSupport;Lorg/scalactic/TripleEqualsSupport$Spread;)Lorg/scalactic/TripleEqualsSupport$TripleEqualsInvocationOnSpread;
         5: areturn
      LineNumberTable:
        line 339: 0
      LocalVariableTable:
        Start  Length  Slot  Name   Signature
            0       6     0  this   Lorg/scalactic/TypeCheckedTripleEquals$;
            0       6     1 right   Lorg/scalactic/TripleEqualsSupport$Spread;
    Signature: #148                         // <T:Ljava/lang/Object;>(Lorg/scalactic/TripleEqualsSupport$Spread<TT;>;)Lorg/scalactic/TripleEqualsSupport$TripleEqualsInvocationOnSpread<TT;>;
    MethodParameters:
      Name                           Flags
      right                          final

  private org.scalactic.TypeCheckedTripleEquals$();
    descriptor: ()V
    flags: (0x0002) ACC_PRIVATE
    Code:
      stack=1, locals=1, args_size=1
         0: aload_0
         1: invokespecial #155                // Method java/lang/Object."<init>":()V
         4: return
      LineNumberTable:
        line 339: 0
      LocalVariableTable:
        Start  Length  Slot  Name   Signature
            0       5     0  this   Lorg/scalactic/TypeCheckedTripleEquals$;
}
InnerClasses:
  public #12= #9 of #11;                  // CheckingEqualizer=class org/scalactic/TripleEqualsSupport$CheckingEqualizer of class org/scalactic/TripleEqualsSupport
  public #15= #14 of #11;                 // Equalizer=class org/scalactic/TripleEqualsSupport$Equalizer of class org/scalactic/TripleEqualsSupport
  public static final #18= #17 of #11;    // Spread=class org/scalactic/TripleEqualsSupport$Spread of class org/scalactic/TripleEqualsSupport
  public static final #21= #20 of #11;    // TripleEqualsInvocation=class org/scalactic/TripleEqualsSupport$TripleEqualsInvocation of class org/scalactic/TripleEqualsSupport
  public static final #24= #23 of #11;    // TripleEqualsInvocationOnSpread=class org/scalactic/TripleEqualsSupport$TripleEqualsInvocationOnSpread of class org/scalactic/TripleEqualsSupport
SourceFile: "TypeCheckedTripleEquals.scala"
  ScalaInlineInfo: length = 0x63 (unknown attribute)
   01 01 00 13 00 87 00 80 01 00 87 00 93 01 00 87
   00 8B 01 00 7F 00 80 01 00 7F 00 93 01 00 7F 00
   8B 01 00 1D 00 1C 01 00 65 00 58 01 00 74 00 49
   01 00 61 00 58 01 00 53 00 49 01 00 6A 00 58 01
   00 38 00 39 01 00 2E 00 2F 01 00 78 00 79 01 00
   57 00 58 01 00 6E 00 49 01 00 48 00 49 01 00 3F
   00 40 01
  Scala: length = 0x0 (unknown attribute)

