Classfile /Users/mw/Projects/slang-braindump/.jar/jar8/assemble/slang-braindump/assemble/content/org/scalatest/verbs/ResultOfTaggedAsInvocation.class
  Last modified May 29, 2022; size 1951 bytes
  SHA-256 checksum 6a31b272a08366283a9bd5836dca317a7c95a8848dc9fa2da200f2c425a0536c
  Compiled from "ResultOfTaggedAsInvocation.scala"
public abstract class org.scalatest.verbs.ResultOfTaggedAsInvocation
  minor version: 0
  major version: 52
  flags: (0x0421) ACC_PUBLIC, ACC_SUPER, ACC_ABSTRACT
  this_class: #2                          // org/scalatest/verbs/ResultOfTaggedAsInvocation
  super_class: #4                         // java/lang/Object
  interfaces: 0, fields: 3, methods: 5, attributes: 4
Constant pool:
   #1 = Utf8               org/scalatest/verbs/ResultOfTaggedAsInvocation
   #2 = Class              #1             // org/scalatest/verbs/ResultOfTaggedAsInvocation
   #3 = Utf8               java/lang/Object
   #4 = Class              #3             // java/lang/Object
   #5 = Utf8               ResultOfTaggedAsInvocation.scala
   #6 = Utf8               Lscala/reflect/ScalaSignature;
   #7 = Utf8               bytes
   #8 = Utf8               \u0006\u000513Q!\u0003\u0006\u0002\u0002EA\u0001\u0002\u0007\u0001\u0003\u0006\u0004%\t!\u0007\u0005\tK\u0001\u0011\t\u0011)A\u00055!Aa\u0005\u0001BC\u0002\u0013\u0005\u0011\u0004\u0003\u0005(\u0001\t\u0005\t\u0015!\u0003\u001b\u0011!A\u0003A!b\u0001\n\u0003I\u0003\u0002C\u001c\u0001\u0005\u0003\u0005\u000b\u0011\u0002\u0016\t\u000ba\u0002A\u0011A\u001d\t\u000b}\u0002a\u0011\u0001!\u00035I+7/\u001e7u\u001f\u001a$\u0016mZ4fI\u0006\u001b\u0018J\u001c<pG\u0006$\u0018n\u001c8\u000b\u0005-a\u0011!\u0002<fe\n\u001c(BA\u0007\u000f\u0003%\u00198-\u00197bi\u0016\u001cHOC\u0001\u0010\u0003\ry\'oZ\u0002\u0001\'\t\u0001!\u0003\u0005\u0002\u0014-5\tACC\u0001\u0016\u0003\u0015\u00198-\u00197b\u0013\t9BC\u0001\u0004B]f\u0014VMZ\u0001\u0005m\u0016\u0014(-F\u0001\u001b!\tY\"E\u0004\u0002\u001dAA\u0011Q\u0004F\u0007\u0002=)\u0011q\u0004E\u0001\u0007yI|w\u000e\u001e \n\u0005\u0005\"\u0012A\u0002)sK\u0012,g-\u0003\u0002$I\t11\u000b\u001e:j]\u001eT!!\t\u000b\u0002\u000bY,\'O\u0019\u0011\u0002\tI,7\u000f^\u0001\u0006e\u0016\u001cH\u000fI\u0001\u0005i\u0006<7/F\u0001+!\rY\u0003g\r\b\u0003Y9r!!H\u0017\n\u0003UI!a\f\u000b\u0002\u000fA\f7m[1hK&\u0011\u0011G\r\u0002\u0005\u0019&\u001cHO\u0003\u00020)A\u0011A\'N\u0007\u0002\u0019%\u0011a\u0007\u0004\u0002\u0004)\u0006<\u0017!\u0002;bON\u0004\u0013A\u0002\u001fj]&$h\b\u0006\u0003;yur\u0004CA\u001e\u0001\u001b\u0005Q\u0001\"\u0002\r\b\u0001\u0004Q\u0002\"\u0002\u0014\b\u0001\u0004Q\u0002\"\u0002\u0015\b\u0001\u0004Q\u0013AA5t)\t\tE\t\u0005\u0002\u0014\u0005&\u00111\t\u0006\u0002\u0005+:LG\u000f\u0003\u0004F\u0011\u0011\u0005\rAR\u0001\bi\u0016\u001cHOR;o!\r\u0019r)S\u0005\u0003\u0011R\u0011\u0001\u0002\u00102z]\u0006lWM\u0010\t\u0003i)K!a\u0013\u0007\u0003!A+g\u000eZ5oON#\u0018\r^3nK:$\b
   #9 = Utf8               verb
  #10 = Utf8               Ljava/lang/String;
  #11 = Utf8               rest
  #12 = Utf8               tags
  #13 = Utf8               Lscala/collection/immutable/List;
  #14 = Utf8               Lscala/collection/immutable/List<Lorg/scalatest/Tag;>;
  #15 = Utf8               ()Ljava/lang/String;
  #16 = NameAndType        #9:#10         // verb:Ljava/lang/String;
  #17 = Fieldref           #2.#16         // org/scalatest/verbs/ResultOfTaggedAsInvocation.verb:Ljava/lang/String;
  #18 = Utf8               this
  #19 = Utf8               Lorg/scalatest/verbs/ResultOfTaggedAsInvocation;
  #20 = NameAndType        #11:#10        // rest:Ljava/lang/String;
  #21 = Fieldref           #2.#20         // org/scalatest/verbs/ResultOfTaggedAsInvocation.rest:Ljava/lang/String;
  #22 = Utf8               ()Lscala/collection/immutable/List;
  #23 = Utf8               ()Lscala/collection/immutable/List<Lorg/scalatest/Tag;>;
  #24 = NameAndType        #12:#13        // tags:Lscala/collection/immutable/List;
  #25 = Fieldref           #2.#24         // org/scalatest/verbs/ResultOfTaggedAsInvocation.tags:Lscala/collection/immutable/List;
  #26 = Utf8               is
  #27 = Utf8               (Lscala/Function0;)V
  #28 = Utf8               (Lscala/Function0<Lorg/scalatest/PendingStatement;>;)V
  #29 = Utf8               testFun
  #30 = Utf8               <init>
  #31 = Utf8               (Ljava/lang/String;Ljava/lang/String;Lscala/collection/immutable/List;)V
  #32 = Utf8               (Ljava/lang/String;Ljava/lang/String;Lscala/collection/immutable/List<Lorg/scalatest/Tag;>;)V
  #33 = Utf8               ()V
  #34 = NameAndType        #30:#33        // "<init>":()V
  #35 = Methodref          #4.#34         // java/lang/Object."<init>":()V
  #36 = Utf8               Signature
  #37 = Utf8               Code
  #38 = Utf8               LineNumberTable
  #39 = Utf8               LocalVariableTable
  #40 = Utf8               MethodParameters
  #41 = Utf8               SourceFile
  #42 = Utf8               RuntimeVisibleAnnotations
  #43 = Utf8               ScalaInlineInfo
  #44 = Utf8               ScalaSig
{
  private final java.lang.String verb;
    descriptor: Ljava/lang/String;
    flags: (0x0012) ACC_PRIVATE, ACC_FINAL

  private final java.lang.String rest;
    descriptor: Ljava/lang/String;
    flags: (0x0012) ACC_PRIVATE, ACC_FINAL

  private final scala.collection.immutable.List<org.scalatest.Tag> tags;
    descriptor: Lscala/collection/immutable/List;
    flags: (0x0012) ACC_PRIVATE, ACC_FINAL
    Signature: #14                          // Lscala/collection/immutable/List<Lorg/scalatest/Tag;>;

  public java.lang.String verb();
    descriptor: ()Ljava/lang/String;
    flags: (0x0001) ACC_PUBLIC
    Code:
      stack=1, locals=1, args_size=1
         0: aload_0
         1: getfield      #17                 // Field verb:Ljava/lang/String;
         4: areturn
      LineNumberTable:
        line 60: 0
      LocalVariableTable:
        Start  Length  Slot  Name   Signature
            0       5     0  this   Lorg/scalatest/verbs/ResultOfTaggedAsInvocation;

  public java.lang.String rest();
    descriptor: ()Ljava/lang/String;
    flags: (0x0001) ACC_PUBLIC
    Code:
      stack=1, locals=1, args_size=1
         0: aload_0
         1: getfield      #21                 // Field rest:Ljava/lang/String;
         4: areturn
      LineNumberTable:
        line 60: 0
      LocalVariableTable:
        Start  Length  Slot  Name   Signature
            0       5     0  this   Lorg/scalatest/verbs/ResultOfTaggedAsInvocation;

  public scala.collection.immutable.List<org.scalatest.Tag> tags();
    descriptor: ()Lscala/collection/immutable/List;
    flags: (0x0001) ACC_PUBLIC
    Code:
      stack=1, locals=1, args_size=1
         0: aload_0
         1: getfield      #25                 // Field tags:Lscala/collection/immutable/List;
         4: areturn
      LineNumberTable:
        line 60: 0
      LocalVariableTable:
        Start  Length  Slot  Name   Signature
            0       5     0  this   Lorg/scalatest/verbs/ResultOfTaggedAsInvocation;
    Signature: #23                          // ()Lscala/collection/immutable/List<Lorg/scalatest/Tag;>;

  public abstract void is(scala.Function0<org.scalatest.PendingStatement>);
    descriptor: (Lscala/Function0;)V
    flags: (0x0401) ACC_PUBLIC, ACC_ABSTRACT
    Signature: #28                          // (Lscala/Function0<Lorg/scalatest/PendingStatement;>;)V
    MethodParameters:
      Name                           Flags
      testFun                        final

  public org.scalatest.verbs.ResultOfTaggedAsInvocation(java.lang.String, java.lang.String, scala.collection.immutable.List<org.scalatest.Tag>);
    descriptor: (Ljava/lang/String;Ljava/lang/String;Lscala/collection/immutable/List;)V
    flags: (0x0001) ACC_PUBLIC
    Code:
      stack=2, locals=4, args_size=4
         0: aload_0
         1: aload_1
         2: putfield      #17                 // Field verb:Ljava/lang/String;
         5: aload_0
         6: aload_2
         7: putfield      #21                 // Field rest:Ljava/lang/String;
        10: aload_0
        11: aload_3
        12: putfield      #25                 // Field tags:Lscala/collection/immutable/List;
        15: aload_0
        16: invokespecial #35                 // Method java/lang/Object."<init>":()V
        19: return
      LineNumberTable:
        line 60: 0
        line 83: 15
        line 60: 19
      LocalVariableTable:
        Start  Length  Slot  Name   Signature
            0      20     0  this   Lorg/scalatest/verbs/ResultOfTaggedAsInvocation;
            0      20     1  verb   Ljava/lang/String;
            0      20     2  rest   Ljava/lang/String;
            0      20     3  tags   Lscala/collection/immutable/List;
    Signature: #32                          // (Ljava/lang/String;Ljava/lang/String;Lscala/collection/immutable/List<Lorg/scalatest/Tag;>;)V
    MethodParameters:
      Name                           Flags
      verb                           final
      rest                           final
      tags                           final
}
SourceFile: "ResultOfTaggedAsInvocation.scala"
RuntimeVisibleAnnotations:
  0: #6(#7=s#8)
    scala.reflect.ScalaSignature(
      bytes="\u0006\u000513Q!\u0003\u0006\u0002\u0002EA\u0001\u0002\u0007\u0001\u0003\u0006\u0004%\t!\u0007\u0005\tK\u0001\u0011\t\u0011)A\u00055!Aa\u0005\u0001BC\u0002\u0013\u0005\u0011\u0004\u0003\u0005(\u0001\t\u0005\t\u0015!\u0003\u001b\u0011!A\u0003A!b\u0001\n\u0003I\u0003\u0002C\u001c\u0001\u0005\u0003\u0005\u000b\u0011\u0002\u0016\t\u000ba\u0002A\u0011A\u001d\t\u000b}\u0002a\u0011\u0001!\u00035I+7/\u001e7u\u001f\u001a$\u0016mZ4fI\u0006\u001b\u0018J\u001c<pG\u0006$\u0018n\u001c8\u000b\u0005-a\u0011!\u0002<fe\n\u001c(BA\u0007\u000f\u0003%\u00198-\u00197bi\u0016\u001cHOC\u0001\u0010\u0003\ry\'oZ\u0002\u0001\'\t\u0001!\u0003\u0005\u0002\u0014-5\tACC\u0001\u0016\u0003\u0015\u00198-\u00197b\u0013\t9BC\u0001\u0004B]f\u0014VMZ\u0001\u0005m\u0016\u0014(-F\u0001\u001b!\tY\"E\u0004\u0002\u001dAA\u0011Q\u0004F\u0007\u0002=)\u0011q\u0004E\u0001\u0007yI|w\u000e\u001e \n\u0005\u0005\"\u0012A\u0002)sK\u0012,g-\u0003\u0002$I\t11\u000b\u001e:j]\u001eT!!\t\u000b\u0002\u000bY,\'O\u0019\u0011\u0002\tI,7\u000f^\u0001\u0006e\u0016\u001cH\u000fI\u0001\u0005i\u0006<7/F\u0001+!\rY\u0003g\r\b\u0003Y9r!!H\u0017\n\u0003UI!a\f\u000b\u0002\u000fA\f7m[1hK&\u0011\u0011G\r\u0002\u0005\u0019&\u001cHO\u0003\u00020)A\u0011A\'N\u0007\u0002\u0019%\u0011a\u0007\u0004\u0002\u0004)\u0006<\u0017!\u0002;bON\u0004\u0013A\u0002\u001fj]&$h\b\u0006\u0003;yur\u0004CA\u001e\u0001\u001b\u0005Q\u0001\"\u0002\r\b\u0001\u0004Q\u0002\"\u0002\u0014\b\u0001\u0004Q\u0002\"\u0002\u0015\b\u0001\u0004Q\u0013AA5t)\t\tE\t\u0005\u0002\u0014\u0005&\u00111\t\u0006\u0002\u0005+:LG\u000f\u0003\u0004F\u0011\u0011\u0005\rAR\u0001\bi\u0016\u001cHOR;o!\r\u0019r)S\u0005\u0003\u0011R\u0011\u0001\u0002\u00102z]\u0006lWM\u0010\t\u0003i)K!a\u0013\u0007\u0003!A+g\u000eZ5oON#\u0018\r^3nK:$\b"
    )
  ScalaInlineInfo: length = 0x1D (unknown attribute)
   01 00 00 05 00 1E 00 1F 00 00 1A 00 1B 00 00 0B
   00 0F 00 00 0C 00 16 00 00 09 00 0F 00
  ScalaSig: length = 0x3 (unknown attribute)
   05 02 00
