Classfile /Users/mw/Projects/slang-braindump/.jar/jar8/assemble/slang-braindump/assemble/content/org/scalatest/verbs/StringVerbBehaveLikeInvocation.class
  Last modified May 29, 2022; size 1009 bytes
  SHA-256 checksum 0bb6311912fb892cfbeffde660ed547e5bb4b807e91d2eeb2d0c30488abf7099
  Compiled from "StringVerbBehaveLikeInvocation.scala"
public abstract class org.scalatest.verbs.StringVerbBehaveLikeInvocation
  minor version: 0
  major version: 52
  flags: (0x0421) ACC_PUBLIC, ACC_SUPER, ACC_ABSTRACT
  this_class: #2                          // org/scalatest/verbs/StringVerbBehaveLikeInvocation
  super_class: #4                         // java/lang/Object
  interfaces: 0, fields: 0, methods: 2, attributes: 4
Constant pool:
   #1 = Utf8               org/scalatest/verbs/StringVerbBehaveLikeInvocation
   #2 = Class              #1             // org/scalatest/verbs/StringVerbBehaveLikeInvocation
   #3 = Utf8               java/lang/Object
   #4 = Class              #3             // java/lang/Object
   #5 = Utf8               StringVerbBehaveLikeInvocation.scala
   #6 = Utf8               Lscala/reflect/ScalaSignature;
   #7 = Utf8               bytes
   #8 = Utf8               \u0006\u0005I2Qa\u0001\u0003\u0002\u0002-AQA\u0005\u0001\u0005\u0002MAQA\u0006\u0001\u0007\u0002]\u0011ad\u0015;sS:<g+\u001a:c\u0005\u0016D\u0017M^3MS.,\u0017J\u001c<pG\u0006$\u0018n\u001c8\u000b\u0005\u00151\u0011!\u0002<fe\n\u001c(BA\u0004\t\u0003%\u00198-\u00197bi\u0016\u001cHOC\u0001\n\u0003\ry\'oZ\u0002\u0001\'\t\u0001A\u0002\u0005\u0002\u000e!5\taBC\u0001\u0010\u0003\u0015\u00198-\u00197b\u0013\t\tbB\u0001\u0004B]f\u0014VMZ\u0001\u0007y%t\u0017\u000e\u001e \u0015\u0003Q\u0001\"!\u0006\u0001\u000e\u0003\u0011\tQ!\u00199qYf$2\u0001G\u000e)!\t)\u0012$\u0003\u0002\u001b\t\tQ!)\u001a5bm\u0016<vN\u001d3\t\u000bq\u0011\u0001\u0019A\u000f\u0002\u000fM,(M[3diB\u0011a$\n\b\u0003?\r\u0002\"\u0001\t\b\u000e\u0003\u0005R!A\t\u0006\u0002\rq\u0012xn\u001c;?\u0013\t!c\"\u0001\u0004Qe\u0016$WMZ\u0005\u0003M\u001d\u0012aa\u0015;sS:<\'B\u0001\u0013\u000f\u0011\u0015I#\u00011\u0001+\u0003\r\u0001xn\u001d\t\u0003WAj\u0011\u0001\f\u0006\u0003[9\naa]8ve\u000e,\'BA\u0018\t\u0003%\u00198-\u00197bGRL7-\u0003\u00022Y\tA\u0001k\\:ji&|g\u000e
   #9 = Utf8               apply
  #10 = Utf8               (Ljava/lang/String;Lorg/scalactic/source/Position;)Lorg/scalatest/verbs/BehaveWord;
  #11 = Utf8               subject
  #12 = Utf8               pos
  #13 = Utf8               <init>
  #14 = Utf8               ()V
  #15 = NameAndType        #13:#14        // "<init>":()V
  #16 = Methodref          #4.#15         // java/lang/Object."<init>":()V
  #17 = Utf8               this
  #18 = Utf8               Lorg/scalatest/verbs/StringVerbBehaveLikeInvocation;
  #19 = Utf8               MethodParameters
  #20 = Utf8               Code
  #21 = Utf8               LineNumberTable
  #22 = Utf8               LocalVariableTable
  #23 = Utf8               SourceFile
  #24 = Utf8               RuntimeVisibleAnnotations
  #25 = Utf8               ScalaInlineInfo
  #26 = Utf8               ScalaSig
{
  public abstract org.scalatest.verbs.BehaveWord apply(java.lang.String, org.scalactic.source.Position);
    descriptor: (Ljava/lang/String;Lorg/scalactic/source/Position;)Lorg/scalatest/verbs/BehaveWord;
    flags: (0x0401) ACC_PUBLIC, ACC_ABSTRACT
    MethodParameters:
      Name                           Flags
      subject                        final
      pos                            final

  public org.scalatest.verbs.StringVerbBehaveLikeInvocation();
    descriptor: ()V
    flags: (0x0001) ACC_PUBLIC
    Code:
      stack=1, locals=1, args_size=1
         0: aload_0
         1: invokespecial #16                 // Method java/lang/Object."<init>":()V
         4: return
      LineNumberTable:
        line 57: 0
        line 39: 4
      LocalVariableTable:
        Start  Length  Slot  Name   Signature
            0       5     0  this   Lorg/scalatest/verbs/StringVerbBehaveLikeInvocation;
}
SourceFile: "StringVerbBehaveLikeInvocation.scala"
RuntimeVisibleAnnotations:
  0: #6(#7=s#8)
    scala.reflect.ScalaSignature(
      bytes="\u0006\u0005I2Qa\u0001\u0003\u0002\u0002-AQA\u0005\u0001\u0005\u0002MAQA\u0006\u0001\u0007\u0002]\u0011ad\u0015;sS:<g+\u001a:c\u0005\u0016D\u0017M^3MS.,\u0017J\u001c<pG\u0006$\u0018n\u001c8\u000b\u0005\u00151\u0011!\u0002<fe\n\u001c(BA\u0004\t\u0003%\u00198-\u00197bi\u0016\u001cHOC\u0001\n\u0003\ry\'oZ\u0002\u0001\'\t\u0001A\u0002\u0005\u0002\u000e!5\taBC\u0001\u0010\u0003\u0015\u00198-\u00197b\u0013\t\tbB\u0001\u0004B]f\u0014VMZ\u0001\u0007y%t\u0017\u000e\u001e \u0015\u0003Q\u0001\"!\u0006\u0001\u000e\u0003\u0011\tQ!\u00199qYf$2\u0001G\u000e)!\t)\u0012$\u0003\u0002\u001b\t\tQ!)\u001a5bm\u0016<vN\u001d3\t\u000bq\u0011\u0001\u0019A\u000f\u0002\u000fM,(M[3diB\u0011a$\n\b\u0003?\r\u0002\"\u0001\t\b\u000e\u0003\u0005R!A\t\u0006\u0002\rq\u0012xn\u001c;?\u0013\t!c\"\u0001\u0004Qe\u0016$WMZ\u0005\u0003M\u001d\u0012aa\u0015;sS:<\'B\u0001\u0013\u000f\u0011\u0015I#\u00011\u0001+\u0003\r\u0001xn\u001d\t\u0003WAj\u0011\u0001\f\u0006\u0003[9\naa]8ve\u000e,\'BA\u0018\t\u0003%\u00198-\u00197bGRL7-\u0003\u00022Y\tA\u0001k\\:ji&|g\u000e"
    )
  ScalaInlineInfo: length = 0xE (unknown attribute)
   01 00 00 02 00 0D 00 0E 00 00 09 00 0A 00
  ScalaSig: length = 0x3 (unknown attribute)
   05 02 00
