Classfile /Users/mw/Projects/slang-braindump/.jar/jar8/assemble/slang-braindump/assemble/content/org/scalatest/verbs/TypeCheckWord.class
  Last modified May 29, 2022; size 582 bytes
  SHA-256 checksum 9b3e31db2e51e8338ab01d929c9aa9da8fde0c463ba14e17838f53a1541ac8be
  Compiled from "TypeCheckWord.scala"
public final class org.scalatest.verbs.TypeCheckWord
  minor version: 0
  major version: 52
  flags: (0x0031) ACC_PUBLIC, ACC_FINAL, ACC_SUPER
  this_class: #2                          // org/scalatest/verbs/TypeCheckWord
  super_class: #4                         // java/lang/Object
  interfaces: 0, fields: 0, methods: 1, attributes: 4
Constant pool:
   #1 = Utf8               org/scalatest/verbs/TypeCheckWord
   #2 = Class              #1             // org/scalatest/verbs/TypeCheckWord
   #3 = Utf8               java/lang/Object
   #4 = Class              #3             // java/lang/Object
   #5 = Utf8               TypeCheckWord.scala
   #6 = Utf8               Lscala/reflect/ScalaSignature;
   #7 = Utf8               bytes
   #8 = Utf8               \u0006\u0005U1AAA\u0002\u0003\u0015!)\u0011\u0003\u0001C\u0001%\tiA+\u001f9f\u0007\",7m[,pe\u0012T!\u0001B\u0003\u0002\u000bY,\'OY:\u000b\u0005\u00199\u0011!C:dC2\fG/Z:u\u0015\u0005A\u0011aA8sO\u000e\u00011C\u0001\u0001\f!\taq\"D\u0001\u000e\u0015\u0005q\u0011!B:dC2\f\u0017B\u0001\t\u000e\u0005\u0019\te.\u001f*fM\u00061A(\u001b8jiz\"\u0012a\u0005\t\u0003)\u0001i\u0011a\u0001
   #9 = Utf8               <init>
  #10 = Utf8               ()V
  #11 = NameAndType        #9:#10         // "<init>":()V
  #12 = Methodref          #4.#11         // java/lang/Object."<init>":()V
  #13 = Utf8               this
  #14 = Utf8               Lorg/scalatest/verbs/TypeCheckWord;
  #15 = Utf8               Code
  #16 = Utf8               LineNumberTable
  #17 = Utf8               LocalVariableTable
  #18 = Utf8               SourceFile
  #19 = Utf8               RuntimeVisibleAnnotations
  #20 = Utf8               ScalaInlineInfo
  #21 = Utf8               ScalaSig
{
  public org.scalatest.verbs.TypeCheckWord();
    descriptor: ()V
    flags: (0x0001) ACC_PUBLIC
    Code:
      stack=1, locals=1, args_size=1
         0: aload_0
         1: invokespecial #12                 // Method java/lang/Object."<init>":()V
         4: return
      LineNumberTable:
        line 25: 0
      LocalVariableTable:
        Start  Length  Slot  Name   Signature
            0       5     0  this   Lorg/scalatest/verbs/TypeCheckWord;
}
SourceFile: "TypeCheckWord.scala"
RuntimeVisibleAnnotations:
  0: #6(#7=s#8)
    scala.reflect.ScalaSignature(
      bytes="\u0006\u0005U1AAA\u0002\u0003\u0015!)\u0011\u0003\u0001C\u0001%\tiA+\u001f9f\u0007\",7m[,pe\u0012T!\u0001B\u0003\u0002\u000bY,\'OY:\u000b\u0005\u00199\u0011!C:dC2\fG/Z:u\u0015\u0005A\u0011aA8sO\u000e\u00011C\u0001\u0001\f!\taq\"D\u0001\u000e\u0015\u0005q\u0011!B:dC2\f\u0017B\u0001\t\u000e\u0005\u0019\te.\u001f*fM\u00061A(\u001b8jiz\"\u0012a\u0005\t\u0003)\u0001i\u0011a\u0001"
    )
  ScalaInlineInfo: length = 0x9 (unknown attribute)
   01 01 00 01 00 09 00 0A 01
  ScalaSig: length = 0x3 (unknown attribute)
   05 02 00
