Classfile /Users/mw/Projects/slang-braindump/.jar/jar11/assemble/slang-braindump/assemble/content/org/scalatest/freespec/AnyFreeSpecLike.class
  Last modified May 29, 2022; size 18563 bytes
  SHA-256 checksum 8ae928272edc9e49791235f1dfe7673789dfec3ec2ff44099054d775d6de551e
  Compiled from "AnyFreeSpecLike.scala"
public interface org.scalatest.freespec.AnyFreeSpecLike extends org.scalatest.TestSuite,org.scalatest.TestRegistration,org.scalatest.Informing,org.scalatest.Notifying,org.scalatest.Alerting,org.scalatest.Documenting
  minor version: 0
  major version: 52
  flags: (0x0601) ACC_PUBLIC, ACC_INTERFACE, ACC_ABSTRACT
  this_class: #2                          // org/scalatest/freespec/AnyFreeSpecLike
  super_class: #4                         // java/lang/Object
  interfaces: 6, fields: 0, methods: 52, attributes: 6
Constant pool:
    #1 = Utf8               org/scalatest/freespec/AnyFreeSpecLike
    #2 = Class              #1            // org/scalatest/freespec/AnyFreeSpecLike
    #3 = Utf8               java/lang/Object
    #4 = Class              #3            // java/lang/Object
    #5 = Utf8               org/scalatest/TestSuite
    #6 = Class              #5            // org/scalatest/TestSuite
    #7 = Utf8               org/scalatest/TestRegistration
    #8 = Class              #7            // org/scalatest/TestRegistration
    #9 = Utf8               org/scalatest/Informing
   #10 = Class              #9            // org/scalatest/Informing
   #11 = Utf8               org/scalatest/Notifying
   #12 = Class              #11           // org/scalatest/Notifying
   #13 = Utf8               org/scalatest/Alerting
   #14 = Class              #13           // org/scalatest/Alerting
   #15 = Utf8               org/scalatest/Documenting
   #16 = Class              #15           // org/scalatest/Documenting
   #17 = Utf8               AnyFreeSpecLike.scala
   #18 = Utf8               Lorg/scalatest/Finders;
   #19 = Utf8               value
   #20 = Utf8               org.scalatest.finders.FreeSpecFinder
   #21 = Utf8               Lscala/reflect/ScalaSignature;
   #22 = Utf8               bytes
   #23 = Utf8               \u0006\u0005\t5faB\u0015+!\u0003\r\t!\r\u0005\u0006\u0017\u0002!\t\u0001\u0014\u0005\b!\u0002\u0011\r\u0011\"\u0004R\u0011\u0015)\u0006\u0001\"\u0005W\u0011\u0015Q\u0006\u0001\"\u0005\\\u0011\u0015y\u0006\u0001\"\u0005a\u0011\u0015!\u0007\u0001\"\u0005f\u0011\u0015I\u0007\u0001\"\u0004k\u0011\u001d\t9\u0003\u0001C\u0003\u0003SAq!a\u000e\u0001\t\u001b\tI\u0004C\u0004\u0002F\u0001!)!a\u0012\t\u000f\u0005U\u0003\u0001\"\u0003\u0002X!9\u0011q\u0010\u0001\u0005\n\u0005\u0005eABAG\u0001)\ty\t\u0003\u0006\u0002\\5\u0011\t\u0011)A\u0005\u0003\u0003A!\"!%\u000e\u0005\u0003\u0005\u000b\u0011BA0\u0011!)XB!A!\u0002\u00131\bbBAJ\u001b\u0011\u0005\u0011Q\u0013\u0005\b\u0003CkA\u0011AAR\u0011\u001d\t9+\u0004C\u0001\u0003SCq!!.\u000e\t\u0003\t9L\u0002\u0004\u0002<\u0002Q\u0011Q\u0018\u0005\u000b\u0003\u007f+\"\u0011!Q\u0001\n\u0005\u0005\u0001\u0002C;\u0016\u0005\u0003\u0005\u000b\u0011\u0002<\t\u000f\u0005MU\u0003\"\u0001\u0002B\"9\u0011\u0011Z\u000b\u0005\u0002\u0005-\u0007bBAQ+\u0011\u0005\u00111\u001b\u0005\b\u0003k+B\u0011AAm\u0011\u001d\t9+\u0006C\u0001\u0003;Dq!!9\u0016\t\u0003\t\u0019\u000fC\u0004\u0002n\u0002!\u0019\"a<\t\u000f\u0005E\u0005\u0001\"\u0011\u0002z\"9!q\u0001\u0001\u0005R\t%\u0001b\u0002B\u0010\u0001\u0011E#\u0011\u0005\u0005\b\u0005[\u0001A\u0011\tB\u0018\u0011\u001d\u0011\t\u0004\u0001C!\u0005gA\u0011B!\u000f\u0001\u0005\u0004%\tBa\u000f\t\u0013\t%\u0003A1A\u0005F\t-\u0003b\u0002B1\u0001\u0011\u0005#1\r\u0005\n\u0005o\u0002\u0011\u0013!C\u0001\u0005sBaBa$\u0001!\u0003\r\t\u0011!C\u0005\u0005#\u00139JA\bB]f4%/Z3Ta\u0016\u001cG*[6f\u0015\tYC&\u0001\u0005ge\u0016,7\u000f]3d\u0015\tic&A\u0005tG\u0006d\u0017\r^3ti*\tq&A\u0002pe\u001e\u001c\u0001a\u0005\u0005\u0001eabtHQ#I!\t\u0019d\'D\u00015\u0015\u0005)\u0014!B:dC2\f\u0017BA\u001c5\u0005\u0019\te.\u001f*fMB\u0011\u0011HO\u0007\u0002Y%\u00111\b\f\u0002\n)\u0016\u001cHoU;ji\u0016\u0004\"!O\u001f\n\u0005yb#\u0001\u0005+fgR\u0014VmZ5tiJ\fG/[8o!\tI\u0004)\u0003\u0002BY\tI\u0011J\u001c4pe6Lgn\u001a\t\u0003s\rK!\u0001\u0012\u0017\u0003\u00139{G/\u001b4zS:<\u0007CA\u001dG\u0013\t9EF\u0001\u0005BY\u0016\u0014H/\u001b8h!\tI\u0014*\u0003\u0002KY\tYAi\\2v[\u0016tG/\u001b8h\u0003\u0019!\u0013N\\5uIQ\tQ\n\u0005\u00024\u001d&\u0011q\n\u000e\u0002\u0005+:LG/\u0001\u0004f]\u001eLg.Z\u000b\u0002%B\u0011\u0011hU\u0005\u0003)2\u0012a!\u00128hS:,\u0017\u0001B5oM>,\u0012a\u0016\t\u0003saK!!\u0017\u0017\u0003\u0011%sgm\u001c:nKJ\fAA\\8uKV\tA\f\u0005\u0002:;&\u0011a\f\f\u0002\t\u001d>$\u0018NZ5fe\u0006)\u0011\r\\3siV\t\u0011\r\u0005\u0002:E&\u00111\r\f\u0002\b\u00032,\'\u000f^3s\u0003\u0019i\u0017M]6vaV\ta\r\u0005\u0002:O&\u0011\u0001\u000e\f\u0002\u000b\t>\u001cW/\\3oi\u0016\u0014\u0018\u0001\u0005:fO&\u001cH/\u001a:UKN$\u0018*\u001c9m)\u0011Yg0a\u0006\u0015\u00075cG\u000f\u0003\u0004n\u000f\u0011\u0005\rA\\\u0001\bi\u0016\u001cHOR;o!\r\u0019t.]\u0005\u0003aR\u0012\u0001\u0002\u00102z]\u0006lWM\u0010\t\u0003gIL!a\u001d\u001b\u0003\u0007\u0005s\u0017\u0010C\u0003v\u000f\u0001\u0007a/A\u0002q_N\u0004\"a\u001e?\u000e\u0003aT!!\u001f>\u0002\rM|WO]2f\u0015\tYh&A\u0005tG\u0006d\u0017m\u0019;jG&\u0011Q\u0010\u001f\u0002\t!>\u001c\u0018\u000e^5p]\"1qp\u0002a\u0001\u0003\u0003\t\u0001\u0002^3tiR+\u0007\u0010\u001e\t\u0005\u0003\u0007\t\tB\u0004\u0003\u0002\u0006\u00055\u0001cAA\u0004i5\u0011\u0011\u0011\u0002\u0006\u0004\u0003\u0017\u0001\u0014A\u0002\u001fs_>$h(C\u0002\u0002\u0010Q\na\u0001\u0015:fI\u00164\u0017\u0002BA\n\u0003+\u0011aa\u0015;sS:<\'bAA\bi!9\u0011\u0011D\u0004A\u0002\u0005m\u0011\u0001\u0003;fgR$\u0016mZ:\u0011\u000bM\ni\"!\t\n\u0007\u0005}AG\u0001\u0006=e\u0016\u0004X-\u0019;fIz\u00022!OA\u0012\u0013\r\t)\u0003\f\u0002\u0004)\u0006<\u0017\u0001\u0004:fO&\u001cH/\u001a:UKN$HCBA\u0016\u0003g\t)\u0004\u0006\u0003\u0002.\u0005EBcA\'\u00020!)Q\u000f\u0003a\u0002m\"1Q\u000e\u0003CA\u00029Daa \u0005A\u0002\u0005\u0005\u0001bBA\r\u0011\u0001\u0007\u00111D\u0001\u0018e\u0016<\u0017n\u001d;fe&;gn\u001c:fIR+7\u000f^%na2$b!a\u000f\u0002B\u0005\rC#B\'\u0002>\u0005}\u0002BB7\n\t\u0003\u0007a\u000eC\u0003v\u0013\u0001\u0007a\u000f\u0003\u0004\u0000\u0013\u0001\u0007\u0011\u0011\u0001\u0005\b\u00033I\u0001\u0019AA\u000e\u0003M\u0011XmZ5ti\u0016\u0014\u0018j\u001a8pe\u0016$G+Z:u)\u0019\tI%!\u0015\u0002TQ!\u00111JA()\ri\u0015Q\n\u0005\u0006k*\u0001\u001dA\u001e\u0005\u0007[*!\t\u0019\u00018\t\r}T\u0001\u0019AA\u0001\u0011\u001d\tIB\u0003a\u0001\u00037\t\u0011C]3hSN$XM\u001d+fgR$vNU;o)-i\u0015\u0011LA/\u0003c\n)(! \t\u000f\u0005m3\u00021\u0001\u0002\u0002\u0005A1\u000f]3d)\u0016DH\u000fC\u0004\u0002\u001a-\u0001\r!a\u0018\u0011\r\u0005\u0005\u00141NA\u0011\u001d\u0011\t\u0019\'a\u001a\u000f\t\u0005\u001d\u0011QM\u0005\u0002k%\u0019\u0011\u0011\u000e\u001b\u0002\u000fA\f7m[1hK&!\u0011QNA8\u0005\u0011a\u0015n\u001d;\u000b\u0007\u0005%D\u0007C\u0004\u0002t-\u0001\r!!\u0001\u0002\u00155,G\u000f[8e\u001d\u0006lW\r\u0003\u0004n\u0017\u0001\u0007\u0011q\u000f\t\u0005g\u0005e\u0014/C\u0002\u0002|Q\u0012\u0011BR;oGRLwN\u001c\u0019\t\u000bU\\\u0001\u0019\u0001<\u0002)I,w-[:uKJ$Vm\u001d;U_&;gn\u001c:f)-i\u00151QAC\u0003\u000f\u000bI)a#\t\u000f\u0005mC\u00021\u0001\u0002\u0002!9\u0011\u0011\u0004\u0007A\u0002\u0005}\u0003bBA:\u0019\u0001\u0007\u0011\u0011\u0001\u0005\u0007[2\u0001\r!a\u001e\t\u000bUd\u0001\u0019\u0001<\u0003EI+7/\u001e7u\u001f\u001a$\u0016mZ4fI\u0006\u001b\u0018J\u001c<pG\u0006$\u0018n\u001c8P]N#(/\u001b8h\'\ti!\'\u0001\u0003uC\u001e\u001c\u0018A\u0002\u001fj]&$h\b\u0006\u0005\u0002\u0018\u0006m\u0015QTAP!\r\tI*D\u0007\u0002\u0001!9\u00111L\tA\u0002\u0005\u0005\u0001bBAI#\u0001\u0007\u0011q\f\u0005\u0006kF\u0001\rA^\u0001\u0003S:$2!TAS\u0011\u0019i\'\u0003\"a\u0001]\u0006\u0011\u0011n\u001d\u000b\u0004\u001b\u0006-\u0006bB7\u0014\t\u0003\u0007\u0011Q\u0016\t\u0005g=\fy\u000bE\u0002:\u0003cK1!a--\u0005A\u0001VM\u001c3j]\u001e\u001cF/\u0019;f[\u0016tG/\u0001\u0004jO:|\'/\u001a\u000b\u0004\u001b\u0006e\u0006BB7\u0015\t\u0003\u0007aNA\u000bGe\u0016,7\u000b]3d\'R\u0014\u0018N\\4Xe\u0006\u0004\b/\u001a:\u0014\u0005U\u0011\u0014AB:ue&tw\r\u0006\u0004\u0002D\u0006\u0015\u0017q\u0019\t\u0004\u00033+\u0002bBA`1\u0001\u0007\u0011\u0011\u0001\u0005\u0006kb\u0001\rA^\u0001\u0007I5Lg.^:\u0015\u00075\u000bi\r\u0003\u0005\u0002Pf!\t\u0019AAi\u0003\r1WO\u001c\t\u0004g=lEcA\'\u0002V\"9\u0011q\u001b\u000e\u0005\u0002\u0004q\u0017!\u00014\u0015\u00075\u000bY\u000eC\u0004\u0002Xn!\t\u0019\u00018\u0015\u00075\u000by\u000e\u0003\u0005\u0002Xr!\t\u0019AAW\u0003!!\u0018mZ4fI\u0006\u001bHCBAL\u0003K\fI\u000fC\u0004\u0002hv\u0001\r!!\t\u0002\u0019\u0019L\'o\u001d;UKN$H+Y4\t\u000f\u0005-X\u00041\u0001\u0002\u001c\u0005iq\u000e\u001e5feR+7\u000f\u001e+bON\fadY8om\u0016\u0014H\u000fV8Ge\u0016,7\u000b]3d\'R\u0014\u0018N\\4Xe\u0006\u0004\b/\u001a:\u0015\t\u0005E\u0018Q\u001f\u000b\u0005\u0003\u0007\f\u0019\u0010C\u0003v=\u0001\u000fa\u000fC\u0004\u0002xz\u0001\r!!\u0001\u0002\u0003M,\"!a?\u0011\u0011\u0005\r\u0011Q`A\u0001\u0005\u0003IA!a@\u0002\u0016\t\u0019Q*\u00199\u0011\r\u0005\r!1AA\u0001\u0013\u0011\u0011)!!\u0006\u0003\u0007M+G/A\u0004sk:$Vm\u001d;\u0015\r\t-!\u0011\u0003B\u000b!\rI$QB\u0005\u0004\u0005\u001fa#AB*uCR,8\u000fC\u0004\u0003\u0014\u0001\u0002\r!!\u0001\u0002\u0011Q,7\u000f\u001e(b[\u0016DqAa\u0006!\u0001\u0004\u0011I\"\u0001\u0003be\u001e\u001c\bcA\u001d\u0003\u001c%\u0019!Q\u0004\u0017\u0003\t\u0005\u0013xm]\u0001\teVtG+Z:ugR1!1\u0002B\u0012\u0005WAqAa\u0005\"\u0001\u0004\u0011)\u0003E\u00034\u0005O\t\t!C\u0002\u0003*Q\u0012aa\u00149uS>t\u0007b\u0002B\fC\u0001\u0007!\u0011D\u0001\ni\u0016\u001cHOT1nKN,\"A!\u0001\u0002\u0007I,h\u000e\u0006\u0004\u0003\f\tU\"q\u0007\u0005\b\u0005\'\u0019\u0003\u0019\u0001B\u0013\u0011\u001d\u00119b\ta\u0001\u00053\taAY3iCZ,WC\u0001B\u001f!\u0011\u0011yD!\u0012\u000e\u0005\t\u0005#b\u0001B\"Y\u0005)a/\u001a:cg&!!q\tB!\u0005)\u0011U\r[1wK^{\'\u000fZ\u0001\ngRLH.\u001a(b[\u0016,\"!!\u0001)\u0017\u0015\u0012yE!\u0016\u0003X\tm#Q\f\t\u0004g\tE\u0013b\u0001B*i\tQA-\u001a9sK\u000e\fG/\u001a3\u0002\u000f5,7o]1hK\u0006\u0012!\u0011L\u0001})\",\u0007e\u001d;zY\u0016t\u0015-\\3!Y&4WmY=dY\u0016\u0004S.\u001a;i_\u0012\u0004\u0003.Y:!E\u0016,g\u000e\t3faJ,7-\u0019;fI\u0002\ng\u000e\u001a\u0011xS2d\u0007EY3!e\u0016lwN^3eA%t\u0007%\u0019\u0011gkR,(/\u001a\u0011wKJ\u001c\u0018n\u001c8!_\u001a\u00043kY1mCR+7\u000f\u001e\u0011xSRD\u0007E\\8!e\u0016\u0004H.Y2f[\u0016tGOL\u0001\u0006g&t7-Z\u0011\u0003\u0005?\nQa\r\u00182]A\n1\u0002^3ti\u0012\u000bG/\u0019$peR1!Q\rB6\u0005[\u00022!\u000fB4\u0013\r\u0011I\u0007\f\u0002\t)\u0016\u001cH\u000fR1uC\"9!1\u0003\u0014A\u0002\u0005\u0005\u0001\"\u0003B8MA\u0005\t\u0019\u0001B9\u00031!\b.Z\"p]\u001aLw-T1q!\rI$1O\u0005\u0004\u0005kb#!C\"p]\u001aLw-T1q\u0003U!Xm\u001d;ECR\fgi\u001c:%I\u00164\u0017-\u001e7uII*\"Aa\u001f+\t\tE$QP\u0016\u0003\u0005\u007f\u0002BA!!\u0003\f6\u0011!1\u0011\u0006\u0005\u0005\u000b\u00139)A\u0005v]\u000eDWmY6fI*\u0019!\u0011\u0012\u001b\u0002\u0015\u0005tgn\u001c;bi&|g.\u0003\u0003\u0003\u000e\n\r%!E;oG\",7m[3e-\u0006\u0014\u0018.\u00198dK\u0006I1/\u001e9fe\u0012\u0012XO\u001c\u000b\u0007\u0005\u0017\u0011\u0019J!&\t\u000f\tM\u0001\u00061\u0001\u0003&!9!q\u0003\u0015A\u0002\te\u0011\u0002\u0002B\u0019\u00053K1Aa\'-\u0005\u0015\u0019V/\u001b;fQ\u001d\u0001!q\u0014BS\u0005O\u00032!\u000fBQ\u0013\r\u0011\u0019\u000b\f\u0002\b\r&tG-\u001a:t\u0003\u00151\u0018\r\\;fY\t\u0011I+\t\u0002\u0003,\u0006!sN]4/g\u000e\fG.\u0019;fgRtc-\u001b8eKJ\u001chF\u0012:fKN\u0003Xm\u0019$j]\u0012,\'\u000f
   #24 = Utf8               java/lang/invoke/MethodHandles$Lookup
   #25 = Class              #24           // java/lang/invoke/MethodHandles$Lookup
   #26 = Utf8               java/lang/invoke/MethodHandles
   #27 = Class              #26           // java/lang/invoke/MethodHandles
   #28 = Utf8               Lookup
   #29 = Utf8               org/scalatest/SuperEngine$Bundle
   #30 = Class              #29           // org/scalatest/SuperEngine$Bundle
   #31 = Utf8               org/scalatest/SuperEngine
   #32 = Class              #31           // org/scalatest/SuperEngine
   #33 = Utf8               Bundle
   #34 = Utf8               org/scalatest/SuperEngine$TestLeaf
   #35 = Class              #34           // org/scalatest/SuperEngine$TestLeaf
   #36 = Utf8               TestLeaf
   #37 = Utf8               org/scalatest/TestSuite$NoArgTest
   #38 = Class              #37           // org/scalatest/TestSuite$NoArgTest
   #39 = Utf8               NoArgTest
   #40 = Utf8               org/scalatest/freespec/AnyFreeSpecLike$$anon$1
   #41 = Class              #40           // org/scalatest/freespec/AnyFreeSpecLike$$anon$1
   #42 = Utf8               org/scalatest/freespec/AnyFreeSpecLike$FreeSpecStringWrapper
   #43 = Class              #42           // org/scalatest/freespec/AnyFreeSpecLike$FreeSpecStringWrapper
   #44 = Utf8               FreeSpecStringWrapper
   #45 = Utf8               org/scalatest/freespec/AnyFreeSpecLike$ResultOfTaggedAsInvocationOnString
   #46 = Class              #45           // org/scalatest/freespec/AnyFreeSpecLike$ResultOfTaggedAsInvocationOnString
   #47 = Utf8               ResultOfTaggedAsInvocationOnString
   #48 = Utf8               org$scalatest$freespec$AnyFreeSpecLike$_setter_$org$scalatest$freespec$AnyFreeSpecLike$$engine_$eq
   #49 = Utf8               (Lorg/scalatest/Engine;)V
   #50 = Utf8               x$1
   #51 = Utf8               org$scalatest$freespec$AnyFreeSpecLike$_setter_$behave_$eq
   #52 = Utf8               (Lorg/scalatest/verbs/BehaveWord;)V
   #53 = Utf8               org$scalatest$freespec$AnyFreeSpecLike$_setter_$styleName_$eq
   #54 = Utf8               (Ljava/lang/String;)V
   #55 = Utf8               org$scalatest$freespec$AnyFreeSpecLike$$super$run
   #56 = Utf8               (Lscala/Option;Lorg/scalatest/Args;)Lorg/scalatest/Status;
   #57 = Utf8               testName
   #58 = Utf8               args
   #59 = Utf8               org$scalatest$freespec$AnyFreeSpecLike$$engine
   #60 = Utf8               ()Lorg/scalatest/Engine;
   #61 = Utf8               info$
   #62 = Utf8               (Lorg/scalatest/freespec/AnyFreeSpecLike;)Lorg/scalatest/Informer;
   #63 = Utf8               $this
   #64 = Utf8               info
   #65 = Utf8               ()Lorg/scalatest/Informer;
   #66 = NameAndType        #64:#65       // info:()Lorg/scalatest/Informer;
   #67 = InterfaceMethodref #2.#66        // org/scalatest/freespec/AnyFreeSpecLike.info:()Lorg/scalatest/Informer;
   #68 = Utf8               Lorg/scalatest/freespec/AnyFreeSpecLike;
   #69 = NameAndType        #59:#60       // org$scalatest$freespec$AnyFreeSpecLike$$engine:()Lorg/scalatest/Engine;
   #70 = InterfaceMethodref #2.#69        // org/scalatest/freespec/AnyFreeSpecLike.org$scalatest$freespec$AnyFreeSpecLike$$engine:()Lorg/scalatest/Engine;
   #71 = Utf8               org/scalatest/Engine
   #72 = Class              #71           // org/scalatest/Engine
   #73 = Utf8               atomicInformer
   #74 = Utf8               ()Ljava/util/concurrent/atomic/AtomicReference;
   #75 = NameAndType        #73:#74       // atomicInformer:()Ljava/util/concurrent/atomic/AtomicReference;
   #76 = Methodref          #72.#75       // org/scalatest/Engine.atomicInformer:()Ljava/util/concurrent/atomic/AtomicReference;
   #77 = Utf8               java/util/concurrent/atomic/AtomicReference
   #78 = Class              #77           // java/util/concurrent/atomic/AtomicReference
   #79 = Utf8               get
   #80 = Utf8               ()Ljava/lang/Object;
   #81 = NameAndType        #79:#80       // get:()Ljava/lang/Object;
   #82 = Methodref          #78.#81       // java/util/concurrent/atomic/AtomicReference.get:()Ljava/lang/Object;
   #83 = Utf8               org/scalatest/Informer
   #84 = Class              #83           // org/scalatest/Informer
   #85 = Utf8               this
   #86 = Utf8               note$
   #87 = Utf8               (Lorg/scalatest/freespec/AnyFreeSpecLike;)Lorg/scalatest/Notifier;
   #88 = Utf8               note
   #89 = Utf8               ()Lorg/scalatest/Notifier;
   #90 = NameAndType        #88:#89       // note:()Lorg/scalatest/Notifier;
   #91 = InterfaceMethodref #2.#90        // org/scalatest/freespec/AnyFreeSpecLike.note:()Lorg/scalatest/Notifier;
   #92 = Utf8               atomicNotifier
   #93 = NameAndType        #92:#74       // atomicNotifier:()Ljava/util/concurrent/atomic/AtomicReference;
   #94 = Methodref          #72.#93       // org/scalatest/Engine.atomicNotifier:()Ljava/util/concurrent/atomic/AtomicReference;
   #95 = Utf8               org/scalatest/Notifier
   #96 = Class              #95           // org/scalatest/Notifier
   #97 = Utf8               alert$
   #98 = Utf8               (Lorg/scalatest/freespec/AnyFreeSpecLike;)Lorg/scalatest/Alerter;
   #99 = Utf8               alert
  #100 = Utf8               ()Lorg/scalatest/Alerter;
  #101 = NameAndType        #99:#100      // alert:()Lorg/scalatest/Alerter;
  #102 = InterfaceMethodref #2.#101       // org/scalatest/freespec/AnyFreeSpecLike.alert:()Lorg/scalatest/Alerter;
  #103 = Utf8               atomicAlerter
  #104 = NameAndType        #103:#74      // atomicAlerter:()Ljava/util/concurrent/atomic/AtomicReference;
  #105 = Methodref          #72.#104      // org/scalatest/Engine.atomicAlerter:()Ljava/util/concurrent/atomic/AtomicReference;
  #106 = Utf8               org/scalatest/Alerter
  #107 = Class              #106          // org/scalatest/Alerter
  #108 = Utf8               markup$
  #109 = Utf8               (Lorg/scalatest/freespec/AnyFreeSpecLike;)Lorg/scalatest/Documenter;
  #110 = Utf8               markup
  #111 = Utf8               ()Lorg/scalatest/Documenter;
  #112 = NameAndType        #110:#111     // markup:()Lorg/scalatest/Documenter;
  #113 = InterfaceMethodref #2.#112       // org/scalatest/freespec/AnyFreeSpecLike.markup:()Lorg/scalatest/Documenter;
  #114 = Utf8               atomicDocumenter
  #115 = NameAndType        #114:#74      // atomicDocumenter:()Ljava/util/concurrent/atomic/AtomicReference;
  #116 = Methodref          #72.#115      // org/scalatest/Engine.atomicDocumenter:()Ljava/util/concurrent/atomic/AtomicReference;
  #117 = Utf8               org/scalatest/Documenter
  #118 = Class              #117          // org/scalatest/Documenter
  #119 = Utf8               registerTestImpl
  #120 = Utf8               (Ljava/lang/String;Lscala/collection/immutable/Seq;Lscala/Function0;Lorg/scalactic/source/Position;)V
  #121 = Utf8               (Ljava/lang/String;Lscala/collection/immutable/Seq<Lorg/scalatest/Tag;>;Lscala/Function0<Ljava/lang/Object;>;Lorg/scalactic/source/Position;)V
  #122 = Utf8               testText
  #123 = Utf8               testTags
  #124 = Utf8               testFun
  #125 = Utf8               pos
  #126 = Utf8               org/scalatest/Transformer
  #127 = Class              #126          // org/scalatest/Transformer
  #128 = Utf8               <init>
  #129 = Utf8               (Lscala/Function0;)V
  #130 = NameAndType        #128:#129     // "<init>":(Lscala/Function0;)V
  #131 = Methodref          #127.#130     // org/scalatest/Transformer."<init>":(Lscala/Function0;)V
  #132 = MethodType         #80           //  ()Ljava/lang/Object;
  #133 = Utf8               $anonfun$registerTestImpl$1
  #134 = Utf8               ()Ljava/lang/String;
  #135 = NameAndType        #133:#134     // $anonfun$registerTestImpl$1:()Ljava/lang/String;
  #136 = InterfaceMethodref #2.#135       // org/scalatest/freespec/AnyFreeSpecLike.$anonfun$registerTestImpl$1:()Ljava/lang/String;
  #137 = MethodHandle       6:#136        // REF_invokeStatic org/scalatest/freespec/AnyFreeSpecLike.$anonfun$registerTestImpl$1:()Ljava/lang/String;
  #138 = MethodType         #134          //  ()Ljava/lang/String;
  #139 = Integer            5
  #140 = Integer            1
  #141 = Utf8               java/lang/invoke/LambdaMetafactory
  #142 = Class              #141          // java/lang/invoke/LambdaMetafactory
  #143 = Utf8               altMetafactory
  #144 = Utf8               (Ljava/lang/invoke/MethodHandles$Lookup;Ljava/lang/String;Ljava/lang/invoke/MethodType;[Ljava/lang/Object;)Ljava/lang/invoke/CallSite;
  #145 = NameAndType        #143:#144     // altMetafactory:(Ljava/lang/invoke/MethodHandles$Lookup;Ljava/lang/String;Ljava/lang/invoke/MethodType;[Ljava/lang/Object;)Ljava/lang/invoke/CallSite;
  #146 = Methodref          #142.#145     // java/lang/invoke/LambdaMetafactory.altMetafactory:(Ljava/lang/invoke/MethodHandles$Lookup;Ljava/lang/String;Ljava/lang/invoke/MethodType;[Ljava/lang/Object;)Ljava/lang/invoke/CallSite;
  #147 = MethodHandle       6:#146        // REF_invokeStatic java/lang/invoke/LambdaMetafactory.altMetafactory:(Ljava/lang/invoke/MethodHandles$Lookup;Ljava/lang/String;Ljava/lang/invoke/MethodType;[Ljava/lang/Object;)Ljava/lang/invoke/CallSite;
  #148 = Utf8               apply
  #149 = Utf8               ()Lscala/Function0;
  #150 = NameAndType        #148:#149     // apply:()Lscala/Function0;
  #151 = InvokeDynamic      #0:#150       // #0:apply:()Lscala/Function0;
  #152 = String             #17           // AnyFreeSpecLike.scala
  #153 = Utf8               registerTest
  #154 = String             #153          // registerTest
  #155 = Utf8               scala/None$
  #156 = Class              #155          // scala/None$
  #157 = Utf8               MODULE$
  #158 = Utf8               Lscala/None$;
  #159 = NameAndType        #157:#158     // MODULE$:Lscala/None$;
  #160 = Fieldref           #156.#159     // scala/None$.MODULE$:Lscala/None$;
  #161 = Utf8               scala/Some
  #162 = Class              #161          // scala/Some
  #163 = Utf8               (Ljava/lang/Object;)V
  #164 = NameAndType        #128:#163     // "<init>":(Ljava/lang/Object;)V
  #165 = Methodref          #162.#164     // scala/Some."<init>":(Ljava/lang/Object;)V
  #166 = Utf8               (Ljava/lang/String;Ljava/lang/Object;Lscala/Function0;Ljava/lang/String;Ljava/lang/String;IILscala/Option;Lscala/Option;Lscala/Option;Lscala/Option;Lscala/collection/immutable/Seq;)Ljava/lang/String;
  #167 = NameAndType        #153:#166     // registerTest:(Ljava/lang/String;Ljava/lang/Object;Lscala/Function0;Ljava/lang/String;Ljava/lang/String;IILscala/Option;Lscala/Option;Lscala/Option;Lscala/Option;Lscala/collection/immutable/Seq;)Ljava/lang/String;
  #168 = Methodref          #72.#167      // org/scalatest/Engine.registerTest:(Ljava/lang/String;Ljava/lang/Object;Lscala/Function0;Ljava/lang/String;Ljava/lang/String;IILscala/Option;Lscala/Option;Lscala/Option;Lscala/Option;Lscala/collection/immutable/Seq;)Ljava/lang/String;
  #169 = Utf8               stackDepthAdjustment
  #170 = Utf8               I
  #171 = Utf8               Ljava/lang/String;
  #172 = Utf8               Lscala/collection/immutable/Seq;
  #173 = Utf8               Lscala/Function0;
  #174 = Utf8               Lorg/scalactic/source/Position;
  #175 = Utf8               registerTest$
  #176 = Utf8               (Lorg/scalatest/freespec/AnyFreeSpecLike;Ljava/lang/String;Lscala/collection/immutable/Seq;Lscala/Function0;Lorg/scalactic/source/Position;)V
  #177 = NameAndType        #153:#120     // registerTest:(Ljava/lang/String;Lscala/collection/immutable/Seq;Lscala/Function0;Lorg/scalactic/source/Position;)V
  #178 = InterfaceMethodref #2.#177       // org/scalatest/freespec/AnyFreeSpecLike.registerTest:(Ljava/lang/String;Lscala/collection/immutable/Seq;Lscala/Function0;Lorg/scalactic/source/Position;)V
  #179 = NameAndType        #119:#120     // registerTestImpl:(Ljava/lang/String;Lscala/collection/immutable/Seq;Lscala/Function0;Lorg/scalactic/source/Position;)V
  #180 = InterfaceMethodref #2.#179       // org/scalatest/freespec/AnyFreeSpecLike.registerTestImpl:(Ljava/lang/String;Lscala/collection/immutable/Seq;Lscala/Function0;Lorg/scalactic/source/Position;)V
  #181 = Utf8               registerIgnoredTestImpl
  #182 = Utf8               $anonfun$registerIgnoredTestImpl$1
  #183 = NameAndType        #182:#134     // $anonfun$registerIgnoredTestImpl$1:()Ljava/lang/String;
  #184 = InterfaceMethodref #2.#183       // org/scalatest/freespec/AnyFreeSpecLike.$anonfun$registerIgnoredTestImpl$1:()Ljava/lang/String;
  #185 = MethodHandle       6:#184        // REF_invokeStatic org/scalatest/freespec/AnyFreeSpecLike.$anonfun$registerIgnoredTestImpl$1:()Ljava/lang/String;
  #186 = InvokeDynamic      #1:#150       // #1:apply:()Lscala/Function0;
  #187 = Utf8               registerIgnoredTest
  #188 = String             #187          // registerIgnoredTest
  #189 = Utf8               (Ljava/lang/String;Ljava/lang/Object;Lscala/Function0;Ljava/lang/String;Ljava/lang/String;IILscala/Option;Lscala/Option;Lscala/collection/immutable/Seq;)V
  #190 = NameAndType        #187:#189     // registerIgnoredTest:(Ljava/lang/String;Ljava/lang/Object;Lscala/Function0;Ljava/lang/String;Ljava/lang/String;IILscala/Option;Lscala/Option;Lscala/collection/immutable/Seq;)V
  #191 = Methodref          #72.#190      // org/scalatest/Engine.registerIgnoredTest:(Ljava/lang/String;Ljava/lang/Object;Lscala/Function0;Ljava/lang/String;Ljava/lang/String;IILscala/Option;Lscala/Option;Lscala/collection/immutable/Seq;)V
  #192 = Utf8               registerIgnoredTest$
  #193 = NameAndType        #187:#120     // registerIgnoredTest:(Ljava/lang/String;Lscala/collection/immutable/Seq;Lscala/Function0;Lorg/scalactic/source/Position;)V
  #194 = InterfaceMethodref #2.#193       // org/scalatest/freespec/AnyFreeSpecLike.registerIgnoredTest:(Ljava/lang/String;Lscala/collection/immutable/Seq;Lscala/Function0;Lorg/scalactic/source/Position;)V
  #195 = NameAndType        #181:#120     // registerIgnoredTestImpl:(Ljava/lang/String;Lscala/collection/immutable/Seq;Lscala/Function0;Lorg/scalactic/source/Position;)V
  #196 = InterfaceMethodref #2.#195       // org/scalatest/freespec/AnyFreeSpecLike.registerIgnoredTestImpl:(Ljava/lang/String;Lscala/collection/immutable/Seq;Lscala/Function0;Lorg/scalactic/source/Position;)V
  #197 = Utf8               org$scalatest$freespec$AnyFreeSpecLike$$registerTestToRun$
  #198 = Utf8               (Lorg/scalatest/freespec/AnyFreeSpecLike;Ljava/lang/String;Lscala/collection/immutable/List;Ljava/lang/String;Lscala/Function0;Lorg/scalactic/source/Position;)V
  #199 = Utf8               specText
  #200 = Utf8               methodName
  #201 = Utf8               org$scalatest$freespec$AnyFreeSpecLike$$registerTestToRun
  #202 = Utf8               (Ljava/lang/String;Lscala/collection/immutable/List;Ljava/lang/String;Lscala/Function0;Lorg/scalactic/source/Position;)V
  #203 = NameAndType        #201:#202     // org$scalatest$freespec$AnyFreeSpecLike$$registerTestToRun:(Ljava/lang/String;Lscala/collection/immutable/List;Ljava/lang/String;Lscala/Function0;Lorg/scalactic/source/Position;)V
  #204 = InterfaceMethodref #2.#203       // org/scalatest/freespec/AnyFreeSpecLike.org$scalatest$freespec$AnyFreeSpecLike$$registerTestToRun:(Ljava/lang/String;Lscala/collection/immutable/List;Ljava/lang/String;Lscala/Function0;Lorg/scalactic/source/Position;)V
  #205 = Utf8               Lscala/collection/immutable/List;
  #206 = Utf8               (Ljava/lang/String;Lscala/collection/immutable/List<Lorg/scalatest/Tag;>;Ljava/lang/String;Lscala/Function0<Ljava/lang/Object;>;Lorg/scalactic/source/Position;)V
  #207 = Utf8               $anonfun$registerTestToRun$1
  #208 = NameAndType        #207:#134     // $anonfun$registerTestToRun$1:()Ljava/lang/String;
  #209 = InterfaceMethodref #2.#208       // org/scalatest/freespec/AnyFreeSpecLike.$anonfun$registerTestToRun$1:()Ljava/lang/String;
  #210 = MethodHandle       6:#209        // REF_invokeStatic org/scalatest/freespec/AnyFreeSpecLike.$anonfun$registerTestToRun$1:()Ljava/lang/String;
  #211 = InvokeDynamic      #2:#150       // #2:apply:()Lscala/Function0;
  #212 = Utf8               stackDepth
  #213 = Utf8               org$scalatest$freespec$AnyFreeSpecLike$$registerTestToIgnore$
  #214 = Utf8               org$scalatest$freespec$AnyFreeSpecLike$$registerTestToIgnore
  #215 = NameAndType        #214:#202     // org$scalatest$freespec$AnyFreeSpecLike$$registerTestToIgnore:(Ljava/lang/String;Lscala/collection/immutable/List;Ljava/lang/String;Lscala/Function0;Lorg/scalactic/source/Position;)V
  #216 = InterfaceMethodref #2.#215       // org/scalatest/freespec/AnyFreeSpecLike.org$scalatest$freespec$AnyFreeSpecLike$$registerTestToIgnore:(Ljava/lang/String;Lscala/collection/immutable/List;Ljava/lang/String;Lscala/Function0;Lorg/scalactic/source/Position;)V
  #217 = Utf8               $anonfun$registerTestToIgnore$1
  #218 = NameAndType        #217:#134     // $anonfun$registerTestToIgnore$1:()Ljava/lang/String;
  #219 = InterfaceMethodref #2.#218       // org/scalatest/freespec/AnyFreeSpecLike.$anonfun$registerTestToIgnore$1:()Ljava/lang/String;
  #220 = MethodHandle       6:#219        // REF_invokeStatic org/scalatest/freespec/AnyFreeSpecLike.$anonfun$registerTestToIgnore$1:()Ljava/lang/String;
  #221 = InvokeDynamic      #3:#150       // #3:apply:()Lscala/Function0;
  #222 = Utf8               convertToFreeSpecStringWrapper$
  #223 = Utf8               (Lorg/scalatest/freespec/AnyFreeSpecLike;Ljava/lang/String;Lorg/scalactic/source/Position;)Lorg/scalatest/freespec/AnyFreeSpecLike$FreeSpecStringWrapper;
  #224 = Utf8               s
  #225 = Utf8               convertToFreeSpecStringWrapper
  #226 = Utf8               (Ljava/lang/String;Lorg/scalactic/source/Position;)Lorg/scalatest/freespec/AnyFreeSpecLike$FreeSpecStringWrapper;
  #227 = NameAndType        #225:#226     // convertToFreeSpecStringWrapper:(Ljava/lang/String;Lorg/scalactic/source/Position;)Lorg/scalatest/freespec/AnyFreeSpecLike$FreeSpecStringWrapper;
  #228 = InterfaceMethodref #2.#227       // org/scalatest/freespec/AnyFreeSpecLike.convertToFreeSpecStringWrapper:(Ljava/lang/String;Lorg/scalactic/source/Position;)Lorg/scalatest/freespec/AnyFreeSpecLike$FreeSpecStringWrapper;
  #229 = Utf8               (Lorg/scalatest/freespec/AnyFreeSpecLike;Ljava/lang/String;Lorg/scalactic/source/Position;)V
  #230 = NameAndType        #128:#229     // "<init>":(Lorg/scalatest/freespec/AnyFreeSpecLike;Ljava/lang/String;Lorg/scalactic/source/Position;)V
  #231 = Methodref          #43.#230      // org/scalatest/freespec/AnyFreeSpecLike$FreeSpecStringWrapper."<init>":(Lorg/scalatest/freespec/AnyFreeSpecLike;Ljava/lang/String;Lorg/scalactic/source/Position;)V
  #232 = Utf8               tags$
  #233 = Utf8               (Lorg/scalatest/freespec/AnyFreeSpecLike;)Lscala/collection/immutable/Map;
  #234 = Utf8               tags
  #235 = Utf8               ()Lscala/collection/immutable/Map;
  #236 = NameAndType        #234:#235     // tags:()Lscala/collection/immutable/Map;
  #237 = InterfaceMethodref #2.#236       // org/scalatest/freespec/AnyFreeSpecLike.tags:()Lscala/collection/immutable/Map;
  #238 = Utf8               ()Lscala/collection/immutable/Map<Ljava/lang/String;Lscala/collection/immutable/Set<Ljava/lang/String;>;>;
  #239 = Utf8               org/scalatest/Suite$
  #240 = Class              #239          // org/scalatest/Suite$
  #241 = Utf8               Lorg/scalatest/Suite$;
  #242 = NameAndType        #157:#241     // MODULE$:Lorg/scalatest/Suite$;
  #243 = Fieldref           #240.#242     // org/scalatest/Suite$.MODULE$:Lorg/scalatest/Suite$;
  #244 = Utf8               atomic
  #245 = NameAndType        #244:#74      // atomic:()Ljava/util/concurrent/atomic/AtomicReference;
  #246 = Methodref          #72.#245      // org/scalatest/Engine.atomic:()Ljava/util/concurrent/atomic/AtomicReference;
  #247 = Utf8               tagsMap
  #248 = NameAndType        #247:#235     // tagsMap:()Lscala/collection/immutable/Map;
  #249 = Methodref          #30.#248      // org/scalatest/SuperEngine$Bundle.tagsMap:()Lscala/collection/immutable/Map;
  #250 = Utf8               autoTagClassAnnotations
  #251 = Utf8               (Lscala/collection/immutable/Map;Lorg/scalatest/Suite;)Lscala/collection/immutable/Map;
  #252 = NameAndType        #250:#251     // autoTagClassAnnotations:(Lscala/collection/immutable/Map;Lorg/scalatest/Suite;)Lscala/collection/immutable/Map;
  #253 = Methodref          #240.#252     // org/scalatest/Suite$.autoTagClassAnnotations:(Lscala/collection/immutable/Map;Lorg/scalatest/Suite;)Lscala/collection/immutable/Map;
  #254 = Utf8               runTest$
  #255 = Utf8               (Lorg/scalatest/freespec/AnyFreeSpecLike;Ljava/lang/String;Lorg/scalatest/Args;)Lorg/scalatest/Status;
  #256 = Utf8               runTest
  #257 = Utf8               (Ljava/lang/String;Lorg/scalatest/Args;)Lorg/scalatest/Status;
  #258 = NameAndType        #256:#257     // runTest:(Ljava/lang/String;Lorg/scalatest/Args;)Lorg/scalatest/Status;
  #259 = InterfaceMethodref #2.#258       // org/scalatest/freespec/AnyFreeSpecLike.runTest:(Ljava/lang/String;Lorg/scalatest/Args;)Lorg/scalatest/Status;
  #260 = Utf8               Lorg/scalatest/Args;
  #261 = Utf8               (Ljava/lang/Object;)Ljava/lang/Object;
  #262 = MethodType         #261          //  (Ljava/lang/Object;)Ljava/lang/Object;
  #263 = Utf8               $anonfun$runTest$1
  #264 = Utf8               (Lorg/scalatest/freespec/AnyFreeSpecLike;Lorg/scalatest/Args;Ljava/lang/String;Lorg/scalatest/SuperEngine$TestLeaf;)Lorg/scalatest/Outcome;
  #265 = NameAndType        #263:#264     // $anonfun$runTest$1:(Lorg/scalatest/freespec/AnyFreeSpecLike;Lorg/scalatest/Args;Ljava/lang/String;Lorg/scalatest/SuperEngine$TestLeaf;)Lorg/scalatest/Outcome;
  #266 = InterfaceMethodref #2.#265       // org/scalatest/freespec/AnyFreeSpecLike.$anonfun$runTest$1:(Lorg/scalatest/freespec/AnyFreeSpecLike;Lorg/scalatest/Args;Ljava/lang/String;Lorg/scalatest/SuperEngine$TestLeaf;)Lorg/scalatest/Outcome;
  #267 = MethodHandle       6:#266        // REF_invokeStatic org/scalatest/freespec/AnyFreeSpecLike.$anonfun$runTest$1:(Lorg/scalatest/freespec/AnyFreeSpecLike;Lorg/scalatest/Args;Ljava/lang/String;Lorg/scalatest/SuperEngine$TestLeaf;)Lorg/scalatest/Outcome;
  #268 = Utf8               (Lorg/scalatest/SuperEngine$TestLeaf;)Lorg/scalatest/Outcome;
  #269 = MethodType         #268          //  (Lorg/scalatest/SuperEngine$TestLeaf;)Lorg/scalatest/Outcome;
  #270 = Utf8               (Lorg/scalatest/freespec/AnyFreeSpecLike;Lorg/scalatest/Args;Ljava/lang/String;)Lscala/Function1;
  #271 = NameAndType        #148:#270     // apply:(Lorg/scalatest/freespec/AnyFreeSpecLike;Lorg/scalatest/Args;Ljava/lang/String;)Lscala/Function1;
  #272 = InvokeDynamic      #4:#271       // #4:apply:(Lorg/scalatest/freespec/AnyFreeSpecLike;Lorg/scalatest/Args;Ljava/lang/String;)Lscala/Function1;
  #273 = Utf8               runTestImpl
  #274 = Utf8               (Lorg/scalatest/Suite;Ljava/lang/String;Lorg/scalatest/Args;ZLscala/Function1;)Lorg/scalatest/Status;
  #275 = NameAndType        #273:#274     // runTestImpl:(Lorg/scalatest/Suite;Ljava/lang/String;Lorg/scalatest/Args;ZLscala/Function1;)Lorg/scalatest/Status;
  #276 = Methodref          #72.#275      // org/scalatest/Engine.runTestImpl:(Lorg/scalatest/Suite;Ljava/lang/String;Lorg/scalatest/Args;ZLscala/Function1;)Lorg/scalatest/Status;
  #277 = Utf8               runTests$
  #278 = Utf8               (Lorg/scalatest/freespec/AnyFreeSpecLike;Lscala/Option;Lorg/scalatest/Args;)Lorg/scalatest/Status;
  #279 = Utf8               runTests
  #280 = NameAndType        #279:#56      // runTests:(Lscala/Option;Lorg/scalatest/Args;)Lorg/scalatest/Status;
  #281 = InterfaceMethodref #2.#280       // org/scalatest/freespec/AnyFreeSpecLike.runTests:(Lscala/Option;Lorg/scalatest/Args;)Lorg/scalatest/Status;
  #282 = Utf8               Lscala/Option;
  #283 = Utf8               (Lscala/Option<Ljava/lang/String;>;Lorg/scalatest/Args;)Lorg/scalatest/Status;
  #284 = Utf8               (Ljava/lang/Object;Ljava/lang/Object;)Ljava/lang/Object;
  #285 = MethodType         #284          //  (Ljava/lang/Object;Ljava/lang/Object;)Ljava/lang/Object;
  #286 = Utf8               $anonfun$runTests$1
  #287 = NameAndType        #286:#255     // $anonfun$runTests$1:(Lorg/scalatest/freespec/AnyFreeSpecLike;Ljava/lang/String;Lorg/scalatest/Args;)Lorg/scalatest/Status;
  #288 = InterfaceMethodref #2.#287       // org/scalatest/freespec/AnyFreeSpecLike.$anonfun$runTests$1:(Lorg/scalatest/freespec/AnyFreeSpecLike;Ljava/lang/String;Lorg/scalatest/Args;)Lorg/scalatest/Status;
  #289 = MethodHandle       6:#288        // REF_invokeStatic org/scalatest/freespec/AnyFreeSpecLike.$anonfun$runTests$1:(Lorg/scalatest/freespec/AnyFreeSpecLike;Ljava/lang/String;Lorg/scalatest/Args;)Lorg/scalatest/Status;
  #290 = MethodType         #257          //  (Ljava/lang/String;Lorg/scalatest/Args;)Lorg/scalatest/Status;
  #291 = Utf8               (Lorg/scalatest/freespec/AnyFreeSpecLike;)Lscala/Function2;
  #292 = NameAndType        #148:#291     // apply:(Lorg/scalatest/freespec/AnyFreeSpecLike;)Lscala/Function2;
  #293 = InvokeDynamic      #5:#292       // #5:apply:(Lorg/scalatest/freespec/AnyFreeSpecLike;)Lscala/Function2;
  #294 = Utf8               runTestsImpl
  #295 = Utf8               (Lorg/scalatest/Suite;Lscala/Option;Lorg/scalatest/Args;Lorg/scalatest/Informer;ZLscala/Function2;)Lorg/scalatest/Status;
  #296 = NameAndType        #294:#295     // runTestsImpl:(Lorg/scalatest/Suite;Lscala/Option;Lorg/scalatest/Args;Lorg/scalatest/Informer;ZLscala/Function2;)Lorg/scalatest/Status;
  #297 = Methodref          #72.#296      // org/scalatest/Engine.runTestsImpl:(Lorg/scalatest/Suite;Lscala/Option;Lorg/scalatest/Args;Lorg/scalatest/Informer;ZLscala/Function2;)Lorg/scalatest/Status;
  #298 = Utf8               testNames$
  #299 = Utf8               (Lorg/scalatest/freespec/AnyFreeSpecLike;)Lscala/collection/immutable/Set;
  #300 = Utf8               testNames
  #301 = Utf8               ()Lscala/collection/immutable/Set;
  #302 = NameAndType        #300:#301     // testNames:()Lscala/collection/immutable/Set;
  #303 = InterfaceMethodref #2.#302       // org/scalatest/freespec/AnyFreeSpecLike.testNames:()Lscala/collection/immutable/Set;
  #304 = Utf8               ()Lscala/collection/immutable/Set<Ljava/lang/String;>;
  #305 = Utf8               org/scalatest/InsertionOrderSet$
  #306 = Class              #305          // org/scalatest/InsertionOrderSet$
  #307 = Utf8               Lorg/scalatest/InsertionOrderSet$;
  #308 = NameAndType        #157:#307     // MODULE$:Lorg/scalatest/InsertionOrderSet$;
  #309 = Fieldref           #306.#308     // org/scalatest/InsertionOrderSet$.MODULE$:Lorg/scalatest/InsertionOrderSet$;
  #310 = Utf8               testNamesList
  #311 = Utf8               ()Lscala/collection/immutable/List;
  #312 = NameAndType        #310:#311     // testNamesList:()Lscala/collection/immutable/List;
  #313 = Methodref          #30.#312      // org/scalatest/SuperEngine$Bundle.testNamesList:()Lscala/collection/immutable/List;
  #314 = Utf8               (Lscala/collection/immutable/List;)Lscala/collection/immutable/Set;
  #315 = NameAndType        #148:#314     // apply:(Lscala/collection/immutable/List;)Lscala/collection/immutable/Set;
  #316 = Methodref          #306.#315     // org/scalatest/InsertionOrderSet$.apply:(Lscala/collection/immutable/List;)Lscala/collection/immutable/Set;
  #317 = Utf8               run$
  #318 = Utf8               run
  #319 = NameAndType        #318:#56      // run:(Lscala/Option;Lorg/scalatest/Args;)Lorg/scalatest/Status;
  #320 = InterfaceMethodref #2.#319       // org/scalatest/freespec/AnyFreeSpecLike.run:(Lscala/Option;Lorg/scalatest/Args;)Lorg/scalatest/Status;
  #321 = Utf8               $anonfun$run$1
  #322 = NameAndType        #321:#278     // $anonfun$run$1:(Lorg/scalatest/freespec/AnyFreeSpecLike;Lscala/Option;Lorg/scalatest/Args;)Lorg/scalatest/Status;
  #323 = InterfaceMethodref #2.#322       // org/scalatest/freespec/AnyFreeSpecLike.$anonfun$run$1:(Lorg/scalatest/freespec/AnyFreeSpecLike;Lscala/Option;Lorg/scalatest/Args;)Lorg/scalatest/Status;
  #324 = MethodHandle       6:#323        // REF_invokeStatic org/scalatest/freespec/AnyFreeSpecLike.$anonfun$run$1:(Lorg/scalatest/freespec/AnyFreeSpecLike;Lscala/Option;Lorg/scalatest/Args;)Lorg/scalatest/Status;
  #325 = MethodType         #56           //  (Lscala/Option;Lorg/scalatest/Args;)Lorg/scalatest/Status;
  #326 = InvokeDynamic      #6:#292       // #6:apply:(Lorg/scalatest/freespec/AnyFreeSpecLike;)Lscala/Function2;
  #327 = Utf8               runImpl
  #328 = Utf8               (Lorg/scalatest/Suite;Lscala/Option;Lorg/scalatest/Args;Lscala/Function2;)Lorg/scalatest/Status;
  #329 = NameAndType        #327:#328     // runImpl:(Lorg/scalatest/Suite;Lscala/Option;Lorg/scalatest/Args;Lscala/Function2;)Lorg/scalatest/Status;
  #330 = Methodref          #72.#329      // org/scalatest/Engine.runImpl:(Lorg/scalatest/Suite;Lscala/Option;Lorg/scalatest/Args;Lscala/Function2;)Lorg/scalatest/Status;
  #331 = Utf8               behave
  #332 = Utf8               ()Lorg/scalatest/verbs/BehaveWord;
  #333 = Utf8               styleName
  #334 = Utf8               testDataFor$
  #335 = Utf8               (Lorg/scalatest/freespec/AnyFreeSpecLike;Ljava/lang/String;Lorg/scalatest/ConfigMap;)Lorg/scalatest/TestData;
  #336 = Utf8               theConfigMap
  #337 = Utf8               testDataFor
  #338 = Utf8               (Ljava/lang/String;Lorg/scalatest/ConfigMap;)Lorg/scalatest/TestData;
  #339 = NameAndType        #337:#338     // testDataFor:(Ljava/lang/String;Lorg/scalatest/ConfigMap;)Lorg/scalatest/TestData;
  #340 = InterfaceMethodref #2.#339       // org/scalatest/freespec/AnyFreeSpecLike.testDataFor:(Ljava/lang/String;Lorg/scalatest/ConfigMap;)Lorg/scalatest/TestData;
  #341 = Utf8               Lorg/scalatest/ConfigMap;
  #342 = Utf8               createTestDataFor
  #343 = Utf8               (Ljava/lang/String;Lorg/scalatest/ConfigMap;Lorg/scalatest/Suite;)Lorg/scalatest/TestData;
  #344 = NameAndType        #342:#343     // createTestDataFor:(Ljava/lang/String;Lorg/scalatest/ConfigMap;Lorg/scalatest/Suite;)Lorg/scalatest/TestData;
  #345 = Methodref          #72.#344      // org/scalatest/Engine.createTestDataFor:(Ljava/lang/String;Lorg/scalatest/ConfigMap;Lorg/scalatest/Suite;)Lorg/scalatest/TestData;
  #346 = Utf8               testDataFor$default$2$
  #347 = Utf8               (Lorg/scalatest/freespec/AnyFreeSpecLike;)Lorg/scalatest/ConfigMap;
  #348 = Utf8               testDataFor$default$2
  #349 = Utf8               ()Lorg/scalatest/ConfigMap;
  #350 = NameAndType        #348:#349     // testDataFor$default$2:()Lorg/scalatest/ConfigMap;
  #351 = InterfaceMethodref #2.#350       // org/scalatest/freespec/AnyFreeSpecLike.testDataFor$default$2:()Lorg/scalatest/ConfigMap;
  #352 = Utf8               org/scalatest/ConfigMap$
  #353 = Class              #352          // org/scalatest/ConfigMap$
  #354 = Utf8               Lorg/scalatest/ConfigMap$;
  #355 = NameAndType        #157:#354     // MODULE$:Lorg/scalatest/ConfigMap$;
  #356 = Fieldref           #353.#355     // org/scalatest/ConfigMap$.MODULE$:Lorg/scalatest/ConfigMap$;
  #357 = Utf8               empty
  #358 = NameAndType        #357:#349     // empty:()Lorg/scalatest/ConfigMap;
  #359 = Methodref          #353.#358     // org/scalatest/ConfigMap$.empty:()Lorg/scalatest/ConfigMap;
  #360 = Utf8               $anonfun$engine$1
  #361 = Utf8               org/scalatest/Resources$
  #362 = Class              #361          // org/scalatest/Resources$
  #363 = Utf8               Lorg/scalatest/Resources$;
  #364 = NameAndType        #157:#363     // MODULE$:Lorg/scalatest/Resources$;
  #365 = Fieldref           #362.#364     // org/scalatest/Resources$.MODULE$:Lorg/scalatest/Resources$;
  #366 = Utf8               concurrentFreeSpecMod
  #367 = NameAndType        #366:#134     // concurrentFreeSpecMod:()Ljava/lang/String;
  #368 = Methodref          #362.#367     // org/scalatest/Resources$.concurrentFreeSpecMod:()Ljava/lang/String;
  #369 = Utf8               testCannotBeNestedInsideAnotherTest
  #370 = NameAndType        #369:#134     // testCannotBeNestedInsideAnotherTest:()Ljava/lang/String;
  #371 = Methodref          #362.#370     // org/scalatest/Resources$.testCannotBeNestedInsideAnotherTest:()Ljava/lang/String;
  #372 = Utf8               inCannotAppearInsideAnotherIn
  #373 = NameAndType        #372:#134     // inCannotAppearInsideAnotherIn:()Ljava/lang/String;
  #374 = Methodref          #362.#373     // org/scalatest/Resources$.inCannotAppearInsideAnotherIn:()Ljava/lang/String;
  #375 = Utf8               ignoreCannotAppearInsideAnIn
  #376 = NameAndType        #375:#134     // ignoreCannotAppearInsideAnIn:()Ljava/lang/String;
  #377 = Methodref          #362.#376     // org/scalatest/Resources$.ignoreCannotAppearInsideAnIn:()Ljava/lang/String;
  #378 = Utf8               invokeWithFixture$1
  #379 = Utf8               (Lorg/scalatest/SuperEngine$TestLeaf;Lorg/scalatest/Args;Ljava/lang/String;)Lorg/scalatest/Outcome;
  #380 = Utf8               theTest
  #381 = Utf8               args$1
  #382 = Utf8               testName$1
  #383 = Utf8               org/scalatest/Args
  #384 = Class              #383          // org/scalatest/Args
  #385 = Utf8               configMap
  #386 = NameAndType        #385:#349     // configMap:()Lorg/scalatest/ConfigMap;
  #387 = Methodref          #384.#386     // org/scalatest/Args.configMap:()Lorg/scalatest/ConfigMap;
  #388 = Utf8               (Lorg/scalatest/freespec/AnyFreeSpecLike;Lorg/scalatest/TestData;Lorg/scalatest/SuperEngine$TestLeaf;)V
  #389 = NameAndType        #128:#388     // "<init>":(Lorg/scalatest/freespec/AnyFreeSpecLike;Lorg/scalatest/TestData;Lorg/scalatest/SuperEngine$TestLeaf;)V
  #390 = Methodref          #41.#389      // org/scalatest/freespec/AnyFreeSpecLike$$anon$1."<init>":(Lorg/scalatest/freespec/AnyFreeSpecLike;Lorg/scalatest/TestData;Lorg/scalatest/SuperEngine$TestLeaf;)V
  #391 = Utf8               withFixture
  #392 = Utf8               (Lorg/scalatest/TestSuite$NoArgTest;)Lorg/scalatest/Outcome;
  #393 = NameAndType        #391:#392     // withFixture:(Lorg/scalatest/TestSuite$NoArgTest;)Lorg/scalatest/Outcome;
  #394 = InterfaceMethodref #2.#393       // org/scalatest/freespec/AnyFreeSpecLike.withFixture:(Lorg/scalatest/TestSuite$NoArgTest;)Lorg/scalatest/Outcome;
  #395 = Utf8               testData
  #396 = Utf8               Lorg/scalatest/TestData;
  #397 = Utf8               Lorg/scalatest/SuperEngine$TestLeaf;
  #398 = NameAndType        #378:#379     // invokeWithFixture$1:(Lorg/scalatest/SuperEngine$TestLeaf;Lorg/scalatest/Args;Ljava/lang/String;)Lorg/scalatest/Outcome;
  #399 = InterfaceMethodref #2.#398       // org/scalatest/freespec/AnyFreeSpecLike.invokeWithFixture$1:(Lorg/scalatest/SuperEngine$TestLeaf;Lorg/scalatest/Args;Ljava/lang/String;)Lorg/scalatest/Outcome;
  #400 = NameAndType        #55:#56       // org$scalatest$freespec$AnyFreeSpecLike$$super$run:(Lscala/Option;Lorg/scalatest/Args;)Lorg/scalatest/Status;
  #401 = InterfaceMethodref #2.#400       // org/scalatest/freespec/AnyFreeSpecLike.org$scalatest$freespec$AnyFreeSpecLike$$super$run:(Lscala/Option;Lorg/scalatest/Args;)Lorg/scalatest/Status;
  #402 = Utf8               $init$
  #403 = Utf8               (Lorg/scalatest/freespec/AnyFreeSpecLike;)V
  #404 = NameAndType        #360:#134     // $anonfun$engine$1:()Ljava/lang/String;
  #405 = InterfaceMethodref #2.#404       // org/scalatest/freespec/AnyFreeSpecLike.$anonfun$engine$1:()Ljava/lang/String;
  #406 = MethodHandle       6:#405        // REF_invokeStatic org/scalatest/freespec/AnyFreeSpecLike.$anonfun$engine$1:()Ljava/lang/String;
  #407 = InvokeDynamic      #7:#150       // #7:apply:()Lscala/Function0;
  #408 = Utf8               FreeSpec
  #409 = String             #408          // FreeSpec
  #410 = Utf8               (Lscala/Function0;Ljava/lang/String;)V
  #411 = NameAndType        #128:#410     // "<init>":(Lscala/Function0;Ljava/lang/String;)V
  #412 = Methodref          #72.#411      // org/scalatest/Engine."<init>":(Lscala/Function0;Ljava/lang/String;)V
  #413 = NameAndType        #48:#49       // org$scalatest$freespec$AnyFreeSpecLike$_setter_$org$scalatest$freespec$AnyFreeSpecLike$$engine_$eq:(Lorg/scalatest/Engine;)V
  #414 = InterfaceMethodref #2.#413       // org/scalatest/freespec/AnyFreeSpecLike.org$scalatest$freespec$AnyFreeSpecLike$_setter_$org$scalatest$freespec$AnyFreeSpecLike$$engine_$eq:(Lorg/scalatest/Engine;)V
  #415 = Utf8               org/scalatest/verbs/BehaveWord
  #416 = Class              #415          // org/scalatest/verbs/BehaveWord
  #417 = Utf8               ()V
  #418 = NameAndType        #128:#417     // "<init>":()V
  #419 = Methodref          #416.#418     // org/scalatest/verbs/BehaveWord."<init>":()V
  #420 = NameAndType        #51:#52       // org$scalatest$freespec$AnyFreeSpecLike$_setter_$behave_$eq:(Lorg/scalatest/verbs/BehaveWord;)V
  #421 = InterfaceMethodref #2.#420       // org/scalatest/freespec/AnyFreeSpecLike.org$scalatest$freespec$AnyFreeSpecLike$_setter_$behave_$eq:(Lorg/scalatest/verbs/BehaveWord;)V
  #422 = Utf8               org.scalatest.FreeSpec
  #423 = String             #422          // org.scalatest.FreeSpec
  #424 = NameAndType        #53:#54       // org$scalatest$freespec$AnyFreeSpecLike$_setter_$styleName_$eq:(Ljava/lang/String;)V
  #425 = InterfaceMethodref #2.#424       // org/scalatest/freespec/AnyFreeSpecLike.org$scalatest$freespec$AnyFreeSpecLike$_setter_$styleName_$eq:(Ljava/lang/String;)V
  #426 = Utf8               $deserializeLambda$
  #427 = Utf8               (Ljava/lang/invoke/SerializedLambda;)Ljava/lang/Object;
  #428 = Utf8               scala/runtime/LambdaDeserialize
  #429 = Class              #428          // scala/runtime/LambdaDeserialize
  #430 = Utf8               bootstrap
  #431 = Utf8               (Ljava/lang/invoke/MethodHandles$Lookup;Ljava/lang/String;Ljava/lang/invoke/MethodType;[Ljava/lang/invoke/MethodHandle;)Ljava/lang/invoke/CallSite;
  #432 = NameAndType        #430:#431     // bootstrap:(Ljava/lang/invoke/MethodHandles$Lookup;Ljava/lang/String;Ljava/lang/invoke/MethodType;[Ljava/lang/invoke/MethodHandle;)Ljava/lang/invoke/CallSite;
  #433 = Methodref          #429.#432     // scala/runtime/LambdaDeserialize.bootstrap:(Ljava/lang/invoke/MethodHandles$Lookup;Ljava/lang/String;Ljava/lang/invoke/MethodType;[Ljava/lang/invoke/MethodHandle;)Ljava/lang/invoke/CallSite;
  #434 = MethodHandle       6:#433        // REF_invokeStatic scala/runtime/LambdaDeserialize.bootstrap:(Ljava/lang/invoke/MethodHandles$Lookup;Ljava/lang/String;Ljava/lang/invoke/MethodType;[Ljava/lang/invoke/MethodHandle;)Ljava/lang/invoke/CallSite;
  #435 = Utf8               lambdaDeserialize
  #436 = NameAndType        #435:#427     // lambdaDeserialize:(Ljava/lang/invoke/SerializedLambda;)Ljava/lang/Object;
  #437 = InvokeDynamic      #8:#436       // #8:lambdaDeserialize:(Ljava/lang/invoke/SerializedLambda;)Ljava/lang/Object;
  #438 = Utf8               MethodParameters
  #439 = Utf8               Code
  #440 = Utf8               LineNumberTable
  #441 = Utf8               LocalVariableTable
  #442 = Utf8               Signature
  #443 = Utf8               Deprecated
  #444 = Utf8               InnerClasses
  #445 = Utf8               SourceFile
  #446 = Utf8               RuntimeVisibleAnnotations
  #447 = Utf8               BootstrapMethods
  #448 = Utf8               ScalaInlineInfo
  #449 = Utf8               ScalaSig
{
  public abstract void org$scalatest$freespec$AnyFreeSpecLike$_setter_$org$scalatest$freespec$AnyFreeSpecLike$$engine_$eq(org.scalatest.Engine);
    descriptor: (Lorg/scalatest/Engine;)V
    flags: (0x0401) ACC_PUBLIC, ACC_ABSTRACT
    MethodParameters:
      Name                           Flags
      x$1                            final

  public abstract void org$scalatest$freespec$AnyFreeSpecLike$_setter_$behave_$eq(org.scalatest.verbs.BehaveWord);
    descriptor: (Lorg/scalatest/verbs/BehaveWord;)V
    flags: (0x0401) ACC_PUBLIC, ACC_ABSTRACT
    MethodParameters:
      Name                           Flags
      x$1                            final

  public abstract void org$scalatest$freespec$AnyFreeSpecLike$_setter_$styleName_$eq(java.lang.String);
    descriptor: (Ljava/lang/String;)V
    flags: (0x0401) ACC_PUBLIC, ACC_ABSTRACT
    MethodParameters:
      Name                           Flags
      x$1                            final

  public abstract org.scalatest.Status org$scalatest$freespec$AnyFreeSpecLike$$super$run(scala.Option, org.scalatest.Args);
    descriptor: (Lscala/Option;Lorg/scalatest/Args;)Lorg/scalatest/Status;
    flags: (0x1401) ACC_PUBLIC, ACC_ABSTRACT, ACC_SYNTHETIC
    MethodParameters:
      Name                           Flags
      testName                       final
      args                           final

  public abstract org.scalatest.Engine org$scalatest$freespec$AnyFreeSpecLike$$engine();
    descriptor: ()Lorg/scalatest/Engine;
    flags: (0x0401) ACC_PUBLIC, ACC_ABSTRACT

  public static org.scalatest.Informer info$(org.scalatest.freespec.AnyFreeSpecLike);
    descriptor: (Lorg/scalatest/freespec/AnyFreeSpecLike;)Lorg/scalatest/Informer;
    flags: (0x1009) ACC_PUBLIC, ACC_STATIC, ACC_SYNTHETIC
    Code:
      stack=1, locals=1, args_size=1
         0: aload_0
         1: invokespecial #67                 // InterfaceMethod info:()Lorg/scalatest/Informer;
         4: areturn
      LineNumberTable:
        line 63: 0
      LocalVariableTable:
        Start  Length  Slot  Name   Signature
            0       5     0 $this   Lorg/scalatest/freespec/AnyFreeSpecLike;
    MethodParameters:
      Name                           Flags
      $this                          final synthetic

  public default org.scalatest.Informer info();
    descriptor: ()Lorg/scalatest/Informer;
    flags: (0x0001) ACC_PUBLIC
    Code:
      stack=1, locals=1, args_size=1
         0: aload_0
         1: invokeinterface #70,  1           // InterfaceMethod org$scalatest$freespec$AnyFreeSpecLike$$engine:()Lorg/scalatest/Engine;
         6: invokevirtual #76                 // Method org/scalatest/Engine.atomicInformer:()Ljava/util/concurrent/atomic/AtomicReference;
         9: invokevirtual #82                 // Method java/util/concurrent/atomic/AtomicReference.get:()Ljava/lang/Object;
        12: checkcast     #84                 // class org/scalatest/Informer
        15: areturn
      LineNumberTable:
        line 63: 0
      LocalVariableTable:
        Start  Length  Slot  Name   Signature
            0      16     0  this   Lorg/scalatest/freespec/AnyFreeSpecLike;

  public static org.scalatest.Notifier note$(org.scalatest.freespec.AnyFreeSpecLike);
    descriptor: (Lorg/scalatest/freespec/AnyFreeSpecLike;)Lorg/scalatest/Notifier;
    flags: (0x1009) ACC_PUBLIC, ACC_STATIC, ACC_SYNTHETIC
    Code:
      stack=1, locals=1, args_size=1
         0: aload_0
         1: invokespecial #91                 // InterfaceMethod note:()Lorg/scalatest/Notifier;
         4: areturn
      LineNumberTable:
        line 73: 0
      LocalVariableTable:
        Start  Length  Slot  Name   Signature
            0       5     0 $this   Lorg/scalatest/freespec/AnyFreeSpecLike;
    MethodParameters:
      Name                           Flags
      $this                          final synthetic

  public default org.scalatest.Notifier note();
    descriptor: ()Lorg/scalatest/Notifier;
    flags: (0x0001) ACC_PUBLIC
    Code:
      stack=1, locals=1, args_size=1
         0: aload_0
         1: invokeinterface #70,  1           // InterfaceMethod org$scalatest$freespec$AnyFreeSpecLike$$engine:()Lorg/scalatest/Engine;
         6: invokevirtual #94                 // Method org/scalatest/Engine.atomicNotifier:()Ljava/util/concurrent/atomic/AtomicReference;
         9: invokevirtual #82                 // Method java/util/concurrent/atomic/AtomicReference.get:()Ljava/lang/Object;
        12: checkcast     #96                 // class org/scalatest/Notifier
        15: areturn
      LineNumberTable:
        line 73: 0
      LocalVariableTable:
        Start  Length  Slot  Name   Signature
            0      16     0  this   Lorg/scalatest/freespec/AnyFreeSpecLike;

  public static org.scalatest.Alerter alert$(org.scalatest.freespec.AnyFreeSpecLike);
    descriptor: (Lorg/scalatest/freespec/AnyFreeSpecLike;)Lorg/scalatest/Alerter;
    flags: (0x1009) ACC_PUBLIC, ACC_STATIC, ACC_SYNTHETIC
    Code:
      stack=1, locals=1, args_size=1
         0: aload_0
         1: invokespecial #102                // InterfaceMethod alert:()Lorg/scalatest/Alerter;
         4: areturn
      LineNumberTable:
        line 83: 0
      LocalVariableTable:
        Start  Length  Slot  Name   Signature
            0       5     0 $this   Lorg/scalatest/freespec/AnyFreeSpecLike;
    MethodParameters:
      Name                           Flags
      $this                          final synthetic

  public default org.scalatest.Alerter alert();
    descriptor: ()Lorg/scalatest/Alerter;
    flags: (0x0001) ACC_PUBLIC
    Code:
      stack=1, locals=1, args_size=1
         0: aload_0
         1: invokeinterface #70,  1           // InterfaceMethod org$scalatest$freespec$AnyFreeSpecLike$$engine:()Lorg/scalatest/Engine;
         6: invokevirtual #105                // Method org/scalatest/Engine.atomicAlerter:()Ljava/util/concurrent/atomic/AtomicReference;
         9: invokevirtual #82                 // Method java/util/concurrent/atomic/AtomicReference.get:()Ljava/lang/Object;
        12: checkcast     #107                // class org/scalatest/Alerter
        15: areturn
      LineNumberTable:
        line 83: 0
      LocalVariableTable:
        Start  Length  Slot  Name   Signature
            0      16     0  this   Lorg/scalatest/freespec/AnyFreeSpecLike;

  public static org.scalatest.Documenter markup$(org.scalatest.freespec.AnyFreeSpecLike);
    descriptor: (Lorg/scalatest/freespec/AnyFreeSpecLike;)Lorg/scalatest/Documenter;
    flags: (0x1009) ACC_PUBLIC, ACC_STATIC, ACC_SYNTHETIC
    Code:
      stack=1, locals=1, args_size=1
         0: aload_0
         1: invokespecial #113                // InterfaceMethod markup:()Lorg/scalatest/Documenter;
         4: areturn
      LineNumberTable:
        line 94: 0
      LocalVariableTable:
        Start  Length  Slot  Name   Signature
            0       5     0 $this   Lorg/scalatest/freespec/AnyFreeSpecLike;
    MethodParameters:
      Name                           Flags
      $this                          final synthetic

  public default org.scalatest.Documenter markup();
    descriptor: ()Lorg/scalatest/Documenter;
    flags: (0x0001) ACC_PUBLIC
    Code:
      stack=1, locals=1, args_size=1
         0: aload_0
         1: invokeinterface #70,  1           // InterfaceMethod org$scalatest$freespec$AnyFreeSpecLike$$engine:()Lorg/scalatest/Engine;
         6: invokevirtual #116                // Method org/scalatest/Engine.atomicDocumenter:()Ljava/util/concurrent/atomic/AtomicReference;
         9: invokevirtual #82                 // Method java/util/concurrent/atomic/AtomicReference.get:()Ljava/lang/Object;
        12: checkcast     #118                // class org/scalatest/Documenter
        15: areturn
      LineNumberTable:
        line 94: 0
      LocalVariableTable:
        Start  Length  Slot  Name   Signature
            0      16     0  this   Lorg/scalatest/freespec/AnyFreeSpecLike;

  private void registerTestImpl(java.lang.String, scala.collection.immutable.Seq<org.scalatest.Tag>, scala.Function0<java.lang.Object>, org.scalactic.source.Position);
    descriptor: (Ljava/lang/String;Lscala/collection/immutable/Seq;Lscala/Function0;Lorg/scalactic/source/Position;)V
    flags: (0x0002) ACC_PRIVATE
    Code:
      stack=13, locals=6, args_size=5
         0: bipush        -2
         2: istore        5
         4: aload_0
         5: invokeinterface #70,  1           // InterfaceMethod org$scalatest$freespec$AnyFreeSpecLike$$engine:()Lorg/scalatest/Engine;
        10: aload_1
        11: new           #127                // class org/scalatest/Transformer
        14: dup
        15: aload_3
        16: invokespecial #131                // Method org/scalatest/Transformer."<init>":(Lscala/Function0;)V
        19: invokedynamic #151,  0            // InvokeDynamic #0:apply:()Lscala/Function0;
        24: ldc           #152                // String AnyFreeSpecLike.scala
        26: ldc           #154                // String registerTest
        28: iconst_5
        29: iload         5
        31: getstatic     #160                // Field scala/None$.MODULE$:Lscala/None$;
        34: getstatic     #160                // Field scala/None$.MODULE$:Lscala/None$;
        37: new           #162                // class scala/Some
        40: dup
        41: aload         4
        43: invokespecial #165                // Method scala/Some."<init>":(Ljava/lang/Object;)V
        46: getstatic     #160                // Field scala/None$.MODULE$:Lscala/None$;
        49: aload_2
        50: invokevirtual #168                // Method org/scalatest/Engine.registerTest:(Ljava/lang/String;Ljava/lang/Object;Lscala/Function0;Ljava/lang/String;Ljava/lang/String;IILscala/Option;Lscala/Option;Lscala/Option;Lscala/Option;Lscala/collection/immutable/Seq;)Ljava/lang/String;
        53: pop
        54: return
      LineNumberTable:
        line 98: 0
        line 101: 4
      LocalVariableTable:
        Start  Length  Slot  Name   Signature
            4      50     5 stackDepthAdjustment   I
            0      55     0  this   Lorg/scalatest/freespec/AnyFreeSpecLike;
            0      55     1 testText   Ljava/lang/String;
            0      55     2 testTags   Lscala/collection/immutable/Seq;
            0      55     3 testFun   Lscala/Function0;
            0      55     4   pos   Lorg/scalactic/source/Position;
    Signature: #121                         // (Ljava/lang/String;Lscala/collection/immutable/Seq<Lorg/scalatest/Tag;>;Lscala/Function0<Ljava/lang/Object;>;Lorg/scalactic/source/Position;)V
    MethodParameters:
      Name                           Flags
      testText                       final
      testTags                       final
      testFun                        final
      pos                            final

  public static void registerTest$(org.scalatest.freespec.AnyFreeSpecLike, java.lang.String, scala.collection.immutable.Seq, scala.Function0, org.scalactic.source.Position);
    descriptor: (Lorg/scalatest/freespec/AnyFreeSpecLike;Ljava/lang/String;Lscala/collection/immutable/Seq;Lscala/Function0;Lorg/scalactic/source/Position;)V
    flags: (0x1009) ACC_PUBLIC, ACC_STATIC, ACC_SYNTHETIC
    Code:
      stack=5, locals=5, args_size=5
         0: aload_0
         1: aload_1
         2: aload_2
         3: aload_3
         4: aload         4
         6: invokespecial #178                // InterfaceMethod registerTest:(Ljava/lang/String;Lscala/collection/immutable/Seq;Lscala/Function0;Lorg/scalactic/source/Position;)V
         9: return
      LineNumberTable:
        line 105: 0
      LocalVariableTable:
        Start  Length  Slot  Name   Signature
            0      10     0 $this   Lorg/scalatest/freespec/AnyFreeSpecLike;
            0      10     1 testText   Ljava/lang/String;
            0      10     2 testTags   Lscala/collection/immutable/Seq;
            0      10     3 testFun   Lscala/Function0;
            0      10     4   pos   Lorg/scalactic/source/Position;
    MethodParameters:
      Name                           Flags
      $this                          final synthetic
      testText                       final
      testTags                       final
      testFun                        final
      pos                            final

  public default void registerTest(java.lang.String, scala.collection.immutable.Seq<org.scalatest.Tag>, scala.Function0<java.lang.Object>, org.scalactic.source.Position);
    descriptor: (Ljava/lang/String;Lscala/collection/immutable/Seq;Lscala/Function0;Lorg/scalactic/source/Position;)V
    flags: (0x0001) ACC_PUBLIC
    Code:
      stack=5, locals=5, args_size=5
         0: aload_0
         1: aload_1
         2: aload_2
         3: aload_3
         4: aload         4
         6: invokespecial #180                // InterfaceMethod registerTestImpl:(Ljava/lang/String;Lscala/collection/immutable/Seq;Lscala/Function0;Lorg/scalactic/source/Position;)V
         9: return
      LineNumberTable:
        line 106: 0
      LocalVariableTable:
        Start  Length  Slot  Name   Signature
            0      10     0  this   Lorg/scalatest/freespec/AnyFreeSpecLike;
            0      10     1 testText   Ljava/lang/String;
            0      10     2 testTags   Lscala/collection/immutable/Seq;
            0      10     3 testFun   Lscala/Function0;
            0      10     4   pos   Lorg/scalactic/source/Position;
    Signature: #121                         // (Ljava/lang/String;Lscala/collection/immutable/Seq<Lorg/scalatest/Tag;>;Lscala/Function0<Ljava/lang/Object;>;Lorg/scalactic/source/Position;)V
    MethodParameters:
      Name                           Flags
      testText                       final
      testTags                       final
      testFun                        final
      pos                            final

  private void registerIgnoredTestImpl(java.lang.String, scala.collection.immutable.Seq<org.scalatest.Tag>, scala.Function0<java.lang.Object>, org.scalactic.source.Position);
    descriptor: (Ljava/lang/String;Lscala/collection/immutable/Seq;Lscala/Function0;Lorg/scalactic/source/Position;)V
    flags: (0x0002) ACC_PRIVATE
    Code:
      stack=12, locals=6, args_size=5
         0: bipush        -3
         2: istore        5
         4: aload_0
         5: invokeinterface #70,  1           // InterfaceMethod org$scalatest$freespec$AnyFreeSpecLike$$engine:()Lorg/scalatest/Engine;
        10: aload_1
        11: new           #127                // class org/scalatest/Transformer
        14: dup
        15: aload_3
        16: invokespecial #131                // Method org/scalatest/Transformer."<init>":(Lscala/Function0;)V
        19: invokedynamic #186,  0            // InvokeDynamic #1:apply:()Lscala/Function0;
        24: ldc           #152                // String AnyFreeSpecLike.scala
        26: ldc           #188                // String registerIgnoredTest
        28: iconst_4
        29: iload         5
        31: getstatic     #160                // Field scala/None$.MODULE$:Lscala/None$;
        34: new           #162                // class scala/Some
        37: dup
        38: aload         4
        40: invokespecial #165                // Method scala/Some."<init>":(Ljava/lang/Object;)V
        43: aload_2
        44: invokevirtual #191                // Method org/scalatest/Engine.registerIgnoredTest:(Ljava/lang/String;Ljava/lang/Object;Lscala/Function0;Ljava/lang/String;Ljava/lang/String;IILscala/Option;Lscala/Option;Lscala/collection/immutable/Seq;)V
        47: return
      LineNumberTable:
        line 115: 0
        line 118: 4
      LocalVariableTable:
        Start  Length  Slot  Name   Signature
            4      43     5 stackDepthAdjustment   I
            0      48     0  this   Lorg/scalatest/freespec/AnyFreeSpecLike;
            0      48     1 testText   Ljava/lang/String;
            0      48     2 testTags   Lscala/collection/immutable/Seq;
            0      48     3 testFun   Lscala/Function0;
            0      48     4   pos   Lorg/scalactic/source/Position;
    Signature: #121                         // (Ljava/lang/String;Lscala/collection/immutable/Seq<Lorg/scalatest/Tag;>;Lscala/Function0<Ljava/lang/Object;>;Lorg/scalactic/source/Position;)V
    MethodParameters:
      Name                           Flags
      testText                       final
      testTags                       final
      testFun                        final
      pos                            final

  public static void registerIgnoredTest$(org.scalatest.freespec.AnyFreeSpecLike, java.lang.String, scala.collection.immutable.Seq, scala.Function0, org.scalactic.source.Position);
    descriptor: (Lorg/scalatest/freespec/AnyFreeSpecLike;Ljava/lang/String;Lscala/collection/immutable/Seq;Lscala/Function0;Lorg/scalactic/source/Position;)V
    flags: (0x1009) ACC_PUBLIC, ACC_STATIC, ACC_SYNTHETIC
    Code:
      stack=5, locals=5, args_size=5
         0: aload_0
         1: aload_1
         2: aload_2
         3: aload_3
         4: aload         4
         6: invokespecial #194                // InterfaceMethod registerIgnoredTest:(Ljava/lang/String;Lscala/collection/immutable/Seq;Lscala/Function0;Lorg/scalactic/source/Position;)V
         9: return
      LineNumberTable:
        line 122: 0
      LocalVariableTable:
        Start  Length  Slot  Name   Signature
            0      10     0 $this   Lorg/scalatest/freespec/AnyFreeSpecLike;
            0      10     1 testText   Ljava/lang/String;
            0      10     2 testTags   Lscala/collection/immutable/Seq;
            0      10     3 testFun   Lscala/Function0;
            0      10     4   pos   Lorg/scalactic/source/Position;
    MethodParameters:
      Name                           Flags
      $this                          final synthetic
      testText                       final
      testTags                       final
      testFun                        final
      pos                            final

  public default void registerIgnoredTest(java.lang.String, scala.collection.immutable.Seq<org.scalatest.Tag>, scala.Function0<java.lang.Object>, org.scalactic.source.Position);
    descriptor: (Ljava/lang/String;Lscala/collection/immutable/Seq;Lscala/Function0;Lorg/scalactic/source/Position;)V
    flags: (0x0001) ACC_PUBLIC
    Code:
      stack=5, locals=5, args_size=5
         0: aload_0
         1: aload_1
         2: aload_2
         3: aload_3
         4: aload         4
         6: invokespecial #196                // InterfaceMethod registerIgnoredTestImpl:(Ljava/lang/String;Lscala/collection/immutable/Seq;Lscala/Function0;Lorg/scalactic/source/Position;)V
         9: return
      LineNumberTable:
        line 123: 0
      LocalVariableTable:
        Start  Length  Slot  Name   Signature
            0      10     0  this   Lorg/scalatest/freespec/AnyFreeSpecLike;
            0      10     1 testText   Ljava/lang/String;
            0      10     2 testTags   Lscala/collection/immutable/Seq;
            0      10     3 testFun   Lscala/Function0;
            0      10     4   pos   Lorg/scalactic/source/Position;
    Signature: #121                         // (Ljava/lang/String;Lscala/collection/immutable/Seq<Lorg/scalatest/Tag;>;Lscala/Function0<Ljava/lang/Object;>;Lorg/scalactic/source/Position;)V
    MethodParameters:
      Name                           Flags
      testText                       final
      testTags                       final
      testFun                        final
      pos                            final

  public static void org$scalatest$freespec$AnyFreeSpecLike$$registerTestToRun$(org.scalatest.freespec.AnyFreeSpecLike, java.lang.String, scala.collection.immutable.List, java.lang.String, scala.Function0, org.scalactic.source.Position);
    descriptor: (Lorg/scalatest/freespec/AnyFreeSpecLike;Ljava/lang/String;Lscala/collection/immutable/List;Ljava/lang/String;Lscala/Function0;Lorg/scalactic/source/Position;)V
    flags: (0x1009) ACC_PUBLIC, ACC_STATIC, ACC_SYNTHETIC
    Code:
      stack=6, locals=6, args_size=6
         0: aload_0
         1: aload_1
         2: aload_2
         3: aload_3
         4: aload         4
         6: aload         5
         8: invokespecial #204                // InterfaceMethod org$scalatest$freespec$AnyFreeSpecLike$$registerTestToRun:(Ljava/lang/String;Lscala/collection/immutable/List;Ljava/lang/String;Lscala/Function0;Lorg/scalactic/source/Position;)V
        11: return
      LineNumberTable:
        line 149: 0
      LocalVariableTable:
        Start  Length  Slot  Name   Signature
            0      12     0 $this   Lorg/scalatest/freespec/AnyFreeSpecLike;
            0      12     1 specText   Ljava/lang/String;
            0      12     2 testTags   Lscala/collection/immutable/List;
            0      12     3 methodName   Ljava/lang/String;
            0      12     4 testFun   Lscala/Function0;
            0      12     5   pos   Lorg/scalactic/source/Position;
    MethodParameters:
      Name                           Flags
      $this                          final synthetic
      specText                       final
      testTags                       final
      methodName                     final
      testFun                        final
      pos                            final

  public default void org$scalatest$freespec$AnyFreeSpecLike$$registerTestToRun(java.lang.String, scala.collection.immutable.List<org.scalatest.Tag>, java.lang.String, scala.Function0<java.lang.Object>, org.scalactic.source.Position);
    descriptor: (Ljava/lang/String;Lscala/collection/immutable/List;Ljava/lang/String;Lscala/Function0;Lorg/scalactic/source/Position;)V
    flags: (0x0001) ACC_PUBLIC
    Code:
      stack=13, locals=8, args_size=6
         0: iconst_4
         1: istore        6
         3: bipush        -3
         5: istore        7
         7: aload_0
         8: invokeinterface #70,  1           // InterfaceMethod org$scalatest$freespec$AnyFreeSpecLike$$engine:()Lorg/scalatest/Engine;
        13: aload_1
        14: new           #127                // class org/scalatest/Transformer
        17: dup
        18: aload         4
        20: invokespecial #131                // Method org/scalatest/Transformer."<init>":(Lscala/Function0;)V
        23: invokedynamic #211,  0            // InvokeDynamic #2:apply:()Lscala/Function0;
        28: ldc           #152                // String AnyFreeSpecLike.scala
        30: aload_3
        31: iload         6
        33: iload         7
        35: getstatic     #160                // Field scala/None$.MODULE$:Lscala/None$;
        38: getstatic     #160                // Field scala/None$.MODULE$:Lscala/None$;
        41: new           #162                // class scala/Some
        44: dup
        45: aload         5
        47: invokespecial #165                // Method scala/Some."<init>":(Ljava/lang/Object;)V
        50: getstatic     #160                // Field scala/None$.MODULE$:Lscala/None$;
        53: aload_2
        54: invokevirtual #168                // Method org/scalatest/Engine.registerTest:(Ljava/lang/String;Ljava/lang/Object;Lscala/Function0;Ljava/lang/String;Ljava/lang/String;IILscala/Option;Lscala/Option;Lscala/Option;Lscala/Option;Lscala/collection/immutable/Seq;)Ljava/lang/String;
        57: pop
        58: return
      LineNumberTable:
        line 151: 0
        line 152: 3
        line 156: 7
      LocalVariableTable:
        Start  Length  Slot  Name   Signature
            3      55     6 stackDepth   I
            7      51     7 stackDepthAdjustment   I
            0      59     0  this   Lorg/scalatest/freespec/AnyFreeSpecLike;
            0      59     1 specText   Ljava/lang/String;
            0      59     2 testTags   Lscala/collection/immutable/List;
            0      59     3 methodName   Ljava/lang/String;
            0      59     4 testFun   Lscala/Function0;
            0      59     5   pos   Lorg/scalactic/source/Position;
    Signature: #206                         // (Ljava/lang/String;Lscala/collection/immutable/List<Lorg/scalatest/Tag;>;Ljava/lang/String;Lscala/Function0<Ljava/lang/Object;>;Lorg/scalactic/source/Position;)V
    MethodParameters:
      Name                           Flags
      specText                       final
      testTags                       final
      methodName                     final
      testFun                        final
      pos                            final

  public static void org$scalatest$freespec$AnyFreeSpecLike$$registerTestToIgnore$(org.scalatest.freespec.AnyFreeSpecLike, java.lang.String, scala.collection.immutable.List, java.lang.String, scala.Function0, org.scalactic.source.Position);
    descriptor: (Lorg/scalatest/freespec/AnyFreeSpecLike;Ljava/lang/String;Lscala/collection/immutable/List;Ljava/lang/String;Lscala/Function0;Lorg/scalactic/source/Position;)V
    flags: (0x1009) ACC_PUBLIC, ACC_STATIC, ACC_SYNTHETIC
    Code:
      stack=6, locals=6, args_size=6
         0: aload_0
         1: aload_1
         2: aload_2
         3: aload_3
         4: aload         4
         6: aload         5
         8: invokespecial #216                // InterfaceMethod org$scalatest$freespec$AnyFreeSpecLike$$registerTestToIgnore:(Ljava/lang/String;Lscala/collection/immutable/List;Ljava/lang/String;Lscala/Function0;Lorg/scalactic/source/Position;)V
        11: return
      LineNumberTable:
        line 178: 0
      LocalVariableTable:
        Start  Length  Slot  Name   Signature
            0      12     0 $this   Lorg/scalatest/freespec/AnyFreeSpecLike;
            0      12     1 specText   Ljava/lang/String;
            0      12     2 testTags   Lscala/collection/immutable/List;
            0      12     3 methodName   Ljava/lang/String;
            0      12     4 testFun   Lscala/Function0;
            0      12     5   pos   Lorg/scalactic/source/Position;
    MethodParameters:
      Name                           Flags
      $this                          final synthetic
      specText                       final
      testTags                       final
      methodName                     final
      testFun                        final
      pos                            final

  public default void org$scalatest$freespec$AnyFreeSpecLike$$registerTestToIgnore(java.lang.String, scala.collection.immutable.List<org.scalatest.Tag>, java.lang.String, scala.Function0<java.lang.Object>, org.scalactic.source.Position);
    descriptor: (Ljava/lang/String;Lscala/collection/immutable/List;Ljava/lang/String;Lscala/Function0;Lorg/scalactic/source/Position;)V
    flags: (0x0001) ACC_PUBLIC
    Code:
      stack=12, locals=8, args_size=6
         0: iconst_4
         1: istore        6
         3: bipush        -4
         5: istore        7
         7: aload_0
         8: invokeinterface #70,  1           // InterfaceMethod org$scalatest$freespec$AnyFreeSpecLike$$engine:()Lorg/scalatest/Engine;
        13: aload_1
        14: new           #127                // class org/scalatest/Transformer
        17: dup
        18: aload         4
        20: invokespecial #131                // Method org/scalatest/Transformer."<init>":(Lscala/Function0;)V
        23: invokedynamic #221,  0            // InvokeDynamic #3:apply:()Lscala/Function0;
        28: ldc           #152                // String AnyFreeSpecLike.scala
        30: aload_3
        31: iload         6
        33: iload         7
        35: getstatic     #160                // Field scala/None$.MODULE$:Lscala/None$;
        38: new           #162                // class scala/Some
        41: dup
        42: aload         5
        44: invokespecial #165                // Method scala/Some."<init>":(Ljava/lang/Object;)V
        47: aload_2
        48: invokevirtual #191                // Method org/scalatest/Engine.registerIgnoredTest:(Ljava/lang/String;Ljava/lang/Object;Lscala/Function0;Ljava/lang/String;Ljava/lang/String;IILscala/Option;Lscala/Option;Lscala/collection/immutable/Seq;)V
        51: return
      LineNumberTable:
        line 180: 0
        line 181: 3
        line 185: 7
      LocalVariableTable:
        Start  Length  Slot  Name   Signature
            3      48     6 stackDepth   I
            7      44     7 stackDepthAdjustment   I
            0      52     0  this   Lorg/scalatest/freespec/AnyFreeSpecLike;
            0      52     1 specText   Ljava/lang/String;
            0      52     2 testTags   Lscala/collection/immutable/List;
            0      52     3 methodName   Ljava/lang/String;
            0      52     4 testFun   Lscala/Function0;
            0      52     5   pos   Lorg/scalactic/source/Position;
    Signature: #206                         // (Ljava/lang/String;Lscala/collection/immutable/List<Lorg/scalatest/Tag;>;Ljava/lang/String;Lscala/Function0<Ljava/lang/Object;>;Lorg/scalactic/source/Position;)V
    MethodParameters:
      Name                           Flags
      specText                       final
      testTags                       final
      methodName                     final
      testFun                        final
      pos                            final

  public static org.scalatest.freespec.AnyFreeSpecLike$FreeSpecStringWrapper convertToFreeSpecStringWrapper$(org.scalatest.freespec.AnyFreeSpecLike, java.lang.String, org.scalactic.source.Position);
    descriptor: (Lorg/scalatest/freespec/AnyFreeSpecLike;Ljava/lang/String;Lorg/scalactic/source/Position;)Lorg/scalatest/freespec/AnyFreeSpecLike$FreeSpecStringWrapper;
    flags: (0x1009) ACC_PUBLIC, ACC_STATIC, ACC_SYNTHETIC
    Code:
      stack=3, locals=3, args_size=3
         0: aload_0
         1: aload_1
         2: aload_2
         3: invokespecial #228                // InterfaceMethod convertToFreeSpecStringWrapper:(Ljava/lang/String;Lorg/scalactic/source/Position;)Lorg/scalatest/freespec/AnyFreeSpecLike$FreeSpecStringWrapper;
         6: areturn
      LineNumberTable:
        line 386: 0
      LocalVariableTable:
        Start  Length  Slot  Name   Signature
            0       7     0 $this   Lorg/scalatest/freespec/AnyFreeSpecLike;
            0       7     1     s   Ljava/lang/String;
            0       7     2   pos   Lorg/scalactic/source/Position;
    MethodParameters:
      Name                           Flags
      $this                          final synthetic
      s                              final
      pos                            final

  public default org.scalatest.freespec.AnyFreeSpecLike$FreeSpecStringWrapper convertToFreeSpecStringWrapper(java.lang.String, org.scalactic.source.Position);
    descriptor: (Ljava/lang/String;Lorg/scalactic/source/Position;)Lorg/scalatest/freespec/AnyFreeSpecLike$FreeSpecStringWrapper;
    flags: (0x0001) ACC_PUBLIC
    Code:
      stack=5, locals=3, args_size=3
         0: new           #43                 // class org/scalatest/freespec/AnyFreeSpecLike$FreeSpecStringWrapper
         3: dup
         4: aload_0
         5: aload_1
         6: aload_2
         7: invokespecial #231                // Method org/scalatest/freespec/AnyFreeSpecLike$FreeSpecStringWrapper."<init>":(Lorg/scalatest/freespec/AnyFreeSpecLike;Ljava/lang/String;Lorg/scalactic/source/Position;)V
        10: areturn
      LineNumberTable:
        line 386: 0
      LocalVariableTable:
        Start  Length  Slot  Name   Signature
            0      11     0  this   Lorg/scalatest/freespec/AnyFreeSpecLike;
            0      11     1     s   Ljava/lang/String;
            0      11     2   pos   Lorg/scalactic/source/Position;
    MethodParameters:
      Name                           Flags
      s                              final
      pos                            final

  public static scala.collection.immutable.Map tags$(org.scalatest.freespec.AnyFreeSpecLike);
    descriptor: (Lorg/scalatest/freespec/AnyFreeSpecLike;)Lscala/collection/immutable/Map;
    flags: (0x1009) ACC_PUBLIC, ACC_STATIC, ACC_SYNTHETIC
    Code:
      stack=1, locals=1, args_size=1
         0: aload_0
         1: invokespecial #237                // InterfaceMethod tags:()Lscala/collection/immutable/Map;
         4: areturn
      LineNumberTable:
        line 407: 0
      LocalVariableTable:
        Start  Length  Slot  Name   Signature
            0       5     0 $this   Lorg/scalatest/freespec/AnyFreeSpecLike;
    MethodParameters:
      Name                           Flags
      $this                          final synthetic

  public default scala.collection.immutable.Map<java.lang.String, scala.collection.immutable.Set<java.lang.String>> tags();
    descriptor: ()Lscala/collection/immutable/Map;
    flags: (0x0001) ACC_PUBLIC
    Code:
      stack=3, locals=1, args_size=1
         0: getstatic     #243                // Field org/scalatest/Suite$.MODULE$:Lorg/scalatest/Suite$;
         3: aload_0
         4: invokeinterface #70,  1           // InterfaceMethod org$scalatest$freespec$AnyFreeSpecLike$$engine:()Lorg/scalatest/Engine;
         9: invokevirtual #246                // Method org/scalatest/Engine.atomic:()Ljava/util/concurrent/atomic/AtomicReference;
        12: invokevirtual #82                 // Method java/util/concurrent/atomic/AtomicReference.get:()Ljava/lang/Object;
        15: checkcast     #30                 // class org/scalatest/SuperEngine$Bundle
        18: invokevirtual #249                // Method org/scalatest/SuperEngine$Bundle.tagsMap:()Lscala/collection/immutable/Map;
        21: aload_0
        22: invokevirtual #253                // Method org/scalatest/Suite$.autoTagClassAnnotations:(Lscala/collection/immutable/Map;Lorg/scalatest/Suite;)Lscala/collection/immutable/Map;
        25: areturn
      LineNumberTable:
        line 407: 0
      LocalVariableTable:
        Start  Length  Slot  Name   Signature
            0      26     0  this   Lorg/scalatest/freespec/AnyFreeSpecLike;
    Signature: #238                         // ()Lscala/collection/immutable/Map<Ljava/lang/String;Lscala/collection/immutable/Set<Ljava/lang/String;>;>;

  public static org.scalatest.Status runTest$(org.scalatest.freespec.AnyFreeSpecLike, java.lang.String, org.scalatest.Args);
    descriptor: (Lorg/scalatest/freespec/AnyFreeSpecLike;Ljava/lang/String;Lorg/scalatest/Args;)Lorg/scalatest/Status;
    flags: (0x1009) ACC_PUBLIC, ACC_STATIC, ACC_SYNTHETIC
    Code:
      stack=3, locals=3, args_size=3
         0: aload_0
         1: aload_1
         2: aload_2
         3: invokespecial #259                // InterfaceMethod runTest:(Ljava/lang/String;Lorg/scalatest/Args;)Lorg/scalatest/Status;
         6: areturn
      LineNumberTable:
        line 422: 0
      LocalVariableTable:
        Start  Length  Slot  Name   Signature
            0       7     0 $this   Lorg/scalatest/freespec/AnyFreeSpecLike;
            0       7     1 testName   Ljava/lang/String;
            0       7     2  args   Lorg/scalatest/Args;
    MethodParameters:
      Name                           Flags
      $this                          final synthetic
      testName                       final
      args                           final

  public default org.scalatest.Status runTest(java.lang.String, org.scalatest.Args);
    descriptor: (Ljava/lang/String;Lorg/scalatest/Args;)Lorg/scalatest/Status;
    flags: (0x0001) ACC_PUBLIC
    Code:
      stack=8, locals=3, args_size=3
         0: aload_0
         1: invokeinterface #70,  1           // InterfaceMethod org$scalatest$freespec$AnyFreeSpecLike$$engine:()Lorg/scalatest/Engine;
         6: aload_0
         7: aload_1
         8: aload_2
         9: iconst_1
        10: aload_0
        11: aload_2
        12: aload_1
        13: invokedynamic #272,  0            // InvokeDynamic #4:apply:(Lorg/scalatest/freespec/AnyFreeSpecLike;Lorg/scalatest/Args;Ljava/lang/String;)Lscala/Function1;
        18: invokevirtual #276                // Method org/scalatest/Engine.runTestImpl:(Lorg/scalatest/Suite;Ljava/lang/String;Lorg/scalatest/Args;ZLscala/Function1;)Lorg/scalatest/Status;
        21: areturn
      LineNumberTable:
        line 440: 0
      LocalVariableTable:
        Start  Length  Slot  Name   Signature
            0      22     0  this   Lorg/scalatest/freespec/AnyFreeSpecLike;
            0      22     1 testName   Ljava/lang/String;
            0      22     2  args   Lorg/scalatest/Args;
    MethodParameters:
      Name                           Flags
      testName                       final
      args                           final

  public static org.scalatest.Status runTests$(org.scalatest.freespec.AnyFreeSpecLike, scala.Option, org.scalatest.Args);
    descriptor: (Lorg/scalatest/freespec/AnyFreeSpecLike;Lscala/Option;Lorg/scalatest/Args;)Lorg/scalatest/Status;
    flags: (0x1009) ACC_PUBLIC, ACC_STATIC, ACC_SYNTHETIC
    Code:
      stack=3, locals=3, args_size=3
         0: aload_0
         1: aload_1
         2: aload_2
         3: invokespecial #281                // InterfaceMethod runTests:(Lscala/Option;Lorg/scalatest/Args;)Lorg/scalatest/Status;
         6: areturn
      LineNumberTable:
        line 498: 0
      LocalVariableTable:
        Start  Length  Slot  Name   Signature
            0       7     0 $this   Lorg/scalatest/freespec/AnyFreeSpecLike;
            0       7     1 testName   Lscala/Option;
            0       7     2  args   Lorg/scalatest/Args;
    MethodParameters:
      Name                           Flags
      $this                          final synthetic
      testName                       final
      args                           final

  public default org.scalatest.Status runTests(scala.Option<java.lang.String>, org.scalatest.Args);
    descriptor: (Lscala/Option;Lorg/scalatest/Args;)Lorg/scalatest/Status;
    flags: (0x0001) ACC_PUBLIC
    Code:
      stack=7, locals=3, args_size=3
         0: aload_0
         1: invokeinterface #70,  1           // InterfaceMethod org$scalatest$freespec$AnyFreeSpecLike$$engine:()Lorg/scalatest/Engine;
         6: aload_0
         7: aload_1
         8: aload_2
         9: aload_0
        10: invokeinterface #67,  1           // InterfaceMethod info:()Lorg/scalatest/Informer;
        15: iconst_1
        16: aload_0
        17: invokedynamic #293,  0            // InvokeDynamic #5:apply:(Lorg/scalatest/freespec/AnyFreeSpecLike;)Lscala/Function2;
        22: invokevirtual #297                // Method org/scalatest/Engine.runTestsImpl:(Lorg/scalatest/Suite;Lscala/Option;Lorg/scalatest/Args;Lorg/scalatest/Informer;ZLscala/Function2;)Lorg/scalatest/Status;
        25: areturn
      LineNumberTable:
        line 499: 0
      LocalVariableTable:
        Start  Length  Slot  Name   Signature
            0      26     0  this   Lorg/scalatest/freespec/AnyFreeSpecLike;
            0      26     1 testName   Lscala/Option;
            0      26     2  args   Lorg/scalatest/Args;
    Signature: #283                         // (Lscala/Option<Ljava/lang/String;>;Lorg/scalatest/Args;)Lorg/scalatest/Status;
    MethodParameters:
      Name                           Flags
      testName                       final
      args                           final

  public static scala.collection.immutable.Set testNames$(org.scalatest.freespec.AnyFreeSpecLike);
    descriptor: (Lorg/scalatest/freespec/AnyFreeSpecLike;)Lscala/collection/immutable/Set;
    flags: (0x1009) ACC_PUBLIC, ACC_STATIC, ACC_SYNTHETIC
    Code:
      stack=1, locals=1, args_size=1
         0: aload_0
         1: invokespecial #303                // InterfaceMethod testNames:()Lscala/collection/immutable/Set;
         4: areturn
      LineNumberTable:
        line 538: 0
      LocalVariableTable:
        Start  Length  Slot  Name   Signature
            0       5     0 $this   Lorg/scalatest/freespec/AnyFreeSpecLike;
    MethodParameters:
      Name                           Flags
      $this                          final synthetic

  public default scala.collection.immutable.Set<java.lang.String> testNames();
    descriptor: ()Lscala/collection/immutable/Set;
    flags: (0x0001) ACC_PUBLIC
    Code:
      stack=2, locals=1, args_size=1
         0: getstatic     #309                // Field org/scalatest/InsertionOrderSet$.MODULE$:Lorg/scalatest/InsertionOrderSet$;
         3: aload_0
         4: invokeinterface #70,  1           // InterfaceMethod org$scalatest$freespec$AnyFreeSpecLike$$engine:()Lorg/scalatest/Engine;
         9: invokevirtual #246                // Method org/scalatest/Engine.atomic:()Ljava/util/concurrent/atomic/AtomicReference;
        12: invokevirtual #82                 // Method java/util/concurrent/atomic/AtomicReference.get:()Ljava/lang/Object;
        15: checkcast     #30                 // class org/scalatest/SuperEngine$Bundle
        18: invokevirtual #313                // Method org/scalatest/SuperEngine$Bundle.testNamesList:()Lscala/collection/immutable/List;
        21: invokevirtual #316                // Method org/scalatest/InsertionOrderSet$.apply:(Lscala/collection/immutable/List;)Lscala/collection/immutable/Set;
        24: areturn
      LineNumberTable:
        line 539: 0
      LocalVariableTable:
        Start  Length  Slot  Name   Signature
            0      25     0  this   Lorg/scalatest/freespec/AnyFreeSpecLike;
    Signature: #304                         // ()Lscala/collection/immutable/Set<Ljava/lang/String;>;

  public static org.scalatest.Status run$(org.scalatest.freespec.AnyFreeSpecLike, scala.Option, org.scalatest.Args);
    descriptor: (Lorg/scalatest/freespec/AnyFreeSpecLike;Lscala/Option;Lorg/scalatest/Args;)Lorg/scalatest/Status;
    flags: (0x1009) ACC_PUBLIC, ACC_STATIC, ACC_SYNTHETIC
    Code:
      stack=3, locals=3, args_size=3
         0: aload_0
         1: aload_1
         2: aload_2
         3: invokespecial #320                // InterfaceMethod run:(Lscala/Option;Lorg/scalatest/Args;)Lorg/scalatest/Status;
         6: areturn
      LineNumberTable:
        line 542: 0
      LocalVariableTable:
        Start  Length  Slot  Name   Signature
            0       7     0 $this   Lorg/scalatest/freespec/AnyFreeSpecLike;
            0       7     1 testName   Lscala/Option;
            0       7     2  args   Lorg/scalatest/Args;
    MethodParameters:
      Name                           Flags
      $this                          final synthetic
      testName                       final
      args                           final

  public default org.scalatest.Status run(scala.Option<java.lang.String>, org.scalatest.Args);
    descriptor: (Lscala/Option;Lorg/scalatest/Args;)Lorg/scalatest/Status;
    flags: (0x0001) ACC_PUBLIC
    Code:
      stack=5, locals=3, args_size=3
         0: aload_0
         1: invokeinterface #70,  1           // InterfaceMethod org$scalatest$freespec$AnyFreeSpecLike$$engine:()Lorg/scalatest/Engine;
         6: aload_0
         7: aload_1
         8: aload_2
         9: aload_0
        10: invokedynamic #326,  0            // InvokeDynamic #6:apply:(Lorg/scalatest/freespec/AnyFreeSpecLike;)Lscala/Function2;
        15: invokevirtual #330                // Method org/scalatest/Engine.runImpl:(Lorg/scalatest/Suite;Lscala/Option;Lorg/scalatest/Args;Lscala/Function2;)Lorg/scalatest/Status;
        18: areturn
      LineNumberTable:
        line 543: 0
      LocalVariableTable:
        Start  Length  Slot  Name   Signature
            0      19     0  this   Lorg/scalatest/freespec/AnyFreeSpecLike;
            0      19     1 testName   Lscala/Option;
            0      19     2  args   Lorg/scalatest/Args;
    Signature: #283                         // (Lscala/Option<Ljava/lang/String;>;Lorg/scalatest/Args;)Lorg/scalatest/Status;
    MethodParameters:
      Name                           Flags
      testName                       final
      args                           final

  public abstract org.scalatest.verbs.BehaveWord behave();
    descriptor: ()Lorg/scalatest/verbs/BehaveWord;
    flags: (0x0401) ACC_PUBLIC, ACC_ABSTRACT

  public abstract java.lang.String styleName();
    descriptor: ()Ljava/lang/String;
    flags: (0x0401) ACC_PUBLIC, ACC_ABSTRACT
    Deprecated: true

  public static org.scalatest.TestData testDataFor$(org.scalatest.freespec.AnyFreeSpecLike, java.lang.String, org.scalatest.ConfigMap);
    descriptor: (Lorg/scalatest/freespec/AnyFreeSpecLike;Ljava/lang/String;Lorg/scalatest/ConfigMap;)Lorg/scalatest/TestData;
    flags: (0x1009) ACC_PUBLIC, ACC_STATIC, ACC_SYNTHETIC
    Code:
      stack=3, locals=3, args_size=3
         0: aload_0
         1: aload_1
         2: aload_2
         3: invokespecial #340                // InterfaceMethod testDataFor:(Ljava/lang/String;Lorg/scalatest/ConfigMap;)Lorg/scalatest/TestData;
         6: areturn
      LineNumberTable:
        line 574: 0
      LocalVariableTable:
        Start  Length  Slot  Name   Signature
            0       7     0 $this   Lorg/scalatest/freespec/AnyFreeSpecLike;
            0       7     1 testName   Ljava/lang/String;
            0       7     2 theConfigMap   Lorg/scalatest/ConfigMap;
    MethodParameters:
      Name                           Flags
      $this                          final synthetic
      testName                       final
      theConfigMap                   final

  public default org.scalatest.TestData testDataFor(java.lang.String, org.scalatest.ConfigMap);
    descriptor: (Ljava/lang/String;Lorg/scalatest/ConfigMap;)Lorg/scalatest/TestData;
    flags: (0x0001) ACC_PUBLIC
    Code:
      stack=4, locals=3, args_size=3
         0: aload_0
         1: invokeinterface #70,  1           // InterfaceMethod org$scalatest$freespec$AnyFreeSpecLike$$engine:()Lorg/scalatest/Engine;
         6: aload_1
         7: aload_2
         8: aload_0
         9: invokevirtual #345                // Method org/scalatest/Engine.createTestDataFor:(Ljava/lang/String;Lorg/scalatest/ConfigMap;Lorg/scalatest/Suite;)Lorg/scalatest/TestData;
        12: areturn
      LineNumberTable:
        line 574: 0
      LocalVariableTable:
        Start  Length  Slot  Name   Signature
            0      13     0  this   Lorg/scalatest/freespec/AnyFreeSpecLike;
            0      13     1 testName   Ljava/lang/String;
            0      13     2 theConfigMap   Lorg/scalatest/ConfigMap;
    MethodParameters:
      Name                           Flags
      testName                       final
      theConfigMap                   final

  public static org.scalatest.ConfigMap testDataFor$default$2$(org.scalatest.freespec.AnyFreeSpecLike);
    descriptor: (Lorg/scalatest/freespec/AnyFreeSpecLike;)Lorg/scalatest/ConfigMap;
    flags: (0x1009) ACC_PUBLIC, ACC_STATIC, ACC_SYNTHETIC
    Code:
      stack=1, locals=1, args_size=1
         0: aload_0
         1: invokespecial #351                // InterfaceMethod testDataFor$default$2:()Lorg/scalatest/ConfigMap;
         4: areturn
      LineNumberTable:
        line 574: 0
      LocalVariableTable:
        Start  Length  Slot  Name   Signature
            0       5     0 $this   Lorg/scalatest/freespec/AnyFreeSpecLike;
    MethodParameters:
      Name                           Flags
      $this                          final synthetic

  public default org.scalatest.ConfigMap testDataFor$default$2();
    descriptor: ()Lorg/scalatest/ConfigMap;
    flags: (0x0001) ACC_PUBLIC
    Code:
      stack=1, locals=1, args_size=1
         0: getstatic     #356                // Field org/scalatest/ConfigMap$.MODULE$:Lorg/scalatest/ConfigMap$;
         3: invokevirtual #359                // Method org/scalatest/ConfigMap$.empty:()Lorg/scalatest/ConfigMap;
         6: areturn
      LineNumberTable:
        line 574: 0
      LocalVariableTable:
        Start  Length  Slot  Name   Signature
            0       7     0  this   Lorg/scalatest/freespec/AnyFreeSpecLike;

  public static java.lang.String $anonfun$engine$1();
    descriptor: ()Ljava/lang/String;
    flags: (0x1009) ACC_PUBLIC, ACC_STATIC, ACC_SYNTHETIC
    Code:
      stack=1, locals=0, args_size=0
         0: getstatic     #365                // Field org/scalatest/Resources$.MODULE$:Lorg/scalatest/Resources$;
         3: invokevirtual #368                // Method org/scalatest/Resources$.concurrentFreeSpecMod:()Ljava/lang/String;
         6: areturn
      LineNumberTable:
        line 51: 0

  public static java.lang.String $anonfun$registerTestImpl$1();
    descriptor: ()Ljava/lang/String;
    flags: (0x1009) ACC_PUBLIC, ACC_STATIC, ACC_SYNTHETIC
    Code:
      stack=1, locals=0, args_size=0
         0: getstatic     #365                // Field org/scalatest/Resources$.MODULE$:Lorg/scalatest/Resources$;
         3: invokevirtual #371                // Method org/scalatest/Resources$.testCannotBeNestedInsideAnotherTest:()Ljava/lang/String;
         6: areturn
      LineNumberTable:
        line 101: 0

  public static java.lang.String $anonfun$registerIgnoredTestImpl$1();
    descriptor: ()Ljava/lang/String;
    flags: (0x1009) ACC_PUBLIC, ACC_STATIC, ACC_SYNTHETIC
    Code:
      stack=1, locals=0, args_size=0
         0: getstatic     #365                // Field org/scalatest/Resources$.MODULE$:Lorg/scalatest/Resources$;
         3: invokevirtual #371                // Method org/scalatest/Resources$.testCannotBeNestedInsideAnotherTest:()Ljava/lang/String;
         6: areturn
      LineNumberTable:
        line 118: 0

  public static java.lang.String $anonfun$registerTestToRun$1();
    descriptor: ()Ljava/lang/String;
    flags: (0x1009) ACC_PUBLIC, ACC_STATIC, ACC_SYNTHETIC
    Code:
      stack=1, locals=0, args_size=0
         0: getstatic     #365                // Field org/scalatest/Resources$.MODULE$:Lorg/scalatest/Resources$;
         3: invokevirtual #374                // Method org/scalatest/Resources$.inCannotAppearInsideAnotherIn:()Ljava/lang/String;
         6: areturn
      LineNumberTable:
        line 156: 0

  public static java.lang.String $anonfun$registerTestToIgnore$1();
    descriptor: ()Ljava/lang/String;
    flags: (0x1009) ACC_PUBLIC, ACC_STATIC, ACC_SYNTHETIC
    Code:
      stack=1, locals=0, args_size=0
         0: getstatic     #365                // Field org/scalatest/Resources$.MODULE$:Lorg/scalatest/Resources$;
         3: invokevirtual #377                // Method org/scalatest/Resources$.ignoreCannotAppearInsideAnIn:()Ljava/lang/String;
         6: areturn
      LineNumberTable:
        line 185: 0

  private org.scalatest.Outcome invokeWithFixture$1(org.scalatest.SuperEngine$TestLeaf, org.scalatest.Args, java.lang.String);
    descriptor: (Lorg/scalatest/SuperEngine$TestLeaf;Lorg/scalatest/Args;Ljava/lang/String;)Lorg/scalatest/Outcome;
    flags: (0x0002) ACC_PRIVATE
    Code:
      stack=6, locals=6, args_size=4
         0: aload_2
         1: invokevirtual #387                // Method org/scalatest/Args.configMap:()Lorg/scalatest/ConfigMap;
         4: astore        4
         6: aload_0
         7: aload_3
         8: aload         4
        10: invokeinterface #340,  3          // InterfaceMethod testDataFor:(Ljava/lang/String;Lorg/scalatest/ConfigMap;)Lorg/scalatest/TestData;
        15: astore        5
        17: aload_0
        18: new           #41                 // class org/scalatest/freespec/AnyFreeSpecLike$$anon$1
        21: dup
        22: aconst_null
        23: aload         5
        25: aload_1
        26: invokespecial #390                // Method org/scalatest/freespec/AnyFreeSpecLike$$anon$1."<init>":(Lorg/scalatest/freespec/AnyFreeSpecLike;Lorg/scalatest/TestData;Lorg/scalatest/SuperEngine$TestLeaf;)V
        29: invokeinterface #394,  2          // InterfaceMethod withFixture:(Lorg/scalatest/TestSuite$NoArgTest;)Lorg/scalatest/Outcome;
        34: areturn
      LineNumberTable:
        line 425: 0
        line 426: 6
        line 427: 17
        line 428: 18
      LocalVariableTable:
        Start  Length  Slot  Name   Signature
            6      28     4 theConfigMap   Lorg/scalatest/ConfigMap;
           17      17     5 testData   Lorg/scalatest/TestData;
            0      35     0  this   Lorg/scalatest/freespec/AnyFreeSpecLike;
            0      35     1 theTest   Lorg/scalatest/SuperEngine$TestLeaf;
            0      35     2 args$1   Lorg/scalatest/Args;
            0      35     3 testName$1   Ljava/lang/String;
    MethodParameters:
      Name                           Flags
      theTest                        final
      args$1                         final
      testName$1                     final

  public static org.scalatest.Outcome $anonfun$runTest$1(org.scalatest.freespec.AnyFreeSpecLike, org.scalatest.Args, java.lang.String, org.scalatest.SuperEngine$TestLeaf);
    descriptor: (Lorg/scalatest/freespec/AnyFreeSpecLike;Lorg/scalatest/Args;Ljava/lang/String;Lorg/scalatest/SuperEngine$TestLeaf;)Lorg/scalatest/Outcome;
    flags: (0x1009) ACC_PUBLIC, ACC_STATIC, ACC_SYNTHETIC
    Code:
      stack=4, locals=4, args_size=4
         0: aload_0
         1: aload_3
         2: aload_1
         3: aload_2
         4: invokespecial #399                // InterfaceMethod invokeWithFixture$1:(Lorg/scalatest/SuperEngine$TestLeaf;Lorg/scalatest/Args;Ljava/lang/String;)Lorg/scalatest/Outcome;
         7: areturn
      LineNumberTable:
        line 440: 0
      LocalVariableTable:
        Start  Length  Slot  Name   Signature
            0       8     0 $this   Lorg/scalatest/freespec/AnyFreeSpecLike;
            0       8     1 args$1   Lorg/scalatest/Args;
            0       8     2 testName$1   Ljava/lang/String;
            0       8     3 theTest   Lorg/scalatest/SuperEngine$TestLeaf;
    MethodParameters:
      Name                           Flags
      $this                          final synthetic
      args$1                         final
      testName$1                     final
      theTest                        final

  public static org.scalatest.Status $anonfun$runTests$1(org.scalatest.freespec.AnyFreeSpecLike, java.lang.String, org.scalatest.Args);
    descriptor: (Lorg/scalatest/freespec/AnyFreeSpecLike;Ljava/lang/String;Lorg/scalatest/Args;)Lorg/scalatest/Status;
    flags: (0x1009) ACC_PUBLIC, ACC_STATIC, ACC_SYNTHETIC
    Code:
      stack=3, locals=3, args_size=3
         0: aload_0
         1: aload_1
         2: aload_2
         3: invokeinterface #259,  3          // InterfaceMethod runTest:(Ljava/lang/String;Lorg/scalatest/Args;)Lorg/scalatest/Status;
         8: areturn
      LineNumberTable:
        line 499: 0
      LocalVariableTable:
        Start  Length  Slot  Name   Signature
            0       9     0 $this   Lorg/scalatest/freespec/AnyFreeSpecLike;
            0       9     1 testName   Ljava/lang/String;
            0       9     2  args   Lorg/scalatest/Args;
    MethodParameters:
      Name                           Flags
      $this                          final synthetic
      testName                       final
      args                           final

  public static org.scalatest.Status $anonfun$run$1(org.scalatest.freespec.AnyFreeSpecLike, scala.Option, org.scalatest.Args);
    descriptor: (Lorg/scalatest/freespec/AnyFreeSpecLike;Lscala/Option;Lorg/scalatest/Args;)Lorg/scalatest/Status;
    flags: (0x1009) ACC_PUBLIC, ACC_STATIC, ACC_SYNTHETIC
    Code:
      stack=3, locals=3, args_size=3
         0: aload_0
         1: aload_1
         2: aload_2
         3: invokeinterface #401,  3          // InterfaceMethod org$scalatest$freespec$AnyFreeSpecLike$$super$run:(Lscala/Option;Lorg/scalatest/Args;)Lorg/scalatest/Status;
         8: areturn
      LineNumberTable:
        line 543: 0
      LocalVariableTable:
        Start  Length  Slot  Name   Signature
            0       9     0 $this   Lorg/scalatest/freespec/AnyFreeSpecLike;
            0       9     1 testName   Lscala/Option;
            0       9     2  args   Lorg/scalatest/Args;
    MethodParameters:
      Name                           Flags
      $this                          final synthetic
      testName                       final
      args                           final

  public static void $init$(org.scalatest.freespec.AnyFreeSpecLike);
    descriptor: (Lorg/scalatest/freespec/AnyFreeSpecLike;)V
    flags: (0x0009) ACC_PUBLIC, ACC_STATIC
    Code:
      stack=5, locals=1, args_size=1
         0: aload_0
         1: new           #72                 // class org/scalatest/Engine
         4: dup
         5: invokedynamic #407,  0            // InvokeDynamic #7:apply:()Lscala/Function0;
        10: ldc_w         #409                // String FreeSpec
        13: invokespecial #412                // Method org/scalatest/Engine."<init>":(Lscala/Function0;Ljava/lang/String;)V
        16: invokeinterface #414,  2          // InterfaceMethod org$scalatest$freespec$AnyFreeSpecLike$_setter_$org$scalatest$freespec$AnyFreeSpecLike$$engine_$eq:(Lorg/scalatest/Engine;)V
        21: aload_0
        22: new           #416                // class org/scalatest/verbs/BehaveWord
        25: dup
        26: invokespecial #419                // Method org/scalatest/verbs/BehaveWord."<init>":()V
        29: invokeinterface #421,  2          // InterfaceMethod org$scalatest$freespec$AnyFreeSpecLike$_setter_$behave_$eq:(Lorg/scalatest/verbs/BehaveWord;)V
        34: aload_0
        35: ldc_w         #423                // String org.scalatest.FreeSpec
        38: invokeinterface #425,  2          // InterfaceMethod org$scalatest$freespec$AnyFreeSpecLike$_setter_$styleName_$eq:(Ljava/lang/String;)V
        43: return
      LineNumberTable:
        line 51: 0
        line 563: 21
        line 572: 34
        line 49: 43
      LocalVariableTable:
        Start  Length  Slot  Name   Signature
            0      44     0 $this   Lorg/scalatest/freespec/AnyFreeSpecLike;
    MethodParameters:
      Name                           Flags
      $this                          final synthetic

  private static java.lang.Object $deserializeLambda$(java.lang.invoke.SerializedLambda);
    descriptor: (Ljava/lang/invoke/SerializedLambda;)Ljava/lang/Object;
    flags: (0x100a) ACC_PRIVATE, ACC_STATIC, ACC_SYNTHETIC
    Code:
      stack=1, locals=1, args_size=1
         0: aload_0
         1: invokedynamic #437,  0            // InvokeDynamic #8:lambdaDeserialize:(Ljava/lang/invoke/SerializedLambda;)Ljava/lang/Object;
         6: areturn
}
InnerClasses:
  public static final #28= #25 of #27;    // Lookup=class java/lang/invoke/MethodHandles$Lookup of class java/lang/invoke/MethodHandles
  public #33= #30 of #32;                 // Bundle=class org/scalatest/SuperEngine$Bundle of class org/scalatest/SuperEngine
  public #36= #35 of #32;                 // TestLeaf=class org/scalatest/SuperEngine$TestLeaf of class org/scalatest/SuperEngine
  public #39= #38 of #6;                  // NoArgTest=class org/scalatest/TestSuite$NoArgTest of class org/scalatest/TestSuite
  public final #41;                       // class org/scalatest/freespec/AnyFreeSpecLike$$anon$1
  public final #44= #43 of #2;            // FreeSpecStringWrapper=class org/scalatest/freespec/AnyFreeSpecLike$FreeSpecStringWrapper of class org/scalatest/freespec/AnyFreeSpecLike
  public final #47= #46 of #2;            // ResultOfTaggedAsInvocationOnString=class org/scalatest/freespec/AnyFreeSpecLike$ResultOfTaggedAsInvocationOnString of class org/scalatest/freespec/AnyFreeSpecLike
SourceFile: "AnyFreeSpecLike.scala"
RuntimeVisibleAnnotations:
  0: #18(#19=[s#20])
    org.scalatest.Finders(
      value=["org.scalatest.finders.FreeSpecFinder"]
    )
  1: #21(#22=s#23)
    scala.reflect.ScalaSignature(
      bytes="\u0006\u0005\t5faB\u0015+!\u0003\r\t!\r\u0005\u0006\u0017\u0002!\t\u0001\u0014\u0005\b!\u0002\u0011\r\u0011\"\u0004R\u0011\u0015)\u0006\u0001\"\u0005W\u0011\u0015Q\u0006\u0001\"\u0005\\\u0011\u0015y\u0006\u0001\"\u0005a\u0011\u0015!\u0007\u0001\"\u0005f\u0011\u0015I\u0007\u0001\"\u0004k\u0011\u001d\t9\u0003\u0001C\u0003\u0003SAq!a\u000e\u0001\t\u001b\tI\u0004C\u0004\u0002F\u0001!)!a\u0012\t\u000f\u0005U\u0003\u0001\"\u0003\u0002X!9\u0011q\u0010\u0001\u0005\n\u0005\u0005eABAG\u0001)\ty\t\u0003\u0006\u0002\\5\u0011\t\u0011)A\u0005\u0003\u0003A!\"!%\u000e\u0005\u0003\u0005\u000b\u0011BA0\u0011!)XB!A!\u0002\u00131\bbBAJ\u001b\u0011\u0005\u0011Q\u0013\u0005\b\u0003CkA\u0011AAR\u0011\u001d\t9+\u0004C\u0001\u0003SCq!!.\u000e\t\u0003\t9L\u0002\u0004\u0002<\u0002Q\u0011Q\u0018\u0005\u000b\u0003\u007f+\"\u0011!Q\u0001\n\u0005\u0005\u0001\u0002C;\u0016\u0005\u0003\u0005\u000b\u0011\u0002<\t\u000f\u0005MU\u0003\"\u0001\u0002B\"9\u0011\u0011Z\u000b\u0005\u0002\u0005-\u0007bBAQ+\u0011\u0005\u00111\u001b\u0005\b\u0003k+B\u0011AAm\u0011\u001d\t9+\u0006C\u0001\u0003;Dq!!9\u0016\t\u0003\t\u0019\u000fC\u0004\u0002n\u0002!\u0019\"a<\t\u000f\u0005E\u0005\u0001\"\u0011\u0002z\"9!q\u0001\u0001\u0005R\t%\u0001b\u0002B\u0010\u0001\u0011E#\u0011\u0005\u0005\b\u0005[\u0001A\u0011\tB\u0018\u0011\u001d\u0011\t\u0004\u0001C!\u0005gA\u0011B!\u000f\u0001\u0005\u0004%\tBa\u000f\t\u0013\t%\u0003A1A\u0005F\t-\u0003b\u0002B1\u0001\u0011\u0005#1\r\u0005\n\u0005o\u0002\u0011\u0013!C\u0001\u0005sBaBa$\u0001!\u0003\r\t\u0011!C\u0005\u0005#\u00139JA\bB]f4%/Z3Ta\u0016\u001cG*[6f\u0015\tYC&\u0001\u0005ge\u0016,7\u000f]3d\u0015\tic&A\u0005tG\u0006d\u0017\r^3ti*\tq&A\u0002pe\u001e\u001c\u0001a\u0005\u0005\u0001eabtHQ#I!\t\u0019d\'D\u00015\u0015\u0005)\u0014!B:dC2\f\u0017BA\u001c5\u0005\u0019\te.\u001f*fMB\u0011\u0011HO\u0007\u0002Y%\u00111\b\f\u0002\n)\u0016\u001cHoU;ji\u0016\u0004\"!O\u001f\n\u0005yb#\u0001\u0005+fgR\u0014VmZ5tiJ\fG/[8o!\tI\u0004)\u0003\u0002BY\tI\u0011J\u001c4pe6Lgn\u001a\t\u0003s\rK!\u0001\u0012\u0017\u0003\u00139{G/\u001b4zS:<\u0007CA\u001dG\u0013\t9EF\u0001\u0005BY\u0016\u0014H/\u001b8h!\tI\u0014*\u0003\u0002KY\tYAi\\2v[\u0016tG/\u001b8h\u0003\u0019!\u0013N\\5uIQ\tQ\n\u0005\u00024\u001d&\u0011q\n\u000e\u0002\u0005+:LG/\u0001\u0004f]\u001eLg.Z\u000b\u0002%B\u0011\u0011hU\u0005\u0003)2\u0012a!\u00128hS:,\u0017\u0001B5oM>,\u0012a\u0016\t\u0003saK!!\u0017\u0017\u0003\u0011%sgm\u001c:nKJ\fAA\\8uKV\tA\f\u0005\u0002:;&\u0011a\f\f\u0002\t\u001d>$\u0018NZ5fe\u0006)\u0011\r\\3siV\t\u0011\r\u0005\u0002:E&\u00111\r\f\u0002\b\u00032,\'\u000f^3s\u0003\u0019i\u0017M]6vaV\ta\r\u0005\u0002:O&\u0011\u0001\u000e\f\u0002\u000b\t>\u001cW/\\3oi\u0016\u0014\u0018\u0001\u0005:fO&\u001cH/\u001a:UKN$\u0018*\u001c9m)\u0011Yg0a\u0006\u0015\u00075cG\u000f\u0003\u0004n\u000f\u0011\u0005\rA\\\u0001\bi\u0016\u001cHOR;o!\r\u0019t.]\u0005\u0003aR\u0012\u0001\u0002\u00102z]\u0006lWM\u0010\t\u0003gIL!a\u001d\u001b\u0003\u0007\u0005s\u0017\u0010C\u0003v\u000f\u0001\u0007a/A\u0002q_N\u0004\"a\u001e?\u000e\u0003aT!!\u001f>\u0002\rM|WO]2f\u0015\tYh&A\u0005tG\u0006d\u0017m\u0019;jG&\u0011Q\u0010\u001f\u0002\t!>\u001c\u0018\u000e^5p]\"1qp\u0002a\u0001\u0003\u0003\t\u0001\u0002^3tiR+\u0007\u0010\u001e\t\u0005\u0003\u0007\t\tB\u0004\u0003\u0002\u0006\u00055\u0001cAA\u0004i5\u0011\u0011\u0011\u0002\u0006\u0004\u0003\u0017\u0001\u0014A\u0002\u001fs_>$h(C\u0002\u0002\u0010Q\na\u0001\u0015:fI\u00164\u0017\u0002BA\n\u0003+\u0011aa\u0015;sS:<\'bAA\bi!9\u0011\u0011D\u0004A\u0002\u0005m\u0011\u0001\u0003;fgR$\u0016mZ:\u0011\u000bM\ni\"!\t\n\u0007\u0005}AG\u0001\u0006=e\u0016\u0004X-\u0019;fIz\u00022!OA\u0012\u0013\r\t)\u0003\f\u0002\u0004)\u0006<\u0017\u0001\u0004:fO&\u001cH/\u001a:UKN$HCBA\u0016\u0003g\t)\u0004\u0006\u0003\u0002.\u0005EBcA\'\u00020!)Q\u000f\u0003a\u0002m\"1Q\u000e\u0003CA\u00029Daa \u0005A\u0002\u0005\u0005\u0001bBA\r\u0011\u0001\u0007\u00111D\u0001\u0018e\u0016<\u0017n\u001d;fe&;gn\u001c:fIR+7\u000f^%na2$b!a\u000f\u0002B\u0005\rC#B\'\u0002>\u0005}\u0002BB7\n\t\u0003\u0007a\u000eC\u0003v\u0013\u0001\u0007a\u000f\u0003\u0004\u0000\u0013\u0001\u0007\u0011\u0011\u0001\u0005\b\u00033I\u0001\u0019AA\u000e\u0003M\u0011XmZ5ti\u0016\u0014\u0018j\u001a8pe\u0016$G+Z:u)\u0019\tI%!\u0015\u0002TQ!\u00111JA()\ri\u0015Q\n\u0005\u0006k*\u0001\u001dA\u001e\u0005\u0007[*!\t\u0019\u00018\t\r}T\u0001\u0019AA\u0001\u0011\u001d\tIB\u0003a\u0001\u00037\t\u0011C]3hSN$XM\u001d+fgR$vNU;o)-i\u0015\u0011LA/\u0003c\n)(! \t\u000f\u0005m3\u00021\u0001\u0002\u0002\u0005A1\u000f]3d)\u0016DH\u000fC\u0004\u0002\u001a-\u0001\r!a\u0018\u0011\r\u0005\u0005\u00141NA\u0011\u001d\u0011\t\u0019\'a\u001a\u000f\t\u0005\u001d\u0011QM\u0005\u0002k%\u0019\u0011\u0011\u000e\u001b\u0002\u000fA\f7m[1hK&!\u0011QNA8\u0005\u0011a\u0015n\u001d;\u000b\u0007\u0005%D\u0007C\u0004\u0002t-\u0001\r!!\u0001\u0002\u00155,G\u000f[8e\u001d\u0006lW\r\u0003\u0004n\u0017\u0001\u0007\u0011q\u000f\t\u0005g\u0005e\u0014/C\u0002\u0002|Q\u0012\u0011BR;oGRLwN\u001c\u0019\t\u000bU\\\u0001\u0019\u0001<\u0002)I,w-[:uKJ$Vm\u001d;U_&;gn\u001c:f)-i\u00151QAC\u0003\u000f\u000bI)a#\t\u000f\u0005mC\u00021\u0001\u0002\u0002!9\u0011\u0011\u0004\u0007A\u0002\u0005}\u0003bBA:\u0019\u0001\u0007\u0011\u0011\u0001\u0005\u0007[2\u0001\r!a\u001e\t\u000bUd\u0001\u0019\u0001<\u0003EI+7/\u001e7u\u001f\u001a$\u0016mZ4fI\u0006\u001b\u0018J\u001c<pG\u0006$\u0018n\u001c8P]N#(/\u001b8h\'\ti!\'\u0001\u0003uC\u001e\u001c\u0018A\u0002\u001fj]&$h\b\u0006\u0005\u0002\u0018\u0006m\u0015QTAP!\r\tI*D\u0007\u0002\u0001!9\u00111L\tA\u0002\u0005\u0005\u0001bBAI#\u0001\u0007\u0011q\f\u0005\u0006kF\u0001\rA^\u0001\u0003S:$2!TAS\u0011\u0019i\'\u0003\"a\u0001]\u0006\u0011\u0011n\u001d\u000b\u0004\u001b\u0006-\u0006bB7\u0014\t\u0003\u0007\u0011Q\u0016\t\u0005g=\fy\u000bE\u0002:\u0003cK1!a--\u0005A\u0001VM\u001c3j]\u001e\u001cF/\u0019;f[\u0016tG/\u0001\u0004jO:|\'/\u001a\u000b\u0004\u001b\u0006e\u0006BB7\u0015\t\u0003\u0007aNA\u000bGe\u0016,7\u000b]3d\'R\u0014\u0018N\\4Xe\u0006\u0004\b/\u001a:\u0014\u0005U\u0011\u0014AB:ue&tw\r\u0006\u0004\u0002D\u0006\u0015\u0017q\u0019\t\u0004\u00033+\u0002bBA`1\u0001\u0007\u0011\u0011\u0001\u0005\u0006kb\u0001\rA^\u0001\u0007I5Lg.^:\u0015\u00075\u000bi\r\u0003\u0005\u0002Pf!\t\u0019AAi\u0003\r1WO\u001c\t\u0004g=lEcA\'\u0002V\"9\u0011q\u001b\u000e\u0005\u0002\u0004q\u0017!\u00014\u0015\u00075\u000bY\u000eC\u0004\u0002Xn!\t\u0019\u00018\u0015\u00075\u000by\u000e\u0003\u0005\u0002Xr!\t\u0019AAW\u0003!!\u0018mZ4fI\u0006\u001bHCBAL\u0003K\fI\u000fC\u0004\u0002hv\u0001\r!!\t\u0002\u0019\u0019L\'o\u001d;UKN$H+Y4\t\u000f\u0005-X\u00041\u0001\u0002\u001c\u0005iq\u000e\u001e5feR+7\u000f\u001e+bON\fadY8om\u0016\u0014H\u000fV8Ge\u0016,7\u000b]3d\'R\u0014\u0018N\\4Xe\u0006\u0004\b/\u001a:\u0015\t\u0005E\u0018Q\u001f\u000b\u0005\u0003\u0007\f\u0019\u0010C\u0003v=\u0001\u000fa\u000fC\u0004\u0002xz\u0001\r!!\u0001\u0002\u0003M,\"!a?\u0011\u0011\u0005\r\u0011Q`A\u0001\u0005\u0003IA!a@\u0002\u0016\t\u0019Q*\u00199\u0011\r\u0005\r!1AA\u0001\u0013\u0011\u0011)!!\u0006\u0003\u0007M+G/A\u0004sk:$Vm\u001d;\u0015\r\t-!\u0011\u0003B\u000b!\rI$QB\u0005\u0004\u0005\u001fa#AB*uCR,8\u000fC\u0004\u0003\u0014\u0001\u0002\r!!\u0001\u0002\u0011Q,7\u000f\u001e(b[\u0016DqAa\u0006!\u0001\u0004\u0011I\"\u0001\u0003be\u001e\u001c\bcA\u001d\u0003\u001c%\u0019!Q\u0004\u0017\u0003\t\u0005\u0013xm]\u0001\teVtG+Z:ugR1!1\u0002B\u0012\u0005WAqAa\u0005\"\u0001\u0004\u0011)\u0003E\u00034\u0005O\t\t!C\u0002\u0003*Q\u0012aa\u00149uS>t\u0007b\u0002B\fC\u0001\u0007!\u0011D\u0001\ni\u0016\u001cHOT1nKN,\"A!\u0001\u0002\u0007I,h\u000e\u0006\u0004\u0003\f\tU\"q\u0007\u0005\b\u0005\'\u0019\u0003\u0019\u0001B\u0013\u0011\u001d\u00119b\ta\u0001\u00053\taAY3iCZ,WC\u0001B\u001f!\u0011\u0011yD!\u0012\u000e\u0005\t\u0005#b\u0001B\"Y\u0005)a/\u001a:cg&!!q\tB!\u0005)\u0011U\r[1wK^{\'\u000fZ\u0001\ngRLH.\u001a(b[\u0016,\"!!\u0001)\u0017\u0015\u0012yE!\u0016\u0003X\tm#Q\f\t\u0004g\tE\u0013b\u0001B*i\tQA-\u001a9sK\u000e\fG/\u001a3\u0002\u000f5,7o]1hK\u0006\u0012!\u0011L\u0001})\",\u0007e\u001d;zY\u0016t\u0015-\\3!Y&4WmY=dY\u0016\u0004S.\u001a;i_\u0012\u0004\u0003.Y:!E\u0016,g\u000e\t3faJ,7-\u0019;fI\u0002\ng\u000e\u001a\u0011xS2d\u0007EY3!e\u0016lwN^3eA%t\u0007%\u0019\u0011gkR,(/\u001a\u0011wKJ\u001c\u0018n\u001c8!_\u001a\u00043kY1mCR+7\u000f\u001e\u0011xSRD\u0007E\\8!e\u0016\u0004H.Y2f[\u0016tGOL\u0001\u0006g&t7-Z\u0011\u0003\u0005?\nQa\r\u00182]A\n1\u0002^3ti\u0012\u000bG/\u0019$peR1!Q\rB6\u0005[\u00022!\u000fB4\u0013\r\u0011I\u0007\f\u0002\t)\u0016\u001cH\u000fR1uC\"9!1\u0003\u0014A\u0002\u0005\u0005\u0001\"\u0003B8MA\u0005\t\u0019\u0001B9\u00031!\b.Z\"p]\u001aLw-T1q!\rI$1O\u0005\u0004\u0005kb#!C\"p]\u001aLw-T1q\u0003U!Xm\u001d;ECR\fgi\u001c:%I\u00164\u0017-\u001e7uII*\"Aa\u001f+\t\tE$QP\u0016\u0003\u0005\u007f\u0002BA!!\u0003\f6\u0011!1\u0011\u0006\u0005\u0005\u000b\u00139)A\u0005v]\u000eDWmY6fI*\u0019!\u0011\u0012\u001b\u0002\u0015\u0005tgn\u001c;bi&|g.\u0003\u0003\u0003\u000e\n\r%!E;oG\",7m[3e-\u0006\u0014\u0018.\u00198dK\u0006I1/\u001e9fe\u0012\u0012XO\u001c\u000b\u0007\u0005\u0017\u0011\u0019J!&\t\u000f\tM\u0001\u00061\u0001\u0003&!9!q\u0003\u0015A\u0002\te\u0011\u0002\u0002B\u0019\u00053K1Aa\'-\u0005\u0015\u0019V/\u001b;fQ\u001d\u0001!q\u0014BS\u0005O\u00032!\u000fBQ\u0013\r\u0011\u0019\u000b\f\u0002\b\r&tG-\u001a:t\u0003\u00151\u0018\r\\;fY\t\u0011I+\t\u0002\u0003,\u0006!sN]4/g\u000e\fG.\u0019;fgRtc-\u001b8eKJ\u001chF\u0012:fKN\u0003Xm\u0019$j]\u0012,\'\u000f"
    )
BootstrapMethods:
  0: #147 REF_invokeStatic java/lang/invoke/LambdaMetafactory.altMetafactory:(Ljava/lang/invoke/MethodHandles$Lookup;Ljava/lang/String;Ljava/lang/invoke/MethodType;[Ljava/lang/Object;)Ljava/lang/invoke/CallSite;
    Method arguments:
      #132 ()Ljava/lang/Object;
      #137 REF_invokeStatic org/scalatest/freespec/AnyFreeSpecLike.$anonfun$registerTestImpl$1:()Ljava/lang/String;
      #138 ()Ljava/lang/String;
      #139 5
      #140 1
      #138 ()Ljava/lang/String;
  1: #147 REF_invokeStatic java/lang/invoke/LambdaMetafactory.altMetafactory:(Ljava/lang/invoke/MethodHandles$Lookup;Ljava/lang/String;Ljava/lang/invoke/MethodType;[Ljava/lang/Object;)Ljava/lang/invoke/CallSite;
    Method arguments:
      #132 ()Ljava/lang/Object;
      #185 REF_invokeStatic org/scalatest/freespec/AnyFreeSpecLike.$anonfun$registerIgnoredTestImpl$1:()Ljava/lang/String;
      #138 ()Ljava/lang/String;
      #139 5
      #140 1
      #138 ()Ljava/lang/String;
  2: #147 REF_invokeStatic java/lang/invoke/LambdaMetafactory.altMetafactory:(Ljava/lang/invoke/MethodHandles$Lookup;Ljava/lang/String;Ljava/lang/invoke/MethodType;[Ljava/lang/Object;)Ljava/lang/invoke/CallSite;
    Method arguments:
      #132 ()Ljava/lang/Object;
      #210 REF_invokeStatic org/scalatest/freespec/AnyFreeSpecLike.$anonfun$registerTestToRun$1:()Ljava/lang/String;
      #138 ()Ljava/lang/String;
      #139 5
      #140 1
      #138 ()Ljava/lang/String;
  3: #147 REF_invokeStatic java/lang/invoke/LambdaMetafactory.altMetafactory:(Ljava/lang/invoke/MethodHandles$Lookup;Ljava/lang/String;Ljava/lang/invoke/MethodType;[Ljava/lang/Object;)Ljava/lang/invoke/CallSite;
    Method arguments:
      #132 ()Ljava/lang/Object;
      #220 REF_invokeStatic org/scalatest/freespec/AnyFreeSpecLike.$anonfun$registerTestToIgnore$1:()Ljava/lang/String;
      #138 ()Ljava/lang/String;
      #139 5
      #140 1
      #138 ()Ljava/lang/String;
  4: #147 REF_invokeStatic java/lang/invoke/LambdaMetafactory.altMetafactory:(Ljava/lang/invoke/MethodHandles$Lookup;Ljava/lang/String;Ljava/lang/invoke/MethodType;[Ljava/lang/Object;)Ljava/lang/invoke/CallSite;
    Method arguments:
      #262 (Ljava/lang/Object;)Ljava/lang/Object;
      #267 REF_invokeStatic org/scalatest/freespec/AnyFreeSpecLike.$anonfun$runTest$1:(Lorg/scalatest/freespec/AnyFreeSpecLike;Lorg/scalatest/Args;Ljava/lang/String;Lorg/scalatest/SuperEngine$TestLeaf;)Lorg/scalatest/Outcome;
      #269 (Lorg/scalatest/SuperEngine$TestLeaf;)Lorg/scalatest/Outcome;
      #139 5
      #140 1
      #269 (Lorg/scalatest/SuperEngine$TestLeaf;)Lorg/scalatest/Outcome;
  5: #147 REF_invokeStatic java/lang/invoke/LambdaMetafactory.altMetafactory:(Ljava/lang/invoke/MethodHandles$Lookup;Ljava/lang/String;Ljava/lang/invoke/MethodType;[Ljava/lang/Object;)Ljava/lang/invoke/CallSite;
    Method arguments:
      #285 (Ljava/lang/Object;Ljava/lang/Object;)Ljava/lang/Object;
      #289 REF_invokeStatic org/scalatest/freespec/AnyFreeSpecLike.$anonfun$runTests$1:(Lorg/scalatest/freespec/AnyFreeSpecLike;Ljava/lang/String;Lorg/scalatest/Args;)Lorg/scalatest/Status;
      #290 (Ljava/lang/String;Lorg/scalatest/Args;)Lorg/scalatest/Status;
      #139 5
      #140 1
      #290 (Ljava/lang/String;Lorg/scalatest/Args;)Lorg/scalatest/Status;
  6: #147 REF_invokeStatic java/lang/invoke/LambdaMetafactory.altMetafactory:(Ljava/lang/invoke/MethodHandles$Lookup;Ljava/lang/String;Ljava/lang/invoke/MethodType;[Ljava/lang/Object;)Ljava/lang/invoke/CallSite;
    Method arguments:
      #285 (Ljava/lang/Object;Ljava/lang/Object;)Ljava/lang/Object;
      #324 REF_invokeStatic org/scalatest/freespec/AnyFreeSpecLike.$anonfun$run$1:(Lorg/scalatest/freespec/AnyFreeSpecLike;Lscala/Option;Lorg/scalatest/Args;)Lorg/scalatest/Status;
      #325 (Lscala/Option;Lorg/scalatest/Args;)Lorg/scalatest/Status;
      #139 5
      #140 1
      #325 (Lscala/Option;Lorg/scalatest/Args;)Lorg/scalatest/Status;
  7: #147 REF_invokeStatic java/lang/invoke/LambdaMetafactory.altMetafactory:(Ljava/lang/invoke/MethodHandles$Lookup;Ljava/lang/String;Ljava/lang/invoke/MethodType;[Ljava/lang/Object;)Ljava/lang/invoke/CallSite;
    Method arguments:
      #132 ()Ljava/lang/Object;
      #406 REF_invokeStatic org/scalatest/freespec/AnyFreeSpecLike.$anonfun$engine$1:()Ljava/lang/String;
      #138 ()Ljava/lang/String;
      #139 5
      #140 1
      #138 ()Ljava/lang/String;
  8: #434 REF_invokeStatic scala/runtime/LambdaDeserialize.bootstrap:(Ljava/lang/invoke/MethodHandles$Lookup;Ljava/lang/String;Ljava/lang/invoke/MethodType;[Ljava/lang/invoke/MethodHandle;)Ljava/lang/invoke/CallSite;
    Method arguments:
      #406 REF_invokeStatic org/scalatest/freespec/AnyFreeSpecLike.$anonfun$engine$1:()Ljava/lang/String;
      #185 REF_invokeStatic org/scalatest/freespec/AnyFreeSpecLike.$anonfun$registerIgnoredTestImpl$1:()Ljava/lang/String;
      #137 REF_invokeStatic org/scalatest/freespec/AnyFreeSpecLike.$anonfun$registerTestImpl$1:()Ljava/lang/String;
      #220 REF_invokeStatic org/scalatest/freespec/AnyFreeSpecLike.$anonfun$registerTestToIgnore$1:()Ljava/lang/String;
      #210 REF_invokeStatic org/scalatest/freespec/AnyFreeSpecLike.$anonfun$registerTestToRun$1:()Ljava/lang/String;
      #324 REF_invokeStatic org/scalatest/freespec/AnyFreeSpecLike.$anonfun$run$1:(Lorg/scalatest/freespec/AnyFreeSpecLike;Lscala/Option;Lorg/scalatest/Args;)Lorg/scalatest/Status;
      #267 REF_invokeStatic org/scalatest/freespec/AnyFreeSpecLike.$anonfun$runTest$1:(Lorg/scalatest/freespec/AnyFreeSpecLike;Lorg/scalatest/Args;Ljava/lang/String;Lorg/scalatest/SuperEngine$TestLeaf;)Lorg/scalatest/Outcome;
      #289 REF_invokeStatic org/scalatest/freespec/AnyFreeSpecLike.$anonfun$runTests$1:(Lorg/scalatest/freespec/AnyFreeSpecLike;Ljava/lang/String;Lorg/scalatest/Args;)Lorg/scalatest/Status;
  ScalaInlineInfo: length = 0x103 (unknown attribute)
   01 00 00 33 01 68 00 86 01 00 B6 00 86 01 00 85
   00 86 01 00 D9 00 86 01 00 CF 00 86 01 01 41 01
   16 01 01 07 01 08 01 01 1E 00 FF 01 01 92 01 93
   01 00 63 00 64 00 00 61 00 62 01 01 4B 01 4C 00
   00 E1 00 E2 00 00 DE 00 DF 01 00 40 00 41 00 00
   3D 00 3E 01 01 7A 01 7B 01 00 6E 00 6F 00 00 6C
   00 6D 01 00 58 00 59 00 00 56 00 57 01 00 3B 00
   3C 00 00 D6 00 CA 01 00 D5 00 C6 01 00 C9 00 CA
   01 00 C5 00 C6 01 00 37 00 38 01 00 33 00 34 00
   00 30 00 31 00 00 35 00 36 00 00 BB 00 78 01 00
   C0 00 B0 01 00 B5 00 78 01 00 99 00 78 01 00 AF
   00 B0 01 00 77 00 78 01 01 3E 00 38 00 01 3D 01
   16 01 01 00 01 01 00 00 FE 00 FF 01 01 17 00 38
   00 01 15 01 16 01 01 4D 00 86 00 00 EA 00 EB 00
   00 E8 00 E9 01 01 51 01 52 00 01 4E 01 4F 01 01
   5C 01 5D 00 01 5A 01 5B 01 01 2C 01 2D 00 01 2A
   01 2B 01
  ScalaSig: length = 0x3 (unknown attribute)
   05 02 00
