Classfile /Users/mw/Projects/slang-braindump/.jar/jar11/assemble/slang-braindump/assemble/content/org/scalatest/freespec/FixtureAnyFreeSpecLike$FreeSpecStringWrapper.class
  Last modified May 29, 2022; size 8318 bytes
  SHA-256 checksum 8202ebb044411ae4eecc4cbb4b63976ff049e0509b2892af3c3b22255edeeb43
  Compiled from "FixtureAnyFreeSpecLike.scala"
public final class org.scalatest.freespec.FixtureAnyFreeSpecLike$FreeSpecStringWrapper
  minor version: 0
  major version: 52
  flags: (0x0031) ACC_PUBLIC, ACC_FINAL, ACC_SUPER
  this_class: #2                          // org/scalatest/freespec/FixtureAnyFreeSpecLike$FreeSpecStringWrapper
  super_class: #4                         // java/lang/Object
  interfaces: 0, fields: 3, methods: 14, attributes: 5
Constant pool:
    #1 = Utf8               org/scalatest/freespec/FixtureAnyFreeSpecLike$FreeSpecStringWrapper
    #2 = Class              #1            // org/scalatest/freespec/FixtureAnyFreeSpecLike$FreeSpecStringWrapper
    #3 = Utf8               java/lang/Object
    #4 = Class              #3            // java/lang/Object
    #5 = Utf8               FixtureAnyFreeSpecLike.scala
    #6 = Utf8               java/lang/invoke/MethodHandles$Lookup
    #7 = Class              #6            // java/lang/invoke/MethodHandles$Lookup
    #8 = Utf8               java/lang/invoke/MethodHandles
    #9 = Class              #8            // java/lang/invoke/MethodHandles
   #10 = Utf8               Lookup
   #11 = Utf8               org/scalatest/freespec/FixtureAnyFreeSpecLike
   #12 = Class              #11           // org/scalatest/freespec/FixtureAnyFreeSpecLike
   #13 = Utf8               FreeSpecStringWrapper
   #14 = Utf8               org/scalatest/freespec/FixtureAnyFreeSpecLike$ResultOfTaggedAsInvocationOnString
   #15 = Class              #14           // org/scalatest/freespec/FixtureAnyFreeSpecLike$ResultOfTaggedAsInvocationOnString
   #16 = Utf8               ResultOfTaggedAsInvocationOnString
   #17 = Utf8               string
   #18 = Utf8               Ljava/lang/String;
   #19 = Utf8               pos
   #20 = Utf8               Lorg/scalactic/source/Position;
   #21 = Utf8               $outer
   #22 = Utf8               Lorg/scalatest/freespec/FixtureAnyFreeSpecLike;
   #23 = Utf8               $minus
   #24 = Utf8               (Lscala/Function0;)V
   #25 = Utf8               (Lscala/Function0<Lscala/runtime/BoxedUnit;>;)V
   #26 = Utf8               fun
   #27 = Utf8               java/lang/Throwable
   #28 = Class              #27           // java/lang/Throwable
   #29 = NameAndType        #21:#22       // $outer:Lorg/scalatest/freespec/FixtureAnyFreeSpecLike;
   #30 = Fieldref           #2.#29        // org/scalatest/freespec/FixtureAnyFreeSpecLike$FreeSpecStringWrapper.$outer:Lorg/scalatest/freespec/FixtureAnyFreeSpecLike;
   #31 = Utf8               org$scalatest$freespec$FixtureAnyFreeSpecLike$$engine
   #32 = Utf8               ()Lorg/scalatest/FixtureEngine;
   #33 = NameAndType        #31:#32       // org$scalatest$freespec$FixtureAnyFreeSpecLike$$engine:()Lorg/scalatest/FixtureEngine;
   #34 = InterfaceMethodref #12.#33       // org/scalatest/freespec/FixtureAnyFreeSpecLike.org$scalatest$freespec$FixtureAnyFreeSpecLike$$engine:()Lorg/scalatest/FixtureEngine;
   #35 = NameAndType        #17:#18       // string:Ljava/lang/String;
   #36 = Fieldref           #2.#35        // org/scalatest/freespec/FixtureAnyFreeSpecLike$FreeSpecStringWrapper.string:Ljava/lang/String;
   #37 = Utf8               scala/None$
   #38 = Class              #37           // scala/None$
   #39 = Utf8               MODULE$
   #40 = Utf8               Lscala/None$;
   #41 = NameAndType        #39:#40       // MODULE$:Lscala/None$;
   #42 = Fieldref           #38.#41       // scala/None$.MODULE$:Lscala/None$;
   #43 = Utf8               ()Ljava/lang/Object;
   #44 = MethodType         #43           //  ()Ljava/lang/Object;
   #45 = Utf8               $anonfun$$minus$1
   #46 = Utf8               ()Ljava/lang/String;
   #47 = NameAndType        #45:#46       // $anonfun$$minus$1:()Ljava/lang/String;
   #48 = Methodref          #2.#47        // org/scalatest/freespec/FixtureAnyFreeSpecLike$FreeSpecStringWrapper.$anonfun$$minus$1:()Ljava/lang/String;
   #49 = MethodHandle       6:#48         // REF_invokeStatic org/scalatest/freespec/FixtureAnyFreeSpecLike$FreeSpecStringWrapper.$anonfun$$minus$1:()Ljava/lang/String;
   #50 = MethodType         #46           //  ()Ljava/lang/String;
   #51 = Integer            5
   #52 = Integer            1
   #53 = Utf8               java/lang/invoke/LambdaMetafactory
   #54 = Class              #53           // java/lang/invoke/LambdaMetafactory
   #55 = Utf8               altMetafactory
   #56 = Utf8               (Ljava/lang/invoke/MethodHandles$Lookup;Ljava/lang/String;Ljava/lang/invoke/MethodType;[Ljava/lang/Object;)Ljava/lang/invoke/CallSite;
   #57 = NameAndType        #55:#56       // altMetafactory:(Ljava/lang/invoke/MethodHandles$Lookup;Ljava/lang/String;Ljava/lang/invoke/MethodType;[Ljava/lang/Object;)Ljava/lang/invoke/CallSite;
   #58 = Methodref          #54.#57       // java/lang/invoke/LambdaMetafactory.altMetafactory:(Ljava/lang/invoke/MethodHandles$Lookup;Ljava/lang/String;Ljava/lang/invoke/MethodType;[Ljava/lang/Object;)Ljava/lang/invoke/CallSite;
   #59 = MethodHandle       6:#58         // REF_invokeStatic java/lang/invoke/LambdaMetafactory.altMetafactory:(Ljava/lang/invoke/MethodHandles$Lookup;Ljava/lang/String;Ljava/lang/invoke/MethodType;[Ljava/lang/Object;)Ljava/lang/invoke/CallSite;
   #60 = Utf8               apply
   #61 = Utf8               ()Lscala/Function0;
   #62 = NameAndType        #60:#61       // apply:()Lscala/Function0;
   #63 = InvokeDynamic      #0:#62        // #0:apply:()Lscala/Function0;
   #64 = Utf8               sourceFileName
   #65 = NameAndType        #64:#46       // sourceFileName:()Ljava/lang/String;
   #66 = InterfaceMethodref #12.#65       // org/scalatest/freespec/FixtureAnyFreeSpecLike.sourceFileName:()Ljava/lang/String;
   #67 = Utf8               -
   #68 = String             #67           // -
   #69 = Utf8               scala/Some
   #70 = Class              #69           // scala/Some
   #71 = NameAndType        #19:#20       // pos:Lorg/scalactic/source/Position;
   #72 = Fieldref           #2.#71        // org/scalatest/freespec/FixtureAnyFreeSpecLike$FreeSpecStringWrapper.pos:Lorg/scalactic/source/Position;
   #73 = Utf8               <init>
   #74 = Utf8               (Ljava/lang/Object;)V
   #75 = NameAndType        #73:#74       // "<init>":(Ljava/lang/Object;)V
   #76 = Methodref          #70.#75       // scala/Some."<init>":(Ljava/lang/Object;)V
   #77 = Utf8               org/scalatest/FixtureEngine
   #78 = Class              #77           // org/scalatest/FixtureEngine
   #79 = Utf8               registerNestedBranch
   #80 = Utf8               (Ljava/lang/String;Lscala/Option;Lscala/Function0;Lscala/Function0;Ljava/lang/String;Ljava/lang/String;IILscala/Option;Lscala/Option;)V
   #81 = NameAndType        #79:#80       // registerNestedBranch:(Ljava/lang/String;Lscala/Option;Lscala/Function0;Lscala/Function0;Ljava/lang/String;Ljava/lang/String;IILscala/Option;Lscala/Option;)V
   #82 = Methodref          #78.#81       // org/scalatest/FixtureEngine.registerNestedBranch:(Ljava/lang/String;Lscala/Option;Lscala/Function0;Lscala/Function0;Ljava/lang/String;Ljava/lang/String;IILscala/Option;Lscala/Option;)V
   #83 = Utf8               org/scalatest/exceptions/TestFailedException
   #84 = Class              #83           // org/scalatest/exceptions/TestFailedException
   #85 = Utf8               org/scalatest/exceptions/NotAllowedException
   #86 = Class              #85           // org/scalatest/exceptions/NotAllowedException
   #87 = Utf8               org/scalatest/FailureMessages$
   #88 = Class              #87           // org/scalatest/FailureMessages$
   #89 = Utf8               Lorg/scalatest/FailureMessages$;
   #90 = NameAndType        #39:#89       // MODULE$:Lorg/scalatest/FailureMessages$;
   #91 = Fieldref           #88.#90       // org/scalatest/FailureMessages$.MODULE$:Lorg/scalatest/FailureMessages$;
   #92 = Utf8               assertionShouldBePutInsideInClauseNotDashClause
   #93 = NameAndType        #92:#46       // assertionShouldBePutInsideInClauseNotDashClause:()Ljava/lang/String;
   #94 = Methodref          #88.#93       // org/scalatest/FailureMessages$.assertionShouldBePutInsideInClauseNotDashClause:()Ljava/lang/String;
   #95 = Utf8               position
   #96 = Utf8               ()Lscala/Option;
   #97 = NameAndType        #95:#96       // position:()Lscala/Option;
   #98 = Methodref          #84.#97       // org/scalatest/exceptions/TestFailedException.position:()Lscala/Option;
   #99 = Utf8               $anonfun$$minus$2
  #100 = Utf8               (Lorg/scalatest/freespec/FixtureAnyFreeSpecLike$FreeSpecStringWrapper;)Lorg/scalactic/source/Position;
  #101 = NameAndType        #99:#100      // $anonfun$$minus$2:(Lorg/scalatest/freespec/FixtureAnyFreeSpecLike$FreeSpecStringWrapper;)Lorg/scalactic/source/Position;
  #102 = Methodref          #2.#101       // org/scalatest/freespec/FixtureAnyFreeSpecLike$FreeSpecStringWrapper.$anonfun$$minus$2:(Lorg/scalatest/freespec/FixtureAnyFreeSpecLike$FreeSpecStringWrapper;)Lorg/scalactic/source/Position;
  #103 = MethodHandle       6:#102        // REF_invokeStatic org/scalatest/freespec/FixtureAnyFreeSpecLike$FreeSpecStringWrapper.$anonfun$$minus$2:(Lorg/scalatest/freespec/FixtureAnyFreeSpecLike$FreeSpecStringWrapper;)Lorg/scalactic/source/Position;
  #104 = Utf8               ()Lorg/scalactic/source/Position;
  #105 = MethodType         #104          //  ()Lorg/scalactic/source/Position;
  #106 = Utf8               (Lorg/scalatest/freespec/FixtureAnyFreeSpecLike$FreeSpecStringWrapper;)Lscala/Function0;
  #107 = NameAndType        #60:#106      // apply:(Lorg/scalatest/freespec/FixtureAnyFreeSpecLike$FreeSpecStringWrapper;)Lscala/Function0;
  #108 = InvokeDynamic      #1:#107       // #1:apply:(Lorg/scalatest/freespec/FixtureAnyFreeSpecLike$FreeSpecStringWrapper;)Lscala/Function0;
  #109 = Utf8               scala/Option
  #110 = Class              #109          // scala/Option
  #111 = Utf8               getOrElse
  #112 = Utf8               (Lscala/Function0;)Ljava/lang/Object;
  #113 = NameAndType        #111:#112     // getOrElse:(Lscala/Function0;)Ljava/lang/Object;
  #114 = Methodref          #110.#113     // scala/Option.getOrElse:(Lscala/Function0;)Ljava/lang/Object;
  #115 = Utf8               org/scalactic/source/Position
  #116 = Class              #115          // org/scalactic/source/Position
  #117 = Utf8               (Ljava/lang/String;Lscala/Option;Lorg/scalactic/source/Position;)V
  #118 = NameAndType        #73:#117      // "<init>":(Ljava/lang/String;Lscala/Option;Lorg/scalactic/source/Position;)V
  #119 = Methodref          #86.#118      // org/scalatest/exceptions/NotAllowedException."<init>":(Ljava/lang/String;Lscala/Option;Lorg/scalactic/source/Position;)V
  #120 = Utf8               org/scalatest/exceptions/TestCanceledException
  #121 = Class              #120          // org/scalatest/exceptions/TestCanceledException
  #122 = Methodref          #121.#97      // org/scalatest/exceptions/TestCanceledException.position:()Lscala/Option;
  #123 = Utf8               $anonfun$$minus$3
  #124 = NameAndType        #123:#100     // $anonfun$$minus$3:(Lorg/scalatest/freespec/FixtureAnyFreeSpecLike$FreeSpecStringWrapper;)Lorg/scalactic/source/Position;
  #125 = Methodref          #2.#124       // org/scalatest/freespec/FixtureAnyFreeSpecLike$FreeSpecStringWrapper.$anonfun$$minus$3:(Lorg/scalatest/freespec/FixtureAnyFreeSpecLike$FreeSpecStringWrapper;)Lorg/scalactic/source/Position;
  #126 = MethodHandle       6:#125        // REF_invokeStatic org/scalatest/freespec/FixtureAnyFreeSpecLike$FreeSpecStringWrapper.$anonfun$$minus$3:(Lorg/scalatest/freespec/FixtureAnyFreeSpecLike$FreeSpecStringWrapper;)Lorg/scalactic/source/Position;
  #127 = InvokeDynamic      #2:#107       // #2:apply:(Lorg/scalatest/freespec/FixtureAnyFreeSpecLike$FreeSpecStringWrapper;)Lscala/Function0;
  #128 = Utf8               org/scalatest/exceptions/TestRegistrationClosedException
  #129 = Class              #128          // org/scalatest/exceptions/TestRegistrationClosedException
  #130 = Utf8               org/scalatest/exceptions/DuplicateTestNameException
  #131 = Class              #130          // org/scalatest/exceptions/DuplicateTestNameException
  #132 = Utf8               org/scalactic/Prettifier$
  #133 = Class              #132          // org/scalactic/Prettifier$
  #134 = Utf8               Lorg/scalactic/Prettifier$;
  #135 = NameAndType        #39:#134      // MODULE$:Lorg/scalactic/Prettifier$;
  #136 = Fieldref           #133.#135     // org/scalactic/Prettifier$.MODULE$:Lorg/scalactic/Prettifier$;
  #137 = Utf8               default
  #138 = Utf8               ()Lorg/scalactic/Prettifier;
  #139 = NameAndType        #137:#138     // default:()Lorg/scalactic/Prettifier;
  #140 = Methodref          #133.#139     // org/scalactic/Prettifier$.default:()Lorg/scalactic/Prettifier;
  #141 = Utf8               org/scalatest/UnquotedString$
  #142 = Class              #141          // org/scalatest/UnquotedString$
  #143 = Utf8               Lorg/scalatest/UnquotedString$;
  #144 = NameAndType        #39:#143      // MODULE$:Lorg/scalatest/UnquotedString$;
  #145 = Fieldref           #142.#144     // org/scalatest/UnquotedString$.MODULE$:Lorg/scalatest/UnquotedString$;
  #146 = Utf8               getClass
  #147 = Utf8               ()Ljava/lang/Class;
  #148 = NameAndType        #146:#147     // getClass:()Ljava/lang/Class;
  #149 = Methodref          #131.#148     // org/scalatest/exceptions/DuplicateTestNameException.getClass:()Ljava/lang/Class;
  #150 = Utf8               java/lang/Class
  #151 = Class              #150          // java/lang/Class
  #152 = Utf8               getName
  #153 = NameAndType        #152:#46      // getName:()Ljava/lang/String;
  #154 = Methodref          #151.#153     // java/lang/Class.getName:()Ljava/lang/String;
  #155 = Utf8               (Ljava/lang/String;)Lorg/scalatest/UnquotedString;
  #156 = NameAndType        #60:#155      // apply:(Ljava/lang/String;)Lorg/scalatest/UnquotedString;
  #157 = Methodref          #142.#156     // org/scalatest/UnquotedString$.apply:(Ljava/lang/String;)Lorg/scalatest/UnquotedString;
  #158 = Utf8               getMessage
  #159 = NameAndType        #158:#46      // getMessage:()Ljava/lang/String;
  #160 = Methodref          #131.#159     // org/scalatest/exceptions/DuplicateTestNameException.getMessage:()Ljava/lang/String;
  #161 = Utf8               exceptionWasThrownInDashClause
  #162 = Utf8               (Lorg/scalactic/Prettifier;Ljava/lang/Object;Ljava/lang/Object;Ljava/lang/Object;)Ljava/lang/String;
  #163 = NameAndType        #161:#162     // exceptionWasThrownInDashClause:(Lorg/scalactic/Prettifier;Ljava/lang/Object;Ljava/lang/Object;Ljava/lang/Object;)Ljava/lang/String;
  #164 = Methodref          #88.#163      // org/scalatest/FailureMessages$.exceptionWasThrownInDashClause:(Lorg/scalactic/Prettifier;Ljava/lang/Object;Ljava/lang/Object;Ljava/lang/Object;)Ljava/lang/String;
  #165 = Methodref          #131.#97      // org/scalatest/exceptions/DuplicateTestNameException.position:()Lscala/Option;
  #166 = Utf8               $anonfun$$minus$4
  #167 = NameAndType        #166:#100     // $anonfun$$minus$4:(Lorg/scalatest/freespec/FixtureAnyFreeSpecLike$FreeSpecStringWrapper;)Lorg/scalactic/source/Position;
  #168 = Methodref          #2.#167       // org/scalatest/freespec/FixtureAnyFreeSpecLike$FreeSpecStringWrapper.$anonfun$$minus$4:(Lorg/scalatest/freespec/FixtureAnyFreeSpecLike$FreeSpecStringWrapper;)Lorg/scalactic/source/Position;
  #169 = MethodHandle       6:#168        // REF_invokeStatic org/scalatest/freespec/FixtureAnyFreeSpecLike$FreeSpecStringWrapper.$anonfun$$minus$4:(Lorg/scalatest/freespec/FixtureAnyFreeSpecLike$FreeSpecStringWrapper;)Lorg/scalactic/source/Position;
  #170 = InvokeDynamic      #3:#107       // #3:apply:(Lorg/scalatest/freespec/FixtureAnyFreeSpecLike$FreeSpecStringWrapper;)Lscala/Function0;
  #171 = Utf8               org/scalatest/Suite$
  #172 = Class              #171          // org/scalatest/Suite$
  #173 = Utf8               Lorg/scalatest/Suite$;
  #174 = NameAndType        #39:#173      // MODULE$:Lorg/scalatest/Suite$;
  #175 = Fieldref           #172.#174     // org/scalatest/Suite$.MODULE$:Lorg/scalatest/Suite$;
  #176 = Utf8               anExceptionThatShouldCauseAnAbort
  #177 = Utf8               (Ljava/lang/Throwable;)Z
  #178 = NameAndType        #176:#177     // anExceptionThatShouldCauseAnAbort:(Ljava/lang/Throwable;)Z
  #179 = Methodref          #172.#178     // org/scalatest/Suite$.anExceptionThatShouldCauseAnAbort:(Ljava/lang/Throwable;)Z
  #180 = Methodref          #28.#148      // java/lang/Throwable.getClass:()Ljava/lang/Class;
  #181 = Methodref          #28.#159      // java/lang/Throwable.getMessage:()Ljava/lang/String;
  #182 = Utf8               stackDepth
  #183 = Utf8               I
  #184 = Utf8               this
  #185 = Utf8               Lorg/scalatest/freespec/FixtureAnyFreeSpecLike$FreeSpecStringWrapper;
  #186 = Utf8               Lscala/Function0;
  #187 = Utf8               scala/Function0
  #188 = Class              #187          // scala/Function0
  #189 = Utf8               in
  #190 = Utf8               (Lscala/Function1;)V
  #191 = Utf8               (Lscala/Function1<Ljava/lang/Object;Ljava/lang/Object;>;)V
  #192 = Utf8               testFun
  #193 = Utf8               scala/package$
  #194 = Class              #193          // scala/package$
  #195 = Utf8               Lscala/package$;
  #196 = NameAndType        #39:#195      // MODULE$:Lscala/package$;
  #197 = Fieldref           #194.#196     // scala/package$.MODULE$:Lscala/package$;
  #198 = Utf8               List
  #199 = Utf8               ()Lscala/collection/immutable/List$;
  #200 = NameAndType        #198:#199     // List:()Lscala/collection/immutable/List$;
  #201 = Methodref          #194.#200     // scala/package$.List:()Lscala/collection/immutable/List$;
  #202 = Utf8               scala/collection/immutable/Nil$
  #203 = Class              #202          // scala/collection/immutable/Nil$
  #204 = Utf8               Lscala/collection/immutable/Nil$;
  #205 = NameAndType        #39:#204      // MODULE$:Lscala/collection/immutable/Nil$;
  #206 = Fieldref           #203.#205     // scala/collection/immutable/Nil$.MODULE$:Lscala/collection/immutable/Nil$;
  #207 = Utf8               scala/collection/immutable/List$
  #208 = Class              #207          // scala/collection/immutable/List$
  #209 = Utf8               (Lscala/collection/immutable/Seq;)Ljava/lang/Object;
  #210 = NameAndType        #60:#209      // apply:(Lscala/collection/immutable/Seq;)Ljava/lang/Object;
  #211 = Methodref          #208.#210     // scala/collection/immutable/List$.apply:(Lscala/collection/immutable/Seq;)Ljava/lang/Object;
  #212 = Utf8               scala/collection/immutable/List
  #213 = Class              #212          // scala/collection/immutable/List
  #214 = String             #189          // in
  #215 = Utf8               org$scalatest$freespec$FixtureAnyFreeSpecLike$$registerTestToRun
  #216 = Utf8               (Ljava/lang/String;Lscala/collection/immutable/List;Ljava/lang/String;Lscala/Function1;Lorg/scalactic/source/Position;)V
  #217 = NameAndType        #215:#216     // org$scalatest$freespec$FixtureAnyFreeSpecLike$$registerTestToRun:(Ljava/lang/String;Lscala/collection/immutable/List;Ljava/lang/String;Lscala/Function1;Lorg/scalactic/source/Position;)V
  #218 = InterfaceMethodref #12.#217      // org/scalatest/freespec/FixtureAnyFreeSpecLike.org$scalatest$freespec$FixtureAnyFreeSpecLike$$registerTestToRun:(Ljava/lang/String;Lscala/collection/immutable/List;Ljava/lang/String;Lscala/Function1;Lorg/scalactic/source/Position;)V
  #219 = Utf8               Lscala/Function1;
  #220 = Utf8               (Lscala/Function0<Ljava/lang/Object;>;)V
  #221 = Utf8               org/scalatest/fixture/NoArgTestWrapper
  #222 = Class              #221          // org/scalatest/fixture/NoArgTestWrapper
  #223 = NameAndType        #73:#24       // "<init>":(Lscala/Function0;)V
  #224 = Methodref          #222.#223     // org/scalatest/fixture/NoArgTestWrapper."<init>":(Lscala/Function0;)V
  #225 = Utf8               is
  #226 = Utf8               (Lscala/Function0<Lorg/scalatest/PendingStatement;>;)V
  #227 = String             #225          // is
  #228 = Utf8               (Ljava/lang/Object;)Ljava/lang/Object;
  #229 = MethodType         #228          //  (Ljava/lang/Object;)Ljava/lang/Object;
  #230 = Utf8               $anonfun$is$2
  #231 = Utf8               (Lscala/Function0;Ljava/lang/Object;)Lorg/scalatest/PendingStatement;
  #232 = NameAndType        #230:#231     // $anonfun$is$2:(Lscala/Function0;Ljava/lang/Object;)Lorg/scalatest/PendingStatement;
  #233 = Methodref          #2.#232       // org/scalatest/freespec/FixtureAnyFreeSpecLike$FreeSpecStringWrapper.$anonfun$is$2:(Lscala/Function0;Ljava/lang/Object;)Lorg/scalatest/PendingStatement;
  #234 = MethodHandle       6:#233        // REF_invokeStatic org/scalatest/freespec/FixtureAnyFreeSpecLike$FreeSpecStringWrapper.$anonfun$is$2:(Lscala/Function0;Ljava/lang/Object;)Lorg/scalatest/PendingStatement;
  #235 = Utf8               (Ljava/lang/Object;)Lorg/scalatest/PendingStatement;
  #236 = MethodType         #235          //  (Ljava/lang/Object;)Lorg/scalatest/PendingStatement;
  #237 = Utf8               (Lscala/Function0;)Lscala/Function1;
  #238 = NameAndType        #60:#237      // apply:(Lscala/Function0;)Lscala/Function1;
  #239 = InvokeDynamic      #4:#238       // #4:apply:(Lscala/Function0;)Lscala/Function1;
  #240 = Utf8               org$scalatest$freespec$FixtureAnyFreeSpecLike$$registerPendingTestToRun
  #241 = NameAndType        #240:#216     // org$scalatest$freespec$FixtureAnyFreeSpecLike$$registerPendingTestToRun:(Ljava/lang/String;Lscala/collection/immutable/List;Ljava/lang/String;Lscala/Function1;Lorg/scalactic/source/Position;)V
  #242 = InterfaceMethodref #12.#241      // org/scalatest/freespec/FixtureAnyFreeSpecLike.org$scalatest$freespec$FixtureAnyFreeSpecLike$$registerPendingTestToRun:(Ljava/lang/String;Lscala/collection/immutable/List;Ljava/lang/String;Lscala/Function1;Lorg/scalactic/source/Position;)V
  #243 = Utf8               ignore
  #244 = String             #243          // ignore
  #245 = Utf8               org$scalatest$freespec$FixtureAnyFreeSpecLike$$registerTestToIgnore
  #246 = NameAndType        #245:#216     // org$scalatest$freespec$FixtureAnyFreeSpecLike$$registerTestToIgnore:(Ljava/lang/String;Lscala/collection/immutable/List;Ljava/lang/String;Lscala/Function1;Lorg/scalactic/source/Position;)V
  #247 = InterfaceMethodref #12.#246      // org/scalatest/freespec/FixtureAnyFreeSpecLike.org$scalatest$freespec$FixtureAnyFreeSpecLike$$registerTestToIgnore:(Ljava/lang/String;Lscala/collection/immutable/List;Ljava/lang/String;Lscala/Function1;Lorg/scalactic/source/Position;)V
  #248 = Utf8               taggedAs
  #249 = Utf8               (Lorg/scalatest/Tag;Lscala/collection/immutable/Seq;)Lorg/scalatest/freespec/FixtureAnyFreeSpecLike$ResultOfTaggedAsInvocationOnString;
  #250 = Utf8               (Lorg/scalatest/Tag;Lscala/collection/immutable/Seq<Lorg/scalatest/Tag;>;)Lorg/scalatest/freespec/FixtureAnyFreeSpecLike$ResultOfTaggedAsInvocationOnString;
  #251 = Utf8               firstTestTag
  #252 = Utf8               otherTestTags
  #253 = Utf8               scala/collection/immutable/Seq
  #254 = Class              #253          // scala/collection/immutable/Seq
  #255 = Utf8               toList
  #256 = Utf8               ()Lscala/collection/immutable/List;
  #257 = NameAndType        #255:#256     // toList:()Lscala/collection/immutable/List;
  #258 = InterfaceMethodref #254.#257     // scala/collection/immutable/Seq.toList:()Lscala/collection/immutable/List;
  #259 = Utf8               $colon$colon
  #260 = Utf8               (Ljava/lang/Object;)Lscala/collection/immutable/List;
  #261 = NameAndType        #259:#260     // $colon$colon:(Ljava/lang/Object;)Lscala/collection/immutable/List;
  #262 = Methodref          #213.#261     // scala/collection/immutable/List.$colon$colon:(Ljava/lang/Object;)Lscala/collection/immutable/List;
  #263 = Utf8               (Lorg/scalatest/freespec/FixtureAnyFreeSpecLike;Ljava/lang/String;Lscala/collection/immutable/List;Lorg/scalactic/source/Position;)V
  #264 = NameAndType        #73:#263      // "<init>":(Lorg/scalatest/freespec/FixtureAnyFreeSpecLike;Ljava/lang/String;Lscala/collection/immutable/List;Lorg/scalactic/source/Position;)V
  #265 = Methodref          #15.#264      // org/scalatest/freespec/FixtureAnyFreeSpecLike$ResultOfTaggedAsInvocationOnString."<init>":(Lorg/scalatest/freespec/FixtureAnyFreeSpecLike;Ljava/lang/String;Lscala/collection/immutable/List;Lorg/scalactic/source/Position;)V
  #266 = Utf8               tagList
  #267 = Utf8               Lscala/collection/immutable/List;
  #268 = Utf8               Lorg/scalatest/Tag;
  #269 = Utf8               Lscala/collection/immutable/Seq;
  #270 = Utf8               org/scalatest/Resources$
  #271 = Class              #270          // org/scalatest/Resources$
  #272 = Utf8               Lorg/scalatest/Resources$;
  #273 = NameAndType        #39:#272      // MODULE$:Lorg/scalatest/Resources$;
  #274 = Fieldref           #271.#273     // org/scalatest/Resources$.MODULE$:Lorg/scalatest/Resources$;
  #275 = Utf8               dashCannotAppearInsideAnIn
  #276 = NameAndType        #275:#46      // dashCannotAppearInsideAnIn:()Ljava/lang/String;
  #277 = Methodref          #271.#276     // org/scalatest/Resources$.dashCannotAppearInsideAnIn:()Ljava/lang/String;
  #278 = Utf8               $this
  #279 = Utf8               testFun$2
  #280 = Utf8               unusedFixtureParam
  #281 = NameAndType        #60:#43       // apply:()Ljava/lang/Object;
  #282 = InterfaceMethodref #188.#281     // scala/Function0.apply:()Ljava/lang/Object;
  #283 = Utf8               org/scalatest/PendingStatement
  #284 = Class              #283          // org/scalatest/PendingStatement
  #285 = Utf8               Ljava/lang/Object;
  #286 = Utf8               (Lorg/scalatest/freespec/FixtureAnyFreeSpecLike;Ljava/lang/String;Lorg/scalactic/source/Position;)V
  #287 = Utf8               ()V
  #288 = NameAndType        #73:#287      // "<init>":()V
  #289 = Methodref          #4.#288       // java/lang/Object."<init>":()V
  #290 = Utf8               $deserializeLambda$
  #291 = Utf8               (Ljava/lang/invoke/SerializedLambda;)Ljava/lang/Object;
  #292 = Utf8               scala/runtime/LambdaDeserialize
  #293 = Class              #292          // scala/runtime/LambdaDeserialize
  #294 = Utf8               bootstrap
  #295 = Utf8               (Ljava/lang/invoke/MethodHandles$Lookup;Ljava/lang/String;Ljava/lang/invoke/MethodType;[Ljava/lang/invoke/MethodHandle;)Ljava/lang/invoke/CallSite;
  #296 = NameAndType        #294:#295     // bootstrap:(Ljava/lang/invoke/MethodHandles$Lookup;Ljava/lang/String;Ljava/lang/invoke/MethodType;[Ljava/lang/invoke/MethodHandle;)Ljava/lang/invoke/CallSite;
  #297 = Methodref          #293.#296     // scala/runtime/LambdaDeserialize.bootstrap:(Ljava/lang/invoke/MethodHandles$Lookup;Ljava/lang/String;Ljava/lang/invoke/MethodType;[Ljava/lang/invoke/MethodHandle;)Ljava/lang/invoke/CallSite;
  #298 = MethodHandle       6:#297        // REF_invokeStatic scala/runtime/LambdaDeserialize.bootstrap:(Ljava/lang/invoke/MethodHandles$Lookup;Ljava/lang/String;Ljava/lang/invoke/MethodType;[Ljava/lang/invoke/MethodHandle;)Ljava/lang/invoke/CallSite;
  #299 = Utf8               lambdaDeserialize
  #300 = NameAndType        #299:#291     // lambdaDeserialize:(Ljava/lang/invoke/SerializedLambda;)Ljava/lang/Object;
  #301 = InvokeDynamic      #5:#300       // #5:lambdaDeserialize:(Ljava/lang/invoke/SerializedLambda;)Ljava/lang/Object;
  #302 = Utf8               Code
  #303 = Utf8               StackMapTable
  #304 = Utf8               LineNumberTable
  #305 = Utf8               LocalVariableTable
  #306 = Utf8               Signature
  #307 = Utf8               MethodParameters
  #308 = Utf8               InnerClasses
  #309 = Utf8               SourceFile
  #310 = Utf8               BootstrapMethods
  #311 = Utf8               ScalaInlineInfo
  #312 = Utf8               Scala
{
  private final java.lang.String string;
    descriptor: Ljava/lang/String;
    flags: (0x0012) ACC_PRIVATE, ACC_FINAL

  private final org.scalactic.source.Position pos;
    descriptor: Lorg/scalactic/source/Position;
    flags: (0x0012) ACC_PRIVATE, ACC_FINAL

  private final org.scalatest.freespec.FixtureAnyFreeSpecLike $outer;
    descriptor: Lorg/scalatest/freespec/FixtureAnyFreeSpecLike;
    flags: (0x1012) ACC_PRIVATE, ACC_FINAL, ACC_SYNTHETIC

  public void $minus(scala.Function0<scala.runtime.BoxedUnit>);
    descriptor: (Lscala/Function0;)V
    flags: (0x0001) ACC_PUBLIC
    Code:
      stack=13, locals=12, args_size=2
         0: iconst_3
         1: istore_3
         2: aload_0
         3: getfield      #30                 // Field $outer:Lorg/scalatest/freespec/FixtureAnyFreeSpecLike;
         6: invokeinterface #34,  1           // InterfaceMethod org/scalatest/freespec/FixtureAnyFreeSpecLike.org$scalatest$freespec$FixtureAnyFreeSpecLike$$engine:()Lorg/scalatest/FixtureEngine;
        11: aload_0
        12: getfield      #36                 // Field string:Ljava/lang/String;
        15: getstatic     #42                 // Field scala/None$.MODULE$:Lscala/None$;
        18: aload_1
        19: invokedynamic #63,  0             // InvokeDynamic #0:apply:()Lscala/Function0;
        24: aload_0
        25: getfield      #30                 // Field $outer:Lorg/scalatest/freespec/FixtureAnyFreeSpecLike;
        28: invokeinterface #66,  1           // InterfaceMethod org/scalatest/freespec/FixtureAnyFreeSpecLike.sourceFileName:()Ljava/lang/String;
        33: ldc           #68                 // String -
        35: iload_3
        36: bipush        -2
        38: getstatic     #42                 // Field scala/None$.MODULE$:Lscala/None$;
        41: new           #70                 // class scala/Some
        44: dup
        45: aload_0
        46: getfield      #72                 // Field pos:Lorg/scalactic/source/Position;
        49: invokespecial #76                 // Method scala/Some."<init>":(Ljava/lang/Object;)V
        52: invokevirtual #82                 // Method org/scalatest/FixtureEngine.registerNestedBranch:(Ljava/lang/String;Lscala/Option;Lscala/Function0;Lscala/Function0;Ljava/lang/String;Ljava/lang/String;IILscala/Option;Lscala/Option;)V
        55: goto          388
        58: astore        4
        60: aload         4
        62: astore        5
        64: aload         5
        66: instanceof    #84                 // class org/scalatest/exceptions/TestFailedException
        69: ifeq          119
        72: aload         5
        74: checkcast     #84                 // class org/scalatest/exceptions/TestFailedException
        77: astore        6
        79: new           #86                 // class org/scalatest/exceptions/NotAllowedException
        82: dup
        83: getstatic     #91                 // Field org/scalatest/FailureMessages$.MODULE$:Lorg/scalatest/FailureMessages$;
        86: invokevirtual #94                 // Method org/scalatest/FailureMessages$.assertionShouldBePutInsideInClauseNotDashClause:()Ljava/lang/String;
        89: new           #70                 // class scala/Some
        92: dup
        93: aload         6
        95: invokespecial #76                 // Method scala/Some."<init>":(Ljava/lang/Object;)V
        98: aload         6
       100: invokevirtual #98                 // Method org/scalatest/exceptions/TestFailedException.position:()Lscala/Option;
       103: aload_0
       104: invokedynamic #108,  0            // InvokeDynamic #1:apply:(Lorg/scalatest/freespec/FixtureAnyFreeSpecLike$FreeSpecStringWrapper;)Lscala/Function0;
       109: invokevirtual #114                // Method scala/Option.getOrElse:(Lscala/Function0;)Ljava/lang/Object;
       112: checkcast     #116                // class org/scalactic/source/Position
       115: invokespecial #119                // Method org/scalatest/exceptions/NotAllowedException."<init>":(Ljava/lang/String;Lscala/Option;Lorg/scalactic/source/Position;)V
       118: athrow
       119: goto          122
       122: aload         5
       124: instanceof    #121                // class org/scalatest/exceptions/TestCanceledException
       127: ifeq          177
       130: aload         5
       132: checkcast     #121                // class org/scalatest/exceptions/TestCanceledException
       135: astore        7
       137: new           #86                 // class org/scalatest/exceptions/NotAllowedException
       140: dup
       141: getstatic     #91                 // Field org/scalatest/FailureMessages$.MODULE$:Lorg/scalatest/FailureMessages$;
       144: invokevirtual #94                 // Method org/scalatest/FailureMessages$.assertionShouldBePutInsideInClauseNotDashClause:()Ljava/lang/String;
       147: new           #70                 // class scala/Some
       150: dup
       151: aload         7
       153: invokespecial #76                 // Method scala/Some."<init>":(Ljava/lang/Object;)V
       156: aload         7
       158: invokevirtual #122                // Method org/scalatest/exceptions/TestCanceledException.position:()Lscala/Option;
       161: aload_0
       162: invokedynamic #127,  0            // InvokeDynamic #2:apply:(Lorg/scalatest/freespec/FixtureAnyFreeSpecLike$FreeSpecStringWrapper;)Lscala/Function0;
       167: invokevirtual #114                // Method scala/Option.getOrElse:(Lscala/Function0;)Ljava/lang/Object;
       170: checkcast     #116                // class org/scalactic/source/Position
       173: invokespecial #119                // Method org/scalatest/exceptions/NotAllowedException."<init>":(Ljava/lang/String;Lscala/Option;Lorg/scalactic/source/Position;)V
       176: athrow
       177: goto          180
       180: aload         5
       182: instanceof    #129                // class org/scalatest/exceptions/TestRegistrationClosedException
       185: ifeq          198
       188: aload         5
       190: checkcast     #129                // class org/scalatest/exceptions/TestRegistrationClosedException
       193: astore        8
       195: aload         8
       197: athrow
       198: goto          201
       201: aload         5
       203: instanceof    #131                // class org/scalatest/exceptions/DuplicateTestNameException
       206: ifeq          285
       209: aload         5
       211: checkcast     #131                // class org/scalatest/exceptions/DuplicateTestNameException
       214: astore        9
       216: new           #86                 // class org/scalatest/exceptions/NotAllowedException
       219: dup
       220: getstatic     #91                 // Field org/scalatest/FailureMessages$.MODULE$:Lorg/scalatest/FailureMessages$;
       223: getstatic     #136                // Field org/scalactic/Prettifier$.MODULE$:Lorg/scalactic/Prettifier$;
       226: invokevirtual #140                // Method org/scalactic/Prettifier$.default:()Lorg/scalactic/Prettifier;
       229: getstatic     #145                // Field org/scalatest/UnquotedString$.MODULE$:Lorg/scalatest/UnquotedString$;
       232: aload         9
       234: invokevirtual #149                // Method org/scalatest/exceptions/DuplicateTestNameException.getClass:()Ljava/lang/Class;
       237: invokevirtual #154                // Method java/lang/Class.getName:()Ljava/lang/String;
       240: invokevirtual #157                // Method org/scalatest/UnquotedString$.apply:(Ljava/lang/String;)Lorg/scalatest/UnquotedString;
       243: aload_0
       244: getfield      #36                 // Field string:Ljava/lang/String;
       247: aload         9
       249: invokevirtual #160                // Method org/scalatest/exceptions/DuplicateTestNameException.getMessage:()Ljava/lang/String;
       252: invokevirtual #164                // Method org/scalatest/FailureMessages$.exceptionWasThrownInDashClause:(Lorg/scalactic/Prettifier;Ljava/lang/Object;Ljava/lang/Object;Ljava/lang/Object;)Ljava/lang/String;
       255: new           #70                 // class scala/Some
       258: dup
       259: aload         9
       261: invokespecial #76                 // Method scala/Some."<init>":(Ljava/lang/Object;)V
       264: aload         9
       266: invokevirtual #165                // Method org/scalatest/exceptions/DuplicateTestNameException.position:()Lscala/Option;
       269: aload_0
       270: invokedynamic #170,  0            // InvokeDynamic #3:apply:(Lorg/scalatest/freespec/FixtureAnyFreeSpecLike$FreeSpecStringWrapper;)Lscala/Function0;
       275: invokevirtual #114                // Method scala/Option.getOrElse:(Lscala/Function0;)Ljava/lang/Object;
       278: checkcast     #116                // class org/scalactic/source/Position
       281: invokespecial #119                // Method org/scalatest/exceptions/NotAllowedException."<init>":(Ljava/lang/String;Lscala/Option;Lorg/scalactic/source/Position;)V
       284: athrow
       285: goto          288
       288: aload         5
       290: ifnull        367
       293: aload         5
       295: astore        10
       297: getstatic     #175                // Field org/scalatest/Suite$.MODULE$:Lorg/scalatest/Suite$;
       300: aload         10
       302: invokevirtual #179                // Method org/scalatest/Suite$.anExceptionThatShouldCauseAnAbort:(Ljava/lang/Throwable;)Z
       305: ifne          364
       308: new           #86                 // class org/scalatest/exceptions/NotAllowedException
       311: dup
       312: getstatic     #91                 // Field org/scalatest/FailureMessages$.MODULE$:Lorg/scalatest/FailureMessages$;
       315: getstatic     #136                // Field org/scalactic/Prettifier$.MODULE$:Lorg/scalactic/Prettifier$;
       318: invokevirtual #140                // Method org/scalactic/Prettifier$.default:()Lorg/scalactic/Prettifier;
       321: getstatic     #145                // Field org/scalatest/UnquotedString$.MODULE$:Lorg/scalatest/UnquotedString$;
       324: aload         10
       326: invokevirtual #180                // Method java/lang/Throwable.getClass:()Ljava/lang/Class;
       329: invokevirtual #154                // Method java/lang/Class.getName:()Ljava/lang/String;
       332: invokevirtual #157                // Method org/scalatest/UnquotedString$.apply:(Ljava/lang/String;)Lorg/scalatest/UnquotedString;
       335: aload_0
       336: getfield      #36                 // Field string:Ljava/lang/String;
       339: aload         10
       341: invokevirtual #181                // Method java/lang/Throwable.getMessage:()Ljava/lang/String;
       344: invokevirtual #164                // Method org/scalatest/FailureMessages$.exceptionWasThrownInDashClause:(Lorg/scalactic/Prettifier;Ljava/lang/Object;Ljava/lang/Object;Ljava/lang/Object;)Ljava/lang/String;
       347: new           #70                 // class scala/Some
       350: dup
       351: aload         10
       353: invokespecial #76                 // Method scala/Some."<init>":(Ljava/lang/Object;)V
       356: aload_0
       357: getfield      #72                 // Field pos:Lorg/scalactic/source/Position;
       360: invokespecial #119                // Method org/scalatest/exceptions/NotAllowedException."<init>":(Ljava/lang/String;Lscala/Option;Lorg/scalactic/source/Position;)V
       363: athrow
       364: goto          370
       367: goto          370
       370: aload         5
       372: ifnull        382
       375: aload         5
       377: astore        11
       379: aload         11
       381: athrow
       382: goto          385
       385: aload         4
       387: athrow
       388: return
      Exception table:
         from    to  target type
             2    55    58   Class java/lang/Throwable
      StackMapTable: number_of_entries = 15
        frame_type = 255 /* full_frame */
          offset_delta = 58
          locals = [ class org/scalatest/freespec/FixtureAnyFreeSpecLike$FreeSpecStringWrapper, class scala/Function0, top, int ]
          stack = [ class java/lang/Throwable ]
        frame_type = 253 /* append */
          offset_delta = 60
          locals = [ class java/lang/Throwable, class java/lang/Throwable ]
        frame_type = 2 /* same */
        frame_type = 54 /* same */
        frame_type = 2 /* same */
        frame_type = 17 /* same */
        frame_type = 2 /* same */
        frame_type = 251 /* same_frame_extended */
          offset_delta = 83
        frame_type = 2 /* same */
        frame_type = 255 /* full_frame */
          offset_delta = 75
          locals = [ class org/scalatest/freespec/FixtureAnyFreeSpecLike$FreeSpecStringWrapper, class scala/Function0, top, int, class java/lang/Throwable, class java/lang/Throwable, top, top, top, top, class java/lang/Throwable ]
          stack = []
        frame_type = 255 /* full_frame */
          offset_delta = 2
          locals = [ class org/scalatest/freespec/FixtureAnyFreeSpecLike$FreeSpecStringWrapper, class scala/Function0, top, int, class java/lang/Throwable, class java/lang/Throwable ]
          stack = []
        frame_type = 2 /* same */
        frame_type = 11 /* same */
        frame_type = 2 /* same */
        frame_type = 249 /* chop */
          offset_delta = 2
      LineNumberTable:
        line 361: 0
        line 366: 2
        line 369: 60
        line 369: 64
        line 370: 122
        line 371: 180
        line 372: 201
        line 373: 288
        line 374: 370
        line 365: 385
      LocalVariableTable:
        Start  Length  Slot  Name   Signature
            2     386     3 stackDepth   I
            0     389     0  this   Lorg/scalatest/freespec/FixtureAnyFreeSpecLike$FreeSpecStringWrapper;
            0     389     1   fun   Lscala/Function0;
    Signature: #25                          // (Lscala/Function0<Lscala/runtime/BoxedUnit;>;)V
    MethodParameters:
      Name                           Flags
      fun                            final

  public void in(scala.Function1<java.lang.Object, java.lang.Object>);
    descriptor: (Lscala/Function1;)V
    flags: (0x0001) ACC_PUBLIC
    Code:
      stack=6, locals=2, args_size=2
         0: aload_0
         1: getfield      #30                 // Field $outer:Lorg/scalatest/freespec/FixtureAnyFreeSpecLike;
         4: aload_0
         5: getfield      #36                 // Field string:Ljava/lang/String;
         8: getstatic     #197                // Field scala/package$.MODULE$:Lscala/package$;
        11: invokevirtual #201                // Method scala/package$.List:()Lscala/collection/immutable/List$;
        14: getstatic     #206                // Field scala/collection/immutable/Nil$.MODULE$:Lscala/collection/immutable/Nil$;
        17: invokevirtual #211                // Method scala/collection/immutable/List$.apply:(Lscala/collection/immutable/Seq;)Ljava/lang/Object;
        20: checkcast     #213                // class scala/collection/immutable/List
        23: ldc           #214                // String in
        25: aload_1
        26: aload_0
        27: getfield      #72                 // Field pos:Lorg/scalactic/source/Position;
        30: invokeinterface #218,  6          // InterfaceMethod org/scalatest/freespec/FixtureAnyFreeSpecLike.org$scalatest$freespec$FixtureAnyFreeSpecLike$$registerTestToRun:(Ljava/lang/String;Lscala/collection/immutable/List;Ljava/lang/String;Lscala/Function1;Lorg/scalactic/source/Position;)V
        35: return
      LineNumberTable:
        line 397: 0
      LocalVariableTable:
        Start  Length  Slot  Name   Signature
            0      36     0  this   Lorg/scalatest/freespec/FixtureAnyFreeSpecLike$FreeSpecStringWrapper;
            0      36     1 testFun   Lscala/Function1;
    Signature: #191                         // (Lscala/Function1<Ljava/lang/Object;Ljava/lang/Object;>;)V
    MethodParameters:
      Name                           Flags
      testFun                        final

  public void in(scala.Function0<java.lang.Object>);
    descriptor: (Lscala/Function0;)V
    flags: (0x0001) ACC_PUBLIC
    Code:
      stack=7, locals=2, args_size=2
         0: aload_0
         1: getfield      #30                 // Field $outer:Lorg/scalatest/freespec/FixtureAnyFreeSpecLike;
         4: aload_0
         5: getfield      #36                 // Field string:Ljava/lang/String;
         8: getstatic     #197                // Field scala/package$.MODULE$:Lscala/package$;
        11: invokevirtual #201                // Method scala/package$.List:()Lscala/collection/immutable/List$;
        14: getstatic     #206                // Field scala/collection/immutable/Nil$.MODULE$:Lscala/collection/immutable/Nil$;
        17: invokevirtual #211                // Method scala/collection/immutable/List$.apply:(Lscala/collection/immutable/Seq;)Ljava/lang/Object;
        20: checkcast     #213                // class scala/collection/immutable/List
        23: ldc           #214                // String in
        25: new           #222                // class org/scalatest/fixture/NoArgTestWrapper
        28: dup
        29: aload_1
        30: invokespecial #224                // Method org/scalatest/fixture/NoArgTestWrapper."<init>":(Lscala/Function0;)V
        33: aload_0
        34: getfield      #72                 // Field pos:Lorg/scalactic/source/Position;
        37: invokeinterface #218,  6          // InterfaceMethod org/scalatest/freespec/FixtureAnyFreeSpecLike.org$scalatest$freespec$FixtureAnyFreeSpecLike$$registerTestToRun:(Ljava/lang/String;Lscala/collection/immutable/List;Ljava/lang/String;Lscala/Function1;Lorg/scalactic/source/Position;)V
        42: return
      LineNumberTable:
        line 419: 0
      LocalVariableTable:
        Start  Length  Slot  Name   Signature
            0      43     0  this   Lorg/scalatest/freespec/FixtureAnyFreeSpecLike$FreeSpecStringWrapper;
            0      43     1 testFun   Lscala/Function0;
    Signature: #220                         // (Lscala/Function0<Ljava/lang/Object;>;)V
    MethodParameters:
      Name                           Flags
      testFun                        final

  public void is(scala.Function0<org.scalatest.PendingStatement>);
    descriptor: (Lscala/Function0;)V
    flags: (0x0001) ACC_PUBLIC
    Code:
      stack=6, locals=2, args_size=2
         0: aload_0
         1: getfield      #30                 // Field $outer:Lorg/scalatest/freespec/FixtureAnyFreeSpecLike;
         4: aload_0
         5: getfield      #36                 // Field string:Ljava/lang/String;
         8: getstatic     #197                // Field scala/package$.MODULE$:Lscala/package$;
        11: invokevirtual #201                // Method scala/package$.List:()Lscala/collection/immutable/List$;
        14: getstatic     #206                // Field scala/collection/immutable/Nil$.MODULE$:Lscala/collection/immutable/Nil$;
        17: invokevirtual #211                // Method scala/collection/immutable/List$.apply:(Lscala/collection/immutable/Seq;)Ljava/lang/Object;
        20: checkcast     #213                // class scala/collection/immutable/List
        23: ldc           #227                // String is
        25: aload_1
        26: invokedynamic #239,  0            // InvokeDynamic #4:apply:(Lscala/Function0;)Lscala/Function1;
        31: aload_0
        32: getfield      #72                 // Field pos:Lorg/scalactic/source/Position;
        35: invokeinterface #242,  6          // InterfaceMethod org/scalatest/freespec/FixtureAnyFreeSpecLike.org$scalatest$freespec$FixtureAnyFreeSpecLike$$registerPendingTestToRun:(Ljava/lang/String;Lscala/collection/immutable/List;Ljava/lang/String;Lscala/Function1;Lorg/scalactic/source/Position;)V
        40: return
      LineNumberTable:
        line 441: 0
      LocalVariableTable:
        Start  Length  Slot  Name   Signature
            0      41     0  this   Lorg/scalatest/freespec/FixtureAnyFreeSpecLike$FreeSpecStringWrapper;
            0      41     1 testFun   Lscala/Function0;
    Signature: #226                         // (Lscala/Function0<Lorg/scalatest/PendingStatement;>;)V
    MethodParameters:
      Name                           Flags
      testFun                        final

  public void ignore(scala.Function1<java.lang.Object, java.lang.Object>);
    descriptor: (Lscala/Function1;)V
    flags: (0x0001) ACC_PUBLIC
    Code:
      stack=6, locals=2, args_size=2
         0: aload_0
         1: getfield      #30                 // Field $outer:Lorg/scalatest/freespec/FixtureAnyFreeSpecLike;
         4: aload_0
         5: getfield      #36                 // Field string:Ljava/lang/String;
         8: getstatic     #197                // Field scala/package$.MODULE$:Lscala/package$;
        11: invokevirtual #201                // Method scala/package$.List:()Lscala/collection/immutable/List$;
        14: getstatic     #206                // Field scala/collection/immutable/Nil$.MODULE$:Lscala/collection/immutable/Nil$;
        17: invokevirtual #211                // Method scala/collection/immutable/List$.apply:(Lscala/collection/immutable/Seq;)Ljava/lang/Object;
        20: checkcast     #213                // class scala/collection/immutable/List
        23: ldc           #244                // String ignore
        25: aload_1
        26: aload_0
        27: getfield      #72                 // Field pos:Lorg/scalactic/source/Position;
        30: invokeinterface #247,  6          // InterfaceMethod org/scalatest/freespec/FixtureAnyFreeSpecLike.org$scalatest$freespec$FixtureAnyFreeSpecLike$$registerTestToIgnore:(Ljava/lang/String;Lscala/collection/immutable/List;Ljava/lang/String;Lscala/Function1;Lorg/scalactic/source/Position;)V
        35: return
      LineNumberTable:
        line 463: 0
      LocalVariableTable:
        Start  Length  Slot  Name   Signature
            0      36     0  this   Lorg/scalatest/freespec/FixtureAnyFreeSpecLike$FreeSpecStringWrapper;
            0      36     1 testFun   Lscala/Function1;
    Signature: #191                         // (Lscala/Function1<Ljava/lang/Object;Ljava/lang/Object;>;)V
    MethodParameters:
      Name                           Flags
      testFun                        final

  public void ignore(scala.Function0<java.lang.Object>);
    descriptor: (Lscala/Function0;)V
    flags: (0x0001) ACC_PUBLIC
    Code:
      stack=7, locals=2, args_size=2
         0: aload_0
         1: getfield      #30                 // Field $outer:Lorg/scalatest/freespec/FixtureAnyFreeSpecLike;
         4: aload_0
         5: getfield      #36                 // Field string:Ljava/lang/String;
         8: getstatic     #197                // Field scala/package$.MODULE$:Lscala/package$;
        11: invokevirtual #201                // Method scala/package$.List:()Lscala/collection/immutable/List$;
        14: getstatic     #206                // Field scala/collection/immutable/Nil$.MODULE$:Lscala/collection/immutable/Nil$;
        17: invokevirtual #211                // Method scala/collection/immutable/List$.apply:(Lscala/collection/immutable/Seq;)Ljava/lang/Object;
        20: checkcast     #213                // class scala/collection/immutable/List
        23: ldc           #244                // String ignore
        25: new           #222                // class org/scalatest/fixture/NoArgTestWrapper
        28: dup
        29: aload_1
        30: invokespecial #224                // Method org/scalatest/fixture/NoArgTestWrapper."<init>":(Lscala/Function0;)V
        33: aload_0
        34: getfield      #72                 // Field pos:Lorg/scalactic/source/Position;
        37: invokeinterface #247,  6          // InterfaceMethod org/scalatest/freespec/FixtureAnyFreeSpecLike.org$scalatest$freespec$FixtureAnyFreeSpecLike$$registerTestToIgnore:(Ljava/lang/String;Lscala/collection/immutable/List;Ljava/lang/String;Lscala/Function1;Lorg/scalactic/source/Position;)V
        42: return
      LineNumberTable:
        line 485: 0
      LocalVariableTable:
        Start  Length  Slot  Name   Signature
            0      43     0  this   Lorg/scalatest/freespec/FixtureAnyFreeSpecLike$FreeSpecStringWrapper;
            0      43     1 testFun   Lscala/Function0;
    Signature: #220                         // (Lscala/Function0<Ljava/lang/Object;>;)V
    MethodParameters:
      Name                           Flags
      testFun                        final

  public org.scalatest.freespec.FixtureAnyFreeSpecLike$ResultOfTaggedAsInvocationOnString taggedAs(org.scalatest.Tag, scala.collection.immutable.Seq<org.scalatest.Tag>);
    descriptor: (Lorg/scalatest/Tag;Lscala/collection/immutable/Seq;)Lorg/scalatest/freespec/FixtureAnyFreeSpecLike$ResultOfTaggedAsInvocationOnString;
    flags: (0x0001) ACC_PUBLIC
    Code:
      stack=6, locals=5, args_size=3
         0: aload_1
         1: astore        4
         3: aload_2
         4: invokeinterface #258,  1          // InterfaceMethod scala/collection/immutable/Seq.toList:()Lscala/collection/immutable/List;
         9: aload         4
        11: invokevirtual #262                // Method scala/collection/immutable/List.$colon$colon:(Ljava/lang/Object;)Lscala/collection/immutable/List;
        14: astore_3
        15: new           #15                 // class org/scalatest/freespec/FixtureAnyFreeSpecLike$ResultOfTaggedAsInvocationOnString
        18: dup
        19: aload_0
        20: getfield      #30                 // Field $outer:Lorg/scalatest/freespec/FixtureAnyFreeSpecLike;
        23: aload_0
        24: getfield      #36                 // Field string:Ljava/lang/String;
        27: aload_3
        28: aload_0
        29: getfield      #72                 // Field pos:Lorg/scalactic/source/Position;
        32: invokespecial #265                // Method org/scalatest/freespec/FixtureAnyFreeSpecLike$ResultOfTaggedAsInvocationOnString."<init>":(Lorg/scalatest/freespec/FixtureAnyFreeSpecLike;Ljava/lang/String;Lscala/collection/immutable/List;Lorg/scalactic/source/Position;)V
        35: areturn
      LineNumberTable:
        line 508: 0
        line 509: 15
      LocalVariableTable:
        Start  Length  Slot  Name   Signature
           15      20     3 tagList   Lscala/collection/immutable/List;
            0      36     0  this   Lorg/scalatest/freespec/FixtureAnyFreeSpecLike$FreeSpecStringWrapper;
            0      36     1 firstTestTag   Lorg/scalatest/Tag;
            0      36     2 otherTestTags   Lscala/collection/immutable/Seq;
    Signature: #250                         // (Lorg/scalatest/Tag;Lscala/collection/immutable/Seq<Lorg/scalatest/Tag;>;)Lorg/scalatest/freespec/FixtureAnyFreeSpecLike$ResultOfTaggedAsInvocationOnString;
    MethodParameters:
      Name                           Flags
      firstTestTag                   final
      otherTestTags                  final

  public static final java.lang.String $anonfun$$minus$1();
    descriptor: ()Ljava/lang/String;
    flags: (0x1019) ACC_PUBLIC, ACC_STATIC, ACC_FINAL, ACC_SYNTHETIC
    Code:
      stack=1, locals=0, args_size=0
         0: getstatic     #274                // Field org/scalatest/Resources$.MODULE$:Lorg/scalatest/Resources$;
         3: invokevirtual #277                // Method org/scalatest/Resources$.dashCannotAppearInsideAnIn:()Ljava/lang/String;
         6: areturn
      LineNumberTable:
        line 366: 0

  public static final org.scalactic.source.Position $anonfun$$minus$2(org.scalatest.freespec.FixtureAnyFreeSpecLike$FreeSpecStringWrapper);
    descriptor: (Lorg/scalatest/freespec/FixtureAnyFreeSpecLike$FreeSpecStringWrapper;)Lorg/scalactic/source/Position;
    flags: (0x1019) ACC_PUBLIC, ACC_STATIC, ACC_FINAL, ACC_SYNTHETIC
    Code:
      stack=1, locals=1, args_size=1
         0: aload_0
         1: getfield      #72                 // Field pos:Lorg/scalactic/source/Position;
         4: areturn
      LineNumberTable:
        line 369: 0
      LocalVariableTable:
        Start  Length  Slot  Name   Signature
            0       5     0 $this   Lorg/scalatest/freespec/FixtureAnyFreeSpecLike$FreeSpecStringWrapper;
    MethodParameters:
      Name                           Flags
      $this                          final synthetic

  public static final org.scalactic.source.Position $anonfun$$minus$3(org.scalatest.freespec.FixtureAnyFreeSpecLike$FreeSpecStringWrapper);
    descriptor: (Lorg/scalatest/freespec/FixtureAnyFreeSpecLike$FreeSpecStringWrapper;)Lorg/scalactic/source/Position;
    flags: (0x1019) ACC_PUBLIC, ACC_STATIC, ACC_FINAL, ACC_SYNTHETIC
    Code:
      stack=1, locals=1, args_size=1
         0: aload_0
         1: getfield      #72                 // Field pos:Lorg/scalactic/source/Position;
         4: areturn
      LineNumberTable:
        line 370: 0
      LocalVariableTable:
        Start  Length  Slot  Name   Signature
            0       5     0 $this   Lorg/scalatest/freespec/FixtureAnyFreeSpecLike$FreeSpecStringWrapper;
    MethodParameters:
      Name                           Flags
      $this                          final synthetic

  public static final org.scalactic.source.Position $anonfun$$minus$4(org.scalatest.freespec.FixtureAnyFreeSpecLike$FreeSpecStringWrapper);
    descriptor: (Lorg/scalatest/freespec/FixtureAnyFreeSpecLike$FreeSpecStringWrapper;)Lorg/scalactic/source/Position;
    flags: (0x1019) ACC_PUBLIC, ACC_STATIC, ACC_FINAL, ACC_SYNTHETIC
    Code:
      stack=1, locals=1, args_size=1
         0: aload_0
         1: getfield      #72                 // Field pos:Lorg/scalactic/source/Position;
         4: areturn
      LineNumberTable:
        line 372: 0
      LocalVariableTable:
        Start  Length  Slot  Name   Signature
            0       5     0 $this   Lorg/scalatest/freespec/FixtureAnyFreeSpecLike$FreeSpecStringWrapper;
    MethodParameters:
      Name                           Flags
      $this                          final synthetic

  public static final org.scalatest.PendingStatement $anonfun$is$2(scala.Function0, java.lang.Object);
    descriptor: (Lscala/Function0;Ljava/lang/Object;)Lorg/scalatest/PendingStatement;
    flags: (0x1019) ACC_PUBLIC, ACC_STATIC, ACC_FINAL, ACC_SYNTHETIC
    Code:
      stack=1, locals=2, args_size=2
         0: aload_0
         1: invokeinterface #282,  1          // InterfaceMethod scala/Function0.apply:()Ljava/lang/Object;
         6: checkcast     #284                // class org/scalatest/PendingStatement
         9: areturn
      LineNumberTable:
        line 441: 0
      LocalVariableTable:
        Start  Length  Slot  Name   Signature
            0      10     0 testFun$2   Lscala/Function0;
            0      10     1 unusedFixtureParam   Ljava/lang/Object;
    MethodParameters:
      Name                           Flags
      testFun$2                      final
      unusedFixtureParam             final

  public org.scalatest.freespec.FixtureAnyFreeSpecLike$FreeSpecStringWrapper(org.scalatest.freespec.FixtureAnyFreeSpecLike, java.lang.String, org.scalactic.source.Position);
    descriptor: (Lorg/scalatest/freespec/FixtureAnyFreeSpecLike;Ljava/lang/String;Lorg/scalactic/source/Position;)V
    flags: (0x0001) ACC_PUBLIC
    Code:
      stack=2, locals=4, args_size=4
         0: aload_0
         1: aload_2
         2: putfield      #36                 // Field string:Ljava/lang/String;
         5: aload_0
         6: aload_3
         7: putfield      #72                 // Field pos:Lorg/scalactic/source/Position;
        10: aload_1
        11: ifnonnull     16
        14: aconst_null
        15: athrow
        16: aload_0
        17: aload_1
        18: putfield      #30                 // Field $outer:Lorg/scalatest/freespec/FixtureAnyFreeSpecLike;
        21: aload_0
        22: invokespecial #289                // Method java/lang/Object."<init>":()V
        25: return
      StackMapTable: number_of_entries = 1
        frame_type = 16 /* same */
      LineNumberTable:
        line 350: 0
        line 513: 21
        line 350: 25
      LocalVariableTable:
        Start  Length  Slot  Name   Signature
            0      26     0  this   Lorg/scalatest/freespec/FixtureAnyFreeSpecLike$FreeSpecStringWrapper;
            0      26     1 $outer   Lorg/scalatest/freespec/FixtureAnyFreeSpecLike;
            0      26     2 string   Ljava/lang/String;
            0      26     3   pos   Lorg/scalactic/source/Position;
    MethodParameters:
      Name                           Flags
      $outer                         final synthetic
      string                         final
      pos                            final

  private static java.lang.Object $deserializeLambda$(java.lang.invoke.SerializedLambda);
    descriptor: (Ljava/lang/invoke/SerializedLambda;)Ljava/lang/Object;
    flags: (0x100a) ACC_PRIVATE, ACC_STATIC, ACC_SYNTHETIC
    Code:
      stack=1, locals=1, args_size=1
         0: aload_0
         1: invokedynamic #301,  0            // InvokeDynamic #5:lambdaDeserialize:(Ljava/lang/invoke/SerializedLambda;)Ljava/lang/Object;
         6: areturn
}
InnerClasses:
  public static final #10= #7 of #9;      // Lookup=class java/lang/invoke/MethodHandles$Lookup of class java/lang/invoke/MethodHandles
  public final #13= #2 of #12;            // FreeSpecStringWrapper=class org/scalatest/freespec/FixtureAnyFreeSpecLike$FreeSpecStringWrapper of class org/scalatest/freespec/FixtureAnyFreeSpecLike
  public final #16= #15 of #12;           // ResultOfTaggedAsInvocationOnString=class org/scalatest/freespec/FixtureAnyFreeSpecLike$ResultOfTaggedAsInvocationOnString of class org/scalatest/freespec/FixtureAnyFreeSpecLike
SourceFile: "FixtureAnyFreeSpecLike.scala"
BootstrapMethods:
  0: #59 REF_invokeStatic java/lang/invoke/LambdaMetafactory.altMetafactory:(Ljava/lang/invoke/MethodHandles$Lookup;Ljava/lang/String;Ljava/lang/invoke/MethodType;[Ljava/lang/Object;)Ljava/lang/invoke/CallSite;
    Method arguments:
      #44 ()Ljava/lang/Object;
      #49 REF_invokeStatic org/scalatest/freespec/FixtureAnyFreeSpecLike$FreeSpecStringWrapper.$anonfun$$minus$1:()Ljava/lang/String;
      #50 ()Ljava/lang/String;
      #51 5
      #52 1
      #50 ()Ljava/lang/String;
  1: #59 REF_invokeStatic java/lang/invoke/LambdaMetafactory.altMetafactory:(Ljava/lang/invoke/MethodHandles$Lookup;Ljava/lang/String;Ljava/lang/invoke/MethodType;[Ljava/lang/Object;)Ljava/lang/invoke/CallSite;
    Method arguments:
      #44 ()Ljava/lang/Object;
      #103 REF_invokeStatic org/scalatest/freespec/FixtureAnyFreeSpecLike$FreeSpecStringWrapper.$anonfun$$minus$2:(Lorg/scalatest/freespec/FixtureAnyFreeSpecLike$FreeSpecStringWrapper;)Lorg/scalactic/source/Position;
      #105 ()Lorg/scalactic/source/Position;
      #51 5
      #52 1
      #105 ()Lorg/scalactic/source/Position;
  2: #59 REF_invokeStatic java/lang/invoke/LambdaMetafactory.altMetafactory:(Ljava/lang/invoke/MethodHandles$Lookup;Ljava/lang/String;Ljava/lang/invoke/MethodType;[Ljava/lang/Object;)Ljava/lang/invoke/CallSite;
    Method arguments:
      #44 ()Ljava/lang/Object;
      #126 REF_invokeStatic org/scalatest/freespec/FixtureAnyFreeSpecLike$FreeSpecStringWrapper.$anonfun$$minus$3:(Lorg/scalatest/freespec/FixtureAnyFreeSpecLike$FreeSpecStringWrapper;)Lorg/scalactic/source/Position;
      #105 ()Lorg/scalactic/source/Position;
      #51 5
      #52 1
      #105 ()Lorg/scalactic/source/Position;
  3: #59 REF_invokeStatic java/lang/invoke/LambdaMetafactory.altMetafactory:(Ljava/lang/invoke/MethodHandles$Lookup;Ljava/lang/String;Ljava/lang/invoke/MethodType;[Ljava/lang/Object;)Ljava/lang/invoke/CallSite;
    Method arguments:
      #44 ()Ljava/lang/Object;
      #169 REF_invokeStatic org/scalatest/freespec/FixtureAnyFreeSpecLike$FreeSpecStringWrapper.$anonfun$$minus$4:(Lorg/scalatest/freespec/FixtureAnyFreeSpecLike$FreeSpecStringWrapper;)Lorg/scalactic/source/Position;
      #105 ()Lorg/scalactic/source/Position;
      #51 5
      #52 1
      #105 ()Lorg/scalactic/source/Position;
  4: #59 REF_invokeStatic java/lang/invoke/LambdaMetafactory.altMetafactory:(Ljava/lang/invoke/MethodHandles$Lookup;Ljava/lang/String;Ljava/lang/invoke/MethodType;[Ljava/lang/Object;)Ljava/lang/invoke/CallSite;
    Method arguments:
      #229 (Ljava/lang/Object;)Ljava/lang/Object;
      #234 REF_invokeStatic org/scalatest/freespec/FixtureAnyFreeSpecLike$FreeSpecStringWrapper.$anonfun$is$2:(Lscala/Function0;Ljava/lang/Object;)Lorg/scalatest/PendingStatement;
      #236 (Ljava/lang/Object;)Lorg/scalatest/PendingStatement;
      #51 5
      #52 1
      #236 (Ljava/lang/Object;)Lorg/scalatest/PendingStatement;
  5: #298 REF_invokeStatic scala/runtime/LambdaDeserialize.bootstrap:(Ljava/lang/invoke/MethodHandles$Lookup;Ljava/lang/String;Ljava/lang/invoke/MethodType;[Ljava/lang/invoke/MethodHandle;)Ljava/lang/invoke/CallSite;
    Method arguments:
      #49 REF_invokeStatic org/scalatest/freespec/FixtureAnyFreeSpecLike$FreeSpecStringWrapper.$anonfun$$minus$1:()Ljava/lang/String;
      #103 REF_invokeStatic org/scalatest/freespec/FixtureAnyFreeSpecLike$FreeSpecStringWrapper.$anonfun$$minus$2:(Lorg/scalatest/freespec/FixtureAnyFreeSpecLike$FreeSpecStringWrapper;)Lorg/scalactic/source/Position;
      #126 REF_invokeStatic org/scalatest/freespec/FixtureAnyFreeSpecLike$FreeSpecStringWrapper.$anonfun$$minus$3:(Lorg/scalatest/freespec/FixtureAnyFreeSpecLike$FreeSpecStringWrapper;)Lorg/scalactic/source/Position;
      #169 REF_invokeStatic org/scalatest/freespec/FixtureAnyFreeSpecLike$FreeSpecStringWrapper.$anonfun$$minus$4:(Lorg/scalatest/freespec/FixtureAnyFreeSpecLike$FreeSpecStringWrapper;)Lorg/scalactic/source/Position;
      #234 REF_invokeStatic org/scalatest/freespec/FixtureAnyFreeSpecLike$FreeSpecStringWrapper.$anonfun$is$2:(Lscala/Function0;Ljava/lang/Object;)Lorg/scalatest/PendingStatement;
  ScalaInlineInfo: length = 0x45 (unknown attribute)
   01 01 00 0D 00 2D 00 2E 01 00 63 00 64 01 00 7B
   00 64 01 00 A6 00 64 01 00 E6 00 E7 01 00 17 00
   18 01 00 49 01 1E 01 00 F3 00 18 01 00 F3 00 BE
   01 00 BD 00 18 01 00 BD 00 BE 01 00 E1 00 18 01
   00 F8 00 F9 01
  Scala: length = 0x0 (unknown attribute)

