Classfile /Users/mw/Projects/slang-braindump/.jar/jar11/assemble/slang-braindump/assemble/content/org/scalatest/freespec/FixtureAsyncFreeSpecLike$$anon$1.class
  Last modified May 29, 2022; size 8656 bytes
  SHA-256 checksum 60d43bf9c4504735e4cb5c9740a973af88a862d7786e39f59103b725df91245c
  Compiled from "FixtureAsyncFreeSpecLike.scala"
public final class org.scalatest.freespec.FixtureAsyncFreeSpecLike$$anon$1 implements org.scalatest.FixtureAsyncTestSuite$OneArgAsyncTest
  minor version: 0
  major version: 52
  flags: (0x0031) ACC_PUBLIC, ACC_FINAL, ACC_SUPER
  this_class: #2                          // org/scalatest/freespec/FixtureAsyncFreeSpecLike$$anon$1
  super_class: #4                         // java/lang/Object
  interfaces: 1, fields: 8, methods: 38, attributes: 5
Constant pool:
    #1 = Utf8               org/scalatest/freespec/FixtureAsyncFreeSpecLike$$anon$1
    #2 = Class              #1            // org/scalatest/freespec/FixtureAsyncFreeSpecLike$$anon$1
    #3 = Utf8               java/lang/Object
    #4 = Class              #3            // java/lang/Object
    #5 = Utf8               org/scalatest/FixtureAsyncTestSuite$OneArgAsyncTest
    #6 = Class              #5            // org/scalatest/FixtureAsyncTestSuite$OneArgAsyncTest
    #7 = Utf8               FixtureAsyncFreeSpecLike.scala
    #8 = Utf8               org/scalatest/freespec/FixtureAsyncFreeSpecLike
    #9 = Class              #8            // org/scalatest/freespec/FixtureAsyncFreeSpecLike
   #10 = Utf8               invokeWithAsyncFixture$1
   #11 = Utf8               (Lorg/scalatest/AsyncSuperEngine$TestLeaf;Lscala/Function1;Lorg/scalatest/Args;Ljava/lang/String;)Lorg/scalatest/AsyncOutcome;
   #12 = NameAndType        #10:#11       // invokeWithAsyncFixture$1:(Lorg/scalatest/AsyncSuperEngine$TestLeaf;Lscala/Function1;Lorg/scalatest/Args;Ljava/lang/String;)Lorg/scalatest/AsyncOutcome;
   #13 = Utf8               org/scalatest/AsyncSuperEngine$TestLeaf
   #14 = Class              #13           // org/scalatest/AsyncSuperEngine$TestLeaf
   #15 = Utf8               org/scalatest/AsyncSuperEngine
   #16 = Class              #15           // org/scalatest/AsyncSuperEngine
   #17 = Utf8               TestLeaf
   #18 = Utf8               org/scalatest/AsyncTestSuite$NoArgAsyncTest
   #19 = Class              #18           // org/scalatest/AsyncTestSuite$NoArgAsyncTest
   #20 = Utf8               org/scalatest/AsyncTestSuite
   #21 = Class              #20           // org/scalatest/AsyncTestSuite
   #22 = Utf8               NoArgAsyncTest
   #23 = Utf8               org/scalatest/FixtureAsyncTestSuite
   #24 = Class              #23           // org/scalatest/FixtureAsyncTestSuite
   #25 = Utf8               OneArgAsyncTest
   #26 = Utf8               name
   #27 = Utf8               Ljava/lang/String;
   #28 = Utf8               configMap
   #29 = Utf8               Lorg/scalatest/ConfigMap;
   #30 = Utf8               scopes
   #31 = Utf8               Lscala/collection/immutable/IndexedSeq;
   #32 = Utf8               Lscala/collection/immutable/IndexedSeq<Ljava/lang/String;>;
   #33 = Utf8               text
   #34 = Utf8               tags
   #35 = Utf8               Lscala/collection/immutable/Set;
   #36 = Utf8               Lscala/collection/immutable/Set<Ljava/lang/String;>;
   #37 = Utf8               pos
   #38 = Utf8               Lscala/Option;
   #39 = Utf8               Lscala/Option<Lorg/scalactic/source/Position;>;
   #40 = Utf8               $outer
   #41 = Utf8               Lorg/scalatest/freespec/FixtureAsyncFreeSpecLike;
   #42 = Utf8               theTest$1
   #43 = Utf8               Lorg/scalatest/AsyncSuperEngine$TestLeaf;
   #44 = Utf8               toNoArgAsyncTest
   #45 = Utf8               (Ljava/lang/Object;)Lorg/scalatest/AsyncTestSuite$NoArgAsyncTest;
   #46 = Utf8               fixture
   #47 = Utf8               toNoArgAsyncTest$
   #48 = Utf8               (Lorg/scalatest/FixtureAsyncTestSuite$OneArgAsyncTest;Ljava/lang/Object;)Lorg/scalatest/AsyncTestSuite$NoArgAsyncTest;
   #49 = NameAndType        #47:#48       // toNoArgAsyncTest$:(Lorg/scalatest/FixtureAsyncTestSuite$OneArgAsyncTest;Ljava/lang/Object;)Lorg/scalatest/AsyncTestSuite$NoArgAsyncTest;
   #50 = InterfaceMethodref #6.#49        // org/scalatest/FixtureAsyncTestSuite$OneArgAsyncTest.toNoArgAsyncTest$:(Lorg/scalatest/FixtureAsyncTestSuite$OneArgAsyncTest;Ljava/lang/Object;)Lorg/scalatest/AsyncTestSuite$NoArgAsyncTest;
   #51 = Utf8               this
   #52 = Utf8               Lorg/scalatest/freespec/FixtureAsyncFreeSpecLike$$anon$1;
   #53 = Utf8               Ljava/lang/Object;
   #54 = Utf8               apply$mcZD$sp
   #55 = Utf8               (D)Z
   #56 = Utf8               v1
   #57 = Utf8               scala/Function1
   #58 = Class              #57           // scala/Function1
   #59 = Utf8               apply$mcZD$sp$
   #60 = Utf8               (Lscala/Function1;D)Z
   #61 = NameAndType        #59:#60       // apply$mcZD$sp$:(Lscala/Function1;D)Z
   #62 = InterfaceMethodref #58.#61       // scala/Function1.apply$mcZD$sp$:(Lscala/Function1;D)Z
   #63 = Utf8               D
   #64 = Utf8               apply$mcDD$sp
   #65 = Utf8               (D)D
   #66 = Utf8               apply$mcDD$sp$
   #67 = Utf8               (Lscala/Function1;D)D
   #68 = NameAndType        #66:#67       // apply$mcDD$sp$:(Lscala/Function1;D)D
   #69 = InterfaceMethodref #58.#68       // scala/Function1.apply$mcDD$sp$:(Lscala/Function1;D)D
   #70 = Utf8               apply$mcFD$sp
   #71 = Utf8               (D)F
   #72 = Utf8               apply$mcFD$sp$
   #73 = Utf8               (Lscala/Function1;D)F
   #74 = NameAndType        #72:#73       // apply$mcFD$sp$:(Lscala/Function1;D)F
   #75 = InterfaceMethodref #58.#74       // scala/Function1.apply$mcFD$sp$:(Lscala/Function1;D)F
   #76 = Utf8               apply$mcID$sp
   #77 = Utf8               (D)I
   #78 = Utf8               apply$mcID$sp$
   #79 = Utf8               (Lscala/Function1;D)I
   #80 = NameAndType        #78:#79       // apply$mcID$sp$:(Lscala/Function1;D)I
   #81 = InterfaceMethodref #58.#80       // scala/Function1.apply$mcID$sp$:(Lscala/Function1;D)I
   #82 = Utf8               apply$mcJD$sp
   #83 = Utf8               (D)J
   #84 = Utf8               apply$mcJD$sp$
   #85 = Utf8               (Lscala/Function1;D)J
   #86 = NameAndType        #84:#85       // apply$mcJD$sp$:(Lscala/Function1;D)J
   #87 = InterfaceMethodref #58.#86       // scala/Function1.apply$mcJD$sp$:(Lscala/Function1;D)J
   #88 = Utf8               apply$mcVD$sp
   #89 = Utf8               (D)V
   #90 = Utf8               apply$mcVD$sp$
   #91 = Utf8               (Lscala/Function1;D)V
   #92 = NameAndType        #90:#91       // apply$mcVD$sp$:(Lscala/Function1;D)V
   #93 = InterfaceMethodref #58.#92       // scala/Function1.apply$mcVD$sp$:(Lscala/Function1;D)V
   #94 = Utf8               apply$mcZF$sp
   #95 = Utf8               (F)Z
   #96 = Utf8               apply$mcZF$sp$
   #97 = Utf8               (Lscala/Function1;F)Z
   #98 = NameAndType        #96:#97       // apply$mcZF$sp$:(Lscala/Function1;F)Z
   #99 = InterfaceMethodref #58.#98       // scala/Function1.apply$mcZF$sp$:(Lscala/Function1;F)Z
  #100 = Utf8               F
  #101 = Utf8               apply$mcDF$sp
  #102 = Utf8               (F)D
  #103 = Utf8               apply$mcDF$sp$
  #104 = Utf8               (Lscala/Function1;F)D
  #105 = NameAndType        #103:#104     // apply$mcDF$sp$:(Lscala/Function1;F)D
  #106 = InterfaceMethodref #58.#105      // scala/Function1.apply$mcDF$sp$:(Lscala/Function1;F)D
  #107 = Utf8               apply$mcFF$sp
  #108 = Utf8               (F)F
  #109 = Utf8               apply$mcFF$sp$
  #110 = Utf8               (Lscala/Function1;F)F
  #111 = NameAndType        #109:#110     // apply$mcFF$sp$:(Lscala/Function1;F)F
  #112 = InterfaceMethodref #58.#111      // scala/Function1.apply$mcFF$sp$:(Lscala/Function1;F)F
  #113 = Utf8               apply$mcIF$sp
  #114 = Utf8               (F)I
  #115 = Utf8               apply$mcIF$sp$
  #116 = Utf8               (Lscala/Function1;F)I
  #117 = NameAndType        #115:#116     // apply$mcIF$sp$:(Lscala/Function1;F)I
  #118 = InterfaceMethodref #58.#117      // scala/Function1.apply$mcIF$sp$:(Lscala/Function1;F)I
  #119 = Utf8               apply$mcJF$sp
  #120 = Utf8               (F)J
  #121 = Utf8               apply$mcJF$sp$
  #122 = Utf8               (Lscala/Function1;F)J
  #123 = NameAndType        #121:#122     // apply$mcJF$sp$:(Lscala/Function1;F)J
  #124 = InterfaceMethodref #58.#123      // scala/Function1.apply$mcJF$sp$:(Lscala/Function1;F)J
  #125 = Utf8               apply$mcVF$sp
  #126 = Utf8               (F)V
  #127 = Utf8               apply$mcVF$sp$
  #128 = Utf8               (Lscala/Function1;F)V
  #129 = NameAndType        #127:#128     // apply$mcVF$sp$:(Lscala/Function1;F)V
  #130 = InterfaceMethodref #58.#129      // scala/Function1.apply$mcVF$sp$:(Lscala/Function1;F)V
  #131 = Utf8               apply$mcZI$sp
  #132 = Utf8               (I)Z
  #133 = Utf8               apply$mcZI$sp$
  #134 = Utf8               (Lscala/Function1;I)Z
  #135 = NameAndType        #133:#134     // apply$mcZI$sp$:(Lscala/Function1;I)Z
  #136 = InterfaceMethodref #58.#135      // scala/Function1.apply$mcZI$sp$:(Lscala/Function1;I)Z
  #137 = Utf8               I
  #138 = Utf8               apply$mcDI$sp
  #139 = Utf8               (I)D
  #140 = Utf8               apply$mcDI$sp$
  #141 = Utf8               (Lscala/Function1;I)D
  #142 = NameAndType        #140:#141     // apply$mcDI$sp$:(Lscala/Function1;I)D
  #143 = InterfaceMethodref #58.#142      // scala/Function1.apply$mcDI$sp$:(Lscala/Function1;I)D
  #144 = Utf8               apply$mcFI$sp
  #145 = Utf8               (I)F
  #146 = Utf8               apply$mcFI$sp$
  #147 = Utf8               (Lscala/Function1;I)F
  #148 = NameAndType        #146:#147     // apply$mcFI$sp$:(Lscala/Function1;I)F
  #149 = InterfaceMethodref #58.#148      // scala/Function1.apply$mcFI$sp$:(Lscala/Function1;I)F
  #150 = Utf8               apply$mcII$sp
  #151 = Utf8               (I)I
  #152 = Utf8               apply$mcII$sp$
  #153 = Utf8               (Lscala/Function1;I)I
  #154 = NameAndType        #152:#153     // apply$mcII$sp$:(Lscala/Function1;I)I
  #155 = InterfaceMethodref #58.#154      // scala/Function1.apply$mcII$sp$:(Lscala/Function1;I)I
  #156 = Utf8               apply$mcJI$sp
  #157 = Utf8               (I)J
  #158 = Utf8               apply$mcJI$sp$
  #159 = Utf8               (Lscala/Function1;I)J
  #160 = NameAndType        #158:#159     // apply$mcJI$sp$:(Lscala/Function1;I)J
  #161 = InterfaceMethodref #58.#160      // scala/Function1.apply$mcJI$sp$:(Lscala/Function1;I)J
  #162 = Utf8               apply$mcVI$sp
  #163 = Utf8               (I)V
  #164 = Utf8               apply$mcVI$sp$
  #165 = Utf8               (Lscala/Function1;I)V
  #166 = NameAndType        #164:#165     // apply$mcVI$sp$:(Lscala/Function1;I)V
  #167 = InterfaceMethodref #58.#166      // scala/Function1.apply$mcVI$sp$:(Lscala/Function1;I)V
  #168 = Utf8               apply$mcZJ$sp
  #169 = Utf8               (J)Z
  #170 = Utf8               apply$mcZJ$sp$
  #171 = Utf8               (Lscala/Function1;J)Z
  #172 = NameAndType        #170:#171     // apply$mcZJ$sp$:(Lscala/Function1;J)Z
  #173 = InterfaceMethodref #58.#172      // scala/Function1.apply$mcZJ$sp$:(Lscala/Function1;J)Z
  #174 = Utf8               J
  #175 = Utf8               apply$mcDJ$sp
  #176 = Utf8               (J)D
  #177 = Utf8               apply$mcDJ$sp$
  #178 = Utf8               (Lscala/Function1;J)D
  #179 = NameAndType        #177:#178     // apply$mcDJ$sp$:(Lscala/Function1;J)D
  #180 = InterfaceMethodref #58.#179      // scala/Function1.apply$mcDJ$sp$:(Lscala/Function1;J)D
  #181 = Utf8               apply$mcFJ$sp
  #182 = Utf8               (J)F
  #183 = Utf8               apply$mcFJ$sp$
  #184 = Utf8               (Lscala/Function1;J)F
  #185 = NameAndType        #183:#184     // apply$mcFJ$sp$:(Lscala/Function1;J)F
  #186 = InterfaceMethodref #58.#185      // scala/Function1.apply$mcFJ$sp$:(Lscala/Function1;J)F
  #187 = Utf8               apply$mcIJ$sp
  #188 = Utf8               (J)I
  #189 = Utf8               apply$mcIJ$sp$
  #190 = Utf8               (Lscala/Function1;J)I
  #191 = NameAndType        #189:#190     // apply$mcIJ$sp$:(Lscala/Function1;J)I
  #192 = InterfaceMethodref #58.#191      // scala/Function1.apply$mcIJ$sp$:(Lscala/Function1;J)I
  #193 = Utf8               apply$mcJJ$sp
  #194 = Utf8               (J)J
  #195 = Utf8               apply$mcJJ$sp$
  #196 = Utf8               (Lscala/Function1;J)J
  #197 = NameAndType        #195:#196     // apply$mcJJ$sp$:(Lscala/Function1;J)J
  #198 = InterfaceMethodref #58.#197      // scala/Function1.apply$mcJJ$sp$:(Lscala/Function1;J)J
  #199 = Utf8               apply$mcVJ$sp
  #200 = Utf8               (J)V
  #201 = Utf8               apply$mcVJ$sp$
  #202 = Utf8               (Lscala/Function1;J)V
  #203 = NameAndType        #201:#202     // apply$mcVJ$sp$:(Lscala/Function1;J)V
  #204 = InterfaceMethodref #58.#203      // scala/Function1.apply$mcVJ$sp$:(Lscala/Function1;J)V
  #205 = Utf8               compose
  #206 = Utf8               (Lscala/Function1;)Lscala/Function1;
  #207 = Utf8               <A:Ljava/lang/Object;>(Lscala/Function1<TA;Ljava/lang/Object;>;)Lscala/Function1<TA;Lorg/scalatest/FutureOutcome;>;
  #208 = Utf8               g
  #209 = Utf8               compose$
  #210 = Utf8               (Lscala/Function1;Lscala/Function1;)Lscala/Function1;
  #211 = NameAndType        #209:#210     // compose$:(Lscala/Function1;Lscala/Function1;)Lscala/Function1;
  #212 = InterfaceMethodref #58.#211      // scala/Function1.compose$:(Lscala/Function1;Lscala/Function1;)Lscala/Function1;
  #213 = Utf8               Lscala/Function1;
  #214 = Utf8               andThen
  #215 = Utf8               <A:Ljava/lang/Object;>(Lscala/Function1<Lorg/scalatest/FutureOutcome;TA;>;)Lscala/Function1<Ljava/lang/Object;TA;>;
  #216 = Utf8               andThen$
  #217 = NameAndType        #216:#210     // andThen$:(Lscala/Function1;Lscala/Function1;)Lscala/Function1;
  #218 = InterfaceMethodref #58.#217      // scala/Function1.andThen$:(Lscala/Function1;Lscala/Function1;)Lscala/Function1;
  #219 = Utf8               toString
  #220 = Utf8               ()Ljava/lang/String;
  #221 = Utf8               toString$
  #222 = Utf8               (Lscala/Function1;)Ljava/lang/String;
  #223 = NameAndType        #221:#222     // toString$:(Lscala/Function1;)Ljava/lang/String;
  #224 = InterfaceMethodref #58.#223      // scala/Function1.toString$:(Lscala/Function1;)Ljava/lang/String;
  #225 = NameAndType        #26:#27       // name:Ljava/lang/String;
  #226 = Fieldref           #2.#225       // org/scalatest/freespec/FixtureAsyncFreeSpecLike$$anon$1.name:Ljava/lang/String;
  #227 = Utf8               apply
  #228 = Utf8               (Ljava/lang/Object;)Lorg/scalatest/FutureOutcome;
  #229 = NameAndType        #42:#43       // theTest$1:Lorg/scalatest/AsyncSuperEngine$TestLeaf;
  #230 = Fieldref           #2.#229       // org/scalatest/freespec/FixtureAsyncFreeSpecLike$$anon$1.theTest$1:Lorg/scalatest/AsyncSuperEngine$TestLeaf;
  #231 = Utf8               testFun
  #232 = Utf8               ()Ljava/lang/Object;
  #233 = NameAndType        #231:#232     // testFun:()Ljava/lang/Object;
  #234 = Methodref          #14.#233      // org/scalatest/AsyncSuperEngine$TestLeaf.testFun:()Ljava/lang/Object;
  #235 = Utf8               (Ljava/lang/Object;)Ljava/lang/Object;
  #236 = NameAndType        #227:#235     // apply:(Ljava/lang/Object;)Ljava/lang/Object;
  #237 = InterfaceMethodref #58.#236      // scala/Function1.apply:(Ljava/lang/Object;)Ljava/lang/Object;
  #238 = Utf8               org/scalatest/AsyncTestHolder
  #239 = Class              #238          // org/scalatest/AsyncTestHolder
  #240 = Utf8               toFutureOutcome
  #241 = Utf8               ()Lorg/scalatest/FutureOutcome;
  #242 = NameAndType        #240:#241     // toFutureOutcome:()Lorg/scalatest/FutureOutcome;
  #243 = InterfaceMethodref #239.#242     // org/scalatest/AsyncTestHolder.toFutureOutcome:()Lorg/scalatest/FutureOutcome;
  #244 = Utf8               ()Lorg/scalatest/ConfigMap;
  #245 = NameAndType        #28:#29       // configMap:Lorg/scalatest/ConfigMap;
  #246 = Fieldref           #2.#245       // org/scalatest/freespec/FixtureAsyncFreeSpecLike$$anon$1.configMap:Lorg/scalatest/ConfigMap;
  #247 = Utf8               ()Lscala/collection/immutable/IndexedSeq;
  #248 = Utf8               ()Lscala/collection/immutable/IndexedSeq<Ljava/lang/String;>;
  #249 = NameAndType        #30:#31       // scopes:Lscala/collection/immutable/IndexedSeq;
  #250 = Fieldref           #2.#249       // org/scalatest/freespec/FixtureAsyncFreeSpecLike$$anon$1.scopes:Lscala/collection/immutable/IndexedSeq;
  #251 = NameAndType        #33:#27       // text:Ljava/lang/String;
  #252 = Fieldref           #2.#251       // org/scalatest/freespec/FixtureAsyncFreeSpecLike$$anon$1.text:Ljava/lang/String;
  #253 = Utf8               ()Lscala/collection/immutable/Set;
  #254 = Utf8               ()Lscala/collection/immutable/Set<Ljava/lang/String;>;
  #255 = NameAndType        #34:#35       // tags:Lscala/collection/immutable/Set;
  #256 = Fieldref           #2.#255       // org/scalatest/freespec/FixtureAsyncFreeSpecLike$$anon$1.tags:Lscala/collection/immutable/Set;
  #257 = Utf8               ()Lscala/Option;
  #258 = Utf8               ()Lscala/Option<Lorg/scalactic/source/Position;>;
  #259 = NameAndType        #37:#38       // pos:Lscala/Option;
  #260 = Fieldref           #2.#259       // org/scalatest/freespec/FixtureAsyncFreeSpecLike$$anon$1.pos:Lscala/Option;
  #261 = Utf8               org$scalatest$FixtureAsyncTestSuite$OneArgAsyncTest$$$outer
  #262 = Utf8               ()Lorg/scalatest/FixtureAsyncTestSuite;
  #263 = NameAndType        #40:#41       // $outer:Lorg/scalatest/freespec/FixtureAsyncFreeSpecLike;
  #264 = Fieldref           #2.#263       // org/scalatest/freespec/FixtureAsyncFreeSpecLike$$anon$1.$outer:Lorg/scalatest/freespec/FixtureAsyncFreeSpecLike;
  #265 = NameAndType        #227:#228     // apply:(Ljava/lang/Object;)Lorg/scalatest/FutureOutcome;
  #266 = Methodref          #2.#265       // org/scalatest/freespec/FixtureAsyncFreeSpecLike$$anon$1.apply:(Ljava/lang/Object;)Lorg/scalatest/FutureOutcome;
  #267 = Utf8               <init>
  #268 = Utf8               (Lorg/scalatest/freespec/FixtureAsyncFreeSpecLike;Lorg/scalatest/TestData;Lorg/scalatest/AsyncSuperEngine$TestLeaf;)V
  #269 = Utf8               testData$1
  #270 = Utf8               ()V
  #271 = NameAndType        #267:#270     // "<init>":()V
  #272 = Methodref          #4.#271       // java/lang/Object."<init>":()V
  #273 = Utf8               $init$
  #274 = Utf8               (Lscala/Function1;)V
  #275 = NameAndType        #273:#274     // $init$:(Lscala/Function1;)V
  #276 = InterfaceMethodref #58.#275      // scala/Function1.$init$:(Lscala/Function1;)V
  #277 = Utf8               (Lorg/scalatest/FixtureAsyncTestSuite$OneArgAsyncTest;)V
  #278 = NameAndType        #273:#277     // $init$:(Lorg/scalatest/FixtureAsyncTestSuite$OneArgAsyncTest;)V
  #279 = InterfaceMethodref #6.#278       // org/scalatest/FixtureAsyncTestSuite$OneArgAsyncTest.$init$:(Lorg/scalatest/FixtureAsyncTestSuite$OneArgAsyncTest;)V
  #280 = Utf8               org/scalatest/TestData
  #281 = Class              #280          // org/scalatest/TestData
  #282 = NameAndType        #26:#220      // name:()Ljava/lang/String;
  #283 = InterfaceMethodref #281.#282     // org/scalatest/TestData.name:()Ljava/lang/String;
  #284 = NameAndType        #28:#244      // configMap:()Lorg/scalatest/ConfigMap;
  #285 = InterfaceMethodref #281.#284     // org/scalatest/TestData.configMap:()Lorg/scalatest/ConfigMap;
  #286 = NameAndType        #30:#247      // scopes:()Lscala/collection/immutable/IndexedSeq;
  #287 = InterfaceMethodref #281.#286     // org/scalatest/TestData.scopes:()Lscala/collection/immutable/IndexedSeq;
  #288 = NameAndType        #33:#220      // text:()Ljava/lang/String;
  #289 = InterfaceMethodref #281.#288     // org/scalatest/TestData.text:()Ljava/lang/String;
  #290 = NameAndType        #34:#253      // tags:()Lscala/collection/immutable/Set;
  #291 = InterfaceMethodref #281.#290     // org/scalatest/TestData.tags:()Lscala/collection/immutable/Set;
  #292 = NameAndType        #37:#257      // pos:()Lscala/Option;
  #293 = InterfaceMethodref #281.#292     // org/scalatest/TestData.pos:()Lscala/Option;
  #294 = Utf8               Lorg/scalatest/TestData;
  #295 = Utf8               Signature
  #296 = Utf8               Code
  #297 = Utf8               LineNumberTable
  #298 = Utf8               LocalVariableTable
  #299 = Utf8               MethodParameters
  #300 = Utf8               StackMapTable
  #301 = Utf8               InnerClasses
  #302 = Utf8               EnclosingMethod
  #303 = Utf8               SourceFile
  #304 = Utf8               ScalaInlineInfo
  #305 = Utf8               Scala
{
  private final java.lang.String name;
    descriptor: Ljava/lang/String;
    flags: (0x0012) ACC_PRIVATE, ACC_FINAL

  private final org.scalatest.ConfigMap configMap;
    descriptor: Lorg/scalatest/ConfigMap;
    flags: (0x0012) ACC_PRIVATE, ACC_FINAL

  private final scala.collection.immutable.IndexedSeq<java.lang.String> scopes;
    descriptor: Lscala/collection/immutable/IndexedSeq;
    flags: (0x0012) ACC_PRIVATE, ACC_FINAL
    Signature: #32                          // Lscala/collection/immutable/IndexedSeq<Ljava/lang/String;>;

  private final java.lang.String text;
    descriptor: Ljava/lang/String;
    flags: (0x0012) ACC_PRIVATE, ACC_FINAL

  private final scala.collection.immutable.Set<java.lang.String> tags;
    descriptor: Lscala/collection/immutable/Set;
    flags: (0x0012) ACC_PRIVATE, ACC_FINAL
    Signature: #36                          // Lscala/collection/immutable/Set<Ljava/lang/String;>;

  private final scala.Option<org.scalactic.source.Position> pos;
    descriptor: Lscala/Option;
    flags: (0x0012) ACC_PRIVATE, ACC_FINAL
    Signature: #39                          // Lscala/Option<Lorg/scalactic/source/Position;>;

  private final org.scalatest.freespec.FixtureAsyncFreeSpecLike $outer;
    descriptor: Lorg/scalatest/freespec/FixtureAsyncFreeSpecLike;
    flags: (0x1012) ACC_PRIVATE, ACC_FINAL, ACC_SYNTHETIC

  private final org.scalatest.AsyncSuperEngine$TestLeaf theTest$1;
    descriptor: Lorg/scalatest/AsyncSuperEngine$TestLeaf;
    flags: (0x0012) ACC_PRIVATE, ACC_FINAL
    Signature: #43                          // Lorg/scalatest/AsyncSuperEngine$TestLeaf;

  public org.scalatest.AsyncTestSuite$NoArgAsyncTest toNoArgAsyncTest(java.lang.Object);
    descriptor: (Ljava/lang/Object;)Lorg/scalatest/AsyncTestSuite$NoArgAsyncTest;
    flags: (0x0001) ACC_PUBLIC
    Code:
      stack=2, locals=2, args_size=2
         0: aload_0
         1: aload_1
         2: invokestatic  #50                 // InterfaceMethod org/scalatest/FixtureAsyncTestSuite$OneArgAsyncTest.toNoArgAsyncTest$:(Lorg/scalatest/FixtureAsyncTestSuite$OneArgAsyncTest;Ljava/lang/Object;)Lorg/scalatest/AsyncTestSuite$NoArgAsyncTest;
         5: areturn
      LineNumberTable:
        line 533: 0
      LocalVariableTable:
        Start  Length  Slot  Name   Signature
            0       6     0  this   Lorg/scalatest/freespec/FixtureAsyncFreeSpecLike$$anon$1;
            0       6     1 fixture   Ljava/lang/Object;
    MethodParameters:
      Name                           Flags
      fixture                        final

  public boolean apply$mcZD$sp(double);
    descriptor: (D)Z
    flags: (0x0001) ACC_PUBLIC
    Code:
      stack=3, locals=3, args_size=2
         0: aload_0
         1: dload_1
         2: invokestatic  #62                 // InterfaceMethod scala/Function1.apply$mcZD$sp$:(Lscala/Function1;D)Z
         5: ireturn
      LineNumberTable:
        line 533: 0
      LocalVariableTable:
        Start  Length  Slot  Name   Signature
            0       6     0  this   Lorg/scalatest/freespec/FixtureAsyncFreeSpecLike$$anon$1;
            0       6     1    v1   D
    MethodParameters:
      Name                           Flags
      v1                             final

  public double apply$mcDD$sp(double);
    descriptor: (D)D
    flags: (0x0001) ACC_PUBLIC
    Code:
      stack=3, locals=3, args_size=2
         0: aload_0
         1: dload_1
         2: invokestatic  #69                 // InterfaceMethod scala/Function1.apply$mcDD$sp$:(Lscala/Function1;D)D
         5: dreturn
      LineNumberTable:
        line 533: 0
      LocalVariableTable:
        Start  Length  Slot  Name   Signature
            0       6     0  this   Lorg/scalatest/freespec/FixtureAsyncFreeSpecLike$$anon$1;
            0       6     1    v1   D
    MethodParameters:
      Name                           Flags
      v1                             final

  public float apply$mcFD$sp(double);
    descriptor: (D)F
    flags: (0x0001) ACC_PUBLIC
    Code:
      stack=3, locals=3, args_size=2
         0: aload_0
         1: dload_1
         2: invokestatic  #75                 // InterfaceMethod scala/Function1.apply$mcFD$sp$:(Lscala/Function1;D)F
         5: freturn
      LineNumberTable:
        line 533: 0
      LocalVariableTable:
        Start  Length  Slot  Name   Signature
            0       6     0  this   Lorg/scalatest/freespec/FixtureAsyncFreeSpecLike$$anon$1;
            0       6     1    v1   D
    MethodParameters:
      Name                           Flags
      v1                             final

  public int apply$mcID$sp(double);
    descriptor: (D)I
    flags: (0x0001) ACC_PUBLIC
    Code:
      stack=3, locals=3, args_size=2
         0: aload_0
         1: dload_1
         2: invokestatic  #81                 // InterfaceMethod scala/Function1.apply$mcID$sp$:(Lscala/Function1;D)I
         5: ireturn
      LineNumberTable:
        line 533: 0
      LocalVariableTable:
        Start  Length  Slot  Name   Signature
            0       6     0  this   Lorg/scalatest/freespec/FixtureAsyncFreeSpecLike$$anon$1;
            0       6     1    v1   D
    MethodParameters:
      Name                           Flags
      v1                             final

  public long apply$mcJD$sp(double);
    descriptor: (D)J
    flags: (0x0001) ACC_PUBLIC
    Code:
      stack=3, locals=3, args_size=2
         0: aload_0
         1: dload_1
         2: invokestatic  #87                 // InterfaceMethod scala/Function1.apply$mcJD$sp$:(Lscala/Function1;D)J
         5: lreturn
      LineNumberTable:
        line 533: 0
      LocalVariableTable:
        Start  Length  Slot  Name   Signature
            0       6     0  this   Lorg/scalatest/freespec/FixtureAsyncFreeSpecLike$$anon$1;
            0       6     1    v1   D
    MethodParameters:
      Name                           Flags
      v1                             final

  public void apply$mcVD$sp(double);
    descriptor: (D)V
    flags: (0x0001) ACC_PUBLIC
    Code:
      stack=3, locals=3, args_size=2
         0: aload_0
         1: dload_1
         2: invokestatic  #93                 // InterfaceMethod scala/Function1.apply$mcVD$sp$:(Lscala/Function1;D)V
         5: return
      LineNumberTable:
        line 533: 0
      LocalVariableTable:
        Start  Length  Slot  Name   Signature
            0       6     0  this   Lorg/scalatest/freespec/FixtureAsyncFreeSpecLike$$anon$1;
            0       6     1    v1   D
    MethodParameters:
      Name                           Flags
      v1                             final

  public boolean apply$mcZF$sp(float);
    descriptor: (F)Z
    flags: (0x0001) ACC_PUBLIC
    Code:
      stack=2, locals=2, args_size=2
         0: aload_0
         1: fload_1
         2: invokestatic  #99                 // InterfaceMethod scala/Function1.apply$mcZF$sp$:(Lscala/Function1;F)Z
         5: ireturn
      LineNumberTable:
        line 533: 0
      LocalVariableTable:
        Start  Length  Slot  Name   Signature
            0       6     0  this   Lorg/scalatest/freespec/FixtureAsyncFreeSpecLike$$anon$1;
            0       6     1    v1   F
    MethodParameters:
      Name                           Flags
      v1                             final

  public double apply$mcDF$sp(float);
    descriptor: (F)D
    flags: (0x0001) ACC_PUBLIC
    Code:
      stack=2, locals=2, args_size=2
         0: aload_0
         1: fload_1
         2: invokestatic  #106                // InterfaceMethod scala/Function1.apply$mcDF$sp$:(Lscala/Function1;F)D
         5: dreturn
      LineNumberTable:
        line 533: 0
      LocalVariableTable:
        Start  Length  Slot  Name   Signature
            0       6     0  this   Lorg/scalatest/freespec/FixtureAsyncFreeSpecLike$$anon$1;
            0       6     1    v1   F
    MethodParameters:
      Name                           Flags
      v1                             final

  public float apply$mcFF$sp(float);
    descriptor: (F)F
    flags: (0x0001) ACC_PUBLIC
    Code:
      stack=2, locals=2, args_size=2
         0: aload_0
         1: fload_1
         2: invokestatic  #112                // InterfaceMethod scala/Function1.apply$mcFF$sp$:(Lscala/Function1;F)F
         5: freturn
      LineNumberTable:
        line 533: 0
      LocalVariableTable:
        Start  Length  Slot  Name   Signature
            0       6     0  this   Lorg/scalatest/freespec/FixtureAsyncFreeSpecLike$$anon$1;
            0       6     1    v1   F
    MethodParameters:
      Name                           Flags
      v1                             final

  public int apply$mcIF$sp(float);
    descriptor: (F)I
    flags: (0x0001) ACC_PUBLIC
    Code:
      stack=2, locals=2, args_size=2
         0: aload_0
         1: fload_1
         2: invokestatic  #118                // InterfaceMethod scala/Function1.apply$mcIF$sp$:(Lscala/Function1;F)I
         5: ireturn
      LineNumberTable:
        line 533: 0
      LocalVariableTable:
        Start  Length  Slot  Name   Signature
            0       6     0  this   Lorg/scalatest/freespec/FixtureAsyncFreeSpecLike$$anon$1;
            0       6     1    v1   F
    MethodParameters:
      Name                           Flags
      v1                             final

  public long apply$mcJF$sp(float);
    descriptor: (F)J
    flags: (0x0001) ACC_PUBLIC
    Code:
      stack=2, locals=2, args_size=2
         0: aload_0
         1: fload_1
         2: invokestatic  #124                // InterfaceMethod scala/Function1.apply$mcJF$sp$:(Lscala/Function1;F)J
         5: lreturn
      LineNumberTable:
        line 533: 0
      LocalVariableTable:
        Start  Length  Slot  Name   Signature
            0       6     0  this   Lorg/scalatest/freespec/FixtureAsyncFreeSpecLike$$anon$1;
            0       6     1    v1   F
    MethodParameters:
      Name                           Flags
      v1                             final

  public void apply$mcVF$sp(float);
    descriptor: (F)V
    flags: (0x0001) ACC_PUBLIC
    Code:
      stack=2, locals=2, args_size=2
         0: aload_0
         1: fload_1
         2: invokestatic  #130                // InterfaceMethod scala/Function1.apply$mcVF$sp$:(Lscala/Function1;F)V
         5: return
      LineNumberTable:
        line 533: 0
      LocalVariableTable:
        Start  Length  Slot  Name   Signature
            0       6     0  this   Lorg/scalatest/freespec/FixtureAsyncFreeSpecLike$$anon$1;
            0       6     1    v1   F
    MethodParameters:
      Name                           Flags
      v1                             final

  public boolean apply$mcZI$sp(int);
    descriptor: (I)Z
    flags: (0x0001) ACC_PUBLIC
    Code:
      stack=2, locals=2, args_size=2
         0: aload_0
         1: iload_1
         2: invokestatic  #136                // InterfaceMethod scala/Function1.apply$mcZI$sp$:(Lscala/Function1;I)Z
         5: ireturn
      LineNumberTable:
        line 533: 0
      LocalVariableTable:
        Start  Length  Slot  Name   Signature
            0       6     0  this   Lorg/scalatest/freespec/FixtureAsyncFreeSpecLike$$anon$1;
            0       6     1    v1   I
    MethodParameters:
      Name                           Flags
      v1                             final

  public double apply$mcDI$sp(int);
    descriptor: (I)D
    flags: (0x0001) ACC_PUBLIC
    Code:
      stack=2, locals=2, args_size=2
         0: aload_0
         1: iload_1
         2: invokestatic  #143                // InterfaceMethod scala/Function1.apply$mcDI$sp$:(Lscala/Function1;I)D
         5: dreturn
      LineNumberTable:
        line 533: 0
      LocalVariableTable:
        Start  Length  Slot  Name   Signature
            0       6     0  this   Lorg/scalatest/freespec/FixtureAsyncFreeSpecLike$$anon$1;
            0       6     1    v1   I
    MethodParameters:
      Name                           Flags
      v1                             final

  public float apply$mcFI$sp(int);
    descriptor: (I)F
    flags: (0x0001) ACC_PUBLIC
    Code:
      stack=2, locals=2, args_size=2
         0: aload_0
         1: iload_1
         2: invokestatic  #149                // InterfaceMethod scala/Function1.apply$mcFI$sp$:(Lscala/Function1;I)F
         5: freturn
      LineNumberTable:
        line 533: 0
      LocalVariableTable:
        Start  Length  Slot  Name   Signature
            0       6     0  this   Lorg/scalatest/freespec/FixtureAsyncFreeSpecLike$$anon$1;
            0       6     1    v1   I
    MethodParameters:
      Name                           Flags
      v1                             final

  public int apply$mcII$sp(int);
    descriptor: (I)I
    flags: (0x0001) ACC_PUBLIC
    Code:
      stack=2, locals=2, args_size=2
         0: aload_0
         1: iload_1
         2: invokestatic  #155                // InterfaceMethod scala/Function1.apply$mcII$sp$:(Lscala/Function1;I)I
         5: ireturn
      LineNumberTable:
        line 533: 0
      LocalVariableTable:
        Start  Length  Slot  Name   Signature
            0       6     0  this   Lorg/scalatest/freespec/FixtureAsyncFreeSpecLike$$anon$1;
            0       6     1    v1   I
    MethodParameters:
      Name                           Flags
      v1                             final

  public long apply$mcJI$sp(int);
    descriptor: (I)J
    flags: (0x0001) ACC_PUBLIC
    Code:
      stack=2, locals=2, args_size=2
         0: aload_0
         1: iload_1
         2: invokestatic  #161                // InterfaceMethod scala/Function1.apply$mcJI$sp$:(Lscala/Function1;I)J
         5: lreturn
      LineNumberTable:
        line 533: 0
      LocalVariableTable:
        Start  Length  Slot  Name   Signature
            0       6     0  this   Lorg/scalatest/freespec/FixtureAsyncFreeSpecLike$$anon$1;
            0       6     1    v1   I
    MethodParameters:
      Name                           Flags
      v1                             final

  public void apply$mcVI$sp(int);
    descriptor: (I)V
    flags: (0x0001) ACC_PUBLIC
    Code:
      stack=2, locals=2, args_size=2
         0: aload_0
         1: iload_1
         2: invokestatic  #167                // InterfaceMethod scala/Function1.apply$mcVI$sp$:(Lscala/Function1;I)V
         5: return
      LineNumberTable:
        line 533: 0
      LocalVariableTable:
        Start  Length  Slot  Name   Signature
            0       6     0  this   Lorg/scalatest/freespec/FixtureAsyncFreeSpecLike$$anon$1;
            0       6     1    v1   I
    MethodParameters:
      Name                           Flags
      v1                             final

  public boolean apply$mcZJ$sp(long);
    descriptor: (J)Z
    flags: (0x0001) ACC_PUBLIC
    Code:
      stack=3, locals=3, args_size=2
         0: aload_0
         1: lload_1
         2: invokestatic  #173                // InterfaceMethod scala/Function1.apply$mcZJ$sp$:(Lscala/Function1;J)Z
         5: ireturn
      LineNumberTable:
        line 533: 0
      LocalVariableTable:
        Start  Length  Slot  Name   Signature
            0       6     0  this   Lorg/scalatest/freespec/FixtureAsyncFreeSpecLike$$anon$1;
            0       6     1    v1   J
    MethodParameters:
      Name                           Flags
      v1                             final

  public double apply$mcDJ$sp(long);
    descriptor: (J)D
    flags: (0x0001) ACC_PUBLIC
    Code:
      stack=3, locals=3, args_size=2
         0: aload_0
         1: lload_1
         2: invokestatic  #180                // InterfaceMethod scala/Function1.apply$mcDJ$sp$:(Lscala/Function1;J)D
         5: dreturn
      LineNumberTable:
        line 533: 0
      LocalVariableTable:
        Start  Length  Slot  Name   Signature
            0       6     0  this   Lorg/scalatest/freespec/FixtureAsyncFreeSpecLike$$anon$1;
            0       6     1    v1   J
    MethodParameters:
      Name                           Flags
      v1                             final

  public float apply$mcFJ$sp(long);
    descriptor: (J)F
    flags: (0x0001) ACC_PUBLIC
    Code:
      stack=3, locals=3, args_size=2
         0: aload_0
         1: lload_1
         2: invokestatic  #186                // InterfaceMethod scala/Function1.apply$mcFJ$sp$:(Lscala/Function1;J)F
         5: freturn
      LineNumberTable:
        line 533: 0
      LocalVariableTable:
        Start  Length  Slot  Name   Signature
            0       6     0  this   Lorg/scalatest/freespec/FixtureAsyncFreeSpecLike$$anon$1;
            0       6     1    v1   J
    MethodParameters:
      Name                           Flags
      v1                             final

  public int apply$mcIJ$sp(long);
    descriptor: (J)I
    flags: (0x0001) ACC_PUBLIC
    Code:
      stack=3, locals=3, args_size=2
         0: aload_0
         1: lload_1
         2: invokestatic  #192                // InterfaceMethod scala/Function1.apply$mcIJ$sp$:(Lscala/Function1;J)I
         5: ireturn
      LineNumberTable:
        line 533: 0
      LocalVariableTable:
        Start  Length  Slot  Name   Signature
            0       6     0  this   Lorg/scalatest/freespec/FixtureAsyncFreeSpecLike$$anon$1;
            0       6     1    v1   J
    MethodParameters:
      Name                           Flags
      v1                             final

  public long apply$mcJJ$sp(long);
    descriptor: (J)J
    flags: (0x0001) ACC_PUBLIC
    Code:
      stack=3, locals=3, args_size=2
         0: aload_0
         1: lload_1
         2: invokestatic  #198                // InterfaceMethod scala/Function1.apply$mcJJ$sp$:(Lscala/Function1;J)J
         5: lreturn
      LineNumberTable:
        line 533: 0
      LocalVariableTable:
        Start  Length  Slot  Name   Signature
            0       6     0  this   Lorg/scalatest/freespec/FixtureAsyncFreeSpecLike$$anon$1;
            0       6     1    v1   J
    MethodParameters:
      Name                           Flags
      v1                             final

  public void apply$mcVJ$sp(long);
    descriptor: (J)V
    flags: (0x0001) ACC_PUBLIC
    Code:
      stack=3, locals=3, args_size=2
         0: aload_0
         1: lload_1
         2: invokestatic  #204                // InterfaceMethod scala/Function1.apply$mcVJ$sp$:(Lscala/Function1;J)V
         5: return
      LineNumberTable:
        line 533: 0
      LocalVariableTable:
        Start  Length  Slot  Name   Signature
            0       6     0  this   Lorg/scalatest/freespec/FixtureAsyncFreeSpecLike$$anon$1;
            0       6     1    v1   J
    MethodParameters:
      Name                           Flags
      v1                             final

  public <A extends java.lang.Object> scala.Function1<A, org.scalatest.FutureOutcome> compose(scala.Function1<A, java.lang.Object>);
    descriptor: (Lscala/Function1;)Lscala/Function1;
    flags: (0x0001) ACC_PUBLIC
    Code:
      stack=2, locals=2, args_size=2
         0: aload_0
         1: aload_1
         2: invokestatic  #212                // InterfaceMethod scala/Function1.compose$:(Lscala/Function1;Lscala/Function1;)Lscala/Function1;
         5: areturn
      LineNumberTable:
        line 533: 0
      LocalVariableTable:
        Start  Length  Slot  Name   Signature
            0       6     0  this   Lorg/scalatest/freespec/FixtureAsyncFreeSpecLike$$anon$1;
            0       6     1     g   Lscala/Function1;
    Signature: #207                         // <A:Ljava/lang/Object;>(Lscala/Function1<TA;Ljava/lang/Object;>;)Lscala/Function1<TA;Lorg/scalatest/FutureOutcome;>;
    MethodParameters:
      Name                           Flags
      g                              final

  public <A extends java.lang.Object> scala.Function1<java.lang.Object, A> andThen(scala.Function1<org.scalatest.FutureOutcome, A>);
    descriptor: (Lscala/Function1;)Lscala/Function1;
    flags: (0x0001) ACC_PUBLIC
    Code:
      stack=2, locals=2, args_size=2
         0: aload_0
         1: aload_1
         2: invokestatic  #218                // InterfaceMethod scala/Function1.andThen$:(Lscala/Function1;Lscala/Function1;)Lscala/Function1;
         5: areturn
      LineNumberTable:
        line 533: 0
      LocalVariableTable:
        Start  Length  Slot  Name   Signature
            0       6     0  this   Lorg/scalatest/freespec/FixtureAsyncFreeSpecLike$$anon$1;
            0       6     1     g   Lscala/Function1;
    Signature: #215                         // <A:Ljava/lang/Object;>(Lscala/Function1<Lorg/scalatest/FutureOutcome;TA;>;)Lscala/Function1<Ljava/lang/Object;TA;>;
    MethodParameters:
      Name                           Flags
      g                              final

  public java.lang.String toString();
    descriptor: ()Ljava/lang/String;
    flags: (0x0001) ACC_PUBLIC
    Code:
      stack=1, locals=1, args_size=1
         0: aload_0
         1: invokestatic  #224                // InterfaceMethod scala/Function1.toString$:(Lscala/Function1;)Ljava/lang/String;
         4: areturn
      LineNumberTable:
        line 533: 0
      LocalVariableTable:
        Start  Length  Slot  Name   Signature
            0       5     0  this   Lorg/scalatest/freespec/FixtureAsyncFreeSpecLike$$anon$1;

  public java.lang.String name();
    descriptor: ()Ljava/lang/String;
    flags: (0x0001) ACC_PUBLIC
    Code:
      stack=1, locals=1, args_size=1
         0: aload_0
         1: getfield      #226                // Field name:Ljava/lang/String;
         4: areturn
      LineNumberTable:
        line 534: 0
      LocalVariableTable:
        Start  Length  Slot  Name   Signature
            0       5     0  this   Lorg/scalatest/freespec/FixtureAsyncFreeSpecLike$$anon$1;

  public org.scalatest.FutureOutcome apply(java.lang.Object);
    descriptor: (Ljava/lang/Object;)Lorg/scalatest/FutureOutcome;
    flags: (0x0001) ACC_PUBLIC
    Code:
      stack=2, locals=2, args_size=2
         0: aload_0
         1: getfield      #230                // Field theTest$1:Lorg/scalatest/AsyncSuperEngine$TestLeaf;
         4: invokevirtual #234                // Method org/scalatest/AsyncSuperEngine$TestLeaf.testFun:()Ljava/lang/Object;
         7: checkcast     #58                 // class scala/Function1
        10: aload_1
        11: invokeinterface #237,  2          // InterfaceMethod scala/Function1.apply:(Ljava/lang/Object;)Ljava/lang/Object;
        16: checkcast     #239                // class org/scalatest/AsyncTestHolder
        19: invokeinterface #243,  1          // InterfaceMethod org/scalatest/AsyncTestHolder.toFutureOutcome:()Lorg/scalatest/FutureOutcome;
        24: areturn
      LineNumberTable:
        line 537: 0
      LocalVariableTable:
        Start  Length  Slot  Name   Signature
            0      25     0  this   Lorg/scalatest/freespec/FixtureAsyncFreeSpecLike$$anon$1;
            0      25     1 fixture   Ljava/lang/Object;
    MethodParameters:
      Name                           Flags
      fixture                        final

  public org.scalatest.ConfigMap configMap();
    descriptor: ()Lorg/scalatest/ConfigMap;
    flags: (0x0001) ACC_PUBLIC
    Code:
      stack=1, locals=1, args_size=1
         0: aload_0
         1: getfield      #246                // Field configMap:Lorg/scalatest/ConfigMap;
         4: areturn
      LineNumberTable:
        line 539: 0
      LocalVariableTable:
        Start  Length  Slot  Name   Signature
            0       5     0  this   Lorg/scalatest/freespec/FixtureAsyncFreeSpecLike$$anon$1;

  public scala.collection.immutable.IndexedSeq<java.lang.String> scopes();
    descriptor: ()Lscala/collection/immutable/IndexedSeq;
    flags: (0x0001) ACC_PUBLIC
    Code:
      stack=1, locals=1, args_size=1
         0: aload_0
         1: getfield      #250                // Field scopes:Lscala/collection/immutable/IndexedSeq;
         4: areturn
      LineNumberTable:
        line 540: 0
      LocalVariableTable:
        Start  Length  Slot  Name   Signature
            0       5     0  this   Lorg/scalatest/freespec/FixtureAsyncFreeSpecLike$$anon$1;
    Signature: #248                         // ()Lscala/collection/immutable/IndexedSeq<Ljava/lang/String;>;

  public java.lang.String text();
    descriptor: ()Ljava/lang/String;
    flags: (0x0001) ACC_PUBLIC
    Code:
      stack=1, locals=1, args_size=1
         0: aload_0
         1: getfield      #252                // Field text:Ljava/lang/String;
         4: areturn
      LineNumberTable:
        line 541: 0
      LocalVariableTable:
        Start  Length  Slot  Name   Signature
            0       5     0  this   Lorg/scalatest/freespec/FixtureAsyncFreeSpecLike$$anon$1;

  public scala.collection.immutable.Set<java.lang.String> tags();
    descriptor: ()Lscala/collection/immutable/Set;
    flags: (0x0001) ACC_PUBLIC
    Code:
      stack=1, locals=1, args_size=1
         0: aload_0
         1: getfield      #256                // Field tags:Lscala/collection/immutable/Set;
         4: areturn
      LineNumberTable:
        line 542: 0
      LocalVariableTable:
        Start  Length  Slot  Name   Signature
            0       5     0  this   Lorg/scalatest/freespec/FixtureAsyncFreeSpecLike$$anon$1;
    Signature: #254                         // ()Lscala/collection/immutable/Set<Ljava/lang/String;>;

  public scala.Option<org.scalactic.source.Position> pos();
    descriptor: ()Lscala/Option;
    flags: (0x0001) ACC_PUBLIC
    Code:
      stack=1, locals=1, args_size=1
         0: aload_0
         1: getfield      #260                // Field pos:Lscala/Option;
         4: areturn
      LineNumberTable:
        line 543: 0
      LocalVariableTable:
        Start  Length  Slot  Name   Signature
            0       5     0  this   Lorg/scalatest/freespec/FixtureAsyncFreeSpecLike$$anon$1;
    Signature: #258                         // ()Lscala/Option<Lorg/scalactic/source/Position;>;

  public org.scalatest.FixtureAsyncTestSuite org$scalatest$FixtureAsyncTestSuite$OneArgAsyncTest$$$outer();
    descriptor: ()Lorg/scalatest/FixtureAsyncTestSuite;
    flags: (0x1001) ACC_PUBLIC, ACC_SYNTHETIC
    Code:
      stack=1, locals=1, args_size=1
         0: aload_0
         1: getfield      #264                // Field $outer:Lorg/scalatest/freespec/FixtureAsyncFreeSpecLike;
         4: areturn
      LineNumberTable:
        line 533: 0
      LocalVariableTable:
        Start  Length  Slot  Name   Signature
            0       5     0  this   Lorg/scalatest/freespec/FixtureAsyncFreeSpecLike$$anon$1;

  public java.lang.Object apply(java.lang.Object);
    descriptor: (Ljava/lang/Object;)Ljava/lang/Object;
    flags: (0x1041) ACC_PUBLIC, ACC_BRIDGE, ACC_SYNTHETIC
    Code:
      stack=2, locals=2, args_size=2
         0: aload_0
         1: aload_1
         2: invokevirtual #266                // Method apply:(Ljava/lang/Object;)Lorg/scalatest/FutureOutcome;
         5: areturn
      LineNumberTable:
        line 533: 0
      LocalVariableTable:
        Start  Length  Slot  Name   Signature
            0       6     0  this   Lorg/scalatest/freespec/FixtureAsyncFreeSpecLike$$anon$1;
            0       6     1    v1   Ljava/lang/Object;
    MethodParameters:
      Name                           Flags
      v1                             final

  public org.scalatest.freespec.FixtureAsyncFreeSpecLike$$anon$1(org.scalatest.freespec.FixtureAsyncFreeSpecLike, org.scalatest.TestData, org.scalatest.AsyncSuperEngine$TestLeaf);
    descriptor: (Lorg/scalatest/freespec/FixtureAsyncFreeSpecLike;Lorg/scalatest/TestData;Lorg/scalatest/AsyncSuperEngine$TestLeaf;)V
    flags: (0x0001) ACC_PUBLIC
    Code:
      stack=2, locals=4, args_size=4
         0: aload_1
         1: ifnonnull     6
         4: aconst_null
         5: athrow
         6: aload_0
         7: aload_1
         8: putfield      #264                // Field $outer:Lorg/scalatest/freespec/FixtureAsyncFreeSpecLike;
        11: aload_0
        12: aload_3
        13: putfield      #230                // Field theTest$1:Lorg/scalatest/AsyncSuperEngine$TestLeaf;
        16: aload_0
        17: invokespecial #272                // Method java/lang/Object."<init>":()V
        20: aload_0
        21: invokestatic  #276                // InterfaceMethod scala/Function1.$init$:(Lscala/Function1;)V
        24: aload_0
        25: invokestatic  #279                // InterfaceMethod org/scalatest/FixtureAsyncTestSuite$OneArgAsyncTest.$init$:(Lorg/scalatest/FixtureAsyncTestSuite$OneArgAsyncTest;)V
        28: aload_0
        29: aload_2
        30: invokeinterface #283,  1          // InterfaceMethod org/scalatest/TestData.name:()Ljava/lang/String;
        35: putfield      #226                // Field name:Ljava/lang/String;
        38: aload_0
        39: aload_2
        40: invokeinterface #285,  1          // InterfaceMethod org/scalatest/TestData.configMap:()Lorg/scalatest/ConfigMap;
        45: putfield      #246                // Field configMap:Lorg/scalatest/ConfigMap;
        48: aload_0
        49: aload_2
        50: invokeinterface #287,  1          // InterfaceMethod org/scalatest/TestData.scopes:()Lscala/collection/immutable/IndexedSeq;
        55: putfield      #250                // Field scopes:Lscala/collection/immutable/IndexedSeq;
        58: aload_0
        59: aload_2
        60: invokeinterface #289,  1          // InterfaceMethod org/scalatest/TestData.text:()Ljava/lang/String;
        65: putfield      #252                // Field text:Ljava/lang/String;
        68: aload_0
        69: aload_2
        70: invokeinterface #291,  1          // InterfaceMethod org/scalatest/TestData.tags:()Lscala/collection/immutable/Set;
        75: putfield      #256                // Field tags:Lscala/collection/immutable/Set;
        78: aload_0
        79: aload_2
        80: invokeinterface #293,  1          // InterfaceMethod org/scalatest/TestData.pos:()Lscala/Option;
        85: putfield      #260                // Field pos:Lscala/Option;
        88: return
      StackMapTable: number_of_entries = 1
        frame_type = 6 /* same */
      LineNumberTable:
        line 533: 0
        line 528: 11
        line 533: 16
        line 534: 28
        line 539: 38
        line 540: 48
        line 541: 58
        line 542: 68
        line 543: 78
        line 533: 88
      LocalVariableTable:
        Start  Length  Slot  Name   Signature
            0      89     0  this   Lorg/scalatest/freespec/FixtureAsyncFreeSpecLike$$anon$1;
            0      89     1 $outer   Lorg/scalatest/freespec/FixtureAsyncFreeSpecLike;
            0      89     2 testData$1   Lorg/scalatest/TestData;
            0      89     3 theTest$1   Lorg/scalatest/AsyncSuperEngine$TestLeaf;
    MethodParameters:
      Name                           Flags
      $outer                         final synthetic
      testData$1                     final
      theTest$1                      final
}
InnerClasses:
  public #17= #14 of #16;                 // TestLeaf=class org/scalatest/AsyncSuperEngine$TestLeaf of class org/scalatest/AsyncSuperEngine
  public #22= #19 of #21;                 // NoArgAsyncTest=class org/scalatest/AsyncTestSuite$NoArgAsyncTest of class org/scalatest/AsyncTestSuite
  public #25= #6 of #24;                  // OneArgAsyncTest=class org/scalatest/FixtureAsyncTestSuite$OneArgAsyncTest of class org/scalatest/FixtureAsyncTestSuite
  public final #2;                        // class org/scalatest/freespec/FixtureAsyncFreeSpecLike$$anon$1
EnclosingMethod: #9.#12                 // org.scalatest.freespec.FixtureAsyncFreeSpecLike.invokeWithAsyncFixture$1
SourceFile: "FixtureAsyncFreeSpecLike.scala"
  ScalaInlineInfo: length = 0xC2 (unknown attribute)
   01 01 00 26 01 0B 01 0C 01 00 D6 00 CE 01 00 E3
   00 EB 01 00 E3 00 E4 01 00 40 00 41 01 00 65 00
   66 01 00 8A 00 8B 01 00 AF 00 B0 01 00 46 00 47
   01 00 6B 00 6C 01 00 90 00 91 01 00 B5 00 B6 01
   00 4C 00 4D 01 00 71 00 72 01 00 96 00 97 01 00
   BB 00 BC 01 00 52 00 53 01 00 77 00 78 01 00 9C
   00 9D 01 00 C1 00 C2 01 00 58 00 59 01 00 7D 00
   7E 01 00 A2 00 A3 01 00 C7 00 C8 01 00 36 00 37
   01 00 5E 00 5F 01 00 83 00 84 01 00 A8 00 A9 01
   00 CD 00 CE 01 00 1C 00 F4 01 00 1A 00 DC 01 01
   05 01 06 01 00 25 01 01 01 00 1E 00 F7 01 00 22
   00 FD 01 00 21 00 DC 01 00 2C 00 2D 01 00 DB 00
   DC 01
  Scala: length = 0x0 (unknown attribute)

