Classfile /Users/mw/Projects/slang-braindump/.jar/jar8/assemble/slang-braindump/assemble/content/org/apache/commons/lang3/text/StrTokenizer.class
  Last modified May 29, 2022; size 13523 bytes
  SHA-256 checksum c22b385b1c232c49bbed6e649967c1c4cc6a32a31ae3ba0e63eb70b861edae26
  Compiled from "StrTokenizer.java"
public class org.apache.commons.lang3.text.StrTokenizer extends java.lang.Object implements java.util.ListIterator<java.lang.String>, java.lang.Cloneable
  minor version: 0
  major version: 52
  flags: (0x0021) ACC_PUBLIC, ACC_SUPER
  this_class: #3                          // org/apache/commons/lang3/text/StrTokenizer
  super_class: #109                       // java/lang/Object
  interfaces: 2, fields: 11, methods: 69, attributes: 4
Constant pool:
    #1 = Fieldref           #3.#263       // org/apache/commons/lang3/text/StrTokenizer.CSV_TOKENIZER_PROTOTYPE:Lorg/apache/commons/lang3/text/StrTokenizer;
    #2 = Methodref          #3.#264       // org/apache/commons/lang3/text/StrTokenizer.clone:()Ljava/lang/Object;
    #3 = Class              #265          // org/apache/commons/lang3/text/StrTokenizer
    #4 = Methodref          #3.#266       // org/apache/commons/lang3/text/StrTokenizer.getCSVClone:()Lorg/apache/commons/lang3/text/StrTokenizer;
    #5 = Methodref          #3.#267       // org/apache/commons/lang3/text/StrTokenizer.reset:(Ljava/lang/String;)Lorg/apache/commons/lang3/text/StrTokenizer;
    #6 = Methodref          #3.#268       // org/apache/commons/lang3/text/StrTokenizer.reset:([C)Lorg/apache/commons/lang3/text/StrTokenizer;
    #7 = Fieldref           #3.#269       // org/apache/commons/lang3/text/StrTokenizer.TSV_TOKENIZER_PROTOTYPE:Lorg/apache/commons/lang3/text/StrTokenizer;
    #8 = Methodref          #3.#270       // org/apache/commons/lang3/text/StrTokenizer.getTSVClone:()Lorg/apache/commons/lang3/text/StrTokenizer;
    #9 = Methodref          #109.#271     // java/lang/Object."<init>":()V
   #10 = Methodref          #272.#273     // org/apache/commons/lang3/text/StrMatcher.splitMatcher:()Lorg/apache/commons/lang3/text/StrMatcher;
   #11 = Fieldref           #3.#274       // org/apache/commons/lang3/text/StrTokenizer.delimMatcher:Lorg/apache/commons/lang3/text/StrMatcher;
   #12 = Methodref          #272.#275     // org/apache/commons/lang3/text/StrMatcher.noneMatcher:()Lorg/apache/commons/lang3/text/StrMatcher;
   #13 = Fieldref           #3.#276       // org/apache/commons/lang3/text/StrTokenizer.quoteMatcher:Lorg/apache/commons/lang3/text/StrMatcher;
   #14 = Fieldref           #3.#277       // org/apache/commons/lang3/text/StrTokenizer.ignoredMatcher:Lorg/apache/commons/lang3/text/StrMatcher;
   #15 = Fieldref           #3.#278       // org/apache/commons/lang3/text/StrTokenizer.trimmerMatcher:Lorg/apache/commons/lang3/text/StrMatcher;
   #16 = Fieldref           #3.#279       // org/apache/commons/lang3/text/StrTokenizer.emptyAsNull:Z
   #17 = Fieldref           #3.#280       // org/apache/commons/lang3/text/StrTokenizer.ignoreEmptyTokens:Z
   #18 = Fieldref           #3.#281       // org/apache/commons/lang3/text/StrTokenizer.chars:[C
   #19 = Methodref          #53.#282      // java/lang/String.toCharArray:()[C
   #20 = Methodref          #3.#283       // org/apache/commons/lang3/text/StrTokenizer."<init>":(Ljava/lang/String;)V
   #21 = Methodref          #3.#284       // org/apache/commons/lang3/text/StrTokenizer.setDelimiterChar:(C)Lorg/apache/commons/lang3/text/StrTokenizer;
   #22 = Methodref          #3.#285       // org/apache/commons/lang3/text/StrTokenizer.setDelimiterString:(Ljava/lang/String;)Lorg/apache/commons/lang3/text/StrTokenizer;
   #23 = Methodref          #3.#286       // org/apache/commons/lang3/text/StrTokenizer.setDelimiterMatcher:(Lorg/apache/commons/lang3/text/StrMatcher;)Lorg/apache/commons/lang3/text/StrTokenizer;
   #24 = Methodref          #3.#287       // org/apache/commons/lang3/text/StrTokenizer."<init>":(Ljava/lang/String;C)V
   #25 = Methodref          #3.#288       // org/apache/commons/lang3/text/StrTokenizer.setQuoteChar:(C)Lorg/apache/commons/lang3/text/StrTokenizer;
   #26 = Methodref          #3.#289       // org/apache/commons/lang3/text/StrTokenizer."<init>":(Ljava/lang/String;Lorg/apache/commons/lang3/text/StrMatcher;)V
   #27 = Methodref          #3.#290       // org/apache/commons/lang3/text/StrTokenizer.setQuoteMatcher:(Lorg/apache/commons/lang3/text/StrMatcher;)Lorg/apache/commons/lang3/text/StrTokenizer;
   #28 = Methodref          #291.#292     // org/apache/commons/lang3/ArrayUtils.clone:([C)[C
   #29 = Methodref          #3.#293       // org/apache/commons/lang3/text/StrTokenizer."<init>":([C)V
   #30 = Methodref          #3.#294       // org/apache/commons/lang3/text/StrTokenizer."<init>":([CC)V
   #31 = Methodref          #3.#295       // org/apache/commons/lang3/text/StrTokenizer."<init>":([CLorg/apache/commons/lang3/text/StrMatcher;)V
   #32 = Methodref          #3.#296       // org/apache/commons/lang3/text/StrTokenizer.checkTokenized:()V
   #33 = Fieldref           #3.#297       // org/apache/commons/lang3/text/StrTokenizer.tokens:[Ljava/lang/String;
   #34 = Methodref          #3.#298       // org/apache/commons/lang3/text/StrTokenizer.hasNext:()Z
   #35 = Fieldref           #3.#299       // org/apache/commons/lang3/text/StrTokenizer.tokenPos:I
   #36 = Methodref          #3.#300       // org/apache/commons/lang3/text/StrTokenizer.hasPrevious:()Z
   #37 = Methodref          #301.#264     // "[Ljava/lang/String;".clone:()Ljava/lang/Object;
   #38 = Class              #118          // "[Ljava/lang/String;"
   #39 = Class              #302          // java/util/ArrayList
   #40 = Methodref          #39.#303      // java/util/ArrayList."<init>":(I)V
   #41 = Methodref          #304.#305     // java/util/Arrays.asList:([Ljava/lang/Object;)Ljava/util/List;
   #42 = InterfaceMethodref #199.#306     // java/util/List.addAll:(Ljava/util/Collection;)Z
   #43 = Methodref          #3.#307       // org/apache/commons/lang3/text/StrTokenizer.reset:()Lorg/apache/commons/lang3/text/StrTokenizer;
   #44 = Class              #308          // java/util/NoSuchElementException
   #45 = Methodref          #44.#271      // java/util/NoSuchElementException."<init>":()V
   #46 = Class              #309          // java/lang/UnsupportedOperationException
   #47 = String             #310          // remove() is unsupported
   #48 = Methodref          #46.#283      // java/lang/UnsupportedOperationException."<init>":(Ljava/lang/String;)V
   #49 = String             #311          // set() is unsupported
   #50 = String             #312          // add() is unsupported
   #51 = Methodref          #3.#313       // org/apache/commons/lang3/text/StrTokenizer.tokenize:([CII)Ljava/util/List;
   #52 = InterfaceMethodref #199.#314     // java/util/List.size:()I
   #53 = Class              #315          // java/lang/String
   #54 = InterfaceMethodref #199.#316     // java/util/List.toArray:([Ljava/lang/Object;)[Ljava/lang/Object;
   #55 = Methodref          #317.#318     // java/util/Collections.emptyList:()Ljava/util/List;
   #56 = Class              #319          // org/apache/commons/lang3/text/StrBuilder
   #57 = Methodref          #56.#271      // org/apache/commons/lang3/text/StrBuilder."<init>":()V
   #58 = Methodref          #39.#271      // java/util/ArrayList."<init>":()V
   #59 = Methodref          #3.#320       // org/apache/commons/lang3/text/StrTokenizer.readNextToken:([CIILorg/apache/commons/lang3/text/StrBuilder;Ljava/util/List;)I
   #60 = Class              #321          // org/apache/commons/lang3/StringUtils
   #61 = String             #322          //
   #62 = Methodref          #3.#323       // org/apache/commons/lang3/text/StrTokenizer.addToken:(Ljava/util/List;Ljava/lang/String;)V
   #63 = Methodref          #60.#324      // org/apache/commons/lang3/StringUtils.isEmpty:(Ljava/lang/CharSequence;)Z
   #64 = Methodref          #3.#325       // org/apache/commons/lang3/text/StrTokenizer.isIgnoreEmptyTokens:()Z
   #65 = Methodref          #3.#326       // org/apache/commons/lang3/text/StrTokenizer.isEmptyTokenAsNull:()Z
   #66 = InterfaceMethodref #199.#327     // java/util/List.add:(Ljava/lang/Object;)Z
   #67 = Methodref          #3.#328       // org/apache/commons/lang3/text/StrTokenizer.getIgnoredMatcher:()Lorg/apache/commons/lang3/text/StrMatcher;
   #68 = Methodref          #272.#329     // org/apache/commons/lang3/text/StrMatcher.isMatch:([CIII)I
   #69 = Methodref          #3.#330       // org/apache/commons/lang3/text/StrTokenizer.getTrimmerMatcher:()Lorg/apache/commons/lang3/text/StrMatcher;
   #70 = Methodref          #331.#332     // java/lang/Math.max:(II)I
   #71 = Methodref          #3.#333       // org/apache/commons/lang3/text/StrTokenizer.getDelimiterMatcher:()Lorg/apache/commons/lang3/text/StrMatcher;
   #72 = Methodref          #3.#334       // org/apache/commons/lang3/text/StrTokenizer.getQuoteMatcher:()Lorg/apache/commons/lang3/text/StrMatcher;
   #73 = Methodref          #3.#335       // org/apache/commons/lang3/text/StrTokenizer.readWithQuotes:([CIILorg/apache/commons/lang3/text/StrBuilder;Ljava/util/List;II)I
   #74 = Methodref          #56.#336      // org/apache/commons/lang3/text/StrBuilder.clear:()Lorg/apache/commons/lang3/text/StrBuilder;
   #75 = Methodref          #3.#337       // org/apache/commons/lang3/text/StrTokenizer.isQuote:([CIIII)Z
   #76 = Methodref          #56.#338      // org/apache/commons/lang3/text/StrBuilder.append:([CII)Lorg/apache/commons/lang3/text/StrBuilder;
   #77 = Methodref          #56.#314      // org/apache/commons/lang3/text/StrBuilder.size:()I
   #78 = Methodref          #56.#339      // org/apache/commons/lang3/text/StrBuilder.append:(C)Lorg/apache/commons/lang3/text/StrBuilder;
   #79 = Methodref          #56.#340      // org/apache/commons/lang3/text/StrBuilder.substring:(II)Ljava/lang/String;
   #80 = Methodref          #272.#341     // org/apache/commons/lang3/text/StrMatcher.charMatcher:(C)Lorg/apache/commons/lang3/text/StrMatcher;
   #81 = Methodref          #272.#342     // org/apache/commons/lang3/text/StrMatcher.stringMatcher:(Ljava/lang/String;)Lorg/apache/commons/lang3/text/StrMatcher;
   #82 = Methodref          #3.#343       // org/apache/commons/lang3/text/StrTokenizer.setIgnoredMatcher:(Lorg/apache/commons/lang3/text/StrMatcher;)Lorg/apache/commons/lang3/text/StrTokenizer;
   #83 = Methodref          #53.#293      // java/lang/String."<init>":([C)V
   #84 = Methodref          #3.#344       // org/apache/commons/lang3/text/StrTokenizer.cloneReset:()Ljava/lang/Object;
   #85 = Class              #345          // java/lang/CloneNotSupportedException
   #86 = Methodref          #109.#264     // java/lang/Object.clone:()Ljava/lang/Object;
   #87 = Methodref          #346.#264     // "[C".clone:()Ljava/lang/Object;
   #88 = Class              #116          // "[C"
   #89 = String             #347          // StrTokenizer[not tokenized yet]
   #90 = Class              #348          // java/lang/StringBuilder
   #91 = Methodref          #90.#271      // java/lang/StringBuilder."<init>":()V
   #92 = String             #349          // StrTokenizer
   #93 = Methodref          #90.#350      // java/lang/StringBuilder.append:(Ljava/lang/String;)Ljava/lang/StringBuilder;
   #94 = Methodref          #3.#351       // org/apache/commons/lang3/text/StrTokenizer.getTokenList:()Ljava/util/List;
   #95 = Methodref          #90.#352      // java/lang/StringBuilder.append:(Ljava/lang/Object;)Ljava/lang/StringBuilder;
   #96 = Methodref          #90.#353      // java/lang/StringBuilder.toString:()Ljava/lang/String;
   #97 = Methodref          #3.#354       // org/apache/commons/lang3/text/StrTokenizer.add:(Ljava/lang/String;)V
   #98 = Methodref          #3.#355       // org/apache/commons/lang3/text/StrTokenizer.set:(Ljava/lang/String;)V
   #99 = Methodref          #3.#356       // org/apache/commons/lang3/text/StrTokenizer.previous:()Ljava/lang/String;
  #100 = Methodref          #3.#357       // org/apache/commons/lang3/text/StrTokenizer.next:()Ljava/lang/String;
  #101 = Methodref          #3.#271       // org/apache/commons/lang3/text/StrTokenizer."<init>":()V
  #102 = Methodref          #272.#358     // org/apache/commons/lang3/text/StrMatcher.commaMatcher:()Lorg/apache/commons/lang3/text/StrMatcher;
  #103 = Methodref          #272.#359     // org/apache/commons/lang3/text/StrMatcher.doubleQuoteMatcher:()Lorg/apache/commons/lang3/text/StrMatcher;
  #104 = Methodref          #272.#360     // org/apache/commons/lang3/text/StrMatcher.trimMatcher:()Lorg/apache/commons/lang3/text/StrMatcher;
  #105 = Methodref          #3.#361       // org/apache/commons/lang3/text/StrTokenizer.setTrimmerMatcher:(Lorg/apache/commons/lang3/text/StrMatcher;)Lorg/apache/commons/lang3/text/StrTokenizer;
  #106 = Methodref          #3.#362       // org/apache/commons/lang3/text/StrTokenizer.setEmptyTokenAsNull:(Z)Lorg/apache/commons/lang3/text/StrTokenizer;
  #107 = Methodref          #3.#363       // org/apache/commons/lang3/text/StrTokenizer.setIgnoreEmptyTokens:(Z)Lorg/apache/commons/lang3/text/StrTokenizer;
  #108 = Methodref          #272.#364     // org/apache/commons/lang3/text/StrMatcher.tabMatcher:()Lorg/apache/commons/lang3/text/StrMatcher;
  #109 = Class              #365          // java/lang/Object
  #110 = Class              #366          // java/util/ListIterator
  #111 = Class              #367          // java/lang/Cloneable
  #112 = Utf8               CSV_TOKENIZER_PROTOTYPE
  #113 = Utf8               Lorg/apache/commons/lang3/text/StrTokenizer;
  #114 = Utf8               TSV_TOKENIZER_PROTOTYPE
  #115 = Utf8               chars
  #116 = Utf8               [C
  #117 = Utf8               tokens
  #118 = Utf8               [Ljava/lang/String;
  #119 = Utf8               tokenPos
  #120 = Utf8               I
  #121 = Utf8               delimMatcher
  #122 = Utf8               Lorg/apache/commons/lang3/text/StrMatcher;
  #123 = Utf8               quoteMatcher
  #124 = Utf8               ignoredMatcher
  #125 = Utf8               trimmerMatcher
  #126 = Utf8               emptyAsNull
  #127 = Utf8               Z
  #128 = Utf8               ignoreEmptyTokens
  #129 = Utf8               getCSVClone
  #130 = Utf8               ()Lorg/apache/commons/lang3/text/StrTokenizer;
  #131 = Utf8               Code
  #132 = Utf8               LineNumberTable
  #133 = Utf8               getCSVInstance
  #134 = Utf8               (Ljava/lang/String;)Lorg/apache/commons/lang3/text/StrTokenizer;
  #135 = Utf8               LocalVariableTable
  #136 = Utf8               input
  #137 = Utf8               Ljava/lang/String;
  #138 = Utf8               tok
  #139 = Utf8               ([C)Lorg/apache/commons/lang3/text/StrTokenizer;
  #140 = Utf8               getTSVClone
  #141 = Utf8               getTSVInstance
  #142 = Utf8               <init>
  #143 = Utf8               ()V
  #144 = Utf8               this
  #145 = Utf8               (Ljava/lang/String;)V
  #146 = Utf8               StackMapTable
  #147 = Utf8               (Ljava/lang/String;C)V
  #148 = Utf8               delim
  #149 = Utf8               C
  #150 = Utf8               (Ljava/lang/String;Ljava/lang/String;)V
  #151 = Utf8               (Ljava/lang/String;Lorg/apache/commons/lang3/text/StrMatcher;)V
  #152 = Utf8               (Ljava/lang/String;CC)V
  #153 = Utf8               quote
  #154 = Utf8               (Ljava/lang/String;Lorg/apache/commons/lang3/text/StrMatcher;Lorg/apache/commons/lang3/text/StrMatcher;)V
  #155 = Utf8               ([C)V
  #156 = Utf8               ([CC)V
  #157 = Utf8               ([CLjava/lang/String;)V
  #158 = Utf8               ([CLorg/apache/commons/lang3/text/StrMatcher;)V
  #159 = Utf8               ([CCC)V
  #160 = Utf8               ([CLorg/apache/commons/lang3/text/StrMatcher;Lorg/apache/commons/lang3/text/StrMatcher;)V
  #161 = Utf8               size
  #162 = Utf8               ()I
  #163 = Utf8               nextToken
  #164 = Utf8               ()Ljava/lang/String;
  #165 = Utf8               previousToken
  #166 = Utf8               getTokenArray
  #167 = Utf8               ()[Ljava/lang/String;
  #168 = Utf8               getTokenList
  #169 = Utf8               ()Ljava/util/List;
  #170 = Utf8               list
  #171 = Utf8               Ljava/util/List;
  #172 = Utf8               LocalVariableTypeTable
  #173 = Utf8               Ljava/util/List<Ljava/lang/String;>;
  #174 = Utf8               Signature
  #175 = Utf8               ()Ljava/util/List<Ljava/lang/String;>;
  #176 = Utf8               reset
  #177 = Utf8               hasNext
  #178 = Utf8               ()Z
  #179 = Utf8               next
  #180 = Utf8               nextIndex
  #181 = Utf8               hasPrevious
  #182 = Utf8               previous
  #183 = Utf8               previousIndex
  #184 = Utf8               remove
  #185 = Utf8               set
  #186 = Utf8               obj
  #187 = Utf8               add
  #188 = Utf8               checkTokenized
  #189 = Utf8               split
  #190 = Utf8               tokenize
  #191 = Utf8               ([CII)Ljava/util/List;
  #192 = Utf8               srcChars
  #193 = Utf8               offset
  #194 = Utf8               count
  #195 = Utf8               buf
  #196 = Utf8               Lorg/apache/commons/lang3/text/StrBuilder;
  #197 = Utf8               tokenList
  #198 = Utf8               pos
  #199 = Class              #368          // java/util/List
  #200 = Utf8               ([CII)Ljava/util/List<Ljava/lang/String;>;
  #201 = Utf8               addToken
  #202 = Utf8               (Ljava/util/List;Ljava/lang/String;)V
  #203 = Utf8               (Ljava/util/List<Ljava/lang/String;>;Ljava/lang/String;)V
  #204 = Utf8               readNextToken
  #205 = Utf8               ([CIILorg/apache/commons/lang3/text/StrBuilder;Ljava/util/List;)I
  #206 = Utf8               removeLen
  #207 = Utf8               start
  #208 = Utf8               len
  #209 = Utf8               workArea
  #210 = Utf8               delimLen
  #211 = Utf8               quoteLen
  #212 = Utf8               ([CIILorg/apache/commons/lang3/text/StrBuilder;Ljava/util/List<Ljava/lang/String;>;)I
  #213 = Utf8               readWithQuotes
  #214 = Utf8               ([CIILorg/apache/commons/lang3/text/StrBuilder;Ljava/util/List;II)I
  #215 = Utf8               ignoredLen
  #216 = Utf8               trimmedLen
  #217 = Utf8               quoteStart
  #218 = Utf8               quoting
  #219 = Utf8               trimStart
  #220 = Utf8               ([CIILorg/apache/commons/lang3/text/StrBuilder;Ljava/util/List<Ljava/lang/String;>;II)I
  #221 = Utf8               isQuote
  #222 = Utf8               ([CIIII)Z
  #223 = Utf8               i
  #224 = Utf8               getDelimiterMatcher
  #225 = Utf8               ()Lorg/apache/commons/lang3/text/StrMatcher;
  #226 = Utf8               setDelimiterMatcher
  #227 = Utf8               (Lorg/apache/commons/lang3/text/StrMatcher;)Lorg/apache/commons/lang3/text/StrTokenizer;
  #228 = Utf8               setDelimiterChar
  #229 = Utf8               (C)Lorg/apache/commons/lang3/text/StrTokenizer;
  #230 = Utf8               setDelimiterString
  #231 = Utf8               getQuoteMatcher
  #232 = Utf8               setQuoteMatcher
  #233 = Utf8               setQuoteChar
  #234 = Utf8               getIgnoredMatcher
  #235 = Utf8               setIgnoredMatcher
  #236 = Utf8               ignored
  #237 = Utf8               setIgnoredChar
  #238 = Utf8               getTrimmerMatcher
  #239 = Utf8               setTrimmerMatcher
  #240 = Utf8               trimmer
  #241 = Utf8               isEmptyTokenAsNull
  #242 = Utf8               setEmptyTokenAsNull
  #243 = Utf8               (Z)Lorg/apache/commons/lang3/text/StrTokenizer;
  #244 = Utf8               isIgnoreEmptyTokens
  #245 = Utf8               setIgnoreEmptyTokens
  #246 = Utf8               getContent
  #247 = Utf8               clone
  #248 = Utf8               ()Ljava/lang/Object;
  #249 = Utf8               ex
  #250 = Utf8               Ljava/lang/CloneNotSupportedException;
  #251 = Utf8               cloneReset
  #252 = Utf8               cloned
  #253 = Utf8               Exceptions
  #254 = Utf8               toString
  #255 = Utf8               (Ljava/lang/Object;)V
  #256 = Utf8               <clinit>
  #257 = Utf8               Ljava/lang/Object;Ljava/util/ListIterator<Ljava/lang/String;>;Ljava/lang/Cloneable;
  #258 = Utf8               SourceFile
  #259 = Utf8               StrTokenizer.java
  #260 = Utf8               Deprecated
  #261 = Utf8               RuntimeVisibleAnnotations
  #262 = Utf8               Ljava/lang/Deprecated;
  #263 = NameAndType        #112:#113     // CSV_TOKENIZER_PROTOTYPE:Lorg/apache/commons/lang3/text/StrTokenizer;
  #264 = NameAndType        #247:#248     // clone:()Ljava/lang/Object;
  #265 = Utf8               org/apache/commons/lang3/text/StrTokenizer
  #266 = NameAndType        #129:#130     // getCSVClone:()Lorg/apache/commons/lang3/text/StrTokenizer;
  #267 = NameAndType        #176:#134     // reset:(Ljava/lang/String;)Lorg/apache/commons/lang3/text/StrTokenizer;
  #268 = NameAndType        #176:#139     // reset:([C)Lorg/apache/commons/lang3/text/StrTokenizer;
  #269 = NameAndType        #114:#113     // TSV_TOKENIZER_PROTOTYPE:Lorg/apache/commons/lang3/text/StrTokenizer;
  #270 = NameAndType        #140:#130     // getTSVClone:()Lorg/apache/commons/lang3/text/StrTokenizer;
  #271 = NameAndType        #142:#143     // "<init>":()V
  #272 = Class              #369          // org/apache/commons/lang3/text/StrMatcher
  #273 = NameAndType        #370:#225     // splitMatcher:()Lorg/apache/commons/lang3/text/StrMatcher;
  #274 = NameAndType        #121:#122     // delimMatcher:Lorg/apache/commons/lang3/text/StrMatcher;
  #275 = NameAndType        #371:#225     // noneMatcher:()Lorg/apache/commons/lang3/text/StrMatcher;
  #276 = NameAndType        #123:#122     // quoteMatcher:Lorg/apache/commons/lang3/text/StrMatcher;
  #277 = NameAndType        #124:#122     // ignoredMatcher:Lorg/apache/commons/lang3/text/StrMatcher;
  #278 = NameAndType        #125:#122     // trimmerMatcher:Lorg/apache/commons/lang3/text/StrMatcher;
  #279 = NameAndType        #126:#127     // emptyAsNull:Z
  #280 = NameAndType        #128:#127     // ignoreEmptyTokens:Z
  #281 = NameAndType        #115:#116     // chars:[C
  #282 = NameAndType        #372:#373     // toCharArray:()[C
  #283 = NameAndType        #142:#145     // "<init>":(Ljava/lang/String;)V
  #284 = NameAndType        #228:#229     // setDelimiterChar:(C)Lorg/apache/commons/lang3/text/StrTokenizer;
  #285 = NameAndType        #230:#134     // setDelimiterString:(Ljava/lang/String;)Lorg/apache/commons/lang3/text/StrTokenizer;
  #286 = NameAndType        #226:#227     // setDelimiterMatcher:(Lorg/apache/commons/lang3/text/StrMatcher;)Lorg/apache/commons/lang3/text/StrTokenizer;
  #287 = NameAndType        #142:#147     // "<init>":(Ljava/lang/String;C)V
  #288 = NameAndType        #233:#229     // setQuoteChar:(C)Lorg/apache/commons/lang3/text/StrTokenizer;
  #289 = NameAndType        #142:#151     // "<init>":(Ljava/lang/String;Lorg/apache/commons/lang3/text/StrMatcher;)V
  #290 = NameAndType        #232:#227     // setQuoteMatcher:(Lorg/apache/commons/lang3/text/StrMatcher;)Lorg/apache/commons/lang3/text/StrTokenizer;
  #291 = Class              #374          // org/apache/commons/lang3/ArrayUtils
  #292 = NameAndType        #247:#375     // clone:([C)[C
  #293 = NameAndType        #142:#155     // "<init>":([C)V
  #294 = NameAndType        #142:#156     // "<init>":([CC)V
  #295 = NameAndType        #142:#158     // "<init>":([CLorg/apache/commons/lang3/text/StrMatcher;)V
  #296 = NameAndType        #188:#143     // checkTokenized:()V
  #297 = NameAndType        #117:#118     // tokens:[Ljava/lang/String;
  #298 = NameAndType        #177:#178     // hasNext:()Z
  #299 = NameAndType        #119:#120     // tokenPos:I
  #300 = NameAndType        #181:#178     // hasPrevious:()Z
  #301 = Class              #118          // "[Ljava/lang/String;"
  #302 = Utf8               java/util/ArrayList
  #303 = NameAndType        #142:#376     // "<init>":(I)V
  #304 = Class              #377          // java/util/Arrays
  #305 = NameAndType        #378:#379     // asList:([Ljava/lang/Object;)Ljava/util/List;
  #306 = NameAndType        #380:#381     // addAll:(Ljava/util/Collection;)Z
  #307 = NameAndType        #176:#130     // reset:()Lorg/apache/commons/lang3/text/StrTokenizer;
  #308 = Utf8               java/util/NoSuchElementException
  #309 = Utf8               java/lang/UnsupportedOperationException
  #310 = Utf8               remove() is unsupported
  #311 = Utf8               set() is unsupported
  #312 = Utf8               add() is unsupported
  #313 = NameAndType        #190:#191     // tokenize:([CII)Ljava/util/List;
  #314 = NameAndType        #161:#162     // size:()I
  #315 = Utf8               java/lang/String
  #316 = NameAndType        #382:#383     // toArray:([Ljava/lang/Object;)[Ljava/lang/Object;
  #317 = Class              #384          // java/util/Collections
  #318 = NameAndType        #385:#169     // emptyList:()Ljava/util/List;
  #319 = Utf8               org/apache/commons/lang3/text/StrBuilder
  #320 = NameAndType        #204:#205     // readNextToken:([CIILorg/apache/commons/lang3/text/StrBuilder;Ljava/util/List;)I
  #321 = Utf8               org/apache/commons/lang3/StringUtils
  #322 = Utf8
  #323 = NameAndType        #201:#202     // addToken:(Ljava/util/List;Ljava/lang/String;)V
  #324 = NameAndType        #386:#387     // isEmpty:(Ljava/lang/CharSequence;)Z
  #325 = NameAndType        #244:#178     // isIgnoreEmptyTokens:()Z
  #326 = NameAndType        #241:#178     // isEmptyTokenAsNull:()Z
  #327 = NameAndType        #187:#388     // add:(Ljava/lang/Object;)Z
  #328 = NameAndType        #234:#225     // getIgnoredMatcher:()Lorg/apache/commons/lang3/text/StrMatcher;
  #329 = NameAndType        #389:#390     // isMatch:([CIII)I
  #330 = NameAndType        #238:#225     // getTrimmerMatcher:()Lorg/apache/commons/lang3/text/StrMatcher;
  #331 = Class              #391          // java/lang/Math
  #332 = NameAndType        #392:#393     // max:(II)I
  #333 = NameAndType        #224:#225     // getDelimiterMatcher:()Lorg/apache/commons/lang3/text/StrMatcher;
  #334 = NameAndType        #231:#225     // getQuoteMatcher:()Lorg/apache/commons/lang3/text/StrMatcher;
  #335 = NameAndType        #213:#214     // readWithQuotes:([CIILorg/apache/commons/lang3/text/StrBuilder;Ljava/util/List;II)I
  #336 = NameAndType        #394:#395     // clear:()Lorg/apache/commons/lang3/text/StrBuilder;
  #337 = NameAndType        #221:#222     // isQuote:([CIIII)Z
  #338 = NameAndType        #396:#397     // append:([CII)Lorg/apache/commons/lang3/text/StrBuilder;
  #339 = NameAndType        #396:#398     // append:(C)Lorg/apache/commons/lang3/text/StrBuilder;
  #340 = NameAndType        #399:#400     // substring:(II)Ljava/lang/String;
  #341 = NameAndType        #401:#402     // charMatcher:(C)Lorg/apache/commons/lang3/text/StrMatcher;
  #342 = NameAndType        #403:#404     // stringMatcher:(Ljava/lang/String;)Lorg/apache/commons/lang3/text/StrMatcher;
  #343 = NameAndType        #235:#227     // setIgnoredMatcher:(Lorg/apache/commons/lang3/text/StrMatcher;)Lorg/apache/commons/lang3/text/StrTokenizer;
  #344 = NameAndType        #251:#248     // cloneReset:()Ljava/lang/Object;
  #345 = Utf8               java/lang/CloneNotSupportedException
  #346 = Class              #116          // "[C"
  #347 = Utf8               StrTokenizer[not tokenized yet]
  #348 = Utf8               java/lang/StringBuilder
  #349 = Utf8               StrTokenizer
  #350 = NameAndType        #396:#405     // append:(Ljava/lang/String;)Ljava/lang/StringBuilder;
  #351 = NameAndType        #168:#169     // getTokenList:()Ljava/util/List;
  #352 = NameAndType        #396:#406     // append:(Ljava/lang/Object;)Ljava/lang/StringBuilder;
  #353 = NameAndType        #254:#164     // toString:()Ljava/lang/String;
  #354 = NameAndType        #187:#145     // add:(Ljava/lang/String;)V
  #355 = NameAndType        #185:#145     // set:(Ljava/lang/String;)V
  #356 = NameAndType        #182:#164     // previous:()Ljava/lang/String;
  #357 = NameAndType        #179:#164     // next:()Ljava/lang/String;
  #358 = NameAndType        #407:#225     // commaMatcher:()Lorg/apache/commons/lang3/text/StrMatcher;
  #359 = NameAndType        #408:#225     // doubleQuoteMatcher:()Lorg/apache/commons/lang3/text/StrMatcher;
  #360 = NameAndType        #409:#225     // trimMatcher:()Lorg/apache/commons/lang3/text/StrMatcher;
  #361 = NameAndType        #239:#227     // setTrimmerMatcher:(Lorg/apache/commons/lang3/text/StrMatcher;)Lorg/apache/commons/lang3/text/StrTokenizer;
  #362 = NameAndType        #242:#243     // setEmptyTokenAsNull:(Z)Lorg/apache/commons/lang3/text/StrTokenizer;
  #363 = NameAndType        #245:#243     // setIgnoreEmptyTokens:(Z)Lorg/apache/commons/lang3/text/StrTokenizer;
  #364 = NameAndType        #410:#225     // tabMatcher:()Lorg/apache/commons/lang3/text/StrMatcher;
  #365 = Utf8               java/lang/Object
  #366 = Utf8               java/util/ListIterator
  #367 = Utf8               java/lang/Cloneable
  #368 = Utf8               java/util/List
  #369 = Utf8               org/apache/commons/lang3/text/StrMatcher
  #370 = Utf8               splitMatcher
  #371 = Utf8               noneMatcher
  #372 = Utf8               toCharArray
  #373 = Utf8               ()[C
  #374 = Utf8               org/apache/commons/lang3/ArrayUtils
  #375 = Utf8               ([C)[C
  #376 = Utf8               (I)V
  #377 = Utf8               java/util/Arrays
  #378 = Utf8               asList
  #379 = Utf8               ([Ljava/lang/Object;)Ljava/util/List;
  #380 = Utf8               addAll
  #381 = Utf8               (Ljava/util/Collection;)Z
  #382 = Utf8               toArray
  #383 = Utf8               ([Ljava/lang/Object;)[Ljava/lang/Object;
  #384 = Utf8               java/util/Collections
  #385 = Utf8               emptyList
  #386 = Utf8               isEmpty
  #387 = Utf8               (Ljava/lang/CharSequence;)Z
  #388 = Utf8               (Ljava/lang/Object;)Z
  #389 = Utf8               isMatch
  #390 = Utf8               ([CIII)I
  #391 = Utf8               java/lang/Math
  #392 = Utf8               max
  #393 = Utf8               (II)I
  #394 = Utf8               clear
  #395 = Utf8               ()Lorg/apache/commons/lang3/text/StrBuilder;
  #396 = Utf8               append
  #397 = Utf8               ([CII)Lorg/apache/commons/lang3/text/StrBuilder;
  #398 = Utf8               (C)Lorg/apache/commons/lang3/text/StrBuilder;
  #399 = Utf8               substring
  #400 = Utf8               (II)Ljava/lang/String;
  #401 = Utf8               charMatcher
  #402 = Utf8               (C)Lorg/apache/commons/lang3/text/StrMatcher;
  #403 = Utf8               stringMatcher
  #404 = Utf8               (Ljava/lang/String;)Lorg/apache/commons/lang3/text/StrMatcher;
  #405 = Utf8               (Ljava/lang/String;)Ljava/lang/StringBuilder;
  #406 = Utf8               (Ljava/lang/Object;)Ljava/lang/StringBuilder;
  #407 = Utf8               commaMatcher
  #408 = Utf8               doubleQuoteMatcher
  #409 = Utf8               trimMatcher
  #410 = Utf8               tabMatcher
{
  private static final org.apache.commons.lang3.text.StrTokenizer CSV_TOKENIZER_PROTOTYPE;
    descriptor: Lorg/apache/commons/lang3/text/StrTokenizer;
    flags: (0x001a) ACC_PRIVATE, ACC_STATIC, ACC_FINAL

  private static final org.apache.commons.lang3.text.StrTokenizer TSV_TOKENIZER_PROTOTYPE;
    descriptor: Lorg/apache/commons/lang3/text/StrTokenizer;
    flags: (0x001a) ACC_PRIVATE, ACC_STATIC, ACC_FINAL

  private char[] chars;
    descriptor: [C
    flags: (0x0002) ACC_PRIVATE

  private java.lang.String[] tokens;
    descriptor: [Ljava/lang/String;
    flags: (0x0002) ACC_PRIVATE

  private int tokenPos;
    descriptor: I
    flags: (0x0002) ACC_PRIVATE

  private org.apache.commons.lang3.text.StrMatcher delimMatcher;
    descriptor: Lorg/apache/commons/lang3/text/StrMatcher;
    flags: (0x0002) ACC_PRIVATE

  private org.apache.commons.lang3.text.StrMatcher quoteMatcher;
    descriptor: Lorg/apache/commons/lang3/text/StrMatcher;
    flags: (0x0002) ACC_PRIVATE

  private org.apache.commons.lang3.text.StrMatcher ignoredMatcher;
    descriptor: Lorg/apache/commons/lang3/text/StrMatcher;
    flags: (0x0002) ACC_PRIVATE

  private org.apache.commons.lang3.text.StrMatcher trimmerMatcher;
    descriptor: Lorg/apache/commons/lang3/text/StrMatcher;
    flags: (0x0002) ACC_PRIVATE

  private boolean emptyAsNull;
    descriptor: Z
    flags: (0x0002) ACC_PRIVATE

  private boolean ignoreEmptyTokens;
    descriptor: Z
    flags: (0x0002) ACC_PRIVATE

  private static org.apache.commons.lang3.text.StrTokenizer getCSVClone();
    descriptor: ()Lorg/apache/commons/lang3/text/StrTokenizer;
    flags: (0x000a) ACC_PRIVATE, ACC_STATIC
    Code:
      stack=1, locals=0, args_size=0
         0: getstatic     #1                  // Field CSV_TOKENIZER_PROTOTYPE:Lorg/apache/commons/lang3/text/StrTokenizer;
         3: invokevirtual #2                  // Method clone:()Ljava/lang/Object;
         6: checkcast     #3                  // class org/apache/commons/lang3/text/StrTokenizer
         9: areturn
      LineNumberTable:
        line 141: 0

  public static org.apache.commons.lang3.text.StrTokenizer getCSVInstance();
    descriptor: ()Lorg/apache/commons/lang3/text/StrTokenizer;
    flags: (0x0009) ACC_PUBLIC, ACC_STATIC
    Code:
      stack=1, locals=0, args_size=0
         0: invokestatic  #4                  // Method getCSVClone:()Lorg/apache/commons/lang3/text/StrTokenizer;
         3: areturn
      LineNumberTable:
        line 154: 0

  public static org.apache.commons.lang3.text.StrTokenizer getCSVInstance(java.lang.String);
    descriptor: (Ljava/lang/String;)Lorg/apache/commons/lang3/text/StrTokenizer;
    flags: (0x0009) ACC_PUBLIC, ACC_STATIC
    Code:
      stack=2, locals=2, args_size=1
         0: invokestatic  #4                  // Method getCSVClone:()Lorg/apache/commons/lang3/text/StrTokenizer;
         3: astore_1
         4: aload_1
         5: aload_0
         6: invokevirtual #5                  // Method reset:(Ljava/lang/String;)Lorg/apache/commons/lang3/text/StrTokenizer;
         9: pop
        10: aload_1
        11: areturn
      LineNumberTable:
        line 167: 0
        line 168: 4
        line 169: 10
      LocalVariableTable:
        Start  Length  Slot  Name   Signature
            0      12     0 input   Ljava/lang/String;
            4       8     1   tok   Lorg/apache/commons/lang3/text/StrTokenizer;

  public static org.apache.commons.lang3.text.StrTokenizer getCSVInstance(char[]);
    descriptor: ([C)Lorg/apache/commons/lang3/text/StrTokenizer;
    flags: (0x0009) ACC_PUBLIC, ACC_STATIC
    Code:
      stack=2, locals=2, args_size=1
         0: invokestatic  #4                  // Method getCSVClone:()Lorg/apache/commons/lang3/text/StrTokenizer;
         3: astore_1
         4: aload_1
         5: aload_0
         6: invokevirtual #6                  // Method reset:([C)Lorg/apache/commons/lang3/text/StrTokenizer;
         9: pop
        10: aload_1
        11: areturn
      LineNumberTable:
        line 182: 0
        line 183: 4
        line 184: 10
      LocalVariableTable:
        Start  Length  Slot  Name   Signature
            0      12     0 input   [C
            4       8     1   tok   Lorg/apache/commons/lang3/text/StrTokenizer;

  private static org.apache.commons.lang3.text.StrTokenizer getTSVClone();
    descriptor: ()Lorg/apache/commons/lang3/text/StrTokenizer;
    flags: (0x000a) ACC_PRIVATE, ACC_STATIC
    Code:
      stack=1, locals=0, args_size=0
         0: getstatic     #7                  // Field TSV_TOKENIZER_PROTOTYPE:Lorg/apache/commons/lang3/text/StrTokenizer;
         3: invokevirtual #2                  // Method clone:()Ljava/lang/Object;
         6: checkcast     #3                  // class org/apache/commons/lang3/text/StrTokenizer
         9: areturn
      LineNumberTable:
        line 193: 0

  public static org.apache.commons.lang3.text.StrTokenizer getTSVInstance();
    descriptor: ()Lorg/apache/commons/lang3/text/StrTokenizer;
    flags: (0x0009) ACC_PUBLIC, ACC_STATIC
    Code:
      stack=1, locals=0, args_size=0
         0: invokestatic  #8                  // Method getTSVClone:()Lorg/apache/commons/lang3/text/StrTokenizer;
         3: areturn
      LineNumberTable:
        line 206: 0

  public static org.apache.commons.lang3.text.StrTokenizer getTSVInstance(java.lang.String);
    descriptor: (Ljava/lang/String;)Lorg/apache/commons/lang3/text/StrTokenizer;
    flags: (0x0009) ACC_PUBLIC, ACC_STATIC
    Code:
      stack=2, locals=2, args_size=1
         0: invokestatic  #8                  // Method getTSVClone:()Lorg/apache/commons/lang3/text/StrTokenizer;
         3: astore_1
         4: aload_1
         5: aload_0
         6: invokevirtual #5                  // Method reset:(Ljava/lang/String;)Lorg/apache/commons/lang3/text/StrTokenizer;
         9: pop
        10: aload_1
        11: areturn
      LineNumberTable:
        line 217: 0
        line 218: 4
        line 219: 10
      LocalVariableTable:
        Start  Length  Slot  Name   Signature
            0      12     0 input   Ljava/lang/String;
            4       8     1   tok   Lorg/apache/commons/lang3/text/StrTokenizer;

  public static org.apache.commons.lang3.text.StrTokenizer getTSVInstance(char[]);
    descriptor: ([C)Lorg/apache/commons/lang3/text/StrTokenizer;
    flags: (0x0009) ACC_PUBLIC, ACC_STATIC
    Code:
      stack=2, locals=2, args_size=1
         0: invokestatic  #8                  // Method getTSVClone:()Lorg/apache/commons/lang3/text/StrTokenizer;
         3: astore_1
         4: aload_1
         5: aload_0
         6: invokevirtual #6                  // Method reset:([C)Lorg/apache/commons/lang3/text/StrTokenizer;
         9: pop
        10: aload_1
        11: areturn
      LineNumberTable:
        line 230: 0
        line 231: 4
        line 232: 10
      LocalVariableTable:
        Start  Length  Slot  Name   Signature
            0      12     0 input   [C
            4       8     1   tok   Lorg/apache/commons/lang3/text/StrTokenizer;

  public org.apache.commons.lang3.text.StrTokenizer();
    descriptor: ()V
    flags: (0x0001) ACC_PUBLIC
    Code:
      stack=2, locals=1, args_size=1
         0: aload_0
         1: invokespecial #9                  // Method java/lang/Object."<init>":()V
         4: aload_0
         5: invokestatic  #10                 // Method org/apache/commons/lang3/text/StrMatcher.splitMatcher:()Lorg/apache/commons/lang3/text/StrMatcher;
         8: putfield      #11                 // Field delimMatcher:Lorg/apache/commons/lang3/text/StrMatcher;
        11: aload_0
        12: invokestatic  #12                 // Method org/apache/commons/lang3/text/StrMatcher.noneMatcher:()Lorg/apache/commons/lang3/text/StrMatcher;
        15: putfield      #13                 // Field quoteMatcher:Lorg/apache/commons/lang3/text/StrMatcher;
        18: aload_0
        19: invokestatic  #12                 // Method org/apache/commons/lang3/text/StrMatcher.noneMatcher:()Lorg/apache/commons/lang3/text/StrMatcher;
        22: putfield      #14                 // Field ignoredMatcher:Lorg/apache/commons/lang3/text/StrMatcher;
        25: aload_0
        26: invokestatic  #12                 // Method org/apache/commons/lang3/text/StrMatcher.noneMatcher:()Lorg/apache/commons/lang3/text/StrMatcher;
        29: putfield      #15                 // Field trimmerMatcher:Lorg/apache/commons/lang3/text/StrMatcher;
        32: aload_0
        33: iconst_0
        34: putfield      #16                 // Field emptyAsNull:Z
        37: aload_0
        38: iconst_1
        39: putfield      #17                 // Field ignoreEmptyTokens:Z
        42: aload_0
        43: aconst_null
        44: putfield      #18                 // Field chars:[C
        47: return
      LineNumberTable:
        line 243: 0
        line 120: 4
        line 122: 11
        line 124: 18
        line 126: 25
        line 129: 32
        line 131: 37
        line 244: 42
        line 245: 47
      LocalVariableTable:
        Start  Length  Slot  Name   Signature
            0      48     0  this   Lorg/apache/commons/lang3/text/StrTokenizer;

  public org.apache.commons.lang3.text.StrTokenizer(java.lang.String);
    descriptor: (Ljava/lang/String;)V
    flags: (0x0001) ACC_PUBLIC
    Code:
      stack=2, locals=2, args_size=2
         0: aload_0
         1: invokespecial #9                  // Method java/lang/Object."<init>":()V
         4: aload_0
         5: invokestatic  #10                 // Method org/apache/commons/lang3/text/StrMatcher.splitMatcher:()Lorg/apache/commons/lang3/text/StrMatcher;
         8: putfield      #11                 // Field delimMatcher:Lorg/apache/commons/lang3/text/StrMatcher;
        11: aload_0
        12: invokestatic  #12                 // Method org/apache/commons/lang3/text/StrMatcher.noneMatcher:()Lorg/apache/commons/lang3/text/StrMatcher;
        15: putfield      #13                 // Field quoteMatcher:Lorg/apache/commons/lang3/text/StrMatcher;
        18: aload_0
        19: invokestatic  #12                 // Method org/apache/commons/lang3/text/StrMatcher.noneMatcher:()Lorg/apache/commons/lang3/text/StrMatcher;
        22: putfield      #14                 // Field ignoredMatcher:Lorg/apache/commons/lang3/text/StrMatcher;
        25: aload_0
        26: invokestatic  #12                 // Method org/apache/commons/lang3/text/StrMatcher.noneMatcher:()Lorg/apache/commons/lang3/text/StrMatcher;
        29: putfield      #15                 // Field trimmerMatcher:Lorg/apache/commons/lang3/text/StrMatcher;
        32: aload_0
        33: iconst_0
        34: putfield      #16                 // Field emptyAsNull:Z
        37: aload_0
        38: iconst_1
        39: putfield      #17                 // Field ignoreEmptyTokens:Z
        42: aload_1
        43: ifnull        57
        46: aload_0
        47: aload_1
        48: invokevirtual #19                 // Method java/lang/String.toCharArray:()[C
        51: putfield      #18                 // Field chars:[C
        54: goto          62
        57: aload_0
        58: aconst_null
        59: putfield      #18                 // Field chars:[C
        62: return
      LineNumberTable:
        line 254: 0
        line 120: 4
        line 122: 11
        line 124: 18
        line 126: 25
        line 129: 32
        line 131: 37
        line 255: 42
        line 256: 46
        line 258: 57
        line 260: 62
      LocalVariableTable:
        Start  Length  Slot  Name   Signature
            0      63     0  this   Lorg/apache/commons/lang3/text/StrTokenizer;
            0      63     1 input   Ljava/lang/String;
      StackMapTable: number_of_entries = 2
        frame_type = 255 /* full_frame */
          offset_delta = 57
          locals = [ class org/apache/commons/lang3/text/StrTokenizer, class java/lang/String ]
          stack = []
        frame_type = 4 /* same */

  public org.apache.commons.lang3.text.StrTokenizer(java.lang.String, char);
    descriptor: (Ljava/lang/String;C)V
    flags: (0x0001) ACC_PUBLIC
    Code:
      stack=2, locals=3, args_size=3
         0: aload_0
         1: aload_1
         2: invokespecial #20                 // Method "<init>":(Ljava/lang/String;)V
         5: aload_0
         6: iload_2
         7: invokevirtual #21                 // Method setDelimiterChar:(C)Lorg/apache/commons/lang3/text/StrTokenizer;
        10: pop
        11: return
      LineNumberTable:
        line 269: 0
        line 270: 5
        line 271: 11
      LocalVariableTable:
        Start  Length  Slot  Name   Signature
            0      12     0  this   Lorg/apache/commons/lang3/text/StrTokenizer;
            0      12     1 input   Ljava/lang/String;
            0      12     2 delim   C

  public org.apache.commons.lang3.text.StrTokenizer(java.lang.String, java.lang.String);
    descriptor: (Ljava/lang/String;Ljava/lang/String;)V
    flags: (0x0001) ACC_PUBLIC
    Code:
      stack=2, locals=3, args_size=3
         0: aload_0
         1: aload_1
         2: invokespecial #20                 // Method "<init>":(Ljava/lang/String;)V
         5: aload_0
         6: aload_2
         7: invokevirtual #22                 // Method setDelimiterString:(Ljava/lang/String;)Lorg/apache/commons/lang3/text/StrTokenizer;
        10: pop
        11: return
      LineNumberTable:
        line 280: 0
        line 281: 5
        line 282: 11
      LocalVariableTable:
        Start  Length  Slot  Name   Signature
            0      12     0  this   Lorg/apache/commons/lang3/text/StrTokenizer;
            0      12     1 input   Ljava/lang/String;
            0      12     2 delim   Ljava/lang/String;

  public org.apache.commons.lang3.text.StrTokenizer(java.lang.String, org.apache.commons.lang3.text.StrMatcher);
    descriptor: (Ljava/lang/String;Lorg/apache/commons/lang3/text/StrMatcher;)V
    flags: (0x0001) ACC_PUBLIC
    Code:
      stack=2, locals=3, args_size=3
         0: aload_0
         1: aload_1
         2: invokespecial #20                 // Method "<init>":(Ljava/lang/String;)V
         5: aload_0
         6: aload_2
         7: invokevirtual #23                 // Method setDelimiterMatcher:(Lorg/apache/commons/lang3/text/StrMatcher;)Lorg/apache/commons/lang3/text/StrTokenizer;
        10: pop
        11: return
      LineNumberTable:
        line 291: 0
        line 292: 5
        line 293: 11
      LocalVariableTable:
        Start  Length  Slot  Name   Signature
            0      12     0  this   Lorg/apache/commons/lang3/text/StrTokenizer;
            0      12     1 input   Ljava/lang/String;
            0      12     2 delim   Lorg/apache/commons/lang3/text/StrMatcher;

  public org.apache.commons.lang3.text.StrTokenizer(java.lang.String, char, char);
    descriptor: (Ljava/lang/String;CC)V
    flags: (0x0001) ACC_PUBLIC
    Code:
      stack=3, locals=4, args_size=4
         0: aload_0
         1: aload_1
         2: iload_2
         3: invokespecial #24                 // Method "<init>":(Ljava/lang/String;C)V
         6: aload_0
         7: iload_3
         8: invokevirtual #25                 // Method setQuoteChar:(C)Lorg/apache/commons/lang3/text/StrTokenizer;
        11: pop
        12: return
      LineNumberTable:
        line 304: 0
        line 305: 6
        line 306: 12
      LocalVariableTable:
        Start  Length  Slot  Name   Signature
            0      13     0  this   Lorg/apache/commons/lang3/text/StrTokenizer;
            0      13     1 input   Ljava/lang/String;
            0      13     2 delim   C
            0      13     3 quote   C

  public org.apache.commons.lang3.text.StrTokenizer(java.lang.String, org.apache.commons.lang3.text.StrMatcher, org.apache.commons.lang3.text.StrMatcher);
    descriptor: (Ljava/lang/String;Lorg/apache/commons/lang3/text/StrMatcher;Lorg/apache/commons/lang3/text/StrMatcher;)V
    flags: (0x0001) ACC_PUBLIC
    Code:
      stack=3, locals=4, args_size=4
         0: aload_0
         1: aload_1
         2: aload_2
         3: invokespecial #26                 // Method "<init>":(Ljava/lang/String;Lorg/apache/commons/lang3/text/StrMatcher;)V
         6: aload_0
         7: aload_3
         8: invokevirtual #27                 // Method setQuoteMatcher:(Lorg/apache/commons/lang3/text/StrMatcher;)Lorg/apache/commons/lang3/text/StrTokenizer;
        11: pop
        12: return
      LineNumberTable:
        line 317: 0
        line 318: 6
        line 319: 12
      LocalVariableTable:
        Start  Length  Slot  Name   Signature
            0      13     0  this   Lorg/apache/commons/lang3/text/StrTokenizer;
            0      13     1 input   Ljava/lang/String;
            0      13     2 delim   Lorg/apache/commons/lang3/text/StrMatcher;
            0      13     3 quote   Lorg/apache/commons/lang3/text/StrMatcher;

  public org.apache.commons.lang3.text.StrTokenizer(char[]);
    descriptor: ([C)V
    flags: (0x0001) ACC_PUBLIC
    Code:
      stack=2, locals=2, args_size=2
         0: aload_0
         1: invokespecial #9                  // Method java/lang/Object."<init>":()V
         4: aload_0
         5: invokestatic  #10                 // Method org/apache/commons/lang3/text/StrMatcher.splitMatcher:()Lorg/apache/commons/lang3/text/StrMatcher;
         8: putfield      #11                 // Field delimMatcher:Lorg/apache/commons/lang3/text/StrMatcher;
        11: aload_0
        12: invokestatic  #12                 // Method org/apache/commons/lang3/text/StrMatcher.noneMatcher:()Lorg/apache/commons/lang3/text/StrMatcher;
        15: putfield      #13                 // Field quoteMatcher:Lorg/apache/commons/lang3/text/StrMatcher;
        18: aload_0
        19: invokestatic  #12                 // Method org/apache/commons/lang3/text/StrMatcher.noneMatcher:()Lorg/apache/commons/lang3/text/StrMatcher;
        22: putfield      #14                 // Field ignoredMatcher:Lorg/apache/commons/lang3/text/StrMatcher;
        25: aload_0
        26: invokestatic  #12                 // Method org/apache/commons/lang3/text/StrMatcher.noneMatcher:()Lorg/apache/commons/lang3/text/StrMatcher;
        29: putfield      #15                 // Field trimmerMatcher:Lorg/apache/commons/lang3/text/StrMatcher;
        32: aload_0
        33: iconst_0
        34: putfield      #16                 // Field emptyAsNull:Z
        37: aload_0
        38: iconst_1
        39: putfield      #17                 // Field ignoreEmptyTokens:Z
        42: aload_0
        43: aload_1
        44: invokestatic  #28                 // Method org/apache/commons/lang3/ArrayUtils.clone:([C)[C
        47: putfield      #18                 // Field chars:[C
        50: return
      LineNumberTable:
        line 328: 0
        line 120: 4
        line 122: 11
        line 124: 18
        line 126: 25
        line 129: 32
        line 131: 37
        line 329: 42
        line 330: 50
      LocalVariableTable:
        Start  Length  Slot  Name   Signature
            0      51     0  this   Lorg/apache/commons/lang3/text/StrTokenizer;
            0      51     1 input   [C

  public org.apache.commons.lang3.text.StrTokenizer(char[], char);
    descriptor: ([CC)V
    flags: (0x0001) ACC_PUBLIC
    Code:
      stack=2, locals=3, args_size=3
         0: aload_0
         1: aload_1
         2: invokespecial #29                 // Method "<init>":([C)V
         5: aload_0
         6: iload_2
         7: invokevirtual #21                 // Method setDelimiterChar:(C)Lorg/apache/commons/lang3/text/StrTokenizer;
        10: pop
        11: return
      LineNumberTable:
        line 339: 0
        line 340: 5
        line 341: 11
      LocalVariableTable:
        Start  Length  Slot  Name   Signature
            0      12     0  this   Lorg/apache/commons/lang3/text/StrTokenizer;
            0      12     1 input   [C
            0      12     2 delim   C

  public org.apache.commons.lang3.text.StrTokenizer(char[], java.lang.String);
    descriptor: ([CLjava/lang/String;)V
    flags: (0x0001) ACC_PUBLIC
    Code:
      stack=2, locals=3, args_size=3
         0: aload_0
         1: aload_1
         2: invokespecial #29                 // Method "<init>":([C)V
         5: aload_0
         6: aload_2
         7: invokevirtual #22                 // Method setDelimiterString:(Ljava/lang/String;)Lorg/apache/commons/lang3/text/StrTokenizer;
        10: pop
        11: return
      LineNumberTable:
        line 350: 0
        line 351: 5
        line 352: 11
      LocalVariableTable:
        Start  Length  Slot  Name   Signature
            0      12     0  this   Lorg/apache/commons/lang3/text/StrTokenizer;
            0      12     1 input   [C
            0      12     2 delim   Ljava/lang/String;

  public org.apache.commons.lang3.text.StrTokenizer(char[], org.apache.commons.lang3.text.StrMatcher);
    descriptor: ([CLorg/apache/commons/lang3/text/StrMatcher;)V
    flags: (0x0001) ACC_PUBLIC
    Code:
      stack=2, locals=3, args_size=3
         0: aload_0
         1: aload_1
         2: invokespecial #29                 // Method "<init>":([C)V
         5: aload_0
         6: aload_2
         7: invokevirtual #23                 // Method setDelimiterMatcher:(Lorg/apache/commons/lang3/text/StrMatcher;)Lorg/apache/commons/lang3/text/StrTokenizer;
        10: pop
        11: return
      LineNumberTable:
        line 361: 0
        line 362: 5
        line 363: 11
      LocalVariableTable:
        Start  Length  Slot  Name   Signature
            0      12     0  this   Lorg/apache/commons/lang3/text/StrTokenizer;
            0      12     1 input   [C
            0      12     2 delim   Lorg/apache/commons/lang3/text/StrMatcher;

  public org.apache.commons.lang3.text.StrTokenizer(char[], char, char);
    descriptor: ([CCC)V
    flags: (0x0001) ACC_PUBLIC
    Code:
      stack=3, locals=4, args_size=4
         0: aload_0
         1: aload_1
         2: iload_2
         3: invokespecial #30                 // Method "<init>":([CC)V
         6: aload_0
         7: iload_3
         8: invokevirtual #25                 // Method setQuoteChar:(C)Lorg/apache/commons/lang3/text/StrTokenizer;
        11: pop
        12: return
      LineNumberTable:
        line 374: 0
        line 375: 6
        line 376: 12
      LocalVariableTable:
        Start  Length  Slot  Name   Signature
            0      13     0  this   Lorg/apache/commons/lang3/text/StrTokenizer;
            0      13     1 input   [C
            0      13     2 delim   C
            0      13     3 quote   C

  public org.apache.commons.lang3.text.StrTokenizer(char[], org.apache.commons.lang3.text.StrMatcher, org.apache.commons.lang3.text.StrMatcher);
    descriptor: ([CLorg/apache/commons/lang3/text/StrMatcher;Lorg/apache/commons/lang3/text/StrMatcher;)V
    flags: (0x0001) ACC_PUBLIC
    Code:
      stack=3, locals=4, args_size=4
         0: aload_0
         1: aload_1
         2: aload_2
         3: invokespecial #31                 // Method "<init>":([CLorg/apache/commons/lang3/text/StrMatcher;)V
         6: aload_0
         7: aload_3
         8: invokevirtual #27                 // Method setQuoteMatcher:(Lorg/apache/commons/lang3/text/StrMatcher;)Lorg/apache/commons/lang3/text/StrTokenizer;
        11: pop
        12: return
      LineNumberTable:
        line 387: 0
        line 388: 6
        line 389: 12
      LocalVariableTable:
        Start  Length  Slot  Name   Signature
            0      13     0  this   Lorg/apache/commons/lang3/text/StrTokenizer;
            0      13     1 input   [C
            0      13     2 delim   Lorg/apache/commons/lang3/text/StrMatcher;
            0      13     3 quote   Lorg/apache/commons/lang3/text/StrMatcher;

  public int size();
    descriptor: ()I
    flags: (0x0001) ACC_PUBLIC
    Code:
      stack=1, locals=1, args_size=1
         0: aload_0
         1: invokespecial #32                 // Method checkTokenized:()V
         4: aload_0
         5: getfield      #33                 // Field tokens:[Ljava/lang/String;
         8: arraylength
         9: ireturn
      LineNumberTable:
        line 399: 0
        line 400: 4
      LocalVariableTable:
        Start  Length  Slot  Name   Signature
            0      10     0  this   Lorg/apache/commons/lang3/text/StrTokenizer;

  public java.lang.String nextToken();
    descriptor: ()Ljava/lang/String;
    flags: (0x0001) ACC_PUBLIC
    Code:
      stack=5, locals=1, args_size=1
         0: aload_0
         1: invokevirtual #34                 // Method hasNext:()Z
         4: ifeq          24
         7: aload_0
         8: getfield      #33                 // Field tokens:[Ljava/lang/String;
        11: aload_0
        12: dup
        13: getfield      #35                 // Field tokenPos:I
        16: dup_x1
        17: iconst_1
        18: iadd
        19: putfield      #35                 // Field tokenPos:I
        22: aaload
        23: areturn
        24: aconst_null
        25: areturn
      LineNumberTable:
        line 411: 0
        line 412: 7
        line 414: 24
      LocalVariableTable:
        Start  Length  Slot  Name   Signature
            0      26     0  this   Lorg/apache/commons/lang3/text/StrTokenizer;
      StackMapTable: number_of_entries = 1
        frame_type = 24 /* same */

  public java.lang.String previousToken();
    descriptor: ()Ljava/lang/String;
    flags: (0x0001) ACC_PUBLIC
    Code:
      stack=4, locals=1, args_size=1
         0: aload_0
         1: invokevirtual #36                 // Method hasPrevious:()Z
         4: ifeq          24
         7: aload_0
         8: getfield      #33                 // Field tokens:[Ljava/lang/String;
        11: aload_0
        12: dup
        13: getfield      #35                 // Field tokenPos:I
        16: iconst_1
        17: isub
        18: dup_x1
        19: putfield      #35                 // Field tokenPos:I
        22: aaload
        23: areturn
        24: aconst_null
        25: areturn
      LineNumberTable:
        line 423: 0
        line 424: 7
        line 426: 24
      LocalVariableTable:
        Start  Length  Slot  Name   Signature
            0      26     0  this   Lorg/apache/commons/lang3/text/StrTokenizer;
      StackMapTable: number_of_entries = 1
        frame_type = 24 /* same */

  public java.lang.String[] getTokenArray();
    descriptor: ()[Ljava/lang/String;
    flags: (0x0001) ACC_PUBLIC
    Code:
      stack=1, locals=1, args_size=1
         0: aload_0
         1: invokespecial #32                 // Method checkTokenized:()V
         4: aload_0
         5: getfield      #33                 // Field tokens:[Ljava/lang/String;
         8: invokevirtual #37                 // Method "[Ljava/lang/String;".clone:()Ljava/lang/Object;
        11: checkcast     #38                 // class "[Ljava/lang/String;"
        14: areturn
      LineNumberTable:
        line 435: 0
        line 436: 4
      LocalVariableTable:
        Start  Length  Slot  Name   Signature
            0      15     0  this   Lorg/apache/commons/lang3/text/StrTokenizer;

  public java.util.List<java.lang.String> getTokenList();
    descriptor: ()Ljava/util/List;
    flags: (0x0001) ACC_PUBLIC
    Code:
      stack=3, locals=2, args_size=1
         0: aload_0
         1: invokespecial #32                 // Method checkTokenized:()V
         4: new           #39                 // class java/util/ArrayList
         7: dup
         8: aload_0
         9: getfield      #33                 // Field tokens:[Ljava/lang/String;
        12: arraylength
        13: invokespecial #40                 // Method java/util/ArrayList."<init>":(I)V
        16: astore_1
        17: aload_1
        18: aload_0
        19: getfield      #33                 // Field tokens:[Ljava/lang/String;
        22: invokestatic  #41                 // Method java/util/Arrays.asList:([Ljava/lang/Object;)Ljava/util/List;
        25: invokeinterface #42,  2           // InterfaceMethod java/util/List.addAll:(Ljava/util/Collection;)Z
        30: pop
        31: aload_1
        32: areturn
      LineNumberTable:
        line 445: 0
        line 446: 4
        line 447: 17
        line 448: 31
      LocalVariableTable:
        Start  Length  Slot  Name   Signature
            0      33     0  this   Lorg/apache/commons/lang3/text/StrTokenizer;
           17      16     1  list   Ljava/util/List;
      LocalVariableTypeTable:
        Start  Length  Slot  Name   Signature
           17      16     1  list   Ljava/util/List<Ljava/lang/String;>;
    Signature: #175                         // ()Ljava/util/List<Ljava/lang/String;>;

  public org.apache.commons.lang3.text.StrTokenizer reset();
    descriptor: ()Lorg/apache/commons/lang3/text/StrTokenizer;
    flags: (0x0001) ACC_PUBLIC
    Code:
      stack=2, locals=1, args_size=1
         0: aload_0
         1: iconst_0
         2: putfield      #35                 // Field tokenPos:I
         5: aload_0
         6: aconst_null
         7: putfield      #33                 // Field tokens:[Ljava/lang/String;
        10: aload_0
        11: areturn
      LineNumberTable:
        line 459: 0
        line 460: 5
        line 461: 10
      LocalVariableTable:
        Start  Length  Slot  Name   Signature
            0      12     0  this   Lorg/apache/commons/lang3/text/StrTokenizer;

  public org.apache.commons.lang3.text.StrTokenizer reset(java.lang.String);
    descriptor: (Ljava/lang/String;)Lorg/apache/commons/lang3/text/StrTokenizer;
    flags: (0x0001) ACC_PUBLIC
    Code:
      stack=2, locals=2, args_size=2
         0: aload_0
         1: invokevirtual #43                 // Method reset:()Lorg/apache/commons/lang3/text/StrTokenizer;
         4: pop
         5: aload_1
         6: ifnull        20
         9: aload_0
        10: aload_1
        11: invokevirtual #19                 // Method java/lang/String.toCharArray:()[C
        14: putfield      #18                 // Field chars:[C
        17: goto          25
        20: aload_0
        21: aconst_null
        22: putfield      #18                 // Field chars:[C
        25: aload_0
        26: areturn
      LineNumberTable:
        line 473: 0
        line 474: 5
        line 475: 9
        line 477: 20
        line 479: 25
      LocalVariableTable:
        Start  Length  Slot  Name   Signature
            0      27     0  this   Lorg/apache/commons/lang3/text/StrTokenizer;
            0      27     1 input   Ljava/lang/String;
      StackMapTable: number_of_entries = 2
        frame_type = 20 /* same */
        frame_type = 4 /* same */

  public org.apache.commons.lang3.text.StrTokenizer reset(char[]);
    descriptor: ([C)Lorg/apache/commons/lang3/text/StrTokenizer;
    flags: (0x0001) ACC_PUBLIC
    Code:
      stack=2, locals=2, args_size=2
         0: aload_0
         1: invokevirtual #43                 // Method reset:()Lorg/apache/commons/lang3/text/StrTokenizer;
         4: pop
         5: aload_0
         6: aload_1
         7: invokestatic  #28                 // Method org/apache/commons/lang3/ArrayUtils.clone:([C)[C
        10: putfield      #18                 // Field chars:[C
        13: aload_0
        14: areturn
      LineNumberTable:
        line 491: 0
        line 492: 5
        line 493: 13
      LocalVariableTable:
        Start  Length  Slot  Name   Signature
            0      15     0  this   Lorg/apache/commons/lang3/text/StrTokenizer;
            0      15     1 input   [C

  public boolean hasNext();
    descriptor: ()Z
    flags: (0x0001) ACC_PUBLIC
    Code:
      stack=2, locals=1, args_size=1
         0: aload_0
         1: invokespecial #32                 // Method checkTokenized:()V
         4: aload_0
         5: getfield      #35                 // Field tokenPos:I
         8: aload_0
         9: getfield      #33                 // Field tokens:[Ljava/lang/String;
        12: arraylength
        13: if_icmpge     20
        16: iconst_1
        17: goto          21
        20: iconst_0
        21: ireturn
      LineNumberTable:
        line 505: 0
        line 506: 4
      LocalVariableTable:
        Start  Length  Slot  Name   Signature
            0      22     0  this   Lorg/apache/commons/lang3/text/StrTokenizer;
      StackMapTable: number_of_entries = 2
        frame_type = 20 /* same */
        frame_type = 64 /* same_locals_1_stack_item */
          stack = [ int ]

  public java.lang.String next();
    descriptor: ()Ljava/lang/String;
    flags: (0x0001) ACC_PUBLIC
    Code:
      stack=5, locals=1, args_size=1
         0: aload_0
         1: invokevirtual #34                 // Method hasNext:()Z
         4: ifeq          24
         7: aload_0
         8: getfield      #33                 // Field tokens:[Ljava/lang/String;
        11: aload_0
        12: dup
        13: getfield      #35                 // Field tokenPos:I
        16: dup_x1
        17: iconst_1
        18: iadd
        19: putfield      #35                 // Field tokenPos:I
        22: aaload
        23: areturn
        24: new           #44                 // class java/util/NoSuchElementException
        27: dup
        28: invokespecial #45                 // Method java/util/NoSuchElementException."<init>":()V
        31: athrow
      LineNumberTable:
        line 517: 0
        line 518: 7
        line 520: 24
      LocalVariableTable:
        Start  Length  Slot  Name   Signature
            0      32     0  this   Lorg/apache/commons/lang3/text/StrTokenizer;
      StackMapTable: number_of_entries = 1
        frame_type = 24 /* same */

  public int nextIndex();
    descriptor: ()I
    flags: (0x0001) ACC_PUBLIC
    Code:
      stack=1, locals=1, args_size=1
         0: aload_0
         1: getfield      #35                 // Field tokenPos:I
         4: ireturn
      LineNumberTable:
        line 530: 0
      LocalVariableTable:
        Start  Length  Slot  Name   Signature
            0       5     0  this   Lorg/apache/commons/lang3/text/StrTokenizer;

  public boolean hasPrevious();
    descriptor: ()Z
    flags: (0x0001) ACC_PUBLIC
    Code:
      stack=1, locals=1, args_size=1
         0: aload_0
         1: invokespecial #32                 // Method checkTokenized:()V
         4: aload_0
         5: getfield      #35                 // Field tokenPos:I
         8: ifle          15
        11: iconst_1
        12: goto          16
        15: iconst_0
        16: ireturn
      LineNumberTable:
        line 540: 0
        line 541: 4
      LocalVariableTable:
        Start  Length  Slot  Name   Signature
            0      17     0  this   Lorg/apache/commons/lang3/text/StrTokenizer;
      StackMapTable: number_of_entries = 2
        frame_type = 15 /* same */
        frame_type = 64 /* same_locals_1_stack_item */
          stack = [ int ]

  public java.lang.String previous();
    descriptor: ()Ljava/lang/String;
    flags: (0x0001) ACC_PUBLIC
    Code:
      stack=4, locals=1, args_size=1
         0: aload_0
         1: invokevirtual #36                 // Method hasPrevious:()Z
         4: ifeq          24
         7: aload_0
         8: getfield      #33                 // Field tokens:[Ljava/lang/String;
        11: aload_0
        12: dup
        13: getfield      #35                 // Field tokenPos:I
        16: iconst_1
        17: isub
        18: dup_x1
        19: putfield      #35                 // Field tokenPos:I
        22: aaload
        23: areturn
        24: new           #44                 // class java/util/NoSuchElementException
        27: dup
        28: invokespecial #45                 // Method java/util/NoSuchElementException."<init>":()V
        31: athrow
      LineNumberTable:
        line 551: 0
        line 552: 7
        line 554: 24
      LocalVariableTable:
        Start  Length  Slot  Name   Signature
            0      32     0  this   Lorg/apache/commons/lang3/text/StrTokenizer;
      StackMapTable: number_of_entries = 1
        frame_type = 24 /* same */

  public int previousIndex();
    descriptor: ()I
    flags: (0x0001) ACC_PUBLIC
    Code:
      stack=2, locals=1, args_size=1
         0: aload_0
         1: getfield      #35                 // Field tokenPos:I
         4: iconst_1
         5: isub
         6: ireturn
      LineNumberTable:
        line 564: 0
      LocalVariableTable:
        Start  Length  Slot  Name   Signature
            0       7     0  this   Lorg/apache/commons/lang3/text/StrTokenizer;

  public void remove();
    descriptor: ()V
    flags: (0x0001) ACC_PUBLIC
    Code:
      stack=3, locals=1, args_size=1
         0: new           #46                 // class java/lang/UnsupportedOperationException
         3: dup
         4: ldc           #47                 // String remove() is unsupported
         6: invokespecial #48                 // Method java/lang/UnsupportedOperationException."<init>":(Ljava/lang/String;)V
         9: athrow
      LineNumberTable:
        line 574: 0
      LocalVariableTable:
        Start  Length  Slot  Name   Signature
            0      10     0  this   Lorg/apache/commons/lang3/text/StrTokenizer;

  public void set(java.lang.String);
    descriptor: (Ljava/lang/String;)V
    flags: (0x0001) ACC_PUBLIC
    Code:
      stack=3, locals=2, args_size=2
         0: new           #46                 // class java/lang/UnsupportedOperationException
         3: dup
         4: ldc           #49                 // String set() is unsupported
         6: invokespecial #48                 // Method java/lang/UnsupportedOperationException."<init>":(Ljava/lang/String;)V
         9: athrow
      LineNumberTable:
        line 584: 0
      LocalVariableTable:
        Start  Length  Slot  Name   Signature
            0      10     0  this   Lorg/apache/commons/lang3/text/StrTokenizer;
            0      10     1   obj   Ljava/lang/String;

  public void add(java.lang.String);
    descriptor: (Ljava/lang/String;)V
    flags: (0x0001) ACC_PUBLIC
    Code:
      stack=3, locals=2, args_size=2
         0: new           #46                 // class java/lang/UnsupportedOperationException
         3: dup
         4: ldc           #50                 // String add() is unsupported
         6: invokespecial #48                 // Method java/lang/UnsupportedOperationException."<init>":(Ljava/lang/String;)V
         9: athrow
      LineNumberTable:
        line 594: 0
      LocalVariableTable:
        Start  Length  Slot  Name   Signature
            0      10     0  this   Lorg/apache/commons/lang3/text/StrTokenizer;
            0      10     1   obj   Ljava/lang/String;

  private void checkTokenized();
    descriptor: ()V
    flags: (0x0002) ACC_PRIVATE
    Code:
      stack=4, locals=2, args_size=1
         0: aload_0
         1: getfield      #33                 // Field tokens:[Ljava/lang/String;
         4: ifnonnull     84
         7: aload_0
         8: getfield      #18                 // Field chars:[C
        11: ifnonnull     47
        14: aload_0
        15: aconst_null
        16: iconst_0
        17: iconst_0
        18: invokevirtual #51                 // Method tokenize:([CII)Ljava/util/List;
        21: astore_1
        22: aload_0
        23: aload_1
        24: aload_1
        25: invokeinterface #52,  1           // InterfaceMethod java/util/List.size:()I
        30: anewarray     #53                 // class java/lang/String
        33: invokeinterface #54,  2           // InterfaceMethod java/util/List.toArray:([Ljava/lang/Object;)[Ljava/lang/Object;
        38: checkcast     #38                 // class "[Ljava/lang/String;"
        41: putfield      #33                 // Field tokens:[Ljava/lang/String;
        44: goto          84
        47: aload_0
        48: aload_0
        49: getfield      #18                 // Field chars:[C
        52: iconst_0
        53: aload_0
        54: getfield      #18                 // Field chars:[C
        57: arraylength
        58: invokevirtual #51                 // Method tokenize:([CII)Ljava/util/List;
        61: astore_1
        62: aload_0
        63: aload_1
        64: aload_1
        65: invokeinterface #52,  1           // InterfaceMethod java/util/List.size:()I
        70: anewarray     #53                 // class java/lang/String
        73: invokeinterface #54,  2           // InterfaceMethod java/util/List.toArray:([Ljava/lang/Object;)[Ljava/lang/Object;
        78: checkcast     #38                 // class "[Ljava/lang/String;"
        81: putfield      #33                 // Field tokens:[Ljava/lang/String;
        84: return
      LineNumberTable:
        line 603: 0
        line 604: 7
        line 606: 14
        line 607: 22
        line 608: 44
        line 609: 47
        line 610: 62
        line 613: 84
      LocalVariableTable:
        Start  Length  Slot  Name   Signature
           22      22     1 split   Ljava/util/List;
           62      22     1 split   Ljava/util/List;
            0      85     0  this   Lorg/apache/commons/lang3/text/StrTokenizer;
      LocalVariableTypeTable:
        Start  Length  Slot  Name   Signature
           22      22     1 split   Ljava/util/List<Ljava/lang/String;>;
           62      22     1 split   Ljava/util/List<Ljava/lang/String;>;
      StackMapTable: number_of_entries = 2
        frame_type = 47 /* same */
        frame_type = 36 /* same */

  protected java.util.List<java.lang.String> tokenize(char[], int, int);
    descriptor: ([CII)Ljava/util/List;
    flags: (0x0004) ACC_PROTECTED
    Code:
      stack=6, locals=7, args_size=4
         0: aload_1
         1: ifnull        8
         4: iload_3
         5: ifne          12
         8: invokestatic  #55                 // Method java/util/Collections.emptyList:()Ljava/util/List;
        11: areturn
        12: new           #56                 // class org/apache/commons/lang3/text/StrBuilder
        15: dup
        16: invokespecial #57                 // Method org/apache/commons/lang3/text/StrBuilder."<init>":()V
        19: astore        4
        21: new           #39                 // class java/util/ArrayList
        24: dup
        25: invokespecial #58                 // Method java/util/ArrayList."<init>":()V
        28: astore        5
        30: iload_2
        31: istore        6
        33: iload         6
        35: iflt          75
        38: iload         6
        40: iload_3
        41: if_icmpge     75
        44: aload_0
        45: aload_1
        46: iload         6
        48: iload_3
        49: aload         4
        51: aload         5
        53: invokespecial #59                 // Method readNextToken:([CIILorg/apache/commons/lang3/text/StrBuilder;Ljava/util/List;)I
        56: istore        6
        58: iload         6
        60: iload_3
        61: if_icmplt     33
        64: aload_0
        65: aload         5
        67: ldc           #61                 // String
        69: invokespecial #62                 // Method addToken:(Ljava/util/List;Ljava/lang/String;)V
        72: goto          33
        75: aload         5
        77: areturn
      LineNumberTable:
        line 636: 0
        line 637: 8
        line 639: 12
        line 640: 21
        line 641: 30
        line 644: 33
        line 646: 44
        line 649: 58
        line 650: 64
        line 653: 75
      LocalVariableTable:
        Start  Length  Slot  Name   Signature
            0      78     0  this   Lorg/apache/commons/lang3/text/StrTokenizer;
            0      78     1 srcChars   [C
            0      78     2 offset   I
            0      78     3 count   I
           21      57     4   buf   Lorg/apache/commons/lang3/text/StrBuilder;
           30      48     5 tokenList   Ljava/util/List;
           33      45     6   pos   I
      LocalVariableTypeTable:
        Start  Length  Slot  Name   Signature
           30      48     5 tokenList   Ljava/util/List<Ljava/lang/String;>;
      StackMapTable: number_of_entries = 4
        frame_type = 8 /* same */
        frame_type = 3 /* same */
        frame_type = 254 /* append */
          offset_delta = 20
          locals = [ class org/apache/commons/lang3/text/StrBuilder, class java/util/List, int ]
        frame_type = 41 /* same */
    Signature: #200                         // ([CII)Ljava/util/List<Ljava/lang/String;>;

  private void addToken(java.util.List<java.lang.String>, java.lang.String);
    descriptor: (Ljava/util/List;Ljava/lang/String;)V
    flags: (0x0002) ACC_PRIVATE
    Code:
      stack=2, locals=3, args_size=3
         0: aload_2
         1: invokestatic  #63                 // Method org/apache/commons/lang3/StringUtils.isEmpty:(Ljava/lang/CharSequence;)Z
         4: ifeq          24
         7: aload_0
         8: invokevirtual #64                 // Method isIgnoreEmptyTokens:()Z
        11: ifeq          15
        14: return
        15: aload_0
        16: invokevirtual #65                 // Method isEmptyTokenAsNull:()Z
        19: ifeq          24
        22: aconst_null
        23: astore_2
        24: aload_1
        25: aload_2
        26: invokeinterface #66,  2           // InterfaceMethod java/util/List.add:(Ljava/lang/Object;)Z
        31: pop
        32: return
      LineNumberTable:
        line 663: 0
        line 664: 7
        line 665: 14
        line 667: 15
        line 668: 22
        line 671: 24
        line 672: 32
      LocalVariableTable:
        Start  Length  Slot  Name   Signature
            0      33     0  this   Lorg/apache/commons/lang3/text/StrTokenizer;
            0      33     1  list   Ljava/util/List;
            0      33     2   tok   Ljava/lang/String;
      LocalVariableTypeTable:
        Start  Length  Slot  Name   Signature
            0      33     1  list   Ljava/util/List<Ljava/lang/String;>;
      StackMapTable: number_of_entries = 2
        frame_type = 15 /* same */
        frame_type = 8 /* same */
    Signature: #203                         // (Ljava/util/List<Ljava/lang/String;>;Ljava/lang/String;)V

  private int readNextToken(char[], int, int, org.apache.commons.lang3.text.StrBuilder, java.util.List<java.lang.String>);
    descriptor: ([CIILorg/apache/commons/lang3/text/StrBuilder;Ljava/util/List;)I
    flags: (0x0002) ACC_PRIVATE
    Code:
      stack=8, locals=8, args_size=6
         0: iload_2
         1: iload_3
         2: if_icmpge     76
         5: aload_0
         6: invokevirtual #67                 // Method getIgnoredMatcher:()Lorg/apache/commons/lang3/text/StrMatcher;
         9: aload_1
        10: iload_2
        11: iload_2
        12: iload_3
        13: invokevirtual #68                 // Method org/apache/commons/lang3/text/StrMatcher.isMatch:([CIII)I
        16: aload_0
        17: invokevirtual #69                 // Method getTrimmerMatcher:()Lorg/apache/commons/lang3/text/StrMatcher;
        20: aload_1
        21: iload_2
        22: iload_2
        23: iload_3
        24: invokevirtual #68                 // Method org/apache/commons/lang3/text/StrMatcher.isMatch:([CIII)I
        27: invokestatic  #70                 // Method java/lang/Math.max:(II)I
        30: istore        6
        32: iload         6
        34: ifeq          76
        37: aload_0
        38: invokevirtual #71                 // Method getDelimiterMatcher:()Lorg/apache/commons/lang3/text/StrMatcher;
        41: aload_1
        42: iload_2
        43: iload_2
        44: iload_3
        45: invokevirtual #68                 // Method org/apache/commons/lang3/text/StrMatcher.isMatch:([CIII)I
        48: ifgt          76
        51: aload_0
        52: invokevirtual #72                 // Method getQuoteMatcher:()Lorg/apache/commons/lang3/text/StrMatcher;
        55: aload_1
        56: iload_2
        57: iload_2
        58: iload_3
        59: invokevirtual #68                 // Method org/apache/commons/lang3/text/StrMatcher.isMatch:([CIII)I
        62: ifle          68
        65: goto          76
        68: iload_2
        69: iload         6
        71: iadd
        72: istore_2
        73: goto          0
        76: iload_2
        77: iload_3
        78: if_icmplt     91
        81: aload_0
        82: aload         5
        84: ldc           #61                 // String
        86: invokespecial #62                 // Method addToken:(Ljava/util/List;Ljava/lang/String;)V
        89: iconst_m1
        90: ireturn
        91: aload_0
        92: invokevirtual #71                 // Method getDelimiterMatcher:()Lorg/apache/commons/lang3/text/StrMatcher;
        95: aload_1
        96: iload_2
        97: iload_2
        98: iload_3
        99: invokevirtual #68                 // Method org/apache/commons/lang3/text/StrMatcher.isMatch:([CIII)I
       102: istore        6
       104: iload         6
       106: ifle          122
       109: aload_0
       110: aload         5
       112: ldc           #61                 // String
       114: invokespecial #62                 // Method addToken:(Ljava/util/List;Ljava/lang/String;)V
       117: iload_2
       118: iload         6
       120: iadd
       121: ireturn
       122: aload_0
       123: invokevirtual #72                 // Method getQuoteMatcher:()Lorg/apache/commons/lang3/text/StrMatcher;
       126: aload_1
       127: iload_2
       128: iload_2
       129: iload_3
       130: invokevirtual #68                 // Method org/apache/commons/lang3/text/StrMatcher.isMatch:([CIII)I
       133: istore        7
       135: iload         7
       137: ifle          158
       140: aload_0
       141: aload_1
       142: iload_2
       143: iload         7
       145: iadd
       146: iload_3
       147: aload         4
       149: aload         5
       151: iload_2
       152: iload         7
       154: invokespecial #73                 // Method readWithQuotes:([CIILorg/apache/commons/lang3/text/StrBuilder;Ljava/util/List;II)I
       157: ireturn
       158: aload_0
       159: aload_1
       160: iload_2
       161: iload_3
       162: aload         4
       164: aload         5
       166: iconst_0
       167: iconst_0
       168: invokespecial #73                 // Method readWithQuotes:([CIILorg/apache/commons/lang3/text/StrBuilder;Ljava/util/List;II)I
       171: ireturn
      LineNumberTable:
        line 688: 0
        line 689: 5
        line 690: 6
        line 691: 17
        line 689: 27
        line 692: 32
        line 693: 38
        line 694: 52
        line 695: 65
        line 697: 68
        line 698: 73
        line 701: 76
        line 702: 81
        line 703: 89
        line 707: 91
        line 708: 104
        line 709: 109
        line 710: 117
        line 714: 122
        line 715: 135
        line 716: 140
        line 718: 158
      LocalVariableTable:
        Start  Length  Slot  Name   Signature
           32      41     6 removeLen   I
            0     172     0  this   Lorg/apache/commons/lang3/text/StrTokenizer;
            0     172     1 srcChars   [C
            0     172     2 start   I
            0     172     3   len   I
            0     172     4 workArea   Lorg/apache/commons/lang3/text/StrBuilder;
            0     172     5 tokenList   Ljava/util/List;
          104      68     6 delimLen   I
          135      37     7 quoteLen   I
      LocalVariableTypeTable:
        Start  Length  Slot  Name   Signature
            0     172     5 tokenList   Ljava/util/List<Ljava/lang/String;>;
      StackMapTable: number_of_entries = 6
        frame_type = 0 /* same */
        frame_type = 252 /* append */
          offset_delta = 67
          locals = [ int ]
        frame_type = 250 /* chop */
          offset_delta = 7
        frame_type = 14 /* same */
        frame_type = 252 /* append */
          offset_delta = 30
          locals = [ int ]
        frame_type = 252 /* append */
          offset_delta = 35
          locals = [ int ]
    Signature: #212                         // ([CIILorg/apache/commons/lang3/text/StrBuilder;Ljava/util/List<Ljava/lang/String;>;)I

  private int readWithQuotes(char[], int, int, org.apache.commons.lang3.text.StrBuilder, java.util.List<java.lang.String>, int, int);
    descriptor: ([CIILorg/apache/commons/lang3/text/StrBuilder;Ljava/util/List;II)I
    flags: (0x0002) ACC_PRIVATE
    Code:
      stack=6, locals=14, args_size=8
         0: aload         4
         2: invokevirtual #74                 // Method org/apache/commons/lang3/text/StrBuilder.clear:()Lorg/apache/commons/lang3/text/StrBuilder;
         5: pop
         6: iload_2
         7: istore        8
         9: iload         7
        11: ifle          18
        14: iconst_1
        15: goto          19
        18: iconst_0
        19: istore        9
        21: iconst_0
        22: istore        10
        24: iload         8
        26: iload_3
        27: if_icmpge     298
        30: iload         9
        32: ifeq          134
        35: aload_0
        36: aload_1
        37: iload         8
        39: iload_3
        40: iload         6
        42: iload         7
        44: invokespecial #75                 // Method isQuote:([CIIII)Z
        47: ifeq          111
        50: aload_0
        51: aload_1
        52: iload         8
        54: iload         7
        56: iadd
        57: iload_3
        58: iload         6
        60: iload         7
        62: invokespecial #75                 // Method isQuote:([CIIII)Z
        65: ifeq          98
        68: aload         4
        70: aload_1
        71: iload         8
        73: iload         7
        75: invokevirtual #76                 // Method org/apache/commons/lang3/text/StrBuilder.append:([CII)Lorg/apache/commons/lang3/text/StrBuilder;
        78: pop
        79: iload         8
        81: iload         7
        83: iconst_2
        84: imul
        85: iadd
        86: istore        8
        88: aload         4
        90: invokevirtual #77                 // Method org/apache/commons/lang3/text/StrBuilder.size:()I
        93: istore        10
        95: goto          24
        98: iconst_0
        99: istore        9
       101: iload         8
       103: iload         7
       105: iadd
       106: istore        8
       108: goto          24
       111: aload         4
       113: aload_1
       114: iload         8
       116: iinc          8, 1
       119: caload
       120: invokevirtual #78                 // Method org/apache/commons/lang3/text/StrBuilder.append:(C)Lorg/apache/commons/lang3/text/StrBuilder;
       123: pop
       124: aload         4
       126: invokevirtual #77                 // Method org/apache/commons/lang3/text/StrBuilder.size:()I
       129: istore        10
       131: goto          24
       134: aload_0
       135: invokevirtual #71                 // Method getDelimiterMatcher:()Lorg/apache/commons/lang3/text/StrMatcher;
       138: aload_1
       139: iload         8
       141: iload_2
       142: iload_3
       143: invokevirtual #68                 // Method org/apache/commons/lang3/text/StrMatcher.isMatch:([CIII)I
       146: istore        11
       148: iload         11
       150: ifle          173
       153: aload_0
       154: aload         5
       156: aload         4
       158: iconst_0
       159: iload         10
       161: invokevirtual #79                 // Method org/apache/commons/lang3/text/StrBuilder.substring:(II)Ljava/lang/String;
       164: invokespecial #62                 // Method addToken:(Ljava/util/List;Ljava/lang/String;)V
       167: iload         8
       169: iload         11
       171: iadd
       172: ireturn
       173: iload         7
       175: ifle          206
       178: aload_0
       179: aload_1
       180: iload         8
       182: iload_3
       183: iload         6
       185: iload         7
       187: invokespecial #75                 // Method isQuote:([CIIII)Z
       190: ifeq          206
       193: iconst_1
       194: istore        9
       196: iload         8
       198: iload         7
       200: iadd
       201: istore        8
       203: goto          24
       206: aload_0
       207: invokevirtual #67                 // Method getIgnoredMatcher:()Lorg/apache/commons/lang3/text/StrMatcher;
       210: aload_1
       211: iload         8
       213: iload_2
       214: iload_3
       215: invokevirtual #68                 // Method org/apache/commons/lang3/text/StrMatcher.isMatch:([CIII)I
       218: istore        12
       220: iload         12
       222: ifle          235
       225: iload         8
       227: iload         12
       229: iadd
       230: istore        8
       232: goto          24
       235: aload_0
       236: invokevirtual #69                 // Method getTrimmerMatcher:()Lorg/apache/commons/lang3/text/StrMatcher;
       239: aload_1
       240: iload         8
       242: iload_2
       243: iload_3
       244: invokevirtual #68                 // Method org/apache/commons/lang3/text/StrMatcher.isMatch:([CIII)I
       247: istore        13
       249: iload         13
       251: ifle          275
       254: aload         4
       256: aload_1
       257: iload         8
       259: iload         13
       261: invokevirtual #76                 // Method org/apache/commons/lang3/text/StrBuilder.append:([CII)Lorg/apache/commons/lang3/text/StrBuilder;
       264: pop
       265: iload         8
       267: iload         13
       269: iadd
       270: istore        8
       272: goto          24
       275: aload         4
       277: aload_1
       278: iload         8
       280: iinc          8, 1
       283: caload
       284: invokevirtual #78                 // Method org/apache/commons/lang3/text/StrBuilder.append:(C)Lorg/apache/commons/lang3/text/StrBuilder;
       287: pop
       288: aload         4
       290: invokevirtual #77                 // Method org/apache/commons/lang3/text/StrBuilder.size:()I
       293: istore        10
       295: goto          24
       298: aload_0
       299: aload         5
       301: aload         4
       303: iconst_0
       304: iload         10
       306: invokevirtual #79                 // Method org/apache/commons/lang3/text/StrBuilder.substring:(II)Ljava/lang/String;
       309: invokespecial #62                 // Method addToken:(Ljava/util/List;Ljava/lang/String;)V
       312: iconst_m1
       313: ireturn
      LineNumberTable:
        line 739: 0
        line 740: 6
        line 741: 9
        line 742: 21
        line 744: 24
        line 748: 30
        line 755: 35
        line 756: 50
        line 758: 68
        line 759: 79
        line 760: 88
        line 761: 95
        line 765: 98
        line 766: 101
        line 767: 108
        line 771: 111
        line 772: 124
        line 778: 134
        line 779: 148
        line 781: 153
        line 782: 167
        line 786: 173
        line 787: 193
        line 788: 196
        line 789: 203
        line 793: 206
        line 794: 220
        line 795: 225
        line 796: 232
        line 802: 235
        line 803: 249
        line 804: 254
        line 805: 265
        line 806: 272
        line 810: 275
        line 811: 288
        line 812: 295
        line 816: 298
        line 817: 312
      LocalVariableTable:
        Start  Length  Slot  Name   Signature
          148     147    11 delimLen   I
          220      75    12 ignoredLen   I
          249      46    13 trimmedLen   I
            0     314     0  this   Lorg/apache/commons/lang3/text/StrTokenizer;
            0     314     1 srcChars   [C
            0     314     2 start   I
            0     314     3   len   I
            0     314     4 workArea   Lorg/apache/commons/lang3/text/StrBuilder;
            0     314     5 tokenList   Ljava/util/List;
            0     314     6 quoteStart   I
            0     314     7 quoteLen   I
            9     305     8   pos   I
           21     293     9 quoting   Z
           24     290    10 trimStart   I
      LocalVariableTypeTable:
        Start  Length  Slot  Name   Signature
            0     314     5 tokenList   Ljava/util/List<Ljava/lang/String;>;
      StackMapTable: number_of_entries = 11
        frame_type = 252 /* append */
          offset_delta = 18
          locals = [ int ]
        frame_type = 64 /* same_locals_1_stack_item */
          stack = [ int ]
        frame_type = 253 /* append */
          offset_delta = 4
          locals = [ int, int ]
        frame_type = 251 /* same_frame_extended */
          offset_delta = 73
        frame_type = 12 /* same */
        frame_type = 22 /* same */
        frame_type = 252 /* append */
          offset_delta = 38
          locals = [ int ]
        frame_type = 32 /* same */
        frame_type = 252 /* append */
          offset_delta = 28
          locals = [ int ]
        frame_type = 252 /* append */
          offset_delta = 39
          locals = [ int ]
        frame_type = 248 /* chop */
          offset_delta = 22
    Signature: #220                         // ([CIILorg/apache/commons/lang3/text/StrBuilder;Ljava/util/List<Ljava/lang/String;>;II)I

  private boolean isQuote(char[], int, int, int, int);
    descriptor: ([CIIII)Z
    flags: (0x0002) ACC_PRIVATE
    Code:
      stack=4, locals=7, args_size=6
         0: iconst_0
         1: istore        6
         3: iload         6
         5: iload         5
         7: if_icmpge     42
        10: iload_2
        11: iload         6
        13: iadd
        14: iload_3
        15: if_icmpge     34
        18: aload_1
        19: iload_2
        20: iload         6
        22: iadd
        23: caload
        24: aload_1
        25: iload         4
        27: iload         6
        29: iadd
        30: caload
        31: if_icmpeq     36
        34: iconst_0
        35: ireturn
        36: iinc          6, 1
        39: goto          3
        42: iconst_1
        43: ireturn
      LineNumberTable:
        line 832: 0
        line 833: 10
        line 834: 34
        line 832: 36
        line 837: 42
      LocalVariableTable:
        Start  Length  Slot  Name   Signature
            3      39     6     i   I
            0      44     0  this   Lorg/apache/commons/lang3/text/StrTokenizer;
            0      44     1 srcChars   [C
            0      44     2   pos   I
            0      44     3   len   I
            0      44     4 quoteStart   I
            0      44     5 quoteLen   I
      StackMapTable: number_of_entries = 4
        frame_type = 252 /* append */
          offset_delta = 3
          locals = [ int ]
        frame_type = 30 /* same */
        frame_type = 1 /* same */
        frame_type = 250 /* chop */
          offset_delta = 5

  public org.apache.commons.lang3.text.StrMatcher getDelimiterMatcher();
    descriptor: ()Lorg/apache/commons/lang3/text/StrMatcher;
    flags: (0x0001) ACC_PUBLIC
    Code:
      stack=1, locals=1, args_size=1
         0: aload_0
         1: getfield      #11                 // Field delimMatcher:Lorg/apache/commons/lang3/text/StrMatcher;
         4: areturn
      LineNumberTable:
        line 848: 0
      LocalVariableTable:
        Start  Length  Slot  Name   Signature
            0       5     0  this   Lorg/apache/commons/lang3/text/StrTokenizer;

  public org.apache.commons.lang3.text.StrTokenizer setDelimiterMatcher(org.apache.commons.lang3.text.StrMatcher);
    descriptor: (Lorg/apache/commons/lang3/text/StrMatcher;)Lorg/apache/commons/lang3/text/StrTokenizer;
    flags: (0x0001) ACC_PUBLIC
    Code:
      stack=2, locals=2, args_size=2
         0: aload_1
         1: ifnonnull     14
         4: aload_0
         5: invokestatic  #12                 // Method org/apache/commons/lang3/text/StrMatcher.noneMatcher:()Lorg/apache/commons/lang3/text/StrMatcher;
         8: putfield      #11                 // Field delimMatcher:Lorg/apache/commons/lang3/text/StrMatcher;
        11: goto          19
        14: aload_0
        15: aload_1
        16: putfield      #11                 // Field delimMatcher:Lorg/apache/commons/lang3/text/StrMatcher;
        19: aload_0
        20: areturn
      LineNumberTable:
        line 860: 0
        line 861: 4
        line 863: 14
        line 865: 19
      LocalVariableTable:
        Start  Length  Slot  Name   Signature
            0      21     0  this   Lorg/apache/commons/lang3/text/StrTokenizer;
            0      21     1 delim   Lorg/apache/commons/lang3/text/StrMatcher;
      StackMapTable: number_of_entries = 2
        frame_type = 14 /* same */
        frame_type = 4 /* same */

  public org.apache.commons.lang3.text.StrTokenizer setDelimiterChar(char);
    descriptor: (C)Lorg/apache/commons/lang3/text/StrTokenizer;
    flags: (0x0001) ACC_PUBLIC
    Code:
      stack=2, locals=2, args_size=2
         0: aload_0
         1: iload_1
         2: invokestatic  #80                 // Method org/apache/commons/lang3/text/StrMatcher.charMatcher:(C)Lorg/apache/commons/lang3/text/StrMatcher;
         5: invokevirtual #23                 // Method setDelimiterMatcher:(Lorg/apache/commons/lang3/text/StrMatcher;)Lorg/apache/commons/lang3/text/StrTokenizer;
         8: areturn
      LineNumberTable:
        line 875: 0
      LocalVariableTable:
        Start  Length  Slot  Name   Signature
            0       9     0  this   Lorg/apache/commons/lang3/text/StrTokenizer;
            0       9     1 delim   C

  public org.apache.commons.lang3.text.StrTokenizer setDelimiterString(java.lang.String);
    descriptor: (Ljava/lang/String;)Lorg/apache/commons/lang3/text/StrTokenizer;
    flags: (0x0001) ACC_PUBLIC
    Code:
      stack=2, locals=2, args_size=2
         0: aload_0
         1: aload_1
         2: invokestatic  #81                 // Method org/apache/commons/lang3/text/StrMatcher.stringMatcher:(Ljava/lang/String;)Lorg/apache/commons/lang3/text/StrMatcher;
         5: invokevirtual #23                 // Method setDelimiterMatcher:(Lorg/apache/commons/lang3/text/StrMatcher;)Lorg/apache/commons/lang3/text/StrTokenizer;
         8: areturn
      LineNumberTable:
        line 885: 0
      LocalVariableTable:
        Start  Length  Slot  Name   Signature
            0       9     0  this   Lorg/apache/commons/lang3/text/StrTokenizer;
            0       9     1 delim   Ljava/lang/String;

  public org.apache.commons.lang3.text.StrMatcher getQuoteMatcher();
    descriptor: ()Lorg/apache/commons/lang3/text/StrMatcher;
    flags: (0x0001) ACC_PUBLIC
    Code:
      stack=1, locals=1, args_size=1
         0: aload_0
         1: getfield      #13                 // Field quoteMatcher:Lorg/apache/commons/lang3/text/StrMatcher;
         4: areturn
      LineNumberTable:
        line 900: 0
      LocalVariableTable:
        Start  Length  Slot  Name   Signature
            0       5     0  this   Lorg/apache/commons/lang3/text/StrTokenizer;

  public org.apache.commons.lang3.text.StrTokenizer setQuoteMatcher(org.apache.commons.lang3.text.StrMatcher);
    descriptor: (Lorg/apache/commons/lang3/text/StrMatcher;)Lorg/apache/commons/lang3/text/StrTokenizer;
    flags: (0x0001) ACC_PUBLIC
    Code:
      stack=2, locals=2, args_size=2
         0: aload_1
         1: ifnull        9
         4: aload_0
         5: aload_1
         6: putfield      #13                 // Field quoteMatcher:Lorg/apache/commons/lang3/text/StrMatcher;
         9: aload_0
        10: areturn
      LineNumberTable:
        line 913: 0
        line 914: 4
        line 916: 9
      LocalVariableTable:
        Start  Length  Slot  Name   Signature
            0      11     0  this   Lorg/apache/commons/lang3/text/StrTokenizer;
            0      11     1 quote   Lorg/apache/commons/lang3/text/StrMatcher;
      StackMapTable: number_of_entries = 1
        frame_type = 9 /* same */

  public org.apache.commons.lang3.text.StrTokenizer setQuoteChar(char);
    descriptor: (C)Lorg/apache/commons/lang3/text/StrTokenizer;
    flags: (0x0001) ACC_PUBLIC
    Code:
      stack=2, locals=2, args_size=2
         0: aload_0
         1: iload_1
         2: invokestatic  #80                 // Method org/apache/commons/lang3/text/StrMatcher.charMatcher:(C)Lorg/apache/commons/lang3/text/StrMatcher;
         5: invokevirtual #27                 // Method setQuoteMatcher:(Lorg/apache/commons/lang3/text/StrMatcher;)Lorg/apache/commons/lang3/text/StrTokenizer;
         8: areturn
      LineNumberTable:
        line 929: 0
      LocalVariableTable:
        Start  Length  Slot  Name   Signature
            0       9     0  this   Lorg/apache/commons/lang3/text/StrTokenizer;
            0       9     1 quote   C

  public org.apache.commons.lang3.text.StrMatcher getIgnoredMatcher();
    descriptor: ()Lorg/apache/commons/lang3/text/StrMatcher;
    flags: (0x0001) ACC_PUBLIC
    Code:
      stack=1, locals=1, args_size=1
         0: aload_0
         1: getfield      #14                 // Field ignoredMatcher:Lorg/apache/commons/lang3/text/StrMatcher;
         4: areturn
      LineNumberTable:
        line 944: 0
      LocalVariableTable:
        Start  Length  Slot  Name   Signature
            0       5     0  this   Lorg/apache/commons/lang3/text/StrTokenizer;

  public org.apache.commons.lang3.text.StrTokenizer setIgnoredMatcher(org.apache.commons.lang3.text.StrMatcher);
    descriptor: (Lorg/apache/commons/lang3/text/StrMatcher;)Lorg/apache/commons/lang3/text/StrTokenizer;
    flags: (0x0001) ACC_PUBLIC
    Code:
      stack=2, locals=2, args_size=2
         0: aload_1
         1: ifnull        9
         4: aload_0
         5: aload_1
         6: putfield      #14                 // Field ignoredMatcher:Lorg/apache/commons/lang3/text/StrMatcher;
         9: aload_0
        10: areturn
      LineNumberTable:
        line 957: 0
        line 958: 4
        line 960: 9
      LocalVariableTable:
        Start  Length  Slot  Name   Signature
            0      11     0  this   Lorg/apache/commons/lang3/text/StrTokenizer;
            0      11     1 ignored   Lorg/apache/commons/lang3/text/StrMatcher;
      StackMapTable: number_of_entries = 1
        frame_type = 9 /* same */

  public org.apache.commons.lang3.text.StrTokenizer setIgnoredChar(char);
    descriptor: (C)Lorg/apache/commons/lang3/text/StrTokenizer;
    flags: (0x0001) ACC_PUBLIC
    Code:
      stack=2, locals=2, args_size=2
         0: aload_0
         1: iload_1
         2: invokestatic  #80                 // Method org/apache/commons/lang3/text/StrMatcher.charMatcher:(C)Lorg/apache/commons/lang3/text/StrMatcher;
         5: invokevirtual #82                 // Method setIgnoredMatcher:(Lorg/apache/commons/lang3/text/StrMatcher;)Lorg/apache/commons/lang3/text/StrTokenizer;
         8: areturn
      LineNumberTable:
        line 973: 0
      LocalVariableTable:
        Start  Length  Slot  Name   Signature
            0       9     0  this   Lorg/apache/commons/lang3/text/StrTokenizer;
            0       9     1 ignored   C

  public org.apache.commons.lang3.text.StrMatcher getTrimmerMatcher();
    descriptor: ()Lorg/apache/commons/lang3/text/StrMatcher;
    flags: (0x0001) ACC_PUBLIC
    Code:
      stack=1, locals=1, args_size=1
         0: aload_0
         1: getfield      #15                 // Field trimmerMatcher:Lorg/apache/commons/lang3/text/StrMatcher;
         4: areturn
      LineNumberTable:
        line 988: 0
      LocalVariableTable:
        Start  Length  Slot  Name   Signature
            0       5     0  this   Lorg/apache/commons/lang3/text/StrTokenizer;

  public org.apache.commons.lang3.text.StrTokenizer setTrimmerMatcher(org.apache.commons.lang3.text.StrMatcher);
    descriptor: (Lorg/apache/commons/lang3/text/StrMatcher;)Lorg/apache/commons/lang3/text/StrTokenizer;
    flags: (0x0001) ACC_PUBLIC
    Code:
      stack=2, locals=2, args_size=2
         0: aload_1
         1: ifnull        9
         4: aload_0
         5: aload_1
         6: putfield      #15                 // Field trimmerMatcher:Lorg/apache/commons/lang3/text/StrMatcher;
         9: aload_0
        10: areturn
      LineNumberTable:
        line 1001: 0
        line 1002: 4
        line 1004: 9
      LocalVariableTable:
        Start  Length  Slot  Name   Signature
            0      11     0  this   Lorg/apache/commons/lang3/text/StrTokenizer;
            0      11     1 trimmer   Lorg/apache/commons/lang3/text/StrMatcher;
      StackMapTable: number_of_entries = 1
        frame_type = 9 /* same */

  public boolean isEmptyTokenAsNull();
    descriptor: ()Z
    flags: (0x0001) ACC_PUBLIC
    Code:
      stack=1, locals=1, args_size=1
         0: aload_0
         1: getfield      #16                 // Field emptyAsNull:Z
         4: ireturn
      LineNumberTable:
        line 1015: 0
      LocalVariableTable:
        Start  Length  Slot  Name   Signature
            0       5     0  this   Lorg/apache/commons/lang3/text/StrTokenizer;

  public org.apache.commons.lang3.text.StrTokenizer setEmptyTokenAsNull(boolean);
    descriptor: (Z)Lorg/apache/commons/lang3/text/StrTokenizer;
    flags: (0x0001) ACC_PUBLIC
    Code:
      stack=2, locals=2, args_size=2
         0: aload_0
         1: iload_1
         2: putfield      #16                 // Field emptyAsNull:Z
         5: aload_0
         6: areturn
      LineNumberTable:
        line 1026: 0
        line 1027: 5
      LocalVariableTable:
        Start  Length  Slot  Name   Signature
            0       7     0  this   Lorg/apache/commons/lang3/text/StrTokenizer;
            0       7     1 emptyAsNull   Z

  public boolean isIgnoreEmptyTokens();
    descriptor: ()Z
    flags: (0x0001) ACC_PUBLIC
    Code:
      stack=1, locals=1, args_size=1
         0: aload_0
         1: getfield      #17                 // Field ignoreEmptyTokens:Z
         4: ireturn
      LineNumberTable:
        line 1038: 0
      LocalVariableTable:
        Start  Length  Slot  Name   Signature
            0       5     0  this   Lorg/apache/commons/lang3/text/StrTokenizer;

  public org.apache.commons.lang3.text.StrTokenizer setIgnoreEmptyTokens(boolean);
    descriptor: (Z)Lorg/apache/commons/lang3/text/StrTokenizer;
    flags: (0x0001) ACC_PUBLIC
    Code:
      stack=2, locals=2, args_size=2
         0: aload_0
         1: iload_1
         2: putfield      #17                 // Field ignoreEmptyTokens:Z
         5: aload_0
         6: areturn
      LineNumberTable:
        line 1049: 0
        line 1050: 5
      LocalVariableTable:
        Start  Length  Slot  Name   Signature
            0       7     0  this   Lorg/apache/commons/lang3/text/StrTokenizer;
            0       7     1 ignoreEmptyTokens   Z

  public java.lang.String getContent();
    descriptor: ()Ljava/lang/String;
    flags: (0x0001) ACC_PUBLIC
    Code:
      stack=3, locals=1, args_size=1
         0: aload_0
         1: getfield      #18                 // Field chars:[C
         4: ifnonnull     9
         7: aconst_null
         8: areturn
         9: new           #53                 // class java/lang/String
        12: dup
        13: aload_0
        14: getfield      #18                 // Field chars:[C
        17: invokespecial #83                 // Method java/lang/String."<init>":([C)V
        20: areturn
      LineNumberTable:
        line 1060: 0
        line 1061: 7
        line 1063: 9
      LocalVariableTable:
        Start  Length  Slot  Name   Signature
            0      21     0  this   Lorg/apache/commons/lang3/text/StrTokenizer;
      StackMapTable: number_of_entries = 1
        frame_type = 9 /* same */

  public java.lang.Object clone();
    descriptor: ()Ljava/lang/Object;
    flags: (0x0001) ACC_PUBLIC
    Code:
      stack=1, locals=2, args_size=1
         0: aload_0
         1: invokevirtual #84                 // Method cloneReset:()Ljava/lang/Object;
         4: areturn
         5: astore_1
         6: aconst_null
         7: areturn
      Exception table:
         from    to  target type
             0     4     5   Class java/lang/CloneNotSupportedException
      LineNumberTable:
        line 1077: 0
        line 1078: 5
        line 1079: 6
      LocalVariableTable:
        Start  Length  Slot  Name   Signature
            6       2     1    ex   Ljava/lang/CloneNotSupportedException;
            0       8     0  this   Lorg/apache/commons/lang3/text/StrTokenizer;
      StackMapTable: number_of_entries = 1
        frame_type = 69 /* same_locals_1_stack_item */
          stack = [ class java/lang/CloneNotSupportedException ]

  java.lang.Object cloneReset() throws java.lang.CloneNotSupportedException;
    descriptor: ()Ljava/lang/Object;
    flags: (0x0000)
    Code:
      stack=2, locals=2, args_size=1
         0: aload_0
         1: invokespecial #86                 // Method java/lang/Object.clone:()Ljava/lang/Object;
         4: checkcast     #3                  // class org/apache/commons/lang3/text/StrTokenizer
         7: astore_1
         8: aload_1
         9: getfield      #18                 // Field chars:[C
        12: ifnull        29
        15: aload_1
        16: aload_1
        17: getfield      #18                 // Field chars:[C
        20: invokevirtual #87                 // Method "[C".clone:()Ljava/lang/Object;
        23: checkcast     #88                 // class "[C"
        26: putfield      #18                 // Field chars:[C
        29: aload_1
        30: invokevirtual #43                 // Method reset:()Lorg/apache/commons/lang3/text/StrTokenizer;
        33: pop
        34: aload_1
        35: areturn
      LineNumberTable:
        line 1092: 0
        line 1093: 8
        line 1094: 15
        line 1096: 29
        line 1097: 34
      LocalVariableTable:
        Start  Length  Slot  Name   Signature
            0      36     0  this   Lorg/apache/commons/lang3/text/StrTokenizer;
            8      28     1 cloned   Lorg/apache/commons/lang3/text/StrTokenizer;
      StackMapTable: number_of_entries = 1
        frame_type = 252 /* append */
          offset_delta = 29
          locals = [ class org/apache/commons/lang3/text/StrTokenizer ]
    Exceptions:
      throws java.lang.CloneNotSupportedException

  public java.lang.String toString();
    descriptor: ()Ljava/lang/String;
    flags: (0x0001) ACC_PUBLIC
    Code:
      stack=2, locals=1, args_size=1
         0: aload_0
         1: getfield      #33                 // Field tokens:[Ljava/lang/String;
         4: ifnonnull     10
         7: ldc           #89                 // String StrTokenizer[not tokenized yet]
         9: areturn
        10: new           #90                 // class java/lang/StringBuilder
        13: dup
        14: invokespecial #91                 // Method java/lang/StringBuilder."<init>":()V
        17: ldc           #92                 // String StrTokenizer
        19: invokevirtual #93                 // Method java/lang/StringBuilder.append:(Ljava/lang/String;)Ljava/lang/StringBuilder;
        22: aload_0
        23: invokevirtual #94                 // Method getTokenList:()Ljava/util/List;
        26: invokevirtual #95                 // Method java/lang/StringBuilder.append:(Ljava/lang/Object;)Ljava/lang/StringBuilder;
        29: invokevirtual #96                 // Method java/lang/StringBuilder.toString:()Ljava/lang/String;
        32: areturn
      LineNumberTable:
        line 1108: 0
        line 1109: 7
        line 1111: 10
      LocalVariableTable:
        Start  Length  Slot  Name   Signature
            0      33     0  this   Lorg/apache/commons/lang3/text/StrTokenizer;
      StackMapTable: number_of_entries = 1
        frame_type = 10 /* same */

  public void add(java.lang.Object);
    descriptor: (Ljava/lang/Object;)V
    flags: (0x1041) ACC_PUBLIC, ACC_BRIDGE, ACC_SYNTHETIC
    Code:
      stack=2, locals=2, args_size=2
         0: aload_0
         1: aload_1
         2: checkcast     #53                 // class java/lang/String
         5: invokevirtual #97                 // Method add:(Ljava/lang/String;)V
         8: return
      LineNumberTable:
        line 89: 0
      LocalVariableTable:
        Start  Length  Slot  Name   Signature
            0       9     0  this   Lorg/apache/commons/lang3/text/StrTokenizer;

  public void set(java.lang.Object);
    descriptor: (Ljava/lang/Object;)V
    flags: (0x1041) ACC_PUBLIC, ACC_BRIDGE, ACC_SYNTHETIC
    Code:
      stack=2, locals=2, args_size=2
         0: aload_0
         1: aload_1
         2: checkcast     #53                 // class java/lang/String
         5: invokevirtual #98                 // Method set:(Ljava/lang/String;)V
         8: return
      LineNumberTable:
        line 89: 0
      LocalVariableTable:
        Start  Length  Slot  Name   Signature
            0       9     0  this   Lorg/apache/commons/lang3/text/StrTokenizer;

  public java.lang.Object previous();
    descriptor: ()Ljava/lang/Object;
    flags: (0x1041) ACC_PUBLIC, ACC_BRIDGE, ACC_SYNTHETIC
    Code:
      stack=1, locals=1, args_size=1
         0: aload_0
         1: invokevirtual #99                 // Method previous:()Ljava/lang/String;
         4: areturn
      LineNumberTable:
        line 89: 0
      LocalVariableTable:
        Start  Length  Slot  Name   Signature
            0       5     0  this   Lorg/apache/commons/lang3/text/StrTokenizer;

  public java.lang.Object next();
    descriptor: ()Ljava/lang/Object;
    flags: (0x1041) ACC_PUBLIC, ACC_BRIDGE, ACC_SYNTHETIC
    Code:
      stack=1, locals=1, args_size=1
         0: aload_0
         1: invokevirtual #100                // Method next:()Ljava/lang/String;
         4: areturn
      LineNumberTable:
        line 89: 0
      LocalVariableTable:
        Start  Length  Slot  Name   Signature
            0       5     0  this   Lorg/apache/commons/lang3/text/StrTokenizer;

  static {};
    descriptor: ()V
    flags: (0x0008) ACC_STATIC
    Code:
      stack=2, locals=0, args_size=0
         0: new           #3                  // class org/apache/commons/lang3/text/StrTokenizer
         3: dup
         4: invokespecial #101                // Method "<init>":()V
         7: putstatic     #1                  // Field CSV_TOKENIZER_PROTOTYPE:Lorg/apache/commons/lang3/text/StrTokenizer;
        10: getstatic     #1                  // Field CSV_TOKENIZER_PROTOTYPE:Lorg/apache/commons/lang3/text/StrTokenizer;
        13: invokestatic  #102                // Method org/apache/commons/lang3/text/StrMatcher.commaMatcher:()Lorg/apache/commons/lang3/text/StrMatcher;
        16: invokevirtual #23                 // Method setDelimiterMatcher:(Lorg/apache/commons/lang3/text/StrMatcher;)Lorg/apache/commons/lang3/text/StrTokenizer;
        19: pop
        20: getstatic     #1                  // Field CSV_TOKENIZER_PROTOTYPE:Lorg/apache/commons/lang3/text/StrTokenizer;
        23: invokestatic  #103                // Method org/apache/commons/lang3/text/StrMatcher.doubleQuoteMatcher:()Lorg/apache/commons/lang3/text/StrMatcher;
        26: invokevirtual #27                 // Method setQuoteMatcher:(Lorg/apache/commons/lang3/text/StrMatcher;)Lorg/apache/commons/lang3/text/StrTokenizer;
        29: pop
        30: getstatic     #1                  // Field CSV_TOKENIZER_PROTOTYPE:Lorg/apache/commons/lang3/text/StrTokenizer;
        33: invokestatic  #12                 // Method org/apache/commons/lang3/text/StrMatcher.noneMatcher:()Lorg/apache/commons/lang3/text/StrMatcher;
        36: invokevirtual #82                 // Method setIgnoredMatcher:(Lorg/apache/commons/lang3/text/StrMatcher;)Lorg/apache/commons/lang3/text/StrTokenizer;
        39: pop
        40: getstatic     #1                  // Field CSV_TOKENIZER_PROTOTYPE:Lorg/apache/commons/lang3/text/StrTokenizer;
        43: invokestatic  #104                // Method org/apache/commons/lang3/text/StrMatcher.trimMatcher:()Lorg/apache/commons/lang3/text/StrMatcher;
        46: invokevirtual #105                // Method setTrimmerMatcher:(Lorg/apache/commons/lang3/text/StrMatcher;)Lorg/apache/commons/lang3/text/StrTokenizer;
        49: pop
        50: getstatic     #1                  // Field CSV_TOKENIZER_PROTOTYPE:Lorg/apache/commons/lang3/text/StrTokenizer;
        53: iconst_0
        54: invokevirtual #106                // Method setEmptyTokenAsNull:(Z)Lorg/apache/commons/lang3/text/StrTokenizer;
        57: pop
        58: getstatic     #1                  // Field CSV_TOKENIZER_PROTOTYPE:Lorg/apache/commons/lang3/text/StrTokenizer;
        61: iconst_0
        62: invokevirtual #107                // Method setIgnoreEmptyTokens:(Z)Lorg/apache/commons/lang3/text/StrTokenizer;
        65: pop
        66: new           #3                  // class org/apache/commons/lang3/text/StrTokenizer
        69: dup
        70: invokespecial #101                // Method "<init>":()V
        73: putstatic     #7                  // Field TSV_TOKENIZER_PROTOTYPE:Lorg/apache/commons/lang3/text/StrTokenizer;
        76: getstatic     #7                  // Field TSV_TOKENIZER_PROTOTYPE:Lorg/apache/commons/lang3/text/StrTokenizer;
        79: invokestatic  #108                // Method org/apache/commons/lang3/text/StrMatcher.tabMatcher:()Lorg/apache/commons/lang3/text/StrMatcher;
        82: invokevirtual #23                 // Method setDelimiterMatcher:(Lorg/apache/commons/lang3/text/StrMatcher;)Lorg/apache/commons/lang3/text/StrTokenizer;
        85: pop
        86: getstatic     #7                  // Field TSV_TOKENIZER_PROTOTYPE:Lorg/apache/commons/lang3/text/StrTokenizer;
        89: invokestatic  #103                // Method org/apache/commons/lang3/text/StrMatcher.doubleQuoteMatcher:()Lorg/apache/commons/lang3/text/StrMatcher;
        92: invokevirtual #27                 // Method setQuoteMatcher:(Lorg/apache/commons/lang3/text/StrMatcher;)Lorg/apache/commons/lang3/text/StrTokenizer;
        95: pop
        96: getstatic     #7                  // Field TSV_TOKENIZER_PROTOTYPE:Lorg/apache/commons/lang3/text/StrTokenizer;
        99: invokestatic  #12                 // Method org/apache/commons/lang3/text/StrMatcher.noneMatcher:()Lorg/apache/commons/lang3/text/StrMatcher;
       102: invokevirtual #82                 // Method setIgnoredMatcher:(Lorg/apache/commons/lang3/text/StrMatcher;)Lorg/apache/commons/lang3/text/StrTokenizer;
       105: pop
       106: getstatic     #7                  // Field TSV_TOKENIZER_PROTOTYPE:Lorg/apache/commons/lang3/text/StrTokenizer;
       109: invokestatic  #104                // Method org/apache/commons/lang3/text/StrMatcher.trimMatcher:()Lorg/apache/commons/lang3/text/StrMatcher;
       112: invokevirtual #105                // Method setTrimmerMatcher:(Lorg/apache/commons/lang3/text/StrMatcher;)Lorg/apache/commons/lang3/text/StrTokenizer;
       115: pop
       116: getstatic     #7                  // Field TSV_TOKENIZER_PROTOTYPE:Lorg/apache/commons/lang3/text/StrTokenizer;
       119: iconst_0
       120: invokevirtual #106                // Method setEmptyTokenAsNull:(Z)Lorg/apache/commons/lang3/text/StrTokenizer;
       123: pop
       124: getstatic     #7                  // Field TSV_TOKENIZER_PROTOTYPE:Lorg/apache/commons/lang3/text/StrTokenizer;
       127: iconst_0
       128: invokevirtual #107                // Method setIgnoreEmptyTokens:(Z)Lorg/apache/commons/lang3/text/StrTokenizer;
       131: pop
       132: return
      LineNumberTable:
        line 95: 0
        line 96: 10
        line 97: 20
        line 98: 30
        line 99: 40
        line 100: 50
        line 101: 58
        line 103: 66
        line 104: 76
        line 105: 86
        line 106: 96
        line 107: 106
        line 108: 116
        line 109: 124
        line 110: 132
}
Signature: #257                         // Ljava/lang/Object;Ljava/util/ListIterator<Ljava/lang/String;>;Ljava/lang/Cloneable;
SourceFile: "StrTokenizer.java"
Deprecated: true
RuntimeVisibleAnnotations:
  0: #262()
    java.lang.Deprecated
