Classfile /Users/mw/Projects/slang-braindump/.jar/jar8/assemble/slang-braindump/assemble/content/org/scalatest/events/SeeStackDepthException.class
  Last modified May 29, 2022; size 2022 bytes
  SHA-256 checksum 6243813045fb9fd18107abc46967c21ebd18686daaba656edb3df19a9f3d19b7
  Compiled from "Location.scala"
public final class org.scalatest.events.SeeStackDepthException
  minor version: 0
  major version: 52
  flags: (0x0031) ACC_PUBLIC, ACC_FINAL, ACC_SUPER
  this_class: #2                          // org/scalatest/events/SeeStackDepthException
  super_class: #4                         // java/lang/Object
  interfaces: 0, fields: 0, methods: 9, attributes: 3
Constant pool:
   #1 = Utf8               org/scalatest/events/SeeStackDepthException
   #2 = Class              #1             // org/scalatest/events/SeeStackDepthException
   #3 = Utf8               java/lang/Object
   #4 = Class              #3             // java/lang/Object
   #5 = Utf8               Location.scala
   #6 = Utf8               Lscala/reflect/ScalaSignature;
   #7 = Utf8               bytes
   #8 = Utf8               \u0006\u0005m;Qa\u0003\u0007\t\u0006N1Q!\u0006\u0007\t\u0006ZAQ\u0001L\u0001\u0005\u00025BqAL\u0001\u0002\u0002\u0013\u0005s\u0006C\u00049\u0003\u0005\u0005I\u0011A\u001d\t\u000fu\n\u0011\u0011!C\u0001}!9A)AA\u0001\n\u0003*\u0005b\u0002\'\u0002\u0003\u0003%\t!\u0014\u0005\b%\u0006\t\t\u0011\"\u0011T\u0011\u001d!\u0016!!A\u0005BUCqAV\u0001\u0002\u0002\u0013%q+\u0001\fTK\u0016\u001cF/Y2l\t\u0016\u0004H\u000f[#yG\u0016\u0004H/[8o\u0015\tia\"\u0001\u0004fm\u0016tGo\u001d\u0006\u0003\u001fA\t\u0011b]2bY\u0006$Xm\u001d;\u000b\u0003E\t1a\u001c:h\u0007\u0001\u0001\"\u0001F\u0001\u000e\u00031\u0011acU3f\'R\f7m\u001b#faRDW\t_2faRLwN\\\n\u0005\u0003]Q\u0002\u0005\u0005\u0002\u00151%\u0011\u0011\u0004\u0004\u0002\t\u0019>\u001c\u0017\r^5p]B\u00111DH\u0007\u00029)\tQ$A\u0003tG\u0006d\u0017-\u0003\u0002 9\t9\u0001K]8ek\u000e$\bCA\u0011*\u001d\t\u0011sE\u0004\u0002$M5\tAE\u0003\u0002&%\u00051AH]8pizJ\u0011!H\u0005\u0003Qq\tq\u0001]1dW\u0006<W-\u0003\u0002+W\ta1+\u001a:jC2L\'0\u00192mK*\u0011\u0001\u0006H\u0001\u0007y%t\u0017\u000e\u001e \u0015\u0003M\tQ\u0002\u001d:pIV\u001cG\u000f\u0015:fM&DX#\u0001\u0019\u0011\u0005E2T\"\u0001\u001a\u000b\u0005M\"\u0014\u0001\u00027b]\u001eT\u0011!N\u0001\u0005U\u00064\u0018-\u0003\u00028e\t11\u000b\u001e:j]\u001e\fA\u0002\u001d:pIV\u001cG/\u0011:jif,\u0012A\u000f\t\u00037mJ!\u0001\u0010\u000f\u0003\u0007%sG/\u0001\bqe>$Wo\u0019;FY\u0016lWM\u001c;\u0015\u0005}\u0012\u0005CA\u000eA\u0013\t\tEDA\u0002B]fDqaQ\u0003\u0002\u0002\u0003\u0007!(A\u0002yIE\nq\u0002\u001d:pIV\u001cG/\u0013;fe\u0006$xN]\u000b\u0002\rB\u0019qIS \u000e\u0003!S!!\u0013\u000f\u0002\u0015\r|G\u000e\\3di&|g.\u0003\u0002L\u0011\nA\u0011\n^3sCR|\'/\u0001\u0005dC:,\u0015/^1m)\tq\u0015\u000b\u0005\u0002\u001c\u001f&\u0011\u0001\u000b\b\u0002\b\u0005>|G.Z1o\u0011\u001d\u0019u!!AA\u0002}\n\u0001\u0002[1tQ\u000e{G-\u001a\u000b\u0002u\u0005AAo\\*ue&tw\rF\u00011\u000319(/\u001b;f%\u0016\u0004H.Y2f)\u0005A\u0006CA\u0019Z\u0013\tQ&G\u0001\u0004PE*,7\r\u001e
   #9 = Utf8               toString
  #10 = Utf8               ()Ljava/lang/String;
  #11 = Utf8               org/scalatest/events/SeeStackDepthException$
  #12 = Class              #11            // org/scalatest/events/SeeStackDepthException$
  #13 = Utf8               MODULE$
  #14 = Utf8               Lorg/scalatest/events/SeeStackDepthException$;
  #15 = NameAndType        #13:#14        // MODULE$:Lorg/scalatest/events/SeeStackDepthException$;
  #16 = Fieldref           #12.#15        // org/scalatest/events/SeeStackDepthException$.MODULE$:Lorg/scalatest/events/SeeStackDepthException$;
  #17 = NameAndType        #9:#10         // toString:()Ljava/lang/String;
  #18 = Methodref          #12.#17        // org/scalatest/events/SeeStackDepthException$.toString:()Ljava/lang/String;
  #19 = Utf8               hashCode
  #20 = Utf8               ()I
  #21 = NameAndType        #19:#20        // hashCode:()I
  #22 = Methodref          #12.#21        // org/scalatest/events/SeeStackDepthException$.hashCode:()I
  #23 = Utf8               canEqual
  #24 = Utf8               (Ljava/lang/Object;)Z
  #25 = Utf8               x$1
  #26 = NameAndType        #23:#24        // canEqual:(Ljava/lang/Object;)Z
  #27 = Methodref          #12.#26        // org/scalatest/events/SeeStackDepthException$.canEqual:(Ljava/lang/Object;)Z
  #28 = Utf8               Ljava/lang/Object;
  #29 = Utf8               productIterator
  #30 = Utf8               ()Lscala/collection/Iterator;
  #31 = Utf8               ()Lscala/collection/Iterator<Ljava/lang/Object;>;
  #32 = NameAndType        #29:#30        // productIterator:()Lscala/collection/Iterator;
  #33 = Methodref          #12.#32        // org/scalatest/events/SeeStackDepthException$.productIterator:()Lscala/collection/Iterator;
  #34 = Utf8               productElement
  #35 = Utf8               (I)Ljava/lang/Object;
  #36 = NameAndType        #34:#35        // productElement:(I)Ljava/lang/Object;
  #37 = Methodref          #12.#36        // org/scalatest/events/SeeStackDepthException$.productElement:(I)Ljava/lang/Object;
  #38 = Utf8               I
  #39 = Utf8               productArity
  #40 = NameAndType        #39:#20        // productArity:()I
  #41 = Methodref          #12.#40        // org/scalatest/events/SeeStackDepthException$.productArity:()I
  #42 = Utf8               productPrefix
  #43 = NameAndType        #42:#10        // productPrefix:()Ljava/lang/String;
  #44 = Methodref          #12.#43        // org/scalatest/events/SeeStackDepthException$.productPrefix:()Ljava/lang/String;
  #45 = Utf8               productElementNames
  #46 = Utf8               ()Lscala/collection/Iterator<Ljava/lang/String;>;
  #47 = NameAndType        #45:#30        // productElementNames:()Lscala/collection/Iterator;
  #48 = Methodref          #12.#47        // org/scalatest/events/SeeStackDepthException$.productElementNames:()Lscala/collection/Iterator;
  #49 = Utf8               productElementName
  #50 = Utf8               (I)Ljava/lang/String;
  #51 = Utf8               n
  #52 = NameAndType        #49:#50        // productElementName:(I)Ljava/lang/String;
  #53 = Methodref          #12.#52        // org/scalatest/events/SeeStackDepthException$.productElementName:(I)Ljava/lang/String;
  #54 = Utf8               Code
  #55 = Utf8               LocalVariableTable
  #56 = Utf8               MethodParameters
  #57 = Utf8               Signature
  #58 = Utf8               SourceFile
  #59 = Utf8               RuntimeVisibleAnnotations
  #60 = Utf8               ScalaSig
{
  public static java.lang.String toString();
    descriptor: ()Ljava/lang/String;
    flags: (0x0009) ACC_PUBLIC, ACC_STATIC
    Code:
      stack=1, locals=0, args_size=0
         0: getstatic     #16                 // Field org/scalatest/events/SeeStackDepthException$.MODULE$:Lorg/scalatest/events/SeeStackDepthException$;
         3: invokevirtual #18                 // Method org/scalatest/events/SeeStackDepthException$.toString:()Ljava/lang/String;
         6: areturn

  public static int hashCode();
    descriptor: ()I
    flags: (0x0009) ACC_PUBLIC, ACC_STATIC
    Code:
      stack=1, locals=0, args_size=0
         0: getstatic     #16                 // Field org/scalatest/events/SeeStackDepthException$.MODULE$:Lorg/scalatest/events/SeeStackDepthException$;
         3: invokevirtual #22                 // Method org/scalatest/events/SeeStackDepthException$.hashCode:()I
         6: ireturn

  public static boolean canEqual(java.lang.Object);
    descriptor: (Ljava/lang/Object;)Z
    flags: (0x0009) ACC_PUBLIC, ACC_STATIC
    Code:
      stack=2, locals=1, args_size=1
         0: getstatic     #16                 // Field org/scalatest/events/SeeStackDepthException$.MODULE$:Lorg/scalatest/events/SeeStackDepthException$;
         3: aload_0
         4: invokevirtual #27                 // Method org/scalatest/events/SeeStackDepthException$.canEqual:(Ljava/lang/Object;)Z
         7: ireturn
      LocalVariableTable:
        Start  Length  Slot  Name   Signature
            0       8     0   x$1   Ljava/lang/Object;
    MethodParameters:
      Name                           Flags
      x$1                            final

  public static scala.collection.Iterator<java.lang.Object> productIterator();
    descriptor: ()Lscala/collection/Iterator;
    flags: (0x0009) ACC_PUBLIC, ACC_STATIC
    Code:
      stack=1, locals=0, args_size=0
         0: getstatic     #16                 // Field org/scalatest/events/SeeStackDepthException$.MODULE$:Lorg/scalatest/events/SeeStackDepthException$;
         3: invokevirtual #33                 // Method org/scalatest/events/SeeStackDepthException$.productIterator:()Lscala/collection/Iterator;
         6: areturn
    Signature: #31                          // ()Lscala/collection/Iterator<Ljava/lang/Object;>;

  public static java.lang.Object productElement(int);
    descriptor: (I)Ljava/lang/Object;
    flags: (0x0009) ACC_PUBLIC, ACC_STATIC
    Code:
      stack=2, locals=1, args_size=1
         0: getstatic     #16                 // Field org/scalatest/events/SeeStackDepthException$.MODULE$:Lorg/scalatest/events/SeeStackDepthException$;
         3: iload_0
         4: invokevirtual #37                 // Method org/scalatest/events/SeeStackDepthException$.productElement:(I)Ljava/lang/Object;
         7: areturn
      LocalVariableTable:
        Start  Length  Slot  Name   Signature
            0       8     0   x$1   I
    MethodParameters:
      Name                           Flags
      x$1                            final

  public static int productArity();
    descriptor: ()I
    flags: (0x0009) ACC_PUBLIC, ACC_STATIC
    Code:
      stack=1, locals=0, args_size=0
         0: getstatic     #16                 // Field org/scalatest/events/SeeStackDepthException$.MODULE$:Lorg/scalatest/events/SeeStackDepthException$;
         3: invokevirtual #41                 // Method org/scalatest/events/SeeStackDepthException$.productArity:()I
         6: ireturn

  public static java.lang.String productPrefix();
    descriptor: ()Ljava/lang/String;
    flags: (0x0009) ACC_PUBLIC, ACC_STATIC
    Code:
      stack=1, locals=0, args_size=0
         0: getstatic     #16                 // Field org/scalatest/events/SeeStackDepthException$.MODULE$:Lorg/scalatest/events/SeeStackDepthException$;
         3: invokevirtual #44                 // Method org/scalatest/events/SeeStackDepthException$.productPrefix:()Ljava/lang/String;
         6: areturn

  public static scala.collection.Iterator<java.lang.String> productElementNames();
    descriptor: ()Lscala/collection/Iterator;
    flags: (0x0009) ACC_PUBLIC, ACC_STATIC
    Code:
      stack=1, locals=0, args_size=0
         0: getstatic     #16                 // Field org/scalatest/events/SeeStackDepthException$.MODULE$:Lorg/scalatest/events/SeeStackDepthException$;
         3: invokevirtual #48                 // Method org/scalatest/events/SeeStackDepthException$.productElementNames:()Lscala/collection/Iterator;
         6: areturn
    Signature: #46                          // ()Lscala/collection/Iterator<Ljava/lang/String;>;

  public static java.lang.String productElementName(int);
    descriptor: (I)Ljava/lang/String;
    flags: (0x0009) ACC_PUBLIC, ACC_STATIC
    Code:
      stack=2, locals=1, args_size=1
         0: getstatic     #16                 // Field org/scalatest/events/SeeStackDepthException$.MODULE$:Lorg/scalatest/events/SeeStackDepthException$;
         3: iload_0
         4: invokevirtual #53                 // Method org/scalatest/events/SeeStackDepthException$.productElementName:(I)Ljava/lang/String;
         7: areturn
      LocalVariableTable:
        Start  Length  Slot  Name   Signature
            0       8     0     n   I
    MethodParameters:
      Name                           Flags
      n                              final
}
SourceFile: "Location.scala"
RuntimeVisibleAnnotations:
  0: #6(#7=s#8)
    scala.reflect.ScalaSignature(
      bytes="\u0006\u0005m;Qa\u0003\u0007\t\u0006N1Q!\u0006\u0007\t\u0006ZAQ\u0001L\u0001\u0005\u00025BqAL\u0001\u0002\u0002\u0013\u0005s\u0006C\u00049\u0003\u0005\u0005I\u0011A\u001d\t\u000fu\n\u0011\u0011!C\u0001}!9A)AA\u0001\n\u0003*\u0005b\u0002\'\u0002\u0003\u0003%\t!\u0014\u0005\b%\u0006\t\t\u0011\"\u0011T\u0011\u001d!\u0016!!A\u0005BUCqAV\u0001\u0002\u0002\u0013%q+\u0001\fTK\u0016\u001cF/Y2l\t\u0016\u0004H\u000f[#yG\u0016\u0004H/[8o\u0015\tia\"\u0001\u0004fm\u0016tGo\u001d\u0006\u0003\u001fA\t\u0011b]2bY\u0006$Xm\u001d;\u000b\u0003E\t1a\u001c:h\u0007\u0001\u0001\"\u0001F\u0001\u000e\u00031\u0011acU3f\'R\f7m\u001b#faRDW\t_2faRLwN\\\n\u0005\u0003]Q\u0002\u0005\u0005\u0002\u00151%\u0011\u0011\u0004\u0004\u0002\t\u0019>\u001c\u0017\r^5p]B\u00111DH\u0007\u00029)\tQ$A\u0003tG\u0006d\u0017-\u0003\u0002 9\t9\u0001K]8ek\u000e$\bCA\u0011*\u001d\t\u0011sE\u0004\u0002$M5\tAE\u0003\u0002&%\u00051AH]8pizJ\u0011!H\u0005\u0003Qq\tq\u0001]1dW\u0006<W-\u0003\u0002+W\ta1+\u001a:jC2L\'0\u00192mK*\u0011\u0001\u0006H\u0001\u0007y%t\u0017\u000e\u001e \u0015\u0003M\tQ\u0002\u001d:pIV\u001cG\u000f\u0015:fM&DX#\u0001\u0019\u0011\u0005E2T\"\u0001\u001a\u000b\u0005M\"\u0014\u0001\u00027b]\u001eT\u0011!N\u0001\u0005U\u00064\u0018-\u0003\u00028e\t11\u000b\u001e:j]\u001e\fA\u0002\u001d:pIV\u001cG/\u0011:jif,\u0012A\u000f\t\u00037mJ!\u0001\u0010\u000f\u0003\u0007%sG/\u0001\bqe>$Wo\u0019;FY\u0016lWM\u001c;\u0015\u0005}\u0012\u0005CA\u000eA\u0013\t\tEDA\u0002B]fDqaQ\u0003\u0002\u0002\u0003\u0007!(A\u0002yIE\nq\u0002\u001d:pIV\u001cG/\u0013;fe\u0006$xN]\u000b\u0002\rB\u0019qIS \u000e\u0003!S!!\u0013\u000f\u0002\u0015\r|G\u000e\\3di&|g.\u0003\u0002L\u0011\nA\u0011\n^3sCR|\'/\u0001\u0005dC:,\u0015/^1m)\tq\u0015\u000b\u0005\u0002\u001c\u001f&\u0011\u0001\u000b\b\u0002\b\u0005>|G.Z1o\u0011\u001d\u0019u!!AA\u0002}\n\u0001\u0002[1tQ\u000e{G-\u001a\u000b\u0002u\u0005AAo\\*ue&tw\rF\u00011\u000319(/\u001b;f%\u0016\u0004H.Y2f)\u0005A\u0006CA\u0019Z\u0013\tQ&G\u0001\u0004PE*,7\r\u001e"
    )
  ScalaSig: length = 0x3 (unknown attribute)
   05 02 00
