Classfile /Users/mw/Projects/slang-braindump/.jar/jar8/assemble/slang-braindump/assemble/content/org/scalatest/events/TestPending.class
  Last modified May 29, 2022; size 23689 bytes
  SHA-256 checksum 9e67935aeb301b47ab45463ea327839c7ad2edaf976e9aa09e361a71b81d6852
  Compiled from "Event.scala"
public final class org.scalatest.events.TestPending extends org.scalatest.events.Event
  minor version: 0
  major version: 52
  flags: (0x0031) ACC_PUBLIC, ACC_FINAL, ACC_SUPER
  this_class: #2                          // org/scalatest/events/TestPending
  super_class: #4                         // org/scalatest/events/Event
  interfaces: 0, fields: 13, methods: 61, attributes: 6
Constant pool:
    #1 = Utf8               org/scalatest/events/TestPending
    #2 = Class              #1            // org/scalatest/events/TestPending
    #3 = Utf8               org/scalatest/events/Event
    #4 = Class              #3            // org/scalatest/events/Event
    #5 = Utf8               Event.scala
    #6 = Utf8               Lscala/reflect/ScalaSignature;
    #7 = Utf8               bytes
    #8 = Utf8               \u0006\u0005\t=g\u0001B%K\u0005FC\u0001\u0002\u001b\u0001\u0003\u0016\u0004%\t!\u001b\u0005\t[\u0002\u0011\t\u0012)A\u0005U\"Aa\u000e\u0001BK\u0002\u0013\u0005q\u000e\u0003\u0005y\u0001\tE\t\u0015!\u0003q\u0011!I\bA!f\u0001\n\u0003y\u0007\u0002\u0003>\u0001\u0005#\u0005\u000b\u0011\u00029\t\u0011m\u0004!Q3A\u0005\u0002qD\u0011\"!\u0001\u0001\u0005#\u0005\u000b\u0011B?\t\u0013\u0005\r\u0001A!f\u0001\n\u0003y\u0007\"CA\u0003\u0001\tE\t\u0015!\u0003q\u0011%\t9\u0001\u0001BK\u0002\u0013\u0005q\u000eC\u0005\u0002\n\u0001\u0011\t\u0012)A\u0005a\"Q\u00111\u0002\u0001\u0003\u0016\u0004%\t!!\u0004\t\u0015\u0005\u0015\u0002A!E!\u0002\u0013\ty\u0001\u0003\u0006\u0002(\u0001\u0011)\u001a!C\u0001\u0003SA!\"a\r\u0001\u0005#\u0005\u000b\u0011BA\u0016\u0011)\t)\u0004\u0001BK\u0002\u0013\u0005\u0011q\u0007\u0005\u000b\u0003\u0003\u0002!\u0011#Q\u0001\n\u0005e\u0002BCA\"\u0001\tU\r\u0011\"\u0001\u0002F!Q\u0011q\n\u0001\u0003\u0012\u0003\u0006I!a\u0012\t\u0015\u0005E\u0003A!f\u0001\n\u0003\t\u0019\u0006\u0003\u0006\u0002^\u0001\u0011\t\u0012)A\u0005\u0003+B\u0011\"a\u0018\u0001\u0005+\u0007I\u0011A8\t\u0013\u0005\u0005\u0004A!E!\u0002\u0013\u0001\bBCA2\u0001\tU\r\u0011\"\u0001\u0002f!Q\u0011q\r\u0001\u0003\u0012\u0003\u0006I!!\f\t\u000f\u0005%\u0004\u0001\"\u0001\u0002l!A\u0011\u0011\u0012\u0001\u0005\u00021\u000bY\tC\u0004\u0002\u001a\u0002!\t\u0001T8\t\u0011\u0005m\u0005\u0001\"\u0001K\u0003;C\u0011\"a)\u0001\u0003\u0003%\t!!*\t\u0013\u0005\u0005\u0007!%A\u0005\u0002\u0005\r\u0007\"CAm\u0001E\u0005I\u0011AAn\u0011%\ty\u000eAI\u0001\n\u0003\tY\u000eC\u0005\u0002b\u0002\t\n\u0011\"\u0001\u0002d\"I\u0011q\u001d\u0001\u0012\u0002\u0013\u0005\u00111\u001c\u0005\n\u0003S\u0004\u0011\u0013!C\u0001\u00037D\u0011\"a;\u0001#\u0003%\t!!<\t\u0013\u0005E\b!%A\u0005\u0002\u0005M\b\"CA|\u0001E\u0005I\u0011AA}\u0011%\ti\u0010AI\u0001\n\u0003\ty\u0010C\u0005\u0003\u0004\u0001\t\n\u0011\"\u0001\u0003\u0006!I!\u0011\u0002\u0001\u0012\u0002\u0013\u0005\u00111\u001c\u0005\n\u0005\u0017\u0001\u0011\u0013!C\u0001\u0005\u001bA\u0011B!\u0005\u0001\u0003\u0003%\tEa\u0005\t\u0013\t\r\u0002!!A\u0005\u0002\t\u0015\u0002\"\u0003B\u0017\u0001\u0005\u0005I\u0011\u0001B\u0018\u0011%\u0011)\u0004AA\u0001\n\u0003\u00129\u0004C\u0005\u0003B\u0001\t\t\u0011\"\u0001\u0003D!I!Q\n\u0001\u0002\u0002\u0013\u0005#q\n\u0005\n\u0005\'\u0002\u0011\u0011!C!\u0005+B\u0011Ba\u0016\u0001\u0003\u0003%\tE!\u0017\t\u0013\tm\u0003!!A\u0005B\tus!\u0003B1\u0015\u0006\u0005\t\u0012\u0001B2\r!I%*!A\t\u0002\t\u0015\u0004bBA5o\u0011\u0005!Q\u0010\u0005\n\u0005/:\u0014\u0011!C#\u00053B\u0011Ba 8\u0003\u0003%\tI!!\t\u0013\tuu\'%A\u0005\u0002\u0005M\b\"\u0003BPoE\u0005I\u0011AA}\u0011%\u0011\tkNI\u0001\n\u0003\ty\u0010C\u0005\u0003$^\n\n\u0011\"\u0001\u0003\u0006!I!QU\u001c\u0012\u0002\u0013\u0005\u00111\u001c\u0005\n\u0005O;\u0014\u0013!C\u0001\u0005\u001bA\u0011B!+8\u0003\u0003%\tIa+\t\u0013\tev\'%A\u0005\u0002\u0005M\b\"\u0003B^oE\u0005I\u0011AA}\u0011%\u0011ilNI\u0001\n\u0003\ty\u0010C\u0005\u0003@^\n\n\u0011\"\u0001\u0003\u0006!I!\u0011Y\u001c\u0012\u0002\u0013\u0005\u00111\u001c\u0005\n\u0005\u0007<\u0014\u0013!C\u0001\u0005\u001bA\u0011B!28\u0003\u0003%IAa2\u0003\u0017Q+7\u000f\u001e)f]\u0012Lgn\u001a\u0006\u0003\u00172\u000ba!\u001a<f]R\u001c(BA\'O\u0003%\u00198-\u00197bi\u0016\u001cHOC\u0001P\u0003\ry\'oZ\u0002\u0001\'\u0011\u0001!K\u0016/\u0011\u0005M#V\"\u0001&\n\u0005US%!B#wK:$\bCA,[\u001b\u0005A&\"A-\u0002\u000bM\u001c\u0017\r\\1\n\u0005mC&a\u0002)s_\u0012,8\r\u001e\t\u0003;\u0016t!AX2\u000f\u0005}\u0013W\"\u00011\u000b\u0005\u0005\u0004\u0016A\u0002\u001fs_>$h(C\u0001Z\u0013\t!\u0007,A\u0004qC\u000e\\\u0017mZ3\n\u0005\u0019<\'\u0001D*fe&\fG.\u001b>bE2,\'B\u00013Y\u0003\u001dy\'\u000fZ5oC2,\u0012A\u001b\t\u0003\'.L!\u0001\u001c&\u0003\u000f=\u0013H-\u001b8bY\u0006AqN\u001d3j]\u0006d\u0007%A\u0005tk&$XMT1nKV\t\u0001\u000f\u0005\u0002rk:\u0011!o\u001d\t\u0003?bK!\u0001\u001e-\u0002\rA\u0013X\rZ3g\u0013\t1xO\u0001\u0004TiJLgn\u001a\u0006\u0003ib\u000b!b];ji\u0016t\u0015-\\3!\u0003\u001d\u0019X/\u001b;f\u0013\u0012\f\u0001b];ji\u0016LE\rI\u0001\u000fgVLG/Z\"mCN\u001ch*Y7f+\u0005i\bcA,\u007fa&\u0011q\u0010\u0017\u0002\u0007\u001fB$\u0018n\u001c8\u0002\u001fM,\u0018\u000e^3DY\u0006\u001c8OT1nK\u0002\n\u0001\u0002^3ti:\u000bW.Z\u0001\ni\u0016\u001cHOT1nK\u0002\n\u0001\u0002^3tiR+\u0007\u0010^\u0001\ni\u0016\u001cH\u000fV3yi\u0002\naB]3d_J$W\rZ#wK:$8/\u0006\u0002\u0002\u0010A1\u0011\u0011CA\u000e\u0003?i!!a\u0005\u000b\t\u0005U\u0011qC\u0001\nS6lW\u000f^1cY\u0016T1!!\u0007Y\u0003)\u0019w\u000e\u001c7fGRLwN\\\u0005\u0005\u0003;\t\u0019B\u0001\u0006J]\u0012,\u00070\u001a3TKF\u00042aUA\u0011\u0013\r\t\u0019C\u0013\u0002\u0010%\u0016\u001cwN\u001d3bE2,WI^3oi\u0006y!/Z2pe\u0012,G-\u0012<f]R\u001c\b%\u0001\u0005ekJ\fG/[8o+\t\tY\u0003\u0005\u0003X}\u00065\u0002cA,\u00020%\u0019\u0011\u0011\u0007-\u0003\t1{gnZ\u0001\nIV\u0014\u0018\r^5p]\u0002\n\u0011BZ8s[\u0006$H/\u001a:\u0016\u0005\u0005e\u0002\u0003B,\u007f\u0003w\u00012aUA\u001f\u0013\r\tyD\u0013\u0002\n\r>\u0014X.\u0019;uKJ\f!BZ8s[\u0006$H/\u001a:!\u0003!awnY1uS>tWCAA$!\u00119f0!\u0013\u0011\u0007M\u000bY%C\u0002\u0002N)\u0013\u0001\u0002T8dCRLwN\\\u0001\nY>\u001c\u0017\r^5p]\u0002\nq\u0001]1zY>\fG-\u0006\u0002\u0002VA!qK`A,!\r9\u0016\u0011L\u0005\u0004\u00037B&aA!os\u0006A\u0001/Y=m_\u0006$\u0007%\u0001\u0006uQJ,\u0017\r\u001a(b[\u0016\f1\u0002\u001e5sK\u0006$g*Y7fA\u0005IA/[7f\'R\fW\u000e]\u000b\u0003\u0003[\t!\u0002^5nKN#\u0018-\u001c9!\u0003\u0019a\u0014N\\5u}Qa\u0012QNA8\u0003c\n\u0019(!\u001e\u0002x\u0005e\u00141PA?\u0003\u007f\n\t)a!\u0002\u0006\u0006\u001d\u0005CA*\u0001\u0011\u0015A7\u00041\u0001k\u0011\u0015q7\u00041\u0001q\u0011\u0015I8\u00041\u0001q\u0011\u0015Y8\u00041\u0001~\u0011\u0019\t\u0019a\u0007a\u0001a\"1\u0011qA\u000eA\u0002ADq!a\u0003\u001c\u0001\u0004\ty\u0001C\u0005\u0002(m\u0001\n\u00111\u0001\u0002,!I\u0011QG\u000e\u0011\u0002\u0003\u0007\u0011\u0011\b\u0005\n\u0003\u0007Z\u0002\u0013!a\u0001\u0003\u000fB\u0011\"!\u0015\u001c!\u0003\u0005\r!!\u0016\t\u0011\u0005}3\u0004%AA\u0002AD\u0011\"a\u0019\u001c!\u0003\u0005\r!!\f\u0002\u000bQ|\u0007,\u001c7\u0016\u0005\u00055\u0005\u0003BAH\u0003+k!!!%\u000b\u0007\u0005M\u0005,A\u0002y[2LA!a&\u0002\u0012\n!Q\t\\3n\u0003\u0019!xNS:p]\u0006Yq/\u001b;i!\u0006LHn\\1e)\u0011\ti\'a(\t\u000f\u0005\u0005f\u00041\u0001\u0002V\u0005Qa.Z<QCfdw.\u00193\u0002\t\r|\u0007/\u001f\u000b\u001d\u0003[\n9+!+\u0002,\u00065\u0016qVAY\u0003g\u000b),a.\u0002:\u0006m\u0016QXA`\u0011\u001dAw\u0004%AA\u0002)DqA\\\u0010\u0011\u0002\u0003\u0007\u0001\u000fC\u0004z?A\u0005\t\u0019\u00019\t\u000fm|\u0002\u0013!a\u0001{\"A\u00111A\u0010\u0011\u0002\u0003\u0007\u0001\u000f\u0003\u0005\u0002\b}\u0001\n\u00111\u0001q\u0011%\tYa\bI\u0001\u0002\u0004\ty\u0001C\u0005\u0002(}\u0001\n\u00111\u0001\u0002,!I\u0011QG\u0010\u0011\u0002\u0003\u0007\u0011\u0011\b\u0005\n\u0003\u0007z\u0002\u0013!a\u0001\u0003\u000fB\u0011\"!\u0015 !\u0003\u0005\r!!\u0016\t\u0011\u0005}s\u0004%AA\u0002AD\u0011\"a\u0019 !\u0003\u0005\r!!\f\u0002\u001d\r|\u0007/\u001f\u0013eK\u001a\fW\u000f\u001c;%cU\u0011\u0011Q\u0019\u0016\u0004U\u0006\u001d7FAAe!\u0011\tY-!6\u000e\u0005\u00055\'\u0002BAh\u0003#\f\u0011\"\u001e8dQ\u0016\u001c7.\u001a3\u000b\u0007\u0005M\u0007,\u0001\u0006b]:|G/\u0019;j_:LA!a6\u0002N\n\tRO\\2iK\u000e\\W\r\u001a,be&\fgnY3\u0002\u001d\r|\u0007/\u001f\u0013eK\u001a\fW\u000f\u001c;%eU\u0011\u0011Q\u001c\u0016\u0004a\u0006\u001d\u0017AD2paf$C-\u001a4bk2$HeM\u0001\u000fG>\u0004\u0018\u0010\n3fM\u0006,H\u000e\u001e\u00135+\t\t)OK\u0002~\u0003\u000f\fabY8qs\u0012\"WMZ1vYR$S\'\u0001\bd_BLH\u0005Z3gCVdG\u000f\n\u001c\u0002\u001d\r|\u0007/\u001f\u0013eK\u001a\fW\u000f\u001c;%oU\u0011\u0011q\u001e\u0016\u0005\u0003\u001f\t9-\u0001\bd_BLH\u0005Z3gCVdG\u000f\n\u001d\u0016\u0005\u0005U(\u0006BA\u0016\u0003\u000f\fabY8qs\u0012\"WMZ1vYR$\u0013(\u0006\u0002\u0002|*\"\u0011\u0011HAd\u0003=\u0019w\u000e]=%I\u00164\u0017-\u001e7uIE\u0002TC\u0001B\u0001U\u0011\t9%a2\u0002\u001f\r|\u0007/\u001f\u0013eK\u001a\fW\u000f\u001c;%cE*\"Aa\u0002+\t\u0005U\u0013qY\u0001\u0010G>\u0004\u0018\u0010\n3fM\u0006,H\u000e\u001e\u00132e\u0005y1m\u001c9zI\u0011,g-Y;mi\u0012\n4\'\u0006\u0002\u0003\u0010)\"\u0011QFAd\u00035\u0001(o\u001c3vGR\u0004&/\u001a4jqV\u0011!Q\u0003\t\u0005\u0005/\u0011\t#\u0004\u0002\u0003\u001a)!!1\u0004B\u000f\u0003\u0011a\u0017M\\4\u000b\u0005\t}\u0011\u0001\u00026bm\u0006L1A\u001eB\r\u00031\u0001(o\u001c3vGR\f%/\u001b;z+\t\u00119\u0003E\u0002X\u0005SI1Aa\u000bY\u0005\rIe\u000e^\u0001\u000faJ|G-^2u\u000b2,W.\u001a8u)\u0011\t9F!\r\t\u0013\tMr&!AA\u0002\t\u001d\u0012a\u0001=%c\u0005y\u0001O]8ek\u000e$\u0018\n^3sCR|\'/\u0006\u0002\u0003:A1!1\bB\u001f\u0003/j!!a\u0006\n\t\t}\u0012q\u0003\u0002\t\u0013R,\'/\u0019;pe\u0006A1-\u00198FcV\fG\u000e\u0006\u0003\u0003F\t-\u0003cA,\u0003H%\u0019!\u0011\n-\u0003\u000f\t{w\u000e\\3b]\"I!1G\u0019\u0002\u0002\u0003\u0007\u0011qK\u0001\u0013aJ|G-^2u\u000b2,W.\u001a8u\u001d\u0006lW\r\u0006\u0003\u0003\u0016\tE\u0003\"\u0003B\u001ae\u0005\u0005\t\u0019\u0001B\u0014\u0003!A\u0017m\u001d5D_\u0012,GC\u0001B\u0014\u0003!!xn\u0015;sS:<GC\u0001B\u000b\u0003\u0019)\u0017/^1mgR!!Q\tB0\u0011%\u0011\u0019$NA\u0001\u0002\u0004\t9&A\u0006UKN$\b+\u001a8eS:<\u0007CA*8\'\u00159$q\rB:!e\u0011IGa\u001ckaBl\b\u000f]A\b\u0003W\tI$a\u0012\u0002VA\fi#!\u001c\u000e\u0005\t-$b\u0001B71\u00069!/\u001e8uS6,\u0017\u0002\u0002B9\u0005W\u0012!#\u00112tiJ\f7\r\u001e$v]\u000e$\u0018n\u001c82gA!!Q\u000fB>\u001b\t\u00119H\u0003\u0003\u0003z\tu\u0011AA5p\u0013\r1\'q\u000f\u000b\u0003\u0005G\nQ!\u00199qYf$B$!\u001c\u0003\u0004\n\u0015%q\u0011BE\u0005\u0017\u0013iIa$\u0003\u0012\nM%Q\u0013BL\u00053\u0013Y\nC\u0003iu\u0001\u0007!\u000eC\u0003ou\u0001\u0007\u0001\u000fC\u0003zu\u0001\u0007\u0001\u000fC\u0003|u\u0001\u0007Q\u0010\u0003\u0004\u0002\u0004i\u0002\r\u0001\u001d\u0005\u0007\u0003\u000fQ\u0004\u0019\u00019\t\u000f\u0005-!\b1\u0001\u0002\u0010!I\u0011q\u0005\u001e\u0011\u0002\u0003\u0007\u00111\u0006\u0005\n\u0003kQ\u0004\u0013!a\u0001\u0003sA\u0011\"a\u0011;!\u0003\u0005\r!a\u0012\t\u0013\u0005E#\b%AA\u0002\u0005U\u0003\u0002CA0uA\u0005\t\u0019\u00019\t\u0013\u0005\r$\b%AA\u0002\u00055\u0012aD1qa2LH\u0005Z3gCVdG\u000f\n\u001d\u0002\u001f\u0005\u0004\b\u000f\\=%I\u00164\u0017-\u001e7uIe\n\u0001#\u00199qYf$C-\u001a4bk2$H%\r\u0019\u0002!\u0005\u0004\b\u000f\\=%I\u00164\u0017-\u001e7uIE\n\u0014\u0001E1qa2LH\u0005Z3gCVdG\u000fJ\u00193\u0003A\t\u0007\u000f\u001d7zI\u0011,g-Y;mi\u0012\n4\'A\u0004v]\u0006\u0004\b\u000f\\=\u0015\t\t5&Q\u0017\t\u0005/z\u0014y\u000b\u0005\fX\u0005cS\u0007\u000f]?qa\u0006=\u00111FA\u001d\u0003\u000f\n)\u0006]A\u0017\u0013\r\u0011\u0019\f\u0017\u0002\b)V\u0004H.Z\u00194\u0011%\u00119,QA\u0001\u0002\u0004\ti\'A\u0002yIA\n1\u0004\n7fgNLg.\u001b;%OJ,\u0017\r^3sI\u0011,g-Y;mi\u0012B\u0014a\u0007\u0013mKN\u001c\u0018N\\5uI\u001d\u0014X-\u0019;fe\u0012\"WMZ1vYR$\u0013(\u0001\u000f%Y\u0016\u001c8/\u001b8ji\u0012:\'/Z1uKJ$C-\u001a4bk2$H%\r\u0019\u00029\u0011bWm]:j]&$He\u001a:fCR,\'\u000f\n3fM\u0006,H\u000e\u001e\u00132c\u0005aB\u0005\\3tg&t\u0017\u000e\u001e\u0013he\u0016\fG/\u001a:%I\u00164\u0017-\u001e7uIE\u0012\u0014\u0001\b\u0013mKN\u001c\u0018N\\5uI\u001d\u0014X-\u0019;fe\u0012\"WMZ1vYR$\u0013gM\u0001\roJLG/\u001a*fa2\f7-\u001a\u000b\u0003\u0005\u0013\u0004BAa\u0006\u0003L&!!Q\u001aB\r\u0005\u0019y%M[3di\u0002
    #9 = Utf8               java/lang/invoke/MethodHandles$Lookup
   #10 = Class              #9            // java/lang/invoke/MethodHandles$Lookup
   #11 = Utf8               java/lang/invoke/MethodHandles
   #12 = Class              #11           // java/lang/invoke/MethodHandles
   #13 = Utf8               Lookup
   #14 = Utf8               org/scalactic/Requirements$RequirementsHelper
   #15 = Class              #14           // org/scalactic/Requirements$RequirementsHelper
   #16 = Utf8               org/scalactic/Requirements
   #17 = Class              #16           // org/scalactic/Requirements
   #18 = Utf8               RequirementsHelper
   #19 = Utf8               org/scalatest/events/Event$EventJsonHelper$
   #20 = Class              #19           // org/scalatest/events/Event$EventJsonHelper$
   #21 = Utf8               EventJsonHelper$
   #22 = Utf8               org/scalatest/events/Event$EventXmlHelper$
   #23 = Class              #22           // org/scalatest/events/Event$EventXmlHelper$
   #24 = Utf8               EventXmlHelper$
   #25 = Utf8               ordinal
   #26 = Utf8               Lorg/scalatest/events/Ordinal;
   #27 = Utf8               suiteName
   #28 = Utf8               Ljava/lang/String;
   #29 = Utf8               suiteId
   #30 = Utf8               suiteClassName
   #31 = Utf8               Lscala/Option;
   #32 = Utf8               Lscala/Option<Ljava/lang/String;>;
   #33 = Utf8               testName
   #34 = Utf8               testText
   #35 = Utf8               recordedEvents
   #36 = Utf8               Lscala/collection/immutable/IndexedSeq;
   #37 = Utf8               Lscala/collection/immutable/IndexedSeq<Lorg/scalatest/events/RecordableEvent;>;
   #38 = Utf8               duration
   #39 = Utf8               Lscala/Option<Ljava/lang/Object;>;
   #40 = Utf8               formatter
   #41 = Utf8               Lscala/Option<Lorg/scalatest/events/Formatter;>;
   #42 = Utf8               location
   #43 = Utf8               Lscala/Option<Lorg/scalatest/events/Location;>;
   #44 = Utf8               payload
   #45 = Utf8               threadName
   #46 = Utf8               timeStamp
   #47 = Utf8               J
   #48 = Utf8               $lessinit$greater$default$13
   #49 = Utf8               ()J
   #50 = Utf8               org/scalatest/events/TestPending$
   #51 = Class              #50           // org/scalatest/events/TestPending$
   #52 = Utf8               MODULE$
   #53 = Utf8               Lorg/scalatest/events/TestPending$;
   #54 = NameAndType        #52:#53       // MODULE$:Lorg/scalatest/events/TestPending$;
   #55 = Fieldref           #51.#54       // org/scalatest/events/TestPending$.MODULE$:Lorg/scalatest/events/TestPending$;
   #56 = NameAndType        #48:#49       // $lessinit$greater$default$13:()J
   #57 = Methodref          #51.#56       // org/scalatest/events/TestPending$.$lessinit$greater$default$13:()J
   #58 = Utf8               $lessinit$greater$default$12
   #59 = Utf8               ()Ljava/lang/String;
   #60 = NameAndType        #58:#59       // $lessinit$greater$default$12:()Ljava/lang/String;
   #61 = Methodref          #51.#60       // org/scalatest/events/TestPending$.$lessinit$greater$default$12:()Ljava/lang/String;
   #62 = Utf8               $lessinit$greater$default$11
   #63 = Utf8               ()Lscala/Option;
   #64 = Utf8               ()Lscala/Option<Ljava/lang/Object;>;
   #65 = NameAndType        #62:#63       // $lessinit$greater$default$11:()Lscala/Option;
   #66 = Methodref          #51.#65       // org/scalatest/events/TestPending$.$lessinit$greater$default$11:()Lscala/Option;
   #67 = Utf8               $lessinit$greater$default$10
   #68 = Utf8               ()Lscala/Option<Lorg/scalatest/events/Location;>;
   #69 = NameAndType        #67:#63       // $lessinit$greater$default$10:()Lscala/Option;
   #70 = Methodref          #51.#69       // org/scalatest/events/TestPending$.$lessinit$greater$default$10:()Lscala/Option;
   #71 = Utf8               $lessinit$greater$default$9
   #72 = Utf8               ()Lscala/Option<Lorg/scalatest/events/Formatter;>;
   #73 = NameAndType        #71:#63       // $lessinit$greater$default$9:()Lscala/Option;
   #74 = Methodref          #51.#73       // org/scalatest/events/TestPending$.$lessinit$greater$default$9:()Lscala/Option;
   #75 = Utf8               $lessinit$greater$default$8
   #76 = NameAndType        #75:#63       // $lessinit$greater$default$8:()Lscala/Option;
   #77 = Methodref          #51.#76       // org/scalatest/events/TestPending$.$lessinit$greater$default$8:()Lscala/Option;
   #78 = Utf8               unapply
   #79 = Utf8               (Lorg/scalatest/events/TestPending;)Lscala/Option;
   #80 = Utf8               (Lorg/scalatest/events/TestPending;)Lscala/Option<Lscala/Tuple13<Lorg/scalatest/events/Ordinal;Ljava/lang/String;Ljava/lang/String;Lscala/Option<Ljava/lang/String;>;Ljava/lang/String;Ljava/lang/String;Lscala/collection/immutable/IndexedSeq<Lorg/scalatest/events/RecordableEvent;>;Lscala/Option<Ljava/lang/Object;>;Lscala/Option<Lorg/scalatest/events/Formatter;>;Lscala/Option<Lorg/scalatest/events/Location;>;Lscala/Option<Ljava/lang/Object;>;Ljava/lang/String;Ljava/lang/Object;>;>;
   #81 = Utf8               x$0
   #82 = NameAndType        #78:#79       // unapply:(Lorg/scalatest/events/TestPending;)Lscala/Option;
   #83 = Methodref          #51.#82       // org/scalatest/events/TestPending$.unapply:(Lorg/scalatest/events/TestPending;)Lscala/Option;
   #84 = Utf8               Lorg/scalatest/events/TestPending;
   #85 = Utf8               apply$default$13
   #86 = NameAndType        #85:#49       // apply$default$13:()J
   #87 = Methodref          #51.#86       // org/scalatest/events/TestPending$.apply$default$13:()J
   #88 = Utf8               apply$default$12
   #89 = NameAndType        #88:#59       // apply$default$12:()Ljava/lang/String;
   #90 = Methodref          #51.#89       // org/scalatest/events/TestPending$.apply$default$12:()Ljava/lang/String;
   #91 = Utf8               apply$default$11
   #92 = NameAndType        #91:#63       // apply$default$11:()Lscala/Option;
   #93 = Methodref          #51.#92       // org/scalatest/events/TestPending$.apply$default$11:()Lscala/Option;
   #94 = Utf8               apply$default$10
   #95 = NameAndType        #94:#63       // apply$default$10:()Lscala/Option;
   #96 = Methodref          #51.#95       // org/scalatest/events/TestPending$.apply$default$10:()Lscala/Option;
   #97 = Utf8               apply$default$9
   #98 = NameAndType        #97:#63       // apply$default$9:()Lscala/Option;
   #99 = Methodref          #51.#98       // org/scalatest/events/TestPending$.apply$default$9:()Lscala/Option;
  #100 = Utf8               apply$default$8
  #101 = NameAndType        #100:#63      // apply$default$8:()Lscala/Option;
  #102 = Methodref          #51.#101      // org/scalatest/events/TestPending$.apply$default$8:()Lscala/Option;
  #103 = Utf8               apply
  #104 = Utf8               (Lorg/scalatest/events/Ordinal;Ljava/lang/String;Ljava/lang/String;Lscala/Option;Ljava/lang/String;Ljava/lang/String;Lscala/collection/immutable/IndexedSeq;Lscala/Option;Lscala/Option;Lscala/Option;Lscala/Option;Ljava/lang/String;J)Lorg/scalatest/events/TestPending;
  #105 = Utf8               (Lorg/scalatest/events/Ordinal;Ljava/lang/String;Ljava/lang/String;Lscala/Option<Ljava/lang/String;>;Ljava/lang/String;Ljava/lang/String;Lscala/collection/immutable/IndexedSeq<Lorg/scalatest/events/RecordableEvent;>;Lscala/Option<Ljava/lang/Object;>;Lscala/Option<Lorg/scalatest/events/Formatter;>;Lscala/Option<Lorg/scalatest/events/Location;>;Lscala/Option<Ljava/lang/Object;>;Ljava/lang/String;J)Lorg/scalatest/events/TestPending;
  #106 = NameAndType        #103:#104     // apply:(Lorg/scalatest/events/Ordinal;Ljava/lang/String;Ljava/lang/String;Lscala/Option;Ljava/lang/String;Ljava/lang/String;Lscala/collection/immutable/IndexedSeq;Lscala/Option;Lscala/Option;Lscala/Option;Lscala/Option;Ljava/lang/String;J)Lorg/scalatest/events/TestPending;
  #107 = Methodref          #51.#106      // org/scalatest/events/TestPending$.apply:(Lorg/scalatest/events/Ordinal;Ljava/lang/String;Ljava/lang/String;Lscala/Option;Ljava/lang/String;Ljava/lang/String;Lscala/collection/immutable/IndexedSeq;Lscala/Option;Lscala/Option;Lscala/Option;Lscala/Option;Ljava/lang/String;J)Lorg/scalatest/events/TestPending;
  #108 = Utf8               tupled
  #109 = Utf8               ()Lscala/Function1;
  #110 = Utf8               ()Lscala/Function1<Lscala/Tuple13<Lorg/scalatest/events/Ordinal;Ljava/lang/String;Ljava/lang/String;Lscala/Option<Ljava/lang/String;>;Ljava/lang/String;Ljava/lang/String;Lscala/collection/immutable/IndexedSeq<Lorg/scalatest/events/RecordableEvent;>;Lscala/Option<Ljava/lang/Object;>;Lscala/Option<Lorg/scalatest/events/Formatter;>;Lscala/Option<Lorg/scalatest/events/Location;>;Lscala/Option<Ljava/lang/Object;>;Ljava/lang/String;Ljava/lang/Object;>;Lorg/scalatest/events/TestPending;>;
  #111 = NameAndType        #108:#109     // tupled:()Lscala/Function1;
  #112 = Methodref          #51.#111      // org/scalatest/events/TestPending$.tupled:()Lscala/Function1;
  #113 = Utf8               curried
  #114 = Utf8               ()Lscala/Function1<Lorg/scalatest/events/Ordinal;Lscala/Function1<Ljava/lang/String;Lscala/Function1<Ljava/lang/String;Lscala/Function1<Lscala/Option<Ljava/lang/String;>;Lscala/Function1<Ljava/lang/String;Lscala/Function1<Ljava/lang/String;Lscala/Function1<Lscala/collection/immutable/IndexedSeq<Lorg/scalatest/events/RecordableEvent;>;Lscala/Function1<Lscala/Option<Ljava/lang/Object;>;Lscala/Function1<Lscala/Option<Lorg/scalatest/events/Formatter;>;Lscala/Function1<Lscala/Option<Lorg/scalatest/events/Location;>;Lscala/Function1<Lscala/Option<Ljava/lang/Object;>;Lscala/Function1<Ljava/lang/String;Lscala/Function1<Ljava/lang/Object;Lorg/scalatest/events/TestPending;>;>;>;>;>;>;>;>;>;>;>;>;>;
  #115 = NameAndType        #113:#109     // curried:()Lscala/Function1;
  #116 = Methodref          #51.#115      // org/scalatest/events/TestPending$.curried:()Lscala/Function1;
  #117 = Utf8               ()Lorg/scalatest/events/Ordinal;
  #118 = NameAndType        #25:#26       // ordinal:Lorg/scalatest/events/Ordinal;
  #119 = Fieldref           #2.#118       // org/scalatest/events/TestPending.ordinal:Lorg/scalatest/events/Ordinal;
  #120 = Utf8               this
  #121 = NameAndType        #27:#28       // suiteName:Ljava/lang/String;
  #122 = Fieldref           #2.#121       // org/scalatest/events/TestPending.suiteName:Ljava/lang/String;
  #123 = NameAndType        #29:#28       // suiteId:Ljava/lang/String;
  #124 = Fieldref           #2.#123       // org/scalatest/events/TestPending.suiteId:Ljava/lang/String;
  #125 = Utf8               ()Lscala/Option<Ljava/lang/String;>;
  #126 = NameAndType        #30:#31       // suiteClassName:Lscala/Option;
  #127 = Fieldref           #2.#126       // org/scalatest/events/TestPending.suiteClassName:Lscala/Option;
  #128 = NameAndType        #33:#28       // testName:Ljava/lang/String;
  #129 = Fieldref           #2.#128       // org/scalatest/events/TestPending.testName:Ljava/lang/String;
  #130 = NameAndType        #34:#28       // testText:Ljava/lang/String;
  #131 = Fieldref           #2.#130       // org/scalatest/events/TestPending.testText:Ljava/lang/String;
  #132 = Utf8               ()Lscala/collection/immutable/IndexedSeq;
  #133 = Utf8               ()Lscala/collection/immutable/IndexedSeq<Lorg/scalatest/events/RecordableEvent;>;
  #134 = NameAndType        #35:#36       // recordedEvents:Lscala/collection/immutable/IndexedSeq;
  #135 = Fieldref           #2.#134       // org/scalatest/events/TestPending.recordedEvents:Lscala/collection/immutable/IndexedSeq;
  #136 = NameAndType        #38:#31       // duration:Lscala/Option;
  #137 = Fieldref           #2.#136       // org/scalatest/events/TestPending.duration:Lscala/Option;
  #138 = NameAndType        #40:#31       // formatter:Lscala/Option;
  #139 = Fieldref           #2.#138       // org/scalatest/events/TestPending.formatter:Lscala/Option;
  #140 = NameAndType        #42:#31       // location:Lscala/Option;
  #141 = Fieldref           #2.#140       // org/scalatest/events/TestPending.location:Lscala/Option;
  #142 = NameAndType        #44:#31       // payload:Lscala/Option;
  #143 = Fieldref           #2.#142       // org/scalatest/events/TestPending.payload:Lscala/Option;
  #144 = NameAndType        #45:#28       // threadName:Ljava/lang/String;
  #145 = Fieldref           #2.#144       // org/scalatest/events/TestPending.threadName:Ljava/lang/String;
  #146 = NameAndType        #46:#47       // timeStamp:J
  #147 = Fieldref           #2.#146       // org/scalatest/events/TestPending.timeStamp:J
  #148 = Utf8               toXml
  #149 = Utf8               ()Lscala/xml/Elem;
  #150 = Utf8               scala/xml/Elem
  #151 = Class              #150          // scala/xml/Elem
  #152 = Utf8               TestPending
  #153 = String             #152          // TestPending
  #154 = Utf8               scala/xml/Null$
  #155 = Class              #154          // scala/xml/Null$
  #156 = Utf8               Lscala/xml/Null$;
  #157 = NameAndType        #52:#156      // MODULE$:Lscala/xml/Null$;
  #158 = Fieldref           #155.#157     // scala/xml/Null$.MODULE$:Lscala/xml/Null$;
  #159 = Utf8               scala/xml/TopScope$
  #160 = Class              #159          // scala/xml/TopScope$
  #161 = Utf8               Lscala/xml/TopScope$;
  #162 = NameAndType        #52:#161      // MODULE$:Lscala/xml/TopScope$;
  #163 = Fieldref           #160.#162     // scala/xml/TopScope$.MODULE$:Lscala/xml/TopScope$;
  #164 = Utf8               scala/xml/NodeSeq$
  #165 = Class              #164          // scala/xml/NodeSeq$
  #166 = Utf8               Lscala/xml/NodeSeq$;
  #167 = NameAndType        #52:#166      // MODULE$:Lscala/xml/NodeSeq$;
  #168 = Fieldref           #165.#167     // scala/xml/NodeSeq$.MODULE$:Lscala/xml/NodeSeq$;
  #169 = Utf8               scala/xml/NodeBuffer
  #170 = Class              #169          // scala/xml/NodeBuffer
  #171 = Utf8               <init>
  #172 = Utf8               ()V
  #173 = NameAndType        #171:#172     // "<init>":()V
  #174 = Methodref          #170.#173     // scala/xml/NodeBuffer."<init>":()V
  #175 = Utf8               scala/xml/Text
  #176 = Class              #175          // scala/xml/Text
  #177 = Utf8               \n
  #178 = String             #177          // \n
  #179 = Utf8               (Ljava/lang/String;)V
  #180 = NameAndType        #171:#179     // "<init>":(Ljava/lang/String;)V
  #181 = Methodref          #176.#180     // scala/xml/Text."<init>":(Ljava/lang/String;)V
  #182 = Utf8               $amp$plus
  #183 = Utf8               (Ljava/lang/Object;)Lscala/xml/NodeBuffer;
  #184 = NameAndType        #182:#183     // $amp$plus:(Ljava/lang/Object;)Lscala/xml/NodeBuffer;
  #185 = Methodref          #170.#184     // scala/xml/NodeBuffer.$amp$plus:(Ljava/lang/Object;)Lscala/xml/NodeBuffer;
  #186 = String             #25           // ordinal
  #187 = Utf8               \n
  #188 = String             #187          // \n
  #189 = Utf8               runStamp
  #190 = String             #189          // runStamp
  #191 = NameAndType        #25:#117      // ordinal:()Lorg/scalatest/events/Ordinal;
  #192 = Methodref          #2.#191       // org/scalatest/events/TestPending.ordinal:()Lorg/scalatest/events/Ordinal;
  #193 = Utf8               org/scalatest/events/Ordinal
  #194 = Class              #193          // org/scalatest/events/Ordinal
  #195 = Utf8               ()I
  #196 = NameAndType        #189:#195     // runStamp:()I
  #197 = Methodref          #194.#196     // org/scalatest/events/Ordinal.runStamp:()I
  #198 = Utf8               scala/runtime/BoxesRunTime
  #199 = Class              #198          // scala/runtime/BoxesRunTime
  #200 = Utf8               boxToInteger
  #201 = Utf8               (I)Ljava/lang/Integer;
  #202 = NameAndType        #200:#201     // boxToInteger:(I)Ljava/lang/Integer;
  #203 = Methodref          #199.#202     // scala/runtime/BoxesRunTime.boxToInteger:(I)Ljava/lang/Integer;
  #204 = Utf8               seqToNodeSeq
  #205 = Utf8               (Lscala/collection/Seq;)Lscala/xml/NodeSeq;
  #206 = NameAndType        #204:#205     // seqToNodeSeq:(Lscala/collection/Seq;)Lscala/xml/NodeSeq;
  #207 = Methodref          #165.#206     // scala/xml/NodeSeq$.seqToNodeSeq:(Lscala/collection/Seq;)Lscala/xml/NodeSeq;
  #208 = Utf8               (Ljava/lang/String;Ljava/lang/String;Lscala/xml/MetaData;Lscala/xml/NamespaceBinding;ZLscala/collection/immutable/Seq;)V
  #209 = NameAndType        #171:#208     // "<init>":(Ljava/lang/String;Ljava/lang/String;Lscala/xml/MetaData;Lscala/xml/NamespaceBinding;ZLscala/collection/immutable/Seq;)V
  #210 = Methodref          #151.#209     // scala/xml/Elem."<init>":(Ljava/lang/String;Ljava/lang/String;Lscala/xml/MetaData;Lscala/xml/NamespaceBinding;ZLscala/collection/immutable/Seq;)V
  #211 = String             #27           // suiteName
  #212 = NameAndType        #27:#59       // suiteName:()Ljava/lang/String;
  #213 = Methodref          #2.#212       // org/scalatest/events/TestPending.suiteName:()Ljava/lang/String;
  #214 = String             #29           // suiteId
  #215 = NameAndType        #29:#59       // suiteId:()Ljava/lang/String;
  #216 = Methodref          #2.#215       // org/scalatest/events/TestPending.suiteId:()Ljava/lang/String;
  #217 = String             #30           // suiteClassName
  #218 = Utf8               EventXmlHelper
  #219 = Utf8               ()Lorg/scalatest/events/Event$EventXmlHelper$;
  #220 = NameAndType        #218:#219     // EventXmlHelper:()Lorg/scalatest/events/Event$EventXmlHelper$;
  #221 = Methodref          #2.#220       // org/scalatest/events/TestPending.EventXmlHelper:()Lorg/scalatest/events/Event$EventXmlHelper$;
  #222 = NameAndType        #30:#63       // suiteClassName:()Lscala/Option;
  #223 = Methodref          #2.#222       // org/scalatest/events/TestPending.suiteClassName:()Lscala/Option;
  #224 = Utf8               stringOption
  #225 = Utf8               (Lscala/Option;)Ljava/lang/String;
  #226 = NameAndType        #224:#225     // stringOption:(Lscala/Option;)Ljava/lang/String;
  #227 = Methodref          #23.#226      // org/scalatest/events/Event$EventXmlHelper$.stringOption:(Lscala/Option;)Ljava/lang/String;
  #228 = String             #38           // duration
  #229 = NameAndType        #38:#63       // duration:()Lscala/Option;
  #230 = Methodref          #2.#229       // org/scalatest/events/TestPending.duration:()Lscala/Option;
  #231 = Utf8               longOption
  #232 = NameAndType        #231:#225     // longOption:(Lscala/Option;)Ljava/lang/String;
  #233 = Methodref          #23.#232      // org/scalatest/events/Event$EventXmlHelper$.longOption:(Lscala/Option;)Ljava/lang/String;
  #234 = String             #33           // testName
  #235 = NameAndType        #33:#59       // testName:()Ljava/lang/String;
  #236 = Methodref          #2.#235       // org/scalatest/events/TestPending.testName:()Ljava/lang/String;
  #237 = String             #34           // testText
  #238 = NameAndType        #34:#59       // testText:()Ljava/lang/String;
  #239 = Methodref          #2.#238       // org/scalatest/events/TestPending.testText:()Ljava/lang/String;
  #240 = String             #35           // recordedEvents
  #241 = NameAndType        #35:#132      // recordedEvents:()Lscala/collection/immutable/IndexedSeq;
  #242 = Methodref          #2.#241       // org/scalatest/events/TestPending.recordedEvents:()Lscala/collection/immutable/IndexedSeq;
  #243 = Utf8               (Ljava/lang/Object;)Ljava/lang/Object;
  #244 = MethodType         #243          //  (Ljava/lang/Object;)Ljava/lang/Object;
  #245 = Utf8               $anonfun$toXml$3
  #246 = Utf8               (Lorg/scalatest/events/RecordableEvent;)Lscala/xml/Elem;
  #247 = NameAndType        #245:#246     // $anonfun$toXml$3:(Lorg/scalatest/events/RecordableEvent;)Lscala/xml/Elem;
  #248 = Methodref          #2.#247       // org/scalatest/events/TestPending.$anonfun$toXml$3:(Lorg/scalatest/events/RecordableEvent;)Lscala/xml/Elem;
  #249 = MethodHandle       6:#248        // REF_invokeStatic org/scalatest/events/TestPending.$anonfun$toXml$3:(Lorg/scalatest/events/RecordableEvent;)Lscala/xml/Elem;
  #250 = MethodType         #246          //  (Lorg/scalatest/events/RecordableEvent;)Lscala/xml/Elem;
  #251 = Integer            5
  #252 = Integer            1
  #253 = Utf8               java/lang/invoke/LambdaMetafactory
  #254 = Class              #253          // java/lang/invoke/LambdaMetafactory
  #255 = Utf8               altMetafactory
  #256 = Utf8               (Ljava/lang/invoke/MethodHandles$Lookup;Ljava/lang/String;Ljava/lang/invoke/MethodType;[Ljava/lang/Object;)Ljava/lang/invoke/CallSite;
  #257 = NameAndType        #255:#256     // altMetafactory:(Ljava/lang/invoke/MethodHandles$Lookup;Ljava/lang/String;Ljava/lang/invoke/MethodType;[Ljava/lang/Object;)Ljava/lang/invoke/CallSite;
  #258 = Methodref          #254.#257     // java/lang/invoke/LambdaMetafactory.altMetafactory:(Ljava/lang/invoke/MethodHandles$Lookup;Ljava/lang/String;Ljava/lang/invoke/MethodType;[Ljava/lang/Object;)Ljava/lang/invoke/CallSite;
  #259 = MethodHandle       6:#258        // REF_invokeStatic java/lang/invoke/LambdaMetafactory.altMetafactory:(Ljava/lang/invoke/MethodHandles$Lookup;Ljava/lang/String;Ljava/lang/invoke/MethodType;[Ljava/lang/Object;)Ljava/lang/invoke/CallSite;
  #260 = NameAndType        #103:#109     // apply:()Lscala/Function1;
  #261 = InvokeDynamic      #0:#260       // #0:apply:()Lscala/Function1;
  #262 = Utf8               scala/collection/immutable/IndexedSeq
  #263 = Class              #262          // scala/collection/immutable/IndexedSeq
  #264 = Utf8               map
  #265 = Utf8               (Lscala/Function1;)Ljava/lang/Object;
  #266 = NameAndType        #264:#265     // map:(Lscala/Function1;)Ljava/lang/Object;
  #267 = InterfaceMethodref #263.#266     // scala/collection/immutable/IndexedSeq.map:(Lscala/Function1;)Ljava/lang/Object;
  #268 = String             #40           // formatter
  #269 = NameAndType        #40:#63       // formatter:()Lscala/Option;
  #270 = Methodref          #2.#269       // org/scalatest/events/TestPending.formatter:()Lscala/Option;
  #271 = Utf8               formatterOption
  #272 = Utf8               (Lscala/Option;)Ljava/lang/Object;
  #273 = NameAndType        #271:#272     // formatterOption:(Lscala/Option;)Ljava/lang/Object;
  #274 = Methodref          #23.#273      // org/scalatest/events/Event$EventXmlHelper$.formatterOption:(Lscala/Option;)Ljava/lang/Object;
  #275 = String             #42           // location
  #276 = NameAndType        #42:#63       // location:()Lscala/Option;
  #277 = Methodref          #2.#276       // org/scalatest/events/TestPending.location:()Lscala/Option;
  #278 = Utf8               locationOption
  #279 = NameAndType        #278:#272     // locationOption:(Lscala/Option;)Ljava/lang/Object;
  #280 = Methodref          #23.#279      // org/scalatest/events/Event$EventXmlHelper$.locationOption:(Lscala/Option;)Ljava/lang/Object;
  #281 = String             #45           // threadName
  #282 = NameAndType        #45:#59       // threadName:()Ljava/lang/String;
  #283 = Methodref          #2.#282       // org/scalatest/events/TestPending.threadName:()Ljava/lang/String;
  #284 = String             #46           // timeStamp
  #285 = NameAndType        #46:#49       // timeStamp:()J
  #286 = Methodref          #2.#285       // org/scalatest/events/TestPending.timeStamp:()J
  #287 = Utf8               boxToLong
  #288 = Utf8               (J)Ljava/lang/Long;
  #289 = NameAndType        #287:#288     // boxToLong:(J)Ljava/lang/Long;
  #290 = Methodref          #199.#289     // scala/runtime/BoxesRunTime.boxToLong:(J)Ljava/lang/Long;
  #291 = Utf8               \n
  #292 = String             #291          // \n
  #293 = Utf8               $buf
  #294 = Utf8               Lscala/xml/NodeBuffer;
  #295 = Utf8               toJson
  #296 = Utf8               scala/collection/StringOps$
  #297 = Class              #296          // scala/collection/StringOps$
  #298 = Utf8               Lscala/collection/StringOps$;
  #299 = NameAndType        #52:#298      // MODULE$:Lscala/collection/StringOps$;
  #300 = Fieldref           #297.#299     // scala/collection/StringOps$.MODULE$:Lscala/collection/StringOps$;
  #301 = Utf8               scala/Predef$
  #302 = Class              #301          // scala/Predef$
  #303 = Utf8               Lscala/Predef$;
  #304 = NameAndType        #52:#303      // MODULE$:Lscala/Predef$;
  #305 = Fieldref           #302.#304     // scala/Predef$.MODULE$:Lscala/Predef$;
  #306 = Utf8               java/lang/StringBuilder
  #307 = Class              #306          // java/lang/StringBuilder
  #308 = Integer            216
  #309 = Utf8               (I)V
  #310 = NameAndType        #171:#309     // "<init>":(I)V
  #311 = Methodref          #307.#310     // java/lang/StringBuilder."<init>":(I)V
  #312 = Utf8               { \"eventType\": \"TestPending\", \"ordinal\":
  #313 = String             #312          // { \"eventType\": \"TestPending\", \"ordinal\":
  #314 = Utf8               append
  #315 = Utf8               (Ljava/lang/String;)Ljava/lang/StringBuilder;
  #316 = NameAndType        #314:#315     // append:(Ljava/lang/String;)Ljava/lang/StringBuilder;
  #317 = Methodref          #307.#316     // java/lang/StringBuilder.append:(Ljava/lang/String;)Ljava/lang/StringBuilder;
  #318 = Utf8               (I)Ljava/lang/StringBuilder;
  #319 = NameAndType        #314:#318     // append:(I)Ljava/lang/StringBuilder;
  #320 = Methodref          #307.#319     // java/lang/StringBuilder.append:(I)Ljava/lang/StringBuilder;
  #321 = Utf8               , \"suiteName\":
  #322 = String             #321          // , \"suiteName\":
  #323 = Utf8               EventJsonHelper
  #324 = Utf8               ()Lorg/scalatest/events/Event$EventJsonHelper$;
  #325 = NameAndType        #323:#324     // EventJsonHelper:()Lorg/scalatest/events/Event$EventJsonHelper$;
  #326 = Methodref          #2.#325       // org/scalatest/events/TestPending.EventJsonHelper:()Lorg/scalatest/events/Event$EventJsonHelper$;
  #327 = Utf8               string
  #328 = Utf8               (Ljava/lang/String;)Ljava/lang/String;
  #329 = NameAndType        #327:#328     // string:(Ljava/lang/String;)Ljava/lang/String;
  #330 = Methodref          #20.#329      // org/scalatest/events/Event$EventJsonHelper$.string:(Ljava/lang/String;)Ljava/lang/String;
  #331 = Utf8               , \"suiteId\":
  #332 = String             #331          // , \"suiteId\":
  #333 = Utf8               , \"suiteClassName\":
  #334 = String             #333          // , \"suiteClassName\":
  #335 = Methodref          #20.#226      // org/scalatest/events/Event$EventJsonHelper$.stringOption:(Lscala/Option;)Ljava/lang/String;
  #336 = Utf8               , \"duration\":
  #337 = String             #336          // , \"duration\":
  #338 = Utf8               ()Ljava/lang/Object;
  #339 = MethodType         #338          //  ()Ljava/lang/Object;
  #340 = Utf8               $anonfun$toJson$5
  #341 = NameAndType        #340:#59      // $anonfun$toJson$5:()Ljava/lang/String;
  #342 = Methodref          #2.#341       // org/scalatest/events/TestPending.$anonfun$toJson$5:()Ljava/lang/String;
  #343 = MethodHandle       6:#342        // REF_invokeStatic org/scalatest/events/TestPending.$anonfun$toJson$5:()Ljava/lang/String;
  #344 = MethodType         #59           //  ()Ljava/lang/String;
  #345 = Utf8               ()Lscala/Function0;
  #346 = NameAndType        #103:#345     // apply:()Lscala/Function0;
  #347 = InvokeDynamic      #1:#346       // #1:apply:()Lscala/Function0;
  #348 = Utf8               scala/Option
  #349 = Class              #348          // scala/Option
  #350 = Utf8               getOrElse
  #351 = Utf8               (Lscala/Function0;)Ljava/lang/Object;
  #352 = NameAndType        #350:#351     // getOrElse:(Lscala/Function0;)Ljava/lang/Object;
  #353 = Methodref          #349.#352     // scala/Option.getOrElse:(Lscala/Function0;)Ljava/lang/Object;
  #354 = Utf8               (Ljava/lang/Object;)Ljava/lang/StringBuilder;
  #355 = NameAndType        #314:#354     // append:(Ljava/lang/Object;)Ljava/lang/StringBuilder;
  #356 = Methodref          #307.#355     // java/lang/StringBuilder.append:(Ljava/lang/Object;)Ljava/lang/StringBuilder;
  #357 = Utf8               , \"testName\":
  #358 = String             #357          // , \"testName\":
  #359 = Utf8               , \"testText\":
  #360 = String             #359          // , \"testText\":
  #361 = Utf8               , \"recordedEvents\" : [
  #362 = String             #361          // , \"recordedEvents\" : [
  #363 = Utf8               $anonfun$toJson$6
  #364 = Utf8               (Lorg/scalatest/events/RecordableEvent;)Ljava/lang/String;
  #365 = NameAndType        #363:#364     // $anonfun$toJson$6:(Lorg/scalatest/events/RecordableEvent;)Ljava/lang/String;
  #366 = Methodref          #2.#365       // org/scalatest/events/TestPending.$anonfun$toJson$6:(Lorg/scalatest/events/RecordableEvent;)Ljava/lang/String;
  #367 = MethodHandle       6:#366        // REF_invokeStatic org/scalatest/events/TestPending.$anonfun$toJson$6:(Lorg/scalatest/events/RecordableEvent;)Ljava/lang/String;
  #368 = MethodType         #364          //  (Lorg/scalatest/events/RecordableEvent;)Ljava/lang/String;
  #369 = InvokeDynamic      #2:#260       // #2:apply:()Lscala/Function1;
  #370 = Utf8               scala/collection/IterableOnceOps
  #371 = Class              #370          // scala/collection/IterableOnceOps
  #372 = Utf8               ,
  #373 = String             #372          // ,
  #374 = Utf8               mkString
  #375 = NameAndType        #374:#328     // mkString:(Ljava/lang/String;)Ljava/lang/String;
  #376 = InterfaceMethodref #371.#375     // scala/collection/IterableOnceOps.mkString:(Ljava/lang/String;)Ljava/lang/String;
  #377 = Utf8               ], \"formatter\":
  #378 = String             #377          // ], \"formatter\":
  #379 = NameAndType        #271:#225     // formatterOption:(Lscala/Option;)Ljava/lang/String;
  #380 = Methodref          #20.#379      // org/scalatest/events/Event$EventJsonHelper$.formatterOption:(Lscala/Option;)Ljava/lang/String;
  #381 = Utf8               , \"location\":
  #382 = String             #381          // , \"location\":
  #383 = NameAndType        #278:#225     // locationOption:(Lscala/Option;)Ljava/lang/String;
  #384 = Methodref          #20.#383      // org/scalatest/events/Event$EventJsonHelper$.locationOption:(Lscala/Option;)Ljava/lang/String;
  #385 = Utf8               , \"threadName\":
  #386 = String             #385          // , \"threadName\":
  #387 = Utf8               , \"timeStamp\":
  #388 = String             #387          // , \"timeStamp\":
  #389 = Utf8               (J)Ljava/lang/StringBuilder;
  #390 = NameAndType        #314:#389     // append:(J)Ljava/lang/StringBuilder;
  #391 = Methodref          #307.#390     // java/lang/StringBuilder.append:(J)Ljava/lang/StringBuilder;
  #392 = Utf8                }
  #393 = String             #392          //  }
  #394 = Utf8               toString
  #395 = NameAndType        #394:#59      // toString:()Ljava/lang/String;
  #396 = Methodref          #307.#395     // java/lang/StringBuilder.toString:()Ljava/lang/String;
  #397 = Utf8               augmentString
  #398 = NameAndType        #397:#328     // augmentString:(Ljava/lang/String;)Ljava/lang/String;
  #399 = Methodref          #302.#398     // scala/Predef$.augmentString:(Ljava/lang/String;)Ljava/lang/String;
  #400 = Utf8               stripMargin$extension
  #401 = NameAndType        #400:#328     // stripMargin$extension:(Ljava/lang/String;)Ljava/lang/String;
  #402 = Methodref          #297.#401     // scala/collection/StringOps$.stripMargin$extension:(Ljava/lang/String;)Ljava/lang/String;
  #403 = Utf8               withPayload
  #404 = Utf8               (Lscala/Option;)Lorg/scalatest/events/TestPending;
  #405 = Utf8               (Lscala/Option<Ljava/lang/Object;>;)Lorg/scalatest/events/TestPending;
  #406 = Utf8               newPayload
  #407 = Utf8               copy$default$1
  #408 = NameAndType        #407:#117     // copy$default$1:()Lorg/scalatest/events/Ordinal;
  #409 = Methodref          #2.#408       // org/scalatest/events/TestPending.copy$default$1:()Lorg/scalatest/events/Ordinal;
  #410 = Utf8               copy$default$2
  #411 = NameAndType        #410:#59      // copy$default$2:()Ljava/lang/String;
  #412 = Methodref          #2.#411       // org/scalatest/events/TestPending.copy$default$2:()Ljava/lang/String;
  #413 = Utf8               copy$default$3
  #414 = NameAndType        #413:#59      // copy$default$3:()Ljava/lang/String;
  #415 = Methodref          #2.#414       // org/scalatest/events/TestPending.copy$default$3:()Ljava/lang/String;
  #416 = Utf8               copy$default$4
  #417 = NameAndType        #416:#63      // copy$default$4:()Lscala/Option;
  #418 = Methodref          #2.#417       // org/scalatest/events/TestPending.copy$default$4:()Lscala/Option;
  #419 = Utf8               copy$default$5
  #420 = NameAndType        #419:#59      // copy$default$5:()Ljava/lang/String;
  #421 = Methodref          #2.#420       // org/scalatest/events/TestPending.copy$default$5:()Ljava/lang/String;
  #422 = Utf8               copy$default$6
  #423 = NameAndType        #422:#59      // copy$default$6:()Ljava/lang/String;
  #424 = Methodref          #2.#423       // org/scalatest/events/TestPending.copy$default$6:()Ljava/lang/String;
  #425 = Utf8               copy$default$7
  #426 = NameAndType        #425:#132     // copy$default$7:()Lscala/collection/immutable/IndexedSeq;
  #427 = Methodref          #2.#426       // org/scalatest/events/TestPending.copy$default$7:()Lscala/collection/immutable/IndexedSeq;
  #428 = Utf8               copy$default$8
  #429 = NameAndType        #428:#63      // copy$default$8:()Lscala/Option;
  #430 = Methodref          #2.#429       // org/scalatest/events/TestPending.copy$default$8:()Lscala/Option;
  #431 = Utf8               copy$default$9
  #432 = NameAndType        #431:#63      // copy$default$9:()Lscala/Option;
  #433 = Methodref          #2.#432       // org/scalatest/events/TestPending.copy$default$9:()Lscala/Option;
  #434 = Utf8               copy$default$10
  #435 = NameAndType        #434:#63      // copy$default$10:()Lscala/Option;
  #436 = Methodref          #2.#435       // org/scalatest/events/TestPending.copy$default$10:()Lscala/Option;
  #437 = Utf8               copy$default$12
  #438 = NameAndType        #437:#59      // copy$default$12:()Ljava/lang/String;
  #439 = Methodref          #2.#438       // org/scalatest/events/TestPending.copy$default$12:()Ljava/lang/String;
  #440 = Utf8               copy$default$13
  #441 = NameAndType        #440:#49      // copy$default$13:()J
  #442 = Methodref          #2.#441       // org/scalatest/events/TestPending.copy$default$13:()J
  #443 = Utf8               copy
  #444 = NameAndType        #443:#104     // copy:(Lorg/scalatest/events/Ordinal;Ljava/lang/String;Ljava/lang/String;Lscala/Option;Ljava/lang/String;Ljava/lang/String;Lscala/collection/immutable/IndexedSeq;Lscala/Option;Lscala/Option;Lscala/Option;Lscala/Option;Ljava/lang/String;J)Lorg/scalatest/events/TestPending;
  #445 = Methodref          #2.#444       // org/scalatest/events/TestPending.copy:(Lorg/scalatest/events/Ordinal;Ljava/lang/String;Ljava/lang/String;Lscala/Option;Ljava/lang/String;Ljava/lang/String;Lscala/collection/immutable/IndexedSeq;Lscala/Option;Lscala/Option;Lscala/Option;Lscala/Option;Ljava/lang/String;J)Lorg/scalatest/events/TestPending;
  #446 = Utf8               x$1
  #447 = Utf8               x$2
  #448 = Utf8               x$3
  #449 = Utf8               x$4
  #450 = Utf8               x$5
  #451 = Utf8               x$6
  #452 = Utf8               x$7
  #453 = Utf8               x$8
  #454 = Utf8               x$9
  #455 = Utf8               x$10
  #456 = Utf8               x$11
  #457 = Utf8               x$12
  #458 = Utf8               x$13
  #459 = Utf8               (Lorg/scalatest/events/Ordinal;Ljava/lang/String;Ljava/lang/String;Lscala/Option;Ljava/lang/String;Ljava/lang/String;Lscala/collection/immutable/IndexedSeq;Lscala/Option;Lscala/Option;Lscala/Option;Lscala/Option;Ljava/lang/String;J)V
  #460 = NameAndType        #171:#459     // "<init>":(Lorg/scalatest/events/Ordinal;Ljava/lang/String;Ljava/lang/String;Lscala/Option;Ljava/lang/String;Ljava/lang/String;Lscala/collection/immutable/IndexedSeq;Lscala/Option;Lscala/Option;Lscala/Option;Lscala/Option;Ljava/lang/String;J)V
  #461 = Methodref          #2.#460       // org/scalatest/events/TestPending."<init>":(Lorg/scalatest/events/Ordinal;Ljava/lang/String;Ljava/lang/String;Lscala/Option;Ljava/lang/String;Ljava/lang/String;Lscala/collection/immutable/IndexedSeq;Lscala/Option;Lscala/Option;Lscala/Option;Lscala/Option;Ljava/lang/String;J)V
  #462 = Utf8               copy$default$11
  #463 = NameAndType        #44:#63       // payload:()Lscala/Option;
  #464 = Methodref          #2.#463       // org/scalatest/events/TestPending.payload:()Lscala/Option;
  #465 = Utf8               productPrefix
  #466 = Utf8               productArity
  #467 = Utf8               productElement
  #468 = Utf8               (I)Ljava/lang/Object;
  #469 = Utf8               scala/runtime/Statics
  #470 = Class              #469          // scala/runtime/Statics
  #471 = Utf8               ioobe
  #472 = NameAndType        #471:#468     // ioobe:(I)Ljava/lang/Object;
  #473 = Methodref          #470.#472     // scala/runtime/Statics.ioobe:(I)Ljava/lang/Object;
  #474 = Utf8               I
  #475 = Utf8               java/lang/Object
  #476 = Class              #475          // java/lang/Object
  #477 = Utf8               productIterator
  #478 = Utf8               ()Lscala/collection/Iterator;
  #479 = Utf8               ()Lscala/collection/Iterator<Ljava/lang/Object;>;
  #480 = Utf8               scala/runtime/ScalaRunTime$
  #481 = Class              #480          // scala/runtime/ScalaRunTime$
  #482 = Utf8               Lscala/runtime/ScalaRunTime$;
  #483 = NameAndType        #52:#482      // MODULE$:Lscala/runtime/ScalaRunTime$;
  #484 = Fieldref           #481.#483     // scala/runtime/ScalaRunTime$.MODULE$:Lscala/runtime/ScalaRunTime$;
  #485 = Utf8               typedProductIterator
  #486 = Utf8               (Lscala/Product;)Lscala/collection/Iterator;
  #487 = NameAndType        #485:#486     // typedProductIterator:(Lscala/Product;)Lscala/collection/Iterator;
  #488 = Methodref          #481.#487     // scala/runtime/ScalaRunTime$.typedProductIterator:(Lscala/Product;)Lscala/collection/Iterator;
  #489 = Utf8               canEqual
  #490 = Utf8               (Ljava/lang/Object;)Z
  #491 = Utf8               Ljava/lang/Object;
  #492 = Utf8               productElementName
  #493 = Utf8               (I)Ljava/lang/String;
  #494 = String             #44           // payload
  #495 = Utf8               java/lang/String
  #496 = Class              #495          // java/lang/String
  #497 = Utf8               hashCode
  #498 = Integer            -889275714
  #499 = NameAndType        #465:#59      // productPrefix:()Ljava/lang/String;
  #500 = Methodref          #2.#499       // org/scalatest/events/TestPending.productPrefix:()Ljava/lang/String;
  #501 = NameAndType        #497:#195     // hashCode:()I
  #502 = Methodref          #496.#501     // java/lang/String.hashCode:()I
  #503 = Utf8               mix
  #504 = Utf8               (II)I
  #505 = NameAndType        #503:#504     // mix:(II)I
  #506 = Methodref          #470.#505     // scala/runtime/Statics.mix:(II)I
  #507 = Utf8               anyHash
  #508 = Utf8               (Ljava/lang/Object;)I
  #509 = NameAndType        #507:#508     // anyHash:(Ljava/lang/Object;)I
  #510 = Methodref          #470.#509     // scala/runtime/Statics.anyHash:(Ljava/lang/Object;)I
  #511 = Utf8               longHash
  #512 = Utf8               (J)I
  #513 = NameAndType        #511:#512     // longHash:(J)I
  #514 = Methodref          #470.#513     // scala/runtime/Statics.longHash:(J)I
  #515 = Utf8               finalizeHash
  #516 = NameAndType        #515:#504     // finalizeHash:(II)I
  #517 = Methodref          #470.#516     // scala/runtime/Statics.finalizeHash:(II)I
  #518 = Utf8               _toString
  #519 = Utf8               (Lscala/Product;)Ljava/lang/String;
  #520 = NameAndType        #518:#519     // _toString:(Lscala/Product;)Ljava/lang/String;
  #521 = Methodref          #481.#520     // scala/runtime/ScalaRunTime$._toString:(Lscala/Product;)Ljava/lang/String;
  #522 = Utf8               equals
  #523 = NameAndType        #522:#490     // equals:(Ljava/lang/Object;)Z
  #524 = Methodref          #476.#523     // java/lang/Object.equals:(Ljava/lang/Object;)Z
  #525 = Utf8               (Lscala/Option;)Lorg/scalatest/events/Event;
  #526 = NameAndType        #403:#404     // withPayload:(Lscala/Option;)Lorg/scalatest/events/TestPending;
  #527 = Methodref          #2.#526       // org/scalatest/events/TestPending.withPayload:(Lscala/Option;)Lorg/scalatest/events/TestPending;
  #528 = NameAndType        #148:#149     // toXml:()Lscala/xml/Elem;
  #529 = Methodref          #4.#528       // org/scalatest/events/Event.toXml:()Lscala/xml/Elem;
  #530 = Utf8               Lorg/scalatest/events/RecordableEvent;
  #531 = Utf8               null
  #532 = String             #531          // null
  #533 = NameAndType        #295:#59      // toJson:()Ljava/lang/String;
  #534 = Methodref          #4.#533       // org/scalatest/events/Event.toJson:()Ljava/lang/String;
  #535 = Utf8               (Lorg/scalatest/events/Ordinal;Ljava/lang/String;Ljava/lang/String;Lscala/Option<Ljava/lang/String;>;Ljava/lang/String;Ljava/lang/String;Lscala/collection/immutable/IndexedSeq<Lorg/scalatest/events/RecordableEvent;>;Lscala/Option<Ljava/lang/Object;>;Lscala/Option<Lorg/scalatest/events/Formatter;>;Lscala/Option<Lorg/scalatest/events/Location;>;Lscala/Option<Ljava/lang/Object;>;Ljava/lang/String;J)V
  #536 = Methodref          #4.#173       // org/scalatest/events/Event."<init>":()V
  #537 = Utf8               org/scalactic/Requirements$
  #538 = Class              #537          // org/scalactic/Requirements$
  #539 = Utf8               Lorg/scalactic/Requirements$;
  #540 = NameAndType        #52:#539      // MODULE$:Lorg/scalactic/Requirements$;
  #541 = Fieldref           #538.#540     // org/scalactic/Requirements$.MODULE$:Lorg/scalactic/Requirements$;
  #542 = Utf8               requirementsHelper
  #543 = Utf8               ()Lorg/scalactic/Requirements$RequirementsHelper;
  #544 = NameAndType        #542:#543     // requirementsHelper:()Lorg/scalactic/Requirements$RequirementsHelper;
  #545 = Methodref          #538.#544     // org/scalactic/Requirements$.requirementsHelper:()Lorg/scalactic/Requirements$RequirementsHelper;
  #546 = Utf8               TestPending.this.ordinal
  #547 = String             #546          // TestPending.this.ordinal
  #548 = Utf8               TestPending.this.suiteName
  #549 = String             #548          // TestPending.this.suiteName
  #550 = Utf8               TestPending.this.suiteId
  #551 = String             #550          // TestPending.this.suiteId
  #552 = Utf8               TestPending.this.suiteClassName
  #553 = String             #552          // TestPending.this.suiteClassName
  #554 = Utf8               TestPending.this.testName
  #555 = String             #554          // TestPending.this.testName
  #556 = Utf8               TestPending.this.testText
  #557 = String             #556          // TestPending.this.testText
  #558 = Utf8               TestPending.this.duration
  #559 = String             #558          // TestPending.this.duration
  #560 = Utf8               TestPending.this.formatter
  #561 = String             #560          // TestPending.this.formatter
  #562 = Utf8               TestPending.this.location
  #563 = String             #562          // TestPending.this.location
  #564 = Utf8               TestPending.this.payload
  #565 = String             #564          // TestPending.this.payload
  #566 = Utf8               TestPending.this.threadName
  #567 = String             #566          // TestPending.this.threadName
  #568 = Utf8               [Ljava/lang/Object;
  #569 = Class              #568          // "[Ljava/lang/Object;"
  #570 = Utf8               [Ljava/lang/String;
  #571 = Class              #570          // "[Ljava/lang/String;"
  #572 = Utf8               org/scalactic/Prettifier$
  #573 = Class              #572          // org/scalactic/Prettifier$
  #574 = Utf8               Lorg/scalactic/Prettifier$;
  #575 = NameAndType        #52:#574      // MODULE$:Lorg/scalactic/Prettifier$;
  #576 = Fieldref           #573.#575     // org/scalactic/Prettifier$.MODULE$:Lorg/scalactic/Prettifier$;
  #577 = Utf8               default
  #578 = Utf8               ()Lorg/scalactic/Prettifier;
  #579 = NameAndType        #577:#578     // default:()Lorg/scalactic/Prettifier;
  #580 = Methodref          #573.#579     // org/scalactic/Prettifier$.default:()Lorg/scalactic/Prettifier;
  #581 = Utf8               org/scalactic/source/Position
  #582 = Class              #581          // org/scalactic/source/Position
  #583 = String             #5            // Event.scala
  #584 = Utf8               Please set the environment variable SCALACTIC_FILL_FILE_PATHNAMES to yes at compile time to enable this feature.
  #585 = String             #584          // Please set the environment variable SCALACTIC_FILL_FILE_PATHNAMES to yes at compile time to enable this feature.
  #586 = Utf8               (Ljava/lang/String;Ljava/lang/String;I)V
  #587 = NameAndType        #171:#586     // "<init>":(Ljava/lang/String;Ljava/lang/String;I)V
  #588 = Methodref          #582.#587     // org/scalactic/source/Position."<init>":(Ljava/lang/String;Ljava/lang/String;I)V
  #589 = Utf8               macroRequireNonNull
  #590 = Utf8               ([Ljava/lang/String;[Ljava/lang/Object;Lorg/scalactic/Prettifier;Lorg/scalactic/source/Position;)V
  #591 = NameAndType        #589:#590     // macroRequireNonNull:([Ljava/lang/String;[Ljava/lang/Object;Lorg/scalactic/Prettifier;Lorg/scalactic/source/Position;)V
  #592 = Methodref          #15.#591      // org/scalactic/Requirements$RequirementsHelper.macroRequireNonNull:([Ljava/lang/String;[Ljava/lang/Object;Lorg/scalactic/Prettifier;Lorg/scalactic/source/Position;)V
  #593 = Utf8               $deserializeLambda$
  #594 = Utf8               (Ljava/lang/invoke/SerializedLambda;)Ljava/lang/Object;
  #595 = Utf8               scala/runtime/LambdaDeserialize
  #596 = Class              #595          // scala/runtime/LambdaDeserialize
  #597 = Utf8               bootstrap
  #598 = Utf8               (Ljava/lang/invoke/MethodHandles$Lookup;Ljava/lang/String;Ljava/lang/invoke/MethodType;[Ljava/lang/invoke/MethodHandle;)Ljava/lang/invoke/CallSite;
  #599 = NameAndType        #597:#598     // bootstrap:(Ljava/lang/invoke/MethodHandles$Lookup;Ljava/lang/String;Ljava/lang/invoke/MethodType;[Ljava/lang/invoke/MethodHandle;)Ljava/lang/invoke/CallSite;
  #600 = Methodref          #596.#599     // scala/runtime/LambdaDeserialize.bootstrap:(Ljava/lang/invoke/MethodHandles$Lookup;Ljava/lang/String;Ljava/lang/invoke/MethodType;[Ljava/lang/invoke/MethodHandle;)Ljava/lang/invoke/CallSite;
  #601 = MethodHandle       6:#600        // REF_invokeStatic scala/runtime/LambdaDeserialize.bootstrap:(Ljava/lang/invoke/MethodHandles$Lookup;Ljava/lang/String;Ljava/lang/invoke/MethodType;[Ljava/lang/invoke/MethodHandle;)Ljava/lang/invoke/CallSite;
  #602 = Utf8               lambdaDeserialize
  #603 = NameAndType        #602:#594     // lambdaDeserialize:(Ljava/lang/invoke/SerializedLambda;)Ljava/lang/Object;
  #604 = InvokeDynamic      #3:#603       // #3:lambdaDeserialize:(Ljava/lang/invoke/SerializedLambda;)Ljava/lang/Object;
  #605 = Utf8               Signature
  #606 = Utf8               Code
  #607 = Utf8               LocalVariableTable
  #608 = Utf8               MethodParameters
  #609 = Utf8               LineNumberTable
  #610 = Utf8               StackMapTable
  #611 = Utf8               InnerClasses
  #612 = Utf8               SourceFile
  #613 = Utf8               RuntimeVisibleAnnotations
  #614 = Utf8               BootstrapMethods
  #615 = Utf8               ScalaInlineInfo
  #616 = Utf8               ScalaSig
{
  private final org.scalatest.events.Ordinal ordinal;
    descriptor: Lorg/scalatest/events/Ordinal;
    flags: (0x0012) ACC_PRIVATE, ACC_FINAL

  private final java.lang.String suiteName;
    descriptor: Ljava/lang/String;
    flags: (0x0012) ACC_PRIVATE, ACC_FINAL

  private final java.lang.String suiteId;
    descriptor: Ljava/lang/String;
    flags: (0x0012) ACC_PRIVATE, ACC_FINAL

  private final scala.Option<java.lang.String> suiteClassName;
    descriptor: Lscala/Option;
    flags: (0x0012) ACC_PRIVATE, ACC_FINAL
    Signature: #32                          // Lscala/Option<Ljava/lang/String;>;

  private final java.lang.String testName;
    descriptor: Ljava/lang/String;
    flags: (0x0012) ACC_PRIVATE, ACC_FINAL

  private final java.lang.String testText;
    descriptor: Ljava/lang/String;
    flags: (0x0012) ACC_PRIVATE, ACC_FINAL

  private final scala.collection.immutable.IndexedSeq<org.scalatest.events.RecordableEvent> recordedEvents;
    descriptor: Lscala/collection/immutable/IndexedSeq;
    flags: (0x0012) ACC_PRIVATE, ACC_FINAL
    Signature: #37                          // Lscala/collection/immutable/IndexedSeq<Lorg/scalatest/events/RecordableEvent;>;

  private final scala.Option<java.lang.Object> duration;
    descriptor: Lscala/Option;
    flags: (0x0012) ACC_PRIVATE, ACC_FINAL
    Signature: #39                          // Lscala/Option<Ljava/lang/Object;>;

  private final scala.Option<org.scalatest.events.Formatter> formatter;
    descriptor: Lscala/Option;
    flags: (0x0012) ACC_PRIVATE, ACC_FINAL
    Signature: #41                          // Lscala/Option<Lorg/scalatest/events/Formatter;>;

  private final scala.Option<org.scalatest.events.Location> location;
    descriptor: Lscala/Option;
    flags: (0x0012) ACC_PRIVATE, ACC_FINAL
    Signature: #43                          // Lscala/Option<Lorg/scalatest/events/Location;>;

  private final scala.Option<java.lang.Object> payload;
    descriptor: Lscala/Option;
    flags: (0x0012) ACC_PRIVATE, ACC_FINAL
    Signature: #39                          // Lscala/Option<Ljava/lang/Object;>;

  private final java.lang.String threadName;
    descriptor: Ljava/lang/String;
    flags: (0x0012) ACC_PRIVATE, ACC_FINAL

  private final long timeStamp;
    descriptor: J
    flags: (0x0012) ACC_PRIVATE, ACC_FINAL

  public static long $lessinit$greater$default$13();
    descriptor: ()J
    flags: (0x0009) ACC_PUBLIC, ACC_STATIC
    Code:
      stack=2, locals=0, args_size=0
         0: getstatic     #55                 // Field org/scalatest/events/TestPending$.MODULE$:Lorg/scalatest/events/TestPending$;
         3: invokevirtual #57                 // Method org/scalatest/events/TestPending$.$lessinit$greater$default$13:()J
         6: lreturn

  public static java.lang.String $lessinit$greater$default$12();
    descriptor: ()Ljava/lang/String;
    flags: (0x0009) ACC_PUBLIC, ACC_STATIC
    Code:
      stack=1, locals=0, args_size=0
         0: getstatic     #55                 // Field org/scalatest/events/TestPending$.MODULE$:Lorg/scalatest/events/TestPending$;
         3: invokevirtual #61                 // Method org/scalatest/events/TestPending$.$lessinit$greater$default$12:()Ljava/lang/String;
         6: areturn

  public static scala.Option<java.lang.Object> $lessinit$greater$default$11();
    descriptor: ()Lscala/Option;
    flags: (0x0009) ACC_PUBLIC, ACC_STATIC
    Code:
      stack=1, locals=0, args_size=0
         0: getstatic     #55                 // Field org/scalatest/events/TestPending$.MODULE$:Lorg/scalatest/events/TestPending$;
         3: invokevirtual #66                 // Method org/scalatest/events/TestPending$.$lessinit$greater$default$11:()Lscala/Option;
         6: areturn
    Signature: #64                          // ()Lscala/Option<Ljava/lang/Object;>;

  public static scala.Option<org.scalatest.events.Location> $lessinit$greater$default$10();
    descriptor: ()Lscala/Option;
    flags: (0x0009) ACC_PUBLIC, ACC_STATIC
    Code:
      stack=1, locals=0, args_size=0
         0: getstatic     #55                 // Field org/scalatest/events/TestPending$.MODULE$:Lorg/scalatest/events/TestPending$;
         3: invokevirtual #70                 // Method org/scalatest/events/TestPending$.$lessinit$greater$default$10:()Lscala/Option;
         6: areturn
    Signature: #68                          // ()Lscala/Option<Lorg/scalatest/events/Location;>;

  public static scala.Option<org.scalatest.events.Formatter> $lessinit$greater$default$9();
    descriptor: ()Lscala/Option;
    flags: (0x0009) ACC_PUBLIC, ACC_STATIC
    Code:
      stack=1, locals=0, args_size=0
         0: getstatic     #55                 // Field org/scalatest/events/TestPending$.MODULE$:Lorg/scalatest/events/TestPending$;
         3: invokevirtual #74                 // Method org/scalatest/events/TestPending$.$lessinit$greater$default$9:()Lscala/Option;
         6: areturn
    Signature: #72                          // ()Lscala/Option<Lorg/scalatest/events/Formatter;>;

  public static scala.Option<java.lang.Object> $lessinit$greater$default$8();
    descriptor: ()Lscala/Option;
    flags: (0x0009) ACC_PUBLIC, ACC_STATIC
    Code:
      stack=1, locals=0, args_size=0
         0: getstatic     #55                 // Field org/scalatest/events/TestPending$.MODULE$:Lorg/scalatest/events/TestPending$;
         3: invokevirtual #77                 // Method org/scalatest/events/TestPending$.$lessinit$greater$default$8:()Lscala/Option;
         6: areturn
    Signature: #64                          // ()Lscala/Option<Ljava/lang/Object;>;

  public static scala.Option<scala.Tuple13<org.scalatest.events.Ordinal, java.lang.String, java.lang.String, scala.Option<java.lang.String>, java.lang.String, java.lang.String, scala.collection.immutable.IndexedSeq<org.scalatest.events.RecordableEvent>, scala.Option<java.lang.Object>, scala.Option<org.scalatest.events.Formatter>, scala.Option<org.scalatest.events.Location>, scala.Option<java.lang.Object>, java.lang.String, java.lang.Object>> unapply(org.scalatest.events.TestPending);
    descriptor: (Lorg/scalatest/events/TestPending;)Lscala/Option;
    flags: (0x0009) ACC_PUBLIC, ACC_STATIC
    Code:
      stack=2, locals=1, args_size=1
         0: getstatic     #55                 // Field org/scalatest/events/TestPending$.MODULE$:Lorg/scalatest/events/TestPending$;
         3: aload_0
         4: invokevirtual #83                 // Method org/scalatest/events/TestPending$.unapply:(Lorg/scalatest/events/TestPending;)Lscala/Option;
         7: areturn
      LocalVariableTable:
        Start  Length  Slot  Name   Signature
            0       8     0   x$0   Lorg/scalatest/events/TestPending;
    Signature: #80                          // (Lorg/scalatest/events/TestPending;)Lscala/Option<Lscala/Tuple13<Lorg/scalatest/events/Ordinal;Ljava/lang/String;Ljava/lang/String;Lscala/Option<Ljava/lang/String;>;Ljava/lang/String;Ljava/lang/String;Lscala/collection/immutable/IndexedSeq<Lorg/scalatest/events/RecordableEvent;>;Lscala/Option<Ljava/lang/Object;>;Lscala/Option<Lorg/scalatest/events/Formatter;>;Lscala/Option<Lorg/scalatest/events/Location;>;Lscala/Option<Ljava/lang/Object;>;Ljava/lang/String;Ljava/lang/Object;>;>;
    MethodParameters:
      Name                           Flags
      x$0                            final

  public static long apply$default$13();
    descriptor: ()J
    flags: (0x0009) ACC_PUBLIC, ACC_STATIC
    Code:
      stack=2, locals=0, args_size=0
         0: getstatic     #55                 // Field org/scalatest/events/TestPending$.MODULE$:Lorg/scalatest/events/TestPending$;
         3: invokevirtual #87                 // Method org/scalatest/events/TestPending$.apply$default$13:()J
         6: lreturn

  public static java.lang.String apply$default$12();
    descriptor: ()Ljava/lang/String;
    flags: (0x0009) ACC_PUBLIC, ACC_STATIC
    Code:
      stack=1, locals=0, args_size=0
         0: getstatic     #55                 // Field org/scalatest/events/TestPending$.MODULE$:Lorg/scalatest/events/TestPending$;
         3: invokevirtual #90                 // Method org/scalatest/events/TestPending$.apply$default$12:()Ljava/lang/String;
         6: areturn

  public static scala.Option<java.lang.Object> apply$default$11();
    descriptor: ()Lscala/Option;
    flags: (0x0009) ACC_PUBLIC, ACC_STATIC
    Code:
      stack=1, locals=0, args_size=0
         0: getstatic     #55                 // Field org/scalatest/events/TestPending$.MODULE$:Lorg/scalatest/events/TestPending$;
         3: invokevirtual #93                 // Method org/scalatest/events/TestPending$.apply$default$11:()Lscala/Option;
         6: areturn
    Signature: #64                          // ()Lscala/Option<Ljava/lang/Object;>;

  public static scala.Option<org.scalatest.events.Location> apply$default$10();
    descriptor: ()Lscala/Option;
    flags: (0x0009) ACC_PUBLIC, ACC_STATIC
    Code:
      stack=1, locals=0, args_size=0
         0: getstatic     #55                 // Field org/scalatest/events/TestPending$.MODULE$:Lorg/scalatest/events/TestPending$;
         3: invokevirtual #96                 // Method org/scalatest/events/TestPending$.apply$default$10:()Lscala/Option;
         6: areturn
    Signature: #68                          // ()Lscala/Option<Lorg/scalatest/events/Location;>;

  public static scala.Option<org.scalatest.events.Formatter> apply$default$9();
    descriptor: ()Lscala/Option;
    flags: (0x0009) ACC_PUBLIC, ACC_STATIC
    Code:
      stack=1, locals=0, args_size=0
         0: getstatic     #55                 // Field org/scalatest/events/TestPending$.MODULE$:Lorg/scalatest/events/TestPending$;
         3: invokevirtual #99                 // Method org/scalatest/events/TestPending$.apply$default$9:()Lscala/Option;
         6: areturn
    Signature: #72                          // ()Lscala/Option<Lorg/scalatest/events/Formatter;>;

  public static scala.Option<java.lang.Object> apply$default$8();
    descriptor: ()Lscala/Option;
    flags: (0x0009) ACC_PUBLIC, ACC_STATIC
    Code:
      stack=1, locals=0, args_size=0
         0: getstatic     #55                 // Field org/scalatest/events/TestPending$.MODULE$:Lorg/scalatest/events/TestPending$;
         3: invokevirtual #102                // Method org/scalatest/events/TestPending$.apply$default$8:()Lscala/Option;
         6: areturn
    Signature: #64                          // ()Lscala/Option<Ljava/lang/Object;>;

  public static org.scalatest.events.TestPending apply(org.scalatest.events.Ordinal, java.lang.String, java.lang.String, scala.Option<java.lang.String>, java.lang.String, java.lang.String, scala.collection.immutable.IndexedSeq<org.scalatest.events.RecordableEvent>, scala.Option<java.lang.Object>, scala.Option<org.scalatest.events.Formatter>, scala.Option<org.scalatest.events.Location>, scala.Option<java.lang.Object>, java.lang.String, long);
    descriptor: (Lorg/scalatest/events/Ordinal;Ljava/lang/String;Ljava/lang/String;Lscala/Option;Ljava/lang/String;Ljava/lang/String;Lscala/collection/immutable/IndexedSeq;Lscala/Option;Lscala/Option;Lscala/Option;Lscala/Option;Ljava/lang/String;J)Lorg/scalatest/events/TestPending;
    flags: (0x0009) ACC_PUBLIC, ACC_STATIC
    Code:
      stack=15, locals=14, args_size=13
         0: getstatic     #55                 // Field org/scalatest/events/TestPending$.MODULE$:Lorg/scalatest/events/TestPending$;
         3: aload_0
         4: aload_1
         5: aload_2
         6: aload_3
         7: aload         4
         9: aload         5
        11: aload         6
        13: aload         7
        15: aload         8
        17: aload         9
        19: aload         10
        21: aload         11
        23: lload         12
        25: invokevirtual #107                // Method org/scalatest/events/TestPending$.apply:(Lorg/scalatest/events/Ordinal;Ljava/lang/String;Ljava/lang/String;Lscala/Option;Ljava/lang/String;Ljava/lang/String;Lscala/collection/immutable/IndexedSeq;Lscala/Option;Lscala/Option;Lscala/Option;Lscala/Option;Ljava/lang/String;J)Lorg/scalatest/events/TestPending;
        28: areturn
      LocalVariableTable:
        Start  Length  Slot  Name   Signature
            0      29     0 ordinal   Lorg/scalatest/events/Ordinal;
            0      29     1 suiteName   Ljava/lang/String;
            0      29     2 suiteId   Ljava/lang/String;
            0      29     3 suiteClassName   Lscala/Option;
            0      29     4 testName   Ljava/lang/String;
            0      29     5 testText   Ljava/lang/String;
            0      29     6 recordedEvents   Lscala/collection/immutable/IndexedSeq;
            0      29     7 duration   Lscala/Option;
            0      29     8 formatter   Lscala/Option;
            0      29     9 location   Lscala/Option;
            0      29    10 payload   Lscala/Option;
            0      29    11 threadName   Ljava/lang/String;
            0      29    12 timeStamp   J
    Signature: #105                         // (Lorg/scalatest/events/Ordinal;Ljava/lang/String;Ljava/lang/String;Lscala/Option<Ljava/lang/String;>;Ljava/lang/String;Ljava/lang/String;Lscala/collection/immutable/IndexedSeq<Lorg/scalatest/events/RecordableEvent;>;Lscala/Option<Ljava/lang/Object;>;Lscala/Option<Lorg/scalatest/events/Formatter;>;Lscala/Option<Lorg/scalatest/events/Location;>;Lscala/Option<Ljava/lang/Object;>;Ljava/lang/String;J)Lorg/scalatest/events/TestPending;
    MethodParameters:
      Name                           Flags
      ordinal                        final
      suiteName                      final
      suiteId                        final
      suiteClassName                 final
      testName                       final
      testText                       final
      recordedEvents                 final
      duration                       final
      formatter                      final
      location                       final
      payload                        final
      threadName                     final
      timeStamp                      final

  public static scala.Function1<scala.Tuple13<org.scalatest.events.Ordinal, java.lang.String, java.lang.String, scala.Option<java.lang.String>, java.lang.String, java.lang.String, scala.collection.immutable.IndexedSeq<org.scalatest.events.RecordableEvent>, scala.Option<java.lang.Object>, scala.Option<org.scalatest.events.Formatter>, scala.Option<org.scalatest.events.Location>, scala.Option<java.lang.Object>, java.lang.String, java.lang.Object>, org.scalatest.events.TestPending> tupled();
    descriptor: ()Lscala/Function1;
    flags: (0x0009) ACC_PUBLIC, ACC_STATIC
    Code:
      stack=1, locals=0, args_size=0
         0: getstatic     #55                 // Field org/scalatest/events/TestPending$.MODULE$:Lorg/scalatest/events/TestPending$;
         3: invokevirtual #112                // Method org/scalatest/events/TestPending$.tupled:()Lscala/Function1;
         6: areturn
    Signature: #110                         // ()Lscala/Function1<Lscala/Tuple13<Lorg/scalatest/events/Ordinal;Ljava/lang/String;Ljava/lang/String;Lscala/Option<Ljava/lang/String;>;Ljava/lang/String;Ljava/lang/String;Lscala/collection/immutable/IndexedSeq<Lorg/scalatest/events/RecordableEvent;>;Lscala/Option<Ljava/lang/Object;>;Lscala/Option<Lorg/scalatest/events/Formatter;>;Lscala/Option<Lorg/scalatest/events/Location;>;Lscala/Option<Ljava/lang/Object;>;Ljava/lang/String;Ljava/lang/Object;>;Lorg/scalatest/events/TestPending;>;

  public static scala.Function1<org.scalatest.events.Ordinal, scala.Function1<java.lang.String, scala.Function1<java.lang.String, scala.Function1<scala.Option<java.lang.String>, scala.Function1<java.lang.String, scala.Function1<java.lang.String, scala.Function1<scala.collection.immutable.IndexedSeq<org.scalatest.events.RecordableEvent>, scala.Function1<scala.Option<java.lang.Object>, scala.Function1<scala.Option<org.scalatest.events.Formatter>, scala.Function1<scala.Option<org.scalatest.events.Location>, scala.Function1<scala.Option<java.lang.Object>, scala.Function1<java.lang.String, scala.Function1<java.lang.Object, org.scalatest.events.TestPending>>>>>>>>>>>>> curried();
    descriptor: ()Lscala/Function1;
    flags: (0x0009) ACC_PUBLIC, ACC_STATIC
    Code:
      stack=1, locals=0, args_size=0
         0: getstatic     #55                 // Field org/scalatest/events/TestPending$.MODULE$:Lorg/scalatest/events/TestPending$;
         3: invokevirtual #116                // Method org/scalatest/events/TestPending$.curried:()Lscala/Function1;
         6: areturn
    Signature: #114                         // ()Lscala/Function1<Lorg/scalatest/events/Ordinal;Lscala/Function1<Ljava/lang/String;Lscala/Function1<Ljava/lang/String;Lscala/Function1<Lscala/Option<Ljava/lang/String;>;Lscala/Function1<Ljava/lang/String;Lscala/Function1<Ljava/lang/String;Lscala/Function1<Lscala/collection/immutable/IndexedSeq<Lorg/scalatest/events/RecordableEvent;>;Lscala/Function1<Lscala/Option<Ljava/lang/Object;>;Lscala/Function1<Lscala/Option<Lorg/scalatest/events/Formatter;>;Lscala/Function1<Lscala/Option<Lorg/scalatest/events/Location;>;Lscala/Function1<Lscala/Option<Ljava/lang/Object;>;Lscala/Function1<Ljava/lang/String;Lscala/Function1<Ljava/lang/Object;Lorg/scalatest/events/TestPending;>;>;>;>;>;>;>;>;>;>;>;>;>;

  public org.scalatest.events.Ordinal ordinal();
    descriptor: ()Lorg/scalatest/events/Ordinal;
    flags: (0x0001) ACC_PUBLIC
    Code:
      stack=1, locals=1, args_size=1
         0: aload_0
         1: getfield      #119                // Field ordinal:Lorg/scalatest/events/Ordinal;
         4: areturn
      LineNumberTable:
        line 817: 0
      LocalVariableTable:
        Start  Length  Slot  Name   Signature
            0       5     0  this   Lorg/scalatest/events/TestPending;

  public java.lang.String suiteName();
    descriptor: ()Ljava/lang/String;
    flags: (0x0001) ACC_PUBLIC
    Code:
      stack=1, locals=1, args_size=1
         0: aload_0
         1: getfield      #122                // Field suiteName:Ljava/lang/String;
         4: areturn
      LineNumberTable:
        line 818: 0
      LocalVariableTable:
        Start  Length  Slot  Name   Signature
            0       5     0  this   Lorg/scalatest/events/TestPending;

  public java.lang.String suiteId();
    descriptor: ()Ljava/lang/String;
    flags: (0x0001) ACC_PUBLIC
    Code:
      stack=1, locals=1, args_size=1
         0: aload_0
         1: getfield      #124                // Field suiteId:Ljava/lang/String;
         4: areturn
      LineNumberTable:
        line 819: 0
      LocalVariableTable:
        Start  Length  Slot  Name   Signature
            0       5     0  this   Lorg/scalatest/events/TestPending;

  public scala.Option<java.lang.String> suiteClassName();
    descriptor: ()Lscala/Option;
    flags: (0x0001) ACC_PUBLIC
    Code:
      stack=1, locals=1, args_size=1
         0: aload_0
         1: getfield      #127                // Field suiteClassName:Lscala/Option;
         4: areturn
      LineNumberTable:
        line 820: 0
      LocalVariableTable:
        Start  Length  Slot  Name   Signature
            0       5     0  this   Lorg/scalatest/events/TestPending;
    Signature: #125                         // ()Lscala/Option<Ljava/lang/String;>;

  public java.lang.String testName();
    descriptor: ()Ljava/lang/String;
    flags: (0x0001) ACC_PUBLIC
    Code:
      stack=1, locals=1, args_size=1
         0: aload_0
         1: getfield      #129                // Field testName:Ljava/lang/String;
         4: areturn
      LineNumberTable:
        line 821: 0
      LocalVariableTable:
        Start  Length  Slot  Name   Signature
            0       5     0  this   Lorg/scalatest/events/TestPending;

  public java.lang.String testText();
    descriptor: ()Ljava/lang/String;
    flags: (0x0001) ACC_PUBLIC
    Code:
      stack=1, locals=1, args_size=1
         0: aload_0
         1: getfield      #131                // Field testText:Ljava/lang/String;
         4: areturn
      LineNumberTable:
        line 822: 0
      LocalVariableTable:
        Start  Length  Slot  Name   Signature
            0       5     0  this   Lorg/scalatest/events/TestPending;

  public scala.collection.immutable.IndexedSeq<org.scalatest.events.RecordableEvent> recordedEvents();
    descriptor: ()Lscala/collection/immutable/IndexedSeq;
    flags: (0x0001) ACC_PUBLIC
    Code:
      stack=1, locals=1, args_size=1
         0: aload_0
         1: getfield      #135                // Field recordedEvents:Lscala/collection/immutable/IndexedSeq;
         4: areturn
      LineNumberTable:
        line 823: 0
      LocalVariableTable:
        Start  Length  Slot  Name   Signature
            0       5     0  this   Lorg/scalatest/events/TestPending;
    Signature: #133                         // ()Lscala/collection/immutable/IndexedSeq<Lorg/scalatest/events/RecordableEvent;>;

  public scala.Option<java.lang.Object> duration();
    descriptor: ()Lscala/Option;
    flags: (0x0001) ACC_PUBLIC
    Code:
      stack=1, locals=1, args_size=1
         0: aload_0
         1: getfield      #137                // Field duration:Lscala/Option;
         4: areturn
      LineNumberTable:
        line 824: 0
      LocalVariableTable:
        Start  Length  Slot  Name   Signature
            0       5     0  this   Lorg/scalatest/events/TestPending;
    Signature: #64                          // ()Lscala/Option<Ljava/lang/Object;>;

  public scala.Option<org.scalatest.events.Formatter> formatter();
    descriptor: ()Lscala/Option;
    flags: (0x0001) ACC_PUBLIC
    Code:
      stack=1, locals=1, args_size=1
         0: aload_0
         1: getfield      #139                // Field formatter:Lscala/Option;
         4: areturn
      LineNumberTable:
        line 825: 0
      LocalVariableTable:
        Start  Length  Slot  Name   Signature
            0       5     0  this   Lorg/scalatest/events/TestPending;
    Signature: #72                          // ()Lscala/Option<Lorg/scalatest/events/Formatter;>;

  public scala.Option<org.scalatest.events.Location> location();
    descriptor: ()Lscala/Option;
    flags: (0x0001) ACC_PUBLIC
    Code:
      stack=1, locals=1, args_size=1
         0: aload_0
         1: getfield      #141                // Field location:Lscala/Option;
         4: areturn
      LineNumberTable:
        line 826: 0
      LocalVariableTable:
        Start  Length  Slot  Name   Signature
            0       5     0  this   Lorg/scalatest/events/TestPending;
    Signature: #68                          // ()Lscala/Option<Lorg/scalatest/events/Location;>;

  public scala.Option<java.lang.Object> payload();
    descriptor: ()Lscala/Option;
    flags: (0x0001) ACC_PUBLIC
    Code:
      stack=1, locals=1, args_size=1
         0: aload_0
         1: getfield      #143                // Field payload:Lscala/Option;
         4: areturn
      LineNumberTable:
        line 827: 0
      LocalVariableTable:
        Start  Length  Slot  Name   Signature
            0       5     0  this   Lorg/scalatest/events/TestPending;
    Signature: #64                          // ()Lscala/Option<Ljava/lang/Object;>;

  public java.lang.String threadName();
    descriptor: ()Ljava/lang/String;
    flags: (0x0001) ACC_PUBLIC
    Code:
      stack=1, locals=1, args_size=1
         0: aload_0
         1: getfield      #145                // Field threadName:Ljava/lang/String;
         4: areturn
      LineNumberTable:
        line 828: 0
      LocalVariableTable:
        Start  Length  Slot  Name   Signature
            0       5     0  this   Lorg/scalatest/events/TestPending;

  public long timeStamp();
    descriptor: ()J
    flags: (0x0001) ACC_PUBLIC
    Code:
      stack=2, locals=1, args_size=1
         0: aload_0
         1: getfield      #147                // Field timeStamp:J
         4: lreturn
      LineNumberTable:
        line 829: 0
      LocalVariableTable:
        Start  Length  Slot  Name   Signature
            0       5     0  this   Lorg/scalatest/events/TestPending;

  public scala.xml.Elem toXml();
    descriptor: ()Lscala/xml/Elem;
    flags: (0x0001) ACC_PUBLIC
    Code:
      stack=28, locals=15, args_size=1
         0: new           #151                // class scala/xml/Elem
         3: dup
         4: aconst_null
         5: ldc           #153                // String TestPending
         7: getstatic     #158                // Field scala/xml/Null$.MODULE$:Lscala/xml/Null$;
        10: getstatic     #163                // Field scala/xml/TopScope$.MODULE$:Lscala/xml/TopScope$;
        13: iconst_0
        14: getstatic     #168                // Field scala/xml/NodeSeq$.MODULE$:Lscala/xml/NodeSeq$;
        17: new           #170                // class scala/xml/NodeBuffer
        20: dup
        21: invokespecial #174                // Method scala/xml/NodeBuffer."<init>":()V
        24: astore_1
        25: aload_1
        26: new           #176                // class scala/xml/Text
        29: dup
        30: ldc           #178                // String \n
        32: invokespecial #181                // Method scala/xml/Text."<init>":(Ljava/lang/String;)V
        35: invokevirtual #185                // Method scala/xml/NodeBuffer.$amp$plus:(Ljava/lang/Object;)Lscala/xml/NodeBuffer;
        38: pop
        39: aload_1
        40: new           #151                // class scala/xml/Elem
        43: dup
        44: aconst_null
        45: ldc           #186                // String ordinal
        47: getstatic     #158                // Field scala/xml/Null$.MODULE$:Lscala/xml/Null$;
        50: getstatic     #163                // Field scala/xml/TopScope$.MODULE$:Lscala/xml/TopScope$;
        53: iconst_0
        54: getstatic     #168                // Field scala/xml/NodeSeq$.MODULE$:Lscala/xml/NodeSeq$;
        57: new           #170                // class scala/xml/NodeBuffer
        60: dup
        61: invokespecial #174                // Method scala/xml/NodeBuffer."<init>":()V
        64: astore_2
        65: aload_2
        66: new           #176                // class scala/xml/Text
        69: dup
        70: ldc           #188                // String \n
        72: invokespecial #181                // Method scala/xml/Text."<init>":(Ljava/lang/String;)V
        75: invokevirtual #185                // Method scala/xml/NodeBuffer.$amp$plus:(Ljava/lang/Object;)Lscala/xml/NodeBuffer;
        78: pop
        79: aload_2
        80: new           #151                // class scala/xml/Elem
        83: dup
        84: aconst_null
        85: ldc           #190                // String runStamp
        87: getstatic     #158                // Field scala/xml/Null$.MODULE$:Lscala/xml/Null$;
        90: getstatic     #163                // Field scala/xml/TopScope$.MODULE$:Lscala/xml/TopScope$;
        93: iconst_0
        94: getstatic     #168                // Field scala/xml/NodeSeq$.MODULE$:Lscala/xml/NodeSeq$;
        97: new           #170                // class scala/xml/NodeBuffer
       100: dup
       101: invokespecial #174                // Method scala/xml/NodeBuffer."<init>":()V
       104: astore_3
       105: aload_3
       106: aload_0
       107: invokevirtual #192                // Method ordinal:()Lorg/scalatest/events/Ordinal;
       110: invokevirtual #197                // Method org/scalatest/events/Ordinal.runStamp:()I
       113: invokestatic  #203                // Method scala/runtime/BoxesRunTime.boxToInteger:(I)Ljava/lang/Integer;
       116: invokevirtual #185                // Method scala/xml/NodeBuffer.$amp$plus:(Ljava/lang/Object;)Lscala/xml/NodeBuffer;
       119: pop
       120: aload_3
       121: invokevirtual #207                // Method scala/xml/NodeSeq$.seqToNodeSeq:(Lscala/collection/Seq;)Lscala/xml/NodeSeq;
       124: invokespecial #210                // Method scala/xml/Elem."<init>":(Ljava/lang/String;Ljava/lang/String;Lscala/xml/MetaData;Lscala/xml/NamespaceBinding;ZLscala/collection/immutable/Seq;)V
       127: invokevirtual #185                // Method scala/xml/NodeBuffer.$amp$plus:(Ljava/lang/Object;)Lscala/xml/NodeBuffer;
       130: pop
       131: aload_2
       132: new           #176                // class scala/xml/Text
       135: dup
       136: ldc           #178                // String \n
       138: invokespecial #181                // Method scala/xml/Text."<init>":(Ljava/lang/String;)V
       141: invokevirtual #185                // Method scala/xml/NodeBuffer.$amp$plus:(Ljava/lang/Object;)Lscala/xml/NodeBuffer;
       144: pop
       145: aload_2
       146: invokevirtual #207                // Method scala/xml/NodeSeq$.seqToNodeSeq:(Lscala/collection/Seq;)Lscala/xml/NodeSeq;
       149: invokespecial #210                // Method scala/xml/Elem."<init>":(Ljava/lang/String;Ljava/lang/String;Lscala/xml/MetaData;Lscala/xml/NamespaceBinding;ZLscala/collection/immutable/Seq;)V
       152: invokevirtual #185                // Method scala/xml/NodeBuffer.$amp$plus:(Ljava/lang/Object;)Lscala/xml/NodeBuffer;
       155: pop
       156: aload_1
       157: new           #176                // class scala/xml/Text
       160: dup
       161: ldc           #178                // String \n
       163: invokespecial #181                // Method scala/xml/Text."<init>":(Ljava/lang/String;)V
       166: invokevirtual #185                // Method scala/xml/NodeBuffer.$amp$plus:(Ljava/lang/Object;)Lscala/xml/NodeBuffer;
       169: pop
       170: aload_1
       171: new           #151                // class scala/xml/Elem
       174: dup
       175: aconst_null
       176: ldc           #211                // String suiteName
       178: getstatic     #158                // Field scala/xml/Null$.MODULE$:Lscala/xml/Null$;
       181: getstatic     #163                // Field scala/xml/TopScope$.MODULE$:Lscala/xml/TopScope$;
       184: iconst_0
       185: getstatic     #168                // Field scala/xml/NodeSeq$.MODULE$:Lscala/xml/NodeSeq$;
       188: new           #170                // class scala/xml/NodeBuffer
       191: dup
       192: invokespecial #174                // Method scala/xml/NodeBuffer."<init>":()V
       195: astore        4
       197: aload         4
       199: aload_0
       200: invokevirtual #213                // Method suiteName:()Ljava/lang/String;
       203: invokevirtual #185                // Method scala/xml/NodeBuffer.$amp$plus:(Ljava/lang/Object;)Lscala/xml/NodeBuffer;
       206: pop
       207: aload         4
       209: invokevirtual #207                // Method scala/xml/NodeSeq$.seqToNodeSeq:(Lscala/collection/Seq;)Lscala/xml/NodeSeq;
       212: invokespecial #210                // Method scala/xml/Elem."<init>":(Ljava/lang/String;Ljava/lang/String;Lscala/xml/MetaData;Lscala/xml/NamespaceBinding;ZLscala/collection/immutable/Seq;)V
       215: invokevirtual #185                // Method scala/xml/NodeBuffer.$amp$plus:(Ljava/lang/Object;)Lscala/xml/NodeBuffer;
       218: pop
       219: aload_1
       220: new           #176                // class scala/xml/Text
       223: dup
       224: ldc           #178                // String \n
       226: invokespecial #181                // Method scala/xml/Text."<init>":(Ljava/lang/String;)V
       229: invokevirtual #185                // Method scala/xml/NodeBuffer.$amp$plus:(Ljava/lang/Object;)Lscala/xml/NodeBuffer;
       232: pop
       233: aload_1
       234: new           #151                // class scala/xml/Elem
       237: dup
       238: aconst_null
       239: ldc           #214                // String suiteId
       241: getstatic     #158                // Field scala/xml/Null$.MODULE$:Lscala/xml/Null$;
       244: getstatic     #163                // Field scala/xml/TopScope$.MODULE$:Lscala/xml/TopScope$;
       247: iconst_0
       248: getstatic     #168                // Field scala/xml/NodeSeq$.MODULE$:Lscala/xml/NodeSeq$;
       251: new           #170                // class scala/xml/NodeBuffer
       254: dup
       255: invokespecial #174                // Method scala/xml/NodeBuffer."<init>":()V
       258: astore        5
       260: aload         5
       262: aload_0
       263: invokevirtual #216                // Method suiteId:()Ljava/lang/String;
       266: invokevirtual #185                // Method scala/xml/NodeBuffer.$amp$plus:(Ljava/lang/Object;)Lscala/xml/NodeBuffer;
       269: pop
       270: aload         5
       272: invokevirtual #207                // Method scala/xml/NodeSeq$.seqToNodeSeq:(Lscala/collection/Seq;)Lscala/xml/NodeSeq;
       275: invokespecial #210                // Method scala/xml/Elem."<init>":(Ljava/lang/String;Ljava/lang/String;Lscala/xml/MetaData;Lscala/xml/NamespaceBinding;ZLscala/collection/immutable/Seq;)V
       278: invokevirtual #185                // Method scala/xml/NodeBuffer.$amp$plus:(Ljava/lang/Object;)Lscala/xml/NodeBuffer;
       281: pop
       282: aload_1
       283: new           #176                // class scala/xml/Text
       286: dup
       287: ldc           #178                // String \n
       289: invokespecial #181                // Method scala/xml/Text."<init>":(Ljava/lang/String;)V
       292: invokevirtual #185                // Method scala/xml/NodeBuffer.$amp$plus:(Ljava/lang/Object;)Lscala/xml/NodeBuffer;
       295: pop
       296: aload_1
       297: new           #151                // class scala/xml/Elem
       300: dup
       301: aconst_null
       302: ldc           #217                // String suiteClassName
       304: getstatic     #158                // Field scala/xml/Null$.MODULE$:Lscala/xml/Null$;
       307: getstatic     #163                // Field scala/xml/TopScope$.MODULE$:Lscala/xml/TopScope$;
       310: iconst_0
       311: getstatic     #168                // Field scala/xml/NodeSeq$.MODULE$:Lscala/xml/NodeSeq$;
       314: new           #170                // class scala/xml/NodeBuffer
       317: dup
       318: invokespecial #174                // Method scala/xml/NodeBuffer."<init>":()V
       321: astore        6
       323: aload         6
       325: aload_0
       326: invokevirtual #221                // Method EventXmlHelper:()Lorg/scalatest/events/Event$EventXmlHelper$;
       329: aload_0
       330: invokevirtual #223                // Method suiteClassName:()Lscala/Option;
       333: invokevirtual #227                // Method org/scalatest/events/Event$EventXmlHelper$.stringOption:(Lscala/Option;)Ljava/lang/String;
       336: invokevirtual #185                // Method scala/xml/NodeBuffer.$amp$plus:(Ljava/lang/Object;)Lscala/xml/NodeBuffer;
       339: pop
       340: aload         6
       342: invokevirtual #207                // Method scala/xml/NodeSeq$.seqToNodeSeq:(Lscala/collection/Seq;)Lscala/xml/NodeSeq;
       345: invokespecial #210                // Method scala/xml/Elem."<init>":(Ljava/lang/String;Ljava/lang/String;Lscala/xml/MetaData;Lscala/xml/NamespaceBinding;ZLscala/collection/immutable/Seq;)V
       348: invokevirtual #185                // Method scala/xml/NodeBuffer.$amp$plus:(Ljava/lang/Object;)Lscala/xml/NodeBuffer;
       351: pop
       352: aload_1
       353: new           #176                // class scala/xml/Text
       356: dup
       357: ldc           #178                // String \n
       359: invokespecial #181                // Method scala/xml/Text."<init>":(Ljava/lang/String;)V
       362: invokevirtual #185                // Method scala/xml/NodeBuffer.$amp$plus:(Ljava/lang/Object;)Lscala/xml/NodeBuffer;
       365: pop
       366: aload_1
       367: new           #151                // class scala/xml/Elem
       370: dup
       371: aconst_null
       372: ldc           #228                // String duration
       374: getstatic     #158                // Field scala/xml/Null$.MODULE$:Lscala/xml/Null$;
       377: getstatic     #163                // Field scala/xml/TopScope$.MODULE$:Lscala/xml/TopScope$;
       380: iconst_0
       381: getstatic     #168                // Field scala/xml/NodeSeq$.MODULE$:Lscala/xml/NodeSeq$;
       384: new           #170                // class scala/xml/NodeBuffer
       387: dup
       388: invokespecial #174                // Method scala/xml/NodeBuffer."<init>":()V
       391: astore        7
       393: aload         7
       395: aload_0
       396: invokevirtual #221                // Method EventXmlHelper:()Lorg/scalatest/events/Event$EventXmlHelper$;
       399: aload_0
       400: invokevirtual #230                // Method duration:()Lscala/Option;
       403: invokevirtual #233                // Method org/scalatest/events/Event$EventXmlHelper$.longOption:(Lscala/Option;)Ljava/lang/String;
       406: invokevirtual #185                // Method scala/xml/NodeBuffer.$amp$plus:(Ljava/lang/Object;)Lscala/xml/NodeBuffer;
       409: pop
       410: aload         7
       412: invokevirtual #207                // Method scala/xml/NodeSeq$.seqToNodeSeq:(Lscala/collection/Seq;)Lscala/xml/NodeSeq;
       415: invokespecial #210                // Method scala/xml/Elem."<init>":(Ljava/lang/String;Ljava/lang/String;Lscala/xml/MetaData;Lscala/xml/NamespaceBinding;ZLscala/collection/immutable/Seq;)V
       418: invokevirtual #185                // Method scala/xml/NodeBuffer.$amp$plus:(Ljava/lang/Object;)Lscala/xml/NodeBuffer;
       421: pop
       422: aload_1
       423: new           #176                // class scala/xml/Text
       426: dup
       427: ldc           #178                // String \n
       429: invokespecial #181                // Method scala/xml/Text."<init>":(Ljava/lang/String;)V
       432: invokevirtual #185                // Method scala/xml/NodeBuffer.$amp$plus:(Ljava/lang/Object;)Lscala/xml/NodeBuffer;
       435: pop
       436: aload_1
       437: new           #151                // class scala/xml/Elem
       440: dup
       441: aconst_null
       442: ldc           #234                // String testName
       444: getstatic     #158                // Field scala/xml/Null$.MODULE$:Lscala/xml/Null$;
       447: getstatic     #163                // Field scala/xml/TopScope$.MODULE$:Lscala/xml/TopScope$;
       450: iconst_0
       451: getstatic     #168                // Field scala/xml/NodeSeq$.MODULE$:Lscala/xml/NodeSeq$;
       454: new           #170                // class scala/xml/NodeBuffer
       457: dup
       458: invokespecial #174                // Method scala/xml/NodeBuffer."<init>":()V
       461: astore        8
       463: aload         8
       465: aload_0
       466: invokevirtual #236                // Method testName:()Ljava/lang/String;
       469: invokevirtual #185                // Method scala/xml/NodeBuffer.$amp$plus:(Ljava/lang/Object;)Lscala/xml/NodeBuffer;
       472: pop
       473: aload         8
       475: invokevirtual #207                // Method scala/xml/NodeSeq$.seqToNodeSeq:(Lscala/collection/Seq;)Lscala/xml/NodeSeq;
       478: invokespecial #210                // Method scala/xml/Elem."<init>":(Ljava/lang/String;Ljava/lang/String;Lscala/xml/MetaData;Lscala/xml/NamespaceBinding;ZLscala/collection/immutable/Seq;)V
       481: invokevirtual #185                // Method scala/xml/NodeBuffer.$amp$plus:(Ljava/lang/Object;)Lscala/xml/NodeBuffer;
       484: pop
       485: aload_1
       486: new           #176                // class scala/xml/Text
       489: dup
       490: ldc           #178                // String \n
       492: invokespecial #181                // Method scala/xml/Text."<init>":(Ljava/lang/String;)V
       495: invokevirtual #185                // Method scala/xml/NodeBuffer.$amp$plus:(Ljava/lang/Object;)Lscala/xml/NodeBuffer;
       498: pop
       499: aload_1
       500: new           #151                // class scala/xml/Elem
       503: dup
       504: aconst_null
       505: ldc           #237                // String testText
       507: getstatic     #158                // Field scala/xml/Null$.MODULE$:Lscala/xml/Null$;
       510: getstatic     #163                // Field scala/xml/TopScope$.MODULE$:Lscala/xml/TopScope$;
       513: iconst_0
       514: getstatic     #168                // Field scala/xml/NodeSeq$.MODULE$:Lscala/xml/NodeSeq$;
       517: new           #170                // class scala/xml/NodeBuffer
       520: dup
       521: invokespecial #174                // Method scala/xml/NodeBuffer."<init>":()V
       524: astore        9
       526: aload         9
       528: aload_0
       529: invokevirtual #239                // Method testText:()Ljava/lang/String;
       532: invokevirtual #185                // Method scala/xml/NodeBuffer.$amp$plus:(Ljava/lang/Object;)Lscala/xml/NodeBuffer;
       535: pop
       536: aload         9
       538: invokevirtual #207                // Method scala/xml/NodeSeq$.seqToNodeSeq:(Lscala/collection/Seq;)Lscala/xml/NodeSeq;
       541: invokespecial #210                // Method scala/xml/Elem."<init>":(Ljava/lang/String;Ljava/lang/String;Lscala/xml/MetaData;Lscala/xml/NamespaceBinding;ZLscala/collection/immutable/Seq;)V
       544: invokevirtual #185                // Method scala/xml/NodeBuffer.$amp$plus:(Ljava/lang/Object;)Lscala/xml/NodeBuffer;
       547: pop
       548: aload_1
       549: new           #176                // class scala/xml/Text
       552: dup
       553: ldc           #178                // String \n
       555: invokespecial #181                // Method scala/xml/Text."<init>":(Ljava/lang/String;)V
       558: invokevirtual #185                // Method scala/xml/NodeBuffer.$amp$plus:(Ljava/lang/Object;)Lscala/xml/NodeBuffer;
       561: pop
       562: aload_1
       563: new           #151                // class scala/xml/Elem
       566: dup
       567: aconst_null
       568: ldc           #240                // String recordedEvents
       570: getstatic     #158                // Field scala/xml/Null$.MODULE$:Lscala/xml/Null$;
       573: getstatic     #163                // Field scala/xml/TopScope$.MODULE$:Lscala/xml/TopScope$;
       576: iconst_0
       577: getstatic     #168                // Field scala/xml/NodeSeq$.MODULE$:Lscala/xml/NodeSeq$;
       580: new           #170                // class scala/xml/NodeBuffer
       583: dup
       584: invokespecial #174                // Method scala/xml/NodeBuffer."<init>":()V
       587: astore        10
       589: aload         10
       591: aload_0
       592: invokevirtual #242                // Method recordedEvents:()Lscala/collection/immutable/IndexedSeq;
       595: invokedynamic #261,  0            // InvokeDynamic #0:apply:()Lscala/Function1;
       600: invokeinterface #267,  2          // InterfaceMethod scala/collection/immutable/IndexedSeq.map:(Lscala/Function1;)Ljava/lang/Object;
       605: invokevirtual #185                // Method scala/xml/NodeBuffer.$amp$plus:(Ljava/lang/Object;)Lscala/xml/NodeBuffer;
       608: pop
       609: aload         10
       611: invokevirtual #207                // Method scala/xml/NodeSeq$.seqToNodeSeq:(Lscala/collection/Seq;)Lscala/xml/NodeSeq;
       614: invokespecial #210                // Method scala/xml/Elem."<init>":(Ljava/lang/String;Ljava/lang/String;Lscala/xml/MetaData;Lscala/xml/NamespaceBinding;ZLscala/collection/immutable/Seq;)V
       617: invokevirtual #185                // Method scala/xml/NodeBuffer.$amp$plus:(Ljava/lang/Object;)Lscala/xml/NodeBuffer;
       620: pop
       621: aload_1
       622: new           #176                // class scala/xml/Text
       625: dup
       626: ldc           #178                // String \n
       628: invokespecial #181                // Method scala/xml/Text."<init>":(Ljava/lang/String;)V
       631: invokevirtual #185                // Method scala/xml/NodeBuffer.$amp$plus:(Ljava/lang/Object;)Lscala/xml/NodeBuffer;
       634: pop
       635: aload_1
       636: new           #151                // class scala/xml/Elem
       639: dup
       640: aconst_null
       641: ldc_w         #268                // String formatter
       644: getstatic     #158                // Field scala/xml/Null$.MODULE$:Lscala/xml/Null$;
       647: getstatic     #163                // Field scala/xml/TopScope$.MODULE$:Lscala/xml/TopScope$;
       650: iconst_0
       651: getstatic     #168                // Field scala/xml/NodeSeq$.MODULE$:Lscala/xml/NodeSeq$;
       654: new           #170                // class scala/xml/NodeBuffer
       657: dup
       658: invokespecial #174                // Method scala/xml/NodeBuffer."<init>":()V
       661: astore        11
       663: aload         11
       665: aload_0
       666: invokevirtual #221                // Method EventXmlHelper:()Lorg/scalatest/events/Event$EventXmlHelper$;
       669: aload_0
       670: invokevirtual #270                // Method formatter:()Lscala/Option;
       673: invokevirtual #274                // Method org/scalatest/events/Event$EventXmlHelper$.formatterOption:(Lscala/Option;)Ljava/lang/Object;
       676: invokevirtual #185                // Method scala/xml/NodeBuffer.$amp$plus:(Ljava/lang/Object;)Lscala/xml/NodeBuffer;
       679: pop
       680: aload         11
       682: invokevirtual #207                // Method scala/xml/NodeSeq$.seqToNodeSeq:(Lscala/collection/Seq;)Lscala/xml/NodeSeq;
       685: invokespecial #210                // Method scala/xml/Elem."<init>":(Ljava/lang/String;Ljava/lang/String;Lscala/xml/MetaData;Lscala/xml/NamespaceBinding;ZLscala/collection/immutable/Seq;)V
       688: invokevirtual #185                // Method scala/xml/NodeBuffer.$amp$plus:(Ljava/lang/Object;)Lscala/xml/NodeBuffer;
       691: pop
       692: aload_1
       693: new           #176                // class scala/xml/Text
       696: dup
       697: ldc           #178                // String \n
       699: invokespecial #181                // Method scala/xml/Text."<init>":(Ljava/lang/String;)V
       702: invokevirtual #185                // Method scala/xml/NodeBuffer.$amp$plus:(Ljava/lang/Object;)Lscala/xml/NodeBuffer;
       705: pop
       706: aload_1
       707: new           #151                // class scala/xml/Elem
       710: dup
       711: aconst_null
       712: ldc_w         #275                // String location
       715: getstatic     #158                // Field scala/xml/Null$.MODULE$:Lscala/xml/Null$;
       718: getstatic     #163                // Field scala/xml/TopScope$.MODULE$:Lscala/xml/TopScope$;
       721: iconst_0
       722: getstatic     #168                // Field scala/xml/NodeSeq$.MODULE$:Lscala/xml/NodeSeq$;
       725: new           #170                // class scala/xml/NodeBuffer
       728: dup
       729: invokespecial #174                // Method scala/xml/NodeBuffer."<init>":()V
       732: astore        12
       734: aload         12
       736: aload_0
       737: invokevirtual #221                // Method EventXmlHelper:()Lorg/scalatest/events/Event$EventXmlHelper$;
       740: aload_0
       741: invokevirtual #277                // Method location:()Lscala/Option;
       744: invokevirtual #280                // Method org/scalatest/events/Event$EventXmlHelper$.locationOption:(Lscala/Option;)Ljava/lang/Object;
       747: invokevirtual #185                // Method scala/xml/NodeBuffer.$amp$plus:(Ljava/lang/Object;)Lscala/xml/NodeBuffer;
       750: pop
       751: aload         12
       753: invokevirtual #207                // Method scala/xml/NodeSeq$.seqToNodeSeq:(Lscala/collection/Seq;)Lscala/xml/NodeSeq;
       756: invokespecial #210                // Method scala/xml/Elem."<init>":(Ljava/lang/String;Ljava/lang/String;Lscala/xml/MetaData;Lscala/xml/NamespaceBinding;ZLscala/collection/immutable/Seq;)V
       759: invokevirtual #185                // Method scala/xml/NodeBuffer.$amp$plus:(Ljava/lang/Object;)Lscala/xml/NodeBuffer;
       762: pop
       763: aload_1
       764: new           #176                // class scala/xml/Text
       767: dup
       768: ldc           #178                // String \n
       770: invokespecial #181                // Method scala/xml/Text."<init>":(Ljava/lang/String;)V
       773: invokevirtual #185                // Method scala/xml/NodeBuffer.$amp$plus:(Ljava/lang/Object;)Lscala/xml/NodeBuffer;
       776: pop
       777: aload_1
       778: new           #151                // class scala/xml/Elem
       781: dup
       782: aconst_null
       783: ldc_w         #281                // String threadName
       786: getstatic     #158                // Field scala/xml/Null$.MODULE$:Lscala/xml/Null$;
       789: getstatic     #163                // Field scala/xml/TopScope$.MODULE$:Lscala/xml/TopScope$;
       792: iconst_0
       793: getstatic     #168                // Field scala/xml/NodeSeq$.MODULE$:Lscala/xml/NodeSeq$;
       796: new           #170                // class scala/xml/NodeBuffer
       799: dup
       800: invokespecial #174                // Method scala/xml/NodeBuffer."<init>":()V
       803: astore        13
       805: aload         13
       807: aload_0
       808: invokevirtual #283                // Method threadName:()Ljava/lang/String;
       811: invokevirtual #185                // Method scala/xml/NodeBuffer.$amp$plus:(Ljava/lang/Object;)Lscala/xml/NodeBuffer;
       814: pop
       815: aload         13
       817: invokevirtual #207                // Method scala/xml/NodeSeq$.seqToNodeSeq:(Lscala/collection/Seq;)Lscala/xml/NodeSeq;
       820: invokespecial #210                // Method scala/xml/Elem."<init>":(Ljava/lang/String;Ljava/lang/String;Lscala/xml/MetaData;Lscala/xml/NamespaceBinding;ZLscala/collection/immutable/Seq;)V
       823: invokevirtual #185                // Method scala/xml/NodeBuffer.$amp$plus:(Ljava/lang/Object;)Lscala/xml/NodeBuffer;
       826: pop
       827: aload_1
       828: new           #176                // class scala/xml/Text
       831: dup
       832: ldc           #178                // String \n
       834: invokespecial #181                // Method scala/xml/Text."<init>":(Ljava/lang/String;)V
       837: invokevirtual #185                // Method scala/xml/NodeBuffer.$amp$plus:(Ljava/lang/Object;)Lscala/xml/NodeBuffer;
       840: pop
       841: aload_1
       842: new           #151                // class scala/xml/Elem
       845: dup
       846: aconst_null
       847: ldc_w         #284                // String timeStamp
       850: getstatic     #158                // Field scala/xml/Null$.MODULE$:Lscala/xml/Null$;
       853: getstatic     #163                // Field scala/xml/TopScope$.MODULE$:Lscala/xml/TopScope$;
       856: iconst_0
       857: getstatic     #168                // Field scala/xml/NodeSeq$.MODULE$:Lscala/xml/NodeSeq$;
       860: new           #170                // class scala/xml/NodeBuffer
       863: dup
       864: invokespecial #174                // Method scala/xml/NodeBuffer."<init>":()V
       867: astore        14
       869: aload         14
       871: aload_0
       872: invokevirtual #286                // Method timeStamp:()J
       875: invokestatic  #290                // Method scala/runtime/BoxesRunTime.boxToLong:(J)Ljava/lang/Long;
       878: invokevirtual #185                // Method scala/xml/NodeBuffer.$amp$plus:(Ljava/lang/Object;)Lscala/xml/NodeBuffer;
       881: pop
       882: aload         14
       884: invokevirtual #207                // Method scala/xml/NodeSeq$.seqToNodeSeq:(Lscala/collection/Seq;)Lscala/xml/NodeSeq;
       887: invokespecial #210                // Method scala/xml/Elem."<init>":(Ljava/lang/String;Ljava/lang/String;Lscala/xml/MetaData;Lscala/xml/NamespaceBinding;ZLscala/collection/immutable/Seq;)V
       890: invokevirtual #185                // Method scala/xml/NodeBuffer.$amp$plus:(Ljava/lang/Object;)Lscala/xml/NodeBuffer;
       893: pop
       894: aload_1
       895: new           #176                // class scala/xml/Text
       898: dup
       899: ldc_w         #292                // String \n
       902: invokespecial #181                // Method scala/xml/Text."<init>":(Ljava/lang/String;)V
       905: invokevirtual #185                // Method scala/xml/NodeBuffer.$amp$plus:(Ljava/lang/Object;)Lscala/xml/NodeBuffer;
       908: pop
       909: aload_1
       910: invokevirtual #207                // Method scala/xml/NodeSeq$.seqToNodeSeq:(Lscala/collection/Seq;)Lscala/xml/NodeSeq;
       913: invokespecial #210                // Method scala/xml/Elem."<init>":(Ljava/lang/String;Ljava/lang/String;Lscala/xml/MetaData;Lscala/xml/NamespaceBinding;ZLscala/collection/immutable/Seq;)V
       916: areturn
      LineNumberTable:
        line 847: 0
        line 848: 40
        line 849: 80
        line 848: 131
        line 849: 132
        line 848: 145
        line 847: 156
        line 850: 157
        line 847: 170
        line 851: 171
        line 847: 219
        line 851: 220
        line 847: 233
        line 852: 234
        line 847: 282
        line 852: 283
        line 847: 296
        line 853: 297
        line 847: 352
        line 853: 353
        line 847: 366
        line 854: 367
        line 847: 422
        line 854: 423
        line 847: 436
        line 855: 437
        line 847: 485
        line 855: 486
        line 847: 499
        line 856: 500
        line 847: 548
        line 856: 549
        line 847: 562
        line 857: 563
        line 847: 621
        line 857: 622
        line 847: 635
        line 858: 636
        line 847: 692
        line 858: 693
        line 847: 706
        line 859: 707
        line 847: 763
        line 859: 764
        line 847: 777
        line 860: 778
        line 847: 827
        line 860: 828
        line 847: 841
        line 861: 842
        line 847: 894
        line 861: 895
        line 847: 909
      LocalVariableTable:
        Start  Length  Slot  Name   Signature
          105      16     3  $buf   Lscala/xml/NodeBuffer;
           65      81     2  $buf   Lscala/xml/NodeBuffer;
          197      12     4  $buf   Lscala/xml/NodeBuffer;
          260      12     5  $buf   Lscala/xml/NodeBuffer;
          323      19     6  $buf   Lscala/xml/NodeBuffer;
          393      19     7  $buf   Lscala/xml/NodeBuffer;
          463      12     8  $buf   Lscala/xml/NodeBuffer;
          526      12     9  $buf   Lscala/xml/NodeBuffer;
          589      22    10  $buf   Lscala/xml/NodeBuffer;
          663      19    11  $buf   Lscala/xml/NodeBuffer;
          734      19    12  $buf   Lscala/xml/NodeBuffer;
          805      12    13  $buf   Lscala/xml/NodeBuffer;
          869      15    14  $buf   Lscala/xml/NodeBuffer;
           25     885     1  $buf   Lscala/xml/NodeBuffer;
            0     917     0  this   Lorg/scalatest/events/TestPending;

  public java.lang.String toJson();
    descriptor: ()Ljava/lang/String;
    flags: (0x0001) ACC_PUBLIC
    Code:
      stack=5, locals=1, args_size=1
         0: getstatic     #300                // Field scala/collection/StringOps$.MODULE$:Lscala/collection/StringOps$;
         3: getstatic     #305                // Field scala/Predef$.MODULE$:Lscala/Predef$;
         6: new           #307                // class java/lang/StringBuilder
         9: dup
        10: ldc_w         #308                // int 216
        13: invokespecial #311                // Method java/lang/StringBuilder."<init>":(I)V
        16: ldc_w         #313                // String { \"eventType\": \"TestPending\", \"ordinal\":
        19: invokevirtual #317                // Method java/lang/StringBuilder.append:(Ljava/lang/String;)Ljava/lang/StringBuilder;
        22: aload_0
        23: invokevirtual #192                // Method ordinal:()Lorg/scalatest/events/Ordinal;
        26: invokevirtual #197                // Method org/scalatest/events/Ordinal.runStamp:()I
        29: invokevirtual #320                // Method java/lang/StringBuilder.append:(I)Ljava/lang/StringBuilder;
        32: ldc_w         #322                // String , \"suiteName\":
        35: invokevirtual #317                // Method java/lang/StringBuilder.append:(Ljava/lang/String;)Ljava/lang/StringBuilder;
        38: aload_0
        39: invokevirtual #326                // Method EventJsonHelper:()Lorg/scalatest/events/Event$EventJsonHelper$;
        42: aload_0
        43: invokevirtual #213                // Method suiteName:()Ljava/lang/String;
        46: invokevirtual #330                // Method org/scalatest/events/Event$EventJsonHelper$.string:(Ljava/lang/String;)Ljava/lang/String;
        49: invokevirtual #317                // Method java/lang/StringBuilder.append:(Ljava/lang/String;)Ljava/lang/StringBuilder;
        52: ldc_w         #332                // String , \"suiteId\":
        55: invokevirtual #317                // Method java/lang/StringBuilder.append:(Ljava/lang/String;)Ljava/lang/StringBuilder;
        58: aload_0
        59: invokevirtual #326                // Method EventJsonHelper:()Lorg/scalatest/events/Event$EventJsonHelper$;
        62: aload_0
        63: invokevirtual #216                // Method suiteId:()Ljava/lang/String;
        66: invokevirtual #330                // Method org/scalatest/events/Event$EventJsonHelper$.string:(Ljava/lang/String;)Ljava/lang/String;
        69: invokevirtual #317                // Method java/lang/StringBuilder.append:(Ljava/lang/String;)Ljava/lang/StringBuilder;
        72: ldc_w         #334                // String , \"suiteClassName\":
        75: invokevirtual #317                // Method java/lang/StringBuilder.append:(Ljava/lang/String;)Ljava/lang/StringBuilder;
        78: aload_0
        79: invokevirtual #326                // Method EventJsonHelper:()Lorg/scalatest/events/Event$EventJsonHelper$;
        82: aload_0
        83: invokevirtual #223                // Method suiteClassName:()Lscala/Option;
        86: invokevirtual #335                // Method org/scalatest/events/Event$EventJsonHelper$.stringOption:(Lscala/Option;)Ljava/lang/String;
        89: invokevirtual #317                // Method java/lang/StringBuilder.append:(Ljava/lang/String;)Ljava/lang/StringBuilder;
        92: ldc_w         #337                // String , \"duration\":
        95: invokevirtual #317                // Method java/lang/StringBuilder.append:(Ljava/lang/String;)Ljava/lang/StringBuilder;
        98: aload_0
        99: invokevirtual #230                // Method duration:()Lscala/Option;
       102: invokedynamic #347,  0            // InvokeDynamic #1:apply:()Lscala/Function0;
       107: invokevirtual #353                // Method scala/Option.getOrElse:(Lscala/Function0;)Ljava/lang/Object;
       110: invokevirtual #356                // Method java/lang/StringBuilder.append:(Ljava/lang/Object;)Ljava/lang/StringBuilder;
       113: ldc_w         #358                // String , \"testName\":
       116: invokevirtual #317                // Method java/lang/StringBuilder.append:(Ljava/lang/String;)Ljava/lang/StringBuilder;
       119: aload_0
       120: invokevirtual #326                // Method EventJsonHelper:()Lorg/scalatest/events/Event$EventJsonHelper$;
       123: aload_0
       124: invokevirtual #236                // Method testName:()Ljava/lang/String;
       127: invokevirtual #330                // Method org/scalatest/events/Event$EventJsonHelper$.string:(Ljava/lang/String;)Ljava/lang/String;
       130: invokevirtual #317                // Method java/lang/StringBuilder.append:(Ljava/lang/String;)Ljava/lang/StringBuilder;
       133: ldc_w         #360                // String , \"testText\":
       136: invokevirtual #317                // Method java/lang/StringBuilder.append:(Ljava/lang/String;)Ljava/lang/StringBuilder;
       139: aload_0
       140: invokevirtual #326                // Method EventJsonHelper:()Lorg/scalatest/events/Event$EventJsonHelper$;
       143: aload_0
       144: invokevirtual #239                // Method testText:()Ljava/lang/String;
       147: invokevirtual #330                // Method org/scalatest/events/Event$EventJsonHelper$.string:(Ljava/lang/String;)Ljava/lang/String;
       150: invokevirtual #317                // Method java/lang/StringBuilder.append:(Ljava/lang/String;)Ljava/lang/StringBuilder;
       153: ldc_w         #362                // String , \"recordedEvents\" : [
       156: invokevirtual #317                // Method java/lang/StringBuilder.append:(Ljava/lang/String;)Ljava/lang/StringBuilder;
       159: aload_0
       160: invokevirtual #242                // Method recordedEvents:()Lscala/collection/immutable/IndexedSeq;
       163: invokedynamic #369,  0            // InvokeDynamic #2:apply:()Lscala/Function1;
       168: invokeinterface #267,  2          // InterfaceMethod scala/collection/immutable/IndexedSeq.map:(Lscala/Function1;)Ljava/lang/Object;
       173: checkcast     #371                // class scala/collection/IterableOnceOps
       176: ldc_w         #373                // String ,
       179: invokeinterface #376,  2          // InterfaceMethod scala/collection/IterableOnceOps.mkString:(Ljava/lang/String;)Ljava/lang/String;
       184: invokevirtual #317                // Method java/lang/StringBuilder.append:(Ljava/lang/String;)Ljava/lang/StringBuilder;
       187: ldc_w         #378                // String ], \"formatter\":
       190: invokevirtual #317                // Method java/lang/StringBuilder.append:(Ljava/lang/String;)Ljava/lang/StringBuilder;
       193: aload_0
       194: invokevirtual #326                // Method EventJsonHelper:()Lorg/scalatest/events/Event$EventJsonHelper$;
       197: aload_0
       198: invokevirtual #270                // Method formatter:()Lscala/Option;
       201: invokevirtual #380                // Method org/scalatest/events/Event$EventJsonHelper$.formatterOption:(Lscala/Option;)Ljava/lang/String;
       204: invokevirtual #317                // Method java/lang/StringBuilder.append:(Ljava/lang/String;)Ljava/lang/StringBuilder;
       207: ldc_w         #382                // String , \"location\":
       210: invokevirtual #317                // Method java/lang/StringBuilder.append:(Ljava/lang/String;)Ljava/lang/StringBuilder;
       213: aload_0
       214: invokevirtual #326                // Method EventJsonHelper:()Lorg/scalatest/events/Event$EventJsonHelper$;
       217: aload_0
       218: invokevirtual #277                // Method location:()Lscala/Option;
       221: invokevirtual #384                // Method org/scalatest/events/Event$EventJsonHelper$.locationOption:(Lscala/Option;)Ljava/lang/String;
       224: invokevirtual #317                // Method java/lang/StringBuilder.append:(Ljava/lang/String;)Ljava/lang/StringBuilder;
       227: ldc_w         #386                // String , \"threadName\":
       230: invokevirtual #317                // Method java/lang/StringBuilder.append:(Ljava/lang/String;)Ljava/lang/StringBuilder;
       233: aload_0
       234: invokevirtual #326                // Method EventJsonHelper:()Lorg/scalatest/events/Event$EventJsonHelper$;
       237: aload_0
       238: invokevirtual #283                // Method threadName:()Ljava/lang/String;
       241: invokevirtual #330                // Method org/scalatest/events/Event$EventJsonHelper$.string:(Ljava/lang/String;)Ljava/lang/String;
       244: invokevirtual #317                // Method java/lang/StringBuilder.append:(Ljava/lang/String;)Ljava/lang/StringBuilder;
       247: ldc_w         #388                // String , \"timeStamp\":
       250: invokevirtual #317                // Method java/lang/StringBuilder.append:(Ljava/lang/String;)Ljava/lang/StringBuilder;
       253: aload_0
       254: invokevirtual #286                // Method timeStamp:()J
       257: invokevirtual #391                // Method java/lang/StringBuilder.append:(J)Ljava/lang/StringBuilder;
       260: ldc_w         #393                // String  }
       263: invokevirtual #317                // Method java/lang/StringBuilder.append:(Ljava/lang/String;)Ljava/lang/StringBuilder;
       266: invokevirtual #396                // Method java/lang/StringBuilder.toString:()Ljava/lang/String;
       269: invokevirtual #399                // Method scala/Predef$.augmentString:(Ljava/lang/String;)Ljava/lang/String;
       272: invokevirtual #402                // Method scala/collection/StringOps$.stripMargin$extension:(Ljava/lang/String;)Ljava/lang/String;
       275: areturn
      LineNumberTable:
        line 868: 3
      LocalVariableTable:
        Start  Length  Slot  Name   Signature
            0     276     0  this   Lorg/scalatest/events/TestPending;

  public org.scalatest.events.TestPending withPayload(scala.Option<java.lang.Object>);
    descriptor: (Lscala/Option;)Lorg/scalatest/events/TestPending;
    flags: (0x0001) ACC_PUBLIC
    Code:
      stack=15, locals=16, args_size=2
         0: aload_1
         1: astore_2
         2: aload_0
         3: invokevirtual #409                // Method copy$default$1:()Lorg/scalatest/events/Ordinal;
         6: astore_3
         7: aload_0
         8: invokevirtual #412                // Method copy$default$2:()Ljava/lang/String;
        11: astore        4
        13: aload_0
        14: invokevirtual #415                // Method copy$default$3:()Ljava/lang/String;
        17: astore        5
        19: aload_0
        20: invokevirtual #418                // Method copy$default$4:()Lscala/Option;
        23: astore        6
        25: aload_0
        26: invokevirtual #421                // Method copy$default$5:()Ljava/lang/String;
        29: astore        7
        31: aload_0
        32: invokevirtual #424                // Method copy$default$6:()Ljava/lang/String;
        35: astore        8
        37: aload_0
        38: invokevirtual #427                // Method copy$default$7:()Lscala/collection/immutable/IndexedSeq;
        41: astore        9
        43: aload_0
        44: invokevirtual #430                // Method copy$default$8:()Lscala/Option;
        47: astore        10
        49: aload_0
        50: invokevirtual #433                // Method copy$default$9:()Lscala/Option;
        53: astore        11
        55: aload_0
        56: invokevirtual #436                // Method copy$default$10:()Lscala/Option;
        59: astore        12
        61: aload_0
        62: invokevirtual #439                // Method copy$default$12:()Ljava/lang/String;
        65: astore        13
        67: aload_0
        68: invokevirtual #442                // Method copy$default$13:()J
        71: lstore        14
        73: aload_0
        74: aload_3
        75: aload         4
        77: aload         5
        79: aload         6
        81: aload         7
        83: aload         8
        85: aload         9
        87: aload         10
        89: aload         11
        91: aload         12
        93: aload_2
        94: aload         13
        96: lload         14
        98: invokevirtual #445                // Method copy:(Lorg/scalatest/events/Ordinal;Ljava/lang/String;Ljava/lang/String;Lscala/Option;Ljava/lang/String;Ljava/lang/String;Lscala/collection/immutable/IndexedSeq;Lscala/Option;Lscala/Option;Lscala/Option;Lscala/Option;Ljava/lang/String;J)Lorg/scalatest/events/TestPending;
       101: areturn
      LineNumberTable:
        line 871: 0
      LocalVariableTable:
        Start  Length  Slot  Name   Signature
            2      99     2   x$1   Lscala/Option;
            7      94     3   x$2   Lorg/scalatest/events/Ordinal;
           13      88     4   x$3   Ljava/lang/String;
           19      82     5   x$4   Ljava/lang/String;
           25      76     6   x$5   Lscala/Option;
           31      70     7   x$6   Ljava/lang/String;
           37      64     8   x$7   Ljava/lang/String;
           43      58     9   x$8   Lscala/collection/immutable/IndexedSeq;
           49      52    10   x$9   Lscala/Option;
           55      46    11  x$10   Lscala/Option;
           61      40    12  x$11   Lscala/Option;
           67      34    13  x$12   Ljava/lang/String;
           73      28    14  x$13   J
            0     102     0  this   Lorg/scalatest/events/TestPending;
            0     102     1 newPayload   Lscala/Option;
    Signature: #405                         // (Lscala/Option<Ljava/lang/Object;>;)Lorg/scalatest/events/TestPending;
    MethodParameters:
      Name                           Flags
      newPayload                     final

  public org.scalatest.events.TestPending copy(org.scalatest.events.Ordinal, java.lang.String, java.lang.String, scala.Option<java.lang.String>, java.lang.String, java.lang.String, scala.collection.immutable.IndexedSeq<org.scalatest.events.RecordableEvent>, scala.Option<java.lang.Object>, scala.Option<org.scalatest.events.Formatter>, scala.Option<org.scalatest.events.Location>, scala.Option<java.lang.Object>, java.lang.String, long);
    descriptor: (Lorg/scalatest/events/Ordinal;Ljava/lang/String;Ljava/lang/String;Lscala/Option;Ljava/lang/String;Ljava/lang/String;Lscala/collection/immutable/IndexedSeq;Lscala/Option;Lscala/Option;Lscala/Option;Lscala/Option;Ljava/lang/String;J)Lorg/scalatest/events/TestPending;
    flags: (0x0001) ACC_PUBLIC
    Code:
      stack=16, locals=15, args_size=14
         0: new           #2                  // class org/scalatest/events/TestPending
         3: dup
         4: aload_1
         5: aload_2
         6: aload_3
         7: aload         4
         9: aload         5
        11: aload         6
        13: aload         7
        15: aload         8
        17: aload         9
        19: aload         10
        21: aload         11
        23: aload         12
        25: lload         13
        27: invokespecial #461                // Method "<init>":(Lorg/scalatest/events/Ordinal;Ljava/lang/String;Ljava/lang/String;Lscala/Option;Ljava/lang/String;Ljava/lang/String;Lscala/collection/immutable/IndexedSeq;Lscala/Option;Lscala/Option;Lscala/Option;Lscala/Option;Ljava/lang/String;J)V
        30: areturn
      LineNumberTable:
        line 816: 0
        line 817: 4
        line 818: 5
        line 819: 6
        line 820: 7
        line 821: 9
        line 822: 11
        line 823: 13
        line 824: 15
        line 825: 17
        line 826: 19
        line 827: 21
        line 828: 23
        line 829: 25
      LocalVariableTable:
        Start  Length  Slot  Name   Signature
            0      31     0  this   Lorg/scalatest/events/TestPending;
            0      31     1 ordinal   Lorg/scalatest/events/Ordinal;
            0      31     2 suiteName   Ljava/lang/String;
            0      31     3 suiteId   Ljava/lang/String;
            0      31     4 suiteClassName   Lscala/Option;
            0      31     5 testName   Ljava/lang/String;
            0      31     6 testText   Ljava/lang/String;
            0      31     7 recordedEvents   Lscala/collection/immutable/IndexedSeq;
            0      31     8 duration   Lscala/Option;
            0      31     9 formatter   Lscala/Option;
            0      31    10 location   Lscala/Option;
            0      31    11 payload   Lscala/Option;
            0      31    12 threadName   Ljava/lang/String;
            0      31    13 timeStamp   J
    Signature: #105                         // (Lorg/scalatest/events/Ordinal;Ljava/lang/String;Ljava/lang/String;Lscala/Option<Ljava/lang/String;>;Ljava/lang/String;Ljava/lang/String;Lscala/collection/immutable/IndexedSeq<Lorg/scalatest/events/RecordableEvent;>;Lscala/Option<Ljava/lang/Object;>;Lscala/Option<Lorg/scalatest/events/Formatter;>;Lscala/Option<Lorg/scalatest/events/Location;>;Lscala/Option<Ljava/lang/Object;>;Ljava/lang/String;J)Lorg/scalatest/events/TestPending;
    MethodParameters:
      Name                           Flags
      ordinal                        final
      suiteName                      final
      suiteId                        final
      suiteClassName                 final
      testName                       final
      testText                       final
      recordedEvents                 final
      duration                       final
      formatter                      final
      location                       final
      payload                        final
      threadName                     final
      timeStamp                      final

  public org.scalatest.events.Ordinal copy$default$1();
    descriptor: ()Lorg/scalatest/events/Ordinal;
    flags: (0x0001) ACC_PUBLIC
    Code:
      stack=1, locals=1, args_size=1
         0: aload_0
         1: invokevirtual #192                // Method ordinal:()Lorg/scalatest/events/Ordinal;
         4: areturn
      LineNumberTable:
        line 817: 0
      LocalVariableTable:
        Start  Length  Slot  Name   Signature
            0       5     0  this   Lorg/scalatest/events/TestPending;

  public scala.Option<org.scalatest.events.Location> copy$default$10();
    descriptor: ()Lscala/Option;
    flags: (0x0001) ACC_PUBLIC
    Code:
      stack=1, locals=1, args_size=1
         0: aload_0
         1: invokevirtual #277                // Method location:()Lscala/Option;
         4: areturn
      LineNumberTable:
        line 826: 0
      LocalVariableTable:
        Start  Length  Slot  Name   Signature
            0       5     0  this   Lorg/scalatest/events/TestPending;
    Signature: #68                          // ()Lscala/Option<Lorg/scalatest/events/Location;>;

  public scala.Option<java.lang.Object> copy$default$11();
    descriptor: ()Lscala/Option;
    flags: (0x0001) ACC_PUBLIC
    Code:
      stack=1, locals=1, args_size=1
         0: aload_0
         1: invokevirtual #464                // Method payload:()Lscala/Option;
         4: areturn
      LineNumberTable:
        line 827: 0
      LocalVariableTable:
        Start  Length  Slot  Name   Signature
            0       5     0  this   Lorg/scalatest/events/TestPending;
    Signature: #64                          // ()Lscala/Option<Ljava/lang/Object;>;

  public java.lang.String copy$default$12();
    descriptor: ()Ljava/lang/String;
    flags: (0x0001) ACC_PUBLIC
    Code:
      stack=1, locals=1, args_size=1
         0: aload_0
         1: invokevirtual #283                // Method threadName:()Ljava/lang/String;
         4: areturn
      LineNumberTable:
        line 828: 0
      LocalVariableTable:
        Start  Length  Slot  Name   Signature
            0       5     0  this   Lorg/scalatest/events/TestPending;

  public long copy$default$13();
    descriptor: ()J
    flags: (0x0001) ACC_PUBLIC
    Code:
      stack=2, locals=1, args_size=1
         0: aload_0
         1: invokevirtual #286                // Method timeStamp:()J
         4: lreturn
      LineNumberTable:
        line 829: 0
      LocalVariableTable:
        Start  Length  Slot  Name   Signature
            0       5     0  this   Lorg/scalatest/events/TestPending;

  public java.lang.String copy$default$2();
    descriptor: ()Ljava/lang/String;
    flags: (0x0001) ACC_PUBLIC
    Code:
      stack=1, locals=1, args_size=1
         0: aload_0
         1: invokevirtual #213                // Method suiteName:()Ljava/lang/String;
         4: areturn
      LineNumberTable:
        line 818: 0
      LocalVariableTable:
        Start  Length  Slot  Name   Signature
            0       5     0  this   Lorg/scalatest/events/TestPending;

  public java.lang.String copy$default$3();
    descriptor: ()Ljava/lang/String;
    flags: (0x0001) ACC_PUBLIC
    Code:
      stack=1, locals=1, args_size=1
         0: aload_0
         1: invokevirtual #216                // Method suiteId:()Ljava/lang/String;
         4: areturn
      LineNumberTable:
        line 819: 0
      LocalVariableTable:
        Start  Length  Slot  Name   Signature
            0       5     0  this   Lorg/scalatest/events/TestPending;

  public scala.Option<java.lang.String> copy$default$4();
    descriptor: ()Lscala/Option;
    flags: (0x0001) ACC_PUBLIC
    Code:
      stack=1, locals=1, args_size=1
         0: aload_0
         1: invokevirtual #223                // Method suiteClassName:()Lscala/Option;
         4: areturn
      LineNumberTable:
        line 820: 0
      LocalVariableTable:
        Start  Length  Slot  Name   Signature
            0       5     0  this   Lorg/scalatest/events/TestPending;
    Signature: #125                         // ()Lscala/Option<Ljava/lang/String;>;

  public java.lang.String copy$default$5();
    descriptor: ()Ljava/lang/String;
    flags: (0x0001) ACC_PUBLIC
    Code:
      stack=1, locals=1, args_size=1
         0: aload_0
         1: invokevirtual #236                // Method testName:()Ljava/lang/String;
         4: areturn
      LineNumberTable:
        line 821: 0
      LocalVariableTable:
        Start  Length  Slot  Name   Signature
            0       5     0  this   Lorg/scalatest/events/TestPending;

  public java.lang.String copy$default$6();
    descriptor: ()Ljava/lang/String;
    flags: (0x0001) ACC_PUBLIC
    Code:
      stack=1, locals=1, args_size=1
         0: aload_0
         1: invokevirtual #239                // Method testText:()Ljava/lang/String;
         4: areturn
      LineNumberTable:
        line 822: 0
      LocalVariableTable:
        Start  Length  Slot  Name   Signature
            0       5     0  this   Lorg/scalatest/events/TestPending;

  public scala.collection.immutable.IndexedSeq<org.scalatest.events.RecordableEvent> copy$default$7();
    descriptor: ()Lscala/collection/immutable/IndexedSeq;
    flags: (0x0001) ACC_PUBLIC
    Code:
      stack=1, locals=1, args_size=1
         0: aload_0
         1: invokevirtual #242                // Method recordedEvents:()Lscala/collection/immutable/IndexedSeq;
         4: areturn
      LineNumberTable:
        line 823: 0
      LocalVariableTable:
        Start  Length  Slot  Name   Signature
            0       5     0  this   Lorg/scalatest/events/TestPending;
    Signature: #133                         // ()Lscala/collection/immutable/IndexedSeq<Lorg/scalatest/events/RecordableEvent;>;

  public scala.Option<java.lang.Object> copy$default$8();
    descriptor: ()Lscala/Option;
    flags: (0x0001) ACC_PUBLIC
    Code:
      stack=1, locals=1, args_size=1
         0: aload_0
         1: invokevirtual #230                // Method duration:()Lscala/Option;
         4: areturn
      LineNumberTable:
        line 824: 0
      LocalVariableTable:
        Start  Length  Slot  Name   Signature
            0       5     0  this   Lorg/scalatest/events/TestPending;
    Signature: #64                          // ()Lscala/Option<Ljava/lang/Object;>;

  public scala.Option<org.scalatest.events.Formatter> copy$default$9();
    descriptor: ()Lscala/Option;
    flags: (0x0001) ACC_PUBLIC
    Code:
      stack=1, locals=1, args_size=1
         0: aload_0
         1: invokevirtual #270                // Method formatter:()Lscala/Option;
         4: areturn
      LineNumberTable:
        line 825: 0
      LocalVariableTable:
        Start  Length  Slot  Name   Signature
            0       5     0  this   Lorg/scalatest/events/TestPending;
    Signature: #72                          // ()Lscala/Option<Lorg/scalatest/events/Formatter;>;

  public java.lang.String productPrefix();
    descriptor: ()Ljava/lang/String;
    flags: (0x0001) ACC_PUBLIC
    Code:
      stack=1, locals=1, args_size=1
         0: ldc           #153                // String TestPending
         2: areturn
      LineNumberTable:
        line 816: 0
      LocalVariableTable:
        Start  Length  Slot  Name   Signature
            0       3     0  this   Lorg/scalatest/events/TestPending;

  public int productArity();
    descriptor: ()I
    flags: (0x0001) ACC_PUBLIC
    Code:
      stack=1, locals=1, args_size=1
         0: bipush        13
         2: ireturn
      LineNumberTable:
        line 816: 0
      LocalVariableTable:
        Start  Length  Slot  Name   Signature
            0       3     0  this   Lorg/scalatest/events/TestPending;

  public java.lang.Object productElement(int);
    descriptor: (I)Ljava/lang/Object;
    flags: (0x0001) ACC_PUBLIC
    Code:
      stack=2, locals=3, args_size=2
         0: iload_1
         1: istore_2
         2: iload_2
         3: tableswitch   { // 0 to 12
                       0: 68
                       1: 75
                       2: 82
                       3: 89
                       4: 96
                       5: 103
                       6: 110
                       7: 117
                       8: 124
                       9: 131
                      10: 138
                      11: 145
                      12: 152
                 default: 162
            }
        68: aload_0
        69: invokevirtual #192                // Method ordinal:()Lorg/scalatest/events/Ordinal;
        72: goto          169
        75: aload_0
        76: invokevirtual #213                // Method suiteName:()Ljava/lang/String;
        79: goto          169
        82: aload_0
        83: invokevirtual #216                // Method suiteId:()Ljava/lang/String;
        86: goto          169
        89: aload_0
        90: invokevirtual #223                // Method suiteClassName:()Lscala/Option;
        93: goto          169
        96: aload_0
        97: invokevirtual #236                // Method testName:()Ljava/lang/String;
       100: goto          169
       103: aload_0
       104: invokevirtual #239                // Method testText:()Ljava/lang/String;
       107: goto          169
       110: aload_0
       111: invokevirtual #242                // Method recordedEvents:()Lscala/collection/immutable/IndexedSeq;
       114: goto          169
       117: aload_0
       118: invokevirtual #230                // Method duration:()Lscala/Option;
       121: goto          169
       124: aload_0
       125: invokevirtual #270                // Method formatter:()Lscala/Option;
       128: goto          169
       131: aload_0
       132: invokevirtual #277                // Method location:()Lscala/Option;
       135: goto          169
       138: aload_0
       139: invokevirtual #464                // Method payload:()Lscala/Option;
       142: goto          169
       145: aload_0
       146: invokevirtual #283                // Method threadName:()Ljava/lang/String;
       149: goto          169
       152: aload_0
       153: invokevirtual #286                // Method timeStamp:()J
       156: invokestatic  #290                // Method scala/runtime/BoxesRunTime.boxToLong:(J)Ljava/lang/Long;
       159: goto          169
       162: iload_1
       163: invokestatic  #473                // Method scala/runtime/Statics.ioobe:(I)Ljava/lang/Object;
       166: goto          169
       169: areturn
      StackMapTable: number_of_entries = 15
        frame_type = 252 /* append */
          offset_delta = 68
          locals = [ int ]
        frame_type = 6 /* same */
        frame_type = 6 /* same */
        frame_type = 6 /* same */
        frame_type = 6 /* same */
        frame_type = 6 /* same */
        frame_type = 6 /* same */
        frame_type = 6 /* same */
        frame_type = 6 /* same */
        frame_type = 6 /* same */
        frame_type = 6 /* same */
        frame_type = 6 /* same */
        frame_type = 6 /* same */
        frame_type = 9 /* same */
        frame_type = 70 /* same_locals_1_stack_item */
          stack = [ class java/lang/Object ]
      LineNumberTable:
        line 816: 0
      LocalVariableTable:
        Start  Length  Slot  Name   Signature
            0     170     0  this   Lorg/scalatest/events/TestPending;
            0     170     1   x$1   I
    MethodParameters:
      Name                           Flags
      x$1                            final

  public scala.collection.Iterator<java.lang.Object> productIterator();
    descriptor: ()Lscala/collection/Iterator;
    flags: (0x0001) ACC_PUBLIC
    Code:
      stack=2, locals=1, args_size=1
         0: getstatic     #484                // Field scala/runtime/ScalaRunTime$.MODULE$:Lscala/runtime/ScalaRunTime$;
         3: aload_0
         4: invokevirtual #488                // Method scala/runtime/ScalaRunTime$.typedProductIterator:(Lscala/Product;)Lscala/collection/Iterator;
         7: areturn
      LineNumberTable:
        line 816: 0
      LocalVariableTable:
        Start  Length  Slot  Name   Signature
            0       8     0  this   Lorg/scalatest/events/TestPending;
    Signature: #479                         // ()Lscala/collection/Iterator<Ljava/lang/Object;>;

  public boolean canEqual(java.lang.Object);
    descriptor: (Ljava/lang/Object;)Z
    flags: (0x0001) ACC_PUBLIC
    Code:
      stack=1, locals=2, args_size=2
         0: aload_1
         1: instanceof    #2                  // class org/scalatest/events/TestPending
         4: ireturn
      LineNumberTable:
        line 816: 0
      LocalVariableTable:
        Start  Length  Slot  Name   Signature
            0       5     0  this   Lorg/scalatest/events/TestPending;
            0       5     1   x$1   Ljava/lang/Object;
    MethodParameters:
      Name                           Flags
      x$1                            final

  public java.lang.String productElementName(int);
    descriptor: (I)Ljava/lang/String;
    flags: (0x0001) ACC_PUBLIC
    Code:
      stack=1, locals=3, args_size=2
         0: iload_1
         1: istore_2
         2: iload_2
         3: tableswitch   { // 0 to 12
                       0: 68
                       1: 73
                       2: 78
                       3: 83
                       4: 88
                       5: 93
                       6: 98
                       7: 103
                       8: 108
                       9: 114
                      10: 120
                      11: 126
                      12: 132
                 default: 138
            }
        68: ldc           #186                // String ordinal
        70: goto          148
        73: ldc           #211                // String suiteName
        75: goto          148
        78: ldc           #214                // String suiteId
        80: goto          148
        83: ldc           #217                // String suiteClassName
        85: goto          148
        88: ldc           #234                // String testName
        90: goto          148
        93: ldc           #237                // String testText
        95: goto          148
        98: ldc           #240                // String recordedEvents
       100: goto          148
       103: ldc           #228                // String duration
       105: goto          148
       108: ldc_w         #268                // String formatter
       111: goto          148
       114: ldc_w         #275                // String location
       117: goto          148
       120: ldc_w         #494                // String payload
       123: goto          148
       126: ldc_w         #281                // String threadName
       129: goto          148
       132: ldc_w         #284                // String timeStamp
       135: goto          148
       138: iload_1
       139: invokestatic  #473                // Method scala/runtime/Statics.ioobe:(I)Ljava/lang/Object;
       142: checkcast     #496                // class java/lang/String
       145: goto          148
       148: areturn
      StackMapTable: number_of_entries = 15
        frame_type = 252 /* append */
          offset_delta = 68
          locals = [ int ]
        frame_type = 4 /* same */
        frame_type = 4 /* same */
        frame_type = 4 /* same */
        frame_type = 4 /* same */
        frame_type = 4 /* same */
        frame_type = 4 /* same */
        frame_type = 4 /* same */
        frame_type = 4 /* same */
        frame_type = 5 /* same */
        frame_type = 5 /* same */
        frame_type = 5 /* same */
        frame_type = 5 /* same */
        frame_type = 5 /* same */
        frame_type = 73 /* same_locals_1_stack_item */
          stack = [ class java/lang/String ]
      LineNumberTable:
        line 816: 0
      LocalVariableTable:
        Start  Length  Slot  Name   Signature
            0     149     0  this   Lorg/scalatest/events/TestPending;
            0     149     1   x$1   I
    MethodParameters:
      Name                           Flags
      x$1                            final

  public int hashCode();
    descriptor: ()I
    flags: (0x0001) ACC_PUBLIC
    Code:
      stack=3, locals=2, args_size=1
         0: ldc_w         #498                // int -889275714
         3: istore_1
         4: iload_1
         5: aload_0
         6: invokevirtual #500                // Method productPrefix:()Ljava/lang/String;
         9: invokevirtual #502                // Method java/lang/String.hashCode:()I
        12: invokestatic  #506                // Method scala/runtime/Statics.mix:(II)I
        15: istore_1
        16: iload_1
        17: aload_0
        18: invokevirtual #192                // Method ordinal:()Lorg/scalatest/events/Ordinal;
        21: invokestatic  #510                // Method scala/runtime/Statics.anyHash:(Ljava/lang/Object;)I
        24: invokestatic  #506                // Method scala/runtime/Statics.mix:(II)I
        27: istore_1
        28: iload_1
        29: aload_0
        30: invokevirtual #213                // Method suiteName:()Ljava/lang/String;
        33: invokestatic  #510                // Method scala/runtime/Statics.anyHash:(Ljava/lang/Object;)I
        36: invokestatic  #506                // Method scala/runtime/Statics.mix:(II)I
        39: istore_1
        40: iload_1
        41: aload_0
        42: invokevirtual #216                // Method suiteId:()Ljava/lang/String;
        45: invokestatic  #510                // Method scala/runtime/Statics.anyHash:(Ljava/lang/Object;)I
        48: invokestatic  #506                // Method scala/runtime/Statics.mix:(II)I
        51: istore_1
        52: iload_1
        53: aload_0
        54: invokevirtual #223                // Method suiteClassName:()Lscala/Option;
        57: invokestatic  #510                // Method scala/runtime/Statics.anyHash:(Ljava/lang/Object;)I
        60: invokestatic  #506                // Method scala/runtime/Statics.mix:(II)I
        63: istore_1
        64: iload_1
        65: aload_0
        66: invokevirtual #236                // Method testName:()Ljava/lang/String;
        69: invokestatic  #510                // Method scala/runtime/Statics.anyHash:(Ljava/lang/Object;)I
        72: invokestatic  #506                // Method scala/runtime/Statics.mix:(II)I
        75: istore_1
        76: iload_1
        77: aload_0
        78: invokevirtual #239                // Method testText:()Ljava/lang/String;
        81: invokestatic  #510                // Method scala/runtime/Statics.anyHash:(Ljava/lang/Object;)I
        84: invokestatic  #506                // Method scala/runtime/Statics.mix:(II)I
        87: istore_1
        88: iload_1
        89: aload_0
        90: invokevirtual #242                // Method recordedEvents:()Lscala/collection/immutable/IndexedSeq;
        93: invokestatic  #510                // Method scala/runtime/Statics.anyHash:(Ljava/lang/Object;)I
        96: invokestatic  #506                // Method scala/runtime/Statics.mix:(II)I
        99: istore_1
       100: iload_1
       101: aload_0
       102: invokevirtual #230                // Method duration:()Lscala/Option;
       105: invokestatic  #510                // Method scala/runtime/Statics.anyHash:(Ljava/lang/Object;)I
       108: invokestatic  #506                // Method scala/runtime/Statics.mix:(II)I
       111: istore_1
       112: iload_1
       113: aload_0
       114: invokevirtual #270                // Method formatter:()Lscala/Option;
       117: invokestatic  #510                // Method scala/runtime/Statics.anyHash:(Ljava/lang/Object;)I
       120: invokestatic  #506                // Method scala/runtime/Statics.mix:(II)I
       123: istore_1
       124: iload_1
       125: aload_0
       126: invokevirtual #277                // Method location:()Lscala/Option;
       129: invokestatic  #510                // Method scala/runtime/Statics.anyHash:(Ljava/lang/Object;)I
       132: invokestatic  #506                // Method scala/runtime/Statics.mix:(II)I
       135: istore_1
       136: iload_1
       137: aload_0
       138: invokevirtual #464                // Method payload:()Lscala/Option;
       141: invokestatic  #510                // Method scala/runtime/Statics.anyHash:(Ljava/lang/Object;)I
       144: invokestatic  #506                // Method scala/runtime/Statics.mix:(II)I
       147: istore_1
       148: iload_1
       149: aload_0
       150: invokevirtual #283                // Method threadName:()Ljava/lang/String;
       153: invokestatic  #510                // Method scala/runtime/Statics.anyHash:(Ljava/lang/Object;)I
       156: invokestatic  #506                // Method scala/runtime/Statics.mix:(II)I
       159: istore_1
       160: iload_1
       161: aload_0
       162: invokevirtual #286                // Method timeStamp:()J
       165: invokestatic  #514                // Method scala/runtime/Statics.longHash:(J)I
       168: invokestatic  #506                // Method scala/runtime/Statics.mix:(II)I
       171: istore_1
       172: iload_1
       173: bipush        13
       175: invokestatic  #517                // Method scala/runtime/Statics.finalizeHash:(II)I
       178: ireturn
      LineNumberTable:
        line 816: 0
      LocalVariableTable:
        Start  Length  Slot  Name   Signature
            0     179     0  this   Lorg/scalatest/events/TestPending;

  public java.lang.String toString();
    descriptor: ()Ljava/lang/String;
    flags: (0x0001) ACC_PUBLIC
    Code:
      stack=2, locals=1, args_size=1
         0: getstatic     #484                // Field scala/runtime/ScalaRunTime$.MODULE$:Lscala/runtime/ScalaRunTime$;
         3: aload_0
         4: invokevirtual #521                // Method scala/runtime/ScalaRunTime$._toString:(Lscala/Product;)Ljava/lang/String;
         7: areturn
      LineNumberTable:
        line 816: 0
      LocalVariableTable:
        Start  Length  Slot  Name   Signature
            0       8     0  this   Lorg/scalatest/events/TestPending;

  public boolean equals(java.lang.Object);
    descriptor: (Ljava/lang/Object;)Z
    flags: (0x0001) ACC_PUBLIC
    Code:
      stack=4, locals=17, args_size=2
         0: aload_0
         1: aload_1
         2: if_acmpeq     442
         5: aload_1
         6: astore_3
         7: aload_3
         8: instanceof    #2                  // class org/scalatest/events/TestPending
        11: ifeq          19
        14: iconst_1
        15: istore_2
        16: goto          27
        19: goto          22
        22: iconst_0
        23: istore_2
        24: goto          27
        27: iload_2
        28: ifeq          446
        31: aload_1
        32: checkcast     #2                  // class org/scalatest/events/TestPending
        35: astore        4
        37: aload_0
        38: invokevirtual #286                // Method timeStamp:()J
        41: aload         4
        43: invokevirtual #286                // Method timeStamp:()J
        46: lcmp
        47: ifne          438
        50: aload_0
        51: invokevirtual #192                // Method ordinal:()Lorg/scalatest/events/Ordinal;
        54: aload         4
        56: invokevirtual #192                // Method ordinal:()Lorg/scalatest/events/Ordinal;
        59: astore        5
        61: dup
        62: ifnonnull     74
        65: pop
        66: aload         5
        68: ifnull        82
        71: goto          438
        74: aload         5
        76: invokevirtual #524                // Method java/lang/Object.equals:(Ljava/lang/Object;)Z
        79: ifeq          438
        82: aload_0
        83: invokevirtual #213                // Method suiteName:()Ljava/lang/String;
        86: aload         4
        88: invokevirtual #213                // Method suiteName:()Ljava/lang/String;
        91: astore        6
        93: dup
        94: ifnonnull     106
        97: pop
        98: aload         6
       100: ifnull        114
       103: goto          438
       106: aload         6
       108: invokevirtual #524                // Method java/lang/Object.equals:(Ljava/lang/Object;)Z
       111: ifeq          438
       114: aload_0
       115: invokevirtual #216                // Method suiteId:()Ljava/lang/String;
       118: aload         4
       120: invokevirtual #216                // Method suiteId:()Ljava/lang/String;
       123: astore        7
       125: dup
       126: ifnonnull     138
       129: pop
       130: aload         7
       132: ifnull        146
       135: goto          438
       138: aload         7
       140: invokevirtual #524                // Method java/lang/Object.equals:(Ljava/lang/Object;)Z
       143: ifeq          438
       146: aload_0
       147: invokevirtual #223                // Method suiteClassName:()Lscala/Option;
       150: aload         4
       152: invokevirtual #223                // Method suiteClassName:()Lscala/Option;
       155: astore        8
       157: dup
       158: ifnonnull     170
       161: pop
       162: aload         8
       164: ifnull        178
       167: goto          438
       170: aload         8
       172: invokevirtual #524                // Method java/lang/Object.equals:(Ljava/lang/Object;)Z
       175: ifeq          438
       178: aload_0
       179: invokevirtual #236                // Method testName:()Ljava/lang/String;
       182: aload         4
       184: invokevirtual #236                // Method testName:()Ljava/lang/String;
       187: astore        9
       189: dup
       190: ifnonnull     202
       193: pop
       194: aload         9
       196: ifnull        210
       199: goto          438
       202: aload         9
       204: invokevirtual #524                // Method java/lang/Object.equals:(Ljava/lang/Object;)Z
       207: ifeq          438
       210: aload_0
       211: invokevirtual #239                // Method testText:()Ljava/lang/String;
       214: aload         4
       216: invokevirtual #239                // Method testText:()Ljava/lang/String;
       219: astore        10
       221: dup
       222: ifnonnull     234
       225: pop
       226: aload         10
       228: ifnull        242
       231: goto          438
       234: aload         10
       236: invokevirtual #524                // Method java/lang/Object.equals:(Ljava/lang/Object;)Z
       239: ifeq          438
       242: aload_0
       243: invokevirtual #242                // Method recordedEvents:()Lscala/collection/immutable/IndexedSeq;
       246: aload         4
       248: invokevirtual #242                // Method recordedEvents:()Lscala/collection/immutable/IndexedSeq;
       251: astore        11
       253: dup
       254: ifnonnull     266
       257: pop
       258: aload         11
       260: ifnull        274
       263: goto          438
       266: aload         11
       268: invokevirtual #524                // Method java/lang/Object.equals:(Ljava/lang/Object;)Z
       271: ifeq          438
       274: aload_0
       275: invokevirtual #230                // Method duration:()Lscala/Option;
       278: aload         4
       280: invokevirtual #230                // Method duration:()Lscala/Option;
       283: astore        12
       285: dup
       286: ifnonnull     298
       289: pop
       290: aload         12
       292: ifnull        306
       295: goto          438
       298: aload         12
       300: invokevirtual #524                // Method java/lang/Object.equals:(Ljava/lang/Object;)Z
       303: ifeq          438
       306: aload_0
       307: invokevirtual #270                // Method formatter:()Lscala/Option;
       310: aload         4
       312: invokevirtual #270                // Method formatter:()Lscala/Option;
       315: astore        13
       317: dup
       318: ifnonnull     330
       321: pop
       322: aload         13
       324: ifnull        338
       327: goto          438
       330: aload         13
       332: invokevirtual #524                // Method java/lang/Object.equals:(Ljava/lang/Object;)Z
       335: ifeq          438
       338: aload_0
       339: invokevirtual #277                // Method location:()Lscala/Option;
       342: aload         4
       344: invokevirtual #277                // Method location:()Lscala/Option;
       347: astore        14
       349: dup
       350: ifnonnull     362
       353: pop
       354: aload         14
       356: ifnull        370
       359: goto          438
       362: aload         14
       364: invokevirtual #524                // Method java/lang/Object.equals:(Ljava/lang/Object;)Z
       367: ifeq          438
       370: aload_0
       371: invokevirtual #464                // Method payload:()Lscala/Option;
       374: aload         4
       376: invokevirtual #464                // Method payload:()Lscala/Option;
       379: astore        15
       381: dup
       382: ifnonnull     394
       385: pop
       386: aload         15
       388: ifnull        402
       391: goto          438
       394: aload         15
       396: invokevirtual #524                // Method java/lang/Object.equals:(Ljava/lang/Object;)Z
       399: ifeq          438
       402: aload_0
       403: invokevirtual #283                // Method threadName:()Ljava/lang/String;
       406: aload         4
       408: invokevirtual #283                // Method threadName:()Ljava/lang/String;
       411: astore        16
       413: dup
       414: ifnonnull     426
       417: pop
       418: aload         16
       420: ifnull        434
       423: goto          438
       426: aload         16
       428: invokevirtual #524                // Method java/lang/Object.equals:(Ljava/lang/Object;)Z
       431: ifeq          438
       434: iconst_1
       435: goto          439
       438: iconst_0
       439: ifeq          446
       442: iconst_1
       443: goto          447
       446: iconst_0
       447: ireturn
      StackMapTable: number_of_entries = 32
        frame_type = 253 /* append */
          offset_delta = 19
          locals = [ top, class java/lang/Object ]
        frame_type = 2 /* same */
        frame_type = 255 /* full_frame */
          offset_delta = 4
          locals = [ class org/scalatest/events/TestPending, class java/lang/Object, int, class java/lang/Object ]
          stack = []
        frame_type = 255 /* full_frame */
          offset_delta = 46
          locals = [ class org/scalatest/events/TestPending, class java/lang/Object, int, class java/lang/Object, class org/scalatest/events/TestPending, class org/scalatest/events/Ordinal ]
          stack = [ class org/scalatest/events/Ordinal ]
        frame_type = 7 /* same */
        frame_type = 255 /* full_frame */
          offset_delta = 23
          locals = [ class org/scalatest/events/TestPending, class java/lang/Object, int, class java/lang/Object, class org/scalatest/events/TestPending, class org/scalatest/events/Ordinal, class java/lang/String ]
          stack = [ class java/lang/String ]
        frame_type = 7 /* same */
        frame_type = 255 /* full_frame */
          offset_delta = 23
          locals = [ class org/scalatest/events/TestPending, class java/lang/Object, int, class java/lang/Object, class org/scalatest/events/TestPending, class org/scalatest/events/Ordinal, class java/lang/String, class java/lang/String ]
          stack = [ class java/lang/String ]
        frame_type = 7 /* same */
        frame_type = 255 /* full_frame */
          offset_delta = 23
          locals = [ class org/scalatest/events/TestPending, class java/lang/Object, int, class java/lang/Object, class org/scalatest/events/TestPending, class org/scalatest/events/Ordinal, class java/lang/String, class java/lang/String, class scala/Option ]
          stack = [ class scala/Option ]
        frame_type = 7 /* same */
        frame_type = 255 /* full_frame */
          offset_delta = 23
          locals = [ class org/scalatest/events/TestPending, class java/lang/Object, int, class java/lang/Object, class org/scalatest/events/TestPending, class org/scalatest/events/Ordinal, class java/lang/String, class java/lang/String, class scala/Option, class java/lang/String ]
          stack = [ class java/lang/String ]
        frame_type = 7 /* same */
        frame_type = 255 /* full_frame */
          offset_delta = 23
          locals = [ class org/scalatest/events/TestPending, class java/lang/Object, int, class java/lang/Object, class org/scalatest/events/TestPending, class org/scalatest/events/Ordinal, class java/lang/String, class java/lang/String, class scala/Option, class java/lang/String, class java/lang/String ]
          stack = [ class java/lang/String ]
        frame_type = 7 /* same */
        frame_type = 255 /* full_frame */
          offset_delta = 23
          locals = [ class org/scalatest/events/TestPending, class java/lang/Object, int, class java/lang/Object, class org/scalatest/events/TestPending, class org/scalatest/events/Ordinal, class java/lang/String, class java/lang/String, class scala/Option, class java/lang/String, class java/lang/String, class scala/collection/immutable/IndexedSeq ]
          stack = [ class scala/collection/immutable/IndexedSeq ]
        frame_type = 7 /* same */
        frame_type = 255 /* full_frame */
          offset_delta = 23
          locals = [ class org/scalatest/events/TestPending, class java/lang/Object, int, class java/lang/Object, class org/scalatest/events/TestPending, class org/scalatest/events/Ordinal, class java/lang/String, class java/lang/String, class scala/Option, class java/lang/String, class java/lang/String, class scala/collection/immutable/IndexedSeq, class scala/Option ]
          stack = [ class scala/Option ]
        frame_type = 7 /* same */
        frame_type = 255 /* full_frame */
          offset_delta = 23
          locals = [ class org/scalatest/events/TestPending, class java/lang/Object, int, class java/lang/Object, class org/scalatest/events/TestPending, class org/scalatest/events/Ordinal, class java/lang/String, class java/lang/String, class scala/Option, class java/lang/String, class java/lang/String, class scala/collection/immutable/IndexedSeq, class scala/Option, class scala/Option ]
          stack = [ class scala/Option ]
        frame_type = 7 /* same */
        frame_type = 255 /* full_frame */
          offset_delta = 23
          locals = [ class org/scalatest/events/TestPending, class java/lang/Object, int, class java/lang/Object, class org/scalatest/events/TestPending, class org/scalatest/events/Ordinal, class java/lang/String, class java/lang/String, class scala/Option, class java/lang/String, class java/lang/String, class scala/collection/immutable/IndexedSeq, class scala/Option, class scala/Option, class scala/Option ]
          stack = [ class scala/Option ]
        frame_type = 7 /* same */
        frame_type = 255 /* full_frame */
          offset_delta = 23
          locals = [ class org/scalatest/events/TestPending, class java/lang/Object, int, class java/lang/Object, class org/scalatest/events/TestPending, class org/scalatest/events/Ordinal, class java/lang/String, class java/lang/String, class scala/Option, class java/lang/String, class java/lang/String, class scala/collection/immutable/IndexedSeq, class scala/Option, class scala/Option, class scala/Option, class scala/Option ]
          stack = [ class scala/Option ]
        frame_type = 7 /* same */
        frame_type = 255 /* full_frame */
          offset_delta = 23
          locals = [ class org/scalatest/events/TestPending, class java/lang/Object, int, class java/lang/Object, class org/scalatest/events/TestPending, class org/scalatest/events/Ordinal, class java/lang/String, class java/lang/String, class scala/Option, class java/lang/String, class java/lang/String, class scala/collection/immutable/IndexedSeq, class scala/Option, class scala/Option, class scala/Option, class scala/Option, class java/lang/String ]
          stack = [ class java/lang/String ]
        frame_type = 7 /* same */
        frame_type = 255 /* full_frame */
          offset_delta = 3
          locals = [ class org/scalatest/events/TestPending, class java/lang/Object, int, class java/lang/Object, class org/scalatest/events/TestPending ]
          stack = []
        frame_type = 64 /* same_locals_1_stack_item */
          stack = [ int ]
        frame_type = 248 /* chop */
          offset_delta = 2
        frame_type = 253 /* append */
          offset_delta = 3
          locals = [ int, class java/lang/Object ]
        frame_type = 255 /* full_frame */
          offset_delta = 0
          locals = [ class org/scalatest/events/TestPending, class java/lang/Object ]
          stack = [ int ]
      LineNumberTable:
        line 816: 0
      LocalVariableTable:
        Start  Length  Slot  Name   Signature
            0     448     0  this   Lorg/scalatest/events/TestPending;
            0     448     1   x$1   Ljava/lang/Object;
    MethodParameters:
      Name                           Flags
      x$1                            final

  public org.scalatest.events.Event withPayload(scala.Option);
    descriptor: (Lscala/Option;)Lorg/scalatest/events/Event;
    flags: (0x1041) ACC_PUBLIC, ACC_BRIDGE, ACC_SYNTHETIC
    Code:
      stack=2, locals=2, args_size=2
         0: aload_0
         1: aload_1
         2: invokevirtual #527                // Method withPayload:(Lscala/Option;)Lorg/scalatest/events/TestPending;
         5: areturn
      LineNumberTable:
        line 816: 0
      LocalVariableTable:
        Start  Length  Slot  Name   Signature
            0       6     0  this   Lorg/scalatest/events/TestPending;
            0       6     1 newPayload   Lscala/Option;
    MethodParameters:
      Name                           Flags
      newPayload                     final

  public static final scala.xml.Elem $anonfun$toXml$3(org.scalatest.events.RecordableEvent);
    descriptor: (Lorg/scalatest/events/RecordableEvent;)Lscala/xml/Elem;
    flags: (0x1019) ACC_PUBLIC, ACC_STATIC, ACC_FINAL, ACC_SYNTHETIC
    Code:
      stack=1, locals=1, args_size=1
         0: aload_0
         1: checkcast     #4                  // class org/scalatest/events/Event
         4: invokevirtual #529                // Method org/scalatest/events/Event.toXml:()Lscala/xml/Elem;
         7: areturn
      LineNumberTable:
        line 857: 0
      LocalVariableTable:
        Start  Length  Slot  Name   Signature
            0       8     0   x$5   Lorg/scalatest/events/RecordableEvent;
    MethodParameters:
      Name                           Flags
      x$5                            final

  public static final java.lang.String $anonfun$toJson$5();
    descriptor: ()Ljava/lang/String;
    flags: (0x1019) ACC_PUBLIC, ACC_STATIC, ACC_FINAL, ACC_SYNTHETIC
    Code:
      stack=1, locals=0, args_size=0
         0: ldc_w         #532                // String null
         3: areturn
      LineNumberTable:
        line 868: 0

  public static final java.lang.String $anonfun$toJson$6(org.scalatest.events.RecordableEvent);
    descriptor: (Lorg/scalatest/events/RecordableEvent;)Ljava/lang/String;
    flags: (0x1019) ACC_PUBLIC, ACC_STATIC, ACC_FINAL, ACC_SYNTHETIC
    Code:
      stack=1, locals=1, args_size=1
         0: aload_0
         1: checkcast     #4                  // class org/scalatest/events/Event
         4: invokevirtual #534                // Method org/scalatest/events/Event.toJson:()Ljava/lang/String;
         7: areturn
      LineNumberTable:
        line 868: 0
      LocalVariableTable:
        Start  Length  Slot  Name   Signature
            0       8     0   x$6   Lorg/scalatest/events/RecordableEvent;
    MethodParameters:
      Name                           Flags
      x$6                            final

  public org.scalatest.events.TestPending(org.scalatest.events.Ordinal, java.lang.String, java.lang.String, scala.Option<java.lang.String>, java.lang.String, java.lang.String, scala.collection.immutable.IndexedSeq<org.scalatest.events.RecordableEvent>, scala.Option<java.lang.Object>, scala.Option<org.scalatest.events.Formatter>, scala.Option<org.scalatest.events.Location>, scala.Option<java.lang.Object>, java.lang.String, long);
    descriptor: (Lorg/scalatest/events/Ordinal;Ljava/lang/String;Ljava/lang/String;Lscala/Option;Ljava/lang/String;Ljava/lang/String;Lscala/collection/immutable/IndexedSeq;Lscala/Option;Lscala/Option;Lscala/Option;Lscala/Option;Ljava/lang/String;J)V
    flags: (0x0001) ACC_PUBLIC
    Code:
      stack=9, locals=15, args_size=14
         0: aload_0
         1: aload_1
         2: putfield      #119                // Field ordinal:Lorg/scalatest/events/Ordinal;
         5: aload_0
         6: aload_2
         7: putfield      #122                // Field suiteName:Ljava/lang/String;
        10: aload_0
        11: aload_3
        12: putfield      #124                // Field suiteId:Ljava/lang/String;
        15: aload_0
        16: aload         4
        18: putfield      #127                // Field suiteClassName:Lscala/Option;
        21: aload_0
        22: aload         5
        24: putfield      #129                // Field testName:Ljava/lang/String;
        27: aload_0
        28: aload         6
        30: putfield      #131                // Field testText:Ljava/lang/String;
        33: aload_0
        34: aload         7
        36: putfield      #135                // Field recordedEvents:Lscala/collection/immutable/IndexedSeq;
        39: aload_0
        40: aload         8
        42: putfield      #137                // Field duration:Lscala/Option;
        45: aload_0
        46: aload         9
        48: putfield      #139                // Field formatter:Lscala/Option;
        51: aload_0
        52: aload         10
        54: putfield      #141                // Field location:Lscala/Option;
        57: aload_0
        58: aload         11
        60: putfield      #143                // Field payload:Lscala/Option;
        63: aload_0
        64: aload         12
        66: putfield      #145                // Field threadName:Ljava/lang/String;
        69: aload_0
        70: lload         13
        72: putfield      #147                // Field timeStamp:J
        75: aload_0
        76: invokespecial #536                // Method org/scalatest/events/Event."<init>":()V
        79: getstatic     #541                // Field org/scalactic/Requirements$.MODULE$:Lorg/scalactic/Requirements$;
        82: invokevirtual #545                // Method org/scalactic/Requirements$.requirementsHelper:()Lorg/scalactic/Requirements$RequirementsHelper;
        85: bipush        11
        87: anewarray     #496                // class java/lang/String
        90: dup
        91: iconst_0
        92: ldc_w         #547                // String TestPending.this.ordinal
        95: aastore
        96: dup
        97: iconst_1
        98: ldc_w         #549                // String TestPending.this.suiteName
       101: aastore
       102: dup
       103: iconst_2
       104: ldc_w         #551                // String TestPending.this.suiteId
       107: aastore
       108: dup
       109: iconst_3
       110: ldc_w         #553                // String TestPending.this.suiteClassName
       113: aastore
       114: dup
       115: iconst_4
       116: ldc_w         #555                // String TestPending.this.testName
       119: aastore
       120: dup
       121: iconst_5
       122: ldc_w         #557                // String TestPending.this.testText
       125: aastore
       126: dup
       127: bipush        6
       129: ldc_w         #559                // String TestPending.this.duration
       132: aastore
       133: dup
       134: bipush        7
       136: ldc_w         #561                // String TestPending.this.formatter
       139: aastore
       140: dup
       141: bipush        8
       143: ldc_w         #563                // String TestPending.this.location
       146: aastore
       147: dup
       148: bipush        9
       150: ldc_w         #565                // String TestPending.this.payload
       153: aastore
       154: dup
       155: bipush        10
       157: ldc_w         #567                // String TestPending.this.threadName
       160: aastore
       161: checkcast     #569                // class "[Ljava/lang/Object;"
       164: checkcast     #571                // class "[Ljava/lang/String;"
       167: bipush        11
       169: anewarray     #476                // class java/lang/Object
       172: dup
       173: iconst_0
       174: aload_1
       175: aastore
       176: dup
       177: iconst_1
       178: aload_2
       179: aastore
       180: dup
       181: iconst_2
       182: aload_3
       183: aastore
       184: dup
       185: iconst_3
       186: aload         4
       188: aastore
       189: dup
       190: iconst_4
       191: aload         5
       193: aastore
       194: dup
       195: iconst_5
       196: aload         6
       198: aastore
       199: dup
       200: bipush        6
       202: aload         8
       204: aastore
       205: dup
       206: bipush        7
       208: aload         9
       210: aastore
       211: dup
       212: bipush        8
       214: aload         10
       216: aastore
       217: dup
       218: bipush        9
       220: aload         11
       222: aastore
       223: dup
       224: bipush        10
       226: aload         12
       228: aastore
       229: checkcast     #569                // class "[Ljava/lang/Object;"
       232: getstatic     #576                // Field org/scalactic/Prettifier$.MODULE$:Lorg/scalactic/Prettifier$;
       235: invokevirtual #580                // Method org/scalactic/Prettifier$.default:()Lorg/scalactic/Prettifier;
       238: new           #582                // class org/scalactic/source/Position
       241: dup
       242: ldc_w         #583                // String Event.scala
       245: ldc_w         #585                // String Please set the environment variable SCALACTIC_FILL_FILE_PATHNAMES to yes at compile time to enable this feature.
       248: sipush        832
       251: invokespecial #588                // Method org/scalactic/source/Position."<init>":(Ljava/lang/String;Ljava/lang/String;I)V
       254: invokevirtual #592                // Method org/scalactic/Requirements$RequirementsHelper.macroRequireNonNull:([Ljava/lang/String;[Ljava/lang/Object;Lorg/scalactic/Prettifier;Lorg/scalactic/source/Position;)V
       257: return
      LineNumberTable:
        line 817: 0
        line 818: 5
        line 819: 10
        line 820: 15
        line 821: 21
        line 822: 27
        line 823: 33
        line 824: 39
        line 825: 45
        line 826: 51
        line 827: 57
        line 828: 63
        line 829: 69
        line 830: 75
        line 832: 79
        line 833: 178
        line 834: 182
        line 835: 186
        line 836: 191
        line 837: 196
        line 838: 202
        line 839: 208
        line 840: 214
        line 841: 220
        line 842: 226
        line 832: 232
        line 816: 257
      LocalVariableTable:
        Start  Length  Slot  Name   Signature
            0     258     0  this   Lorg/scalatest/events/TestPending;
            0     258     1 ordinal   Lorg/scalatest/events/Ordinal;
            0     258     2 suiteName   Ljava/lang/String;
            0     258     3 suiteId   Ljava/lang/String;
            0     258     4 suiteClassName   Lscala/Option;
            0     258     5 testName   Ljava/lang/String;
            0     258     6 testText   Ljava/lang/String;
            0     258     7 recordedEvents   Lscala/collection/immutable/IndexedSeq;
            0     258     8 duration   Lscala/Option;
            0     258     9 formatter   Lscala/Option;
            0     258    10 location   Lscala/Option;
            0     258    11 payload   Lscala/Option;
            0     258    12 threadName   Ljava/lang/String;
            0     258    13 timeStamp   J
    Signature: #535                         // (Lorg/scalatest/events/Ordinal;Ljava/lang/String;Ljava/lang/String;Lscala/Option<Ljava/lang/String;>;Ljava/lang/String;Ljava/lang/String;Lscala/collection/immutable/IndexedSeq<Lorg/scalatest/events/RecordableEvent;>;Lscala/Option<Ljava/lang/Object;>;Lscala/Option<Lorg/scalatest/events/Formatter;>;Lscala/Option<Lorg/scalatest/events/Location;>;Lscala/Option<Ljava/lang/Object;>;Ljava/lang/String;J)V
    MethodParameters:
      Name                           Flags
      ordinal                        final
      suiteName                      final
      suiteId                        final
      suiteClassName                 final
      testName                       final
      testText                       final
      recordedEvents                 final
      duration                       final
      formatter                      final
      location                       final
      payload                        final
      threadName                     final
      timeStamp                      final

  private static java.lang.Object $deserializeLambda$(java.lang.invoke.SerializedLambda);
    descriptor: (Ljava/lang/invoke/SerializedLambda;)Ljava/lang/Object;
    flags: (0x100a) ACC_PRIVATE, ACC_STATIC, ACC_SYNTHETIC
    Code:
      stack=1, locals=1, args_size=1
         0: aload_0
         1: invokedynamic #604,  0            // InvokeDynamic #3:lambdaDeserialize:(Ljava/lang/invoke/SerializedLambda;)Ljava/lang/Object;
         6: areturn
}
InnerClasses:
  public static final #13= #10 of #12;    // Lookup=class java/lang/invoke/MethodHandles$Lookup of class java/lang/invoke/MethodHandles
  public static #18= #15 of #17;          // RequirementsHelper=class org/scalactic/Requirements$RequirementsHelper of class org/scalactic/Requirements
  public #21= #20 of #4;                  // EventJsonHelper$=class org/scalatest/events/Event$EventJsonHelper$ of class org/scalatest/events/Event
  public #24= #23 of #4;                  // EventXmlHelper$=class org/scalatest/events/Event$EventXmlHelper$ of class org/scalatest/events/Event
SourceFile: "Event.scala"
RuntimeVisibleAnnotations:
  0: #6(#7=s#8)
    scala.reflect.ScalaSignature(
      bytes="\u0006\u0005\t=g\u0001B%K\u0005FC\u0001\u0002\u001b\u0001\u0003\u0016\u0004%\t!\u001b\u0005\t[\u0002\u0011\t\u0012)A\u0005U\"Aa\u000e\u0001BK\u0002\u0013\u0005q\u000e\u0003\u0005y\u0001\tE\t\u0015!\u0003q\u0011!I\bA!f\u0001\n\u0003y\u0007\u0002\u0003>\u0001\u0005#\u0005\u000b\u0011\u00029\t\u0011m\u0004!Q3A\u0005\u0002qD\u0011\"!\u0001\u0001\u0005#\u0005\u000b\u0011B?\t\u0013\u0005\r\u0001A!f\u0001\n\u0003y\u0007\"CA\u0003\u0001\tE\t\u0015!\u0003q\u0011%\t9\u0001\u0001BK\u0002\u0013\u0005q\u000eC\u0005\u0002\n\u0001\u0011\t\u0012)A\u0005a\"Q\u00111\u0002\u0001\u0003\u0016\u0004%\t!!\u0004\t\u0015\u0005\u0015\u0002A!E!\u0002\u0013\ty\u0001\u0003\u0006\u0002(\u0001\u0011)\u001a!C\u0001\u0003SA!\"a\r\u0001\u0005#\u0005\u000b\u0011BA\u0016\u0011)\t)\u0004\u0001BK\u0002\u0013\u0005\u0011q\u0007\u0005\u000b\u0003\u0003\u0002!\u0011#Q\u0001\n\u0005e\u0002BCA\"\u0001\tU\r\u0011\"\u0001\u0002F!Q\u0011q\n\u0001\u0003\u0012\u0003\u0006I!a\u0012\t\u0015\u0005E\u0003A!f\u0001\n\u0003\t\u0019\u0006\u0003\u0006\u0002^\u0001\u0011\t\u0012)A\u0005\u0003+B\u0011\"a\u0018\u0001\u0005+\u0007I\u0011A8\t\u0013\u0005\u0005\u0004A!E!\u0002\u0013\u0001\bBCA2\u0001\tU\r\u0011\"\u0001\u0002f!Q\u0011q\r\u0001\u0003\u0012\u0003\u0006I!!\f\t\u000f\u0005%\u0004\u0001\"\u0001\u0002l!A\u0011\u0011\u0012\u0001\u0005\u00021\u000bY\tC\u0004\u0002\u001a\u0002!\t\u0001T8\t\u0011\u0005m\u0005\u0001\"\u0001K\u0003;C\u0011\"a)\u0001\u0003\u0003%\t!!*\t\u0013\u0005\u0005\u0007!%A\u0005\u0002\u0005\r\u0007\"CAm\u0001E\u0005I\u0011AAn\u0011%\ty\u000eAI\u0001\n\u0003\tY\u000eC\u0005\u0002b\u0002\t\n\u0011\"\u0001\u0002d\"I\u0011q\u001d\u0001\u0012\u0002\u0013\u0005\u00111\u001c\u0005\n\u0003S\u0004\u0011\u0013!C\u0001\u00037D\u0011\"a;\u0001#\u0003%\t!!<\t\u0013\u0005E\b!%A\u0005\u0002\u0005M\b\"CA|\u0001E\u0005I\u0011AA}\u0011%\ti\u0010AI\u0001\n\u0003\ty\u0010C\u0005\u0003\u0004\u0001\t\n\u0011\"\u0001\u0003\u0006!I!\u0011\u0002\u0001\u0012\u0002\u0013\u0005\u00111\u001c\u0005\n\u0005\u0017\u0001\u0011\u0013!C\u0001\u0005\u001bA\u0011B!\u0005\u0001\u0003\u0003%\tEa\u0005\t\u0013\t\r\u0002!!A\u0005\u0002\t\u0015\u0002\"\u0003B\u0017\u0001\u0005\u0005I\u0011\u0001B\u0018\u0011%\u0011)\u0004AA\u0001\n\u0003\u00129\u0004C\u0005\u0003B\u0001\t\t\u0011\"\u0001\u0003D!I!Q\n\u0001\u0002\u0002\u0013\u0005#q\n\u0005\n\u0005\'\u0002\u0011\u0011!C!\u0005+B\u0011Ba\u0016\u0001\u0003\u0003%\tE!\u0017\t\u0013\tm\u0003!!A\u0005B\tus!\u0003B1\u0015\u0006\u0005\t\u0012\u0001B2\r!I%*!A\t\u0002\t\u0015\u0004bBA5o\u0011\u0005!Q\u0010\u0005\n\u0005/:\u0014\u0011!C#\u00053B\u0011Ba 8\u0003\u0003%\tI!!\t\u0013\tuu\'%A\u0005\u0002\u0005M\b\"\u0003BPoE\u0005I\u0011AA}\u0011%\u0011\tkNI\u0001\n\u0003\ty\u0010C\u0005\u0003$^\n\n\u0011\"\u0001\u0003\u0006!I!QU\u001c\u0012\u0002\u0013\u0005\u00111\u001c\u0005\n\u0005O;\u0014\u0013!C\u0001\u0005\u001bA\u0011B!+8\u0003\u0003%\tIa+\t\u0013\tev\'%A\u0005\u0002\u0005M\b\"\u0003B^oE\u0005I\u0011AA}\u0011%\u0011ilNI\u0001\n\u0003\ty\u0010C\u0005\u0003@^\n\n\u0011\"\u0001\u0003\u0006!I!\u0011Y\u001c\u0012\u0002\u0013\u0005\u00111\u001c\u0005\n\u0005\u0007<\u0014\u0013!C\u0001\u0005\u001bA\u0011B!28\u0003\u0003%IAa2\u0003\u0017Q+7\u000f\u001e)f]\u0012Lgn\u001a\u0006\u0003\u00172\u000ba!\u001a<f]R\u001c(BA\'O\u0003%\u00198-\u00197bi\u0016\u001cHOC\u0001P\u0003\ry\'oZ\u0002\u0001\'\u0011\u0001!K\u0016/\u0011\u0005M#V\"\u0001&\n\u0005US%!B#wK:$\bCA,[\u001b\u0005A&\"A-\u0002\u000bM\u001c\u0017\r\\1\n\u0005mC&a\u0002)s_\u0012,8\r\u001e\t\u0003;\u0016t!AX2\u000f\u0005}\u0013W\"\u00011\u000b\u0005\u0005\u0004\u0016A\u0002\u001fs_>$h(C\u0001Z\u0013\t!\u0007,A\u0004qC\u000e\\\u0017mZ3\n\u0005\u0019<\'\u0001D*fe&\fG.\u001b>bE2,\'B\u00013Y\u0003\u001dy\'\u000fZ5oC2,\u0012A\u001b\t\u0003\'.L!\u0001\u001c&\u0003\u000f=\u0013H-\u001b8bY\u0006AqN\u001d3j]\u0006d\u0007%A\u0005tk&$XMT1nKV\t\u0001\u000f\u0005\u0002rk:\u0011!o\u001d\t\u0003?bK!\u0001\u001e-\u0002\rA\u0013X\rZ3g\u0013\t1xO\u0001\u0004TiJLgn\u001a\u0006\u0003ib\u000b!b];ji\u0016t\u0015-\\3!\u0003\u001d\u0019X/\u001b;f\u0013\u0012\f\u0001b];ji\u0016LE\rI\u0001\u000fgVLG/Z\"mCN\u001ch*Y7f+\u0005i\bcA,\u007fa&\u0011q\u0010\u0017\u0002\u0007\u001fB$\u0018n\u001c8\u0002\u001fM,\u0018\u000e^3DY\u0006\u001c8OT1nK\u0002\n\u0001\u0002^3ti:\u000bW.Z\u0001\ni\u0016\u001cHOT1nK\u0002\n\u0001\u0002^3tiR+\u0007\u0010^\u0001\ni\u0016\u001cH\u000fV3yi\u0002\naB]3d_J$W\rZ#wK:$8/\u0006\u0002\u0002\u0010A1\u0011\u0011CA\u000e\u0003?i!!a\u0005\u000b\t\u0005U\u0011qC\u0001\nS6lW\u000f^1cY\u0016T1!!\u0007Y\u0003)\u0019w\u000e\u001c7fGRLwN\\\u0005\u0005\u0003;\t\u0019B\u0001\u0006J]\u0012,\u00070\u001a3TKF\u00042aUA\u0011\u0013\r\t\u0019C\u0013\u0002\u0010%\u0016\u001cwN\u001d3bE2,WI^3oi\u0006y!/Z2pe\u0012,G-\u0012<f]R\u001c\b%\u0001\u0005ekJ\fG/[8o+\t\tY\u0003\u0005\u0003X}\u00065\u0002cA,\u00020%\u0019\u0011\u0011\u0007-\u0003\t1{gnZ\u0001\nIV\u0014\u0018\r^5p]\u0002\n\u0011BZ8s[\u0006$H/\u001a:\u0016\u0005\u0005e\u0002\u0003B,\u007f\u0003w\u00012aUA\u001f\u0013\r\tyD\u0013\u0002\n\r>\u0014X.\u0019;uKJ\f!BZ8s[\u0006$H/\u001a:!\u0003!awnY1uS>tWCAA$!\u00119f0!\u0013\u0011\u0007M\u000bY%C\u0002\u0002N)\u0013\u0001\u0002T8dCRLwN\\\u0001\nY>\u001c\u0017\r^5p]\u0002\nq\u0001]1zY>\fG-\u0006\u0002\u0002VA!qK`A,!\r9\u0016\u0011L\u0005\u0004\u00037B&aA!os\u0006A\u0001/Y=m_\u0006$\u0007%\u0001\u0006uQJ,\u0017\r\u001a(b[\u0016\f1\u0002\u001e5sK\u0006$g*Y7fA\u0005IA/[7f\'R\fW\u000e]\u000b\u0003\u0003[\t!\u0002^5nKN#\u0018-\u001c9!\u0003\u0019a\u0014N\\5u}Qa\u0012QNA8\u0003c\n\u0019(!\u001e\u0002x\u0005e\u00141PA?\u0003\u007f\n\t)a!\u0002\u0006\u0006\u001d\u0005CA*\u0001\u0011\u0015A7\u00041\u0001k\u0011\u0015q7\u00041\u0001q\u0011\u0015I8\u00041\u0001q\u0011\u0015Y8\u00041\u0001~\u0011\u0019\t\u0019a\u0007a\u0001a\"1\u0011qA\u000eA\u0002ADq!a\u0003\u001c\u0001\u0004\ty\u0001C\u0005\u0002(m\u0001\n\u00111\u0001\u0002,!I\u0011QG\u000e\u0011\u0002\u0003\u0007\u0011\u0011\b\u0005\n\u0003\u0007Z\u0002\u0013!a\u0001\u0003\u000fB\u0011\"!\u0015\u001c!\u0003\u0005\r!!\u0016\t\u0011\u0005}3\u0004%AA\u0002AD\u0011\"a\u0019\u001c!\u0003\u0005\r!!\f\u0002\u000bQ|\u0007,\u001c7\u0016\u0005\u00055\u0005\u0003BAH\u0003+k!!!%\u000b\u0007\u0005M\u0005,A\u0002y[2LA!a&\u0002\u0012\n!Q\t\\3n\u0003\u0019!xNS:p]\u0006Yq/\u001b;i!\u0006LHn\\1e)\u0011\ti\'a(\t\u000f\u0005\u0005f\u00041\u0001\u0002V\u0005Qa.Z<QCfdw.\u00193\u0002\t\r|\u0007/\u001f\u000b\u001d\u0003[\n9+!+\u0002,\u00065\u0016qVAY\u0003g\u000b),a.\u0002:\u0006m\u0016QXA`\u0011\u001dAw\u0004%AA\u0002)DqA\\\u0010\u0011\u0002\u0003\u0007\u0001\u000fC\u0004z?A\u0005\t\u0019\u00019\t\u000fm|\u0002\u0013!a\u0001{\"A\u00111A\u0010\u0011\u0002\u0003\u0007\u0001\u000f\u0003\u0005\u0002\b}\u0001\n\u00111\u0001q\u0011%\tYa\bI\u0001\u0002\u0004\ty\u0001C\u0005\u0002(}\u0001\n\u00111\u0001\u0002,!I\u0011QG\u0010\u0011\u0002\u0003\u0007\u0011\u0011\b\u0005\n\u0003\u0007z\u0002\u0013!a\u0001\u0003\u000fB\u0011\"!\u0015 !\u0003\u0005\r!!\u0016\t\u0011\u0005}s\u0004%AA\u0002AD\u0011\"a\u0019 !\u0003\u0005\r!!\f\u0002\u001d\r|\u0007/\u001f\u0013eK\u001a\fW\u000f\u001c;%cU\u0011\u0011Q\u0019\u0016\u0004U\u0006\u001d7FAAe!\u0011\tY-!6\u000e\u0005\u00055\'\u0002BAh\u0003#\f\u0011\"\u001e8dQ\u0016\u001c7.\u001a3\u000b\u0007\u0005M\u0007,\u0001\u0006b]:|G/\u0019;j_:LA!a6\u0002N\n\tRO\\2iK\u000e\\W\r\u001a,be&\fgnY3\u0002\u001d\r|\u0007/\u001f\u0013eK\u001a\fW\u000f\u001c;%eU\u0011\u0011Q\u001c\u0016\u0004a\u0006\u001d\u0017AD2paf$C-\u001a4bk2$HeM\u0001\u000fG>\u0004\u0018\u0010\n3fM\u0006,H\u000e\u001e\u00135+\t\t)OK\u0002~\u0003\u000f\fabY8qs\u0012\"WMZ1vYR$S\'\u0001\bd_BLH\u0005Z3gCVdG\u000f\n\u001c\u0002\u001d\r|\u0007/\u001f\u0013eK\u001a\fW\u000f\u001c;%oU\u0011\u0011q\u001e\u0016\u0005\u0003\u001f\t9-\u0001\bd_BLH\u0005Z3gCVdG\u000f\n\u001d\u0016\u0005\u0005U(\u0006BA\u0016\u0003\u000f\fabY8qs\u0012\"WMZ1vYR$\u0013(\u0006\u0002\u0002|*\"\u0011\u0011HAd\u0003=\u0019w\u000e]=%I\u00164\u0017-\u001e7uIE\u0002TC\u0001B\u0001U\u0011\t9%a2\u0002\u001f\r|\u0007/\u001f\u0013eK\u001a\fW\u000f\u001c;%cE*\"Aa\u0002+\t\u0005U\u0013qY\u0001\u0010G>\u0004\u0018\u0010\n3fM\u0006,H\u000e\u001e\u00132e\u0005y1m\u001c9zI\u0011,g-Y;mi\u0012\n4\'\u0006\u0002\u0003\u0010)\"\u0011QFAd\u00035\u0001(o\u001c3vGR\u0004&/\u001a4jqV\u0011!Q\u0003\t\u0005\u0005/\u0011\t#\u0004\u0002\u0003\u001a)!!1\u0004B\u000f\u0003\u0011a\u0017M\\4\u000b\u0005\t}\u0011\u0001\u00026bm\u0006L1A\u001eB\r\u00031\u0001(o\u001c3vGR\f%/\u001b;z+\t\u00119\u0003E\u0002X\u0005SI1Aa\u000bY\u0005\rIe\u000e^\u0001\u000faJ|G-^2u\u000b2,W.\u001a8u)\u0011\t9F!\r\t\u0013\tMr&!AA\u0002\t\u001d\u0012a\u0001=%c\u0005y\u0001O]8ek\u000e$\u0018\n^3sCR|\'/\u0006\u0002\u0003:A1!1\bB\u001f\u0003/j!!a\u0006\n\t\t}\u0012q\u0003\u0002\t\u0013R,\'/\u0019;pe\u0006A1-\u00198FcV\fG\u000e\u0006\u0003\u0003F\t-\u0003cA,\u0003H%\u0019!\u0011\n-\u0003\u000f\t{w\u000e\\3b]\"I!1G\u0019\u0002\u0002\u0003\u0007\u0011qK\u0001\u0013aJ|G-^2u\u000b2,W.\u001a8u\u001d\u0006lW\r\u0006\u0003\u0003\u0016\tE\u0003\"\u0003B\u001ae\u0005\u0005\t\u0019\u0001B\u0014\u0003!A\u0017m\u001d5D_\u0012,GC\u0001B\u0014\u0003!!xn\u0015;sS:<GC\u0001B\u000b\u0003\u0019)\u0017/^1mgR!!Q\tB0\u0011%\u0011\u0019$NA\u0001\u0002\u0004\t9&A\u0006UKN$\b+\u001a8eS:<\u0007CA*8\'\u00159$q\rB:!e\u0011IGa\u001ckaBl\b\u000f]A\b\u0003W\tI$a\u0012\u0002VA\fi#!\u001c\u000e\u0005\t-$b\u0001B71\u00069!/\u001e8uS6,\u0017\u0002\u0002B9\u0005W\u0012!#\u00112tiJ\f7\r\u001e$v]\u000e$\u0018n\u001c82gA!!Q\u000fB>\u001b\t\u00119H\u0003\u0003\u0003z\tu\u0011AA5p\u0013\r1\'q\u000f\u000b\u0003\u0005G\nQ!\u00199qYf$B$!\u001c\u0003\u0004\n\u0015%q\u0011BE\u0005\u0017\u0013iIa$\u0003\u0012\nM%Q\u0013BL\u00053\u0013Y\nC\u0003iu\u0001\u0007!\u000eC\u0003ou\u0001\u0007\u0001\u000fC\u0003zu\u0001\u0007\u0001\u000fC\u0003|u\u0001\u0007Q\u0010\u0003\u0004\u0002\u0004i\u0002\r\u0001\u001d\u0005\u0007\u0003\u000fQ\u0004\u0019\u00019\t\u000f\u0005-!\b1\u0001\u0002\u0010!I\u0011q\u0005\u001e\u0011\u0002\u0003\u0007\u00111\u0006\u0005\n\u0003kQ\u0004\u0013!a\u0001\u0003sA\u0011\"a\u0011;!\u0003\u0005\r!a\u0012\t\u0013\u0005E#\b%AA\u0002\u0005U\u0003\u0002CA0uA\u0005\t\u0019\u00019\t\u0013\u0005\r$\b%AA\u0002\u00055\u0012aD1qa2LH\u0005Z3gCVdG\u000f\n\u001d\u0002\u001f\u0005\u0004\b\u000f\\=%I\u00164\u0017-\u001e7uIe\n\u0001#\u00199qYf$C-\u001a4bk2$H%\r\u0019\u0002!\u0005\u0004\b\u000f\\=%I\u00164\u0017-\u001e7uIE\n\u0014\u0001E1qa2LH\u0005Z3gCVdG\u000fJ\u00193\u0003A\t\u0007\u000f\u001d7zI\u0011,g-Y;mi\u0012\n4\'A\u0004v]\u0006\u0004\b\u000f\\=\u0015\t\t5&Q\u0017\t\u0005/z\u0014y\u000b\u0005\fX\u0005cS\u0007\u000f]?qa\u0006=\u00111FA\u001d\u0003\u000f\n)\u0006]A\u0017\u0013\r\u0011\u0019\f\u0017\u0002\b)V\u0004H.Z\u00194\u0011%\u00119,QA\u0001\u0002\u0004\ti\'A\u0002yIA\n1\u0004\n7fgNLg.\u001b;%OJ,\u0017\r^3sI\u0011,g-Y;mi\u0012B\u0014a\u0007\u0013mKN\u001c\u0018N\\5uI\u001d\u0014X-\u0019;fe\u0012\"WMZ1vYR$\u0013(\u0001\u000f%Y\u0016\u001c8/\u001b8ji\u0012:\'/Z1uKJ$C-\u001a4bk2$H%\r\u0019\u00029\u0011bWm]:j]&$He\u001a:fCR,\'\u000f\n3fM\u0006,H\u000e\u001e\u00132c\u0005aB\u0005\\3tg&t\u0017\u000e\u001e\u0013he\u0016\fG/\u001a:%I\u00164\u0017-\u001e7uIE\u0012\u0014\u0001\b\u0013mKN\u001c\u0018N\\5uI\u001d\u0014X-\u0019;fe\u0012\"WMZ1vYR$\u0013gM\u0001\roJLG/\u001a*fa2\f7-\u001a\u000b\u0003\u0005\u0013\u0004BAa\u0006\u0003L&!!Q\u001aB\r\u0005\u0019y%M[3di\u0002"
    )
BootstrapMethods:
  0: #259 REF_invokeStatic java/lang/invoke/LambdaMetafactory.altMetafactory:(Ljava/lang/invoke/MethodHandles$Lookup;Ljava/lang/String;Ljava/lang/invoke/MethodType;[Ljava/lang/Object;)Ljava/lang/invoke/CallSite;
    Method arguments:
      #244 (Ljava/lang/Object;)Ljava/lang/Object;
      #249 REF_invokeStatic org/scalatest/events/TestPending.$anonfun$toXml$3:(Lorg/scalatest/events/RecordableEvent;)Lscala/xml/Elem;
      #250 (Lorg/scalatest/events/RecordableEvent;)Lscala/xml/Elem;
      #251 5
      #252 1
      #250 (Lorg/scalatest/events/RecordableEvent;)Lscala/xml/Elem;
  1: #259 REF_invokeStatic java/lang/invoke/LambdaMetafactory.altMetafactory:(Ljava/lang/invoke/MethodHandles$Lookup;Ljava/lang/String;Ljava/lang/invoke/MethodType;[Ljava/lang/Object;)Ljava/lang/invoke/CallSite;
    Method arguments:
      #339 ()Ljava/lang/Object;
      #343 REF_invokeStatic org/scalatest/events/TestPending.$anonfun$toJson$5:()Ljava/lang/String;
      #344 ()Ljava/lang/String;
      #251 5
      #252 1
      #344 ()Ljava/lang/String;
  2: #259 REF_invokeStatic java/lang/invoke/LambdaMetafactory.altMetafactory:(Ljava/lang/invoke/MethodHandles$Lookup;Ljava/lang/String;Ljava/lang/invoke/MethodType;[Ljava/lang/Object;)Ljava/lang/invoke/CallSite;
    Method arguments:
      #244 (Ljava/lang/Object;)Ljava/lang/Object;
      #367 REF_invokeStatic org/scalatest/events/TestPending.$anonfun$toJson$6:(Lorg/scalatest/events/RecordableEvent;)Ljava/lang/String;
      #368 (Lorg/scalatest/events/RecordableEvent;)Ljava/lang/String;
      #251 5
      #252 1
      #368 (Lorg/scalatest/events/RecordableEvent;)Ljava/lang/String;
  3: #601 REF_invokeStatic scala/runtime/LambdaDeserialize.bootstrap:(Ljava/lang/invoke/MethodHandles$Lookup;Ljava/lang/String;Ljava/lang/invoke/MethodType;[Ljava/lang/invoke/MethodHandle;)Ljava/lang/invoke/CallSite;
    Method arguments:
      #343 REF_invokeStatic org/scalatest/events/TestPending.$anonfun$toJson$5:()Ljava/lang/String;
      #367 REF_invokeStatic org/scalatest/events/TestPending.$anonfun$toJson$6:(Lorg/scalatest/events/RecordableEvent;)Ljava/lang/String;
      #249 REF_invokeStatic org/scalatest/events/TestPending.$anonfun$toXml$3:(Lorg/scalatest/events/RecordableEvent;)Lscala/xml/Elem;
  ScalaInlineInfo: length = 0xE0 (unknown attribute)
   01 01 00 2C 01 54 00 3B 01 01 6B 01 6C 01 00 F5
   00 F6 01 00 AB 01 CB 01 01 E9 01 EA 01 01 BB 00
   68 01 01 97 00 75 01 01 B2 00 3F 01 01 CE 00 3F
   01 01 B5 00 3B 01 01 B8 00 31 01 01 9A 00 3B 01
   01 9D 00 3B 01 01 A0 00 3F 01 01 A3 00 3B 01 01
   A6 00 3B 01 01 A9 00 84 01 01 AC 00 3F 01 01 AF
   00 3F 01 00 26 00 3F 01 02 0A 01 EA 01 00 28 00
   3F 01 01 F1 00 C3 01 00 2A 00 3F 01 00 19 00 75
   01 00 2C 00 3F 01 01 D2 00 C3 01 01 D3 01 D4 01
   01 EC 01 ED 01 01 DD 01 DE 01 01 D1 00 3B 01 00
   23 00 84 01 00 1E 00 3F 01 00 1D 00 3B 01 00 1B
   00 3B 01 00 21 00 3B 01 00 22 00 3B 01 00 2D 00
   3B 01 00 2E 00 31 01 01 27 00 3B 01 01 8A 00 3B
   01 00 94 00 95 01 01 93 02 0D 01 01 93 01 94 01

  ScalaSig: length = 0x3 (unknown attribute)
   05 02 00
