Classfile /Users/mw/Projects/slang-braindump/.jar/jar8/assemble/slang-braindump/assemble/content/org/scalatest/events/TestCanceled.class
  Last modified May 29, 2022; size 27871 bytes
  SHA-256 checksum 75bc7477874d8242d64b92d61d6cc50dc4b7410aefb3ed073e5f48115dfe0066
  Compiled from "Event.scala"
public final class org.scalatest.events.TestCanceled extends org.scalatest.events.Event implements org.scalatest.events.ExceptionalEvent
  minor version: 0
  major version: 52
  flags: (0x0031) ACC_PUBLIC, ACC_FINAL, ACC_SUPER
  this_class: #2                          // org/scalatest/events/TestCanceled
  super_class: #4                         // org/scalatest/events/Event
  interfaces: 1, fields: 16, methods: 73, attributes: 6
Constant pool:
    #1 = Utf8               org/scalatest/events/TestCanceled
    #2 = Class              #1            // org/scalatest/events/TestCanceled
    #3 = Utf8               org/scalatest/events/Event
    #4 = Class              #3            // org/scalatest/events/Event
    #5 = Utf8               org/scalatest/events/ExceptionalEvent
    #6 = Class              #5            // org/scalatest/events/ExceptionalEvent
    #7 = Utf8               Event.scala
    #8 = Utf8               Lscala/reflect/ScalaSignature;
    #9 = Utf8               bytes
   #10 = Utf8               \u0006\u0005\reb\u0001\u0002-Z\u0005\u0002D\u0001B\u001f\u0001\u0003\u0016\u0004%\ta\u001f\u0005\t\u007f\u0002\u0011\t\u0012)A\u0005y\"Q\u0011\u0011\u0001\u0001\u0003\u0016\u0004%\t!a\u0001\t\u0015\u0005U\u0001A!E!\u0002\u0013\t)\u0001\u0003\u0006\u0002\u0018\u0001\u0011)\u001a!C\u0001\u0003\u0007A!\"!\u0007\u0001\u0005#\u0005\u000b\u0011BA\u0003\u0011)\tY\u0002\u0001BK\u0002\u0013\u0005\u00111\u0001\u0005\u000b\u0003;\u0001!\u0011#Q\u0001\n\u0005\u0015\u0001BCA\u0010\u0001\tU\r\u0011\"\u0001\u0002\"!Q\u0011\u0011\u0006\u0001\u0003\u0012\u0003\u0006I!a\t\t\u0015\u0005-\u0002A!f\u0001\n\u0003\t\u0019\u0001\u0003\u0006\u0002.\u0001\u0011\t\u0012)A\u0005\u0003\u000bA!\"a\f\u0001\u0005+\u0007I\u0011AA\u0002\u0011)\t\t\u0004\u0001B\tB\u0003%\u0011Q\u0001\u0005\u000b\u0003g\u0001!Q3A\u0005\u0002\u0005U\u0002BCA\'\u0001\tE\t\u0015!\u0003\u00028!Q\u0011q\n\u0001\u0003\u0016\u0004%\t!!\u0015\t\u0015\u0005m\u0003A!E!\u0002\u0013\t\u0019\u0006\u0003\u0006\u0002^\u0001\u0011)\u001a!C\u0001\u0003?B!\"!\u001b\u0001\u0005#\u0005\u000b\u0011BA1\u0011)\tY\u0007\u0001BK\u0002\u0013\u0005\u0011Q\u000e\u0005\u000b\u0003o\u0002!\u0011#Q\u0001\n\u0005=\u0004BCA=\u0001\tU\r\u0011\"\u0001\u0002|!Q\u0011Q\u0011\u0001\u0003\u0012\u0003\u0006I!! \t\u0015\u0005\u001d\u0005A!f\u0001\n\u0003\t\t\u0003\u0003\u0006\u0002\n\u0002\u0011\t\u0012)A\u0005\u0003GA!\"a#\u0001\u0005+\u0007I\u0011AAG\u0011)\t9\n\u0001B\tB\u0003%\u0011q\u0012\u0005\u000b\u00033\u0003!Q3A\u0005\u0002\u0005\r\u0001BCAN\u0001\tE\t\u0015!\u0003\u0002\u0006!Q\u0011Q\u0014\u0001\u0003\u0016\u0004%\t!a(\t\u0015\u0005\u0005\u0006A!E!\u0002\u0013\t\u0019\u0007C\u0004\u0002$\u0002!\t!!*\t\u0011\u0005%\u0007\u0001\"\u0001\\\u0003\u0017D\u0001\"!7\u0001\t\u0003Y\u00161\u0001\u0005\t\u00037\u0004A\u0011A-\u0002^\"A\u00111\u001d\u0001\u0005Be\u000b)\u000f\u0003\u0005\u0002l\u0002!\teWAw\u0011%\ty\u000fAA\u0001\n\u0003\t\t\u0010C\u0005\u0003\u0014\u0001\t\n\u0011\"\u0001\u0003\u0016!I!1\u0006\u0001\u0012\u0002\u0013\u0005!Q\u0006\u0005\n\u0005c\u0001\u0011\u0013!C\u0001\u0005[A\u0011Ba\r\u0001#\u0003%\tA!\f\t\u0013\tU\u0002!%A\u0005\u0002\t]\u0002\"\u0003B\u001e\u0001E\u0005I\u0011\u0001B\u0017\u0011%\u0011i\u0004AI\u0001\n\u0003\u0011i\u0003C\u0005\u0003@\u0001\t\n\u0011\"\u0001\u0003B!I!Q\t\u0001\u0012\u0002\u0013\u0005!q\t\u0005\n\u0005\u0017\u0002\u0011\u0013!C\u0001\u0005\u001bB\u0011B!\u0015\u0001#\u0003%\tAa\u0015\t\u0013\t]\u0003!%A\u0005\u0002\te\u0003\"\u0003B/\u0001E\u0005I\u0011\u0001B\u001c\u0011%\u0011y\u0006AI\u0001\n\u0003\u0011\t\u0007C\u0005\u0003f\u0001\t\n\u0011\"\u0001\u0003.!I!q\r\u0001\u0012\u0002\u0013\u0005!\u0011\u000e\u0005\n\u0005[\u0002\u0011\u0011!C!\u0005_B\u0011Ba \u0001\u0003\u0003%\tA!!\t\u0013\t%\u0005!!A\u0005\u0002\t-\u0005\"\u0003BI\u0001\u0005\u0005I\u0011\tBJ\u0011%\u0011i\nAA\u0001\n\u0003\u0011y\nC\u0005\u0003*\u0002\t\t\u0011\"\u0011\u0003,\"I!q\u0016\u0001\u0002\u0002\u0013\u0005#\u0011\u0017\u0005\n\u0005g\u0003\u0011\u0011!C!\u0005kC\u0011Ba.\u0001\u0003\u0003%\tE!/\b\u0013\tu\u0016,!A\t\u0002\t}f\u0001\u0003-Z\u0003\u0003E\tA!1\t\u000f\u0005\r&\t\"\u0001\u0003Z\"I!1\u0017\"\u0002\u0002\u0013\u0015#Q\u0017\u0005\n\u00057\u0014\u0015\u0011!CA\u0005;D\u0011Ba@C#\u0003%\tAa\u0012\t\u0013\r\u0005!)%A\u0005\u0002\t5\u0003\"CB\u0002\u0005F\u0005I\u0011\u0001B*\u0011%\u0019)AQI\u0001\n\u0003\u0011I\u0006C\u0005\u0004\b\t\u000b\n\u0011\"\u0001\u00038!I1\u0011\u0002\"\u0012\u0002\u0013\u0005!\u0011\r\u0005\n\u0007\u0017\u0011\u0015\u0013!C\u0001\u0005[A\u0011b!\u0004C#\u0003%\tA!\u001b\t\u0013\r=!)!A\u0005\u0002\u000eE\u0001\"CB\u0010\u0005F\u0005I\u0011\u0001B$\u0011%\u0019\tCQI\u0001\n\u0003\u0011i\u0005C\u0005\u0004$\t\u000b\n\u0011\"\u0001\u0003T!I1Q\u0005\"\u0012\u0002\u0013\u0005!\u0011\f\u0005\n\u0007O\u0011\u0015\u0013!C\u0001\u0005oA\u0011b!\u000bC#\u0003%\tA!\u0019\t\u0013\r-\")%A\u0005\u0002\t5\u0002\"CB\u0017\u0005F\u0005I\u0011\u0001B5\u0011%\u0019yCQA\u0001\n\u0013\u0019\tD\u0001\u0007UKN$8)\u00198dK2,GM\u0003\u0002[7\u00061QM^3oiNT!\u0001X/\u0002\u0013M\u001c\u0017\r\\1uKN$(\"\u00010\u0002\u0007=\u0014xm\u0001\u0001\u0014\u000b\u0001\tW\r\u001b8\u0011\u0005\t\u001cW\"A-\n\u0005\u0011L&!B#wK:$\bC\u00012g\u0013\t9\u0017L\u0001\tFq\u000e,\u0007\u000f^5p]\u0006dWI^3oiB\u0011\u0011\u000e\\\u0007\u0002U*\t1.A\u0003tG\u0006d\u0017-\u0003\u0002nU\n9\u0001K]8ek\u000e$\bCA8x\u001d\t\u0001XO\u0004\u0002ri6\t!O\u0003\u0002t?\u00061AH]8pizJ\u0011a[\u0005\u0003m*\fq\u0001]1dW\u0006<W-\u0003\u0002ys\na1+\u001a:jC2L\'0\u00192mK*\u0011aO[\u0001\b_J$\u0017N\\1m+\u0005a\bC\u00012~\u0013\tq\u0018LA\u0004Pe\u0012Lg.\u00197\u0002\u0011=\u0014H-\u001b8bY\u0002\nq!\\3tg\u0006<W-\u0006\u0002\u0002\u0006A!\u0011qAA\b\u001d\u0011\tI!a\u0003\u0011\u0005ET\u0017bAA\u0007U\u00061\u0001K]3eK\u001aLA!!\u0005\u0002\u0014\t11\u000b\u001e:j]\u001eT1!!\u0004k\u0003!iWm]:bO\u0016\u0004\u0013!C:vSR,g*Y7f\u0003)\u0019X/\u001b;f\u001d\u0006lW\rI\u0001\bgVLG/Z%e\u0003!\u0019X/\u001b;f\u0013\u0012\u0004\u0013AD:vSR,7\t\\1tg:\u000bW.Z\u000b\u0003\u0003G\u0001R![A\u0013\u0003\u000bI1!a\nk\u0005\u0019y\u0005\u000f^5p]\u0006y1/^5uK\u000ec\u0017m]:OC6,\u0007%\u0001\u0005uKN$h*Y7f\u0003%!Xm\u001d;OC6,\u0007%\u0001\u0005uKN$H+\u001a=u\u0003%!Xm\u001d;UKb$\b%\u0001\bsK\u000e|\'\u000fZ3e\u000bZ,g\u000e^:\u0016\u0005\u0005]\u0002CBA\u001d\u0003\u0007\n9%\u0004\u0002\u0002<)!\u0011QHA \u0003%IW.\\;uC\ndWMC\u0002\u0002B)\f!bY8mY\u0016\u001cG/[8o\u0013\u0011\t)%a\u000f\u0003\u0015%sG-\u001a=fIN+\u0017\u000fE\u0002c\u0003\u0013J1!a\u0013Z\u0005=\u0011VmY8sI\u0006\u0014G.Z#wK:$\u0018a\u0004:fG>\u0014H-\u001a3Fm\u0016tGo\u001d\u0011\u0002\u0013QD\'o\\<bE2,WCAA*!\u0015I\u0017QEA+!\ry\u0017qK\u0005\u0004\u00033J(!\u0003+ie><\u0018M\u00197f\u0003)!\bN]8xC\ndW\rI\u0001\tIV\u0014\u0018\r^5p]V\u0011\u0011\u0011\r\t\u0006S\u0006\u0015\u00121\r\t\u0004S\u0006\u0015\u0014bAA4U\n!Aj\u001c8h\u0003%!WO]1uS>t\u0007%A\u0005g_Jl\u0017\r\u001e;feV\u0011\u0011q\u000e\t\u0006S\u0006\u0015\u0012\u0011\u000f\t\u0004E\u0006M\u0014bAA;3\nIai\u001c:nCR$XM]\u0001\u000bM>\u0014X.\u0019;uKJ\u0004\u0013\u0001\u00037pG\u0006$\u0018n\u001c8\u0016\u0005\u0005u\u0004#B5\u0002&\u0005}\u0004c\u00012\u0002\u0002&\u0019\u00111Q-\u0003\u00111{7-\u0019;j_:\f\u0011\u0002\\8dCRLwN\u001c\u0011\u0002\u0011I,\'/\u001e8oKJ\f\u0011B]3sk:tWM\u001d\u0011\u0002\u000fA\f\u0017\u0010\\8bIV\u0011\u0011q\u0012\t\u0006S\u0006\u0015\u0012\u0011\u0013\t\u0004S\u0006M\u0015bAAKU\n\u0019\u0011I\\=\u0002\u0011A\f\u0017\u0010\\8bI\u0002\n!\u0002\u001e5sK\u0006$g*Y7f\u0003-!\bN]3bI:\u000bW.\u001a\u0011\u0002\u0013QLW.Z*uC6\u0004XCAA2\u0003)!\u0018.\\3Ti\u0006l\u0007\u000fI\u0001\u0007y%t\u0017\u000e\u001e \u0015E\u0005\u001d\u0016\u0011VAV\u0003[\u000by+!-\u00024\u0006U\u0016qWA]\u0003w\u000bi,a0\u0002B\u0006\r\u0017QYAd!\t\u0011\u0007\u0001C\u0003{C\u0001\u0007A\u0010C\u0004\u0002\u0002\u0005\u0002\r!!\u0002\t\u000f\u0005]\u0011\u00051\u0001\u0002\u0006!9\u00111D\u0011A\u0002\u0005\u0015\u0001bBA\u0010C\u0001\u0007\u00111\u0005\u0005\b\u0003W\t\u0003\u0019AA\u0003\u0011\u001d\ty#\ta\u0001\u0003\u000bAq!a\r\"\u0001\u0004\t9\u0004C\u0005\u0002P\u0005\u0002\n\u00111\u0001\u0002T!I\u0011QL\u0011\u0011\u0002\u0003\u0007\u0011\u0011\r\u0005\n\u0003W\n\u0003\u0013!a\u0001\u0003_B\u0011\"!\u001f\"!\u0003\u0005\r!! \t\u0013\u0005\u001d\u0015\u0005%AA\u0002\u0005\r\u0002\"CAFCA\u0005\t\u0019AAH\u0011%\tI*\tI\u0001\u0002\u0004\t)\u0001C\u0005\u0002\u001e\u0006\u0002\n\u00111\u0001\u0002d\u0005)Ao\u001c-nYV\u0011\u0011Q\u001a\t\u0005\u0003\u001f\f).\u0004\u0002\u0002R*\u0019\u00111\u001b6\u0002\u0007alG.\u0003\u0003\u0002X\u0006E\'\u0001B#mK6\fa\u0001^8Kg>t\u0017aC<ji\"\u0004\u0016-\u001f7pC\u0012$B!a*\u0002`\"9\u0011\u0011\u001d\u0013A\u0002\u0005=\u0015A\u00038foB\u000b\u0017\u0010\\8bI\u0006iq/\u001b;i)\"\u0014xn^1cY\u0016$2!YAt\u0011\u001d\tI/\na\u0001\u0003\'\nAB\\3x)\"\u0014xn^1cY\u0016\f!#\u001a8tkJ,7+\u001a:jC2L\'0\u00192mKR\t\u0011-\u0001\u0003d_BLHCIAT\u0003g\f)0a>\u0002z\u0006m\u0018Q`A\u0000\u0005\u0003\u0011\u0019A!\u0002\u0003\b\t%!1\u0002B\u0007\u0005\u001f\u0011\t\u0002C\u0004{OA\u0005\t\u0019\u0001?\t\u0013\u0005\u0005q\u0005%AA\u0002\u0005\u0015\u0001\"CA\fOA\u0005\t\u0019AA\u0003\u0011%\tYb\nI\u0001\u0002\u0004\t)\u0001C\u0005\u0002 \u001d\u0002\n\u00111\u0001\u0002$!I\u00111F\u0014\u0011\u0002\u0003\u0007\u0011Q\u0001\u0005\n\u0003_9\u0003\u0013!a\u0001\u0003\u000bA\u0011\"a\r(!\u0003\u0005\r!a\u000e\t\u0013\u0005=s\u0005%AA\u0002\u0005M\u0003\"CA/OA\u0005\t\u0019AA1\u0011%\tYg\nI\u0001\u0002\u0004\ty\u0007C\u0005\u0002z\u001d\u0002\n\u00111\u0001\u0002~!I\u0011qQ\u0014\u0011\u0002\u0003\u0007\u00111\u0005\u0005\n\u0003\u0017;\u0003\u0013!a\u0001\u0003\u001fC\u0011\"!\'(!\u0003\u0005\r!!\u0002\t\u0013\u0005uu\u0005%AA\u0002\u0005\r\u0014AD2paf$C-\u001a4bk2$H%M\u000b\u0003\u0005/Q3\u0001 B\rW\t\u0011Y\u0002\u0005\u0003\u0003\u001e\t\u001dRB\u0001B\u0010\u0015\u0011\u0011\tCa\t\u0002\u0013Ut7\r[3dW\u0016$\'b\u0001B\u0013U\u0006Q\u0011M\u001c8pi\u0006$\u0018n\u001c8\n\t\t%\"q\u0004\u0002\u0012k:\u001c\u0007.Z2lK\u00124\u0016M]5b]\u000e,\u0017AD2paf$C-\u001a4bk2$HEM\u000b\u0003\u0005_QC!!\u0002\u0003\u001a\u0005q1m\u001c9zI\u0011,g-Y;mi\u0012\u001a\u0014AD2paf$C-\u001a4bk2$H\u0005N\u0001\u000fG>\u0004\u0018\u0010\n3fM\u0006,H\u000e\u001e\u00136+\t\u0011ID\u000b\u0003\u0002$\te\u0011AD2paf$C-\u001a4bk2$HEN\u0001\u000fG>\u0004\u0018\u0010\n3fM\u0006,H\u000e\u001e\u00138\u00039\u0019w\u000e]=%I\u00164\u0017-\u001e7uIa*\"Aa\u0011+\t\u0005]\"\u0011D\u0001\u000fG>\u0004\u0018\u0010\n3fM\u0006,H\u000e\u001e\u0013:+\t\u0011IE\u000b\u0003\u0002T\te\u0011aD2paf$C-\u001a4bk2$H%\r\u0019\u0016\u0005\t=#\u0006BA1\u00053\tqbY8qs\u0012\"WMZ1vYR$\u0013\'M\u000b\u0003\u0005+RC!a\u001c\u0003\u001a\u0005y1m\u001c9zI\u0011,g-Y;mi\u0012\n$\'\u0006\u0002\u0003\\)\"\u0011Q\u0010B\r\u0003=\u0019w\u000e]=%I\u00164\u0017-\u001e7uIE\u001a\u0014aD2paf$C-\u001a4bk2$H%\r\u001b\u0016\u0005\t\r$\u0006BAH\u00053\tqbY8qs\u0012\"WMZ1vYR$\u0013\'N\u0001\u0010G>\u0004\u0018\u0010\n3fM\u0006,H\u000e\u001e\u00132mU\u0011!1\u000e\u0016\u0005\u0003G\u0012I\"A\u0007qe>$Wo\u0019;Qe\u00164\u0017\u000e_\u000b\u0003\u0005c\u0002BAa\u001d\u0003~5\u0011!Q\u000f\u0006\u0005\u0005o\u0012I(\u0001\u0003mC:<\'B\u0001B>\u0003\u0011Q\u0017M^1\n\t\u0005E!QO\u0001\raJ|G-^2u\u0003JLG/_\u000b\u0003\u0005\u0007\u00032!\u001bBC\u0013\r\u00119I\u001b\u0002\u0004\u0013:$\u0018A\u00049s_\u0012,8\r^#mK6,g\u000e\u001e\u000b\u0005\u0003#\u0013i\tC\u0005\u0003\u0010j\n\t\u00111\u0001\u0003\u0004\u0006\u0019\u0001\u0010J\u0019\u0002\u001fA\u0014x\u000eZ;di&#XM]1u_J,\"A!&\u0011\r\t]%\u0011TAI\u001b\t\ty$\u0003\u0003\u0003\u001c\u0006}\"\u0001C%uKJ\fGo\u001c:\u0002\u0011\r\fg.R9vC2$BA!)\u0003(B\u0019\u0011Na)\n\u0007\t\u0015&NA\u0004C_>dW-\u00198\t\u0013\t=E(!AA\u0002\u0005E\u0015A\u00059s_\u0012,8\r^#mK6,g\u000e\u001e(b[\u0016$BA!\u001d\u0003.\"I!qR\u001f\u0002\u0002\u0003\u0007!1Q\u0001\tQ\u0006\u001c\bnQ8eKR\u0011!1Q\u0001\ti>\u001cFO]5oOR\u0011!\u0011O\u0001\u0007KF,\u0018\r\\:\u0015\t\t\u0005&1\u0018\u0005\n\u0005\u001f\u0003\u0015\u0011!a\u0001\u0003#\u000bA\u0002V3ti\u000e\u000bgnY3mK\u0012\u0004\"A\u0019\"\u0014\u000b\t\u0013\u0019Ma4\u0011K\t\u0015\'1\u001a?\u0002\u0006\u0005\u0015\u0011QAA\u0012\u0003\u000b\t)!a\u000e\u0002T\u0005\u0005\u0014qNA?\u0003G\ty)!\u0002\u0002d\u0005\u001dVB\u0001Bd\u0015\r\u0011IM[\u0001\beVtG/[7f\u0013\u0011\u0011iMa2\u0003%\u0005\u00137\u000f\u001e:bGR4UO\\2uS>t\u0017G\u000e\t\u0005\u0005#\u00149.\u0004\u0002\u0003T*!!Q\u001bB=\u0003\tIw.C\u0002y\u0005\'$\"Aa0\u0002\u000b\u0005\u0004\b\u000f\\=\u0015E\u0005\u001d&q\u001cBq\u0005G\u0014)Oa:\u0003j\n-(Q\u001eBx\u0005c\u0014\u0019P!>\u0003x\ne(1 B\u007f\u0011\u0015QX\t1\u0001}\u0011\u001d\t\t!\u0012a\u0001\u0003\u000bAq!a\u0006F\u0001\u0004\t)\u0001C\u0004\u0002\u001c\u0015\u0003\r!!\u0002\t\u000f\u0005}Q\t1\u0001\u0002$!9\u00111F#A\u0002\u0005\u0015\u0001bBA\u0018\u000b\u0002\u0007\u0011Q\u0001\u0005\b\u0003g)\u0005\u0019AA\u001c\u0011%\ty%\u0012I\u0001\u0002\u0004\t\u0019\u0006C\u0005\u0002^\u0015\u0003\n\u00111\u0001\u0002b!I\u00111N#\u0011\u0002\u0003\u0007\u0011q\u000e\u0005\n\u0003s*\u0005\u0013!a\u0001\u0003{B\u0011\"a\"F!\u0003\u0005\r!a\t\t\u0013\u0005-U\t%AA\u0002\u0005=\u0005\"CAM\u000bB\u0005\t\u0019AA\u0003\u0011%\ti*\u0012I\u0001\u0002\u0004\t\u0019\'A\bbaBd\u0017\u0010\n3fM\u0006,H\u000e\u001e\u0013:\u0003A\t\u0007\u000f\u001d7zI\u0011,g-Y;mi\u0012\n\u0004\'\u0001\tbaBd\u0017\u0010\n3fM\u0006,H\u000e\u001e\u00132c\u0005\u0001\u0012\r\u001d9ms\u0012\"WMZ1vYR$\u0013GM\u0001\u0011CB\u0004H.\u001f\u0013eK\u001a\fW\u000f\u001c;%cM\n\u0001#\u00199qYf$C-\u001a4bk2$H%\r\u001b\u0002!\u0005\u0004\b\u000f\\=%I\u00164\u0017-\u001e7uIE*\u0014\u0001E1qa2LH\u0005Z3gCVdG\u000fJ\u00197\u0003\u001d)h.\u00199qYf$Baa\u0005\u0004\u001cA)\u0011.!\n\u0004\u0016A\u0011\u0013na\u0006}\u0003\u000b\t)!!\u0002\u0002$\u0005\u0015\u0011QAA\u001c\u0003\'\n\t\'a\u001c\u0002~\u0005\r\u0012qRA\u0003\u0003GJ1a!\u0007k\u0005\u001d!V\u000f\u001d7fcYB\u0011b!\bO\u0003\u0003\u0005\r!a*\u0002\u0007a$\u0003\'A\u000e%Y\u0016\u001c8/\u001b8ji\u0012:\'/Z1uKJ$C-\u001a4bk2$H%O\u0001\u001dI1,7o]5oSR$sM]3bi\u0016\u0014H\u0005Z3gCVdG\u000fJ\u00191\u0003q!C.Z:tS:LG\u000fJ4sK\u0006$XM\u001d\u0013eK\u001a\fW\u000f\u001c;%cE\nA\u0004\n7fgNLg.\u001b;%OJ,\u0017\r^3sI\u0011,g-Y;mi\u0012\n$\'\u0001\u000f%Y\u0016\u001c8/\u001b8ji\u0012:\'/Z1uKJ$C-\u001a4bk2$H%M\u001a\u00029\u0011bWm]:j]&$He\u001a:fCR,\'\u000f\n3fM\u0006,H\u000e\u001e\u00132i\u0005aB\u0005\\3tg&t\u0017\u000e\u001e\u0013he\u0016\fG/\u001a:%I\u00164\u0017-\u001e7uIE*\u0014\u0001\b\u0013mKN\u001c\u0018N\\5uI\u001d\u0014X-\u0019;fe\u0012\"WMZ1vYR$\u0013GN\u0001\roJLG/\u001a*fa2\f7-\u001a\u000b\u0003\u0007g\u0001BAa\u001d\u00046%!1q\u0007B;\u0005\u0019y%M[3di\u0002
   #11 = Utf8               java/lang/invoke/MethodHandles$Lookup
   #12 = Class              #11           // java/lang/invoke/MethodHandles$Lookup
   #13 = Utf8               java/lang/invoke/MethodHandles
   #14 = Class              #13           // java/lang/invoke/MethodHandles
   #15 = Utf8               Lookup
   #16 = Utf8               org/scalactic/Requirements$RequirementsHelper
   #17 = Class              #16           // org/scalactic/Requirements$RequirementsHelper
   #18 = Utf8               org/scalactic/Requirements
   #19 = Class              #18           // org/scalactic/Requirements
   #20 = Utf8               RequirementsHelper
   #21 = Utf8               org/scalatest/events/Event$EventJsonHelper$
   #22 = Class              #21           // org/scalatest/events/Event$EventJsonHelper$
   #23 = Utf8               EventJsonHelper$
   #24 = Utf8               org/scalatest/events/Event$EventXmlHelper$
   #25 = Class              #24           // org/scalatest/events/Event$EventXmlHelper$
   #26 = Utf8               EventXmlHelper$
   #27 = Utf8               ordinal
   #28 = Utf8               Lorg/scalatest/events/Ordinal;
   #29 = Utf8               message
   #30 = Utf8               Ljava/lang/String;
   #31 = Utf8               suiteName
   #32 = Utf8               suiteId
   #33 = Utf8               suiteClassName
   #34 = Utf8               Lscala/Option;
   #35 = Utf8               Lscala/Option<Ljava/lang/String;>;
   #36 = Utf8               testName
   #37 = Utf8               testText
   #38 = Utf8               recordedEvents
   #39 = Utf8               Lscala/collection/immutable/IndexedSeq;
   #40 = Utf8               Lscala/collection/immutable/IndexedSeq<Lorg/scalatest/events/RecordableEvent;>;
   #41 = Utf8               throwable
   #42 = Utf8               Lscala/Option<Ljava/lang/Throwable;>;
   #43 = Utf8               duration
   #44 = Utf8               Lscala/Option<Ljava/lang/Object;>;
   #45 = Utf8               formatter
   #46 = Utf8               Lscala/Option<Lorg/scalatest/events/Formatter;>;
   #47 = Utf8               location
   #48 = Utf8               Lscala/Option<Lorg/scalatest/events/Location;>;
   #49 = Utf8               rerunner
   #50 = Utf8               payload
   #51 = Utf8               threadName
   #52 = Utf8               timeStamp
   #53 = Utf8               J
   #54 = Utf8               $lessinit$greater$default$16
   #55 = Utf8               ()J
   #56 = Utf8               org/scalatest/events/TestCanceled$
   #57 = Class              #56           // org/scalatest/events/TestCanceled$
   #58 = Utf8               MODULE$
   #59 = Utf8               Lorg/scalatest/events/TestCanceled$;
   #60 = NameAndType        #58:#59       // MODULE$:Lorg/scalatest/events/TestCanceled$;
   #61 = Fieldref           #57.#60       // org/scalatest/events/TestCanceled$.MODULE$:Lorg/scalatest/events/TestCanceled$;
   #62 = NameAndType        #54:#55       // $lessinit$greater$default$16:()J
   #63 = Methodref          #57.#62       // org/scalatest/events/TestCanceled$.$lessinit$greater$default$16:()J
   #64 = Utf8               $lessinit$greater$default$15
   #65 = Utf8               ()Ljava/lang/String;
   #66 = NameAndType        #64:#65       // $lessinit$greater$default$15:()Ljava/lang/String;
   #67 = Methodref          #57.#66       // org/scalatest/events/TestCanceled$.$lessinit$greater$default$15:()Ljava/lang/String;
   #68 = Utf8               $lessinit$greater$default$14
   #69 = Utf8               ()Lscala/Option;
   #70 = Utf8               ()Lscala/Option<Ljava/lang/Object;>;
   #71 = NameAndType        #68:#69       // $lessinit$greater$default$14:()Lscala/Option;
   #72 = Methodref          #57.#71       // org/scalatest/events/TestCanceled$.$lessinit$greater$default$14:()Lscala/Option;
   #73 = Utf8               $lessinit$greater$default$13
   #74 = Utf8               ()Lscala/Option<Ljava/lang/String;>;
   #75 = NameAndType        #73:#69       // $lessinit$greater$default$13:()Lscala/Option;
   #76 = Methodref          #57.#75       // org/scalatest/events/TestCanceled$.$lessinit$greater$default$13:()Lscala/Option;
   #77 = Utf8               $lessinit$greater$default$12
   #78 = Utf8               ()Lscala/Option<Lorg/scalatest/events/Location;>;
   #79 = NameAndType        #77:#69       // $lessinit$greater$default$12:()Lscala/Option;
   #80 = Methodref          #57.#79       // org/scalatest/events/TestCanceled$.$lessinit$greater$default$12:()Lscala/Option;
   #81 = Utf8               $lessinit$greater$default$11
   #82 = Utf8               ()Lscala/Option<Lorg/scalatest/events/Formatter;>;
   #83 = NameAndType        #81:#69       // $lessinit$greater$default$11:()Lscala/Option;
   #84 = Methodref          #57.#83       // org/scalatest/events/TestCanceled$.$lessinit$greater$default$11:()Lscala/Option;
   #85 = Utf8               $lessinit$greater$default$10
   #86 = NameAndType        #85:#69       // $lessinit$greater$default$10:()Lscala/Option;
   #87 = Methodref          #57.#86       // org/scalatest/events/TestCanceled$.$lessinit$greater$default$10:()Lscala/Option;
   #88 = Utf8               $lessinit$greater$default$9
   #89 = Utf8               ()Lscala/Option<Ljava/lang/Throwable;>;
   #90 = NameAndType        #88:#69       // $lessinit$greater$default$9:()Lscala/Option;
   #91 = Methodref          #57.#90       // org/scalatest/events/TestCanceled$.$lessinit$greater$default$9:()Lscala/Option;
   #92 = Utf8               unapply
   #93 = Utf8               (Lorg/scalatest/events/TestCanceled;)Lscala/Option;
   #94 = Utf8               (Lorg/scalatest/events/TestCanceled;)Lscala/Option<Lscala/Tuple16<Lorg/scalatest/events/Ordinal;Ljava/lang/String;Ljava/lang/String;Ljava/lang/String;Lscala/Option<Ljava/lang/String;>;Ljava/lang/String;Ljava/lang/String;Lscala/collection/immutable/IndexedSeq<Lorg/scalatest/events/RecordableEvent;>;Lscala/Option<Ljava/lang/Throwable;>;Lscala/Option<Ljava/lang/Object;>;Lscala/Option<Lorg/scalatest/events/Formatter;>;Lscala/Option<Lorg/scalatest/events/Location;>;Lscala/Option<Ljava/lang/String;>;Lscala/Option<Ljava/lang/Object;>;Ljava/lang/String;Ljava/lang/Object;>;>;
   #95 = Utf8               x$0
   #96 = NameAndType        #92:#93       // unapply:(Lorg/scalatest/events/TestCanceled;)Lscala/Option;
   #97 = Methodref          #57.#96       // org/scalatest/events/TestCanceled$.unapply:(Lorg/scalatest/events/TestCanceled;)Lscala/Option;
   #98 = Utf8               Lorg/scalatest/events/TestCanceled;
   #99 = Utf8               apply$default$16
  #100 = NameAndType        #99:#55       // apply$default$16:()J
  #101 = Methodref          #57.#100      // org/scalatest/events/TestCanceled$.apply$default$16:()J
  #102 = Utf8               apply$default$15
  #103 = NameAndType        #102:#65      // apply$default$15:()Ljava/lang/String;
  #104 = Methodref          #57.#103      // org/scalatest/events/TestCanceled$.apply$default$15:()Ljava/lang/String;
  #105 = Utf8               apply$default$14
  #106 = NameAndType        #105:#69      // apply$default$14:()Lscala/Option;
  #107 = Methodref          #57.#106      // org/scalatest/events/TestCanceled$.apply$default$14:()Lscala/Option;
  #108 = Utf8               apply$default$13
  #109 = NameAndType        #108:#69      // apply$default$13:()Lscala/Option;
  #110 = Methodref          #57.#109      // org/scalatest/events/TestCanceled$.apply$default$13:()Lscala/Option;
  #111 = Utf8               apply$default$12
  #112 = NameAndType        #111:#69      // apply$default$12:()Lscala/Option;
  #113 = Methodref          #57.#112      // org/scalatest/events/TestCanceled$.apply$default$12:()Lscala/Option;
  #114 = Utf8               apply$default$11
  #115 = NameAndType        #114:#69      // apply$default$11:()Lscala/Option;
  #116 = Methodref          #57.#115      // org/scalatest/events/TestCanceled$.apply$default$11:()Lscala/Option;
  #117 = Utf8               apply$default$10
  #118 = NameAndType        #117:#69      // apply$default$10:()Lscala/Option;
  #119 = Methodref          #57.#118      // org/scalatest/events/TestCanceled$.apply$default$10:()Lscala/Option;
  #120 = Utf8               apply$default$9
  #121 = NameAndType        #120:#69      // apply$default$9:()Lscala/Option;
  #122 = Methodref          #57.#121      // org/scalatest/events/TestCanceled$.apply$default$9:()Lscala/Option;
  #123 = Utf8               apply
  #124 = Utf8               (Lorg/scalatest/events/Ordinal;Ljava/lang/String;Ljava/lang/String;Ljava/lang/String;Lscala/Option;Ljava/lang/String;Ljava/lang/String;Lscala/collection/immutable/IndexedSeq;Lscala/Option;Lscala/Option;Lscala/Option;Lscala/Option;Lscala/Option;Lscala/Option;Ljava/lang/String;J)Lorg/scalatest/events/TestCanceled;
  #125 = Utf8               (Lorg/scalatest/events/Ordinal;Ljava/lang/String;Ljava/lang/String;Ljava/lang/String;Lscala/Option<Ljava/lang/String;>;Ljava/lang/String;Ljava/lang/String;Lscala/collection/immutable/IndexedSeq<Lorg/scalatest/events/RecordableEvent;>;Lscala/Option<Ljava/lang/Throwable;>;Lscala/Option<Ljava/lang/Object;>;Lscala/Option<Lorg/scalatest/events/Formatter;>;Lscala/Option<Lorg/scalatest/events/Location;>;Lscala/Option<Ljava/lang/String;>;Lscala/Option<Ljava/lang/Object;>;Ljava/lang/String;J)Lorg/scalatest/events/TestCanceled;
  #126 = NameAndType        #123:#124     // apply:(Lorg/scalatest/events/Ordinal;Ljava/lang/String;Ljava/lang/String;Ljava/lang/String;Lscala/Option;Ljava/lang/String;Ljava/lang/String;Lscala/collection/immutable/IndexedSeq;Lscala/Option;Lscala/Option;Lscala/Option;Lscala/Option;Lscala/Option;Lscala/Option;Ljava/lang/String;J)Lorg/scalatest/events/TestCanceled;
  #127 = Methodref          #57.#126      // org/scalatest/events/TestCanceled$.apply:(Lorg/scalatest/events/Ordinal;Ljava/lang/String;Ljava/lang/String;Ljava/lang/String;Lscala/Option;Ljava/lang/String;Ljava/lang/String;Lscala/collection/immutable/IndexedSeq;Lscala/Option;Lscala/Option;Lscala/Option;Lscala/Option;Lscala/Option;Lscala/Option;Ljava/lang/String;J)Lorg/scalatest/events/TestCanceled;
  #128 = Utf8               tupled
  #129 = Utf8               ()Lscala/Function1;
  #130 = Utf8               ()Lscala/Function1<Lscala/Tuple16<Lorg/scalatest/events/Ordinal;Ljava/lang/String;Ljava/lang/String;Ljava/lang/String;Lscala/Option<Ljava/lang/String;>;Ljava/lang/String;Ljava/lang/String;Lscala/collection/immutable/IndexedSeq<Lorg/scalatest/events/RecordableEvent;>;Lscala/Option<Ljava/lang/Throwable;>;Lscala/Option<Ljava/lang/Object;>;Lscala/Option<Lorg/scalatest/events/Formatter;>;Lscala/Option<Lorg/scalatest/events/Location;>;Lscala/Option<Ljava/lang/String;>;Lscala/Option<Ljava/lang/Object;>;Ljava/lang/String;Ljava/lang/Object;>;Lorg/scalatest/events/TestCanceled;>;
  #131 = NameAndType        #128:#129     // tupled:()Lscala/Function1;
  #132 = Methodref          #57.#131      // org/scalatest/events/TestCanceled$.tupled:()Lscala/Function1;
  #133 = Utf8               curried
  #134 = Utf8               ()Lscala/Function1<Lorg/scalatest/events/Ordinal;Lscala/Function1<Ljava/lang/String;Lscala/Function1<Ljava/lang/String;Lscala/Function1<Ljava/lang/String;Lscala/Function1<Lscala/Option<Ljava/lang/String;>;Lscala/Function1<Ljava/lang/String;Lscala/Function1<Ljava/lang/String;Lscala/Function1<Lscala/collection/immutable/IndexedSeq<Lorg/scalatest/events/RecordableEvent;>;Lscala/Function1<Lscala/Option<Ljava/lang/Throwable;>;Lscala/Function1<Lscala/Option<Ljava/lang/Object;>;Lscala/Function1<Lscala/Option<Lorg/scalatest/events/Formatter;>;Lscala/Function1<Lscala/Option<Lorg/scalatest/events/Location;>;Lscala/Function1<Lscala/Option<Ljava/lang/String;>;Lscala/Function1<Lscala/Option<Ljava/lang/Object;>;Lscala/Function1<Ljava/lang/String;Lscala/Function1<Ljava/lang/Object;Lorg/scalatest/events/TestCanceled;>;>;>;>;>;>;>;>;>;>;>;>;>;>;>;>;
  #135 = NameAndType        #133:#129     // curried:()Lscala/Function1;
  #136 = Methodref          #57.#135      // org/scalatest/events/TestCanceled$.curried:()Lscala/Function1;
  #137 = Utf8               ()Lorg/scalatest/events/Ordinal;
  #138 = NameAndType        #27:#28       // ordinal:Lorg/scalatest/events/Ordinal;
  #139 = Fieldref           #2.#138       // org/scalatest/events/TestCanceled.ordinal:Lorg/scalatest/events/Ordinal;
  #140 = Utf8               this
  #141 = NameAndType        #29:#30       // message:Ljava/lang/String;
  #142 = Fieldref           #2.#141       // org/scalatest/events/TestCanceled.message:Ljava/lang/String;
  #143 = NameAndType        #31:#30       // suiteName:Ljava/lang/String;
  #144 = Fieldref           #2.#143       // org/scalatest/events/TestCanceled.suiteName:Ljava/lang/String;
  #145 = NameAndType        #32:#30       // suiteId:Ljava/lang/String;
  #146 = Fieldref           #2.#145       // org/scalatest/events/TestCanceled.suiteId:Ljava/lang/String;
  #147 = NameAndType        #33:#34       // suiteClassName:Lscala/Option;
  #148 = Fieldref           #2.#147       // org/scalatest/events/TestCanceled.suiteClassName:Lscala/Option;
  #149 = NameAndType        #36:#30       // testName:Ljava/lang/String;
  #150 = Fieldref           #2.#149       // org/scalatest/events/TestCanceled.testName:Ljava/lang/String;
  #151 = NameAndType        #37:#30       // testText:Ljava/lang/String;
  #152 = Fieldref           #2.#151       // org/scalatest/events/TestCanceled.testText:Ljava/lang/String;
  #153 = Utf8               ()Lscala/collection/immutable/IndexedSeq;
  #154 = Utf8               ()Lscala/collection/immutable/IndexedSeq<Lorg/scalatest/events/RecordableEvent;>;
  #155 = NameAndType        #38:#39       // recordedEvents:Lscala/collection/immutable/IndexedSeq;
  #156 = Fieldref           #2.#155       // org/scalatest/events/TestCanceled.recordedEvents:Lscala/collection/immutable/IndexedSeq;
  #157 = NameAndType        #41:#34       // throwable:Lscala/Option;
  #158 = Fieldref           #2.#157       // org/scalatest/events/TestCanceled.throwable:Lscala/Option;
  #159 = NameAndType        #43:#34       // duration:Lscala/Option;
  #160 = Fieldref           #2.#159       // org/scalatest/events/TestCanceled.duration:Lscala/Option;
  #161 = NameAndType        #45:#34       // formatter:Lscala/Option;
  #162 = Fieldref           #2.#161       // org/scalatest/events/TestCanceled.formatter:Lscala/Option;
  #163 = NameAndType        #47:#34       // location:Lscala/Option;
  #164 = Fieldref           #2.#163       // org/scalatest/events/TestCanceled.location:Lscala/Option;
  #165 = NameAndType        #49:#34       // rerunner:Lscala/Option;
  #166 = Fieldref           #2.#165       // org/scalatest/events/TestCanceled.rerunner:Lscala/Option;
  #167 = NameAndType        #50:#34       // payload:Lscala/Option;
  #168 = Fieldref           #2.#167       // org/scalatest/events/TestCanceled.payload:Lscala/Option;
  #169 = NameAndType        #51:#30       // threadName:Ljava/lang/String;
  #170 = Fieldref           #2.#169       // org/scalatest/events/TestCanceled.threadName:Ljava/lang/String;
  #171 = NameAndType        #52:#53       // timeStamp:J
  #172 = Fieldref           #2.#171       // org/scalatest/events/TestCanceled.timeStamp:J
  #173 = Utf8               toXml
  #174 = Utf8               ()Lscala/xml/Elem;
  #175 = Utf8               scala/xml/Elem
  #176 = Class              #175          // scala/xml/Elem
  #177 = Utf8               TestCanceled
  #178 = String             #177          // TestCanceled
  #179 = Utf8               scala/xml/Null$
  #180 = Class              #179          // scala/xml/Null$
  #181 = Utf8               Lscala/xml/Null$;
  #182 = NameAndType        #58:#181      // MODULE$:Lscala/xml/Null$;
  #183 = Fieldref           #180.#182     // scala/xml/Null$.MODULE$:Lscala/xml/Null$;
  #184 = Utf8               scala/xml/TopScope$
  #185 = Class              #184          // scala/xml/TopScope$
  #186 = Utf8               Lscala/xml/TopScope$;
  #187 = NameAndType        #58:#186      // MODULE$:Lscala/xml/TopScope$;
  #188 = Fieldref           #185.#187     // scala/xml/TopScope$.MODULE$:Lscala/xml/TopScope$;
  #189 = Utf8               scala/xml/NodeSeq$
  #190 = Class              #189          // scala/xml/NodeSeq$
  #191 = Utf8               Lscala/xml/NodeSeq$;
  #192 = NameAndType        #58:#191      // MODULE$:Lscala/xml/NodeSeq$;
  #193 = Fieldref           #190.#192     // scala/xml/NodeSeq$.MODULE$:Lscala/xml/NodeSeq$;
  #194 = Utf8               scala/xml/NodeBuffer
  #195 = Class              #194          // scala/xml/NodeBuffer
  #196 = Utf8               <init>
  #197 = Utf8               ()V
  #198 = NameAndType        #196:#197     // "<init>":()V
  #199 = Methodref          #195.#198     // scala/xml/NodeBuffer."<init>":()V
  #200 = Utf8               scala/xml/Text
  #201 = Class              #200          // scala/xml/Text
  #202 = Utf8               \n
  #203 = String             #202          // \n
  #204 = Utf8               (Ljava/lang/String;)V
  #205 = NameAndType        #196:#204     // "<init>":(Ljava/lang/String;)V
  #206 = Methodref          #201.#205     // scala/xml/Text."<init>":(Ljava/lang/String;)V
  #207 = Utf8               $amp$plus
  #208 = Utf8               (Ljava/lang/Object;)Lscala/xml/NodeBuffer;
  #209 = NameAndType        #207:#208     // $amp$plus:(Ljava/lang/Object;)Lscala/xml/NodeBuffer;
  #210 = Methodref          #195.#209     // scala/xml/NodeBuffer.$amp$plus:(Ljava/lang/Object;)Lscala/xml/NodeBuffer;
  #211 = String             #27           // ordinal
  #212 = Utf8               \n
  #213 = String             #212          // \n
  #214 = Utf8               runStamp
  #215 = String             #214          // runStamp
  #216 = NameAndType        #27:#137      // ordinal:()Lorg/scalatest/events/Ordinal;
  #217 = Methodref          #2.#216       // org/scalatest/events/TestCanceled.ordinal:()Lorg/scalatest/events/Ordinal;
  #218 = Utf8               org/scalatest/events/Ordinal
  #219 = Class              #218          // org/scalatest/events/Ordinal
  #220 = Utf8               ()I
  #221 = NameAndType        #214:#220     // runStamp:()I
  #222 = Methodref          #219.#221     // org/scalatest/events/Ordinal.runStamp:()I
  #223 = Utf8               scala/runtime/BoxesRunTime
  #224 = Class              #223          // scala/runtime/BoxesRunTime
  #225 = Utf8               boxToInteger
  #226 = Utf8               (I)Ljava/lang/Integer;
  #227 = NameAndType        #225:#226     // boxToInteger:(I)Ljava/lang/Integer;
  #228 = Methodref          #224.#227     // scala/runtime/BoxesRunTime.boxToInteger:(I)Ljava/lang/Integer;
  #229 = Utf8               seqToNodeSeq
  #230 = Utf8               (Lscala/collection/Seq;)Lscala/xml/NodeSeq;
  #231 = NameAndType        #229:#230     // seqToNodeSeq:(Lscala/collection/Seq;)Lscala/xml/NodeSeq;
  #232 = Methodref          #190.#231     // scala/xml/NodeSeq$.seqToNodeSeq:(Lscala/collection/Seq;)Lscala/xml/NodeSeq;
  #233 = Utf8               (Ljava/lang/String;Ljava/lang/String;Lscala/xml/MetaData;Lscala/xml/NamespaceBinding;ZLscala/collection/immutable/Seq;)V
  #234 = NameAndType        #196:#233     // "<init>":(Ljava/lang/String;Ljava/lang/String;Lscala/xml/MetaData;Lscala/xml/NamespaceBinding;ZLscala/collection/immutable/Seq;)V
  #235 = Methodref          #176.#234     // scala/xml/Elem."<init>":(Ljava/lang/String;Ljava/lang/String;Lscala/xml/MetaData;Lscala/xml/NamespaceBinding;ZLscala/collection/immutable/Seq;)V
  #236 = String             #29           // message
  #237 = NameAndType        #29:#65       // message:()Ljava/lang/String;
  #238 = Methodref          #2.#237       // org/scalatest/events/TestCanceled.message:()Ljava/lang/String;
  #239 = String             #31           // suiteName
  #240 = NameAndType        #31:#65       // suiteName:()Ljava/lang/String;
  #241 = Methodref          #2.#240       // org/scalatest/events/TestCanceled.suiteName:()Ljava/lang/String;
  #242 = String             #32           // suiteId
  #243 = NameAndType        #32:#65       // suiteId:()Ljava/lang/String;
  #244 = Methodref          #2.#243       // org/scalatest/events/TestCanceled.suiteId:()Ljava/lang/String;
  #245 = String             #33           // suiteClassName
  #246 = Utf8               EventXmlHelper
  #247 = Utf8               ()Lorg/scalatest/events/Event$EventXmlHelper$;
  #248 = NameAndType        #246:#247     // EventXmlHelper:()Lorg/scalatest/events/Event$EventXmlHelper$;
  #249 = Methodref          #2.#248       // org/scalatest/events/TestCanceled.EventXmlHelper:()Lorg/scalatest/events/Event$EventXmlHelper$;
  #250 = NameAndType        #33:#69       // suiteClassName:()Lscala/Option;
  #251 = Methodref          #2.#250       // org/scalatest/events/TestCanceled.suiteClassName:()Lscala/Option;
  #252 = Utf8               stringOption
  #253 = Utf8               (Lscala/Option;)Ljava/lang/String;
  #254 = NameAndType        #252:#253     // stringOption:(Lscala/Option;)Ljava/lang/String;
  #255 = Methodref          #25.#254      // org/scalatest/events/Event$EventXmlHelper$.stringOption:(Lscala/Option;)Ljava/lang/String;
  #256 = String             #43           // duration
  #257 = NameAndType        #43:#69       // duration:()Lscala/Option;
  #258 = Methodref          #2.#257       // org/scalatest/events/TestCanceled.duration:()Lscala/Option;
  #259 = Utf8               longOption
  #260 = NameAndType        #259:#253     // longOption:(Lscala/Option;)Ljava/lang/String;
  #261 = Methodref          #25.#260      // org/scalatest/events/Event$EventXmlHelper$.longOption:(Lscala/Option;)Ljava/lang/String;
  #262 = String             #36           // testName
  #263 = NameAndType        #36:#65       // testName:()Ljava/lang/String;
  #264 = Methodref          #2.#263       // org/scalatest/events/TestCanceled.testName:()Ljava/lang/String;
  #265 = String             #37           // testText
  #266 = NameAndType        #37:#65       // testText:()Ljava/lang/String;
  #267 = Methodref          #2.#266       // org/scalatest/events/TestCanceled.testText:()Ljava/lang/String;
  #268 = String             #38           // recordedEvents
  #269 = NameAndType        #38:#153      // recordedEvents:()Lscala/collection/immutable/IndexedSeq;
  #270 = Methodref          #2.#269       // org/scalatest/events/TestCanceled.recordedEvents:()Lscala/collection/immutable/IndexedSeq;
  #271 = Utf8               (Ljava/lang/Object;)Ljava/lang/Object;
  #272 = MethodType         #271          //  (Ljava/lang/Object;)Ljava/lang/Object;
  #273 = Utf8               $anonfun$toXml$4
  #274 = Utf8               (Lorg/scalatest/events/RecordableEvent;)Lscala/xml/Elem;
  #275 = NameAndType        #273:#274     // $anonfun$toXml$4:(Lorg/scalatest/events/RecordableEvent;)Lscala/xml/Elem;
  #276 = Methodref          #2.#275       // org/scalatest/events/TestCanceled.$anonfun$toXml$4:(Lorg/scalatest/events/RecordableEvent;)Lscala/xml/Elem;
  #277 = MethodHandle       6:#276        // REF_invokeStatic org/scalatest/events/TestCanceled.$anonfun$toXml$4:(Lorg/scalatest/events/RecordableEvent;)Lscala/xml/Elem;
  #278 = MethodType         #274          //  (Lorg/scalatest/events/RecordableEvent;)Lscala/xml/Elem;
  #279 = Integer            5
  #280 = Integer            1
  #281 = Utf8               java/lang/invoke/LambdaMetafactory
  #282 = Class              #281          // java/lang/invoke/LambdaMetafactory
  #283 = Utf8               altMetafactory
  #284 = Utf8               (Ljava/lang/invoke/MethodHandles$Lookup;Ljava/lang/String;Ljava/lang/invoke/MethodType;[Ljava/lang/Object;)Ljava/lang/invoke/CallSite;
  #285 = NameAndType        #283:#284     // altMetafactory:(Ljava/lang/invoke/MethodHandles$Lookup;Ljava/lang/String;Ljava/lang/invoke/MethodType;[Ljava/lang/Object;)Ljava/lang/invoke/CallSite;
  #286 = Methodref          #282.#285     // java/lang/invoke/LambdaMetafactory.altMetafactory:(Ljava/lang/invoke/MethodHandles$Lookup;Ljava/lang/String;Ljava/lang/invoke/MethodType;[Ljava/lang/Object;)Ljava/lang/invoke/CallSite;
  #287 = MethodHandle       6:#286        // REF_invokeStatic java/lang/invoke/LambdaMetafactory.altMetafactory:(Ljava/lang/invoke/MethodHandles$Lookup;Ljava/lang/String;Ljava/lang/invoke/MethodType;[Ljava/lang/Object;)Ljava/lang/invoke/CallSite;
  #288 = NameAndType        #123:#129     // apply:()Lscala/Function1;
  #289 = InvokeDynamic      #0:#288       // #0:apply:()Lscala/Function1;
  #290 = Utf8               scala/collection/immutable/IndexedSeq
  #291 = Class              #290          // scala/collection/immutable/IndexedSeq
  #292 = Utf8               map
  #293 = Utf8               (Lscala/Function1;)Ljava/lang/Object;
  #294 = NameAndType        #292:#293     // map:(Lscala/Function1;)Ljava/lang/Object;
  #295 = InterfaceMethodref #291.#294     // scala/collection/immutable/IndexedSeq.map:(Lscala/Function1;)Ljava/lang/Object;
  #296 = String             #41           // throwable
  #297 = NameAndType        #41:#69       // throwable:()Lscala/Option;
  #298 = Methodref          #2.#297       // org/scalatest/events/TestCanceled.throwable:()Lscala/Option;
  #299 = Utf8               throwableOption
  #300 = Utf8               (Lscala/Option;)Ljava/lang/Object;
  #301 = NameAndType        #299:#300     // throwableOption:(Lscala/Option;)Ljava/lang/Object;
  #302 = Methodref          #25.#301      // org/scalatest/events/Event$EventXmlHelper$.throwableOption:(Lscala/Option;)Ljava/lang/Object;
  #303 = String             #45           // formatter
  #304 = NameAndType        #45:#69       // formatter:()Lscala/Option;
  #305 = Methodref          #2.#304       // org/scalatest/events/TestCanceled.formatter:()Lscala/Option;
  #306 = Utf8               formatterOption
  #307 = NameAndType        #306:#300     // formatterOption:(Lscala/Option;)Ljava/lang/Object;
  #308 = Methodref          #25.#307      // org/scalatest/events/Event$EventXmlHelper$.formatterOption:(Lscala/Option;)Ljava/lang/Object;
  #309 = String             #47           // location
  #310 = NameAndType        #47:#69       // location:()Lscala/Option;
  #311 = Methodref          #2.#310       // org/scalatest/events/TestCanceled.location:()Lscala/Option;
  #312 = Utf8               locationOption
  #313 = NameAndType        #312:#300     // locationOption:(Lscala/Option;)Ljava/lang/Object;
  #314 = Methodref          #25.#313      // org/scalatest/events/Event$EventXmlHelper$.locationOption:(Lscala/Option;)Ljava/lang/Object;
  #315 = String             #49           // rerunner
  #316 = NameAndType        #49:#69       // rerunner:()Lscala/Option;
  #317 = Methodref          #2.#316       // org/scalatest/events/TestCanceled.rerunner:()Lscala/Option;
  #318 = String             #51           // threadName
  #319 = NameAndType        #51:#65       // threadName:()Ljava/lang/String;
  #320 = Methodref          #2.#319       // org/scalatest/events/TestCanceled.threadName:()Ljava/lang/String;
  #321 = String             #52           // timeStamp
  #322 = NameAndType        #52:#55       // timeStamp:()J
  #323 = Methodref          #2.#322       // org/scalatest/events/TestCanceled.timeStamp:()J
  #324 = Utf8               boxToLong
  #325 = Utf8               (J)Ljava/lang/Long;
  #326 = NameAndType        #324:#325     // boxToLong:(J)Ljava/lang/Long;
  #327 = Methodref          #224.#326     // scala/runtime/BoxesRunTime.boxToLong:(J)Ljava/lang/Long;
  #328 = Utf8               \n
  #329 = String             #328          // \n
  #330 = Utf8               $buf
  #331 = Utf8               Lscala/xml/NodeBuffer;
  #332 = Utf8               toJson
  #333 = Utf8               scala/collection/StringOps$
  #334 = Class              #333          // scala/collection/StringOps$
  #335 = Utf8               Lscala/collection/StringOps$;
  #336 = NameAndType        #58:#335      // MODULE$:Lscala/collection/StringOps$;
  #337 = Fieldref           #334.#336     // scala/collection/StringOps$.MODULE$:Lscala/collection/StringOps$;
  #338 = Utf8               scala/Predef$
  #339 = Class              #338          // scala/Predef$
  #340 = Utf8               Lscala/Predef$;
  #341 = NameAndType        #58:#340      // MODULE$:Lscala/Predef$;
  #342 = Fieldref           #339.#341     // scala/Predef$.MODULE$:Lscala/Predef$;
  #343 = Utf8               java/lang/StringBuilder
  #344 = Class              #343          // java/lang/StringBuilder
  #345 = Integer            259
  #346 = Utf8               (I)V
  #347 = NameAndType        #196:#346     // "<init>":(I)V
  #348 = Methodref          #344.#347     // java/lang/StringBuilder."<init>":(I)V
  #349 = Utf8               { \"eventType\": \"TestCanceled\", \"ordinal\":
  #350 = String             #349          // { \"eventType\": \"TestCanceled\", \"ordinal\":
  #351 = Utf8               append
  #352 = Utf8               (Ljava/lang/String;)Ljava/lang/StringBuilder;
  #353 = NameAndType        #351:#352     // append:(Ljava/lang/String;)Ljava/lang/StringBuilder;
  #354 = Methodref          #344.#353     // java/lang/StringBuilder.append:(Ljava/lang/String;)Ljava/lang/StringBuilder;
  #355 = Utf8               (I)Ljava/lang/StringBuilder;
  #356 = NameAndType        #351:#355     // append:(I)Ljava/lang/StringBuilder;
  #357 = Methodref          #344.#356     // java/lang/StringBuilder.append:(I)Ljava/lang/StringBuilder;
  #358 = Utf8               , \"message\":
  #359 = String             #358          // , \"message\":
  #360 = Utf8               EventJsonHelper
  #361 = Utf8               ()Lorg/scalatest/events/Event$EventJsonHelper$;
  #362 = NameAndType        #360:#361     // EventJsonHelper:()Lorg/scalatest/events/Event$EventJsonHelper$;
  #363 = Methodref          #2.#362       // org/scalatest/events/TestCanceled.EventJsonHelper:()Lorg/scalatest/events/Event$EventJsonHelper$;
  #364 = Utf8               string
  #365 = Utf8               (Ljava/lang/String;)Ljava/lang/String;
  #366 = NameAndType        #364:#365     // string:(Ljava/lang/String;)Ljava/lang/String;
  #367 = Methodref          #22.#366      // org/scalatest/events/Event$EventJsonHelper$.string:(Ljava/lang/String;)Ljava/lang/String;
  #368 = Utf8               , \"suiteName\":
  #369 = String             #368          // , \"suiteName\":
  #370 = Utf8               , \"suiteId\":
  #371 = String             #370          // , \"suiteId\":
  #372 = Utf8               , \"suiteClassName\":
  #373 = String             #372          // , \"suiteClassName\":
  #374 = Methodref          #22.#254      // org/scalatest/events/Event$EventJsonHelper$.stringOption:(Lscala/Option;)Ljava/lang/String;
  #375 = Utf8               , \"duration\":
  #376 = String             #375          // , \"duration\":
  #377 = Utf8               ()Ljava/lang/Object;
  #378 = MethodType         #377          //  ()Ljava/lang/Object;
  #379 = Utf8               $anonfun$toJson$7
  #380 = NameAndType        #379:#65      // $anonfun$toJson$7:()Ljava/lang/String;
  #381 = Methodref          #2.#380       // org/scalatest/events/TestCanceled.$anonfun$toJson$7:()Ljava/lang/String;
  #382 = MethodHandle       6:#381        // REF_invokeStatic org/scalatest/events/TestCanceled.$anonfun$toJson$7:()Ljava/lang/String;
  #383 = MethodType         #65           //  ()Ljava/lang/String;
  #384 = Utf8               ()Lscala/Function0;
  #385 = NameAndType        #123:#384     // apply:()Lscala/Function0;
  #386 = InvokeDynamic      #1:#385       // #1:apply:()Lscala/Function0;
  #387 = Utf8               scala/Option
  #388 = Class              #387          // scala/Option
  #389 = Utf8               getOrElse
  #390 = Utf8               (Lscala/Function0;)Ljava/lang/Object;
  #391 = NameAndType        #389:#390     // getOrElse:(Lscala/Function0;)Ljava/lang/Object;
  #392 = Methodref          #388.#391     // scala/Option.getOrElse:(Lscala/Function0;)Ljava/lang/Object;
  #393 = Utf8               (Ljava/lang/Object;)Ljava/lang/StringBuilder;
  #394 = NameAndType        #351:#393     // append:(Ljava/lang/Object;)Ljava/lang/StringBuilder;
  #395 = Methodref          #344.#394     // java/lang/StringBuilder.append:(Ljava/lang/Object;)Ljava/lang/StringBuilder;
  #396 = Utf8               , \"testName\":
  #397 = String             #396          // , \"testName\":
  #398 = Utf8               , \"testText\":
  #399 = String             #398          // , \"testText\":
  #400 = Utf8               , \"recordedEvents\" : [
  #401 = String             #400          // , \"recordedEvents\" : [
  #402 = Utf8               $anonfun$toJson$8
  #403 = Utf8               (Lorg/scalatest/events/RecordableEvent;)Ljava/lang/String;
  #404 = NameAndType        #402:#403     // $anonfun$toJson$8:(Lorg/scalatest/events/RecordableEvent;)Ljava/lang/String;
  #405 = Methodref          #2.#404       // org/scalatest/events/TestCanceled.$anonfun$toJson$8:(Lorg/scalatest/events/RecordableEvent;)Ljava/lang/String;
  #406 = MethodHandle       6:#405        // REF_invokeStatic org/scalatest/events/TestCanceled.$anonfun$toJson$8:(Lorg/scalatest/events/RecordableEvent;)Ljava/lang/String;
  #407 = MethodType         #403          //  (Lorg/scalatest/events/RecordableEvent;)Ljava/lang/String;
  #408 = InvokeDynamic      #2:#288       // #2:apply:()Lscala/Function1;
  #409 = Utf8               scala/collection/IterableOnceOps
  #410 = Class              #409          // scala/collection/IterableOnceOps
  #411 = Utf8               ,
  #412 = String             #411          // ,
  #413 = Utf8               mkString
  #414 = NameAndType        #413:#365     // mkString:(Ljava/lang/String;)Ljava/lang/String;
  #415 = InterfaceMethodref #410.#414     // scala/collection/IterableOnceOps.mkString:(Ljava/lang/String;)Ljava/lang/String;
  #416 = Utf8               ], \"throwable\":
  #417 = String             #416          // ], \"throwable\":
  #418 = NameAndType        #299:#253     // throwableOption:(Lscala/Option;)Ljava/lang/String;
  #419 = Methodref          #22.#418      // org/scalatest/events/Event$EventJsonHelper$.throwableOption:(Lscala/Option;)Ljava/lang/String;
  #420 = Utf8               , \"formatter\":
  #421 = String             #420          // , \"formatter\":
  #422 = NameAndType        #306:#253     // formatterOption:(Lscala/Option;)Ljava/lang/String;
  #423 = Methodref          #22.#422      // org/scalatest/events/Event$EventJsonHelper$.formatterOption:(Lscala/Option;)Ljava/lang/String;
  #424 = Utf8               , \"location\":
  #425 = String             #424          // , \"location\":
  #426 = NameAndType        #312:#253     // locationOption:(Lscala/Option;)Ljava/lang/String;
  #427 = Methodref          #22.#426      // org/scalatest/events/Event$EventJsonHelper$.locationOption:(Lscala/Option;)Ljava/lang/String;
  #428 = Utf8               , \"rerunner\":
  #429 = String             #428          // , \"rerunner\":
  #430 = Utf8               , \"threadName\":
  #431 = String             #430          // , \"threadName\":
  #432 = Utf8               , \"timeStamp\":
  #433 = String             #432          // , \"timeStamp\":
  #434 = Utf8               (J)Ljava/lang/StringBuilder;
  #435 = NameAndType        #351:#434     // append:(J)Ljava/lang/StringBuilder;
  #436 = Methodref          #344.#435     // java/lang/StringBuilder.append:(J)Ljava/lang/StringBuilder;
  #437 = Utf8                }
  #438 = String             #437          //  }
  #439 = Utf8               toString
  #440 = NameAndType        #439:#65      // toString:()Ljava/lang/String;
  #441 = Methodref          #344.#440     // java/lang/StringBuilder.toString:()Ljava/lang/String;
  #442 = Utf8               augmentString
  #443 = NameAndType        #442:#365     // augmentString:(Ljava/lang/String;)Ljava/lang/String;
  #444 = Methodref          #339.#443     // scala/Predef$.augmentString:(Ljava/lang/String;)Ljava/lang/String;
  #445 = Utf8               stripMargin$extension
  #446 = NameAndType        #445:#365     // stripMargin$extension:(Ljava/lang/String;)Ljava/lang/String;
  #447 = Methodref          #334.#446     // scala/collection/StringOps$.stripMargin$extension:(Ljava/lang/String;)Ljava/lang/String;
  #448 = Utf8               withPayload
  #449 = Utf8               (Lscala/Option;)Lorg/scalatest/events/TestCanceled;
  #450 = Utf8               (Lscala/Option<Ljava/lang/Object;>;)Lorg/scalatest/events/TestCanceled;
  #451 = Utf8               newPayload
  #452 = Utf8               withThrowable
  #453 = Utf8               (Lscala/Option;)Lorg/scalatest/events/Event;
  #454 = Utf8               (Lscala/Option<Ljava/lang/Throwable;>;)Lorg/scalatest/events/Event;
  #455 = Utf8               newThrowable
  #456 = Utf8               copy$default$1
  #457 = NameAndType        #456:#137     // copy$default$1:()Lorg/scalatest/events/Ordinal;
  #458 = Methodref          #2.#457       // org/scalatest/events/TestCanceled.copy$default$1:()Lorg/scalatest/events/Ordinal;
  #459 = Utf8               copy$default$2
  #460 = NameAndType        #459:#65      // copy$default$2:()Ljava/lang/String;
  #461 = Methodref          #2.#460       // org/scalatest/events/TestCanceled.copy$default$2:()Ljava/lang/String;
  #462 = Utf8               copy$default$3
  #463 = NameAndType        #462:#65      // copy$default$3:()Ljava/lang/String;
  #464 = Methodref          #2.#463       // org/scalatest/events/TestCanceled.copy$default$3:()Ljava/lang/String;
  #465 = Utf8               copy$default$4
  #466 = NameAndType        #465:#65      // copy$default$4:()Ljava/lang/String;
  #467 = Methodref          #2.#466       // org/scalatest/events/TestCanceled.copy$default$4:()Ljava/lang/String;
  #468 = Utf8               copy$default$5
  #469 = NameAndType        #468:#69      // copy$default$5:()Lscala/Option;
  #470 = Methodref          #2.#469       // org/scalatest/events/TestCanceled.copy$default$5:()Lscala/Option;
  #471 = Utf8               copy$default$6
  #472 = NameAndType        #471:#65      // copy$default$6:()Ljava/lang/String;
  #473 = Methodref          #2.#472       // org/scalatest/events/TestCanceled.copy$default$6:()Ljava/lang/String;
  #474 = Utf8               copy$default$7
  #475 = NameAndType        #474:#65      // copy$default$7:()Ljava/lang/String;
  #476 = Methodref          #2.#475       // org/scalatest/events/TestCanceled.copy$default$7:()Ljava/lang/String;
  #477 = Utf8               copy$default$8
  #478 = NameAndType        #477:#153     // copy$default$8:()Lscala/collection/immutable/IndexedSeq;
  #479 = Methodref          #2.#478       // org/scalatest/events/TestCanceled.copy$default$8:()Lscala/collection/immutable/IndexedSeq;
  #480 = Utf8               copy$default$10
  #481 = NameAndType        #480:#69      // copy$default$10:()Lscala/Option;
  #482 = Methodref          #2.#481       // org/scalatest/events/TestCanceled.copy$default$10:()Lscala/Option;
  #483 = Utf8               copy$default$11
  #484 = NameAndType        #483:#69      // copy$default$11:()Lscala/Option;
  #485 = Methodref          #2.#484       // org/scalatest/events/TestCanceled.copy$default$11:()Lscala/Option;
  #486 = Utf8               copy$default$12
  #487 = NameAndType        #486:#69      // copy$default$12:()Lscala/Option;
  #488 = Methodref          #2.#487       // org/scalatest/events/TestCanceled.copy$default$12:()Lscala/Option;
  #489 = Utf8               copy$default$13
  #490 = NameAndType        #489:#69      // copy$default$13:()Lscala/Option;
  #491 = Methodref          #2.#490       // org/scalatest/events/TestCanceled.copy$default$13:()Lscala/Option;
  #492 = Utf8               copy$default$14
  #493 = NameAndType        #492:#69      // copy$default$14:()Lscala/Option;
  #494 = Methodref          #2.#493       // org/scalatest/events/TestCanceled.copy$default$14:()Lscala/Option;
  #495 = Utf8               copy$default$15
  #496 = NameAndType        #495:#65      // copy$default$15:()Ljava/lang/String;
  #497 = Methodref          #2.#496       // org/scalatest/events/TestCanceled.copy$default$15:()Ljava/lang/String;
  #498 = Utf8               copy$default$16
  #499 = NameAndType        #498:#55      // copy$default$16:()J
  #500 = Methodref          #2.#499       // org/scalatest/events/TestCanceled.copy$default$16:()J
  #501 = Utf8               copy
  #502 = NameAndType        #501:#124     // copy:(Lorg/scalatest/events/Ordinal;Ljava/lang/String;Ljava/lang/String;Ljava/lang/String;Lscala/Option;Ljava/lang/String;Ljava/lang/String;Lscala/collection/immutable/IndexedSeq;Lscala/Option;Lscala/Option;Lscala/Option;Lscala/Option;Lscala/Option;Lscala/Option;Ljava/lang/String;J)Lorg/scalatest/events/TestCanceled;
  #503 = Methodref          #2.#502       // org/scalatest/events/TestCanceled.copy:(Lorg/scalatest/events/Ordinal;Ljava/lang/String;Ljava/lang/String;Ljava/lang/String;Lscala/Option;Ljava/lang/String;Ljava/lang/String;Lscala/collection/immutable/IndexedSeq;Lscala/Option;Lscala/Option;Lscala/Option;Lscala/Option;Lscala/Option;Lscala/Option;Ljava/lang/String;J)Lorg/scalatest/events/TestCanceled;
  #504 = Utf8               x$1
  #505 = Utf8               x$2
  #506 = Utf8               x$3
  #507 = Utf8               x$4
  #508 = Utf8               x$5
  #509 = Utf8               x$6
  #510 = Utf8               x$7
  #511 = Utf8               x$8
  #512 = Utf8               x$9
  #513 = Utf8               x$10
  #514 = Utf8               x$11
  #515 = Utf8               x$12
  #516 = Utf8               x$13
  #517 = Utf8               x$14
  #518 = Utf8               x$15
  #519 = Utf8               x$16
  #520 = Utf8               ensureSerializable
  #521 = Utf8               ()Lorg/scalatest/events/Event;
  #522 = NameAndType        #50:#69       // payload:()Lscala/Option;
  #523 = Methodref          #2.#522       // org/scalatest/events/TestCanceled.payload:()Lscala/Option;
  #524 = Utf8               ensurePayloadSerializable
  #525 = NameAndType        #524:#453     // ensurePayloadSerializable:(Lscala/Option;)Lorg/scalatest/events/Event;
  #526 = Methodref          #2.#525       // org/scalatest/events/TestCanceled.ensurePayloadSerializable:(Lscala/Option;)Lorg/scalatest/events/Event;
  #527 = Utf8               ensureThrowableSerializable
  #528 = NameAndType        #527:#453     // ensureThrowableSerializable:(Lscala/Option;)Lorg/scalatest/events/Event;
  #529 = Methodref          #4.#528       // org/scalatest/events/Event.ensureThrowableSerializable:(Lscala/Option;)Lorg/scalatest/events/Event;
  #530 = Utf8               (Lorg/scalatest/events/Ordinal;Ljava/lang/String;Ljava/lang/String;Ljava/lang/String;Lscala/Option;Ljava/lang/String;Ljava/lang/String;Lscala/collection/immutable/IndexedSeq;Lscala/Option;Lscala/Option;Lscala/Option;Lscala/Option;Lscala/Option;Lscala/Option;Ljava/lang/String;J)V
  #531 = NameAndType        #196:#530     // "<init>":(Lorg/scalatest/events/Ordinal;Ljava/lang/String;Ljava/lang/String;Ljava/lang/String;Lscala/Option;Ljava/lang/String;Ljava/lang/String;Lscala/collection/immutable/IndexedSeq;Lscala/Option;Lscala/Option;Lscala/Option;Lscala/Option;Lscala/Option;Lscala/Option;Ljava/lang/String;J)V
  #532 = Methodref          #2.#531       // org/scalatest/events/TestCanceled."<init>":(Lorg/scalatest/events/Ordinal;Ljava/lang/String;Ljava/lang/String;Ljava/lang/String;Lscala/Option;Ljava/lang/String;Ljava/lang/String;Lscala/collection/immutable/IndexedSeq;Lscala/Option;Lscala/Option;Lscala/Option;Lscala/Option;Lscala/Option;Lscala/Option;Ljava/lang/String;J)V
  #533 = Utf8               copy$default$9
  #534 = Utf8               productPrefix
  #535 = Utf8               productArity
  #536 = Utf8               productElement
  #537 = Utf8               (I)Ljava/lang/Object;
  #538 = Utf8               scala/runtime/Statics
  #539 = Class              #538          // scala/runtime/Statics
  #540 = Utf8               ioobe
  #541 = NameAndType        #540:#537     // ioobe:(I)Ljava/lang/Object;
  #542 = Methodref          #539.#541     // scala/runtime/Statics.ioobe:(I)Ljava/lang/Object;
  #543 = Utf8               I
  #544 = Utf8               java/lang/Object
  #545 = Class              #544          // java/lang/Object
  #546 = Utf8               productIterator
  #547 = Utf8               ()Lscala/collection/Iterator;
  #548 = Utf8               ()Lscala/collection/Iterator<Ljava/lang/Object;>;
  #549 = Utf8               scala/runtime/ScalaRunTime$
  #550 = Class              #549          // scala/runtime/ScalaRunTime$
  #551 = Utf8               Lscala/runtime/ScalaRunTime$;
  #552 = NameAndType        #58:#551      // MODULE$:Lscala/runtime/ScalaRunTime$;
  #553 = Fieldref           #550.#552     // scala/runtime/ScalaRunTime$.MODULE$:Lscala/runtime/ScalaRunTime$;
  #554 = Utf8               typedProductIterator
  #555 = Utf8               (Lscala/Product;)Lscala/collection/Iterator;
  #556 = NameAndType        #554:#555     // typedProductIterator:(Lscala/Product;)Lscala/collection/Iterator;
  #557 = Methodref          #550.#556     // scala/runtime/ScalaRunTime$.typedProductIterator:(Lscala/Product;)Lscala/collection/Iterator;
  #558 = Utf8               canEqual
  #559 = Utf8               (Ljava/lang/Object;)Z
  #560 = Utf8               Ljava/lang/Object;
  #561 = Utf8               productElementName
  #562 = Utf8               (I)Ljava/lang/String;
  #563 = String             #50           // payload
  #564 = Utf8               java/lang/String
  #565 = Class              #564          // java/lang/String
  #566 = Utf8               hashCode
  #567 = Integer            -889275714
  #568 = NameAndType        #534:#65      // productPrefix:()Ljava/lang/String;
  #569 = Methodref          #2.#568       // org/scalatest/events/TestCanceled.productPrefix:()Ljava/lang/String;
  #570 = NameAndType        #566:#220     // hashCode:()I
  #571 = Methodref          #565.#570     // java/lang/String.hashCode:()I
  #572 = Utf8               mix
  #573 = Utf8               (II)I
  #574 = NameAndType        #572:#573     // mix:(II)I
  #575 = Methodref          #539.#574     // scala/runtime/Statics.mix:(II)I
  #576 = Utf8               anyHash
  #577 = Utf8               (Ljava/lang/Object;)I
  #578 = NameAndType        #576:#577     // anyHash:(Ljava/lang/Object;)I
  #579 = Methodref          #539.#578     // scala/runtime/Statics.anyHash:(Ljava/lang/Object;)I
  #580 = Utf8               longHash
  #581 = Utf8               (J)I
  #582 = NameAndType        #580:#581     // longHash:(J)I
  #583 = Methodref          #539.#582     // scala/runtime/Statics.longHash:(J)I
  #584 = Utf8               finalizeHash
  #585 = NameAndType        #584:#573     // finalizeHash:(II)I
  #586 = Methodref          #539.#585     // scala/runtime/Statics.finalizeHash:(II)I
  #587 = Utf8               _toString
  #588 = Utf8               (Lscala/Product;)Ljava/lang/String;
  #589 = NameAndType        #587:#588     // _toString:(Lscala/Product;)Ljava/lang/String;
  #590 = Methodref          #550.#589     // scala/runtime/ScalaRunTime$._toString:(Lscala/Product;)Ljava/lang/String;
  #591 = Utf8               equals
  #592 = NameAndType        #591:#559     // equals:(Ljava/lang/Object;)Z
  #593 = Methodref          #545.#592     // java/lang/Object.equals:(Ljava/lang/Object;)Z
  #594 = NameAndType        #448:#449     // withPayload:(Lscala/Option;)Lorg/scalatest/events/TestCanceled;
  #595 = Methodref          #2.#594       // org/scalatest/events/TestCanceled.withPayload:(Lscala/Option;)Lorg/scalatest/events/TestCanceled;
  #596 = NameAndType        #173:#174     // toXml:()Lscala/xml/Elem;
  #597 = Methodref          #4.#596       // org/scalatest/events/Event.toXml:()Lscala/xml/Elem;
  #598 = Utf8               Lorg/scalatest/events/RecordableEvent;
  #599 = Utf8               null
  #600 = String             #599          // null
  #601 = NameAndType        #332:#65      // toJson:()Ljava/lang/String;
  #602 = Methodref          #4.#601       // org/scalatest/events/Event.toJson:()Ljava/lang/String;
  #603 = Utf8               (Lorg/scalatest/events/Ordinal;Ljava/lang/String;Ljava/lang/String;Ljava/lang/String;Lscala/Option<Ljava/lang/String;>;Ljava/lang/String;Ljava/lang/String;Lscala/collection/immutable/IndexedSeq<Lorg/scalatest/events/RecordableEvent;>;Lscala/Option<Ljava/lang/Throwable;>;Lscala/Option<Ljava/lang/Object;>;Lscala/Option<Lorg/scalatest/events/Formatter;>;Lscala/Option<Lorg/scalatest/events/Location;>;Lscala/Option<Ljava/lang/String;>;Lscala/Option<Ljava/lang/Object;>;Ljava/lang/String;J)V
  #604 = Methodref          #4.#198       // org/scalatest/events/Event."<init>":()V
  #605 = Utf8               org/scalactic/Requirements$
  #606 = Class              #605          // org/scalactic/Requirements$
  #607 = Utf8               Lorg/scalactic/Requirements$;
  #608 = NameAndType        #58:#607      // MODULE$:Lorg/scalactic/Requirements$;
  #609 = Fieldref           #606.#608     // org/scalactic/Requirements$.MODULE$:Lorg/scalactic/Requirements$;
  #610 = Utf8               requirementsHelper
  #611 = Utf8               ()Lorg/scalactic/Requirements$RequirementsHelper;
  #612 = NameAndType        #610:#611     // requirementsHelper:()Lorg/scalactic/Requirements$RequirementsHelper;
  #613 = Methodref          #606.#612     // org/scalactic/Requirements$.requirementsHelper:()Lorg/scalactic/Requirements$RequirementsHelper;
  #614 = Utf8               TestCanceled.this.ordinal
  #615 = String             #614          // TestCanceled.this.ordinal
  #616 = Utf8               TestCanceled.this.message
  #617 = String             #616          // TestCanceled.this.message
  #618 = Utf8               TestCanceled.this.suiteName
  #619 = String             #618          // TestCanceled.this.suiteName
  #620 = Utf8               TestCanceled.this.suiteId
  #621 = String             #620          // TestCanceled.this.suiteId
  #622 = Utf8               TestCanceled.this.suiteClassName
  #623 = String             #622          // TestCanceled.this.suiteClassName
  #624 = Utf8               TestCanceled.this.testName
  #625 = String             #624          // TestCanceled.this.testName
  #626 = Utf8               TestCanceled.this.testText
  #627 = String             #626          // TestCanceled.this.testText
  #628 = Utf8               TestCanceled.this.duration
  #629 = String             #628          // TestCanceled.this.duration
  #630 = Utf8               TestCanceled.this.throwable
  #631 = String             #630          // TestCanceled.this.throwable
  #632 = Utf8               TestCanceled.this.formatter
  #633 = String             #632          // TestCanceled.this.formatter
  #634 = Utf8               TestCanceled.this.location
  #635 = String             #634          // TestCanceled.this.location
  #636 = Utf8               TestCanceled.this.rerunner
  #637 = String             #636          // TestCanceled.this.rerunner
  #638 = Utf8               TestCanceled.this.payload
  #639 = String             #638          // TestCanceled.this.payload
  #640 = Utf8               TestCanceled.this.threadName
  #641 = String             #640          // TestCanceled.this.threadName
  #642 = Utf8               [Ljava/lang/Object;
  #643 = Class              #642          // "[Ljava/lang/Object;"
  #644 = Utf8               [Ljava/lang/String;
  #645 = Class              #644          // "[Ljava/lang/String;"
  #646 = Utf8               org/scalactic/Prettifier$
  #647 = Class              #646          // org/scalactic/Prettifier$
  #648 = Utf8               Lorg/scalactic/Prettifier$;
  #649 = NameAndType        #58:#648      // MODULE$:Lorg/scalactic/Prettifier$;
  #650 = Fieldref           #647.#649     // org/scalactic/Prettifier$.MODULE$:Lorg/scalactic/Prettifier$;
  #651 = Utf8               default
  #652 = Utf8               ()Lorg/scalactic/Prettifier;
  #653 = NameAndType        #651:#652     // default:()Lorg/scalactic/Prettifier;
  #654 = Methodref          #647.#653     // org/scalactic/Prettifier$.default:()Lorg/scalactic/Prettifier;
  #655 = Utf8               org/scalactic/source/Position
  #656 = Class              #655          // org/scalactic/source/Position
  #657 = String             #7            // Event.scala
  #658 = Utf8               Please set the environment variable SCALACTIC_FILL_FILE_PATHNAMES to yes at compile time to enable this feature.
  #659 = String             #658          // Please set the environment variable SCALACTIC_FILL_FILE_PATHNAMES to yes at compile time to enable this feature.
  #660 = Utf8               (Ljava/lang/String;Ljava/lang/String;I)V
  #661 = NameAndType        #196:#660     // "<init>":(Ljava/lang/String;Ljava/lang/String;I)V
  #662 = Methodref          #656.#661     // org/scalactic/source/Position."<init>":(Ljava/lang/String;Ljava/lang/String;I)V
  #663 = Utf8               macroRequireNonNull
  #664 = Utf8               ([Ljava/lang/String;[Ljava/lang/Object;Lorg/scalactic/Prettifier;Lorg/scalactic/source/Position;)V
  #665 = NameAndType        #663:#664     // macroRequireNonNull:([Ljava/lang/String;[Ljava/lang/Object;Lorg/scalactic/Prettifier;Lorg/scalactic/source/Position;)V
  #666 = Methodref          #17.#665      // org/scalactic/Requirements$RequirementsHelper.macroRequireNonNull:([Ljava/lang/String;[Ljava/lang/Object;Lorg/scalactic/Prettifier;Lorg/scalactic/source/Position;)V
  #667 = Utf8               $deserializeLambda$
  #668 = Utf8               (Ljava/lang/invoke/SerializedLambda;)Ljava/lang/Object;
  #669 = Utf8               scala/runtime/LambdaDeserialize
  #670 = Class              #669          // scala/runtime/LambdaDeserialize
  #671 = Utf8               bootstrap
  #672 = Utf8               (Ljava/lang/invoke/MethodHandles$Lookup;Ljava/lang/String;Ljava/lang/invoke/MethodType;[Ljava/lang/invoke/MethodHandle;)Ljava/lang/invoke/CallSite;
  #673 = NameAndType        #671:#672     // bootstrap:(Ljava/lang/invoke/MethodHandles$Lookup;Ljava/lang/String;Ljava/lang/invoke/MethodType;[Ljava/lang/invoke/MethodHandle;)Ljava/lang/invoke/CallSite;
  #674 = Methodref          #670.#673     // scala/runtime/LambdaDeserialize.bootstrap:(Ljava/lang/invoke/MethodHandles$Lookup;Ljava/lang/String;Ljava/lang/invoke/MethodType;[Ljava/lang/invoke/MethodHandle;)Ljava/lang/invoke/CallSite;
  #675 = MethodHandle       6:#674        // REF_invokeStatic scala/runtime/LambdaDeserialize.bootstrap:(Ljava/lang/invoke/MethodHandles$Lookup;Ljava/lang/String;Ljava/lang/invoke/MethodType;[Ljava/lang/invoke/MethodHandle;)Ljava/lang/invoke/CallSite;
  #676 = Utf8               lambdaDeserialize
  #677 = NameAndType        #676:#668     // lambdaDeserialize:(Ljava/lang/invoke/SerializedLambda;)Ljava/lang/Object;
  #678 = InvokeDynamic      #3:#677       // #3:lambdaDeserialize:(Ljava/lang/invoke/SerializedLambda;)Ljava/lang/Object;
  #679 = Utf8               Signature
  #680 = Utf8               Code
  #681 = Utf8               LocalVariableTable
  #682 = Utf8               MethodParameters
  #683 = Utf8               LineNumberTable
  #684 = Utf8               StackMapTable
  #685 = Utf8               InnerClasses
  #686 = Utf8               SourceFile
  #687 = Utf8               RuntimeVisibleAnnotations
  #688 = Utf8               BootstrapMethods
  #689 = Utf8               ScalaInlineInfo
  #690 = Utf8               ScalaSig
{
  private final org.scalatest.events.Ordinal ordinal;
    descriptor: Lorg/scalatest/events/Ordinal;
    flags: (0x0012) ACC_PRIVATE, ACC_FINAL

  private final java.lang.String message;
    descriptor: Ljava/lang/String;
    flags: (0x0012) ACC_PRIVATE, ACC_FINAL

  private final java.lang.String suiteName;
    descriptor: Ljava/lang/String;
    flags: (0x0012) ACC_PRIVATE, ACC_FINAL

  private final java.lang.String suiteId;
    descriptor: Ljava/lang/String;
    flags: (0x0012) ACC_PRIVATE, ACC_FINAL

  private final scala.Option<java.lang.String> suiteClassName;
    descriptor: Lscala/Option;
    flags: (0x0012) ACC_PRIVATE, ACC_FINAL
    Signature: #35                          // Lscala/Option<Ljava/lang/String;>;

  private final java.lang.String testName;
    descriptor: Ljava/lang/String;
    flags: (0x0012) ACC_PRIVATE, ACC_FINAL

  private final java.lang.String testText;
    descriptor: Ljava/lang/String;
    flags: (0x0012) ACC_PRIVATE, ACC_FINAL

  private final scala.collection.immutable.IndexedSeq<org.scalatest.events.RecordableEvent> recordedEvents;
    descriptor: Lscala/collection/immutable/IndexedSeq;
    flags: (0x0012) ACC_PRIVATE, ACC_FINAL
    Signature: #40                          // Lscala/collection/immutable/IndexedSeq<Lorg/scalatest/events/RecordableEvent;>;

  private final scala.Option<java.lang.Throwable> throwable;
    descriptor: Lscala/Option;
    flags: (0x0012) ACC_PRIVATE, ACC_FINAL
    Signature: #42                          // Lscala/Option<Ljava/lang/Throwable;>;

  private final scala.Option<java.lang.Object> duration;
    descriptor: Lscala/Option;
    flags: (0x0012) ACC_PRIVATE, ACC_FINAL
    Signature: #44                          // Lscala/Option<Ljava/lang/Object;>;

  private final scala.Option<org.scalatest.events.Formatter> formatter;
    descriptor: Lscala/Option;
    flags: (0x0012) ACC_PRIVATE, ACC_FINAL
    Signature: #46                          // Lscala/Option<Lorg/scalatest/events/Formatter;>;

  private final scala.Option<org.scalatest.events.Location> location;
    descriptor: Lscala/Option;
    flags: (0x0012) ACC_PRIVATE, ACC_FINAL
    Signature: #48                          // Lscala/Option<Lorg/scalatest/events/Location;>;

  private final scala.Option<java.lang.String> rerunner;
    descriptor: Lscala/Option;
    flags: (0x0012) ACC_PRIVATE, ACC_FINAL
    Signature: #35                          // Lscala/Option<Ljava/lang/String;>;

  private final scala.Option<java.lang.Object> payload;
    descriptor: Lscala/Option;
    flags: (0x0012) ACC_PRIVATE, ACC_FINAL
    Signature: #44                          // Lscala/Option<Ljava/lang/Object;>;

  private final java.lang.String threadName;
    descriptor: Ljava/lang/String;
    flags: (0x0012) ACC_PRIVATE, ACC_FINAL

  private final long timeStamp;
    descriptor: J
    flags: (0x0012) ACC_PRIVATE, ACC_FINAL

  public static long $lessinit$greater$default$16();
    descriptor: ()J
    flags: (0x0009) ACC_PUBLIC, ACC_STATIC
    Code:
      stack=2, locals=0, args_size=0
         0: getstatic     #61                 // Field org/scalatest/events/TestCanceled$.MODULE$:Lorg/scalatest/events/TestCanceled$;
         3: invokevirtual #63                 // Method org/scalatest/events/TestCanceled$.$lessinit$greater$default$16:()J
         6: lreturn

  public static java.lang.String $lessinit$greater$default$15();
    descriptor: ()Ljava/lang/String;
    flags: (0x0009) ACC_PUBLIC, ACC_STATIC
    Code:
      stack=1, locals=0, args_size=0
         0: getstatic     #61                 // Field org/scalatest/events/TestCanceled$.MODULE$:Lorg/scalatest/events/TestCanceled$;
         3: invokevirtual #67                 // Method org/scalatest/events/TestCanceled$.$lessinit$greater$default$15:()Ljava/lang/String;
         6: areturn

  public static scala.Option<java.lang.Object> $lessinit$greater$default$14();
    descriptor: ()Lscala/Option;
    flags: (0x0009) ACC_PUBLIC, ACC_STATIC
    Code:
      stack=1, locals=0, args_size=0
         0: getstatic     #61                 // Field org/scalatest/events/TestCanceled$.MODULE$:Lorg/scalatest/events/TestCanceled$;
         3: invokevirtual #72                 // Method org/scalatest/events/TestCanceled$.$lessinit$greater$default$14:()Lscala/Option;
         6: areturn
    Signature: #70                          // ()Lscala/Option<Ljava/lang/Object;>;

  public static scala.Option<java.lang.String> $lessinit$greater$default$13();
    descriptor: ()Lscala/Option;
    flags: (0x0009) ACC_PUBLIC, ACC_STATIC
    Code:
      stack=1, locals=0, args_size=0
         0: getstatic     #61                 // Field org/scalatest/events/TestCanceled$.MODULE$:Lorg/scalatest/events/TestCanceled$;
         3: invokevirtual #76                 // Method org/scalatest/events/TestCanceled$.$lessinit$greater$default$13:()Lscala/Option;
         6: areturn
    Signature: #74                          // ()Lscala/Option<Ljava/lang/String;>;

  public static scala.Option<org.scalatest.events.Location> $lessinit$greater$default$12();
    descriptor: ()Lscala/Option;
    flags: (0x0009) ACC_PUBLIC, ACC_STATIC
    Code:
      stack=1, locals=0, args_size=0
         0: getstatic     #61                 // Field org/scalatest/events/TestCanceled$.MODULE$:Lorg/scalatest/events/TestCanceled$;
         3: invokevirtual #80                 // Method org/scalatest/events/TestCanceled$.$lessinit$greater$default$12:()Lscala/Option;
         6: areturn
    Signature: #78                          // ()Lscala/Option<Lorg/scalatest/events/Location;>;

  public static scala.Option<org.scalatest.events.Formatter> $lessinit$greater$default$11();
    descriptor: ()Lscala/Option;
    flags: (0x0009) ACC_PUBLIC, ACC_STATIC
    Code:
      stack=1, locals=0, args_size=0
         0: getstatic     #61                 // Field org/scalatest/events/TestCanceled$.MODULE$:Lorg/scalatest/events/TestCanceled$;
         3: invokevirtual #84                 // Method org/scalatest/events/TestCanceled$.$lessinit$greater$default$11:()Lscala/Option;
         6: areturn
    Signature: #82                          // ()Lscala/Option<Lorg/scalatest/events/Formatter;>;

  public static scala.Option<java.lang.Object> $lessinit$greater$default$10();
    descriptor: ()Lscala/Option;
    flags: (0x0009) ACC_PUBLIC, ACC_STATIC
    Code:
      stack=1, locals=0, args_size=0
         0: getstatic     #61                 // Field org/scalatest/events/TestCanceled$.MODULE$:Lorg/scalatest/events/TestCanceled$;
         3: invokevirtual #87                 // Method org/scalatest/events/TestCanceled$.$lessinit$greater$default$10:()Lscala/Option;
         6: areturn
    Signature: #70                          // ()Lscala/Option<Ljava/lang/Object;>;

  public static scala.Option<java.lang.Throwable> $lessinit$greater$default$9();
    descriptor: ()Lscala/Option;
    flags: (0x0009) ACC_PUBLIC, ACC_STATIC
    Code:
      stack=1, locals=0, args_size=0
         0: getstatic     #61                 // Field org/scalatest/events/TestCanceled$.MODULE$:Lorg/scalatest/events/TestCanceled$;
         3: invokevirtual #91                 // Method org/scalatest/events/TestCanceled$.$lessinit$greater$default$9:()Lscala/Option;
         6: areturn
    Signature: #89                          // ()Lscala/Option<Ljava/lang/Throwable;>;

  public static scala.Option<scala.Tuple16<org.scalatest.events.Ordinal, java.lang.String, java.lang.String, java.lang.String, scala.Option<java.lang.String>, java.lang.String, java.lang.String, scala.collection.immutable.IndexedSeq<org.scalatest.events.RecordableEvent>, scala.Option<java.lang.Throwable>, scala.Option<java.lang.Object>, scala.Option<org.scalatest.events.Formatter>, scala.Option<org.scalatest.events.Location>, scala.Option<java.lang.String>, scala.Option<java.lang.Object>, java.lang.String, java.lang.Object>> unapply(org.scalatest.events.TestCanceled);
    descriptor: (Lorg/scalatest/events/TestCanceled;)Lscala/Option;
    flags: (0x0009) ACC_PUBLIC, ACC_STATIC
    Code:
      stack=2, locals=1, args_size=1
         0: getstatic     #61                 // Field org/scalatest/events/TestCanceled$.MODULE$:Lorg/scalatest/events/TestCanceled$;
         3: aload_0
         4: invokevirtual #97                 // Method org/scalatest/events/TestCanceled$.unapply:(Lorg/scalatest/events/TestCanceled;)Lscala/Option;
         7: areturn
      LocalVariableTable:
        Start  Length  Slot  Name   Signature
            0       8     0   x$0   Lorg/scalatest/events/TestCanceled;
    Signature: #94                          // (Lorg/scalatest/events/TestCanceled;)Lscala/Option<Lscala/Tuple16<Lorg/scalatest/events/Ordinal;Ljava/lang/String;Ljava/lang/String;Ljava/lang/String;Lscala/Option<Ljava/lang/String;>;Ljava/lang/String;Ljava/lang/String;Lscala/collection/immutable/IndexedSeq<Lorg/scalatest/events/RecordableEvent;>;Lscala/Option<Ljava/lang/Throwable;>;Lscala/Option<Ljava/lang/Object;>;Lscala/Option<Lorg/scalatest/events/Formatter;>;Lscala/Option<Lorg/scalatest/events/Location;>;Lscala/Option<Ljava/lang/String;>;Lscala/Option<Ljava/lang/Object;>;Ljava/lang/String;Ljava/lang/Object;>;>;
    MethodParameters:
      Name                           Flags
      x$0                            final

  public static long apply$default$16();
    descriptor: ()J
    flags: (0x0009) ACC_PUBLIC, ACC_STATIC
    Code:
      stack=2, locals=0, args_size=0
         0: getstatic     #61                 // Field org/scalatest/events/TestCanceled$.MODULE$:Lorg/scalatest/events/TestCanceled$;
         3: invokevirtual #101                // Method org/scalatest/events/TestCanceled$.apply$default$16:()J
         6: lreturn

  public static java.lang.String apply$default$15();
    descriptor: ()Ljava/lang/String;
    flags: (0x0009) ACC_PUBLIC, ACC_STATIC
    Code:
      stack=1, locals=0, args_size=0
         0: getstatic     #61                 // Field org/scalatest/events/TestCanceled$.MODULE$:Lorg/scalatest/events/TestCanceled$;
         3: invokevirtual #104                // Method org/scalatest/events/TestCanceled$.apply$default$15:()Ljava/lang/String;
         6: areturn

  public static scala.Option<java.lang.Object> apply$default$14();
    descriptor: ()Lscala/Option;
    flags: (0x0009) ACC_PUBLIC, ACC_STATIC
    Code:
      stack=1, locals=0, args_size=0
         0: getstatic     #61                 // Field org/scalatest/events/TestCanceled$.MODULE$:Lorg/scalatest/events/TestCanceled$;
         3: invokevirtual #107                // Method org/scalatest/events/TestCanceled$.apply$default$14:()Lscala/Option;
         6: areturn
    Signature: #70                          // ()Lscala/Option<Ljava/lang/Object;>;

  public static scala.Option<java.lang.String> apply$default$13();
    descriptor: ()Lscala/Option;
    flags: (0x0009) ACC_PUBLIC, ACC_STATIC
    Code:
      stack=1, locals=0, args_size=0
         0: getstatic     #61                 // Field org/scalatest/events/TestCanceled$.MODULE$:Lorg/scalatest/events/TestCanceled$;
         3: invokevirtual #110                // Method org/scalatest/events/TestCanceled$.apply$default$13:()Lscala/Option;
         6: areturn
    Signature: #74                          // ()Lscala/Option<Ljava/lang/String;>;

  public static scala.Option<org.scalatest.events.Location> apply$default$12();
    descriptor: ()Lscala/Option;
    flags: (0x0009) ACC_PUBLIC, ACC_STATIC
    Code:
      stack=1, locals=0, args_size=0
         0: getstatic     #61                 // Field org/scalatest/events/TestCanceled$.MODULE$:Lorg/scalatest/events/TestCanceled$;
         3: invokevirtual #113                // Method org/scalatest/events/TestCanceled$.apply$default$12:()Lscala/Option;
         6: areturn
    Signature: #78                          // ()Lscala/Option<Lorg/scalatest/events/Location;>;

  public static scala.Option<org.scalatest.events.Formatter> apply$default$11();
    descriptor: ()Lscala/Option;
    flags: (0x0009) ACC_PUBLIC, ACC_STATIC
    Code:
      stack=1, locals=0, args_size=0
         0: getstatic     #61                 // Field org/scalatest/events/TestCanceled$.MODULE$:Lorg/scalatest/events/TestCanceled$;
         3: invokevirtual #116                // Method org/scalatest/events/TestCanceled$.apply$default$11:()Lscala/Option;
         6: areturn
    Signature: #82                          // ()Lscala/Option<Lorg/scalatest/events/Formatter;>;

  public static scala.Option<java.lang.Object> apply$default$10();
    descriptor: ()Lscala/Option;
    flags: (0x0009) ACC_PUBLIC, ACC_STATIC
    Code:
      stack=1, locals=0, args_size=0
         0: getstatic     #61                 // Field org/scalatest/events/TestCanceled$.MODULE$:Lorg/scalatest/events/TestCanceled$;
         3: invokevirtual #119                // Method org/scalatest/events/TestCanceled$.apply$default$10:()Lscala/Option;
         6: areturn
    Signature: #70                          // ()Lscala/Option<Ljava/lang/Object;>;

  public static scala.Option<java.lang.Throwable> apply$default$9();
    descriptor: ()Lscala/Option;
    flags: (0x0009) ACC_PUBLIC, ACC_STATIC
    Code:
      stack=1, locals=0, args_size=0
         0: getstatic     #61                 // Field org/scalatest/events/TestCanceled$.MODULE$:Lorg/scalatest/events/TestCanceled$;
         3: invokevirtual #122                // Method org/scalatest/events/TestCanceled$.apply$default$9:()Lscala/Option;
         6: areturn
    Signature: #89                          // ()Lscala/Option<Ljava/lang/Throwable;>;

  public static org.scalatest.events.TestCanceled apply(org.scalatest.events.Ordinal, java.lang.String, java.lang.String, java.lang.String, scala.Option<java.lang.String>, java.lang.String, java.lang.String, scala.collection.immutable.IndexedSeq<org.scalatest.events.RecordableEvent>, scala.Option<java.lang.Throwable>, scala.Option<java.lang.Object>, scala.Option<org.scalatest.events.Formatter>, scala.Option<org.scalatest.events.Location>, scala.Option<java.lang.String>, scala.Option<java.lang.Object>, java.lang.String, long);
    descriptor: (Lorg/scalatest/events/Ordinal;Ljava/lang/String;Ljava/lang/String;Ljava/lang/String;Lscala/Option;Ljava/lang/String;Ljava/lang/String;Lscala/collection/immutable/IndexedSeq;Lscala/Option;Lscala/Option;Lscala/Option;Lscala/Option;Lscala/Option;Lscala/Option;Ljava/lang/String;J)Lorg/scalatest/events/TestCanceled;
    flags: (0x0009) ACC_PUBLIC, ACC_STATIC
    Code:
      stack=18, locals=17, args_size=16
         0: getstatic     #61                 // Field org/scalatest/events/TestCanceled$.MODULE$:Lorg/scalatest/events/TestCanceled$;
         3: aload_0
         4: aload_1
         5: aload_2
         6: aload_3
         7: aload         4
         9: aload         5
        11: aload         6
        13: aload         7
        15: aload         8
        17: aload         9
        19: aload         10
        21: aload         11
        23: aload         12
        25: aload         13
        27: aload         14
        29: lload         15
        31: invokevirtual #127                // Method org/scalatest/events/TestCanceled$.apply:(Lorg/scalatest/events/Ordinal;Ljava/lang/String;Ljava/lang/String;Ljava/lang/String;Lscala/Option;Ljava/lang/String;Ljava/lang/String;Lscala/collection/immutable/IndexedSeq;Lscala/Option;Lscala/Option;Lscala/Option;Lscala/Option;Lscala/Option;Lscala/Option;Ljava/lang/String;J)Lorg/scalatest/events/TestCanceled;
        34: areturn
      LocalVariableTable:
        Start  Length  Slot  Name   Signature
            0      35     0 ordinal   Lorg/scalatest/events/Ordinal;
            0      35     1 message   Ljava/lang/String;
            0      35     2 suiteName   Ljava/lang/String;
            0      35     3 suiteId   Ljava/lang/String;
            0      35     4 suiteClassName   Lscala/Option;
            0      35     5 testName   Ljava/lang/String;
            0      35     6 testText   Ljava/lang/String;
            0      35     7 recordedEvents   Lscala/collection/immutable/IndexedSeq;
            0      35     8 throwable   Lscala/Option;
            0      35     9 duration   Lscala/Option;
            0      35    10 formatter   Lscala/Option;
            0      35    11 location   Lscala/Option;
            0      35    12 rerunner   Lscala/Option;
            0      35    13 payload   Lscala/Option;
            0      35    14 threadName   Ljava/lang/String;
            0      35    15 timeStamp   J
    Signature: #125                         // (Lorg/scalatest/events/Ordinal;Ljava/lang/String;Ljava/lang/String;Ljava/lang/String;Lscala/Option<Ljava/lang/String;>;Ljava/lang/String;Ljava/lang/String;Lscala/collection/immutable/IndexedSeq<Lorg/scalatest/events/RecordableEvent;>;Lscala/Option<Ljava/lang/Throwable;>;Lscala/Option<Ljava/lang/Object;>;Lscala/Option<Lorg/scalatest/events/Formatter;>;Lscala/Option<Lorg/scalatest/events/Location;>;Lscala/Option<Ljava/lang/String;>;Lscala/Option<Ljava/lang/Object;>;Ljava/lang/String;J)Lorg/scalatest/events/TestCanceled;
    MethodParameters:
      Name                           Flags
      ordinal                        final
      message                        final
      suiteName                      final
      suiteId                        final
      suiteClassName                 final
      testName                       final
      testText                       final
      recordedEvents                 final
      throwable                      final
      duration                       final
      formatter                      final
      location                       final
      rerunner                       final
      payload                        final
      threadName                     final
      timeStamp                      final

  public static scala.Function1<scala.Tuple16<org.scalatest.events.Ordinal, java.lang.String, java.lang.String, java.lang.String, scala.Option<java.lang.String>, java.lang.String, java.lang.String, scala.collection.immutable.IndexedSeq<org.scalatest.events.RecordableEvent>, scala.Option<java.lang.Throwable>, scala.Option<java.lang.Object>, scala.Option<org.scalatest.events.Formatter>, scala.Option<org.scalatest.events.Location>, scala.Option<java.lang.String>, scala.Option<java.lang.Object>, java.lang.String, java.lang.Object>, org.scalatest.events.TestCanceled> tupled();
    descriptor: ()Lscala/Function1;
    flags: (0x0009) ACC_PUBLIC, ACC_STATIC
    Code:
      stack=1, locals=0, args_size=0
         0: getstatic     #61                 // Field org/scalatest/events/TestCanceled$.MODULE$:Lorg/scalatest/events/TestCanceled$;
         3: invokevirtual #132                // Method org/scalatest/events/TestCanceled$.tupled:()Lscala/Function1;
         6: areturn
    Signature: #130                         // ()Lscala/Function1<Lscala/Tuple16<Lorg/scalatest/events/Ordinal;Ljava/lang/String;Ljava/lang/String;Ljava/lang/String;Lscala/Option<Ljava/lang/String;>;Ljava/lang/String;Ljava/lang/String;Lscala/collection/immutable/IndexedSeq<Lorg/scalatest/events/RecordableEvent;>;Lscala/Option<Ljava/lang/Throwable;>;Lscala/Option<Ljava/lang/Object;>;Lscala/Option<Lorg/scalatest/events/Formatter;>;Lscala/Option<Lorg/scalatest/events/Location;>;Lscala/Option<Ljava/lang/String;>;Lscala/Option<Ljava/lang/Object;>;Ljava/lang/String;Ljava/lang/Object;>;Lorg/scalatest/events/TestCanceled;>;

  public static scala.Function1<org.scalatest.events.Ordinal, scala.Function1<java.lang.String, scala.Function1<java.lang.String, scala.Function1<java.lang.String, scala.Function1<scala.Option<java.lang.String>, scala.Function1<java.lang.String, scala.Function1<java.lang.String, scala.Function1<scala.collection.immutable.IndexedSeq<org.scalatest.events.RecordableEvent>, scala.Function1<scala.Option<java.lang.Throwable>, scala.Function1<scala.Option<java.lang.Object>, scala.Function1<scala.Option<org.scalatest.events.Formatter>, scala.Function1<scala.Option<org.scalatest.events.Location>, scala.Function1<scala.Option<java.lang.String>, scala.Function1<scala.Option<java.lang.Object>, scala.Function1<java.lang.String, scala.Function1<java.lang.Object, org.scalatest.events.TestCanceled>>>>>>>>>>>>>>>> curried();
    descriptor: ()Lscala/Function1;
    flags: (0x0009) ACC_PUBLIC, ACC_STATIC
    Code:
      stack=1, locals=0, args_size=0
         0: getstatic     #61                 // Field org/scalatest/events/TestCanceled$.MODULE$:Lorg/scalatest/events/TestCanceled$;
         3: invokevirtual #136                // Method org/scalatest/events/TestCanceled$.curried:()Lscala/Function1;
         6: areturn
    Signature: #134                         // ()Lscala/Function1<Lorg/scalatest/events/Ordinal;Lscala/Function1<Ljava/lang/String;Lscala/Function1<Ljava/lang/String;Lscala/Function1<Ljava/lang/String;Lscala/Function1<Lscala/Option<Ljava/lang/String;>;Lscala/Function1<Ljava/lang/String;Lscala/Function1<Ljava/lang/String;Lscala/Function1<Lscala/collection/immutable/IndexedSeq<Lorg/scalatest/events/RecordableEvent;>;Lscala/Function1<Lscala/Option<Ljava/lang/Throwable;>;Lscala/Function1<Lscala/Option<Ljava/lang/Object;>;Lscala/Function1<Lscala/Option<Lorg/scalatest/events/Formatter;>;Lscala/Function1<Lscala/Option<Lorg/scalatest/events/Location;>;Lscala/Function1<Lscala/Option<Ljava/lang/String;>;Lscala/Function1<Lscala/Option<Ljava/lang/Object;>;Lscala/Function1<Ljava/lang/String;Lscala/Function1<Ljava/lang/Object;Lorg/scalatest/events/TestCanceled;>;>;>;>;>;>;>;>;>;>;>;>;>;>;>;>;

  public org.scalatest.events.Ordinal ordinal();
    descriptor: ()Lorg/scalatest/events/Ordinal;
    flags: (0x0001) ACC_PUBLIC
    Code:
      stack=1, locals=1, args_size=1
         0: aload_0
         1: getfield      #139                // Field ordinal:Lorg/scalatest/events/Ordinal;
         4: areturn
      LineNumberTable:
        line 920: 0
      LocalVariableTable:
        Start  Length  Slot  Name   Signature
            0       5     0  this   Lorg/scalatest/events/TestCanceled;

  public java.lang.String message();
    descriptor: ()Ljava/lang/String;
    flags: (0x0001) ACC_PUBLIC
    Code:
      stack=1, locals=1, args_size=1
         0: aload_0
         1: getfield      #142                // Field message:Ljava/lang/String;
         4: areturn
      LineNumberTable:
        line 921: 0
      LocalVariableTable:
        Start  Length  Slot  Name   Signature
            0       5     0  this   Lorg/scalatest/events/TestCanceled;

  public java.lang.String suiteName();
    descriptor: ()Ljava/lang/String;
    flags: (0x0001) ACC_PUBLIC
    Code:
      stack=1, locals=1, args_size=1
         0: aload_0
         1: getfield      #144                // Field suiteName:Ljava/lang/String;
         4: areturn
      LineNumberTable:
        line 922: 0
      LocalVariableTable:
        Start  Length  Slot  Name   Signature
            0       5     0  this   Lorg/scalatest/events/TestCanceled;

  public java.lang.String suiteId();
    descriptor: ()Ljava/lang/String;
    flags: (0x0001) ACC_PUBLIC
    Code:
      stack=1, locals=1, args_size=1
         0: aload_0
         1: getfield      #146                // Field suiteId:Ljava/lang/String;
         4: areturn
      LineNumberTable:
        line 923: 0
      LocalVariableTable:
        Start  Length  Slot  Name   Signature
            0       5     0  this   Lorg/scalatest/events/TestCanceled;

  public scala.Option<java.lang.String> suiteClassName();
    descriptor: ()Lscala/Option;
    flags: (0x0001) ACC_PUBLIC
    Code:
      stack=1, locals=1, args_size=1
         0: aload_0
         1: getfield      #148                // Field suiteClassName:Lscala/Option;
         4: areturn
      LineNumberTable:
        line 924: 0
      LocalVariableTable:
        Start  Length  Slot  Name   Signature
            0       5     0  this   Lorg/scalatest/events/TestCanceled;
    Signature: #74                          // ()Lscala/Option<Ljava/lang/String;>;

  public java.lang.String testName();
    descriptor: ()Ljava/lang/String;
    flags: (0x0001) ACC_PUBLIC
    Code:
      stack=1, locals=1, args_size=1
         0: aload_0
         1: getfield      #150                // Field testName:Ljava/lang/String;
         4: areturn
      LineNumberTable:
        line 925: 0
      LocalVariableTable:
        Start  Length  Slot  Name   Signature
            0       5     0  this   Lorg/scalatest/events/TestCanceled;

  public java.lang.String testText();
    descriptor: ()Ljava/lang/String;
    flags: (0x0001) ACC_PUBLIC
    Code:
      stack=1, locals=1, args_size=1
         0: aload_0
         1: getfield      #152                // Field testText:Ljava/lang/String;
         4: areturn
      LineNumberTable:
        line 926: 0
      LocalVariableTable:
        Start  Length  Slot  Name   Signature
            0       5     0  this   Lorg/scalatest/events/TestCanceled;

  public scala.collection.immutable.IndexedSeq<org.scalatest.events.RecordableEvent> recordedEvents();
    descriptor: ()Lscala/collection/immutable/IndexedSeq;
    flags: (0x0001) ACC_PUBLIC
    Code:
      stack=1, locals=1, args_size=1
         0: aload_0
         1: getfield      #156                // Field recordedEvents:Lscala/collection/immutable/IndexedSeq;
         4: areturn
      LineNumberTable:
        line 927: 0
      LocalVariableTable:
        Start  Length  Slot  Name   Signature
            0       5     0  this   Lorg/scalatest/events/TestCanceled;
    Signature: #154                         // ()Lscala/collection/immutable/IndexedSeq<Lorg/scalatest/events/RecordableEvent;>;

  public scala.Option<java.lang.Throwable> throwable();
    descriptor: ()Lscala/Option;
    flags: (0x0001) ACC_PUBLIC
    Code:
      stack=1, locals=1, args_size=1
         0: aload_0
         1: getfield      #158                // Field throwable:Lscala/Option;
         4: areturn
      LineNumberTable:
        line 928: 0
      LocalVariableTable:
        Start  Length  Slot  Name   Signature
            0       5     0  this   Lorg/scalatest/events/TestCanceled;
    Signature: #89                          // ()Lscala/Option<Ljava/lang/Throwable;>;

  public scala.Option<java.lang.Object> duration();
    descriptor: ()Lscala/Option;
    flags: (0x0001) ACC_PUBLIC
    Code:
      stack=1, locals=1, args_size=1
         0: aload_0
         1: getfield      #160                // Field duration:Lscala/Option;
         4: areturn
      LineNumberTable:
        line 929: 0
      LocalVariableTable:
        Start  Length  Slot  Name   Signature
            0       5     0  this   Lorg/scalatest/events/TestCanceled;
    Signature: #70                          // ()Lscala/Option<Ljava/lang/Object;>;

  public scala.Option<org.scalatest.events.Formatter> formatter();
    descriptor: ()Lscala/Option;
    flags: (0x0001) ACC_PUBLIC
    Code:
      stack=1, locals=1, args_size=1
         0: aload_0
         1: getfield      #162                // Field formatter:Lscala/Option;
         4: areturn
      LineNumberTable:
        line 930: 0
      LocalVariableTable:
        Start  Length  Slot  Name   Signature
            0       5     0  this   Lorg/scalatest/events/TestCanceled;
    Signature: #82                          // ()Lscala/Option<Lorg/scalatest/events/Formatter;>;

  public scala.Option<org.scalatest.events.Location> location();
    descriptor: ()Lscala/Option;
    flags: (0x0001) ACC_PUBLIC
    Code:
      stack=1, locals=1, args_size=1
         0: aload_0
         1: getfield      #164                // Field location:Lscala/Option;
         4: areturn
      LineNumberTable:
        line 931: 0
      LocalVariableTable:
        Start  Length  Slot  Name   Signature
            0       5     0  this   Lorg/scalatest/events/TestCanceled;
    Signature: #78                          // ()Lscala/Option<Lorg/scalatest/events/Location;>;

  public scala.Option<java.lang.String> rerunner();
    descriptor: ()Lscala/Option;
    flags: (0x0001) ACC_PUBLIC
    Code:
      stack=1, locals=1, args_size=1
         0: aload_0
         1: getfield      #166                // Field rerunner:Lscala/Option;
         4: areturn
      LineNumberTable:
        line 932: 0
      LocalVariableTable:
        Start  Length  Slot  Name   Signature
            0       5     0  this   Lorg/scalatest/events/TestCanceled;
    Signature: #74                          // ()Lscala/Option<Ljava/lang/String;>;

  public scala.Option<java.lang.Object> payload();
    descriptor: ()Lscala/Option;
    flags: (0x0001) ACC_PUBLIC
    Code:
      stack=1, locals=1, args_size=1
         0: aload_0
         1: getfield      #168                // Field payload:Lscala/Option;
         4: areturn
      LineNumberTable:
        line 933: 0
      LocalVariableTable:
        Start  Length  Slot  Name   Signature
            0       5     0  this   Lorg/scalatest/events/TestCanceled;
    Signature: #70                          // ()Lscala/Option<Ljava/lang/Object;>;

  public java.lang.String threadName();
    descriptor: ()Ljava/lang/String;
    flags: (0x0001) ACC_PUBLIC
    Code:
      stack=1, locals=1, args_size=1
         0: aload_0
         1: getfield      #170                // Field threadName:Ljava/lang/String;
         4: areturn
      LineNumberTable:
        line 934: 0
      LocalVariableTable:
        Start  Length  Slot  Name   Signature
            0       5     0  this   Lorg/scalatest/events/TestCanceled;

  public long timeStamp();
    descriptor: ()J
    flags: (0x0001) ACC_PUBLIC
    Code:
      stack=2, locals=1, args_size=1
         0: aload_0
         1: getfield      #172                // Field timeStamp:J
         4: lreturn
      LineNumberTable:
        line 935: 0
      LocalVariableTable:
        Start  Length  Slot  Name   Signature
            0       5     0  this   Lorg/scalatest/events/TestCanceled;

  public scala.xml.Elem toXml();
    descriptor: ()Lscala/xml/Elem;
    flags: (0x0001) ACC_PUBLIC
    Code:
      stack=28, locals=18, args_size=1
         0: new           #176                // class scala/xml/Elem
         3: dup
         4: aconst_null
         5: ldc           #178                // String TestCanceled
         7: getstatic     #183                // Field scala/xml/Null$.MODULE$:Lscala/xml/Null$;
        10: getstatic     #188                // Field scala/xml/TopScope$.MODULE$:Lscala/xml/TopScope$;
        13: iconst_0
        14: getstatic     #193                // Field scala/xml/NodeSeq$.MODULE$:Lscala/xml/NodeSeq$;
        17: new           #195                // class scala/xml/NodeBuffer
        20: dup
        21: invokespecial #199                // Method scala/xml/NodeBuffer."<init>":()V
        24: astore_1
        25: aload_1
        26: new           #201                // class scala/xml/Text
        29: dup
        30: ldc           #203                // String \n
        32: invokespecial #206                // Method scala/xml/Text."<init>":(Ljava/lang/String;)V
        35: invokevirtual #210                // Method scala/xml/NodeBuffer.$amp$plus:(Ljava/lang/Object;)Lscala/xml/NodeBuffer;
        38: pop
        39: aload_1
        40: new           #176                // class scala/xml/Elem
        43: dup
        44: aconst_null
        45: ldc           #211                // String ordinal
        47: getstatic     #183                // Field scala/xml/Null$.MODULE$:Lscala/xml/Null$;
        50: getstatic     #188                // Field scala/xml/TopScope$.MODULE$:Lscala/xml/TopScope$;
        53: iconst_0
        54: getstatic     #193                // Field scala/xml/NodeSeq$.MODULE$:Lscala/xml/NodeSeq$;
        57: new           #195                // class scala/xml/NodeBuffer
        60: dup
        61: invokespecial #199                // Method scala/xml/NodeBuffer."<init>":()V
        64: astore_2
        65: aload_2
        66: new           #201                // class scala/xml/Text
        69: dup
        70: ldc           #213                // String \n
        72: invokespecial #206                // Method scala/xml/Text."<init>":(Ljava/lang/String;)V
        75: invokevirtual #210                // Method scala/xml/NodeBuffer.$amp$plus:(Ljava/lang/Object;)Lscala/xml/NodeBuffer;
        78: pop
        79: aload_2
        80: new           #176                // class scala/xml/Elem
        83: dup
        84: aconst_null
        85: ldc           #215                // String runStamp
        87: getstatic     #183                // Field scala/xml/Null$.MODULE$:Lscala/xml/Null$;
        90: getstatic     #188                // Field scala/xml/TopScope$.MODULE$:Lscala/xml/TopScope$;
        93: iconst_0
        94: getstatic     #193                // Field scala/xml/NodeSeq$.MODULE$:Lscala/xml/NodeSeq$;
        97: new           #195                // class scala/xml/NodeBuffer
       100: dup
       101: invokespecial #199                // Method scala/xml/NodeBuffer."<init>":()V
       104: astore_3
       105: aload_3
       106: aload_0
       107: invokevirtual #217                // Method ordinal:()Lorg/scalatest/events/Ordinal;
       110: invokevirtual #222                // Method org/scalatest/events/Ordinal.runStamp:()I
       113: invokestatic  #228                // Method scala/runtime/BoxesRunTime.boxToInteger:(I)Ljava/lang/Integer;
       116: invokevirtual #210                // Method scala/xml/NodeBuffer.$amp$plus:(Ljava/lang/Object;)Lscala/xml/NodeBuffer;
       119: pop
       120: aload_3
       121: invokevirtual #232                // Method scala/xml/NodeSeq$.seqToNodeSeq:(Lscala/collection/Seq;)Lscala/xml/NodeSeq;
       124: invokespecial #235                // Method scala/xml/Elem."<init>":(Ljava/lang/String;Ljava/lang/String;Lscala/xml/MetaData;Lscala/xml/NamespaceBinding;ZLscala/collection/immutable/Seq;)V
       127: invokevirtual #210                // Method scala/xml/NodeBuffer.$amp$plus:(Ljava/lang/Object;)Lscala/xml/NodeBuffer;
       130: pop
       131: aload_2
       132: new           #201                // class scala/xml/Text
       135: dup
       136: ldc           #203                // String \n
       138: invokespecial #206                // Method scala/xml/Text."<init>":(Ljava/lang/String;)V
       141: invokevirtual #210                // Method scala/xml/NodeBuffer.$amp$plus:(Ljava/lang/Object;)Lscala/xml/NodeBuffer;
       144: pop
       145: aload_2
       146: invokevirtual #232                // Method scala/xml/NodeSeq$.seqToNodeSeq:(Lscala/collection/Seq;)Lscala/xml/NodeSeq;
       149: invokespecial #235                // Method scala/xml/Elem."<init>":(Ljava/lang/String;Ljava/lang/String;Lscala/xml/MetaData;Lscala/xml/NamespaceBinding;ZLscala/collection/immutable/Seq;)V
       152: invokevirtual #210                // Method scala/xml/NodeBuffer.$amp$plus:(Ljava/lang/Object;)Lscala/xml/NodeBuffer;
       155: pop
       156: aload_1
       157: new           #201                // class scala/xml/Text
       160: dup
       161: ldc           #203                // String \n
       163: invokespecial #206                // Method scala/xml/Text."<init>":(Ljava/lang/String;)V
       166: invokevirtual #210                // Method scala/xml/NodeBuffer.$amp$plus:(Ljava/lang/Object;)Lscala/xml/NodeBuffer;
       169: pop
       170: aload_1
       171: new           #176                // class scala/xml/Elem
       174: dup
       175: aconst_null
       176: ldc           #236                // String message
       178: getstatic     #183                // Field scala/xml/Null$.MODULE$:Lscala/xml/Null$;
       181: getstatic     #188                // Field scala/xml/TopScope$.MODULE$:Lscala/xml/TopScope$;
       184: iconst_0
       185: getstatic     #193                // Field scala/xml/NodeSeq$.MODULE$:Lscala/xml/NodeSeq$;
       188: new           #195                // class scala/xml/NodeBuffer
       191: dup
       192: invokespecial #199                // Method scala/xml/NodeBuffer."<init>":()V
       195: astore        4
       197: aload         4
       199: aload_0
       200: invokevirtual #238                // Method message:()Ljava/lang/String;
       203: invokevirtual #210                // Method scala/xml/NodeBuffer.$amp$plus:(Ljava/lang/Object;)Lscala/xml/NodeBuffer;
       206: pop
       207: aload         4
       209: invokevirtual #232                // Method scala/xml/NodeSeq$.seqToNodeSeq:(Lscala/collection/Seq;)Lscala/xml/NodeSeq;
       212: invokespecial #235                // Method scala/xml/Elem."<init>":(Ljava/lang/String;Ljava/lang/String;Lscala/xml/MetaData;Lscala/xml/NamespaceBinding;ZLscala/collection/immutable/Seq;)V
       215: invokevirtual #210                // Method scala/xml/NodeBuffer.$amp$plus:(Ljava/lang/Object;)Lscala/xml/NodeBuffer;
       218: pop
       219: aload_1
       220: new           #201                // class scala/xml/Text
       223: dup
       224: ldc           #203                // String \n
       226: invokespecial #206                // Method scala/xml/Text."<init>":(Ljava/lang/String;)V
       229: invokevirtual #210                // Method scala/xml/NodeBuffer.$amp$plus:(Ljava/lang/Object;)Lscala/xml/NodeBuffer;
       232: pop
       233: aload_1
       234: new           #176                // class scala/xml/Elem
       237: dup
       238: aconst_null
       239: ldc           #239                // String suiteName
       241: getstatic     #183                // Field scala/xml/Null$.MODULE$:Lscala/xml/Null$;
       244: getstatic     #188                // Field scala/xml/TopScope$.MODULE$:Lscala/xml/TopScope$;
       247: iconst_0
       248: getstatic     #193                // Field scala/xml/NodeSeq$.MODULE$:Lscala/xml/NodeSeq$;
       251: new           #195                // class scala/xml/NodeBuffer
       254: dup
       255: invokespecial #199                // Method scala/xml/NodeBuffer."<init>":()V
       258: astore        5
       260: aload         5
       262: aload_0
       263: invokevirtual #241                // Method suiteName:()Ljava/lang/String;
       266: invokevirtual #210                // Method scala/xml/NodeBuffer.$amp$plus:(Ljava/lang/Object;)Lscala/xml/NodeBuffer;
       269: pop
       270: aload         5
       272: invokevirtual #232                // Method scala/xml/NodeSeq$.seqToNodeSeq:(Lscala/collection/Seq;)Lscala/xml/NodeSeq;
       275: invokespecial #235                // Method scala/xml/Elem."<init>":(Ljava/lang/String;Ljava/lang/String;Lscala/xml/MetaData;Lscala/xml/NamespaceBinding;ZLscala/collection/immutable/Seq;)V
       278: invokevirtual #210                // Method scala/xml/NodeBuffer.$amp$plus:(Ljava/lang/Object;)Lscala/xml/NodeBuffer;
       281: pop
       282: aload_1
       283: new           #201                // class scala/xml/Text
       286: dup
       287: ldc           #203                // String \n
       289: invokespecial #206                // Method scala/xml/Text."<init>":(Ljava/lang/String;)V
       292: invokevirtual #210                // Method scala/xml/NodeBuffer.$amp$plus:(Ljava/lang/Object;)Lscala/xml/NodeBuffer;
       295: pop
       296: aload_1
       297: new           #176                // class scala/xml/Elem
       300: dup
       301: aconst_null
       302: ldc           #242                // String suiteId
       304: getstatic     #183                // Field scala/xml/Null$.MODULE$:Lscala/xml/Null$;
       307: getstatic     #188                // Field scala/xml/TopScope$.MODULE$:Lscala/xml/TopScope$;
       310: iconst_0
       311: getstatic     #193                // Field scala/xml/NodeSeq$.MODULE$:Lscala/xml/NodeSeq$;
       314: new           #195                // class scala/xml/NodeBuffer
       317: dup
       318: invokespecial #199                // Method scala/xml/NodeBuffer."<init>":()V
       321: astore        6
       323: aload         6
       325: aload_0
       326: invokevirtual #244                // Method suiteId:()Ljava/lang/String;
       329: invokevirtual #210                // Method scala/xml/NodeBuffer.$amp$plus:(Ljava/lang/Object;)Lscala/xml/NodeBuffer;
       332: pop
       333: aload         6
       335: invokevirtual #232                // Method scala/xml/NodeSeq$.seqToNodeSeq:(Lscala/collection/Seq;)Lscala/xml/NodeSeq;
       338: invokespecial #235                // Method scala/xml/Elem."<init>":(Ljava/lang/String;Ljava/lang/String;Lscala/xml/MetaData;Lscala/xml/NamespaceBinding;ZLscala/collection/immutable/Seq;)V
       341: invokevirtual #210                // Method scala/xml/NodeBuffer.$amp$plus:(Ljava/lang/Object;)Lscala/xml/NodeBuffer;
       344: pop
       345: aload_1
       346: new           #201                // class scala/xml/Text
       349: dup
       350: ldc           #203                // String \n
       352: invokespecial #206                // Method scala/xml/Text."<init>":(Ljava/lang/String;)V
       355: invokevirtual #210                // Method scala/xml/NodeBuffer.$amp$plus:(Ljava/lang/Object;)Lscala/xml/NodeBuffer;
       358: pop
       359: aload_1
       360: new           #176                // class scala/xml/Elem
       363: dup
       364: aconst_null
       365: ldc           #245                // String suiteClassName
       367: getstatic     #183                // Field scala/xml/Null$.MODULE$:Lscala/xml/Null$;
       370: getstatic     #188                // Field scala/xml/TopScope$.MODULE$:Lscala/xml/TopScope$;
       373: iconst_0
       374: getstatic     #193                // Field scala/xml/NodeSeq$.MODULE$:Lscala/xml/NodeSeq$;
       377: new           #195                // class scala/xml/NodeBuffer
       380: dup
       381: invokespecial #199                // Method scala/xml/NodeBuffer."<init>":()V
       384: astore        7
       386: aload         7
       388: aload_0
       389: invokevirtual #249                // Method EventXmlHelper:()Lorg/scalatest/events/Event$EventXmlHelper$;
       392: aload_0
       393: invokevirtual #251                // Method suiteClassName:()Lscala/Option;
       396: invokevirtual #255                // Method org/scalatest/events/Event$EventXmlHelper$.stringOption:(Lscala/Option;)Ljava/lang/String;
       399: invokevirtual #210                // Method scala/xml/NodeBuffer.$amp$plus:(Ljava/lang/Object;)Lscala/xml/NodeBuffer;
       402: pop
       403: aload         7
       405: invokevirtual #232                // Method scala/xml/NodeSeq$.seqToNodeSeq:(Lscala/collection/Seq;)Lscala/xml/NodeSeq;
       408: invokespecial #235                // Method scala/xml/Elem."<init>":(Ljava/lang/String;Ljava/lang/String;Lscala/xml/MetaData;Lscala/xml/NamespaceBinding;ZLscala/collection/immutable/Seq;)V
       411: invokevirtual #210                // Method scala/xml/NodeBuffer.$amp$plus:(Ljava/lang/Object;)Lscala/xml/NodeBuffer;
       414: pop
       415: aload_1
       416: new           #201                // class scala/xml/Text
       419: dup
       420: ldc           #203                // String \n
       422: invokespecial #206                // Method scala/xml/Text."<init>":(Ljava/lang/String;)V
       425: invokevirtual #210                // Method scala/xml/NodeBuffer.$amp$plus:(Ljava/lang/Object;)Lscala/xml/NodeBuffer;
       428: pop
       429: aload_1
       430: new           #176                // class scala/xml/Elem
       433: dup
       434: aconst_null
       435: ldc_w         #256                // String duration
       438: getstatic     #183                // Field scala/xml/Null$.MODULE$:Lscala/xml/Null$;
       441: getstatic     #188                // Field scala/xml/TopScope$.MODULE$:Lscala/xml/TopScope$;
       444: iconst_0
       445: getstatic     #193                // Field scala/xml/NodeSeq$.MODULE$:Lscala/xml/NodeSeq$;
       448: new           #195                // class scala/xml/NodeBuffer
       451: dup
       452: invokespecial #199                // Method scala/xml/NodeBuffer."<init>":()V
       455: astore        8
       457: aload         8
       459: aload_0
       460: invokevirtual #249                // Method EventXmlHelper:()Lorg/scalatest/events/Event$EventXmlHelper$;
       463: aload_0
       464: invokevirtual #258                // Method duration:()Lscala/Option;
       467: invokevirtual #261                // Method org/scalatest/events/Event$EventXmlHelper$.longOption:(Lscala/Option;)Ljava/lang/String;
       470: invokevirtual #210                // Method scala/xml/NodeBuffer.$amp$plus:(Ljava/lang/Object;)Lscala/xml/NodeBuffer;
       473: pop
       474: aload         8
       476: invokevirtual #232                // Method scala/xml/NodeSeq$.seqToNodeSeq:(Lscala/collection/Seq;)Lscala/xml/NodeSeq;
       479: invokespecial #235                // Method scala/xml/Elem."<init>":(Ljava/lang/String;Ljava/lang/String;Lscala/xml/MetaData;Lscala/xml/NamespaceBinding;ZLscala/collection/immutable/Seq;)V
       482: invokevirtual #210                // Method scala/xml/NodeBuffer.$amp$plus:(Ljava/lang/Object;)Lscala/xml/NodeBuffer;
       485: pop
       486: aload_1
       487: new           #201                // class scala/xml/Text
       490: dup
       491: ldc           #203                // String \n
       493: invokespecial #206                // Method scala/xml/Text."<init>":(Ljava/lang/String;)V
       496: invokevirtual #210                // Method scala/xml/NodeBuffer.$amp$plus:(Ljava/lang/Object;)Lscala/xml/NodeBuffer;
       499: pop
       500: aload_1
       501: new           #176                // class scala/xml/Elem
       504: dup
       505: aconst_null
       506: ldc_w         #262                // String testName
       509: getstatic     #183                // Field scala/xml/Null$.MODULE$:Lscala/xml/Null$;
       512: getstatic     #188                // Field scala/xml/TopScope$.MODULE$:Lscala/xml/TopScope$;
       515: iconst_0
       516: getstatic     #193                // Field scala/xml/NodeSeq$.MODULE$:Lscala/xml/NodeSeq$;
       519: new           #195                // class scala/xml/NodeBuffer
       522: dup
       523: invokespecial #199                // Method scala/xml/NodeBuffer."<init>":()V
       526: astore        9
       528: aload         9
       530: aload_0
       531: invokevirtual #264                // Method testName:()Ljava/lang/String;
       534: invokevirtual #210                // Method scala/xml/NodeBuffer.$amp$plus:(Ljava/lang/Object;)Lscala/xml/NodeBuffer;
       537: pop
       538: aload         9
       540: invokevirtual #232                // Method scala/xml/NodeSeq$.seqToNodeSeq:(Lscala/collection/Seq;)Lscala/xml/NodeSeq;
       543: invokespecial #235                // Method scala/xml/Elem."<init>":(Ljava/lang/String;Ljava/lang/String;Lscala/xml/MetaData;Lscala/xml/NamespaceBinding;ZLscala/collection/immutable/Seq;)V
       546: invokevirtual #210                // Method scala/xml/NodeBuffer.$amp$plus:(Ljava/lang/Object;)Lscala/xml/NodeBuffer;
       549: pop
       550: aload_1
       551: new           #201                // class scala/xml/Text
       554: dup
       555: ldc           #203                // String \n
       557: invokespecial #206                // Method scala/xml/Text."<init>":(Ljava/lang/String;)V
       560: invokevirtual #210                // Method scala/xml/NodeBuffer.$amp$plus:(Ljava/lang/Object;)Lscala/xml/NodeBuffer;
       563: pop
       564: aload_1
       565: new           #176                // class scala/xml/Elem
       568: dup
       569: aconst_null
       570: ldc_w         #265                // String testText
       573: getstatic     #183                // Field scala/xml/Null$.MODULE$:Lscala/xml/Null$;
       576: getstatic     #188                // Field scala/xml/TopScope$.MODULE$:Lscala/xml/TopScope$;
       579: iconst_0
       580: getstatic     #193                // Field scala/xml/NodeSeq$.MODULE$:Lscala/xml/NodeSeq$;
       583: new           #195                // class scala/xml/NodeBuffer
       586: dup
       587: invokespecial #199                // Method scala/xml/NodeBuffer."<init>":()V
       590: astore        10
       592: aload         10
       594: aload_0
       595: invokevirtual #267                // Method testText:()Ljava/lang/String;
       598: invokevirtual #210                // Method scala/xml/NodeBuffer.$amp$plus:(Ljava/lang/Object;)Lscala/xml/NodeBuffer;
       601: pop
       602: aload         10
       604: invokevirtual #232                // Method scala/xml/NodeSeq$.seqToNodeSeq:(Lscala/collection/Seq;)Lscala/xml/NodeSeq;
       607: invokespecial #235                // Method scala/xml/Elem."<init>":(Ljava/lang/String;Ljava/lang/String;Lscala/xml/MetaData;Lscala/xml/NamespaceBinding;ZLscala/collection/immutable/Seq;)V
       610: invokevirtual #210                // Method scala/xml/NodeBuffer.$amp$plus:(Ljava/lang/Object;)Lscala/xml/NodeBuffer;
       613: pop
       614: aload_1
       615: new           #201                // class scala/xml/Text
       618: dup
       619: ldc           #203                // String \n
       621: invokespecial #206                // Method scala/xml/Text."<init>":(Ljava/lang/String;)V
       624: invokevirtual #210                // Method scala/xml/NodeBuffer.$amp$plus:(Ljava/lang/Object;)Lscala/xml/NodeBuffer;
       627: pop
       628: aload_1
       629: new           #176                // class scala/xml/Elem
       632: dup
       633: aconst_null
       634: ldc_w         #268                // String recordedEvents
       637: getstatic     #183                // Field scala/xml/Null$.MODULE$:Lscala/xml/Null$;
       640: getstatic     #188                // Field scala/xml/TopScope$.MODULE$:Lscala/xml/TopScope$;
       643: iconst_0
       644: getstatic     #193                // Field scala/xml/NodeSeq$.MODULE$:Lscala/xml/NodeSeq$;
       647: new           #195                // class scala/xml/NodeBuffer
       650: dup
       651: invokespecial #199                // Method scala/xml/NodeBuffer."<init>":()V
       654: astore        11
       656: aload         11
       658: aload_0
       659: invokevirtual #270                // Method recordedEvents:()Lscala/collection/immutable/IndexedSeq;
       662: invokedynamic #289,  0            // InvokeDynamic #0:apply:()Lscala/Function1;
       667: invokeinterface #295,  2          // InterfaceMethod scala/collection/immutable/IndexedSeq.map:(Lscala/Function1;)Ljava/lang/Object;
       672: invokevirtual #210                // Method scala/xml/NodeBuffer.$amp$plus:(Ljava/lang/Object;)Lscala/xml/NodeBuffer;
       675: pop
       676: aload         11
       678: invokevirtual #232                // Method scala/xml/NodeSeq$.seqToNodeSeq:(Lscala/collection/Seq;)Lscala/xml/NodeSeq;
       681: invokespecial #235                // Method scala/xml/Elem."<init>":(Ljava/lang/String;Ljava/lang/String;Lscala/xml/MetaData;Lscala/xml/NamespaceBinding;ZLscala/collection/immutable/Seq;)V
       684: invokevirtual #210                // Method scala/xml/NodeBuffer.$amp$plus:(Ljava/lang/Object;)Lscala/xml/NodeBuffer;
       687: pop
       688: aload_1
       689: new           #201                // class scala/xml/Text
       692: dup
       693: ldc           #203                // String \n
       695: invokespecial #206                // Method scala/xml/Text."<init>":(Ljava/lang/String;)V
       698: invokevirtual #210                // Method scala/xml/NodeBuffer.$amp$plus:(Ljava/lang/Object;)Lscala/xml/NodeBuffer;
       701: pop
       702: aload_1
       703: new           #176                // class scala/xml/Elem
       706: dup
       707: aconst_null
       708: ldc_w         #296                // String throwable
       711: getstatic     #183                // Field scala/xml/Null$.MODULE$:Lscala/xml/Null$;
       714: getstatic     #188                // Field scala/xml/TopScope$.MODULE$:Lscala/xml/TopScope$;
       717: iconst_0
       718: getstatic     #193                // Field scala/xml/NodeSeq$.MODULE$:Lscala/xml/NodeSeq$;
       721: new           #195                // class scala/xml/NodeBuffer
       724: dup
       725: invokespecial #199                // Method scala/xml/NodeBuffer."<init>":()V
       728: astore        12
       730: aload         12
       732: aload_0
       733: invokevirtual #249                // Method EventXmlHelper:()Lorg/scalatest/events/Event$EventXmlHelper$;
       736: aload_0
       737: invokevirtual #298                // Method throwable:()Lscala/Option;
       740: invokevirtual #302                // Method org/scalatest/events/Event$EventXmlHelper$.throwableOption:(Lscala/Option;)Ljava/lang/Object;
       743: invokevirtual #210                // Method scala/xml/NodeBuffer.$amp$plus:(Ljava/lang/Object;)Lscala/xml/NodeBuffer;
       746: pop
       747: aload         12
       749: invokevirtual #232                // Method scala/xml/NodeSeq$.seqToNodeSeq:(Lscala/collection/Seq;)Lscala/xml/NodeSeq;
       752: invokespecial #235                // Method scala/xml/Elem."<init>":(Ljava/lang/String;Ljava/lang/String;Lscala/xml/MetaData;Lscala/xml/NamespaceBinding;ZLscala/collection/immutable/Seq;)V
       755: invokevirtual #210                // Method scala/xml/NodeBuffer.$amp$plus:(Ljava/lang/Object;)Lscala/xml/NodeBuffer;
       758: pop
       759: aload_1
       760: new           #201                // class scala/xml/Text
       763: dup
       764: ldc           #203                // String \n
       766: invokespecial #206                // Method scala/xml/Text."<init>":(Ljava/lang/String;)V
       769: invokevirtual #210                // Method scala/xml/NodeBuffer.$amp$plus:(Ljava/lang/Object;)Lscala/xml/NodeBuffer;
       772: pop
       773: aload_1
       774: new           #176                // class scala/xml/Elem
       777: dup
       778: aconst_null
       779: ldc_w         #303                // String formatter
       782: getstatic     #183                // Field scala/xml/Null$.MODULE$:Lscala/xml/Null$;
       785: getstatic     #188                // Field scala/xml/TopScope$.MODULE$:Lscala/xml/TopScope$;
       788: iconst_0
       789: getstatic     #193                // Field scala/xml/NodeSeq$.MODULE$:Lscala/xml/NodeSeq$;
       792: new           #195                // class scala/xml/NodeBuffer
       795: dup
       796: invokespecial #199                // Method scala/xml/NodeBuffer."<init>":()V
       799: astore        13
       801: aload         13
       803: aload_0
       804: invokevirtual #249                // Method EventXmlHelper:()Lorg/scalatest/events/Event$EventXmlHelper$;
       807: aload_0
       808: invokevirtual #305                // Method formatter:()Lscala/Option;
       811: invokevirtual #308                // Method org/scalatest/events/Event$EventXmlHelper$.formatterOption:(Lscala/Option;)Ljava/lang/Object;
       814: invokevirtual #210                // Method scala/xml/NodeBuffer.$amp$plus:(Ljava/lang/Object;)Lscala/xml/NodeBuffer;
       817: pop
       818: aload         13
       820: invokevirtual #232                // Method scala/xml/NodeSeq$.seqToNodeSeq:(Lscala/collection/Seq;)Lscala/xml/NodeSeq;
       823: invokespecial #235                // Method scala/xml/Elem."<init>":(Ljava/lang/String;Ljava/lang/String;Lscala/xml/MetaData;Lscala/xml/NamespaceBinding;ZLscala/collection/immutable/Seq;)V
       826: invokevirtual #210                // Method scala/xml/NodeBuffer.$amp$plus:(Ljava/lang/Object;)Lscala/xml/NodeBuffer;
       829: pop
       830: aload_1
       831: new           #201                // class scala/xml/Text
       834: dup
       835: ldc           #203                // String \n
       837: invokespecial #206                // Method scala/xml/Text."<init>":(Ljava/lang/String;)V
       840: invokevirtual #210                // Method scala/xml/NodeBuffer.$amp$plus:(Ljava/lang/Object;)Lscala/xml/NodeBuffer;
       843: pop
       844: aload_1
       845: new           #176                // class scala/xml/Elem
       848: dup
       849: aconst_null
       850: ldc_w         #309                // String location
       853: getstatic     #183                // Field scala/xml/Null$.MODULE$:Lscala/xml/Null$;
       856: getstatic     #188                // Field scala/xml/TopScope$.MODULE$:Lscala/xml/TopScope$;
       859: iconst_0
       860: getstatic     #193                // Field scala/xml/NodeSeq$.MODULE$:Lscala/xml/NodeSeq$;
       863: new           #195                // class scala/xml/NodeBuffer
       866: dup
       867: invokespecial #199                // Method scala/xml/NodeBuffer."<init>":()V
       870: astore        14
       872: aload         14
       874: aload_0
       875: invokevirtual #249                // Method EventXmlHelper:()Lorg/scalatest/events/Event$EventXmlHelper$;
       878: aload_0
       879: invokevirtual #311                // Method location:()Lscala/Option;
       882: invokevirtual #314                // Method org/scalatest/events/Event$EventXmlHelper$.locationOption:(Lscala/Option;)Ljava/lang/Object;
       885: invokevirtual #210                // Method scala/xml/NodeBuffer.$amp$plus:(Ljava/lang/Object;)Lscala/xml/NodeBuffer;
       888: pop
       889: aload         14
       891: invokevirtual #232                // Method scala/xml/NodeSeq$.seqToNodeSeq:(Lscala/collection/Seq;)Lscala/xml/NodeSeq;
       894: invokespecial #235                // Method scala/xml/Elem."<init>":(Ljava/lang/String;Ljava/lang/String;Lscala/xml/MetaData;Lscala/xml/NamespaceBinding;ZLscala/collection/immutable/Seq;)V
       897: invokevirtual #210                // Method scala/xml/NodeBuffer.$amp$plus:(Ljava/lang/Object;)Lscala/xml/NodeBuffer;
       900: pop
       901: aload_1
       902: new           #201                // class scala/xml/Text
       905: dup
       906: ldc           #203                // String \n
       908: invokespecial #206                // Method scala/xml/Text."<init>":(Ljava/lang/String;)V
       911: invokevirtual #210                // Method scala/xml/NodeBuffer.$amp$plus:(Ljava/lang/Object;)Lscala/xml/NodeBuffer;
       914: pop
       915: aload_1
       916: new           #176                // class scala/xml/Elem
       919: dup
       920: aconst_null
       921: ldc_w         #315                // String rerunner
       924: getstatic     #183                // Field scala/xml/Null$.MODULE$:Lscala/xml/Null$;
       927: getstatic     #188                // Field scala/xml/TopScope$.MODULE$:Lscala/xml/TopScope$;
       930: iconst_0
       931: getstatic     #193                // Field scala/xml/NodeSeq$.MODULE$:Lscala/xml/NodeSeq$;
       934: new           #195                // class scala/xml/NodeBuffer
       937: dup
       938: invokespecial #199                // Method scala/xml/NodeBuffer."<init>":()V
       941: astore        15
       943: aload         15
       945: aload_0
       946: invokevirtual #249                // Method EventXmlHelper:()Lorg/scalatest/events/Event$EventXmlHelper$;
       949: aload_0
       950: invokevirtual #317                // Method rerunner:()Lscala/Option;
       953: invokevirtual #255                // Method org/scalatest/events/Event$EventXmlHelper$.stringOption:(Lscala/Option;)Ljava/lang/String;
       956: invokevirtual #210                // Method scala/xml/NodeBuffer.$amp$plus:(Ljava/lang/Object;)Lscala/xml/NodeBuffer;
       959: pop
       960: aload         15
       962: invokevirtual #232                // Method scala/xml/NodeSeq$.seqToNodeSeq:(Lscala/collection/Seq;)Lscala/xml/NodeSeq;
       965: invokespecial #235                // Method scala/xml/Elem."<init>":(Ljava/lang/String;Ljava/lang/String;Lscala/xml/MetaData;Lscala/xml/NamespaceBinding;ZLscala/collection/immutable/Seq;)V
       968: invokevirtual #210                // Method scala/xml/NodeBuffer.$amp$plus:(Ljava/lang/Object;)Lscala/xml/NodeBuffer;
       971: pop
       972: aload_1
       973: new           #201                // class scala/xml/Text
       976: dup
       977: ldc           #203                // String \n
       979: invokespecial #206                // Method scala/xml/Text."<init>":(Ljava/lang/String;)V
       982: invokevirtual #210                // Method scala/xml/NodeBuffer.$amp$plus:(Ljava/lang/Object;)Lscala/xml/NodeBuffer;
       985: pop
       986: aload_1
       987: new           #176                // class scala/xml/Elem
       990: dup
       991: aconst_null
       992: ldc_w         #318                // String threadName
       995: getstatic     #183                // Field scala/xml/Null$.MODULE$:Lscala/xml/Null$;
       998: getstatic     #188                // Field scala/xml/TopScope$.MODULE$:Lscala/xml/TopScope$;
      1001: iconst_0
      1002: getstatic     #193                // Field scala/xml/NodeSeq$.MODULE$:Lscala/xml/NodeSeq$;
      1005: new           #195                // class scala/xml/NodeBuffer
      1008: dup
      1009: invokespecial #199                // Method scala/xml/NodeBuffer."<init>":()V
      1012: astore        16
      1014: aload         16
      1016: aload_0
      1017: invokevirtual #320                // Method threadName:()Ljava/lang/String;
      1020: invokevirtual #210                // Method scala/xml/NodeBuffer.$amp$plus:(Ljava/lang/Object;)Lscala/xml/NodeBuffer;
      1023: pop
      1024: aload         16
      1026: invokevirtual #232                // Method scala/xml/NodeSeq$.seqToNodeSeq:(Lscala/collection/Seq;)Lscala/xml/NodeSeq;
      1029: invokespecial #235                // Method scala/xml/Elem."<init>":(Ljava/lang/String;Ljava/lang/String;Lscala/xml/MetaData;Lscala/xml/NamespaceBinding;ZLscala/collection/immutable/Seq;)V
      1032: invokevirtual #210                // Method scala/xml/NodeBuffer.$amp$plus:(Ljava/lang/Object;)Lscala/xml/NodeBuffer;
      1035: pop
      1036: aload_1
      1037: new           #201                // class scala/xml/Text
      1040: dup
      1041: ldc           #203                // String \n
      1043: invokespecial #206                // Method scala/xml/Text."<init>":(Ljava/lang/String;)V
      1046: invokevirtual #210                // Method scala/xml/NodeBuffer.$amp$plus:(Ljava/lang/Object;)Lscala/xml/NodeBuffer;
      1049: pop
      1050: aload_1
      1051: new           #176                // class scala/xml/Elem
      1054: dup
      1055: aconst_null
      1056: ldc_w         #321                // String timeStamp
      1059: getstatic     #183                // Field scala/xml/Null$.MODULE$:Lscala/xml/Null$;
      1062: getstatic     #188                // Field scala/xml/TopScope$.MODULE$:Lscala/xml/TopScope$;
      1065: iconst_0
      1066: getstatic     #193                // Field scala/xml/NodeSeq$.MODULE$:Lscala/xml/NodeSeq$;
      1069: new           #195                // class scala/xml/NodeBuffer
      1072: dup
      1073: invokespecial #199                // Method scala/xml/NodeBuffer."<init>":()V
      1076: astore        17
      1078: aload         17
      1080: aload_0
      1081: invokevirtual #323                // Method timeStamp:()J
      1084: invokestatic  #327                // Method scala/runtime/BoxesRunTime.boxToLong:(J)Ljava/lang/Long;
      1087: invokevirtual #210                // Method scala/xml/NodeBuffer.$amp$plus:(Ljava/lang/Object;)Lscala/xml/NodeBuffer;
      1090: pop
      1091: aload         17
      1093: invokevirtual #232                // Method scala/xml/NodeSeq$.seqToNodeSeq:(Lscala/collection/Seq;)Lscala/xml/NodeSeq;
      1096: invokespecial #235                // Method scala/xml/Elem."<init>":(Ljava/lang/String;Ljava/lang/String;Lscala/xml/MetaData;Lscala/xml/NamespaceBinding;ZLscala/collection/immutable/Seq;)V
      1099: invokevirtual #210                // Method scala/xml/NodeBuffer.$amp$plus:(Ljava/lang/Object;)Lscala/xml/NodeBuffer;
      1102: pop
      1103: aload_1
      1104: new           #201                // class scala/xml/Text
      1107: dup
      1108: ldc_w         #329                // String \n
      1111: invokespecial #206                // Method scala/xml/Text."<init>":(Ljava/lang/String;)V
      1114: invokevirtual #210                // Method scala/xml/NodeBuffer.$amp$plus:(Ljava/lang/Object;)Lscala/xml/NodeBuffer;
      1117: pop
      1118: aload_1
      1119: invokevirtual #232                // Method scala/xml/NodeSeq$.seqToNodeSeq:(Lscala/collection/Seq;)Lscala/xml/NodeSeq;
      1122: invokespecial #235                // Method scala/xml/Elem."<init>":(Ljava/lang/String;Ljava/lang/String;Lscala/xml/MetaData;Lscala/xml/NamespaceBinding;ZLscala/collection/immutable/Seq;)V
      1125: areturn
      LineNumberTable:
        line 956: 0
        line 957: 40
        line 958: 80
        line 957: 131
        line 958: 132
        line 957: 145
        line 956: 156
        line 959: 157
        line 956: 170
        line 960: 171
        line 956: 219
        line 960: 220
        line 956: 233
        line 961: 234
        line 956: 282
        line 961: 283
        line 956: 296
        line 962: 297
        line 956: 345
        line 962: 346
        line 956: 359
        line 963: 360
        line 956: 415
        line 963: 416
        line 956: 429
        line 964: 430
        line 956: 486
        line 964: 487
        line 956: 500
        line 965: 501
        line 956: 550
        line 965: 551
        line 956: 564
        line 966: 565
        line 956: 614
        line 966: 615
        line 956: 628
        line 967: 629
        line 956: 688
        line 967: 689
        line 956: 702
        line 968: 703
        line 956: 759
        line 968: 760
        line 956: 773
        line 969: 774
        line 956: 830
        line 969: 831
        line 956: 844
        line 970: 845
        line 956: 901
        line 970: 902
        line 956: 915
        line 971: 916
        line 956: 972
        line 971: 973
        line 956: 986
        line 972: 987
        line 956: 1036
        line 972: 1037
        line 956: 1050
        line 973: 1051
        line 956: 1103
        line 973: 1104
        line 956: 1118
      LocalVariableTable:
        Start  Length  Slot  Name   Signature
          105      16     3  $buf   Lscala/xml/NodeBuffer;
           65      81     2  $buf   Lscala/xml/NodeBuffer;
          197      12     4  $buf   Lscala/xml/NodeBuffer;
          260      12     5  $buf   Lscala/xml/NodeBuffer;
          323      12     6  $buf   Lscala/xml/NodeBuffer;
          386      19     7  $buf   Lscala/xml/NodeBuffer;
          457      19     8  $buf   Lscala/xml/NodeBuffer;
          528      12     9  $buf   Lscala/xml/NodeBuffer;
          592      12    10  $buf   Lscala/xml/NodeBuffer;
          656      22    11  $buf   Lscala/xml/NodeBuffer;
          730      19    12  $buf   Lscala/xml/NodeBuffer;
          801      19    13  $buf   Lscala/xml/NodeBuffer;
          872      19    14  $buf   Lscala/xml/NodeBuffer;
          943      19    15  $buf   Lscala/xml/NodeBuffer;
         1014      12    16  $buf   Lscala/xml/NodeBuffer;
         1078      15    17  $buf   Lscala/xml/NodeBuffer;
           25    1094     1  $buf   Lscala/xml/NodeBuffer;
            0    1126     0  this   Lorg/scalatest/events/TestCanceled;

  public java.lang.String toJson();
    descriptor: ()Ljava/lang/String;
    flags: (0x0001) ACC_PUBLIC
    Code:
      stack=5, locals=1, args_size=1
         0: getstatic     #337                // Field scala/collection/StringOps$.MODULE$:Lscala/collection/StringOps$;
         3: getstatic     #342                // Field scala/Predef$.MODULE$:Lscala/Predef$;
         6: new           #344                // class java/lang/StringBuilder
         9: dup
        10: ldc_w         #345                // int 259
        13: invokespecial #348                // Method java/lang/StringBuilder."<init>":(I)V
        16: ldc_w         #350                // String { \"eventType\": \"TestCanceled\", \"ordinal\":
        19: invokevirtual #354                // Method java/lang/StringBuilder.append:(Ljava/lang/String;)Ljava/lang/StringBuilder;
        22: aload_0
        23: invokevirtual #217                // Method ordinal:()Lorg/scalatest/events/Ordinal;
        26: invokevirtual #222                // Method org/scalatest/events/Ordinal.runStamp:()I
        29: invokevirtual #357                // Method java/lang/StringBuilder.append:(I)Ljava/lang/StringBuilder;
        32: ldc_w         #359                // String , \"message\":
        35: invokevirtual #354                // Method java/lang/StringBuilder.append:(Ljava/lang/String;)Ljava/lang/StringBuilder;
        38: aload_0
        39: invokevirtual #363                // Method EventJsonHelper:()Lorg/scalatest/events/Event$EventJsonHelper$;
        42: aload_0
        43: invokevirtual #238                // Method message:()Ljava/lang/String;
        46: invokevirtual #367                // Method org/scalatest/events/Event$EventJsonHelper$.string:(Ljava/lang/String;)Ljava/lang/String;
        49: invokevirtual #354                // Method java/lang/StringBuilder.append:(Ljava/lang/String;)Ljava/lang/StringBuilder;
        52: ldc_w         #369                // String , \"suiteName\":
        55: invokevirtual #354                // Method java/lang/StringBuilder.append:(Ljava/lang/String;)Ljava/lang/StringBuilder;
        58: aload_0
        59: invokevirtual #363                // Method EventJsonHelper:()Lorg/scalatest/events/Event$EventJsonHelper$;
        62: aload_0
        63: invokevirtual #241                // Method suiteName:()Ljava/lang/String;
        66: invokevirtual #367                // Method org/scalatest/events/Event$EventJsonHelper$.string:(Ljava/lang/String;)Ljava/lang/String;
        69: invokevirtual #354                // Method java/lang/StringBuilder.append:(Ljava/lang/String;)Ljava/lang/StringBuilder;
        72: ldc_w         #371                // String , \"suiteId\":
        75: invokevirtual #354                // Method java/lang/StringBuilder.append:(Ljava/lang/String;)Ljava/lang/StringBuilder;
        78: aload_0
        79: invokevirtual #363                // Method EventJsonHelper:()Lorg/scalatest/events/Event$EventJsonHelper$;
        82: aload_0
        83: invokevirtual #244                // Method suiteId:()Ljava/lang/String;
        86: invokevirtual #367                // Method org/scalatest/events/Event$EventJsonHelper$.string:(Ljava/lang/String;)Ljava/lang/String;
        89: invokevirtual #354                // Method java/lang/StringBuilder.append:(Ljava/lang/String;)Ljava/lang/StringBuilder;
        92: ldc_w         #373                // String , \"suiteClassName\":
        95: invokevirtual #354                // Method java/lang/StringBuilder.append:(Ljava/lang/String;)Ljava/lang/StringBuilder;
        98: aload_0
        99: invokevirtual #363                // Method EventJsonHelper:()Lorg/scalatest/events/Event$EventJsonHelper$;
       102: aload_0
       103: invokevirtual #251                // Method suiteClassName:()Lscala/Option;
       106: invokevirtual #374                // Method org/scalatest/events/Event$EventJsonHelper$.stringOption:(Lscala/Option;)Ljava/lang/String;
       109: invokevirtual #354                // Method java/lang/StringBuilder.append:(Ljava/lang/String;)Ljava/lang/StringBuilder;
       112: ldc_w         #376                // String , \"duration\":
       115: invokevirtual #354                // Method java/lang/StringBuilder.append:(Ljava/lang/String;)Ljava/lang/StringBuilder;
       118: aload_0
       119: invokevirtual #258                // Method duration:()Lscala/Option;
       122: invokedynamic #386,  0            // InvokeDynamic #1:apply:()Lscala/Function0;
       127: invokevirtual #392                // Method scala/Option.getOrElse:(Lscala/Function0;)Ljava/lang/Object;
       130: invokevirtual #395                // Method java/lang/StringBuilder.append:(Ljava/lang/Object;)Ljava/lang/StringBuilder;
       133: ldc_w         #397                // String , \"testName\":
       136: invokevirtual #354                // Method java/lang/StringBuilder.append:(Ljava/lang/String;)Ljava/lang/StringBuilder;
       139: aload_0
       140: invokevirtual #363                // Method EventJsonHelper:()Lorg/scalatest/events/Event$EventJsonHelper$;
       143: aload_0
       144: invokevirtual #264                // Method testName:()Ljava/lang/String;
       147: invokevirtual #367                // Method org/scalatest/events/Event$EventJsonHelper$.string:(Ljava/lang/String;)Ljava/lang/String;
       150: invokevirtual #354                // Method java/lang/StringBuilder.append:(Ljava/lang/String;)Ljava/lang/StringBuilder;
       153: ldc_w         #399                // String , \"testText\":
       156: invokevirtual #354                // Method java/lang/StringBuilder.append:(Ljava/lang/String;)Ljava/lang/StringBuilder;
       159: aload_0
       160: invokevirtual #363                // Method EventJsonHelper:()Lorg/scalatest/events/Event$EventJsonHelper$;
       163: aload_0
       164: invokevirtual #267                // Method testText:()Ljava/lang/String;
       167: invokevirtual #367                // Method org/scalatest/events/Event$EventJsonHelper$.string:(Ljava/lang/String;)Ljava/lang/String;
       170: invokevirtual #354                // Method java/lang/StringBuilder.append:(Ljava/lang/String;)Ljava/lang/StringBuilder;
       173: ldc_w         #401                // String , \"recordedEvents\" : [
       176: invokevirtual #354                // Method java/lang/StringBuilder.append:(Ljava/lang/String;)Ljava/lang/StringBuilder;
       179: aload_0
       180: invokevirtual #270                // Method recordedEvents:()Lscala/collection/immutable/IndexedSeq;
       183: invokedynamic #408,  0            // InvokeDynamic #2:apply:()Lscala/Function1;
       188: invokeinterface #295,  2          // InterfaceMethod scala/collection/immutable/IndexedSeq.map:(Lscala/Function1;)Ljava/lang/Object;
       193: checkcast     #410                // class scala/collection/IterableOnceOps
       196: ldc_w         #412                // String ,
       199: invokeinterface #415,  2          // InterfaceMethod scala/collection/IterableOnceOps.mkString:(Ljava/lang/String;)Ljava/lang/String;
       204: invokevirtual #354                // Method java/lang/StringBuilder.append:(Ljava/lang/String;)Ljava/lang/StringBuilder;
       207: ldc_w         #417                // String ], \"throwable\":
       210: invokevirtual #354                // Method java/lang/StringBuilder.append:(Ljava/lang/String;)Ljava/lang/StringBuilder;
       213: aload_0
       214: invokevirtual #363                // Method EventJsonHelper:()Lorg/scalatest/events/Event$EventJsonHelper$;
       217: aload_0
       218: invokevirtual #298                // Method throwable:()Lscala/Option;
       221: invokevirtual #419                // Method org/scalatest/events/Event$EventJsonHelper$.throwableOption:(Lscala/Option;)Ljava/lang/String;
       224: invokevirtual #354                // Method java/lang/StringBuilder.append:(Ljava/lang/String;)Ljava/lang/StringBuilder;
       227: ldc_w         #421                // String , \"formatter\":
       230: invokevirtual #354                // Method java/lang/StringBuilder.append:(Ljava/lang/String;)Ljava/lang/StringBuilder;
       233: aload_0
       234: invokevirtual #363                // Method EventJsonHelper:()Lorg/scalatest/events/Event$EventJsonHelper$;
       237: aload_0
       238: invokevirtual #305                // Method formatter:()Lscala/Option;
       241: invokevirtual #423                // Method org/scalatest/events/Event$EventJsonHelper$.formatterOption:(Lscala/Option;)Ljava/lang/String;
       244: invokevirtual #354                // Method java/lang/StringBuilder.append:(Ljava/lang/String;)Ljava/lang/StringBuilder;
       247: ldc_w         #425                // String , \"location\":
       250: invokevirtual #354                // Method java/lang/StringBuilder.append:(Ljava/lang/String;)Ljava/lang/StringBuilder;
       253: aload_0
       254: invokevirtual #363                // Method EventJsonHelper:()Lorg/scalatest/events/Event$EventJsonHelper$;
       257: aload_0
       258: invokevirtual #311                // Method location:()Lscala/Option;
       261: invokevirtual #427                // Method org/scalatest/events/Event$EventJsonHelper$.locationOption:(Lscala/Option;)Ljava/lang/String;
       264: invokevirtual #354                // Method java/lang/StringBuilder.append:(Ljava/lang/String;)Ljava/lang/StringBuilder;
       267: ldc_w         #429                // String , \"rerunner\":
       270: invokevirtual #354                // Method java/lang/StringBuilder.append:(Ljava/lang/String;)Ljava/lang/StringBuilder;
       273: aload_0
       274: invokevirtual #363                // Method EventJsonHelper:()Lorg/scalatest/events/Event$EventJsonHelper$;
       277: aload_0
       278: invokevirtual #317                // Method rerunner:()Lscala/Option;
       281: invokevirtual #374                // Method org/scalatest/events/Event$EventJsonHelper$.stringOption:(Lscala/Option;)Ljava/lang/String;
       284: invokevirtual #354                // Method java/lang/StringBuilder.append:(Ljava/lang/String;)Ljava/lang/StringBuilder;
       287: ldc_w         #431                // String , \"threadName\":
       290: invokevirtual #354                // Method java/lang/StringBuilder.append:(Ljava/lang/String;)Ljava/lang/StringBuilder;
       293: aload_0
       294: invokevirtual #363                // Method EventJsonHelper:()Lorg/scalatest/events/Event$EventJsonHelper$;
       297: aload_0
       298: invokevirtual #320                // Method threadName:()Ljava/lang/String;
       301: invokevirtual #367                // Method org/scalatest/events/Event$EventJsonHelper$.string:(Ljava/lang/String;)Ljava/lang/String;
       304: invokevirtual #354                // Method java/lang/StringBuilder.append:(Ljava/lang/String;)Ljava/lang/StringBuilder;
       307: ldc_w         #433                // String , \"timeStamp\":
       310: invokevirtual #354                // Method java/lang/StringBuilder.append:(Ljava/lang/String;)Ljava/lang/StringBuilder;
       313: aload_0
       314: invokevirtual #323                // Method timeStamp:()J
       317: invokevirtual #436                // Method java/lang/StringBuilder.append:(J)Ljava/lang/StringBuilder;
       320: ldc_w         #438                // String  }
       323: invokevirtual #354                // Method java/lang/StringBuilder.append:(Ljava/lang/String;)Ljava/lang/StringBuilder;
       326: invokevirtual #441                // Method java/lang/StringBuilder.toString:()Ljava/lang/String;
       329: invokevirtual #444                // Method scala/Predef$.augmentString:(Ljava/lang/String;)Ljava/lang/String;
       332: invokevirtual #447                // Method scala/collection/StringOps$.stripMargin$extension:(Ljava/lang/String;)Ljava/lang/String;
       335: areturn
      LineNumberTable:
        line 980: 3
      LocalVariableTable:
        Start  Length  Slot  Name   Signature
            0     336     0  this   Lorg/scalatest/events/TestCanceled;

  public org.scalatest.events.TestCanceled withPayload(scala.Option<java.lang.Object>);
    descriptor: (Lscala/Option;)Lorg/scalatest/events/TestCanceled;
    flags: (0x0001) ACC_PUBLIC
    Code:
      stack=1, locals=2, args_size=2
         0: aload_0
         1: areturn
      LineNumberTable:
        line 983: 0
      LocalVariableTable:
        Start  Length  Slot  Name   Signature
            0       2     0  this   Lorg/scalatest/events/TestCanceled;
            0       2     1 newPayload   Lscala/Option;
    Signature: #450                         // (Lscala/Option<Ljava/lang/Object;>;)Lorg/scalatest/events/TestCanceled;
    MethodParameters:
      Name                           Flags
      newPayload                     final

  public org.scalatest.events.Event withThrowable(scala.Option<java.lang.Throwable>);
    descriptor: (Lscala/Option;)Lorg/scalatest/events/Event;
    flags: (0x0001) ACC_PUBLIC
    Code:
      stack=18, locals=19, args_size=2
         0: aload_1
         1: astore_2
         2: aload_0
         3: invokevirtual #458                // Method copy$default$1:()Lorg/scalatest/events/Ordinal;
         6: astore_3
         7: aload_0
         8: invokevirtual #461                // Method copy$default$2:()Ljava/lang/String;
        11: astore        4
        13: aload_0
        14: invokevirtual #464                // Method copy$default$3:()Ljava/lang/String;
        17: astore        5
        19: aload_0
        20: invokevirtual #467                // Method copy$default$4:()Ljava/lang/String;
        23: astore        6
        25: aload_0
        26: invokevirtual #470                // Method copy$default$5:()Lscala/Option;
        29: astore        7
        31: aload_0
        32: invokevirtual #473                // Method copy$default$6:()Ljava/lang/String;
        35: astore        8
        37: aload_0
        38: invokevirtual #476                // Method copy$default$7:()Ljava/lang/String;
        41: astore        9
        43: aload_0
        44: invokevirtual #479                // Method copy$default$8:()Lscala/collection/immutable/IndexedSeq;
        47: astore        10
        49: aload_0
        50: invokevirtual #482                // Method copy$default$10:()Lscala/Option;
        53: astore        11
        55: aload_0
        56: invokevirtual #485                // Method copy$default$11:()Lscala/Option;
        59: astore        12
        61: aload_0
        62: invokevirtual #488                // Method copy$default$12:()Lscala/Option;
        65: astore        13
        67: aload_0
        68: invokevirtual #491                // Method copy$default$13:()Lscala/Option;
        71: astore        14
        73: aload_0
        74: invokevirtual #494                // Method copy$default$14:()Lscala/Option;
        77: astore        15
        79: aload_0
        80: invokevirtual #497                // Method copy$default$15:()Ljava/lang/String;
        83: astore        16
        85: aload_0
        86: invokevirtual #500                // Method copy$default$16:()J
        89: lstore        17
        91: aload_0
        92: aload_3
        93: aload         4
        95: aload         5
        97: aload         6
        99: aload         7
       101: aload         8
       103: aload         9
       105: aload         10
       107: aload_2
       108: aload         11
       110: aload         12
       112: aload         13
       114: aload         14
       116: aload         15
       118: aload         16
       120: lload         17
       122: invokevirtual #503                // Method copy:(Lorg/scalatest/events/Ordinal;Ljava/lang/String;Ljava/lang/String;Ljava/lang/String;Lscala/Option;Ljava/lang/String;Ljava/lang/String;Lscala/collection/immutable/IndexedSeq;Lscala/Option;Lscala/Option;Lscala/Option;Lscala/Option;Lscala/Option;Lscala/Option;Ljava/lang/String;J)Lorg/scalatest/events/TestCanceled;
       125: areturn
      LineNumberTable:
        line 985: 0
      LocalVariableTable:
        Start  Length  Slot  Name   Signature
            2     123     2   x$1   Lscala/Option;
            7     118     3   x$2   Lorg/scalatest/events/Ordinal;
           13     112     4   x$3   Ljava/lang/String;
           19     106     5   x$4   Ljava/lang/String;
           25     100     6   x$5   Ljava/lang/String;
           31      94     7   x$6   Lscala/Option;
           37      88     8   x$7   Ljava/lang/String;
           43      82     9   x$8   Ljava/lang/String;
           49      76    10   x$9   Lscala/collection/immutable/IndexedSeq;
           55      70    11  x$10   Lscala/Option;
           61      64    12  x$11   Lscala/Option;
           67      58    13  x$12   Lscala/Option;
           73      52    14  x$13   Lscala/Option;
           79      46    15  x$14   Lscala/Option;
           85      40    16  x$15   Ljava/lang/String;
           91      34    17  x$16   J
            0     126     0  this   Lorg/scalatest/events/TestCanceled;
            0     126     1 newThrowable   Lscala/Option;
    Signature: #454                         // (Lscala/Option<Ljava/lang/Throwable;>;)Lorg/scalatest/events/Event;
    MethodParameters:
      Name                           Flags
      newThrowable                   final

  public org.scalatest.events.Event ensureSerializable();
    descriptor: ()Lorg/scalatest/events/Event;
    flags: (0x0001) ACC_PUBLIC
    Code:
      stack=2, locals=1, args_size=1
         0: aload_0
         1: aload_0
         2: invokevirtual #523                // Method payload:()Lscala/Option;
         5: invokevirtual #526                // Method ensurePayloadSerializable:(Lscala/Option;)Lorg/scalatest/events/Event;
         8: aload_0
         9: invokevirtual #298                // Method throwable:()Lscala/Option;
        12: invokevirtual #529                // Method org/scalatest/events/Event.ensureThrowableSerializable:(Lscala/Option;)Lorg/scalatest/events/Event;
        15: areturn
      LineNumberTable:
        line 988: 0
      LocalVariableTable:
        Start  Length  Slot  Name   Signature
            0      16     0  this   Lorg/scalatest/events/TestCanceled;

  public org.scalatest.events.TestCanceled copy(org.scalatest.events.Ordinal, java.lang.String, java.lang.String, java.lang.String, scala.Option<java.lang.String>, java.lang.String, java.lang.String, scala.collection.immutable.IndexedSeq<org.scalatest.events.RecordableEvent>, scala.Option<java.lang.Throwable>, scala.Option<java.lang.Object>, scala.Option<org.scalatest.events.Formatter>, scala.Option<org.scalatest.events.Location>, scala.Option<java.lang.String>, scala.Option<java.lang.Object>, java.lang.String, long);
    descriptor: (Lorg/scalatest/events/Ordinal;Ljava/lang/String;Ljava/lang/String;Ljava/lang/String;Lscala/Option;Ljava/lang/String;Ljava/lang/String;Lscala/collection/immutable/IndexedSeq;Lscala/Option;Lscala/Option;Lscala/Option;Lscala/Option;Lscala/Option;Lscala/Option;Ljava/lang/String;J)Lorg/scalatest/events/TestCanceled;
    flags: (0x0001) ACC_PUBLIC
    Code:
      stack=19, locals=18, args_size=17
         0: new           #2                  // class org/scalatest/events/TestCanceled
         3: dup
         4: aload_1
         5: aload_2
         6: aload_3
         7: aload         4
         9: aload         5
        11: aload         6
        13: aload         7
        15: aload         8
        17: aload         9
        19: aload         10
        21: aload         11
        23: aload         12
        25: aload         13
        27: aload         14
        29: aload         15
        31: lload         16
        33: invokespecial #532                // Method "<init>":(Lorg/scalatest/events/Ordinal;Ljava/lang/String;Ljava/lang/String;Ljava/lang/String;Lscala/Option;Ljava/lang/String;Ljava/lang/String;Lscala/collection/immutable/IndexedSeq;Lscala/Option;Lscala/Option;Lscala/Option;Lscala/Option;Lscala/Option;Lscala/Option;Ljava/lang/String;J)V
        36: areturn
      LineNumberTable:
        line 919: 0
        line 920: 4
        line 921: 5
        line 922: 6
        line 923: 7
        line 924: 9
        line 925: 11
        line 926: 13
        line 927: 15
        line 928: 17
        line 929: 19
        line 930: 21
        line 931: 23
        line 932: 25
        line 933: 27
        line 934: 29
        line 935: 31
      LocalVariableTable:
        Start  Length  Slot  Name   Signature
            0      37     0  this   Lorg/scalatest/events/TestCanceled;
            0      37     1 ordinal   Lorg/scalatest/events/Ordinal;
            0      37     2 message   Ljava/lang/String;
            0      37     3 suiteName   Ljava/lang/String;
            0      37     4 suiteId   Ljava/lang/String;
            0      37     5 suiteClassName   Lscala/Option;
            0      37     6 testName   Ljava/lang/String;
            0      37     7 testText   Ljava/lang/String;
            0      37     8 recordedEvents   Lscala/collection/immutable/IndexedSeq;
            0      37     9 throwable   Lscala/Option;
            0      37    10 duration   Lscala/Option;
            0      37    11 formatter   Lscala/Option;
            0      37    12 location   Lscala/Option;
            0      37    13 rerunner   Lscala/Option;
            0      37    14 payload   Lscala/Option;
            0      37    15 threadName   Ljava/lang/String;
            0      37    16 timeStamp   J
    Signature: #125                         // (Lorg/scalatest/events/Ordinal;Ljava/lang/String;Ljava/lang/String;Ljava/lang/String;Lscala/Option<Ljava/lang/String;>;Ljava/lang/String;Ljava/lang/String;Lscala/collection/immutable/IndexedSeq<Lorg/scalatest/events/RecordableEvent;>;Lscala/Option<Ljava/lang/Throwable;>;Lscala/Option<Ljava/lang/Object;>;Lscala/Option<Lorg/scalatest/events/Formatter;>;Lscala/Option<Lorg/scalatest/events/Location;>;Lscala/Option<Ljava/lang/String;>;Lscala/Option<Ljava/lang/Object;>;Ljava/lang/String;J)Lorg/scalatest/events/TestCanceled;
    MethodParameters:
      Name                           Flags
      ordinal                        final
      message                        final
      suiteName                      final
      suiteId                        final
      suiteClassName                 final
      testName                       final
      testText                       final
      recordedEvents                 final
      throwable                      final
      duration                       final
      formatter                      final
      location                       final
      rerunner                       final
      payload                        final
      threadName                     final
      timeStamp                      final

  public org.scalatest.events.Ordinal copy$default$1();
    descriptor: ()Lorg/scalatest/events/Ordinal;
    flags: (0x0001) ACC_PUBLIC
    Code:
      stack=1, locals=1, args_size=1
         0: aload_0
         1: invokevirtual #217                // Method ordinal:()Lorg/scalatest/events/Ordinal;
         4: areturn
      LineNumberTable:
        line 920: 0
      LocalVariableTable:
        Start  Length  Slot  Name   Signature
            0       5     0  this   Lorg/scalatest/events/TestCanceled;

  public scala.Option<java.lang.Object> copy$default$10();
    descriptor: ()Lscala/Option;
    flags: (0x0001) ACC_PUBLIC
    Code:
      stack=1, locals=1, args_size=1
         0: aload_0
         1: invokevirtual #258                // Method duration:()Lscala/Option;
         4: areturn
      LineNumberTable:
        line 929: 0
      LocalVariableTable:
        Start  Length  Slot  Name   Signature
            0       5     0  this   Lorg/scalatest/events/TestCanceled;
    Signature: #70                          // ()Lscala/Option<Ljava/lang/Object;>;

  public scala.Option<org.scalatest.events.Formatter> copy$default$11();
    descriptor: ()Lscala/Option;
    flags: (0x0001) ACC_PUBLIC
    Code:
      stack=1, locals=1, args_size=1
         0: aload_0
         1: invokevirtual #305                // Method formatter:()Lscala/Option;
         4: areturn
      LineNumberTable:
        line 930: 0
      LocalVariableTable:
        Start  Length  Slot  Name   Signature
            0       5     0  this   Lorg/scalatest/events/TestCanceled;
    Signature: #82                          // ()Lscala/Option<Lorg/scalatest/events/Formatter;>;

  public scala.Option<org.scalatest.events.Location> copy$default$12();
    descriptor: ()Lscala/Option;
    flags: (0x0001) ACC_PUBLIC
    Code:
      stack=1, locals=1, args_size=1
         0: aload_0
         1: invokevirtual #311                // Method location:()Lscala/Option;
         4: areturn
      LineNumberTable:
        line 931: 0
      LocalVariableTable:
        Start  Length  Slot  Name   Signature
            0       5     0  this   Lorg/scalatest/events/TestCanceled;
    Signature: #78                          // ()Lscala/Option<Lorg/scalatest/events/Location;>;

  public scala.Option<java.lang.String> copy$default$13();
    descriptor: ()Lscala/Option;
    flags: (0x0001) ACC_PUBLIC
    Code:
      stack=1, locals=1, args_size=1
         0: aload_0
         1: invokevirtual #317                // Method rerunner:()Lscala/Option;
         4: areturn
      LineNumberTable:
        line 932: 0
      LocalVariableTable:
        Start  Length  Slot  Name   Signature
            0       5     0  this   Lorg/scalatest/events/TestCanceled;
    Signature: #74                          // ()Lscala/Option<Ljava/lang/String;>;

  public scala.Option<java.lang.Object> copy$default$14();
    descriptor: ()Lscala/Option;
    flags: (0x0001) ACC_PUBLIC
    Code:
      stack=1, locals=1, args_size=1
         0: aload_0
         1: invokevirtual #523                // Method payload:()Lscala/Option;
         4: areturn
      LineNumberTable:
        line 933: 0
      LocalVariableTable:
        Start  Length  Slot  Name   Signature
            0       5     0  this   Lorg/scalatest/events/TestCanceled;
    Signature: #70                          // ()Lscala/Option<Ljava/lang/Object;>;

  public java.lang.String copy$default$15();
    descriptor: ()Ljava/lang/String;
    flags: (0x0001) ACC_PUBLIC
    Code:
      stack=1, locals=1, args_size=1
         0: aload_0
         1: invokevirtual #320                // Method threadName:()Ljava/lang/String;
         4: areturn
      LineNumberTable:
        line 934: 0
      LocalVariableTable:
        Start  Length  Slot  Name   Signature
            0       5     0  this   Lorg/scalatest/events/TestCanceled;

  public long copy$default$16();
    descriptor: ()J
    flags: (0x0001) ACC_PUBLIC
    Code:
      stack=2, locals=1, args_size=1
         0: aload_0
         1: invokevirtual #323                // Method timeStamp:()J
         4: lreturn
      LineNumberTable:
        line 935: 0
      LocalVariableTable:
        Start  Length  Slot  Name   Signature
            0       5     0  this   Lorg/scalatest/events/TestCanceled;

  public java.lang.String copy$default$2();
    descriptor: ()Ljava/lang/String;
    flags: (0x0001) ACC_PUBLIC
    Code:
      stack=1, locals=1, args_size=1
         0: aload_0
         1: invokevirtual #238                // Method message:()Ljava/lang/String;
         4: areturn
      LineNumberTable:
        line 921: 0
      LocalVariableTable:
        Start  Length  Slot  Name   Signature
            0       5     0  this   Lorg/scalatest/events/TestCanceled;

  public java.lang.String copy$default$3();
    descriptor: ()Ljava/lang/String;
    flags: (0x0001) ACC_PUBLIC
    Code:
      stack=1, locals=1, args_size=1
         0: aload_0
         1: invokevirtual #241                // Method suiteName:()Ljava/lang/String;
         4: areturn
      LineNumberTable:
        line 922: 0
      LocalVariableTable:
        Start  Length  Slot  Name   Signature
            0       5     0  this   Lorg/scalatest/events/TestCanceled;

  public java.lang.String copy$default$4();
    descriptor: ()Ljava/lang/String;
    flags: (0x0001) ACC_PUBLIC
    Code:
      stack=1, locals=1, args_size=1
         0: aload_0
         1: invokevirtual #244                // Method suiteId:()Ljava/lang/String;
         4: areturn
      LineNumberTable:
        line 923: 0
      LocalVariableTable:
        Start  Length  Slot  Name   Signature
            0       5     0  this   Lorg/scalatest/events/TestCanceled;

  public scala.Option<java.lang.String> copy$default$5();
    descriptor: ()Lscala/Option;
    flags: (0x0001) ACC_PUBLIC
    Code:
      stack=1, locals=1, args_size=1
         0: aload_0
         1: invokevirtual #251                // Method suiteClassName:()Lscala/Option;
         4: areturn
      LineNumberTable:
        line 924: 0
      LocalVariableTable:
        Start  Length  Slot  Name   Signature
            0       5     0  this   Lorg/scalatest/events/TestCanceled;
    Signature: #74                          // ()Lscala/Option<Ljava/lang/String;>;

  public java.lang.String copy$default$6();
    descriptor: ()Ljava/lang/String;
    flags: (0x0001) ACC_PUBLIC
    Code:
      stack=1, locals=1, args_size=1
         0: aload_0
         1: invokevirtual #264                // Method testName:()Ljava/lang/String;
         4: areturn
      LineNumberTable:
        line 925: 0
      LocalVariableTable:
        Start  Length  Slot  Name   Signature
            0       5     0  this   Lorg/scalatest/events/TestCanceled;

  public java.lang.String copy$default$7();
    descriptor: ()Ljava/lang/String;
    flags: (0x0001) ACC_PUBLIC
    Code:
      stack=1, locals=1, args_size=1
         0: aload_0
         1: invokevirtual #267                // Method testText:()Ljava/lang/String;
         4: areturn
      LineNumberTable:
        line 926: 0
      LocalVariableTable:
        Start  Length  Slot  Name   Signature
            0       5     0  this   Lorg/scalatest/events/TestCanceled;

  public scala.collection.immutable.IndexedSeq<org.scalatest.events.RecordableEvent> copy$default$8();
    descriptor: ()Lscala/collection/immutable/IndexedSeq;
    flags: (0x0001) ACC_PUBLIC
    Code:
      stack=1, locals=1, args_size=1
         0: aload_0
         1: invokevirtual #270                // Method recordedEvents:()Lscala/collection/immutable/IndexedSeq;
         4: areturn
      LineNumberTable:
        line 927: 0
      LocalVariableTable:
        Start  Length  Slot  Name   Signature
            0       5     0  this   Lorg/scalatest/events/TestCanceled;
    Signature: #154                         // ()Lscala/collection/immutable/IndexedSeq<Lorg/scalatest/events/RecordableEvent;>;

  public scala.Option<java.lang.Throwable> copy$default$9();
    descriptor: ()Lscala/Option;
    flags: (0x0001) ACC_PUBLIC
    Code:
      stack=1, locals=1, args_size=1
         0: aload_0
         1: invokevirtual #298                // Method throwable:()Lscala/Option;
         4: areturn
      LineNumberTable:
        line 928: 0
      LocalVariableTable:
        Start  Length  Slot  Name   Signature
            0       5     0  this   Lorg/scalatest/events/TestCanceled;
    Signature: #89                          // ()Lscala/Option<Ljava/lang/Throwable;>;

  public java.lang.String productPrefix();
    descriptor: ()Ljava/lang/String;
    flags: (0x0001) ACC_PUBLIC
    Code:
      stack=1, locals=1, args_size=1
         0: ldc           #178                // String TestCanceled
         2: areturn
      LineNumberTable:
        line 919: 0
      LocalVariableTable:
        Start  Length  Slot  Name   Signature
            0       3     0  this   Lorg/scalatest/events/TestCanceled;

  public int productArity();
    descriptor: ()I
    flags: (0x0001) ACC_PUBLIC
    Code:
      stack=1, locals=1, args_size=1
         0: bipush        16
         2: ireturn
      LineNumberTable:
        line 919: 0
      LocalVariableTable:
        Start  Length  Slot  Name   Signature
            0       3     0  this   Lorg/scalatest/events/TestCanceled;

  public java.lang.Object productElement(int);
    descriptor: (I)Ljava/lang/Object;
    flags: (0x0001) ACC_PUBLIC
    Code:
      stack=2, locals=3, args_size=2
         0: iload_1
         1: istore_2
         2: iload_2
         3: tableswitch   { // 0 to 15
                       0: 80
                       1: 87
                       2: 94
                       3: 101
                       4: 108
                       5: 115
                       6: 122
                       7: 129
                       8: 136
                       9: 143
                      10: 150
                      11: 157
                      12: 164
                      13: 171
                      14: 178
                      15: 185
                 default: 195
            }
        80: aload_0
        81: invokevirtual #217                // Method ordinal:()Lorg/scalatest/events/Ordinal;
        84: goto          202
        87: aload_0
        88: invokevirtual #238                // Method message:()Ljava/lang/String;
        91: goto          202
        94: aload_0
        95: invokevirtual #241                // Method suiteName:()Ljava/lang/String;
        98: goto          202
       101: aload_0
       102: invokevirtual #244                // Method suiteId:()Ljava/lang/String;
       105: goto          202
       108: aload_0
       109: invokevirtual #251                // Method suiteClassName:()Lscala/Option;
       112: goto          202
       115: aload_0
       116: invokevirtual #264                // Method testName:()Ljava/lang/String;
       119: goto          202
       122: aload_0
       123: invokevirtual #267                // Method testText:()Ljava/lang/String;
       126: goto          202
       129: aload_0
       130: invokevirtual #270                // Method recordedEvents:()Lscala/collection/immutable/IndexedSeq;
       133: goto          202
       136: aload_0
       137: invokevirtual #298                // Method throwable:()Lscala/Option;
       140: goto          202
       143: aload_0
       144: invokevirtual #258                // Method duration:()Lscala/Option;
       147: goto          202
       150: aload_0
       151: invokevirtual #305                // Method formatter:()Lscala/Option;
       154: goto          202
       157: aload_0
       158: invokevirtual #311                // Method location:()Lscala/Option;
       161: goto          202
       164: aload_0
       165: invokevirtual #317                // Method rerunner:()Lscala/Option;
       168: goto          202
       171: aload_0
       172: invokevirtual #523                // Method payload:()Lscala/Option;
       175: goto          202
       178: aload_0
       179: invokevirtual #320                // Method threadName:()Ljava/lang/String;
       182: goto          202
       185: aload_0
       186: invokevirtual #323                // Method timeStamp:()J
       189: invokestatic  #327                // Method scala/runtime/BoxesRunTime.boxToLong:(J)Ljava/lang/Long;
       192: goto          202
       195: iload_1
       196: invokestatic  #542                // Method scala/runtime/Statics.ioobe:(I)Ljava/lang/Object;
       199: goto          202
       202: areturn
      StackMapTable: number_of_entries = 18
        frame_type = 252 /* append */
          offset_delta = 80
          locals = [ int ]
        frame_type = 6 /* same */
        frame_type = 6 /* same */
        frame_type = 6 /* same */
        frame_type = 6 /* same */
        frame_type = 6 /* same */
        frame_type = 6 /* same */
        frame_type = 6 /* same */
        frame_type = 6 /* same */
        frame_type = 6 /* same */
        frame_type = 6 /* same */
        frame_type = 6 /* same */
        frame_type = 6 /* same */
        frame_type = 6 /* same */
        frame_type = 6 /* same */
        frame_type = 6 /* same */
        frame_type = 9 /* same */
        frame_type = 70 /* same_locals_1_stack_item */
          stack = [ class java/lang/Object ]
      LineNumberTable:
        line 919: 0
      LocalVariableTable:
        Start  Length  Slot  Name   Signature
            0     203     0  this   Lorg/scalatest/events/TestCanceled;
            0     203     1   x$1   I
    MethodParameters:
      Name                           Flags
      x$1                            final

  public scala.collection.Iterator<java.lang.Object> productIterator();
    descriptor: ()Lscala/collection/Iterator;
    flags: (0x0001) ACC_PUBLIC
    Code:
      stack=2, locals=1, args_size=1
         0: getstatic     #553                // Field scala/runtime/ScalaRunTime$.MODULE$:Lscala/runtime/ScalaRunTime$;
         3: aload_0
         4: invokevirtual #557                // Method scala/runtime/ScalaRunTime$.typedProductIterator:(Lscala/Product;)Lscala/collection/Iterator;
         7: areturn
      LineNumberTable:
        line 919: 0
      LocalVariableTable:
        Start  Length  Slot  Name   Signature
            0       8     0  this   Lorg/scalatest/events/TestCanceled;
    Signature: #548                         // ()Lscala/collection/Iterator<Ljava/lang/Object;>;

  public boolean canEqual(java.lang.Object);
    descriptor: (Ljava/lang/Object;)Z
    flags: (0x0001) ACC_PUBLIC
    Code:
      stack=1, locals=2, args_size=2
         0: aload_1
         1: instanceof    #2                  // class org/scalatest/events/TestCanceled
         4: ireturn
      LineNumberTable:
        line 919: 0
      LocalVariableTable:
        Start  Length  Slot  Name   Signature
            0       5     0  this   Lorg/scalatest/events/TestCanceled;
            0       5     1   x$1   Ljava/lang/Object;
    MethodParameters:
      Name                           Flags
      x$1                            final

  public java.lang.String productElementName(int);
    descriptor: (I)Ljava/lang/String;
    flags: (0x0001) ACC_PUBLIC
    Code:
      stack=1, locals=3, args_size=2
         0: iload_1
         1: istore_2
         2: iload_2
         3: tableswitch   { // 0 to 15
                       0: 80
                       1: 85
                       2: 90
                       3: 95
                       4: 100
                       5: 105
                       6: 111
                       7: 117
                       8: 123
                       9: 129
                      10: 135
                      11: 141
                      12: 147
                      13: 153
                      14: 159
                      15: 165
                 default: 171
            }
        80: ldc           #211                // String ordinal
        82: goto          181
        85: ldc           #236                // String message
        87: goto          181
        90: ldc           #239                // String suiteName
        92: goto          181
        95: ldc           #242                // String suiteId
        97: goto          181
       100: ldc           #245                // String suiteClassName
       102: goto          181
       105: ldc_w         #262                // String testName
       108: goto          181
       111: ldc_w         #265                // String testText
       114: goto          181
       117: ldc_w         #268                // String recordedEvents
       120: goto          181
       123: ldc_w         #296                // String throwable
       126: goto          181
       129: ldc_w         #256                // String duration
       132: goto          181
       135: ldc_w         #303                // String formatter
       138: goto          181
       141: ldc_w         #309                // String location
       144: goto          181
       147: ldc_w         #315                // String rerunner
       150: goto          181
       153: ldc_w         #563                // String payload
       156: goto          181
       159: ldc_w         #318                // String threadName
       162: goto          181
       165: ldc_w         #321                // String timeStamp
       168: goto          181
       171: iload_1
       172: invokestatic  #542                // Method scala/runtime/Statics.ioobe:(I)Ljava/lang/Object;
       175: checkcast     #565                // class java/lang/String
       178: goto          181
       181: areturn
      StackMapTable: number_of_entries = 18
        frame_type = 252 /* append */
          offset_delta = 80
          locals = [ int ]
        frame_type = 4 /* same */
        frame_type = 4 /* same */
        frame_type = 4 /* same */
        frame_type = 4 /* same */
        frame_type = 4 /* same */
        frame_type = 5 /* same */
        frame_type = 5 /* same */
        frame_type = 5 /* same */
        frame_type = 5 /* same */
        frame_type = 5 /* same */
        frame_type = 5 /* same */
        frame_type = 5 /* same */
        frame_type = 5 /* same */
        frame_type = 5 /* same */
        frame_type = 5 /* same */
        frame_type = 5 /* same */
        frame_type = 73 /* same_locals_1_stack_item */
          stack = [ class java/lang/String ]
      LineNumberTable:
        line 919: 0
      LocalVariableTable:
        Start  Length  Slot  Name   Signature
            0     182     0  this   Lorg/scalatest/events/TestCanceled;
            0     182     1   x$1   I
    MethodParameters:
      Name                           Flags
      x$1                            final

  public int hashCode();
    descriptor: ()I
    flags: (0x0001) ACC_PUBLIC
    Code:
      stack=3, locals=2, args_size=1
         0: ldc_w         #567                // int -889275714
         3: istore_1
         4: iload_1
         5: aload_0
         6: invokevirtual #569                // Method productPrefix:()Ljava/lang/String;
         9: invokevirtual #571                // Method java/lang/String.hashCode:()I
        12: invokestatic  #575                // Method scala/runtime/Statics.mix:(II)I
        15: istore_1
        16: iload_1
        17: aload_0
        18: invokevirtual #217                // Method ordinal:()Lorg/scalatest/events/Ordinal;
        21: invokestatic  #579                // Method scala/runtime/Statics.anyHash:(Ljava/lang/Object;)I
        24: invokestatic  #575                // Method scala/runtime/Statics.mix:(II)I
        27: istore_1
        28: iload_1
        29: aload_0
        30: invokevirtual #238                // Method message:()Ljava/lang/String;
        33: invokestatic  #579                // Method scala/runtime/Statics.anyHash:(Ljava/lang/Object;)I
        36: invokestatic  #575                // Method scala/runtime/Statics.mix:(II)I
        39: istore_1
        40: iload_1
        41: aload_0
        42: invokevirtual #241                // Method suiteName:()Ljava/lang/String;
        45: invokestatic  #579                // Method scala/runtime/Statics.anyHash:(Ljava/lang/Object;)I
        48: invokestatic  #575                // Method scala/runtime/Statics.mix:(II)I
        51: istore_1
        52: iload_1
        53: aload_0
        54: invokevirtual #244                // Method suiteId:()Ljava/lang/String;
        57: invokestatic  #579                // Method scala/runtime/Statics.anyHash:(Ljava/lang/Object;)I
        60: invokestatic  #575                // Method scala/runtime/Statics.mix:(II)I
        63: istore_1
        64: iload_1
        65: aload_0
        66: invokevirtual #251                // Method suiteClassName:()Lscala/Option;
        69: invokestatic  #579                // Method scala/runtime/Statics.anyHash:(Ljava/lang/Object;)I
        72: invokestatic  #575                // Method scala/runtime/Statics.mix:(II)I
        75: istore_1
        76: iload_1
        77: aload_0
        78: invokevirtual #264                // Method testName:()Ljava/lang/String;
        81: invokestatic  #579                // Method scala/runtime/Statics.anyHash:(Ljava/lang/Object;)I
        84: invokestatic  #575                // Method scala/runtime/Statics.mix:(II)I
        87: istore_1
        88: iload_1
        89: aload_0
        90: invokevirtual #267                // Method testText:()Ljava/lang/String;
        93: invokestatic  #579                // Method scala/runtime/Statics.anyHash:(Ljava/lang/Object;)I
        96: invokestatic  #575                // Method scala/runtime/Statics.mix:(II)I
        99: istore_1
       100: iload_1
       101: aload_0
       102: invokevirtual #270                // Method recordedEvents:()Lscala/collection/immutable/IndexedSeq;
       105: invokestatic  #579                // Method scala/runtime/Statics.anyHash:(Ljava/lang/Object;)I
       108: invokestatic  #575                // Method scala/runtime/Statics.mix:(II)I
       111: istore_1
       112: iload_1
       113: aload_0
       114: invokevirtual #298                // Method throwable:()Lscala/Option;
       117: invokestatic  #579                // Method scala/runtime/Statics.anyHash:(Ljava/lang/Object;)I
       120: invokestatic  #575                // Method scala/runtime/Statics.mix:(II)I
       123: istore_1
       124: iload_1
       125: aload_0
       126: invokevirtual #258                // Method duration:()Lscala/Option;
       129: invokestatic  #579                // Method scala/runtime/Statics.anyHash:(Ljava/lang/Object;)I
       132: invokestatic  #575                // Method scala/runtime/Statics.mix:(II)I
       135: istore_1
       136: iload_1
       137: aload_0
       138: invokevirtual #305                // Method formatter:()Lscala/Option;
       141: invokestatic  #579                // Method scala/runtime/Statics.anyHash:(Ljava/lang/Object;)I
       144: invokestatic  #575                // Method scala/runtime/Statics.mix:(II)I
       147: istore_1
       148: iload_1
       149: aload_0
       150: invokevirtual #311                // Method location:()Lscala/Option;
       153: invokestatic  #579                // Method scala/runtime/Statics.anyHash:(Ljava/lang/Object;)I
       156: invokestatic  #575                // Method scala/runtime/Statics.mix:(II)I
       159: istore_1
       160: iload_1
       161: aload_0
       162: invokevirtual #317                // Method rerunner:()Lscala/Option;
       165: invokestatic  #579                // Method scala/runtime/Statics.anyHash:(Ljava/lang/Object;)I
       168: invokestatic  #575                // Method scala/runtime/Statics.mix:(II)I
       171: istore_1
       172: iload_1
       173: aload_0
       174: invokevirtual #523                // Method payload:()Lscala/Option;
       177: invokestatic  #579                // Method scala/runtime/Statics.anyHash:(Ljava/lang/Object;)I
       180: invokestatic  #575                // Method scala/runtime/Statics.mix:(II)I
       183: istore_1
       184: iload_1
       185: aload_0
       186: invokevirtual #320                // Method threadName:()Ljava/lang/String;
       189: invokestatic  #579                // Method scala/runtime/Statics.anyHash:(Ljava/lang/Object;)I
       192: invokestatic  #575                // Method scala/runtime/Statics.mix:(II)I
       195: istore_1
       196: iload_1
       197: aload_0
       198: invokevirtual #323                // Method timeStamp:()J
       201: invokestatic  #583                // Method scala/runtime/Statics.longHash:(J)I
       204: invokestatic  #575                // Method scala/runtime/Statics.mix:(II)I
       207: istore_1
       208: iload_1
       209: bipush        16
       211: invokestatic  #586                // Method scala/runtime/Statics.finalizeHash:(II)I
       214: ireturn
      LineNumberTable:
        line 919: 0
      LocalVariableTable:
        Start  Length  Slot  Name   Signature
            0     215     0  this   Lorg/scalatest/events/TestCanceled;

  public java.lang.String toString();
    descriptor: ()Ljava/lang/String;
    flags: (0x0001) ACC_PUBLIC
    Code:
      stack=2, locals=1, args_size=1
         0: getstatic     #553                // Field scala/runtime/ScalaRunTime$.MODULE$:Lscala/runtime/ScalaRunTime$;
         3: aload_0
         4: invokevirtual #590                // Method scala/runtime/ScalaRunTime$._toString:(Lscala/Product;)Ljava/lang/String;
         7: areturn
      LineNumberTable:
        line 919: 0
      LocalVariableTable:
        Start  Length  Slot  Name   Signature
            0       8     0  this   Lorg/scalatest/events/TestCanceled;

  public boolean equals(java.lang.Object);
    descriptor: (Ljava/lang/Object;)Z
    flags: (0x0001) ACC_PUBLIC
    Code:
      stack=4, locals=20, args_size=2
         0: aload_0
         1: aload_1
         2: if_acmpeq     538
         5: aload_1
         6: astore_3
         7: aload_3
         8: instanceof    #2                  // class org/scalatest/events/TestCanceled
        11: ifeq          19
        14: iconst_1
        15: istore_2
        16: goto          27
        19: goto          22
        22: iconst_0
        23: istore_2
        24: goto          27
        27: iload_2
        28: ifeq          542
        31: aload_1
        32: checkcast     #2                  // class org/scalatest/events/TestCanceled
        35: astore        4
        37: aload_0
        38: invokevirtual #323                // Method timeStamp:()J
        41: aload         4
        43: invokevirtual #323                // Method timeStamp:()J
        46: lcmp
        47: ifne          534
        50: aload_0
        51: invokevirtual #217                // Method ordinal:()Lorg/scalatest/events/Ordinal;
        54: aload         4
        56: invokevirtual #217                // Method ordinal:()Lorg/scalatest/events/Ordinal;
        59: astore        5
        61: dup
        62: ifnonnull     74
        65: pop
        66: aload         5
        68: ifnull        82
        71: goto          534
        74: aload         5
        76: invokevirtual #593                // Method java/lang/Object.equals:(Ljava/lang/Object;)Z
        79: ifeq          534
        82: aload_0
        83: invokevirtual #238                // Method message:()Ljava/lang/String;
        86: aload         4
        88: invokevirtual #238                // Method message:()Ljava/lang/String;
        91: astore        6
        93: dup
        94: ifnonnull     106
        97: pop
        98: aload         6
       100: ifnull        114
       103: goto          534
       106: aload         6
       108: invokevirtual #593                // Method java/lang/Object.equals:(Ljava/lang/Object;)Z
       111: ifeq          534
       114: aload_0
       115: invokevirtual #241                // Method suiteName:()Ljava/lang/String;
       118: aload         4
       120: invokevirtual #241                // Method suiteName:()Ljava/lang/String;
       123: astore        7
       125: dup
       126: ifnonnull     138
       129: pop
       130: aload         7
       132: ifnull        146
       135: goto          534
       138: aload         7
       140: invokevirtual #593                // Method java/lang/Object.equals:(Ljava/lang/Object;)Z
       143: ifeq          534
       146: aload_0
       147: invokevirtual #244                // Method suiteId:()Ljava/lang/String;
       150: aload         4
       152: invokevirtual #244                // Method suiteId:()Ljava/lang/String;
       155: astore        8
       157: dup
       158: ifnonnull     170
       161: pop
       162: aload         8
       164: ifnull        178
       167: goto          534
       170: aload         8
       172: invokevirtual #593                // Method java/lang/Object.equals:(Ljava/lang/Object;)Z
       175: ifeq          534
       178: aload_0
       179: invokevirtual #251                // Method suiteClassName:()Lscala/Option;
       182: aload         4
       184: invokevirtual #251                // Method suiteClassName:()Lscala/Option;
       187: astore        9
       189: dup
       190: ifnonnull     202
       193: pop
       194: aload         9
       196: ifnull        210
       199: goto          534
       202: aload         9
       204: invokevirtual #593                // Method java/lang/Object.equals:(Ljava/lang/Object;)Z
       207: ifeq          534
       210: aload_0
       211: invokevirtual #264                // Method testName:()Ljava/lang/String;
       214: aload         4
       216: invokevirtual #264                // Method testName:()Ljava/lang/String;
       219: astore        10
       221: dup
       222: ifnonnull     234
       225: pop
       226: aload         10
       228: ifnull        242
       231: goto          534
       234: aload         10
       236: invokevirtual #593                // Method java/lang/Object.equals:(Ljava/lang/Object;)Z
       239: ifeq          534
       242: aload_0
       243: invokevirtual #267                // Method testText:()Ljava/lang/String;
       246: aload         4
       248: invokevirtual #267                // Method testText:()Ljava/lang/String;
       251: astore        11
       253: dup
       254: ifnonnull     266
       257: pop
       258: aload         11
       260: ifnull        274
       263: goto          534
       266: aload         11
       268: invokevirtual #593                // Method java/lang/Object.equals:(Ljava/lang/Object;)Z
       271: ifeq          534
       274: aload_0
       275: invokevirtual #270                // Method recordedEvents:()Lscala/collection/immutable/IndexedSeq;
       278: aload         4
       280: invokevirtual #270                // Method recordedEvents:()Lscala/collection/immutable/IndexedSeq;
       283: astore        12
       285: dup
       286: ifnonnull     298
       289: pop
       290: aload         12
       292: ifnull        306
       295: goto          534
       298: aload         12
       300: invokevirtual #593                // Method java/lang/Object.equals:(Ljava/lang/Object;)Z
       303: ifeq          534
       306: aload_0
       307: invokevirtual #298                // Method throwable:()Lscala/Option;
       310: aload         4
       312: invokevirtual #298                // Method throwable:()Lscala/Option;
       315: astore        13
       317: dup
       318: ifnonnull     330
       321: pop
       322: aload         13
       324: ifnull        338
       327: goto          534
       330: aload         13
       332: invokevirtual #593                // Method java/lang/Object.equals:(Ljava/lang/Object;)Z
       335: ifeq          534
       338: aload_0
       339: invokevirtual #258                // Method duration:()Lscala/Option;
       342: aload         4
       344: invokevirtual #258                // Method duration:()Lscala/Option;
       347: astore        14
       349: dup
       350: ifnonnull     362
       353: pop
       354: aload         14
       356: ifnull        370
       359: goto          534
       362: aload         14
       364: invokevirtual #593                // Method java/lang/Object.equals:(Ljava/lang/Object;)Z
       367: ifeq          534
       370: aload_0
       371: invokevirtual #305                // Method formatter:()Lscala/Option;
       374: aload         4
       376: invokevirtual #305                // Method formatter:()Lscala/Option;
       379: astore        15
       381: dup
       382: ifnonnull     394
       385: pop
       386: aload         15
       388: ifnull        402
       391: goto          534
       394: aload         15
       396: invokevirtual #593                // Method java/lang/Object.equals:(Ljava/lang/Object;)Z
       399: ifeq          534
       402: aload_0
       403: invokevirtual #311                // Method location:()Lscala/Option;
       406: aload         4
       408: invokevirtual #311                // Method location:()Lscala/Option;
       411: astore        16
       413: dup
       414: ifnonnull     426
       417: pop
       418: aload         16
       420: ifnull        434
       423: goto          534
       426: aload         16
       428: invokevirtual #593                // Method java/lang/Object.equals:(Ljava/lang/Object;)Z
       431: ifeq          534
       434: aload_0
       435: invokevirtual #317                // Method rerunner:()Lscala/Option;
       438: aload         4
       440: invokevirtual #317                // Method rerunner:()Lscala/Option;
       443: astore        17
       445: dup
       446: ifnonnull     458
       449: pop
       450: aload         17
       452: ifnull        466
       455: goto          534
       458: aload         17
       460: invokevirtual #593                // Method java/lang/Object.equals:(Ljava/lang/Object;)Z
       463: ifeq          534
       466: aload_0
       467: invokevirtual #523                // Method payload:()Lscala/Option;
       470: aload         4
       472: invokevirtual #523                // Method payload:()Lscala/Option;
       475: astore        18
       477: dup
       478: ifnonnull     490
       481: pop
       482: aload         18
       484: ifnull        498
       487: goto          534
       490: aload         18
       492: invokevirtual #593                // Method java/lang/Object.equals:(Ljava/lang/Object;)Z
       495: ifeq          534
       498: aload_0
       499: invokevirtual #320                // Method threadName:()Ljava/lang/String;
       502: aload         4
       504: invokevirtual #320                // Method threadName:()Ljava/lang/String;
       507: astore        19
       509: dup
       510: ifnonnull     522
       513: pop
       514: aload         19
       516: ifnull        530
       519: goto          534
       522: aload         19
       524: invokevirtual #593                // Method java/lang/Object.equals:(Ljava/lang/Object;)Z
       527: ifeq          534
       530: iconst_1
       531: goto          535
       534: iconst_0
       535: ifeq          542
       538: iconst_1
       539: goto          543
       542: iconst_0
       543: ireturn
      StackMapTable: number_of_entries = 38
        frame_type = 253 /* append */
          offset_delta = 19
          locals = [ top, class java/lang/Object ]
        frame_type = 2 /* same */
        frame_type = 255 /* full_frame */
          offset_delta = 4
          locals = [ class org/scalatest/events/TestCanceled, class java/lang/Object, int, class java/lang/Object ]
          stack = []
        frame_type = 255 /* full_frame */
          offset_delta = 46
          locals = [ class org/scalatest/events/TestCanceled, class java/lang/Object, int, class java/lang/Object, class org/scalatest/events/TestCanceled, class org/scalatest/events/Ordinal ]
          stack = [ class org/scalatest/events/Ordinal ]
        frame_type = 7 /* same */
        frame_type = 255 /* full_frame */
          offset_delta = 23
          locals = [ class org/scalatest/events/TestCanceled, class java/lang/Object, int, class java/lang/Object, class org/scalatest/events/TestCanceled, class org/scalatest/events/Ordinal, class java/lang/String ]
          stack = [ class java/lang/String ]
        frame_type = 7 /* same */
        frame_type = 255 /* full_frame */
          offset_delta = 23
          locals = [ class org/scalatest/events/TestCanceled, class java/lang/Object, int, class java/lang/Object, class org/scalatest/events/TestCanceled, class org/scalatest/events/Ordinal, class java/lang/String, class java/lang/String ]
          stack = [ class java/lang/String ]
        frame_type = 7 /* same */
        frame_type = 255 /* full_frame */
          offset_delta = 23
          locals = [ class org/scalatest/events/TestCanceled, class java/lang/Object, int, class java/lang/Object, class org/scalatest/events/TestCanceled, class org/scalatest/events/Ordinal, class java/lang/String, class java/lang/String, class java/lang/String ]
          stack = [ class java/lang/String ]
        frame_type = 7 /* same */
        frame_type = 255 /* full_frame */
          offset_delta = 23
          locals = [ class org/scalatest/events/TestCanceled, class java/lang/Object, int, class java/lang/Object, class org/scalatest/events/TestCanceled, class org/scalatest/events/Ordinal, class java/lang/String, class java/lang/String, class java/lang/String, class scala/Option ]
          stack = [ class scala/Option ]
        frame_type = 7 /* same */
        frame_type = 255 /* full_frame */
          offset_delta = 23
          locals = [ class org/scalatest/events/TestCanceled, class java/lang/Object, int, class java/lang/Object, class org/scalatest/events/TestCanceled, class org/scalatest/events/Ordinal, class java/lang/String, class java/lang/String, class java/lang/String, class scala/Option, class java/lang/String ]
          stack = [ class java/lang/String ]
        frame_type = 7 /* same */
        frame_type = 255 /* full_frame */
          offset_delta = 23
          locals = [ class org/scalatest/events/TestCanceled, class java/lang/Object, int, class java/lang/Object, class org/scalatest/events/TestCanceled, class org/scalatest/events/Ordinal, class java/lang/String, class java/lang/String, class java/lang/String, class scala/Option, class java/lang/String, class java/lang/String ]
          stack = [ class java/lang/String ]
        frame_type = 7 /* same */
        frame_type = 255 /* full_frame */
          offset_delta = 23
          locals = [ class org/scalatest/events/TestCanceled, class java/lang/Object, int, class java/lang/Object, class org/scalatest/events/TestCanceled, class org/scalatest/events/Ordinal, class java/lang/String, class java/lang/String, class java/lang/String, class scala/Option, class java/lang/String, class java/lang/String, class scala/collection/immutable/IndexedSeq ]
          stack = [ class scala/collection/immutable/IndexedSeq ]
        frame_type = 7 /* same */
        frame_type = 255 /* full_frame */
          offset_delta = 23
          locals = [ class org/scalatest/events/TestCanceled, class java/lang/Object, int, class java/lang/Object, class org/scalatest/events/TestCanceled, class org/scalatest/events/Ordinal, class java/lang/String, class java/lang/String, class java/lang/String, class scala/Option, class java/lang/String, class java/lang/String, class scala/collection/immutable/IndexedSeq, class scala/Option ]
          stack = [ class scala/Option ]
        frame_type = 7 /* same */
        frame_type = 255 /* full_frame */
          offset_delta = 23
          locals = [ class org/scalatest/events/TestCanceled, class java/lang/Object, int, class java/lang/Object, class org/scalatest/events/TestCanceled, class org/scalatest/events/Ordinal, class java/lang/String, class java/lang/String, class java/lang/String, class scala/Option, class java/lang/String, class java/lang/String, class scala/collection/immutable/IndexedSeq, class scala/Option, class scala/Option ]
          stack = [ class scala/Option ]
        frame_type = 7 /* same */
        frame_type = 255 /* full_frame */
          offset_delta = 23
          locals = [ class org/scalatest/events/TestCanceled, class java/lang/Object, int, class java/lang/Object, class org/scalatest/events/TestCanceled, class org/scalatest/events/Ordinal, class java/lang/String, class java/lang/String, class java/lang/String, class scala/Option, class java/lang/String, class java/lang/String, class scala/collection/immutable/IndexedSeq, class scala/Option, class scala/Option, class scala/Option ]
          stack = [ class scala/Option ]
        frame_type = 7 /* same */
        frame_type = 255 /* full_frame */
          offset_delta = 23
          locals = [ class org/scalatest/events/TestCanceled, class java/lang/Object, int, class java/lang/Object, class org/scalatest/events/TestCanceled, class org/scalatest/events/Ordinal, class java/lang/String, class java/lang/String, class java/lang/String, class scala/Option, class java/lang/String, class java/lang/String, class scala/collection/immutable/IndexedSeq, class scala/Option, class scala/Option, class scala/Option, class scala/Option ]
          stack = [ class scala/Option ]
        frame_type = 7 /* same */
        frame_type = 255 /* full_frame */
          offset_delta = 23
          locals = [ class org/scalatest/events/TestCanceled, class java/lang/Object, int, class java/lang/Object, class org/scalatest/events/TestCanceled, class org/scalatest/events/Ordinal, class java/lang/String, class java/lang/String, class java/lang/String, class scala/Option, class java/lang/String, class java/lang/String, class scala/collection/immutable/IndexedSeq, class scala/Option, class scala/Option, class scala/Option, class scala/Option, class scala/Option ]
          stack = [ class scala/Option ]
        frame_type = 7 /* same */
        frame_type = 255 /* full_frame */
          offset_delta = 23
          locals = [ class org/scalatest/events/TestCanceled, class java/lang/Object, int, class java/lang/Object, class org/scalatest/events/TestCanceled, class org/scalatest/events/Ordinal, class java/lang/String, class java/lang/String, class java/lang/String, class scala/Option, class java/lang/String, class java/lang/String, class scala/collection/immutable/IndexedSeq, class scala/Option, class scala/Option, class scala/Option, class scala/Option, class scala/Option, class scala/Option ]
          stack = [ class scala/Option ]
        frame_type = 7 /* same */
        frame_type = 255 /* full_frame */
          offset_delta = 23
          locals = [ class org/scalatest/events/TestCanceled, class java/lang/Object, int, class java/lang/Object, class org/scalatest/events/TestCanceled, class org/scalatest/events/Ordinal, class java/lang/String, class java/lang/String, class java/lang/String, class scala/Option, class java/lang/String, class java/lang/String, class scala/collection/immutable/IndexedSeq, class scala/Option, class scala/Option, class scala/Option, class scala/Option, class scala/Option, class scala/Option, class java/lang/String ]
          stack = [ class java/lang/String ]
        frame_type = 7 /* same */
        frame_type = 255 /* full_frame */
          offset_delta = 3
          locals = [ class org/scalatest/events/TestCanceled, class java/lang/Object, int, class java/lang/Object, class org/scalatest/events/TestCanceled ]
          stack = []
        frame_type = 64 /* same_locals_1_stack_item */
          stack = [ int ]
        frame_type = 248 /* chop */
          offset_delta = 2
        frame_type = 253 /* append */
          offset_delta = 3
          locals = [ int, class java/lang/Object ]
        frame_type = 255 /* full_frame */
          offset_delta = 0
          locals = [ class org/scalatest/events/TestCanceled, class java/lang/Object ]
          stack = [ int ]
      LineNumberTable:
        line 919: 0
      LocalVariableTable:
        Start  Length  Slot  Name   Signature
            0     544     0  this   Lorg/scalatest/events/TestCanceled;
            0     544     1   x$1   Ljava/lang/Object;
    MethodParameters:
      Name                           Flags
      x$1                            final

  public org.scalatest.events.Event withPayload(scala.Option);
    descriptor: (Lscala/Option;)Lorg/scalatest/events/Event;
    flags: (0x1041) ACC_PUBLIC, ACC_BRIDGE, ACC_SYNTHETIC
    Code:
      stack=2, locals=2, args_size=2
         0: aload_0
         1: aload_1
         2: invokevirtual #595                // Method withPayload:(Lscala/Option;)Lorg/scalatest/events/TestCanceled;
         5: areturn
      LineNumberTable:
        line 919: 0
      LocalVariableTable:
        Start  Length  Slot  Name   Signature
            0       6     0  this   Lorg/scalatest/events/TestCanceled;
            0       6     1 newPayload   Lscala/Option;
    MethodParameters:
      Name                           Flags
      newPayload                     final

  public static final scala.xml.Elem $anonfun$toXml$4(org.scalatest.events.RecordableEvent);
    descriptor: (Lorg/scalatest/events/RecordableEvent;)Lscala/xml/Elem;
    flags: (0x1019) ACC_PUBLIC, ACC_STATIC, ACC_FINAL, ACC_SYNTHETIC
    Code:
      stack=1, locals=1, args_size=1
         0: aload_0
         1: checkcast     #4                  // class org/scalatest/events/Event
         4: invokevirtual #597                // Method org/scalatest/events/Event.toXml:()Lscala/xml/Elem;
         7: areturn
      LineNumberTable:
        line 967: 0
      LocalVariableTable:
        Start  Length  Slot  Name   Signature
            0       8     0   x$7   Lorg/scalatest/events/RecordableEvent;
    MethodParameters:
      Name                           Flags
      x$7                            final

  public static final java.lang.String $anonfun$toJson$7();
    descriptor: ()Ljava/lang/String;
    flags: (0x1019) ACC_PUBLIC, ACC_STATIC, ACC_FINAL, ACC_SYNTHETIC
    Code:
      stack=1, locals=0, args_size=0
         0: ldc_w         #600                // String null
         3: areturn
      LineNumberTable:
        line 980: 0

  public static final java.lang.String $anonfun$toJson$8(org.scalatest.events.RecordableEvent);
    descriptor: (Lorg/scalatest/events/RecordableEvent;)Ljava/lang/String;
    flags: (0x1019) ACC_PUBLIC, ACC_STATIC, ACC_FINAL, ACC_SYNTHETIC
    Code:
      stack=1, locals=1, args_size=1
         0: aload_0
         1: checkcast     #4                  // class org/scalatest/events/Event
         4: invokevirtual #602                // Method org/scalatest/events/Event.toJson:()Ljava/lang/String;
         7: areturn
      LineNumberTable:
        line 980: 0
      LocalVariableTable:
        Start  Length  Slot  Name   Signature
            0       8     0   x$8   Lorg/scalatest/events/RecordableEvent;
    MethodParameters:
      Name                           Flags
      x$8                            final

  public org.scalatest.events.TestCanceled(org.scalatest.events.Ordinal, java.lang.String, java.lang.String, java.lang.String, scala.Option<java.lang.String>, java.lang.String, java.lang.String, scala.collection.immutable.IndexedSeq<org.scalatest.events.RecordableEvent>, scala.Option<java.lang.Throwable>, scala.Option<java.lang.Object>, scala.Option<org.scalatest.events.Formatter>, scala.Option<org.scalatest.events.Location>, scala.Option<java.lang.String>, scala.Option<java.lang.Object>, java.lang.String, long);
    descriptor: (Lorg/scalatest/events/Ordinal;Ljava/lang/String;Ljava/lang/String;Ljava/lang/String;Lscala/Option;Ljava/lang/String;Ljava/lang/String;Lscala/collection/immutable/IndexedSeq;Lscala/Option;Lscala/Option;Lscala/Option;Lscala/Option;Lscala/Option;Lscala/Option;Ljava/lang/String;J)V
    flags: (0x0001) ACC_PUBLIC
    Code:
      stack=9, locals=18, args_size=17
         0: aload_0
         1: aload_1
         2: putfield      #139                // Field ordinal:Lorg/scalatest/events/Ordinal;
         5: aload_0
         6: aload_2
         7: putfield      #142                // Field message:Ljava/lang/String;
        10: aload_0
        11: aload_3
        12: putfield      #144                // Field suiteName:Ljava/lang/String;
        15: aload_0
        16: aload         4
        18: putfield      #146                // Field suiteId:Ljava/lang/String;
        21: aload_0
        22: aload         5
        24: putfield      #148                // Field suiteClassName:Lscala/Option;
        27: aload_0
        28: aload         6
        30: putfield      #150                // Field testName:Ljava/lang/String;
        33: aload_0
        34: aload         7
        36: putfield      #152                // Field testText:Ljava/lang/String;
        39: aload_0
        40: aload         8
        42: putfield      #156                // Field recordedEvents:Lscala/collection/immutable/IndexedSeq;
        45: aload_0
        46: aload         9
        48: putfield      #158                // Field throwable:Lscala/Option;
        51: aload_0
        52: aload         10
        54: putfield      #160                // Field duration:Lscala/Option;
        57: aload_0
        58: aload         11
        60: putfield      #162                // Field formatter:Lscala/Option;
        63: aload_0
        64: aload         12
        66: putfield      #164                // Field location:Lscala/Option;
        69: aload_0
        70: aload         13
        72: putfield      #166                // Field rerunner:Lscala/Option;
        75: aload_0
        76: aload         14
        78: putfield      #168                // Field payload:Lscala/Option;
        81: aload_0
        82: aload         15
        84: putfield      #170                // Field threadName:Ljava/lang/String;
        87: aload_0
        88: lload         16
        90: putfield      #172                // Field timeStamp:J
        93: aload_0
        94: invokespecial #604                // Method org/scalatest/events/Event."<init>":()V
        97: getstatic     #609                // Field org/scalactic/Requirements$.MODULE$:Lorg/scalactic/Requirements$;
       100: invokevirtual #613                // Method org/scalactic/Requirements$.requirementsHelper:()Lorg/scalactic/Requirements$RequirementsHelper;
       103: bipush        14
       105: anewarray     #565                // class java/lang/String
       108: dup
       109: iconst_0
       110: ldc_w         #615                // String TestCanceled.this.ordinal
       113: aastore
       114: dup
       115: iconst_1
       116: ldc_w         #617                // String TestCanceled.this.message
       119: aastore
       120: dup
       121: iconst_2
       122: ldc_w         #619                // String TestCanceled.this.suiteName
       125: aastore
       126: dup
       127: iconst_3
       128: ldc_w         #621                // String TestCanceled.this.suiteId
       131: aastore
       132: dup
       133: iconst_4
       134: ldc_w         #623                // String TestCanceled.this.suiteClassName
       137: aastore
       138: dup
       139: iconst_5
       140: ldc_w         #625                // String TestCanceled.this.testName
       143: aastore
       144: dup
       145: bipush        6
       147: ldc_w         #627                // String TestCanceled.this.testText
       150: aastore
       151: dup
       152: bipush        7
       154: ldc_w         #629                // String TestCanceled.this.duration
       157: aastore
       158: dup
       159: bipush        8
       161: ldc_w         #631                // String TestCanceled.this.throwable
       164: aastore
       165: dup
       166: bipush        9
       168: ldc_w         #633                // String TestCanceled.this.formatter
       171: aastore
       172: dup
       173: bipush        10
       175: ldc_w         #635                // String TestCanceled.this.location
       178: aastore
       179: dup
       180: bipush        11
       182: ldc_w         #637                // String TestCanceled.this.rerunner
       185: aastore
       186: dup
       187: bipush        12
       189: ldc_w         #639                // String TestCanceled.this.payload
       192: aastore
       193: dup
       194: bipush        13
       196: ldc_w         #641                // String TestCanceled.this.threadName
       199: aastore
       200: checkcast     #643                // class "[Ljava/lang/Object;"
       203: checkcast     #645                // class "[Ljava/lang/String;"
       206: bipush        14
       208: anewarray     #545                // class java/lang/Object
       211: dup
       212: iconst_0
       213: aload_1
       214: aastore
       215: dup
       216: iconst_1
       217: aload_2
       218: aastore
       219: dup
       220: iconst_2
       221: aload_3
       222: aastore
       223: dup
       224: iconst_3
       225: aload         4
       227: aastore
       228: dup
       229: iconst_4
       230: aload         5
       232: aastore
       233: dup
       234: iconst_5
       235: aload         6
       237: aastore
       238: dup
       239: bipush        6
       241: aload         7
       243: aastore
       244: dup
       245: bipush        7
       247: aload         10
       249: aastore
       250: dup
       251: bipush        8
       253: aload         9
       255: aastore
       256: dup
       257: bipush        9
       259: aload         11
       261: aastore
       262: dup
       263: bipush        10
       265: aload         12
       267: aastore
       268: dup
       269: bipush        11
       271: aload         13
       273: aastore
       274: dup
       275: bipush        12
       277: aload         14
       279: aastore
       280: dup
       281: bipush        13
       283: aload         15
       285: aastore
       286: checkcast     #643                // class "[Ljava/lang/Object;"
       289: getstatic     #650                // Field org/scalactic/Prettifier$.MODULE$:Lorg/scalactic/Prettifier$;
       292: invokevirtual #654                // Method org/scalactic/Prettifier$.default:()Lorg/scalactic/Prettifier;
       295: new           #656                // class org/scalactic/source/Position
       298: dup
       299: ldc_w         #657                // String Event.scala
       302: ldc_w         #659                // String Please set the environment variable SCALACTIC_FILL_FILE_PATHNAMES to yes at compile time to enable this feature.
       305: sipush        938
       308: invokespecial #662                // Method org/scalactic/source/Position."<init>":(Ljava/lang/String;Ljava/lang/String;I)V
       311: invokevirtual #666                // Method org/scalactic/Requirements$RequirementsHelper.macroRequireNonNull:([Ljava/lang/String;[Ljava/lang/Object;Lorg/scalactic/Prettifier;Lorg/scalactic/source/Position;)V
       314: return
      LineNumberTable:
        line 920: 0
        line 921: 5
        line 922: 10
        line 923: 15
        line 924: 21
        line 925: 27
        line 926: 33
        line 927: 39
        line 928: 45
        line 929: 51
        line 930: 57
        line 931: 63
        line 932: 69
        line 933: 75
        line 934: 81
        line 935: 87
        line 936: 93
        line 938: 97
        line 939: 217
        line 940: 221
        line 941: 225
        line 942: 230
        line 943: 235
        line 944: 241
        line 945: 247
        line 946: 253
        line 947: 259
        line 948: 265
        line 949: 271
        line 950: 277
        line 951: 283
        line 938: 289
        line 919: 314
      LocalVariableTable:
        Start  Length  Slot  Name   Signature
            0     315     0  this   Lorg/scalatest/events/TestCanceled;
            0     315     1 ordinal   Lorg/scalatest/events/Ordinal;
            0     315     2 message   Ljava/lang/String;
            0     315     3 suiteName   Ljava/lang/String;
            0     315     4 suiteId   Ljava/lang/String;
            0     315     5 suiteClassName   Lscala/Option;
            0     315     6 testName   Ljava/lang/String;
            0     315     7 testText   Ljava/lang/String;
            0     315     8 recordedEvents   Lscala/collection/immutable/IndexedSeq;
            0     315     9 throwable   Lscala/Option;
            0     315    10 duration   Lscala/Option;
            0     315    11 formatter   Lscala/Option;
            0     315    12 location   Lscala/Option;
            0     315    13 rerunner   Lscala/Option;
            0     315    14 payload   Lscala/Option;
            0     315    15 threadName   Ljava/lang/String;
            0     315    16 timeStamp   J
    Signature: #603                         // (Lorg/scalatest/events/Ordinal;Ljava/lang/String;Ljava/lang/String;Ljava/lang/String;Lscala/Option<Ljava/lang/String;>;Ljava/lang/String;Ljava/lang/String;Lscala/collection/immutable/IndexedSeq<Lorg/scalatest/events/RecordableEvent;>;Lscala/Option<Ljava/lang/Throwable;>;Lscala/Option<Ljava/lang/Object;>;Lscala/Option<Lorg/scalatest/events/Formatter;>;Lscala/Option<Lorg/scalatest/events/Location;>;Lscala/Option<Ljava/lang/String;>;Lscala/Option<Ljava/lang/Object;>;Ljava/lang/String;J)V
    MethodParameters:
      Name                           Flags
      ordinal                        final
      message                        final
      suiteName                      final
      suiteId                        final
      suiteClassName                 final
      testName                       final
      testText                       final
      recordedEvents                 final
      throwable                      final
      duration                       final
      formatter                      final
      location                       final
      rerunner                       final
      payload                        final
      threadName                     final
      timeStamp                      final

  private static java.lang.Object $deserializeLambda$(java.lang.invoke.SerializedLambda);
    descriptor: (Ljava/lang/invoke/SerializedLambda;)Ljava/lang/Object;
    flags: (0x100a) ACC_PRIVATE, ACC_STATIC, ACC_SYNTHETIC
    Code:
      stack=1, locals=1, args_size=1
         0: aload_0
         1: invokedynamic #678,  0            // InvokeDynamic #3:lambdaDeserialize:(Ljava/lang/invoke/SerializedLambda;)Ljava/lang/Object;
         6: areturn
}
InnerClasses:
  public static final #15= #12 of #14;    // Lookup=class java/lang/invoke/MethodHandles$Lookup of class java/lang/invoke/MethodHandles
  public static #20= #17 of #19;          // RequirementsHelper=class org/scalactic/Requirements$RequirementsHelper of class org/scalactic/Requirements
  public #23= #22 of #4;                  // EventJsonHelper$=class org/scalatest/events/Event$EventJsonHelper$ of class org/scalatest/events/Event
  public #26= #25 of #4;                  // EventXmlHelper$=class org/scalatest/events/Event$EventXmlHelper$ of class org/scalatest/events/Event
SourceFile: "Event.scala"
RuntimeVisibleAnnotations:
  0: #8(#9=s#10)
    scala.reflect.ScalaSignature(
      bytes="\u0006\u0005\reb\u0001\u0002-Z\u0005\u0002D\u0001B\u001f\u0001\u0003\u0016\u0004%\ta\u001f\u0005\t\u007f\u0002\u0011\t\u0012)A\u0005y\"Q\u0011\u0011\u0001\u0001\u0003\u0016\u0004%\t!a\u0001\t\u0015\u0005U\u0001A!E!\u0002\u0013\t)\u0001\u0003\u0006\u0002\u0018\u0001\u0011)\u001a!C\u0001\u0003\u0007A!\"!\u0007\u0001\u0005#\u0005\u000b\u0011BA\u0003\u0011)\tY\u0002\u0001BK\u0002\u0013\u0005\u00111\u0001\u0005\u000b\u0003;\u0001!\u0011#Q\u0001\n\u0005\u0015\u0001BCA\u0010\u0001\tU\r\u0011\"\u0001\u0002\"!Q\u0011\u0011\u0006\u0001\u0003\u0012\u0003\u0006I!a\t\t\u0015\u0005-\u0002A!f\u0001\n\u0003\t\u0019\u0001\u0003\u0006\u0002.\u0001\u0011\t\u0012)A\u0005\u0003\u000bA!\"a\f\u0001\u0005+\u0007I\u0011AA\u0002\u0011)\t\t\u0004\u0001B\tB\u0003%\u0011Q\u0001\u0005\u000b\u0003g\u0001!Q3A\u0005\u0002\u0005U\u0002BCA\'\u0001\tE\t\u0015!\u0003\u00028!Q\u0011q\n\u0001\u0003\u0016\u0004%\t!!\u0015\t\u0015\u0005m\u0003A!E!\u0002\u0013\t\u0019\u0006\u0003\u0006\u0002^\u0001\u0011)\u001a!C\u0001\u0003?B!\"!\u001b\u0001\u0005#\u0005\u000b\u0011BA1\u0011)\tY\u0007\u0001BK\u0002\u0013\u0005\u0011Q\u000e\u0005\u000b\u0003o\u0002!\u0011#Q\u0001\n\u0005=\u0004BCA=\u0001\tU\r\u0011\"\u0001\u0002|!Q\u0011Q\u0011\u0001\u0003\u0012\u0003\u0006I!! \t\u0015\u0005\u001d\u0005A!f\u0001\n\u0003\t\t\u0003\u0003\u0006\u0002\n\u0002\u0011\t\u0012)A\u0005\u0003GA!\"a#\u0001\u0005+\u0007I\u0011AAG\u0011)\t9\n\u0001B\tB\u0003%\u0011q\u0012\u0005\u000b\u00033\u0003!Q3A\u0005\u0002\u0005\r\u0001BCAN\u0001\tE\t\u0015!\u0003\u0002\u0006!Q\u0011Q\u0014\u0001\u0003\u0016\u0004%\t!a(\t\u0015\u0005\u0005\u0006A!E!\u0002\u0013\t\u0019\u0007C\u0004\u0002$\u0002!\t!!*\t\u0011\u0005%\u0007\u0001\"\u0001\\\u0003\u0017D\u0001\"!7\u0001\t\u0003Y\u00161\u0001\u0005\t\u00037\u0004A\u0011A-\u0002^\"A\u00111\u001d\u0001\u0005Be\u000b)\u000f\u0003\u0005\u0002l\u0002!\teWAw\u0011%\ty\u000fAA\u0001\n\u0003\t\t\u0010C\u0005\u0003\u0014\u0001\t\n\u0011\"\u0001\u0003\u0016!I!1\u0006\u0001\u0012\u0002\u0013\u0005!Q\u0006\u0005\n\u0005c\u0001\u0011\u0013!C\u0001\u0005[A\u0011Ba\r\u0001#\u0003%\tA!\f\t\u0013\tU\u0002!%A\u0005\u0002\t]\u0002\"\u0003B\u001e\u0001E\u0005I\u0011\u0001B\u0017\u0011%\u0011i\u0004AI\u0001\n\u0003\u0011i\u0003C\u0005\u0003@\u0001\t\n\u0011\"\u0001\u0003B!I!Q\t\u0001\u0012\u0002\u0013\u0005!q\t\u0005\n\u0005\u0017\u0002\u0011\u0013!C\u0001\u0005\u001bB\u0011B!\u0015\u0001#\u0003%\tAa\u0015\t\u0013\t]\u0003!%A\u0005\u0002\te\u0003\"\u0003B/\u0001E\u0005I\u0011\u0001B\u001c\u0011%\u0011y\u0006AI\u0001\n\u0003\u0011\t\u0007C\u0005\u0003f\u0001\t\n\u0011\"\u0001\u0003.!I!q\r\u0001\u0012\u0002\u0013\u0005!\u0011\u000e\u0005\n\u0005[\u0002\u0011\u0011!C!\u0005_B\u0011Ba \u0001\u0003\u0003%\tA!!\t\u0013\t%\u0005!!A\u0005\u0002\t-\u0005\"\u0003BI\u0001\u0005\u0005I\u0011\tBJ\u0011%\u0011i\nAA\u0001\n\u0003\u0011y\nC\u0005\u0003*\u0002\t\t\u0011\"\u0011\u0003,\"I!q\u0016\u0001\u0002\u0002\u0013\u0005#\u0011\u0017\u0005\n\u0005g\u0003\u0011\u0011!C!\u0005kC\u0011Ba.\u0001\u0003\u0003%\tE!/\b\u0013\tu\u0016,!A\t\u0002\t}f\u0001\u0003-Z\u0003\u0003E\tA!1\t\u000f\u0005\r&\t\"\u0001\u0003Z\"I!1\u0017\"\u0002\u0002\u0013\u0015#Q\u0017\u0005\n\u00057\u0014\u0015\u0011!CA\u0005;D\u0011Ba@C#\u0003%\tAa\u0012\t\u0013\r\u0005!)%A\u0005\u0002\t5\u0003\"CB\u0002\u0005F\u0005I\u0011\u0001B*\u0011%\u0019)AQI\u0001\n\u0003\u0011I\u0006C\u0005\u0004\b\t\u000b\n\u0011\"\u0001\u00038!I1\u0011\u0002\"\u0012\u0002\u0013\u0005!\u0011\r\u0005\n\u0007\u0017\u0011\u0015\u0013!C\u0001\u0005[A\u0011b!\u0004C#\u0003%\tA!\u001b\t\u0013\r=!)!A\u0005\u0002\u000eE\u0001\"CB\u0010\u0005F\u0005I\u0011\u0001B$\u0011%\u0019\tCQI\u0001\n\u0003\u0011i\u0005C\u0005\u0004$\t\u000b\n\u0011\"\u0001\u0003T!I1Q\u0005\"\u0012\u0002\u0013\u0005!\u0011\f\u0005\n\u0007O\u0011\u0015\u0013!C\u0001\u0005oA\u0011b!\u000bC#\u0003%\tA!\u0019\t\u0013\r-\")%A\u0005\u0002\t5\u0002\"CB\u0017\u0005F\u0005I\u0011\u0001B5\u0011%\u0019yCQA\u0001\n\u0013\u0019\tD\u0001\u0007UKN$8)\u00198dK2,GM\u0003\u0002[7\u00061QM^3oiNT!\u0001X/\u0002\u0013M\u001c\u0017\r\\1uKN$(\"\u00010\u0002\u0007=\u0014xm\u0001\u0001\u0014\u000b\u0001\tW\r\u001b8\u0011\u0005\t\u001cW\"A-\n\u0005\u0011L&!B#wK:$\bC\u00012g\u0013\t9\u0017L\u0001\tFq\u000e,\u0007\u000f^5p]\u0006dWI^3oiB\u0011\u0011\u000e\\\u0007\u0002U*\t1.A\u0003tG\u0006d\u0017-\u0003\u0002nU\n9\u0001K]8ek\u000e$\bCA8x\u001d\t\u0001XO\u0004\u0002ri6\t!O\u0003\u0002t?\u00061AH]8pizJ\u0011a[\u0005\u0003m*\fq\u0001]1dW\u0006<W-\u0003\u0002ys\na1+\u001a:jC2L\'0\u00192mK*\u0011aO[\u0001\b_J$\u0017N\\1m+\u0005a\bC\u00012~\u0013\tq\u0018LA\u0004Pe\u0012Lg.\u00197\u0002\u0011=\u0014H-\u001b8bY\u0002\nq!\\3tg\u0006<W-\u0006\u0002\u0002\u0006A!\u0011qAA\b\u001d\u0011\tI!a\u0003\u0011\u0005ET\u0017bAA\u0007U\u00061\u0001K]3eK\u001aLA!!\u0005\u0002\u0014\t11\u000b\u001e:j]\u001eT1!!\u0004k\u0003!iWm]:bO\u0016\u0004\u0013!C:vSR,g*Y7f\u0003)\u0019X/\u001b;f\u001d\u0006lW\rI\u0001\bgVLG/Z%e\u0003!\u0019X/\u001b;f\u0013\u0012\u0004\u0013AD:vSR,7\t\\1tg:\u000bW.Z\u000b\u0003\u0003G\u0001R![A\u0013\u0003\u000bI1!a\nk\u0005\u0019y\u0005\u000f^5p]\u0006y1/^5uK\u000ec\u0017m]:OC6,\u0007%\u0001\u0005uKN$h*Y7f\u0003%!Xm\u001d;OC6,\u0007%\u0001\u0005uKN$H+\u001a=u\u0003%!Xm\u001d;UKb$\b%\u0001\bsK\u000e|\'\u000fZ3e\u000bZ,g\u000e^:\u0016\u0005\u0005]\u0002CBA\u001d\u0003\u0007\n9%\u0004\u0002\u0002<)!\u0011QHA \u0003%IW.\\;uC\ndWMC\u0002\u0002B)\f!bY8mY\u0016\u001cG/[8o\u0013\u0011\t)%a\u000f\u0003\u0015%sG-\u001a=fIN+\u0017\u000fE\u0002c\u0003\u0013J1!a\u0013Z\u0005=\u0011VmY8sI\u0006\u0014G.Z#wK:$\u0018a\u0004:fG>\u0014H-\u001a3Fm\u0016tGo\u001d\u0011\u0002\u0013QD\'o\\<bE2,WCAA*!\u0015I\u0017QEA+!\ry\u0017qK\u0005\u0004\u00033J(!\u0003+ie><\u0018M\u00197f\u0003)!\bN]8xC\ndW\rI\u0001\tIV\u0014\u0018\r^5p]V\u0011\u0011\u0011\r\t\u0006S\u0006\u0015\u00121\r\t\u0004S\u0006\u0015\u0014bAA4U\n!Aj\u001c8h\u0003%!WO]1uS>t\u0007%A\u0005g_Jl\u0017\r\u001e;feV\u0011\u0011q\u000e\t\u0006S\u0006\u0015\u0012\u0011\u000f\t\u0004E\u0006M\u0014bAA;3\nIai\u001c:nCR$XM]\u0001\u000bM>\u0014X.\u0019;uKJ\u0004\u0013\u0001\u00037pG\u0006$\u0018n\u001c8\u0016\u0005\u0005u\u0004#B5\u0002&\u0005}\u0004c\u00012\u0002\u0002&\u0019\u00111Q-\u0003\u00111{7-\u0019;j_:\f\u0011\u0002\\8dCRLwN\u001c\u0011\u0002\u0011I,\'/\u001e8oKJ\f\u0011B]3sk:tWM\u001d\u0011\u0002\u000fA\f\u0017\u0010\\8bIV\u0011\u0011q\u0012\t\u0006S\u0006\u0015\u0012\u0011\u0013\t\u0004S\u0006M\u0015bAAKU\n\u0019\u0011I\\=\u0002\u0011A\f\u0017\u0010\\8bI\u0002\n!\u0002\u001e5sK\u0006$g*Y7f\u0003-!\bN]3bI:\u000bW.\u001a\u0011\u0002\u0013QLW.Z*uC6\u0004XCAA2\u0003)!\u0018.\\3Ti\u0006l\u0007\u000fI\u0001\u0007y%t\u0017\u000e\u001e \u0015E\u0005\u001d\u0016\u0011VAV\u0003[\u000by+!-\u00024\u0006U\u0016qWA]\u0003w\u000bi,a0\u0002B\u0006\r\u0017QYAd!\t\u0011\u0007\u0001C\u0003{C\u0001\u0007A\u0010C\u0004\u0002\u0002\u0005\u0002\r!!\u0002\t\u000f\u0005]\u0011\u00051\u0001\u0002\u0006!9\u00111D\u0011A\u0002\u0005\u0015\u0001bBA\u0010C\u0001\u0007\u00111\u0005\u0005\b\u0003W\t\u0003\u0019AA\u0003\u0011\u001d\ty#\ta\u0001\u0003\u000bAq!a\r\"\u0001\u0004\t9\u0004C\u0005\u0002P\u0005\u0002\n\u00111\u0001\u0002T!I\u0011QL\u0011\u0011\u0002\u0003\u0007\u0011\u0011\r\u0005\n\u0003W\n\u0003\u0013!a\u0001\u0003_B\u0011\"!\u001f\"!\u0003\u0005\r!! \t\u0013\u0005\u001d\u0015\u0005%AA\u0002\u0005\r\u0002\"CAFCA\u0005\t\u0019AAH\u0011%\tI*\tI\u0001\u0002\u0004\t)\u0001C\u0005\u0002\u001e\u0006\u0002\n\u00111\u0001\u0002d\u0005)Ao\u001c-nYV\u0011\u0011Q\u001a\t\u0005\u0003\u001f\f).\u0004\u0002\u0002R*\u0019\u00111\u001b6\u0002\u0007alG.\u0003\u0003\u0002X\u0006E\'\u0001B#mK6\fa\u0001^8Kg>t\u0017aC<ji\"\u0004\u0016-\u001f7pC\u0012$B!a*\u0002`\"9\u0011\u0011\u001d\u0013A\u0002\u0005=\u0015A\u00038foB\u000b\u0017\u0010\\8bI\u0006iq/\u001b;i)\"\u0014xn^1cY\u0016$2!YAt\u0011\u001d\tI/\na\u0001\u0003\'\nAB\\3x)\"\u0014xn^1cY\u0016\f!#\u001a8tkJ,7+\u001a:jC2L\'0\u00192mKR\t\u0011-\u0001\u0003d_BLHCIAT\u0003g\f)0a>\u0002z\u0006m\u0018Q`A\u0000\u0005\u0003\u0011\u0019A!\u0002\u0003\b\t%!1\u0002B\u0007\u0005\u001f\u0011\t\u0002C\u0004{OA\u0005\t\u0019\u0001?\t\u0013\u0005\u0005q\u0005%AA\u0002\u0005\u0015\u0001\"CA\fOA\u0005\t\u0019AA\u0003\u0011%\tYb\nI\u0001\u0002\u0004\t)\u0001C\u0005\u0002 \u001d\u0002\n\u00111\u0001\u0002$!I\u00111F\u0014\u0011\u0002\u0003\u0007\u0011Q\u0001\u0005\n\u0003_9\u0003\u0013!a\u0001\u0003\u000bA\u0011\"a\r(!\u0003\u0005\r!a\u000e\t\u0013\u0005=s\u0005%AA\u0002\u0005M\u0003\"CA/OA\u0005\t\u0019AA1\u0011%\tYg\nI\u0001\u0002\u0004\ty\u0007C\u0005\u0002z\u001d\u0002\n\u00111\u0001\u0002~!I\u0011qQ\u0014\u0011\u0002\u0003\u0007\u00111\u0005\u0005\n\u0003\u0017;\u0003\u0013!a\u0001\u0003\u001fC\u0011\"!\'(!\u0003\u0005\r!!\u0002\t\u0013\u0005uu\u0005%AA\u0002\u0005\r\u0014AD2paf$C-\u001a4bk2$H%M\u000b\u0003\u0005/Q3\u0001 B\rW\t\u0011Y\u0002\u0005\u0003\u0003\u001e\t\u001dRB\u0001B\u0010\u0015\u0011\u0011\tCa\t\u0002\u0013Ut7\r[3dW\u0016$\'b\u0001B\u0013U\u0006Q\u0011M\u001c8pi\u0006$\u0018n\u001c8\n\t\t%\"q\u0004\u0002\u0012k:\u001c\u0007.Z2lK\u00124\u0016M]5b]\u000e,\u0017AD2paf$C-\u001a4bk2$HEM\u000b\u0003\u0005_QC!!\u0002\u0003\u001a\u0005q1m\u001c9zI\u0011,g-Y;mi\u0012\u001a\u0014AD2paf$C-\u001a4bk2$H\u0005N\u0001\u000fG>\u0004\u0018\u0010\n3fM\u0006,H\u000e\u001e\u00136+\t\u0011ID\u000b\u0003\u0002$\te\u0011AD2paf$C-\u001a4bk2$HEN\u0001\u000fG>\u0004\u0018\u0010\n3fM\u0006,H\u000e\u001e\u00138\u00039\u0019w\u000e]=%I\u00164\u0017-\u001e7uIa*\"Aa\u0011+\t\u0005]\"\u0011D\u0001\u000fG>\u0004\u0018\u0010\n3fM\u0006,H\u000e\u001e\u0013:+\t\u0011IE\u000b\u0003\u0002T\te\u0011aD2paf$C-\u001a4bk2$H%\r\u0019\u0016\u0005\t=#\u0006BA1\u00053\tqbY8qs\u0012\"WMZ1vYR$\u0013\'M\u000b\u0003\u0005+RC!a\u001c\u0003\u001a\u0005y1m\u001c9zI\u0011,g-Y;mi\u0012\n$\'\u0006\u0002\u0003\\)\"\u0011Q\u0010B\r\u0003=\u0019w\u000e]=%I\u00164\u0017-\u001e7uIE\u001a\u0014aD2paf$C-\u001a4bk2$H%\r\u001b\u0016\u0005\t\r$\u0006BAH\u00053\tqbY8qs\u0012\"WMZ1vYR$\u0013\'N\u0001\u0010G>\u0004\u0018\u0010\n3fM\u0006,H\u000e\u001e\u00132mU\u0011!1\u000e\u0016\u0005\u0003G\u0012I\"A\u0007qe>$Wo\u0019;Qe\u00164\u0017\u000e_\u000b\u0003\u0005c\u0002BAa\u001d\u0003~5\u0011!Q\u000f\u0006\u0005\u0005o\u0012I(\u0001\u0003mC:<\'B\u0001B>\u0003\u0011Q\u0017M^1\n\t\u0005E!QO\u0001\raJ|G-^2u\u0003JLG/_\u000b\u0003\u0005\u0007\u00032!\u001bBC\u0013\r\u00119I\u001b\u0002\u0004\u0013:$\u0018A\u00049s_\u0012,8\r^#mK6,g\u000e\u001e\u000b\u0005\u0003#\u0013i\tC\u0005\u0003\u0010j\n\t\u00111\u0001\u0003\u0004\u0006\u0019\u0001\u0010J\u0019\u0002\u001fA\u0014x\u000eZ;di&#XM]1u_J,\"A!&\u0011\r\t]%\u0011TAI\u001b\t\ty$\u0003\u0003\u0003\u001c\u0006}\"\u0001C%uKJ\fGo\u001c:\u0002\u0011\r\fg.R9vC2$BA!)\u0003(B\u0019\u0011Na)\n\u0007\t\u0015&NA\u0004C_>dW-\u00198\t\u0013\t=E(!AA\u0002\u0005E\u0015A\u00059s_\u0012,8\r^#mK6,g\u000e\u001e(b[\u0016$BA!\u001d\u0003.\"I!qR\u001f\u0002\u0002\u0003\u0007!1Q\u0001\tQ\u0006\u001c\bnQ8eKR\u0011!1Q\u0001\ti>\u001cFO]5oOR\u0011!\u0011O\u0001\u0007KF,\u0018\r\\:\u0015\t\t\u0005&1\u0018\u0005\n\u0005\u001f\u0003\u0015\u0011!a\u0001\u0003#\u000bA\u0002V3ti\u000e\u000bgnY3mK\u0012\u0004\"A\u0019\"\u0014\u000b\t\u0013\u0019Ma4\u0011K\t\u0015\'1\u001a?\u0002\u0006\u0005\u0015\u0011QAA\u0012\u0003\u000b\t)!a\u000e\u0002T\u0005\u0005\u0014qNA?\u0003G\ty)!\u0002\u0002d\u0005\u001dVB\u0001Bd\u0015\r\u0011IM[\u0001\beVtG/[7f\u0013\u0011\u0011iMa2\u0003%\u0005\u00137\u000f\u001e:bGR4UO\\2uS>t\u0017G\u000e\t\u0005\u0005#\u00149.\u0004\u0002\u0003T*!!Q\u001bB=\u0003\tIw.C\u0002y\u0005\'$\"Aa0\u0002\u000b\u0005\u0004\b\u000f\\=\u0015E\u0005\u001d&q\u001cBq\u0005G\u0014)Oa:\u0003j\n-(Q\u001eBx\u0005c\u0014\u0019P!>\u0003x\ne(1 B\u007f\u0011\u0015QX\t1\u0001}\u0011\u001d\t\t!\u0012a\u0001\u0003\u000bAq!a\u0006F\u0001\u0004\t)\u0001C\u0004\u0002\u001c\u0015\u0003\r!!\u0002\t\u000f\u0005}Q\t1\u0001\u0002$!9\u00111F#A\u0002\u0005\u0015\u0001bBA\u0018\u000b\u0002\u0007\u0011Q\u0001\u0005\b\u0003g)\u0005\u0019AA\u001c\u0011%\ty%\u0012I\u0001\u0002\u0004\t\u0019\u0006C\u0005\u0002^\u0015\u0003\n\u00111\u0001\u0002b!I\u00111N#\u0011\u0002\u0003\u0007\u0011q\u000e\u0005\n\u0003s*\u0005\u0013!a\u0001\u0003{B\u0011\"a\"F!\u0003\u0005\r!a\t\t\u0013\u0005-U\t%AA\u0002\u0005=\u0005\"CAM\u000bB\u0005\t\u0019AA\u0003\u0011%\ti*\u0012I\u0001\u0002\u0004\t\u0019\'A\bbaBd\u0017\u0010\n3fM\u0006,H\u000e\u001e\u0013:\u0003A\t\u0007\u000f\u001d7zI\u0011,g-Y;mi\u0012\n\u0004\'\u0001\tbaBd\u0017\u0010\n3fM\u0006,H\u000e\u001e\u00132c\u0005\u0001\u0012\r\u001d9ms\u0012\"WMZ1vYR$\u0013GM\u0001\u0011CB\u0004H.\u001f\u0013eK\u001a\fW\u000f\u001c;%cM\n\u0001#\u00199qYf$C-\u001a4bk2$H%\r\u001b\u0002!\u0005\u0004\b\u000f\\=%I\u00164\u0017-\u001e7uIE*\u0014\u0001E1qa2LH\u0005Z3gCVdG\u000fJ\u00197\u0003\u001d)h.\u00199qYf$Baa\u0005\u0004\u001cA)\u0011.!\n\u0004\u0016A\u0011\u0013na\u0006}\u0003\u000b\t)!!\u0002\u0002$\u0005\u0015\u0011QAA\u001c\u0003\'\n\t\'a\u001c\u0002~\u0005\r\u0012qRA\u0003\u0003GJ1a!\u0007k\u0005\u001d!V\u000f\u001d7fcYB\u0011b!\bO\u0003\u0003\u0005\r!a*\u0002\u0007a$\u0003\'A\u000e%Y\u0016\u001c8/\u001b8ji\u0012:\'/Z1uKJ$C-\u001a4bk2$H%O\u0001\u001dI1,7o]5oSR$sM]3bi\u0016\u0014H\u0005Z3gCVdG\u000fJ\u00191\u0003q!C.Z:tS:LG\u000fJ4sK\u0006$XM\u001d\u0013eK\u001a\fW\u000f\u001c;%cE\nA\u0004\n7fgNLg.\u001b;%OJ,\u0017\r^3sI\u0011,g-Y;mi\u0012\n$\'\u0001\u000f%Y\u0016\u001c8/\u001b8ji\u0012:\'/Z1uKJ$C-\u001a4bk2$H%M\u001a\u00029\u0011bWm]:j]&$He\u001a:fCR,\'\u000f\n3fM\u0006,H\u000e\u001e\u00132i\u0005aB\u0005\\3tg&t\u0017\u000e\u001e\u0013he\u0016\fG/\u001a:%I\u00164\u0017-\u001e7uIE*\u0014\u0001\b\u0013mKN\u001c\u0018N\\5uI\u001d\u0014X-\u0019;fe\u0012\"WMZ1vYR$\u0013GN\u0001\roJLG/\u001a*fa2\f7-\u001a\u000b\u0003\u0007g\u0001BAa\u001d\u00046%!1q\u0007B;\u0005\u0019y%M[3di\u0002"
    )
BootstrapMethods:
  0: #287 REF_invokeStatic java/lang/invoke/LambdaMetafactory.altMetafactory:(Ljava/lang/invoke/MethodHandles$Lookup;Ljava/lang/String;Ljava/lang/invoke/MethodType;[Ljava/lang/Object;)Ljava/lang/invoke/CallSite;
    Method arguments:
      #272 (Ljava/lang/Object;)Ljava/lang/Object;
      #277 REF_invokeStatic org/scalatest/events/TestCanceled.$anonfun$toXml$4:(Lorg/scalatest/events/RecordableEvent;)Lscala/xml/Elem;
      #278 (Lorg/scalatest/events/RecordableEvent;)Lscala/xml/Elem;
      #279 5
      #280 1
      #278 (Lorg/scalatest/events/RecordableEvent;)Lscala/xml/Elem;
  1: #287 REF_invokeStatic java/lang/invoke/LambdaMetafactory.altMetafactory:(Ljava/lang/invoke/MethodHandles$Lookup;Ljava/lang/String;Ljava/lang/invoke/MethodType;[Ljava/lang/Object;)Ljava/lang/invoke/CallSite;
    Method arguments:
      #378 ()Ljava/lang/Object;
      #382 REF_invokeStatic org/scalatest/events/TestCanceled.$anonfun$toJson$7:()Ljava/lang/String;
      #383 ()Ljava/lang/String;
      #279 5
      #280 1
      #383 ()Ljava/lang/String;
  2: #287 REF_invokeStatic java/lang/invoke/LambdaMetafactory.altMetafactory:(Ljava/lang/invoke/MethodHandles$Lookup;Ljava/lang/String;Ljava/lang/invoke/MethodType;[Ljava/lang/Object;)Ljava/lang/invoke/CallSite;
    Method arguments:
      #272 (Ljava/lang/Object;)Ljava/lang/Object;
      #406 REF_invokeStatic org/scalatest/events/TestCanceled.$anonfun$toJson$8:(Lorg/scalatest/events/RecordableEvent;)Ljava/lang/String;
      #407 (Lorg/scalatest/events/RecordableEvent;)Ljava/lang/String;
      #279 5
      #280 1
      #407 (Lorg/scalatest/events/RecordableEvent;)Ljava/lang/String;
  3: #675 REF_invokeStatic scala/runtime/LambdaDeserialize.bootstrap:(Ljava/lang/invoke/MethodHandles$Lookup;Ljava/lang/String;Ljava/lang/invoke/MethodType;[Ljava/lang/invoke/MethodHandle;)Ljava/lang/invoke/CallSite;
    Method arguments:
      #382 REF_invokeStatic org/scalatest/events/TestCanceled.$anonfun$toJson$7:()Ljava/lang/String;
      #406 REF_invokeStatic org/scalatest/events/TestCanceled.$anonfun$toJson$8:(Lorg/scalatest/events/RecordableEvent;)Ljava/lang/String;
      #277 REF_invokeStatic org/scalatest/events/TestCanceled.$anonfun$toXml$4:(Lorg/scalatest/events/RecordableEvent;)Lscala/xml/Elem;
  ScalaInlineInfo: length = 0x108 (unknown attribute)
   01 01 00 34 01 7B 00 41 01 01 92 01 93 01 01 11
   01 12 01 00 C4 02 12 01 02 2E 02 2F 01 01 F5 00
   7C 01 01 C8 00 89 01 01 E0 00 45 01 01 E3 00 45
   01 01 E6 00 45 01 01 E9 00 45 01 01 EC 00 45 01
   01 EF 00 41 01 01 F2 00 37 01 01 CB 00 41 01 01
   CE 00 41 01 01 D1 00 41 01 01 D4 00 45 01 01 D7
   00 41 01 01 DA 00 41 01 01 DD 00 99 01 02 15 00
   45 01 00 2B 00 45 01 02 08 02 09 01 02 4F 02 2F
   01 00 2D 00 45 01 02 36 00 DC 01 00 2F 00 45 01
   00 1D 00 41 01 00 1B 00 89 01 00 32 00 45 01 02
   17 00 DC 01 02 18 02 19 01 02 31 02 32 01 02 22
   02 23 01 02 16 00 41 01 00 26 00 99 01 00 31 00
   45 01 00 21 00 45 01 00 20 00 41 01 00 1F 00 41
   01 00 24 00 41 01 00 25 00 41 01 00 33 00 41 01
   00 29 00 45 01 00 34 00 37 01 01 4C 00 41 01 01
   B7 00 41 01 00 AD 00 AE 01 01 C0 01 C5 01 01 C0
   01 C1 01 01 C4 01 C5 01
  ScalaSig: length = 0x3 (unknown attribute)
   05 02 00
