Classfile /Users/mw/Projects/slang-braindump/.jar/jar8/assemble/slang-braindump/assemble/content/org/scalatest/events/TestFailed$.class
  Last modified May 29, 2022; size 8123 bytes
  SHA-256 checksum 651ed91fd0143784c6eb94219a6ee0d73bfde775cb1fe5fa109ed3022eb72f37
  Compiled from "Event.scala"
public final class org.scalatest.events.TestFailed$ extends scala.runtime.AbstractFunction17<org.scalatest.events.Ordinal, java.lang.String, java.lang.String, java.lang.String, scala.Option<java.lang.String>, java.lang.String, java.lang.String, scala.collection.immutable.IndexedSeq<org.scalatest.events.RecordableEvent>, scala.collection.immutable.IndexedSeq<java.lang.String>, scala.Option<java.lang.Throwable>, scala.Option<java.lang.Object>, scala.Option<org.scalatest.events.Formatter>, scala.Option<org.scalatest.events.Location>, scala.Option<java.lang.String>, scala.Option<java.lang.Object>, java.lang.String, java.lang.Object, org.scalatest.events.TestFailed> implements java.io.Serializable
  minor version: 0
  major version: 52
  flags: (0x0031) ACC_PUBLIC, ACC_FINAL, ACC_SUPER
  this_class: #2                          // org/scalatest/events/TestFailed$
  super_class: #5                         // scala/runtime/AbstractFunction17
  interfaces: 1, fields: 1, methods: 23, attributes: 4
Constant pool:
    #1 = Utf8               org/scalatest/events/TestFailed$
    #2 = Class              #1            // org/scalatest/events/TestFailed$
    #3 = Utf8               Lscala/runtime/AbstractFunction17<Lorg/scalatest/events/Ordinal;Ljava/lang/String;Ljava/lang/String;Ljava/lang/String;Lscala/Option<Ljava/lang/String;>;Ljava/lang/String;Ljava/lang/String;Lscala/collection/immutable/IndexedSeq<Lorg/scalatest/events/RecordableEvent;>;Lscala/collection/immutable/IndexedSeq<Ljava/lang/String;>;Lscala/Option<Ljava/lang/Throwable;>;Lscala/Option<Ljava/lang/Object;>;Lscala/Option<Lorg/scalatest/events/Formatter;>;Lscala/Option<Lorg/scalatest/events/Location;>;Lscala/Option<Ljava/lang/String;>;Lscala/Option<Ljava/lang/Object;>;Ljava/lang/String;Ljava/lang/Object;Lorg/scalatest/events/TestFailed;>;Ljava/io/Serializable;
    #4 = Utf8               scala/runtime/AbstractFunction17
    #5 = Class              #4            // scala/runtime/AbstractFunction17
    #6 = Utf8               java/io/Serializable
    #7 = Class              #6            // java/io/Serializable
    #8 = Utf8               Event.scala
    #9 = Utf8               MODULE$
   #10 = Utf8               Lorg/scalatest/events/TestFailed$;
   #11 = Utf8               <clinit>
   #12 = Utf8               ()V
   #13 = Utf8               <init>
   #14 = NameAndType        #13:#12       // "<init>":()V
   #15 = Methodref          #2.#14        // org/scalatest/events/TestFailed$."<init>":()V
   #16 = NameAndType        #9:#10        // MODULE$:Lorg/scalatest/events/TestFailed$;
   #17 = Fieldref           #2.#16        // org/scalatest/events/TestFailed$.MODULE$:Lorg/scalatest/events/TestFailed$;
   #18 = Utf8               $lessinit$greater$default$10
   #19 = Utf8               ()Lscala/Option;
   #20 = Utf8               ()Lscala/Option<Ljava/lang/Throwable;>;
   #21 = Utf8               scala/None$
   #22 = Class              #21           // scala/None$
   #23 = Utf8               Lscala/None$;
   #24 = NameAndType        #9:#23        // MODULE$:Lscala/None$;
   #25 = Fieldref           #22.#24       // scala/None$.MODULE$:Lscala/None$;
   #26 = Utf8               this
   #27 = Utf8               $lessinit$greater$default$11
   #28 = Utf8               ()Lscala/Option<Ljava/lang/Object;>;
   #29 = Utf8               $lessinit$greater$default$12
   #30 = Utf8               ()Lscala/Option<Lorg/scalatest/events/Formatter;>;
   #31 = Utf8               $lessinit$greater$default$13
   #32 = Utf8               ()Lscala/Option<Lorg/scalatest/events/Location;>;
   #33 = Utf8               $lessinit$greater$default$14
   #34 = Utf8               ()Lscala/Option<Ljava/lang/String;>;
   #35 = Utf8               $lessinit$greater$default$15
   #36 = Utf8               $lessinit$greater$default$16
   #37 = Utf8               ()Ljava/lang/String;
   #38 = Utf8               java/lang/Thread
   #39 = Class              #38           // java/lang/Thread
   #40 = Utf8               currentThread
   #41 = Utf8               ()Ljava/lang/Thread;
   #42 = NameAndType        #40:#41       // currentThread:()Ljava/lang/Thread;
   #43 = Methodref          #39.#42       // java/lang/Thread.currentThread:()Ljava/lang/Thread;
   #44 = Utf8               getName
   #45 = NameAndType        #44:#37       // getName:()Ljava/lang/String;
   #46 = Methodref          #39.#45       // java/lang/Thread.getName:()Ljava/lang/String;
   #47 = Utf8               $lessinit$greater$default$17
   #48 = Utf8               ()J
   #49 = Utf8               java/util/Date
   #50 = Class              #49           // java/util/Date
   #51 = Methodref          #50.#14       // java/util/Date."<init>":()V
   #52 = Utf8               getTime
   #53 = NameAndType        #52:#48       // getTime:()J
   #54 = Methodref          #50.#53       // java/util/Date.getTime:()J
   #55 = Utf8               toString
   #56 = Utf8               TestFailed
   #57 = String             #56           // TestFailed
   #58 = Utf8               apply
   #59 = Utf8               (Lorg/scalatest/events/Ordinal;Ljava/lang/String;Ljava/lang/String;Ljava/lang/String;Lscala/Option;Ljava/lang/String;Ljava/lang/String;Lscala/collection/immutable/IndexedSeq;Lscala/collection/immutable/IndexedSeq;Lscala/Option;Lscala/Option;Lscala/Option;Lscala/Option;Lscala/Option;Lscala/Option;Ljava/lang/String;J)Lorg/scalatest/events/TestFailed;
   #60 = Utf8               (Lorg/scalatest/events/Ordinal;Ljava/lang/String;Ljava/lang/String;Ljava/lang/String;Lscala/Option<Ljava/lang/String;>;Ljava/lang/String;Ljava/lang/String;Lscala/collection/immutable/IndexedSeq<Lorg/scalatest/events/RecordableEvent;>;Lscala/collection/immutable/IndexedSeq<Ljava/lang/String;>;Lscala/Option<Ljava/lang/Throwable;>;Lscala/Option<Ljava/lang/Object;>;Lscala/Option<Lorg/scalatest/events/Formatter;>;Lscala/Option<Lorg/scalatest/events/Location;>;Lscala/Option<Ljava/lang/String;>;Lscala/Option<Ljava/lang/Object;>;Ljava/lang/String;J)Lorg/scalatest/events/TestFailed;
   #61 = Utf8               ordinal
   #62 = Utf8               message
   #63 = Utf8               suiteName
   #64 = Utf8               suiteId
   #65 = Utf8               suiteClassName
   #66 = Utf8               testName
   #67 = Utf8               testText
   #68 = Utf8               recordedEvents
   #69 = Utf8               analysis
   #70 = Utf8               throwable
   #71 = Utf8               duration
   #72 = Utf8               formatter
   #73 = Utf8               location
   #74 = Utf8               rerunner
   #75 = Utf8               payload
   #76 = Utf8               threadName
   #77 = Utf8               timeStamp
   #78 = Utf8               org/scalatest/events/TestFailed
   #79 = Class              #78           // org/scalatest/events/TestFailed
   #80 = Utf8               (Lorg/scalatest/events/Ordinal;Ljava/lang/String;Ljava/lang/String;Ljava/lang/String;Lscala/Option;Ljava/lang/String;Ljava/lang/String;Lscala/collection/immutable/IndexedSeq;Lscala/collection/immutable/IndexedSeq;Lscala/Option;Lscala/Option;Lscala/Option;Lscala/Option;Lscala/Option;Lscala/Option;Ljava/lang/String;J)V
   #81 = NameAndType        #13:#80       // "<init>":(Lorg/scalatest/events/Ordinal;Ljava/lang/String;Ljava/lang/String;Ljava/lang/String;Lscala/Option;Ljava/lang/String;Ljava/lang/String;Lscala/collection/immutable/IndexedSeq;Lscala/collection/immutable/IndexedSeq;Lscala/Option;Lscala/Option;Lscala/Option;Lscala/Option;Lscala/Option;Lscala/Option;Ljava/lang/String;J)V
   #82 = Methodref          #79.#81       // org/scalatest/events/TestFailed."<init>":(Lorg/scalatest/events/Ordinal;Ljava/lang/String;Ljava/lang/String;Ljava/lang/String;Lscala/Option;Ljava/lang/String;Ljava/lang/String;Lscala/collection/immutable/IndexedSeq;Lscala/collection/immutable/IndexedSeq;Lscala/Option;Lscala/Option;Lscala/Option;Lscala/Option;Lscala/Option;Lscala/Option;Ljava/lang/String;J)V
   #83 = Utf8               Lorg/scalatest/events/Ordinal;
   #84 = Utf8               Ljava/lang/String;
   #85 = Utf8               Lscala/Option;
   #86 = Utf8               Lscala/collection/immutable/IndexedSeq;
   #87 = Utf8               J
   #88 = Utf8               apply$default$10
   #89 = Utf8               apply$default$11
   #90 = Utf8               apply$default$12
   #91 = Utf8               apply$default$13
   #92 = Utf8               apply$default$14
   #93 = Utf8               apply$default$15
   #94 = Utf8               apply$default$16
   #95 = Utf8               apply$default$17
   #96 = Utf8               unapply
   #97 = Utf8               (Lorg/scalatest/events/TestFailed;)Lscala/Option;
   #98 = Utf8               (Lorg/scalatest/events/TestFailed;)Lscala/Option<Lscala/Tuple17<Lorg/scalatest/events/Ordinal;Ljava/lang/String;Ljava/lang/String;Ljava/lang/String;Lscala/Option<Ljava/lang/String;>;Ljava/lang/String;Ljava/lang/String;Lscala/collection/immutable/IndexedSeq<Lorg/scalatest/events/RecordableEvent;>;Lscala/collection/immutable/IndexedSeq<Ljava/lang/String;>;Lscala/Option<Ljava/lang/Throwable;>;Lscala/Option<Ljava/lang/Object;>;Lscala/Option<Lorg/scalatest/events/Formatter;>;Lscala/Option<Lorg/scalatest/events/Location;>;Lscala/Option<Ljava/lang/String;>;Lscala/Option<Ljava/lang/Object;>;Ljava/lang/String;Ljava/lang/Object;>;>;
   #99 = Utf8               x$0
  #100 = Utf8               scala/Some
  #101 = Class              #100          // scala/Some
  #102 = Utf8               scala/Tuple17
  #103 = Class              #102          // scala/Tuple17
  #104 = Utf8               ()Lorg/scalatest/events/Ordinal;
  #105 = NameAndType        #61:#104      // ordinal:()Lorg/scalatest/events/Ordinal;
  #106 = Methodref          #79.#105      // org/scalatest/events/TestFailed.ordinal:()Lorg/scalatest/events/Ordinal;
  #107 = NameAndType        #62:#37       // message:()Ljava/lang/String;
  #108 = Methodref          #79.#107      // org/scalatest/events/TestFailed.message:()Ljava/lang/String;
  #109 = NameAndType        #63:#37       // suiteName:()Ljava/lang/String;
  #110 = Methodref          #79.#109      // org/scalatest/events/TestFailed.suiteName:()Ljava/lang/String;
  #111 = NameAndType        #64:#37       // suiteId:()Ljava/lang/String;
  #112 = Methodref          #79.#111      // org/scalatest/events/TestFailed.suiteId:()Ljava/lang/String;
  #113 = NameAndType        #65:#19       // suiteClassName:()Lscala/Option;
  #114 = Methodref          #79.#113      // org/scalatest/events/TestFailed.suiteClassName:()Lscala/Option;
  #115 = NameAndType        #66:#37       // testName:()Ljava/lang/String;
  #116 = Methodref          #79.#115      // org/scalatest/events/TestFailed.testName:()Ljava/lang/String;
  #117 = NameAndType        #67:#37       // testText:()Ljava/lang/String;
  #118 = Methodref          #79.#117      // org/scalatest/events/TestFailed.testText:()Ljava/lang/String;
  #119 = Utf8               ()Lscala/collection/immutable/IndexedSeq;
  #120 = NameAndType        #68:#119      // recordedEvents:()Lscala/collection/immutable/IndexedSeq;
  #121 = Methodref          #79.#120      // org/scalatest/events/TestFailed.recordedEvents:()Lscala/collection/immutable/IndexedSeq;
  #122 = NameAndType        #69:#119      // analysis:()Lscala/collection/immutable/IndexedSeq;
  #123 = Methodref          #79.#122      // org/scalatest/events/TestFailed.analysis:()Lscala/collection/immutable/IndexedSeq;
  #124 = NameAndType        #70:#19       // throwable:()Lscala/Option;
  #125 = Methodref          #79.#124      // org/scalatest/events/TestFailed.throwable:()Lscala/Option;
  #126 = NameAndType        #71:#19       // duration:()Lscala/Option;
  #127 = Methodref          #79.#126      // org/scalatest/events/TestFailed.duration:()Lscala/Option;
  #128 = NameAndType        #72:#19       // formatter:()Lscala/Option;
  #129 = Methodref          #79.#128      // org/scalatest/events/TestFailed.formatter:()Lscala/Option;
  #130 = NameAndType        #73:#19       // location:()Lscala/Option;
  #131 = Methodref          #79.#130      // org/scalatest/events/TestFailed.location:()Lscala/Option;
  #132 = NameAndType        #74:#19       // rerunner:()Lscala/Option;
  #133 = Methodref          #79.#132      // org/scalatest/events/TestFailed.rerunner:()Lscala/Option;
  #134 = NameAndType        #75:#19       // payload:()Lscala/Option;
  #135 = Methodref          #79.#134      // org/scalatest/events/TestFailed.payload:()Lscala/Option;
  #136 = NameAndType        #76:#37       // threadName:()Ljava/lang/String;
  #137 = Methodref          #79.#136      // org/scalatest/events/TestFailed.threadName:()Ljava/lang/String;
  #138 = NameAndType        #77:#48       // timeStamp:()J
  #139 = Methodref          #79.#138      // org/scalatest/events/TestFailed.timeStamp:()J
  #140 = Utf8               scala/runtime/BoxesRunTime
  #141 = Class              #140          // scala/runtime/BoxesRunTime
  #142 = Utf8               boxToLong
  #143 = Utf8               (J)Ljava/lang/Long;
  #144 = NameAndType        #142:#143     // boxToLong:(J)Ljava/lang/Long;
  #145 = Methodref          #141.#144     // scala/runtime/BoxesRunTime.boxToLong:(J)Ljava/lang/Long;
  #146 = Utf8               (Ljava/lang/Object;Ljava/lang/Object;Ljava/lang/Object;Ljava/lang/Object;Ljava/lang/Object;Ljava/lang/Object;Ljava/lang/Object;Ljava/lang/Object;Ljava/lang/Object;Ljava/lang/Object;Ljava/lang/Object;Ljava/lang/Object;Ljava/lang/Object;Ljava/lang/Object;Ljava/lang/Object;Ljava/lang/Object;Ljava/lang/Object;)V
  #147 = NameAndType        #13:#146      // "<init>":(Ljava/lang/Object;Ljava/lang/Object;Ljava/lang/Object;Ljava/lang/Object;Ljava/lang/Object;Ljava/lang/Object;Ljava/lang/Object;Ljava/lang/Object;Ljava/lang/Object;Ljava/lang/Object;Ljava/lang/Object;Ljava/lang/Object;Ljava/lang/Object;Ljava/lang/Object;Ljava/lang/Object;Ljava/lang/Object;Ljava/lang/Object;)V
  #148 = Methodref          #103.#147     // scala/Tuple17."<init>":(Ljava/lang/Object;Ljava/lang/Object;Ljava/lang/Object;Ljava/lang/Object;Ljava/lang/Object;Ljava/lang/Object;Ljava/lang/Object;Ljava/lang/Object;Ljava/lang/Object;Ljava/lang/Object;Ljava/lang/Object;Ljava/lang/Object;Ljava/lang/Object;Ljava/lang/Object;Ljava/lang/Object;Ljava/lang/Object;Ljava/lang/Object;)V
  #149 = Utf8               (Ljava/lang/Object;)V
  #150 = NameAndType        #13:#149      // "<init>":(Ljava/lang/Object;)V
  #151 = Methodref          #101.#150     // scala/Some."<init>":(Ljava/lang/Object;)V
  #152 = Utf8               Lorg/scalatest/events/TestFailed;
  #153 = Utf8               scala/Option
  #154 = Class              #153          // scala/Option
  #155 = Utf8               writeReplace
  #156 = Utf8               ()Ljava/lang/Object;
  #157 = Utf8               scala/runtime/ModuleSerializationProxy
  #158 = Class              #157          // scala/runtime/ModuleSerializationProxy
  #159 = Utf8               (Ljava/lang/Class;)V
  #160 = NameAndType        #13:#159      // "<init>":(Ljava/lang/Class;)V
  #161 = Methodref          #158.#160     // scala/runtime/ModuleSerializationProxy."<init>":(Ljava/lang/Class;)V
  #162 = Utf8               (Ljava/lang/Object;Ljava/lang/Object;Ljava/lang/Object;Ljava/lang/Object;Ljava/lang/Object;Ljava/lang/Object;Ljava/lang/Object;Ljava/lang/Object;Ljava/lang/Object;Ljava/lang/Object;Ljava/lang/Object;Ljava/lang/Object;Ljava/lang/Object;Ljava/lang/Object;Ljava/lang/Object;Ljava/lang/Object;Ljava/lang/Object;)Ljava/lang/Object;
  #163 = Utf8               v1
  #164 = Utf8               v2
  #165 = Utf8               v3
  #166 = Utf8               v4
  #167 = Utf8               v5
  #168 = Utf8               v6
  #169 = Utf8               v7
  #170 = Utf8               v8
  #171 = Utf8               v9
  #172 = Utf8               v10
  #173 = Utf8               v11
  #174 = Utf8               v12
  #175 = Utf8               v13
  #176 = Utf8               v14
  #177 = Utf8               v15
  #178 = Utf8               v16
  #179 = Utf8               v17
  #180 = Utf8               org/scalatest/events/Ordinal
  #181 = Class              #180          // org/scalatest/events/Ordinal
  #182 = Utf8               java/lang/String
  #183 = Class              #182          // java/lang/String
  #184 = Utf8               scala/collection/immutable/IndexedSeq
  #185 = Class              #184          // scala/collection/immutable/IndexedSeq
  #186 = Utf8               unboxToLong
  #187 = Utf8               (Ljava/lang/Object;)J
  #188 = NameAndType        #186:#187     // unboxToLong:(Ljava/lang/Object;)J
  #189 = Methodref          #141.#188     // scala/runtime/BoxesRunTime.unboxToLong:(Ljava/lang/Object;)J
  #190 = NameAndType        #58:#59       // apply:(Lorg/scalatest/events/Ordinal;Ljava/lang/String;Ljava/lang/String;Ljava/lang/String;Lscala/Option;Ljava/lang/String;Ljava/lang/String;Lscala/collection/immutable/IndexedSeq;Lscala/collection/immutable/IndexedSeq;Lscala/Option;Lscala/Option;Lscala/Option;Lscala/Option;Lscala/Option;Lscala/Option;Ljava/lang/String;J)Lorg/scalatest/events/TestFailed;
  #191 = Methodref          #2.#190       // org/scalatest/events/TestFailed$.apply:(Lorg/scalatest/events/Ordinal;Ljava/lang/String;Ljava/lang/String;Ljava/lang/String;Lscala/Option;Ljava/lang/String;Ljava/lang/String;Lscala/collection/immutable/IndexedSeq;Lscala/collection/immutable/IndexedSeq;Lscala/Option;Lscala/Option;Lscala/Option;Lscala/Option;Lscala/Option;Lscala/Option;Ljava/lang/String;J)Lorg/scalatest/events/TestFailed;
  #192 = Utf8               Ljava/lang/Object;
  #193 = Methodref          #5.#14        // scala/runtime/AbstractFunction17."<init>":()V
  #194 = Utf8               Code
  #195 = Utf8               LineNumberTable
  #196 = Utf8               LocalVariableTable
  #197 = Utf8               Signature
  #198 = Utf8               MethodParameters
  #199 = Utf8               StackMapTable
  #200 = Utf8               SourceFile
  #201 = Utf8               ScalaInlineInfo
  #202 = Utf8               Scala
{
  public static final org.scalatest.events.TestFailed$ MODULE$;
    descriptor: Lorg/scalatest/events/TestFailed$;
    flags: (0x0019) ACC_PUBLIC, ACC_STATIC, ACC_FINAL

  public static {};
    descriptor: ()V
    flags: (0x0009) ACC_PUBLIC, ACC_STATIC
    Code:
      stack=2, locals=0, args_size=0
         0: new           #2                  // class org/scalatest/events/TestFailed$
         3: dup
         4: invokespecial #15                 // Method "<init>":()V
         7: putstatic     #17                 // Field MODULE$:Lorg/scalatest/events/TestFailed$;
        10: return
      LineNumberTable:
        line 605: 0

  public scala.Option<java.lang.Throwable> $lessinit$greater$default$10();
    descriptor: ()Lscala/Option;
    flags: (0x0001) ACC_PUBLIC
    Code:
      stack=1, locals=1, args_size=1
         0: getstatic     #25                 // Field scala/None$.MODULE$:Lscala/None$;
         3: areturn
      LineNumberTable:
        line 615: 0
      LocalVariableTable:
        Start  Length  Slot  Name   Signature
            0       4     0  this   Lorg/scalatest/events/TestFailed$;
    Signature: #20                          // ()Lscala/Option<Ljava/lang/Throwable;>;

  public scala.Option<java.lang.Object> $lessinit$greater$default$11();
    descriptor: ()Lscala/Option;
    flags: (0x0001) ACC_PUBLIC
    Code:
      stack=1, locals=1, args_size=1
         0: getstatic     #25                 // Field scala/None$.MODULE$:Lscala/None$;
         3: areturn
      LineNumberTable:
        line 616: 0
      LocalVariableTable:
        Start  Length  Slot  Name   Signature
            0       4     0  this   Lorg/scalatest/events/TestFailed$;
    Signature: #28                          // ()Lscala/Option<Ljava/lang/Object;>;

  public scala.Option<org.scalatest.events.Formatter> $lessinit$greater$default$12();
    descriptor: ()Lscala/Option;
    flags: (0x0001) ACC_PUBLIC
    Code:
      stack=1, locals=1, args_size=1
         0: getstatic     #25                 // Field scala/None$.MODULE$:Lscala/None$;
         3: areturn
      LineNumberTable:
        line 617: 0
      LocalVariableTable:
        Start  Length  Slot  Name   Signature
            0       4     0  this   Lorg/scalatest/events/TestFailed$;
    Signature: #30                          // ()Lscala/Option<Lorg/scalatest/events/Formatter;>;

  public scala.Option<org.scalatest.events.Location> $lessinit$greater$default$13();
    descriptor: ()Lscala/Option;
    flags: (0x0001) ACC_PUBLIC
    Code:
      stack=1, locals=1, args_size=1
         0: getstatic     #25                 // Field scala/None$.MODULE$:Lscala/None$;
         3: areturn
      LineNumberTable:
        line 618: 0
      LocalVariableTable:
        Start  Length  Slot  Name   Signature
            0       4     0  this   Lorg/scalatest/events/TestFailed$;
    Signature: #32                          // ()Lscala/Option<Lorg/scalatest/events/Location;>;

  public scala.Option<java.lang.String> $lessinit$greater$default$14();
    descriptor: ()Lscala/Option;
    flags: (0x0001) ACC_PUBLIC
    Code:
      stack=1, locals=1, args_size=1
         0: getstatic     #25                 // Field scala/None$.MODULE$:Lscala/None$;
         3: areturn
      LineNumberTable:
        line 619: 0
      LocalVariableTable:
        Start  Length  Slot  Name   Signature
            0       4     0  this   Lorg/scalatest/events/TestFailed$;
    Signature: #34                          // ()Lscala/Option<Ljava/lang/String;>;

  public scala.Option<java.lang.Object> $lessinit$greater$default$15();
    descriptor: ()Lscala/Option;
    flags: (0x0001) ACC_PUBLIC
    Code:
      stack=1, locals=1, args_size=1
         0: getstatic     #25                 // Field scala/None$.MODULE$:Lscala/None$;
         3: areturn
      LineNumberTable:
        line 620: 0
      LocalVariableTable:
        Start  Length  Slot  Name   Signature
            0       4     0  this   Lorg/scalatest/events/TestFailed$;
    Signature: #28                          // ()Lscala/Option<Ljava/lang/Object;>;

  public java.lang.String $lessinit$greater$default$16();
    descriptor: ()Ljava/lang/String;
    flags: (0x0001) ACC_PUBLIC
    Code:
      stack=1, locals=1, args_size=1
         0: invokestatic  #43                 // Method java/lang/Thread.currentThread:()Ljava/lang/Thread;
         3: invokevirtual #46                 // Method java/lang/Thread.getName:()Ljava/lang/String;
         6: areturn
      LineNumberTable:
        line 621: 0
      LocalVariableTable:
        Start  Length  Slot  Name   Signature
            0       7     0  this   Lorg/scalatest/events/TestFailed$;

  public long $lessinit$greater$default$17();
    descriptor: ()J
    flags: (0x0001) ACC_PUBLIC
    Code:
      stack=2, locals=1, args_size=1
         0: new           #50                 // class java/util/Date
         3: dup
         4: invokespecial #51                 // Method java/util/Date."<init>":()V
         7: invokevirtual #54                 // Method java/util/Date.getTime:()J
        10: lreturn
      LineNumberTable:
        line 622: 0
      LocalVariableTable:
        Start  Length  Slot  Name   Signature
            0      11     0  this   Lorg/scalatest/events/TestFailed$;

  public final java.lang.String toString();
    descriptor: ()Ljava/lang/String;
    flags: (0x0011) ACC_PUBLIC, ACC_FINAL
    Code:
      stack=1, locals=1, args_size=1
         0: ldc           #57                 // String TestFailed
         2: areturn
      LineNumberTable:
        line 605: 0
      LocalVariableTable:
        Start  Length  Slot  Name   Signature
            0       3     0  this   Lorg/scalatest/events/TestFailed$;

  public org.scalatest.events.TestFailed apply(org.scalatest.events.Ordinal, java.lang.String, java.lang.String, java.lang.String, scala.Option<java.lang.String>, java.lang.String, java.lang.String, scala.collection.immutable.IndexedSeq<org.scalatest.events.RecordableEvent>, scala.collection.immutable.IndexedSeq<java.lang.String>, scala.Option<java.lang.Throwable>, scala.Option<java.lang.Object>, scala.Option<org.scalatest.events.Formatter>, scala.Option<org.scalatest.events.Location>, scala.Option<java.lang.String>, scala.Option<java.lang.Object>, java.lang.String, long);
    descriptor: (Lorg/scalatest/events/Ordinal;Ljava/lang/String;Ljava/lang/String;Ljava/lang/String;Lscala/Option;Ljava/lang/String;Ljava/lang/String;Lscala/collection/immutable/IndexedSeq;Lscala/collection/immutable/IndexedSeq;Lscala/Option;Lscala/Option;Lscala/Option;Lscala/Option;Lscala/Option;Lscala/Option;Ljava/lang/String;J)Lorg/scalatest/events/TestFailed;
    flags: (0x0001) ACC_PUBLIC
    Code:
      stack=20, locals=19, args_size=18
         0: new           #79                 // class org/scalatest/events/TestFailed
         3: dup
         4: aload_1
         5: aload_2
         6: aload_3
         7: aload         4
         9: aload         5
        11: aload         6
        13: aload         7
        15: aload         8
        17: aload         9
        19: aload         10
        21: aload         11
        23: aload         12
        25: aload         13
        27: aload         14
        29: aload         15
        31: aload         16
        33: lload         17
        35: invokespecial #82                 // Method org/scalatest/events/TestFailed."<init>":(Lorg/scalatest/events/Ordinal;Ljava/lang/String;Ljava/lang/String;Ljava/lang/String;Lscala/Option;Ljava/lang/String;Ljava/lang/String;Lscala/collection/immutable/IndexedSeq;Lscala/collection/immutable/IndexedSeq;Lscala/Option;Lscala/Option;Lscala/Option;Lscala/Option;Lscala/Option;Lscala/Option;Ljava/lang/String;J)V
        38: areturn
      LineNumberTable:
        line 605: 0
      LocalVariableTable:
        Start  Length  Slot  Name   Signature
            0      39     0  this   Lorg/scalatest/events/TestFailed$;
            0      39     1 ordinal   Lorg/scalatest/events/Ordinal;
            0      39     2 message   Ljava/lang/String;
            0      39     3 suiteName   Ljava/lang/String;
            0      39     4 suiteId   Ljava/lang/String;
            0      39     5 suiteClassName   Lscala/Option;
            0      39     6 testName   Ljava/lang/String;
            0      39     7 testText   Ljava/lang/String;
            0      39     8 recordedEvents   Lscala/collection/immutable/IndexedSeq;
            0      39     9 analysis   Lscala/collection/immutable/IndexedSeq;
            0      39    10 throwable   Lscala/Option;
            0      39    11 duration   Lscala/Option;
            0      39    12 formatter   Lscala/Option;
            0      39    13 location   Lscala/Option;
            0      39    14 rerunner   Lscala/Option;
            0      39    15 payload   Lscala/Option;
            0      39    16 threadName   Ljava/lang/String;
            0      39    17 timeStamp   J
    Signature: #60                          // (Lorg/scalatest/events/Ordinal;Ljava/lang/String;Ljava/lang/String;Ljava/lang/String;Lscala/Option<Ljava/lang/String;>;Ljava/lang/String;Ljava/lang/String;Lscala/collection/immutable/IndexedSeq<Lorg/scalatest/events/RecordableEvent;>;Lscala/collection/immutable/IndexedSeq<Ljava/lang/String;>;Lscala/Option<Ljava/lang/Throwable;>;Lscala/Option<Ljava/lang/Object;>;Lscala/Option<Lorg/scalatest/events/Formatter;>;Lscala/Option<Lorg/scalatest/events/Location;>;Lscala/Option<Ljava/lang/String;>;Lscala/Option<Ljava/lang/Object;>;Ljava/lang/String;J)Lorg/scalatest/events/TestFailed;
    MethodParameters:
      Name                           Flags
      ordinal                        final
      message                        final
      suiteName                      final
      suiteId                        final
      suiteClassName                 final
      testName                       final
      testText                       final
      recordedEvents                 final
      analysis                       final
      throwable                      final
      duration                       final
      formatter                      final
      location                       final
      rerunner                       final
      payload                        final
      threadName                     final
      timeStamp                      final

  public scala.Option<java.lang.Throwable> apply$default$10();
    descriptor: ()Lscala/Option;
    flags: (0x0001) ACC_PUBLIC
    Code:
      stack=1, locals=1, args_size=1
         0: getstatic     #25                 // Field scala/None$.MODULE$:Lscala/None$;
         3: areturn
      LineNumberTable:
        line 615: 0
      LocalVariableTable:
        Start  Length  Slot  Name   Signature
            0       4     0  this   Lorg/scalatest/events/TestFailed$;
    Signature: #20                          // ()Lscala/Option<Ljava/lang/Throwable;>;

  public scala.Option<java.lang.Object> apply$default$11();
    descriptor: ()Lscala/Option;
    flags: (0x0001) ACC_PUBLIC
    Code:
      stack=1, locals=1, args_size=1
         0: getstatic     #25                 // Field scala/None$.MODULE$:Lscala/None$;
         3: areturn
      LineNumberTable:
        line 616: 0
      LocalVariableTable:
        Start  Length  Slot  Name   Signature
            0       4     0  this   Lorg/scalatest/events/TestFailed$;
    Signature: #28                          // ()Lscala/Option<Ljava/lang/Object;>;

  public scala.Option<org.scalatest.events.Formatter> apply$default$12();
    descriptor: ()Lscala/Option;
    flags: (0x0001) ACC_PUBLIC
    Code:
      stack=1, locals=1, args_size=1
         0: getstatic     #25                 // Field scala/None$.MODULE$:Lscala/None$;
         3: areturn
      LineNumberTable:
        line 617: 0
      LocalVariableTable:
        Start  Length  Slot  Name   Signature
            0       4     0  this   Lorg/scalatest/events/TestFailed$;
    Signature: #30                          // ()Lscala/Option<Lorg/scalatest/events/Formatter;>;

  public scala.Option<org.scalatest.events.Location> apply$default$13();
    descriptor: ()Lscala/Option;
    flags: (0x0001) ACC_PUBLIC
    Code:
      stack=1, locals=1, args_size=1
         0: getstatic     #25                 // Field scala/None$.MODULE$:Lscala/None$;
         3: areturn
      LineNumberTable:
        line 618: 0
      LocalVariableTable:
        Start  Length  Slot  Name   Signature
            0       4     0  this   Lorg/scalatest/events/TestFailed$;
    Signature: #32                          // ()Lscala/Option<Lorg/scalatest/events/Location;>;

  public scala.Option<java.lang.String> apply$default$14();
    descriptor: ()Lscala/Option;
    flags: (0x0001) ACC_PUBLIC
    Code:
      stack=1, locals=1, args_size=1
         0: getstatic     #25                 // Field scala/None$.MODULE$:Lscala/None$;
         3: areturn
      LineNumberTable:
        line 619: 0
      LocalVariableTable:
        Start  Length  Slot  Name   Signature
            0       4     0  this   Lorg/scalatest/events/TestFailed$;
    Signature: #34                          // ()Lscala/Option<Ljava/lang/String;>;

  public scala.Option<java.lang.Object> apply$default$15();
    descriptor: ()Lscala/Option;
    flags: (0x0001) ACC_PUBLIC
    Code:
      stack=1, locals=1, args_size=1
         0: getstatic     #25                 // Field scala/None$.MODULE$:Lscala/None$;
         3: areturn
      LineNumberTable:
        line 620: 0
      LocalVariableTable:
        Start  Length  Slot  Name   Signature
            0       4     0  this   Lorg/scalatest/events/TestFailed$;
    Signature: #28                          // ()Lscala/Option<Ljava/lang/Object;>;

  public java.lang.String apply$default$16();
    descriptor: ()Ljava/lang/String;
    flags: (0x0001) ACC_PUBLIC
    Code:
      stack=1, locals=1, args_size=1
         0: invokestatic  #43                 // Method java/lang/Thread.currentThread:()Ljava/lang/Thread;
         3: invokevirtual #46                 // Method java/lang/Thread.getName:()Ljava/lang/String;
         6: areturn
      LineNumberTable:
        line 621: 0
      LocalVariableTable:
        Start  Length  Slot  Name   Signature
            0       7     0  this   Lorg/scalatest/events/TestFailed$;

  public long apply$default$17();
    descriptor: ()J
    flags: (0x0001) ACC_PUBLIC
    Code:
      stack=2, locals=1, args_size=1
         0: new           #50                 // class java/util/Date
         3: dup
         4: invokespecial #51                 // Method java/util/Date."<init>":()V
         7: invokevirtual #54                 // Method java/util/Date.getTime:()J
        10: lreturn
      LineNumberTable:
        line 622: 0
      LocalVariableTable:
        Start  Length  Slot  Name   Signature
            0      11     0  this   Lorg/scalatest/events/TestFailed$;

  public scala.Option<scala.Tuple17<org.scalatest.events.Ordinal, java.lang.String, java.lang.String, java.lang.String, scala.Option<java.lang.String>, java.lang.String, java.lang.String, scala.collection.immutable.IndexedSeq<org.scalatest.events.RecordableEvent>, scala.collection.immutable.IndexedSeq<java.lang.String>, scala.Option<java.lang.Throwable>, scala.Option<java.lang.Object>, scala.Option<org.scalatest.events.Formatter>, scala.Option<org.scalatest.events.Location>, scala.Option<java.lang.String>, scala.Option<java.lang.Object>, java.lang.String, java.lang.Object>> unapply(org.scalatest.events.TestFailed);
    descriptor: (Lorg/scalatest/events/TestFailed;)Lscala/Option;
    flags: (0x0001) ACC_PUBLIC
    Code:
      stack=22, locals=2, args_size=2
         0: aload_1
         1: ifnonnull     10
         4: getstatic     #25                 // Field scala/None$.MODULE$:Lscala/None$;
         7: goto          95
        10: new           #101                // class scala/Some
        13: dup
        14: new           #103                // class scala/Tuple17
        17: dup
        18: aload_1
        19: invokevirtual #106                // Method org/scalatest/events/TestFailed.ordinal:()Lorg/scalatest/events/Ordinal;
        22: aload_1
        23: invokevirtual #108                // Method org/scalatest/events/TestFailed.message:()Ljava/lang/String;
        26: aload_1
        27: invokevirtual #110                // Method org/scalatest/events/TestFailed.suiteName:()Ljava/lang/String;
        30: aload_1
        31: invokevirtual #112                // Method org/scalatest/events/TestFailed.suiteId:()Ljava/lang/String;
        34: aload_1
        35: invokevirtual #114                // Method org/scalatest/events/TestFailed.suiteClassName:()Lscala/Option;
        38: aload_1
        39: invokevirtual #116                // Method org/scalatest/events/TestFailed.testName:()Ljava/lang/String;
        42: aload_1
        43: invokevirtual #118                // Method org/scalatest/events/TestFailed.testText:()Ljava/lang/String;
        46: aload_1
        47: invokevirtual #121                // Method org/scalatest/events/TestFailed.recordedEvents:()Lscala/collection/immutable/IndexedSeq;
        50: aload_1
        51: invokevirtual #123                // Method org/scalatest/events/TestFailed.analysis:()Lscala/collection/immutable/IndexedSeq;
        54: aload_1
        55: invokevirtual #125                // Method org/scalatest/events/TestFailed.throwable:()Lscala/Option;
        58: aload_1
        59: invokevirtual #127                // Method org/scalatest/events/TestFailed.duration:()Lscala/Option;
        62: aload_1
        63: invokevirtual #129                // Method org/scalatest/events/TestFailed.formatter:()Lscala/Option;
        66: aload_1
        67: invokevirtual #131                // Method org/scalatest/events/TestFailed.location:()Lscala/Option;
        70: aload_1
        71: invokevirtual #133                // Method org/scalatest/events/TestFailed.rerunner:()Lscala/Option;
        74: aload_1
        75: invokevirtual #135                // Method org/scalatest/events/TestFailed.payload:()Lscala/Option;
        78: aload_1
        79: invokevirtual #137                // Method org/scalatest/events/TestFailed.threadName:()Ljava/lang/String;
        82: aload_1
        83: invokevirtual #139                // Method org/scalatest/events/TestFailed.timeStamp:()J
        86: invokestatic  #145                // Method scala/runtime/BoxesRunTime.boxToLong:(J)Ljava/lang/Long;
        89: invokespecial #148                // Method scala/Tuple17."<init>":(Ljava/lang/Object;Ljava/lang/Object;Ljava/lang/Object;Ljava/lang/Object;Ljava/lang/Object;Ljava/lang/Object;Ljava/lang/Object;Ljava/lang/Object;Ljava/lang/Object;Ljava/lang/Object;Ljava/lang/Object;Ljava/lang/Object;Ljava/lang/Object;Ljava/lang/Object;Ljava/lang/Object;Ljava/lang/Object;Ljava/lang/Object;)V
        92: invokespecial #151                // Method scala/Some."<init>":(Ljava/lang/Object;)V
        95: areturn
      StackMapTable: number_of_entries = 2
        frame_type = 10 /* same */
        frame_type = 247 /* same_locals_1_stack_item_frame_extended */
          offset_delta = 84
          stack = [ class scala/Option ]
      LineNumberTable:
        line 605: 0
      LocalVariableTable:
        Start  Length  Slot  Name   Signature
            0      96     0  this   Lorg/scalatest/events/TestFailed$;
            0      96     1   x$0   Lorg/scalatest/events/TestFailed;
    Signature: #98                          // (Lorg/scalatest/events/TestFailed;)Lscala/Option<Lscala/Tuple17<Lorg/scalatest/events/Ordinal;Ljava/lang/String;Ljava/lang/String;Ljava/lang/String;Lscala/Option<Ljava/lang/String;>;Ljava/lang/String;Ljava/lang/String;Lscala/collection/immutable/IndexedSeq<Lorg/scalatest/events/RecordableEvent;>;Lscala/collection/immutable/IndexedSeq<Ljava/lang/String;>;Lscala/Option<Ljava/lang/Throwable;>;Lscala/Option<Ljava/lang/Object;>;Lscala/Option<Lorg/scalatest/events/Formatter;>;Lscala/Option<Lorg/scalatest/events/Location;>;Lscala/Option<Ljava/lang/String;>;Lscala/Option<Ljava/lang/Object;>;Ljava/lang/String;Ljava/lang/Object;>;>;
    MethodParameters:
      Name                           Flags
      x$0                            final

  private java.lang.Object writeReplace();
    descriptor: ()Ljava/lang/Object;
    flags: (0x0002) ACC_PRIVATE
    Code:
      stack=3, locals=1, args_size=1
         0: new           #158                // class scala/runtime/ModuleSerializationProxy
         3: dup
         4: ldc           #2                  // class org/scalatest/events/TestFailed$
         6: invokespecial #161                // Method scala/runtime/ModuleSerializationProxy."<init>":(Ljava/lang/Class;)V
         9: areturn
      LineNumberTable:
        line 605: 0
      LocalVariableTable:
        Start  Length  Slot  Name   Signature
            0      10     0  this   Lorg/scalatest/events/TestFailed$;

  public java.lang.Object apply(java.lang.Object, java.lang.Object, java.lang.Object, java.lang.Object, java.lang.Object, java.lang.Object, java.lang.Object, java.lang.Object, java.lang.Object, java.lang.Object, java.lang.Object, java.lang.Object, java.lang.Object, java.lang.Object, java.lang.Object, java.lang.Object, java.lang.Object);
    descriptor: (Ljava/lang/Object;Ljava/lang/Object;Ljava/lang/Object;Ljava/lang/Object;Ljava/lang/Object;Ljava/lang/Object;Ljava/lang/Object;Ljava/lang/Object;Ljava/lang/Object;Ljava/lang/Object;Ljava/lang/Object;Ljava/lang/Object;Ljava/lang/Object;Ljava/lang/Object;Ljava/lang/Object;Ljava/lang/Object;Ljava/lang/Object;)Ljava/lang/Object;
    flags: (0x1041) ACC_PUBLIC, ACC_BRIDGE, ACC_SYNTHETIC
    Code:
      stack=19, locals=18, args_size=18
         0: aload_0
         1: aload_1
         2: checkcast     #181                // class org/scalatest/events/Ordinal
         5: aload_2
         6: checkcast     #183                // class java/lang/String
         9: aload_3
        10: checkcast     #183                // class java/lang/String
        13: aload         4
        15: checkcast     #183                // class java/lang/String
        18: aload         5
        20: checkcast     #154                // class scala/Option
        23: aload         6
        25: checkcast     #183                // class java/lang/String
        28: aload         7
        30: checkcast     #183                // class java/lang/String
        33: aload         8
        35: checkcast     #185                // class scala/collection/immutable/IndexedSeq
        38: aload         9
        40: checkcast     #185                // class scala/collection/immutable/IndexedSeq
        43: aload         10
        45: checkcast     #154                // class scala/Option
        48: aload         11
        50: checkcast     #154                // class scala/Option
        53: aload         12
        55: checkcast     #154                // class scala/Option
        58: aload         13
        60: checkcast     #154                // class scala/Option
        63: aload         14
        65: checkcast     #154                // class scala/Option
        68: aload         15
        70: checkcast     #154                // class scala/Option
        73: aload         16
        75: checkcast     #183                // class java/lang/String
        78: aload         17
        80: invokestatic  #189                // Method scala/runtime/BoxesRunTime.unboxToLong:(Ljava/lang/Object;)J
        83: invokevirtual #191                // Method apply:(Lorg/scalatest/events/Ordinal;Ljava/lang/String;Ljava/lang/String;Ljava/lang/String;Lscala/Option;Ljava/lang/String;Ljava/lang/String;Lscala/collection/immutable/IndexedSeq;Lscala/collection/immutable/IndexedSeq;Lscala/Option;Lscala/Option;Lscala/Option;Lscala/Option;Lscala/Option;Lscala/Option;Ljava/lang/String;J)Lorg/scalatest/events/TestFailed;
        86: areturn
      LineNumberTable:
        line 605: 0
      LocalVariableTable:
        Start  Length  Slot  Name   Signature
            0      87     0  this   Lorg/scalatest/events/TestFailed$;
            0      87     1    v1   Ljava/lang/Object;
            0      87     2    v2   Ljava/lang/Object;
            0      87     3    v3   Ljava/lang/Object;
            0      87     4    v4   Ljava/lang/Object;
            0      87     5    v5   Ljava/lang/Object;
            0      87     6    v6   Ljava/lang/Object;
            0      87     7    v7   Ljava/lang/Object;
            0      87     8    v8   Ljava/lang/Object;
            0      87     9    v9   Ljava/lang/Object;
            0      87    10   v10   Ljava/lang/Object;
            0      87    11   v11   Ljava/lang/Object;
            0      87    12   v12   Ljava/lang/Object;
            0      87    13   v13   Ljava/lang/Object;
            0      87    14   v14   Ljava/lang/Object;
            0      87    15   v15   Ljava/lang/Object;
            0      87    16   v16   Ljava/lang/Object;
            0      87    17   v17   Ljava/lang/Object;
    MethodParameters:
      Name                           Flags
      v1                             final
      v2                             final
      v3                             final
      v4                             final
      v5                             final
      v6                             final
      v7                             final
      v8                             final
      v9                             final
      v10                            final
      v11                            final
      v12                            final
      v13                            final
      v14                            final
      v15                            final
      v16                            final
      v17                            final

  private org.scalatest.events.TestFailed$();
    descriptor: ()V
    flags: (0x0002) ACC_PRIVATE
    Code:
      stack=1, locals=1, args_size=1
         0: aload_0
         1: invokespecial #193                // Method scala/runtime/AbstractFunction17."<init>":()V
         4: return
      LineNumberTable:
        line 605: 0
      LocalVariableTable:
        Start  Length  Slot  Name   Signature
            0       5     0  this   Lorg/scalatest/events/TestFailed$;
}
Signature: #3                           // Lscala/runtime/AbstractFunction17<Lorg/scalatest/events/Ordinal;Ljava/lang/String;Ljava/lang/String;Ljava/lang/String;Lscala/Option<Ljava/lang/String;>;Ljava/lang/String;Ljava/lang/String;Lscala/collection/immutable/IndexedSeq<Lorg/scalatest/events/RecordableEvent;>;Lscala/collection/immutable/IndexedSeq<Ljava/lang/String;>;Lscala/Option<Ljava/lang/Throwable;>;Lscala/Option<Ljava/lang/Object;>;Lscala/Option<Lorg/scalatest/events/Formatter;>;Lscala/Option<Lorg/scalatest/events/Location;>;Lscala/Option<Ljava/lang/String;>;Lscala/Option<Ljava/lang/Object;>;Ljava/lang/String;Ljava/lang/Object;Lorg/scalatest/events/TestFailed;>;Ljava/io/Serializable;
SourceFile: "Event.scala"
  ScalaInlineInfo: length = 0x72 (unknown attribute)
   01 01 00 16 00 12 00 13 01 00 1B 00 13 01 00 1D
   00 13 01 00 1F 00 13 01 00 21 00 13 01 00 23 00
   13 01 00 24 00 25 01 00 2F 00 30 01 00 0D 00 0C
   01 00 3A 00 A2 01 00 3A 00 3B 01 00 58 00 13 01
   00 59 00 13 01 00 5A 00 13 01 00 5B 00 13 01 00
   5C 00 13 01 00 5D 00 13 01 00 5E 00 25 01 00 5F
   00 30 01 00 37 00 25 01 00 60 00 61 01 00 9B 00
   9C 01
  Scala: length = 0x0 (unknown attribute)

