Classfile /Users/mw/Projects/slang-braindump/.jar/jar8/assemble/slang-braindump/assemble/content/scala/reflect/ClassTag$.class
  Last modified May 29, 2022; size 6159 bytes
  SHA-256 checksum e7558b9e65d3e4f805ff16641a80b0c88bfade6bf8954f5dd0a918fbff03dfb4
  Compiled from "ClassTag.scala"
public final class scala.reflect.ClassTag$ implements java.io.Serializable
  minor version: 0
  major version: 52
  flags: (0x0031) ACC_PUBLIC, ACC_FINAL, ACC_SUPER
  this_class: #2                          // scala/reflect/ClassTag$
  super_class: #4                         // java/lang/Object
  interfaces: 1, fields: 20, methods: 21, attributes: 4
Constant pool:
    #1 = Utf8               scala/reflect/ClassTag$
    #2 = Class              #1            // scala/reflect/ClassTag$
    #3 = Utf8               java/lang/Object
    #4 = Class              #3            // java/lang/Object
    #5 = Utf8               java/io/Serializable
    #6 = Class              #5            // java/io/Serializable
    #7 = Utf8               ClassTag.scala
    #8 = Utf8               scala/reflect/ClassTag$cache$
    #9 = Class              #8            // scala/reflect/ClassTag$cache$
   #10 = Utf8               scala/reflect/ClassTag
   #11 = Class              #10           // scala/reflect/ClassTag
   #12 = Utf8               cache$
   #13 = Utf8               scala/reflect/ManifestFactory$BooleanManifest
   #14 = Class              #13           // scala/reflect/ManifestFactory$BooleanManifest
   #15 = Utf8               scala/reflect/ManifestFactory
   #16 = Class              #15           // scala/reflect/ManifestFactory
   #17 = Utf8               BooleanManifest
   #18 = Utf8               scala/reflect/ManifestFactory$ByteManifest
   #19 = Class              #18           // scala/reflect/ManifestFactory$ByteManifest
   #20 = Utf8               ByteManifest
   #21 = Utf8               scala/reflect/ManifestFactory$CharManifest
   #22 = Class              #21           // scala/reflect/ManifestFactory$CharManifest
   #23 = Utf8               CharManifest
   #24 = Utf8               scala/reflect/ManifestFactory$DoubleManifest
   #25 = Class              #24           // scala/reflect/ManifestFactory$DoubleManifest
   #26 = Utf8               DoubleManifest
   #27 = Utf8               scala/reflect/ManifestFactory$FloatManifest
   #28 = Class              #27           // scala/reflect/ManifestFactory$FloatManifest
   #29 = Utf8               FloatManifest
   #30 = Utf8               scala/reflect/ManifestFactory$IntManifest
   #31 = Class              #30           // scala/reflect/ManifestFactory$IntManifest
   #32 = Utf8               IntManifest
   #33 = Utf8               scala/reflect/ManifestFactory$LongManifest
   #34 = Class              #33           // scala/reflect/ManifestFactory$LongManifest
   #35 = Utf8               LongManifest
   #36 = Utf8               scala/reflect/ManifestFactory$ShortManifest
   #37 = Class              #36           // scala/reflect/ManifestFactory$ShortManifest
   #38 = Utf8               ShortManifest
   #39 = Utf8               scala/reflect/ManifestFactory$UnitManifest
   #40 = Class              #39           // scala/reflect/ManifestFactory$UnitManifest
   #41 = Utf8               UnitManifest
   #42 = Utf8               MODULE$
   #43 = Utf8               Lscala/reflect/ClassTag$;
   #44 = Utf8               scala$reflect$ClassTag$$ObjectTYPE
   #45 = Utf8               Ljava/lang/Class;
   #46 = Utf8               Ljava/lang/Class<Ljava/lang/Object;>;
   #47 = Utf8               scala$reflect$ClassTag$$NothingTYPE
   #48 = Utf8               Ljava/lang/Class<Lscala/runtime/Nothing$;>;
   #49 = Utf8               scala$reflect$ClassTag$$NullTYPE
   #50 = Utf8               Ljava/lang/Class<Lscala/runtime/Null$;>;
   #51 = Utf8               Byte
   #52 = Utf8               Lscala/reflect/ManifestFactory$ByteManifest;
   #53 = Utf8               Short
   #54 = Utf8               Lscala/reflect/ManifestFactory$ShortManifest;
   #55 = Utf8               Char
   #56 = Utf8               Lscala/reflect/ManifestFactory$CharManifest;
   #57 = Utf8               Int
   #58 = Utf8               Lscala/reflect/ManifestFactory$IntManifest;
   #59 = Utf8               Long
   #60 = Utf8               Lscala/reflect/ManifestFactory$LongManifest;
   #61 = Utf8               Float
   #62 = Utf8               Lscala/reflect/ManifestFactory$FloatManifest;
   #63 = Utf8               Double
   #64 = Utf8               Lscala/reflect/ManifestFactory$DoubleManifest;
   #65 = Utf8               Boolean
   #66 = Utf8               Lscala/reflect/ManifestFactory$BooleanManifest;
   #67 = Utf8               Unit
   #68 = Utf8               Lscala/reflect/ManifestFactory$UnitManifest;
   #69 = Utf8               Any
   #70 = Utf8               Lscala/reflect/ClassTag;
   #71 = Utf8               Lscala/reflect/ClassTag<Ljava/lang/Object;>;
   #72 = Utf8               Object
   #73 = Utf8               AnyVal
   #74 = Utf8               AnyRef
   #75 = Utf8               Nothing
   #76 = Utf8               Lscala/reflect/ClassTag<Lscala/runtime/Nothing$;>;
   #77 = Utf8               Null
   #78 = Utf8               Lscala/reflect/ClassTag<Lscala/runtime/Null$;>;
   #79 = Utf8               cacheDisabled
   #80 = Utf8               Z
   #81 = Utf8               <clinit>
   #82 = Utf8               ()V
   #83 = Utf8               <init>
   #84 = NameAndType        #83:#82       // "<init>":()V
   #85 = Methodref          #2.#84        // scala/reflect/ClassTag$."<init>":()V
   #86 = NameAndType        #42:#43       // MODULE$:Lscala/reflect/ClassTag$;
   #87 = Fieldref           #2.#86        // scala/reflect/ClassTag$.MODULE$:Lscala/reflect/ClassTag$;
   #88 = NameAndType        #44:#45       // scala$reflect$ClassTag$$ObjectTYPE:Ljava/lang/Class;
   #89 = Fieldref           #2.#88        // scala/reflect/ClassTag$.scala$reflect$ClassTag$$ObjectTYPE:Ljava/lang/Class;
   #90 = Utf8               scala/runtime/Nothing$
   #91 = Class              #90           // scala/runtime/Nothing$
   #92 = NameAndType        #47:#45       // scala$reflect$ClassTag$$NothingTYPE:Ljava/lang/Class;
   #93 = Fieldref           #2.#92        // scala/reflect/ClassTag$.scala$reflect$ClassTag$$NothingTYPE:Ljava/lang/Class;
   #94 = Utf8               scala/runtime/Null$
   #95 = Class              #94           // scala/runtime/Null$
   #96 = NameAndType        #49:#45       // scala$reflect$ClassTag$$NullTYPE:Ljava/lang/Class;
   #97 = Fieldref           #2.#96        // scala/reflect/ClassTag$.scala$reflect$ClassTag$$NullTYPE:Ljava/lang/Class;
   #98 = Utf8               scala/reflect/Manifest$
   #99 = Class              #98           // scala/reflect/Manifest$
  #100 = Utf8               Lscala/reflect/Manifest$;
  #101 = NameAndType        #42:#100      // MODULE$:Lscala/reflect/Manifest$;
  #102 = Fieldref           #99.#101      // scala/reflect/Manifest$.MODULE$:Lscala/reflect/Manifest$;
  #103 = Utf8               ()Lscala/reflect/ManifestFactory$ByteManifest;
  #104 = NameAndType        #51:#103      // Byte:()Lscala/reflect/ManifestFactory$ByteManifest;
  #105 = Methodref          #99.#104      // scala/reflect/Manifest$.Byte:()Lscala/reflect/ManifestFactory$ByteManifest;
  #106 = NameAndType        #51:#52       // Byte:Lscala/reflect/ManifestFactory$ByteManifest;
  #107 = Fieldref           #2.#106       // scala/reflect/ClassTag$.Byte:Lscala/reflect/ManifestFactory$ByteManifest;
  #108 = Utf8               ()Lscala/reflect/ManifestFactory$ShortManifest;
  #109 = NameAndType        #53:#108      // Short:()Lscala/reflect/ManifestFactory$ShortManifest;
  #110 = Methodref          #99.#109      // scala/reflect/Manifest$.Short:()Lscala/reflect/ManifestFactory$ShortManifest;
  #111 = NameAndType        #53:#54       // Short:Lscala/reflect/ManifestFactory$ShortManifest;
  #112 = Fieldref           #2.#111       // scala/reflect/ClassTag$.Short:Lscala/reflect/ManifestFactory$ShortManifest;
  #113 = Utf8               ()Lscala/reflect/ManifestFactory$CharManifest;
  #114 = NameAndType        #55:#113      // Char:()Lscala/reflect/ManifestFactory$CharManifest;
  #115 = Methodref          #99.#114      // scala/reflect/Manifest$.Char:()Lscala/reflect/ManifestFactory$CharManifest;
  #116 = NameAndType        #55:#56       // Char:Lscala/reflect/ManifestFactory$CharManifest;
  #117 = Fieldref           #2.#116       // scala/reflect/ClassTag$.Char:Lscala/reflect/ManifestFactory$CharManifest;
  #118 = Utf8               ()Lscala/reflect/ManifestFactory$IntManifest;
  #119 = NameAndType        #57:#118      // Int:()Lscala/reflect/ManifestFactory$IntManifest;
  #120 = Methodref          #99.#119      // scala/reflect/Manifest$.Int:()Lscala/reflect/ManifestFactory$IntManifest;
  #121 = NameAndType        #57:#58       // Int:Lscala/reflect/ManifestFactory$IntManifest;
  #122 = Fieldref           #2.#121       // scala/reflect/ClassTag$.Int:Lscala/reflect/ManifestFactory$IntManifest;
  #123 = Utf8               ()Lscala/reflect/ManifestFactory$LongManifest;
  #124 = NameAndType        #59:#123      // Long:()Lscala/reflect/ManifestFactory$LongManifest;
  #125 = Methodref          #99.#124      // scala/reflect/Manifest$.Long:()Lscala/reflect/ManifestFactory$LongManifest;
  #126 = NameAndType        #59:#60       // Long:Lscala/reflect/ManifestFactory$LongManifest;
  #127 = Fieldref           #2.#126       // scala/reflect/ClassTag$.Long:Lscala/reflect/ManifestFactory$LongManifest;
  #128 = Utf8               ()Lscala/reflect/ManifestFactory$FloatManifest;
  #129 = NameAndType        #61:#128      // Float:()Lscala/reflect/ManifestFactory$FloatManifest;
  #130 = Methodref          #99.#129      // scala/reflect/Manifest$.Float:()Lscala/reflect/ManifestFactory$FloatManifest;
  #131 = NameAndType        #61:#62       // Float:Lscala/reflect/ManifestFactory$FloatManifest;
  #132 = Fieldref           #2.#131       // scala/reflect/ClassTag$.Float:Lscala/reflect/ManifestFactory$FloatManifest;
  #133 = Utf8               ()Lscala/reflect/ManifestFactory$DoubleManifest;
  #134 = NameAndType        #63:#133      // Double:()Lscala/reflect/ManifestFactory$DoubleManifest;
  #135 = Methodref          #99.#134      // scala/reflect/Manifest$.Double:()Lscala/reflect/ManifestFactory$DoubleManifest;
  #136 = NameAndType        #63:#64       // Double:Lscala/reflect/ManifestFactory$DoubleManifest;
  #137 = Fieldref           #2.#136       // scala/reflect/ClassTag$.Double:Lscala/reflect/ManifestFactory$DoubleManifest;
  #138 = Utf8               ()Lscala/reflect/ManifestFactory$BooleanManifest;
  #139 = NameAndType        #65:#138      // Boolean:()Lscala/reflect/ManifestFactory$BooleanManifest;
  #140 = Methodref          #99.#139      // scala/reflect/Manifest$.Boolean:()Lscala/reflect/ManifestFactory$BooleanManifest;
  #141 = NameAndType        #65:#66       // Boolean:Lscala/reflect/ManifestFactory$BooleanManifest;
  #142 = Fieldref           #2.#141       // scala/reflect/ClassTag$.Boolean:Lscala/reflect/ManifestFactory$BooleanManifest;
  #143 = Utf8               ()Lscala/reflect/ManifestFactory$UnitManifest;
  #144 = NameAndType        #67:#143      // Unit:()Lscala/reflect/ManifestFactory$UnitManifest;
  #145 = Methodref          #99.#144      // scala/reflect/Manifest$.Unit:()Lscala/reflect/ManifestFactory$UnitManifest;
  #146 = NameAndType        #67:#68       // Unit:Lscala/reflect/ManifestFactory$UnitManifest;
  #147 = Fieldref           #2.#146       // scala/reflect/ClassTag$.Unit:Lscala/reflect/ManifestFactory$UnitManifest;
  #148 = Utf8               ()Lscala/reflect/Manifest;
  #149 = NameAndType        #69:#148      // Any:()Lscala/reflect/Manifest;
  #150 = Methodref          #99.#149      // scala/reflect/Manifest$.Any:()Lscala/reflect/Manifest;
  #151 = NameAndType        #69:#70       // Any:Lscala/reflect/ClassTag;
  #152 = Fieldref           #2.#151       // scala/reflect/ClassTag$.Any:Lscala/reflect/ClassTag;
  #153 = NameAndType        #72:#148      // Object:()Lscala/reflect/Manifest;
  #154 = Methodref          #99.#153      // scala/reflect/Manifest$.Object:()Lscala/reflect/Manifest;
  #155 = NameAndType        #72:#70       // Object:Lscala/reflect/ClassTag;
  #156 = Fieldref           #2.#155       // scala/reflect/ClassTag$.Object:Lscala/reflect/ClassTag;
  #157 = NameAndType        #73:#148      // AnyVal:()Lscala/reflect/Manifest;
  #158 = Methodref          #99.#157      // scala/reflect/Manifest$.AnyVal:()Lscala/reflect/Manifest;
  #159 = NameAndType        #73:#70       // AnyVal:Lscala/reflect/ClassTag;
  #160 = Fieldref           #2.#159       // scala/reflect/ClassTag$.AnyVal:Lscala/reflect/ClassTag;
  #161 = NameAndType        #74:#148      // AnyRef:()Lscala/reflect/Manifest;
  #162 = Methodref          #99.#161      // scala/reflect/Manifest$.AnyRef:()Lscala/reflect/Manifest;
  #163 = NameAndType        #74:#70       // AnyRef:Lscala/reflect/ClassTag;
  #164 = Fieldref           #2.#163       // scala/reflect/ClassTag$.AnyRef:Lscala/reflect/ClassTag;
  #165 = NameAndType        #75:#148      // Nothing:()Lscala/reflect/Manifest;
  #166 = Methodref          #99.#165      // scala/reflect/Manifest$.Nothing:()Lscala/reflect/Manifest;
  #167 = NameAndType        #75:#70       // Nothing:Lscala/reflect/ClassTag;
  #168 = Fieldref           #2.#167       // scala/reflect/ClassTag$.Nothing:Lscala/reflect/ClassTag;
  #169 = NameAndType        #77:#148      // Null:()Lscala/reflect/Manifest;
  #170 = Methodref          #99.#169      // scala/reflect/Manifest$.Null:()Lscala/reflect/Manifest;
  #171 = NameAndType        #77:#70       // Null:Lscala/reflect/ClassTag;
  #172 = Fieldref           #2.#171       // scala/reflect/ClassTag$.Null:Lscala/reflect/ClassTag;
  #173 = Utf8               scala.reflect.classtag.cache.disable
  #174 = String             #173          // scala.reflect.classtag.cache.disable
  #175 = Utf8               java/lang/Boolean
  #176 = Class              #175          // java/lang/Boolean
  #177 = Utf8               getBoolean
  #178 = Utf8               (Ljava/lang/String;)Z
  #179 = NameAndType        #177:#178     // getBoolean:(Ljava/lang/String;)Z
  #180 = Methodref          #176.#179     // java/lang/Boolean.getBoolean:(Ljava/lang/String;)Z
  #181 = NameAndType        #79:#80       // cacheDisabled:Z
  #182 = Fieldref           #2.#181       // scala/reflect/ClassTag$.cacheDisabled:Z
  #183 = Utf8               this
  #184 = Utf8               ()Lscala/reflect/ClassTag;
  #185 = Utf8               ()Lscala/reflect/ClassTag<Ljava/lang/Object;>;
  #186 = Utf8               ()Lscala/reflect/ClassTag<Lscala/runtime/Nothing$;>;
  #187 = Utf8               ()Lscala/reflect/ClassTag<Lscala/runtime/Null$;>;
  #188 = Utf8               ()Z
  #189 = Utf8               apply
  #190 = Utf8               (Ljava/lang/Class;)Lscala/reflect/ClassTag;
  #191 = Utf8               <T:Ljava/lang/Object;>(Ljava/lang/Class<*>;)Lscala/reflect/ClassTag<TT;>;
  #192 = Utf8               runtimeClass1
  #193 = NameAndType        #79:#188      // cacheDisabled:()Z
  #194 = Methodref          #2.#193       // scala/reflect/ClassTag$.cacheDisabled:()Z
  #195 = Utf8               Lscala/reflect/ClassTag$cache$;
  #196 = NameAndType        #42:#195      // MODULE$:Lscala/reflect/ClassTag$cache$;
  #197 = Fieldref           #9.#196       // scala/reflect/ClassTag$cache$.MODULE$:Lscala/reflect/ClassTag$cache$;
  #198 = Utf8               computeTag
  #199 = NameAndType        #198:#190     // computeTag:(Ljava/lang/Class;)Lscala/reflect/ClassTag;
  #200 = Methodref          #9.#199       // scala/reflect/ClassTag$cache$.computeTag:(Ljava/lang/Class;)Lscala/reflect/ClassTag;
  #201 = Utf8               get
  #202 = Utf8               (Ljava/lang/Class;)Ljava/lang/Object;
  #203 = NameAndType        #201:#202     // get:(Ljava/lang/Class;)Ljava/lang/Object;
  #204 = Methodref          #9.#203       // scala/reflect/ClassTag$cache$.get:(Ljava/lang/Class;)Ljava/lang/Object;
  #205 = Utf8               java/lang/ref/WeakReference
  #206 = Class              #205          // java/lang/ref/WeakReference
  #207 = Utf8               ()Ljava/lang/Object;
  #208 = NameAndType        #201:#207     // get:()Ljava/lang/Object;
  #209 = Methodref          #206.#208     // java/lang/ref/WeakReference.get:()Ljava/lang/Object;
  #210 = Utf8               remove
  #211 = Utf8               (Ljava/lang/Class;)V
  #212 = NameAndType        #210:#211     // remove:(Ljava/lang/Class;)V
  #213 = Methodref          #9.#212       // scala/reflect/ClassTag$cache$.remove:(Ljava/lang/Class;)V
  #214 = Utf8               tag
  #215 = Utf8               unapply
  #216 = Utf8               (Lscala/reflect/ClassTag;)Lscala/Option;
  #217 = Utf8               <T:Ljava/lang/Object;>(Lscala/reflect/ClassTag<TT;>;)Lscala/Option<Ljava/lang/Class<*>;>;
  #218 = Utf8               ctag
  #219 = Utf8               scala/Some
  #220 = Class              #219          // scala/Some
  #221 = Utf8               runtimeClass
  #222 = Utf8               ()Ljava/lang/Class;
  #223 = NameAndType        #221:#222     // runtimeClass:()Ljava/lang/Class;
  #224 = InterfaceMethodref #11.#223      // scala/reflect/ClassTag.runtimeClass:()Ljava/lang/Class;
  #225 = Utf8               (Ljava/lang/Object;)V
  #226 = NameAndType        #83:#225      // "<init>":(Ljava/lang/Object;)V
  #227 = Methodref          #220.#226     // scala/Some."<init>":(Ljava/lang/Object;)V
  #228 = Utf8               writeReplace
  #229 = Utf8               scala/runtime/ModuleSerializationProxy
  #230 = Class              #229          // scala/runtime/ModuleSerializationProxy
  #231 = NameAndType        #83:#211      // "<init>":(Ljava/lang/Class;)V
  #232 = Methodref          #230.#231     // scala/runtime/ModuleSerializationProxy."<init>":(Ljava/lang/Class;)V
  #233 = Methodref          #4.#84        // java/lang/Object."<init>":()V
  #234 = Utf8               Signature
  #235 = Utf8               Code
  #236 = Utf8               LineNumberTable
  #237 = Utf8               LocalVariableTable
  #238 = Utf8               StackMapTable
  #239 = Utf8               MethodParameters
  #240 = Utf8               InnerClasses
  #241 = Utf8               SourceFile
  #242 = Utf8               ScalaInlineInfo
  #243 = Utf8               Scala
{
  public static final scala.reflect.ClassTag$ MODULE$;
    descriptor: Lscala/reflect/ClassTag$;
    flags: (0x0019) ACC_PUBLIC, ACC_STATIC, ACC_FINAL

  public static final java.lang.Class<java.lang.Object> scala$reflect$ClassTag$$ObjectTYPE;
    descriptor: Ljava/lang/Class;
    flags: (0x0019) ACC_PUBLIC, ACC_STATIC, ACC_FINAL
    Signature: #46                          // Ljava/lang/Class<Ljava/lang/Object;>;

  public static final java.lang.Class<scala.runtime.Nothing$> scala$reflect$ClassTag$$NothingTYPE;
    descriptor: Ljava/lang/Class;
    flags: (0x0019) ACC_PUBLIC, ACC_STATIC, ACC_FINAL
    Signature: #48                          // Ljava/lang/Class<Lscala/runtime/Nothing$;>;

  public static final java.lang.Class<scala.runtime.Null$> scala$reflect$ClassTag$$NullTYPE;
    descriptor: Ljava/lang/Class;
    flags: (0x0019) ACC_PUBLIC, ACC_STATIC, ACC_FINAL
    Signature: #50                          // Ljava/lang/Class<Lscala/runtime/Null$;>;

  private static final scala.reflect.ManifestFactory$ByteManifest Byte;
    descriptor: Lscala/reflect/ManifestFactory$ByteManifest;
    flags: (0x001a) ACC_PRIVATE, ACC_STATIC, ACC_FINAL

  private static final scala.reflect.ManifestFactory$ShortManifest Short;
    descriptor: Lscala/reflect/ManifestFactory$ShortManifest;
    flags: (0x001a) ACC_PRIVATE, ACC_STATIC, ACC_FINAL

  private static final scala.reflect.ManifestFactory$CharManifest Char;
    descriptor: Lscala/reflect/ManifestFactory$CharManifest;
    flags: (0x001a) ACC_PRIVATE, ACC_STATIC, ACC_FINAL

  private static final scala.reflect.ManifestFactory$IntManifest Int;
    descriptor: Lscala/reflect/ManifestFactory$IntManifest;
    flags: (0x001a) ACC_PRIVATE, ACC_STATIC, ACC_FINAL

  private static final scala.reflect.ManifestFactory$LongManifest Long;
    descriptor: Lscala/reflect/ManifestFactory$LongManifest;
    flags: (0x001a) ACC_PRIVATE, ACC_STATIC, ACC_FINAL

  private static final scala.reflect.ManifestFactory$FloatManifest Float;
    descriptor: Lscala/reflect/ManifestFactory$FloatManifest;
    flags: (0x001a) ACC_PRIVATE, ACC_STATIC, ACC_FINAL

  private static final scala.reflect.ManifestFactory$DoubleManifest Double;
    descriptor: Lscala/reflect/ManifestFactory$DoubleManifest;
    flags: (0x001a) ACC_PRIVATE, ACC_STATIC, ACC_FINAL

  private static final scala.reflect.ManifestFactory$BooleanManifest Boolean;
    descriptor: Lscala/reflect/ManifestFactory$BooleanManifest;
    flags: (0x001a) ACC_PRIVATE, ACC_STATIC, ACC_FINAL

  private static final scala.reflect.ManifestFactory$UnitManifest Unit;
    descriptor: Lscala/reflect/ManifestFactory$UnitManifest;
    flags: (0x001a) ACC_PRIVATE, ACC_STATIC, ACC_FINAL

  private static final scala.reflect.ClassTag<java.lang.Object> Any;
    descriptor: Lscala/reflect/ClassTag;
    flags: (0x001a) ACC_PRIVATE, ACC_STATIC, ACC_FINAL
    Signature: #71                          // Lscala/reflect/ClassTag<Ljava/lang/Object;>;

  private static final scala.reflect.ClassTag<java.lang.Object> Object;
    descriptor: Lscala/reflect/ClassTag;
    flags: (0x001a) ACC_PRIVATE, ACC_STATIC, ACC_FINAL
    Signature: #71                          // Lscala/reflect/ClassTag<Ljava/lang/Object;>;

  private static final scala.reflect.ClassTag<java.lang.Object> AnyVal;
    descriptor: Lscala/reflect/ClassTag;
    flags: (0x001a) ACC_PRIVATE, ACC_STATIC, ACC_FINAL
    Signature: #71                          // Lscala/reflect/ClassTag<Ljava/lang/Object;>;

  private static final scala.reflect.ClassTag<java.lang.Object> AnyRef;
    descriptor: Lscala/reflect/ClassTag;
    flags: (0x001a) ACC_PRIVATE, ACC_STATIC, ACC_FINAL
    Signature: #71                          // Lscala/reflect/ClassTag<Ljava/lang/Object;>;

  private static final scala.reflect.ClassTag<scala.runtime.Nothing$> Nothing;
    descriptor: Lscala/reflect/ClassTag;
    flags: (0x001a) ACC_PRIVATE, ACC_STATIC, ACC_FINAL
    Signature: #76                          // Lscala/reflect/ClassTag<Lscala/runtime/Nothing$;>;

  private static final scala.reflect.ClassTag<scala.runtime.Null$> Null;
    descriptor: Lscala/reflect/ClassTag;
    flags: (0x001a) ACC_PRIVATE, ACC_STATIC, ACC_FINAL
    Signature: #78                          // Lscala/reflect/ClassTag<Lscala/runtime/Null$;>;

  private static final boolean cacheDisabled;
    descriptor: Z
    flags: (0x001a) ACC_PRIVATE, ACC_STATIC, ACC_FINAL

  public static {};
    descriptor: ()V
    flags: (0x0009) ACC_PUBLIC, ACC_STATIC
    Code:
      stack=2, locals=0, args_size=0
         0: new           #2                  // class scala/reflect/ClassTag$
         3: dup
         4: invokespecial #85                 // Method "<init>":()V
         7: putstatic     #87                 // Field MODULE$:Lscala/reflect/ClassTag$;
        10: ldc           #4                  // class java/lang/Object
        12: putstatic     #89                 // Field scala$reflect$ClassTag$$ObjectTYPE:Ljava/lang/Class;
        15: ldc           #91                 // class scala/runtime/Nothing$
        17: putstatic     #93                 // Field scala$reflect$ClassTag$$NothingTYPE:Ljava/lang/Class;
        20: ldc           #95                 // class scala/runtime/Null$
        22: putstatic     #97                 // Field scala$reflect$ClassTag$$NullTYPE:Ljava/lang/Class;
        25: getstatic     #102                // Field scala/reflect/Manifest$.MODULE$:Lscala/reflect/Manifest$;
        28: invokevirtual #105                // Method scala/reflect/Manifest$.Byte:()Lscala/reflect/ManifestFactory$ByteManifest;
        31: putstatic     #107                // Field Byte:Lscala/reflect/ManifestFactory$ByteManifest;
        34: getstatic     #102                // Field scala/reflect/Manifest$.MODULE$:Lscala/reflect/Manifest$;
        37: invokevirtual #110                // Method scala/reflect/Manifest$.Short:()Lscala/reflect/ManifestFactory$ShortManifest;
        40: putstatic     #112                // Field Short:Lscala/reflect/ManifestFactory$ShortManifest;
        43: getstatic     #102                // Field scala/reflect/Manifest$.MODULE$:Lscala/reflect/Manifest$;
        46: invokevirtual #115                // Method scala/reflect/Manifest$.Char:()Lscala/reflect/ManifestFactory$CharManifest;
        49: putstatic     #117                // Field Char:Lscala/reflect/ManifestFactory$CharManifest;
        52: getstatic     #102                // Field scala/reflect/Manifest$.MODULE$:Lscala/reflect/Manifest$;
        55: invokevirtual #120                // Method scala/reflect/Manifest$.Int:()Lscala/reflect/ManifestFactory$IntManifest;
        58: putstatic     #122                // Field Int:Lscala/reflect/ManifestFactory$IntManifest;
        61: getstatic     #102                // Field scala/reflect/Manifest$.MODULE$:Lscala/reflect/Manifest$;
        64: invokevirtual #125                // Method scala/reflect/Manifest$.Long:()Lscala/reflect/ManifestFactory$LongManifest;
        67: putstatic     #127                // Field Long:Lscala/reflect/ManifestFactory$LongManifest;
        70: getstatic     #102                // Field scala/reflect/Manifest$.MODULE$:Lscala/reflect/Manifest$;
        73: invokevirtual #130                // Method scala/reflect/Manifest$.Float:()Lscala/reflect/ManifestFactory$FloatManifest;
        76: putstatic     #132                // Field Float:Lscala/reflect/ManifestFactory$FloatManifest;
        79: getstatic     #102                // Field scala/reflect/Manifest$.MODULE$:Lscala/reflect/Manifest$;
        82: invokevirtual #135                // Method scala/reflect/Manifest$.Double:()Lscala/reflect/ManifestFactory$DoubleManifest;
        85: putstatic     #137                // Field Double:Lscala/reflect/ManifestFactory$DoubleManifest;
        88: getstatic     #102                // Field scala/reflect/Manifest$.MODULE$:Lscala/reflect/Manifest$;
        91: invokevirtual #140                // Method scala/reflect/Manifest$.Boolean:()Lscala/reflect/ManifestFactory$BooleanManifest;
        94: putstatic     #142                // Field Boolean:Lscala/reflect/ManifestFactory$BooleanManifest;
        97: getstatic     #102                // Field scala/reflect/Manifest$.MODULE$:Lscala/reflect/Manifest$;
       100: invokevirtual #145                // Method scala/reflect/Manifest$.Unit:()Lscala/reflect/ManifestFactory$UnitManifest;
       103: putstatic     #147                // Field Unit:Lscala/reflect/ManifestFactory$UnitManifest;
       106: getstatic     #102                // Field scala/reflect/Manifest$.MODULE$:Lscala/reflect/Manifest$;
       109: invokevirtual #150                // Method scala/reflect/Manifest$.Any:()Lscala/reflect/Manifest;
       112: putstatic     #152                // Field Any:Lscala/reflect/ClassTag;
       115: getstatic     #102                // Field scala/reflect/Manifest$.MODULE$:Lscala/reflect/Manifest$;
       118: invokevirtual #154                // Method scala/reflect/Manifest$.Object:()Lscala/reflect/Manifest;
       121: putstatic     #156                // Field Object:Lscala/reflect/ClassTag;
       124: getstatic     #102                // Field scala/reflect/Manifest$.MODULE$:Lscala/reflect/Manifest$;
       127: invokevirtual #158                // Method scala/reflect/Manifest$.AnyVal:()Lscala/reflect/Manifest;
       130: putstatic     #160                // Field AnyVal:Lscala/reflect/ClassTag;
       133: getstatic     #102                // Field scala/reflect/Manifest$.MODULE$:Lscala/reflect/Manifest$;
       136: invokevirtual #162                // Method scala/reflect/Manifest$.AnyRef:()Lscala/reflect/Manifest;
       139: putstatic     #164                // Field AnyRef:Lscala/reflect/ClassTag;
       142: getstatic     #102                // Field scala/reflect/Manifest$.MODULE$:Lscala/reflect/Manifest$;
       145: invokevirtual #166                // Method scala/reflect/Manifest$.Nothing:()Lscala/reflect/Manifest;
       148: putstatic     #168                // Field Nothing:Lscala/reflect/ClassTag;
       151: getstatic     #102                // Field scala/reflect/Manifest$.MODULE$:Lscala/reflect/Manifest$;
       154: invokevirtual #170                // Method scala/reflect/Manifest$.Null:()Lscala/reflect/Manifest;
       157: putstatic     #172                // Field Null:Lscala/reflect/ClassTag;
       160: ldc           #174                // String scala.reflect.classtag.cache.disable
       162: invokestatic  #180                // Method java/lang/Boolean.getBoolean:(Ljava/lang/String;)Z
       165: putstatic     #182                // Field cacheDisabled:Z
       168: return
      LineNumberTable:
        line 95: 0
        line 96: 10
        line 97: 15
        line 98: 20
        line 102: 25
        line 103: 34
        line 104: 43
        line 105: 52
        line 106: 61
        line 107: 70
        line 108: 79
        line 109: 88
        line 110: 97
        line 111: 106
        line 112: 115
        line 113: 124
        line 114: 133
        line 115: 142
        line 116: 151
        line 118: 160
        line 95: 168

  public scala.reflect.ManifestFactory$ByteManifest Byte();
    descriptor: ()Lscala/reflect/ManifestFactory$ByteManifest;
    flags: (0x0001) ACC_PUBLIC
    Code:
      stack=1, locals=1, args_size=1
         0: getstatic     #107                // Field Byte:Lscala/reflect/ManifestFactory$ByteManifest;
         3: areturn
      LineNumberTable:
        line 102: 0
      LocalVariableTable:
        Start  Length  Slot  Name   Signature
            0       4     0  this   Lscala/reflect/ClassTag$;

  public scala.reflect.ManifestFactory$ShortManifest Short();
    descriptor: ()Lscala/reflect/ManifestFactory$ShortManifest;
    flags: (0x0001) ACC_PUBLIC
    Code:
      stack=1, locals=1, args_size=1
         0: getstatic     #112                // Field Short:Lscala/reflect/ManifestFactory$ShortManifest;
         3: areturn
      LineNumberTable:
        line 103: 0
      LocalVariableTable:
        Start  Length  Slot  Name   Signature
            0       4     0  this   Lscala/reflect/ClassTag$;

  public scala.reflect.ManifestFactory$CharManifest Char();
    descriptor: ()Lscala/reflect/ManifestFactory$CharManifest;
    flags: (0x0001) ACC_PUBLIC
    Code:
      stack=1, locals=1, args_size=1
         0: getstatic     #117                // Field Char:Lscala/reflect/ManifestFactory$CharManifest;
         3: areturn
      LineNumberTable:
        line 104: 0
      LocalVariableTable:
        Start  Length  Slot  Name   Signature
            0       4     0  this   Lscala/reflect/ClassTag$;

  public scala.reflect.ManifestFactory$IntManifest Int();
    descriptor: ()Lscala/reflect/ManifestFactory$IntManifest;
    flags: (0x0001) ACC_PUBLIC
    Code:
      stack=1, locals=1, args_size=1
         0: getstatic     #122                // Field Int:Lscala/reflect/ManifestFactory$IntManifest;
         3: areturn
      LineNumberTable:
        line 105: 0
      LocalVariableTable:
        Start  Length  Slot  Name   Signature
            0       4     0  this   Lscala/reflect/ClassTag$;

  public scala.reflect.ManifestFactory$LongManifest Long();
    descriptor: ()Lscala/reflect/ManifestFactory$LongManifest;
    flags: (0x0001) ACC_PUBLIC
    Code:
      stack=1, locals=1, args_size=1
         0: getstatic     #127                // Field Long:Lscala/reflect/ManifestFactory$LongManifest;
         3: areturn
      LineNumberTable:
        line 106: 0
      LocalVariableTable:
        Start  Length  Slot  Name   Signature
            0       4     0  this   Lscala/reflect/ClassTag$;

  public scala.reflect.ManifestFactory$FloatManifest Float();
    descriptor: ()Lscala/reflect/ManifestFactory$FloatManifest;
    flags: (0x0001) ACC_PUBLIC
    Code:
      stack=1, locals=1, args_size=1
         0: getstatic     #132                // Field Float:Lscala/reflect/ManifestFactory$FloatManifest;
         3: areturn
      LineNumberTable:
        line 107: 0
      LocalVariableTable:
        Start  Length  Slot  Name   Signature
            0       4     0  this   Lscala/reflect/ClassTag$;

  public scala.reflect.ManifestFactory$DoubleManifest Double();
    descriptor: ()Lscala/reflect/ManifestFactory$DoubleManifest;
    flags: (0x0001) ACC_PUBLIC
    Code:
      stack=1, locals=1, args_size=1
         0: getstatic     #137                // Field Double:Lscala/reflect/ManifestFactory$DoubleManifest;
         3: areturn
      LineNumberTable:
        line 108: 0
      LocalVariableTable:
        Start  Length  Slot  Name   Signature
            0       4     0  this   Lscala/reflect/ClassTag$;

  public scala.reflect.ManifestFactory$BooleanManifest Boolean();
    descriptor: ()Lscala/reflect/ManifestFactory$BooleanManifest;
    flags: (0x0001) ACC_PUBLIC
    Code:
      stack=1, locals=1, args_size=1
         0: getstatic     #142                // Field Boolean:Lscala/reflect/ManifestFactory$BooleanManifest;
         3: areturn
      LineNumberTable:
        line 109: 0
      LocalVariableTable:
        Start  Length  Slot  Name   Signature
            0       4     0  this   Lscala/reflect/ClassTag$;

  public scala.reflect.ManifestFactory$UnitManifest Unit();
    descriptor: ()Lscala/reflect/ManifestFactory$UnitManifest;
    flags: (0x0001) ACC_PUBLIC
    Code:
      stack=1, locals=1, args_size=1
         0: getstatic     #147                // Field Unit:Lscala/reflect/ManifestFactory$UnitManifest;
         3: areturn
      LineNumberTable:
        line 110: 0
      LocalVariableTable:
        Start  Length  Slot  Name   Signature
            0       4     0  this   Lscala/reflect/ClassTag$;

  public scala.reflect.ClassTag<java.lang.Object> Any();
    descriptor: ()Lscala/reflect/ClassTag;
    flags: (0x0001) ACC_PUBLIC
    Code:
      stack=1, locals=1, args_size=1
         0: getstatic     #152                // Field Any:Lscala/reflect/ClassTag;
         3: areturn
      LineNumberTable:
        line 111: 0
      LocalVariableTable:
        Start  Length  Slot  Name   Signature
            0       4     0  this   Lscala/reflect/ClassTag$;
    Signature: #185                         // ()Lscala/reflect/ClassTag<Ljava/lang/Object;>;

  public scala.reflect.ClassTag<java.lang.Object> Object();
    descriptor: ()Lscala/reflect/ClassTag;
    flags: (0x0001) ACC_PUBLIC
    Code:
      stack=1, locals=1, args_size=1
         0: getstatic     #156                // Field Object:Lscala/reflect/ClassTag;
         3: areturn
      LineNumberTable:
        line 112: 0
      LocalVariableTable:
        Start  Length  Slot  Name   Signature
            0       4     0  this   Lscala/reflect/ClassTag$;
    Signature: #185                         // ()Lscala/reflect/ClassTag<Ljava/lang/Object;>;

  public scala.reflect.ClassTag<java.lang.Object> AnyVal();
    descriptor: ()Lscala/reflect/ClassTag;
    flags: (0x0001) ACC_PUBLIC
    Code:
      stack=1, locals=1, args_size=1
         0: getstatic     #160                // Field AnyVal:Lscala/reflect/ClassTag;
         3: areturn
      LineNumberTable:
        line 113: 0
      LocalVariableTable:
        Start  Length  Slot  Name   Signature
            0       4     0  this   Lscala/reflect/ClassTag$;
    Signature: #185                         // ()Lscala/reflect/ClassTag<Ljava/lang/Object;>;

  public scala.reflect.ClassTag<java.lang.Object> AnyRef();
    descriptor: ()Lscala/reflect/ClassTag;
    flags: (0x0001) ACC_PUBLIC
    Code:
      stack=1, locals=1, args_size=1
         0: getstatic     #164                // Field AnyRef:Lscala/reflect/ClassTag;
         3: areturn
      LineNumberTable:
        line 114: 0
      LocalVariableTable:
        Start  Length  Slot  Name   Signature
            0       4     0  this   Lscala/reflect/ClassTag$;
    Signature: #185                         // ()Lscala/reflect/ClassTag<Ljava/lang/Object;>;

  public scala.reflect.ClassTag<scala.runtime.Nothing$> Nothing();
    descriptor: ()Lscala/reflect/ClassTag;
    flags: (0x0001) ACC_PUBLIC
    Code:
      stack=1, locals=1, args_size=1
         0: getstatic     #168                // Field Nothing:Lscala/reflect/ClassTag;
         3: areturn
      LineNumberTable:
        line 115: 0
      LocalVariableTable:
        Start  Length  Slot  Name   Signature
            0       4     0  this   Lscala/reflect/ClassTag$;
    Signature: #186                         // ()Lscala/reflect/ClassTag<Lscala/runtime/Nothing$;>;

  public scala.reflect.ClassTag<scala.runtime.Null$> Null();
    descriptor: ()Lscala/reflect/ClassTag;
    flags: (0x0001) ACC_PUBLIC
    Code:
      stack=1, locals=1, args_size=1
         0: getstatic     #172                // Field Null:Lscala/reflect/ClassTag;
         3: areturn
      LineNumberTable:
        line 116: 0
      LocalVariableTable:
        Start  Length  Slot  Name   Signature
            0       4     0  this   Lscala/reflect/ClassTag$;
    Signature: #187                         // ()Lscala/reflect/ClassTag<Lscala/runtime/Null$;>;

  private boolean cacheDisabled();
    descriptor: ()Z
    flags: (0x0002) ACC_PRIVATE
    Code:
      stack=1, locals=1, args_size=1
         0: getstatic     #182                // Field cacheDisabled:Z
         3: ireturn
      LineNumberTable:
        line 118: 0
      LocalVariableTable:
        Start  Length  Slot  Name   Signature
            0       4     0  this   Lscala/reflect/ClassTag$;

  public <T extends java.lang.Object> scala.reflect.ClassTag<T> apply(java.lang.Class<?>);
    descriptor: (Ljava/lang/Class;)Lscala/reflect/ClassTag;
    flags: (0x0001) ACC_PUBLIC
    Code:
      stack=2, locals=3, args_size=2
         0: aload_0
         1: invokespecial #194                // Method cacheDisabled:()Z
         4: ifeq          15
         7: getstatic     #197                // Field scala/reflect/ClassTag$cache$.MODULE$:Lscala/reflect/ClassTag$cache$;
        10: aload_1
        11: invokevirtual #200                // Method scala/reflect/ClassTag$cache$.computeTag:(Ljava/lang/Class;)Lscala/reflect/ClassTag;
        14: areturn
        15: getstatic     #197                // Field scala/reflect/ClassTag$cache$.MODULE$:Lscala/reflect/ClassTag$cache$;
        18: aload_1
        19: invokevirtual #204                // Method scala/reflect/ClassTag$cache$.get:(Ljava/lang/Class;)Ljava/lang/Object;
        22: checkcast     #206                // class java/lang/ref/WeakReference
        25: invokevirtual #209                // Method java/lang/ref/WeakReference.get:()Ljava/lang/Object;
        28: checkcast     #11                 // class scala/reflect/ClassTag
        31: astore_2
        32: aload_2
        33: ifnonnull     51
        36: getstatic     #197                // Field scala/reflect/ClassTag$cache$.MODULE$:Lscala/reflect/ClassTag$cache$;
        39: aload_1
        40: invokevirtual #213                // Method scala/reflect/ClassTag$cache$.remove:(Ljava/lang/Class;)V
        43: getstatic     #197                // Field scala/reflect/ClassTag$cache$.MODULE$:Lscala/reflect/ClassTag$cache$;
        46: aload_1
        47: invokevirtual #200                // Method scala/reflect/ClassTag$cache$.computeTag:(Ljava/lang/Class;)Lscala/reflect/ClassTag;
        50: astore_2
        51: aload_2
        52: areturn
      StackMapTable: number_of_entries = 2
        frame_type = 15 /* same */
        frame_type = 252 /* append */
          offset_delta = 35
          locals = [ class scala/reflect/ClassTag ]
      LineNumberTable:
        line 154: 0
        line 155: 7
        line 157: 15
        line 158: 25
        line 159: 32
        line 160: 36
        line 161: 43
        line 163: 51
      LocalVariableTable:
        Start  Length  Slot  Name   Signature
           32      20     2   tag   Lscala/reflect/ClassTag;
            0      53     0  this   Lscala/reflect/ClassTag$;
            0      53     1 runtimeClass1   Ljava/lang/Class;
    Signature: #191                         // <T:Ljava/lang/Object;>(Ljava/lang/Class<*>;)Lscala/reflect/ClassTag<TT;>;
    MethodParameters:
      Name                           Flags
      runtimeClass1                  final

  public <T extends java.lang.Object> scala.Option<java.lang.Class<?>> unapply(scala.reflect.ClassTag<T>);
    descriptor: (Lscala/reflect/ClassTag;)Lscala/Option;
    flags: (0x0001) ACC_PUBLIC
    Code:
      stack=3, locals=2, args_size=2
         0: new           #220                // class scala/Some
         3: dup
         4: aload_1
         5: invokeinterface #224,  1          // InterfaceMethod scala/reflect/ClassTag.runtimeClass:()Ljava/lang/Class;
        10: invokespecial #227                // Method scala/Some."<init>":(Ljava/lang/Object;)V
        13: areturn
      LineNumberTable:
        line 167: 0
      LocalVariableTable:
        Start  Length  Slot  Name   Signature
            0      14     0  this   Lscala/reflect/ClassTag$;
            0      14     1  ctag   Lscala/reflect/ClassTag;
    Signature: #217                         // <T:Ljava/lang/Object;>(Lscala/reflect/ClassTag<TT;>;)Lscala/Option<Ljava/lang/Class<*>;>;
    MethodParameters:
      Name                           Flags
      ctag                           final

  private java.lang.Object writeReplace();
    descriptor: ()Ljava/lang/Object;
    flags: (0x0002) ACC_PRIVATE
    Code:
      stack=3, locals=1, args_size=1
         0: new           #230                // class scala/runtime/ModuleSerializationProxy
         3: dup
         4: ldc           #2                  // class scala/reflect/ClassTag$
         6: invokespecial #232                // Method scala/runtime/ModuleSerializationProxy."<init>":(Ljava/lang/Class;)V
         9: areturn
      LineNumberTable:
        line 95: 0
      LocalVariableTable:
        Start  Length  Slot  Name   Signature
            0      10     0  this   Lscala/reflect/ClassTag$;

  private scala.reflect.ClassTag$();
    descriptor: ()V
    flags: (0x0002) ACC_PRIVATE
    Code:
      stack=1, locals=1, args_size=1
         0: aload_0
         1: invokespecial #233                // Method java/lang/Object."<init>":()V
         4: return
      LineNumberTable:
        line 95: 0
      LocalVariableTable:
        Start  Length  Slot  Name   Signature
            0       5     0  this   Lscala/reflect/ClassTag$;
}
InnerClasses:
  private static #12= #9 of #11;          // cache$=class scala/reflect/ClassTag$cache$ of class scala/reflect/ClassTag
  public static final #17= #14 of #16;    // BooleanManifest=class scala/reflect/ManifestFactory$BooleanManifest of class scala/reflect/ManifestFactory
  public static final #20= #19 of #16;    // ByteManifest=class scala/reflect/ManifestFactory$ByteManifest of class scala/reflect/ManifestFactory
  public static final #23= #22 of #16;    // CharManifest=class scala/reflect/ManifestFactory$CharManifest of class scala/reflect/ManifestFactory
  public static final #26= #25 of #16;    // DoubleManifest=class scala/reflect/ManifestFactory$DoubleManifest of class scala/reflect/ManifestFactory
  public static final #29= #28 of #16;    // FloatManifest=class scala/reflect/ManifestFactory$FloatManifest of class scala/reflect/ManifestFactory
  public static final #32= #31 of #16;    // IntManifest=class scala/reflect/ManifestFactory$IntManifest of class scala/reflect/ManifestFactory
  public static final #35= #34 of #16;    // LongManifest=class scala/reflect/ManifestFactory$LongManifest of class scala/reflect/ManifestFactory
  public static final #38= #37 of #16;    // ShortManifest=class scala/reflect/ManifestFactory$ShortManifest of class scala/reflect/ManifestFactory
  public static final #41= #40 of #16;    // UnitManifest=class scala/reflect/ManifestFactory$UnitManifest of class scala/reflect/ManifestFactory
SourceFile: "ClassTag.scala"
  ScalaInlineInfo: length = 0x68 (unknown attribute)
   01 01 00 14 00 53 00 52 01 00 45 00 B8 01 00 4A
   00 B8 01 00 49 00 B8 01 00 41 00 8A 01 00 33 00
   67 01 00 37 00 71 01 00 3F 00 85 01 00 3D 00 80
   01 00 39 00 76 01 00 3B 00 7B 01 00 4B 00 B8 01
   00 4D 00 B8 01 00 48 00 B8 01 00 35 00 6C 01 00
   43 00 8F 01 00 BD 00 BE 01 00 4F 00 BC 01 00 D7
   00 D8 01 00 E4 00 CF 01
  Scala: length = 0x0 (unknown attribute)

