Classfile /Users/mw/Projects/slang-braindump/.jar/jar8/assemble/slang-braindump/assemble/content/scala/reflect/ManifestFactory$.class
  Last modified May 29, 2022; size 10244 bytes
  SHA-256 checksum e47b767d4529dc4231144abc057bd5b03afc8bb9e06da5cc7e5e6bcf847aca52
  Compiled from "Manifest.scala"
public final class scala.reflect.ManifestFactory$
  minor version: 0
  major version: 52
  flags: (0x0031) ACC_PUBLIC, ACC_FINAL, ACC_SUPER
  this_class: #2                          // scala/reflect/ManifestFactory$
  super_class: #4                         // java/lang/Object
  interfaces: 0, fields: 19, methods: 26, attributes: 4
Constant pool:
    #1 = Utf8               scala/reflect/ManifestFactory$
    #2 = Class              #1            // scala/reflect/ManifestFactory$
    #3 = Utf8               java/lang/Object
    #4 = Class              #3            // java/lang/Object
    #5 = Utf8               Manifest.scala
    #6 = Utf8               scala/reflect/ManifestFactory$AbstractTypeManifest
    #7 = Class              #6            // scala/reflect/ManifestFactory$AbstractTypeManifest
    #8 = Utf8               scala/reflect/ManifestFactory
    #9 = Class              #8            // scala/reflect/ManifestFactory
   #10 = Utf8               AbstractTypeManifest
   #11 = Utf8               scala/reflect/ManifestFactory$AnyManifest
   #12 = Class              #11           // scala/reflect/ManifestFactory$AnyManifest
   #13 = Utf8               AnyManifest
   #14 = Utf8               scala/reflect/ManifestFactory$AnyValPhantomManifest
   #15 = Class              #14           // scala/reflect/ManifestFactory$AnyValPhantomManifest
   #16 = Utf8               AnyValPhantomManifest
   #17 = Utf8               scala/reflect/ManifestFactory$BooleanManifest
   #18 = Class              #17           // scala/reflect/ManifestFactory$BooleanManifest
   #19 = Utf8               BooleanManifest
   #20 = Utf8               scala/reflect/ManifestFactory$ByteManifest
   #21 = Class              #20           // scala/reflect/ManifestFactory$ByteManifest
   #22 = Utf8               ByteManifest
   #23 = Utf8               scala/reflect/ManifestFactory$CharManifest
   #24 = Class              #23           // scala/reflect/ManifestFactory$CharManifest
   #25 = Utf8               CharManifest
   #26 = Utf8               scala/reflect/ManifestFactory$ClassTypeManifest
   #27 = Class              #26           // scala/reflect/ManifestFactory$ClassTypeManifest
   #28 = Utf8               ClassTypeManifest
   #29 = Utf8               scala/reflect/ManifestFactory$DoubleManifest
   #30 = Class              #29           // scala/reflect/ManifestFactory$DoubleManifest
   #31 = Utf8               DoubleManifest
   #32 = Utf8               scala/reflect/ManifestFactory$FloatManifest
   #33 = Class              #32           // scala/reflect/ManifestFactory$FloatManifest
   #34 = Utf8               FloatManifest
   #35 = Utf8               scala/reflect/ManifestFactory$IntManifest
   #36 = Class              #35           // scala/reflect/ManifestFactory$IntManifest
   #37 = Utf8               IntManifest
   #38 = Utf8               scala/reflect/ManifestFactory$IntersectionTypeManifest
   #39 = Class              #38           // scala/reflect/ManifestFactory$IntersectionTypeManifest
   #40 = Utf8               IntersectionTypeManifest
   #41 = Utf8               scala/reflect/ManifestFactory$LongManifest
   #42 = Class              #41           // scala/reflect/ManifestFactory$LongManifest
   #43 = Utf8               LongManifest
   #44 = Utf8               scala/reflect/ManifestFactory$NothingManifest
   #45 = Class              #44           // scala/reflect/ManifestFactory$NothingManifest
   #46 = Utf8               NothingManifest
   #47 = Utf8               scala/reflect/ManifestFactory$NullManifest
   #48 = Class              #47           // scala/reflect/ManifestFactory$NullManifest
   #49 = Utf8               NullManifest
   #50 = Utf8               scala/reflect/ManifestFactory$ObjectManifest
   #51 = Class              #50           // scala/reflect/ManifestFactory$ObjectManifest
   #52 = Utf8               ObjectManifest
   #53 = Utf8               scala/reflect/ManifestFactory$ShortManifest
   #54 = Class              #53           // scala/reflect/ManifestFactory$ShortManifest
   #55 = Utf8               ShortManifest
   #56 = Utf8               scala/reflect/ManifestFactory$SingletonTypeManifest
   #57 = Class              #56           // scala/reflect/ManifestFactory$SingletonTypeManifest
   #58 = Utf8               SingletonTypeManifest
   #59 = Utf8               scala/reflect/ManifestFactory$UnitManifest
   #60 = Class              #59           // scala/reflect/ManifestFactory$UnitManifest
   #61 = Utf8               UnitManifest
   #62 = Utf8               scala/reflect/ManifestFactory$WildcardManifest
   #63 = Class              #62           // scala/reflect/ManifestFactory$WildcardManifest
   #64 = Utf8               WildcardManifest
   #65 = Utf8               MODULE$
   #66 = Utf8               Lscala/reflect/ManifestFactory$;
   #67 = Utf8               Byte
   #68 = Utf8               Lscala/reflect/ManifestFactory$ByteManifest;
   #69 = Utf8               Short
   #70 = Utf8               Lscala/reflect/ManifestFactory$ShortManifest;
   #71 = Utf8               Char
   #72 = Utf8               Lscala/reflect/ManifestFactory$CharManifest;
   #73 = Utf8               Int
   #74 = Utf8               Lscala/reflect/ManifestFactory$IntManifest;
   #75 = Utf8               Long
   #76 = Utf8               Lscala/reflect/ManifestFactory$LongManifest;
   #77 = Utf8               Float
   #78 = Utf8               Lscala/reflect/ManifestFactory$FloatManifest;
   #79 = Utf8               Double
   #80 = Utf8               Lscala/reflect/ManifestFactory$DoubleManifest;
   #81 = Utf8               Boolean
   #82 = Utf8               Lscala/reflect/ManifestFactory$BooleanManifest;
   #83 = Utf8               Unit
   #84 = Utf8               Lscala/reflect/ManifestFactory$UnitManifest;
   #85 = Utf8               scala$reflect$ManifestFactory$$ObjectTYPE
   #86 = Utf8               Ljava/lang/Class;
   #87 = Utf8               Ljava/lang/Class<Ljava/lang/Object;>;
   #88 = Utf8               scala$reflect$ManifestFactory$$NothingTYPE
   #89 = Utf8               Ljava/lang/Class<Lscala/runtime/Nothing$;>;
   #90 = Utf8               scala$reflect$ManifestFactory$$NullTYPE
   #91 = Utf8               Ljava/lang/Class<Lscala/runtime/Null$;>;
   #92 = Utf8               Any
   #93 = Utf8               Lscala/reflect/Manifest;
   #94 = Utf8               Lscala/reflect/Manifest<Ljava/lang/Object;>;
   #95 = Utf8               Object
   #96 = Utf8               AnyRef
   #97 = Utf8               AnyVal
   #98 = Utf8               Null
   #99 = Utf8               Lscala/reflect/Manifest<Lscala/runtime/Null$;>;
  #100 = Utf8               Nothing
  #101 = Utf8               Lscala/reflect/Manifest<Lscala/runtime/Nothing$;>;
  #102 = Utf8               <clinit>
  #103 = Utf8               ()V
  #104 = Utf8               <init>
  #105 = NameAndType        #104:#103     // "<init>":()V
  #106 = Methodref          #2.#105       // scala/reflect/ManifestFactory$."<init>":()V
  #107 = NameAndType        #65:#66       // MODULE$:Lscala/reflect/ManifestFactory$;
  #108 = Fieldref           #2.#107       // scala/reflect/ManifestFactory$.MODULE$:Lscala/reflect/ManifestFactory$;
  #109 = Methodref          #21.#105      // scala/reflect/ManifestFactory$ByteManifest."<init>":()V
  #110 = NameAndType        #67:#68       // Byte:Lscala/reflect/ManifestFactory$ByteManifest;
  #111 = Fieldref           #2.#110       // scala/reflect/ManifestFactory$.Byte:Lscala/reflect/ManifestFactory$ByteManifest;
  #112 = Methodref          #54.#105      // scala/reflect/ManifestFactory$ShortManifest."<init>":()V
  #113 = NameAndType        #69:#70       // Short:Lscala/reflect/ManifestFactory$ShortManifest;
  #114 = Fieldref           #2.#113       // scala/reflect/ManifestFactory$.Short:Lscala/reflect/ManifestFactory$ShortManifest;
  #115 = Methodref          #24.#105      // scala/reflect/ManifestFactory$CharManifest."<init>":()V
  #116 = NameAndType        #71:#72       // Char:Lscala/reflect/ManifestFactory$CharManifest;
  #117 = Fieldref           #2.#116       // scala/reflect/ManifestFactory$.Char:Lscala/reflect/ManifestFactory$CharManifest;
  #118 = Methodref          #36.#105      // scala/reflect/ManifestFactory$IntManifest."<init>":()V
  #119 = NameAndType        #73:#74       // Int:Lscala/reflect/ManifestFactory$IntManifest;
  #120 = Fieldref           #2.#119       // scala/reflect/ManifestFactory$.Int:Lscala/reflect/ManifestFactory$IntManifest;
  #121 = Methodref          #42.#105      // scala/reflect/ManifestFactory$LongManifest."<init>":()V
  #122 = NameAndType        #75:#76       // Long:Lscala/reflect/ManifestFactory$LongManifest;
  #123 = Fieldref           #2.#122       // scala/reflect/ManifestFactory$.Long:Lscala/reflect/ManifestFactory$LongManifest;
  #124 = Methodref          #33.#105      // scala/reflect/ManifestFactory$FloatManifest."<init>":()V
  #125 = NameAndType        #77:#78       // Float:Lscala/reflect/ManifestFactory$FloatManifest;
  #126 = Fieldref           #2.#125       // scala/reflect/ManifestFactory$.Float:Lscala/reflect/ManifestFactory$FloatManifest;
  #127 = Methodref          #30.#105      // scala/reflect/ManifestFactory$DoubleManifest."<init>":()V
  #128 = NameAndType        #79:#80       // Double:Lscala/reflect/ManifestFactory$DoubleManifest;
  #129 = Fieldref           #2.#128       // scala/reflect/ManifestFactory$.Double:Lscala/reflect/ManifestFactory$DoubleManifest;
  #130 = Methodref          #18.#105      // scala/reflect/ManifestFactory$BooleanManifest."<init>":()V
  #131 = NameAndType        #81:#82       // Boolean:Lscala/reflect/ManifestFactory$BooleanManifest;
  #132 = Fieldref           #2.#131       // scala/reflect/ManifestFactory$.Boolean:Lscala/reflect/ManifestFactory$BooleanManifest;
  #133 = Methodref          #60.#105      // scala/reflect/ManifestFactory$UnitManifest."<init>":()V
  #134 = NameAndType        #83:#84       // Unit:Lscala/reflect/ManifestFactory$UnitManifest;
  #135 = Fieldref           #2.#134       // scala/reflect/ManifestFactory$.Unit:Lscala/reflect/ManifestFactory$UnitManifest;
  #136 = NameAndType        #85:#86       // scala$reflect$ManifestFactory$$ObjectTYPE:Ljava/lang/Class;
  #137 = Fieldref           #2.#136       // scala/reflect/ManifestFactory$.scala$reflect$ManifestFactory$$ObjectTYPE:Ljava/lang/Class;
  #138 = Utf8               scala/runtime/Nothing$
  #139 = Class              #138          // scala/runtime/Nothing$
  #140 = NameAndType        #88:#86       // scala$reflect$ManifestFactory$$NothingTYPE:Ljava/lang/Class;
  #141 = Fieldref           #2.#140       // scala/reflect/ManifestFactory$.scala$reflect$ManifestFactory$$NothingTYPE:Ljava/lang/Class;
  #142 = Utf8               scala/runtime/Null$
  #143 = Class              #142          // scala/runtime/Null$
  #144 = NameAndType        #90:#86       // scala$reflect$ManifestFactory$$NullTYPE:Ljava/lang/Class;
  #145 = Fieldref           #2.#144       // scala/reflect/ManifestFactory$.scala$reflect$ManifestFactory$$NullTYPE:Ljava/lang/Class;
  #146 = Methodref          #12.#105      // scala/reflect/ManifestFactory$AnyManifest."<init>":()V
  #147 = NameAndType        #92:#93       // Any:Lscala/reflect/Manifest;
  #148 = Fieldref           #2.#147       // scala/reflect/ManifestFactory$.Any:Lscala/reflect/Manifest;
  #149 = Methodref          #51.#105      // scala/reflect/ManifestFactory$ObjectManifest."<init>":()V
  #150 = NameAndType        #95:#93       // Object:Lscala/reflect/Manifest;
  #151 = Fieldref           #2.#150       // scala/reflect/ManifestFactory$.Object:Lscala/reflect/Manifest;
  #152 = Utf8               ()Lscala/reflect/Manifest;
  #153 = NameAndType        #95:#152      // Object:()Lscala/reflect/Manifest;
  #154 = Methodref          #2.#153       // scala/reflect/ManifestFactory$.Object:()Lscala/reflect/Manifest;
  #155 = NameAndType        #96:#93       // AnyRef:Lscala/reflect/Manifest;
  #156 = Fieldref           #2.#155       // scala/reflect/ManifestFactory$.AnyRef:Lscala/reflect/Manifest;
  #157 = Methodref          #15.#105      // scala/reflect/ManifestFactory$AnyValPhantomManifest."<init>":()V
  #158 = NameAndType        #97:#93       // AnyVal:Lscala/reflect/Manifest;
  #159 = Fieldref           #2.#158       // scala/reflect/ManifestFactory$.AnyVal:Lscala/reflect/Manifest;
  #160 = Methodref          #48.#105      // scala/reflect/ManifestFactory$NullManifest."<init>":()V
  #161 = NameAndType        #98:#93       // Null:Lscala/reflect/Manifest;
  #162 = Fieldref           #2.#161       // scala/reflect/ManifestFactory$.Null:Lscala/reflect/Manifest;
  #163 = Methodref          #45.#105      // scala/reflect/ManifestFactory$NothingManifest."<init>":()V
  #164 = NameAndType        #100:#93      // Nothing:Lscala/reflect/Manifest;
  #165 = Fieldref           #2.#164       // scala/reflect/ManifestFactory$.Nothing:Lscala/reflect/Manifest;
  #166 = Utf8               valueManifests
  #167 = Utf8               ()Lscala/collection/immutable/List;
  #168 = Utf8               ()Lscala/collection/immutable/List<Lscala/reflect/AnyValManifest<*>;>;
  #169 = Utf8               scala/package$
  #170 = Class              #169          // scala/package$
  #171 = Utf8               Lscala/package$;
  #172 = NameAndType        #65:#171      // MODULE$:Lscala/package$;
  #173 = Fieldref           #170.#172     // scala/package$.MODULE$:Lscala/package$;
  #174 = Utf8               List
  #175 = Utf8               ()Lscala/collection/immutable/List$;
  #176 = NameAndType        #174:#175     // List:()Lscala/collection/immutable/List$;
  #177 = Methodref          #170.#176     // scala/package$.List:()Lscala/collection/immutable/List$;
  #178 = Utf8               scala/runtime/ScalaRunTime$
  #179 = Class              #178          // scala/runtime/ScalaRunTime$
  #180 = Utf8               Lscala/runtime/ScalaRunTime$;
  #181 = NameAndType        #65:#180      // MODULE$:Lscala/runtime/ScalaRunTime$;
  #182 = Fieldref           #179.#181     // scala/runtime/ScalaRunTime$.MODULE$:Lscala/runtime/ScalaRunTime$;
  #183 = Utf8               scala/reflect/AnyValManifest
  #184 = Class              #183          // scala/reflect/AnyValManifest
  #185 = Utf8               ()Lscala/reflect/ManifestFactory$ByteManifest;
  #186 = NameAndType        #67:#185      // Byte:()Lscala/reflect/ManifestFactory$ByteManifest;
  #187 = Methodref          #2.#186       // scala/reflect/ManifestFactory$.Byte:()Lscala/reflect/ManifestFactory$ByteManifest;
  #188 = Utf8               ()Lscala/reflect/ManifestFactory$ShortManifest;
  #189 = NameAndType        #69:#188      // Short:()Lscala/reflect/ManifestFactory$ShortManifest;
  #190 = Methodref          #2.#189       // scala/reflect/ManifestFactory$.Short:()Lscala/reflect/ManifestFactory$ShortManifest;
  #191 = Utf8               ()Lscala/reflect/ManifestFactory$CharManifest;
  #192 = NameAndType        #71:#191      // Char:()Lscala/reflect/ManifestFactory$CharManifest;
  #193 = Methodref          #2.#192       // scala/reflect/ManifestFactory$.Char:()Lscala/reflect/ManifestFactory$CharManifest;
  #194 = Utf8               ()Lscala/reflect/ManifestFactory$IntManifest;
  #195 = NameAndType        #73:#194      // Int:()Lscala/reflect/ManifestFactory$IntManifest;
  #196 = Methodref          #2.#195       // scala/reflect/ManifestFactory$.Int:()Lscala/reflect/ManifestFactory$IntManifest;
  #197 = Utf8               ()Lscala/reflect/ManifestFactory$LongManifest;
  #198 = NameAndType        #75:#197      // Long:()Lscala/reflect/ManifestFactory$LongManifest;
  #199 = Methodref          #2.#198       // scala/reflect/ManifestFactory$.Long:()Lscala/reflect/ManifestFactory$LongManifest;
  #200 = Utf8               ()Lscala/reflect/ManifestFactory$FloatManifest;
  #201 = NameAndType        #77:#200      // Float:()Lscala/reflect/ManifestFactory$FloatManifest;
  #202 = Methodref          #2.#201       // scala/reflect/ManifestFactory$.Float:()Lscala/reflect/ManifestFactory$FloatManifest;
  #203 = Utf8               ()Lscala/reflect/ManifestFactory$DoubleManifest;
  #204 = NameAndType        #79:#203      // Double:()Lscala/reflect/ManifestFactory$DoubleManifest;
  #205 = Methodref          #2.#204       // scala/reflect/ManifestFactory$.Double:()Lscala/reflect/ManifestFactory$DoubleManifest;
  #206 = Utf8               ()Lscala/reflect/ManifestFactory$BooleanManifest;
  #207 = NameAndType        #81:#206      // Boolean:()Lscala/reflect/ManifestFactory$BooleanManifest;
  #208 = Methodref          #2.#207       // scala/reflect/ManifestFactory$.Boolean:()Lscala/reflect/ManifestFactory$BooleanManifest;
  #209 = Utf8               ()Lscala/reflect/ManifestFactory$UnitManifest;
  #210 = NameAndType        #83:#209      // Unit:()Lscala/reflect/ManifestFactory$UnitManifest;
  #211 = Methodref          #2.#210       // scala/reflect/ManifestFactory$.Unit:()Lscala/reflect/ManifestFactory$UnitManifest;
  #212 = Utf8               wrapRefArray
  #213 = Utf8               ([Ljava/lang/Object;)Lscala/collection/immutable/ArraySeq;
  #214 = NameAndType        #212:#213     // wrapRefArray:([Ljava/lang/Object;)Lscala/collection/immutable/ArraySeq;
  #215 = Methodref          #179.#214     // scala/runtime/ScalaRunTime$.wrapRefArray:([Ljava/lang/Object;)Lscala/collection/immutable/ArraySeq;
  #216 = Utf8               scala/collection/immutable/Nil$
  #217 = Class              #216          // scala/collection/immutable/Nil$
  #218 = Utf8               Lscala/collection/immutable/Nil$;
  #219 = NameAndType        #65:#218      // MODULE$:Lscala/collection/immutable/Nil$;
  #220 = Fieldref           #217.#219     // scala/collection/immutable/Nil$.MODULE$:Lscala/collection/immutable/Nil$;
  #221 = Utf8               prependedAll
  #222 = Utf8               (Lscala/collection/IterableOnce;)Lscala/collection/immutable/List;
  #223 = NameAndType        #221:#222     // prependedAll:(Lscala/collection/IterableOnce;)Lscala/collection/immutable/List;
  #224 = Methodref          #217.#223     // scala/collection/immutable/Nil$.prependedAll:(Lscala/collection/IterableOnce;)Lscala/collection/immutable/List;
  #225 = Utf8               this
  #226 = Utf8               apply_elems
  #227 = Utf8               Lscala/collection/immutable/Seq;
  #228 = Utf8               scala/collection/immutable/ArraySeq
  #229 = Class              #228          // scala/collection/immutable/ArraySeq
  #230 = Utf8               ()Lscala/reflect/Manifest<Ljava/lang/Object;>;
  #231 = Utf8               ()Lscala/reflect/Manifest<Lscala/runtime/Null$;>;
  #232 = Utf8               ()Lscala/reflect/Manifest<Lscala/runtime/Nothing$;>;
  #233 = Utf8               singleType
  #234 = Utf8               (Ljava/lang/Object;)Lscala/reflect/Manifest;
  #235 = Utf8               <T:Ljava/lang/Object;>(Ljava/lang/Object;)Lscala/reflect/Manifest<TT;>;
  #236 = Utf8               value
  #237 = Utf8               (Ljava/lang/Object;)V
  #238 = NameAndType        #104:#237     // "<init>":(Ljava/lang/Object;)V
  #239 = Methodref          #57.#238      // scala/reflect/ManifestFactory$SingletonTypeManifest."<init>":(Ljava/lang/Object;)V
  #240 = Utf8               Ljava/lang/Object;
  #241 = Utf8               classType
  #242 = Utf8               (Ljava/lang/Class;)Lscala/reflect/Manifest;
  #243 = Utf8               <T:Ljava/lang/Object;>(Ljava/lang/Class<*>;)Lscala/reflect/Manifest<TT;>;
  #244 = Utf8               clazz
  #245 = Utf8               scala/None$
  #246 = Class              #245          // scala/None$
  #247 = Utf8               Lscala/None$;
  #248 = NameAndType        #65:#247      // MODULE$:Lscala/None$;
  #249 = Fieldref           #246.#248     // scala/None$.MODULE$:Lscala/None$;
  #250 = Utf8               Nil
  #251 = Utf8               ()Lscala/collection/immutable/Nil$;
  #252 = NameAndType        #250:#251     // Nil:()Lscala/collection/immutable/Nil$;
  #253 = Methodref          #170.#252     // scala/package$.Nil:()Lscala/collection/immutable/Nil$;
  #254 = Utf8               (Lscala/Option;Ljava/lang/Class;Lscala/collection/immutable/List;)V
  #255 = NameAndType        #104:#254     // "<init>":(Lscala/Option;Ljava/lang/Class;Lscala/collection/immutable/List;)V
  #256 = Methodref          #27.#255      // scala/reflect/ManifestFactory$ClassTypeManifest."<init>":(Lscala/Option;Ljava/lang/Class;Lscala/collection/immutable/List;)V
  #257 = Utf8               (Ljava/lang/Class;Lscala/reflect/Manifest;Lscala/collection/immutable/Seq;)Lscala/reflect/Manifest;
  #258 = Utf8               <T:Ljava/lang/Object;>(Ljava/lang/Class<TT;>;Lscala/reflect/Manifest<*>;Lscala/collection/immutable/Seq<Lscala/reflect/Manifest<*>;>;)Lscala/reflect/Manifest<TT;>;
  #259 = Utf8               arg1
  #260 = Utf8               args
  #261 = Utf8               scala/collection/immutable/Seq
  #262 = Class              #261          // scala/collection/immutable/Seq
  #263 = Utf8               toList
  #264 = NameAndType        #263:#167     // toList:()Lscala/collection/immutable/List;
  #265 = InterfaceMethodref #262.#264     // scala/collection/immutable/Seq.toList:()Lscala/collection/immutable/List;
  #266 = Utf8               scala/collection/immutable/$colon$colon
  #267 = Class              #266          // scala/collection/immutable/$colon$colon
  #268 = Utf8               (Ljava/lang/Object;Lscala/collection/immutable/List;)V
  #269 = NameAndType        #104:#268     // "<init>":(Ljava/lang/Object;Lscala/collection/immutable/List;)V
  #270 = Methodref          #267.#269     // scala/collection/immutable/$colon$colon."<init>":(Ljava/lang/Object;Lscala/collection/immutable/List;)V
  #271 = Utf8               $colon$colon_this
  #272 = Utf8               Lscala/collection/immutable/List;
  #273 = Utf8               java/lang/Class
  #274 = Class              #273          // java/lang/Class
  #275 = Utf8               scala/reflect/Manifest
  #276 = Class              #275          // scala/reflect/Manifest
  #277 = Utf8               scala/collection/immutable/List
  #278 = Class              #277          // scala/collection/immutable/List
  #279 = Utf8               (Lscala/reflect/Manifest;Ljava/lang/Class;Lscala/collection/immutable/Seq;)Lscala/reflect/Manifest;
  #280 = Utf8               <T:Ljava/lang/Object;>(Lscala/reflect/Manifest<*>;Ljava/lang/Class<*>;Lscala/collection/immutable/Seq<Lscala/reflect/Manifest<*>;>;)Lscala/reflect/Manifest<TT;>;
  #281 = Utf8               prefix
  #282 = Utf8               scala/Some
  #283 = Class              #282          // scala/Some
  #284 = Methodref          #283.#238     // scala/Some."<init>":(Ljava/lang/Object;)V
  #285 = Utf8               arrayType
  #286 = Utf8               (Lscala/reflect/Manifest;)Lscala/reflect/Manifest;
  #287 = Utf8               <T:Ljava/lang/Object;>(Lscala/reflect/Manifest<*>;)Lscala/reflect/Manifest<Ljava/lang/Object;>;
  #288 = Utf8               arg
  #289 = Utf8               arrayManifest
  #290 = NameAndType        #289:#152     // arrayManifest:()Lscala/reflect/Manifest;
  #291 = InterfaceMethodref #276.#290     // scala/reflect/Manifest.arrayManifest:()Lscala/reflect/Manifest;
  #292 = Utf8               abstractType
  #293 = Utf8               (Lscala/reflect/Manifest;Ljava/lang/String;Ljava/lang/Class;Lscala/collection/immutable/Seq;)Lscala/reflect/Manifest;
  #294 = Utf8               <T:Ljava/lang/Object;>(Lscala/reflect/Manifest<*>;Ljava/lang/String;Ljava/lang/Class<*>;Lscala/collection/immutable/Seq<Lscala/reflect/Manifest<*>;>;)Lscala/reflect/Manifest<TT;>;
  #295 = Utf8               name
  #296 = Utf8               upperBound
  #297 = Utf8               (Lscala/reflect/Manifest;Ljava/lang/String;Ljava/lang/Class;Lscala/collection/Seq;)V
  #298 = NameAndType        #104:#297     // "<init>":(Lscala/reflect/Manifest;Ljava/lang/String;Ljava/lang/Class;Lscala/collection/Seq;)V
  #299 = Methodref          #7.#298       // scala/reflect/ManifestFactory$AbstractTypeManifest."<init>":(Lscala/reflect/Manifest;Ljava/lang/String;Ljava/lang/Class;Lscala/collection/Seq;)V
  #300 = Utf8               Ljava/lang/String;
  #301 = Utf8               wildcardType
  #302 = Utf8               (Lscala/reflect/Manifest;Lscala/reflect/Manifest;)Lscala/reflect/Manifest;
  #303 = Utf8               <T:Ljava/lang/Object;>(Lscala/reflect/Manifest<*>;Lscala/reflect/Manifest<*>;)Lscala/reflect/Manifest<TT;>;
  #304 = Utf8               lowerBound
  #305 = Utf8               (Lscala/reflect/Manifest;Lscala/reflect/Manifest;)V
  #306 = NameAndType        #104:#305     // "<init>":(Lscala/reflect/Manifest;Lscala/reflect/Manifest;)V
  #307 = Methodref          #63.#306      // scala/reflect/ManifestFactory$WildcardManifest."<init>":(Lscala/reflect/Manifest;Lscala/reflect/Manifest;)V
  #308 = Utf8               intersectionType
  #309 = Utf8               (Lscala/collection/immutable/Seq;)Lscala/reflect/Manifest;
  #310 = Utf8               <T:Ljava/lang/Object;>(Lscala/collection/immutable/Seq<Lscala/reflect/Manifest<*>;>;)Lscala/reflect/Manifest<TT;>;
  #311 = Utf8               parents
  #312 = Utf8               scala/reflect/ClassTag$
  #313 = Class              #312          // scala/reflect/ClassTag$
  #314 = Utf8               Lscala/reflect/ClassTag$;
  #315 = NameAndType        #65:#314      // MODULE$:Lscala/reflect/ClassTag$;
  #316 = Fieldref           #313.#315     // scala/reflect/ClassTag$.MODULE$:Lscala/reflect/ClassTag$;
  #317 = Utf8               apply
  #318 = Utf8               (Ljava/lang/Class;)Lscala/reflect/ClassTag;
  #319 = NameAndType        #317:#318     // apply:(Ljava/lang/Class;)Lscala/reflect/ClassTag;
  #320 = Methodref          #313.#319     // scala/reflect/ClassTag$.apply:(Ljava/lang/Class;)Lscala/reflect/ClassTag;
  #321 = Utf8               toArray
  #322 = Utf8               (Lscala/reflect/ClassTag;)Ljava/lang/Object;
  #323 = NameAndType        #321:#322     // toArray:(Lscala/reflect/ClassTag;)Ljava/lang/Object;
  #324 = InterfaceMethodref #262.#323     // scala/collection/immutable/Seq.toArray:(Lscala/reflect/ClassTag;)Ljava/lang/Object;
  #325 = Utf8               [Lscala/reflect/Manifest;
  #326 = Class              #325          // "[Lscala/reflect/Manifest;"
  #327 = Utf8               ([Lscala/reflect/Manifest;)V
  #328 = NameAndType        #104:#327     // "<init>":([Lscala/reflect/Manifest;)V
  #329 = Methodref          #39.#328      // scala/reflect/ManifestFactory$IntersectionTypeManifest."<init>":([Lscala/reflect/Manifest;)V
  #330 = Methodref          #4.#105       // java/lang/Object."<init>":()V
  #331 = Utf8               Signature
  #332 = Utf8               Code
  #333 = Utf8               LineNumberTable
  #334 = Utf8               StackMapTable
  #335 = Utf8               LocalVariableTable
  #336 = Utf8               MethodParameters
  #337 = Utf8               InnerClasses
  #338 = Utf8               SourceFile
  #339 = Utf8               ScalaInlineInfo
  #340 = Utf8               Scala
{
  public static final scala.reflect.ManifestFactory$ MODULE$;
    descriptor: Lscala/reflect/ManifestFactory$;
    flags: (0x0019) ACC_PUBLIC, ACC_STATIC, ACC_FINAL

  private static final scala.reflect.ManifestFactory$ByteManifest Byte;
    descriptor: Lscala/reflect/ManifestFactory$ByteManifest;
    flags: (0x001a) ACC_PRIVATE, ACC_STATIC, ACC_FINAL

  private static final scala.reflect.ManifestFactory$ShortManifest Short;
    descriptor: Lscala/reflect/ManifestFactory$ShortManifest;
    flags: (0x001a) ACC_PRIVATE, ACC_STATIC, ACC_FINAL

  private static final scala.reflect.ManifestFactory$CharManifest Char;
    descriptor: Lscala/reflect/ManifestFactory$CharManifest;
    flags: (0x001a) ACC_PRIVATE, ACC_STATIC, ACC_FINAL

  private static final scala.reflect.ManifestFactory$IntManifest Int;
    descriptor: Lscala/reflect/ManifestFactory$IntManifest;
    flags: (0x001a) ACC_PRIVATE, ACC_STATIC, ACC_FINAL

  private static final scala.reflect.ManifestFactory$LongManifest Long;
    descriptor: Lscala/reflect/ManifestFactory$LongManifest;
    flags: (0x001a) ACC_PRIVATE, ACC_STATIC, ACC_FINAL

  private static final scala.reflect.ManifestFactory$FloatManifest Float;
    descriptor: Lscala/reflect/ManifestFactory$FloatManifest;
    flags: (0x001a) ACC_PRIVATE, ACC_STATIC, ACC_FINAL

  private static final scala.reflect.ManifestFactory$DoubleManifest Double;
    descriptor: Lscala/reflect/ManifestFactory$DoubleManifest;
    flags: (0x001a) ACC_PRIVATE, ACC_STATIC, ACC_FINAL

  private static final scala.reflect.ManifestFactory$BooleanManifest Boolean;
    descriptor: Lscala/reflect/ManifestFactory$BooleanManifest;
    flags: (0x001a) ACC_PRIVATE, ACC_STATIC, ACC_FINAL

  private static final scala.reflect.ManifestFactory$UnitManifest Unit;
    descriptor: Lscala/reflect/ManifestFactory$UnitManifest;
    flags: (0x001a) ACC_PRIVATE, ACC_STATIC, ACC_FINAL

  public static final java.lang.Class<java.lang.Object> scala$reflect$ManifestFactory$$ObjectTYPE;
    descriptor: Ljava/lang/Class;
    flags: (0x0019) ACC_PUBLIC, ACC_STATIC, ACC_FINAL
    Signature: #87                          // Ljava/lang/Class<Ljava/lang/Object;>;

  public static final java.lang.Class<scala.runtime.Nothing$> scala$reflect$ManifestFactory$$NothingTYPE;
    descriptor: Ljava/lang/Class;
    flags: (0x0019) ACC_PUBLIC, ACC_STATIC, ACC_FINAL
    Signature: #89                          // Ljava/lang/Class<Lscala/runtime/Nothing$;>;

  public static final java.lang.Class<scala.runtime.Null$> scala$reflect$ManifestFactory$$NullTYPE;
    descriptor: Ljava/lang/Class;
    flags: (0x0019) ACC_PUBLIC, ACC_STATIC, ACC_FINAL
    Signature: #91                          // Ljava/lang/Class<Lscala/runtime/Null$;>;

  private static final scala.reflect.Manifest<java.lang.Object> Any;
    descriptor: Lscala/reflect/Manifest;
    flags: (0x001a) ACC_PRIVATE, ACC_STATIC, ACC_FINAL
    Signature: #94                          // Lscala/reflect/Manifest<Ljava/lang/Object;>;

  private static final scala.reflect.Manifest<java.lang.Object> Object;
    descriptor: Lscala/reflect/Manifest;
    flags: (0x001a) ACC_PRIVATE, ACC_STATIC, ACC_FINAL
    Signature: #94                          // Lscala/reflect/Manifest<Ljava/lang/Object;>;

  private static final scala.reflect.Manifest<java.lang.Object> AnyRef;
    descriptor: Lscala/reflect/Manifest;
    flags: (0x001a) ACC_PRIVATE, ACC_STATIC, ACC_FINAL
    Signature: #94                          // Lscala/reflect/Manifest<Ljava/lang/Object;>;

  private static final scala.reflect.Manifest<java.lang.Object> AnyVal;
    descriptor: Lscala/reflect/Manifest;
    flags: (0x001a) ACC_PRIVATE, ACC_STATIC, ACC_FINAL
    Signature: #94                          // Lscala/reflect/Manifest<Ljava/lang/Object;>;

  private static final scala.reflect.Manifest<scala.runtime.Null$> Null;
    descriptor: Lscala/reflect/Manifest;
    flags: (0x001a) ACC_PRIVATE, ACC_STATIC, ACC_FINAL
    Signature: #99                          // Lscala/reflect/Manifest<Lscala/runtime/Null$;>;

  private static final scala.reflect.Manifest<scala.runtime.Nothing$> Nothing;
    descriptor: Lscala/reflect/Manifest;
    flags: (0x001a) ACC_PRIVATE, ACC_STATIC, ACC_FINAL
    Signature: #101                         // Lscala/reflect/Manifest<Lscala/runtime/Nothing$;>;

  public static {};
    descriptor: ()V
    flags: (0x0009) ACC_PUBLIC, ACC_STATIC
    Code:
      stack=2, locals=0, args_size=0
         0: new           #2                  // class scala/reflect/ManifestFactory$
         3: dup
         4: invokespecial #106                // Method "<init>":()V
         7: putstatic     #108                // Field MODULE$:Lscala/reflect/ManifestFactory$;
        10: new           #21                 // class scala/reflect/ManifestFactory$ByteManifest
        13: dup
        14: invokespecial #109                // Method scala/reflect/ManifestFactory$ByteManifest."<init>":()V
        17: putstatic     #111                // Field Byte:Lscala/reflect/ManifestFactory$ByteManifest;
        20: new           #54                 // class scala/reflect/ManifestFactory$ShortManifest
        23: dup
        24: invokespecial #112                // Method scala/reflect/ManifestFactory$ShortManifest."<init>":()V
        27: putstatic     #114                // Field Short:Lscala/reflect/ManifestFactory$ShortManifest;
        30: new           #24                 // class scala/reflect/ManifestFactory$CharManifest
        33: dup
        34: invokespecial #115                // Method scala/reflect/ManifestFactory$CharManifest."<init>":()V
        37: putstatic     #117                // Field Char:Lscala/reflect/ManifestFactory$CharManifest;
        40: new           #36                 // class scala/reflect/ManifestFactory$IntManifest
        43: dup
        44: invokespecial #118                // Method scala/reflect/ManifestFactory$IntManifest."<init>":()V
        47: putstatic     #120                // Field Int:Lscala/reflect/ManifestFactory$IntManifest;
        50: new           #42                 // class scala/reflect/ManifestFactory$LongManifest
        53: dup
        54: invokespecial #121                // Method scala/reflect/ManifestFactory$LongManifest."<init>":()V
        57: putstatic     #123                // Field Long:Lscala/reflect/ManifestFactory$LongManifest;
        60: new           #33                 // class scala/reflect/ManifestFactory$FloatManifest
        63: dup
        64: invokespecial #124                // Method scala/reflect/ManifestFactory$FloatManifest."<init>":()V
        67: putstatic     #126                // Field Float:Lscala/reflect/ManifestFactory$FloatManifest;
        70: new           #30                 // class scala/reflect/ManifestFactory$DoubleManifest
        73: dup
        74: invokespecial #127                // Method scala/reflect/ManifestFactory$DoubleManifest."<init>":()V
        77: putstatic     #129                // Field Double:Lscala/reflect/ManifestFactory$DoubleManifest;
        80: new           #18                 // class scala/reflect/ManifestFactory$BooleanManifest
        83: dup
        84: invokespecial #130                // Method scala/reflect/ManifestFactory$BooleanManifest."<init>":()V
        87: putstatic     #132                // Field Boolean:Lscala/reflect/ManifestFactory$BooleanManifest;
        90: new           #60                 // class scala/reflect/ManifestFactory$UnitManifest
        93: dup
        94: invokespecial #133                // Method scala/reflect/ManifestFactory$UnitManifest."<init>":()V
        97: putstatic     #135                // Field Unit:Lscala/reflect/ManifestFactory$UnitManifest;
       100: ldc           #4                  // class java/lang/Object
       102: putstatic     #137                // Field scala$reflect$ManifestFactory$$ObjectTYPE:Ljava/lang/Class;
       105: ldc           #139                // class scala/runtime/Nothing$
       107: putstatic     #141                // Field scala$reflect$ManifestFactory$$NothingTYPE:Ljava/lang/Class;
       110: ldc           #143                // class scala/runtime/Null$
       112: putstatic     #145                // Field scala$reflect$ManifestFactory$$NullTYPE:Ljava/lang/Class;
       115: new           #12                 // class scala/reflect/ManifestFactory$AnyManifest
       118: dup
       119: invokespecial #146                // Method scala/reflect/ManifestFactory$AnyManifest."<init>":()V
       122: putstatic     #148                // Field Any:Lscala/reflect/Manifest;
       125: new           #51                 // class scala/reflect/ManifestFactory$ObjectManifest
       128: dup
       129: invokespecial #149                // Method scala/reflect/ManifestFactory$ObjectManifest."<init>":()V
       132: putstatic     #151                // Field Object:Lscala/reflect/Manifest;
       135: getstatic     #108                // Field MODULE$:Lscala/reflect/ManifestFactory$;
       138: invokevirtual #154                // Method Object:()Lscala/reflect/Manifest;
       141: putstatic     #156                // Field AnyRef:Lscala/reflect/Manifest;
       144: new           #15                 // class scala/reflect/ManifestFactory$AnyValPhantomManifest
       147: dup
       148: invokespecial #157                // Method scala/reflect/ManifestFactory$AnyValPhantomManifest."<init>":()V
       151: putstatic     #159                // Field AnyVal:Lscala/reflect/Manifest;
       154: new           #48                 // class scala/reflect/ManifestFactory$NullManifest
       157: dup
       158: invokespecial #160                // Method scala/reflect/ManifestFactory$NullManifest."<init>":()V
       161: putstatic     #162                // Field Null:Lscala/reflect/Manifest;
       164: new           #45                 // class scala/reflect/ManifestFactory$NothingManifest
       167: dup
       168: invokespecial #163                // Method scala/reflect/ManifestFactory$NothingManifest."<init>":()V
       171: putstatic     #165                // Field Nothing:Lscala/reflect/Manifest;
       174: return
      LineNumberTable:
        line 170: 0
        line 188: 10
        line 204: 20
        line 220: 30
        line 236: 40
        line 252: 50
        line 268: 60
        line 285: 70
        line 301: 80
        line 320: 90
        line 322: 100
        line 323: 105
        line 324: 110
        line 332: 115
        line 340: 125
        line 342: 135
        line 350: 144
        line 359: 154
        line 367: 164
        line 170: 174

  public scala.collection.immutable.List<scala.reflect.AnyValManifest<?>> valueManifests();
    descriptor: ()Lscala/collection/immutable/List;
    flags: (0x0001) ACC_PUBLIC
    Code:
      stack=6, locals=2, args_size=1
         0: getstatic     #173                // Field scala/package$.MODULE$:Lscala/package$;
         3: invokevirtual #177                // Method scala/package$.List:()Lscala/collection/immutable/List$;
         6: getstatic     #182                // Field scala/runtime/ScalaRunTime$.MODULE$:Lscala/runtime/ScalaRunTime$;
         9: bipush        9
        11: anewarray     #184                // class scala/reflect/AnyValManifest
        14: dup
        15: iconst_0
        16: aload_0
        17: invokevirtual #187                // Method Byte:()Lscala/reflect/ManifestFactory$ByteManifest;
        20: aastore
        21: dup
        22: iconst_1
        23: aload_0
        24: invokevirtual #190                // Method Short:()Lscala/reflect/ManifestFactory$ShortManifest;
        27: aastore
        28: dup
        29: iconst_2
        30: aload_0
        31: invokevirtual #193                // Method Char:()Lscala/reflect/ManifestFactory$CharManifest;
        34: aastore
        35: dup
        36: iconst_3
        37: aload_0
        38: invokevirtual #196                // Method Int:()Lscala/reflect/ManifestFactory$IntManifest;
        41: aastore
        42: dup
        43: iconst_4
        44: aload_0
        45: invokevirtual #199                // Method Long:()Lscala/reflect/ManifestFactory$LongManifest;
        48: aastore
        49: dup
        50: iconst_5
        51: aload_0
        52: invokevirtual #202                // Method Float:()Lscala/reflect/ManifestFactory$FloatManifest;
        55: aastore
        56: dup
        57: bipush        6
        59: aload_0
        60: invokevirtual #205                // Method Double:()Lscala/reflect/ManifestFactory$DoubleManifest;
        63: aastore
        64: dup
        65: bipush        7
        67: aload_0
        68: invokevirtual #208                // Method Boolean:()Lscala/reflect/ManifestFactory$BooleanManifest;
        71: aastore
        72: dup
        73: bipush        8
        75: aload_0
        76: invokevirtual #211                // Method Unit:()Lscala/reflect/ManifestFactory$UnitManifest;
        79: aastore
        80: invokevirtual #215                // Method scala/runtime/ScalaRunTime$.wrapRefArray:([Ljava/lang/Object;)Lscala/collection/immutable/ArraySeq;
        83: astore_1
        84: ifnonnull     89
        87: aconst_null
        88: athrow
        89: getstatic     #220                // Field scala/collection/immutable/Nil$.MODULE$:Lscala/collection/immutable/Nil$;
        92: aload_1
        93: invokevirtual #224                // Method scala/collection/immutable/Nil$.prependedAll:(Lscala/collection/IterableOnce;)Lscala/collection/immutable/List;
        96: areturn
      StackMapTable: number_of_entries = 1
        frame_type = 252 /* append */
          offset_delta = 89
          locals = [ class scala/collection/immutable/ArraySeq ]
      LineNumberTable:
        line 172: 0
      LocalVariableTable:
        Start  Length  Slot  Name   Signature
            0      97     0  this   Lscala/reflect/ManifestFactory$;
           89       7     1 apply_elems   Lscala/collection/immutable/Seq;
    Signature: #168                         // ()Lscala/collection/immutable/List<Lscala/reflect/AnyValManifest<*>;>;

  public scala.reflect.ManifestFactory$ByteManifest Byte();
    descriptor: ()Lscala/reflect/ManifestFactory$ByteManifest;
    flags: (0x0001) ACC_PUBLIC
    Code:
      stack=1, locals=1, args_size=1
         0: getstatic     #111                // Field Byte:Lscala/reflect/ManifestFactory$ByteManifest;
         3: areturn
      LineNumberTable:
        line 188: 0
      LocalVariableTable:
        Start  Length  Slot  Name   Signature
            0       4     0  this   Lscala/reflect/ManifestFactory$;

  public scala.reflect.ManifestFactory$ShortManifest Short();
    descriptor: ()Lscala/reflect/ManifestFactory$ShortManifest;
    flags: (0x0001) ACC_PUBLIC
    Code:
      stack=1, locals=1, args_size=1
         0: getstatic     #114                // Field Short:Lscala/reflect/ManifestFactory$ShortManifest;
         3: areturn
      LineNumberTable:
        line 204: 0
      LocalVariableTable:
        Start  Length  Slot  Name   Signature
            0       4     0  this   Lscala/reflect/ManifestFactory$;

  public scala.reflect.ManifestFactory$CharManifest Char();
    descriptor: ()Lscala/reflect/ManifestFactory$CharManifest;
    flags: (0x0001) ACC_PUBLIC
    Code:
      stack=1, locals=1, args_size=1
         0: getstatic     #117                // Field Char:Lscala/reflect/ManifestFactory$CharManifest;
         3: areturn
      LineNumberTable:
        line 220: 0
      LocalVariableTable:
        Start  Length  Slot  Name   Signature
            0       4     0  this   Lscala/reflect/ManifestFactory$;

  public scala.reflect.ManifestFactory$IntManifest Int();
    descriptor: ()Lscala/reflect/ManifestFactory$IntManifest;
    flags: (0x0001) ACC_PUBLIC
    Code:
      stack=1, locals=1, args_size=1
         0: getstatic     #120                // Field Int:Lscala/reflect/ManifestFactory$IntManifest;
         3: areturn
      LineNumberTable:
        line 236: 0
      LocalVariableTable:
        Start  Length  Slot  Name   Signature
            0       4     0  this   Lscala/reflect/ManifestFactory$;

  public scala.reflect.ManifestFactory$LongManifest Long();
    descriptor: ()Lscala/reflect/ManifestFactory$LongManifest;
    flags: (0x0001) ACC_PUBLIC
    Code:
      stack=1, locals=1, args_size=1
         0: getstatic     #123                // Field Long:Lscala/reflect/ManifestFactory$LongManifest;
         3: areturn
      LineNumberTable:
        line 252: 0
      LocalVariableTable:
        Start  Length  Slot  Name   Signature
            0       4     0  this   Lscala/reflect/ManifestFactory$;

  public scala.reflect.ManifestFactory$FloatManifest Float();
    descriptor: ()Lscala/reflect/ManifestFactory$FloatManifest;
    flags: (0x0001) ACC_PUBLIC
    Code:
      stack=1, locals=1, args_size=1
         0: getstatic     #126                // Field Float:Lscala/reflect/ManifestFactory$FloatManifest;
         3: areturn
      LineNumberTable:
        line 268: 0
      LocalVariableTable:
        Start  Length  Slot  Name   Signature
            0       4     0  this   Lscala/reflect/ManifestFactory$;

  public scala.reflect.ManifestFactory$DoubleManifest Double();
    descriptor: ()Lscala/reflect/ManifestFactory$DoubleManifest;
    flags: (0x0001) ACC_PUBLIC
    Code:
      stack=1, locals=1, args_size=1
         0: getstatic     #129                // Field Double:Lscala/reflect/ManifestFactory$DoubleManifest;
         3: areturn
      LineNumberTable:
        line 285: 0
      LocalVariableTable:
        Start  Length  Slot  Name   Signature
            0       4     0  this   Lscala/reflect/ManifestFactory$;

  public scala.reflect.ManifestFactory$BooleanManifest Boolean();
    descriptor: ()Lscala/reflect/ManifestFactory$BooleanManifest;
    flags: (0x0001) ACC_PUBLIC
    Code:
      stack=1, locals=1, args_size=1
         0: getstatic     #132                // Field Boolean:Lscala/reflect/ManifestFactory$BooleanManifest;
         3: areturn
      LineNumberTable:
        line 301: 0
      LocalVariableTable:
        Start  Length  Slot  Name   Signature
            0       4     0  this   Lscala/reflect/ManifestFactory$;

  public scala.reflect.ManifestFactory$UnitManifest Unit();
    descriptor: ()Lscala/reflect/ManifestFactory$UnitManifest;
    flags: (0x0001) ACC_PUBLIC
    Code:
      stack=1, locals=1, args_size=1
         0: getstatic     #135                // Field Unit:Lscala/reflect/ManifestFactory$UnitManifest;
         3: areturn
      LineNumberTable:
        line 320: 0
      LocalVariableTable:
        Start  Length  Slot  Name   Signature
            0       4     0  this   Lscala/reflect/ManifestFactory$;

  public scala.reflect.Manifest<java.lang.Object> Any();
    descriptor: ()Lscala/reflect/Manifest;
    flags: (0x0001) ACC_PUBLIC
    Code:
      stack=1, locals=1, args_size=1
         0: getstatic     #148                // Field Any:Lscala/reflect/Manifest;
         3: areturn
      LineNumberTable:
        line 332: 0
      LocalVariableTable:
        Start  Length  Slot  Name   Signature
            0       4     0  this   Lscala/reflect/ManifestFactory$;
    Signature: #230                         // ()Lscala/reflect/Manifest<Ljava/lang/Object;>;

  public scala.reflect.Manifest<java.lang.Object> Object();
    descriptor: ()Lscala/reflect/Manifest;
    flags: (0x0001) ACC_PUBLIC
    Code:
      stack=1, locals=1, args_size=1
         0: getstatic     #151                // Field Object:Lscala/reflect/Manifest;
         3: areturn
      LineNumberTable:
        line 340: 0
      LocalVariableTable:
        Start  Length  Slot  Name   Signature
            0       4     0  this   Lscala/reflect/ManifestFactory$;
    Signature: #230                         // ()Lscala/reflect/Manifest<Ljava/lang/Object;>;

  public scala.reflect.Manifest<java.lang.Object> AnyRef();
    descriptor: ()Lscala/reflect/Manifest;
    flags: (0x0001) ACC_PUBLIC
    Code:
      stack=1, locals=1, args_size=1
         0: getstatic     #156                // Field AnyRef:Lscala/reflect/Manifest;
         3: areturn
      LineNumberTable:
        line 342: 0
      LocalVariableTable:
        Start  Length  Slot  Name   Signature
            0       4     0  this   Lscala/reflect/ManifestFactory$;
    Signature: #230                         // ()Lscala/reflect/Manifest<Ljava/lang/Object;>;

  public scala.reflect.Manifest<java.lang.Object> AnyVal();
    descriptor: ()Lscala/reflect/Manifest;
    flags: (0x0001) ACC_PUBLIC
    Code:
      stack=1, locals=1, args_size=1
         0: getstatic     #159                // Field AnyVal:Lscala/reflect/Manifest;
         3: areturn
      LineNumberTable:
        line 350: 0
      LocalVariableTable:
        Start  Length  Slot  Name   Signature
            0       4     0  this   Lscala/reflect/ManifestFactory$;
    Signature: #230                         // ()Lscala/reflect/Manifest<Ljava/lang/Object;>;

  public scala.reflect.Manifest<scala.runtime.Null$> Null();
    descriptor: ()Lscala/reflect/Manifest;
    flags: (0x0001) ACC_PUBLIC
    Code:
      stack=1, locals=1, args_size=1
         0: getstatic     #162                // Field Null:Lscala/reflect/Manifest;
         3: areturn
      LineNumberTable:
        line 359: 0
      LocalVariableTable:
        Start  Length  Slot  Name   Signature
            0       4     0  this   Lscala/reflect/ManifestFactory$;
    Signature: #231                         // ()Lscala/reflect/Manifest<Lscala/runtime/Null$;>;

  public scala.reflect.Manifest<scala.runtime.Nothing$> Nothing();
    descriptor: ()Lscala/reflect/Manifest;
    flags: (0x0001) ACC_PUBLIC
    Code:
      stack=1, locals=1, args_size=1
         0: getstatic     #165                // Field Nothing:Lscala/reflect/Manifest;
         3: areturn
      LineNumberTable:
        line 367: 0
      LocalVariableTable:
        Start  Length  Slot  Name   Signature
            0       4     0  this   Lscala/reflect/ManifestFactory$;
    Signature: #232                         // ()Lscala/reflect/Manifest<Lscala/runtime/Nothing$;>;

  public <T extends java.lang.Object> scala.reflect.Manifest<T> singleType(java.lang.Object);
    descriptor: (Ljava/lang/Object;)Lscala/reflect/Manifest;
    flags: (0x0001) ACC_PUBLIC
    Code:
      stack=3, locals=2, args_size=2
         0: new           #57                 // class scala/reflect/ManifestFactory$SingletonTypeManifest
         3: dup
         4: aload_1
         5: invokespecial #239                // Method scala/reflect/ManifestFactory$SingletonTypeManifest."<init>":(Ljava/lang/Object;)V
         8: areturn
      LineNumberTable:
        line 377: 0
      LocalVariableTable:
        Start  Length  Slot  Name   Signature
            0       9     0  this   Lscala/reflect/ManifestFactory$;
            0       9     1 value   Ljava/lang/Object;
    Signature: #235                         // <T:Ljava/lang/Object;>(Ljava/lang/Object;)Lscala/reflect/Manifest<TT;>;
    MethodParameters:
      Name                           Flags
      value                          final

  public <T extends java.lang.Object> scala.reflect.Manifest<T> classType(java.lang.Class<?>);
    descriptor: (Ljava/lang/Class;)Lscala/reflect/Manifest;
    flags: (0x0001) ACC_PUBLIC
    Code:
      stack=5, locals=2, args_size=2
         0: new           #27                 // class scala/reflect/ManifestFactory$ClassTypeManifest
         3: dup
         4: getstatic     #249                // Field scala/None$.MODULE$:Lscala/None$;
         7: aload_1
         8: getstatic     #173                // Field scala/package$.MODULE$:Lscala/package$;
        11: invokevirtual #253                // Method scala/package$.Nil:()Lscala/collection/immutable/Nil$;
        14: invokespecial #256                // Method scala/reflect/ManifestFactory$ClassTypeManifest."<init>":(Lscala/Option;Ljava/lang/Class;Lscala/collection/immutable/List;)V
        17: areturn
      LineNumberTable:
        line 387: 0
      LocalVariableTable:
        Start  Length  Slot  Name   Signature
            0      18     0  this   Lscala/reflect/ManifestFactory$;
            0      18     1 clazz   Ljava/lang/Class;
    Signature: #243                         // <T:Ljava/lang/Object;>(Ljava/lang/Class<*>;)Lscala/reflect/Manifest<TT;>;
    MethodParameters:
      Name                           Flags
      clazz                          final

  public <T extends java.lang.Object> scala.reflect.Manifest<T> classType(java.lang.Class<T>, scala.reflect.Manifest<?>, scala.collection.immutable.Seq<scala.reflect.Manifest<?>>);
    descriptor: (Ljava/lang/Class;Lscala/reflect/Manifest;Lscala/collection/immutable/Seq;)Lscala/reflect/Manifest;
    flags: (0x0001) ACC_PUBLIC
    Code:
      stack=8, locals=5, args_size=4
         0: new           #27                 // class scala/reflect/ManifestFactory$ClassTypeManifest
         3: dup
         4: getstatic     #249                // Field scala/None$.MODULE$:Lscala/None$;
         7: aload_1
         8: aload_3
         9: invokeinterface #265,  1          // InterfaceMethod scala/collection/immutable/Seq.toList:()Lscala/collection/immutable/List;
        14: dup
        15: ifnonnull     20
        18: aconst_null
        19: athrow
        20: astore        4
        22: new           #267                // class scala/collection/immutable/$colon$colon
        25: dup
        26: aload_2
        27: aload         4
        29: invokespecial #270                // Method scala/collection/immutable/$colon$colon."<init>":(Ljava/lang/Object;Lscala/collection/immutable/List;)V
        32: aconst_null
        33: astore        4
        35: invokespecial #256                // Method scala/reflect/ManifestFactory$ClassTypeManifest."<init>":(Lscala/Option;Ljava/lang/Class;Lscala/collection/immutable/List;)V
        38: areturn
      StackMapTable: number_of_entries = 1
        frame_type = 255 /* full_frame */
          offset_delta = 20
          locals = [ class scala/reflect/ManifestFactory$, class java/lang/Class, class scala/reflect/Manifest, class scala/collection/immutable/Seq ]
          stack = [ uninitialized 0, uninitialized 0, class scala/None$, class java/lang/Class, class scala/collection/immutable/List ]
      LineNumberTable:
        line 392: 0
      LocalVariableTable:
        Start  Length  Slot  Name   Signature
            0      39     0  this   Lscala/reflect/ManifestFactory$;
            0      39     1 clazz   Ljava/lang/Class;
            0      39     2  arg1   Lscala/reflect/Manifest;
            0      39     3  args   Lscala/collection/immutable/Seq;
           22      10     4 $colon$colon_this   Lscala/collection/immutable/List;
    Signature: #258                         // <T:Ljava/lang/Object;>(Ljava/lang/Class<TT;>;Lscala/reflect/Manifest<*>;Lscala/collection/immutable/Seq<Lscala/reflect/Manifest<*>;>;)Lscala/reflect/Manifest<TT;>;
    MethodParameters:
      Name                           Flags
      clazz                          final
      arg1                           final
      args                           final

  public <T extends java.lang.Object> scala.reflect.Manifest<T> classType(scala.reflect.Manifest<?>, java.lang.Class<?>, scala.collection.immutable.Seq<scala.reflect.Manifest<?>>);
    descriptor: (Lscala/reflect/Manifest;Ljava/lang/Class;Lscala/collection/immutable/Seq;)Lscala/reflect/Manifest;
    flags: (0x0001) ACC_PUBLIC
    Code:
      stack=5, locals=4, args_size=4
         0: new           #27                 // class scala/reflect/ManifestFactory$ClassTypeManifest
         3: dup
         4: new           #283                // class scala/Some
         7: dup
         8: aload_1
         9: invokespecial #284                // Method scala/Some."<init>":(Ljava/lang/Object;)V
        12: aload_2
        13: aload_3
        14: invokeinterface #265,  1          // InterfaceMethod scala/collection/immutable/Seq.toList:()Lscala/collection/immutable/List;
        19: invokespecial #256                // Method scala/reflect/ManifestFactory$ClassTypeManifest."<init>":(Lscala/Option;Ljava/lang/Class;Lscala/collection/immutable/List;)V
        22: areturn
      LineNumberTable:
        line 398: 0
      LocalVariableTable:
        Start  Length  Slot  Name   Signature
            0      23     0  this   Lscala/reflect/ManifestFactory$;
            0      23     1 prefix   Lscala/reflect/Manifest;
            0      23     2 clazz   Ljava/lang/Class;
            0      23     3  args   Lscala/collection/immutable/Seq;
    Signature: #280                         // <T:Ljava/lang/Object;>(Lscala/reflect/Manifest<*>;Ljava/lang/Class<*>;Lscala/collection/immutable/Seq<Lscala/reflect/Manifest<*>;>;)Lscala/reflect/Manifest<TT;>;
    MethodParameters:
      Name                           Flags
      prefix                         final
      clazz                          final
      args                           final

  public <T extends java.lang.Object> scala.reflect.Manifest<java.lang.Object> arrayType(scala.reflect.Manifest<?>);
    descriptor: (Lscala/reflect/Manifest;)Lscala/reflect/Manifest;
    flags: (0x0001) ACC_PUBLIC
    Code:
      stack=1, locals=2, args_size=2
         0: aload_1
         1: invokeinterface #291,  1          // InterfaceMethod scala/reflect/Manifest.arrayManifest:()Lscala/reflect/Manifest;
         6: areturn
      LineNumberTable:
        line 421: 0
      LocalVariableTable:
        Start  Length  Slot  Name   Signature
            0       7     0  this   Lscala/reflect/ManifestFactory$;
            0       7     1   arg   Lscala/reflect/Manifest;
    Signature: #287                         // <T:Ljava/lang/Object;>(Lscala/reflect/Manifest<*>;)Lscala/reflect/Manifest<Ljava/lang/Object;>;
    MethodParameters:
      Name                           Flags
      arg                            final

  public <T extends java.lang.Object> scala.reflect.Manifest<T> abstractType(scala.reflect.Manifest<?>, java.lang.String, java.lang.Class<?>, scala.collection.immutable.Seq<scala.reflect.Manifest<?>>);
    descriptor: (Lscala/reflect/Manifest;Ljava/lang/String;Ljava/lang/Class;Lscala/collection/immutable/Seq;)Lscala/reflect/Manifest;
    flags: (0x0001) ACC_PUBLIC
    Code:
      stack=6, locals=5, args_size=5
         0: new           #7                  // class scala/reflect/ManifestFactory$AbstractTypeManifest
         3: dup
         4: aload_1
         5: aload_2
         6: aload_3
         7: aload         4
         9: invokespecial #299                // Method scala/reflect/ManifestFactory$AbstractTypeManifest."<init>":(Lscala/reflect/Manifest;Ljava/lang/String;Ljava/lang/Class;Lscala/collection/Seq;)V
        12: areturn
      LineNumberTable:
        line 434: 0
      LocalVariableTable:
        Start  Length  Slot  Name   Signature
            0      13     0  this   Lscala/reflect/ManifestFactory$;
            0      13     1 prefix   Lscala/reflect/Manifest;
            0      13     2  name   Ljava/lang/String;
            0      13     3 upperBound   Ljava/lang/Class;
            0      13     4  args   Lscala/collection/immutable/Seq;
    Signature: #294                         // <T:Ljava/lang/Object;>(Lscala/reflect/Manifest<*>;Ljava/lang/String;Ljava/lang/Class<*>;Lscala/collection/immutable/Seq<Lscala/reflect/Manifest<*>;>;)Lscala/reflect/Manifest<TT;>;
    MethodParameters:
      Name                           Flags
      prefix                         final
      name                           final
      upperBound                     final
      args                           final

  public <T extends java.lang.Object> scala.reflect.Manifest<T> wildcardType(scala.reflect.Manifest<?>, scala.reflect.Manifest<?>);
    descriptor: (Lscala/reflect/Manifest;Lscala/reflect/Manifest;)Lscala/reflect/Manifest;
    flags: (0x0001) ACC_PUBLIC
    Code:
      stack=4, locals=3, args_size=3
         0: new           #63                 // class scala/reflect/ManifestFactory$WildcardManifest
         3: dup
         4: aload_1
         5: aload_2
         6: invokespecial #307                // Method scala/reflect/ManifestFactory$WildcardManifest."<init>":(Lscala/reflect/Manifest;Lscala/reflect/Manifest;)V
         9: areturn
      LineNumberTable:
        line 448: 0
      LocalVariableTable:
        Start  Length  Slot  Name   Signature
            0      10     0  this   Lscala/reflect/ManifestFactory$;
            0      10     1 lowerBound   Lscala/reflect/Manifest;
            0      10     2 upperBound   Lscala/reflect/Manifest;
    Signature: #303                         // <T:Ljava/lang/Object;>(Lscala/reflect/Manifest<*>;Lscala/reflect/Manifest<*>;)Lscala/reflect/Manifest<TT;>;
    MethodParameters:
      Name                           Flags
      lowerBound                     final
      upperBound                     final

  public <T extends java.lang.Object> scala.reflect.Manifest<T> intersectionType(scala.collection.immutable.Seq<scala.reflect.Manifest<?>>);
    descriptor: (Lscala/collection/immutable/Seq;)Lscala/reflect/Manifest;
    flags: (0x0001) ACC_PUBLIC
    Code:
      stack=5, locals=2, args_size=2
         0: new           #39                 // class scala/reflect/ManifestFactory$IntersectionTypeManifest
         3: dup
         4: aload_1
         5: getstatic     #316                // Field scala/reflect/ClassTag$.MODULE$:Lscala/reflect/ClassTag$;
         8: ldc_w         #276                // class scala/reflect/Manifest
        11: invokevirtual #320                // Method scala/reflect/ClassTag$.apply:(Ljava/lang/Class;)Lscala/reflect/ClassTag;
        14: invokeinterface #324,  2          // InterfaceMethod scala/collection/immutable/Seq.toArray:(Lscala/reflect/ClassTag;)Ljava/lang/Object;
        19: checkcast     #326                // class "[Lscala/reflect/Manifest;"
        22: invokespecial #329                // Method scala/reflect/ManifestFactory$IntersectionTypeManifest."<init>":([Lscala/reflect/Manifest;)V
        25: areturn
      LineNumberTable:
        line 460: 0
      LocalVariableTable:
        Start  Length  Slot  Name   Signature
            0      26     0  this   Lscala/reflect/ManifestFactory$;
            0      26     1 parents   Lscala/collection/immutable/Seq;
    Signature: #310                         // <T:Ljava/lang/Object;>(Lscala/collection/immutable/Seq<Lscala/reflect/Manifest<*>;>;)Lscala/reflect/Manifest<TT;>;
    MethodParameters:
      Name                           Flags
      parents                        final

  private scala.reflect.ManifestFactory$();
    descriptor: ()V
    flags: (0x0002) ACC_PRIVATE
    Code:
      stack=1, locals=1, args_size=1
         0: aload_0
         1: invokespecial #330                // Method java/lang/Object."<init>":()V
         4: return
      LineNumberTable:
        line 170: 0
      LocalVariableTable:
        Start  Length  Slot  Name   Signature
            0       5     0  this   Lscala/reflect/ManifestFactory$;
}
InnerClasses:
  private static #10= #7 of #9;           // AbstractTypeManifest=class scala/reflect/ManifestFactory$AbstractTypeManifest of class scala/reflect/ManifestFactory
  private static final #13= #12 of #9;    // AnyManifest=class scala/reflect/ManifestFactory$AnyManifest of class scala/reflect/ManifestFactory
  private static final #16= #15 of #9;    // AnyValPhantomManifest=class scala/reflect/ManifestFactory$AnyValPhantomManifest of class scala/reflect/ManifestFactory
  public static final #19= #18 of #9;     // BooleanManifest=class scala/reflect/ManifestFactory$BooleanManifest of class scala/reflect/ManifestFactory
  public static final #22= #21 of #9;     // ByteManifest=class scala/reflect/ManifestFactory$ByteManifest of class scala/reflect/ManifestFactory
  public static final #25= #24 of #9;     // CharManifest=class scala/reflect/ManifestFactory$CharManifest of class scala/reflect/ManifestFactory
  private static #28= #27 of #9;          // ClassTypeManifest=class scala/reflect/ManifestFactory$ClassTypeManifest of class scala/reflect/ManifestFactory
  public static final #31= #30 of #9;     // DoubleManifest=class scala/reflect/ManifestFactory$DoubleManifest of class scala/reflect/ManifestFactory
  public static final #34= #33 of #9;     // FloatManifest=class scala/reflect/ManifestFactory$FloatManifest of class scala/reflect/ManifestFactory
  public static final #37= #36 of #9;     // IntManifest=class scala/reflect/ManifestFactory$IntManifest of class scala/reflect/ManifestFactory
  private static #40= #39 of #9;          // IntersectionTypeManifest=class scala/reflect/ManifestFactory$IntersectionTypeManifest of class scala/reflect/ManifestFactory
  public static final #43= #42 of #9;     // LongManifest=class scala/reflect/ManifestFactory$LongManifest of class scala/reflect/ManifestFactory
  private static final #46= #45 of #9;    // NothingManifest=class scala/reflect/ManifestFactory$NothingManifest of class scala/reflect/ManifestFactory
  private static final #49= #48 of #9;    // NullManifest=class scala/reflect/ManifestFactory$NullManifest of class scala/reflect/ManifestFactory
  private static final #52= #51 of #9;    // ObjectManifest=class scala/reflect/ManifestFactory$ObjectManifest of class scala/reflect/ManifestFactory
  public static final #55= #54 of #9;     // ShortManifest=class scala/reflect/ManifestFactory$ShortManifest of class scala/reflect/ManifestFactory
  private static final #58= #57 of #9;    // SingletonTypeManifest=class scala/reflect/ManifestFactory$SingletonTypeManifest of class scala/reflect/ManifestFactory
  public static final #61= #60 of #9;     // UnitManifest=class scala/reflect/ManifestFactory$UnitManifest of class scala/reflect/ManifestFactory
  private static #64= #63 of #9;          // WildcardManifest=class scala/reflect/ManifestFactory$WildcardManifest of class scala/reflect/ManifestFactory
SourceFile: "Manifest.scala"
  ScalaInlineInfo: length = 0x81 (unknown attribute)
   01 01 00 19 00 68 00 67 01 00 5C 00 98 01 00 60
   00 98 01 00 61 00 98 01 00 51 00 CE 01 00 43 00
   B9 01 00 47 00 BF 01 00 4F 00 CB 01 00 4D 00 C8
   01 00 49 00 C2 01 00 4B 00 C5 01 00 64 00 98 01
   00 62 00 98 01 00 5F 00 98 01 00 45 00 BC 01 00
   53 00 D1 01 01 24 01 25 01 01 1D 01 1E 01 00 F1
   00 F2 01 00 F1 01 01 01 00 F1 01 17 01 01 34 01
   35 01 00 E9 00 EA 01 00 A6 00 A7 01 01 2D 01 2E
   01
  Scala: length = 0x0 (unknown attribute)

