Classfile /Users/mw/Projects/slang-braindump/.jar/jar8/assemble/slang-braindump/assemble/content/org/apache/commons/io/serialization/FullClassNameMatcher.class
  Last modified May 29, 2022; size 1057 bytes
  SHA-256 checksum d0d6847fd2f672f8a2171f17fbcc238d87fe94f3e5a0ec6353b2b431ef964691
  Compiled from "FullClassNameMatcher.java"
final class org.apache.commons.io.serialization.FullClassNameMatcher implements org.apache.commons.io.serialization.ClassNameMatcher
  minor version: 0
  major version: 52
  flags: (0x0030) ACC_FINAL, ACC_SUPER
  this_class: #8                          // org/apache/commons/io/serialization/FullClassNameMatcher
  super_class: #9                         // java/lang/Object
  interfaces: 1, fields: 1, methods: 2, attributes: 1
Constant pool:
   #1 = Methodref          #9.#30         // java/lang/Object."<init>":()V
   #2 = Class              #31            // java/util/HashSet
   #3 = Methodref          #32.#33        // java/util/Arrays.asList:([Ljava/lang/Object;)Ljava/util/List;
   #4 = Methodref          #2.#34         // java/util/HashSet."<init>":(Ljava/util/Collection;)V
   #5 = Methodref          #35.#36        // java/util/Collections.unmodifiableSet:(Ljava/util/Set;)Ljava/util/Set;
   #6 = Fieldref           #8.#37         // org/apache/commons/io/serialization/FullClassNameMatcher.classesSet:Ljava/util/Set;
   #7 = InterfaceMethodref #38.#39        // java/util/Set.contains:(Ljava/lang/Object;)Z
   #8 = Class              #40            // org/apache/commons/io/serialization/FullClassNameMatcher
   #9 = Class              #41            // java/lang/Object
  #10 = Class              #42            // org/apache/commons/io/serialization/ClassNameMatcher
  #11 = Utf8               classesSet
  #12 = Utf8               Ljava/util/Set;
  #13 = Utf8               Signature
  #14 = Utf8               Ljava/util/Set<Ljava/lang/String;>;
  #15 = Utf8               <init>
  #16 = Utf8               ([Ljava/lang/String;)V
  #17 = Utf8               Code
  #18 = Utf8               LineNumberTable
  #19 = Utf8               LocalVariableTable
  #20 = Utf8               this
  #21 = Utf8               Lorg/apache/commons/io/serialization/FullClassNameMatcher;
  #22 = Utf8               classes
  #23 = Utf8               [Ljava/lang/String;
  #24 = Utf8               matches
  #25 = Utf8               (Ljava/lang/String;)Z
  #26 = Utf8               className
  #27 = Utf8               Ljava/lang/String;
  #28 = Utf8               SourceFile
  #29 = Utf8               FullClassNameMatcher.java
  #30 = NameAndType        #15:#43        // "<init>":()V
  #31 = Utf8               java/util/HashSet
  #32 = Class              #44            // java/util/Arrays
  #33 = NameAndType        #45:#46        // asList:([Ljava/lang/Object;)Ljava/util/List;
  #34 = NameAndType        #15:#47        // "<init>":(Ljava/util/Collection;)V
  #35 = Class              #48            // java/util/Collections
  #36 = NameAndType        #49:#50        // unmodifiableSet:(Ljava/util/Set;)Ljava/util/Set;
  #37 = NameAndType        #11:#12        // classesSet:Ljava/util/Set;
  #38 = Class              #51            // java/util/Set
  #39 = NameAndType        #52:#53        // contains:(Ljava/lang/Object;)Z
  #40 = Utf8               org/apache/commons/io/serialization/FullClassNameMatcher
  #41 = Utf8               java/lang/Object
  #42 = Utf8               org/apache/commons/io/serialization/ClassNameMatcher
  #43 = Utf8               ()V
  #44 = Utf8               java/util/Arrays
  #45 = Utf8               asList
  #46 = Utf8               ([Ljava/lang/Object;)Ljava/util/List;
  #47 = Utf8               (Ljava/util/Collection;)V
  #48 = Utf8               java/util/Collections
  #49 = Utf8               unmodifiableSet
  #50 = Utf8               (Ljava/util/Set;)Ljava/util/Set;
  #51 = Utf8               java/util/Set
  #52 = Utf8               contains
  #53 = Utf8               (Ljava/lang/Object;)Z
{
  private final java.util.Set<java.lang.String> classesSet;
    descriptor: Ljava/util/Set;
    flags: (0x0012) ACC_PRIVATE, ACC_FINAL
    Signature: #14                          // Ljava/util/Set<Ljava/lang/String;>;

  public org.apache.commons.io.serialization.FullClassNameMatcher(java.lang.String...);
    descriptor: ([Ljava/lang/String;)V
    flags: (0x0081) ACC_PUBLIC, ACC_VARARGS
    Code:
      stack=4, locals=2, args_size=2
         0: aload_0
         1: invokespecial #1                  // Method java/lang/Object."<init>":()V
         4: aload_0
         5: new           #2                  // class java/util/HashSet
         8: dup
         9: aload_1
        10: invokestatic  #3                  // Method java/util/Arrays.asList:([Ljava/lang/Object;)Ljava/util/List;
        13: invokespecial #4                  // Method java/util/HashSet."<init>":(Ljava/util/Collection;)V
        16: invokestatic  #5                  // Method java/util/Collections.unmodifiableSet:(Ljava/util/Set;)Ljava/util/Set;
        19: putfield      #6                  // Field classesSet:Ljava/util/Set;
        22: return
      LineNumberTable:
        line 41: 0
        line 42: 4
        line 43: 22
      LocalVariableTable:
        Start  Length  Slot  Name   Signature
            0      23     0  this   Lorg/apache/commons/io/serialization/FullClassNameMatcher;
            0      23     1 classes   [Ljava/lang/String;

  public boolean matches(java.lang.String);
    descriptor: (Ljava/lang/String;)Z
    flags: (0x0001) ACC_PUBLIC
    Code:
      stack=2, locals=2, args_size=2
         0: aload_0
         1: getfield      #6                  // Field classesSet:Ljava/util/Set;
         4: aload_1
         5: invokeinterface #7,  2            // InterfaceMethod java/util/Set.contains:(Ljava/lang/Object;)Z
        10: ireturn
      LineNumberTable:
        line 47: 0
      LocalVariableTable:
        Start  Length  Slot  Name   Signature
            0      11     0  this   Lorg/apache/commons/io/serialization/FullClassNameMatcher;
            0      11     1 className   Ljava/lang/String;
}
SourceFile: "FullClassNameMatcher.java"
