Classfile /Users/mw/Projects/slang-braindump/.jar/jar8/assemble/slang-braindump/assemble/content/shapeless/$colon$colon$.class
  Last modified May 29, 2022; size 1752 bytes
  SHA-256 checksum 02d6301528cde9d03dd5c1d6b92f4405cb2e4ea21e93faee9e97418a4e2c28da
  Compiled from "hlists.scala"
public final class shapeless.$colon$colon$ implements java.io.Serializable
  minor version: 0
  major version: 52
  flags: (0x0031) ACC_PUBLIC, ACC_FINAL, ACC_SUPER
  this_class: #2                          // shapeless/$colon$colon$
  super_class: #4                         // java/lang/Object
  interfaces: 1, fields: 1, methods: 6, attributes: 3
Constant pool:
   #1 = Utf8               shapeless/$colon$colon$
   #2 = Class              #1             // shapeless/$colon$colon$
   #3 = Utf8               java/lang/Object
   #4 = Class              #3             // java/lang/Object
   #5 = Utf8               java/io/Serializable
   #6 = Class              #5             // java/io/Serializable
   #7 = Utf8               hlists.scala
   #8 = Utf8               MODULE$
   #9 = Utf8               Lshapeless/$colon$colon$;
  #10 = Utf8               <clinit>
  #11 = Utf8               ()V
  #12 = Utf8               <init>
  #13 = NameAndType        #12:#11        // "<init>":()V
  #14 = Methodref          #2.#13         // shapeless/$colon$colon$."<init>":()V
  #15 = NameAndType        #8:#9          // MODULE$:Lshapeless/$colon$colon$;
  #16 = Fieldref           #2.#15         // shapeless/$colon$colon$.MODULE$:Lshapeless/$colon$colon$;
  #17 = Utf8               toString
  #18 = Utf8               ()Ljava/lang/String;
  #19 = Utf8               ::
  #20 = String             #19            // ::
  #21 = Utf8               this
  #22 = Utf8               apply
  #23 = Utf8               (Ljava/lang/Object;Lshapeless/HList;)Lshapeless/$colon$colon;
  #24 = Utf8               <H:Ljava/lang/Object;T::Lshapeless/HList;>(TH;TT;)Lshapeless/$colon$colon<TH;TT;>;
  #25 = Utf8               head
  #26 = Utf8               tail
  #27 = Utf8               shapeless/$colon$colon
  #28 = Class              #27            // shapeless/$colon$colon
  #29 = Utf8               (Ljava/lang/Object;Lshapeless/HList;)V
  #30 = NameAndType        #12:#29        // "<init>":(Ljava/lang/Object;Lshapeless/HList;)V
  #31 = Methodref          #28.#30        // shapeless/$colon$colon."<init>":(Ljava/lang/Object;Lshapeless/HList;)V
  #32 = Utf8               Ljava/lang/Object;
  #33 = Utf8               Lshapeless/HList;
  #34 = Utf8               unapply
  #35 = Utf8               (Lshapeless/$colon$colon;)Lscala/Option;
  #36 = Utf8               <H:Ljava/lang/Object;T::Lshapeless/HList;>(Lshapeless/$colon$colon<TH;TT;>;)Lscala/Option<Lscala/Tuple2<TH;TT;>;>;
  #37 = Utf8               x$0
  #38 = Utf8               scala/None$
  #39 = Class              #38            // scala/None$
  #40 = Utf8               Lscala/None$;
  #41 = NameAndType        #8:#40         // MODULE$:Lscala/None$;
  #42 = Fieldref           #39.#41        // scala/None$.MODULE$:Lscala/None$;
  #43 = Utf8               scala/Some
  #44 = Class              #43            // scala/Some
  #45 = Utf8               scala/Tuple2
  #46 = Class              #45            // scala/Tuple2
  #47 = Utf8               ()Ljava/lang/Object;
  #48 = NameAndType        #25:#47        // head:()Ljava/lang/Object;
  #49 = Methodref          #28.#48        // shapeless/$colon$colon.head:()Ljava/lang/Object;
  #50 = Utf8               ()Lshapeless/HList;
  #51 = NameAndType        #26:#50        // tail:()Lshapeless/HList;
  #52 = Methodref          #28.#51        // shapeless/$colon$colon.tail:()Lshapeless/HList;
  #53 = Utf8               (Ljava/lang/Object;Ljava/lang/Object;)V
  #54 = NameAndType        #12:#53        // "<init>":(Ljava/lang/Object;Ljava/lang/Object;)V
  #55 = Methodref          #46.#54        // scala/Tuple2."<init>":(Ljava/lang/Object;Ljava/lang/Object;)V
  #56 = Utf8               (Ljava/lang/Object;)V
  #57 = NameAndType        #12:#56        // "<init>":(Ljava/lang/Object;)V
  #58 = Methodref          #44.#57        // scala/Some."<init>":(Ljava/lang/Object;)V
  #59 = Utf8               Lshapeless/$colon$colon;
  #60 = Utf8               scala/Option
  #61 = Class              #60            // scala/Option
  #62 = Utf8               writeReplace
  #63 = Utf8               scala/runtime/ModuleSerializationProxy
  #64 = Class              #63            // scala/runtime/ModuleSerializationProxy
  #65 = Utf8               (Ljava/lang/Class;)V
  #66 = NameAndType        #12:#65        // "<init>":(Ljava/lang/Class;)V
  #67 = Methodref          #64.#66        // scala/runtime/ModuleSerializationProxy."<init>":(Ljava/lang/Class;)V
  #68 = Methodref          #4.#13         // java/lang/Object."<init>":()V
  #69 = Utf8               Code
  #70 = Utf8               LineNumberTable
  #71 = Utf8               LocalVariableTable
  #72 = Utf8               Signature
  #73 = Utf8               MethodParameters
  #74 = Utf8               StackMapTable
  #75 = Utf8               SourceFile
  #76 = Utf8               ScalaInlineInfo
  #77 = Utf8               Scala
{
  public static final shapeless.$colon$colon$ MODULE$;
    descriptor: Lshapeless/$colon$colon$;
    flags: (0x0019) ACC_PUBLIC, ACC_STATIC, ACC_FINAL

  public static {};
    descriptor: ()V
    flags: (0x0009) ACC_PUBLIC, ACC_STATIC
    Code:
      stack=2, locals=0, args_size=0
         0: new           #2                  // class shapeless/$colon$colon$
         3: dup
         4: invokespecial #14                 // Method "<init>":()V
         7: putstatic     #16                 // Field MODULE$:Lshapeless/$colon$colon$;
        10: return
      LineNumberTable:
        line 37: 0

  public final java.lang.String toString();
    descriptor: ()Ljava/lang/String;
    flags: (0x0011) ACC_PUBLIC, ACC_FINAL
    Code:
      stack=1, locals=1, args_size=1
         0: ldc           #20                 // String ::
         2: areturn
      LineNumberTable:
        line 37: 0
      LocalVariableTable:
        Start  Length  Slot  Name   Signature
            0       3     0  this   Lshapeless/$colon$colon$;

  public <H extends java.lang.Object, T extends shapeless.HList> shapeless.$colon$colon<H, T> apply(H, T);
    descriptor: (Ljava/lang/Object;Lshapeless/HList;)Lshapeless/$colon$colon;
    flags: (0x0001) ACC_PUBLIC
    Code:
      stack=4, locals=3, args_size=3
         0: new           #28                 // class shapeless/$colon$colon
         3: dup
         4: aload_1
         5: aload_2
         6: invokespecial #31                 // Method shapeless/$colon$colon."<init>":(Ljava/lang/Object;Lshapeless/HList;)V
         9: areturn
      LineNumberTable:
        line 37: 0
      LocalVariableTable:
        Start  Length  Slot  Name   Signature
            0      10     0  this   Lshapeless/$colon$colon$;
            0      10     1  head   Ljava/lang/Object;
            0      10     2  tail   Lshapeless/HList;
    Signature: #24                          // <H:Ljava/lang/Object;T::Lshapeless/HList;>(TH;TT;)Lshapeless/$colon$colon<TH;TT;>;
    MethodParameters:
      Name                           Flags
      head                           final
      tail                           final

  public <H extends java.lang.Object, T extends shapeless.HList> scala.Option<scala.Tuple2<H, T>> unapply(shapeless.$colon$colon<H, T>);
    descriptor: (Lshapeless/$colon$colon;)Lscala/Option;
    flags: (0x0001) ACC_PUBLIC
    Code:
      stack=6, locals=2, args_size=2
         0: aload_1
         1: ifnonnull     10
         4: getstatic     #42                 // Field scala/None$.MODULE$:Lscala/None$;
         7: goto          32
        10: new           #44                 // class scala/Some
        13: dup
        14: new           #46                 // class scala/Tuple2
        17: dup
        18: aload_1
        19: invokevirtual #49                 // Method shapeless/$colon$colon.head:()Ljava/lang/Object;
        22: aload_1
        23: invokevirtual #52                 // Method shapeless/$colon$colon.tail:()Lshapeless/HList;
        26: invokespecial #55                 // Method scala/Tuple2."<init>":(Ljava/lang/Object;Ljava/lang/Object;)V
        29: invokespecial #58                 // Method scala/Some."<init>":(Ljava/lang/Object;)V
        32: areturn
      StackMapTable: number_of_entries = 2
        frame_type = 10 /* same */
        frame_type = 85 /* same_locals_1_stack_item */
          stack = [ class scala/Option ]
      LineNumberTable:
        line 37: 0
      LocalVariableTable:
        Start  Length  Slot  Name   Signature
            0      33     0  this   Lshapeless/$colon$colon$;
            0      33     1   x$0   Lshapeless/$colon$colon;
    Signature: #36                          // <H:Ljava/lang/Object;T::Lshapeless/HList;>(Lshapeless/$colon$colon<TH;TT;>;)Lscala/Option<Lscala/Tuple2<TH;TT;>;>;
    MethodParameters:
      Name                           Flags
      x$0                            final

  private java.lang.Object writeReplace();
    descriptor: ()Ljava/lang/Object;
    flags: (0x0002) ACC_PRIVATE
    Code:
      stack=3, locals=1, args_size=1
         0: new           #64                 // class scala/runtime/ModuleSerializationProxy
         3: dup
         4: ldc           #2                  // class shapeless/$colon$colon$
         6: invokespecial #67                 // Method scala/runtime/ModuleSerializationProxy."<init>":(Ljava/lang/Class;)V
         9: areturn
      LineNumberTable:
        line 37: 0
      LocalVariableTable:
        Start  Length  Slot  Name   Signature
            0      10     0  this   Lshapeless/$colon$colon$;

  private shapeless.$colon$colon$();
    descriptor: ()V
    flags: (0x0002) ACC_PRIVATE
    Code:
      stack=1, locals=1, args_size=1
         0: aload_0
         1: invokespecial #68                 // Method java/lang/Object."<init>":()V
         4: return
      LineNumberTable:
        line 37: 0
      LocalVariableTable:
        Start  Length  Slot  Name   Signature
            0       5     0  this   Lshapeless/$colon$colon$;
}
SourceFile: "hlists.scala"
  ScalaInlineInfo: length = 0x1D (unknown attribute)
   01 01 00 05 00 0C 00 0B 01 00 16 00 17 01 00 11
   00 12 01 00 22 00 23 01 00 3E 00 2F 01
  Scala: length = 0x0 (unknown attribute)

