Classfile /Users/mw/Projects/slang-braindump/.jar/jar8/assemble/slang-braindump/assemble/content/shapeless/CaseClassMacrosVersionSpecifics.class
  Last modified May 29, 2022; size 4986 bytes
  SHA-256 checksum d9fb402d515d6ace538f4c608b3d7325a8fffaee896db136e476216ce19b1f23
  Compiled from "versionspecifics.scala"
public interface shapeless.CaseClassMacrosVersionSpecifics
  minor version: 0
  major version: 52
  flags: (0x0601) ACC_PUBLIC, ACC_INTERFACE, ACC_ABSTRACT
  this_class: #2                          // shapeless/CaseClassMacrosVersionSpecifics
  super_class: #4                         // java/lang/Object
  interfaces: 0, fields: 0, methods: 5, attributes: 5
Constant pool:
    #1 = Utf8               shapeless/CaseClassMacrosVersionSpecifics
    #2 = Class              #1            // shapeless/CaseClassMacrosVersionSpecifics
    #3 = Utf8               java/lang/Object
    #4 = Class              #3            // java/lang/Object
    #5 = Utf8               versionspecifics.scala
    #6 = Utf8               Lscala/reflect/ScalaSignature;
    #7 = Utf8               bytes
    #8 = Utf8               \u0006\u0005]2\u0001\u0002B\u0003\u0011\u0002\u0007\u0005\u0001\"\u000e\u0005\u0006\u001f\u0001!\t\u0001\u0005\u0005\b)\u0001\u0011\r\u0011\"\u0001\u0016\u0011\u001dq\u0003A1A\u0005\u0002=\u0012qdQ1tK\u000ec\u0017m]:NC\u000e\u0014xn\u001d,feNLwN\\*qK\u000eLg-[2t\u0015\u00051\u0011!C:iCB,G.Z:t\u0007\u0001\u0019\"\u0001A\u0005\u0011\u0005)iQ\"A\u0006\u000b\u00031\tQa]2bY\u0006L!AD\u0006\u0003\r\u0005s\u0017PU3g\u0003\u0019!\u0013N\\5uIQ\t\u0011\u0003\u0005\u0002\u000b%%\u00111c\u0003\u0002\u0005+:LG/A\u0005wCJ\f\'o\u001a+qiV\ta\u0003\u0005\u0002\u0018Q9\u0011\u0001D\b\b\u00033ii\u0011\u0001A\u0005\u00037q\t\u0011aY\u0005\u0003;\u0015\u0011qbQ1tK\u000ec\u0017m]:NC\u000e\u0014xn]\u0005\u0003?\u0001\n\u0001\"\u001e8jm\u0016\u00148/Z\u0005\u0003C\t\u0012qaQ8oi\u0016DHO\u0003\u0002$I\u0005A!\r\\1dW\n|\u0007P\u0003\u0002&M\u00051Q.Y2s_NT!aJ\u0006\u0002\u000fI,g\r\\3di&\u0011\u0011F\u000b\u0002\u0007\'\u0016dWm\u0019;\n\u0005-b#!\u0002+sK\u0016\u001c(BA\u0017\'\u0003\r\t\u0007/[\u0001\tm\u0006\u0014\u0018M]4U\u0007V\t\u0001\u0007\u0005\u0002\u0018c%\u0011!g\r\u0002\u0005)f\u0004X-\u0003\u00025Y\t)A+\u001f9fgB\u0011a\u0007H\u0007\u0002\u000b\u0001
    #9 = Utf8               scala/reflect/api/Internals$InternalApi
   #10 = Class              #9            // scala/reflect/api/Internals$InternalApi
   #11 = Utf8               scala/reflect/api/Internals
   #12 = Class              #11           // scala/reflect/api/Internals
   #13 = Utf8               InternalApi
   #14 = Utf8               scala/reflect/api/Internals$ReificationSupportApi
   #15 = Class              #14           // scala/reflect/api/Internals$ReificationSupportApi
   #16 = Utf8               ReificationSupportApi
   #17 = Utf8               scala/reflect/api/Internals$ReificationSupportApi$SyntacticSelectTermExtractor
   #18 = Class              #17           // scala/reflect/api/Internals$ReificationSupportApi$SyntacticSelectTermExtractor
   #19 = Utf8               SyntacticSelectTermExtractor
   #20 = Utf8               scala/reflect/api/Internals$ReificationSupportApi$SyntacticSelectTypeExtractor
   #21 = Class              #20           // scala/reflect/api/Internals$ReificationSupportApi$SyntacticSelectTypeExtractor
   #22 = Utf8               SyntacticSelectTypeExtractor
   #23 = Utf8               scala/reflect/api/Internals$ReificationSupportApi$SyntacticTermIdentExtractor
   #24 = Class              #23           // scala/reflect/api/Internals$ReificationSupportApi$SyntacticTermIdentExtractor
   #25 = Utf8               SyntacticTermIdentExtractor
   #26 = Utf8               scala/reflect/api/Names$TermNameApi
   #27 = Class              #26           // scala/reflect/api/Names$TermNameApi
   #28 = Utf8               scala/reflect/api/Names
   #29 = Class              #28           // scala/reflect/api/Names
   #30 = Utf8               TermNameApi
   #31 = Utf8               scala/reflect/api/Names$TermNameExtractor
   #32 = Class              #31           // scala/reflect/api/Names$TermNameExtractor
   #33 = Utf8               TermNameExtractor
   #34 = Utf8               scala/reflect/api/Names$TypeNameApi
   #35 = Class              #34           // scala/reflect/api/Names$TypeNameApi
   #36 = Utf8               TypeNameApi
   #37 = Utf8               scala/reflect/api/Names$TypeNameExtractor
   #38 = Class              #37           // scala/reflect/api/Names$TypeNameExtractor
   #39 = Utf8               TypeNameExtractor
   #40 = Utf8               scala/reflect/api/Trees$IdentApi
   #41 = Class              #40           // scala/reflect/api/Trees$IdentApi
   #42 = Utf8               scala/reflect/api/Trees
   #43 = Class              #42           // scala/reflect/api/Trees
   #44 = Utf8               IdentApi
   #45 = Utf8               scala/reflect/api/Trees$SelectApi
   #46 = Class              #45           // scala/reflect/api/Trees$SelectApi
   #47 = Utf8               SelectApi
   #48 = Utf8               scala/reflect/api/Trees$TreeApi
   #49 = Class              #48           // scala/reflect/api/Trees$TreeApi
   #50 = Utf8               TreeApi
   #51 = Utf8               scala/reflect/api/TypeTags$TypeTag
   #52 = Class              #51           // scala/reflect/api/TypeTags$TypeTag
   #53 = Utf8               scala/reflect/api/TypeTags
   #54 = Class              #53           // scala/reflect/api/TypeTags
   #55 = Utf8               TypeTag
   #56 = Utf8               scala/reflect/api/TypeTags$TypeTag$
   #57 = Class              #56           // scala/reflect/api/TypeTags$TypeTag$
   #58 = Utf8               TypeTag$
   #59 = Utf8               scala/reflect/api/Types$TypeApi
   #60 = Class              #59           // scala/reflect/api/Types$TypeApi
   #61 = Utf8               scala/reflect/api/Types
   #62 = Class              #61           // scala/reflect/api/Types
   #63 = Utf8               TypeApi
   #64 = Utf8               shapeless/CaseClassMacrosVersionSpecifics$$typecreator1$1
   #65 = Class              #64           // shapeless/CaseClassMacrosVersionSpecifics$$typecreator1$1
   #66 = Utf8               $typecreator1$1
   #67 = Utf8               shapeless$CaseClassMacrosVersionSpecifics$_setter_$varargTpt_$eq
   #68 = Utf8               (Lscala/reflect/api/Trees$SelectApi;)V
   #69 = Utf8               x$1
   #70 = Utf8               shapeless$CaseClassMacrosVersionSpecifics$_setter_$varargTC_$eq
   #71 = Utf8               (Lscala/reflect/api/Types$TypeApi;)V
   #72 = Utf8               varargTpt
   #73 = Utf8               ()Lscala/reflect/api/Trees$SelectApi;
   #74 = Utf8               varargTC
   #75 = Utf8               ()Lscala/reflect/api/Types$TypeApi;
   #76 = Utf8               $init$
   #77 = Utf8               (Lshapeless/CaseClassMacrosVersionSpecifics;)V
   #78 = Utf8               $this
   #79 = Utf8               shapeless/CaseClassMacros
   #80 = Class              #79           // shapeless/CaseClassMacros
   #81 = Utf8               c
   #82 = Utf8               ()Lscala/reflect/macros/whitebox/Context;
   #83 = NameAndType        #81:#82       // c:()Lscala/reflect/macros/whitebox/Context;
   #84 = InterfaceMethodref #80.#83       // shapeless/CaseClassMacros.c:()Lscala/reflect/macros/whitebox/Context;
   #85 = Utf8               scala/reflect/macros/whitebox/Context
   #86 = Class              #85           // scala/reflect/macros/whitebox/Context
   #87 = Utf8               universe
   #88 = Utf8               ()Lscala/reflect/macros/Universe;
   #89 = NameAndType        #87:#88       // universe:()Lscala/reflect/macros/Universe;
   #90 = InterfaceMethodref #86.#89       // scala/reflect/macros/whitebox/Context.universe:()Lscala/reflect/macros/Universe;
   #91 = Utf8               scala/reflect/macros/Universe
   #92 = Class              #91           // scala/reflect/macros/Universe
   #93 = Utf8               internal
   #94 = Utf8               ()Lscala/reflect/api/Internals$InternalApi;
   #95 = NameAndType        #93:#94       // internal:()Lscala/reflect/api/Internals$InternalApi;
   #96 = Methodref          #92.#95       // scala/reflect/macros/Universe.internal:()Lscala/reflect/api/Internals$InternalApi;
   #97 = Utf8               reificationSupport
   #98 = Utf8               ()Lscala/reflect/api/Internals$ReificationSupportApi;
   #99 = NameAndType        #97:#98       // reificationSupport:()Lscala/reflect/api/Internals$ReificationSupportApi;
  #100 = InterfaceMethodref #10.#99       // scala/reflect/api/Internals$InternalApi.reificationSupport:()Lscala/reflect/api/Internals$ReificationSupportApi;
  #101 = Utf8               SyntacticSelectType
  #102 = Utf8               ()Lscala/reflect/api/Internals$ReificationSupportApi$SyntacticSelectTypeExtractor;
  #103 = NameAndType        #101:#102     // SyntacticSelectType:()Lscala/reflect/api/Internals$ReificationSupportApi$SyntacticSelectTypeExtractor;
  #104 = InterfaceMethodref #15.#103      // scala/reflect/api/Internals$ReificationSupportApi.SyntacticSelectType:()Lscala/reflect/api/Internals$ReificationSupportApi$SyntacticSelectTypeExtractor;
  #105 = Utf8               SyntacticSelectTerm
  #106 = Utf8               ()Lscala/reflect/api/Internals$ReificationSupportApi$SyntacticSelectTermExtractor;
  #107 = NameAndType        #105:#106     // SyntacticSelectTerm:()Lscala/reflect/api/Internals$ReificationSupportApi$SyntacticSelectTermExtractor;
  #108 = InterfaceMethodref #15.#107      // scala/reflect/api/Internals$ReificationSupportApi.SyntacticSelectTerm:()Lscala/reflect/api/Internals$ReificationSupportApi$SyntacticSelectTermExtractor;
  #109 = Utf8               SyntacticTermIdent
  #110 = Utf8               ()Lscala/reflect/api/Internals$ReificationSupportApi$SyntacticTermIdentExtractor;
  #111 = NameAndType        #109:#110     // SyntacticTermIdent:()Lscala/reflect/api/Internals$ReificationSupportApi$SyntacticTermIdentExtractor;
  #112 = InterfaceMethodref #15.#111      // scala/reflect/api/Internals$ReificationSupportApi.SyntacticTermIdent:()Lscala/reflect/api/Internals$ReificationSupportApi$SyntacticTermIdentExtractor;
  #113 = Utf8               TermName
  #114 = Utf8               ()Lscala/reflect/api/Names$TermNameExtractor;
  #115 = NameAndType        #113:#114     // TermName:()Lscala/reflect/api/Names$TermNameExtractor;
  #116 = Methodref          #92.#115      // scala/reflect/macros/Universe.TermName:()Lscala/reflect/api/Names$TermNameExtractor;
  #117 = Utf8               _root_
  #118 = String             #117          // _root_
  #119 = Utf8               apply
  #120 = Utf8               (Ljava/lang/String;)Lscala/reflect/api/Names$TermNameApi;
  #121 = NameAndType        #119:#120     // apply:(Ljava/lang/String;)Lscala/reflect/api/Names$TermNameApi;
  #122 = Methodref          #32.#121      // scala/reflect/api/Names$TermNameExtractor.apply:(Ljava/lang/String;)Lscala/reflect/api/Names$TermNameApi;
  #123 = Utf8               (Lscala/reflect/api/Names$TermNameApi;Z)Lscala/reflect/api/Trees$IdentApi;
  #124 = NameAndType        #119:#123     // apply:(Lscala/reflect/api/Names$TermNameApi;Z)Lscala/reflect/api/Trees$IdentApi;
  #125 = InterfaceMethodref #24.#124      // scala/reflect/api/Internals$ReificationSupportApi$SyntacticTermIdentExtractor.apply:(Lscala/reflect/api/Names$TermNameApi;Z)Lscala/reflect/api/Trees$IdentApi;
  #126 = Utf8               scala
  #127 = String             #126          // scala
  #128 = Utf8               (Lscala/reflect/api/Trees$TreeApi;Lscala/reflect/api/Names$TermNameApi;)Lscala/reflect/api/Trees$SelectApi;
  #129 = NameAndType        #119:#128     // apply:(Lscala/reflect/api/Trees$TreeApi;Lscala/reflect/api/Names$TermNameApi;)Lscala/reflect/api/Trees$SelectApi;
  #130 = InterfaceMethodref #18.#129      // scala/reflect/api/Internals$ReificationSupportApi$SyntacticSelectTermExtractor.apply:(Lscala/reflect/api/Trees$TreeApi;Lscala/reflect/api/Names$TermNameApi;)Lscala/reflect/api/Trees$SelectApi;
  #131 = Utf8               collection
  #132 = String             #131          // collection
  #133 = Utf8               immutable
  #134 = String             #133          // immutable
  #135 = Utf8               TypeName
  #136 = Utf8               ()Lscala/reflect/api/Names$TypeNameExtractor;
  #137 = NameAndType        #135:#136     // TypeName:()Lscala/reflect/api/Names$TypeNameExtractor;
  #138 = Methodref          #92.#137      // scala/reflect/macros/Universe.TypeName:()Lscala/reflect/api/Names$TypeNameExtractor;
  #139 = Utf8               Seq
  #140 = String             #139          // Seq
  #141 = Utf8               (Ljava/lang/String;)Lscala/reflect/api/Names$TypeNameApi;
  #142 = NameAndType        #119:#141     // apply:(Ljava/lang/String;)Lscala/reflect/api/Names$TypeNameApi;
  #143 = Methodref          #38.#142      // scala/reflect/api/Names$TypeNameExtractor.apply:(Ljava/lang/String;)Lscala/reflect/api/Names$TypeNameApi;
  #144 = Utf8               (Lscala/reflect/api/Trees$TreeApi;Lscala/reflect/api/Names$TypeNameApi;)Lscala/reflect/api/Trees$SelectApi;
  #145 = NameAndType        #119:#144     // apply:(Lscala/reflect/api/Trees$TreeApi;Lscala/reflect/api/Names$TypeNameApi;)Lscala/reflect/api/Trees$SelectApi;
  #146 = InterfaceMethodref #21.#145      // scala/reflect/api/Internals$ReificationSupportApi$SyntacticSelectTypeExtractor.apply:(Lscala/reflect/api/Trees$TreeApi;Lscala/reflect/api/Names$TypeNameApi;)Lscala/reflect/api/Trees$SelectApi;
  #147 = NameAndType        #67:#68       // shapeless$CaseClassMacrosVersionSpecifics$_setter_$varargTpt_$eq:(Lscala/reflect/api/Trees$SelectApi;)V
  #148 = InterfaceMethodref #2.#147       // shapeless/CaseClassMacrosVersionSpecifics.shapeless$CaseClassMacrosVersionSpecifics$_setter_$varargTpt_$eq:(Lscala/reflect/api/Trees$SelectApi;)V
  #149 = Utf8               rootMirror
  #150 = Utf8               ()Lscala/reflect/api/Mirror;
  #151 = NameAndType        #149:#150     // rootMirror:()Lscala/reflect/api/Mirror;
  #152 = Methodref          #92.#151      // scala/reflect/macros/Universe.rootMirror:()Lscala/reflect/api/Mirror;
  #153 = Utf8               ()Lscala/reflect/api/TypeTags$TypeTag$;
  #154 = NameAndType        #55:#153      // TypeTag:()Lscala/reflect/api/TypeTags$TypeTag$;
  #155 = Methodref          #92.#154      // scala/reflect/macros/Universe.TypeTag:()Lscala/reflect/api/TypeTags$TypeTag$;
  #156 = Utf8               <init>
  #157 = Utf8               (Lshapeless/CaseClassMacros;)V
  #158 = NameAndType        #156:#157     // "<init>":(Lshapeless/CaseClassMacros;)V
  #159 = Methodref          #65.#158      // shapeless/CaseClassMacrosVersionSpecifics$$typecreator1$1."<init>":(Lshapeless/CaseClassMacros;)V
  #160 = Utf8               (Lscala/reflect/api/Mirror;Lscala/reflect/api/TypeCreator;)Lscala/reflect/api/TypeTags$TypeTag;
  #161 = NameAndType        #119:#160     // apply:(Lscala/reflect/api/Mirror;Lscala/reflect/api/TypeCreator;)Lscala/reflect/api/TypeTags$TypeTag;
  #162 = Methodref          #57.#161      // scala/reflect/api/TypeTags$TypeTag$.apply:(Lscala/reflect/api/Mirror;Lscala/reflect/api/TypeCreator;)Lscala/reflect/api/TypeTags$TypeTag;
  #163 = Utf8               typeOf
  #164 = Utf8               (Lscala/reflect/api/TypeTags$TypeTag;)Lscala/reflect/api/Types$TypeApi;
  #165 = NameAndType        #163:#164     // typeOf:(Lscala/reflect/api/TypeTags$TypeTag;)Lscala/reflect/api/Types$TypeApi;
  #166 = Methodref          #92.#165      // scala/reflect/macros/Universe.typeOf:(Lscala/reflect/api/TypeTags$TypeTag;)Lscala/reflect/api/Types$TypeApi;
  #167 = Utf8               typeConstructor
  #168 = NameAndType        #167:#75      // typeConstructor:()Lscala/reflect/api/Types$TypeApi;
  #169 = Methodref          #60.#168      // scala/reflect/api/Types$TypeApi.typeConstructor:()Lscala/reflect/api/Types$TypeApi;
  #170 = NameAndType        #70:#71       // shapeless$CaseClassMacrosVersionSpecifics$_setter_$varargTC_$eq:(Lscala/reflect/api/Types$TypeApi;)V
  #171 = InterfaceMethodref #2.#170       // shapeless/CaseClassMacrosVersionSpecifics.shapeless$CaseClassMacrosVersionSpecifics$_setter_$varargTC_$eq:(Lscala/reflect/api/Types$TypeApi;)V
  #172 = Utf8               $u
  #173 = Utf8               Lscala/reflect/macros/Universe;
  #174 = Utf8               $m
  #175 = Utf8               Lscala/reflect/api/Mirror;
  #176 = Utf8               Lshapeless/CaseClassMacrosVersionSpecifics;
  #177 = Utf8               MethodParameters
  #178 = Utf8               Code
  #179 = Utf8               LineNumberTable
  #180 = Utf8               LocalVariableTable
  #181 = Utf8               InnerClasses
  #182 = Utf8               SourceFile
  #183 = Utf8               RuntimeVisibleAnnotations
  #184 = Utf8               ScalaInlineInfo
  #185 = Utf8               ScalaSig
{
  public abstract void shapeless$CaseClassMacrosVersionSpecifics$_setter_$varargTpt_$eq(scala.reflect.api.Trees$SelectApi);
    descriptor: (Lscala/reflect/api/Trees$SelectApi;)V
    flags: (0x0401) ACC_PUBLIC, ACC_ABSTRACT
    MethodParameters:
      Name                           Flags
      x$1                            final

  public abstract void shapeless$CaseClassMacrosVersionSpecifics$_setter_$varargTC_$eq(scala.reflect.api.Types$TypeApi);
    descriptor: (Lscala/reflect/api/Types$TypeApi;)V
    flags: (0x0401) ACC_PUBLIC, ACC_ABSTRACT
    MethodParameters:
      Name                           Flags
      x$1                            final

  public abstract scala.reflect.api.Trees$SelectApi varargTpt();
    descriptor: ()Lscala/reflect/api/Trees$SelectApi;
    flags: (0x0401) ACC_PUBLIC, ACC_ABSTRACT

  public abstract scala.reflect.api.Types$TypeApi varargTC();
    descriptor: ()Lscala/reflect/api/Types$TypeApi;
    flags: (0x0401) ACC_PUBLIC, ACC_ABSTRACT

  public static void $init$(shapeless.CaseClassMacrosVersionSpecifics);
    descriptor: (Lshapeless/CaseClassMacrosVersionSpecifics;)V
    flags: (0x0009) ACC_PUBLIC, ACC_STATIC
    Code:
      stack=8, locals=3, args_size=1
         0: aload_0
         1: aload_0
         2: checkcast     #80                 // class shapeless/CaseClassMacros
         5: invokeinterface #84,  1           // InterfaceMethod shapeless/CaseClassMacros.c:()Lscala/reflect/macros/whitebox/Context;
        10: invokeinterface #90,  1           // InterfaceMethod scala/reflect/macros/whitebox/Context.universe:()Lscala/reflect/macros/Universe;
        15: invokevirtual #96                 // Method scala/reflect/macros/Universe.internal:()Lscala/reflect/api/Internals$InternalApi;
        18: invokeinterface #100,  1          // InterfaceMethod scala/reflect/api/Internals$InternalApi.reificationSupport:()Lscala/reflect/api/Internals$ReificationSupportApi;
        23: invokeinterface #104,  1          // InterfaceMethod scala/reflect/api/Internals$ReificationSupportApi.SyntacticSelectType:()Lscala/reflect/api/Internals$ReificationSupportApi$SyntacticSelectTypeExtractor;
        28: aload_0
        29: checkcast     #80                 // class shapeless/CaseClassMacros
        32: invokeinterface #84,  1           // InterfaceMethod shapeless/CaseClassMacros.c:()Lscala/reflect/macros/whitebox/Context;
        37: invokeinterface #90,  1           // InterfaceMethod scala/reflect/macros/whitebox/Context.universe:()Lscala/reflect/macros/Universe;
        42: invokevirtual #96                 // Method scala/reflect/macros/Universe.internal:()Lscala/reflect/api/Internals$InternalApi;
        45: invokeinterface #100,  1          // InterfaceMethod scala/reflect/api/Internals$InternalApi.reificationSupport:()Lscala/reflect/api/Internals$ReificationSupportApi;
        50: invokeinterface #108,  1          // InterfaceMethod scala/reflect/api/Internals$ReificationSupportApi.SyntacticSelectTerm:()Lscala/reflect/api/Internals$ReificationSupportApi$SyntacticSelectTermExtractor;
        55: aload_0
        56: checkcast     #80                 // class shapeless/CaseClassMacros
        59: invokeinterface #84,  1           // InterfaceMethod shapeless/CaseClassMacros.c:()Lscala/reflect/macros/whitebox/Context;
        64: invokeinterface #90,  1           // InterfaceMethod scala/reflect/macros/whitebox/Context.universe:()Lscala/reflect/macros/Universe;
        69: invokevirtual #96                 // Method scala/reflect/macros/Universe.internal:()Lscala/reflect/api/Internals$InternalApi;
        72: invokeinterface #100,  1          // InterfaceMethod scala/reflect/api/Internals$InternalApi.reificationSupport:()Lscala/reflect/api/Internals$ReificationSupportApi;
        77: invokeinterface #108,  1          // InterfaceMethod scala/reflect/api/Internals$ReificationSupportApi.SyntacticSelectTerm:()Lscala/reflect/api/Internals$ReificationSupportApi$SyntacticSelectTermExtractor;
        82: aload_0
        83: checkcast     #80                 // class shapeless/CaseClassMacros
        86: invokeinterface #84,  1           // InterfaceMethod shapeless/CaseClassMacros.c:()Lscala/reflect/macros/whitebox/Context;
        91: invokeinterface #90,  1           // InterfaceMethod scala/reflect/macros/whitebox/Context.universe:()Lscala/reflect/macros/Universe;
        96: invokevirtual #96                 // Method scala/reflect/macros/Universe.internal:()Lscala/reflect/api/Internals$InternalApi;
        99: invokeinterface #100,  1          // InterfaceMethod scala/reflect/api/Internals$InternalApi.reificationSupport:()Lscala/reflect/api/Internals$ReificationSupportApi;
       104: invokeinterface #108,  1          // InterfaceMethod scala/reflect/api/Internals$ReificationSupportApi.SyntacticSelectTerm:()Lscala/reflect/api/Internals$ReificationSupportApi$SyntacticSelectTermExtractor;
       109: aload_0
       110: checkcast     #80                 // class shapeless/CaseClassMacros
       113: invokeinterface #84,  1           // InterfaceMethod shapeless/CaseClassMacros.c:()Lscala/reflect/macros/whitebox/Context;
       118: invokeinterface #90,  1           // InterfaceMethod scala/reflect/macros/whitebox/Context.universe:()Lscala/reflect/macros/Universe;
       123: invokevirtual #96                 // Method scala/reflect/macros/Universe.internal:()Lscala/reflect/api/Internals$InternalApi;
       126: invokeinterface #100,  1          // InterfaceMethod scala/reflect/api/Internals$InternalApi.reificationSupport:()Lscala/reflect/api/Internals$ReificationSupportApi;
       131: invokeinterface #112,  1          // InterfaceMethod scala/reflect/api/Internals$ReificationSupportApi.SyntacticTermIdent:()Lscala/reflect/api/Internals$ReificationSupportApi$SyntacticTermIdentExtractor;
       136: aload_0
       137: checkcast     #80                 // class shapeless/CaseClassMacros
       140: invokeinterface #84,  1           // InterfaceMethod shapeless/CaseClassMacros.c:()Lscala/reflect/macros/whitebox/Context;
       145: invokeinterface #90,  1           // InterfaceMethod scala/reflect/macros/whitebox/Context.universe:()Lscala/reflect/macros/Universe;
       150: invokevirtual #116                // Method scala/reflect/macros/Universe.TermName:()Lscala/reflect/api/Names$TermNameExtractor;
       153: ldc           #118                // String _root_
       155: invokevirtual #122                // Method scala/reflect/api/Names$TermNameExtractor.apply:(Ljava/lang/String;)Lscala/reflect/api/Names$TermNameApi;
       158: iconst_0
       159: invokeinterface #125,  3          // InterfaceMethod scala/reflect/api/Internals$ReificationSupportApi$SyntacticTermIdentExtractor.apply:(Lscala/reflect/api/Names$TermNameApi;Z)Lscala/reflect/api/Trees$IdentApi;
       164: aload_0
       165: checkcast     #80                 // class shapeless/CaseClassMacros
       168: invokeinterface #84,  1           // InterfaceMethod shapeless/CaseClassMacros.c:()Lscala/reflect/macros/whitebox/Context;
       173: invokeinterface #90,  1           // InterfaceMethod scala/reflect/macros/whitebox/Context.universe:()Lscala/reflect/macros/Universe;
       178: invokevirtual #116                // Method scala/reflect/macros/Universe.TermName:()Lscala/reflect/api/Names$TermNameExtractor;
       181: ldc           #127                // String scala
       183: invokevirtual #122                // Method scala/reflect/api/Names$TermNameExtractor.apply:(Ljava/lang/String;)Lscala/reflect/api/Names$TermNameApi;
       186: invokeinterface #130,  3          // InterfaceMethod scala/reflect/api/Internals$ReificationSupportApi$SyntacticSelectTermExtractor.apply:(Lscala/reflect/api/Trees$TreeApi;Lscala/reflect/api/Names$TermNameApi;)Lscala/reflect/api/Trees$SelectApi;
       191: aload_0
       192: checkcast     #80                 // class shapeless/CaseClassMacros
       195: invokeinterface #84,  1           // InterfaceMethod shapeless/CaseClassMacros.c:()Lscala/reflect/macros/whitebox/Context;
       200: invokeinterface #90,  1           // InterfaceMethod scala/reflect/macros/whitebox/Context.universe:()Lscala/reflect/macros/Universe;
       205: invokevirtual #116                // Method scala/reflect/macros/Universe.TermName:()Lscala/reflect/api/Names$TermNameExtractor;
       208: ldc           #132                // String collection
       210: invokevirtual #122                // Method scala/reflect/api/Names$TermNameExtractor.apply:(Ljava/lang/String;)Lscala/reflect/api/Names$TermNameApi;
       213: invokeinterface #130,  3          // InterfaceMethod scala/reflect/api/Internals$ReificationSupportApi$SyntacticSelectTermExtractor.apply:(Lscala/reflect/api/Trees$TreeApi;Lscala/reflect/api/Names$TermNameApi;)Lscala/reflect/api/Trees$SelectApi;
       218: aload_0
       219: checkcast     #80                 // class shapeless/CaseClassMacros
       222: invokeinterface #84,  1           // InterfaceMethod shapeless/CaseClassMacros.c:()Lscala/reflect/macros/whitebox/Context;
       227: invokeinterface #90,  1           // InterfaceMethod scala/reflect/macros/whitebox/Context.universe:()Lscala/reflect/macros/Universe;
       232: invokevirtual #116                // Method scala/reflect/macros/Universe.TermName:()Lscala/reflect/api/Names$TermNameExtractor;
       235: ldc           #134                // String immutable
       237: invokevirtual #122                // Method scala/reflect/api/Names$TermNameExtractor.apply:(Ljava/lang/String;)Lscala/reflect/api/Names$TermNameApi;
       240: invokeinterface #130,  3          // InterfaceMethod scala/reflect/api/Internals$ReificationSupportApi$SyntacticSelectTermExtractor.apply:(Lscala/reflect/api/Trees$TreeApi;Lscala/reflect/api/Names$TermNameApi;)Lscala/reflect/api/Trees$SelectApi;
       245: aload_0
       246: checkcast     #80                 // class shapeless/CaseClassMacros
       249: invokeinterface #84,  1           // InterfaceMethod shapeless/CaseClassMacros.c:()Lscala/reflect/macros/whitebox/Context;
       254: invokeinterface #90,  1           // InterfaceMethod scala/reflect/macros/whitebox/Context.universe:()Lscala/reflect/macros/Universe;
       259: invokevirtual #138                // Method scala/reflect/macros/Universe.TypeName:()Lscala/reflect/api/Names$TypeNameExtractor;
       262: ldc           #140                // String Seq
       264: invokevirtual #143                // Method scala/reflect/api/Names$TypeNameExtractor.apply:(Ljava/lang/String;)Lscala/reflect/api/Names$TypeNameApi;
       267: invokeinterface #146,  3          // InterfaceMethod scala/reflect/api/Internals$ReificationSupportApi$SyntacticSelectTypeExtractor.apply:(Lscala/reflect/api/Trees$TreeApi;Lscala/reflect/api/Names$TypeNameApi;)Lscala/reflect/api/Trees$SelectApi;
       272: invokeinterface #148,  2          // InterfaceMethod shapeless$CaseClassMacrosVersionSpecifics$_setter_$varargTpt_$eq:(Lscala/reflect/api/Trees$SelectApi;)V
       277: aload_0
       278: aload_0
       279: checkcast     #80                 // class shapeless/CaseClassMacros
       282: invokeinterface #84,  1           // InterfaceMethod shapeless/CaseClassMacros.c:()Lscala/reflect/macros/whitebox/Context;
       287: invokeinterface #90,  1           // InterfaceMethod scala/reflect/macros/whitebox/Context.universe:()Lscala/reflect/macros/Universe;
       292: aload_0
       293: checkcast     #80                 // class shapeless/CaseClassMacros
       296: invokeinterface #84,  1           // InterfaceMethod shapeless/CaseClassMacros.c:()Lscala/reflect/macros/whitebox/Context;
       301: invokeinterface #90,  1           // InterfaceMethod scala/reflect/macros/whitebox/Context.universe:()Lscala/reflect/macros/Universe;
       306: astore_1
       307: aload_0
       308: checkcast     #80                 // class shapeless/CaseClassMacros
       311: invokeinterface #84,  1           // InterfaceMethod shapeless/CaseClassMacros.c:()Lscala/reflect/macros/whitebox/Context;
       316: invokeinterface #90,  1           // InterfaceMethod scala/reflect/macros/whitebox/Context.universe:()Lscala/reflect/macros/Universe;
       321: invokevirtual #152                // Method scala/reflect/macros/Universe.rootMirror:()Lscala/reflect/api/Mirror;
       324: astore_2
       325: aload_1
       326: invokevirtual #155                // Method scala/reflect/macros/Universe.TypeTag:()Lscala/reflect/api/TypeTags$TypeTag$;
       329: aload_2
       330: new           #65                 // class shapeless/CaseClassMacrosVersionSpecifics$$typecreator1$1
       333: dup
       334: aload_0
       335: checkcast     #80                 // class shapeless/CaseClassMacros
       338: invokespecial #159                // Method shapeless/CaseClassMacrosVersionSpecifics$$typecreator1$1."<init>":(Lshapeless/CaseClassMacros;)V
       341: invokevirtual #162                // Method scala/reflect/api/TypeTags$TypeTag$.apply:(Lscala/reflect/api/Mirror;Lscala/reflect/api/TypeCreator;)Lscala/reflect/api/TypeTags$TypeTag;
       344: invokevirtual #166                // Method scala/reflect/macros/Universe.typeOf:(Lscala/reflect/api/TypeTags$TypeTag;)Lscala/reflect/api/Types$TypeApi;
       347: invokevirtual #169                // Method scala/reflect/api/Types$TypeApi.typeConstructor:()Lscala/reflect/api/Types$TypeApi;
       350: invokeinterface #171,  2          // InterfaceMethod shapeless$CaseClassMacrosVersionSpecifics$_setter_$varargTC_$eq:(Lscala/reflect/api/Types$TypeApi;)V
       355: return
      LineNumberTable:
        line 43: 0
        line 44: 277
        line 40: 355
      LocalVariableTable:
        Start  Length  Slot  Name   Signature
          306      38     1    $u   Lscala/reflect/macros/Universe;
          324      20     2    $m   Lscala/reflect/api/Mirror;
            0     356     0 $this   Lshapeless/CaseClassMacrosVersionSpecifics;
    MethodParameters:
      Name                           Flags
      $this                          final synthetic
}
InnerClasses:
  public #13= #10 of #12;                 // InternalApi=class scala/reflect/api/Internals$InternalApi of class scala/reflect/api/Internals
  public #16= #15 of #12;                 // ReificationSupportApi=class scala/reflect/api/Internals$ReificationSupportApi of class scala/reflect/api/Internals
  public #19= #18 of #15;                 // SyntacticSelectTermExtractor=class scala/reflect/api/Internals$ReificationSupportApi$SyntacticSelectTermExtractor of class scala/reflect/api/Internals$ReificationSupportApi
  public #22= #21 of #15;                 // SyntacticSelectTypeExtractor=class scala/reflect/api/Internals$ReificationSupportApi$SyntacticSelectTypeExtractor of class scala/reflect/api/Internals$ReificationSupportApi
  public #25= #24 of #15;                 // SyntacticTermIdentExtractor=class scala/reflect/api/Internals$ReificationSupportApi$SyntacticTermIdentExtractor of class scala/reflect/api/Internals$ReificationSupportApi
  public #30= #27 of #29;                 // TermNameApi=class scala/reflect/api/Names$TermNameApi of class scala/reflect/api/Names
  public abstract #33= #32 of #29;        // TermNameExtractor=class scala/reflect/api/Names$TermNameExtractor of class scala/reflect/api/Names
  public #36= #35 of #29;                 // TypeNameApi=class scala/reflect/api/Names$TypeNameApi of class scala/reflect/api/Names
  public abstract #39= #38 of #29;        // TypeNameExtractor=class scala/reflect/api/Names$TypeNameExtractor of class scala/reflect/api/Names
  public #44= #41 of #43;                 // IdentApi=class scala/reflect/api/Trees$IdentApi of class scala/reflect/api/Trees
  public #47= #46 of #43;                 // SelectApi=class scala/reflect/api/Trees$SelectApi of class scala/reflect/api/Trees
  public #50= #49 of #43;                 // TreeApi=class scala/reflect/api/Trees$TreeApi of class scala/reflect/api/Trees
  public #55= #52 of #54;                 // TypeTag=class scala/reflect/api/TypeTags$TypeTag of class scala/reflect/api/TypeTags
  public #58= #57 of #54;                 // TypeTag$=class scala/reflect/api/TypeTags$TypeTag$ of class scala/reflect/api/TypeTags
  public abstract #63= #60 of #62;        // TypeApi=class scala/reflect/api/Types$TypeApi of class scala/reflect/api/Types
  public final #66= #65;                  // $typecreator1$1=class shapeless/CaseClassMacrosVersionSpecifics$$typecreator1$1
SourceFile: "versionspecifics.scala"
RuntimeVisibleAnnotations:
  0: #6(#7=s#8)
    scala.reflect.ScalaSignature(
      bytes="\u0006\u0005]2\u0001\u0002B\u0003\u0011\u0002\u0007\u0005\u0001\"\u000e\u0005\u0006\u001f\u0001!\t\u0001\u0005\u0005\b)\u0001\u0011\r\u0011\"\u0001\u0016\u0011\u001dq\u0003A1A\u0005\u0002=\u0012qdQ1tK\u000ec\u0017m]:NC\u000e\u0014xn\u001d,feNLwN\\*qK\u000eLg-[2t\u0015\u00051\u0011!C:iCB,G.Z:t\u0007\u0001\u0019\"\u0001A\u0005\u0011\u0005)iQ\"A\u0006\u000b\u00031\tQa]2bY\u0006L!AD\u0006\u0003\r\u0005s\u0017PU3g\u0003\u0019!\u0013N\\5uIQ\t\u0011\u0003\u0005\u0002\u000b%%\u00111c\u0003\u0002\u0005+:LG/A\u0005wCJ\f\'o\u001a+qiV\ta\u0003\u0005\u0002\u0018Q9\u0011\u0001D\b\b\u00033ii\u0011\u0001A\u0005\u00037q\t\u0011aY\u0005\u0003;\u0015\u0011qbQ1tK\u000ec\u0017m]:NC\u000e\u0014xn]\u0005\u0003?\u0001\n\u0001\"\u001e8jm\u0016\u00148/Z\u0005\u0003C\t\u0012qaQ8oi\u0016DHO\u0003\u0002$I\u0005A!\r\\1dW\n|\u0007P\u0003\u0002&M\u00051Q.Y2s_NT!aJ\u0006\u0002\u000fI,g\r\\3di&\u0011\u0011F\u000b\u0002\u0007\'\u0016dWm\u0019;\n\u0005-b#!\u0002+sK\u0016\u001c(BA\u0017\'\u0003\r\t\u0007/[\u0001\tm\u0006\u0014\u0018M]4U\u0007V\t\u0001\u0007\u0005\u0002\u0018c%\u0011!g\r\u0002\u0005)f\u0004X-\u0003\u00025Y\t)A+\u001f9fgB\u0011a\u0007H\u0007\u0002\u000b\u0001"
    )
  ScalaInlineInfo: length = 0x1D (unknown attribute)
   01 00 00 05 00 4C 00 4D 01 00 46 00 47 00 00 43
   00 44 00 00 4A 00 4B 00 00 48 00 49 00
  ScalaSig: length = 0x3 (unknown attribute)
   05 02 00
