Classfile /Users/mw/Projects/slang-braindump/.jar/jar8/assemble/slang-braindump/assemble/content/shapeless/DataT.class
  Last modified May 29, 2022; size 6173 bytes
  SHA-256 checksum 54f831a9c3df83aec2cea2df7d15fc2a27f1b7f929a270541d3891a3c929feba
  Compiled from "sybclass.scala"
public interface shapeless.DataT<F extends java.lang.Object, T extends java.lang.Object> extends java.io.Serializable
  minor version: 0
  major version: 52
  flags: (0x0601) ACC_PUBLIC, ACC_INTERFACE, ACC_ABSTRACT
  this_class: #2                          // shapeless/DataT
  super_class: #5                         // java/lang/Object
  interfaces: 1, fields: 0, methods: 11, attributes: 6
Constant pool:
   #1 = Utf8               shapeless/DataT
   #2 = Class              #1             // shapeless/DataT
   #3 = Utf8               <F:Ljava/lang/Object;T:Ljava/lang/Object;>Ljava/lang/Object;Ljava/io/Serializable;
   #4 = Utf8               java/lang/Object
   #5 = Class              #4             // java/lang/Object
   #6 = Utf8               java/io/Serializable
   #7 = Class              #6             // java/io/Serializable
   #8 = Utf8               sybclass.scala
   #9 = Utf8               Lscala/reflect/ScalaSignature;
  #10 = Utf8               bytes
  #11 = Utf8               \u0006\u0005\tuda\u0002\t\u0012!\u0003\r\n\u0001\u0006\u0003\u0006Q\u0001\u0011\t!\u000b\u0005\u0006a\u00011\t!M\u0004\u0006yEA\t!\u0010\u0004\u0006!EA\ta\u0010\u0005\u0006\u0015\u0012!\ta\u0013\u0005\u0006\u0019\u0012!\t!\u0014\u0005\u0006a\u0011!\tA\u0017\u0005\u0006]\u0012!\ta\u001c\u0005\b\u0003\u007f!A1AA!\u0011\u001d\t\t\t\u0002C\u0002\u0003\u0007Cq!a4\u0005\t\u0007\t\t\u000eC\u0004\u0002b\u0012!\u0019!a9\t\u000f\t\rB\u0001b\u0001\u0003&!9!Q\u0007\u0003\u0005\u0004\t]\u0002\"\u0003B7\t\u0005\u0005I\u0011\u0002B8\u0005\u0015!\u0015\r^1U\u0015\u0005\u0011\u0012!C:iCB,G.Z:t\u0007\u0001)2!\u0006\u001e9\'\r\u0001a\u0003\b\t\u0003/ii\u0011\u0001\u0007\u0006\u00023\u0005)1oY1mC&\u00111\u0004\u0007\u0002\u0007\u0003:L(+\u001a4\u0011\u0005u)cB\u0001\u0010$\u001d\ty\"%D\u0001!\u0015\t\t3#\u0001\u0004=e>|GOP\u0005\u00023%\u0011A\u0005G\u0001\ba\u0006\u001c7.Y4f\u0013\t1sE\u0001\u0007TKJL\u0017\r\\5{C\ndWM\u0003\u0002%1\t\u0019q*\u001e;\u0012\u0005)j\u0003CA\f,\u0013\ta\u0003DA\u0004O_RD\u0017N\\4\u0011\u0005]q\u0013BA\u0018\u0019\u0005\r\te._\u0001\u0006O6\f\u0007\u000f\u0016\u000b\u0003eQ\u0002\"aM\u0001\u000e\u0003\u0001AQ!\u000e\u0002A\u0002Y\n\u0011\u0001\u001e\t\u0003oab\u0001\u0001B\u0003:\u0001\t\u0007\u0011FA\u0001U\t\u0015Y\u0004A1\u0001*\u0005\u00051\u0015!\u0002#bi\u0006$\u0006C\u0001 \u0005\u001b\u0005\t2\u0003\u0002\u0003\u0017\u0001\u000e\u0003\"AP!\n\u0005\t\u000b\"A\u0002#bi\u0006$\u0016\u0007\u0005\u0002E\u00136\tQI\u0003\u0002G\u000f\u0006\u0011\u0011n\u001c\u0006\u0002\u0011\u0006!!.\u0019<b\u0013\t1S)\u0001\u0004=S:LGO\u0010\u000b\u0002{\u0005)\u0011\r\u001d9msV\u0019a*\u0015+\u0015\u0005=+\u0006\u0003\u0002 \u0001!N\u0003\"aN)\u0005\u000bI3!\u0019A\u0015\u0003\u0003A\u0003\"a\u000e+\u0005\u000be2!\u0019A\u0015\t\u000bY3\u00019A,\u0002\u0007\u0011$H\u000fE\u0002?1>K!!W\t\u0003\t1\u000b\'0_\u000b\u00047\u001aDGC\u0001/m)\ti6\u000e\u0006\u0002_CB\u0011q,\u0001\b\u0003A&t!aN1\t\u000b\t<\u00019A2\u0002\t\u0011\fG/\u0019\t\u0004}a#\u0007\u0003\u0002 \u0001K\u001e\u0004\"a\u000e4\u0005\u000bm:!\u0019A\u0015\u0011\u0005]BG!B\u001d\b\u0005\u0004I\u0013B\u00016Y\u0003\u00151\u0018\r\\;f\u0011\u0015)t\u00011\u0001h\u0011\u0015iw\u00011\u0001f\u0003\u00051\u0017!\u00037jgR$\u0015\r^1U+\u0019\u0001\b0a\u0001\u0002\nQ\u0019\u0011/!\u0004\u0011\rI\u001cx/`A\u0003\u001b\u0005!\u0011B\u0001;v\u0005\r\tU\u000f_\u0005\u0003mF\u0011a\u0001R1uCR\u0003\u0004CA\u001cy\t\u0015Y\u0004B1\u0001z#\tQ#\u0010\u0005\u0002?w&\u0011A0\u0005\u0002\u0005!>d\u0017\u0010\u0005\u0003\u001e}\u0006\u0005\u0011BA@(\u0005\u0011a\u0015n\u001d;\u0011\u0007]\n\u0019\u0001B\u0003:\u0011\t\u0007\u0011\u0006\u0005\u0003\u001e}\u0006\u001d\u0001cA\u001c\u0002\n\u00111\u00111\u0002\u0005C\u0002%\u0012\u0011!\u0016\u0005\b\u0003\u001fA\u00019AA\t\u0003\t1G\u000f\u0005\u0003?1\u0006M\u0001#CA\u000b\u0003W9\u0018\u0011AA\u0004\u001d\u0011\t9\"a\t\u000f\t\u0005e\u0011Q\u0004\b\u0004}\u0005m\u0011B\u0001\u0013\u0012\u0013\u0011\ty\"!\t\u0002\tA|G.\u001f\u0006\u0003IEIA!!\n\u0002(\u0005)1)Y:fc%\u0019\u0011\u0011F\t\u0003\u000b\r\u000b7/Z:\n\u0007Q\fiC\u0003\u0003\u0002&\u0005\u001d\u0002f\u0002\u0005\u00022\u0005]\u00121\b\t\u0004/\u0005M\u0012bAA\u001b1\tQA-\u001a9sK\u000e\fG/\u001a3\"\u0005\u0005e\u0012!I*va\u0016\u00148/\u001a3fI\u0002\u0012\u0017\u0010I4f]R\u0013\u0018M^3sg\u0006\u0014G.\u001a#bi\u0006$\u0016EAA\u001f\u0003\u0015\u0011df\r\u00182\u0003M9WM\u001c+sCZ,\'o]1cY\u0016$\u0015\r^1U+)\t\u0019%!\u0013\u0002N\u0005%\u0014q\u000e\u000b\u0007\u0003\u000b\n\t(a\u001e\u0011\u0011I\u001c\u0018qIA&\u0003W\u00022aNA%\t\u0015Y\u0014B1\u0001z!\u00159\u0014QJA4\t\u001d\ty%\u0003b\u0001\u0003#\u0012!aQ\"\u0016\t\u0005M\u00131M\t\u0004U\u0005U\u0003CBA,\u0003;\n\t\'\u0004\u0002\u0002Z)\u0019\u00111\f\r\u0002\u0015\r|G\u000e\\3di&|g.\u0003\u0003\u0002`\u0005e#\u0001C%uKJ\f\'\r\\3\u0011\u0007]\n\u0019\u0007B\u0004\u0002f\u00055#\u0019A\u0015\u0003\u0003a\u00032aNA5\t\u0015I\u0014B1\u0001*!\u00159\u0014QJA7!\r9\u0014q\u000e\u0003\u0007\u0003\u0017I!\u0019A\u0015\t\u000f\u0005=\u0011\u0002q\u0001\u0002tA!a\bWA;!)\t)\"a\u000b\u0002H\u0005\u001d\u0014Q\u000e\u0005\b\u0003sJ\u00019AA>\u0003\r\u0019\'M\u001a\t\t\u0003/\ni(!\u001c\u0002l%!\u0011qPA-\u0005\u001d1\u0015m\u0019;pef\f1bZ3o\u001b\u0006\u0004H)\u0019;b)Va\u0011QQAF\u0003\u001f\u000bi*a)\u0002,RA\u0011qQAW\u0003{\u000b)\r\u0005\u0005sg\u0006%\u0015QRAT!\r9\u00141\u0012\u0003\u0006w)\u0011\r!\u001f\t\bo\u0005=\u00151TAQ\t\u001d\t\tJ\u0003b\u0001\u0003\'\u0013\u0011!T\u000b\u0006S\u0005U\u0015q\u0013\u0003\b\u0003K\nyI1\u0001*\t\u001d\tI*a$C\u0002%\u0012\u0011!\u0017\t\u0004o\u0005uEABAP\u0015\t\u0007\u0011FA\u0001L!\r9\u00141\u0015\u0003\u0007\u0003KS!\u0019A\u0015\u0003\u0003Y\u0003raNAH\u00037\u000bI\u000bE\u00028\u0003W#a!a\u0003\u000b\u0005\u0004I\u0003bBAX\u0015\u0001\u000f\u0011\u0011W\u0001\u0003KZ\u0004raFAZ\u0003\u001b\u000b9,C\u0002\u00026b\u0011\u0001\u0003\n7fgN$3m\u001c7p]\u0012bWm]:\u0011\u0011\u0005]\u0013\u0011XAN\u0003CKA!a/\u0002Z\t\u0019Q*\u00199\t\u000f\u0005}&\u0002q\u0001\u0002B\u0006\u0011aM\u001e\t\u0005}a\u000b\u0019\r\u0005\u0006\u0002\u0016\u0005-\u0012\u0011RAQ\u0003SCq!!\u001f\u000b\u0001\b\t9\r\u0005\u0005\u0002X\u0005u\u0014\u0011ZAT!\u001d9\u00121ZAN\u0003SK1!!4\u0019\u0005\u0019!V\u000f\u001d7fe\u0005QA-\u001a:jm\u0016De*\u001b7\u0016\t\u0005M\u0017\u0011\\\u000b\u0003\u0003+\u0004\u0002B]:\u0002X\u0006m\u00171\u001c\t\u0004o\u0005eG!\u0002*\f\u0005\u0004I\u0003c\u0001 \u0002^&\u0019\u0011q\\\t\u0003\t!s\u0015\u000e\\\u0001\fI\u0016\u0014\u0018N^3I\u0007>t7/\u0006\u0007\u0002f\u0006-\u0018Q_A~\u0005\u0013\u0011y\u0001\u0006\u0004\u0002h\nM!1\u0004\t\teN\fI/!<\u0003\u0006A\u0019q\'a;\u0005\u000bIc!\u0019A\u0015\u0011\u000fy\ny/a=\u0002z&\u0019\u0011\u0011_\t\u0003\u0019\u0011\u001aw\u000e\\8oI\r|Gn\u001c8\u0011\u0007]\n)\u0010\u0002\u0004\u0002x2\u0011\r!\u000b\u0002\u0002\u0011B\u0019q\'a?\u0005\reb!\u0019AA\u007f#\rQ\u0013q \t\u0004}\t\u0005\u0011b\u0001B\u0002#\t)\u0001\nT5tiB9a(a<\u0003\b\t5\u0001cA\u001c\u0003\n\u00111!1\u0002\u0007C\u0002%\u0012AaT;u\u0011B\u0019qGa\u0004\u0005\u000f\tEAB1\u0001\u0002~\n!q*\u001e;U\u0011\u001d\u0011)\u0002\u0004a\u0002\u0005/\t!a\u00195\u0011\tyB&\u0011\u0004\t\u000b\u0003+\tY#!;\u0002t\n\u001d\u0001B\u0002,\r\u0001\b\u0011i\u0002\u0005\u0003?1\n}\u0001#\u0003B\u0011g\u0006%\u0018\u0011 B\u0007\u001d\tq4!\u0001\u0006eKJLg/Z\"OS2,BAa\n\u0003.U\u0011!\u0011\u0006\t\teN\u0014YCa\f\u00030A\u0019qG!\f\u0005\u000bIk!\u0019A\u0015\u0011\u0007y\u0012\t$C\u0002\u00034E\u0011Aa\u0011(jY\u0006YA-\u001a:jm\u0016\u001c5i\u001c8t+1\u0011IDa\u0010\u0003J\t5#1\fB0)\u0019\u0011YD!\u0019\u0003hAA!o\u001dB\u001f\u0005\u0003\u00129\u0006E\u00028\u0005\u007f!QA\u0015\bC\u0002%\u0002rA\u0010B\"\u0005\u000f\u0012Y%C\u0002\u0003FE\u0011\u0011\u0003J2pY>tG\u0005\u001d7vg\u0012\u001aw\u000e\\8o!\r9$\u0011\n\u0003\u0007\u0003ot!\u0019A\u0015\u0011\u0007]\u0012i\u0005\u0002\u0004:\u001d\t\u0007!qJ\t\u0004U\tE\u0003c\u0001 \u0003T%\u0019!QK\t\u0003\u0013\r{\u0007O]8ek\u000e$\bc\u0002 \u0003D\te#Q\f\t\u0004o\tmCA\u0002B\u0006\u001d\t\u0007\u0011\u0006E\u00028\u0005?\"qA!\u0005\u000f\u0005\u0004\u0011y\u0005C\u0004\u0003\u00169\u0001\u001dAa\u0019\u0011\tyB&Q\r\t\u000b\u0003+\tYC!\u0010\u0003H\te\u0003B\u0002,\u000f\u0001\b\u0011I\u0007\u0005\u0003?1\n-\u0004#\u0003B\u0011g\nu\"1\nB/\u000319(/\u001b;f%\u0016\u0004H.Y2f)\t\u0011\t\b\u0005\u0003\u0003t\teTB\u0001B;\u0015\r\u00119hR\u0001\u0005Y\u0006tw-\u0003\u0003\u0003|\tU$AB(cU\u0016\u001cG\u000f
  #12 = Utf8               shapeless/PolyDefns$Case
  #13 = Class              #12            // shapeless/PolyDefns$Case
  #14 = Utf8               shapeless/PolyDefns
  #15 = Class              #14            // shapeless/PolyDefns
  #16 = Utf8               Case
  #17 = Utf8               deriveCCons
  #18 = Utf8               (Lshapeless/Lazy;Lshapeless/Lazy;)Lshapeless/DataT;
  #19 = Utf8               <P:Ljava/lang/Object;H:Ljava/lang/Object;T::Lshapeless/Coproduct;OutH:Ljava/lang/Object;OutT::Lshapeless/Coproduct;>(Lshapeless/Lazy<Lshapeless/PolyDefns$Case<TP;Lshapeless/$colon$colon<TH;Lshapeless/HNil;>;>;>;Lshapeless/Lazy<Lshapeless/DataT<TP;TT;>;>;)Lshapeless/DataT<TP;Lshapeless/$colon$plus$colon<TH;TT;>;>;
  #20 = Utf8               ch
  #21 = Utf8               dtt
  #22 = Utf8               shapeless/DataT$
  #23 = Class              #22            // shapeless/DataT$
  #24 = Utf8               MODULE$
  #25 = Utf8               Lshapeless/DataT$;
  #26 = NameAndType        #24:#25        // MODULE$:Lshapeless/DataT$;
  #27 = Fieldref           #23.#26        // shapeless/DataT$.MODULE$:Lshapeless/DataT$;
  #28 = NameAndType        #17:#18        // deriveCCons:(Lshapeless/Lazy;Lshapeless/Lazy;)Lshapeless/DataT;
  #29 = Methodref          #23.#28        // shapeless/DataT$.deriveCCons:(Lshapeless/Lazy;Lshapeless/Lazy;)Lshapeless/DataT;
  #30 = Utf8               deriveCNil
  #31 = Utf8               ()Lshapeless/DataT;
  #32 = Utf8               <P:Ljava/lang/Object;>()Lshapeless/DataT<TP;Lshapeless/CNil;>;
  #33 = NameAndType        #30:#31        // deriveCNil:()Lshapeless/DataT;
  #34 = Methodref          #23.#33        // shapeless/DataT$.deriveCNil:()Lshapeless/DataT;
  #35 = Utf8               deriveHCons
  #36 = Utf8               <P:Ljava/lang/Object;H:Ljava/lang/Object;T::Lshapeless/HList;OutH:Ljava/lang/Object;OutT::Lshapeless/HList;>(Lshapeless/Lazy<Lshapeless/PolyDefns$Case<TP;Lshapeless/$colon$colon<TH;Lshapeless/HNil;>;>;>;Lshapeless/Lazy<Lshapeless/DataT<TP;TT;>;>;)Lshapeless/DataT<TP;Lshapeless/$colon$colon<TH;TT;>;>;
  #37 = NameAndType        #35:#18        // deriveHCons:(Lshapeless/Lazy;Lshapeless/Lazy;)Lshapeless/DataT;
  #38 = Methodref          #23.#37        // shapeless/DataT$.deriveHCons:(Lshapeless/Lazy;Lshapeless/Lazy;)Lshapeless/DataT;
  #39 = Utf8               deriveHNil
  #40 = Utf8               <P:Ljava/lang/Object;>()Lshapeless/DataT<TP;Lshapeless/HNil;>;
  #41 = NameAndType        #39:#31        // deriveHNil:()Lshapeless/DataT;
  #42 = Methodref          #23.#41        // shapeless/DataT$.deriveHNil:()Lshapeless/DataT;
  #43 = Utf8               genMapDataT
  #44 = Utf8               (Lscala/$less$colon$less;Lshapeless/Lazy;Lscala/collection/Factory;)Lshapeless/DataT;
  #45 = Utf8               <F::Lshapeless/Poly;M:Ljava/lang/Object;K:Ljava/lang/Object;V:Ljava/lang/Object;U:Ljava/lang/Object;>(Lscala/$less$colon$less<TM;Lscala/collection/Map<TK;TV;>;>;Lshapeless/Lazy<Lshapeless/PolyDefns$Case<TF;Lshapeless/$colon$colon<TV;Lshapeless/HNil;>;>;>;Lscala/collection/Factory<Lscala/Tuple2<TK;TU;>;TM;>;)Lshapeless/DataT<TF;TM;>;
  #46 = Utf8               ev
  #47 = Utf8               fv
  #48 = Utf8               cbf
  #49 = NameAndType        #43:#44        // genMapDataT:(Lscala/$less$colon$less;Lshapeless/Lazy;Lscala/collection/Factory;)Lshapeless/DataT;
  #50 = Methodref          #23.#49        // shapeless/DataT$.genMapDataT:(Lscala/$less$colon$less;Lshapeless/Lazy;Lscala/collection/Factory;)Lshapeless/DataT;
  #51 = Utf8               genTraversableDataT
  #52 = Utf8               (Lshapeless/Lazy;Lscala/collection/Factory;)Lshapeless/DataT;
  #53 = Utf8               <F::Lshapeless/Poly;CC::Lscala/collection/Iterable<Ljava/lang/Object;>;T:Ljava/lang/Object;U:Ljava/lang/Object;>(Lshapeless/Lazy<Lshapeless/PolyDefns$Case<TF;Lshapeless/$colon$colon<TT;Lshapeless/HNil;>;>;>;Lscala/collection/Factory<TU;TCC;>;)Lshapeless/DataT<TF;TCC;>;
  #54 = Utf8               ft
  #55 = NameAndType        #51:#52        // genTraversableDataT:(Lshapeless/Lazy;Lscala/collection/Factory;)Lshapeless/DataT;
  #56 = Methodref          #23.#55        // shapeless/DataT$.genTraversableDataT:(Lshapeless/Lazy;Lscala/collection/Factory;)Lshapeless/DataT;
  #57 = Utf8               listDataT
  #58 = Utf8               (Lshapeless/Lazy;)Lshapeless/DataT;
  #59 = Utf8               <F::Lshapeless/Poly;T:Ljava/lang/Object;U:Ljava/lang/Object;>(Lshapeless/Lazy<Lshapeless/PolyDefns$Case<TF;Lshapeless/$colon$colon<TT;Lshapeless/HNil;>;>;>;)Lshapeless/DataT<TF;Lscala/collection/immutable/List<TT;>;>;
  #60 = NameAndType        #57:#58        // listDataT:(Lshapeless/Lazy;)Lshapeless/DataT;
  #61 = Methodref          #23.#60        // shapeless/DataT$.listDataT:(Lshapeless/Lazy;)Lshapeless/DataT;
  #62 = Utf8               apply
  #63 = Utf8               <P:Ljava/lang/Object;T:Ljava/lang/Object;>(Lshapeless/Lazy<Lshapeless/DataT<TP;TT;>;>;)Lshapeless/DataT<TP;TT;>;
  #64 = NameAndType        #62:#58        // apply:(Lshapeless/Lazy;)Lshapeless/DataT;
  #65 = Methodref          #23.#64        // shapeless/DataT$.apply:(Lshapeless/Lazy;)Lshapeless/DataT;
  #66 = Utf8               deriveInstance
  #67 = Utf8               (Lshapeless/Generic;Lshapeless/Lazy;)Lshapeless/DataT;
  #68 = Utf8               <P:Ljava/lang/Object;F:Ljava/lang/Object;G:Ljava/lang/Object;>(Lshapeless/Generic<TF;>;Lshapeless/Lazy<Lshapeless/DataT<TP;TG;>;>;)Lshapeless/DataT<TP;TF;>;
  #69 = Utf8               gen
  #70 = Utf8               dtg
  #71 = NameAndType        #66:#67        // deriveInstance:(Lshapeless/Generic;Lshapeless/Lazy;)Lshapeless/DataT;
  #72 = Methodref          #23.#71        // shapeless/DataT$.deriveInstance:(Lshapeless/Generic;Lshapeless/Lazy;)Lshapeless/DataT;
  #73 = Utf8               dfltDataT
  #74 = Utf8               <F:Ljava/lang/Object;T:Ljava/lang/Object;>()Lshapeless/DataT<TF;TT;>;
  #75 = NameAndType        #73:#31        // dfltDataT:()Lshapeless/DataT;
  #76 = Methodref          #23.#75        // shapeless/DataT$.dfltDataT:()Lshapeless/DataT;
  #77 = Utf8               gmapT
  #78 = Utf8               (Ljava/lang/Object;)Ljava/lang/Object;
  #79 = Utf8               (TT;)Ljava/lang/Object;
  #80 = Utf8               t
  #81 = Utf8               Code
  #82 = Utf8               Signature
  #83 = Utf8               MethodParameters
  #84 = Utf8               Deprecated
  #85 = Utf8               InnerClasses
  #86 = Utf8               SourceFile
  #87 = Utf8               RuntimeVisibleAnnotations
  #88 = Utf8               ScalaInlineInfo
  #89 = Utf8               ScalaSig
{
  public static <P extends java.lang.Object, H extends java.lang.Object, T extends shapeless.Coproduct, OutH extends java.lang.Object, OutT extends shapeless.Coproduct> shapeless.DataT<P, shapeless.$colon$plus$colon<H, T>> deriveCCons(shapeless.Lazy<shapeless.PolyDefns$Case<P, shapeless.$colon$colon<H, shapeless.HNil>>>, shapeless.Lazy<shapeless.DataT<P, T>>);
    descriptor: (Lshapeless/Lazy;Lshapeless/Lazy;)Lshapeless/DataT;
    flags: (0x0009) ACC_PUBLIC, ACC_STATIC
    Code:
      stack=3, locals=2, args_size=2
         0: getstatic     #27                 // Field shapeless/DataT$.MODULE$:Lshapeless/DataT$;
         3: aload_0
         4: aload_1
         5: invokevirtual #29                 // Method shapeless/DataT$.deriveCCons:(Lshapeless/Lazy;Lshapeless/Lazy;)Lshapeless/DataT;
         8: areturn
    Signature: #19                          // <P:Ljava/lang/Object;H:Ljava/lang/Object;T::Lshapeless/Coproduct;OutH:Ljava/lang/Object;OutT::Lshapeless/Coproduct;>(Lshapeless/Lazy<Lshapeless/PolyDefns$Case<TP;Lshapeless/$colon$colon<TH;Lshapeless/HNil;>;>;>;Lshapeless/Lazy<Lshapeless/DataT<TP;TT;>;>;)Lshapeless/DataT<TP;Lshapeless/$colon$plus$colon<TH;TT;>;>;
    MethodParameters:
      Name                           Flags
      ch                             final
      dtt                            final

  public static <P extends java.lang.Object> shapeless.DataT<P, shapeless.CNil> deriveCNil();
    descriptor: ()Lshapeless/DataT;
    flags: (0x0009) ACC_PUBLIC, ACC_STATIC
    Code:
      stack=1, locals=0, args_size=0
         0: getstatic     #27                 // Field shapeless/DataT$.MODULE$:Lshapeless/DataT$;
         3: invokevirtual #34                 // Method shapeless/DataT$.deriveCNil:()Lshapeless/DataT;
         6: areturn
    Signature: #32                          // <P:Ljava/lang/Object;>()Lshapeless/DataT<TP;Lshapeless/CNil;>;

  public static <P extends java.lang.Object, H extends java.lang.Object, T extends shapeless.HList, OutH extends java.lang.Object, OutT extends shapeless.HList> shapeless.DataT<P, shapeless.$colon$colon<H, T>> deriveHCons(shapeless.Lazy<shapeless.PolyDefns$Case<P, shapeless.$colon$colon<H, shapeless.HNil>>>, shapeless.Lazy<shapeless.DataT<P, T>>);
    descriptor: (Lshapeless/Lazy;Lshapeless/Lazy;)Lshapeless/DataT;
    flags: (0x0009) ACC_PUBLIC, ACC_STATIC
    Code:
      stack=3, locals=2, args_size=2
         0: getstatic     #27                 // Field shapeless/DataT$.MODULE$:Lshapeless/DataT$;
         3: aload_0
         4: aload_1
         5: invokevirtual #38                 // Method shapeless/DataT$.deriveHCons:(Lshapeless/Lazy;Lshapeless/Lazy;)Lshapeless/DataT;
         8: areturn
    Signature: #36                          // <P:Ljava/lang/Object;H:Ljava/lang/Object;T::Lshapeless/HList;OutH:Ljava/lang/Object;OutT::Lshapeless/HList;>(Lshapeless/Lazy<Lshapeless/PolyDefns$Case<TP;Lshapeless/$colon$colon<TH;Lshapeless/HNil;>;>;>;Lshapeless/Lazy<Lshapeless/DataT<TP;TT;>;>;)Lshapeless/DataT<TP;Lshapeless/$colon$colon<TH;TT;>;>;
    MethodParameters:
      Name                           Flags
      ch                             final
      dtt                            final

  public static <P extends java.lang.Object> shapeless.DataT<P, shapeless.HNil> deriveHNil();
    descriptor: ()Lshapeless/DataT;
    flags: (0x0009) ACC_PUBLIC, ACC_STATIC
    Code:
      stack=1, locals=0, args_size=0
         0: getstatic     #27                 // Field shapeless/DataT$.MODULE$:Lshapeless/DataT$;
         3: invokevirtual #42                 // Method shapeless/DataT$.deriveHNil:()Lshapeless/DataT;
         6: areturn
    Signature: #40                          // <P:Ljava/lang/Object;>()Lshapeless/DataT<TP;Lshapeless/HNil;>;

  public static <F extends shapeless.Poly, M extends java.lang.Object, K extends java.lang.Object, V extends java.lang.Object, U extends java.lang.Object> shapeless.DataT<F, M> genMapDataT(scala.$less$colon$less<M, scala.collection.Map<K, V>>, shapeless.Lazy<shapeless.PolyDefns$Case<F, shapeless.$colon$colon<V, shapeless.HNil>>>, scala.collection.Factory<scala.Tuple2<K, U>, M>);
    descriptor: (Lscala/$less$colon$less;Lshapeless/Lazy;Lscala/collection/Factory;)Lshapeless/DataT;
    flags: (0x0009) ACC_PUBLIC, ACC_STATIC
    Code:
      stack=4, locals=3, args_size=3
         0: getstatic     #27                 // Field shapeless/DataT$.MODULE$:Lshapeless/DataT$;
         3: aload_0
         4: aload_1
         5: aload_2
         6: invokevirtual #50                 // Method shapeless/DataT$.genMapDataT:(Lscala/$less$colon$less;Lshapeless/Lazy;Lscala/collection/Factory;)Lshapeless/DataT;
         9: areturn
    Signature: #45                          // <F::Lshapeless/Poly;M:Ljava/lang/Object;K:Ljava/lang/Object;V:Ljava/lang/Object;U:Ljava/lang/Object;>(Lscala/$less$colon$less<TM;Lscala/collection/Map<TK;TV;>;>;Lshapeless/Lazy<Lshapeless/PolyDefns$Case<TF;Lshapeless/$colon$colon<TV;Lshapeless/HNil;>;>;>;Lscala/collection/Factory<Lscala/Tuple2<TK;TU;>;TM;>;)Lshapeless/DataT<TF;TM;>;
    MethodParameters:
      Name                           Flags
      ev                             final
      fv                             final
      cbf                            final

  public static <F extends shapeless.Poly, CC extends scala.collection.Iterable<java.lang.Object>, T extends java.lang.Object, U extends java.lang.Object> shapeless.DataT<F, CC> genTraversableDataT(shapeless.Lazy<shapeless.PolyDefns$Case<F, shapeless.$colon$colon<T, shapeless.HNil>>>, scala.collection.Factory<U, CC>);
    descriptor: (Lshapeless/Lazy;Lscala/collection/Factory;)Lshapeless/DataT;
    flags: (0x0009) ACC_PUBLIC, ACC_STATIC
    Code:
      stack=3, locals=2, args_size=2
         0: getstatic     #27                 // Field shapeless/DataT$.MODULE$:Lshapeless/DataT$;
         3: aload_0
         4: aload_1
         5: invokevirtual #56                 // Method shapeless/DataT$.genTraversableDataT:(Lshapeless/Lazy;Lscala/collection/Factory;)Lshapeless/DataT;
         8: areturn
    Signature: #53                          // <F::Lshapeless/Poly;CC::Lscala/collection/Iterable<Ljava/lang/Object;>;T:Ljava/lang/Object;U:Ljava/lang/Object;>(Lshapeless/Lazy<Lshapeless/PolyDefns$Case<TF;Lshapeless/$colon$colon<TT;Lshapeless/HNil;>;>;>;Lscala/collection/Factory<TU;TCC;>;)Lshapeless/DataT<TF;TCC;>;
    MethodParameters:
      Name                           Flags
      ft                             final
      cbf                            final

  public static <F extends shapeless.Poly, T extends java.lang.Object, U extends java.lang.Object> shapeless.DataT<F, scala.collection.immutable.List<T>> listDataT(shapeless.Lazy<shapeless.PolyDefns$Case<F, shapeless.$colon$colon<T, shapeless.HNil>>>);
    descriptor: (Lshapeless/Lazy;)Lshapeless/DataT;
    flags: (0x0009) ACC_PUBLIC, ACC_STATIC
    Code:
      stack=2, locals=1, args_size=1
         0: getstatic     #27                 // Field shapeless/DataT$.MODULE$:Lshapeless/DataT$;
         3: aload_0
         4: invokevirtual #61                 // Method shapeless/DataT$.listDataT:(Lshapeless/Lazy;)Lshapeless/DataT;
         7: areturn
    Signature: #59                          // <F::Lshapeless/Poly;T:Ljava/lang/Object;U:Ljava/lang/Object;>(Lshapeless/Lazy<Lshapeless/PolyDefns$Case<TF;Lshapeless/$colon$colon<TT;Lshapeless/HNil;>;>;>;)Lshapeless/DataT<TF;Lscala/collection/immutable/List<TT;>;>;
    Deprecated: true
    MethodParameters:
      Name                           Flags
      ft                             final

  public static <P extends java.lang.Object, T extends java.lang.Object> shapeless.DataT<P, T> apply(shapeless.Lazy<shapeless.DataT<P, T>>);
    descriptor: (Lshapeless/Lazy;)Lshapeless/DataT;
    flags: (0x0009) ACC_PUBLIC, ACC_STATIC
    Code:
      stack=2, locals=1, args_size=1
         0: getstatic     #27                 // Field shapeless/DataT$.MODULE$:Lshapeless/DataT$;
         3: aload_0
         4: invokevirtual #65                 // Method shapeless/DataT$.apply:(Lshapeless/Lazy;)Lshapeless/DataT;
         7: areturn
    Signature: #63                          // <P:Ljava/lang/Object;T:Ljava/lang/Object;>(Lshapeless/Lazy<Lshapeless/DataT<TP;TT;>;>;)Lshapeless/DataT<TP;TT;>;
    MethodParameters:
      Name                           Flags
      dtt                            final

  public static <P extends java.lang.Object, F extends java.lang.Object, G extends java.lang.Object> shapeless.DataT<P, F> deriveInstance(shapeless.Generic<F>, shapeless.Lazy<shapeless.DataT<P, G>>);
    descriptor: (Lshapeless/Generic;Lshapeless/Lazy;)Lshapeless/DataT;
    flags: (0x0009) ACC_PUBLIC, ACC_STATIC
    Code:
      stack=3, locals=2, args_size=2
         0: getstatic     #27                 // Field shapeless/DataT$.MODULE$:Lshapeless/DataT$;
         3: aload_0
         4: aload_1
         5: invokevirtual #72                 // Method shapeless/DataT$.deriveInstance:(Lshapeless/Generic;Lshapeless/Lazy;)Lshapeless/DataT;
         8: areturn
    Signature: #68                          // <P:Ljava/lang/Object;F:Ljava/lang/Object;G:Ljava/lang/Object;>(Lshapeless/Generic<TF;>;Lshapeless/Lazy<Lshapeless/DataT<TP;TG;>;>;)Lshapeless/DataT<TP;TF;>;
    MethodParameters:
      Name                           Flags
      gen                            final
      dtg                            final

  public static <F extends java.lang.Object, T extends java.lang.Object> shapeless.DataT<F, T> dfltDataT();
    descriptor: ()Lshapeless/DataT;
    flags: (0x0009) ACC_PUBLIC, ACC_STATIC
    Code:
      stack=1, locals=0, args_size=0
         0: getstatic     #27                 // Field shapeless/DataT$.MODULE$:Lshapeless/DataT$;
         3: invokevirtual #76                 // Method shapeless/DataT$.dfltDataT:()Lshapeless/DataT;
         6: areturn
    Signature: #74                          // <F:Ljava/lang/Object;T:Ljava/lang/Object;>()Lshapeless/DataT<TF;TT;>;

  public abstract java.lang.Object gmapT(T);
    descriptor: (Ljava/lang/Object;)Ljava/lang/Object;
    flags: (0x0401) ACC_PUBLIC, ACC_ABSTRACT
    Signature: #79                          // (TT;)Ljava/lang/Object;
    MethodParameters:
      Name                           Flags
      t                              final
}
InnerClasses:
  public static abstract #16= #13 of #15; // Case=class shapeless/PolyDefns$Case of class shapeless/PolyDefns
Signature: #3                           // <F:Ljava/lang/Object;T:Ljava/lang/Object;>Ljava/lang/Object;Ljava/io/Serializable;
SourceFile: "sybclass.scala"
RuntimeVisibleAnnotations:
  0: #9(#10=s#11)
    scala.reflect.ScalaSignature(
      bytes="\u0006\u0005\tuda\u0002\t\u0012!\u0003\r\n\u0001\u0006\u0003\u0006Q\u0001\u0011\t!\u000b\u0005\u0006a\u00011\t!M\u0004\u0006yEA\t!\u0010\u0004\u0006!EA\ta\u0010\u0005\u0006\u0015\u0012!\ta\u0013\u0005\u0006\u0019\u0012!\t!\u0014\u0005\u0006a\u0011!\tA\u0017\u0005\u0006]\u0012!\ta\u001c\u0005\b\u0003\u007f!A1AA!\u0011\u001d\t\t\t\u0002C\u0002\u0003\u0007Cq!a4\u0005\t\u0007\t\t\u000eC\u0004\u0002b\u0012!\u0019!a9\t\u000f\t\rB\u0001b\u0001\u0003&!9!Q\u0007\u0003\u0005\u0004\t]\u0002\"\u0003B7\t\u0005\u0005I\u0011\u0002B8\u0005\u0015!\u0015\r^1U\u0015\u0005\u0011\u0012!C:iCB,G.Z:t\u0007\u0001)2!\u0006\u001e9\'\r\u0001a\u0003\b\t\u0003/ii\u0011\u0001\u0007\u0006\u00023\u0005)1oY1mC&\u00111\u0004\u0007\u0002\u0007\u0003:L(+\u001a4\u0011\u0005u)cB\u0001\u0010$\u001d\ty\"%D\u0001!\u0015\t\t3#\u0001\u0004=e>|GOP\u0005\u00023%\u0011A\u0005G\u0001\ba\u0006\u001c7.Y4f\u0013\t1sE\u0001\u0007TKJL\u0017\r\\5{C\ndWM\u0003\u0002%1\t\u0019q*\u001e;\u0012\u0005)j\u0003CA\f,\u0013\ta\u0003DA\u0004O_RD\u0017N\\4\u0011\u0005]q\u0013BA\u0018\u0019\u0005\r\te._\u0001\u0006O6\f\u0007\u000f\u0016\u000b\u0003eQ\u0002\"aM\u0001\u000e\u0003\u0001AQ!\u000e\u0002A\u0002Y\n\u0011\u0001\u001e\t\u0003oab\u0001\u0001B\u0003:\u0001\t\u0007\u0011FA\u0001U\t\u0015Y\u0004A1\u0001*\u0005\u00051\u0015!\u0002#bi\u0006$\u0006C\u0001 \u0005\u001b\u0005\t2\u0003\u0002\u0003\u0017\u0001\u000e\u0003\"AP!\n\u0005\t\u000b\"A\u0002#bi\u0006$\u0016\u0007\u0005\u0002E\u00136\tQI\u0003\u0002G\u000f\u0006\u0011\u0011n\u001c\u0006\u0002\u0011\u0006!!.\u0019<b\u0013\t1S)\u0001\u0004=S:LGO\u0010\u000b\u0002{\u0005)\u0011\r\u001d9msV\u0019a*\u0015+\u0015\u0005=+\u0006\u0003\u0002 \u0001!N\u0003\"aN)\u0005\u000bI3!\u0019A\u0015\u0003\u0003A\u0003\"a\u000e+\u0005\u000be2!\u0019A\u0015\t\u000bY3\u00019A,\u0002\u0007\u0011$H\u000fE\u0002?1>K!!W\t\u0003\t1\u000b\'0_\u000b\u00047\u001aDGC\u0001/m)\ti6\u000e\u0006\u0002_CB\u0011q,\u0001\b\u0003A&t!aN1\t\u000b\t<\u00019A2\u0002\t\u0011\fG/\u0019\t\u0004}a#\u0007\u0003\u0002 \u0001K\u001e\u0004\"a\u000e4\u0005\u000bm:!\u0019A\u0015\u0011\u0005]BG!B\u001d\b\u0005\u0004I\u0013B\u00016Y\u0003\u00151\u0018\r\\;f\u0011\u0015)t\u00011\u0001h\u0011\u0015iw\u00011\u0001f\u0003\u00051\u0017!\u00037jgR$\u0015\r^1U+\u0019\u0001\b0a\u0001\u0002\nQ\u0019\u0011/!\u0004\u0011\rI\u001cx/`A\u0003\u001b\u0005!\u0011B\u0001;v\u0005\r\tU\u000f_\u0005\u0003mF\u0011a\u0001R1uCR\u0003\u0004CA\u001cy\t\u0015Y\u0004B1\u0001z#\tQ#\u0010\u0005\u0002?w&\u0011A0\u0005\u0002\u0005!>d\u0017\u0010\u0005\u0003\u001e}\u0006\u0005\u0011BA@(\u0005\u0011a\u0015n\u001d;\u0011\u0007]\n\u0019\u0001B\u0003:\u0011\t\u0007\u0011\u0006\u0005\u0003\u001e}\u0006\u001d\u0001cA\u001c\u0002\n\u00111\u00111\u0002\u0005C\u0002%\u0012\u0011!\u0016\u0005\b\u0003\u001fA\u00019AA\t\u0003\t1G\u000f\u0005\u0003?1\u0006M\u0001#CA\u000b\u0003W9\u0018\u0011AA\u0004\u001d\u0011\t9\"a\t\u000f\t\u0005e\u0011Q\u0004\b\u0004}\u0005m\u0011B\u0001\u0013\u0012\u0013\u0011\ty\"!\t\u0002\tA|G.\u001f\u0006\u0003IEIA!!\n\u0002(\u0005)1)Y:fc%\u0019\u0011\u0011F\t\u0003\u000b\r\u000b7/Z:\n\u0007Q\fiC\u0003\u0003\u0002&\u0005\u001d\u0002f\u0002\u0005\u00022\u0005]\u00121\b\t\u0004/\u0005M\u0012bAA\u001b1\tQA-\u001a9sK\u000e\fG/\u001a3\"\u0005\u0005e\u0012!I*va\u0016\u00148/\u001a3fI\u0002\u0012\u0017\u0010I4f]R\u0013\u0018M^3sg\u0006\u0014G.\u001a#bi\u0006$\u0016EAA\u001f\u0003\u0015\u0011df\r\u00182\u0003M9WM\u001c+sCZ,\'o]1cY\u0016$\u0015\r^1U+)\t\u0019%!\u0013\u0002N\u0005%\u0014q\u000e\u000b\u0007\u0003\u000b\n\t(a\u001e\u0011\u0011I\u001c\u0018qIA&\u0003W\u00022aNA%\t\u0015Y\u0014B1\u0001z!\u00159\u0014QJA4\t\u001d\ty%\u0003b\u0001\u0003#\u0012!aQ\"\u0016\t\u0005M\u00131M\t\u0004U\u0005U\u0003CBA,\u0003;\n\t\'\u0004\u0002\u0002Z)\u0019\u00111\f\r\u0002\u0015\r|G\u000e\\3di&|g.\u0003\u0003\u0002`\u0005e#\u0001C%uKJ\f\'\r\\3\u0011\u0007]\n\u0019\u0007B\u0004\u0002f\u00055#\u0019A\u0015\u0003\u0003a\u00032aNA5\t\u0015I\u0014B1\u0001*!\u00159\u0014QJA7!\r9\u0014q\u000e\u0003\u0007\u0003\u0017I!\u0019A\u0015\t\u000f\u0005=\u0011\u0002q\u0001\u0002tA!a\bWA;!)\t)\"a\u000b\u0002H\u0005\u001d\u0014Q\u000e\u0005\b\u0003sJ\u00019AA>\u0003\r\u0019\'M\u001a\t\t\u0003/\ni(!\u001c\u0002l%!\u0011qPA-\u0005\u001d1\u0015m\u0019;pef\f1bZ3o\u001b\u0006\u0004H)\u0019;b)Va\u0011QQAF\u0003\u001f\u000bi*a)\u0002,RA\u0011qQAW\u0003{\u000b)\r\u0005\u0005sg\u0006%\u0015QRAT!\r9\u00141\u0012\u0003\u0006w)\u0011\r!\u001f\t\bo\u0005=\u00151TAQ\t\u001d\t\tJ\u0003b\u0001\u0003\'\u0013\u0011!T\u000b\u0006S\u0005U\u0015q\u0013\u0003\b\u0003K\nyI1\u0001*\t\u001d\tI*a$C\u0002%\u0012\u0011!\u0017\t\u0004o\u0005uEABAP\u0015\t\u0007\u0011FA\u0001L!\r9\u00141\u0015\u0003\u0007\u0003KS!\u0019A\u0015\u0003\u0003Y\u0003raNAH\u00037\u000bI\u000bE\u00028\u0003W#a!a\u0003\u000b\u0005\u0004I\u0003bBAX\u0015\u0001\u000f\u0011\u0011W\u0001\u0003KZ\u0004raFAZ\u0003\u001b\u000b9,C\u0002\u00026b\u0011\u0001\u0003\n7fgN$3m\u001c7p]\u0012bWm]:\u0011\u0011\u0005]\u0013\u0011XAN\u0003CKA!a/\u0002Z\t\u0019Q*\u00199\t\u000f\u0005}&\u0002q\u0001\u0002B\u0006\u0011aM\u001e\t\u0005}a\u000b\u0019\r\u0005\u0006\u0002\u0016\u0005-\u0012\u0011RAQ\u0003SCq!!\u001f\u000b\u0001\b\t9\r\u0005\u0005\u0002X\u0005u\u0014\u0011ZAT!\u001d9\u00121ZAN\u0003SK1!!4\u0019\u0005\u0019!V\u000f\u001d7fe\u0005QA-\u001a:jm\u0016De*\u001b7\u0016\t\u0005M\u0017\u0011\\\u000b\u0003\u0003+\u0004\u0002B]:\u0002X\u0006m\u00171\u001c\t\u0004o\u0005eG!\u0002*\f\u0005\u0004I\u0003c\u0001 \u0002^&\u0019\u0011q\\\t\u0003\t!s\u0015\u000e\\\u0001\fI\u0016\u0014\u0018N^3I\u0007>t7/\u0006\u0007\u0002f\u0006-\u0018Q_A~\u0005\u0013\u0011y\u0001\u0006\u0004\u0002h\nM!1\u0004\t\teN\fI/!<\u0003\u0006A\u0019q\'a;\u0005\u000bIc!\u0019A\u0015\u0011\u000fy\ny/a=\u0002z&\u0019\u0011\u0011_\t\u0003\u0019\u0011\u001aw\u000e\\8oI\r|Gn\u001c8\u0011\u0007]\n)\u0010\u0002\u0004\u0002x2\u0011\r!\u000b\u0002\u0002\u0011B\u0019q\'a?\u0005\reb!\u0019AA\u007f#\rQ\u0013q \t\u0004}\t\u0005\u0011b\u0001B\u0002#\t)\u0001\nT5tiB9a(a<\u0003\b\t5\u0001cA\u001c\u0003\n\u00111!1\u0002\u0007C\u0002%\u0012AaT;u\u0011B\u0019qGa\u0004\u0005\u000f\tEAB1\u0001\u0002~\n!q*\u001e;U\u0011\u001d\u0011)\u0002\u0004a\u0002\u0005/\t!a\u00195\u0011\tyB&\u0011\u0004\t\u000b\u0003+\tY#!;\u0002t\n\u001d\u0001B\u0002,\r\u0001\b\u0011i\u0002\u0005\u0003?1\n}\u0001#\u0003B\u0011g\u0006%\u0018\u0011 B\u0007\u001d\tq4!\u0001\u0006eKJLg/Z\"OS2,BAa\n\u0003.U\u0011!\u0011\u0006\t\teN\u0014YCa\f\u00030A\u0019qG!\f\u0005\u000bIk!\u0019A\u0015\u0011\u0007y\u0012\t$C\u0002\u00034E\u0011Aa\u0011(jY\u0006YA-\u001a:jm\u0016\u001c5i\u001c8t+1\u0011IDa\u0010\u0003J\t5#1\fB0)\u0019\u0011YD!\u0019\u0003hAA!o\u001dB\u001f\u0005\u0003\u00129\u0006E\u00028\u0005\u007f!QA\u0015\bC\u0002%\u0002rA\u0010B\"\u0005\u000f\u0012Y%C\u0002\u0003FE\u0011\u0011\u0003J2pY>tG\u0005\u001d7vg\u0012\u001aw\u000e\\8o!\r9$\u0011\n\u0003\u0007\u0003ot!\u0019A\u0015\u0011\u0007]\u0012i\u0005\u0002\u0004:\u001d\t\u0007!qJ\t\u0004U\tE\u0003c\u0001 \u0003T%\u0019!QK\t\u0003\u0013\r{\u0007O]8ek\u000e$\bc\u0002 \u0003D\te#Q\f\t\u0004o\tmCA\u0002B\u0006\u001d\t\u0007\u0011\u0006E\u00028\u0005?\"qA!\u0005\u000f\u0005\u0004\u0011y\u0005C\u0004\u0003\u00169\u0001\u001dAa\u0019\u0011\tyB&Q\r\t\u000b\u0003+\tYC!\u0010\u0003H\te\u0003B\u0002,\u000f\u0001\b\u0011I\u0007\u0005\u0003?1\n-\u0004#\u0003B\u0011g\nu\"1\nB/\u000319(/\u001b;f%\u0016\u0004H.Y2f)\t\u0011\t\b\u0005\u0003\u0003t\teTB\u0001B;\u0015\r\u00119hR\u0001\u0005Y\u0006tw-\u0003\u0003\u0003|\tU$AB(cU\u0016\u001cG\u000f"
    )
  ScalaInlineInfo: length = 0x9 (unknown attribute)
   01 00 00 01 00 4D 00 4E 00
  ScalaSig: length = 0x3 (unknown attribute)
   05 02 00
