Classfile /Users/mw/Projects/slang-braindump/.jar/jar8/assemble/slang-braindump/assemble/content/shapeless/Default$AsRecord$Helper$.class
  Last modified May 29, 2022; size 2432 bytes
  SHA-256 checksum 03471630fa02a8a661e026b432a3386f02cdbfc3a67bdab8743ba442dd0bb581
  Compiled from "default.scala"
public class shapeless.Default$AsRecord$Helper$ implements java.io.Serializable
  minor version: 0
  major version: 52
  flags: (0x0021) ACC_PUBLIC, ACC_SUPER
  this_class: #2                          // shapeless/Default$AsRecord$Helper$
  super_class: #4                         // java/lang/Object
  interfaces: 1, fields: 1, methods: 7, attributes: 4
Constant pool:
   #1 = Utf8               shapeless/Default$AsRecord$Helper$
   #2 = Class              #1             // shapeless/Default$AsRecord$Helper$
   #3 = Utf8               java/lang/Object
   #4 = Class              #3             // java/lang/Object
   #5 = Utf8               java/io/Serializable
   #6 = Class              #5             // java/io/Serializable
   #7 = Utf8               default.scala
   #8 = Utf8               shapeless/Default$AsRecord$
   #9 = Class              #8             // shapeless/Default$AsRecord$
  #10 = Utf8               shapeless/Default
  #11 = Class              #10            // shapeless/Default
  #12 = Utf8               AsRecord$
  #13 = Utf8               shapeless/Default$AsRecord$Helper
  #14 = Class              #13            // shapeless/Default$AsRecord$Helper
  #15 = Utf8               Helper
  #16 = Utf8               Helper$
  #17 = Utf8               shapeless/Default$AsRecord$Helper$$anon$2
  #18 = Class              #17            // shapeless/Default$AsRecord$Helper$$anon$2
  #19 = Utf8               shapeless/Default$AsRecord$Helper$$anon$3
  #20 = Class              #19            // shapeless/Default$AsRecord$Helper$$anon$3
  #21 = Utf8               shapeless/Default$AsRecord$Helper$$anon$4
  #22 = Class              #21            // shapeless/Default$AsRecord$Helper$$anon$4
  #23 = Utf8               MODULE$
  #24 = Utf8               Lshapeless/Default$AsRecord$Helper$;
  #25 = Utf8               <clinit>
  #26 = Utf8               ()V
  #27 = Utf8               <init>
  #28 = NameAndType        #27:#26        // "<init>":()V
  #29 = Methodref          #2.#28         // shapeless/Default$AsRecord$Helper$."<init>":()V
  #30 = NameAndType        #23:#24        // MODULE$:Lshapeless/Default$AsRecord$Helper$;
  #31 = Fieldref           #2.#30         // shapeless/Default$AsRecord$Helper$.MODULE$:Lshapeless/Default$AsRecord$Helper$;
  #32 = Utf8               apply
  #33 = Utf8               (Lshapeless/Default$AsRecord$Helper;)Lshapeless/Default$AsRecord$Helper;
  #34 = Utf8               <L::Lshapeless/HList;Labels::Lshapeless/HList;>(Lshapeless/Default$AsRecord$Helper<TL;TLabels;>;)Lshapeless/Default$AsRecord$Helper<TL;TLabels;>;
  #35 = Utf8               helper
  #36 = Utf8               this
  #37 = Utf8               Lshapeless/Default$AsRecord$Helper;
  #38 = Utf8               hnilHelper
  #39 = Utf8               ()Lshapeless/Default$AsRecord$Helper;
  #40 = Utf8               ()Lshapeless/Default$AsRecord$Helper<Lshapeless/HNil;Lshapeless/HNil;>;
  #41 = Methodref          #18.#28        // shapeless/Default$AsRecord$Helper$$anon$2."<init>":()V
  #42 = Utf8               hconsSomeHelper
  #43 = Utf8               <K:Lscala/Symbol;H:Ljava/lang/Object;T::Lshapeless/HList;LabT::Lshapeless/HList;OutT::Lshapeless/HList;>(Lshapeless/Default$AsRecord$Helper<TT;TLabT;>;)Lshapeless/Default$AsRecord$Helper<Lshapeless/$colon$colon<Lscala/Some<TH;>;TT;>;Lshapeless/$colon$colon<TK;TLabT;>;>;
  #44 = Utf8               tailHelper
  #45 = Utf8               (Lshapeless/Default$AsRecord$Helper;)V
  #46 = NameAndType        #27:#45        // "<init>":(Lshapeless/Default$AsRecord$Helper;)V
  #47 = Methodref          #20.#46        // shapeless/Default$AsRecord$Helper$$anon$3."<init>":(Lshapeless/Default$AsRecord$Helper;)V
  #48 = Utf8               hconsNoneHelper
  #49 = Utf8               <K:Lscala/Symbol;T::Lshapeless/HList;LabT::Lshapeless/HList;OutT::Lshapeless/HList;>(Lshapeless/Default$AsRecord$Helper<TT;TLabT;>;)Lshapeless/Default$AsRecord$Helper<Lshapeless/$colon$colon<Lscala/None$;TT;>;Lshapeless/$colon$colon<TK;TLabT;>;>;
  #50 = Methodref          #22.#46        // shapeless/Default$AsRecord$Helper$$anon$4."<init>":(Lshapeless/Default$AsRecord$Helper;)V
  #51 = Utf8               writeReplace
  #52 = Utf8               ()Ljava/lang/Object;
  #53 = Utf8               scala/runtime/ModuleSerializationProxy
  #54 = Class              #53            // scala/runtime/ModuleSerializationProxy
  #55 = Utf8               (Ljava/lang/Class;)V
  #56 = NameAndType        #27:#55        // "<init>":(Ljava/lang/Class;)V
  #57 = Methodref          #54.#56        // scala/runtime/ModuleSerializationProxy."<init>":(Ljava/lang/Class;)V
  #58 = Methodref          #4.#28         // java/lang/Object."<init>":()V
  #59 = Utf8               Code
  #60 = Utf8               LineNumberTable
  #61 = Utf8               LocalVariableTable
  #62 = Utf8               Signature
  #63 = Utf8               MethodParameters
  #64 = Utf8               InnerClasses
  #65 = Utf8               SourceFile
  #66 = Utf8               ScalaInlineInfo
  #67 = Utf8               Scala
{
  public static final shapeless.Default$AsRecord$Helper$ MODULE$;
    descriptor: Lshapeless/Default$AsRecord$Helper$;
    flags: (0x0019) ACC_PUBLIC, ACC_STATIC, ACC_FINAL

  public static {};
    descriptor: ()V
    flags: (0x0009) ACC_PUBLIC, ACC_STATIC
    Code:
      stack=2, locals=0, args_size=0
         0: new           #2                  // class shapeless/Default$AsRecord$Helper$
         3: dup
         4: invokespecial #29                 // Method "<init>":()V
         7: putstatic     #31                 // Field MODULE$:Lshapeless/Default$AsRecord$Helper$;
        10: return
      LineNumberTable:
        line 87: 0

  public <L extends shapeless.HList, Labels extends shapeless.HList> shapeless.Default$AsRecord$Helper<L, Labels> apply(shapeless.Default$AsRecord$Helper<L, Labels>);
    descriptor: (Lshapeless/Default$AsRecord$Helper;)Lshapeless/Default$AsRecord$Helper;
    flags: (0x0001) ACC_PUBLIC
    Code:
      stack=1, locals=2, args_size=2
         0: aload_1
         1: areturn
      LineNumberTable:
        line 88: 0
      LocalVariableTable:
        Start  Length  Slot  Name   Signature
            0       2     0  this   Lshapeless/Default$AsRecord$Helper$;
            0       2     1 helper   Lshapeless/Default$AsRecord$Helper;
    Signature: #34                          // <L::Lshapeless/HList;Labels::Lshapeless/HList;>(Lshapeless/Default$AsRecord$Helper<TL;TLabels;>;)Lshapeless/Default$AsRecord$Helper<TL;TLabels;>;
    MethodParameters:
      Name                           Flags
      helper                         final

  public shapeless.Default$AsRecord$Helper<shapeless.HNil, shapeless.HNil> hnilHelper();
    descriptor: ()Lshapeless/Default$AsRecord$Helper;
    flags: (0x0001) ACC_PUBLIC
    Code:
      stack=2, locals=1, args_size=1
         0: new           #18                 // class shapeless/Default$AsRecord$Helper$$anon$2
         3: dup
         4: invokespecial #41                 // Method shapeless/Default$AsRecord$Helper$$anon$2."<init>":()V
         7: areturn
      LineNumberTable:
        line 93: 0
      LocalVariableTable:
        Start  Length  Slot  Name   Signature
            0       8     0  this   Lshapeless/Default$AsRecord$Helper$;
    Signature: #40                          // ()Lshapeless/Default$AsRecord$Helper<Lshapeless/HNil;Lshapeless/HNil;>;

  public <K extends scala.Symbol, H extends java.lang.Object, T extends shapeless.HList, LabT extends shapeless.HList, OutT extends shapeless.HList> shapeless.Default$AsRecord$Helper<shapeless.$colon$colon<scala.Some<H>, T>, shapeless.$colon$colon<K, LabT>> hconsSomeHelper(shapeless.Default$AsRecord$Helper<T, LabT>);
    descriptor: (Lshapeless/Default$AsRecord$Helper;)Lshapeless/Default$AsRecord$Helper;
    flags: (0x0001) ACC_PUBLIC
    Code:
      stack=3, locals=2, args_size=2
         0: new           #20                 // class shapeless/Default$AsRecord$Helper$$anon$3
         3: dup
         4: aload_1
         5: invokespecial #47                 // Method shapeless/Default$AsRecord$Helper$$anon$3."<init>":(Lshapeless/Default$AsRecord$Helper;)V
         8: areturn
      LineNumberTable:
        line 102: 0
      LocalVariableTable:
        Start  Length  Slot  Name   Signature
            0       9     0  this   Lshapeless/Default$AsRecord$Helper$;
            0       9     1 tailHelper   Lshapeless/Default$AsRecord$Helper;
    Signature: #43                          // <K:Lscala/Symbol;H:Ljava/lang/Object;T::Lshapeless/HList;LabT::Lshapeless/HList;OutT::Lshapeless/HList;>(Lshapeless/Default$AsRecord$Helper<TT;TLabT;>;)Lshapeless/Default$AsRecord$Helper<Lshapeless/$colon$colon<Lscala/Some<TH;>;TT;>;Lshapeless/$colon$colon<TK;TLabT;>;>;
    MethodParameters:
      Name                           Flags
      tailHelper                     final

  public <K extends scala.Symbol, T extends shapeless.HList, LabT extends shapeless.HList, OutT extends shapeless.HList> shapeless.Default$AsRecord$Helper<shapeless.$colon$colon<scala.None$, T>, shapeless.$colon$colon<K, LabT>> hconsNoneHelper(shapeless.Default$AsRecord$Helper<T, LabT>);
    descriptor: (Lshapeless/Default$AsRecord$Helper;)Lshapeless/Default$AsRecord$Helper;
    flags: (0x0001) ACC_PUBLIC
    Code:
      stack=3, locals=2, args_size=2
         0: new           #22                 // class shapeless/Default$AsRecord$Helper$$anon$4
         3: dup
         4: aload_1
         5: invokespecial #50                 // Method shapeless/Default$AsRecord$Helper$$anon$4."<init>":(Lshapeless/Default$AsRecord$Helper;)V
         8: areturn
      LineNumberTable:
        line 111: 0
      LocalVariableTable:
        Start  Length  Slot  Name   Signature
            0       9     0  this   Lshapeless/Default$AsRecord$Helper$;
            0       9     1 tailHelper   Lshapeless/Default$AsRecord$Helper;
    Signature: #49                          // <K:Lscala/Symbol;T::Lshapeless/HList;LabT::Lshapeless/HList;OutT::Lshapeless/HList;>(Lshapeless/Default$AsRecord$Helper<TT;TLabT;>;)Lshapeless/Default$AsRecord$Helper<Lshapeless/$colon$colon<Lscala/None$;TT;>;Lshapeless/$colon$colon<TK;TLabT;>;>;
    MethodParameters:
      Name                           Flags
      tailHelper                     final

  private java.lang.Object writeReplace();
    descriptor: ()Ljava/lang/Object;
    flags: (0x0002) ACC_PRIVATE
    Code:
      stack=3, locals=1, args_size=1
         0: new           #54                 // class scala/runtime/ModuleSerializationProxy
         3: dup
         4: ldc           #2                  // class shapeless/Default$AsRecord$Helper$
         6: invokespecial #57                 // Method scala/runtime/ModuleSerializationProxy."<init>":(Ljava/lang/Class;)V
         9: areturn
      LineNumberTable:
        line 87: 0
      LocalVariableTable:
        Start  Length  Slot  Name   Signature
            0      10     0  this   Lshapeless/Default$AsRecord$Helper$;

  public shapeless.Default$AsRecord$Helper$();
    descriptor: ()V
    flags: (0x0001) ACC_PUBLIC
    Code:
      stack=1, locals=1, args_size=1
         0: aload_0
         1: invokespecial #58                 // Method java/lang/Object."<init>":()V
         4: return
      LineNumberTable:
        line 117: 0
        line 87: 4
      LocalVariableTable:
        Start  Length  Slot  Name   Signature
            0       5     0  this   Lshapeless/Default$AsRecord$Helper$;
}
InnerClasses:
  public static #12= #9 of #11;           // AsRecord$=class shapeless/Default$AsRecord$ of class shapeless/Default
  public static #15= #14 of #9;           // Helper=class shapeless/Default$AsRecord$Helper of class shapeless/Default$AsRecord$
  public static #16= #2 of #9;            // Helper$=class shapeless/Default$AsRecord$Helper$ of class shapeless/Default$AsRecord$
  public final #18;                       // class shapeless/Default$AsRecord$Helper$$anon$2
  public final #20;                       // class shapeless/Default$AsRecord$Helper$$anon$3
  public final #22;                       // class shapeless/Default$AsRecord$Helper$$anon$4
SourceFile: "default.scala"
  ScalaInlineInfo: length = 0x22 (unknown attribute)
   01 01 00 06 00 1B 00 1A 01 00 20 00 21 01 00 30
   00 21 01 00 2A 00 21 01 00 26 00 27 01 00 33 00
   34 01
  Scala: length = 0x0 (unknown attribute)

