Classfile /Users/mw/Projects/slang-braindump/.jar/jar8/assemble/slang-braindump/assemble/content/shapeless/Default$AsOptions$Helper$$anon$6.class
  Last modified May 29, 2022; size 1211 bytes
  SHA-256 checksum 00597d2abbf9bd735760fd426119a7f9995ee03c0beeaa08b91f76cc0bcbd2b4
  Compiled from "default.scala"
public final class shapeless.Default$AsOptions$Helper$$anon$6 extends java.lang.Object implements shapeless.Default$AsOptions$Helper<shapeless.HNil, shapeless.HNil>
  minor version: 0
  major version: 52
  flags: (0x0031) ACC_PUBLIC, ACC_FINAL, ACC_SUPER
  this_class: #2                          // shapeless/Default$AsOptions$Helper$$anon$6
  super_class: #5                         // java/lang/Object
  interfaces: 1, fields: 0, methods: 3, attributes: 6
Constant pool:
   #1 = Utf8               shapeless/Default$AsOptions$Helper$$anon$6
   #2 = Class              #1             // shapeless/Default$AsOptions$Helper$$anon$6
   #3 = Utf8               Ljava/lang/Object;Lshapeless/Default$AsOptions$Helper<Lshapeless/HNil;Lshapeless/HNil;>;
   #4 = Utf8               java/lang/Object
   #5 = Class              #4             // java/lang/Object
   #6 = Utf8               shapeless/Default$AsOptions$Helper
   #7 = Class              #6             // shapeless/Default$AsOptions$Helper
   #8 = Utf8               default.scala
   #9 = Utf8               shapeless/Default$AsOptions$Helper$
  #10 = Class              #9             // shapeless/Default$AsOptions$Helper$
  #11 = Utf8               hnilHelper
  #12 = Utf8               ()Lshapeless/Default$AsOptions$Helper;
  #13 = NameAndType        #11:#12        // hnilHelper:()Lshapeless/Default$AsOptions$Helper;
  #14 = Utf8               shapeless/Default$AsOptions$
  #15 = Class              #14            // shapeless/Default$AsOptions$
  #16 = Utf8               shapeless/Default
  #17 = Class              #16            // shapeless/Default
  #18 = Utf8               AsOptions$
  #19 = Utf8               Helper
  #20 = Utf8               Helper$
  #21 = Utf8               apply
  #22 = Utf8               (Lshapeless/HNil;)Lshapeless/HNil$;
  #23 = Utf8               l
  #24 = Utf8               shapeless/HNil$
  #25 = Class              #24            // shapeless/HNil$
  #26 = Utf8               MODULE$
  #27 = Utf8               Lshapeless/HNil$;
  #28 = NameAndType        #26:#27        // MODULE$:Lshapeless/HNil$;
  #29 = Fieldref           #25.#28        // shapeless/HNil$.MODULE$:Lshapeless/HNil$;
  #30 = Utf8               this
  #31 = Utf8               Lshapeless/Default$AsOptions$Helper$$anon$6;
  #32 = Utf8               Lshapeless/HNil;
  #33 = Utf8               (Ljava/lang/Object;)Ljava/lang/Object;
  #34 = Utf8               t
  #35 = Utf8               shapeless/HNil
  #36 = Class              #35            // shapeless/HNil
  #37 = NameAndType        #21:#22        // apply:(Lshapeless/HNil;)Lshapeless/HNil$;
  #38 = Methodref          #2.#37         // shapeless/Default$AsOptions$Helper$$anon$6.apply:(Lshapeless/HNil;)Lshapeless/HNil$;
  #39 = Utf8               Ljava/lang/Object;
  #40 = Utf8               <init>
  #41 = Utf8               ()V
  #42 = NameAndType        #40:#41        // "<init>":()V
  #43 = Methodref          #5.#42         // java/lang/Object."<init>":()V
  #44 = Utf8               Code
  #45 = Utf8               LineNumberTable
  #46 = Utf8               LocalVariableTable
  #47 = Utf8               MethodParameters
  #48 = Utf8               InnerClasses
  #49 = Utf8               EnclosingMethod
  #50 = Utf8               Signature
  #51 = Utf8               SourceFile
  #52 = Utf8               ScalaInlineInfo
  #53 = Utf8               Scala
{
  public shapeless.HNil$ apply(shapeless.HNil);
    descriptor: (Lshapeless/HNil;)Lshapeless/HNil$;
    flags: (0x0001) ACC_PUBLIC
    Code:
      stack=1, locals=2, args_size=2
         0: getstatic     #29                 // Field shapeless/HNil$.MODULE$:Lshapeless/HNil$;
         3: areturn
      LineNumberTable:
        line 176: 0
      LocalVariableTable:
        Start  Length  Slot  Name   Signature
            0       4     0  this   Lshapeless/Default$AsOptions$Helper$$anon$6;
            0       4     1     l   Lshapeless/HNil;
    MethodParameters:
      Name                           Flags
      l                              final

  public java.lang.Object apply(java.lang.Object);
    descriptor: (Ljava/lang/Object;)Ljava/lang/Object;
    flags: (0x1041) ACC_PUBLIC, ACC_BRIDGE, ACC_SYNTHETIC
    Code:
      stack=2, locals=2, args_size=2
         0: aload_0
         1: aload_1
         2: checkcast     #36                 // class shapeless/HNil
         5: invokevirtual #38                 // Method apply:(Lshapeless/HNil;)Lshapeless/HNil$;
         8: areturn
      LineNumberTable:
        line 174: 0
      LocalVariableTable:
        Start  Length  Slot  Name   Signature
            0       9     0  this   Lshapeless/Default$AsOptions$Helper$$anon$6;
            0       9     1     t   Ljava/lang/Object;
    MethodParameters:
      Name                           Flags
      t                              final

  public shapeless.Default$AsOptions$Helper$$anon$6();
    descriptor: ()V
    flags: (0x0001) ACC_PUBLIC
    Code:
      stack=1, locals=1, args_size=1
         0: aload_0
         1: invokespecial #43                 // Method java/lang/Object."<init>":()V
         4: return
      LineNumberTable:
        line 174: 0
      LocalVariableTable:
        Start  Length  Slot  Name   Signature
            0       5     0  this   Lshapeless/Default$AsOptions$Helper$$anon$6;
}
InnerClasses:
  public static #18= #15 of #17;          // AsOptions$=class shapeless/Default$AsOptions$ of class shapeless/Default
  public static #19= #7 of #15;           // Helper=class shapeless/Default$AsOptions$Helper of class shapeless/Default$AsOptions$
  public static #20= #10 of #15;          // Helper$=class shapeless/Default$AsOptions$Helper$ of class shapeless/Default$AsOptions$
  public final #2;                        // class shapeless/Default$AsOptions$Helper$$anon$6
EnclosingMethod: #10.#13                // shapeless.Default$AsOptions$Helper$.hnilHelper
Signature: #3                           // Ljava/lang/Object;Lshapeless/Default$AsOptions$Helper<Lshapeless/HNil;Lshapeless/HNil;>;
SourceFile: "default.scala"
  ScalaInlineInfo: length = 0x13 (unknown attribute)
   01 01 00 03 00 28 00 29 01 00 15 00 21 01 00 15
   00 16 01
  Scala: length = 0x0 (unknown attribute)

