Classfile /Users/mw/Projects/slang-braindump/.jar/jar8/assemble/slang-braindump/assemble/content/shapeless/FinSucc$.class
  Last modified May 29, 2022; size 1245 bytes
  SHA-256 checksum 0e9b29a29fff57405e5b44571b456398b5cdb96c6dbe3a8ba9e09499d63470a3
  Compiled from "fin.scala"
public final class shapeless.FinSucc$ implements java.io.Serializable
  minor version: 0
  major version: 52
  flags: (0x0031) ACC_PUBLIC, ACC_FINAL, ACC_SUPER
  this_class: #2                          // shapeless/FinSucc$
  super_class: #4                         // java/lang/Object
  interfaces: 1, fields: 1, methods: 6, attributes: 3
Constant pool:
   #1 = Utf8               shapeless/FinSucc$
   #2 = Class              #1             // shapeless/FinSucc$
   #3 = Utf8               java/lang/Object
   #4 = Class              #3             // java/lang/Object
   #5 = Utf8               java/io/Serializable
   #6 = Class              #5             // java/io/Serializable
   #7 = Utf8               fin.scala
   #8 = Utf8               MODULE$
   #9 = Utf8               Lshapeless/FinSucc$;
  #10 = Utf8               <clinit>
  #11 = Utf8               ()V
  #12 = Utf8               <init>
  #13 = NameAndType        #12:#11        // "<init>":()V
  #14 = Methodref          #2.#13         // shapeless/FinSucc$."<init>":()V
  #15 = NameAndType        #8:#9          // MODULE$:Lshapeless/FinSucc$;
  #16 = Fieldref           #2.#15         // shapeless/FinSucc$.MODULE$:Lshapeless/FinSucc$;
  #17 = Utf8               toString
  #18 = Utf8               ()Ljava/lang/String;
  #19 = Utf8               FinSucc
  #20 = String             #19            // FinSucc
  #21 = Utf8               this
  #22 = Utf8               apply
  #23 = Utf8               ()Lshapeless/FinSucc;
  #24 = Utf8               <N:Lshapeless/Succ<*>;P::Lshapeless/Fin<TN;>;>()Lshapeless/FinSucc<TN;TP;>;
  #25 = Utf8               shapeless/FinSucc
  #26 = Class              #25            // shapeless/FinSucc
  #27 = Methodref          #26.#13        // shapeless/FinSucc."<init>":()V
  #28 = Utf8               unapply
  #29 = Utf8               (Lshapeless/FinSucc;)Z
  #30 = Utf8               <N:Lshapeless/Succ<*>;P::Lshapeless/Fin<TN;>;>(Lshapeless/FinSucc<TN;TP;>;)Z
  #31 = Utf8               x$0
  #32 = Utf8               Lshapeless/FinSucc;
  #33 = Utf8               writeReplace
  #34 = Utf8               ()Ljava/lang/Object;
  #35 = Utf8               scala/runtime/ModuleSerializationProxy
  #36 = Class              #35            // scala/runtime/ModuleSerializationProxy
  #37 = Utf8               (Ljava/lang/Class;)V
  #38 = NameAndType        #12:#37        // "<init>":(Ljava/lang/Class;)V
  #39 = Methodref          #36.#38        // scala/runtime/ModuleSerializationProxy."<init>":(Ljava/lang/Class;)V
  #40 = Methodref          #4.#13         // java/lang/Object."<init>":()V
  #41 = Utf8               Code
  #42 = Utf8               LineNumberTable
  #43 = Utf8               LocalVariableTable
  #44 = Utf8               Signature
  #45 = Utf8               StackMapTable
  #46 = Utf8               MethodParameters
  #47 = Utf8               SourceFile
  #48 = Utf8               ScalaInlineInfo
  #49 = Utf8               Scala
{
  public static final shapeless.FinSucc$ MODULE$;
    descriptor: Lshapeless/FinSucc$;
    flags: (0x0019) ACC_PUBLIC, ACC_STATIC, ACC_FINAL

  public static {};
    descriptor: ()V
    flags: (0x0009) ACC_PUBLIC, ACC_STATIC
    Code:
      stack=2, locals=0, args_size=0
         0: new           #2                  // class shapeless/FinSucc$
         3: dup
         4: invokespecial #14                 // Method "<init>":()V
         7: putstatic     #16                 // Field MODULE$:Lshapeless/FinSucc$;
        10: return
      LineNumberTable:
        line 33: 0

  public final java.lang.String toString();
    descriptor: ()Ljava/lang/String;
    flags: (0x0011) ACC_PUBLIC, ACC_FINAL
    Code:
      stack=1, locals=1, args_size=1
         0: ldc           #20                 // String FinSucc
         2: areturn
      LineNumberTable:
        line 33: 0
      LocalVariableTable:
        Start  Length  Slot  Name   Signature
            0       3     0  this   Lshapeless/FinSucc$;

  public <N extends shapeless.Succ<?>, P extends shapeless.Fin<N>> shapeless.FinSucc<N, P> apply();
    descriptor: ()Lshapeless/FinSucc;
    flags: (0x0001) ACC_PUBLIC
    Code:
      stack=2, locals=1, args_size=1
         0: new           #26                 // class shapeless/FinSucc
         3: dup
         4: invokespecial #27                 // Method shapeless/FinSucc."<init>":()V
         7: areturn
      LineNumberTable:
        line 33: 0
      LocalVariableTable:
        Start  Length  Slot  Name   Signature
            0       8     0  this   Lshapeless/FinSucc$;
    Signature: #24                          // <N:Lshapeless/Succ<*>;P::Lshapeless/Fin<TN;>;>()Lshapeless/FinSucc<TN;TP;>;

  public <N extends shapeless.Succ<?>, P extends shapeless.Fin<N>> boolean unapply(shapeless.FinSucc<N, P>);
    descriptor: (Lshapeless/FinSucc;)Z
    flags: (0x0001) ACC_PUBLIC
    Code:
      stack=1, locals=2, args_size=2
         0: aload_1
         1: ifnonnull     8
         4: iconst_0
         5: goto          9
         8: iconst_1
         9: ireturn
      StackMapTable: number_of_entries = 2
        frame_type = 8 /* same */
        frame_type = 64 /* same_locals_1_stack_item */
          stack = [ int ]
      LineNumberTable:
        line 33: 0
      LocalVariableTable:
        Start  Length  Slot  Name   Signature
            0      10     0  this   Lshapeless/FinSucc$;
            0      10     1   x$0   Lshapeless/FinSucc;
    Signature: #30                          // <N:Lshapeless/Succ<*>;P::Lshapeless/Fin<TN;>;>(Lshapeless/FinSucc<TN;TP;>;)Z
    MethodParameters:
      Name                           Flags
      x$0                            final

  private java.lang.Object writeReplace();
    descriptor: ()Ljava/lang/Object;
    flags: (0x0002) ACC_PRIVATE
    Code:
      stack=3, locals=1, args_size=1
         0: new           #36                 // class scala/runtime/ModuleSerializationProxy
         3: dup
         4: ldc           #2                  // class shapeless/FinSucc$
         6: invokespecial #39                 // Method scala/runtime/ModuleSerializationProxy."<init>":(Ljava/lang/Class;)V
         9: areturn
      LineNumberTable:
        line 33: 0
      LocalVariableTable:
        Start  Length  Slot  Name   Signature
            0      10     0  this   Lshapeless/FinSucc$;

  private shapeless.FinSucc$();
    descriptor: ()V
    flags: (0x0002) ACC_PRIVATE
    Code:
      stack=1, locals=1, args_size=1
         0: aload_0
         1: invokespecial #40                 // Method java/lang/Object."<init>":()V
         4: return
      LineNumberTable:
        line 33: 0
      LocalVariableTable:
        Start  Length  Slot  Name   Signature
            0       5     0  this   Lshapeless/FinSucc$;
}
SourceFile: "fin.scala"
  ScalaInlineInfo: length = 0x1D (unknown attribute)
   01 01 00 05 00 0C 00 0B 01 00 16 00 17 01 00 11
   00 12 01 00 1C 00 1D 01 00 21 00 22 01
  Scala: length = 0x0 (unknown attribute)

