Classfile /Users/mw/Projects/slang-braindump/.jar/jar8/assemble/slang-braindump/assemble/content/shapeless/HList$FillWithOps.class
  Last modified May 29, 2022; size 923 bytes
  SHA-256 checksum 68faa8be5deb1426bae2d00683c6d0b2fd2828fd063b0512bed2c71040532727
  Compiled from "hlists.scala"
public final class shapeless.HList$FillWithOps<L extends shapeless.HList> extends java.lang.Object
  minor version: 0
  major version: 52
  flags: (0x0031) ACC_PUBLIC, ACC_FINAL, ACC_SUPER
  this_class: #2                          // shapeless/HList$FillWithOps
  super_class: #5                         // java/lang/Object
  interfaces: 0, fields: 0, methods: 2, attributes: 5
Constant pool:
   #1 = Utf8               shapeless/HList$FillWithOps
   #2 = Class              #1             // shapeless/HList$FillWithOps
   #3 = Utf8               <L::Lshapeless/HList;>Ljava/lang/Object;
   #4 = Utf8               java/lang/Object
   #5 = Class              #4             // java/lang/Object
   #6 = Utf8               hlists.scala
   #7 = Utf8               shapeless/HList
   #8 = Class              #7             // shapeless/HList
   #9 = Utf8               FillWithOps
  #10 = Utf8               shapeless/ops/hlist$FillWith
  #11 = Class              #10            // shapeless/ops/hlist$FillWith
  #12 = Utf8               shapeless/ops/hlist
  #13 = Class              #12            // shapeless/ops/hlist
  #14 = Utf8               FillWith
  #15 = Utf8               apply
  #16 = Utf8               (Lshapeless/Poly;Lshapeless/ops/hlist$FillWith;)Lshapeless/HList;
  #17 = Utf8               <F::Lshapeless/Poly;>(TF;Lshapeless/ops/hlist$FillWith<TF;TL;>;)TL;
  #18 = Utf8               f
  #19 = Utf8               fillWith
  #20 = Utf8               ()Ljava/lang/Object;
  #21 = NameAndType        #15:#20        // apply:()Ljava/lang/Object;
  #22 = InterfaceMethodref #11.#21        // shapeless/ops/hlist$FillWith.apply:()Ljava/lang/Object;
  #23 = Utf8               this
  #24 = Utf8               Lshapeless/HList$FillWithOps;
  #25 = Utf8               Lshapeless/Poly;
  #26 = Utf8               Lshapeless/ops/hlist$FillWith;
  #27 = Utf8               <init>
  #28 = Utf8               ()V
  #29 = NameAndType        #27:#28        // "<init>":()V
  #30 = Methodref          #5.#29         // java/lang/Object."<init>":()V
  #31 = Utf8               Code
  #32 = Utf8               LineNumberTable
  #33 = Utf8               LocalVariableTable
  #34 = Utf8               Signature
  #35 = Utf8               MethodParameters
  #36 = Utf8               InnerClasses
  #37 = Utf8               SourceFile
  #38 = Utf8               ScalaInlineInfo
  #39 = Utf8               Scala
{
  public <F extends shapeless.Poly> L apply(F, shapeless.ops.hlist$FillWith<F, L>);
    descriptor: (Lshapeless/Poly;Lshapeless/ops/hlist$FillWith;)Lshapeless/HList;
    flags: (0x0001) ACC_PUBLIC
    Code:
      stack=1, locals=3, args_size=3
         0: aload_2
         1: invokeinterface #22,  1           // InterfaceMethod shapeless/ops/hlist$FillWith.apply:()Ljava/lang/Object;
         6: checkcast     #8                  // class shapeless/HList
         9: areturn
      LineNumberTable:
        line 82: 0
      LocalVariableTable:
        Start  Length  Slot  Name   Signature
            0      10     0  this   Lshapeless/HList$FillWithOps;
            0      10     1     f   Lshapeless/Poly;
            0      10     2 fillWith   Lshapeless/ops/hlist$FillWith;
    Signature: #17                          // <F::Lshapeless/Poly;>(TF;Lshapeless/ops/hlist$FillWith<TF;TL;>;)TL;
    MethodParameters:
      Name                           Flags
      f                              final
      fillWith                       final

  public shapeless.HList$FillWithOps();
    descriptor: ()V
    flags: (0x0001) ACC_PUBLIC
    Code:
      stack=1, locals=1, args_size=1
         0: aload_0
         1: invokespecial #30                 // Method java/lang/Object."<init>":()V
         4: return
      LineNumberTable:
        line 90: 0
        line 81: 4
      LocalVariableTable:
        Start  Length  Slot  Name   Signature
            0       5     0  this   Lshapeless/HList$FillWithOps;
}
InnerClasses:
  public static final #9= #2 of #8;       // FillWithOps=class shapeless/HList$FillWithOps of class shapeless/HList
  public static #14= #11 of #13;          // FillWith=class shapeless/ops/hlist$FillWith of class shapeless/ops/hlist
Signature: #3                           // <L::Lshapeless/HList;>Ljava/lang/Object;
SourceFile: "hlists.scala"
  ScalaInlineInfo: length = 0xE (unknown attribute)
   01 01 00 02 00 1B 00 1C 01 00 0F 00 10 01
  Scala: length = 0x0 (unknown attribute)

